{
  "type": "Feature",
  "properties": {
    "iso:country":"ES",
    "sg:address":"Carrer de Gregal, 19",
    "sg:city":"Pinatella",
    "sg:orig_category":"Maquinaria Para Industrias Diversas",
    "sg:phone":"+34 936 83 03 27",
    "sg:postcode":"08759",
    "sg:province":"Barcelona",
    "wof:name":"Juan Carlos Obras Y Servicios S.l.",
    "wof:placetype":"venue"
},
  "geometry": {"coordinates":[1.8986229897,41.3762321472],"type":"Point"}
}