{
  "type": "Feature",
  "properties": {
    "iso:country":"ES",
    "sg:address":"Avda Ricardo Carapeto Zambrano, 83",
    "sg:city":"Badajoz",
    "sg:orig_category":"Venta, Montaje De Neum\u00c1ticos",
    "sg:phone":"+34 924 25 04 29",
    "sg:postcode":"06008",
    "sg:province":"Badajoz",
    "sg:website":"www.neumaticosbadajoz.50megs.com",
    "wof:name":"Neumaticos Badajoz S.l.",
    "wof:placetype":"venue"
},
  "geometry": {"coordinates":[-6.9513192177,38.8783493042],"type":"Point"}
}