{
  "type": "Feature",
  "properties": {
    "iso:country":"ES",
    "sg:address":"Calle de Luis Doreste Silva, 60",
    "sg:city":"Palmas De Gran Canaria",
    "sg:orig_category":"Sindicatos De Trabajadores",
    "sg:phone":"+34 928 24 48 87",
    "sg:postcode":"35004",
    "sg:province":"Las Palmas",
    "wof:name":"Sindicato Profesional De Medicos De Las Palmas",
    "wof:placetype":"venue"
},
  "geometry": {"coordinates":[-15.4245634079,28.1200466156],"type":"Point"}
}