{
  "type": "Feature",
  "properties": {
    "addr:full":"Calle de Mesa Del Mar, S/n Mesa Del Mar Santa Cruz De Tenerife 38350",
    "addr:postcode":"38350",
    "addr:street":"Calle De Mesa Del Mar S / N Mesa Del",
    "iso:country":"ES",
    "sg:address":"Calle de Mesa Del Mar, S/n",
    "sg:city":"Mesa Del Mar",
    "sg:orig_category":"Alumbrados",
    "sg:phone":"+34 922 56 07 61",
    "sg:postcode":"38350",
    "sg:province":"Santa Cruz De Tenerife",
    "wof:name":"High Voltage S.l.",
    "wof:placetype":"venue"
},
  "geometry": {"coordinates":[-16.4174289703,28.4756546021],"type":"Point"}
}