{
  "type": "Feature",
  "properties": {
    "addr:full":"Trav De Gracia, 166 Barcelona Barcelona 08012",
    "addr:housenumber":"166",
    "addr:postcode":"08012",
    "addr:street":"Trav De Gracia",
    "iso:country":"ES",
    "sg:address":"Trav De Gracia, 166",
    "sg:city":"Barcelona",
    "sg:orig_category":"Empresarios",
    "sg:phone":"+34 932 18 79 48",
    "sg:postcode":"08012",
    "sg:province":"Barcelona",
    "wof:name":"Vives Subira Antonio",
    "wof:placetype":"venue"
},
  "geometry": {"coordinates":[2.1526939869,41.4024467468],"type":"Point"}
}