{
  "type": "Feature",
  "properties": {
    "addr:full":"Ctra Corcoya-badolatosa, S/n Corcoya Sevilla 41599",
    "addr:housenumber":"s",
    "addr:postcode":"41599",
    "addr:street":"Ctra Corcoya-Badolatosa;/ N Corcoya",
    "iso:country":"ES",
    "sg:address":"Ctra Corcoya-badolatosa, S/n",
    "sg:city":"Corcoya",
    "sg:orig_category":"Cooperativas Agr\u00cdcolas",
    "sg:phone":"+34 954 01 10 57",
    "sg:postcode":"41599",
    "sg:province":"Sevilla",
    "wof:name":"Cooperativa Olivarera Nuestra Se\u00f1ora De La Fuensanta",
    "wof:placetype":"venue"
},
  "geometry": {"coordinates":[-4.6900839806,37.2707939148],"type":"Point"}
}