{
  "type": "Feature",
  "properties": {
    "iso:country":"ES",
    "sg:address":"Avda Luis Rodriguez De Miguel, 4",
    "sg:city":"Toro",
    "sg:orig_category":"Fabricaci\u00d3n De Quesos",
    "sg:phone":"+34 980 69 02 89",
    "sg:postcode":"49800",
    "sg:province":"Zamora",
    "wof:name":"Queserias Castro S.l.",
    "wof:placetype":"venue"
},
  "geometry": {"coordinates":[-5.3891701698,41.52551651],"type":"Point"}
}