{
  "type": "Feature",
  "properties": {
    "iso:country":"ES",
    "sg:address":"Calle de Cendeja, 6",
    "sg:city":"San Juan De Muskiz",
    "sg:orig_category":"Pescader\u00cdas (al Por Menor)",
    "sg:phone":"+34 946 70 83 29",
    "sg:postcode":"48550",
    "sg:province":"Vizcaya",
    "wof:name":"Ere\u00f1o Pagola Maria Angeles",
    "wof:placetype":"venue"
},
  "geometry": {"coordinates":[-3.121576786,43.321975708],"type":"Point"}
}