{
  "type": "Feature",
  "properties": {
    "addr:full":"Calle de Navas, 5 Granada Granada 18009",
    "addr:housenumber":"5",
    "addr:postcode":"18009",
    "addr:street":"Calle De Navas",
    "iso:country":"ES",
    "sg:address":"Calle de Navas, 5",
    "sg:city":"Granada",
    "sg:orig_category":"Caf\u00c9s, Bares, Cervecer\u00cdas",
    "sg:phone":"+34 958 22 69 26",
    "sg:postcode":"18009",
    "sg:province":"Granada",
    "wof:name":"Cases Ferrero Naria Soledad",
    "wof:placetype":"venue"
},
  "geometry": {"coordinates":[-3.5973069668,37.1730804443],"type":"Point"}
}