{
  "type": "Feature",
  "properties": {
    "iso:country":"ES",
    "sg:address":"Pase Delicias, 65",
    "sg:city":"Madrid",
    "sg:orig_category":"Comercio, Reparaci\u00d3n De Bicicletas, De Motocicletas, De Accesorios",
    "sg:phone":"+34 915 30 77 87",
    "sg:postcode":"28045",
    "sg:province":"Madrid",
    "wof:name":"Ciclos Delicias S.l.",
    "wof:placetype":"venue"
},
  "geometry": {"coordinates":[-3.6940031052,40.3987884521],"type":"Point"}
}