{
  "type": "Feature",
  "properties": {
    "iso:country":"ES",
    "sg:address":"Calle de Ametzaga\u00d1a, 35",
    "sg:city":"Donostia-san Sebastian",
    "sg:orig_category":"Veh\u00cdculos De Ocasi\u00d3n",
    "sg:phone":"+34 943 28 36 99",
    "sg:postcode":"20012",
    "sg:province":"Guip\u00f9zcoa",
    "wof:name":"Zubeldia Leiba I\u00f1aki",
    "wof:placetype":"venue"
},
  "geometry": {"coordinates":[-1.9691524506,43.3170776367],"type":"Point"}
}