{
  "type": "Feature",
  "properties": {
    "addr:full":"Calle de Venecia, 39 Zaragoza Zaragoza 50007",
    "addr:housenumber":"39",
    "addr:postcode":"50007",
    "addr:street":"Calle De Venecia",
    "iso:country":"ES",
    "sg:address":"Calle de Venecia, 39",
    "sg:city":"Zaragoza",
    "sg:orig_category":"Electricidad, Electr\u00d3nica: Material Y Suministros (al Por Mayor)",
    "sg:phone":"+34 976 27 90 47",
    "sg:postcode":"50007",
    "sg:province":"Zaragoza",
    "wof:name":"Sonido Electronica Y Comunicaciones S.a.",
    "wof:placetype":"venue"
},
  "geometry": {"coordinates":[-0.8878164291,41.6328048706],"type":"Point"}
}