{
  "type": "Feature",
  "properties": {
    "iso:country":"ES",
    "sg:address":"Calle de Arroyazo, 19",
    "sg:city":"Don Benito",
    "sg:orig_category":"Supermercados Y Hipermercados",
    "sg:phone":"+34 924 81 20 66",
    "sg:postcode":"06400",
    "sg:province":"Badajoz",
    "wof:name":"Rola S.l.",
    "wof:placetype":"venue"
},
  "geometry": {"coordinates":[-5.8641791344,38.9549102783],"type":"Point"}
}