{
  "type": "Feature",
  "properties": {
    "addr:full":"Calle de Francisco Borobia Lopez, 4 Guadalajara Guadalajara 19004",
    "addr:housenumber":"4",
    "addr:postcode":"19004",
    "addr:street":"Calle De Francisco Borobia Lopez",
    "iso:country":"ES",
    "sg:address":"Calle de Francisco Borobia Lopez, 4",
    "sg:city":"Guadalajara",
    "sg:orig_category":"Inmobiliaria (agencias)",
    "sg:phone":"+34 949 21 21 79",
    "sg:postcode":"19004",
    "sg:province":"Guadalajara",
    "wof:name":"Jersos Servicios Generales S.l.",
    "wof:placetype":"venue"
},
  "geometry": {"coordinates":[-3.1859731674,40.6388206482],"type":"Point"}
}