{
  "type": "Feature",
  "properties": {
    "iso:country":"ES",
    "sg:address":"Avda Galicia, 1",
    "sg:city":"Vegadeo",
    "sg:orig_category":"Transportes En Cisternas",
    "sg:phone":"+34 985 63 45 94",
    "sg:postcode":"33770",
    "sg:province":"Asturias",
    "wof:name":"Rodriguez Jardon Jose Manuel",
    "wof:placetype":"venue"
},
  "geometry": {"coordinates":[-7.0532112122,43.4648132324],"type":"Point"}
}