{
  "type": "Feature",
  "properties": {
    "iso:country":"ES",
    "sg:address":"Pl Rellotge, 4",
    "sg:city":"Santa Coloma De Gramenet",
    "sg:orig_category":"Ropa Para Se\u00d1oras (al Por Menor)",
    "sg:phone":"+34 933 92 10 06",
    "sg:postcode":"08922",
    "sg:province":"Barcelona",
    "wof:name":"Palomar Vinuesa Jose Manuel",
    "wof:placetype":"venue"
},
  "geometry": {"coordinates":[2.2189381123,41.4498825073],"type":"Point"}
}