{
  "type": "Feature",
  "properties": {
    "addr:full":"Carr Santanyi, De, 48 Campos Islas Baleares 07630",
    "addr:housenumber":"48",
    "addr:postcode":"07630",
    "addr:street":"Carr Santanyi De",
    "iso:country":"ES",
    "sg:address":"Carr Santanyi, De, 48",
    "sg:city":"Campos",
    "sg:orig_category":"M\u00c9dicos: Estomatolog\u00cda",
    "sg:phone":"+34 971 65 15 15",
    "sg:postcode":"07630",
    "sg:province":"Islas Baleares",
    "wof:name":"Aguilo Marti Pedro",
    "wof:placetype":"venue"
},
  "geometry": {"coordinates":[3.0276710987,39.4245071411],"type":"Point"}
}