{
  "type": "Feature",
  "properties": {
    "iso:country":"ES",
    "sg:address":"Carrer de Ample, 23",
    "sg:city":"Barcelona",
    "sg:orig_category":"Grafistas",
    "sg:phone":"+34 934 12 60 32",
    "sg:postcode":"08002",
    "sg:province":"Barcelona",
    "sg:website":"www.phineas.com",
    "wof:name":"Phineas Taylor Barnum S.l.",
    "wof:placetype":"venue"
},
  "geometry": {"coordinates":[2.1794478893,41.379863739],"type":"Point"}
}