{
  "type": "Feature",
  "properties": {
    "iso:country":"ES",
    "sg:address":"Calle de Antonio Machado, 5",
    "sg:city":"Albacete",
    "sg:classifiers":[
        {
            "category":"Personal",
            "subcategory":"Barber",
            "type":"Services"
        }
    ],
    "sg:phone":"+34 967 22 20 34",
    "sg:postcode":"02003",
    "sg:province":"Albacete",
    "sg:tags":[
        "caballeros",
        "de",
        "peluqueros"
    ],
    "wof:name":"Nu\u00f1ez Garcia Julian",
    "wof:placetype":"venue"
},
  "geometry": {"coordinates":[-1.8586757183,38.9886360168],"type":"Point"}
}