{
  "type": "Feature",
  "properties": {
    "addr:full":"Carrer de Antoni Roig (d'), 47 Torredembarra Tarragona 43830",
    "addr:housenumber":"47",
    "addr:postcode":"43830",
    "addr:street":"Carrer De Antoni Roig D '",
    "iso:country":"ES",
    "sg:address":"Carrer de Antoni Roig (d'), 47",
    "sg:city":"Torredembarra",
    "sg:orig_category":"Forjas Y Altos Hornos",
    "sg:phone":"+34 977 64 01 87",
    "sg:postcode":"43830",
    "sg:province":"Tarragona",
    "wof:name":"Garcia Arribas Gervasio",
    "wof:placetype":"venue"
},
  "geometry": {"coordinates":[1.3990290165,41.1441879272],"type":"Point"}
}