{
  "type": "Feature",
  "properties": {
    "addr:full":"Calle de Convento, 3 Castalla Alicante 03420",
    "addr:housenumber":"3",
    "addr:postcode":"03420",
    "addr:street":"Calle De Convento",
    "iso:country":"ES",
    "sg:address":"Calle de Convento, 3",
    "sg:city":"Castalla",
    "sg:orig_category":"Artes Gr\u00c1ficas, Artes Pl\u00c1sticas (curso)",
    "sg:phone":"+34 965 56 07 78",
    "sg:postcode":"03420",
    "sg:province":"Alicante",
    "wof:name":"Ideas Graficas San Antonio S.l",
    "wof:placetype":"venue"
},
  "geometry": {"coordinates":[-0.6725649834,38.5932312012],"type":"Point"}
}