{
  "type": "Feature",
  "properties": {
    "addr:full":"Carrer de Santissima Trinitat, 69 Crevillent Alicante 03330",
    "addr:housenumber":"69",
    "addr:postcode":"03330",
    "addr:street":"Carrer De Santissima Trinitat",
    "iso:country":"ES",
    "sg:address":"Carrer de Santissima Trinitat, 69",
    "sg:city":"Crevillent",
    "sg:orig_category":"Art\u00cdculos Funerarios (al Por Menor)",
    "sg:phone":"+34 965 40 06 92",
    "sg:postcode":"03330",
    "sg:province":"Alicante",
    "wof:name":"Unisanbel S.l.",
    "wof:placetype":"venue"
},
  "geometry": {"coordinates":[-0.8118029833,38.2457351685],"type":"Point"}
}