{
  "type": "Feature",
  "properties": {
    "addr:full":"Avda Santander, 3 Noja Cantabria 39180",
    "addr:housenumber":"3",
    "addr:postcode":"39180",
    "addr:street":"Avda Santander",
    "iso:country":"ES",
    "sg:address":"Avda Santander, 3",
    "sg:city":"Noja",
    "sg:orig_category":"Cester\u00cda (fabricaci\u00d3n)",
    "sg:phone":"+34 942 67 50 42",
    "sg:postcode":"39180",
    "sg:province":"Cantabria",
    "wof:name":"Ideas Sociedad Civil",
    "wof:placetype":"venue"
},
  "geometry": {"coordinates":[-3.5297250748,43.4793777466],"type":"Point"}
}