{
  "type": "Feature",
  "properties": {
    "addr:full":"Cra Santa Creu De Calafell, 52 Gava Barcelona 08850",
    "addr:housenumber":"52",
    "addr:postcode":"08850",
    "addr:street":"Gava Barcelona",
    "iso:country":"ES",
    "sg:address":"Cra Santa Creu De Calafell, 52",
    "sg:city":"Gava",
    "sg:orig_category":"Reposter\u00cdas",
    "sg:phone":"+34 936 62 22 88",
    "sg:postcode":"08850",
    "sg:province":"Barcelona",
    "wof:name":"Gavalda Zurriaga Francisco Javier",
    "wof:placetype":"venue"
},
  "geometry": {"coordinates":[2.0081100464,41.3033065796],"type":"Point"}
}