{
  "type": "Feature",
  "properties": {
    "iso:country":"ES",
    "sg:address":"Rua Nova De Caranza, 98",
    "sg:city":"Ferrol",
    "sg:orig_category":"Sociedades, Compa\u00d1\u00cdas Aseguradoras",
    "sg:phone":"+34 981 37 01 61",
    "sg:postcode":"15404",
    "sg:province":"La Coru\u00f1a",
    "wof:name":"Liberty Seguros Compa\u00d1ia De Seguros Y Reaseguros S.a.",
    "wof:placetype":"venue"
},
  "geometry": {"coordinates":[-8.2175579071,43.4883499146],"type":"Point"}
}