{
  "type": "Feature",
  "properties": {
    "iso:country":"ES",
    "sg:address":"Carrer de Tenor Masini, 5",
    "sg:city":"Barcelona",
    "sg:orig_category":"M\u00c1quinas De Coser Y De Hacer Punto (al Por Mayor)",
    "sg:phone":"+34 934 90 39 72",
    "sg:postcode":"08028",
    "sg:province":"Barcelona",
    "wof:name":"Rubio Nicolas Concepcion",
    "wof:placetype":"venue"
},
  "geometry": {"coordinates":[2.1323599815,41.375617981],"type":"Point"}
}