{
  "type": "Feature",
  "properties": {
    "addr:full":"Calle de Angel Del Alcazar, 20 Talavera Reina Toledo 45600",
    "addr:housenumber":"20",
    "addr:postcode":"45600",
    "addr:street":"Calle De Angel Del Alcazar",
    "iso:country":"ES",
    "sg:address":"Calle de Angel Del Alcazar, 20",
    "sg:city":"Talavera Reina",
    "sg:orig_category":"Papeler\u00cdas, Librer\u00cdas",
    "sg:phone":"+34 925 81 81 50",
    "sg:postcode":"45600",
    "sg:province":"Toledo",
    "wof:name":"Copias Paris S.l.",
    "wof:placetype":"venue"
},
  "geometry": {"coordinates":[-4.8232374191,39.9633483887],"type":"Point"}
}