{
  "type": "Feature",
  "properties": {
    "iso:country":"ES",
    "sg:address":"Carrer de Sant Francesc, S/n",
    "sg:city":"Berga-ciudad",
    "sg:orig_category":"Ense\u00d1anza, Formaci\u00d3n Profesional: Aprendizaje",
    "sg:phone":"+34 938 21 16 00",
    "sg:postcode":"08600",
    "sg:province":"Barcelona",
    "wof:name":"Escuela Tecnico Profesional Sant Francesc",
    "wof:placetype":"venue"
},
  "geometry": {"coordinates":[1.8446400166,42.1039352417],"type":"Point"}
}