{
  "type": "Feature",
  "properties": {
    "addr:full":"Carrer de Mossen Jacint Verdaguer, 33 Cornella Llobregat Barcelona 08940",
    "addr:housenumber":"33",
    "addr:postcode":"08940",
    "addr:street":"Carrer De Mossen Jacint Verdaguer",
    "iso:country":"ES",
    "sg:address":"Carrer de Mossen Jacint Verdaguer, 33",
    "sg:city":"Cornella Llobregat",
    "sg:orig_category":"Molduras, Junquillos, Listones Y Molduras Perforadas",
    "sg:phone":"+34 933 77 25 66",
    "sg:postcode":"08940",
    "sg:province":"Barcelona",
    "wof:name":"Trafi Guillaume Joaquin",
    "wof:placetype":"venue"
},
  "geometry": {"coordinates":[2.0714960098,41.3538284302],"type":"Point"}
}