{
  "type": "Feature",
  "properties": {
    "addr:full":"Rua Carlos Iii, 42 Becerrea Lugo 27640",
    "addr:housenumber":"42",
    "addr:postcode":"27640",
    "addr:street":"Rua Carlos Iii",
    "iso:country":"ES",
    "sg:address":"Rua Carlos Iii, 42",
    "sg:city":"Becerrea",
    "sg:orig_category":"Bancos",
    "sg:phone":"+34 982 36 04 12",
    "sg:postcode":"27640",
    "sg:province":"Lugo",
    "wof:name":"Banco De Galicia",
    "wof:placetype":"venue"
},
  "geometry": {"coordinates":[-7.1613059044,42.8526229858],"type":"Point"}
}