{
  "type": "Feature",
  "properties": {
    "iso:country":"ES",
    "sg:address":"Calle de Berna, 2",
    "sg:city":"Pozuelo De Alarcon",
    "sg:orig_category":"Asesor\u00cda Sobre Comunicaci\u00d3n De Empresas",
    "sg:phone":"+34 917 13 05 90",
    "sg:postcode":"28224",
    "sg:province":"Madrid",
    "wof:name":"Visual 3d Publicidad S.l.",
    "wof:placetype":"venue"
},
  "geometry": {"coordinates":[-3.7901279926,40.4436225891],"type":"Point"}
}