{
  "type": "Feature",
  "properties": {
    "addr:full":"Calle de Juan Ramon Jimenez (de), 4 Mostoles Madrid 28932",
    "addr:postcode":"28932",
    "addr:street":"Calle De Juan Ramon Jimenez De 4 Mostoles",
    "iso:country":"ES",
    "sg:address":"Calle de Juan Ramon Jimenez (de), 4",
    "sg:city":"Mostoles",
    "sg:orig_category":"Explotaci\u00d3n De Aparcamientos",
    "sg:phone":"+34 902 36 47 35",
    "sg:postcode":"28932",
    "sg:province":"Madrid",
    "wof:name":"Servialeyfa De Control Y Servicios S.l.",
    "wof:placetype":"venue"
},
  "geometry": {"coordinates":[-3.8586421013,40.3310890198],"type":"Point"}
}