{
  "type": "Feature",
  "properties": {
    "addr:full":"Av Alameda (l'), 74 Alcoi Alicante 03803",
    "addr:housenumber":"74",
    "addr:postcode":"03803",
    "addr:street":"Av Alameda L '",
    "iso:country":"ES",
    "sg:address":"Av Alameda (l'), 74",
    "sg:city":"Alcoi",
    "sg:orig_category":"Bisuter\u00cda, Joyer\u00cda, Relojer\u00cda (al Por Menor)",
    "sg:phone":"+34 966 52 18 33",
    "sg:postcode":"03803",
    "sg:province":"Alicante",
    "wof:name":"Aura Hernandez Andrea",
    "wof:placetype":"venue"
},
  "geometry": {"coordinates":[-0.4758729935,38.7030448914],"type":"Point"}
}