{
  "type": "Feature",
  "properties": {
    "addr:full":"Rua Pintor Seijo Rubio, 1 Betanzos La Coru\u00f1a 15300",
    "addr:housenumber":"1",
    "addr:postcode":"15300",
    "addr:street":"Rua Pintor Seijo Rubio;La",
    "iso:country":"ES",
    "sg:address":"Rua Pintor Seijo Rubio, 1",
    "sg:city":"Betanzos",
    "sg:orig_category":"Fabricaci\u00d3n De Su\u00c9ters Y Chalecos De Punto",
    "sg:phone":"+34 981 77 20 05",
    "sg:postcode":"15300",
    "sg:province":"La Coru\u00f1a",
    "wof:name":"Barallobre Pazos Jose",
    "wof:placetype":"venue"
},
  "geometry": {"coordinates":[-8.2119092941,43.279914856],"type":"Point"}
}