{
  "type": "Feature",
  "properties": {
    "addr:full":"Ctra. H-sevilla, Km. 0597,0 Palma Condado Huelva 21700",
    "addr:postcode":"21700",
    "addr:street":"Ctra. H-Sevilla Km. 0597,0",
    "iso:country":"ES",
    "sg:address":"Ctra. H-sevilla, Km. 0597,0",
    "sg:city":"Palma Condado",
    "sg:orig_category":"Contenedores (mercanc\u00cdas)",
    "sg:phone":"+34 959 50 60 15",
    "sg:postcode":"21700",
    "sg:province":"Huelva",
    "wof:name":"Hermanos Dominguez Casado S.l.",
    "wof:placetype":"venue"
},
  "geometry": {"coordinates":[-6.556842804,37.3890342712],"type":"Point"}
}