{
  "type": "Feature",
  "properties": {
    "iso:country":"ES",
    "sg:address":"Ctra. Andratx, 28",
    "sg:city":"Portals Nous",
    "sg:orig_category":"Fabricaci\u00d3n De Peines Y De Accesorios De Peluquer\u00cda",
    "sg:phone":"+34 971 67 60 26",
    "sg:postcode":"07181",
    "sg:province":"Islas Baleares",
    "wof:name":"Continental Business S.l.",
    "wof:placetype":"venue"
},
  "geometry": {"coordinates":[2.5722010136,39.5353431702],"type":"Point"}
}