{
  "type": "Feature",
  "properties": {
    "iso:country":"ES",
    "sg:address":"Carrer de Navas De Tolosa, 290",
    "sg:city":"Barcelona",
    "sg:orig_category":"Artes Gr\u00c1ficas, Artes Pl\u00c1sticas (curso)",
    "sg:phone":"+34 933 51 42 50",
    "sg:postcode":"08027",
    "sg:province":"Barcelona",
    "wof:name":"Servei Grafic S.l.",
    "wof:placetype":"venue"
},
  "geometry": {"coordinates":[2.1860749722,41.4161109924],"type":"Point"}
}