{
  "type": "Feature",
  "properties": {
    "iso:country":"ES",
    "sg:address":"Calle de Molina Lario, 5",
    "sg:city":"Malaga",
    "sg:orig_category":"Imprenta",
    "sg:phone":"+34 952 21 12 86",
    "sg:postcode":"29015",
    "sg:province":"M\u00e1laga",
    "wof:name":"Ruiz Tellez Jose",
    "wof:placetype":"venue"
},
  "geometry": {"coordinates":[-4.4199571609,36.7210426331],"type":"Point"}
}