{
  "type": "Feature",
  "properties": {
    "iso:country":"ES",
    "sg:address":"Calle de Quintana, 10",
    "sg:city":"Madrid",
    "sg:orig_category":"Comerciantes Al Por Mayor De Vinos, Licores Y Alcoholes",
    "sg:phone":"+34 915 48 23 42",
    "sg:postcode":"28008",
    "sg:province":"Madrid",
    "wof:name":"Miguel Lafuente Lorenzo S.a.",
    "wof:placetype":"venue"
},
  "geometry": {"coordinates":[-3.7167131901,40.428188324],"type":"Point"}
}