{
  "type": "Feature",
  "properties": {
    "addr:full":"Carrer de Vivet, 9 Taradell Barcelona 08552",
    "addr:housenumber":"9",
    "addr:postcode":"08552",
    "addr:street":"Carrer De Vivet",
    "iso:country":"ES",
    "sg:address":"Carrer de Vivet, 9",
    "sg:city":"Taradell",
    "sg:orig_category":"Construcciones Met\u00c1licas",
    "sg:phone":"+34 938 80 11 82",
    "sg:postcode":"08552",
    "sg:province":"Barcelona",
    "wof:name":"Meta%urgiques Mora S.l.",
    "wof:placetype":"venue"
},
  "geometry": {"coordinates":[2.2850599289,41.8756103516],"type":"Point"}
}