{
  "type": "Feature",
  "properties": {
    "iso:country":"ES",
    "sg:address":"Av Sant Bernat Calbo, 11",
    "sg:city":"Vic",
    "sg:orig_category":"Peluquer\u00cdas, Peluquer\u00cda Mixta",
    "sg:phone":"+34 938 86 39 84",
    "sg:postcode":"08500",
    "sg:province":"Barcelona",
    "wof:name":"Vic Estil Perruquers S.l.",
    "wof:placetype":"venue"
},
  "geometry": {"coordinates":[2.2616739273,41.9354362488],"type":"Point"}
}