{
  "type": "Feature",
  "properties": {
    "addr:full":"Calle de Practicante Casto Moros, 25 Ojos De Garza Las Palmas 35219",
    "addr:housenumber":"25",
    "addr:postcode":"35219",
    "addr:street":"Calle De Practicante;Moros;Las Palmas",
    "iso:country":"ES",
    "sg:address":"Calle de Practicante Casto Moros, 25",
    "sg:city":"Ojos De Garza",
    "sg:orig_category":"Supermercados Y Hipermercados",
    "sg:phone":"+34 928 57 52 54",
    "sg:postcode":"35219",
    "sg:province":"Las Palmas",
    "wof:name":"Padilla Galera Fernando",
    "wof:placetype":"venue"
},
  "geometry": {"coordinates":[-15.3971271515,27.9631061554],"type":"Point"}
}