{
  "type": "Feature",
  "properties": {
    "iso:country":"ES",
    "sg:address":"Santa Marina, 28",
    "sg:city":"S. Cristobal Entrevi\u00f1as",
    "sg:orig_category":"Colchones (fabricaci\u00d3n, Al Por Mayor, Al Por Menor)",
    "sg:phone":"+34 980 64 35 36",
    "sg:postcode":"49690",
    "sg:province":"Zamora",
    "sg:website":"www.minuit.es",
    "wof:name":"Minuit S.a.",
    "wof:placetype":"venue"
},
  "geometry": {"coordinates":[-5.6349887848,42.0465202332],"type":"Point"}
}