{
  "type": "Feature",
  "properties": {
    "iso:country":"ES",
    "sg:address":"Calle de Trivi\u00d1o, 24",
    "sg:city":"Santa Lucia",
    "sg:orig_category":"Plomeros",
    "sg:phone":"+34 968 50 80 79",
    "sg:postcode":"30202",
    "sg:province":"Murcia",
    "wof:name":"Jerez Moreno Angel",
    "wof:placetype":"venue"
},
  "geometry": {"coordinates":[-1.1302499771,37.9829597473],"type":"Point"}
}