{
  "type": "Feature",
  "properties": {
    "iso:country":"ES",
    "sg:address":"Carrer de L'escorial, 168",
    "sg:city":"Barcelona",
    "sg:orig_category":"Molduras, Junquillos, Listones Y Molduras Perforadas",
    "sg:phone":"+34 932 10 16 96",
    "sg:postcode":"08024",
    "sg:province":"Barcelona",
    "wof:name":"Ventacafe S.l.",
    "wof:placetype":"venue"
},
  "geometry": {"coordinates":[2.1583952904,41.4104652405],"type":"Point"}
}