{
  "type": "Feature",
  "properties": {
    "addr:full":"Pg Estacio, 3 Balaguer Lleida 25600",
    "addr:housenumber":"3",
    "addr:postcode":"25600",
    "addr:street":"Pg Estacio",
    "iso:country":"ES",
    "sg:address":"Pg Estacio, 3",
    "sg:city":"Balaguer",
    "sg:orig_category":"Procuradores",
    "sg:phone":"+34 973 44 56 50",
    "sg:postcode":"25600",
    "sg:province":"Lleida",
    "wof:name":"Vilalta Escobar Fernando",
    "wof:placetype":"venue"
},
  "geometry": {"coordinates":[0.8090530038,41.7896003723],"type":"Point"}
}