{
  "type": "Feature",
  "properties": {
    "addr:full":"Calle de Enrique Mari\u00d1as Romero Periodista, 36 Coru\u00d1a A Coru\u00f1a 15009",
    "addr:housenumber":"36",
    "addr:postcode":"15009",
    "addr:street":"Calle De Enrique Marin\u0303As Romero Periodista;Corun\u0303A",
    "iso:country":"ES",
    "sg:address":"Calle de Enrique Mari\u00d1as Romero Periodista, 36",
    "sg:city":"Coru\u00d1a",
    "sg:orig_category":"Promotores Constructores",
    "sg:phone":"+34 981 20 25 91",
    "sg:postcode":"15009",
    "sg:province":"A Coru\u00f1a",
    "wof:name":"Urazca S.a.",
    "wof:placetype":"venue"
},
  "geometry": {"coordinates":[-8.4042072296,43.3402061462],"type":"Point"}
}