{
  "type": "Feature",
  "properties": {
    "addr:full":"Calle de Sierra Nevada, S/n Peligros Granada 18210",
    "addr:housenumber":"/ n",
    "addr:postcode":"18210",
    "addr:street":"Calle De Sierra Nevada S",
    "iso:country":"ES",
    "sg:address":"Calle de Sierra Nevada, S/n",
    "sg:city":"Peligros",
    "sg:orig_category":"Muebles",
    "sg:phone":"+34 958 40 51 12",
    "sg:postcode":"18210",
    "sg:province":"Granada",
    "wof:name":"Lodecam S.l.",
    "wof:placetype":"venue"
},
  "geometry": {"coordinates":[-3.6256990433,37.2233581543],"type":"Point"}
}