{
  "type": "Feature",
  "properties": {
    "addr:full":"Calle de Vandergoten, 8 Madrid Madrid 28014",
    "addr:housenumber":"8",
    "addr:postcode":"madrid;28014",
    "addr:street":"Calle De Vandergoten",
    "iso:country":"ES",
    "sg:address":"Calle de Vandergoten, 8",
    "sg:city":"Madrid",
    "sg:orig_category":"Oficinas: Suministros Para (fabricaci\u00d3n, Al Por Mayor)",
    "sg:phone":"+34 915 52 13 64",
    "sg:postcode":"28014",
    "sg:province":"Madrid",
    "sg:website":"www.computershopsl.com",
    "wof:name":"Computer Shop S.l.",
    "wof:placetype":"venue"
},
  "geometry": {"coordinates":[-3.6820340157,40.4053192139],"type":"Point"}
}