{
  "type": "Feature",
  "properties": {
    "addr:full":"Avda Santa Ana, 7 Leioa Vizcaya 48940",
    "addr:housenumber":"7",
    "addr:postcode":"48940",
    "addr:street":"Avda Santa Ana",
    "iso:country":"ES",
    "sg:address":"Avda Santa Ana, 7",
    "sg:city":"Leioa",
    "sg:orig_category":"Transportes Por Carretera: Lotes Completos, Mercanc\u00cdas Diversas",
    "sg:phone":"+34 944 02 29 38",
    "sg:postcode":"48940",
    "sg:province":"Vizcaya",
    "wof:name":"Larrauri Distribucion Alimentacion, S.l",
    "wof:placetype":"venue"
},
  "geometry": {"coordinates":[-3.0085060596,43.3205986023],"type":"Point"}
}