{
  "type": "Feature",
  "properties": {
    "iso:country":"ES",
    "sg:address":"Calle de Compositor Mario Medina, S/n",
    "sg:city":"Santa Maria De Gracia",
    "sg:orig_category":"Inform\u00c1tica (estudios, Servicios, Asesor\u00cda, Formaci\u00d3n)",
    "sg:phone":"+34 968 27 45 09",
    "sg:postcode":"30100",
    "sg:province":"Murcia",
    "sg:website":"www.alquiline.es",
    "wof:name":"Mercantil Aquiline Computer S.l.",
    "wof:placetype":"venue"
},
  "geometry": {"coordinates":[-1.1298867464,37.9834747314],"type":"Point"}
}