{
  "type": "Feature",
  "properties": {
    "iso:country":"ES",
    "sg:address":"Calle de Padre Mendez, 116",
    "sg:city":"Torrent",
    "sg:orig_category":"Molduras, Junquillos, Listones Y Molduras Perforadas",
    "sg:phone":"+34 961 57 39 62",
    "sg:postcode":"46900",
    "sg:province":"Valencia",
    "wof:name":"Hernandez Ferrando Jose",
    "wof:placetype":"venue"
},
  "geometry": {"coordinates":[-0.4699769914,39.4322471619],"type":"Point"}
}