{
  "type": "Feature",
  "properties": {
    "iso:country":"ES",
    "sg:address":"Calle de Jose Luis Gallo, 3",
    "sg:city":"Talavera Reina",
    "sg:orig_category":"Restaurantes",
    "sg:phone":"+34 925 81 12 25",
    "sg:postcode":"45600",
    "sg:province":"Toledo",
    "wof:name":"Trampal Cortazar Fidel",
    "wof:placetype":"venue"
},
  "geometry": {"coordinates":[-4.8322629929,39.9565429688],"type":"Point"}
}