{
  "type": "Feature",
  "properties": {
    "addr:full":"Carrer de Blatera, 2 Son Ferriol Islas Baleares 07198",
    "addr:housenumber":"2",
    "addr:postcode":"07198",
    "addr:street":"Carrer De Blatera",
    "iso:country":"ES",
    "sg:address":"Carrer de Blatera, 2",
    "sg:city":"Son Ferriol",
    "sg:orig_category":"Ferreter\u00cda Artesanal",
    "sg:phone":"+34 971 42 95 79",
    "sg:postcode":"07198",
    "sg:province":"Islas Baleares",
    "wof:name":"Nadal Mulet Francisco",
    "wof:placetype":"venue"
},
  "geometry": {"coordinates":[2.7170300484,39.5755653381],"type":"Point"}
}