{
  "type": "Feature",
  "properties": {
    "iso:country":"ES",
    "sg:address":"Calle de Tapia De Casariego, 5",
    "sg:city":"Madrid",
    "sg:orig_category":"Electricidad: Instaladores",
    "sg:phone":"+34 913 57 43 06",
    "sg:postcode":"28023",
    "sg:province":"Madrid",
    "wof:name":"Prado Oeste S.l.",
    "wof:placetype":"venue"
},
  "geometry": {"coordinates":[-3.7757790089,40.4639663696],"type":"Point"}
}