{
  "type": "Feature",
  "properties": {
    "addr:full":"Barr Valleja, 14 Barcena Cudon Cantabria 39312",
    "addr:housenumber":"14",
    "addr:postcode":"39312",
    "addr:street":"Valleja",
    "iso:country":"ES",
    "sg:address":"Barr Valleja, 14",
    "sg:city":"Barcena Cudon",
    "sg:orig_category":"Material Y Herramientas Agr\u00cdcolas",
    "sg:phone":"+34 942 57 61 25",
    "sg:postcode":"39312",
    "sg:province":"Cantabria",
    "wof:name":"Perez Poo Javier",
    "wof:placetype":"venue"
},
  "geometry": {"coordinates":[-4.0284891129,43.3888206482],"type":"Point"}
}