{
  "type": "Feature",
  "properties": {
    "iso:country":"ES",
    "sg:address":"Calle de Conde Lopez Mu\u00d1oz, 32",
    "sg:city":"Huelva",
    "sg:orig_category":"Inform\u00c1tica: Material Y Suministros",
    "sg:phone":"+34 959 23 30 23",
    "sg:postcode":"21006",
    "sg:province":"Huelva",
    "wof:name":"Onuseinin S.l.",
    "wof:placetype":"venue"
},
  "geometry": {"coordinates":[-6.9354577065,37.2593765259],"type":"Point"}
}