{
  "type": "Feature",
  "properties": {
    "addr:full":"Avda Reyes Catolicos, 1 Albolote Granada 18220",
    "addr:housenumber":"1",
    "addr:postcode":"18220",
    "addr:street":"Avda Reyes Catolicos",
    "iso:country":"ES",
    "sg:address":"Avda Reyes Catolicos, 1",
    "sg:city":"Albolote",
    "sg:orig_category":"Cl\u00cdnicas M\u00c9dicas",
    "sg:phone":"+34 958 46 69 99",
    "sg:postcode":"18220",
    "sg:province":"Granada",
    "sg:website":"www.polisalud.com",
    "wof:name":"Policlinica Cristo De La Salud S.l.",
    "wof:placetype":"venue"
},
  "geometry": {"coordinates":[-3.6538929939,37.228187561],"type":"Point"}
}