{
  "type": "Feature",
  "properties": {
    "iso:country":"ES",
    "sg:address":"Carrer de Sant Carles, 51",
    "sg:city":"Santa Coloma De Gramenet",
    "sg:orig_category":"Reposter\u00cdas",
    "sg:phone":"+34 934 66 07 56",
    "sg:postcode":"08922",
    "sg:province":"Barcelona",
    "wof:name":"Pareja Moraleda Antonia",
    "wof:placetype":"venue"
},
  "geometry": {"coordinates":[2.2090859413,41.4496307373],"type":"Point"}
}