{
  "type": "Feature",
  "properties": {
    "iso:country":"ES",
    "sg:address":"De Malaga, 54",
    "sg:city":"Almeria",
    "sg:orig_category":"Fabricaci\u00d3n, Reparaci\u00d3n Y Mantenimiento De Construcciones Navales Y Fluviales",
    "sg:phone":"+34 950 27 12 57",
    "sg:postcode":"04002",
    "sg:province":"Almer\u00eda",
    "sg:website":"www.nauticagines.es",
    "wof:name":"Nautica Gines Alonso S.l.",
    "wof:placetype":"venue"
},
  "geometry": {"coordinates":[-2.4815320969,36.8369445801],"type":"Point"}
}