{
  "type": "Feature",
  "properties": {
    "iso:country":"ES",
    "sg:address":"Calle de Colon, 8",
    "sg:city":"Fuensalida",
    "sg:orig_category":"Asesor\u00cda Sobre Comunicaci\u00d3n De Empresas",
    "sg:phone":"+34 925 77 61 03",
    "sg:postcode":"45510",
    "sg:province":"Toledo",
    "wof:name":"Eurofomento Inmobiliario S.l.",
    "wof:placetype":"venue"
},
  "geometry": {"coordinates":[-4.211974144,40.0481185913],"type":"Point"}
}