{
  "type": "Feature",
  "properties": {
    "addr:full":"Calle de Toledo, 60 Madrid Madrid 28005",
    "addr:housenumber":"60",
    "addr:postcode":"madrid;28005",
    "addr:street":"Calle De Toledo",
    "iso:country":"ES",
    "sg:address":"Calle de Toledo, 60",
    "sg:city":"Madrid",
    "sg:orig_category":"Establecimientos De Cura, Prevenci\u00d3n Y Readaptaci\u00d3n",
    "sg:phone":"+34 913 65 61 45",
    "sg:postcode":"28005",
    "sg:province":"Madrid",
    "wof:name":"Asociacion Epsilon",
    "wof:placetype":"venue"
},
  "geometry": {"coordinates":[-3.7093572617,40.4101676941],"type":"Point"}
}