{
  "type": "Feature",
  "properties": {
    "addr:full":"Calle de Puente Espinosa, 16 Granada Granada 18009",
    "addr:housenumber":"16",
    "addr:postcode":"18009",
    "addr:street":"Calle De Puente Espinosa",
    "iso:country":"ES",
    "sg:address":"Calle de Puente Espinosa, 16",
    "sg:city":"Granada",
    "sg:orig_category":"Ense\u00d1ante, Direcci\u00d3n",
    "sg:phone":"+34 958 22 00 06",
    "sg:postcode":"18009",
    "sg:province":"Granada",
    "wof:name":"Fernandez-crehuet Lopez Ignacio",
    "wof:placetype":"venue"
},
  "geometry": {"coordinates":[-3.5930359364,37.1779098511],"type":"Point"}
}