{
  "type": "Feature",
  "properties": {
    "addr:full":"Carrer de Ingeniero Mira, 10 Guardamar Segura Alicante 03140",
    "addr:housenumber":"10",
    "addr:postcode":"03140",
    "addr:street":"Carrer De Ingeniero Mira",
    "iso:country":"ES",
    "sg:address":"Carrer de Ingeniero Mira, 10",
    "sg:city":"Guardamar Segura",
    "sg:orig_category":"Agencias De Viajes",
    "sg:phone":"+34 965 72 77 13",
    "sg:postcode":"03140",
    "sg:province":"Alicante",
    "wof:name":"Martinez Teva Sagrario",
    "wof:placetype":"venue"
},
  "geometry": {"coordinates":[-0.6540290117,38.086681366],"type":"Point"}
}