{
  "type": "Feature",
  "properties": {
    "iso:country":"ES",
    "sg:address":"Castilla La Mancha(p I Zarate), 9",
    "sg:city":"Peligros",
    "sg:orig_category":"Comercio De Piezas De Recambio Y De Accesorios De Veh\u00cdculos, Veh\u00cdculos Industriales",
    "sg:phone":"+34 958 43 03 53",
    "sg:postcode":"18210",
    "sg:province":"Granada",
    "wof:name":"Recambios Salysan S.l.l",
    "wof:placetype":"venue"
},
  "geometry": {"coordinates":[-3.6335589886,37.2246208191],"type":"Point"}
}