{
  "type": "Feature",
  "properties": {
    "addr:full":"Calle de Carrion, 10 Malaga M\u00e1laga 29013",
    "addr:housenumber":"10",
    "addr:postcode":"29013",
    "addr:street":"Calle De Carrion;Ma\u0301Laga",
    "iso:country":"ES",
    "sg:address":"Calle de Carrion, 10",
    "sg:city":"Malaga",
    "sg:orig_category":"Ingeniero",
    "sg:phone":"+34 952 25 83 42",
    "sg:postcode":"29013",
    "sg:province":"M\u00e1laga",
    "wof:name":"Sanchez Olmos Antonia",
    "wof:placetype":"venue"
},
  "geometry": {"coordinates":[-4.4191613197,36.7267532349],"type":"Point"}
}