{
  "type": "Feature",
  "properties": {
    "iso:country":"ES",
    "sg:address":"Avda Reyes Catolicos, 14",
    "sg:city":"Alcala Henares",
    "sg:orig_category":"Asesor\u00cda Fiscal Y Jur\u00cddica",
    "sg:phone":"+34 918 83 20 02",
    "sg:postcode":"28802",
    "sg:province":"Madrid",
    "wof:name":"Asesoria Reyes Catolicos S.l.",
    "wof:placetype":"venue"
},
  "geometry": {"coordinates":[-3.3737545013,40.4774475098],"type":"Point"}
}