{
  "type": "Feature",
  "properties": {
    "addr:full":"Calle de Loma Redonda, 24 Loma Murcia 30394",
    "addr:housenumber":"24",
    "addr:postcode":"30394",
    "addr:street":"Calle De Loma Redonda",
    "iso:country":"ES",
    "sg:address":"Calle de Loma Redonda, 24",
    "sg:city":"Loma",
    "sg:orig_category":"Controles De Edificaci\u00d3n (construcci\u00d3n, Seguridad)",
    "sg:phone":"+34 968 55 39 55",
    "sg:postcode":"30394",
    "sg:province":"Murcia",
    "wof:name":"Viviendas Sambra S.l",
    "wof:placetype":"venue"
},
  "geometry": {"coordinates":[-1.1298867464,37.9834747314],"type":"Point"}
}