{
  "type": "Feature",
  "properties": {
    "addr:full":"Calle de San Francisco, 51 Villanueva Serena Badajoz 06700",
    "addr:housenumber":"51",
    "addr:postcode":"06700",
    "addr:street":"Calle De San Francisco",
    "iso:country":"ES",
    "sg:address":"Calle de San Francisco, 51",
    "sg:city":"Villanueva Serena",
    "sg:orig_category":"Electrodom\u00c9sticos (al Por Menor)",
    "sg:phone":"+34 924 84 30 03",
    "sg:postcode":"06700",
    "sg:province":"Badajoz",
    "wof:name":"Hermanos Gilgado Galan C.b.",
    "wof:placetype":"venue"
},
  "geometry": {"coordinates":[-5.7958989143,38.9737129211],"type":"Point"}
}