{
  "type": "Feature",
  "properties": {
    "addr:full":"Carrer de Barcelona, 205 Sant Vicen\u00c7 Dels Horts Barcelona 08620",
    "addr:housenumber":"205",
    "addr:postcode":"08620",
    "addr:street":"Carrer De Barcelona;Sant Vicenc\u0327 Dels Horts Barcelona",
    "iso:country":"ES",
    "sg:address":"Carrer de Barcelona, 205",
    "sg:city":"Sant Vicen\u00c7 Dels Horts",
    "sg:orig_category":"Ropa Para Ni\u00d1os (al Por Menor)",
    "sg:phone":"+34 936 56 75 90",
    "sg:postcode":"08620",
    "sg:province":"Barcelona",
    "wof:name":"Lopez Alvarez Maria Carmen",
    "wof:placetype":"venue"
},
  "geometry": {"coordinates":[2.0080559254,41.3981361389],"type":"Point"}
}