{
  "type": "Feature",
  "properties": {
    "addr:full":"Calle de Salmon, 6 Granada Granada 18015",
    "addr:housenumber":"6",
    "addr:postcode":"18015",
    "addr:street":"Calle De Salmon",
    "iso:country":"ES",
    "sg:address":"Calle de Salmon, 6",
    "sg:city":"Granada",
    "sg:orig_category":"Agencias Y Agentes Comerciales, Representantes",
    "sg:phone":"+34 958 20 97 06",
    "sg:postcode":"18015",
    "sg:province":"Granada",
    "wof:name":"Representaciones Ernesto Faciaben Madrid S.l.",
    "wof:placetype":"venue"
},
  "geometry": {"coordinates":[-3.6356139183,37.1961364746],"type":"Point"}
}