{
  "type": "Feature",
  "properties": {
    "addr:full":"Rua Severino Rivas, S/n Castro Lugo 27260",
    "addr:housenumber":"s / n",
    "addr:postcode":"27260",
    "addr:street":"Rua Severino Rivas",
    "iso:country":"ES",
    "sg:address":"Rua Severino Rivas, S/n",
    "sg:city":"Castro",
    "sg:orig_category":"Cooperativas Agr\u00cdcolas",
    "sg:phone":"+34 982 31 01 32",
    "sg:postcode":"27260",
    "sg:province":"Lugo",
    "wof:name":"Gonzalez Lage Josefa",
    "wof:placetype":"venue"
},
  "geometry": {"coordinates":[-7.4948401451,43.1400909424],"type":"Point"}
}