{
  "type": "Feature",
  "properties": {
    "iso:country":"ES",
    "sg:address":"Calle de Juan De Miranda, 4",
    "sg:city":"Palmas De Gran Canaria",
    "sg:orig_category":"Inmobiliaria (agencias)",
    "sg:phone":"+34 928 22 43 99",
    "sg:postcode":"35008",
    "sg:province":"Las Palmas",
    "wof:name":"Disonomo Canario S.l",
    "wof:placetype":"venue"
},
  "geometry": {"coordinates":[-15.4321985245,28.142490387],"type":"Point"}
}