{
  "type": "Feature",
  "properties": {
    "iso:country":"ES",
    "sg:address":"Carrer de Monterols, 27",
    "sg:city":"Reus",
    "sg:orig_category":"Fabricaci\u00d3n De Su\u00c9ters Y Chalecos De Punto",
    "sg:phone":"+34 977 12 87 69",
    "sg:postcode":"43201",
    "sg:province":"Tarragona",
    "wof:name":"Tallarda Castells Montserrat",
    "wof:placetype":"venue"
},
  "geometry": {"coordinates":[1.1077990532,41.1558151245],"type":"Point"}
}