{
  "type": "Feature",
  "properties": {
    "addr:full":"Po Los Llanos, S/n Estella Navarra 31200",
    "addr:housenumber":"s / n",
    "addr:postcode":"31200",
    "addr:street":"Los Llanos",
    "iso:country":"ES",
    "sg:address":"Po Los Llanos, S/n",
    "sg:city":"Estella",
    "sg:orig_category":"Centros De Educaci\u00d3n Especial",
    "sg:phone":"+34 948 55 50 99",
    "sg:postcode":"31200",
    "sg:province":"Navarra",
    "wof:name":"Lizarra Haur Eskola S.l.",
    "wof:placetype":"venue"
},
  "geometry": {"coordinates":[-2.0353488922,42.6726417542],"type":"Point"}
}