{
  "type": "Feature",
  "properties": {
    "iso:country":"ES",
    "sg:address":"Carrer de Calatrava, 71",
    "sg:city":"Barcelona",
    "sg:orig_category":"Agencias Y Asesores De Publicidad",
    "sg:phone":"+34 934 34 34 34",
    "sg:postcode":"08...",
    "sg:province":"Barcelona",
    "wof:name":"Segarra Cuesta Puig Fernandez De Castro S.l.",
    "wof:placetype":"venue"
},
  "geometry": {"coordinates":[2.1278409958,41.4017524719],"type":"Point"}
}