{
  "type": "Feature",
  "properties": {
    "iso:country":"ES",
    "sg:address":"Plaz Espa\u00d1a, 2",
    "sg:city":"Ciudad Real",
    "sg:orig_category":"Caf\u00c9s, Bares, Cervecer\u00cdas",
    "sg:phone":"+34 926 25 60 45",
    "sg:postcode":"13003",
    "sg:province":"Ciudad Real",
    "wof:name":"Chillalon Huecas Pedro",
    "wof:placetype":"venue"
},
  "geometry": {"coordinates":[-3.9273989201,38.9929542542],"type":"Point"}
}