{
  "type": "Feature",
  "properties": {
    "iso:country":"ES",
    "sg:address":"Calle de Montalbos, 39",
    "sg:city":"Madrid",
    "sg:orig_category":"Centros Empresariales",
    "sg:phone":"+34 913 82 18 10",
    "sg:postcode":"28043",
    "sg:province":"Madrid",
    "wof:name":"Eurocivil S.l.",
    "wof:placetype":"venue"
},
  "geometry": {"coordinates":[-3.6395289898,40.4645881653],"type":"Point"}
}