{
  "type": "Feature",
  "properties": {
    "addr:full":"Calle de Libertad, 9 Zamora Zamora 49010",
    "addr:housenumber":"9",
    "addr:postcode":"49010",
    "addr:street":"Calle De Libertad",
    "iso:country":"ES",
    "sg:address":"Calle de Libertad, 9",
    "sg:city":"Zamora",
    "sg:orig_category":"Carnicer\u00cdas, Carnicer\u00cdas",
    "sg:phone":"+34 980 52 25 96",
    "sg:postcode":"49010",
    "sg:province":"Zamora",
    "wof:name":"Calvo Andres Jesus",
    "wof:placetype":"venue"
},
  "geometry": {"coordinates":[-5.7427330017,41.5121459961],"type":"Point"}
}