{
  "type": "Feature",
  "properties": {
    "iso:country":"ES",
    "sg:address":"Avda Palos De La Frontera, 104",
    "sg:city":"Niebla",
    "sg:orig_category":"Mec\u00c1nico Del Autom\u00d3vil",
    "sg:phone":"+34 959 36 23 54",
    "sg:postcode":"21840",
    "sg:province":"Huelva",
    "wof:name":"Neugope S.l.l.",
    "wof:placetype":"venue"
},
  "geometry": {"coordinates":[-6.6856379509,37.3586463928],"type":"Point"}
}