{
  "type": "Feature",
  "properties": {
    "addr:full":"Rio Alhama, 198 Sequero La Rioja 26509",
    "addr:housenumber":"198",
    "addr:postcode":"26509",
    "addr:street":"Alhama;Sequero;Rioja",
    "iso:country":"ES",
    "sg:address":"Rio Alhama, 198",
    "sg:city":"Sequero",
    "sg:orig_category":"Construcciones Met\u00c1licas",
    "sg:phone":"+34 941 43 14 31",
    "sg:postcode":"26509",
    "sg:province":"La Rioja",
    "wof:name":"Caldereria Mateo Hermanos S.l.",
    "wof:placetype":"venue"
},
  "geometry": {"coordinates":[-2.1222639084,42.4031410217],"type":"Point"}
}