{
  "type": "Feature",
  "properties": {
    "addr:full":"Ctra. General, S/n Vegadeo Asturias 33770",
    "addr:postcode":"33770",
    "addr:street":"Ctra. General S / N",
    "iso:country":"ES",
    "sg:address":"Ctra. General, S/n",
    "sg:city":"Vegadeo",
    "sg:classifiers":[
        {
            "category":"Taxi",
            "type":"Transportation"
        }
    ],
    "sg:phone":"+34 985 63 45 90",
    "sg:postcode":"33770",
    "sg:province":"Asturias",
    "wof:name":"Casta\u00f1o Rodriguez Marcelino",
    "wof:placetype":"venue"
},
  "geometry": {"coordinates":[-7.0507240295,43.464225769],"type":"Point"}
}