{
  "type": "Feature",
  "properties": {
    "iso:country":"ES",
    "sg:address":"Calle de Zodiaco, 13",
    "sg:city":"Arroyo De La Miel-benalmadena Costa",
    "sg:orig_category":"Inmobiliaria (agencias)",
    "sg:phone":"+34 952 57 68 76",
    "sg:postcode":"29630",
    "sg:province":"M\u00e1laga",
    "wof:name":"Traisa S.a.",
    "wof:placetype":"venue"
},
  "geometry": {"coordinates":[-4.527739048,36.598613739],"type":"Point"}
}