{
  "type": "Feature",
  "properties": {
    "iso:country":"ES",
    "sg:address":"Calle de Cardenal Torquemada, 24",
    "sg:city":"Valladolid",
    "sg:orig_category":"Zapatos (al Por Menor)",
    "sg:phone":"+34 983 25 31 63",
    "sg:postcode":"47010",
    "sg:province":"Valladolid",
    "wof:name":"Perez Gusano Miguel",
    "wof:placetype":"venue"
},
  "geometry": {"coordinates":[-4.719016552,41.6651115417],"type":"Point"}
}