{
  "type": "Feature",
  "properties": {
    "iso:country":"ES",
    "sg:address":"Rbla Bobiles, S/n",
    "sg:city":"Martorell",
    "sg:orig_category":"Carnicer\u00cdas, Carnicer\u00cdas",
    "sg:phone":"+34 937 76 96 26",
    "sg:postcode":"08760",
    "sg:province":"Barcelona",
    "wof:name":"Dominguez Ruiz Candido",
    "wof:placetype":"venue"
},
  "geometry": {"coordinates":[1.9169800282,41.4771957397],"type":"Point"}
}