{
  "type": "Feature",
  "properties": {
    "addr:full":"Avda Malecon, 41 Santa Uxia De Ribeira La Coru\u00f1a 15960",
    "addr:housenumber":"41",
    "addr:postcode":"15960",
    "addr:street":"Avda Malecon;Corun\u0303A",
    "iso:country":"ES",
    "sg:address":"Avda Malecon, 41",
    "sg:city":"Santa Uxia De Ribeira",
    "sg:orig_category":"Molduras, Junquillos, Listones Y Molduras Perforadas",
    "sg:phone":"+34 981 87 07 78",
    "sg:postcode":"15960",
    "sg:province":"La Coru\u00f1a",
    "wof:name":"Mari\u00f1o Gonzalez Juan",
    "wof:placetype":"venue"
},
  "geometry": {"coordinates":[-8.9921865463,42.557598114],"type":"Point"}
}