{
  "type": "Feature",
  "properties": {
    "iso:country":"ES",
    "sg:address":"Cmno Salabosque, 31",
    "sg:city":"Aljucer",
    "sg:orig_category":"Empresas De Carpinter\u00cda Met\u00c1lica",
    "sg:phone":"+34 968 26 03 67",
    "sg:postcode":"30152",
    "sg:province":"Murcia",
    "wof:name":"Antonio Y Angel Gallego S.l.",
    "wof:placetype":"venue"
},
  "geometry": {"coordinates":[-1.1461594105,37.9602508545],"type":"Point"}
}