{
  "type": "Feature",
  "properties": {
    "iso:country":"ES",
    "sg:address":"Conde De Lucanor, 35",
    "sg:city":"Malaga",
    "sg:orig_category":"Inversiones",
    "sg:phone":"+34 952 23 73 34",
    "sg:postcode":"29004",
    "sg:province":"M\u00e1laga",
    "wof:name":"Ansoal S.l.",
    "wof:placetype":"venue"
},
  "geometry": {"coordinates":[-4.4636058807,36.6699142456],"type":"Point"}
}