{
  "type": "Feature",
  "properties": {
    "addr:full":"Rua Meson, 3 Fonsagrada Lugo 27100",
    "addr:housenumber":"3",
    "addr:postcode":"27100",
    "addr:street":"Rua Meson",
    "iso:country":"ES",
    "sg:address":"Rua Meson, 3",
    "sg:city":"Fonsagrada",
    "sg:classifiers":[
        {
            "category":"Taxi",
            "type":"Transportation"
        }
    ],
    "sg:phone":"+34 982 34 00 18",
    "sg:postcode":"27100",
    "sg:province":"Lugo",
    "wof:name":"Alvarez Alvarez Eustasio",
    "wof:placetype":"venue"
},
  "geometry": {"coordinates":[-7.0660610199,43.1240158081],"type":"Point"}
}