{
  "type": "Feature",
  "properties": {
    "iso:country":"ES",
    "sg:address":"Avda Gran Capitan (del), 44",
    "sg:city":"Cordoba",
    "sg:orig_category":"Inmobiliaria (agencias)",
    "sg:phone":"+34 957 47 64 21",
    "sg:postcode":"14001",
    "sg:province":"C\u00f3rdoba",
    "wof:name":"Lopesol S.a.",
    "wof:placetype":"venue"
},
  "geometry": {"coordinates":[-4.7827749252,37.8903846741],"type":"Point"}
}