{
  "type": "Feature",
  "properties": {
    "addr:full":"Avda Suel Urb Ajolin, 2 Fuengirola M\u00e1laga 29640",
    "addr:housenumber":"2",
    "addr:postcode":"29640",
    "addr:street":"Avda Suel Urb Ajolin;Ma\u0301Laga",
    "iso:country":"ES",
    "sg:address":"Avda Suel Urb Ajolin, 2",
    "sg:city":"Fuengirola",
    "sg:orig_category":"Pescader\u00cdas (al Por Menor)",
    "sg:phone":"+34 952 58 88 63",
    "sg:postcode":"29640",
    "sg:province":"M\u00e1laga",
    "wof:name":"Fernandez Jimenez Rosalia",
    "wof:placetype":"venue"
},
  "geometry": {"coordinates":[-4.6239790916,36.5414886475],"type":"Point"}
}