{
  "type": "Feature",
  "properties": {
    "addr:full":"Carrer de Ramon Farguell, 16 Manresa Barcelona 08243",
    "addr:housenumber":"16",
    "addr:postcode":"08243",
    "addr:street":"Carrer De Ramon Farguell",
    "iso:country":"ES",
    "sg:address":"Carrer de Ramon Farguell, 16",
    "sg:city":"Manresa",
    "sg:orig_category":"Construcci\u00d3n Mec\u00c1nica",
    "sg:phone":"+34 938 77 00 74",
    "sg:postcode":"08243",
    "sg:province":"Barcelona",
    "wof:name":"Construcciones Mecanicas Orriols S.cv",
    "wof:placetype":"venue"
},
  "geometry": {"coordinates":[1.8430459499,41.7125587463],"type":"Point"}
}