{
  "type": "Feature",
  "properties": {
    "addr:full":"Av Comte Guifre, S/n Centre Urba Girona 17500",
    "addr:housenumber":"s / n",
    "addr:postcode":"17500",
    "addr:street":"Guifre;Centre Urba",
    "iso:country":"ES",
    "sg:address":"Av Comte Guifre, S/n",
    "sg:city":"Centre Urba",
    "sg:orig_category":"Guarder\u00cdas",
    "sg:phone":"+34 972 70 15 54",
    "sg:postcode":"17500",
    "sg:province":"Girona",
    "wof:name":"Centre De Telecomunicaciones De Catalunya",
    "wof:placetype":"venue"
},
  "geometry": {"coordinates":[2.1959049702,42.1965866089],"type":"Point"}
}