{
  "type": "Feature",
  "properties": {
    "iso:country":"ES",
    "sg:address":"Avda Gaspar Aguilar, 114",
    "sg:city":"Valencia",
    "sg:orig_category":"Lavado, Limpieza De Veh\u00cdculos",
    "sg:phone":"+34 963 57 48 53",
    "sg:postcode":"46017",
    "sg:province":"Valencia",
    "wof:name":"Auto Avenida Gaspar Aguilar S.l.",
    "wof:placetype":"venue"
},
  "geometry": {"coordinates":[-0.3940140009,39.4512519836],"type":"Point"}
}