{
  "type": "Feature",
  "properties": {
    "addr:full":"Calle de Guadalajara, 5 Madrid Madrid 28042",
    "addr:housenumber":"5",
    "addr:postcode":"28042",
    "addr:street":"Calle De Guadalajara",
    "iso:country":"ES",
    "sg:address":"Calle de Guadalajara, 5",
    "sg:city":"Madrid",
    "sg:orig_category":"Arquitectos",
    "sg:phone":"+34 917 41 81 55",
    "sg:postcode":"28042",
    "sg:province":"Madrid",
    "wof:name":"Ladron De Guevara Rovira Pedro Isaac",
    "wof:placetype":"venue"
},
  "geometry": {"coordinates":[-3.6151130199,40.4523086548],"type":"Point"}
}