{
  "type": "Feature",
  "properties": {
    "addr:full":"Calle de Soria, 9 Montijo Badajoz 06480",
    "addr:housenumber":"9",
    "addr:postcode":"06480",
    "addr:street":"Calle De Soria",
    "iso:country":"ES",
    "sg:address":"Calle de Soria, 9",
    "sg:city":"Montijo",
    "sg:orig_category":"Asociaciones Humanitarias, De Cooperaci\u00d3n, De Acci\u00d3n Social",
    "sg:phone":"+34 924 45 05 81",
    "sg:postcode":"06480",
    "sg:province":"Badajoz",
    "wof:name":"Asociacion Espa\u00f1ola Contra El Cancer",
    "wof:placetype":"venue"
},
  "geometry": {"coordinates":[-6.6174530983,38.902885437],"type":"Point"}
}