{
  "type": "Feature",
  "properties": {
    "addr:full":"Calle de Bidasoa, 9 Errenteria Guip\u00f9zcoa 20100",
    "addr:housenumber":"9",
    "addr:postcode":"20100",
    "addr:street":"Calle De Bidasoa;Guipu\u0300Zcoa",
    "iso:country":"ES",
    "sg:address":"Calle de Bidasoa, 9",
    "sg:city":"Errenteria",
    "sg:orig_category":"Inform\u00c1tica (estudios, Servicios, Asesor\u00cda, Formaci\u00d3n)",
    "sg:phone":"+34 943 00 40 03",
    "sg:postcode":"20100",
    "sg:province":"Guip\u00f9zcoa",
    "wof:name":"Oarsolan Sistemas Informaticos, S.l.",
    "wof:placetype":"venue"
},
  "geometry": {"coordinates":[-1.9023002386,43.3131332397],"type":"Point"}
}