{
  "type": "Feature",
  "properties": {
    "addr:full":"Avda Via Roma (la), 56 Segovia Segovia 40003",
    "addr:housenumber":"56",
    "addr:postcode":"40003",
    "addr:street":"Avda Via Roma La",
    "iso:country":"ES",
    "sg:address":"Avda Via Roma (la), 56",
    "sg:city":"Segovia",
    "sg:orig_category":"Promotores Constructores",
    "sg:phone":"+34 921 41 20 50",
    "sg:postcode":"40003",
    "sg:province":"Segovia",
    "sg:website":"www.pygsur.com",
    "wof:name":"Pygsur Construccion S.a.",
    "wof:placetype":"venue"
},
  "geometry": {"coordinates":[-4.1083059311,40.9549980164],"type":"Point"}
}