{
  "type": "Feature",
  "properties": {
    "addr:full":"Carrer de Milans Del Bosch, S/n S. Vicen\u00e7 Montalt Barcelona 08394",
    "addr:housenumber":"s",
    "addr:postcode":"08394",
    "addr:street":"Carrer De Milans Del Bosch;/ N S. Vicenc\u0327 Montalt Barcelona",
    "iso:country":"ES",
    "sg:address":"Carrer de Milans Del Bosch, S/n",
    "sg:city":"S. Vicen\u00e7 Montalt",
    "sg:orig_category":"Organizaci\u00d3n De Actos, Seminarios Y Congresos",
    "sg:phone":"+34 937 91 15 29",
    "sg:postcode":"08394",
    "sg:province":"Barcelona",
    "wof:name":"Castell De L'oliver S.a.",
    "wof:placetype":"venue"
},
  "geometry": {"coordinates":[2.5138399601,41.5831031799],"type":"Point"}
}