{
  "type": "Feature",
  "properties": {
    "addr:full":"Rua Ervedelo, 31 Ourense Ourense 32002",
    "addr:housenumber":"31",
    "addr:postcode":"32002",
    "addr:street":"Rua Ervedelo",
    "iso:country":"ES",
    "sg:address":"Rua Ervedelo, 31",
    "sg:city":"Ourense",
    "sg:orig_category":"Cajas De Ahorro",
    "sg:phone":"+34 988 22 32 96",
    "sg:postcode":"32002",
    "sg:province":"Ourense",
    "wof:name":"Caixa De Aforros De Vigo Ourense E Pontevedra",
    "wof:placetype":"venue"
},
  "geometry": {"coordinates":[-7.8704152107,42.3392944336],"type":"Point"}
}