{
  "type": "Feature",
  "properties": {
    "addr:full":"Calle de Nicolas Torre, 5 Castro Urdiales Cantabria 39700",
    "addr:housenumber":"5",
    "addr:postcode":"39700",
    "addr:street":"Calle De Nicolas Torre",
    "iso:country":"ES",
    "sg:address":"Calle de Nicolas Torre, 5",
    "sg:city":"Castro Urdiales",
    "sg:orig_category":"Transportes Por V\u00cdas Navegables",
    "sg:phone":"+34 942 87 29 21",
    "sg:postcode":"39700",
    "sg:province":"Cantabria",
    "wof:name":"Transportes Jose Maria Llaguno",
    "wof:placetype":"venue"
},
  "geometry": {"coordinates":[-3.2061154842,43.3709220886],"type":"Point"}
}