{
  "type": "Feature",
  "properties": {
    "iso:country":"ES",
    "sg:address":"Calle de Constitucion, 149",
    "sg:city":"Zarza Granadilla",
    "sg:orig_category":"Charcuter\u00cdas (al Por Menor)",
    "sg:phone":"+34 927 48 60 36",
    "sg:postcode":"10710",
    "sg:province":"C\u00e1ceres",
    "wof:name":"Garcia Jimenez Jose",
    "wof:placetype":"venue"
},
  "geometry": {"coordinates":[-6.0474267006,40.2378997803],"type":"Point"}
}