{
  "type": "Feature",
  "properties": {
    "addr:full":"Calle de Victoria, 45 Malaga M\u00e1laga 29012",
    "addr:housenumber":"45",
    "addr:postcode":"29012",
    "addr:street":"Calle De Victoria;Ma\u0301Laga",
    "iso:country":"ES",
    "sg:address":"Calle de Victoria, 45",
    "sg:city":"Malaga",
    "sg:orig_category":"M\u00c9dicos: Pediatr\u00cda. Enfermedades De Los Ni\u00d1os",
    "sg:phone":"+34 952 65 21 66",
    "sg:postcode":"29012",
    "sg:province":"M\u00e1laga",
    "wof:name":"Garcia Bru Jose Manuel",
    "wof:placetype":"venue"
},
  "geometry": {"coordinates":[-4.4153299332,36.725189209],"type":"Point"}
}