{
  "type": "Feature",
  "properties": {
    "addr:full":"Carrer de Loreto, 50 Barcelona Barcelona 08029",
    "addr:housenumber":"50",
    "addr:postcode":"08029",
    "addr:street":"Carrer De Loreto",
    "iso:country":"ES",
    "sg:address":"Carrer de Loreto, 50",
    "sg:city":"Barcelona",
    "sg:orig_category":"Peluquer\u00cdas, Peluquer\u00cda Mixta",
    "sg:phone":"+34 933 22 04 82",
    "sg:postcode":"08029",
    "sg:province":"Barcelona",
    "wof:name":"Muxa Marxa S.c.p.",
    "wof:placetype":"venue"
},
  "geometry": {"coordinates":[2.1427140236,41.3914489746],"type":"Point"}
}