{
  "type": "Feature",
  "properties": {
    "addr:full":"Pase Reina Sofia, Km. 0299,0 Muela Zaragoza 50196",
    "addr:postcode":"50196",
    "addr:street":"Sofia Km. 0299,0 Muela",
    "iso:country":"ES",
    "sg:address":"Pase Reina Sofia, Km. 0299,0",
    "sg:city":"Muela",
    "sg:orig_category":"Distribuci\u00d3n De Petr\u00d3leo Y Derivados",
    "sg:phone":"+34 976 14 43 55",
    "sg:postcode":"50196",
    "sg:province":"Zaragoza",
    "wof:name":"Area De Servicios La Muela S.l.u",
    "wof:placetype":"venue"
},
  "geometry": {"coordinates":[-1.1131180525,41.5795402527],"type":"Point"}
}