{
  "type": "Feature",
  "properties": {
    "addr:full":"Calle de Via Complutense, 122 Alcala Henares Madrid 28805",
    "addr:housenumber":"122",
    "addr:postcode":"28805",
    "addr:street":"Calle De Via Complutense",
    "iso:country":"ES",
    "sg:address":"Calle de Via Complutense, 122",
    "sg:city":"Alcala Henares",
    "sg:orig_category":"Centros Empresariales",
    "sg:phone":"+34 918 88 46 45",
    "sg:postcode":"28805",
    "sg:province":"Madrid",
    "wof:name":"Moreno Villanueva Rafael",
    "wof:placetype":"venue"
},
  "geometry": {"coordinates":[-3.3437519073,40.4967765808],"type":"Point"}
}