{
  "type": "Feature",
  "properties": {
    "addr:full":"Rua Real, 185 Ferrol La Coru\u00f1a 15402",
    "addr:housenumber":"185",
    "addr:postcode":"15402",
    "addr:street":"Rua Real;La Corun\u0303A",
    "iso:country":"ES",
    "sg:address":"Rua Real, 185",
    "sg:city":"Ferrol",
    "sg:orig_category":"Asociaciones Y Clubs Deportivos",
    "sg:phone":"+34 981 35 15 95",
    "sg:postcode":"15402",
    "sg:province":"La Coru\u00f1a",
    "wof:name":"Andres Fraga Vellon Y Otros S.c.",
    "wof:placetype":"venue"
},
  "geometry": {"coordinates":[-8.2367992401,43.4823875427],"type":"Point"}
}