{
  "type": "Feature",
  "properties": {
    "addr:full":"Olakua Auzoa, 8 O\u00f1ati Guip\u00f9zcoa 20560",
    "addr:housenumber":"8",
    "addr:postcode":"20560",
    "addr:street":"Olakua Auzoa;Guipu\u0300Zcoa",
    "iso:country":"ES",
    "sg:address":"Olakua Auzoa, 8",
    "sg:city":"O\u00f1ati",
    "sg:orig_category":"Supermercados Y Hipermercados",
    "sg:phone":"+34 943 78 12 22",
    "sg:postcode":"20560",
    "sg:province":"Guip\u00f9zcoa",
    "wof:name":"O\u00f1adis S.l.",
    "wof:placetype":"venue"
},
  "geometry": {"coordinates":[-2.4036300182,43.0317001343],"type":"Point"}
}