{
  "type": "Feature",
  "properties": {
    "addr:full":"Rua Pousada, 23 Grove Pontevedra 36980",
    "addr:housenumber":"23",
    "addr:postcode":"36980",
    "addr:street":"Rua Pousada;Grove Pontevedra",
    "iso:country":"ES",
    "sg:address":"Rua Pousada, 23",
    "sg:city":"Grove",
    "sg:orig_category":"Pintura, Barniz, Productos Asimilables (fabricaci\u00d3n, Al Por Mayor)",
    "sg:phone":"+34 986 73 37 76",
    "sg:postcode":"36980",
    "sg:province":"Pontevedra",
    "wof:name":"Pingrove S.l.",
    "wof:placetype":"venue"
},
  "geometry": {"coordinates":[-8.8653888702,42.4902114868],"type":"Point"}
}