{
  "type": "Feature",
  "properties": {
    "iso:country":"ES",
    "sg:address":"Polo, 54",
    "sg:city":"La Orotava",
    "sg:orig_category":"Reposter\u00cdas",
    "sg:phone":"+34 922 33 16 00",
    "sg:postcode":"38300",
    "sg:province":"Santa Cruz De Tenerife",
    "wof:name":"Hernandez Trujillo Ciro",
    "wof:placetype":"venue"
},
  "geometry": {"coordinates":[-16.5175170898,28.3853034973],"type":"Point"}
}