{
  "type": "Feature",
  "properties": {
    "addr:full":"Carr Animes, 5 Palafrugell Girona 17200",
    "addr:housenumber":"5",
    "addr:postcode":"17200",
    "addr:street":"Carr Animes",
    "iso:country":"ES",
    "sg:address":"Carr Animes, 5",
    "sg:city":"Palafrugell",
    "sg:orig_category":"M\u00c9dicos: Medicina General Orientada A La Acupuntura",
    "sg:phone":"+34 972 30 82 50",
    "sg:postcode":"17200",
    "sg:province":"Girona",
    "wof:name":"Acufitui S.l.",
    "wof:placetype":"venue"
},
  "geometry": {"coordinates":[3.1654627323,41.9164199829],"type":"Point"}
}