{
  "type": "Feature",
  "properties": {
    "iso:country":"ES",
    "sg:address":"Cami Font Del Sastre, S/n",
    "sg:city":"S. Hilari Sacalm",
    "sg:orig_category":"Mec\u00c1nico Del Autom\u00d3vil",
    "sg:phone":"+34 972 86 80 81",
    "sg:postcode":"17403",
    "sg:province":"Girona",
    "wof:name":"Moca De Josep Cardona Tarres I Lluis Moriscot Riera C.b.",
    "wof:placetype":"venue"
},
  "geometry": {"coordinates":[2.5134689808,41.8821105957],"type":"Point"}
}