{
  "type": "Feature",
  "properties": {
    "iso:country":"ES",
    "sg:address":"Avda General Peron, 40",
    "sg:city":"Madrid",
    "sg:orig_category":"Sociedades, Compa\u00d1\u00cdas Aseguradoras",
    "sg:phone":"+34 915 78 09 66",
    "sg:postcode":"28020",
    "sg:province":"Madrid",
    "wof:name":"Pool Espa\u00d1ol De Grandes Riesgos A.i.e.",
    "wof:placetype":"venue"
},
  "geometry": {"coordinates":[-3.6916680336,40.4520454407],"type":"Point"}
}