{
  "type": "Feature",
  "properties": {
    "addr:full":"Calle de Comercio, 10 Ribadesella Asturias 33560",
    "addr:housenumber":"10",
    "addr:postcode":"33560",
    "addr:street":"Calle De Comercio",
    "iso:country":"ES",
    "sg:address":"Calle de Comercio, 10",
    "sg:city":"Ribadesella",
    "sg:orig_category":"Farmacias",
    "sg:phone":"+34 985 86 02 01",
    "sg:postcode":"33560",
    "sg:province":"Asturias",
    "wof:name":"Garcia Martin Paz",
    "wof:placetype":"venue"
},
  "geometry": {"coordinates":[-5.0587363243,43.4626083374],"type":"Point"}
}