{
  "type": "Feature",
  "properties": {
    "addr:full":"Avda Fontanar, 2 Pozo Alcon Ja\u00e9n 23485",
    "addr:housenumber":"2",
    "addr:postcode":"23485",
    "addr:street":"Avda Fontanar;Alcon Jae\u0301N",
    "iso:country":"ES",
    "sg:address":"Avda Fontanar, 2",
    "sg:city":"Pozo Alcon",
    "sg:orig_category":"Maquinaria Para Industrias Diversas",
    "sg:phone":"+34 953 73 89 72",
    "sg:postcode":"23485",
    "sg:province":"Ja\u00e9n",
    "wof:name":"Excavaciones Bruanda S.r.l.",
    "wof:placetype":"venue"
},
  "geometry": {"coordinates":[-2.9368391037,37.7030410767],"type":"Point"}
}