{
  "type": "Feature",
  "properties": {
    "addr:full":"Carr Tardor, 10 Badalona Barcelona 08918",
    "addr:housenumber":"10",
    "addr:postcode":"08918",
    "addr:street":"Carr Tardor",
    "iso:country":"ES",
    "sg:address":"Carr Tardor, 10",
    "sg:city":"Badalona",
    "sg:orig_category":"Construcciones Met\u00c1licas",
    "sg:phone":"+34 934 60 74 97",
    "sg:postcode":"08918",
    "sg:province":"Barcelona",
    "wof:name":"Construcciones Metalicas Jamsa S. A.",
    "wof:placetype":"venue"
},
  "geometry": {"coordinates":[2.2267799377,41.4320793152],"type":"Point"}
}