{
  "type": "Feature",
  "properties": {
    "addr:full":"Avda Doctor Solis Pascual, 2 Ubrique C\u00e1diz 11600",
    "addr:housenumber":"2",
    "addr:postcode":"11600",
    "addr:street":"Avda Doctor Solis Pascual;Ca\u0301Diz",
    "iso:country":"ES",
    "sg:address":"Avda Doctor Solis Pascual, 2",
    "sg:city":"Ubrique",
    "sg:orig_category":"Arquitectos",
    "sg:phone":"+34 956 46 12 37",
    "sg:postcode":"11600",
    "sg:province":"C\u00e1diz",
    "wof:name":"Romero Lora Jose Manuel",
    "wof:placetype":"venue"
},
  "geometry": {"coordinates":[-5.4448170662,36.6770782471],"type":"Point"}
}