{
  "type": "Feature",
  "properties": {
    "addr:full":"Calle de Ramirez De Arellano, 29 Madrid Madrid 28043",
    "addr:housenumber":"29",
    "addr:postcode":"madrid;28043",
    "addr:street":"Calle De Ramirez De Arellano",
    "iso:country":"ES",
    "sg:address":"Calle de Ramirez De Arellano, 29",
    "sg:city":"Madrid",
    "sg:orig_category":"Ingeniero",
    "sg:phone":"+34 915 19 44 94",
    "sg:postcode":"28043",
    "sg:province":"Madrid",
    "wof:name":"Bt Espa\u00d1a Integracion General De Sistemas S.l.",
    "wof:placetype":"venue"
},
  "geometry": {"coordinates":[-3.6573960781,40.4479484558],"type":"Point"}
}