{
  "type": "Feature",
  "properties": {
    "addr:full":"Calle de Manuel Caballero Venzala, 18 Jaen Ja\u00e9n 23009",
    "addr:housenumber":"18;jae\u0301n",
    "addr:postcode":"23009",
    "addr:street":"Calle De Manuel Caballero Venzala",
    "iso:country":"ES",
    "sg:address":"Calle de Manuel Caballero Venzala, 18",
    "sg:city":"Jaen",
    "sg:orig_category":"Ingeniero",
    "sg:phone":"+34 953 29 13 77",
    "sg:postcode":"23009",
    "sg:province":"Ja\u00e9n",
    "wof:name":"Laula Ingenieria S.l.",
    "wof:placetype":"venue"
},
  "geometry": {"coordinates":[-3.7881689072,37.7815055847],"type":"Point"}
}