{
  "type": "Feature",
  "properties": {
    "iso:country":"ES",
    "sg:address":"Calle de Manuel Caballero Venzala, 18",
    "sg:city":"Jaen",
    "sg:orig_category":"Ingeniero",
    "sg:phone":"+34 953 29 13 77",
    "sg:postcode":"23009",
    "sg:province":"Ja\u00e9n",
    "wof:name":"Laula Ingenieria S.l.",
    "wof:placetype":"venue"
},
  "geometry": {"coordinates":[-3.7881689072,37.7815055847],"type":"Point"}
}