{
  "type": "Feature",
  "properties": {
    "iso:country":"ES",
    "sg:address":"Plg. Ind. El Alto, S/n",
    "sg:city":"Brihuega",
    "sg:orig_category":"Puertas Y Portales",
    "sg:phone":"+34 949 28 01 53",
    "sg:postcode":"19400",
    "sg:province":"Guadalajara",
    "wof:name":"Orterga Cepero Tomas",
    "wof:placetype":"venue"
},
  "geometry": {"coordinates":[-2.8832190037,40.7596435547],"type":"Point"}
}