{
  "type": "Feature",
  "properties": {
    "iso:country":"ES",
    "sg:address":"Carrer de Girona, 42",
    "sg:city":"Sant Jaume D'enveja",
    "sg:orig_category":"M\u00c9dicos: Estomatolog\u00cda",
    "sg:phone":"+34 977 46 81 60",
    "sg:postcode":"43877",
    "sg:province":"Tarragona",
    "wof:name":"Manette  Roberto Hugo",
    "wof:placetype":"venue"
},
  "geometry": {"coordinates":[1.2563979626,41.1187362671],"type":"Point"}
}