{
  "type": "Feature",
  "properties": {
    "iso:country":"ES",
    "sg:address":"Calle de Carrera, 42",
    "sg:city":"Antequera",
    "sg:orig_category":"Delegados, Agentes De Tr\u00c1nsito, Auxiliares De Transporte Internacional",
    "sg:phone":"+34 952 84 26 99",
    "sg:postcode":"29200",
    "sg:province":"M\u00e1laga",
    "wof:name":"Romero Perez Luis",
    "wof:placetype":"venue"
},
  "geometry": {"coordinates":[-4.5548014641,37.0199241638],"type":"Point"}
}