{
  "type": "Feature",
  "properties": {
    "iso:country":"ES",
    "sg:address":"Muel Pesquero, S/n",
    "sg:city":"Marin",
    "sg:orig_category":"Pescader\u00cdas (al Por Menor)",
    "sg:phone":"+34 986 83 80 67",
    "sg:postcode":"36900",
    "sg:province":"Pontevedra",
    "wof:name":"Areapesca S.a.",
    "wof:placetype":"venue"
},
  "geometry": {"coordinates":[-8.6875658035,42.3635902405],"type":"Point"}
}