{
  "type": "Feature",
  "properties": {
    "iso:country":"ES",
    "sg:address":"Carrer de Lluis Domenech I Muntaner, 6",
    "sg:city":"Esplugues Llobregat",
    "sg:orig_category":"Agencias Y Asesores De Publicidad",
    "sg:phone":"+34 933 71 37 84",
    "sg:postcode":"08950",
    "sg:province":"Barcelona",
    "wof:name":"Slosem Intermedia S.l.",
    "wof:placetype":"venue"
},
  "geometry": {"coordinates":[2.0920660496,41.380897522],"type":"Point"}
}