{
  "type": "Feature",
  "properties": {
    "addr:full":"Calle de Alemania, 17 Malaga M\u00e1laga 29001",
    "addr:housenumber":"17",
    "addr:postcode":"29001",
    "addr:street":"Calle De Alemania;Ma\u0301Laga",
    "iso:country":"ES",
    "sg:address":"Calle de Alemania, 17",
    "sg:city":"Malaga",
    "sg:orig_category":"M\u00c9dicos: Otorrinolaringolog\u00cda",
    "sg:phone":"+34 952 22 61 44",
    "sg:postcode":"29001",
    "sg:province":"M\u00e1laga",
    "wof:name":"Iba\u00f1ez Roa Nicolas",
    "wof:placetype":"venue"
},
  "geometry": {"coordinates":[-4.4249024391,36.7136688232],"type":"Point"}
}