{
  "type": "Feature",
  "properties": {
    "addr:full":"Calle de Gordoniz, 32 Bilbao Vizcaya 48012",
    "addr:housenumber":"32",
    "addr:postcode":"48012",
    "addr:street":"Calle De Gordoniz",
    "iso:country":"ES",
    "sg:address":"Calle de Gordoniz, 32",
    "sg:city":"Bilbao",
    "sg:orig_category":"Agencias Y Asesores De Publicidad",
    "sg:phone":"+34 944 43 27 30",
    "sg:postcode":"48012",
    "sg:province":"Vizcaya",
    "sg:website":"www.grupodexa.com",
    "wof:name":"Grupo Dexa Publicidad S.l.",
    "wof:placetype":"venue"
},
  "geometry": {"coordinates":[-2.9427063465,43.2563858032],"type":"Point"}
}