{
  "type": "Feature",
  "properties": {
    "addr:full":"Calle de Garcia Lorca, 12 Canena Ja\u00e9n 23420",
    "addr:housenumber":"12",
    "addr:postcode":"23420",
    "addr:street":"Calle De Garcia Lorca",
    "iso:country":"ES",
    "sg:address":"Calle de Garcia Lorca, 12",
    "sg:city":"Canena",
    "sg:orig_category":"Empresas De Electricidad En General",
    "sg:phone":"+34 953 77 04 59",
    "sg:postcode":"23420",
    "sg:province":"Ja\u00e9n",
    "wof:name":"Electra La Loma S.l.",
    "wof:placetype":"venue"
},
  "geometry": {"coordinates":[-3.482738018,38.0489616394],"type":"Point"}
}