{
  "type": "Feature",
  "properties": {
    "addr:full":"Carrer de General O'donnell, 20 S. Boi Llobregat Barcelona 08830",
    "addr:housenumber":"20",
    "addr:postcode":"08830",
    "addr:street":"Carrer De General O'Donnell",
    "iso:country":"ES",
    "sg:address":"Carrer de General O'donnell, 20",
    "sg:city":"S. Boi Llobregat",
    "sg:orig_category":"Art\u00cdculos De Decoraci\u00d3n (fabricaci\u00d3n Y Al Por Mayor)",
    "sg:phone":"+34 936 30 16 42",
    "sg:postcode":"08830",
    "sg:province":"Barcelona",
    "wof:name":"Gonzalez Lopez Domingo",
    "wof:placetype":"venue"
},
  "geometry": {"coordinates":[2.0415408611,41.346988678],"type":"Point"}
}