{
  "type": "Feature",
  "properties": {
    "iso:country":"ES",
    "sg:address":"Calle de Fernan Gonzalez, 4",
    "sg:city":"Roa",
    "sg:orig_category":"Molduras, Junquillos, Listones Y Molduras Perforadas",
    "sg:phone":"+34 947 54 12 40",
    "sg:postcode":"09300",
    "sg:province":"Burgos",
    "wof:name":"Pascual Fernandez Fernando",
    "wof:placetype":"venue"
},
  "geometry": {"coordinates":[-3.9314389229,41.6962547302],"type":"Point"}
}