{
  "type": "Feature",
  "properties": {
    "addr:full":"Calle de Alameda, S/n Alcazar S. Juan Ciudad Real 13600",
    "addr:housenumber":"s / n",
    "addr:postcode":"13600",
    "addr:street":"Calle De Alameda;Alcazar S. Juan Ciudad Real",
    "iso:country":"ES",
    "sg:address":"Calle de Alameda, S/n",
    "sg:city":"Alcazar S. Juan",
    "sg:orig_category":"Promotores Constructores",
    "sg:phone":"+34 926 54 66 08",
    "sg:postcode":"13600",
    "sg:province":"Ciudad Real",
    "wof:name":"Materiales De Construccion Racionero S.l.",
    "wof:placetype":"venue"
},
  "geometry": {"coordinates":[-3.2052278519,39.3785629272],"type":"Point"}
}