{
  "type": "Feature",
  "properties": {
    "iso:country":"ES",
    "sg:address":"Avda Peru, S/n",
    "sg:city":"Trujillo",
    "sg:orig_category":"Molduras, Junquillos, Listones Y Molduras Perforadas",
    "sg:phone":"+34 927 32 21 69",
    "sg:postcode":"10200",
    "sg:province":"C\u00e1ceres",
    "wof:name":"Fernandez Mu\u00f1oz Pablo",
    "wof:placetype":"venue"
},
  "geometry": {"coordinates":[-5.8860888481,39.453704834],"type":"Point"}
}