{
  "type": "Feature",
  "properties": {
    "iso:country":"ES",
    "sg:address":"Calle de Andevalo, 5",
    "sg:city":"Madrid",
    "sg:orig_category":"Perfumer\u00cda (al Por Menor)",
    "sg:phone":"+34 917 85 20 18",
    "sg:postcode":"28053",
    "sg:province":"Madrid",
    "wof:name":"Diaz Cano Maria Jesus",
    "wof:placetype":"venue"
},
  "geometry": {"coordinates":[-3.6687777042,40.3749465942],"type":"Point"}
}