{
  "type": "Feature",
  "properties": {
    "iso:country":"ES",
    "sg:address":"Avda Maisonnave, 9",
    "sg:city":"Alacant",
    "sg:orig_category":"Creaci\u00d3n De Sitios, Hosting Internet",
    "sg:phone":"+34 965 12 26 92",
    "sg:postcode":"03003",
    "sg:province":"Alicante",
    "sg:website":"www.alac.es",
    "wof:name":"Virtual Affairs S.l.",
    "wof:placetype":"venue"
},
  "geometry": {"coordinates":[-0.4896180034,38.3434295654],"type":"Point"}
}