{
  "type": "Feature",
  "properties": {
    "iso:country":"ES",
    "sg:address":"Pase Quince De Mayo, 18",
    "sg:city":"Madrid",
    "sg:orig_category":"Molduras, Junquillos, Listones Y Molduras Perforadas",
    "sg:phone":"+34 914 69 15 86",
    "sg:postcode":"28019",
    "sg:province":"Madrid",
    "wof:name":"Gallego Gil Jose Luis",
    "wof:placetype":"venue"
},
  "geometry": {"coordinates":[-3.7187728882,40.3981018066],"type":"Point"}
}