{
  "type": "Feature",
  "properties": {
    "iso:country":"ES",
    "sg:address":"Avda Franco, 17",
    "sg:city":"Melide",
    "sg:orig_category":"\u00d3ptica: Instrumentos (fabricaci\u00d3n)",
    "sg:phone":"+34 981 50 54 67",
    "sg:postcode":"15800",
    "sg:province":"La Coru\u00f1a",
    "wof:name":"Gonzalez Salgado Marta",
    "wof:placetype":"venue"
},
  "geometry": {"coordinates":[-8.0155601501,42.9146118164],"type":"Point"}
}