{
  "type": "Feature",
  "properties": {
    "addr:full":"Calle de Gomez Cortina, 8 San Nicolas Murcia 30005",
    "addr:housenumber":"8",
    "addr:postcode":"30005",
    "addr:street":"Calle De Gomez Cortina",
    "iso:country":"ES",
    "sg:address":"Calle de Gomez Cortina, 8",
    "sg:city":"San Nicolas",
    "sg:orig_category":"Promotores Constructores",
    "sg:phone":"+34 968 28 03 20",
    "sg:postcode":"30005",
    "sg:province":"Murcia",
    "wof:name":"Invercosta 2000 S.l.",
    "wof:placetype":"venue"
},
  "geometry": {"coordinates":[-1.1361750364,37.9872817993],"type":"Point"}
}