{
  "type": "Feature",
  "properties": {
    "addr:full":"Mar Blau (urb Colls), 24 S. Pere Ribes Barcelona 08810",
    "addr:housenumber":"24",
    "addr:postcode":"08810",
    "addr:street":"Urb Colls;S. Pere Ribes Barcelona",
    "iso:country":"ES",
    "sg:address":"Mar Blau (urb Colls), 24",
    "sg:city":"S. Pere Ribes",
    "sg:orig_category":"Servicios Gsm",
    "sg:phone":"+34 938 93 21 24",
    "sg:postcode":"08810",
    "sg:province":"Barcelona",
    "wof:name":"Sellers Telecomunicacions S.l.",
    "wof:placetype":"venue"
},
  "geometry": {"coordinates":[1.7786979675,41.2564849854],"type":"Point"}
}