{
  "type": "Feature",
  "properties": {
    "addr:full":"Calle de Soledad, 27 Molina Guadalajara 19300",
    "addr:housenumber":"27",
    "addr:postcode":"19300",
    "addr:street":"Calle De Soledad",
    "iso:country":"ES",
    "sg:address":"Calle de Soledad, 27",
    "sg:city":"Molina",
    "sg:orig_category":"Mec\u00c1nico Del Autom\u00d3vil",
    "sg:phone":"+34 949 83 01 78",
    "sg:postcode":"19300",
    "sg:province":"Guadalajara",
    "wof:name":"Guillen Ruiz Jose Miguel",
    "wof:placetype":"venue"
},
  "geometry": {"coordinates":[-1.891528964,40.8481903076],"type":"Point"}
}