{
  "type": "Feature",
  "properties": {
    "iso:country":"ES",
    "sg:address":"Calle de Joaquin Maria Lopez, 23",
    "sg:city":"Madrid",
    "sg:orig_category":"Edici\u00d3n De Diarios, Revistas, Boletines",
    "sg:phone":"+34 915 43 04 31",
    "sg:postcode":"28015",
    "sg:province":"Madrid",
    "wof:name":"Taller De Publicaciones S.l.laboral",
    "wof:placetype":"venue"
},
  "geometry": {"coordinates":[-3.7118349075,40.4374542236],"type":"Point"}
}