{
  "type": "Feature",
  "properties": {
    "addr:full":"Carrer de Calvari, 57 Ulldecona Tarragona 43550",
    "addr:postcode":"43550",
    "addr:street":"Carrer De Calvari 57",
    "iso:country":"ES",
    "sg:address":"Carrer de Calvari, 57",
    "sg:city":"Ulldecona",
    "sg:orig_category":"Molduras, Junquillos, Listones Y Molduras Perforadas",
    "sg:phone":"+34 977 57 32 18",
    "sg:postcode":"43550",
    "sg:province":"Tarragona",
    "wof:name":"Sans Guarch Pere",
    "wof:placetype":"venue"
},
  "geometry": {"coordinates":[0.4438030124,40.5966186523],"type":"Point"}
}