{
  "type": "Feature",
  "properties": {
    "addr:full":"Avda De Bara\u00f1ain, 52 Iru\u00f1a Navarra 31008",
    "addr:housenumber":"52",
    "addr:postcode":"31008",
    "addr:street":"Avda De Baran\u0303Ain",
    "iso:country":"ES",
    "sg:address":"Avda De Bara\u00f1ain, 52",
    "sg:city":"Iru\u00f1a",
    "sg:orig_category":"Empresas De Portes Y Mensajer\u00cda",
    "sg:phone":"+34 948 17 79 37",
    "sg:postcode":"31008",
    "sg:province":"Navarra",
    "sg:website":"www.mrw.es",
    "wof:name":"Mensajeros Pamplona S.l.",
    "wof:placetype":"venue"
},
  "geometry": {"coordinates":[-1.6647906303,42.8095054626],"type":"Point"}
}