{
  "type": "Feature",
  "properties": {
    "iso:country":"ES",
    "sg:address":"Carr Santa Caterina, 94",
    "sg:city":"Torroella Montgri",
    "sg:orig_category":"Fabricaci\u00d3n, Importaci\u00d3n De L\u00c1mparas Y Bombillas",
    "sg:phone":"+34 972 75 85 31",
    "sg:postcode":"17257",
    "sg:province":"Girona",
    "wof:name":"Bruguera Mato Juan",
    "wof:placetype":"venue"
},
  "geometry": {"coordinates":[3.1331520081,42.0438728333],"type":"Point"}
}