{
  "type": "Feature",
  "properties": {
    "iso:country":"ES",
    "sg:address":"Carrer de Sant Josep, 8",
    "sg:city":"Roses",
    "sg:orig_category":"Art\u00cdculos De Regalo (al Por Menor)",
    "sg:phone":"+34 972 25 77 53",
    "sg:postcode":"17480",
    "sg:province":"Girona",
    "wof:name":"Salgado Fari\u00f1as Maria Jesus",
    "wof:placetype":"venue"
},
  "geometry": {"coordinates":[3.1754939556,42.2631378174],"type":"Point"}
}