{
  "type": "Feature",
  "properties": {
    "iso:country":"ES",
    "sg:address":"Avda Ruzafa, S/n",
    "sg:city":"Benidorm",
    "sg:orig_category":"Procuradores",
    "sg:phone":"+34 965 86 31 60",
    "sg:postcode":"03500",
    "sg:province":"Alicante",
    "wof:name":"Lloret Sebastian Jaime",
    "wof:placetype":"venue"
},
  "geometry": {"coordinates":[-0.1305190027,38.5406188965],"type":"Point"}
}