{
  "type": "Feature",
  "properties": {
    "addr:full":"Via Augusta, 124 Barcelona Barcelona 08006",
    "addr:housenumber":"124",
    "addr:postcode":"08006",
    "addr:street":"Via Augusta",
    "iso:country":"ES",
    "sg:address":"Via Augusta, 124",
    "sg:city":"Barcelona",
    "sg:orig_category":"M\u00c9dicos: Estomatolog\u00cda",
    "sg:phone":"+34 934 14 62 65",
    "sg:postcode":"08006",
    "sg:province":"Barcelona",
    "wof:name":"Chimenos Kustner Eduardo",
    "wof:placetype":"venue"
},
  "geometry": {"coordinates":[2.1458890438,41.4004936218],"type":"Point"}
}