{
  "type": "Feature",
  "properties": {
    "iso:country":"ES",
    "sg:address":"Calle de Asturias, 11",
    "sg:city":"Oviedo",
    "sg:orig_category":"Farmacias",
    "sg:phone":"+34 985 24 05 00",
    "sg:postcode":"33004",
    "sg:province":"Asturias",
    "wof:name":"Somoano Ojanguren Arturo",
    "wof:placetype":"venue"
},
  "geometry": {"coordinates":[-5.8544373512,43.3626098633],"type":"Point"}
}