{
  "type": "Feature",
  "properties": {
    "addr:full":"Ptge Massorra, 22 S. Andreu Llavaneres Barcelona 08392",
    "addr:housenumber":"22",
    "addr:postcode":"08392",
    "addr:street":"Ptge Massorra;S. Andreu Llavaneres Barcelona",
    "iso:country":"ES",
    "sg:address":"Ptge Massorra, 22",
    "sg:city":"S. Andreu Llavaneres",
    "sg:orig_category":"Semiller\u00cdas",
    "sg:phone":"+34 937 92 60 73",
    "sg:postcode":"08392",
    "sg:province":"Barcelona",
    "wof:name":"Cultivos Casas Mas S.c.p.",
    "wof:placetype":"venue"
},
  "geometry": {"coordinates":[2.4849700928,41.5697517395],"type":"Point"}
}