{
  "type": "Feature",
  "properties": {
    "iso:country":"ES",
    "sg:address":"Calle de Venegas, 15",
    "sg:city":"Palmas De Gran Canaria",
    "sg:orig_category":"Inform\u00c1tica, Ofim\u00c1tica (estudios, Asesor\u00cda, Ingenier\u00cda, Formaci\u00d3n)",
    "sg:phone":"+34 928 36 19 79",
    "sg:postcode":"35003",
    "sg:province":"Las Palmas",
    "wof:name":"Explhota S.a.",
    "wof:placetype":"venue"
},
  "geometry": {"coordinates":[-15.4173212051,28.1103954315],"type":"Point"}
}