{
  "type": "Feature",
  "properties": {
    "addr:full":"Ctra Villafranco-balboa, Km. 0001,2 Villafranco Guadiana Badajoz 06195",
    "addr:postcode":"06195",
    "addr:street":"Ctra Villafranco-Balboa Km. 0001,2 Villafranco",
    "iso:country":"ES",
    "sg:address":"Ctra Villafranco-balboa, Km. 0001,2",
    "sg:city":"Villafranco Guadiana",
    "sg:orig_category":"Cooperativas Agr\u00cdcolas",
    "sg:phone":"+34 924 24 56 69",
    "sg:postcode":"06195",
    "sg:province":"Badajoz",
    "wof:name":"Asociacion Mesa Del Tomate",
    "wof:placetype":"venue"
},
  "geometry": {"coordinates":[-6.6908564568,38.9296798706],"type":"Point"}
}