{
  "type": "Feature",
  "properties": {
    "iso:country":"ES",
    "sg:address":"Calle de Fisicas, 72",
    "sg:city":"Alcorcon",
    "sg:orig_category":"Decoraci\u00d3n: Instalaci\u00d3n Y Talleres",
    "sg:phone":"+34 916 44 29 86",
    "sg:postcode":"28921",
    "sg:province":"Madrid",
    "wof:name":"Indeco Regero S.l",
    "wof:placetype":"venue"
},
  "geometry": {"coordinates":[-3.8142709732,40.3351097107],"type":"Point"}
}