{
  "type": "Feature",
  "properties": {
    "addr:full":"Calle de Paloma, 2 Pe\u00e7aranda De Bracamonte Salamanca 37300",
    "addr:housenumber":"2",
    "addr:postcode":"37300",
    "addr:street":"Calle De Paloma",
    "iso:country":"ES",
    "sg:address":"Calle de Paloma, 2",
    "sg:city":"Pe\u00e7aranda De Bracamonte",
    "sg:orig_category":"Empresas De Carpinter\u00cda Met\u00c1lica",
    "sg:phone":"+34 923 54 14 49",
    "sg:postcode":"37300",
    "sg:province":"Salamanca",
    "wof:name":"Carpinteria Metalica Hnos. Madrid S.l.",
    "wof:placetype":"venue"
},
  "geometry": {"coordinates":[-5.199985981,40.9037742615],"type":"Point"}
}