{
  "type": "Feature",
  "properties": {
    "addr:full":"Calle de General Ricardos, 104 Madrid Madrid 28019",
    "addr:housenumber":"104",
    "addr:postcode":"28019",
    "addr:street":"Calle De General Ricardos",
    "iso:country":"ES",
    "sg:address":"Calle de General Ricardos, 104",
    "sg:city":"Madrid",
    "sg:orig_category":"Muebles Y Accesorios Para Cocinas Y Cuartos De Ba\u00d1o (al Por Menor)",
    "sg:phone":"+34 914 71 45 71",
    "sg:postcode":"28019",
    "sg:province":"Madrid",
    "wof:name":"Gestion Y Compra S.a.",
    "wof:placetype":"venue"
},
  "geometry": {"coordinates":[-3.7252902985,40.392578125],"type":"Point"}
}