{
  "type": "Feature",
  "properties": {
    "iso:country":"ES",
    "sg:address":"Avda. Jerez, 254",
    "sg:city":"Mijas Costa",
    "sg:orig_category":"Zonas De Acampada, Aparcamiento Para Caravanas",
    "sg:phone":"+34 952 58 75 15",
    "sg:postcode":"29649",
    "sg:province":"M\u00e1laga",
    "wof:name":"Luis Alvarez Fernandez S.l.",
    "wof:placetype":"venue"
},
  "geometry": {"coordinates":[-4.6931939125,36.4994316101],"type":"Point"}
}