{
  "type": "Feature",
  "properties": {
    "iso:country":"ES",
    "sg:address":"Camino Huerta, S/n",
    "sg:city":"Espejon",
    "sg:orig_category":"Centros De Educaci\u00d3n Especial",
    "sg:phone":"+34 975 37 27 34",
    "sg:postcode":"42142",
    "sg:province":"Soria",
    "wof:name":"Cra Pinares Sur",
    "wof:placetype":"venue"
},
  "geometry": {"coordinates":[-3.2571439743,41.8299102783],"type":"Point"}
}