{
  "type": "Feature",
  "properties": {
    "addr:full":"Cruz De Mayo, 21 Chipiona C\u00e1diz 11550",
    "addr:housenumber":"21",
    "addr:postcode":"11550",
    "addr:street":"Cruz;Mayo",
    "iso:country":"ES",
    "sg:address":"Cruz De Mayo, 21",
    "sg:city":"Chipiona",
    "sg:orig_category":"Vinos Y Licores (venta Al Por Menor)",
    "sg:phone":"+34 956 37 44 40",
    "sg:postcode":"11550",
    "sg:province":"C\u00e1diz",
    "wof:name":"Florido Romero Cesar",
    "wof:placetype":"venue"
},
  "geometry": {"coordinates":[-6.4372091293,36.7388801575],"type":"Point"}
}