{
  "type": "Feature",
  "properties": {
    "addr:full":"Carrer de Cami Ral De Valencia, 23 Castelldefels Barcelona 08860",
    "addr:housenumber":"23",
    "addr:postcode":"08860",
    "addr:street":"Carrer De;Ral;Valencia",
    "iso:country":"ES",
    "sg:address":"Carrer de Cami Ral De Valencia, 23",
    "sg:city":"Castelldefels",
    "sg:orig_category":"Aparatos, Material Y Suministros Para Laboratorios",
    "sg:phone":"+34 936 36 02 70",
    "sg:postcode":"08860",
    "sg:province":"Barcelona",
    "wof:name":"Incotecnic Lab-pre S. L.",
    "wof:placetype":"venue"
},
  "geometry": {"coordinates":[1.9803459644,41.2786483765],"type":"Point"}
}