{
  "type": "Feature",
  "properties": {
    "addr:full":"Urb Real Panorama, 140 Rio Real M\u00e1laga 29600",
    "addr:housenumber":"140",
    "addr:postcode":"29600",
    "addr:street":"Urb;Panorama;Rio Real Ma\u0301Laga",
    "iso:country":"ES",
    "sg:address":"Urb Real Panorama, 140",
    "sg:city":"Rio Real",
    "sg:orig_category":"Bisuter\u00cda, Joyer\u00cda, Relojer\u00cda (al Por Menor)",
    "sg:phone":"+34 952 82 12 69",
    "sg:postcode":"29600",
    "sg:province":"M\u00e1laga",
    "wof:name":"Gebrus S.l.",
    "wof:placetype":"venue"
},
  "geometry": {"coordinates":[-4.4201598167,36.7183189392],"type":"Point"}
}