{
  "type": "Feature",
  "properties": {
    "iso:country":"ES",
    "sg:address":"Plaz Maestro Granados (del), 5",
    "sg:city":"Alcobendas",
    "sg:orig_category":"Zapatos (al Por Menor)",
    "sg:phone":"+34 916 54 50 73",
    "sg:postcode":"28100",
    "sg:province":"Madrid",
    "wof:name":"Palomar Sanz Rafael",
    "wof:placetype":"venue"
},
  "geometry": {"coordinates":[-3.6444580555,40.5483093262],"type":"Point"}
}