{
  "type": "Feature",
  "properties": {
    "iso:country":"ES",
    "sg:address":"Unic, 1",
    "sg:city":"Torreneral",
    "sg:orig_category":"Agricultores, Agricultores",
    "sg:phone":"+34 973 61 02 61",
    "sg:postcode":"25333",
    "sg:province":"Lleida",
    "wof:name":"Ferrer Fisas Raimon",
    "wof:placetype":"venue"
},
  "geometry": {"coordinates":[0.966899991,41.7238006592],"type":"Point"}
}