{
  "type": "Feature",
  "properties": {
    "iso:country":"ES",
    "sg:address":"Avgd Jaume I, 58",
    "sg:city":"Pedreguer",
    "sg:orig_category":"Agentes Generales De Seguros",
    "sg:phone":"+34 965 76 12 36",
    "sg:postcode":"03750",
    "sg:province":"Alicante",
    "wof:name":"Andres Ferrando Teresa",
    "wof:placetype":"venue"
},
  "geometry": {"coordinates":[0.0352476016,38.7955245972],"type":"Point"}
}