{
  "type": "Feature",
  "properties": {
    "addr:full":"Calle de Escuza Jose Maria, 16 Bilbao Vizcaya 48013",
    "addr:housenumber":"16",
    "addr:postcode":"48013",
    "addr:street":"Calle De Escuza Jose Maria",
    "iso:country":"ES",
    "sg:address":"Calle de Escuza Jose Maria, 16",
    "sg:city":"Bilbao",
    "sg:orig_category":"Deportes Diversos",
    "sg:phone":"+34 944 27 53 45",
    "sg:postcode":"48013",
    "sg:province":"Vizcaya",
    "wof:name":"Federacion Vizcaina De Hipica",
    "wof:placetype":"venue"
},
  "geometry": {"coordinates":[-2.9456601143,43.261505127],"type":"Point"}
}