{
  "type": "Feature",
  "properties": {
    "iso:country":"ES",
    "sg:address":"Praz Bergondo, S/n",
    "sg:city":"Noia",
    "sg:orig_category":"Bebidas",
    "sg:phone":"+34 981 82 00 77",
    "sg:postcode":"15200",
    "sg:province":"A Coru\u00f1a",
    "wof:name":"Vega Lopez Jose Luis",
    "wof:placetype":"venue"
},
  "geometry": {"coordinates":[-8.8883037567,42.788608551],"type":"Point"}
}