{
  "type": "Feature",
  "properties": {
    "addr:full":"Carrer de Barcelona, 7 Mataro Barcelona 08301",
    "addr:housenumber":"7",
    "addr:postcode":"08301",
    "addr:street":"Carrer De Barcelona",
    "iso:country":"ES",
    "sg:address":"Carrer de Barcelona, 7",
    "sg:city":"Mataro",
    "sg:orig_category":"Centros M\u00c9dicos Y Sociales, Dispensarios",
    "sg:phone":"+34 937 96 30 95",
    "sg:postcode":"08301",
    "sg:province":"Barcelona",
    "wof:name":"Barbany Cahiz Montserrat",
    "wof:placetype":"venue"
},
  "geometry": {"coordinates":[2.4452340603,41.5385246277],"type":"Point"}
}