{
  "type": "Feature",
  "properties": {
    "addr:full":"Calle de Comercio, 11 Aguilar Campoo Palencia 34800",
    "addr:housenumber":"11",
    "addr:postcode":"34800",
    "addr:street":"Calle De Comercio",
    "iso:country":"ES",
    "sg:address":"Calle de Comercio, 11",
    "sg:city":"Aguilar Campoo",
    "sg:orig_category":"Zapater\u00cdas",
    "sg:phone":"+34 979 12 60 10",
    "sg:postcode":"34800",
    "sg:province":"Palencia",
    "wof:name":"Zapacampo S.l.",
    "wof:placetype":"venue"
},
  "geometry": {"coordinates":[-4.5311746597,42.0124588013],"type":"Point"}
}