{
  "type": "Feature",
  "properties": {
    "iso:country":"ES",
    "sg:address":"Carr Carme, 11",
    "sg:city":"Girona",
    "sg:orig_category":"Sociedades, Compa\u00d1\u00cdas Aseguradoras",
    "sg:phone":"+34 972 22 22 79",
    "sg:postcode":"17004",
    "sg:province":"Girona",
    "wof:name":"Mussap Mutualidad De Seguros Generales",
    "wof:placetype":"venue"
},
  "geometry": {"coordinates":[2.8244049549,41.9805145264],"type":"Point"}
}