{
  "type": "Feature",
  "properties": {
    "addr:full":"Calle de Hilera, 5 Malaga M\u00e1laga 29007",
    "addr:housenumber":"5",
    "addr:postcode":"29007",
    "addr:street":"Calle De Hilera;Ma\u0301Laga",
    "iso:country":"ES",
    "sg:address":"Calle de Hilera, 5",
    "sg:city":"Malaga",
    "sg:orig_category":"Notarios",
    "sg:phone":"+34 952 07 02 26",
    "sg:postcode":"29007",
    "sg:province":"M\u00e1laga",
    "wof:name":"Olmedo Martinez Miguel",
    "wof:placetype":"venue"
},
  "geometry": {"coordinates":[-4.4301791191,36.7178840637],"type":"Point"}
}