{
  "type": "Feature",
  "properties": {
    "iso:country":"ES",
    "sg:address":"Calle de Ignacio Aznar, 25",
    "sg:city":"Palma",
    "sg:orig_category":"Peluqueros: De Se\u00d1oras",
    "sg:phone":"+34 968 16 55 87",
    "sg:postcode":"30593",
    "sg:province":"Murcia",
    "wof:name":"Sanchez Martinez Isabel",
    "wof:placetype":"venue"
},
  "geometry": {"coordinates":[-0.962247014,37.6913833618],"type":"Point"}
}