{
  "type": "Feature",
  "properties": {
    "addr:full":"Ricardo De La Cierva, 4 Benissa Alicante 03720",
    "addr:housenumber":"4",
    "addr:postcode":"03720",
    "addr:street":"Ricardo;La Cierva",
    "iso:country":"ES",
    "sg:address":"Ricardo De La Cierva, 4",
    "sg:city":"Benissa",
    "sg:orig_category":"Aguas (distribuci\u00d3n, Servicios)",
    "sg:phone":"+34 965 73 23 84",
    "sg:postcode":"03720",
    "sg:province":"Alicante",
    "wof:name":"Astral Pool Espa\u00d1a S.a.u.",
    "wof:placetype":"venue"
},
  "geometry": {"coordinates":[0.0718241036,38.7258644104],"type":"Point"}
}