{
  "type": "Feature",
  "properties": {
    "addr:full":"Calle de Aconcagua (del), 20 Fuenlabrada Madrid 28940",
    "addr:housenumber":"20",
    "addr:postcode":"28940",
    "addr:street":"Calle De Aconcagua Del",
    "iso:country":"ES",
    "sg:address":"Calle de Aconcagua (del), 20",
    "sg:city":"Fuenlabrada",
    "sg:orig_category":"Fabricaci\u00d3n De Sobres, Bolsas Y Fundas",
    "sg:phone":"+34 916 97 44 30",
    "sg:postcode":"28940",
    "sg:province":"Madrid",
    "wof:name":"Estuches Yma S.l.",
    "wof:placetype":"venue"
},
  "geometry": {"coordinates":[-3.8033390045,40.2792434692],"type":"Point"}
}