{
  "type": "Feature",
  "properties": {
    "addr:full":"Avda Navarra, S/n Ezcaray La Rioja 26280",
    "addr:housenumber":"/ n",
    "addr:postcode":"26280",
    "addr:street":"Avda Navarra S;Rioja",
    "iso:country":"ES",
    "sg:address":"Avda Navarra, S/n",
    "sg:city":"Ezcaray",
    "sg:orig_category":"Inmobiliaria (agencias)",
    "sg:phone":"+34 941 42 71 52",
    "sg:postcode":"26280",
    "sg:province":"La Rioja",
    "wof:name":"Valga\u00f1on Perez Consuelo",
    "wof:placetype":"venue"
},
  "geometry": {"coordinates":[-3.0108640194,42.3267860413],"type":"Point"}
}