{
  "type": "Feature",
  "properties": {
    "addr:full":"Calle de Virgen De La Paloma, 7 Torrejon Ardoz Madrid 28850",
    "addr:housenumber":"7",
    "addr:postcode":"28850",
    "addr:street":"Calle De Virgen De La Paloma",
    "iso:country":"ES",
    "sg:address":"Calle de Virgen De La Paloma, 7",
    "sg:city":"Torrejon Ardoz",
    "sg:orig_category":"Centros M\u00c9dicos Y Sociales, Dispensarios",
    "sg:phone":"+34 916 77 35 40",
    "sg:postcode":"28850",
    "sg:province":"Madrid",
    "sg:website":"www.centromedicolapaloma.com",
    "wof:name":"Centro Medico La Paloma",
    "wof:placetype":"venue"
},
  "geometry": {"coordinates":[-3.4770400524,40.459564209],"type":"Point"}
}