{
  "type": "Feature",
  "properties": {
    "addr:full":"Ctra Zorrotza-kastrexana, 4 Bilbao Vizcaya 48013",
    "addr:housenumber":"4",
    "addr:postcode":"48013",
    "addr:street":"Ctra Zorrotza-Kastrexana",
    "iso:country":"ES",
    "sg:address":"Ctra Zorrotza-kastrexana, 4",
    "sg:city":"Bilbao",
    "sg:orig_category":"Carnicer\u00cdas, Carnicer\u00cdas",
    "sg:phone":"+34 944 27 69 48",
    "sg:postcode":"48013",
    "sg:province":"Vizcaya",
    "wof:name":"Lozano Broncano Juan",
    "wof:placetype":"venue"
},
  "geometry": {"coordinates":[-2.971626997,43.2760238647],"type":"Point"}
}