{
  "type": "Feature",
  "properties": {
    "addr:full":"Plaz San Jeronimo Hermosilla, 11 Santo Domingo De La Calzada La Rioja 26250",
    "addr:housenumber":"11",
    "addr:postcode":"26250",
    "addr:street":"Plaz;Hermosilla;Rioja",
    "iso:country":"ES",
    "sg:address":"Plaz San Jeronimo Hermosilla, 11",
    "sg:city":"Santo Domingo De La Calzada",
    "sg:orig_category":"Agentes Generales De Seguros",
    "sg:phone":"+34 941 34 32 02",
    "sg:postcode":"26250",
    "sg:province":"La Rioja",
    "wof:name":"Corcuera Briones Maria Jesus",
    "wof:placetype":"venue"
},
  "geometry": {"coordinates":[-2.9529099464,42.438873291],"type":"Point"}
}