{
  "type": "Feature",
  "properties": {
    "iso:country":"ES",
    "sg:address":"Avda Sancho El Sabio, 10",
    "sg:city":"Donostia-san Sebastian",
    "sg:orig_category":"Farmacias",
    "sg:phone":"+34 943 45 95 43",
    "sg:postcode":"20010",
    "sg:province":"Guip\u00f9zcoa",
    "wof:name":"Goenaga Alvarez Maria Luisa",
    "wof:placetype":"venue"
},
  "geometry": {"coordinates":[-1.9803359509,43.3103179932],"type":"Point"}
}