{
  "type": "Feature",
  "properties": {
    "addr:full":"Carrer de Compositor Pep Ventura, 71 Olot Girona 17800",
    "addr:housenumber":"71",
    "addr:postcode":"17800",
    "addr:street":"Carrer De Compositor Pep Ventura",
    "iso:country":"ES",
    "sg:address":"Carrer de Compositor Pep Ventura, 71",
    "sg:city":"Olot",
    "sg:orig_category":"Comercio De Hierro",
    "sg:phone":"+34 972 27 13 17",
    "sg:postcode":"17800",
    "sg:province":"Girona",
    "wof:name":"Ferros Agusti S.l.",
    "wof:placetype":"venue"
},
  "geometry": {"coordinates":[2.5082058907,42.1925354004],"type":"Point"}
}