{
  "type": "Feature",
  "properties": {
    "addr:full":"Calle de Doctor Mara\u00d1on, 14 Dolores Alicante 03150",
    "addr:housenumber":"14",
    "addr:postcode":"03150",
    "addr:street":"Calle De Doctor Maran\u0303On",
    "iso:country":"ES",
    "sg:address":"Calle de Doctor Mara\u00d1on, 14",
    "sg:city":"Dolores",
    "sg:orig_category":"Maquinaria Para Industrias Diversas",
    "sg:phone":"+34 965 72 64 29",
    "sg:postcode":"03150",
    "sg:province":"Alicante",
    "wof:name":"Roca Martinez Rosario",
    "wof:placetype":"venue"
},
  "geometry": {"coordinates":[-0.7692232132,38.1398773193],"type":"Point"}
}