{
  "type": "Feature",
  "properties": {
    "addr:full":"Calle de Ronda De La Manca, 10 Cordoba C\u00f3rdoba 14010",
    "addr:housenumber":"10",
    "addr:postcode":"14010",
    "addr:street":"Calle De Ronda De La Manca;Co\u0301Rdoba",
    "iso:country":"ES",
    "sg:address":"Calle de Ronda De La Manca, 10",
    "sg:city":"Cordoba",
    "sg:orig_category":"Inform\u00c1tica, Ofim\u00c1tica (estudios, Asesor\u00cda, Ingenier\u00cda, Formaci\u00d3n)",
    "sg:phone":"+34 957 43 90 34",
    "sg:postcode":"14010",
    "sg:province":"C\u00f3rdoba",
    "sg:website":"www.pc-online.net",
    "wof:name":"Pc-online S.l.",
    "wof:placetype":"venue"
},
  "geometry": {"coordinates":[-4.7651147842,37.88722229],"type":"Point"}
}