{
  "type": "Feature",
  "properties": {
    "iso:country":"ES",
    "sg:address":"Carrer de Manresa, 17",
    "sg:city":"Navarcles",
    "sg:orig_category":"Fabricaci\u00d3n De Sobres, Bolsas Y Fundas",
    "sg:phone":"+34 938 31 00 55",
    "sg:postcode":"08270",
    "sg:province":"Barcelona",
    "wof:name":"Feliu Bastardas Maria Antonia",
    "wof:placetype":"venue"
},
  "geometry": {"coordinates":[1.9013880491,41.752658844],"type":"Point"}
}