{
  "type": "Feature",
  "properties": {
    "iso:country":"ES",
    "sg:address":"Calle de Badaia, 21",
    "sg:city":"Vitoria-gasteiz",
    "sg:orig_category":"Moda",
    "sg:phone":"+34 945 14 31 50",
    "sg:postcode":"01012",
    "sg:province":"\u00c1lava",
    "wof:name":"Shen Li S.l.",
    "wof:placetype":"venue"
},
  "geometry": {"coordinates":[-2.6773920059,42.8506240845],"type":"Point"}
}