{
  "type": "Feature",
  "properties": {
    "iso:country":"ES",
    "sg:address":"Avda Joaquin Costa, 2",
    "sg:city":"Caspe",
    "sg:orig_category":"Asesor\u00cda Sobre Comunicaci\u00d3n De Empresas",
    "sg:phone":"+34 976 63 94 70",
    "sg:postcode":"50700",
    "sg:province":"Zaragoza",
    "wof:name":"Aparicio Magallon S.l.",
    "wof:placetype":"venue"
},
  "geometry": {"coordinates":[-0.0445118994,41.2360839844],"type":"Point"}
}