{
  "type": "Feature",
  "properties": {
    "iso:country":"ES",
    "sg:address":"Crro De La Cuesta Redonda, S/n",
    "sg:city":"La Cisterniga",
    "sg:orig_category":"Radiocomunicaciones, Telefon\u00cda M\u00d3vil, Radiomensajer\u00cda: Servicios, Comercializaci\u00d3n",
    "sg:phone":"+34 983 40 13 72",
    "sg:postcode":"47193",
    "sg:province":"Valladolid",
    "wof:name":"Net Radio Medialatina S.a.",
    "wof:placetype":"venue"
},
  "geometry": {"coordinates":[-4.6859240532,41.6106681824],"type":"Point"}
}