{
  "type": "Feature",
  "properties": {
    "iso:country":"ES",
    "sg:address":"Calle de Hamlet, S/n",
    "sg:city":"Malaga",
    "sg:orig_category":"Pistas Y Clases De Tenis",
    "sg:phone":"+34 952 35 05 40",
    "sg:postcode":"29006",
    "sg:province":"M\u00e1laga",
    "wof:name":"Centro Deportivo Ripoll S.c.a",
    "wof:placetype":"venue"
},
  "geometry": {"coordinates":[-4.4656639099,36.7103462219],"type":"Point"}
}