{
  "type": "Feature",
  "properties": {
    "addr:full":"Avda Askatasun Etorbidea, 44 Durango Vizcaya 48200",
    "addr:housenumber":"44",
    "addr:postcode":"48200",
    "addr:street":"Avda Askatasun Etorbidea",
    "iso:country":"ES",
    "sg:address":"Avda Askatasun Etorbidea, 44",
    "sg:city":"Durango",
    "sg:orig_category":"Servicio De Salud",
    "sg:phone":"+34 946 81 10 66",
    "sg:postcode":"48200",
    "sg:province":"Vizcaya",
    "wof:name":"Domingo Azpiri S. A.",
    "wof:placetype":"venue"
},
  "geometry": {"coordinates":[-2.6117420197,43.194644928],"type":"Point"}
}