{
  "type": "Feature",
  "properties": {
    "addr:full":"Calle de San Sebastian, 2 Rozas De Madrid Madrid 28230",
    "addr:housenumber":"2",
    "addr:postcode":"28230",
    "addr:street":"Calle De San Sebastian",
    "iso:country":"ES",
    "sg:address":"Calle de San Sebastian, 2",
    "sg:city":"Rozas De Madrid",
    "sg:orig_category":"Audiovisuales (producci\u00d3n, Edici\u00d3n, Realizaci\u00d3n)",
    "sg:phone":"+34 916 37 15 87",
    "sg:postcode":"28230",
    "sg:province":"Madrid",
    "sg:website":"www.aiceaaudiovisual.com",
    "wof:name":"Aicea Producciones C.a. S.l.",
    "wof:placetype":"venue"
},
  "geometry": {"coordinates":[-4.4606566429,40.2610626221],"type":"Point"}
}