{
  "type": "Feature",
  "properties": {
    "iso:country":"ES",
    "sg:address":"Calle de Dendari Kalea, 29",
    "sg:city":"Lekeitio",
    "sg:orig_category":"Muebles, Minoristas",
    "sg:phone":"+34 946 84 28 93",
    "sg:postcode":"48280",
    "sg:province":"Vizcaya",
    "wof:name":"Josu Xabier Erkiaga Santamaria - Zuhaitza Altzariak",
    "wof:placetype":"venue"
},
  "geometry": {"coordinates":[-2.5049796104,43.3625144958],"type":"Point"}
}