{
  "type": "Feature",
  "properties": {
    "addr:full":"Plaz Mercado, S/n Castro Urdiales Cantabria 39700",
    "addr:postcode":"39700",
    "addr:street":"S / N",
    "iso:country":"ES",
    "sg:address":"Plaz Mercado, S/n",
    "sg:city":"Castro Urdiales",
    "sg:orig_category":"Carnes De Carnicer\u00cda (al Por Mayor)",
    "sg:phone":"+34 942 86 11 57",
    "sg:postcode":"39700",
    "sg:province":"Cantabria",
    "wof:name":"Manuel R.isla S.l.",
    "wof:placetype":"venue"
},
  "geometry": {"coordinates":[-3.2204790115,43.3830718994],"type":"Point"}
}