{
  "type": "Feature",
  "properties": {
    "addr:full":"Avda General Lopez Dominguez, 12 Marbella M\u00e1laga 29600",
    "addr:postcode":"29600",
    "addr:street":"Avda General Lopez Dominguez 12;Ma\u0301Laga",
    "iso:country":"ES",
    "sg:address":"Avda General Lopez Dominguez, 12",
    "sg:city":"Marbella",
    "sg:orig_category":"Librer\u00cdas",
    "sg:phone":"+34 952 77 58 59",
    "sg:postcode":"29600",
    "sg:province":"M\u00e1laga",
    "sg:website":"www.libreriafm.com",
    "wof:name":"Libreria Fm S.l.",
    "wof:placetype":"venue"
},
  "geometry": {"coordinates":[-4.8761219978,36.5112495422],"type":"Point"}
}