{
  "type": "Feature",
  "properties": {
    "addr:full":"Plaz Euskal Herria Plaza, 12 Tolosa Guip\u00f9zcoa 20400",
    "addr:housenumber":"12",
    "addr:postcode":"20400",
    "addr:street":"Euskal Herria Plaza;Guipu\u0300Zcoa",
    "iso:country":"ES",
    "sg:address":"Plaz Euskal Herria Plaza, 12",
    "sg:city":"Tolosa",
    "sg:orig_category":"Abogados",
    "sg:phone":"+34 943 65 41 10",
    "sg:postcode":"20400",
    "sg:province":"Guip\u00f9zcoa",
    "wof:name":"Arrieta Galarraga Maria Isabel",
    "wof:placetype":"venue"
},
  "geometry": {"coordinates":[-2.0742518902,43.1375656128],"type":"Point"}
}