{
  "type": "Feature",
  "properties": {
    "addr:full":"Calle de Constancia, 33 Madrid Madrid 28002",
    "addr:housenumber":"33",
    "addr:postcode":"madrid;28002",
    "addr:street":"Calle De Constancia",
    "iso:country":"ES",
    "sg:address":"Calle de Constancia, 33",
    "sg:city":"Madrid",
    "sg:orig_category":"Promotores Constructores",
    "sg:phone":"+34 915 19 19 24",
    "sg:postcode":"28002",
    "sg:province":"Madrid",
    "wof:name":"Edificaciones Hispanoamericanas Tecnicas S. A.",
    "wof:placetype":"venue"
},
  "geometry": {"coordinates":[-3.6727159023,40.4423522949],"type":"Point"}
}