{
  "type": "Feature",
  "properties": {
    "iso:country":"ES",
    "sg:address":"Avda Gran Via, 7",
    "sg:city":"Vigo",
    "sg:orig_category":"Institutos De Belleza (productos Y Aparatos)",
    "sg:phone":"+34 986 41 07 03",
    "sg:postcode":"36204",
    "sg:province":"Pontevedra",
    "wof:name":"Valverde Acea Maria Carmen De Jesus",
    "wof:placetype":"venue"
},
  "geometry": {"coordinates":[-8.7164468765,42.2338676453],"type":"Point"}
}