{
  "type": "Feature",
  "properties": {
    "iso:country":"ES",
    "sg:address":"Avda Generalisimo, 18",
    "sg:city":"Puerto Cruz",
    "sg:orig_category":"Zapatos (al Por Menor)",
    "sg:phone":"+34 922 38 18 38",
    "sg:postcode":"38400",
    "sg:province":"Santa Cruz De Tenerife",
    "wof:name":"Gonzalez Estevez Ligia",
    "wof:placetype":"venue"
},
  "geometry": {"coordinates":[-16.5447559357,28.4161891937],"type":"Point"}
}