{
  "type": "Feature",
  "properties": {
    "addr:full":"Pg Costa Brava, 69 Poblenou Barcelona 08397",
    "addr:housenumber":"69",
    "addr:postcode":"08397",
    "addr:street":"Pg Costa Brava",
    "iso:country":"ES",
    "sg:address":"Pg Costa Brava, 69",
    "sg:city":"Poblenou",
    "sg:orig_category":"Alimentaci\u00d3n General (al Por Mayor)",
    "sg:phone":"+34 937 66 20 84",
    "sg:postcode":"08397",
    "sg:province":"Barcelona",
    "wof:name":"Diaz Solis Araceli",
    "wof:placetype":"venue"
},
  "geometry": {"coordinates":[2.6741099358,41.6205062866],"type":"Point"}
}