{
  "type": "Feature",
  "properties": {
    "iso:country":"ES",
    "sg:address":"Carrer de Agricultura, 26",
    "sg:city":"Terrassa",
    "sg:orig_category":"M\u00c9dicos: Medicina Del Trabajo",
    "sg:phone":"+34 937 84 50 49",
    "sg:postcode":"08223",
    "sg:province":"Barcelona",
    "wof:name":"Prevengraf S.l.",
    "wof:placetype":"venue"
},
  "geometry": {"coordinates":[2.0224359035,41.5574111938],"type":"Point"}
}