{
  "type": "Feature",
  "properties": {
    "iso:country":"ES",
    "sg:address":"Carr Corregidor Escofet, 24",
    "sg:city":"Lleida",
    "sg:orig_category":"Librer\u00cdas",
    "sg:phone":"+34 973 23 95 72",
    "sg:postcode":"25005",
    "sg:province":"Lleida",
    "wof:name":"Jove Escanuy David",
    "wof:placetype":"venue"
},
  "geometry": {"coordinates":[0.637624979,41.6236877441],"type":"Point"}
}