{
  "type": "Feature",
  "properties": {
    "addr:full":"Avda Juan Carlos I, S/n Costa Ballena C\u00e1diz 11520",
    "addr:housenumber":"s / n",
    "addr:postcode":"11520",
    "addr:street":"Avda Juan Carlos I;Costa Ballena Ca\u0301Diz",
    "iso:country":"ES",
    "sg:address":"Avda Juan Carlos I, S/n",
    "sg:city":"Costa Ballena",
    "sg:orig_category":"Art\u00cdculos De Regalo (al Por Menor)",
    "sg:phone":"+34 956 84 74 60",
    "sg:postcode":"11520",
    "sg:province":"C\u00e1diz",
    "wof:name":"Luque Campos Maria Concepcion",
    "wof:placetype":"venue"
},
  "geometry": {"coordinates":[-6.413643837,36.6910705566],"type":"Point"}
}