{
  "type": "Feature",
  "properties": {
    "iso:country":"ES",
    "sg:address":"Calle de Doctor Garcia Castrillo, 2",
    "sg:city":"Palmas De Gran Canaria",
    "sg:orig_category":"Doctores En Medicina",
    "sg:phone":"+34 928 23 01 42",
    "sg:postcode":"35005",
    "sg:province":"Las Palmas",
    "wof:name":"Caceres Arvelo Manuel",
    "wof:placetype":"venue"
},
  "geometry": {"coordinates":[-15.4318971634,28.1225528717],"type":"Point"}
}