{
  "type": "Feature",
  "properties": {
    "addr:full":"Avda Mirat, 24 Salamanca Salamanca 37005",
    "addr:housenumber":"24",
    "addr:postcode":"37005",
    "addr:street":"Avda Mirat",
    "iso:country":"ES",
    "sg:address":"Avda Mirat, 24",
    "sg:city":"Salamanca",
    "sg:orig_category":"Ambulancias",
    "sg:phone":"+34 923 28 20 43",
    "sg:postcode":"37005",
    "sg:province":"Salamanca",
    "sg:website":"www.emersan.com",
    "wof:name":"Emergencias Sanitarias S.a. U.t.e.",
    "wof:placetype":"venue"
},
  "geometry": {"coordinates":[-5.6610798836,40.9695549011],"type":"Point"}
}