{
  "type": "Feature",
  "properties": {
    "iso:country":"ES",
    "sg:address":"Pase Zorrilla, 74",
    "sg:city":"Valladolid",
    "sg:orig_category":"Inmobiliaria (agencias)",
    "sg:phone":"+34 983 23 60 32",
    "sg:postcode":"47006",
    "sg:province":"Valladolid",
    "wof:name":"Velez Luis Teodoro",
    "wof:placetype":"venue"
},
  "geometry": {"coordinates":[-4.7375302315,41.6416931152],"type":"Point"}
}