{
  "type": "Feature",
  "properties": {
    "addr:full":"Avda Alicante, 37 Agost Alicante 03698",
    "addr:housenumber":"37",
    "addr:postcode":"03698",
    "addr:street":"Avda Alicante",
    "iso:country":"ES",
    "sg:address":"Avda Alicante, 37",
    "sg:city":"Agost",
    "sg:orig_category":"Frutas Y Legumbres Frescas (al Por Mayor)",
    "sg:phone":"+34 965 69 23 56",
    "sg:postcode":"03698",
    "sg:province":"Alicante",
    "wof:name":"Horticolas D'agost S.l.u.",
    "wof:placetype":"venue"
},
  "geometry": {"coordinates":[-0.6375210285,38.4370994568],"type":"Point"}
}