{
  "type": "Feature",
  "properties": {
    "iso:country":"ES",
    "sg:address":"Carr Arnus, S/n",
    "sg:city":"Badalona",
    "sg:orig_category":"Carnicer\u00cdas, Carnicer\u00cdas",
    "sg:phone":"+34 933 84 66 54",
    "sg:postcode":"08911",
    "sg:province":"Barcelona",
    "wof:name":"Carns Fibla S.c.p.",
    "wof:placetype":"venue"
},
  "geometry": {"coordinates":[2.2464900017,41.4490394592],"type":"Point"}
}