{
  "type": "Feature",
  "properties": {
    "addr:full":"Carrer de Onze De Setembre, 32 Mollet Valles Barcelona 08100",
    "addr:housenumber":"32",
    "addr:postcode":"08100",
    "addr:street":"Carrer De Onze De Setembre",
    "iso:country":"ES",
    "sg:address":"Carrer de Onze De Setembre, 32",
    "sg:city":"Mollet Valles",
    "sg:orig_category":"M\u00c9dicos: Estomatolog\u00cda",
    "sg:phone":"+34 935 70 63 73",
    "sg:postcode":"08100",
    "sg:province":"Barcelona",
    "wof:name":"Mauri Martinez Eduard",
    "wof:placetype":"venue"
},
  "geometry": {"coordinates":[2.2166249752,41.5438613892],"type":"Point"}
}