{
  "type": "Feature",
  "properties": {
    "addr:full":"Calle de Padre Rubio, 134 Dalias Almer\u00eda 04750",
    "addr:housenumber":"134",
    "addr:postcode":"04750",
    "addr:street":"Calle De Padre Rubio;Almeri\u0301A",
    "iso:country":"ES",
    "sg:address":"Calle de Padre Rubio, 134",
    "sg:city":"Dalias",
    "sg:orig_category":"Molduras, Junquillos, Listones Y Molduras Perforadas",
    "sg:phone":"+34 950 49 40 83",
    "sg:postcode":"04750",
    "sg:province":"Almer\u00eda",
    "wof:name":"Espinosa Rubio Antonio",
    "wof:placetype":"venue"
},
  "geometry": {"coordinates":[-2.8719789982,36.8285903931],"type":"Point"}
}