{
  "type": "Feature",
  "properties": {
    "iso:country":"ES",
    "sg:address":"Rua Pondal, 1",
    "sg:city":"Sarria",
    "sg:orig_category":"Fabricaci\u00d3n, Venta, Instalaci\u00d3n De R\u00d3tulos, De R\u00d3tulos Luminosos",
    "sg:phone":"+34 982 53 37 32",
    "sg:postcode":"27600",
    "sg:province":"Lugo",
    "wof:name":"Multinformatica S.l.",
    "wof:placetype":"venue"
},
  "geometry": {"coordinates":[-7.4143462181,42.7737312317],"type":"Point"}
}