{
  "type": "Feature",
  "properties": {
    "addr:full":"Ctra. Madrid, 30 Le\u00f3n Le\u00f3n 24005",
    "addr:housenumber":"30",
    "addr:postcode":"24005",
    "addr:street":"Ctra. Madrid;Leo\u0301N",
    "iso:country":"ES",
    "sg:address":"Ctra. Madrid, 30",
    "sg:city":"Le\u00f3n",
    "sg:orig_category":"Peluqueros: De Se\u00d1oras",
    "sg:phone":"+34 987 20 09 95",
    "sg:postcode":"24005",
    "sg:province":"Le\u00f3n",
    "wof:name":"Castro Castro Maria Ricarda",
    "wof:placetype":"venue"
},
  "geometry": {"coordinates":[-5.5522208214,42.5807952881],"type":"Point"}
}