{
  "type": "Feature",
  "properties": {
    "addr:full":"Calle de Menendez Pelayo, 83 Villena Alicante 03400",
    "addr:housenumber":"83",
    "addr:postcode":"03400",
    "addr:street":"Calle De Menendez Pelayo",
    "iso:country":"ES",
    "sg:address":"Calle de Menendez Pelayo, 83",
    "sg:city":"Villena",
    "sg:orig_category":"Colchones (fabricaci\u00d3n, Al Por Mayor, Al Por Menor)",
    "sg:phone":"+34 965 34 84 65",
    "sg:postcode":"03400",
    "sg:province":"Alicante",
    "wof:name":"Hernandez Palau Antonio",
    "wof:placetype":"venue"
},
  "geometry": {"coordinates":[-0.8669940233,38.6351852417],"type":"Point"}
}