{
  "type": "Feature",
  "properties": {
    "iso:country":"ES",
    "sg:address":"Carrer de Muntaner, 107",
    "sg:city":"Barcelona",
    "sg:orig_category":"Poli\u00c9ster",
    "sg:phone":"+34 934 53 30 13",
    "sg:postcode":"08036",
    "sg:province":"Barcelona",
    "sg:website":"www.macla.es",
    "wof:name":"Macla S.a.",
    "wof:placetype":"venue"
},
  "geometry": {"coordinates":[2.1558001041,41.3891487122],"type":"Point"}
}