{
  "type": "Feature",
  "properties": {
    "iso:country":"ES",
    "sg:address":"Calle de Castilla, 67",
    "sg:city":"Santander",
    "sg:orig_category":"Comercio De Mobiliario De Oficina",
    "sg:phone":"+34 942 21 08 47",
    "sg:postcode":"39009",
    "sg:province":"Cantabria",
    "wof:name":"Alberi Fernandez Jose Alfonso",
    "wof:placetype":"venue"
},
  "geometry": {"coordinates":[-3.8177654743,43.4555206299],"type":"Point"}
}