{
  "type": "Feature",
  "properties": {
    "addr:full":"Calle de Pasico, 2 Calasparra Murcia 30420",
    "addr:housenumber":"2",
    "addr:postcode":"30420",
    "addr:street":"Calle De Pasico",
    "iso:country":"ES",
    "sg:address":"Calle de Pasico, 2",
    "sg:city":"Calasparra",
    "sg:orig_category":"Agencias Y Agentes Comerciales, Representantes",
    "sg:phone":"+34 968 74 61 20",
    "sg:postcode":"30420",
    "sg:province":"Murcia",
    "wof:name":"Espin Salinas Jose",
    "wof:placetype":"venue"
},
  "geometry": {"coordinates":[-1.6981409788,38.2315864563],"type":"Point"}
}