{
  "type": "Feature",
  "properties": {
    "addr:full":"Luga Martinete, 13 Martinete La Coru\u00f1a 15008",
    "addr:housenumber":"13",
    "addr:postcode":"15008",
    "addr:street":"Martinete;Martinete La Corun\u0303A",
    "iso:country":"ES",
    "sg:address":"Luga Martinete, 13",
    "sg:city":"Martinete",
    "sg:orig_category":"Electrodom\u00c9sticos (fabricaci\u00d3n, Al Por Mayor)",
    "sg:phone":"+34 981 13 17 00",
    "sg:postcode":"15008",
    "sg:province":"La Coru\u00f1a",
    "wof:name":"Cogad S.l.",
    "wof:placetype":"venue"
},
  "geometry": {"coordinates":[-8.4512443542,43.3434753418],"type":"Point"}
}