{
  "type": "Feature",
  "properties": {
    "iso:country":"ES",
    "sg:address":"Carrer de Cunit, 5",
    "sg:city":"Gava",
    "sg:orig_category":"Administraciones Regionales, Departamentales Y Locales",
    "sg:phone":"+34 900 66 33 88",
    "sg:postcode":"08850",
    "sg:province":"Barcelona",
    "wof:name":"Ajuntament De Gava",
    "wof:placetype":"venue"
},
  "geometry": {"coordinates":[2.0198304653,41.2683601379],"type":"Point"}
}