{
  "type": "Feature",
  "properties": {
    "iso:country":"ES",
    "sg:address":"Calle de Hermanos Machado, S/n",
    "sg:city":"Almeria",
    "sg:orig_category":"Aparcamientos (infraestructuras, Accesorios)",
    "sg:phone":"+34 950 25 94 46",
    "sg:postcode":"04004",
    "sg:province":"Almer\u00eda",
    "wof:name":"Requena Y Martinez S.a.",
    "wof:placetype":"venue"
},
  "geometry": {"coordinates":[-2.4610190392,36.8356513977],"type":"Point"}
}