{
  "type": "Feature",
  "properties": {
    "iso:country":"ES",
    "sg:address":"Calle de Luis Doreste Silva, 5",
    "sg:city":"S.juan",
    "sg:orig_category":"Abogados",
    "sg:phone":"+34 928 68 21 61",
    "sg:postcode":"35200",
    "sg:province":"Las Palmas",
    "wof:name":"Asensio Del Pino Francisco Javier",
    "wof:placetype":"venue"
},
  "geometry": {"coordinates":[-15.4300060272,28.1248226166],"type":"Point"}
}