{
  "type": "Feature",
  "properties": {
    "addr:full":"Calle de Serena, 1 Gargaligas Badajoz 06711",
    "addr:housenumber":"1",
    "addr:postcode":"06711",
    "addr:street":"Calle De Serena",
    "iso:country":"ES",
    "sg:address":"Calle de Serena, 1",
    "sg:city":"Gargaligas",
    "sg:orig_category":"Frutas, Legumbres Frescas Y Tempranas (al Por Menor)",
    "sg:phone":"+34 924 83 29 20",
    "sg:postcode":"06711",
    "sg:province":"Badajoz",
    "wof:name":"Cordero Sierra Santos",
    "wof:placetype":"venue"
},
  "geometry": {"coordinates":[-5.654946804,39.0510940552],"type":"Point"}
}