{
  "type": "Feature",
  "properties": {
    "addr:full":"Calle de General Elizaicin, 31 Alacant Alicante 03013",
    "addr:housenumber":"31",
    "addr:postcode":"03013",
    "addr:street":"Calle De General Elizaicin",
    "iso:country":"ES",
    "sg:address":"Calle de General Elizaicin, 31",
    "sg:city":"Alacant",
    "sg:orig_category":"Peluqueros: De Se\u00d1oras",
    "sg:phone":"+34 965 14 13 69",
    "sg:postcode":"03013",
    "sg:province":"Alicante",
    "wof:name":"Zamorano Zancajo Maria Cristina",
    "wof:placetype":"venue"
},
  "geometry": {"coordinates":[-0.4782088101,38.3541259766],"type":"Point"}
}