{
  "type": "Feature",
  "properties": {
    "iso:country":"ES",
    "sg:address":"Carrobide, 5",
    "sg:city":"Atarrabia",
    "sg:orig_category":"Venta, Instalaci\u00d3n De Cocinas",
    "sg:phone":"+34 948 12 26 38",
    "sg:postcode":"31610",
    "sg:province":"Navarra",
    "wof:name":"Obregon Moral Francisco",
    "wof:placetype":"venue"
},
  "geometry": {"coordinates":[-1.6134810448,42.8330497742],"type":"Point"}
}