{
  "type": "Feature",
  "properties": {
    "iso:country":"ES",
    "sg:address":"Calle de Nardos (de Los), 2",
    "sg:city":"Fuenlabrada",
    "sg:orig_category":"Fotocopias, Reprograf\u00cda",
    "sg:phone":"+34 916 06 37 35",
    "sg:postcode":"28941",
    "sg:province":"Madrid",
    "wof:name":"Perez Punzon Angel",
    "wof:placetype":"venue"
},
  "geometry": {"coordinates":[-3.798705101,40.2870063782],"type":"Point"}
}