{
  "type": "Feature",
  "properties": {
    "addr:full":"Rua Gabriela Nieto Chain, 50 Rabade Lugo 27370",
    "addr:housenumber":"50",
    "addr:postcode":"27370",
    "addr:street":"Rua Gabriela Nieto Chain",
    "iso:country":"ES",
    "sg:address":"Rua Gabriela Nieto Chain, 50",
    "sg:city":"Rabade",
    "sg:orig_category":"Estancos",
    "sg:phone":"+34 982 39 02 08",
    "sg:postcode":"27370",
    "sg:province":"Lugo",
    "wof:name":"Corral Teijeiro Maria Elvira",
    "wof:placetype":"venue"
},
  "geometry": {"coordinates":[-7.6223301888,43.1232719421],"type":"Point"}
}