{
  "type": "Feature",
  "properties": {
    "iso:country":"ES",
    "sg:address":"Calle de Maestro Ramis, 79",
    "sg:city":"Novelda",
    "sg:orig_category":"Inversiones",
    "sg:phone":"+34 965 60 12 78",
    "sg:postcode":"03660",
    "sg:province":"Alicante",
    "wof:name":"Internovel Gest S.l.",
    "wof:placetype":"venue"
},
  "geometry": {"coordinates":[-0.7604020238,38.384601593],"type":"Point"}
}