{
  "type": "Feature",
  "properties": {
    "iso:country":"ES",
    "sg:address":"Carr Arbres (dels), 45",
    "sg:city":"Algemesi",
    "sg:orig_category":"Notarios",
    "sg:phone":"+34 962 42 22 63",
    "sg:postcode":"46680",
    "sg:province":"Valencia",
    "wof:name":"Garcia-granero Colomer Ana Victoria",
    "wof:placetype":"venue"
},
  "geometry": {"coordinates":[-0.4392401874,39.1926345825],"type":"Point"}
}