{
  "type": "Feature",
  "properties": {
    "addr:full":"Pl Cuba, 18 Mataro Barcelona 08302",
    "addr:housenumber":"18",
    "addr:postcode":"08302",
    "addr:street":"Pl Cuba",
    "iso:country":"ES",
    "sg:address":"Pl Cuba, 18",
    "sg:city":"Mataro",
    "sg:orig_category":"Sindicatos De Trabajadores",
    "sg:phone":"+34 937 90 90 34",
    "sg:postcode":"08302",
    "sg:province":"Barcelona",
    "wof:name":"Confederacio General Del Treball De Catalunya",
    "wof:placetype":"venue"
},
  "geometry": {"coordinates":[2.4410560131,41.5373802185],"type":"Point"}
}