{
  "type": "Feature",
  "properties": {
    "addr:full":"Pque Erreniega Parkea, 59 Zizur Mayor Navarra 31180",
    "addr:housenumber":"59",
    "addr:postcode":"31180",
    "addr:street":"Parkea",
    "iso:country":"ES",
    "sg:address":"Pque Erreniega Parkea, 59",
    "sg:city":"Zizur Mayor",
    "sg:orig_category":"Grafistas",
    "sg:phone":"+34 948 18 62 25",
    "sg:postcode":"31180",
    "sg:province":"Navarra",
    "wof:name":"Perez Lizaso Rafael",
    "wof:placetype":"venue"
},
  "geometry": {"coordinates":[-1.6888610125,42.7848129272],"type":"Point"}
}