{
  "type": "Feature",
  "properties": {
    "addr:full":"Ctra Cabo La Nao Pla, 65 Javea Alicante 03730",
    "addr:housenumber":"65",
    "addr:postcode":"03730",
    "addr:street":"Ctra Cabo La Nao Pla",
    "iso:country":"ES",
    "sg:address":"Ctra Cabo La Nao Pla, 65",
    "sg:city":"Javea",
    "sg:orig_category":"Inmobiliaria (agencias)",
    "sg:phone":"+34 965 77 05 25",
    "sg:postcode":"03730",
    "sg:province":"Alicante",
    "wof:name":"Valuvillas S.l.",
    "wof:placetype":"venue"
},
  "geometry": {"coordinates":[0.1570300013,38.7885093689],"type":"Point"}
}