{
  "type": "Feature",
  "properties": {
    "iso:country":"ES",
    "sg:address":"Avda Albufera, 93",
    "sg:city":"Madrid",
    "sg:orig_category":"\u00d3ptica: Instrumentos (fabricaci\u00d3n)",
    "sg:phone":"+34 913 28 31 21",
    "sg:postcode":"28038",
    "sg:province":"Madrid",
    "wof:name":"Martin Lopez Pablo",
    "wof:placetype":"venue"
},
  "geometry": {"coordinates":[-3.6613020897,40.3943214417],"type":"Point"}
}