{
  "type": "Feature",
  "properties": {
    "addr:full":"Trva Ronda, 8 Madrid Madrid 28022",
    "addr:housenumber":"8",
    "addr:postcode":"madrid;28022",
    "addr:street":"Trva Ronda",
    "iso:country":"ES",
    "sg:address":"Trva Ronda, 8",
    "sg:city":"Madrid",
    "sg:orig_category":"Zapatos (al Por Menor)",
    "sg:phone":"+34 913 06 25 93",
    "sg:postcode":"28022",
    "sg:province":"Madrid",
    "wof:name":"Zapatos Ruth Arcos S.l.",
    "wof:placetype":"venue"
},
  "geometry": {"coordinates":[-3.5863313675,40.4419937134],"type":"Point"}
}