{
  "type": "Feature",
  "properties": {
    "addr:full":"Calle de Camarena, 107 Madrid Madrid 28047",
    "addr:housenumber":"107",
    "addr:postcode":"28047",
    "addr:street":"Calle De Camarena",
    "iso:country":"ES",
    "sg:address":"Calle de Camarena, 107",
    "sg:city":"Madrid",
    "sg:orig_category":"Cervecer\u00cdas",
    "sg:phone":"+34 917 17 00 07",
    "sg:postcode":"28047",
    "sg:province":"Madrid",
    "wof:name":"Cortijo Martinez Josefa",
    "wof:placetype":"venue"
},
  "geometry": {"coordinates":[-3.7556400299,40.3929405212],"type":"Point"}
}