{
  "type": "Feature",
  "properties": {
    "addr:full":"Iberre Edificio 1, 1 Sondika Vizcaya 48150",
    "addr:housenumber":"1",
    "addr:postcode":"48150",
    "iso:country":"ES",
    "sg:address":"Iberre Edificio 1, 1",
    "sg:city":"Sondika",
    "sg:orig_category":"Puertas Y Portales",
    "sg:phone":"+34 944 06 05 36",
    "sg:postcode":"48150",
    "sg:province":"Vizcaya",
    "wof:name":"Javier Olcoz Gurruchaga",
    "wof:placetype":"venue"
},
  "geometry": {"coordinates":[-2.937153101,43.2957115173],"type":"Point"}
}