{
  "type": "Feature",
  "properties": {
    "addr:full":"C\u00d1ad De La Vizana, 90 Benavente Zamora 49600",
    "addr:housenumber":"90",
    "addr:postcode":"49600",
    "iso:country":"ES",
    "sg:address":"C\u00d1ad De La Vizana, 90",
    "sg:city":"Benavente",
    "sg:orig_category":"Reparaci\u00d3n Y Restauraci\u00d3n De Objetos Diversos",
    "sg:phone":"+34 980 63 73 73",
    "sg:postcode":"49600",
    "sg:province":"Zamora",
    "wof:name":"Hernando Figuera Angel",
    "wof:placetype":"venue"
},
  "geometry": {"coordinates":[-5.6843042374,42.0074653625],"type":"Point"}
}