{
  "type": "Feature",
  "properties": {
    "addr:full":"Calle de Luis Velasco, 29 Playa De Arinaga Las Palmas 35118",
    "addr:housenumber":"29",
    "addr:postcode":"35118",
    "addr:street":"Calle De Luis Velasco",
    "iso:country":"ES",
    "sg:address":"Calle de Luis Velasco, 29",
    "sg:city":"Playa De Arinaga",
    "sg:orig_category":"Centros Comerciales Y Grandes Tiendas",
    "sg:phone":"+34 928 18 09 14",
    "sg:postcode":"35118",
    "sg:province":"Las Palmas",
    "wof:name":"Sistelcom-telemensaje S.a.",
    "wof:placetype":"venue"
},
  "geometry": {"coordinates":[-15.3943252563,27.8576850891],"type":"Point"}
}