{
  "type": "Feature",
  "properties": {
    "addr:full":"Calle de Rosario, 9 Sevilla Sevilla 41001",
    "addr:housenumber":"9",
    "addr:postcode":"41001",
    "addr:street":"Calle De Rosario",
    "iso:country":"ES",
    "sg:address":"Calle de Rosario, 9",
    "sg:city":"Sevilla",
    "sg:orig_category":"Estilistas Y Estudios De Estilo De Corte Y Confecci\u00d3n",
    "sg:phone":"+34 954 56 17 11",
    "sg:postcode":"41001",
    "sg:province":"Sevilla",
    "wof:name":"Jonoru S.l.",
    "wof:placetype":"venue"
},
  "geometry": {"coordinates":[-5.9961738586,37.3899497986],"type":"Point"}
}