{
  "type": "Feature",
  "properties": {
    "iso:country":"ES",
    "sg:address":"Plaz Primo De Rivera, 1",
    "sg:city":"Calatayud",
    "sg:orig_category":"Asesor\u00cda De Formaci\u00d3n Y Gesti\u00d3n De Personal",
    "sg:phone":"+34 976 88 20 85",
    "sg:postcode":"50300",
    "sg:province":"Zaragoza",
    "wof:name":"Centro De Calculo Calatayud S. L.",
    "wof:placetype":"venue"
},
  "geometry": {"coordinates":[-1.6424759626,41.3522186279],"type":"Point"}
}