{
  "type": "Feature",
  "properties": {
    "addr:full":"Avda Playas Del Duque, S/n Nueva Andalucia M\u00e1laga 29660",
    "addr:housenumber":"s / n",
    "addr:postcode":"29660",
    "addr:street":"Avda Playas Del Duque;Ma\u0301Laga",
    "iso:country":"ES",
    "sg:address":"Avda Playas Del Duque, S/n",
    "sg:city":"Nueva Andalucia",
    "sg:orig_category":"Ingeniero",
    "sg:phone":"+34 952 81 76 19",
    "sg:postcode":"29660",
    "sg:province":"M\u00e1laga",
    "wof:name":"Uricma Consulting Sl",
    "wof:placetype":"venue"
},
  "geometry": {"coordinates":[-4.9572491646,36.4902381897],"type":"Point"}
}