{
  "type": "Feature",
  "properties": {
    "addr:full":"Calle de General Casta\u00d1os, 33 Portugalete Vizcaya 48920",
    "addr:housenumber":"33",
    "addr:postcode":"48920",
    "addr:street":"Calle De General Castan\u0303Os",
    "iso:country":"ES",
    "sg:address":"Calle de General Casta\u00d1os, 33",
    "sg:city":"Portugalete",
    "sg:orig_category":"\u00d3ptica: Instrumentos (fabricaci\u00d3n)",
    "sg:phone":"+34 944 83 63 01",
    "sg:postcode":"48920",
    "sg:province":"Vizcaya",
    "wof:name":"Ignacio Elias Perez Bego\u00f1a Beitia Gorriaran C.b",
    "wof:placetype":"venue"
},
  "geometry": {"coordinates":[-3.020526886,43.3205986023],"type":"Point"}
}