{
  "type": "Feature",
  "properties": {
    "addr:full":"Calle de Rio Sella, 1 Mieres Asturias 33600",
    "addr:housenumber":"1",
    "addr:postcode":"33600",
    "addr:street":"Calle De Rio Sella",
    "iso:country":"ES",
    "sg:address":"Calle de Rio Sella, 1",
    "sg:city":"Mieres",
    "sg:classifiers":[
        {
            "category":"Personal",
            "subcategory":"Barber",
            "type":"Services"
        }
    ],
    "sg:phone":"+34 985 46 14 21",
    "sg:postcode":"33600",
    "sg:province":"Asturias",
    "sg:tags":[
        "caballeros",
        "de",
        "peluqueros"
    ],
    "wof:name":"Gonzalez Suarez Jose Ignacio",
    "wof:placetype":"venue"
},
  "geometry": {"coordinates":[-5.7783927917,43.2493286133],"type":"Point"}
}