{
  "type": "Feature",
  "properties": {
    "addr:full":"Carrer de Wagner, 13 Rubi Barcelona 08191",
    "addr:housenumber":"13",
    "addr:postcode":"08191",
    "addr:street":"Carrer De Wagner",
    "iso:country":"ES",
    "sg:address":"Carrer de Wagner, 13",
    "sg:city":"Rubi",
    "sg:classifiers":[
        {
            "category":"Building & Trades",
            "subcategory":"Construction",
            "type":"Services"
        }
    ],
    "sg:phone":"+34 936 99 27 37",
    "sg:postcode":"08191",
    "sg:province":"Barcelona",
    "sg:tags":[
        "calefacci\u00d3n",
        "central",
        "para",
        "de",
        "fabricaci\u00d3n",
        "caldera"
    ],
    "wof:name":"Saumell Verges Eusebio",
    "wof:placetype":"venue"
},
  "geometry": {"coordinates":[2.0243859291,41.4697189331],"type":"Point"}
}