{
  "type": "Feature",
  "properties": {
    "iso:country":"ES",
    "sg:address":"Pg Maragall, 142",
    "sg:city":"Barcelona",
    "sg:orig_category":"Lencer\u00cda Femenina, Corseter\u00cda, Trajes De Ba\u00d1o (al Por Menor)",
    "sg:phone":"+34 934 08 07 18",
    "sg:postcode":"08027",
    "sg:province":"Barcelona",
    "wof:name":"Navarro Rubio Antonia",
    "wof:placetype":"venue"
},
  "geometry": {"coordinates":[2.1786329746,41.422908783],"type":"Point"}
}