{
  "type": "Feature",
  "properties": {
    "iso:country":"ES",
    "sg:address":"Calle de Arganzuela, 18",
    "sg:city":"Madrid",
    "sg:orig_category":"Cursos Particulares, Asistencia Escolar",
    "sg:phone":"+34 913 65 56 48",
    "sg:postcode":"28005",
    "sg:province":"Madrid",
    "wof:name":"Ramudo Crist Mariana",
    "wof:placetype":"venue"
},
  "geometry": {"coordinates":[-3.7096858025,40.4077224731],"type":"Point"}
}