{
  "type": "Feature",
  "properties": {
    "iso:country":"ES",
    "sg:address":"Av Pere Matutes Noguera, 24",
    "sg:city":"Eivissa",
    "sg:orig_category":"Electrodom\u00c9sticos (al Por Menor)",
    "sg:phone":"+34 971 30 24 82",
    "sg:postcode":"07800",
    "sg:province":"Islas Baleares",
    "wof:name":"Riera Planells Vicente",
    "wof:placetype":"venue"
},
  "geometry": {"coordinates":[1.4191689491,38.9026298523],"type":"Point"}
}