{
  "type": "Feature",
  "properties": {
    "iso:country":"ES",
    "sg:address":"Calle de Triunfo, 2",
    "sg:city":"Donostia-san Sebastian",
    "sg:orig_category":"Peluquer\u00cdas, Peluquer\u00cda Mixta",
    "sg:phone":"+34 943 46 40 89",
    "sg:postcode":"20007",
    "sg:province":"Guip\u00f9zcoa",
    "wof:name":"Hernandez Garcia Isabel",
    "wof:placetype":"venue"
},
  "geometry": {"coordinates":[-1.9855309725,43.316368103],"type":"Point"}
}