{
  "type": "Feature",
  "properties": {
    "iso:country":"ES",
    "sg:address":"Calle de Mariano Pola, 44",
    "sg:city":"Gijon",
    "sg:orig_category":"Iglesia Cat\u00d3lica",
    "sg:phone":"+34 985 30 16 69",
    "sg:postcode":"33212",
    "sg:province":"Asturias",
    "wof:name":"Compania De Jesus Prov De Castilla Curia Provincial.",
    "wof:placetype":"venue"
},
  "geometry": {"coordinates":[-5.679918766,43.5401496887],"type":"Point"}
}