{
  "type": "Feature",
  "properties": {
    "iso:country":"ES",
    "sg:address":"Ctra Canillas, 140",
    "sg:city":"Madrid",
    "sg:orig_category":"Loter\u00cda Y T\u00d3mbola",
    "sg:phone":"+34 913 81 00 16",
    "sg:postcode":"28043",
    "sg:province":"Madrid",
    "wof:name":"Blanquez Alcalde Francisco Javier",
    "wof:placetype":"venue"
},
  "geometry": {"coordinates":[-3.6391510963,40.4651298523],"type":"Point"}
}