{
  "type": "Feature",
  "properties": {
    "addr:full":"Trva Irmans Martinez, 4 Bande Ourense 32840",
    "addr:housenumber":"4",
    "addr:postcode":"32840",
    "addr:street":"Trva Irmans Martinez",
    "iso:country":"ES",
    "sg:address":"Trva Irmans Martinez, 4",
    "sg:city":"Bande",
    "sg:orig_category":"Confecci\u00d3n (fabricaci\u00d3n, Al Por Mayor)",
    "sg:phone":"+34 988 44 32 55",
    "sg:postcode":"32840",
    "sg:province":"Ourense",
    "wof:name":"Suarez Dominguez Edmundo Amador",
    "wof:placetype":"venue"
},
  "geometry": {"coordinates":[-7.9744958878,42.032497406],"type":"Point"}
}