{
  "type": "Feature",
  "properties": {
    "iso:country":"ES",
    "sg:address":"Carrer de Gran Via De Lluis Companys, 196",
    "sg:city":"Premia Mar",
    "sg:orig_category":"Molduras, Junquillos, Listones Y Molduras Perforadas",
    "sg:phone":"+34 937 52 36 87",
    "sg:postcode":"08330",
    "sg:province":"Barcelona",
    "wof:name":"Zamora Gonzalez Samuel",
    "wof:placetype":"venue"
},
  "geometry": {"coordinates":[2.353110075,41.4906196594],"type":"Point"}
}