{
  "type": "Feature",
  "properties": {
    "addr:full":"Calle de Madrid, 60 Humanes De Madrid Madrid 28970",
    "addr:housenumber":"60",
    "addr:postcode":"28970",
    "addr:street":"Calle De Madrid",
    "iso:country":"ES",
    "sg:address":"Calle de Madrid, 60",
    "sg:city":"Humanes De Madrid",
    "sg:orig_category":"Inmobiliaria (agencias)",
    "sg:phone":"+34 914 98 09 80",
    "sg:postcode":"28970",
    "sg:province":"Madrid",
    "wof:name":"Adosm 2005 S.l.",
    "wof:placetype":"venue"
},
  "geometry": {"coordinates":[-3.8257262707,40.2551765442],"type":"Point"}
}