{
  "type": "Feature",
  "properties": {
    "iso:country":"ES",
    "sg:address":"Calle de Juan Frances Bosca, 5",
    "sg:city":"Malaga",
    "sg:orig_category":"Asociaciones Humanitarias, De Cooperaci\u00d3n, De Acci\u00d3n Social",
    "sg:phone":"+34 952 28 59 54",
    "sg:postcode":"29010",
    "sg:province":"M\u00e1laga",
    "wof:name":"Asociacion De Padres De Ni\u00f1os Y Adultos Autistas",
    "wof:placetype":"venue"
},
  "geometry": {"coordinates":[-4.4655227661,36.7271347046],"type":"Point"}
}