{
  "type": "Feature",
  "properties": {
    "iso:country":"ES",
    "sg:address":"Calle de Ruiz Hernandez, 15",
    "sg:city":"Valladolid",
    "sg:orig_category":"Psic\u00d3logos",
    "sg:phone":"+34 983 39 23 86",
    "sg:postcode":"47002",
    "sg:province":"Valladolid",
    "wof:name":"Perez Montes Alicia",
    "wof:placetype":"venue"
},
  "geometry": {"coordinates":[-4.7197232246,41.6529655457],"type":"Point"}
}