{
  "type": "Feature",
  "properties": {
    "addr:full":"Carrer de Major, 40 Calvia Islas Baleares 07184",
    "addr:housenumber":"40",
    "addr:postcode":"07184",
    "addr:street":"Carrer De Major",
    "iso:country":"ES",
    "sg:address":"Carrer de Major, 40",
    "sg:city":"Calvia",
    "sg:orig_category":"Supermercados Y Hipermercados",
    "sg:phone":"+34 971 67 01 07",
    "sg:postcode":"07184",
    "sg:province":"Islas Baleares",
    "wof:name":"Super Ca Na Bosca S.l.",
    "wof:placetype":"venue"
},
  "geometry": {"coordinates":[2.507297039,39.5661773682],"type":"Point"}
}