{
  "type": "Feature",
  "properties": {
    "iso:country":"ES",
    "sg:address":"Carrer de Girfalc, 8",
    "sg:city":"Son Ferrer",
    "sg:orig_category":"Florister\u00cdas",
    "sg:phone":"+34 971 23 11 54",
    "sg:postcode":"07182",
    "sg:province":"Islas Baleares",
    "wof:name":"Juan Vila Antonio",
    "wof:placetype":"venue"
},
  "geometry": {"coordinates":[2.5056760311,39.4961967468],"type":"Point"}
}