{
  "type": "Feature",
  "properties": {
    "iso:country":"ES",
    "sg:address":"Avda Lisboa, 10",
    "sg:city":"Alcorcon",
    "sg:orig_category":"Ingeniero",
    "sg:phone":"+34 916 19 13 25",
    "sg:postcode":"28924",
    "sg:province":"Madrid",
    "wof:name":"Cuesta Gomez Enrique",
    "wof:placetype":"venue"
},
  "geometry": {"coordinates":[-3.8183729649,40.3534088135],"type":"Point"}
}