{
  "type": "Feature",
  "properties": {
    "iso:country":"ES",
    "sg:address":"Avda Toledo, 23",
    "sg:city":"Torrijos",
    "sg:orig_category":"Bombas De Agua",
    "sg:phone":"+34 925 76 22 70",
    "sg:postcode":"45500",
    "sg:province":"Toledo",
    "wof:name":"Riego Garcia Marcos S.cv.",
    "wof:placetype":"venue"
},
  "geometry": {"coordinates":[-4.2689957619,39.9786338806],"type":"Point"}
}