{
  "type": "Feature",
  "properties": {
    "iso:country":"ES",
    "sg:address":"Calle de Vallehermoso, 52",
    "sg:city":"Madrid",
    "sg:orig_category":"Colchones (fabricaci\u00d3n, Al Por Mayor, Al Por Menor)",
    "sg:phone":"+34 915 93 22 15",
    "sg:postcode":"28015",
    "sg:province":"Madrid",
    "wof:name":"Cuesta De Oro Pedro Luis",
    "wof:placetype":"venue"
},
  "geometry": {"coordinates":[-3.7083570957,40.4357566833],"type":"Point"}
}