{
  "type": "Feature",
  "properties": {
    "addr:full":"Av Barcelona, 228 Terrassa Barcelona 08222",
    "addr:housenumber":"228",
    "addr:postcode":"08222",
    "addr:street":"Av Barcelona",
    "iso:country":"ES",
    "sg:address":"Av Barcelona, 228",
    "sg:city":"Terrassa",
    "sg:orig_category":"Ropa Para Se\u00d1oras (al Por Menor)",
    "sg:phone":"+34 937 31 45 94",
    "sg:postcode":"08222",
    "sg:province":"Barcelona",
    "wof:name":"Castro Montoro Ana Maria",
    "wof:placetype":"venue"
},
  "geometry": {"coordinates":[2.0269830227,41.5668106079],"type":"Point"}
}