{
  "type": "Feature",
  "properties": {
    "addr:full":"Pase Marqueses De Linares, 28 Linares Ja\u00e9n 23700",
    "addr:housenumber":"28",
    "addr:postcode":"23700",
    "addr:street":"Linares;Jae\u0301N",
    "iso:country":"ES",
    "sg:address":"Pase Marqueses De Linares, 28",
    "sg:city":"Linares",
    "sg:orig_category":"Obras Y Organismos Sociales",
    "sg:phone":"+34 953 69 25 05",
    "sg:postcode":"23700",
    "sg:province":"Ja\u00e9n",
    "wof:name":"Patronato Asilo De Ancianos Nuestra Se\u00f1ora De Las Mercedes",
    "wof:placetype":"venue"
},
  "geometry": {"coordinates":[-3.6270730495,38.0877418518],"type":"Point"}
}