{
  "type": "Feature",
  "properties": {
    "iso:country":"ES",
    "sg:address":"Calle de Teresa De Calcuta, S/n",
    "sg:city":"Cordoba",
    "sg:orig_category":"Guarder\u00cdas",
    "sg:phone":"+34 957 27 98 51",
    "sg:postcode":"14011",
    "sg:province":"C\u00f3rdoba",
    "wof:name":"El Lapicero Sociedad Cooperativa Andaluza",
    "wof:placetype":"venue"
},
  "geometry": {"coordinates":[-4.7975687981,37.8948783875],"type":"Point"}
}