{
  "type": "Feature",
  "properties": {
    "addr:full":"Calle de Infantes, 6 San Lorenzo De El Escorial Madrid 28200",
    "addr:housenumber":"6",
    "addr:postcode":"28200",
    "addr:street":"Calle De Infantes",
    "iso:country":"ES",
    "sg:address":"Calle de Infantes, 6",
    "sg:city":"San Lorenzo De El Escorial",
    "sg:orig_category":"Psic\u00d3logos",
    "sg:phone":"+34 918 90 39 89",
    "sg:postcode":"28200",
    "sg:province":"Madrid",
    "wof:name":"Del Pozo Salmeron Angel",
    "wof:placetype":"venue"
},
  "geometry": {"coordinates":[-4.1419649124,40.5925827026],"type":"Point"}
}