{
  "type": "Feature",
  "properties": {
    "addr:full":"Via Augusta, 187 Barcelona Barcelona 08021",
    "addr:housenumber":"187",
    "addr:postcode":"08021",
    "addr:street":"Via Augusta",
    "iso:country":"ES",
    "sg:address":"Via Augusta, 187",
    "sg:city":"Barcelona",
    "sg:orig_category":"Agencias Y Agentes Comerciales, Representantes",
    "sg:phone":"+34 934 14 00 80",
    "sg:postcode":"08021",
    "sg:province":"Barcelona",
    "wof:name":"Xicc Import S.l.",
    "wof:placetype":"venue"
},
  "geometry": {"coordinates":[2.1409509182,41.398021698],"type":"Point"}
}