{
  "type": "Feature",
  "properties": {
    "addr:full":"Avda Sousas (de), 6 Verin Ourense 32600",
    "addr:housenumber":"6",
    "addr:postcode":"32600",
    "addr:street":"Avda Sousas De",
    "iso:country":"ES",
    "sg:address":"Avda Sousas (de), 6",
    "sg:city":"Verin",
    "sg:orig_category":"Contenedores (mercanc\u00cdas)",
    "sg:phone":"+34 988 41 00 38",
    "sg:postcode":"32600",
    "sg:province":"Ourense",
    "wof:name":"Patatas Puga Verin, S.l.",
    "wof:placetype":"venue"
},
  "geometry": {"coordinates":[-7.430521965,41.9407119751],"type":"Point"}
}