{
  "type": "Feature",
  "properties": {
    "addr:full":"Avda Pureza Canelo, 30 Moraleja C\u00e1ceres 10840",
    "addr:housenumber":"30",
    "addr:postcode":"10840",
    "addr:street":"Avda Pureza Canelo;Ca\u0301Ceres",
    "iso:country":"ES",
    "sg:address":"Avda Pureza Canelo, 30",
    "sg:city":"Moraleja",
    "sg:orig_category":"Cajas De Ahorro",
    "sg:phone":"+34 927 14 76 17",
    "sg:postcode":"10840",
    "sg:province":"C\u00e1ceres",
    "wof:name":"Caja De Ahorros Y Monte De Piedad De Cordoba",
    "wof:placetype":"venue"
},
  "geometry": {"coordinates":[-6.655629158,40.0679016113],"type":"Point"}
}