{
  "type": "Feature",
  "properties": {
    "iso:country":"ES",
    "sg:address":"Llamaral, S/n",
    "sg:city":"Fariza",
    "sg:orig_category":"Cerrajer\u00cda, Ferrallista",
    "sg:phone":"+34 980 61 78 00",
    "sg:postcode":"49213",
    "sg:province":"Zamora",
    "wof:name":"Garrido Robles Octavio",
    "wof:placetype":"venue"
},
  "geometry": {"coordinates":[-6.2704591751,41.4201202393],"type":"Point"}
}