{
  "type": "Feature",
  "properties": {
    "iso:country":"ES",
    "sg:address":"Calle de Rueda Lopez, 12",
    "sg:city":"Almeria",
    "sg:orig_category":"Peluqueros: De Se\u00d1oras",
    "sg:phone":"+34 950 23 62 01",
    "sg:postcode":"04004",
    "sg:province":"Almer\u00eda",
    "sg:website":"www.serinves.es / capri",
    "wof:name":"Labordeta Gimeno Fernando",
    "wof:placetype":"venue"
},
  "geometry": {"coordinates":[-2.4624910355,36.8377380371],"type":"Point"}
}