{
  "type": "Feature",
  "properties": {
    "iso:country":"ES",
    "sg:address":"Avda Nuestra Se\u00d1ora De Fatima, 59",
    "sg:city":"Madrid",
    "sg:orig_category":"M\u00c1quinas De Coser Y De Hacer Punto (al Por Mayor)",
    "sg:phone":"+34 914 62 26 38",
    "sg:postcode":"28047",
    "sg:province":"Madrid",
    "wof:name":"Herrero Lopez Martin",
    "wof:placetype":"venue"
},
  "geometry": {"coordinates":[-3.7471659184,40.3833961487],"type":"Point"}
}