{
  "type": "Feature",
  "properties": {
    "iso:country":"ES",
    "sg:address":"Carrer de Notari Closells, 6",
    "sg:city":"Olot",
    "sg:orig_category":"Arquitectos",
    "sg:phone":"+34 972 26 84 25",
    "sg:postcode":"17800",
    "sg:province":"Girona",
    "wof:name":"Massegur Soy Ramon",
    "wof:placetype":"venue"
},
  "geometry": {"coordinates":[2.4833979607,42.1803245544],"type":"Point"}
}