{
  "type": "Feature",
  "properties": {
    "addr:full":"Rua Montero Rios, S/n Noia A Coru\u00f1a 15200",
    "addr:postcode":"15200",
    "addr:street":"Rua Montero Rios S / N;A Corun\u0303A",
    "iso:country":"ES",
    "sg:address":"Rua Montero Rios, S/n",
    "sg:city":"Noia",
    "sg:orig_category":"Librer\u00cdas",
    "sg:phone":"+34 981 82 16 05",
    "sg:postcode":"15200",
    "sg:province":"A Coru\u00f1a",
    "wof:name":"Toxosoutos S.l.",
    "wof:placetype":"venue"
},
  "geometry": {"coordinates":[-8.8880157471,42.7836303711],"type":"Point"}
}