{
  "type": "Feature",
  "properties": {
    "addr:full":"Major, 49 Torrefarrera Lleida 25123",
    "addr:housenumber":"49",
    "addr:postcode":"25123",
    "addr:street":"Major",
    "iso:country":"ES",
    "sg:address":"Major, 49",
    "sg:city":"Torrefarrera",
    "sg:orig_category":"Mercer\u00cda, Lencer\u00cda (al Por Menor)",
    "sg:phone":"+34 973 75 00 29",
    "sg:postcode":"25123",
    "sg:province":"Lleida",
    "wof:name":"Siurana Creus Julio",
    "wof:placetype":"venue"
},
  "geometry": {"coordinates":[0.6062830091,41.6737251282],"type":"Point"}
}