{
  "type": "Feature",
  "properties": {
    "addr:full":"Carrer de Treball, 2 S. Just Desvern Barcelona 08960",
    "addr:housenumber":"2",
    "addr:postcode":"08960",
    "addr:street":"Carrer De Treball",
    "iso:country":"ES",
    "sg:address":"Carrer de Treball, 2",
    "sg:city":"S. Just Desvern",
    "sg:orig_category":"Fabricaci\u00d3n De Telas Y Sedas",
    "sg:phone":"+34 934 73 33 32",
    "sg:postcode":"08960",
    "sg:province":"Barcelona",
    "wof:name":"Natural Fabrics S.l.",
    "wof:placetype":"venue"
},
  "geometry": {"coordinates":[2.0782721043,41.3850669861],"type":"Point"}
}