{
  "type": "Feature",
  "properties": {
    "iso:country":"ES",
    "sg:address":"Calle de Jover, 28",
    "sg:city":"Castellon",
    "sg:orig_category":"Comercio, Reparaci\u00d3n De Motocicletas, Bicicletas Y Piezas Sueltas",
    "sg:phone":"+34 964 20 90 18",
    "sg:postcode":"12002",
    "sg:province":"Castell\u00f3n",
    "wof:name":"Gorrita Urrea Vicente Baltasar",
    "wof:placetype":"venue"
},
  "geometry": {"coordinates":[-0.0383009985,39.9808425903],"type":"Point"}
}