{
  "type": "Feature",
  "properties": {
    "addr:full":"Av Peru, 17 Mataro Barcelona 08304",
    "addr:housenumber":"17",
    "addr:postcode":"08304",
    "addr:street":"Av Peru",
    "iso:country":"ES",
    "sg:address":"Av Peru, 17",
    "sg:city":"Mataro",
    "sg:orig_category":"Iglesia Cat\u00d3lica",
    "sg:phone":"+34 937 90 22 62",
    "sg:postcode":"08304",
    "sg:province":"Barcelona",
    "wof:name":"Parroquia De Nuestra Se\u00f1ora De La Esperanza",
    "wof:placetype":"venue"
},
  "geometry": {"coordinates":[2.4482109547,41.5485954285],"type":"Point"}
}