{
  "type": "Feature",
  "properties": {
    "addr:full":"Plaz Mayor, 4 Tornavacas C\u00e1ceres 10611",
    "addr:housenumber":"4",
    "addr:postcode":"10611",
    "addr:street":"Plaz Mayor;Ca\u0301Ceres",
    "iso:country":"ES",
    "sg:address":"Plaz Mayor, 4",
    "sg:city":"Tornavacas",
    "sg:orig_category":"Administraciones Regionales, Departamentales Y Locales",
    "sg:phone":"+34 927 17 70 18",
    "sg:postcode":"10611",
    "sg:province":"C\u00e1ceres",
    "wof:name":"Ayuntamiento De Tornavacas",
    "wof:placetype":"venue"
},
  "geometry": {"coordinates":[-5.6773509979,40.2413024902],"type":"Point"}
}