{
  "type": "Feature",
  "properties": {
    "iso:country":"ES",
    "sg:address":"Luga Ramil, S/n",
    "sg:city":"Lestedo",
    "sg:orig_category":"Importaci\u00d3n",
    "sg:phone":"+34 981 50 23 14",
    "sg:postcode":"15881",
    "sg:province":"La Coru\u00f1a",
    "wof:name":"Blanco Jose Olegario",
    "wof:placetype":"venue"
},
  "geometry": {"coordinates":[-8.4128170013,42.8135566711],"type":"Point"}
}