{
  "type": "Feature",
  "properties": {
    "iso:country":"ES",
    "sg:address":"Carr Sant Jaume, 8",
    "sg:city":"Pallerols",
    "sg:orig_category":"Confecci\u00d3n (fabricaci\u00d3n, Al Por Mayor)",
    "sg:phone":"+34 973 54 00 47",
    "sg:postcode":"25213",
    "sg:province":"Lleida",
    "wof:name":"Confeccions Ramona S.l.",
    "wof:placetype":"venue"
},
  "geometry": {"coordinates":[1.3531969786,41.6189041138],"type":"Point"}
}