{
  "type": "Feature",
  "properties": {
    "iso:country":"ES",
    "sg:address":"Rua Ameas (das), S/n",
    "sg:city":"Santiago De Compostela",
    "sg:orig_category":"Carnicer\u00cdas, Carnicer\u00cdas",
    "sg:phone":"+34 981 58 34 35",
    "sg:postcode":"15704",
    "sg:province":"La Coru\u00f1a",
    "wof:name":"Grela Freire Benedicta",
    "wof:placetype":"venue"
},
  "geometry": {"coordinates":[-8.5415287018,42.8800773621],"type":"Point"}
}