{
  "type": "Feature",
  "properties": {
    "iso:country":"ES",
    "sg:address":"Calle de Pedro Velasco, 31",
    "sg:city":"Vitigudino",
    "sg:orig_category":"Frutas, Legumbres Frescas Y Tempranas (al Por Menor)",
    "sg:phone":"+34 923 50 04 52",
    "sg:postcode":"37210",
    "sg:province":"Salamanca",
    "wof:name":"Fernandez Gonzalez Luis",
    "wof:placetype":"venue"
},
  "geometry": {"coordinates":[-6.4325389862,41.0086975098],"type":"Point"}
}