{
  "type": "Feature",
  "properties": {
    "addr:full":"Calle de Gabolatz, 5 Soraluze-placencia Armas Guip\u00f9zcoa 20590",
    "addr:housenumber":"5",
    "addr:postcode":"20590",
    "addr:street":"Calle De Gabolatz;Armas Guipu\u0300Zcoa",
    "iso:country":"ES",
    "sg:address":"Calle de Gabolatz, 5",
    "sg:city":"Soraluze-placencia Armas",
    "sg:orig_category":"M\u00c9dicos: Medicina Y Biolog\u00cda Del Deporte",
    "sg:phone":"+34 943 75 12 88",
    "sg:postcode":"20590",
    "sg:province":"Guip\u00f9zcoa",
    "wof:name":"Pe\u00f1alba Badiola Jose Maria",
    "wof:placetype":"venue"
},
  "geometry": {"coordinates":[-2.419989109,43.1778755188],"type":"Point"}
}