{
  "type": "Feature",
  "properties": {
    "addr:full":"Pol Ind Olivos, S/n Pobla Tornesa Castell\u00f3n 12191",
    "addr:postcode":"12191",
    "addr:street":"Olivos S / N",
    "iso:country":"ES",
    "sg:address":"Pol Ind Olivos, S/n",
    "sg:city":"Pobla Tornesa",
    "sg:orig_category":"Impermeabilizantes",
    "sg:phone":"+34 964 24 78 23",
    "sg:postcode":"12191",
    "sg:province":"Castell\u00f3n",
    "wof:name":"Nuran Impermeabilizaciones Materiales Y Pavimentos S.l.",
    "wof:placetype":"venue"
},
  "geometry": {"coordinates":[-0.00097,40.1001205444],"type":"Point"}
}