{
  "type": "Feature",
  "properties": {
    "addr:full":"Tarento, 5 Garrapinillos Zaragoza 50197",
    "addr:housenumber":"5",
    "addr:postcode":"50197",
    "addr:street":"Tarento",
    "iso:country":"ES",
    "sg:address":"Tarento, 5",
    "sg:city":"Garrapinillos",
    "sg:orig_category":"Suministros Y Materiales Industriales",
    "sg:phone":"+34 976 46 31 37",
    "sg:postcode":"50197",
    "sg:province":"Zaragoza",
    "wof:name":"Global Bulon S.l.",
    "wof:placetype":"venue"
},
  "geometry": {"coordinates":[-1.0269140005,41.6842803955],"type":"Point"}
}