{
  "type": "Feature",
  "properties": {
    "addr:full":"Calle de Menendez Valdes, 25 Gijon Asturias 33201",
    "addr:housenumber":"25",
    "addr:postcode":"33201",
    "addr:street":"Calle De Menendez Valdes",
    "iso:country":"ES",
    "sg:address":"Calle de Menendez Valdes, 25",
    "sg:city":"Gijon",
    "sg:orig_category":"Ropa Para Se\u00d1oras Y Caballeros (al Por Menor)",
    "sg:phone":"+34 985 17 00 50",
    "sg:postcode":"33201",
    "sg:province":"Asturias",
    "wof:name":"Tizza Y 20 Ans C.b.",
    "wof:placetype":"venue"
},
  "geometry": {"coordinates":[-5.6591010094,43.5403442383],"type":"Point"}
}