{
  "type": "Feature",
  "properties": {
    "addr:full":"Avda Buenos Aires, 110 Lalin Pontevedra 36500",
    "addr:housenumber":"110",
    "addr:postcode":"36500",
    "addr:street":"Avda Buenos Aires",
    "iso:country":"ES",
    "sg:address":"Avda Buenos Aires, 110",
    "sg:city":"Lalin",
    "sg:orig_category":"Cooperativas Agr\u00cdcolas",
    "sg:phone":"+34 986 78 36 93",
    "sg:postcode":"36500",
    "sg:province":"Pontevedra",
    "wof:name":"Unions Agrarias Do Ribeiro",
    "wof:placetype":"venue"
},
  "geometry": {"coordinates":[-8.1126489639,42.6599311829],"type":"Point"}
}