{
  "type": "Feature",
  "properties": {
    "iso:country":"ES",
    "sg:address":"Plaz Mayor, 3",
    "sg:city":"Oca\u00f1a",
    "sg:orig_category":"Inmobiliaria (agencias)",
    "sg:phone":"+34 925 12 06 64",
    "sg:postcode":"45300",
    "sg:province":"Toledo",
    "wof:name":"Izquierdo Selles Francisco",
    "wof:placetype":"venue"
},
  "geometry": {"coordinates":[-3.5003080368,39.9588470459],"type":"Point"}
}