{
  "type": "Feature",
  "properties": {
    "iso:country":"ES",
    "sg:address":"Calle de Antonio Martelo, 3",
    "sg:city":"Malaga",
    "sg:orig_category":"Bisuteros (fabricaci\u00d3n, Al Por Mayor)",
    "sg:phone":"+34 952 34 28 28",
    "sg:postcode":"29006",
    "sg:province":"M\u00e1laga",
    "wof:name":"Caballero Romero Maria Del Mar",
    "wof:placetype":"venue"
},
  "geometry": {"coordinates":[-4.4412388802,36.7111282349],"type":"Point"}
}