{
  "type": "Feature",
  "properties": {
    "addr:full":"Avda Generalisimo, S/n Hoyo De Pinares \u00c1vila 05250",
    "addr:housenumber":"s / n",
    "addr:postcode":"05250",
    "addr:street":"Avda Generalisimo;A\u0301Vila",
    "iso:country":"ES",
    "sg:address":"Avda Generalisimo, S/n",
    "sg:city":"Hoyo De Pinares",
    "sg:orig_category":"Sales (al Por Mayor)",
    "sg:phone":"+34 918 63 90 93",
    "sg:postcode":"05250",
    "sg:province":"\u00c1vila",
    "wof:name":"Santamaria Rodriguez Juan Jose",
    "wof:placetype":"venue"
},
  "geometry": {"coordinates":[-4.4238262177,40.4995574951],"type":"Point"}
}