{
  "type": "Feature",
  "properties": {
    "iso:country":"ES",
    "sg:address":"Cra. Banyeres, Km. 1600,0",
    "sg:city":"Arbo\u00e7",
    "sg:orig_category":"Refiner\u00cdas De Petr\u00d3leo",
    "sg:phone":"+34 977 67 17 00",
    "sg:postcode":"43720",
    "sg:province":"Tarragona",
    "wof:name":"Oilinvest Espa\u00f1a S.a.",
    "wof:placetype":"venue"
},
  "geometry": {"coordinates":[1.6028549671,41.2648735046],"type":"Point"}
}