{
  "type": "Feature",
  "properties": {
    "addr:full":"Ctra Coru\u00d1a, 15 San Rafael Segovia 40410",
    "addr:housenumber":"15",
    "addr:postcode":"40410",
    "addr:street":"Ctra Corun\u0303A",
    "iso:country":"ES",
    "sg:address":"Ctra Coru\u00d1a, 15",
    "sg:city":"San Rafael",
    "sg:orig_category":"Confiter\u00cdas, Chocolater\u00cdas (al Por Menor)",
    "sg:phone":"+34 921 17 22 32",
    "sg:postcode":"40410",
    "sg:province":"Segovia",
    "wof:name":"Novatel Plus S.l.",
    "wof:placetype":"venue"
},
  "geometry": {"coordinates":[-4.1855669022,40.7127342224],"type":"Point"}
}