{
  "type": "Feature",
  "properties": {
    "iso:country":"ES",
    "sg:address":"Calle de Nueva, 12",
    "sg:city":"Elda",
    "sg:orig_category":"Organizaci\u00d3n De Actos, Seminarios Y Congresos",
    "sg:phone":"+34 965 38 09 73",
    "sg:postcode":"03600",
    "sg:province":"Alicante",
    "wof:name":"Catering Isla Interior S.l.",
    "wof:placetype":"venue"
},
  "geometry": {"coordinates":[-0.7972229719,38.4777641296],"type":"Point"}
}