{
  "type": "Feature",
  "properties": {
    "addr:full":"Extramuros, S/n Tarancon Cuenca 16400",
    "addr:postcode":"16400",
    "addr:street":"Extramuros S / N",
    "iso:country":"ES",
    "sg:address":"Extramuros, S/n",
    "sg:city":"Tarancon",
    "sg:orig_category":"Mataderos Y Talleres De Despiezado",
    "sg:phone":"+34 969 14 84 14",
    "sg:postcode":"16400",
    "sg:province":"Cuenca",
    "wof:name":"Granjas Cuniculas Fergarma S.l.",
    "wof:placetype":"venue"
},
  "geometry": {"coordinates":[-3.00634408,40.0024261475],"type":"Point"}
}