{
  "type": "Feature",
  "properties": {
    "addr:full":"Carrer de Cala Joanet, 2 Ametlla Mar Tarragona 43860",
    "addr:housenumber":"2",
    "addr:postcode":"43860",
    "addr:street":"Carrer De Cala Joanet",
    "iso:country":"ES",
    "sg:address":"Carrer de Cala Joanet, 2",
    "sg:city":"Ametlla Mar",
    "sg:orig_category":"Distribuci\u00d3n De Petr\u00d3leo Y Derivados",
    "sg:phone":"+34 977 45 66 92",
    "sg:postcode":"43860",
    "sg:province":"Tarragona",
    "wof:name":"Garcia-juan C.b.",
    "wof:placetype":"venue"
},
  "geometry": {"coordinates":[0.7986710072,40.8819274902],"type":"Point"}
}