{
  "type": "Feature",
  "properties": {
    "addr:full":"Pl Mestre Clave, 2 Hospitalet Llobregat Barcelona 08901",
    "addr:housenumber":"2",
    "addr:postcode":"08901",
    "addr:street":"Pl Mestre Clave",
    "iso:country":"ES",
    "sg:address":"Pl Mestre Clave, 2",
    "sg:city":"Hospitalet Llobregat",
    "sg:orig_category":"Asesor\u00cda Sobre Comunicaci\u00d3n De Empresas",
    "sg:phone":"+34 933 37 91 48",
    "sg:postcode":"08901",
    "sg:province":"Barcelona",
    "sg:website":"www.agio.es",
    "wof:name":"Agio Servicios Centralizados S.a.",
    "wof:placetype":"venue"
},
  "geometry": {"coordinates":[2.1068880558,41.3614654541],"type":"Point"}
}