{
  "type": "Feature",
  "properties": {
    "addr:full":"Carrer de Igualada, 54 Vilafranca Penedes Barcelona 08720",
    "addr:housenumber":"54",
    "addr:postcode":"08720",
    "addr:street":"Carrer De Igualada",
    "iso:country":"ES",
    "sg:address":"Carrer de Igualada, 54",
    "sg:city":"Vilafranca Penedes",
    "sg:orig_category":"Asesor\u00cda Sobre Comunicaci\u00d3n De Empresas",
    "sg:phone":"+34 938 18 20 79",
    "sg:postcode":"08720",
    "sg:province":"Barcelona",
    "wof:name":"Torra Badia Economistes Auditors S.l.",
    "wof:placetype":"venue"
},
  "geometry": {"coordinates":[1.7036399841,41.3488006592],"type":"Point"}
}