{
  "type": "Feature",
  "properties": {
    "iso:country":"ES",
    "sg:address":"Pol Ind Capellania, 2",
    "sg:city":"Archena",
    "sg:orig_category":"Veh\u00cdculos De Ocasi\u00d3n",
    "sg:phone":"+34 968 67 04 22",
    "sg:postcode":"30600",
    "sg:province":"Murcia",
    "wof:name":"Abenza Martinez Francisco Jose",
    "wof:placetype":"venue"
},
  "geometry": {"coordinates":[-1.303551,38.114105],"type":"Point"}
}