{
  "type": "Feature",
  "properties": {
    "addr:full":"Calle de Gambrinus, 103 Grela La Coru\u00f1a 15008",
    "addr:housenumber":"103",
    "addr:postcode":"15008",
    "addr:street":"Calle De Gambrinus;La Corun\u0303A",
    "iso:country":"ES",
    "sg:address":"Calle de Gambrinus, 103",
    "sg:city":"Grela",
    "sg:orig_category":"Ropa Para Se\u00d1oras (al Por Menor)",
    "sg:phone":"+34 981 64 10 83",
    "sg:postcode":"15008",
    "sg:province":"La Coru\u00f1a",
    "sg:website":"www.antonio-pernas.es",
    "wof:name":"Antonio Pernas S. A.",
    "wof:placetype":"venue"
},
  "geometry": {"coordinates":[-8.4471950531,43.0565299988],"type":"Point"}
}