{
  "type": "Feature",
  "properties": {
    "addr:full":"Carr Coll I Pujol, 26 Badalona Barcelona 08912",
    "addr:housenumber":"26",
    "addr:postcode":"08912",
    "addr:street":"Carr Coll I Pujol",
    "iso:country":"ES",
    "sg:address":"Carr Coll I Pujol, 26",
    "sg:city":"Badalona",
    "sg:orig_category":"Molduras, Junquillos, Listones Y Molduras Perforadas",
    "sg:phone":"+34 933 87 10 83",
    "sg:postcode":"08912",
    "sg:province":"Barcelona",
    "wof:name":"Escondrijo De Los Tres S.l.",
    "wof:placetype":"venue"
},
  "geometry": {"coordinates":[2.2423949242,41.4488677979],"type":"Point"}
}