{
  "type": "Feature",
  "properties": {
    "addr:full":"Avda Manolete, 17 Cordoba C\u00f3rdoba 14005",
    "addr:housenumber":"17",
    "addr:postcode":"14005",
    "addr:street":"Avda Manolete;Co\u0301Rdoba",
    "iso:country":"ES",
    "sg:address":"Avda Manolete, 17",
    "sg:city":"Cordoba",
    "sg:orig_category":"Inmobiliaria (agencias)",
    "sg:phone":"+34 957 76 13 97",
    "sg:postcode":"14005",
    "sg:province":"C\u00f3rdoba",
    "wof:name":"Aif Alboroque S.l",
    "wof:placetype":"venue"
},
  "geometry": {"coordinates":[-4.7965726852,37.8796844482],"type":"Point"}
}