{
  "type": "Feature",
  "properties": {
    "addr:full":"Calle de Veracruz, 15 Alora M\u00e1laga 29500",
    "addr:housenumber":"15",
    "addr:postcode":"29500",
    "addr:street":"Calle De Veracruz;Ma\u0301Laga",
    "iso:country":"ES",
    "sg:address":"Calle de Veracruz, 15",
    "sg:city":"Alora",
    "sg:orig_category":"Electrodom\u00c9sticos (al Por Menor)",
    "sg:phone":"+34 952 49 89 57",
    "sg:postcode":"29500",
    "sg:province":"M\u00e1laga",
    "wof:name":"Vila Sanchez Jose Luis",
    "wof:placetype":"venue"
},
  "geometry": {"coordinates":[-4.7058849335,36.8241271973],"type":"Point"}
}