{
  "type": "Feature",
  "properties": {
    "addr:full":"Carrer de Carles Mercader, 14 S. Just Desvern Barcelona 08960",
    "addr:housenumber":"14",
    "addr:postcode":"08960",
    "addr:street":"Carrer De Carles Mercader",
    "iso:country":"ES",
    "sg:address":"Carrer de Carles Mercader, 14",
    "sg:city":"S. Just Desvern",
    "sg:orig_category":"Promotores Constructores",
    "sg:phone":"+34 933 71 13 10",
    "sg:postcode":"08960",
    "sg:province":"Barcelona",
    "wof:name":"Magade S.l",
    "wof:placetype":"venue"
},
  "geometry": {"coordinates":[2.075783968,41.3861427307],"type":"Point"}
}