{
  "type": "Feature",
  "properties": {
    "addr:full":"Calle de Iglesia, 16 Cantalejo Segovia 40320",
    "addr:housenumber":"16",
    "addr:postcode":"40320",
    "addr:street":"Calle De Iglesia",
    "iso:country":"ES",
    "sg:address":"Calle de Iglesia, 16",
    "sg:city":"Cantalejo",
    "sg:orig_category":"Florister\u00cdas",
    "sg:phone":"+34 921 52 12 26",
    "sg:postcode":"40320",
    "sg:province":"Segovia",
    "wof:name":"Huerta Trapero Felix",
    "wof:placetype":"venue"
},
  "geometry": {"coordinates":[-3.9272708893,41.2588768005],"type":"Point"}
}