{
  "type": "Feature",
  "properties": {
    "addr:full":"Calle de Musico Gines, 33 Valencia Valencia 46022",
    "addr:housenumber":"33",
    "addr:postcode":"46022",
    "addr:street":"Calle De Musico Gines",
    "iso:country":"ES",
    "sg:address":"Calle de Musico Gines, 33",
    "sg:city":"Valencia",
    "sg:orig_category":"Farmacias",
    "sg:phone":"+34 963 72 56 70",
    "sg:postcode":"46022",
    "sg:province":"Valencia",
    "wof:name":"Andreu-sanz Cb",
    "wof:placetype":"venue"
},
  "geometry": {"coordinates":[-0.3430503011,39.4708480835],"type":"Point"}
}