{
  "type": "Feature",
  "properties": {
    "iso:country":"ES",
    "sg:address":"Calle de Leon, 48",
    "sg:city":"Astorga",
    "sg:orig_category":"Comercio De Piezas De Recambio Y De Accesorios De Veh\u00cdculos, Veh\u00cdculos Industriales",
    "sg:phone":"+34 987 61 84 21",
    "sg:postcode":"24700",
    "sg:province":"Le\u00f3n",
    "wof:name":"Abad Prieto Benito",
    "wof:placetype":"venue"
},
  "geometry": {"coordinates":[-6.061556,42.458858],"type":"Point"}
}