{
  "type": "Feature",
  "properties": {
    "iso:country":"ES",
    "sg:address":"Ctra Cta Reina-tol., Km. 0010,4",
    "sg:city":"Mocejon",
    "sg:orig_category":"Poller\u00cda Y Caza (al Por Menor)",
    "sg:phone":"+34 925 27 07 74",
    "sg:postcode":"45270",
    "sg:province":"Toledo",
    "wof:name":"Cerro Fernandez Francisco",
    "wof:placetype":"venue"
},
  "geometry": {"coordinates":[-3.9195990562,39.937046051],"type":"Point"}
}