{
  "type": "Feature",
  "properties": {
    "addr:full":"Calle de Aurea Galindo, 50 Linares Ja\u00e9n 23700",
    "addr:housenumber":"50",
    "addr:postcode":"23700",
    "addr:street":"Calle De Aurea Galindo;Jae\u0301N",
    "iso:country":"ES",
    "sg:address":"Calle de Aurea Galindo, 50",
    "sg:city":"Linares",
    "sg:orig_category":"Ferreter\u00cda (diversos)",
    "sg:phone":"+34 953 69 38 07",
    "sg:postcode":"23700",
    "sg:province":"Ja\u00e9n",
    "wof:name":"Jover Rodriguez Felix",
    "wof:placetype":"venue"
},
  "geometry": {"coordinates":[-3.6422841549,38.0937004089],"type":"Point"}
}