{
  "type": "Feature",
  "properties": {
    "addr:full":"Avda Paz (la), S/n Villena Alicante 03400",
    "addr:postcode":"03400",
    "addr:street":"Avda Paz La S / N",
    "iso:country":"ES",
    "sg:address":"Avda Paz (la), S/n",
    "sg:city":"Villena",
    "sg:orig_category":"Mec\u00c1nico Del Autom\u00d3vil",
    "sg:phone":"+34 965 80 21 46",
    "sg:postcode":"03400",
    "sg:province":"Alicante",
    "wof:name":"Domene Garcia Sl",
    "wof:placetype":"venue"
},
  "geometry": {"coordinates":[-0.8678089976,38.6453437805],"type":"Point"}
}