{
  "type": "Feature",
  "properties": {
    "iso:country":"ES",
    "sg:address":"Calle de San Clemente, 18",
    "sg:city":"Villarrobledo",
    "sg:orig_category":"Bisuter\u00cda, Joyer\u00cda, Relojer\u00cda (al Por Menor)",
    "sg:phone":"+34 967 14 38 07",
    "sg:postcode":"02600",
    "sg:province":"Albacete",
    "wof:name":"Navarro Carretero Bonifacia",
    "wof:placetype":"venue"
},
  "geometry": {"coordinates":[-2.6005129814,39.2681159973],"type":"Point"}
}