{
  "type": "Feature",
  "properties": {
    "iso:country":"ES",
    "sg:address":"Pla\u00c7 Enric Cristofol Ricart, 26",
    "sg:city":"Vilanova I La Geltru",
    "sg:orig_category":"Estilistas Y Estudios De Estilo De Corte Y Confecci\u00d3n",
    "sg:phone":"+34 938 15 27 50",
    "sg:postcode":"08800",
    "sg:province":"Barcelona",
    "wof:name":"Sapovi S.l.",
    "wof:placetype":"venue"
},
  "geometry": {"coordinates":[1.7237429619,41.2221755981],"type":"Point"}
}