{
  "type": "Feature",
  "properties": {
    "addr:full":"Calle de Estribor, 10 Perellonet Valencia 46012",
    "addr:housenumber":"10",
    "addr:postcode":"46012",
    "addr:street":"Calle De Estribor",
    "iso:country":"ES",
    "sg:address":"Calle de Estribor, 10",
    "sg:city":"Perellonet",
    "sg:orig_category":"Estancos",
    "sg:phone":"+34 961 77 63 71",
    "sg:postcode":"46012",
    "sg:province":"Valencia",
    "wof:name":"Mocholi Pons Vicenta",
    "wof:placetype":"venue"
},
  "geometry": {"coordinates":[-0.2805939913,39.2854652405],"type":"Point"}
}