{
  "type": "Feature",
  "properties": {
    "iso:country":"ES",
    "sg:address":"Plaz Espa\u00d1a, 22",
    "sg:city":"Zafra",
    "sg:orig_category":"Abogados",
    "sg:phone":"+34 924 55 11 93",
    "sg:postcode":"06300",
    "sg:province":"Badajoz",
    "wof:name":"Pineda Nu\u00f1ez Ramon",
    "wof:placetype":"venue"
},
  "geometry": {"coordinates":[-6.4175138474,38.4224853516],"type":"Point"}
}