{
  "type": "Feature",
  "properties": {
    "addr:full":"Zona Pebret, Km. 0001,8 Pe\u00f1iscola Castell\u00f3n 12598",
    "addr:postcode":"12598",
    "addr:street":"Pebret Km. 0001,8 Pen\u0303Iscola Castello\u0301N",
    "iso:country":"ES",
    "sg:address":"Zona Pebret, Km. 0001,8",
    "sg:city":"Pe\u00f1iscola",
    "sg:orig_category":"Inmobiliaria (agencias)",
    "sg:phone":"+34 964 49 10 10",
    "sg:postcode":"12598",
    "sg:province":"Castell\u00f3n",
    "wof:name":"Promobelrosa S.l.",
    "wof:placetype":"venue"
},
  "geometry": {"coordinates":[-0.0456800014,39.9851417542],"type":"Point"}
}