{
  "type": "Feature",
  "properties": {
    "addr:full":"Rua Marcelo Macias, 1 Xinzo De Limia Ourense 32630",
    "addr:housenumber":"1",
    "addr:postcode":"32630",
    "addr:street":"Rua Marcelo Macias",
    "iso:country":"ES",
    "sg:address":"Rua Marcelo Macias, 1",
    "sg:city":"Xinzo De Limia",
    "sg:orig_category":"Apicultura",
    "sg:phone":"+34 988 46 01 69",
    "sg:postcode":"32630",
    "sg:province":"Ourense",
    "wof:name":"Peralta Corderi Jose Manuel",
    "wof:placetype":"venue"
},
  "geometry": {"coordinates":[-7.7260317802,42.0642585754],"type":"Point"}
}