{
  "type": "Feature",
  "properties": {
    "iso:country":"ES",
    "sg:address":"Avda Orense, S/n",
    "sg:city":"Marin",
    "sg:orig_category":"Estudios Y Construcci\u00d3n De Acuarios Y Viveros",
    "sg:phone":"+34 986 89 12 14",
    "sg:postcode":"36900",
    "sg:province":"Pontevedra",
    "wof:name":"Tradepana Espa\u00d1a S.a.",
    "wof:placetype":"venue"
},
  "geometry": {"coordinates":[-8.6970291138,42.3926391602],"type":"Point"}
}