{
  "type": "Feature",
  "properties": {
    "iso:country":"ES",
    "sg:address":"Carr Major, 6",
    "sg:city":"Besalu",
    "sg:orig_category":"Centros De Coordinaci\u00d3n",
    "sg:phone":"+34 972 59 01 54",
    "sg:postcode":"17850",
    "sg:province":"Girona",
    "wof:name":"J.m.i E. Bassols S.l.",
    "wof:placetype":"venue"
},
  "geometry": {"coordinates":[2.7091920376,42.2370147705],"type":"Point"}
}