{
  "type": "Feature",
  "properties": {
    "addr:full":"Av Francesc De Borja Moll, 28 Ciutadella Menorca Islas Baleares 07760",
    "addr:housenumber":"28",
    "addr:postcode":"07760",
    "addr:street":"Av Francesc De Borja Moll",
    "iso:country":"ES",
    "sg:address":"Av Francesc De Borja Moll, 28",
    "sg:city":"Ciutadella Menorca",
    "sg:orig_category":"Empresas De Carpinter\u00cda De Madera",
    "sg:phone":"+34 971 38 07 38",
    "sg:postcode":"07760",
    "sg:province":"Islas Baleares",
    "wof:name":"Fusteria Sebastia S.l.",
    "wof:placetype":"venue"
},
  "geometry": {"coordinates":[3.8388569355,40.0051689148],"type":"Point"}
}