{
  "type": "Feature",
  "properties": {
    "iso:country":"ES",
    "sg:address":"Calle de Poeta Garcia Lorca, 18",
    "sg:city":"Bujalance",
    "sg:orig_category":"Cl\u00cdnicas Dentales",
    "sg:phone":"+34 957 17 02 75",
    "sg:postcode":"14650",
    "sg:province":"C\u00f3rdoba",
    "wof:name":"Clinica Dental Santa Maria S.l.",
    "wof:placetype":"venue"
},
  "geometry": {"coordinates":[-4.380669117,37.8950386047],"type":"Point"}
}