{
  "type": "Feature",
  "properties": {
    "iso:country":"ES",
    "sg:address":"Poligono Industrial, S/n",
    "sg:city":"Vicolozano",
    "sg:orig_category":"Puros, Cigarrillos Y Tabaco (fabricaci\u00d3n, Al Por Mayor)",
    "sg:phone":"+34 920 25 90 72",
    "sg:postcode":"05194",
    "sg:province":"\u00c1vila",
    "wof:name":"Jimenez Jimenez Santiago",
    "wof:placetype":"venue"
},
  "geometry": {"coordinates":[-4.6319680214,40.6813316345],"type":"Point"}
}