{
  "type": "Feature",
  "properties": {
    "addr:full":"Calle de Mayor, 11 Santa Cruz De La Zarza Toledo 45370",
    "addr:housenumber":"11",
    "addr:postcode":"45370",
    "addr:street":"Calle De Mayor",
    "iso:country":"ES",
    "sg:address":"Calle de Mayor, 11",
    "sg:city":"Santa Cruz De La Zarza",
    "sg:orig_category":"Promotores Constructores",
    "sg:phone":"+34 925 12 58 44",
    "sg:postcode":"45370",
    "sg:province":"Toledo",
    "sg:website":"www.copcisa.com",
    "wof:name":"Copcisa S.a.",
    "wof:placetype":"venue"
},
  "geometry": {"coordinates":[-3.1886160374,39.9814376831],"type":"Point"}
}