{
  "type": "Feature",
  "properties": {
    "iso:country":"ES",
    "sg:address":"Calle de Hortaleza, 80",
    "sg:city":"Madrid",
    "sg:orig_category":"Frutas Y Legumbres Secas (al Por Mayor)",
    "sg:phone":"+34 913 08 05 68",
    "sg:postcode":"28004",
    "sg:province":"Madrid",
    "wof:name":"Zhu  Shaoguang",
    "wof:placetype":"venue"
},
  "geometry": {"coordinates":[-3.6986508369,40.4236297607],"type":"Point"}
}