{
  "type": "Feature",
  "properties": {
    "addr:full":"Calle de Ramon De Dura\u00d1ona, 3 Valle Trapaga Vizcaya 48510",
    "addr:housenumber":"3",
    "addr:postcode":"48510",
    "addr:street":"Calle De Ramon De Duran\u0303Ona;Trapaga",
    "iso:country":"ES",
    "sg:address":"Calle de Ramon De Dura\u00d1ona, 3",
    "sg:city":"Valle Trapaga",
    "sg:orig_category":"Loter\u00cda Y T\u00d3mbola",
    "sg:phone":"+34 944 92 27 17",
    "sg:postcode":"48510",
    "sg:province":"Vizcaya",
    "wof:name":"Preiss Sanchez Emma",
    "wof:placetype":"venue"
},
  "geometry": {"coordinates":[-3.0363080502,43.303237915],"type":"Point"}
}