{
  "type": "Feature",
  "properties": {
    "addr:full":"Eras, S/n S. Miguel Due\u00f1as Le\u00f3n 24398",
    "addr:housenumber":"s",
    "addr:postcode":"24398",
    "addr:street":"Eras;/ N S. Miguel Duen\u0303As Leo\u0301N",
    "iso:country":"ES",
    "sg:address":"Eras, S/n",
    "sg:city":"S. Miguel Due\u00f1as",
    "sg:orig_category":"Farmacias",
    "sg:phone":"+34 987 46 70 02",
    "sg:postcode":"24398",
    "sg:province":"Le\u00f3n",
    "wof:name":"Gutierrez Gutierrez Faustina",
    "wof:placetype":"venue"
},
  "geometry": {"coordinates":[-6.5223469734,42.5866127014],"type":"Point"}
}