{
  "type": "Feature",
  "properties": {
    "addr:full":"Calle de Nueve De Mayo, 2 Oviedo Asturias 33002",
    "addr:housenumber":"2",
    "addr:postcode":"33002",
    "addr:street":"Calle De Nueve De Mayo",
    "iso:country":"ES",
    "sg:address":"Calle de Nueve De Mayo, 2",
    "sg:city":"Oviedo",
    "sg:orig_category":"Asistencia Y Consejos",
    "sg:phone":"+34 985 20 77 55",
    "sg:postcode":"33002",
    "sg:province":"Asturias",
    "sg:website":"www.labyfis.com",
    "wof:name":"Labyfis S.l.",
    "wof:placetype":"venue"
},
  "geometry": {"coordinates":[-5.8496723175,43.3654174805],"type":"Point"}
}