{
  "type": "Feature",
  "properties": {
    "addr:full":"Calle de Castellon De La Plana, 6 Ibi Alicante 03440",
    "addr:housenumber":"6",
    "addr:postcode":"03440",
    "addr:street":"Calle De Castellon De La Plana",
    "iso:country":"ES",
    "sg:address":"Calle de Castellon De La Plana, 6",
    "sg:city":"Ibi",
    "sg:orig_category":"Albergues",
    "sg:phone":"+34 965 55 29 78",
    "sg:postcode":"03440",
    "sg:province":"Alicante",
    "sg:website":"www.bgspazio.com",
    "wof:name":"Spazio Hispano Italiana S.l.",
    "wof:placetype":"venue"
},
  "geometry": {"coordinates":[-0.5971693993,38.6107826233],"type":"Point"}
}