{
  "type": "Feature",
  "properties": {
    "iso:country":"ES",
    "sg:address":"Ptge Strauss, 3",
    "sg:city":"Rubi",
    "sg:orig_category":"Grabados",
    "sg:phone":"+34 936 99 73 11",
    "sg:postcode":"08191",
    "sg:province":"Barcelona",
    "wof:name":"Grabados Rubi S.c.p.",
    "wof:placetype":"venue"
},
  "geometry": {"coordinates":[2.0189890862,41.4725379944],"type":"Point"}
}