{
  "type": "Feature",
  "properties": {
    "iso:country":"ES",
    "sg:address":"Calle de Corpus Christi, 17",
    "sg:city":"Toledo",
    "sg:orig_category":"Ropa Para Caballeros (al Por Menor)",
    "sg:phone":"+34 925 25 33 09",
    "sg:postcode":"45005",
    "sg:province":"Toledo",
    "wof:name":"Julian Mu\u00f1oz Confeccion S.l.",
    "wof:placetype":"venue"
},
  "geometry": {"coordinates":[-4.0322713852,39.8746795654],"type":"Point"}
}