{
  "type": "Feature",
  "properties": {
    "iso:country":"ES",
    "sg:address":"Trav De Gracia, 342",
    "sg:city":"Barcelona",
    "sg:orig_category":"Inform\u00c1tica: Mantenimiento Y Reparaci\u00d3n De Ordenadores",
    "sg:phone":"+34 934 46 23 61",
    "sg:postcode":"08025",
    "sg:province":"Barcelona",
    "sg:website":"www.sosmatic.es",
    "wof:name":"Sosmatic S.l.",
    "wof:placetype":"venue"
},
  "geometry": {"coordinates":[2.1701040268,41.4088783264],"type":"Point"}
}