{
  "type": "Feature",
  "properties": {
    "iso:country":"ES",
    "sg:address":"Barr Muelle (el), S/n",
    "sg:city":"Pedre\u00f1a",
    "sg:orig_category":"Peluqueros: De Se\u00d1oras",
    "sg:phone":"+34 942 50 10 58",
    "sg:postcode":"39130",
    "sg:province":"Cantabria",
    "wof:name":"Ortiz Agudo Isabel",
    "wof:placetype":"venue"
},
  "geometry": {"coordinates":[-3.7695939541,43.4376564026],"type":"Point"}
}