{
  "type": "Feature",
  "properties": {
    "addr:full":"Rbla Catalunya, 14 Barcelona Barcelona 08007",
    "addr:housenumber":"14",
    "addr:postcode":"08007",
    "addr:street":"Rbla Catalunya",
    "iso:country":"ES",
    "sg:address":"Rbla Catalunya, 14",
    "sg:city":"Barcelona",
    "sg:orig_category":"Grafistas",
    "sg:phone":"+34 933 17 46 15",
    "sg:postcode":"08007",
    "sg:province":"Barcelona",
    "wof:name":"Artworkers Barcelona S.l.",
    "wof:placetype":"venue"
},
  "geometry": {"coordinates":[2.1674830914,41.3881568909],"type":"Point"}
}