{
  "type": "Feature",
  "properties": {
    "addr:full":"Calle de Conde De Benavente, 1 Valladolid Valladolid 47003",
    "addr:housenumber":"1",
    "addr:postcode":"47003",
    "addr:street":"Calle De Conde De Benavente",
    "iso:country":"ES",
    "sg:address":"Calle de Conde De Benavente, 1",
    "sg:city":"Valladolid",
    "sg:orig_category":"Pescader\u00cdas (al Por Menor)",
    "sg:phone":"+34 983 35 85 78",
    "sg:postcode":"47003",
    "sg:province":"Valladolid",
    "wof:name":"Hermanos Sanchez Repiso",
    "wof:placetype":"venue"
},
  "geometry": {"coordinates":[-4.7303090096,41.6581993103],"type":"Point"}
}