{
  "type": "Feature",
  "properties": {
    "addr:full":"Av Gaudi, 8 Barcelona Barcelona 08025",
    "addr:housenumber":"8",
    "addr:postcode":"08025",
    "addr:street":"Av Gaudi",
    "iso:country":"ES",
    "sg:address":"Av Gaudi, 8",
    "sg:city":"Barcelona",
    "sg:orig_category":"Elementos Para Suelos Prefabricados",
    "sg:phone":"+34 934 46 11 08",
    "sg:postcode":"08025",
    "sg:province":"Barcelona",
    "wof:name":"Karinas Parket S.l.",
    "wof:placetype":"venue"
},
  "geometry": {"coordinates":[2.174683094,41.4050941467],"type":"Point"}
}