{
  "type": "Feature",
  "properties": {
    "iso:country":"ES",
    "sg:address":"Calle de Caliza, 16",
    "sg:city":"Madrid",
    "sg:orig_category":"Juegos Y Juguetes (al Por Menor)",
    "sg:phone":"+34 917 76 65 01",
    "sg:postcode":"28032",
    "sg:province":"Madrid",
    "wof:name":"Gonzalez Ramos Alejandro",
    "wof:placetype":"venue"
},
  "geometry": {"coordinates":[-3.6040916443,40.3976364136],"type":"Point"}
}