{
  "type": "Feature",
  "properties": {
    "iso:country":"ES",
    "sg:address":"Calle de Fundadores, 10",
    "sg:city":"Madrid",
    "sg:orig_category":"Radiocomunicaciones, Telefon\u00cda M\u00d3vil, Radiomensajer\u00cda: Servicios, Comercializaci\u00d3n",
    "sg:phone":"+34 913 55 22 59",
    "sg:postcode":"28028",
    "sg:province":"Madrid",
    "wof:name":"Almeida Perez Lorena Del Carmen",
    "wof:placetype":"venue"
},
  "geometry": {"coordinates":[-3.66720891,40.4246520996],"type":"Point"}
}