{
  "type": "Feature",
  "properties": {
    "addr:full":"Avda Espa\u00d1a, 50 Majadahonda Madrid 28220",
    "addr:housenumber":"50",
    "addr:postcode":"28220",
    "addr:street":"Avda Espan\u0303A",
    "iso:country":"ES",
    "sg:address":"Avda Espa\u00d1a, 50",
    "sg:city":"Majadahonda",
    "sg:orig_category":"Ropa Y Art\u00cdculos Pre",
    "sg:phone":"+34 916 38 76 23",
    "sg:postcode":"28220",
    "sg:province":"Madrid",
    "wof:name":"Rubio Noguera Victor",
    "wof:placetype":"venue"
},
  "geometry": {"coordinates":[-3.866975069,40.4647598267],"type":"Point"}
}