{
  "type": "Feature",
  "properties": {
    "iso:country":"ES",
    "sg:address":"Carrer de Sant Agusti (de), 10",
    "sg:city":"Tarragona",
    "sg:orig_category":"Fabricaci\u00d3n De Sobres, Bolsas Y Fundas",
    "sg:phone":"+34 977 23 20 78",
    "sg:postcode":"43003",
    "sg:province":"Tarragona",
    "sg:website":"www.misako.com",
    "wof:name":"Frag Comercio Internacional S.l.",
    "wof:placetype":"venue"
},
  "geometry": {"coordinates":[1.2547860146,41.1151313782],"type":"Point"}
}