{
  "type": "Feature",
  "properties": {
    "iso:country":"ES",
    "sg:address":"Calle de Fernandez Y Gonzalez, 2",
    "sg:city":"Sevilla",
    "sg:orig_category":"Agencias Y Asesores De Publicidad",
    "sg:phone":"+34 954 21 07 30",
    "sg:postcode":"41001",
    "sg:province":"Sevilla",
    "sg:website":"www.optimedia.es",
    "wof:name":"Optimedia S.a.",
    "wof:placetype":"venue"
},
  "geometry": {"coordinates":[-5.9946188927,37.3879203796],"type":"Point"}
}