{
  "type": "Feature",
  "properties": {
    "iso:country":"ES",
    "sg:address":"Carrer de Topazi, 29",
    "sg:city":"Barcelona",
    "sg:orig_category":"Asociaciones Humanitarias, De Cooperaci\u00d3n, De Acci\u00d3n Social",
    "sg:phone":"+34 932 17 46 61",
    "sg:postcode":"08012",
    "sg:province":"Barcelona",
    "wof:name":"Acfames",
    "wof:placetype":"venue"
},
  "geometry": {"coordinates":[2.1544370651,41.4053573608],"type":"Point"}
}