{
  "type": "Feature",
  "properties": {
    "addr:full":"Carrer de Montcada (de), 10 Tortosa Tarragona 43500",
    "addr:housenumber":"10",
    "addr:postcode":"43500",
    "addr:street":"Carrer De Montcada De",
    "iso:country":"ES",
    "sg:address":"Carrer de Montcada (de), 10",
    "sg:city":"Tortosa",
    "sg:orig_category":"Perfumer\u00cda, Art\u00cdculos De Ba\u00d1o (fabricaci\u00d3n, Al Por Mayor)",
    "sg:phone":"+34 977 51 11 86",
    "sg:postcode":"43500",
    "sg:province":"Tarragona",
    "wof:name":"Mascarell Prades Ester",
    "wof:placetype":"venue"
},
  "geometry": {"coordinates":[0.5222049952,40.8122444153],"type":"Point"}
}