{
  "type": "Feature",
  "properties": {
    "addr:full":"Juan Gris, 59 Palma Islas Baleares 07011",
    "addr:housenumber":"59",
    "addr:postcode":"07011",
    "addr:street":"Juan Gris",
    "iso:country":"ES",
    "sg:address":"Juan Gris, 59",
    "sg:city":"Palma",
    "sg:orig_category":"Importaci\u00d3n",
    "sg:phone":"+34 971 40 71 16",
    "sg:postcode":"07011",
    "sg:province":"Islas Baleares",
    "wof:name":"Lopez Holgeras Jose Humberto",
    "wof:placetype":"venue"
},
  "geometry": {"coordinates":[2.634524107,39.5868644714],"type":"Point"}
}