{
  "type": "Feature",
  "properties": {
    "iso:country":"ES",
    "sg:address":"I. Ondo, 2",
    "sg:city":"Andra Mari",
    "sg:orig_category":"Supermercados Y Hipermercados",
    "sg:phone":"+34 944 60 38 01",
    "sg:postcode":"48993",
    "sg:province":"Vizcaya",
    "wof:name":"Maria Luisa Argueso Gonzalez S.l",
    "wof:placetype":"venue"
},
  "geometry": {"coordinates":[-2.7541499138,43.2982711792],"type":"Point"}
}