{
  "type": "Feature",
  "properties": {
    "iso:country":"ES",
    "sg:address":"Calle de Rua Mayor, 22",
    "sg:city":"Salamanca",
    "sg:orig_category":"Art\u00cdculos De Regalo (al Por Menor)",
    "sg:phone":"+34 923 27 10 09",
    "sg:postcode":"37002",
    "sg:province":"Salamanca",
    "sg:website":"www.patiochico.com",
    "wof:name":"Ca\u00f1ada Isidro Jeronimo",
    "wof:placetype":"venue"
},
  "geometry": {"coordinates":[-5.6653652191,40.9632568359],"type":"Point"}
}