{
  "type": "Feature",
  "properties": {
    "addr:full":"Calle de Uruguay, 5 Alcantarilla Murcia 30820",
    "addr:housenumber":"5",
    "addr:postcode":"30820",
    "addr:street":"Calle De Uruguay",
    "iso:country":"ES",
    "sg:address":"Calle de Uruguay, 5",
    "sg:city":"Alcantarilla",
    "sg:orig_category":"Construcciones Met\u00c1licas",
    "sg:phone":"+34 968 80 23 50",
    "sg:postcode":"30820",
    "sg:province":"Murcia",
    "sg:website":"www.navidur.es",
    "wof:name":"Navimur S.l.",
    "wof:placetype":"venue"
},
  "geometry": {"coordinates":[-1.1927496195,37.9573974609],"type":"Point"}
}