{
  "type": "Feature",
  "properties": {
    "iso:country":"ES",
    "sg:address":"Beethoven",
    "sg:city":"Malaga",
    "sg:orig_category":"Carnicer\u00cdas, Carnicer\u00cdas",
    "sg:phone":"+34 952 23 53 19",
    "sg:postcode":"29004",
    "sg:province":"M\u00e1laga",
    "wof:name":"Francisco Pelayo Y Otros S.c.",
    "wof:placetype":"venue"
},
  "geometry": {"coordinates":[-4.4506278038,36.6947593689],"type":"Point"}
}