{
  "type": "Feature",
  "properties": {
    "iso:country":"ES",
    "sg:address":"Carr Major, 1",
    "sg:city":"Fontanilles",
    "sg:orig_category":"Producci\u00d3n, Venta De Productos De Agricultura Biol\u00d3gica",
    "sg:phone":"+34 972 75 74 78",
    "sg:postcode":"17257",
    "sg:province":"Girona",
    "wof:name":"Agricola Mas Bagur S.l.",
    "wof:placetype":"venue"
},
  "geometry": {"coordinates":[3.1034295559,42.0304794312],"type":"Point"}
}