{
  "type": "Feature",
  "properties": {
    "addr:full":"Pla\u00c7 Llibertat, De La, 10 Ciutadella Menorca Islas Baleares 07760",
    "addr:postcode":"07760",
    "iso:country":"ES",
    "sg:address":"Pla\u00c7 Llibertat, De La, 10",
    "sg:city":"Ciutadella Menorca",
    "sg:orig_category":"Carnicer\u00cdas, Carnicer\u00cdas",
    "sg:phone":"+34 971 38 17 77",
    "sg:postcode":"07760",
    "sg:province":"Islas Baleares",
    "wof:name":"Carnicaria Salord",
    "wof:placetype":"venue"
},
  "geometry": {"coordinates":[3.8416149616,40.0027542114],"type":"Point"}
}