{
  "type": "Feature",
  "properties": {
    "addr:full":"Carrer de Taxdirt, 61 Barcelona Barcelona 08025",
    "addr:housenumber":"61",
    "addr:postcode":"08025",
    "addr:street":"Carrer De Taxdirt",
    "iso:country":"ES",
    "sg:address":"Carrer de Taxdirt, 61",
    "sg:city":"Barcelona",
    "sg:orig_category":"Mec\u00c1nico Del Autom\u00d3vil",
    "sg:phone":"+34 934 35 07 84",
    "sg:postcode":"08025",
    "sg:province":"Barcelona",
    "wof:name":"Gallego Estrada Toribio",
    "wof:placetype":"venue"
},
  "geometry": {"coordinates":[2.1678190231,41.4103736877],"type":"Point"}
}