{
  "type": "Feature",
  "properties": {
    "addr:full":"Carrer de Marques De Monistrol, 25 S. Joan Despi Barcelona 08970",
    "addr:housenumber":"25",
    "addr:postcode":"08970",
    "addr:street":"Carrer De Marques De Monistrol;S. Joan Despi",
    "iso:country":"ES",
    "sg:address":"Carrer de Marques De Monistrol, 25",
    "sg:city":"S. Joan Despi",
    "sg:orig_category":"Agencias Y Agentes Comerciales, Representantes",
    "sg:phone":"+34 934 77 06 54",
    "sg:postcode":"08970",
    "sg:province":"Barcelona",
    "wof:name":"L'etnoc S.a.",
    "wof:placetype":"venue"
},
  "geometry": {"coordinates":[2.0696458817,41.3724365234],"type":"Point"}
}