{
  "type": "Feature",
  "properties": {
    "iso:country":"ES",
    "sg:address":"Carrer de Sardenya, 497",
    "sg:city":"Barcelona",
    "sg:orig_category":"Peluqueros: De Se\u00d1oras",
    "sg:phone":"+34 932 10 14 56",
    "sg:postcode":"08025",
    "sg:province":"Barcelona",
    "wof:name":"Abril Garcia Maria Del Rosario",
    "wof:placetype":"venue"
},
  "geometry": {"coordinates":[2.164332,41.41021],"type":"Point"}
}