{
  "type": "Feature",
  "properties": {
    "iso:country":"ES",
    "sg:address":"Calle de Hnos. De La Instruccion Cristiana, 21",
    "sg:city":"Portugalete",
    "sg:orig_category":"Carnicer\u00cdas, Carnicer\u00cdas",
    "sg:phone":"+34 944 06 57 14",
    "sg:postcode":"48920",
    "sg:province":"Vizcaya",
    "wof:name":"Pedro, Jose Luis Soto Zabala Cb",
    "wof:placetype":"venue"
},
  "geometry": {"coordinates":[-3.0242800713,43.3233528137],"type":"Point"}
}