{
  "type": "Feature",
  "properties": {
    "addr:full":"Ctra Pego, Km. 0004,5 Muro Alcoy Alicante 03830",
    "addr:postcode":"03830",
    "addr:street":"Ctra Pego Km. 0004,5 Muro",
    "iso:country":"ES",
    "sg:address":"Ctra Pego, Km. 0004,5",
    "sg:city":"Muro Alcoy",
    "sg:orig_category":"Fabricaci\u00d3n De Su\u00c9ters Y Chalecos De Punto",
    "sg:phone":"+34 965 53 03 89",
    "sg:postcode":"03830",
    "sg:province":"Alicante",
    "wof:name":"Seu-punt S.l.",
    "wof:placetype":"venue"
},
  "geometry": {"coordinates":[-0.4414289892,38.7812538147],"type":"Point"}
}