{
  "type": "Feature",
  "properties": {
    "iso:country":"ES",
    "sg:address":"Calle de Carretas, 1",
    "sg:city":"Bullas",
    "sg:orig_category":"Farmacias",
    "sg:phone":"+34 968 65 21 82",
    "sg:postcode":"30180",
    "sg:province":"Murcia",
    "wof:name":"Marin Fuentes Juan",
    "wof:placetype":"venue"
},
  "geometry": {"coordinates":[-1.6717875004,38.047088623],"type":"Point"}
}