{
  "type": "Feature",
  "properties": {
    "addr:full":"Calle de Puerto De Santa Maria, 43 Madrid Madrid 28043",
    "addr:housenumber":"43",
    "addr:postcode":"madrid;28043",
    "addr:street":"Calle De Puerto De Santa Maria",
    "iso:country":"ES",
    "sg:address":"Calle de Puerto De Santa Maria, 43",
    "sg:city":"Madrid",
    "sg:orig_category":"Agencias Y Asesores De Publicidad",
    "sg:phone":"+34 917 59 82 73",
    "sg:postcode":"28043",
    "sg:province":"Madrid",
    "wof:name":"Angel Orive Publicidad S.l.",
    "wof:placetype":"venue"
},
  "geometry": {"coordinates":[-4.1466302872,40.5977287292],"type":"Point"}
}