{
  "type": "Feature",
  "properties": {
    "addr:full":"Avda Dos De Mayo, 19 Leganes Madrid 28912",
    "addr:housenumber":"19",
    "addr:postcode":"28912",
    "addr:street":"Avda Dos De Mayo",
    "iso:country":"ES",
    "sg:address":"Avda Dos De Mayo, 19",
    "sg:city":"Leganes",
    "sg:orig_category":"Peluquer\u00cdas, Peluquer\u00cda Mixta",
    "sg:phone":"+34 916 88 50 47",
    "sg:postcode":"28912",
    "sg:province":"Madrid",
    "wof:name":"Madrid Boyero Leonor",
    "wof:placetype":"venue"
},
  "geometry": {"coordinates":[-3.7614939213,40.335609436],"type":"Point"}
}