{
  "type": "Feature",
  "properties": {
    "addr:full":"Carr Sant Genis, 3 Vila-robau Girona 17475",
    "addr:housenumber":"3",
    "addr:postcode":"17475",
    "addr:street":"Carr Sant Genis",
    "iso:country":"ES",
    "sg:address":"Carr Sant Genis, 3",
    "sg:city":"Vila-robau",
    "sg:orig_category":"Cr\u00cda De Animales",
    "sg:phone":"+34 972 79 30 81",
    "sg:postcode":"17475",
    "sg:province":"Girona",
    "wof:name":"Frigola-costa C.b.",
    "wof:placetype":"venue"
},
  "geometry": {"coordinates":[2.9914700985,42.1741333008],"type":"Point"}
}