{
  "type": "Feature",
  "properties": {
    "iso:country":"ES",
    "sg:address":"General Franco, 10",
    "sg:city":"Gallegos Del Pan",
    "sg:orig_category":"Plomeros",
    "sg:phone":"+34 980 50 36 55",
    "sg:postcode":"49539",
    "sg:province":"Zamora",
    "wof:name":"Raton Martin Antonio",
    "wof:placetype":"venue"
},
  "geometry": {"coordinates":[-5.5461440086,41.6103286743],"type":"Point"}
}