{
  "type": "Feature",
  "properties": {
    "addr:full":"Avda Escultora Miss Whitney, 9 Huelva Huelva 21003",
    "addr:housenumber":"9",
    "addr:postcode":"21003",
    "addr:street":"Avda Escultora Miss Whitney",
    "iso:country":"ES",
    "sg:address":"Avda Escultora Miss Whitney, 9",
    "sg:city":"Huelva",
    "sg:orig_category":"Agentes, Concesionarios Y Sucursales De Veh\u00cdculos",
    "sg:phone":"+34 959 28 47 55",
    "sg:postcode":"21003",
    "sg:province":"Huelva",
    "wof:name":"Automoviles 4 Ruedas S.a.",
    "wof:placetype":"venue"
},
  "geometry": {"coordinates":[-6.9453377724,37.2540855408],"type":"Point"}
}