{
  "type": "Feature",
  "properties": {
    "addr:full":"Carrer de Amadeu Vives, 6 Lloret Mar Girona 17310",
    "addr:housenumber":"6",
    "addr:postcode":"17310",
    "addr:street":"Carrer De Amadeu Vives",
    "iso:country":"ES",
    "sg:address":"Carrer de Amadeu Vives, 6",
    "sg:city":"Lloret Mar",
    "sg:orig_category":"Transporte En General",
    "sg:phone":"+34 972 37 34 41",
    "sg:postcode":"17310",
    "sg:province":"Girona",
    "wof:name":"Kenny  Evelyn",
    "wof:placetype":"venue"
},
  "geometry": {"coordinates":[2.8631649017,41.7070617676],"type":"Point"}
}