{
  "type": "Feature",
  "properties": {
    "addr:full":"Cami Marina (de La), 1 Cambrils Tarragona 43850",
    "addr:housenumber":"1",
    "addr:postcode":"43850",
    "addr:street":"Marina;La",
    "iso:country":"ES",
    "sg:address":"Cami Marina (de La), 1",
    "sg:city":"Cambrils",
    "sg:orig_category":"Centros De Educaci\u00d3n Especial",
    "sg:phone":"+34 977 79 37 02",
    "sg:postcode":"43850",
    "sg:province":"Tarragona",
    "wof:name":"Generalitat De Catalunya Serveis D'ensenyament Co%egi Public De E",
    "wof:placetype":"venue"
},
  "geometry": {"coordinates":[1.0573099852,41.0727615356],"type":"Point"}
}