{
  "type": "Feature",
  "properties": {
    "iso:country":"ES",
    "sg:address":"Carr Progres, 404",
    "sg:city":"Badalona",
    "sg:orig_category":"Bisuteros (fabricaci\u00d3n, Al Por Mayor)",
    "sg:phone":"+34 934 60 72 72",
    "sg:postcode":"08918",
    "sg:province":"Barcelona",
    "wof:name":"S.a. Marina Rose",
    "wof:placetype":"venue"
},
  "geometry": {"coordinates":[2.2290210724,41.4308547974],"type":"Point"}
}