{
  "type": "Feature",
  "properties": {
    "iso:country":"ES",
    "sg:address":"Calle de Trece De Diciembre, 5",
    "sg:city":"Villavaliente",
    "sg:orig_category":"Farmacias",
    "sg:phone":"+34 967 40 14 09",
    "sg:postcode":"02154",
    "sg:province":"Albacete",
    "wof:name":"Acitores Parra Maria Del Pilar",
    "wof:placetype":"venue"
},
  "geometry": {"coordinates":[-1.458278656,39.125705719],"type":"Point"}
}