{
  "type": "Feature",
  "properties": {
    "iso:country":"ES",
    "sg:address":"Calle de Villanueva, 33",
    "sg:city":"Madrid",
    "sg:orig_category":"Fabricaci\u00d3n De Mobiliario Met\u00c1lico",
    "sg:phone":"+34 914 01 47 31",
    "sg:postcode":"28001",
    "sg:province":"Madrid",
    "wof:name":"Cadarso Diez Jesus",
    "wof:placetype":"venue"
},
  "geometry": {"coordinates":[-3.6827709675,40.4223861694],"type":"Point"}
}