{
  "type": "Feature",
  "properties": {
    "addr:full":"Av Flores, 3 Lepe Huelva 21440",
    "addr:housenumber":"3",
    "addr:postcode":"21440",
    "addr:street":"Av Flores",
    "iso:country":"ES",
    "sg:address":"Av Flores, 3",
    "sg:city":"Lepe",
    "sg:orig_category":"Inform\u00c1tica: Material Y Suministros",
    "sg:phone":"+34 959 38 11 96",
    "sg:postcode":"21440",
    "sg:province":"Huelva",
    "wof:name":"Resest U.k.s.l.",
    "wof:placetype":"venue"
},
  "geometry": {"coordinates":[-7.1961421967,37.2570877075],"type":"Point"}
}