{
  "type": "Feature",
  "properties": {
    "addr:full":"Calle de Doctoral (el), 1 Astorga Le\u00f3n 24700",
    "addr:housenumber":"1",
    "addr:postcode":"24700",
    "addr:street":"Calle De Doctoral El;Leo\u0301N",
    "iso:country":"ES",
    "sg:address":"Calle de Doctoral (el), 1",
    "sg:city":"Astorga",
    "sg:orig_category":"Venta, Instalaci\u00d3n De Calefacci\u00d3n",
    "sg:phone":"+34 987 60 30 71",
    "sg:postcode":"24700",
    "sg:province":"Le\u00f3n",
    "wof:name":"Ma\u00d1anes Ips S.a.",
    "wof:placetype":"venue"
},
  "geometry": {"coordinates":[-6.0565185547,42.4562187195],"type":"Point"}
}