{
  "type": "Feature",
  "properties": {
    "iso:country":"ES",
    "sg:address":"Ptge. Riuet (st M. Empuries), 17",
    "sg:city":"Escala",
    "sg:orig_category":"Hoteles",
    "sg:phone":"+34 972 77 03 62",
    "sg:postcode":"17130",
    "sg:province":"Girona",
    "wof:name":"Male Ros Juan",
    "wof:placetype":"venue"
},
  "geometry": {"coordinates":[3.1321649551,42.1229934692],"type":"Point"}
}