{
  "type": "Feature",
  "properties": {
    "addr:full":"Pase Florida, 27 Madrid Madrid 28008",
    "addr:housenumber":"27",
    "addr:postcode":"madrid;28008",
    "addr:street":"Florida",
    "iso:country":"ES",
    "sg:address":"Pase Florida, 27",
    "sg:city":"Madrid",
    "sg:orig_category":"Perfumer\u00cda (al Por Menor)",
    "sg:phone":"+34 915 47 62 35",
    "sg:postcode":"28008",
    "sg:province":"Madrid",
    "wof:name":"Sanchez Garcia Carmen",
    "wof:placetype":"venue"
},
  "geometry": {"coordinates":[-3.7225699425,40.4222831726],"type":"Point"}
}