{
  "type": "Feature",
  "properties": {
    "iso:country":"ES",
    "sg:address":"Carrer de Arbos, 6",
    "sg:city":"Barcelona",
    "sg:orig_category":"Molduras, Junquillos, Listones Y Molduras Perforadas",
    "sg:phone":"+34 933 57 30 85",
    "sg:postcode":"08032",
    "sg:province":"Barcelona",
    "wof:name":"Gonzalez Angullo Antonio",
    "wof:placetype":"venue"
},
  "geometry": {"coordinates":[2.1588799953,41.4216499329],"type":"Point"}
}