{
  "type": "Feature",
  "properties": {
    "iso:country":"ES",
    "sg:address":"Carrer de Vila, 18",
    "sg:city":"Lloret Mar",
    "sg:orig_category":"Tiendas De Grano, Frutas Y Legumbres Secas (al Por Menor)",
    "sg:phone":"+34 972 37 10 19",
    "sg:postcode":"17310",
    "sg:province":"Girona",
    "wof:name":"Palma Lopez Maria Teresa",
    "wof:placetype":"venue"
},
  "geometry": {"coordinates":[2.8480279446,41.6996078491],"type":"Point"}
}