{
  "type": "Feature",
  "properties": {
    "iso:country":"ES",
    "sg:address":"Carrer de Calderon De La Barca, 27",
    "sg:city":"Hospitalet Llobregat",
    "sg:orig_category":"Mec\u00c1nico Del Autom\u00d3vil",
    "sg:phone":"+34 934 37 54 70",
    "sg:postcode":"08906",
    "sg:province":"Barcelona",
    "wof:name":"Boix Martorell Jose",
    "wof:placetype":"venue"
},
  "geometry": {"coordinates":[2.10257411,41.3722267151],"type":"Point"}
}