{
  "type": "Feature",
  "properties": {
    "addr:full":"Trva Colorado Del, S/n Torremolinos M\u00e1laga 29620",
    "addr:housenumber":"/ n",
    "addr:postcode":"29620",
    "addr:street":"Trva Colorado Del S;Ma\u0301Laga",
    "iso:country":"ES",
    "sg:address":"Trva Colorado Del, S/n",
    "sg:city":"Torremolinos",
    "sg:orig_category":"Asociaciones Y Clubs Deportivos",
    "sg:phone":"+34 952 38 05 14",
    "sg:postcode":"29620",
    "sg:province":"M\u00e1laga",
    "wof:name":"Gonzalez Narvaez Cristina",
    "wof:placetype":"venue"
},
  "geometry": {"coordinates":[-4.5160393715,36.6265563965],"type":"Point"}
}