{
  "type": "Feature",
  "properties": {
    "addr:full":"Calle de Virgen Blanca, 3 Granada Granada 18004",
    "addr:housenumber":"3",
    "addr:postcode":"18004",
    "addr:street":"Calle De Virgen Blanca",
    "iso:country":"ES",
    "sg:address":"Calle de Virgen Blanca, 3",
    "sg:city":"Granada",
    "sg:orig_category":"Inmobiliaria (agencias)",
    "sg:phone":"+34 958 53 68 88",
    "sg:postcode":"18004",
    "sg:province":"Granada",
    "wof:name":"Frai Desarrollos Inmobiliarios S.l.",
    "wof:placetype":"venue"
},
  "geometry": {"coordinates":[-3.6072390079,37.1703186035],"type":"Point"}
}