{
  "type": "Feature",
  "properties": {
    "iso:country":"ES",
    "sg:address":"Calle de Virgen De La Soledad, 26",
    "sg:city":"Guadalajara",
    "sg:orig_category":"Contenedores (mercanc\u00cdas)",
    "sg:phone":"+34 949 22 14 32",
    "sg:postcode":"19003",
    "sg:province":"Guadalajara",
    "wof:name":"Gomez Diaz Marcelino",
    "wof:placetype":"venue"
},
  "geometry": {"coordinates":[-3.1650140285,40.62682724],"type":"Point"}
}