{
  "type": "Feature",
  "properties": {
    "iso:country":"ES",
    "sg:address":"Calle de Real, 16",
    "sg:city":"Parla",
    "sg:orig_category":"Asesor\u00cdas Y Estudios Financieros",
    "sg:phone":"+34 916 64 40 90",
    "sg:postcode":"28980",
    "sg:province":"Madrid",
    "wof:name":"Citifin S.a. E.f.c.",
    "wof:placetype":"venue"
},
  "geometry": {"coordinates":[-3.7706708908,40.2371902466],"type":"Point"}
}