{
  "type": "Feature",
  "properties": {
    "iso:country":"ES",
    "sg:address":"Carr Centre, 8",
    "sg:city":"Alpicat",
    "sg:orig_category":"Peluquer\u00cdas, Peluquer\u00cda Mixta",
    "sg:phone":"+34 973 73 61 10",
    "sg:postcode":"25110",
    "sg:province":"Lleida",
    "wof:name":"Teresa I Rosa Scp",
    "wof:placetype":"venue"
},
  "geometry": {"coordinates":[0.5297340155,41.6597290039],"type":"Point"}
}