{
  "type": "Feature",
  "properties": {
    "addr:full":"Carrer de Espronceda, 267 Barcelona Barcelona 08018",
    "addr:housenumber":"267",
    "addr:postcode":"08018",
    "addr:street":"Carrer De Espronceda",
    "iso:country":"ES",
    "sg:address":"Carrer de Espronceda, 267",
    "sg:city":"Barcelona",
    "sg:orig_category":"Estancos",
    "sg:phone":"+34 933 08 98 85",
    "sg:postcode":"08018",
    "sg:province":"Barcelona",
    "wof:name":"Catasus Lacruz Maria",
    "wof:placetype":"venue"
},
  "geometry": {"coordinates":[2.1944470406,41.4128723145],"type":"Point"}
}