{
  "type": "Feature",
  "properties": {
    "addr:full":"Cami Cabanes, S/n Javea Alicante 03730",
    "addr:housenumber":"s / n",
    "addr:postcode":"03730",
    "addr:street":"Cabanes",
    "iso:country":"ES",
    "sg:address":"Cami Cabanes, S/n",
    "sg:city":"Javea",
    "sg:orig_category":"Semiller\u00cdas",
    "sg:phone":"+34 965 79 56 11",
    "sg:postcode":"03730",
    "sg:province":"Alicante",
    "wof:name":"Tormos Buigues Antonio",
    "wof:placetype":"venue"
},
  "geometry": {"coordinates":[0.1175979972,38.7742004395],"type":"Point"}
}