{
  "type": "Feature",
  "properties": {
    "iso:country":"ES",
    "sg:address":"Carr H, S/n",
    "sg:city":"Pont-xetmar",
    "sg:orig_category":"Rectificaci\u00d3n, Mecanizado, Fresado",
    "sg:phone":"+34 972 59 41 71",
    "sg:postcode":"17844",
    "sg:province":"Girona",
    "wof:name":"Tallers Panday S.l.",
    "wof:placetype":"venue"
},
  "geometry": {"coordinates":[2.8163619041,42.0891227722],"type":"Point"}
}