{
  "type": "Feature",
  "properties": {
    "addr:full":"Avda Reina Victoria, 27 Madrid Madrid 28003",
    "addr:housenumber":"27",
    "addr:postcode":"madrid;28003",
    "addr:street":"Avda Reina Victoria",
    "iso:country":"ES",
    "sg:address":"Avda Reina Victoria, 27",
    "sg:city":"Madrid",
    "sg:orig_category":"Comercio De Piezas De Recambio Y De Accesorios De Veh\u00cdculos, Veh\u00cdculos Industriales",
    "sg:phone":"+34 915 54 52 00",
    "sg:postcode":"28003",
    "sg:province":"Madrid",
    "sg:website":"www.donparabrisas.es",
    "wof:name":"Auto Cristalerias S. A.",
    "wof:placetype":"venue"
},
  "geometry": {"coordinates":[-3.7095160484,40.4469566345],"type":"Point"}
}