{
  "type": "Feature",
  "properties": {
    "addr:full":"Avgd Ausias March, 13 Alboraya Valencia 46120",
    "addr:housenumber":"13",
    "addr:postcode":"46120",
    "addr:street":"March",
    "iso:country":"ES",
    "sg:address":"Avgd Ausias March, 13",
    "sg:city":"Alboraya",
    "sg:orig_category":"Inmobiliaria (agencias)",
    "sg:phone":"+34 961 85 13 66",
    "sg:postcode":"46120",
    "sg:province":"Valencia",
    "wof:name":"Gestiones Administrativas Y Servicios Inmobiliarios Mar S.l.",
    "wof:placetype":"venue"
},
  "geometry": {"coordinates":[-0.3518792987,39.4962501526],"type":"Point"}
}