{
  "type": "Feature",
  "properties": {
    "addr:full":"Carr Cipriano Garijo, 6 Eivissa Islas Baleares 07800",
    "addr:housenumber":"6",
    "addr:postcode":"07800",
    "addr:street":"Carr Cipriano Garijo",
    "iso:country":"ES",
    "sg:address":"Carr Cipriano Garijo, 6",
    "sg:city":"Eivissa",
    "sg:orig_category":"Alimentaci\u00d3n General (al Por Menor)",
    "sg:phone":"+34 971 31 02 19",
    "sg:postcode":"07800",
    "sg:province":"Islas Baleares",
    "wof:name":"Manuel Mari Juan",
    "wof:placetype":"venue"
},
  "geometry": {"coordinates":[1.4397599697,38.9092216492],"type":"Point"}
}