{
  "type": "Feature",
  "properties": {
    "addr:full":"Urb V Centenario, S/n Jerez De Los Caballeros Badajoz 06380",
    "addr:housenumber":"s / n",
    "addr:postcode":"06380",
    "addr:street":"Urb V Centenario",
    "iso:country":"ES",
    "sg:address":"Urb V Centenario, S/n",
    "sg:city":"Jerez De Los Caballeros",
    "sg:orig_category":"Electricidad: Instaladores",
    "sg:phone":"+34 924 75 19 00",
    "sg:postcode":"06380",
    "sg:province":"Badajoz",
    "wof:name":"Instalaciones Jerezanas S.coop.",
    "wof:placetype":"venue"
},
  "geometry": {"coordinates":[-6.7708559036,38.3294639587],"type":"Point"}
}