{
  "type": "Feature",
  "properties": {
    "iso:country":"ES",
    "sg:address":"Calle de Llamargos (los), 5",
    "sg:city":"Azadinos",
    "sg:classifiers":[
        {
            "category":"Manufacturing",
            "subcategory":"Building Materials",
            "type":"Manufacturing & Wholesale Goods"
        }
    ],
    "sg:phone":"+34 987 28 06 78",
    "sg:postcode":"24121",
    "sg:province":"Le\u00f3n",
    "sg:tags":[
        "de",
        "industrial",
        "alquiler"
    ],
    "wof:name":"Paramo Fonseca Jose Luis",
    "wof:placetype":"venue"
},
  "geometry": {"coordinates":[-5.6219902039,42.6353607178],"type":"Point"}
}