{
  "type": "Feature",
  "properties": {
    "addr:full":"Carr Virgen Del Carmen, 22 Eliana Valencia 46183",
    "addr:housenumber":"22",
    "addr:postcode":"46183",
    "addr:street":"Carr Virgen Del Carmen",
    "iso:country":"ES",
    "sg:address":"Carr Virgen Del Carmen, 22",
    "sg:city":"Eliana",
    "sg:orig_category":"Asesor\u00cda Fiscal Y Jur\u00cddica",
    "sg:phone":"+34 962 74 05 52",
    "sg:postcode":"46183",
    "sg:province":"Valencia",
    "wof:name":"Paricio Guillen Juan",
    "wof:placetype":"venue"
},
  "geometry": {"coordinates":[-0.5299299955,39.567325592],"type":"Point"}
}