{
  "type": "Feature",
  "properties": {
    "iso:country":"ES",
    "sg:address":"Calle de Virgen De Las Vi\u00d1as, 7",
    "sg:city":"Madrid",
    "sg:orig_category":"Cervecer\u00cdas",
    "sg:phone":"+34 913 31 68 82",
    "sg:postcode":"28031",
    "sg:province":"Madrid",
    "wof:name":"Valenciano Del Horno Joaquin",
    "wof:placetype":"venue"
},
  "geometry": {"coordinates":[-3.6057178974,40.3811302185],"type":"Point"}
}