{
  "type": "Feature",
  "properties": {
    "iso:country":"ES",
    "sg:address":"Carrer de Gabriel Carbonell, 33",
    "sg:city":"Palma",
    "sg:orig_category":"Colchones (fabricaci\u00d3n, Al Por Mayor, Al Por Menor)",
    "sg:phone":"+34 971 27 80 90",
    "sg:postcode":"07008",
    "sg:province":"Islas Baleares",
    "wof:name":"Martinez Martinez Simon",
    "wof:placetype":"venue"
},
  "geometry": {"coordinates":[2.6697499752,39.5743484497],"type":"Point"}
}