{
  "type": "Feature",
  "properties": {
    "addr:full":"P. Garcia De Najera, 2 Iru\u00f1a Navarra 31008",
    "addr:housenumber":"2",
    "addr:postcode":"31008",
    "addr:street":"P. Garcia De Najera",
    "iso:country":"ES",
    "sg:address":"P. Garcia De Najera, 2",
    "sg:city":"Iru\u00f1a",
    "sg:orig_category":"Iglesia Cat\u00d3lica",
    "sg:phone":"+34 948 25 95 97",
    "sg:postcode":"31008",
    "sg:province":"Navarra",
    "wof:name":"Parroquia Corpus Christi",
    "wof:placetype":"venue"
},
  "geometry": {"coordinates":[-1.6601779461,42.8098068237],"type":"Point"}
}