{
  "type": "Feature",
  "properties": {
    "iso:country":"ES",
    "sg:address":"Calle de Sor Maria De San Jose, 1",
    "sg:city":"Avila",
    "sg:orig_category":"Arquitectos",
    "sg:phone":"+34 920 25 56 77",
    "sg:postcode":"05001",
    "sg:province":"\u00c1vila",
    "wof:name":"Vinuesa I\u00f1iguez Fernando",
    "wof:placetype":"venue"
},
  "geometry": {"coordinates":[-4.6940908432,40.6546707153],"type":"Point"}
}