{
  "type": "Feature",
  "properties": {
    "addr:full":"Avda Cairo (del), 1 Cordoba C\u00f3rdoba 14014",
    "addr:housenumber":"1",
    "addr:postcode":"14014",
    "addr:street":"Avda Cairo Del;Co\u0301Rdoba",
    "iso:country":"ES",
    "sg:address":"Avda Cairo (del), 1",
    "sg:city":"Cordoba",
    "sg:orig_category":"Electromec\u00c1nica",
    "sg:phone":"+34 957 43 90 65",
    "sg:postcode":"14014",
    "sg:province":"C\u00f3rdoba",
    "wof:name":"Infante Ruiz Antonio",
    "wof:placetype":"venue"
},
  "geometry": {"coordinates":[-4.7559142113,37.8921737671],"type":"Point"}
}