{
  "type": "Feature",
  "properties": {
    "iso:country":"ES",
    "sg:address":"Calle de Carreterica Posete, 47",
    "sg:city":"Cieza",
    "sg:orig_category":"Servicios De Telecomunicaciones",
    "sg:phone":"+34 968 76 25 12",
    "sg:postcode":"30530",
    "sg:province":"Murcia",
    "wof:name":"Antena 3 De Radio S. A.",
    "wof:placetype":"venue"
},
  "geometry": {"coordinates":[-1.4197738171,38.2371902466],"type":"Point"}
}