{
  "type": "Feature",
  "properties": {
    "addr:full":"Calle de Santana, 15 Azuaga Badajoz 06920",
    "addr:housenumber":"15",
    "addr:postcode":"06920",
    "addr:street":"Calle De Santana",
    "iso:country":"ES",
    "sg:address":"Calle de Santana, 15",
    "sg:city":"Azuaga",
    "sg:orig_category":"Doctores En Medicina",
    "sg:phone":"+34 924 89 24 42",
    "sg:postcode":"06920",
    "sg:province":"Badajoz",
    "wof:name":"Jimenez Rivera Valentin",
    "wof:placetype":"venue"
},
  "geometry": {"coordinates":[-5.6791930199,38.2547683716],"type":"Point"}
}