{
  "type": "Feature",
  "properties": {
    "iso:country":"ES",
    "sg:address":"Calle de Benidorm, 24",
    "sg:city":"Agost",
    "sg:orig_category":"Peluqueros: De Se\u00d1oras",
    "sg:phone":"+34 965 69 19 86",
    "sg:postcode":"03698",
    "sg:province":"Alicante",
    "wof:name":"Molla Berenguer Maria Jose",
    "wof:placetype":"venue"
},
  "geometry": {"coordinates":[-0.635586977,38.4357452393],"type":"Point"}
}