{
  "type": "Feature",
  "properties": {
    "iso:country":"ES",
    "sg:address":"Calle de Virgen De Los Peligros, 3",
    "sg:city":"Madrid",
    "sg:orig_category":"Agencias De Viajes",
    "sg:phone":"+34 915 31 11 00",
    "sg:postcode":"28013",
    "sg:province":"Madrid",
    "wof:name":"Gullivers Travel Associates S.a.",
    "wof:placetype":"venue"
},
  "geometry": {"coordinates":[-3.6996688843,40.4183044434],"type":"Point"}
}