{
  "type": "Feature",
  "properties": {
    "addr:full":"C/ Sabadell, 10 Alcoi Alicante 03804",
    "addr:housenumber":"10",
    "addr:postcode":"03804",
    "addr:street":"C / Sabadell",
    "iso:country":"ES",
    "sg:address":"C/ Sabadell, 10",
    "sg:city":"Alcoi",
    "sg:orig_category":"Farmacias",
    "sg:phone":"+34 965 33 12 48",
    "sg:postcode":"03804",
    "sg:province":"Alicante",
    "wof:name":"Duart Bosch Maria",
    "wof:placetype":"venue"
},
  "geometry": {"coordinates":[-0.4677209854,38.7091331482],"type":"Point"}
}