{
  "type": "Feature",
  "properties": {
    "addr:full":"Avda Esteiro, 57 Ferrol A Coru\u00f1a 15403",
    "addr:housenumber":"57",
    "addr:postcode":"15403",
    "addr:street":"Avda Esteiro;A Corun\u0303A",
    "iso:country":"ES",
    "sg:address":"Avda Esteiro, 57",
    "sg:city":"Ferrol",
    "sg:orig_category":"Asesor\u00cda Fiscal Y Jur\u00cddica",
    "sg:phone":"+34 981 35 97 04",
    "sg:postcode":"15403",
    "sg:province":"A Coru\u00f1a",
    "wof:name":"Sociedade Cooperativa Galega De Gestion Administrativa De Empresas",
    "wof:placetype":"venue"
},
  "geometry": {"coordinates":[-8.2239189148,43.4840011597],"type":"Point"}
}