{
  "type": "Feature",
  "properties": {
    "addr:full":"Carr Nou, 4 Girona Girona 17001",
    "addr:housenumber":"4",
    "addr:postcode":"17001",
    "addr:street":"Carr Nou",
    "iso:country":"ES",
    "sg:address":"Carr Nou, 4",
    "sg:city":"Girona",
    "sg:orig_category":"Psic\u00d3logos",
    "sg:phone":"+34 972 21 34 99",
    "sg:postcode":"17001",
    "sg:province":"Girona",
    "wof:name":"Ara Psicologia Gestalt Y Relacion",
    "wof:placetype":"venue"
},
  "geometry": {"coordinates":[2.8224842548,41.9827270508],"type":"Point"}
}