{
  "type": "Feature",
  "properties": {
    "addr:full":"C/ Sant Mateu, De, 2 S. Antoni Portmany Islas Baleares 07820",
    "addr:postcode":"07820",
    "addr:street":"C / Sant Mateu De 2 S. Antoni Portmany",
    "iso:country":"ES",
    "sg:address":"C/ Sant Mateu, De, 2",
    "sg:city":"S. Antoni Portmany",
    "sg:orig_category":"Peluquer\u00cdas, Peluquer\u00cda Mixta",
    "sg:phone":"+34 971 34 26 08",
    "sg:postcode":"07820",
    "sg:province":"Islas Baleares",
    "wof:name":"Sala Rosello Ines",
    "wof:placetype":"venue"
},
  "geometry": {"coordinates":[1.5188339949,39.1094055176],"type":"Point"}
}