{
  "type": "Feature",
  "properties": {
    "addr:full":"Madera, 9 Carranque Toledo 45216",
    "addr:housenumber":"9",
    "addr:postcode":"45216",
    "addr:street":"Madera",
    "iso:country":"ES",
    "sg:address":"Madera, 9",
    "sg:city":"Carranque",
    "sg:orig_category":"Transporte En General",
    "sg:phone":"+34 925 54 44 53",
    "sg:postcode":"45216",
    "sg:province":"Toledo",
    "wof:name":"Mundo Hostelero S. L.",
    "wof:placetype":"venue"
},
  "geometry": {"coordinates":[-3.8871788979,40.1836738586],"type":"Point"}
}