{
  "type": "Feature",
  "properties": {
    "iso:country":"ES",
    "sg:address":"Calle de Galicia, 4",
    "sg:city":"Dos Hermanas",
    "sg:orig_category":"Mec\u00c1nico Del Autom\u00d3vil",
    "sg:phone":"+34 954 72 13 96",
    "sg:postcode":"41700",
    "sg:province":"Sevilla",
    "wof:name":"Bando Ortega Francisco Manuel",
    "wof:placetype":"venue"
},
  "geometry": {"coordinates":[-5.9247999191,37.2769699097],"type":"Point"}
}