{
  "type": "Feature",
  "properties": {
    "iso:country":"ES",
    "sg:address":"Pase Rosa, 144",
    "sg:city":"Toledo",
    "sg:orig_category":"Ense\u00d1anza Variada",
    "sg:phone":"+34 925 25 02 00",
    "sg:postcode":"45006",
    "sg:province":"Toledo",
    "wof:name":"Sif Servicios Integrales De Formacion S.l.",
    "wof:placetype":"venue"
},
  "geometry": {"coordinates":[-4.0053992271,39.860748291],"type":"Point"}
}