{
  "type": "Feature",
  "properties": {
    "iso:country":"ES",
    "sg:address":"Calle de Marques De Leis, 15",
    "sg:city":"Madrid",
    "sg:orig_category":"Servicios De Telecomunicaciones",
    "sg:phone":"+34 915 67 00 66",
    "sg:postcode":"28020",
    "sg:province":"Madrid",
    "wof:name":"Dominguez Cobo Ramiro",
    "wof:placetype":"venue"
},
  "geometry": {"coordinates":[-3.6993060112,40.4576950073],"type":"Point"}
}