{
  "type": "Feature",
  "properties": {
    "addr:full":"Carrer de Rubens, 15 Barcelona Barcelona 08023",
    "addr:housenumber":"15",
    "addr:postcode":"08023",
    "addr:street":"Carrer De Rubens",
    "iso:country":"ES",
    "sg:address":"Carrer de Rubens, 15",
    "sg:city":"Barcelona",
    "sg:orig_category":"Agua",
    "sg:phone":"+34 932 85 23 90",
    "sg:postcode":"08023",
    "sg:province":"Barcelona",
    "sg:website":"www.gasmedi.com",
    "wof:name":"Gasmedi 2000 S.a.u.",
    "wof:placetype":"venue"
},
  "geometry": {"coordinates":[2.1455550194,41.4147224426],"type":"Point"}
}