{
  "type": "Feature",
  "properties": {
    "iso:country":"ES",
    "sg:address":"Calle de San Jose, 2",
    "sg:city":"Nerja",
    "sg:orig_category":"Asesor\u00cda Fiscal Y Jur\u00cddica",
    "sg:phone":"+34 952 52 28 00",
    "sg:postcode":"29780",
    "sg:province":"M\u00e1laga",
    "wof:name":"Rojo Moyano Jose Francisco",
    "wof:placetype":"venue"
},
  "geometry": {"coordinates":[-3.8761479855,36.7475166321],"type":"Point"}
}