{
  "type": "Feature",
  "properties": {
    "iso:country":"ES",
    "sg:address":"Calle de Manuel Robles Pintado, S/n",
    "sg:city":"Tudela",
    "sg:orig_category":"Herboristas (al Por Menor)",
    "sg:phone":"+34 948 41 05 47",
    "sg:postcode":"31500",
    "sg:province":"Navarra",
    "wof:name":"Garcia Gracia Ana Ines",
    "wof:placetype":"venue"
},
  "geometry": {"coordinates":[-1.6050390005,42.0561599731],"type":"Point"}
}