{
  "type": "Feature",
  "properties": {
    "iso:country":"ES",
    "sg:address":"Carrer de Proven\u00c7a, 327",
    "sg:city":"Barcelona",
    "sg:orig_category":"Asociaciones Humanitarias, De Cooperaci\u00d3n, De Acci\u00d3n Social",
    "sg:phone":"+34 934 57 90 03",
    "sg:postcode":"08037",
    "sg:province":"Barcelona",
    "wof:name":"Asociacion Barcelonesa De Laringectomizados",
    "wof:placetype":"venue"
},
  "geometry": {"coordinates":[2.167545557,41.3993263245],"type":"Point"}
}