{
  "type": "Feature",
  "properties": {
    "iso:country":"ES",
    "sg:address":"Calle de Hermanos Alvarez Quintero, 6",
    "sg:city":"Castilleja De Guzman",
    "sg:orig_category":"Psic\u00d3logos",
    "sg:phone":"+34 955 72 97 36",
    "sg:postcode":"41908",
    "sg:province":"Sevilla",
    "wof:name":"Tocino Diaz Cristina",
    "wof:placetype":"venue"
},
  "geometry": {"coordinates":[-6.0556759834,37.3851127625],"type":"Point"}
}