{
  "type": "Feature",
  "properties": {
    "addr:full":"Calle de Doctor Muguerza Bernal, S/n Malaga M\u00e1laga 29011",
    "addr:housenumber":"s",
    "addr:postcode":"29011",
    "addr:street":"Calle De Doctor Muguerza Bernal;/ N;Ma\u0301Laga",
    "iso:country":"ES",
    "sg:address":"Calle de Doctor Muguerza Bernal, S/n",
    "sg:city":"Malaga",
    "sg:orig_category":"Electrodom\u00c9sticos (al Por Menor)",
    "sg:phone":"+34 952 28 12 97",
    "sg:postcode":"29011",
    "sg:province":"M\u00e1laga",
    "wof:name":"Fernandez Martin Francisco Javier",
    "wof:placetype":"venue"
},
  "geometry": {"coordinates":[-4.4280190468,36.7402763367],"type":"Point"}
}