{
  "type": "Feature",
  "properties": {
    "iso:country":"ES",
    "sg:address":"Calle de Impresores, 35",
    "sg:city":"Getafe",
    "sg:orig_category":"Transportes Por Carretera: Lotes Completos, Mercanc\u00cdas Diversas",
    "sg:phone":"+34 916 83 53 79",
    "sg:postcode":"28906",
    "sg:province":"Madrid",
    "wof:name":"Servidist R Y L S.l.",
    "wof:placetype":"venue"
},
  "geometry": {"coordinates":[-3.6977140903,40.3106384277],"type":"Point"}
}