{
  "type": "Feature",
  "properties": {
    "iso:country":"ES",
    "sg:address":"Uriz, S/n",
    "sg:city":"Lakuntza",
    "sg:orig_category":"Empresas De Carpinter\u00cda De Madera",
    "sg:phone":"+34 948 57 60 65",
    "sg:postcode":"31830",
    "sg:province":"Navarra",
    "wof:name":"Gamboa Miranda Nicanor",
    "wof:placetype":"venue"
},
  "geometry": {"coordinates":[-2.0240540504,42.922328949],"type":"Point"}
}