{
  "type": "Feature",
  "properties": {
    "addr:full":"Calle de Zaragoza, 3 Calamocha Teruel 44200",
    "addr:housenumber":"3",
    "addr:postcode":"44200",
    "addr:street":"Calle De Zaragoza",
    "iso:country":"ES",
    "sg:address":"Calle de Zaragoza, 3",
    "sg:city":"Calamocha",
    "sg:orig_category":"T\u00c9cnicos Veterinarios",
    "sg:phone":"+34 978 73 02 36",
    "sg:postcode":"44200",
    "sg:province":"Teruel",
    "wof:name":"Yague Leon Javier",
    "wof:placetype":"venue"
},
  "geometry": {"coordinates":[-1.2966983318,40.9209785461],"type":"Point"}
}