{
  "type": "Feature",
  "properties": {
    "iso:country":"ES",
    "sg:address":"Ctra Cordoba-valencia, Km. 0169,0",
    "sg:city":"Villacarrillo",
    "sg:orig_category":"Producci\u00d3n, Venta De Productos De Agricultura Biol\u00d3gica",
    "sg:phone":"+34 953 12 81 98",
    "sg:postcode":"23300",
    "sg:province":"Ja\u00e9n",
    "wof:name":"Calancha S. A.",
    "wof:placetype":"venue"
},
  "geometry": {"coordinates":[-3.0878789425,38.1153488159],"type":"Point"}
}