{
  "type": "Feature",
  "properties": {
    "addr:full":"Navarreria, 15 Iru\u00f1a Navarra 31001",
    "addr:housenumber":"15",
    "addr:postcode":"31001",
    "addr:street":"Navarreria",
    "iso:country":"ES",
    "sg:address":"Navarreria, 15",
    "sg:city":"Iru\u00f1a",
    "sg:orig_category":"Asociaciones, Organismos Culturales Y Socioeducativos",
    "sg:phone":"+34 948 22 47 57",
    "sg:postcode":"31001",
    "sg:province":"Navarra",
    "wof:name":"Asociacion Cultural Biltzarra",
    "wof:placetype":"venue"
},
  "geometry": {"coordinates":[-1.6429526806,42.8191680908],"type":"Point"}
}