{
  "type": "Feature",
  "properties": {
    "iso:country":"ES",
    "sg:address":"C/ Marques D'asprella, 41",
    "sg:city":"Elche",
    "sg:orig_category":"Inform\u00c1tica: Soportes De Informaci\u00d3n, Suministros & Accesorios",
    "sg:phone":"+34 965 46 85 14",
    "sg:postcode":"03201",
    "sg:province":"Alicante",
    "wof:name":"Suresdata Complementos Informaticos S.l",
    "wof:placetype":"venue"
},
  "geometry": {"coordinates":[-0.7026640177,38.2681045532],"type":"Point"}
}