{
  "type": "Feature",
  "properties": {
    "iso:country":"ES",
    "sg:address":"Barr Intzuntza, 8",
    "sg:city":"Intzuntza",
    "sg:orig_category":"Carnicer\u00cdas, Carnicer\u00cdas",
    "sg:phone":"+34 946 31 33 80",
    "sg:postcode":"48330",
    "sg:province":"Vizcaya",
    "wof:name":"Atucha Echevarria Antonio",
    "wof:placetype":"venue"
},
  "geometry": {"coordinates":[-2.6983869076,43.2204284668],"type":"Point"}
}