{
  "type": "Feature",
  "properties": {
    "iso:country":"ES",
    "sg:address":"C/ Pau Ferran, 13",
    "sg:city":"Tarrega",
    "sg:orig_category":"Comercio De Cuadros, L\u00c1minas Y Reproducciones De Obras De Arte",
    "sg:phone":"+34 973 31 31 28",
    "sg:postcode":"25300",
    "sg:province":"Lleida",
    "sg:website":"www.eurocuadro.com",
    "wof:name":"Eurocuadro S.l.",
    "wof:placetype":"venue"
},
  "geometry": {"coordinates":[1.1410850286,41.6482696533],"type":"Point"}
}