{
  "type": "Feature",
  "properties": {
    "iso:country":"ES",
    "sg:address":"Calle de Santo Domingo, 100",
    "sg:city":"Sanlucar De Barrameda",
    "sg:orig_category":"Bazares, Art\u00cdculos De Limpieza Y De Cocina (al Por Menor)",
    "sg:phone":"+34 956 36 33 17",
    "sg:postcode":"11540",
    "sg:province":"C\u00e1diz",
    "wof:name":"Sarrion Diaz Alvaro De Guzman",
    "wof:placetype":"venue"
},
  "geometry": {"coordinates":[-6.3489689827,36.7812614441],"type":"Point"}
}