{
  "type": "Feature",
  "properties": {
    "addr:full":"Plaz Espa\u00d1a, S/n Onda Castell\u00f3n 12200",
    "addr:housenumber":"s / n",
    "addr:postcode":"12200",
    "addr:street":"Plaz Espan\u0303A;Castello\u0301N",
    "iso:country":"ES",
    "sg:address":"Plaz Espa\u00d1a, S/n",
    "sg:city":"Onda",
    "sg:orig_category":"Reposter\u00cdas",
    "sg:phone":"+34 964 60 36 10",
    "sg:postcode":"12200",
    "sg:province":"Castell\u00f3n",
    "wof:name":"Perez Perez Mari Carmen",
    "wof:placetype":"venue"
},
  "geometry": {"coordinates":[-0.2620640099,39.9651794434],"type":"Point"}
}