{
  "type": "Feature",
  "properties": {
    "iso:country":"ES",
    "sg:address":"Calle de Montreal, 63",
    "sg:city":"Valladolid",
    "sg:orig_category":"Clubes, Asociaciones De Ocio",
    "sg:phone":"+34 983 27 28 62",
    "sg:postcode":"47008",
    "sg:province":"Valladolid",
    "wof:name":"Multipark Espectaculos S.l.",
    "wof:placetype":"venue"
},
  "geometry": {"coordinates":[-4.7643270493,41.6173591614],"type":"Point"}
}