{
  "type": "Feature",
  "properties": {
    "addr:full":"Calle de Alcalde Juan Filter, 10 Ca\u00e7ada Rosal Sevilla 41439",
    "addr:housenumber":"10",
    "addr:postcode":"41439",
    "addr:street":"Calle De Alcalde Juan Filter;Rosal",
    "iso:country":"ES",
    "sg:address":"Calle de Alcalde Juan Filter, 10",
    "sg:city":"Ca\u00e7ada Rosal",
    "sg:classifiers":[
        {
            "category":"Communications",
            "type":"Services"
        }
    ],
    "sg:phone":"+34 954 83 91 77",
    "sg:postcode":"41439",
    "sg:province":"Sevilla",
    "sg:tags":[
        "televisiones",
        "y",
        "radio"
    ],
    "wof:name":"Ayuntamiento De Ca\u00d1ada Del Rosal",
    "wof:placetype":"venue"
},
  "geometry": {"coordinates":[-5.9962949753,37.3826408386],"type":"Point"}
}