{
  "type": "Feature",
  "properties": {
    "iso:country":"ES",
    "sg:address":"Carrer de Roger De Flor, 157",
    "sg:city":"Barcelona",
    "sg:orig_category":"Transporte En General",
    "sg:phone":"+34 932 31 99 44",
    "sg:postcode":"08013",
    "sg:province":"Barcelona",
    "wof:name":"Barcelonesa De Guix I Escaiola S.l.",
    "wof:placetype":"venue"
},
  "geometry": {"coordinates":[2.173470974,41.3979530334],"type":"Point"}
}