{
  "type": "Feature",
  "properties": {
    "iso:country":"ES",
    "sg:address":"Avda Duque De Tamames, 17",
    "sg:city":"Orihuela",
    "sg:classifiers":[
        {
            "category":"Autos & Motor Vehicles",
            "subcategory":"Automobile Sales",
            "type":"Retail Goods"
        }
    ],
    "sg:phone":"+34 965 30 13 32",
    "sg:postcode":"03300",
    "sg:province":"Alicante",
    "wof:name":"Pertegal Y Valero S.l.",
    "wof:placetype":"venue"
},
  "geometry": {"coordinates":[-0.9460070133,38.0817451477],"type":"Point"}
}