{
  "type": "Feature",
  "properties": {
    "iso:country":"ES",
    "sg:address":"Carr Cautiva, De La, 14",
    "sg:city":"Barri De Porta",
    "sg:orig_category":"Complementos De Vestir (al Por Menor)",
    "sg:phone":"+34 961 54 14 78",
    "sg:postcode":"46930",
    "sg:province":"Valencia",
    "wof:name":"Abanicos Clavijo S.l.",
    "wof:placetype":"venue"
},
  "geometry": {"coordinates":[-0.456952,39.477589],"type":"Point"}
}