{
  "type": "Feature",
  "properties": {
    "addr:full":"Calle de General Moscardo, 5 Talavera Reina Toledo 45600",
    "addr:housenumber":"5",
    "addr:postcode":"45600",
    "addr:street":"Calle De General Moscardo",
    "iso:country":"ES",
    "sg:address":"Calle de General Moscardo, 5",
    "sg:city":"Talavera Reina",
    "sg:orig_category":"Radiocomunicaciones, Telefon\u00cda M\u00d3vil, Radiomensajer\u00cda: Servicios, Comercializaci\u00d3n",
    "sg:phone":"+34 925 72 12 19",
    "sg:postcode":"45600",
    "sg:province":"Toledo",
    "wof:name":"Telesantos Comunicaciones S.l.",
    "wof:placetype":"venue"
},
  "geometry": {"coordinates":[-4.8207998276,39.9631309509],"type":"Point"}
}