{
  "type": "Feature",
  "properties": {
    "iso:country":"ES",
    "sg:address":"Pl Chapi, 2",
    "sg:city":"Crevillent",
    "sg:orig_category":"Farmacias",
    "sg:phone":"+34 965 40 09 43",
    "sg:postcode":"03330",
    "sg:province":"Alicante",
    "wof:name":"Candela Pastor Josefa",
    "wof:placetype":"venue"
},
  "geometry": {"coordinates":[-0.8115000129,38.2481994629],"type":"Point"}
}