{
  "type": "Feature",
  "properties": {
    "iso:country":"ES",
    "sg:address":"Urb San Jeronimo, S/n",
    "sg:city":"San Jeronimo",
    "sg:orig_category":"Bisuter\u00cda, Joyer\u00cda, Relojer\u00cda (al Por Menor)",
    "sg:phone":"+34 922 32 16 43",
    "sg:postcode":"38312",
    "sg:province":"Santa Cruz De Tenerife",
    "wof:name":"Morales Cano Francisco Jose",
    "wof:placetype":"venue"
},
  "geometry": {"coordinates":[-16.5448322296,28.3948001862],"type":"Point"}
}