{
  "type": "Feature",
  "properties": {
    "addr:full":"Pg Gran Passeig Ronda, 168 Lleida Lleida 25008",
    "addr:housenumber":"168",
    "addr:postcode":"25008",
    "addr:street":"Pg Gran Passeig Ronda",
    "iso:country":"ES",
    "sg:address":"Pg Gran Passeig Ronda, 168",
    "sg:city":"Lleida",
    "sg:orig_category":"Urbanistas",
    "sg:phone":"+34 973 24 70 98",
    "sg:postcode":"25008",
    "sg:province":"Lleida",
    "wof:name":"Leridana De Arquitectura Internacional S.l.",
    "wof:placetype":"venue"
},
  "geometry": {"coordinates":[0.6224089861,41.6248855591],"type":"Point"}
}