{
  "type": "Feature",
  "properties": {
    "iso:country":"ES",
    "sg:address":"Agricultores (p I Huerto Ordo\u00f1ez), 2",
    "sg:city":"Arahal",
    "sg:orig_category":"Conservas De Legumbres (fabricaci\u00d3n, Al Por Mayor)",
    "sg:phone":"+34 955 84 24 32",
    "sg:postcode":"41600",
    "sg:province":"Sevilla",
    "wof:name":"Aceitunas Sevillanas Cabello S.l.",
    "wof:placetype":"venue"
},
  "geometry": {"coordinates":[-5.5428285599,37.2640991211],"type":"Point"}
}