{
  "type": "Feature",
  "properties": {
    "addr:full":"Calle de Reinante, 16 Ribadeo Lugo 27700",
    "addr:housenumber":"16",
    "addr:postcode":"27700",
    "addr:street":"Calle De Reinante",
    "iso:country":"ES",
    "sg:address":"Calle de Reinante, 16",
    "sg:city":"Ribadeo",
    "sg:orig_category":"Ropa Para Se\u00d1oras (al Por Menor)",
    "sg:phone":"+34 982 12 85 60",
    "sg:postcode":"27700",
    "sg:province":"Lugo",
    "wof:name":"Anaismenia C.b",
    "wof:placetype":"venue"
},
  "geometry": {"coordinates":[-7.0419983864,43.5361938477],"type":"Point"}
}