{
  "type": "Feature",
  "properties": {
    "iso:country":"ES",
    "sg:address":"San Francisco Del Monte, S/n",
    "sg:city":"Villafranca Cordoba",
    "sg:orig_category":"Muebles Y Accesorios Para Cocinas Y Cuartos De Ba\u00d1o (al Por Menor)",
    "sg:phone":"+34 957 19 04 48",
    "sg:postcode":"14420",
    "sg:province":"C\u00f3rdoba",
    "wof:name":"Carpinteria Castro C.b.",
    "wof:placetype":"venue"
},
  "geometry": {"coordinates":[-4.5488638878,37.9624938965],"type":"Point"}
}