{
  "type": "Feature",
  "properties": {
    "addr:full":"Carrer de Bosc De La Torroja, 7 Palleja Barcelona 08780",
    "addr:housenumber":"7",
    "addr:postcode":"08780",
    "addr:street":"Carrer De Bosc De La Torroja",
    "iso:country":"ES",
    "sg:address":"Carrer de Bosc De La Torroja, 7",
    "sg:city":"Palleja",
    "sg:orig_category":"Barcos",
    "sg:phone":"+34 936 63 30 91",
    "sg:postcode":"08780",
    "sg:province":"Barcelona",
    "wof:name":"Iberica Tanker Chartering S.l.",
    "wof:placetype":"venue"
},
  "geometry": {"coordinates":[1.9951119423,41.4181785583],"type":"Point"}
}