{
  "type": "Feature",
  "properties": {
    "iso:country":"ES",
    "sg:address":"Calle de Braulio Navas, 14",
    "sg:city":"Hervas",
    "sg:orig_category":"Iglesia Cat\u00d3lica",
    "sg:phone":"+34 927 48 11 35",
    "sg:postcode":"10700",
    "sg:province":"C\u00e1ceres",
    "wof:name":"Parroquia Nuestra Se\u00f1ora De La Asuncion",
    "wof:placetype":"venue"
},
  "geometry": {"coordinates":[-5.8599319458,40.2729949951],"type":"Point"}
}