{
  "type": "Feature",
  "properties": {
    "iso:country":"ES",
    "sg:address":"Calle de Pilar Garcia, 47",
    "sg:city":"Algaba",
    "sg:orig_category":"Cajas Para Embalar",
    "sg:phone":"+34 955 78 79 73",
    "sg:postcode":"41980",
    "sg:province":"Sevilla",
    "wof:name":"Caja Rural Del Sur Sociedad Cooperativa",
    "wof:placetype":"venue"
},
  "geometry": {"coordinates":[-6.0153942108,37.4607162476],"type":"Point"}
}