{
  "type": "Feature",
  "properties": {
    "iso:country":"ES",
    "sg:address":"Calle de Teodosio, 95",
    "sg:city":"Sevilla",
    "sg:orig_category":"Abogados",
    "sg:phone":"+34 954 37 04 82",
    "sg:postcode":"41002",
    "sg:province":"Sevilla",
    "wof:name":"Delis Martin Manuel",
    "wof:placetype":"venue"
},
  "geometry": {"coordinates":[-5.9970917702,37.3996925354],"type":"Point"}
}