{
  "type": "Feature",
  "properties": {
    "iso:country":"ES",
    "sg:address":"Avd. Teguise, S/n",
    "sg:city":"Costa Teguise",
    "sg:orig_category":"Bancos",
    "sg:phone":"+34 928 59 03 21",
    "sg:postcode":"35509",
    "sg:province":"Las Palmas",
    "sg:website":"www.bancopopular.es",
    "wof:name":"Banco Popular Espa\u00f1ol",
    "wof:placetype":"venue"
},
  "geometry": {"coordinates":[-13.5916891098,28.955160141],"type":"Point"}
}