{
  "type": "Feature",
  "properties": {
    "iso:country":"ES",
    "sg:address":"Rua Matias Lopez, 94",
    "sg:city":"Sarria",
    "sg:orig_category":"Reposter\u00cdas",
    "sg:phone":"+34 982 53 00 63",
    "sg:postcode":"27600",
    "sg:province":"Lugo",
    "wof:name":"Garcia Castro Manuel",
    "wof:placetype":"venue"
},
  "geometry": {"coordinates":[-7.4144887924,42.782081604],"type":"Point"}
}