{
  "type": "Feature",
  "properties": {
    "addr:full":"Calle de Virgen Del Buen Suceso, 10 Cieza Murcia 30530",
    "addr:housenumber":"10",
    "addr:postcode":"30530",
    "addr:street":"Calle De Virgen Del Buen Suceso",
    "iso:country":"ES",
    "sg:address":"Calle de Virgen Del Buen Suceso, 10",
    "sg:city":"Cieza",
    "sg:orig_category":"Quincaller\u00cda (al Por Menor)",
    "sg:phone":"+34 968 76 29 91",
    "sg:postcode":"30530",
    "sg:province":"Murcia",
    "wof:name":"Comercial Alonso Riquelme E Hijos S.l.",
    "wof:placetype":"venue"
},
  "geometry": {"coordinates":[-1.4234509468,38.2377815247],"type":"Point"}
}