{
  "type": "Feature",
  "properties": {
    "iso:country":"ES",
    "sg:address":"Plaz Mayor, 11",
    "sg:city":"Brunete",
    "sg:orig_category":"Cobro De Pr\u00c9stamos",
    "sg:phone":"+34 918 15 83 57",
    "sg:postcode":"28690",
    "sg:province":"Madrid",
    "wof:name":"Hermanos Alonso Polo S.l.",
    "wof:placetype":"venue"
},
  "geometry": {"coordinates":[-3.9982941151,40.405128479],"type":"Point"}
}