{
  "type": "Feature",
  "properties": {
    "addr:full":"Ctra Montcada, 95 Terrassa Barcelona 08221",
    "addr:housenumber":"95",
    "addr:postcode":"08221",
    "addr:street":"Ctra Montcada",
    "iso:country":"ES",
    "sg:address":"Ctra Montcada, 95",
    "sg:city":"Terrassa",
    "sg:orig_category":"Laboratorios Y Cl\u00cdnicas Veterinarias",
    "sg:phone":"+34 937 33 35 49",
    "sg:postcode":"08221",
    "sg:province":"Barcelona",
    "wof:name":"Mateu Cama\u00f1es Maria Eugenia",
    "wof:placetype":"venue"
},
  "geometry": {"coordinates":[2.0076680183,41.5571212769],"type":"Point"}
}