{
  "type": "Feature",
  "properties": {
    "addr:full":"Crta Santander, Km. 0009,0 El Astillero Cantabria 39610",
    "addr:postcode":"39610",
    "addr:street":"Crta Santander Km. 0009,0",
    "iso:country":"ES",
    "sg:address":"Crta Santander, Km. 0009,0",
    "sg:city":"El Astillero",
    "sg:orig_category":"Alimentaci\u00d3n General (al Por Mayor)",
    "sg:phone":"+34 942 55 92 72",
    "sg:postcode":"39610",
    "sg:province":"Cantabria",
    "wof:name":"Pascual De Aranda S.a.",
    "wof:placetype":"venue"
},
  "geometry": {"coordinates":[-3.821928978,43.4001655579],"type":"Point"}
}