{
  "type": "Feature",
  "properties": {
    "iso:country":"ES",
    "sg:address":"Calle de Alfonso V, 7",
    "sg:city":"Le\u00f3n",
    "sg:orig_category":"Notarios",
    "sg:phone":"+34 987 23 60 00",
    "sg:postcode":"24001",
    "sg:province":"Le\u00f3n",
    "wof:name":"Gomez Poblacion Sanchez-llorente Y Prieto C.b.",
    "wof:placetype":"venue"
},
  "geometry": {"coordinates":[-5.5741376877,42.5980148315],"type":"Point"}
}