{
  "type": "Feature",
  "properties": {
    "addr:full":"Cm\u00d1o Laxe De Rons, S/n Virxe Das Mareas Pontevedra 36980",
    "addr:housenumber":"s / n",
    "addr:postcode":"36980",
    "addr:street":"Cmn\u0303O;Rons",
    "iso:country":"ES",
    "sg:address":"Cm\u00d1o Laxe De Rons, S/n",
    "sg:city":"Virxe Das Mareas",
    "sg:orig_category":"Estudios Y Construcci\u00d3n De Acuarios Y Viveros",
    "sg:phone":"+34 986 73 24 71",
    "sg:postcode":"36980",
    "sg:province":"Pontevedra",
    "wof:name":"Mariscos Meifer S.l.",
    "wof:placetype":"venue"
},
  "geometry": {"coordinates":[-8.8819255829,42.4950904846],"type":"Point"}
}