{
  "type": "Feature",
  "properties": {
    "addr:full":"Rua Alfonso Xiii, 1 Vigo Pontevedra 36201",
    "addr:housenumber":"1",
    "addr:postcode":"36201",
    "addr:street":"Rua Alfonso Xiii",
    "iso:country":"ES",
    "sg:address":"Rua Alfonso Xiii, 1",
    "sg:city":"Vigo",
    "sg:orig_category":"Librer\u00cdas",
    "sg:phone":"+34 986 22 63 64",
    "sg:postcode":"36201",
    "sg:province":"Pontevedra",
    "wof:name":"Vila Lorenzo Teresa Angelica",
    "wof:placetype":"venue"
},
  "geometry": {"coordinates":[-8.7157526016,42.2359237671],"type":"Point"}
}