{
  "type": "Feature",
  "properties": {
    "addr:full":"Carrer de Prat De La Riba, 37 Santa Perpetua De Mogoda Barcelona 08130",
    "addr:housenumber":"37",
    "addr:postcode":"08130",
    "addr:street":"Carrer De Prat De La Riba",
    "iso:country":"ES",
    "sg:address":"Carrer de Prat De La Riba, 37",
    "sg:city":"Santa Perpetua De Mogoda",
    "sg:orig_category":"Poller\u00cda Y Caza (al Por Menor)",
    "sg:phone":"+34 935 60 19 20",
    "sg:postcode":"08130",
    "sg:province":"Barcelona",
    "wof:name":"Oller Casamiquela Juan Maria",
    "wof:placetype":"venue"
},
  "geometry": {"coordinates":[2.1814959049,41.5357017517],"type":"Point"}
}