{
  "type": "Feature",
  "properties": {
    "addr:full":"Calle de San Agustin, 1 Le\u00f3n Le\u00f3n 24001",
    "addr:housenumber":"1",
    "addr:postcode":"24001",
    "addr:street":"Calle De San Agustin;Leo\u0301N",
    "iso:country":"ES",
    "sg:address":"Calle de San Agustin, 1",
    "sg:city":"Le\u00f3n",
    "sg:orig_category":"Asesor\u00cda Fiscal Y Jur\u00cddica",
    "sg:phone":"+34 987 23 80 09",
    "sg:postcode":"24001",
    "sg:province":"Le\u00f3n",
    "wof:name":"Pollan Y Vega S.c.",
    "wof:placetype":"venue"
},
  "geometry": {"coordinates":[-5.5744171143,42.5984535217],"type":"Point"}
}