{
  "type": "Feature",
  "properties": {
    "iso:country":"ES",
    "sg:address":"Calle de Temple, 18",
    "sg:city":"Zaragoza",
    "sg:orig_category":"Molduras, Junquillos, Listones Y Molduras Perforadas",
    "sg:phone":"+34 976 20 07 63",
    "sg:postcode":"50003",
    "sg:province":"Zaragoza",
    "wof:name":"El Jardin Del Temple S.l.",
    "wof:placetype":"venue"
},
  "geometry": {"coordinates":[-0.881461978,41.655620575],"type":"Point"}
}