{
  "type": "Feature",
  "properties": {
    "addr:full":"Calle de Poza (la), 7 Hervas C\u00e1ceres 10700",
    "addr:housenumber":"7",
    "addr:postcode":"10700",
    "addr:street":"Calle De Poza La;Ca\u0301Ceres",
    "iso:country":"ES",
    "sg:address":"Calle de Poza (la), 7",
    "sg:city":"Hervas",
    "sg:orig_category":"Supermercados Y Hipermercados",
    "sg:phone":"+34 927 48 12 90",
    "sg:postcode":"10700",
    "sg:province":"C\u00e1ceres",
    "wof:name":"Grupo El Arbol Distribucion Y Supermercados S.a. Unipersonal",
    "wof:placetype":"venue"
},
  "geometry": {"coordinates":[-5.8620128632,40.2744255066],"type":"Point"}
}