{
  "type": "Feature",
  "properties": {
    "iso:country":"ES",
    "sg:address":"Calle de Inmaculada Concepcion, 26",
    "sg:city":"Madrid",
    "sg:orig_category":"Ropa Para Se\u00d1oras Y Caballeros (al Por Menor)",
    "sg:phone":"+34 914 60 51 90",
    "sg:postcode":"28019",
    "sg:province":"Madrid",
    "wof:name":"Arroyo Garcia Antonio",
    "wof:placetype":"venue"
},
  "geometry": {"coordinates":[-3.7120447159,40.3937835693],"type":"Point"}
}