{
  "type": "Feature",
  "properties": {
    "addr:full":"Calle de Primo De Rivera, 14 Povedilla Albacete 02311",
    "addr:housenumber":"14",
    "addr:postcode":"02311",
    "addr:street":"Calle De Primo De Rivera",
    "iso:country":"ES",
    "sg:address":"Calle de Primo De Rivera, 14",
    "sg:city":"Povedilla",
    "sg:orig_category":"Cajas Para Embalar",
    "sg:phone":"+34 967 39 20 67",
    "sg:postcode":"02311",
    "sg:province":"Albacete",
    "wof:name":"Caja Rural De Albacete",
    "wof:placetype":"venue"
},
  "geometry": {"coordinates":[-2.601733923,38.6990852356],"type":"Point"}
}