{
  "type": "Feature",
  "properties": {
    "addr:full":"Carrer de Mare De Deu De Port, 271 Barcelona Barcelona 08038",
    "addr:housenumber":"271",
    "addr:postcode":"08038",
    "addr:street":"Carrer De Mare De Deu;Port",
    "iso:country":"ES",
    "sg:address":"Carrer de Mare De Deu De Port, 271",
    "sg:city":"Barcelona",
    "sg:orig_category":"Carnicer\u00cdas, Carnicer\u00cdas",
    "sg:phone":"+34 934 21 87 26",
    "sg:postcode":"08038",
    "sg:province":"Barcelona",
    "wof:name":"Ime Mil S.l.",
    "wof:placetype":"venue"
},
  "geometry": {"coordinates":[2.1422529221,41.3593177795],"type":"Point"}
}