{
  "type": "Feature",
  "properties": {
    "iso:country":"ES",
    "sg:address":"Calle de Almendros, Los, 11",
    "sg:city":"Calpe",
    "sg:orig_category":"Farmacias",
    "sg:phone":"+34 965 83 11 96",
    "sg:postcode":"03710",
    "sg:province":"Alicante",
    "wof:name":"Savall Mascarell Francisco",
    "wof:placetype":"venue"
},
  "geometry": {"coordinates":[0.0464899987,38.6449623108],"type":"Point"}
}