{
  "type": "Feature",
  "properties": {
    "addr:full":"Calle de Maestro Garrido, 6 Alcala Real Ja\u00e9n 23680",
    "addr:housenumber":"6",
    "addr:postcode":"23680",
    "addr:street":"Calle De Maestro Garrido;Jae\u0301N",
    "iso:country":"ES",
    "sg:address":"Calle de Maestro Garrido, 6",
    "sg:city":"Alcala Real",
    "sg:orig_category":"Promotores Constructores",
    "sg:phone":"+34 953 58 26 85",
    "sg:postcode":"23680",
    "sg:province":"Ja\u00e9n",
    "wof:name":"Constmuro S.l.",
    "wof:placetype":"venue"
},
  "geometry": {"coordinates":[-3.9179890156,37.4610328674],"type":"Point"}
}