{
  "type": "Feature",
  "properties": {
    "iso:country":"ES",
    "sg:address":"Carrer de Volta, 9",
    "sg:city":"Terrassa",
    "sg:orig_category":"Caf\u00c9s, Bares, Cervecer\u00cdas",
    "sg:phone":"+34 937 89 48 32",
    "sg:postcode":"08224",
    "sg:province":"Barcelona",
    "wof:name":"Rubio Navas Francisco Javier",
    "wof:placetype":"venue"
},
  "geometry": {"coordinates":[2.0071749687,41.5635604858],"type":"Point"}
}