{
  "type": "Feature",
  "properties": {
    "addr:full":"Calle de Juan Carlos I, 12 Pe\u00e7arroya-pueblonuevo C\u00f3rdoba 14200",
    "addr:housenumber":"12",
    "addr:postcode":"14200",
    "addr:street":"Calle De Juan Carlos I;Co\u0301Rdoba",
    "iso:country":"ES",
    "sg:address":"Calle de Juan Carlos I, 12",
    "sg:city":"Pe\u00e7arroya-pueblonuevo",
    "sg:orig_category":"Bisuter\u00cda, Joyer\u00cda, Relojer\u00cda (al Por Menor)",
    "sg:phone":"+34 957 57 11 00",
    "sg:postcode":"14200",
    "sg:province":"C\u00f3rdoba",
    "wof:name":"Romero Mu\u00f1oz Francisco Javier",
    "wof:placetype":"venue"
},
  "geometry": {"coordinates":[-5.2655301094,38.2986526489],"type":"Point"}
}