{
  "type": "Feature",
  "properties": {
    "addr:full":"Plaz Rutherford, 1 Corrales Huelva 21120",
    "addr:housenumber":"1",
    "addr:postcode":"21120",
    "addr:street":"Plaz Rutherford",
    "iso:country":"ES",
    "sg:address":"Plaz Rutherford, 1",
    "sg:city":"Corrales",
    "sg:orig_category":"Controles De Edificaci\u00d3n (construcci\u00d3n, Seguridad)",
    "sg:phone":"+34 959 49 01 38",
    "sg:postcode":"21120",
    "sg:province":"Huelva",
    "wof:name":"Inversiones Aldar S.l.",
    "wof:placetype":"venue"
},
  "geometry": {"coordinates":[-6.9876918793,37.2748298645],"type":"Point"}
}