{
  "type": "Feature",
  "properties": {
    "iso:country":"ES",
    "sg:address":"Cami Atall (l') Z.alcossebre, 12",
    "sg:city":"Alcossebre",
    "sg:orig_category":"Inmobiliaria (agencias)",
    "sg:phone":"+34 964 15 72 41",
    "sg:postcode":"12579",
    "sg:province":"Castell\u00f3n",
    "wof:name":"Eurogestion Europea De Gestion Inmobiliaria S.l.",
    "wof:placetype":"venue"
},
  "geometry": {"coordinates":[0.2850950062,40.2547187805],"type":"Point"}
}