{
  "type": "Feature",
  "properties": {
    "addr:full":"Carrer de Lluis Sagnier, 48 Barcelona Barcelona 08032",
    "addr:housenumber":"48",
    "addr:postcode":"08032",
    "addr:street":"Carrer De Lluis Sagnier",
    "iso:country":"ES",
    "sg:address":"Carrer de Lluis Sagnier, 48",
    "sg:city":"Barcelona",
    "sg:orig_category":"Arquitectos",
    "sg:phone":"+34 934 35 36 06",
    "sg:postcode":"08032",
    "sg:province":"Barcelona",
    "wof:name":"Sole Vidal Francisco",
    "wof:placetype":"venue"
},
  "geometry": {"coordinates":[2.1735899448,41.4253768921],"type":"Point"}
}