{
  "type": "Feature",
  "properties": {
    "addr:full":"Areas, 68 Areas Pontevedra 36099",
    "addr:housenumber":"68",
    "addr:postcode":"36099",
    "addr:street":"Areas",
    "iso:country":"ES",
    "sg:address":"Areas, 68",
    "sg:city":"Areas",
    "sg:orig_category":"Alimentaci\u00d3n General (al Por Mayor)",
    "sg:phone":"+34 986 84 08 02",
    "sg:postcode":"36099",
    "sg:province":"Pontevedra",
    "wof:name":"Varela Sieiro Maria Del Carmen",
    "wof:placetype":"venue"
},
  "geometry": {"coordinates":[-8.6275186539,42.1733207703],"type":"Point"}
}