{
  "type": "Feature",
  "properties": {
    "iso:country":"ES",
    "sg:address":"Carrer de Muntanya, 1",
    "sg:city":"S. Cebria Vallalta",
    "sg:orig_category":"Inform\u00c1tica: Soportes De Informaci\u00d3n, Suministros & Accesorios",
    "sg:phone":"+34 937 63 14 79",
    "sg:postcode":"08396",
    "sg:province":"Barcelona",
    "wof:name":"Pcr Systemlaser Sll.",
    "wof:placetype":"venue"
},
  "geometry": {"coordinates":[2.6146900654,41.6515693665],"type":"Point"}
}