{
  "type": "Feature",
  "properties": {
    "addr:full":"Plaz Iglesia, S/n Murtas Granada 18490",
    "addr:housenumber":"s / n",
    "addr:postcode":"18490",
    "addr:street":"Murtas Granada",
    "iso:country":"ES",
    "sg:address":"Plaz Iglesia, S/n",
    "sg:city":"Murtas",
    "sg:orig_category":"Administraciones Regionales, Departamentales Y Locales",
    "sg:phone":"+34 958 85 50 02",
    "sg:postcode":"18490",
    "sg:province":"Granada",
    "wof:name":"Ayuntamiento",
    "wof:placetype":"venue"
},
  "geometry": {"coordinates":[-3.1087560654,36.8867149353],"type":"Point"}
}