{
  "type": "Feature",
  "properties": {
    "iso:country":"ES",
    "sg:address":"Calle de Goya, 9",
    "sg:city":"Jamilena",
    "sg:orig_category":"Fabricaci\u00d3n De Enlosados, Soler\u00cdas",
    "sg:phone":"+34 953 56 60 16",
    "sg:postcode":"23658",
    "sg:province":"Ja\u00e9n",
    "wof:name":"Liebana Lopez Bernardo",
    "wof:placetype":"venue"
},
  "geometry": {"coordinates":[-3.9134190083,37.748210907],"type":"Point"}
}