{
  "type": "Feature",
  "properties": {
    "iso:country":"ES",
    "sg:address":"Alam San Mames, 37",
    "sg:city":"Bilbao",
    "sg:orig_category":"Asesor\u00cda Sobre Comunicaci\u00d3n De Empresas",
    "sg:phone":"+34 944 21 63 97",
    "sg:postcode":"48010",
    "sg:province":"Vizcaya",
    "wof:name":"Tobalina Arrieta Gonzalo",
    "wof:placetype":"venue"
},
  "geometry": {"coordinates":[-2.9382989407,43.2593727112],"type":"Point"}
}