{
  "type": "Feature",
  "properties": {
    "addr:full":"Avda Ayora, S/n Almansa Albacete 02640",
    "addr:housenumber":"s / n",
    "addr:postcode":"02640",
    "addr:street":"Avda Ayora",
    "iso:country":"ES",
    "sg:address":"Avda Ayora, S/n",
    "sg:city":"Almansa",
    "sg:orig_category":"Mec\u00c1nico Del Autom\u00d3vil",
    "sg:phone":"+34 967 34 01 83",
    "sg:postcode":"02640",
    "sg:province":"Albacete",
    "wof:name":"Talleres Castillo Marquez S.l.",
    "wof:placetype":"venue"
},
  "geometry": {"coordinates":[-1.1026890278,38.8706932068],"type":"Point"}
}