{
  "type": "Feature",
  "properties": {
    "addr:full":"Calle de Alemanes, S/n Sevilla Sevilla 41004",
    "addr:housenumber":"s / n",
    "addr:postcode":"41004",
    "addr:street":"Calle De Alemanes",
    "iso:country":"ES",
    "sg:address":"Calle de Alemanes, S/n",
    "sg:city":"Sevilla",
    "sg:orig_category":"Bibliotecas, Mediatecas",
    "sg:phone":"+34 954 56 07 69",
    "sg:postcode":"41004",
    "sg:province":"Sevilla",
    "wof:name":"Institucion Colombina-cabildo Catedral",
    "wof:placetype":"venue"
},
  "geometry": {"coordinates":[-5.9933457375,37.3867454529],"type":"Point"}
}