{
  "type": "Feature",
  "properties": {
    "iso:country":"ES",
    "sg:address":"Calle de Pilar (el), 12",
    "sg:city":"Santa Cruz Palma",
    "sg:orig_category":"Ense\u00d1anza Secundaria: Colegios Y Escuelas Privadas",
    "sg:phone":"+34 922 41 28 00",
    "sg:postcode":"38700",
    "sg:province":"Santa Cruz De Tenerife",
    "wof:name":"Gobierno De Canarias-ies Luis Cobiellas Cuevas",
    "wof:placetype":"venue"
},
  "geometry": {"coordinates":[-17.7651233673,28.6867370605],"type":"Point"}
}