{
  "type": "Feature",
  "properties": {
    "iso:country":"ES",
    "sg:address":"C/ Torre De Les Ma\u00c7anes, 5",
    "sg:city":"Alcoi",
    "sg:orig_category":"Prot\u00c9sicos Dentales",
    "sg:phone":"+34 965 54 11 94",
    "sg:postcode":"03801",
    "sg:province":"Alicante",
    "wof:name":"Pascual Perez Gustavo",
    "wof:placetype":"venue"
},
  "geometry": {"coordinates":[-0.4601489902,38.7133598328],"type":"Point"}
}