{
  "type": "Feature",
  "properties": {
    "iso:country":"ES",
    "sg:address":"Avda Constitucion, 25",
    "sg:city":"Don Benito",
    "sg:orig_category":"Peluquer\u00cdas",
    "sg:phone":"+34 924 80 54 01",
    "sg:postcode":"06400",
    "sg:province":"Badajoz",
    "wof:name":"Peluqueria Pablo C.b.",
    "wof:placetype":"venue"
},
  "geometry": {"coordinates":[-5.8627138138,38.9662666321],"type":"Point"}
}