{
  "type": "Feature",
  "properties": {
    "addr:full":"Carrer de Saragossa, 102 Amposta Tarragona 43870",
    "addr:housenumber":"102",
    "addr:postcode":"43870",
    "addr:street":"Carrer De Saragossa",
    "iso:country":"ES",
    "sg:address":"Carrer de Saragossa, 102",
    "sg:city":"Amposta",
    "sg:orig_category":"Administradores De Bienes Y Delegados De Comunidades De Propietarios",
    "sg:phone":"+34 977 70 36 95",
    "sg:postcode":"43870",
    "sg:province":"Tarragona",
    "wof:name":"Barrera Guix Josefa",
    "wof:placetype":"venue"
},
  "geometry": {"coordinates":[0.5762330294,40.7055587769],"type":"Point"}
}