{
  "type": "Feature",
  "properties": {
    "addr:full":"Calle de Conde De Halcon, 24 Sevilla Sevilla 41008",
    "addr:housenumber":"24",
    "addr:postcode":"41008",
    "addr:street":"Calle De Conde De Halcon",
    "iso:country":"ES",
    "sg:address":"Calle de Conde De Halcon, 24",
    "sg:city":"Sevilla",
    "sg:orig_category":"Asesor\u00cda Fiscal Y Jur\u00cddica",
    "sg:phone":"+34 954 36 22 56",
    "sg:postcode":"41008",
    "sg:province":"Sevilla",
    "wof:name":"Gestiones Complementarias S.l.",
    "wof:placetype":"venue"
},
  "geometry": {"coordinates":[-5.9794564247,37.4048614502],"type":"Point"}
}