{
  "type": "Feature",
  "properties": {
    "iso:country":"ES",
    "sg:address":"Enebro, S/n",
    "sg:city":"Monte Real",
    "sg:orig_category":"Cooperativas Agr\u00cdcolas",
    "sg:phone":"+34 961 57 59 73",
    "sg:postcode":"46900",
    "sg:province":"Valencia",
    "wof:name":"Sociedad Cooperativa De Viviendas Monte Real",
    "wof:placetype":"venue"
},
  "geometry": {"coordinates":[-0.5212299824,39.4128303528],"type":"Point"}
}