{
  "type": "Feature",
  "properties": {
    "addr:full":"Camino Viejo Simancas, S/n Valladolid Valladolid 47008",
    "addr:housenumber":"s / n",
    "addr:postcode":"47008",
    "addr:street":"Camino Viejo Simancas",
    "iso:country":"ES",
    "sg:address":"Camino Viejo Simancas, S/n",
    "sg:city":"Valladolid",
    "sg:orig_category":"\u00d3ptica: Instrumentos (fabricaci\u00d3n)",
    "sg:phone":"+34 983 47 56 58",
    "sg:postcode":"47008",
    "sg:province":"Valladolid",
    "wof:name":"General Optica S.a.",
    "wof:placetype":"venue"
},
  "geometry": {"coordinates":[-4.7844028473,41.6075973511],"type":"Point"}
}