{
  "type": "Feature",
  "properties": {
    "addr:full":"Avda Europa, 57 Leganes Madrid 28915",
    "addr:housenumber":"57",
    "addr:postcode":"28915",
    "addr:street":"Avda Europa",
    "iso:country":"ES",
    "sg:address":"Avda Europa, 57",
    "sg:city":"Leganes",
    "sg:orig_category":"Edici\u00d3n De Diarios, Revistas, Boletines",
    "sg:phone":"+34 916 86 31 98",
    "sg:postcode":"28915",
    "sg:province":"Madrid",
    "wof:name":"Rodriguez Gallegos Enrique",
    "wof:placetype":"venue"
},
  "geometry": {"coordinates":[-3.7483980656,40.3389549255],"type":"Point"}
}