{
  "type": "Feature",
  "properties": {
    "iso:country":"ES",
    "sg:address":"Rua Rosalia De Castro (de), 68",
    "sg:city":"Castroverde",
    "sg:orig_category":"Quincaller\u00cda (al Por Menor)",
    "sg:phone":"+34 982 31 20 19",
    "sg:postcode":"27120",
    "sg:province":"Lugo",
    "wof:name":"Gomez Nu\u00f1ez Ramon",
    "wof:placetype":"venue"
},
  "geometry": {"coordinates":[-7.3260197639,43.0300979614],"type":"Point"}
}