{
  "type": "Feature",
  "properties": {
    "addr:full":"Ctra. Alcudia-arta, 47 Can Picafort Islas Baleares 07458",
    "addr:housenumber":"47",
    "addr:postcode":"07458",
    "addr:street":"Ctra. Alcudia-Arta",
    "iso:country":"ES",
    "sg:address":"Ctra. Alcudia-arta, 47",
    "sg:city":"Can Picafort",
    "sg:orig_category":"Ropa Para Se\u00d1oras (al Por Menor)",
    "sg:phone":"+34 971 85 14 29",
    "sg:postcode":"07458",
    "sg:province":"Islas Baleares",
    "wof:name":"Ramon Plomer Francisca Maria",
    "wof:placetype":"venue"
},
  "geometry": {"coordinates":[3.1486649513,39.7653236389],"type":"Point"}
}