{
  "type": "Feature",
  "properties": {
    "iso:country":"ES",
    "sg:address":"Calle de Majada De Las Monjas (de), 81",
    "sg:city":"Becerril Sierra",
    "sg:orig_category":"Grabados",
    "sg:phone":"+34 918 53 78 33",
    "sg:postcode":"28490",
    "sg:province":"Madrid",
    "wof:name":"Rodriguez Gonzalez Fernando",
    "wof:placetype":"venue"
},
  "geometry": {"coordinates":[-3.9853839874,40.7024421692],"type":"Point"}
}