{
  "type": "Feature",
  "properties": {
    "iso:country":"ES",
    "sg:address":"Calle de Caballero Rejoneador Gines Cartagena, 1",
    "sg:city":"Benidorm",
    "sg:orig_category":"Reposter\u00cdas",
    "sg:phone":"+34 965 86 47 20",
    "sg:postcode":"03500",
    "sg:province":"Alicante",
    "wof:name":"Panaderia La Vienesa Comunidad De Bienes",
    "wof:placetype":"venue"
},
  "geometry": {"coordinates":[-0.1344134063,38.5463180542],"type":"Point"}
}