{
  "type": "Feature",
  "properties": {
    "iso:country":"ES",
    "sg:address":"Poligono Industrial Boch, 26",
    "sg:city":"Poligono Industrial Boch",
    "sg:orig_category":"Alimentaci\u00d3n General (al Por Menor)",
    "sg:phone":"+34 965 40 15 02",
    "sg:postcode":"03330",
    "sg:province":"Alicante",
    "wof:name":"Manufacturas Tiana S.l.u.",
    "wof:placetype":"venue"
},
  "geometry": {"coordinates":[-0.8056010008,38.241355896],"type":"Point"}
}