{
  "type": "Feature",
  "properties": {
    "addr:full":"Carrer de Joaquim Costa, 33 Terrassa Barcelona 08222",
    "addr:housenumber":"33",
    "addr:postcode":"08222",
    "addr:street":"Carrer De Joaquim Costa",
    "iso:country":"ES",
    "sg:address":"Carrer de Joaquim Costa, 33",
    "sg:city":"Terrassa",
    "sg:orig_category":"Inmobiliaria (agencias)",
    "sg:phone":"+34 937 83 92 39",
    "sg:postcode":"08222",
    "sg:province":"Barcelona",
    "wof:name":"Promociones Inmobiliarias Grupo Escultor Blay",
    "wof:placetype":"venue"
},
  "geometry": {"coordinates":[2.0246829987,41.5652084351],"type":"Point"}
}