{
  "type": "Feature",
  "properties": {
    "iso:country":"ES",
    "sg:address":"Artesano Jose M. Silva, S/n",
    "sg:city":"S. Fernando",
    "sg:orig_category":"Supermercados Y Hipermercados",
    "sg:phone":"+34 956 48 76 09",
    "sg:postcode":"11100",
    "sg:province":"C\u00e1diz",
    "wof:name":"Estudillo Barroso Manuela",
    "wof:placetype":"venue"
},
  "geometry": {"coordinates":[-6.208876133,36.447555542],"type":"Point"}
}