{
  "type": "Feature",
  "properties": {
    "iso:country":"ES",
    "sg:address":"Plaz Espa\u00d1a (de), 14",
    "sg:city":"Pozuelo Calatrava",
    "sg:orig_category":"Pescader\u00cdas (al Por Menor)",
    "sg:phone":"+34 926 84 06 63",
    "sg:postcode":"13179",
    "sg:province":"Ciudad Real",
    "wof:name":"Mu\u00f1oz Garrido Gregorio",
    "wof:placetype":"venue"
},
  "geometry": {"coordinates":[-3.8354260921,38.9131889343],"type":"Point"}
}