{
  "type": "Feature",
  "properties": {
    "iso:country":"ES",
    "sg:address":"Calle de Josefa Tome Y Orgaz (de), 12",
    "sg:city":"Casarrubuelos",
    "sg:orig_category":"Fabricaci\u00d3n De Tapices Y Moquetas Para Suelos Y Paredes",
    "sg:phone":"+34 918 16 74 89",
    "sg:postcode":"28978",
    "sg:province":"Madrid",
    "wof:name":"Terrazos Pompa S. A.",
    "wof:placetype":"venue"
},
  "geometry": {"coordinates":[-3.8341441154,40.1709747314],"type":"Point"}
}