{
  "type": "Feature",
  "properties": {
    "addr:full":"Avda Zumalacarregui, 28 Bilbao Vizcaya 48006",
    "addr:housenumber":"28",
    "addr:postcode":"48006",
    "addr:street":"Avda Zumalacarregui",
    "iso:country":"ES",
    "sg:address":"Avda Zumalacarregui, 28",
    "sg:city":"Bilbao",
    "sg:classifiers":[
        {
            "category":"Autos & Motor Vehicles",
            "subcategory":"Automobile Sales",
            "type":"Retail Goods"
        }
    ],
    "sg:phone":"+34 944 73 44 89",
    "sg:postcode":"48006",
    "sg:province":"Vizcaya",
    "wof:name":"Karting Kaiku S.a.",
    "wof:placetype":"venue"
},
  "geometry": {"coordinates":[-2.912678957,43.257938385],"type":"Point"}
}