{
  "type": "Feature",
  "properties": {
    "iso:country":"ES",
    "sg:address":"Julio Altadill, 2",
    "sg:city":"Iru\u00f1a",
    "sg:orig_category":"Centros M\u00c9dicos Y Sociales, Dispensarios",
    "sg:phone":"+34 948 17 81 70",
    "sg:postcode":"31008",
    "sg:province":"Navarra",
    "sg:website":"www.cenreomedicovital.com",
    "wof:name":"Garcia Ciriza Cristina",
    "wof:placetype":"venue"
},
  "geometry": {"coordinates":[-1.6687812805,42.8102302551],"type":"Point"}
}