{
  "type": "Feature",
  "properties": {
    "addr:full":"Calle de Castellote, 9 Alca\u00f1iz Teruel 44600",
    "addr:housenumber":"9",
    "addr:postcode":"44600",
    "addr:street":"Calle De Castellote",
    "iso:country":"ES",
    "sg:address":"Calle de Castellote, 9",
    "sg:city":"Alca\u00f1iz",
    "sg:orig_category":"Empresas De Pintura Y Revestimientos",
    "sg:phone":"+34 978 83 22 15",
    "sg:postcode":"44600",
    "sg:province":"Teruel",
    "wof:name":"Herrera Abizanda Antonio",
    "wof:placetype":"venue"
},
  "geometry": {"coordinates":[-0.1286869943,41.0484771729],"type":"Point"}
}