{
  "type": "Feature",
  "properties": {
    "addr:full":"Carrer de Joan Maragall, S/n Corro D'avall Barcelona 08520",
    "addr:housenumber":"s / n",
    "addr:postcode":"08520",
    "addr:street":"Carrer De Joan Maragall;D'Avall Barcelona",
    "iso:country":"ES",
    "sg:address":"Carrer de Joan Maragall, S/n",
    "sg:city":"Corro D'avall",
    "sg:orig_category":"Suministros Y Materiales Industriales",
    "sg:phone":"+34 938 49 44 15",
    "sg:postcode":"08520",
    "sg:province":"Barcelona",
    "wof:name":"Tuboflex S.c.p.",
    "wof:placetype":"venue"
},
  "geometry": {"coordinates":[2.2123360634,41.4197158813],"type":"Point"}
}