{
  "type": "Feature",
  "properties": {
    "addr:full":"Calle de Peregrino, 3 Malaga M\u00e1laga 29002",
    "addr:housenumber":"3",
    "addr:postcode":"29002",
    "addr:street":"Calle De Peregrino;Ma\u0301Laga",
    "iso:country":"ES",
    "sg:address":"Calle de Peregrino, 3",
    "sg:city":"Malaga",
    "sg:classifiers":[
        {
            "category":"Communications",
            "type":"Services"
        }
    ],
    "sg:phone":"+34 952 31 91 66",
    "sg:postcode":"29002",
    "sg:province":"M\u00e1laga",
    "sg:tags":[
        "televisiones",
        "y",
        "radio"
    ],
    "sg:website":"www.ondacero.es",
    "wof:name":"Uniprex-onda Cero",
    "wof:placetype":"venue"
},
  "geometry": {"coordinates":[-4.4273848534,36.7149467468],"type":"Point"}
}