{
  "type": "Feature",
  "properties": {
    "iso:country":"ES",
    "sg:address":"Carrer de Balmes, 62",
    "sg:city":"Barcelona",
    "sg:orig_category":"Asociaciones, Organismos Culturales Y Socioeducativos",
    "sg:phone":"+34 934 87 53 80",
    "sg:postcode":"08007",
    "sg:province":"Barcelona",
    "wof:name":"Sociedad De Extension Cultural",
    "wof:placetype":"venue"
},
  "geometry": {"coordinates":[2.1622838974,41.3897628784],"type":"Point"}
}