{
  "type": "Feature",
  "properties": {
    "addr:full":"Avda Bulevar De El Ejido, 1 Ejido Almer\u00eda 04700",
    "addr:housenumber":"1",
    "addr:postcode":"04700",
    "addr:street":"Bulevar De El Ejido;Almeri\u0301A",
    "iso:country":"ES",
    "sg:address":"Avda Bulevar De El Ejido, 1",
    "sg:city":"Ejido",
    "sg:orig_category":"Agentes, Concesionarios Y Sucursales De Veh\u00cdculos",
    "sg:phone":"+34 950 57 03 40",
    "sg:postcode":"04700",
    "sg:province":"Almer\u00eda",
    "wof:name":"Serrano Maldonado Motor S.a.",
    "wof:placetype":"venue"
},
  "geometry": {"coordinates":[-2.8058309555,36.7609977722],"type":"Point"}
}