{
  "type": "Feature",
  "properties": {
    "iso:country":"ES",
    "sg:address":"Avda Bulevar De El Ejido, 1",
    "sg:city":"Ejido",
    "sg:orig_category":"Agentes, Concesionarios Y Sucursales De Veh\u00cdculos",
    "sg:phone":"+34 950 57 03 40",
    "sg:postcode":"04700",
    "sg:province":"Almer\u00eda",
    "wof:name":"Serrano Maldonado Motor S.a.",
    "wof:placetype":"venue"
},
  "geometry": {"coordinates":[-2.8058309555,36.7609977722],"type":"Point"}
}