{
  "type": "Feature",
  "properties": {
    "iso:country":"ES",
    "sg:address":"Calle de Zaida, 4",
    "sg:city":"Madrid",
    "sg:orig_category":"Asesor\u00cda Fiscal Y Jur\u00cddica",
    "sg:phone":"+34 914 72 00 44",
    "sg:postcode":"28019",
    "sg:province":"Madrid",
    "wof:name":"Herreruela Vazquez Fidel Mariano",
    "wof:placetype":"venue"
},
  "geometry": {"coordinates":[-3.7338819504,40.3984603882],"type":"Point"}
}