{
  "type": "Feature",
  "properties": {
    "addr:full":"Calle de Duran Loriga, 9 Coru\u00d1a La Coru\u00f1a 15003",
    "addr:housenumber":"9",
    "addr:postcode":"15003",
    "addr:street":"Calle De Duran Loriga;La Corun\u0303A",
    "iso:country":"ES",
    "sg:address":"Calle de Duran Loriga, 9",
    "sg:city":"Coru\u00d1a",
    "sg:orig_category":"Abogados",
    "sg:phone":"+34 981 20 94 74",
    "sg:postcode":"15003",
    "sg:province":"La Coru\u00f1a",
    "wof:name":"Chain Carballo Elia",
    "wof:placetype":"venue"
},
  "geometry": {"coordinates":[-8.4051103592,43.3673706055],"type":"Point"}
}