{
  "type": "Feature",
  "properties": {
    "iso:country":"ES",
    "sg:address":"Plaz Mayor, 14",
    "sg:city":"Villardeciervos",
    "sg:orig_category":"Cajas De Ahorro",
    "sg:phone":"+34 980 65 59 03",
    "sg:postcode":"49562",
    "sg:province":"Zamora",
    "sg:website":"www.cajaespana.es",
    "wof:name":"Caja Espa\u00f1a De Inversiones Caja De Ahorros Y Monte De Piedad",
    "wof:placetype":"venue"
},
  "geometry": {"coordinates":[-6.2866091728,41.9417915344],"type":"Point"}
}