{
  "type": "Feature",
  "properties": {
    "iso:country":"ES",
    "sg:address":"Cmno Llanos (los), S/n",
    "sg:city":"Alcaudete",
    "sg:orig_category":"Escayola Y Productos De Escayola (fabricaci\u00d3n, Al Por Mayor)",
    "sg:phone":"+34 953 56 12 11",
    "sg:postcode":"23660",
    "sg:province":"Ja\u00e9n",
    "wof:name":"Mantas Aguilera Antonio",
    "wof:placetype":"venue"
},
  "geometry": {"coordinates":[-4.0821909904,37.5862617493],"type":"Point"}
}