{
  "type": "Feature",
  "properties": {
    "iso:country":"ES",
    "sg:address":"Avda Rio Boladiez, S/n",
    "sg:city":"Poligono Sta M. De Benquerencia",
    "sg:orig_category":"Ropa Para Se\u00d1oras (al Por Menor)",
    "sg:phone":"+34 925 23 43 19",
    "sg:postcode":"45007",
    "sg:province":"Toledo",
    "sg:website":"www.sobervia.net",
    "wof:name":"Indic Asociacion Investigacion Dise\u00f1o Castilla-la Mancha",
    "wof:placetype":"venue"
},
  "geometry": {"coordinates":[-3.9338080883,39.8714675903],"type":"Point"}
}