{
  "type": "Feature",
  "properties": {
    "addr:full":"Sanguijuela, S/n Ronda M\u00e1laga 29400",
    "addr:housenumber":"/ n",
    "addr:postcode":"29400",
    "addr:street":"Sanguijuela S;Ronda Ma\u0301Laga",
    "iso:country":"ES",
    "sg:address":"Sanguijuela, S/n",
    "sg:city":"Ronda",
    "sg:orig_category":"Inmobiliaria (agencias)",
    "sg:phone":"+34 952 11 43 36",
    "sg:postcode":"29400",
    "sg:province":"M\u00e1laga",
    "wof:name":"Klinz  Manfred",
    "wof:placetype":"venue"
},
  "geometry": {"coordinates":[-5.1662788391,36.7417945862],"type":"Point"}
}