{
  "type": "Feature",
  "properties": {
    "iso:country":"ES",
    "sg:address":"Av. Marques Villanueva Del Prado, S/n",
    "sg:city":"Puerto Cruz",
    "sg:orig_category":"Agentes Generales De Seguros",
    "sg:phone":"+34 922 38 72 78",
    "sg:postcode":"38400",
    "sg:province":"Santa Cruz De Tenerife",
    "wof:name":"Blanc Schroer Maria",
    "wof:placetype":"venue"
},
  "geometry": {"coordinates":[-16.5422172546,28.4132347107],"type":"Point"}
}