{
  "type": "Feature",
  "properties": {
    "iso:country":"ES",
    "sg:address":"Cllo Menores, 5",
    "sg:city":"Toledo",
    "sg:orig_category":"Organismos De Desarrollo",
    "sg:phone":"+34 925 25 74 66",
    "sg:postcode":"45001",
    "sg:province":"Toledo",
    "sg:website":"www.fundacionfide.org",
    "wof:name":"Fundacion Iberoamericana Para El Desarrollo",
    "wof:placetype":"venue"
},
  "geometry": {"coordinates":[-4.025138855,39.8618774414],"type":"Point"}
}