{
  "type": "Feature",
  "properties": {
    "iso:country":"ES",
    "sg:address":"Calle de Carpesa, 4",
    "sg:city":"Madrid",
    "sg:orig_category":"Poller\u00cda Y Caza (al Por Menor)",
    "sg:phone":"+34 915 18 63 41",
    "sg:postcode":"28024",
    "sg:province":"Madrid",
    "wof:name":"Alonso Manzanares Eugenio",
    "wof:placetype":"venue"
},
  "geometry": {"coordinates":[-3.7707180977,40.3954467773],"type":"Point"}
}