{
  "type": "Feature",
  "properties": {
    "iso:country":"ES",
    "sg:address":"Carrer de Muntaner, 231",
    "sg:city":"Barcelona",
    "sg:orig_category":"Bisuter\u00cda, Joyer\u00cda, Relojer\u00cda (al Por Menor)",
    "sg:phone":"+34 932 02 04 98",
    "sg:postcode":"08021",
    "sg:province":"Barcelona",
    "wof:name":"Buxeda Corrales Alberto",
    "wof:placetype":"venue"
},
  "geometry": {"coordinates":[2.1490039825,41.394329071],"type":"Point"}
}