{
  "type": "Feature",
  "properties": {
    "addr:full":"Plaz Constitucion, 7 Salamanca Salamanca 37001",
    "addr:housenumber":"7",
    "addr:postcode":"37001",
    "addr:street":"Constitucion",
    "iso:country":"ES",
    "sg:address":"Plaz Constitucion, 7",
    "sg:city":"Salamanca",
    "sg:orig_category":"C\u00c1maras De Comercio E Industria, Oficios, Agricultura",
    "sg:phone":"+34 923 21 70 44",
    "sg:postcode":"37001",
    "sg:province":"Salamanca",
    "wof:name":"Asociacion Camara De La Propiedad Urbana De Salamanca",
    "wof:placetype":"venue"
},
  "geometry": {"coordinates":[-5.6604628563,40.9662094116],"type":"Point"}
}