{
  "type": "Feature",
  "properties": {
    "iso:country":"ES",
    "sg:address":"Ptge Clave, 11",
    "sg:city":"Sabadell",
    "sg:orig_category":"Promotores Constructores",
    "sg:phone":"+34 937 15 62 83",
    "sg:postcode":"08201",
    "sg:province":"Barcelona",
    "wof:name":"Comercial Ceramica Sabadell Sl",
    "wof:placetype":"venue"
},
  "geometry": {"coordinates":[2.1018359661,41.5449943542],"type":"Point"}
}