{
  "type": "Feature",
  "properties": {
    "addr:full":"Pl Iglesia, 2 Altea Alicante 03590",
    "addr:housenumber":"2",
    "addr:postcode":"03590",
    "addr:street":"Pl Iglesia",
    "iso:country":"ES",
    "sg:address":"Pl Iglesia, 2",
    "sg:city":"Altea",
    "sg:orig_category":"Comunidades Religiosas",
    "sg:phone":"+34 965 84 01 17",
    "sg:postcode":"03590",
    "sg:province":"Alicante",
    "wof:name":"Parroquia Nuestra Senora Del Consuelo",
    "wof:placetype":"venue"
},
  "geometry": {"coordinates":[-0.0519249998,38.5987510681],"type":"Point"}
}