{
  "type": "Feature",
  "properties": {
    "addr:full":"A Retirosa, S/n Retirosa Pontevedra 36947",
    "addr:housenumber":"s",
    "addr:postcode":"36947",
    "addr:street":"/ N",
    "iso:country":"ES",
    "sg:address":"A Retirosa, S/n",
    "sg:city":"Retirosa",
    "sg:orig_category":"Piedra Natural",
    "sg:phone":"+34 986 30 30 65",
    "sg:postcode":"36947",
    "sg:province":"Pontevedra",
    "wof:name":"Cao Pereira Raul",
    "wof:placetype":"venue"
},
  "geometry": {"coordinates":[-8.7698926926,42.2647743225],"type":"Point"}
}