{
  "type": "Feature",
  "properties": {
    "iso:country":"ES",
    "sg:address":"Carrer de Sant Jaume, 321",
    "sg:city":"Calella",
    "sg:orig_category":"M\u00dasica Diversa",
    "sg:phone":"+34 937 69 72 16",
    "sg:postcode":"08370",
    "sg:province":"Barcelona",
    "wof:name":"Escola De Musica Can Llobet S.s.l",
    "wof:placetype":"venue"
},
  "geometry": {"coordinates":[2.6613509655,41.6171112061],"type":"Point"}
}