{
  "type": "Feature",
  "properties": {
    "addr:full":"Calle de Cristo Del Grao, 4 Valencia Valencia 46011",
    "addr:housenumber":"4",
    "addr:postcode":"46011",
    "addr:street":"Calle De Cristo Del Grao",
    "iso:country":"ES",
    "sg:address":"Calle de Cristo Del Grao, 4",
    "sg:city":"Valencia",
    "sg:orig_category":"Arquitectos",
    "sg:phone":"+34 963 67 60 34",
    "sg:postcode":"46011",
    "sg:province":"Valencia",
    "wof:name":"Calabuig Ortu\u00f1o Jose Luis",
    "wof:placetype":"venue"
},
  "geometry": {"coordinates":[-0.3343859911,39.4608383179],"type":"Point"}
}