{
  "type": "Feature",
  "properties": {
    "addr:full":"Calle de Vicente Romero, 6 Aguilar De La Frontera C\u00f3rdoba 14920",
    "addr:housenumber":"6",
    "addr:postcode":"14920",
    "addr:street":"Calle De Vicente Romero",
    "iso:country":"ES",
    "sg:address":"Calle de Vicente Romero, 6",
    "sg:city":"Aguilar De La Frontera",
    "sg:orig_category":"Revestimiento De Suelos Industriales",
    "sg:phone":"+34 957 66 17 63",
    "sg:postcode":"14920",
    "sg:province":"C\u00f3rdoba",
    "wof:name":"Perez Bonilla Antonio",
    "wof:placetype":"venue"
},
  "geometry": {"coordinates":[-4.6580629349,37.5102424622],"type":"Point"}
}