{
  "type": "Feature",
  "properties": {
    "iso:country":"ES",
    "sg:address":"Ctra Seu D'urgell(la), 16",
    "sg:city":"Ponts",
    "sg:orig_category":"Limpieza Industrial",
    "sg:phone":"+34 973 46 04 41",
    "sg:postcode":"25740",
    "sg:province":"Lleida",
    "wof:name":"Bogaderia Amada",
    "wof:placetype":"venue"
},
  "geometry": {"coordinates":[1.1860300303,41.9163017273],"type":"Point"}
}