{
  "type": "Feature",
  "properties": {
    "iso:country":"ES",
    "sg:address":"Carrer de Progres, 56",
    "sg:city":"Hospitalet Llobregat",
    "sg:orig_category":"Inmobiliaria (agencias)",
    "sg:phone":"+34 934 47 23 11",
    "sg:postcode":"08904",
    "sg:province":"Barcelona",
    "wof:name":"Pilva-60 S.l.",
    "wof:placetype":"venue"
},
  "geometry": {"coordinates":[2.1197750568,41.373714447],"type":"Point"}
}