{
  "type": "Feature",
  "properties": {
    "addr:full":"Plaz Txalupagillene, 5 Donostia-san Sebastian Guip\u00f9zcoa 20008",
    "addr:housenumber":"5",
    "addr:postcode":"20008",
    "addr:street":"Plaz Txalupagillene",
    "iso:country":"ES",
    "sg:address":"Plaz Txalupagillene, 5",
    "sg:city":"Donostia-san Sebastian",
    "sg:orig_category":"M\u00c9dicos: Estomatolog\u00cda",
    "sg:phone":"+34 943 21 11 54",
    "sg:postcode":"20008",
    "sg:province":"Guip\u00f9zcoa",
    "wof:name":"Gomez Montalvo Gorka",
    "wof:placetype":"venue"
},
  "geometry": {"coordinates":[-2.0035710335,43.3128166199],"type":"Point"}
}