{
  "type": "Feature",
  "properties": {
    "iso:country":"ES",
    "sg:address":"Carrer de Sant Andreu, 66",
    "sg:city":"Santa Coloma De Gramenet",
    "sg:orig_category":"Herradores, Herreros, Carreteros",
    "sg:phone":"+34 934 68 29 45",
    "sg:postcode":"08923",
    "sg:province":"Barcelona",
    "wof:name":"Suministros Industriales Suminosa S.l.",
    "wof:placetype":"venue"
},
  "geometry": {"coordinates":[2.2168650627,41.4463844299],"type":"Point"}
}