{
  "type": "Feature",
  "properties": {
    "addr:full":"Calle de Alava (de), 16 San Fernando De Henares Madrid 28830",
    "addr:housenumber":"16",
    "addr:postcode":"28830",
    "addr:street":"Calle De Alava De",
    "iso:country":"ES",
    "sg:address":"Calle de Alava (de), 16",
    "sg:city":"San Fernando De Henares",
    "sg:orig_category":"Electricidad: Instaladores",
    "sg:phone":"+34 916 74 33 95",
    "sg:postcode":"28830",
    "sg:province":"Madrid",
    "wof:name":"Intalacon S.l.",
    "wof:placetype":"venue"
},
  "geometry": {"coordinates":[-3.5262885094,40.4200134277],"type":"Point"}
}