{
  "type": "Feature",
  "properties": {
    "addr:full":"Plaz San Antonio, 2 Barbastro Huesca 22300",
    "addr:housenumber":"2",
    "addr:postcode":"22300",
    "addr:street":"Plaz San Antonio",
    "iso:country":"ES",
    "sg:address":"Plaz San Antonio, 2",
    "sg:city":"Barbastro",
    "sg:orig_category":"Partidos Pol\u00cdticos",
    "sg:phone":"+34 974 31 24 63",
    "sg:postcode":"22300",
    "sg:province":"Huesca",
    "wof:name":"Partido Popular",
    "wof:placetype":"venue"
},
  "geometry": {"coordinates":[0.127057001,42.0381278992],"type":"Point"}
}