{
  "type": "Feature",
  "properties": {
    "addr:full":"Calle de Sierra Morena (de La), 9 Poligono De San Fernando De Henares Madrid 28830",
    "addr:housenumber":"9",
    "addr:postcode":"28830",
    "addr:street":"Calle De Sierra Morena De La",
    "iso:country":"ES",
    "sg:address":"Calle de Sierra Morena (de La), 9",
    "sg:city":"Poligono De San Fernando De Henares",
    "sg:orig_category":"Empresas De Hormig\u00d3n, Hormig\u00d3n Armado Y Pretensado",
    "sg:phone":"+34 916 76 01 11",
    "sg:postcode":"28830",
    "sg:province":"Madrid",
    "wof:name":"Prefabricados Inol S.a.",
    "wof:placetype":"venue"
},
  "geometry": {"coordinates":[-3.5057740211,40.451713562],"type":"Point"}
}