{
  "type": "Feature",
  "properties": {
    "iso:country":"ES",
    "sg:address":"Plaz Santo Domingo, 9",
    "sg:city":"Madrid",
    "sg:orig_category":"Florister\u00cdas",
    "sg:phone":"+34 915 59 85 35",
    "sg:postcode":"28013",
    "sg:province":"Madrid",
    "wof:name":"Vazquez Garcia David",
    "wof:placetype":"venue"
},
  "geometry": {"coordinates":[-3.7091610432,40.4200935364],"type":"Point"}
}