{
  "type": "Feature",
  "properties": {
    "addr:full":"Calle de Entrepe\u00d1as, S/n Alcala Henares Madrid 28803",
    "addr:housenumber":"s",
    "addr:postcode":"28803",
    "addr:street":"Calle De Entrepen\u0303As;/ N",
    "iso:country":"ES",
    "sg:address":"Calle de Entrepe\u00d1as, S/n",
    "sg:city":"Alcala Henares",
    "sg:orig_category":"Supermercados Y Hipermercados",
    "sg:phone":"+34 918 82 17 19",
    "sg:postcode":"28803",
    "sg:province":"Madrid",
    "wof:name":"Todymas S.a.",
    "wof:placetype":"venue"
},
  "geometry": {"coordinates":[-3.3630640507,40.4700698853],"type":"Point"}
}