{
  "type": "Feature",
  "properties": {
    "addr:full":"Urdaneta Kalea, 1 Zarautz Guip\u00f9zcoa 20800",
    "addr:housenumber":"1",
    "addr:postcode":"20800",
    "addr:street":"Urdaneta Kalea;Guipu\u0300Zcoa",
    "iso:country":"ES",
    "sg:address":"Urdaneta Kalea, 1",
    "sg:city":"Zarautz",
    "sg:orig_category":"Cristaler\u00cdas",
    "sg:phone":"+34 943 01 33 49",
    "sg:postcode":"20800",
    "sg:province":"Guip\u00f9zcoa",
    "wof:name":"Cristaleria Aranburu, Cb",
    "wof:placetype":"venue"
},
  "geometry": {"coordinates":[-2.1739099026,43.282951355],"type":"Point"}
}