{
  "type": "Feature",
  "properties": {
    "addr:full":"Calle de Manuel Cortina, 4 Villaviciosa Asturias 33300",
    "addr:housenumber":"4",
    "addr:postcode":"33300",
    "addr:street":"Calle De Manuel Cortina",
    "iso:country":"ES",
    "sg:address":"Calle de Manuel Cortina, 4",
    "sg:city":"Villaviciosa",
    "sg:orig_category":"Talleres: Ropa A Medida",
    "sg:phone":"+34 985 89 11 44",
    "sg:postcode":"33300",
    "sg:province":"Asturias",
    "wof:name":"Isla Zapirain Javier",
    "wof:placetype":"venue"
},
  "geometry": {"coordinates":[-5.4336190224,43.4801368713],"type":"Point"}
}