{
  "type": "Feature",
  "properties": {
    "iso:country":"ES",
    "sg:address":"Avda Alay, 2",
    "sg:city":"Arroyo De La Miel-benalmadena Costa",
    "sg:orig_category":"Oficinas De Cambio",
    "sg:phone":"+34 952 44 35 28",
    "sg:postcode":"29630",
    "sg:province":"M\u00e1laga",
    "wof:name":"Jan Willem Wesselink S.c.",
    "wof:placetype":"venue"
},
  "geometry": {"coordinates":[-4.5170850754,36.5981903076],"type":"Point"}
}