{
  "type": "Feature",
  "properties": {
    "iso:country":"ES",
    "sg:address":"Calle de Alcalde Vicente Arencibia, S/n",
    "sg:city":"Valleseco",
    "sg:orig_category":"Material Y Herramientas Agr\u00cdcolas",
    "sg:phone":"+34 928 61 87 80",
    "sg:postcode":"35340",
    "sg:province":"Las Palmas",
    "wof:name":"Reyes Navarro Francisca",
    "wof:placetype":"venue"
},
  "geometry": {"coordinates":[-15.5751419067,28.0501251221],"type":"Point"}
}