{
  "type": "Feature",
  "properties": {
    "iso:country":"ES",
    "sg:address":"Calle de Benito Cellier, 8",
    "sg:city":"S. Fernando",
    "sg:orig_category":"Abogados",
    "sg:phone":"+34 956 88 86 86",
    "sg:postcode":"11100",
    "sg:province":"C\u00e1diz",
    "wof:name":"Toscano Perez Maria Teresa",
    "wof:placetype":"venue"
},
  "geometry": {"coordinates":[-6.2043790817,36.466468811],"type":"Point"}
}