{
  "type": "Feature",
  "properties": {
    "addr:full":"Calle de Foncalada, 36 Oviedo Asturias 33002",
    "addr:housenumber":"36",
    "addr:postcode":"33002",
    "addr:street":"Calle De Foncalada",
    "iso:country":"ES",
    "sg:address":"Calle de Foncalada, 36",
    "sg:city":"Oviedo",
    "sg:orig_category":"Carnicer\u00cdas, Carnicer\u00cdas",
    "sg:phone":"+34 985 20 31 78",
    "sg:postcode":"33002",
    "sg:province":"Asturias",
    "wof:name":"Alimentacion Vetusta S.l.",
    "wof:placetype":"venue"
},
  "geometry": {"coordinates":[-5.8461914062,43.366394043],"type":"Point"}
}