{
  "type": "Feature",
  "properties": {
    "addr:full":"Calle de Xermade, S/n Guitiriz Lugo 27300",
    "addr:housenumber":"s / n",
    "addr:postcode":"27300",
    "addr:street":"Calle De Xermade",
    "iso:country":"ES",
    "sg:address":"Calle de Xermade, S/n",
    "sg:city":"Guitiriz",
    "sg:orig_category":"Caf\u00c9s, Bares, Cervecer\u00cdas",
    "sg:phone":"+34 982 37 21 01",
    "sg:postcode":"27300",
    "sg:province":"Lugo",
    "wof:name":"Fernandez Losada Esperanza",
    "wof:placetype":"venue"
},
  "geometry": {"coordinates":[-7.8988189697,43.1811637878],"type":"Point"}
}