{
  "type": "Feature",
  "properties": {
    "addr:full":"Calle de Ildefonso Cruz Rodriguez, 2 Santa Cruz De Tenerife Santa Cruz De Tenerife 38009",
    "addr:housenumber":"2",
    "addr:postcode":"38009",
    "addr:street":"Calle De Ildefonso Cruz Rodriguez",
    "iso:country":"ES",
    "sg:address":"Calle de Ildefonso Cruz Rodriguez, 2",
    "sg:city":"Santa Cruz De Tenerife",
    "sg:orig_category":"Servicios Diversos",
    "sg:phone":"+34 922 64 60 31",
    "sg:postcode":"38009",
    "sg:province":"Santa Cruz De Tenerife",
    "wof:name":"Topografia Canaria S.l.",
    "wof:placetype":"venue"
},
  "geometry": {"coordinates":[-17.7755756378,28.6416091919],"type":"Point"}
}