{
  "type": "Feature",
  "properties": {
    "iso:country":"ES",
    "sg:address":"Avda Pablo Iglesias, 31",
    "sg:city":"Madrid",
    "sg:orig_category":"Asociaciones, Organismos Culturales Y Socioeducativos",
    "sg:phone":"+34 915 34 91 92",
    "sg:postcode":"28039",
    "sg:province":"Madrid",
    "wof:name":"Asociacion Cultural Grupo De Coros Y Danzas De Madrid",
    "wof:placetype":"venue"
},
  "geometry": {"coordinates":[-3.7093315125,40.4484596252],"type":"Point"}
}