{
  "type": "Feature",
  "properties": {
    "iso:country":"ES",
    "sg:address":"Carrer de Minerva, 41",
    "sg:city":"S. Andreu Llavaneres",
    "sg:orig_category":"Papel (al Por Mayor)",
    "sg:phone":"+34 937 92 80 13",
    "sg:postcode":"08392",
    "sg:province":"Barcelona",
    "sg:website":"www.kimberly-clark.com",
    "wof:name":"Kimberly-clark S.l.",
    "wof:placetype":"venue"
},
  "geometry": {"coordinates":[2.4817700386,41.5696601868],"type":"Point"}
}