{
  "type": "Feature",
  "properties": {
    "iso:country":"ES",
    "sg:address":"Alberto Lafuente, 1",
    "sg:city":"Melide",
    "sg:orig_category":"Molduras, Junquillos, Listones Y Molduras Perforadas",
    "sg:phone":"+34 981 50 51 84",
    "sg:postcode":"15800",
    "sg:province":"A Coru\u00f1a",
    "wof:name":"Sexto Mejuto Luis",
    "wof:placetype":"venue"
},
  "geometry": {"coordinates":[-8.0166921616,42.9134788513],"type":"Point"}
}