{
  "type": "Feature",
  "properties": {
    "addr:full":"Carrer de Convent, 28 Sabadell Barcelona 08202",
    "addr:housenumber":"28",
    "addr:postcode":"08202",
    "addr:street":"Carrer De Convent",
    "iso:country":"ES",
    "sg:address":"Carrer de Convent, 28",
    "sg:city":"Sabadell",
    "sg:orig_category":"Agentes De Seguros",
    "sg:phone":"+34 937 25 20 77",
    "sg:postcode":"08202",
    "sg:province":"Barcelona",
    "wof:name":"Alberto Bernardo Bis Correduria De Seguros S.a.",
    "wof:placetype":"venue"
},
  "geometry": {"coordinates":[2.1088087559,41.5504455566],"type":"Point"}
}