{
  "type": "Feature",
  "properties": {
    "addr:full":"Calle de Marques De Albaida, 12 Palencia Palencia 34005",
    "addr:housenumber":"12",
    "addr:postcode":"34005",
    "addr:street":"Calle De Marques De Albaida",
    "iso:country":"ES",
    "sg:address":"Calle de Marques De Albaida, 12",
    "sg:city":"Palencia",
    "sg:orig_category":"Fabricaci\u00d3n, Importaci\u00d3n De L\u00c1mparas Y Bombillas",
    "sg:phone":"+34 979 74 33 76",
    "sg:postcode":"34005",
    "sg:province":"Palencia",
    "wof:name":"Ferrer Roca S.l.",
    "wof:placetype":"venue"
},
  "geometry": {"coordinates":[-4.533449173,42.007358551],"type":"Point"}
}