{
  "type": "Feature",
  "properties": {
    "addr:full":"Carrer de Castillejos, 323 Barcelona Barcelona 08025",
    "addr:housenumber":"323",
    "addr:postcode":"08025",
    "addr:street":"Carrer De Castillejos",
    "iso:country":"ES",
    "sg:address":"Carrer de Castillejos, 323",
    "sg:city":"Barcelona",
    "sg:orig_category":"Imprenta",
    "sg:phone":"+34 934 35 20 04",
    "sg:postcode":"08025",
    "sg:province":"Barcelona",
    "wof:name":"Artes Graficas Majoral S.l.",
    "wof:placetype":"venue"
},
  "geometry": {"coordinates":[2.1751618385,41.4089012146],"type":"Point"}
}