{
  "type": "Feature",
  "properties": {
    "addr:full":"Calle de Miguel Hernandez, 1 Valdemoro Madrid 28340",
    "addr:housenumber":"1",
    "addr:postcode":"28340",
    "addr:street":"Calle De Miguel Hernandez",
    "iso:country":"ES",
    "sg:address":"Calle de Miguel Hernandez, 1",
    "sg:city":"Valdemoro",
    "sg:orig_category":"Cl\u00cdnicas Dentales",
    "sg:phone":"+34 918 01 78 83",
    "sg:postcode":"28340",
    "sg:province":"Madrid",
    "wof:name":"Natural Dent Union Dental S.l.",
    "wof:placetype":"venue"
},
  "geometry": {"coordinates":[-3.6832690239,40.1928367615],"type":"Point"}
}