{
  "type": "Feature",
  "properties": {
    "iso:country":"ES",
    "sg:address":"Calle de Bethencourt Alfonso, 3",
    "sg:city":"Santa Cruz De Tenerife",
    "sg:orig_category":"Bazares, Art\u00cdculos De Limpieza Y De Cocina (al Por Menor)",
    "sg:phone":"+34 922 24 61 54",
    "sg:postcode":"38002",
    "sg:province":"Santa Cruz De Tenerife",
    "wof:name":"Tulsidas Dadlani Sawtri",
    "wof:placetype":"venue"
},
  "geometry": {"coordinates":[-16.2485809326,28.4673309326],"type":"Point"}
}