{
  "type": "Feature",
  "properties": {
    "addr:full":"Calle de Jose De Erviti, 8 Errenteria Guip\u00f9zcoa 20100",
    "addr:housenumber":"8",
    "addr:postcode":"20100",
    "addr:street":"Calle De Jose De Erviti;Guipu\u0300Zcoa",
    "iso:country":"ES",
    "sg:address":"Calle de Jose De Erviti, 8",
    "sg:city":"Errenteria",
    "sg:orig_category":"Peluqueros: De Se\u00d1oras",
    "sg:phone":"+34 943 51 55 24",
    "sg:postcode":"20100",
    "sg:province":"Guip\u00f9zcoa",
    "wof:name":"Mu\u00f1oz Ruiz Miguel",
    "wof:placetype":"venue"
},
  "geometry": {"coordinates":[-1.9001899958,43.3136520386],"type":"Point"}
}