{
  "type": "Feature",
  "properties": {
    "addr:full":"Calle de Ribera De Curtidores, 29 Madrid Madrid 28005",
    "addr:housenumber":"29",
    "addr:postcode":"madrid;28005",
    "addr:street":"Calle De Ribera De Curtidores",
    "iso:country":"ES",
    "sg:address":"Calle de Ribera De Curtidores, 29",
    "sg:city":"Madrid",
    "sg:orig_category":"Porcelana Decorativa",
    "sg:phone":"+34 915 28 69 75",
    "sg:postcode":"28005",
    "sg:province":"Madrid",
    "sg:website":"www.artesaniamr.com",
    "wof:name":"Martinez Ruiz Antonio",
    "wof:placetype":"venue"
},
  "geometry": {"coordinates":[-3.7071669102,40.4077911377],"type":"Point"}
}