{
  "type": "Feature",
  "properties": {
    "addr:full":"Calle de Teresa Monje, 1 Le\u00f3n Le\u00f3n 24008",
    "addr:housenumber":"1",
    "addr:postcode":"24008",
    "addr:street":"Calle De Teresa Monje;Leo\u0301N",
    "iso:country":"ES",
    "sg:address":"Calle de Teresa Monje, 1",
    "sg:city":"Le\u00f3n",
    "sg:orig_category":"Fabricaci\u00d3n De Juguetes Autom\u00c1ticos",
    "sg:phone":"+34 987 80 11 09",
    "sg:postcode":"24008",
    "sg:province":"Le\u00f3n",
    "wof:name":"Fernandez Cadenas Maria Cruz",
    "wof:placetype":"venue"
},
  "geometry": {"coordinates":[-5.5884728432,42.6137886047],"type":"Point"}
}