{
  "type": "Feature",
  "properties": {
    "iso:country":"ES",
    "sg:address":"Calle de Ercilla, 24",
    "sg:city":"Bilbao",
    "sg:orig_category":"Abogados",
    "sg:phone":"+34 944 16 03 71",
    "sg:postcode":"48011",
    "sg:province":"Vizcaya",
    "wof:name":"Jose Ignacio Goitisolo Arriaga",
    "wof:placetype":"venue"
},
  "geometry": {"coordinates":[-2.9359359741,43.2627182007],"type":"Point"}
}