{
  "type": "Feature",
  "properties": {
    "iso:country":"ES",
    "sg:address":"Ctra Zorrotza-kastrexana, 25",
    "sg:city":"Bilbao",
    "sg:orig_category":"T\u00c9cnicos Veterinarios",
    "sg:phone":"+34 944 42 20 98",
    "sg:postcode":"48013",
    "sg:province":"Vizcaya",
    "wof:name":"Lopez De Molina Zurimendi Ana Maria",
    "wof:placetype":"venue"
},
  "geometry": {"coordinates":[-2.972630024,43.2749786377],"type":"Point"}
}