{
  "type": "Feature",
  "properties": {
    "iso:country":"ES",
    "sg:address":"C/ Buixcarro, 8",
    "sg:city":"Alcoi",
    "sg:orig_category":"Metalizados",
    "sg:phone":"+34 965 52 13 35",
    "sg:postcode":"03802",
    "sg:province":"Alicante",
    "wof:name":"Mecanizados Valls S.l.",
    "wof:placetype":"venue"
},
  "geometry": {"coordinates":[-0.4960399866,38.6891937256],"type":"Point"}
}