{
  "type": "Feature",
  "properties": {
    "addr:full":"Torre, 10 Laraxe A Coru\u00f1a 15622",
    "addr:postcode":"15622",
    "addr:street":"Corun\u0303A",
    "iso:country":"ES",
    "sg:address":"Torre, 10",
    "sg:city":"Laraxe",
    "sg:orig_category":"Transportes Por V\u00cdas Navegables",
    "sg:phone":"+34 981 43 02 25",
    "sg:postcode":"15622",
    "sg:province":"A Coru\u00f1a",
    "wof:name":"Transmi\u00f1o S.l.",
    "wof:placetype":"venue"
},
  "geometry": {"coordinates":[-8.1660118103,43.4209518433],"type":"Point"}
}