{
  "type": "Feature",
  "properties": {
    "addr:full":"Ctra General, S/n Barrio Asturias 33990",
    "addr:postcode":"33990",
    "addr:street":"Ctra General S / N Barrio Asturias",
    "iso:country":"ES",
    "sg:address":"Ctra General, S/n",
    "sg:city":"Barrio",
    "sg:orig_category":"Asociaciones, Organismos Culturales Y Socioeducativos",
    "sg:phone":"+34 985 60 80 61",
    "sg:postcode":"33990",
    "sg:province":"Asturias",
    "wof:name":"Asociacion Centro De Desarrollo Rural Arnicio",
    "wof:placetype":"venue"
},
  "geometry": {"coordinates":[-6.1030440331,43.1163101196],"type":"Point"}
}