{
  "type": "Feature",
  "properties": {
    "addr:full":"Calle de Cadiz, S/n Benahadux Almer\u00eda 04410",
    "addr:housenumber":"s / n",
    "addr:postcode":"04410",
    "addr:street":"Calle De Cadiz",
    "iso:country":"ES",
    "sg:address":"Calle de Cadiz, S/n",
    "sg:city":"Benahadux",
    "sg:orig_category":"Asociaciones Humanitarias, De Cooperaci\u00d3n, De Acci\u00d3n Social",
    "sg:phone":"+34 950 31 11 32",
    "sg:postcode":"04410",
    "sg:province":"Almer\u00eda",
    "wof:name":"Asociacion Comarcal De Minusvalidos Fisicos El Saliente",
    "wof:placetype":"venue"
},
  "geometry": {"coordinates":[-2.4581518173,36.9284934998],"type":"Point"}
}