{
  "type": "Feature",
  "properties": {
    "iso:country":"ES",
    "sg:address":"Pg Francesc Macia, 72",
    "sg:city":"Rubi",
    "sg:orig_category":"Caf\u00c9s, Bares, Cervecer\u00cdas",
    "sg:phone":"+34 936 97 01 41",
    "sg:postcode":"08191",
    "sg:province":"Barcelona",
    "wof:name":"Nebraska Cafeto S.l.",
    "wof:placetype":"venue"
},
  "geometry": {"coordinates":[2.0315899849,41.4907684326],"type":"Point"}
}