{
  "type": "Feature",
  "properties": {
    "addr:full":"Carrer de Major, 21 Amposta Tarragona 43870",
    "addr:housenumber":"21",
    "addr:postcode":"43870",
    "addr:street":"Carrer De Major",
    "iso:country":"ES",
    "sg:address":"Carrer de Major, 21",
    "sg:city":"Amposta",
    "sg:orig_category":"Librer\u00cdas",
    "sg:phone":"+34 977 70 28 95",
    "sg:postcode":"43870",
    "sg:province":"Tarragona",
    "wof:name":"Salvado Caballe Clara",
    "wof:placetype":"venue"
},
  "geometry": {"coordinates":[0.580121994,40.7127685547],"type":"Point"}
}