{
  "type": "Feature",
  "properties": {
    "addr:full":"Calle de Jose Garrote Tobar, 2 Valladolid Valladolid 47014",
    "addr:housenumber":"2",
    "addr:postcode":"47014",
    "addr:street":"Calle De Jose Garrote Tobar",
    "iso:country":"ES",
    "sg:address":"Calle de Jose Garrote Tobar, 2",
    "sg:city":"Valladolid",
    "sg:orig_category":"Frutas, Legumbres Frescas Y Tempranas (al Por Menor)",
    "sg:phone":"+34 983 37 29 04",
    "sg:postcode":"47014",
    "sg:province":"Valladolid",
    "wof:name":"Blanco Aguado Francisco Javier",
    "wof:placetype":"venue"
},
  "geometry": {"coordinates":[-4.7562317848,41.6342163086],"type":"Point"}
}