{
  "type": "Feature",
  "properties": {
    "addr:full":"Souto, 20 S.miguel De Barcala Pontevedra 36683",
    "addr:housenumber":"20",
    "addr:postcode":"36683",
    "addr:street":"Souto",
    "iso:country":"ES",
    "sg:address":"Souto, 20",
    "sg:city":"S.miguel De Barcala",
    "sg:orig_category":"Venta Al Preg\u00d3n",
    "sg:phone":"+34 986 68 96 77",
    "sg:postcode":"36683",
    "sg:province":"Pontevedra",
    "wof:name":"Magan Barreiro Jose Maria",
    "wof:placetype":"venue"
},
  "geometry": {"coordinates":[-8.4296836853,42.6781806946],"type":"Point"}
}