{
  "type": "Feature",
  "properties": {
    "iso:country":"ES",
    "sg:address":"Ten-bel, S/n",
    "sg:city":"Costa Del Silencio",
    "sg:orig_category":"Bazares, Art\u00cdculos De Limpieza Y De Cocina (al Por Menor)",
    "sg:phone":"+34 922 73 06 13",
    "sg:postcode":"38630",
    "sg:province":"Santa Cruz De Tenerife",
    "wof:name":"Sadarangani  Lachman",
    "wof:placetype":"venue"
},
  "geometry": {"coordinates":[-16.6498088837,28.0104541779],"type":"Point"}
}