{
  "type": "Feature",
  "properties": {
    "addr:full":"Calle de Infantes, 2 Elda Alicante 03600",
    "addr:housenumber":"2",
    "addr:postcode":"03600",
    "addr:street":"Calle De Infantes",
    "iso:country":"ES",
    "sg:address":"Calle de Infantes, 2",
    "sg:city":"Elda",
    "sg:orig_category":"Peluquer\u00cdas, Peluquer\u00cda Mixta",
    "sg:phone":"+34 965 39 93 55",
    "sg:postcode":"03600",
    "sg:province":"Alicante",
    "wof:name":"Ba\u00f1on Rico Encarnacion",
    "wof:placetype":"venue"
},
  "geometry": {"coordinates":[-0.7958880067,38.4725151062],"type":"Point"}
}