{
  "type": "Feature",
  "properties": {
    "iso:country":"ES",
    "sg:address":"Ctra Calatayud-alhama, Km. 0039,1",
    "sg:city":"Nuevalos",
    "sg:orig_category":"Zonas De Acampada, Aparcamiento Para Caravanas",
    "sg:phone":"+34 976 84 90 38",
    "sg:postcode":"50210",
    "sg:province":"Zaragoza",
    "wof:name":"Jofesa S. A.",
    "wof:placetype":"venue"
},
  "geometry": {"coordinates":[-1.7890290022,41.212638855],"type":"Point"}
}