{
  "type": "Feature",
  "properties": {
    "iso:country":"ES",
    "sg:address":"Carrer de Abat Escarre, 25",
    "sg:city":"Mataro",
    "sg:orig_category":"Encuadernaci\u00d3n E Impresi\u00d3n De Folletos",
    "sg:phone":"+34 937 57 59 11",
    "sg:postcode":"08302",
    "sg:province":"Barcelona",
    "wof:name":"Divergrup S.c.c.l.",
    "wof:placetype":"venue"
},
  "geometry": {"coordinates":[2.4271769524,41.5301208496],"type":"Point"}
}