{
  "type": "Feature",
  "properties": {
    "iso:country":"ES",
    "sg:address":"Calle de Real, 28",
    "sg:city":"Valle Abdalajis",
    "sg:classifiers":[
        {
            "category":"Taxi",
            "type":"Transportation"
        }
    ],
    "sg:phone":"+34 952 48 81 24",
    "sg:postcode":"29240",
    "sg:province":"M\u00e1laga",
    "wof:name":"Garcia Carrasco Francisco",
    "wof:placetype":"venue"
},
  "geometry": {"coordinates":[-4.6814141273,36.9322433472],"type":"Point"}
}