{
  "type": "Feature",
  "properties": {
    "addr:full":"Carrer de Llobregat, 15 Can Cortes-pedra Llarga Barcelona 08184",
    "addr:housenumber":"15",
    "addr:postcode":"08184",
    "addr:street":"Carrer De Llobregat",
    "iso:country":"ES",
    "sg:address":"Carrer de Llobregat, 15",
    "sg:city":"Can Cortes-pedra Llarga",
    "sg:orig_category":"Poller\u00cda Y Caza (al Por Menor)",
    "sg:phone":"+34 938 66 76 39",
    "sg:postcode":"08184",
    "sg:province":"Barcelona",
    "wof:name":"Perez Monico S.l.",
    "wof:placetype":"venue"
},
  "geometry": {"coordinates":[2.1748299599,41.5814590454],"type":"Point"}
}