{
  "type": "Feature",
  "properties": {
    "addr:full":"Av Manuel Lopez, 9 Santa Maria D'olo Barcelona 08273",
    "addr:housenumber":"9",
    "addr:postcode":"08273",
    "addr:street":"Av Manuel Lopez",
    "iso:country":"ES",
    "sg:address":"Av Manuel Lopez, 9",
    "sg:city":"Santa Maria D'olo",
    "sg:orig_category":"Alimentaci\u00d3n General (al Por Menor)",
    "sg:phone":"+34 938 38 51 39",
    "sg:postcode":"08273",
    "sg:province":"Barcelona",
    "wof:name":"Olle Jubany Jaime",
    "wof:placetype":"venue"
},
  "geometry": {"coordinates":[2.034645319,41.8744888306],"type":"Point"}
}