{
  "type": "Feature",
  "properties": {
    "addr:full":"Calle de Gil Y Polo, 7 Madrid Madrid 28017",
    "addr:housenumber":"7",
    "addr:postcode":"madrid;28017",
    "addr:street":"Calle De Gil Y Polo",
    "iso:country":"ES",
    "sg:address":"Calle de Gil Y Polo, 7",
    "sg:city":"Madrid",
    "sg:orig_category":"Internados & Ense\u00d1anza Privada",
    "sg:phone":"+34 914 07 53 72",
    "sg:postcode":"28017",
    "sg:province":"Madrid",
    "wof:name":"Colegio Maria Reina S. A. L.",
    "wof:placetype":"venue"
},
  "geometry": {"coordinates":[-3.642318964,40.4302024841],"type":"Point"}
}