{
  "type": "Feature",
  "properties": {
    "addr:full":"Calle de Goya, 133 Madrid Madrid 28009",
    "addr:housenumber":"133",
    "addr:postcode":"28009",
    "addr:street":"Calle De Goya",
    "iso:country":"ES",
    "sg:address":"Calle de Goya, 133",
    "sg:city":"Madrid",
    "sg:orig_category":"Peleter\u00cdas",
    "sg:phone":"+34 913 09 05 93",
    "sg:postcode":"28009",
    "sg:province":"Madrid",
    "wof:name":"Rojas Pavon Eusebio",
    "wof:placetype":"venue"
},
  "geometry": {"coordinates":[-3.6700119972,40.4246673584],"type":"Point"}
}