{
  "type": "Feature",
  "properties": {
    "iso:country":"ES",
    "sg:address":"Calle de O\u00d1a, 143",
    "sg:city":"Madrid",
    "sg:orig_category":"Material Y Suministros Para Fotocopiadoras, Reprograf\u00cda",
    "sg:phone":"+34 917 66 11 95",
    "sg:postcode":"28050",
    "sg:province":"Madrid",
    "wof:name":"Dentages S.l.",
    "wof:placetype":"venue"
},
  "geometry": {"coordinates":[-3.6622350216,40.4894371033],"type":"Point"}
}