{
  "type": "Feature",
  "properties": {
    "iso:country":"ES",
    "sg:address":"Carr Otger, 2",
    "sg:city":"Badalona",
    "sg:orig_category":"Farmacias",
    "sg:phone":"+34 933 87 47 87",
    "sg:postcode":"08917",
    "sg:province":"Barcelona",
    "wof:name":"Barloque Trius Nuria",
    "wof:placetype":"venue"
},
  "geometry": {"coordinates":[2.2216889858,41.4528656006],"type":"Point"}
}