{
  "type": "Feature",
  "properties": {
    "addr:full":"Avda De La Mediterranea, 21 Moncada Valencia 46113",
    "addr:housenumber":"21",
    "addr:postcode":"46113",
    "addr:street":"Avda De La Mediterranea",
    "iso:country":"ES",
    "sg:address":"Avda De La Mediterranea, 21",
    "sg:city":"Moncada",
    "sg:orig_category":"M\u00c9dicos: Pediatr\u00cda. Enfermedades De Los Ni\u00d1os",
    "sg:phone":"+34 961 30 32 23",
    "sg:postcode":"46113",
    "sg:province":"Valencia",
    "wof:name":"Miranda Mallea Javier",
    "wof:placetype":"venue"
},
  "geometry": {"coordinates":[-0.3955839872,39.5440063477],"type":"Point"}
}