{
  "type": "Feature",
  "properties": {
    "addr:full":"Avda Martin Alonso Pinzon, 10 Huelva Huelva 21003",
    "addr:housenumber":"10",
    "addr:postcode":"21003",
    "addr:street":"Avda Martin Alonso Pinzon",
    "iso:country":"ES",
    "sg:address":"Avda Martin Alonso Pinzon, 10",
    "sg:city":"Huelva",
    "sg:orig_category":"Mutuas De Seguros",
    "sg:phone":"+34 959 24 85 45",
    "sg:postcode":"21003",
    "sg:province":"Huelva",
    "wof:name":"Mutua General Seguros",
    "wof:placetype":"venue"
},
  "geometry": {"coordinates":[-6.9490199089,37.2558746338],"type":"Point"}
}