{
  "type": "Feature",
  "properties": {
    "addr:full":"Calle de Santa Ana (de), 4 Paracuellos De Jarama Madrid 28860",
    "addr:postcode":"28860",
    "addr:street":"Calle De",
    "iso:country":"ES",
    "sg:address":"Calle de Santa Ana (de), 4",
    "sg:city":"Paracuellos De Jarama",
    "sg:orig_category":"Barbacoas Y Accesorios",
    "sg:phone":"+34 916 58 06 29",
    "sg:postcode":"28860",
    "sg:province":"Madrid",
    "wof:name":"Bar Restaurante El Pela S.l.",
    "wof:placetype":"venue"
},
  "geometry": {"coordinates":[-3.5319979191,40.5044021606],"type":"Point"}
}