{
  "type": "Feature",
  "properties": {
    "addr:full":"Calle de A\u00d1astro, 16 Madrid Madrid 28033",
    "addr:housenumber":"16",
    "addr:postcode":"madrid;28033",
    "addr:street":"Calle De An\u0303Astro",
    "iso:country":"ES",
    "sg:address":"Calle de A\u00d1astro, 16",
    "sg:city":"Madrid",
    "sg:orig_category":"Peluquer\u00cdas, Peluquer\u00cda Mixta",
    "sg:phone":"+34 913 02 47 09",
    "sg:postcode":"28033",
    "sg:province":"Madrid",
    "wof:name":"Ara Moreno Angel Felipe",
    "wof:placetype":"venue"
},
  "geometry": {"coordinates":[-3.6620109081,40.468547821],"type":"Point"}
}