{
  "type": "Feature",
  "properties": {
    "addr:full":"Carr Clot, 11 Deya Islas Baleares 07179",
    "addr:housenumber":"11",
    "addr:postcode":"07179",
    "addr:street":"Carr Clot;Islas",
    "iso:country":"ES",
    "sg:address":"Carr Clot, 11",
    "sg:city":"Deya",
    "sg:orig_category":"Confecci\u00d3n (fabricaci\u00d3n, Al Por Mayor)",
    "sg:phone":"+34 971 63 95 04",
    "sg:postcode":"07179",
    "sg:province":"Islas Baleares",
    "wof:name":"Anderson Raphael Claire",
    "wof:placetype":"venue"
},
  "geometry": {"coordinates":[2.6451067924,39.7470359802],"type":"Point"}
}