{
  "type": "Feature",
  "properties": {
    "addr:full":"Carr Puig D'esquer, 4 Bateria Girona 17490",
    "addr:housenumber":"4",
    "addr:postcode":"17490",
    "addr:street":"Carr Puig D'Esquer",
    "iso:country":"ES",
    "sg:address":"Carr Puig D'esquer, 4",
    "sg:city":"Bateria",
    "sg:orig_category":"Albergues",
    "sg:phone":"+34 972 38 02 70",
    "sg:postcode":"17490",
    "sg:province":"Girona",
    "wof:name":"Pau Germillach Jose",
    "wof:placetype":"venue"
},
  "geometry": {"coordinates":[2.8097579479,41.9930419922],"type":"Point"}
}