{
  "type": "Feature",
  "properties": {
    "iso:country":"ES",
    "sg:address":"Calle de Rua Mayor, 13",
    "sg:city":"Salamanca",
    "sg:orig_category":"Fabricaci\u00d3n De Art\u00cdculos Para Papeler\u00cdas",
    "sg:phone":"+34 923 21 20 52",
    "sg:postcode":"37002",
    "sg:province":"Salamanca",
    "wof:name":"Hijos De Francisco Nu\u00f1ez S. R. C.",
    "wof:placetype":"venue"
},
  "geometry": {"coordinates":[-5.6649308205,40.963306427],"type":"Point"}
}