{
  "type": "Feature",
  "properties": {
    "iso:country":"ES",
    "sg:address":"Calle de General Gomez Nu\u00d1ez, 44",
    "sg:city":"Ponferrada",
    "sg:orig_category":"Confiter\u00cdas, Chocolater\u00cdas (al Por Menor)",
    "sg:phone":"+34 987 41 20 40",
    "sg:postcode":"24400",
    "sg:province":"Le\u00f3n",
    "wof:name":"Sanchez De Los Cobos Miguel Angel",
    "wof:placetype":"venue"
},
  "geometry": {"coordinates":[-6.5975089073,42.5488090515],"type":"Point"}
}