{
  "type": "Feature",
  "properties": {
    "iso:country":"ES",
    "sg:address":"C/ San Crispin, 8",
    "sg:city":"Torrellano",
    "sg:orig_category":"Pescader\u00cdas (al Por Menor)",
    "sg:phone":"+34 965 68 04 33",
    "sg:postcode":"03320",
    "sg:province":"Alicante",
    "wof:name":"Agullo Molla Jose Juan",
    "wof:placetype":"venue"
},
  "geometry": {"coordinates":[-0.5874937177,38.2939300537],"type":"Point"}
}