{
  "type": "Feature",
  "properties": {
    "addr:full":"Calle de Occidente, 6 Arroyo De La Miel-benalmadena Costa M\u00e1laga 29630",
    "addr:housenumber":"6",
    "addr:postcode":"29630",
    "addr:street":"Calle De Occidente;Arroyo De La Miel-Benalmadena Costa Ma\u0301Laga",
    "iso:country":"ES",
    "sg:address":"Calle de Occidente, 6",
    "sg:city":"Arroyo De La Miel-benalmadena Costa",
    "sg:orig_category":"Tapiceros Y Tapiceros",
    "sg:phone":"+34 952 57 50 86",
    "sg:postcode":"29630",
    "sg:province":"M\u00e1laga",
    "wof:name":"Bermudez Moreno Juan Jose",
    "wof:placetype":"venue"
},
  "geometry": {"coordinates":[-4.5224218369,36.5994186401],"type":"Point"}
}