{
  "type": "Feature",
  "properties": {
    "addr:full":"Av Generalitat (de La), 13 Tortosa Tarragona 43500",
    "addr:housenumber":"13",
    "addr:postcode":"43500",
    "addr:street":"Av Generalitat De La",
    "iso:country":"ES",
    "sg:address":"Av Generalitat (de La), 13",
    "sg:city":"Tortosa",
    "sg:orig_category":"Mercer\u00cda, Lencer\u00cda (al Por Menor)",
    "sg:phone":"+34 977 44 02 76",
    "sg:postcode":"43500",
    "sg:province":"Tarragona",
    "wof:name":"Mascarell Ferre Salvador",
    "wof:placetype":"venue"
},
  "geometry": {"coordinates":[0.5208179951,40.8118095398],"type":"Point"}
}