{
  "type": "Feature",
  "properties": {
    "addr:full":"Calle de Armando Mu\u00d1oz Calero, 8 Aguilas Murcia 30880",
    "addr:housenumber":"8",
    "addr:postcode":"30880",
    "addr:street":"Calle De Armando Mun\u0303Oz Calero",
    "iso:country":"ES",
    "sg:address":"Calle de Armando Mu\u00d1oz Calero, 8",
    "sg:city":"Aguilas",
    "sg:orig_category":"Quincaller\u00cda (al Por Menor)",
    "sg:phone":"+34 968 41 39 03",
    "sg:postcode":"30880",
    "sg:province":"Murcia",
    "wof:name":"Ferretaymar S.l",
    "wof:placetype":"venue"
},
  "geometry": {"coordinates":[-1.5853351355,37.4045829773],"type":"Point"}
}