{
  "type": "Feature",
  "properties": {
    "iso:country":"ES",
    "sg:address":"Calle de Concepcion Arenal, 2",
    "sg:city":"Castellon",
    "sg:orig_category":"Arquitectos",
    "sg:phone":"+34 964 20 12 83",
    "sg:postcode":"12004",
    "sg:province":"Castell\u00f3n",
    "wof:name":"Acantto Estudio De Arquitectura Y Urbanismo S.l.",
    "wof:placetype":"venue"
},
  "geometry": {"coordinates":[-0.0428932011,39.9893875122],"type":"Point"}
}