{
  "type": "Feature",
  "properties": {
    "iso:country":"ES",
    "sg:address":"Calle de Caceres, 1",
    "sg:city":"Madrid",
    "sg:orig_category":"Complementos De Vestir (al Por Menor)",
    "sg:phone":"+34 915 30 52 23",
    "sg:postcode":"28045",
    "sg:province":"Madrid",
    "wof:name":"Rodriguez Afonso C.b.",
    "wof:placetype":"venue"
},
  "geometry": {"coordinates":[-3.6943120956,40.3984870911],"type":"Point"}
}