{
  "type": "Feature",
  "properties": {
    "addr:full":"Avda Constitucion, 98 Villena Alicante 03400",
    "addr:housenumber":"98",
    "addr:postcode":"03400",
    "addr:street":"Avda Constitucion",
    "iso:country":"ES",
    "sg:address":"Avda Constitucion, 98",
    "sg:city":"Villena",
    "sg:orig_category":"Farmacias",
    "sg:phone":"+34 965 80 14 73",
    "sg:postcode":"03400",
    "sg:province":"Alicante",
    "wof:name":"Lopez Jornet Mercedes",
    "wof:placetype":"venue"
},
  "geometry": {"coordinates":[-0.8657109737,38.6358032227],"type":"Point"}
}