{
  "type": "Feature",
  "properties": {
    "addr:full":"Rua Padre Sarmiento, 15 Portonovo Pontevedra 36970",
    "addr:housenumber":"15",
    "addr:postcode":"36970",
    "addr:street":"Rua Padre Sarmiento",
    "iso:country":"ES",
    "sg:address":"Rua Padre Sarmiento, 15",
    "sg:city":"Portonovo",
    "sg:orig_category":"Inmobiliaria (agencias)",
    "sg:phone":"+34 986 69 14 06",
    "sg:postcode":"36970",
    "sg:province":"Pontevedra",
    "wof:name":"Promociones Inmobiliarias Maryalvarez S.l",
    "wof:placetype":"venue"
},
  "geometry": {"coordinates":[-8.8286962509,42.3900756836],"type":"Point"}
}