{
  "type": "Feature",
  "properties": {
    "iso:country":"ES",
    "sg:address":"Av Marti Genis I Aguilar, 31",
    "sg:city":"Vic",
    "sg:orig_category":"Venta, Instalaci\u00d3n De Calefacci\u00d3n",
    "sg:phone":"+34 938 85 08 53",
    "sg:postcode":"08500",
    "sg:province":"Barcelona",
    "wof:name":"Calefaccions J.vinyeta S.l.",
    "wof:placetype":"venue"
},
  "geometry": {"coordinates":[2.2562088966,41.9249954224],"type":"Point"}
}