{
  "type": "Feature",
  "properties": {
    "addr:full":"Calle de Santa Ana, 27 Estepa Sevilla 41560",
    "addr:housenumber":"27",
    "addr:postcode":"41560",
    "addr:street":"Calle De Santa Ana;Sevilla",
    "iso:country":"ES",
    "sg:address":"Calle de Santa Ana, 27",
    "sg:city":"Estepa",
    "sg:orig_category":"M\u00c9dicos: Oftalmolog\u00cda",
    "sg:phone":"+34 955 91 35 39",
    "sg:postcode":"41560",
    "sg:province":"Sevilla",
    "wof:name":"Pulido Aguilera Maria Del Carmen",
    "wof:placetype":"venue"
},
  "geometry": {"coordinates":[-4.8760910034,37.2916183472],"type":"Point"}
}