{
  "type": "Feature",
  "properties": {
    "iso:country":"ES",
    "sg:address":"Ctra Caceres (pi Plasencia), S/n",
    "sg:city":"Plasencia",
    "sg:orig_category":"Panader\u00cdas, Pasteler\u00cdas, Boller\u00cda Industriale (fabricaci\u00d3n, Al Por Mayor)",
    "sg:phone":"+34 927 41 64 50",
    "sg:postcode":"10600",
    "sg:province":"C\u00e1ceres",
    "wof:name":"Leon Corral Maria Del Carmen",
    "wof:placetype":"venue"
},
  "geometry": {"coordinates":[-6.0898518562,40.0299453735],"type":"Point"}
}