{
  "type": "Feature",
  "properties": {
    "iso:country":"ES",
    "sg:address":"Calle de San Quintin, 9",
    "sg:city":"Fraga",
    "sg:orig_category":"Sindicatos De Trabajadores",
    "sg:phone":"+34 974 47 03 39",
    "sg:postcode":"22520",
    "sg:province":"Huesca",
    "wof:name":"Union Sindical De Comisiones Obreras De Aragon",
    "wof:placetype":"venue"
},
  "geometry": {"coordinates":[0.349404186,41.520488739],"type":"Point"}
}