{
  "type": "Feature",
  "properties": {
    "addr:full":"Calle de Marina Lavandeira, 12 Madrid Madrid 28025",
    "addr:housenumber":"12",
    "addr:postcode":"madrid;28025",
    "addr:street":"Calle De Marina Lavandeira",
    "iso:country":"ES",
    "sg:address":"Calle de Marina Lavandeira, 12",
    "sg:city":"Madrid",
    "sg:orig_category":"Construcciones Met\u00c1licas",
    "sg:phone":"+34 914 65 01 82",
    "sg:postcode":"28025",
    "sg:province":"Madrid",
    "wof:name":"Rubio Diez Rosel Leon",
    "wof:placetype":"venue"
},
  "geometry": {"coordinates":[-3.7404060364,40.3872299194],"type":"Point"}
}