{
  "type": "Feature",
  "properties": {
    "addr:full":"Ctra San Vicente, 9 Valle Trapaga Vizcaya 48510",
    "addr:housenumber":"9",
    "addr:postcode":"48510",
    "addr:street":"Ctra San Vicente;Trapaga",
    "iso:country":"ES",
    "sg:address":"Ctra San Vicente, 9",
    "sg:city":"Valle Trapaga",
    "sg:orig_category":"Alquiler De Gr\u00daas",
    "sg:phone":"+34 944 62 51 21",
    "sg:postcode":"48510",
    "sg:province":"Vizcaya",
    "wof:name":"Montajes Gertu S.a.l.",
    "wof:placetype":"venue"
},
  "geometry": {"coordinates":[-3.0249938965,43.299949646],"type":"Point"}
}