{
  "type": "Feature",
  "properties": {
    "addr:full":"Ctra Villafria, 16 Orbaneja-riopico Burgos 09192",
    "addr:housenumber":"16",
    "addr:postcode":"09192",
    "addr:street":"Ctra Villafria",
    "iso:country":"ES",
    "sg:address":"Ctra Villafria, 16",
    "sg:city":"Orbaneja-riopico",
    "sg:orig_category":"Empresas De Carpinter\u00cda Met\u00c1lica",
    "sg:phone":"+34 947 43 09 03",
    "sg:postcode":"09192",
    "sg:province":"Burgos",
    "wof:name":"Manso Pastor Jose Antonio",
    "wof:placetype":"venue"
},
  "geometry": {"coordinates":[-3.5605039597,42.3589515686],"type":"Point"}
}