{
  "type": "Feature",
  "properties": {
    "iso:country":"ES",
    "sg:address":"Veinat De Valldeix, S/n",
    "sg:city":"Mataro",
    "sg:orig_category":"Cr\u00cda De Animales",
    "sg:phone":"+34 937 90 29 84",
    "sg:postcode":"08304",
    "sg:province":"Barcelona",
    "wof:name":"Santamaria Abajo Enrique",
    "wof:placetype":"venue"
},
  "geometry": {"coordinates":[2.4698801041,41.5688247681],"type":"Point"}
}