{
  "type": "Feature",
  "properties": {
    "iso:country":"ES",
    "sg:address":"Calle de Borrero, 11",
    "sg:city":"Pedro\u00d1eras",
    "sg:orig_category":"Inmobiliaria (agencias)",
    "sg:phone":"+34 967 16 01 53",
    "sg:postcode":"16660",
    "sg:province":"Cuenca",
    "wof:name":"Proyectos Integrales Fincasa S.l.l.",
    "wof:placetype":"venue"
},
  "geometry": {"coordinates":[-2.6716320515,39.4476890564],"type":"Point"}
}