{
  "type": "Feature",
  "properties": {
    "addr:full":"Calle de Serpis, 64 Valencia Valencia 46022",
    "addr:housenumber":"64",
    "addr:postcode":"46022",
    "addr:street":"Calle De Serpis",
    "iso:country":"ES",
    "sg:address":"Calle de Serpis, 64",
    "sg:city":"Valencia",
    "sg:orig_category":"Ingenier\u00cda, Centros De Estudios (diversos)",
    "sg:phone":"+34 963 89 10 21",
    "sg:postcode":"46022",
    "sg:province":"Valencia",
    "wof:name":"Avl Iberica S.a.",
    "wof:placetype":"venue"
},
  "geometry": {"coordinates":[-0.3431592882,39.474357605],"type":"Point"}
}