{
  "type": "Feature",
  "properties": {
    "iso:country":"ES",
    "sg:address":"Rua Republica Argentina, 7",
    "sg:city":"Vigo",
    "sg:orig_category":"Molduras, Junquillos, Listones Y Molduras Perforadas",
    "sg:phone":"+34 986 22 65 99",
    "sg:postcode":"36201",
    "sg:province":"Pontevedra",
    "wof:name":"Peti C.b.",
    "wof:placetype":"venue"
},
  "geometry": {"coordinates":[-8.7175588608,42.2388267517],"type":"Point"}
}