{
  "type": "Feature",
  "properties": {
    "addr:full":"Monasterio Irache, 44 Iru\u00f1a Navarra 31011",
    "addr:housenumber":"44",
    "addr:postcode":"31011",
    "addr:street":"Irache",
    "iso:country":"ES",
    "sg:address":"Monasterio Irache, 44",
    "sg:city":"Iru\u00f1a",
    "sg:orig_category":"Cr\u00cda De Animales De Caza Menor",
    "sg:phone":"+34 948 26 00 83",
    "sg:postcode":"31011",
    "sg:province":"Navarra",
    "sg:website":"www.fedecaza.com",
    "wof:name":"Oneca Ardanaz Nicasia",
    "wof:placetype":"venue"
},
  "geometry": {"coordinates":[-1.6633349657,42.8160820007],"type":"Point"}
}