{
  "type": "Feature",
  "properties": {
    "addr:full":"Avda Extremadura, 158 Santa Marta Badajoz 06150",
    "addr:housenumber":"158",
    "addr:postcode":"06150",
    "addr:street":"Avda Extremadura",
    "iso:country":"ES",
    "sg:address":"Avda Extremadura, 158",
    "sg:city":"Santa Marta",
    "sg:orig_category":"Organizaciones Internacionales",
    "sg:phone":"+34 924 69 07 68",
    "sg:postcode":"06150",
    "sg:province":"Badajoz",
    "wof:name":"Apag-extremadura Jovenes Agricultores Y Ganaderos",
    "wof:placetype":"venue"
},
  "geometry": {"coordinates":[-6.6677956581,38.7264709473],"type":"Point"}
}