{
  "type": "Feature",
  "properties": {
    "iso:country":"ES",
    "sg:address":"Calle de Doctor Fleming, S/n",
    "sg:city":"Espera",
    "sg:orig_category":"Combustibles: Fuel",
    "sg:phone":"+34 956 72 00 12",
    "sg:postcode":"11648",
    "sg:province":"C\u00e1diz",
    "sg:website":"www.garrucho.com",
    "wof:name":"Gestion Rivero S.a.",
    "wof:placetype":"venue"
},
  "geometry": {"coordinates":[-5.8064508438,36.8697128296],"type":"Point"}
}