{
  "type": "Feature",
  "properties": {
    "addr:full":"Calle de Helgueras, 30 Noja Cantabria 39180",
    "addr:housenumber":"30",
    "addr:postcode":"39180",
    "addr:street":"Calle De Helgueras",
    "iso:country":"ES",
    "sg:address":"Calle de Helgueras, 30",
    "sg:city":"Noja",
    "sg:orig_category":"Carnicer\u00cdas, Carnicer\u00cdas",
    "sg:phone":"+34 942 63 13 36",
    "sg:postcode":"39180",
    "sg:province":"Cantabria",
    "wof:name":"Pelayo Portilla Adolfo",
    "wof:placetype":"venue"
},
  "geometry": {"coordinates":[-3.505669117,43.4724082947],"type":"Point"}
}