{
  "type": "Feature",
  "properties": {
    "addr:full":"Canar Es, 14 Sta. Eularia Riu Islas Baleares 07840",
    "addr:housenumber":"14",
    "addr:postcode":"07840",
    "addr:street":"Es;Baleares",
    "iso:country":"ES",
    "sg:address":"Canar Es, 14",
    "sg:city":"Sta. Eularia Riu",
    "sg:orig_category":"Doctores En Medicina",
    "sg:phone":"+34 971 33 83 73",
    "sg:postcode":"07840",
    "sg:province":"Islas Baleares",
    "wof:name":"Lukata  Al Najjar",
    "wof:placetype":"venue"
},
  "geometry": {"coordinates":[1.5341850519,38.9850311279],"type":"Point"}
}