{
  "type": "Feature",
  "properties": {
    "addr:full":"Calle de Monsalupe, 14 Madrid Madrid 28047",
    "addr:housenumber":"14",
    "addr:postcode":"madrid;28047",
    "addr:street":"Calle De Monsalupe",
    "iso:country":"ES",
    "sg:address":"Calle de Monsalupe, 14",
    "sg:city":"Madrid",
    "sg:orig_category":"Centros Empresariales",
    "sg:phone":"+34 914 63 19 57",
    "sg:postcode":"28047",
    "sg:province":"Madrid",
    "sg:website":"www.aquimisa.com",
    "wof:name":"Aquimisa S.l.",
    "wof:placetype":"venue"
},
  "geometry": {"coordinates":[-3.7534708977,40.4009056091],"type":"Point"}
}