{
  "type": "Feature",
  "properties": {
    "addr:full":"Calle de Virgen De La Monjia, 1 Madrid Madrid 28027",
    "addr:housenumber":"1",
    "addr:postcode":"28027",
    "addr:street":"Calle De Virgen De La Monjia",
    "iso:country":"ES",
    "sg:address":"Calle de Virgen De La Monjia, 1",
    "sg:city":"Madrid",
    "sg:orig_category":"Empresas De Limpieza",
    "sg:phone":"+34 913 26 01 19",
    "sg:postcode":"28027",
    "sg:province":"Madrid",
    "wof:name":"Alcalimp S.l.",
    "wof:placetype":"venue"
},
  "geometry": {"coordinates":[-3.6516265869,40.4369392395],"type":"Point"}
}