{
  "type": "Feature",
  "properties": {
    "addr:full":"Pl Tetuan, 3 Barcelona Barcelona 08010",
    "addr:housenumber":"3",
    "addr:postcode":"08010",
    "addr:street":"Pl Tetuan",
    "iso:country":"ES",
    "sg:address":"Pl Tetuan, 3",
    "sg:city":"Barcelona",
    "sg:orig_category":"Mutuas De Seguros",
    "sg:phone":"+34 932 65 67 00",
    "sg:postcode":"08010",
    "sg:province":"Barcelona",
    "wof:name":"Mutua Previsora Barcelona",
    "wof:placetype":"venue"
},
  "geometry": {"coordinates":[2.1758239269,41.394241333],"type":"Point"}
}