{
  "type": "Feature",
  "properties": {
    "iso:country":"ES",
    "sg:address":"Carr Emili Grahit, 13",
    "sg:city":"Girona",
    "sg:orig_category":"Ingeniero",
    "sg:phone":"+34 972 20 37 83",
    "sg:postcode":"17002",
    "sg:province":"Girona",
    "wof:name":"Carreras Arnau Ramon",
    "wof:placetype":"venue"
},
  "geometry": {"coordinates":[2.8183860779,41.9753952026],"type":"Point"}
}