{
  "type": "Feature",
  "properties": {
    "addr:full":"Pase San Roque (de), 19 Avila \u00c1vila 05003",
    "addr:postcode":"05003",
    "addr:street":"A\u0301Vila",
    "iso:country":"ES",
    "sg:address":"Pase San Roque (de), 19",
    "sg:city":"Avila",
    "sg:orig_category":"Ropa Para Se\u00d1oras (al Por Menor)",
    "sg:phone":"+34 920 21 17 39",
    "sg:postcode":"05003",
    "sg:province":"\u00c1vila",
    "wof:name":"Robles Garcia Azucena",
    "wof:placetype":"venue"
},
  "geometry": {"coordinates":[-4.6887078285,40.6537284851],"type":"Point"}
}