{
  "type": "Feature",
  "properties": {
    "iso:country":"ES",
    "sg:address":"Carrer de Major, 26",
    "sg:city":"Amposta",
    "sg:orig_category":"Telas Y Sedas (al Por Menor)",
    "sg:phone":"+34 977 70 00 71",
    "sg:postcode":"43870",
    "sg:province":"Tarragona",
    "wof:name":"Casa Chorda S.l.",
    "wof:placetype":"venue"
},
  "geometry": {"coordinates":[0.5804409981,40.7126426697],"type":"Point"}
}