{
  "type": "Feature",
  "properties": {
    "iso:country":"ES",
    "sg:address":"Carr Censals (de), 15",
    "sg:city":"Lliria",
    "sg:orig_category":"Granos Y Forrajes",
    "sg:phone":"+34 962 79 20 18",
    "sg:postcode":"46160",
    "sg:province":"Valencia",
    "wof:name":"Garrofas Quiles Y Ortiz S.a.",
    "wof:placetype":"venue"
},
  "geometry": {"coordinates":[-0.5903626084,39.6365890503],"type":"Point"}
}