{
  "type": "Feature",
  "properties": {
    "iso:country":"ES",
    "sg:address":"Luga Explanada Tomas Quevedo, S/n",
    "sg:city":"Palmas De Gran Canaria",
    "sg:orig_category":"Distribuci\u00d3n De Petr\u00d3leo Y Derivados",
    "sg:phone":"+34 928 46 83 76",
    "sg:postcode":"35008",
    "sg:province":"Las Palmas",
    "wof:name":"Pescados Amaro Gonzalez S. A.",
    "wof:placetype":"venue"
},
  "geometry": {"coordinates":[-15.419380188,28.1532001495],"type":"Point"}
}