{
  "type": "Feature",
  "properties": {
    "iso:country":"ES",
    "sg:address":"Calle de Olof Palme, 23",
    "sg:city":"Palmas De Gran Canaria",
    "sg:orig_category":"Ense\u00d1ante, Direcci\u00d3n",
    "sg:phone":"+34 928 22 00 04",
    "sg:postcode":"35010",
    "sg:province":"Las Palmas",
    "wof:name":"Arbelo Gonzalez Miguel",
    "wof:placetype":"venue"
},
  "geometry": {"coordinates":[-15.43663311,28.1351699829],"type":"Point"}
}