{
  "type": "Feature",
  "properties": {
    "addr:full":"Avda Republica Argentina, 54 Miranda Ebro Burgos 09200",
    "addr:housenumber":"54",
    "addr:postcode":"09200",
    "addr:street":"Avda Republica Argentina",
    "iso:country":"ES",
    "sg:address":"Avda Republica Argentina, 54",
    "sg:city":"Miranda Ebro",
    "sg:orig_category":"Cajas De Ahorro",
    "sg:phone":"+34 947 34 74 35",
    "sg:postcode":"09200",
    "sg:province":"Burgos",
    "sg:website":"www.cajalaboral.es",
    "wof:name":"Caja Laboral Popular",
    "wof:placetype":"venue"
},
  "geometry": {"coordinates":[-2.9394900799,42.686126709],"type":"Point"}
}