{
  "type": "Feature",
  "properties": {
    "iso:country":"ES",
    "sg:address":"Carrer de Jaume Vicens I Vives, 7",
    "sg:city":"Barcelona",
    "sg:orig_category":"Arquitectos",
    "sg:phone":"+34 932 21 05 91",
    "sg:postcode":"08005",
    "sg:province":"Barcelona",
    "wof:name":"Moro Domingo Antonio",
    "wof:placetype":"venue"
},
  "geometry": {"coordinates":[2.2020759583,41.3933982849],"type":"Point"}
}