{
  "type": "Feature",
  "properties": {
    "iso:country":"ES",
    "sg:address":"Calle de Estanco (del), 2",
    "sg:city":"Colmenar Viejo",
    "sg:orig_category":"Frutas, Legumbres Frescas Y Tempranas (al Por Menor)",
    "sg:phone":"+34 918 45 22 10",
    "sg:postcode":"28770",
    "sg:province":"Madrid",
    "wof:name":"Pinilla Cancela Miguel",
    "wof:placetype":"venue"
},
  "geometry": {"coordinates":[-3.765730381,40.6591491699],"type":"Point"}
}