{
  "type": "Feature",
  "properties": {
    "addr:full":"Avda Andalucia, 28 Gibraleon Huelva 21500",
    "addr:housenumber":"28",
    "addr:postcode":"21500",
    "addr:street":"Avda Andalucia",
    "iso:country":"ES",
    "sg:address":"Avda Andalucia, 28",
    "sg:city":"Gibraleon",
    "sg:orig_category":"Estancos",
    "sg:phone":"+34 959 30 19 60",
    "sg:postcode":"21500",
    "sg:province":"Huelva",
    "wof:name":"Gonzalez Hermoso Alfredo",
    "wof:placetype":"venue"
},
  "geometry": {"coordinates":[-6.9682898521,37.375629425],"type":"Point"}
}