{
  "type": "Feature",
  "properties": {
    "addr:full":"Rua Sanjurjo Badia, 109 Vigo Pontevedra 36207",
    "addr:housenumber":"109",
    "addr:postcode":"36207",
    "addr:street":"Rua Sanjurjo Badia",
    "iso:country":"ES",
    "sg:address":"Rua Sanjurjo Badia, 109",
    "sg:city":"Vigo",
    "sg:orig_category":"Servicios Gsm",
    "sg:phone":"+34 986 27 00 60",
    "sg:postcode":"36207",
    "sg:province":"Pontevedra",
    "wof:name":"Blucom Redes Y Comunicaciones S.l.",
    "wof:placetype":"venue"
},
  "geometry": {"coordinates":[-8.7010154724,42.2465858459],"type":"Point"}
}