{
  "type": "Feature",
  "properties": {
    "iso:country":"ES",
    "sg:address":"Calle de Zurbaran, 1",
    "sg:city":"Alcala Henares",
    "sg:orig_category":"Supermercados Y Hipermercados",
    "sg:phone":"+34 918 82 37 24",
    "sg:postcode":"28802",
    "sg:province":"Madrid",
    "wof:name":"Todymas S.a.",
    "wof:placetype":"venue"
},
  "geometry": {"coordinates":[-3.3768239021,40.4757156372],"type":"Point"}
}