{
  "type": "Feature",
  "properties": {
    "addr:full":"Fuente De La Mora, S/n Antequera M\u00e1laga 29200",
    "addr:housenumber":"s",
    "addr:postcode":"29200",
    "addr:street":"/ N;Ma\u0301Laga",
    "iso:country":"ES",
    "sg:address":"Fuente De La Mora, S/n",
    "sg:city":"Antequera",
    "sg:orig_category":"Promotores Constructores",
    "sg:phone":"+34 952 70 23 55",
    "sg:postcode":"29200",
    "sg:province":"M\u00e1laga",
    "wof:name":"Bermudez Delgado E Hijos S.l.",
    "wof:placetype":"venue"
},
  "geometry": {"coordinates":[-4.5759592056,37.0178337097],"type":"Point"}
}