{
  "type": "Feature",
  "properties": {
    "iso:country":"ES",
    "sg:address":"Calle de Victoriano Fernandez, 57",
    "sg:city":"San Roman",
    "sg:orig_category":"Fabricaci\u00d3n De Ventanas",
    "sg:phone":"+34 942 34 80 84",
    "sg:postcode":"39012",
    "sg:province":"Cantabria",
    "wof:name":"Eurovent Manu Metalicas S.l.",
    "wof:placetype":"venue"
},
  "geometry": {"coordinates":[-3.8596680164,43.4700202942],"type":"Point"}
}