{
  "type": "Feature",
  "properties": {
    "addr:full":"Calle de Mendibile, 1 Leioa Vizcaya 48940",
    "addr:housenumber":"1",
    "addr:postcode":"48940",
    "addr:street":"Calle De Mendibile",
    "iso:country":"ES",
    "sg:address":"Calle de Mendibile, 1",
    "sg:city":"Leioa",
    "sg:orig_category":"Electricidad: Instaladores",
    "sg:phone":"+34 944 64 20 18",
    "sg:postcode":"48940",
    "sg:province":"Vizcaya",
    "wof:name":"Udaille",
    "wof:placetype":"venue"
},
  "geometry": {"coordinates":[-2.9828679562,43.3242225647],"type":"Point"}
}