{
  "type": "Feature",
  "properties": {
    "addr:full":"Calle de Prim, 44 Badajoz Badajoz 06001",
    "addr:housenumber":"44",
    "addr:postcode":"06001",
    "addr:street":"Calle De Prim",
    "iso:country":"ES",
    "sg:address":"Calle de Prim, 44",
    "sg:city":"Badajoz",
    "sg:orig_category":"Abogados",
    "sg:phone":"+34 924 22 28 42",
    "sg:postcode":"06001",
    "sg:province":"Badajoz",
    "wof:name":"Tellez Valdes Javier",
    "wof:placetype":"venue"
},
  "geometry": {"coordinates":[-6.9748058319,38.8800392151],"type":"Point"}
}