{
  "type": "Feature",
  "properties": {
    "iso:country":"ES",
    "sg:address":"Calle de San Jorge, 2",
    "sg:city":"Villanueva Carrizo",
    "sg:orig_category":"Iglesia Cat\u00d3lica",
    "sg:phone":"+34 987 35 85 42",
    "sg:postcode":"24270",
    "sg:province":"Le\u00f3n",
    "wof:name":"Parroquia De Villanueva De Carrizo",
    "wof:placetype":"venue"
},
  "geometry": {"coordinates":[-5.8166742325,42.5773086548],"type":"Point"}
}