{
  "type": "Feature",
  "properties": {
    "iso:country":"ES",
    "sg:address":"Avda Virgen Del Carmen, 27",
    "sg:city":"Algeciras",
    "sg:orig_category":"Abogados",
    "sg:phone":"+34 956 63 02 63",
    "sg:postcode":"11201",
    "sg:province":"C\u00e1diz",
    "wof:name":"Jaramillo De Nova Ernestina",
    "wof:placetype":"venue"
},
  "geometry": {"coordinates":[-5.4454498291,36.1307220459],"type":"Point"}
}