{
  "type": "Feature",
  "properties": {
    "addr:full":"Del Mar, 60 Torre Mar M\u00e1laga 29740",
    "addr:housenumber":"60",
    "addr:postcode":"29740",
    "addr:street":"Del Mar;Ma\u0301Laga",
    "iso:country":"ES",
    "sg:address":"Del Mar, 60",
    "sg:city":"Torre Mar",
    "sg:orig_category":"Muebles Y Accesorios Para Cocinas Y Cuartos De Ba\u00d1o (al Por Menor)",
    "sg:phone":"+34 952 54 55 27",
    "sg:postcode":"29740",
    "sg:province":"M\u00e1laga",
    "wof:name":"Muebles Torresur S.l.",
    "wof:placetype":"venue"
},
  "geometry": {"coordinates":[-4.3590788841,36.7187805176],"type":"Point"}
}