{
  "type": "Feature",
  "properties": {
    "addr:full":"Rua Marques De Trives, 11 Pobra Trives Ourense 32780",
    "addr:housenumber":"11",
    "addr:postcode":"32780",
    "addr:street":"Rua Marques De Trives",
    "iso:country":"ES",
    "sg:address":"Rua Marques De Trives, 11",
    "sg:city":"Pobra Trives",
    "sg:orig_category":"Confecci\u00d3n (fabricaci\u00d3n, Al Por Mayor)",
    "sg:phone":"+34 988 33 07 80",
    "sg:postcode":"32780",
    "sg:province":"Ourense",
    "wof:name":"Dominguez Perez Dominga",
    "wof:placetype":"venue"
},
  "geometry": {"coordinates":[-7.2539892197,42.3392906189],"type":"Point"}
}