{
  "type": "Feature",
  "properties": {
    "addr:full":"Calle de Paulino Garcia, 60 Tudela Veguin Asturias 33910",
    "addr:housenumber":"60",
    "addr:postcode":"33910",
    "addr:street":"Calle De Paulino Garcia;Veguin Asturias",
    "iso:country":"ES",
    "sg:address":"Calle de Paulino Garcia, 60",
    "sg:city":"Tudela Veguin",
    "sg:orig_category":"Agentes Generales De Seguros",
    "sg:phone":"+34 985 78 90 26",
    "sg:postcode":"33910",
    "sg:province":"Asturias",
    "wof:name":"Villanueva Prieto Maria Jesus",
    "wof:placetype":"venue"
},
  "geometry": {"coordinates":[-5.7506370544,43.3397521973],"type":"Point"}
}