{
  "type": "Feature",
  "properties": {
    "addr:full":"Rbla Marina, S/n Hospitalet Llobregat Barcelona 08907",
    "addr:housenumber":"s",
    "addr:postcode":"08907",
    "addr:street":"Rbla Marina;/ N",
    "iso:country":"ES",
    "sg:address":"Rbla Marina, S/n",
    "sg:city":"Hospitalet Llobregat",
    "sg:orig_category":"Flores Y Plantas Naturales (al Por Mayor)",
    "sg:phone":"+34 933 35 68 02",
    "sg:postcode":"08907",
    "sg:province":"Barcelona",
    "wof:name":"Morillas Paredes Manuel",
    "wof:placetype":"venue"
},
  "geometry": {"coordinates":[2.1112101078,41.3508987427],"type":"Point"}
}