{
  "type": "Feature",
  "properties": {
    "addr:full":"Carr Independencia, 9 Palafrugell Girona 17200",
    "addr:housenumber":"9",
    "addr:postcode":"17200",
    "addr:street":"Carr Independencia",
    "iso:country":"ES",
    "sg:address":"Carr Independencia, 9",
    "sg:city":"Palafrugell",
    "sg:orig_category":"Maquinaria Para Industrias Diversas",
    "sg:phone":"+34 972 30 02 36",
    "sg:postcode":"17200",
    "sg:province":"Girona",
    "wof:name":"Medina Bretxa Joan",
    "wof:placetype":"venue"
},
  "geometry": {"coordinates":[3.1610779762,41.9144439697],"type":"Point"}
}