{
  "type": "Feature",
  "properties": {
    "iso:country":"ES",
    "sg:address":"Calle de Alvarez De Abreu, 70",
    "sg:city":"Santa Cruz Palma",
    "sg:orig_category":"Organismos De Investigaciones Cient\u00cdficas Y T\u00c9cnicas",
    "sg:phone":"+34 922 42 54 00",
    "sg:postcode":"38...",
    "sg:province":"Santa Cruz De Tenerife",
    "sg:website":"www.ing.iac.es",
    "wof:name":"Science And Engineering Research Council",
    "wof:placetype":"venue"
},
  "geometry": {"coordinates":[-17.7665081024,28.6812171936],"type":"Point"}
}