{
  "type": "Feature",
  "properties": {
    "iso:country":"ES",
    "sg:address":"Calle de Pelayo, 15",
    "sg:city":"Lugo De Llanera",
    "sg:orig_category":"Hoteles",
    "sg:phone":"+34 985 77 11 25",
    "sg:postcode":"33690",
    "sg:province":"Asturias",
    "wof:name":"Reguera Alvarez Celso",
    "wof:placetype":"venue"
},
  "geometry": {"coordinates":[-5.8176450729,43.4421882629],"type":"Point"}
}