{
  "type": "Feature",
  "properties": {
    "addr:full":"Calle de Berlin, 1 Parla Madrid 28980",
    "addr:housenumber":"1",
    "addr:postcode":"28980",
    "addr:street":"Calle De Berlin",
    "iso:country":"ES",
    "sg:address":"Calle de Berlin, 1",
    "sg:city":"Parla",
    "sg:classifiers":[
        {
            "category":"Banks & Credit Unions",
            "subcategory":"Bureau De Change",
            "type":"Services"
        }
    ],
    "sg:phone":"+34 916 99 91 44",
    "sg:postcode":"28980",
    "sg:province":"Madrid",
    "sg:tags":[
        "organismos",
        "control"
    ],
    "wof:name":"Tuv Rheinland Iberica S.a.",
    "wof:placetype":"venue"
},
  "geometry": {"coordinates":[-3.7584090233,40.238079071],"type":"Point"}
}