{
  "type": "Feature",
  "properties": {
    "addr:full":"Ctra. Aranjuez Oca\u00f1a, Km. 0043,0 Aranjuez Madrid 28300",
    "addr:postcode":"28300",
    "addr:street":"Ctra. Aranjuez Ocan\u0303A Km. 0043,0",
    "iso:country":"ES",
    "sg:address":"Ctra. Aranjuez Oca\u00f1a, Km. 0043,0",
    "sg:city":"Aranjuez",
    "sg:orig_category":"Hormigonados",
    "sg:phone":"+34 918 75 40 73",
    "sg:postcode":"28300",
    "sg:province":"Madrid",
    "wof:name":"Holcim Espa\u00f1a S.a.",
    "wof:placetype":"venue"
},
  "geometry": {"coordinates":[-3.6042790413,40.0360946655],"type":"Point"}
}