{
  "type": "Feature",
  "properties": {
    "addr:full":"Avda America, 40 Zaragoza Zaragoza 50007",
    "addr:housenumber":"40",
    "addr:postcode":"50007",
    "addr:street":"Avda America",
    "iso:country":"ES",
    "sg:address":"Avda America, 40",
    "sg:city":"Zaragoza",
    "sg:orig_category":"Poller\u00cda Y Caza (al Por Menor)",
    "sg:phone":"+34 976 38 61 51",
    "sg:postcode":"50007",
    "sg:province":"Zaragoza",
    "wof:name":"Moyano Garcia Judith",
    "wof:placetype":"venue"
},
  "geometry": {"coordinates":[-0.8857830167,41.6304473877],"type":"Point"}
}