{
  "type": "Feature",
  "properties": {
    "iso:country":"ES",
    "sg:address":"Barr Goitioltza, S/n",
    "sg:city":"Goitioltza",
    "sg:orig_category":"Semiller\u00cdas",
    "sg:phone":"+34 944 55 61 77",
    "sg:postcode":"48196",
    "sg:province":"Vizcaya",
    "wof:name":"Kima Landarak S.l.",
    "wof:placetype":"venue"
},
  "geometry": {"coordinates":[-2.8347494602,43.2850990295],"type":"Point"}
}