{
  "type": "Feature",
  "properties": {
    "iso:country":"ES",
    "sg:address":"Calle de Charcones, S/n",
    "sg:city":"San Pedro Arroyo",
    "sg:orig_category":"Carnicer\u00cdas, Carnicer\u00cdas",
    "sg:phone":"+34 920 24 02 21",
    "sg:postcode":"05350",
    "sg:province":"\u00c1vila",
    "wof:name":"Lucas Gonzalez Guillermo",
    "wof:placetype":"venue"
},
  "geometry": {"coordinates":[-4.8721547127,40.8029785156],"type":"Point"}
}