{
  "type": "Feature",
  "properties": {
    "addr:full":"Calle de Blas Infante, 4 Antas Almer\u00eda 04628",
    "addr:housenumber":"4",
    "addr:postcode":"04628",
    "addr:street":"Calle De Blas Infante",
    "iso:country":"ES",
    "sg:address":"Calle de Blas Infante, 4",
    "sg:city":"Antas",
    "sg:orig_category":"Asesor\u00cda Sobre Comunicaci\u00d3n De Empresas",
    "sg:phone":"+34 950 61 90 00",
    "sg:postcode":"04628",
    "sg:province":"Almer\u00eda",
    "wof:name":"Campos Gestion Y Asesoria S.l.",
    "wof:placetype":"venue"
},
  "geometry": {"coordinates":[-1.9186029434,37.2463493347],"type":"Point"}
}