{
  "type": "Feature",
  "properties": {
    "iso:country":"ES",
    "sg:address":"Calle de Secundino Alonso, 22",
    "sg:city":"Pto. Rosario",
    "sg:orig_category":"Asesor\u00cda De Formaci\u00d3n Y Gesti\u00d3n De Personal",
    "sg:phone":"+34 928 85 11 69",
    "sg:postcode":"35600",
    "sg:province":"Las Palmas",
    "wof:name":"Hernandez Trujillo Salvador",
    "wof:placetype":"venue"
},
  "geometry": {"coordinates":[-13.861779213,28.4986858368],"type":"Point"}
}