{
  "type": "Feature",
  "properties": {
    "iso:country":"ES",
    "sg:address":"Calle de Aragon, 16",
    "sg:city":"Fuente Alamo",
    "sg:orig_category":"Ingeniero",
    "sg:phone":"+34 968 59 85 29",
    "sg:postcode":"30320",
    "sg:province":"Murcia",
    "wof:name":"Pagan Garcia Gaspar",
    "wof:placetype":"venue"
},
  "geometry": {"coordinates":[-1.1749478579,37.7178993225],"type":"Point"}
}