{
  "type": "Feature",
  "properties": {
    "iso:country":"ES",
    "sg:address":"Calle de Salvador Moreno, 10",
    "sg:city":"Marin",
    "sg:orig_category":"Navegaci\u00d3n (equipos Fluviales)",
    "sg:phone":"+34 986 88 35 35",
    "sg:postcode":"36900",
    "sg:province":"Pontevedra",
    "wof:name":"Nores Rodriguez Jose Antonio",
    "wof:placetype":"venue"
},
  "geometry": {"coordinates":[-8.69962883,42.3875083923],"type":"Point"}
}