{
  "type": "Feature",
  "properties": {
    "iso:country":"ES",
    "sg:address":"Rua Seixedo, 17",
    "sg:city":"Vilarrodis",
    "sg:orig_category":"Chapister\u00cda",
    "sg:phone":"+34 981 60 01 64",
    "sg:postcode":"15141",
    "sg:province":"La Coru\u00f1a",
    "wof:name":"Aldao Varela Calos Manuel",
    "wof:placetype":"venue"
},
  "geometry": {"coordinates":[-8.4871311188,43.3164863586],"type":"Point"}
}