{
  "type": "Feature",
  "properties": {
    "iso:country":"ES",
    "sg:address":"Carrer de Valencia, 327",
    "sg:city":"Barcelona",
    "sg:orig_category":"Agencias Y Agentes Comerciales, Representantes",
    "sg:phone":"+34 934 59 21 92",
    "sg:postcode":"08009",
    "sg:province":"Barcelona",
    "wof:name":"Pascual Sellent Joaquin",
    "wof:placetype":"venue"
},
  "geometry": {"coordinates":[2.1688849926,41.3970909119],"type":"Point"}
}