{
  "type": "Feature",
  "properties": {
    "iso:country":"ES",
    "sg:address":"Carrer de Girona, 98",
    "sg:city":"Barcelona",
    "sg:orig_category":"Mec\u00c1nico Del Autom\u00d3vil",
    "sg:phone":"+34 934 58 76 40",
    "sg:postcode":"08009",
    "sg:province":"Barcelona",
    "wof:name":"Montserrat Sado Isabel",
    "wof:placetype":"venue"
},
  "geometry": {"coordinates":[2.1695048809,41.3962783813],"type":"Point"}
}