{
  "type": "Feature",
  "properties": {
    "addr:full":"Calle de Valencia, 13 Vall D'uixo Castell\u00f3n 12600",
    "addr:housenumber":"13",
    "addr:postcode":"12600",
    "addr:street":"Calle De Valencia",
    "iso:country":"ES",
    "sg:address":"Calle de Valencia, 13",
    "sg:city":"Vall D'uixo",
    "sg:orig_category":"Centros Empresariales",
    "sg:phone":"+34 964 66 74 55",
    "sg:postcode":"12600",
    "sg:province":"Castell\u00f3n",
    "wof:name":"Bartolome Castello Vicenta",
    "wof:placetype":"venue"
},
  "geometry": {"coordinates":[-0.0502690002,39.9763679504],"type":"Point"}
}