{
  "type": "Feature",
  "properties": {
    "addr:full":"Cim Valles (pol Ind Minetes), 5 Sta. Perpetua Mogoda Barcelona 08130",
    "addr:housenumber":"5",
    "addr:postcode":"08130",
    "addr:street":"Ind Minetes",
    "iso:country":"ES",
    "sg:address":"Cim Valles (pol Ind Minetes), 5",
    "sg:city":"Sta. Perpetua Mogoda",
    "sg:orig_category":"Delegados, Agentes De Tr\u00c1nsito, Auxiliares De Transporte Internacional",
    "sg:phone":"+34 935 60 61 63",
    "sg:postcode":"08130",
    "sg:province":"Barcelona",
    "sg:website":"www.gomez.es",
    "wof:name":"Transcamer S.a.",
    "wof:placetype":"venue"
},
  "geometry": {"coordinates":[2.1802799702,41.5371818542],"type":"Point"}
}