{
  "type": "Feature",
  "properties": {
    "iso:country":"ES",
    "sg:address":"Pg Pau Casals (de), 59",
    "sg:city":"Pineda",
    "sg:orig_category":"Deportes N\u00c1uticos, Acu\u00c1ticos Y Subacu\u00c1ticos: Art\u00cdculos Y Equipo (al Por Menor)",
    "sg:phone":"+34 977 37 05 15",
    "sg:postcode":"43480",
    "sg:province":"Tarragona",
    "wof:name":"Hawaii Cinco Cero Sl",
    "wof:placetype":"venue"
},
  "geometry": {"coordinates":[1.1441899538,41.1080245972],"type":"Point"}
}