{
  "type": "Feature",
  "properties": {
    "iso:country":"ES",
    "sg:address":"Calle de La Corte De Faraon, 4",
    "sg:city":"Madrid",
    "sg:orig_category":"Molduras, Junquillos, Listones Y Molduras Perforadas",
    "sg:phone":"+34 913 17 52 26",
    "sg:postcode":"28041",
    "sg:province":"Madrid",
    "wof:name":"Pindado Blazquez Antoliano",
    "wof:placetype":"venue"
},
  "geometry": {"coordinates":[-3.6982278824,40.3614692688],"type":"Point"}
}