{
  "type": "Feature",
  "properties": {
    "iso:country":"ES",
    "sg:address":"Calle de Alejandro Moran, 24",
    "sg:city":"Madrid",
    "sg:orig_category":"Laboratorios Y Trabajos De Fotograf\u00cda, V\u00cddeo Y Cine",
    "sg:phone":"+34 914 66 22 18",
    "sg:postcode":"28025",
    "sg:province":"Madrid",
    "wof:name":"Microlink Movil S.l.",
    "wof:placetype":"venue"
},
  "geometry": {"coordinates":[-3.731785059,40.3856124878],"type":"Point"}
}