{
  "type": "Feature",
  "properties": {
    "addr:full":"Avda Caldas (das), 49 Ourense Ourense 32001",
    "addr:housenumber":"49",
    "addr:postcode":"32001",
    "addr:street":"Avda Caldas Das",
    "iso:country":"ES",
    "sg:address":"Avda Caldas (das), 49",
    "sg:city":"Ourense",
    "sg:orig_category":"Zapatos (al Por Menor)",
    "sg:phone":"+34 988 37 48 10",
    "sg:postcode":"32001",
    "sg:province":"Ourense",
    "wof:name":"Lorenzo Montes Maximino",
    "wof:placetype":"venue"
},
  "geometry": {"coordinates":[-7.8715758324,42.349319458],"type":"Point"}
}