{
  "type": "Feature",
  "properties": {
    "iso:country":"ES",
    "sg:address":"Borreiros, S/n",
    "sg:city":"Borreiros",
    "sg:orig_category":"Empresas De Carpinter\u00cda De Madera",
    "sg:phone":"+34 982 55 90 86",
    "sg:postcode":"27866",
    "sg:province":"Lugo",
    "wof:name":"Garcia Gomez Abilio",
    "wof:placetype":"venue"
},
  "geometry": {"coordinates":[-7.6078701019,43.5982322693],"type":"Point"}
}