{
  "type": "Feature",
  "properties": {
    "addr:full":"Calle de Palenciana, S/n Lucena C\u00f3rdoba 14900",
    "addr:housenumber":"s",
    "addr:postcode":"14900",
    "addr:street":"Calle De Palenciana;/ N",
    "iso:country":"ES",
    "sg:address":"Calle de Palenciana, S/n",
    "sg:city":"Lucena",
    "sg:orig_category":"Carnicer\u00cdas, Carnicer\u00cdas",
    "sg:phone":"+34 957 51 58 62",
    "sg:postcode":"14900",
    "sg:province":"C\u00f3rdoba",
    "wof:name":"Medina Onieva Miguel",
    "wof:placetype":"venue"
},
  "geometry": {"coordinates":[-4.4773788452,37.4067687988],"type":"Point"}
}