{
  "type": "Feature",
  "properties": {
    "iso:country":"ES",
    "sg:address":"Calle de Arnau, 32",
    "sg:city":"Isla Cristina",
    "sg:orig_category":"Frutas Y Legumbres Frescas (al Por Mayor)",
    "sg:phone":"+34 959 33 07 97",
    "sg:postcode":"21410",
    "sg:province":"Huelva",
    "wof:name":"Moreno Martin Juan Pedro",
    "wof:placetype":"venue"
},
  "geometry": {"coordinates":[-7.31569767,37.1987915039],"type":"Point"}
}