{
  "type": "Feature",
  "properties": {
    "addr:full":"Calle de Maria Gil Vallejos, 15 Torrevieja Alicante 03180",
    "addr:housenumber":"15",
    "addr:postcode":"03180",
    "addr:street":"Calle De Maria Gil Vallejos",
    "iso:country":"ES",
    "sg:address":"Calle de Maria Gil Vallejos, 15",
    "sg:city":"Torrevieja",
    "sg:orig_category":"Administradores De Bienes Y Delegados De Comunidades De Propietarios",
    "sg:phone":"+34 965 71 77 06",
    "sg:postcode":"03180",
    "sg:province":"Alicante",
    "wof:name":"Aniorte Tur Veronica",
    "wof:placetype":"venue"
},
  "geometry": {"coordinates":[-0.672514379,37.9811935425],"type":"Point"}
}