{
  "type": "Feature",
  "properties": {
    "iso:country":"ES",
    "sg:address":"Carr Bellaire, 4",
    "sg:city":"Cadaques",
    "sg:orig_category":"Reposter\u00cdas",
    "sg:phone":"+34 972 25 87 55",
    "sg:postcode":"17488",
    "sg:province":"Girona",
    "wof:name":"Baro Noguer Angel",
    "wof:placetype":"venue"
},
  "geometry": {"coordinates":[3.2777349949,42.2890510559],"type":"Point"}
}