{
  "type": "Feature",
  "properties": {
    "iso:country":"ES",
    "sg:address":"Plaz General Ordo\u00d1ez Del, 1",
    "sg:city":"Oviedo",
    "sg:orig_category":"Sindicatos De Trabajadores",
    "sg:phone":"+34 985 25 32 43",
    "sg:postcode":"33005",
    "sg:province":"Asturias",
    "wof:name":"Union General De Trabajadores Federacion De Transportes Comunicaciones Y Mar",
    "wof:placetype":"venue"
},
  "geometry": {"coordinates":[-5.8475308418,43.3626899719],"type":"Point"}
}