{
  "type": "Feature",
  "properties": {
    "iso:country":"ES",
    "sg:address":"Carrer de Sant Iscle, 11",
    "sg:city":"Barcelona",
    "sg:orig_category":"Poller\u00cda Y Caza (al Por Menor)",
    "sg:phone":"+34 934 20 48 20",
    "sg:postcode":"08031",
    "sg:province":"Barcelona",
    "wof:name":"Ares Diaz Cesareo",
    "wof:placetype":"venue"
},
  "geometry": {"coordinates":[2.1736915112,41.4310073853],"type":"Point"}
}