{
  "type": "Feature",
  "properties": {
    "addr:full":"Cta. Madrid-cartag., Km. 0193,0 Minaya Albacete 02620",
    "addr:postcode":"02620",
    "addr:street":"Madrid-Cartag. Km. 0193,0",
    "iso:country":"ES",
    "sg:address":"Cta. Madrid-cartag., Km. 0193,0",
    "sg:city":"Minaya",
    "sg:orig_category":"Sales (al Por Mayor)",
    "sg:phone":"+34 967 45 00 10",
    "sg:postcode":"02620",
    "sg:province":"Albacete",
    "sg:website":"www.jacorrel.com",
    "wof:name":"J.a. Corell S.l.",
    "wof:placetype":"venue"
},
  "geometry": {"coordinates":[-2.3216319084,39.2727508545],"type":"Point"}
}