{
  "type": "Feature",
  "properties": {
    "iso:country":"ES",
    "sg:address":"Calle de Zaragoza, 22",
    "sg:city":"Ugena",
    "sg:orig_category":"Aceros Especiales",
    "sg:phone":"+34 925 53 33 52",
    "sg:postcode":"45217",
    "sg:province":"Toledo",
    "wof:name":"Inoxidables Y Laton S.l.",
    "wof:placetype":"venue"
},
  "geometry": {"coordinates":[-3.877669096,40.1581344604],"type":"Point"}
}