{
  "type": "Feature",
  "properties": {
    "addr:full":"C/ Major Del Pla, 30 Elche Alicante 03201",
    "addr:housenumber":"30",
    "addr:postcode":"03201",
    "addr:street":"C / Major Del Pla",
    "iso:country":"ES",
    "sg:address":"C/ Major Del Pla, 30",
    "sg:city":"Elche",
    "sg:orig_category":"Lencer\u00cda Femenina, Corseter\u00cda, Trajes De Ba\u00d1o (al Por Menor)",
    "sg:phone":"+34 965 43 89 20",
    "sg:postcode":"03201",
    "sg:province":"Alicante",
    "wof:name":"Morell Soler Francisca",
    "wof:placetype":"venue"
},
  "geometry": {"coordinates":[-0.7023090124,38.2630348206],"type":"Point"}
}