{
  "type": "Feature",
  "properties": {
    "addr:full":"Calle de Delicias, 28 Duruelo Sierra Soria 42158",
    "addr:housenumber":"28",
    "addr:postcode":"42158",
    "addr:street":"Calle De Delicias",
    "iso:country":"ES",
    "sg:address":"Calle de Delicias, 28",
    "sg:city":"Duruelo Sierra",
    "sg:orig_category":"Cr\u00cda De Animales",
    "sg:phone":"+34 975 37 10 97",
    "sg:postcode":"42158",
    "sg:province":"Soria",
    "wof:name":"Ayuso Hernando Urbano",
    "wof:placetype":"venue"
},
  "geometry": {"coordinates":[-2.9325118065,41.9531860352],"type":"Point"}
}