{
  "type": "Feature",
  "properties": {
    "addr:full":"Ventosa, S/n Covas La Coru\u00f1a 15864",
    "addr:housenumber":"s / n",
    "addr:postcode":"15864",
    "addr:street":"Ventosa",
    "iso:country":"ES",
    "sg:address":"Ventosa, S/n",
    "sg:city":"Covas",
    "sg:orig_category":"Fabricaci\u00d3n, Distribuci\u00d3n De Material Para La Climatizaci\u00d3n, Aireaci\u00d3n Y Ventilaci\u00d3n",
    "sg:phone":"+34 981 89 16 14",
    "sg:postcode":"15864",
    "sg:province":"La Coru\u00f1a",
    "wof:name":"Mata Garcia Claudio",
    "wof:placetype":"venue"
},
  "geometry": {"coordinates":[-8.6849870682,42.8890686035],"type":"Point"}
}