{
  "type": "Feature",
  "properties": {
    "iso:country":"ES",
    "sg:address":"Calle de Principe De Vergara, 154",
    "sg:city":"Madrid",
    "sg:classifiers":[
        {
            "category":"Banks & Credit Unions",
            "subcategory":"Bureau De Change",
            "type":"Services"
        }
    ],
    "sg:phone":"+34 915 90 36 38",
    "sg:postcode":"28002",
    "sg:province":"Madrid",
    "sg:tags":[
        "organismos",
        "control"
    ],
    "wof:name":"Consejo Oleicola Internacional",
    "wof:placetype":"venue"
},
  "geometry": {"coordinates":[-3.6778199673,40.4479293823],"type":"Point"}
}