{
  "type": "Feature",
  "properties": {
    "addr:full":"Pazo(galegos), S/n Fonte Santaia La Coru\u00f1a 15686",
    "addr:housenumber":"s",
    "addr:postcode":"15686",
    "addr:street":"/ N Fonte Santaia La Corun\u0303A",
    "iso:country":"ES",
    "sg:address":"Pazo(galegos), S/n",
    "sg:city":"Fonte Santaia",
    "sg:orig_category":"Art\u00cdculos Funerarios (al Por Menor)",
    "sg:phone":"+34 981 19 80 68",
    "sg:postcode":"15686",
    "sg:province":"La Coru\u00f1a",
    "wof:name":"Funeraria Martinez Sl",
    "wof:placetype":"venue"
},
  "geometry": {"coordinates":[-8.5658655167,43.2986602783],"type":"Point"}
}