{
  "type": "Feature",
  "properties": {
    "iso:country":"ES",
    "sg:address":"Pl Molina, 8",
    "sg:city":"Barcelona",
    "sg:orig_category":"Molduras, Junquillos, Listones Y Molduras Perforadas",
    "sg:phone":"+34 932 37 09 39",
    "sg:postcode":"08006",
    "sg:province":"Barcelona",
    "wof:name":"Servicios De Hosteleria Y Bares S.l.",
    "wof:placetype":"venue"
},
  "geometry": {"coordinates":[2.1476941109,41.4009857178],"type":"Point"}
}