{
  "type": "Feature",
  "properties": {
    "iso:country":"ES",
    "sg:address":"Calle de Corporaciones De Lena, S/n",
    "sg:city":"Pola De Lena",
    "sg:orig_category":"Oficinas De Turismo, Asociaciones De Iniciativa",
    "sg:phone":"+34 985 49 76 08",
    "sg:postcode":"33630",
    "sg:province":"Asturias",
    "wof:name":"Ayuntamiento De Lena",
    "wof:placetype":"venue"
},
  "geometry": {"coordinates":[-5.8294272423,43.1608161926],"type":"Point"}
}