{
  "type": "Feature",
  "properties": {
    "iso:country":"ES",
    "sg:address":"Av Sarria, 125",
    "sg:city":"Barcelona",
    "sg:orig_category":"Ingenier\u00cda, Centros De Estudios (diversos)",
    "sg:phone":"+34 932 04 30 81",
    "sg:postcode":"08017",
    "sg:province":"Barcelona",
    "wof:name":"Enginyeria De Serveis S.l.",
    "wof:placetype":"venue"
},
  "geometry": {"coordinates":[2.1336359978,41.3918991089],"type":"Point"}
}