{
  "type": "Feature",
  "properties": {
    "addr:full":"Carrer de Moll Comercial, S/n Canyelles-almadrava-puig-rom Girona 17480",
    "addr:housenumber":"s / n",
    "addr:postcode":"17480",
    "addr:street":"Carrer De Moll Comercial",
    "iso:country":"ES",
    "sg:address":"Carrer de Moll Comercial, S/n",
    "sg:city":"Canyelles-almadrava-puig-rom",
    "sg:orig_category":"Pescader\u00cdas (al Por Menor)",
    "sg:phone":"+34 972 25 72 84",
    "sg:postcode":"17480",
    "sg:province":"Girona",
    "wof:name":"Su\u00f1er Girona S.l.",
    "wof:placetype":"venue"
},
  "geometry": {"coordinates":[3.1663351059,42.2661399841],"type":"Point"}
}