{
  "type": "Feature",
  "properties": {
    "addr:full":"Callizo Carmen, 1 Alca\u00f1iz Teruel 44600",
    "addr:housenumber":"1",
    "addr:postcode":"44600",
    "addr:street":"Alcan\u0303Iz Teruel",
    "iso:country":"ES",
    "sg:address":"Callizo Carmen, 1",
    "sg:city":"Alca\u00f1iz",
    "sg:orig_category":"Bares, Piano",
    "sg:phone":"+34 978 83 10 96",
    "sg:postcode":"44600",
    "sg:province":"Teruel",
    "wof:name":"Robres Centelles Luis Ignacio",
    "wof:placetype":"venue"
},
  "geometry": {"coordinates":[-0.1330740005,41.0518913269],"type":"Point"}
}