{
  "type": "Feature",
  "properties": {
    "addr:full":"Praz Curros Enriquez (de), 1 Pontevedra Pontevedra 36002",
    "addr:housenumber":"1",
    "addr:postcode":"36002",
    "addr:street":"Praz Curros Enriquez De",
    "iso:country":"ES",
    "sg:address":"Praz Curros Enriquez (de), 1",
    "sg:city":"Pontevedra",
    "sg:orig_category":"Arquitectos",
    "sg:phone":"+34 986 85 50 85",
    "sg:postcode":"36002",
    "sg:province":"Pontevedra",
    "wof:name":"Balbuena Fernandez Miguel Angel",
    "wof:placetype":"venue"
},
  "geometry": {"coordinates":[-8.6447868347,42.4319496155],"type":"Point"}
}