{
  "type": "Feature",
  "properties": {
    "iso:country":"ES",
    "sg:address":"Noria, 11",
    "sg:city":"Alca\u00f1ices",
    "sg:orig_category":"Promotores Constructores",
    "sg:phone":"+34 980 68 04 04",
    "sg:postcode":"49500",
    "sg:province":"Zamora",
    "wof:name":"Construcciones Angel Dominguez S.l.",
    "wof:placetype":"venue"
},
  "geometry": {"coordinates":[-6.3422679901,41.7003631592],"type":"Point"}
}