{
  "type": "Feature",
  "properties": {
    "addr:full":"Calle de Entrepe\u00d1as, 6 Sacedon Guadalajara 19120",
    "addr:housenumber":"6",
    "addr:postcode":"19120",
    "addr:street":"Calle De Entrepen\u0303As",
    "iso:country":"ES",
    "sg:address":"Calle de Entrepe\u00d1as, 6",
    "sg:city":"Sacedon",
    "sg:orig_category":"Contables",
    "sg:phone":"+34 949 35 07 87",
    "sg:postcode":"19120",
    "sg:province":"Guadalajara",
    "wof:name":"Maria Jesus Ciruelos Novella Y Otra Cdad.",
    "wof:placetype":"venue"
},
  "geometry": {"coordinates":[-2.7365586758,40.4905586243],"type":"Point"}
}