{
  "type": "Feature",
  "properties": {
    "iso:country":"ES",
    "sg:address":"Carr Progres, 346",
    "sg:city":"Badalona",
    "sg:orig_category":"Confecci\u00d3n De Trajes Para Se\u00d1oras",
    "sg:phone":"+34 933 97 00 54",
    "sg:postcode":"08918",
    "sg:province":"Barcelona",
    "wof:name":"Eurocorset S. A.",
    "wof:placetype":"venue"
},
  "geometry": {"coordinates":[2.2312760353,41.4330787659],"type":"Point"}
}