{
  "type": "Feature",
  "properties": {
    "iso:country":"ES",
    "sg:address":"Carrer de Margarida Biosca, 11",
    "sg:city":"Olesa Montserrat",
    "sg:orig_category":"Pintura Y Barniz (al Por Menor)",
    "sg:phone":"+34 937 78 44 59",
    "sg:postcode":"08640",
    "sg:province":"Barcelona",
    "wof:name":"Reyes Y Olesa S.l.",
    "wof:placetype":"venue"
},
  "geometry": {"coordinates":[1.8980950117,41.5430030823],"type":"Point"}
}