{
  "type": "Feature",
  "properties": {
    "addr:full":"Pol Ind Saprelorca, S/n Lorca Murcia 30800",
    "addr:housenumber":"s / n",
    "addr:postcode":"30800",
    "iso:country":"ES",
    "sg:address":"Pol Ind Saprelorca, S/n",
    "sg:city":"Lorca",
    "sg:orig_category":"Carnes De Carnicer\u00cda (al Por Mayor)",
    "sg:phone":"+34 968 44 14 09",
    "sg:postcode":"30800",
    "sg:province":"Murcia",
    "sg:website":"www.friter.com",
    "wof:name":"Friter S.l.",
    "wof:placetype":"venue"
},
  "geometry": {"coordinates":[-1.6905640364,37.680557251],"type":"Point"}
}