{
  "type": "Feature",
  "properties": {
    "addr:full":"Calle de Mercedes (las), 25 Getxo Vizcaya 48930",
    "addr:housenumber":"25",
    "addr:postcode":"48930",
    "addr:street":"Calle De Mercedes Las",
    "iso:country":"ES",
    "sg:address":"Calle de Mercedes (las), 25",
    "sg:city":"Getxo",
    "sg:orig_category":"Sociedades, Compa\u00d1\u00cdas Aseguradoras",
    "sg:phone":"+34 944 64 62 88",
    "sg:postcode":"48930",
    "sg:province":"Vizcaya",
    "wof:name":"Fernando Oraa (correduria Oraa)",
    "wof:placetype":"venue"
},
  "geometry": {"coordinates":[-3.0131719112,43.3271179199],"type":"Point"}
}