{
  "type": "Feature",
  "properties": {
    "addr:full":"Calle de San Raimundo, 69 Madrid Madrid 28039",
    "addr:housenumber":"69",
    "addr:postcode":"madrid;28039",
    "addr:street":"Calle De San",
    "iso:country":"ES",
    "sg:address":"Calle de San Raimundo, 69",
    "sg:city":"Madrid",
    "sg:classifiers":[
        {
            "category":"Community Center",
            "subcategory":"Youth",
            "type":"Public Place"
        }
    ],
    "sg:phone":"+34 914 59 25 62",
    "sg:postcode":"28039",
    "sg:province":"Madrid",
    "sg:tags":[
        "juventud",
        "administraci\u00d3n",
        "la",
        "en",
        "deporte",
        "el",
        "y"
    ],
    "wof:name":"Jose Fernandez Y Pedro Coronado C.b.",
    "wof:placetype":"venue"
},
  "geometry": {"coordinates":[-3.7091488838,40.4515457153],"type":"Point"}
}