{
  "type": "Feature",
  "properties": {
    "addr:full":"Carrer de Ortigosa, 14 Barcelona Barcelona 08003",
    "addr:housenumber":"14",
    "addr:postcode":"08003",
    "addr:street":"Carrer De Ortigosa",
    "iso:country":"ES",
    "sg:address":"Carrer de Ortigosa, 14",
    "sg:city":"Barcelona",
    "sg:orig_category":"Asesor\u00cda Sobre Comunicaci\u00d3n De Empresas",
    "sg:phone":"+34 932 68 08 86",
    "sg:postcode":"08003",
    "sg:province":"Barcelona",
    "wof:name":"Mazarredo Mestres Luis",
    "wof:placetype":"venue"
},
  "geometry": {"coordinates":[2.1755559444,41.3884925842],"type":"Point"}
}