{
  "type": "Feature",
  "properties": {
    "iso:country":"ES",
    "sg:address":"Calle de Isaac Newton (de), 1",
    "sg:city":"Tres Cantos",
    "sg:orig_category":"Inform\u00c1tica (estudios, Servicios, Asesor\u00cda, Formaci\u00d3n)",
    "sg:phone":"+34 918 04 64 04",
    "sg:postcode":"28760",
    "sg:province":"Madrid",
    "sg:website":"www.tedico.com",
    "wof:name":"Tedico Soluciones Informaticas S.l.",
    "wof:placetype":"venue"
},
  "geometry": {"coordinates":[-3.7080750465,40.5942764282],"type":"Point"}
}