{
  "type": "Feature",
  "properties": {
    "addr:full":"Calle de Kupueta, 1 Orkoien Navarra 31160",
    "addr:housenumber":"1",
    "addr:postcode":"31160",
    "addr:street":"Calle De Kupueta",
    "iso:country":"ES",
    "sg:address":"Calle de Kupueta, 1",
    "sg:city":"Orkoien",
    "sg:orig_category":"Panader\u00cdas, Panader\u00cdas",
    "sg:phone":"+34 948 32 51 38",
    "sg:postcode":"31160",
    "sg:province":"Navarra",
    "wof:name":"Echaleku Latienda Elena",
    "wof:placetype":"venue"
},
  "geometry": {"coordinates":[-1.6958860159,42.8231773376],"type":"Point"}
}