{
  "type": "Feature",
  "properties": {
    "addr:full":"Poli Elegarcu, 8 Cacicedo Cantabria 39608",
    "addr:housenumber":"8",
    "addr:postcode":"39608",
    "addr:street":"Poli Elegarcu",
    "iso:country":"ES",
    "sg:address":"Poli Elegarcu, 8",
    "sg:city":"Cacicedo",
    "sg:orig_category":"Fabricaci\u00d3n, Instalaci\u00d3n Y Reparaci\u00d3n De Bombas",
    "sg:phone":"+34 942 25 12 58",
    "sg:postcode":"39608",
    "sg:province":"Cantabria",
    "wof:name":"Tecnicas Del Agua Marval S.l.",
    "wof:placetype":"venue"
},
  "geometry": {"coordinates":[-3.8830139637,43.4323272705],"type":"Point"}
}