{
  "type": "Feature",
  "properties": {
    "addr:full":"Fnc Pbla. Mendoza, S/n Fuentelahiguera De Albatages Guadalajara 19182",
    "addr:housenumber":"s",
    "addr:postcode":"19182",
    "addr:street":"Mendoza;/ N",
    "iso:country":"ES",
    "sg:address":"Fnc Pbla. Mendoza, S/n",
    "sg:city":"Fuentelahiguera De Albatages",
    "sg:orig_category":"Producci\u00d3n, Venta De Productos De Agricultura Biol\u00d3gica",
    "sg:phone":"+34 949 33 91 20",
    "sg:postcode":"19182",
    "sg:province":"Guadalajara",
    "wof:name":"La Puebla De Mendoza C.b.",
    "wof:placetype":"venue"
},
  "geometry": {"coordinates":[-3.2697970867,40.714176178],"type":"Point"}
}