{
  "type": "Feature",
  "properties": {
    "addr:full":"Avda Alfonso Xiii, 55 Elda Alicante 03600",
    "addr:housenumber":"55",
    "addr:postcode":"03600",
    "addr:street":"Avda Alfonso Xiii",
    "iso:country":"ES",
    "sg:address":"Avda Alfonso Xiii, 55",
    "sg:city":"Elda",
    "sg:orig_category":"Cajas De Ahorro",
    "sg:phone":"+34 966 96 57 90",
    "sg:postcode":"03600",
    "sg:province":"Alicante",
    "wof:name":"Caja De Ahorros Del Mediterraneo",
    "wof:placetype":"venue"
},
  "geometry": {"coordinates":[-0.7954090238,38.4715194702],"type":"Point"}
}