{
  "type": "Feature",
  "properties": {
    "iso:country":"ES",
    "sg:address":"Calle de Pedro Cabanes, 124",
    "sg:city":"Valencia",
    "sg:orig_category":"Promotores Constructores",
    "sg:phone":"+34 963 40 66 13",
    "sg:postcode":"46025",
    "sg:province":"Valencia",
    "wof:name":"Solados Jovisa S.l.",
    "wof:placetype":"venue"
},
  "geometry": {"coordinates":[-0.382868588,39.4932441711],"type":"Point"}
}