{
  "type": "Feature",
  "properties": {
    "iso:country":"ES",
    "sg:address":"Calle de Alcalde Pedro Gonzalez Gonzalez, 3",
    "sg:city":"Leganes",
    "sg:orig_category":"Peluquer\u00cdas, Peluquer\u00cda Mixta",
    "sg:phone":"+34 916 48 44 29",
    "sg:postcode":"28914",
    "sg:province":"Madrid",
    "wof:name":"Cid Martinez Sonia",
    "wof:placetype":"venue"
},
  "geometry": {"coordinates":[-3.7847964764,40.3190460205],"type":"Point"}
}