{
  "type": "Feature",
  "properties": {
    "iso:country":"ES",
    "sg:address":"Elizazpi Kalea, 26",
    "sg:city":"Bakaiku",
    "sg:orig_category":"Delegados, Agentes De Tr\u00c1nsito, Auxiliares De Transporte Internacional",
    "sg:phone":"+34 948 56 26 58",
    "sg:postcode":"31810",
    "sg:province":"Navarra",
    "wof:name":"Goicoechea Vives Jose Luis",
    "wof:placetype":"venue"
},
  "geometry": {"coordinates":[-2.1024289131,42.892288208],"type":"Point"}
}