{
  "type": "Feature",
  "properties": {
    "iso:country":"ES",
    "sg:address":"Calle de Trujillo, 2",
    "sg:city":"Burgos",
    "sg:orig_category":"Comerciantes Al Por Mayor De Vinos, Licores Y Alcoholes",
    "sg:phone":"+34 947 48 61 11",
    "sg:postcode":"09007",
    "sg:province":"Burgos",
    "wof:name":"Martinez Martinez Maria Encarnacion",
    "wof:placetype":"venue"
},
  "geometry": {"coordinates":[-3.6557910442,42.3632888794],"type":"Point"}
}