{
  "type": "Feature",
  "properties": {
    "addr:full":"Calle de Mayor, 30 Guadalajara Guadalajara 19001",
    "addr:housenumber":"30",
    "addr:postcode":"19001",
    "addr:street":"Calle De Mayor",
    "iso:country":"ES",
    "sg:address":"Calle de Mayor, 30",
    "sg:city":"Guadalajara",
    "sg:orig_category":"Contables",
    "sg:phone":"+34 949 22 60 95",
    "sg:postcode":"19001",
    "sg:province":"Guadalajara",
    "wof:name":"Ramos De Lucas Rosa",
    "wof:placetype":"venue"
},
  "geometry": {"coordinates":[-3.1651964188,40.6316680908],"type":"Point"}
}