{
  "type": "Feature",
  "properties": {
    "addr:full":"Calle de Lopez De Hoyos, 389 Madrid Madrid 28043",
    "addr:housenumber":"389",
    "addr:postcode":"28043",
    "addr:street":"Calle De Lopez De Hoyos",
    "iso:country":"ES",
    "sg:address":"Calle de Lopez De Hoyos, 389",
    "sg:city":"Madrid",
    "sg:orig_category":"Asesor\u00cda Sobre Comunicaci\u00d3n De Empresas",
    "sg:phone":"+34 913 81 61 82",
    "sg:postcode":"28043",
    "sg:province":"Madrid",
    "wof:name":"Aguilar Huerta Jesus",
    "wof:placetype":"venue"
},
  "geometry": {"coordinates":[-3.6501131058,40.4717483521],"type":"Point"}
}