{
  "type": "Feature",
  "properties": {
    "iso:country":"ES",
    "sg:address":"Calle de Lapa (la), 7",
    "sg:city":"Playa Blanca",
    "sg:orig_category":"Inmobiliaria (agencias)",
    "sg:phone":"+34 928 34 95 54",
    "sg:postcode":"35580",
    "sg:province":"Las Palmas",
    "wof:name":"Seaside Villas S.l.",
    "wof:placetype":"venue"
},
  "geometry": {"coordinates":[-13.8270702362,28.8644714355],"type":"Point"}
}