{
  "type": "Feature",
  "properties": {
    "addr:full":"Calle de Rosario, S/n Fompedraza Valladolid 47311",
    "addr:housenumber":"/ n",
    "addr:postcode":"47311",
    "addr:street":"Calle De Rosario S",
    "iso:country":"ES",
    "sg:address":"Calle de Rosario, S/n",
    "sg:city":"Fompedraza",
    "sg:orig_category":"Productores Recolectores, Venta Directa De Vinos",
    "sg:phone":"+34 983 89 20 08",
    "sg:postcode":"47311",
    "sg:province":"Valladolid",
    "wof:name":"Bodegas Briego Albesa S.a.",
    "wof:placetype":"venue"
},
  "geometry": {"coordinates":[-4.144094944,41.5356063843],"type":"Point"}
}