{
  "type": "Feature",
  "properties": {
    "addr:full":"Yerri, 13 Estella Navarra 31200",
    "addr:housenumber":"13",
    "addr:postcode":"31200",
    "addr:street":"Yerri",
    "iso:country":"ES",
    "sg:address":"Yerri, 13",
    "sg:city":"Estella",
    "sg:orig_category":"Electricidad Veh\u00cdculo",
    "sg:phone":"+34 948 55 33 60",
    "sg:postcode":"31200",
    "sg:province":"Navarra",
    "wof:name":"Solano Salanueva Jaime",
    "wof:placetype":"venue"
},
  "geometry": {"coordinates":[-2.0352010727,42.6741142273],"type":"Point"}
}