{
  "type": "Feature",
  "properties": {
    "addr:full":"Cno. V. Llucmajor, S/n Son San Juan Islas Baleares 07611",
    "addr:housenumber":"s / n",
    "addr:postcode":"07611",
    "addr:street":"Cno. V. Llucmajor",
    "iso:country":"ES",
    "sg:address":"Cno. V. Llucmajor, S/n",
    "sg:city":"Son San Juan",
    "sg:orig_category":"Restaurantes",
    "sg:phone":"+34 971 74 56 66",
    "sg:postcode":"07611",
    "sg:province":"Islas Baleares",
    "sg:website":"www.lsgskychefs.com",
    "wof:name":"Lsg Sky Chefs Espa\u00f1a S.a.",
    "wof:placetype":"venue"
},
  "geometry": {"coordinates":[1.5129300356,39.0777397156],"type":"Point"}
}