{
  "type": "Feature",
  "properties": {
    "addr:full":"Calle de Pico El, 20 Ribadesella Asturias 33560",
    "addr:postcode":"33560",
    "addr:street":"Calle De Pico El",
    "iso:country":"ES",
    "sg:address":"Calle de Pico El, 20",
    "sg:city":"Ribadesella",
    "sg:orig_category":"Arquitectos",
    "sg:phone":"+34 985 86 10 47",
    "sg:postcode":"33560",
    "sg:province":"Asturias",
    "wof:name":"Blanco Casta\u00f1o Juan Alberto",
    "wof:placetype":"venue"
},
  "geometry": {"coordinates":[-5.0604438782,43.4609565735],"type":"Point"}
}