{
  "type": "Feature",
  "properties": {
    "iso:country":"ES",
    "sg:address":"Carretera De Burgos, 6",
    "sg:city":"Salas Infantes",
    "sg:orig_category":"Hoteles",
    "sg:phone":"+34 947 38 01 31",
    "sg:postcode":"09600",
    "sg:province":"Burgos",
    "wof:name":"Salas Guerrero Ricardo",
    "wof:placetype":"venue"
},
  "geometry": {"coordinates":[-3.2894539833,42.0231819153],"type":"Point"}
}