{
  "type": "Feature",
  "properties": {
    "iso:country":"ES",
    "sg:address":"Calle de Espada, 23",
    "sg:city":"Alcorcon",
    "sg:orig_category":"Herboristas (al Por Menor)",
    "sg:phone":"+34 916 43 49 98",
    "sg:postcode":"28921",
    "sg:province":"Madrid",
    "wof:name":"Montero Moya Isabel Paloma",
    "wof:placetype":"venue"
},
  "geometry": {"coordinates":[-3.8261480331,40.3465194702],"type":"Point"}
}