{
  "type": "Feature",
  "properties": {
    "addr:full":"Calle de Vela Zanetti, 2 Burgos Burgos 09007",
    "addr:housenumber":"2",
    "addr:postcode":"09007",
    "addr:street":"Calle De Vela Zanetti",
    "iso:country":"ES",
    "sg:address":"Calle de Vela Zanetti, 2",
    "sg:city":"Burgos",
    "sg:orig_category":"Chapister\u00cda",
    "sg:phone":"+34 947 48 20 48",
    "sg:postcode":"09007",
    "sg:province":"Burgos",
    "wof:name":"Urien Saez Alberto Rodrigo",
    "wof:placetype":"venue"
},
  "geometry": {"coordinates":[-3.6597700119,42.3638534546],"type":"Point"}
}