{
  "type": "Feature",
  "properties": {
    "addr:full":"Pase Palmeras Las, S/n Huelva Huelva 21002",
    "addr:postcode":"21002",
    "addr:street":"Las S / N",
    "iso:country":"ES",
    "sg:address":"Pase Palmeras Las, S/n",
    "sg:city":"Huelva",
    "sg:orig_category":"Cajas De Ahorro",
    "sg:phone":"+34 959 26 14 22",
    "sg:postcode":"21002",
    "sg:province":"Huelva",
    "wof:name":"Cajagranada",
    "wof:placetype":"venue"
},
  "geometry": {"coordinates":[-6.9542789459,37.2632255554],"type":"Point"}
}