{
  "type": "Feature",
  "properties": {
    "iso:country":"ES",
    "sg:address":"Calle de Zaragoza, 2",
    "sg:city":"Sevilla",
    "sg:orig_category":"Electrodom\u00c9sticos (al Por Menor)",
    "sg:phone":"+34 954 56 30 37",
    "sg:postcode":"41001",
    "sg:province":"Sevilla",
    "sg:website":"www.cafeteindias.com",
    "wof:name":"Serrarta S.l.",
    "wof:placetype":"venue"
},
  "geometry": {"coordinates":[-5.999341011,37.3891029358],"type":"Point"}
}