{
  "type": "Feature",
  "properties": {
    "addr:full":"Calle de Via Complutense, 117 Alcala Henares Madrid 28805",
    "addr:housenumber":"117",
    "addr:postcode":"28805",
    "addr:street":"Calle De Via Complutense",
    "iso:country":"ES",
    "sg:address":"Calle de Via Complutense, 117",
    "sg:city":"Alcala Henares",
    "sg:orig_category":"Muebles, Minoristas",
    "sg:phone":"+34 918 88 73 11",
    "sg:postcode":"28805",
    "sg:province":"Madrid",
    "wof:name":"Cuvall S.c.",
    "wof:placetype":"venue"
},
  "geometry": {"coordinates":[-3.3492519855,40.4932823181],"type":"Point"}
}