{
  "type": "Feature",
  "properties": {
    "iso:country":"ES",
    "sg:address":"Calle de Budapest, 1",
    "sg:city":"Torreciega",
    "sg:orig_category":"Pintura Y Barniz (al Por Menor)",
    "sg:phone":"+34 968 50 04 04",
    "sg:postcode":"30391",
    "sg:province":"Murcia",
    "wof:name":"Vicente Diaz Sale S.l.",
    "wof:placetype":"venue"
},
  "geometry": {"coordinates":[-0.9512301087,37.6262359619],"type":"Point"}
}