{
  "type": "Feature",
  "properties": {
    "addr:full":"E Poligono Landaben, S/n Iru\u00f1a Navarra 31012",
    "addr:housenumber":"s",
    "addr:postcode":"31012",
    "addr:street":"E Poligono Landaben;/ N Irun\u0303A Navarra",
    "iso:country":"ES",
    "sg:address":"E Poligono Landaben, S/n",
    "sg:city":"Iru\u00f1a",
    "sg:orig_category":"Venta, Alquiler, Mantenimiento De Calderas",
    "sg:phone":"+34 948 18 88 10",
    "sg:postcode":"31012",
    "sg:province":"Navarra",
    "wof:name":"Industria Navarra De La Galvanotecnia S. L. L.",
    "wof:placetype":"venue"
},
  "geometry": {"coordinates":[-1.6437540054,42.81275177],"type":"Point"}
}