{
  "type": "Feature",
  "properties": {
    "addr:full":"Calle de Amistad, 9 Arenas -areeta Vizcaya 48930",
    "addr:housenumber":"9;areeta",
    "addr:postcode":"48930",
    "addr:street":"Calle De Amistad",
    "iso:country":"ES",
    "sg:address":"Calle de Amistad, 9",
    "sg:city":"Arenas -areeta",
    "sg:orig_category":"Art\u00cdculos De Decoraci\u00d3n (fabricaci\u00d3n Y Al Por Mayor)",
    "sg:phone":"+34 944 80 12 92",
    "sg:postcode":"48930",
    "sg:province":"Vizcaya",
    "wof:name":"Bell House S.l.",
    "wof:placetype":"venue"
},
  "geometry": {"coordinates":[-3.014993906,43.3249969482],"type":"Point"}
}