{
  "type": "Feature",
  "properties": {
    "iso:country":"ES",
    "sg:address":"Carrer de Mossen Jaume Sole, 18",
    "sg:city":"Cornella Llobregat",
    "sg:orig_category":"Florister\u00cdas",
    "sg:phone":"+34 933 76 33 99",
    "sg:postcode":"08940",
    "sg:province":"Barcelona",
    "wof:name":"Lopez Lucas Renato",
    "wof:placetype":"venue"
},
  "geometry": {"coordinates":[2.0757958889,41.3614730835],"type":"Point"}
}