{
  "type": "Feature",
  "properties": {
    "addr:full":"Collet, S/n Guardiola Bergueda Barcelona 08694",
    "addr:housenumber":"s / n",
    "addr:postcode":"08694",
    "addr:street":"Collet;Guardiola Bergueda",
    "iso:country":"ES",
    "sg:address":"Collet, S/n",
    "sg:city":"Guardiola Bergueda",
    "sg:classifiers":[
        {
            "category":"Manufacturing",
            "subcategory":"Building Materials",
            "type":"Manufacturing & Wholesale Goods"
        }
    ],
    "sg:phone":"+34 938 22 73 70",
    "sg:postcode":"08694",
    "sg:province":"Barcelona",
    "sg:tags":[
        "cemento",
        "y",
        "de",
        "fabricaci\u00d3n",
        "cal"
    ],
    "wof:name":"Cementos Collet S.l",
    "wof:placetype":"venue"
},
  "geometry": {"coordinates":[1.8791999817,42.232509613],"type":"Point"}
}