{
  "type": "Feature",
  "properties": {
    "iso:country":"ES",
    "sg:address":"Calle de Eskoikiz, 4",
    "sg:city":"Bermeo",
    "sg:classifiers":[
        {
            "category":"Autos & Motor Vehicles",
            "subcategory":"Automobile Sales",
            "type":"Retail Goods"
        }
    ],
    "sg:phone":"+34 946 88 29 83",
    "sg:postcode":"48370",
    "sg:province":"Vizcaya",
    "wof:name":"Aritzlan S.l.",
    "wof:placetype":"venue"
},
  "geometry": {"coordinates":[-2.7247970104,43.4185256958],"type":"Point"}
}