{
  "type": "Feature",
  "properties": {
    "addr:full":"Calle de Senda Mitjana, 11 Nules Castell\u00f3n 12520",
    "addr:housenumber":"11",
    "addr:postcode":"12520",
    "addr:street":"Calle De Senda Mitjana",
    "iso:country":"ES",
    "sg:address":"Calle de Senda Mitjana, 11",
    "sg:city":"Nules",
    "sg:orig_category":"Contenedores (mercanc\u00cdas)",
    "sg:phone":"+34 964 67 12 14",
    "sg:postcode":"12520",
    "sg:province":"Castell\u00f3n",
    "wof:name":"Transportes Y Excavaciones Jose Luis Garcia S.l",
    "wof:placetype":"venue"
},
  "geometry": {"coordinates":[-0.1518619955,39.8516387939],"type":"Point"}
}