{
  "type": "Feature",
  "properties": {
    "addr:full":"Cmno Molinos (de Los), 107 Zaragoza Zaragoza 50015",
    "addr:housenumber":"107",
    "addr:postcode":"50015",
    "addr:street":"Cmno Molinos De Los",
    "iso:country":"ES",
    "sg:address":"Cmno Molinos (de Los), 107",
    "sg:city":"Zaragoza",
    "sg:orig_category":"Metales (labores, Pulido)",
    "sg:phone":"+34 976 51 31 11",
    "sg:postcode":"50015",
    "sg:province":"Zaragoza",
    "sg:website":"www.famesa.com",
    "wof:name":"Fabricacion De Matriceria Y Estampaciones S. A.",
    "wof:placetype":"venue"
},
  "geometry": {"coordinates":[-0.8629540205,41.6912841797],"type":"Point"}
}