{
  "type": "Feature",
  "properties": {
    "iso:country":"ES",
    "sg:address":"Calle de Goya, 35",
    "sg:city":"Valencia",
    "sg:orig_category":"Centros Empresariales",
    "sg:phone":"+34 963 83 77 89",
    "sg:postcode":"46018",
    "sg:province":"Valencia",
    "wof:name":"Contreras Lara Manuel",
    "wof:placetype":"venue"
},
  "geometry": {"coordinates":[-0.398191005,39.4721755981],"type":"Point"}
}