{
  "type": "Feature",
  "properties": {
    "iso:country":"ES",
    "sg:address":"Calle de Orihuela, 43",
    "sg:city":"Albatera",
    "sg:orig_category":"Enfermeras: Consultas, Atenci\u00d3n A Domicilio",
    "sg:phone":"+34 965 48 50 08",
    "sg:postcode":"03340",
    "sg:province":"Alicante",
    "wof:name":"Martinez Juan Enrique",
    "wof:placetype":"venue"
},
  "geometry": {"coordinates":[-0.8709589839,38.1771392822],"type":"Point"}
}