{
  "type": "Feature",
  "properties": {
    "iso:country":"ES",
    "sg:address":"C/ Ruperto Chapi, 51",
    "sg:city":"Elche",
    "sg:orig_category":"Venta, Alquiler De Instrumentos Y Accesorios De M\u00dasica",
    "sg:phone":"+34 966 67 48 63",
    "sg:postcode":"03201",
    "sg:province":"Alicante",
    "wof:name":"Corral Navarro Antonio",
    "wof:placetype":"venue"
},
  "geometry": {"coordinates":[-0.7032110095,38.2682304382],"type":"Point"}
}