{
  "type": "Feature",
  "properties": {
    "addr:full":"Calle de Cervantes, 6 Carrizosa Ciudad Real 13329",
    "addr:housenumber":"6",
    "addr:postcode":"13329",
    "addr:street":"Calle De Cervantes",
    "iso:country":"ES",
    "sg:address":"Calle de Cervantes, 6",
    "sg:city":"Carrizosa",
    "sg:orig_category":"Mercer\u00cda, Lencer\u00cda (al Por Menor)",
    "sg:phone":"+34 926 36 90 12",
    "sg:postcode":"13329",
    "sg:province":"Ciudad Real",
    "wof:name":"Comercial Pelaez Cdad",
    "wof:placetype":"venue"
},
  "geometry": {"coordinates":[-2.9922549725,38.8423080444],"type":"Point"}
}