{
  "type": "Feature",
  "properties": {
    "iso:country":"ES",
    "sg:address":"Rua Montero Rios, 30",
    "sg:city":"Vigo",
    "sg:orig_category":"Ingenier\u00cda, Centros De Estudios (diversos)",
    "sg:phone":"+34 986 43 05 60",
    "sg:postcode":"36201",
    "sg:province":"Pontevedra",
    "wof:name":"Faustino Carceller S.l.",
    "wof:placetype":"venue"
},
  "geometry": {"coordinates":[-8.7216005325,42.2403717041],"type":"Point"}
}