{
  "type": "Feature",
  "properties": {
    "addr:full":"Calle de Monzon, 24 Sevilla Sevilla 41012",
    "addr:housenumber":"24",
    "addr:postcode":"41012",
    "addr:street":"Calle De Monzon",
    "iso:country":"ES",
    "sg:address":"Calle de Monzon, 24",
    "sg:city":"Sevilla",
    "sg:orig_category":"Platos Preparados Refrigerados (fabricaci\u00d3n, Al Por Mayor)",
    "sg:phone":"+34 954 24 00 07",
    "sg:postcode":"41012",
    "sg:province":"Sevilla",
    "wof:name":"Lopez Perez Blanca",
    "wof:placetype":"venue"
},
  "geometry": {"coordinates":[-5.9857912064,37.3590126038],"type":"Point"}
}