{
  "type": "Feature",
  "properties": {
    "addr:full":"Ibai-ondo Bailara, 16 Irura Guip\u00f9zcoa 20271",
    "addr:housenumber":"16",
    "addr:postcode":"20271",
    "addr:street":"Ibai-Ondo Bailara;Guipu\u0300Zcoa",
    "iso:country":"ES",
    "sg:address":"Ibai-ondo Bailara, 16",
    "sg:city":"Irura",
    "sg:orig_category":"Limpieza De Alfombras",
    "sg:phone":"+34 943 69 22 56",
    "sg:postcode":"20271",
    "sg:province":"Guip\u00f9zcoa",
    "wof:name":"Arrospide Aburuza Miguel",
    "wof:placetype":"venue"
},
  "geometry": {"coordinates":[-2.0686199665,43.1666641235],"type":"Point"}
}