{
  "type": "Feature",
  "properties": {
    "addr:full":"Calle de Arostegi, 34 Bermeo Vizcaya 48370",
    "addr:housenumber":"34",
    "addr:postcode":"48370",
    "addr:street":"Calle De Arostegi",
    "iso:country":"ES",
    "sg:address":"Calle de Arostegi, 34",
    "sg:city":"Bermeo",
    "sg:orig_category":"Sindicatos De Trabajadores",
    "sg:phone":"+34 946 88 54 95",
    "sg:postcode":"48370",
    "sg:province":"Vizcaya",
    "wof:name":"Langile Abertzaleen Batzordeak",
    "wof:placetype":"venue"
},
  "geometry": {"coordinates":[-2.7211072445,43.4193916321],"type":"Point"}
}