{
  "type": "Feature",
  "properties": {
    "iso:country":"ES",
    "sg:address":"Calle de Viteri, 48",
    "sg:city":"Errenteria",
    "sg:orig_category":"Sociedades, Compa\u00d1\u00cdas Aseguradoras",
    "sg:phone":"+34 943 51 60 54",
    "sg:postcode":"20100",
    "sg:province":"Guip\u00f9zcoa",
    "wof:name":"Luis Lete Lizaso Y Maria Del Carmen Murugarren Martell Cdad",
    "wof:placetype":"venue"
},
  "geometry": {"coordinates":[-1.9032310247,43.3145713806],"type":"Point"}
}