{
  "type": "Feature",
  "properties": {
    "iso:country":"ES",
    "sg:address":"Calle de San Bartolome, 32",
    "sg:city":"Aguadulce",
    "sg:orig_category":"Quincaller\u00cda (al Por Menor)",
    "sg:phone":"+34 954 81 65 87",
    "sg:postcode":"41550",
    "sg:province":"Sevilla",
    "wof:name":"Martin Sanchez Elisa",
    "wof:placetype":"venue"
},
  "geometry": {"coordinates":[-4.9925980568,37.2524185181],"type":"Point"}
}