{
  "type": "Feature",
  "properties": {
    "addr:full":"Rua Magdalena, 141 Ferrol La Coru\u00f1a 15402",
    "addr:housenumber":"141",
    "addr:postcode":"15402",
    "addr:street":"Rua Magdalena;La Corun\u0303A",
    "iso:country":"ES",
    "sg:address":"Rua Magdalena, 141",
    "sg:city":"Ferrol",
    "sg:orig_category":"Art\u00cdculos De Regalo (al Por Menor)",
    "sg:phone":"+34 981 35 99 90",
    "sg:postcode":"15402",
    "sg:province":"La Coru\u00f1a",
    "wof:name":"Marbal Galega S.l.",
    "wof:placetype":"venue"
},
  "geometry": {"coordinates":[-8.2349729538,43.4826545715],"type":"Point"}
}