{
  "type": "Feature",
  "properties": {
    "iso:country":"ES",
    "sg:address":"Calle de Corredera (la), 38",
    "sg:city":"Utrera",
    "sg:orig_category":"Ropa Para Se\u00d1oras Y Caballeros (al Por Menor)",
    "sg:phone":"+34 955 86 01 94",
    "sg:postcode":"41710",
    "sg:province":"Sevilla",
    "wof:name":"Amaya Redondo Justo",
    "wof:placetype":"venue"
},
  "geometry": {"coordinates":[-5.7853841782,37.1838150024],"type":"Point"}
}