{
  "type": "Feature",
  "properties": {
    "addr:full":"Calle de Barca, 3 Chiclana De La Frontera C\u00e1diz 11130",
    "addr:housenumber":"3",
    "addr:postcode":"11130",
    "addr:street":"Calle De Barca",
    "iso:country":"ES",
    "sg:address":"Calle de Barca, 3",
    "sg:city":"Chiclana De La Frontera",
    "sg:orig_category":"Centros Comerciales Y Grandes Tiendas",
    "sg:phone":"+34 956 49 41 39",
    "sg:postcode":"11130",
    "sg:province":"C\u00e1diz",
    "wof:name":"Zepelin 92 S.l.",
    "wof:placetype":"venue"
},
  "geometry": {"coordinates":[-6.153447628,36.4232215881],"type":"Point"}
}