{
  "type": "Feature",
  "properties": {
    "iso:country":"ES",
    "sg:address":"Carrer de Balmes, 209",
    "sg:city":"Barcelona",
    "sg:orig_category":"Centros Empresariales",
    "sg:phone":"+34 932 38 47 21",
    "sg:postcode":"08006",
    "sg:province":"Barcelona",
    "wof:name":"Asesoria Tormat S.l.",
    "wof:placetype":"venue"
},
  "geometry": {"coordinates":[2.151396513,41.398059845],"type":"Point"}
}