{
  "type": "Feature",
  "properties": {
    "addr:full":"Calle de Malaga, 30 Moron Frontera Sevilla 41530",
    "addr:housenumber":"30",
    "addr:postcode":"41530",
    "addr:street":"Calle De Malaga",
    "iso:country":"ES",
    "sg:address":"Calle de Malaga, 30",
    "sg:city":"Moron Frontera",
    "sg:orig_category":"Estancos",
    "sg:phone":"+34 955 85 16 08",
    "sg:postcode":"41530",
    "sg:province":"Sevilla",
    "wof:name":"Cabrera Nu\u00f1ez Carmen",
    "wof:placetype":"venue"
},
  "geometry": {"coordinates":[-5.4528231621,37.1294212341],"type":"Point"}
}