{
  "type": "Feature",
  "properties": {
    "iso:country":"ES",
    "sg:address":"Calle de Prim, 14",
    "sg:city":"Daimiel",
    "sg:orig_category":"Sindicatos De Trabajadores",
    "sg:phone":"+34 926 85 39 94",
    "sg:postcode":"13250",
    "sg:province":"Ciudad Real",
    "wof:name":"Union General De Trabajadores Regional De Castilla La Mancha",
    "wof:placetype":"venue"
},
  "geometry": {"coordinates":[-3.610450983,39.0692138672],"type":"Point"}
}