{
  "type": "Feature",
  "properties": {
    "addr:full":"Calle de Centurion, 21 Merida Badajoz 06800",
    "addr:housenumber":"21",
    "addr:postcode":"06800",
    "addr:street":"Calle De Centurion",
    "iso:country":"ES",
    "sg:address":"Calle de Centurion, 21",
    "sg:city":"Merida",
    "sg:orig_category":"Productos Qu\u00cdmicos (fabricaci\u00d3n, Al Por Mayor)",
    "sg:phone":"+34 924 30 45 65",
    "sg:postcode":"06800",
    "sg:province":"Badajoz",
    "wof:name":"Vorsevi S.a.",
    "wof:placetype":"venue"
},
  "geometry": {"coordinates":[-6.3487482071,38.9286956787],"type":"Point"}
}