{
  "type": "Feature",
  "properties": {
    "addr:full":"Avda Carlos I De, 1 Donostia-san Sebastian Guip\u00f9zcoa 20011",
    "addr:housenumber":"1",
    "addr:postcode":"20011",
    "addr:street":"Avda Carlos I De",
    "iso:country":"ES",
    "sg:address":"Avda Carlos I De, 1",
    "sg:city":"Donostia-san Sebastian",
    "sg:orig_category":"Psic\u00d3logos",
    "sg:phone":"+34 943 45 08 06",
    "sg:postcode":"20011",
    "sg:province":"Guip\u00f9zcoa",
    "wof:name":"Landaburu Illarramendi Miren Itziar Estibaliz",
    "wof:placetype":"venue"
},
  "geometry": {"coordinates":[-1.9786059856,43.3046684265],"type":"Point"}
}