{
  "type": "Feature",
  "properties": {
    "addr:full":"Calle de Guillem De Castro, 79 Valencia Valencia 46008",
    "addr:housenumber":"79",
    "addr:postcode":"46008",
    "addr:street":"Calle De Guillem De Castro",
    "iso:country":"ES",
    "sg:address":"Calle de Guillem De Castro, 79",
    "sg:city":"Valencia",
    "sg:orig_category":"Agricultores, Agricultores",
    "sg:phone":"+34 963 15 32 56",
    "sg:postcode":"46008",
    "sg:province":"Valencia",
    "wof:name":"Asociacion De Criadores De Caballos De Pura Raza Espa\u00d1ola",
    "wof:placetype":"venue"
},
  "geometry": {"coordinates":[-0.3840394914,39.4718666077],"type":"Point"}
}