{
  "type": "Feature",
  "properties": {
    "iso:country":"ES",
    "sg:address":"Calle de Jorge Manrique, 4",
    "sg:city":"Madrid",
    "sg:orig_category":"Organismos De Turismo",
    "sg:phone":"+34 915 61 68 74",
    "sg:postcode":"28006",
    "sg:province":"Madrid",
    "wof:name":"Compa\u00f1ia Intereses Y Tramitaciones S.a.",
    "wof:placetype":"venue"
},
  "geometry": {"coordinates":[-3.6904718876,40.4434623718],"type":"Point"}
}