{
  "type": "Feature",
  "properties": {
    "iso:country":"ES",
    "sg:address":"Calle de Ramon Y Cajal, 11",
    "sg:city":"Trigueros",
    "sg:orig_category":"Perfumer\u00cda (al Por Menor)",
    "sg:phone":"+34 959 30 62 01",
    "sg:postcode":"21620",
    "sg:province":"Huelva",
    "wof:name":"Vega Gonzalez Maria Dolores",
    "wof:placetype":"venue"
},
  "geometry": {"coordinates":[-6.8346438408,37.3822898865],"type":"Point"}
}