{
  "type": "Feature",
  "properties": {
    "addr:full":"Calle de Castello, 128 Madrid Madrid 28006",
    "addr:housenumber":"128",
    "addr:postcode":"28006",
    "addr:street":"Calle De Castello",
    "iso:country":"ES",
    "sg:address":"Calle de Castello, 128",
    "sg:city":"Madrid",
    "sg:orig_category":"Centros Empresariales",
    "sg:phone":"+34 914 11 80 26",
    "sg:postcode":"28006",
    "sg:province":"Madrid",
    "sg:website":"www.fersinasa.es",
    "wof:name":"Promociones Navarra Madrid S.a.",
    "wof:placetype":"venue"
},
  "geometry": {"coordinates":[-3.6804711819,40.4386062622],"type":"Point"}
}