{
  "type": "Feature",
  "properties": {
    "addr:full":"Calle de Alonso De Bazan, 4 Marbella M\u00e1laga 29600",
    "addr:housenumber":"4",
    "addr:postcode":"29600",
    "addr:street":"Calle De Alonso De Bazan;Ma\u0301Laga",
    "iso:country":"ES",
    "sg:address":"Calle de Alonso De Bazan, 4",
    "sg:city":"Marbella",
    "sg:orig_category":"Servicios Gsm",
    "sg:phone":"+34 952 90 16 46",
    "sg:postcode":"29600",
    "sg:province":"M\u00e1laga",
    "sg:website":"www.movilorozzn.com",
    "wof:name":"Corona Del Huracan S.l.",
    "wof:placetype":"venue"
},
  "geometry": {"coordinates":[-4.8896865845,36.5096702576],"type":"Point"}
}