{
  "type": "Feature",
  "properties": {
    "iso:country":"ES",
    "sg:address":"Jaume I, 8",
    "sg:city":"Real Montroi",
    "sg:orig_category":"Comercio, Reparaci\u00d3n De Bicicletas, De Motocicletas, De Accesorios",
    "sg:phone":"+34 962 55 58 00",
    "sg:postcode":"46194",
    "sg:province":"Valencia",
    "wof:name":"Arocas Herrera Jose Vicente",
    "wof:placetype":"venue"
},
  "geometry": {"coordinates":[-0.6091364026,39.3354949951],"type":"Point"}
}