{
  "type": "Feature",
  "properties": {
    "iso:country":"ES",
    "sg:address":"Ctra Tordesillas, Km. 0434,0",
    "sg:city":"Toro",
    "sg:orig_category":"Productores Recolectores, Venta Directa De Vinos",
    "sg:phone":"+34 980 69 24 31",
    "sg:postcode":"49800",
    "sg:province":"Zamora",
    "wof:name":"Bodegas Toresanas S.l.",
    "wof:placetype":"venue"
},
  "geometry": {"coordinates":[-5.3810381889,41.5245513916],"type":"Point"}
}