{
  "type": "Feature",
  "properties": {
    "addr:full":"Avda Estepona, 4 Genalguacil M\u00e1laga 29492",
    "addr:housenumber":"4",
    "addr:postcode":"29492",
    "addr:street":"Avda Estepona;Ma\u0301Laga",
    "iso:country":"ES",
    "sg:address":"Avda Estepona, 4",
    "sg:city":"Genalguacil",
    "sg:orig_category":"Ingeniero",
    "sg:phone":"+34 952 15 20 88",
    "sg:postcode":"29492",
    "sg:province":"M\u00e1laga",
    "wof:name":"Pi\u00f1el Galache Francisco Jose",
    "wof:placetype":"venue"
},
  "geometry": {"coordinates":[-5.2357501984,36.5457687378],"type":"Point"}
}