{
  "type": "Feature",
  "properties": {
    "iso:country":"ES",
    "sg:address":"Riera (la), 31",
    "sg:city":"Mataro",
    "sg:orig_category":"M\u00c9dicos: Oftalmolog\u00cda",
    "sg:phone":"+34 937 90 57 05",
    "sg:postcode":"08302",
    "sg:province":"Barcelona",
    "wof:name":"Arasanz Julia Agustin",
    "wof:placetype":"venue"
},
  "geometry": {"coordinates":[2.4448707104,41.5391273499],"type":"Point"}
}