{
  "type": "Feature",
  "properties": {
    "iso:country":"ES",
    "sg:address":"Av De El Romeral (p I Antequera), 4",
    "sg:city":"Antequera",
    "sg:orig_category":"Fabricaci\u00d3n De Su\u00c9ters Y Chalecos De Punto",
    "sg:phone":"+34 952 84 07 14",
    "sg:postcode":"29200",
    "sg:province":"M\u00e1laga",
    "wof:name":"Antal S. A.",
    "wof:placetype":"venue"
},
  "geometry": {"coordinates":[-4.536049366,37.2492408752],"type":"Point"}
}