{
  "type": "Feature",
  "properties": {
    "addr:full":"Urb Urb Xarblanca, S/n Marbella M\u00e1laga 29600",
    "addr:housenumber":"s / n",
    "addr:postcode":"29600",
    "addr:street":"Urb Xarblanca;Ma\u0301Laga",
    "iso:country":"ES",
    "sg:address":"Urb Urb Xarblanca, S/n",
    "sg:city":"Marbella",
    "sg:orig_category":"Promotores Constructores",
    "sg:phone":"+34 952 82 43 42",
    "sg:postcode":"29600",
    "sg:province":"M\u00e1laga",
    "wof:name":"Taylor Woodrow Espa\u00d1a S.a.",
    "wof:placetype":"venue"
},
  "geometry": {"coordinates":[-4.8833007812,36.5079956055],"type":"Point"}
}