{
  "type": "Feature",
  "properties": {
    "iso:country":"ES",
    "sg:address":"Carr Sant Jaume, 8",
    "sg:city":"Lleida",
    "sg:orig_category":"Electricidad: Instaladores",
    "sg:phone":"+34 973 20 07 27",
    "sg:postcode":"25001",
    "sg:province":"Lleida",
    "wof:name":"Herrero Llata Rafael",
    "wof:placetype":"venue"
},
  "geometry": {"coordinates":[0.6426730156,41.6047935486],"type":"Point"}
}