{
  "type": "Feature",
  "properties": {
    "addr:full":"Calle de Claudio Marcelo, 15 Cordoba C\u00f3rdoba 14002",
    "addr:housenumber":"15",
    "addr:postcode":"14002",
    "addr:street":"Calle De Claudio Marcelo;Co\u0301Rdoba",
    "iso:country":"ES",
    "sg:address":"Calle de Claudio Marcelo, 15",
    "sg:city":"Cordoba",
    "sg:orig_category":"Ropa Para Caballeros (al Por Menor)",
    "sg:phone":"+34 957 47 81 62",
    "sg:postcode":"14002",
    "sg:province":"C\u00f3rdoba",
    "wof:name":"Checa Alamillos Roberto",
    "wof:placetype":"venue"
},
  "geometry": {"coordinates":[-4.7782111168,37.8844184875],"type":"Point"}
}