{
  "type": "Feature",
  "properties": {
    "iso:country":"ES",
    "sg:address":"Rua Plateria, 32",
    "sg:city":"Grove",
    "sg:orig_category":"Bares, Piano",
    "sg:phone":"+34 986 73 31 94",
    "sg:postcode":"36980",
    "sg:province":"Pontevedra",
    "wof:name":"Caneda Tri\u00f1anes Cristian",
    "wof:placetype":"venue"
},
  "geometry": {"coordinates":[-8.8633785248,42.4949417114],"type":"Point"}
}