{
  "type": "Feature",
  "properties": {
    "iso:country":"ES",
    "sg:address":"Calle de Bolivia, 1",
    "sg:city":"Nerja",
    "sg:orig_category":"Molduras, Junquillos, Listones Y Molduras Perforadas",
    "sg:phone":"+34 952 52 89 51",
    "sg:postcode":"29780",
    "sg:province":"M\u00e1laga",
    "wof:name":"La Puntilla S.c.",
    "wof:placetype":"venue"
},
  "geometry": {"coordinates":[-3.8746635914,36.7499008179],"type":"Point"}
}