{
  "type": "Feature",
  "properties": {
    "iso:country":"ES",
    "sg:address":"Ctra. B-granada, Km. 0017,0",
    "sg:city":"Badajoz",
    "sg:orig_category":"Producci\u00d3n, Venta De Productos De Agricultura Biol\u00d3gica",
    "sg:phone":"+34 924 14 02 30",
    "sg:postcode":"06009",
    "sg:province":"Badajoz",
    "wof:name":"Diaz Valera Maria Del Carmen",
    "wof:placetype":"venue"
},
  "geometry": {"coordinates":[-6.8764038086,38.8433265686],"type":"Point"}
}