{
  "type": "Feature",
  "properties": {
    "iso:country":"ES",
    "sg:address":"Av Sant Bernat Calbo, 18",
    "sg:city":"Reus",
    "sg:orig_category":"Cables Y Hilos El\u00c9ctricos (fabricaci\u00d3n, Al Por Mayor)",
    "sg:phone":"+34 977 75 08 90",
    "sg:postcode":"43205",
    "sg:province":"Tarragona",
    "wof:name":"Tainco Gestio S.a.",
    "wof:placetype":"venue"
},
  "geometry": {"coordinates":[1.1070569754,41.1449584961],"type":"Point"}
}