{
  "type": "Feature",
  "properties": {
    "iso:country":"ES",
    "sg:address":"Calle de Obispo Salinas, 8",
    "sg:city":"Castellon",
    "sg:orig_category":"Centros De Coordinaci\u00d3n",
    "sg:phone":"+34 964 23 48 90",
    "sg:postcode":"12003",
    "sg:province":"Castell\u00f3n",
    "wof:name":"Pitarch Escrig Jose Vicente",
    "wof:placetype":"venue"
},
  "geometry": {"coordinates":[-0.0326780006,39.9841270447],"type":"Point"}
}