{
  "type": "Feature",
  "properties": {
    "addr:full":"Avda Generalisimo, S/n Barbate C\u00e1diz 11160",
    "addr:housenumber":"s / n",
    "addr:postcode":"11160",
    "addr:street":"Avda Generalisimo",
    "iso:country":"ES",
    "sg:address":"Avda Generalisimo, S/n",
    "sg:city":"Barbate",
    "sg:orig_category":"Molduras, Junquillos, Listones Y Molduras Perforadas",
    "sg:phone":"+34 956 43 09 48",
    "sg:postcode":"11160",
    "sg:province":"C\u00e1diz",
    "wof:name":"Alvarado Pinto Juan",
    "wof:placetype":"venue"
},
  "geometry": {"coordinates":[-5.9213933945,36.1900596619],"type":"Point"}
}