{
  "type": "Feature",
  "properties": {
    "addr:full":"Carr Estacio, 51 Almacelles Lleida 25100",
    "addr:housenumber":"51",
    "addr:postcode":"25100",
    "addr:street":"Carr Estacio",
    "iso:country":"ES",
    "sg:address":"Carr Estacio, 51",
    "sg:city":"Almacelles",
    "sg:orig_category":"Producci\u00d3n, Venta De Productos De Agricultura Biol\u00d3gica",
    "sg:phone":"+34 973 74 06 18",
    "sg:postcode":"25100",
    "sg:province":"Lleida",
    "wof:name":"Robles Buenavida Antonio",
    "wof:placetype":"venue"
},
  "geometry": {"coordinates":[0.443167001,41.7306022644],"type":"Point"}
}