{
  "type": "Feature",
  "properties": {
    "addr:full":"Carr Diputat Villanueva O Dels Hostals, 13 Xativa Valencia 46800",
    "addr:housenumber":"13",
    "addr:postcode":"46800",
    "addr:street":"Carr Diputat;Dels Hostals",
    "iso:country":"ES",
    "sg:address":"Carr Diputat Villanueva O Dels Hostals, 13",
    "sg:city":"Xativa",
    "sg:orig_category":"Panader\u00cdas, Panader\u00cdas",
    "sg:phone":"+34 962 27 51 36",
    "sg:postcode":"46800",
    "sg:province":"Valencia",
    "wof:name":"Ortiz Bernabeu Salvador",
    "wof:placetype":"venue"
},
  "geometry": {"coordinates":[-0.5251089931,38.9884185791],"type":"Point"}
}