{
  "type": "Feature",
  "properties": {
    "iso:country":"ES",
    "sg:address":"Carrer de Comte D'urgell, 239",
    "sg:city":"Barcelona",
    "sg:orig_category":"Autob\u00das (explotaci\u00d3n Y Servicios De)",
    "sg:phone":"+34 934 30 78 16",
    "sg:postcode":"08036",
    "sg:province":"Barcelona",
    "sg:website":"www.autocarescanals.es",
    "wof:name":"Autocares Canals S. A",
    "wof:placetype":"venue"
},
  "geometry": {"coordinates":[2.1469094753,41.3909034729],"type":"Point"}
}