{
  "type": "Feature",
  "properties": {
    "addr:full":"General Infante, 2 Olivenza Badajoz 06100",
    "addr:housenumber":"2",
    "addr:postcode":"06100",
    "addr:street":"General Infante",
    "iso:country":"ES",
    "sg:address":"General Infante, 2",
    "sg:city":"Olivenza",
    "sg:orig_category":"M\u00c9dicos: Medicina Interna",
    "sg:phone":"+34 924 49 06 82",
    "sg:postcode":"06100",
    "sg:province":"Badajoz",
    "wof:name":"Rodriguez Vidigal Francisco Felix",
    "wof:placetype":"venue"
},
  "geometry": {"coordinates":[-7.0980257988,38.6860122681],"type":"Point"}
}