{
  "type": "Feature",
  "properties": {
    "addr:full":"Plaz Pinazo, 16 Madrid Madrid 28021",
    "addr:housenumber":"16",
    "addr:postcode":"madrid;28021",
    "addr:street":"Plaz Pinazo",
    "iso:country":"ES",
    "sg:address":"Plaz Pinazo, 16",
    "sg:city":"Madrid",
    "sg:orig_category":"Herboristas (al Por Menor)",
    "sg:phone":"+34 917 98 12 11",
    "sg:postcode":"28021",
    "sg:province":"Madrid",
    "wof:name":"Martinez Fernandez Lidia",
    "wof:placetype":"venue"
},
  "geometry": {"coordinates":[-3.6910209656,40.3424606323],"type":"Point"}
}