{
  "type": "Feature",
  "properties": {
    "iso:country":"ES",
    "sg:address":"Carrer de Onze De Setembre, S/n",
    "sg:city":"Vilallonga Camp",
    "sg:orig_category":"M\u00c1quinas De Coser Y De Hacer Punto (al Por Mayor)",
    "sg:phone":"+34 977 84 02 89",
    "sg:postcode":"43141",
    "sg:province":"Tarragona",
    "wof:name":"Pau Roig S.c.p.",
    "wof:placetype":"venue"
},
  "geometry": {"coordinates":[1.2034349442,41.2105941772],"type":"Point"}
}