{
  "type": "Feature",
  "properties": {
    "addr:full":"Calle de Navasfrias, 1 Salamanca Salamanca 37007",
    "addr:housenumber":"1",
    "addr:postcode":"37007",
    "addr:street":"Calle De Navasfrias",
    "iso:country":"ES",
    "sg:address":"Calle de Navasfrias, 1",
    "sg:city":"Salamanca",
    "sg:orig_category":"Peluquer\u00cdas, Peluquer\u00cda Mixta",
    "sg:phone":"+34 923 23 73 23",
    "sg:postcode":"37007",
    "sg:province":"Salamanca",
    "wof:name":"Rodriguez Lorenzo Crescencia",
    "wof:placetype":"venue"
},
  "geometry": {"coordinates":[-5.6742019653,40.9693946838],"type":"Point"}
}