{
  "type": "Feature",
  "properties": {
    "iso:country":"ES",
    "sg:address":"Sauce, S/n",
    "sg:city":"Ponteareas",
    "sg:orig_category":"Quincaller\u00cda (al Por Menor)",
    "sg:phone":"+34 986 66 99 55",
    "sg:postcode":"36860",
    "sg:province":"Pontevedra",
    "wof:name":"Ferreteria Ponteferr, S.l.",
    "wof:placetype":"venue"
},
  "geometry": {"coordinates":[-8.5015640259,42.1726455688],"type":"Point"}
}