{
  "type": "Feature",
  "properties": {
    "iso:country":"ES",
    "sg:address":"Calle de Ctra. Onda, Km. 0002,0",
    "sg:city":"Alcora",
    "sg:orig_category":"Transportes Por Carretera: Lotes Completos, Mercanc\u00cdas Diversas",
    "sg:phone":"+34 964 36 01 17",
    "sg:postcode":"12110",
    "sg:province":"Castell\u00f3n",
    "wof:name":"Transportes Grangel S.l.",
    "wof:placetype":"venue"
},
  "geometry": {"coordinates":[-0.2178789973,40.0734786987],"type":"Point"}
}