{
  "type": "Feature",
  "properties": {
    "iso:country":"ES",
    "sg:address":"Plaza Andramariko, 3",
    "sg:city":"Amorebieta-etxano",
    "sg:orig_category":"Ense\u00d1anza Variada",
    "sg:phone":"+34 946 73 05 98",
    "sg:postcode":"48340",
    "sg:province":"Vizcaya",
    "wof:name":"Libe Txasko Barrenetxea",
    "wof:placetype":"venue"
},
  "geometry": {"coordinates":[-2.732708931,43.2186317444],"type":"Point"}
}