{
  "type": "Feature",
  "properties": {
    "addr:full":"Avda Granada, 47 Jaen Ja\u00e9n 23001",
    "addr:housenumber":"47;jae\u0301n",
    "addr:postcode":"23001",
    "addr:street":"Avda Granada",
    "iso:country":"ES",
    "sg:address":"Avda Granada, 47",
    "sg:city":"Jaen",
    "sg:orig_category":"Instalaci\u00d3n, Reparaci\u00d3n De Ascensores Y Montacargas",
    "sg:phone":"+34 953 24 19 12",
    "sg:postcode":"23001",
    "sg:province":"Ja\u00e9n",
    "sg:website":"www.enbarba.com",
    "wof:name":"Ascensores Embarba S. A.",
    "wof:placetype":"venue"
},
  "geometry": {"coordinates":[-3.7819709778,37.7694244385],"type":"Point"}
}