{
  "type": "Feature",
  "properties": {
    "iso:country":"ES",
    "sg:address":"Carrer de Josep De Togores, 10",
    "sg:city":"Lloret Mar",
    "sg:orig_category":"Restaurantes",
    "sg:phone":"+34 972 36 74 91",
    "sg:postcode":"17310",
    "sg:province":"Girona",
    "wof:name":"Arguello Fernandez Aldo Ignacio",
    "wof:placetype":"venue"
},
  "geometry": {"coordinates":[2.8404591084,41.6995315552],"type":"Point"}
}