{
  "type": "Feature",
  "properties": {
    "addr:full":"Calle de Mayor, 95 Castellon Castell\u00f3n 12001",
    "addr:housenumber":"95",
    "addr:postcode":"12001",
    "addr:street":"Calle De Mayor",
    "iso:country":"ES",
    "sg:address":"Calle de Mayor, 95",
    "sg:city":"Castellon",
    "sg:orig_category":"Agencias De Viajes",
    "sg:phone":"+34 964 23 90 62",
    "sg:postcode":"12001",
    "sg:province":"Castell\u00f3n",
    "sg:website":"www-barceloviajes.com",
    "wof:name":"Viajes Barcelo S.l.",
    "wof:placetype":"venue"
},
  "geometry": {"coordinates":[-0.0390900001,39.9866714478],"type":"Point"}
}