{
  "type": "Feature",
  "properties": {
    "addr:full":"Carr General Weyler, 87 Badalona Barcelona 08912",
    "addr:housenumber":"87",
    "addr:postcode":"08912",
    "addr:street":"Carr General Weyler",
    "iso:country":"ES",
    "sg:address":"Carr General Weyler, 87",
    "sg:city":"Badalona",
    "sg:orig_category":"Artes Gr\u00c1ficas, Artes Pl\u00c1sticas (curso)",
    "sg:phone":"+34 934 60 44 64",
    "sg:postcode":"08912",
    "sg:province":"Barcelona",
    "wof:name":"Artes Graficas Venus S.l.",
    "wof:placetype":"venue"
},
  "geometry": {"coordinates":[2.2390291691,41.4415550232],"type":"Point"}
}