{
  "type": "Feature",
  "properties": {
    "iso:country":"ES",
    "sg:address":"Calle de Castillejos, 28",
    "sg:city":"Palmas De Gran Canaria",
    "sg:orig_category":"Molduras, Junquillos, Listones Y Molduras Perforadas",
    "sg:phone":"+34 928 27 35 73",
    "sg:postcode":"35010",
    "sg:province":"Las Palmas",
    "wof:name":"Perez Falcon Manuel",
    "wof:placetype":"venue"
},
  "geometry": {"coordinates":[-15.4432458878,28.1295433044],"type":"Point"}
}