{
  "type": "Feature",
  "properties": {
    "addr:full":"Cmno Ronda (de), 122 Granada Granada 18003",
    "addr:housenumber":"122",
    "addr:postcode":"18003",
    "addr:street":"Cmno Ronda De",
    "iso:country":"ES",
    "sg:address":"Cmno Ronda (de), 122",
    "sg:city":"Granada",
    "sg:orig_category":"Aparatos E Instalaci\u00d3n De Regad\u00cdos",
    "sg:phone":"+34 958 29 32 09",
    "sg:postcode":"18003",
    "sg:province":"Granada",
    "wof:name":"Suministros Riegosur S.l.",
    "wof:placetype":"venue"
},
  "geometry": {"coordinates":[-3.6087739468,37.1750297546],"type":"Point"}
}