{
  "type": "Feature",
  "properties": {
    "addr:full":"Calle de Castillo (el), 3 Cadrete Zaragoza 50420",
    "addr:housenumber":"3",
    "addr:postcode":"50420",
    "addr:street":"Calle De Castillo El",
    "iso:country":"ES",
    "sg:address":"Calle de Castillo (el), 3",
    "sg:city":"Cadrete",
    "sg:orig_category":"Cer\u00c1mica Art\u00cdstica Y Decorativa",
    "sg:phone":"+34 976 12 62 70",
    "sg:postcode":"50420",
    "sg:province":"Zaragoza",
    "wof:name":"Keramol Ceramica S.c.",
    "wof:placetype":"venue"
},
  "geometry": {"coordinates":[-0.9591836929,41.5545692444],"type":"Point"}
}