{
  "type": "Feature",
  "properties": {
    "addr:full":"Calle de Arramel, 1 Salvatierra O Agurain \u00c1lava 01200",
    "addr:housenumber":"1",
    "addr:postcode":"01200",
    "addr:street":"Calle De Arramel;A\u0301Lava",
    "iso:country":"ES",
    "sg:address":"Calle de Arramel, 1",
    "sg:city":"Salvatierra O Agurain",
    "sg:orig_category":"Asociaciones, Organismos Culturales Y Socioeducativos",
    "sg:phone":"+34 945 31 25 24",
    "sg:postcode":"01200",
    "sg:province":"\u00c1lava",
    "wof:name":"Partido Nacionalista Vasco",
    "wof:placetype":"venue"
},
  "geometry": {"coordinates":[-2.3885509968,42.8498191833],"type":"Point"}
}