{
  "type": "Feature",
  "properties": {
    "iso:country":"ES",
    "sg:address":"Calle de Villaviciosa, 32",
    "sg:city":"Madrid",
    "sg:orig_category":"Asesor\u00cda Sobre Comunicaci\u00d3n De Empresas",
    "sg:phone":"+34 915 18 26 72",
    "sg:postcode":"28024",
    "sg:province":"Madrid",
    "wof:name":"Gonzalez Baute Claudio",
    "wof:placetype":"venue"
},
  "geometry": {"coordinates":[-3.769051075,40.3978805542],"type":"Point"}
}