{
  "type": "Feature",
  "properties": {
    "addr:full":"Carrer de Diputacio, 397 Barcelona Barcelona 08013",
    "addr:housenumber":"397",
    "addr:postcode":"08013",
    "addr:street":"Carrer De Diputacio",
    "iso:country":"ES",
    "sg:address":"Carrer de Diputacio, 397",
    "sg:city":"Barcelona",
    "sg:orig_category":"\u00d3ptica: Instrumentos (fabricaci\u00d3n)",
    "sg:phone":"+34 932 32 81 63",
    "sg:postcode":"08013",
    "sg:province":"Barcelona",
    "wof:name":"Arboit Caparros Miriam",
    "wof:placetype":"venue"
},
  "geometry": {"coordinates":[2.1766145229,41.3975982666],"type":"Point"}
}