{
  "type": "Feature",
  "properties": {
    "addr:full":"Carr Fornaca, 34 Blanes Girona 17300",
    "addr:housenumber":"34",
    "addr:postcode":"17300",
    "addr:street":"Carr Fornaca",
    "iso:country":"ES",
    "sg:address":"Carr Fornaca, 34",
    "sg:city":"Blanes",
    "sg:orig_category":"Art\u00cdculos De Decoraci\u00d3n (fabricaci\u00d3n Y Al Por Mayor)",
    "sg:phone":"+34 972 35 14 28",
    "sg:postcode":"17300",
    "sg:province":"Girona",
    "wof:name":"Escarpanter Bassas Montserrat",
    "wof:placetype":"venue"
},
  "geometry": {"coordinates":[2.7906849384,41.6724243164],"type":"Point"}
}