{
  "type": "Feature",
  "properties": {
    "addr:full":"Ctra Agost, 64 San Vicente Del Raspeig-sant Vicent Del Raspeig Alicante 03690",
    "addr:housenumber":"64",
    "addr:postcode":"03690",
    "addr:street":"Ctra Agost",
    "iso:country":"ES",
    "sg:address":"Ctra Agost, 64",
    "sg:city":"San Vicente Del Raspeig-sant Vicent Del Raspeig",
    "sg:orig_category":"Publicidad (soportes Y Gesti\u00d3n)",
    "sg:phone":"+34 965 66 00 03",
    "sg:postcode":"03690",
    "sg:province":"Alicante",
    "sg:website":"www.e-publex.com",
    "wof:name":"Hidrosanex S.l.",
    "wof:placetype":"venue"
},
  "geometry": {"coordinates":[-0.5211820006,38.4007606506],"type":"Point"}
}