{
  "type": "Feature",
  "properties": {
    "iso:country":"ES",
    "sg:address":"Calle de Virgen De La Cabeza, 6",
    "sg:city":"Dos Hermanas",
    "sg:orig_category":"Fabricaci\u00d3n De Moldes Y Modelos",
    "sg:phone":"+34 955 66 33 27",
    "sg:postcode":"41700",
    "sg:province":"Sevilla",
    "wof:name":"Sanguino Santos Manuela",
    "wof:placetype":"venue"
},
  "geometry": {"coordinates":[-5.9322738647,37.2688751221],"type":"Point"}
}