{
  "type": "Feature",
  "properties": {
    "iso:country":"ES",
    "sg:address":"C/ Filet De Fora, 40",
    "sg:city":"Elche",
    "sg:orig_category":"Arquitectos",
    "sg:phone":"+34 965 45 83 93",
    "sg:postcode":"03203",
    "sg:province":"Alicante",
    "wof:name":"Urban Brotons Pascual",
    "wof:placetype":"venue"
},
  "geometry": {"coordinates":[-0.696130991,38.2627067566],"type":"Point"}
}