{
  "type": "Feature",
  "properties": {
    "iso:country":"ES",
    "sg:address":"Calle de Capitan Dema, 17",
    "sg:city":"Alacant",
    "sg:orig_category":"Abogados",
    "sg:phone":"+34 965 11 61 06",
    "sg:postcode":"03007",
    "sg:province":"Alicante",
    "wof:name":"Rives Santos Francisco Jose",
    "wof:placetype":"venue"
},
  "geometry": {"coordinates":[-0.5004398227,38.3417701721],"type":"Point"}
}