{
  "type": "Feature",
  "properties": {
    "iso:country":"ES",
    "sg:address":"Rua Coru\u00d1a, 2",
    "sg:city":"Carballo",
    "sg:orig_category":"Bisuter\u00cda, Joyer\u00cda, Relojer\u00cda (al Por Menor)",
    "sg:phone":"+34 981 70 17 04",
    "sg:postcode":"15100",
    "sg:province":"A Coru\u00f1a",
    "wof:name":"Seoane Varela Maria Jose",
    "wof:placetype":"venue"
},
  "geometry": {"coordinates":[-8.6896438599,43.2125701904],"type":"Point"}
}