{
  "type": "Feature",
  "properties": {
    "addr:full":"Calle de Vista Alegre, S/n Selaya Cantabria 39696",
    "addr:housenumber":"s / n",
    "addr:postcode":"39696",
    "addr:street":"Calle De Vista Alegre",
    "iso:country":"ES",
    "sg:address":"Calle de Vista Alegre, S/n",
    "sg:city":"Selaya",
    "sg:orig_category":"Peluquer\u00cdas, Peluquer\u00cda Mixta",
    "sg:phone":"+34 942 59 05 99",
    "sg:postcode":"39696",
    "sg:province":"Cantabria",
    "wof:name":"Garcia Gutierrez Nuria",
    "wof:placetype":"venue"
},
  "geometry": {"coordinates":[-3.8050539494,43.2141494751],"type":"Point"}
}