{
  "type": "Feature",
  "properties": {
    "addr:full":"Pase Victoria (de La), 49 Cordoba C\u00f3rdoba 14004",
    "addr:postcode":"14004",
    "addr:street":"Co\u0301Rdoba",
    "iso:country":"ES",
    "sg:address":"Pase Victoria (de La), 49",
    "sg:city":"Cordoba",
    "sg:orig_category":"Ropa Para Beb\u00c9s Y Ni\u00d1os (confecci\u00d3n, Al Por Mayor)",
    "sg:phone":"+34 957 29 68 00",
    "sg:postcode":"14004",
    "sg:province":"C\u00f3rdoba",
    "wof:name":"Maria Luisa Artesania De La Torre Y Otros Cdad.",
    "wof:placetype":"venue"
},
  "geometry": {"coordinates":[-4.7845849991,37.8822250366],"type":"Point"}
}