{
  "type": "Feature",
  "properties": {
    "addr:full":"Calle de Iglesia, 1 Figueruela De Arriba Zamora 49520",
    "addr:housenumber":"1",
    "addr:postcode":"49520",
    "addr:street":"Calle De Iglesia",
    "iso:country":"ES",
    "sg:address":"Calle de Iglesia, 1",
    "sg:city":"Figueruela De Arriba",
    "sg:orig_category":"Ense\u00d1anza, Formaci\u00d3n Profesional: Aprendizaje",
    "sg:phone":"+34 980 68 30 48",
    "sg:postcode":"49520",
    "sg:province":"Zamora",
    "wof:name":"Ayuntamiento De Figueruela De Arriba",
    "wof:placetype":"venue"
},
  "geometry": {"coordinates":[-6.4461407661,41.8690071106],"type":"Point"}
}