{
  "type": "Feature",
  "properties": {
    "addr:full":"Avda Breogan, 61 Ferrol La Coru\u00f1a 15401",
    "addr:housenumber":"61",
    "addr:postcode":"15401",
    "addr:street":"Avda Breogan;La Corun\u0303A",
    "iso:country":"ES",
    "sg:address":"Avda Breogan, 61",
    "sg:city":"Ferrol",
    "sg:orig_category":"Ingenier\u00cda, Centros De Estudios (diversos)",
    "sg:phone":"+34 981 35 81 81",
    "sg:postcode":"15401",
    "sg:province":"La Coru\u00f1a",
    "wof:name":"Garcia Lopez Pablo Santiago",
    "wof:placetype":"venue"
},
  "geometry": {"coordinates":[-8.2463188171,43.4815406799],"type":"Point"}
}