{
  "type": "Feature",
  "properties": {
    "addr:full":"Calle de Doctor Gea Mari\u00d1o, 6 Castellon Castell\u00f3n 12005",
    "addr:housenumber":"6",
    "addr:postcode":"12005",
    "addr:street":"Calle De Doctor Gea Marin\u0303O;Castello\u0301N",
    "iso:country":"ES",
    "sg:address":"Calle de Doctor Gea Mari\u00d1o, 6",
    "sg:city":"Castellon",
    "sg:orig_category":"Controles De Edificaci\u00d3n (construcci\u00d3n, Seguridad)",
    "sg:phone":"+34 964 24 43 03",
    "sg:postcode":"12005",
    "sg:province":"Castell\u00f3n",
    "wof:name":"Rex Control S.l.",
    "wof:placetype":"venue"
},
  "geometry": {"coordinates":[-0.0479838997,39.9754066467],"type":"Point"}
}