{
  "type": "Feature",
  "properties": {
    "iso:country":"ES",
    "sg:address":"Carrer de Parellada, 10",
    "sg:city":"Rubi",
    "sg:orig_category":"Fabricaci\u00d3n De Banderas Y De Banderines",
    "sg:phone":"+34 935 88 12 87",
    "sg:postcode":"08191",
    "sg:province":"Barcelona",
    "wof:name":"Molina Cortes Juan",
    "wof:placetype":"venue"
},
  "geometry": {"coordinates":[2.0279231071,41.4941368103],"type":"Point"}
}