{
  "type": "Feature",
  "properties": {
    "iso:country":"ES",
    "sg:address":"Pg Josep Mundet, S/n",
    "sg:city":"S. Antoni Calonge",
    "sg:orig_category":"Peluqueros: De Se\u00d1oras",
    "sg:phone":"+34 972 65 14 46",
    "sg:postcode":"17252",
    "sg:province":"Girona",
    "wof:name":"Costa Pous Pedro",
    "wof:placetype":"venue"
},
  "geometry": {"coordinates":[3.1000049114,41.843952179],"type":"Point"}
}