{
  "type": "Feature",
  "properties": {
    "addr:full":"Paraje La Majuela, S/n Cari\u00f1ena Zaragoza 50400",
    "addr:housenumber":"s / n",
    "addr:postcode":"50400",
    "addr:street":"Paraje La Majuela",
    "iso:country":"ES",
    "sg:address":"Paraje La Majuela, S/n",
    "sg:city":"Cari\u00f1ena",
    "sg:orig_category":"Aguas (distribuci\u00d3n, Servicios)",
    "sg:phone":"+34 976 62 50 30",
    "sg:postcode":"50400",
    "sg:province":"Zaragoza",
    "wof:name":"Aguas Sierra Del Aguila S.a.",
    "wof:placetype":"venue"
},
  "geometry": {"coordinates":[-1.1929113865,41.3348999023],"type":"Point"}
}