{
  "type": "Feature",
  "properties": {
    "iso:country":"ES",
    "sg:address":"Calle de Alcora, 46",
    "sg:city":"Almazora",
    "sg:orig_category":"Cerrajer\u00cda, Ferrallista",
    "sg:phone":"+34 964 56 02 99",
    "sg:postcode":"12550",
    "sg:province":"Castell\u00f3n",
    "wof:name":"Gandia Beltran Jose",
    "wof:placetype":"venue"
},
  "geometry": {"coordinates":[-0.0643595979,39.9437904358],"type":"Point"}
}