{
  "type": "Feature",
  "properties": {
    "addr:full":"Avda Jose Fari\u00d1a, 44 Huelva Huelva 21006",
    "addr:housenumber":"44",
    "addr:postcode":"21006",
    "addr:street":"Avda Jose Farin\u0303A",
    "iso:country":"ES",
    "sg:address":"Avda Jose Fari\u00d1a, 44",
    "sg:city":"Huelva",
    "sg:orig_category":"Camas (al Por Menor)",
    "sg:phone":"+34 959 23 30 63",
    "sg:postcode":"21006",
    "sg:province":"Huelva",
    "wof:name":"Ruiz Felipe Fernando",
    "wof:placetype":"venue"
},
  "geometry": {"coordinates":[-6.9356122017,37.2602806091],"type":"Point"}
}