{
  "type": "Feature",
  "properties": {
    "addr:full":"Vi\u00f1a, S/n Lorca Murcia 30800",
    "addr:housenumber":"/ n",
    "addr:postcode":"30800",
    "addr:street":"Vin\u0303A S",
    "iso:country":"ES",
    "sg:address":"Vi\u00f1a, S/n",
    "sg:city":"Lorca",
    "sg:orig_category":"Centros De Educaci\u00d3n Especial",
    "sg:phone":"+34 968 44 44 46",
    "sg:postcode":"30800",
    "sg:province":"Murcia",
    "wof:name":"Colegio Publico Educacion Especial Comarcal",
    "wof:placetype":"venue"
},
  "geometry": {"coordinates":[-1.6905640364,37.680557251],"type":"Point"}
}