{
  "type": "Feature",
  "properties": {
    "addr:full":"Avd Jerez Edf Sevilla Sur, S/n Sevilla Sevilla 41014",
    "addr:housenumber":"s / n",
    "addr:postcode":"41014",
    "addr:street":"Avd Jerez",
    "iso:country":"ES",
    "sg:address":"Avd Jerez Edf Sevilla Sur, S/n",
    "sg:city":"Sevilla",
    "sg:orig_category":"Instalaci\u00d3n, Mantenimiento De Porteros Electr\u00d3nicos Y Controles De Acceso",
    "sg:phone":"+34 954 61 99 22",
    "sg:postcode":"41014",
    "sg:province":"Sevilla",
    "wof:name":"Spec S. A.",
    "wof:placetype":"venue"
},
  "geometry": {"coordinates":[-5.9596791267,37.3278617859],"type":"Point"}
}