{
  "type": "Feature",
  "properties": {
    "iso:country":"ES",
    "sg:address":"Carrer de Sant Artur (de), 43",
    "sg:city":"Vilassar De Mar",
    "sg:orig_category":"Peluquer\u00cdas, Peluquer\u00cda Mixta",
    "sg:phone":"+34 937 50 29 24",
    "sg:postcode":"08340",
    "sg:province":"Barcelona",
    "wof:name":"Gonzalez Diaz Luisa",
    "wof:placetype":"venue"
},
  "geometry": {"coordinates":[2.3873689175,41.4998016357],"type":"Point"}
}