{
  "type": "Feature",
  "properties": {
    "addr:full":"Calle de San Juan, 21 Molina Guadalajara 19300",
    "addr:housenumber":"21",
    "addr:postcode":"19300",
    "addr:street":"Calle De San Juan",
    "iso:country":"ES",
    "sg:address":"Calle de San Juan, 21",
    "sg:city":"Molina",
    "sg:orig_category":"Asesor\u00cda Fiscal Y Jur\u00cddica",
    "sg:phone":"+34 949 83 18 96",
    "sg:postcode":"19300",
    "sg:province":"Guadalajara",
    "wof:name":"Aseloma S.l.",
    "wof:placetype":"venue"
},
  "geometry": {"coordinates":[-1.8839375973,40.843132019],"type":"Point"}
}