{
  "type": "Feature",
  "properties": {
    "addr:full":"Pl Margarida Xirgu, 2 Sabadell Barcelona 08204",
    "addr:housenumber":"2",
    "addr:postcode":"08204",
    "addr:street":"Pl Margarida Xirgu",
    "iso:country":"ES",
    "sg:address":"Pl Margarida Xirgu, 2",
    "sg:city":"Sabadell",
    "sg:orig_category":"Impuestos, Tesoro P\u00dablico",
    "sg:phone":"+34 937 12 27 49",
    "sg:postcode":"08204",
    "sg:province":"Barcelona",
    "wof:name":"Gabitax S.l.",
    "wof:placetype":"venue"
},
  "geometry": {"coordinates":[2.1057798862,41.5285644531],"type":"Point"}
}