{
  "type": "Feature",
  "properties": {
    "addr:full":"Carrer de Sant Hermenegild, 18 Barcelona Barcelona 08006",
    "addr:housenumber":"18",
    "addr:postcode":"08006",
    "addr:street":"Carrer De Sant Hermenegild",
    "iso:country":"ES",
    "sg:address":"Carrer de Sant Hermenegild, 18",
    "sg:city":"Barcelona",
    "sg:orig_category":"Molduras, Junquillos, Listones Y Molduras Perforadas",
    "sg:phone":"+34 932 11 65 75",
    "sg:postcode":"08006",
    "sg:province":"Barcelona",
    "wof:name":"Reyes Pangan Amparo",
    "wof:placetype":"venue"
},
  "geometry": {"coordinates":[2.1450109482,41.4038124084],"type":"Point"}
}