{
  "type": "Feature",
  "properties": {
    "iso:country":"ES",
    "sg:address":"Ispizua Kalea, 1",
    "sg:city":"Hernani",
    "sg:orig_category":"Ebanistas Y Talladores De Muebles Y Objetos De Arte",
    "sg:phone":"+34 943 55 08 83",
    "sg:postcode":"20120",
    "sg:province":"Guip\u00f9zcoa",
    "wof:name":"Nerea Bergara Comin Y Otra C.b.",
    "wof:placetype":"venue"
},
  "geometry": {"coordinates":[-1.9767010212,43.2659416199],"type":"Point"}
}