{
  "type": "Feature",
  "properties": {
    "addr:full":"Avda Gasteiz, 84 Vitoria-gasteiz \u00c1lava 01012",
    "addr:housenumber":"84",
    "addr:postcode":"01012",
    "addr:street":"Avda Gasteiz",
    "iso:country":"ES",
    "sg:address":"Avda Gasteiz, 84",
    "sg:city":"Vitoria-gasteiz",
    "sg:orig_category":"Art\u00cdculos De Regalo (al Por Menor)",
    "sg:phone":"+34 945 22 00 68",
    "sg:postcode":"01012",
    "sg:province":"\u00c1lava",
    "wof:name":"Vega Perillan Miguel",
    "wof:placetype":"venue"
},
  "geometry": {"coordinates":[-2.6795730591,42.8543205261],"type":"Point"}
}