{
  "type": "Feature",
  "properties": {
    "addr:full":"Rua Galicia (de), 2 Vilalba Lugo 27800",
    "addr:housenumber":"2",
    "addr:postcode":"27800",
    "addr:street":"Rua Galicia De",
    "iso:country":"ES",
    "sg:address":"Rua Galicia (de), 2",
    "sg:city":"Vilalba",
    "sg:orig_category":"Molduras, Junquillos, Listones Y Molduras Perforadas",
    "sg:phone":"+34 982 51 15 53",
    "sg:postcode":"27800",
    "sg:province":"Lugo",
    "wof:name":"Carreira Otero Francisco",
    "wof:placetype":"venue"
},
  "geometry": {"coordinates":[-7.6814827919,43.295791626],"type":"Point"}
}