{
  "type": "Feature",
  "properties": {
    "addr:full":"Calle de San Cristobal, 8 Ponferrada Le\u00f3n 24400",
    "addr:postcode":"24400",
    "addr:street":"Calle De San Cristobal 8;Leo\u0301N",
    "iso:country":"ES",
    "sg:address":"Calle de San Cristobal, 8",
    "sg:city":"Ponferrada",
    "sg:orig_category":"Bordado, Marcado A Medida",
    "sg:phone":"+34 987 42 91 66",
    "sg:postcode":"24400",
    "sg:province":"Le\u00f3n",
    "wof:name":"Rodriguez Cascallana Carmen",
    "wof:placetype":"venue"
},
  "geometry": {"coordinates":[-6.6010088921,42.5487060547],"type":"Point"}
}