{
  "type": "Feature",
  "properties": {
    "iso:country":"ES",
    "sg:address":"Calle de Hornos, 14",
    "sg:city":"Monesterio",
    "sg:orig_category":"Producci\u00d3n, Venta De Productos De Agricultura Biol\u00d3gica",
    "sg:phone":"+34 924 51 70 68",
    "sg:postcode":"06260",
    "sg:province":"Badajoz",
    "wof:name":"Martin Arranz S.a.",
    "wof:placetype":"venue"
},
  "geometry": {"coordinates":[-6.2763881683,38.0871047974],"type":"Point"}
}