{
  "type": "Feature",
  "properties": {
    "addr:full":"Ctra Tortosa, Km. 0000,5 Amposta Tarragona 43870",
    "addr:postcode":"43870",
    "addr:street":"Ctra Tortosa Km. 0000,5",
    "iso:country":"ES",
    "sg:address":"Ctra Tortosa, Km. 0000,5",
    "sg:city":"Amposta",
    "sg:orig_category":"Materias Pl\u00c1sticas: Art\u00cdculos Para La Industria",
    "sg:phone":"+34 977 70 54 83",
    "sg:postcode":"43870",
    "sg:province":"Tarragona",
    "wof:name":"Astral Pool Espa\u00d1a S.a.u.",
    "wof:placetype":"venue"
},
  "geometry": {"coordinates":[0.5302429199,40.71616745],"type":"Point"}
}