{
  "type": "Feature",
  "properties": {
    "addr:full":"Andres Maria Pastor, 12 Massanassa Valencia 46470",
    "addr:housenumber":"12",
    "addr:postcode":"46470",
    "addr:street":"Pastor",
    "iso:country":"ES",
    "sg:address":"Andres Maria Pastor, 12",
    "sg:city":"Massanassa",
    "sg:orig_category":"Internados & Ense\u00d1anza Privada",
    "sg:phone":"+34 961 25 05 81",
    "sg:postcode":"46470",
    "sg:province":"Valencia",
    "wof:name":"Fundacion Ee San Jose San Andres Y San Benito",
    "wof:placetype":"venue"
},
  "geometry": {"coordinates":[-0.3961870074,39.4081764221],"type":"Point"}
}