{
  "type": "Feature",
  "properties": {
    "iso:country":"ES",
    "sg:address":"Calle de Apote, 10",
    "sg:city":"Irurita",
    "sg:orig_category":"Serrer\u00cdas De Madera",
    "sg:phone":"+34 948 58 01 68",
    "sg:postcode":"31730",
    "sg:province":"Navarra",
    "wof:name":"Vaquero Arrache Mikel",
    "wof:placetype":"venue"
},
  "geometry": {"coordinates":[-1.5474791527,43.1269760132],"type":"Point"}
}