{
  "type": "Feature",
  "properties": {
    "iso:country":"ES",
    "sg:address":"Pol. Ind. Sia-sta. Barbara, S/n",
    "sg:city":"Lugones",
    "sg:orig_category":"Cristaler\u00cdas",
    "sg:phone":"+34 985 26 06 05",
    "sg:postcode":"33420",
    "sg:province":"Asturias",
    "wof:name":"Alucris S. A.",
    "wof:placetype":"venue"
},
  "geometry": {"coordinates":[-5.8103342056,43.4049339294],"type":"Point"}
}