{
  "type": "Feature",
  "properties": {
    "iso:country":"ES",
    "sg:address":"Calle de Gil Roger, 6",
    "sg:city":"Valencia",
    "sg:orig_category":"Cl\u00cdnicas Dentales",
    "sg:phone":"+34 963 49 39 20",
    "sg:postcode":"46009",
    "sg:province":"Valencia",
    "wof:name":"Collado Monteagudo Rafael",
    "wof:placetype":"venue"
},
  "geometry": {"coordinates":[-0.3898639977,39.4860725403],"type":"Point"}
}