{
  "type": "Feature",
  "properties": {
    "iso:country":"ES",
    "sg:address":"Carrer de Gran De Sant Andreu, 261",
    "sg:city":"Barcelona",
    "sg:orig_category":"Mercer\u00cda, Lencer\u00cda (al Por Menor)",
    "sg:phone":"+34 933 45 04 57",
    "sg:postcode":"08030",
    "sg:province":"Barcelona",
    "wof:name":"Perello Cura Concepcion",
    "wof:placetype":"venue"
},
  "geometry": {"coordinates":[2.1895599365,41.4356689453],"type":"Point"}
}