{
  "type": "Feature",
  "properties": {
    "addr:full":"Rua Cruz Gallastegui, 2 Pontevedra Pontevedra 36001",
    "addr:housenumber":"2",
    "addr:postcode":"36001",
    "addr:street":"Rua Cruz Gallastegui",
    "iso:country":"ES",
    "sg:address":"Rua Cruz Gallastegui, 2",
    "sg:city":"Pontevedra",
    "sg:orig_category":"Asesor\u00cda Sobre Comunicaci\u00d3n De Empresas",
    "sg:phone":"+34 986 84 03 34",
    "sg:postcode":"36001",
    "sg:province":"Pontevedra",
    "wof:name":"Asesoria Zeus S.l.",
    "wof:placetype":"venue"
},
  "geometry": {"coordinates":[-8.6412982941,42.4296989441],"type":"Point"}
}