{
  "type": "Feature",
  "properties": {
    "addr:full":"Tollo, 47 Tollo Pontevedra 36750",
    "addr:housenumber":"47",
    "addr:postcode":"36750",
    "addr:street":"Tollo",
    "iso:country":"ES",
    "sg:address":"Tollo, 47",
    "sg:city":"Tollo",
    "sg:orig_category":"Semiller\u00cdas",
    "sg:phone":"+34 986 60 97 09",
    "sg:postcode":"36750",
    "sg:province":"Pontevedra",
    "wof:name":"Viveiros Rio Tollo S L",
    "wof:placetype":"venue"
},
  "geometry": {"coordinates":[-8.6480531693,42.4336204529],"type":"Point"}
}