{
  "type": "Feature",
  "properties": {
    "iso:country":"ES",
    "sg:address":"Calle de Jose Tallavi, 8",
    "sg:city":"Malaga",
    "sg:orig_category":"Peluquer\u00cdas, Peluquer\u00cda Mixta",
    "sg:phone":"+34 952 26 30 91",
    "sg:postcode":"29014",
    "sg:province":"M\u00e1laga",
    "wof:name":"Castillo Manzanero Carmen",
    "wof:placetype":"venue"
},
  "geometry": {"coordinates":[-4.4218277931,36.7407302856],"type":"Point"}
}