{
  "type": "Feature",
  "properties": {
    "addr:full":"Calle de Cuesta Del Rosario, 8 Sevilla Sevilla 41004",
    "addr:housenumber":"8",
    "addr:postcode":"41004",
    "addr:street":"Calle De Cuesta Del Rosario",
    "iso:country":"ES",
    "sg:address":"Calle de Cuesta Del Rosario, 8",
    "sg:city":"Sevilla",
    "sg:orig_category":"Agencias De Viajes",
    "sg:phone":"+34 954 21 36 00",
    "sg:postcode":"41004",
    "sg:province":"Sevilla",
    "wof:name":"Viajes Iberojet",
    "wof:placetype":"venue"
},
  "geometry": {"coordinates":[-5.9916272163,37.3897247314],"type":"Point"}
}