{
  "type": "Feature",
  "properties": {
    "addr:full":"Calle de San Jose, 11 Burgos Burgos 09002",
    "addr:housenumber":"11",
    "addr:postcode":"09002",
    "addr:street":"Calle De San",
    "iso:country":"ES",
    "sg:address":"Calle de San Jose, 11",
    "sg:city":"Burgos",
    "sg:orig_category":"Asociaciones, Organismos Culturales Y Socioeducativos",
    "sg:phone":"+34 947 26 11 78",
    "sg:postcode":"09002",
    "sg:province":"Burgos",
    "wof:name":"Pe\u00f1a San Juan Del Monte",
    "wof:placetype":"venue"
},
  "geometry": {"coordinates":[-3.6927719116,42.3385734558],"type":"Point"}
}