{
  "type": "Feature",
  "properties": {
    "iso:country":"ES",
    "sg:address":"Olabide, 11",
    "sg:city":"Moreaga",
    "sg:orig_category":"Fabricaci\u00d3n, Reparaci\u00d3n Y Mantenimiento De Construcciones Navales Y Fluviales",
    "sg:phone":"+34 946 76 06 97",
    "sg:postcode":"48600",
    "sg:province":"Vizcaya",
    "sg:website":"www.infonegocio.com/reacomar",
    "wof:name":"Reacomar S.a.l.",
    "wof:placetype":"venue"
},
  "geometry": {"coordinates":[-2.9704329967,43.3788414001],"type":"Point"}
}