{
  "type": "Feature",
  "properties": {
    "iso:country":"ES",
    "sg:address":"Calle de Empedrada, 2",
    "sg:city":"Medina Rioseco",
    "sg:orig_category":"Loter\u00cda Y T\u00d3mbola",
    "sg:phone":"+34 983 70 02 10",
    "sg:postcode":"47800",
    "sg:province":"Valladolid",
    "wof:name":"Garcia Blanco Francisco Javier",
    "wof:placetype":"venue"
},
  "geometry": {"coordinates":[-5.0439190865,41.8827590942],"type":"Point"}
}