{
  "type": "Feature",
  "properties": {
    "iso:country":"ES",
    "sg:address":"Pase Pocillo, 4",
    "sg:city":"San Ildefonso O La Granja",
    "sg:orig_category":"Molduras, Junquillos, Listones Y Molduras Perforadas",
    "sg:phone":"+34 921 47 10 58",
    "sg:postcode":"40100",
    "sg:province":"Segovia",
    "wof:name":"Delgado Garcia Francisco",
    "wof:placetype":"venue"
},
  "geometry": {"coordinates":[-4.0045309067,40.9069519043],"type":"Point"}
}