{
  "type": "Feature",
  "properties": {
    "iso:country":"ES",
    "sg:address":"Avda Europa, 15",
    "sg:city":"Pozuelo De Alarcon",
    "sg:orig_category":"Armas Y Municiones (fabricaci\u00d3n, Al Por Mayor)",
    "sg:phone":"+34 913 52 76 88",
    "sg:postcode":"28224",
    "sg:province":"Madrid",
    "wof:name":"Safari Express Armeria C.b.",
    "wof:placetype":"venue"
},
  "geometry": {"coordinates":[-3.7898540497,40.4400367737],"type":"Point"}
}