{
  "type": "Feature",
  "properties": {
    "iso:country":"ES",
    "sg:address":"Av Gaudi, 6",
    "sg:city":"Barcelona",
    "sg:orig_category":"Zapatos (al Por Menor)",
    "sg:phone":"+34 934 55 24 26",
    "sg:postcode":"08025",
    "sg:province":"Barcelona",
    "wof:name":"Lloret I\u00f1esta Maria Teresa",
    "wof:placetype":"venue"
},
  "geometry": {"coordinates":[2.1746850014,41.4049797058],"type":"Point"}
}