{
  "type": "Feature",
  "properties": {
    "addr:full":"Plaz Virgen (de La), 26 Cullera Valencia 46400",
    "addr:housenumber":"26",
    "addr:postcode":"46400",
    "addr:street":"Plaz Virgen De La",
    "iso:country":"ES",
    "sg:address":"Plaz Virgen (de La), 26",
    "sg:city":"Cullera",
    "sg:orig_category":"Ropa Para Caballeros (al Por Menor)",
    "sg:phone":"+34 961 73 86 97",
    "sg:postcode":"46400",
    "sg:province":"Valencia",
    "wof:name":"Jose Varela S.l.u.",
    "wof:placetype":"venue"
},
  "geometry": {"coordinates":[-0.2562240064,39.1653251648],"type":"Point"}
}