{
  "type": "Feature",
  "properties": {
    "iso:country":"ES",
    "sg:address":"Calle de Sepulveda (de), 11",
    "sg:city":"Alcobendas",
    "sg:orig_category":"Automatizaci\u00d3n De Procesos Industriales Y De Edificaci\u00d3n (estudios, Instalaci\u00d3n)",
    "sg:phone":"+34 916 57 21 21",
    "sg:postcode":"28...",
    "sg:province":"Madrid",
    "wof:name":"Vdo Kienzle Espa\u00d1a S.a.",
    "wof:placetype":"venue"
},
  "geometry": {"coordinates":[-3.6555390358,40.5274353027],"type":"Point"}
}