{
  "type": "Feature",
  "properties": {
    "iso:country":"ES",
    "sg:address":"Carr Francesc Ciurana, 15",
    "sg:city":"Girona",
    "sg:orig_category":"Psic\u00d3logos",
    "sg:phone":"+34 972 20 07 15",
    "sg:postcode":"17002",
    "sg:province":"Girona",
    "wof:name":"Pueyo Cabo Jose Miguel",
    "wof:placetype":"venue"
},
  "geometry": {"coordinates":[2.8184850216,41.9769210815],"type":"Point"}
}