{
  "type": "Feature",
  "properties": {
    "addr:full":"Calle de Molino Blanco, 27 S. Pedro Martir I Las Palmas 35110",
    "addr:housenumber":"27",
    "addr:postcode":"35110",
    "addr:street":"Calle De Molino Blanco;S. Pedro",
    "iso:country":"ES",
    "sg:address":"Calle de Molino Blanco, 27",
    "sg:city":"S. Pedro Martir I",
    "sg:orig_category":"Embalajes",
    "sg:phone":"+34 928 75 04 51",
    "sg:postcode":"35110",
    "sg:province":"Las Palmas",
    "wof:name":"Cooperativa Union De Agricultores Y Ganaderos De Sardina Del Sur",
    "wof:placetype":"venue"
},
  "geometry": {"coordinates":[-15.4485340118,27.8392906189],"type":"Point"}
}