{
  "type": "Feature",
  "properties": {
    "addr:full":"Calle de Marques De Mondejar, 46 Granada Granada 18004",
    "addr:housenumber":"46",
    "addr:postcode":"18004",
    "addr:street":"Calle De Marques De Mondejar",
    "iso:country":"ES",
    "sg:address":"Calle de Marques De Mondejar, 46",
    "sg:city":"Granada",
    "sg:orig_category":"Agentes Generales De Seguros",
    "sg:phone":"+34 958 25 17 34",
    "sg:postcode":"18004",
    "sg:province":"Granada",
    "wof:name":"Ortega Martin Antonio",
    "wof:placetype":"venue"
},
  "geometry": {"coordinates":[-3.6033740044,37.1684646606],"type":"Point"}
}