{
  "type": "Feature",
  "properties": {
    "iso:country":"ES",
    "sg:address":"Ctra Isla Menor (la), Km. 0032,0",
    "sg:city":"Sevilla",
    "sg:orig_category":"Negocio De Madera",
    "sg:phone":"+34 954 69 14 12",
    "sg:postcode":"41014",
    "sg:province":"Sevilla",
    "wof:name":"Maderas Morcillo S. L.",
    "wof:placetype":"venue"
},
  "geometry": {"coordinates":[-5.9596791267,37.3278617859],"type":"Point"}
}