{
  "type": "Feature",
  "properties": {
    "iso:country":"ES",
    "sg:address":"Calle de Petra Sanchez (de), 6",
    "sg:city":"Coslada",
    "sg:orig_category":"Electrodom\u00c9sticos (al Por Menor)",
    "sg:phone":"+34 916 73 17 46",
    "sg:postcode":"28820",
    "sg:province":"Madrid",
    "wof:name":"Canal 7 S. A.",
    "wof:placetype":"venue"
},
  "geometry": {"coordinates":[-3.5635399818,40.4250106812],"type":"Point"}
}