{
  "type": "Feature",
  "properties": {
    "addr:full":"Carrer de Llu\u00c7anes, 41 Sabadell Barcelona 08207",
    "addr:housenumber":"41",
    "addr:postcode":"08207",
    "addr:street":"Carrer De Lluc\u0327Anes",
    "iso:country":"ES",
    "sg:address":"Carrer de Llu\u00c7anes, 41",
    "sg:city":"Sabadell",
    "sg:orig_category":"Alimentaci\u00d3n General (al Por Menor)",
    "sg:phone":"+34 937 17 45 01",
    "sg:postcode":"08207",
    "sg:province":"Barcelona",
    "wof:name":"Artisan Fontanet Joaquin",
    "wof:placetype":"venue"
},
  "geometry": {"coordinates":[2.0917410851,41.5671157837],"type":"Point"}
}