{
  "type": "Feature",
  "properties": {
    "addr:full":"Calle de Virgen Del Carmen, 10 Manzanares Ciudad Real 13200",
    "addr:housenumber":"10",
    "addr:postcode":"13200",
    "addr:street":"Calle De Virgen Del Carmen",
    "iso:country":"ES",
    "sg:address":"Calle de Virgen Del Carmen, 10",
    "sg:city":"Manzanares",
    "sg:orig_category":"Teatros Y Salas De Espect\u00c1culos",
    "sg:phone":"+34 926 61 17 36",
    "sg:postcode":"13200",
    "sg:province":"Ciudad Real",
    "wof:name":"Agrupacion Lazarillo. Teatro Camara Y Ensayo",
    "wof:placetype":"venue"
},
  "geometry": {"coordinates":[-3.3712623119,38.9950141907],"type":"Point"}
}