{
  "type": "Feature",
  "properties": {
    "iso:country":"ES",
    "sg:address":"Carrer de Raiguer (del), S/n",
    "sg:city":"Montornes Nord",
    "sg:orig_category":"Confiter\u00cdas, Chocolater\u00cdas (al Por Menor)",
    "sg:phone":"+34 935 72 20 42",
    "sg:postcode":"08170",
    "sg:province":"Barcelona",
    "wof:name":"Ferrero Iberica S.a.",
    "wof:placetype":"venue"
},
  "geometry": {"coordinates":[2.2627000809,41.5591583252],"type":"Point"}
}