{
  "type": "Feature",
  "properties": {
    "addr:full":"Carrer de Montcada, 2 Castellar Valles Barcelona 08211",
    "addr:housenumber":"2",
    "addr:postcode":"08211",
    "addr:street":"Carrer De Montcada",
    "iso:country":"ES",
    "sg:address":"Carrer de Montcada, 2",
    "sg:city":"Castellar Valles",
    "sg:orig_category":"Sociedades, Compa\u00d1\u00cdas Aseguradoras",
    "sg:phone":"+34 937 14 79 47",
    "sg:postcode":"08211",
    "sg:province":"Barcelona",
    "wof:name":"Mapfre Servicios De Informatica",
    "wof:placetype":"venue"
},
  "geometry": {"coordinates":[2.0885519981,41.6160545349],"type":"Point"}
}