{
  "type": "Feature",
  "properties": {
    "iso:country":"ES",
    "sg:address":"Av Catalunya, S/n",
    "sg:city":"Hospitalet Llobregat",
    "sg:orig_category":"Librer\u00cdas",
    "sg:phone":"+34 933 34 76 35",
    "sg:postcode":"08905",
    "sg:province":"Barcelona",
    "wof:name":"Garicano Mu\u00f1oz Antonio",
    "wof:placetype":"venue"
},
  "geometry": {"coordinates":[2.1120004654,41.3682479858],"type":"Point"}
}