{
  "type": "Feature",
  "properties": {
    "addr:full":"Maria Zambrano, 2 Manilva M\u00e1laga 29692",
    "addr:housenumber":"2",
    "addr:postcode":"29692",
    "iso:country":"ES",
    "sg:address":"Maria Zambrano, 2",
    "sg:city":"Manilva",
    "sg:orig_category":"Molduras, Junquillos, Listones Y Molduras Perforadas",
    "sg:phone":"+34 952 89 00 48",
    "sg:postcode":"29692",
    "sg:province":"M\u00e1laga",
    "wof:name":"Rita Gracia Ileana",
    "wof:placetype":"venue"
},
  "geometry": {"coordinates":[-5.2270689011,36.3641700745],"type":"Point"}
}