{
  "type": "Feature",
  "properties": {
    "addr:full":"Ctra Malaga (de), S/n Granada Granada 18015",
    "addr:housenumber":"/ n",
    "addr:postcode":"18015",
    "addr:street":"Ctra Malaga De S",
    "iso:country":"ES",
    "sg:address":"Ctra Malaga (de), S/n",
    "sg:city":"Granada",
    "sg:orig_category":"Cajas De Ahorro",
    "sg:phone":"+34 958 28 57 70",
    "sg:postcode":"18015",
    "sg:province":"Granada",
    "sg:website":"www.caja-granada.es",
    "wof:name":"Cajagranada",
    "wof:placetype":"venue"
},
  "geometry": {"coordinates":[-3.6263940334,37.189365387],"type":"Point"}
}