{
  "type": "Feature",
  "properties": {
    "addr:full":"Calle de Zapateria, 22 Vitoria-gasteiz \u00c1lava 01001",
    "addr:housenumber":"22",
    "addr:postcode":"01001",
    "addr:street":"Calle De Zapateria",
    "iso:country":"ES",
    "sg:address":"Calle de Zapateria, 22",
    "sg:city":"Vitoria-gasteiz",
    "sg:orig_category":"Droguer\u00cdas (al Por Menor)",
    "sg:phone":"+34 945 25 99 26",
    "sg:postcode":"01001",
    "sg:province":"\u00c1lava",
    "wof:name":"Lasaga Gil Alfredo",
    "wof:placetype":"venue"
},
  "geometry": {"coordinates":[-2.6737880707,42.8475646973],"type":"Point"}
}