{
  "type": "Feature",
  "properties": {
    "iso:country":"ES",
    "sg:address":"Pase Berabera De, 4",
    "sg:city":"Donostia-san Sebastian",
    "sg:orig_category":"Promotores Constructores",
    "sg:phone":"+34 943 31 39 15",
    "sg:postcode":"20009",
    "sg:province":"Guip\u00f9zcoa",
    "wof:name":"Aranegi Zubiaurre Gorka",
    "wof:placetype":"venue"
},
  "geometry": {"coordinates":[-1.9916290045,43.3014945984],"type":"Point"}
}