{
  "type": "Feature",
  "properties": {
    "addr:full":"Mutilva Baja, 32 Iru\u00f1a Navarra 31006",
    "addr:housenumber":"32",
    "addr:postcode":"31006",
    "addr:street":"Mutilva Baja",
    "iso:country":"ES",
    "sg:address":"Mutilva Baja, 32",
    "sg:city":"Iru\u00f1a",
    "sg:orig_category":"Promotores Constructores",
    "sg:phone":"+34 948 15 37 87",
    "sg:postcode":"31006",
    "sg:province":"Navarra",
    "wof:name":"Iruek S.l.",
    "wof:placetype":"venue"
},
  "geometry": {"coordinates":[-1.6328109503,42.8053359985],"type":"Point"}
}