{
  "type": "Feature",
  "properties": {
    "addr:full":"Nafarroa Etorbidea, 4 Arrasate Guip\u00f9zcoa 20500",
    "addr:housenumber":"4",
    "addr:postcode":"20500",
    "addr:street":"Nafarroa Etorbidea;Guipu\u0300Zcoa",
    "iso:country":"ES",
    "sg:address":"Nafarroa Etorbidea, 4",
    "sg:city":"Arrasate",
    "sg:orig_category":"Ense\u00d1anza, Formaci\u00d3n Profesional: Aprendizaje",
    "sg:phone":"+34 943 79 71 45",
    "sg:postcode":"20500",
    "sg:province":"Guip\u00f9zcoa",
    "wof:name":"Servicio Publico De Empleo Estatal",
    "wof:placetype":"venue"
},
  "geometry": {"coordinates":[-2.485033989,43.063873291],"type":"Point"}
}