{
  "type": "Feature",
  "properties": {
    "addr:full":"Jos\u00e9 Luis Laguillo, 23 Villanueva Pe\u00f1a Cantabria 39509",
    "addr:housenumber":"23",
    "addr:postcode":"39509",
    "addr:street":"Laguillo",
    "iso:country":"ES",
    "sg:address":"Jos\u00e9 Luis Laguillo, 23",
    "sg:city":"Villanueva Pe\u00f1a",
    "sg:orig_category":"Cajas De Ahorro",
    "sg:phone":"+34 942 70 86 76",
    "sg:postcode":"39509",
    "sg:province":"Cantabria",
    "sg:website":"www.cajacantabria.es",
    "wof:name":"Cableuropa",
    "wof:placetype":"venue"
},
  "geometry": {"coordinates":[-4.2100739479,43.2973518372],"type":"Point"}
}