{
  "type": "Feature",
  "properties": {
    "addr:full":"Ptge Marco Polo, 4 Sabadell Barcelona 08208",
    "addr:housenumber":"4",
    "addr:postcode":"08208",
    "addr:street":"Ptge Marco Polo",
    "iso:country":"ES",
    "sg:address":"Ptge Marco Polo, 4",
    "sg:city":"Sabadell",
    "sg:orig_category":"Promotores Constructores",
    "sg:phone":"+34 937 24 31 04",
    "sg:postcode":"08208",
    "sg:province":"Barcelona",
    "wof:name":"Khan  Sanaullah",
    "wof:placetype":"venue"
},
  "geometry": {"coordinates":[2.1345500946,41.5642738342],"type":"Point"}
}