{
  "type": "Feature",
  "properties": {
    "addr:full":"Carrer de Diputacio, 11 S. Celoni Barcelona 08470",
    "addr:housenumber":"11",
    "addr:postcode":"08470",
    "addr:street":"Carrer De Diputacio;S. Celoni Barcelona",
    "iso:country":"ES",
    "sg:address":"Carrer de Diputacio, 11",
    "sg:city":"S. Celoni",
    "sg:orig_category":"Servidores Y Editores De Bases De Datos",
    "sg:phone":"+34 938 67 23 23",
    "sg:postcode":"08470",
    "sg:province":"Barcelona",
    "wof:name":"Arroba Creations S.l",
    "wof:placetype":"venue"
},
  "geometry": {"coordinates":[2.4866085052,41.6909675598],"type":"Point"}
}