{
  "type": "Feature",
  "properties": {
    "iso:country":"ES",
    "sg:address":"Carrer de Roger De Flor, 122",
    "sg:city":"Barcelona",
    "sg:orig_category":"Fabricaci\u00d3n De Sobres, Bolsas Y Fundas",
    "sg:phone":"+34 932 45 78 88",
    "sg:postcode":"08013",
    "sg:province":"Barcelona",
    "wof:name":"Bolsos Xinglong Si",
    "wof:placetype":"venue"
},
  "geometry": {"coordinates":[2.1773951054,41.3954048157],"type":"Point"}
}