{
  "type": "Feature",
  "properties": {
    "addr:full":"Ctra Manresa, Km. 0002,0 Igualada Barcelona 08700",
    "addr:postcode":"08700",
    "addr:street":"Ctra Manresa Km. 0002,0",
    "iso:country":"ES",
    "sg:address":"Ctra Manresa, Km. 0002,0",
    "sg:city":"Igualada",
    "sg:orig_category":"Agencias Y Asesores De Publicidad",
    "sg:phone":"+34 938 04 22 02",
    "sg:postcode":"08700",
    "sg:province":"Barcelona",
    "wof:name":"Ultramagic S.a.",
    "wof:placetype":"venue"
},
  "geometry": {"coordinates":[1.6128000021,41.5842399597],"type":"Point"}
}