{
  "type": "Feature",
  "properties": {
    "addr:full":"Carrer de Mecanica, 4 Polingons Industrials Santa Rita-agripina Barcelona 08755",
    "addr:housenumber":"4",
    "addr:postcode":"08755",
    "addr:street":"Carrer De Mecanica",
    "iso:country":"ES",
    "sg:address":"Carrer de Mecanica, 4",
    "sg:city":"Polingons Industrials Santa Rita-agripina",
    "sg:orig_category":"Carnes De Carnicer\u00cda (al Por Mayor)",
    "sg:phone":"+34 937 72 03 52",
    "sg:postcode":"08755",
    "sg:province":"Barcelona",
    "wof:name":"Aldercarn",
    "wof:placetype":"venue"
},
  "geometry": {"coordinates":[2.1699187756,41.3879165649],"type":"Point"}
}