{
  "type": "Feature",
  "properties": {
    "addr:full":"Ctra Murcia (de), 57 Caravaca Cruz Murcia 30400",
    "addr:housenumber":"57",
    "addr:postcode":"30400",
    "addr:street":"Ctra Murcia De",
    "iso:country":"ES",
    "sg:address":"Ctra Murcia (de), 57",
    "sg:city":"Caravaca Cruz",
    "sg:orig_category":"Producci\u00d3n, Distribuci\u00d3n De Gas Butano Y Propano",
    "sg:phone":"+34 968 70 36 70",
    "sg:postcode":"30400",
    "sg:province":"Murcia",
    "wof:name":"Bualgas S.a.",
    "wof:placetype":"venue"
},
  "geometry": {"coordinates":[-1.8493139744,38.1046409607],"type":"Point"}
}