{
  "type": "Feature",
  "properties": {
    "addr:full":"Pase Castellanos, 48 Madrid Madrid 28025",
    "addr:housenumber":"48",
    "addr:postcode":"madrid;28025",
    "iso:country":"ES",
    "sg:address":"Pase Castellanos, 48",
    "sg:city":"Madrid",
    "sg:orig_category":"Tapicer\u00cdas",
    "sg:phone":"+34 914 61 00 35",
    "sg:postcode":"28025",
    "sg:province":"Madrid",
    "wof:name":"Ocampos Dominguez Luis",
    "wof:placetype":"venue"
},
  "geometry": {"coordinates":[-3.7435541153,40.3746490479],"type":"Point"}
}