{
  "type": "Feature",
  "properties": {
    "addr:full":"Carr Doctor Segarra, 17 Borges Blanques Lleida 25400",
    "addr:housenumber":"17",
    "addr:postcode":"25400",
    "addr:street":"Carr Doctor Segarra",
    "iso:country":"ES",
    "sg:address":"Carr Doctor Segarra, 17",
    "sg:city":"Borges Blanques",
    "sg:orig_category":"Empresarios",
    "sg:phone":"+34 973 14 23 24",
    "sg:postcode":"25400",
    "sg:province":"Lleida",
    "wof:name":"Quintana Peiro Jose",
    "wof:placetype":"venue"
},
  "geometry": {"coordinates":[0.8636100292,41.5230865479],"type":"Point"}
}