{
  "type": "Feature",
  "properties": {
    "addr:full":"Calle de Tortolas, 14 Malaga M\u00e1laga 29190",
    "addr:housenumber":"14",
    "addr:postcode":"29190",
    "addr:street":"Calle De Tortolas;Ma\u0301Laga",
    "iso:country":"ES",
    "sg:address":"Calle de Tortolas, 14",
    "sg:city":"Malaga",
    "sg:orig_category":"Mec\u00c1nico Del Autom\u00d3vil",
    "sg:phone":"+34 952 10 04 75",
    "sg:postcode":"29190",
    "sg:province":"M\u00e1laga",
    "wof:name":"Cobos Brenes Diego Jesus",
    "wof:placetype":"venue"
},
  "geometry": {"coordinates":[-4.4797310829,36.7335968018],"type":"Point"}
}