{
  "type": "Feature",
  "properties": {
    "iso:country":"ES",
    "sg:address":"La Pisa, S/n",
    "sg:city":"Canicosa De La Sierra",
    "sg:orig_category":"Centros De Educaci\u00d3n Especial",
    "sg:phone":"+34 947 39 15 42",
    "sg:postcode":"09692",
    "sg:province":"Burgos",
    "wof:name":"Colegio Rural Agrupado Sierra De Pinares",
    "wof:placetype":"venue"
},
  "geometry": {"coordinates":[-3.0397400856,41.9356231689],"type":"Point"}
}