{
  "type": "Feature",
  "properties": {
    "addr:full":"Calle de Libertad (de La), 7 Alcobendas Madrid 28100",
    "addr:postcode":"28100",
    "addr:street":"Calle De Libertad De La 7",
    "iso:country":"ES",
    "sg:address":"Calle de Libertad (de La), 7",
    "sg:city":"Alcobendas",
    "sg:orig_category":"Promotores Constructores",
    "sg:phone":"+34 916 54 28 43",
    "sg:postcode":"28100",
    "sg:province":"Madrid",
    "wof:name":"Desarrollos Doble Al S.a.",
    "wof:placetype":"venue"
},
  "geometry": {"coordinates":[-3.633893013,40.5407371521],"type":"Point"}
}