{
  "type": "Feature",
  "properties": {
    "iso:country":"ES",
    "sg:address":"Avda Nuestra Se\u00d1ora Del Sagrado Corazon, 26",
    "sg:city":"Jerez De La Frontera",
    "sg:orig_category":"Escuelas Primarias P\u00dablicas",
    "sg:phone":"+34 956 31 10 03",
    "sg:postcode":"11407",
    "sg:province":"C\u00e1diz",
    "wof:name":"Colegio Virgen De Perpetuo Socorro Hijas De Ntra Sra Del Sagrado Corazon Prov Espana",
    "wof:placetype":"venue"
},
  "geometry": {"coordinates":[-6.1353092194,36.7065887451],"type":"Point"}
}