{
  "type": "Feature",
  "properties": {
    "iso:country":"ES",
    "sg:address":"Carrer de Alcolea, 36",
    "sg:city":"Barcelona",
    "sg:orig_category":"Venta, Instalaci\u00d3n De Calefacci\u00d3n",
    "sg:phone":"+34 935 11 25 95",
    "sg:postcode":"08014",
    "sg:province":"Barcelona",
    "wof:name":"Angel Lahoz Sesma",
    "wof:placetype":"venue"
},
  "geometry": {"coordinates":[2.136485815,41.3767242432],"type":"Point"}
}