{
  "type": "Feature",
  "properties": {
    "iso:country":"ES",
    "sg:address":"Carrer de Batllori, 24",
    "sg:city":"Barcelona",
    "sg:orig_category":"Molduras, Junquillos, Listones Y Molduras Perforadas",
    "sg:phone":"+34 933 53 48 59",
    "sg:postcode":"08042",
    "sg:province":"Barcelona",
    "wof:name":"Chumping  Hu",
    "wof:placetype":"venue"
},
  "geometry": {"coordinates":[2.1774330139,41.4438552856],"type":"Point"}
}