{
  "type": "Feature",
  "properties": {
    "iso:country":"ES",
    "sg:address":"Calle de Santander, 3",
    "sg:city":"Alcorcon",
    "sg:orig_category":"Mec\u00c1nico Del Autom\u00d3vil",
    "sg:phone":"+34 916 43 36 25",
    "sg:postcode":"28922",
    "sg:province":"Madrid",
    "wof:name":"Diaz Diaz Isidro",
    "wof:placetype":"venue"
},
  "geometry": {"coordinates":[-3.8304269314,40.3441543579],"type":"Point"}
}