{
  "type": "Feature",
  "properties": {
    "addr:full":"Calle de Madera (de La), 24 Partija-santa Monica Madrid 28529",
    "addr:housenumber":"24",
    "addr:postcode":"28529",
    "addr:street":"Calle De Madera De La",
    "iso:country":"ES",
    "sg:address":"Calle de Madera (de La), 24",
    "sg:city":"Partija-santa Monica",
    "sg:orig_category":"Inform\u00c1tica (estudios, Servicios, Asesor\u00cda, Formaci\u00d3n)",
    "sg:phone":"+34 916 70 23 60",
    "sg:postcode":"28529",
    "sg:province":"Madrid",
    "wof:name":"Aincab S.l.",
    "wof:placetype":"venue"
},
  "geometry": {"coordinates":[-3.7003455162,40.4166908264],"type":"Point"}
}