{
  "type": "Feature",
  "properties": {
    "addr:full":"Calle de Gorbeia, 5 Bilbao Vizcaya 48014",
    "addr:housenumber":"5",
    "addr:postcode":"48014",
    "addr:street":"Calle De Gorbeia",
    "iso:country":"ES",
    "sg:address":"Calle de Gorbeia, 5",
    "sg:city":"Bilbao",
    "sg:orig_category":"Prendas De Cuero Y De Piel (al Por Menor)",
    "sg:phone":"+34 944 47 69 60",
    "sg:postcode":"48014",
    "sg:province":"Vizcaya",
    "wof:name":"Vazquez Garcia Saladina",
    "wof:placetype":"venue"
},
  "geometry": {"coordinates":[-2.9458274841,43.2752685547],"type":"Point"}
}