{
  "type": "Feature",
  "properties": {
    "iso:country":"ES",
    "sg:address":"Calle de Marquesas, 6",
    "sg:city":"Torrejon Ardoz",
    "sg:orig_category":"Carnicer\u00cdas, Carnicer\u00cdas",
    "sg:phone":"+34 916 74 96 21",
    "sg:postcode":"28850",
    "sg:province":"Madrid",
    "wof:name":"Sanchez Romero Felix",
    "wof:placetype":"venue"
},
  "geometry": {"coordinates":[-3.4810109138,40.4589881897],"type":"Point"}
}