{
  "type": "Feature",
  "properties": {
    "addr:full":"Calle de Carrera La, 39 Ojen M\u00e1laga 29610",
    "addr:housenumber":"39",
    "addr:postcode":"29610",
    "addr:street":"Calle De Carrera La;Ma\u0301Laga",
    "iso:country":"ES",
    "sg:address":"Calle de Carrera La, 39",
    "sg:city":"Ojen",
    "sg:orig_category":"Productores Recolectores, Venta Directa De Vinos",
    "sg:phone":"+34 952 88 14 53",
    "sg:postcode":"29610",
    "sg:province":"M\u00e1laga",
    "wof:name":"Tienda Museo Del Vino S.l.",
    "wof:placetype":"venue"
},
  "geometry": {"coordinates":[-4.8543190956,36.5646591187],"type":"Point"}
}