{
  "type": "Feature",
  "properties": {
    "iso:country":"ES",
    "sg:address":"Pl Mossen Jacint Verdaguer, 12",
    "sg:city":"Terrassa",
    "sg:orig_category":"Inmobiliaria (agencias)",
    "sg:phone":"+34 937 31 68 26",
    "sg:postcode":"08221",
    "sg:province":"Barcelona",
    "wof:name":"Edifci Olimpic Sl",
    "wof:placetype":"venue"
},
  "geometry": {"coordinates":[2.0133500099,41.5665931702],"type":"Point"}
}