{
  "type": "Feature",
  "properties": {
    "addr:full":"Avda Camara De La Industria, 9 Mostoles Madrid 28938",
    "addr:housenumber":"9",
    "addr:postcode":"28938",
    "addr:street":"Avda Camara;La Industria",
    "iso:country":"ES",
    "sg:address":"Avda Camara De La Industria, 9",
    "sg:city":"Mostoles",
    "sg:orig_category":"Electricidad: Equipos Industriales, Componentes (fabricaci\u00d3n)",
    "sg:phone":"+34 916 45 63 59",
    "sg:postcode":"28938",
    "sg:province":"Madrid",
    "sg:website":"www.gepowercontrols.com",
    "wof:name":"Power Controls Iberica S.l.",
    "wof:placetype":"venue"
},
  "geometry": {"coordinates":[-3.8720560074,40.3130683899],"type":"Point"}
}