{
  "type": "Feature",
  "properties": {
    "iso:country":"ES",
    "sg:address":"Avda Salvador Allende, 42",
    "sg:city":"Zaragoza",
    "sg:orig_category":"Par\u00cds",
    "sg:phone":"+34 976 51 01 96",
    "sg:postcode":"50015",
    "sg:province":"Zaragoza",
    "wof:name":"Iba\u00f1ez Alcolea Maria Dolores",
    "wof:placetype":"venue"
},
  "geometry": {"coordinates":[-0.8767499924,41.6723709106],"type":"Point"}
}