{
  "type": "Feature",
  "properties": {
    "iso:country":"ES",
    "sg:address":"Calle de Soria, 1",
    "sg:city":"Fuenlabrada",
    "sg:orig_category":"Droguer\u00cdas (al Por Menor)",
    "sg:phone":"+34 916 06 56 46",
    "sg:postcode":"28941",
    "sg:province":"Madrid",
    "wof:name":"Sobrino Vaquerizo Juan Carlos",
    "wof:placetype":"venue"
},
  "geometry": {"coordinates":[-3.80301404,40.2926330566],"type":"Point"}
}