{
  "type": "Feature",
  "properties": {
    "iso:country":"ES",
    "sg:address":"Calle de San Pablo, 39",
    "sg:city":"Burgos",
    "sg:orig_category":"Caf\u00c9s, Bares, Cervecer\u00cdas",
    "sg:phone":"+34 947 20 74 42",
    "sg:postcode":"09002",
    "sg:province":"Burgos",
    "wof:name":"Garcia Frias Angel",
    "wof:placetype":"venue"
},
  "geometry": {"coordinates":[-3.6997859478,42.3362960815],"type":"Point"}
}