{
  "type": "Feature",
  "properties": {
    "addr:full":"Carrer de Roig, 22 Barcelona Barcelona 08001",
    "addr:housenumber":"22",
    "addr:postcode":"08001",
    "addr:street":"Carrer De Roig",
    "iso:country":"ES",
    "sg:address":"Carrer de Roig, 22",
    "sg:city":"Barcelona",
    "sg:orig_category":"Carnicer\u00cdas, Carnicer\u00cdas",
    "sg:phone":"+34 934 42 67 34",
    "sg:postcode":"08001",
    "sg:province":"Barcelona",
    "wof:name":"Bertran Tor Jose",
    "wof:placetype":"venue"
},
  "geometry": {"coordinates":[2.1689081192,41.3806533813],"type":"Point"}
}