{
  "type": "Feature",
  "properties": {
    "iso:country":"ES",
    "sg:address":"La Calzada, 15",
    "sg:city":"Las Quintanillas",
    "sg:orig_category":"Asociaciones Ecologistas",
    "sg:phone":"+34 947 45 02 83",
    "sg:postcode":"09594",
    "sg:province":"Burgos",
    "wof:name":"Gestion Y Estudios Ambientales Sdad.coop.lda.",
    "wof:placetype":"venue"
},
  "geometry": {"coordinates":[-3.418637991,42.9055976868],"type":"Point"}
}