{
  "type": "Feature",
  "properties": {
    "addr:full":"Calle de Santa Rosalia, 55 Santa Cruz De Tenerife Santa Cruz De Tenerife 38002",
    "addr:housenumber":"55",
    "addr:postcode":"38002",
    "addr:street":"Calle De Santa Rosalia",
    "iso:country":"ES",
    "sg:address":"Calle de Santa Rosalia, 55",
    "sg:city":"Santa Cruz De Tenerife",
    "sg:orig_category":"Estancos",
    "sg:phone":"+34 922 27 18 53",
    "sg:postcode":"38002",
    "sg:province":"Santa Cruz De Tenerife",
    "wof:name":"Santos Duran Jesus Alberto",
    "wof:placetype":"venue"
},
  "geometry": {"coordinates":[-16.2512722015,28.4706802368],"type":"Point"}
}