{
  "type": "Feature",
  "properties": {
    "addr:full":"Poli Industrial Casals, S/n Xeresa Valencia 46790",
    "addr:housenumber":"s",
    "addr:postcode":"46790",
    "addr:street":"/ N",
    "iso:country":"ES",
    "sg:address":"Poli Industrial Casals, S/n",
    "sg:city":"Xeresa",
    "sg:orig_category":"Arboricultura Y Producci\u00d3n De Frutas",
    "sg:phone":"+34 962 89 52 52",
    "sg:postcode":"46790",
    "sg:province":"Valencia",
    "wof:name":"Solsafor Sat Num 9976",
    "wof:placetype":"venue"
},
  "geometry": {"coordinates":[-0.2175740004,39.0116996765],"type":"Point"}
}