{
  "type": "Feature",
  "properties": {
    "addr:full":"Carrer de Independencia, 242 Barcelona Barcelona 08026",
    "addr:housenumber":"242",
    "addr:postcode":"08026",
    "addr:street":"Carrer De Independencia",
    "iso:country":"ES",
    "sg:address":"Carrer de Independencia, 242",
    "sg:city":"Barcelona",
    "sg:orig_category":"Papeler\u00cdas, Librer\u00cdas",
    "sg:phone":"+34 932 31 75 08",
    "sg:postcode":"08026",
    "sg:province":"Barcelona",
    "wof:name":"Morales Lopez Jaime",
    "wof:placetype":"venue"
},
  "geometry": {"coordinates":[2.1852340698,41.4065933228],"type":"Point"}
}