{
  "type": "Feature",
  "properties": {
    "iso:country":"ES",
    "sg:address":"Calle de Portal De Zurbano, 15",
    "sg:city":"Vitoria-gasteiz",
    "sg:orig_category":"Negocio De Madera",
    "sg:phone":"+34 945 12 11 32",
    "sg:postcode":"01013",
    "sg:province":"\u00c1lava",
    "sg:website":"www.echemaderas.com",
    "wof:name":"Echemaderas S.l.",
    "wof:placetype":"venue"
},
  "geometry": {"coordinates":[-2.6498539448,42.8642807007],"type":"Point"}
}