{
  "type": "Feature",
  "properties": {
    "addr:full":"Rond Barcelona, 5 Figueres Girona 17600",
    "addr:postcode":"17600",
    "iso:country":"ES",
    "sg:address":"Rond Barcelona, 5",
    "sg:city":"Figueres",
    "sg:orig_category":"Cajas De Ahorro",
    "sg:phone":"+34 972 51 10 65",
    "sg:postcode":"17600",
    "sg:province":"Girona",
    "sg:website":"www.lacaixa.es",
    "wof:name":"Caixa D'estalvis I Pensions De Barcelona",
    "wof:placetype":"venue"
},
  "geometry": {"coordinates":[2.9586150646,42.2624206543],"type":"Point"}
}