{
  "type": "Feature",
  "properties": {
    "iso:country":"ES",
    "sg:address":"A Igrexa, S/n",
    "sg:city":"Breto\u00f1a",
    "sg:orig_category":"Cooperativas Agr\u00cdcolas",
    "sg:phone":"+34 982 34 90 00",
    "sg:postcode":"27286",
    "sg:province":"Lugo",
    "wof:name":"Agro-xulnasl",
    "wof:placetype":"venue"
},
  "geometry": {"coordinates":[-7.5558514595,43.0120849609],"type":"Point"}
}