{
  "type": "Feature",
  "properties": {
    "iso:country":"ES",
    "sg:address":"Calle de Nardos (los), 2",
    "sg:city":"Alcorcon",
    "sg:orig_category":"Venta, Alquiler De Grupos Electr\u00d3genos",
    "sg:phone":"+34 916 42 67 97",
    "sg:postcode":"28925",
    "sg:province":"Madrid",
    "wof:name":"Generacion Y Proyectos S.l.",
    "wof:placetype":"venue"
},
  "geometry": {"coordinates":[-3.8071539402,40.3569946289],"type":"Point"}
}