{
  "type": "Feature",
  "properties": {
    "iso:country":"ES",
    "sg:address":"Pla\u00c7 Carme, 16",
    "sg:city":"Mao",
    "sg:orig_category":"Alcoholes Y Aguardientes (fabricaci\u00d3n, Al Por Mayor)",
    "sg:phone":"+34 971 36 26 11",
    "sg:postcode":"07702",
    "sg:province":"Islas Baleares",
    "wof:name":"Miguel Pons Justo S.a.",
    "wof:placetype":"venue"
},
  "geometry": {"coordinates":[4.265625,39.8903694153],"type":"Point"}
}