{
  "type": "Feature",
  "properties": {
    "addr:full":"Tras Marmolejos, 54 Marmolejos Las Palmas 35460",
    "addr:housenumber":"54",
    "addr:postcode":"35460",
    "addr:street":"Marmolejos;Palmas",
    "iso:country":"ES",
    "sg:address":"Tras Marmolejos, 54",
    "sg:city":"Marmolejos",
    "sg:orig_category":"Comercio De Hierro",
    "sg:phone":"+34 928 88 01 91",
    "sg:postcode":"35460",
    "sg:province":"Las Palmas",
    "wof:name":"Gonzalez Mendoza Francisco",
    "wof:placetype":"venue"
},
  "geometry": {"coordinates":[-15.6574954987,28.1366043091],"type":"Point"}
}