{
  "type": "Feature",
  "properties": {
    "addr:full":"Calle de Jaen, 5 Pozo Alcon Ja\u00e9n 23485",
    "addr:housenumber":"5",
    "addr:postcode":"23485",
    "addr:street":"Calle De Jaen;Alcon Jae\u0301N",
    "iso:country":"ES",
    "sg:address":"Calle de Jaen, 5",
    "sg:city":"Pozo Alcon",
    "sg:orig_category":"Panader\u00cdas, Panader\u00cdas",
    "sg:phone":"+34 953 71 83 09",
    "sg:postcode":"23485",
    "sg:province":"Ja\u00e9n",
    "wof:name":"Gomez Arredondo Agustin",
    "wof:placetype":"venue"
},
  "geometry": {"coordinates":[-2.9349598885,37.70362854],"type":"Point"}
}