{
  "type": "Feature",
  "properties": {
    "iso:country":"ES",
    "sg:address":"Gandara, 11",
    "sg:city":"Gandara",
    "sg:orig_category":"Agentes, Concesionarios Y Sucursales De Veh\u00cdculos",
    "sg:phone":"+34 986 62 02 88",
    "sg:postcode":"36750",
    "sg:province":"Pontevedra",
    "wof:name":"Automarca Center S.l.",
    "wof:placetype":"venue"
},
  "geometry": {"coordinates":[-8.7837343216,41.951499939],"type":"Point"}
}