{
  "type": "Feature",
  "properties": {
    "iso:country":"ES",
    "sg:address":"Ctra Sur, S/n",
    "sg:city":"S. Agustin-playa Ingles",
    "sg:orig_category":"Suministros Para Hoteles",
    "sg:phone":"+34 928 76 59 79",
    "sg:postcode":"35100",
    "sg:province":"Las Palmas",
    "wof:name":"Surace S.l.",
    "wof:placetype":"venue"
},
  "geometry": {"coordinates":[-15.4397096634,28.1302204132],"type":"Point"}
}