{
  "type": "Feature",
  "properties": {
    "addr:full":"Calle de Diaz De Haro Maria, 33 Bilbao Vizcaya 48010",
    "addr:housenumber":"33",
    "addr:postcode":"48010",
    "addr:street":"Calle De Diaz De Haro Maria",
    "iso:country":"ES",
    "sg:address":"Calle de Diaz De Haro Maria, 33",
    "sg:city":"Bilbao",
    "sg:orig_category":"Sociedades, Compa\u00d1\u00cdas Aseguradoras",
    "sg:phone":"+34 944 39 50 42",
    "sg:postcode":"48010",
    "sg:province":"Vizcaya",
    "wof:name":"Banco Vitalicio De Espa\u00f1a",
    "wof:placetype":"venue"
},
  "geometry": {"coordinates":[-2.944644928,43.260269165],"type":"Point"}
}