{
  "type": "Feature",
  "properties": {
    "addr:full":"Calle de Tres Cruces, S/n Malaga M\u00e1laga 29003",
    "addr:housenumber":"s",
    "addr:postcode":"29003",
    "addr:street":"Calle De Tres Cruces;/ N;Ma\u0301Laga",
    "iso:country":"ES",
    "sg:address":"Calle de Tres Cruces, S/n",
    "sg:city":"Malaga",
    "sg:orig_category":"Ense\u00d1anza, Formaci\u00d3n Profesional: Aprendizaje",
    "sg:phone":"+34 952 32 09 64",
    "sg:postcode":"29003",
    "sg:province":"M\u00e1laga",
    "wof:name":"Junta De Andalucia-consejeria De Cultura",
    "wof:placetype":"venue"
},
  "geometry": {"coordinates":[-4.4511141777,36.7017860413],"type":"Point"}
}