{
  "type": "Feature",
  "properties": {
    "iso:country":"ES",
    "sg:address":"Calle de Henriquez De Jorquera, 11",
    "sg:city":"Granada",
    "sg:orig_category":"Farmacias",
    "sg:phone":"+34 958 15 26 08",
    "sg:postcode":"18011",
    "sg:province":"Granada",
    "wof:name":"Serrano Pe\u00f1uela Marina",
    "wof:placetype":"venue"
},
  "geometry": {"coordinates":[-3.6002929211,37.2015838623],"type":"Point"}
}