{
  "type": "Feature",
  "properties": {
    "addr:full":"O Alcouce, 34 Alcouce Pontevedra 36140",
    "addr:housenumber":"34",
    "addr:postcode":"36140",
    "addr:street":"Alcouce",
    "iso:country":"ES",
    "sg:address":"O Alcouce, 34",
    "sg:city":"Alcouce",
    "sg:orig_category":"Pintura, Barniz, Productos Asimilables (fabricaci\u00d3n, Al Por Mayor)",
    "sg:phone":"+34 986 70 80 94",
    "sg:postcode":"36140",
    "sg:province":"Pontevedra",
    "wof:name":"Construcciones Perez Abilleira S.l.",
    "wof:placetype":"venue"
},
  "geometry": {"coordinates":[-8.6514892578,42.3227615356],"type":"Point"}
}