{
  "type": "Feature",
  "properties": {
    "addr:full":"Pase Tilos Los, 65 Malaga M\u00e1laga 29006",
    "addr:postcode":"29006",
    "addr:street":"Ma\u0301Laga",
    "iso:country":"ES",
    "sg:address":"Pase Tilos Los, 65",
    "sg:city":"Malaga",
    "sg:orig_category":"Flores Y Plantas Naturales (al Por Mayor)",
    "sg:phone":"+34 952 34 13 98",
    "sg:postcode":"29006",
    "sg:province":"M\u00e1laga",
    "wof:name":"Medina Ortega Rafael",
    "wof:placetype":"venue"
},
  "geometry": {"coordinates":[-4.4980049133,36.7106819153],"type":"Point"}
}