{
  "type": "Feature",
  "properties": {
    "iso:country":"ES",
    "sg:address":"Calle de Landabe, 14",
    "sg:city":"Moreaga",
    "sg:orig_category":"Centros De Coordinaci\u00d3n",
    "sg:phone":"+34 946 76 19 16",
    "sg:postcode":"48600",
    "sg:province":"Vizcaya",
    "wof:name":"Rincon Gutierrez Maria Pilar",
    "wof:placetype":"venue"
},
  "geometry": {"coordinates":[-2.9807760715,43.3799667358],"type":"Point"}
}