{
  "type": "Feature",
  "properties": {
    "iso:country":"ES",
    "sg:address":"Av Pi I Margall, 128",
    "sg:city":"Caldes Montbui",
    "sg:orig_category":"Albergues",
    "sg:phone":"+34 938 65 15 18",
    "sg:postcode":"08140",
    "sg:province":"Barcelona",
    "wof:name":"Stil Regal S.l.",
    "wof:placetype":"venue"
},
  "geometry": {"coordinates":[2.1677401066,41.6276817322],"type":"Point"}
}