{
  "type": "Feature",
  "properties": {
    "addr:full":"Pase Santa Maria De La Cabeza, 39 Madrid Madrid 28045",
    "addr:housenumber":"39",
    "addr:postcode":"madrid;28045",
    "addr:street":"Cabeza",
    "iso:country":"ES",
    "sg:address":"Pase Santa Maria De La Cabeza, 39",
    "sg:city":"Madrid",
    "sg:orig_category":"Art\u00cdculos De Decoraci\u00d3n",
    "sg:phone":"+34 914 67 74 00",
    "sg:postcode":"28045",
    "sg:province":"Madrid",
    "wof:name":"Aguerri Zayas Javier",
    "wof:placetype":"venue"
},
  "geometry": {"coordinates":[-3.6902165413,40.3954772949],"type":"Point"}
}