{
  "type": "Feature",
  "properties": {
    "addr:full":"Calle de Dos Hermanas, 8 Madrid Madrid 28012",
    "addr:housenumber":"8",
    "addr:postcode":"madrid;28012",
    "addr:street":"Calle De Dos Hermanas",
    "iso:country":"ES",
    "sg:address":"Calle de Dos Hermanas, 8",
    "sg:city":"Madrid",
    "sg:orig_category":"Bazares, Art\u00cdculos De Limpieza Y De Cocina (al Por Menor)",
    "sg:phone":"+34 914 68 79 36",
    "sg:postcode":"28012",
    "sg:province":"Madrid",
    "wof:name":"Ren  Shunyin",
    "wof:placetype":"venue"
},
  "geometry": {"coordinates":[-3.7052276134,40.4105224609],"type":"Point"}
}