{
  "type": "Feature",
  "properties": {
    "iso:country":"ES",
    "sg:address":"Avda Aeroporto, 565",
    "sg:city":"Vigo",
    "sg:orig_category":"Cintas Transportadoras",
    "sg:phone":"+34 986 48 68 85",
    "sg:postcode":"36318",
    "sg:province":"Pontevedra",
    "wof:name":"Suministro Y Mantenimiento Suyman S.l.",
    "wof:placetype":"venue"
},
  "geometry": {"coordinates":[-8.6429719925,42.2334251404],"type":"Point"}
}