{
  "type": "Feature",
  "properties": {
    "iso:country":"ES",
    "sg:address":"Carrer de Rubio I Ors, 4",
    "sg:city":"Cornella Llobregat",
    "sg:orig_category":"Ebanister\u00cda",
    "sg:phone":"+34 933 77 63 18",
    "sg:postcode":"08940",
    "sg:province":"Barcelona",
    "wof:name":"Montadecor S.c.p.",
    "wof:placetype":"venue"
},
  "geometry": {"coordinates":[2.0663459301,41.3560371399],"type":"Point"}
}