{
  "type": "Feature",
  "properties": {
    "addr:full":"Carrer de Jaume Casanovas, 132 Prat Llobregat Barcelona 08820",
    "addr:housenumber":"132",
    "addr:postcode":"08820",
    "addr:street":"Carrer De Jaume Casanovas;Llobregat",
    "iso:country":"ES",
    "sg:address":"Carrer de Jaume Casanovas, 132",
    "sg:city":"Prat Llobregat",
    "sg:orig_category":"Peluquer\u00cdas, Peluquer\u00cda Mixta",
    "sg:phone":"+34 933 79 65 78",
    "sg:postcode":"08820",
    "sg:province":"Barcelona",
    "wof:name":"Marin Yelamos Maria Del Mar",
    "wof:placetype":"venue"
},
  "geometry": {"coordinates":[2.0929191113,41.3253898621],"type":"Point"}
}