{
  "type": "Feature",
  "properties": {
    "iso:country":"ES",
    "sg:address":"Calle de Chorron, 38",
    "sg:city":"Guadalajara",
    "sg:orig_category":"Delegados, Agentes De Tr\u00c1nsito, Auxiliares De Transporte Internacional",
    "sg:phone":"+34 949 22 90 70",
    "sg:postcode":"19005",
    "sg:province":"Guadalajara",
    "wof:name":"Sanz Rojo Angel",
    "wof:placetype":"venue"
},
  "geometry": {"coordinates":[-3.1593999863,40.6305656433],"type":"Point"}
}