{
  "type": "Feature",
  "properties": {
    "addr:full":"Calle de Ignacio Santos Vi\u00d1uelas, 22 Madrid Madrid 28021",
    "addr:housenumber":"22",
    "addr:postcode":"madrid;28021",
    "addr:street":"Calle De Ignacio Santos Vin\u0303Uelas",
    "iso:country":"ES",
    "sg:address":"Calle de Ignacio Santos Vi\u00d1uelas, 22",
    "sg:city":"Madrid",
    "sg:orig_category":"Telas Para Tapizar, Cortinas, Pasamaner\u00cda (fabricaci\u00d3n, Al Por Mayor)",
    "sg:phone":"+34 915 05 30 23",
    "sg:postcode":"28021",
    "sg:province":"Madrid",
    "wof:name":"Romera Calabria Misedicordia",
    "wof:placetype":"venue"
},
  "geometry": {"coordinates":[-3.6888010502,40.3493919373],"type":"Point"}
}