{
  "type": "Feature",
  "properties": {
    "iso:country":"ES",
    "sg:address":"Calle de Txalaparta, 3",
    "sg:city":"Vitoria-gasteiz",
    "sg:orig_category":"Cristaler\u00cda Art\u00cdstica, Vidrio Soplado (fabricaci\u00d3n, Al Por Mayor)",
    "sg:phone":"+34 945 13 59 54",
    "sg:postcode":"01006",
    "sg:province":"\u00c1lava",
    "wof:name":"Gonzalez Martinez Luis Miguel",
    "wof:placetype":"venue"
},
  "geometry": {"coordinates":[-2.6648919582,42.8375663757],"type":"Point"}
}