{
  "type": "Feature",
  "properties": {
    "iso:country":"ES",
    "sg:address":"Carrer de Riera, 76",
    "sg:city":"Barriada Nova",
    "sg:orig_category":"Alimentaci\u00d3n General (al Por Menor)",
    "sg:phone":"+34 938 49 52 26",
    "sg:postcode":"08420",
    "sg:province":"Barcelona",
    "wof:name":"Rodriguez Avila Jose",
    "wof:placetype":"venue"
},
  "geometry": {"coordinates":[2.2780098915,41.6220703125],"type":"Point"}
}