{
  "type": "Feature",
  "properties": {
    "iso:country":"ES",
    "sg:address":"Carrer de Doctor Balari, 148",
    "sg:city":"Sabadell",
    "sg:orig_category":"Fabricaci\u00d3n, Distribuci\u00d3n De Material Para La Climatizaci\u00d3n, Aireaci\u00d3n Y Ventilaci\u00d3n",
    "sg:phone":"+34 937 12 21 43",
    "sg:postcode":"08203",
    "sg:province":"Barcelona",
    "sg:website":"www.novatub.com",
    "wof:name":"Novatub S.l.",
    "wof:placetype":"venue"
},
  "geometry": {"coordinates":[2.1075758934,41.5315246582],"type":"Point"}
}