{
  "type": "Feature",
  "properties": {
    "addr:full":"Calle de Maestro Varela, 15 Albacete Albacete 02005",
    "addr:housenumber":"15",
    "addr:postcode":"02005",
    "addr:street":"Calle De Maestro Varela",
    "iso:country":"ES",
    "sg:address":"Calle de Maestro Varela, 15",
    "sg:city":"Albacete",
    "sg:orig_category":"Ense\u00d1anza: Peluquer\u00cda Est\u00c9tica",
    "sg:phone":"+34 967 24 91 37",
    "sg:postcode":"02005",
    "sg:province":"Albacete",
    "wof:name":"Pelurroda S.l.",
    "wof:placetype":"venue"
},
  "geometry": {"coordinates":[-1.8658009768,39.0015525818],"type":"Point"}
}