{
  "type": "Feature",
  "properties": {
    "iso:country":"ES",
    "sg:address":"Calle de Jose Cadalso, 9",
    "sg:city":"Torrejon Ardoz",
    "sg:orig_category":"Peluqueros: De Se\u00d1oras",
    "sg:phone":"+34 916 77 95 03",
    "sg:postcode":"28850",
    "sg:province":"Madrid",
    "wof:name":"Ucesga S.l.",
    "wof:placetype":"venue"
},
  "geometry": {"coordinates":[-3.461468935,40.442741394],"type":"Point"}
}