{
  "type": "Feature",
  "properties": {
    "addr:full":"Rua Lodeiro, 12 Bertamirans A Coru\u00f1a 15220",
    "addr:housenumber":"12",
    "addr:postcode":"15220",
    "addr:street":"Rua Lodeiro;Corun\u0303A",
    "iso:country":"ES",
    "sg:address":"Rua Lodeiro, 12",
    "sg:city":"Bertamirans",
    "sg:orig_category":"Serrer\u00cdas De Madera",
    "sg:phone":"+34 981 88 33 02",
    "sg:postcode":"15220",
    "sg:province":"A Coru\u00f1a",
    "wof:name":"Tojo Blanco Jose",
    "wof:placetype":"venue"
},
  "geometry": {"coordinates":[-8.6493988037,42.8606491089],"type":"Point"}
}