{
  "type": "Feature",
  "properties": {
    "iso:country":"ES",
    "sg:address":"Calle de Emperatriz Eugenia, 5",
    "sg:city":"Granada",
    "sg:orig_category":"Asociaciones, Organismos Culturales Y Socioeducativos",
    "sg:phone":"+34 958 29 14 68",
    "sg:postcode":"18002",
    "sg:province":"Granada",
    "wof:name":"Asociacion De Familias Numerosas De Andalucia Oriental",
    "wof:placetype":"venue"
},
  "geometry": {"coordinates":[-3.6065340042,37.1763267517],"type":"Point"}
}