{
  "type": "Feature",
  "properties": {
    "iso:country":"ES",
    "sg:address":"Av L'hospital Militar, 149",
    "sg:city":"Barcelona",
    "sg:orig_category":"M\u00c9dicos: Gastroenterolog\u00cda Y Hepatolog\u00cda (aparato Digestivo)",
    "sg:phone":"+34 932 11 81 53",
    "sg:postcode":"08023",
    "sg:province":"Barcelona",
    "wof:name":"Marti Sirvent Dolores",
    "wof:placetype":"venue"
},
  "geometry": {"coordinates":[2.1406440735,41.4200019836],"type":"Point"}
}