{
  "type": "Feature",
  "properties": {
    "addr:full":"Av Baile Calbeto Barra, 16 Vielha Lleida 25530",
    "addr:housenumber":"16",
    "addr:postcode":"25530",
    "addr:street":"Av Baile;Barra",
    "iso:country":"ES",
    "sg:address":"Av Baile Calbeto Barra, 16",
    "sg:city":"Vielha",
    "sg:orig_category":"Arquitectos",
    "sg:phone":"+34 973 64 09 11",
    "sg:postcode":"25530",
    "sg:province":"Lleida",
    "wof:name":"Ni\u00f1erola Xucla Juan Antonio",
    "wof:placetype":"venue"
},
  "geometry": {"coordinates":[0.793775022,42.70287323],"type":"Point"}
}