{
  "type": "Feature",
  "properties": {
    "addr:full":"F. La Mojadilla, S/n Torrecilla Angeles C\u00e1ceres 10869",
    "addr:housenumber":"s / n",
    "addr:postcode":"10869",
    "addr:street":"F.",
    "iso:country":"ES",
    "sg:address":"F. La Mojadilla, S/n",
    "sg:city":"Torrecilla Angeles",
    "sg:orig_category":"Hormigonados",
    "sg:phone":"+34 927 67 72 44",
    "sg:postcode":"10869",
    "sg:province":"C\u00e1ceres",
    "wof:name":"Gomez Tello Eusebio",
    "wof:placetype":"venue"
},
  "geometry": {"coordinates":[-6.4124441147,40.2475967407],"type":"Point"}
}