{
  "type": "Feature",
  "properties": {
    "iso:country":"ES",
    "sg:address":"Canet, S/n",
    "sg:city":"Tallada Emporda",
    "sg:orig_category":"Producci\u00d3n, Venta De Productos De Agricultura Biol\u00d3gica",
    "sg:phone":"+34 972 78 03 97",
    "sg:postcode":"17134",
    "sg:province":"Girona",
    "wof:name":"Agroemporda S.l.",
    "wof:placetype":"venue"
},
  "geometry": {"coordinates":[3.0666658878,42.0520133972],"type":"Point"}
}