{
  "type": "Feature",
  "properties": {
    "iso:country":"ES",
    "sg:address":"Calle de Ferrocarril, 30",
    "sg:city":"Talavera Reina",
    "sg:orig_category":"Piedra Natural",
    "sg:phone":"+34 925 80 99 56",
    "sg:postcode":"45600",
    "sg:province":"Toledo",
    "wof:name":"Hijos De Miguel Del Pino C.b",
    "wof:placetype":"venue"
},
  "geometry": {"coordinates":[-4.8262782097,39.9674758911],"type":"Point"}
}