{
  "type": "Feature",
  "properties": {
    "addr:full":"Calle de San Jeronimo, 25 Alaquas Valencia 46970",
    "addr:housenumber":"25",
    "addr:postcode":"46970",
    "addr:street":"Calle De San Jeronimo",
    "iso:country":"ES",
    "sg:address":"Calle de San Jeronimo, 25",
    "sg:city":"Alaquas",
    "sg:orig_category":"Ebanister\u00cda",
    "sg:phone":"+34 961 50 64 63",
    "sg:postcode":"46970",
    "sg:province":"Valencia",
    "wof:name":"Yuste Provencio Argimiro",
    "wof:placetype":"venue"
},
  "geometry": {"coordinates":[-0.4612062871,39.4583015442],"type":"Point"}
}