{
  "type": "Feature",
  "properties": {
    "iso:country":"ES",
    "sg:address":"Avda Espa\u00d1a, 35",
    "sg:city":"Alhama Murcia",
    "sg:orig_category":"Condimentos, Especias, Vinagres, Salsas Preparadas (fabricaci\u00d3n, Al Por Mayor)",
    "sg:phone":"+34 968 63 15 72",
    "sg:postcode":"30840",
    "sg:province":"Murcia",
    "wof:name":"Distribuciones J Gabarron S.l.",
    "wof:placetype":"venue"
},
  "geometry": {"coordinates":[-1.4210230112,37.8502578735],"type":"Point"}
}