{
  "type": "Feature",
  "properties": {
    "addr:full":"Carrer de Tenor Vi\u00d1as, 4 Barcelona Barcelona 08021",
    "addr:housenumber":"4",
    "addr:postcode":"08021",
    "addr:street":"Carrer De Tenor Vin\u0303As",
    "iso:country":"ES",
    "sg:address":"Carrer de Tenor Vi\u00d1as, 4",
    "sg:city":"Barcelona",
    "sg:orig_category":"Ropa Para Se\u00d1oras (al Por Menor)",
    "sg:phone":"+34 932 01 37 49",
    "sg:postcode":"08021",
    "sg:province":"Barcelona",
    "wof:name":"Blanch Quirao Joana",
    "wof:placetype":"venue"
},
  "geometry": {"coordinates":[2.1422150135,41.3944549561],"type":"Point"}
}