{
  "type": "Feature",
  "properties": {
    "addr:full":"Polig. Industrial, S/n Vilalba Lugo 27800",
    "addr:housenumber":"/ n",
    "addr:postcode":"27800",
    "addr:street":"Industrial",
    "iso:country":"ES",
    "sg:address":"Polig. Industrial, S/n",
    "sg:city":"Vilalba",
    "sg:orig_category":"Ense\u00d1anza, Formaci\u00d3n Profesional: Aprendizaje",
    "sg:phone":"+34 982 51 13 03",
    "sg:postcode":"27800",
    "sg:province":"Lugo",
    "wof:name":"Cruz Roja Espa\u00f1ola",
    "wof:placetype":"venue"
},
  "geometry": {"coordinates":[-7.6795740128,43.2989387512],"type":"Point"}
}