{
  "type": "Feature",
  "properties": {
    "iso:country":"ES",
    "sg:address":"Calle de Padre Javier De Valladolid, 5",
    "sg:city":"Le\u00f3n",
    "sg:orig_category":"M\u00c9dicos: Ginecolog\u00cda Y Obstetricia",
    "sg:phone":"+34 987 21 12 33",
    "sg:postcode":"24005",
    "sg:province":"Le\u00f3n",
    "sg:website":"www.paginasamarillas.es",
    "wof:name":"Carriles Sastre Raul",
    "wof:placetype":"venue"
},
  "geometry": {"coordinates":[-5.554669857,42.5806999207],"type":"Point"}
}