{
  "type": "Feature",
  "properties": {
    "addr:full":"Carrer de Bruc, 85 Barcelona Barcelona 08009",
    "addr:housenumber":"85",
    "addr:postcode":"08009",
    "addr:street":"Carrer De Bruc",
    "iso:country":"ES",
    "sg:address":"Carrer de Bruc, 85",
    "sg:city":"Barcelona",
    "sg:orig_category":"Ropa De Hogar (al Por Menor)",
    "sg:phone":"+34 934 57 67 18",
    "sg:postcode":"08009",
    "sg:province":"Barcelona",
    "wof:name":"Peiron Reus Maria Inmaculada",
    "wof:placetype":"venue"
},
  "geometry": {"coordinates":[2.1684401035,41.3950233459],"type":"Point"}
}