{
  "type": "Feature",
  "properties": {
    "iso:country":"ES",
    "sg:address":"Avda Vilar, 1",
    "sg:city":"Vilar",
    "sg:orig_category":"Librer\u00cdas",
    "sg:phone":"+34 986 74 31 12",
    "sg:postcode":"36990",
    "sg:province":"Pontevedra",
    "wof:name":"Agraso Perez Jose Luis",
    "wof:placetype":"venue"
},
  "geometry": {"coordinates":[-8.7134418488,42.4453849792],"type":"Point"}
}