{
  "type": "Feature",
  "properties": {
    "addr:full":"Av Collidors, 11 Pu\u00e7ol Valencia 46530",
    "addr:housenumber":"11",
    "addr:postcode":"46530",
    "addr:street":"Av Collidors",
    "iso:country":"ES",
    "sg:address":"Av Collidors, 11",
    "sg:city":"Pu\u00e7ol",
    "sg:orig_category":"Aguas (distribuci\u00d3n, Servicios)",
    "sg:phone":"+34 961 42 40 73",
    "sg:postcode":"46530",
    "sg:province":"Valencia",
    "sg:website":"www.aguasdecastellon.es",
    "wof:name":"Aguas De Castellon S.l.",
    "wof:placetype":"venue"
},
  "geometry": {"coordinates":[-0.302243799,39.6238937378],"type":"Point"}
}