{
  "type": "Feature",
  "properties": {
    "addr:full":"Calle de Calvario, 1 Aldeaseca \u00c1vila 05214",
    "addr:housenumber":"1",
    "addr:postcode":"05214",
    "addr:street":"Calle De Calvario;A\u0301Vila",
    "iso:country":"ES",
    "sg:address":"Calle de Calvario, 1",
    "sg:city":"Aldeaseca",
    "sg:orig_category":"Carnicer\u00cdas, Carnicer\u00cdas",
    "sg:phone":"+34 920 30 60 14",
    "sg:postcode":"05214",
    "sg:province":"\u00c1vila",
    "wof:name":"Sanz Velazquez Marcelo",
    "wof:placetype":"venue"
},
  "geometry": {"coordinates":[-4.8165631294,41.0483779907],"type":"Point"}
}