{
  "type": "Feature",
  "properties": {
    "addr:full":"Calle de Cruz Verde (de La), 23 Alameda Sagra Toledo 45240",
    "addr:housenumber":"23",
    "addr:postcode":"45240",
    "addr:street":"Calle De Cruz Verde De La;Sagra",
    "iso:country":"ES",
    "sg:address":"Calle de Cruz Verde (de La), 23",
    "sg:city":"Alameda Sagra",
    "sg:orig_category":"Promotores Constructores",
    "sg:phone":"+34 925 54 92 05",
    "sg:postcode":"45240",
    "sg:province":"Toledo",
    "wof:name":"Construcciones Y Proyectos Jeymar S.l.",
    "wof:placetype":"venue"
},
  "geometry": {"coordinates":[-3.7962658405,40.0132598877],"type":"Point"}
}