{
  "type": "Feature",
  "properties": {
    "iso:country":"ES",
    "sg:address":"Calle de Reina Amalia, 12",
    "sg:city":"Quintanar Orden",
    "sg:orig_category":"Centros De Coordinaci\u00d3n",
    "sg:phone":"+34 925 56 42 90",
    "sg:postcode":"45800",
    "sg:province":"Toledo",
    "wof:name":"Gestoria Pati\u00f1o S.l.",
    "wof:placetype":"venue"
},
  "geometry": {"coordinates":[-3.0416209698,39.5885772705],"type":"Point"}
}