{
  "type": "Feature",
  "properties": {
    "iso:country":"ES",
    "sg:address":"Ptge Roma, 5",
    "sg:city":"Premia Mar",
    "sg:orig_category":"Promotores Constructores",
    "sg:phone":"+34 937 51 06 54",
    "sg:postcode":"08330",
    "sg:province":"Barcelona",
    "wof:name":"Estructuras Y Forjados Tres Aces S.l.",
    "wof:placetype":"venue"
},
  "geometry": {"coordinates":[2.3519411087,41.4893913269],"type":"Point"}
}