{
  "type": "Feature",
  "properties": {
    "addr:full":"Calle de Madrid, 11 Luisiana Sevilla 41430",
    "addr:housenumber":"11",
    "addr:postcode":"41430",
    "addr:street":"Calle De Madrid",
    "iso:country":"ES",
    "sg:address":"Calle de Madrid, 11",
    "sg:city":"Luisiana",
    "sg:orig_category":"Panader\u00cdas, Panader\u00cdas",
    "sg:phone":"+34 955 90 77 88",
    "sg:postcode":"41430",
    "sg:province":"Sevilla",
    "wof:name":"Coproha Sdad. Coop. Andaluza",
    "wof:placetype":"venue"
},
  "geometry": {"coordinates":[-5.2405819893,37.5295410156],"type":"Point"}
}