{
  "type": "Feature",
  "properties": {
    "iso:country":"ES",
    "sg:address":"Urb. Castillitos, 6",
    "sg:city":"Los Dolores",
    "sg:orig_category":"Pr\u00c1ctica De Vela, Navegaci\u00d3n Y Deportes N\u00c1uticos Y Acu\u00c1ticos",
    "sg:phone":"+34 968 31 43 14",
    "sg:postcode":"30310",
    "sg:province":"Murcia",
    "wof:name":"Silva Portela Rosa Maria",
    "wof:placetype":"venue"
},
  "geometry": {"coordinates":[-1.0039989948,37.6324462891],"type":"Point"}
}