{
  "type": "Feature",
  "properties": {
    "addr:full":"Calle de Joaquin Vazquez, 23 Almeria Almer\u00eda 04007",
    "addr:housenumber":"23",
    "addr:postcode":"04007",
    "addr:street":"Calle De Joaquin Vazquez",
    "iso:country":"ES",
    "sg:address":"Calle de Joaquin Vazquez, 23",
    "sg:city":"Almeria",
    "sg:orig_category":"Ense\u00d1anza: Idiomas",
    "sg:phone":"+34 950 25 97 45",
    "sg:postcode":"04007",
    "sg:province":"Almer\u00eda",
    "wof:name":"Mcginty School Of English",
    "wof:placetype":"venue"
},
  "geometry": {"coordinates":[-2.454875946,36.8306884766],"type":"Point"}
}