{
  "type": "Feature",
  "properties": {
    "iso:country":"ES",
    "sg:address":"Avda Pais Valencia, 118",
    "sg:city":"Torrent",
    "sg:orig_category":"Cajas De Ahorro",
    "sg:phone":"+34 961 56 44 56",
    "sg:postcode":"46900",
    "sg:province":"Valencia",
    "sg:website":"www.ccm.es",
    "wof:name":"Caja De Ahorros De Castilla La Mancha",
    "wof:placetype":"venue"
},
  "geometry": {"coordinates":[-0.4747439921,39.4309463501],"type":"Point"}
}