{
  "type": "Feature",
  "properties": {
    "addr:full":"Calle de Recoletas, 12 Tafalla Navarra 31300",
    "addr:housenumber":"12",
    "addr:postcode":"31300",
    "addr:street":"Calle De Recoletas",
    "iso:country":"ES",
    "sg:address":"Calle de Recoletas, 12",
    "sg:city":"Tafalla",
    "sg:orig_category":"Herboristas (al Por Menor)",
    "sg:phone":"+34 948 70 24 10",
    "sg:postcode":"31300",
    "sg:province":"Navarra",
    "wof:name":"Tapia Ancin Saturnina",
    "wof:placetype":"venue"
},
  "geometry": {"coordinates":[-1.6755839586,42.5261955261],"type":"Point"}
}