{
  "type": "Feature",
  "properties": {
    "iso:country":"ES",
    "sg:address":"Carrer de Rasa, 118",
    "sg:city":"Terrassa",
    "sg:orig_category":"Reposter\u00cdas",
    "sg:phone":"+34 937 88 18 47",
    "sg:postcode":"08221",
    "sg:province":"Barcelona",
    "wof:name":"Girabent Pujol Ramon",
    "wof:placetype":"venue"
},
  "geometry": {"coordinates":[2.008300066,41.5638809204],"type":"Point"}
}