{
  "type": "Feature",
  "properties": {
    "iso:country":"ES",
    "sg:address":"Calle de Real De Arriba, 26",
    "sg:city":"Valverde Camino",
    "sg:orig_category":"Electrodom\u00c9sticos (al Por Menor)",
    "sg:phone":"+34 959 55 17 52",
    "sg:postcode":"21600",
    "sg:province":"Huelva",
    "wof:name":"Tecnovision Stef C.b.",
    "wof:placetype":"venue"
},
  "geometry": {"coordinates":[-6.7533731461,37.5735282898],"type":"Point"}
}