{
  "type": "Feature",
  "properties": {
    "addr:full":"Tafalla, 3 Iru\u00f1a Navarra 31004",
    "addr:housenumber":"3",
    "addr:postcode":"31004",
    "addr:street":"Tafalla",
    "iso:country":"ES",
    "sg:address":"Tafalla, 3",
    "sg:city":"Iru\u00f1a",
    "sg:orig_category":"Empresarios",
    "sg:phone":"+34 948 29 19 09",
    "sg:postcode":"31004",
    "sg:province":"Navarra",
    "wof:name":"Fundacion Empresa Y Solidaridad",
    "wof:placetype":"venue"
},
  "geometry": {"coordinates":[-1.6354249716,42.8131332397],"type":"Point"}
}