{
  "type": "Feature",
  "properties": {
    "addr:full":"Avda J. Antonio, 21 Villarrubia C\u00f3rdoba 14710",
    "addr:housenumber":"21",
    "addr:postcode":"14710",
    "addr:street":"Avda J. Antonio;Co\u0301Rdoba",
    "iso:country":"ES",
    "sg:address":"Avda J. Antonio, 21",
    "sg:city":"Villarrubia",
    "sg:orig_category":"Carnicer\u00cdas, Carnicer\u00cdas",
    "sg:phone":"+34 957 32 70 09",
    "sg:postcode":"14710",
    "sg:province":"C\u00f3rdoba",
    "wof:name":"Cano Villalba Maria Del Carmen",
    "wof:placetype":"venue"
},
  "geometry": {"coordinates":[-4.9146289825,37.8490753174],"type":"Point"}
}