{
  "type": "Feature",
  "properties": {
    "addr:full":"Calle de La Del Manojo De Rosas, 80 Madrid Madrid 28041",
    "addr:housenumber":"80",
    "addr:postcode":"madrid;28041",
    "addr:street":"Calle De La Del Manojo De Rosas",
    "iso:country":"ES",
    "sg:address":"Calle de La Del Manojo De Rosas, 80",
    "sg:city":"Madrid",
    "sg:orig_category":"Peluqueros: De Se\u00d1oras",
    "sg:phone":"+34 913 17 16 47",
    "sg:postcode":"28041",
    "sg:province":"Madrid",
    "wof:name":"Salon De Peluqueria Ambar S.l.l.",
    "wof:placetype":"venue"
},
  "geometry": {"coordinates":[-3.6980109215,40.3549728394],"type":"Point"}
}