{
  "type": "Feature",
  "properties": {
    "addr:full":"Prolongacion De Granada, 85 Cuevas San Marcos M\u00e1laga 29210",
    "addr:housenumber":"85",
    "addr:postcode":"29210",
    "addr:street":"Prolongacion De Granada",
    "iso:country":"ES",
    "sg:address":"Prolongacion De Granada, 85",
    "sg:city":"Cuevas San Marcos",
    "sg:orig_category":"Bares, Piano",
    "sg:phone":"+34 952 72 84 85",
    "sg:postcode":"29210",
    "sg:province":"M\u00e1laga",
    "wof:name":"Almacenes Lusan S.l.",
    "wof:placetype":"venue"
},
  "geometry": {"coordinates":[-4.4095220566,37.2680282593],"type":"Point"}
}