{
  "type": "Feature",
  "properties": {
    "iso:country":"ES",
    "sg:address":"Calle de Delicias, 88",
    "sg:city":"Zaragoza",
    "sg:orig_category":"Reposter\u00cdas",
    "sg:phone":"+34 976 34 68 59",
    "sg:postcode":"50017",
    "sg:province":"Zaragoza",
    "wof:name":"Pcgestimac S.l.",
    "wof:placetype":"venue"
},
  "geometry": {"coordinates":[-0.9038786888,41.6482543945],"type":"Point"}
}