{
  "type": "Feature",
  "properties": {
    "iso:country":"ES",
    "sg:address":"Plaz Virgen De La Caridad, 1",
    "sg:city":"Camarena",
    "sg:orig_category":"Ense\u00d1anza, Formaci\u00d3n Profesional: Aprendizaje",
    "sg:phone":"+34 918 17 40 19",
    "sg:postcode":"45180",
    "sg:province":"Toledo",
    "wof:name":"Ayuntamiento De Camarena",
    "wof:placetype":"venue"
},
  "geometry": {"coordinates":[-4.1190609932,40.0928726196],"type":"Point"}
}