{
  "type": "Feature",
  "properties": {
    "iso:country":"ES",
    "sg:address":"Calle de Ramon Y Cajal, 77",
    "sg:city":"Arjonilla",
    "sg:orig_category":"Comercio, Reparaci\u00d3n De Motocicletas, Bicicletas Y Piezas Sueltas",
    "sg:phone":"+34 953 52 07 34",
    "sg:postcode":"23750",
    "sg:province":"Ja\u00e9n",
    "wof:name":"Zuheros Extremera Custodio",
    "wof:placetype":"venue"
},
  "geometry": {"coordinates":[-4.1081829071,37.9707336426],"type":"Point"}
}