{
  "type": "Feature",
  "properties": {
    "iso:country":"ES",
    "sg:address":"Carrer de Almogavers, 22",
    "sg:city":"Barcelona",
    "sg:orig_category":"Frutas Y Legumbres Frescas (al Por Mayor)",
    "sg:phone":"+34 934 85 09 01",
    "sg:postcode":"08018",
    "sg:province":"Barcelona",
    "wof:name":"Chicheno S.l.",
    "wof:placetype":"venue"
},
  "geometry": {"coordinates":[2.1837930679,41.3922996521],"type":"Point"}
}