{
  "type": "Feature",
  "properties": {
    "addr:full":"Avda Angeles (los), 268 Angeles De San Rafael Segovia 40424",
    "addr:housenumber":"268",
    "addr:postcode":"40424",
    "addr:street":"Avda Angeles Los",
    "iso:country":"ES",
    "sg:address":"Avda Angeles (los), 268",
    "sg:city":"Angeles De San Rafael",
    "sg:orig_category":"Arquitectos",
    "sg:phone":"+34 921 17 28 47",
    "sg:postcode":"40424",
    "sg:province":"Segovia",
    "wof:name":"Arquetipo Almacenistas S.l.",
    "wof:placetype":"venue"
},
  "geometry": {"coordinates":[-4.2197880745,40.7779388428],"type":"Point"}
}