{
  "type": "Feature",
  "properties": {
    "addr:full":"Pol Ind Pque Comercial Nevada, S/n Armilla Granada 18100",
    "addr:housenumber":"s / n",
    "addr:postcode":"18100",
    "iso:country":"ES",
    "sg:address":"Pol Ind Pque Comercial Nevada, S/n",
    "sg:city":"Armilla",
    "sg:orig_category":"Promotores Constructores",
    "sg:phone":"+34 958 57 89 69",
    "sg:postcode":"18100",
    "sg:province":"Granada",
    "wof:name":"Aldesa Construcciones S.a.",
    "wof:placetype":"venue"
},
  "geometry": {"coordinates":[-3.6192471981,37.148475647],"type":"Point"}
}