{
  "type": "Feature",
  "properties": {
    "addr:full":"Pg Germanies (de Les), 53 Gandia Valencia 46700",
    "addr:housenumber":"53",
    "addr:postcode":"46700",
    "addr:street":"Pg Germanies De Les;Valencia",
    "iso:country":"ES",
    "sg:address":"Pg Germanies (de Les), 53",
    "sg:city":"Gandia",
    "sg:orig_category":"Pr\u00c9stamos Personales E Hipotecarios",
    "sg:phone":"+34 962 86 21 58",
    "sg:postcode":"46700",
    "sg:province":"Valencia",
    "wof:name":"Gomez Dura Maria Del Carmen",
    "wof:placetype":"venue"
},
  "geometry": {"coordinates":[-0.1871960014,38.9660873413],"type":"Point"}
}