{
  "type": "Feature",
  "properties": {
    "iso:country":"ES",
    "sg:address":"Praj Fabrica Harinas Santa Marta, S/n",
    "sg:city":"Santa Marta",
    "sg:orig_category":"Fabricaci\u00d3n De Harinas, S\u00c9molas, Productos De Elaboraci\u00d3n Del Grano",
    "sg:phone":"+34 967 57 00 00",
    "sg:postcode":"02639",
    "sg:province":"Albacete",
    "wof:name":"Harinas Marta S.l.",
    "wof:placetype":"venue"
},
  "geometry": {"coordinates":[-2.2009239197,39.044303894],"type":"Point"}
}