{
  "type": "Feature",
  "properties": {
    "iso:country":"ES",
    "sg:address":"Ca Tajonar, 23",
    "sg:city":"Iru\u00f1a",
    "sg:orig_category":"Molduras, Junquillos, Listones Y Molduras Perforadas",
    "sg:phone":"+34 948 23 10 12",
    "sg:postcode":"31006",
    "sg:province":"Navarra",
    "wof:name":"Esparza Perez Jose Felix",
    "wof:placetype":"venue"
},
  "geometry": {"coordinates":[-1.6348079443,42.8053207397],"type":"Point"}
}