{
  "type": "Feature",
  "properties": {
    "iso:country":"ES",
    "sg:address":"Carrer de Barcelona, 21",
    "sg:city":"Constanti",
    "sg:orig_category":"Librer\u00cdas",
    "sg:phone":"+34 977 52 33 47",
    "sg:postcode":"43120",
    "sg:province":"Tarragona",
    "wof:name":"Martinez Parra Maria Dolores",
    "wof:placetype":"venue"
},
  "geometry": {"coordinates":[1.2153990269,41.151134491],"type":"Point"}
}