{
  "type": "Feature",
  "properties": {
    "addr:full":"Donostia Ibilbidea, 90 Astigarraga Guip\u00f9zcoa 20115",
    "addr:housenumber":"90",
    "addr:postcode":"20115",
    "addr:street":"Donostia Ibilbidea;Guipu\u0300Zcoa",
    "iso:country":"ES",
    "sg:address":"Donostia Ibilbidea, 90",
    "sg:city":"Astigarraga",
    "sg:orig_category":"Cristaler\u00cdas",
    "sg:phone":"+34 943 33 71 75",
    "sg:postcode":"20115",
    "sg:province":"Guip\u00f9zcoa",
    "wof:name":"Cristaleria Igara S.l.",
    "wof:placetype":"venue"
},
  "geometry": {"coordinates":[-1.9514549971,43.2819786072],"type":"Point"}
}