{
  "type": "Feature",
  "properties": {
    "addr:full":"Carr Pla De L'estany, 17 Cassa Selva Girona 17...",
    "addr:housenumber":"17",
    "addr:street":"Carr Pla De L'Estany",
    "iso:country":"ES",
    "sg:address":"Carr Pla De L'estany, 17",
    "sg:city":"Cassa Selva",
    "sg:orig_category":"Agencias De Trabajo Temporal",
    "sg:phone":"+34 972 18 10 10",
    "sg:postcode":"17...",
    "sg:province":"Girona",
    "wof:name":"Eurofirms Ett S.l.",
    "wof:placetype":"venue"
},
  "geometry": {"coordinates":[2.8187398911,41.9808616638],"type":"Point"}
}