{
  "type": "Feature",
  "properties": {
    "addr:full":"Avda Casalduch, 28 Castellon Castell\u00f3n 12005",
    "addr:housenumber":"28",
    "addr:postcode":"12005",
    "addr:street":"Avda Casalduch",
    "iso:country":"ES",
    "sg:address":"Avda Casalduch, 28",
    "sg:city":"Castellon",
    "sg:orig_category":"Bancos",
    "sg:phone":"+34 964 23 98 12",
    "sg:postcode":"12005",
    "sg:province":"Castell\u00f3n",
    "wof:name":"Banc Sabadell S.a.",
    "wof:placetype":"venue"
},
  "geometry": {"coordinates":[-0.0375149995,39.9806098938],"type":"Point"}
}