{
  "type": "Feature",
  "properties": {
    "addr:full":"Pg Estacio De L', 41 Valls Tarragona 43800",
    "addr:housenumber":"41",
    "addr:postcode":"43800",
    "addr:street":"Pg Estacio De L '",
    "iso:country":"ES",
    "sg:address":"Pg Estacio De L', 41",
    "sg:city":"Valls",
    "sg:orig_category":"Clases De M\u00dasica Y Canto",
    "sg:phone":"+34 977 60 44 54",
    "sg:postcode":"43800",
    "sg:province":"Tarragona",
    "wof:name":"Ajuntament De Valls",
    "wof:placetype":"venue"
},
  "geometry": {"coordinates":[1.2562065125,41.287651062],"type":"Point"}
}