{
  "type": "Feature",
  "properties": {
    "iso:country":"ES",
    "sg:address":"Barreras, 6",
    "sg:city":"Baeza",
    "sg:orig_category":"Bisuter\u00cda, Joyer\u00cda, Relojer\u00cda (al Por Menor)",
    "sg:phone":"+34 953 74 19 52",
    "sg:postcode":"23440",
    "sg:province":"Ja\u00e9n",
    "wof:name":"Salcedo Checa Jose",
    "wof:placetype":"venue"
},
  "geometry": {"coordinates":[-3.4674789906,37.9929199219],"type":"Point"}
}