{
  "type": "Feature",
  "properties": {
    "iso:country":"ES",
    "sg:address":"Ctra General Del Norte, S/n",
    "sg:city":"Montillo",
    "sg:orig_category":"Fabricaci\u00d3n De Camas",
    "sg:phone":"+34 922 56 02 21",
    "sg:postcode":"38360",
    "sg:province":"Santa Cruz De Tenerife",
    "wof:name":"Dulces Sue\u00d1os S.l.u.",
    "wof:placetype":"venue"
},
  "geometry": {"coordinates":[-16.4350795746,28.4798755646],"type":"Point"}
}