{
  "type": "Feature",
  "properties": {
    "addr:full":"Fte Hierro, 5 Iru\u00f1a Navarra 31007",
    "addr:housenumber":"5",
    "addr:postcode":"31007",
    "addr:street":"Irun\u0303A Navarra",
    "iso:country":"ES",
    "sg:address":"Fte Hierro, 5",
    "sg:city":"Iru\u00f1a",
    "sg:orig_category":"Centros P\u00dablicos De Formaci\u00d3n Profesional Y T\u00c9cnica",
    "sg:phone":"+34 948 26 78 14",
    "sg:postcode":"31007",
    "sg:province":"Navarra",
    "wof:name":"Colegio Oficial De Ingenieros Agronomos",
    "wof:placetype":"venue"
},
  "geometry": {"coordinates":[-1.6538150311,42.8084907532],"type":"Point"}
}