{
  "type": "Feature",
  "properties": {
    "addr:full":"Calle de San Juan, 3 Almoguera Guadalajara 19115",
    "addr:housenumber":"3",
    "addr:postcode":"19115",
    "addr:street":"Calle De San Juan",
    "iso:country":"ES",
    "sg:address":"Calle de San Juan, 3",
    "sg:city":"Almoguera",
    "sg:orig_category":"Autob\u00das (explotaci\u00d3n Y Servicios De)",
    "sg:phone":"+34 949 38 01 85",
    "sg:postcode":"19115",
    "sg:province":"Guadalajara",
    "wof:name":"Autocares Manzano S.l.",
    "wof:placetype":"venue"
},
  "geometry": {"coordinates":[-2.9816160202,40.2964286804],"type":"Point"}
}