{
  "type": "Feature",
  "properties": {
    "addr:full":"Barr Oguena, 11 Amorebieta Vizcaya 48340",
    "addr:housenumber":"11",
    "addr:postcode":"48340",
    "addr:street":"Oguena",
    "iso:country":"ES",
    "sg:address":"Barr Oguena, 11",
    "sg:city":"Amorebieta",
    "sg:orig_category":"Tratamiento De Metales",
    "sg:phone":"+34 946 30 84 20",
    "sg:postcode":"48340",
    "sg:province":"Vizcaya",
    "wof:name":"Tratamientos Termicos Tratermic S.a.l.",
    "wof:placetype":"venue"
},
  "geometry": {"coordinates":[-2.7321588993,43.2210960388],"type":"Point"}
}