{
  "type": "Feature",
  "properties": {
    "iso:country":"ES",
    "sg:address":"Carrer de Alcalde Armengou, 28",
    "sg:city":"Manresa",
    "sg:orig_category":"Doctores En Medicina",
    "sg:phone":"+34 938 74 61 05",
    "sg:postcode":"08242",
    "sg:province":"Barcelona",
    "wof:name":"Dedeu Baraldes Antonio",
    "wof:placetype":"venue"
},
  "geometry": {"coordinates":[1.8213889599,41.7314567566],"type":"Point"}
}