{
  "type": "Feature",
  "properties": {
    "addr:full":"Calle de General Sueiro, 24 Zaragoza Zaragoza 50008",
    "addr:housenumber":"24",
    "addr:postcode":"50008",
    "addr:street":"Calle De General Sueiro",
    "iso:country":"ES",
    "sg:address":"Calle de General Sueiro, 24",
    "sg:city":"Zaragoza",
    "sg:orig_category":"Psic\u00d3logos",
    "sg:phone":"+34 976 21 57 30",
    "sg:postcode":"50008",
    "sg:province":"Zaragoza",
    "wof:name":"Carreras Gargallo Alberto",
    "wof:placetype":"venue"
},
  "geometry": {"coordinates":[-0.8821409941,41.6449165344],"type":"Point"}
}