{
  "type": "Feature",
  "properties": {
    "iso:country":"ES",
    "sg:address":"Calle de Sargento Provisional, 19",
    "sg:city":"Santa Cruz De Tenerife",
    "sg:orig_category":"Comercio De Piezas De Recambio Y De Accesorios De Veh\u00cdculos, Veh\u00cdculos Industriales",
    "sg:phone":"+34 922 64 79 11",
    "sg:postcode":"38010",
    "sg:province":"Santa Cruz De Tenerife",
    "wof:name":"Jerez Martin Agustin",
    "wof:placetype":"venue"
},
  "geometry": {"coordinates":[-16.2870559692,28.4525642395],"type":"Point"}
}