{
  "type": "Feature",
  "properties": {
    "iso:country":"ES",
    "sg:address":"Calle de Fuentepelayo, S/n",
    "sg:city":"Navalmanzano",
    "sg:orig_category":"Fabricaci\u00d3n Y Comercio De M\u00c1quinas",
    "sg:phone":"+34 921 57 51 97",
    "sg:postcode":"40280",
    "sg:province":"Segovia",
    "wof:name":"Hidra Gomez S.l.",
    "wof:placetype":"venue"
},
  "geometry": {"coordinates":[-4.2545905113,41.2150115967],"type":"Point"}
}