{
  "type": "Feature",
  "properties": {
    "iso:country":"ES",
    "sg:address":"Calle de San Fernando, 4",
    "sg:city":"Cabra",
    "sg:orig_category":"Molduras, Junquillos, Listones Y Molduras Perforadas",
    "sg:phone":"+34 957 52 09 13",
    "sg:postcode":"14940",
    "sg:province":"C\u00f3rdoba",
    "wof:name":"Caballero Lucena Juan",
    "wof:placetype":"venue"
},
  "geometry": {"coordinates":[-4.4292078018,37.4767951965],"type":"Point"}
}