{
  "type": "Feature",
  "properties": {
    "iso:country":"ES",
    "sg:address":"Calle de Pio Xii, 33",
    "sg:city":"Torre De La Horadada",
    "sg:orig_category":"Molduras, Junquillos, Listones Y Molduras Perforadas",
    "sg:phone":"+34 966 76 96 37",
    "sg:postcode":"03191",
    "sg:province":"Alicante",
    "wof:name":"Sanchez Marin Juan",
    "wof:placetype":"venue"
},
  "geometry": {"coordinates":[-0.4804739952,38.3440856934],"type":"Point"}
}