{
  "type": "Feature",
  "properties": {
    "iso:country":"ES",
    "sg:address":"Estaci\u00f3n, 19",
    "sg:city":"Torreblanca",
    "sg:orig_category":"Electrodom\u00c9sticos (fabricaci\u00d3n, Al Por Mayor)",
    "sg:phone":"+34 964 42 12 35",
    "sg:postcode":"12596",
    "sg:province":"Castell\u00f3n",
    "wof:name":"Ferrer Orenga S.l.",
    "wof:placetype":"venue"
},
  "geometry": {"coordinates":[0.1967840046,40.2177658081],"type":"Point"}
}