{
  "type": "Feature",
  "properties": {
    "iso:country":"ES",
    "sg:address":"Abenda\u00d1o Kalea, 25",
    "sg:city":"Zarautz",
    "sg:orig_category":"Madera Para Construcci\u00d3n E Industria",
    "sg:phone":"+34 943 13 13 22",
    "sg:postcode":"20800",
    "sg:province":"Guip\u00f9zcoa",
    "wof:name":"Carpinteria Zulaika S.l.",
    "wof:placetype":"venue"
},
  "geometry": {"coordinates":[-2.1817948818,43.2763252258],"type":"Point"}
}