{
  "type": "Feature",
  "properties": {
    "iso:country":"ES",
    "sg:address":"Carrer de Comte D'urgell, 110",
    "sg:city":"Barcelona",
    "sg:orig_category":"Peluqueros: De Se\u00d1oras",
    "sg:phone":"+34 934 54 08 10",
    "sg:postcode":"08011",
    "sg:province":"Barcelona",
    "wof:name":"Martinez Vicario Victoriano",
    "wof:placetype":"venue"
},
  "geometry": {"coordinates":[2.1561582088,41.3839874268],"type":"Point"}
}