{
  "type": "Feature",
  "properties": {
    "addr:full":"Carrer de Madrazo, 109 Barcelona Barcelona 08021",
    "addr:housenumber":"109",
    "addr:postcode":"08021",
    "addr:street":"Carrer De Madrazo",
    "iso:country":"ES",
    "sg:address":"Carrer de Madrazo, 109",
    "sg:city":"Barcelona",
    "sg:orig_category":"Seguridad En El Trabajo Y Prevenci\u00d3n De Riesgos Laborales",
    "sg:phone":"+34 934 14 63 35",
    "sg:postcode":"08021",
    "sg:province":"Barcelona",
    "sg:website":"www.erbogrup.com",
    "wof:name":"Ceteg S.l.",
    "wof:placetype":"venue"
},
  "geometry": {"coordinates":[2.1461980343,41.3979263306],"type":"Point"}
}