{
  "type": "Feature",
  "properties": {
    "iso:country":"ES",
    "sg:address":"Calle de Padre Cortazar, 1",
    "sg:city":"Portugalete",
    "sg:orig_category":"T\u00c9cnicos Veterinarios",
    "sg:phone":"+34 944 95 17 60",
    "sg:postcode":"48920",
    "sg:province":"Vizcaya",
    "wof:name":"Miguel I\u00f1iguez De Onzo\u00f1o Ramirez-escuder",
    "wof:placetype":"venue"
},
  "geometry": {"coordinates":[-3.0190927982,43.3228874207],"type":"Point"}
}