{
  "type": "Feature",
  "properties": {
    "addr:full":"Calle de Alibarra, 16 Vitoria-gasteiz \u00c1lava 01010",
    "addr:housenumber":"16",
    "addr:postcode":"01010",
    "addr:street":"Calle De Alibarra",
    "iso:country":"ES",
    "sg:address":"Calle de Alibarra, 16",
    "sg:city":"Vitoria-gasteiz",
    "sg:orig_category":"Bares, Piano",
    "sg:phone":"+34 945 24 25 50",
    "sg:postcode":"01010",
    "sg:province":"\u00c1lava",
    "wof:name":"Heredad De Bujo S.l.",
    "wof:placetype":"venue"
},
  "geometry": {"coordinates":[-2.7178530693,42.8609046936],"type":"Point"}
}