{
  "type": "Feature",
  "properties": {
    "iso:country":"ES",
    "sg:address":"Avda Arga (el), 11",
    "sg:city":"Falces",
    "sg:orig_category":"Agencias Y Agentes Comerciales, Representantes",
    "sg:phone":"+34 948 73 40 77",
    "sg:postcode":"31370",
    "sg:province":"Navarra",
    "wof:name":"Palau Leon S.l.",
    "wof:placetype":"venue"
},
  "geometry": {"coordinates":[-1.791211009,42.3861732483],"type":"Point"}
}