{
  "type": "Feature",
  "properties": {
    "addr:full":"Carretera, S/n Cubells Lleida 25737",
    "addr:postcode":"25737",
    "addr:street":"Carretera S / N",
    "iso:country":"ES",
    "sg:address":"Carretera, S/n",
    "sg:city":"Cubells",
    "sg:orig_category":"Centros De Educaci\u00d3n Especial",
    "sg:phone":"+34 973 45 90 05",
    "sg:postcode":"25737",
    "sg:province":"Lleida",
    "wof:name":"Ajuntament De Cubells",
    "wof:placetype":"venue"
},
  "geometry": {"coordinates":[1.0128653049,41.877040863],"type":"Point"}
}