{
  "type": "Feature",
  "properties": {
    "iso:country":"ES",
    "sg:address":"Calle de Teniente General Gutierrez Mellado, 9",
    "sg:city":"Fama",
    "sg:orig_category":"Promotores Constructores",
    "sg:phone":"+34 968 24 07 17",
    "sg:postcode":"30008",
    "sg:province":"Murcia",
    "wof:name":"Obrascon Huarte Lain S.a.",
    "wof:placetype":"venue"
},
  "geometry": {"coordinates":[-1.1277829409,37.9899139404],"type":"Point"}
}