{
  "type": "Feature",
  "properties": {
    "iso:country":"ES",
    "sg:address":"Ctra. El Berrueco, Km. 0007,0",
    "sg:city":"Arjona",
    "sg:orig_category":"Aceites Y Grasas Alimentarias (fabricaci\u00d3n, Al Por Mayor)",
    "sg:phone":"+34 953 12 24 74",
    "sg:postcode":"23760",
    "sg:province":"Ja\u00e9n",
    "wof:name":"Contreras Gomez De Cortinas Maria Jose",
    "wof:placetype":"venue"
},
  "geometry": {"coordinates":[-4.0609068871,37.9375991821],"type":"Point"}
}