{
  "type": "Feature",
  "properties": {
    "addr:full":"Cra Mata (de), 68 Mataro Barcelona 08304",
    "addr:postcode":"08304",
    "iso:country":"ES",
    "sg:address":"Cra Mata (de), 68",
    "sg:city":"Mataro",
    "sg:classifiers":[
        {
            "category":"Autos & Motor Vehicles",
            "subcategory":"Automobile Sales",
            "type":"Retail Goods"
        }
    ],
    "sg:phone":"+34 937 90 27 85",
    "sg:postcode":"08304",
    "sg:province":"Barcelona",
    "wof:name":"Gregal Mix S.l.",
    "wof:placetype":"venue"
},
  "geometry": {"coordinates":[2.4531331062,41.5492935181],"type":"Point"}
}