{
  "type": "Feature",
  "properties": {
    "addr:full":"Calle de Federico Garcia Lorca, 3 Do\u00e7a Mencia C\u00f3rdoba 14860",
    "addr:housenumber":"3",
    "addr:postcode":"14860",
    "addr:street":"Calle De Federico Garcia Lorca;Co\u0301Rdoba",
    "iso:country":"ES",
    "sg:address":"Calle de Federico Garcia Lorca, 3",
    "sg:city":"Do\u00e7a Mencia",
    "sg:orig_category":"Promotores Constructores",
    "sg:phone":"+34 957 67 63 87",
    "sg:postcode":"14860",
    "sg:province":"C\u00f3rdoba",
    "wof:name":"Urbanizacion Bellavista S.l.",
    "wof:placetype":"venue"
},
  "geometry": {"coordinates":[-4.3571228981,37.554107666],"type":"Point"}
}