{
  "type": "Feature",
  "properties": {
    "addr:full":"Calle de Leones, 45 Valencia Valencia 46022",
    "addr:housenumber":"45",
    "addr:postcode":"46022",
    "addr:street":"Calle De Leones",
    "iso:country":"ES",
    "sg:address":"Calle de Leones, 45",
    "sg:city":"Valencia",
    "sg:orig_category":"Producci\u00d3n, Distribuci\u00d3n De Electricidad",
    "sg:phone":"+34 963 55 08 73",
    "sg:postcode":"46022",
    "sg:province":"Valencia",
    "wof:name":"Gurrea Isaach Josefa Francisca",
    "wof:placetype":"venue"
},
  "geometry": {"coordinates":[-0.3474360108,39.4687995911],"type":"Point"}
}