{
  "type": "Feature",
  "properties": {
    "iso:country":"ES",
    "sg:address":"Carrer de Caceres, 17",
    "sg:city":"Barcelona",
    "sg:orig_category":"Fabricaci\u00d3n De Pastas Alimentarias",
    "sg:phone":"+34 933 39 51 63",
    "sg:postcode":"08028",
    "sg:province":"Barcelona",
    "wof:name":"Productos Gala S.a.",
    "wof:placetype":"venue"
},
  "geometry": {"coordinates":[2.1319348812,41.3746109009],"type":"Point"}
}