{
  "type": "Feature",
  "properties": {
    "iso:country":"ES",
    "sg:address":"Carrer de General Padros, 87",
    "sg:city":"Caldes Montbui",
    "sg:orig_category":"Molduras, Junquillos, Listones Y Molduras Perforadas",
    "sg:phone":"+34 938 65 47 95",
    "sg:postcode":"08140",
    "sg:province":"Barcelona",
    "wof:name":"Romero Franques Carlos",
    "wof:placetype":"venue"
},
  "geometry": {"coordinates":[2.1665999889,41.6266174316],"type":"Point"}
}