{
  "type": "Feature",
  "properties": {
    "addr:full":"Carr Bisbe Cardona, Del, 7 Eivissa Islas Baleares 07800",
    "addr:housenumber":"7",
    "addr:postcode":"07800",
    "addr:street":"Carr Bisbe Cardona Del",
    "iso:country":"ES",
    "sg:address":"Carr Bisbe Cardona, Del, 7",
    "sg:city":"Eivissa",
    "sg:orig_category":"Peluquer\u00cdas, Peluquer\u00cda Mixta",
    "sg:phone":"+34 971 31 42 19",
    "sg:postcode":"07800",
    "sg:province":"Islas Baleares",
    "wof:name":"House Of Hair C.b.",
    "wof:placetype":"venue"
},
  "geometry": {"coordinates":[1.4293489456,38.911075592],"type":"Point"}
}