{
  "type": "Feature",
  "properties": {
    "iso:country":"ES",
    "sg:address":"Cra Madrid-cadiz-p I La Fundicion, Km. 0325,0",
    "sg:city":"Andujar",
    "sg:orig_category":"Agencias Y Asesores De Publicidad",
    "sg:phone":"+34 953 50 48 38",
    "sg:postcode":"23740",
    "sg:province":"Ja\u00e9n",
    "wof:name":"A3 Comunicacion S.c.a",
    "wof:placetype":"venue"
},
  "geometry": {"coordinates":[-4.028678,38.289757],"type":"Point"}
}