{
  "type": "Feature",
  "properties": {
    "addr:full":"Calle de Isaac Peral, 24 Estacion De Benacazon Sevilla 41800",
    "addr:housenumber":"24 estacion",
    "addr:postcode":"41800",
    "addr:street":"Calle De Isaac Peral",
    "iso:country":"ES",
    "sg:address":"Calle de Isaac Peral, 24",
    "sg:city":"Estacion De Benacazon",
    "sg:orig_category":"Piedra, Vidrio, Cer\u00c1mica Y Porcelana",
    "sg:phone":"+34 955 70 24 08",
    "sg:postcode":"41800",
    "sg:province":"Sevilla",
    "wof:name":"M.c. Don Azulejo S.l.",
    "wof:placetype":"venue"
},
  "geometry": {"coordinates":[-6.1956338882,37.3855361938],"type":"Point"}
}