{
  "type": "Feature",
  "properties": {
    "iso:country":"ES",
    "sg:address":"Avda Val Mi\u00d1or, 2",
    "sg:city":"Vilamean",
    "sg:orig_category":"Edici\u00d3n De Diarios, Revistas, Boletines",
    "sg:phone":"+34 986 36 81 76",
    "sg:postcode":"36350",
    "sg:province":"Pontevedra",
    "wof:name":"Big Norte Comunicaciones S.l",
    "wof:placetype":"venue"
},
  "geometry": {"coordinates":[-8.8061733246,42.1419296265],"type":"Point"}
}