{
  "type": "Feature",
  "properties": {
    "iso:country":"ES",
    "sg:address":"C/ Sant Lluis, 56",
    "sg:city":"Sant Lluis",
    "sg:orig_category":"Molduras, Junquillos, Listones Y Molduras Perforadas",
    "sg:phone":"+34 971 15 65 13",
    "sg:postcode":"07710",
    "sg:province":"Islas Baleares",
    "wof:name":"Vioque Lozano Jose",
    "wof:placetype":"venue"
},
  "geometry": {"coordinates":[4.2691421509,39.8487739563],"type":"Point"}
}