{
  "type": "Feature",
  "properties": {
    "iso:country":"ES",
    "sg:address":"Barr Boroa, S/n",
    "sg:city":"Boroa",
    "sg:orig_category":"Negocio De Madera",
    "sg:phone":"+34 946 73 42 00",
    "sg:postcode":"48340",
    "sg:province":"Vizcaya",
    "wof:name":"Jose De Ezpeleta S.a.",
    "wof:placetype":"venue"
},
  "geometry": {"coordinates":[-2.7321588993,43.2210960388],"type":"Point"}
}