{
  "type": "Feature",
  "properties": {
    "addr:full":"Carrer de Mare De Deu De Port, 279 Barcelona Barcelona 08038",
    "addr:housenumber":"279",
    "addr:postcode":"08038",
    "addr:street":"Carrer De Mare De Deu;Port",
    "iso:country":"ES",
    "sg:address":"Carrer de Mare De Deu De Port, 279",
    "sg:city":"Barcelona",
    "sg:orig_category":"Ropa Para Se\u00d1oras (al Por Menor)",
    "sg:phone":"+34 934 31 43 09",
    "sg:postcode":"08038",
    "sg:province":"Barcelona",
    "wof:name":"Lin  Miaogui",
    "wof:placetype":"venue"
},
  "geometry": {"coordinates":[2.1416580677,41.3597335815],"type":"Point"}
}