{
  "type": "Feature",
  "properties": {
    "addr:full":"Avda Doctor Federico Rubio Y Gali, 39 Madrid Madrid 28039",
    "addr:housenumber":"39",
    "addr:postcode":"madrid;28039",
    "addr:street":"Avda Doctor Federico Rubio Y Gali",
    "iso:country":"ES",
    "sg:address":"Avda Doctor Federico Rubio Y Gali, 39",
    "sg:city":"Madrid",
    "sg:orig_category":"Asesor\u00cda Fiscal Y Jur\u00cddica",
    "sg:phone":"+34 913 11 49 55",
    "sg:postcode":"28039",
    "sg:province":"Madrid",
    "wof:name":"Bodelon Fernandez Silvia",
    "wof:placetype":"venue"
},
  "geometry": {"coordinates":[-3.7095160484,40.4515953064],"type":"Point"}
}