{
  "type": "Feature",
  "properties": {
    "addr:full":"Pg Jose Canalejas, 1 Girona Girona 17001",
    "addr:housenumber":"1",
    "addr:postcode":"17001",
    "addr:street":"Pg Jose Canalejas",
    "iso:country":"ES",
    "sg:address":"Pg Jose Canalejas, 1",
    "sg:city":"Girona",
    "sg:orig_category":"Abogados",
    "sg:phone":"+34 972 20 21 56",
    "sg:postcode":"17001",
    "sg:province":"Girona",
    "wof:name":"Brell Crespo Roberto",
    "wof:placetype":"venue"
},
  "geometry": {"coordinates":[2.8234810829,41.9866333008],"type":"Point"}
}