{
  "type": "Feature",
  "properties": {
    "addr:full":"Calle de La Libertad, 3 Vitoria-gasteiz \u00c1lava 01002",
    "addr:housenumber":"3",
    "addr:postcode":"01002",
    "addr:street":"Calle De La Libertad",
    "iso:country":"ES",
    "sg:address":"Calle de La Libertad, 3",
    "sg:city":"Vitoria-gasteiz",
    "sg:orig_category":"Producci\u00d3n, Comercio De Cereales",
    "sg:phone":"+34 945 25 12 58",
    "sg:postcode":"01002",
    "sg:province":"\u00c1lava",
    "wof:name":"Gonzalo Ochoa Jose Luis",
    "wof:placetype":"venue"
},
  "geometry": {"coordinates":[-2.6676340103,42.8480453491],"type":"Point"}
}