{
  "type": "Feature",
  "properties": {
    "iso:country":"ES",
    "sg:address":"Calle de Vicente Carballal, 5",
    "sg:city":"Madrid",
    "sg:orig_category":"Alquiler De V\u00cddeo",
    "sg:phone":"+34 917 98 36 19",
    "sg:postcode":"28021",
    "sg:province":"Madrid",
    "wof:name":"Carrasco Romero Prudencio",
    "wof:placetype":"venue"
},
  "geometry": {"coordinates":[-3.6825709343,40.3530464172],"type":"Point"}
}