{
  "type": "Feature",
  "properties": {
    "addr:full":"Calle de Alfonso I, 25 Zaragoza Zaragoza 50003",
    "addr:housenumber":"25",
    "addr:postcode":"50003",
    "addr:street":"Calle De Alfonso I",
    "iso:country":"ES",
    "sg:address":"Calle de Alfonso I, 25",
    "sg:city":"Zaragoza",
    "sg:orig_category":"Procuradores",
    "sg:phone":"+34 976 20 55 69",
    "sg:postcode":"50003",
    "sg:province":"Zaragoza",
    "wof:name":"Cortes Carbonel Ana Cristina",
    "wof:placetype":"venue"
},
  "geometry": {"coordinates":[-0.8805962205,41.6545982361],"type":"Point"}
}