{
  "type": "Feature",
  "properties": {
    "addr:full":"Av Del Bosc, 52 Colonia Del Palau Barcelona 08740",
    "addr:housenumber":"52",
    "addr:postcode":"08740",
    "addr:street":"Av Del Bosc",
    "iso:country":"ES",
    "sg:address":"Av Del Bosc, 52",
    "sg:city":"Colonia Del Palau",
    "sg:orig_category":"Almacenes Para Venta: Muebles Y Varios",
    "sg:phone":"+34 936 82 31 31",
    "sg:postcode":"08740",
    "sg:province":"Barcelona",
    "wof:name":"Mas I Oliveras Pere",
    "wof:placetype":"venue"
},
  "geometry": {"coordinates":[1.958006978,41.4490814209],"type":"Point"}
}