{
  "type": "Feature",
  "properties": {
    "addr:full":"Av Drassanes, 27 Barcelona Barcelona 08001",
    "addr:housenumber":"27",
    "addr:postcode":"08001",
    "addr:street":"Av Drassanes",
    "iso:country":"ES",
    "sg:address":"Av Drassanes, 27",
    "sg:city":"Barcelona",
    "sg:orig_category":"Asistencia Domiciliaria",
    "sg:phone":"+34 933 29 84 65",
    "sg:postcode":"08001",
    "sg:province":"Barcelona",
    "wof:name":"Lujan Vallverde Juana Edita",
    "wof:placetype":"venue"
},
  "geometry": {"coordinates":[2.172342062,41.3767089844],"type":"Point"}
}