{
  "type": "Feature",
  "properties": {
    "addr:full":"Castanedo, 75 Castanedo Cantabria 39150",
    "addr:housenumber":"75",
    "addr:postcode":"39150",
    "addr:street":"Castanedo",
    "iso:country":"ES",
    "sg:address":"Castanedo, 75",
    "sg:city":"Castanedo",
    "sg:orig_category":"Empresas De Carpinter\u00cda De Madera",
    "sg:phone":"+34 942 50 90 78",
    "sg:postcode":"39150",
    "sg:province":"Cantabria",
    "wof:name":"Aja Acebo Marcelino",
    "wof:placetype":"venue"
},
  "geometry": {"coordinates":[-3.6973183155,43.4481506348],"type":"Point"}
}