{
  "type": "Feature",
  "properties": {
    "iso:country":"ES",
    "sg:address":"Calle de Hnos Espinosa Alfonso, 22",
    "sg:city":"Santa Maria Aguila",
    "sg:orig_category":"Mec\u00c1nico Del Autom\u00d3vil",
    "sg:phone":"+34 950 58 02 21",
    "sg:postcode":"04710",
    "sg:province":"Almer\u00eda",
    "wof:name":"Petrof Petrof Quiril",
    "wof:placetype":"venue"
},
  "geometry": {"coordinates":[-2.7739970684,36.781463623],"type":"Point"}
}