{
  "type": "Feature",
  "properties": {
    "addr:full":"Pque Virgen Del Manzano, 10 Burgos Burgos 09004",
    "addr:housenumber":"10",
    "addr:postcode":"09004",
    "addr:street":"Manzano",
    "iso:country":"ES",
    "sg:address":"Pque Virgen Del Manzano, 10",
    "sg:city":"Burgos",
    "sg:orig_category":"Electrodom\u00c9sticos (al Por Menor)",
    "sg:phone":"+34 947 21 51 41",
    "sg:postcode":"09004",
    "sg:province":"Burgos",
    "wof:name":"Guillermo Y Gabriel Electrodomesticos S.l.",
    "wof:placetype":"venue"
},
  "geometry": {"coordinates":[-3.6928110123,42.3451881409],"type":"Point"}
}