{
  "type": "Feature",
  "properties": {
    "iso:country":"ES",
    "sg:address":"Avda Reyes Catolicos, 18",
    "sg:city":"Burgos",
    "sg:orig_category":"Fotograf\u00cda Art\u00cdstica Y Retratos",
    "sg:phone":"+34 947 22 97 83",
    "sg:postcode":"09005",
    "sg:province":"Burgos",
    "wof:name":"Santiago Gutierrez Mansilla S.c.",
    "wof:placetype":"venue"
},
  "geometry": {"coordinates":[-3.693764925,42.3467597961],"type":"Point"}
}