{
  "type": "Feature",
  "properties": {
    "addr:full":"Ctra Castellar, 544 Terrassa Barcelona 08227",
    "addr:housenumber":"544",
    "addr:postcode":"08227",
    "addr:street":"Ctra Castellar",
    "iso:country":"ES",
    "sg:address":"Ctra Castellar, 544",
    "sg:city":"Terrassa",
    "sg:orig_category":"Electricidad, Electr\u00d3nica: Material Y Suministros (al Por Mayor)",
    "sg:phone":"+34 937 35 02 83",
    "sg:postcode":"08227",
    "sg:province":"Barcelona",
    "wof:name":"Eprom Electronica S.a.",
    "wof:placetype":"venue"
},
  "geometry": {"coordinates":[2.0344409943,41.5781669617],"type":"Point"}
}