{
  "type": "Feature",
  "properties": {
    "addr:full":"Carrer de Victor Balaguer, 27 S. Boi Llobregat Barcelona 08830",
    "addr:housenumber":"27",
    "addr:postcode":"08830",
    "addr:street":"Carrer De Victor Balaguer",
    "iso:country":"ES",
    "sg:address":"Carrer de Victor Balaguer, 27",
    "sg:city":"S. Boi Llobregat",
    "sg:orig_category":"Mantenimiento Industrial",
    "sg:phone":"+34 936 54 39 96",
    "sg:postcode":"08830",
    "sg:province":"Barcelona",
    "wof:name":"Antarys S.l.",
    "wof:placetype":"venue"
},
  "geometry": {"coordinates":[2.0383892059,41.34557724],"type":"Point"}
}