{
  "type": "Feature",
  "properties": {
    "addr:full":"Calle de Calvario-la Orotava (el), 38 Orotava Santa Cruz De Tenerife 38300",
    "addr:postcode":"38300",
    "addr:street":"Calle De Calvario-La;El;Orotava",
    "iso:country":"ES",
    "sg:address":"Calle de Calvario-la Orotava (el), 38",
    "sg:city":"Orotava",
    "sg:orig_category":"Bancos",
    "sg:phone":"+34 922 33 01 66",
    "sg:postcode":"38300",
    "sg:province":"Santa Cruz De Tenerife",
    "wof:name":"Banca March S.a.",
    "wof:placetype":"venue"
},
  "geometry": {"coordinates":[-16.5189990997,28.3903846741],"type":"Point"}
}