{
  "type": "Feature",
  "properties": {
    "addr:full":"Calle de Yunque, 16 Leganes Madrid 28918",
    "addr:housenumber":"16",
    "addr:postcode":"28918",
    "addr:street":"Calle De Yunque",
    "iso:country":"ES",
    "sg:address":"Calle de Yunque, 16",
    "sg:city":"Leganes",
    "sg:orig_category":"Adhesivos (fabricaci\u00d3n, Al Por Mayor)",
    "sg:phone":"+34 916 43 98 25",
    "sg:postcode":"28918",
    "sg:province":"Madrid",
    "wof:name":"Suministros Rayo S.a.",
    "wof:placetype":"venue"
},
  "geometry": {"coordinates":[-3.8008403778,40.3433952332],"type":"Point"}
}