{
  "type": "Feature",
  "properties": {
    "addr:full":"Calle de Independencia, 41 Oviedo Asturias 33004",
    "addr:housenumber":"41",
    "addr:postcode":"33004",
    "addr:street":"Calle De Independencia",
    "iso:country":"ES",
    "sg:address":"Calle de Independencia, 41",
    "sg:city":"Oviedo",
    "sg:orig_category":"Establecimientos De Cura, Prevenci\u00d3n Y Readaptaci\u00d3n",
    "sg:phone":"+34 985 24 58 30",
    "sg:postcode":"33004",
    "sg:province":"Asturias",
    "wof:name":"Rodriguez Colubi Luis Ignacio",
    "wof:placetype":"venue"
},
  "geometry": {"coordinates":[-5.8569850922,43.3644561768],"type":"Point"}
}