{
  "type": "Feature",
  "properties": {
    "addr:full":"Iru-bide, S/n Galdakao Vizcaya 48960",
    "addr:housenumber":"s / n",
    "addr:postcode":"48960",
    "addr:street":"Iru-Bide",
    "iso:country":"ES",
    "sg:address":"Iru-bide, S/n",
    "sg:city":"Galdakao",
    "sg:orig_category":"Agentes, Concesionarios Y Sucursales De Veh\u00cdculos",
    "sg:phone":"+34 944 73 01 43",
    "sg:postcode":"48960",
    "sg:province":"Vizcaya",
    "wof:name":"Turismos Bolueta S. A.",
    "wof:placetype":"venue"
},
  "geometry": {"coordinates":[-2.8676741123,43.2344512939],"type":"Point"}
}