{
  "type": "Feature",
  "properties": {
    "iso:country":"ES",
    "sg:address":"Calle de Brihuega, 25",
    "sg:city":"Madrid",
    "sg:orig_category":"Comidas Por Encargo, Organizaci\u00d3n De Recepciones",
    "sg:phone":"+34 914 71 57 81",
    "sg:postcode":"28019",
    "sg:province":"Madrid",
    "wof:name":"Serini  Marcello",
    "wof:placetype":"venue"
},
  "geometry": {"coordinates":[-3.7354950905,40.3943099976],"type":"Point"}
}