{
  "type": "Feature",
  "properties": {
    "addr:full":"Calle de Julia Minguillon, 3 Coru\u00d1a La Coru\u00f1a 15011",
    "addr:housenumber":"3",
    "addr:postcode":"15011",
    "addr:street":"Calle De Julia Minguillon;La Corun\u0303A",
    "iso:country":"ES",
    "sg:address":"Calle de Julia Minguillon, 3",
    "sg:city":"Coru\u00d1a",
    "sg:orig_category":"Confecci\u00d3n (fabricaci\u00d3n, Al Por Mayor)",
    "sg:phone":"+34 981 25 95 98",
    "sg:postcode":"15011",
    "sg:province":"La Coru\u00f1a",
    "wof:name":"Karpi Confeccion S.l.",
    "wof:placetype":"venue"
},
  "geometry": {"coordinates":[-8.4223356247,43.3652763367],"type":"Point"}
}