{
  "type": "Feature",
  "properties": {
    "iso:country":"ES",
    "sg:address":"Calle de Pablo Mayayo, 36",
    "sg:city":"Algeciras",
    "sg:orig_category":"Abogados",
    "sg:phone":"+34 956 66 63 26",
    "sg:postcode":"11201",
    "sg:province":"C\u00e1diz",
    "wof:name":"Mayor Mensua Maria Luisa",
    "wof:placetype":"venue"
},
  "geometry": {"coordinates":[-5.4461770058,36.1317825317],"type":"Point"}
}