{
  "type": "Feature",
  "properties": {
    "addr:full":"Calle de Virgen, 1 Valdepe\u00f1as Ciudad Real 13300",
    "addr:housenumber":"1",
    "addr:postcode":"13300",
    "addr:street":"Calle De Virgen",
    "iso:country":"ES",
    "sg:address":"Calle de Virgen, 1",
    "sg:city":"Valdepe\u00f1as",
    "sg:orig_category":"Transportes Por Carretera: Lotes Completos, Mercanc\u00cdas Diversas",
    "sg:phone":"+34 926 32 20 91",
    "sg:postcode":"13300",
    "sg:province":"Ciudad Real",
    "wof:name":"Donado Pintado Roman",
    "wof:placetype":"venue"
},
  "geometry": {"coordinates":[-3.3907949924,38.7514343262],"type":"Point"}
}