{
  "type": "Feature",
  "properties": {
    "addr:full":"Calle de Canalejas, 12 Almoradi Alicante 03160",
    "addr:housenumber":"12",
    "addr:postcode":"03160",
    "addr:street":"Calle De Canalejas",
    "iso:country":"ES",
    "sg:address":"Calle de Canalejas, 12",
    "sg:city":"Almoradi",
    "sg:orig_category":"Librer\u00cdas",
    "sg:phone":"+34 965 70 00 59",
    "sg:postcode":"03160",
    "sg:province":"Alicante",
    "wof:name":"Grima Librerias Y Papelerias C.b.",
    "wof:placetype":"venue"
},
  "geometry": {"coordinates":[-0.7920203209,38.111076355],"type":"Point"}
}