{
  "type": "Feature",
  "properties": {
    "iso:country":"ES",
    "sg:address":"Pl Esperanto, 3",
    "sg:city":"Castelldefels",
    "sg:orig_category":"Promotores Constructores",
    "sg:phone":"+34 936 64 43 10",
    "sg:postcode":"08860",
    "sg:province":"Barcelona",
    "wof:name":"Excavaciones Castellfranc S.l.",
    "wof:placetype":"venue"
},
  "geometry": {"coordinates":[1.9824529886,41.2818183899],"type":"Point"}
}