{
  "type": "Feature",
  "properties": {
    "addr:full":"Calle de Veintitres De Mayo, S/n Puebla Del Principe Ciudad Real 13342",
    "addr:housenumber":"s / n",
    "addr:postcode":"13342",
    "addr:street":"Calle De Veintitres De Mayo;Del Principe",
    "iso:country":"ES",
    "sg:address":"Calle de Veintitres De Mayo, S/n",
    "sg:city":"Puebla Del Principe",
    "sg:orig_category":"Centros De Educaci\u00d3n Especial",
    "sg:phone":"+34 926 35 90 66",
    "sg:postcode":"13342",
    "sg:province":"Ciudad Real",
    "wof:name":"Colegio Nacional Miguel Gonzalez Calero",
    "wof:placetype":"venue"
},
  "geometry": {"coordinates":[-2.9272990227,38.5675048828],"type":"Point"}
}