{
  "type": "Feature",
  "properties": {
    "iso:country":"ES",
    "sg:address":"Plaz Teniente Linares, 10",
    "sg:city":"Orihuela",
    "sg:orig_category":"\u00d3ptica: Instrumentos (fabricaci\u00d3n)",
    "sg:phone":"+34 965 30 07 79",
    "sg:postcode":"03300",
    "sg:province":"Alicante",
    "wof:name":"Peralta Rodriguez Julio Joaquin",
    "wof:placetype":"venue"
},
  "geometry": {"coordinates":[-0.9453849792,38.0860328674],"type":"Point"}
}