{
  "type": "Feature",
  "properties": {
    "addr:full":"C/ Trinquet, 5 Elche Alicante 03202",
    "addr:housenumber":"5",
    "addr:postcode":"03202",
    "addr:street":"C / Trinquet",
    "iso:country":"ES",
    "sg:address":"C/ Trinquet, 5",
    "sg:city":"Elche",
    "sg:orig_category":"Ense\u00d1anza Variada",
    "sg:phone":"+34 965 45 46 50",
    "sg:postcode":"03202",
    "sg:province":"Alicante",
    "wof:name":"Centro De Formacion Profesional Europa S",
    "wof:placetype":"venue"
},
  "geometry": {"coordinates":[-0.6966509819,38.2668533325],"type":"Point"}
}