{
  "type": "Feature",
  "properties": {
    "addr:full":"Avda Andalucia, 54 Salar Granada 18310",
    "addr:housenumber":"54",
    "addr:postcode":"18310",
    "addr:street":"Avda Andalucia;Granada",
    "iso:country":"ES",
    "sg:address":"Avda Andalucia, 54",
    "sg:city":"Salar",
    "sg:orig_category":"Administraciones Regionales, Departamentales Y Locales",
    "sg:phone":"+34 958 31 60 61",
    "sg:postcode":"18310",
    "sg:province":"Granada",
    "wof:name":"Ayuntamiento De Salar",
    "wof:placetype":"venue"
},
  "geometry": {"coordinates":[-4.0668392181,37.1522827148],"type":"Point"}
}