{
  "type": "Feature",
  "properties": {
    "addr:full":"Av Marina, 1 S. Boi Llobregat Barcelona 08830",
    "addr:housenumber":"1",
    "addr:postcode":"08830",
    "addr:street":"Av Marina",
    "iso:country":"ES",
    "sg:address":"Av Marina, 1",
    "sg:city":"S. Boi Llobregat",
    "sg:orig_category":"Fabricaci\u00d3n, Instalaci\u00d3n De Armarios",
    "sg:phone":"+34 936 30 33 73",
    "sg:postcode":"08830",
    "sg:province":"Barcelona",
    "sg:website":"www.desmon.com",
    "wof:name":"Armariosarkas.a.",
    "wof:placetype":"venue"
},
  "geometry": {"coordinates":[2.0516281128,41.3342590332],"type":"Point"}
}