{
  "type": "Feature",
  "properties": {
    "addr:full":"Avda Ruiz Jarabo, 13 Teruel Teruel 44002",
    "addr:housenumber":"13",
    "addr:postcode":"44002",
    "addr:street":"Avda Ruiz Jarabo",
    "iso:country":"ES",
    "sg:address":"Avda Ruiz Jarabo, 13",
    "sg:city":"Teruel",
    "sg:orig_category":"Doctores En Medicina",
    "sg:phone":"+34 978 62 00 55",
    "sg:postcode":"44002",
    "sg:province":"Teruel",
    "wof:name":"Esteban Gomez Gregorio Luis",
    "wof:placetype":"venue"
},
  "geometry": {"coordinates":[-1.1081730127,40.3321609497],"type":"Point"}
}