{
  "type": "Feature",
  "properties": {
    "iso:country":"ES",
    "sg:address":"Avda Guadalajara, 1",
    "sg:city":"Madrid",
    "sg:orig_category":"Fabricaci\u00d3n, Importaci\u00d3n, Venta De Material De Telefon\u00cda, Peritelefon\u00cda",
    "sg:phone":"+34 913 06 52 91",
    "sg:postcode":"28032",
    "sg:province":"Madrid",
    "wof:name":"Offi Telefonia S.a.",
    "wof:placetype":"venue"
},
  "geometry": {"coordinates":[-3.6228170395,40.4187011719],"type":"Point"}
}