{
  "type": "Feature",
  "properties": {
    "addr:full":"Carrer de Pou, 61 Calafell Tarragona 43820",
    "addr:housenumber":"61",
    "addr:postcode":"43820",
    "addr:street":"Carrer De Pou",
    "iso:country":"ES",
    "sg:address":"Carrer de Pou, 61",
    "sg:city":"Calafell",
    "sg:orig_category":"Cerrajer\u00cda, Ferrallista",
    "sg:phone":"+34 977 69 52 88",
    "sg:postcode":"43820",
    "sg:province":"Tarragona",
    "wof:name":"Gomez Martinez Juan",
    "wof:placetype":"venue"
},
  "geometry": {"coordinates":[1.5719300508,41.1980018616],"type":"Point"}
}