{
  "type": "Feature",
  "properties": {
    "iso:country":"ES",
    "sg:address":"Av En Joan Carles I, 12",
    "sg:city":"Elche",
    "sg:orig_category":"Asociaciones, Organismos Culturales Y Socioeducativos",
    "sg:phone":"+34 965 45 50 63",
    "sg:postcode":"03203",
    "sg:province":"Alicante",
    "wof:name":"Club De Leones De Elche",
    "wof:placetype":"venue"
},
  "geometry": {"coordinates":[-0.6944019794,38.2664833069],"type":"Point"}
}