{
  "type": "Feature",
  "properties": {
    "addr:full":"Carrer de Felipe De Paz, 17 Barcelona Barcelona 08028",
    "addr:housenumber":"17",
    "addr:postcode":"08028",
    "addr:street":"Carrer De Felipe De Paz",
    "iso:country":"ES",
    "sg:address":"Carrer de Felipe De Paz, 17",
    "sg:city":"Barcelona",
    "sg:orig_category":"Distribuci\u00d3n De Petr\u00d3leo Y Derivados",
    "sg:phone":"+34 934 90 12 89",
    "sg:postcode":"08028",
    "sg:province":"Barcelona",
    "wof:name":"El Raco Del Pallars S.l.",
    "wof:placetype":"venue"
},
  "geometry": {"coordinates":[2.1256558895,41.3791122437],"type":"Point"}
}