{
  "type": "Feature",
  "properties": {
    "iso:country":"ES",
    "sg:address":"Avda Pumarin De, 36",
    "sg:city":"Oviedo",
    "sg:orig_category":"Panader\u00cdas, Panader\u00cdas",
    "sg:phone":"+34 985 29 85 63",
    "sg:postcode":"33011",
    "sg:province":"Asturias",
    "wof:name":"Prieto Andres Jose Maria",
    "wof:placetype":"venue"
},
  "geometry": {"coordinates":[-5.8437209129,43.3687477112],"type":"Point"}
}