{
  "type": "Feature",
  "properties": {
    "iso:country":"ES",
    "sg:address":"Calle de Real, S/n",
    "sg:city":"Campillos",
    "sg:orig_category":"Negocio De Materiales De Construcci\u00d3n",
    "sg:phone":"+34 952 72 20 63",
    "sg:postcode":"29320",
    "sg:province":"M\u00e1laga",
    "wof:name":"Hermanas Gallardo Pineda C.b.",
    "wof:placetype":"venue"
},
  "geometry": {"coordinates":[-4.8613238335,37.0483398438],"type":"Point"}
}