{
  "type": "Feature",
  "properties": {
    "iso:country":"ES",
    "sg:address":"Carr Primitiu Artigas, 17",
    "sg:city":"Cassa Selva",
    "sg:orig_category":"Contenedores (mercanc\u00cdas)",
    "sg:phone":"+34 972 46 03 41",
    "sg:postcode":"17244",
    "sg:province":"Girona",
    "wof:name":"Gibert Tarres Pedro",
    "wof:placetype":"venue"
},
  "geometry": {"coordinates":[2.8756868839,41.8858833313],"type":"Point"}
}