{
  "type": "Feature",
  "properties": {
    "addr:full":"Calle de Luis Chamizo, 13 Logrosan C\u00e1ceres 10120",
    "addr:housenumber":"13",
    "addr:postcode":"10120",
    "addr:street":"Calle De Luis Chamizo;Ca\u0301Ceres",
    "iso:country":"ES",
    "sg:address":"Calle de Luis Chamizo, 13",
    "sg:city":"Logrosan",
    "sg:orig_category":"Material Y Suministros Para Perforaciones, Sondeos",
    "sg:phone":"+34 927 36 04 77",
    "sg:postcode":"10120",
    "sg:province":"C\u00e1ceres",
    "wof:name":"Rebollo Cortijo Juan Jose",
    "wof:placetype":"venue"
},
  "geometry": {"coordinates":[-5.4919610023,39.3375968933],"type":"Point"}
}