{
  "type": "Feature",
  "properties": {
    "addr:full":"Alcora, 24 Castello Plana Castell\u00f3n 12006",
    "addr:housenumber":"24",
    "addr:postcode":"12006",
    "addr:street":"Alcora;Castello\u0301N",
    "iso:country":"ES",
    "sg:address":"Alcora, 24",
    "sg:city":"Castello Plana",
    "sg:orig_category":"Comercio De Piezas De Recambio Y De Accesorios De Veh\u00cdculos, Veh\u00cdculos Industriales",
    "sg:phone":"+34 964 25 72 57",
    "sg:postcode":"12006",
    "sg:province":"Castell\u00f3n",
    "wof:name":"Amadeo Marti Carbonell S. A.",
    "wof:placetype":"venue"
},
  "geometry": {"coordinates":[-0.0522348993,39.9858894348],"type":"Point"}
}