{
  "type": "Feature",
  "properties": {
    "addr:full":"Pl. B. Navarra, 10 Iru\u00f1a Navarra 31004",
    "addr:housenumber":"10",
    "addr:postcode":"31004",
    "addr:street":"Irun\u0303A Navarra",
    "iso:country":"ES",
    "sg:address":"Pl. B. Navarra, 10",
    "sg:city":"Iru\u00f1a",
    "sg:orig_category":"Comercio De Mobiliario De Oficina",
    "sg:phone":"+34 948 23 66 44",
    "sg:postcode":"31004",
    "sg:province":"Navarra",
    "sg:website":"www.navarra.2000.com",
    "wof:name":"Papeleria Sancho's S.l.",
    "wof:placetype":"venue"
},
  "geometry": {"coordinates":[-1.6351699829,42.8118286133],"type":"Point"}
}