{
  "type": "Feature",
  "properties": {
    "addr:full":"Ctra Sur, S/n S. Agustin-playa Ingles Las Palmas 35100",
    "addr:housenumber":"s",
    "addr:postcode":"35100",
    "addr:street":"Ctra Sur;/ N S. Agustin-Playa",
    "iso:country":"ES",
    "sg:address":"Ctra Sur, S/n",
    "sg:city":"S. Agustin-playa Ingles",
    "sg:orig_category":"Venta, Instalaci\u00d3n, Reparaci\u00d3n De Antenas Para Televisi\u00d3n",
    "sg:phone":"+34 928 77 77 77",
    "sg:postcode":"35100",
    "sg:province":"Las Palmas",
    "wof:name":"Telepastel Strudel Scp",
    "wof:placetype":"venue"
},
  "geometry": {"coordinates":[-15.4397096634,28.1302204132],"type":"Point"}
}