{
  "type": "Feature",
  "properties": {
    "addr:full":"Pl Constitucio, 1 Rubi Barcelona 08191",
    "addr:housenumber":"1",
    "addr:postcode":"08191",
    "addr:street":"Pl Constitucio",
    "iso:country":"ES",
    "sg:address":"Pl Constitucio, 1",
    "sg:city":"Rubi",
    "sg:orig_category":"Ropa Para Ni\u00d1os (al Por Menor)",
    "sg:phone":"+34 936 97 22 62",
    "sg:postcode":"08191",
    "sg:province":"Barcelona",
    "wof:name":"Marian Modas",
    "wof:placetype":"venue"
},
  "geometry": {"coordinates":[2.0311610699,41.4842948914],"type":"Point"}
}