{
  "type": "Feature",
  "properties": {
    "iso:country":"ES",
    "sg:address":"Carrer de Sol, 11",
    "sg:city":"Ondara",
    "sg:orig_category":"Cueros Y Pieles (al Por Mayor)",
    "sg:phone":"+34 966 47 60 94",
    "sg:postcode":"03760",
    "sg:province":"Alicante",
    "wof:name":"Maru Marroq S.l.",
    "wof:placetype":"venue"
},
  "geometry": {"coordinates":[0.0194099993,38.8281745911],"type":"Point"}
}