{
  "type": "Feature",
  "properties": {
    "iso:country":"ES",
    "sg:address":"Carrer de Mare De Deu Dels Angels, 16",
    "sg:city":"Santa Coloma De Gramenet",
    "sg:orig_category":"Extinci\u00d3n De Incendios: Material Y Suministros (fabricaci\u00d3n, Al Por Mayor)",
    "sg:phone":"+34 933 85 89 54",
    "sg:postcode":"08921",
    "sg:province":"Barcelona",
    "wof:name":"Extintores Servi Foc S.l.",
    "wof:placetype":"venue"
},
  "geometry": {"coordinates":[2.2033100128,41.4525642395],"type":"Point"}
}