{
  "type": "Feature",
  "properties": {
    "iso:country":"ES",
    "sg:address":"Avda Andalucia (de), S/n",
    "sg:city":"Alcala Real",
    "sg:orig_category":"Cajas De Ahorro",
    "sg:phone":"+34 953 58 48 72",
    "sg:postcode":"23680",
    "sg:province":"Ja\u00e9n",
    "sg:website":"www.unicaja.es",
    "wof:name":"Unicaja",
    "wof:placetype":"venue"
},
  "geometry": {"coordinates":[-3.8254740238,37.4174499512],"type":"Point"}
}