{
  "type": "Feature",
  "properties": {
    "iso:country":"ES",
    "sg:address":"C/ Major, 119",
    "sg:city":"Salt",
    "sg:orig_category":"Quincaller\u00cda (al Por Menor)",
    "sg:phone":"+34 972 23 93 59",
    "sg:postcode":"17190",
    "sg:province":"Girona",
    "wof:name":"Antoner Vivolas Jose",
    "wof:placetype":"venue"
},
  "geometry": {"coordinates":[2.7889397144,41.9746856689],"type":"Point"}
}