{
  "type": "Feature",
  "properties": {
    "iso:country":"ES",
    "sg:address":"Calle de San Anton, 24",
    "sg:city":"Logro\u00f1o",
    "sg:orig_category":"Alimentaci\u00d3n General (al Por Menor)",
    "sg:phone":"+34 941 24 35 82",
    "sg:postcode":"26002",
    "sg:province":"La Rioja",
    "wof:name":"Ruiz Temi\u00f1o Evedio",
    "wof:placetype":"venue"
},
  "geometry": {"coordinates":[-2.4466090202,42.4610443115],"type":"Point"}
}