{
  "type": "Feature",
  "properties": {
    "addr:full":"Pl Pins, 5 Roca Valles Barcelona 08430",
    "addr:housenumber":"5",
    "addr:postcode":"08430",
    "addr:street":"Pl Pins;Barcelona",
    "iso:country":"ES",
    "sg:address":"Pl Pins, 5",
    "sg:city":"Roca Valles",
    "sg:orig_category":"Controles De Edificaci\u00d3n (construcci\u00d3n, Seguridad)",
    "sg:phone":"+34 938 42 05 13",
    "sg:postcode":"08430",
    "sg:province":"Barcelona",
    "wof:name":"Obras Garcia Valdivia S.l.",
    "wof:placetype":"venue"
},
  "geometry": {"coordinates":[2.3770260811,41.6025276184],"type":"Point"}
}