{
  "type": "Feature",
  "properties": {
    "addr:full":"Calle de Haba, 8 Villanueva Serena Badajoz 06700",
    "addr:housenumber":"8",
    "addr:postcode":"06700",
    "addr:street":"Calle De Haba",
    "iso:country":"ES",
    "sg:address":"Calle de Haba, 8",
    "sg:city":"Villanueva Serena",
    "sg:orig_category":"Abogados",
    "sg:phone":"+34 924 84 62 91",
    "sg:postcode":"06700",
    "sg:province":"Badajoz",
    "wof:name":"Sanchez Morillo-velarde Maria Jose",
    "wof:placetype":"venue"
},
  "geometry": {"coordinates":[-5.7990198135,38.9718704224],"type":"Point"}
}