{
  "type": "Feature",
  "properties": {
    "addr:full":"Calle de Zahina, 15 Alcala Guadaira Sevilla 41500",
    "addr:housenumber":"15",
    "addr:postcode":"41500",
    "addr:street":"Calle De Zahina",
    "iso:country":"ES",
    "sg:address":"Calle de Zahina, 15",
    "sg:city":"Alcala Guadaira",
    "sg:orig_category":"Maquinaria Para Industrias Diversas",
    "sg:phone":"+34 955 61 15 23",
    "sg:postcode":"41500",
    "sg:province":"Sevilla",
    "wof:name":"Trimaquinaria S.l.",
    "wof:placetype":"venue"
},
  "geometry": {"coordinates":[-5.8461327553,37.3469314575],"type":"Point"}
}