{
  "type": "Feature",
  "properties": {
    "addr:full":"Calle de Magdalena, S/n Castillo Madrid 28850",
    "addr:housenumber":"s",
    "addr:postcode":"28850",
    "addr:street":"Calle De Magdalena;/ N Castillo",
    "iso:country":"ES",
    "sg:address":"Calle de Magdalena, S/n",
    "sg:city":"Castillo",
    "sg:orig_category":"Centros De Educaci\u00d3n Especial",
    "sg:phone":"+34 916 56 56 78",
    "sg:postcode":"28850",
    "sg:province":"Madrid",
    "wof:name":"Comunidad Autonoma De Madrid-centros De Educacion",
    "wof:placetype":"venue"
},
  "geometry": {"coordinates":[-3.4763290882,40.4592514038],"type":"Point"}
}