{
  "type": "Feature",
  "properties": {
    "iso:country":"ES",
    "sg:address":"Av Principat D'andorra, 10",
    "sg:city":"Tarragona",
    "sg:orig_category":"Mec\u00c1nico Del Autom\u00d3vil",
    "sg:phone":"+34 977 22 59 51",
    "sg:postcode":"43002",
    "sg:province":"Tarragona",
    "wof:name":"Cosculluela Fumanal Joaquin Moises",
    "wof:placetype":"venue"
},
  "geometry": {"coordinates":[1.2421449423,41.1258277893],"type":"Point"}
}