{
  "type": "Feature",
  "properties": {
    "iso:country":"ES",
    "sg:address":"Calle de Corredera De San Marcos, 37",
    "sg:city":"Linares",
    "sg:orig_category":"M\u00c9dicos: Medicina General Orientada A La Acupuntura",
    "sg:phone":"+34 953 65 11 62",
    "sg:postcode":"23700",
    "sg:province":"Ja\u00e9n",
    "wof:name":"Quero Rueda Luis Carlos",
    "wof:placetype":"venue"
},
  "geometry": {"coordinates":[-3.6336314678,38.0972480774],"type":"Point"}
}