{
  "type": "Feature",
  "properties": {
    "iso:country":"ES",
    "sg:address":"Calle de Mallorca, 3",
    "sg:city":"Fuengirola",
    "sg:orig_category":"Peluqueros: De Se\u00d1oras",
    "sg:phone":"+34 952 46 68 90",
    "sg:postcode":"29640",
    "sg:province":"M\u00e1laga",
    "wof:name":"Serrano Jimenez Paola",
    "wof:placetype":"venue"
},
  "geometry": {"coordinates":[-4.6285429001,36.5458068848],"type":"Point"}
}