{
  "type": "Feature",
  "properties": {
    "addr:full":"Avda Huesca, 53 Sena Huesca 22230",
    "addr:housenumber":"53",
    "addr:postcode":"22230",
    "addr:street":"Avda Huesca",
    "iso:country":"ES",
    "sg:address":"Avda Huesca, 53",
    "sg:city":"Sena",
    "sg:orig_category":"Plomeros",
    "sg:phone":"+34 974 57 83 74",
    "sg:postcode":"22230",
    "sg:province":"Huesca",
    "wof:name":"Santamaria Palacin Antonio",
    "wof:placetype":"venue"
},
  "geometry": {"coordinates":[-0.0490700006,41.7147216797],"type":"Point"}
}