{
  "type": "Feature",
  "properties": {
    "addr:full":"Calle de Paco Miranda, 13 Malaga M\u00e1laga 29013",
    "addr:housenumber":"13",
    "addr:postcode":"29013",
    "addr:street":"Calle De Paco Miranda;Ma\u0301Laga",
    "iso:country":"ES",
    "sg:address":"Calle de Paco Miranda, 13",
    "sg:city":"Malaga",
    "sg:orig_category":"Ingeniero",
    "sg:phone":"+34 952 25 03 38",
    "sg:postcode":"29013",
    "sg:province":"M\u00e1laga",
    "wof:name":"Ruiz Garcia Emilio Angel",
    "wof:placetype":"venue"
},
  "geometry": {"coordinates":[-4.4167428017,36.7298927307],"type":"Point"}
}