{
  "type": "Feature",
  "properties": {
    "iso:country":"ES",
    "sg:address":"Calle de Suarez Guerra, 63",
    "sg:city":"Santa Cruz De Tenerife",
    "sg:orig_category":"Inmobiliaria (agencias)",
    "sg:phone":"+34 922 24 44 37",
    "sg:postcode":"38002",
    "sg:province":"Santa Cruz De Tenerife",
    "sg:website":"www.domingomoralesruiz.com",
    "wof:name":"Morales Ruiz Domingo",
    "wof:placetype":"venue"
},
  "geometry": {"coordinates":[-16.2510604858,28.4690265656],"type":"Point"}
}