{
  "type": "Feature",
  "properties": {
    "addr:full":"Calle de Albacete, 11 Malaga M\u00e1laga 29010",
    "addr:housenumber":"11",
    "addr:postcode":"29010",
    "addr:street":"Calle De Albacete;Ma\u0301Laga",
    "iso:country":"ES",
    "sg:address":"Calle de Albacete, 11",
    "sg:city":"Malaga",
    "sg:orig_category":"Zapatos (al Por Menor)",
    "sg:phone":"+34 952 39 85 99",
    "sg:postcode":"29010",
    "sg:province":"M\u00e1laga",
    "wof:name":"Aranda Martin Luis",
    "wof:placetype":"venue"
},
  "geometry": {"coordinates":[-4.4443330765,36.7278366089],"type":"Point"}
}