{
  "type": "Feature",
  "properties": {
    "iso:country":"ES",
    "sg:address":"Calle de Doctor Casal, 16",
    "sg:city":"Oviedo",
    "sg:orig_category":"Asociaciones Y Clubs Deportivos",
    "sg:phone":"+34 985 22 29 11",
    "sg:postcode":"33001",
    "sg:province":"Asturias",
    "sg:website":"www.footlocker.com",
    "wof:name":"Foot Locker Spain S.l.",
    "wof:placetype":"venue"
},
  "geometry": {"coordinates":[-5.8502855301,43.3654785156],"type":"Point"}
}