{
  "type": "Feature",
  "properties": {
    "iso:country":"ES",
    "sg:address":"Calle de Barrio Nuevo, S/n",
    "sg:city":"Figueruelas",
    "sg:orig_category":"Autob\u00das (explotaci\u00d3n Y Servicios De)",
    "sg:phone":"+34 976 65 60 04",
    "sg:postcode":"50639",
    "sg:province":"Zaragoza",
    "wof:name":"Leza Fondevilla Fausto",
    "wof:placetype":"venue"
},
  "geometry": {"coordinates":[-1.1791243553,41.7643623352],"type":"Point"}
}