{
  "type": "Feature",
  "properties": {
    "iso:country":"ES",
    "sg:address":"Carr Tramuntana, (de), 11",
    "sg:city":"Carlet",
    "sg:orig_category":"Contenedores (mercanc\u00cdas)",
    "sg:phone":"+34 962 53 82 22",
    "sg:postcode":"46240",
    "sg:province":"Valencia",
    "wof:name":"Francisco Navarro Pardo S.l.",
    "wof:placetype":"venue"
},
  "geometry": {"coordinates":[-0.4892269969,39.2327423096],"type":"Point"}
}