{
  "type": "Feature",
  "properties": {
    "addr:full":"C/ Rocabruna, 27 Ripollet Barcelona 08291",
    "addr:housenumber":"27",
    "addr:postcode":"08291",
    "addr:street":"C / Rocabruna",
    "iso:country":"ES",
    "sg:address":"C/ Rocabruna, 27",
    "sg:city":"Ripollet",
    "sg:orig_category":"Entrega Y Recogida (servicios)",
    "sg:phone":"+34 935 80 78 42",
    "sg:postcode":"08291",
    "sg:province":"Barcelona",
    "wof:name":"Disflove S.l.",
    "wof:placetype":"venue"
},
  "geometry": {"coordinates":[2.1633191109,41.4991378784],"type":"Point"}
}