{
  "type": "Feature",
  "properties": {
    "iso:country":"ES",
    "sg:address":"Pase Catalina De Ribera, 4",
    "sg:city":"Sevilla",
    "sg:orig_category":"Productores Recolectores, Venta Directa De Vinos",
    "sg:phone":"+34 954 41 06 00",
    "sg:postcode":"41004",
    "sg:province":"Sevilla",
    "wof:name":"Vinerias Santelmo S.l.",
    "wof:placetype":"venue"
},
  "geometry": {"coordinates":[-5.9872140884,37.3854408264],"type":"Point"}
}