{
  "type": "Feature",
  "properties": {
    "addr:full":"Calle de Ramon Franco, 203 Arzua La Coru\u00f1a 15810",
    "addr:housenumber":"203",
    "addr:postcode":"15810",
    "addr:street":"Calle De Ramon Franco;La Corun\u0303A",
    "iso:country":"ES",
    "sg:address":"Calle de Ramon Franco, 203",
    "sg:city":"Arzua",
    "sg:orig_category":"Explotaci\u00d3n De Bosques",
    "sg:phone":"+34 981 50 09 86",
    "sg:postcode":"15810",
    "sg:province":"La Coru\u00f1a",
    "wof:name":"Hermanos Souto Sanchez S.l.",
    "wof:placetype":"venue"
},
  "geometry": {"coordinates":[-8.1626787186,42.9319992065],"type":"Point"}
}