{
  "type": "Feature",
  "properties": {
    "iso:country":"ES",
    "sg:address":"Calle de San Vicente, 43",
    "sg:city":"San Vicente De Barakaldo",
    "sg:orig_category":"Perfumer\u00cda (al Por Menor)",
    "sg:phone":"+34 944 37 55 62",
    "sg:postcode":"48902",
    "sg:province":"Vizcaya",
    "wof:name":"Gomez Lopez Maria Victoria",
    "wof:placetype":"venue"
},
  "geometry": {"coordinates":[-2.9949600697,43.2957344055],"type":"Point"}
}