{
  "type": "Feature",
  "properties": {
    "iso:country":"ES",
    "sg:address":"Calle de Santiago Ramon Y Cajal (de), 4",
    "sg:city":"Humanes De Madrid",
    "sg:orig_category":"Inmobiliaria (agencias)",
    "sg:phone":"+34 916 48 11 50",
    "sg:postcode":"28970",
    "sg:province":"Madrid",
    "wof:name":"Estudio Intercasa S.l.",
    "wof:placetype":"venue"
},
  "geometry": {"coordinates":[-3.822024107,40.2585334778],"type":"Point"}
}