{
  "type": "Feature",
  "properties": {
    "iso:country":"ES",
    "sg:address":"Av Mar De La, 55",
    "sg:city":"Bellreguard",
    "sg:orig_category":"Contenedores Para Dep\u00d3sito De Sustancias Peligrosas (fabricaci\u00d3n, Al Por Mayor)",
    "sg:phone":"+34 962 81 63 79",
    "sg:postcode":"46713",
    "sg:province":"Valencia",
    "wof:name":"Forcoma S.l.",
    "wof:placetype":"venue"
},
  "geometry": {"coordinates":[-0.1629119962,38.9464607239],"type":"Point"}
}