{
  "type": "Feature",
  "properties": {
    "addr:full":"Calle de Tablas, 1 Granada Granada 18002",
    "addr:housenumber":"1",
    "addr:postcode":"18002",
    "addr:street":"Calle De Tablas",
    "iso:country":"ES",
    "sg:address":"Calle de Tablas, 1",
    "sg:city":"Granada",
    "sg:orig_category":"Bordado, Marcado A Medida",
    "sg:phone":"+34 958 25 62 01",
    "sg:postcode":"18002",
    "sg:province":"Granada",
    "wof:name":"Lopez Pi\u00f1ero Jaime",
    "wof:placetype":"venue"
},
  "geometry": {"coordinates":[-3.6023495197,37.1761932373],"type":"Point"}
}