{
  "type": "Feature",
  "properties": {
    "iso:country":"ES",
    "sg:address":"Carr Mossen Anton, 56",
    "sg:city":"Badalona",
    "sg:orig_category":"Agencias Y Agentes Comerciales, Representantes",
    "sg:phone":"+34 933 84 36 48",
    "sg:postcode":"08912",
    "sg:province":"Barcelona",
    "wof:name":"Representacions Alimentarias Ma\u00f1e S.c.p.",
    "wof:placetype":"venue"
},
  "geometry": {"coordinates":[2.2466249466,41.4452018738],"type":"Point"}
}