{
  "type": "Feature",
  "properties": {
    "addr:full":"Carr Anselm Charles, 9 Lleida Lleida 25005",
    "addr:housenumber":"9",
    "addr:postcode":"25005",
    "addr:street":"Carr Anselm Charles",
    "iso:country":"ES",
    "sg:address":"Carr Anselm Charles, 9",
    "sg:city":"Lleida",
    "sg:orig_category":"Ropa Para Se\u00d1oras Y Caballeros (al Por Menor)",
    "sg:phone":"+34 973 23 97 38",
    "sg:postcode":"25005",
    "sg:province":"Lleida",
    "wof:name":"Lopez Lopez Maria Rosa",
    "wof:placetype":"venue"
},
  "geometry": {"coordinates":[0.6375100017,41.6267089844],"type":"Point"}
}