{
  "type": "Feature",
  "properties": {
    "addr:full":"Carrer de Moli, 35 Hospitalet Llobregat Barcelona 08906",
    "addr:housenumber":"35",
    "addr:postcode":"08906",
    "addr:street":"Carrer De Moli",
    "iso:country":"ES",
    "sg:address":"Carrer de Moli, 35",
    "sg:city":"Hospitalet Llobregat",
    "sg:orig_category":"Bazares, Art\u00cdculos De Limpieza Y De Cocina (al Por Menor)",
    "sg:phone":"+34 934 37 81 67",
    "sg:postcode":"08906",
    "sg:province":"Barcelona",
    "wof:name":"Pe\u00f1albert Herrera Julio",
    "wof:placetype":"venue"
},
  "geometry": {"coordinates":[2.1015820503,41.367893219],"type":"Point"}
}