{
  "type": "Feature",
  "properties": {
    "addr:full":"Avda Duque De Arcos, 3 Arcos Frontera C\u00e1diz 11630",
    "addr:housenumber":"3",
    "addr:postcode":"11630",
    "addr:street":"Avda Duque De Arcos",
    "iso:country":"ES",
    "sg:address":"Avda Duque De Arcos, 3",
    "sg:city":"Arcos Frontera",
    "sg:orig_category":"Electricidad: Equipos Industriales, Componentes (fabricaci\u00d3n)",
    "sg:phone":"+34 956 70 33 02",
    "sg:postcode":"11630",
    "sg:province":"C\u00e1diz",
    "wof:name":"La Agraria Arcense S.l.",
    "wof:placetype":"venue"
},
  "geometry": {"coordinates":[-5.8179864883,36.7502822876],"type":"Point"}
}