{
  "type": "Feature",
  "properties": {
    "iso:country":"ES",
    "sg:address":"Urb Tropicana Dos, 40",
    "sg:city":"Almu\u00f1ecar",
    "sg:orig_category":"M\u00c9dicos: Pediatr\u00cda. Enfermedades De Los Ni\u00d1os",
    "sg:phone":"+34 958 63 54 68",
    "sg:postcode":"18690",
    "sg:province":"Granada",
    "wof:name":"Vega Lopez Soledad",
    "wof:placetype":"venue"
},
  "geometry": {"coordinates":[-3.6808969975,36.7321929932],"type":"Point"}
}