{
  "type": "Feature",
  "properties": {
    "iso:country":"ES",
    "sg:address":"Carr Pompeu Fabra, 20",
    "sg:city":"Albages",
    "sg:orig_category":"Farmacias",
    "sg:phone":"+34 973 12 10 88",
    "sg:postcode":"25155",
    "sg:province":"Lleida",
    "wof:name":"Aluja Gine Montserrat",
    "wof:placetype":"venue"
},
  "geometry": {"coordinates":[0.7402896881,41.4477958679],"type":"Point"}
}