{
  "type": "Feature",
  "properties": {
    "iso:country":"ES",
    "sg:address":"Carr Sant Antoni Maria Claret, S/n",
    "sg:city":"Bellvis",
    "sg:orig_category":"Empresarios",
    "sg:phone":"+34 973 56 55 00",
    "sg:postcode":"25142",
    "sg:province":"Lleida",
    "wof:name":"Oro Miquel Jaime",
    "wof:placetype":"venue"
},
  "geometry": {"coordinates":[0.8191450238,41.6749305725],"type":"Point"}
}