{
  "type": "Feature",
  "properties": {
    "addr:full":"Carrer de Marina, 43 Barcelona Barcelona 08005",
    "addr:housenumber":"43",
    "addr:postcode":"08005",
    "addr:street":"Carrer De Marina",
    "iso:country":"ES",
    "sg:address":"Carrer de Marina, 43",
    "sg:city":"Barcelona",
    "sg:orig_category":"Transportes Por V\u00cdas Navegables",
    "sg:phone":"+34 932 21 11 27",
    "sg:postcode":"08005",
    "sg:province":"Barcelona",
    "wof:name":"Transportes Ferrolanos Montero S.l.",
    "wof:placetype":"venue"
},
  "geometry": {"coordinates":[2.1920239925,41.3907394409],"type":"Point"}
}