{
  "type": "Feature",
  "properties": {
    "addr:full":"Avda San Jose, 5 Zaragoza Zaragoza 50013",
    "addr:housenumber":"5",
    "addr:postcode":"50013",
    "addr:street":"Avda San Jose",
    "iso:country":"ES",
    "sg:address":"Avda San Jose, 5",
    "sg:city":"Zaragoza",
    "sg:orig_category":"Peluquer\u00cdas, Peluquer\u00cda Mixta",
    "sg:phone":"+34 976 13 35 81",
    "sg:postcode":"50013",
    "sg:province":"Zaragoza",
    "wof:name":"Paulastar S.l.",
    "wof:placetype":"venue"
},
  "geometry": {"coordinates":[-0.8721479774,41.6459274292],"type":"Point"}
}