{
  "type": "Feature",
  "properties": {
    "iso:country":"ES",
    "sg:address":"Pg Sunyer, 1",
    "sg:city":"Reus",
    "sg:orig_category":"Agentes Generales De Seguros",
    "sg:phone":"+34 977 31 05 95",
    "sg:postcode":"43202",
    "sg:province":"Tarragona",
    "wof:name":"Carnicer Tobias Francesc",
    "wof:placetype":"venue"
},
  "geometry": {"coordinates":[1.1019200087,41.1564483643],"type":"Point"}
}