{
  "type": "Feature",
  "properties": {
    "addr:full":"Carrer de Joan Grau, 31 Borras Barcelona 08296",
    "addr:housenumber":"31",
    "addr:postcode":"08296",
    "addr:street":"Carrer De Joan Grau;Barcelona",
    "iso:country":"ES",
    "sg:address":"Carrer de Joan Grau, 31",
    "sg:city":"Borras",
    "sg:orig_category":"Flores Y Plantas Naturales (al Por Mayor)",
    "sg:phone":"+34 938 28 23 30",
    "sg:postcode":"08296",
    "sg:province":"Barcelona",
    "wof:name":"Bueno Ruiz Remedios",
    "wof:placetype":"venue"
},
  "geometry": {"coordinates":[1.8607000113,41.6295089722],"type":"Point"}
}