{
  "type": "Feature",
  "properties": {
    "addr:full":"Calle de Velazquez, 19 Madrid Madrid 28001",
    "addr:housenumber":"19",
    "addr:postcode":"madrid;28001",
    "addr:street":"Calle De Velazquez",
    "iso:country":"ES",
    "sg:address":"Calle de Velazquez, 19",
    "sg:city":"Madrid",
    "sg:orig_category":"Asesor\u00cda Sobre Comunicaci\u00d3n De Empresas",
    "sg:phone":"+34 914 02 44 07",
    "sg:postcode":"28001",
    "sg:province":"Madrid",
    "wof:name":"Audilex Auditores S.l.",
    "wof:placetype":"venue"
},
  "geometry": {"coordinates":[-3.6844611168,40.4232940674],"type":"Point"}
}