{
  "type": "Feature",
  "properties": {
    "iso:country":"ES",
    "sg:address":"Calle de Ildefonso Manuel Gil, 12",
    "sg:city":"Zaragoza",
    "sg:orig_category":"Perfumer\u00cda (al Por Menor)",
    "sg:phone":"+34 976 73 03 56",
    "sg:postcode":"50015",
    "sg:province":"Zaragoza",
    "wof:name":"Asfar Hawaly Mustafa",
    "wof:placetype":"venue"
},
  "geometry": {"coordinates":[-0.8873270154,41.6715278625],"type":"Point"}
}