{
  "type": "Feature",
  "properties": {
    "iso:country":"ES",
    "sg:address":"Calle de Juan Frances De Iribarren, 19",
    "sg:city":"Sang\u00fcesa",
    "sg:orig_category":"Energ\u00cda Solar Y Nuevas Energ\u00cdas (equipo, Estudios)",
    "sg:phone":"+34 948 43 01 91",
    "sg:postcode":"31400",
    "sg:province":"Navarra",
    "wof:name":"Rabal Lopez Pedro",
    "wof:placetype":"venue"
},
  "geometry": {"coordinates":[-1.2793090343,42.5757217407],"type":"Point"}
}