{
  "type": "Feature",
  "properties": {
    "iso:country":"ES",
    "sg:address":"Calle de Caruana, 15",
    "sg:city":"Sagunt",
    "sg:orig_category":"Asesor\u00cda Fiscal Y Jur\u00cddica",
    "sg:phone":"+34 962 66 28 23",
    "sg:postcode":"46500",
    "sg:province":"Valencia",
    "wof:name":"Jomarbe Asesores S.l.",
    "wof:placetype":"venue"
},
  "geometry": {"coordinates":[-0.2741150856,39.6797027588],"type":"Point"}
}