{
  "type": "Feature",
  "properties": {
    "addr:full":"Calle de Conchita Piquer, S/n Alberic Valencia 46260",
    "addr:housenumber":"s / n",
    "addr:postcode":"46260",
    "addr:street":"Calle De;Piquer",
    "iso:country":"ES",
    "sg:address":"Calle de Conchita Piquer, S/n",
    "sg:city":"Alberic",
    "sg:orig_category":"Promotores Constructores",
    "sg:phone":"+34 962 44 25 09",
    "sg:postcode":"46260",
    "sg:province":"Valencia",
    "wof:name":"Inmoval 99 S.l.",
    "wof:placetype":"venue"
},
  "geometry": {"coordinates":[-0.5208284259,39.1215896606],"type":"Point"}
}