{
  "type": "Feature",
  "properties": {
    "addr:full":"Avda Cid Campeador, 2 Burgos Burgos 09005",
    "addr:housenumber":"2",
    "addr:postcode":"09005",
    "addr:street":"Avda Cid Campeador",
    "iso:country":"ES",
    "sg:address":"Avda Cid Campeador, 2",
    "sg:city":"Burgos",
    "sg:orig_category":"Molduras, Junquillos, Listones Y Molduras Perforadas",
    "sg:phone":"+34 947 27 80 14",
    "sg:postcode":"09005",
    "sg:province":"Burgos",
    "wof:name":"Gutierrez Carrera Maria Mercedes",
    "wof:placetype":"venue"
},
  "geometry": {"coordinates":[-3.6980009079,42.3451805115],"type":"Point"}
}