{
  "type": "Feature",
  "properties": {
    "addr:full":"Port Torredembarra, 1 Torredembarra Tarragona 43830",
    "addr:housenumber":"1",
    "addr:postcode":"43830",
    "addr:street":"Torredembarra",
    "iso:country":"ES",
    "sg:address":"Port Torredembarra, 1",
    "sg:city":"Torredembarra",
    "sg:orig_category":"Deportes N\u00c1uticos, Acu\u00c1ticos Y Subacu\u00c1ticos: Art\u00cdculos Y Equipo (al Por Menor)",
    "sg:phone":"+34 977 64 04 25",
    "sg:postcode":"43830",
    "sg:province":"Tarragona",
    "wof:name":"Gutierrez Garcia Jesus",
    "wof:placetype":"venue"
},
  "geometry": {"coordinates":[1.395424962,41.1436691284],"type":"Point"}
}