{
  "type": "Feature",
  "properties": {
    "addr:full":"Rond Castillo, S/n Olite Navarra 31390",
    "addr:housenumber":"s / n",
    "addr:postcode":"31390",
    "addr:street":"Rond Castillo",
    "iso:country":"ES",
    "sg:address":"Rond Castillo, S/n",
    "sg:city":"Olite",
    "sg:orig_category":"Arte, Cultura, Edici\u00d3n",
    "sg:phone":"+34 948 74 00 35",
    "sg:postcode":"31390",
    "sg:province":"Navarra",
    "wof:name":"Opnatel",
    "wof:placetype":"venue"
},
  "geometry": {"coordinates":[-1.6516640186,42.4829597473],"type":"Point"}
}