{
  "type": "Feature",
  "properties": {
    "iso:country":"ES",
    "sg:address":"Lizeaga Kalea, 2",
    "sg:city":"Hernani",
    "sg:orig_category":"Peluquer\u00cdas, Peluquer\u00cda Mixta",
    "sg:phone":"+34 943 33 07 33",
    "sg:postcode":"20120",
    "sg:province":"Guip\u00f9zcoa",
    "wof:name":"Gotzone Azkue Loinaz",
    "wof:placetype":"venue"
},
  "geometry": {"coordinates":[-1.9763530493,43.2648391724],"type":"Point"}
}