{
  "type": "Feature",
  "properties": {
    "iso:country":"ES",
    "sg:address":"Calle de Carril Del Picon, 22",
    "sg:city":"Granada",
    "sg:orig_category":"Farmacias",
    "sg:phone":"+34 958 27 85 02",
    "sg:postcode":"18002",
    "sg:province":"Granada",
    "wof:name":"Islan Molero Maria Del Dulce Nombre",
    "wof:placetype":"venue"
},
  "geometry": {"coordinates":[-3.6051464081,37.176651001],"type":"Point"}
}