{
  "type": "Feature",
  "properties": {
    "iso:country":"ES",
    "sg:address":"Avda Oviedo, 19",
    "sg:city":"Alacant",
    "sg:orig_category":"Andamiajes Y Escaleras De Mano (fabricaci\u00d3n, Al Por Mayor)",
    "sg:phone":"+34 965 26 27 90",
    "sg:postcode":"03540",
    "sg:province":"Alicante",
    "wof:name":"Layher S.a.",
    "wof:placetype":"venue"
},
  "geometry": {"coordinates":[-0.4182319939,38.3768501282],"type":"Point"}
}