{
  "type": "Feature",
  "properties": {
    "addr:full":"Calle de Herradero, 3 Arenas San Pedro \u00c1vila 05400",
    "addr:housenumber":"3",
    "addr:postcode":"05400",
    "addr:street":"Calle De Herradero;A\u0301Vila",
    "iso:country":"ES",
    "sg:address":"Calle de Herradero, 3",
    "sg:city":"Arenas San Pedro",
    "sg:orig_category":"Servicio De Salud",
    "sg:phone":"+34 920 37 06 81",
    "sg:postcode":"05400",
    "sg:province":"\u00c1vila",
    "wof:name":"Aquagest S.a.",
    "wof:placetype":"venue"
},
  "geometry": {"coordinates":[-5.086004734,40.2095108032],"type":"Point"}
}