{
  "type": "Feature",
  "properties": {
    "iso:country":"ES",
    "sg:address":"Calle de Los Herran, 84",
    "sg:city":"Vitoria-gasteiz",
    "sg:orig_category":"Radiocomunicaciones, Telefon\u00cda M\u00d3vil, Radiomensajer\u00cda: Servicios, Comercializaci\u00d3n",
    "sg:phone":"+34 945 28 64 19",
    "sg:postcode":"01002",
    "sg:province":"\u00c1lava",
    "wof:name":"Telmulti S.l.",
    "wof:placetype":"venue"
},
  "geometry": {"coordinates":[-2.6660621166,42.8519668579],"type":"Point"}
}