{
  "type": "Feature",
  "properties": {
    "addr:full":"Rua Coru\u00d1a (a), 22 Barco Ourense 32300",
    "addr:housenumber":"22",
    "addr:postcode":"32300",
    "addr:street":"Rua Corun\u0303A A",
    "iso:country":"ES",
    "sg:address":"Rua Coru\u00d1a (a), 22",
    "sg:city":"Barco",
    "sg:orig_category":"Ense\u00d1anza Secundaria: Colegios Y Escuelas Privadas",
    "sg:phone":"+34 988 32 09 31",
    "sg:postcode":"32300",
    "sg:province":"Ourense",
    "wof:name":"Instituto De Ensino Secundario Martaguis",
    "wof:placetype":"venue"
},
  "geometry": {"coordinates":[-6.9837059975,42.4104614258],"type":"Point"}
}