{
  "type": "Feature",
  "properties": {
    "addr:full":"Calle de Copenhague, 2 Torrejon Ardoz Madrid 28850",
    "addr:housenumber":"2",
    "addr:postcode":"28850",
    "addr:street":"Calle De Copenhague",
    "iso:country":"ES",
    "sg:address":"Calle de Copenhague, 2",
    "sg:city":"Torrejon Ardoz",
    "sg:orig_category":"Peluqueros: De Se\u00d1oras",
    "sg:phone":"+34 916 76 10 77",
    "sg:postcode":"28850",
    "sg:province":"Madrid",
    "wof:name":"Gonzalez Gonzalez Paloma",
    "wof:placetype":"venue"
},
  "geometry": {"coordinates":[-3.4722049236,40.4605751038],"type":"Point"}
}