{
  "type": "Feature",
  "properties": {
    "iso:country":"ES",
    "sg:address":"Plaz Iglesia, 2",
    "sg:city":"Casillas",
    "sg:orig_category":"Peluqueros: De Se\u00d1oras",
    "sg:phone":"+34 968 30 29 99",
    "sg:postcode":"30007",
    "sg:province":"Murcia",
    "wof:name":"Aragon Buendia Violante",
    "wof:placetype":"venue"
},
  "geometry": {"coordinates":[-1.1298867464,37.9834747314],"type":"Point"}
}