{
  "type": "Feature",
  "properties": {
    "addr:full":"Calle de Alfonso De Castro, 13 Rute C\u00f3rdoba 14960",
    "addr:housenumber":"13",
    "addr:postcode":"14960",
    "addr:street":"Calle De Alfonso De Castro;Co\u0301Rdoba",
    "iso:country":"ES",
    "sg:address":"Calle de Alfonso De Castro, 13",
    "sg:city":"Rute",
    "sg:orig_category":"Agencias De Viajes",
    "sg:phone":"+34 957 53 86 15",
    "sg:postcode":"14960",
    "sg:province":"C\u00f3rdoba",
    "wof:name":"Global Festival S.l.",
    "wof:placetype":"venue"
},
  "geometry": {"coordinates":[-4.3703813553,37.3255004883],"type":"Point"}
}