{
  "type": "Feature",
  "properties": {
    "addr:full":"Avgd Balmes, 5 Igualada Barcelona 08700",
    "addr:housenumber":"5",
    "addr:postcode":"08700",
    "addr:street":"Avgd Balmes",
    "iso:country":"ES",
    "sg:address":"Avgd Balmes, 5",
    "sg:city":"Igualada",
    "sg:orig_category":"Almacenes Para Venta: Muebles Y Varios",
    "sg:phone":"+34 938 05 12 86",
    "sg:postcode":"08700",
    "sg:province":"Barcelona",
    "wof:name":"Rodriguez Lorente Mercedes",
    "wof:placetype":"venue"
},
  "geometry": {"coordinates":[1.6108640432,41.5812187195],"type":"Point"}
}