{
  "type": "Feature",
  "properties": {
    "addr:full":"Calle de Luis Bejar, 3 Pozuelo De Alarcon Madrid 28223",
    "addr:housenumber":"3",
    "addr:postcode":"28223",
    "addr:street":"Calle De Luis Bejar",
    "iso:country":"ES",
    "sg:address":"Calle de Luis Bejar, 3",
    "sg:city":"Pozuelo De Alarcon",
    "sg:orig_category":"Panader\u00cdas, Panader\u00cdas",
    "sg:phone":"+34 917 15 79 68",
    "sg:postcode":"28223",
    "sg:province":"Madrid",
    "wof:name":"Sociedad Mercantil Anonima Pamde S. A.",
    "wof:placetype":"venue"
},
  "geometry": {"coordinates":[-3.8148601055,40.43567276],"type":"Point"}
}