{
  "type": "Feature",
  "properties": {
    "iso:country":"ES",
    "sg:address":"Avda Castilla Y Leon, S/n",
    "sg:city":"Burgos",
    "sg:orig_category":"Fabricaci\u00d3n, Importaci\u00d3n De L\u00c1mparas Y Bombillas",
    "sg:phone":"+34 947 22 61 85",
    "sg:postcode":"09006",
    "sg:province":"Burgos",
    "wof:name":"Solano Gutierrez Pedro",
    "wof:placetype":"venue"
},
  "geometry": {"coordinates":[-3.6826889515,42.3497962952],"type":"Point"}
}