{
  "type": "Feature",
  "properties": {
    "addr:full":"Calle de Doctor Mara\u00d1on, 31 Villanueva De Los Infantes Ciudad Real 13320",
    "addr:housenumber":"31",
    "addr:postcode":"13320",
    "addr:street":"Calle De Doctor Maran\u0303On;Infantes",
    "iso:country":"ES",
    "sg:address":"Calle de Doctor Mara\u00d1on, 31",
    "sg:city":"Villanueva De Los Infantes",
    "sg:orig_category":"Peluquer\u00cdas, Peluquer\u00cda Mixta",
    "sg:phone":"+34 926 36 09 27",
    "sg:postcode":"13320",
    "sg:province":"Ciudad Real",
    "wof:name":"Martinez Ya\u00f1ez Trinidad",
    "wof:placetype":"venue"
},
  "geometry": {"coordinates":[-3.013053894,38.7324333191],"type":"Point"}
}