{
  "type": "Feature",
  "properties": {
    "addr:full":"Pol Ind (marismas De Bengoa), 14 Santo\u00f1a Cantabria 39740",
    "addr:housenumber":"14",
    "addr:postcode":"39740",
    "addr:street":"Santon\u0303A",
    "iso:country":"ES",
    "sg:address":"Pol Ind (marismas De Bengoa), 14",
    "sg:city":"Santo\u00f1a",
    "sg:orig_category":"Empresas De Carpinter\u00cda Met\u00c1lica",
    "sg:phone":"+34 942 66 23 96",
    "sg:postcode":"39740",
    "sg:province":"Cantabria",
    "wof:name":"Aluminios Somarriba S.l",
    "wof:placetype":"venue"
},
  "geometry": {"coordinates":[-3.4447863102,43.4560623169],"type":"Point"}
}