{
  "type": "Feature",
  "properties": {
    "addr:full":"Tvsia. Pozo Moron, 1 Torrejoncillo C\u00e1ceres 10830",
    "addr:housenumber":"1",
    "addr:postcode":"10830",
    "addr:street":"Moron;Ca\u0301Ceres",
    "iso:country":"ES",
    "sg:address":"Tvsia. Pozo Moron, 1",
    "sg:city":"Torrejoncillo",
    "sg:orig_category":"Alfarer\u00cda",
    "sg:phone":"+34 927 30 42 20",
    "sg:postcode":"10830",
    "sg:province":"C\u00e1ceres",
    "wof:name":"Moreno Arias Antonio",
    "wof:placetype":"venue"
},
  "geometry": {"coordinates":[-6.4716582298,39.903465271],"type":"Point"}
}