{
  "type": "Feature",
  "properties": {
    "iso:country":"ES",
    "sg:address":"Avda Estacion (de La), 25",
    "sg:city":"Almeria",
    "sg:orig_category":"Molduras, Junquillos, Listones Y Molduras Perforadas",
    "sg:phone":"+34 950 22 30 84",
    "sg:postcode":"04005",
    "sg:province":"Almer\u00eda",
    "wof:name":"Martinez Martinez Antonia",
    "wof:placetype":"venue"
},
  "geometry": {"coordinates":[-2.4578380585,36.8373069763],"type":"Point"}
}