{
  "type": "Feature",
  "properties": {
    "iso:country":"ES",
    "sg:address":"Calle de San Miguel, 35",
    "sg:city":"Torremolinos",
    "sg:orig_category":"Zapatos (al Por Menor)",
    "sg:phone":"+34 952 05 70 65",
    "sg:postcode":"29620",
    "sg:province":"M\u00e1laga",
    "wof:name":"Calzados Recogidas S.l.",
    "wof:placetype":"venue"
},
  "geometry": {"coordinates":[-4.4982481003,36.6232414246],"type":"Point"}
}