{
  "type": "Feature",
  "properties": {
    "addr:full":"Calle de Real, S/n Yuncos Toledo 45210",
    "addr:housenumber":"s / n",
    "addr:postcode":"45210",
    "addr:street":"Calle De Real",
    "iso:country":"ES",
    "sg:address":"Calle de Real, S/n",
    "sg:city":"Yuncos",
    "sg:orig_category":"Molduras, Junquillos, Listones Y Molduras Perforadas",
    "sg:phone":"+34 925 53 72 36",
    "sg:postcode":"45210",
    "sg:province":"Toledo",
    "wof:name":"Sese\u00f1a Yepes Juan Carlos",
    "wof:placetype":"venue"
},
  "geometry": {"coordinates":[-3.8756189346,40.0842552185],"type":"Point"}
}