{
  "type": "Feature",
  "properties": {
    "addr:full":"Calle de Granada, 44 Albolote Granada 18220",
    "addr:housenumber":"44",
    "addr:postcode":"18220",
    "addr:street":"Calle De Granada",
    "iso:country":"ES",
    "sg:address":"Calle de Granada, 44",
    "sg:city":"Albolote",
    "sg:orig_category":"Peluqueros: De Se\u00d1oras",
    "sg:phone":"+34 958 46 55 63",
    "sg:postcode":"18220",
    "sg:province":"Granada",
    "wof:name":"Pozo Garcia Matilde",
    "wof:placetype":"venue"
},
  "geometry": {"coordinates":[-3.6557691097,37.2294807434],"type":"Point"}
}