{
  "type": "Feature",
  "properties": {
    "iso:country":"ES",
    "sg:address":"Carrer de Paborde Del, 46",
    "sg:city":"Valls",
    "sg:orig_category":"Frutas, Legumbres Frescas Y Tempranas (al Por Menor)",
    "sg:phone":"+34 977 61 48 17",
    "sg:postcode":"43800",
    "sg:province":"Tarragona",
    "wof:name":"Roset Domingo Jordi",
    "wof:placetype":"venue"
},
  "geometry": {"coordinates":[1.2496390343,41.2861938477],"type":"Point"}
}