{
  "type": "Feature",
  "properties": {
    "iso:country":"ES",
    "sg:address":"Carrer de Garraf, 15",
    "sg:city":"Ca L'artigues",
    "sg:orig_category":"Construcciones Met\u00c1licas",
    "sg:phone":"+34 938 41 49 85",
    "sg:postcode":"08186",
    "sg:province":"Barcelona",
    "wof:name":"Vilches Martinez Francisco",
    "wof:placetype":"venue"
},
  "geometry": {"coordinates":[2.1882059574,41.4379615784],"type":"Point"}
}