{
  "type": "Feature",
  "properties": {
    "addr:full":"Carrer de Sant Francesc Xavier, 31 Esplugues Llobregat Barcelona 08950",
    "addr:housenumber":"31",
    "addr:postcode":"08950",
    "addr:street":"Carrer De Sant Francesc Xavier",
    "iso:country":"ES",
    "sg:address":"Carrer de Sant Francesc Xavier, 31",
    "sg:city":"Esplugues Llobregat",
    "sg:orig_category":"Mec\u00c1nico Del Autom\u00d3vil",
    "sg:phone":"+34 934 99 05 74",
    "sg:postcode":"08950",
    "sg:province":"Barcelona",
    "wof:name":"Automoviles Di-an S.l.",
    "wof:placetype":"venue"
},
  "geometry": {"coordinates":[2.0848209858,41.3758201599],"type":"Point"}
}