{
  "type": "Feature",
  "properties": {
    "iso:country":"ES",
    "sg:address":"Plaz Santa Maria, 10",
    "sg:city":"Ferreira",
    "sg:orig_category":"Bancos",
    "sg:phone":"+34 982 57 42 32",
    "sg:postcode":"27770",
    "sg:province":"Lugo",
    "wof:name":"Banco Gallego S.a.",
    "wof:placetype":"venue"
},
  "geometry": {"coordinates":[-7.4409542084,43.5518302917],"type":"Point"}
}