{
  "type": "Feature",
  "properties": {
    "iso:country":"ES",
    "sg:address":"Carrer de Francesc Bastos (de), 16",
    "sg:city":"Tarragona",
    "sg:orig_category":"Peluquer\u00cdas, Peluquer\u00cda Mixta",
    "sg:phone":"+34 977 24 20 72",
    "sg:postcode":"43005",
    "sg:province":"Tarragona",
    "wof:name":"Ortiz Teba Cristina",
    "wof:placetype":"venue"
},
  "geometry": {"coordinates":[1.2423490286,41.1148452759],"type":"Point"}
}