{
  "type": "Feature",
  "properties": {
    "addr:full":"Carr. Mijas, Km. 0008,0 Mijas Costa M\u00e1laga 29649",
    "addr:postcode":"29649",
    "addr:street":"Mijas Km. 0008,0",
    "iso:country":"ES",
    "sg:address":"Carr. Mijas, Km. 0008,0",
    "sg:city":"Mijas Costa",
    "sg:orig_category":"Molduras, Junquillos, Listones Y Molduras Perforadas",
    "sg:phone":"+34 952 66 74 78",
    "sg:postcode":"29649",
    "sg:province":"M\u00e1laga",
    "wof:name":"Curvaplast S.l.",
    "wof:placetype":"venue"
},
  "geometry": {"coordinates":[-4.7157039642,36.4931945801],"type":"Point"}
}