{
  "type": "Feature",
  "properties": {
    "addr:full":"Trapiche, 20 Marbella M\u00e1laga 29600",
    "addr:housenumber":"20",
    "addr:postcode":"29600",
    "addr:street":"Trapiche;Ma\u0301Laga",
    "iso:country":"ES",
    "sg:address":"Trapiche, 20",
    "sg:city":"Marbella",
    "sg:orig_category":"Herboristas (al Por Menor)",
    "sg:phone":"+34 952 86 04 18",
    "sg:postcode":"29600",
    "sg:province":"M\u00e1laga",
    "wof:name":"Becerra Roman Yolanda",
    "wof:placetype":"venue"
},
  "geometry": {"coordinates":[-4.8883428574,36.5168495178],"type":"Point"}
}