{
  "type": "Feature",
  "properties": {
    "addr:full":"Avda Valladolid, 13 Palencia Palencia 34002",
    "addr:housenumber":"13",
    "addr:postcode":"34002",
    "addr:street":"Avda Valladolid",
    "iso:country":"ES",
    "sg:address":"Avda Valladolid, 13",
    "sg:city":"Palencia",
    "sg:orig_category":"Molduras, Junquillos, Listones Y Molduras Perforadas",
    "sg:phone":"+34 979 72 00 28",
    "sg:postcode":"34002",
    "sg:province":"Palencia",
    "wof:name":"Martin De La Rosa Miguel Angel",
    "wof:placetype":"venue"
},
  "geometry": {"coordinates":[-4.5267710686,42.0013008118],"type":"Point"}
}