{
  "type": "Feature",
  "properties": {
    "addr:full":"Calle de Sol Del Sur, 2 Galletas Santa Cruz De Tenerife 38631",
    "addr:housenumber":"2",
    "addr:postcode":"38631",
    "addr:street":"Calle De Sol Del Sur",
    "iso:country":"ES",
    "sg:address":"Calle de Sol Del Sur, 2",
    "sg:city":"Galletas",
    "sg:orig_category":"Bisuter\u00cda, Joyer\u00cda, Relojer\u00cda (al Por Menor)",
    "sg:phone":"+34 922 73 31 29",
    "sg:postcode":"38631",
    "sg:province":"Santa Cruz De Tenerife",
    "wof:name":"Francis 1952 S.l.",
    "wof:placetype":"venue"
},
  "geometry": {"coordinates":[-16.6539421082,28.0083026886],"type":"Point"}
}