{
  "type": "Feature",
  "properties": {
    "iso:country":"ES",
    "sg:address":"Calle de Columela, 6",
    "sg:city":"Madrid",
    "sg:orig_category":"Zapatos (al Por Menor)",
    "sg:phone":"+34 914 31 01 67",
    "sg:postcode":"28001",
    "sg:province":"Madrid",
    "sg:website":"www.columela.net",
    "wof:name":"Hermanas Antolin 2003 S.l.",
    "wof:placetype":"venue"
},
  "geometry": {"coordinates":[-3.6876876354,40.4211502075],"type":"Point"}
}