{
  "type": "Feature",
  "properties": {
    "iso:country":"ES",
    "sg:address":"Calle de Lago San Mauricio, 9",
    "sg:city":"Aguadulce",
    "sg:orig_category":"Doctores En Medicina",
    "sg:phone":"+34 950 34 28 23",
    "sg:postcode":"04720",
    "sg:province":"Almer\u00eda",
    "wof:name":"Cruz Cruz Maria Dolores",
    "wof:placetype":"venue"
},
  "geometry": {"coordinates":[-2.5649540424,36.8188819885],"type":"Point"}
}