{
  "type": "Feature",
  "properties": {
    "addr:full":"Rbla Catalunya, 1 Barcelona Barcelona 08007",
    "addr:housenumber":"1",
    "addr:postcode":"08007",
    "addr:street":"Rbla Catalunya",
    "iso:country":"ES",
    "sg:address":"Rbla Catalunya, 1",
    "sg:city":"Barcelona",
    "sg:orig_category":"Farmacias",
    "sg:phone":"+34 933 01 07 27",
    "sg:postcode":"08007",
    "sg:province":"Barcelona",
    "wof:name":"Espona Messeguer Nuria",
    "wof:placetype":"venue"
},
  "geometry": {"coordinates":[2.1683859825,41.387386322],"type":"Point"}
}