{
  "type": "Feature",
  "properties": {
    "iso:country":"ES",
    "sg:address":"Calle de Coso, 2",
    "sg:city":"Illescas",
    "sg:orig_category":"Panader\u00cdas, Panader\u00cdas",
    "sg:phone":"+34 925 51 21 28",
    "sg:postcode":"45200",
    "sg:province":"Toledo",
    "wof:name":"Guijarro Oporto Juan Jose",
    "wof:placetype":"venue"
},
  "geometry": {"coordinates":[-3.849344492,40.1240196228],"type":"Point"}
}