{
  "type": "Feature",
  "properties": {
    "addr:full":"Calle de Casimiro Sainz, 15 Santander Cantabria 39003",
    "addr:housenumber":"15",
    "addr:postcode":"39003",
    "addr:street":"Calle De Casimiro Sainz",
    "iso:country":"ES",
    "sg:address":"Calle de Casimiro Sainz, 15",
    "sg:city":"Santander",
    "sg:orig_category":"Carnicer\u00cdas, Carnicer\u00cdas",
    "sg:phone":"+34 942 21 51 67",
    "sg:postcode":"39003",
    "sg:province":"Cantabria",
    "wof:name":"Angulo Martinez Jose Miguel",
    "wof:placetype":"venue"
},
  "geometry": {"coordinates":[-3.7968506813,43.4643707275],"type":"Point"}
}