{
  "type": "Feature",
  "properties": {
    "addr:full":"Ctra De La Bolera, S/n Pozo Alcon Ja\u00e9n 23485",
    "addr:housenumber":"s / n",
    "addr:postcode":"23485",
    "addr:street":"Ctra De La Bolera;Alcon Jae\u0301N",
    "iso:country":"ES",
    "sg:address":"Ctra De La Bolera, S/n",
    "sg:city":"Pozo Alcon",
    "sg:orig_category":"Ense\u00d1anza, Formaci\u00d3n Profesional: Aprendizaje",
    "sg:phone":"+34 953 71 83 68",
    "sg:postcode":"23485",
    "sg:province":"Ja\u00e9n",
    "wof:name":"Ayuntamiento De Pozo Alcon",
    "wof:placetype":"venue"
},
  "geometry": {"coordinates":[-2.9067339897,37.7629394531],"type":"Point"}
}