{
  "type": "Feature",
  "properties": {
    "addr:full":"Calle de Amapola, 4 Algeciras C\u00e1diz 11204",
    "addr:housenumber":"4;ca\u0301diz",
    "addr:postcode":"11204",
    "addr:street":"Calle De Amapola",
    "iso:country":"ES",
    "sg:address":"Calle de Amapola, 4",
    "sg:city":"Algeciras",
    "sg:orig_category":"Panader\u00cdas, Panader\u00cdas",
    "sg:phone":"+34 956 65 05 84",
    "sg:postcode":"11204",
    "sg:province":"C\u00e1diz",
    "wof:name":"Distribuidora La Juzcare\u00f1a S.l.",
    "wof:placetype":"venue"
},
  "geometry": {"coordinates":[-5.461742878,36.1472702026],"type":"Point"}
}