{
  "type": "Feature",
  "properties": {
    "addr:full":"Carrer de Josep Tarradellas, 7 Amposta Tarragona 43870",
    "addr:housenumber":"7",
    "addr:postcode":"43870",
    "addr:street":"Carrer De Josep Tarradellas",
    "iso:country":"ES",
    "sg:address":"Carrer de Josep Tarradellas, 7",
    "sg:city":"Amposta",
    "sg:orig_category":"Venta, Colocaci\u00d3n, Reparaci\u00d3n De Radiadores Para Veh\u00cdculos",
    "sg:phone":"+34 977 70 21 52",
    "sg:postcode":"43870",
    "sg:province":"Tarragona",
    "wof:name":"Gisbert Arrufat Juan Antonio",
    "wof:placetype":"venue"
},
  "geometry": {"coordinates":[0.5534189939,40.6996498108],"type":"Point"}
}