{
  "type": "Feature",
  "properties": {
    "addr:full":"Carrer de Bellaire, 15 Olot Girona 17800",
    "addr:housenumber":"15",
    "addr:postcode":"17800",
    "addr:street":"Carrer De Bellaire",
    "iso:country":"ES",
    "sg:address":"Carrer de Bellaire, 15",
    "sg:city":"Olot",
    "sg:orig_category":"Servicios De Telecomunicaciones",
    "sg:phone":"+34 972 27 68 36",
    "sg:postcode":"17800",
    "sg:province":"Girona",
    "wof:name":"Martinez  Gloria Elsi",
    "wof:placetype":"venue"
},
  "geometry": {"coordinates":[2.4903318882,42.1822929382],"type":"Point"}
}