{
  "type": "Feature",
  "properties": {
    "iso:country":"ES",
    "sg:address":"Avda Generalisimo (del), 30",
    "sg:city":"Valdelaguna",
    "sg:orig_category":"Condimentos, Especias, Vinagres, Salsas Preparadas (fabricaci\u00d3n, Al Por Mayor)",
    "sg:phone":"+34 918 93 70 32",
    "sg:postcode":"28391",
    "sg:province":"Madrid",
    "wof:name":"Sat 592 Hermanos Lopez Martinez",
    "wof:placetype":"venue"
},
  "geometry": {"coordinates":[-3.3695731163,40.1616973877],"type":"Point"}
}