{
  "type": "Feature",
  "properties": {
    "iso:country":"ES",
    "sg:address":"Calle de Iturkoa, 1",
    "sg:city":"Berriozar",
    "sg:orig_category":"Organismos De Reclutamiento",
    "sg:phone":"+34 948 35 41 05",
    "sg:postcode":"31013",
    "sg:province":"Navarra",
    "wof:name":"Aranaz Hernandez Idoya",
    "wof:placetype":"venue"
},
  "geometry": {"coordinates":[-1.6707295179,42.8328132629],"type":"Point"}
}