{
  "type": "Feature",
  "properties": {
    "addr:full":"Barr Tejera (la) (boo), 3 Boo Cantabria 39478",
    "addr:housenumber":"3",
    "addr:postcode":"39478",
    "iso:country":"ES",
    "sg:address":"Barr Tejera (la) (boo), 3",
    "sg:city":"Boo",
    "sg:orig_category":"Delegados, Agentes De Tr\u00c1nsito, Auxiliares De Transporte Internacional",
    "sg:phone":"+34 942 58 61 18",
    "sg:postcode":"39478",
    "sg:province":"Cantabria",
    "wof:name":"Trastote S.l.",
    "wof:placetype":"venue"
},
  "geometry": {"coordinates":[-3.9400789738,43.4105300903],"type":"Point"}
}