{
  "type": "Feature",
  "properties": {
    "addr:full":"Calle de Colon, 31 Alcorcon Madrid 28921",
    "addr:housenumber":"31",
    "addr:postcode":"28921",
    "addr:street":"Calle De Colon",
    "iso:country":"ES",
    "sg:address":"Calle de Colon, 31",
    "sg:city":"Alcorcon",
    "sg:orig_category":"Cajas De Ahorro",
    "sg:phone":"+34 914 86 12 92",
    "sg:postcode":"28921",
    "sg:province":"Madrid",
    "wof:name":"Caja De Ahorros Del Mediterraneo",
    "wof:placetype":"venue"
},
  "geometry": {"coordinates":[-3.828248024,40.3464126587],"type":"Point"}
}