{
  "type": "Feature",
  "properties": {
    "iso:country":"ES",
    "sg:address":"Ctra Magallon, S/n",
    "sg:city":"Fuendejalon",
    "sg:orig_category":"Producci\u00d3n De Champi\u00d1ones",
    "sg:phone":"+34 976 86 23 49",
    "sg:postcode":"50529",
    "sg:province":"Zaragoza",
    "wof:name":"Garcia Sanmartin Jose Maria",
    "wof:placetype":"venue"
},
  "geometry": {"coordinates":[-1.4747070074,41.7618141174],"type":"Point"}
}