{
  "type": "Feature",
  "properties": {
    "addr:full":"La Hondura, 8 Puerto Santiago Santa Cruz De Tenerife 38683",
    "addr:housenumber":"8",
    "addr:postcode":"38683",
    "addr:street":"Hondura",
    "iso:country":"ES",
    "sg:address":"La Hondura, 8",
    "sg:city":"Puerto Santiago",
    "sg:orig_category":"Bazares, Art\u00cdculos De Limpieza Y De Cocina (al Por Menor)",
    "sg:phone":"+34 922 86 21 36",
    "sg:postcode":"38683",
    "sg:province":"Santa Cruz De Tenerife",
    "wof:name":"Striegl  Ana Maria",
    "wof:placetype":"venue"
},
  "geometry": {"coordinates":[-16.8448352814,28.2389850616],"type":"Point"}
}