{
  "type": "Feature",
  "properties": {
    "addr:full":"Playa Almadraba, S/n Roses Girona 17480",
    "addr:housenumber":"s / n",
    "addr:postcode":"17480",
    "addr:street":"Almadraba",
    "iso:country":"ES",
    "sg:address":"Playa Almadraba, S/n",
    "sg:city":"Roses",
    "sg:orig_category":"Hoteles",
    "sg:phone":"+34 972 25 65 50",
    "sg:postcode":"17480",
    "sg:province":"Girona",
    "wof:name":"Almadraba Park S. A.",
    "wof:placetype":"venue"
},
  "geometry": {"coordinates":[3.2127430439,42.2365379333],"type":"Point"}
}