{
  "type": "Feature",
  "properties": {
    "iso:country":"ES",
    "sg:address":"Calle de Ebro, 10",
    "sg:city":"Granada",
    "sg:orig_category":"Extinci\u00d3n De Incendios: Material Y Suministros (fabricaci\u00d3n, Al Por Mayor)",
    "sg:phone":"+34 958 13 39 06",
    "sg:postcode":"18007",
    "sg:province":"Granada",
    "wof:name":"Extintores Servicios Y Mantenimiento Contra Incendios S.l",
    "wof:placetype":"venue"
},
  "geometry": {"coordinates":[-3.6001718044,37.1522521973],"type":"Point"}
}