{
  "type": "Feature",
  "properties": {
    "addr:full":"Calle de Presbitero Conrado Poveda, 2 Petrer Alicante 03610",
    "addr:housenumber":"2",
    "addr:postcode":"03610",
    "addr:street":"Calle De Presbitero Conrado Poveda",
    "iso:country":"ES",
    "sg:address":"Calle de Presbitero Conrado Poveda, 2",
    "sg:city":"Petrer",
    "sg:orig_category":"M\u00c1rmoles, Granitos Y Piedras Naturales",
    "sg:phone":"+34 965 37 07 03",
    "sg:postcode":"03610",
    "sg:province":"Alicante",
    "wof:name":"Pastor Roman Roque",
    "wof:placetype":"venue"
},
  "geometry": {"coordinates":[-0.7886589766,38.4893112183],"type":"Point"}
}