{
  "type": "Feature",
  "properties": {
    "addr:full":"Calle de San Juan, 16 Burgos Burgos 09004",
    "addr:housenumber":"16",
    "addr:postcode":"09004",
    "addr:street":"Calle De San Juan",
    "iso:country":"ES",
    "sg:address":"Calle de San Juan, 16",
    "sg:city":"Burgos",
    "sg:orig_category":"Ropa Para Se\u00d1oras (al Por Menor)",
    "sg:phone":"+34 947 26 41 72",
    "sg:postcode":"09004",
    "sg:province":"Burgos",
    "sg:website":"www.benetton.com",
    "wof:name":"Perez Solana Julio",
    "wof:placetype":"venue"
},
  "geometry": {"coordinates":[-3.6991019249,42.3427772522],"type":"Point"}
}