{
  "type": "Feature",
  "properties": {
    "iso:country":"ES",
    "sg:address":"Psaj Milan, 121",
    "sg:city":"Tejina",
    "sg:orig_category":"Transporte En General",
    "sg:phone":"+34 922 54 03 52",
    "sg:postcode":"38260",
    "sg:province":"Santa Cruz De Tenerife",
    "wof:name":"Hernandez Rodriguez Timoteo",
    "wof:placetype":"venue"
},
  "geometry": {"coordinates":[-16.3620090485,28.543718338],"type":"Point"}
}