{
  "type": "Feature",
  "properties": {
    "addr:full":"Calle de Espejo, 9 Madrid Madrid 28013",
    "addr:housenumber":"9",
    "addr:postcode":"madrid;28013",
    "addr:street":"Calle De Espejo",
    "iso:country":"ES",
    "sg:address":"Calle de Espejo, 9",
    "sg:city":"Madrid",
    "sg:orig_category":"Asesor\u00cda Sobre Comunicaci\u00d3n De Empresas",
    "sg:phone":"+34 915 41 09 46",
    "sg:postcode":"28013",
    "sg:province":"Madrid",
    "wof:name":"Elite Central Entretenimiento S.l.",
    "wof:placetype":"venue"
},
  "geometry": {"coordinates":[-3.7098829746,40.4169540405],"type":"Point"}
}