{
  "type": "Feature",
  "properties": {
    "iso:country":"ES",
    "sg:address":"Calle de Maidagan, 47 D",
    "sg:city":"Getxo",
    "sg:orig_category":"Peluquer\u00cdas, Peluquer\u00cda Mixta",
    "sg:phone":"+34 944 60 48 00",
    "sg:postcode":"48990",
    "sg:province":"Vizcaya",
    "wof:name":"Amado Maillo Gutierrez",
    "wof:placetype":"venue"
},
  "geometry": {"coordinates":[-3.0146713257,43.3611907959],"type":"Point"}
}