{
  "type": "Feature",
  "properties": {
    "addr:full":"G. Parrizas, 19 Huetor-tajar Granada 18360",
    "addr:housenumber":"19",
    "addr:postcode":"18360",
    "addr:street":"G. Parrizas",
    "iso:country":"ES",
    "sg:address":"G. Parrizas, 19",
    "sg:city":"Huetor-tajar",
    "sg:orig_category":"Plomeros",
    "sg:phone":"+34 958 33 38 87",
    "sg:postcode":"18360",
    "sg:province":"Granada",
    "wof:name":"Instalfon Huetor Tajar S.l.",
    "wof:placetype":"venue"
},
  "geometry": {"coordinates":[-4.0706038475,37.2185134888],"type":"Point"}
}