{
  "type": "Feature",
  "properties": {
    "iso:country":"ES",
    "sg:address":"Rua Freixos, 2",
    "sg:city":"Coroto",
    "sg:orig_category":"Minerales (al Por Mayor)",
    "sg:phone":"+34 981 66 14 18",
    "sg:postcode":"15176",
    "sg:province":"La Coru\u00f1a",
    "wof:name":"Iber Piedra Naturstone,sl",
    "wof:placetype":"venue"
},
  "geometry": {"coordinates":[-8.3316135406,43.3172149658],"type":"Point"}
}