{
  "type": "Feature",
  "properties": {
    "addr:full":"Calle de Bravo Murillo, 300 Madrid Madrid 28020",
    "addr:housenumber":"300",
    "addr:postcode":"28020",
    "addr:street":"Calle De Bravo Murillo",
    "iso:country":"ES",
    "sg:address":"Calle de Bravo Murillo, 300",
    "sg:city":"Madrid",
    "sg:orig_category":"\u00d3ptica: Instrumentos (fabricaci\u00d3n)",
    "sg:phone":"+34 915 70 73 69",
    "sg:postcode":"28020",
    "sg:province":"Madrid",
    "sg:website":"www.sangabino.com",
    "wof:name":"Opticas San Gabino S.l.",
    "wof:placetype":"venue"
},
  "geometry": {"coordinates":[-3.6971395016,40.4627532959],"type":"Point"}
}