{
  "type": "Feature",
  "properties": {
    "iso:country":"ES",
    "sg:address":"Illa De Buda, S/n",
    "sg:city":"Almassora",
    "sg:orig_category":"Empresas De Pintura Y Revestimientos",
    "sg:phone":"+34 964 55 92 00",
    "sg:postcode":"12550",
    "sg:province":"Castell\u00f3n",
    "wof:name":"Cubillas Lopez Jose",
    "wof:placetype":"venue"
},
  "geometry": {"coordinates":[-0.000389,39.9354896545],"type":"Point"}
}