{
  "type": "Feature",
  "properties": {
    "addr:full":"Calle de Aita Elorriaga, 8 Mungia Vizcaya 48100",
    "addr:housenumber":"8",
    "addr:postcode":"48100",
    "addr:street":"Calle De Aita Elorriaga",
    "iso:country":"ES",
    "sg:address":"Calle de Aita Elorriaga, 8",
    "sg:city":"Mungia",
    "sg:orig_category":"Muebles Y Accesorios Para Cocinas Y Cuartos De Ba\u00d1o (al Por Menor)",
    "sg:phone":"+34 946 15 62 90",
    "sg:postcode":"48100",
    "sg:province":"Vizcaya",
    "wof:name":"Cocinas Izadi C.b",
    "wof:placetype":"venue"
},
  "geometry": {"coordinates":[-2.8454866409,43.3535041809],"type":"Point"}
}