{
  "type": "Feature",
  "properties": {
    "addr:full":"Calle de Maria Auxiliadora, 15 Sevilla Sevilla 41003",
    "addr:housenumber":"15",
    "addr:postcode":"41003",
    "addr:street":"Calle De Maria Auxiliadora",
    "iso:country":"ES",
    "sg:address":"Calle de Maria Auxiliadora, 15",
    "sg:city":"Sevilla",
    "sg:orig_category":"Moda",
    "sg:phone":"+34 954 41 38 52",
    "sg:postcode":"41003",
    "sg:province":"Sevilla",
    "wof:name":"Bisuteria Y Complementos De Moda S.l.",
    "wof:placetype":"venue"
},
  "geometry": {"coordinates":[-5.9838190079,37.3937416077],"type":"Point"}
}