{
  "type": "Feature",
  "properties": {
    "addr:full":"Calle de Banderas De Castilla, 6 Toledo Toledo 45005",
    "addr:housenumber":"6",
    "addr:postcode":"45005",
    "addr:street":"Calle De Banderas De Castilla",
    "iso:country":"ES",
    "sg:address":"Calle de Banderas De Castilla, 6",
    "sg:city":"Toledo",
    "sg:orig_category":"Inmobiliaria (agencias)",
    "sg:phone":"+34 925 25 75 75",
    "sg:postcode":"45005",
    "sg:province":"Toledo",
    "sg:website":"www paginasamarilas.es",
    "wof:name":"Del Viso Copado Angel",
    "wof:placetype":"venue"
},
  "geometry": {"coordinates":[-4.0328230858,39.8716659546],"type":"Point"}
}