{
  "type": "Feature",
  "properties": {
    "iso:country":"ES",
    "sg:address":"Calle de Lopez Mezquia, 9",
    "sg:city":"Madrid",
    "sg:orig_category":"Servicio De Salud",
    "sg:phone":"+34 914 66 56 68",
    "sg:postcode":"28019",
    "sg:province":"Madrid",
    "wof:name":"Gonzalez Alcaide Luis",
    "wof:placetype":"venue"
},
  "geometry": {"coordinates":[-3.7385020256,40.3943099976],"type":"Point"}
}