{
  "type": "Feature",
  "properties": {
    "iso:country":"ES",
    "sg:address":"Cmno Vera, 25",
    "sg:city":"Campohermoso",
    "sg:orig_category":"Laboratorios Y Trabajos De Fotograf\u00cda, V\u00cddeo Y Cine",
    "sg:phone":"+34 950 38 56 06",
    "sg:postcode":"04110",
    "sg:province":"Almer\u00eda",
    "wof:name":"Fernandez Rodriguez Antonio",
    "wof:placetype":"venue"
},
  "geometry": {"coordinates":[-2.1324241161,36.9409065247],"type":"Point"}
}