{
  "type": "Feature",
  "properties": {
    "addr:full":"Calle de Luis Rojas, 4 Orihuela Alicante 03300",
    "addr:housenumber":"4",
    "addr:postcode":"03300",
    "addr:street":"Calle De Luis Rojas",
    "iso:country":"ES",
    "sg:address":"Calle de Luis Rojas, 4",
    "sg:city":"Orihuela",
    "sg:orig_category":"Ropa Para Se\u00d1oras (al Por Menor)",
    "sg:phone":"+34 965 30 11 87",
    "sg:postcode":"03300",
    "sg:province":"Alicante",
    "wof:name":"Aracil Riera Josefina",
    "wof:placetype":"venue"
},
  "geometry": {"coordinates":[-0.9479879141,38.0846061707],"type":"Point"}
}