{
  "type": "Feature",
  "properties": {
    "addr:full":"Calle de Condes De Aragon, 12 Zaragoza Zaragoza 50009",
    "addr:housenumber":"12",
    "addr:postcode":"50009",
    "addr:street":"Calle De Condes De Aragon",
    "iso:country":"ES",
    "sg:address":"Calle de Condes De Aragon, 12",
    "sg:city":"Zaragoza",
    "sg:orig_category":"Alimentaci\u00d3n General (al Por Menor)",
    "sg:phone":"+34 976 56 58 81",
    "sg:postcode":"50009",
    "sg:province":"Zaragoza",
    "wof:name":"Garcia Tabuenca Maria Luisa",
    "wof:placetype":"venue"
},
  "geometry": {"coordinates":[-0.9054359794,41.6396522522],"type":"Point"}
}