{
  "type": "Feature",
  "properties": {
    "iso:country":"ES",
    "sg:address":"Calle de Monreal, 38",
    "sg:city":"Zaragoza",
    "sg:orig_category":"Pescader\u00cdas (al Por Menor)",
    "sg:phone":"+34 976 39 79 31",
    "sg:postcode":"50002",
    "sg:province":"Zaragoza",
    "wof:name":"Radio Perez Marta",
    "wof:placetype":"venue"
},
  "geometry": {"coordinates":[-0.8700640202,41.6518440247],"type":"Point"}
}