{
  "type": "Feature",
  "properties": {
    "iso:country":"ES",
    "sg:address":"Rua Alonso Lopez, 88",
    "sg:city":"Ferrol",
    "sg:orig_category":"Organizaciones Profesionales",
    "sg:phone":"+34 981 35 22 02",
    "sg:postcode":"15401",
    "sg:province":"La Coru\u00f1a",
    "wof:name":"Perez Torres Santiago",
    "wof:placetype":"venue"
},
  "geometry": {"coordinates":[-8.2446813583,43.4814910889],"type":"Point"}
}