{
  "type": "Feature",
  "properties": {
    "addr:full":"Calle de Campoamor, 16 San Vicente Del Raspeig-sant Vicent Del Raspeig Alicante 03690",
    "addr:housenumber":"16",
    "addr:postcode":"03690",
    "addr:street":"Calle De Campoamor",
    "iso:country":"ES",
    "sg:address":"Calle de Campoamor, 16",
    "sg:city":"San Vicente Del Raspeig-sant Vicent Del Raspeig",
    "sg:orig_category":"Inform\u00c1tica (estudios, Servicios, Asesor\u00cda, Formaci\u00d3n)",
    "sg:phone":"+34 965 67 19 81",
    "sg:postcode":"03690",
    "sg:province":"Alicante",
    "wof:name":"Tecnograma Servicios Computerizados S.l.",
    "wof:placetype":"venue"
},
  "geometry": {"coordinates":[-0.5295817256,38.3980827332],"type":"Point"}
}