{
  "type": "Feature",
  "properties": {
    "iso:country":"ES",
    "sg:address":"Pase Santa Maria De La Cabeza, 72",
    "sg:city":"Madrid",
    "sg:orig_category":"Mec\u00c1nica Y Herramientas De Precisi\u00d3n",
    "sg:phone":"+34 914 74 27 59",
    "sg:postcode":"28045",
    "sg:province":"Madrid",
    "wof:name":"Kalibra Ingenieria S.l.",
    "wof:placetype":"venue"
},
  "geometry": {"coordinates":[-3.7008569241,40.3994407654],"type":"Point"}
}