{
  "type": "Feature",
  "properties": {
    "addr:full":"Calle de Gonzalez Damian Maestro, 7 Bilbao Vizcaya 48007",
    "addr:housenumber":"7",
    "addr:postcode":"48007",
    "addr:street":"Calle De Gonzalez Damian Maestro",
    "iso:country":"ES",
    "sg:address":"Calle de Gonzalez Damian Maestro, 7",
    "sg:city":"Bilbao",
    "sg:orig_category":"Empresas De Carpinter\u00cda De Madera",
    "sg:phone":"+34 944 45 83 45",
    "sg:postcode":"48007",
    "sg:province":"Vizcaya",
    "wof:name":"Jose Luis Diez Perez",
    "wof:placetype":"venue"
},
  "geometry": {"coordinates":[-2.9258189201,43.2697410583],"type":"Point"}
}