{
  "type": "Feature",
  "properties": {
    "iso:country":"ES",
    "sg:address":"Carrer de Joan Llampallas, 5",
    "sg:city":"Masnou",
    "sg:orig_category":"Arquitectos",
    "sg:phone":"+34 935 55 20 16",
    "sg:postcode":"08320",
    "sg:province":"Barcelona",
    "wof:name":"Tecnica Masnou S.l.",
    "wof:placetype":"venue"
},
  "geometry": {"coordinates":[2.3094100952,41.481212616],"type":"Point"}
}