{
  "type": "Feature",
  "properties": {
    "addr:full":"Calle de Circo Romano, 5 Merida Badajoz 06800",
    "addr:housenumber":"5",
    "addr:postcode":"06800",
    "addr:street":"Calle De Circo Romano",
    "iso:country":"ES",
    "sg:address":"Calle de Circo Romano, 5",
    "sg:city":"Merida",
    "sg:orig_category":"Carnicer\u00cdas, Carnicer\u00cdas",
    "sg:phone":"+34 924 31 98 65",
    "sg:postcode":"06800",
    "sg:province":"Badajoz",
    "wof:name":"Pajuelo Pinilla Carlos",
    "wof:placetype":"venue"
},
  "geometry": {"coordinates":[-6.3307833672,38.9213638306],"type":"Point"}
}