{
  "type": "Feature",
  "properties": {
    "iso:country":"ES",
    "sg:address":"Serres, S/n",
    "sg:city":"Serres",
    "sg:orig_category":"Iglesia Cat\u00d3lica",
    "sg:phone":"+34 981 82 60 30",
    "sg:postcode":"15250",
    "sg:province":"La Coru\u00f1a",
    "wof:name":"Parroquia De San Juan De Serres",
    "wof:placetype":"venue"
},
  "geometry": {"coordinates":[-9.0718431473,42.7884521484],"type":"Point"}
}