{
  "type": "Feature",
  "properties": {
    "iso:country":"ES",
    "sg:address":"Calle de Tercia, 3",
    "sg:city":"Porzuna",
    "sg:orig_category":"Reposter\u00cdas",
    "sg:phone":"+34 926 78 01 31",
    "sg:postcode":"13120",
    "sg:province":"Ciudad Real",
    "wof:name":"Blanco Rodriguez Marino",
    "wof:placetype":"venue"
},
  "geometry": {"coordinates":[-4.1545958519,39.1473464966],"type":"Point"}
}