{
  "type": "Feature",
  "properties": {
    "addr:full":"Alam Cervantes (de), Km. 0002,0 San Mateo Murcia 30800",
    "addr:postcode":"30800",
    "addr:street":"Alam Cervantes De Km. 0002,0",
    "iso:country":"ES",
    "sg:address":"Alam Cervantes (de), Km. 0002,0",
    "sg:city":"San Mateo",
    "sg:orig_category":"Fabricaci\u00d3n, Importaci\u00d3n De L\u00c1mparas Y Bombillas",
    "sg:phone":"+34 968 47 04 76",
    "sg:postcode":"30800",
    "sg:province":"Murcia",
    "sg:website":"www.fuentesiluminacion.com",
    "wof:name":"Fuentes Serrano Jesus",
    "wof:placetype":"venue"
},
  "geometry": {"coordinates":[-1.6905640364,37.680557251],"type":"Point"}
}