{
  "type": "Feature",
  "properties": {
    "iso:country":"ES",
    "sg:address":"Ctra Murcia (de), 47",
    "sg:city":"Caravaca Cruz",
    "sg:orig_category":"Comercio De Piezas De Recambio Y De Accesorios De Veh\u00cdculos, Veh\u00cdculos Industriales",
    "sg:phone":"+34 968 70 72 08",
    "sg:postcode":"30400",
    "sg:province":"Murcia",
    "wof:name":"Recambios Paco S.l.",
    "wof:placetype":"venue"
},
  "geometry": {"coordinates":[-1.8540019989,38.104850769],"type":"Point"}
}