{
  "type": "Feature",
  "properties": {
    "addr:full":"Pla\u00c7 De La Coronaci\u00e9, 1 Ontinyent Valencia 46870",
    "addr:housenumber":"1",
    "addr:postcode":"46870",
    "iso:country":"ES",
    "sg:address":"Pla\u00c7 De La Coronaci\u00e9, 1",
    "sg:city":"Ontinyent",
    "sg:orig_category":"Quincaller\u00cda (al Por Menor)",
    "sg:phone":"+34 962 91 42 79",
    "sg:postcode":"46870",
    "sg:province":"Valencia",
    "wof:name":"Ferreteria El Barranquet S.l.",
    "wof:placetype":"venue"
},
  "geometry": {"coordinates":[-0.6030989885,38.8258895874],"type":"Point"}
}