{
  "type": "Feature",
  "properties": {
    "addr:full":"Avda Dacio Darias, 66 Valverde Santa Cruz De Tenerife 38910",
    "addr:housenumber":"66",
    "addr:postcode":"38910",
    "addr:street":"Avda Dacio Darias",
    "iso:country":"ES",
    "sg:address":"Avda Dacio Darias, 66",
    "sg:city":"Valverde",
    "sg:orig_category":"Abogados",
    "sg:phone":"+34 922 55 03 54",
    "sg:postcode":"38910",
    "sg:province":"Santa Cruz De Tenerife",
    "wof:name":"Armas Perez Jose Francisco",
    "wof:placetype":"venue"
},
  "geometry": {"coordinates":[-17.9152011871,27.8128795624],"type":"Point"}
}