{
  "type": "Feature",
  "properties": {
    "iso:country":"ES",
    "sg:address":"Calle de Palacio El, 24",
    "sg:city":"Vegadeo",
    "sg:orig_category":"Albergues",
    "sg:phone":"+34 985 63 42 61",
    "sg:postcode":"33770",
    "sg:province":"Asturias",
    "wof:name":"Santamarina Fernandez Jose Antonio",
    "wof:placetype":"venue"
},
  "geometry": {"coordinates":[-7.0479111671,43.4646568298],"type":"Point"}
}