{
  "type": "Feature",
  "properties": {
    "iso:country":"ES",
    "sg:address":"Calle de Mayor, 252",
    "sg:city":"Garrucha",
    "sg:orig_category":"Centros Comerciales Y Grandes Tiendas",
    "sg:phone":"+34 950 46 04 29",
    "sg:postcode":"04630",
    "sg:province":"Almer\u00eda",
    "wof:name":"Garper Comercial Mediterraneo S.l.",
    "wof:placetype":"venue"
},
  "geometry": {"coordinates":[-1.8234219551,37.1760482788],"type":"Point"}
}