{
  "type": "Feature",
  "properties": {
    "iso:country":"ES",
    "sg:address":"Ctra Logro\u00d1o, 7",
    "sg:city":"Calahorra",
    "sg:orig_category":"Agencias De Viajes",
    "sg:phone":"+34 941 13 58 04",
    "sg:postcode":"26500",
    "sg:province":"La Rioja",
    "sg:website":"www.viajeseroski.es",
    "wof:name":"Viajes Eroski S.a.",
    "wof:placetype":"venue"
},
  "geometry": {"coordinates":[-1.9620640278,42.3058395386],"type":"Point"}
}