{
  "type": "Feature",
  "properties": {
    "addr:full":"Poli Mocholi, S/n Noain Navarra 31110",
    "addr:housenumber":"s",
    "addr:postcode":"31110",
    "addr:street":"/ N",
    "iso:country":"ES",
    "sg:address":"Poli Mocholi, S/n",
    "sg:city":"Noain",
    "sg:orig_category":"Negocio De Granos Y Harinas",
    "sg:phone":"+34 948 31 86 03",
    "sg:postcode":"31110",
    "sg:province":"Navarra",
    "wof:name":"Harivasa 2000 S.a.",
    "wof:placetype":"venue"
},
  "geometry": {"coordinates":[-1.6356370449,42.7540054321],"type":"Point"}
}