{
  "type": "Feature",
  "properties": {
    "iso:country":"ES",
    "sg:address":"Calle de Gobernador, 29",
    "sg:city":"Madrid",
    "sg:orig_category":"Inmobiliaria (agencias)",
    "sg:phone":"+34 913 69 70 38",
    "sg:postcode":"28014",
    "sg:province":"Madrid",
    "wof:name":"Infocasa Consulting S.l.",
    "wof:placetype":"venue"
},
  "geometry": {"coordinates":[-3.6943900585,40.411655426],"type":"Point"}
}