{
  "type": "Feature",
  "properties": {
    "addr:full":"Calle de Gibraltar, 1 Huesca Huesca 22006",
    "addr:housenumber":"1",
    "addr:postcode":"22006",
    "addr:street":"Calle De Gibraltar",
    "iso:country":"ES",
    "sg:address":"Calle de Gibraltar, 1",
    "sg:city":"Huesca",
    "sg:classifiers":[
        {
            "category":"Personal",
            "subcategory":"Barber",
            "type":"Services"
        }
    ],
    "sg:phone":"+34 974 22 68 29",
    "sg:postcode":"22006",
    "sg:province":"Huesca",
    "sg:tags":[
        "caballeros",
        "de",
        "peluqueros"
    ],
    "wof:name":"Diaz Carrasco Carmen",
    "wof:placetype":"venue"
},
  "geometry": {"coordinates":[-0.3986169994,42.1401100159],"type":"Point"}
}