{
  "type": "Feature",
  "properties": {
    "iso:country":"ES",
    "sg:address":"Calle de Julian Romea, 7",
    "sg:city":"Madrid",
    "sg:orig_category":"Asesor\u00cda Sobre Comunicaci\u00d3n De Empresas",
    "sg:phone":"+34 915 34 02 34",
    "sg:postcode":"28003",
    "sg:province":"Madrid",
    "wof:name":"Alvarez Reyes Hispanica Asesores S.l.",
    "wof:placetype":"venue"
},
  "geometry": {"coordinates":[-3.7143929005,40.4426727295],"type":"Point"}
}