{
  "type": "Feature",
  "properties": {
    "iso:country":"ES",
    "sg:address":"Calle de Nicaragua, 35",
    "sg:city":"Torres Cotillas",
    "sg:orig_category":"Mec\u00c1nico Del Autom\u00d3vil",
    "sg:phone":"+34 968 62 69 94",
    "sg:postcode":"30565",
    "sg:province":"Murcia",
    "wof:name":"Legaz Gabarron Francisco",
    "wof:placetype":"venue"
},
  "geometry": {"coordinates":[-1.2474300861,38.0232505798],"type":"Point"}
}