{
  "type": "Feature",
  "properties": {
    "iso:country":"ES",
    "sg:address":"Plaz Martires, 13",
    "sg:city":"Calera Y Chozas",
    "sg:orig_category":"Farmacias",
    "sg:phone":"+34 925 84 62 12",
    "sg:postcode":"45595",
    "sg:province":"Toledo",
    "wof:name":"Vega Casales Ricardo De La",
    "wof:placetype":"venue"
},
  "geometry": {"coordinates":[-5.0072097778,39.8687896729],"type":"Point"}
}