{
  "type": "Feature",
  "properties": {
    "addr:full":"Calle de Conde De Altea, 66 Altea Alicante 03590",
    "addr:housenumber":"66",
    "addr:postcode":"03590",
    "addr:street":"Calle De Conde De Altea",
    "iso:country":"ES",
    "sg:address":"Calle de Conde De Altea, 66",
    "sg:city":"Altea",
    "sg:orig_category":"Inmobiliaria (agencias)",
    "sg:phone":"+34 966 88 20 12",
    "sg:postcode":"03590",
    "sg:province":"Alicante",
    "wof:name":"Jorro Rodriguez Melania",
    "wof:placetype":"venue"
},
  "geometry": {"coordinates":[-0.0447513014,38.6033287048],"type":"Point"}
}