{
  "type": "Feature",
  "properties": {
    "addr:full":"Calle de Inmaculada Concepcion, 11 Madrid Madrid 28019",
    "addr:housenumber":"11",
    "addr:postcode":"madrid;28019",
    "addr:street":"Calle De Inmaculada Concepcion",
    "iso:country":"ES",
    "sg:address":"Calle de Inmaculada Concepcion, 11",
    "sg:city":"Madrid",
    "sg:orig_category":"Venta, Alquiler De Plataformas Y Barquillas Elevadoras",
    "sg:phone":"+34 914 69 21 54",
    "sg:postcode":"28019",
    "sg:province":"Madrid",
    "wof:name":"Martinez Cantero Corina",
    "wof:placetype":"venue"
},
  "geometry": {"coordinates":[-3.7117490768,40.3942947388],"type":"Point"}
}