{
  "type": "Feature",
  "properties": {
    "addr:full":"Calle de Campito, 1 Aracena Huelva 21200",
    "addr:housenumber":"1",
    "addr:postcode":"21200",
    "addr:street":"Calle De Campito",
    "iso:country":"ES",
    "sg:address":"Calle de Campito, 1",
    "sg:city":"Aracena",
    "sg:orig_category":"Cajas Para Embalar",
    "sg:phone":"+34 959 12 61 51",
    "sg:postcode":"21200",
    "sg:province":"Huelva",
    "wof:name":"Caja Rural Del Sur Sociedad Cooperativa",
    "wof:placetype":"venue"
},
  "geometry": {"coordinates":[-6.5617380142,37.894405365],"type":"Point"}
}