{
  "type": "Feature",
  "properties": {
    "addr:full":"Calle de Monte Carmelo, 63 Sevilla Sevilla 41011",
    "addr:housenumber":"63",
    "addr:postcode":"41011",
    "addr:street":"Calle De Monte Carmelo",
    "iso:country":"ES",
    "sg:address":"Calle de Monte Carmelo, 63",
    "sg:city":"Sevilla",
    "sg:orig_category":"Art\u00cdculos De Regalo (al Por Menor)",
    "sg:phone":"+34 954 27 45 90",
    "sg:postcode":"41011",
    "sg:province":"Sevilla",
    "sg:website":"www.tiendaenrile.com",
    "wof:name":"Garcia Enrile Antonio",
    "wof:placetype":"venue"
},
  "geometry": {"coordinates":[-5.9964008331,37.3730354309],"type":"Point"}
}