{
  "type": "Feature",
  "properties": {
    "addr:full":"Calle de Doctor Calero, 33 Majadahonda Madrid 28220",
    "addr:housenumber":"33",
    "addr:postcode":"28220",
    "addr:street":"Calle De Doctor Calero",
    "iso:country":"ES",
    "sg:address":"Calle de Doctor Calero, 33",
    "sg:city":"Majadahonda",
    "sg:orig_category":"Muebles, Minoristas",
    "sg:phone":"+34 916 38 48 32",
    "sg:postcode":"28220",
    "sg:province":"Madrid",
    "wof:name":"Proyectos Del Hogar S. A.",
    "wof:placetype":"venue"
},
  "geometry": {"coordinates":[-3.8690474033,40.4738121033],"type":"Point"}
}