{
  "type": "Feature",
  "properties": {
    "iso:country":"ES",
    "sg:address":"Calle de Pando Y Valle, 10",
    "sg:city":"Villaviciosa",
    "sg:orig_category":"Sociedades, Compa\u00d1\u00cdas Aseguradoras",
    "sg:phone":"+34 985 89 34 35",
    "sg:postcode":"33300",
    "sg:province":"Asturias",
    "wof:name":"Laso Fernandez Amaya",
    "wof:placetype":"venue"
},
  "geometry": {"coordinates":[-5.4363341331,43.4846496582],"type":"Point"}
}