{
  "type": "Feature",
  "properties": {
    "addr:full":"Calle de Mosen Romualdo Soler, 24 Alca\u00f1iz Teruel 44600",
    "addr:housenumber":"24",
    "addr:postcode":"44600",
    "addr:street":"Calle De Mosen Romualdo Soler",
    "iso:country":"ES",
    "sg:address":"Calle de Mosen Romualdo Soler, 24",
    "sg:city":"Alca\u00f1iz",
    "sg:orig_category":"Venta, Montaje De Neum\u00c1ticos",
    "sg:phone":"+34 978 83 20 57",
    "sg:postcode":"44600",
    "sg:province":"Teruel",
    "wof:name":"Alcabal S.cv.",
    "wof:placetype":"venue"
},
  "geometry": {"coordinates":[-0.1413187981,41.0524559021],"type":"Point"}
}