{
  "type": "Feature",
  "properties": {
    "iso:country":"ES",
    "sg:address":"Calle de Colon, 2",
    "sg:city":"Riba-roja Turia",
    "sg:orig_category":"Ropa Para Ni\u00d1os (al Por Menor)",
    "sg:phone":"+34 962 77 02 08",
    "sg:postcode":"46190",
    "sg:province":"Valencia",
    "wof:name":"Darlop C.b.",
    "wof:placetype":"venue"
},
  "geometry": {"coordinates":[-0.5667864084,39.5445480347],"type":"Point"}
}