{
  "type": "Feature",
  "properties": {
    "iso:country":"ES",
    "sg:address":"Calle de Demostenes, 2",
    "sg:city":"Malaga",
    "sg:orig_category":"Estaciones Y Oficinas De Meteorolog\u00cda",
    "sg:phone":"+34 952 61 19 25",
    "sg:postcode":"29010",
    "sg:province":"M\u00e1laga",
    "sg:website":"www.inm.es",
    "wof:name":"Direccion General Del Instituto Nacional De Meteorologia",
    "wof:placetype":"venue"
},
  "geometry": {"coordinates":[-4.4830150604,36.7183609009],"type":"Point"}
}