{
  "type": "Feature",
  "properties": {
    "iso:country":"ES",
    "sg:address":"Rbla Francesc Macia, 160",
    "sg:city":"Terrassa",
    "sg:orig_category":"Perfumer\u00cda (al Por Menor)",
    "sg:phone":"+34 937 36 21 44",
    "sg:postcode":"08226",
    "sg:province":"Barcelona",
    "wof:name":"Martinez Martinez Antonio",
    "wof:placetype":"venue"
},
  "geometry": {"coordinates":[2.0197269917,41.5763053894],"type":"Point"}
}