{
  "type": "Feature",
  "properties": {
    "addr:full":"Carrer de Sant Cristofol, 178 Amposta Tarragona 43870",
    "addr:housenumber":"178",
    "addr:postcode":"43870",
    "addr:street":"Carrer De Sant Cristofol",
    "iso:country":"ES",
    "sg:address":"Carrer de Sant Cristofol, 178",
    "sg:city":"Amposta",
    "sg:classifiers":[
        {
            "category":"Banks & Credit Unions",
            "subcategory":"Bureau De Change",
            "type":"Services"
        }
    ],
    "sg:phone":"+34 977 70 08 76",
    "sg:postcode":"43870",
    "sg:province":"Tarragona",
    "sg:tags":[
        "organismos",
        "control"
    ],
    "wof:name":"Laboratori De L'ebre S.l.",
    "wof:placetype":"venue"
},
  "geometry": {"coordinates":[0.5687249899,40.7006454468],"type":"Point"}
}