{
  "type": "Feature",
  "properties": {
    "addr:full":"Avda Republica Argentina, 13 Logro\u00f1o La Rioja 26002",
    "addr:housenumber":"13",
    "addr:postcode":"26002",
    "addr:street":"Avda Republica Argentina;Rioja",
    "iso:country":"ES",
    "sg:address":"Avda Republica Argentina, 13",
    "sg:city":"Logro\u00f1o",
    "sg:orig_category":"Inmobiliaria (agencias)",
    "sg:phone":"+34 941 25 55 37",
    "sg:postcode":"26002",
    "sg:province":"La Rioja",
    "wof:name":"Arsenet Inmobiliaria Y Gestion Riojana S.l.",
    "wof:placetype":"venue"
},
  "geometry": {"coordinates":[-2.448589325,42.4623680115],"type":"Point"}
}