{
  "type": "Feature",
  "properties": {
    "iso:country":"ES",
    "sg:address":"Calle de Leon Felipe, 5",
    "sg:city":"Albolote",
    "sg:orig_category":"Papeler\u00cdas, Librer\u00cdas",
    "sg:phone":"+34 958 46 81 87",
    "sg:postcode":"18220",
    "sg:province":"Granada",
    "wof:name":"Gedadi S.l.",
    "wof:placetype":"venue"
},
  "geometry": {"coordinates":[-3.6551339626,37.2290649414],"type":"Point"}
}