{
  "type": "Feature",
  "properties": {
    "addr:full":"Avda Alfredo Baeschlin, 34 Abadi\u00e7o-zelaieta Vizcaya 48220",
    "addr:housenumber":"34",
    "addr:postcode":"48220",
    "addr:street":"Avda Alfredo Baeschlin",
    "iso:country":"ES",
    "sg:address":"Avda Alfredo Baeschlin, 34",
    "sg:city":"Abadi\u00e7o-zelaieta",
    "sg:orig_category":"Muebles",
    "sg:phone":"+34 946 20 04 73",
    "sg:postcode":"48220",
    "sg:province":"Vizcaya",
    "wof:name":"Talleres Mendiola S.l.",
    "wof:placetype":"venue"
},
  "geometry": {"coordinates":[-2.6077690125,43.146938324],"type":"Point"}
}