{
  "type": "Feature",
  "properties": {
    "addr:full":"Carrer de Mallorca, 29 S. Boi Llobregat Barcelona 08830",
    "addr:housenumber":"29",
    "addr:postcode":"08830",
    "addr:street":"Carrer De Mallorca",
    "iso:country":"ES",
    "sg:address":"Carrer de Mallorca, 29",
    "sg:city":"S. Boi Llobregat",
    "sg:orig_category":"Peluquer\u00cdas, Peluquer\u00cda Mixta",
    "sg:phone":"+34 936 30 04 67",
    "sg:postcode":"08830",
    "sg:province":"Barcelona",
    "wof:name":"Gonzalez Calzado Antonia",
    "wof:placetype":"venue"
},
  "geometry": {"coordinates":[2.0433399677,41.3419113159],"type":"Point"}
}