{
  "type": "Feature",
  "properties": {
    "iso:country":"ES",
    "sg:address":"Calle de Pozo (del), 40",
    "sg:city":"Barco De Avila",
    "sg:orig_category":"Frutas Y Legumbres Frescas (al Por Mayor)",
    "sg:phone":"+34 920 34 03 06",
    "sg:postcode":"05600",
    "sg:province":"\u00c1vila",
    "wof:name":"Vidal Sanchez E Hijos S.l.",
    "wof:placetype":"venue"
},
  "geometry": {"coordinates":[-5.5222029686,40.3559761047],"type":"Point"}
}