{
  "type": "Feature",
  "properties": {
    "addr:full":"Av Collserola, 39 Molins Rei Barcelona 08750",
    "addr:housenumber":"39",
    "addr:postcode":"08750",
    "addr:street":"Av Collserola;Barcelona",
    "iso:country":"ES",
    "sg:address":"Av Collserola, 39",
    "sg:city":"Molins Rei",
    "sg:orig_category":"Delineantes",
    "sg:phone":"+34 936 73 29 00",
    "sg:postcode":"08750",
    "sg:province":"Barcelona",
    "wof:name":"M.a.g. Informatic S.l.",
    "wof:placetype":"venue"
},
  "geometry": {"coordinates":[2.0201001167,41.4208488464],"type":"Point"}
}