{
  "type": "Feature",
  "properties": {
    "iso:country":"ES",
    "sg:address":"Ctra Benagalbon, Km. 0001,7",
    "sg:city":"Rincon Victoria",
    "sg:orig_category":"Equitaci\u00d3n Y Centros De H\u00cdpica",
    "sg:phone":"+34 952 40 45 45",
    "sg:postcode":"29730",
    "sg:province":"M\u00e1laga",
    "wof:name":"Marfil Aguilar Jose Miguel",
    "wof:placetype":"venue"
},
  "geometry": {"coordinates":[-4.2807641029,36.714641571],"type":"Point"}
}