{
  "type": "Feature",
  "properties": {
    "addr:full":"Arrate Plaza, 6 Andoain Guip\u00f9zcoa 20140",
    "addr:housenumber":"6",
    "addr:postcode":"20140",
    "addr:street":"Arrate Plaza;Guipu\u0300Zcoa",
    "iso:country":"ES",
    "sg:address":"Arrate Plaza, 6",
    "sg:city":"Andoain",
    "sg:orig_category":"Partidos Pol\u00cdticos",
    "sg:phone":"+34 943 30 05 40",
    "sg:postcode":"20140",
    "sg:province":"Guip\u00f9zcoa",
    "wof:name":"Partido Socialista Obrero Espa\u00f1ol",
    "wof:placetype":"venue"
},
  "geometry": {"coordinates":[-2.0198719501,43.2212600708],"type":"Point"}
}