{
  "type": "Feature",
  "properties": {
    "iso:country":"ES",
    "sg:address":"Calle de Alfaro, 13",
    "sg:city":"Pinto",
    "sg:orig_category":"Frutos Y Legumbres",
    "sg:phone":"+34 916 92 52 94",
    "sg:postcode":"28320",
    "sg:province":"Madrid",
    "wof:name":"Fruitfer S.a.",
    "wof:placetype":"venue"
},
  "geometry": {"coordinates":[-3.6961538792,40.2451858521],"type":"Point"}
}