{
  "type": "Feature",
  "properties": {
    "addr:full":"Rua Llorente, 24 Vigo Pontevedra 36202",
    "addr:housenumber":"24",
    "addr:postcode":"36202",
    "addr:street":"Rua Llorente",
    "iso:country":"ES",
    "sg:address":"Rua Llorente, 24",
    "sg:city":"Vigo",
    "sg:orig_category":"Alquiler De Casas Y Habitaciones Amuebladas",
    "sg:phone":"+34 986 43 52 02",
    "sg:postcode":"36202",
    "sg:province":"Pontevedra",
    "wof:name":"Reverendos Padres Franciscanos",
    "wof:placetype":"venue"
},
  "geometry": {"coordinates":[-8.7299213409,42.2349052429],"type":"Point"}
}