{
  "type": "Feature",
  "properties": {
    "addr:full":"Barr Donibane, 1 Zubiaur Vizcaya 48410",
    "addr:housenumber":"1",
    "addr:postcode":"48410",
    "addr:street":"Donibane",
    "iso:country":"ES",
    "sg:address":"Barr Donibane, 1",
    "sg:city":"Zubiaur",
    "sg:orig_category":"Serrer\u00cdas De Madera",
    "sg:phone":"+34 946 33 95 00",
    "sg:postcode":"48410",
    "sg:province":"Vizcaya",
    "wof:name":"Aserraderos Orozco S.l.",
    "wof:placetype":"venue"
},
  "geometry": {"coordinates":[-2.912156105,43.1083488464],"type":"Point"}
}