{
  "type": "Feature",
  "properties": {
    "addr:full":"Ctra Garganta, S/n Estacion De El Espinar Segovia 40400",
    "addr:housenumber":"s",
    "addr:postcode":"40400",
    "addr:street":"Ctra Garganta;/ N Estacion De El;Segovia",
    "iso:country":"ES",
    "sg:address":"Ctra Garganta, S/n",
    "sg:city":"Estacion De El Espinar",
    "sg:orig_category":"Sanatorios M\u00c9dico",
    "sg:phone":"+34 921 18 83 35",
    "sg:postcode":"40400",
    "sg:province":"Segovia",
    "wof:name":"Ayuntamiento De El Espinar",
    "wof:placetype":"venue"
},
  "geometry": {"coordinates":[-4.1880350113,40.7375221252],"type":"Point"}
}