{
  "type": "Feature",
  "properties": {
    "iso:country":"ES",
    "sg:address":"Carrer de Sola, 23",
    "sg:city":"Fatarella",
    "sg:orig_category":"Empresarios",
    "sg:phone":"+34 977 41 39 02",
    "sg:postcode":"43781",
    "sg:province":"Tarragona",
    "wof:name":"Fundacio El Sola",
    "wof:placetype":"venue"
},
  "geometry": {"coordinates":[0.472420007,41.1627502441],"type":"Point"}
}