{
  "type": "Feature",
  "properties": {
    "iso:country":"ES",
    "sg:address":"Calle de Privilegio De La Union, 23",
    "sg:city":"Zaragoza",
    "sg:orig_category":"Electricidad: Instaladores",
    "sg:phone":"+34 976 49 16 53",
    "sg:postcode":"50013",
    "sg:province":"Zaragoza",
    "wof:name":"Abad Labrador Instalaciones Electricas S.l.",
    "wof:placetype":"venue"
},
  "geometry": {"coordinates":[-0.871539,41.64204],"type":"Point"}
}