{
  "type": "Feature",
  "properties": {
    "addr:full":"Avda Lugo, 55 Friol Lugo 27220",
    "addr:housenumber":"55",
    "addr:postcode":"27220",
    "addr:street":"Avda Lugo",
    "iso:country":"ES",
    "sg:address":"Avda Lugo, 55",
    "sg:city":"Friol",
    "sg:orig_category":"Molduras, Junquillos, Listones Y Molduras Perforadas",
    "sg:phone":"+34 982 37 51 32",
    "sg:postcode":"27220",
    "sg:province":"Lugo",
    "wof:name":"Racamonde Vigo Rogelio",
    "wof:placetype":"venue"
},
  "geometry": {"coordinates":[-7.7798857689,43.0251045227],"type":"Point"}
}