{
  "type": "Feature",
  "properties": {
    "addr:full":"Calle de Casino, 51 Torreaguera Murcia 30579",
    "addr:housenumber":"51",
    "addr:postcode":"30579",
    "addr:street":"Calle De Casino",
    "iso:country":"ES",
    "sg:address":"Calle de Casino, 51",
    "sg:city":"Torreaguera",
    "sg:orig_category":"Empresas De Pintura Y Revestimientos",
    "sg:phone":"+34 968 82 43 95",
    "sg:postcode":"30579",
    "sg:province":"Murcia",
    "wof:name":"Sanchez Quintana Alfredo",
    "wof:placetype":"venue"
},
  "geometry": {"coordinates":[-1.0923242569,37.9564552307],"type":"Point"}
}