{
  "type": "Feature",
  "properties": {
    "iso:country":"ES",
    "sg:address":"Avda Hermanos Bou, 29",
    "sg:city":"Castellon",
    "sg:orig_category":"Inform\u00c1tica (estudios, Servicios, Asesor\u00cda, Formaci\u00d3n)",
    "sg:phone":"+34 964 72 22 36",
    "sg:postcode":"12003",
    "sg:province":"Castell\u00f3n",
    "sg:website":"www.fidelity.es",
    "wof:name":"Fidelity Software Group 2002 S.l.",
    "wof:placetype":"venue"
},
  "geometry": {"coordinates":[-0.0077,39.9836883545],"type":"Point"}
}