{
  "type": "Feature",
  "properties": {
    "iso:country":"ES",
    "sg:address":"Carr Bascula, (de La), 12",
    "sg:city":"Carlet",
    "sg:orig_category":"Frutas, Legumbres Frescas Y Tempranas (al Por Menor)",
    "sg:phone":"+34 962 53 16 23",
    "sg:postcode":"46240",
    "sg:province":"Valencia",
    "wof:name":"Garcia Soriano Teresa",
    "wof:placetype":"venue"
},
  "geometry": {"coordinates":[-0.5218359828,39.225227356],"type":"Point"}
}