{
  "type": "Feature",
  "properties": {
    "addr:full":"Calle de Saulo Toron, 12 Carrizal Las Palmas 35240",
    "addr:housenumber":"12",
    "addr:postcode":"35240",
    "addr:street":"Calle De Saulo Toron",
    "iso:country":"ES",
    "sg:address":"Calle de Saulo Toron, 12",
    "sg:city":"Carrizal",
    "sg:orig_category":"Peluquer\u00cdas, Peluquer\u00cda Mixta",
    "sg:phone":"+34 928 78 67 03",
    "sg:postcode":"35240",
    "sg:province":"Las Palmas",
    "wof:name":"Ramirez Suarez Ascension 00937260b S.l.n.e",
    "wof:placetype":"venue"
},
  "geometry": {"coordinates":[-15.4080963135,27.9121112823],"type":"Point"}
}