{
  "type": "Feature",
  "properties": {
    "iso:country":"ES",
    "sg:address":"Carr Cartagena, 12",
    "sg:city":"Girona",
    "sg:orig_category":"Electricidad: Equipos Industriales, Componentes (fabricaci\u00d3n)",
    "sg:phone":"+34 972 23 14 50",
    "sg:postcode":"17005",
    "sg:province":"Girona",
    "wof:name":"Comelgrup Girona S.l.",
    "wof:placetype":"venue"
},
  "geometry": {"coordinates":[2.8106169701,41.9667205811],"type":"Point"}
}