{
  "type": "Feature",
  "properties": {
    "addr:full":"Pg Miramar (de), 91 Salou Tarragona 43840",
    "addr:housenumber":"91",
    "addr:postcode":"43840",
    "addr:street":"Pg Miramar De",
    "iso:country":"ES",
    "sg:address":"Pg Miramar (de), 91",
    "sg:city":"Salou",
    "sg:orig_category":"Restaurantes",
    "sg:phone":"+34 977 38 54 67",
    "sg:postcode":"43840",
    "sg:province":"Tarragona",
    "wof:name":"Perez Marin Jose",
    "wof:placetype":"venue"
},
  "geometry": {"coordinates":[1.1308000088,41.0755195618],"type":"Point"}
}