{
  "type": "Feature",
  "properties": {
    "iso:country":"ES",
    "sg:address":"Plaz Conde Luna, 5",
    "sg:city":"Benavides De Orbigo",
    "sg:orig_category":"Bancos",
    "sg:phone":"+34 987 37 01 02",
    "sg:postcode":"24280",
    "sg:province":"Le\u00f3n",
    "wof:name":"Banc Sabadell S.a.",
    "wof:placetype":"venue"
},
  "geometry": {"coordinates":[-5.9000339508,42.5035362244],"type":"Point"}
}