{
  "type": "Feature",
  "properties": {
    "iso:country":"ES",
    "sg:address":"Calle de Paris, 41",
    "sg:city":"Malaga",
    "sg:orig_category":"Muebles, Minoristas",
    "sg:phone":"+34 952 34 81 88",
    "sg:postcode":"29006",
    "sg:province":"M\u00e1laga",
    "sg:website":"www.tiendasbricomania.com",
    "wof:name":"Atlas Informatica S.l.",
    "wof:placetype":"venue"
},
  "geometry": {"coordinates":[-4.4728369713,36.7024803162],"type":"Point"}
}