{
  "type": "Feature",
  "properties": {
    "iso:country":"ES",
    "sg:address":"Cmno Lobas, S/n",
    "sg:city":"Laguna Duero",
    "sg:orig_category":"Contenedores (mercanc\u00cdas)",
    "sg:phone":"+34 983 54 00 99",
    "sg:postcode":"47140",
    "sg:province":"Valladolid",
    "wof:name":"Aja Morchon Distribuciones S.l.",
    "wof:placetype":"venue"
},
  "geometry": {"coordinates":[-4.7321448326,41.5690879822],"type":"Point"}
}