{
  "type": "Feature",
  "properties": {
    "addr:full":"Calle de Covadonga, 4 Arriondas Asturias 33540",
    "addr:housenumber":"4",
    "addr:postcode":"33540",
    "addr:street":"Calle De Covadonga",
    "iso:country":"ES",
    "sg:address":"Calle de Covadonga, 4",
    "sg:city":"Arriondas",
    "sg:orig_category":"Asociaciones Y Clubs Deportivos",
    "sg:phone":"+34 985 84 05 62",
    "sg:postcode":"33540",
    "sg:province":"Asturias",
    "sg:website":"www.descensodelsella.com",
    "wof:name":"Comite Organizador Del Descenso Internacional Del Sella",
    "wof:placetype":"venue"
},
  "geometry": {"coordinates":[-5.1878919601,43.3891143799],"type":"Point"}
}