{
  "type": "Feature",
  "properties": {
    "addr:full":"Calle de Carolinas, 3 Madrid Madrid 28039",
    "addr:housenumber":"3",
    "addr:postcode":"28039",
    "addr:street":"Calle De Carolinas",
    "iso:country":"ES",
    "sg:address":"Calle de Carolinas, 3",
    "sg:city":"Madrid",
    "sg:orig_category":"Farmacias",
    "sg:phone":"+34 915 34 23 73",
    "sg:postcode":"28039",
    "sg:province":"Madrid",
    "wof:name":"Lopez Rodriguez Maria Victoria",
    "wof:placetype":"venue"
},
  "geometry": {"coordinates":[-3.703555584,40.4510917664],"type":"Point"}
}