{
  "type": "Feature",
  "properties": {
    "addr:full":"Calle-f P I Valdeferrin, 27 Ejea Caballeros Zaragoza 50600",
    "addr:housenumber":"27",
    "addr:postcode":"50600",
    "addr:street":"Calle-F;Valdeferrin",
    "iso:country":"ES",
    "sg:address":"Calle-f P I Valdeferrin, 27",
    "sg:city":"Ejea Caballeros",
    "sg:orig_category":"Sales (al Por Mayor)",
    "sg:phone":"+34 976 66 77 20",
    "sg:postcode":"50600",
    "sg:province":"Zaragoza",
    "wof:name":"Saez Senero Ana Belen",
    "wof:placetype":"venue"
},
  "geometry": {"coordinates":[-1.1382750273,42.1269798279],"type":"Point"}
}