{
  "type": "Feature",
  "properties": {
    "iso:country":"ES",
    "sg:address":"Calle de Rosario, 4",
    "sg:city":"Viso Del Alcor",
    "sg:orig_category":"Supermercados Y Hipermercados",
    "sg:phone":"+34 955 94 53 56",
    "sg:postcode":"41520",
    "sg:province":"Sevilla",
    "wof:name":"Ferrusola Jimenez Maria Antonia",
    "wof:placetype":"venue"
},
  "geometry": {"coordinates":[-5.7223310471,37.3866920471],"type":"Point"}
}