{
  "type": "Feature",
  "properties": {
    "addr:full":"Carr Cecili Metel, 78 Pollen\u00e7a Islas Baleares 07460",
    "addr:housenumber":"78",
    "addr:postcode":"07460",
    "addr:street":"Carr Cecili Metel",
    "iso:country":"ES",
    "sg:address":"Carr Cecili Metel, 78",
    "sg:city":"Pollen\u00e7a",
    "sg:orig_category":"Promotores Constructores",
    "sg:phone":"+34 971 53 05 87",
    "sg:postcode":"07460",
    "sg:province":"Islas Baleares",
    "wof:name":"Construcciones Manuel Alvarez S.l.",
    "wof:placetype":"venue"
},
  "geometry": {"coordinates":[3.0154700279,39.8734855652],"type":"Point"}
}