{
  "type": "Feature",
  "properties": {
    "addr:full":"Calle de Dos De Mayo, 3 Puente-genil C\u00f3rdoba 14500",
    "addr:housenumber":"3",
    "addr:postcode":"14500",
    "addr:street":"Calle De Dos De Mayo;Co\u0301Rdoba",
    "iso:country":"ES",
    "sg:address":"Calle de Dos De Mayo, 3",
    "sg:city":"Puente-genil",
    "sg:orig_category":"Ropa Para Se\u00d1oras (al Por Menor)",
    "sg:phone":"+34 957 60 03 86",
    "sg:postcode":"14500",
    "sg:province":"C\u00f3rdoba",
    "wof:name":"Casting Coleccion Moda S.l.",
    "wof:placetype":"venue"
},
  "geometry": {"coordinates":[-4.7779579163,37.3909187317],"type":"Point"}
}