{
  "type": "Feature",
  "properties": {
    "addr:full":"Carrer de Emili Pascual, 14 Esparreguera Barcelona 08292",
    "addr:housenumber":"14",
    "addr:postcode":"08292",
    "addr:street":"Carrer De Emili Pascual",
    "iso:country":"ES",
    "sg:address":"Carrer de Emili Pascual, 14",
    "sg:city":"Esparreguera",
    "sg:orig_category":"Inform\u00c1tica (estudios, Servicios, Asesor\u00cda, Formaci\u00d3n)",
    "sg:phone":"+34 937 77 70 63",
    "sg:postcode":"08292",
    "sg:province":"Barcelona",
    "wof:name":"Garriga Vernis Juan Antonio",
    "wof:placetype":"venue"
},
  "geometry": {"coordinates":[1.8127340078,41.5431747437],"type":"Point"}
}