{
  "type": "Feature",
  "properties": {
    "addr:full":"Calle de Pino Alto, 33 Pino Alto-santa Ursula Santa Cruz De Tenerife 38390",
    "addr:housenumber":"33",
    "addr:postcode":"38390",
    "addr:street":"Calle De Pino Alto",
    "iso:country":"ES",
    "sg:address":"Calle de Pino Alto, 33",
    "sg:city":"Pino Alto-santa Ursula",
    "sg:orig_category":"Estancos",
    "sg:phone":"+34 922 33 70 11",
    "sg:postcode":"38390",
    "sg:province":"Santa Cruz De Tenerife",
    "wof:name":"Mederos Diaz Rodolfo",
    "wof:placetype":"venue"
},
  "geometry": {"coordinates":[-16.4985561371,28.409866333],"type":"Point"}
}