{
  "type": "Feature",
  "properties": {
    "addr:full":"Ramalleira, 7 Ramalleira Pontevedra 36140",
    "addr:housenumber":"7",
    "addr:postcode":"36140",
    "addr:street":"Ramalleira",
    "iso:country":"ES",
    "sg:address":"Ramalleira, 7",
    "sg:city":"Ramalleira",
    "sg:orig_category":"Cer\u00c1micas: Material Y Suministros",
    "sg:phone":"+34 986 67 90 10",
    "sg:postcode":"36140",
    "sg:province":"Pontevedra",
    "wof:name":"Felix Ferre\u00f1o S.l.",
    "wof:placetype":"venue"
},
  "geometry": {"coordinates":[-8.6514892578,42.3227615356],"type":"Point"}
}