{
  "type": "Feature",
  "properties": {
    "iso:country":"ES",
    "sg:address":"Calle de General Benavides, 2",
    "sg:city":"Le\u00f3n",
    "sg:orig_category":"Transportes En Volquetes Basculantes",
    "sg:phone":"+34 987 20 12 80",
    "sg:postcode":"24005",
    "sg:province":"Le\u00f3n",
    "wof:name":"Excavaciones Hermanos Moran S.l.",
    "wof:placetype":"venue"
},
  "geometry": {"coordinates":[-5.564435482,42.5903282166],"type":"Point"}
}