{
  "type": "Feature",
  "properties": {
    "iso:country":"ES",
    "sg:address":"Novecientos Uno (mayorazgo), 2",
    "sg:city":"Sta Cruz Tenerife",
    "sg:orig_category":"Agencias De Aduana",
    "sg:phone":"+34 922 20 78 10",
    "sg:postcode":"38010",
    "sg:province":"Santa Cruz De Tenerife",
    "sg:website":"www.redur.es",
    "wof:name":"Cargosur Canarias S.l.",
    "wof:placetype":"venue"
},
  "geometry": {"coordinates":[-16.3302192688,28.4371891022],"type":"Point"}
}