{
  "type": "Feature",
  "properties": {
    "addr:full":"Barr Meabe, 37 Meabe Vizcaya 48279",
    "addr:housenumber":"37",
    "addr:postcode":"48279",
    "addr:street":"Meabe",
    "iso:country":"ES",
    "sg:address":"Barr Meabe, 37",
    "sg:city":"Meabe",
    "sg:orig_category":"M\u00c1rmoles, Granitos Y Piedras Naturales",
    "sg:phone":"+34 946 16 76 01",
    "sg:postcode":"48279",
    "sg:province":"Vizcaya",
    "wof:name":"Marmoles Markina S.l.",
    "wof:placetype":"venue"
},
  "geometry": {"coordinates":[-2.5078349113,43.2667007446],"type":"Point"}
}