{
  "type": "Feature",
  "properties": {
    "addr:full":"Carrer de Anselm Clave, 10 Granollers Barcelona 08401",
    "addr:housenumber":"10",
    "addr:postcode":"08401",
    "addr:street":"Carrer De Anselm Clave",
    "iso:country":"ES",
    "sg:address":"Carrer de Anselm Clave, 10",
    "sg:city":"Granollers",
    "sg:orig_category":"Complementos De Vestir (al Por Menor)",
    "sg:phone":"+34 938 70 20 26",
    "sg:postcode":"08401",
    "sg:province":"Barcelona",
    "sg:website":"www.benetton.com",
    "wof:name":"Duran Ramos Tania",
    "wof:placetype":"venue"
},
  "geometry": {"coordinates":[2.2887449265,41.6080513],"type":"Point"}
}