{
  "type": "Feature",
  "properties": {
    "iso:country":"ES",
    "sg:address":"Carr Alcalde Juan Sancho, 5",
    "sg:city":"Oliva",
    "sg:orig_category":"Animales (al Por Menor)",
    "sg:phone":"+34 962 83 80 26",
    "sg:postcode":"46780",
    "sg:province":"Valencia",
    "wof:name":"Gregori Agud Vicenta",
    "wof:placetype":"venue"
},
  "geometry": {"coordinates":[-0.1187627017,38.9225654602],"type":"Point"}
}