{
  "type": "Feature",
  "properties": {
    "iso:country":"ES",
    "sg:address":"Carr Begur, 119",
    "sg:city":"Palafrugell",
    "sg:orig_category":"Ense\u00d1anza Variada",
    "sg:phone":"+34 972 61 19 97",
    "sg:postcode":"17200",
    "sg:province":"Girona",
    "sg:website":"www.mecacentre.com",
    "wof:name":"Meca Centre S.l.",
    "wof:placetype":"venue"
},
  "geometry": {"coordinates":[3.1597599983,41.9181594849],"type":"Point"}
}