{
  "type": "Feature",
  "properties": {
    "iso:country":"ES",
    "sg:address":"Calle de Charles Darwin, S/n",
    "sg:city":"Sevilla",
    "sg:orig_category":"Farmacias",
    "sg:phone":"+34 954 46 12 74",
    "sg:postcode":"41092",
    "sg:province":"Sevilla",
    "wof:name":"Junco Sanz Maria Del Pino",
    "wof:placetype":"venue"
},
  "geometry": {"coordinates":[-6.0056385994,37.4022331238],"type":"Point"}
}