{
  "type": "Feature",
  "properties": {
    "iso:country":"ES",
    "sg:address":"Cami Vell Avinyonet, 17",
    "sg:city":"Vilafant",
    "sg:orig_category":"Inmobiliaria (agencias)",
    "sg:phone":"+34 972 51 13 36",
    "sg:postcode":"17740",
    "sg:province":"Girona",
    "wof:name":"Inmodas Emporda S.l.",
    "wof:placetype":"venue"
},
  "geometry": {"coordinates":[2.9358100891,42.2463035583],"type":"Point"}
}