{
  "type": "Feature",
  "properties": {
    "addr:full":"Mtra D Benilde Perez Lainez, 1 Caudiel Castell\u00f3n 12440",
    "addr:housenumber":"1",
    "addr:postcode":"12440",
    "addr:street":"Mtra;Lainez;Castello\u0301N",
    "iso:country":"ES",
    "sg:address":"Mtra D Benilde Perez Lainez, 1",
    "sg:city":"Caudiel",
    "sg:orig_category":"Cooperativas Agr\u00cdcolas",
    "sg:phone":"+34 964 14 44 01",
    "sg:postcode":"12440",
    "sg:province":"Castell\u00f3n",
    "wof:name":"Cooperativa Agricola San Isidro De Caudiel",
    "wof:placetype":"venue"
},
  "geometry": {"coordinates":[-0.5679320097,39.9473381042],"type":"Point"}
}