{
  "type": "Feature",
  "properties": {
    "iso:country":"ES",
    "sg:address":"Carrer de Angel Guimera, 49",
    "sg:city":"Manresa",
    "sg:orig_category":"Relojer\u00cda (al Por Menor, Reparaci\u00d3n)",
    "sg:phone":"+34 938 72 39 61",
    "sg:postcode":"08241",
    "sg:province":"Barcelona",
    "wof:name":"Tarrago Costa Maria Merce",
    "wof:placetype":"venue"
},
  "geometry": {"coordinates":[1.8240129948,41.7279281616],"type":"Point"}
}