{
  "type": "Feature",
  "properties": {
    "iso:country":"ES",
    "sg:address":"Ctr De La Solana, S/n",
    "sg:city":"Membrilla",
    "sg:orig_category":"Material Y Herramientas Agr\u00cdcolas",
    "sg:phone":"+34 926 63 71 51",
    "sg:postcode":"13230",
    "sg:province":"Ciudad Real",
    "wof:name":"Agrobellon",
    "wof:placetype":"venue"
},
  "geometry": {"coordinates":[-3.3187470436,38.9197921753],"type":"Point"}
}