{
  "type": "Feature",
  "properties": {
    "iso:country":"ES",
    "sg:address":"Carrer de Joaquin Costa, 50",
    "sg:city":"Barcelona",
    "sg:orig_category":"M\u00c1quinas De Escribir, M\u00c1quinas De Oficina (al Por Menor, Reparaci\u00d3n)",
    "sg:phone":"+34 933 18 49 68",
    "sg:postcode":"08001",
    "sg:province":"Barcelona",
    "sg:website":"www.empreses.net/comercjs",
    "wof:name":"Sanchez Alarcon Jorge",
    "wof:placetype":"venue"
},
  "geometry": {"coordinates":[2.1652801037,41.3831367493],"type":"Point"}
}