{
  "type": "Feature",
  "properties": {
    "addr:full":"Calle de Antonio Machado, 2 Nerva Huelva 21670",
    "addr:housenumber":"2",
    "addr:postcode":"21670",
    "addr:street":"Calle De Antonio Machado",
    "iso:country":"ES",
    "sg:address":"Calle de Antonio Machado, 2",
    "sg:city":"Nerva",
    "sg:orig_category":"Museos",
    "sg:phone":"+34 959 58 28 11",
    "sg:postcode":"21670",
    "sg:province":"Huelva",
    "sg:website":"www.vazquezdiaz.org",
    "wof:name":"Museo Vazquez Diaz",
    "wof:placetype":"venue"
},
  "geometry": {"coordinates":[-6.5493292809,37.6945648193],"type":"Point"}
}