{
  "type": "Feature",
  "properties": {
    "iso:country":"ES",
    "sg:address":"C/ Valencia, 4",
    "sg:city":"Ripollet",
    "sg:orig_category":"Empresas De Carpinter\u00cda Met\u00c1lica",
    "sg:phone":"+34 936 92 44 39",
    "sg:postcode":"08291",
    "sg:province":"Barcelona",
    "wof:name":"Franher Construcciones Metalicas S.l.",
    "wof:placetype":"venue"
},
  "geometry": {"coordinates":[2.1696660519,41.4946937561],"type":"Point"}
}