{
  "type": "Feature",
  "properties": {
    "iso:country":"ES",
    "sg:address":"Calle de Ventura Rodriguez, 1",
    "sg:city":"Oviedo",
    "sg:orig_category":"Art\u00cdculos De Regalo (al Por Menor)",
    "sg:phone":"+34 985 24 41 26",
    "sg:postcode":"33004",
    "sg:province":"Asturias",
    "wof:name":"Gayoso Hernandez Maria Ascension",
    "wof:placetype":"venue"
},
  "geometry": {"coordinates":[-5.8539810181,43.364616394],"type":"Point"}
}