{
  "type": "Feature",
  "properties": {
    "addr:full":"Altzate Karrika, 34 Bera Navarra 31780",
    "addr:housenumber":"34",
    "addr:postcode":"31780",
    "addr:street":"Karrika",
    "iso:country":"ES",
    "sg:address":"Altzate Karrika, 34",
    "sg:city":"Bera",
    "sg:orig_category":"Molduras, Junquillos, Listones Y Molduras Perforadas",
    "sg:phone":"+34 948 63 01 79",
    "sg:postcode":"31780",
    "sg:province":"Navarra",
    "wof:name":"Alzugaray Alzuguren Fidel",
    "wof:placetype":"venue"
},
  "geometry": {"coordinates":[-1.6804430485,43.2816047668],"type":"Point"}
}