{
  "type": "Feature",
  "properties": {
    "addr:full":"Calle de Juan De Austria, 40 Playa De Arinaga Las Palmas 35118",
    "addr:housenumber":"40",
    "addr:postcode":"35118",
    "addr:street":"Calle De Juan De Austria",
    "iso:country":"ES",
    "sg:address":"Calle de Juan De Austria, 40",
    "sg:city":"Playa De Arinaga",
    "sg:orig_category":"Pescader\u00cdas (al Por Menor)",
    "sg:phone":"+34 928 18 84 48",
    "sg:postcode":"35118",
    "sg:province":"Las Palmas",
    "wof:name":"Estevez Santana Rafael",
    "wof:placetype":"venue"
},
  "geometry": {"coordinates":[-15.3951740265,27.8587493896],"type":"Point"}
}