{
  "type": "Feature",
  "properties": {
    "addr:full":"Calle de Baleares, 33 Conil De La Frontera C\u00e1diz 11140",
    "addr:housenumber":"33",
    "addr:postcode":"11140",
    "addr:street":"Calle De Baleares",
    "iso:country":"ES",
    "sg:address":"Calle de Baleares, 33",
    "sg:city":"Conil De La Frontera",
    "sg:orig_category":"Guarder\u00cdas",
    "sg:phone":"+34 956 44 17 45",
    "sg:postcode":"11140",
    "sg:province":"C\u00e1diz",
    "wof:name":"Moreno Aragon Antonia Maria",
    "wof:placetype":"venue"
},
  "geometry": {"coordinates":[-6.0842885971,36.2810592651],"type":"Point"}
}