{
  "type": "Feature",
  "properties": {
    "iso:country":"ES",
    "sg:address":"Avda Paz (la), 59",
    "sg:city":"Viso Del Alcor",
    "sg:classifiers":[
        {
            "category":"Taxi",
            "type":"Transportation"
        }
    ],
    "sg:phone":"+34 955 94 55 12",
    "sg:postcode":"41520",
    "sg:province":"Sevilla",
    "wof:name":"Franco Sanchez Jose Antonio",
    "wof:placetype":"venue"
},
  "geometry": {"coordinates":[-5.726336956,37.3801727295],"type":"Point"}
}