{
  "type": "Feature",
  "properties": {
    "iso:country":"ES",
    "sg:address":"Avda Costa Blanca, 16",
    "sg:city":"Alacant",
    "sg:orig_category":"Ingeniero",
    "sg:phone":"+34 965 16 38 67",
    "sg:postcode":"03540",
    "sg:province":"Alicante",
    "wof:name":"Vivatel Gestiones Telefonicas S.l.",
    "wof:placetype":"venue"
},
  "geometry": {"coordinates":[-0.4326271117,38.3614234924],"type":"Point"}
}