{
  "type": "Feature",
  "properties": {
    "iso:country":"ES",
    "sg:address":"Carrer de Doctor Salarich, 6",
    "sg:city":"Vic",
    "sg:orig_category":"Centros P\u00dablicos De Formaci\u00d3n Profesional Y T\u00c9cnica",
    "sg:phone":"+34 938 83 21 69",
    "sg:postcode":"08500",
    "sg:province":"Barcelona",
    "wof:name":"Co%egi De Fisioterapeutes De Catalunya",
    "wof:placetype":"venue"
},
  "geometry": {"coordinates":[2.2538950443,41.9236373901],"type":"Point"}
}