{
  "type": "Feature",
  "properties": {
    "addr:full":"Calle de Carretera De Almeria, 29 Adra Almer\u00eda 04770",
    "addr:housenumber":"29",
    "addr:postcode":"04770",
    "addr:street":"Calle De Carretera De Almeria;Almeri\u0301A",
    "iso:country":"ES",
    "sg:address":"Calle de Carretera De Almeria, 29",
    "sg:city":"Adra",
    "sg:orig_category":"Autob\u00das (explotaci\u00d3n Y Servicios De)",
    "sg:phone":"+34 950 40 10 56",
    "sg:postcode":"04770",
    "sg:province":"Almer\u00eda",
    "wof:name":"Viajes Rodriblan S.l.",
    "wof:placetype":"venue"
},
  "geometry": {"coordinates":[-2.998388052,36.7483940125],"type":"Point"}
}