{
  "type": "Feature",
  "properties": {
    "iso:country":"ES",
    "sg:address":"Av Ramon Y Cajal, 2",
    "sg:city":"Moncofa",
    "sg:orig_category":"\u00d3ptica: Instrumentos (fabricaci\u00d3n)",
    "sg:phone":"+34 964 58 06 91",
    "sg:postcode":"12593",
    "sg:province":"Castell\u00f3n",
    "wof:name":"Navarro Salvador Juan",
    "wof:placetype":"venue"
},
  "geometry": {"coordinates":[-0.1444710046,39.8074035645],"type":"Point"}
}