{
  "type": "Feature",
  "properties": {
    "addr:full":"Carr Major, 4 Campos Islas Baleares 07630",
    "addr:housenumber":"4",
    "addr:postcode":"07630",
    "addr:street":"Carr Major",
    "iso:country":"ES",
    "sg:address":"Carr Major, 4",
    "sg:city":"Campos",
    "sg:orig_category":"Servicios De Telecomunicaciones",
    "sg:phone":"+34 971 65 08 34",
    "sg:postcode":"07630",
    "sg:province":"Islas Baleares",
    "wof:name":"Mamarniels S.l.",
    "wof:placetype":"venue"
},
  "geometry": {"coordinates":[3.0188989639,39.4312095642],"type":"Point"}
}