{
  "type": "Feature",
  "properties": {
    "addr:full":"Calle de Soliva, 11 Malaga M\u00e1laga 29007",
    "addr:housenumber":"11",
    "addr:postcode":"29007",
    "addr:street":"Calle De Soliva;Ma\u0301Laga",
    "iso:country":"ES",
    "sg:address":"Calle de Soliva, 11",
    "sg:city":"Malaga",
    "sg:orig_category":"Controles De Edificaci\u00d3n (construcci\u00d3n, Seguridad)",
    "sg:phone":"+34 952 07 22 16",
    "sg:postcode":"29007",
    "sg:province":"M\u00e1laga",
    "wof:name":"Invisol S.l.",
    "wof:placetype":"venue"
},
  "geometry": {"coordinates":[-4.4523282051,36.7220687866],"type":"Point"}
}