{
  "type": "Feature",
  "properties": {
    "iso:country":"ES",
    "sg:address":"Avda Hermanos Bou, 2",
    "sg:city":"Castellon",
    "sg:orig_category":"Transportes Por Carretera: Lotes Completos, Mercanc\u00cdas Diversas",
    "sg:phone":"+34 964 22 08 05",
    "sg:postcode":"12003",
    "sg:province":"Castell\u00f3n",
    "wof:name":"Repredi S. A.",
    "wof:placetype":"venue"
},
  "geometry": {"coordinates":[-0.0338950008,39.9836883545],"type":"Point"}
}