{
  "type": "Feature",
  "properties": {
    "addr:full":"Rier Blanca, 89 Barcelona Barcelona 08028",
    "addr:housenumber":"89",
    "addr:postcode":"08028",
    "addr:street":"Rier Blanca",
    "iso:country":"ES",
    "sg:address":"Rier Blanca, 89",
    "sg:city":"Barcelona",
    "sg:orig_category":"Alimentaci\u00d3n General (al Por Menor)",
    "sg:phone":"+34 934 49 57 70",
    "sg:postcode":"08028",
    "sg:province":"Barcelona",
    "wof:name":"Escobar Romero Jose",
    "wof:placetype":"venue"
},
  "geometry": {"coordinates":[2.1261239052,41.3725357056],"type":"Point"}
}