{
  "type": "Feature",
  "properties": {
    "addr:full":"Carr Saragossa, 2 Lleida Lleida 25007",
    "addr:housenumber":"2",
    "addr:postcode":"25007",
    "addr:street":"Carr Saragossa",
    "iso:country":"ES",
    "sg:address":"Carr Saragossa, 2",
    "sg:city":"Lleida",
    "sg:orig_category":"Administradores De Bienes Y Delegados De Comunidades De Propietarios",
    "sg:phone":"+34 973 24 53 62",
    "sg:postcode":"25007",
    "sg:province":"Lleida",
    "wof:name":"Finques Sant Joan S.c.p.",
    "wof:placetype":"venue"
},
  "geometry": {"coordinates":[0.6276819706,41.61561203],"type":"Point"}
}