{
  "type": "Feature",
  "properties": {
    "iso:country":"ES",
    "sg:address":"C\u00f1o. Sartego-tellado, 34",
    "sg:city":"Fene",
    "sg:orig_category":"Asociaciones Y Clubs Deportivos",
    "sg:phone":"+34 981 34 26 15",
    "sg:postcode":"15500",
    "sg:province":"La Coru\u00f1a",
    "wof:name":"Club Atletismo Ria Ferrol",
    "wof:placetype":"venue"
},
  "geometry": {"coordinates":[-8.1644191742,43.4750747681],"type":"Point"}
}