{
  "type": "Feature",
  "properties": {
    "iso:country":"ES",
    "sg:address":"Pl El Salvador, 11",
    "sg:city":"Setla Mirarrosa",
    "sg:orig_category":"Iglesia Cat\u00d3lica",
    "sg:phone":"+34 966 47 43 94",
    "sg:postcode":"03779",
    "sg:province":"Alicante",
    "wof:name":"Parroquia Del Divino Salvador",
    "wof:placetype":"venue"
},
  "geometry": {"coordinates":[0.01609,38.8481712341],"type":"Point"}
}