{
  "type": "Feature",
  "properties": {
    "addr:full":"Av Estacio, 18 Blanes Girona 17300",
    "addr:housenumber":"18",
    "addr:postcode":"17300",
    "addr:street":"Av Estacio",
    "iso:country":"ES",
    "sg:address":"Av Estacio, 18",
    "sg:city":"Blanes",
    "sg:classifiers":[
        {
            "category":"Casinos & Gambling",
            "type":"Entertainment"
        }
    ],
    "sg:phone":"+34 972 35 28 94",
    "sg:postcode":"17300",
    "sg:province":"Girona",
    "sg:tags":[
        "locale",
        "de",
        "juego"
    ],
    "wof:name":"Torres Murillo Alfonso",
    "wof:placetype":"venue"
},
  "geometry": {"coordinates":[2.7765250206,41.6757049561],"type":"Point"}
}