{
  "type": "Feature",
  "properties": {
    "iso:country":"ES",
    "sg:address":"Aramanti, S/n",
    "sg:city":"Aramanti",
    "sg:orig_category":"Producci\u00d3n De Sidra",
    "sg:phone":"+34 985 74 83 42",
    "sg:postcode":"33518",
    "sg:province":"Asturias",
    "wof:name":"Autocares Hortal S. A.",
    "wof:placetype":"venue"
},
  "geometry": {"coordinates":[-5.5597882271,43.4101409912],"type":"Point"}
}