{
  "type": "Feature",
  "properties": {
    "addr:full":"Calle de Ortega De Prados, 11 Malaga M\u00e1laga 29010",
    "addr:housenumber":"11",
    "addr:postcode":"29010",
    "addr:street":"Calle De Ortega De Prados;Ma\u0301Laga",
    "iso:country":"ES",
    "sg:address":"Calle de Ortega De Prados, 11",
    "sg:city":"Malaga",
    "sg:orig_category":"Fabricaci\u00d3n, Venta De Cuadros, Accesorios Para Enmarcar",
    "sg:phone":"+34 952 39 28 50",
    "sg:postcode":"29010",
    "sg:province":"M\u00e1laga",
    "wof:name":"Representaciones Dobar S.l.",
    "wof:placetype":"venue"
},
  "geometry": {"coordinates":[-4.4551138878,36.7229576111],"type":"Point"}
}