{
  "type": "Feature",
  "properties": {
    "addr:full":"Calle de Gordillo, 12 Osuna Sevilla 41640",
    "addr:housenumber":"12",
    "addr:postcode":"41640",
    "addr:street":"Calle De Gordillo",
    "iso:country":"ES",
    "sg:address":"Calle de Gordillo, 12",
    "sg:city":"Osuna",
    "sg:orig_category":"M\u00c9dicos: An\u00c1lisis Cl\u00cdnicos",
    "sg:phone":"+34 955 82 02 07",
    "sg:postcode":"41640",
    "sg:province":"Sevilla",
    "wof:name":"Cruz Pinzon Rafael",
    "wof:placetype":"venue"
},
  "geometry": {"coordinates":[-5.1052241325,37.2387237549],"type":"Point"}
}