{
  "type": "Feature",
  "properties": {
    "iso:country":"ES",
    "sg:address":"Calle de General Mola, S/n",
    "sg:city":"Mu\u00f1ana",
    "sg:orig_category":"Empresarios",
    "sg:phone":"+34 920 23 13 73",
    "sg:postcode":"05540",
    "sg:province":"\u00c1vila",
    "wof:name":"Gomez Marquez Fernando",
    "wof:placetype":"venue"
},
  "geometry": {"coordinates":[-5.0146193504,40.5900840759],"type":"Point"}
}