{
  "type": "Feature",
  "properties": {
    "iso:country":"ES",
    "sg:address":"Calle de Aviacion, 8",
    "sg:city":"San Vicente Del Raspeig-sant Vicent Del Raspeig",
    "sg:orig_category":"Zapatos (al Por Menor)",
    "sg:phone":"+34 965 66 65 30",
    "sg:postcode":"03690",
    "sg:province":"Alicante",
    "wof:name":"El Ydrissi  Tourya",
    "wof:placetype":"venue"
},
  "geometry": {"coordinates":[-0.521294117,38.3948669434],"type":"Point"}
}