{
  "type": "Feature",
  "properties": {
    "addr:full":"Urb. Jardin De Llanera, 2 Lugo Asturias 33690",
    "addr:housenumber":"2",
    "addr:postcode":"33690",
    "iso:country":"ES",
    "sg:address":"Urb. Jardin De Llanera, 2",
    "sg:city":"Lugo",
    "sg:orig_category":"Negocio De Materiales De Construcci\u00d3n",
    "sg:phone":"+34 985 77 35 97",
    "sg:postcode":"33690",
    "sg:province":"Asturias",
    "wof:name":"Comercial De Preresa S.a.",
    "wof:placetype":"venue"
},
  "geometry": {"coordinates":[-5.810836792,43.4387741089],"type":"Point"}
}