{
  "type": "Feature",
  "properties": {
    "addr:full":"Avda Dilar (de), 84 Granada Granada 18007",
    "addr:housenumber":"84",
    "addr:postcode":"18007",
    "addr:street":"Avda Dilar De",
    "iso:country":"ES",
    "sg:address":"Avda Dilar (de), 84",
    "sg:city":"Granada",
    "sg:orig_category":"Droguer\u00cdas (al Por Menor)",
    "sg:phone":"+34 958 13 06 90",
    "sg:postcode":"18007",
    "sg:province":"Granada",
    "wof:name":"Pinturas Antequera S.l.",
    "wof:placetype":"venue"
},
  "geometry": {"coordinates":[-3.6006970406,37.1542243958],"type":"Point"}
}