{
  "type": "Feature",
  "properties": {
    "iso:country":"ES",
    "sg:address":"Carrer de Vasco Da Gama, 12",
    "sg:city":"Sabadell",
    "sg:orig_category":"Empresas De Operaciones Portuarias Y Elevaci\u00d3n De Mercanc\u00cdas",
    "sg:phone":"+34 937 11 59 89",
    "sg:postcode":"08204",
    "sg:province":"Barcelona",
    "wof:name":"Lozano Sanchez Margarita",
    "wof:placetype":"venue"
},
  "geometry": {"coordinates":[2.1198589802,41.5252952576],"type":"Point"}
}