{
  "type": "Feature",
  "properties": {
    "addr:full":"Calle de Molinos, 54 Granada Granada 18009",
    "addr:housenumber":"54",
    "addr:postcode":"18009",
    "addr:street":"Calle De Molinos",
    "iso:country":"ES",
    "sg:address":"Calle de Molinos, 54",
    "sg:city":"Granada",
    "sg:orig_category":"Fabricaci\u00d3n, Comercio De Flores Y Plantas Artificiales",
    "sg:phone":"+34 958 22 63 53",
    "sg:postcode":"18009",
    "sg:province":"Granada",
    "wof:name":"Quero Montoro Salvador",
    "wof:placetype":"venue"
},
  "geometry": {"coordinates":[-3.5915250778,37.1717071533],"type":"Point"}
}