{
  "type": "Feature",
  "properties": {
    "iso:country":"ES",
    "sg:address":"Carrer de Mestre Nicolau, 10",
    "sg:city":"Barcelona",
    "sg:orig_category":"Ropa Para Ni\u00d1os (al Por Menor)",
    "sg:phone":"+34 934 14 34 70",
    "sg:postcode":"08021",
    "sg:province":"Barcelona",
    "wof:name":"T.c. Barcelona S.l.",
    "wof:placetype":"venue"
},
  "geometry": {"coordinates":[2.1425440311,41.3933143616],"type":"Point"}
}