{
  "type": "Feature",
  "properties": {
    "iso:country":"ES",
    "sg:address":"Calle de Mayor, 10",
    "sg:city":"Hinojosos",
    "sg:orig_category":"Carnicer\u00cdas, Carnicer\u00cdas",
    "sg:phone":"+34 969 12 94 09",
    "sg:postcode":"16417",
    "sg:province":"Cuenca",
    "wof:name":"Ortega Ruiz Eduardo",
    "wof:placetype":"venue"
},
  "geometry": {"coordinates":[-2.8267509937,39.6038589478],"type":"Point"}
}