{
  "type": "Feature",
  "properties": {
    "iso:country":"ES",
    "sg:address":"Calle de Juan De Mena, 12",
    "sg:city":"Castro Urdiales",
    "sg:orig_category":"Electricidad: Instaladores",
    "sg:phone":"+34 942 87 00 20",
    "sg:postcode":"39700",
    "sg:province":"Cantabria",
    "wof:name":"Instalaciones Electricas Yoni-pisus S.l.",
    "wof:placetype":"venue"
},
  "geometry": {"coordinates":[-3.2206110954,43.3848609924],"type":"Point"}
}