{
  "type": "Feature",
  "properties": {
    "addr:full":"Calle de Rio Jarama, 140 Poligono Sta M. De Benquerencia Toledo 45007",
    "addr:housenumber":"140 poligono",
    "addr:postcode":"45007",
    "addr:street":"Calle De Rio Jarama;Sta M. De Benquerencia",
    "iso:country":"ES",
    "sg:address":"Calle de Rio Jarama, 140",
    "sg:city":"Poligono Sta M. De Benquerencia",
    "sg:orig_category":"Piezas Para Maquinaria Agr\u00cdcola",
    "sg:phone":"+34 925 25 45 57",
    "sg:postcode":"45007",
    "sg:province":"Toledo",
    "wof:name":"Cabello Maquinas Y Equipos, S.l",
    "wof:placetype":"venue"
},
  "geometry": {"coordinates":[-3.9443030357,39.8752746582],"type":"Point"}
}