{
  "type": "Feature",
  "properties": {
    "addr:full":"Grup Sagarminaga, 10 Bilbao Vizcaya 48004",
    "addr:housenumber":"10",
    "addr:postcode":"48004",
    "addr:street":"Grup Sagarminaga",
    "iso:country":"ES",
    "sg:address":"Grup Sagarminaga, 10",
    "sg:city":"Bilbao",
    "sg:orig_category":"Peluqueros: De Se\u00d1oras",
    "sg:phone":"+34 944 11 38 86",
    "sg:postcode":"48004",
    "sg:province":"Vizcaya",
    "wof:name":"Justo Rodriguez Mari Carmen",
    "wof:placetype":"venue"
},
  "geometry": {"coordinates":[-2.9111099243,43.2482070923],"type":"Point"}
}