{
  "type": "Feature",
  "properties": {
    "iso:country":"ES",
    "sg:address":"Ctra. Miraflores, S/n",
    "sg:city":"Sevilla",
    "sg:orig_category":"Empresarios",
    "sg:phone":"+34 954 36 02 72",
    "sg:postcode":"41008",
    "sg:province":"Sevilla",
    "wof:name":"Fundacion Indace",
    "wof:placetype":"venue"
},
  "geometry": {"coordinates":[-5.9501729012,37.4201316833],"type":"Point"}
}