{
  "type": "Feature",
  "properties": {
    "addr:full":"Avda Bahia (la), 1 Algeciras C\u00e1diz 11206",
    "addr:housenumber":"1;ca\u0301diz",
    "addr:postcode":"11206",
    "addr:street":"Avda Bahia La",
    "iso:country":"ES",
    "sg:address":"Avda Bahia (la), 1",
    "sg:city":"Algeciras",
    "sg:orig_category":"Distribuci\u00d3n De Petr\u00d3leo Y Derivados",
    "sg:phone":"+34 956 67 61 17",
    "sg:postcode":"11206",
    "sg:province":"C\u00e1diz",
    "wof:name":"Pescados Vaimar S.l.",
    "wof:placetype":"venue"
},
  "geometry": {"coordinates":[-5.5359191895,36.1193008423],"type":"Point"}
}