{
  "type": "Feature",
  "properties": {
    "addr:full":"Calle de Melquiades Biencinto, 38 Madrid Madrid 28053",
    "addr:housenumber":"38",
    "addr:postcode":"madrid;28053",
    "addr:street":"Calle De Melquiades Biencinto",
    "iso:country":"ES",
    "sg:address":"Calle de Melquiades Biencinto, 38",
    "sg:city":"Madrid",
    "sg:orig_category":"Mec\u00c1nico Del Autom\u00d3vil",
    "sg:phone":"+34 915 01 29 84",
    "sg:postcode":"28053",
    "sg:province":"Madrid",
    "wof:name":"Gomez Mora Jose",
    "wof:placetype":"venue"
},
  "geometry": {"coordinates":[-3.6704850197,40.3957290649],"type":"Point"}
}