{
  "type": "Feature",
  "properties": {
    "addr:full":"Calle de Amann, 3 Algorta Vizcaya 48992",
    "addr:housenumber":"3",
    "addr:postcode":"48992",
    "addr:street":"Calle De Amann",
    "iso:country":"ES",
    "sg:address":"Calle de Amann, 3",
    "sg:city":"Algorta",
    "sg:orig_category":"Asesor\u00cda Fiscal Y Jur\u00cddica",
    "sg:phone":"+34 944 91 47 01",
    "sg:postcode":"48992",
    "sg:province":"Vizcaya",
    "wof:name":"Esb Y Cia S.r.l.",
    "wof:placetype":"venue"
},
  "geometry": {"coordinates":[-3.0079972744,43.3379440308],"type":"Point"}
}