{
  "type": "Feature",
  "properties": {
    "iso:country":"ES",
    "sg:address":"Rosario, 24",
    "sg:city":"Gilena",
    "sg:orig_category":"Minerales (al Por Mayor)",
    "sg:phone":"+34 954 82 61 00",
    "sg:postcode":"41565",
    "sg:province":"Sevilla",
    "wof:name":"Taljedi S.l.",
    "wof:placetype":"venue"
},
  "geometry": {"coordinates":[-4.9191040993,37.2508506775],"type":"Point"}
}