{
  "type": "Feature",
  "properties": {
    "iso:country":"ES",
    "sg:address":"Calle de Juan Jose Perez Del Molino, 23",
    "sg:city":"Santander",
    "sg:orig_category":"Electrodom\u00c9sticos (al Por Menor)",
    "sg:phone":"+34 942 23 10 03",
    "sg:postcode":"39006",
    "sg:province":"Cantabria",
    "wof:name":"Arroyo Fernandez Francisco",
    "wof:placetype":"venue"
},
  "geometry": {"coordinates":[-3.8153176308,43.4649620056],"type":"Point"}
}