{
  "type": "Feature",
  "properties": {
    "iso:country":"ES",
    "sg:address":"Carrer de Sant Mateu, 17",
    "sg:city":"Xixona",
    "sg:orig_category":"Aparatos E Instalaci\u00d3n De Regad\u00cdos",
    "sg:phone":"+34 965 61 18 79",
    "sg:postcode":"03100",
    "sg:province":"Alicante",
    "wof:name":"Angel Chorro E Hijos S.l.",
    "wof:placetype":"venue"
},
  "geometry": {"coordinates":[-0.5068824291,38.5469474792],"type":"Point"}
}