{
  "type": "Feature",
  "properties": {
    "iso:country":"ES",
    "sg:address":"Calle de Silvestre Ochoa, 11",
    "sg:city":"Castro Urdiales",
    "sg:orig_category":"Muebles Y Accesorios Para Cocinas Y Cuartos De Ba\u00d1o (al Por Menor)",
    "sg:phone":"+34 942 86 35 64",
    "sg:postcode":"39700",
    "sg:province":"Cantabria",
    "wof:name":"Arandilla Santamaria Purificacion Avelina",
    "wof:placetype":"venue"
},
  "geometry": {"coordinates":[-3.2262787819,43.3857727051],"type":"Point"}
}