{
  "type": "Feature",
  "properties": {
    "addr:full":"Avda Pablo Iglesias, 58 Gijon Asturias 33204",
    "addr:housenumber":"58",
    "addr:postcode":"33204",
    "addr:street":"Avda Pablo Iglesias",
    "iso:country":"ES",
    "sg:address":"Avda Pablo Iglesias, 58",
    "sg:city":"Gijon",
    "sg:orig_category":"Cajas Para Embalar",
    "sg:phone":"+34 985 37 02 52",
    "sg:postcode":"33204",
    "sg:province":"Asturias",
    "wof:name":"Caja Rural De Gijon",
    "wof:placetype":"venue"
},
  "geometry": {"coordinates":[-5.6525950432,43.5353164673],"type":"Point"}
}