{
  "type": "Feature",
  "properties": {
    "iso:country":"ES",
    "sg:address":"Calle de Llana, 2",
    "sg:city":"Pegalajar",
    "sg:orig_category":"Aceites Y Grasas Alimentarias (fabricaci\u00d3n, Al Por Mayor)",
    "sg:phone":"+34 953 36 00 16",
    "sg:postcode":"23110",
    "sg:province":"Ja\u00e9n",
    "wof:name":"Chica Jimenez Ana",
    "wof:placetype":"venue"
},
  "geometry": {"coordinates":[-3.6479001045,37.740524292],"type":"Point"}
}