{
  "type": "Feature",
  "properties": {
    "iso:country":"ES",
    "sg:address":"Calle de Lopez De Hoyos, 170",
    "sg:city":"Madrid",
    "sg:orig_category":"Centros Empresariales",
    "sg:phone":"+34 915 19 51 20",
    "sg:postcode":"28002",
    "sg:province":"Madrid",
    "sg:website":"motorshowfestival.com",
    "wof:name":"Motor Show Festival S.a.",
    "wof:placetype":"venue"
},
  "geometry": {"coordinates":[-3.6696898937,40.4469795227],"type":"Point"}
}