{
  "type": "Feature",
  "properties": {
    "addr:full":"Rua Casti\u00d1eiros (dos), 11 Santiago De Compostela La Coru\u00f1a 15705",
    "addr:housenumber":"11",
    "addr:postcode":"15705",
    "addr:street":"Rua Castin\u0303Eiros Dos;Corun\u0303A",
    "iso:country":"ES",
    "sg:address":"Rua Casti\u00d1eiros (dos), 11",
    "sg:city":"Santiago De Compostela",
    "sg:orig_category":"Imprenta",
    "sg:phone":"+34 981 56 06 38",
    "sg:postcode":"15705",
    "sg:province":"La Coru\u00f1a",
    "wof:name":"Gutenberg Impresores S.l.",
    "wof:placetype":"venue"
},
  "geometry": {"coordinates":[-8.5448694229,42.8855514526],"type":"Point"}
}