{
  "type": "Feature",
  "properties": {
    "addr:full":"Calle de Juan Ramon Jimenez, S/n Granada Granada 18015",
    "addr:postcode":"18015",
    "addr:street":"Calle De Juan Ramon Jimenez S / N",
    "iso:country":"ES",
    "sg:address":"Calle de Juan Ramon Jimenez, S/n",
    "sg:city":"Granada",
    "sg:orig_category":"Confecci\u00d3n De Trajes Para Se\u00d1oras",
    "sg:phone":"+34 958 20 03 49",
    "sg:postcode":"18015",
    "sg:province":"Granada",
    "wof:name":"Santos Terribas Rosario",
    "wof:placetype":"venue"
},
  "geometry": {"coordinates":[-3.6250839233,37.1898155212],"type":"Point"}
}