{
  "type": "Feature",
  "properties": {
    "iso:country":"ES",
    "sg:address":"Ctra Palma(barreros), 28",
    "sg:city":"Cartagena",
    "sg:classifiers":[
        {
            "category":"Autos & Motor Vehicles",
            "subcategory":"Automobile Sales",
            "type":"Retail Goods"
        }
    ],
    "sg:phone":"+34 968 53 59 59",
    "sg:postcode":"30310",
    "sg:province":"Murcia",
    "wof:name":"Auto Escuela Iter S.l.",
    "wof:placetype":"venue"
},
  "geometry": {"coordinates":[-1.1544963121,37.611743927],"type":"Point"}
}