{
  "type": "Feature",
  "properties": {
    "iso:country":"ES",
    "sg:address":"Calle de Vicente Vallina, 10",
    "sg:city":"Langreo",
    "sg:orig_category":"Zapatos (al Por Menor)",
    "sg:phone":"+34 985 67 48 03",
    "sg:postcode":"33900",
    "sg:province":"Asturias",
    "wof:name":"Fernandez Lozano Otilia",
    "wof:placetype":"venue"
},
  "geometry": {"coordinates":[-5.6766247749,43.2915153503],"type":"Point"}
}