{
  "type": "Feature",
  "properties": {
    "addr:full":"Calle de Rufino, 6 Cuesta Santa Cruz De Tenerife 38320",
    "addr:housenumber":"6",
    "addr:postcode":"38320",
    "addr:street":"Calle De Rufino",
    "iso:country":"ES",
    "sg:address":"Calle de Rufino, 6",
    "sg:city":"Cuesta",
    "sg:orig_category":"Asociaciones Humanitarias, De Cooperaci\u00d3n, De Acci\u00d3n Social",
    "sg:phone":"+34 922 64 89 59",
    "sg:postcode":"38320",
    "sg:province":"Santa Cruz De Tenerife",
    "wof:name":"Asociacion Con P.c.i. San Lazaro Amor A Los Ni\u00f1os",
    "wof:placetype":"venue"
},
  "geometry": {"coordinates":[-16.2947444916,28.4630260468],"type":"Point"}
}