{
  "type": "Feature",
  "properties": {
    "addr:full":"Eivissa, 11 S. Miquel Balansat Islas Baleares 07815",
    "addr:housenumber":"11",
    "addr:postcode":"07815",
    "addr:street":"Eivissa;S. Miquel Balansat",
    "iso:country":"ES",
    "sg:address":"Eivissa, 11",
    "sg:city":"S. Miquel Balansat",
    "sg:orig_category":"Agentes Generales De Seguros",
    "sg:phone":"+34 971 33 47 17",
    "sg:postcode":"07815",
    "sg:province":"Islas Baleares",
    "wof:name":"Daroca Fontana Vicente",
    "wof:placetype":"venue"
},
  "geometry": {"coordinates":[1.4415199757,39.0782051086],"type":"Point"}
}