{
  "type": "Feature",
  "properties": {
    "addr:full":"Carretera Madrid-coru\u00f1a, Km. 0386,0 Ponferrada Le\u00f3n 24400",
    "addr:postcode":"24400",
    "addr:street":"Carretera Madrid-Corun\u0303A Km. 0386,0;Leo\u0301N",
    "iso:country":"ES",
    "sg:address":"Carretera Madrid-coru\u00f1a, Km. 0386,0",
    "sg:city":"Ponferrada",
    "sg:orig_category":"Congelados: Productos Alimentarios (fabricaci\u00d3n, Al Por Mayor)",
    "sg:phone":"+34 987 40 97 42",
    "sg:postcode":"24400",
    "sg:province":"Le\u00f3n",
    "wof:name":"Al Fresco Del Bierzo Sl",
    "wof:placetype":"venue"
},
  "geometry": {"coordinates":[-6.5687417984,42.5531463623],"type":"Point"}
}