{
  "type": "Feature",
  "properties": {
    "iso:country":"ES",
    "sg:address":"Ctra Tarahales De Los, 89",
    "sg:city":"Palmas De Gran Canaria",
    "sg:orig_category":"Contenedores (mercanc\u00cdas)",
    "sg:phone":"+34 928 41 28 96",
    "sg:postcode":"35013",
    "sg:province":"Las Palmas",
    "wof:name":"Diaz Martel Maria Concepcion",
    "wof:placetype":"venue"
},
  "geometry": {"coordinates":[-15.5745563507,28.1141796112],"type":"Point"}
}