{
  "type": "Feature",
  "properties": {
    "iso:country":"ES",
    "sg:address":"Covadonga, 23",
    "sg:city":"Infiesto",
    "sg:orig_category":"Material Y Suministros Para Veterinarios",
    "sg:phone":"+34 985 71 15 01",
    "sg:postcode":"33530",
    "sg:province":"Asturias",
    "sg:website":"www.infiesto.comercialmati",
    "wof:name":"Blanco Gonzalez Isabel",
    "wof:placetype":"venue"
},
  "geometry": {"coordinates":[-5.3634881973,43.3474502563],"type":"Point"}
}