{
  "type": "Feature",
  "properties": {
    "iso:country":"ES",
    "sg:address":"Pla\u00c7 Sant Pere, 14",
    "sg:city":"Alfarras",
    "sg:orig_category":"Alquiler De V\u00cddeo",
    "sg:phone":"+34 973 76 01 62",
    "sg:postcode":"25120",
    "sg:province":"Lleida",
    "wof:name":"Provid Instant S.l",
    "wof:placetype":"venue"
},
  "geometry": {"coordinates":[0.5706400275,41.8297424316],"type":"Point"}
}