{
  "type": "Feature",
  "properties": {
    "addr:full":"Calle de Junco, 77 Malaga M\u00e1laga 29190",
    "addr:housenumber":"77",
    "addr:postcode":"29190",
    "addr:street":"Calle De Junco;Ma\u0301Laga",
    "iso:country":"ES",
    "sg:address":"Calle de Junco, 77",
    "sg:city":"Malaga",
    "sg:orig_category":"Empresarios",
    "sg:phone":"+34 952 43 11 44",
    "sg:postcode":"29190",
    "sg:province":"M\u00e1laga",
    "wof:name":"Aranda Leiva Francisco",
    "wof:placetype":"venue"
},
  "geometry": {"coordinates":[-4.4900574684,36.7422904968],"type":"Point"}
}