{
  "type": "Feature",
  "properties": {
    "addr:full":"C\u00f1o. Barreiras, S/n Hio Pontevedra 36948",
    "addr:housenumber":"s",
    "addr:postcode":"36948",
    "addr:street":"Cn\u0303O;/ N",
    "iso:country":"ES",
    "sg:address":"C\u00f1o. Barreiras, S/n",
    "sg:city":"Hio",
    "sg:orig_category":"Fotocopias, Reprograf\u00cda",
    "sg:phone":"+34 986 32 99 34",
    "sg:postcode":"36948",
    "sg:province":"Pontevedra",
    "wof:name":"Pena Gayo Marco Antonio",
    "wof:placetype":"venue"
},
  "geometry": {"coordinates":[-8.6428003311,42.4304618835],"type":"Point"}
}