{
  "type": "Feature",
  "properties": {
    "addr:full":"Calle de Valladolid, 4 Vitoria-gasteiz \u00c1lava 01002",
    "addr:housenumber":"4",
    "addr:postcode":"01002",
    "addr:street":"Calle De Valladolid",
    "iso:country":"ES",
    "sg:address":"Calle de Valladolid, 4",
    "sg:city":"Vitoria-gasteiz",
    "sg:orig_category":"Frutas, Legumbres Frescas Y Tempranas (al Por Menor)",
    "sg:phone":"+34 945 01 10 30",
    "sg:postcode":"01002",
    "sg:province":"\u00c1lava",
    "wof:name":"Frutas Bego\u00f1a, S.l",
    "wof:placetype":"venue"
},
  "geometry": {"coordinates":[-2.6636090279,42.8530006409],"type":"Point"}
}