{
  "type": "Feature",
  "properties": {
    "addr:full":"Calle de Diderot, 9 Malaga M\u00e1laga 29004",
    "addr:housenumber":"9",
    "addr:postcode":"29004",
    "addr:street":"Calle De Diderot;Ma\u0301Laga",
    "iso:country":"ES",
    "sg:address":"Calle de Diderot, 9",
    "sg:city":"Malaga",
    "sg:orig_category":"Agencias Y Agentes Comerciales, Representantes",
    "sg:phone":"+34 952 17 38 80",
    "sg:postcode":"29004",
    "sg:province":"M\u00e1laga",
    "wof:name":"Alcrespo S.l.",
    "wof:placetype":"venue"
},
  "geometry": {"coordinates":[-4.4711561203,36.6925010681],"type":"Point"}
}