{
  "type": "Feature",
  "properties": {
    "addr:full":"Carr Furs (els), 3 Picassent Valencia 46220",
    "addr:housenumber":"3",
    "addr:postcode":"46220",
    "addr:street":"Carr Furs Els",
    "iso:country":"ES",
    "sg:address":"Carr Furs (els), 3",
    "sg:city":"Picassent",
    "sg:orig_category":"Peluqueros: De Se\u00d1oras",
    "sg:phone":"+34 961 23 40 25",
    "sg:postcode":"46220",
    "sg:province":"Valencia",
    "wof:name":"Higueras Gomez Maria Victoria",
    "wof:placetype":"venue"
},
  "geometry": {"coordinates":[-0.4595290124,39.3631401062],"type":"Point"}
}