{
  "type": "Feature",
  "properties": {
    "addr:full":"Carr Bisbe Cardona, Del, 1 Eivissa Islas Baleares 07800",
    "addr:housenumber":"1",
    "addr:postcode":"07800",
    "addr:street":"Carr Bisbe Cardona Del",
    "iso:country":"ES",
    "sg:address":"Carr Bisbe Cardona, Del, 1",
    "sg:city":"Eivissa",
    "sg:orig_category":"Ropa Para Se\u00d1oras (al Por Menor)",
    "sg:phone":"+34 971 19 29 48",
    "sg:postcode":"07800",
    "sg:province":"Islas Baleares",
    "wof:name":"Coromina Rofes Gloria",
    "wof:placetype":"venue"
},
  "geometry": {"coordinates":[1.4294749498,38.9106941223],"type":"Point"}
}