{
  "type": "Feature",
  "properties": {
    "iso:country":"ES",
    "sg:address":"Carrer de Saragossa, 19",
    "sg:city":"Rubi",
    "sg:orig_category":"Edici\u00d3n De Diarios, Revistas, Boletines",
    "sg:phone":"+34 935 87 25 82",
    "sg:postcode":"08191",
    "sg:province":"Barcelona",
    "wof:name":"Cohent Skalli Lionel",
    "wof:placetype":"venue"
},
  "geometry": {"coordinates":[2.043129921,41.5001945496],"type":"Point"}
}