{
  "type": "Feature",
  "properties": {
    "addr:full":"Nta Sra Mercedes, 71 Moral Calatrava Ciudad Real 13350",
    "addr:housenumber":"71",
    "addr:postcode":"13350",
    "addr:street":"Sra;Moral Calatrava",
    "iso:country":"ES",
    "sg:address":"Nta Sra Mercedes, 71",
    "sg:city":"Moral Calatrava",
    "sg:orig_category":"M\u00c1rmoles, Granitos Y Piedras Naturales",
    "sg:phone":"+34 926 33 09 39",
    "sg:postcode":"13350",
    "sg:province":"Ciudad Real",
    "wof:name":"Marmoles Y Granitos C.b.",
    "wof:placetype":"venue"
},
  "geometry": {"coordinates":[-3.5793139935,38.8292617798],"type":"Point"}
}