{
  "type": "Feature",
  "properties": {
    "addr:full":"Calle de Coronel Moscoso, 3 S. Roque C\u00e1diz 11360",
    "addr:housenumber":"3",
    "addr:postcode":"11360",
    "addr:street":"Calle De Coronel Moscoso;S. Roque Ca\u0301Diz",
    "iso:country":"ES",
    "sg:address":"Calle de Coronel Moscoso, 3",
    "sg:city":"S. Roque",
    "sg:orig_category":"Albergues",
    "sg:phone":"+34 956 78 02 66",
    "sg:postcode":"11360",
    "sg:province":"C\u00e1diz",
    "wof:name":"Lett  Michael Stanley",
    "wof:placetype":"venue"
},
  "geometry": {"coordinates":[-5.3838295937,36.2117538452],"type":"Point"}
}