{
  "type": "Feature",
  "properties": {
    "iso:country":"ES",
    "sg:address":"Calle de Enrique Velasco, 10",
    "sg:city":"Madrid",
    "sg:orig_category":"Imprenta",
    "sg:phone":"+34 914 37 13 81",
    "sg:postcode":"28038",
    "sg:province":"Madrid",
    "wof:name":"Imprenta Laguna S.a.l.",
    "wof:placetype":"venue"
},
  "geometry": {"coordinates":[-3.6626243591,40.3961753845],"type":"Point"}
}