{
  "type": "Feature",
  "properties": {
    "addr:full":"Ctra. Des Port, Km. 0054,0 Pollen\u00e7a Islas Baleares 07460",
    "addr:postcode":"07460",
    "addr:street":"Ctra. Des Port Km. 0054,0",
    "iso:country":"ES",
    "sg:address":"Ctra. Des Port, Km. 0054,0",
    "sg:city":"Pollen\u00e7a",
    "sg:orig_category":"Cooperativas Agr\u00cdcolas",
    "sg:phone":"+34 971 53 41 46",
    "sg:postcode":"07460",
    "sg:province":"Islas Baleares",
    "wof:name":"Cooperativa Pagesa De Pollensa",
    "wof:placetype":"venue"
},
  "geometry": {"coordinates":[3.0190351009,39.8781204224],"type":"Point"}
}