{
  "type": "Feature",
  "properties": {
    "addr:full":"Calle de Lorenzo De La Carrera, 2 Baiona Pontevedra 36300",
    "addr:housenumber":"2",
    "addr:postcode":"36300",
    "addr:street":"Calle De Lorenzo De La Carrera",
    "iso:country":"ES",
    "sg:address":"Calle de Lorenzo De La Carrera, 2",
    "sg:city":"Baiona",
    "sg:orig_category":"Alimentaci\u00d3n General (al Por Menor)",
    "sg:phone":"+34 986 35 52 30",
    "sg:postcode":"36300",
    "sg:province":"Pontevedra",
    "wof:name":"Grande Lopez Fernando",
    "wof:placetype":"venue"
},
  "geometry": {"coordinates":[-97.78224945069999,45.7040786743],"type":"Point"}
}