{
  "type": "Feature",
  "properties": {
    "iso:country":"ES",
    "sg:address":"O Igrexario, 46",
    "sg:city":"Hio",
    "sg:orig_category":"Material Y Suministros Para Peluquer\u00cda",
    "sg:phone":"+34 986 32 80 09",
    "sg:postcode":"36948",
    "sg:province":"Pontevedra",
    "wof:name":"Salon De Belleza Alines S.l.",
    "wof:placetype":"venue"
},
  "geometry": {"coordinates":[-8.6428003311,42.4304618835],"type":"Point"}
}