{
  "type": "Feature",
  "properties": {
    "addr:full":"Plaz Magdalena, 10 Toledo Toledo 45001",
    "addr:housenumber":"10",
    "addr:postcode":"45001",
    "addr:street":"Magdalena",
    "iso:country":"ES",
    "sg:address":"Plaz Magdalena, 10",
    "sg:city":"Toledo",
    "sg:classifiers":[
        {
            "category":"Tea Room",
            "subcategory":"None",
            "type":"Food & Drink"
        }
    ],
    "sg:phone":"+34 925 22 33 84",
    "sg:postcode":"45001",
    "sg:province":"Toledo",
    "sg:tags":[
        "snack"
    ],
    "wof:name":"Cytasa Comunicaciones S.l.",
    "wof:placetype":"venue"
},
  "geometry": {"coordinates":[-4.0215759277,39.8588027954],"type":"Point"}
}