{
  "type": "Feature",
  "properties": {
    "iso:country":"ES",
    "sg:address":"Carretera De Ronda-campillos, Km. 0001,3",
    "sg:city":"Ronda",
    "sg:orig_category":"Restaurantes",
    "sg:phone":"+34 952 87 06 87",
    "sg:postcode":"29400",
    "sg:province":"M\u00e1laga",
    "wof:name":"Pizzeria La Cascada S.l.",
    "wof:placetype":"venue"
},
  "geometry": {"coordinates":[-5.1662788391,36.7417945862],"type":"Point"}
}