{
  "type": "Feature",
  "properties": {
    "addr:full":"Avda Mari\u00d1a (da), 43 Foz Lugo 27780",
    "addr:housenumber":"43",
    "addr:postcode":"27780",
    "addr:street":"Avda Marin\u0303A Da",
    "iso:country":"ES",
    "sg:address":"Avda Mari\u00d1a (da), 43",
    "sg:city":"Foz",
    "sg:orig_category":"Electrodom\u00c9sticos (al Por Menor)",
    "sg:phone":"+34 982 14 03 62",
    "sg:postcode":"27780",
    "sg:province":"Lugo",
    "wof:name":"Hijas De Celso Vazquez S.l.",
    "wof:placetype":"venue"
},
  "geometry": {"coordinates":[-7.2584090233,43.5688743591],"type":"Point"}
}