{
  "type": "Feature",
  "properties": {
    "addr:full":"Calle de Mayor, 22 Llanes Asturias 33500",
    "addr:housenumber":"22",
    "addr:postcode":"33500",
    "addr:street":"Calle De Mayor",
    "iso:country":"ES",
    "sg:address":"Calle de Mayor, 22",
    "sg:city":"Llanes",
    "sg:orig_category":"Complementos De Vestir (al Por Menor)",
    "sg:phone":"+34 985 40 28 59",
    "sg:postcode":"33500",
    "sg:province":"Asturias",
    "wof:name":"Iglesias Garcia Maria Angeles",
    "wof:placetype":"venue"
},
  "geometry": {"coordinates":[-4.7531571388,43.4207305908],"type":"Point"}
}