{
  "type": "Feature",
  "properties": {
    "iso:country":"ES",
    "sg:address":"Jundiz Kalea, 6",
    "sg:city":"Jundiz",
    "sg:orig_category":"Madera Para Construcci\u00d3n E Industria",
    "sg:phone":"+34 945 29 20 44",
    "sg:postcode":"01015",
    "sg:province":"\u00c1lava",
    "wof:name":"Kraslan-laminados De Madera S.a.",
    "wof:placetype":"venue"
},
  "geometry": {"coordinates":[-6.1999697685,43.3617782593],"type":"Point"}
}