{
  "type": "Feature",
  "properties": {
    "addr:full":"Ctra Cardon Del, 83 Palmas De Gran Canaria Las Palmas 35010",
    "addr:postcode":"35010",
    "addr:street":"Ctra Cardon Del 83",
    "iso:country":"ES",
    "sg:address":"Ctra Cardon Del, 83",
    "sg:city":"Palmas De Gran Canaria",
    "sg:orig_category":"Instalaci\u00d3n, Reparaci\u00d3n De Ascensores Y Montacargas",
    "sg:phone":"+34 928 27 42 20",
    "sg:postcode":"35010",
    "sg:province":"Las Palmas",
    "wof:name":"Ascensores Eguren S.a.",
    "wof:placetype":"venue"
},
  "geometry": {"coordinates":[-15.4531106949,28.1177501678],"type":"Point"}
}