{
  "type": "Feature",
  "properties": {
    "iso:country":"ES",
    "sg:address":"Calle de Principe De Vergara, 197",
    "sg:city":"Madrid",
    "sg:orig_category":"Cervecer\u00cdas",
    "sg:phone":"+34 915 62 42 43",
    "sg:postcode":"28002",
    "sg:province":"Madrid",
    "wof:name":"Telemensaje S.a.",
    "wof:placetype":"venue"
},
  "geometry": {"coordinates":[-3.6780729294,40.4483833313],"type":"Point"}
}