{
  "type": "Feature",
  "properties": {
    "addr:full":"Carr Ses Falques, 13 Blanes Girona 17300",
    "addr:housenumber":"13",
    "addr:postcode":"17300",
    "addr:street":"Carr Ses Falques",
    "iso:country":"ES",
    "sg:address":"Carr Ses Falques, 13",
    "sg:city":"Blanes",
    "sg:orig_category":"Fabricaci\u00d3n De Taburetes, Sillas Y Sillones",
    "sg:phone":"+34 972 33 11 57",
    "sg:postcode":"17300",
    "sg:province":"Girona",
    "wof:name":"Navarro Quiles Andreu",
    "wof:placetype":"venue"
},
  "geometry": {"coordinates":[2.7906849384,41.6724243164],"type":"Point"}
}