{
  "type": "Feature",
  "properties": {
    "iso:country":"ES",
    "sg:address":"C/ Poeta Miguel Hernandez, 107",
    "sg:city":"Elche",
    "sg:orig_category":"Servicios De Telecomunicaciones",
    "sg:phone":"+34 966 66 52 13",
    "sg:postcode":"03201",
    "sg:province":"Alicante",
    "wof:name":"Diop  Barra",
    "wof:placetype":"venue"
},
  "geometry": {"coordinates":[-0.7108399868,38.2645225525],"type":"Point"}
}