{
  "type": "Feature",
  "properties": {
    "addr:full":"Roibeira, 4 Roibeira La Coru\u00f1a 15319",
    "addr:housenumber":"4",
    "addr:postcode":"15319",
    "addr:street":"Roibeira;La Corun\u0303A",
    "iso:country":"ES",
    "sg:address":"Roibeira, 4",
    "sg:city":"Roibeira",
    "sg:orig_category":"Molduras, Junquillos, Listones Y Molduras Perforadas",
    "sg:phone":"+34 981 77 16 57",
    "sg:postcode":"15319",
    "sg:province":"La Coru\u00f1a",
    "wof:name":"Amado Pandelo Mercedes",
    "wof:placetype":"venue"
},
  "geometry": {"coordinates":[-8.2104768753,43.2697143555],"type":"Point"}
}