{
  "type": "Feature",
  "properties": {
    "addr:full":"Calle de Azucena, 16 Ciudad Real Ciudad Real 13002",
    "addr:housenumber":"16",
    "addr:postcode":"13002",
    "addr:street":"Calle De Azucena",
    "iso:country":"ES",
    "sg:address":"Calle de Azucena, 16",
    "sg:city":"Ciudad Real",
    "sg:orig_category":"Muebles Y Accesorios Para Cocinas Y Cuartos De Ba\u00d1o (al Por Menor)",
    "sg:phone":"+34 926 22 43 94",
    "sg:postcode":"13002",
    "sg:province":"Ciudad Real",
    "wof:name":"Nuevo Ba\u00f1o S.l.",
    "wof:placetype":"venue"
},
  "geometry": {"coordinates":[-3.9311089516,38.9870758057],"type":"Point"}
}