{
  "type": "Feature",
  "properties": {
    "addr:full":"Plaz Ferrocarril, 12 Matas-pinar-monte Rozas Madrid 28290",
    "addr:housenumber":"12",
    "addr:postcode":"28290",
    "addr:street":"Plaz Ferrocarril",
    "iso:country":"ES",
    "sg:address":"Plaz Ferrocarril, 12",
    "sg:city":"Matas-pinar-monte Rozas",
    "sg:orig_category":"Carnicer\u00cdas, Carnicer\u00cdas",
    "sg:phone":"+34 916 30 06 50",
    "sg:postcode":"28290",
    "sg:province":"Madrid",
    "wof:name":"Ramirez Coleto Pedro",
    "wof:placetype":"venue"
},
  "geometry": {"coordinates":[-3.8965299129,40.5532569885],"type":"Point"}
}