{
  "type": "Feature",
  "properties": {
    "iso:country":"ES",
    "sg:address":"Carr Prat De La Riba, S/n",
    "sg:city":"Termens",
    "sg:orig_category":"Cooperativas Agr\u00cdcolas",
    "sg:phone":"+34 973 18 00 84",
    "sg:postcode":"25670",
    "sg:province":"Lleida",
    "wof:name":"Cooperativa Del Camp De Termens Sdad. Coop. C. Ltda",
    "wof:placetype":"venue"
},
  "geometry": {"coordinates":[0.7646049857,41.7199249268],"type":"Point"}
}