{
  "type": "Feature",
  "properties": {
    "iso:country":"ES",
    "sg:address":"Rbla Catalunya, 66",
    "sg:city":"Barcelona",
    "sg:orig_category":"Fisioterapia",
    "sg:phone":"+34 932 15 23 93",
    "sg:postcode":"08007",
    "sg:province":"Barcelona",
    "wof:name":"Estudio Tres Pilates Reformer S.c.p.",
    "wof:placetype":"venue"
},
  "geometry": {"coordinates":[2.1630630493,41.3916778564],"type":"Point"}
}