{
  "type": "Feature",
  "properties": {
    "iso:country":"ES",
    "sg:address":"Calle de Diecinueve De Octubre, 17",
    "sg:city":"San Pedro Alcantara",
    "sg:orig_category":"Albergues",
    "sg:phone":"+34 952 78 30 41",
    "sg:postcode":"29670",
    "sg:province":"M\u00e1laga",
    "wof:name":"Hostal Acemar",
    "wof:placetype":"venue"
},
  "geometry": {"coordinates":[-4.9888691902,36.4859161377],"type":"Point"}
}