{
  "type": "Feature",
  "properties": {
    "iso:country":"ES",
    "sg:address":"Psaj Miramar Del Palo, 11",
    "sg:city":"Malaga",
    "sg:orig_category":"Ingeniero",
    "sg:phone":"+34 952 29 23 24",
    "sg:postcode":"29017",
    "sg:province":"M\u00e1laga",
    "wof:name":"Serrano Fernandez Antonio",
    "wof:placetype":"venue"
},
  "geometry": {"coordinates":[-4.3634672165,36.7204437256],"type":"Point"}
}