{
  "type": "Feature",
  "properties": {
    "iso:country":"ES",
    "sg:address":"Avda Luis Espada, 17",
    "sg:city":"Verin",
    "sg:orig_category":"Consultas M\u00c9dicas",
    "sg:phone":"+34 988 41 01 02",
    "sg:postcode":"32600",
    "sg:province":"Ourense",
    "wof:name":"Gamote Alvarez Antonia",
    "wof:placetype":"venue"
},
  "geometry": {"coordinates":[-7.4357500076,41.9401855469],"type":"Point"}
}