{
  "type": "Feature",
  "properties": {
    "addr:full":"Calle de Rozabella, 6 Matas-pinar-monte Rozas Madrid 28290",
    "addr:housenumber":"6",
    "addr:postcode":"28290",
    "addr:street":"Calle De Rozabella",
    "iso:country":"ES",
    "sg:address":"Calle de Rozabella, 6",
    "sg:city":"Matas-pinar-monte Rozas",
    "sg:orig_category":"Aparatos De Medida, Control, Regulaci\u00d3n Y Detecci\u00d3n",
    "sg:phone":"+34 916 40 06 40",
    "sg:postcode":"28290",
    "sg:province":"Madrid",
    "sg:website":"www.ifrinternational.com",
    "wof:name":"Aeroflex Technologies",
    "wof:placetype":"venue"
},
  "geometry": {"coordinates":[-3.8940443993,40.5407791138],"type":"Point"}
}