{
  "type": "Feature",
  "properties": {
    "iso:country":"ES",
    "sg:address":"Pl. Mercado, 1",
    "sg:city":"La Pola",
    "sg:orig_category":"Alquiler De V\u00cddeo",
    "sg:phone":"+34 985 49 00 44",
    "sg:postcode":"33630",
    "sg:province":"Asturias",
    "wof:name":"Terrones Vega Susana",
    "wof:placetype":"venue"
},
  "geometry": {"coordinates":[-5.829144001,43.1592941284],"type":"Point"}
}