{
  "type": "Feature",
  "properties": {
    "addr:full":"Calle de Castillo, 63 Hornachuelos C\u00f3rdoba 14740",
    "addr:housenumber":"63",
    "addr:postcode":"14740",
    "addr:street":"Calle De Castillo",
    "iso:country":"ES",
    "sg:address":"Calle de Castillo, 63",
    "sg:city":"Hornachuelos",
    "sg:orig_category":"Cl\u00cdnicas M\u00c9dicas",
    "sg:phone":"+34 957 64 01 01",
    "sg:postcode":"14740",
    "sg:province":"C\u00f3rdoba",
    "wof:name":"Moral Cuesta Maria Josefa",
    "wof:placetype":"venue"
},
  "geometry": {"coordinates":[-5.2450408936,37.8331336975],"type":"Point"}
}