{
  "type": "Feature",
  "properties": {
    "iso:country":"ES",
    "sg:address":"Calle de Martinez Oviol, 35",
    "sg:city":"Madrid",
    "sg:orig_category":"Farmacias",
    "sg:phone":"+34 917 97 98 67",
    "sg:postcode":"28021",
    "sg:province":"Madrid",
    "wof:name":"Ruiz Jalon Maria Angeles",
    "wof:placetype":"venue"
},
  "geometry": {"coordinates":[-3.688149929,40.3502197266],"type":"Point"}
}