{
  "type": "Feature",
  "properties": {
    "iso:country":"ES",
    "sg:address":"Ctra Granada (de), 32",
    "sg:city":"San Jose",
    "sg:orig_category":"M\u00c9dicos: Estomatolog\u00cda",
    "sg:phone":"+34 968 44 20 31",
    "sg:postcode":"30800",
    "sg:province":"Murcia",
    "wof:name":"Martinez Casaseca Luis Gabriel",
    "wof:placetype":"venue"
},
  "geometry": {"coordinates":[-1.6905640364,37.680557251],"type":"Point"}
}