{
  "type": "Feature",
  "properties": {
    "addr:full":"Calle de Villalobos, 12 Cadiz C\u00e1diz 11005",
    "addr:housenumber":"12",
    "addr:postcode":"11005",
    "addr:street":"Calle De Villalobos",
    "iso:country":"ES",
    "sg:address":"Calle de Villalobos, 12",
    "sg:city":"Cadiz",
    "sg:orig_category":"Bisuter\u00cda, Joyer\u00cda, Relojer\u00cda (al Por Menor)",
    "sg:phone":"+34 956 28 58 53",
    "sg:postcode":"11005",
    "sg:province":"C\u00e1diz",
    "wof:name":"Rendon Garcia Juan",
    "wof:placetype":"venue"
},
  "geometry": {"coordinates":[-6.2942881584,36.5304908752],"type":"Point"}
}