{
  "type": "Feature",
  "properties": {
    "addr:full":"Rua Pontevedra, 6 Santa Comba A Coru\u00f1a 15840",
    "addr:housenumber":"6",
    "addr:postcode":"15840",
    "addr:street":"Rua Pontevedra;Corun\u0303A",
    "iso:country":"ES",
    "sg:address":"Rua Pontevedra, 6",
    "sg:city":"Santa Comba",
    "sg:orig_category":"Agencias De Viajes",
    "sg:phone":"+34 981 88 05 25",
    "sg:postcode":"15840",
    "sg:province":"A Coru\u00f1a",
    "wof:name":"Viajes Raso S. L.",
    "wof:placetype":"venue"
},
  "geometry": {"coordinates":[-8.8163843155,43.0361595154],"type":"Point"}
}