{
  "type": "Feature",
  "properties": {
    "iso:country":"ES",
    "sg:address":"Calle de Teodoro Camino, 29",
    "sg:city":"Albacete",
    "sg:orig_category":"Art\u00cdculos De Decoraci\u00d3n (fabricaci\u00d3n Y Al Por Mayor)",
    "sg:phone":"+34 967 59 00 32",
    "sg:postcode":"02002",
    "sg:province":"Albacete",
    "wof:name":"Sucesores Tomas Navarro Gomez S.l.",
    "wof:placetype":"venue"
},
  "geometry": {"coordinates":[-1.855240941,38.9911651611],"type":"Point"}
}