{
  "type": "Feature",
  "properties": {
    "iso:country":"ES",
    "sg:address":"Ctra Valverde, Km. 0009,5",
    "sg:city":"Badajoz",
    "sg:orig_category":"Reciclaje Y Tratamiento De Desechos Varios",
    "sg:phone":"+34 924 14 05 80",
    "sg:postcode":"06010",
    "sg:province":"Badajoz",
    "wof:name":"Fomento De Construcciones Y Contratas S A",
    "wof:placetype":"venue"
},
  "geometry": {"coordinates":[-6.9718742371,38.862613678],"type":"Point"}
}