{
  "type": "Feature",
  "properties": {
    "iso:country":"ES",
    "sg:address":"Calle de Fuentes (las), 2",
    "sg:city":"Le\u00f3n",
    "sg:orig_category":"Colocaci\u00d3n, Mantenimiento, Vitrificaci\u00d3n De Parquets",
    "sg:phone":"+34 987 21 15 82",
    "sg:postcode":"24005",
    "sg:province":"Le\u00f3n",
    "wof:name":"Miguelez Trigueros Maria Teresa",
    "wof:placetype":"venue"
},
  "geometry": {"coordinates":[-5.5686049461,42.592830658],"type":"Point"}
}