{
  "type": "Feature",
  "properties": {
    "addr:full":"Pol Ind Los Bermejales, 1 Niebla Huelva 21840",
    "addr:housenumber":"1",
    "addr:postcode":"21840",
    "addr:street":"Los Bermejales",
    "iso:country":"ES",
    "sg:address":"Pol Ind Los Bermejales, 1",
    "sg:city":"Niebla",
    "sg:orig_category":"Mec\u00c1nico Del Autom\u00d3vil",
    "sg:phone":"+34 959 36 33 99",
    "sg:postcode":"21840",
    "sg:province":"Huelva",
    "wof:name":"Bonipla Automocion S.l.l.",
    "wof:placetype":"venue"
},
  "geometry": {"coordinates":[-6.6775889397,37.3641014099],"type":"Point"}
}