{
  "type": "Feature",
  "properties": {
    "iso:country":"ES",
    "sg:address":"Calle de Maestro Galindo Arjona, 28",
    "sg:city":"Riopar",
    "sg:orig_category":"Ambulancias",
    "sg:phone":"+34 967 43 53 09",
    "sg:postcode":"02450",
    "sg:province":"Albacete",
    "wof:name":"Ambulancias Riopar S.l",
    "wof:placetype":"venue"
},
  "geometry": {"coordinates":[-2.4158923626,38.4995803833],"type":"Point"}
}