{
  "type": "Feature",
  "properties": {
    "iso:country":"ES",
    "sg:address":"Bjad Berrocales (los), 12",
    "sg:city":"Avila",
    "sg:orig_category":"Asociaciones, Organismos Culturales Y Socioeducativos",
    "sg:phone":"+34 920 21 11 54",
    "sg:postcode":"05003",
    "sg:province":"\u00c1vila",
    "wof:name":"Juventud Obrera Cristiana De Espa\u00f1a",
    "wof:placetype":"venue"
},
  "geometry": {"coordinates":[-4.6956219673,40.6514015198],"type":"Point"}
}