{
  "type": "Feature",
  "properties": {
    "addr:full":"Rua Colon, 8 Ourense Ourense 32005",
    "addr:housenumber":"8",
    "addr:postcode":"32005",
    "addr:street":"Rua Colon",
    "iso:country":"ES",
    "sg:address":"Rua Colon, 8",
    "sg:city":"Ourense",
    "sg:orig_category":"Fabricaci\u00d3n, Venta De Cuadros, Accesorios Para Enmarcar",
    "sg:phone":"+34 988 22 91 02",
    "sg:postcode":"32005",
    "sg:province":"Ourense",
    "wof:name":"Marcos Y Molduras S.l.",
    "wof:placetype":"venue"
},
  "geometry": {"coordinates":[-7.8636288643,42.3343009949],"type":"Point"}
}