{
  "type": "Feature",
  "properties": {
    "addr:full":"Alam Urquijo, 25 Bilbao Vizcaya 48008",
    "addr:housenumber":"25",
    "addr:postcode":"48008",
    "addr:street":"Alam Urquijo",
    "iso:country":"ES",
    "sg:address":"Alam Urquijo, 25",
    "sg:city":"Bilbao",
    "sg:orig_category":"Fabricaci\u00d3n Y Comercio De M\u00c1quinas",
    "sg:phone":"+34 944 43 34 95",
    "sg:postcode":"48008",
    "sg:province":"Vizcaya",
    "sg:website":"www.cimesa.es",
    "wof:name":"Comercio Industrial Mecanico Cime, S.a.",
    "wof:placetype":"venue"
},
  "geometry": {"coordinates":[-2.9333651066,43.2595214844],"type":"Point"}
}