{
  "type": "Feature",
  "properties": {
    "iso:country":"ES",
    "sg:address":"Avda Bulevar De El Ejido, Km. 0077,4",
    "sg:city":"Ejido",
    "sg:orig_category":"Frutas Y Legumbres Frescas (al Por Mayor)",
    "sg:phone":"+34 950 48 36 14",
    "sg:postcode":"04700",
    "sg:province":"Almer\u00eda",
    "wof:name":"Mayba S.a.t.",
    "wof:placetype":"venue"
},
  "geometry": {"coordinates":[-2.8176040649,36.7727012634],"type":"Point"}
}