{
  "type": "Feature",
  "properties": {
    "addr:full":"Pou Nou, S/n Pou Nou Islas Baleares 07710",
    "addr:housenumber":"s / n",
    "addr:postcode":"07710",
    "iso:country":"ES",
    "sg:address":"Pou Nou, S/n",
    "sg:city":"Pou Nou",
    "sg:orig_category":"Tintorer\u00cdas, Limpieza En Seco",
    "sg:phone":"+34 971 15 11 01",
    "sg:postcode":"07710",
    "sg:province":"Islas Baleares",
    "wof:name":"Vidal Carreras Rafael",
    "wof:placetype":"venue"
},
  "geometry": {"coordinates":[4.2691421509,39.8487739563],"type":"Point"}
}