{
  "type": "Feature",
  "properties": {
    "iso:country":"ES",
    "sg:address":"Calle de Zarautz, 90",
    "sg:city":"Donostia-san Sebastian",
    "sg:orig_category":"Librer\u00cdas",
    "sg:phone":"+34 943 21 54 22",
    "sg:postcode":"20018",
    "sg:province":"Guip\u00f9zcoa",
    "wof:name":"Juan Carlos Cilveti Morrondo",
    "wof:placetype":"venue"
},
  "geometry": {"coordinates":[-2.0050780773,43.3052101135],"type":"Point"}
}