{
  "type": "Feature",
  "properties": {
    "iso:country":"ES",
    "sg:address":"Calle de Orfebres Santalinea, 5",
    "sg:city":"Castellon",
    "sg:orig_category":"M\u00c9dicos: Cirug\u00cda Pl\u00c1stica, Reconstructiva Y Est\u00c9tica",
    "sg:phone":"+34 964 24 11 55",
    "sg:postcode":"12005",
    "sg:province":"Castell\u00f3n",
    "wof:name":"Comice Valencia S.l.",
    "wof:placetype":"venue"
},
  "geometry": {"coordinates":[-0.0410940014,39.9804763794],"type":"Point"}
}