{
  "type": "Feature",
  "properties": {
    "iso:country":"ES",
    "sg:address":"Zubiaurre, 34",
    "sg:city":"Ermua",
    "sg:orig_category":"Molduras, Junquillos, Listones Y Molduras Perforadas",
    "sg:phone":"+34 943 03 01 06",
    "sg:postcode":"48260",
    "sg:province":"Vizcaya",
    "wof:name":"Susana Caro Galan (haizea Cafeteria)",
    "wof:placetype":"venue"
},
  "geometry": {"coordinates":[-2.5021290779,43.1898574829],"type":"Point"}
}