{
  "type": "Feature",
  "properties": {
    "iso:country":"ES",
    "sg:address":"La Carretera, S/n",
    "sg:city":"San Feliz Torio",
    "sg:orig_category":"Iglesia Cat\u00d3lica",
    "sg:phone":"+34 987 57 87 25",
    "sg:postcode":"24890",
    "sg:province":"Le\u00f3n",
    "wof:name":"Parroquia De San Feliz",
    "wof:placetype":"venue"
},
  "geometry": {"coordinates":[-5.5317540169,42.7085990906],"type":"Point"}
}