{
  "type": "Feature",
  "properties": {
    "addr:full":"Avda Oscar Espla, 18 Alacant Alicante 03003",
    "addr:housenumber":"18",
    "addr:postcode":"03003",
    "addr:street":"Avda Oscar Espla",
    "iso:country":"ES",
    "sg:address":"Avda Oscar Espla, 18",
    "sg:city":"Alacant",
    "sg:orig_category":"M\u00c9dicos: Pediatr\u00cda. Enfermedades De Los Ni\u00d1os",
    "sg:phone":"+34 965 22 90 87",
    "sg:postcode":"03003",
    "sg:province":"Alicante",
    "wof:name":"Millan Merino Juan",
    "wof:placetype":"venue"
},
  "geometry": {"coordinates":[-0.4935649931,38.3406982422],"type":"Point"}
}