{
  "type": "Feature",
  "properties": {
    "iso:country":"ES",
    "sg:address":"Av Perpinya, 49",
    "sg:city":"Figueres",
    "sg:orig_category":"Agencias Y Agentes Comerciales, Representantes",
    "sg:phone":"+34 972 50 56 26",
    "sg:postcode":"17600",
    "sg:province":"Girona",
    "wof:name":"Soler Galobardes Fidel",
    "wof:placetype":"venue"
},
  "geometry": {"coordinates":[2.9542989731,42.2753944397],"type":"Point"}
}