{
  "type": "Feature",
  "properties": {
    "iso:country":"ES",
    "sg:address":"Avda Monsacro, 2",
    "sg:city":"Morcin",
    "sg:orig_category":"Cajas De Ahorro",
    "sg:phone":"+34 985 78 31 49",
    "sg:postcode":"33612",
    "sg:province":"Asturias",
    "sg:website":"www.cajastur.es",
    "wof:name":"Caja De Ahorros De Asturias",
    "wof:placetype":"venue"
},
  "geometry": {"coordinates":[-5.7479071617,43.2100067139],"type":"Point"}
}