{
  "type": "Feature",
  "properties": {
    "iso:country":"ES",
    "sg:address":"Carrer de Ramon Pla, 2",
    "sg:city":"Cabrera Mar",
    "sg:orig_category":"Arquitectos",
    "sg:phone":"+34 937 59 01 93",
    "sg:postcode":"08349",
    "sg:province":"Barcelona",
    "wof:name":"Roldos Reniu Teodoro",
    "wof:placetype":"venue"
},
  "geometry": {"coordinates":[2.3933050632,41.5273513794],"type":"Point"}
}