{
  "type": "Feature",
  "properties": {
    "addr:full":"Rua Via Norte, 40 Vigo Pontevedra 36204",
    "addr:housenumber":"40",
    "addr:postcode":"36204",
    "addr:street":"Rua Via Norte",
    "iso:country":"ES",
    "sg:address":"Rua Via Norte, 40",
    "sg:city":"Vigo",
    "sg:orig_category":"Confecci\u00d3n De Trajes Para Se\u00d1oras",
    "sg:phone":"+34 986 48 01 37",
    "sg:postcode":"36204",
    "sg:province":"Pontevedra",
    "wof:name":"Cami\u00f1a Francisco Manuela",
    "wof:placetype":"venue"
},
  "geometry": {"coordinates":[-8.7097005844,42.2346420288],"type":"Point"}
}