{
  "type": "Feature",
  "properties": {
    "iso:country":"ES",
    "sg:address":"Ptda Curva, S/n",
    "sg:city":"Villena",
    "sg:orig_category":"Fabricaci\u00d3n De Quesos",
    "sg:phone":"+34 965 80 73 19",
    "sg:postcode":"03400",
    "sg:province":"Alicante",
    "wof:name":"Gonzalez Guerrero Valentina",
    "wof:placetype":"venue"
},
  "geometry": {"coordinates":[-0.868753016,38.6403503418],"type":"Point"}
}