{
  "type": "Feature",
  "properties": {
    "addr:full":"Calle de Malaga, 4 Ejido Almer\u00eda 04700",
    "addr:housenumber":"4",
    "addr:postcode":"04700",
    "addr:street":"Calle De Malaga;Almeri\u0301A",
    "iso:country":"ES",
    "sg:address":"Calle de Malaga, 4",
    "sg:city":"Ejido",
    "sg:orig_category":"Fisioterapia",
    "sg:phone":"+34 950 57 20 75",
    "sg:postcode":"04700",
    "sg:province":"Almer\u00eda",
    "wof:name":"Saba Romero Oswaldo Carlos",
    "wof:placetype":"venue"
},
  "geometry": {"coordinates":[-2.8195691109,36.7730102539],"type":"Point"}
}