{
  "type": "Feature",
  "properties": {
    "addr:full":"Calle de Alfonso Xi, 16 Algeciras C\u00e1diz 11201",
    "addr:housenumber":"16;ca\u0301diz",
    "addr:postcode":"11201",
    "addr:street":"Calle De Alfonso Xi",
    "iso:country":"ES",
    "sg:address":"Calle de Alfonso Xi, 16",
    "sg:city":"Algeciras",
    "sg:orig_category":"Asociaciones, Organismos Culturales Y Socioeducativos",
    "sg:phone":"+34 956 66 97 98",
    "sg:postcode":"11201",
    "sg:province":"C\u00e1diz",
    "wof:name":"Club Altes",
    "wof:placetype":"venue"
},
  "geometry": {"coordinates":[-5.4397826195,36.135761261],"type":"Point"}
}