{
  "type": "Feature",
  "properties": {
    "addr:full":"Carr Sant Miquel, 75 Vila-sana Lleida 25245",
    "addr:housenumber":"75",
    "addr:postcode":"25245",
    "addr:street":"Carr Sant Miquel",
    "iso:country":"ES",
    "sg:address":"Carr Sant Miquel, 75",
    "sg:city":"Vila-sana",
    "sg:orig_category":"Agricultores, Agricultores",
    "sg:phone":"+34 973 60 19 23",
    "sg:postcode":"25245",
    "sg:province":"Lleida",
    "wof:name":"Sangra Guzman Jose Maria",
    "wof:placetype":"venue"
},
  "geometry": {"coordinates":[0.9334700108,41.6641540527],"type":"Point"}
}