{
  "type": "Feature",
  "properties": {
    "addr:full":"Calle de Divino Valles, 3 Alcala Henares Madrid 28805",
    "addr:housenumber":"3",
    "addr:postcode":"28805",
    "addr:street":"Calle De Divino Valles",
    "iso:country":"ES",
    "sg:address":"Calle de Divino Valles, 3",
    "sg:city":"Alcala Henares",
    "sg:orig_category":"Fabricaci\u00d3n Y Refinado De Az\u00dacares",
    "sg:phone":"+34 918 77 03 03",
    "sg:postcode":"28805",
    "sg:province":"Madrid",
    "wof:name":"Soluciones Integrales Hipotecarias Gecredit S.l",
    "wof:placetype":"venue"
},
  "geometry": {"coordinates":[-3.3596363068,40.4858360291],"type":"Point"}
}