{
  "type": "Feature",
  "properties": {
    "addr:full":"Calle de General Vara De Rey, 48 Logro\u00f1o La Rioja 26002",
    "addr:housenumber":"48",
    "addr:postcode":"26002",
    "addr:street":"Calle De General Vara De Rey;Rioja",
    "iso:country":"ES",
    "sg:address":"Calle de General Vara De Rey, 48",
    "sg:city":"Logro\u00f1o",
    "sg:orig_category":"Pescader\u00cdas (al Por Menor)",
    "sg:phone":"+34 941 23 75 17",
    "sg:postcode":"26002",
    "sg:province":"La Rioja",
    "wof:name":"Gonzalez Mollinedo Antonio",
    "wof:placetype":"venue"
},
  "geometry": {"coordinates":[-2.4462273121,42.4597587585],"type":"Point"}
}