{
  "type": "Feature",
  "properties": {
    "addr:full":"Cra. Sta Creu Calafell-barcelona, S/n Calafell Tarragona 43820",
    "addr:postcode":"43820",
    "addr:street":"Calafell-Barcelona S / N",
    "iso:country":"ES",
    "sg:address":"Cra. Sta Creu Calafell-barcelona, S/n",
    "sg:city":"Calafell",
    "sg:orig_category":"Empresas De Hormig\u00d3n, Hormig\u00d3n Armado Y Pretensado",
    "sg:phone":"+34 977 69 31 48",
    "sg:postcode":"43820",
    "sg:province":"Tarragona",
    "wof:name":"Viguetas Sole S.a.",
    "wof:placetype":"venue"
},
  "geometry": {"coordinates":[1.5950700045,41.2305297852],"type":"Point"}
}