{
  "type": "Feature",
  "properties": {
    "addr:full":"Calle de Jeronimo Hernandez, 19 Sevilla Sevilla 41003",
    "addr:housenumber":"19",
    "addr:postcode":"41003",
    "addr:street":"Calle De Jeronimo Hernandez",
    "iso:country":"ES",
    "sg:address":"Calle de Jeronimo Hernandez, 19",
    "sg:city":"Sevilla",
    "sg:orig_category":"Inmobiliaria (agencias)",
    "sg:phone":"+34 954 21 81 77",
    "sg:postcode":"41003",
    "sg:province":"Sevilla",
    "wof:name":"Alquimetro S.l.",
    "wof:placetype":"venue"
},
  "geometry": {"coordinates":[-5.9909486771,37.3945465088],"type":"Point"}
}