{
  "type": "Feature",
  "properties": {
    "iso:country":"ES",
    "sg:address":"Calle de Azafran, 3",
    "sg:city":"Sevilla",
    "sg:orig_category":"Reposter\u00cdas",
    "sg:phone":"+34 954 21 32 19",
    "sg:postcode":"41003",
    "sg:province":"Sevilla",
    "wof:name":"Francisco Pe\u00f1a Marchena Y Otros Cdad",
    "wof:placetype":"venue"
},
  "geometry": {"coordinates":[-5.9876060486,37.3928489685],"type":"Point"}
}