{
  "type": "Feature",
  "properties": {
    "iso:country":"ES",
    "sg:address":"Carrer de Castanyer, 30",
    "sg:city":"Barcelona",
    "sg:orig_category":"Arquitectos",
    "sg:phone":"+34 932 12 03 42",
    "sg:postcode":"08022",
    "sg:province":"Barcelona",
    "wof:name":"Estudio Casta\u00f1er S.l.",
    "wof:placetype":"venue"
},
  "geometry": {"coordinates":[2.1394019127,41.407333374],"type":"Point"}
}