{
  "type": "Feature",
  "properties": {
    "iso:country":"ES",
    "sg:address":"Trva Calvo Sotelo, S/n",
    "sg:city":"Santiba\u00e7ez De Tera",
    "sg:orig_category":"Reposter\u00cdas",
    "sg:phone":"+34 980 65 30 23",
    "sg:postcode":"49625",
    "sg:province":"Zamora",
    "wof:name":"Carro Tabuyo Mateo",
    "wof:placetype":"venue"
},
  "geometry": {"coordinates":[-5.9234690666,41.9846801758],"type":"Point"}
}