{
  "type": "Feature",
  "properties": {
    "iso:country":"ES",
    "sg:address":"Avda Guipuzcoa, 27",
    "sg:city":"Berriozar",
    "sg:orig_category":"Molduras, Junquillos, Listones Y Molduras Perforadas",
    "sg:phone":"+34 948 21 50 29",
    "sg:postcode":"31013",
    "sg:province":"Navarra",
    "wof:name":"Montoya Ujve Ana Maria",
    "wof:placetype":"venue"
},
  "geometry": {"coordinates":[-97.78224945069999,45.7040786743],"type":"Point"}
}