{
  "type": "Feature",
  "properties": {
    "addr:full":"Calle de Doctor Eduardo Garcia-trivi\u00d1o Lopez, 2 Jaen Ja\u00e9n 23007",
    "addr:housenumber":"2;jae\u0301n",
    "addr:postcode":"23007",
    "addr:street":"Calle De Doctor Eduardo Garcia-Trivin\u0303O Lopez",
    "iso:country":"ES",
    "sg:address":"Calle de Doctor Eduardo Garcia-trivi\u00d1o Lopez, 2",
    "sg:city":"Jaen",
    "sg:orig_category":"Muebles, Minoristas",
    "sg:phone":"+34 953 26 79 34",
    "sg:postcode":"23007",
    "sg:province":"Ja\u00e9n",
    "sg:website":"www.azcue.com",
    "wof:name":"Muebles Bonsai S.l. Unipersonal",
    "wof:placetype":"venue"
},
  "geometry": {"coordinates":[-3.7889027596,37.7797241211],"type":"Point"}
}