{
  "type": "Feature",
  "properties": {
    "iso:country":"ES",
    "sg:address":"Calle de Azorin (de), 8",
    "sg:city":"Mostoles",
    "sg:orig_category":"Poller\u00cda Y Caza (al Por Menor)",
    "sg:phone":"+34 916 64 34 31",
    "sg:postcode":"28935",
    "sg:province":"Madrid",
    "wof:name":"Izquierdo Vizuete Jose",
    "wof:placetype":"venue"
},
  "geometry": {"coordinates":[-3.8779141903,40.3218078613],"type":"Point"}
}