{
  "type": "Feature",
  "properties": {
    "addr:full":"Calle de Ronda (la), 40 Castro Urdiales Cantabria 39700",
    "addr:housenumber":"40",
    "addr:postcode":"39700",
    "addr:street":"Calle De Ronda La",
    "iso:country":"ES",
    "sg:address":"Calle de Ronda (la), 40",
    "sg:city":"Castro Urdiales",
    "sg:orig_category":"Negocio De Materiales De Construcci\u00d3n",
    "sg:phone":"+34 942 86 26 11",
    "sg:postcode":"39700",
    "sg:province":"Cantabria",
    "sg:website":"www.encos-encofrados.com",
    "wof:name":"Encos Xxi S.l.",
    "wof:placetype":"venue"
},
  "geometry": {"coordinates":[-3.2192618847,43.3798866272],"type":"Point"}
}