{
  "type": "Feature",
  "properties": {
    "addr:full":"Avda Africa (de), 7 Ceuta Ceuta 51001",
    "addr:housenumber":"7",
    "addr:postcode":"51001",
    "addr:street":"Avda Africa De",
    "iso:country":"ES",
    "sg:address":"Avda Africa (de), 7",
    "sg:city":"Ceuta",
    "sg:orig_category":"Inform\u00c1tica (estudios, Servicios, Asesor\u00cda, Formaci\u00d3n)",
    "sg:phone":"+34 956 52 40 50",
    "sg:postcode":"51001",
    "sg:province":"Ceuta",
    "wof:name":"Computer Serviceuta S.l.",
    "wof:placetype":"venue"
},
  "geometry": {"coordinates":[-5.3218989372,35.8883934021],"type":"Point"}
}