{
  "type": "Feature",
  "properties": {
    "iso:country":"ES",
    "sg:address":"Avda Alcalde Manuel Platas Varela, 10",
    "sg:city":"Vilarrodis",
    "sg:classifiers":[
        {
            "category":"Taxi",
            "type":"Transportation"
        }
    ],
    "sg:phone":"+34 981 60 05 35",
    "sg:postcode":"15141",
    "sg:province":"La Coru\u00f1a",
    "wof:name":"Asociacion De Taxis De Arteixo",
    "wof:placetype":"venue"
},
  "geometry": {"coordinates":[-8.4752206802,43.323600769],"type":"Point"}
}