{
  "type": "Feature",
  "properties": {
    "addr:full":"Calle de Taula De Canvis, 8 Valencia Valencia 46001",
    "addr:housenumber":"8",
    "addr:postcode":"46001",
    "addr:street":"Calle De Taula;Canvis",
    "iso:country":"ES",
    "sg:address":"Calle de Taula De Canvis, 8",
    "sg:city":"Valencia",
    "sg:orig_category":"Art\u00cdculos De Regalo (al Por Menor)",
    "sg:phone":"+34 963 91 30 96",
    "sg:postcode":"46001",
    "sg:province":"Valencia",
    "wof:name":"Marvencien S.l.",
    "wof:placetype":"venue"
},
  "geometry": {"coordinates":[-0.3794099987,39.4749488831],"type":"Point"}
}