{
  "type": "Feature",
  "properties": {
    "addr:full":"Carr Ramon Llull, 7 Llubi Islas Baleares 07430",
    "addr:housenumber":"7",
    "addr:postcode":"07430",
    "addr:street":"Carr Ramon Llull;Islas",
    "iso:country":"ES",
    "sg:address":"Carr Ramon Llull, 7",
    "sg:city":"Llubi",
    "sg:orig_category":"Forjas Y Altos Hornos",
    "sg:phone":"+34 971 52 22 16",
    "sg:postcode":"07430",
    "sg:province":"Islas Baleares",
    "wof:name":"Oliver Aznar Benito",
    "wof:placetype":"venue"
},
  "geometry": {"coordinates":[3.005975008,39.6988716125],"type":"Point"}
}