{
  "type": "Feature",
  "properties": {
    "addr:full":"Calle de Sixto Celorrio, 19 Zaragoza Zaragoza 50015",
    "addr:housenumber":"19",
    "addr:postcode":"50015",
    "addr:street":"Calle De Sixto Celorrio",
    "iso:country":"ES",
    "sg:address":"Calle de Sixto Celorrio, 19",
    "sg:city":"Zaragoza",
    "sg:orig_category":"Poller\u00cda Y Caza (al Por Menor)",
    "sg:phone":"+34 976 52 21 47",
    "sg:postcode":"50015",
    "sg:province":"Zaragoza",
    "wof:name":"Cortes Carmona Maria Dolores",
    "wof:placetype":"venue"
},
  "geometry": {"coordinates":[-0.8761289716,41.6598510742],"type":"Point"}
}