{
  "type": "Feature",
  "properties": {
    "iso:country":"ES",
    "sg:address":"Dr. Roure, 15",
    "sg:city":"Tremp",
    "sg:orig_category":"Pescader\u00cdas (al Por Menor)",
    "sg:phone":"+34 973 65 02 58",
    "sg:postcode":"25620",
    "sg:province":"Lleida",
    "wof:name":"Belart Mora Rosa",
    "wof:placetype":"venue"
},
  "geometry": {"coordinates":[0.8949750066,42.1675834656],"type":"Point"}
}