{
  "type": "Feature",
  "properties": {
    "iso:country":"ES",
    "sg:address":"Carrer de Elda, 16",
    "sg:city":"Mutxamel",
    "sg:orig_category":"Librer\u00cdas",
    "sg:phone":"+34 965 95 13 73",
    "sg:postcode":"03110",
    "sg:province":"Alicante",
    "wof:name":"Cascales Rubio Maria Del Carmen",
    "wof:placetype":"venue"
},
  "geometry": {"coordinates":[-0.4495550096,38.4196510315],"type":"Point"}
}