{
  "type": "Feature",
  "properties": {
    "iso:country":"ES",
    "sg:address":"Calle de San Cristobal, 21",
    "sg:city":"Almansa",
    "sg:orig_category":"Peluqueros: De Se\u00d1oras",
    "sg:phone":"+34 967 34 01 81",
    "sg:postcode":"02640",
    "sg:province":"Albacete",
    "wof:name":"Martinez Alcocel Josefa",
    "wof:placetype":"venue"
},
  "geometry": {"coordinates":[-1.0971782207,38.8678817749],"type":"Point"}
}