{
  "type": "Feature",
  "properties": {
    "addr:full":"M. Rojals, S/n Mora Ebre Tarragona 43740",
    "addr:housenumber":"s / n",
    "addr:postcode":"43740",
    "addr:street":"Ebre",
    "iso:country":"ES",
    "sg:address":"M. Rojals, S/n",
    "sg:city":"Mora Ebre",
    "sg:orig_category":"Conservatorios",
    "sg:phone":"+34 977 40 16 00",
    "sg:postcode":"43740",
    "sg:province":"Tarragona",
    "wof:name":"Patronat De L'escola Municipal De Musica I Dansa De L'ajuntament De Mora D'ebre",
    "wof:placetype":"venue"
},
  "geometry": {"coordinates":[0.6392750144,41.0884246826],"type":"Point"}
}