{
  "type": "Feature",
  "properties": {
    "addr:full":"Av Unio, S/n Calonge Girona 17251",
    "addr:housenumber":"s / n",
    "addr:postcode":"17251",
    "addr:street":"Av Unio",
    "iso:country":"ES",
    "sg:address":"Av Unio, S/n",
    "sg:city":"Calonge",
    "sg:orig_category":"Asociaciones Y Clubs Deportivos",
    "sg:phone":"+34 972 65 07 03",
    "sg:postcode":"17251",
    "sg:province":"Girona",
    "wof:name":"Pibernat Trincado Joaquin",
    "wof:placetype":"venue"
},
  "geometry": {"coordinates":[3.0880630016,41.8507728577],"type":"Point"}
}