{
  "type": "Feature",
  "properties": {
    "iso:country":"ES",
    "sg:address":"Calle de Burriana, 49",
    "sg:city":"Valencia",
    "sg:orig_category":"Agencias Y Agentes Comerciales, Representantes",
    "sg:phone":"+34 963 33 14 05",
    "sg:postcode":"46005",
    "sg:province":"Valencia",
    "wof:name":"Sirera Almagro Juan Antonio",
    "wof:placetype":"venue"
},
  "geometry": {"coordinates":[-0.3636080027,39.4665870667],"type":"Point"}
}