{
  "type": "Feature",
  "properties": {
    "addr:full":"Calle de Cobo De Guzman, 17 Cordoba C\u00f3rdoba 14006",
    "addr:housenumber":"17",
    "addr:postcode":"14006",
    "addr:street":"Calle De Cobo De Guzman;Co\u0301Rdoba",
    "iso:country":"ES",
    "sg:address":"Calle de Cobo De Guzman, 17",
    "sg:city":"Cordoba",
    "sg:orig_category":"Bisuter\u00cda, Joyer\u00cda, Relojer\u00cda (al Por Menor)",
    "sg:phone":"+34 957 40 07 94",
    "sg:postcode":"14006",
    "sg:province":"C\u00f3rdoba",
    "wof:name":"Gonzalez Leon Baldomero",
    "wof:placetype":"venue"
},
  "geometry": {"coordinates":[-4.775390625,37.8975067139],"type":"Point"}
}