{
  "type": "Feature",
  "properties": {
    "iso:country":"ES",
    "sg:address":"Carr Rei San\u00c7, 2",
    "sg:city":"Felanitx",
    "sg:orig_category":"Lavander\u00cdas Para Particulares, Autoservicio De Lavander\u00cdas",
    "sg:phone":"+34 971 58 01 80",
    "sg:postcode":"07200",
    "sg:province":"Islas Baleares",
    "wof:name":"Adrover Nadal Pedro",
    "wof:placetype":"venue"
},
  "geometry": {"coordinates":[3.1475143433,39.4732246399],"type":"Point"}
}