{
  "type": "Feature",
  "properties": {
    "addr:full":"Calle de San Bernardo, 4 Benavente Zamora 49600",
    "addr:housenumber":"4",
    "addr:postcode":"49600",
    "addr:street":"Calle De San Bernardo",
    "iso:country":"ES",
    "sg:address":"Calle de San Bernardo, 4",
    "sg:city":"Benavente",
    "sg:orig_category":"Promotores Constructores",
    "sg:phone":"+34 980 63 07 13",
    "sg:postcode":"49600",
    "sg:province":"Zamora",
    "wof:name":"Garcia Ojanda Victor",
    "wof:placetype":"venue"
},
  "geometry": {"coordinates":[-5.6771578789,42.0001678467],"type":"Point"}
}