{
  "type": "Feature",
  "properties": {
    "addr:full":"Pl Vila (la), 8 Prat Llobregat Barcelona 08820",
    "addr:housenumber":"8",
    "addr:postcode":"08820",
    "addr:street":"Pl Vila La;Llobregat",
    "iso:country":"ES",
    "sg:address":"Pl Vila (la), 8",
    "sg:city":"Prat Llobregat",
    "sg:orig_category":"Centros M\u00c9dicos Y Sociales, Dispensarios",
    "sg:phone":"+34 933 70 88 53",
    "sg:postcode":"08820",
    "sg:province":"Barcelona",
    "wof:name":"Centro Medico Para El Automovilista S.l.",
    "wof:placetype":"venue"
},
  "geometry": {"coordinates":[2.0932219028,41.3302574158],"type":"Point"}
}