{
  "type": "Feature",
  "properties": {
    "addr:full":"Calle de Gabino Jimeno, 5 Madrid Madrid 28026",
    "addr:housenumber":"5",
    "addr:postcode":"28026",
    "addr:street":"Calle De Gabino Jimeno",
    "iso:country":"ES",
    "sg:address":"Calle de Gabino Jimeno, 5",
    "sg:city":"Madrid",
    "sg:orig_category":"Supermercados Y Hipermercados",
    "sg:phone":"+34 914 76 97 95",
    "sg:postcode":"28026",
    "sg:province":"Madrid",
    "wof:name":"Super Fresh S. A",
    "wof:placetype":"venue"
},
  "geometry": {"coordinates":[-3.7070717812,40.3863639832],"type":"Point"}
}