{
  "type": "Feature",
  "properties": {
    "addr:full":"Calle de Bravo Murillo, 373 Madrid Madrid 28020",
    "addr:housenumber":"373",
    "addr:postcode":"28020",
    "addr:street":"Calle De Bravo Murillo",
    "iso:country":"ES",
    "sg:address":"Calle de Bravo Murillo, 373",
    "sg:city":"Madrid",
    "sg:orig_category":"Peleter\u00cdas",
    "sg:phone":"+34 915 71 66 05",
    "sg:postcode":"28020",
    "sg:province":"Madrid",
    "wof:name":"Sanchez Corraliza Maria",
    "wof:placetype":"venue"
},
  "geometry": {"coordinates":[-3.6913673878,40.4655418396],"type":"Point"}
}