{
  "type": "Feature",
  "properties": {
    "iso:country":"ES",
    "sg:address":"Avda Murcia (de), 3",
    "sg:city":"San Sebastian De Los Reyes",
    "sg:classifiers":[
        {
            "category":"Autos & Motor Vehicles",
            "subcategory":"Automobile Sales",
            "type":"Retail Goods"
        }
    ],
    "sg:phone":"+34 916 52 04 96",
    "sg:postcode":"28700",
    "sg:province":"Madrid",
    "sg:website":"www.autoescuelaboston.com",
    "wof:name":"Autoescuela Boston S.l.",
    "wof:placetype":"venue"
},
  "geometry": {"coordinates":[-3.6293101311,40.552986145],"type":"Point"}
}