{
  "type": "Feature",
  "properties": {
    "addr:full":"Pque. Genil, S/n Granada Granada 18004",
    "addr:housenumber":"s / n",
    "addr:postcode":"18004",
    "addr:street":"Pque.",
    "iso:country":"ES",
    "sg:address":"Pque. Genil, S/n",
    "sg:city":"Granada",
    "sg:orig_category":"Sonorizaci\u00d3n, Iluminaci\u00d3n Para Cine, Teatro Y Discotecas (al Por Mayor, Al Por Menor)",
    "sg:phone":"+34 958 25 87 71",
    "sg:postcode":"18004",
    "sg:province":"Granada",
    "wof:name":"Fernandez Salvador Fernando",
    "wof:placetype":"venue"
},
  "geometry": {"coordinates":[-3.6054260731,37.1703987122],"type":"Point"}
}