{
  "type": "Feature",
  "properties": {
    "addr:full":"C/ Maestro Giner, 14 Elche Alicante 03201",
    "addr:housenumber":"14",
    "addr:postcode":"03201",
    "addr:street":"C / Maestro Giner",
    "iso:country":"ES",
    "sg:address":"C/ Maestro Giner, 14",
    "sg:city":"Elche",
    "sg:orig_category":"Quincaller\u00cda (al Por Menor)",
    "sg:phone":"+34 965 43 04 98",
    "sg:postcode":"03201",
    "sg:province":"Alicante",
    "wof:name":"Ferreteria Antonio Garcia S.l.",
    "wof:placetype":"venue"
},
  "geometry": {"coordinates":[-0.5391439795,38.2737541199],"type":"Point"}
}