{
  "type": "Feature",
  "properties": {
    "iso:country":"ES",
    "sg:address":"Rua Rosalia De Castro, 31",
    "sg:city":"Vigo",
    "sg:orig_category":"Vinos Y Licores (venta Al Por Menor)",
    "sg:phone":"+34 986 43 37 07",
    "sg:postcode":"36201",
    "sg:province":"Pontevedra",
    "wof:name":"Alonso Nogueira Manuel",
    "wof:placetype":"venue"
},
  "geometry": {"coordinates":[-8.716632843,42.2378921509],"type":"Point"}
}