{
  "type": "Feature",
  "properties": {
    "iso:country":"ES",
    "sg:address":"Zesareo Diaz Enparantza, 9",
    "sg:city":"Zestoa",
    "sg:orig_category":"Asociaciones, Organismos Culturales Y Socioeducativos",
    "sg:phone":"+34 943 14 73 81",
    "sg:postcode":"20740",
    "sg:province":"Guip\u00f9zcoa",
    "wof:name":"Sociedad Ertxim-pe",
    "wof:placetype":"venue"
},
  "geometry": {"coordinates":[-2.2592670918,43.2400741577],"type":"Point"}
}