{
  "type": "Feature",
  "properties": {
    "iso:country":"ES",
    "sg:address":"Calle de Nuestra Se\u00d1ora De Valme, 30",
    "sg:city":"Dos Hermanas",
    "sg:orig_category":"Agencias De Viajes",
    "sg:phone":"+34 955 67 78 32",
    "sg:postcode":"41700",
    "sg:province":"Sevilla",
    "sg:website":"www.viajeselcorteingles.es",
    "wof:name":"Viajes El Corte Ingles S.a.",
    "wof:placetype":"venue"
},
  "geometry": {"coordinates":[-5.9228420258,37.2850036621],"type":"Point"}
}