{
  "type": "Feature",
  "properties": {
    "addr:full":"Onteniente, 42 Montaverner Valencia 46892",
    "addr:housenumber":"42",
    "addr:postcode":"46892",
    "addr:street":"Onteniente",
    "iso:country":"ES",
    "sg:address":"Onteniente, 42",
    "sg:city":"Montaverner",
    "sg:orig_category":"Maquinaria Para Industrias Diversas",
    "sg:phone":"+34 962 29 75 04",
    "sg:postcode":"46892",
    "sg:province":"Valencia",
    "wof:name":"David Peiro Excavaciones S.l.",
    "wof:placetype":"venue"
},
  "geometry": {"coordinates":[-0.4932389855,38.8878860474],"type":"Point"}
}