{
  "type": "Feature",
  "properties": {
    "iso:country":"ES",
    "sg:address":"San Roque, 25",
    "sg:city":"Puente Tocinos",
    "sg:orig_category":"Herramientas Manuales (fabricaci\u00d3n, Al Por Mayor)",
    "sg:phone":"+34 968 30 05 40",
    "sg:postcode":"30006",
    "sg:province":"Murcia",
    "wof:name":"Afilados Hijos De Garcia Ortega S.l.",
    "wof:placetype":"venue"
},
  "geometry": {"coordinates":[-1.096031785,38.0072250366],"type":"Point"}
}