{
  "type": "Feature",
  "properties": {
    "iso:country":"ES",
    "sg:address":"Uranio (p I Calonge), 9",
    "sg:city":"Sevilla",
    "sg:orig_category":"Energ\u00cda Solar Y Nuevas Energ\u00cdas (equipo, Estudios)",
    "sg:phone":"+34 954 35 00 39",
    "sg:postcode":"41007",
    "sg:province":"Sevilla",
    "wof:name":"Aplicaciones Y Recursos Energeticos S.l",
    "wof:placetype":"venue"
},
  "geometry": {"coordinates":[-5.9541826248,37.401134491],"type":"Point"}
}