{
  "type": "Feature",
  "properties": {
    "addr:full":"Calle de Patio (el), 1 Valle S. Lorenzo Santa Cruz De Tenerife 38626",
    "addr:postcode":"38626",
    "addr:street":"Calle De;El;Valle S. Lorenzo",
    "iso:country":"ES",
    "sg:address":"Calle de Patio (el), 1",
    "sg:city":"Valle S. Lorenzo",
    "sg:orig_category":"Empresas De Carpinter\u00cda De Madera",
    "sg:phone":"+34 922 76 62 60",
    "sg:postcode":"38626",
    "sg:province":"Santa Cruz De Tenerife",
    "wof:name":"Hernandez Perez Miguel Angel",
    "wof:placetype":"venue"
},
  "geometry": {"coordinates":[-16.6702098846,28.0729980469],"type":"Point"}
}