{
  "type": "Feature",
  "properties": {
    "iso:country":"ES",
    "sg:address":"Avda Fonteculler, 6",
    "sg:city":"Fonteculler",
    "sg:orig_category":"Empresas De Carpinter\u00cda De Madera",
    "sg:phone":"+34 981 66 09 79",
    "sg:postcode":"15174",
    "sg:province":"La Coru\u00f1a",
    "sg:website":"www.carpinteriapaz.com",
    "wof:name":"Carpinteria Paz Ba\u00f1a S.l.",
    "wof:placetype":"venue"
},
  "geometry": {"coordinates":[-8.3826389313,43.3110656738],"type":"Point"}
}