{
  "type": "Feature",
  "properties": {
    "iso:country":"ES",
    "sg:address":"Calle de Santa Barbara, 2",
    "sg:city":"Donostia-san Sebastian",
    "sg:orig_category":"Plomeros",
    "sg:phone":"+34 943 35 33 26",
    "sg:postcode":"20017",
    "sg:province":"Guip\u00f9zcoa",
    "wof:name":"Perez Perez Timoteo",
    "wof:placetype":"venue"
},
  "geometry": {"coordinates":[-1.9302710295,43.3170471191],"type":"Point"}
}