{
  "type": "Feature",
  "properties": {
    "iso:country":"ES",
    "sg:address":"Calle de Juan Madrazo, 25",
    "sg:city":"Le\u00f3n",
    "sg:orig_category":"Transporte En General",
    "sg:phone":"+34 987 24 68 25",
    "sg:postcode":"24002",
    "sg:province":"Le\u00f3n",
    "wof:name":"Broker Y Broker 98 S.l.",
    "wof:placetype":"venue"
},
  "geometry": {"coordinates":[-5.577422142,42.6011695862],"type":"Point"}
}