{
  "type": "Feature",
  "properties": {
    "iso:country":"ES",
    "sg:address":"Carrer de Narcis Giralt, 13",
    "sg:city":"Sabadell",
    "sg:orig_category":"Abogados",
    "sg:phone":"+34 937 25 81 96",
    "sg:postcode":"08202",
    "sg:province":"Barcelona",
    "wof:name":"Gomez Caldero Irene",
    "wof:placetype":"venue"
},
  "geometry": {"coordinates":[2.1105918884,41.546169281],"type":"Point"}
}