{
  "type": "Feature",
  "properties": {
    "iso:country":"ES",
    "sg:address":"San Juan, 50",
    "sg:city":"San Juan De Mozarrifar",
    "sg:orig_category":"Electricidad: Instalaciones Industriales",
    "sg:phone":"+34 976 58 72 06",
    "sg:postcode":"50820",
    "sg:province":"Zaragoza",
    "wof:name":"Jose Manuel Sanchez Gracia S.l.",
    "wof:placetype":"venue"
},
  "geometry": {"coordinates":[-0.8380060196,41.7157287598],"type":"Point"}
}