{
  "type": "Feature",
  "properties": {
    "iso:country":"ES",
    "sg:address":"Calle de Ruiz Tagle, 10",
    "sg:city":"Torrelavega",
    "sg:orig_category":"Abogados",
    "sg:phone":"+34 942 80 02 18",
    "sg:postcode":"39300",
    "sg:province":"Cantabria",
    "wof:name":"Holanda Obregon Jose Luis",
    "wof:placetype":"venue"
},
  "geometry": {"coordinates":[-4.0494370461,43.3488502502],"type":"Point"}
}