{
  "type": "Feature",
  "properties": {
    "iso:country":"ES",
    "sg:address":"Calle de Don Pedro, 6",
    "sg:city":"Madrid",
    "sg:orig_category":"Agencias Y Asesores De Publicidad",
    "sg:phone":"+34 913 65 26 41",
    "sg:postcode":"28005",
    "sg:province":"Madrid",
    "wof:name":"Zigurat Comunicacion Grafica",
    "wof:placetype":"venue"
},
  "geometry": {"coordinates":[-3.7121737003,40.4115486145],"type":"Point"}
}