{
  "type": "Feature",
  "properties": {
    "iso:country":"ES",
    "sg:address":"Avda Juan Carlos I, 2",
    "sg:city":"Urbanizacion Media Sala",
    "sg:orig_category":"Venta, Montaje De Neum\u00c1ticos",
    "sg:phone":"+34 968 51 27 69",
    "sg:postcode":"30310",
    "sg:province":"Murcia",
    "wof:name":"Arnau Montero Antonio",
    "wof:placetype":"venue"
},
  "geometry": {"coordinates":[-1.1298867464,37.9834747314],"type":"Point"}
}