{
  "type": "Feature",
  "properties": {
    "addr:full":"Av Sarria, 12 Barcelona Barcelona 08029",
    "addr:housenumber":"12",
    "addr:postcode":"08029",
    "addr:street":"Av Sarria",
    "iso:country":"ES",
    "sg:address":"Av Sarria, 12",
    "sg:city":"Barcelona",
    "sg:orig_category":"Aparcamientos (infraestructuras, Accesorios)",
    "sg:phone":"+34 934 30 77 13",
    "sg:postcode":"08029",
    "sg:province":"Barcelona",
    "wof:name":"Antonio Aleix Mu\u00f1oz S.a.",
    "wof:placetype":"venue"
},
  "geometry": {"coordinates":[2.1458792686,41.3901824951],"type":"Point"}
}