{
  "type": "Feature",
  "properties": {
    "addr:full":"C/ Carlos Anton Pastor, 91 Elche Alicante 03206",
    "addr:housenumber":"91",
    "addr:postcode":"03206",
    "addr:street":"C / Carlos Anton Pastor",
    "iso:country":"ES",
    "sg:address":"C/ Carlos Anton Pastor, 91",
    "sg:city":"Elche",
    "sg:orig_category":"Promotores Constructores",
    "sg:phone":"+34 966 66 05 30",
    "sg:postcode":"03206",
    "sg:province":"Alicante",
    "wof:name":"Kasdan S.l.",
    "wof:placetype":"venue"
},
  "geometry": {"coordinates":[-0.7132560015,38.2749633789],"type":"Point"}
}