{
  "type": "Feature",
  "properties": {
    "iso:country":"ES",
    "sg:address":"Calle de Montepio, 10",
    "sg:city":"Miajadas",
    "sg:orig_category":"\u00d3ptica: Instrumentos (fabricaci\u00d3n)",
    "sg:phone":"+34 927 16 15 39",
    "sg:postcode":"10100",
    "sg:province":"C\u00e1ceres",
    "wof:name":"Ruiz Alvarez Ana Maria",
    "wof:placetype":"venue"
},
  "geometry": {"coordinates":[-5.9058699608,39.1511955261],"type":"Point"}
}