{
  "type": "Feature",
  "properties": {
    "addr:full":"Calle de Estacion, 2 Canillas Aceituno M\u00e1laga 29716",
    "addr:housenumber":"2",
    "addr:postcode":"29716",
    "addr:street":"Calle De Estacion;Ma\u0301Laga",
    "iso:country":"ES",
    "sg:address":"Calle de Estacion, 2",
    "sg:city":"Canillas Aceituno",
    "sg:orig_category":"Venta, Alquiler Y Mantenimiento De Juegos De Sal\u00d3n O Casinos",
    "sg:phone":"+34 952 51 82 93",
    "sg:postcode":"29716",
    "sg:province":"M\u00e1laga",
    "wof:name":"Hidalgo Jimenez Antonio Manuel",
    "wof:placetype":"venue"
},
  "geometry": {"coordinates":[-4.0841245651,36.8733406067],"type":"Point"}
}