{
  "type": "Feature",
  "properties": {
    "iso:country":"ES",
    "sg:address":"Avda Habana (la), S/n",
    "sg:city":"Cristianos",
    "sg:orig_category":"Peluquer\u00cdas, Peluquer\u00cda Mixta",
    "sg:phone":"+34 922 79 31 24",
    "sg:postcode":"38650",
    "sg:province":"Santa Cruz De Tenerife",
    "wof:name":"Rankin  Ruth",
    "wof:placetype":"venue"
},
  "geometry": {"coordinates":[-16.7210445404,28.0514259338],"type":"Point"}
}