{
  "type": "Feature",
  "properties": {
    "addr:full":"Calle de Costa Rica, 8 Madrid Madrid 28016",
    "addr:housenumber":"8",
    "addr:postcode":"madrid;28016",
    "addr:street":"Calle De Costa Rica",
    "iso:country":"ES",
    "sg:address":"Calle de Costa Rica, 8",
    "sg:city":"Madrid",
    "sg:orig_category":"Abogados",
    "sg:phone":"+34 914 57 37 85",
    "sg:postcode":"28016",
    "sg:province":"Madrid",
    "wof:name":"Aguirre Garcia Adolfo",
    "wof:placetype":"venue"
},
  "geometry": {"coordinates":[-3.6760520935,40.4585266113],"type":"Point"}
}