{
  "type": "Feature",
  "properties": {
    "addr:full":"Cami Mig (del), 32 Mataro Barcelona 08302",
    "addr:postcode":"08302",
    "addr:street":"Mig",
    "iso:country":"ES",
    "sg:address":"Cami Mig (del), 32",
    "sg:city":"Mataro",
    "sg:orig_category":"Peluquer\u00cdas, Peluquer\u00cda Mixta",
    "sg:phone":"+34 937 98 77 31",
    "sg:postcode":"08302",
    "sg:province":"Barcelona",
    "wof:name":"Ribas Ruiz Manuel",
    "wof:placetype":"venue"
},
  "geometry": {"coordinates":[2.4317901134,41.536693573],"type":"Point"}
}