{
  "type": "Feature",
  "properties": {
    "iso:country":"ES",
    "sg:address":"Plaz Julian Coca, 15",
    "sg:city":"Guijuelo",
    "sg:orig_category":"Bares, Piano",
    "sg:phone":"+34 923 58 17 14",
    "sg:postcode":"37770",
    "sg:province":"Salamanca",
    "wof:name":"Vega Blanco Manuel",
    "wof:placetype":"venue"
},
  "geometry": {"coordinates":[-5.6718320847,40.558052063],"type":"Point"}
}