{
  "type": "Feature",
  "properties": {
    "iso:country":"ES",
    "sg:address":"Calle de Arisgotas, 10",
    "sg:city":"Orgaz",
    "sg:orig_category":"Abogados",
    "sg:phone":"+34 925 31 72 45",
    "sg:postcode":"45450",
    "sg:province":"Toledo",
    "wof:name":"Diaz-suelto Villarrubia Alejandro Javier",
    "wof:placetype":"venue"
},
  "geometry": {"coordinates":[-3.8802495003,39.6476325989],"type":"Point"}
}