{
  "type": "Feature",
  "properties": {
    "iso:country":"ES",
    "sg:address":"Calle de Ancha, 10",
    "sg:city":"Huetor-tajar",
    "sg:orig_category":"Fabricaci\u00d3n De Productos Textiles Sin Tejer",
    "sg:phone":"+34 958 33 20 71",
    "sg:postcode":"18360",
    "sg:province":"Granada",
    "wof:name":"Garofano Gamiz Jose",
    "wof:placetype":"venue"
},
  "geometry": {"coordinates":[-4.0465316772,37.1952018738],"type":"Point"}
}