{
  "type": "Feature",
  "properties": {
    "addr:full":"Carrer de Abadia, 8 Asco Tarragona 43791",
    "addr:housenumber":"8",
    "addr:postcode":"43791",
    "addr:street":"Carrer De Abadia",
    "iso:country":"ES",
    "sg:address":"Carrer de Abadia, 8",
    "sg:city":"Asco",
    "sg:orig_category":"Iglesia Cat\u00d3lica",
    "sg:phone":"+34 977 40 50 39",
    "sg:postcode":"43791",
    "sg:province":"Tarragona",
    "wof:name":"Bisbat De Tortosa-parroquia Sant Joan Baptista",
    "wof:placetype":"venue"
},
  "geometry": {"coordinates":[0.5668060184,41.1806907654],"type":"Point"}
}