{
  "type": "Feature",
  "properties": {
    "iso:country":"ES",
    "sg:address":"Calle de San Agustin, 24",
    "sg:city":"Segovia",
    "sg:orig_category":"Molduras, Junquillos, Listones Y Molduras Perforadas",
    "sg:phone":"+34 921 46 32 42",
    "sg:postcode":"40001",
    "sg:province":"Segovia",
    "wof:name":"Manrique Lobo Antonio",
    "wof:placetype":"venue"
},
  "geometry": {"coordinates":[-4.1184148788,40.9499473572],"type":"Point"}
}