{
  "type": "Feature",
  "properties": {
    "iso:country":"ES",
    "sg:address":"Avda Aragon, 183",
    "sg:city":"Puebla Vicar",
    "sg:orig_category":"Asesor\u00cda Sobre Comunicaci\u00d3n De Empresas",
    "sg:phone":"+34 950 55 54 38",
    "sg:postcode":"04738",
    "sg:province":"Almer\u00eda",
    "wof:name":"Lopez Manzano Maria",
    "wof:placetype":"venue"
},
  "geometry": {"coordinates":[-2.6517090797,36.8000984192],"type":"Point"}
}