{
  "type": "Feature",
  "properties": {
    "addr:full":"Calle de Eras Bajas, 24 Huetor-tajar Granada 18360",
    "addr:housenumber":"24",
    "addr:postcode":"18360",
    "addr:street":"Calle De Eras Bajas",
    "iso:country":"ES",
    "sg:address":"Calle de Eras Bajas, 24",
    "sg:city":"Huetor-tajar",
    "sg:orig_category":"Librer\u00cdas",
    "sg:phone":"+34 958 33 20 59",
    "sg:postcode":"18360",
    "sg:province":"Granada",
    "wof:name":"Paco Casa Ras S.l.",
    "wof:placetype":"venue"
},
  "geometry": {"coordinates":[-4.0483179092,37.1954994202],"type":"Point"}
}