{
  "type": "Feature",
  "properties": {
    "addr:full":"Pol Ind Polysol, 37 Alcala Guadaira Sevilla 41500",
    "addr:housenumber":"37",
    "addr:postcode":"41500",
    "addr:street":"Polysol",
    "iso:country":"ES",
    "sg:address":"Pol Ind Polysol, 37",
    "sg:city":"Alcala Guadaira",
    "sg:orig_category":"Centros Empresariales",
    "sg:phone":"+34 954 10 17 30",
    "sg:postcode":"41500",
    "sg:province":"Sevilla",
    "wof:name":"Msp-traysimec S.l.",
    "wof:placetype":"venue"
},
  "geometry": {"coordinates":[-5.8398590088,37.3383140564],"type":"Point"}
}