{
  "type": "Feature",
  "properties": {
    "addr:full":"O. Redondo, 12 Fuente Alamo Murcia 30320",
    "addr:housenumber":"12",
    "addr:postcode":"30320",
    "iso:country":"ES",
    "sg:address":"O. Redondo, 12",
    "sg:city":"Fuente Alamo",
    "sg:orig_category":"Empresas De Carpinter\u00cda Met\u00c1lica",
    "sg:phone":"+34 968 59 70 41",
    "sg:postcode":"30320",
    "sg:province":"Murcia",
    "wof:name":"Simon Valero Martinez S.l.",
    "wof:placetype":"venue"
},
  "geometry": {"coordinates":[-1.1687190533,37.7235946655],"type":"Point"}
}