{
  "type": "Feature",
  "properties": {
    "addr:full":"Calle de Toros, 37 Tobarra Albacete 02500",
    "addr:housenumber":"37",
    "addr:postcode":"02500",
    "addr:street":"Calle De Toros",
    "iso:country":"ES",
    "sg:address":"Calle de Toros, 37",
    "sg:city":"Tobarra",
    "sg:orig_category":"Ferreter\u00cda Artesanal",
    "sg:phone":"+34 967 32 51 56",
    "sg:postcode":"02500",
    "sg:province":"Albacete",
    "wof:name":"Cotillas Lopez Bernardino",
    "wof:placetype":"venue"
},
  "geometry": {"coordinates":[-1.6879730225,38.5946235657],"type":"Point"}
}