{
  "type": "Feature",
  "properties": {
    "iso:country":"ES",
    "sg:address":"Rua Salamanca, 17",
    "sg:city":"Vigo",
    "sg:orig_category":"Inmobiliaria (agencias)",
    "sg:phone":"+34 986 42 10 03",
    "sg:postcode":"36211",
    "sg:province":"Pontevedra",
    "wof:name":"Alvarez Gonzalez Pedro Marcelo Moises",
    "wof:placetype":"venue"
},
  "geometry": {"coordinates":[-8.7269058228,42.2222480774],"type":"Point"}
}