{
  "type": "Feature",
  "properties": {
    "iso:country":"ES",
    "sg:address":"Heroes De Pontesampaio, S/n",
    "sg:city":"Ponte",
    "sg:orig_category":"Pescader\u00cdas (al Por Menor)",
    "sg:phone":"+34 986 70 00 93",
    "sg:postcode":"36690",
    "sg:province":"Pontevedra",
    "wof:name":"Productos Arcade Para Ganaderia S.a.",
    "wof:placetype":"venue"
},
  "geometry": {"coordinates":[-8.6073894501,42.3485717773],"type":"Point"}
}