{
  "type": "Feature",
  "properties": {
    "addr:full":"Carrer de Comte D'urgell, 50 Barcelona Barcelona 08011",
    "addr:housenumber":"50",
    "addr:postcode":"08011",
    "addr:street":"Carrer De Comte D'Urgell",
    "iso:country":"ES",
    "sg:address":"Carrer de Comte D'urgell, 50",
    "sg:city":"Barcelona",
    "sg:orig_category":"Molduras, Junquillos, Listones Y Molduras Perforadas",
    "sg:phone":"+34 934 53 60 45",
    "sg:postcode":"08011",
    "sg:province":"Barcelona",
    "wof:name":"Pascual Vicente Monserrat",
    "wof:placetype":"venue"
},
  "geometry": {"coordinates":[2.1597645283,41.3812561035],"type":"Point"}
}