{
  "type": "Feature",
  "properties": {
    "addr:full":"Avda Enrique Martin Cuevas, S/n Motril Granada 18600",
    "addr:housenumber":"s / n",
    "addr:postcode":"18600",
    "addr:street":"Avda Enrique Martin Cuevas",
    "iso:country":"ES",
    "sg:address":"Avda Enrique Martin Cuevas, S/n",
    "sg:city":"Motril",
    "sg:orig_category":"Librer\u00cdas",
    "sg:phone":"+34 958 60 14 57",
    "sg:postcode":"18600",
    "sg:province":"Granada",
    "wof:name":"Perez Jimenez Maria",
    "wof:placetype":"venue"
},
  "geometry": {"coordinates":[-3.5196490288,36.7499694824],"type":"Point"}
}