{
  "type": "Feature",
  "properties": {
    "addr:full":"Calle de Sogueros (de), 7 Colmenar Viejo Madrid 28770",
    "addr:postcode":"28770",
    "addr:street":"Calle De Sogueros De",
    "iso:country":"ES",
    "sg:address":"Calle de Sogueros (de), 7",
    "sg:city":"Colmenar Viejo",
    "sg:orig_category":"Comercio De Minerales, F\u00d3siles Y Conchas",
    "sg:phone":"+34 918 45 27 42",
    "sg:postcode":"28770",
    "sg:province":"Madrid",
    "wof:name":"Ruiz Villar Jose Helios",
    "wof:placetype":"venue"
},
  "geometry": {"coordinates":[-3.7687060833,40.6616363525],"type":"Point"}
}