{
  "type": "Feature",
  "properties": {
    "iso:country":"ES",
    "sg:address":"Calle de Perez Galdos, 1",
    "sg:city":"Oviedo",
    "sg:orig_category":"Maquinaria Para Industrias Diversas",
    "sg:phone":"+34 985 11 03 75",
    "sg:postcode":"33012",
    "sg:province":"Asturias",
    "wof:name":"Ascensores Modro\u00f1o S.c.",
    "wof:placetype":"venue"
},
  "geometry": {"coordinates":[-5.8492836952,43.3721466064],"type":"Point"}
}