{
  "type": "Feature",
  "properties": {
    "iso:country":"ES",
    "sg:address":"Calle de Gudari Kalea, 3",
    "sg:city":"Tolosa",
    "sg:orig_category":"Electricidad: Instalaciones Industriales",
    "sg:phone":"+34 943 65 25 14",
    "sg:postcode":"20400",
    "sg:province":"Guip\u00f9zcoa",
    "wof:name":"Goena S.l.",
    "wof:placetype":"venue"
},
  "geometry": {"coordinates":[-2.0750739574,43.1339645386],"type":"Point"}
}