{
  "type": "Feature",
  "properties": {
    "addr:full":"Rua Ponte (da), 41 Lalin Pontevedra 36500",
    "addr:housenumber":"41",
    "addr:postcode":"36500",
    "addr:street":"Rua Ponte Da",
    "iso:country":"ES",
    "sg:address":"Rua Ponte (da), 41",
    "sg:city":"Lalin",
    "sg:orig_category":"Electricidad Veh\u00cdculo",
    "sg:phone":"+34 986 78 05 47",
    "sg:postcode":"36500",
    "sg:province":"Pontevedra",
    "wof:name":"Taller Electrico Silva S.cv.",
    "wof:placetype":"venue"
},
  "geometry": {"coordinates":[-8.1130685806,42.6647605896],"type":"Point"}
}