{
  "type": "Feature",
  "properties": {
    "addr:full":"Calle de Triana, 31 Madrid Madrid 28016",
    "addr:housenumber":"31",
    "addr:postcode":"madrid;28016",
    "addr:street":"Calle De Triana",
    "iso:country":"ES",
    "sg:address":"Calle de Triana, 31",
    "sg:city":"Madrid",
    "sg:orig_category":"Inmobiliaria (agencias)",
    "sg:phone":"+34 913 57 31 40",
    "sg:postcode":"28016",
    "sg:province":"Madrid",
    "wof:name":"Garcia Galan Alfonso",
    "wof:placetype":"venue"
},
  "geometry": {"coordinates":[-3.6769781113,40.4627952576],"type":"Point"}
}