{
  "type": "Feature",
  "properties": {
    "iso:country":"ES",
    "sg:address":"Calle de Carmen Laffon, 7",
    "sg:city":"Cantillana",
    "sg:orig_category":"Promotores Constructores",
    "sg:phone":"+34 955 73 01 49",
    "sg:postcode":"41320",
    "sg:province":"Sevilla",
    "wof:name":"Ofideco De Cantillana S.l.",
    "wof:placetype":"venue"
},
  "geometry": {"coordinates":[-5.8254547119,37.6127662659],"type":"Point"}
}