{
  "type": "Feature",
  "properties": {
    "addr:full":"Carrer de Doctor Gomez Ferrer (del), 49 Gata Gorgos Alicante 03740",
    "addr:housenumber":"49",
    "addr:postcode":"03740",
    "addr:street":"Carrer De Doctor Gomez Ferrer Del",
    "iso:country":"ES",
    "sg:address":"Carrer de Doctor Gomez Ferrer (del), 49",
    "sg:city":"Gata Gorgos",
    "sg:orig_category":"Peluqueros: De Se\u00d1oras",
    "sg:phone":"+34 966 45 43 32",
    "sg:postcode":"03740",
    "sg:province":"Alicante",
    "wof:name":"Lozano Peluqueria Y Estetica S.l.",
    "wof:placetype":"venue"
},
  "geometry": {"coordinates":[0.0839589983,38.7751502991],"type":"Point"}
}