{
  "type": "Feature",
  "properties": {
    "addr:full":"Calle de Uruguay, S/n Alcantarilla Murcia 30820",
    "addr:housenumber":"s / n",
    "addr:postcode":"30820",
    "addr:street":"Calle De Uruguay",
    "iso:country":"ES",
    "sg:address":"Calle de Uruguay, S/n",
    "sg:city":"Alcantarilla",
    "sg:orig_category":"Tubos Met\u00c1licos",
    "sg:phone":"+34 968 89 35 50",
    "sg:postcode":"30820",
    "sg:province":"Murcia",
    "sg:website":"www.rytarques.com",
    "wof:name":"Riegos Y Tuberias Arques S.l.",
    "wof:placetype":"venue"
},
  "geometry": {"coordinates":[-1.1980240345,37.9597854614],"type":"Point"}
}