{
  "type": "Feature",
  "properties": {
    "addr:full":"Calle de Alcalde Velasco Navarro, 1 Cordoba C\u00f3rdoba 14004",
    "addr:housenumber":"1",
    "addr:postcode":"14004",
    "addr:street":"Calle De Alcalde Velasco Navarro;Co\u0301Rdoba",
    "iso:country":"ES",
    "sg:address":"Calle de Alcalde Velasco Navarro, 1",
    "sg:city":"Cordoba",
    "sg:orig_category":"Cl\u00cdnicas Dentales",
    "sg:phone":"+34 957 41 06 00",
    "sg:postcode":"14004",
    "sg:province":"C\u00f3rdoba",
    "wof:name":"Haba Giraldo Purificacion De La",
    "wof:placetype":"venue"
},
  "geometry": {"coordinates":[-4.7885727882,37.8813056946],"type":"Point"}
}