{
  "type": "Feature",
  "properties": {
    "iso:country":"ES",
    "sg:address":"Calle de Marques Viudo De Pontejos, 1",
    "sg:city":"Madrid",
    "sg:orig_category":"Procuradores",
    "sg:phone":"+34 915 21 04 80",
    "sg:postcode":"28012",
    "sg:province":"Madrid",
    "wof:name":"Rincon Mayoral Gloria Maria",
    "wof:placetype":"venue"
},
  "geometry": {"coordinates":[-3.7042579651,40.4156532288],"type":"Point"}
}