{
  "type": "Feature",
  "properties": {
    "addr:full":"Avda Cantabria, 85 Burgos Burgos 09006",
    "addr:housenumber":"85",
    "addr:postcode":"09006",
    "addr:street":"Avda Cantabria",
    "iso:country":"ES",
    "sg:address":"Avda Cantabria, 85",
    "sg:city":"Burgos",
    "sg:orig_category":"Art\u00cdculos De Limpieza Y De Cocina (fabricaci\u00d3n, Al Por Mayor)",
    "sg:phone":"+34 947 24 01 63",
    "sg:postcode":"09006",
    "sg:province":"Burgos",
    "wof:name":"Cipriano Alvarez Tapia S.l.",
    "wof:placetype":"venue"
},
  "geometry": {"coordinates":[-3.6915791035,42.3541908264],"type":"Point"}
}