{
  "type": "Feature",
  "properties": {
    "iso:country":"ES",
    "sg:address":"Avda Paz De (la), 53",
    "sg:city":"Logro\u00f1o",
    "sg:orig_category":"Confecci\u00d3n (fabricaci\u00d3n, Al Por Mayor)",
    "sg:phone":"+34 941 24 00 55",
    "sg:postcode":"26004",
    "sg:province":"La Rioja",
    "wof:name":"Galerias Salamanca S. A.",
    "wof:placetype":"venue"
},
  "geometry": {"coordinates":[-2.4345889091,42.4645843506],"type":"Point"}
}