{
  "type": "Feature",
  "properties": {
    "addr:full":"Avda Vigo, 106 Laredo Pontevedra 36320",
    "addr:housenumber":"106",
    "addr:postcode":"36320",
    "addr:street":"Avda Vigo",
    "iso:country":"ES",
    "sg:address":"Avda Vigo, 106",
    "sg:city":"Laredo",
    "sg:orig_category":"Delegados, Agentes De Tr\u00c1nsito, Auxiliares De Transporte Internacional",
    "sg:phone":"+34 986 45 07 65",
    "sg:postcode":"36320",
    "sg:province":"Pontevedra",
    "wof:name":"Lopez Novoa Manuel",
    "wof:placetype":"venue"
},
  "geometry": {"coordinates":[-8.6428003311,42.4304618835],"type":"Point"}
}