{
  "type": "Feature",
  "properties": {
    "iso:country":"ES",
    "sg:address":"Avda Libia (de), 15",
    "sg:city":"Cordoba",
    "sg:orig_category":"Servicio De Salud",
    "sg:phone":"+34 957 26 60 38",
    "sg:postcode":"14010",
    "sg:province":"C\u00f3rdoba",
    "wof:name":"Capote Carillo Antonio",
    "wof:placetype":"venue"
},
  "geometry": {"coordinates":[-4.7617502213,37.8892784119],"type":"Point"}
}