{
  "type": "Feature",
  "properties": {
    "iso:country":"ES",
    "sg:address":"Calle de Garcia Arista, 19",
    "sg:city":"Zaragoza",
    "sg:orig_category":"Centros Empresariales",
    "sg:phone":"+34 976 52 19 96",
    "sg:postcode":"50015",
    "sg:province":"Zaragoza",
    "sg:website":"www.ramel.com",
    "wof:name":"Acciona Facility Services S.a.",
    "wof:placetype":"venue"
},
  "geometry": {"coordinates":[-0.8768798113,41.6592445374],"type":"Point"}
}