{
  "type": "Feature",
  "properties": {
    "addr:full":"Camino Rabosero, 25 Mota Cuervo Cuenca 16630",
    "addr:housenumber":"25",
    "addr:postcode":"16630",
    "addr:street":"Camino Rabosero",
    "iso:country":"ES",
    "sg:address":"Camino Rabosero, 25",
    "sg:city":"Mota Cuervo",
    "sg:orig_category":"Negocio De Materiales De Construcci\u00d3n",
    "sg:phone":"+34 967 18 27 06",
    "sg:postcode":"16630",
    "sg:province":"Cuenca",
    "wof:name":"Lopez Villarreal Angel Luis",
    "wof:placetype":"venue"
},
  "geometry": {"coordinates":[-2.8780429363,39.5050735474],"type":"Point"}
}