{
  "type": "Feature",
  "properties": {
    "addr:full":"Calle de Cruz, 2 Fuente Maestre Badajoz 06360",
    "addr:housenumber":"2",
    "addr:postcode":"06360",
    "addr:street":"Calle De Cruz",
    "iso:country":"ES",
    "sg:address":"Calle de Cruz, 2",
    "sg:city":"Fuente Maestre",
    "sg:orig_category":"Contenedores (mercanc\u00cdas)",
    "sg:phone":"+34 924 53 02 09",
    "sg:postcode":"06360",
    "sg:province":"Badajoz",
    "wof:name":"Rojas Zambrano Antonio",
    "wof:placetype":"venue"
},
  "geometry": {"coordinates":[-6.4483389854,38.5288772583],"type":"Point"}
}