{
  "type": "Feature",
  "properties": {
    "iso:country":"ES",
    "sg:address":"Navarro Villoslada, 15",
    "sg:city":"Iru\u00f1a",
    "sg:orig_category":"Asociaciones, Organismos Culturales Y Socioeducativos",
    "sg:phone":"+34 948 24 19 09",
    "sg:postcode":"31003",
    "sg:province":"Navarra",
    "wof:name":"Asociacion Cultural Don Saturnino",
    "wof:placetype":"venue"
},
  "geometry": {"coordinates":[-1.6422675848,42.8112602234],"type":"Point"}
}