{
  "type": "Feature",
  "properties": {
    "iso:country":"ES",
    "sg:address":"Mayor, 73",
    "sg:city":"Estella",
    "sg:orig_category":"Farmacias",
    "sg:phone":"+34 948 55 03 40",
    "sg:postcode":"31200",
    "sg:province":"Navarra",
    "wof:name":"Manso Gorostola Milagros",
    "wof:placetype":"venue"
},
  "geometry": {"coordinates":[-2.0304489136,42.6710205078],"type":"Point"}
}