{
  "type": "Feature",
  "properties": {
    "addr:full":"Calle de Rosario, 12 Cadiz C\u00e1diz 11004",
    "addr:housenumber":"12",
    "addr:postcode":"11004",
    "addr:street":"Calle De Rosario",
    "iso:country":"ES",
    "sg:address":"Calle de Rosario, 12",
    "sg:city":"Cadiz",
    "sg:orig_category":"Art\u00cdculos De Regalo (al Por Menor)",
    "sg:phone":"+34 956 22 90 50",
    "sg:postcode":"11004",
    "sg:province":"C\u00e1diz",
    "wof:name":"Carde\u00f1osa Gonzalez Silvia",
    "wof:placetype":"venue"
},
  "geometry": {"coordinates":[-6.2948718071,36.5330505371],"type":"Point"}
}