{
  "type": "Feature",
  "properties": {
    "addr:full":"Pla\u00c7 Ajuntament, 20 Igualada Barcelona 08700",
    "addr:housenumber":"20",
    "addr:postcode":"08700",
    "iso:country":"ES",
    "sg:address":"Pla\u00c7 Ajuntament, 20",
    "sg:city":"Igualada",
    "sg:orig_category":"Agencias De Viajes",
    "sg:phone":"+34 938 05 56 56",
    "sg:postcode":"08700",
    "sg:province":"Barcelona",
    "sg:website":"www.halconviajes.com",
    "wof:name":"Viajes Halcon S.a.",
    "wof:placetype":"venue"
},
  "geometry": {"coordinates":[1.6169519424,41.578704834],"type":"Point"}
}