{
  "type": "Feature",
  "properties": {
    "iso:country":"ES",
    "sg:address":"Plaz Espa\u00d1a, 8",
    "sg:city":"Ribera Fresno",
    "sg:orig_category":"Asesor\u00cda Fiscal Y Jur\u00cddica",
    "sg:phone":"+34 924 53 61 51",
    "sg:postcode":"06225",
    "sg:province":"Badajoz",
    "wof:name":"Estudio Cinco Cdad",
    "wof:placetype":"venue"
},
  "geometry": {"coordinates":[-6.2413439751,38.5495986938],"type":"Point"}
}