{
  "type": "Feature",
  "properties": {
    "addr:full":"Calle de Doctor Severo Ochoa, 14 Aspe Alicante 03680",
    "addr:housenumber":"14",
    "addr:postcode":"03680",
    "addr:street":"Calle De Doctor Severo Ochoa",
    "iso:country":"ES",
    "sg:address":"Calle de Doctor Severo Ochoa, 14",
    "sg:city":"Aspe",
    "sg:orig_category":"Abogados",
    "sg:phone":"+34 965 49 49 84",
    "sg:postcode":"03680",
    "sg:province":"Alicante",
    "wof:name":"Conesa Sanchez Francisco Ramon",
    "wof:placetype":"venue"
},
  "geometry": {"coordinates":[-0.7700070739,38.3469924927],"type":"Point"}
}