{
  "type": "Feature",
  "properties": {
    "iso:country":"ES",
    "sg:address":"Calle de Fruta De La, 2",
    "sg:city":"Aviles",
    "sg:orig_category":"M\u00c9dicos: Cirug\u00cda Ortop\u00c9dica Y Traumatolog\u00cda",
    "sg:phone":"+34 985 54 59 11",
    "sg:postcode":"33402",
    "sg:province":"Asturias",
    "wof:name":"Llorente De Blas Belen",
    "wof:placetype":"venue"
},
  "geometry": {"coordinates":[-5.9221291542,43.5557022095],"type":"Point"}
}