{
  "type": "Feature",
  "properties": {
    "iso:country":"ES",
    "sg:address":"Plaz Mayor, 10",
    "sg:city":"Burgos",
    "sg:orig_category":"Inform\u00c1tica (estudios, Servicios, Asesor\u00cda, Formaci\u00d3n)",
    "sg:phone":"+34 947 27 38 69",
    "sg:postcode":"09003",
    "sg:province":"Burgos",
    "wof:name":"Micro-infor Salamanca S.l.",
    "wof:placetype":"venue"
},
  "geometry": {"coordinates":[-3.7021698952,42.3411750793],"type":"Point"}
}