{
  "type": "Feature",
  "properties": {
    "iso:country":"ES",
    "sg:address":"Urb. Navalpino, 16",
    "sg:city":"La Adrada",
    "sg:orig_category":"Locales Deportivos",
    "sg:phone":"+34 918 67 03 49",
    "sg:postcode":"05430",
    "sg:province":"\u00c1vila",
    "wof:name":"Arias Perez David",
    "wof:placetype":"venue"
},
  "geometry": {"coordinates":[-4.6553678513,40.2868766785],"type":"Point"}
}