{
  "type": "Feature",
  "properties": {
    "addr:full":"Avda Tirajana (de), 9 Playa Del Ingles Las Palmas 35100",
    "addr:housenumber":"9",
    "addr:postcode":"35100",
    "addr:street":"Avda Tirajana De",
    "iso:country":"ES",
    "sg:address":"Avda Tirajana (de), 9",
    "sg:city":"Playa Del Ingles",
    "sg:orig_category":"Asesor\u00cda Sobre Comunicaci\u00d3n De Empresas",
    "sg:phone":"+34 928 76 00 32",
    "sg:postcode":"35100",
    "sg:province":"Las Palmas",
    "wof:name":"Law Consulting Canarias Asesores S.l.l.",
    "wof:placetype":"venue"
},
  "geometry": {"coordinates":[-15.5778646469,27.7535362244],"type":"Point"}
}