{
  "type": "Feature",
  "properties": {
    "iso:country":"ES",
    "sg:address":"Calle de Nueva, 4",
    "sg:city":"Ceclavin",
    "sg:orig_category":"Reposter\u00cdas",
    "sg:phone":"+34 927 37 45 87",
    "sg:postcode":"10870",
    "sg:province":"C\u00e1ceres",
    "wof:name":"Modenes Mangas Victor Ramon",
    "wof:placetype":"venue"
},
  "geometry": {"coordinates":[-6.7753000259,39.8214187622],"type":"Point"}
}