{
  "type": "Feature",
  "properties": {
    "iso:country":"ES",
    "sg:address":"Ctra Madrid N-iv (extrarradio), 82",
    "sg:city":"Alcolea",
    "sg:orig_category":"Alimentaci\u00d3n General (al Por Menor)",
    "sg:phone":"+34 957 32 00 45",
    "sg:postcode":"14610",
    "sg:province":"C\u00f3rdoba",
    "wof:name":"Fragueiro Puerma Benito",
    "wof:placetype":"venue"
},
  "geometry": {"coordinates":[-4.6721282005,37.932636261],"type":"Point"}
}