{
  "type": "Feature",
  "properties": {
    "iso:country":"ES",
    "sg:address":"Avda Canarias, 201",
    "sg:city":"Vecindario",
    "sg:orig_category":"Ropa Para Se\u00d1oras Y Caballeros (al Por Menor)",
    "sg:phone":"+34 928 75 83 16",
    "sg:postcode":"35110",
    "sg:province":"Las Palmas",
    "wof:name":"Garbor Modas S.l.",
    "wof:placetype":"venue"
},
  "geometry": {"coordinates":[-15.4408483505,27.8512592316],"type":"Point"}
}