{
  "type": "Feature",
  "properties": {
    "iso:country":"ES",
    "sg:address":"Avda Ara\u00d1ones (de Los), 7",
    "sg:city":"Canfranc-estacion",
    "sg:orig_category":"Estancos",
    "sg:phone":"+34 974 37 30 79",
    "sg:postcode":"22880",
    "sg:province":"Huesca",
    "wof:name":"Munuera Moreno Fernando",
    "wof:placetype":"venue"
},
  "geometry": {"coordinates":[-0.5158740282,42.7473754883],"type":"Point"}
}