{
  "type": "Feature",
  "properties": {
    "addr:full":"Calle de San Marcial (de), 20 Mostoles Madrid 28931",
    "addr:postcode":"28931",
    "addr:street":"Calle De San;De;Mostoles",
    "iso:country":"ES",
    "sg:address":"Calle de San Marcial (de), 20",
    "sg:city":"Mostoles",
    "sg:orig_category":"Fabricaci\u00d3n De Sobres, Bolsas Y Fundas",
    "sg:phone":"+34 916 14 61 18",
    "sg:postcode":"28931",
    "sg:province":"Madrid",
    "wof:name":"Solana Dise\u00f1os S.l.",
    "wof:placetype":"venue"
},
  "geometry": {"coordinates":[-3.8607060909,40.3248596191],"type":"Point"}
}