{
  "type": "Feature",
  "properties": {
    "addr:full":"Lizaur Kalea, 1 O\u00f1ati Guip\u00f9zcoa 20560",
    "addr:housenumber":"1",
    "addr:postcode":"20560",
    "addr:street":"Lizaur Kalea;Guipu\u0300Zcoa",
    "iso:country":"ES",
    "sg:address":"Lizaur Kalea, 1",
    "sg:city":"O\u00f1ati",
    "sg:orig_category":"Fabricaci\u00d3n De Acumuladores Y De Pilas El\u00c9ctricas",
    "sg:phone":"+34 943 78 03 52",
    "sg:postcode":"20560",
    "sg:province":"Guip\u00f9zcoa",
    "wof:name":"Energia Portatil S.a.",
    "wof:placetype":"venue"
},
  "geometry": {"coordinates":[-2.4163489342,43.0346946716],"type":"Point"}
}