{
  "type": "Feature",
  "properties": {
    "iso:country":"ES",
    "sg:address":"J M Guelbenzu, 40",
    "sg:city":"Iru\u00f1a",
    "sg:orig_category":"Mec\u00c1nico Del Autom\u00d3vil",
    "sg:phone":"+34 948 23 55 22",
    "sg:postcode":"31005",
    "sg:province":"Navarra",
    "wof:name":"Talleres Salbea S.l.",
    "wof:placetype":"venue"
},
  "geometry": {"coordinates":[-1.6424529552,42.8057250977],"type":"Point"}
}