{
  "type": "Feature",
  "properties": {
    "iso:country":"ES",
    "sg:address":"Calle de Zapateria, 11",
    "sg:city":"Tarancon",
    "sg:orig_category":"\u00d3ptica: Instrumentos (fabricaci\u00d3n)",
    "sg:phone":"+34 969 32 00 98",
    "sg:postcode":"16400",
    "sg:province":"Cuenca",
    "wof:name":"Farmacia Cezar Garcia De Madariaga C.b.",
    "wof:placetype":"venue"
},
  "geometry": {"coordinates":[-3.0044839382,40.0114746094],"type":"Point"}
}