{
  "type": "Feature",
  "properties": {
    "addr:full":"Pl. Trobada, S/n Montferrer Lleida 25711",
    "addr:housenumber":"s / n",
    "addr:postcode":"25711",
    "addr:street":"Pl. Trobada",
    "iso:country":"ES",
    "sg:address":"Pl. Trobada, S/n",
    "sg:city":"Montferrer",
    "sg:orig_category":"Asociaciones Ecologistas",
    "sg:phone":"+34 973 35 57 28",
    "sg:postcode":"25711",
    "sg:province":"Lleida",
    "wof:name":"Comunitat De Regants Rec Dels 4 Pobles",
    "wof:placetype":"venue"
},
  "geometry": {"coordinates":[1.4278459549,42.3417358398],"type":"Point"}
}