{
  "type": "Feature",
  "properties": {
    "iso:country":"ES",
    "sg:address":"Calle de Pico De Los Artilleros, 121",
    "sg:city":"Madrid",
    "sg:orig_category":"Peluquer\u00cdas, Peluquer\u00cda Mixta",
    "sg:phone":"+34 917 72 51 55",
    "sg:postcode":"28030",
    "sg:province":"Madrid",
    "wof:name":"Duo Peluqueros S.l.",
    "wof:placetype":"venue"
},
  "geometry": {"coordinates":[-3.6429510117,40.4011573792],"type":"Point"}
}