{
  "type": "Feature",
  "properties": {
    "iso:country":"ES",
    "sg:address":"Rond Mu\u00d1oces (de Los), 58",
    "sg:city":"Pozoblanco",
    "sg:orig_category":"Alimentaci\u00d3n General (al Por Menor)",
    "sg:phone":"+34 957 77 29 22",
    "sg:postcode":"14400",
    "sg:province":"C\u00f3rdoba",
    "wof:name":"Caballero Lopez Isabel",
    "wof:placetype":"venue"
},
  "geometry": {"coordinates":[-4.8532218933,38.3778419495],"type":"Point"}
}