{
  "type": "Feature",
  "properties": {
    "iso:country":"ES",
    "sg:address":"Calle de Don Ramon De La Cruz, 98",
    "sg:city":"Madrid",
    "sg:orig_category":"Cl\u00cdnicas Dentales",
    "sg:phone":"+34 914 01 94 24",
    "sg:postcode":"28006",
    "sg:province":"Madrid",
    "wof:name":"Ramos Heras German",
    "wof:placetype":"venue"
},
  "geometry": {"coordinates":[-3.6704678535,40.4284629822],"type":"Point"}
}