{
  "type": "Feature",
  "properties": {
    "addr:full":"Carrer de Jocs Florals, 5 Esplugues Llobregat Barcelona 08950",
    "addr:housenumber":"5",
    "addr:postcode":"08950",
    "addr:street":"Carrer De Jocs Florals",
    "iso:country":"ES",
    "sg:address":"Carrer de Jocs Florals, 5",
    "sg:city":"Esplugues Llobregat",
    "sg:orig_category":"Iglesias Cristianas Diversas",
    "sg:phone":"+34 933 71 02 75",
    "sg:postcode":"08950",
    "sg:province":"Barcelona",
    "wof:name":"Testigos Cristianos De Jehova",
    "wof:placetype":"venue"
},
  "geometry": {"coordinates":[2.0959200859,41.3722381592],"type":"Point"}
}