{
  "type": "Feature",
  "properties": {
    "iso:country":"ES",
    "sg:address":"Milmanda, 1",
    "sg:city":"Sta. Eufemia",
    "sg:orig_category":"Empresas De Limpieza",
    "sg:phone":"+34 988 43 19 44",
    "sg:postcode":"32815",
    "sg:province":"Ourense",
    "wof:name":"Gomez Acebedo Evaristo",
    "wof:placetype":"venue"
},
  "geometry": {"coordinates":[-7.9767999649,42.0889549255],"type":"Point"}
}