{
  "type": "Feature",
  "properties": {
    "iso:country":"ES",
    "sg:address":"Avda Gudarien Etorbidea, S/n",
    "sg:city":"Andoain",
    "sg:orig_category":"Inform\u00c1tica (estudios, Servicios, Asesor\u00cda, Formaci\u00d3n)",
    "sg:phone":"+34 943 59 04 43",
    "sg:postcode":"20140",
    "sg:province":"Guip\u00f9zcoa",
    "sg:website":"www.plazagunea.com",
    "wof:name":"Plazagunea S.l.",
    "wof:placetype":"venue"
},
  "geometry": {"coordinates":[-2.0118739605,43.2246284485],"type":"Point"}
}