{
  "type": "Feature",
  "properties": {
    "iso:country":"ES",
    "sg:address":"Avda Aragon, 25",
    "sg:city":"Getafe",
    "sg:orig_category":"Servicio De Salud",
    "sg:phone":"+34 916 96 71 60",
    "sg:postcode":"28903",
    "sg:province":"Madrid",
    "wof:name":"Herrero Rodriguez Antonio",
    "wof:placetype":"venue"
},
  "geometry": {"coordinates":[-3.7156820297,40.3126907349],"type":"Point"}
}