{
  "type": "Feature",
  "properties": {
    "addr:full":"Calle de Ramon De Aguinaga, 15 Madrid Madrid 28028",
    "addr:housenumber":"15",
    "addr:postcode":"madrid;28028",
    "addr:street":"Calle De Ramon De Aguinaga",
    "iso:country":"ES",
    "sg:address":"Calle de Ramon De Aguinaga, 15",
    "sg:city":"Madrid",
    "sg:orig_category":"Inmobiliaria (agencias)",
    "sg:phone":"+34 913 56 82 00",
    "sg:postcode":"28028",
    "sg:province":"Madrid",
    "wof:name":"Comunidad De Propietarios Residencia Niagara",
    "wof:placetype":"venue"
},
  "geometry": {"coordinates":[-3.662072897,40.4269332886],"type":"Point"}
}