{
  "type": "Feature",
  "properties": {
    "addr:full":"Calle de Jorge Torner, 18 Cuenca Cuenca 16004",
    "addr:housenumber":"18",
    "addr:postcode":"16004",
    "addr:street":"Calle De Jorge Torner",
    "iso:country":"ES",
    "sg:address":"Calle de Jorge Torner, 18",
    "sg:city":"Cuenca",
    "sg:orig_category":"Postigos, Persianas Y Celos\u00cdas",
    "sg:phone":"+34 969 22 15 17",
    "sg:postcode":"16004",
    "sg:province":"Cuenca",
    "wof:name":"Garcia Nu\u00f1o Jesus",
    "wof:placetype":"venue"
},
  "geometry": {"coordinates":[-2.1341850758,40.0678596497],"type":"Point"}
}