{
  "type": "Feature",
  "properties": {
    "addr:full":"Rua Carral, 30 Vigo Pontevedra 36202",
    "addr:housenumber":"30",
    "addr:postcode":"36202",
    "addr:street":"Rua Carral",
    "iso:country":"ES",
    "sg:address":"Rua Carral, 30",
    "sg:city":"Vigo",
    "sg:orig_category":"Asesor\u00cda Sobre Comunicaci\u00d3n De Empresas",
    "sg:phone":"+34 986 22 81 10",
    "sg:postcode":"36202",
    "sg:province":"Pontevedra",
    "wof:name":"Fernandez Fernandez Alvaro",
    "wof:placetype":"venue"
},
  "geometry": {"coordinates":[-8.7245349884,42.2397994995],"type":"Point"}
}