{
  "type": "Feature",
  "properties": {
    "addr:full":"Calle de Puerto, 22 Puertollano Ciudad Real 13500",
    "addr:housenumber":"22",
    "addr:postcode":"13500",
    "addr:street":"Calle De Puerto",
    "iso:country":"ES",
    "sg:address":"Calle de Puerto, 22",
    "sg:city":"Puertollano",
    "sg:orig_category":"Molduras, Junquillos, Listones Y Molduras Perforadas",
    "sg:phone":"+34 926 43 20 29",
    "sg:postcode":"13500",
    "sg:province":"Ciudad Real",
    "wof:name":"Ruiz Aparicio Maria Jesus",
    "wof:placetype":"venue"
},
  "geometry": {"coordinates":[-4.1087341309,38.6897735596],"type":"Point"}
}