{
  "type": "Feature",
  "properties": {
    "iso:country":"ES",
    "sg:address":"Calle de Hortaleza, 41",
    "sg:city":"Madrid",
    "sg:orig_category":"Asociaciones Y Clubs Deportivos",
    "sg:phone":"+34 915 31 08 95",
    "sg:postcode":"28004",
    "sg:province":"Madrid",
    "wof:name":"Viva El Musculo S.l.",
    "wof:placetype":"venue"
},
  "geometry": {"coordinates":[-3.6995234489,40.4224700928],"type":"Point"}
}