{
  "type": "Feature",
  "properties": {
    "iso:country":"ES",
    "sg:address":"G.v. Corts Catalanes, 547",
    "sg:city":"Barcelona",
    "sg:orig_category":"Ense\u00d1anza: Comercio, Gesti\u00d3n, Inform\u00c1tica",
    "sg:phone":"+34 934 53 11 98",
    "sg:postcode":"08011",
    "sg:province":"Barcelona",
    "wof:name":"Camps Miro Magdalena",
    "wof:placetype":"venue"
},
  "geometry": {"coordinates":[2.1599969864,41.3836402893],"type":"Point"}
}