{
  "type": "Feature",
  "properties": {
    "iso:country":"ES",
    "sg:address":"Plaz Espa\u00d1a, 5",
    "sg:city":"Albolote",
    "sg:orig_category":"Electrodom\u00c9sticos (al Por Menor)",
    "sg:phone":"+34 958 46 74 15",
    "sg:postcode":"18220",
    "sg:province":"Granada",
    "wof:name":"Medina Lopez Antonio",
    "wof:placetype":"venue"
},
  "geometry": {"coordinates":[-3.656826973,37.2307167053],"type":"Point"}
}