{
  "type": "Feature",
  "properties": {
    "iso:country":"ES",
    "sg:address":"Avda Dos De Mayo (del), 27",
    "sg:city":"Mostoles",
    "sg:orig_category":"Art\u00cdculos De Regalo (al Por Menor)",
    "sg:phone":"+34 916 64 00 67",
    "sg:postcode":"28934",
    "sg:province":"Madrid",
    "wof:name":"Regale Bien S.l.",
    "wof:placetype":"venue"
},
  "geometry": {"coordinates":[-3.8699660301,40.3201293945],"type":"Point"}
}