{
  "type": "Feature",
  "properties": {
    "addr:full":"Calle de Guevara, 23 Santander Cantabria 39001",
    "addr:housenumber":"23",
    "addr:postcode":"39001",
    "addr:street":"Calle De Guevara",
    "iso:country":"ES",
    "sg:address":"Calle de Guevara, 23",
    "sg:city":"Santander",
    "sg:orig_category":"Bisuter\u00cda, Joyer\u00cda, Relojer\u00cda (al Por Menor)",
    "sg:phone":"+34 942 22 91 00",
    "sg:postcode":"39001",
    "sg:province":"Cantabria",
    "wof:name":"Lopez Polvorosa Francisco",
    "wof:placetype":"venue"
},
  "geometry": {"coordinates":[-3.8057620525,43.4635353088],"type":"Point"}
}