{
  "type": "Feature",
  "properties": {
    "iso:country":"ES",
    "sg:address":"Calle de Carreteria, 27",
    "sg:city":"Cuenca",
    "sg:orig_category":"Ropa Para Caballeros (al Por Menor)",
    "sg:phone":"+34 969 22 86 65",
    "sg:postcode":"16002",
    "sg:province":"Cuenca",
    "wof:name":"Cortefiel S.a.",
    "wof:placetype":"venue"
},
  "geometry": {"coordinates":[-2.1362628937,40.0727653503],"type":"Point"}
}