{
  "type": "Feature",
  "properties": {
    "addr:full":"Avda Casanova De Eiris, 31 Coru\u00d1a La Coru\u00f1a 15009",
    "addr:housenumber":"31",
    "addr:postcode":"15009",
    "addr:street":"Avda Casanova De Eiris;La Corun\u0303A",
    "iso:country":"ES",
    "sg:address":"Avda Casanova De Eiris, 31",
    "sg:city":"Coru\u00d1a",
    "sg:orig_category":"Desinfecci\u00d3n, Desinsectaci\u00d3n, Desratizaci\u00d3n",
    "sg:phone":"+34 981 13 75 18",
    "sg:postcode":"15009",
    "sg:province":"La Coru\u00f1a",
    "wof:name":"Control De Plagas Andrade S.l.",
    "wof:placetype":"venue"
},
  "geometry": {"coordinates":[-8.3969182968,43.3489379883],"type":"Point"}
}