{
  "type": "Feature",
  "properties": {
    "iso:country":"ES",
    "sg:address":"Errekarte Kalea, 34",
    "sg:city":"Beasain",
    "sg:orig_category":"Tapiceros Y Tapiceros",
    "sg:phone":"+34 943 88 54 53",
    "sg:postcode":"20200",
    "sg:province":"Guip\u00f9zcoa",
    "wof:name":"Diez Mosquera Teodora Isabel",
    "wof:placetype":"venue"
},
  "geometry": {"coordinates":[-2.2138659954,43.0471496582],"type":"Point"}
}