{
  "type": "Feature",
  "properties": {
    "iso:country":"ES",
    "sg:address":"Carr Dr. Rafel Rotger I Mestre, 2",
    "sg:city":"Sineu",
    "sg:orig_category":"M\u00c1rmoles, Granitos Y Piedras Naturales",
    "sg:phone":"+34 971 85 53 02",
    "sg:postcode":"07510",
    "sg:province":"Islas Baleares",
    "wof:name":"Marmoles Maesma S.l.",
    "wof:placetype":"venue"
},
  "geometry": {"coordinates":[3.0094261169,39.6433181763],"type":"Point"}
}