{
  "type": "Feature",
  "properties": {
    "iso:country":"ES",
    "sg:address":"Astronomia, 15",
    "sg:city":"Rubi",
    "sg:orig_category":"Agencias Y Agentes Comerciales, Representantes",
    "sg:phone":"+34 935 88 25 04",
    "sg:postcode":"08191",
    "sg:province":"Barcelona",
    "wof:name":"Comunidad De Propietarios Astronomia 15",
    "wof:placetype":"venue"
},
  "geometry": {"coordinates":[2.0425920486,41.4883728027],"type":"Point"}
}