{
  "type": "Feature",
  "properties": {
    "addr:full":"Ctra M-111 (paracuellos-belvis), 3 El Cruce Madrid 28860",
    "addr:housenumber":"3",
    "addr:postcode":"28860",
    "addr:street":"Ctra M-111 Paracuellos-Belvis",
    "iso:country":"ES",
    "sg:address":"Ctra M-111 (paracuellos-belvis), 3",
    "sg:city":"El Cruce",
    "sg:orig_category":"Fabricaci\u00d3n De Bordes Y Molduras Para Edificaci\u00d3n Y Decoraci\u00d3n",
    "sg:phone":"+34 916 58 04 23",
    "sg:postcode":"28860",
    "sg:province":"Madrid",
    "wof:name":"Maderas Morcillo S. L.",
    "wof:placetype":"venue"
},
  "geometry": {"coordinates":[-3.5296940804,40.5049209595],"type":"Point"}
}