{
  "type": "Feature",
  "properties": {
    "addr:full":"Rua Rosalia De Castro, 26 Burela Lugo 27880",
    "addr:housenumber":"26",
    "addr:postcode":"27880",
    "addr:street":"Rua Rosalia De Castro",
    "iso:country":"ES",
    "sg:address":"Rua Rosalia De Castro, 26",
    "sg:city":"Burela",
    "sg:orig_category":"Carnicer\u00cdas, Carnicer\u00cdas",
    "sg:phone":"+34 982 58 63 03",
    "sg:postcode":"27880",
    "sg:province":"Lugo",
    "wof:name":"Dayanpri S.l.",
    "wof:placetype":"venue"
},
  "geometry": {"coordinates":[-7.3625588417,43.6638298035],"type":"Point"}
}