{
  "type": "Feature",
  "properties": {
    "iso:country":"ES",
    "sg:address":"Carrer de Mineria, 5",
    "sg:city":"Barcelona",
    "sg:orig_category":"M\u00c9dicos: Estomatolog\u00cda",
    "sg:phone":"+34 932 96 83 85",
    "sg:postcode":"08038",
    "sg:province":"Barcelona",
    "wof:name":"Puigpelat Marti Ana Maria",
    "wof:placetype":"venue"
},
  "geometry": {"coordinates":[2.1370589733,41.3643264771],"type":"Point"}
}