{
  "type": "Feature",
  "properties": {
    "addr:full":"Plaz Estacion (de La), 1 Jerez De La Frontera C\u00e1diz 11401",
    "addr:postcode":"11401",
    "iso:country":"ES",
    "sg:address":"Plaz Estacion (de La), 1",
    "sg:city":"Jerez De La Frontera",
    "sg:orig_category":"Molduras, Junquillos, Listones Y Molduras Perforadas",
    "sg:phone":"+34 956 34 68 99",
    "sg:postcode":"11401",
    "sg:province":"C\u00e1diz",
    "wof:name":"Pizarro Marin Miguel",
    "wof:placetype":"venue"
},
  "geometry": {"coordinates":[-6.126748085,36.6793212891],"type":"Point"}
}