{
  "type": "Feature",
  "properties": {
    "addr:full":"Bard Carabina (la), 14 Chiclana De La Frontera C\u00e1diz 11130",
    "addr:postcode":"11130",
    "addr:street":"Carabina",
    "iso:country":"ES",
    "sg:address":"Bard Carabina (la), 14",
    "sg:city":"Chiclana De La Frontera",
    "sg:orig_category":"Carnicer\u00cdas, Carnicer\u00cdas",
    "sg:phone":"+34 956 53 80 58",
    "sg:postcode":"11130",
    "sg:province":"C\u00e1diz",
    "wof:name":"Rendon Bernal Jose",
    "wof:placetype":"venue"
},
  "geometry": {"coordinates":[-6.1553521156,36.3683242798],"type":"Point"}
}