{
  "type": "Feature",
  "properties": {
    "addr:full":"Ctra Rosario (del), Km. 0004,0 Santa Cruz De Tenerife Santa Cruz De Tenerife 38009",
    "addr:postcode":"38009",
    "addr:street":"Ctra Rosario Del Km. 0004,0",
    "iso:country":"ES",
    "sg:address":"Ctra Rosario (del), Km. 0004,0",
    "sg:city":"Santa Cruz De Tenerife",
    "sg:orig_category":"Ense\u00d1anza, Formaci\u00d3n Profesional: Aprendizaje",
    "sg:phone":"+34 922 64 42 90",
    "sg:postcode":"38009",
    "sg:province":"Santa Cruz De Tenerife",
    "wof:name":"Gobierno De Canarias",
    "wof:placetype":"venue"
},
  "geometry": {"coordinates":[-17.7755756378,28.6416091919],"type":"Point"}
}