{
  "type": "Feature",
  "properties": {
    "addr:full":"Carrer de Uetam, 9 Palma Islas Baleares 07006",
    "addr:housenumber":"9",
    "addr:postcode":"07006",
    "addr:street":"Carrer De Uetam",
    "iso:country":"ES",
    "sg:address":"Carrer de Uetam, 9",
    "sg:city":"Palma",
    "sg:orig_category":"Servicios De Telecomunicaciones",
    "sg:phone":"+34 971 77 75 63",
    "sg:postcode":"07006",
    "sg:province":"Islas Baleares",
    "wof:name":"Ahmed Nie  Shahazad",
    "wof:placetype":"venue"
},
  "geometry": {"coordinates":[2.659807682,39.5742950439],"type":"Point"}
}