{
  "type": "Feature",
  "properties": {
    "addr:full":"Luga Finca Zagaleta, 21 Artola M\u00e1laga 29679",
    "addr:housenumber":"21",
    "addr:postcode":"29679",
    "addr:street":"Artola Ma\u0301Laga",
    "iso:country":"ES",
    "sg:address":"Luga Finca Zagaleta, 21",
    "sg:city":"Artola",
    "sg:orig_category":"Inmobiliaria (agencias)",
    "sg:phone":"+34 952 85 60 16",
    "sg:postcode":"29679",
    "sg:province":"M\u00e1laga",
    "wof:name":"Infinorsa Gestion Inmobiliaria Y Financiera S.a.",
    "wof:placetype":"venue"
},
  "geometry": {"coordinates":[-4.756207943,36.4944267273],"type":"Point"}
}