{
  "type": "Feature",
  "properties": {
    "iso:country":"ES",
    "sg:address":"Calle de Tomas El Medico (don), 7",
    "sg:city":"Villanueva De Los Infantes",
    "sg:orig_category":"Molduras, Junquillos, Listones Y Molduras Perforadas",
    "sg:phone":"+34 926 36 03 07",
    "sg:postcode":"13320",
    "sg:province":"Ciudad Real",
    "wof:name":"Zopeque Santos Felipe",
    "wof:placetype":"venue"
},
  "geometry": {"coordinates":[-3.0115945339,38.7347564697],"type":"Point"}
}