{
  "type": "Feature",
  "properties": {
    "iso:country":"ES",
    "sg:address":"Avda Europa, 185",
    "sg:city":"Mojonera",
    "sg:orig_category":"Transportes Por Carretera: Lotes Completos, Mercanc\u00cdas Diversas",
    "sg:phone":"+34 950 33 06 28",
    "sg:postcode":"04745",
    "sg:province":"Almer\u00eda",
    "wof:name":"Torres Alferez Jose",
    "wof:placetype":"venue"
},
  "geometry": {"coordinates":[-2.6837658882,36.7547721863],"type":"Point"}
}