{
  "type": "Feature",
  "properties": {
    "addr:full":"Calle de Ezequiel Solana, 16 Madrid Madrid 28017",
    "addr:housenumber":"16",
    "addr:postcode":"madrid;28017",
    "addr:street":"Calle De Ezequiel Solana",
    "iso:country":"ES",
    "sg:address":"Calle de Ezequiel Solana, 16",
    "sg:city":"Madrid",
    "sg:orig_category":"Venta, Instalaci\u00d3n De Sistemas De Alarmas Y Vigilancia",
    "sg:phone":"+34 913 77 51 68",
    "sg:postcode":"28017",
    "sg:province":"Madrid",
    "wof:name":"Kelly Alarm S.l.",
    "wof:placetype":"venue"
},
  "geometry": {"coordinates":[-3.6469209194,40.4329605103],"type":"Point"}
}