{
  "type": "Feature",
  "properties": {
    "iso:country":"ES",
    "sg:address":"Calle de Maqueda, 20",
    "sg:city":"Madrid",
    "sg:orig_category":"Herboristas (al Por Menor)",
    "sg:phone":"+34 917 11 75 28",
    "sg:postcode":"28024",
    "sg:province":"Madrid",
    "wof:name":"Fernandez Fernandez Ascension",
    "wof:placetype":"venue"
},
  "geometry": {"coordinates":[-3.7664968967,40.3938407898],"type":"Point"}
}