{
  "type": "Feature",
  "properties": {
    "addr:full":"Av Cami De Mao, 142 Ciutadella Menorca Islas Baleares 07760",
    "addr:housenumber":"142",
    "addr:postcode":"07760",
    "addr:street":"Av Cami De Mao",
    "iso:country":"ES",
    "sg:address":"Av Cami De Mao, 142",
    "sg:city":"Ciutadella Menorca",
    "sg:orig_category":"Venta, Montaje De Neum\u00c1ticos",
    "sg:phone":"+34 971 38 43 08",
    "sg:postcode":"07760",
    "sg:province":"Islas Baleares",
    "wof:name":"Pneumatics Ciutadella S.l.",
    "wof:placetype":"venue"
},
  "geometry": {"coordinates":[3.8416149616,40.0027542114],"type":"Point"}
}