{
  "type": "Feature",
  "properties": {
    "iso:country":"ES",
    "sg:address":"Calle de Gil De Andrade, 11",
    "sg:city":"Alcala Henares",
    "sg:orig_category":"Molduras, Junquillos, Listones Y Molduras Perforadas",
    "sg:phone":"+34 918 80 64 36",
    "sg:postcode":"28804",
    "sg:province":"Madrid",
    "wof:name":"Paniagua Sanchez Gregorio",
    "wof:placetype":"venue"
},
  "geometry": {"coordinates":[-3.3547992706,40.4880523682],"type":"Point"}
}