{
  "type": "Feature",
  "properties": {
    "iso:country":"ES",
    "sg:address":"Calle de Montes De Oca, 17",
    "sg:city":"Villalonquejar",
    "sg:orig_category":"Paletas",
    "sg:phone":"+34 947 29 86 04",
    "sg:postcode":"09001",
    "sg:province":"Burgos",
    "wof:name":"Roberto Y Oscar Nu\u00f1ez Garcia Cb",
    "wof:placetype":"venue"
},
  "geometry": {"coordinates":[-3.7568581104,42.3604011536],"type":"Point"}
}