{
  "type": "Feature",
  "properties": {
    "addr:full":"Rond Bellavista, 7 Mataro Barcelona 08303",
    "addr:housenumber":"7",
    "addr:postcode":"08303",
    "addr:street":"Bellavista",
    "iso:country":"ES",
    "sg:address":"Rond Bellavista, 7",
    "sg:city":"Mataro",
    "sg:orig_category":"Muebles Y Accesorios Para Cocinas Y Cuartos De Ba\u00d1o (al Por Menor)",
    "sg:phone":"+34 937 57 61 13",
    "sg:postcode":"08303",
    "sg:province":"Barcelona",
    "wof:name":"Fernandez Lopez Antonio",
    "wof:placetype":"venue"
},
  "geometry": {"coordinates":[2.4251599312,41.5447463989],"type":"Point"}
}