{
  "type": "Feature",
  "properties": {
    "addr:full":"Calle de Escuelas (las), S/n Belver De Cinca Huesca 22533",
    "addr:postcode":"22533",
    "addr:street":"Calle De Escuelas Las S / N",
    "iso:country":"ES",
    "sg:address":"Calle de Escuelas (las), S/n",
    "sg:city":"Belver De Cinca",
    "sg:orig_category":"Mec\u00c1nico Del Autom\u00d3vil",
    "sg:phone":"+34 974 46 81 74",
    "sg:postcode":"22533",
    "sg:province":"Huesca",
    "wof:name":"Talleres Ibarz S.c.",
    "wof:placetype":"venue"
},
  "geometry": {"coordinates":[0.1767639965,41.6935882568],"type":"Point"}
}