{
  "type": "Feature",
  "properties": {
    "addr:full":"Carrer de Francisco Giner, 52 Barcelona Barcelona 08012",
    "addr:housenumber":"52",
    "addr:postcode":"08012",
    "addr:street":"Carrer De Francisco Giner",
    "iso:country":"ES",
    "sg:address":"Carrer de Francisco Giner, 52",
    "sg:city":"Barcelona",
    "sg:orig_category":"Compraventa De Antig\u00dcedades",
    "sg:phone":"+34 932 18 63 34",
    "sg:postcode":"08012",
    "sg:province":"Barcelona",
    "wof:name":"Sangenis Crotogino Alberto",
    "wof:placetype":"venue"
},
  "geometry": {"coordinates":[2.158479929,41.3999290466],"type":"Point"}
}