{
  "type": "Feature",
  "properties": {
    "iso:country":"ES",
    "sg:address":"Carrer de Alfou, 17",
    "sg:city":"Cardedeu",
    "sg:orig_category":"Institutos De Belleza",
    "sg:phone":"+34 938 45 40 15",
    "sg:postcode":"08440",
    "sg:province":"Barcelona",
    "wof:name":"Borras Padillo Marta",
    "wof:placetype":"venue"
},
  "geometry": {"coordinates":[2.3624560833,41.642124176],"type":"Point"}
}