{
  "type": "Feature",
  "properties": {
    "iso:country":"ES",
    "sg:address":"Pl. Muelle, S/n",
    "sg:city":"Sanlucar",
    "sg:orig_category":"Fabricaci\u00d3n, Reparaci\u00d3n Y Mantenimiento De Construcciones Navales Y Fluviales",
    "sg:phone":"+34 956 36 19 68",
    "sg:postcode":"11540",
    "sg:province":"C\u00e1diz",
    "wof:name":"Guerrero Romero Jose Antonio",
    "wof:placetype":"venue"
},
  "geometry": {"coordinates":[-6.3369340897,36.8030014038],"type":"Point"}
}