{
  "type": "Feature",
  "properties": {
    "addr:full":"Av Cornella, 30 Esplugues Llobregat Barcelona 08950",
    "addr:housenumber":"30",
    "addr:postcode":"08950",
    "addr:street":"Av Cornella",
    "iso:country":"ES",
    "sg:address":"Av Cornella, 30",
    "sg:city":"Esplugues Llobregat",
    "sg:orig_category":"Agencias De Viajes",
    "sg:phone":"+34 933 72 73 11",
    "sg:postcode":"08950",
    "sg:province":"Barcelona",
    "sg:website":"www.viajesiberia.com",
    "wof:name":"Viajes Iberia S.a.",
    "wof:placetype":"venue"
},
  "geometry": {"coordinates":[2.0869650841,41.375995636],"type":"Point"}
}