{
  "type": "Feature",
  "properties": {
    "iso:country":"ES",
    "sg:address":"Isla(el Acantilado), 1",
    "sg:city":"Cabo Palos",
    "sg:orig_category":"Arquitectos",
    "sg:phone":"+34 968 14 62 85",
    "sg:postcode":"30370",
    "sg:province":"Murcia",
    "wof:name":"Martin Tebar Rogelio",
    "wof:placetype":"venue"
},
  "geometry": {"coordinates":[-0.7274389863,37.6292953491],"type":"Point"}
}