{
  "type": "Feature",
  "properties": {
    "iso:country":"ES",
    "sg:address":"Calle de Reina (de La), 16",
    "sg:city":"Aranjuez",
    "sg:orig_category":"Asociaciones Y Clubs Deportivos",
    "sg:phone":"+34 918 91 68 03",
    "sg:postcode":"28300",
    "sg:province":"Madrid",
    "wof:name":"Centro Cultural De Pesca",
    "wof:placetype":"venue"
},
  "geometry": {"coordinates":[-3.6008338928,40.0369033813],"type":"Point"}
}