{
  "type": "Feature",
  "properties": {
    "iso:country":"ES",
    "sg:address":"Ctra Tacoronte Tejina, 319",
    "sg:city":"Tacoronte",
    "sg:orig_category":"Centros Empresariales",
    "sg:phone":"+34 922 56 42 62",
    "sg:postcode":"38350",
    "sg:province":"Santa Cruz De Tenerife",
    "wof:name":"Argot Consultores De Comunicacion S.l.",
    "wof:placetype":"venue"
},
  "geometry": {"coordinates":[-16.409412384,28.4911975861],"type":"Point"}
}