{
  "type": "Feature",
  "properties": {
    "iso:country":"ES",
    "sg:address":"Carrer de Vicente Tofi\u00d1o, 26",
    "sg:city":"Coll De'n Rabassa",
    "sg:orig_category":"Reposter\u00cdas",
    "sg:phone":"+34 971 26 62 57",
    "sg:postcode":"07007",
    "sg:province":"Islas Baleares",
    "sg:website":"www.forndecampos.com",
    "wof:name":"Maquinas De Internet S.l.",
    "wof:placetype":"venue"
},
  "geometry": {"coordinates":[2.9117100239,39.6136398315],"type":"Point"}
}