{
  "type": "Feature",
  "properties": {
    "addr:full":"Avda Molsa, 38 Sesue Huesca 22467",
    "addr:housenumber":"38",
    "addr:postcode":"22467",
    "addr:street":"Avda Molsa",
    "iso:country":"ES",
    "sg:address":"Avda Molsa, 38",
    "sg:city":"Sesue",
    "sg:orig_category":"Asociaciones, Organismos Culturales Y Socioeducativos",
    "sg:phone":"+34 974 55 35 46",
    "sg:postcode":"22467",
    "sg:province":"Huesca",
    "wof:name":"Asociacion Guayente El Remos",
    "wof:placetype":"venue"
},
  "geometry": {"coordinates":[0.4727303088,42.5516586304],"type":"Point"}
}