{
  "type": "Feature",
  "properties": {
    "addr:full":"Calle de Mar Mediterraneo (del), 4 Poligono De San Fernando De Henares Madrid 28830",
    "addr:housenumber":"4",
    "addr:postcode":"28830",
    "addr:street":"Calle De Mar Mediterraneo Del",
    "iso:country":"ES",
    "sg:address":"Calle de Mar Mediterraneo (del), 4",
    "sg:city":"Poligono De San Fernando De Henares",
    "sg:orig_category":"Marketing Directo",
    "sg:phone":"+34 916 75 22 23",
    "sg:postcode":"28830",
    "sg:province":"Madrid",
    "wof:name":"Dorna Sports S.l.",
    "wof:placetype":"venue"
},
  "geometry": {"coordinates":[-3.5041151047,40.4550743103],"type":"Point"}
}