{
  "type": "Feature",
  "properties": {
    "addr:full":"Carrer de Madrazo, 153 Barcelona Barcelona 08021",
    "addr:housenumber":"153",
    "addr:postcode":"08021",
    "addr:street":"Carrer De Madrazo",
    "iso:country":"ES",
    "sg:address":"Carrer de Madrazo, 153",
    "sg:city":"Barcelona",
    "sg:orig_category":"Empresarios",
    "sg:phone":"+34 932 09 22 94",
    "sg:postcode":"08021",
    "sg:province":"Barcelona",
    "wof:name":"Maig 95 S.l.",
    "wof:placetype":"venue"
},
  "geometry": {"coordinates":[2.1432828903,41.3957710266],"type":"Point"}
}