{
  "type": "Feature",
  "properties": {
    "addr:full":"Czad San Pedro, 12 Ledesma Salamanca 37100",
    "addr:housenumber":"12",
    "addr:postcode":"37100",
    "addr:street":"San Pedro",
    "iso:country":"ES",
    "sg:address":"Czad San Pedro, 12",
    "sg:city":"Ledesma",
    "sg:orig_category":"Iglesia Cat\u00d3lica",
    "sg:phone":"+34 923 57 00 97",
    "sg:postcode":"37100",
    "sg:province":"Salamanca",
    "wof:name":"Obispado De Salamanca",
    "wof:placetype":"venue"
},
  "geometry": {"coordinates":[-5.9992961884,41.0876197815],"type":"Point"}
}