{
  "type": "Feature",
  "properties": {
    "iso:country":"ES",
    "sg:address":"Ctra Madrid-alicante, S/n",
    "sg:city":"Chinchilla Monte-aragon",
    "sg:orig_category":"Piscinas, Accesorios, Suministros (fabricaci\u00d3n, Al Por Mayor)",
    "sg:phone":"+34 967 26 01 91",
    "sg:postcode":"02520",
    "sg:province":"Albacete",
    "wof:name":"Ayuntamiento De Chinchilla",
    "wof:placetype":"venue"
},
  "geometry": {"coordinates":[-1.8600701094,38.9976501465],"type":"Point"}
}