{
  "type": "Feature",
  "properties": {
    "iso:country":"ES",
    "sg:address":"Avda Emilio Romero (de), 11",
    "sg:city":"Arevalo",
    "sg:orig_category":"Abogados",
    "sg:phone":"+34 920 30 35 36",
    "sg:postcode":"05200",
    "sg:province":"\u00c1vila",
    "wof:name":"Alba Caro Luis De",
    "wof:placetype":"venue"
},
  "geometry": {"coordinates":[-4.7182145119,41.0585174561],"type":"Point"}
}