{
  "type": "Feature",
  "properties": {
    "iso:country":"ES",
    "sg:address":"Rua Campo De San Antonio, 21",
    "sg:city":"Monforte De Lemos",
    "sg:orig_category":"Mec\u00c1nico Del Autom\u00d3vil",
    "sg:phone":"+34 982 40 22 56",
    "sg:postcode":"27400",
    "sg:province":"Lugo",
    "wof:name":"Carballo Corujo Jaime",
    "wof:placetype":"venue"
},
  "geometry": {"coordinates":[-7.5172939301,42.5221710205],"type":"Point"}
}