{
  "type": "Feature",
  "properties": {
    "addr:full":"Calle de Bidebarri, 3 Algorta Vizcaya 48991",
    "addr:housenumber":"3",
    "addr:postcode":"48991",
    "addr:street":"Calle De Bidebarri",
    "iso:country":"ES",
    "sg:address":"Calle de Bidebarri, 3",
    "sg:city":"Algorta",
    "sg:orig_category":"Mercer\u00cda, Lencer\u00cda (al Por Menor)",
    "sg:phone":"+34 944 30 85 89",
    "sg:postcode":"48991",
    "sg:province":"Vizcaya",
    "wof:name":"Rus Mu\u00f1oz Alfonsa",
    "wof:placetype":"venue"
},
  "geometry": {"coordinates":[-3.009059906,43.3524589539],"type":"Point"}
}