{
  "type": "Feature",
  "properties": {
    "iso:country":"ES",
    "sg:address":"Calle de Marcos Zapata, 42",
    "sg:city":"Zaragoza",
    "sg:classifiers":[
        {
            "category":"Casinos & Gambling",
            "type":"Entertainment"
        }
    ],
    "sg:phone":"+34 976 32 86 20",
    "sg:postcode":"50010",
    "sg:province":"Zaragoza",
    "sg:tags":[
        "locale",
        "de",
        "juego"
    ],
    "wof:name":"Aragonesa Juegos Sociedad Anonima",
    "wof:placetype":"venue"
},
  "geometry": {"coordinates":[-0.907525599,41.6530189514],"type":"Point"}
}