{
  "type": "Feature",
  "properties": {
    "iso:country":"ES",
    "sg:address":"Plaz Iglesia (de La), 1",
    "sg:city":"Peguerinos",
    "sg:orig_category":"Sanatorios M\u00c9dico",
    "sg:phone":"+34 918 98 30 17",
    "sg:postcode":"05293",
    "sg:province":"\u00c1vila",
    "wof:name":"Ayuntamiento De Peguerinos",
    "wof:placetype":"venue"
},
  "geometry": {"coordinates":[-4.2327275276,40.6272850037],"type":"Point"}
}