{
  "type": "Feature",
  "properties": {
    "iso:country":"ES",
    "sg:address":"Canton De La Iglesia, 2",
    "sg:city":"Padron",
    "sg:orig_category":"Molduras, Junquillos, Listones Y Molduras Perforadas",
    "sg:phone":"+34 981 81 21 11",
    "sg:postcode":"15900",
    "sg:province":"La Coru\u00f1a",
    "wof:name":"Gil Abalo Jose Manuel",
    "wof:placetype":"venue"
},
  "geometry": {"coordinates":[-8.6612787247,42.7393226624],"type":"Point"}
}