{
  "type": "Feature",
  "properties": {
    "addr:full":"Avgd Marques De Sant Mori, 159 Badalona Barcelona 08914",
    "addr:housenumber":"159",
    "addr:postcode":"08914",
    "addr:street":"Mori",
    "iso:country":"ES",
    "sg:address":"Avgd Marques De Sant Mori, 159",
    "sg:city":"Badalona",
    "sg:orig_category":"Partidos Pol\u00cdticos",
    "sg:phone":"+34 934 60 28 81",
    "sg:postcode":"08914",
    "sg:province":"Barcelona",
    "wof:name":"Partit Dels Comunistes De Catalunya",
    "wof:placetype":"venue"
},
  "geometry": {"coordinates":[2.2237100601,41.4420204163],"type":"Point"}
}