{
  "type": "Feature",
  "properties": {
    "addr:full":"Uarkape Kalea, 2 Arrasate Guip\u00f9zcoa 20500",
    "addr:housenumber":"2",
    "addr:postcode":"20500",
    "addr:street":"Uarkape Kalea;Guipu\u0300Zcoa",
    "iso:country":"ES",
    "sg:address":"Uarkape Kalea, 2",
    "sg:city":"Arrasate",
    "sg:orig_category":"Contenedores Para Transporte De Mercanc\u00cdas",
    "sg:phone":"+34 943 77 12 40",
    "sg:postcode":"20500",
    "sg:province":"Guip\u00f9zcoa",
    "wof:name":"Ceciaga Ibarrondo Jose",
    "wof:placetype":"venue"
},
  "geometry": {"coordinates":[-2.4895451069,43.06772995],"type":"Point"}
}