{
  "type": "Feature",
  "properties": {
    "addr:full":"Calle de Berastegui, 5 Bilbao Vizcaya 48001",
    "addr:housenumber":"5",
    "addr:postcode":"48001",
    "addr:street":"Calle De Berastegui",
    "iso:country":"ES",
    "sg:address":"Calle de Berastegui, 5",
    "sg:city":"Bilbao",
    "sg:orig_category":"Empresas De Limpieza",
    "sg:phone":"+34 944 24 67 80",
    "sg:postcode":"48001",
    "sg:province":"Vizcaya",
    "wof:name":"Garnica S. A.",
    "wof:placetype":"venue"
},
  "geometry": {"coordinates":[-2.927955389,43.2622947693],"type":"Point"}
}