{
  "type": "Feature",
  "properties": {
    "iso:country":"ES",
    "sg:address":"Avda Perimetral, 1",
    "sg:city":"Jaca",
    "sg:orig_category":"Pintura Y Barniz (al Por Menor)",
    "sg:phone":"+34 974 35 55 62",
    "sg:postcode":"22700",
    "sg:province":"Huesca",
    "wof:name":"Pinturas Manuel Ines S.l.",
    "wof:placetype":"venue"
},
  "geometry": {"coordinates":[-0.5536850095,42.5664215088],"type":"Point"}
}