{
  "type": "Feature",
  "properties": {
    "iso:country":"ES",
    "sg:address":"Calle de Benigno Soto, 5",
    "sg:city":"Madrid",
    "sg:orig_category":"Aparcamientos (infraestructuras, Accesorios)",
    "sg:phone":"+34 914 16 68 26",
    "sg:postcode":"28002",
    "sg:province":"Madrid",
    "wof:name":"Moraleja Frias Jesus",
    "wof:placetype":"venue"
},
  "geometry": {"coordinates":[-3.6751778126,40.4479484558],"type":"Point"}
}