{
  "type": "Feature",
  "properties": {
    "addr:full":"Carrer de Sardenya, 342 Barcelona Barcelona 08025",
    "addr:housenumber":"342",
    "addr:postcode":"08025",
    "addr:street":"Carrer De Sardenya",
    "iso:country":"ES",
    "sg:address":"Carrer de Sardenya, 342",
    "sg:city":"Barcelona",
    "sg:orig_category":"Molduras, Junquillos, Listones Y Molduras Perforadas",
    "sg:phone":"+34 934 55 70 01",
    "sg:postcode":"08025",
    "sg:province":"Barcelona",
    "wof:name":"Lamelas Veigas Manuel Jesus",
    "wof:placetype":"venue"
},
  "geometry": {"coordinates":[2.1719939709,41.4045791626],"type":"Point"}
}