{
  "type": "Feature",
  "properties": {
    "addr:full":"Calle de Gernika, S/n Kurtzea Vizcaya 48960",
    "addr:housenumber":"s / n",
    "addr:postcode":"48960",
    "addr:street":"Calle De Gernika",
    "iso:country":"ES",
    "sg:address":"Calle de Gernika, S/n",
    "sg:city":"Kurtzea",
    "sg:orig_category":"Venta, Montaje De Neum\u00c1ticos",
    "sg:phone":"+34 944 57 02 03",
    "sg:postcode":"48960",
    "sg:province":"Vizcaya",
    "wof:name":"Neumaticos Galdakao S.l.",
    "wof:placetype":"venue"
},
  "geometry": {"coordinates":[-2.8418591022,43.2264060974],"type":"Point"}
}