{
  "type": "Feature",
  "properties": {
    "addr:full":"Avda Baviera, 10 Madrid Madrid 28028",
    "addr:housenumber":"10",
    "addr:postcode":"madrid;28028",
    "addr:street":"Avda Baviera",
    "iso:country":"ES",
    "sg:address":"Avda Baviera, 10",
    "sg:city":"Madrid",
    "sg:orig_category":"Asociaciones Y Clubs Deportivos",
    "sg:phone":"+34 913 56 93 77",
    "sg:postcode":"28028",
    "sg:province":"Madrid",
    "wof:name":"Lois Oltra Isabel",
    "wof:placetype":"venue"
},
  "geometry": {"coordinates":[-3.6631519794,40.4421768188],"type":"Point"}
}