{
  "type": "Feature",
  "properties": {
    "iso:country":"ES",
    "sg:address":"Ctra Granada (de), Km. 0318,0",
    "sg:city":"Castro Rio",
    "sg:orig_category":"Centros De Educaci\u00d3n Especial",
    "sg:phone":"+34 957 33 20 41",
    "sg:postcode":"14840",
    "sg:province":"C\u00f3rdoba",
    "wof:name":"Asociacion Provincial De Padres Y Protectores De Discapacitados In Telectuales(aprosub",
    "wof:placetype":"venue"
},
  "geometry": {"coordinates":[-4.6010651588,37.7613143921],"type":"Point"}
}