{
  "type": "Feature",
  "properties": {
    "iso:country":"ES",
    "sg:address":"Calle de Cabestany, 3",
    "sg:city":"Huesca",
    "sg:orig_category":"Estancos",
    "sg:phone":"+34 974 24 37 67",
    "sg:postcode":"22005",
    "sg:province":"Huesca",
    "wof:name":"Ferrer Usieto Francisco Jose",
    "wof:placetype":"venue"
},
  "geometry": {"coordinates":[-0.40852651,42.1343307495],"type":"Point"}
}