{
  "type": "Feature",
  "properties": {
    "addr:full":"Calle de Pe\u00d1iscola, 7 Castellon Castell\u00f3n 12003",
    "addr:housenumber":"7",
    "addr:postcode":"12003",
    "addr:street":"Calle De Pen\u0303Iscola;Castello\u0301N",
    "iso:country":"ES",
    "sg:address":"Calle de Pe\u00d1iscola, 7",
    "sg:city":"Castellon",
    "sg:orig_category":"Arquitectos",
    "sg:phone":"+34 964 22 74 45",
    "sg:postcode":"12003",
    "sg:province":"Castell\u00f3n",
    "wof:name":"Agost Lopez Miguel Joaquin",
    "wof:placetype":"venue"
},
  "geometry": {"coordinates":[-0.0330942012,39.9864311218],"type":"Point"}
}