{
  "type": "Feature",
  "properties": {
    "addr:full":"Calle de Jose Rufino Olaso, 26 Valle Trapaga Vizcaya 48510",
    "addr:housenumber":"26",
    "addr:postcode":"48510",
    "addr:street":"Calle De Jose Rufino Olaso;Trapaga",
    "iso:country":"ES",
    "sg:address":"Calle de Jose Rufino Olaso, 26",
    "sg:city":"Valle Trapaga",
    "sg:orig_category":"Transportes Por V\u00cdas Navegables",
    "sg:phone":"+34 944 92 12 32",
    "sg:postcode":"48510",
    "sg:province":"Vizcaya",
    "wof:name":"Vazquez Mari\u00f1o Arturo",
    "wof:placetype":"venue"
},
  "geometry": {"coordinates":[-3.0397019386,43.303894043],"type":"Point"}
}