{
  "type": "Feature",
  "properties": {
    "iso:country":"ES",
    "sg:address":"Calle de Martires, 8",
    "sg:city":"Roda",
    "sg:orig_category":"Producci\u00d3n, Venta De Productos De Agricultura Biol\u00d3gica",
    "sg:phone":"+34 967 44 23 94",
    "sg:postcode":"02630",
    "sg:province":"Albacete",
    "wof:name":"S.a.t. Manteleros Numero 9515",
    "wof:placetype":"venue"
},
  "geometry": {"coordinates":[-2.1594998837,39.2061157227],"type":"Point"}
}