{
  "type": "Feature",
  "properties": {
    "addr:full":"Calle de Capitan De Oro, 1 Madrid Madrid 28019",
    "addr:housenumber":"1",
    "addr:postcode":"28019",
    "addr:street":"Calle De Capitan De Oro",
    "iso:country":"ES",
    "sg:address":"Calle de Capitan De Oro, 1",
    "sg:city":"Madrid",
    "sg:orig_category":"Institutos De Belleza",
    "sg:phone":"+34 914 72 43 39",
    "sg:postcode":"28019",
    "sg:province":"Madrid",
    "wof:name":"Eyra Estetica S.l.",
    "wof:placetype":"venue"
},
  "geometry": {"coordinates":[-3.7292563915,40.3898391724],"type":"Point"}
}