{
  "type": "Feature",
  "properties": {
    "addr:full":"Calle de Ravel, 2 Malaga M\u00e1laga 29004",
    "addr:housenumber":"2",
    "addr:postcode":"29004",
    "addr:street":"Calle De Ravel;Ma\u0301Laga",
    "iso:country":"ES",
    "sg:address":"Calle de Ravel, 2",
    "sg:city":"Malaga",
    "sg:orig_category":"Abogados",
    "sg:phone":"+34 952 23 08 49",
    "sg:postcode":"29004",
    "sg:province":"M\u00e1laga",
    "wof:name":"F.b.gabinete Juridico Tributario S.l.",
    "wof:placetype":"venue"
},
  "geometry": {"coordinates":[-4.451458931,36.6946487427],"type":"Point"}
}