{
  "type": "Feature",
  "properties": {
    "addr:full":"Avda La Glorieta, 6 Alberic Valencia 46260",
    "addr:housenumber":"6",
    "addr:postcode":"46260",
    "addr:street":"Avda La Glorieta",
    "iso:country":"ES",
    "sg:address":"Avda La Glorieta, 6",
    "sg:city":"Alberic",
    "sg:orig_category":"Asesor\u00cda Sobre Comunicaci\u00d3n De Empresas",
    "sg:phone":"+34 962 44 12 40",
    "sg:postcode":"46260",
    "sg:province":"Valencia",
    "wof:name":"Asteplade S.l.",
    "wof:placetype":"venue"
},
  "geometry": {"coordinates":[-0.5215473771,39.116973877],"type":"Point"}
}