{
  "type": "Feature",
  "properties": {
    "addr:full":"Juan Ruiz Jimenez, S/n Marbella M\u00e1laga 29600",
    "addr:postcode":"29600",
    "addr:street":"Juan;Jimenez S / N;Ma\u0301Laga",
    "iso:country":"ES",
    "sg:address":"Juan Ruiz Jimenez, S/n",
    "sg:city":"Marbella",
    "sg:orig_category":"Inform\u00c1tica: Material Y Suministros",
    "sg:phone":"+34 952 86 62 15",
    "sg:postcode":"29600",
    "sg:province":"M\u00e1laga",
    "wof:name":"Marbell Computer S.l.",
    "wof:placetype":"venue"
},
  "geometry": {"coordinates":[-4.8892669678,36.5106887817],"type":"Point"}
}