{
  "type": "Feature",
  "properties": {
    "iso:country":"ES",
    "sg:address":"Calle de Feria (la), 5",
    "sg:city":"Adrada",
    "sg:orig_category":"Pescader\u00cdas (al Por Menor)",
    "sg:phone":"+34 918 67 00 65",
    "sg:postcode":"05430",
    "sg:province":"\u00c1vila",
    "wof:name":"Rio Martin Maximo Del",
    "wof:placetype":"venue"
},
  "geometry": {"coordinates":[-4.638753891,40.3024139404],"type":"Point"}
}