{
  "type": "Feature",
  "properties": {
    "addr:full":"Avda Primero De Mayo, 112 Coria Rio Sevilla 41100",
    "addr:housenumber":"112",
    "addr:postcode":"41100",
    "addr:street":"Avda Primero De Mayo;Rio Sevilla",
    "iso:country":"ES",
    "sg:address":"Avda Primero De Mayo, 112",
    "sg:city":"Coria Rio",
    "sg:orig_category":"Financiaci\u00d3n Y Cr\u00c9ditos",
    "sg:phone":"+34 954 77 29 06",
    "sg:postcode":"41100",
    "sg:province":"Sevilla",
    "wof:name":"Meridional De Intermediacion, S. L.",
    "wof:placetype":"venue"
},
  "geometry": {"coordinates":[-6.0520391464,37.2930107117],"type":"Point"}
}