{
  "type": "Feature",
  "properties": {
    "iso:country":"ES",
    "sg:address":"Cno. Sevilleja, S/n",
    "sg:city":"Bailen",
    "sg:orig_category":"Alfarer\u00cda",
    "sg:phone":"+34 953 67 50 28",
    "sg:postcode":"23710",
    "sg:province":"Ja\u00e9n",
    "wof:name":"Cozar Martinez Miguel",
    "wof:placetype":"venue"
},
  "geometry": {"coordinates":[-3.7710540295,38.0965309143],"type":"Point"}
}