{
  "type": "Feature",
  "properties": {
    "addr:full":"Calle de Nu\u00d1ez De Balboa, 95 Madrid Madrid 28006",
    "addr:housenumber":"95",
    "addr:postcode":"madrid;28006",
    "addr:street":"Calle De Nun\u0303Ez De Balboa",
    "iso:country":"ES",
    "sg:address":"Calle de Nu\u00d1ez De Balboa, 95",
    "sg:city":"Madrid",
    "sg:orig_category":"Ropa Para Ni\u00d1os (al Por Menor)",
    "sg:phone":"+34 915 75 98 14",
    "sg:postcode":"28006",
    "sg:province":"Madrid",
    "wof:name":"Cashmere Y Seda Company S.l.",
    "wof:placetype":"venue"
},
  "geometry": {"coordinates":[-3.6821761131,40.4345283508],"type":"Point"}
}