{
  "type": "Feature",
  "properties": {
    "iso:country":"ES",
    "sg:address":"Cjo. Poloria, S/n",
    "sg:city":"Dehesas Viejas",
    "sg:orig_category":"Aceites Y Grasas Alimentarias (fabricaci\u00d3n, Al Por Mayor)",
    "sg:phone":"+34 958 38 53 06",
    "sg:postcode":"18567",
    "sg:province":"Granada",
    "wof:name":"Cooperativa Nuestra Se\u00f1ora De Los Dolores",
    "wof:placetype":"venue"
},
  "geometry": {"coordinates":[-3.5081889629,37.495880127],"type":"Point"}
}