{
  "type": "Feature",
  "properties": {
    "iso:country":"ES",
    "sg:address":"Calle de Aldaya, 18",
    "sg:city":"Barrio Orba",
    "sg:orig_category":"Molduras, Junquillos, Listones Y Molduras Perforadas",
    "sg:phone":"+34 963 76 24 27",
    "sg:postcode":"46910",
    "sg:province":"Valencia",
    "wof:name":"Cercos Garcia Emiliano",
    "wof:placetype":"venue"
},
  "geometry": {"coordinates":[-0.063861303,38.7803611755],"type":"Point"}
}