{
  "type": "Feature",
  "properties": {
    "addr:full":"Calle de Baja(quinzano), Km. 0232,0 Quinzano Huesca 22810",
    "addr:postcode":"22810",
    "addr:street":"Calle De Baja Quinzano Km. 0232,0",
    "iso:country":"ES",
    "sg:address":"Calle de Baja(quinzano), Km. 0232,0",
    "sg:city":"Quinzano",
    "sg:orig_category":"Agricultura: Abastecimiento Y Cosechado (negocio)",
    "sg:phone":"+34 974 27 04 96",
    "sg:postcode":"22810",
    "sg:province":"Huesca",
    "wof:name":"Gimenez De Azcarate Mu\u00f1oz-cobo Diego",
    "wof:placetype":"venue"
},
  "geometry": {"coordinates":[-0.6036288738,42.2471351624],"type":"Point"}
}