{
  "type": "Feature",
  "properties": {
    "iso:country":"ES",
    "sg:address":"Calle de Santa Justa, 5",
    "sg:city":"Orihuela",
    "sg:orig_category":"Procuradores",
    "sg:phone":"+34 966 74 38 08",
    "sg:postcode":"03300",
    "sg:province":"Alicante",
    "wof:name":"Amoros Lorente Ramon",
    "wof:placetype":"venue"
},
  "geometry": {"coordinates":[-0.9494323134,38.0854759216],"type":"Point"}
}