{
  "type": "Feature",
  "properties": {
    "addr:full":"Carrer de Major, 17 Altafulla Tarragona 43893",
    "addr:housenumber":"17",
    "addr:postcode":"43893",
    "addr:street":"Carrer De Major",
    "iso:country":"ES",
    "sg:address":"Carrer de Major, 17",
    "sg:city":"Altafulla",
    "sg:orig_category":"Peluqueros: De Se\u00d1oras",
    "sg:phone":"+34 977 65 25 31",
    "sg:postcode":"43893",
    "sg:province":"Tarragona",
    "wof:name":"Gonzalez Garcia Rosa",
    "wof:placetype":"venue"
},
  "geometry": {"coordinates":[1.3764499426,41.1428337097],"type":"Point"}
}