{
  "type": "Feature",
  "properties": {
    "addr:full":"Via Laietana, 9 Barcelona Barcelona 08003",
    "addr:housenumber":"9",
    "addr:postcode":"08003",
    "addr:street":"Via Laietana",
    "iso:country":"ES",
    "sg:address":"Via Laietana, 9",
    "sg:city":"Barcelona",
    "sg:orig_category":"Deportes Diversos",
    "sg:phone":"+34 932 68 23 07",
    "sg:postcode":"08003",
    "sg:province":"Barcelona",
    "wof:name":"Federacio Catalana De Ca\u00e7a",
    "wof:placetype":"venue"
},
  "geometry": {"coordinates":[2.1802101135,41.3826599121],"type":"Point"}
}