{
  "type": "Feature",
  "properties": {
    "iso:country":"ES",
    "sg:address":"Calle de Roque Morera, 2",
    "sg:city":"Palmas De Gran Canaria",
    "sg:orig_category":"M\u00c9dicos: Estomatolog\u00cda",
    "sg:phone":"+34 928 31 03 54",
    "sg:postcode":"35001",
    "sg:province":"Las Palmas",
    "wof:name":"Diaz-saavedra De Morales Jose",
    "wof:placetype":"venue"
},
  "geometry": {"coordinates":[-15.4122695923,28.1012306213],"type":"Point"}
}