{
  "type": "Feature",
  "properties": {
    "addr:full":"Calle de Viriato, 41 Madrid Madrid 28010",
    "addr:housenumber":"41",
    "addr:postcode":"madrid;28010",
    "addr:street":"Calle De Viriato",
    "iso:country":"ES",
    "sg:address":"Calle de Viriato, 41",
    "sg:city":"Madrid",
    "sg:orig_category":"Gastronom\u00cda: Especialidades Regionales Y Extranjeras (producci\u00d3n, Al Por Mayor)",
    "sg:phone":"+34 915 91 01 42",
    "sg:postcode":"28010",
    "sg:province":"Madrid",
    "wof:name":"Mercedes Flores Blanca",
    "wof:placetype":"venue"
},
  "geometry": {"coordinates":[-3.6995167732,40.4358100891],"type":"Point"}
}