{
  "type": "Feature",
  "properties": {
    "addr:full":"Calle de Zuberoa, 3 Galdakao Vizcaya 48960",
    "addr:housenumber":"3",
    "addr:postcode":"48960",
    "addr:street":"Calle De Zuberoa",
    "iso:country":"ES",
    "sg:address":"Calle de Zuberoa, 3",
    "sg:city":"Galdakao",
    "sg:orig_category":"Empresas De Carpinter\u00cda Met\u00c1lica",
    "sg:phone":"+34 944 56 55 28",
    "sg:postcode":"48960",
    "sg:province":"Vizcaya",
    "wof:name":"Maria Isabel Rojo (carpinteria  Metalica Galex)",
    "wof:placetype":"venue"
},
  "geometry": {"coordinates":[-2.8463408947,43.2301979065],"type":"Point"}
}