{
  "type": "Feature",
  "properties": {
    "addr:full":"Calle de Oca, 31 Madrid Madrid 28025",
    "addr:housenumber":"31",
    "addr:postcode":"madrid;28025",
    "addr:street":"Calle De Oca",
    "iso:country":"ES",
    "sg:address":"Calle de Oca, 31",
    "sg:city":"Madrid",
    "sg:orig_category":"Negocio De Madera",
    "sg:phone":"+34 914 61 15 12",
    "sg:postcode":"28025",
    "sg:province":"Madrid",
    "wof:name":"Alba Robles Vicente",
    "wof:placetype":"venue"
},
  "geometry": {"coordinates":[-3.7362689972,40.3895225525],"type":"Point"}
}