{
  "type": "Feature",
  "properties": {
    "iso:country":"ES",
    "sg:address":"Carr Antoni Sole, 18",
    "sg:city":"Lleida",
    "sg:orig_category":"Molduras, Junquillos, Listones Y Molduras Perforadas",
    "sg:phone":"+34 973 21 24 90",
    "sg:postcode":"25001",
    "sg:province":"Lleida",
    "wof:name":"Lopez Gil Alberto",
    "wof:placetype":"venue"
},
  "geometry": {"coordinates":[0.6445990205,41.6020126343],"type":"Point"}
}