{
  "type": "Feature",
  "properties": {
    "addr:full":"Plaz Paz (la), 6 Vall D'uixo Castell\u00f3n 12600",
    "addr:postcode":"12600",
    "addr:street":"Plaz;La 6",
    "iso:country":"ES",
    "sg:address":"Plaz Paz (la), 6",
    "sg:city":"Vall D'uixo",
    "sg:orig_category":"Ropa Para Se\u00d1oras (al Por Menor)",
    "sg:phone":"+34 964 66 00 44",
    "sg:postcode":"12600",
    "sg:province":"Castell\u00f3n",
    "wof:name":"Petit Llevant S.l.",
    "wof:placetype":"venue"
},
  "geometry": {"coordinates":[-0.0377339981,39.9835891724],"type":"Point"}
}