{
  "type": "Feature",
  "properties": {
    "iso:country":"ES",
    "sg:address":"La Juncal, 19",
    "sg:city":"Villaquilambre",
    "sg:orig_category":"Reposter\u00cdas",
    "sg:phone":"+34 987 28 31 88",
    "sg:postcode":"24008",
    "sg:province":"Le\u00f3n",
    "wof:name":"Morente Cobo Antonio",
    "wof:placetype":"venue"
},
  "geometry": {"coordinates":[-5.5566468239,42.6441726685],"type":"Point"}
}