{
  "type": "Feature",
  "properties": {
    "iso:country":"ES",
    "sg:address":"Calle de Xuquer, 72",
    "sg:city":"Alzira",
    "sg:orig_category":"Comercio, Reparaci\u00d3n De Motocicletas, Bicicletas Y Piezas Sueltas",
    "sg:phone":"+34 962 41 20 32",
    "sg:postcode":"46600",
    "sg:province":"Valencia",
    "wof:name":"Sanchis Fenollosa Salvador",
    "wof:placetype":"venue"
},
  "geometry": {"coordinates":[-0.4373089969,39.1540107727],"type":"Point"}
}