{
  "type": "Feature",
  "properties": {
    "addr:full":"Plaz Mercado, S/n Ledesma Salamanca 37100",
    "addr:housenumber":"/ n",
    "addr:postcode":"37100",
    "addr:street":"S",
    "iso:country":"ES",
    "sg:address":"Plaz Mercado, S/n",
    "sg:city":"Ledesma",
    "sg:orig_category":"Sanatorios M\u00c9dico",
    "sg:phone":"+34 923 57 00 29",
    "sg:postcode":"37100",
    "sg:province":"Salamanca",
    "wof:name":"Gerencia Atencion Primaria Salamanca",
    "wof:placetype":"venue"
},
  "geometry": {"coordinates":[-6.0018901825,41.0871772766],"type":"Point"}
}