{
  "type": "Feature",
  "properties": {
    "addr:full":"Lagunillas, S/n Madro\u00f1era C\u00e1ceres 10210",
    "addr:housenumber":"s / n",
    "addr:postcode":"10210",
    "addr:street":"Lagunillas;Ca\u0301Ceres",
    "iso:country":"ES",
    "sg:address":"Lagunillas, S/n",
    "sg:city":"Madro\u00f1era",
    "sg:orig_category":"Mec\u00c1nico Del Autom\u00d3vil",
    "sg:phone":"+34 927 33 41 87",
    "sg:postcode":"10210",
    "sg:province":"C\u00e1ceres",
    "wof:name":"Jimenez Gonzalez Mario",
    "wof:placetype":"venue"
},
  "geometry": {"coordinates":[-5.7559142113,39.4252433777],"type":"Point"}
}