{
  "type": "Feature",
  "properties": {
    "addr:full":"Calle de Pinar, 4 Blanca Murcia 30540",
    "addr:housenumber":"4",
    "addr:postcode":"30540",
    "addr:street":"Calle De Pinar",
    "iso:country":"ES",
    "sg:address":"Calle de Pinar, 4",
    "sg:city":"Blanca",
    "sg:orig_category":"Contenedores (mercanc\u00cdas)",
    "sg:phone":"+34 968 45 93 05",
    "sg:postcode":"30540",
    "sg:province":"Murcia",
    "wof:name":"Perez Bastida Antonio",
    "wof:placetype":"venue"
},
  "geometry": {"coordinates":[-1.3739680052,38.1806411743],"type":"Point"}
}