{
  "type": "Feature",
  "properties": {
    "addr:full":"Carrer de Cristofor Colom, 30 Tarragona Tarragona 43001",
    "addr:housenumber":"30",
    "addr:postcode":"43001",
    "addr:street":"Carrer De Cristofor Colom",
    "iso:country":"ES",
    "sg:address":"Carrer de Cristofor Colom, 30",
    "sg:city":"Tarragona",
    "sg:orig_category":"Alimentaci\u00d3n General (al Por Menor)",
    "sg:phone":"+34 977 24 00 65",
    "sg:postcode":"43001",
    "sg:province":"Tarragona",
    "wof:name":"Mercade Boquera Maria Dolores",
    "wof:placetype":"venue"
},
  "geometry": {"coordinates":[1.2475670576,41.1150550842],"type":"Point"}
}