{
  "type": "Feature",
  "properties": {
    "iso:country":"ES",
    "sg:address":"Avda Cortes Valencianas, 28",
    "sg:city":"Torrevieja",
    "sg:orig_category":"Empresarios",
    "sg:phone":"+34 965 71 88 99",
    "sg:postcode":"03180",
    "sg:province":"Alicante",
    "wof:name":"Multiservicio Eurocol S.l.",
    "wof:placetype":"venue"
},
  "geometry": {"coordinates":[-0.6723889709,37.9968681335],"type":"Point"}
}