{
  "type": "Feature",
  "properties": {
    "addr:full":"Calle de Maria Antonia Jesus Tirado, S/n Jerez De La Frontera C\u00e1diz 11401",
    "addr:housenumber":"s / n",
    "addr:postcode":"11401",
    "addr:street":"Calle De Maria Antonia Jesus Tirado",
    "iso:country":"ES",
    "sg:address":"Calle de Maria Antonia Jesus Tirado, S/n",
    "sg:city":"Jerez De La Frontera",
    "sg:orig_category":"Caf\u00c9s, Bares, Cervecer\u00cdas",
    "sg:phone":"+34 956 33 98 10",
    "sg:postcode":"11401",
    "sg:province":"C\u00e1diz",
    "wof:name":"Tecnirest Sociedad Limitada",
    "wof:placetype":"venue"
},
  "geometry": {"coordinates":[-6.1301121712,36.6828346252],"type":"Point"}
}