{
  "type": "Feature",
  "properties": {
    "iso:country":"ES",
    "sg:address":"Carr Marques De La Romana, 3",
    "sg:city":"Faro",
    "sg:orig_category":"Supermercados Y Hipermercados",
    "sg:phone":"+34 961 74 68 99",
    "sg:postcode":"46408",
    "sg:province":"Valencia",
    "wof:name":"Herrero Lozano Pedro Ramos",
    "wof:placetype":"venue"
},
  "geometry": {"coordinates":[-0.2200289965,39.1826400757],"type":"Point"}
}