{
  "type": "Feature",
  "properties": {
    "iso:country":"ES",
    "sg:address":"Praz Maior, 41",
    "sg:city":"Ponteareas",
    "sg:orig_category":"Panader\u00cdas, Panader\u00cdas",
    "sg:phone":"+34 986 64 00 98",
    "sg:postcode":"36860",
    "sg:province":"Pontevedra",
    "wof:name":"Confiteria Dinguilindin C.b.",
    "wof:placetype":"venue"
},
  "geometry": {"coordinates":[-8.5163888931,42.1783599854],"type":"Point"}
}