{
  "type": "Feature",
  "properties": {
    "iso:country":"ES",
    "sg:address":"Calle de Santa Ana, 1",
    "sg:city":"Etxebarri",
    "sg:orig_category":"Electrodom\u00c9sticos (al Por Menor)",
    "sg:phone":"+34 944 40 90 53",
    "sg:postcode":"48450",
    "sg:province":"Vizcaya",
    "wof:name":"Muebles Y Electrodomesticos Zal, S.l.",
    "wof:placetype":"venue"
},
  "geometry": {"coordinates":[-2.8912250996,43.2456588745],"type":"Point"}
}