{
  "type": "Feature",
  "properties": {
    "addr:full":"Plaz Espa\u00d1a, S/n Casas Monte C\u00e1ceres 10730",
    "addr:housenumber":"s",
    "addr:postcode":"10730",
    "addr:street":"Plaz Espan\u0303A;/ N Casas Monte Ca\u0301Ceres",
    "iso:country":"ES",
    "sg:address":"Plaz Espa\u00d1a, S/n",
    "sg:city":"Casas Monte",
    "sg:orig_category":"Administraciones Regionales, Departamentales Y Locales",
    "sg:phone":"+34 927 17 90 23",
    "sg:postcode":"10730",
    "sg:province":"C\u00e1ceres",
    "wof:name":"Ayuntamiento De Casas Del Monte",
    "wof:placetype":"venue"
},
  "geometry": {"coordinates":[-5.9633669853,40.2041282654],"type":"Point"}
}