{
  "type": "Feature",
  "properties": {
    "addr:full":"Calle de Eusebio Villalvilla, 27 Arganda Madrid 28500",
    "addr:housenumber":"27",
    "addr:postcode":"28500",
    "addr:street":"Calle De Eusebio Villalvilla",
    "iso:country":"ES",
    "sg:address":"Calle de Eusebio Villalvilla, 27",
    "sg:city":"Arganda",
    "sg:orig_category":"Electricidad: Instaladores",
    "sg:phone":"+34 918 71 49 09",
    "sg:postcode":"28500",
    "sg:province":"Madrid",
    "wof:name":"Aguilar De La Torre Joaquin",
    "wof:placetype":"venue"
},
  "geometry": {"coordinates":[-3.4374344349,40.2991981506],"type":"Point"}
}