{
  "type": "Feature",
  "properties": {
    "addr:full":"Marzaniella, 49 Trasona Asturias 33468",
    "addr:housenumber":"49",
    "addr:postcode":"33468",
    "addr:street":"Marzaniella",
    "iso:country":"ES",
    "sg:address":"Marzaniella, 49",
    "sg:city":"Trasona",
    "sg:orig_category":"Electricidad Veh\u00cdculo",
    "sg:phone":"+34 985 57 57 66",
    "sg:postcode":"33468",
    "sg:province":"Asturias",
    "wof:name":"Taller Electrico Feyva S.l.",
    "wof:placetype":"venue"
},
  "geometry": {"coordinates":[-5.8703289032,43.563129425],"type":"Point"}
}