{
  "type": "Feature",
  "properties": {
    "iso:country":"ES",
    "sg:address":"Carrer de Rubi, 7",
    "sg:city":"Palma",
    "sg:orig_category":"Abogados",
    "sg:phone":"+34 971 71 51 85",
    "sg:postcode":"07002",
    "sg:province":"Islas Baleares",
    "wof:name":"Coll Fluxa Bernardo Javier",
    "wof:placetype":"venue"
},
  "geometry": {"coordinates":[2.6524159908,39.5712432861],"type":"Point"}
}