{
  "type": "Feature",
  "properties": {
    "addr:full":"Av Salvador Allende, 37 Cornella Llobregat Barcelona 08940",
    "addr:housenumber":"37",
    "addr:postcode":"08940",
    "addr:street":"Av Salvador Allende",
    "iso:country":"ES",
    "sg:address":"Av Salvador Allende, 37",
    "sg:city":"Cornella Llobregat",
    "sg:orig_category":"Bisuter\u00cda, Joyer\u00cda, Relojer\u00cda (al Por Menor)",
    "sg:phone":"+34 934 71 18 94",
    "sg:postcode":"08940",
    "sg:province":"Barcelona",
    "wof:name":"Avila Lancharro Joyeros S.l.",
    "wof:placetype":"venue"
},
  "geometry": {"coordinates":[2.0791759491,41.3580970764],"type":"Point"}
}