{
  "type": "Feature",
  "properties": {
    "addr:full":"Avda Hontanilla (de La), 16 Hinojosos Cuenca 16417",
    "addr:housenumber":"16",
    "addr:postcode":"16417",
    "addr:street":"Avda Hontanilla De La",
    "iso:country":"ES",
    "sg:address":"Avda Hontanilla (de La), 16",
    "sg:city":"Hinojosos",
    "sg:orig_category":"Venta Al Preg\u00d3n",
    "sg:phone":"+34 969 12 94 88",
    "sg:postcode":"16417",
    "sg:province":"Cuenca",
    "wof:name":"Sanz Garcia Jesus",
    "wof:placetype":"venue"
},
  "geometry": {"coordinates":[-2.8283560276,39.6049461365],"type":"Point"}
}