{
  "type": "Feature",
  "properties": {
    "iso:country":"ES",
    "sg:address":"Pl Portal (del), 1",
    "sg:city":"Alcover",
    "sg:orig_category":"Cajas De Ahorro",
    "sg:phone":"+34 977 84 62 44",
    "sg:postcode":"43460",
    "sg:province":"Tarragona",
    "sg:website":"www.caixatarragona.es",
    "wof:name":"Caixa D'estalvis De Tarragona",
    "wof:placetype":"venue"
},
  "geometry": {"coordinates":[1.1944639683,41.2955131531],"type":"Point"}
}