{
  "type": "Feature",
  "properties": {
    "addr:full":"Calle de Sanchez Robledo, 6 Yebenes Toledo 45470",
    "addr:housenumber":"6",
    "addr:postcode":"45470",
    "addr:street":"Calle De Sanchez Robledo",
    "iso:country":"ES",
    "sg:address":"Calle de Sanchez Robledo, 6",
    "sg:city":"Yebenes",
    "sg:orig_category":"Bebidas",
    "sg:phone":"+34 925 34 82 51",
    "sg:postcode":"45470",
    "sg:province":"Toledo",
    "wof:name":"Moreno Calvo Jose Antonio",
    "wof:placetype":"venue"
},
  "geometry": {"coordinates":[-3.8664910793,39.5825614929],"type":"Point"}
}