{
  "type": "Feature",
  "properties": {
    "iso:country":"ES",
    "sg:address":"Urb Lances (los), S/n",
    "sg:city":"Tarifa",
    "sg:orig_category":"Piscinas, Accesorios, Suministros (fabricaci\u00d3n, Al Por Mayor)",
    "sg:phone":"+34 956 68 07 44",
    "sg:postcode":"11380",
    "sg:province":"C\u00e1diz",
    "wof:name":"Urbanizadora Tarife\u00d1a S.a.",
    "wof:placetype":"venue"
},
  "geometry": {"coordinates":[-5.6137690544,36.0219268799],"type":"Point"}
}