{
  "type": "Feature",
  "properties": {
    "iso:country":"ES",
    "sg:address":"Avda Fermina Sevillano, 3",
    "sg:city":"Madrid",
    "sg:orig_category":"Oficinas: Suministros Para (fabricaci\u00d3n, Al Por Mayor)",
    "sg:phone":"+34 913 29 44 47",
    "sg:postcode":"28022",
    "sg:province":"Madrid",
    "wof:name":"Retoner S.l.",
    "wof:placetype":"venue"
},
  "geometry": {"coordinates":[-3.5657880306,40.4468841553],"type":"Point"}
}