{
  "type": "Feature",
  "properties": {
    "iso:country":"ES",
    "sg:address":"Rond Firal, 11",
    "sg:city":"Figueres",
    "sg:orig_category":"Agentes, Concesionarios Y Sucursales De Veh\u00cdculos",
    "sg:phone":"+34 972 50 96 81",
    "sg:postcode":"17600",
    "sg:province":"Girona",
    "wof:name":"Auto Canigo S.a.",
    "wof:placetype":"venue"
},
  "geometry": {"coordinates":[2.9625587463,42.2720336914],"type":"Point"}
}