{
  "type": "Feature",
  "properties": {
    "iso:country":"ES",
    "sg:address":"Se\u00f1orio De Amocain, 2",
    "sg:city":"Iru\u00f1a",
    "sg:orig_category":"Lencer\u00cda Femenina, Corseter\u00cda, Trajes De Ba\u00d1o (al Por Menor)",
    "sg:phone":"+34 948 16 38 86",
    "sg:postcode":"31016",
    "sg:province":"Navarra",
    "wof:name":"Martinez Villanueva Sofia",
    "wof:placetype":"venue"
},
  "geometry": {"coordinates":[-1.6134259701,42.8135452271],"type":"Point"}
}