{
  "type": "Feature",
  "properties": {
    "iso:country":"ES",
    "sg:address":"Calle de Santa Rosa, 9",
    "sg:city":"Sevilla",
    "sg:orig_category":"Agencias Y Agentes Comerciales, Representantes",
    "sg:phone":"+34 954 23 46 74",
    "sg:postcode":"41013",
    "sg:province":"Sevilla",
    "wof:name":"Radial De Comercio Y Representaciones S.l.",
    "wof:placetype":"venue"
},
  "geometry": {"coordinates":[-5.9838218689,37.3732757568],"type":"Point"}
}