{
  "type": "Feature",
  "properties": {
    "addr:full":"Calle de Galoponte, 14 Medano Santa Cruz De Tenerife 38612",
    "addr:housenumber":"14",
    "addr:postcode":"38612",
    "addr:street":"Calle De Galoponte",
    "iso:country":"ES",
    "sg:address":"Calle de Galoponte, 14",
    "sg:city":"Medano",
    "sg:orig_category":"Promotores Constructores",
    "sg:phone":"+34 922 17 82 22",
    "sg:postcode":"38612",
    "sg:province":"Santa Cruz De Tenerife",
    "wof:name":"Promotora Valenciana Tinerfe\u00f1a Valtin S.l.",
    "wof:placetype":"venue"
},
  "geometry": {"coordinates":[-16.5262241364,28.0532035828],"type":"Point"}
}