{
  "type": "Feature",
  "properties": {
    "addr:full":"Calle de Benahoare, 34 Santa Cruz De Tenerife Santa Cruz De Tenerife 38008",
    "addr:housenumber":"34",
    "addr:postcode":"38008",
    "addr:street":"Calle De Benahoare",
    "iso:country":"ES",
    "sg:address":"Calle de Benahoare, 34",
    "sg:city":"Santa Cruz De Tenerife",
    "sg:orig_category":"Ropa Para Se\u00d1oras Y Caballeros (al Por Menor)",
    "sg:phone":"+34 922 21 80 18",
    "sg:postcode":"38008",
    "sg:province":"Santa Cruz De Tenerife",
    "wof:name":"Rivero Rodriguez Jesus Domingo",
    "wof:placetype":"venue"
},
  "geometry": {"coordinates":[-16.2712345123,28.470369339],"type":"Point"}
}