{
  "type": "Feature",
  "properties": {
    "addr:full":"Carrer de Moja, Km. 0000,9 Vilafranca Penedes Barcelona 08720",
    "addr:postcode":"08720",
    "addr:street":"Carrer De Moja Km. 0000,9 Vilafranca;Barcelona",
    "iso:country":"ES",
    "sg:address":"Carrer de Moja, Km. 0000,9",
    "sg:city":"Vilafranca Penedes",
    "sg:orig_category":"Maquinaria Para Industrias Diversas",
    "sg:phone":"+34 938 90 05 06",
    "sg:postcode":"08720",
    "sg:province":"Barcelona",
    "wof:name":"Tallers Bevi S.l",
    "wof:placetype":"venue"
},
  "geometry": {"coordinates":[1.6992199421,41.3447799683],"type":"Point"}
}