{
  "type": "Feature",
  "properties": {
    "addr:full":"Avda Huelva, 42 Aracena Huelva 21200",
    "addr:housenumber":"42",
    "addr:postcode":"21200",
    "addr:street":"Avda Huelva",
    "iso:country":"ES",
    "sg:address":"Avda Huelva, 42",
    "sg:city":"Aracena",
    "sg:orig_category":"Tapones Y Art\u00cdculos De Corcho",
    "sg:phone":"+34 959 12 70 28",
    "sg:postcode":"21200",
    "sg:province":"Huelva",
    "wof:name":"Carrion Martin Jesus Moises",
    "wof:placetype":"venue"
},
  "geometry": {"coordinates":[-6.564904213,37.8924026489],"type":"Point"}
}