{
  "type": "Feature",
  "properties": {
    "addr:full":"Calle de Alemania, 6 Valencia Valencia 46010",
    "addr:housenumber":"6",
    "addr:postcode":"46010",
    "addr:street":"Calle De Alemania",
    "iso:country":"ES",
    "sg:address":"Calle de Alemania, 6",
    "sg:city":"Valencia",
    "sg:orig_category":"Ropa Para Beb\u00c9s Y Ni\u00d1os (confecci\u00d3n, Al Por Mayor)",
    "sg:phone":"+34 963 60 34 37",
    "sg:postcode":"46010",
    "sg:province":"Valencia",
    "wof:name":"Furio Sirera Cristina",
    "wof:placetype":"venue"
},
  "geometry": {"coordinates":[-0.3617542088,39.4813270569],"type":"Point"}
}