{
  "type": "Feature",
  "properties": {
    "addr:full":"Carrer de Sant Quinti, 104 Barcelona Barcelona 08041",
    "addr:housenumber":"104",
    "addr:postcode":"08041",
    "addr:street":"Carrer De Sant Quinti",
    "iso:country":"ES",
    "sg:address":"Carrer de Sant Quinti, 104",
    "sg:city":"Barcelona",
    "sg:orig_category":"Confecci\u00d3n De Trajes Para Se\u00d1oras",
    "sg:phone":"+34 934 35 64 19",
    "sg:postcode":"08041",
    "sg:province":"Barcelona",
    "wof:name":"Audellar S.l.",
    "wof:placetype":"venue"
},
  "geometry": {"coordinates":[2.1756110191,41.4155235291],"type":"Point"}
}