{
  "type": "Feature",
  "properties": {
    "addr:full":"Calle de Serrano, 52 Madrid Madrid 28001",
    "addr:housenumber":"52",
    "addr:postcode":"madrid;28001",
    "addr:street":"Calle De Serrano",
    "iso:country":"ES",
    "sg:address":"Calle de Serrano, 52",
    "sg:city":"Madrid",
    "sg:orig_category":"Librer\u00cdas",
    "sg:phone":"+34 915 76 45 01",
    "sg:postcode":"28001",
    "sg:province":"Madrid",
    "wof:name":"Pastor Garcia Jose Andres",
    "wof:placetype":"venue"
},
  "geometry": {"coordinates":[-3.6872410774,40.4276123047],"type":"Point"}
}