{
  "type": "Feature",
  "properties": {
    "addr:full":"Esteban Lasa Kalea, 1 Beasain Guip\u00f9zcoa 20200",
    "addr:housenumber":"1",
    "addr:postcode":"20200",
    "addr:street":"Esteban Lasa Kalea;Guipu\u0300Zcoa",
    "iso:country":"ES",
    "sg:address":"Esteban Lasa Kalea, 1",
    "sg:city":"Beasain",
    "sg:orig_category":"Revestimientos Industriales",
    "sg:phone":"+34 943 88 59 24",
    "sg:postcode":"20200",
    "sg:province":"Guip\u00f9zcoa",
    "wof:name":"Toural Otero Rafael",
    "wof:placetype":"venue"
},
  "geometry": {"coordinates":[-2.1964581013,43.0476951599],"type":"Point"}
}