{
  "type": "Feature",
  "properties": {
    "iso:country":"ES",
    "sg:address":"Balneario Fuente En Segures, S/n",
    "sg:city":"Balneario",
    "sg:orig_category":"Molduras, Junquillos, Listones Y Molduras Perforadas",
    "sg:phone":"+34 964 43 11 91",
    "sg:postcode":"12160",
    "sg:province":"Castell\u00f3n",
    "wof:name":"Belles Badal Manuel",
    "wof:placetype":"venue"
},
  "geometry": {"coordinates":[-0.1405189931,40.3801345825],"type":"Point"}
}