{
  "type": "Feature",
  "properties": {
    "iso:country":"ES",
    "sg:address":"Avda Juan Carlos I, S/n",
    "sg:city":"Cristianos",
    "sg:orig_category":"Servicios De Telecomunicaciones",
    "sg:phone":"+34 922 78 71 11",
    "sg:postcode":"38650",
    "sg:province":"Santa Cruz De Tenerife",
    "wof:name":"Dial Direct Telecom S.l.",
    "wof:placetype":"venue"
},
  "geometry": {"coordinates":[-16.7118148804,28.0564250946],"type":"Point"}
}