{
  "type": "Feature",
  "properties": {
    "iso:country":"ES",
    "sg:address":"Calle de Mayor, 1",
    "sg:city":"Jaca",
    "sg:orig_category":"Bancos",
    "sg:phone":"+34 974 36 00 94",
    "sg:postcode":"22700",
    "sg:province":"Huesca",
    "sg:website":"www.gruposantander.es",
    "wof:name":"Bt Espa\u00d1a Compa\u00d1ia De Servicios Globales De Telecomunicaciones S.a.u.",
    "wof:placetype":"venue"
},
  "geometry": {"coordinates":[-0.5500190258,42.5693321228],"type":"Point"}
}