{
  "type": "Feature",
  "properties": {
    "addr:full":"Calle de Gordillo, 44 Palmas De Gran Canaria Las Palmas 35009",
    "addr:housenumber":"44",
    "addr:postcode":"35009",
    "addr:street":"Calle De Gordillo",
    "iso:country":"ES",
    "sg:address":"Calle de Gordillo, 44",
    "sg:city":"Palmas De Gran Canaria",
    "sg:orig_category":"Alimentaci\u00d3n General (al Por Menor)",
    "sg:phone":"+34 928 46 11 98",
    "sg:postcode":"35009",
    "sg:province":"Las Palmas",
    "wof:name":"Garcia Castellano Jose",
    "wof:placetype":"venue"
},
  "geometry": {"coordinates":[-15.4265556335,28.1511688232],"type":"Point"}
}