{
  "type": "Feature",
  "properties": {
    "addr:full":"Plaz General Llopis, 1 Dolores Alicante 03150",
    "addr:housenumber":"1",
    "addr:postcode":"03150",
    "addr:street":"Llopis",
    "iso:country":"ES",
    "sg:address":"Plaz General Llopis, 1",
    "sg:city":"Dolores",
    "sg:orig_category":"Administraciones Regionales, Departamentales Y Locales",
    "sg:phone":"+34 966 71 11 09",
    "sg:postcode":"03150",
    "sg:province":"Alicante",
    "sg:website":"www.aytodolores.es",
    "wof:name":"Ayuntamiento De Dolores",
    "wof:placetype":"venue"
},
  "geometry": {"coordinates":[-0.7700796723,38.1386108398],"type":"Point"}
}