{
  "type": "Feature",
  "properties": {
    "iso:country":"ES",
    "sg:address":"Calle de Industria La, 7",
    "sg:city":"Langreo",
    "sg:orig_category":"Bazares, Art\u00cdculos De Limpieza Y De Cocina (al Por Menor)",
    "sg:phone":"+34 985 69 42 46",
    "sg:postcode":"33900",
    "sg:province":"Asturias",
    "wof:name":"Gonzalez Menendez Manuel",
    "wof:placetype":"venue"
},
  "geometry": {"coordinates":[-5.6692090034,43.2883987427],"type":"Point"}
}