{
  "type": "Feature",
  "properties": {
    "iso:country":"ES",
    "sg:address":"Calle de Borox, 2",
    "sg:city":"Esquivias",
    "sg:orig_category":"Fabrica De Cer\u00c1micas",
    "sg:phone":"+34 925 52 00 50",
    "sg:postcode":"45221",
    "sg:province":"Toledo",
    "wof:name":"Diaz Olivares Lopez S.l.",
    "wof:placetype":"venue"
},
  "geometry": {"coordinates":[-3.7645492554,40.1023750305],"type":"Point"}
}