{
  "type": "Feature",
  "properties": {
    "iso:country":"ES",
    "sg:address":"Calle de Marroquina, 55",
    "sg:city":"Madrid",
    "sg:orig_category":"Poller\u00cda Y Caza (al Por Menor)",
    "sg:phone":"+34 914 39 47 04",
    "sg:postcode":"28030",
    "sg:province":"Madrid",
    "wof:name":"Briones Domingo Zacarias",
    "wof:placetype":"venue"
},
  "geometry": {"coordinates":[-3.6470758915,40.4101371765],"type":"Point"}
}