{
  "type": "Feature",
  "properties": {
    "iso:country":"ES",
    "sg:address":"Avda Pio Xii, 2",
    "sg:city":"Valencia",
    "sg:orig_category":"Molduras, Junquillos, Listones Y Molduras Perforadas",
    "sg:phone":"+34 963 46 34 96",
    "sg:postcode":"46009",
    "sg:province":"Valencia",
    "wof:name":"Public Phone Vending S L",
    "wof:placetype":"venue"
},
  "geometry": {"coordinates":[-0.3910419941,39.4790344238],"type":"Point"}
}