{
  "type": "Feature",
  "properties": {
    "iso:country":"ES",
    "sg:address":"Calle de Hermanos Becerril, 11",
    "sg:city":"Cuenca",
    "sg:orig_category":"Centros De Coordinaci\u00d3n",
    "sg:phone":"+34 969 23 37 34",
    "sg:postcode":"16004",
    "sg:province":"Cuenca",
    "wof:name":"Barambio Odriozola Alvaro",
    "wof:placetype":"venue"
},
  "geometry": {"coordinates":[-2.1329059601,40.0642662048],"type":"Point"}
}