{
  "type": "Feature",
  "properties": {
    "iso:country":"ES",
    "sg:address":"Avda Autonomia, 20",
    "sg:city":"Zaragoza",
    "sg:orig_category":"Alquiler De Gr\u00daas",
    "sg:phone":"+34 976 43 71 78",
    "sg:postcode":"50003",
    "sg:province":"Zaragoza",
    "wof:name":"Domingo Rincon Santiago",
    "wof:placetype":"venue"
},
  "geometry": {"coordinates":[-0.9059200287,41.6602783203],"type":"Point"}
}