{
  "type": "Feature",
  "properties": {
    "addr:full":"Carrer de Mare De Deu Dels Angels, 3 Barcelona Barcelona 08035",
    "addr:housenumber":"3",
    "addr:postcode":"08035",
    "addr:street":"Carrer De Mare De Deu",
    "iso:country":"ES",
    "sg:address":"Carrer de Mare De Deu Dels Angels, 3",
    "sg:city":"Barcelona",
    "sg:orig_category":"Guarder\u00cdas",
    "sg:phone":"+34 934 17 47 91",
    "sg:postcode":"08035",
    "sg:province":"Barcelona",
    "wof:name":"Cros Arranz Mercedes",
    "wof:placetype":"venue"
},
  "geometry": {"coordinates":[2.1467700005,41.4212417603],"type":"Point"}
}