{
  "type": "Feature",
  "properties": {
    "addr:full":"Euskadi Etorbidea, 27 Pasai S. Pedro Guip\u00f9zcoa 20110",
    "addr:housenumber":"27",
    "addr:postcode":"20110",
    "addr:street":"Euskadi Etorbidea;Guipu\u0300Zcoa",
    "iso:country":"ES",
    "sg:address":"Euskadi Etorbidea, 27",
    "sg:city":"Pasai S. Pedro",
    "sg:orig_category":"Confecci\u00d3n (fabricaci\u00d3n, Al Por Mayor)",
    "sg:phone":"+34 943 39 14 03",
    "sg:postcode":"20110",
    "sg:province":"Guip\u00f9zcoa",
    "wof:name":"Leize Moda Textil S.l.",
    "wof:placetype":"venue"
},
  "geometry": {"coordinates":[-1.9300839901,43.3229217529],"type":"Point"}
}