{
  "type": "Feature",
  "properties": {
    "iso:country":"ES",
    "sg:address":"Calle de Miguel Hernandez, 11",
    "sg:city":"Argamasilla Alba",
    "sg:orig_category":"Ropa De Hogar (al Por Menor)",
    "sg:phone":"+34 926 52 15 26",
    "sg:postcode":"13710",
    "sg:province":"Ciudad Real",
    "wof:name":"Hilario Montalban Josefa",
    "wof:placetype":"venue"
},
  "geometry": {"coordinates":[-3.0943241119,39.1289596558],"type":"Point"}
}