{
  "type": "Feature",
  "properties": {
    "addr:full":"Carrer de Camprodon, 16 Granollers Barcelona 08402",
    "addr:housenumber":"16",
    "addr:postcode":"08402",
    "addr:street":"Carrer De Camprodon",
    "iso:country":"ES",
    "sg:address":"Carrer de Camprodon, 16",
    "sg:city":"Granollers",
    "sg:orig_category":"Aparatos E Instalaci\u00d3n De Regad\u00cdos",
    "sg:phone":"+34 938 70 39 77",
    "sg:postcode":"08402",
    "sg:province":"Barcelona",
    "wof:name":"Pont Cucurull Juan",
    "wof:placetype":"venue"
},
  "geometry": {"coordinates":[2.2938768864,41.6049385071],"type":"Point"}
}