{
  "type": "Feature",
  "properties": {
    "iso:country":"ES",
    "sg:address":"Calle de Corazon De Maria, 21",
    "sg:city":"Madrid",
    "sg:orig_category":"Marketing Directo",
    "sg:phone":"+34 915 19 94 72",
    "sg:postcode":"28002",
    "sg:province":"Madrid",
    "wof:name":"Gescidi S.l.",
    "wof:placetype":"venue"
},
  "geometry": {"coordinates":[-3.6696109772,40.4418373108],"type":"Point"}
}