{
  "type": "Feature",
  "properties": {
    "iso:country":"ES",
    "sg:address":"Carrer de Salva, 13",
    "sg:city":"Barcelona",
    "sg:orig_category":"Grafistas",
    "sg:phone":"+34 934 42 04 76",
    "sg:postcode":"08004",
    "sg:province":"Barcelona",
    "wof:name":"Bauer  Mary",
    "wof:placetype":"venue"
},
  "geometry": {"coordinates":[2.1665680408,41.3740921021],"type":"Point"}
}