{
  "type": "Feature",
  "properties": {
    "addr:full":"Calle de Adriano Vi, 11 Vitoria-gasteiz \u00c1lava 01008",
    "addr:housenumber":"11",
    "addr:postcode":"01008",
    "addr:street":"Calle De Adriano Vi",
    "iso:country":"ES",
    "sg:address":"Calle de Adriano Vi, 11",
    "sg:city":"Vitoria-gasteiz",
    "sg:orig_category":"Agencias De Viajes",
    "sg:phone":"+34 945 13 36 56",
    "sg:postcode":"01008",
    "sg:province":"\u00c1lava",
    "sg:website":"www.viajeseroski.es",
    "wof:name":"Viajes Eroski S.a.",
    "wof:placetype":"venue"
},
  "geometry": {"coordinates":[-2.6813900471,42.8469848633],"type":"Point"}
}