{
  "type": "Feature",
  "properties": {
    "addr:full":"Pase Acacias, 11 Madrid Madrid 28005",
    "addr:housenumber":"11",
    "addr:postcode":"madrid;28005",
    "addr:street":"Acacias",
    "iso:country":"ES",
    "sg:address":"Pase Acacias, 11",
    "sg:city":"Madrid",
    "sg:orig_category":"Molduras, Junquillos, Listones Y Molduras Perforadas",
    "sg:phone":"+34 915 17 31 41",
    "sg:postcode":"28005",
    "sg:province":"Madrid",
    "wof:name":"Quintana Martin Manuel",
    "wof:placetype":"venue"
},
  "geometry": {"coordinates":[-3.7043409348,40.4044837952],"type":"Point"}
}