{
  "type": "Feature",
  "properties": {
    "addr:full":"Calle de Padre Claret, 3 Logro\u00f1o La Rioja 26004",
    "addr:housenumber":"3",
    "addr:postcode":"26004",
    "addr:street":"Calle De Padre Claret;Rioja",
    "iso:country":"ES",
    "sg:address":"Calle de Padre Claret, 3",
    "sg:city":"Logro\u00f1o",
    "sg:orig_category":"Agencias Y Asesores De Publicidad",
    "sg:phone":"+34 941 23 75 20",
    "sg:postcode":"26004",
    "sg:province":"La Rioja",
    "sg:website":"www.laprensadelrioja.com",
    "wof:name":"J. Pascual Comunicacion S.cv.",
    "wof:placetype":"venue"
},
  "geometry": {"coordinates":[-2.433478117,42.4635658264],"type":"Point"}
}