{
  "type": "Feature",
  "properties": {
    "addr:full":"Calle de Ramon Y Cajal, 12 Teruel Teruel 44001",
    "addr:housenumber":"12",
    "addr:postcode":"44001",
    "addr:street":"Calle De Ramon Y Cajal",
    "iso:country":"ES",
    "sg:address":"Calle de Ramon Y Cajal, 12",
    "sg:city":"Teruel",
    "sg:orig_category":"Librer\u00cdas",
    "sg:phone":"+34 978 60 13 15",
    "sg:postcode":"44001",
    "sg:province":"Teruel",
    "wof:name":"Gomez Sebastian Francisco Javier",
    "wof:placetype":"venue"
},
  "geometry": {"coordinates":[-1.1072800159,40.341884613],"type":"Point"}
}