{
  "type": "Feature",
  "properties": {
    "iso:country":"ES",
    "sg:address":"Carrer de Assemblea De Catalunya, 2",
    "sg:city":"Vic",
    "sg:orig_category":"Institutos De Belleza",
    "sg:phone":"+34 938 86 81 37",
    "sg:postcode":"08500",
    "sg:province":"Barcelona",
    "wof:name":"Elles Estetica Scp",
    "wof:placetype":"venue"
},
  "geometry": {"coordinates":[2.2514400482,41.9337310791],"type":"Point"}
}