{
  "type": "Feature",
  "properties": {
    "addr:full":"C/ Porta Oriola, 6 Elche Alicante 03203",
    "addr:housenumber":"6",
    "addr:postcode":"03203",
    "addr:street":"C / Porta Oriola",
    "iso:country":"ES",
    "sg:address":"C/ Porta Oriola, 6",
    "sg:city":"Elche",
    "sg:orig_category":"Zapatos: Material, Suministros, Accesorios (fabricaci\u00d3n, Al Por Mayor)",
    "sg:phone":"+34 965 45 03 34",
    "sg:postcode":"03203",
    "sg:province":"Alicante",
    "wof:name":"Ferrandez Bas Manuel",
    "wof:placetype":"venue"
},
  "geometry": {"coordinates":[-0.6988809705,38.2636909485],"type":"Point"}
}