{
  "type": "Feature",
  "properties": {
    "iso:country":"ES",
    "sg:address":"Trav Corts, 64",
    "sg:city":"Barcelona",
    "sg:orig_category":"Inmobiliaria (agencias)",
    "sg:phone":"+34 934 48 08 22",
    "sg:postcode":"08028",
    "sg:province":"Barcelona",
    "wof:name":"Predinvest S.l.",
    "wof:placetype":"venue"
},
  "geometry": {"coordinates":[2.1223599911,41.3784103394],"type":"Point"}
}