{
  "type": "Feature",
  "properties": {
    "iso:country":"ES",
    "sg:address":"Calle de Romero Robledo, 21",
    "sg:city":"Madrid",
    "sg:orig_category":"Abogados",
    "sg:phone":"+34 915 43 01 61",
    "sg:postcode":"28008",
    "sg:province":"Madrid",
    "wof:name":"Salado Gangoso Felix",
    "wof:placetype":"venue"
},
  "geometry": {"coordinates":[-3.7217650414,40.4312858582],"type":"Point"}
}