{
  "type": "Feature",
  "properties": {
    "iso:country":"ES",
    "sg:address":"Calle de Gabriel Y Galan, 2",
    "sg:city":"Villanueva Serena",
    "sg:orig_category":"Relojer\u00cda (al Por Menor, Reparaci\u00d3n)",
    "sg:phone":"+34 924 84 18 33",
    "sg:postcode":"06700",
    "sg:province":"Badajoz",
    "wof:name":"Puerto Segador Manuel",
    "wof:placetype":"venue"
},
  "geometry": {"coordinates":[-5.7964439392,38.9743385315],"type":"Point"}
}