{
  "type": "Feature",
  "properties": {
    "addr:full":"Luga Barranco De Los Canarios, S/n Mal Nombre Las Palmas 35628",
    "addr:housenumber":"s / n",
    "addr:postcode":"35628",
    "addr:street":"Canarios;Nombre",
    "iso:country":"ES",
    "sg:address":"Luga Barranco De Los Canarios, S/n",
    "sg:city":"Mal Nombre",
    "sg:orig_category":"Distribuci\u00d3n De Petr\u00d3leo Y Derivados",
    "sg:phone":"+34 928 54 95 17",
    "sg:postcode":"35628",
    "sg:province":"Las Palmas",
    "wof:name":"Glogreca S.l.",
    "wof:placetype":"venue"
},
  "geometry": {"coordinates":[-14.1094636917,28.3498058319],"type":"Point"}
}