{
  "type": "Feature",
  "properties": {
    "iso:country":"ES",
    "sg:address":"Psaj Do\u00d1a Jimena, 3",
    "sg:city":"Ibi",
    "sg:orig_category":"Agencias De Viajes",
    "sg:phone":"+34 965 55 00 00",
    "sg:postcode":"03440",
    "sg:province":"Alicante",
    "sg:website":"www.halconviajes.com",
    "wof:name":"Viajes Halcon S.a.",
    "wof:placetype":"venue"
},
  "geometry": {"coordinates":[-0.5780689716,38.6202316284],"type":"Point"}
}