{
  "type": "Feature",
  "properties": {
    "addr:full":"Calle de Rio Salado, 29 Chipiona C\u00e1diz 11550",
    "addr:housenumber":"29",
    "addr:postcode":"11550",
    "addr:street":"Calle De Rio Salado",
    "iso:country":"ES",
    "sg:address":"Calle de Rio Salado, 29",
    "sg:city":"Chipiona",
    "sg:orig_category":"Electromec\u00c1nica",
    "sg:phone":"+34 956 37 50 26",
    "sg:postcode":"11550",
    "sg:province":"C\u00e1diz",
    "wof:name":"Taller Anbar Cb",
    "wof:placetype":"venue"
},
  "geometry": {"coordinates":[-6.4258060455,36.7418022156],"type":"Point"}
}