{
  "type": "Feature",
  "properties": {
    "addr:full":"Calle de Via De La Plata, 19 Ba\u00d1eza Le\u00f3n 24750",
    "addr:housenumber":"19",
    "addr:postcode":"24750",
    "addr:street":"Calle De Via De La Plata;Leo\u0301N",
    "iso:country":"ES",
    "sg:address":"Calle de Via De La Plata, 19",
    "sg:city":"Ba\u00d1eza",
    "sg:orig_category":"Laboratorios Y Trabajos De Fotograf\u00cda, V\u00cddeo Y Cine",
    "sg:phone":"+34 987 65 52 16",
    "sg:postcode":"24750",
    "sg:province":"Le\u00f3n",
    "wof:name":"Cano Ja\u00f1ez Maria",
    "wof:placetype":"venue"
},
  "geometry": {"coordinates":[-5.9242091179,42.3069114685],"type":"Point"}
}