{
  "type": "Feature",
  "properties": {
    "iso:country":"ES",
    "sg:address":"Ramon Y Cajal, 36",
    "sg:city":"Infiesto",
    "sg:orig_category":"Chapister\u00cda",
    "sg:phone":"+34 985 71 16 13",
    "sg:postcode":"33530",
    "sg:province":"Asturias",
    "wof:name":"Perez Villar Manuel",
    "wof:placetype":"venue"
},
  "geometry": {"coordinates":[-5.3746089935,43.3523712158],"type":"Point"}
}