{
  "type": "Feature",
  "properties": {
    "iso:country":"ES",
    "sg:address":"Carrer de Rafael De Casanova, 19",
    "sg:city":"Molins Rei",
    "sg:orig_category":"Arquitectos",
    "sg:phone":"+34 936 80 20 18",
    "sg:postcode":"08750",
    "sg:province":"Barcelona",
    "wof:name":"Tort Estefanell  Valenti",
    "wof:placetype":"venue"
},
  "geometry": {"coordinates":[2.0181109905,41.4110031128],"type":"Point"}
}