{
  "type": "Feature",
  "properties": {
    "iso:country":"ES",
    "sg:address":"Carrer de Mar, 16",
    "sg:city":"Hospitalet De L'infant",
    "sg:orig_category":"Inmobiliaria (agencias)",
    "sg:phone":"+34 977 82 07 83",
    "sg:postcode":"43890",
    "sg:province":"Tarragona",
    "wof:name":"Gestion Inmobiliaria Gramontel",
    "wof:placetype":"venue"
},
  "geometry": {"coordinates":[1.2775230408,41.1217651367],"type":"Point"}
}