{
  "type": "Feature",
  "properties": {
    "addr:full":"Carrer de Anselm Clave, 38 Roca Valles Barcelona 08430",
    "addr:housenumber":"38",
    "addr:postcode":"08430",
    "addr:street":"Carrer De Anselm Clave;Barcelona",
    "iso:country":"ES",
    "sg:address":"Carrer de Anselm Clave, 38",
    "sg:city":"Roca Valles",
    "sg:orig_category":"Bancos",
    "sg:phone":"+34 938 42 20 94",
    "sg:postcode":"08430",
    "sg:province":"Barcelona",
    "wof:name":"Banco Espa\u00f1ol De Credito S.a.",
    "wof:placetype":"venue"
},
  "geometry": {"coordinates":[2.3770260811,41.6025276184],"type":"Point"}
}