{
  "type": "Feature",
  "properties": {
    "addr:full":"Calle de San Jose, 37 Cadiz C\u00e1diz 11003",
    "addr:housenumber":"37",
    "addr:postcode":"11003",
    "addr:street":"Calle De San;Cadiz Ca\u0301Diz",
    "iso:country":"ES",
    "sg:address":"Calle de San Jose, 37",
    "sg:city":"Cadiz",
    "sg:orig_category":"Electrodom\u00c9sticos (al Por Menor)",
    "sg:phone":"+34 956 21 39 10",
    "sg:postcode":"11003",
    "sg:province":"C\u00e1diz",
    "wof:name":"Montesinos Barranco Rivero S.l.",
    "wof:placetype":"venue"
},
  "geometry": {"coordinates":[-6.2995281219,36.5333824158],"type":"Point"}
}