{
  "type": "Feature",
  "properties": {
    "iso:country":"ES",
    "sg:address":"Carrer de Azorin, 2",
    "sg:city":"Castalla",
    "sg:orig_category":"Agencias De Viajes",
    "sg:phone":"+34 966 56 01 77",
    "sg:postcode":"03420",
    "sg:province":"Alicante",
    "sg:website":"www.zafirotours.es",
    "wof:name":"Rodriguez Vicent Jose Luis",
    "wof:placetype":"venue"
},
  "geometry": {"coordinates":[-0.6703860164,38.591960907],"type":"Point"}
}