{
  "type": "Feature",
  "properties": {
    "addr:full":"Calle de Principe De Vergara, 53 Madrid Madrid 28006",
    "addr:housenumber":"53",
    "addr:postcode":"madrid;28006",
    "addr:street":"Calle De Principe De Vergara",
    "iso:country":"ES",
    "sg:address":"Calle de Principe De Vergara, 53",
    "sg:city":"Madrid",
    "sg:orig_category":"M\u00c9dicos: Radioterapia (radioterapia Como Opci\u00d3n Oncol\u00d3gica)",
    "sg:phone":"+34 915 75 48 66",
    "sg:postcode":"28006",
    "sg:province":"Madrid",
    "wof:name":"Jose Maria Perez Aznar S.l.",
    "wof:placetype":"venue"
},
  "geometry": {"coordinates":[-3.6797549725,40.431968689],"type":"Point"}
}