{
  "type": "Feature",
  "properties": {
    "iso:country":"ES",
    "sg:address":"Calle de Almirante Apodaca, 23",
    "sg:city":"Sevilla",
    "sg:orig_category":"Librer\u00cdas",
    "sg:phone":"+34 954 21 40 84",
    "sg:postcode":"41003",
    "sg:province":"Sevilla",
    "wof:name":"Reguera Ramirez Julio",
    "wof:placetype":"venue"
},
  "geometry": {"coordinates":[-5.9886617661,37.3928794861],"type":"Point"}
}