{
  "type": "Feature",
  "properties": {
    "addr:full":"Calle de Alicante, 4 Teruel Teruel 44002",
    "addr:housenumber":"4",
    "addr:postcode":"44002",
    "addr:street":"Calle De Alicante",
    "iso:country":"ES",
    "sg:address":"Calle de Alicante, 4",
    "sg:city":"Teruel",
    "sg:orig_category":"Empleado Administrativo",
    "sg:phone":"+34 978 60 12 05",
    "sg:postcode":"44002",
    "sg:province":"Teruel",
    "wof:name":"Gestoria Medina Sociedad Civil",
    "wof:placetype":"venue"
},
  "geometry": {"coordinates":[-1.10300982,40.3359107971],"type":"Point"}
}