{
  "type": "Feature",
  "properties": {
    "addr:full":"Plaz Saint Palais, 6 Sang\u00fcesa Navarra 31400",
    "addr:housenumber":"6",
    "addr:postcode":"31400",
    "addr:street":"Plaz;Palais",
    "iso:country":"ES",
    "sg:address":"Plaz Saint Palais, 6",
    "sg:city":"Sang\u00fcesa",
    "sg:orig_category":"Peluqueros: De Se\u00d1oras",
    "sg:phone":"+34 948 87 16 85",
    "sg:postcode":"31400",
    "sg:province":"Navarra",
    "wof:name":"Hijarrubia Dome\u00f1o Virginia",
    "wof:placetype":"venue"
},
  "geometry": {"coordinates":[-1.2794743776,42.5732498169],"type":"Point"}
}