{
  "type": "Feature",
  "properties": {
    "iso:country":"ES",
    "sg:address":"Avda Jesus De Nazaret, 22",
    "sg:city":"Llerena",
    "sg:orig_category":"Contenedores (mercanc\u00cdas)",
    "sg:phone":"+34 924 87 02 65",
    "sg:postcode":"06900",
    "sg:province":"Badajoz",
    "wof:name":"Garcia Garcia Maximiano",
    "wof:placetype":"venue"
},
  "geometry": {"coordinates":[-6.0154027939,38.2411155701],"type":"Point"}
}