{
  "type": "Feature",
  "properties": {
    "iso:country":"ES",
    "sg:address":"Avda Juan Xxiii, 1",
    "sg:city":"Bosque",
    "sg:orig_category":"Electrodom\u00c9sticos (fabricaci\u00d3n, Al Por Mayor)",
    "sg:phone":"+34 956 71 60 13",
    "sg:postcode":"11670",
    "sg:province":"C\u00e1diz",
    "wof:name":"Chacon Gonzalez Alejandra",
    "wof:placetype":"venue"
},
  "geometry": {"coordinates":[-5.5036587715,36.7589988708],"type":"Point"}
}