{
  "type": "Feature",
  "properties": {
    "iso:country":"ES",
    "sg:address":"Calle de Orilla Del Azarbe, 64",
    "sg:city":"Huerta De Llano De Brujas",
    "sg:orig_category":"Molduras, Junquillos, Listones Y Molduras Perforadas",
    "sg:phone":"+34 968 85 04 30",
    "sg:postcode":"30161",
    "sg:province":"Murcia",
    "wof:name":"Saez Gallego Jose",
    "wof:placetype":"venue"
},
  "geometry": {"coordinates":[-1.070909977,38.0056495667],"type":"Point"}
}