{
  "type": "Feature",
  "properties": {
    "addr:full":"Calle de Salvador Y Merino, 8 Coru\u00d1a La Coru\u00f1a 15008",
    "addr:housenumber":"8",
    "addr:postcode":"15008",
    "addr:street":"Calle De Salvador Y Merino;La Corun\u0303A",
    "iso:country":"ES",
    "sg:address":"Calle de Salvador Y Merino, 8",
    "sg:city":"Coru\u00d1a",
    "sg:orig_category":"Florister\u00cdas",
    "sg:phone":"+34 981 15 31 41",
    "sg:postcode":"15008",
    "sg:province":"La Coru\u00f1a",
    "wof:name":"Otero Amado Antonio Manuel",
    "wof:placetype":"venue"
},
  "geometry": {"coordinates":[-8.408288002,43.3507347107],"type":"Point"}
}