{
  "type": "Feature",
  "properties": {
    "addr:full":"Carrer de Assalt (de L'), 5 Tarragona Tarragona 43003",
    "addr:housenumber":"5",
    "addr:postcode":"43003",
    "addr:street":"Carrer De Assalt De L '",
    "iso:country":"ES",
    "sg:address":"Carrer de Assalt (de L'), 5",
    "sg:city":"Tarragona",
    "sg:orig_category":"Reciclaje Y Tratamiento De Desechos Varios",
    "sg:phone":"+34 977 21 15 08",
    "sg:postcode":"43003",
    "sg:province":"Tarragona",
    "wof:name":"Fomento De Construcciones Y Contratas S.a.",
    "wof:placetype":"venue"
},
  "geometry": {"coordinates":[1.2523490191,41.1172065735],"type":"Point"}
}