{
  "type": "Feature",
  "properties": {
    "iso:country":"ES",
    "sg:address":"Calle de Arrosals, 2",
    "sg:city":"Riba-roja Turia",
    "sg:orig_category":"Promotores Constructores",
    "sg:phone":"+34 962 77 20 04",
    "sg:postcode":"46190",
    "sg:province":"Valencia",
    "wof:name":"Construcciones Del Turia Coop. V.",
    "wof:placetype":"venue"
},
  "geometry": {"coordinates":[-0.577167809,39.5454597473],"type":"Point"}
}