{
  "type": "Feature",
  "properties": {
    "iso:country":"ES",
    "sg:address":"Carrer de Santa Amelia, 2",
    "sg:city":"Barcelona",
    "sg:orig_category":"Molduras, Junquillos, Listones Y Molduras Perforadas",
    "sg:phone":"+34 932 04 10 02",
    "sg:postcode":"08034",
    "sg:province":"Barcelona",
    "wof:name":"Bosch Planas Carme",
    "wof:placetype":"venue"
},
  "geometry": {"coordinates":[2.1222400665,41.3930206299],"type":"Point"}
}