{
  "type": "Feature",
  "properties": {
    "iso:country":"ES",
    "sg:address":"Calle de Belgrado, 2",
    "sg:city":"Torrejon Ardoz",
    "sg:orig_category":"Ingeniero",
    "sg:phone":"+34 916 77 11 62",
    "sg:postcode":"28850",
    "sg:province":"Madrid",
    "wof:name":"S T M Comunicaciones S.l.",
    "wof:placetype":"venue"
},
  "geometry": {"coordinates":[-3.4741613865,40.461063385],"type":"Point"}
}