{
  "type": "Feature",
  "properties": {
    "iso:country":"ES",
    "sg:address":"Calle de Santo Domingo, 28",
    "sg:city":"G\u00fcimar",
    "sg:orig_category":"Bazares, Art\u00cdculos De Limpieza Y De Cocina (al Por Menor)",
    "sg:phone":"+34 922 51 37 55",
    "sg:postcode":"38500",
    "sg:province":"Santa Cruz De Tenerife",
    "wof:name":"Abrante Concepcion Alfredo",
    "wof:placetype":"venue"
},
  "geometry": {"coordinates":[-16.411642,28.314121],"type":"Point"}
}