{
  "type": "Feature",
  "properties": {
    "addr:full":"Avda Sierra De Gata, 21 Coria C\u00e1ceres 10800",
    "addr:housenumber":"21",
    "addr:postcode":"10800",
    "addr:street":"Avda Sierra De Gata;Ca\u0301Ceres",
    "iso:country":"ES",
    "sg:address":"Avda Sierra De Gata, 21",
    "sg:city":"Coria",
    "sg:orig_category":"Loter\u00cda Y T\u00d3mbola",
    "sg:phone":"+34 927 50 42 94",
    "sg:postcode":"10800",
    "sg:province":"C\u00e1ceres",
    "wof:name":"Pulido Lorenzo Eustaquio Javier",
    "wof:placetype":"venue"
},
  "geometry": {"coordinates":[-6.5369467735,39.9854202271],"type":"Point"}
}