{
  "type": "Feature",
  "properties": {
    "addr:full":"Avda Roquetas, 4 Roquetas Mar Almer\u00eda 04740",
    "addr:housenumber":"4",
    "addr:postcode":"04740",
    "addr:street":"Avda Roquetas",
    "iso:country":"ES",
    "sg:address":"Avda Roquetas, 4",
    "sg:city":"Roquetas Mar",
    "sg:orig_category":"Inmobiliaria (agencias)",
    "sg:phone":"+34 950 32 18 66",
    "sg:postcode":"04740",
    "sg:province":"Almer\u00eda",
    "wof:name":"Finca Sur Gestion Inmobiliaria S.l.",
    "wof:placetype":"venue"
},
  "geometry": {"coordinates":[-2.638466835,36.7327423096],"type":"Point"}
}