{
  "type": "Feature",
  "properties": {
    "iso:country":"ES",
    "sg:address":"Carrer de Nil Fabra, 7",
    "sg:city":"Barcelona",
    "sg:orig_category":"Arquitectos",
    "sg:phone":"+34 934 16 16 39",
    "sg:postcode":"08012",
    "sg:province":"Barcelona",
    "wof:name":"Projitel Europa Sl",
    "wof:placetype":"venue"
},
  "geometry": {"coordinates":[2.1510269642,41.4059066772],"type":"Point"}
}