{
  "type": "Feature",
  "properties": {
    "addr:full":"Calle de Mayor, 8 Vinaros Castell\u00f3n 12500",
    "addr:housenumber":"8",
    "addr:postcode":"12500",
    "addr:street":"Calle De Mayor",
    "iso:country":"ES",
    "sg:address":"Calle de Mayor, 8",
    "sg:city":"Vinaros",
    "sg:orig_category":"Perfumer\u00cda (al Por Menor)",
    "sg:phone":"+34 964 45 22 62",
    "sg:postcode":"12500",
    "sg:province":"Castell\u00f3n",
    "wof:name":"Perfumeria Arrieta S.l.",
    "wof:placetype":"venue"
},
  "geometry": {"coordinates":[0.4749450088,40.4711990356],"type":"Point"}
}