{
  "type": "Feature",
  "properties": {
    "addr:full":"Calle de Catalina De Erauso, 10 Donostia-san Sebastian Guip\u00f9zcoa 20010",
    "addr:housenumber":"10",
    "addr:postcode":"20010",
    "addr:street":"Calle De Catalina De Erauso",
    "iso:country":"ES",
    "sg:address":"Calle de Catalina De Erauso, 10",
    "sg:city":"Donostia-san Sebastian",
    "sg:orig_category":"Agencias Y Agentes Comerciales, Representantes",
    "sg:phone":"+34 943 45 74 91",
    "sg:postcode":"20010",
    "sg:province":"Guip\u00f9zcoa",
    "wof:name":"Comendador Regalado Felix Jesus",
    "wof:placetype":"venue"
},
  "geometry": {"coordinates":[-1.9810760021,43.3048286438],"type":"Point"}
}