{
  "type": "Feature",
  "properties": {
    "addr:full":"Plaz Independencia, 4 Carde\u00f1a C\u00f3rdoba 14445",
    "addr:housenumber":"4",
    "addr:postcode":"14445",
    "addr:street":"Plaz Independencia;Co\u0301Rdoba",
    "iso:country":"ES",
    "sg:address":"Plaz Independencia, 4",
    "sg:city":"Carde\u00f1a",
    "sg:orig_category":"Droguer\u00cdas (al Por Menor)",
    "sg:phone":"+34 957 17 40 20",
    "sg:postcode":"14445",
    "sg:province":"C\u00f3rdoba",
    "wof:name":"Galan Bollero Jesus Mario",
    "wof:placetype":"venue"
},
  "geometry": {"coordinates":[-4.3252439499,38.2739257812],"type":"Point"}
}