{
  "type": "Feature",
  "properties": {
    "iso:country":"ES",
    "sg:address":"Calle de Vega, 18",
    "sg:city":"Valladolid",
    "sg:orig_category":"Abogados",
    "sg:phone":"+34 983 21 19 88",
    "sg:postcode":"47004",
    "sg:province":"Valladolid",
    "wof:name":"Robles Granja Maria Domnina",
    "wof:placetype":"venue"
},
  "geometry": {"coordinates":[-4.7223510742,41.6478118896],"type":"Point"}
}