{
  "type": "Feature",
  "properties": {
    "addr:full":"Ptda Les Rotes, 1 Altea Alicante 03590",
    "addr:housenumber":"1",
    "addr:postcode":"03590",
    "addr:street":"Ptda Les Rotes",
    "iso:country":"ES",
    "sg:address":"Ptda Les Rotes, 1",
    "sg:city":"Altea",
    "sg:orig_category":"Teatros Y Salas De Espect\u00c1culos",
    "sg:phone":"+34 966 88 19 24",
    "sg:postcode":"03590",
    "sg:province":"Alicante",
    "wof:name":"Ayuntamiento De Altea",
    "wof:placetype":"venue"
},
  "geometry": {"coordinates":[-0.0506840013,38.6008338928],"type":"Point"}
}