{
  "type": "Feature",
  "properties": {
    "iso:country":"ES",
    "sg:address":"Carrer de Frederica Montseny, 4",
    "sg:city":"Sant Feliu Llobregat",
    "sg:orig_category":"Arquitectos",
    "sg:phone":"+34 936 32 52 74",
    "sg:postcode":"08980",
    "sg:province":"Barcelona",
    "wof:name":"Tamayo Colon Alfons",
    "wof:placetype":"venue"
},
  "geometry": {"coordinates":[2.0568799973,41.3856201172],"type":"Point"}
}