{
  "type": "Feature",
  "properties": {
    "addr:full":"Poli Industrial 1 De Mayo, S/n Miajadas C\u00e1ceres 10100",
    "addr:housenumber":"s / n",
    "addr:postcode":"10100",
    "addr:street":"Mayo;Ca\u0301Ceres",
    "iso:country":"ES",
    "sg:address":"Poli Industrial 1 De Mayo, S/n",
    "sg:city":"Miajadas",
    "sg:orig_category":"Veh\u00cdculos De Ocasi\u00d3n",
    "sg:phone":"+34 927 34 50 57",
    "sg:postcode":"10100",
    "sg:province":"C\u00e1ceres",
    "wof:name":"Diauto C.b.",
    "wof:placetype":"venue"
},
  "geometry": {"coordinates":[-5.9082989693,39.1555213928],"type":"Point"}
}