{
  "type": "Feature",
  "properties": {
    "iso:country":"ES",
    "sg:address":"Calle de Iglesia, 12",
    "sg:city":"Fuentes Ebro",
    "sg:orig_category":"Confecci\u00d3n (fabricaci\u00d3n, Al Por Mayor)",
    "sg:phone":"+34 976 16 01 39",
    "sg:postcode":"50740",
    "sg:province":"Zaragoza",
    "wof:name":"Olmos Carot Marina",
    "wof:placetype":"venue"
},
  "geometry": {"coordinates":[-0.6312590241,41.512878418],"type":"Point"}
}