{
  "type": "Feature",
  "properties": {
    "addr:full":"Calle de Libertador Simon Bolivar, 1 Cordoba C\u00f3rdoba 14013",
    "addr:housenumber":"1",
    "addr:postcode":"14013",
    "addr:street":"Calle De Libertador Simon Bolivar;Co\u0301Rdoba",
    "iso:country":"ES",
    "sg:address":"Calle de Libertador Simon Bolivar, 1",
    "sg:city":"Cordoba",
    "sg:orig_category":"Panader\u00cdas, Panader\u00cdas",
    "sg:phone":"+34 957 42 11 23",
    "sg:postcode":"14013",
    "sg:province":"C\u00f3rdoba",
    "wof:name":"Rivas Alcayde Leonor",
    "wof:placetype":"venue"
},
  "geometry": {"coordinates":[-4.7808451653,37.860786438],"type":"Point"}
}