{
  "type": "Feature",
  "properties": {
    "iso:country":"ES",
    "sg:address":"Pase Real De La Feria, 5",
    "sg:city":"Alcazares",
    "sg:orig_category":"Inmobiliaria (agencias)",
    "sg:phone":"+34 968 57 47 21",
    "sg:postcode":"30710",
    "sg:province":"Murcia",
    "sg:website":"www.comprarcasa.com",
    "wof:name":"Agencia Flores Cb",
    "wof:placetype":"venue"
},
  "geometry": {"coordinates":[-1.1298867464,37.9834747314],"type":"Point"}
}