{
  "type": "Feature",
  "properties": {
    "iso:country":"ES",
    "sg:address":"Avda Castilla (de), 2",
    "sg:city":"Poligono De San Fernando De Henares",
    "sg:orig_category":"Administradores De Bienes Y Delegados De Comunidades De Propietarios",
    "sg:phone":"+34 916 78 79 00",
    "sg:postcode":"28830",
    "sg:province":"Madrid",
    "sg:website":"www.intervalword.com",
    "wof:name":"Interval Internacional Espa\u00d1a S.a.",
    "wof:placetype":"venue"
},
  "geometry": {"coordinates":[-3.5104780197,40.4524345398],"type":"Point"}
}