{
  "type": "Feature",
  "properties": {
    "iso:country":"ES",
    "sg:address":"Carr Marques Del Turia, 9",
    "sg:city":"Quart Poblet",
    "sg:orig_category":"Distribuci\u00d3n De Petr\u00d3leo Y Derivados",
    "sg:phone":"+34 961 52 14 81",
    "sg:postcode":"46930",
    "sg:province":"Valencia",
    "wof:name":"Oil Quart S.c.p.",
    "wof:placetype":"venue"
},
  "geometry": {"coordinates":[-0.4445950091,39.4789886475],"type":"Point"}
}