{
  "type": "Feature",
  "properties": {
    "addr:full":"Calle de Medea, 4 Madrid Madrid 28032",
    "addr:housenumber":"4",
    "addr:postcode":"28032",
    "addr:street":"Calle De Medea",
    "iso:country":"ES",
    "sg:address":"Calle de Medea, 4",
    "sg:city":"Madrid",
    "sg:orig_category":"M\u00c1quinas Y Material Para La Industria De La Alimentaci\u00d3n",
    "sg:phone":"+34 917 54 05 13",
    "sg:postcode":"28032",
    "sg:province":"Madrid",
    "wof:name":"Equipos Para Manutencion Y Obras S.a.",
    "wof:placetype":"venue"
},
  "geometry": {"coordinates":[-3.6244060993,40.4396400452],"type":"Point"}
}