{
  "type": "Feature",
  "properties": {
    "iso:country":"ES",
    "sg:address":"Calle de Casiodoro De Reina, S/n",
    "sg:city":"Sevilla",
    "sg:orig_category":"Iglesias Evang\u00c9licas",
    "sg:phone":"+34 954 44 15 23",
    "sg:postcode":"41020",
    "sg:province":"Sevilla",
    "wof:name":"Iglesia Evangelica Bautista Beatriz Suabia",
    "wof:placetype":"venue"
},
  "geometry": {"coordinates":[-5.92146492,37.3921470642],"type":"Point"}
}