{
  "type": "Feature",
  "properties": {
    "addr:full":"Del Sol, 26 Castellar Santiago Ciudad Real 13750",
    "addr:postcode":"13750",
    "iso:country":"ES",
    "sg:address":"Del Sol, 26",
    "sg:city":"Castellar Santiago",
    "sg:orig_category":"Pescader\u00cdas (al Por Menor)",
    "sg:phone":"+34 926 34 02 67",
    "sg:postcode":"13750",
    "sg:province":"Ciudad Real",
    "wof:name":"Martinez Gimenez Atanasio",
    "wof:placetype":"venue"
},
  "geometry": {"coordinates":[-3.2766900063,38.5396995544],"type":"Point"}
}