{
  "type": "Feature",
  "properties": {
    "addr:full":"Planeta (la), S/n Mancha Real Ja\u00e9n 23100",
    "addr:housenumber":"/ n",
    "addr:postcode":"23100",
    "addr:street":"La S",
    "iso:country":"ES",
    "sg:address":"Planeta (la), S/n",
    "sg:city":"Mancha Real",
    "sg:orig_category":"Ropa Y Art\u00cdculos Pre",
    "sg:phone":"+34 953 35 29 92",
    "sg:postcode":"23100",
    "sg:province":"Ja\u00e9n",
    "wof:name":"Leiva Gomez Francisca",
    "wof:placetype":"venue"
},
  "geometry": {"coordinates":[-3.609249115,37.7891464233],"type":"Point"}
}