{
  "type": "Feature",
  "properties": {
    "addr:full":"Urb Torre Del Ram, 117 Torre Del Ram Islas Baleares 07769",
    "addr:housenumber":"117",
    "addr:postcode":"07769",
    "addr:street":"Urb Torre Del Ram;Islas",
    "iso:country":"ES",
    "sg:address":"Urb Torre Del Ram, 117",
    "sg:city":"Torre Del Ram",
    "sg:orig_category":"Molduras, Junquillos, Listones Y Molduras Perforadas",
    "sg:phone":"+34 971 38 85 35",
    "sg:postcode":"07769",
    "sg:province":"Islas Baleares",
    "wof:name":"Leon Rojo S.l.",
    "wof:placetype":"venue"
},
  "geometry": {"coordinates":[3.8426098824,39.9794692993],"type":"Point"}
}