{
  "type": "Feature",
  "properties": {
    "addr:full":"Calle de Finlandia, 4 Valencia Valencia 46010",
    "addr:housenumber":"4",
    "addr:postcode":"46010",
    "addr:street":"Calle De Finlandia",
    "iso:country":"ES",
    "sg:address":"Calle de Finlandia, 4",
    "sg:city":"Valencia",
    "sg:orig_category":"Librer\u00cdas",
    "sg:phone":"+34 963 61 80 35",
    "sg:postcode":"46010",
    "sg:province":"Valencia",
    "wof:name":"Castillo Garcia Ramon",
    "wof:placetype":"venue"
},
  "geometry": {"coordinates":[-0.3602800071,39.4725074768],"type":"Point"}
}