{
  "type": "Feature",
  "properties": {
    "addr:full":"Calle de Pio Baroja, 4 Bigastro Alicante 03380",
    "addr:housenumber":"4",
    "addr:postcode":"03380",
    "addr:street":"Calle De Pio Baroja",
    "iso:country":"ES",
    "sg:address":"Calle de Pio Baroja, 4",
    "sg:city":"Bigastro",
    "sg:orig_category":"Empresarios",
    "sg:phone":"+34 966 77 02 27",
    "sg:postcode":"03380",
    "sg:province":"Alicante",
    "wof:name":"Ropajopa 2003 S.l",
    "wof:placetype":"venue"
},
  "geometry": {"coordinates":[-0.9063079953,38.0640029907],"type":"Point"}
}