{
  "type": "Feature",
  "properties": {
    "iso:country":"ES",
    "sg:address":"Av Pais Valencia, 28",
    "sg:city":"Benissa",
    "sg:orig_category":"Cl\u00cdnicas Dentales",
    "sg:phone":"+34 965 73 17 75",
    "sg:postcode":"03720",
    "sg:province":"Alicante",
    "wof:name":"Marti Roig Cristina",
    "wof:placetype":"venue"
},
  "geometry": {"coordinates":[0.1034357995,38.6825065613],"type":"Point"}
}