{
  "type": "Feature",
  "properties": {
    "addr:full":"Estacion, 2 Estacion Ourense 32530",
    "addr:postcode":"32530",
    "addr:street":"Estacion 2 Estacion Ourense",
    "iso:country":"ES",
    "sg:address":"Estacion, 2",
    "sg:city":"Estacion",
    "sg:orig_category":"Empresas De Carpinter\u00cda De Madera",
    "sg:phone":"+34 988 28 74 89",
    "sg:postcode":"32530",
    "sg:province":"Ourense",
    "wof:name":"Bernardez Cerdeira Manuel",
    "wof:placetype":"venue"
},
  "geometry": {"coordinates":[-8.1174564362,42.5105514526],"type":"Point"}
}