{
  "type": "Feature",
  "properties": {
    "addr:full":"Calle de Irunbidea, 4 Orkoien Navarra 31160",
    "addr:housenumber":"4",
    "addr:postcode":"31160",
    "addr:street":"Calle De Irunbidea",
    "iso:country":"ES",
    "sg:address":"Calle de Irunbidea, 4",
    "sg:city":"Orkoien",
    "sg:classifiers":[
        {
            "category":"Communications",
            "subcategory":"Radio Station",
            "type":"Services"
        }
    ],
    "sg:phone":"+34 948 32 65 04",
    "sg:postcode":"31160",
    "sg:province":"Navarra",
    "sg:tags":[
        "de",
        "electr\u00d3nica",
        "material",
        "fabricaci\u00d3n",
        "y",
        "profesional"
    ],
    "wof:name":"Iru\u00f1a Navarrra Tecnica S.l",
    "wof:placetype":"venue"
},
  "geometry": {"coordinates":[-1.7063260078,42.8236083984],"type":"Point"}
}