{
  "type": "Feature",
  "properties": {
    "addr:full":"Marzaniella, 21 Trasona Asturias 33468",
    "addr:housenumber":"21",
    "addr:postcode":"33468",
    "addr:street":"Marzaniella;Asturias",
    "iso:country":"ES",
    "sg:address":"Marzaniella, 21",
    "sg:city":"Trasona",
    "sg:orig_category":"Venta, Instalaci\u00d3n De Calefacci\u00d3n",
    "sg:phone":"+34 985 51 62 29",
    "sg:postcode":"33468",
    "sg:province":"Asturias",
    "wof:name":"Instalaciones Corvera S.l.",
    "wof:placetype":"venue"
},
  "geometry": {"coordinates":[-5.9832577705,43.2504386902],"type":"Point"}
}