{
  "type": "Feature",
  "properties": {
    "iso:country":"ES",
    "sg:address":"C/ Fray Luis De Leon, 3",
    "sg:city":"Elche",
    "sg:orig_category":"Abogados",
    "sg:phone":"+34 965 42 77 31",
    "sg:postcode":"03203",
    "sg:province":"Alicante",
    "wof:name":"Comunidad De Propietarios Fray Luis De Leon 3",
    "wof:placetype":"venue"
},
  "geometry": {"coordinates":[-0.696408987,38.2592926025],"type":"Point"}
}