{
  "type": "Feature",
  "properties": {
    "iso:country":"ES",
    "sg:address":"Avenida De Solvay, 113",
    "sg:city":"Torrelavega",
    "sg:orig_category":"Molduras, Junquillos, Listones Y Molduras Perforadas",
    "sg:phone":"+34 942 80 14 46",
    "sg:postcode":"39300",
    "sg:province":"Cantabria",
    "wof:name":"Pedrajo Alcocer Miguel Angel",
    "wof:placetype":"venue"
},
  "geometry": {"coordinates":[-4.0417170525,43.3719482422],"type":"Point"}
}