{
  "type": "Feature",
  "properties": {
    "iso:country":"ES",
    "sg:address":"Avda Valdes, 38",
    "sg:city":"Ponferrada",
    "sg:orig_category":"Grafistas",
    "sg:phone":"+34 987 40 41 89",
    "sg:postcode":"24400",
    "sg:province":"Le\u00f3n",
    "wof:name":"Salvi Vega Juan Manuel",
    "wof:placetype":"venue"
},
  "geometry": {"coordinates":[-6.601170063,42.5494308472],"type":"Point"}
}