{
  "type": "Feature",
  "properties": {
    "addr:full":"Carr Menendez Y Pelayo, 9 Aldaia Valencia 46960",
    "addr:housenumber":"9",
    "addr:postcode":"46960",
    "addr:street":"Carr Menendez Y Pelayo",
    "iso:country":"ES",
    "sg:address":"Carr Menendez Y Pelayo, 9",
    "sg:city":"Aldaia",
    "sg:orig_category":"Ropa Para Se\u00d1oras Y Caballeros (al Por Menor)",
    "sg:phone":"+34 961 51 38 67",
    "sg:postcode":"46960",
    "sg:province":"Valencia",
    "wof:name":"Montesinos Valverde Jose Antonio",
    "wof:placetype":"venue"
},
  "geometry": {"coordinates":[-0.4646480083,39.4587593079],"type":"Point"}
}