{
  "type": "Feature",
  "properties": {
    "iso:country":"ES",
    "sg:address":"Calle de San Francisco, 35",
    "sg:city":"Alcora",
    "sg:orig_category":"Tintes (fabricaci\u00d3n, Al Por Mayor)",
    "sg:phone":"+34 964 36 23 22",
    "sg:postcode":"12110",
    "sg:province":"Castell\u00f3n",
    "wof:name":"Galdu Ordu\u00f1a Maria Luisa",
    "wof:placetype":"venue"
},
  "geometry": {"coordinates":[-0.2125770003,40.0734786987],"type":"Point"}
}