{
  "type": "Feature",
  "properties": {
    "iso:country":"ES",
    "sg:address":"Calle de Maidagan, 47",
    "sg:city":"Andra Mari",
    "sg:orig_category":"Arquitectos",
    "sg:phone":"+34 944 60 02 04",
    "sg:postcode":"48993",
    "sg:province":"Vizcaya",
    "wof:name":"Arriazu & Garay S.l.",
    "wof:placetype":"venue"
},
  "geometry": {"coordinates":[-3.0146713257,43.3611907959],"type":"Point"}
}