{
  "type": "Feature",
  "properties": {
    "iso:country":"ES",
    "sg:address":"Hiribarren Kalea, 10",
    "sg:city":"Lazkao",
    "sg:orig_category":"M\u00dasicos Int\u00c9rpretes",
    "sg:phone":"+34 943 16 13 42",
    "sg:postcode":"20210",
    "sg:province":"Guip\u00f9zcoa",
    "wof:name":"Pelaez Aramburu Alberto",
    "wof:placetype":"venue"
},
  "geometry": {"coordinates":[-2.1893870831,43.0391349792],"type":"Point"}
}