{
  "type": "Feature",
  "properties": {
    "addr:full":"La Carrera, S/n La Carrera Asturias 33519",
    "addr:housenumber":"/ n",
    "addr:postcode":"33519",
    "addr:street":"La Carrera S",
    "iso:country":"ES",
    "sg:address":"La Carrera, S/n",
    "sg:city":"La Carrera",
    "sg:orig_category":"Maquinaria Para Industrias Diversas",
    "sg:phone":"+34 985 74 09 09",
    "sg:postcode":"33519",
    "sg:province":"Asturias",
    "wof:name":"Alonso Felipe Carlos",
    "wof:placetype":"venue"
},
  "geometry": {"coordinates":[-5.9832577705,43.2504386902],"type":"Point"}
}