{
  "type": "Feature",
  "properties": {
    "iso:country":"ES",
    "sg:address":"Calle de Uhagon Felipe Alcalde, 2",
    "sg:city":"Bilbao",
    "sg:orig_category":"Fabricaci\u00d3n, Venta De Cuadros, Accesorios Para Enmarcar",
    "sg:phone":"+34 944 22 19 60",
    "sg:postcode":"48010",
    "sg:province":"Vizcaya",
    "wof:name":"Mota Cuadros Y Enmarcaciones, C.b.",
    "wof:placetype":"venue"
},
  "geometry": {"coordinates":[-2.9384551048,43.2590141296],"type":"Point"}
}