{
  "type": "Feature",
  "properties": {
    "addr:full":"Carr Nuestra Se\u00d1ora Angeles, 4 Silla Valencia 46460",
    "addr:housenumber":"4",
    "addr:postcode":"46460",
    "addr:street":"Carr Nuestra Sen\u0303Ora Angeles",
    "iso:country":"ES",
    "sg:address":"Carr Nuestra Se\u00d1ora Angeles, 4",
    "sg:city":"Silla",
    "sg:orig_category":"Maquinaria Para Industrias Diversas",
    "sg:phone":"+34 961 20 00 64",
    "sg:postcode":"46460",
    "sg:province":"Valencia",
    "wof:name":"Zaragoza S.l.",
    "wof:placetype":"venue"
},
  "geometry": {"coordinates":[-0.4127776027,39.3612709045],"type":"Point"}
}