{
  "type": "Feature",
  "properties": {
    "addr:full":"Constitucion Espa\u00f1ola, 52 Ingenio Las Palmas 35250",
    "addr:housenumber":"52",
    "addr:postcode":"35250",
    "addr:street":"Espan\u0303Ola",
    "iso:country":"ES",
    "sg:address":"Constitucion Espa\u00f1ola, 52",
    "sg:city":"Ingenio",
    "sg:orig_category":"Tapicer\u00cdas",
    "sg:phone":"+34 928 78 62 26",
    "sg:postcode":"35250",
    "sg:province":"Las Palmas",
    "wof:name":"Ramirez Quintana Maria Del Pino",
    "wof:placetype":"venue"
},
  "geometry": {"coordinates":[-15.4355688095,27.922290802],"type":"Point"}
}