{
  "type": "Feature",
  "properties": {
    "addr:full":"La Ribera, S/n Burgos Burgos 09007",
    "addr:housenumber":"s / n",
    "addr:postcode":"09007",
    "addr:street":"Ribera",
    "iso:country":"ES",
    "sg:address":"La Ribera, S/n",
    "sg:city":"Burgos",
    "sg:orig_category":"Persianas Interiores, Exteriores",
    "sg:phone":"+34 947 47 50 78",
    "sg:postcode":"09007",
    "sg:province":"Burgos",
    "wof:name":"Zumel Garcia Pedro",
    "wof:placetype":"venue"
},
  "geometry": {"coordinates":[-3.6468536854,42.3492622375],"type":"Point"}
}