{
  "type": "Feature",
  "properties": {
    "iso:country":"ES",
    "sg:address":"Calle de Diego De Ria\u00d1o, 4",
    "sg:city":"Sevilla",
    "sg:orig_category":"Abogados",
    "sg:phone":"+34 954 41 96 15",
    "sg:postcode":"41004",
    "sg:province":"Sevilla",
    "wof:name":"Medianero Hernanadez Concepcion",
    "wof:placetype":"venue"
},
  "geometry": {"coordinates":[-5.9847793579,37.3800506592],"type":"Point"}
}