{
  "type": "Feature",
  "properties": {
    "iso:country":"ES",
    "sg:address":"Carrer de Girona, 11",
    "sg:city":"Centelles",
    "sg:orig_category":"Distribuci\u00d3n De Petr\u00d3leo Y Derivados",
    "sg:phone":"+34 938 81 06 06",
    "sg:postcode":"08540",
    "sg:province":"Barcelona",
    "wof:name":"Gas-oil Centelles S.l.",
    "wof:placetype":"venue"
},
  "geometry": {"coordinates":[2.2209000587,41.7938804626],"type":"Point"}
}