{
  "type": "Feature",
  "properties": {
    "addr:full":"Calle de Jesus Del Gran Poder, 10 Sevilla Sevilla 41002",
    "addr:housenumber":"10",
    "addr:postcode":"41002",
    "addr:street":"Calle De Jesus Del Gran Poder",
    "iso:country":"ES",
    "sg:address":"Calle de Jesus Del Gran Poder, 10",
    "sg:city":"Sevilla",
    "sg:orig_category":"Estancos",
    "sg:phone":"+34 954 38 60 58",
    "sg:postcode":"41002",
    "sg:province":"Sevilla",
    "wof:name":"Borrero Rodriguez Manuel",
    "wof:placetype":"venue"
},
  "geometry": {"coordinates":[-5.9958600998,37.3943061829],"type":"Point"}
}