{
  "type": "Feature",
  "properties": {
    "addr:full":"C/ Joaquin Santos, 28 Elche Alicante 03203",
    "addr:housenumber":"28",
    "addr:postcode":"03203",
    "addr:street":"C / Joaquin Santos",
    "iso:country":"ES",
    "sg:address":"C/ Joaquin Santos, 28",
    "sg:city":"Elche",
    "sg:classifiers":[
        {
            "category":"Taxi",
            "type":"Transportation"
        }
    ],
    "sg:phone":"+34 965 45 61 77",
    "sg:postcode":"03203",
    "sg:province":"Alicante",
    "wof:name":"Macia Escaplez Gaspar",
    "wof:placetype":"venue"
},
  "geometry": {"coordinates":[-0.6974279881,38.2581214905],"type":"Point"}
}