{
  "type": "Feature",
  "properties": {
    "iso:country":"ES",
    "sg:address":"Calle de Motilla Del Palancar, 18",
    "sg:city":"Madrid",
    "sg:orig_category":"Arreglo, Reparaci\u00d3n, Piezas Sueltas De Televisi\u00d3n, V\u00cddeo, Hi",
    "sg:phone":"+34 917 59 78 98",
    "sg:postcode":"28043",
    "sg:province":"Madrid",
    "wof:name":"Pardo Perez Maria Jose",
    "wof:placetype":"venue"
},
  "geometry": {"coordinates":[-3.6325139999,40.4651107788],"type":"Point"}
}