{
  "type": "Feature",
  "properties": {
    "iso:country":"ES",
    "sg:address":"Plzl Esteban Carro Celada, 4",
    "sg:city":"Astorga",
    "sg:orig_category":"Productos Alimentarios",
    "sg:phone":"+34 987 61 74 82",
    "sg:postcode":"24700",
    "sg:province":"Le\u00f3n",
    "wof:name":"Martinez Gonzalo Jaime",
    "wof:placetype":"venue"
},
  "geometry": {"coordinates":[-6.0595240593,42.4569358826],"type":"Point"}
}