{
  "type": "Feature",
  "properties": {
    "iso:country":"ES",
    "sg:address":"Cmno Ronda (de), 32",
    "sg:city":"Granada",
    "sg:orig_category":"Electricidad Veh\u00cdculo",
    "sg:phone":"+34 958 25 53 66",
    "sg:postcode":"18004",
    "sg:province":"Granada",
    "wof:name":"Garrido Alvarez Juan",
    "wof:placetype":"venue"
},
  "geometry": {"coordinates":[-3.6032540798,37.166179657],"type":"Point"}
}