{
  "type": "Feature",
  "properties": {
    "iso:country":"ES",
    "sg:address":"Pg Maritim, 17",
    "sg:city":"Castelldefels",
    "sg:orig_category":"Pr\u00c1ctica De Vela, Navegaci\u00d3n Y Deportes N\u00c1uticos Y Acu\u00c1ticos",
    "sg:phone":"+34 936 65 54 56",
    "sg:postcode":"08860",
    "sg:province":"Barcelona",
    "wof:name":"Club Maritimo De Castelldefels",
    "wof:placetype":"venue"
},
  "geometry": {"coordinates":[1.9974499941,41.2651519775],"type":"Point"}
}