{
  "type": "Feature",
  "properties": {
    "iso:country":"ES",
    "sg:address":"Avda Portugal, S/n",
    "sg:city":"Talavera Reina",
    "sg:orig_category":"Mec\u00c1nico Del Autom\u00d3vil",
    "sg:phone":"+34 925 80 46 60",
    "sg:postcode":"45600",
    "sg:province":"Toledo",
    "wof:name":"Talleres Auto-mecha Comunidad De Bienes",
    "wof:placetype":"venue"
},
  "geometry": {"coordinates":[-4.8471841812,39.9579467773],"type":"Point"}
}