{
  "type": "Feature",
  "properties": {
    "iso:country":"ES",
    "sg:address":"Calle de Cadiz, 10",
    "sg:city":"Getafe",
    "sg:orig_category":"Asesor\u00cda, Estudio Y Control Medioambiental",
    "sg:phone":"+34 916 01 97 95",
    "sg:postcode":"28903",
    "sg:province":"Madrid",
    "wof:name":"Analisis E Informacion Ambiental S.l",
    "wof:placetype":"venue"
},
  "geometry": {"coordinates":[-3.7218809128,40.3146209717],"type":"Point"}
}