{
  "type": "Feature",
  "properties": {
    "iso:country":"ES",
    "sg:address":"Avda Alcala (de), 3",
    "sg:city":"Azuqueca Henares",
    "sg:orig_category":"Abogados",
    "sg:phone":"+34 949 26 55 45",
    "sg:postcode":"19200",
    "sg:province":"Guadalajara",
    "wof:name":"Rojas Diaz Alfonso",
    "wof:placetype":"venue"
},
  "geometry": {"coordinates":[-3.2718839645,40.5607872009],"type":"Point"}
}