{
  "type": "Feature",
  "properties": {
    "iso:country":"ES",
    "sg:address":"Carrer de Argullos, 100",
    "sg:city":"Barcelona",
    "sg:orig_category":"M\u00c1quinas Para Recortar Y Pegar",
    "sg:phone":"+34 933 50 54 95",
    "sg:postcode":"08016",
    "sg:province":"Barcelona",
    "wof:name":"Benitez Luis Antonia",
    "wof:placetype":"venue"
},
  "geometry": {"coordinates":[2.1792869568,41.4429359436],"type":"Point"}
}