{
  "type": "Feature",
  "properties": {
    "addr:full":"Calle de General Saliquet, 10 Madrid Madrid 28044",
    "addr:housenumber":"10",
    "addr:postcode":"madrid;28044",
    "addr:street":"Calle De General Saliquet",
    "iso:country":"ES",
    "sg:address":"Calle de General Saliquet, 10",
    "sg:city":"Madrid",
    "sg:orig_category":"Alimentaci\u00d3n General (al Por Menor)",
    "sg:phone":"+34 917 06 61 13",
    "sg:postcode":"28044",
    "sg:province":"Madrid",
    "wof:name":"Carvajal Garcia Julian",
    "wof:placetype":"venue"
},
  "geometry": {"coordinates":[-3.7750470638,40.3766326904],"type":"Point"}
}