{
  "type": "Feature",
  "properties": {
    "iso:country":"ES",
    "sg:address":"Calle de Fernando El Catolico, 61",
    "sg:city":"Madrid",
    "sg:orig_category":"Caf\u00c9s, Bares, Cervecer\u00cdas",
    "sg:phone":"+34 915 49 30 62",
    "sg:postcode":"28015",
    "sg:province":"Madrid",
    "wof:name":"Gallego Arias Nazario",
    "wof:placetype":"venue"
},
  "geometry": {"coordinates":[-3.7146954536,40.4343528748],"type":"Point"}
}