{
  "type": "Feature",
  "properties": {
    "iso:country":"ES",
    "sg:address":"Avda Lourdes, S/n",
    "sg:city":"Arenas San Pedro",
    "sg:orig_category":"Ense\u00d1anza Secundaria: Colegios Y Escuelas Privadas",
    "sg:phone":"+34 920 37 00 56",
    "sg:postcode":"05400",
    "sg:province":"\u00c1vila",
    "wof:name":"Instituto De Bachillerato Juana De Pimentel-m Educacion Ciencia",
    "wof:placetype":"venue"
},
  "geometry": {"coordinates":[-5.0844602585,40.2106819153],"type":"Point"}
}