{
  "type": "Feature",
  "properties": {
    "addr:full":"Calle de Eos, 6 Torrejon Ardoz Madrid 28850",
    "addr:housenumber":"6",
    "addr:postcode":"28850",
    "addr:street":"Calle De Eos",
    "iso:country":"ES",
    "sg:address":"Calle de Eos, 6",
    "sg:city":"Torrejon Ardoz",
    "sg:orig_category":"Panader\u00cdas, Panader\u00cdas",
    "sg:phone":"+34 916 56 94 46",
    "sg:postcode":"28850",
    "sg:province":"Madrid",
    "wof:name":"Dodu  Marinel",
    "wof:placetype":"venue"
},
  "geometry": {"coordinates":[-3.4763290882,40.4592514038],"type":"Point"}
}