{
  "type": "Feature",
  "properties": {
    "addr:full":"Ctra Paradas-arahal, S/n Paradas Sevilla 41610",
    "addr:housenumber":"s",
    "addr:postcode":"41610",
    "addr:street":"Ctra Paradas-Arahal;/ N Paradas",
    "iso:country":"ES",
    "sg:address":"Ctra Paradas-arahal, S/n",
    "sg:city":"Paradas",
    "sg:orig_category":"Papel (al Por Mayor)",
    "sg:phone":"+34 955 84 49 07",
    "sg:postcode":"41610",
    "sg:province":"Sevilla",
    "sg:website":"www.gomacamps.com",
    "wof:name":"Goma-camps S.a.",
    "wof:placetype":"venue"
},
  "geometry": {"coordinates":[-5.4962830544,37.290561676],"type":"Point"}
}