{
  "type": "Feature",
  "properties": {
    "addr:full":"Calle de Teniente General Gutierrez Mellado, S/n Fama Murcia 30008",
    "addr:housenumber":"s / n",
    "addr:postcode":"30008",
    "addr:street":"Calle De Teniente General Gutierrez Mellado",
    "iso:country":"ES",
    "sg:address":"Calle de Teniente General Gutierrez Mellado, S/n",
    "sg:city":"Fama",
    "sg:orig_category":"Agencias Y Agentes Comerciales, Representantes",
    "sg:phone":"+34 968 23 01 90",
    "sg:postcode":"30008",
    "sg:province":"Murcia",
    "wof:name":"Comercial Rodenas C.b.",
    "wof:placetype":"venue"
},
  "geometry": {"coordinates":[-1.1283069849,37.9897270203],"type":"Point"}
}