{
  "type": "Feature",
  "properties": {
    "addr:full":"Calle de Zubiaurre, 12 Iurreta Vizcaya 48215",
    "addr:housenumber":"12",
    "addr:postcode":"48215",
    "addr:street":"Calle De Zubiaurre",
    "iso:country":"ES",
    "sg:address":"Calle de Zubiaurre, 12",
    "sg:city":"Iurreta",
    "sg:orig_category":"Ense\u00d1anza, Formaci\u00d3n Profesional: Aprendizaje",
    "sg:phone":"+34 946 81 12 96",
    "sg:postcode":"48215",
    "sg:province":"Vizcaya",
    "wof:name":"Servicio Publico De Empleo Estatal-dron. Prov. Bizkaia",
    "wof:placetype":"venue"
},
  "geometry": {"coordinates":[-2.6373159885,43.1737594604],"type":"Point"}
}