{
  "type": "Feature",
  "properties": {
    "iso:country":"ES",
    "sg:address":"Carrer de Primer De Maig, 3",
    "sg:city":"Crevillent",
    "sg:orig_category":"Zapatos (al Por Menor)",
    "sg:phone":"+34 965 40 04 33",
    "sg:postcode":"03330",
    "sg:province":"Alicante",
    "wof:name":"Adan Macia Maria Teresa",
    "wof:placetype":"venue"
},
  "geometry": {"coordinates":[-0.81001091,38.2479019165],"type":"Point"}
}