{
  "type": "Feature",
  "properties": {
    "iso:country":"ES",
    "sg:address":"Carrer de Sant Pere, 12",
    "sg:city":"Rubi",
    "sg:orig_category":"Centros De Educaci\u00d3n Especial",
    "sg:phone":"+34 936 99 08 31",
    "sg:postcode":"08191",
    "sg:province":"Barcelona",
    "wof:name":"Co%egi Schola",
    "wof:placetype":"venue"
},
  "geometry": {"coordinates":[2.0326550007,41.4899749756],"type":"Point"}
}