{
  "type": "Feature",
  "properties": {
    "iso:country":"ES",
    "sg:address":"Av. Andalucia",
    "sg:city":"Malaga",
    "sg:orig_category":"M\u00c9dicos: Radiolog\u00cda (radiodiagn\u00d3stico E Im\u00c1genes En Medicina)",
    "sg:phone":"+34 952 34 59 30",
    "sg:postcode":"29006",
    "sg:province":"M\u00e1laga",
    "wof:name":"Centro De Diagnostico Scanner S.a.",
    "wof:placetype":"venue"
},
  "geometry": {"coordinates":[-4.4274520874,36.7161445618],"type":"Point"}
}