{
  "type": "Feature",
  "properties": {
    "iso:country":"ES",
    "sg:address":"Avda Principe De Asturias, 15",
    "sg:city":"Cuevas Reyllo",
    "sg:orig_category":"Material Y Herramientas Agr\u00cdcolas",
    "sg:phone":"+34 968 15 12 44",
    "sg:postcode":"30333",
    "sg:province":"Murcia",
    "wof:name":"Gomez Pagan Isabel Maria",
    "wof:placetype":"venue"
},
  "geometry": {"coordinates":[-1.2451150417,37.7358093262],"type":"Point"}
}