{
  "type": "Feature",
  "properties": {
    "iso:country":"ES",
    "sg:address":"Rond Prado, 105",
    "sg:city":"Villamayor De Campos",
    "sg:orig_category":"Cr\u00cda De Animales",
    "sg:phone":"+34 980 66 27 87",
    "sg:postcode":"49131",
    "sg:province":"Zamora",
    "wof:name":"Cepeda Gonzalez Manuel Fernando",
    "wof:placetype":"venue"
},
  "geometry": {"coordinates":[-5.3580880165,41.8985176086],"type":"Point"}
}