{
  "type": "Feature",
  "properties": {
    "addr:full":"Vista Bella, 11 Aizoain Navarra 31195",
    "addr:housenumber":"11",
    "addr:postcode":"31195",
    "addr:street":"Vista Bella",
    "iso:country":"ES",
    "sg:address":"Vista Bella, 11",
    "sg:city":"Aizoain",
    "sg:orig_category":"Autob\u00das (explotaci\u00d3n Y Servicios De)",
    "sg:phone":"+34 948 30 26 23",
    "sg:postcode":"31195",
    "sg:province":"Navarra",
    "wof:name":"Autobuses La Muguiroarra Sociedad Anonima",
    "wof:placetype":"venue"
},
  "geometry": {"coordinates":[-1.6858575344,42.8433761597],"type":"Point"}
}