{
  "type": "Feature",
  "properties": {
    "addr:full":"Calle de Sibelius, 26 Malaga M\u00e1laga 29016",
    "addr:housenumber":"26",
    "addr:postcode":"29016",
    "addr:street":"Calle De Sibelius;Ma\u0301Laga",
    "iso:country":"ES",
    "sg:address":"Calle de Sibelius, 26",
    "sg:city":"Malaga",
    "sg:orig_category":"Doctores En Medicina",
    "sg:phone":"+34 952 20 01 27",
    "sg:postcode":"29016",
    "sg:province":"M\u00e1laga",
    "wof:name":"Guerrero Zamorano Rafael Damian",
    "wof:placetype":"venue"
},
  "geometry": {"coordinates":[-4.3915739059,36.7262001038],"type":"Point"}
}