{
  "type": "Feature",
  "properties": {
    "addr:full":"Carrer de Codols, 21 Barcelona Barcelona 08002",
    "addr:housenumber":"21",
    "addr:postcode":"08002",
    "addr:street":"Carrer De Codols",
    "iso:country":"ES",
    "sg:address":"Carrer de Codols, 21",
    "sg:city":"Barcelona",
    "sg:orig_category":"Caf\u00c9s, Bares, Cervecer\u00cdas",
    "sg:phone":"+34 933 02 00 74",
    "sg:postcode":"08002",
    "sg:province":"Barcelona",
    "wof:name":"Estereo Grup S.c.p.",
    "wof:placetype":"venue"
},
  "geometry": {"coordinates":[2.1786260605,41.3795166016],"type":"Point"}
}