{
  "type": "Feature",
  "properties": {
    "iso:country":"ES",
    "sg:address":"Pda Monte Horquera, 232",
    "sg:city":"Vilamarxant",
    "sg:orig_category":"Agencias Y Agentes Comerciales, Representantes",
    "sg:phone":"+34 962 13 30 54",
    "sg:postcode":"46191",
    "sg:province":"Valencia",
    "wof:name":"Mu\u00f1oza Carneros Maximiliano De La",
    "wof:placetype":"venue"
},
  "geometry": {"coordinates":[-0.6272540092,39.5677604675],"type":"Point"}
}