{
  "type": "Feature",
  "properties": {
    "iso:country":"ES",
    "sg:address":"Carr Pelegri Ballester, 23",
    "sg:city":"Vilanova I La Geltru",
    "sg:orig_category":"Ropa Para Se\u00d1oras Y Caballeros (al Por Menor)",
    "sg:phone":"+34 938 15 78 27",
    "sg:postcode":"08800",
    "sg:province":"Barcelona",
    "wof:name":"Unilen S.a.",
    "wof:placetype":"venue"
},
  "geometry": {"coordinates":[1.7203329802,41.2214622498],"type":"Point"}
}