{
  "type": "Feature",
  "properties": {
    "iso:country":"ES",
    "sg:address":"Avda Vicalvaro (de), S/n",
    "sg:city":"Coslada",
    "sg:orig_category":"Alimentaci\u00d3n General (al Por Menor)",
    "sg:phone":"+34 916 71 40 20",
    "sg:postcode":"28820",
    "sg:province":"Madrid",
    "wof:name":"Bernabe Morera Bonifacio",
    "wof:placetype":"venue"
},
  "geometry": {"coordinates":[-3.5426540375,40.4154663086],"type":"Point"}
}