{
  "type": "Feature",
  "properties": {
    "iso:country":"ES",
    "sg:address":"Rua Alfredo Bra\u00d1as (de), 7",
    "sg:city":"Santiago De Compostela",
    "sg:orig_category":"Abogados",
    "sg:phone":"+34 981 58 93 62",
    "sg:postcode":"15701",
    "sg:province":"La Coru\u00f1a",
    "wof:name":"Morgadas Lago Blanca Aurora",
    "wof:placetype":"venue"
},
  "geometry": {"coordinates":[-8.5474033356,42.8749313354],"type":"Point"}
}