{
  "type": "Feature",
  "properties": {
    "addr:full":"Calle de Marques De Lema, 46 Alcorisa Teruel 44550",
    "addr:housenumber":"46",
    "addr:postcode":"44550",
    "addr:street":"Calle De Marques De Lema",
    "iso:country":"ES",
    "sg:address":"Calle de Marques De Lema, 46",
    "sg:city":"Alcorisa",
    "sg:orig_category":"Centros De Adelgazamiento Y De Est\u00c9tica",
    "sg:phone":"+34 978 84 10 18",
    "sg:postcode":"44550",
    "sg:province":"Teruel",
    "wof:name":"Nuez Palos Mario",
    "wof:placetype":"venue"
},
  "geometry": {"coordinates":[-0.3840349913,40.8908538818],"type":"Point"}
}