{
  "type": "Feature",
  "properties": {
    "iso:country":"ES",
    "sg:address":"Calle de Consuelo Guzman, 15",
    "sg:city":"Madrid",
    "sg:orig_category":"Venta, Instalaci\u00d3n, Reparaci\u00d3n De Antenas Para Televisi\u00d3n",
    "sg:phone":"+34 915 08 62 78",
    "sg:postcode":"28044",
    "sg:province":"Madrid",
    "wof:name":"Antelsat S.l.",
    "wof:placetype":"venue"
},
  "geometry": {"coordinates":[-3.753875494,40.3758468628],"type":"Point"}
}