{
  "type": "Feature",
  "properties": {
    "iso:country":"ES",
    "sg:address":"Rua Enrique X. Macias, 7",
    "sg:city":"Vigo",
    "sg:orig_category":"Distribuci\u00d3n De Petr\u00d3leo Y Derivados",
    "sg:phone":"+34 986 49 32 26",
    "sg:postcode":"36203",
    "sg:province":"Pontevedra",
    "wof:name":"Molugel S.l.",
    "wof:placetype":"venue"
},
  "geometry": {"coordinates":[-8.7261734009,42.2271728516],"type":"Point"}
}