{
  "type": "Feature",
  "properties": {
    "iso:country":"ES",
    "sg:address":"Calle de Jeronima Llorente, 48",
    "sg:city":"Madrid",
    "sg:orig_category":"Promotores Constructores",
    "sg:phone":"+34 914 59 18 03",
    "sg:postcode":"28039",
    "sg:province":"Madrid",
    "wof:name":"Tejera Ferrao Juan Francisco",
    "wof:placetype":"venue"
},
  "geometry": {"coordinates":[-3.7080368996,40.453792572],"type":"Point"}
}