{
  "type": "Feature",
  "properties": {
    "addr:full":"Calle de Herri Bide, 11 Mungia Vizcaya 48100",
    "addr:housenumber":"11",
    "addr:postcode":"48100",
    "addr:street":"Calle De Herri Bide",
    "iso:country":"ES",
    "sg:address":"Calle de Herri Bide, 11",
    "sg:city":"Mungia",
    "sg:orig_category":"Empresarios",
    "sg:phone":"+34 946 15 59 35",
    "sg:postcode":"48100",
    "sg:province":"Vizcaya",
    "wof:name":"Jon Vander Y Otro C.b",
    "wof:placetype":"venue"
},
  "geometry": {"coordinates":[-2.8437957764,43.3551216125],"type":"Point"}
}