{
  "type": "Feature",
  "properties": {
    "iso:country":"ES",
    "sg:address":"Carrer de Misericordia, 6",
    "sg:city":"Reus",
    "sg:orig_category":"Muebles, Minoristas",
    "sg:phone":"+34 977 75 48 58",
    "sg:postcode":"43205",
    "sg:province":"Tarragona",
    "wof:name":"Valero Iba\u00f1es Joan",
    "wof:placetype":"venue"
},
  "geometry": {"coordinates":[1.1087009907,41.1524543762],"type":"Point"}
}