{
  "type": "Feature",
  "properties": {
    "iso:country":"ES",
    "sg:address":"Calle de Godino, 9",
    "sg:city":"Malaga",
    "sg:orig_category":"Asociaciones Humanitarias, De Cooperaci\u00d3n, De Acci\u00d3n Social",
    "sg:phone":"+34 952 27 40 40",
    "sg:postcode":"29009",
    "sg:province":"M\u00e1laga",
    "wof:name":"Asociacion Sindrome De Down De Malaga Nueva Esperanza",
    "wof:placetype":"venue"
},
  "geometry": {"coordinates":[-4.4292526245,36.7307815552],"type":"Point"}
}