{
  "type": "Feature",
  "properties": {
    "addr:full":"Calle de Ancha, 1 Calzada Calatrava Ciudad Real 13370",
    "addr:housenumber":"1",
    "addr:postcode":"13370",
    "addr:street":"Calle De Ancha",
    "iso:country":"ES",
    "sg:address":"Calle de Ancha, 1",
    "sg:city":"Calzada Calatrava",
    "sg:orig_category":"Fabricaci\u00d3n De Tapices Y Moquetas Para Suelos Y Paredes",
    "sg:phone":"+34 926 87 51 27",
    "sg:postcode":"13370",
    "sg:province":"Ciudad Real",
    "wof:name":"Pavifort Y Dacal S.l.",
    "wof:placetype":"venue"
},
  "geometry": {"coordinates":[-3.7769942284,38.7086639404],"type":"Point"}
}