{
  "type": "Feature",
  "properties": {
    "addr:full":"Calle de Rector Tovar, 1 Salamanca Salamanca 37002",
    "addr:housenumber":"1",
    "addr:postcode":"37002",
    "addr:street":"Calle De Rector Tovar",
    "iso:country":"ES",
    "sg:address":"Calle de Rector Tovar, 1",
    "sg:city":"Salamanca",
    "sg:orig_category":"Molduras, Junquillos, Listones Y Molduras Perforadas",
    "sg:phone":"+34 923 21 26 31",
    "sg:postcode":"37002",
    "sg:province":"Salamanca",
    "wof:name":"Mori\u00f1igo Calais Alexis",
    "wof:placetype":"venue"
},
  "geometry": {"coordinates":[-5.6629581451,40.9671897888],"type":"Point"}
}