{
  "type": "Feature",
  "properties": {
    "addr:full":"Calle de Cristobal Colon, 24 Pilas Sevilla 41840",
    "addr:housenumber":"24",
    "addr:postcode":"41840",
    "addr:street":"Calle De Cristobal Colon",
    "iso:country":"ES",
    "sg:address":"Calle de Cristobal Colon, 24",
    "sg:city":"Pilas",
    "sg:orig_category":"Mec\u00c1nico Del Autom\u00d3vil",
    "sg:phone":"+34 954 75 02 62",
    "sg:postcode":"41840",
    "sg:province":"Sevilla",
    "wof:name":"Ruiz Valladares Manuel",
    "wof:placetype":"venue"
},
  "geometry": {"coordinates":[-6.295735836,37.3032302856],"type":"Point"}
}