{
  "type": "Feature",
  "properties": {
    "addr:full":"Avda Garcia Si\u00d1eriz, 5 Miajadas C\u00e1ceres 10100",
    "addr:housenumber":"5",
    "addr:postcode":"10100",
    "addr:street":"Avda Garcia Sin\u0303Eriz;Ca\u0301Ceres",
    "iso:country":"ES",
    "sg:address":"Avda Garcia Si\u00d1eriz, 5",
    "sg:city":"Miajadas",
    "sg:orig_category":"Promotores Constructores",
    "sg:phone":"+34 927 34 75 44",
    "sg:postcode":"10100",
    "sg:province":"C\u00e1ceres",
    "wof:name":"Construcciones Eugenio Ruiz S.l.",
    "wof:placetype":"venue"
},
  "geometry": {"coordinates":[-5.9193902016,39.1453285217],"type":"Point"}
}