{
  "type": "Feature",
  "properties": {
    "iso:country":"ES",
    "sg:address":"Rua Horreo (do), 166",
    "sg:city":"Santiago De Compostela",
    "sg:orig_category":"Muebles Y Accesorios Para Cocinas Y Cuartos De Ba\u00d1o (al Por Menor)",
    "sg:phone":"+34 981 59 40 18",
    "sg:postcode":"15702",
    "sg:province":"La Coru\u00f1a",
    "wof:name":"Decox S.a.",
    "wof:placetype":"venue"
},
  "geometry": {"coordinates":[-8.5469141006,42.8703460693],"type":"Point"}
}