{
  "type": "Feature",
  "properties": {
    "addr:full":"Pso. Milana, S/n Priego Cordoba C\u00f3rdoba 14800",
    "addr:housenumber":"s",
    "addr:postcode":"14800",
    "addr:street":"Milana;/ N Priego Cordoba Co\u0301Rdoba",
    "iso:country":"ES",
    "sg:address":"Pso. Milana, S/n",
    "sg:city":"Priego Cordoba",
    "sg:orig_category":"Distribuci\u00d3n De Petr\u00d3leo Y Derivados",
    "sg:phone":"+34 957 54 22 44",
    "sg:postcode":"14800",
    "sg:province":"C\u00f3rdoba",
    "wof:name":"Rafael Ruiz Amores S.l.",
    "wof:placetype":"venue"
},
  "geometry": {"coordinates":[-4.215490818,37.4418144226],"type":"Point"}
}