{
  "type": "Feature",
  "properties": {
    "addr:full":"Calle de Alvarez De Castro, 34 Almeria Almer\u00eda 04002",
    "addr:housenumber":"34",
    "addr:postcode":"04002",
    "addr:street":"Calle De Alvarez De Castro",
    "iso:country":"ES",
    "sg:address":"Calle de Alvarez De Castro, 34",
    "sg:city":"Almeria",
    "sg:orig_category":"Laboratorios Y Trabajos De Fotograf\u00cda, V\u00cddeo Y Cine",
    "sg:phone":"+34 950 26 47 96",
    "sg:postcode":"04002",
    "sg:province":"Almer\u00eda",
    "wof:name":"Chaib  Khaled",
    "wof:placetype":"venue"
},
  "geometry": {"coordinates":[-2.4654593468,36.8357391357],"type":"Point"}
}