{
  "type": "Feature",
  "properties": {
    "addr:full":"Avda Santalla De Oscos, 32 Toral De Los Vados Le\u00f3n 24560",
    "addr:housenumber":"32",
    "addr:postcode":"24560",
    "addr:street":"Avda Santalla De Oscos",
    "iso:country":"ES",
    "sg:address":"Avda Santalla De Oscos, 32",
    "sg:city":"Toral De Los Vados",
    "sg:orig_category":"Asesor\u00cda Sobre Comunicaci\u00d3n De Empresas",
    "sg:phone":"+34 987 54 53 25",
    "sg:postcode":"24560",
    "sg:province":"Le\u00f3n",
    "wof:name":"Asesoria Toral S.l.",
    "wof:placetype":"venue"
},
  "geometry": {"coordinates":[-6.7749547958,42.5455780029],"type":"Point"}
}