{
  "type": "Feature",
  "properties": {
    "iso:country":"ES",
    "sg:address":"Cra Cordoba-malaga-p I Las Palomas, Km. 0474,0",
    "sg:city":"Lucena",
    "sg:orig_category":"Papeler\u00cdas: Art\u00cdculos (al Por Mayor)",
    "sg:phone":"+34 957 51 12 42",
    "sg:postcode":"14900",
    "sg:province":"C\u00f3rdoba",
    "wof:name":"A-4 Oficinas S.l.u.",
    "wof:placetype":"venue"
},
  "geometry": {"coordinates":[-4.541814,37.359844],"type":"Point"}
}