{
  "type": "Feature",
  "properties": {
    "addr:full":"Villaverde, 18 Villaverde Pontones Cantabria 39793",
    "addr:housenumber":"18",
    "addr:postcode":"39793",
    "addr:street":"Villaverde",
    "iso:country":"ES",
    "sg:address":"Villaverde, 18",
    "sg:city":"Villaverde Pontones",
    "sg:orig_category":"Estancos",
    "sg:phone":"+34 942 50 82 77",
    "sg:postcode":"39793",
    "sg:province":"Cantabria",
    "wof:name":"Fernandez Perez Maria Mercedes",
    "wof:placetype":"venue"
},
  "geometry": {"coordinates":[-3.6982638836,43.4129295349],"type":"Point"}
}