{
  "type": "Feature",
  "properties": {
    "addr:full":"Calle de Rafael Quintana Rosado, 16 Torremolinos M\u00e1laga 29620",
    "addr:housenumber":"16",
    "addr:postcode":"29620",
    "addr:street":"Calle De Rafael Quintana Rosado;Ma\u0301Laga",
    "iso:country":"ES",
    "sg:address":"Calle de Rafael Quintana Rosado, 16",
    "sg:city":"Torremolinos",
    "sg:orig_category":"Ropa Para Se\u00d1oras Y Caballeros (al Por Menor)",
    "sg:phone":"+34 952 38 17 48",
    "sg:postcode":"29620",
    "sg:province":"M\u00e1laga",
    "wof:name":"Gonzalez Ruiz Rafael",
    "wof:placetype":"venue"
},
  "geometry": {"coordinates":[-4.50563097,36.6223335266],"type":"Point"}
}