{
  "type": "Feature",
  "properties": {
    "addr:full":"Carr Nuno San\u00c7, 12 Felanitx Islas Baleares 07200",
    "addr:housenumber":"12",
    "addr:postcode":"07200",
    "addr:street":"Carr Nuno Sanc\u0327",
    "iso:country":"ES",
    "sg:address":"Carr Nuno San\u00c7, 12",
    "sg:city":"Felanitx",
    "sg:orig_category":"Armas Y Municiones (fabricaci\u00d3n, Al Por Mayor)",
    "sg:phone":"+34 971 58 29 60",
    "sg:postcode":"07200",
    "sg:province":"Islas Baleares",
    "wof:name":"Fiol Vadell Juan",
    "wof:placetype":"venue"
},
  "geometry": {"coordinates":[3.1477410793,39.4687652588],"type":"Point"}
}