{
  "type": "Feature",
  "properties": {
    "addr:full":"Carrer de Sant Jaume, 31 Esparreguera Barcelona 08292",
    "addr:housenumber":"31",
    "addr:postcode":"08292",
    "addr:street":"Carrer De Sant Jaume",
    "iso:country":"ES",
    "sg:address":"Carrer de Sant Jaume, 31",
    "sg:city":"Esparreguera",
    "sg:orig_category":"Centros Empresariales",
    "sg:phone":"+34 937 77 32 19",
    "sg:postcode":"08292",
    "sg:province":"Barcelona",
    "wof:name":"Uea Consulting S.l.",
    "wof:placetype":"venue"
},
  "geometry": {"coordinates":[1.8705439568,41.540271759],"type":"Point"}
}