{
  "type": "Feature",
  "properties": {
    "iso:country":"ES",
    "sg:address":"Egipto, 9",
    "sg:city":"Boiro",
    "sg:orig_category":"Alimentaci\u00d3n General (al Por Menor)",
    "sg:phone":"+34 981 84 97 46",
    "sg:postcode":"15930",
    "sg:province":"La Coru\u00f1a",
    "wof:name":"Alonso Fernandez Marcelino",
    "wof:placetype":"venue"
},
  "geometry": {"coordinates":[-8.9355735779,42.6803779602],"type":"Point"}
}