{
  "type": "Feature",
  "properties": {
    "iso:country":"ES",
    "sg:address":"Calle de Marques De Urquijo, 45",
    "sg:city":"Madrid",
    "sg:orig_category":"Inversiones",
    "sg:phone":"+34 915 41 18 57",
    "sg:postcode":"28008",
    "sg:province":"Madrid",
    "wof:name":"Quetzal Marigil S.a",
    "wof:placetype":"venue"
},
  "geometry": {"coordinates":[-3.7210988998,40.4289321899],"type":"Point"}
}