{
  "type": "Feature",
  "properties": {
    "iso:country":"ES",
    "sg:address":"Kale Nagusia, 23",
    "sg:city":"Etxarri-aranatz",
    "sg:orig_category":"Molduras, Junquillos, Listones Y Molduras Perforadas",
    "sg:phone":"+34 948 46 12 28",
    "sg:postcode":"31820",
    "sg:province":"Navarra",
    "wof:name":"Asociacion Bierrik",
    "wof:placetype":"venue"
},
  "geometry": {"coordinates":[-2.0647878647,42.9075889587],"type":"Point"}
}