{
  "type": "Feature",
  "properties": {
    "iso:country":"ES",
    "sg:address":"Rua Dr. Cadaval, 21",
    "sg:city":"Vigo",
    "sg:orig_category":"Abogados",
    "sg:phone":"+34 986 22 75 86",
    "sg:postcode":"36202",
    "sg:province":"Pontevedra",
    "wof:name":"Rios Garcia Margarita",
    "wof:placetype":"venue"
},
  "geometry": {"coordinates":[-8.7241945267,42.2364425659],"type":"Point"}
}