{
  "type": "Feature",
  "properties": {
    "addr:full":"Pol De As Gandaras, S/n Poligono De Gandaras Pontevedra 36475",
    "addr:housenumber":"s / n",
    "addr:postcode":"36475",
    "iso:country":"ES",
    "sg:address":"Pol De As Gandaras, S/n",
    "sg:city":"Poligono De Gandaras",
    "sg:orig_category":"Armaduras De Hormig\u00d3n",
    "sg:phone":"+34 986 34 62 69",
    "sg:postcode":"36475",
    "sg:province":"Pontevedra",
    "wof:name":"Productos Y Sistemas Aplicados S. A.",
    "wof:placetype":"venue"
},
  "geometry": {"coordinates":[-8.606926918,42.1053466797],"type":"Point"}
}