{
  "type": "Feature",
  "properties": {
    "iso:country":"ES",
    "sg:address":"Carr Carme, 103",
    "sg:city":"Girona",
    "sg:orig_category":"Asesor\u00cda Sobre Comunicaci\u00d3n De Empresas",
    "sg:phone":"+34 972 22 47 00",
    "sg:postcode":"17004",
    "sg:province":"Girona",
    "wof:name":"Nous Tramits S.l.",
    "wof:placetype":"venue"
},
  "geometry": {"coordinates":[2.8244259357,41.9775810242],"type":"Point"}
}