{
  "type": "Feature",
  "properties": {
    "addr:full":"Ctra Palmar, 303 Barracas Murcia 30152",
    "addr:housenumber":"303",
    "addr:postcode":"30152",
    "addr:street":"Ctra Palmar",
    "iso:country":"ES",
    "sg:address":"Ctra Palmar, 303",
    "sg:city":"Barracas",
    "sg:orig_category":"Negocio De Materiales De Construcci\u00d3n",
    "sg:phone":"+34 968 34 40 54",
    "sg:postcode":"30152",
    "sg:province":"Murcia",
    "wof:name":"Miralles Azulejos Y Gres S.l",
    "wof:placetype":"venue"
},
  "geometry": {"coordinates":[-1.1452490091,37.9643058777],"type":"Point"}
}