{
  "type": "Feature",
  "properties": {
    "addr:full":"Baja Navarra, 7 Estella Navarra 31200",
    "addr:housenumber":"7",
    "addr:postcode":"31200",
    "addr:street":"Navarra",
    "iso:country":"ES",
    "sg:address":"Baja Navarra, 7",
    "sg:city":"Estella",
    "sg:orig_category":"Farmacias",
    "sg:phone":"+34 948 55 02 31",
    "sg:postcode":"31200",
    "sg:province":"Navarra",
    "wof:name":"Goyache Sainz De Vicu\u00f1a Maria Del Mar",
    "wof:placetype":"venue"
},
  "geometry": {"coordinates":[-2.0291230679,42.6709899902],"type":"Point"}
}