{
  "type": "Feature",
  "properties": {
    "iso:country":"ES",
    "sg:address":"Calle de Carretera De Brenes, Km. 0012,0",
    "sg:city":"Carmona",
    "sg:orig_category":"Explosivos",
    "sg:phone":"+34 955 95 36 50",
    "sg:postcode":"41410",
    "sg:province":"Sevilla",
    "wof:name":"Mp Medioambiente S.l.",
    "wof:placetype":"venue"
},
  "geometry": {"coordinates":[-5.6449589729,37.4738731384],"type":"Point"}
}