{
  "type": "Feature",
  "properties": {
    "iso:country":"ES",
    "sg:address":"Calle de Antonio Lopez, 57",
    "sg:city":"Madrid",
    "sg:orig_category":"Agencias Y Agentes Comerciales, Representantes",
    "sg:phone":"+34 914 69 54 45",
    "sg:postcode":"28019",
    "sg:province":"Madrid",
    "wof:name":"Bernal Moreno Victoria De Los Angeles",
    "wof:placetype":"venue"
},
  "geometry": {"coordinates":[-3.7090189457,40.3947372437],"type":"Point"}
}