{
  "type": "Feature",
  "properties": {
    "addr:full":"Calle de Mar Artico, 6 Caceres C\u00e1ceres 10005",
    "addr:housenumber":"6",
    "addr:postcode":"10005",
    "addr:street":"Calle De Mar Artico;Ca\u0301Ceres",
    "iso:country":"ES",
    "sg:address":"Calle de Mar Artico, 6",
    "sg:city":"Caceres",
    "sg:orig_category":"Bebidas",
    "sg:phone":"+34 927 22 70 77",
    "sg:postcode":"10005",
    "sg:province":"C\u00e1ceres",
    "wof:name":"Comercial De Bebidas De Caceres S.l.",
    "wof:placetype":"venue"
},
  "geometry": {"coordinates":[-6.3668828011,39.4536247253],"type":"Point"}
}