{
  "type": "Feature",
  "properties": {
    "iso:country":"ES",
    "sg:address":"Pol. Ind. Castellanos, S/n",
    "sg:city":"Castellanos Moriscos",
    "sg:orig_category":"Congelados: Productos Alimentarios (al Por Menor)",
    "sg:phone":"+34 923 36 15 49",
    "sg:postcode":"37439",
    "sg:province":"Salamanca",
    "sg:website":"www.lapolar.net",
    "wof:name":"Helados La Polar S.l.",
    "wof:placetype":"venue"
},
  "geometry": {"coordinates":[-5.5927238464,41.0200881958],"type":"Point"}
}