{
  "type": "Feature",
  "properties": {
    "addr:full":"Carr Doctor Casals, 75 Santa Cristina D'aro Girona 17246",
    "addr:housenumber":"75",
    "addr:postcode":"17246",
    "addr:street":"Carr Doctor Casals",
    "iso:country":"ES",
    "sg:address":"Carr Doctor Casals, 75",
    "sg:city":"Santa Cristina D'aro",
    "sg:orig_category":"Mec\u00c1nico Del Autom\u00d3vil",
    "sg:phone":"+34 972 83 78 73",
    "sg:postcode":"17246",
    "sg:province":"Girona",
    "wof:name":"Autotaller Ridaura S.c.",
    "wof:placetype":"venue"
},
  "geometry": {"coordinates":[2.9974689484,41.8135070801],"type":"Point"}
}