{
  "type": "Feature",
  "properties": {
    "addr:full":"Col. Sto. Duque, 1 Grao Gandia Valencia 46730",
    "addr:housenumber":"1",
    "addr:postcode":"46730",
    "addr:street":"Col.;Duque",
    "iso:country":"ES",
    "sg:address":"Col. Sto. Duque, 1",
    "sg:city":"Grao Gandia",
    "sg:orig_category":"Molduras, Junquillos, Listones Y Molduras Perforadas",
    "sg:phone":"+34 962 84 19 94",
    "sg:postcode":"46730",
    "sg:province":"Valencia",
    "wof:name":"Martinez Castro Antonio",
    "wof:placetype":"venue"
},
  "geometry": {"coordinates":[-0.1664949954,38.9994888306],"type":"Point"}
}