{
  "type": "Feature",
  "properties": {
    "addr:full":"Carr Castanyers, 29 Vilanova I La Geltru Barcelona 08800",
    "addr:housenumber":"29",
    "addr:postcode":"08800",
    "addr:street":"Carr Castanyers",
    "iso:country":"ES",
    "sg:address":"Carr Castanyers, 29",
    "sg:city":"Vilanova I La Geltru",
    "sg:orig_category":"Productos Qu\u00cdmicos (fabricaci\u00d3n, Al Por Mayor)",
    "sg:phone":"+34 938 95 31 50",
    "sg:postcode":"08800",
    "sg:province":"Barcelona",
    "wof:name":"Petro Import S.l.",
    "wof:placetype":"venue"
},
  "geometry": {"coordinates":[1.6825549603,41.220413208],"type":"Point"}
}