{
  "type": "Feature",
  "properties": {
    "addr:full":"Carrer de Can Fosalba, 7 Mas D'en Gall Barcelona 08292",
    "addr:housenumber":"7",
    "addr:postcode":"08292",
    "addr:street":"Carrer De Can Fosalba;Barcelona",
    "iso:country":"ES",
    "sg:address":"Carrer de Can Fosalba, 7",
    "sg:city":"Mas D'en Gall",
    "sg:orig_category":"Negocio De Materiales De Construcci\u00d3n",
    "sg:phone":"+34 937 77 26 56",
    "sg:postcode":"08292",
    "sg:province":"Barcelona",
    "wof:name":"Materiales De Construccion Alert S.l.",
    "wof:placetype":"venue"
},
  "geometry": {"coordinates":[2.1699187756,41.3879165649],"type":"Point"}
}