{
  "type": "Feature",
  "properties": {
    "addr:full":"Calle de Pradolongo, 2 Madrid Madrid 28041",
    "addr:housenumber":"2",
    "addr:postcode":"28041",
    "addr:street":"Calle De Pradolongo",
    "iso:country":"ES",
    "sg:address":"Calle de Pradolongo, 2",
    "sg:city":"Madrid",
    "sg:orig_category":"Fabricaci\u00d3n De Peines Y De Accesorios De Peluquer\u00cda",
    "sg:phone":"+34 913 41 81 82",
    "sg:postcode":"28041",
    "sg:province":"Madrid",
    "wof:name":"Clar Distribuciones S.l.",
    "wof:placetype":"venue"
},
  "geometry": {"coordinates":[-3.7094020844,40.369392395],"type":"Point"}
}