{
  "type": "Feature",
  "properties": {
    "addr:full":"O Pazo, 3 Pazo Pontevedra 36655",
    "addr:housenumber":"3",
    "addr:postcode":"36655",
    "addr:street":"Pazo Pontevedra",
    "iso:country":"ES",
    "sg:address":"O Pazo, 3",
    "sg:city":"Pazo",
    "sg:orig_category":"Transportes Por V\u00cdas Navegables",
    "sg:phone":"+34 986 54 00 66",
    "sg:postcode":"36655",
    "sg:province":"Pontevedra",
    "wof:name":"Rizo Trans S.l.",
    "wof:placetype":"venue"
},
  "geometry": {"coordinates":[-8.6441202164,42.4047698975],"type":"Point"}
}