{
  "type": "Feature",
  "properties": {
    "iso:country":"ES",
    "sg:address":"Del Call, 1",
    "sg:city":"Castello Empuries",
    "sg:orig_category":"Lencer\u00cda Femenina, Corseter\u00cda, Trajes De Ba\u00d1o (al Por Menor)",
    "sg:phone":"+34 972 15 80 62",
    "sg:postcode":"17486",
    "sg:province":"Girona",
    "wof:name":"Nicolas Gol Sonia",
    "wof:placetype":"venue"
},
  "geometry": {"coordinates":[3.0764598846,42.2558937073],"type":"Point"}
}