{
  "type": "Feature",
  "properties": {
    "addr:full":"Calle de Hernan Cortes, 41 Santander Cantabria 39003",
    "addr:housenumber":"41",
    "addr:postcode":"39003",
    "addr:street":"Calle De Hernan Cortes",
    "iso:country":"ES",
    "sg:address":"Calle de Hernan Cortes, 41",
    "sg:city":"Santander",
    "sg:orig_category":"Panader\u00cdas, Panader\u00cdas",
    "sg:phone":"+34 942 21 59 57",
    "sg:postcode":"39003",
    "sg:province":"Cantabria",
    "wof:name":"Ruiz Vega Luis",
    "wof:placetype":"venue"
},
  "geometry": {"coordinates":[-3.7997779846,43.4630737305],"type":"Point"}
}