{
  "type": "Feature",
  "properties": {
    "addr:full":"Calle de Reyes, 7 Madrid Madrid 28015",
    "addr:housenumber":"7",
    "addr:postcode":"madrid;28015",
    "addr:street":"Calle De Reyes",
    "iso:country":"ES",
    "sg:address":"Calle de Reyes, 7",
    "sg:city":"Madrid",
    "sg:orig_category":"Cl\u00cdnicas Dentales",
    "sg:phone":"+34 915 24 04 12",
    "sg:postcode":"28015",
    "sg:province":"Madrid",
    "wof:name":"Campos Tristan Gerardo",
    "wof:placetype":"venue"
},
  "geometry": {"coordinates":[-3.7087299824,40.4241867065],"type":"Point"}
}