{
  "type": "Feature",
  "properties": {
    "addr:full":"Carrer de Clot, 218 Barcelona Barcelona 08027",
    "addr:housenumber":"218",
    "addr:postcode":"08027",
    "addr:street":"Carrer De Clot",
    "iso:country":"ES",
    "sg:address":"Carrer de Clot, 218",
    "sg:city":"Barcelona",
    "sg:orig_category":"Venta, Montaje De Neum\u00c1ticos",
    "sg:phone":"+34 933 40 41 32",
    "sg:postcode":"08027",
    "sg:province":"Barcelona",
    "wof:name":"Roldan Vargas Paulina",
    "wof:placetype":"venue"
},
  "geometry": {"coordinates":[2.1909890175,41.4147262573],"type":"Point"}
}