{
  "type": "Feature",
  "properties": {
    "addr:full":"Calle de Luis Doreste Silva, 95 Palmas De Gran Canaria Las Palmas 35004",
    "addr:housenumber":"95",
    "addr:postcode":"35004",
    "addr:street":"Calle De Luis Doreste Silva",
    "iso:country":"ES",
    "sg:address":"Calle de Luis Doreste Silva, 95",
    "sg:city":"Palmas De Gran Canaria",
    "sg:orig_category":"Promotores Constructores",
    "sg:phone":"+34 928 24 32 51",
    "sg:postcode":"35004",
    "sg:province":"Las Palmas",
    "wof:name":"Construcciones Y Edificios Especiales S. A.",
    "wof:placetype":"venue"
},
  "geometry": {"coordinates":[-15.4244785309,28.1195316315],"type":"Point"}
}