{
  "type": "Feature",
  "properties": {
    "iso:country":"ES",
    "sg:address":"Avda Principes De Espa\u00d1a, 7",
    "sg:city":"Santa Cruz De Tenerife",
    "sg:orig_category":"Agencias De Viajes",
    "sg:phone":"+34 922 65 26 40",
    "sg:postcode":"38010",
    "sg:province":"Santa Cruz De Tenerife",
    "wof:name":"Viajes Gomera S. L.",
    "wof:placetype":"venue"
},
  "geometry": {"coordinates":[-16.2855453491,28.4527206421],"type":"Point"}
}