{
  "type": "Feature",
  "properties": {
    "iso:country":"ES",
    "sg:address":"Plaz Virgen De La Victoria, 9",
    "sg:city":"Aldaia",
    "sg:orig_category":"Fabricaci\u00d3n De Transformadores, De M\u00c1quinas Giratorias De Peque\u00d1a Y Media Potencia",
    "sg:phone":"+34 961 51 03 59",
    "sg:postcode":"46960",
    "sg:province":"Valencia",
    "wof:name":"Rubber Rollers Iberica S.a.",
    "wof:placetype":"venue"
},
  "geometry": {"coordinates":[-0.4653890133,39.4629898071],"type":"Point"}
}