{
  "type": "Feature",
  "properties": {
    "iso:country":"ES",
    "sg:address":"Pl Major, 22",
    "sg:city":"Mollet Valles",
    "sg:orig_category":"Fabricaci\u00d3n, Importaci\u00d3n, Venta De Material De Telefon\u00cda, Peritelefon\u00cda",
    "sg:phone":"+34 935 44 51 20",
    "sg:postcode":"08100",
    "sg:province":"Barcelona",
    "wof:name":"Tdc 2000 Comunicaciones Globales Srl.",
    "wof:placetype":"venue"
},
  "geometry": {"coordinates":[2.2111039162,41.5358467102],"type":"Point"}
}