{
  "type": "Feature",
  "properties": {
    "iso:country":"ES",
    "sg:address":"Carr Doctor Vicente Buigues, 3",
    "sg:city":"Benissa",
    "sg:orig_category":"Supermercados Y Hipermercados",
    "sg:phone":"+34 965 73 16 40",
    "sg:postcode":"03720",
    "sg:province":"Alicante",
    "wof:name":"Juan Fornes Fornes S.a.",
    "wof:placetype":"venue"
},
  "geometry": {"coordinates":[0.0493640006,38.7152519226],"type":"Point"}
}