{
  "type": "Feature",
  "properties": {
    "iso:country":"ES",
    "sg:address":"Avda Castilla Leon, 38",
    "sg:city":"Campo Criptana",
    "sg:orig_category":"Postigos, Persianas Y Celos\u00cdas",
    "sg:phone":"+34 926 56 41 99",
    "sg:postcode":"13610",
    "sg:province":"Ciudad Real",
    "sg:website":"www.persianasolivares.com",
    "wof:name":"Persianas Olivares S.l.u.",
    "wof:placetype":"venue"
},
  "geometry": {"coordinates":[-3.1243391037,39.403339386],"type":"Point"}
}