{
  "type": "Feature",
  "properties": {
    "iso:country":"ES",
    "sg:address":"Avda Colon, 9",
    "sg:city":"Badajoz",
    "sg:orig_category":"Librer\u00cdas",
    "sg:phone":"+34 924 22 54 06",
    "sg:postcode":"06005",
    "sg:province":"Badajoz",
    "wof:name":"Casado Martin Jose Maria",
    "wof:placetype":"venue"
},
  "geometry": {"coordinates":[-6.976913929,38.8756027222],"type":"Point"}
}