{
  "type": "Feature",
  "properties": {
    "addr:full":"Avda Pirralos (los), 92 Dos Hermanas Sevilla 41700",
    "addr:housenumber":"92",
    "addr:postcode":"41700",
    "addr:street":"Avda Pirralos Los",
    "iso:country":"ES",
    "sg:address":"Avda Pirralos (los), 92",
    "sg:city":"Dos Hermanas",
    "sg:orig_category":"Desinfecci\u00d3n, Desinsectaci\u00d3n, Desratizaci\u00d3n",
    "sg:phone":"+34 954 72 50 81",
    "sg:postcode":"41700",
    "sg:province":"Sevilla",
    "wof:name":"Eurosur Ambiental S.l.",
    "wof:placetype":"venue"
},
  "geometry": {"coordinates":[-5.928592205,37.2758178711],"type":"Point"}
}