{
  "type": "Feature",
  "properties": {
    "iso:country":"ES",
    "sg:address":"Calle de Costa Rica, 11",
    "sg:city":"Alcantarilla",
    "sg:orig_category":"Materiales De Aislamiento T\u00c9rmico Y Ac\u00dastico",
    "sg:phone":"+34 968 80 33 35",
    "sg:postcode":"30820",
    "sg:province":"Murcia",
    "wof:name":"Policarpo Briones S.l.",
    "wof:placetype":"venue"
},
  "geometry": {"coordinates":[-1.2374949455,37.9569244385],"type":"Point"}
}