{
  "type": "Feature",
  "properties": {
    "addr:full":"Calle de Vivero, 8 Madrid Madrid 28040",
    "addr:housenumber":"8",
    "addr:postcode":"madrid;28040",
    "addr:street":"Calle De Vivero",
    "iso:country":"ES",
    "sg:address":"Calle de Vivero, 8",
    "sg:city":"Madrid",
    "sg:orig_category":"Electricidad, Electr\u00d3nica: Material Y Suministros (al Por Mayor)",
    "sg:phone":"+34 915 35 84 10",
    "sg:postcode":"28040",
    "sg:province":"Madrid",
    "wof:name":"Soniben Internacional S.l.",
    "wof:placetype":"venue"
},
  "geometry": {"coordinates":[-3.7104475498,40.4484024048],"type":"Point"}
}