{
  "type": "Feature",
  "properties": {
    "iso:country":"ES",
    "sg:address":"Plaza Del Conde, 5",
    "sg:city":"Pontedeume",
    "sg:orig_category":"Peluqueros: De Se\u00d1oras",
    "sg:phone":"+34 981 43 39 49",
    "sg:postcode":"15600",
    "sg:province":"La Coru\u00f1a",
    "wof:name":"Lopez Filgueiras Natividad",
    "wof:placetype":"venue"
},
  "geometry": {"coordinates":[-8.1714544296,43.4073867798],"type":"Point"}
}