{
  "type": "Feature",
  "properties": {
    "iso:country":"ES",
    "sg:address":"Calle de Valle (el), 17",
    "sg:city":"Benavides De Orbigo",
    "sg:orig_category":"Carpinteros",
    "sg:phone":"+34 987 37 01 29",
    "sg:postcode":"24280",
    "sg:province":"Le\u00f3n",
    "wof:name":"Blanco De Vega Maria Visitacion",
    "wof:placetype":"venue"
},
  "geometry": {"coordinates":[-5.9004092216,42.5051689148],"type":"Point"}
}