{
  "type": "Feature",
  "properties": {
    "iso:country":"ES",
    "sg:address":"C/ Troneta, 12",
    "sg:city":"Elche",
    "sg:orig_category":"Promotores Constructores",
    "sg:phone":"+34 965 45 97 12",
    "sg:postcode":"03203",
    "sg:province":"Alicante",
    "wof:name":"Calendura Promociones Inmobiliarias Sl",
    "wof:placetype":"venue"
},
  "geometry": {"coordinates":[-0.6977620125,38.2652359009],"type":"Point"}
}