{
  "type": "Feature",
  "properties": {
    "iso:country":"ES",
    "sg:address":"Carr Onze De Setembre, 5",
    "sg:city":"Mont-ras",
    "sg:orig_category":"Promotores Constructores",
    "sg:phone":"+34 972 30 31 55",
    "sg:postcode":"17253",
    "sg:province":"Girona",
    "wof:name":"Edificaciones Y Proyectos Del Ampurdan S.a.",
    "wof:placetype":"venue"
},
  "geometry": {"coordinates":[3.1450579166,41.9089241028],"type":"Point"}
}