{
  "type": "Feature",
  "properties": {
    "iso:country":"ES",
    "sg:address":"Calle de San Martin, 32",
    "sg:city":"Medina Campo",
    "sg:orig_category":"Ense\u00d1anza, Formaci\u00d3n Profesional: Aprendizaje",
    "sg:phone":"+34 983 81 10 92",
    "sg:postcode":"47400",
    "sg:province":"Valladolid",
    "wof:name":"Ayuntamiento De Medina Del Campo",
    "wof:placetype":"venue"
},
  "geometry": {"coordinates":[-4.9181547165,41.309299469],"type":"Point"}
}