{
  "type": "Feature",
  "properties": {
    "iso:country":"ES",
    "sg:address":"Pol Ind Juncaril, S/n",
    "sg:city":"Peligros",
    "sg:orig_category":"Estudios, Instalaci\u00d3n De Climatizaci\u00d3n",
    "sg:phone":"+34 958 49 00 58",
    "sg:postcode":"18210",
    "sg:province":"Granada",
    "wof:name":"Tienda Sur S.a.",
    "wof:placetype":"venue"
},
  "geometry": {"coordinates":[-3.6330029964,37.2238349915],"type":"Point"}
}