{
  "type": "Feature",
  "properties": {
    "iso:country":"ES",
    "sg:address":"Calle de Sangenjo, 20",
    "sg:city":"Madrid",
    "sg:orig_category":"Empresas De Portes Y Mensajer\u00cda",
    "sg:phone":"+34 917 39 81 06",
    "sg:postcode":"28034",
    "sg:province":"Madrid",
    "wof:name":"Logistica De Distribucion Rem S.l.",
    "wof:placetype":"venue"
},
  "geometry": {"coordinates":[-3.6984949112,40.4863090515],"type":"Point"}
}