{
  "type": "Feature",
  "properties": {
    "addr:full":"Calle de Belgica, 20 Valencia Valencia 46021",
    "addr:housenumber":"20",
    "addr:postcode":"46021",
    "addr:street":"Calle De Belgica",
    "iso:country":"ES",
    "sg:address":"Calle de Belgica, 20",
    "sg:city":"Valencia",
    "sg:orig_category":"Abogados",
    "sg:phone":"+34 963 39 05 16",
    "sg:postcode":"46021",
    "sg:province":"Valencia",
    "wof:name":"Gestion De Proyectos De Arquitectura Y Urbanismo S.l.",
    "wof:placetype":"venue"
},
  "geometry": {"coordinates":[-0.3554809988,39.4741134644],"type":"Point"}
}