{
  "type": "Feature",
  "properties": {
    "addr:full":"Rua Evaristo Vaamonde (de), 16 Carballi\u00f1o Ourense 32500",
    "addr:housenumber":"16",
    "addr:postcode":"32500",
    "addr:street":"Rua Evaristo Vaamonde De",
    "iso:country":"ES",
    "sg:address":"Rua Evaristo Vaamonde (de), 16",
    "sg:city":"Carballi\u00f1o",
    "sg:orig_category":"Promotores Constructores",
    "sg:phone":"+34 988 27 28 90",
    "sg:postcode":"32500",
    "sg:province":"Ourense",
    "wof:name":"Agrupconsa S.l.",
    "wof:placetype":"venue"
},
  "geometry": {"coordinates":[-8.0745382309,42.4311637878],"type":"Point"}
}