{
  "type": "Feature",
  "properties": {
    "addr:full":"Av Onze De Setembre, 47 Sant Joan De Palamos Girona 17230",
    "addr:housenumber":"47",
    "addr:postcode":"17230",
    "addr:street":"Av Onze De Setembre",
    "iso:country":"ES",
    "sg:address":"Av Onze De Setembre, 47",
    "sg:city":"Sant Joan De Palamos",
    "sg:orig_category":"\u00d3ptica: Instrumentos (fabricaci\u00d3n)",
    "sg:phone":"+34 972 31 45 70",
    "sg:postcode":"17230",
    "sg:province":"Girona",
    "wof:name":"Sardo Puig Pere",
    "wof:placetype":"venue"
},
  "geometry": {"coordinates":[3.1281778812,41.8479270935],"type":"Point"}
}