{
  "type": "Feature",
  "properties": {
    "addr:full":"Ptda Pla Conde, S/n Albaida Valencia 46860",
    "addr:housenumber":"s / n",
    "addr:postcode":"46860",
    "addr:street":"Ptda Pla Conde",
    "iso:country":"ES",
    "sg:address":"Ptda Pla Conde, S/n",
    "sg:city":"Albaida",
    "sg:orig_category":"Fabricaci\u00d3n De Telas Y Sedas",
    "sg:phone":"+34 962 90 11 14",
    "sg:postcode":"46860",
    "sg:province":"Valencia",
    "wof:name":"Soler Pastor Jose Ramon",
    "wof:placetype":"venue"
},
  "geometry": {"coordinates":[-0.5242289901,38.8424339294],"type":"Point"}
}