{
  "type": "Feature",
  "properties": {
    "addr:full":"Calle de Encuentros, 61 Argamasilla Alba Ciudad Real 13710",
    "addr:housenumber":"61",
    "addr:postcode":"alba;13710",
    "addr:street":"Calle De Encuentros",
    "iso:country":"ES",
    "sg:address":"Calle de Encuentros, 61",
    "sg:city":"Argamasilla Alba",
    "sg:orig_category":"Delegados, Agentes De Tr\u00c1nsito, Auxiliares De Transporte Internacional",
    "sg:phone":"+34 926 52 12 24",
    "sg:postcode":"13710",
    "sg:province":"Ciudad Real",
    "wof:name":"Rubio Torres Jeronimo",
    "wof:placetype":"venue"
},
  "geometry": {"coordinates":[-3.1010000706,39.1277885437],"type":"Point"}
}