{
  "type": "Feature",
  "properties": {
    "addr:full":"Carrer de Fluvia, S/n Barcelona Barcelona 08020",
    "addr:housenumber":"s / n",
    "addr:postcode":"08020",
    "addr:street":"Carrer De Fluvia",
    "iso:country":"ES",
    "sg:address":"Carrer de Fluvia, S/n",
    "sg:city":"Barcelona",
    "sg:orig_category":"Centros De Educaci\u00d3n Especial",
    "sg:phone":"+34 933 07 14 31",
    "sg:postcode":"08020",
    "sg:province":"Barcelona",
    "wof:name":"Ajuntament De Barcelona",
    "wof:placetype":"venue"
},
  "geometry": {"coordinates":[2.2017652988,41.4109420776],"type":"Point"}
}