{
  "type": "Feature",
  "properties": {
    "addr:full":"Carrer de Jacint Verdaguer, 150 Sabadell Barcelona 08205",
    "addr:housenumber":"150",
    "addr:postcode":"08205",
    "addr:street":"Carrer De Jacint Verdaguer",
    "iso:country":"ES",
    "sg:address":"Carrer de Jacint Verdaguer, 150",
    "sg:city":"Sabadell",
    "sg:orig_category":"Molduras, Junquillos, Listones Y Molduras Perforadas",
    "sg:phone":"+34 937 12 12 15",
    "sg:postcode":"08205",
    "sg:province":"Barcelona",
    "wof:name":"Rephon S.c.p.",
    "wof:placetype":"venue"
},
  "geometry": {"coordinates":[2.1037399769,41.5351905823],"type":"Point"}
}