{
  "type": "Feature",
  "properties": {
    "addr:full":"Calle de Isla De Mouro, 11 Somo Cantabria 39140",
    "addr:housenumber":"11",
    "addr:postcode":"39140",
    "addr:street":"Calle De Isla De Mouro",
    "iso:country":"ES",
    "sg:address":"Calle de Isla De Mouro, 11",
    "sg:city":"Somo",
    "sg:orig_category":"Farmacias",
    "sg:phone":"+34 942 51 05 84",
    "sg:postcode":"39140",
    "sg:province":"Cantabria",
    "wof:name":"Martin Rodriguez Miguel Angel",
    "wof:placetype":"venue"
},
  "geometry": {"coordinates":[-3.7439231873,43.4553031921],"type":"Point"}
}