{
  "type": "Feature",
  "properties": {
    "iso:country":"ES",
    "sg:address":"Calle de Pando Y Valle, 8",
    "sg:city":"Villaviciosa",
    "sg:orig_category":"Comercio De Piezas De Recambio Y De Accesorios De Veh\u00cdculos, Veh\u00cdculos Industriales",
    "sg:phone":"+34 985 89 32 30",
    "sg:postcode":"33300",
    "sg:province":"Asturias",
    "wof:name":"Auto Recambio Gijon S.a.l.",
    "wof:placetype":"venue"
},
  "geometry": {"coordinates":[-5.4363918304,43.4844207764],"type":"Point"}
}