{
  "type": "Feature",
  "properties": {
    "iso:country":"ES",
    "sg:address":"Pase Zorrilla, 96",
    "sg:city":"Valladolid",
    "sg:orig_category":"Complementos De Vestir (al Por Menor)",
    "sg:phone":"+34 983 47 87 15",
    "sg:postcode":"47006",
    "sg:province":"Valladolid",
    "wof:name":"Mucai C.b",
    "wof:placetype":"venue"
},
  "geometry": {"coordinates":[-4.7384538651,41.6395874023],"type":"Point"}
}