{
  "type": "Feature",
  "properties": {
    "iso:country":"ES",
    "sg:address":"Carr Mirador, S/n",
    "sg:city":"Port D'alcudia",
    "sg:orig_category":"Inmobiliaria (agencias)",
    "sg:phone":"+34 971 54 85 11",
    "sg:postcode":"07410",
    "sg:province":"Islas Baleares",
    "wof:name":"Inmobiliaria Alcanada S.a.",
    "wof:placetype":"venue"
},
  "geometry": {"coordinates":[3.1233201027,39.8516082764],"type":"Point"}
}