{
  "type": "Feature",
  "properties": {
    "addr:full":"Avda Maritima, 16 Santa Cruz Palma Santa Cruz De Tenerife 38700",
    "addr:housenumber":"16",
    "addr:postcode":"38700",
    "addr:street":"Avda Maritima",
    "iso:country":"ES",
    "sg:address":"Avda Maritima, 16",
    "sg:city":"Santa Cruz Palma",
    "sg:orig_category":"Bazares, Art\u00cdculos De Limpieza Y De Cocina (al Por Menor)",
    "sg:phone":"+34 922 41 30 52",
    "sg:postcode":"38700",
    "sg:province":"Santa Cruz De Tenerife",
    "wof:name":"Artesania Sanlupe S.l.",
    "wof:placetype":"venue"
},
  "geometry": {"coordinates":[-17.7648639679,28.6820983887],"type":"Point"}
}