{
  "type": "Feature",
  "properties": {
    "iso:country":"ES",
    "sg:address":"Barr Poligono De Granda, 2",
    "sg:city":"Granda",
    "sg:orig_category":"Negocio De Madera",
    "sg:phone":"+34 985 79 31 26",
    "sg:postcode":"33199",
    "sg:province":"Asturias",
    "wof:name":"Maderas Jomastur",
    "wof:placetype":"venue"
},
  "geometry": {"coordinates":[-5.7771863937,43.3823051453],"type":"Point"}
}