{
  "type": "Feature",
  "properties": {
    "iso:country":"ES",
    "sg:address":"Calle de Horca (la), 12",
    "sg:city":"Labastida",
    "sg:orig_category":"Productores Recolectores, Venta Directa De Vinos",
    "sg:phone":"+34 945 33 16 24",
    "sg:postcode":"01330",
    "sg:province":"\u00c1lava",
    "wof:name":"Echave Roman S.cv.",
    "wof:placetype":"venue"
},
  "geometry": {"coordinates":[-2.7974441051,42.5904388428],"type":"Point"}
}