{
  "type": "Feature",
  "properties": {
    "addr:full":"Calle de Nazareno, 8 Villanueva Serena Badajoz 06700",
    "addr:housenumber":"8",
    "addr:postcode":"06700",
    "addr:street":"Calle De Nazareno",
    "iso:country":"ES",
    "sg:address":"Calle de Nazareno, 8",
    "sg:city":"Villanueva Serena",
    "sg:orig_category":"Agencias Y Agentes Comerciales, Representantes",
    "sg:phone":"+34 924 84 50 87",
    "sg:postcode":"06700",
    "sg:province":"Badajoz",
    "wof:name":"Alvarez Espino Pedro",
    "wof:placetype":"venue"
},
  "geometry": {"coordinates":[-5.8002691269,38.9752006531],"type":"Point"}
}