{
  "type": "Feature",
  "properties": {
    "iso:country":"ES",
    "sg:address":"Avda Monforte De Lemos, 166",
    "sg:city":"Madrid",
    "sg:orig_category":"Cristaler\u00cdas",
    "sg:phone":"+34 913 86 58 99",
    "sg:postcode":"28029",
    "sg:province":"Madrid",
    "wof:name":"Cristalerias Crisar S.l.",
    "wof:placetype":"venue"
},
  "geometry": {"coordinates":[-3.7149500847,40.4775085449],"type":"Point"}
}