{
  "type": "Feature",
  "properties": {
    "iso:country":"ES",
    "sg:address":"Carr Major, 71",
    "sg:city":"Maria De La Salut",
    "sg:orig_category":"Psic\u00d3logos",
    "sg:phone":"+34 971 52 52 94",
    "sg:postcode":"07519",
    "sg:province":"Islas Baleares",
    "wof:name":"Bergas Mas Francesca",
    "wof:placetype":"venue"
},
  "geometry": {"coordinates":[3.0711569786,39.6644248962],"type":"Point"}
}