{
  "type": "Feature",
  "properties": {
    "addr:full":"Pl Adria, 5 Barcelona Barcelona 08021",
    "addr:housenumber":"5",
    "addr:postcode":"08021",
    "addr:street":"Pl Adria",
    "iso:country":"ES",
    "sg:address":"Pl Adria, 5",
    "sg:city":"Barcelona",
    "sg:orig_category":"Ropa Para Ni\u00d1os (al Por Menor)",
    "sg:phone":"+34 932 41 22 85",
    "sg:postcode":"08021",
    "sg:province":"Barcelona",
    "wof:name":"Dedamaris S.c.p.",
    "wof:placetype":"venue"
},
  "geometry": {"coordinates":[2.1388640404,41.4011688232],"type":"Point"}
}