{
  "type": "Feature",
  "properties": {
    "addr:full":"Calle de Andalucia, 49 Torredelcampo Ja\u00e9n 23640",
    "addr:housenumber":"49",
    "addr:postcode":"23640",
    "addr:street":"Calle De Andalucia;Jae\u0301N",
    "iso:country":"ES",
    "sg:address":"Calle de Andalucia, 49",
    "sg:city":"Torredelcampo",
    "sg:orig_category":"Contenedores (mercanc\u00cdas)",
    "sg:phone":"+34 953 56 74 07",
    "sg:postcode":"23640",
    "sg:province":"Ja\u00e9n",
    "wof:name":"Sanchez Alcantara Juana",
    "wof:placetype":"venue"
},
  "geometry": {"coordinates":[-3.8930253983,37.7727851868],"type":"Point"}
}