{
  "type": "Feature",
  "properties": {
    "iso:country":"ES",
    "sg:address":"Avda Comunidad Europea, 32",
    "sg:city":"Palencia",
    "sg:orig_category":"Calefacci\u00d3n Central: Material (fabricaci\u00d3n, Al Por Mayor)",
    "sg:phone":"+34 979 72 34 02",
    "sg:postcode":"34003",
    "sg:province":"Palencia",
    "sg:website":"paginasamarillas.es",
    "wof:name":"Material De Calefaccion Pardo Y Cuevas S.l.",
    "wof:placetype":"venue"
},
  "geometry": {"coordinates":[-4.5097279549,42.0057640076],"type":"Point"}
}