{
  "type": "Feature",
  "properties": {
    "addr:full":"Calle de El Rio, S/n San Pedro De Latarce Valladolid 47851",
    "addr:housenumber":"/ n",
    "addr:postcode":"47851",
    "addr:street":"Calle De El;S",
    "iso:country":"ES",
    "sg:address":"Calle de El Rio, S/n",
    "sg:city":"San Pedro De Latarce",
    "sg:orig_category":"Centros De Educaci\u00d3n Especial",
    "sg:phone":"+34 983 72 31 01",
    "sg:postcode":"47851",
    "sg:province":"Valladolid",
    "wof:name":"Colegio Rural Agrupado Villas Del Sequillo",
    "wof:placetype":"venue"
},
  "geometry": {"coordinates":[-5.3260130882,41.7375793457],"type":"Point"}
}