{
  "type": "Feature",
  "properties": {
    "iso:country":"ES",
    "sg:address":"Carrer de Fran\u00c7a, 27",
    "sg:city":"Olot",
    "sg:orig_category":"Andamiajes Y Escaleras De Mano (fabricaci\u00d3n, Al Por Mayor)",
    "sg:phone":"+34 972 26 29 50",
    "sg:postcode":"17800",
    "sg:province":"Girona",
    "sg:website":"www.germanspairo.com",
    "wof:name":"Germans Pairo S.a.",
    "wof:placetype":"venue"
},
  "geometry": {"coordinates":[2.4836850166,42.1929092407],"type":"Point"}
}