{
  "type": "Feature",
  "properties": {
    "addr:full":"Cmno A Monte Atras, 1 Rigada Vizcaya 48550",
    "addr:housenumber":"1",
    "addr:postcode":"48550",
    "addr:street":"Cmno A Monte Atras",
    "iso:country":"ES",
    "sg:address":"Cmno A Monte Atras, 1",
    "sg:city":"Rigada",
    "sg:orig_category":"Ingeniero",
    "sg:phone":"+34 946 70 81 91",
    "sg:postcode":"48550",
    "sg:province":"Vizcaya",
    "wof:name":"Laboratio De Ensayos Icim Lab S.l.",
    "wof:placetype":"venue"
},
  "geometry": {"coordinates":[-3.1228249073,43.3224563599],"type":"Point"}
}