{
  "type": "Feature",
  "properties": {
    "addr:full":"Carr Francisco Gozalbes, 1 Xativa Valencia 46800",
    "addr:housenumber":"1",
    "addr:postcode":"46800",
    "addr:street":"Carr Francisco Gozalbes",
    "iso:country":"ES",
    "sg:address":"Carr Francisco Gozalbes, 1",
    "sg:city":"Xativa",
    "sg:orig_category":"Peluquer\u00cdas, Peluquer\u00cda Mixta",
    "sg:phone":"+34 962 27 33 34",
    "sg:postcode":"46800",
    "sg:province":"Valencia",
    "wof:name":"Martinez Vidal Angel Ramon",
    "wof:placetype":"venue"
},
  "geometry": {"coordinates":[-0.5200830102,38.9934272766],"type":"Point"}
}