{
  "type": "Feature",
  "properties": {
    "addr:full":"Carrer de Montserrat, 57 Esplugues Llobregat Barcelona 08950",
    "addr:housenumber":"57",
    "addr:postcode":"08950",
    "addr:street":"Carrer De Montserrat",
    "iso:country":"ES",
    "sg:address":"Carrer de Montserrat, 57",
    "sg:city":"Esplugues Llobregat",
    "sg:orig_category":"Escultores, Estatuarios E Imagineros",
    "sg:phone":"+34 934 73 16 47",
    "sg:postcode":"08950",
    "sg:province":"Barcelona",
    "wof:name":"Centro De Actividades E Investigaciones Artisticas De Cataluna Fundacion X. Corbero",
    "wof:placetype":"venue"
},
  "geometry": {"coordinates":[2.0842609406,41.3737335205],"type":"Point"}
}