{
  "type": "Feature",
  "properties": {
    "iso:country":"ES",
    "sg:address":"Calle de Arzobispo Elias Yanes, 50",
    "sg:city":"San Lazaro",
    "sg:orig_category":"Congelados: Productos Alimentarios (al Por Menor)",
    "sg:phone":"+34 922 25 09 48",
    "sg:postcode":"38206",
    "sg:province":"Santa Cruz De Tenerife",
    "wof:name":"Salcedo Dorta Eulogio Domingo",
    "wof:placetype":"venue"
},
  "geometry": {"coordinates":[-16.2548561096,28.4698104858],"type":"Point"}
}