{
  "type": "Feature",
  "properties": {
    "addr:full":"Ibur-erreka, S/n Eibar Guip\u00f9zcoa 20600",
    "addr:postcode":"20600",
    "addr:street":"Ibur-Erreka S / N;Guipu\u0300Zcoa",
    "iso:country":"ES",
    "sg:address":"Ibur-erreka, S/n",
    "sg:city":"Eibar",
    "sg:orig_category":"Metalurgia",
    "sg:phone":"+34 943 82 01 70",
    "sg:postcode":"20600",
    "sg:province":"Guip\u00f9zcoa",
    "wof:name":"Tecnicas Eibarresas De Curvado S.l.",
    "wof:placetype":"venue"
},
  "geometry": {"coordinates":[-2.4618649483,43.188495636],"type":"Point"}
}