{
  "type": "Feature",
  "properties": {
    "iso:country":"ES",
    "sg:address":"C/ Pont De Sant Jordi, 2",
    "sg:city":"Alcoi",
    "sg:orig_category":"Restaurantes",
    "sg:phone":"+34 965 52 33 55",
    "sg:postcode":"03803",
    "sg:province":"Alicante",
    "wof:name":"Sanchis Montoya Juan Jose",
    "wof:placetype":"venue"
},
  "geometry": {"coordinates":[-0.4744929969,38.6996231079],"type":"Point"}
}