{
  "type": "Feature",
  "properties": {
    "iso:country":"ES",
    "sg:address":"Calle de Emilia Pardo Bazan (de), S/n",
    "sg:city":"Algete",
    "sg:orig_category":"Librer\u00cdas",
    "sg:phone":"+34 916 28 06 25",
    "sg:postcode":"28110",
    "sg:province":"Madrid",
    "wof:name":"Pascual Sanz Nuria",
    "wof:placetype":"venue"
},
  "geometry": {"coordinates":[-3.5062270164,40.6007995605],"type":"Point"}
}