{
  "type": "Feature",
  "properties": {
    "addr:full":"Rua Echegaray, 16 Pontevedra Pontevedra 36002",
    "addr:housenumber":"16",
    "addr:postcode":"36002",
    "addr:street":"Rua Echegaray",
    "iso:country":"ES",
    "sg:address":"Rua Echegaray, 16",
    "sg:city":"Pontevedra",
    "sg:orig_category":"Ingenier\u00cda, Centros De Estudios (diversos)",
    "sg:phone":"+34 986 85 61 93",
    "sg:postcode":"36002",
    "sg:province":"Pontevedra",
    "wof:name":"Zugasti Enrique Gerardo",
    "wof:placetype":"venue"
},
  "geometry": {"coordinates":[-8.6505241394,42.4317169189],"type":"Point"}
}