{
  "type": "Feature",
  "properties": {
    "addr:full":"Avda Donostiarra, 19 Madrid Madrid 28027",
    "addr:housenumber":"19",
    "addr:postcode":"madrid;28027",
    "addr:street":"Avda Donostiarra",
    "iso:country":"ES",
    "sg:address":"Avda Donostiarra, 19",
    "sg:city":"Madrid",
    "sg:orig_category":"Sociedades, Compa\u00d1\u00cdas Aseguradoras",
    "sg:phone":"+34 913 26 61 57",
    "sg:postcode":"28027",
    "sg:province":"Madrid",
    "wof:name":"Ryg Segurs Agencia De Seguros S.l.",
    "wof:placetype":"venue"
},
  "geometry": {"coordinates":[-3.6573688984,40.43491745],"type":"Point"}
}