{
  "type": "Feature",
  "properties": {
    "addr:full":"Poli Peguera (la), 21 Barraco \u00c1vila 05110",
    "addr:postcode":"05110",
    "addr:street":"Barraco",
    "iso:country":"ES",
    "sg:address":"Poli Peguera (la), 21",
    "sg:city":"Barraco",
    "sg:orig_category":"Fabricaci\u00d3n De Productos L\u00c1cteos Y Derivados",
    "sg:phone":"+34 920 28 14 70",
    "sg:postcode":"05110",
    "sg:province":"\u00c1vila",
    "wof:name":"Ganaderos De Caprino Del Alberche S. C. L.",
    "wof:placetype":"venue"
},
  "geometry": {"coordinates":[-4.6382842064,40.4788093567],"type":"Point"}
}