{
  "type": "Feature",
  "properties": {
    "iso:country":"ES",
    "sg:address":"Calle de Sancho Davila, 23",
    "sg:city":"Madrid",
    "sg:orig_category":"Arreglo, Reparaci\u00d3n, Piezas Sueltas De Televisi\u00d3n, V\u00cddeo, Hi",
    "sg:phone":"+34 913 56 14 00",
    "sg:postcode":"28028",
    "sg:province":"Madrid",
    "wof:name":"Servicios Tecnicos Concertados S. A.",
    "wof:placetype":"venue"
},
  "geometry": {"coordinates":[-3.6616530418,40.4264755249],"type":"Point"}
}