{
  "type": "Feature",
  "properties": {
    "addr:full":"Calle de Garcia Morato, 9 Port D'andratx Islas Baleares 07157",
    "addr:housenumber":"9",
    "addr:postcode":"07157",
    "addr:street":"Calle De Garcia Morato",
    "iso:country":"ES",
    "sg:address":"Calle de Garcia Morato, 9",
    "sg:city":"Port D'andratx",
    "sg:orig_category":"Ropa Para Se\u00d1oras Y Caballeros (al Por Menor)",
    "sg:phone":"+34 971 67 11 06",
    "sg:postcode":"07157",
    "sg:province":"Islas Baleares",
    "wof:name":"Es Puig Tomir S.l.",
    "wof:placetype":"venue"
},
  "geometry": {"coordinates":[2.9117100239,39.6136398315],"type":"Point"}
}