{
  "type": "Feature",
  "properties": {
    "iso:country":"ES",
    "sg:address":"Carrer de Pensament, 10",
    "sg:city":"Palma",
    "sg:orig_category":"Centros Empresariales",
    "sg:phone":"+34 971 73 51 90",
    "sg:postcode":"07014",
    "sg:province":"Islas Baleares",
    "wof:name":"Sis4 Solutions S.l.",
    "wof:placetype":"venue"
},
  "geometry": {"coordinates":[2.6245861053,39.578250885],"type":"Point"}
}