{
  "type": "Feature",
  "properties": {
    "addr:full":"Calle de Pedro Antonio De Alarcon, 62 Granada Granada 18002",
    "addr:housenumber":"62",
    "addr:postcode":"18002",
    "addr:street":"Calle De Pedro Antonio De Alarcon",
    "iso:country":"ES",
    "sg:address":"Calle de Pedro Antonio De Alarcon, 62",
    "sg:city":"Granada",
    "sg:orig_category":"Inform\u00c1tica: Material Y Suministros",
    "sg:phone":"+34 958 20 57 32",
    "sg:postcode":"18002",
    "sg:province":"Granada",
    "sg:website":"www.faninternet.com",
    "wof:name":"Costela Villodres Alicia",
    "wof:placetype":"venue"
},
  "geometry": {"coordinates":[-3.6076350212,37.1752357483],"type":"Point"}
}