{
  "type": "Feature",
  "properties": {
    "iso:country":"ES",
    "sg:address":"Carrer de Sant Sebastia, 18",
    "sg:city":"Crevillent",
    "sg:orig_category":"Fabricaci\u00d3n De Jabones, Detergentes Y Lej\u00cdas",
    "sg:phone":"+34 965 40 64 33",
    "sg:postcode":"03330",
    "sg:province":"Alicante",
    "wof:name":"Bayer Cropscience S.l.",
    "wof:placetype":"venue"
},
  "geometry": {"coordinates":[-0.8119879961,38.2484016418],"type":"Point"}
}