{
  "type": "Feature",
  "properties": {
    "iso:country":"ES",
    "sg:address":"Moll Bosch I Alsina, S/n",
    "sg:city":"Barcelona",
    "sg:orig_category":"Aparcamientos (infraestructuras, Accesorios)",
    "sg:phone":"+34 932 21 50 15",
    "sg:postcode":"08039",
    "sg:province":"Barcelona",
    "wof:name":"Barcelona De Serveis Municipals S.a.",
    "wof:placetype":"venue"
},
  "geometry": {"coordinates":[2.1836469173,41.3809814453],"type":"Point"}
}