{
  "type": "Feature",
  "properties": {
    "iso:country":"ES",
    "sg:address":"Calle de Mayor, 62",
    "sg:city":"Quinto",
    "sg:orig_category":"Empresas De Pintura Y Revestimientos",
    "sg:phone":"+34 976 17 70 14",
    "sg:postcode":"50770",
    "sg:province":"Zaragoza",
    "wof:name":"Bes Calvo Maria Jesus",
    "wof:placetype":"venue"
},
  "geometry": {"coordinates":[-0.4983009994,41.4258041382],"type":"Point"}
}