{
  "type": "Feature",
  "properties": {
    "addr:full":"Calle de San Sebastian, 10 Huelva Huelva 21004",
    "addr:housenumber":"10",
    "addr:postcode":"21004",
    "addr:street":"Calle De San Sebastian",
    "iso:country":"ES",
    "sg:address":"Calle de San Sebastian, 10",
    "sg:city":"Huelva",
    "sg:orig_category":"Caf\u00c9s, Bares, Cervecer\u00cdas",
    "sg:phone":"+34 959 26 01 67",
    "sg:postcode":"21004",
    "sg:province":"Huelva",
    "wof:name":"Ocionuba S.l.",
    "wof:placetype":"venue"
},
  "geometry": {"coordinates":[-6.9467811584,37.2605247498],"type":"Point"}
}