{
  "type": "Feature",
  "properties": {
    "addr:full":"Calle de San Roque, 1 Calamocha Teruel 44200",
    "addr:housenumber":"1",
    "addr:postcode":"44200",
    "addr:street":"Calle De San Roque",
    "iso:country":"ES",
    "sg:address":"Calle de San Roque, 1",
    "sg:city":"Calamocha",
    "sg:orig_category":"Cajas Para Embalar",
    "sg:phone":"+34 978 73 02 61",
    "sg:postcode":"44200",
    "sg:province":"Teruel",
    "wof:name":"Caja Rural De Teruel",
    "wof:placetype":"venue"
},
  "geometry": {"coordinates":[-1.2977180481,40.9204826355],"type":"Point"}
}