{
  "type": "Feature",
  "properties": {
    "addr:full":"Calle de Capuchinos, 5 Valladolid Valladolid 47006",
    "addr:housenumber":"5",
    "addr:postcode":"47006",
    "addr:street":"Calle De Capuchinos",
    "iso:country":"ES",
    "sg:address":"Calle de Capuchinos, 5",
    "sg:city":"Valladolid",
    "sg:orig_category":"Frutas, Legumbres Frescas Y Tempranas (al Por Menor)",
    "sg:phone":"+34 983 47 15 87",
    "sg:postcode":"47006",
    "sg:province":"Valladolid",
    "wof:name":"Montes Vicente Jose Luis",
    "wof:placetype":"venue"
},
  "geometry": {"coordinates":[-4.736656189,41.6441459656],"type":"Point"}
}