{
  "type": "Feature",
  "properties": {
    "iso:country":"ES",
    "sg:address":"Calle de Rio Guadalete, 25",
    "sg:city":"Martos",
    "sg:orig_category":"Empresas De Carpinter\u00cda De Madera",
    "sg:phone":"+34 953 55 22 17",
    "sg:postcode":"23600",
    "sg:province":"Ja\u00e9n",
    "wof:name":"Gonzalez Luque Facundo",
    "wof:placetype":"venue"
},
  "geometry": {"coordinates":[-3.9711670876,37.7099456787],"type":"Point"}
}