{
  "type": "Feature",
  "properties": {
    "iso:country":"ES",
    "sg:address":"Plaz Manuel Aza\u00d1a De, 3",
    "sg:city":"Malaga",
    "sg:orig_category":"Sindicatos De Trabajadores",
    "sg:phone":"+34 952 32 49 14",
    "sg:postcode":"29006",
    "sg:province":"M\u00e1laga",
    "wof:name":"Sindicato Profesional De Policia",
    "wof:placetype":"venue"
},
  "geometry": {"coordinates":[-4.448431015,36.7147483826],"type":"Point"}
}