{
  "type": "Feature",
  "properties": {
    "iso:country":"ES",
    "sg:address":"Carr Puig Cargol, S/n",
    "sg:city":"Sant Joan De Palamos",
    "sg:orig_category":"Art\u00cdculos De Regalo (al Por Menor)",
    "sg:phone":"+34 972 60 20 19",
    "sg:postcode":"17230",
    "sg:province":"Girona",
    "wof:name":"Illa Rey Rosa",
    "wof:placetype":"venue"
},
  "geometry": {"coordinates":[3.1278250217,41.8641967773],"type":"Point"}
}