{
  "type": "Feature",
  "properties": {
    "addr:full":"Calle de Colombia, 2 Villanueva Gallego Zaragoza 50830",
    "addr:housenumber":"2",
    "addr:postcode":"50830",
    "addr:street":"Calle De Colombia",
    "iso:country":"ES",
    "sg:address":"Calle de Colombia, 2",
    "sg:city":"Villanueva Gallego",
    "sg:orig_category":"Prot\u00c9sicos Dentales",
    "sg:phone":"+34 976 18 63 72",
    "sg:postcode":"50830",
    "sg:province":"Zaragoza",
    "wof:name":"Gadea-cebrian S.l.",
    "wof:placetype":"venue"
},
  "geometry": {"coordinates":[-0.8298835754,41.766910553],"type":"Point"}
}