{
  "type": "Feature",
  "properties": {
    "addr:full":"Calle de Caleta (la), 45 Costa Ballena C\u00e1diz 11520",
    "addr:housenumber":"45",
    "addr:postcode":"11520",
    "addr:street":"Calle De Caleta La;Costa;Ca\u0301Diz",
    "iso:country":"ES",
    "sg:address":"Calle de Caleta (la), 45",
    "sg:city":"Costa Ballena",
    "sg:orig_category":"Agricultura: Abastecimiento Y Cosechado (negocio)",
    "sg:phone":"+34 956 84 90 06",
    "sg:postcode":"11520",
    "sg:province":"C\u00e1diz",
    "wof:name":"Prime Time Properties Corp",
    "wof:placetype":"venue"
},
  "geometry": {"coordinates":[-6.4129796028,36.6823196411],"type":"Point"}
}