{
  "type": "Feature",
  "properties": {
    "addr:full":"Calle de Riotinto, 27 Malaga M\u00e1laga 29010",
    "addr:housenumber":"27",
    "addr:postcode":"29010",
    "addr:street":"Calle De Riotinto;Ma\u0301Laga",
    "iso:country":"ES",
    "sg:address":"Calle de Riotinto, 27",
    "sg:city":"Malaga",
    "sg:orig_category":"Empresas De Carpinter\u00cda Met\u00c1lica",
    "sg:phone":"+34 952 27 21 20",
    "sg:postcode":"29010",
    "sg:province":"M\u00e1laga",
    "wof:name":"Aluplast 2001 S.l.",
    "wof:placetype":"venue"
},
  "geometry": {"coordinates":[-4.4516925812,36.7341651917],"type":"Point"}
}