{
  "type": "Feature",
  "properties": {
    "iso:country":"ES",
    "sg:address":"Plaz Encarnacion, 1",
    "sg:city":"Velez-rubio",
    "sg:orig_category":"Ense\u00d1anza, Formaci\u00d3n Profesional: Aprendizaje",
    "sg:phone":"+34 950 61 40 15",
    "sg:postcode":"04820",
    "sg:province":"Almer\u00eda",
    "wof:name":"Ayuntamiento De Velez Rubio",
    "wof:placetype":"venue"
},
  "geometry": {"coordinates":[-2.074231863,37.648021698],"type":"Point"}
}