{
  "type": "Feature",
  "properties": {
    "iso:country":"ES",
    "sg:address":"Calle de Pellejero Villoria, 3",
    "sg:city":"Salamanca",
    "sg:orig_category":"Empresarios",
    "sg:phone":"+34 923 22 74 00",
    "sg:postcode":"37004",
    "sg:province":"Salamanca",
    "wof:name":"Corral Martin Leopoldo Manuel",
    "wof:placetype":"venue"
},
  "geometry": {"coordinates":[-5.6550059319,40.9752082825],"type":"Point"}
}