{
  "type": "Feature",
  "properties": {
    "iso:country":"ES",
    "sg:address":"Calle de Real, 19",
    "sg:city":"Navalucillos",
    "sg:orig_category":"Iglesia Cat\u00d3lica",
    "sg:phone":"+34 925 42 63 85",
    "sg:postcode":"45130",
    "sg:province":"Toledo",
    "wof:name":"Parroquia San Sebastian",
    "wof:placetype":"venue"
},
  "geometry": {"coordinates":[-4.6427631378,39.671836853],"type":"Point"}
}