{
  "type": "Feature",
  "properties": {
    "iso:country":"ES",
    "sg:address":"Pg. Circumva%acio, 1",
    "sg:city":"Premia Mar",
    "sg:orig_category":"Planchado",
    "sg:phone":"+34 937 52 08 96",
    "sg:postcode":"08330",
    "sg:province":"Barcelona",
    "wof:name":"Gabin Salas Antonio",
    "wof:placetype":"venue"
},
  "geometry": {"coordinates":[2.3487730026,41.4896507263],"type":"Point"}
}