{
  "type": "Feature",
  "properties": {
    "addr:full":"Calle de Rufino Gea Martinez, 2 Orihuela Alicante 03300",
    "addr:housenumber":"2",
    "addr:postcode":"03300",
    "addr:street":"Calle De Rufino Gea Martinez",
    "iso:country":"ES",
    "sg:address":"Calle de Rufino Gea Martinez, 2",
    "sg:city":"Orihuela",
    "sg:orig_category":"Centros De Coordinaci\u00d3n",
    "sg:phone":"+34 965 30 09 38",
    "sg:postcode":"03300",
    "sg:province":"Alicante",
    "wof:name":"Gestoria Cartagena S.l.",
    "wof:placetype":"venue"
},
  "geometry": {"coordinates":[-0.9443209767,38.085319519],"type":"Point"}
}