{
  "type": "Feature",
  "properties": {
    "iso:country":"ES",
    "sg:address":"Plaz Constitucion, 19",
    "sg:city":"Montehermoso",
    "sg:orig_category":"Molduras, Junquillos, Listones Y Molduras Perforadas",
    "sg:phone":"+34 927 43 06 75",
    "sg:postcode":"10810",
    "sg:province":"C\u00e1ceres",
    "wof:name":"Alvarez Garcia Jose",
    "wof:placetype":"venue"
},
  "geometry": {"coordinates":[-6.3487591743,40.088508606],"type":"Point"}
}