{
  "type": "Feature",
  "properties": {
    "addr:full":"Calle de Julian Ceballos, 6 Torrelavega Cantabria 39300",
    "addr:housenumber":"6",
    "addr:postcode":"39300",
    "addr:street":"Calle De Julian Ceballos",
    "iso:country":"ES",
    "sg:address":"Calle de Julian Ceballos, 6",
    "sg:city":"Torrelavega",
    "sg:orig_category":"Asesor\u00cdas Y Estudios Financieros",
    "sg:phone":"+34 942 89 15 42",
    "sg:postcode":"39300",
    "sg:province":"Cantabria",
    "wof:name":"Lopez Saiz David",
    "wof:placetype":"venue"
},
  "geometry": {"coordinates":[-4.0510659218,43.3486213684],"type":"Point"}
}