{
  "type": "Feature",
  "properties": {
    "addr:full":"Calle de Andres Larrazabal, 2 Arenas -areeta Vizcaya 48930",
    "addr:housenumber":"2;areeta",
    "addr:postcode":"48930",
    "addr:street":"Calle De Andres Larrazabal",
    "iso:country":"ES",
    "sg:address":"Calle de Andres Larrazabal, 2",
    "sg:city":"Arenas -areeta",
    "sg:orig_category":"Ropa Para Se\u00d1oras Y Caballeros (al Por Menor)",
    "sg:phone":"+34 944 63 67 11",
    "sg:postcode":"48930",
    "sg:province":"Vizcaya",
    "wof:name":"Alguer E Hijos S.l.",
    "wof:placetype":"venue"
},
  "geometry": {"coordinates":[-3.0135309696,43.3258171082],"type":"Point"}
}