{
  "type": "Feature",
  "properties": {
    "iso:country":"ES",
    "sg:address":"Pza. F. Jesus V. Chamorro, 4",
    "sg:city":"Valverde Fresno",
    "sg:orig_category":"Librer\u00cdas",
    "sg:phone":"+34 927 51 05 19",
    "sg:postcode":"10890",
    "sg:province":"C\u00e1ceres",
    "wof:name":"Carrero Carrasco Melani",
    "wof:placetype":"venue"
},
  "geometry": {"coordinates":[-6.8789291382,40.2212944031],"type":"Point"}
}