{
  "type": "Feature",
  "properties": {
    "addr:full":"Carrer de Verge Del Pilar (de La), 2 Salou Tarragona 43840",
    "addr:housenumber":"2",
    "addr:postcode":"43840",
    "addr:street":"Carrer De Verge Del Pilar De La",
    "iso:country":"ES",
    "sg:address":"Carrer de Verge Del Pilar (de La), 2",
    "sg:city":"Salou",
    "sg:orig_category":"Fisioterapia",
    "sg:phone":"+34 977 35 04 13",
    "sg:postcode":"43840",
    "sg:province":"Tarragona",
    "wof:name":"Magraner Rullan Javier",
    "wof:placetype":"venue"
},
  "geometry": {"coordinates":[1.1436860561,41.0737037659],"type":"Point"}
}