{
  "type": "Feature",
  "properties": {
    "addr:full":"Calle de Jara, 16 Zafra Badajoz 06300",
    "addr:housenumber":"16",
    "addr:postcode":"06300",
    "addr:street":"Calle De Jara",
    "iso:country":"ES",
    "sg:address":"Calle de Jara, 16",
    "sg:city":"Zafra",
    "sg:orig_category":"Reposter\u00cdas",
    "sg:phone":"+34 924 55 03 24",
    "sg:postcode":"06300",
    "sg:province":"Badajoz",
    "wof:name":"Gomez Gutierrez Julian",
    "wof:placetype":"venue"
},
  "geometry": {"coordinates":[-6.4167900085,38.4184532166],"type":"Point"}
}