{
  "type": "Feature",
  "properties": {
    "addr:full":"Ctra Alcolea Del Pinar, 62 Urbanitzacio Sol I Vista Tarragona 43206",
    "addr:housenumber":"62",
    "addr:postcode":"43206",
    "addr:street":"Ctra Alcolea Del Pinar;Urbanitzacio;I Vista",
    "iso:country":"ES",
    "sg:address":"Ctra Alcolea Del Pinar, 62",
    "sg:city":"Urbanitzacio Sol I Vista",
    "sg:orig_category":"Artes Gr\u00c1ficas, Artes Pl\u00c1sticas (curso)",
    "sg:phone":"+34 977 31 36 00",
    "sg:postcode":"43206",
    "sg:province":"Tarragona",
    "wof:name":"Caro Grande Jose",
    "wof:placetype":"venue"
},
  "geometry": {"coordinates":[1.1039400101,41.1745300293],"type":"Point"}
}