{
  "type": "Feature",
  "properties": {
    "iso:country":"ES",
    "sg:address":"Carrer de Joan Vidal I Jumbert, 34",
    "sg:city":"Granollers",
    "sg:orig_category":"Animales (al Por Menor)",
    "sg:phone":"+34 938 46 80 10",
    "sg:postcode":"08403",
    "sg:province":"Barcelona",
    "wof:name":"Campdelacreu Mauri Montserrrat",
    "wof:placetype":"venue"
},
  "geometry": {"coordinates":[2.2794759274,41.6142196655],"type":"Point"}
}