{
  "type": "Feature",
  "properties": {
    "iso:country":"ES",
    "sg:address":"Avda Alfonso Xiii, 145",
    "sg:city":"Madrid",
    "sg:orig_category":"Pintura Y Barniz (al Por Menor)",
    "sg:phone":"+34 913 59 61 94",
    "sg:postcode":"28016",
    "sg:province":"Madrid",
    "wof:name":"Pinturas Ynamela S.l.",
    "wof:placetype":"venue"
},
  "geometry": {"coordinates":[-3.6757121086,40.4602279663],"type":"Point"}
}