{
  "type": "Feature",
  "properties": {
    "iso:country":"ES",
    "sg:address":"Pol Txako, 3",
    "sg:city":"Txako",
    "sg:orig_category":"Carpinteros",
    "sg:phone":"+34 946 71 41 52",
    "sg:postcode":"48480",
    "sg:province":"Vizcaya",
    "wof:name":"Aluplast Iberica S.a.",
    "wof:placetype":"venue"
},
  "geometry": {"coordinates":[-2.6983869076,43.2204284668],"type":"Point"}
}