{
  "type": "Feature",
  "properties": {
    "iso:country":"ES",
    "sg:address":"Calle de Libreros, 18",
    "sg:city":"Alcala Henares",
    "sg:orig_category":"M\u00c9dicos: Estomatolog\u00cda",
    "sg:phone":"+34 918 83 29 17",
    "sg:postcode":"28801",
    "sg:province":"Madrid",
    "wof:name":"Esteban Mugica Asensio",
    "wof:placetype":"venue"
},
  "geometry": {"coordinates":[-3.3633151054,40.4838218689],"type":"Point"}
}