{
  "type": "Feature",
  "properties": {
    "addr:full":"Calle de Mariano Menendez Valdes, 11 Pola De Laviana Asturias 33980",
    "addr:housenumber":"11",
    "addr:postcode":"33980",
    "addr:street":"Calle De Mariano Menendez Valdes;Pola",
    "iso:country":"ES",
    "sg:address":"Calle de Mariano Menendez Valdes, 11",
    "sg:city":"Pola De Laviana",
    "sg:orig_category":"Bebidas",
    "sg:phone":"+34 985 60 10 70",
    "sg:postcode":"33980",
    "sg:province":"Asturias",
    "wof:name":"Gonzalez Antu\u00f1a Medita",
    "wof:placetype":"venue"
},
  "geometry": {"coordinates":[-5.5640420914,43.24766922],"type":"Point"}
}