{
  "type": "Feature",
  "properties": {
    "addr:full":"Calle de Maria De Luna, 3 Baza Granada 18800",
    "addr:housenumber":"3",
    "addr:postcode":"18800",
    "addr:street":"Calle De Maria De Luna",
    "iso:country":"ES",
    "sg:address":"Calle de Maria De Luna, 3",
    "sg:city":"Baza",
    "sg:orig_category":"Hoteles",
    "sg:phone":"+34 958 86 09 98",
    "sg:postcode":"18800",
    "sg:province":"Granada",
    "wof:name":"Campos Carmona Mercedes",
    "wof:placetype":"venue"
},
  "geometry": {"coordinates":[-2.7663009167,37.4914321899],"type":"Point"}
}