{
  "type": "Feature",
  "properties": {
    "iso:country":"ES",
    "sg:address":"Aizkibel Kalea, 16",
    "sg:city":"Azkoitia",
    "sg:orig_category":"Internados & Ense\u00d1anza Privada",
    "sg:phone":"+34 943 85 11 00",
    "sg:postcode":"20720",
    "sg:province":"Guip\u00f9zcoa",
    "wof:name":"Iraurgi Lantzen S.a.",
    "wof:placetype":"venue"
},
  "geometry": {"coordinates":[-2.3140389919,43.1782188416],"type":"Point"}
}