{
  "type": "Feature",
  "properties": {
    "addr:full":"Avda Tolerancia (de La), 12 Villares Madrid 28500",
    "addr:housenumber":"12",
    "addr:postcode":"28500",
    "addr:street":"Avda Tolerancia De La",
    "iso:country":"ES",
    "sg:address":"Avda Tolerancia (de La), 12",
    "sg:city":"Villares",
    "sg:orig_category":"Inmobiliaria (agencias)",
    "sg:phone":"+34 918 71 79 80",
    "sg:postcode":"28500",
    "sg:province":"Madrid",
    "wof:name":"Miranda Gonzalez Ana Belen",
    "wof:placetype":"venue"
},
  "geometry": {"coordinates":[-3.4406979084,40.2999954224],"type":"Point"}
}