{
  "type": "Feature",
  "properties": {
    "iso:country":"ES",
    "sg:address":"La Redondada, 8",
    "sg:city":"Requejo De La Vega",
    "sg:orig_category":"Fabricaci\u00d3n De Pernos, Tornillos Y Clavos",
    "sg:phone":"+34 987 64 45 61",
    "sg:postcode":"24763",
    "sg:province":"Le\u00f3n",
    "wof:name":"Rio Lopez Ramon Del",
    "wof:placetype":"venue"
},
  "geometry": {"coordinates":[-5.8558688164,42.3618392944],"type":"Point"}
}