{
  "type": "Feature",
  "properties": {
    "addr:full":"Rua Santo Graal, 82 Lugo Lugo 27003",
    "addr:housenumber":"82",
    "addr:postcode":"27003",
    "addr:street":"Rua Santo Graal",
    "iso:country":"ES",
    "sg:address":"Rua Santo Graal, 82",
    "sg:city":"Lugo",
    "sg:orig_category":"Fachadas",
    "sg:phone":"+34 982 20 22 30",
    "sg:postcode":"27003",
    "sg:province":"Lugo",
    "wof:name":"Conlugo S.l.",
    "wof:placetype":"venue"
},
  "geometry": {"coordinates":[-7.5726819038,43.0251274109],"type":"Point"}
}