{
  "type": "Feature",
  "properties": {
    "addr:full":"Av Carles Iii (de), 51 Vilassar De Mar Barcelona 08340",
    "addr:housenumber":"51",
    "addr:postcode":"08340",
    "addr:street":"Av Carles Iii De",
    "iso:country":"ES",
    "sg:address":"Av Carles Iii (de), 51",
    "sg:city":"Vilassar De Mar",
    "sg:orig_category":"Agencias Y Agentes Comerciales, Representantes",
    "sg:phone":"+34 937 59 41 08",
    "sg:postcode":"08340",
    "sg:province":"Barcelona",
    "wof:name":"Oroval Planas Esteve",
    "wof:placetype":"venue"
},
  "geometry": {"coordinates":[2.3889100552,41.5065994263],"type":"Point"}
}