{
  "type": "Feature",
  "properties": {
    "iso:country":"ES",
    "sg:address":"Calle de Entrepe\u00d1as, 7",
    "sg:city":"Alcala Henares",
    "sg:orig_category":"Contenedores (mercanc\u00cdas)",
    "sg:phone":"+34 918 89 11 11",
    "sg:postcode":"28803",
    "sg:province":"Madrid",
    "wof:name":"Alonso Mendoza Manuel",
    "wof:placetype":"venue"
},
  "geometry": {"coordinates":[-3.36439991,40.4699554443],"type":"Point"}
}