{
  "type": "Feature",
  "properties": {
    "addr:full":"F. Valdeaguas, S/n Fuente Maestre Badajoz 06360",
    "addr:housenumber":"s",
    "addr:postcode":"06360",
    "addr:street":"F. Valdeaguas;/ N Fuente Maestre",
    "iso:country":"ES",
    "sg:address":"F. Valdeaguas, S/n",
    "sg:city":"Fuente Maestre",
    "sg:orig_category":"Mec\u00c1nico Del Autom\u00d3vil",
    "sg:phone":"+34 924 53 09 44",
    "sg:postcode":"06360",
    "sg:province":"Badajoz",
    "wof:name":"Barrio Sanchez Antonio",
    "wof:placetype":"venue"
},
  "geometry": {"coordinates":[-6.442150116,38.5292739868],"type":"Point"}
}