{
  "type": "Feature",
  "properties": {
    "iso:country":"ES",
    "sg:address":"Calle de Marques De La Hermida, 64",
    "sg:city":"Santander",
    "sg:orig_category":"Estancos",
    "sg:phone":"+34 942 34 21 99",
    "sg:postcode":"39009",
    "sg:province":"Cantabria",
    "wof:name":"Gonzalez Gomez Eduardo Javier",
    "wof:placetype":"venue"
},
  "geometry": {"coordinates":[-3.8228120804,43.453037262],"type":"Point"}
}