{
  "type": "Feature",
  "properties": {
    "iso:country":"ES",
    "sg:address":"Carr Pare Palau, 94",
    "sg:city":"Aitona",
    "sg:orig_category":"Aceites Y Grasas Alimentarias (fabricaci\u00d3n, Al Por Mayor)",
    "sg:phone":"+34 973 79 40 16",
    "sg:postcode":"25182",
    "sg:province":"Lleida",
    "wof:name":"Gaya Samprieto Gayeta",
    "wof:placetype":"venue"
},
  "geometry": {"coordinates":[0.5191699862,41.4816703796],"type":"Point"}
}