{
  "type": "Feature",
  "properties": {
    "addr:full":"Rond Pio Basanta, 39 Mojados Valladolid 47250",
    "addr:housenumber":"39",
    "addr:postcode":"47250",
    "addr:street":"Basanta",
    "iso:country":"ES",
    "sg:address":"Rond Pio Basanta, 39",
    "sg:city":"Mojados",
    "sg:orig_category":"Electricidad: Instaladores",
    "sg:phone":"+34 983 60 71 12",
    "sg:postcode":"47250",
    "sg:province":"Valladolid",
    "wof:name":"Garcia Vaca Gregorio",
    "wof:placetype":"venue"
},
  "geometry": {"coordinates":[-4.6654248238,41.430393219],"type":"Point"}
}