{
  "type": "Feature",
  "properties": {
    "addr:full":"Cril Pablos, 8 Puente Tocinos Murcia 30006",
    "addr:housenumber":"8",
    "addr:postcode":"30006",
    "addr:street":"Pablos",
    "iso:country":"ES",
    "sg:address":"Cril Pablos, 8",
    "sg:city":"Puente Tocinos",
    "sg:orig_category":"Empresas De Limpieza",
    "sg:phone":"+34 968 30 10 61",
    "sg:postcode":"30006",
    "sg:province":"Murcia",
    "wof:name":"Abellon Sanchez Juana",
    "wof:placetype":"venue"
},
  "geometry": {"coordinates":[-1.094797,37.990208],"type":"Point"}
}