{
  "type": "Feature",
  "properties": {
    "addr:full":"Plaz Pintor Inocencio Medina Vera, 5 Vista Alegre Murcia 30007",
    "addr:housenumber":"5",
    "addr:postcode":"30007",
    "addr:street":"Plaz;Inocencio Medina Vera",
    "iso:country":"ES",
    "sg:address":"Plaz Pintor Inocencio Medina Vera, 5",
    "sg:city":"Vista Alegre",
    "sg:orig_category":"Pirotecnia (espect\u00c1culos)",
    "sg:phone":"+34 968 23 04 61",
    "sg:postcode":"30007",
    "sg:province":"Murcia",
    "wof:name":"Ortega Lopez Pedro",
    "wof:placetype":"venue"
},
  "geometry": {"coordinates":[-1.1142389774,37.9970092773],"type":"Point"}
}