{
  "type": "Feature",
  "properties": {
    "addr:full":"Carrer de Jaume Balmes, 43 S. Pere Ribes Barcelona 08810",
    "addr:housenumber":"43",
    "addr:postcode":"08810",
    "addr:street":"Carrer De Jaume Balmes;S. Pere Ribes Barcelona",
    "iso:country":"ES",
    "sg:address":"Carrer de Jaume Balmes, 43",
    "sg:city":"S. Pere Ribes",
    "sg:orig_category":"Chocolater\u00cda Y Exquisiteces",
    "sg:phone":"+34 938 96 47 08",
    "sg:postcode":"08810",
    "sg:province":"Barcelona",
    "wof:name":"Lon Pre Seleccion S.l.",
    "wof:placetype":"venue"
},
  "geometry": {"coordinates":[1.7708489895,41.2605781555],"type":"Point"}
}