{
  "type": "Feature",
  "properties": {
    "addr:full":"Miguel Hernandez, 8 Castro Rio C\u00f3rdoba 14840",
    "addr:housenumber":"8",
    "addr:postcode":"14840",
    "addr:street":"Miguel Hernandez;Rio Co\u0301Rdoba",
    "iso:country":"ES",
    "sg:address":"Miguel Hernandez, 8",
    "sg:city":"Castro Rio",
    "sg:orig_category":"Promotores Constructores",
    "sg:phone":"+34 957 37 25 76",
    "sg:postcode":"14840",
    "sg:province":"C\u00f3rdoba",
    "wof:name":"Cordobes Sanchez Juan",
    "wof:placetype":"venue"
},
  "geometry": {"coordinates":[-4.4870738983,37.6935997009],"type":"Point"}
}