{
  "type": "Feature",
  "properties": {
    "iso:country":"ES",
    "sg:address":"Urbanizacion A Campi\u00f1a, S/n",
    "sg:city":"Campi\u00f1a",
    "sg:orig_category":"Empresas De Carpinter\u00cda Met\u00c1lica",
    "sg:phone":"+34 982 30 32 14",
    "sg:postcode":"27192",
    "sg:province":"Lugo",
    "wof:name":"Lopez Mouriz C. B.",
    "wof:placetype":"venue"
},
  "geometry": {"coordinates":[-7.5558514595,43.0120849609],"type":"Point"}
}