{
  "type": "Feature",
  "properties": {
    "addr:full":"Carrer de Jacquard, 46 Sabadell Barcelona 08205",
    "addr:housenumber":"46",
    "addr:postcode":"08205",
    "addr:street":"Carrer De Jacquard",
    "iso:country":"ES",
    "sg:address":"Carrer de Jacquard, 46",
    "sg:city":"Sabadell",
    "sg:orig_category":"Fabricaci\u00d3n De Telas Y Sedas",
    "sg:phone":"+34 937 26 97 95",
    "sg:postcode":"08205",
    "sg:province":"Barcelona",
    "wof:name":"Sanchez Garcia Benito",
    "wof:placetype":"venue"
},
  "geometry": {"coordinates":[2.0973799229,41.5429115295],"type":"Point"}
}