{
  "type": "Feature",
  "properties": {
    "iso:country":"ES",
    "sg:address":"Plaz Santa Maria De Betancuria, S/n",
    "sg:city":"Betancuria",
    "sg:orig_category":"Bazares, Art\u00cdculos De Limpieza Y De Cocina (al Por Menor)",
    "sg:phone":"+34 928 87 84 27",
    "sg:postcode":"35637",
    "sg:province":"Las Palmas",
    "wof:name":"Teguise Mar S.l.",
    "wof:placetype":"venue"
},
  "geometry": {"coordinates":[-14.0574150085,28.4245796204],"type":"Point"}
}