{
  "type": "Feature",
  "properties": {
    "addr:full":"Av Escultor Monjo (de L'), 8 Vilassar De Mar Barcelona 08340",
    "addr:housenumber":"8",
    "addr:postcode":"08340",
    "addr:street":"Av Escultor Monjo De L '",
    "iso:country":"ES",
    "sg:address":"Av Escultor Monjo (de L'), 8",
    "sg:city":"Vilassar De Mar",
    "sg:orig_category":"Bancos",
    "sg:phone":"+34 937 59 26 96",
    "sg:postcode":"08340",
    "sg:province":"Barcelona",
    "wof:name":"Banco Popular Espa\u00f1ol",
    "wof:placetype":"venue"
},
  "geometry": {"coordinates":[2.3907299042,41.5019264221],"type":"Point"}
}