{
  "type": "Feature",
  "properties": {
    "iso:country":"ES",
    "sg:address":"Calle de Alondra, 19",
    "sg:city":"Aljaraque",
    "sg:orig_category":"Ingenier\u00cda, Centros De Estudios (diversos)",
    "sg:phone":"+34 959 31 72 23",
    "sg:postcode":"21110",
    "sg:province":"Huelva",
    "wof:name":"Sabando Gonzalez Fernando",
    "wof:placetype":"venue"
},
  "geometry": {"coordinates":[-7.0188212395,37.2693099976],"type":"Point"}
}