{
  "type": "Feature",
  "properties": {
    "iso:country":"ES",
    "sg:address":"Calle de Tercia, 22",
    "sg:city":"Campo Criptana",
    "sg:orig_category":"Zapatos (al Por Menor)",
    "sg:phone":"+34 926 56 10 58",
    "sg:postcode":"13610",
    "sg:province":"Ciudad Real",
    "wof:name":"Jesus Calzado Alarcos S.l.u.",
    "wof:placetype":"venue"
},
  "geometry": {"coordinates":[-3.1248428822,39.4037284851],"type":"Point"}
}