{
  "type": "Feature",
  "properties": {
    "addr:full":"Calle de Tofio, 1 Arrecife Las Palmas 35500",
    "addr:housenumber":"1",
    "addr:postcode":"35500",
    "addr:street":"Calle De Tofio",
    "iso:country":"ES",
    "sg:address":"Calle de Tofio, 1",
    "sg:city":"Arrecife",
    "sg:orig_category":"Molduras, Junquillos, Listones Y Molduras Perforadas",
    "sg:phone":"+34 928 81 58 51",
    "sg:postcode":"35500",
    "sg:province":"Las Palmas",
    "wof:name":"Hernandez Pacheco Zoilo Santiago",
    "wof:placetype":"venue"
},
  "geometry": {"coordinates":[-13.5576381683,28.9607906342],"type":"Point"}
}