{
  "type": "Feature",
  "properties": {
    "iso:country":"ES",
    "sg:address":"Calle de Miguel De Cervantes, 2",
    "sg:city":"Arenas San Pedro",
    "sg:orig_category":"Promotores Constructores",
    "sg:phone":"+34 920 37 06 47",
    "sg:postcode":"05400",
    "sg:province":"\u00c1vila",
    "wof:name":"Crejadel S.l",
    "wof:placetype":"venue"
},
  "geometry": {"coordinates":[-5.0951237679,40.2119445801],"type":"Point"}
}