{
  "type": "Feature",
  "properties": {
    "iso:country":"ES",
    "sg:address":"Calle de Castillo, 82",
    "sg:city":"Hornachuelos",
    "sg:orig_category":"Ense\u00d1anza: Profesiones Art\u00cdsticas",
    "sg:phone":"+34 957 64 01 23",
    "sg:postcode":"14740",
    "sg:province":"C\u00f3rdoba",
    "wof:name":"Molina Moreno Antonio De Lo Reyes",
    "wof:placetype":"venue"
},
  "geometry": {"coordinates":[-5.2454695702,37.8334693909],"type":"Point"}
}