{
  "type": "Feature",
  "properties": {
    "iso:country":"ES",
    "sg:address":"Carrer de Roger De Lluria, 31",
    "sg:city":"Cambrils",
    "sg:orig_category":"Peluquer\u00cdas, Peluquer\u00cda Mixta",
    "sg:phone":"+34 977 36 98 18",
    "sg:postcode":"43850",
    "sg:province":"Tarragona",
    "sg:website":"www.cebado.es",
    "wof:name":"Margalef Llao Marian",
    "wof:placetype":"venue"
},
  "geometry": {"coordinates":[1.0621249676,41.0670013428],"type":"Point"}
}