{
  "type": "Feature",
  "properties": {
    "iso:country":"ES",
    "sg:address":"Carr Sang De Crist, 7",
    "sg:city":"Villarreal",
    "sg:orig_category":"Sociedades, Compa\u00d1\u00cdas Aseguradoras",
    "sg:phone":"+34 964 52 05 05",
    "sg:postcode":"12540",
    "sg:province":"Castell\u00f3n",
    "wof:name":"Porcar Beltran Catalan S.l.l.",
    "wof:placetype":"venue"
},
  "geometry": {"coordinates":[-0.0952939987,39.9453048706],"type":"Point"}
}