{
  "type": "Feature",
  "properties": {
    "addr:full":"Pol Ind Las Yeguas, 10 Sanlucar Mayor Sevilla 41800",
    "addr:housenumber":"10",
    "addr:postcode":"41800",
    "addr:street":"Yeguas",
    "iso:country":"ES",
    "sg:address":"Pol Ind Las Yeguas, 10",
    "sg:city":"Sanlucar Mayor",
    "sg:orig_category":"Pintura Y Barniz (al Por Menor)",
    "sg:phone":"+34 955 70 12 13",
    "sg:postcode":"41800",
    "sg:province":"Sevilla",
    "wof:name":"Sevilla Color S.l.",
    "wof:placetype":"venue"
},
  "geometry": {"coordinates":[-6.1956338882,37.3855361938],"type":"Point"}
}