{
  "type": "Feature",
  "properties": {
    "addr:full":"Calle de Mayor, 77 Madrid Madrid 28013",
    "addr:housenumber":"77",
    "addr:postcode":"madrid;28013",
    "addr:street":"Calle De Mayor",
    "iso:country":"ES",
    "sg:address":"Calle de Mayor, 77",
    "sg:city":"Madrid",
    "sg:orig_category":"Arquitectos",
    "sg:phone":"+34 915 42 53 87",
    "sg:postcode":"28013",
    "sg:province":"Madrid",
    "wof:name":"Castellanos De Ubao Barbier Eduardo",
    "wof:placetype":"venue"
},
  "geometry": {"coordinates":[-3.7120389938,40.4151725769],"type":"Point"}
}