{
  "type": "Feature",
  "properties": {
    "addr:full":"Cm\u00f1o. Da Calzada, 22 Allariz Ourense 32660",
    "addr:housenumber":"22",
    "addr:postcode":"32660",
    "addr:street":"Calzada",
    "iso:country":"ES",
    "sg:address":"Cm\u00f1o. Da Calzada, 22",
    "sg:city":"Allariz",
    "sg:orig_category":"Centros Empresariales",
    "sg:phone":"+34 988 44 13 32",
    "sg:postcode":"32660",
    "sg:province":"Ourense",
    "wof:name":"Sodes S.a.",
    "wof:placetype":"venue"
},
  "geometry": {"coordinates":[-7.8033738136,42.1896362305],"type":"Point"}
}