{
  "type": "Feature",
  "properties": {
    "iso:country":"ES",
    "sg:address":"Carrer de Angel Guimera, 1",
    "sg:city":"Reus",
    "sg:orig_category":"Reposter\u00cdas",
    "sg:phone":"+34 977 31 59 60",
    "sg:postcode":"43202",
    "sg:province":"Tarragona",
    "wof:name":"Guzman Gonzalez Francisco",
    "wof:placetype":"venue"
},
  "geometry": {"coordinates":[1.0991729498,41.1585922241],"type":"Point"}
}