{
  "type": "Feature",
  "properties": {
    "addr:full":"Calle de La Florida, 5 San Vicente De Barakaldo Vizcaya 48902",
    "addr:postcode":"48902",
    "addr:street":"Calle De La Florida 5",
    "iso:country":"ES",
    "sg:address":"Calle de La Florida, 5",
    "sg:city":"San Vicente De Barakaldo",
    "sg:orig_category":"M\u00c9dicos: Estomatolog\u00cda",
    "sg:phone":"+34 944 38 73 45",
    "sg:postcode":"48902",
    "sg:province":"Vizcaya",
    "wof:name":"Sainz Medina Maria Bego\u00f1a",
    "wof:placetype":"venue"
},
  "geometry": {"coordinates":[-2.9879620075,43.2945251465],"type":"Point"}
}