{
  "type": "Feature",
  "properties": {
    "iso:country":"ES",
    "sg:address":"Filadores, 4",
    "sg:city":"Badalona",
    "sg:orig_category":"Camiser\u00cda Y Ropa Interior Masculina (al Por Menor)",
    "sg:phone":"+34 933 88 53 11",
    "sg:postcode":"08918",
    "sg:province":"Barcelona",
    "wof:name":"Novowink S.a.",
    "wof:placetype":"venue"
},
  "geometry": {"coordinates":[2.2364459038,41.4338760376],"type":"Point"}
}