{
  "type": "Feature",
  "properties": {
    "iso:country":"ES",
    "sg:address":"Calle de Archiduque Carlos, 61",
    "sg:city":"Valencia",
    "sg:orig_category":"Medias Y Calcetines (fabricaci\u00d3n, Al Por Mayor)",
    "sg:phone":"+34 963 77 03 96",
    "sg:postcode":"46018",
    "sg:province":"Valencia",
    "wof:name":"Gascon Beltran Pedro",
    "wof:placetype":"venue"
},
  "geometry": {"coordinates":[-0.3964298069,39.4635887146],"type":"Point"}
}