{
  "type": "Feature",
  "properties": {
    "iso:country":"ES",
    "sg:address":"Ctra San Cucao, 5",
    "sg:city":"Posada",
    "sg:orig_category":"Acero: Productos Sider\u00dargicos Y Transformados (fabricaci\u00d3n, Negocio)",
    "sg:phone":"+34 985 77 06 78",
    "sg:postcode":"33424",
    "sg:province":"Asturias",
    "wof:name":"Sidercal Minerales S.a.",
    "wof:placetype":"venue"
},
  "geometry": {"coordinates":[-5.8528108597,43.4384460449],"type":"Point"}
}