{
  "type": "Feature",
  "properties": {
    "addr:full":"Avda Mariano Andres, 193 Le\u00f3n Le\u00f3n 24008",
    "addr:housenumber":"193",
    "addr:postcode":"24008",
    "addr:street":"Avda Mariano Andres;Leo\u0301N",
    "iso:country":"ES",
    "sg:address":"Avda Mariano Andres, 193",
    "sg:city":"Le\u00f3n",
    "sg:orig_category":"Internados & Ense\u00d1anza Privada",
    "sg:phone":"+34 987 22 66 28",
    "sg:postcode":"24008",
    "sg:province":"Le\u00f3n",
    "wof:name":"Colegio De La Asuncion",
    "wof:placetype":"venue"
},
  "geometry": {"coordinates":[-5.5662660599,42.6189918518],"type":"Point"}
}