{
  "type": "Feature",
  "properties": {
    "addr:full":"Calle de Ramal (el), S/n Abalos La Rioja 26339",
    "addr:housenumber":"s / n",
    "addr:postcode":"26339",
    "addr:street":"Calle De Ramal El;Abalos;Rioja",
    "iso:country":"ES",
    "sg:address":"Calle de Ramal (el), S/n",
    "sg:city":"Abalos",
    "sg:orig_category":"Centros De Educaci\u00d3n Especial",
    "sg:phone":"+34 941 30 80 88",
    "sg:postcode":"26339",
    "sg:province":"La Rioja",
    "wof:name":"Centro Rural Agrupado San Vicente",
    "wof:placetype":"venue"
},
  "geometry": {"coordinates":[-2.7120420933,42.5725059509],"type":"Point"}
}