{
  "type": "Feature",
  "properties": {
    "addr:full":"Calle de Fernando Poo, 5 Madrid Madrid 28045",
    "addr:housenumber":"5",
    "addr:postcode":"28045",
    "addr:street":"Calle De Fernando Poo",
    "iso:country":"ES",
    "sg:address":"Calle de Fernando Poo, 5",
    "sg:city":"Madrid",
    "sg:orig_category":"Institutos De Belleza",
    "sg:phone":"+34 914 73 35 46",
    "sg:postcode":"28045",
    "sg:province":"Madrid",
    "wof:name":"Blasco Lucea Virginia",
    "wof:placetype":"venue"
},
  "geometry": {"coordinates":[-3.6993730068,40.3995742798],"type":"Point"}
}