{
  "type": "Feature",
  "properties": {
    "iso:country":"ES",
    "sg:address":"Carrer de Herrera, 47",
    "sg:city":"Mataro",
    "sg:orig_category":"Fabricaci\u00d3n De Su\u00c9ters Y Chalecos De Punto",
    "sg:phone":"+34 937 96 16 49",
    "sg:postcode":"08301",
    "sg:province":"Barcelona",
    "wof:name":"Nomes Punt S.l.",
    "wof:placetype":"venue"
},
  "geometry": {"coordinates":[2.4527719021,41.5436134338],"type":"Point"}
}