{
  "type": "Feature",
  "properties": {
    "addr:full":"Calle de Alvarez Quintero, 8 Sevilla Sevilla 41004",
    "addr:housenumber":"8",
    "addr:postcode":"41004",
    "addr:street":"Calle De Alvarez Quintero",
    "iso:country":"ES",
    "sg:address":"Calle de Alvarez Quintero, 8",
    "sg:city":"Sevilla",
    "sg:orig_category":"Art\u00cdculos De Regalo (al Por Menor)",
    "sg:phone":"+34 954 22 33 58",
    "sg:postcode":"41004",
    "sg:province":"Sevilla",
    "wof:name":"Alvarez-ossorio Alvarez Concepcion",
    "wof:placetype":"venue"
},
  "geometry": {"coordinates":[-5.9932918549,37.3895301819],"type":"Point"}
}