{
  "type": "Feature",
  "properties": {
    "iso:country":"ES",
    "sg:address":"Calle de San Vicente Martir, 172",
    "sg:city":"Valencia",
    "sg:orig_category":"Peluquer\u00cdas, Peluquer\u00cda Mixta",
    "sg:phone":"+34 963 41 75 10",
    "sg:postcode":"46007",
    "sg:province":"Valencia",
    "wof:name":"Onestetic S.l",
    "wof:placetype":"venue"
},
  "geometry": {"coordinates":[-0.3828130066,39.4611701965],"type":"Point"}
}