{
  "type": "Feature",
  "properties": {
    "addr:full":"Calle de Lerida, 47 Binefar Huesca 22500",
    "addr:housenumber":"47",
    "addr:postcode":"22500",
    "addr:street":"Calle De Lerida",
    "iso:country":"ES",
    "sg:address":"Calle de Lerida, 47",
    "sg:city":"Binefar",
    "sg:orig_category":"Cr\u00cda De Animales",
    "sg:phone":"+34 974 42 87 44",
    "sg:postcode":"22500",
    "sg:province":"Huesca",
    "wof:name":"Tomas Porte Isidro",
    "wof:placetype":"venue"
},
  "geometry": {"coordinates":[0.2969937921,41.8507919312],"type":"Point"}
}