{
  "type": "Feature",
  "properties": {
    "addr:full":"Meiras, S/n Meiras La Coru\u00f1a 15550",
    "addr:postcode":"15550",
    "addr:street":"Meiras S / N Meiras La Corun\u0303A",
    "iso:country":"ES",
    "sg:address":"Meiras, S/n",
    "sg:city":"Meiras",
    "sg:orig_category":"Asociaciones Y Clubs Deportivos",
    "sg:phone":"+34 981 48 65 55",
    "sg:postcode":"15550",
    "sg:province":"La Coru\u00f1a",
    "wof:name":"Meiras Club De Futbol",
    "wof:placetype":"venue"
},
  "geometry": {"coordinates":[-8.1737756729,43.5668754578],"type":"Point"}
}