{
  "type": "Feature",
  "properties": {
    "addr:full":"Plaz Rios (de Los), S/n Cuenca Cuenca 16001",
    "addr:housenumber":"/ n",
    "addr:postcode":"16001",
    "addr:street":"S",
    "iso:country":"ES",
    "sg:address":"Plaz Rios (de Los), S/n",
    "sg:city":"Cuenca",
    "sg:orig_category":"Cajas De Ahorro",
    "sg:phone":"+34 969 23 41 65",
    "sg:postcode":"16001",
    "sg:province":"Cuenca",
    "wof:name":"Caja De Ahorros De Castilla La Mancha",
    "wof:placetype":"venue"
},
  "geometry": {"coordinates":[-2.1362390518,40.0720710754],"type":"Point"}
}