{
  "type": "Feature",
  "properties": {
    "addr:full":"Calle de Peregrina, 1 Palmas De Gran Canaria Las Palmas 35002",
    "addr:housenumber":"1",
    "addr:postcode":"35002",
    "addr:street":"Calle De Peregrina",
    "iso:country":"ES",
    "sg:address":"Calle de Peregrina, 1",
    "sg:city":"Palmas De Gran Canaria",
    "sg:orig_category":"Caf\u00c9s, Bares, Cervecer\u00cdas",
    "sg:phone":"+34 928 36 67 74",
    "sg:postcode":"35002",
    "sg:province":"Las Palmas",
    "wof:name":"Rivero Rodriguez Jonas",
    "wof:placetype":"venue"
},
  "geometry": {"coordinates":[-15.4156227112,28.1027736664],"type":"Point"}
}