{
  "type": "Feature",
  "properties": {
    "addr:full":"Grup Alonso Allende, 15 Portugalete Vizcaya 48920",
    "addr:housenumber":"15",
    "addr:postcode":"48920",
    "addr:street":"Allende",
    "iso:country":"ES",
    "sg:address":"Grup Alonso Allende, 15",
    "sg:city":"Portugalete",
    "sg:orig_category":"Inform\u00c1tica: Mantenimiento Y Reparaci\u00d3n De Ordenadores",
    "sg:phone":"+34 944 96 52 98",
    "sg:postcode":"48920",
    "sg:province":"Vizcaya",
    "wof:name":"Soluciones Informaticas Biko S.l.",
    "wof:placetype":"venue"
},
  "geometry": {"coordinates":[-3.0164299011,43.3134689331],"type":"Point"}
}