{
  "type": "Feature",
  "properties": {
    "addr:full":"Calle de Alora, 18 Malaga M\u00e1laga 29004",
    "addr:housenumber":"18",
    "addr:postcode":"29004",
    "addr:street":"Calle De Alora;Ma\u0301Laga",
    "iso:country":"ES",
    "sg:address":"Calle de Alora, 18",
    "sg:city":"Malaga",
    "sg:orig_category":"Mec\u00c1nico Del Autom\u00d3vil",
    "sg:phone":"+34 952 24 15 66",
    "sg:postcode":"29004",
    "sg:province":"M\u00e1laga",
    "wof:name":"Talleres Raproel S.l.",
    "wof:placetype":"venue"
},
  "geometry": {"coordinates":[-4.4656767845,36.6809120178],"type":"Point"}
}