{
  "type": "Feature",
  "properties": {
    "iso:country":"ES",
    "sg:address":"Calle de Callao (de), 60",
    "sg:city":"Fuenlabrada",
    "sg:orig_category":"Peluquer\u00cdas, Peluquer\u00cda Mixta",
    "sg:phone":"+34 916 06 45 74",
    "sg:postcode":"28945",
    "sg:province":"Madrid",
    "wof:name":"Fraile Corcho Trinidad",
    "wof:placetype":"venue"
},
  "geometry": {"coordinates":[-3.7850925922,40.2946929932],"type":"Point"}
}