{
  "type": "Feature",
  "properties": {
    "addr:full":"Avda Arsenio Iglesias, S/n Arteixo La Coru\u00f1a 15142",
    "addr:postcode":"15142",
    "addr:street":"Avda Arsenio Iglesias S / N;La Corun\u0303A",
    "iso:country":"ES",
    "sg:address":"Avda Arsenio Iglesias, S/n",
    "sg:city":"Arteixo",
    "sg:orig_category":"Maquinaria Para Industrias Diversas",
    "sg:phone":"+34 981 64 09 80",
    "sg:postcode":"15142",
    "sg:province":"La Coru\u00f1a",
    "wof:name":"Alquigal-alquileres Galicia S.l.",
    "wof:placetype":"venue"
},
  "geometry": {"coordinates":[-8.5092220306,43.3099517822],"type":"Point"}
}