{
  "type": "Feature",
  "properties": {
    "iso:country":"ES",
    "sg:address":"Calle de Infantas, 21",
    "sg:city":"Madrid",
    "sg:orig_category":"Cine (producci\u00d3n, Realizaci\u00d3n)",
    "sg:phone":"+34 913 60 48 28",
    "sg:postcode":"28004",
    "sg:province":"Madrid",
    "wof:name":"El Rayo Films",
    "wof:placetype":"venue"
},
  "geometry": {"coordinates":[-3.6978878975,40.4202919006],"type":"Point"}
}