{
  "type": "Feature",
  "properties": {
    "addr:full":"Pl Infants, 12 Manresa Barcelona 08241",
    "addr:housenumber":"12",
    "addr:postcode":"08241",
    "addr:street":"Infants",
    "iso:country":"ES",
    "sg:address":"Pl Infants, 12",
    "sg:city":"Manresa",
    "sg:orig_category":"Cajas De Ahorro",
    "sg:phone":"+34 938 72 05 50",
    "sg:postcode":"08241",
    "sg:province":"Barcelona",
    "wof:name":"Caixa D'estalvis De Catalunya",
    "wof:placetype":"venue"
},
  "geometry": {"coordinates":[1.8269150257,41.7254066467],"type":"Point"}
}