{
  "type": "Feature",
  "properties": {
    "addr:full":"Paraje De Maldonado, S/n Monda M\u00e1laga 29110",
    "addr:housenumber":"s / n",
    "addr:postcode":"29110",
    "addr:street":"Paraje;Maldonado",
    "iso:country":"ES",
    "sg:address":"Paraje De Maldonado, S/n",
    "sg:city":"Monda",
    "sg:orig_category":"Arenas, Guijarros Y Granulados",
    "sg:phone":"+34 952 58 92 00",
    "sg:postcode":"29110",
    "sg:province":"M\u00e1laga",
    "wof:name":"Holcim Aridos S.l.",
    "wof:placetype":"venue"
},
  "geometry": {"coordinates":[-4.8280038834,36.6316719055],"type":"Point"}
}