{
  "type": "Feature",
  "properties": {
    "iso:country":"ES",
    "sg:address":"Calle de Cuevas, 1",
    "sg:city":"Motril",
    "sg:orig_category":"Ense\u00d1anza, Formaci\u00d3n Profesional: Aprendizaje",
    "sg:phone":"+34 958 83 31 90",
    "sg:postcode":"18600",
    "sg:province":"Granada",
    "sg:website":"www.en-costatropical.com",
    "wof:name":"Mancomunidad De Municipios Costa Tropical De Granada",
    "wof:placetype":"venue"
},
  "geometry": {"coordinates":[-3.5164110661,36.7447662354],"type":"Point"}
}