{
  "type": "Feature",
  "properties": {
    "addr:full":"Carrer de Pubilla Casas, 53 Esplugues Llobregat Barcelona 08950",
    "addr:housenumber":"53",
    "addr:postcode":"08950",
    "addr:street":"Carrer De Pubilla Casas",
    "iso:country":"ES",
    "sg:address":"Carrer de Pubilla Casas, 53",
    "sg:city":"Esplugues Llobregat",
    "sg:orig_category":"Institutos De Belleza",
    "sg:phone":"+34 934 73 61 99",
    "sg:postcode":"08950",
    "sg:province":"Barcelona",
    "wof:name":"Miranda Moreno Virtudes",
    "wof:placetype":"venue"
},
  "geometry": {"coordinates":[2.0995368958,41.3727798462],"type":"Point"}
}