{
  "type": "Feature",
  "properties": {
    "iso:country":"ES",
    "sg:address":"Calle de Brasil, 14",
    "sg:city":"Guarda",
    "sg:orig_category":"Internados & Ense\u00d1anza Privada",
    "sg:phone":"+34 986 61 01 55",
    "sg:postcode":"36780",
    "sg:province":"Pontevedra",
    "wof:name":"Colegio San Jose En La Guardia Carmelitas De La Caridad Prov Leon",
    "wof:placetype":"venue"
},
  "geometry": {"coordinates":[-8.8688240051,41.9064064026],"type":"Point"}
}