{
  "type": "Feature",
  "properties": {
    "addr:full":"Calle de General Casta\u00d1os, 4 Salamanca Salamanca 37006",
    "addr:housenumber":"4",
    "addr:postcode":"37006",
    "addr:street":"Calle De General Castan\u0303Os",
    "iso:country":"ES",
    "sg:address":"Calle de General Casta\u00d1os, 4",
    "sg:city":"Salamanca",
    "sg:orig_category":"Alquiler De Gr\u00daas",
    "sg:phone":"+34 923 22 90 78",
    "sg:postcode":"37006",
    "sg:province":"Salamanca",
    "wof:name":"Gruas F. Rio S.l.",
    "wof:placetype":"venue"
},
  "geometry": {"coordinates":[-5.6641550064,40.9745979309],"type":"Point"}
}