{
  "type": "Feature",
  "properties": {
    "iso:country":"ES",
    "sg:address":"Calle de San Lesmes, 6",
    "sg:city":"Burgos",
    "sg:orig_category":"Asesor\u00cda Fiscal Y Jur\u00cddica",
    "sg:phone":"+34 947 20 41 60",
    "sg:postcode":"09004",
    "sg:province":"Burgos",
    "wof:name":"Olalla Martinez Mariano",
    "wof:placetype":"venue"
},
  "geometry": {"coordinates":[-3.6969509125,42.341884613],"type":"Point"}
}