{
  "type": "Feature",
  "properties": {
    "iso:country":"ES",
    "sg:address":"Calle de Heros, 14",
    "sg:city":"Bilbao",
    "sg:orig_category":"Agencias Y Asesores De Publicidad",
    "sg:phone":"+34 944 23 00 72",
    "sg:postcode":"48009",
    "sg:province":"Vizcaya",
    "wof:name":"Signo Asociados S.l.",
    "wof:placetype":"venue"
},
  "geometry": {"coordinates":[-2.9323279858,43.2658462524],"type":"Point"}
}