{
  "type": "Feature",
  "properties": {
    "addr:full":"Ctra Santa Ana, S/n Fuente Del Rey Ja\u00e9n 23692",
    "addr:housenumber":"s / n",
    "addr:postcode":"23692",
    "addr:street":"Ctra Santa Ana;Jae\u0301N",
    "iso:country":"ES",
    "sg:address":"Ctra Santa Ana, S/n",
    "sg:city":"Fuente Del Rey",
    "sg:orig_category":"Material Y Herramientas Agr\u00cdcolas",
    "sg:phone":"+34 953 59 71 77",
    "sg:postcode":"23692",
    "sg:province":"Ja\u00e9n",
    "wof:name":"Aguilera Bermudez Antonio Marino",
    "wof:placetype":"venue"
},
  "geometry": {"coordinates":[-3.8982744217,37.4604454041],"type":"Point"}
}