{
  "type": "Feature",
  "properties": {
    "iso:country":"ES",
    "sg:address":"Calle de Genciana, 7",
    "sg:city":"Madrid",
    "sg:orig_category":"Ingeniero",
    "sg:phone":"+34 914 50 22 23",
    "sg:postcode":"28039",
    "sg:province":"Madrid",
    "wof:name":"Sholk  Maxim",
    "wof:placetype":"venue"
},
  "geometry": {"coordinates":[-3.7038109303,40.4638786316],"type":"Point"}
}