{
  "type": "Feature",
  "properties": {
    "addr:full":"Calle de Jose Zorrilla, 89 Segovia Segovia 40002",
    "addr:housenumber":"89",
    "addr:postcode":"40002",
    "addr:street":"Calle De Jose Zorrilla",
    "iso:country":"ES",
    "sg:address":"Calle de Jose Zorrilla, 89",
    "sg:city":"Segovia",
    "sg:orig_category":"Empresas De Carpinter\u00cda",
    "sg:phone":"+34 921 42 99 27",
    "sg:postcode":"40002",
    "sg:province":"Segovia",
    "wof:name":"Hernandez Villagroy Esteban",
    "wof:placetype":"venue"
},
  "geometry": {"coordinates":[-4.1146612167,40.9396743774],"type":"Point"}
}