{
  "type": "Feature",
  "properties": {
    "iso:country":"ES",
    "sg:address":"C/ Ciutat De Sevilla, 72",
    "sg:city":"Paterna",
    "sg:classifiers":[
        {
            "category":"Manufacturing",
            "subcategory":"Metals",
            "type":"Manufacturing & Wholesale Goods"
        }
    ],
    "sg:phone":"+34 961 34 16 65",
    "sg:postcode":"46988",
    "sg:province":"Valencia",
    "sg:tags":[
        "en",
        "fundiciones"
    ],
    "wof:name":"Bronces Levante S.l.",
    "wof:placetype":"venue"
},
  "geometry": {"coordinates":[-0.4662489891,39.522819519],"type":"Point"}
}