{
  "type": "Feature",
  "properties": {
    "addr:full":"Barr Cuatro Caminos, S/n Pedre\u00f1a Cantabria 39130",
    "addr:housenumber":"s",
    "addr:postcode":"39130",
    "addr:street":"Caminos;/ N",
    "iso:country":"ES",
    "sg:address":"Barr Cuatro Caminos, S/n",
    "sg:city":"Pedre\u00f1a",
    "sg:orig_category":"Carnicer\u00cdas, Carnicer\u00cdas",
    "sg:phone":"+34 942 50 03 64",
    "sg:postcode":"39130",
    "sg:province":"Cantabria",
    "wof:name":"Tricio San Emeterio Ricardo",
    "wof:placetype":"venue"
},
  "geometry": {"coordinates":[-3.7672259808,43.4420394897],"type":"Point"}
}