{
  "type": "Feature",
  "properties": {
    "iso:country":"ES",
    "sg:address":"Poligono Industrial, S/n",
    "sg:city":"San Claudio",
    "sg:orig_category":"Material Y Suministros Para Minas Y Canteras",
    "sg:phone":"+34 985 78 13 23",
    "sg:postcode":"33191",
    "sg:province":"Asturias",
    "wof:name":"Europa Minera S.a.",
    "wof:placetype":"venue"
},
  "geometry": {"coordinates":[-5.9176192284,43.3596382141],"type":"Point"}
}