{
  "type": "Feature",
  "properties": {
    "iso:country":"ES",
    "sg:address":"Avda Descubrimientos (los), S/n",
    "sg:city":"Mairena Aljarafe",
    "sg:orig_category":"Cajas De Ahorro",
    "sg:phone":"+34 954 18 67 24",
    "sg:postcode":"41927",
    "sg:province":"Sevilla",
    "wof:name":"Caixa D'estalvis De Catalunya",
    "wof:placetype":"venue"
},
  "geometry": {"coordinates":[-6.048664093,37.3507614136],"type":"Point"}
}