{
  "type": "Feature",
  "properties": {
    "iso:country":"ES",
    "sg:address":"Calle de Serrano, 29",
    "sg:city":"Tomelloso",
    "sg:classifiers":[
        {
            "category":"Taxi",
            "type":"Transportation"
        }
    ],
    "sg:phone":"+34 926 51 52 82",
    "sg:postcode":"13700",
    "sg:province":"Ciudad Real",
    "wof:name":"Lopez Benito Emilio",
    "wof:placetype":"venue"
},
  "geometry": {"coordinates":[-3.0279889107,39.1584396362],"type":"Point"}
}