{
  "type": "Feature",
  "properties": {
    "addr:full":"Calle de Ba\u00d1eza (de La), 19 Fuenlabrada Madrid 28947",
    "addr:housenumber":"19",
    "addr:postcode":"28947",
    "addr:street":"Calle De Ban\u0303Eza De La",
    "iso:country":"ES",
    "sg:address":"Calle de Ba\u00d1eza (de La), 19",
    "sg:city":"Fuenlabrada",
    "sg:orig_category":"Textiles: Suministros Y Accesorios Para Industrias (fabricaci\u00d3n, Negocio)",
    "sg:phone":"+34 916 42 14 83",
    "sg:postcode":"28947",
    "sg:province":"Madrid",
    "wof:name":"Moda Coco Import-export S.l.",
    "wof:placetype":"venue"
},
  "geometry": {"coordinates":[-3.7482612133,40.2662010193],"type":"Point"}
}