{
  "type": "Feature",
  "properties": {
    "iso:country":"ES",
    "sg:address":"Avda Literato Azorin, 3",
    "sg:city":"Yecla",
    "sg:orig_category":"Herboristas (al Por Menor)",
    "sg:phone":"+34 968 79 52 71",
    "sg:postcode":"30510",
    "sg:province":"Murcia",
    "wof:name":"Lopez Azorin Maria Belen",
    "wof:placetype":"venue"
},
  "geometry": {"coordinates":[-1.1060129404,38.6129074097],"type":"Point"}
}