{
  "type": "Feature",
  "properties": {
    "iso:country":"ES",
    "sg:address":"Calle de Azoka Kalea, 1",
    "sg:city":"Durango",
    "sg:orig_category":"Ense\u00d1anza: Idiomas",
    "sg:phone":"+34 944 66 93 73",
    "sg:postcode":"48200",
    "sg:province":"Vizcaya",
    "wof:name":"Yolanda Rodriguez Morera",
    "wof:placetype":"venue"
},
  "geometry": {"coordinates":[-2.6312289238,43.1690979004],"type":"Point"}
}