{
  "type": "Feature",
  "properties": {
    "addr:full":"Ctra Cordoba-malaga, Km. 0435,9 Montemayor C\u00f3rdoba 14530",
    "addr:postcode":"14530",
    "addr:street":"Ctra Cordoba-Malaga Km. 0435,9",
    "iso:country":"ES",
    "sg:address":"Ctra Cordoba-malaga, Km. 0435,9",
    "sg:city":"Montemayor",
    "sg:orig_category":"Mec\u00c1nico Del Autom\u00d3vil",
    "sg:phone":"+34 957 38 40 34",
    "sg:postcode":"14530",
    "sg:province":"C\u00f3rdoba",
    "wof:name":"Auto Monte Mayor S.l",
    "wof:placetype":"venue"
},
  "geometry": {"coordinates":[-4.704978466,37.6474075317],"type":"Point"}
}