{
  "type": "Feature",
  "properties": {
    "iso:country":"ES",
    "sg:address":"Calle de Monasterio Ntra Sra Del Pueyo, 3",
    "sg:city":"Zaragoza",
    "sg:orig_category":"Molduras, Junquillos, Listones Y Molduras Perforadas",
    "sg:phone":"+34 976 59 42 14",
    "sg:postcode":"50002",
    "sg:province":"Zaragoza",
    "wof:name":"Hernandez Soto Benito",
    "wof:placetype":"venue"
},
  "geometry": {"coordinates":[-0.8665360212,41.6463737488],"type":"Point"}
}