{
  "type": "Feature",
  "properties": {
    "iso:country":"ES",
    "sg:address":"Calle de Prieta, 5",
    "sg:city":"Conil De La Frontera",
    "sg:orig_category":"Electrodom\u00c9sticos (al Por Menor)",
    "sg:phone":"+34 956 44 03 09",
    "sg:postcode":"11140",
    "sg:province":"C\u00e1diz",
    "wof:name":"Mu\u00f1oz Aragon Jesus",
    "wof:placetype":"venue"
},
  "geometry": {"coordinates":[-6.088034153,36.2764434814],"type":"Point"}
}