{
  "type": "Feature",
  "properties": {
    "addr:full":"Calle de Carmen Tato, 9 Alacant Alicante 03005",
    "addr:housenumber":"9",
    "addr:postcode":"03005",
    "addr:street":"Calle De Carmen Tato",
    "iso:country":"ES",
    "sg:address":"Calle de Carmen Tato, 9",
    "sg:city":"Alacant",
    "sg:orig_category":"Inform\u00c1tica, Ofim\u00c1tica (estudios, Asesor\u00cda, Ingenier\u00cda, Formaci\u00d3n)",
    "sg:phone":"+34 965 92 49 12",
    "sg:postcode":"03005",
    "sg:province":"Alicante",
    "sg:website":"www.informaticakaos.com",
    "wof:name":"Kaos Informatica S.l.l.",
    "wof:placetype":"venue"
},
  "geometry": {"coordinates":[-0.4951424897,38.3469734192],"type":"Point"}
}