{
  "type": "Feature",
  "properties": {
    "addr:full":"Calle de Espoz Y Mina, 3 Santa Pola Alicante 03130",
    "addr:housenumber":"3",
    "addr:postcode":"03130",
    "addr:street":"Calle De Espoz Y Mina",
    "iso:country":"ES",
    "sg:address":"Calle de Espoz Y Mina, 3",
    "sg:city":"Santa Pola",
    "sg:orig_category":"Cajas Para Embalar",
    "sg:phone":"+34 965 41 29 06",
    "sg:postcode":"03130",
    "sg:province":"Alicante",
    "sg:website":"www.ruralcaja.es",
    "wof:name":"Caja Rural Del Mediterraneo Ruralcaja S Coop De Credito",
    "wof:placetype":"venue"
},
  "geometry": {"coordinates":[-0.5563719869,38.1914176941],"type":"Point"}
}