{
  "type": "Feature",
  "properties": {
    "iso:country":"ES",
    "sg:address":"Calle de Zurbano, 5",
    "sg:city":"Madrid",
    "sg:orig_category":"Agencias Y Agentes Comerciales, Representantes",
    "sg:phone":"+34 913 10 04 02",
    "sg:postcode":"28010",
    "sg:province":"Madrid",
    "wof:name":"Vi\u00f1uela Ferrero Luis",
    "wof:placetype":"venue"
},
  "geometry": {"coordinates":[-3.6939458847,40.4278068542],"type":"Point"}
}