{
  "type": "Feature",
  "properties": {
    "iso:country":"ES",
    "sg:address":"Carrer de Puig I Cadafalch, 1",
    "sg:city":"Sabadell",
    "sg:orig_category":"Peluquer\u00cdas, Peluquer\u00cda Mixta",
    "sg:phone":"+34 937 10 80 26",
    "sg:postcode":"08203",
    "sg:province":"Barcelona",
    "wof:name":"Arboleda Cuenca Yolanda",
    "wof:placetype":"venue"
},
  "geometry": {"coordinates":[2.1082010269,41.5381126404],"type":"Point"}
}