{
  "type": "Feature",
  "properties": {
    "iso:country":"ES",
    "sg:address":"Carrer de Remallaire (de La), 17",
    "sg:city":"Mataro",
    "sg:orig_category":"Inform\u00c1tica: Consultores",
    "sg:phone":"+34 937 58 86 46",
    "sg:postcode":"08302",
    "sg:province":"Barcelona",
    "wof:name":"Guell Consulting Technologies S.l.",
    "wof:placetype":"venue"
},
  "geometry": {"coordinates":[2.4297909737,41.5288276672],"type":"Point"}
}