{
  "type": "Feature",
  "properties": {
    "iso:country":"ES",
    "sg:address":"Calle de Picasso, S/n",
    "sg:city":"Mula",
    "sg:orig_category":"Producci\u00d3n, Venta De Productos De Agricultura Biol\u00d3gica",
    "sg:phone":"+34 968 66 09 13",
    "sg:postcode":"30170",
    "sg:province":"Murcia",
    "wof:name":"Conservas Marlu S.l.",
    "wof:placetype":"venue"
},
  "geometry": {"coordinates":[-1.4932340384,38.0388565063],"type":"Point"}
}