{
  "type": "Feature",
  "properties": {
    "addr:full":"Calle de General Rincon, 14 Coin M\u00e1laga 29100",
    "addr:housenumber":"14",
    "addr:postcode":"29100",
    "addr:street":"Calle De General Rincon;Ma\u0301Laga",
    "iso:country":"ES",
    "sg:address":"Calle de General Rincon, 14",
    "sg:city":"Coin",
    "sg:orig_category":"Fabricaci\u00d3n, Alquiler, Venta De Encofrados",
    "sg:phone":"+34 952 45 04 25",
    "sg:postcode":"29100",
    "sg:province":"M\u00e1laga",
    "wof:name":"Luna Hevilla Antonio",
    "wof:placetype":"venue"
},
  "geometry": {"coordinates":[-4.7549028397,36.6583518982],"type":"Point"}
}