{
  "type": "Feature",
  "properties": {
    "iso:country":"ES",
    "sg:address":"Calle de Pedro Mu\u00d1oz Seca, 20",
    "sg:city":"Puerto De Santa Maria",
    "sg:orig_category":"Confecci\u00d3n De Trajes Para Se\u00d1oras",
    "sg:phone":"+34 956 87 44 08",
    "sg:postcode":"11500",
    "sg:province":"C\u00e1diz",
    "wof:name":"Millan Aviles Rosario Maria",
    "wof:placetype":"venue"
},
  "geometry": {"coordinates":[-6.22666502,36.5990333557],"type":"Point"}
}