{
  "type": "Feature",
  "properties": {
    "addr:full":"Calle de Ruben Dario, 4 Navahermosa Toledo 45150",
    "addr:housenumber":"4",
    "addr:postcode":"45150",
    "addr:street":"Calle De Ruben Dario",
    "iso:country":"ES",
    "sg:address":"Calle de Ruben Dario, 4",
    "sg:city":"Navahermosa",
    "sg:orig_category":"Ferreter\u00cda Artesanal",
    "sg:phone":"+34 925 42 90 42",
    "sg:postcode":"45150",
    "sg:province":"Toledo",
    "wof:name":"De La Torre Navarro Juan Antonio",
    "wof:placetype":"venue"
},
  "geometry": {"coordinates":[-4.4798121452,39.6360168457],"type":"Point"}
}