{
  "type": "Feature",
  "properties": {
    "addr:full":"Calle de Santiago, 4 Palencia Palencia 34004",
    "addr:housenumber":"4",
    "addr:postcode":"34004",
    "addr:street":"Calle De Santiago",
    "iso:country":"ES",
    "sg:address":"Calle de Santiago, 4",
    "sg:city":"Palencia",
    "sg:orig_category":"Alquiler De V\u00cddeo",
    "sg:phone":"+34 979 72 56 00",
    "sg:postcode":"34004",
    "sg:province":"Palencia",
    "wof:name":"Video Club Acuario S.l.",
    "wof:placetype":"venue"
},
  "geometry": {"coordinates":[-4.522881031,41.9986038208],"type":"Point"}
}