{
  "type": "Feature",
  "properties": {
    "addr:full":"Calle de Fray Tomas Del Valle, S/n Algeciras C\u00e1diz 11202",
    "addr:housenumber":"/ n;ca\u0301diz",
    "addr:postcode":"11202",
    "addr:street":"Calle De Fray Tomas Del;S",
    "iso:country":"ES",
    "sg:address":"Calle de Fray Tomas Del Valle, S/n",
    "sg:city":"Algeciras",
    "sg:orig_category":"Ense\u00d1anza: Profesiones Art\u00cdsticas",
    "sg:phone":"+34 956 66 22 61",
    "sg:postcode":"11202",
    "sg:province":"C\u00e1diz",
    "wof:name":"Junta De Andalucia",
    "wof:placetype":"venue"
},
  "geometry": {"coordinates":[-5.4478421211,36.1374359131],"type":"Point"}
}