{
  "type": "Feature",
  "properties": {
    "addr:full":"Calle de Toledo, 66 Alcazar S. Juan Ciudad Real 13600",
    "addr:housenumber":"66",
    "addr:postcode":"13600",
    "addr:street":"Calle De Toledo;Alcazar S. Juan Ciudad Real",
    "iso:country":"ES",
    "sg:address":"Calle de Toledo, 66",
    "sg:city":"Alcazar S. Juan",
    "sg:orig_category":"Asistencia Social",
    "sg:phone":"+34 926 54 25 96",
    "sg:postcode":"13600",
    "sg:province":"Ciudad Real",
    "wof:name":"Asociacion De Servicios Aser",
    "wof:placetype":"venue"
},
  "geometry": {"coordinates":[-3.2158124447,39.3943099976],"type":"Point"}
}