{
  "type": "Feature",
  "properties": {
    "iso:country":"ES",
    "sg:address":"Calle de Arquitecto Arnau, 8",
    "sg:city":"Valencia",
    "sg:orig_category":"Peluqueros: De Se\u00d1oras",
    "sg:phone":"+34 963 62 56 95",
    "sg:postcode":"46020",
    "sg:province":"Valencia",
    "wof:name":"Iserte Saez Maria Manuela",
    "wof:placetype":"venue"
},
  "geometry": {"coordinates":[-0.3566600978,39.484462738],"type":"Point"}
}