{
  "type": "Feature",
  "properties": {
    "addr:full":"Calle de Los Fresnos, 39 Caceres C\u00e1ceres 10004",
    "addr:housenumber":"39",
    "addr:postcode":"10004",
    "addr:street":"Calle De Los Fresnos;Ca\u0301Ceres",
    "iso:country":"ES",
    "sg:address":"Calle de Los Fresnos, 39",
    "sg:city":"Caceres",
    "sg:orig_category":"Mudanzas",
    "sg:phone":"+34 927 18 22 02",
    "sg:postcode":"10004",
    "sg:province":"C\u00e1ceres",
    "wof:name":"Portillo Trejo Jose Manuel",
    "wof:placetype":"venue"
},
  "geometry": {"coordinates":[-6.3583831787,39.5027656555],"type":"Point"}
}