{
  "type": "Feature",
  "properties": {
    "addr:full":"Calle de Rosario, 12 Bollullos Par Condado Huelva 21710",
    "addr:housenumber":"12",
    "addr:postcode":"21710",
    "addr:street":"Calle De Rosario",
    "iso:country":"ES",
    "sg:address":"Calle de Rosario, 12",
    "sg:city":"Bollullos Par Condado",
    "sg:orig_category":"Reparaciones Y Remolcado De Veh\u00cdculos",
    "sg:phone":"+34 959 41 07 10",
    "sg:postcode":"21710",
    "sg:province":"Huelva",
    "wof:name":"Cano Valdayo Mario",
    "wof:placetype":"venue"
},
  "geometry": {"coordinates":[-6.5415949821,37.3479881287],"type":"Point"}
}