{
  "type": "Feature",
  "properties": {
    "iso:country":"ES",
    "sg:address":"Trva Meson, 3",
    "sg:city":"Albatera",
    "sg:orig_category":"Bisuter\u00cda, Joyer\u00cda, Relojer\u00cda (al Por Menor)",
    "sg:phone":"+34 965 48 60 01",
    "sg:postcode":"03340",
    "sg:province":"Alicante",
    "wof:name":"Juan Rubio Miguel Carmelo",
    "wof:placetype":"venue"
},
  "geometry": {"coordinates":[-0.871671021,38.1784133911],"type":"Point"}
}