{
  "type": "Feature",
  "properties": {
    "iso:country":"ES",
    "sg:address":"Calle de Diaz Moreu, 33",
    "sg:city":"Alacant",
    "sg:orig_category":"Empresas De Limpieza",
    "sg:phone":"+34 965 20 11 73",
    "sg:postcode":"03004",
    "sg:province":"Alicante",
    "sg:website":"www.arrakis.es/-roka",
    "wof:name":"Multiservicios Roka S.l.",
    "wof:placetype":"venue"
},
  "geometry": {"coordinates":[-0.4843640924,38.3494186401],"type":"Point"}
}