{
  "type": "Feature",
  "properties": {
    "iso:country":"ES",
    "sg:address":"Carrer de Major, 40",
    "sg:city":"Terrassa",
    "sg:orig_category":"M\u00c9dicos: Endocrinolog\u00cda Y Metabolismo",
    "sg:phone":"+34 937 88 08 86",
    "sg:postcode":"08221",
    "sg:province":"Barcelona",
    "wof:name":"Gorina Arnau Francisco",
    "wof:placetype":"venue"
},
  "geometry": {"coordinates":[2.009444952,41.561378479],"type":"Point"}
}