{
  "type": "Feature",
  "properties": {
    "addr:full":"Calle de Marinas, Km. 0011,0 Denia Alicante 03700",
    "addr:postcode":"03700",
    "addr:street":"Calle De Marinas Km. 0011,0",
    "iso:country":"ES",
    "sg:address":"Calle de Marinas, Km. 0011,0",
    "sg:city":"Denia",
    "sg:orig_category":"Promotores Constructores",
    "sg:phone":"+34 965 75 51 64",
    "sg:postcode":"03700",
    "sg:province":"Alicante",
    "wof:name":"Promociones Jilocasol S.l.",
    "wof:placetype":"venue"
},
  "geometry": {"coordinates":[0.1114400029,38.8428153992],"type":"Point"}
}