{
  "type": "Feature",
  "properties": {
    "addr:full":"Riera (la), 10 Mataro Barcelona 08301",
    "addr:postcode":"08301",
    "addr:street":"Riera;Mataro Barcelona",
    "iso:country":"ES",
    "sg:address":"Riera (la), 10",
    "sg:city":"Mataro",
    "sg:orig_category":"Farmacias",
    "sg:phone":"+34 937 90 10 58",
    "sg:postcode":"08301",
    "sg:province":"Barcelona",
    "wof:name":"Sempere Palacios Gema",
    "wof:placetype":"venue"
},
  "geometry": {"coordinates":[2.4469149113,41.5458068848],"type":"Point"}
}