{
  "type": "Feature",
  "properties": {
    "addr:full":"Calle de San Ignacio De Loyola, 6 Zaragoza Zaragoza 50008",
    "addr:housenumber":"6",
    "addr:postcode":"50008",
    "addr:street":"Calle De San Ignacio De Loyola",
    "iso:country":"ES",
    "sg:address":"Calle de San Ignacio De Loyola, 6",
    "sg:city":"Zaragoza",
    "sg:orig_category":"Empresarios",
    "sg:phone":"+34 976 21 24 50",
    "sg:postcode":"50008",
    "sg:province":"Zaragoza",
    "wof:name":"Bailo Remon Desiderio",
    "wof:placetype":"venue"
},
  "geometry": {"coordinates":[-0.8826398849,41.6473655701],"type":"Point"}
}