{
  "type": "Feature",
  "properties": {
    "iso:country":"ES",
    "sg:address":"Cortes, S/n",
    "sg:city":"Cortes",
    "sg:orig_category":"Empresarios",
    "sg:phone":"+34 981 86 05 07",
    "sg:postcode":"15920",
    "sg:province":"La Coru\u00f1a",
    "wof:name":"Iglesias Sanchez Alberto",
    "wof:placetype":"venue"
},
  "geometry": {"coordinates":[-8.8172187805,42.6528091431],"type":"Point"}
}