{
  "type": "Feature",
  "properties": {
    "addr:full":"Carrer de Antonio Machado, 4 Barcelona Barcelona 08042",
    "addr:housenumber":"4",
    "addr:postcode":"08042",
    "addr:street":"Carrer De Antonio Machado",
    "iso:country":"ES",
    "sg:address":"Carrer de Antonio Machado, 4",
    "sg:city":"Barcelona",
    "sg:orig_category":"Poller\u00cda Y Caza (al Por Menor)",
    "sg:phone":"+34 934 27 18 11",
    "sg:postcode":"08042",
    "sg:province":"Barcelona",
    "wof:name":"Casanovas Aixas Angel",
    "wof:placetype":"venue"
},
  "geometry": {"coordinates":[2.1634778976,41.441608429],"type":"Point"}
}