{
  "type": "Feature",
  "properties": {
    "addr:full":"Calle de Bolbaite, S/n Anna Valencia 46820",
    "addr:housenumber":"s / n",
    "addr:postcode":"46820",
    "addr:street":"Calle De Bolbaite",
    "iso:country":"ES",
    "sg:address":"Calle de Bolbaite, S/n",
    "sg:city":"Anna",
    "sg:orig_category":"Fabrica De Charcuter\u00cda",
    "sg:phone":"+34 962 21 06 07",
    "sg:postcode":"46820",
    "sg:province":"Valencia",
    "wof:name":"Sarrion Sala Antonio",
    "wof:placetype":"venue"
},
  "geometry": {"coordinates":[-0.6509659886,39.0242156982],"type":"Point"}
}