{
  "type": "Feature",
  "properties": {
    "iso:country":"ES",
    "sg:address":"Avda Jesus Morante Borras, 236",
    "sg:city":"Valencia",
    "sg:orig_category":"Contenedores Para Dep\u00d3sito De Sustancias Peligrosas (fabricaci\u00d3n, Al Por Mayor)",
    "sg:phone":"+34 963 67 79 82",
    "sg:postcode":"46012",
    "sg:province":"Valencia",
    "wof:name":"Reparacion De Containers S.l.",
    "wof:placetype":"venue"
},
  "geometry": {"coordinates":[-0.3438880146,39.4398841858],"type":"Point"}
}