{
  "type": "Feature",
  "properties": {
    "addr:full":"Carr Cibeles, S/n Grau I Platja Valencia 46730",
    "addr:housenumber":"s",
    "addr:postcode":"46730",
    "addr:street":"Carr Cibeles;/ N",
    "iso:country":"ES",
    "sg:address":"Carr Cibeles, S/n",
    "sg:city":"Grau I Platja",
    "sg:orig_category":"Supermercados Y Hipermercados",
    "sg:phone":"+34 962 84 38 00",
    "sg:postcode":"46730",
    "sg:province":"Valencia",
    "wof:name":"Princesalisimo S. L.",
    "wof:placetype":"venue"
},
  "geometry": {"coordinates":[-0.1620139927,38.9968032837],"type":"Point"}
}