{
  "type": "Feature",
  "properties": {
    "addr:full":"Carrer de Santa Eulalia, 23 Sabadell Barcelona 08208",
    "addr:housenumber":"23",
    "addr:postcode":"08208",
    "addr:street":"Carrer De Santa Eulalia",
    "iso:country":"ES",
    "sg:address":"Carrer de Santa Eulalia, 23",
    "sg:city":"Sabadell",
    "sg:orig_category":"Promotores Constructores",
    "sg:phone":"+34 937 16 35 21",
    "sg:postcode":"08208",
    "sg:province":"Barcelona",
    "wof:name":"Comunidad De Propietarios Santa Eulalia 23",
    "wof:placetype":"venue"
},
  "geometry": {"coordinates":[2.1015400887,41.5623970032],"type":"Point"}
}