{
  "type": "Feature",
  "properties": {
    "addr:full":"Avda Canovas Del Castillo, S/n Malaga M\u00e1laga 29016",
    "addr:housenumber":"s",
    "addr:postcode":"29016",
    "addr:street":"Avda Canovas Del Castillo;/ N;Ma\u0301Laga",
    "iso:country":"ES",
    "sg:address":"Avda Canovas Del Castillo, S/n",
    "sg:city":"Malaga",
    "sg:orig_category":"Iglesia Cat\u00d3lica",
    "sg:phone":"+34 952 21 08 36",
    "sg:postcode":"29016",
    "sg:province":"M\u00e1laga",
    "wof:name":"Obispado De Malaga",
    "wof:placetype":"venue"
},
  "geometry": {"coordinates":[-4.4106488228,36.7188186646],"type":"Point"}
}