{
  "type": "Feature",
  "properties": {
    "addr:full":"Ctra Villamediana, Km. 0003,5 Murillo De Rio Leza La Rioja 26143",
    "addr:postcode":"26143",
    "addr:street":"Ctra Villamediana Km. 0003,5;Rioja",
    "iso:country":"ES",
    "sg:address":"Ctra Villamediana, Km. 0003,5",
    "sg:city":"Murillo De Rio Leza",
    "sg:orig_category":"Reciclaje, Desguace De Veh\u00cdculos",
    "sg:phone":"+34 941 74 00 95",
    "sg:postcode":"26143",
    "sg:province":"La Rioja",
    "wof:name":"Saenz Saenz Gregorio",
    "wof:placetype":"venue"
},
  "geometry": {"coordinates":[-2.3255090714,42.401058197],"type":"Point"}
}