{
  "type": "Feature",
  "properties": {
    "addr:full":"Calle de Doctor Remon, 11 Autol La Rioja 26560",
    "addr:housenumber":"11",
    "addr:postcode":"26560",
    "addr:street":"Calle De Doctor Remon;Rioja",
    "iso:country":"ES",
    "sg:address":"Calle de Doctor Remon, 11",
    "sg:city":"Autol",
    "sg:orig_category":"Peluquer\u00cdas, Peluquer\u00cda Mixta",
    "sg:phone":"+34 941 40 13 09",
    "sg:postcode":"26560",
    "sg:province":"La Rioja",
    "wof:name":"Sat Los Vegalez",
    "wof:placetype":"venue"
},
  "geometry": {"coordinates":[-2.0041520596,42.2141265869],"type":"Point"}
}