{
  "type": "Feature",
  "properties": {
    "iso:country":"ES",
    "sg:address":"Avda Canarias, 322",
    "sg:city":"Vecindario",
    "sg:orig_category":"Fabricaci\u00d3n De Juegos Y Juguetes",
    "sg:phone":"+34 928 79 00 91",
    "sg:postcode":"35110",
    "sg:province":"Las Palmas",
    "wof:name":"Tatumundo S.l.",
    "wof:placetype":"venue"
},
  "geometry": {"coordinates":[-15.4444026947,27.845954895],"type":"Point"}
}