{
  "type": "Feature",
  "properties": {
    "addr:full":"Calle de Poligono Industrial La Frontera 3, 18 Ugena Toledo 45217",
    "addr:housenumber":"3 18",
    "addr:postcode":"45217",
    "addr:street":"Calle De Poligono Industrial La",
    "iso:country":"ES",
    "sg:address":"Calle de Poligono Industrial La Frontera 3, 18",
    "sg:city":"Ugena",
    "sg:orig_category":"Tratamiento De Metales",
    "sg:phone":"+34 925 53 35 41",
    "sg:postcode":"45217",
    "sg:province":"Toledo",
    "wof:name":"Esnipla S.l.",
    "wof:placetype":"venue"
},
  "geometry": {"coordinates":[-3.877669096,40.1581344604],"type":"Point"}
}