{
  "type": "Feature",
  "properties": {
    "iso:country":"ES",
    "sg:address":"Carrer de Muntaner, 551",
    "sg:city":"Barcelona",
    "sg:orig_category":"Ropa Para Beb\u00c9s Y Ni\u00d1os (confecci\u00d3n, Al Por Mayor)",
    "sg:phone":"+34 934 34 35 50",
    "sg:postcode":"08022",
    "sg:province":"Barcelona",
    "wof:name":"Colorful Licenses Espa\u00f1a S.l.",
    "wof:placetype":"venue"
},
  "geometry": {"coordinates":[2.135299921,41.4050331116],"type":"Point"}
}