{
  "type": "Feature",
  "properties": {
    "addr:full":"Carrer de Llibertat, 12-14 S. Boi Llobregat Barcelona 08830",
    "addr:housenumber":"12-14",
    "addr:postcode":"08830",
    "addr:street":"Carrer De Llibertat;S.",
    "iso:country":"ES",
    "sg:address":"Carrer de Llibertat, 12-14",
    "sg:city":"S. Boi Llobregat",
    "sg:orig_category":"Agencias De Viajes",
    "sg:phone":"+34 936 30 82 38",
    "sg:postcode":"08830",
    "sg:province":"Barcelona",
    "wof:name":"Aleina Club De Viatges S.l.",
    "wof:placetype":"venue"
},
  "geometry": {"coordinates":[2.0311610699,41.3473052979],"type":"Point"}
}