{
  "type": "Feature",
  "properties": {
    "iso:country":"ES",
    "sg:address":"Calle de Turin, 94",
    "sg:city":"Bahia De Javea",
    "sg:orig_category":"Int\u00c9rpretes",
    "sg:phone":"+34 965 79 07 13",
    "sg:postcode":"03730",
    "sg:province":"Alicante",
    "wof:name":"Duke  Robert Logan",
    "wof:placetype":"venue"
},
  "geometry": {"coordinates":[0.1570300013,38.7885093689],"type":"Point"}
}