{
  "type": "Feature",
  "properties": {
    "iso:country":"ES",
    "sg:address":"Ctra Marquesado (del), Km. 0000,2",
    "sg:city":"Chiclana De La Frontera",
    "sg:orig_category":"Asesor\u00cda Sobre Comunicaci\u00d3n De Empresas",
    "sg:phone":"+34 956 40 70 75",
    "sg:postcode":"11130",
    "sg:province":"C\u00e1diz",
    "sg:website":"www.asesoriaelmarquesado.com",
    "wof:name":"Troya Prado Rafael",
    "wof:placetype":"venue"
},
  "geometry": {"coordinates":[-6.1194581985,36.443939209],"type":"Point"}
}