{
  "type": "Feature",
  "properties": {
    "iso:country":"ES",
    "sg:address":"Calle de Fernandez Ladreda, 70",
    "sg:city":"Valladolid",
    "sg:orig_category":"Charcuter\u00cdas (al Por Mayor)",
    "sg:phone":"+34 983 27 49 80",
    "sg:postcode":"47008",
    "sg:province":"Valladolid",
    "wof:name":"Distribuciones De Alimentacion Martinez Pastor S.l.",
    "wof:placetype":"venue"
},
  "geometry": {"coordinates":[-4.7367019653,41.6262359619],"type":"Point"}
}