{
  "type": "Feature",
  "properties": {
    "iso:country":"ES",
    "sg:address":"Carrer de Doctor Pi I Molist, 13",
    "sg:city":"Barcelona",
    "sg:orig_category":"Ropa Para Ni\u00d1os (al Por Menor)",
    "sg:phone":"+34 934 08 54 69",
    "sg:postcode":"08031",
    "sg:province":"Barcelona",
    "wof:name":"Costa Martinez Esther",
    "wof:placetype":"venue"
},
  "geometry": {"coordinates":[2.1738870144,41.4320144653],"type":"Point"}
}