{
  "type": "Feature",
  "properties": {
    "addr:full":"Urb. Os Tilos, S/n Tilos La Coru\u00f1a 15894",
    "addr:housenumber":"s / n",
    "addr:postcode":"15894",
    "addr:street":"Tilos La Corun\u0303A",
    "iso:country":"ES",
    "sg:address":"Urb. Os Tilos, S/n",
    "sg:city":"Tilos",
    "sg:orig_category":"M\u00c9dicos: Cirug\u00cda Ortop\u00c9dica Y Traumatolog\u00cda",
    "sg:phone":"+34 981 80 10 96",
    "sg:postcode":"15894",
    "sg:province":"La Coru\u00f1a",
    "wof:name":"Concheiro Barreiro Gonzalo Ramon",
    "wof:placetype":"venue"
},
  "geometry": {"coordinates":[-8.5459394455,42.8326034546],"type":"Point"}
}