{
  "type": "Feature",
  "properties": {
    "addr:full":"Calle de Real Del Arrabal, 5 Toledo Toledo 45003",
    "addr:housenumber":"5",
    "addr:postcode":"45003",
    "addr:street":"Calle De Real Del Arrabal",
    "iso:country":"ES",
    "sg:address":"Calle de Real Del Arrabal, 5",
    "sg:city":"Toledo",
    "sg:orig_category":"Artesan\u00cda",
    "sg:phone":"+34 925 21 47 51",
    "sg:postcode":"45003",
    "sg:province":"Toledo",
    "wof:name":"Potenciano Fuertes-moreno Juan Pedro",
    "wof:placetype":"venue"
},
  "geometry": {"coordinates":[-4.0225868225,39.8611068726],"type":"Point"}
}