{
  "type": "Feature",
  "properties": {
    "addr:full":"Alza, S/n Ribadeo Lugo 27700",
    "addr:housenumber":"s / n",
    "addr:postcode":"27700",
    "iso:country":"ES",
    "sg:address":"Alza, S/n",
    "sg:city":"Ribadeo",
    "sg:orig_category":"Asociaciones Y Clubs Deportivos",
    "sg:phone":"+34 982 13 03 00",
    "sg:postcode":"27700",
    "sg:province":"Lugo",
    "wof:name":"Club De Tenis Ribadeo",
    "wof:placetype":"venue"
},
  "geometry": {"coordinates":[-7.0417490005,43.5329360962],"type":"Point"}
}