{
  "type": "Feature",
  "properties": {
    "addr:full":"Calle de Paco Miranda, S/n Malaga M\u00e1laga 29013",
    "addr:housenumber":"s / n",
    "addr:postcode":"29013",
    "addr:street":"Calle De Paco Miranda;Ma\u0301Laga",
    "iso:country":"ES",
    "sg:address":"Calle de Paco Miranda, S/n",
    "sg:city":"Malaga",
    "sg:orig_category":"Ingenier\u00cda, Centros De Estudios (diversos)",
    "sg:phone":"+34 952 26 24 09",
    "sg:postcode":"29013",
    "sg:province":"M\u00e1laga",
    "wof:name":"B.r.estudios Y Proyectos S.l.",
    "wof:placetype":"venue"
},
  "geometry": {"coordinates":[-4.4159288406,36.7323532104],"type":"Point"}
}