{
  "type": "Feature",
  "properties": {
    "iso:country":"ES",
    "sg:address":"Calle de Arguelles, 30",
    "sg:city":"Linares",
    "sg:orig_category":"Corridas",
    "sg:phone":"+34 953 69 08 49",
    "sg:postcode":"23700",
    "sg:province":"Ja\u00e9n",
    "wof:name":"Plaza De Toros",
    "wof:placetype":"venue"
},
  "geometry": {"coordinates":[-3.6323449612,38.0971755981],"type":"Point"}
}