{
  "type": "Feature",
  "properties": {
    "addr:full":"Ctra. Murcia, Km. 0235,7 Huercal-overa Almer\u00eda 04600",
    "addr:postcode":"04600",
    "addr:street":"Ctra. Murcia Km. 0235,7 Huercal-Overa Almeri\u0301A",
    "iso:country":"ES",
    "sg:address":"Ctra. Murcia, Km. 0235,7",
    "sg:city":"Huercal-overa",
    "sg:orig_category":"Empresas De Hormig\u00d3n, Hormig\u00d3n Armado Y Pretensado",
    "sg:phone":"+34 950 47 03 12",
    "sg:postcode":"04600",
    "sg:province":"Almer\u00eda",
    "wof:name":"Garcia Parra Alfonso",
    "wof:placetype":"venue"
},
  "geometry": {"coordinates":[-1.820622921,37.5610771179],"type":"Point"}
}