{
  "type": "Feature",
  "properties": {
    "iso:country":"ES",
    "sg:address":"Calle de Pedregal, 10",
    "sg:city":"Villarrobledo",
    "sg:orig_category":"Discapacitados",
    "sg:phone":"+34 967 14 23 94",
    "sg:postcode":"02600",
    "sg:province":"Albacete",
    "wof:name":"Fundacion Amparo Eres Y Marguenda",
    "wof:placetype":"venue"
},
  "geometry": {"coordinates":[-2.6000440121,39.264881134],"type":"Point"}
}