{
  "type": "Feature",
  "properties": {
    "iso:country":"ES",
    "sg:address":"Ctra Palomares, Km. 0001,0",
    "sg:city":"Mairena Aljarafe",
    "sg:orig_category":"Internados & Ense\u00d1anza Privada",
    "sg:phone":"+34 954 76 01 00",
    "sg:postcode":"41927",
    "sg:province":"Sevilla",
    "wof:name":"Colegio Del Aljarafe S.a.",
    "wof:placetype":"venue"
},
  "geometry": {"coordinates":[-6.0626192093,37.3473587036],"type":"Point"}
}