{
  "type": "Feature",
  "properties": {
    "iso:country":"ES",
    "sg:address":"Carrer de Sant Pere, 36",
    "sg:city":"Playa De Calafell",
    "sg:orig_category":"Comercio, Reparaci\u00d3n De Motocicletas, Bicicletas Y Piezas Sueltas",
    "sg:phone":"+34 977 69 36 68",
    "sg:postcode":"43820",
    "sg:province":"Tarragona",
    "wof:name":"Junyent Figueras Andres",
    "wof:placetype":"venue"
},
  "geometry": {"coordinates":[1.5694990158,41.1881141663],"type":"Point"}
}