{
  "type": "Feature",
  "properties": {
    "iso:country":"ES",
    "sg:address":"Tarrio, S/n",
    "sg:city":"Tarrio",
    "sg:orig_category":"Transportes Por V\u00cdas Navegables",
    "sg:phone":"+34 981 19 89 03",
    "sg:postcode":"15685",
    "sg:province":"La Coru\u00f1a",
    "wof:name":"Lata Castro Manuel",
    "wof:placetype":"venue"
},
  "geometry": {"coordinates":[-8.4406900406,42.9297523499],"type":"Point"}
}