{
  "type": "Feature",
  "properties": {
    "addr:full":"Plaz San Juan El Viejo, 8 Calatayud Zaragoza 50300",
    "addr:housenumber":"8",
    "addr:postcode":"50300",
    "addr:street":"Plaz;El Viejo",
    "iso:country":"ES",
    "sg:address":"Plaz San Juan El Viejo, 8",
    "sg:city":"Calatayud",
    "sg:orig_category":"Escayola Y Productos De Escayola (fabricaci\u00d3n, Al Por Mayor)",
    "sg:phone":"+34 976 88 16 13",
    "sg:postcode":"50300",
    "sg:province":"Zaragoza",
    "wof:name":"Navarro Hurtado Antonio",
    "wof:placetype":"venue"
},
  "geometry": {"coordinates":[-1.6449370384,41.3560676575],"type":"Point"}
}