{
  "type": "Feature",
  "properties": {
    "iso:country":"ES",
    "sg:address":"Calle de Zabaleta, 30",
    "sg:city":"Donostia-san Sebastian",
    "sg:orig_category":"Electricidad: Instaladores",
    "sg:phone":"+34 943 28 56 11",
    "sg:postcode":"20002",
    "sg:province":"Guip\u00f9zcoa",
    "wof:name":"Setalde Suministros Electricos S. A. L.",
    "wof:placetype":"venue"
},
  "geometry": {"coordinates":[-1.9736030102,43.3246917725],"type":"Point"}
}