{
  "type": "Feature",
  "properties": {
    "addr:full":"Carr Bellpuig, 17 Felanitx Islas Baleares 07200",
    "addr:housenumber":"17",
    "addr:postcode":"07200",
    "addr:street":"Carr Bellpuig",
    "iso:country":"ES",
    "sg:address":"Carr Bellpuig, 17",
    "sg:city":"Felanitx",
    "sg:orig_category":"Abogados",
    "sg:phone":"+34 971 58 17 52",
    "sg:postcode":"07200",
    "sg:province":"Islas Baleares",
    "wof:name":"Valladolid Cushion Abogados S. C.",
    "wof:placetype":"venue"
},
  "geometry": {"coordinates":[3.1525070667,39.4700012207],"type":"Point"}
}