{
  "type": "Feature",
  "properties": {
    "addr:full":"Carrer de Corsega, 349 Barcelona Barcelona 08037",
    "addr:housenumber":"349",
    "addr:postcode":"08037",
    "addr:street":"Carrer De Corsega",
    "iso:country":"ES",
    "sg:address":"Carrer de Corsega, 349",
    "sg:city":"Barcelona",
    "sg:orig_category":"Caf\u00c9s, Bares, Cervecer\u00cdas",
    "sg:phone":"+34 934 59 24 85",
    "sg:postcode":"08037",
    "sg:province":"Barcelona",
    "sg:website":"www.jamaicacoffeeshop.es",
    "wof:name":"Jamaica Loranca S.l.",
    "wof:placetype":"venue"
},
  "geometry": {"coordinates":[2.1615819931,41.3982963562],"type":"Point"}
}