{
  "type": "Feature",
  "properties": {
    "iso:country":"ES",
    "sg:address":"Av. Marques Villanueva Del Prado, S/n",
    "sg:city":"Puerto Cruz",
    "sg:orig_category":"Fabricaci\u00d3n, Importaci\u00d3n De Material Y Sistemas De Telecomunicaciones",
    "sg:phone":"+34 922 38 99 71",
    "sg:postcode":"38400",
    "sg:province":"Santa Cruz De Tenerife",
    "sg:website":"www.mediasshop2xs.net",
    "wof:name":"Media-world S.l.",
    "wof:placetype":"venue"
},
  "geometry": {"coordinates":[-16.5422172546,28.4132347107],"type":"Point"}
}