{
  "type": "Feature",
  "properties": {
    "addr:full":"Fco Bergamin, 14 Iru\u00f1a Navarra 31003",
    "addr:housenumber":"14",
    "addr:postcode":"31003",
    "addr:street":"Fco Bergamin",
    "iso:country":"ES",
    "sg:address":"Fco Bergamin, 14",
    "sg:city":"Iru\u00f1a",
    "sg:orig_category":"Ense\u00d1anza: Idiomas",
    "sg:phone":"+34 948 24 92 99",
    "sg:postcode":"31003",
    "sg:province":"Navarra",
    "wof:name":"Arandigoyen Urbiola Juan Jose",
    "wof:placetype":"venue"
},
  "geometry": {"coordinates":[-1.6414630413,42.8112335205],"type":"Point"}
}