{
  "type": "Feature",
  "properties": {
    "iso:country":"ES",
    "sg:address":"Carrer de Lima, 21",
    "sg:city":"Barcelona",
    "sg:orig_category":"Ropa Y Accesorios",
    "sg:phone":"+34 932 74 70 00",
    "sg:postcode":"08...",
    "sg:province":"Barcelona",
    "sg:website":"www.burberry.es",
    "wof:name":"Burberry Spain S.a.",
    "wof:placetype":"venue"
},
  "geometry": {"coordinates":[2.2060530186,41.4396934509],"type":"Point"}
}