{
  "type": "Feature",
  "properties": {
    "iso:country":"ES",
    "sg:address":"Carrer de Llibertat, 14",
    "sg:city":"Ondara",
    "sg:orig_category":"Electricidad, Electr\u00d3nica: Suministros (al Por Menor)",
    "sg:phone":"+34 965 76 66 76",
    "sg:postcode":"03760",
    "sg:province":"Alicante",
    "wof:name":"Oliver Mi\u00f1ana Maria",
    "wof:placetype":"venue"
},
  "geometry": {"coordinates":[0.0185630005,38.8269424438],"type":"Point"}
}