{
  "type": "Feature",
  "properties": {
    "iso:country":"ES",
    "sg:address":"Avda Ayora, S/n",
    "sg:city":"Casas De Juan Nu\u00e7ez",
    "sg:orig_category":"Distribuci\u00d3n De Petr\u00d3leo Y Derivados",
    "sg:phone":"+34 967 40 50 47",
    "sg:postcode":"02151",
    "sg:province":"Albacete",
    "wof:name":"Iba\u00f1ez Del Rey S.c.",
    "wof:placetype":"venue"
},
  "geometry": {"coordinates":[-1.5519030094,39.0994491577],"type":"Point"}
}