{
  "type": "Feature",
  "properties": {
    "addr:full":"Calle de Luis Piernas, 38 Madrid Madrid 28017",
    "addr:housenumber":"38",
    "addr:postcode":"madrid;28017",
    "addr:street":"Calle De Luis Piernas",
    "iso:country":"ES",
    "sg:address":"Calle de Luis Piernas, 38",
    "sg:city":"Madrid",
    "sg:orig_category":"Artes Gr\u00c1ficas, Artes Pl\u00c1sticas (curso)",
    "sg:phone":"+34 914 04 64 84",
    "sg:postcode":"28017",
    "sg:province":"Madrid",
    "wof:name":"Almodovar Sobrino Angela",
    "wof:placetype":"venue"
},
  "geometry": {"coordinates":[-3.6527481079,40.4268341064],"type":"Point"}
}