{
  "type": "Feature",
  "properties": {
    "addr:full":"Carrer de Font Dels Capellans, S/n Manresa Barcelona 08243",
    "addr:housenumber":"s / n",
    "addr:postcode":"08243",
    "addr:street":"Carrer De Font Dels Capellans",
    "iso:country":"ES",
    "sg:address":"Carrer de Font Dels Capellans, S/n",
    "sg:city":"Manresa",
    "sg:orig_category":"Farmacias",
    "sg:phone":"+34 938 74 78 00",
    "sg:postcode":"08243",
    "sg:province":"Barcelona",
    "wof:name":"Barcelona Pedret Juan Ramon",
    "wof:placetype":"venue"
},
  "geometry": {"coordinates":[1.8407640457,41.7305107117],"type":"Point"}
}