{
  "type": "Feature",
  "properties": {
    "addr:full":"Rua Gran Via, 216 Carballo La Coru\u00f1a 15100",
    "addr:housenumber":"216",
    "addr:postcode":"15100",
    "addr:street":"Rua Gran Via;La Corun\u0303A",
    "iso:country":"ES",
    "sg:address":"Rua Gran Via, 216",
    "sg:city":"Carballo",
    "sg:orig_category":"Deportes Diversos",
    "sg:phone":"+34 981 70 29 57",
    "sg:postcode":"15100",
    "sg:province":"La Coru\u00f1a",
    "wof:name":"Federacion Provincial De Caza De La Coru\u00f1a",
    "wof:placetype":"venue"
},
  "geometry": {"coordinates":[-8.6850347519,43.2209205627],"type":"Point"}
}