{
  "type": "Feature",
  "properties": {
    "addr:full":"Calle de Domingo De Sautu, 21 Murguia \u00c1lava 01130",
    "addr:housenumber":"21",
    "addr:postcode":"01130",
    "addr:street":"Calle De Domingo De Sautu;A\u0301Lava",
    "iso:country":"ES",
    "sg:address":"Calle de Domingo De Sautu, 21",
    "sg:city":"Murguia",
    "sg:orig_category":"Carnicer\u00cdas, Carnicer\u00cdas",
    "sg:phone":"+34 945 43 01 23",
    "sg:postcode":"01130",
    "sg:province":"\u00c1lava",
    "wof:name":"Arregui Velar Jose Luis",
    "wof:placetype":"venue"
},
  "geometry": {"coordinates":[-2.8200314045,42.9560852051],"type":"Point"}
}