{
  "type": "Feature",
  "properties": {
    "addr:full":"Carrer de Comadran, 11 Barbera Valles Barcelona 08210",
    "addr:housenumber":"11",
    "addr:postcode":"08210",
    "addr:street":"Carrer De Comadran",
    "iso:country":"ES",
    "sg:address":"Carrer de Comadran, 11",
    "sg:city":"Barbera Valles",
    "sg:orig_category":"Materias Pl\u00c1sticas: Productos Acabados Y Semiacabados (fabricaci\u00d3n)",
    "sg:phone":"+34 937 19 21 28",
    "sg:postcode":"08210",
    "sg:province":"Barcelona",
    "wof:name":"Mainplas S.l.",
    "wof:placetype":"venue"
},
  "geometry": {"coordinates":[2.1552400589,41.5135765076],"type":"Point"}
}