{
  "type": "Feature",
  "properties": {
    "iso:country":"ES",
    "sg:address":"Avgd Port, S/n",
    "sg:city":"Vila Joiosa",
    "sg:orig_category":"Caf\u00c9s, Bares, Cervecer\u00cdas",
    "sg:phone":"+34 966 85 19 80",
    "sg:postcode":"03570",
    "sg:province":"Alicante",
    "wof:name":"Ahoranet S.l.",
    "wof:placetype":"venue"
},
  "geometry": {"coordinates":[-0.222984001,38.5085868835],"type":"Point"}
}