{
  "type": "Feature",
  "properties": {
    "iso:country":"ES",
    "sg:address":"Ctra Briviesca, S/n",
    "sg:city":"Belorado",
    "sg:orig_category":"Hormigonados",
    "sg:phone":"+34 947 58 10 40",
    "sg:postcode":"09250",
    "sg:province":"Burgos",
    "wof:name":"Hortisa S.a.",
    "wof:placetype":"venue"
},
  "geometry": {"coordinates":[-3.1943469048,42.4489326477],"type":"Point"}
}