{
  "type": "Feature",
  "properties": {
    "iso:country":"ES",
    "sg:address":"Solidaritat, 14",
    "sg:city":"Aldaia",
    "sg:orig_category":"Mec\u00c1nico Del Autom\u00d3vil",
    "sg:phone":"+34 961 51 81 13",
    "sg:postcode":"46960",
    "sg:province":"Valencia",
    "wof:name":"Autoaldaya Motor S.l.",
    "wof:placetype":"venue"
},
  "geometry": {"coordinates":[-0.4560202062,39.4756011963],"type":"Point"}
}