{
  "type": "Feature",
  "properties": {
    "iso:country":"ES",
    "sg:address":"Horta, 28",
    "sg:city":"Godella",
    "sg:orig_category":"Inform\u00c1tica (estudios, Servicios, Asesor\u00cda, Formaci\u00d3n)",
    "sg:phone":"+34 963 63 78 61",
    "sg:postcode":"46110",
    "sg:province":"Valencia",
    "wof:name":"Alonso Alvarez Miguel",
    "wof:placetype":"venue"
},
  "geometry": {"coordinates":[-0.4117479026,39.5264930725],"type":"Point"}
}