{
  "type": "Feature",
  "properties": {
    "addr:full":"Calle de Martin Lopez, 14 Carmona Sevilla 41410",
    "addr:housenumber":"14",
    "addr:postcode":"41410",
    "addr:street":"Calle De Martin Lopez",
    "iso:country":"ES",
    "sg:address":"Calle de Martin Lopez, 14",
    "sg:city":"Carmona",
    "sg:orig_category":"Supermercados Y Hipermercados",
    "sg:phone":"+34 954 19 11 21",
    "sg:postcode":"41410",
    "sg:province":"Sevilla",
    "wof:name":"Super Rocio S.l.",
    "wof:placetype":"venue"
},
  "geometry": {"coordinates":[-5.6381559372,37.4729995728],"type":"Point"}
}