{
  "type": "Feature",
  "properties": {
    "addr:full":"Carr Asalto, 32 Pobla Islas Baleares 07420",
    "addr:housenumber":"32",
    "addr:postcode":"07420",
    "addr:street":"Carr Asalto;Baleares",
    "iso:country":"ES",
    "sg:address":"Carr Asalto, 32",
    "sg:city":"Pobla",
    "sg:orig_category":"Ense\u00d1anza: Profesiones Art\u00cdsticas",
    "sg:phone":"+34 971 54 06 83",
    "sg:postcode":"07420",
    "sg:province":"Islas Baleares",
    "wof:name":"Llompart Ochogavia Antonio",
    "wof:placetype":"venue"
},
  "geometry": {"coordinates":[3.0273399353,39.7708282471],"type":"Point"}
}