{
  "type": "Feature",
  "properties": {
    "addr:full":"Avda Gines Campos, 34 Alhama Murcia Murcia 30840",
    "addr:housenumber":"34",
    "addr:postcode":"30840",
    "addr:street":"Avda Gines Campos",
    "iso:country":"ES",
    "sg:address":"Avda Gines Campos, 34",
    "sg:city":"Alhama Murcia",
    "sg:orig_category":"Mec\u00c1nico Del Autom\u00d3vil",
    "sg:phone":"+34 968 63 22 70",
    "sg:postcode":"30840",
    "sg:province":"Murcia",
    "wof:name":"Garcia Cuestas Juan Andres",
    "wof:placetype":"venue"
},
  "geometry": {"coordinates":[-1.4126000404,37.853351593],"type":"Point"}
}