{
  "type": "Feature",
  "properties": {
    "addr:full":"Carr Pollentia, 14 Alcudia Islas Baleares 07400",
    "addr:housenumber":"14",
    "addr:postcode":"07400",
    "addr:street":"Carr Pollentia",
    "iso:country":"ES",
    "sg:address":"Carr Pollentia, 14",
    "sg:city":"Alcudia",
    "sg:orig_category":"Art\u00cdculos De Decoraci\u00d3n",
    "sg:phone":"+34 971 54 83 03",
    "sg:postcode":"07400",
    "sg:province":"Islas Baleares",
    "wof:name":"Macipa S.l.",
    "wof:placetype":"venue"
},
  "geometry": {"coordinates":[3.1247808933,39.8521080017],"type":"Point"}
}