{
  "type": "Feature",
  "properties": {
    "iso:country":"ES",
    "sg:address":"Carr Mare De Deu De Les Neus, 3",
    "sg:city":"Bunyola",
    "sg:orig_category":"Centros De Educaci\u00d3n Especial",
    "sg:phone":"+34 971 61 35 24",
    "sg:postcode":"07110",
    "sg:province":"Islas Baleares",
    "wof:name":"Ajuntament De Bunyola",
    "wof:placetype":"venue"
},
  "geometry": {"coordinates":[2.6997725964,39.6960601807],"type":"Point"}
}