{
  "type": "Feature",
  "properties": {
    "iso:country":"ES",
    "sg:address":"Carrer de Pau (de Na), 14",
    "sg:city":"Mataro",
    "sg:orig_category":"Artes Gr\u00c1ficas, Artes Pl\u00c1sticas (curso)",
    "sg:phone":"+34 937 55 02 73",
    "sg:postcode":"08301",
    "sg:province":"Barcelona",
    "wof:name":"Lleuc S.c.p.",
    "wof:placetype":"venue"
},
  "geometry": {"coordinates":[2.4467298985,41.5397796631],"type":"Point"}
}