{
  "type": "Feature",
  "properties": {
    "iso:country":"ES",
    "sg:address":"Avda Florida, 12",
    "sg:city":"Vigo",
    "sg:orig_category":"Cajas De Ahorro",
    "sg:phone":"+34 986 21 32 28",
    "sg:postcode":"36210",
    "sg:province":"Pontevedra",
    "sg:website":"www.bancaja.es",
    "wof:name":"Caja De Ahorros De Valencia Castellon Y Alicante",
    "wof:placetype":"venue"
},
  "geometry": {"coordinates":[-8.7476491928,42.2103309631],"type":"Point"}
}