{
  "type": "Feature",
  "properties": {
    "addr:full":"Calle de San Jeronimo, 22 Donostia-san Sebastian Guip\u00f9zcoa 20003",
    "addr:housenumber":"22",
    "addr:postcode":"20003",
    "addr:street":"Calle De San Jeronimo",
    "iso:country":"ES",
    "sg:address":"Calle de San Jeronimo, 22",
    "sg:city":"Donostia-san Sebastian",
    "sg:orig_category":"Perfumer\u00cda (al Por Menor)",
    "sg:phone":"+34 943 43 01 18",
    "sg:postcode":"20003",
    "sg:province":"Guip\u00f9zcoa",
    "wof:name":"Narros Gago Victoria",
    "wof:placetype":"venue"
},
  "geometry": {"coordinates":[-1.985532999,43.3239250183],"type":"Point"}
}