{
  "type": "Feature",
  "properties": {
    "addr:full":"Rio Guadiaro (p I La Rosa), 44 Alhaurin Grande M\u00e1laga 29120",
    "addr:housenumber":"44",
    "addr:postcode":"29120",
    "addr:street":"Rio Guadiaro P;La Rosa",
    "iso:country":"ES",
    "sg:address":"Rio Guadiaro (p I La Rosa), 44",
    "sg:city":"Alhaurin Grande",
    "sg:orig_category":"Importaci\u00d3n",
    "sg:phone":"+34 952 59 67 21",
    "sg:postcode":"29120",
    "sg:province":"M\u00e1laga",
    "wof:name":"Importaciones Macias S.l.",
    "wof:placetype":"venue"
},
  "geometry": {"coordinates":[-4.6899290085,36.659828186],"type":"Point"}
}