{
  "type": "Feature",
  "properties": {
    "iso:country":"ES",
    "sg:address":"Calle de Maldonado, 1",
    "sg:city":"Mora",
    "sg:orig_category":"M\u00c1quinas De Coser Y De Hacer Punto (al Por Mayor)",
    "sg:phone":"+34 925 30 04 14",
    "sg:postcode":"45400",
    "sg:province":"Toledo",
    "wof:name":"Margom S.c.",
    "wof:placetype":"venue"
},
  "geometry": {"coordinates":[-3.7807190418,39.6822052002],"type":"Point"}
}