{
  "type": "Feature",
  "properties": {
    "addr:full":"Calle de Alfonso Vi, 4 Toledo Toledo 45003",
    "addr:housenumber":"4",
    "addr:postcode":"45003",
    "addr:street":"Calle De Alfonso Vi",
    "iso:country":"ES",
    "sg:address":"Calle de Alfonso Vi, 4",
    "sg:city":"Toledo",
    "sg:orig_category":"Iglesia Cat\u00d3lica",
    "sg:phone":"+34 925 21 37 34",
    "sg:postcode":"45003",
    "sg:province":"Toledo",
    "wof:name":"Parroquia Santiago El Mayor",
    "wof:placetype":"venue"
},
  "geometry": {"coordinates":[-4.0258421898,39.862361908],"type":"Point"}
}