{
  "type": "Feature",
  "properties": {
    "iso:country":"ES",
    "sg:address":"Av Olivera, 11",
    "sg:city":"Magaluf",
    "sg:orig_category":"Molduras, Junquillos, Listones Y Molduras Perforadas",
    "sg:phone":"+34 971 13 20 40",
    "sg:postcode":"07181",
    "sg:province":"Islas Baleares",
    "wof:name":"Perez Rodriguez Victor",
    "wof:placetype":"venue"
},
  "geometry": {"coordinates":[2.5321509838,39.5081748962],"type":"Point"}
}