{
  "type": "Feature",
  "properties": {
    "addr:full":"Puerto De Denia, 1 Denia Alicante 03700",
    "addr:housenumber":"1",
    "addr:postcode":"03700",
    "addr:street":"Puerto De Denia",
    "iso:country":"ES",
    "sg:address":"Puerto De Denia, 1",
    "sg:city":"Denia",
    "sg:orig_category":"Inmobiliaria (agencias)",
    "sg:phone":"+34 965 78 53 25",
    "sg:postcode":"03700",
    "sg:province":"Alicante",
    "wof:name":"Cafe Bar Latitude",
    "wof:placetype":"venue"
},
  "geometry": {"coordinates":[0.1114400029,38.8428153992],"type":"Point"}
}