{
  "type": "Feature",
  "properties": {
    "iso:country":"ES",
    "sg:address":"Ctra Alcazar, Km. 0008,2",
    "sg:city":"Miguel Esteban",
    "sg:orig_category":"Calderer\u00cda",
    "sg:phone":"+34 925 17 20 63",
    "sg:postcode":"45830",
    "sg:province":"Toledo",
    "wof:name":"Talleres Ferji S. L.",
    "wof:placetype":"venue"
},
  "geometry": {"coordinates":[-3.0778141022,39.5287094116],"type":"Point"}
}