{
  "type": "Feature",
  "properties": {
    "iso:country":"ES",
    "sg:address":"Calle de Casas Iba\u00d1ez, 2",
    "sg:city":"Alborea",
    "sg:orig_category":"Asociaciones, Organismos Culturales Y Socioeducativos",
    "sg:phone":"+34 967 47 71 57",
    "sg:postcode":"02215",
    "sg:province":"Albacete",
    "wof:name":"Ayuntamiento De Alborea",
    "wof:placetype":"venue"
},
  "geometry": {"coordinates":[-1.3972353935,39.2797088623],"type":"Point"}
}