{
  "type": "Feature",
  "properties": {
    "addr:full":"Pl Ajuntament (de L'), 6 Vilassar De Mar Barcelona 08340",
    "addr:postcode":"08340",
    "addr:street":"Pl;'",
    "iso:country":"ES",
    "sg:address":"Pl Ajuntament (de L'), 6",
    "sg:city":"Vilassar De Mar",
    "sg:orig_category":"Ense\u00d1anza, Formaci\u00d3n Profesional: Aprendizaje",
    "sg:phone":"+34 937 54 24 00",
    "sg:postcode":"08340",
    "sg:province":"Barcelona",
    "wof:name":"Ajuntament De Vilassar De Mar",
    "wof:placetype":"venue"
},
  "geometry": {"coordinates":[2.3957941532,41.5036239624],"type":"Point"}
}