{
  "type": "Feature",
  "properties": {
    "iso:country":"ES",
    "sg:address":"Carrer de Pau Casals, S/n",
    "sg:city":"S. Boi Llobregat",
    "sg:orig_category":"Carnicer\u00cdas, Carnicer\u00cdas",
    "sg:phone":"+34 936 40 63 85",
    "sg:postcode":"08830",
    "sg:province":"Barcelona",
    "wof:name":"Pares Closa Juan",
    "wof:placetype":"venue"
},
  "geometry": {"coordinates":[2.0302500725,41.3577194214],"type":"Point"}
}