{
  "type": "Feature",
  "properties": {
    "addr:full":"Calle de Villa Carmela, 1 Logro\u00f1o La Rioja 26006",
    "addr:housenumber":"1",
    "addr:postcode":"26006",
    "addr:street":"Calle De Villa Carmela;Rioja",
    "iso:country":"ES",
    "sg:address":"Calle de Villa Carmela, 1",
    "sg:city":"Logro\u00f1o",
    "sg:orig_category":"Asesor\u00cda De Formaci\u00d3n Y Gesti\u00d3n De Personal",
    "sg:phone":"+34 941 44 98 92",
    "sg:postcode":"26006",
    "sg:province":"La Rioja",
    "wof:name":"Montero Maria-cospedal Rafael",
    "wof:placetype":"venue"
},
  "geometry": {"coordinates":[-2.4036989212,42.46043396],"type":"Point"}
}