{
  "type": "Feature",
  "properties": {
    "addr:full":"Ctra. Malaga, Km. 0340,0 Mollina M\u00e1laga 29532",
    "addr:postcode":"29532",
    "addr:street":"Ctra. Malaga Km. 0340,0;Ma\u0301Laga",
    "iso:country":"ES",
    "sg:address":"Ctra. Malaga, Km. 0340,0",
    "sg:city":"Mollina",
    "sg:orig_category":"Producci\u00d3n, Comercio De Cereales",
    "sg:phone":"+34 952 03 14 31",
    "sg:postcode":"29532",
    "sg:province":"M\u00e1laga",
    "wof:name":"Aceitunas Y Cereales Huracan S.l.",
    "wof:placetype":"venue"
},
  "geometry": {"coordinates":[-4.6586637497,37.1292266846],"type":"Point"}
}