{
  "type": "Feature",
  "properties": {
    "iso:country":"ES",
    "sg:address":"Carrer de Pare Joan Crespi, 14",
    "sg:city":"Palma",
    "sg:orig_category":"Molduras, Junquillos, Listones Y Molduras Perforadas",
    "sg:phone":"+34 971 47 27 97",
    "sg:postcode":"07008",
    "sg:province":"Islas Baleares",
    "wof:name":"Torregrosa Garrido Eva",
    "wof:placetype":"venue"
},
  "geometry": {"coordinates":[2.6736729145,39.5833091736],"type":"Point"}
}