{
  "type": "Feature",
  "properties": {
    "addr:full":"Olmo, S/n Caraquiz Guadalajara 19185",
    "addr:postcode":"19185",
    "addr:street":"Olmo S / N Caraquiz",
    "iso:country":"ES",
    "sg:address":"Olmo, S/n",
    "sg:city":"Caraquiz",
    "sg:orig_category":"Complementos De Vestir (al Por Menor)",
    "sg:phone":"+34 949 85 79 78",
    "sg:postcode":"19185",
    "sg:province":"Guadalajara",
    "wof:name":"Ure\u00f1a Morales Francisca",
    "wof:placetype":"venue"
},
  "geometry": {"coordinates":[-3.4905240536,40.7870941162],"type":"Point"}
}