{
  "type": "Feature",
  "properties": {
    "addr:full":"Vallina, 5 Navia Asturias 33710",
    "addr:housenumber":"5",
    "addr:postcode":"33710",
    "addr:street":"Vallina",
    "iso:country":"ES",
    "sg:address":"Vallina, 5",
    "sg:city":"Navia",
    "sg:orig_category":"Imprenta",
    "sg:phone":"+34 985 47 34 33",
    "sg:postcode":"33710",
    "sg:province":"Asturias",
    "wof:name":"Vega Fernandez Maria Jesus",
    "wof:placetype":"venue"
},
  "geometry": {"coordinates":[-6.7245330811,43.5406150818],"type":"Point"}
}