{
  "type": "Feature",
  "properties": {
    "addr:full":"Ctra. Guadalupe, Km. 0001,5 Villanueva Serena Badajoz 06700",
    "addr:postcode":"06700",
    "addr:street":"Ctra. Guadalupe Km. 0001,5",
    "iso:country":"ES",
    "sg:address":"Ctra. Guadalupe, Km. 0001,5",
    "sg:city":"Villanueva Serena",
    "sg:orig_category":"Escayola Y Productos De Escayola (fabricaci\u00d3n, Al Por Mayor)",
    "sg:phone":"+34 924 84 55 78",
    "sg:postcode":"06700",
    "sg:province":"Badajoz",
    "wof:name":"Manuel Carmona Nieto S.l.",
    "wof:placetype":"venue"
},
  "geometry": {"coordinates":[-5.7927408218,38.9731750488],"type":"Point"}
}