{
  "type": "Feature",
  "properties": {
    "addr:full":"A Madanela, 22 Lampon La Coru\u00f1a 15992",
    "addr:housenumber":"22",
    "addr:postcode":"15992",
    "addr:street":"Lampon La Corun\u0303A",
    "iso:country":"ES",
    "sg:address":"A Madanela, 22",
    "sg:city":"Lampon",
    "sg:orig_category":"Guarder\u00cdas",
    "sg:phone":"+34 981 84 47 31",
    "sg:postcode":"15992",
    "sg:province":"La Coru\u00f1a",
    "wof:name":"Religiosas Hijas De La Caridad",
    "wof:placetype":"venue"
},
  "geometry": {"coordinates":[-8.9047136307,42.6364364624],"type":"Point"}
}