{
  "type": "Feature",
  "properties": {
    "addr:full":"Calle de Prieta, 2 Conil De La Frontera C\u00e1diz 11140",
    "addr:housenumber":"2",
    "addr:postcode":"11140",
    "addr:street":"Calle De Prieta",
    "iso:country":"ES",
    "sg:address":"Calle de Prieta, 2",
    "sg:city":"Conil De La Frontera",
    "sg:orig_category":"Centros De Coordinaci\u00d3n",
    "sg:phone":"+34 956 44 12 79",
    "sg:postcode":"11140",
    "sg:province":"C\u00e1diz",
    "wof:name":"Gonzalez Fernandez Alejandro",
    "wof:placetype":"venue"
},
  "geometry": {"coordinates":[-6.0882639885,36.2764129639],"type":"Point"}
}