{
  "type": "Feature",
  "properties": {
    "iso:country":"ES",
    "sg:address":"D (p I Store), 4",
    "sg:city":"Sevilla",
    "sg:orig_category":"Fabricaci\u00d3n, Importaci\u00d3n, Venta De Material De Telefon\u00cda, Peritelefon\u00cda",
    "sg:phone":"+34 954 35 16 71",
    "sg:postcode":"41008",
    "sg:province":"Sevilla",
    "wof:name":"Nexans Iberia S.l.",
    "wof:placetype":"venue"
},
  "geometry": {"coordinates":[-5.9678640366,37.3363685608],"type":"Point"}
}