{
  "type": "Feature",
  "properties": {
    "addr:full":"Calle de Pinto, 29 Parla Madrid 28980",
    "addr:housenumber":"29",
    "addr:postcode":"28980",
    "addr:street":"Calle De Pinto",
    "iso:country":"ES",
    "sg:address":"Calle de Pinto, 29",
    "sg:city":"Parla",
    "sg:orig_category":"Ropa Para Caballeros (al Por Menor)",
    "sg:phone":"+34 916 99 13 11",
    "sg:postcode":"28980",
    "sg:province":"Madrid",
    "wof:name":"Garcia Torres Feliciano",
    "wof:placetype":"venue"
},
  "geometry": {"coordinates":[-3.7676270008,40.2392158508],"type":"Point"}
}