{
  "type": "Feature",
  "properties": {
    "iso:country":"ES",
    "sg:address":"Calle de Galileo, 75",
    "sg:city":"Madrid",
    "sg:orig_category":"Estancos",
    "sg:phone":"+34 915 34 90 16",
    "sg:postcode":"28015",
    "sg:province":"Madrid",
    "wof:name":"Ayesta Fernandezpacheco Maria Silvia",
    "wof:placetype":"venue"
},
  "geometry": {"coordinates":[-3.7100789547,40.4376335144],"type":"Point"}
}