{
  "type": "Feature",
  "properties": {
    "iso:country":"ES",
    "sg:address":"Plaz Caudillo (del), 1",
    "sg:city":"Belmonte",
    "sg:orig_category":"Servicios Y Funcionarios De Polic\u00cda",
    "sg:phone":"+34 967 17 04 06",
    "sg:postcode":"16640",
    "sg:province":"Cuenca",
    "sg:website":"www.perso.wanadoo.es/belmonte",
    "wof:name":"Ayuntamiento De Belmonte-policia",
    "wof:placetype":"venue"
},
  "geometry": {"coordinates":[-2.7082540989,39.5593261719],"type":"Point"}
}