{
  "type": "Feature",
  "properties": {
    "iso:country":"ES",
    "sg:address":"Mayor, 129",
    "sg:city":"Monta\u00d1ana",
    "sg:orig_category":"Rectificaci\u00d3n, Mecanizado, Fresado",
    "sg:phone":"+34 976 57 51 12",
    "sg:postcode":"50059",
    "sg:province":"Zaragoza",
    "wof:name":"Mecanizados Poyva S. L.",
    "wof:placetype":"venue"
},
  "geometry": {"coordinates":[-0.8235831857,41.6849784851],"type":"Point"}
}