{
  "type": "Feature",
  "properties": {
    "addr:full":"Calle de San Bernardo (de), 9 Alcobendas Madrid 28108",
    "addr:postcode":"28108",
    "addr:street":"Calle De San;De;Alcobendas",
    "iso:country":"ES",
    "sg:address":"Calle de San Bernardo (de), 9",
    "sg:city":"Alcobendas",
    "sg:orig_category":"Quincaller\u00cda (al Por Menor)",
    "sg:phone":"+34 916 62 02 84",
    "sg:postcode":"28108",
    "sg:province":"Madrid",
    "wof:name":"Aruba Business S.l.",
    "wof:placetype":"venue"
},
  "geometry": {"coordinates":[-3.6463720798,40.5358848572],"type":"Point"}
}