{
  "type": "Feature",
  "properties": {
    "addr:full":"Polig. Ind. Proni-meres, 43 Ti\u00f1ana Asturias 33199",
    "addr:housenumber":"43",
    "addr:postcode":"33199",
    "addr:street":"Polig. Ind. Proni-Meres",
    "iso:country":"ES",
    "sg:address":"Polig. Ind. Proni-meres, 43",
    "sg:city":"Ti\u00f1ana",
    "sg:orig_category":"Calefacci\u00d3n Central: Material (fabricaci\u00d3n, Al Por Mayor)",
    "sg:phone":"+34 985 79 46 64",
    "sg:postcode":"33199",
    "sg:province":"Asturias",
    "wof:name":"Climalia Principado S.l.",
    "wof:placetype":"venue"
},
  "geometry": {"coordinates":[-5.7986898422,43.3584632874],"type":"Point"}
}