{
  "type": "Feature",
  "properties": {
    "addr:full":"G.v. Corts Catalanes, 1176 Barcelona Barcelona 08020",
    "addr:postcode":"1176;08020",
    "addr:street":"Catalanes",
    "iso:country":"ES",
    "sg:address":"G.v. Corts Catalanes, 1176",
    "sg:city":"Barcelona",
    "sg:orig_category":"Agencias Y Asesores De Publicidad",
    "sg:phone":"+34 932 78 02 91",
    "sg:postcode":"08020",
    "sg:province":"Barcelona",
    "wof:name":"Tanit Grafic S.l.",
    "wof:placetype":"venue"
},
  "geometry": {"coordinates":[2.2094969749,41.4196624756],"type":"Point"}
}