{
  "type": "Feature",
  "properties": {
    "iso:country":"ES",
    "sg:address":"Canti\u00f1o(urb. Aldea Nova), 7",
    "sg:city":"Orto\u00f1o",
    "sg:orig_category":"Doctores En Medicina",
    "sg:phone":"+34 981 88 46 19",
    "sg:postcode":"15220",
    "sg:province":"La Coru\u00f1a",
    "wof:name":"Nebril Loureiro Benito",
    "wof:placetype":"venue"
},
  "geometry": {"coordinates":[-8.6529092789,42.8592033386],"type":"Point"}
}