{
  "type": "Feature",
  "properties": {
    "iso:country":"ES",
    "sg:address":"Calle de Mayor, 92",
    "sg:city":"Garrucha",
    "sg:orig_category":"Bisuter\u00cda, Joyer\u00cda, Relojer\u00cda (al Por Menor)",
    "sg:phone":"+34 950 13 25 43",
    "sg:postcode":"04630",
    "sg:province":"Almer\u00eda",
    "wof:name":"Caparros Lopez Pedro",
    "wof:placetype":"venue"
},
  "geometry": {"coordinates":[-1.8215670586,37.1823768616],"type":"Point"}
}