{
  "type": "Feature",
  "properties": {
    "addr:full":"Calle de Villamartin, 34 Arahal Sevilla 41600",
    "addr:housenumber":"34",
    "addr:postcode":"41600",
    "addr:street":"Calle De Villamartin",
    "iso:country":"ES",
    "sg:address":"Calle de Villamartin, 34",
    "sg:city":"Arahal",
    "sg:orig_category":"Molduras, Junquillos, Listones Y Molduras Perforadas",
    "sg:phone":"+34 954 84 16 12",
    "sg:postcode":"41600",
    "sg:province":"Sevilla",
    "wof:name":"Fernandez Martin Ana",
    "wof:placetype":"venue"
},
  "geometry": {"coordinates":[-5.5495390892,37.255279541],"type":"Point"}
}