{
  "type": "Feature",
  "properties": {
    "iso:country":"ES",
    "sg:address":"Solsones (parc Neg Mas Blau I), 2",
    "sg:city":"Prat Llobregat",
    "sg:orig_category":"Televisi\u00d3n, V\u00cddeo: Aparatos Y Accesorios (venta)",
    "sg:phone":"+34 902 10 00 36",
    "sg:postcode":"08820",
    "sg:province":"Barcelona",
    "wof:name":"Grundig Espa\u00d1a S.a.",
    "wof:placetype":"venue"
},
  "geometry": {"coordinates":[2.1699187756,41.3879165649],"type":"Point"}
}