{
  "type": "Feature",
  "properties": {
    "iso:country":"ES",
    "sg:address":"Senda De San Lazaro, S/n",
    "sg:city":"Mansilla Mulas",
    "sg:orig_category":"Productos Alimentarios",
    "sg:phone":"+34 987 31 10 99",
    "sg:postcode":"24210",
    "sg:province":"Le\u00f3n",
    "wof:name":"Piensos Goyo S.l.",
    "wof:placetype":"venue"
},
  "geometry": {"coordinates":[-5.4119777679,42.4977912903],"type":"Point"}
}