{
  "type": "Feature",
  "properties": {
    "iso:country":"ES",
    "sg:address":"Calle de Camichi, 30",
    "sg:city":"Madrid",
    "sg:orig_category":"Ropa Y Accesorios",
    "sg:phone":"+34 914 62 20 57",
    "sg:postcode":"28025",
    "sg:province":"Madrid",
    "wof:name":"Sanchez Sanchez Julian",
    "wof:placetype":"venue"
},
  "geometry": {"coordinates":[-3.7430970669,40.3905334473],"type":"Point"}
}