{
  "type": "Feature",
  "properties": {
    "addr:full":"Camino Morente, 93 Montoro C\u00f3rdoba 14600",
    "addr:housenumber":"93",
    "addr:postcode":"14600",
    "addr:street":"Camino Morente;Co\u0301Rdoba",
    "iso:country":"ES",
    "sg:address":"Camino Morente, 93",
    "sg:city":"Montoro",
    "sg:orig_category":"Mec\u00c1nico Del Autom\u00d3vil",
    "sg:phone":"+34 957 16 21 06",
    "sg:postcode":"14600",
    "sg:province":"C\u00f3rdoba",
    "wof:name":"Cabrera Gomez Antonio Manuel",
    "wof:placetype":"venue"
},
  "geometry": {"coordinates":[-4.3840899467,38.0029029846],"type":"Point"}
}