{
  "type": "Feature",
  "properties": {
    "addr:full":"Calle de Jose Miguel Barandiaran, 32 Santurtzi Vizcaya 48980",
    "addr:housenumber":"32",
    "addr:postcode":"48980",
    "addr:street":"Calle De Jose Miguel Barandiaran",
    "iso:country":"ES",
    "sg:address":"Calle de Jose Miguel Barandiaran, 32",
    "sg:city":"Santurtzi",
    "sg:orig_category":"Panader\u00cdas, Panader\u00cdas",
    "sg:phone":"+34 944 93 65 12",
    "sg:postcode":"48980",
    "sg:province":"Vizcaya",
    "wof:name":"Virgut  Inversiones   Sl",
    "wof:placetype":"venue"
},
  "geometry": {"coordinates":[-3.0345540047,43.3251876831],"type":"Point"}
}