{
  "type": "Feature",
  "properties": {
    "iso:country":"ES",
    "sg:address":"Avda Paz (de La), 40",
    "sg:city":"Casalarreina",
    "sg:orig_category":"Charcuter\u00cdas (al Por Mayor)",
    "sg:phone":"+34 941 32 40 84",
    "sg:postcode":"26230",
    "sg:province":"La Rioja",
    "wof:name":"Embutidos Gamboa S.l.",
    "wof:placetype":"venue"
},
  "geometry": {"coordinates":[-2.9167239666,42.5488357544],"type":"Point"}
}