{
  "type": "Feature",
  "properties": {
    "iso:country":"ES",
    "sg:address":"Calle de Dimas Madariaga, 14",
    "sg:city":"Salamanca",
    "sg:orig_category":"Abogados",
    "sg:phone":"+34 923 12 34 88",
    "sg:postcode":"37005",
    "sg:province":"Salamanca",
    "wof:name":"Sanchez Lucas Ana Isabel",
    "wof:placetype":"venue"
},
  "geometry": {"coordinates":[-5.6602101326,40.9699859619],"type":"Point"}
}