{
  "type": "Feature",
  "properties": {
    "addr:full":"Calle de Gabriel Garcia Marquez, 4 Villahermosa Ciudad Real 13332",
    "addr:housenumber":"4",
    "addr:postcode":"13332",
    "addr:street":"Calle De Gabriel Garcia Marquez",
    "iso:country":"ES",
    "sg:address":"Calle de Gabriel Garcia Marquez, 4",
    "sg:city":"Villahermosa",
    "sg:orig_category":"Carnicer\u00cdas, Carnicer\u00cdas",
    "sg:phone":"+34 926 37 50 15",
    "sg:postcode":"13332",
    "sg:province":"Ciudad Real",
    "wof:name":"Carnes Primitivo S.l.",
    "wof:placetype":"venue"
},
  "geometry": {"coordinates":[-2.871917963,38.7496681213],"type":"Point"}
}