{
  "type": "Feature",
  "properties": {
    "addr:full":"Carrer de Jacint Verdaguer, 31 Vic Barcelona 08500",
    "addr:housenumber":"31",
    "addr:postcode":"08500",
    "addr:street":"Carrer De Jacint Verdaguer",
    "iso:country":"ES",
    "sg:address":"Carrer de Jacint Verdaguer, 31",
    "sg:city":"Vic",
    "sg:orig_category":"Oficinas: Suministros Para (fabricaci\u00d3n, Al Por Mayor)",
    "sg:phone":"+34 938 85 26 25",
    "sg:postcode":"08500",
    "sg:province":"Barcelona",
    "wof:name":"Sales Gonzalez Maria Alicia",
    "wof:placetype":"venue"
},
  "geometry": {"coordinates":[2.2498569489,41.9307632446],"type":"Point"}
}