{
  "type": "Feature",
  "properties": {
    "addr:full":"Ctra Obispo, 59 Gijon Asturias 33210",
    "addr:housenumber":"59",
    "addr:postcode":"33210",
    "addr:street":"Ctra Obispo",
    "iso:country":"ES",
    "sg:address":"Ctra Obispo, 59",
    "sg:city":"Gijon",
    "sg:orig_category":"Transportes Por Carretera: Lotes Completos, Mercanc\u00cdas Diversas",
    "sg:phone":"+34 985 99 09 34",
    "sg:postcode":"33210",
    "sg:province":"Asturias",
    "wof:name":"Grupo El Arbol Distribucion Y Supermercados S.a. Unipersonal",
    "wof:placetype":"venue"
},
  "geometry": {"coordinates":[-5.6650857925,43.5218467712],"type":"Point"}
}