{
  "type": "Feature",
  "properties": {
    "addr:full":"Carr Vicente Marti, 2 Benifaio Valencia 46450",
    "addr:housenumber":"2",
    "addr:postcode":"46450",
    "addr:street":"Carr Vicente Marti",
    "iso:country":"ES",
    "sg:address":"Carr Vicente Marti, 2",
    "sg:city":"Benifaio",
    "sg:orig_category":"Empresas De Carpinter\u00cda De Madera",
    "sg:phone":"+34 961 78 04 38",
    "sg:postcode":"46450",
    "sg:province":"Valencia",
    "wof:name":"Rovira Lizondo Vicente",
    "wof:placetype":"venue"
},
  "geometry": {"coordinates":[-0.4252299964,39.2804794312],"type":"Point"}
}