{
  "type": "Feature",
  "properties": {
    "iso:country":"ES",
    "sg:address":"Calle de Valdes, 4",
    "sg:city":"Marbella",
    "sg:orig_category":"Zapatos (al Por Menor)",
    "sg:phone":"+34 952 77 28 90",
    "sg:postcode":"29600",
    "sg:province":"M\u00e1laga",
    "wof:name":"Mata Rueda Antonio",
    "wof:placetype":"venue"
},
  "geometry": {"coordinates":[-4.8852148056,36.5098609924],"type":"Point"}
}