{
  "type": "Feature",
  "properties": {
    "addr:full":"Calle de Mayor, 39 Sang\u00fcesa Navarra 31400",
    "addr:housenumber":"39",
    "addr:postcode":"31400",
    "addr:street":"Calle De Mayor",
    "iso:country":"ES",
    "sg:address":"Calle de Mayor, 39",
    "sg:city":"Sang\u00fcesa",
    "sg:orig_category":"Confecci\u00d3n (fabricaci\u00d3n, Al Por Mayor)",
    "sg:phone":"+34 948 87 00 89",
    "sg:postcode":"31400",
    "sg:province":"Navarra",
    "wof:name":"Castillo Mayo Jose Ramon Del",
    "wof:placetype":"venue"
},
  "geometry": {"coordinates":[-1.2833989859,42.5763130188],"type":"Point"}
}