{
  "type": "Feature",
  "properties": {
    "iso:country":"ES",
    "sg:address":"Avda Valle De Esgueva, S/n",
    "sg:city":"Valladolid",
    "sg:orig_category":"Mec\u00c1nico Del Autom\u00d3vil",
    "sg:phone":"+34 983 25 93 32",
    "sg:postcode":"47011",
    "sg:province":"Valladolid",
    "wof:name":"Talleres Turbocar S.l.",
    "wof:placetype":"venue"
},
  "geometry": {"coordinates":[-4.7051548958,41.6598014832],"type":"Point"}
}