{
  "type": "Feature",
  "properties": {
    "iso:country":"ES",
    "sg:address":"Plaz Matute, 7",
    "sg:city":"Madrid",
    "sg:orig_category":"Art\u00cdculos De Decoraci\u00d3n",
    "sg:phone":"+34 914 20 42 65",
    "sg:postcode":"28012",
    "sg:province":"Madrid",
    "wof:name":"Jethani  Prakash",
    "wof:placetype":"venue"
},
  "geometry": {"coordinates":[-3.6997330189,40.4132919312],"type":"Point"}
}