{
  "type": "Feature",
  "properties": {
    "addr:full":"Calle de Italia, 44 Elda Alicante 03600",
    "addr:housenumber":"44",
    "addr:postcode":"03600",
    "addr:street":"Calle De Italia",
    "iso:country":"ES",
    "sg:address":"Calle de Italia, 44",
    "sg:city":"Elda",
    "sg:orig_category":"Zapater\u00cdas",
    "sg:phone":"+34 965 38 02 09",
    "sg:postcode":"03600",
    "sg:province":"Alicante",
    "wof:name":"Derivados Aberden S.l.",
    "wof:placetype":"venue"
},
  "geometry": {"coordinates":[-0.8168269992,38.4619674683],"type":"Point"}
}