{
  "type": "Feature",
  "properties": {
    "addr:full":"Plaz Barcelona (de), 4 Getafe Madrid 28903",
    "addr:postcode":"28903",
    "addr:street":"Plaz",
    "iso:country":"ES",
    "sg:address":"Plaz Barcelona (de), 4",
    "sg:city":"Getafe",
    "sg:orig_category":"Bisuter\u00cda, Joyer\u00cda, Relojer\u00cda (al Por Menor)",
    "sg:phone":"+34 916 95 36 33",
    "sg:postcode":"28903",
    "sg:province":"Madrid",
    "wof:name":"Grupo C.g. 1969 S.l.",
    "wof:placetype":"venue"
},
  "geometry": {"coordinates":[-3.7240080833,40.3110122681],"type":"Point"}
}