{
  "type": "Feature",
  "properties": {
    "iso:country":"ES",
    "sg:address":"Calle de Tudela, 7",
    "sg:city":"Bilbao",
    "sg:orig_category":"Asesor\u00cda Sobre Comunicaci\u00d3n De Empresas",
    "sg:phone":"+34 944 74 62 58",
    "sg:postcode":"48015",
    "sg:province":"Vizcaya",
    "wof:name":"Asesoria San Sebastian Sl",
    "wof:placetype":"venue"
},
  "geometry": {"coordinates":[-2.9594659805,43.2781562805],"type":"Point"}
}