{
  "type": "Feature",
  "properties": {
    "addr:full":"Carrer de Luis Marti, 25 Monovar Alicante 03640",
    "addr:housenumber":"25",
    "addr:postcode":"03640",
    "addr:street":"Carrer De Luis Marti;Alicante",
    "iso:country":"ES",
    "sg:address":"Carrer de Luis Marti, 25",
    "sg:city":"Monovar",
    "sg:orig_category":"Reposter\u00cdas",
    "sg:phone":"+34 965 47 28 29",
    "sg:postcode":"03640",
    "sg:province":"Alicante",
    "wof:name":"Esteve Falco Juana",
    "wof:placetype":"venue"
},
  "geometry": {"coordinates":[-0.8389629722,38.4352111816],"type":"Point"}
}