{
  "type": "Feature",
  "properties": {
    "addr:full":"Plaz Capuchinas (de), 1 Cordoba C\u00f3rdoba 14001",
    "addr:postcode":"14001",
    "addr:street":"Co\u0301Rdoba",
    "iso:country":"ES",
    "sg:address":"Plaz Capuchinas (de), 1",
    "sg:city":"Cordoba",
    "sg:orig_category":"Pod\u00d3logos: Pedicuros",
    "sg:phone":"+34 957 47 33 11",
    "sg:postcode":"14001",
    "sg:province":"C\u00f3rdoba",
    "wof:name":"Bretones Garcia Miguel",
    "wof:placetype":"venue"
},
  "geometry": {"coordinates":[-4.7781529427,37.8883323669],"type":"Point"}
}