{
  "type": "Feature",
  "properties": {
    "addr:full":"Calle de San Pedro De Carde\u00d1a, 38 Burgos Burgos 09002",
    "addr:housenumber":"38",
    "addr:postcode":"09002",
    "addr:street":"Calle De;Carden\u0303A",
    "iso:country":"ES",
    "sg:address":"Calle de San Pedro De Carde\u00d1a, 38",
    "sg:city":"Burgos",
    "sg:orig_category":"Veh\u00cdculos De Ocasi\u00d3n",
    "sg:phone":"+34 947 26 48 02",
    "sg:postcode":"09002",
    "sg:province":"Burgos",
    "wof:name":"Movil 2 S.l.",
    "wof:placetype":"venue"
},
  "geometry": {"coordinates":[-3.6893730164,42.3387718201],"type":"Point"}
}