{
  "type": "Feature",
  "properties": {
    "iso:country":"ES",
    "sg:address":"Calle de Bernardo Lopez, 11",
    "sg:city":"Jaen",
    "sg:orig_category":"Librer\u00cdas",
    "sg:phone":"+34 953 23 24 15",
    "sg:postcode":"23004",
    "sg:province":"Ja\u00e9n",
    "wof:name":"Lechuga Oya Juan Francisco",
    "wof:placetype":"venue"
},
  "geometry": {"coordinates":[-3.7907779217,37.7661743164],"type":"Point"}
}