{
  "type": "Feature",
  "properties": {
    "iso:country":"ES",
    "sg:address":"Polig. Ind. Ordes, S/n",
    "sg:city":"Conde",
    "sg:orig_category":"Promotores Constructores",
    "sg:phone":"+34 981 68 02 52",
    "sg:postcode":"15680",
    "sg:province":"La Coru\u00f1a",
    "wof:name":"Crc Obras Y Servicios S.l.",
    "wof:placetype":"venue"
},
  "geometry": {"coordinates":[-8.4072790146,43.0771408081],"type":"Point"}
}