{
  "type": "Feature",
  "properties": {
    "addr:full":"Ctra Madrid-cadiz, S/n Jerez De La Frontera C\u00e1diz 11407",
    "addr:postcode":"11407",
    "addr:street":"Ctra Madrid-Cadiz S / N",
    "iso:country":"ES",
    "sg:address":"Ctra Madrid-cadiz, S/n",
    "sg:city":"Jerez De La Frontera",
    "sg:orig_category":"Servicios Gsm",
    "sg:phone":"+34 956 14 24 44",
    "sg:postcode":"11407",
    "sg:province":"C\u00e1diz",
    "wof:name":"G.s.m.bahia S.l.",
    "wof:placetype":"venue"
},
  "geometry": {"coordinates":[-6.1112380028,36.7113761902],"type":"Point"}
}