{
  "type": "Feature",
  "properties": {
    "iso:country":"ES",
    "sg:address":"Calle de Marroquina, 40",
    "sg:city":"Madrid",
    "sg:orig_category":"Agencias De Viajes",
    "sg:phone":"+34 914 30 12 13",
    "sg:postcode":"28030",
    "sg:province":"Madrid",
    "wof:name":"Viajes Citur S.a.",
    "wof:placetype":"venue"
},
  "geometry": {"coordinates":[-3.6478009224,40.4084472656],"type":"Point"}
}