{
  "type": "Feature",
  "properties": {
    "addr:full":"Carrer de Pujades, 77 Barcelona Barcelona 08005",
    "addr:housenumber":"77",
    "addr:postcode":"08005",
    "addr:street":"Carrer De Pujades",
    "iso:country":"ES",
    "sg:address":"Carrer de Pujades, 77",
    "sg:city":"Barcelona",
    "sg:orig_category":"Aparatos, Sistemas De Tele",
    "sg:phone":"+34 934 85 60 30",
    "sg:postcode":"08005",
    "sg:province":"Barcelona",
    "wof:name":"P.b.seguridad S.a.",
    "wof:placetype":"venue"
},
  "geometry": {"coordinates":[2.1943171024,41.397064209],"type":"Point"}
}