{
  "type": "Feature",
  "properties": {
    "iso:country":"ES",
    "sg:address":"Lazarraga Kalea, 2",
    "sg:city":"O\u00f1ati",
    "sg:orig_category":"\u00d3ptica: Instrumentos (fabricaci\u00d3n)",
    "sg:phone":"+34 943 71 60 63",
    "sg:postcode":"20560",
    "sg:province":"Guip\u00f9zcoa",
    "wof:name":"Sorkunde Arkauz Arabaolaza",
    "wof:placetype":"venue"
},
  "geometry": {"coordinates":[-2.4093060493,43.0313262939],"type":"Point"}
}