{
  "type": "Feature",
  "properties": {
    "iso:country":"ES",
    "sg:address":"Calle de Libertad (de La), 18",
    "sg:city":"Mostoles",
    "sg:orig_category":"Ense\u00d1anza: Idiomas",
    "sg:phone":"+34 916 47 38 47",
    "sg:postcode":"28936",
    "sg:province":"Madrid",
    "wof:name":"Sebastian Perez Angelines",
    "wof:placetype":"venue"
},
  "geometry": {"coordinates":[-3.8548591137,40.3282165527],"type":"Point"}
}