{
  "type": "Feature",
  "properties": {
    "addr:full":"Carrer de Churruca, 15 Mataro Barcelona 08301",
    "addr:housenumber":"15",
    "addr:postcode":"08301",
    "addr:street":"Carrer De Churruca",
    "iso:country":"ES",
    "sg:address":"Carrer de Churruca, 15",
    "sg:city":"Mataro",
    "sg:orig_category":"Agentes, Concesionarios Y Sucursales De Camiones Y Veh\u00cdculos Industriales",
    "sg:phone":"+34 937 96 24 75",
    "sg:postcode":"08301",
    "sg:province":"Barcelona",
    "wof:name":"Extreme Quads S.l.l.",
    "wof:placetype":"venue"
},
  "geometry": {"coordinates":[2.4432799816,41.5352973938],"type":"Point"}
}