{
  "type": "Feature",
  "properties": {
    "iso:country":"ES",
    "sg:address":"Irure, Barrio, S/n",
    "sg:city":"Soraluze-placencia Armas",
    "sg:orig_category":"Fijaciones Industriales",
    "sg:phone":"+34 943 75 13 88",
    "sg:postcode":"20590",
    "sg:province":"Guip\u00f9zcoa",
    "wof:name":"Tornilleria Lucio Ariznabarreta S.l.",
    "wof:placetype":"venue"
},
  "geometry": {"coordinates":[-2.2066218853,43.16746521],"type":"Point"}
}