{
  "type": "Feature",
  "properties": {
    "addr:full":"Ctra Santa Barbara, Km. 0003,0 Amposta Tarragona 43870",
    "addr:postcode":"43870",
    "addr:street":"Ctra Santa Barbara Km. 0003,0",
    "iso:country":"ES",
    "sg:address":"Ctra Santa Barbara, Km. 0003,0",
    "sg:city":"Amposta",
    "sg:orig_category":"Construcciones Met\u00c1licas",
    "sg:phone":"+34 977 70 20 00",
    "sg:postcode":"43870",
    "sg:province":"Tarragona",
    "wof:name":"Comercial Cem S.l.",
    "wof:placetype":"venue"
},
  "geometry": {"coordinates":[0.5651999712,40.7010192871],"type":"Point"}
}