{
  "type": "Feature",
  "properties": {
    "addr:full":"Calle de Arrabal, 106 Mairena Alcor Sevilla 41510",
    "addr:housenumber":"106",
    "addr:postcode":"41510",
    "addr:street":"Calle De Arrabal",
    "iso:country":"ES",
    "sg:address":"Calle de Arrabal, 106",
    "sg:city":"Mairena Alcor",
    "sg:orig_category":"Peluquer\u00cdas, Peluquer\u00cda Mixta",
    "sg:phone":"+34 955 74 67 83",
    "sg:postcode":"41510",
    "sg:province":"Sevilla",
    "wof:name":"Sanchez Borreguero Jesus",
    "wof:placetype":"venue"
},
  "geometry": {"coordinates":[-5.7507519722,37.3726348877],"type":"Point"}
}