{
  "type": "Feature",
  "properties": {
    "iso:country":"ES",
    "sg:address":"Cmno Ronda (de), 202",
    "sg:city":"Granada",
    "sg:classifiers":[
        {
            "category":"Autos & Motor Vehicles",
            "subcategory":"Automobile Sales",
            "type":"Retail Goods"
        }
    ],
    "sg:phone":"+34 958 29 11 62",
    "sg:postcode":"18003",
    "sg:province":"Granada",
    "sg:website":"www.webrrs.com",
    "wof:name":"Romero Racing Team S.l.l",
    "wof:placetype":"venue"
},
  "geometry": {"coordinates":[-3.614538908,37.1853752136],"type":"Point"}
}