{
  "type": "Feature",
  "properties": {
    "addr:full":"Ctra Tudela, Km. 0003,5 Cascante Navarra 31520",
    "addr:housenumber":"km.",
    "addr:postcode":"31520",
    "addr:street":"Ctra Tudela;0003,5",
    "iso:country":"ES",
    "sg:address":"Ctra Tudela, Km. 0003,5",
    "sg:city":"Cascante",
    "sg:orig_category":"Distribuci\u00d3n De Petr\u00d3leo Y Derivados",
    "sg:phone":"+34 948 41 13 31",
    "sg:postcode":"31520",
    "sg:province":"Navarra",
    "wof:name":"Erg Gestion Iberica S.l.",
    "wof:placetype":"venue"
},
  "geometry": {"coordinates":[-1.681483984,42.0028533936],"type":"Point"}
}