{
  "type": "Feature",
  "properties": {
    "addr:full":"Calle de Virgen De La Cabeza (de La), 22 Coslada Madrid 28820",
    "addr:postcode":"28820",
    "addr:street":"Calle De Virgen",
    "iso:country":"ES",
    "sg:address":"Calle de Virgen De La Cabeza (de La), 22",
    "sg:city":"Coslada",
    "sg:orig_category":"Fabricaci\u00d3n, Importaci\u00d3n, Venta De Material De Telefon\u00cda, Peritelefon\u00cda",
    "sg:phone":"+34 916 72 71 59",
    "sg:postcode":"28820",
    "sg:province":"Madrid",
    "wof:name":"Telemovil Torrejon S.l.",
    "wof:placetype":"venue"
},
  "geometry": {"coordinates":[-3.5654797554,40.4299278259],"type":"Point"}
}