{
  "type": "Feature",
  "properties": {
    "iso:country":"ES",
    "sg:address":"Calle de Iglesia, 13",
    "sg:city":"Jauja",
    "sg:orig_category":"Cajas Para Embalar",
    "sg:phone":"+34 957 51 90 59",
    "sg:postcode":"14911",
    "sg:province":"C\u00f3rdoba",
    "wof:name":"Caja Rural De Cordoba",
    "wof:placetype":"venue"
},
  "geometry": {"coordinates":[-4.6554641724,37.3033676147],"type":"Point"}
}