{
  "type": "Feature",
  "properties": {
    "iso:country":"ES",
    "sg:address":"Carrer de Angel Guimera, 26",
    "sg:city":"Calella",
    "sg:orig_category":"Abogados",
    "sg:phone":"+34 937 69 76 79",
    "sg:postcode":"08370",
    "sg:province":"Barcelona",
    "wof:name":"Gabinete Juridico Fiscal C. B.",
    "wof:placetype":"venue"
},
  "geometry": {"coordinates":[2.6692500114,41.6167221069],"type":"Point"}
}