{
  "type": "Feature",
  "properties": {
    "addr:full":"Carr Tio Tonet El De La Foia, 3 Petrer Alicante 03610",
    "addr:housenumber":"3",
    "addr:postcode":"03610",
    "addr:street":"Carr Tio;Foia",
    "iso:country":"ES",
    "sg:address":"Carr Tio Tonet El De La Foia, 3",
    "sg:city":"Petrer",
    "sg:orig_category":"Confecci\u00d3n De Guantes",
    "sg:phone":"+34 965 37 10 85",
    "sg:postcode":"03610",
    "sg:province":"Alicante",
    "wof:name":"Martinez Blazquez Felipe",
    "wof:placetype":"venue"
},
  "geometry": {"coordinates":[-0.7685139775,38.4822387695],"type":"Point"}
}