{
  "type": "Feature",
  "properties": {
    "addr:full":"Avda Ilustracion (la), 25 Zaragoza Zaragoza 50012",
    "addr:housenumber":"25",
    "addr:postcode":"50012",
    "addr:street":"Avda Ilustracion La",
    "iso:country":"ES",
    "sg:address":"Avda Ilustracion (la), 25",
    "sg:city":"Zaragoza",
    "sg:orig_category":"Agencias Y Agentes Comerciales, Representantes",
    "sg:phone":"+34 976 75 55 14",
    "sg:postcode":"50012",
    "sg:province":"Zaragoza",
    "wof:name":"A.c. Trinchan S.l.",
    "wof:placetype":"venue"
},
  "geometry": {"coordinates":[-0.9364143014,41.6312065125],"type":"Point"}
}