{
  "type": "Feature",
  "properties": {
    "addr:full":"Calle de Real, 97 Yuncos Toledo 45210",
    "addr:housenumber":"97",
    "addr:postcode":"45210",
    "addr:street":"Calle De Real",
    "iso:country":"ES",
    "sg:address":"Calle de Real, 97",
    "sg:city":"Yuncos",
    "sg:orig_category":"Ense\u00d1anza: Profesiones Art\u00cdsticas",
    "sg:phone":"+34 925 53 71 05",
    "sg:postcode":"45210",
    "sg:province":"Toledo",
    "sg:website":"www.taurophoto.com",
    "wof:name":"Humanes Caballero Jose Angel",
    "wof:placetype":"venue"
},
  "geometry": {"coordinates":[-3.8733189106,40.0875511169],"type":"Point"}
}