{
  "type": "Feature",
  "properties": {
    "iso:country":"ES",
    "sg:address":"Calle de Carril De Huete, Km. 0002,0",
    "sg:city":"Tarancon",
    "sg:orig_category":"Producci\u00d3n, Comercio De Cereales",
    "sg:phone":"+34 969 32 25 48",
    "sg:postcode":"16400",
    "sg:province":"Cuenca",
    "wof:name":"Cooperativa Del Campo Nuestra Se\u00f1ora De Riansares",
    "wof:placetype":"venue"
},
  "geometry": {"coordinates":[-2.998030901,40.0025177002],"type":"Point"}
}