{
  "type": "Feature",
  "properties": {
    "iso:country":"ES",
    "sg:address":"Avda Hito (del), 18",
    "sg:city":"Pe\u00d1ascales",
    "sg:orig_category":"Arquitectos",
    "sg:phone":"+34 918 59 96 32",
    "sg:postcode":"28250",
    "sg:province":"Madrid",
    "wof:name":"Diez Veces Diez S.l",
    "wof:placetype":"venue"
},
  "geometry": {"coordinates":[-3.8846120834,40.5799942017],"type":"Point"}
}