{
  "type": "Feature",
  "properties": {
    "iso:country":"ES",
    "sg:address":"Calle de Mayor, 85",
    "sg:city":"Sang\u00fcesa",
    "sg:orig_category":"Cl\u00cdnicas Dentales",
    "sg:phone":"+34 948 87 15 18",
    "sg:postcode":"31400",
    "sg:province":"Navarra",
    "wof:name":"Irebena S.l.",
    "wof:placetype":"venue"
},
  "geometry": {"coordinates":[-1.2816259861,42.5761375427],"type":"Point"}
}