{
  "type": "Feature",
  "properties": {
    "addr:full":"Avda Juan Carlos I, 86 Alhama Murcia Murcia 30840",
    "addr:housenumber":"86",
    "addr:postcode":"30840",
    "addr:street":"Avda Juan Carlos I",
    "iso:country":"ES",
    "sg:address":"Avda Juan Carlos I, 86",
    "sg:city":"Alhama Murcia",
    "sg:orig_category":"Mec\u00c1nico Del Autom\u00d3vil",
    "sg:phone":"+34 968 63 10 73",
    "sg:postcode":"30840",
    "sg:province":"Murcia",
    "wof:name":"Saez Munuera Andres Manuel",
    "wof:placetype":"venue"
},
  "geometry": {"coordinates":[-1.4259690046,37.8471603394],"type":"Point"}
}