{
  "type": "Feature",
  "properties": {
    "iso:country":"ES",
    "sg:address":"Calle de Peris Mencheta, 18",
    "sg:city":"Valencia",
    "sg:orig_category":"Empresas De Carpinter\u00cda De Madera",
    "sg:phone":"+34 963 93 56 53",
    "sg:postcode":"46020",
    "sg:province":"Valencia",
    "wof:name":"Magro Ortiz Jesus",
    "wof:placetype":"venue"
},
  "geometry": {"coordinates":[-0.3598940074,39.4842529297],"type":"Point"}
}