{
  "type": "Feature",
  "properties": {
    "iso:country":"ES",
    "sg:address":"Calle de Convento, S/n",
    "sg:city":"Gotor",
    "sg:orig_category":"Confecci\u00d3n De Zapatos",
    "sg:phone":"+34 976 82 02 17",
    "sg:postcode":"50257",
    "sg:province":"Zaragoza",
    "wof:name":"Sebastian Gaspar Antonio",
    "wof:placetype":"venue"
},
  "geometry": {"coordinates":[-1.6491880417,41.5466079712],"type":"Point"}
}