{
  "type": "Feature",
  "properties": {
    "addr:full":"Calle de Malmoe, 27 Madrid Madrid 28032",
    "addr:housenumber":"27",
    "addr:postcode":"madrid;28032",
    "addr:street":"Calle De Malmoe",
    "iso:country":"ES",
    "sg:address":"Calle de Malmoe, 27",
    "sg:city":"Madrid",
    "sg:orig_category":"Ropa Para Ni\u00d1os (al Por Menor)",
    "sg:phone":"+34 917 75 45 40",
    "sg:postcode":"28032",
    "sg:province":"Madrid",
    "wof:name":"Bayon Del Rio Fuensanta",
    "wof:placetype":"venue"
},
  "geometry": {"coordinates":[-3.6252770424,40.4156951904],"type":"Point"}
}