{
  "type": "Feature",
  "properties": {
    "addr:full":"Calle de Altas Del Norte, S/n Jabalquinto Ja\u00e9n 23712",
    "addr:housenumber":"s / n",
    "addr:postcode":"23712",
    "addr:street":"Calle De Altas Del Norte",
    "iso:country":"ES",
    "sg:address":"Calle de Altas Del Norte, S/n",
    "sg:city":"Jabalquinto",
    "sg:orig_category":"Aparatos E Instalaci\u00d3n De Regad\u00cdos",
    "sg:phone":"+34 953 61 73 27",
    "sg:postcode":"23712",
    "sg:province":"Ja\u00e9n",
    "wof:name":"Balsas Andalucia S.l.",
    "wof:placetype":"venue"
},
  "geometry": {"coordinates":[-3.7263331413,38.0198516846],"type":"Point"}
}