{
  "type": "Feature",
  "properties": {
    "iso:country":"ES",
    "sg:address":"Calle de Ricardo Beltran Y Rozpide, 19",
    "sg:city":"Madrid",
    "sg:orig_category":"Edici\u00d3n De Diarios, Revistas, Boletines",
    "sg:phone":"+34 914 69 85 17",
    "sg:postcode":"28026",
    "sg:province":"Madrid",
    "wof:name":"Sanz Mora Jose",
    "wof:placetype":"venue"
},
  "geometry": {"coordinates":[-3.7173199654,40.3819236755],"type":"Point"}
}