{
  "type": "Feature",
  "properties": {
    "iso:country":"ES",
    "sg:address":"Carrer de Felip Ii, 162",
    "sg:city":"Barcelona",
    "sg:orig_category":"Carnicer\u00cdas, Carnicer\u00cdas",
    "sg:phone":"+34 933 52 81 06",
    "sg:postcode":"08027",
    "sg:province":"Barcelona",
    "wof:name":"Bosch Mateu Jaime",
    "wof:placetype":"venue"
},
  "geometry": {"coordinates":[2.1818349361,41.424495697],"type":"Point"}
}