{
  "type": "Feature",
  "properties": {
    "addr:full":"Ctra Madrid, Km. 0434,0 Los Dolores Murcia 30310",
    "addr:postcode":"30310",
    "addr:street":"Ctra Madrid Km. 0434,0",
    "iso:country":"ES",
    "sg:address":"Ctra Madrid, Km. 0434,0",
    "sg:city":"Los Dolores",
    "sg:orig_category":"Distribuci\u00d3n De Petr\u00d3leo Y Derivados",
    "sg:phone":"+34 968 53 53 81",
    "sg:postcode":"30310",
    "sg:province":"Murcia",
    "wof:name":"Repsol Ypf S.a.",
    "wof:placetype":"venue"
},
  "geometry": {"coordinates":[-1.0082689524,37.6360816956],"type":"Point"}
}