{
  "type": "Feature",
  "properties": {
    "iso:country":"ES",
    "sg:address":"Calle de Republica Dominicana (de La), 3",
    "sg:city":"Palencia",
    "sg:orig_category":"Plomeros",
    "sg:phone":"+34 979 17 90 26",
    "sg:postcode":"34003",
    "sg:province":"Palencia",
    "wof:name":"Garcia Martin Jose Maria",
    "wof:placetype":"venue"
},
  "geometry": {"coordinates":[-4.5342788696,42.028011322],"type":"Point"}
}