{
  "type": "Feature",
  "properties": {
    "addr:full":"Carretera De Peloche, Km. 0004,0 Herrera Duque Badajoz 06670",
    "addr:postcode":"06670",
    "addr:street":"Carretera De Peloche Km. 0004,0 Herrera;Badajoz",
    "iso:country":"ES",
    "sg:address":"Carretera De Peloche, Km. 0004,0",
    "sg:city":"Herrera Duque",
    "sg:orig_category":"Zonas De Acampada, Aparcamiento Para Caravanas",
    "sg:phone":"+34 924 14 50 84",
    "sg:postcode":"06670",
    "sg:province":"Badajoz",
    "wof:name":"Ayuntamiento De Herrera Del Duque",
    "wof:placetype":"venue"
},
  "geometry": {"coordinates":[-5.056702137,39.1682472229],"type":"Point"}
}