{
  "type": "Feature",
  "properties": {
    "iso:country":"ES",
    "sg:address":"Avgd Antonio Almela, 38",
    "sg:city":"Alcudia",
    "sg:orig_category":"Notarios",
    "sg:phone":"+34 962 54 12 03",
    "sg:postcode":"46250",
    "sg:province":"Valencia",
    "wof:name":"Saez Luz Maria Isabel",
    "wof:placetype":"venue"
},
  "geometry": {"coordinates":[-0.5070289969,39.1940689087],"type":"Point"}
}