{
  "type": "Feature",
  "properties": {
    "addr:full":"Calle de Baja, 40 Alca\u00f1iz Teruel 44600",
    "addr:housenumber":"40",
    "addr:postcode":"44600",
    "addr:street":"Calle De Baja",
    "iso:country":"ES",
    "sg:address":"Calle de Baja, 40",
    "sg:city":"Alca\u00f1iz",
    "sg:orig_category":"Ropa Para Ni\u00d1os (al Por Menor)",
    "sg:phone":"+34 978 83 33 75",
    "sg:postcode":"44600",
    "sg:province":"Teruel",
    "wof:name":"Rocatin Ari\u00f1o Pilar",
    "wof:placetype":"venue"
},
  "geometry": {"coordinates":[-0.1301195025,41.0459136963],"type":"Point"}
}