{
  "type": "Feature",
  "properties": {
    "addr:full":"Pase Igeldo De, 25 Donostia-san Sebastian Guip\u00f9zcoa 20008",
    "addr:housenumber":"25",
    "addr:postcode":"20008",
    "iso:country":"ES",
    "sg:address":"Pase Igeldo De, 25",
    "sg:city":"Donostia-san Sebastian",
    "sg:orig_category":"Asociaciones, Organismos Culturales Y Socioeducativos",
    "sg:phone":"+34 943 21 24 27",
    "sg:postcode":"20008",
    "sg:province":"Guip\u00f9zcoa",
    "wof:name":"Euskal Herriko Bertsozale Elkartea",
    "wof:placetype":"venue"
},
  "geometry": {"coordinates":[-2.007062912,43.3149261475],"type":"Point"}
}