{
  "type": "Feature",
  "properties": {
    "iso:country":"ES",
    "sg:address":"Rua Cardenal Quiroga, 4",
    "sg:city":"Ourense",
    "sg:orig_category":"Laboratorios Y Trabajos De Fotograf\u00cda, V\u00cddeo Y Cine",
    "sg:phone":"+34 988 23 31 04",
    "sg:postcode":"32003",
    "sg:province":"Ourense",
    "wof:name":"Gonzalez Parejo Francisco",
    "wof:placetype":"venue"
},
  "geometry": {"coordinates":[-7.8653888702,42.3381843567],"type":"Point"}
}