{
  "type": "Feature",
  "properties": {
    "iso:country":"ES",
    "sg:address":"Calle de Henriquez De Jorquera, 2",
    "sg:city":"Granada",
    "sg:orig_category":"Molduras, Junquillos, Listones Y Molduras Perforadas",
    "sg:phone":"+34 958 16 12 71",
    "sg:postcode":"18011",
    "sg:province":"Granada",
    "wof:name":"Rodelas Chinchilla Fernando",
    "wof:placetype":"venue"
},
  "geometry": {"coordinates":[-3.5999550819,37.201587677],"type":"Point"}
}