{
  "type": "Feature",
  "properties": {
    "addr:full":"Calle de Benjumeda, 7 Cadiz C\u00e1diz 11003",
    "addr:housenumber":"7",
    "addr:postcode":"11003",
    "addr:street":"Calle De Benjumeda",
    "iso:country":"ES",
    "sg:address":"Calle de Benjumeda, 7",
    "sg:city":"Cadiz",
    "sg:orig_category":"Centros P\u00dablicos De Formaci\u00d3n Profesional Y T\u00c9cnica",
    "sg:phone":"+34 956 21 16 91",
    "sg:postcode":"11003",
    "sg:province":"C\u00e1diz",
    "wof:name":"Colegio Oficial De Medicos De Cadiz",
    "wof:placetype":"venue"
},
  "geometry": {"coordinates":[-6.2984571457,36.5331840515],"type":"Point"}
}