{
  "type": "Feature",
  "properties": {
    "addr:full":"Calle de Gran Via, 2 Molina Segura Murcia 30500",
    "addr:postcode":"30500",
    "addr:street":"Calle De Gran Via 2 Molina",
    "iso:country":"ES",
    "sg:address":"Calle de Gran Via, 2",
    "sg:city":"Molina Segura",
    "sg:orig_category":"Cajas De Ahorro",
    "sg:phone":"+34 968 61 24 59",
    "sg:postcode":"30500",
    "sg:province":"Murcia",
    "sg:website":"www.cajamurcia.es",
    "wof:name":"Caja De Ahorros De Murcia",
    "wof:placetype":"venue"
},
  "geometry": {"coordinates":[-1.2075769901,38.0530166626],"type":"Point"}
}