{
  "type": "Feature",
  "properties": {
    "iso:country":"ES",
    "sg:address":"Calle de Goya, 2",
    "sg:city":"Cordoba",
    "sg:orig_category":"Bricolaje, Herramientas (al Por Menor)",
    "sg:phone":"+34 957 27 32 78",
    "sg:postcode":"14006",
    "sg:province":"C\u00f3rdoba",
    "wof:name":"Chelini Giolli Vasco",
    "wof:placetype":"venue"
},
  "geometry": {"coordinates":[-4.7840528488,37.8949127197],"type":"Point"}
}