{
  "type": "Feature",
  "properties": {
    "addr:full":"Calle de Nogal, 31 Puebla Alfinden Zaragoza 50171",
    "addr:housenumber":"31",
    "addr:postcode":"50171",
    "addr:street":"Calle De Nogal;Alfinden",
    "iso:country":"ES",
    "sg:address":"Calle de Nogal, 31",
    "sg:city":"Puebla Alfinden",
    "sg:orig_category":"Fabricaci\u00d3n De Material Y Sistemas De Se\u00d1alizaci\u00d3n De Carreteras, Urbanos Y De Obras",
    "sg:phone":"+34 902 18 20 22",
    "sg:postcode":"50171",
    "sg:province":"Zaragoza",
    "wof:name":"Impresiones Planas Serigraficas S.l.l.",
    "wof:placetype":"venue"
},
  "geometry": {"coordinates":[-0.7647240162,41.6391983032],"type":"Point"}
}