{
  "type": "Feature",
  "properties": {
    "iso:country":"ES",
    "sg:address":"Ptge Marimon, 17",
    "sg:city":"Barcelona",
    "sg:orig_category":"Confecci\u00d3n De Trajes Para Se\u00d1oras",
    "sg:phone":"+34 932 00 05 79",
    "sg:postcode":"08021",
    "sg:province":"Barcelona",
    "wof:name":"Daher  Rauf",
    "wof:placetype":"venue"
},
  "geometry": {"coordinates":[2.1475679874,41.39453125],"type":"Point"}
}