{
  "type": "Feature",
  "properties": {
    "iso:country":"ES",
    "sg:address":"Carr Joan Maragall, 2",
    "sg:city":"Bell-lloc D'urgell",
    "sg:orig_category":"Rectificaci\u00d3n, Mecanizado, Fresado",
    "sg:phone":"+34 973 56 07 87",
    "sg:postcode":"25220",
    "sg:province":"Lleida",
    "wof:name":"Mecanitzats Bell Lloc S.l.",
    "wof:placetype":"venue"
},
  "geometry": {"coordinates":[0.7750914097,41.6316070557],"type":"Point"}
}