{
  "type": "Feature",
  "properties": {
    "addr:full":"Calle de Nicaragua, 10 Vitoria-gasteiz \u00c1lava 01012",
    "addr:housenumber":"10",
    "addr:postcode":"01012",
    "addr:street":"Calle De Nicaragua",
    "iso:country":"ES",
    "sg:address":"Calle de Nicaragua, 10",
    "sg:city":"Vitoria-gasteiz",
    "sg:orig_category":"Electromec\u00c1nica",
    "sg:phone":"+34 945 22 95 10",
    "sg:postcode":"01012",
    "sg:province":"\u00c1lava",
    "sg:website":"www.asistencia2000.com",
    "wof:name":"Christian Vadillo Duarte",
    "wof:placetype":"venue"
},
  "geometry": {"coordinates":[-2.6775500774,42.8551483154],"type":"Point"}
}