{
  "type": "Feature",
  "properties": {
    "iso:country":"ES",
    "sg:address":"Calle de Prado La Hueria, 1",
    "sg:city":"Pola De Laviana",
    "sg:orig_category":"Alimentaci\u00d3n General (al Por Mayor)",
    "sg:phone":"+34 985 60 02 11",
    "sg:postcode":"33980",
    "sg:province":"Asturias",
    "wof:name":"Fernandez Vallin Juan Jose",
    "wof:placetype":"venue"
},
  "geometry": {"coordinates":[-5.5613760948,43.2466468811],"type":"Point"}
}