{
  "type": "Feature",
  "properties": {
    "iso:country":"ES",
    "sg:address":"C/ Hospital, 5",
    "sg:city":"Elche",
    "sg:orig_category":"Ropa De Hogar (al Por Menor)",
    "sg:phone":"+34 966 61 39 86",
    "sg:postcode":"03203",
    "sg:province":"Alicante",
    "sg:website":"www.textura-interiors.com",
    "wof:name":"Textil Textura S.l.",
    "wof:placetype":"venue"
},
  "geometry": {"coordinates":[-0.6973329782,38.265499115],"type":"Point"}
}