{
  "type": "Feature",
  "properties": {
    "addr:full":"Cmno San Cristobal, S/n Medina Campo Valladolid 47400",
    "addr:postcode":"47400",
    "addr:street":"Cmno San Cristobal S / N Medina",
    "iso:country":"ES",
    "sg:address":"Cmno San Cristobal, S/n",
    "sg:city":"Medina Campo",
    "sg:orig_category":"Fabricaci\u00d3n, Comercio De Muebles Para Ni\u00d1os",
    "sg:phone":"+34 983 81 12 31",
    "sg:postcode":"47400",
    "sg:province":"Valladolid",
    "wof:name":"Sacul 2002 S.l",
    "wof:placetype":"venue"
},
  "geometry": {"coordinates":[-4.913184166,41.3120155334],"type":"Point"}
}