{
  "type": "Feature",
  "properties": {
    "addr:full":"Ramon Y Cajal, 5 Piles Valencia 46712",
    "addr:housenumber":"5",
    "addr:postcode":"46712",
    "addr:street":"Ramon Y Cajal",
    "iso:country":"ES",
    "sg:address":"Ramon Y Cajal, 5",
    "sg:city":"Piles",
    "sg:orig_category":"Parques De Atracciones Y Centros De Esparcimiento",
    "sg:phone":"+34 962 83 18 68",
    "sg:postcode":"46712",
    "sg:province":"Valencia",
    "wof:name":"Recreativos Giner Molto S. L.",
    "wof:placetype":"venue"
},
  "geometry": {"coordinates":[-0.1338690072,38.938999176],"type":"Point"}
}