{
  "type": "Feature",
  "properties": {
    "addr:full":"Calle de Infante Don Fernando, 20 Antequera M\u00e1laga 29200",
    "addr:housenumber":"20",
    "addr:postcode":"29200",
    "addr:street":"Calle De Infante Don Fernando",
    "iso:country":"ES",
    "sg:address":"Calle de Infante Don Fernando, 20",
    "sg:city":"Antequera",
    "sg:orig_category":"Institutos De Belleza",
    "sg:phone":"+34 952 84 28 03",
    "sg:postcode":"29200",
    "sg:province":"M\u00e1laga",
    "wof:name":"Ramirez Garcia Rosario",
    "wof:placetype":"venue"
},
  "geometry": {"coordinates":[-4.5601840019,37.0174102783],"type":"Point"}
}