{
  "type": "Feature",
  "properties": {
    "addr:full":"Rua Ladeira, 45 Ba\u00e7os De Molgas Ourense 32701",
    "addr:housenumber":"45",
    "addr:postcode":"32701",
    "addr:street":"Rua Ladeira",
    "iso:country":"ES",
    "sg:address":"Rua Ladeira, 45",
    "sg:city":"Ba\u00e7os De Molgas",
    "sg:orig_category":"Venta, Instalaci\u00d3n, Reparaci\u00d3n De Antenas Para Televisi\u00d3n",
    "sg:phone":"+34 988 43 03 07",
    "sg:postcode":"32701",
    "sg:province":"Ourense",
    "wof:name":"Diaz Villar Jose",
    "wof:placetype":"venue"
},
  "geometry": {"coordinates":[-7.6720380783,42.2407493591],"type":"Point"}
}