{
  "type": "Feature",
  "properties": {
    "addr:full":"En Proy., S/n Llosa Ranes Valencia 46815",
    "addr:housenumber":"s / n",
    "addr:postcode":"46815",
    "iso:country":"ES",
    "sg:address":"En Proy., S/n",
    "sg:city":"Llosa Ranes",
    "sg:orig_category":"Cer\u00c1micas: Material Y Suministros",
    "sg:phone":"+34 962 92 40 14",
    "sg:postcode":"46815",
    "sg:province":"Valencia",
    "wof:name":"Plasvina S.l.",
    "wof:placetype":"venue"
},
  "geometry": {"coordinates":[-0.5338389874,39.0177955627],"type":"Point"}
}