{
  "type": "Feature",
  "properties": {
    "iso:country":"ES",
    "sg:address":"Ptda Salinetas, 4",
    "sg:city":"Novelda",
    "sg:orig_category":"Hormigonados",
    "sg:phone":"+34 965 62 46 23",
    "sg:postcode":"03660",
    "sg:province":"Alicante",
    "wof:name":"Holcim Hormigones",
    "wof:placetype":"venue"
},
  "geometry": {"coordinates":[-0.7638189793,38.3825035095],"type":"Point"}
}