{
  "type": "Feature",
  "properties": {
    "addr:full":"Carrer de Marquet, 2 Barcelona Barcelona 08002",
    "addr:housenumber":"2",
    "addr:postcode":"08002",
    "addr:street":"Carrer De Marquet",
    "iso:country":"ES",
    "sg:address":"Carrer de Marquet, 2",
    "sg:city":"Barcelona",
    "sg:orig_category":"Molduras, Junquillos, Listones Y Molduras Perforadas",
    "sg:phone":"+34 933 10 73 74",
    "sg:postcode":"08002",
    "sg:province":"Barcelona",
    "wof:name":"Fazli Khan Millan",
    "wof:placetype":"venue"
},
  "geometry": {"coordinates":[2.1804358959,41.3808288574],"type":"Point"}
}