{
  "type": "Feature",
  "properties": {
    "iso:country":"ES",
    "sg:address":"Calle de Estacion, 17",
    "sg:city":"Villarrobledo",
    "sg:orig_category":"Discapacitados",
    "sg:phone":"+34 967 14 52 72",
    "sg:postcode":"02600",
    "sg:province":"Albacete",
    "wof:name":"Organizacion Impulsora De Discapacitados O.i.d.",
    "wof:placetype":"venue"
},
  "geometry": {"coordinates":[-2.6026275158,39.2628288269],"type":"Point"}
}