{
  "type": "Feature",
  "properties": {
    "addr:full":"C/ Cardenal Benlloch, 4 Paterna Valencia 46980",
    "addr:housenumber":"4",
    "addr:postcode":"46980",
    "addr:street":"C / Cardenal Benlloch",
    "iso:country":"ES",
    "sg:address":"C/ Cardenal Benlloch, 4",
    "sg:city":"Paterna",
    "sg:orig_category":"Estancos",
    "sg:phone":"+34 961 37 25 21",
    "sg:postcode":"46980",
    "sg:province":"Valencia",
    "wof:name":"Moragon Comes Maria Teresa",
    "wof:placetype":"venue"
},
  "geometry": {"coordinates":[-0.4343920052,39.4981040955],"type":"Point"}
}