{
  "type": "Feature",
  "properties": {
    "addr:full":"Calle de Santa Maria, 2 Bilbao Vizcaya 48005",
    "addr:housenumber":"2",
    "addr:postcode":"48005",
    "addr:street":"Calle De Santa Maria",
    "iso:country":"ES",
    "sg:address":"Calle de Santa Maria, 2",
    "sg:city":"Bilbao",
    "sg:orig_category":"Centros De Educaci\u00d3n Especial",
    "sg:phone":"+34 944 15 09 19",
    "sg:postcode":"48005",
    "sg:province":"Vizcaya",
    "wof:name":"Colegio Ense\u00f1anza Primaria Mugika-solokdetxe",
    "wof:placetype":"venue"
},
  "geometry": {"coordinates":[-2.9264690876,43.2585601807],"type":"Point"}
}