{
  "type": "Feature",
  "properties": {
    "addr:full":"Calle de Amor De Dios, 35 Sevilla Sevilla 41002",
    "addr:housenumber":"35",
    "addr:postcode":"41002",
    "addr:street":"Calle De Amor De Dios",
    "iso:country":"ES",
    "sg:address":"Calle de Amor De Dios, 35",
    "sg:city":"Sevilla",
    "sg:orig_category":"Asociaciones Y Clubs Deportivos",
    "sg:phone":"+34 954 90 10 20",
    "sg:postcode":"41002",
    "sg:province":"Sevilla",
    "wof:name":"Castillo Dominguez Ana Maria",
    "wof:placetype":"venue"
},
  "geometry": {"coordinates":[-5.9944105148,37.3957481384],"type":"Point"}
}