{
  "type": "Feature",
  "properties": {
    "addr:full":"Carrer de Marconi, 1 Sector Autopista Barcelona 08150",
    "addr:housenumber":"1",
    "addr:postcode":"08150",
    "addr:street":"Carrer De Marconi;Autopista Barcelona",
    "iso:country":"ES",
    "sg:address":"Carrer de Marconi, 1",
    "sg:city":"Sector Autopista",
    "sg:orig_category":"Delegados, Agentes De Tr\u00c1nsito, Auxiliares De Transporte Internacional",
    "sg:phone":"+34 935 62 47 03",
    "sg:postcode":"08150",
    "sg:province":"Barcelona",
    "wof:name":"Transmollet S.a.",
    "wof:placetype":"venue"
},
  "geometry": {"coordinates":[2.2293000221,41.5678787231],"type":"Point"}
}