{
  "type": "Feature",
  "properties": {
    "addr:full":"Carrer de Pont, 6 Flix Tarragona 43750",
    "addr:housenumber":"6",
    "addr:postcode":"43750",
    "addr:street":"Carrer De Pont",
    "iso:country":"ES",
    "sg:address":"Carrer de Pont, 6",
    "sg:city":"Flix",
    "sg:orig_category":"Aceites Y Grasas Alimentarias (fabricaci\u00d3n, Al Por Mayor)",
    "sg:phone":"+34 977 41 06 00",
    "sg:postcode":"43750",
    "sg:province":"Tarragona",
    "sg:website":"www.oliflix.com",
    "wof:name":"Rey Sole Antonio",
    "wof:placetype":"venue"
},
  "geometry": {"coordinates":[0.5494599938,41.2323455811],"type":"Point"}
}