{
  "type": "Feature",
  "properties": {
    "addr:full":"Avda Espa\u00d1a (de), 89 Ubrique C\u00e1diz 11600",
    "addr:housenumber":"89",
    "addr:postcode":"11600",
    "addr:street":"Avda Espan\u0303A De;Ca\u0301Diz",
    "iso:country":"ES",
    "sg:address":"Avda Espa\u00d1a (de), 89",
    "sg:city":"Ubrique",
    "sg:orig_category":"Farmacias",
    "sg:phone":"+34 956 46 01 58",
    "sg:postcode":"11600",
    "sg:province":"C\u00e1diz",
    "wof:name":"Torres Torres Antonio",
    "wof:placetype":"venue"
},
  "geometry": {"coordinates":[-5.4480090141,36.6727218628],"type":"Point"}
}