{
  "type": "Feature",
  "properties": {
    "addr:full":"Calle de Augusto Echeverria, 19 Mendavia Navarra 31587",
    "addr:housenumber":"19",
    "addr:postcode":"31587",
    "addr:street":"Calle De Augusto Echeverria",
    "iso:country":"ES",
    "sg:address":"Calle de Augusto Echeverria, 19",
    "sg:city":"Mendavia",
    "sg:orig_category":"Cl\u00cdnicas Dentales",
    "sg:phone":"+34 948 69 54 49",
    "sg:postcode":"31587",
    "sg:province":"Navarra",
    "wof:name":"Clinica Dental Maria J. Provedo",
    "wof:placetype":"venue"
},
  "geometry": {"coordinates":[-2.1997754574,42.4436149597],"type":"Point"}
}