{
  "type": "Feature",
  "properties": {
    "addr:full":"Carrer de Crom, 33 Hospitalet Llobregat Barcelona 08907",
    "addr:housenumber":"33",
    "addr:postcode":"08907",
    "addr:street":"Carrer De Crom",
    "iso:country":"ES",
    "sg:address":"Carrer de Crom, 33",
    "sg:city":"Hospitalet Llobregat",
    "sg:orig_category":"Tapiceros Y Tapiceros",
    "sg:phone":"+34 933 35 19 88",
    "sg:postcode":"08907",
    "sg:province":"Barcelona",
    "wof:name":"Tapiceria J. Hernandez S.l.",
    "wof:placetype":"venue"
},
  "geometry": {"coordinates":[2.1037809849,41.3523979187],"type":"Point"}
}