{
  "type": "Feature",
  "properties": {
    "addr:full":"Avda Andalucia (de), 38 Valdemoro Madrid 28340",
    "addr:housenumber":"38",
    "addr:postcode":"28340",
    "addr:street":"Avda Andalucia De",
    "iso:country":"ES",
    "sg:address":"Avda Andalucia (de), 38",
    "sg:city":"Valdemoro",
    "sg:orig_category":"Grafistas",
    "sg:phone":"+34 918 01 89 09",
    "sg:postcode":"28340",
    "sg:province":"Madrid",
    "wof:name":"Martin Plaza Benjamin",
    "wof:placetype":"venue"
},
  "geometry": {"coordinates":[-3.6744329929,40.1929702759],"type":"Point"}
}