{
  "type": "Feature",
  "properties": {
    "addr:full":"C/ Manuel Alcaraz Mora, 25 Elche Alicante 03204",
    "addr:housenumber":"25",
    "addr:postcode":"03204",
    "addr:street":"C / Manuel Alcaraz Mora",
    "iso:country":"ES",
    "sg:address":"C/ Manuel Alcaraz Mora, 25",
    "sg:city":"Elche",
    "sg:orig_category":"Bobinado, Reparaci\u00d3n De Material El\u00c9ctrico Profesional",
    "sg:phone":"+34 966 63 21 11",
    "sg:postcode":"03204",
    "sg:province":"Alicante",
    "wof:name":"Jordan Gea Francisco Antonio",
    "wof:placetype":"venue"
},
  "geometry": {"coordinates":[-0.7047290206,38.2547531128],"type":"Point"}
}