{
  "type": "Feature",
  "properties": {
    "addr:full":"Vilari\u00f1o(soandres), S/n Santa Marta La Coru\u00f1a 15145",
    "addr:housenumber":"s / n",
    "addr:postcode":"15145",
    "addr:street":"Santa Marta La Corun\u0303A",
    "iso:country":"ES",
    "sg:address":"Vilari\u00f1o(soandres), S/n",
    "sg:city":"Santa Marta",
    "sg:orig_category":"Explosivos",
    "sg:phone":"+34 981 63 01 68",
    "sg:postcode":"15145",
    "sg:province":"La Coru\u00f1a",
    "wof:name":"Explosivos Galicia S.a.",
    "wof:placetype":"venue"
},
  "geometry": {"coordinates":[-8.5813436508,43.2482681274],"type":"Point"}
}