{
  "type": "Feature",
  "properties": {
    "iso:country":"ES",
    "sg:address":"Calle de Lope De Rueda, 181",
    "sg:city":"Malaga",
    "sg:orig_category":"Asociaciones Y Clubs Deportivos",
    "sg:phone":"+34 952 43 81 81",
    "sg:postcode":"29190",
    "sg:province":"M\u00e1laga",
    "wof:name":"Club Deportivo Europa",
    "wof:placetype":"venue"
},
  "geometry": {"coordinates":[-4.492369175,36.7465209961],"type":"Point"}
}