{
  "type": "Feature",
  "properties": {
    "addr:full":"Calle de Carniceria, 10 Molinos Duero Soria 42155",
    "addr:housenumber":"10",
    "addr:postcode":"42155",
    "addr:street":"Calle De Carniceria",
    "iso:country":"ES",
    "sg:address":"Calle de Carniceria, 10",
    "sg:city":"Molinos Duero",
    "sg:orig_category":"Delegados, Agentes De Tr\u00c1nsito, Auxiliares De Transporte Internacional",
    "sg:phone":"+34 975 37 83 07",
    "sg:postcode":"42155",
    "sg:province":"Soria",
    "wof:name":"Bonilla Calvo Nicolas-miguel",
    "wof:placetype":"venue"
},
  "geometry": {"coordinates":[-2.46916008,41.7646484375],"type":"Point"}
}