{
  "type": "Feature",
  "properties": {
    "addr:full":"Calle de Jose Zorrilla, 81 Segovia Segovia 40002",
    "addr:housenumber":"81",
    "addr:postcode":"40002",
    "addr:street":"Calle De Jose Zorrilla",
    "iso:country":"ES",
    "sg:address":"Calle de Jose Zorrilla, 81",
    "sg:city":"Segovia",
    "sg:orig_category":"Carnicer\u00cdas, Carnicer\u00cdas",
    "sg:phone":"+34 921 42 16 27",
    "sg:postcode":"40002",
    "sg:province":"Segovia",
    "wof:name":"Herranz Gomez Felix Antonio",
    "wof:placetype":"venue"
},
  "geometry": {"coordinates":[-4.1150450706,40.9403381348],"type":"Point"}
}