{
  "type": "Feature",
  "properties": {
    "addr:full":"Carrer de Guadiana, 22 Barcelona Barcelona 08014",
    "addr:housenumber":"22",
    "addr:postcode":"08014",
    "addr:street":"Carrer De Guadiana",
    "iso:country":"ES",
    "sg:address":"Carrer de Guadiana, 22",
    "sg:city":"Barcelona",
    "sg:orig_category":"Cooperativas Agr\u00cdcolas",
    "sg:phone":"+34 934 21 67 40",
    "sg:postcode":"08014",
    "sg:province":"Barcelona",
    "wof:name":"Sociedad Cooperativa La Nueva Obrera",
    "wof:placetype":"venue"
},
  "geometry": {"coordinates":[2.1390500069,41.374294281],"type":"Point"}
}