{
  "type": "Feature",
  "properties": {
    "addr:full":"Calle de Carretera, Km. 0253,2 Cerro Muriano C\u00f3rdoba 14350",
    "addr:postcode":"14350",
    "addr:street":"Calle De Carretera Km. 0253,2 Cerro;Co\u0301Rdoba",
    "iso:country":"ES",
    "sg:address":"Calle de Carretera, Km. 0253,2",
    "sg:city":"Cerro Muriano",
    "sg:orig_category":"Distribuci\u00d3n De Petr\u00d3leo Y Derivados",
    "sg:phone":"+34 957 35 01 48",
    "sg:postcode":"14350",
    "sg:province":"C\u00f3rdoba",
    "wof:name":"Idibsa S. A.",
    "wof:placetype":"venue"
},
  "geometry": {"coordinates":[-4.7729697227,38.0026054382],"type":"Point"}
}