{
  "type": "Feature",
  "properties": {
    "iso:country":"ES",
    "sg:address":"Calle de Carrera, 26",
    "sg:city":"Archidona",
    "sg:orig_category":"Fabricaci\u00d3n, Venta De Productos Base Farmac\u00c9uticos",
    "sg:phone":"+34 952 71 40 83",
    "sg:postcode":"29300",
    "sg:province":"M\u00e1laga",
    "wof:name":"Perez Diaz Jose",
    "wof:placetype":"venue"
},
  "geometry": {"coordinates":[-4.3887343407,37.0953483582],"type":"Point"}
}