{
  "type": "Feature",
  "properties": {
    "iso:country":"ES",
    "sg:address":"Ponte Cabaleiros, 4",
    "sg:city":"Puente Cabaleiros",
    "sg:orig_category":"Teatros Y Salas De Espect\u00c1culos",
    "sg:phone":"+34 986 66 50 61",
    "sg:postcode":"36430",
    "sg:province":"Pontevedra",
    "wof:name":"Gil Gil Juan Manuel",
    "wof:placetype":"venue"
},
  "geometry": {"coordinates":[-8.2902040482,42.1192703247],"type":"Point"}
}