{
  "type": "Feature",
  "properties": {
    "iso:country":"ES",
    "sg:address":"Urb Calahonda Ro, S/n",
    "sg:city":"Mijas Costa",
    "sg:orig_category":"M\u00c9dicos: Estomatolog\u00cda",
    "sg:phone":"+34 952 93 59 80",
    "sg:postcode":"29649",
    "sg:province":"M\u00e1laga",
    "wof:name":"Gamboa Fernandez Rosario",
    "wof:placetype":"venue"
},
  "geometry": {"coordinates":[-4.6411604881,36.5099143982],"type":"Point"}
}