{
  "type": "Feature",
  "properties": {
    "addr:full":"Plaz Hernan Cortes, 4 Leganes Madrid 28911",
    "addr:housenumber":"4",
    "addr:postcode":"28911",
    "addr:street":"Plaz Hernan Cortes",
    "iso:country":"ES",
    "sg:address":"Plaz Hernan Cortes, 4",
    "sg:city":"Leganes",
    "sg:orig_category":"Muebles, Minoristas",
    "sg:phone":"+34 916 93 26 75",
    "sg:postcode":"28911",
    "sg:province":"Madrid",
    "wof:name":"Carrasco Pacios Jose Antonio",
    "wof:placetype":"venue"
},
  "geometry": {"coordinates":[-3.7676510811,40.3242454529],"type":"Point"}
}