{
  "type": "Feature",
  "properties": {
    "iso:country":"ES",
    "sg:address":"Calle de Valencia, 2",
    "sg:city":"Alfafar",
    "sg:orig_category":"M\u00c9dicos: Otorrinolaringolog\u00cda",
    "sg:phone":"+34 963 76 46 44",
    "sg:postcode":"46910",
    "sg:province":"Valencia",
    "wof:name":"Mocholi Alamar Enrique",
    "wof:placetype":"venue"
},
  "geometry": {"coordinates":[-0.3887139857,39.4253158569],"type":"Point"}
}