{
  "type": "Feature",
  "properties": {
    "iso:country":"ES",
    "sg:address":"Avda Principe Felipe, 82",
    "sg:city":"Martos",
    "sg:orig_category":"Perfumer\u00cda (al Por Menor)",
    "sg:phone":"+34 953 70 46 48",
    "sg:postcode":"23600",
    "sg:province":"Ja\u00e9n",
    "wof:name":"Sociedad Cooperativa Andaluza Drogasur",
    "wof:placetype":"venue"
},
  "geometry": {"coordinates":[-3.9685819149,37.7130622864],"type":"Point"}
}