{
  "type": "Feature",
  "properties": {
    "iso:country":"ES",
    "sg:address":"Ouvigo, Km. 0006,0",
    "sg:city":"Ouvigo",
    "sg:orig_category":"M\u00c1rmoles, Granitos Y Piedras Naturales",
    "sg:phone":"+34 988 40 84 67",
    "sg:postcode":"32634",
    "sg:province":"Ourense",
    "wof:name":"Granitos Poligono Antela S.l.",
    "wof:placetype":"venue"
},
  "geometry": {"coordinates":[-7.7509541512,42.0000267029],"type":"Point"}
}