{
  "type": "Feature",
  "properties": {
    "iso:country":"ES",
    "sg:address":"Avda Constitucion (de La), 10",
    "sg:city":"Azuqueca Henares",
    "sg:orig_category":"Ropa Para Ni\u00d1os (al Por Menor)",
    "sg:phone":"+34 949 26 52 31",
    "sg:postcode":"19200",
    "sg:province":"Guadalajara",
    "wof:name":"Alonso Hernanz Maria Jesus",
    "wof:placetype":"venue"
},
  "geometry": {"coordinates":[-3.2660570145,40.5634231567],"type":"Point"}
}