{
  "type": "Feature",
  "properties": {
    "addr:full":"Avda Dos De Mayo (del), 24 Mostoles Madrid 28934",
    "addr:housenumber":"24",
    "addr:postcode":"28934",
    "addr:street":"Avda Dos De Mayo Del",
    "iso:country":"ES",
    "sg:address":"Avda Dos De Mayo (del), 24",
    "sg:city":"Mostoles",
    "sg:orig_category":"Frutas, Legumbres Frescas Y Tempranas (al Por Menor)",
    "sg:phone":"+34 916 18 47 54",
    "sg:postcode":"28934",
    "sg:province":"Madrid",
    "wof:name":"Gutierrez Alba Martin",
    "wof:placetype":"venue"
},
  "geometry": {"coordinates":[-3.8670079708,40.3209037781],"type":"Point"}
}