{
  "type": "Feature",
  "properties": {
    "addr:full":"Avda Alcalde Paco Gonzalez, S/n Arguineguin Las Palmas 35120",
    "addr:postcode":"35120",
    "addr:street":"Avda Alcalde Paco Gonzalez S / N;Palmas",
    "iso:country":"ES",
    "sg:address":"Avda Alcalde Paco Gonzalez, S/n",
    "sg:city":"Arguineguin",
    "sg:orig_category":"Asociaciones Y Clubs Deportivos",
    "sg:phone":"+34 928 15 13 76",
    "sg:postcode":"35120",
    "sg:province":"Las Palmas",
    "wof:name":"Club Deportivo De Arguineguin",
    "wof:placetype":"venue"
},
  "geometry": {"coordinates":[-15.6801586151,27.7579250336],"type":"Point"}
}