{
  "type": "Feature",
  "properties": {
    "addr:full":"Calle de Vitigudino, 21 Salamanca Salamanca 37007",
    "addr:housenumber":"21",
    "addr:postcode":"37007",
    "addr:street":"Calle De Vitigudino",
    "iso:country":"ES",
    "sg:address":"Calle de Vitigudino, 21",
    "sg:city":"Salamanca",
    "sg:orig_category":"Droguer\u00cdas (al Por Menor)",
    "sg:phone":"+34 923 24 36 60",
    "sg:postcode":"37007",
    "sg:province":"Salamanca",
    "wof:name":"Cojo Marcos Teresa",
    "wof:placetype":"venue"
},
  "geometry": {"coordinates":[-5.6692810059,40.9717903137],"type":"Point"}
}