{
  "type": "Feature",
  "properties": {
    "iso:country":"ES",
    "sg:address":"Calle de Pastillo, 13",
    "sg:city":"Huelva",
    "sg:orig_category":"Florister\u00cdas",
    "sg:phone":"+34 959 23 56 83",
    "sg:postcode":"21006",
    "sg:province":"Huelva",
    "wof:name":"Florido Ventura Manuela",
    "wof:placetype":"venue"
},
  "geometry": {"coordinates":[-6.9356951714,37.2611045837],"type":"Point"}
}