{
  "type": "Feature",
  "properties": {
    "iso:country":"ES",
    "sg:address":"Calle de Eras Bajas, 54",
    "sg:city":"Huetor-tajar",
    "sg:orig_category":"Reposter\u00cdas",
    "sg:phone":"+34 958 33 21 10",
    "sg:postcode":"18360",
    "sg:province":"Granada",
    "wof:name":"Ramos Correal Luis",
    "wof:placetype":"venue"
},
  "geometry": {"coordinates":[-4.0508489609,37.1960296631],"type":"Point"}
}