{
  "type": "Feature",
  "properties": {
    "addr:full":"Pol Ind El Oliveral, 57 P. I. El Oliveral Valencia 46190",
    "addr:housenumber":"57 p.",
    "addr:postcode":"46190",
    "addr:street":"Oliveral;I. El Oliveral",
    "iso:country":"ES",
    "sg:address":"Pol Ind El Oliveral, 57",
    "sg:city":"P. I. El Oliveral",
    "sg:orig_category":"Artes Gr\u00c1ficas, Artes Pl\u00c1sticas: Material Y Suministros (al Por Menor)",
    "sg:phone":"+34 961 66 84 82",
    "sg:postcode":"46190",
    "sg:province":"Valencia",
    "sg:website":"www.sakatainx.es",
    "wof:name":"Sakata Inx Espa\u00d1a S.a.",
    "wof:placetype":"venue"
},
  "geometry": {"coordinates":[-0.5698940158,39.5458450317],"type":"Point"}
}