{
  "type": "Feature",
  "properties": {
    "iso:country":"ES",
    "sg:address":"Mercat Hostafrancs, 88",
    "sg:city":"Barcelona",
    "sg:orig_category":"Carnicer\u00cdas, Carnicer\u00cdas",
    "sg:phone":"+34 934 31 51 31",
    "sg:postcode":"08014",
    "sg:province":"Barcelona",
    "wof:name":"Garcia Gine Ramon",
    "wof:placetype":"venue"
},
  "geometry": {"coordinates":[2.1443099976,41.3752288818],"type":"Point"}
}