{
  "type": "Feature",
  "properties": {
    "iso:country":"ES",
    "sg:address":"Carrer de L'artesania, 34",
    "sg:city":"Barcelona",
    "sg:orig_category":"Confecci\u00d3n (fabricaci\u00d3n, Al Por Mayor)",
    "sg:phone":"+34 933 54 32 49",
    "sg:postcode":"08042",
    "sg:province":"Barcelona",
    "wof:name":"Garcia Fernandez Juan Antonio",
    "wof:placetype":"venue"
},
  "geometry": {"coordinates":[2.1747159958,41.4394760132],"type":"Point"}
}