{
  "type": "Feature",
  "properties": {
    "addr:full":"Vilamartin, 2 Rioaveso Lugo 27818",
    "addr:housenumber":"2",
    "addr:postcode":"27818",
    "addr:street":"Vilamartin",
    "iso:country":"ES",
    "sg:address":"Vilamartin, 2",
    "sg:city":"Rioaveso",
    "sg:orig_category":"Lavado, Limpieza De Veh\u00cdculos",
    "sg:phone":"+34 982 52 30 08",
    "sg:postcode":"27818",
    "sg:province":"Lugo",
    "wof:name":"Lavado Rioaveso S.l.",
    "wof:placetype":"venue"
},
  "geometry": {"coordinates":[-7.6814470291,43.245716095],"type":"Point"}
}