{
  "type": "Feature",
  "properties": {
    "iso:country":"ES",
    "sg:address":"Calle de Correo, 25",
    "sg:city":"Bilbao",
    "sg:orig_category":"Perfumer\u00cda (al Por Menor)",
    "sg:phone":"+34 944 16 60 61",
    "sg:postcode":"48005",
    "sg:province":"Vizcaya",
    "wof:name":"Maria Mertxe Pikabea Etxegoien",
    "wof:placetype":"venue"
},
  "geometry": {"coordinates":[-2.9233748913,43.2572364807],"type":"Point"}
}