{
  "type": "Feature",
  "properties": {
    "addr:full":"Carr Industria, 77 Angles Girona 17160",
    "addr:housenumber":"77",
    "addr:postcode":"17160",
    "addr:street":"Carr Industria",
    "iso:country":"ES",
    "sg:address":"Carr Industria, 77",
    "sg:city":"Angles",
    "sg:orig_category":"Alimentaci\u00d3n General (al Por Menor)",
    "sg:phone":"+34 972 42 02 52",
    "sg:postcode":"17160",
    "sg:province":"Girona",
    "wof:name":"Puigdemont Casabo Ffrancesc",
    "wof:placetype":"venue"
},
  "geometry": {"coordinates":[2.6361498833,41.9570388794],"type":"Point"}
}