{
  "type": "Feature",
  "properties": {
    "addr:full":"Carrer de Arenys, 6 Gava Barcelona 08850",
    "addr:housenumber":"6",
    "addr:postcode":"08850",
    "addr:street":"Carrer De Arenys",
    "iso:country":"ES",
    "sg:address":"Carrer de Arenys, 6",
    "sg:city":"Gava",
    "sg:orig_category":"Centros Empresariales",
    "sg:phone":"+34 936 33 15 74",
    "sg:postcode":"08850",
    "sg:province":"Barcelona",
    "wof:name":"Bitterlich  Helga",
    "wof:placetype":"venue"
},
  "geometry": {"coordinates":[2.0305991173,41.2698249817],"type":"Point"}
}