{
  "type": "Feature",
  "properties": {
    "iso:country":"ES",
    "sg:address":"C/ Canal, 37",
    "sg:city":"Banyoles",
    "sg:orig_category":"Frutas, Legumbres Frescas Y Tempranas (al Por Menor)",
    "sg:phone":"+34 972 58 30 30",
    "sg:postcode":"17820",
    "sg:province":"Girona",
    "wof:name":"Teixidor Ramio Jose",
    "wof:placetype":"venue"
},
  "geometry": {"coordinates":[2.7650918961,42.1190338135],"type":"Point"}
}