{
  "type": "Feature",
  "properties": {
    "iso:country":"ES",
    "sg:address":"Carrer de Alcoi, 21",
    "sg:city":"Barcelona",
    "sg:orig_category":"Centros P\u00dablicos De Formaci\u00d3n Profesional Y T\u00c9cnica",
    "sg:phone":"+34 932 12 81 08",
    "sg:postcode":"08022",
    "sg:province":"Barcelona",
    "wof:name":"Co%egi Oficial De Diplomats En Enfermeria",
    "wof:placetype":"venue"
},
  "geometry": {"coordinates":[2.1294848919,41.407081604],"type":"Point"}
}