{
  "type": "Feature",
  "properties": {
    "iso:country":"ES",
    "sg:address":"Rua Rio Xubia, 1",
    "sg:city":"Ferrol",
    "sg:orig_category":"Librer\u00cdas",
    "sg:phone":"+34 981 32 08 33",
    "sg:postcode":"15403",
    "sg:province":"A Coru\u00f1a",
    "wof:name":"Testa Rodriguez Jose Antonio",
    "wof:placetype":"venue"
},
  "geometry": {"coordinates":[-8.2253723145,43.4902496338],"type":"Point"}
}