{
  "type": "Feature",
  "properties": {
    "addr:full":"Calle de Blas De Lezo, 11 Palmas De Gran Canaria Las Palmas 35009",
    "addr:housenumber":"11",
    "addr:postcode":"35009",
    "addr:street":"Calle De Blas De Lezo",
    "iso:country":"ES",
    "sg:address":"Calle de Blas De Lezo, 11",
    "sg:city":"Palmas De Gran Canaria",
    "sg:orig_category":"Electricidad (montaje, Ensamblaje De Componentes)",
    "sg:phone":"+34 928 46 06 55",
    "sg:postcode":"35009",
    "sg:province":"Las Palmas",
    "wof:name":"Santana Moreno Victor",
    "wof:placetype":"venue"
},
  "geometry": {"coordinates":[-15.4318323135,28.1535835266],"type":"Point"}
}