{
  "type": "Feature",
  "properties": {
    "addr:full":"Av Catalunya, 25 Tossa Girona 17320",
    "addr:housenumber":"25",
    "addr:postcode":"17320",
    "addr:street":"Av Catalunya",
    "iso:country":"ES",
    "sg:address":"Av Catalunya, 25",
    "sg:city":"Tossa",
    "sg:orig_category":"Pescader\u00cdas (al Por Menor)",
    "sg:phone":"+34 972 34 15 12",
    "sg:postcode":"17320",
    "sg:province":"Girona",
    "wof:name":"Salvador Badenas Joaquin",
    "wof:placetype":"venue"
},
  "geometry": {"coordinates":[2.9276740551,41.72498703],"type":"Point"}
}