{
  "type": "Feature",
  "properties": {
    "iso:country":"ES",
    "sg:address":"Calle de Mayor, 81",
    "sg:city":"Daroca",
    "sg:orig_category":"Plomeros",
    "sg:phone":"+34 976 80 07 54",
    "sg:postcode":"50360",
    "sg:province":"Zaragoza",
    "wof:name":"Gomez Arnillas Antonio",
    "wof:placetype":"venue"
},
  "geometry": {"coordinates":[-1.4134470224,41.1141281128],"type":"Point"}
}