{
  "type": "Feature",
  "properties": {
    "iso:country":"ES",
    "sg:address":"Ctra Castilnuevo, S/n",
    "sg:city":"Molina",
    "sg:orig_category":"Transporte En General",
    "sg:phone":"+34 949 83 19 30",
    "sg:postcode":"19300",
    "sg:province":"Guadalajara",
    "wof:name":"Almacenes Manuel Martinez S.a.",
    "wof:placetype":"venue"
},
  "geometry": {"coordinates":[-1.8862109184,40.8351554871],"type":"Point"}
}