{
  "type": "Feature",
  "properties": {
    "addr:full":"Calle de Luisa De Carvajal, 24 Madrid Madrid 28037",
    "addr:housenumber":"24",
    "addr:postcode":"madrid;28037",
    "addr:street":"Calle De Luisa De Carvajal",
    "iso:country":"ES",
    "sg:address":"Calle de Luisa De Carvajal, 24",
    "sg:city":"Madrid",
    "sg:orig_category":"Centros Empresariales",
    "sg:phone":"+34 913 27 24 33",
    "sg:postcode":"28037",
    "sg:province":"Madrid",
    "wof:name":"Borrero Sanchez Concepcion",
    "wof:placetype":"venue"
},
  "geometry": {"coordinates":[-3.6185491085,40.4372062683],"type":"Point"}
}