{
  "type": "Feature",
  "properties": {
    "addr:full":"Calle de Moret, 34 Caceres C\u00e1ceres 10003",
    "addr:housenumber":"34",
    "addr:postcode":"10003",
    "addr:street":"Calle De Moret;Ca\u0301Ceres",
    "iso:country":"ES",
    "sg:address":"Calle de Moret, 34",
    "sg:city":"Caceres",
    "sg:orig_category":"Inmobiliaria (agencias)",
    "sg:phone":"+34 927 24 24 15",
    "sg:postcode":"10003",
    "sg:province":"C\u00e1ceres",
    "wof:name":"Benitez Alfaro Antonio Vicente",
    "wof:placetype":"venue"
},
  "geometry": {"coordinates":[-6.3731708527,39.4741325378],"type":"Point"}
}