{
  "type": "Feature",
  "properties": {
    "iso:country":"ES",
    "sg:address":"Avda Crucero Baleares, S/n",
    "sg:city":"Rota",
    "sg:orig_category":"Veh\u00cdculos De Ocasi\u00d3n",
    "sg:phone":"+34 956 81 27 06",
    "sg:postcode":"11520",
    "sg:province":"C\u00e1diz",
    "wof:name":"Sanchez Ruiz Manuel",
    "wof:placetype":"venue"
},
  "geometry": {"coordinates":[-6.3448262215,36.6267738342],"type":"Point"}
}