{
  "type": "Feature",
  "properties": {
    "iso:country":"ES",
    "sg:address":"Cra Fuente De San Luis, 132",
    "sg:city":"Valencia",
    "sg:orig_category":"Ingenier\u00cda, Centros De Estudios (diversos)",
    "sg:phone":"+34 963 35 59 20",
    "sg:postcode":"46013",
    "sg:province":"Valencia",
    "wof:name":"S.i.c.a.ingenieria S.l.",
    "wof:placetype":"venue"
},
  "geometry": {"coordinates":[-0.3687250018,39.4487342834],"type":"Point"}
}