{
  "type": "Feature",
  "properties": {
    "iso:country":"ES",
    "sg:address":"Etxe-alai Auzunea, 8",
    "sg:city":"Azpeitia",
    "sg:orig_category":"Chapister\u00cda",
    "sg:phone":"+34 943 15 04 77",
    "sg:postcode":"20730",
    "sg:province":"Guip\u00f9zcoa",
    "wof:name":"Margarito Benitez Coronado",
    "wof:placetype":"venue"
},
  "geometry": {"coordinates":[-2.2683539391,43.1828269958],"type":"Point"}
}