{
  "type": "Feature",
  "properties": {
    "iso:country":"ES",
    "sg:address":"Rua Souto, 2",
    "sg:city":"Vilaboa",
    "sg:orig_category":"Promotores Constructores",
    "sg:phone":"+34 981 65 19 55",
    "sg:postcode":"15174",
    "sg:province":"La Coru\u00f1a",
    "wof:name":"Juge Gestion,s.l.",
    "wof:placetype":"venue"
},
  "geometry": {"coordinates":[-8.3806362152,43.3110542297],"type":"Point"}
}