{
  "type": "Feature",
  "properties": {
    "iso:country":"ES",
    "sg:address":"Carrer de Mallorca, 84",
    "sg:city":"Barcelona",
    "sg:orig_category":"Ropa Para Se\u00d1oras (al Por Menor)",
    "sg:phone":"+34 934 39 04 37",
    "sg:postcode":"08029",
    "sg:province":"Barcelona",
    "wof:name":"Royo Villarroya Montserrat",
    "wof:placetype":"venue"
},
  "geometry": {"coordinates":[2.1510190964,41.3849525452],"type":"Point"}
}