{
  "type": "Feature",
  "properties": {
    "iso:country":"ES",
    "sg:address":"Av Bartomeu De Rosello, 24",
    "sg:city":"Eivissa",
    "sg:orig_category":"Promotores Constructores",
    "sg:phone":"+34 971 31 69 54",
    "sg:postcode":"07800",
    "sg:province":"Islas Baleares",
    "sg:website":"www.ibigolf.com",
    "wof:name":"Karakala S.a.",
    "wof:placetype":"venue"
},
  "geometry": {"coordinates":[1.4325380325,38.910697937],"type":"Point"}
}