{
  "type": "Feature",
  "properties": {
    "addr:full":"Carrer de Repartidor Sant Isidre, 2 Lloret Mar Girona 17310",
    "addr:housenumber":"2",
    "addr:postcode":"17310",
    "addr:street":"Carrer De Repartidor Sant Isidre",
    "iso:country":"ES",
    "sg:address":"Carrer de Repartidor Sant Isidre, 2",
    "sg:city":"Lloret Mar",
    "sg:orig_category":"Confecci\u00d3n De Trajes Para Se\u00d1oras",
    "sg:phone":"+34 972 36 11 00",
    "sg:postcode":"17310",
    "sg:province":"Girona",
    "wof:name":"Gomez Sanchez Jose Luis",
    "wof:placetype":"venue"
},
  "geometry": {"coordinates":[2.8500430584,41.7017211914],"type":"Point"}
}