{
  "type": "Feature",
  "properties": {
    "iso:country":"ES",
    "sg:address":"Avenida I, S/n",
    "sg:city":"Mi\u00f1ano Menor",
    "sg:orig_category":"Organismos De Desarrollo",
    "sg:phone":"+34 945 29 70 32",
    "sg:postcode":"01510",
    "sg:province":"\u00c1lava",
    "sg:website":"www.ikerlan.es",
    "wof:name":"Ikerlan S.coop.",
    "wof:placetype":"venue"
},
  "geometry": {"coordinates":[-2.6685824394,42.9237670898],"type":"Point"}
}