{
  "type": "Feature",
  "properties": {
    "addr:full":"Calle de Alpes (los), 2 Utebo Zaragoza 50180",
    "addr:housenumber":"2",
    "addr:postcode":"50180",
    "addr:street":"Calle De Alpes Los",
    "iso:country":"ES",
    "sg:address":"Calle de Alpes (los), 2",
    "sg:city":"Utebo",
    "sg:orig_category":"Mercer\u00cda, Lencer\u00cda (al Por Menor)",
    "sg:phone":"+34 976 77 51 33",
    "sg:postcode":"50180",
    "sg:province":"Zaragoza",
    "wof:name":"Serrano Latorre Mercedes",
    "wof:placetype":"venue"
},
  "geometry": {"coordinates":[-1.0238640308,41.7170257568],"type":"Point"}
}