{
  "type": "Feature",
  "properties": {
    "addr:full":"Calle de Mayor, S/n Burbaguena Teruel 44330",
    "addr:housenumber":"s",
    "addr:postcode":"44330",
    "addr:street":"Calle De Mayor;/ N",
    "iso:country":"ES",
    "sg:address":"Calle de Mayor, S/n",
    "sg:city":"Burbaguena",
    "sg:orig_category":"Farmacias",
    "sg:phone":"+34 978 73 32 03",
    "sg:postcode":"44330",
    "sg:province":"Teruel",
    "wof:name":"Navarro Gomez Jose Maria",
    "wof:placetype":"venue"
},
  "geometry": {"coordinates":[-1.3418860435,41.0205345154],"type":"Point"}
}