{
  "type": "Feature",
  "properties": {
    "iso:country":"ES",
    "sg:address":"Praz Canteira, 6",
    "sg:city":"Perillo",
    "sg:orig_category":"Polideportivos",
    "sg:phone":"+34 981 63 40 30",
    "sg:postcode":"15172",
    "sg:province":"A Coru\u00f1a",
    "wof:name":"Sidecu S.l.",
    "wof:placetype":"venue"
},
  "geometry": {"coordinates":[-8.3740053177,43.3324584961],"type":"Point"}
}