{
  "type": "Feature",
  "properties": {
    "iso:country":"ES",
    "sg:address":"Calle de Talisio, 9",
    "sg:city":"Madrid",
    "sg:orig_category":"Coches Y Camiones (caja De Cambios, Embrague Y Frenos)",
    "sg:phone":"+34 914 08 68 10",
    "sg:postcode":"28027",
    "sg:province":"Madrid",
    "wof:name":"Ruiz Fernandez Francisco",
    "wof:placetype":"venue"
},
  "geometry": {"coordinates":[-3.64478302,40.4386062622],"type":"Point"}
}