{
  "type": "Feature",
  "properties": {
    "addr:full":"Calle de Abedul, 8 Torrejon Ardoz Madrid 28850",
    "addr:housenumber":"8",
    "addr:postcode":"28850",
    "addr:street":"Calle De Abedul",
    "iso:country":"ES",
    "sg:address":"Calle de Abedul, 8",
    "sg:city":"Torrejon Ardoz",
    "sg:orig_category":"Molduras, Junquillos, Listones Y Molduras Perforadas",
    "sg:phone":"+34 916 56 22 52",
    "sg:postcode":"28850",
    "sg:province":"Madrid",
    "wof:name":"Carmona Fernandez Antonia",
    "wof:placetype":"venue"
},
  "geometry": {"coordinates":[-3.4539461136,40.4541816711],"type":"Point"}
}