{
  "type": "Feature",
  "properties": {
    "iso:country":"ES",
    "sg:address":"Barr Basaldua, S/n",
    "sg:city":"Urdu\u00e7a-ordu\u00e7a",
    "sg:orig_category":"Embalajes",
    "sg:phone":"+34 945 38 36 16",
    "sg:postcode":"48460",
    "sg:province":"Vizcaya",
    "wof:name":"Embalajes Atxa S.l.",
    "wof:placetype":"venue"
},
  "geometry": {"coordinates":[-3.0069389343,42.9948730469],"type":"Point"}
}