{
  "type": "Feature",
  "properties": {
    "iso:country":"ES",
    "sg:address":"Avda Ricardo Soriano, 11",
    "sg:city":"Marbella",
    "sg:orig_category":"Sindicatos De Trabajadores",
    "sg:phone":"+34 952 77 95 44",
    "sg:postcode":"29600",
    "sg:province":"M\u00e1laga",
    "wof:name":"Union General De Trabajadores De Andalucia",
    "wof:placetype":"venue"
},
  "geometry": {"coordinates":[-4.8880639076,36.5097312927],"type":"Point"}
}