{
  "type": "Feature",
  "properties": {
    "iso:country":"ES",
    "sg:address":"Calle de Horno Espadero, 19",
    "sg:city":"Granada",
    "sg:orig_category":"Partidos Pol\u00cdticos",
    "sg:phone":"+34 958 26 59 50",
    "sg:postcode":"18005",
    "sg:province":"Granada",
    "wof:name":"Izquierda Unida-los Verdes Convocatoria Por Andalucia",
    "wof:placetype":"venue"
},
  "geometry": {"coordinates":[-3.6012449265,37.1717033386],"type":"Point"}
}