{
  "type": "Feature",
  "properties": {
    "iso:country":"ES",
    "sg:address":"Calle de Principe, 12",
    "sg:city":"Madrid",
    "sg:orig_category":"Organizaciones Internacionales",
    "sg:phone":"+34 915 21 72 83",
    "sg:postcode":"28012",
    "sg:province":"Madrid",
    "wof:name":"Survival International (espa\u00f1a",
    "wof:placetype":"venue"
},
  "geometry": {"coordinates":[-3.7004880905,40.415599823],"type":"Point"}
}