{
  "type": "Feature",
  "properties": {
    "addr:full":"Plaz San Marcos, S/n Adra Almer\u00eda 04770",
    "addr:housenumber":"s / n",
    "addr:postcode":"04770",
    "addr:street":"Plaz San Marcos;Almeri\u0301A",
    "iso:country":"ES",
    "sg:address":"Plaz San Marcos, S/n",
    "sg:city":"Adra",
    "sg:orig_category":"Alquiler De V\u00cddeo",
    "sg:phone":"+34 950 40 05 07",
    "sg:postcode":"04770",
    "sg:province":"Almer\u00eda",
    "wof:name":"Video Club Maestoni C.b.",
    "wof:placetype":"venue"
},
  "geometry": {"coordinates":[-2.9857189655,36.7566947937],"type":"Point"}
}