{
  "type": "Feature",
  "properties": {
    "iso:country":"ES",
    "sg:address":"Carrer de Mallorca, 634",
    "sg:city":"Barcelona",
    "sg:orig_category":"M\u00c9dicos: Estomatolog\u00cda",
    "sg:phone":"+34 934 08 46 50",
    "sg:postcode":"08026",
    "sg:province":"Barcelona",
    "wof:name":"Valladares Lama Cecilia",
    "wof:placetype":"venue"
},
  "geometry": {"coordinates":[2.187830925,41.4126434326],"type":"Point"}
}