{
  "type": "Feature",
  "properties": {
    "iso:country":"ES",
    "sg:address":"Avda Menendez Pelayo, S/n",
    "sg:city":"Torrelavega",
    "sg:orig_category":"Caf\u00c9s, Bares, Cervecer\u00cdas",
    "sg:phone":"+34 942 80 03 23",
    "sg:postcode":"39300",
    "sg:province":"Cantabria",
    "wof:name":"Gonzalez Carrion Felix",
    "wof:placetype":"venue"
},
  "geometry": {"coordinates":[-4.050465107,43.3503990173],"type":"Point"}
}