{
  "type": "Feature",
  "properties": {
    "addr:full":"Rbla Catalunya, 47 Barcelona Barcelona 08007",
    "addr:housenumber":"47",
    "addr:postcode":"08007",
    "addr:street":"Rbla Catalunya",
    "iso:country":"ES",
    "sg:address":"Rbla Catalunya, 47",
    "sg:city":"Barcelona",
    "sg:orig_category":"Asesor\u00cdas Y Estudios Financieros",
    "sg:phone":"+34 934 88 28 60",
    "sg:postcode":"08007",
    "sg:province":"Barcelona",
    "wof:name":"Gibernau Plana & Asociados S. L.",
    "wof:placetype":"venue"
},
  "geometry": {"coordinates":[2.1641049385,41.3902931213],"type":"Point"}
}