{
  "type": "Feature",
  "properties": {
    "addr:full":"Carr Mare De Deu Del Carme, 1 Port D'alcudia Islas Baleares 07410",
    "addr:housenumber":"1",
    "addr:postcode":"07410",
    "addr:street":"Carr Mare De Deu Del Carme",
    "iso:country":"ES",
    "sg:address":"Carr Mare De Deu Del Carme, 1",
    "sg:city":"Port D'alcudia",
    "sg:orig_category":"Agencias De Viajes",
    "sg:phone":"+34 971 89 79 08",
    "sg:postcode":"07410",
    "sg:province":"Islas Baleares",
    "wof:name":"Viarsegui S.l.u",
    "wof:placetype":"venue"
},
  "geometry": {"coordinates":[3.1162230968,39.8512649536],"type":"Point"}
}