{
  "type": "Feature",
  "properties": {
    "addr:full":"Pase Santa Maria De La Cabeza, 114 Madrid Madrid 28019",
    "addr:housenumber":"114",
    "addr:postcode":"28019",
    "addr:street":"Cabeza",
    "iso:country":"ES",
    "sg:address":"Pase Santa Maria De La Cabeza, 114",
    "sg:city":"Madrid",
    "sg:orig_category":"Reposter\u00cdas",
    "sg:phone":"+34 915 60 86 21",
    "sg:postcode":"28019",
    "sg:province":"Madrid",
    "wof:name":"Caldeiro Martin Jose",
    "wof:placetype":"venue"
},
  "geometry": {"coordinates":[-3.7090070248,40.3914642334],"type":"Point"}
}