{
  "type": "Feature",
  "properties": {
    "addr:full":"Calle de Covadonga, 11 Sevilla Sevilla 41010",
    "addr:housenumber":"11",
    "addr:postcode":"41010",
    "addr:street":"Calle De Covadonga",
    "iso:country":"ES",
    "sg:address":"Calle de Covadonga, 11",
    "sg:city":"Sevilla",
    "sg:orig_category":"Electrodom\u00c9sticos (al Por Menor)",
    "sg:phone":"+34 954 34 31 16",
    "sg:postcode":"41010",
    "sg:province":"Sevilla",
    "wof:name":"Rosa Rodriguez Luis De La",
    "wof:placetype":"venue"
},
  "geometry": {"coordinates":[-6.005361557,37.3844451904],"type":"Point"}
}