{
  "type": "Feature",
  "properties": {
    "addr:full":"Rbla Guipuscoa, 132 Barcelona Barcelona 08020",
    "addr:housenumber":"132",
    "addr:postcode":"08020",
    "addr:street":"Rbla Guipuscoa",
    "iso:country":"ES",
    "sg:address":"Rbla Guipuscoa, 132",
    "sg:city":"Barcelona",
    "sg:orig_category":"Institutos De Belleza",
    "sg:phone":"+34 933 14 66 68",
    "sg:postcode":"08020",
    "sg:province":"Barcelona",
    "wof:name":"Cazorla Asencio Etelvina",
    "wof:placetype":"venue"
},
  "geometry": {"coordinates":[2.2035770416,41.4208831787],"type":"Point"}
}