{
  "type": "Feature",
  "properties": {
    "addr:full":"Calle de Caceres (de), 18 Alcobendas Madrid 28100",
    "addr:housenumber":"18",
    "addr:postcode":"28100",
    "addr:street":"Calle De Caceres De",
    "iso:country":"ES",
    "sg:address":"Calle de Caceres (de), 18",
    "sg:city":"Alcobendas",
    "sg:orig_category":"Asociaciones Y Clubs Deportivos",
    "sg:phone":"+34 916 51 17 97",
    "sg:postcode":"28100",
    "sg:province":"Madrid",
    "wof:name":"Agrupacion Deportiva Amigos Del Billar",
    "wof:placetype":"venue"
},
  "geometry": {"coordinates":[-3.6314537525,40.5385360718],"type":"Point"}
}