{
  "type": "Feature",
  "properties": {
    "addr:full":"Avda Aviacion Espa\u00d1ola, 43 Castro Rei Lugo 27250",
    "addr:housenumber":"43",
    "addr:postcode":"27250",
    "addr:street":"Avda Aviacion Espan\u0303Ola",
    "iso:country":"ES",
    "sg:address":"Avda Aviacion Espa\u00d1ola, 43",
    "sg:city":"Castro Rei",
    "sg:orig_category":"Farmacias",
    "sg:phone":"+34 982 31 41 51",
    "sg:postcode":"27250",
    "sg:province":"Lugo",
    "wof:name":"Ansede Pastor Maria Jesus",
    "wof:placetype":"venue"
},
  "geometry": {"coordinates":[-7.395960331,43.2069549561],"type":"Point"}
}