{
  "type": "Feature",
  "properties": {
    "addr:full":"Cno. De La Monta\u00f1a, 4 Alcudia Valencia 46250",
    "addr:housenumber":"4",
    "addr:postcode":"46250",
    "addr:street":"Cno. De La Montan\u0303A",
    "iso:country":"ES",
    "sg:address":"Cno. De La Monta\u00f1a, 4",
    "sg:city":"Alcudia",
    "sg:orig_category":"Molduras, Junquillos, Listones Y Molduras Perforadas",
    "sg:phone":"+34 962 54 08 45",
    "sg:postcode":"46250",
    "sg:province":"Valencia",
    "wof:name":"Gonzalez Mu\u00f1oz Jose Antonio",
    "wof:placetype":"venue"
},
  "geometry": {"coordinates":[-0.5070289969,39.1940689087],"type":"Point"}
}