{
  "type": "Feature",
  "properties": {
    "iso:country":"ES",
    "sg:address":"Calle de Juan Antonio Bravo, 22",
    "sg:city":"Cudillero",
    "sg:orig_category":"Arreglo, Reparaci\u00d3n, Piezas Sueltas De Televisi\u00d3n, V\u00cddeo, Hi",
    "sg:phone":"+34 985 59 12 79",
    "sg:postcode":"33150",
    "sg:province":"Asturias",
    "wof:name":"Ovia\u00f1o Fernandez Manuel Adolfo",
    "wof:placetype":"venue"
},
  "geometry": {"coordinates":[-6.1495938301,43.5591011047],"type":"Point"}
}