{
  "type": "Feature",
  "properties": {
    "iso:country":"ES",
    "sg:address":"Rua Doctor Batallan, 3",
    "sg:city":"Santa Lucia De Mora\u00e7a",
    "sg:orig_category":"Electrodom\u00c9sticos (al Por Menor)",
    "sg:phone":"+34 986 55 20 80",
    "sg:postcode":"36660",
    "sg:province":"Pontevedra",
    "wof:name":"Electronica Rivas Mora\u00f1a S.l.",
    "wof:placetype":"venue"
},
  "geometry": {"coordinates":[-8.5895185471,42.5900993347],"type":"Point"}
}