{
  "type": "Feature",
  "properties": {
    "iso:country":"ES",
    "sg:address":"Calle de Santa Ana, 4",
    "sg:city":"Arroyo Luz",
    "sg:orig_category":"Supermercados Y Hipermercados",
    "sg:phone":"+34 927 27 01 68",
    "sg:postcode":"10900",
    "sg:province":"C\u00e1ceres",
    "wof:name":"Madalu S. A.",
    "wof:placetype":"venue"
},
  "geometry": {"coordinates":[-6.5839018822,39.4847373962],"type":"Point"}
}