{
  "type": "Feature",
  "properties": {
    "addr:full":"Rua Victoria, 16 Carballo La Coru\u00f1a 15100",
    "addr:housenumber":"16",
    "addr:postcode":"15100",
    "addr:street":"Rua Victoria;La Corun\u0303A",
    "iso:country":"ES",
    "sg:address":"Rua Victoria, 16",
    "sg:city":"Carballo",
    "sg:orig_category":"Comercio, Reparaci\u00d3n De Bicicletas, De Motocicletas, De Accesorios",
    "sg:phone":"+34 981 70 06 13",
    "sg:postcode":"15100",
    "sg:province":"La Coru\u00f1a",
    "wof:name":"Cervi\u00f1o Sanchez Maria Victoria",
    "wof:placetype":"venue"
},
  "geometry": {"coordinates":[-8.6912689209,43.2124137878],"type":"Point"}
}