{
  "type": "Feature",
  "properties": {
    "iso:country":"ES",
    "sg:address":"Calle de Zurita, 6",
    "sg:city":"Zaragoza",
    "sg:orig_category":"Contenedores (mercanc\u00cdas)",
    "sg:phone":"+34 976 21 11 41",
    "sg:postcode":"50001",
    "sg:province":"Zaragoza",
    "wof:name":"Parra Barbod Cristina",
    "wof:placetype":"venue"
},
  "geometry": {"coordinates":[-0.8820080161,41.6502037048],"type":"Point"}
}