{
  "type": "Feature",
  "properties": {
    "addr:full":"Avgd Antonio Almela, 5 Alcudia Valencia 46250",
    "addr:housenumber":"5",
    "addr:postcode":"46250",
    "addr:street":"Almela",
    "iso:country":"ES",
    "sg:address":"Avgd Antonio Almela, 5",
    "sg:city":"Alcudia",
    "sg:orig_category":"Supermercados Y Hipermercados",
    "sg:phone":"+34 962 99 71 87",
    "sg:postcode":"46250",
    "sg:province":"Valencia",
    "sg:website":"www.mercadona.es",
    "wof:name":"Mercadona S.a.",
    "wof:placetype":"venue"
},
  "geometry": {"coordinates":[-0.5042049885,39.1985054016],"type":"Point"}
}