{
  "type": "Feature",
  "properties": {
    "addr:full":"Rua Real Do Cantodarea, 6 Marin Pontevedra 36900",
    "addr:housenumber":"6",
    "addr:postcode":"36900",
    "addr:street":"Rua Real Do Cantodarea",
    "iso:country":"ES",
    "sg:address":"Rua Real Do Cantodarea, 6",
    "sg:city":"Marin",
    "sg:orig_category":"Caf\u00c9s, Bares, Cervecer\u00cdas",
    "sg:phone":"+34 986 88 01 45",
    "sg:postcode":"36900",
    "sg:province":"Pontevedra",
    "wof:name":"Rodriguez Garcia Paz",
    "wof:placetype":"venue"
},
  "geometry": {"coordinates":[-8.6922836304,42.3962898254],"type":"Point"}
}