{
  "type": "Feature",
  "properties": {
    "iso:country":"ES",
    "sg:address":"C/ Rutlla, 7",
    "sg:city":"Calonge",
    "sg:orig_category":"Electrodom\u00c9sticos (al Por Menor)",
    "sg:phone":"+34 972 65 00 94",
    "sg:postcode":"17251",
    "sg:province":"Girona",
    "wof:name":"Radio Pepe S. A.",
    "wof:placetype":"venue"
},
  "geometry": {"coordinates":[3.0746610165,41.8615951538],"type":"Point"}
}