{
  "type": "Feature",
  "properties": {
    "addr:full":"Calle de Loizaga Kalea, 3 Gernika-lumo Vizcaya 48300",
    "addr:housenumber":"3",
    "addr:postcode":"48300",
    "addr:street":"Calle De Loizaga Kalea",
    "iso:country":"ES",
    "sg:address":"Calle de Loizaga Kalea, 3",
    "sg:city":"Gernika-lumo",
    "sg:orig_category":"Peluqueros: De Se\u00d1oras",
    "sg:phone":"+34 946 25 79 35",
    "sg:postcode":"48300",
    "sg:province":"Vizcaya",
    "wof:name":"Itziar Goiria Mendiolea",
    "wof:placetype":"venue"
},
  "geometry": {"coordinates":[-2.6830849648,43.3131904602],"type":"Point"}
}