{
  "type": "Feature",
  "properties": {
    "iso:country":"ES",
    "sg:address":"Ctra. Valdepe\u00f1as, Km. 0215,0",
    "sg:city":"Sta. Cruz Mudela",
    "sg:orig_category":"Fabricaci\u00d3n De Ventanas",
    "sg:phone":"+34 926 34 22 31",
    "sg:postcode":"13730",
    "sg:province":"Ciudad Real",
    "sg:website":"www.molinahuertas.com",
    "wof:name":"Molina Huertas S.l",
    "wof:placetype":"venue"
},
  "geometry": {"coordinates":[-3.465243578,38.6478881836],"type":"Point"}
}