{
  "type": "Feature",
  "properties": {
    "iso:country":"ES",
    "sg:address":"Calle de Ibarra, 17",
    "sg:city":"San Vicente De Barakaldo",
    "sg:orig_category":"Ropa Para Ni\u00d1os (al Por Menor)",
    "sg:phone":"+34 944 37 46 31",
    "sg:postcode":"48901",
    "sg:province":"Vizcaya",
    "wof:name":"Galvan Garcia Maria Jose",
    "wof:placetype":"venue"
},
  "geometry": {"coordinates":[-2.9846570492,43.2991523743],"type":"Point"}
}