{
  "type": "Feature",
  "properties": {
    "addr:full":"Avda Valencia, 85 Casinos Valencia 46171",
    "addr:housenumber":"85",
    "addr:postcode":"46171",
    "addr:street":"Avda Valencia",
    "iso:country":"ES",
    "sg:address":"Avda Valencia, 85",
    "sg:city":"Casinos",
    "sg:orig_category":"Conservas De Legumbres (fabricaci\u00d3n, Al Por Mayor)",
    "sg:phone":"+34 961 64 72 00",
    "sg:postcode":"46171",
    "sg:province":"Valencia",
    "wof:name":"Ni\u00f1erola Martinez Jose",
    "wof:placetype":"venue"
},
  "geometry": {"coordinates":[-0.7076990008,39.6965408325],"type":"Point"}
}