{
  "type": "Feature",
  "properties": {
    "addr:full":"Plaz Costa Del Sol, S/n Torremolinos M\u00e1laga 29620",
    "addr:housenumber":"/ n",
    "addr:postcode":"29620",
    "addr:street":"Plaz Costa Del Sol S;Ma\u0301Laga",
    "iso:country":"ES",
    "sg:address":"Plaz Costa Del Sol, S/n",
    "sg:city":"Torremolinos",
    "sg:orig_category":"Agencias De Viajes",
    "sg:phone":"+34 952 37 52 52",
    "sg:postcode":"29620",
    "sg:province":"M\u00e1laga",
    "wof:name":"Occidentaltour S.a.",
    "wof:placetype":"venue"
},
  "geometry": {"coordinates":[-4.49954319,36.6249160767],"type":"Point"}
}