{
  "type": "Feature",
  "properties": {
    "iso:country":"ES",
    "sg:address":"Calle de Embajadores, 157",
    "sg:city":"Madrid",
    "sg:orig_category":"Decoraci\u00d3n: Instalaci\u00d3n Y Talleres",
    "sg:phone":"+34 914 73 22 78",
    "sg:postcode":"28045",
    "sg:province":"Madrid",
    "wof:name":"Garzon Mendez Cesareo",
    "wof:placetype":"venue"
},
  "geometry": {"coordinates":[-3.6956248283,40.3956794739],"type":"Point"}
}