{
  "type": "Feature",
  "properties": {
    "addr:full":"Ctra. Gibraleon-cartaya, S/n Gibraleon Huelva 21500",
    "addr:housenumber":"s / n",
    "addr:postcode":"21500",
    "addr:street":"Ctra. Gibraleon-Cartaya",
    "iso:country":"ES",
    "sg:address":"Ctra. Gibraleon-cartaya, S/n",
    "sg:city":"Gibraleon",
    "sg:orig_category":"Hormig\u00d3n Listo Para Usar",
    "sg:phone":"+34 959 50 90 57",
    "sg:postcode":"21500",
    "sg:province":"Huelva",
    "wof:name":"Hormigones Odiel S.a.",
    "wof:placetype":"venue"
},
  "geometry": {"coordinates":[-6.9744291306,37.3773460388],"type":"Point"}
}