{
  "type": "Feature",
  "properties": {
    "iso:country":"ES",
    "sg:address":"Calle de Maldonado, 8",
    "sg:city":"Valladolid",
    "sg:orig_category":"Guarder\u00cdas",
    "sg:phone":"+34 983 39 83 56",
    "sg:postcode":"47002",
    "sg:province":"Valladolid",
    "wof:name":"Hormia Gavilan Consuelo",
    "wof:placetype":"venue"
},
  "geometry": {"coordinates":[-4.7183117867,41.6504669189],"type":"Point"}
}