{
  "type": "Feature",
  "properties": {
    "addr:full":"Los Angeles, 7 Puerto Santiago Santa Cruz De Tenerife 38683",
    "addr:housenumber":"7",
    "addr:postcode":"38683",
    "addr:street":"Los Angeles",
    "iso:country":"ES",
    "sg:address":"Los Angeles, 7",
    "sg:city":"Puerto Santiago",
    "sg:orig_category":"Electricidad: Instaladores",
    "sg:phone":"+34 922 86 24 40",
    "sg:postcode":"38683",
    "sg:province":"Santa Cruz De Tenerife",
    "wof:name":"Socas Jimenez Miguel Angel",
    "wof:placetype":"venue"
},
  "geometry": {"coordinates":[-16.8407382965,28.2389469147],"type":"Point"}
}