{
  "type": "Feature",
  "properties": {
    "iso:country":"ES",
    "sg:address":"Carrer de Huelva, 59",
    "sg:city":"Barcelona",
    "sg:orig_category":"Alimentaci\u00d3n General (al Por Menor)",
    "sg:phone":"+34 933 03 39 02",
    "sg:postcode":"08020",
    "sg:province":"Barcelona",
    "wof:name":"Hinarejos Montano Enrique",
    "wof:placetype":"venue"
},
  "geometry": {"coordinates":[2.1958889961,41.4173698425],"type":"Point"}
}