{
  "type": "Feature",
  "properties": {
    "iso:country":"ES",
    "sg:address":"Carrer de Camp Arriassa, 92",
    "sg:city":"Barcelona",
    "sg:orig_category":"Peluqueros: De Se\u00d1oras",
    "sg:phone":"+34 933 13 08 96",
    "sg:postcode":"08020",
    "sg:province":"Barcelona",
    "wof:name":"Gavalda Del Rio Pilar",
    "wof:placetype":"venue"
},
  "geometry": {"coordinates":[2.2025380135,41.4250221252],"type":"Point"}
}