{
  "type": "Feature",
  "properties": {
    "addr:full":"Calle de Silva, 1 Cedeira La Coru\u00f1a 15350",
    "addr:housenumber":"1",
    "addr:postcode":"15350",
    "addr:street":"Calle De Silva;La Corun\u0303A",
    "iso:country":"ES",
    "sg:address":"Calle de Silva, 1",
    "sg:city":"Cedeira",
    "sg:orig_category":"Molduras, Junquillos, Listones Y Molduras Perforadas",
    "sg:phone":"+34 981 48 03 28",
    "sg:postcode":"15350",
    "sg:province":"La Coru\u00f1a",
    "wof:name":"Guergue Perez Josefa",
    "wof:placetype":"venue"
},
  "geometry": {"coordinates":[-8.0522060394,43.6624412537],"type":"Point"}
}