{
  "type": "Feature",
  "properties": {
    "addr:full":"Calle de Ermita, 4 Burlada Navarra 31600",
    "addr:housenumber":"4",
    "addr:postcode":"31600",
    "addr:street":"Calle De Ermita",
    "iso:country":"ES",
    "sg:address":"Calle de Ermita, 4",
    "sg:city":"Burlada",
    "sg:orig_category":"Chapister\u00cda",
    "sg:phone":"+34 948 23 82 95",
    "sg:postcode":"31600",
    "sg:province":"Navarra",
    "wof:name":"Garriz Elizagaray Jesus Y Murillo Martinez Rafael",
    "wof:placetype":"venue"
},
  "geometry": {"coordinates":[-1.6136356592,42.825378418],"type":"Point"}
}