{
  "type": "Feature",
  "properties": {
    "iso:country":"ES",
    "sg:address":"Par. Torradors, 4",
    "sg:city":"Pals",
    "sg:orig_category":"Confecci\u00d3n (fabricaci\u00d3n, Al Por Mayor)",
    "sg:phone":"+34 972 19 60 42",
    "sg:postcode":"17256",
    "sg:province":"Girona",
    "wof:name":"Onspanje S.l.",
    "wof:placetype":"venue"
},
  "geometry": {"coordinates":[3.1482629776,41.9678573608],"type":"Point"}
}