{
  "type": "Feature",
  "properties": {
    "addr:full":"Carrer de Josep Antoni Barraquer, 4 Urbanizacion Els Saulons-finca Ribo Barcelona 08140",
    "addr:housenumber":"4",
    "addr:postcode":"08140",
    "addr:street":"Carrer De Josep Antoni Barraquer",
    "iso:country":"ES",
    "sg:address":"Carrer de Josep Antoni Barraquer, 4",
    "sg:city":"Urbanizacion Els Saulons-finca Ribo",
    "sg:orig_category":"Radiocomunicaciones, Telefon\u00cda M\u00d3vil, Radiomensajer\u00cda: Servicios, Comercializaci\u00d3n",
    "sg:phone":"+34 938 66 75 73",
    "sg:postcode":"08140",
    "sg:province":"Barcelona",
    "wof:name":"Josep Maria Sole I Gemma Garriga S.c.p.",
    "wof:placetype":"venue"
},
  "geometry": {"coordinates":[2.1581070423,41.6491889954],"type":"Point"}
}