{
  "type": "Feature",
  "properties": {
    "iso:country":"ES",
    "sg:address":"Calle de Antonio Acu\u00d1a, 21",
    "sg:city":"Madrid",
    "sg:orig_category":"Aparcamientos (infraestructuras, Accesorios)",
    "sg:phone":"+34 915 76 06 38",
    "sg:postcode":"28009",
    "sg:province":"Madrid",
    "wof:name":"Garaje Matilla C.b.",
    "wof:placetype":"venue"
},
  "geometry": {"coordinates":[-3.6789021492,40.4219932556],"type":"Point"}
}