{
  "type": "Feature",
  "properties": {
    "addr:full":"Calle de Cincho, 16 Santovenia Pisuerga Valladolid 47155",
    "addr:housenumber":"16",
    "addr:postcode":"47155",
    "addr:street":"Calle De Cincho",
    "iso:country":"ES",
    "sg:address":"Calle de Cincho, 16",
    "sg:city":"Santovenia Pisuerga",
    "sg:orig_category":"Empresas De Carpinter\u00cda",
    "sg:phone":"+34 983 40 07 12",
    "sg:postcode":"47155",
    "sg:province":"Valladolid",
    "wof:name":"Gutierrez Moncada Gerardo",
    "wof:placetype":"venue"
},
  "geometry": {"coordinates":[-4.6714420319,41.688369751],"type":"Point"}
}