{
  "type": "Feature",
  "properties": {
    "iso:country":"ES",
    "sg:address":"Calle de Miraflores, 13",
    "sg:city":"Zaragoza",
    "sg:orig_category":"Peluqueros: De Se\u00d1oras",
    "sg:phone":"+34 976 59 70 38",
    "sg:postcode":"50008",
    "sg:province":"Zaragoza",
    "wof:name":"Segovia Aguila Jose Maria",
    "wof:placetype":"venue"
},
  "geometry": {"coordinates":[-0.8745059967,41.644153595],"type":"Point"}
}