{
  "type": "Feature",
  "properties": {
    "addr:full":"Parque San Jose, S/n Costa Del Silencio Santa Cruz De Tenerife 38630",
    "addr:housenumber":"s / n",
    "addr:postcode":"38630",
    "iso:country":"ES",
    "sg:address":"Parque San Jose, S/n",
    "sg:city":"Costa Del Silencio",
    "sg:orig_category":"Alquiler De Veh\u00cdculos: Turismos Y Utilitarios",
    "sg:phone":"+34 922 73 03 53",
    "sg:postcode":"38630",
    "sg:province":"Santa Cruz De Tenerife",
    "wof:name":"Luis Mica Rodriguez S.l.",
    "wof:placetype":"venue"
},
  "geometry": {"coordinates":[-16.6443786621,28.008354187],"type":"Point"}
}