{
  "type": "Feature",
  "properties": {
    "addr:full":"Calle de Gaztelu, 23 Donostia-san Sebastian Guip\u00f9zcoa 20013",
    "addr:housenumber":"23",
    "addr:postcode":"20013",
    "addr:street":"Calle De Gaztelu",
    "iso:country":"ES",
    "sg:address":"Calle de Gaztelu, 23",
    "sg:city":"Donostia-san Sebastian",
    "sg:orig_category":"Alquiler De V\u00cddeo",
    "sg:phone":"+34 943 27 88 53",
    "sg:postcode":"20013",
    "sg:province":"Guip\u00f9zcoa",
    "wof:name":"Rico Del Amo Jose Miguel",
    "wof:placetype":"venue"
},
  "geometry": {"coordinates":[-1.9555042982,43.3185844421],"type":"Point"}
}