{
  "type": "Feature",
  "properties": {
    "addr:full":"Ctra Madrid, Km. 0311,0 Zaragoza Zaragoza 50...",
    "addr:housenumber":"50 ...",
    "addr:street":"Ctra Madrid Km. 0311,0;Zaragoza",
    "iso:country":"ES",
    "sg:address":"Ctra Madrid, Km. 0311,0",
    "sg:city":"Zaragoza",
    "sg:orig_category":"Comit\u00c9s De Organizaci\u00d3n De Exposiciones, Ferias, Salones",
    "sg:phone":"+34 976 76 47 00",
    "sg:postcode":"50...",
    "sg:province":"Zaragoza",
    "sg:website":"www.feriazaragoza.com",
    "wof:name":"Feria De Zaragoza",
    "wof:placetype":"venue"
},
  "geometry": {"coordinates":[-0.8813189864,41.6517295837],"type":"Point"}
}