{
  "type": "Feature",
  "properties": {
    "iso:country":"ES",
    "sg:address":"Calle de Valderribas, 24",
    "sg:city":"Madrid",
    "sg:orig_category":"Florister\u00cdas",
    "sg:phone":"+34 915 51 68 27",
    "sg:postcode":"28007",
    "sg:province":"Madrid",
    "wof:name":"Fernandez Encinar Luis",
    "wof:placetype":"venue"
},
  "geometry": {"coordinates":[-3.6766281128,40.4048156738],"type":"Point"}
}