{
  "type": "Feature",
  "properties": {
    "addr:full":"Carr Alberes Comercial, 43 Empuriabrava Girona 17487",
    "addr:housenumber":"43",
    "addr:postcode":"17487",
    "addr:street":"Carr Alberes Comercial",
    "iso:country":"ES",
    "sg:address":"Carr Alberes Comercial, 43",
    "sg:city":"Empuriabrava",
    "sg:orig_category":"Quincaller\u00cda (al Por Menor)",
    "sg:phone":"+34 972 45 05 95",
    "sg:postcode":"17487",
    "sg:province":"Girona",
    "wof:name":"Seppels Schlemmerladen, S.l.",
    "wof:placetype":"venue"
},
  "geometry": {"coordinates":[3.1107430458,42.2461395264],"type":"Point"}
}