{
  "type": "Feature",
  "properties": {
    "iso:country":"ES",
    "sg:address":"Calle de Nueva Del Rosario, 9",
    "sg:city":"Pulianas",
    "sg:orig_category":"Chapister\u00cda",
    "sg:phone":"+34 958 42 63 95",
    "sg:postcode":"18197",
    "sg:province":"Granada",
    "wof:name":"Lopez Fernandez Francisco",
    "wof:placetype":"venue"
},
  "geometry": {"coordinates":[-3.6060650349,37.2214012146],"type":"Point"}
}