{
  "type": "Feature",
  "properties": {
    "iso:country":"ES",
    "sg:address":"Calle de Jose Cueto, 3",
    "sg:city":"Aviles",
    "sg:orig_category":"Asociaciones Humanitarias, De Cooperaci\u00d3n, De Acci\u00d3n Social",
    "sg:phone":"+34 985 52 04 72",
    "sg:postcode":"33401",
    "sg:province":"Asturias",
    "wof:name":"Asociacion Espa\u00f1ola Contra El Cancer",
    "wof:placetype":"venue"
},
  "geometry": {"coordinates":[-5.9252352715,43.5580596924],"type":"Point"}
}