{
  "type": "Feature",
  "properties": {
    "addr:full":"Calle de Sierra Espu\u00d1a, 12 Urbanizacion Nueva Cartagena Murcia 30310",
    "addr:housenumber":"12",
    "addr:postcode":"30310",
    "addr:street":"Calle De Sierra Espun\u0303A",
    "iso:country":"ES",
    "sg:address":"Calle de Sierra Espu\u00d1a, 12",
    "sg:city":"Urbanizacion Nueva Cartagena",
    "sg:orig_category":"Arreglo, Reparaci\u00d3n, Piezas Sueltas De Televisi\u00d3n, V\u00cddeo, Hi",
    "sg:phone":"+34 968 31 26 96",
    "sg:postcode":"30310",
    "sg:province":"Murcia",
    "wof:name":"Garcia Navarro Asensio",
    "wof:placetype":"venue"
},
  "geometry": {"coordinates":[-1.0048370361,37.6200256348],"type":"Point"}
}