{
  "type": "Feature",
  "properties": {
    "addr:full":"Avda. De Santander-berron, 12 La Carrera Asturias 33186",
    "addr:housenumber":"12",
    "addr:postcode":"33186",
    "addr:street":"Avda. De Santander-Berron",
    "iso:country":"ES",
    "sg:address":"Avda. De Santander-berron, 12",
    "sg:city":"La Carrera",
    "sg:orig_category":"Serrer\u00cdas De Madera",
    "sg:phone":"+34 985 74 03 71",
    "sg:postcode":"33186",
    "sg:province":"Asturias",
    "wof:name":"Maderas Adolfo Lopez S.l.",
    "wof:placetype":"venue"
},
  "geometry": {"coordinates":[-5.9832577705,43.2504386902],"type":"Point"}
}