{
  "type": "Feature",
  "properties": {
    "addr:full":"Calle de Palencia, 48 Navalcarnero Madrid 28600",
    "addr:housenumber":"48",
    "addr:postcode":"28600",
    "addr:street":"Calle De Palencia",
    "iso:country":"ES",
    "sg:address":"Calle de Palencia, 48",
    "sg:city":"Navalcarnero",
    "sg:orig_category":"Mec\u00c1nico Del Autom\u00d3vil",
    "sg:phone":"+34 918 11 08 37",
    "sg:postcode":"28600",
    "sg:province":"Madrid",
    "wof:name":"Gonzalez Britos Bernardino",
    "wof:placetype":"venue"
},
  "geometry": {"coordinates":[-4.0093398094,40.2913703918],"type":"Point"}
}