{
  "type": "Feature",
  "properties": {
    "iso:country":"ES",
    "sg:address":"Calle de Viana, 15",
    "sg:city":"San Cristobal De La Laguna",
    "sg:orig_category":"Ropa Para Se\u00d1oras Y Caballeros (al Por Menor)",
    "sg:phone":"+34 922 26 61 95",
    "sg:postcode":"38204",
    "sg:province":"Santa Cruz De Tenerife",
    "wof:name":"Maceda Hernandez Maria Del Cristo",
    "wof:placetype":"venue"
},
  "geometry": {"coordinates":[-16.3148155212,28.4880695343],"type":"Point"}
}