{
  "type": "Feature",
  "properties": {
    "addr:full":"Calle de Soledad, 1 Benavente Zamora 49600",
    "addr:housenumber":"1",
    "addr:postcode":"49600",
    "addr:street":"Calle De Soledad",
    "iso:country":"ES",
    "sg:address":"Calle de Soledad, 1",
    "sg:city":"Benavente",
    "sg:orig_category":"Inmobiliaria (agencias)",
    "sg:phone":"+34 980 63 32 76",
    "sg:postcode":"49600",
    "sg:province":"Zamora",
    "wof:name":"Don Piso Don Chalet S.l.",
    "wof:placetype":"venue"
},
  "geometry": {"coordinates":[-5.6736540794,42.0032310486],"type":"Point"}
}