{
  "type": "Feature",
  "properties": {
    "iso:country":"ES",
    "sg:address":"Ctra Villamarchante, 31",
    "sg:city":"Riba-roja Turia",
    "sg:orig_category":"Asociaciones Y Clubs Deportivos",
    "sg:phone":"+34 962 77 05 41",
    "sg:postcode":"46190",
    "sg:province":"Valencia",
    "wof:name":"Montaner Verdeguer Francisco",
    "wof:placetype":"venue"
},
  "geometry": {"coordinates":[-0.5716459751,39.5446052551],"type":"Point"}
}