{
  "type": "Feature",
  "properties": {
    "addr:full":"Av Carrilet, 125 Hospitalet Llobregat Barcelona 08902",
    "addr:housenumber":"125",
    "addr:postcode":"08902",
    "addr:street":"Av Carrilet",
    "iso:country":"ES",
    "sg:address":"Av Carrilet, 125",
    "sg:city":"Hospitalet Llobregat",
    "sg:orig_category":"Centros Empresariales",
    "sg:phone":"+34 932 98 89 30",
    "sg:postcode":"08902",
    "sg:province":"Barcelona",
    "wof:name":"Denbolan Ett S.a.",
    "wof:placetype":"venue"
},
  "geometry": {"coordinates":[2.1216669083,41.3647041321],"type":"Point"}
}