{
  "type": "Feature",
  "properties": {
    "addr:full":"Calle de Lima (de), 69 Fuenlabrada Madrid 28945",
    "addr:housenumber":"69",
    "addr:postcode":"28945",
    "addr:street":"Calle De Lima De",
    "iso:country":"ES",
    "sg:address":"Calle de Lima (de), 69",
    "sg:city":"Fuenlabrada",
    "sg:orig_category":"Sociedades, Compa\u00d1\u00cdas Aseguradoras",
    "sg:phone":"+34 914 92 00 54",
    "sg:postcode":"28945",
    "sg:province":"Madrid",
    "wof:name":"Martin Perez Maria Angela",
    "wof:placetype":"venue"
},
  "geometry": {"coordinates":[-3.7868878841,40.2946777344],"type":"Point"}
}