{
  "type": "Feature",
  "properties": {
    "iso:country":"ES",
    "sg:address":"Calle de Fuente Del Casta\u00d1o, 22",
    "sg:city":"Bormujos",
    "sg:orig_category":"Edici\u00d3n De Diarios, Revistas, Boletines",
    "sg:phone":"+34 954 78 80 22",
    "sg:postcode":"41930",
    "sg:province":"Sevilla",
    "wof:name":"Circulo Ateneo De Ediciones Ypromociones",
    "wof:placetype":"venue"
},
  "geometry": {"coordinates":[-6.0640392303,37.3776092529],"type":"Point"}
}