{
  "type": "Feature",
  "properties": {
    "addr:full":"Quebrantos-la Arena, 1 Ranon Asturias 33125",
    "addr:housenumber":"1",
    "addr:postcode":"33125",
    "addr:street":"Ranon Asturias",
    "iso:country":"ES",
    "sg:address":"Quebrantos-la Arena, 1",
    "sg:city":"Ranon",
    "sg:orig_category":"Cajas De Ahorro",
    "sg:phone":"+34 985 58 60 32",
    "sg:postcode":"33125",
    "sg:province":"Asturias",
    "wof:name":"Cajastur",
    "wof:placetype":"venue"
},
  "geometry": {"coordinates":[-6.0765638351,43.557674408],"type":"Point"}
}