{
  "type": "Feature",
  "properties": {
    "iso:country":"ES",
    "sg:address":"Calle de Coso, 55",
    "sg:city":"Zaragoza",
    "sg:orig_category":"\u00d3ptica: Instrumentos (fabricaci\u00d3n)",
    "sg:phone":"+34 976 29 84 33",
    "sg:postcode":"50001",
    "sg:province":"Zaragoza",
    "sg:website":"www.visionlab.es",
    "wof:name":"Visionlab S.a.",
    "wof:placetype":"venue"
},
  "geometry": {"coordinates":[-0.8794819713,41.6518516541],"type":"Point"}
}