{
  "type": "Feature",
  "properties": {
    "iso:country":"ES",
    "sg:address":"Calle de Babel, 2",
    "sg:city":"Malaga",
    "sg:orig_category":"Fabricaci\u00d3n De Material Y Sistemas De Se\u00d1alizaci\u00d3n De Carreteras, Urbanos Y De Obras",
    "sg:phone":"+34 952 33 24 67",
    "sg:postcode":"29006",
    "sg:province":"M\u00e1laga",
    "wof:name":"Martin Jimenez Diego",
    "wof:placetype":"venue"
},
  "geometry": {"coordinates":[-4.4365329742,36.7153816223],"type":"Point"}
}