{
  "type": "Feature",
  "properties": {
    "iso:country":"ES",
    "sg:address":"Avda Campon El, 31",
    "sg:city":"Salinas",
    "sg:orig_category":"Serigraf\u00cda (material Y Suministros)",
    "sg:phone":"+34 985 51 89 19",
    "sg:postcode":"33405",
    "sg:province":"Asturias",
    "sg:website":"www.marganlmi.com",
    "wof:name":"Margen C.b.",
    "wof:placetype":"venue"
},
  "geometry": {"coordinates":[-5.9549570084,43.5722923279],"type":"Point"}
}