{
  "type": "Feature",
  "properties": {
    "iso:country":"ES",
    "sg:address":"Calle de Musico Peydro, 3",
    "sg:city":"Valencia",
    "sg:orig_category":"Zapatos (al Por Menor)",
    "sg:phone":"+34 963 94 08 43",
    "sg:postcode":"46001",
    "sg:province":"Valencia",
    "wof:name":"Boluda Moreno Oscar Luis",
    "wof:placetype":"venue"
},
  "geometry": {"coordinates":[-0.3779309988,39.4724311829],"type":"Point"}
}