{
  "type": "Feature",
  "properties": {
    "iso:country":"ES",
    "sg:address":"Rua Manuel Lemos, 108",
    "sg:city":"Ramallosa",
    "sg:orig_category":"Negocio De Madera",
    "sg:phone":"+34 986 35 34 40",
    "sg:postcode":"36379",
    "sg:province":"Pontevedra",
    "wof:name":"Maderas Cadaval S. L.",
    "wof:placetype":"venue"
},
  "geometry": {"coordinates":[-8.8125343323,42.1196670532],"type":"Point"}
}