{
  "type": "Feature",
  "properties": {
    "iso:country":"ES",
    "sg:address":"Calle de Parque Eugenia De Montijo, 4",
    "sg:city":"Madrid",
    "sg:orig_category":"Plomeros",
    "sg:phone":"+34 914 66 18 36",
    "sg:postcode":"28047",
    "sg:province":"Madrid",
    "wof:name":"Instalaciones Riesco P4 S.l.",
    "wof:placetype":"venue"
},
  "geometry": {"coordinates":[-3.7548000813,40.3779754639],"type":"Point"}
}