{
  "type": "Feature",
  "properties": {
    "addr:full":"C/ Valencia, 5 Alcoi Alicante 03804",
    "addr:housenumber":"5",
    "addr:postcode":"03804",
    "addr:street":"C / Valencia",
    "iso:country":"ES",
    "sg:address":"C/ Valencia, 5",
    "sg:city":"Alcoi",
    "sg:orig_category":"Agentes Generales De Seguros",
    "sg:phone":"+34 965 33 60 22",
    "sg:postcode":"03804",
    "sg:province":"Alicante",
    "wof:name":"Verdu Esparza Fernando",
    "wof:placetype":"venue"
},
  "geometry": {"coordinates":[-0.4671010077,38.7110671997],"type":"Point"}
}