{
  "type": "Feature",
  "properties": {
    "addr:full":"Villa, S/n Villa Asturias 33529",
    "addr:housenumber":"/ n",
    "addr:postcode":"33529",
    "addr:street":"S;Asturias",
    "iso:country":"ES",
    "sg:address":"Villa, S/n",
    "sg:city":"Villa",
    "sg:orig_category":"Charcuter\u00cdas (al Por Mayor)",
    "sg:phone":"+34 985 71 60 55",
    "sg:postcode":"33529",
    "sg:province":"Asturias",
    "wof:name":"Martinez Garcia Francisco",
    "wof:placetype":"venue"
},
  "geometry": {"coordinates":[-5.4692487717,43.408908844],"type":"Point"}
}