{
  "type": "Feature",
  "properties": {
    "addr:full":"Calle de Real, 65 Almeria Almer\u00eda 04001",
    "addr:housenumber":"65",
    "addr:postcode":"04001",
    "addr:street":"Calle De Real",
    "iso:country":"ES",
    "sg:address":"Calle de Real, 65",
    "sg:city":"Almeria",
    "sg:orig_category":"Bisuter\u00cda, Joyer\u00cda, Relojer\u00cda (al Por Menor)",
    "sg:phone":"+34 950 26 06 31",
    "sg:postcode":"04001",
    "sg:province":"Almer\u00eda",
    "wof:name":"Valls Lopez Manuel",
    "wof:placetype":"venue"
},
  "geometry": {"coordinates":[-2.465569973,36.8378868103],"type":"Point"}
}