{
  "type": "Feature",
  "properties": {
    "iso:country":"ES",
    "sg:address":"Es Migjorn Gran, S/n",
    "sg:city":"Ferreries",
    "sg:orig_category":"Ense\u00d1anza, Formaci\u00d3n Profesional: Aprendizaje",
    "sg:phone":"+34 971 37 45 05",
    "sg:postcode":"07750",
    "sg:province":"Islas Baleares",
    "wof:name":"Ajuntament De Ferreries",
    "wof:placetype":"venue"
},
  "geometry": {"coordinates":[3.9980485439,39.9843063354],"type":"Point"}
}