{
  "type": "Feature",
  "properties": {
    "iso:country":"ES",
    "sg:address":"Carrer de Sant Pau, 1",
    "sg:city":"Barcelona",
    "sg:orig_category":"Teatros Y Salas De Espect\u00c1culos",
    "sg:phone":"+34 934 12 43 51",
    "sg:postcode":"08001",
    "sg:province":"Barcelona",
    "wof:name":"Sociedad Del Gran Teatro Del Liceo",
    "wof:placetype":"venue"
},
  "geometry": {"coordinates":[2.1732840538,41.3809432983],"type":"Point"}
}