{
  "type": "Feature",
  "properties": {
    "addr:full":"Calle de San Miguel, 13 Moguer Huelva 21800",
    "addr:housenumber":"13",
    "addr:postcode":"21800",
    "addr:street":"Calle De San Miguel",
    "iso:country":"ES",
    "sg:address":"Calle de San Miguel, 13",
    "sg:city":"Moguer",
    "sg:orig_category":"Ropa Y Accesorios",
    "sg:phone":"+34 959 37 24 07",
    "sg:postcode":"21800",
    "sg:province":"Huelva",
    "wof:name":"Rodriguez Barrio Brigida",
    "wof:placetype":"venue"
},
  "geometry": {"coordinates":[-6.8397321701,37.277256012],"type":"Point"}
}