{
  "type": "Feature",
  "properties": {
    "iso:country":"ES",
    "sg:address":"Calle de Castellana, 8",
    "sg:city":"Vadillo De La Guare\u00e7a",
    "sg:orig_category":"Producci\u00d3n, Venta De Productos De Agricultura Biol\u00d3gica",
    "sg:phone":"+34 980 60 70 12",
    "sg:postcode":"49420",
    "sg:province":"Zamora",
    "wof:name":"Herloal Sociedad Cooperativa",
    "wof:placetype":"venue"
},
  "geometry": {"coordinates":[-5.3565764427,41.2819786072],"type":"Point"}
}