{
  "type": "Feature",
  "properties": {
    "iso:country":"ES",
    "sg:address":"Pase Toyo (del), S/n",
    "sg:city":"Retamar",
    "sg:orig_category":"Promotores Constructores",
    "sg:phone":"+34 950 20 73 65",
    "sg:postcode":"04130",
    "sg:province":"Almer\u00eda",
    "sg:website":"www.fadesa.es",
    "wof:name":"Fadesa Inmobiliaria S.a.",
    "wof:placetype":"venue"
},
  "geometry": {"coordinates":[-2.3529150486,36.8523406982],"type":"Point"}
}