{
  "type": "Feature",
  "properties": {
    "iso:country":"ES",
    "sg:address":"Calle de Morenos, 8",
    "sg:city":"Jerez De La Frontera",
    "sg:orig_category":"Promotores Constructores",
    "sg:phone":"+34 956 16 85 34",
    "sg:postcode":"11402",
    "sg:province":"C\u00e1diz",
    "wof:name":"Cobos Y Roman S.l.",
    "wof:placetype":"venue"
},
  "geometry": {"coordinates":[-6.1340289116,36.6847190857],"type":"Point"}
}