{
  "type": "Feature",
  "properties": {
    "iso:country":"ES",
    "sg:address":"C/ Major, 26",
    "sg:city":"Salt",
    "sg:orig_category":"Alimentaci\u00d3n General (al Por Menor)",
    "sg:phone":"+34 972 23 89 80",
    "sg:postcode":"17190",
    "sg:province":"Girona",
    "wof:name":"Puigdevall Terrats Isidro",
    "wof:placetype":"venue"
},
  "geometry": {"coordinates":[2.794490099,41.9755401611],"type":"Point"}
}