{
  "type": "Feature",
  "properties": {
    "iso:country":"ES",
    "sg:address":"Calle de Alameda Del Rio, 25",
    "sg:city":"Chiclana De La Frontera",
    "sg:orig_category":"Agencias Y Asesores De Publicidad",
    "sg:phone":"+34 956 53 67 92",
    "sg:postcode":"11130",
    "sg:province":"C\u00e1diz",
    "sg:website":"www.plusmedia.es",
    "wof:name":"Plusmedia Comunicacion Visual S.l.",
    "wof:placetype":"venue"
},
  "geometry": {"coordinates":[-6.1479110718,36.42137146],"type":"Point"}
}