{
  "type": "Feature",
  "properties": {
    "addr:full":"Calle de Marques De Benavites, 2 Avila \u00c1vila 05001",
    "addr:housenumber":"2",
    "addr:postcode":"05001",
    "addr:street":"Calle De Marques De Benavites;A\u0301Vila",
    "iso:country":"ES",
    "sg:address":"Calle de Marques De Benavites, 2",
    "sg:city":"Avila",
    "sg:orig_category":"Abogados",
    "sg:phone":"+34 920 22 32 40",
    "sg:postcode":"05001",
    "sg:province":"\u00c1vila",
    "wof:name":"Martinez Gonzalez Juan Angel",
    "wof:placetype":"venue"
},
  "geometry": {"coordinates":[-4.6997308731,40.6569786072],"type":"Point"}
}