{
  "type": "Feature",
  "properties": {
    "addr:full":"Calle de Calvo Sotelo, 41 Alar Del Rey Palencia 34480",
    "addr:housenumber":"41",
    "addr:postcode":"34480",
    "addr:street":"Calle De Calvo Sotelo",
    "iso:country":"ES",
    "sg:address":"Calle de Calvo Sotelo, 41",
    "sg:city":"Alar Del Rey",
    "sg:orig_category":"Iglesia Cat\u00d3lica",
    "sg:phone":"+34 979 13 31 03",
    "sg:postcode":"34480",
    "sg:province":"Palencia",
    "wof:name":"Parroquia De Nuestra Se\u00f1ora Del Carmen",
    "wof:placetype":"venue"
},
  "geometry": {"coordinates":[-4.310874939,42.6587486267],"type":"Point"}
}