{
  "type": "Feature",
  "properties": {
    "addr:full":"Ctra Su Eminencia, S/n Sevilla Sevilla 41006",
    "addr:housenumber":"s / n",
    "addr:postcode":"41006",
    "addr:street":"Ctra Su Eminencia",
    "iso:country":"ES",
    "sg:address":"Ctra Su Eminencia, S/n",
    "sg:city":"Sevilla",
    "sg:orig_category":"Cervezas (negociantes Y Depositarios)",
    "sg:phone":"+34 954 68 07 48",
    "sg:postcode":"41006",
    "sg:province":"Sevilla",
    "sg:website":"www.grupvivo.com",
    "wof:name":"Inversiones Ivindo S.l.",
    "wof:placetype":"venue"
},
  "geometry": {"coordinates":[-5.9573841095,37.3631248474],"type":"Point"}
}