{
  "type": "Feature",
  "properties": {
    "iso:country":"ES",
    "sg:address":"Av Espanya, 10",
    "sg:city":"Eivissa",
    "sg:orig_category":"Zapatos (al Por Menor)",
    "sg:phone":"+34 971 30 74 08",
    "sg:postcode":"07800",
    "sg:province":"Islas Baleares",
    "wof:name":"Ibizazapato S.l.",
    "wof:placetype":"venue"
},
  "geometry": {"coordinates":[1.4312249422,38.9087524414],"type":"Point"}
}