{
  "type": "Feature",
  "properties": {
    "iso:country":"ES",
    "sg:address":"Ctra Tacoronte Tejina, 7",
    "sg:city":"Tacoronte",
    "sg:orig_category":"\u00d3ptica: Instrumentos (fabricaci\u00d3n)",
    "sg:phone":"+34 922 57 01 55",
    "sg:postcode":"38350",
    "sg:province":"Santa Cruz De Tenerife",
    "wof:name":"Optica Alvarez S.l.",
    "wof:placetype":"venue"
},
  "geometry": {"coordinates":[-16.4148635864,28.4775829315],"type":"Point"}
}