{
  "type": "Feature",
  "properties": {
    "addr:full":"Ctra Carmona, Km. 0001,1 Utrera Sevilla 41710",
    "addr:postcode":"41710",
    "addr:street":"Ctra Carmona Km. 0001,1",
    "iso:country":"ES",
    "sg:address":"Ctra Carmona, Km. 0001,1",
    "sg:city":"Utrera",
    "sg:orig_category":"Hielo Artificial (fabricaci\u00d3n, Distribuci\u00d3n)",
    "sg:phone":"+34 954 86 18 60",
    "sg:postcode":"41710",
    "sg:province":"Sevilla",
    "sg:website":"www.royne.es",
    "wof:name":"Clesa Helados S.l.",
    "wof:placetype":"venue"
},
  "geometry": {"coordinates":[-5.7909588814,37.1916007996],"type":"Point"}
}