{
  "type": "Feature",
  "properties": {
    "addr:full":"Calle de Merced (la) (miralbueno), 6 Zaragoza Zaragoza 50011",
    "addr:housenumber":"6",
    "addr:postcode":"50011",
    "addr:street":"Calle De Merced La Miralbueno",
    "iso:country":"ES",
    "sg:address":"Calle de Merced (la) (miralbueno), 6",
    "sg:city":"Zaragoza",
    "sg:orig_category":"Carnicer\u00cdas, Carnicer\u00cdas",
    "sg:phone":"+34 976 53 04 15",
    "sg:postcode":"50011",
    "sg:province":"Zaragoza",
    "wof:name":"Castan Hernandez Rafael",
    "wof:placetype":"venue"
},
  "geometry": {"coordinates":[-0.9417279959,41.6592407227],"type":"Point"}
}