{
  "type": "Feature",
  "properties": {
    "addr:full":"Calle de Bao, 11 Boiro La Coru\u00f1a 15930",
    "addr:housenumber":"11",
    "addr:postcode":"15930",
    "addr:street":"Calle De Bao;La Corun\u0303A",
    "iso:country":"ES",
    "sg:address":"Calle de Bao, 11",
    "sg:city":"Boiro",
    "sg:orig_category":"Panader\u00cdas, Panader\u00cdas",
    "sg:phone":"+34 981 84 54 45",
    "sg:postcode":"15930",
    "sg:province":"La Coru\u00f1a",
    "wof:name":"Frazon Quintas Josefa",
    "wof:placetype":"venue"
},
  "geometry": {"coordinates":[-8.8849544525,42.6482009888],"type":"Point"}
}