{
  "type": "Feature",
  "properties": {
    "addr:full":"Rua Xoan De Novoa, 2 Ourense Ourense 32004",
    "addr:housenumber":"2",
    "addr:postcode":"32004",
    "addr:street":"Rua Xoan De Novoa",
    "iso:country":"ES",
    "sg:address":"Rua Xoan De Novoa, 2",
    "sg:city":"Ourense",
    "sg:orig_category":"Electrodom\u00c9sticos (al Por Menor)",
    "sg:phone":"+34 988 26 96 28",
    "sg:postcode":"32004",
    "sg:province":"Ourense",
    "wof:name":"Luzmatel S.l.",
    "wof:placetype":"venue"
},
  "geometry": {"coordinates":[-7.8584918976,42.3403816223],"type":"Point"}
}