{
  "type": "Feature",
  "properties": {
    "iso:country":"ES",
    "sg:address":"Avda Alfonso Xiii, 94",
    "sg:city":"Madrid",
    "sg:orig_category":"Equipo De Refrigeraci\u00d3n Industrial",
    "sg:phone":"+34 914 13 85 52",
    "sg:postcode":"28016",
    "sg:province":"Madrid",
    "wof:name":"Consfri S.a.",
    "wof:placetype":"venue"
},
  "geometry": {"coordinates":[-3.6668770313,40.4559288025],"type":"Point"}
}