{
  "type": "Feature",
  "properties": {
    "iso:country":"ES",
    "sg:address":"Calle de Conejal, S/n",
    "sg:city":"Villavieja Yeltes",
    "sg:orig_category":"Granos Y Forrajes",
    "sg:phone":"+34 923 52 60 57",
    "sg:postcode":"37260",
    "sg:province":"Salamanca",
    "wof:name":"Hernandez Pi\u00f1uel Pedro",
    "wof:placetype":"venue"
},
  "geometry": {"coordinates":[-6.465651989,40.8737106323],"type":"Point"}
}