{
  "type": "Feature",
  "properties": {
    "iso:country":"ES",
    "sg:address":"Avda Madrid, 4",
    "sg:city":"Aspe",
    "sg:orig_category":"Perfumer\u00cda (al Por Menor)",
    "sg:phone":"+34 965 49 06 81",
    "sg:postcode":"03680",
    "sg:province":"Alicante",
    "wof:name":"Perfumerias Celia S.l.",
    "wof:placetype":"venue"
},
  "geometry": {"coordinates":[-0.7657750249,38.3434257507],"type":"Point"}
}