{
  "type": "Feature",
  "properties": {
    "addr:full":"Calle de Juan Sala De Pablo, 20 Montejo Tiermes Soria 42341",
    "addr:housenumber":"20",
    "addr:postcode":"42341",
    "addr:street":"Calle De Juan Sala;Pablo",
    "iso:country":"ES",
    "sg:address":"Calle de Juan Sala De Pablo, 20",
    "sg:city":"Montejo Tiermes",
    "sg:orig_category":"Suministros Y Materiales Industriales",
    "sg:phone":"+34 975 35 20 43",
    "sg:postcode":"42341",
    "sg:province":"Soria",
    "wof:name":"Egar C.b.",
    "wof:placetype":"venue"
},
  "geometry": {"coordinates":[-3.2007329464,41.3692398071],"type":"Point"}
}