{
  "type": "Feature",
  "properties": {
    "addr:full":"Ctra. Navalpino, Km. 0013,0 Guadamur Toledo 45160",
    "addr:postcode":"45160",
    "addr:street":"Ctra. Navalpino Km. 0013,0",
    "iso:country":"ES",
    "sg:address":"Ctra. Navalpino, Km. 0013,0",
    "sg:city":"Guadamur",
    "sg:orig_category":"Fabricaci\u00d3n De Productos L\u00c1cteos Y Derivados",
    "sg:phone":"+34 925 29 10 12",
    "sg:postcode":"45160",
    "sg:province":"Toledo",
    "wof:name":"Almendros Holstein S.l.",
    "wof:placetype":"venue"
},
  "geometry": {"coordinates":[-4.141140461,39.8150787354],"type":"Point"}
}