{
  "type": "Feature",
  "properties": {
    "iso:country":"ES",
    "sg:address":"Av Pais Valenciano, 10",
    "sg:city":"Museros",
    "sg:orig_category":"\u00d3ptica: Instrumentos (fabricaci\u00d3n)",
    "sg:phone":"+34 961 45 06 86",
    "sg:postcode":"46136",
    "sg:province":"Valencia",
    "wof:name":"Optica Museros C.b.",
    "wof:placetype":"venue"
},
  "geometry": {"coordinates":[-0.3412480056,39.5626831055],"type":"Point"}
}