{
  "type": "Feature",
  "properties": {
    "addr:full":"Calle de Creu (la), 67 Banyeres Mariola Alicante 03450",
    "addr:housenumber":"67",
    "addr:postcode":"03450",
    "addr:street":"Calle De Creu La",
    "iso:country":"ES",
    "sg:address":"Calle de Creu (la), 67",
    "sg:city":"Banyeres Mariola",
    "sg:orig_category":"Tapiceros Y Tapiceros",
    "sg:phone":"+34 965 56 66 05",
    "sg:postcode":"03450",
    "sg:province":"Alicante",
    "wof:name":"Perez Llopis Alejandra",
    "wof:placetype":"venue"
},
  "geometry": {"coordinates":[-0.6558588147,38.7187080383],"type":"Point"}
}