{
  "type": "Feature",
  "properties": {
    "iso:country":"ES",
    "sg:address":"Carr Capita Pere, 51",
    "sg:city":"Pobla",
    "sg:orig_category":"Arquitectos",
    "sg:phone":"+34 971 54 01 87",
    "sg:postcode":"07420",
    "sg:province":"Islas Baleares",
    "wof:name":"Pomar Comas Miguel",
    "wof:placetype":"venue"
},
  "geometry": {"coordinates":[3.025769949,39.7738304138],"type":"Point"}
}