{
  "type": "Feature",
  "properties": {
    "addr:full":"Plaz Espa\u00d1a De, 3 Aviles Asturias 33402",
    "addr:postcode":"33402",
    "addr:street":"Plaz",
    "iso:country":"ES",
    "sg:address":"Plaz Espa\u00d1a De, 3",
    "sg:city":"Aviles",
    "sg:orig_category":"Mercer\u00cda, Lencer\u00cda (al Por Menor)",
    "sg:phone":"+34 985 54 09 29",
    "sg:postcode":"33402",
    "sg:province":"Asturias",
    "wof:name":"Garcia Granda Ramona",
    "wof:placetype":"venue"
},
  "geometry": {"coordinates":[-5.9263877869,43.534324646],"type":"Point"}
}