{
  "type": "Feature",
  "properties": {
    "iso:country":"ES",
    "sg:address":"Calle de Catapilco, 3",
    "sg:city":"Malaga",
    "sg:orig_category":"Par\u00cds",
    "sg:phone":"+34 952 24 42 60",
    "sg:postcode":"29004",
    "sg:province":"M\u00e1laga",
    "wof:name":"Martinez Lopez Maria De La Luz",
    "wof:placetype":"venue"
},
  "geometry": {"coordinates":[-4.4534349442,36.690448761],"type":"Point"}
}