{
  "type": "Feature",
  "properties": {
    "iso:country":"ES",
    "sg:address":"Rua Parda (da), S/n",
    "sg:city":"Pontevedra",
    "sg:orig_category":"Alquiler De Gr\u00daas",
    "sg:phone":"+34 986 86 05 00",
    "sg:postcode":"36004",
    "sg:province":"Pontevedra",
    "sg:website":"www.gruasdoniz.com",
    "wof:name":"Gruas Doniz S. A.",
    "wof:placetype":"venue"
},
  "geometry": {"coordinates":[-8.6322727203,42.4205627441],"type":"Point"}
}