{
  "type": "Feature",
  "properties": {
    "addr:full":"Poli Industrial La Alberca, 12 Guare\u00f1a Badajoz 06470",
    "addr:housenumber":"12",
    "addr:postcode":"06470",
    "addr:street":"Alberca",
    "iso:country":"ES",
    "sg:address":"Poli Industrial La Alberca, 12",
    "sg:city":"Guare\u00f1a",
    "sg:orig_category":"Muebles, Minoristas",
    "sg:phone":"+34 924 35 16 64",
    "sg:postcode":"06470",
    "sg:province":"Badajoz",
    "wof:name":"Hidalgo Dise\u00d1o S.l.",
    "wof:placetype":"venue"
},
  "geometry": {"coordinates":[-6.0888390541,38.8579902649],"type":"Point"}
}