{
  "type": "Feature",
  "properties": {
    "addr:full":"Plaz Escuelas, 2 Aldeaseca \u00c1vila 05214",
    "addr:housenumber":"2",
    "addr:postcode":"05214",
    "addr:street":"Plaz Escuelas;A\u0301Vila",
    "iso:country":"ES",
    "sg:address":"Plaz Escuelas, 2",
    "sg:city":"Aldeaseca",
    "sg:orig_category":"Centros De Educaci\u00d3n Especial",
    "sg:phone":"+34 920 30 62 87",
    "sg:postcode":"05214",
    "sg:province":"\u00c1vila",
    "wof:name":"Colegio Rural Agrupado Tierra De Arevalo",
    "wof:placetype":"venue"
},
  "geometry": {"coordinates":[-4.6407837868,40.924446106],"type":"Point"}
}