{
  "type": "Feature",
  "properties": {
    "addr:full":"Calle de Silo (el), 4 Barrax Albacete 02639",
    "addr:housenumber":"4",
    "addr:postcode":"02639",
    "addr:street":"Calle De Silo El",
    "iso:country":"ES",
    "sg:address":"Calle de Silo (el), 4",
    "sg:city":"Barrax",
    "sg:orig_category":"Promotores Constructores",
    "sg:phone":"+34 967 36 53 00",
    "sg:postcode":"02639",
    "sg:province":"Albacete",
    "wof:name":"Construcciones Santicano S.l.",
    "wof:placetype":"venue"
},
  "geometry": {"coordinates":[-2.2010400295,39.043674469],"type":"Point"}
}