{
  "type": "Feature",
  "properties": {
    "addr:full":"Poli Industrial Berriainz, 166 Berriozar Navarra 31013",
    "addr:housenumber":"166",
    "addr:postcode":"31013",
    "iso:country":"ES",
    "sg:address":"Poli Industrial Berriainz, 166",
    "sg:city":"Berriozar",
    "sg:orig_category":"Oficinas: Suministros Para (fabricaci\u00d3n, Al Por Mayor)",
    "sg:phone":"+34 948 30 34 87",
    "sg:postcode":"31013",
    "sg:province":"Navarra",
    "wof:name":"Dina Distribuidora Iberica Navarra S.l.",
    "wof:placetype":"venue"
},
  "geometry": {"coordinates":[-97.78224945069999,45.7040786743],"type":"Point"}
}