{
  "type": "Feature",
  "properties": {
    "addr:full":"Avda Santiago (de), 109 Ourense Ourense 32001",
    "addr:housenumber":"109",
    "addr:postcode":"32001",
    "addr:street":"Avda Santiago De",
    "iso:country":"ES",
    "sg:address":"Avda Santiago (de), 109",
    "sg:city":"Ourense",
    "sg:orig_category":"Obras Y Organismos Sociales",
    "sg:phone":"+34 988 21 46 02",
    "sg:postcode":"32001",
    "sg:province":"Ourense",
    "wof:name":"Remar Espa\u00f1a",
    "wof:placetype":"venue"
},
  "geometry": {"coordinates":[-7.8654460907,42.3562202454],"type":"Point"}
}