{
  "type": "Feature",
  "properties": {
    "iso:country":"ES",
    "sg:address":"Carr Major, 34",
    "sg:city":"Manises",
    "sg:orig_category":"Tapiceros Y Tapiceros",
    "sg:phone":"+34 961 53 72 02",
    "sg:postcode":"46940",
    "sg:province":"Valencia",
    "wof:name":"Segovia Martinez Francisco Jose",
    "wof:placetype":"venue"
},
  "geometry": {"coordinates":[-0.4578079879,39.491771698],"type":"Point"}
}