{
  "type": "Feature",
  "properties": {
    "iso:country":"ES",
    "sg:address":"Calle de Pablo De Xerica, 5",
    "sg:city":"Vitoria-gasteiz",
    "sg:orig_category":"Pescader\u00cdas (al Por Menor)",
    "sg:phone":"+34 945 13 64 48",
    "sg:postcode":"01006",
    "sg:province":"\u00c1lava",
    "wof:name":"Est\u00cdbaliz Cameno Corres",
    "wof:placetype":"venue"
},
  "geometry": {"coordinates":[-2.6685180664,42.8357200623],"type":"Point"}
}