{
  "type": "Feature",
  "properties": {
    "iso:country":"ES",
    "sg:address":"Avda Doctor Oloriz, 4",
    "sg:city":"Granada",
    "sg:orig_category":"Abogados",
    "sg:phone":"+34 958 20 62 27",
    "sg:postcode":"18012",
    "sg:province":"Granada",
    "wof:name":"Bellido Salguero Josefa",
    "wof:placetype":"venue"
},
  "geometry": {"coordinates":[-3.6078219414,37.1866912842],"type":"Point"}
}