{
  "type": "Feature",
  "properties": {
    "iso:country":"ES",
    "sg:address":"Leon-astorga, Km. 0005,5",
    "sg:city":"Trobajo Camino",
    "sg:orig_category":"Transportes Por V\u00cdas Navegables",
    "sg:phone":"+34 987 80 81 29",
    "sg:postcode":"24010",
    "sg:province":"Le\u00f3n",
    "sg:website":"www.transxtar.es",
    "wof:name":"M C T & Trans S.l.",
    "wof:placetype":"venue"
},
  "geometry": {"coordinates":[-5.5716600418,42.5981292725],"type":"Point"}
}