{
  "type": "Feature",
  "properties": {
    "iso:country":"ES",
    "sg:address":"Avda Lugo, 21",
    "sg:city":"Pontes Garcia Rodriguez",
    "sg:orig_category":"Art\u00cdculos Funerarios (al Por Menor)",
    "sg:phone":"+34 981 45 29 12",
    "sg:postcode":"15320",
    "sg:province":"A Coru\u00f1a",
    "wof:name":"Servicios San Roqui\u00f1o S.l.",
    "wof:placetype":"venue"
},
  "geometry": {"coordinates":[-7.8471689224,43.4444999695],"type":"Point"}
}