{
  "type": "Feature",
  "properties": {
    "iso:country":"ES",
    "sg:address":"Rua Parque Municipal, 26",
    "sg:city":"Ordes",
    "sg:orig_category":"Veh\u00cdculos De Ocasi\u00d3n",
    "sg:phone":"+34 981 68 01 17",
    "sg:postcode":"15680",
    "sg:province":"La Coru\u00f1a",
    "wof:name":"Liste Mosquera Jesus",
    "wof:placetype":"venue"
},
  "geometry": {"coordinates":[-8.408039093,43.076915741],"type":"Point"}
}