{
  "type": "Feature",
  "properties": {
    "addr:full":"Calle de Prieto Molina, 73 Azuaga Badajoz 06920",
    "addr:housenumber":"73",
    "addr:postcode":"06920",
    "addr:street":"Calle De Prieto Molina",
    "iso:country":"ES",
    "sg:address":"Calle de Prieto Molina, 73",
    "sg:city":"Azuaga",
    "sg:orig_category":"Papeler\u00cdas, Librer\u00cdas",
    "sg:phone":"+34 924 89 10 88",
    "sg:postcode":"06920",
    "sg:province":"Badajoz",
    "wof:name":"Carrizosa Naranjo Manuel Angel",
    "wof:placetype":"venue"
},
  "geometry": {"coordinates":[-5.6846189499,38.2606811523],"type":"Point"}
}