{
  "type": "Feature",
  "properties": {
    "addr:full":"Calle de Arfe, S/n Sevilla Sevilla 41001",
    "addr:housenumber":"s / n",
    "addr:postcode":"41001",
    "addr:street":"Calle De Arfe",
    "iso:country":"ES",
    "sg:address":"Calle de Arfe, S/n",
    "sg:city":"Sevilla",
    "sg:orig_category":"Bisuteros (fabricaci\u00d3n, Al Por Mayor)",
    "sg:phone":"+34 954 35 64 22",
    "sg:postcode":"41001",
    "sg:province":"Sevilla",
    "wof:name":"Bustamante Pe\u00f1alosa Antonio",
    "wof:placetype":"venue"
},
  "geometry": {"coordinates":[-5.9956207275,37.3858413696],"type":"Point"}
}