{
  "type": "Feature",
  "properties": {
    "addr:full":"Plaz Casta\u00d1ares De Rioja, 3 Haro La Rioja 26200",
    "addr:housenumber":"3",
    "addr:postcode":"26200",
    "addr:street":"Plaz;Rioja",
    "iso:country":"ES",
    "sg:address":"Plaz Casta\u00d1ares De Rioja, 3",
    "sg:city":"Haro",
    "sg:orig_category":"Venta, Instalaci\u00d3n De Calefacci\u00d3n",
    "sg:phone":"+34 941 31 26 06",
    "sg:postcode":"26200",
    "sg:province":"La Rioja",
    "wof:name":"Garcia Frias Jose Miguel",
    "wof:placetype":"venue"
},
  "geometry": {"coordinates":[-2.8523449898,42.573677063],"type":"Point"}
}