{
  "type": "Feature",
  "properties": {
    "iso:country":"ES",
    "sg:address":"Calle de Teniente Flomesta, 10",
    "sg:city":"Calasparra",
    "sg:orig_category":"Cajas De Ahorro",
    "sg:phone":"+34 968 72 12 97",
    "sg:postcode":"30420",
    "sg:province":"Murcia",
    "sg:website":"www.cajamurcia.es",
    "wof:name":"Caja De Ahorros De Murcia",
    "wof:placetype":"venue"
},
  "geometry": {"coordinates":[-1.7003599405,38.2357597351],"type":"Point"}
}