{
  "type": "Feature",
  "properties": {
    "addr:full":"Calle de Vicente Delgado Algaba, 106 Badajoz Badajoz 06010",
    "addr:housenumber":"106",
    "addr:postcode":"06010",
    "addr:street":"Calle De Vicente Delgado Algaba",
    "iso:country":"ES",
    "sg:address":"Calle de Vicente Delgado Algaba, 106",
    "sg:city":"Badajoz",
    "sg:orig_category":"Administradores De Bienes Y Delegados De Comunidades De Propietarios",
    "sg:phone":"+34 924 22 92 70",
    "sg:postcode":"06010",
    "sg:province":"Badajoz",
    "wof:name":"Cyma Agencia Empresarial S.l.",
    "wof:placetype":"venue"
},
  "geometry": {"coordinates":[-6.9751291275,38.8659515381],"type":"Point"}
}