{
  "type": "Feature",
  "properties": {
    "addr:full":"Carr Alcoi, S/n Grau I Platja Valencia 46730",
    "addr:housenumber":"s / n",
    "addr:postcode":"46730",
    "addr:street":"Carr Alcoi",
    "iso:country":"ES",
    "sg:address":"Carr Alcoi, S/n",
    "sg:city":"Grau I Platja",
    "sg:orig_category":"Promotores Constructores",
    "sg:phone":"+34 962 84 45 83",
    "sg:postcode":"46730",
    "sg:province":"Valencia",
    "wof:name":"Promociones Grupo 88 S.l.",
    "wof:placetype":"venue"
},
  "geometry": {"coordinates":[-0.1613429934,38.9958686829],"type":"Point"}
}