{
  "type": "Feature",
  "properties": {
    "addr:full":"Carrer de Canal, 12 Reus Tarragona 43205",
    "addr:housenumber":"12",
    "addr:postcode":"43205",
    "addr:street":"Carrer De Canal",
    "iso:country":"ES",
    "sg:address":"Carrer de Canal, 12",
    "sg:city":"Reus",
    "sg:orig_category":"Carnicer\u00cdas, Carnicer\u00cdas",
    "sg:phone":"+34 977 75 51 53",
    "sg:postcode":"43205",
    "sg:province":"Tarragona",
    "wof:name":"Ramos Ledesma Francisco",
    "wof:placetype":"venue"
},
  "geometry": {"coordinates":[1.1087269783,41.1508369446],"type":"Point"}
}