{
  "type": "Feature",
  "properties": {
    "iso:country":"ES",
    "sg:address":"Carrer de Joan Baptista Lambert, 34",
    "sg:city":"Lloret Mar",
    "sg:orig_category":"Limpieza Industrial",
    "sg:phone":"+34 972 36 23 53",
    "sg:postcode":"17310",
    "sg:province":"Girona",
    "wof:name":"Quintero Perez Jacson Alejandro",
    "wof:placetype":"venue"
},
  "geometry": {"coordinates":[2.850579977,41.703540802],"type":"Point"}
}