{
  "type": "Feature",
  "properties": {
    "addr:full":"Poli Cantabria, S/n Logro\u00f1o La Rioja 26006",
    "addr:housenumber":"s / n",
    "addr:postcode":"26006",
    "addr:street":"Rioja",
    "iso:country":"ES",
    "sg:address":"Poli Cantabria, S/n",
    "sg:city":"Logro\u00f1o",
    "sg:orig_category":"Tratamiento De Metales",
    "sg:phone":"+34 941 23 41 33",
    "sg:postcode":"26006",
    "sg:province":"La Rioja",
    "wof:name":"Eural S.a.",
    "wof:placetype":"venue"
},
  "geometry": {"coordinates":[-2.4036989212,42.46043396],"type":"Point"}
}