{
  "type": "Feature",
  "properties": {
    "iso:country":"ES",
    "sg:address":"Calle de Maria Paz Unciti, 11",
    "sg:city":"Madrid",
    "sg:orig_category":"Prot\u00c9sicos Dentales",
    "sg:phone":"+34 914 78 97 72",
    "sg:postcode":"28053",
    "sg:province":"Madrid",
    "wof:name":"Vasco Pegalajar Miguel",
    "wof:placetype":"venue"
},
  "geometry": {"coordinates":[-3.6635859013,40.393989563],"type":"Point"}
}