{
  "type": "Feature",
  "properties": {
    "addr:full":"Calle de Santiago, 15 Almeria Almer\u00eda 04006",
    "addr:housenumber":"15",
    "addr:postcode":"04006",
    "addr:street":"Calle De Santiago",
    "iso:country":"ES",
    "sg:address":"Calle de Santiago, 15",
    "sg:city":"Almeria",
    "sg:orig_category":"Quincaller\u00cda (al Por Menor)",
    "sg:phone":"+34 950 22 12 18",
    "sg:postcode":"04006",
    "sg:province":"Almer\u00eda",
    "wof:name":"Salcedo Jimenez Isabel",
    "wof:placetype":"venue"
},
  "geometry": {"coordinates":[-2.4496190548,36.8403816223],"type":"Point"}
}