{
  "type": "Feature",
  "properties": {
    "addr:full":"Carrer de Aribau, 195 Barcelona Barcelona 08021",
    "addr:housenumber":"195",
    "addr:postcode":"08021",
    "addr:street":"Carrer De Aribau",
    "iso:country":"ES",
    "sg:address":"Carrer de Aribau, 195",
    "sg:city":"Barcelona",
    "sg:orig_category":"Complementos De Vestir (al Por Menor)",
    "sg:phone":"+34 932 00 90 54",
    "sg:postcode":"08021",
    "sg:province":"Barcelona",
    "wof:name":"Fundacion Instituto Edad Y Vida",
    "wof:placetype":"venue"
},
  "geometry": {"coordinates":[2.1497910023,41.3953971863],"type":"Point"}
}