{
  "type": "Feature",
  "properties": {
    "addr:full":"Plaz Campo De Las Ferias, 28 Colindres Cantabria 39750",
    "addr:housenumber":"28",
    "addr:postcode":"39750",
    "addr:street":"Ferias",
    "iso:country":"ES",
    "sg:address":"Plaz Campo De Las Ferias, 28",
    "sg:city":"Colindres",
    "sg:orig_category":"M\u00c9dicos: Cirug\u00cda Pl\u00c1stica, Reconstructiva Y Est\u00c9tica",
    "sg:phone":"+34 942 65 11 18",
    "sg:postcode":"39750",
    "sg:province":"Cantabria",
    "wof:name":"Berrire Ortiz Jose Ramon",
    "wof:placetype":"venue"
},
  "geometry": {"coordinates":[-3.4509289265,43.3939704895],"type":"Point"}
}