{
  "type": "Feature",
  "properties": {
    "addr:full":"Calle de Trillo, 10 Cisterniga Valladolid 47193",
    "addr:housenumber":"10",
    "addr:postcode":"47193",
    "addr:street":"Calle De Trillo",
    "iso:country":"ES",
    "sg:address":"Calle de Trillo, 10",
    "sg:city":"Cisterniga",
    "sg:orig_category":"Promotores Constructores",
    "sg:phone":"+34 983 40 17 35",
    "sg:postcode":"47193",
    "sg:province":"Valladolid",
    "wof:name":"Construcciones Nuevas Del Duero S.l.",
    "wof:placetype":"venue"
},
  "geometry": {"coordinates":[-4.6809549332,41.6083450317],"type":"Point"}
}