{
  "type": "Feature",
  "properties": {
    "iso:country":"ES",
    "sg:address":"Av. Can Vullpalleres, 22",
    "sg:city":"S. Cugat Valles",
    "sg:orig_category":"Promotores Constructores",
    "sg:phone":"+34 935 89 01 67",
    "sg:postcode":"08173",
    "sg:province":"Barcelona",
    "wof:name":"Comunidad De Propietarios Sant Cugat Bloque 37",
    "wof:placetype":"venue"
},
  "geometry": {"coordinates":[2.0779109001,41.4788856506],"type":"Point"}
}