{
  "type": "Feature",
  "properties": {
    "iso:country":"ES",
    "sg:address":"Calle de Doctor Eustasio Quevedo, 53",
    "sg:city":"Palmas De Gran Canaria",
    "sg:orig_category":"Doctores En Medicina",
    "sg:phone":"+34 928 25 92 13",
    "sg:postcode":"35011",
    "sg:province":"Las Palmas",
    "wof:name":"Deepak  Lalwani Idnani",
    "wof:placetype":"venue"
},
  "geometry": {"coordinates":[-15.4320259094,28.1171474457],"type":"Point"}
}