{
  "type": "Feature",
  "properties": {
    "iso:country":"ES",
    "sg:address":"Calle de Elfo, 78",
    "sg:city":"Madrid",
    "sg:orig_category":"Peluqueros: De Se\u00d1oras",
    "sg:phone":"+34 913 67 27 55",
    "sg:postcode":"28027",
    "sg:province":"Madrid",
    "wof:name":"Elfo Real Peluqueros S.l.l",
    "wof:placetype":"venue"
},
  "geometry": {"coordinates":[-3.6463160515,40.4353218079],"type":"Point"}
}