{
  "type": "Feature",
  "properties": {
    "addr:full":"Avda Gran Capitan (del), 21 Cordoba C\u00f3rdoba 14008",
    "addr:housenumber":"21",
    "addr:postcode":"14008",
    "addr:street":"Avda Gran Capitan Del;Co\u0301Rdoba",
    "iso:country":"ES",
    "sg:address":"Avda Gran Capitan (del), 21",
    "sg:city":"Cordoba",
    "sg:orig_category":"Peluqueros: De Se\u00d1oras",
    "sg:phone":"+34 957 47 30 11",
    "sg:postcode":"14008",
    "sg:province":"C\u00f3rdoba",
    "wof:name":"Reyes Garcia Emilio",
    "wof:placetype":"venue"
},
  "geometry": {"coordinates":[-4.782834053,37.888458252],"type":"Point"}
}