{
  "type": "Feature",
  "properties": {
    "addr:full":"Avda Matias Saenz De Tejada, S/n Fuengirola M\u00e1laga 29640",
    "addr:housenumber":"/ n",
    "addr:postcode":"29640",
    "addr:street":"Avda Matias Saenz De Tejada S;Ma\u0301Laga",
    "iso:country":"ES",
    "sg:address":"Avda Matias Saenz De Tejada, S/n",
    "sg:city":"Fuengirola",
    "sg:orig_category":"Traductores",
    "sg:phone":"+34 952 58 87 35",
    "sg:postcode":"29640",
    "sg:province":"M\u00e1laga",
    "wof:name":"Eurogestion Traducciones Service Center",
    "wof:placetype":"venue"
},
  "geometry": {"coordinates":[-4.62266922,36.5412940979],"type":"Point"}
}