{
  "type": "Feature",
  "properties": {
    "addr:full":"Calle de Aguayo, 1 Ecija Sevilla 41400",
    "addr:housenumber":"1",
    "addr:postcode":"41400",
    "addr:street":"Calle De Aguayo",
    "iso:country":"ES",
    "sg:address":"Calle de Aguayo, 1",
    "sg:city":"Ecija",
    "sg:orig_category":"Zootecnia",
    "sg:phone":"+34 954 83 46 78",
    "sg:postcode":"41400",
    "sg:province":"Sevilla",
    "wof:name":"Asociacion Ornitologica Ciudad Del Sol",
    "wof:placetype":"venue"
},
  "geometry": {"coordinates":[-5.0814580917,37.5469436646],"type":"Point"}
}