{
  "type": "Feature",
  "properties": {
    "addr:full":"Avda Carlos Iii, S/n Carlota C\u00f3rdoba 14100",
    "addr:housenumber":"s / n",
    "addr:postcode":"14100",
    "addr:street":"Avda Carlos Iii;Carlota Co\u0301Rdoba",
    "iso:country":"ES",
    "sg:address":"Avda Carlos Iii, S/n",
    "sg:city":"Carlota",
    "sg:orig_category":"Metalurgia",
    "sg:phone":"+34 957 30 03 11",
    "sg:postcode":"14100",
    "sg:province":"C\u00f3rdoba",
    "wof:name":"Trefilados Urbano S.l.",
    "wof:placetype":"venue"
},
  "geometry": {"coordinates":[-4.9389038086,37.6681060791],"type":"Point"}
}