{
  "type": "Feature",
  "properties": {
    "iso:country":"ES",
    "sg:address":"Hispanidad, 56",
    "sg:city":"Villanueva Gallego",
    "sg:orig_category":"Electricidad: Instaladores",
    "sg:phone":"+34 976 18 54 00",
    "sg:postcode":"50830",
    "sg:province":"Zaragoza",
    "wof:name":"Monta\u00f1es Gonzalvo Fernando",
    "wof:placetype":"venue"
},
  "geometry": {"coordinates":[-0.8222020268,41.7705192566],"type":"Point"}
}