{
  "type": "Feature",
  "properties": {
    "addr:full":"C/ Gonzalez, 21 Cerdanyola Valles Barcelona 08290",
    "addr:housenumber":"21",
    "addr:postcode":"08290",
    "addr:street":"C / Gonzalez;Valles Barcelona",
    "iso:country":"ES",
    "sg:address":"C/ Gonzalez, 21",
    "sg:city":"Cerdanyola Valles",
    "sg:orig_category":"M\u00c9dicos: Estomatolog\u00cda",
    "sg:phone":"+34 935 92 02 05",
    "sg:postcode":"08290",
    "sg:province":"Barcelona",
    "wof:name":"Grauer Lijtenstein Julio Manuel",
    "wof:placetype":"venue"
},
  "geometry": {"coordinates":[2.1470150948,41.4924812317],"type":"Point"}
}