{
  "type": "Feature",
  "properties": {
    "iso:country":"ES",
    "sg:address":"Calle de Mercaderes, 8",
    "sg:city":"Llanes",
    "sg:orig_category":"Panader\u00cdas, Panader\u00cdas",
    "sg:phone":"+34 985 40 08 22",
    "sg:postcode":"33500",
    "sg:province":"Asturias",
    "wof:name":"Confiteria Vega C.b.",
    "wof:placetype":"venue"
},
  "geometry": {"coordinates":[-4.7543129921,43.4195289612],"type":"Point"}
}