{
  "type": "Feature",
  "properties": {
    "addr:full":"Calle de Jativa, 53 Madrid Madrid 28007",
    "addr:housenumber":"53",
    "addr:postcode":"madrid;28007",
    "addr:street":"Calle De Jativa",
    "iso:country":"ES",
    "sg:address":"Calle de Jativa, 53",
    "sg:city":"Madrid",
    "sg:orig_category":"Agentes, Concesionarios Y Sucursales De Veh\u00cdculos",
    "sg:phone":"+34 914 33 62 40",
    "sg:postcode":"28007",
    "sg:province":"Madrid",
    "wof:name":"Reparacion De Automoviles Alvarez S.l.",
    "wof:placetype":"venue"
},
  "geometry": {"coordinates":[-3.6711089611,40.3973083496],"type":"Point"}
}