{
  "type": "Feature",
  "properties": {
    "iso:country":"ES",
    "sg:address":"Trva Arteixo, 74",
    "sg:city":"Arteixo",
    "sg:orig_category":"Mec\u00c1nico Del Autom\u00d3vil",
    "sg:phone":"+34 981 60 09 04",
    "sg:postcode":"15142",
    "sg:province":"La Coru\u00f1a",
    "wof:name":"Martinez Sanmamed Manuel",
    "wof:placetype":"venue"
},
  "geometry": {"coordinates":[-8.4979763031,43.3130912781],"type":"Point"}
}