{
  "type": "Feature",
  "properties": {
    "iso:country":"ES",
    "sg:address":"Cmno Valderribas, 95",
    "sg:city":"Madrid",
    "sg:orig_category":"Papeler\u00cdas, Librer\u00cdas",
    "sg:phone":"+34 914 37 61 80",
    "sg:postcode":"28038",
    "sg:province":"Madrid",
    "wof:name":"Benito Garcia Maria Carmen",
    "wof:placetype":"venue"
},
  "geometry": {"coordinates":[-3.6607179642,40.3990783691],"type":"Point"}
}