{
  "type": "Feature",
  "properties": {
    "iso:country":"ES",
    "sg:address":"Carrer de Gaiarre, 19",
    "sg:city":"Barcelona",
    "sg:orig_category":"Papeler\u00cdas, Librer\u00cdas",
    "sg:phone":"+34 934 32 39 31",
    "sg:postcode":"08014",
    "sg:province":"Barcelona",
    "wof:name":"Martinez Cami Antonio",
    "wof:placetype":"venue"
},
  "geometry": {"coordinates":[2.1402199268,41.3745918274],"type":"Point"}
}