{
  "type": "Feature",
  "properties": {
    "iso:country":"ES",
    "sg:address":"Avda Gran Via, 128",
    "sg:city":"Vigo",
    "sg:orig_category":"Textil",
    "sg:phone":"+34 986 42 05 22",
    "sg:postcode":"36203",
    "sg:province":"Pontevedra",
    "wof:name":"Bera 2000 S.l.",
    "wof:placetype":"venue"
},
  "geometry": {"coordinates":[-8.7247810364,42.2233505249],"type":"Point"}
}