{
  "type": "Feature",
  "properties": {
    "addr:full":"Calle de Luz, 4 Valdepe\u00f1as Ciudad Real 13300",
    "addr:housenumber":"4",
    "addr:postcode":"13300",
    "addr:street":"Calle De Luz",
    "iso:country":"ES",
    "sg:address":"Calle de Luz, 4",
    "sg:city":"Valdepe\u00f1as",
    "sg:orig_category":"Audiovisuales, Tv, Hi",
    "sg:phone":"+34 902 30 23 03",
    "sg:postcode":"13300",
    "sg:province":"Ciudad Real",
    "sg:website":"www.siemprecreativos.com",
    "wof:name":"Siempre Creativos Producciones Audiovisuales S.l.",
    "wof:placetype":"venue"
},
  "geometry": {"coordinates":[-3.3787679672,38.7546615601],"type":"Point"}
}