{
  "type": "Feature",
  "properties": {
    "addr:full":"Ctra Madrid N-iv (extrarradio), Km. 0385,0 Alcolea C\u00f3rdoba 14610",
    "addr:postcode":"14610",
    "addr:street":"Ctra Madrid N-Iv Extrarradio Km. 0385,0",
    "iso:country":"ES",
    "sg:address":"Ctra Madrid N-iv (extrarradio), Km. 0385,0",
    "sg:city":"Alcolea",
    "sg:orig_category":"Alimentaci\u00d3n General (al Por Menor)",
    "sg:phone":"+34 957 32 02 56",
    "sg:postcode":"14610",
    "sg:province":"C\u00f3rdoba",
    "wof:name":"Repsol Ypf S.a.",
    "wof:placetype":"venue"
},
  "geometry": {"coordinates":[-4.6694087982,37.9339485168],"type":"Point"}
}