{
  "type": "Feature",
  "properties": {
    "addr:full":"Carr Vallcalent, 43 Lleida Lleida 25006",
    "addr:housenumber":"43",
    "addr:postcode":"25006",
    "addr:street":"Carr Vallcalent",
    "iso:country":"ES",
    "sg:address":"Carr Vallcalent, 43",
    "sg:city":"Lleida",
    "sg:orig_category":"Caf\u00c9s, Bares, Cervecer\u00cdas",
    "sg:phone":"+34 973 26 59 36",
    "sg:postcode":"25006",
    "sg:province":"Lleida",
    "wof:name":"La Coba Del Marraco S.l.",
    "wof:placetype":"venue"
},
  "geometry": {"coordinates":[0.6176910996,41.6175727844],"type":"Point"}
}