{
  "type": "Feature",
  "properties": {
    "iso:country":"ES",
    "sg:address":"Carr Mendizabal, 103",
    "sg:city":"Burjassot",
    "sg:orig_category":"Reposter\u00cdas",
    "sg:phone":"+34 963 63 82 53",
    "sg:postcode":"46100",
    "sg:province":"Valencia",
    "wof:name":"Pla E Hijos S.l.",
    "wof:placetype":"venue"
},
  "geometry": {"coordinates":[-0.4159780145,39.512966156],"type":"Point"}
}