{
  "type": "Feature",
  "properties": {
    "iso:country":"ES",
    "sg:address":"Carr Castell (del), 2",
    "sg:city":"Artesa Lleida",
    "sg:orig_category":"Cajas De Ahorro",
    "sg:phone":"+34 973 16 71 84",
    "sg:postcode":"25150",
    "sg:province":"Lleida",
    "wof:name":"Caixa D'estalvis De Catalunya",
    "wof:placetype":"venue"
},
  "geometry": {"coordinates":[0.7057800293,41.5531044006],"type":"Point"}
}