{
  "type": "Feature",
  "properties": {
    "addr:full":"Rua Corzas, 38 Mugardos A Coru\u00f1a 15620",
    "addr:housenumber":"38",
    "addr:postcode":"15620",
    "addr:street":"Rua Corzas;Corun\u0303A",
    "iso:country":"ES",
    "sg:address":"Rua Corzas, 38",
    "sg:city":"Mugardos",
    "sg:orig_category":"Panader\u00cdas, Pasteler\u00cdas, Boller\u00cda Industriale (fabricaci\u00d3n, Al Por Mayor)",
    "sg:phone":"+34 981 47 00 48",
    "sg:postcode":"15620",
    "sg:province":"A Coru\u00f1a",
    "wof:name":"Teijeiro Fari\u00f1a Vicente Ramon",
    "wof:placetype":"venue"
},
  "geometry": {"coordinates":[-8.2535219193,43.4585876465],"type":"Point"}
}