{
  "type": "Feature",
  "properties": {
    "addr:full":"Calle de Puerto De Pozazal, 4 Madrid Madrid 28031",
    "addr:housenumber":"4",
    "addr:postcode":"28031",
    "addr:street":"Calle De Puerto De Pozazal",
    "iso:country":"ES",
    "sg:address":"Calle de Puerto De Pozazal, 4",
    "sg:city":"Madrid",
    "sg:orig_category":"Agencias Y Asesores De Publicidad",
    "sg:phone":"+34 917 77 51 61",
    "sg:postcode":"28031",
    "sg:province":"Madrid",
    "wof:name":"Redeam S.a.",
    "wof:placetype":"venue"
},
  "geometry": {"coordinates":[-3.6281449795,40.3794746399],"type":"Point"}
}