{
  "type": "Feature",
  "properties": {
    "addr:full":"Ctra Cordoba, 10 Alcaudete Ja\u00e9n 23660",
    "addr:housenumber":"10",
    "addr:postcode":"23660",
    "addr:street":"Ctra Cordoba;Jae\u0301N",
    "iso:country":"ES",
    "sg:address":"Ctra Cordoba, 10",
    "sg:city":"Alcaudete",
    "sg:orig_category":"Supermercados Y Hipermercados",
    "sg:phone":"+34 953 56 07 51",
    "sg:postcode":"23660",
    "sg:province":"Ja\u00e9n",
    "wof:name":"Luis Pi\u00f1a S.a.",
    "wof:placetype":"venue"
},
  "geometry": {"coordinates":[-4.0824050903,37.5879173279],"type":"Point"}
}