{
  "type": "Feature",
  "properties": {
    "addr:full":"Calle de Galapagar, 28 Barriada Del Angel C\u00f3rdoba 14610",
    "addr:housenumber":"28",
    "addr:postcode":"14610",
    "addr:street":"Calle De Galapagar;Barriada Del Angel Co\u0301Rdoba",
    "iso:country":"ES",
    "sg:address":"Calle de Galapagar, 28",
    "sg:city":"Barriada Del Angel",
    "sg:orig_category":"Mercer\u00cda, Lencer\u00cda (al Por Menor)",
    "sg:phone":"+34 957 32 00 53",
    "sg:postcode":"14610",
    "sg:province":"C\u00f3rdoba",
    "wof:name":"Velasco Pe\u00f1alvez Francisco",
    "wof:placetype":"venue"
},
  "geometry": {"coordinates":[-4.6766438484,37.9309043884],"type":"Point"}
}