{
  "type": "Feature",
  "properties": {
    "iso:country":"ES",
    "sg:address":"Calle de Marcelino Suarez, 16",
    "sg:city":"Oviedo",
    "sg:orig_category":"Frutas, Legumbres Frescas Y Tempranas (al Por Menor)",
    "sg:phone":"+34 985 27 43 85",
    "sg:postcode":"33012",
    "sg:province":"Asturias",
    "wof:name":"Don Tomate S.l.",
    "wof:placetype":"venue"
},
  "geometry": {"coordinates":[-5.8621912003,43.3639411926],"type":"Point"}
}