{
  "type": "Feature",
  "properties": {
    "iso:country":"ES",
    "sg:address":"La Era, 5",
    "sg:city":"Gines",
    "sg:orig_category":"Audiovisuales (producci\u00d3n, Edici\u00d3n, Realizaci\u00d3n)",
    "sg:phone":"+34 954 71 50 49",
    "sg:postcode":"41960",
    "sg:province":"Sevilla",
    "wof:name":"Macondo Films S.l.",
    "wof:placetype":"venue"
},
  "geometry": {"coordinates":[-6.0808691978,37.388420105],"type":"Point"}
}