{
  "type": "Feature",
  "properties": {
    "addr:full":"Calle de Utrillas, 10 Zaragoza Zaragoza 50013",
    "addr:housenumber":"10",
    "addr:postcode":"50013",
    "addr:street":"Calle De Utrillas",
    "iso:country":"ES",
    "sg:address":"Calle de Utrillas, 10",
    "sg:city":"Zaragoza",
    "sg:orig_category":"Garajes De Veh\u00cdculos",
    "sg:phone":"+34 976 42 00 58",
    "sg:postcode":"50013",
    "sg:province":"Zaragoza",
    "wof:name":"Miguel Servet 59 S.l.",
    "wof:placetype":"venue"
},
  "geometry": {"coordinates":[-0.8683390021,41.643661499],"type":"Point"}
}