{
  "type": "Feature",
  "properties": {
    "iso:country":"ES",
    "sg:address":"Carrer de Gran De Gracia, 73",
    "sg:city":"Barcelona",
    "sg:orig_category":"M\u00c9dicos: Endocrinolog\u00cda Y Metabolismo",
    "sg:phone":"+34 932 17 33 47",
    "sg:postcode":"08012",
    "sg:province":"Barcelona",
    "wof:name":"Ma\u00f1a Turbi Jose",
    "wof:placetype":"venue"
},
  "geometry": {"coordinates":[2.1549830437,41.4000663757],"type":"Point"}
}