{
  "type": "Feature",
  "properties": {
    "addr:full":"Calle de Carre\u00d1o Miranda, 4 Mieres Asturias 33600",
    "addr:housenumber":"4",
    "addr:postcode":"33600",
    "addr:street":"Calle De Carren\u0303O Miranda",
    "iso:country":"ES",
    "sg:address":"Calle de Carre\u00d1o Miranda, 4",
    "sg:city":"Mieres",
    "sg:orig_category":"Institutos De Belleza",
    "sg:phone":"+34 985 45 00 20",
    "sg:postcode":"33600",
    "sg:province":"Asturias",
    "wof:name":"Alvarez Dominguez Gemma Maria",
    "wof:placetype":"venue"
},
  "geometry": {"coordinates":[-5.7728104591,43.2523155212],"type":"Point"}
}