{
  "type": "Feature",
  "properties": {
    "iso:country":"ES",
    "sg:address":"Carrer de Sant Carles, 25",
    "sg:city":"Santa Coloma De Gramenet",
    "sg:orig_category":"Ropa Para Se\u00d1oras (al Por Menor)",
    "sg:phone":"+34 934 66 51 58",
    "sg:postcode":"08922",
    "sg:province":"Barcelona",
    "wof:name":"In Bloom S.c.p.",
    "wof:placetype":"venue"
},
  "geometry": {"coordinates":[2.2084009647,41.4508323669],"type":"Point"}
}