{
  "type": "Feature",
  "properties": {
    "addr:full":"Calle de Mariano Royo, 1 Zaragoza Zaragoza 50006",
    "addr:housenumber":"1",
    "addr:postcode":"50006",
    "addr:street":"Calle De Mariano Royo",
    "iso:country":"ES",
    "sg:address":"Calle de Mariano Royo, 1",
    "sg:city":"Zaragoza",
    "sg:orig_category":"Decoradores",
    "sg:phone":"+34 976 23 74 22",
    "sg:postcode":"50006",
    "sg:province":"Zaragoza",
    "wof:name":"T. M. Estudio S. C.",
    "wof:placetype":"venue"
},
  "geometry": {"coordinates":[-0.8870142102,41.646282196],"type":"Point"}
}