{
  "type": "Feature",
  "properties": {
    "iso:country":"ES",
    "sg:address":"Calle de Valdes Bazan, 2",
    "sg:city":"Pravia",
    "sg:orig_category":"Cooperativas Agr\u00cdcolas",
    "sg:phone":"+34 985 82 04 22",
    "sg:postcode":"33120",
    "sg:province":"Asturias",
    "wof:name":"Cooperativa De Labradores Y Ganaderos",
    "wof:placetype":"venue"
},
  "geometry": {"coordinates":[-6.1105389595,43.4901313782],"type":"Point"}
}