{
  "type": "Feature",
  "properties": {
    "iso:country":"ES",
    "sg:address":"Rond General Mitre, 132",
    "sg:city":"Barcelona",
    "sg:orig_category":"Asesor\u00cda Fiscal Y Jur\u00cddica",
    "sg:phone":"+34 932 00 01 09",
    "sg:postcode":"08006",
    "sg:province":"Barcelona",
    "wof:name":"F.alegret Puig S.l.",
    "wof:placetype":"venue"
},
  "geometry": {"coordinates":[2.1383800507,41.4028625488],"type":"Point"}
}