{
  "type": "Feature",
  "properties": {
    "iso:country":"ES",
    "sg:address":"Calle de Alesanco, 5",
    "sg:city":"Najera",
    "sg:orig_category":"Barnizadores",
    "sg:phone":"+34 941 36 36 12",
    "sg:postcode":"26300",
    "sg:province":"La Rioja",
    "wof:name":"Simon Garcia Pedro",
    "wof:placetype":"venue"
},
  "geometry": {"coordinates":[-2.726929903,42.4175224304],"type":"Point"}
}