{
  "type": "Feature",
  "properties": {
    "iso:country":"ES",
    "sg:address":"Av Marignane, 6",
    "sg:city":"Figueres",
    "sg:orig_category":"Sociedades, Compa\u00d1\u00cdas Aseguradoras",
    "sg:phone":"+34 972 51 24 62",
    "sg:postcode":"17600",
    "sg:province":"Girona",
    "sg:website":"www.mutu-intercomarcal.com",
    "wof:name":"Mutua Intercomarcal",
    "wof:placetype":"venue"
},
  "geometry": {"coordinates":[2.9577729702,42.2707595825],"type":"Point"}
}