{
  "type": "Feature",
  "properties": {
    "iso:country":"ES",
    "sg:address":"Calle de Garachico, 51",
    "sg:city":"Villafranqueza - Palamo",
    "sg:orig_category":"Empresas De Carpinter\u00cda Met\u00c1lica",
    "sg:phone":"+34 965 17 86 32",
    "sg:postcode":"03112",
    "sg:province":"Alicante",
    "wof:name":"Ferma Metales S.l.",
    "wof:placetype":"venue"
},
  "geometry": {"coordinates":[-0.4690259993,38.4094772339],"type":"Point"}
}