{
  "type": "Feature",
  "properties": {
    "addr:full":"Calle de Dr Fleming (del), 25 Coslada Madrid 28820",
    "addr:housenumber":"25",
    "addr:postcode":"28820",
    "addr:street":"Calle De Dr Fleming Del",
    "iso:country":"ES",
    "sg:address":"Calle de Dr Fleming (del), 25",
    "sg:city":"Coslada",
    "sg:orig_category":"Quincaller\u00cda (al Por Menor)",
    "sg:phone":"+34 916 73 95 19",
    "sg:postcode":"28820",
    "sg:province":"Madrid",
    "wof:name":"Ferrielectro S.l.",
    "wof:placetype":"venue"
},
  "geometry": {"coordinates":[-3.5662550926,40.4237632751],"type":"Point"}
}