{
  "type": "Feature",
  "properties": {
    "addr:full":"Carr San Juan De Ribera, 57 Aldaia Valencia 46960",
    "addr:housenumber":"57",
    "addr:postcode":"46960",
    "addr:street":"Carr San;De Ribera",
    "iso:country":"ES",
    "sg:address":"Carr San Juan De Ribera, 57",
    "sg:city":"Aldaia",
    "sg:orig_category":"Electricidad: Instaladores",
    "sg:phone":"+34 961 51 44 19",
    "sg:postcode":"46960",
    "sg:province":"Valencia",
    "wof:name":"Jucama-digital S.l",
    "wof:placetype":"venue"
},
  "geometry": {"coordinates":[-0.4647890031,39.4679412842],"type":"Point"}
}