{
  "type": "Feature",
  "properties": {
    "iso:country":"ES",
    "sg:address":"Cinc (p I La Ermita), 7",
    "sg:city":"Marbella",
    "sg:orig_category":"Servicio De Salud",
    "sg:phone":"+34 952 82 26 11",
    "sg:postcode":"29600",
    "sg:province":"M\u00e1laga",
    "wof:name":"Saneamientos Puya S.l.",
    "wof:placetype":"venue"
},
  "geometry": {"coordinates":[-4.9114089012,36.5289497375],"type":"Point"}
}