{
  "type": "Feature",
  "properties": {
    "iso:country":"ES",
    "sg:address":"Carrer de Eusebi Guell, 42",
    "sg:city":"S. Boi Llobregat",
    "sg:orig_category":"Grafistas",
    "sg:phone":"+34 936 54 29 81",
    "sg:postcode":"08830",
    "sg:province":"Barcelona",
    "wof:name":"Eventos Visuales 3dtres S.l.",
    "wof:placetype":"venue"
},
  "geometry": {"coordinates":[2.0336310863,41.3477096558],"type":"Point"}
}