{
  "type": "Feature",
  "properties": {
    "addr:full":"Pla\u00c7 Sol, 2 Palafrugell Girona 17200",
    "addr:housenumber":"2",
    "addr:postcode":"17200",
    "iso:country":"ES",
    "sg:address":"Pla\u00c7 Sol, 2",
    "sg:city":"Palafrugell",
    "sg:orig_category":"Molduras, Junquillos, Listones Y Molduras Perforadas",
    "sg:phone":"+34 972 30 17 59",
    "sg:postcode":"17200",
    "sg:province":"Girona",
    "wof:name":"Guerrero Camacho Juan Antonio",
    "wof:placetype":"venue"
},
  "geometry": {"coordinates":[3.1629064083,41.9109420776],"type":"Point"}
}