{
  "type": "Feature",
  "properties": {
    "addr:full":"Avda Republica Argentina, 10 Le\u00f3n Le\u00f3n 24004",
    "addr:housenumber":"10",
    "addr:postcode":"24004",
    "addr:street":"Avda Republica Argentina;Leo\u0301N",
    "iso:country":"ES",
    "sg:address":"Avda Republica Argentina, 10",
    "sg:city":"Le\u00f3n",
    "sg:orig_category":"Empresas De Carpinter\u00cda",
    "sg:phone":"+34 987 20 33 03",
    "sg:postcode":"24004",
    "sg:province":"Le\u00f3n",
    "wof:name":"Bazar Radioelectrico Fama S.l.",
    "wof:placetype":"venue"
},
  "geometry": {"coordinates":[-5.573032856,42.5948753357],"type":"Point"}
}