{
  "type": "Feature",
  "properties": {
    "iso:country":"ES",
    "sg:address":"Carrer de Ocells, 6",
    "sg:city":"Palma",
    "sg:orig_category":"Materias Pl\u00c1sticas: Productos De Consumo Masivo (fabricaci\u00d3n, Al Por Mayor)",
    "sg:phone":"+34 971 73 72 14",
    "sg:postcode":"07011",
    "sg:province":"Islas Baleares",
    "wof:name":"Retosa C.b.",
    "wof:placetype":"venue"
},
  "geometry": {"coordinates":[2.6366651058,39.5813713074],"type":"Point"}
}