{
  "type": "Feature",
  "properties": {
    "iso:country":"ES",
    "sg:address":"Calle de Marques De Murrieta, 5",
    "sg:city":"Logro\u00f1o",
    "sg:orig_category":"Lencer\u00cda Femenina, Corseter\u00cda, Trajes De Ba\u00d1o (al Por Menor)",
    "sg:phone":"+34 941 22 11 37",
    "sg:postcode":"26005",
    "sg:province":"La Rioja",
    "wof:name":"Lenceria Anayvi Sc",
    "wof:placetype":"venue"
},
  "geometry": {"coordinates":[-2.4548389912,42.4651603699],"type":"Point"}
}