{
  "type": "Feature",
  "properties": {
    "iso:country":"ES",
    "sg:address":"Calle de Faustino Osorio, 29",
    "sg:city":"Madrid",
    "sg:orig_category":"Asesor\u00cda, Estudio Y Control Medioambiental",
    "sg:phone":"+34 915 26 46 00",
    "sg:postcode":"28047",
    "sg:province":"Madrid",
    "sg:website":"www.embio.es",
    "wof:name":"Equipamiento Medio Ambiental Y Biotecnologia S.l.",
    "wof:placetype":"venue"
},
  "geometry": {"coordinates":[-3.7316119671,40.4033813477],"type":"Point"}
}