{
  "type": "Feature",
  "properties": {
    "iso:country":"ES",
    "sg:address":"Calle de Perez De Rozas, 27",
    "sg:city":"Santa Cruz De Tenerife",
    "sg:orig_category":"M\u00c9dicos: Endocrinolog\u00cda Y Metabolismo",
    "sg:phone":"+34 922 28 27 50",
    "sg:postcode":"38004",
    "sg:province":"Santa Cruz De Tenerife",
    "wof:name":"Friend Sicilia Harry Ireneo",
    "wof:placetype":"venue"
},
  "geometry": {"coordinates":[-16.2585697174,28.4688987732],"type":"Point"}
}