{
  "type": "Feature",
  "properties": {
    "addr:full":"Carrer de Aribau, 9 Rubi Barcelona 08191",
    "addr:housenumber":"9",
    "addr:postcode":"08191",
    "addr:street":"Carrer De Aribau",
    "iso:country":"ES",
    "sg:address":"Carrer de Aribau, 9",
    "sg:city":"Rubi",
    "sg:orig_category":"Mercer\u00cda, Lencer\u00cda (al Por Menor)",
    "sg:phone":"+34 936 99 58 04",
    "sg:postcode":"08191",
    "sg:province":"Barcelona",
    "wof:name":"Mercera Puntades S.c. Particular",
    "wof:placetype":"venue"
},
  "geometry": {"coordinates":[2.0316240788,41.4919128418],"type":"Point"}
}