{
  "type": "Feature",
  "properties": {
    "addr:full":"Carrer de Llevant, 1 S. Adria Besos Barcelona 08930",
    "addr:housenumber":"1",
    "addr:postcode":"08930",
    "addr:street":"Carrer De Llevant;Barcelona",
    "iso:country":"ES",
    "sg:address":"Carrer de Llevant, 1",
    "sg:city":"S. Adria Besos",
    "sg:orig_category":"Asociaciones, Organismos Culturales Y Socioeducativos",
    "sg:phone":"+34 933 81 23 89",
    "sg:postcode":"08930",
    "sg:province":"Barcelona",
    "wof:name":"Centro Cultural Gitano De La Mina",
    "wof:placetype":"venue"
},
  "geometry": {"coordinates":[2.2231500149,41.4191589355],"type":"Point"}
}