{
  "type": "Feature",
  "properties": {
    "iso:country":"ES",
    "sg:address":"Calle de Jose Ruiz Ruiz, 37",
    "sg:city":"Caudete",
    "sg:orig_category":"Electricidad Veh\u00cdculo",
    "sg:phone":"+34 965 82 51 81",
    "sg:postcode":"02660",
    "sg:province":"Albacete",
    "wof:name":"Figueras Marti Josefa",
    "wof:placetype":"venue"
},
  "geometry": {"coordinates":[-0.9829890132,38.7065505981],"type":"Point"}
}