{
  "type": "Feature",
  "properties": {
    "iso:country":"ES",
    "sg:address":"Avda Artesanos (de Los), 62",
    "sg:city":"Tres Cantos",
    "sg:orig_category":"Ense\u00d1anza Variada",
    "sg:phone":"+34 918 03 60 01",
    "sg:postcode":"28760",
    "sg:province":"Madrid",
    "wof:name":"Ociorama Norte Sl",
    "wof:placetype":"venue"
},
  "geometry": {"coordinates":[-3.7088890076,40.6144828796],"type":"Point"}
}