{
  "type": "Feature",
  "properties": {
    "addr:full":"Calle de Santiago Maganto, 37 Pozuelo De Alarcon Madrid 28224",
    "addr:housenumber":"37",
    "addr:postcode":"28224",
    "addr:street":"Calle De Santiago Maganto",
    "iso:country":"ES",
    "sg:address":"Calle de Santiago Maganto, 37",
    "sg:city":"Pozuelo De Alarcon",
    "sg:classifiers":[
        {
            "category":"Professional",
            "subcategory":"Management & Consulting",
            "type":"Services"
        }
    ],
    "sg:phone":"+34 913 52 77 56",
    "sg:postcode":"28224",
    "sg:province":"Madrid",
    "sg:tags":[
        "asesor\u00cda",
        "en",
        "marketing"
    ],
    "wof:name":"Lodeiro Rey Jose",
    "wof:placetype":"venue"
},
  "geometry": {"coordinates":[-3.8032019138,40.4548492432],"type":"Point"}
}