{
  "type": "Feature",
  "properties": {
    "iso:country":"ES",
    "sg:address":"Ctra Mojon A Zeneta, Km. 0000,5",
    "sg:city":"Raiguero-la Villa",
    "sg:orig_category":"Negocio De Enlosados, Soler\u00cdas",
    "sg:phone":"+34 968 85 42 70",
    "sg:postcode":"30588",
    "sg:province":"Murcia",
    "wof:name":"Salvador Rodriguez Gomariz S.l.",
    "wof:placetype":"venue"
},
  "geometry": {"coordinates":[-0.9957690239,38.0119514465],"type":"Point"}
}