{
  "type": "Feature",
  "properties": {
    "iso:country":"ES",
    "sg:address":"Calle de Grandeza Espa\u00d1ola, 42",
    "sg:city":"Madrid",
    "sg:orig_category":"Droguer\u00cdas (al Por Menor)",
    "sg:phone":"+34 914 79 71 09",
    "sg:postcode":"28011",
    "sg:province":"Madrid",
    "wof:name":"Mantenimiento Cals S.l.",
    "wof:placetype":"venue"
},
  "geometry": {"coordinates":[-3.7324750423,40.4115333557],"type":"Point"}
}