{
  "type": "Feature",
  "properties": {
    "iso:country":"ES",
    "sg:address":"Po. Escolar, S/n",
    "sg:city":"Oropesa",
    "sg:orig_category":"Centros De Educaci\u00d3n Especial",
    "sg:phone":"+34 925 43 02 54",
    "sg:postcode":"45560",
    "sg:province":"Toledo",
    "wof:name":"Grupo Escolar Martin Gallinar",
    "wof:placetype":"venue"
},
  "geometry": {"coordinates":[-5.1782941818,39.9192237854],"type":"Point"}
}