{
  "type": "Feature",
  "properties": {
    "iso:country":"ES",
    "sg:address":"Carr Nadal Meroles, 18",
    "sg:city":"Lleida",
    "sg:orig_category":"Laboratorios Y Cl\u00cdnicas Veterinarias",
    "sg:phone":"+34 973 22 50 61",
    "sg:postcode":"25008",
    "sg:province":"Lleida",
    "wof:name":"Union De Mejora Genetica S.l.",
    "wof:placetype":"venue"
},
  "geometry": {"coordinates":[0.6210179925,41.6226615906],"type":"Point"}
}