{
  "type": "Feature",
  "properties": {
    "addr:full":"Carrer de Francesc Macia, 48 Suredes D'en Mairo-grecs-muntanyeta Girona 17480",
    "addr:housenumber":"48",
    "addr:postcode":"17480",
    "addr:street":"Carrer De Francesc Macia",
    "iso:country":"ES",
    "sg:address":"Carrer de Francesc Macia, 48",
    "sg:city":"Suredes D'en Mairo-grecs-muntanyeta",
    "sg:orig_category":"Cristaler\u00cdas",
    "sg:phone":"+34 972 25 33 92",
    "sg:postcode":"17480",
    "sg:province":"Girona",
    "wof:name":"Cristalerias Roses S.cv.",
    "wof:placetype":"venue"
},
  "geometry": {"coordinates":[2.8307719231,41.9969215393],"type":"Point"}
}