{
  "type": "Feature",
  "properties": {
    "addr:full":"Euskadi Etorbidea, S/n Pasai S. Pedro Guip\u00f9zcoa 20110",
    "addr:housenumber":"s",
    "addr:postcode":"20110",
    "addr:street":"Euskadi Etorbidea;/ N Pasai;Guipu\u0300Zcoa",
    "iso:country":"ES",
    "sg:address":"Euskadi Etorbidea, S/n",
    "sg:city":"Pasai S. Pedro",
    "sg:orig_category":"Iglesia Cat\u00d3lica",
    "sg:phone":"+34 943 39 03 17",
    "sg:postcode":"20110",
    "sg:province":"Guip\u00f9zcoa",
    "wof:name":"Parroquia Nuestra Se\u00f1ora Del Carmen",
    "wof:placetype":"venue"
},
  "geometry": {"coordinates":[-1.9300839901,43.3230705261],"type":"Point"}
}