{
  "type": "Feature",
  "properties": {
    "addr:full":"Calle de Ugarte, 22 Bilbao Vizcaya 48004",
    "addr:housenumber":"22",
    "addr:postcode":"48004",
    "addr:street":"Calle De Ugarte",
    "iso:country":"ES",
    "sg:address":"Calle de Ugarte, 22",
    "sg:city":"Bilbao",
    "sg:orig_category":"Peluquer\u00cdas, Peluquer\u00cda Mixta",
    "sg:phone":"+34 944 12 44 32",
    "sg:postcode":"48004",
    "sg:province":"Vizcaya",
    "wof:name":"Jose Ignacio Garcia Abad",
    "wof:placetype":"venue"
},
  "geometry": {"coordinates":[-2.9021780491,43.2596626282],"type":"Point"}
}