{
  "type": "Feature",
  "properties": {
    "addr:full":"Cami Moli, Des, 7 S. Antoni Portmany Islas Baleares 07820",
    "addr:postcode":"07820",
    "addr:street":"7 S. Antoni Portmany",
    "iso:country":"ES",
    "sg:address":"Cami Moli, Des, 7",
    "sg:city":"S. Antoni Portmany",
    "sg:orig_category":"Molduras, Junquillos, Listones Y Molduras Perforadas",
    "sg:phone":"+34 971 34 15 99",
    "sg:postcode":"07820",
    "sg:province":"Islas Baleares",
    "wof:name":"Cantoni Pera S.a.",
    "wof:placetype":"venue"
},
  "geometry": {"coordinates":[1.3046350479,38.9706878662],"type":"Point"}
}