{
  "type": "Feature",
  "properties": {
    "iso:country":"ES",
    "sg:address":"Carrer de Industria, 157",
    "sg:city":"Barcelona",
    "sg:orig_category":"Art\u00cdculos De Regalo (al Por Menor)",
    "sg:phone":"+34 934 35 71 57",
    "sg:postcode":"08025",
    "sg:province":"Barcelona",
    "wof:name":"Gadgets And Drinks S.l.",
    "wof:placetype":"venue"
},
  "geometry": {"coordinates":[2.1743779182,41.4095878601],"type":"Point"}
}