{
  "type": "Feature",
  "properties": {
    "addr:full":"Avda Chile, 13 Villanueva Serena Badajoz 06700",
    "addr:housenumber":"13",
    "addr:postcode":"06700",
    "addr:street":"Avda Chile",
    "iso:country":"ES",
    "sg:address":"Avda Chile, 13",
    "sg:city":"Villanueva Serena",
    "sg:orig_category":"Molduras, Junquillos, Listones Y Molduras Perforadas",
    "sg:phone":"+34 924 84 39 30",
    "sg:postcode":"06700",
    "sg:province":"Badajoz",
    "wof:name":"Borrego Hernandez Andres",
    "wof:placetype":"venue"
},
  "geometry": {"coordinates":[-5.7927408218,38.9731750488],"type":"Point"}
}