{
  "type": "Feature",
  "properties": {
    "addr:full":"Plaza De Los Valles, 5 Torrelavega Cantabria 39300",
    "addr:housenumber":"5",
    "addr:postcode":"39300",
    "addr:street":"Valles",
    "iso:country":"ES",
    "sg:address":"Plaza De Los Valles, 5",
    "sg:city":"Torrelavega",
    "sg:orig_category":"Panader\u00cdas, Panader\u00cdas",
    "sg:phone":"+34 942 80 22 26",
    "sg:postcode":"39300",
    "sg:province":"Cantabria",
    "wof:name":"Calvo Domingo Felipe",
    "wof:placetype":"venue"
},
  "geometry": {"coordinates":[-4.0533652306,43.3420524597],"type":"Point"}
}