{
  "type": "Feature",
  "properties": {
    "iso:country":"ES",
    "sg:address":"Calle de Autonomia, 18",
    "sg:city":"Sodupe",
    "sg:orig_category":"Fabricaci\u00d3n De Juguetes Autom\u00c1ticos",
    "sg:phone":"+34 946 69 23 36",
    "sg:postcode":"48830",
    "sg:province":"Vizcaya",
    "wof:name":"Erreka-ondo S.a.",
    "wof:placetype":"venue"
},
  "geometry": {"coordinates":[-3.0499193668,43.200466156],"type":"Point"}
}