{
  "type": "Feature",
  "properties": {
    "iso:country":"ES",
    "sg:address":"Avenida Del Paseo, S/n",
    "sg:city":"Villalon Campos",
    "sg:orig_category":"Centros De Educaci\u00d3n Especial",
    "sg:phone":"+34 983 74 01 85",
    "sg:postcode":"47600",
    "sg:province":"Valladolid",
    "wof:name":"Colegio Publico Tierra De Campos",
    "wof:placetype":"venue"
},
  "geometry": {"coordinates":[-5.0293889046,42.099521637],"type":"Point"}
}