{
  "type": "Feature",
  "properties": {
    "iso:country":"ES",
    "sg:address":"Carrer de Gloria, 5",
    "sg:city":"Hospitalet Llobregat",
    "sg:orig_category":"Art\u00cdculos De Decoraci\u00d3n",
    "sg:phone":"+34 932 96 63 78",
    "sg:postcode":"08902",
    "sg:province":"Barcelona",
    "wof:name":"Atenbric S.l.",
    "wof:placetype":"venue"
},
  "geometry": {"coordinates":[2.1190509796,41.3674125671],"type":"Point"}
}