{
  "type": "Feature",
  "properties": {
    "iso:country":"ES",
    "sg:address":"Fra Francesc D'eiximenis, 14",
    "sg:city":"Parets Del Valles",
    "sg:orig_category":"Institutos De Belleza",
    "sg:phone":"+34 935 62 46 55",
    "sg:postcode":"08150",
    "sg:province":"Barcelona",
    "wof:name":"Gausachs Manzano Laura",
    "wof:placetype":"venue"
},
  "geometry": {"coordinates":[2.2296199799,41.5624351501],"type":"Point"}
}