{
  "type": "Feature",
  "properties": {
    "iso:country":"ES",
    "sg:address":"Urb Residencial Gelves-guadalquivir, S/n",
    "sg:city":"Gelves",
    "sg:orig_category":"Comercio, Reparaci\u00d3n De Motocicletas, Bicicletas Y Piezas Sueltas",
    "sg:phone":"+34 955 76 13 22",
    "sg:postcode":"41120",
    "sg:province":"Sevilla",
    "wof:name":"Romero Mu\u00f1oz Maria Dolores",
    "wof:placetype":"venue"
},
  "geometry": {"coordinates":[-6.0274190903,37.3452682495],"type":"Point"}
}