{
  "type": "Feature",
  "properties": {
    "addr:full":"Calle de Linares, 33 Valladolid Valladolid 47010",
    "addr:housenumber":"33",
    "addr:postcode":"47010",
    "addr:street":"Calle De Linares",
    "iso:country":"ES",
    "sg:address":"Calle de Linares, 33",
    "sg:city":"Valladolid",
    "sg:orig_category":"Molduras, Junquillos, Listones Y Molduras Perforadas",
    "sg:phone":"+34 983 26 46 31",
    "sg:postcode":"47010",
    "sg:province":"Valladolid",
    "wof:name":"Garcia Alvarez Francisco",
    "wof:placetype":"venue"
},
  "geometry": {"coordinates":[-4.7219939232,41.6622467041],"type":"Point"}
}