{
  "type": "Feature",
  "properties": {
    "addr:full":"Poli Ciudad Del Transporte, 3 San Juan De Mozarrifar Zaragoza 50820",
    "addr:housenumber":"3",
    "addr:postcode":"50820",
    "addr:street":"Transporte;Juan De Mozarrifar",
    "iso:country":"ES",
    "sg:address":"Poli Ciudad Del Transporte, 3",
    "sg:city":"San Juan De Mozarrifar",
    "sg:orig_category":"Agencias De Aduana",
    "sg:phone":"+34 976 58 76 68",
    "sg:postcode":"50820",
    "sg:province":"Zaragoza",
    "sg:website":"aduana2000@teleline.es",
    "wof:name":"Aduanas 2000 S.a.",
    "wof:placetype":"venue"
},
  "geometry": {"coordinates":[-0.8407598138,41.7179450989],"type":"Point"}
}