{
  "type": "Feature",
  "properties": {
    "addr:full":"Calle de Nueva, 6 Cabeza Buey Badajoz 06600",
    "addr:housenumber":"6",
    "addr:postcode":"06600",
    "addr:street":"Calle De Nueva",
    "iso:country":"ES",
    "sg:address":"Calle de Nueva, 6",
    "sg:city":"Cabeza Buey",
    "sg:orig_category":"Asesor\u00cda Sobre Comunicaci\u00d3n De Empresas",
    "sg:phone":"+34 924 60 09 25",
    "sg:postcode":"06600",
    "sg:province":"Badajoz",
    "wof:name":"Agustin Vilaplana S.l.",
    "wof:placetype":"venue"
},
  "geometry": {"coordinates":[-5.2198243141,38.72133255],"type":"Point"}
}