{
  "type": "Feature",
  "properties": {
    "iso:country":"ES",
    "sg:address":"Carrer de Igualada, 4",
    "sg:city":"Playa De Calafell",
    "sg:orig_category":"Comercio, Reparaci\u00d3n De Motocicletas, Bicicletas Y Piezas Sueltas",
    "sg:phone":"+34 977 69 12 59",
    "sg:postcode":"43820",
    "sg:province":"Tarragona",
    "wof:name":"Seisdedos Infante Juan Manuel",
    "wof:placetype":"venue"
},
  "geometry": {"coordinates":[1.5677280426,41.1877822876],"type":"Point"}
}