{
  "type": "Feature",
  "properties": {
    "addr:full":"Carr Santa Caterina, 14 Villarreal Castell\u00f3n 12540",
    "addr:housenumber":"14",
    "addr:postcode":"12540",
    "addr:street":"Carr Santa Caterina",
    "iso:country":"ES",
    "sg:address":"Carr Santa Caterina, 14",
    "sg:city":"Villarreal",
    "sg:orig_category":"Cerrajer\u00cda, Ferrallista",
    "sg:phone":"+34 964 52 29 66",
    "sg:postcode":"12540",
    "sg:province":"Castell\u00f3n",
    "wof:name":"Andres Ferrer Antonio",
    "wof:placetype":"venue"
},
  "geometry": {"coordinates":[-0.0976291969,39.9421157837],"type":"Point"}
}