{
  "type": "Feature",
  "properties": {
    "iso:country":"ES",
    "sg:address":"Avda Malaga, 30",
    "sg:city":"Ronda",
    "sg:orig_category":"Inmobiliaria (agencias)",
    "sg:phone":"+34 952 87 67 50",
    "sg:postcode":"29400",
    "sg:province":"M\u00e1laga",
    "wof:name":"Tecnocasa Estudio Ronda Sl",
    "wof:placetype":"venue"
},
  "geometry": {"coordinates":[-5.1542539597,36.7488632202],"type":"Point"}
}