{
  "type": "Feature",
  "properties": {
    "iso:country":"ES",
    "sg:address":"Calle de Prosperidad, 16",
    "sg:city":"Cortes",
    "sg:orig_category":"Empresas De Carpinter\u00cda Met\u00c1lica",
    "sg:phone":"+34 948 80 03 99",
    "sg:postcode":"31530",
    "sg:province":"Navarra",
    "wof:name":"Alcega Cerdan Carlos",
    "wof:placetype":"venue"
},
  "geometry": {"coordinates":[-1.4224607944,41.9247817993],"type":"Point"}
}