{
  "type": "Feature",
  "properties": {
    "addr:full":"Calle de Felix Pizcueta, 23 Valencia Valencia 46004",
    "addr:housenumber":"23",
    "addr:postcode":"46004",
    "addr:street":"Calle De Felix Pizcueta",
    "iso:country":"ES",
    "sg:address":"Calle de Felix Pizcueta, 23",
    "sg:city":"Valencia",
    "sg:orig_category":"Mercer\u00cda, Lencer\u00cda (al Por Menor)",
    "sg:phone":"+34 963 51 01 99",
    "sg:postcode":"46004",
    "sg:province":"Valencia",
    "wof:name":"Carmen Ramon Ros E Inmaculada Irlan Ferrer Cdad.",
    "wof:placetype":"venue"
},
  "geometry": {"coordinates":[-0.3725059927,39.4663963318],"type":"Point"}
}