{
  "type": "Feature",
  "properties": {
    "iso:country":"ES",
    "sg:address":"Calle de Salvador Salva, 1",
    "sg:city":"Javea",
    "sg:orig_category":"Asesor\u00cda Fiscal Y Jur\u00cddica",
    "sg:phone":"+34 966 46 26 53",
    "sg:postcode":"03730",
    "sg:province":"Alicante",
    "wof:name":"Webster Asesores S.l.",
    "wof:placetype":"venue"
},
  "geometry": {"coordinates":[0.1697950065,38.7895088196],"type":"Point"}
}