{
  "type": "Feature",
  "properties": {
    "iso:country":"ES",
    "sg:address":"Cmno Cementerio, S/n",
    "sg:city":"Cuellar",
    "sg:orig_category":"Muebles Y Accesorios Para Cocinas Y Cuartos De Ba\u00d1o (al Por Menor)",
    "sg:phone":"+34 921 14 16 25",
    "sg:postcode":"40200",
    "sg:province":"Segovia",
    "wof:name":"Sancho Espeso Fernando",
    "wof:placetype":"venue"
},
  "geometry": {"coordinates":[-4.322247982,41.4066505432],"type":"Point"}
}