{
  "type": "Feature",
  "properties": {
    "addr:full":"Vista Bella, 14 Berrioplano Navarra 31195",
    "addr:housenumber":"14",
    "addr:postcode":"31195",
    "addr:street":"Vista Bella",
    "iso:country":"ES",
    "sg:address":"Vista Bella, 14",
    "sg:city":"Berrioplano",
    "sg:orig_category":"Metalizados",
    "sg:phone":"+34 948 30 31 19",
    "sg:postcode":"31195",
    "sg:province":"Navarra",
    "wof:name":"Lecumberri Martinez Francisco Javier Y Redin Palacios Francisco S.cv",
    "wof:placetype":"venue"
},
  "geometry": {"coordinates":[-1.6867979765,42.8470611572],"type":"Point"}
}