{
  "type": "Feature",
  "properties": {
    "addr:full":"Calle de Doctor Moreno, 24 Valladolid Valladolid 47008",
    "addr:housenumber":"24",
    "addr:postcode":"47008",
    "addr:street":"Calle De Doctor Moreno",
    "iso:country":"ES",
    "sg:address":"Calle de Doctor Moreno, 24",
    "sg:city":"Valladolid",
    "sg:orig_category":"Tiendas De Grano, Frutas Y Legumbres Secas (al Por Menor)",
    "sg:phone":"+34 983 22 00 92",
    "sg:postcode":"47008",
    "sg:province":"Valladolid",
    "wof:name":"Perez Fernandez Maria Covadonga",
    "wof:placetype":"venue"
},
  "geometry": {"coordinates":[-4.7407708168,41.6252174377],"type":"Point"}
}