{
  "type": "Feature",
  "properties": {
    "iso:country":"ES",
    "sg:address":"La Esperanza, S/n",
    "sg:city":"Loja",
    "sg:orig_category":"Estudios Y Construcci\u00d3n De Acuarios Y Viveros",
    "sg:phone":"+34 958 32 37 05",
    "sg:postcode":"18300",
    "sg:province":"Granada",
    "wof:name":"Piscifactorias Andaluzas S. A.",
    "wof:placetype":"venue"
},
  "geometry": {"coordinates":[-4.1293940544,37.1738243103],"type":"Point"}
}