{
  "type": "Feature",
  "properties": {
    "addr:full":"Calle de Almirante Ferrandiz, 30 Nerja M\u00e1laga 29780",
    "addr:housenumber":"30",
    "addr:postcode":"29780",
    "addr:street":"Calle De Almirante Ferrandiz",
    "iso:country":"ES",
    "sg:address":"Calle de Almirante Ferrandiz, 30",
    "sg:city":"Nerja",
    "sg:orig_category":"Bazares, Art\u00cdculos De Limpieza Y De Cocina (al Por Menor)",
    "sg:phone":"+34 952 52 73 45",
    "sg:postcode":"29780",
    "sg:province":"M\u00e1laga",
    "wof:name":"El Khalifi  Abdali",
    "wof:placetype":"venue"
},
  "geometry": {"coordinates":[-3.8755459785,36.7466278076],"type":"Point"}
}