{
  "type": "Feature",
  "properties": {
    "addr:full":"Calle de Plaza (la), 7 Mures Ja\u00e9n 23686",
    "addr:housenumber":"7",
    "addr:postcode":"23686",
    "addr:street":"Calle De Plaza La;Jae\u0301N",
    "iso:country":"ES",
    "sg:address":"Calle de Plaza (la), 7",
    "sg:city":"Mures",
    "sg:orig_category":"Pescader\u00cdas (al Por Menor)",
    "sg:phone":"+34 953 59 55 28",
    "sg:postcode":"23686",
    "sg:province":"Ja\u00e9n",
    "wof:name":"Garcia Perez Ramona",
    "wof:placetype":"venue"
},
  "geometry": {"coordinates":[-3.8691298962,37.4061050415],"type":"Point"}
}