{
  "type": "Feature",
  "properties": {
    "iso:country":"ES",
    "sg:address":"Avda Brasil, 30",
    "sg:city":"Madrid",
    "sg:orig_category":"Asociaciones, Organismos Culturales Y Socioeducativos",
    "sg:phone":"+34 915 97 05 14",
    "sg:postcode":"28020",
    "sg:province":"Madrid",
    "wof:name":"Fundacion Alfonso Martin Escudero",
    "wof:placetype":"venue"
},
  "geometry": {"coordinates":[-3.6930971146,40.4567604065],"type":"Point"}
}