{
  "type": "Feature",
  "properties": {
    "addr:full":"Calle de Via Cornelia, 5 Santander Cantabria 39001",
    "addr:housenumber":"5",
    "addr:postcode":"39001",
    "addr:street":"Calle De Via Cornelia",
    "iso:country":"ES",
    "sg:address":"Calle de Via Cornelia, 5",
    "sg:city":"Santander",
    "sg:orig_category":"Panader\u00cdas, Panader\u00cdas",
    "sg:phone":"+34 942 37 49 62",
    "sg:postcode":"39001",
    "sg:province":"Cantabria",
    "wof:name":"Celador Jimenez Maria Del Mar",
    "wof:placetype":"venue"
},
  "geometry": {"coordinates":[-3.8114750385,43.4647827148],"type":"Point"}
}