{
  "type": "Feature",
  "properties": {
    "iso:country":"ES",
    "sg:address":"J. Antonio, 2",
    "sg:city":"Alamedilla",
    "sg:orig_category":"Iglesia Cat\u00d3lica",
    "sg:phone":"+34 958 39 25 06",
    "sg:postcode":"18520",
    "sg:province":"Granada",
    "wof:name":"Obispado De Guadix",
    "wof:placetype":"venue"
},
  "geometry": {"coordinates":[-3.2447559834,37.5830001831],"type":"Point"}
}