{
  "type": "Feature",
  "properties": {
    "iso:country":"ES",
    "sg:address":"Rond Collsalarca, 187",
    "sg:city":"Sabadell",
    "sg:orig_category":"Agentes, Concesionarios Y Sucursales De Veh\u00cdculos",
    "sg:phone":"+34 937 16 88 96",
    "sg:postcode":"08207",
    "sg:province":"Barcelona",
    "sg:website":"www.barrinet.net/autoformula",
    "wof:name":"Auto Formula Del Valles S.l.",
    "wof:placetype":"venue"
},
  "geometry": {"coordinates":[2.0911726952,41.5690345764],"type":"Point"}
}