{
  "type": "Feature",
  "properties": {
    "iso:country":"ES",
    "sg:address":"Carr S Marti De Tous, 2",
    "sg:city":"Igualada",
    "sg:orig_category":"Inmobiliaria (agencias)",
    "sg:phone":"+34 938 03 97 51",
    "sg:postcode":"08700",
    "sg:province":"Barcelona",
    "wof:name":"Finques Agramunt S.c.p.",
    "wof:placetype":"venue"
},
  "geometry": {"coordinates":[1.6182310581,41.5878067017],"type":"Point"}
}