{
  "type": "Feature",
  "properties": {
    "iso:country":"ES",
    "sg:address":"Calle de Francisco Ruesta, 7",
    "sg:city":"Zaragoza",
    "sg:orig_category":"Cristaler\u00cdas",
    "sg:phone":"+34 976 34 10 71",
    "sg:postcode":"50011",
    "sg:province":"Zaragoza",
    "wof:name":"Navarro Del Cacho Jorge",
    "wof:placetype":"venue"
},
  "geometry": {"coordinates":[-0.9218459129,41.6535797119],"type":"Point"}
}