{
  "type": "Feature",
  "properties": {
    "iso:country":"ES",
    "sg:address":"Avda Republica Argentina, 38",
    "sg:city":"Logro\u00f1o",
    "sg:orig_category":"Electrodom\u00c9sticos (al Por Menor)",
    "sg:phone":"+34 941 24 52 18",
    "sg:postcode":"26002",
    "sg:province":"La Rioja",
    "wof:name":"Ezquerro Calleja Armando",
    "wof:placetype":"venue"
},
  "geometry": {"coordinates":[-2.4493830204,42.4608459473],"type":"Point"}
}