{
  "type": "Feature",
  "properties": {
    "addr:full":"Avda Calvo Sotelo, S/n Huetor-tajar Granada 18360",
    "addr:housenumber":"s / n",
    "addr:postcode":"18360",
    "addr:street":"Avda Calvo Sotelo",
    "iso:country":"ES",
    "sg:address":"Avda Calvo Sotelo, S/n",
    "sg:city":"Huetor-tajar",
    "sg:orig_category":"Electricidad (montaje, Ensamblaje De Componentes)",
    "sg:phone":"+34 958 33 24 33",
    "sg:postcode":"18360",
    "sg:province":"Granada",
    "wof:name":"Jaimez Lopez Manuel",
    "wof:placetype":"venue"
},
  "geometry": {"coordinates":[-4.0477142334,37.199634552],"type":"Point"}
}