{
  "type": "Feature",
  "properties": {
    "iso:country":"ES",
    "sg:address":"Carr Castell De Solterra, 8",
    "sg:city":"Girona",
    "sg:orig_category":"Empresarios",
    "sg:phone":"+34 972 41 15 74",
    "sg:postcode":"17003",
    "sg:province":"Girona",
    "wof:name":"Pardillo Alvarez Manuel Pedro",
    "wof:placetype":"venue"
},
  "geometry": {"coordinates":[2.8272459507,41.9726753235],"type":"Point"}
}