{
  "type": "Feature",
  "properties": {
    "iso:country":"ES",
    "sg:address":"Rbla Rambla, 18",
    "sg:city":"Figueres",
    "sg:orig_category":"Librer\u00cdas",
    "sg:phone":"+34 972 50 02 27",
    "sg:postcode":"17600",
    "sg:province":"Girona",
    "wof:name":"Masdevall Moncanut Jose",
    "wof:placetype":"venue"
},
  "geometry": {"coordinates":[2.959952116,42.2659721375],"type":"Point"}
}