{
  "type": "Feature",
  "properties": {
    "iso:country":"ES",
    "sg:address":"Carr Barcelona, 17",
    "sg:city":"Girona",
    "sg:orig_category":"M\u00c9dicos: Estomatolog\u00cda",
    "sg:phone":"+34 972 22 13 99",
    "sg:postcode":"17002",
    "sg:province":"Girona",
    "wof:name":"Lloran Gallego Rodrigo",
    "wof:placetype":"venue"
},
  "geometry": {"coordinates":[2.8187849522,41.9805641174],"type":"Point"}
}