{
  "type": "Feature",
  "properties": {
    "iso:country":"ES",
    "sg:address":"Calle de Nieremberg, 17",
    "sg:city":"Madrid",
    "sg:orig_category":"Inform\u00c1tica Equipo Y Programas (al Por Mayor)",
    "sg:phone":"+34 915 19 44 86",
    "sg:postcode":"28002",
    "sg:province":"Madrid",
    "wof:name":"Efe Uno Consultores De Gestion Y Software S.l.",
    "wof:placetype":"venue"
},
  "geometry": {"coordinates":[-3.6718509197,40.4474029541],"type":"Point"}
}