{
  "type": "Feature",
  "properties": {
    "addr:full":"Villa Matilde, Km. 0006,0 Villarrubia C\u00f3rdoba 14710",
    "addr:postcode":"14710",
    "addr:street":"Km. 0006,0 Villarrubia Co\u0301Rdoba",
    "iso:country":"ES",
    "sg:address":"Villa Matilde, Km. 0006,0",
    "sg:city":"Villarrubia",
    "sg:orig_category":"Limpieza Industrial",
    "sg:phone":"+34 957 32 77 84",
    "sg:postcode":"14710",
    "sg:province":"C\u00f3rdoba",
    "wof:name":"Lavanderia Industrial Rubio S.r.l",
    "wof:placetype":"venue"
},
  "geometry": {"coordinates":[-4.9146289825,37.8490753174],"type":"Point"}
}