{
  "type": "Feature",
  "properties": {
    "iso:country":"ES",
    "sg:address":"Avda Laza (de), Km. 0001,0",
    "sg:city":"Verin",
    "sg:orig_category":"Promotores Constructores",
    "sg:phone":"+34 988 41 10 48",
    "sg:postcode":"32600",
    "sg:province":"Ourense",
    "wof:name":"Granitos De Verin S. L.",
    "wof:placetype":"venue"
},
  "geometry": {"coordinates":[-7.433760643,41.9456787109],"type":"Point"}
}