{
  "type": "Feature",
  "properties": {
    "addr:full":"Pl. Europa, S/n La Linea C\u00e1diz 11300",
    "addr:housenumber":"s / n",
    "addr:postcode":"11300",
    "addr:street":"Pl. Europa;La Linea Ca\u0301Diz",
    "iso:country":"ES",
    "sg:address":"Pl. Europa, S/n",
    "sg:city":"La Linea",
    "sg:orig_category":"Fabricaci\u00d3n De Art\u00cdculos Para Papeler\u00cdas",
    "sg:phone":"+34 956 17 68 79",
    "sg:postcode":"11300",
    "sg:province":"C\u00e1diz",
    "wof:name":"Aldanondo Cruz Aurelio",
    "wof:placetype":"venue"
},
  "geometry": {"coordinates":[-5.3501858711,36.1577835083],"type":"Point"}
}