{
  "type": "Feature",
  "properties": {
    "addr:full":"Calle de Portuene, 9 Donostia-san Sebastian Guip\u00f9zcoa 20008",
    "addr:housenumber":"9",
    "addr:postcode":"20008",
    "addr:street":"Calle De Portuene",
    "iso:country":"ES",
    "sg:address":"Calle de Portuene, 9",
    "sg:city":"Donostia-san Sebastian",
    "sg:orig_category":"Explosivos",
    "sg:phone":"+34 943 21 86 09",
    "sg:postcode":"20008",
    "sg:province":"Guip\u00f9zcoa",
    "wof:name":"Perforaciones Laka S.a.",
    "wof:placetype":"venue"
},
  "geometry": {"coordinates":[-1.9979569912,43.3102073669],"type":"Point"}
}