{
  "type": "Feature",
  "properties": {
    "iso:country":"ES",
    "sg:address":"Carrer de Francesc Layret, 45",
    "sg:city":"Mollet Valles",
    "sg:orig_category":"Peluqueros: De Se\u00d1oras",
    "sg:phone":"+34 935 70 41 89",
    "sg:postcode":"08100",
    "sg:province":"Barcelona",
    "wof:name":"Vilchez Bueno Pilar",
    "wof:placetype":"venue"
},
  "geometry": {"coordinates":[2.2041549683,41.5454139709],"type":"Point"}
}