{
  "type": "Feature",
  "properties": {
    "iso:country":"ES",
    "sg:address":"Calle de Rafael Salgado, 17",
    "sg:city":"Sevilla",
    "sg:orig_category":"Peluqueros: De Se\u00d1oras",
    "sg:phone":"+34 954 61 87 53",
    "sg:postcode":"41013",
    "sg:province":"Sevilla",
    "wof:name":"Nati Y Ali Peluqueria Y Belleza S.l.",
    "wof:placetype":"venue"
},
  "geometry": {"coordinates":[-5.9782071114,37.3599243164],"type":"Point"}
}