{
  "type": "Feature",
  "properties": {
    "addr:full":"Avda Alicante, 47 Denia Alicante 03700",
    "addr:housenumber":"47",
    "addr:postcode":"03700",
    "addr:street":"Avda Alicante",
    "iso:country":"ES",
    "sg:address":"Avda Alicante, 47",
    "sg:city":"Denia",
    "sg:orig_category":"Empresas De Limpieza",
    "sg:phone":"+34 966 42 70 68",
    "sg:postcode":"03700",
    "sg:province":"Alicante",
    "wof:name":"Netejes Cristall-net S.l.",
    "wof:placetype":"venue"
},
  "geometry": {"coordinates":[0.1005209982,38.8387565613],"type":"Point"}
}