{
  "type": "Feature",
  "properties": {
    "addr:full":"Calle de Lagrima, 7 Malaga M\u00e1laga 29014",
    "addr:housenumber":"7",
    "addr:postcode":"29014",
    "addr:street":"Calle De Lagrima;Ma\u0301Laga",
    "iso:country":"ES",
    "sg:address":"Calle de Lagrima, 7",
    "sg:city":"Malaga",
    "sg:orig_category":"Contenedores (mercanc\u00cdas)",
    "sg:phone":"+34 952 25 83 47",
    "sg:postcode":"29014",
    "sg:province":"M\u00e1laga",
    "wof:name":"Rojas Escalona Juan Miguel",
    "wof:placetype":"venue"
},
  "geometry": {"coordinates":[-4.4161510468,36.7464141846],"type":"Point"}
}