{
  "type": "Feature",
  "properties": {
    "iso:country":"ES",
    "sg:address":"Pg Vint-i-dos De Juliol, 406",
    "sg:city":"Terrassa",
    "sg:orig_category":"Droguer\u00cdas (al Por Menor)",
    "sg:phone":"+34 937 83 57 33",
    "sg:postcode":"08221",
    "sg:province":"Barcelona",
    "wof:name":"Buron Alcolea Antonio",
    "wof:placetype":"venue"
},
  "geometry": {"coordinates":[2.0148038864,41.5696754456],"type":"Point"}
}