{
  "type": "Feature",
  "properties": {
    "iso:country":"ES",
    "sg:address":"Rua Coru\u00d1a, S/n",
    "sg:city":"Vigo",
    "sg:orig_category":"Carnicer\u00cdas, Carnicer\u00cdas",
    "sg:phone":"+34 986 23 96 56",
    "sg:postcode":"36208",
    "sg:province":"Pontevedra",
    "wof:name":"Pintos Comesa\u00f1a Manuel Fernando",
    "wof:placetype":"venue"
},
  "geometry": {"coordinates":[-8.7374687195,42.2263908386],"type":"Point"}
}