{
  "type": "Feature",
  "properties": {
    "addr:full":"Calle de Vinaroz, 12 Madrid Madrid 28002",
    "addr:housenumber":"12",
    "addr:postcode":"madrid;28002",
    "addr:street":"Calle De Vinaroz",
    "iso:country":"ES",
    "sg:address":"Calle de Vinaroz, 12",
    "sg:city":"Madrid",
    "sg:orig_category":"Financiaci\u00d3n Y Cr\u00c9ditos",
    "sg:phone":"+34 915 19 55 81",
    "sg:postcode":"28002",
    "sg:province":"Madrid",
    "wof:name":"Jacel Creditos S.l.",
    "wof:placetype":"venue"
},
  "geometry": {"coordinates":[-3.6760919094,40.4460678101],"type":"Point"}
}