{
  "type": "Feature",
  "properties": {
    "iso:country":"ES",
    "sg:address":"Carrer de Bartomeu Robert, 44",
    "sg:city":"Mollet Valles",
    "sg:orig_category":"Alquiler De Climatizadores",
    "sg:phone":"+34 935 70 66 28",
    "sg:postcode":"08100",
    "sg:province":"Barcelona",
    "wof:name":"Everest Climatizacion S.l.",
    "wof:placetype":"venue"
},
  "geometry": {"coordinates":[2.2170479298,41.5421485901],"type":"Point"}
}