{
  "type": "Feature",
  "properties": {
    "addr:full":"Calle de Frailes (de Los), 118 Colmenar Viejo Madrid 28770",
    "addr:housenumber":"118",
    "addr:postcode":"28770",
    "addr:street":"Calle De Frailes De Los",
    "iso:country":"ES",
    "sg:address":"Calle de Frailes (de Los), 118",
    "sg:city":"Colmenar Viejo",
    "sg:orig_category":"Peluquer\u00cdas, Peluquer\u00cda Mixta",
    "sg:phone":"+34 918 45 65 08",
    "sg:postcode":"28770",
    "sg:province":"Madrid",
    "wof:name":"Ruiz Berzosa Fernando",
    "wof:placetype":"venue"
},
  "geometry": {"coordinates":[-3.7705450058,40.6655082703],"type":"Point"}
}