{
  "type": "Feature",
  "properties": {
    "iso:country":"ES",
    "sg:address":"Avda Juan Carlos I, 12",
    "sg:city":"Herrera Duque",
    "sg:orig_category":"Comercio De Piezas De Recambio Y De Accesorios De Veh\u00cdculos, Veh\u00cdculos Industriales",
    "sg:phone":"+34 924 65 08 26",
    "sg:postcode":"06670",
    "sg:province":"Badajoz",
    "wof:name":"Sa\u00f1udo Jimenez Jose Javier",
    "wof:placetype":"venue"
},
  "geometry": {"coordinates":[-5.046795845,39.170665741],"type":"Point"}
}