{
  "type": "Feature",
  "properties": {
    "iso:country":"ES",
    "sg:address":"Pl Pere San, S/n",
    "sg:city":"S. Cugat Valles",
    "sg:orig_category":"Pescader\u00cdas (al Por Menor)",
    "sg:phone":"+34 936 74 86 01",
    "sg:postcode":"08172",
    "sg:province":"Barcelona",
    "wof:name":"Pujol Coronado Rosa",
    "wof:placetype":"venue"
},
  "geometry": {"coordinates":[2.0822649002,41.4730415344],"type":"Point"}
}