{
  "type": "Feature",
  "properties": {
    "iso:country":"ES",
    "sg:address":"Carr Magi Morera, 17",
    "sg:city":"Lleida",
    "sg:orig_category":"Agricultores, Agricultores",
    "sg:phone":"+34 973 26 88 59",
    "sg:postcode":"25006",
    "sg:province":"Lleida",
    "wof:name":"Integraciones Y Explotaciones Bergua S.l.",
    "wof:placetype":"venue"
},
  "geometry": {"coordinates":[0.6164360046,41.6173248291],"type":"Point"}
}