{
  "type": "Feature",
  "properties": {
    "addr:full":"Av Gran Via De Valencia, 8 Mutxamel Alicante 03110",
    "addr:housenumber":"8",
    "addr:postcode":"03110",
    "addr:street":"Av Gran Via De Valencia",
    "iso:country":"ES",
    "sg:address":"Av Gran Via De Valencia, 8",
    "sg:city":"Mutxamel",
    "sg:orig_category":"Papeler\u00cdas, Librer\u00cdas",
    "sg:phone":"+34 965 95 21 93",
    "sg:postcode":"03110",
    "sg:province":"Alicante",
    "wof:name":"El Palau S.c.",
    "wof:placetype":"venue"
},
  "geometry": {"coordinates":[-0.4457679987,38.4177894592],"type":"Point"}
}