{
  "type": "Feature",
  "properties": {
    "iso:country":"ES",
    "sg:address":"Calle de Treviana, S/n",
    "sg:city":"Madrid",
    "sg:orig_category":"Polideportivos",
    "sg:phone":"+34 914 16 42 59",
    "sg:postcode":"28043",
    "sg:province":"Madrid",
    "wof:name":"Iam Informatica Del Ayuntamiento De Madrid",
    "wof:placetype":"venue"
},
  "geometry": {"coordinates":[-3.6590089798,40.4498672485],"type":"Point"}
}