{
  "type": "Feature",
  "properties": {
    "iso:country":"ES",
    "sg:address":"Calle de Emilio Castelar, 19",
    "sg:city":"Algeciras",
    "sg:orig_category":"Bisuter\u00cda, Joyer\u00cda, Relojer\u00cda (al Por Menor)",
    "sg:phone":"+34 956 66 35 43",
    "sg:postcode":"11201",
    "sg:province":"C\u00e1diz",
    "wof:name":"Algecor S L",
    "wof:placetype":"venue"
},
  "geometry": {"coordinates":[-5.4471354485,36.1288299561],"type":"Point"}
}