{
  "type": "Feature",
  "properties": {
    "iso:country":"ES",
    "sg:address":"Calle de Palacio Valdes, 7",
    "sg:city":"Valladolid",
    "sg:orig_category":"Peluqueros: De Se\u00d1oras",
    "sg:phone":"+34 983 29 63 70",
    "sg:postcode":"47005",
    "sg:province":"Valladolid",
    "wof:name":"Gonzalez Monedero Maria Del Carmen",
    "wof:placetype":"venue"
},
  "geometry": {"coordinates":[-4.7123022079,41.6520309448],"type":"Point"}
}