{
  "type": "Feature",
  "properties": {
    "addr:full":"Calle de Calderon De La Barca, 2 San Bartolome Murcia 30001",
    "addr:housenumber":"2",
    "addr:postcode":"30001",
    "addr:street":"Calle De Calderon De La Barca",
    "iso:country":"ES",
    "sg:address":"Calle de Calderon De La Barca, 2",
    "sg:city":"San Bartolome",
    "sg:orig_category":"Bisuter\u00cda, Joyer\u00cda, Relojer\u00cda (al Por Menor)",
    "sg:phone":"+34 968 22 32 17",
    "sg:postcode":"30001",
    "sg:province":"Murcia",
    "wof:name":"El Pericante S.l.",
    "wof:placetype":"venue"
},
  "geometry": {"coordinates":[-0.4617904127,38.4436988831],"type":"Point"}
}