{
  "type": "Feature",
  "properties": {
    "addr:full":"Calle de Puerta De Berrozana, 4 Plasencia C\u00e1ceres 10600",
    "addr:housenumber":"4",
    "addr:postcode":"10600",
    "addr:street":"Calle De Puerta De Berrozana;Ca\u0301Ceres",
    "iso:country":"ES",
    "sg:address":"Calle de Puerta De Berrozana, 4",
    "sg:city":"Plasencia",
    "sg:orig_category":"Empresas De Carpinter\u00cda",
    "sg:phone":"+34 927 41 32 65",
    "sg:postcode":"10600",
    "sg:province":"C\u00e1ceres",
    "wof:name":"Garzon Gallego Jesus Maria",
    "wof:placetype":"venue"
},
  "geometry": {"coordinates":[-6.0929288864,40.0302391052],"type":"Point"}
}