{
  "type": "Feature",
  "properties": {
    "iso:country":"ES",
    "sg:address":"Rua Galicia, 15",
    "sg:city":"Noia",
    "sg:orig_category":"Ingeniero",
    "sg:phone":"+34 981 82 57 13",
    "sg:postcode":"15200",
    "sg:province":"La Coru\u00f1a",
    "wof:name":"Barreiro Carre\u00f1o Juan Ramon",
    "wof:placetype":"venue"
},
  "geometry": {"coordinates":[-8.8864488602,42.7847709656],"type":"Point"}
}