{
  "type": "Feature",
  "properties": {
    "addr:full":"Calle de Belchite, 15 S. Pedro Pinatar Murcia 30740",
    "addr:housenumber":"15",
    "addr:postcode":"30740",
    "addr:street":"Calle De Belchite;S. Pedro",
    "iso:country":"ES",
    "sg:address":"Calle de Belchite, 15",
    "sg:city":"S. Pedro Pinatar",
    "sg:orig_category":"Electricidad, Electr\u00d3nica: Suministros (al Por Menor)",
    "sg:phone":"+34 968 18 77 00",
    "sg:postcode":"30740",
    "sg:province":"Murcia",
    "wof:name":"Electronica Amstrong S.l.",
    "wof:placetype":"venue"
},
  "geometry": {"coordinates":[-0.7931212783,37.8325805664],"type":"Point"}
}