{
  "type": "Feature",
  "properties": {
    "addr:full":"Calle de San Francisco, 141 Burgos Burgos 09005",
    "addr:housenumber":"141",
    "addr:postcode":"09005",
    "addr:street":"Calle De San Francisco",
    "iso:country":"ES",
    "sg:address":"Calle de San Francisco, 141",
    "sg:city":"Burgos",
    "sg:orig_category":"Servicios Diversos",
    "sg:phone":"+34 947 24 41 74",
    "sg:postcode":"09005",
    "sg:province":"Burgos",
    "sg:website":"www.atisae.com",
    "wof:name":"Asistencia Tecnica Industrial S.a.e.",
    "wof:placetype":"venue"
},
  "geometry": {"coordinates":[-3.6986386776,42.349445343],"type":"Point"}
}