{
  "type": "Feature",
  "properties": {
    "addr:full":"Ferrerias Kalea, 6 Elgoibar Guip\u00f9zcoa 20870",
    "addr:housenumber":"6",
    "addr:postcode":"20870",
    "addr:street":"Ferrerias Kalea;Guipu\u0300Zcoa",
    "iso:country":"ES",
    "sg:address":"Ferrerias Kalea, 6",
    "sg:city":"Elgoibar",
    "sg:orig_category":"Negocio De Metales No Ferrosos",
    "sg:phone":"+34 943 74 19 12",
    "sg:postcode":"20870",
    "sg:province":"Guip\u00f9zcoa",
    "wof:name":"Claudio San Martin S.a.",
    "wof:placetype":"venue"
},
  "geometry": {"coordinates":[-2.4138290882,43.2163581848],"type":"Point"}
}