{
  "type": "Feature",
  "properties": {
    "iso:country":"ES",
    "sg:address":"Avda Gasteiz, 33",
    "sg:city":"Vitoria-gasteiz",
    "sg:orig_category":"Pescader\u00cdas (al Por Menor)",
    "sg:phone":"+34 945 22 44 20",
    "sg:postcode":"01008",
    "sg:province":"\u00c1lava",
    "wof:name":"I\u00f1igo Hueto Maria Belen",
    "wof:placetype":"venue"
},
  "geometry": {"coordinates":[-2.6822249889,42.8463439941],"type":"Point"}
}