{
  "type": "Feature",
  "properties": {
    "addr:full":"San Anton, 46 Iru\u00f1a Navarra 31001",
    "addr:housenumber":"46",
    "addr:postcode":"31001",
    "addr:street":"San Anton",
    "iso:country":"ES",
    "sg:address":"San Anton, 46",
    "sg:city":"Iru\u00f1a",
    "sg:orig_category":"Ense\u00d1anza: Costura",
    "sg:phone":"+34 948 22 78 83",
    "sg:postcode":"31001",
    "sg:province":"Navarra",
    "wof:name":"Garro Iturri Virginia Esther",
    "wof:placetype":"venue"
},
  "geometry": {"coordinates":[-1.646794796,42.8159790039],"type":"Point"}
}