{
  "type": "Feature",
  "properties": {
    "iso:country":"ES",
    "sg:address":"Avda Suecia (de), 15",
    "sg:city":"Cristianos",
    "sg:orig_category":"Agencias De Viajes",
    "sg:phone":"+34 922 75 00 48",
    "sg:postcode":"38650",
    "sg:province":"Santa Cruz De Tenerife",
    "wof:name":"Viajes Bitacora S.l.",
    "wof:placetype":"venue"
},
  "geometry": {"coordinates":[-16.7184391022,28.05194664],"type":"Point"}
}