{
  "type": "Feature",
  "properties": {
    "addr:full":"Via Sergia, 69 Mataro Barcelona 08302",
    "addr:housenumber":"69",
    "addr:postcode":"08302",
    "addr:street":"Via Sergia",
    "iso:country":"ES",
    "sg:address":"Via Sergia, 69",
    "sg:city":"Mataro",
    "sg:orig_category":"Publicidad (soportes Y Gesti\u00d3n)",
    "sg:phone":"+34 937 57 35 22",
    "sg:postcode":"08302",
    "sg:province":"Barcelona",
    "wof:name":"Sema Publicitat S.c.p.",
    "wof:placetype":"venue"
},
  "geometry": {"coordinates":[2.4234089851,41.5306854248],"type":"Point"}
}