{
  "type": "Feature",
  "properties": {
    "addr:full":"Rua Nova, 125 Lugo Lugo 27001",
    "addr:housenumber":"125",
    "addr:postcode":"27001",
    "addr:street":"Rua Nova",
    "iso:country":"ES",
    "sg:address":"Rua Nova, 125",
    "sg:city":"Lugo",
    "sg:orig_category":"Zapatos (al Por Menor)",
    "sg:phone":"+34 982 24 61 08",
    "sg:postcode":"27001",
    "sg:province":"Lugo",
    "wof:name":"Galizapato Sl",
    "wof:placetype":"venue"
},
  "geometry": {"coordinates":[-7.5602807999,43.0134544373],"type":"Point"}
}