{
  "type": "Feature",
  "properties": {
    "addr:full":"Calle de San Lorenzo, 20 Santa Eulalia Islas Baleares 07840",
    "addr:housenumber":"20",
    "addr:postcode":"07840",
    "addr:street":"Calle De San Lorenzo",
    "iso:country":"ES",
    "sg:address":"Calle de San Lorenzo, 20",
    "sg:city":"Santa Eulalia",
    "sg:orig_category":"Zapatos (al Por Menor)",
    "sg:phone":"+34 971 33 07 80",
    "sg:postcode":"07840",
    "sg:province":"Islas Baleares",
    "wof:name":"Bebia Cordero Concepcion",
    "wof:placetype":"venue"
},
  "geometry": {"coordinates":[2.9117100239,39.6136398315],"type":"Point"}
}