{
  "type": "Feature",
  "properties": {
    "iso:country":"ES",
    "sg:address":"Av Montserrat, 64",
    "sg:city":"S. Esteve Sesrovires",
    "sg:orig_category":"Delineantes",
    "sg:phone":"+34 937 71 44 55",
    "sg:postcode":"08635",
    "sg:province":"Barcelona",
    "wof:name":"Modelos Y Prototipos Lasarte S.l.",
    "wof:placetype":"venue"
},
  "geometry": {"coordinates":[1.8710819483,41.4966583252],"type":"Point"}
}