{
  "type": "Feature",
  "properties": {
    "addr:full":"Carr Bisbe Lorenzana, 33 Girona Girona 17002",
    "addr:housenumber":"33",
    "addr:postcode":"17002",
    "addr:street":"Carr Bisbe Lorenzana",
    "iso:country":"ES",
    "sg:address":"Carr Bisbe Lorenzana, 33",
    "sg:city":"Girona",
    "sg:orig_category":"M\u00c9dicos: Gastroenterolog\u00cda Y Hepatolog\u00cda (aparato Digestivo)",
    "sg:phone":"+34 972 21 53 84",
    "sg:postcode":"17002",
    "sg:province":"Girona",
    "wof:name":"Lopez Oliu Carlos",
    "wof:placetype":"venue"
},
  "geometry": {"coordinates":[2.8206329346,41.978351593],"type":"Point"}
}