{
  "type": "Feature",
  "properties": {
    "addr:full":"A Revolta, 44 Revolta La Coru\u00f1a 15966",
    "addr:housenumber":"44",
    "addr:postcode":"15966",
    "addr:street":"Revolta;La Corun\u0303A",
    "iso:country":"ES",
    "sg:address":"A Revolta, 44",
    "sg:city":"Revolta",
    "sg:orig_category":"Empresarios",
    "sg:phone":"+34 981 84 13 77",
    "sg:postcode":"15966",
    "sg:province":"La Coru\u00f1a",
    "wof:name":"Pena Franco Jose",
    "wof:placetype":"venue"
},
  "geometry": {"coordinates":[-8.9895505905,42.5456504822],"type":"Point"}
}