{
  "type": "Feature",
  "properties": {
    "addr:full":"Calle de Arroyo Cantaelgallo, 24 Toledo Toledo 45007",
    "addr:housenumber":"24",
    "addr:postcode":"45007",
    "addr:street":"Calle De Arroyo Cantaelgallo",
    "iso:country":"ES",
    "sg:address":"Calle de Arroyo Cantaelgallo, 24",
    "sg:city":"Toledo",
    "sg:orig_category":"Cristaler\u00cdas",
    "sg:phone":"+34 925 23 32 39",
    "sg:postcode":"45007",
    "sg:province":"Toledo",
    "wof:name":"Tolpertol S.l.",
    "wof:placetype":"venue"
},
  "geometry": {"coordinates":[-3.9474089146,39.8690643311],"type":"Point"}
}