{
  "type": "Feature",
  "properties": {
    "addr:full":"Avda Galicia, 49 Pontes Garcia Rodriguez La Coru\u00f1a 15320",
    "addr:housenumber":"49",
    "addr:postcode":"15320",
    "addr:street":"Avda Galicia;Corun\u0303A",
    "iso:country":"ES",
    "sg:address":"Avda Galicia, 49",
    "sg:city":"Pontes Garcia Rodriguez",
    "sg:orig_category":"M\u00c9dicos: Oftalmolog\u00cda",
    "sg:phone":"+34 981 44 09 00",
    "sg:postcode":"15320",
    "sg:province":"La Coru\u00f1a",
    "wof:name":"Instituto Gallego De Cirugia Ocular S.l.",
    "wof:placetype":"venue"
},
  "geometry": {"coordinates":[-7.8541431427,43.447479248],"type":"Point"}
}