{
  "type": "Feature",
  "properties": {
    "addr:full":"Poli Industrial C/t, 6 Rozas De Madrid Madrid 28230",
    "addr:housenumber":"6",
    "addr:postcode":"28230",
    "addr:street":"T",
    "iso:country":"ES",
    "sg:address":"Poli Industrial C/t, 6",
    "sg:city":"Rozas De Madrid",
    "sg:orig_category":"Torrefactado De Caf\u00c9",
    "sg:phone":"+34 916 40 74 85",
    "sg:postcode":"28230",
    "sg:province":"Madrid",
    "sg:website":"www.cafescastel.com",
    "wof:name":"Cafes Castel S. A.",
    "wof:placetype":"venue"
},
  "geometry": {"coordinates":[-3.8913800716,40.5247497559],"type":"Point"}
}