{
  "type": "Feature",
  "properties": {
    "addr:full":"Calle de San Vicente Martir, 4 Zaragoza Zaragoza 50008",
    "addr:housenumber":"4",
    "addr:postcode":"50008",
    "addr:street":"Calle De San Vicente Martir",
    "iso:country":"ES",
    "sg:address":"Calle de San Vicente Martir, 4",
    "sg:city":"Zaragoza",
    "sg:orig_category":"M\u00c9dicos: Oftalmolog\u00cda",
    "sg:phone":"+34 976 22 47 61",
    "sg:postcode":"50008",
    "sg:province":"Zaragoza",
    "wof:name":"Elia Casanova Francisco Javier",
    "wof:placetype":"venue"
},
  "geometry": {"coordinates":[-0.882404983,41.6440048218],"type":"Point"}
}