{
  "type": "Feature",
  "properties": {
    "addr:full":"Calle de Genova, 22 Madrid Madrid 28004",
    "addr:housenumber":"22",
    "addr:postcode":"madrid;28004",
    "addr:street":"Calle De Genova",
    "iso:country":"ES",
    "sg:address":"Calle de Genova, 22",
    "sg:city":"Madrid",
    "sg:orig_category":"Funcionario De Justicia",
    "sg:phone":"+34 913 19 68 26",
    "sg:postcode":"28004",
    "sg:province":"Madrid",
    "wof:name":"Administracion De Justicia",
    "wof:placetype":"venue"
},
  "geometry": {"coordinates":[-3.6929831505,40.4262237549],"type":"Point"}
}