{
  "type": "Feature",
  "properties": {
    "addr:full":"Calle de Profesor Mulian, 3 Almeria Almer\u00eda 04009",
    "addr:housenumber":"3",
    "addr:postcode":"04009",
    "addr:street":"Calle De Profesor Mulian",
    "iso:country":"ES",
    "sg:address":"Calle de Profesor Mulian, 3",
    "sg:city":"Almeria",
    "sg:orig_category":"Art\u00cdculos De Regalo (al Por Menor)",
    "sg:phone":"+34 950 22 31 03",
    "sg:postcode":"04009",
    "sg:province":"Almer\u00eda",
    "sg:website":"www.regalossanluis.com",
    "wof:name":"Oca\u00f1a Perez Maria",
    "wof:placetype":"venue"
},
  "geometry": {"coordinates":[-2.4496340752,36.848033905],"type":"Point"}
}