{
  "type": "Feature",
  "properties": {
    "iso:country":"ES",
    "sg:address":"Mina, 5",
    "sg:city":"Carballi\u00f1o",
    "sg:orig_category":"Art\u00cdculos De Decoraci\u00d3n",
    "sg:phone":"+34 988 27 09 84",
    "sg:postcode":"32500",
    "sg:province":"Ourense",
    "wof:name":"Balcon Decor S.c.",
    "wof:placetype":"venue"
},
  "geometry": {"coordinates":[-8.0628862381,42.4484519958],"type":"Point"}
}