{
  "type": "Feature",
  "properties": {
    "addr:full":"Avda Rio Cidacos, 132 Agoncillo La Rioja 26509",
    "addr:housenumber":"132",
    "addr:postcode":"26509",
    "addr:street":"Avda Rio Cidacos;Rioja",
    "iso:country":"ES",
    "sg:address":"Avda Rio Cidacos, 132",
    "sg:city":"Agoncillo",
    "sg:orig_category":"Cajas Y Embalajes De Pl\u00c1stico",
    "sg:phone":"+34 941 43 14 05",
    "sg:postcode":"26509",
    "sg:province":"La Rioja",
    "sg:website":"www.plastini.com",
    "wof:name":"Plastinal S.l",
    "wof:placetype":"venue"
},
  "geometry": {"coordinates":[-2.1222639084,42.4031410217],"type":"Point"}
}