{
  "type": "Feature",
  "properties": {
    "iso:country":"ES",
    "sg:address":"Rua Ramon Gonzalez, 32",
    "sg:city":"Porri\u00f1o",
    "sg:orig_category":"Zapatos (al Por Menor)",
    "sg:phone":"+34 986 33 90 00",
    "sg:postcode":"36400",
    "sg:province":"Pontevedra",
    "wof:name":"Dominguez Gil Rogelio",
    "wof:placetype":"venue"
},
  "geometry": {"coordinates":[-8.6179990768,42.1610298157],"type":"Point"}
}