{
  "type": "Feature",
  "properties": {
    "addr:full":"Pol Ind La Vi\u00f1uela, S/n Lucena C\u00f3rdoba 14900",
    "addr:postcode":"14900",
    "addr:street":"Vin\u0303Uela S / N",
    "iso:country":"ES",
    "sg:address":"Pol Ind La Vi\u00f1uela, S/n",
    "sg:city":"Lucena",
    "sg:orig_category":"Fabricaci\u00d3n De Muebles",
    "sg:phone":"+34 957 51 10 12",
    "sg:postcode":"14900",
    "sg:province":"C\u00f3rdoba",
    "wof:name":"Muebles Hermanos Pineda Mu\u00f1oz S.l.",
    "wof:placetype":"venue"
},
  "geometry": {"coordinates":[-4.4847187996,37.4150352478],"type":"Point"}
}