{
  "type": "Feature",
  "properties": {
    "addr:full":"Carrer de Doctor Bove, 63 Barcelona Barcelona 08032",
    "addr:housenumber":"63",
    "addr:postcode":"08032",
    "addr:street":"Carrer De Doctor Bove",
    "iso:country":"ES",
    "sg:address":"Carrer de Doctor Bove, 63",
    "sg:city":"Barcelona",
    "sg:orig_category":"Plomeros",
    "sg:phone":"+34 933 58 09 14",
    "sg:postcode":"08032",
    "sg:province":"Barcelona",
    "wof:name":"Ferma S.l.",
    "wof:placetype":"venue"
},
  "geometry": {"coordinates":[2.16229105,41.4210128784],"type":"Point"}
}