{
  "type": "Feature",
  "properties": {
    "iso:country":"ES",
    "sg:address":"Calle de Pedriza, 14",
    "sg:city":"Albolote",
    "sg:orig_category":"Maquinaria Para Industrias Diversas",
    "sg:phone":"+34 958 46 65 07",
    "sg:postcode":"18220",
    "sg:province":"Granada",
    "wof:name":"Castro Cortaceros Mariano Antonio",
    "wof:placetype":"venue"
},
  "geometry": {"coordinates":[-3.6573810577,37.2347793579],"type":"Point"}
}