{
  "type": "Feature",
  "properties": {
    "iso:country":"ES",
    "sg:address":"Carrer de Gaieta Vinzia, 47",
    "sg:city":"Mollet Valles",
    "sg:orig_category":"Marroquiner\u00cda (confecci\u00d3n)",
    "sg:phone":"+34 935 70 26 92",
    "sg:postcode":"08100",
    "sg:province":"Barcelona",
    "wof:name":"L'isard S.c.p.",
    "wof:placetype":"venue"
},
  "geometry": {"coordinates":[2.2110950947,41.5403671265],"type":"Point"}
}