{
  "type": "Feature",
  "properties": {
    "addr:full":"Raval Belianes, 1 Sant Marti De Malda Lleida 25344",
    "addr:housenumber":"1",
    "addr:postcode":"25344",
    "addr:street":"Belianes",
    "iso:country":"ES",
    "sg:address":"Raval Belianes, 1",
    "sg:city":"Sant Marti De Malda",
    "sg:orig_category":"Semiller\u00cdas",
    "sg:phone":"+34 973 33 01 91",
    "sg:postcode":"25344",
    "sg:province":"Lleida",
    "wof:name":"Cullere Caimons Salvador",
    "wof:placetype":"venue"
},
  "geometry": {"coordinates":[1.0529489517,41.5599784851],"type":"Point"}
}