{
  "type": "Feature",
  "properties": {
    "iso:country":"ES",
    "sg:address":"E. Ferrocarril, S/n",
    "sg:city":"Antequera",
    "sg:classifiers":[
        {
            "category":"Manufacturing",
            "subcategory":"Building Materials",
            "type":"Manufacturing & Wholesale Goods"
        }
    ],
    "sg:phone":"+34 952 84 01 54",
    "sg:postcode":"29200",
    "sg:province":"M\u00e1laga",
    "sg:tags":[
        "cemento",
        "y",
        "de",
        "fabricaci\u00d3n",
        "cal"
    ],
    "wof:name":"Cementos De Andalucia S.l.",
    "wof:placetype":"venue"
},
  "geometry": {"coordinates":[-4.5636138916,37.0203018188],"type":"Point"}
}