{
  "type": "Feature",
  "properties": {
    "iso:country":"ES",
    "sg:address":"Calle de Camino De Los Vinateros, 40",
    "sg:city":"Madrid",
    "sg:orig_category":"Transportes Por Carretera: Lotes Completos, Mercanc\u00cdas Diversas",
    "sg:phone":"+34 914 30 14 13",
    "sg:postcode":"28030",
    "sg:province":"Madrid",
    "wof:name":"Martinez Perpi\u00f1a Justo",
    "wof:placetype":"venue"
},
  "geometry": {"coordinates":[-3.6551718712,40.4105949402],"type":"Point"}
}