{
  "type": "Feature",
  "properties": {
    "addr:full":"Ctra General Tf-6237, 19 Playa San Juan Santa Cruz De Tenerife 38687",
    "addr:housenumber":"19",
    "addr:postcode":"38687",
    "addr:street":"Ctra General Tf-6237",
    "iso:country":"ES",
    "sg:address":"Ctra General Tf-6237, 19",
    "sg:city":"Playa San Juan",
    "sg:orig_category":"Muebles, Minoristas",
    "sg:phone":"+34 922 86 62 19",
    "sg:postcode":"38687",
    "sg:province":"Santa Cruz De Tenerife",
    "wof:name":"Maderas Y Coden S.l.",
    "wof:placetype":"venue"
},
  "geometry": {"coordinates":[-16.8154582977,28.1830596924],"type":"Point"}
}