{
  "type": "Feature",
  "properties": {
    "addr:full":"Calle de San Isidro, 10 Villacedre Le\u00f3n 24194",
    "addr:housenumber":"10",
    "addr:postcode":"24194",
    "addr:street":"Calle De San Isidro;Leo\u0301N",
    "iso:country":"ES",
    "sg:address":"Calle de San Isidro, 10",
    "sg:city":"Villacedre",
    "sg:orig_category":"Venta, Alquiler, Mantenimiento De Calderas",
    "sg:phone":"+34 987 21 83 32",
    "sg:postcode":"24194",
    "sg:province":"Le\u00f3n",
    "wof:name":"Montajes Mikel S.l.",
    "wof:placetype":"venue"
},
  "geometry": {"coordinates":[-5.5860338211,42.5638847351],"type":"Point"}
}