{
  "type": "Feature",
  "properties": {
    "addr:full":"Calle de Guzman El Bueno, 66 Madrid Madrid 28015",
    "addr:housenumber":"66",
    "addr:postcode":"madrid;28015",
    "addr:street":"Calle De Guzman El Bueno",
    "iso:country":"ES",
    "sg:address":"Calle de Guzman El Bueno, 66",
    "sg:city":"Madrid",
    "sg:orig_category":"Bibliotecas, Mediatecas",
    "sg:phone":"+34 915 44 37 30",
    "sg:postcode":"28015",
    "sg:province":"Madrid",
    "sg:website":"www.obrasocialcajamadrid.org",
    "wof:name":"Gecesa Gestion De Centros Culturales S.a",
    "wof:placetype":"venue"
},
  "geometry": {"coordinates":[-3.7129528522,40.4377479553],"type":"Point"}
}