{
  "type": "Feature",
  "properties": {
    "addr:full":"Calle de Rosal, 50 Puebla De Don Rodrigo Ciudad Real 13109",
    "addr:housenumber":"50",
    "addr:postcode":"13109",
    "addr:street":"Calle De Rosal",
    "iso:country":"ES",
    "sg:address":"Calle de Rosal, 50",
    "sg:city":"Puebla De Don Rodrigo",
    "sg:orig_category":"Armas Y Municiones (fabricaci\u00d3n, Al Por Mayor)",
    "sg:phone":"+34 926 77 73 09",
    "sg:postcode":"13109",
    "sg:province":"Ciudad Real",
    "wof:name":"Villa Gutierrez Amparo",
    "wof:placetype":"venue"
},
  "geometry": {"coordinates":[-4.6177787781,39.0822792053],"type":"Point"}
}