{
  "type": "Feature",
  "properties": {
    "iso:country":"ES",
    "sg:address":"Avda Paralela, 55",
    "sg:city":"Majadahonda",
    "sg:orig_category":"Inform\u00c1tica: Consultores",
    "sg:phone":"+34 916 34 37 54",
    "sg:postcode":"28220",
    "sg:province":"Madrid",
    "wof:name":"Envision Technologies",
    "wof:placetype":"venue"
},
  "geometry": {"coordinates":[-3.8585999012,40.4753799438],"type":"Point"}
}