{
  "type": "Feature",
  "properties": {
    "iso:country":"ES",
    "sg:address":"Calle de Re\u00d1idero, S/n",
    "sg:city":"Granada",
    "sg:orig_category":"Agencias Y Asesores De Publicidad",
    "sg:phone":"+34 958 53 61 03",
    "sg:postcode":"18005",
    "sg:province":"Granada",
    "sg:website":"www.cempresarial.com/disenoycomunicacionlinan",
    "wof:name":"Dise\u00f1o Y Comunicacion Li\u00f1an S.l.l.",
    "wof:placetype":"venue"
},
  "geometry": {"coordinates":[-3.5971040726,37.1688156128],"type":"Point"}
}