{
  "type": "Feature",
  "properties": {
    "iso:country":"ES",
    "sg:address":"Cmno Soto (el), 13",
    "sg:city":"Berrioplano",
    "sg:orig_category":"Calderer\u00cda",
    "sg:phone":"+34 948 30 32 77",
    "sg:postcode":"31195",
    "sg:province":"Navarra",
    "wof:name":"Pelegrin Domenech Pedro Maria",
    "wof:placetype":"venue"
},
  "geometry": {"coordinates":[-1.685428977,42.8449516296],"type":"Point"}
}