{
  "type": "Feature",
  "properties": {
    "addr:full":"Avda Salinero (el), 6 Costa Teguise Las Palmas 35509",
    "addr:housenumber":"6",
    "addr:postcode":"35509",
    "addr:street":"Avda Salinero El",
    "iso:country":"ES",
    "sg:address":"Avda Salinero (el), 6",
    "sg:city":"Costa Teguise",
    "sg:orig_category":"Molduras, Junquillos, Listones Y Molduras Perforadas",
    "sg:phone":"+34 928 59 24 71",
    "sg:postcode":"35509",
    "sg:province":"Las Palmas",
    "wof:name":"Gates  Michel",
    "wof:placetype":"venue"
},
  "geometry": {"coordinates":[-13.5079612732,28.9865322113],"type":"Point"}
}