{
  "type": "Feature",
  "properties": {
    "addr:full":"Sepes Poligono, S/n Huesca Huesca 22099",
    "addr:postcode":"22099",
    "addr:street":"Poligono S / N",
    "iso:country":"ES",
    "sg:address":"Sepes Poligono, S/n",
    "sg:city":"Huesca",
    "sg:orig_category":"Comercio De Hierro",
    "sg:phone":"+34 974 24 42 58",
    "sg:postcode":"22099",
    "sg:province":"Huesca",
    "wof:name":"Hierros Huesca S. A.",
    "wof:placetype":"venue"
},
  "geometry": {"coordinates":[-0.4083139896,42.1365661621],"type":"Point"}
}