{
  "type": "Feature",
  "properties": {
    "iso:country":"ES",
    "sg:address":"Carrer de Blasco De Garay, 9",
    "sg:city":"Barcelona",
    "sg:orig_category":"Mec\u00c1nico Del Autom\u00d3vil",
    "sg:phone":"+34 934 42 01 49",
    "sg:postcode":"08004",
    "sg:province":"Barcelona",
    "wof:name":"Omega Motor S.a.l.",
    "wof:placetype":"venue"
},
  "geometry": {"coordinates":[2.163367033,41.3744125366],"type":"Point"}
}