{
  "type": "Feature",
  "properties": {
    "addr:full":"Carrer de Panta De Tremp, 4 Barcelona Barcelona 08032",
    "addr:housenumber":"4",
    "addr:postcode":"08032",
    "addr:street":"Carrer De Panta;Tremp",
    "iso:country":"ES",
    "sg:address":"Carrer de Panta De Tremp, 4",
    "sg:city":"Barcelona",
    "sg:orig_category":"Frutas, Legumbres Frescas Y Tempranas (al Por Menor)",
    "sg:phone":"+34 933 57 17 21",
    "sg:postcode":"08032",
    "sg:province":"Barcelona",
    "wof:name":"Fernandez Alvarez Benjamin",
    "wof:placetype":"venue"
},
  "geometry": {"coordinates":[2.1559569836,41.4245643616],"type":"Point"}
}