{
  "type": "Feature",
  "properties": {
    "iso:country":"ES",
    "sg:address":"Calle de Pergolas, 3",
    "sg:city":"Cadiz",
    "sg:orig_category":"M\u00c9dicos: Cirug\u00cda Maxilofacial",
    "sg:phone":"+34 956 27 37 39",
    "sg:postcode":"11007",
    "sg:province":"C\u00e1diz",
    "wof:name":"Dr. Modelo-maxilofacial S.l.",
    "wof:placetype":"venue"
},
  "geometry": {"coordinates":[-6.2858099937,36.5253791809],"type":"Point"}
}