{
  "type": "Feature",
  "properties": {
    "addr:full":"Av Primavera, 11 Cerdanyola Valles Barcelona 08290",
    "addr:housenumber":"11",
    "addr:postcode":"08290",
    "addr:street":"Av Primavera;Valles Barcelona",
    "iso:country":"ES",
    "sg:address":"Av Primavera, 11",
    "sg:city":"Cerdanyola Valles",
    "sg:orig_category":"Confecci\u00d3n De Trajes Para Se\u00d1oras",
    "sg:phone":"+34 935 80 68 22",
    "sg:postcode":"08290",
    "sg:province":"Barcelona",
    "wof:name":"Escude Arconada Rosa",
    "wof:placetype":"venue"
},
  "geometry": {"coordinates":[2.1456310749,41.490776062],"type":"Point"}
}