{
  "type": "Feature",
  "properties": {
    "addr:full":"Avda Constitucion, 7 San Pedro Alcantara M\u00e1laga 29670",
    "addr:housenumber":"7",
    "addr:postcode":"29670",
    "addr:street":"Avda Constitucion",
    "iso:country":"ES",
    "sg:address":"Avda Constitucion, 7",
    "sg:city":"San Pedro Alcantara",
    "sg:orig_category":"Tapiceros Y Tapiceros",
    "sg:phone":"+34 952 85 33 85",
    "sg:postcode":"29670",
    "sg:province":"M\u00e1laga",
    "wof:name":"M.m. Dise\u00f1o De Interior 2003 S.l.",
    "wof:placetype":"venue"
},
  "geometry": {"coordinates":[-4.9916062355,36.4844551086],"type":"Point"}
}