{
  "type": "Feature",
  "properties": {
    "addr:full":"Calle de Letra F, 5 Puebla Alfinden Zaragoza 50171",
    "addr:housenumber":"5",
    "addr:postcode":"50171",
    "addr:street":"Calle De Letra;Puebla Alfinden",
    "iso:country":"ES",
    "sg:address":"Calle de Letra F, 5",
    "sg:city":"Puebla Alfinden",
    "sg:orig_category":"Art\u00cdculos De Aluminio",
    "sg:phone":"+34 976 10 99 85",
    "sg:postcode":"50171",
    "sg:province":"Zaragoza",
    "wof:name":"Aluminios Azuara S.l.l.",
    "wof:placetype":"venue"
},
  "geometry": {"coordinates":[-0.7554336786,41.6345596313],"type":"Point"}
}