{
  "type": "Feature",
  "properties": {
    "iso:country":"ES",
    "sg:address":"Calle de Castillo De Ucles, 53",
    "sg:city":"Madrid",
    "sg:orig_category":"Tapicer\u00cdas",
    "sg:phone":"+34 917 54 55 57",
    "sg:postcode":"28037",
    "sg:province":"Madrid",
    "wof:name":"Cardenal Moreno Antonio",
    "wof:placetype":"venue"
},
  "geometry": {"coordinates":[-3.622948885,40.4321174622],"type":"Point"}
}