{
  "type": "Feature",
  "properties": {
    "iso:country":"ES",
    "sg:address":"Rbla Sant Jordi (de), 103",
    "sg:city":"Ripollet",
    "sg:orig_category":"Fabricaci\u00d3n, Instalaci\u00d3n De Escaleras",
    "sg:phone":"+34 935 92 23 01",
    "sg:postcode":"08291",
    "sg:province":"Barcelona",
    "wof:name":"Mohammad  Alzaal",
    "wof:placetype":"venue"
},
  "geometry": {"coordinates":[2.1657791138,41.4951133728],"type":"Point"}
}