{
  "type": "Feature",
  "properties": {
    "addr:full":"Avda Bos Aires, 2 Mondo\u00f1edo Lugo 27740",
    "addr:housenumber":"2",
    "addr:postcode":"27740",
    "addr:street":"Avda Bos Aires",
    "iso:country":"ES",
    "sg:address":"Avda Bos Aires, 2",
    "sg:city":"Mondo\u00f1edo",
    "sg:orig_category":"Asesor\u00cda Fiscal Y Jur\u00cddica",
    "sg:phone":"+34 982 52 40 34",
    "sg:postcode":"27740",
    "sg:province":"Lugo",
    "wof:name":"Lopez Rejes Maria Rosa",
    "wof:placetype":"venue"
},
  "geometry": {"coordinates":[-7.3599891663,43.4278488159],"type":"Point"}
}