{
  "type": "Feature",
  "properties": {
    "iso:country":"ES",
    "sg:address":"Rua Areal, 68",
    "sg:city":"Vigo",
    "sg:orig_category":"Internados & Ense\u00d1anza Privada",
    "sg:phone":"+34 986 22 25 03",
    "sg:postcode":"36201",
    "sg:province":"Pontevedra",
    "sg:website":"www.cibermedia.com/seforma/",
    "wof:name":"Seforma S.l.",
    "wof:placetype":"venue"
},
  "geometry": {"coordinates":[-8.715051651,42.2387504578],"type":"Point"}
}