{
  "type": "Feature",
  "properties": {
    "iso:country":"ES",
    "sg:address":"Calle de Francisco De Rojas, 5",
    "sg:city":"Madrid",
    "sg:orig_category":"M\u00c9dicos: Estomatolog\u00cda",
    "sg:phone":"+34 914 47 67 09",
    "sg:postcode":"28010",
    "sg:province":"Madrid",
    "wof:name":"Ituarte Martinez Sergio Gabriel",
    "wof:placetype":"venue"
},
  "geometry": {"coordinates":[-3.6996424198,40.4292182922],"type":"Point"}
}