{
  "type": "Feature",
  "properties": {
    "iso:country":"ES",
    "sg:address":"Avda Europa, 128",
    "sg:city":"Mojonera",
    "sg:orig_category":"Abogados",
    "sg:phone":"+34 950 33 08 45",
    "sg:postcode":"04745",
    "sg:province":"Almer\u00eda",
    "wof:name":"Ruiz Luque Amador",
    "wof:placetype":"venue"
},
  "geometry": {"coordinates":[-2.681178093,36.7549514771],"type":"Point"}
}