{
  "type": "Feature",
  "properties": {
    "iso:country":"ES",
    "sg:address":"O Pi\u00f1eiral, 25",
    "sg:city":"S. Cibrao Vi\u00f1as",
    "sg:orig_category":"Muebles Y Accesorios Para Cocinas Y Cuartos De Ba\u00d1o (al Por Menor)",
    "sg:phone":"+34 988 22 35 58",
    "sg:postcode":"32911",
    "sg:province":"Ourense",
    "wof:name":"Cofady S.l.",
    "wof:placetype":"venue"
},
  "geometry": {"coordinates":[-7.8636841774,42.3073043823],"type":"Point"}
}