{
  "type": "Feature",
  "properties": {
    "addr:full":"Carrer de Puerto Rico, 15 Palma Islas Baleares 07...",
    "addr:housenumber":"15;07 ...",
    "addr:street":"Carrer De Puerto Rico;Islas Baleares",
    "iso:country":"ES",
    "sg:address":"Carrer de Puerto Rico, 15",
    "sg:city":"Palma",
    "sg:orig_category":"Edici\u00d3n De Diarios, Revistas, Boletines",
    "sg:phone":"+34 971 17 03 00",
    "sg:postcode":"07...",
    "sg:province":"Islas Baleares",
    "sg:website":"www.diariodemallorca.es",
    "wof:name":"Editora Balear S.a.",
    "wof:placetype":"venue"
},
  "geometry": {"coordinates":[2.6683499813,39.5642776489],"type":"Point"}
}