{
  "type": "Feature",
  "properties": {
    "addr:full":"Avda Oviedo De, 39 Cangas Narcea Asturias 33800",
    "addr:housenumber":"39",
    "addr:postcode":"33800",
    "addr:street":"Avda Oviedo De",
    "iso:country":"ES",
    "sg:address":"Avda Oviedo De, 39",
    "sg:city":"Cangas Narcea",
    "sg:orig_category":"Mec\u00c1nico Del Autom\u00d3vil",
    "sg:phone":"+34 985 81 31 81",
    "sg:postcode":"33800",
    "sg:province":"Asturias",
    "wof:name":"Autocentro Cangas S.l.",
    "wof:placetype":"venue"
},
  "geometry": {"coordinates":[-6.5450954437,43.1824035645],"type":"Point"}
}