{
  "type": "Feature",
  "properties": {
    "iso:country":"ES",
    "sg:address":"Avda Andalucia (de), 21",
    "sg:city":"Montilla",
    "sg:classifiers":[
        {
            "category":"Autos & Motor Vehicles",
            "subcategory":"Automobile Sales",
            "type":"Retail Goods"
        }
    ],
    "sg:phone":"+34 957 65 70 10",
    "sg:postcode":"14550",
    "sg:province":"C\u00f3rdoba",
    "wof:name":"Zafra Aguilar Jose",
    "wof:placetype":"venue"
},
  "geometry": {"coordinates":[-4.6470623016,37.5808486938],"type":"Point"}
}