{
  "type": "Feature",
  "properties": {
    "addr:full":"Pl L'estacio, 6 Barcelona Barcelona 08030",
    "addr:housenumber":"6",
    "addr:postcode":"08030",
    "addr:street":"Pl L'Estacio",
    "iso:country":"ES",
    "sg:address":"Pl L'estacio, 6",
    "sg:city":"Barcelona",
    "sg:orig_category":"Molduras, Junquillos, Listones Y Molduras Perforadas",
    "sg:phone":"+34 933 46 46 67",
    "sg:postcode":"08030",
    "sg:province":"Barcelona",
    "wof:name":"Rivera Martinez Virgilio",
    "wof:placetype":"venue"
},
  "geometry": {"coordinates":[2.1932370663,41.4361190796],"type":"Point"}
}