{
  "type": "Feature",
  "properties": {
    "addr:full":"Calle de Gobernador Marin Acu\u00d1a, 29 Palmas De Gran Canaria Las Palmas 35014",
    "addr:housenumber":"29",
    "addr:postcode":"35014",
    "addr:street":"Calle De Gobernador Marin Acun\u0303A",
    "iso:country":"ES",
    "sg:address":"Calle de Gobernador Marin Acu\u00d1a, 29",
    "sg:city":"Palmas De Gran Canaria",
    "sg:orig_category":"Farmacias",
    "sg:phone":"+34 928 37 35 30",
    "sg:postcode":"35014",
    "sg:province":"Las Palmas",
    "wof:name":"Mir Gomez Maria Dolores",
    "wof:placetype":"venue"
},
  "geometry": {"coordinates":[-15.4253511429,28.1035118103],"type":"Point"}
}