{
  "type": "Feature",
  "properties": {
    "addr:full":"Calle de Ca\u00d1ada Del Parral, 2 Coria Rio Sevilla 41100",
    "addr:housenumber":"2",
    "addr:postcode":"41100",
    "addr:street":"Calle De Can\u0303Ada Del Parral;Rio Sevilla",
    "iso:country":"ES",
    "sg:address":"Calle de Ca\u00d1ada Del Parral, 2",
    "sg:city":"Coria Rio",
    "sg:orig_category":"Comadronas",
    "sg:phone":"+34 954 77 17 07",
    "sg:postcode":"41100",
    "sg:province":"Sevilla",
    "wof:name":"Hernandez Astola Alicia",
    "wof:placetype":"venue"
},
  "geometry": {"coordinates":[-6.0512604713,37.2899589539],"type":"Point"}
}