{
  "type": "Feature",
  "properties": {
    "addr:full":"Calle de San Vicente De Paul, 54 Zaragoza Zaragoza 50001",
    "addr:housenumber":"54",
    "addr:postcode":"50001",
    "addr:street":"Calle De San Vicente De Paul",
    "iso:country":"ES",
    "sg:address":"Calle de San Vicente De Paul, 54",
    "sg:city":"Zaragoza",
    "sg:orig_category":"M\u00c1quinas De Escribir, M\u00c1quinas De Oficina (al Por Menor, Reparaci\u00d3n)",
    "sg:phone":"+34 976 39 66 42",
    "sg:postcode":"50001",
    "sg:province":"Zaragoza",
    "wof:name":"Serrano Arruego Blas",
    "wof:placetype":"venue"
},
  "geometry": {"coordinates":[-0.8733879924,41.6548995972],"type":"Point"}
}