{
  "type": "Feature",
  "properties": {
    "addr:full":"Avda Gran Via Rey Juan Carlos I, 6 Logro\u00f1o La Rioja 26002",
    "addr:housenumber":"6",
    "addr:postcode":"26002",
    "addr:street":"Avda Gran Via Rey Juan Carlos I;Rioja",
    "iso:country":"ES",
    "sg:address":"Avda Gran Via Rey Juan Carlos I, 6",
    "sg:city":"Logro\u00f1o",
    "sg:orig_category":"M\u00c9dicos: An\u00c1lisis Cl\u00cdnicos",
    "sg:phone":"+34 941 22 67 90",
    "sg:postcode":"26002",
    "sg:province":"La Rioja",
    "wof:name":"Laboratorios Calvo Salazar C.b.",
    "wof:placetype":"venue"
},
  "geometry": {"coordinates":[-2.4458429813,42.4631958008],"type":"Point"}
}