{
  "type": "Feature",
  "properties": {
    "iso:country":"ES",
    "sg:address":"Calle de Olmos, 23",
    "sg:city":"Ciudad Real",
    "sg:orig_category":"M\u00c9dicos: Cirug\u00cda Urol\u00d3gica",
    "sg:phone":"+34 926 21 60 45",
    "sg:postcode":"13002",
    "sg:province":"Ciudad Real",
    "wof:name":"Ortiz Solana Antonia",
    "wof:placetype":"venue"
},
  "geometry": {"coordinates":[-3.9399590492,38.9785690308],"type":"Point"}
}