{
  "type": "Feature",
  "properties": {
    "addr:full":"Av. Cuarta, 4 Madrid Madrid 28022",
    "addr:housenumber":"4",
    "addr:postcode":"28022",
    "addr:street":"Av. Cuarta",
    "iso:country":"ES",
    "sg:address":"Av. Cuarta, 4",
    "sg:city":"Madrid",
    "sg:orig_category":"Caf\u00c9s, Bares, Cervecer\u00cdas",
    "sg:phone":"+34 917 42 67 46",
    "sg:postcode":"28022",
    "sg:province":"Madrid",
    "wof:name":"Porras Galvez Antonio",
    "wof:placetype":"venue"
},
  "geometry": {"coordinates":[-3.6686639786,40.4545669556],"type":"Point"}
}