{
  "type": "Feature",
  "properties": {
    "addr:full":"Las Eras, 30 Solera Ja\u00e9n 23569",
    "addr:housenumber":"30",
    "addr:postcode":"23569",
    "addr:street":"Las Eras;Jae\u0301N",
    "iso:country":"ES",
    "sg:address":"Las Eras, 30",
    "sg:city":"Solera",
    "sg:orig_category":"Confecci\u00d3n (fabricaci\u00d3n, Al Por Mayor)",
    "sg:phone":"+34 953 39 43 50",
    "sg:postcode":"23569",
    "sg:province":"Ja\u00e9n",
    "wof:name":"Pi\u00f1ar Gomez Isabel",
    "wof:placetype":"venue"
},
  "geometry": {"coordinates":[-3.3699970245,37.6831436157],"type":"Point"}
}