{
  "type": "Feature",
  "properties": {
    "iso:country":"ES",
    "sg:address":"Carrer de Dalia, 14",
    "sg:city":"Terra Nostra",
    "sg:orig_category":"Rectificaci\u00d3n, Mecanizado, Fresado",
    "sg:phone":"+34 935 64 20 96",
    "sg:postcode":"08110",
    "sg:province":"Barcelona",
    "sg:website":"www.mecanicaesmiper.es",
    "wof:name":"Mecanica Esmiper S.l.",
    "wof:placetype":"venue"
},
  "geometry": {"coordinates":[2.1732759476,41.4835891724],"type":"Point"}
}