{
  "type": "Feature",
  "properties": {
    "iso:country":"ES",
    "sg:address":"Carrer de Gutenberg, 25",
    "sg:city":"Terrassa",
    "sg:orig_category":"Ropa Para Ni\u00d1os (al Por Menor)",
    "sg:phone":"+34 937 89 15 10",
    "sg:postcode":"08224",
    "sg:province":"Barcelona",
    "wof:name":"Fortin Gisbert Carmen",
    "wof:placetype":"venue"
},
  "geometry": {"coordinates":[2.0068619251,41.560508728],"type":"Point"}
}