{
  "type": "Feature",
  "properties": {
    "addr:full":"Calle de Padre Anton Martin, 3 Valencia Valencia 46011",
    "addr:housenumber":"3",
    "addr:postcode":"46011",
    "addr:street":"Calle De Padre Anton Martin",
    "iso:country":"ES",
    "sg:address":"Calle de Padre Anton Martin, 3",
    "sg:city":"Valencia",
    "sg:orig_category":"Librer\u00cdas",
    "sg:phone":"+34 963 71 13 74",
    "sg:postcode":"46011",
    "sg:province":"Valencia",
    "wof:name":"Pastor Segovia Emilio",
    "wof:placetype":"venue"
},
  "geometry": {"coordinates":[-0.3287639916,39.4755516052],"type":"Point"}
}