{
  "type": "Feature",
  "properties": {
    "iso:country":"ES",
    "sg:address":"Carrer de Girona, 49",
    "sg:city":"Granollers",
    "sg:orig_category":"Reposter\u00cdas",
    "sg:phone":"+34 938 70 38 33",
    "sg:postcode":"08402",
    "sg:province":"Barcelona",
    "wof:name":"Fleca P. Bretcha S.l.",
    "wof:placetype":"venue"
},
  "geometry": {"coordinates":[2.2910490036,41.6114959717],"type":"Point"}
}