{
  "type": "Feature",
  "properties": {
    "addr:full":"Ctra Oca\u00d1a, S/n Alacant Alicante 03006",
    "addr:housenumber":"s / n",
    "addr:postcode":"03006",
    "addr:street":"Ctra Ocan\u0303A",
    "iso:country":"ES",
    "sg:address":"Ctra Oca\u00d1a, S/n",
    "sg:city":"Alacant",
    "sg:orig_category":"Complementos Para Pasteler\u00cdas, Confiter\u00cdas Y Chocolater\u00cdas",
    "sg:phone":"+34 965 28 21 00",
    "sg:postcode":"03006",
    "sg:province":"Alicante",
    "wof:name":"Comodin Suministros De Accesorios Y Productos Alimenticios S.a.",
    "wof:placetype":"venue"
},
  "geometry": {"coordinates":[-0.5382739902,38.34400177],"type":"Point"}
}