{
  "type": "Feature",
  "properties": {
    "addr:full":"Calle de Jacinto Benavente (de), 2 Boadilla Del Monte Madrid 28660",
    "addr:housenumber":"2",
    "addr:postcode":"28660",
    "addr:street":"Calle De Jacinto Benavente De",
    "iso:country":"ES",
    "sg:address":"Calle de Jacinto Benavente (de), 2",
    "sg:city":"Boadilla Del Monte",
    "sg:orig_category":"Electricidad: Equipos Industriales, Componentes (fabricaci\u00d3n)",
    "sg:phone":"+34 916 33 94 85",
    "sg:postcode":"28660",
    "sg:province":"Madrid",
    "wof:name":"Cintubex S.l.",
    "wof:placetype":"venue"
},
  "geometry": {"coordinates":[-3.9005439281,40.4025802612],"type":"Point"}
}