{
  "type": "Feature",
  "properties": {
    "iso:country":"ES",
    "sg:address":"Calle de Hospital, 24",
    "sg:city":"Torrejon Ardoz",
    "sg:orig_category":"Plomeros",
    "sg:phone":"+34 916 77 09 78",
    "sg:postcode":"28850",
    "sg:province":"Madrid",
    "wof:name":"Saneamientos Reni S.a.",
    "wof:placetype":"venue"
},
  "geometry": {"coordinates":[-3.4772698879,40.4588890076],"type":"Point"}
}