{
  "type": "Feature",
  "properties": {
    "addr:full":"Calle de Marques De Villamagna, 6 Madrid Madrid 28...",
    "addr:housenumber":"6;28 ...",
    "addr:street":"Calle De Marques De Villamagna;Madrid",
    "iso:country":"ES",
    "sg:address":"Calle de Marques De Villamagna, 6",
    "sg:city":"Madrid",
    "sg:orig_category":"Puros, Cigarrillos Y Tabaco (fabricaci\u00d3n, Al Por Mayor)",
    "sg:phone":"+34 915 20 00 30",
    "sg:postcode":"28...",
    "sg:province":"Madrid",
    "sg:website":"www.jt.com",
    "wof:name":"Equant European Networks B.v.",
    "wof:placetype":"venue"
},
  "geometry": {"coordinates":[-3.6879959106,40.4294548035],"type":"Point"}
}