{
  "type": "Feature",
  "properties": {
    "addr:full":"Pg. Enric Morera, 15 S. Pere Ribes Barcelona 08810",
    "addr:housenumber":"15",
    "addr:postcode":"08810",
    "addr:street":"Pg. Enric Morera;S. Pere Ribes Barcelona",
    "iso:country":"ES",
    "sg:address":"Pg. Enric Morera, 15",
    "sg:city":"S. Pere Ribes",
    "sg:orig_category":"Inmobiliaria (agencias)",
    "sg:phone":"+34 938 96 35 51",
    "sg:postcode":"08810",
    "sg:province":"Barcelona",
    "wof:name":"Selbamar S.a.",
    "wof:placetype":"venue"
},
  "geometry": {"coordinates":[1.7805219889,41.2579040527],"type":"Point"}
}