{
  "type": "Feature",
  "properties": {
    "addr:full":"Calle de Allariz, 10 Madrid Madrid 28044",
    "addr:housenumber":"10",
    "addr:postcode":"madrid;28044",
    "addr:street":"Calle De Allariz",
    "iso:country":"ES",
    "sg:address":"Calle de Allariz, 10",
    "sg:city":"Madrid",
    "sg:orig_category":"Librer\u00cdas",
    "sg:phone":"+34 915 08 68 57",
    "sg:postcode":"28044",
    "sg:province":"Madrid",
    "wof:name":"Casta\u00f1o Ruiz Aurora",
    "wof:placetype":"venue"
},
  "geometry": {"coordinates":[-3.7552108765,40.367401123],"type":"Point"}
}