{
  "type": "Feature",
  "properties": {
    "addr:full":"Calle de Colon, 15 Madrid Madrid 28004",
    "addr:housenumber":"15",
    "addr:postcode":"madrid;28004",
    "addr:street":"Calle De Colon",
    "iso:country":"ES",
    "sg:address":"Calle de Colon, 15",
    "sg:city":"Madrid",
    "sg:orig_category":"Molduras, Junquillos, Listones Y Molduras Perforadas",
    "sg:phone":"+34 915 21 84 03",
    "sg:postcode":"28004",
    "sg:province":"Madrid",
    "wof:name":"Diaz Diaz Julian",
    "wof:placetype":"venue"
},
  "geometry": {"coordinates":[-3.7022235394,40.4238243103],"type":"Point"}
}