{
  "type": "Feature",
  "properties": {
    "addr:full":"Calle de Santa Barbara, 36 Elda Alicante 03600",
    "addr:housenumber":"36",
    "addr:postcode":"03600",
    "addr:street":"Calle De Santa Barbara",
    "iso:country":"ES",
    "sg:address":"Calle de Santa Barbara, 36",
    "sg:city":"Elda",
    "sg:orig_category":"Clubes Y Asociaciones Deportivas Y De Actividades Invernales Y De Monta\u00d1a",
    "sg:phone":"+34 965 38 61 03",
    "sg:postcode":"03600",
    "sg:province":"Alicante",
    "wof:name":"Club Billar Idella",
    "wof:placetype":"venue"
},
  "geometry": {"coordinates":[-0.7907480001,38.4818229675],"type":"Point"}
}