{
  "type": "Feature",
  "properties": {
    "addr:full":"Calle de Puerto De Porzuna, 7 Madrid Madrid 28031",
    "addr:housenumber":"7",
    "addr:postcode":"madrid;28031",
    "addr:street":"Calle De Puerto De Porzuna",
    "iso:country":"ES",
    "sg:address":"Calle de Puerto De Porzuna, 7",
    "sg:city":"Madrid",
    "sg:orig_category":"Pod\u00d3logos: Pedicuros",
    "sg:phone":"+34 913 32 43 08",
    "sg:postcode":"28031",
    "sg:province":"Madrid",
    "wof:name":"Gomez Maya Montserrat",
    "wof:placetype":"venue"
},
  "geometry": {"coordinates":[-3.6211240292,40.3756637573],"type":"Point"}
}