{
  "type": "Feature",
  "properties": {
    "addr:full":"Calle de D.manuel Duran Lopez, 6 Torre Mar M\u00e1laga 29740",
    "addr:housenumber":"6",
    "addr:postcode":"29740",
    "addr:street":"Calle De D.Manuel;Lopez;Ma\u0301Laga",
    "iso:country":"ES",
    "sg:address":"Calle de D.manuel Duran Lopez, 6",
    "sg:city":"Torre Mar",
    "sg:orig_category":"Cristaler\u00cdas",
    "sg:phone":"+34 952 54 77 91",
    "sg:postcode":"29740",
    "sg:province":"M\u00e1laga",
    "wof:name":"Martin Gomez Sergio",
    "wof:placetype":"venue"
},
  "geometry": {"coordinates":[-4.4200186729,36.7196464539],"type":"Point"}
}