{
  "type": "Feature",
  "properties": {
    "iso:country":"ES",
    "sg:address":"Calle de Heraclio Fournier, 4",
    "sg:city":"Vitoria-gasteiz",
    "sg:orig_category":"Caf\u00c9s, Bares, Cervecer\u00cdas",
    "sg:phone":"+34 945 13 92 31",
    "sg:postcode":"01006",
    "sg:province":"\u00c1lava",
    "wof:name":"Fermu\u00f1 S.c.",
    "wof:placetype":"venue"
},
  "geometry": {"coordinates":[-2.6654109955,42.8382415771],"type":"Point"}
}