{
  "type": "Feature",
  "properties": {
    "iso:country":"ES",
    "sg:address":"Carrer de Pansa (de La), 14",
    "sg:city":"Pedreguer",
    "sg:orig_category":"Fabricaci\u00d3n De Ventanas",
    "sg:phone":"+34 966 45 72 53",
    "sg:postcode":"03750",
    "sg:province":"Alicante",
    "wof:name":"Cristal Windows Doors & Conservatories S.l.",
    "wof:placetype":"venue"
},
  "geometry": {"coordinates":[0.0418800004,38.8007316589],"type":"Point"}
}