{
  "type": "Feature",
  "properties": {
    "iso:country":"ES",
    "sg:address":"Calle de Velazquez, 2",
    "sg:city":"Sevilla",
    "sg:orig_category":"Zapatos (al Por Menor)",
    "sg:phone":"+34 954 56 22 35",
    "sg:postcode":"41001",
    "sg:province":"Sevilla",
    "wof:name":"Jacinta Parra Arcos S.c.",
    "wof:placetype":"venue"
},
  "geometry": {"coordinates":[-5.9955620766,37.3917961121],"type":"Point"}
}