{
  "type": "Feature",
  "properties": {
    "addr:full":"Calle de Moya, 12 Ejido Almer\u00eda 04700",
    "addr:housenumber":"12 ejido",
    "addr:postcode":"04700",
    "addr:street":"Calle De Moya;Almeri\u0301A",
    "iso:country":"ES",
    "sg:address":"Calle de Moya, 12",
    "sg:city":"Ejido",
    "sg:classifiers":[
        {
            "category":"Communications",
            "type":"Services"
        }
    ],
    "sg:phone":"+34 950 57 08 06",
    "sg:postcode":"04700",
    "sg:province":"Almer\u00eda",
    "sg:tags":[
        "televisiones",
        "y",
        "radio"
    ],
    "sg:website":"www.ejidotv.com",
    "wof:name":"Producciones Del Poniente S.l",
    "wof:placetype":"venue"
},
  "geometry": {"coordinates":[-2.8185589314,36.7720298767],"type":"Point"}
}