{
  "type": "Feature",
  "properties": {
    "addr:full":"C/ Assegador, 27 Alcoi Alicante 03802",
    "addr:housenumber":"27",
    "addr:postcode":"03802",
    "addr:street":"C / Assegador",
    "iso:country":"ES",
    "sg:address":"C/ Assegador, 27",
    "sg:city":"Alcoi",
    "sg:orig_category":"Carnicer\u00cdas, Carnicer\u00cdas",
    "sg:phone":"+34 965 33 44 80",
    "sg:postcode":"03802",
    "sg:province":"Alicante",
    "wof:name":"Sanchez Perez Jose",
    "wof:placetype":"venue"
},
  "geometry": {"coordinates":[-0.4928799868,38.688873291],"type":"Point"}
}