{
  "type": "Feature",
  "properties": {
    "addr:full":"Calle de Rey Juan Carlos I, 14 Villanueva Ariscal Sevilla 41808",
    "addr:housenumber":"14",
    "addr:postcode":"41808",
    "addr:street":"Calle De Rey Juan Carlos I",
    "iso:country":"ES",
    "sg:address":"Calle de Rey Juan Carlos I, 14",
    "sg:city":"Villanueva Ariscal",
    "sg:orig_category":"Asociaciones Y Clubs Deportivos",
    "sg:phone":"+34 954 11 31 34",
    "sg:postcode":"41808",
    "sg:province":"Sevilla",
    "wof:name":"Pe\u00f1a Betica Villanueva",
    "wof:placetype":"venue"
},
  "geometry": {"coordinates":[-6.1437211037,37.395149231],"type":"Point"}
}