{
  "type": "Feature",
  "properties": {
    "addr:full":"Avda Sagunto (de), 114 Teruel Teruel 44002",
    "addr:housenumber":"114",
    "addr:postcode":"44002",
    "addr:street":"Avda Sagunto De",
    "iso:country":"ES",
    "sg:address":"Avda Sagunto (de), 114",
    "sg:city":"Teruel",
    "sg:orig_category":"Electrodom\u00c9sticos (al Por Menor)",
    "sg:phone":"+34 978 22 11 94",
    "sg:postcode":"44002",
    "sg:province":"Teruel",
    "wof:name":"Domar Electrodomesticos S.l.",
    "wof:placetype":"venue"
},
  "geometry": {"coordinates":[-1.0925890207,40.333278656],"type":"Point"}
}