{
  "type": "Feature",
  "properties": {
    "addr:full":"Pase Zorrilla, 130 Valladolid Valladolid 47006",
    "addr:housenumber":"130",
    "addr:postcode":"47006",
    "addr:street":"Zorrilla",
    "iso:country":"ES",
    "sg:address":"Pase Zorrilla, 130",
    "sg:city":"Valladolid",
    "sg:orig_category":"Agencias De Viajes",
    "sg:phone":"+34 983 22 54 34",
    "sg:postcode":"47006",
    "sg:province":"Valladolid",
    "sg:website":"www.viajeselcorteingles.es",
    "wof:name":"Viajes El Corte Ingles S.a.",
    "wof:placetype":"venue"
},
  "geometry": {"coordinates":[-4.739346981,41.6367988586],"type":"Point"}
}