{
  "type": "Feature",
  "properties": {
    "iso:country":"ES",
    "sg:address":"Calle de Puerta Del Sol, 2",
    "sg:city":"Algete",
    "sg:orig_category":"Agentes Generales De Seguros",
    "sg:phone":"+34 916 28 15 42",
    "sg:postcode":"28110",
    "sg:province":"Madrid",
    "wof:name":"De La Puebla De Mesa Jose Maria",
    "wof:placetype":"venue"
},
  "geometry": {"coordinates":[-3.4975910187,40.5953483582],"type":"Point"}
}