{
  "type": "Feature",
  "properties": {
    "addr:full":"Carrer de Sant Fructuos, 5 Tarragona Tarragona 43003",
    "addr:housenumber":"5",
    "addr:postcode":"43003",
    "addr:street":"Carrer De Sant Fructuos",
    "iso:country":"ES",
    "sg:address":"Carrer de Sant Fructuos, 5",
    "sg:city":"Tarragona",
    "sg:orig_category":"Caf\u00c9s, Bares, Cervecer\u00cdas",
    "sg:phone":"+34 977 23 47 51",
    "sg:postcode":"43003",
    "sg:province":"Tarragona",
    "wof:name":"Castro Benitez Luisa",
    "wof:placetype":"venue"
},
  "geometry": {"coordinates":[1.2543859482,41.1169052124],"type":"Point"}
}