{
  "type": "Feature",
  "properties": {
    "addr:full":"Carrer de Llovera, 30 Reus Tarragona 43201",
    "addr:housenumber":"30",
    "addr:postcode":"43201",
    "addr:street":"Carrer De Llovera",
    "iso:country":"ES",
    "sg:address":"Carrer de Llovera, 30",
    "sg:city":"Reus",
    "sg:orig_category":"Bisuter\u00cda, Joyer\u00cda, Relojer\u00cda (al Por Menor)",
    "sg:phone":"+34 977 31 51 20",
    "sg:postcode":"43201",
    "sg:province":"Tarragona",
    "wof:name":"Rovira Fuster S.l.",
    "wof:placetype":"venue"
},
  "geometry": {"coordinates":[1.1063469648,41.1567955017],"type":"Point"}
}