{
  "type": "Feature",
  "properties": {
    "addr:full":"Calle de Cordoba, 33 Rincon Victoria M\u00e1laga 29730",
    "addr:housenumber":"33",
    "addr:postcode":"29730",
    "addr:street":"Calle De Cordoba;Ma\u0301Laga",
    "iso:country":"ES",
    "sg:address":"Calle de Cordoba, 33",
    "sg:city":"Rincon Victoria",
    "sg:orig_category":"Mec\u00c1nico Del Autom\u00d3vil",
    "sg:phone":"+34 952 40 54 76",
    "sg:postcode":"29730",
    "sg:province":"M\u00e1laga",
    "wof:name":"Moreno Aranda Jose",
    "wof:placetype":"venue"
},
  "geometry": {"coordinates":[-4.2837734222,36.7153129578],"type":"Point"}
}