{
  "type": "Feature",
  "properties": {
    "iso:country":"ES",
    "sg:address":"Pol Ind Alfares, 5",
    "sg:city":"Rambla",
    "sg:orig_category":"Alfarer\u00cda",
    "sg:phone":"+34 957 68 30 49",
    "sg:postcode":"14540",
    "sg:province":"C\u00f3rdoba",
    "wof:name":"Ceramica Los Amigos",
    "wof:placetype":"venue"
},
  "geometry": {"coordinates":[-4.7416338921,37.6080932617],"type":"Point"}
}