{
  "type": "Feature",
  "properties": {
    "addr:full":"Calle de Real, 9 Navatejera Le\u00f3n 24008",
    "addr:housenumber":"9",
    "addr:postcode":"24008",
    "addr:street":"Calle De Real;Leo\u0301N",
    "iso:country":"ES",
    "sg:address":"Calle de Real, 9",
    "sg:city":"Navatejera",
    "sg:orig_category":"Motores Diessel",
    "sg:phone":"+34 987 28 54 48",
    "sg:postcode":"24008",
    "sg:province":"Le\u00f3n",
    "sg:website":"www.paginasamarillas.es",
    "wof:name":"Ricardo Vuelta Villafa\u00f1e Y Bernardo Vuelta Villafa\u00f1e C.b.",
    "wof:placetype":"venue"
},
  "geometry": {"coordinates":[-5.5550928116,42.6448745728],"type":"Point"}
}