{
  "type": "Feature",
  "properties": {
    "addr:full":"Rbla Anselm Clave, 39 Cornella Llobregat Barcelona 08940",
    "addr:housenumber":"39",
    "addr:postcode":"08940",
    "addr:street":"Rbla Anselm Clave",
    "iso:country":"ES",
    "sg:address":"Rbla Anselm Clave, 39",
    "sg:city":"Cornella Llobregat",
    "sg:orig_category":"Relojer\u00cda (al Por Menor, Reparaci\u00d3n)",
    "sg:phone":"+34 933 77 08 81",
    "sg:postcode":"08940",
    "sg:province":"Barcelona",
    "wof:name":"Joieria Macia S.c.p.",
    "wof:placetype":"venue"
},
  "geometry": {"coordinates":[2.073472023,41.3538360596],"type":"Point"}
}