{
  "type": "Feature",
  "properties": {
    "iso:country":"ES",
    "sg:address":"Rua Ramon Cabanillas, 18",
    "sg:city":"Ourense",
    "sg:orig_category":"Caf\u00c9s, Bares, Cervecer\u00cdas",
    "sg:phone":"+34 988 23 43 61",
    "sg:postcode":"32004",
    "sg:province":"Ourense",
    "wof:name":"Jam Session S.l.",
    "wof:placetype":"venue"
},
  "geometry": {"coordinates":[-7.8602890968,42.3412284851],"type":"Point"}
}