{
  "type": "Feature",
  "properties": {
    "iso:country":"ES",
    "sg:address":"Calle de Reina Sofia, S/n",
    "sg:city":"Puerto Del Carmen",
    "sg:classifiers":[
        {
            "category":"Arts & Performance",
            "subcategory":"Art Gallery",
            "type":"Entertainment"
        }
    ],
    "sg:phone":"+34 928 51 68 53",
    "sg:postcode":"35510",
    "sg:province":"Las Palmas",
    "sg:tags":[
        "arte",
        "de",
        "galer\u00cdas"
    ],
    "wof:name":"Art Canary Island S.l.",
    "wof:placetype":"venue"
},
  "geometry": {"coordinates":[-13.6741609573,28.9247341156],"type":"Point"}
}