{
  "type": "Feature",
  "properties": {
    "iso:country":"ES",
    "sg:address":"Calle de San Anton, 1",
    "sg:city":"Mota Cuervo",
    "sg:orig_category":"Inform\u00c1tica: Consultores",
    "sg:phone":"+34 967 13 95 39",
    "sg:postcode":"16630",
    "sg:province":"Cuenca",
    "wof:name":"Cruz Casero S. L.",
    "wof:placetype":"venue"
},
  "geometry": {"coordinates":[-2.8714790344,39.4979438782],"type":"Point"}
}