{
  "type": "Feature",
  "properties": {
    "addr:full":"Carrer de Pau, S/n Manresa Barcelona 08243",
    "addr:housenumber":"s / n",
    "addr:postcode":"08243",
    "addr:street":"Carrer De Pau",
    "iso:country":"ES",
    "sg:address":"Carrer de Pau, S/n",
    "sg:city":"Manresa",
    "sg:orig_category":"Internados & Ense\u00d1anza Privada",
    "sg:phone":"+34 938 74 03 51",
    "sg:postcode":"08243",
    "sg:province":"Barcelona",
    "wof:name":"Hermanos Escuelas Cristianas La Salle",
    "wof:placetype":"venue"
},
  "geometry": {"coordinates":[1.8327499628,41.7367248535],"type":"Point"}
}