{
  "type": "Feature",
  "properties": {
    "addr:full":"Calle de Juan Jose Ruano, 1 Torrelavega Cantabria 39300",
    "addr:housenumber":"1",
    "addr:postcode":"39300",
    "addr:street":"Calle De Juan Jose Ruano",
    "iso:country":"ES",
    "sg:address":"Calle de Juan Jose Ruano, 1",
    "sg:city":"Torrelavega",
    "sg:orig_category":"Ropa Para Se\u00d1oras (al Por Menor)",
    "sg:phone":"+34 942 80 52 44",
    "sg:postcode":"39300",
    "sg:province":"Cantabria",
    "wof:name":"Versuss S.c.",
    "wof:placetype":"venue"
},
  "geometry": {"coordinates":[-4.0461611748,43.3499183655],"type":"Point"}
}