{
  "type": "Feature",
  "properties": {
    "iso:country":"ES",
    "sg:address":"Avda Cadiz, 15",
    "sg:city":"Sevilla",
    "sg:orig_category":"Molduras, Junquillos, Listones Y Molduras Perforadas",
    "sg:phone":"+34 954 42 30 58",
    "sg:postcode":"41004",
    "sg:province":"Sevilla",
    "wof:name":"Castillo Salazar Antonio",
    "wof:placetype":"venue"
},
  "geometry": {"coordinates":[-5.9856300354,37.3829345703],"type":"Point"}
}