{
  "type": "Feature",
  "properties": {
    "iso:country":"ES",
    "sg:address":"Avda San Francisco Javier, 22",
    "sg:city":"Sevilla",
    "sg:orig_category":"Organismos De Reclutamiento",
    "sg:phone":"+34 954 65 07 48",
    "sg:postcode":"41018",
    "sg:province":"Sevilla",
    "wof:name":"Garcia Perez Inmaculada",
    "wof:placetype":"venue"
},
  "geometry": {"coordinates":[-5.9746484756,37.3791542053],"type":"Point"}
}