{
  "type": "Feature",
  "properties": {
    "iso:country":"ES",
    "sg:address":"Calle de Reyes Catolicos, 6",
    "sg:city":"Parla",
    "sg:classifiers":[
        {
            "category":"Autos & Motor Vehicles",
            "subcategory":"Automobile Sales",
            "type":"Retail Goods"
        }
    ],
    "sg:phone":"+34 916 05 06 44",
    "sg:postcode":"28980",
    "sg:province":"Madrid",
    "wof:name":"Auto Escuela Jelba S.l",
    "wof:placetype":"venue"
},
  "geometry": {"coordinates":[-3.7664525509,40.2311553955],"type":"Point"}
}