{
  "type": "Feature",
  "properties": {
    "addr:full":"Calle de Alcalde Cano Coloma, 8 Valencia Valencia 46022",
    "addr:housenumber":"8",
    "addr:postcode":"46022",
    "addr:street":"Calle De Alcalde Cano Coloma",
    "iso:country":"ES",
    "sg:address":"Calle de Alcalde Cano Coloma, 8",
    "sg:city":"Valencia",
    "sg:orig_category":"Venta, Localizaci\u00d3n, Reparaci\u00d3n De Material E Instrumental M\u00c9dico",
    "sg:phone":"+34 963 56 80 71",
    "sg:postcode":"46022",
    "sg:province":"Valencia",
    "wof:name":"Bioclar S.l.",
    "wof:placetype":"venue"
},
  "geometry": {"coordinates":[-0.33637321,39.465965271],"type":"Point"}
}