{
  "type": "Feature",
  "properties": {
    "addr:full":"Calle de Santa Clara, 136 Ciudad Rodrigo Salamanca 37500",
    "addr:housenumber":"136",
    "addr:postcode":"37500",
    "addr:street":"Calle De Santa Clara",
    "iso:country":"ES",
    "sg:address":"Calle de Santa Clara, 136",
    "sg:city":"Ciudad Rodrigo",
    "sg:orig_category":"Asociaciones Y Clubs Deportivos",
    "sg:phone":"+34 923 48 19 07",
    "sg:postcode":"37500",
    "sg:province":"Salamanca",
    "wof:name":"Ciudad Rodrigo C.f.",
    "wof:placetype":"venue"
},
  "geometry": {"coordinates":[-6.5247511864,40.6059532166],"type":"Point"}
}