{
  "type": "Feature",
  "properties": {
    "addr:full":"Calle de Jose Nogales, 17 Huelva Huelva 21001",
    "addr:housenumber":"17",
    "addr:postcode":"21001",
    "addr:street":"Calle De Jose Nogales",
    "iso:country":"ES",
    "sg:address":"Calle de Jose Nogales, 17",
    "sg:city":"Huelva",
    "sg:orig_category":"Zapatos (al Por Menor)",
    "sg:phone":"+34 959 25 50 67",
    "sg:postcode":"21001",
    "sg:province":"Huelva",
    "wof:name":"Zambrano Gordillo Maribel",
    "wof:placetype":"venue"
},
  "geometry": {"coordinates":[-6.9546790123,37.2584190369],"type":"Point"}
}