{
  "type": "Feature",
  "properties": {
    "iso:country":"ES",
    "sg:address":"Avda Zaragoza, 54",
    "sg:city":"Borriol",
    "sg:orig_category":"Muebles, Minoristas",
    "sg:phone":"+34 964 32 10 40",
    "sg:postcode":"12190",
    "sg:province":"Castell\u00f3n",
    "wof:name":"Delcampo Ramos Antonio",
    "wof:placetype":"venue"
},
  "geometry": {"coordinates":[-0.0718579963,40.0403633118],"type":"Point"}
}