{
  "type": "Feature",
  "properties": {
    "addr:full":"Calle de Iturribide, 118 Bilbao Vizcaya 48006",
    "addr:housenumber":"118",
    "addr:postcode":"48006",
    "addr:street":"Calle De Iturribide",
    "iso:country":"ES",
    "sg:address":"Calle de Iturribide, 118",
    "sg:city":"Bilbao",
    "sg:orig_category":"Asociaciones, Organismos Culturales Y Socioeducativos",
    "sg:phone":"+34 944 33 60 07",
    "sg:postcode":"48006",
    "sg:province":"Vizcaya",
    "wof:name":"Centro Extreme\u00f1o De Bilbao",
    "wof:placetype":"venue"
},
  "geometry": {"coordinates":[-2.9170489311,43.2552909851],"type":"Point"}
}