{
  "type": "Feature",
  "properties": {
    "iso:country":"ES",
    "sg:address":"Calle de Plata (del), 7",
    "sg:city":"Fuenlabrada",
    "sg:orig_category":"Aguas (distribuci\u00d3n, Servicios)",
    "sg:phone":"+34 916 90 95 79",
    "sg:postcode":"28944",
    "sg:province":"Madrid",
    "wof:name":"Ramos Guillen Jose",
    "wof:placetype":"venue"
},
  "geometry": {"coordinates":[-3.7887558937,40.2844657898],"type":"Point"}
}