{
  "type": "Feature",
  "properties": {
    "addr:full":"Carrer de Nou, 16 S. Pere Ribes Barcelona 08810",
    "addr:housenumber":"16",
    "addr:postcode":"08810",
    "addr:street":"Carrer De Nou;S. Pere Ribes Barcelona",
    "iso:country":"ES",
    "sg:address":"Carrer de Nou, 16",
    "sg:city":"S. Pere Ribes",
    "sg:orig_category":"Cajas De Ahorro",
    "sg:phone":"+34 938 96 32 68",
    "sg:postcode":"08810",
    "sg:province":"Barcelona",
    "wof:name":"Caixa D'estalvis Del Penedes",
    "wof:placetype":"venue"
},
  "geometry": {"coordinates":[1.7721960545,41.2617988586],"type":"Point"}
}