{
  "type": "Feature",
  "properties": {
    "iso:country":"ES",
    "sg:address":"Avda Cordoba (de), S/n",
    "sg:city":"Arrecife",
    "sg:orig_category":"Mec\u00c1nico Del Autom\u00d3vil",
    "sg:phone":"+34 957 30 58 03",
    "sg:postcode":"14191",
    "sg:province":"C\u00f3rdoba",
    "wof:name":"Jimenez Pino Alfonso",
    "wof:placetype":"venue"
},
  "geometry": {"coordinates":[-4.8806638718,37.7054252625],"type":"Point"}
}