{
  "type": "Feature",
  "properties": {
    "addr:full":"Calle de Almirante Bonifaz, 12 Burgos Burgos 09003",
    "addr:housenumber":"12",
    "addr:postcode":"09003",
    "addr:street":"Calle De Almirante Bonifaz",
    "iso:country":"ES",
    "sg:address":"Calle de Almirante Bonifaz, 12",
    "sg:city":"Burgos",
    "sg:orig_category":"Agencias De Viajes",
    "sg:phone":"+34 947 25 62 63",
    "sg:postcode":"09003",
    "sg:province":"Burgos",
    "sg:website":"www.viajeselcorteingles.es",
    "wof:name":"Viajes El Corte Ingles S.a.",
    "wof:placetype":"venue"
},
  "geometry": {"coordinates":[-3.7004220486,42.3421783447],"type":"Point"}
}