{
  "type": "Feature",
  "properties": {
    "addr:full":"Av Catalunya, 10 Anglesola Lleida 25320",
    "addr:housenumber":"10",
    "addr:postcode":"25320",
    "addr:street":"Av Catalunya",
    "iso:country":"ES",
    "sg:address":"Av Catalunya, 10",
    "sg:city":"Anglesola",
    "sg:orig_category":"Inform\u00c1tica, Ofim\u00c1tica (estudios, Asesor\u00cda, Ingenier\u00cda, Formaci\u00d3n)",
    "sg:phone":"+34 973 30 83 01",
    "sg:postcode":"25320",
    "sg:province":"Lleida",
    "wof:name":"Vidal Ginesta Antoni",
    "wof:placetype":"venue"
},
  "geometry": {"coordinates":[1.0837850571,41.6582374573],"type":"Point"}
}