{
  "type": "Feature",
  "properties": {
    "addr:full":"Calle de Mirasierra, S/n Navalcarnero Madrid 28600",
    "addr:housenumber":"s / n",
    "addr:postcode":"28600",
    "addr:street":"Calle De Mirasierra",
    "iso:country":"ES",
    "sg:address":"Calle de Mirasierra, S/n",
    "sg:city":"Navalcarnero",
    "sg:orig_category":"Bricolaje, Herramientas (al Por Menor)",
    "sg:phone":"+34 918 11 16 39",
    "sg:postcode":"28600",
    "sg:province":"Madrid",
    "wof:name":"Pomares Montalban Agustina",
    "wof:placetype":"venue"
},
  "geometry": {"coordinates":[-4.0149497986,40.2931251526],"type":"Point"}
}