{
  "type": "Feature",
  "properties": {
    "iso:country":"ES",
    "sg:address":"Carrer de Queralt, 4",
    "sg:city":"Barcelona",
    "sg:orig_category":"Art\u00cdculos De Regalo (al Por Menor)",
    "sg:phone":"+34 934 06 91 52",
    "sg:postcode":"08017",
    "sg:province":"Barcelona",
    "wof:name":"Coll Borras Gemma",
    "wof:placetype":"venue"
},
  "geometry": {"coordinates":[2.1047899723,41.4132766724],"type":"Point"}
}