{
  "type": "Feature",
  "properties": {
    "iso:country":"ES",
    "sg:address":"Poli Industrial C/n, S/n",
    "sg:city":"Rozas De Madrid",
    "sg:orig_category":"Material De Ocasi\u00d3n (compra, Reventa)",
    "sg:phone":"+34 916 37 23 74",
    "sg:postcode":"28230",
    "sg:province":"Madrid",
    "wof:name":"Inversail S.a.",
    "wof:placetype":"venue"
},
  "geometry": {"coordinates":[-3.8913800716,40.5247497559],"type":"Point"}
}