{
  "type": "Feature",
  "properties": {
    "addr:full":"Calle de Lepe, 4 Cartaya Huelva 21450",
    "addr:housenumber":"4",
    "addr:postcode":"21450",
    "addr:street":"Calle De Lepe",
    "iso:country":"ES",
    "sg:address":"Calle de Lepe, 4",
    "sg:city":"Cartaya",
    "sg:orig_category":"Peluqueros: De Se\u00d1oras",
    "sg:phone":"+34 959 39 12 56",
    "sg:postcode":"21450",
    "sg:province":"Huelva",
    "wof:name":"Maestre Cruz Josefa",
    "wof:placetype":"venue"
},
  "geometry": {"coordinates":[-7.1528987885,37.2844581604],"type":"Point"}
}