{
  "type": "Feature",
  "properties": {
    "iso:country":"ES",
    "sg:address":"Carrer de Pintor Fortuny, 26",
    "sg:city":"Barcelona",
    "sg:orig_category":"Alimentaci\u00d3n General (al Por Menor)",
    "sg:phone":"+34 933 18 84 87",
    "sg:postcode":"08001",
    "sg:province":"Barcelona",
    "wof:name":"Plaza Del Moral Saturnino",
    "wof:placetype":"venue"
},
  "geometry": {"coordinates":[2.1690440178,41.3826522827],"type":"Point"}
}