{
  "type": "Feature",
  "properties": {
    "addr:full":"Calle de Jose Simon Cabarga, 8 Santander Cantabria 39005",
    "addr:housenumber":"8",
    "addr:postcode":"39005",
    "addr:street":"Calle De Jose Simon Cabarga",
    "iso:country":"ES",
    "sg:address":"Calle de Jose Simon Cabarga, 8",
    "sg:city":"Santander",
    "sg:orig_category":"Institutos De Belleza",
    "sg:phone":"+34 942 27 80 55",
    "sg:postcode":"39005",
    "sg:province":"Cantabria",
    "wof:name":"Martinez Gutierrez Inmaculada",
    "wof:placetype":"venue"
},
  "geometry": {"coordinates":[-3.7898509502,43.4712371826],"type":"Point"}
}