{
  "type": "Feature",
  "properties": {
    "addr:full":"Carrer de Teide, 48 Hospitalet Llobregat Barcelona 08901",
    "addr:housenumber":"48",
    "addr:postcode":"08901",
    "addr:street":"Carrer De Teide",
    "iso:country":"ES",
    "sg:address":"Carrer de Teide, 48",
    "sg:city":"Hospitalet Llobregat",
    "sg:orig_category":"Empresas De Carpinter\u00cda De Madera",
    "sg:phone":"+34 934 38 02 92",
    "sg:postcode":"08901",
    "sg:province":"Barcelona",
    "wof:name":"Carranza Esquivel Jose Maria",
    "wof:placetype":"venue"
},
  "geometry": {"coordinates":[2.105494976,41.3626899719],"type":"Point"}
}