{
  "type": "Feature",
  "properties": {
    "iso:country":"ES",
    "sg:address":"Av Sant Esteve, 70",
    "sg:city":"Granollers",
    "sg:orig_category":"Administradores De Bienes Y Delegados De Comunidades De Propietarios",
    "sg:phone":"+34 938 70 57 05",
    "sg:postcode":"08402",
    "sg:province":"Barcelona",
    "sg:website":"www.alfainmo.com",
    "wof:name":"Inmobiliaria D'administradors Alfa Barcelona S.a.",
    "wof:placetype":"venue"
},
  "geometry": {"coordinates":[2.2906420231,41.601600647],"type":"Point"}
}