{
  "type": "Feature",
  "properties": {
    "addr:full":"Calle de Carramajuelos, S/n Carbonero El Mayor Segovia 40270",
    "addr:housenumber":"s / n",
    "addr:postcode":"40270",
    "addr:street":"Calle De Carramajuelos",
    "iso:country":"ES",
    "sg:address":"Calle de Carramajuelos, S/n",
    "sg:city":"Carbonero El Mayor",
    "sg:orig_category":"Pescader\u00cdas (al Por Menor)",
    "sg:phone":"+34 921 56 08 56",
    "sg:postcode":"40270",
    "sg:province":"Segovia",
    "wof:name":"Herrero Manso Marcos",
    "wof:placetype":"venue"
},
  "geometry": {"coordinates":[-4.2619895935,41.124332428],"type":"Point"}
}