{
  "type": "Feature",
  "properties": {
    "addr:full":"Calle de Puerto De La Mano De Hierro, 4 Madrid Madrid 28053",
    "addr:housenumber":"4",
    "addr:postcode":"28053",
    "addr:street":"Calle De Puerto De La",
    "iso:country":"ES",
    "sg:address":"Calle de Puerto De La Mano De Hierro, 4",
    "sg:city":"Madrid",
    "sg:orig_category":"Empresas De Limpieza",
    "sg:phone":"+34 914 78 56 84",
    "sg:postcode":"28053",
    "sg:province":"Madrid",
    "wof:name":"Urbaser S.a.",
    "wof:placetype":"venue"
},
  "geometry": {"coordinates":[-3.6707570553,40.3915748596],"type":"Point"}
}