{
  "type": "Feature",
  "properties": {
    "addr:full":"Calle de Pelayo, 6 Valencia Valencia 46007",
    "addr:housenumber":"6",
    "addr:postcode":"46007",
    "addr:street":"Calle De Pelayo",
    "iso:country":"ES",
    "sg:address":"Calle de Pelayo, 6",
    "sg:city":"Valencia",
    "sg:orig_category":"Caf\u00c9s, Bares, Cervecer\u00cdas",
    "sg:phone":"+34 963 52 68 45",
    "sg:postcode":"46007",
    "sg:province":"Valencia",
    "wof:name":"Trinquete De Pelayo S. A.",
    "wof:placetype":"venue"
},
  "geometry": {"coordinates":[-0.378531009,39.4674453735],"type":"Point"}
}