{
  "type": "Feature",
  "properties": {
    "iso:country":"ES",
    "sg:address":"Cmno Capuchinos, 2",
    "sg:city":"Alca\u00f1iz",
    "sg:orig_category":"Producci\u00d3n, Venta De Productos De Agricultura Biol\u00d3gica",
    "sg:phone":"+34 978 83 35 98",
    "sg:postcode":"44600",
    "sg:province":"Teruel",
    "wof:name":"Agut Vilalta Isabel",
    "wof:placetype":"venue"
},
  "geometry": {"coordinates":[-0.1380237043,41.0527839661],"type":"Point"}
}