{
  "type": "Feature",
  "properties": {
    "addr:full":"Cno. Tirez, S/n Villaca\u00f1as Toledo 45860",
    "addr:postcode":"45860",
    "addr:street":"Tirez S / N Villacan\u0303As",
    "iso:country":"ES",
    "sg:address":"Cno. Tirez, S/n",
    "sg:city":"Villaca\u00f1as",
    "sg:orig_category":"Cl\u00cdnicas M\u00c9dicas",
    "sg:phone":"+34 925 20 17 29",
    "sg:postcode":"45860",
    "sg:province":"Toledo",
    "wof:name":"Servicio De Salud De Castilla La Mancha",
    "wof:placetype":"venue"
},
  "geometry": {"coordinates":[-3.3340990543,39.6178359985],"type":"Point"}
}