{
  "type": "Feature",
  "properties": {
    "iso:country":"ES",
    "sg:address":"Avda Vilari\u00d1o, 20",
    "sg:city":"Cambados",
    "sg:orig_category":"Arquitectos",
    "sg:phone":"+34 986 54 31 29",
    "sg:postcode":"36630",
    "sg:province":"Pontevedra",
    "wof:name":"Oubi\u00f1a Bua Elias Antonio",
    "wof:placetype":"venue"
},
  "geometry": {"coordinates":[-8.810464859,42.5161590576],"type":"Point"}
}