{
  "type": "Feature",
  "properties": {
    "addr:full":"Rubiacos, S/n Luintra Ourense 32160",
    "addr:postcode":"32160",
    "addr:street":"Rubiacos S / N",
    "iso:country":"ES",
    "sg:address":"Rubiacos, S/n",
    "sg:city":"Luintra",
    "sg:orig_category":"Suministros Para Empresas De Pintura",
    "sg:phone":"+34 988 20 10 14",
    "sg:postcode":"32160",
    "sg:province":"Ourense",
    "wof:name":"Al-rifay Alvarez Omar",
    "wof:placetype":"venue"
},
  "geometry": {"coordinates":[-7.7279982567,42.4117088318],"type":"Point"}
}