{
  "type": "Feature",
  "properties": {
    "addr:full":"Cami Vileta (la), 11 Vileta Islas Baleares 07011",
    "addr:housenumber":"11",
    "addr:postcode":"07011",
    "addr:street":"Vileta;Vileta Islas",
    "iso:country":"ES",
    "sg:address":"Cami Vileta (la), 11",
    "sg:city":"Vileta",
    "sg:orig_category":"Trabajos De Fotocomposici\u00d3n",
    "sg:phone":"+34 971 28 51 76",
    "sg:postcode":"07011",
    "sg:province":"Islas Baleares",
    "wof:name":"Soporte Informatico De Baleares S.l.",
    "wof:placetype":"venue"
},
  "geometry": {"coordinates":[2.6247079372,39.5888137817],"type":"Point"}
}