{
  "type": "Feature",
  "properties": {
    "addr:full":"Calle de Severo Ochoa, 1 Lugones Asturias 33420",
    "addr:housenumber":"1",
    "addr:postcode":"33420",
    "addr:street":"Calle De Severo Ochoa",
    "iso:country":"ES",
    "sg:address":"Calle de Severo Ochoa, 1",
    "sg:city":"Lugones",
    "sg:orig_category":"Retoques De Vestidos",
    "sg:phone":"+34 985 26 21 18",
    "sg:postcode":"33420",
    "sg:province":"Asturias",
    "wof:name":"Vega Fernandez Maria Yodita",
    "wof:placetype":"venue"
},
  "geometry": {"coordinates":[-5.8109025955,43.4016838074],"type":"Point"}
}