{
  "type": "Feature",
  "properties": {
    "iso:country":"ES",
    "sg:address":"Calle de Juan Ramon Jimenez, 2",
    "sg:city":"Umbrete",
    "sg:orig_category":"Pirotecnia (espect\u00c1culos)",
    "sg:phone":"+34 955 71 63 13",
    "sg:postcode":"41806",
    "sg:province":"Sevilla",
    "wof:name":"Campos Simon Antonio",
    "wof:placetype":"venue"
},
  "geometry": {"coordinates":[-6.1566419601,37.3677177429],"type":"Point"}
}