{
  "type": "Feature",
  "properties": {
    "addr:full":"La Isleta, S/n El Campello Alicante 03560",
    "addr:housenumber":"s / n",
    "addr:postcode":"03560",
    "addr:street":"Isleta",
    "iso:country":"ES",
    "sg:address":"La Isleta, S/n",
    "sg:city":"El Campello",
    "sg:orig_category":"Restaurantes",
    "sg:phone":"+34 965 63 43 71",
    "sg:postcode":"03560",
    "sg:province":"Alicante",
    "wof:name":"Lledo Vaello Emilio",
    "wof:placetype":"venue"
},
  "geometry": {"coordinates":[-0.3906340003,38.4271888733],"type":"Point"}
}