{
  "type": "Feature",
  "properties": {
    "addr:full":"Carrer de Francesc Macia, 32 Castellbisbal Barcelona 08755",
    "addr:housenumber":"32",
    "addr:postcode":"08755",
    "addr:street":"Carrer De Francesc Macia",
    "iso:country":"ES",
    "sg:address":"Carrer de Francesc Macia, 32",
    "sg:city":"Castellbisbal",
    "sg:orig_category":"Agencias Y Agentes Comerciales, Representantes",
    "sg:phone":"+34 937 71 13 50",
    "sg:postcode":"08755",
    "sg:province":"Barcelona",
    "wof:name":"Roman Espada Rafael",
    "wof:placetype":"venue"
},
  "geometry": {"coordinates":[1.9835699797,41.4762916565],"type":"Point"}
}