{
  "type": "Feature",
  "properties": {
    "iso:country":"ES",
    "sg:address":"Estd Castela, 212",
    "sg:city":"Ferrol",
    "sg:orig_category":"Caf\u00c9s, Bares, Cervecer\u00cdas",
    "sg:phone":"+34 981 37 07 59",
    "sg:postcode":"15404",
    "sg:province":"La Coru\u00f1a",
    "wof:name":"Rubido Alonso Pilar",
    "wof:placetype":"venue"
},
  "geometry": {"coordinates":[-8.214050293,43.4919471741],"type":"Point"}
}