{
  "type": "Feature",
  "properties": {
    "iso:country":"ES",
    "sg:address":"Cmno Coco, 10",
    "sg:city":"Baldio",
    "sg:orig_category":"Inform\u00c1tica (estudios, Servicios, Asesor\u00cda, Formaci\u00d3n)",
    "sg:phone":"+34 922 54 10 45",
    "sg:postcode":"38280",
    "sg:province":"Santa Cruz De Tenerife",
    "wof:name":"Gutierrez Alonso Crisanto Mateos",
    "wof:placetype":"venue"
},
  "geometry": {"coordinates":[-16.3384094238,28.5215549469],"type":"Point"}
}