{
  "type": "Feature",
  "properties": {
    "iso:country":"ES",
    "sg:address":"Calle de General Rodrigo, 6",
    "sg:city":"Madrid",
    "sg:orig_category":"Promotores Constructores",
    "sg:phone":"+34 915 35 35 82",
    "sg:postcode":"28003",
    "sg:province":"Madrid",
    "wof:name":"Proesinco S.a.",
    "wof:placetype":"venue"
},
  "geometry": {"coordinates":[-3.71398592,40.4434928894],"type":"Point"}
}