{
  "type": "Feature",
  "properties": {
    "iso:country":"ES",
    "sg:address":"Carrer de Floridablanca, 10",
    "sg:city":"Barcelona",
    "sg:orig_category":"Artes Gr\u00c1ficas, Artes Pl\u00c1sticas (curso)",
    "sg:phone":"+34 934 23 84 93",
    "sg:postcode":"08015",
    "sg:province":"Barcelona",
    "wof:name":"Hermanos Veguillas S.a.",
    "wof:placetype":"venue"
},
  "geometry": {"coordinates":[2.1548659801,41.3755645752],"type":"Point"}
}