{
  "type": "Feature",
  "properties": {
    "addr:full":"Calle de Moreria, 6 Cordoba C\u00f3rdoba 14008",
    "addr:housenumber":"6",
    "addr:postcode":"14008",
    "addr:street":"Calle De Moreria;Co\u0301Rdoba",
    "iso:country":"ES",
    "sg:address":"Calle de Moreria, 6",
    "sg:city":"Cordoba",
    "sg:orig_category":"M\u00c9dicos: Psiquiatr\u00cda",
    "sg:phone":"+34 957 49 01 63",
    "sg:postcode":"14008",
    "sg:province":"C\u00f3rdoba",
    "wof:name":"Aguera Fernandez Antonio Jose",
    "wof:placetype":"venue"
},
  "geometry": {"coordinates":[-4.7805523872,37.8851394653],"type":"Point"}
}