{
  "type": "Feature",
  "properties": {
    "addr:full":"Ramon Irizar Kalea, 2 O\u00f1ati Guip\u00f9zcoa 20560",
    "addr:housenumber":"2",
    "addr:postcode":"20560",
    "addr:street":"Ramon Irizar Kalea;Guipu\u0300Zcoa",
    "iso:country":"ES",
    "sg:address":"Ramon Irizar Kalea, 2",
    "sg:city":"O\u00f1ati",
    "sg:orig_category":"Fabricaci\u00d3n, Venta De Cuadros, Accesorios Para Enmarcar",
    "sg:phone":"+34 943 78 33 43",
    "sg:postcode":"20560",
    "sg:province":"Guip\u00f9zcoa",
    "wof:name":"Zuri\u00f1e Mendia Landa (hegoia)",
    "wof:placetype":"venue"
},
  "geometry": {"coordinates":[-2.4126799107,43.0317077637],"type":"Point"}
}