{
  "type": "Feature",
  "properties": {
    "iso:country":"ES",
    "sg:address":"Calle de Jacinto Guerrero, 3",
    "sg:city":"Talavera Reina",
    "sg:orig_category":"Peluquer\u00cdas",
    "sg:phone":"+34 925 82 11 10",
    "sg:postcode":"45600",
    "sg:province":"Toledo",
    "wof:name":"Traid Look S.l.",
    "wof:placetype":"venue"
},
  "geometry": {"coordinates":[-4.8296408653,39.960647583],"type":"Point"}
}