{
  "type": "Feature",
  "properties": {
    "iso:country":"ES",
    "sg:address":"Calle de Ingeniero Torres Quevedo, S/n",
    "sg:city":"Cordoba",
    "sg:orig_category":"Condimentos, Especias, Vinagres, Salsas Preparadas (fabricaci\u00d3n, Al Por Mayor)",
    "sg:phone":"+34 957 20 22 67",
    "sg:postcode":"14013",
    "sg:province":"C\u00f3rdoba",
    "wof:name":"Adilasa S.l.",
    "wof:placetype":"venue"
},
  "geometry": {"coordinates":[-4.7928767204,37.852722168],"type":"Point"}
}