{
  "type": "Feature",
  "properties": {
    "iso:country":"ES",
    "sg:address":"Avda Reyes Catolicos, 25",
    "sg:city":"Arnedo",
    "sg:classifiers":[
        {
            "category":"Taxi",
            "type":"Transportation"
        }
    ],
    "sg:phone":"+34 941 38 00 61",
    "sg:postcode":"26580",
    "sg:province":"La Rioja",
    "wof:name":"Herreros Salcedo Jose Antonio",
    "wof:placetype":"venue"
},
  "geometry": {"coordinates":[-2.1033740044,42.2232170105],"type":"Point"}
}