{
  "type": "Feature",
  "properties": {
    "iso:country":"ES",
    "sg:address":"Av Paral.lel, 120",
    "sg:city":"Barcelona",
    "sg:orig_category":"Peluqueros: De Se\u00d1oras",
    "sg:phone":"+34 934 42 41 36",
    "sg:postcode":"08015",
    "sg:province":"Barcelona",
    "wof:name":"Martinez Vicente Escolastico",
    "wof:placetype":"venue"
},
  "geometry": {"coordinates":[2.1626970768,41.3751106262],"type":"Point"}
}