{
  "type": "Feature",
  "properties": {
    "iso:country":"ES",
    "sg:address":"Calle de Secretario Artiles, 20",
    "sg:city":"Palmas De Gran Canaria",
    "sg:orig_category":"Agencias De Aduana",
    "sg:phone":"+34 928 27 31 22",
    "sg:postcode":"35007",
    "sg:province":"Las Palmas",
    "wof:name":"Gonzalez Pavon Juan",
    "wof:placetype":"venue"
},
  "geometry": {"coordinates":[-15.4316864014,28.1371841431],"type":"Point"}
}