{
  "type": "Feature",
  "properties": {
    "addr:full":"Carrer de Omelades, 2 Palma Islas Baleares 07012",
    "addr:housenumber":"2",
    "addr:postcode":"07012",
    "addr:street":"Carrer De Omelades",
    "iso:country":"ES",
    "sg:address":"Carrer de Omelades, 2",
    "sg:city":"Palma",
    "sg:orig_category":"Asesor\u00cda Fiscal Y Jur\u00cddica",
    "sg:phone":"+34 971 71 60 47",
    "sg:postcode":"07012",
    "sg:province":"Islas Baleares",
    "wof:name":"Roca & Fornes Auditores Consultores S.l.",
    "wof:placetype":"venue"
},
  "geometry": {"coordinates":[2.6451210976,39.5744171143],"type":"Point"}
}