{
  "type": "Feature",
  "properties": {
    "addr:full":"Calle de Plaza La Fruta, S/n Arcos Navarra 31210",
    "addr:housenumber":"s",
    "addr:postcode":"31210",
    "addr:street":"Calle De Plaza La Fruta;/ N",
    "iso:country":"ES",
    "sg:address":"Calle de Plaza La Fruta, S/n",
    "sg:city":"Arcos",
    "sg:orig_category":"Cr\u00cda De Bovinos",
    "sg:phone":"+34 948 64 02 20",
    "sg:postcode":"31210",
    "sg:province":"Navarra",
    "wof:name":"Lopez De Dicastillo Perez Fortunato",
    "wof:placetype":"venue"
},
  "geometry": {"coordinates":[-2.1922340393,42.568271637],"type":"Point"}
}