{
  "type": "Feature",
  "properties": {
    "addr:full":"Calle de Vereda Real, S/n Requena Valencia 46340",
    "addr:housenumber":"s / n",
    "addr:postcode":"46340",
    "addr:street":"Calle De Vereda Real",
    "iso:country":"ES",
    "sg:address":"Calle de Vereda Real, S/n",
    "sg:city":"Requena",
    "sg:orig_category":"Promotores Constructores",
    "sg:phone":"+34 962 30 48 30",
    "sg:postcode":"46340",
    "sg:province":"Valencia",
    "wof:name":"Francisco Navarro Garcia,s.l.",
    "wof:placetype":"venue"
},
  "geometry": {"coordinates":[-1.1044889688,39.4837493896],"type":"Point"}
}