{
  "type": "Feature",
  "properties": {
    "addr:full":"Calle de Adurtza, 8 Vitoria-gasteiz \u00c1lava 01006",
    "addr:housenumber":"8",
    "addr:postcode":"01006",
    "addr:street":"Calle De Adurtza",
    "iso:country":"ES",
    "sg:address":"Calle de Adurtza, 8",
    "sg:city":"Vitoria-gasteiz",
    "sg:orig_category":"Pintura, Barniz, Productos Asimilables (fabricaci\u00d3n, Al Por Mayor)",
    "sg:phone":"+34 945 13 65 47",
    "sg:postcode":"01006",
    "sg:province":"\u00c1lava",
    "wof:name":"Urteaga Ciardegui Esperanza",
    "wof:placetype":"venue"
},
  "geometry": {"coordinates":[-2.6628670692,42.8363647461],"type":"Point"}
}