{
  "type": "Feature",
  "properties": {
    "iso:country":"ES",
    "sg:address":"Ptda Pla De La Vallonga, 8",
    "sg:city":"Pla De La Vallonga",
    "sg:orig_category":"Guarda",
    "sg:phone":"+34 965 10 47 01",
    "sg:postcode":"03113",
    "sg:province":"Alicante",
    "wof:name":"Arrowpak International S.l.",
    "wof:placetype":"venue"
},
  "geometry": {"coordinates":[-0.5889509916,38.3436164856],"type":"Point"}
}