{
  "type": "Feature",
  "properties": {
    "iso:country":"ES",
    "sg:address":"Carrer de Roger De Flor, 289",
    "sg:city":"Barcelona",
    "sg:orig_category":"Asesor\u00cda Para La Organizaci\u00d3n Y Gesti\u00d3n Del Transporte",
    "sg:phone":"+34 932 08 17 17",
    "sg:postcode":"08025",
    "sg:province":"Barcelona",
    "wof:name":"Tourline Express Mensajeria S.l. Sociedad Unipersonal",
    "wof:placetype":"venue"
},
  "geometry": {"coordinates":[2.1648659706,41.404499054],"type":"Point"}
}