{
  "type": "Feature",
  "properties": {
    "addr:full":"C/ Antonio Campos Javaloyes, 9 Elche Alicante 03203",
    "addr:housenumber":"9",
    "addr:postcode":"03203",
    "addr:street":"C / Antonio Campos Javaloyes",
    "iso:country":"ES",
    "sg:address":"C/ Antonio Campos Javaloyes, 9",
    "sg:city":"Elche",
    "sg:orig_category":"Empresarios",
    "sg:phone":"+34 966 67 33 90",
    "sg:postcode":"03203",
    "sg:province":"Alicante",
    "wof:name":"Construcciones Edificaciones Y Reformas S.l.",
    "wof:placetype":"venue"
},
  "geometry": {"coordinates":[-0.6863510013,38.2677841187],"type":"Point"}
}