{
  "type": "Feature",
  "properties": {
    "addr:full":"Calle de Pe\u00d1as De Aya, 2 Irun Guip\u00f9zcoa 20301",
    "addr:housenumber":"2",
    "addr:postcode":"20301",
    "addr:street":"Calle De Pen\u0303As De Aya;Guipu\u0300Zcoa",
    "iso:country":"ES",
    "sg:address":"Calle de Pe\u00d1as De Aya, 2",
    "sg:city":"Irun",
    "sg:orig_category":"Pescader\u00cdas (al Por Menor)",
    "sg:phone":"+34 943 61 66 14",
    "sg:postcode":"20301",
    "sg:province":"Guip\u00f9zcoa",
    "wof:name":"Ochoa Martinez Jose",
    "wof:placetype":"venue"
},
  "geometry": {"coordinates":[-1.8079559803,43.34141922],"type":"Point"}
}