{
  "type": "Feature",
  "properties": {
    "iso:country":"ES",
    "sg:address":"Calle de Parroco Hernandez Benitez, 3",
    "sg:city":"San Isidro",
    "sg:orig_category":"Alimentaci\u00d3n General (al Por Menor)",
    "sg:phone":"+34 928 88 11 35",
    "sg:postcode":"35460",
    "sg:province":"Las Palmas",
    "wof:name":"Sanchez Diaz Jose",
    "wof:placetype":"venue"
},
  "geometry": {"coordinates":[-15.6604413986,28.1322040558],"type":"Point"}
}