{
  "type": "Feature",
  "properties": {
    "addr:full":"Ctra. Estacion, S/n Huercal-overa Almer\u00eda 04600",
    "addr:postcode":"04600",
    "addr:street":"Ctra. Estacion S / N Huercal-Overa Almeri\u0301A",
    "iso:country":"ES",
    "sg:address":"Ctra. Estacion, S/n",
    "sg:city":"Huercal-overa",
    "sg:orig_category":"Negocio De Materiales De Construcci\u00d3n",
    "sg:phone":"+34 950 47 01 91",
    "sg:postcode":"04600",
    "sg:province":"Almer\u00eda",
    "wof:name":"Perez Sanchez Antonio",
    "wof:placetype":"venue"
},
  "geometry": {"coordinates":[-1.9482389688,37.3946914673],"type":"Point"}
}