{
  "type": "Feature",
  "properties": {
    "addr:full":"Carrer de Sant Josep, 166 Sant Feliu Llobregat Barcelona 08980",
    "addr:housenumber":"166",
    "addr:postcode":"08980",
    "addr:street":"Carrer De Sant Josep",
    "iso:country":"ES",
    "sg:address":"Carrer de Sant Josep, 166",
    "sg:city":"Sant Feliu Llobregat",
    "sg:orig_category":"Discotecas Y Salas De Baile",
    "sg:phone":"+34 936 85 14 15",
    "sg:postcode":"08980",
    "sg:province":"Barcelona",
    "sg:website":"www.discoeden.com",
    "wof:name":"Pla Defesta S.l.",
    "wof:placetype":"venue"
},
  "geometry": {"coordinates":[2.032982111,41.3943748474],"type":"Point"}
}