{
  "type": "Feature",
  "properties": {
    "iso:country":"ES",
    "sg:address":"Carr Mariana Cabrera, 84",
    "sg:city":"Villarreal",
    "sg:orig_category":"Importaci\u00d3n",
    "sg:phone":"+34 964 53 77 01",
    "sg:postcode":"12540",
    "sg:province":"Castell\u00f3n",
    "wof:name":"Addex Importacions I Exportacions S.l.",
    "wof:placetype":"venue"
},
  "geometry": {"coordinates":[-0.1012820974,39.9302825928],"type":"Point"}
}