{
  "type": "Feature",
  "properties": {
    "iso:country":"ES",
    "sg:address":"Calle de Gran Canaria (corralejo), 3",
    "sg:city":"Corralejo Playa",
    "sg:orig_category":"Residencias De Turismo, Residencias Hoteleras",
    "sg:phone":"+34 928 53 57 72",
    "sg:postcode":"35660",
    "sg:province":"Las Palmas",
    "wof:name":"Oasis Dunas De Corralejo S.a.",
    "wof:placetype":"venue"
},
  "geometry": {"coordinates":[-13.8632392883,28.728269577],"type":"Point"}
}