{
  "type": "Feature",
  "properties": {
    "addr:full":"Calle de Doctor Gonzalez Serrano (del), 12 Colmenar Viejo Madrid 28770",
    "addr:postcode":"28770",
    "addr:street":"Calle De Doctor Gonzalez Serrano Del",
    "iso:country":"ES",
    "sg:address":"Calle de Doctor Gonzalez Serrano (del), 12",
    "sg:city":"Colmenar Viejo",
    "sg:orig_category":"Agencias Y Asesores De Publicidad",
    "sg:phone":"+34 918 45 35 61",
    "sg:postcode":"28770",
    "sg:province":"Madrid",
    "wof:name":"Alsina Galiana Jorge",
    "wof:placetype":"venue"
},
  "geometry": {"coordinates":[-3.7669270039,40.6597061157],"type":"Point"}
}