{
  "type": "Feature",
  "properties": {
    "iso:country":"ES",
    "sg:address":"Avda Soldevilla Vazquez, 10",
    "sg:city":"Posadas",
    "sg:classifiers":[
        {
            "category":"Autos & Motor Vehicles",
            "subcategory":"Automobile Sales",
            "type":"Retail Goods"
        }
    ],
    "sg:phone":"+34 957 63 14 53",
    "sg:postcode":"14730",
    "sg:province":"C\u00f3rdoba",
    "wof:name":"Navarrete Sanchez Juan Antonio",
    "wof:placetype":"venue"
},
  "geometry": {"coordinates":[-97.78224945069999,45.7040786743],"type":"Point"}
}