{
  "type": "Feature",
  "properties": {
    "addr:full":"Avda Dos De Mayo (del), 25 Mostoles Madrid 28934",
    "addr:housenumber":"25",
    "addr:postcode":"28934",
    "addr:street":"Avda Dos De Mayo Del",
    "iso:country":"ES",
    "sg:address":"Avda Dos De Mayo (del), 25",
    "sg:city":"Mostoles",
    "sg:classifiers":[
        {
            "category":"Tea Room",
            "subcategory":"None",
            "type":"Food & Drink"
        }
    ],
    "sg:phone":"+34 916 64 10 58",
    "sg:postcode":"28934",
    "sg:province":"Madrid",
    "sg:tags":[
        "snack"
    ],
    "wof:name":"Sanchez Mateo Maria Guadalupe",
    "wof:placetype":"venue"
},
  "geometry": {"coordinates":[-3.8691620827,40.3202476501],"type":"Point"}
}