{
  "type": "Feature",
  "properties": {
    "iso:country":"ES",
    "sg:address":"Carrer de Llull, 231",
    "sg:city":"Barcelona",
    "sg:orig_category":"Frutas, Legumbres Frescas Y Tempranas (al Por Menor)",
    "sg:phone":"+34 933 00 29 03",
    "sg:postcode":"08005",
    "sg:province":"Barcelona",
    "wof:name":"Della Cerda Rosa Maria",
    "wof:placetype":"venue"
},
  "geometry": {"coordinates":[2.2045340538,41.4029197693],"type":"Point"}
}