{
  "type": "Feature",
  "properties": {
    "addr:full":"Carr Vilaclosa, 2 Mollerussa Lleida 25230",
    "addr:housenumber":"2",
    "addr:postcode":"25230",
    "addr:street":"Carr Vilaclosa",
    "iso:country":"ES",
    "sg:address":"Carr Vilaclosa, 2",
    "sg:city":"Mollerussa",
    "sg:orig_category":"Bisuter\u00cda, Joyer\u00cda, Relojer\u00cda (al Por Menor)",
    "sg:phone":"+34 973 71 26 49",
    "sg:postcode":"25230",
    "sg:province":"Lleida",
    "wof:name":"Tresvuit Joies S.l.l.",
    "wof:placetype":"venue"
},
  "geometry": {"coordinates":[0.894209981,41.6293296814],"type":"Point"}
}