{
  "type": "Feature",
  "properties": {
    "iso:country":"ES",
    "sg:address":"Ctra. Mozoncillo, 5",
    "sg:city":"Escalona Prado",
    "sg:orig_category":"T\u00c9cnicos Veterinarios",
    "sg:phone":"+34 921 57 04 73",
    "sg:postcode":"40350",
    "sg:province":"Segovia",
    "wof:name":"Pablo Roberto Jose Luisde",
    "wof:placetype":"venue"
},
  "geometry": {"coordinates":[-4.1218671799,41.1667861938],"type":"Point"}
}