{
  "type": "Feature",
  "properties": {
    "iso:country":"ES",
    "sg:address":"Carrer de Preso Vella, 7",
    "sg:city":"Olot",
    "sg:orig_category":"Telas Y Sedas (al Por Menor)",
    "sg:phone":"+34 972 26 82 53",
    "sg:postcode":"17800",
    "sg:province":"Girona",
    "wof:name":"De Bodas Remola Teresa",
    "wof:placetype":"venue"
},
  "geometry": {"coordinates":[2.488961935,42.1824111938],"type":"Point"}
}