{
  "type": "Feature",
  "properties": {
    "addr:full":"Pl Ind Campo Alto, 147 Elda Alicante 03600",
    "addr:housenumber":"147",
    "addr:postcode":"03600",
    "addr:street":"Pl;Campo Alto",
    "iso:country":"ES",
    "sg:address":"Pl Ind Campo Alto, 147",
    "sg:city":"Elda",
    "sg:orig_category":"Zapater\u00cdas",
    "sg:phone":"+34 966 98 00 64",
    "sg:postcode":"03600",
    "sg:province":"Alicante",
    "wof:name":"Tecnotac S.l.u.",
    "wof:placetype":"venue"
},
  "geometry": {"coordinates":[-0.7966089845,38.4770317078],"type":"Point"}
}