{
  "type": "Feature",
  "properties": {
    "addr:full":"Sbid Relfas, 12 Marco Pontevedra 36214",
    "addr:housenumber":"12",
    "addr:postcode":"36214",
    "addr:street":"Relfas",
    "iso:country":"ES",
    "sg:address":"Sbid Relfas, 12",
    "sg:city":"Marco",
    "sg:orig_category":"Reparaciones Y Remolcado De Veh\u00cdculos",
    "sg:phone":"+34 986 26 26 58",
    "sg:postcode":"36214",
    "sg:province":"Pontevedra",
    "wof:name":"Gruas Pancho S.l.",
    "wof:placetype":"venue"
},
  "geometry": {"coordinates":[-8.7059106827,42.2124443054],"type":"Point"}
}