{
  "type": "Feature",
  "properties": {
    "addr:full":"Calle de Zamakoa, 1 Kurtzea Vizcaya 48960",
    "addr:housenumber":"1",
    "addr:postcode":"48960",
    "addr:street":"Calle De Zamakoa",
    "iso:country":"ES",
    "sg:address":"Calle de Zamakoa, 1",
    "sg:city":"Kurtzea",
    "sg:orig_category":"Complementos De Vestir (al Por Menor)",
    "sg:phone":"+34 944 56 01 89",
    "sg:postcode":"48960",
    "sg:province":"Vizcaya",
    "wof:name":"Cedegal S.l.",
    "wof:placetype":"venue"
},
  "geometry": {"coordinates":[-2.8427569866,43.2309036255],"type":"Point"}
}