{
  "type": "Feature",
  "properties": {
    "iso:country":"ES",
    "sg:address":"Avda Jesus Santos Rein, 11",
    "sg:city":"Torremolinos",
    "sg:orig_category":"Bazares, Art\u00cdculos De Limpieza Y De Cocina (al Por Menor)",
    "sg:phone":"+34 952 38 23 13",
    "sg:postcode":"29620",
    "sg:province":"M\u00e1laga",
    "wof:name":"Chen  Zhenheng",
    "wof:placetype":"venue"
},
  "geometry": {"coordinates":[-4.4991188049,36.622543335],"type":"Point"}
}