{
  "type": "Feature",
  "properties": {
    "iso:country":"ES",
    "sg:address":"Valle De Valdebezana, 1",
    "sg:city":"Burgos",
    "sg:orig_category":"Escayola Y Productos De Escayola (fabricaci\u00d3n, Al Por Mayor)",
    "sg:phone":"+34 947 48 00 65",
    "sg:postcode":"09007",
    "sg:province":"Burgos",
    "wof:name":"Jose Santiago Martinez Gutierrez Y Otra",
    "wof:placetype":"venue"
},
  "geometry": {"coordinates":[-3.6449348927,42.3631896973],"type":"Point"}
}