{
  "type": "Feature",
  "properties": {
    "addr:full":"Lg Pereira (a Pereiri\u00f1a), S/n Truebe La Coru\u00f1a 15846",
    "addr:housenumber":"s",
    "addr:postcode":"15846",
    "addr:street":"/ N Truebe La Corun\u0303A",
    "iso:country":"ES",
    "sg:address":"Lg Pereira (a Pereiri\u00f1a), S/n",
    "sg:city":"Truebe",
    "sg:orig_category":"Distribuci\u00d3n De Petr\u00d3leo Y Derivados",
    "sg:phone":"+34 981 89 67 30",
    "sg:postcode":"15846",
    "sg:province":"La Coru\u00f1a",
    "wof:name":"Estacion De Servicio Mui\u00f1o Grande S.l.",
    "wof:placetype":"venue"
},
  "geometry": {"coordinates":[-8.8160686493,43.0137138367],"type":"Point"}
}