{
  "type": "Feature",
  "properties": {
    "iso:country":"ES",
    "sg:address":"Plaz Sierra Castilla, 25",
    "sg:city":"Marina-oasis",
    "sg:orig_category":"Inmobiliaria (agencias)",
    "sg:phone":"+34 966 79 60 12",
    "sg:postcode":"03177",
    "sg:province":"Alicante",
    "wof:name":"Asesores Inmobiliarios Marco Marco S.l.",
    "wof:placetype":"venue"
},
  "geometry": {"coordinates":[-0.4810059965,38.3452033997],"type":"Point"}
}