{
  "type": "Feature",
  "properties": {
    "iso:country":"ES",
    "sg:address":"Calle de Honda, 5",
    "sg:city":"Cartagena",
    "sg:orig_category":"Perfumer\u00cda (al Por Menor)",
    "sg:phone":"+34 968 50 15 11",
    "sg:postcode":"30201",
    "sg:province":"Murcia",
    "wof:name":"Gomiz Y Compa\u00f1ia S. L.",
    "wof:placetype":"venue"
},
  "geometry": {"coordinates":[-0.9859780073,37.6017341614],"type":"Point"}
}