{
  "type": "Feature",
  "properties": {
    "iso:country":"ES",
    "sg:address":"Ptda Plano, S/n",
    "sg:city":"Anna",
    "sg:orig_category":"Ingeniero",
    "sg:phone":"+34 962 21 10 73",
    "sg:postcode":"46820",
    "sg:province":"Valencia",
    "wof:name":"Eurofins-gab Gmbh",
    "wof:placetype":"venue"
},
  "geometry": {"coordinates":[-0.6475340128,39.0191268921],"type":"Point"}
}