{
  "type": "Feature",
  "properties": {
    "iso:country":"ES",
    "sg:address":"Calle de Ingeniero La Cierva, 49",
    "sg:city":"Sevilla",
    "sg:orig_category":"Farmacias",
    "sg:phone":"+34 954 63 50 42",
    "sg:postcode":"41006",
    "sg:province":"Sevilla",
    "wof:name":"Moreno Montoya Maria Antonia",
    "wof:placetype":"venue"
},
  "geometry": {"coordinates":[-5.9492549896,37.3725013733],"type":"Point"}
}