{
  "type": "Feature",
  "properties": {
    "addr:full":"Calle de San Leonardo, 3 Madrid Madrid 28015",
    "addr:housenumber":"3",
    "addr:postcode":"28015",
    "addr:street":"Calle De San Leonardo",
    "iso:country":"ES",
    "sg:address":"Calle de San Leonardo, 3",
    "sg:city":"Madrid",
    "sg:orig_category":"Restaurantes",
    "sg:phone":"+34 915 47 54 39",
    "sg:postcode":"28015",
    "sg:province":"Madrid",
    "wof:name":"Restaurante El Charro Mejicano S.a.",
    "wof:placetype":"venue"
},
  "geometry": {"coordinates":[-3.7105209827,40.4248733521],"type":"Point"}
}