{
  "type": "Feature",
  "properties": {
    "addr:full":"Avda Entrena, 3 Lardero La Rioja 26140",
    "addr:housenumber":"3",
    "addr:postcode":"26140",
    "addr:street":"Avda Entrena;Rioja",
    "iso:country":"ES",
    "sg:address":"Avda Entrena, 3",
    "sg:city":"Lardero",
    "sg:orig_category":"Escayola Y Productos De Escayola (fabricaci\u00d3n, Al Por Mayor)",
    "sg:phone":"+34 941 44 90 62",
    "sg:postcode":"26140",
    "sg:province":"La Rioja",
    "wof:name":"Flores Martinez Carlos",
    "wof:placetype":"venue"
},
  "geometry": {"coordinates":[-2.4634439945,42.4267120361],"type":"Point"}
}