{
  "type": "Feature",
  "properties": {
    "iso:country":"ES",
    "sg:address":"Calle de Victoriano Cremer, 19",
    "sg:city":"Le\u00f3n",
    "sg:orig_category":"Contenedores (mercanc\u00cdas)",
    "sg:phone":"+34 987 22 30 70",
    "sg:postcode":"24007",
    "sg:province":"Le\u00f3n",
    "wof:name":"Arenes Reguera Juan Jesus",
    "wof:placetype":"venue"
},
  "geometry": {"coordinates":[-5.5635523796,42.6059570312],"type":"Point"}
}