{
  "type": "Feature",
  "properties": {
    "addr:full":"Calle de Mayor De Reinoso, 35 Bejar Salamanca 37700",
    "addr:housenumber":"35",
    "addr:postcode":"37700",
    "addr:street":"Calle De Mayor De Reinoso",
    "iso:country":"ES",
    "sg:address":"Calle de Mayor De Reinoso, 35",
    "sg:city":"Bejar",
    "sg:orig_category":"Ropa Para Se\u00d1oras Y Caballeros (al Por Menor)",
    "sg:phone":"+34 923 40 03 45",
    "sg:postcode":"37700",
    "sg:province":"Salamanca",
    "wof:name":"Perez Corrales Manuel",
    "wof:placetype":"venue"
},
  "geometry": {"coordinates":[-5.7665991783,40.386390686],"type":"Point"}
}