{
  "type": "Feature",
  "properties": {
    "iso:country":"ES",
    "sg:address":"Calle de San Lorenzo, 27",
    "sg:city":"Malaga",
    "sg:orig_category":"Arquitectos",
    "sg:phone":"+34 952 60 84 11",
    "sg:postcode":"29001",
    "sg:province":"M\u00e1laga",
    "wof:name":"Rodriguez Iba\u00f1ez Fernando",
    "wof:placetype":"venue"
},
  "geometry": {"coordinates":[-4.4238328934,36.7146186829],"type":"Point"}
}