{
  "type": "Feature",
  "properties": {
    "iso:country":"ES",
    "sg:address":"Calle de Guillen, 7",
    "sg:city":"Icod De Los Vinos",
    "sg:orig_category":"Mec\u00c1nico Del Autom\u00d3vil",
    "sg:phone":"+34 922 81 04 68",
    "sg:postcode":"38430",
    "sg:province":"Santa Cruz De Tenerife",
    "wof:name":"Gonzalez Gonzalez Roberto",
    "wof:placetype":"venue"
},
  "geometry": {"coordinates":[-16.7124137878,28.3696880341],"type":"Point"}
}