{
  "type": "Feature",
  "properties": {
    "iso:country":"ES",
    "sg:address":"Avda Catalu\u00d1a, 92",
    "sg:city":"Zaragoza",
    "sg:orig_category":"Panader\u00cdas, Panader\u00cdas",
    "sg:phone":"+34 976 39 36 31",
    "sg:postcode":"50014",
    "sg:province":"Zaragoza",
    "wof:name":"Pasteleria Liria S. L.",
    "wof:placetype":"venue"
},
  "geometry": {"coordinates":[-0.863812983,41.6625061035],"type":"Point"}
}