{
  "type": "Feature",
  "properties": {
    "addr:full":"Calle de Colon, 27 Segorbe Castell\u00f3n 12400",
    "addr:housenumber":"27",
    "addr:postcode":"12400",
    "addr:street":"Calle De Colon",
    "iso:country":"ES",
    "sg:address":"Calle de Colon, 27",
    "sg:city":"Segorbe",
    "sg:orig_category":"Bisuter\u00cda, Joyer\u00cda, Relojer\u00cda (al Por Menor)",
    "sg:phone":"+34 964 71 07 02",
    "sg:postcode":"12400",
    "sg:province":"Castell\u00f3n",
    "wof:name":"Asensio Ors Jose",
    "wof:placetype":"venue"
},
  "geometry": {"coordinates":[-0.4885069132,39.8518180847],"type":"Point"}
}