{
  "type": "Feature",
  "properties": {
    "addr:full":"Calle de Hurtado De Amezaga, 11 Bilbao Vizcaya 48008",
    "addr:housenumber":"11",
    "addr:postcode":"48008",
    "addr:street":"Calle De Hurtado De Amezaga",
    "iso:country":"ES",
    "sg:address":"Calle de Hurtado De Amezaga, 11",
    "sg:city":"Bilbao",
    "sg:orig_category":"Florister\u00cdas",
    "sg:phone":"+34 944 10 28 06",
    "sg:postcode":"48008",
    "sg:province":"Vizcaya",
    "sg:website":"www.inesquintana.com",
    "wof:name":"Ines Quintana S.l.",
    "wof:placetype":"venue"
},
  "geometry": {"coordinates":[-2.9320690632,43.2583198547],"type":"Point"}
}