{
  "type": "Feature",
  "properties": {
    "iso:country":"ES",
    "sg:address":"Calle de Colon, 6",
    "sg:city":"Almansa",
    "sg:orig_category":"Ropa Para Se\u00d1oras (al Por Menor)",
    "sg:phone":"+34 967 31 12 31",
    "sg:postcode":"02640",
    "sg:province":"Albacete",
    "wof:name":"Modas Aplicate Siglo Xxi S.l.",
    "wof:placetype":"venue"
},
  "geometry": {"coordinates":[-1.0953185558,38.8681526184],"type":"Point"}
}