{
  "type": "Feature",
  "properties": {
    "iso:country":"ES",
    "sg:address":"Calle de Mauricio Legendre, 9",
    "sg:city":"Madrid",
    "sg:orig_category":"Molduras, Junquillos, Listones Y Molduras Perforadas",
    "sg:phone":"+34 913 15 70 75",
    "sg:postcode":"28046",
    "sg:province":"Madrid",
    "wof:name":"Garcia Simon Javier",
    "wof:placetype":"venue"
},
  "geometry": {"coordinates":[-3.6867990494,40.4695739746],"type":"Point"}
}