{
  "type": "Feature",
  "properties": {
    "addr:full":"Jardines De Espa\u00f1a, 3 La Alcaidesa C\u00e1diz 11311",
    "addr:housenumber":"3",
    "addr:postcode":"11311",
    "addr:street":"Espan\u0303A;Ca\u0301Diz",
    "iso:country":"ES",
    "sg:address":"Jardines De Espa\u00f1a, 3",
    "sg:city":"La Alcaidesa",
    "sg:orig_category":"M\u00c9dicos: Reumatolog\u00cda",
    "sg:phone":"+34 956 79 13 54",
    "sg:postcode":"11311",
    "sg:province":"C\u00e1diz",
    "wof:name":"Chipolina  Roy",
    "wof:placetype":"venue"
},
  "geometry": {"coordinates":[-5.2987089157,36.2937660217],"type":"Point"}
}