{
  "type": "Feature",
  "properties": {
    "iso:country":"ES",
    "sg:address":"Calle de Virgen, 1",
    "sg:city":"Navas De Jorquera",
    "sg:orig_category":"Cajas Para Embalar",
    "sg:phone":"+34 967 48 21 39",
    "sg:postcode":"02246",
    "sg:province":"Albacete",
    "wof:name":"Caja Rural De Albacete",
    "wof:placetype":"venue"
},
  "geometry": {"coordinates":[-1.7188359499,39.2796936035],"type":"Point"}
}