{
  "type": "Feature",
  "properties": {
    "iso:country":"ES",
    "sg:address":"Sect Pueblos, 16",
    "sg:city":"Tres Cantos",
    "sg:orig_category":"Pod\u00d3logos: Pedicuros",
    "sg:phone":"+34 918 03 62 26",
    "sg:postcode":"28760",
    "sg:province":"Madrid",
    "wof:name":"Pastor Nadal Maria De Los Angeles",
    "wof:placetype":"venue"
},
  "geometry": {"coordinates":[-3.7127680779,40.6118278503],"type":"Point"}
}