{
  "type": "Feature",
  "properties": {
    "iso:country":"ES",
    "sg:address":"Cm\u00d1o Travesan, 1",
    "sg:city":"Paraixal",
    "sg:orig_category":"M\u00c1rmoles, Granitos Y Piedras Naturales",
    "sg:phone":"+34 986 25 32 84",
    "sg:postcode":"36207",
    "sg:province":"Pontevedra",
    "wof:name":"Marmoleria Gofer S.l.",
    "wof:placetype":"venue"
},
  "geometry": {"coordinates":[-8.6428003311,42.4304618835],"type":"Point"}
}