{
  "type": "Feature",
  "properties": {
    "addr:full":"Calle de General Varela, 20 Fuenllana Ciudad Real 13333",
    "addr:housenumber":"20",
    "addr:postcode":"13333",
    "addr:street":"Calle De General Varela",
    "iso:country":"ES",
    "sg:address":"Calle de General Varela, 20",
    "sg:city":"Fuenllana",
    "sg:orig_category":"Carnicer\u00cdas, Carnicer\u00cdas",
    "sg:phone":"+34 926 36 03 01",
    "sg:postcode":"13333",
    "sg:province":"Ciudad Real",
    "wof:name":"Garcia Jimenez Manuel",
    "wof:placetype":"venue"
},
  "geometry": {"coordinates":[-2.9579160213,38.75573349],"type":"Point"}
}