{
  "type": "Feature",
  "properties": {
    "addr:full":"Pase Isabel La Catolica, 10 Valladolid Valladolid 47001",
    "addr:housenumber":"10",
    "addr:postcode":"47001",
    "addr:street":"Isabel La Catolica",
    "iso:country":"ES",
    "sg:address":"Pase Isabel La Catolica, 10",
    "sg:city":"Valladolid",
    "sg:orig_category":"Cl\u00cdnicas Dentales",
    "sg:phone":"+34 983 33 82 56",
    "sg:postcode":"47001",
    "sg:province":"Valladolid",
    "wof:name":"Llorente Sanchez Joaquin",
    "wof:placetype":"venue"
},
  "geometry": {"coordinates":[-4.7322559357,41.65234375],"type":"Point"}
}