{
  "type": "Feature",
  "properties": {
    "addr:full":"Calle de Goya, 18 Madrid Madrid 28001",
    "addr:housenumber":"18",
    "addr:postcode":"madrid;28001",
    "addr:street":"Calle De Goya",
    "iso:country":"ES",
    "sg:address":"Calle de Goya, 18",
    "sg:city":"Madrid",
    "sg:orig_category":"Caf\u00c9s, Bares, Cervecer\u00cdas",
    "sg:phone":"+34 915 78 29 05",
    "sg:postcode":"28001",
    "sg:province":"Madrid",
    "sg:website":"www.cafeandte.com",
    "wof:name":"Compa\u00f1ia Del Tropico De Cafe Y Te S. L.",
    "wof:placetype":"venue"
},
  "geometry": {"coordinates":[-3.683868885,40.4250526428],"type":"Point"}
}