{
  "type": "Feature",
  "properties": {
    "addr:full":"Avda Virgen De Argeme, 13 Coria C\u00e1ceres 10800",
    "addr:housenumber":"13",
    "addr:postcode":"10800",
    "addr:street":"Avda Virgen De Argeme;Ca\u0301Ceres",
    "iso:country":"ES",
    "sg:address":"Avda Virgen De Argeme, 13",
    "sg:city":"Coria",
    "sg:orig_category":"Caf\u00c9s, Bares, Cervecer\u00cdas",
    "sg:phone":"+34 927 50 04 28",
    "sg:postcode":"10800",
    "sg:province":"C\u00e1ceres",
    "wof:name":"Pizarro Monforte Esther",
    "wof:placetype":"venue"
},
  "geometry": {"coordinates":[-6.5413789749,39.9916801453],"type":"Point"}
}