{
  "type": "Feature",
  "properties": {
    "iso:country":"ES",
    "sg:address":"Calle de Arroyo, 28",
    "sg:city":"Villares",
    "sg:orig_category":"Art\u00cdculos De Regalo (al Por Menor)",
    "sg:phone":"+34 953 32 12 40",
    "sg:postcode":"23160",
    "sg:province":"Ja\u00e9n",
    "wof:name":"Siles Cardenas Jose",
    "wof:placetype":"venue"
},
  "geometry": {"coordinates":[-3.8177471161,37.6887931824],"type":"Point"}
}