{
  "type": "Feature",
  "properties": {
    "addr:full":"Carr Colon, 91 Burjassot Valencia 46100",
    "addr:housenumber":"91",
    "addr:postcode":"46100",
    "addr:street":"Carr Colon",
    "iso:country":"ES",
    "sg:address":"Carr Colon, 91",
    "sg:city":"Burjassot",
    "sg:orig_category":"Fabricaci\u00d3n De Productos Textiles Sin Tejer",
    "sg:phone":"+34 963 64 30 00",
    "sg:postcode":"46100",
    "sg:province":"Valencia",
    "wof:name":"Gonzalez Ruiz Antonio",
    "wof:placetype":"venue"
},
  "geometry": {"coordinates":[-0.4142816961,39.5123710632],"type":"Point"}
}