{
  "type": "Feature",
  "properties": {
    "iso:country":"ES",
    "sg:address":"Rbla Del Fondo, 20",
    "sg:city":"Santa Coloma De Gramenet",
    "sg:orig_category":"Torrefactado De Caf\u00c9",
    "sg:phone":"+34 934 68 10 38",
    "sg:postcode":"08922",
    "sg:province":"Barcelona",
    "wof:name":"Ruiz Badosa Rosa",
    "wof:placetype":"venue"
},
  "geometry": {"coordinates":[2.2170710564,41.4511909485],"type":"Point"}
}