{
  "type": "Feature",
  "properties": {
    "iso:country":"ES",
    "sg:address":"Calle de Doctor Francesc Bono, 1",
    "sg:city":"Alzira",
    "sg:orig_category":"Lavado, Limpieza De Veh\u00cdculos",
    "sg:phone":"+34 962 41 93 02",
    "sg:postcode":"46600",
    "sg:province":"Valencia",
    "wof:name":"Auto Net Alzira S.l.",
    "wof:placetype":"venue"
},
  "geometry": {"coordinates":[-0.4314334989,39.1567573547],"type":"Point"}
}