{
  "type": "Feature",
  "properties": {
    "addr:full":"Avgd Marques De Montroig, 88 Badalona Barcelona 08912",
    "addr:housenumber":"88",
    "addr:postcode":"08912",
    "addr:street":"Montroig",
    "iso:country":"ES",
    "sg:address":"Avgd Marques De Montroig, 88",
    "sg:city":"Badalona",
    "sg:orig_category":"Electricidad, Electr\u00d3nica: Suministros (al Por Menor)",
    "sg:phone":"+34 933 83 17 33",
    "sg:postcode":"08912",
    "sg:province":"Barcelona",
    "wof:name":"Set Instruments S.l.",
    "wof:placetype":"venue"
},
  "geometry": {"coordinates":[2.2339370251,41.4408340454],"type":"Point"}
}