{
  "type": "Feature",
  "properties": {
    "addr:full":"Carr Gracia, 155 Mao Islas Baleares 07702",
    "addr:housenumber":"155",
    "addr:postcode":"07702",
    "addr:street":"Carr Gracia",
    "iso:country":"ES",
    "sg:address":"Carr Gracia, 155",
    "sg:city":"Mao",
    "sg:orig_category":"Caf\u00c9s, Bares, Cervecer\u00cdas",
    "sg:phone":"+34 971 35 34 77",
    "sg:postcode":"07702",
    "sg:province":"Islas Baleares",
    "wof:name":"Mu\u00f1oz Segura Luciano",
    "wof:placetype":"venue"
},
  "geometry": {"coordinates":[4.2638258934,39.884727478],"type":"Point"}
}