{
  "type": "Feature",
  "properties": {
    "iso:country":"ES",
    "sg:address":"Paperera Torras, S/n",
    "sg:city":"S. Joan Fonts",
    "sg:orig_category":"Papel (al Por Mayor)",
    "sg:phone":"+34 972 29 05 08",
    "sg:postcode":"17857",
    "sg:province":"Girona",
    "wof:name":"Torras Papel S.a.",
    "wof:placetype":"venue"
},
  "geometry": {"coordinates":[2.5167200565,42.2127914429],"type":"Point"}
}