{
  "type": "Feature",
  "properties": {
    "iso:country":"ES",
    "sg:address":"Pl Sants Martirs (dels), 14",
    "sg:city":"Vic",
    "sg:orig_category":"Charcuter\u00cdas (al Por Menor)",
    "sg:phone":"+34 938 89 30 34",
    "sg:postcode":"08500",
    "sg:province":"Barcelona",
    "sg:website":"www.casarieraordeix.com",
    "wof:name":"Casa Riera Ordeix S.a.",
    "wof:placetype":"venue"
},
  "geometry": {"coordinates":[2.2583549023,41.9310874939],"type":"Point"}
}