{
  "type": "Feature",
  "properties": {
    "iso:country":"ES",
    "sg:address":"Plaz Constitucion, 10",
    "sg:city":"Almorox",
    "sg:orig_category":"Cervecer\u00cdas",
    "sg:phone":"+34 918 62 36 98",
    "sg:postcode":"45900",
    "sg:province":"Toledo",
    "wof:name":"Prado Cortes Jesus Angel Del",
    "wof:placetype":"venue"
},
  "geometry": {"coordinates":[-4.3904328346,40.2335128784],"type":"Point"}
}