{
  "type": "Feature",
  "properties": {
    "iso:country":"ES",
    "sg:address":"M. Ba\u00f1uelos, 4",
    "sg:city":"Cordoba",
    "sg:orig_category":"Confecci\u00d3n De Trajes Para Se\u00d1oras",
    "sg:phone":"+34 957 49 06 68",
    "sg:postcode":"14001",
    "sg:province":"C\u00f3rdoba",
    "wof:name":"Mu\u00f1oz Cubero Luis",
    "wof:placetype":"venue"
},
  "geometry": {"coordinates":[-4.7784028053,37.8779411316],"type":"Point"}
}