{
  "type": "Feature",
  "properties": {
    "iso:country":"ES",
    "sg:address":"Pl. Obpo Irurita, 6",
    "sg:city":"Iru\u00f1a",
    "sg:orig_category":"Agencias Y Agentes Comerciales, Representantes",
    "sg:phone":"+34 948 25 31 54",
    "sg:postcode":"31011",
    "sg:province":"Navarra",
    "wof:name":"Multimedia Navarra De Comunicacion Sl",
    "wof:placetype":"venue"
},
  "geometry": {"coordinates":[-1.6594729424,42.8132400513],"type":"Point"}
}