{
  "type": "Feature",
  "properties": {
    "iso:country":"ES",
    "sg:address":"Los Hornillos, S/n",
    "sg:city":"Ejido",
    "sg:orig_category":"Delegados, Agentes De Tr\u00c1nsito, Auxiliares De Transporte Internacional",
    "sg:phone":"+34 950 58 06 81",
    "sg:postcode":"04700",
    "sg:province":"Almer\u00eda",
    "wof:name":"Transportes Barbero S.l.",
    "wof:placetype":"venue"
},
  "geometry": {"coordinates":[-2.7933049202,36.7624816895],"type":"Point"}
}