{
  "type": "Feature",
  "properties": {
    "addr:full":"Resille, S/n Ardan Pontevedra 36912",
    "addr:housenumber":"/ n",
    "addr:postcode":"36912",
    "addr:street":"Resille S",
    "iso:country":"ES",
    "sg:address":"Resille, S/n",
    "sg:city":"Ardan",
    "sg:orig_category":"Alquiler De Salones",
    "sg:phone":"+34 986 70 30 12",
    "sg:postcode":"36912",
    "sg:province":"Pontevedra",
    "wof:name":"Superficies Comerciales S.l.",
    "wof:placetype":"venue"
},
  "geometry": {"coordinates":[-8.7497062683,42.3486213684],"type":"Point"}
}