{
  "type": "Feature",
  "properties": {
    "addr:full":"Calle de Lope De Vega, 6 Bormujos Sevilla 41930",
    "addr:housenumber":"6",
    "addr:postcode":"41930",
    "addr:street":"Calle De Lope De Vega",
    "iso:country":"ES",
    "sg:address":"Calle de Lope De Vega, 6",
    "sg:city":"Bormujos",
    "sg:orig_category":"Alquiler De V\u00cddeo",
    "sg:phone":"+34 955 72 59 62",
    "sg:postcode":"41930",
    "sg:province":"Sevilla",
    "wof:name":"Duma Sistemas Y Comunicaciones S.l.",
    "wof:placetype":"venue"
},
  "geometry": {"coordinates":[-6.0747208595,37.3681793213],"type":"Point"}
}