{
  "type": "Feature",
  "properties": {
    "iso:country":"ES",
    "sg:address":"Calle de Pamplona, 2",
    "sg:city":"Playa",
    "sg:orig_category":"Hielo Artificial (fabricaci\u00d3n, Distribuci\u00d3n)",
    "sg:phone":"+34 964 31 10 05",
    "sg:postcode":"12594",
    "sg:province":"Castell\u00f3n",
    "wof:name":"Vidales Blanco Anselmo",
    "wof:placetype":"venue"
},
  "geometry": {"coordinates":[0.135344997,40.0945358276],"type":"Point"}
}