{
  "type": "Feature",
  "properties": {
    "addr:full":"Carrer de Sardenya, 505 Barcelona Barcelona 08024",
    "addr:housenumber":"505",
    "addr:postcode":"08024",
    "addr:street":"Carrer De Sardenya",
    "iso:country":"ES",
    "sg:address":"Carrer de Sardenya, 505",
    "sg:city":"Barcelona",
    "sg:orig_category":"Aparcamientos (infraestructuras, Accesorios)",
    "sg:phone":"+34 932 19 49 97",
    "sg:postcode":"08024",
    "sg:province":"Barcelona",
    "wof:name":"Parking Europa S. A.",
    "wof:placetype":"venue"
},
  "geometry": {"coordinates":[2.1635639668,41.4106483459],"type":"Point"}
}