{
  "type": "Feature",
  "properties": {
    "addr:full":"Pase Sagasta, 43 Zaragoza Zaragoza 50007",
    "addr:housenumber":"43",
    "addr:postcode":"50007",
    "iso:country":"ES",
    "sg:address":"Pase Sagasta, 43",
    "sg:city":"Zaragoza",
    "sg:orig_category":"Fabricaci\u00d3n, Venta De Productos Base Farmac\u00c9uticos",
    "sg:phone":"+34 976 27 62 06",
    "sg:postcode":"50007",
    "sg:province":"Zaragoza",
    "wof:name":"Perez Calvo Maria Jose",
    "wof:placetype":"venue"
},
  "geometry": {"coordinates":[-0.8861439824,41.6404190063],"type":"Point"}
}