{
  "type": "Feature",
  "properties": {
    "addr:full":"Calle de Cuenca, 11 Catarroja Valencia 46470",
    "addr:housenumber":"11",
    "addr:postcode":"46470",
    "addr:street":"Calle De Cuenca",
    "iso:country":"ES",
    "sg:address":"Calle de Cuenca, 11",
    "sg:city":"Catarroja",
    "sg:orig_category":"Empresas De Limpieza",
    "sg:phone":"+34 961 27 05 16",
    "sg:postcode":"46470",
    "sg:province":"Valencia",
    "wof:name":"Servicios Integrales De Limpieza La Ribera S.l.",
    "wof:placetype":"venue"
},
  "geometry": {"coordinates":[-0.4083110094,39.4053382874],"type":"Point"}
}