{
  "type": "Feature",
  "properties": {
    "iso:country":"ES",
    "sg:address":"Calle de Ribera, 14",
    "sg:city":"Valencia",
    "sg:orig_category":"M\u00c9dicos: Dermatolog\u00cda Y Venereolog\u00cda",
    "sg:phone":"+34 963 52 14 63",
    "sg:postcode":"46002",
    "sg:province":"Valencia",
    "wof:name":"Centro Dermatologico Dr.bonillo",
    "wof:placetype":"venue"
},
  "geometry": {"coordinates":[-0.3760890067,39.4679031372],"type":"Point"}
}