{
  "type": "Feature",
  "properties": {
    "addr:full":"Rua Paraiso, S/n Ordes A Coru\u00f1a 15680",
    "addr:postcode":"15680",
    "addr:street":"Rua Paraiso S / N;A Corun\u0303A",
    "iso:country":"ES",
    "sg:address":"Rua Paraiso, S/n",
    "sg:city":"Ordes",
    "sg:orig_category":"Suministros Y Materiales Industriales",
    "sg:phone":"+34 981 68 24 40",
    "sg:postcode":"15680",
    "sg:province":"A Coru\u00f1a",
    "sg:website":"www.vilanovaycruz.com",
    "wof:name":"Vilanova Y Cruz S.l.",
    "wof:placetype":"venue"
},
  "geometry": {"coordinates":[-8.3999042511,43.0729789734],"type":"Point"}
}