{
  "type": "Feature",
  "properties": {
    "addr:full":"Calle de Venezuela, S/n Alcantarilla Murcia 30820",
    "addr:housenumber":"s / n",
    "addr:postcode":"30820",
    "addr:street":"Calle De Venezuela",
    "iso:country":"ES",
    "sg:address":"Calle de Venezuela, S/n",
    "sg:city":"Alcantarilla",
    "sg:orig_category":"Remolques, Carretillas De Mano Para Operaciones Portuarias",
    "sg:phone":"+34 968 88 23 34",
    "sg:postcode":"30820",
    "sg:province":"Murcia",
    "wof:name":"Tecnotrailer Murcia S.l.",
    "wof:placetype":"venue"
},
  "geometry": {"coordinates":[-1.2086009979,37.9554252625],"type":"Point"}
}