{
  "type": "Feature",
  "properties": {
    "addr:full":"Vergara, 9 Madrid Madrid 28013",
    "addr:housenumber":"9",
    "addr:postcode":"madrid;28013",
    "addr:street":"Vergara",
    "iso:country":"ES",
    "sg:address":"Vergara, 9",
    "sg:city":"Madrid",
    "sg:orig_category":"Asesor\u00cda Sobre Comunicaci\u00d3n De Empresas",
    "sg:phone":"+34 915 40 03 06",
    "sg:postcode":"28013",
    "sg:province":"Madrid",
    "sg:website":"www.lasasesorias.com",
    "wof:name":"Asociacion De Asesores De Empresas En Internet",
    "wof:placetype":"venue"
},
  "geometry": {"coordinates":[-3.7110669613,40.4174537659],"type":"Point"}
}