{
  "type": "Feature",
  "properties": {
    "iso:country":"ES",
    "sg:address":"Pase Muelle Del, S/n",
    "sg:city":"Luanco",
    "sg:orig_category":"Ense\u00d1anza, Formaci\u00d3n Profesional: Aprendizaje",
    "sg:phone":"+34 985 88 00 06",
    "sg:postcode":"33440",
    "sg:province":"Asturias",
    "wof:name":"Cofradia De Pescadores Del Santisimo Cristo Del Socorro",
    "wof:placetype":"venue"
},
  "geometry": {"coordinates":[-5.7969498634,43.6147079468],"type":"Point"}
}