{
  "type": "Feature",
  "properties": {
    "iso:country":"ES",
    "sg:address":"Luga Cruz De Illas, 2",
    "sg:city":"Cruz De Illas",
    "sg:orig_category":"Mudanzas",
    "sg:phone":"+34 985 54 13 12",
    "sg:postcode":"33410",
    "sg:province":"Asturias",
    "wof:name":"Mudanzas Asur S.l.",
    "wof:placetype":"venue"
},
  "geometry": {"coordinates":[-5.9452137947,43.5376472473],"type":"Point"}
}