{
  "type": "Feature",
  "properties": {
    "addr:full":"Ptge Rector Felip I Gibert, 8 Lloret Mar Girona 17310",
    "addr:housenumber":"8",
    "addr:postcode":"17310",
    "addr:street":"Ptge Rector Felip I Gibert",
    "iso:country":"ES",
    "sg:address":"Ptge Rector Felip I Gibert, 8",
    "sg:city":"Lloret Mar",
    "sg:orig_category":"Ense\u00d1anza: Idiomas",
    "sg:phone":"+34 972 36 05 38",
    "sg:postcode":"17310",
    "sg:province":"Girona",
    "wof:name":"Caselles Soler Jacqueline",
    "wof:placetype":"venue"
},
  "geometry": {"coordinates":[2.8486280441,41.7021369934],"type":"Point"}
}