{
  "type": "Feature",
  "properties": {
    "addr:full":"Calle de Ronda, 45 Caparroso Navarra 31380",
    "addr:housenumber":"45",
    "addr:postcode":"31380",
    "addr:street":"Calle De Ronda",
    "iso:country":"ES",
    "sg:address":"Calle de Ronda, 45",
    "sg:city":"Caparroso",
    "sg:orig_category":"Fabricaci\u00d3n De Telas Y Sedas",
    "sg:phone":"+34 948 73 03 37",
    "sg:postcode":"31380",
    "sg:province":"Navarra",
    "wof:name":"Gorina S. A.",
    "wof:placetype":"venue"
},
  "geometry": {"coordinates":[-1.6525110006,42.3412742615],"type":"Point"}
}