{
  "type": "Feature",
  "properties": {
    "iso:country":"ES",
    "sg:address":"Plaz Heredia, 13",
    "sg:city":"Caspe",
    "sg:orig_category":"Carnicer\u00cdas, Carnicer\u00cdas",
    "sg:phone":"+34 976 63 24 52",
    "sg:postcode":"50700",
    "sg:province":"Zaragoza",
    "wof:name":"Gresa Barcelo Maria Isabel",
    "wof:placetype":"venue"
},
  "geometry": {"coordinates":[-0.0400880016,41.2366523743],"type":"Point"}
}