{
  "type": "Feature",
  "properties": {
    "addr:full":"Calle de Doctor Marco Merenciano, 2 Valencia Valencia 46025",
    "addr:housenumber":"2",
    "addr:postcode":"46025",
    "addr:street":"Calle De Doctor Marco Merenciano",
    "iso:country":"ES",
    "sg:address":"Calle de Doctor Marco Merenciano, 2",
    "sg:city":"Valencia",
    "sg:orig_category":"Panader\u00cdas, Panader\u00cdas",
    "sg:phone":"+34 963 47 68 46",
    "sg:postcode":"46025",
    "sg:province":"Valencia",
    "wof:name":"Garcia Ca\u00f1izares Francisco",
    "wof:placetype":"venue"
},
  "geometry": {"coordinates":[-0.3794313073,39.4920578003],"type":"Point"}
}