{
  "type": "Feature",
  "properties": {
    "addr:full":"Pol. I. Calgat, 4 S. Joan Abadesses Girona 17860",
    "addr:housenumber":"4",
    "addr:postcode":"17860",
    "addr:street":"Pol. I. Calgat;S. Joan Abadesses",
    "iso:country":"ES",
    "sg:address":"Pol. I. Calgat, 4",
    "sg:city":"S. Joan Abadesses",
    "sg:orig_category":"Fabricaci\u00d3n, Venta De Cuadros, Accesorios Para Enmarcar",
    "sg:phone":"+34 972 72 30 24",
    "sg:postcode":"17860",
    "sg:province":"Girona",
    "wof:name":"Decor Mark Santigosa S.l.",
    "wof:placetype":"venue"
},
  "geometry": {"coordinates":[2.2854809761,42.2338752747],"type":"Point"}
}