{
  "type": "Feature",
  "properties": {
    "addr:full":"Calle de Albert Einstein, 10 Palmas De Gran Canaria Las Palmas 35013",
    "addr:housenumber":"10",
    "addr:postcode":"35013",
    "addr:street":"Calle De Albert Einstein",
    "iso:country":"ES",
    "sg:address":"Calle de Albert Einstein, 10",
    "sg:city":"Palmas De Gran Canaria",
    "sg:orig_category":"Comercio De Cuadros, L\u00c1minas Y Reproducciones De Obras De Arte",
    "sg:phone":"+34 928 41 61 06",
    "sg:postcode":"35013",
    "sg:province":"Las Palmas",
    "wof:name":"Carsaa De Comunicacion S.l",
    "wof:placetype":"venue"
},
  "geometry": {"coordinates":[-15.4511842728,28.0920619965],"type":"Point"}
}