{
  "type": "Feature",
  "properties": {
    "iso:country":"ES",
    "sg:address":"Calle de Valdeosera, 8",
    "sg:city":"Logro\u00f1o",
    "sg:orig_category":"Materias Pl\u00c1sticas: Productos De Consumo Masivo (fabricaci\u00d3n, Al Por Mayor)",
    "sg:phone":"+34 941 21 66 82",
    "sg:postcode":"26005",
    "sg:province":"La Rioja",
    "wof:name":"Ge Plastics Espa\u00d1a Sociedad Comanditaria Por Acciones",
    "wof:placetype":"venue"
},
  "geometry": {"coordinates":[-2.4595088959,42.4679336548],"type":"Point"}
}