{
  "type": "Feature",
  "properties": {
    "addr:full":"Calle de Correhuela, 24 Salamanca Salamanca 37001",
    "addr:housenumber":"24",
    "addr:postcode":"37001",
    "addr:street":"Calle De Correhuela",
    "iso:country":"ES",
    "sg:address":"Calle de Correhuela, 24",
    "sg:city":"Salamanca",
    "sg:orig_category":"Vinos Y Licores (venta Al Por Menor)",
    "sg:phone":"+34 923 21 31 48",
    "sg:postcode":"37001",
    "sg:province":"Salamanca",
    "sg:website":"www.palaciolicores.com",
    "wof:name":"New Palacio De Los Licores S.l.",
    "wof:placetype":"venue"
},
  "geometry": {"coordinates":[-5.6608977318,40.9651107788],"type":"Point"}
}