{
  "type": "Feature",
  "properties": {
    "iso:country":"ES",
    "sg:address":"Calle de Sancha De Lara, 7",
    "sg:city":"Malaga",
    "sg:orig_category":"Cl\u00cdnicas M\u00c9dicas",
    "sg:phone":"+34 952 21 20 22",
    "sg:postcode":"29015",
    "sg:province":"M\u00e1laga",
    "wof:name":"Garcia Alberca Jose Maria",
    "wof:placetype":"venue"
},
  "geometry": {"coordinates":[-4.4209189415,36.7188072205],"type":"Point"}
}