{
  "type": "Feature",
  "properties": {
    "addr:full":"Avda Reyes Catolicos, 42 Alcala Henares Madrid 28802",
    "addr:housenumber":"42",
    "addr:postcode":"28802",
    "addr:street":"Avda Reyes Catolicos",
    "iso:country":"ES",
    "sg:address":"Avda Reyes Catolicos, 42",
    "sg:city":"Alcala Henares",
    "sg:orig_category":"Servicio De Salud",
    "sg:phone":"+34 918 81 44 84",
    "sg:postcode":"28802",
    "sg:province":"Madrid",
    "sg:website":"www.expert.es",
    "wof:name":"Saneamientos L.martinez S.a.",
    "wof:placetype":"venue"
},
  "geometry": {"coordinates":[-3.3780970573,40.4740371704],"type":"Point"}
}