{
  "type": "Feature",
  "properties": {
    "addr:full":"Arcade De Riba, S/n Arcade Pontevedra 36690",
    "addr:housenumber":"s / n",
    "addr:postcode":"36690",
    "iso:country":"ES",
    "sg:address":"Arcade De Riba, S/n",
    "sg:city":"Arcade",
    "sg:orig_category":"Centros De Educaci\u00d3n Especial",
    "sg:phone":"+34 986 70 00 49",
    "sg:postcode":"36690",
    "sg:province":"Pontevedra",
    "wof:name":"Centro Publico Integrado Padin Truiteiro",
    "wof:placetype":"venue"
},
  "geometry": {"coordinates":[-8.6055440903,42.3392410278],"type":"Point"}
}