{
  "type": "Feature",
  "properties": {
    "addr:full":"Calle de General Aguilera, 17 Ciudad Real Ciudad Real 13001",
    "addr:housenumber":"17",
    "addr:postcode":"13001",
    "addr:street":"Calle De General Aguilera",
    "iso:country":"ES",
    "sg:address":"Calle de General Aguilera, 17",
    "sg:city":"Ciudad Real",
    "sg:orig_category":"Ropa Para Se\u00d1oras (al Por Menor)",
    "sg:phone":"+34 926 25 11 23",
    "sg:postcode":"13001",
    "sg:province":"Ciudad Real",
    "wof:name":"Buendia Ayuso Consuelo",
    "wof:placetype":"venue"
},
  "geometry": {"coordinates":[-3.9283161163,38.9839401245],"type":"Point"}
}