{
  "type": "Feature",
  "properties": {
    "iso:country":"ES",
    "sg:address":"Cta. Prado Del Rey-arcos, Km. 0004,5",
    "sg:city":"Prado Del Rey",
    "sg:orig_category":"Fabricaci\u00d3n De Muebles",
    "sg:phone":"+34 956 72 33 07",
    "sg:postcode":"11660",
    "sg:province":"C\u00e1diz",
    "wof:name":"Arteprama C.b.",
    "wof:placetype":"venue"
},
  "geometry": {"coordinates":[-5.5636034012,36.7670669556],"type":"Point"}
}