{
  "type": "Feature",
  "properties": {
    "iso:country":"ES",
    "sg:address":"Cmno Hormigueras, 124",
    "sg:city":"Madrid",
    "sg:orig_category":"Encuadernaci\u00d3n E Impresi\u00d3n De Folletos",
    "sg:phone":"+34 914 46 12 86",
    "sg:postcode":"28031",
    "sg:province":"Madrid",
    "wof:name":"Grupo Mundoprint,s.l.",
    "wof:placetype":"venue"
},
  "geometry": {"coordinates":[-3.6441969872,40.374256134],"type":"Point"}
}