{
  "type": "Feature",
  "properties": {
    "addr:full":"Avda Sotileza, S/n Santander Cantabria 39009",
    "addr:housenumber":"s / n",
    "addr:postcode":"39009",
    "addr:street":"Avda Sotileza",
    "iso:country":"ES",
    "sg:address":"Avda Sotileza, S/n",
    "sg:city":"Santander",
    "sg:orig_category":"Empresas Portuarias",
    "sg:phone":"+34 942 36 46 94",
    "sg:postcode":"39009",
    "sg:province":"Cantabria",
    "wof:name":"Remolques Maritimos S.a.",
    "wof:placetype":"venue"
},
  "geometry": {"coordinates":[-3.8202490807,43.4506149292],"type":"Point"}
}