{
  "type": "Feature",
  "properties": {
    "addr:full":"Calle de Zurbaran, 45 Castuera Badajoz 06420",
    "addr:housenumber":"45",
    "addr:postcode":"06420",
    "addr:street":"Calle De Zurbaran",
    "iso:country":"ES",
    "sg:address":"Calle de Zurbaran, 45",
    "sg:city":"Castuera",
    "sg:orig_category":"Delegados, Agentes De Tr\u00c1nsito, Auxiliares De Transporte Internacional",
    "sg:phone":"+34 924 77 20 52",
    "sg:postcode":"06420",
    "sg:province":"Badajoz",
    "wof:name":"Rodriguez Fernandez Manuel",
    "wof:placetype":"venue"
},
  "geometry": {"coordinates":[-5.5457310677,38.7184486389],"type":"Point"}
}