{
  "type": "Feature",
  "properties": {
    "iso:country":"ES",
    "sg:address":"Carr Joan Carles I, 19",
    "sg:city":"Muro",
    "sg:orig_category":"Artes Gr\u00c1ficas, Artes Pl\u00c1sticas (curso)",
    "sg:phone":"+34 971 86 04 44",
    "sg:postcode":"07440",
    "sg:province":"Islas Baleares",
    "sg:website":"www.imuro.com",
    "wof:name":"Impremta Muro S.l.",
    "wof:placetype":"venue"
},
  "geometry": {"coordinates":[3.0560970306,39.7358131409],"type":"Point"}
}