{
  "type": "Feature",
  "properties": {
    "iso:country":"ES",
    "sg:address":"Tragove, S/n",
    "sg:city":"Tragove",
    "sg:orig_category":"Cerrajer\u00cda, Ferrallista",
    "sg:phone":"+34 986 54 25 29",
    "sg:postcode":"36639",
    "sg:province":"Pontevedra",
    "wof:name":"Pi\u00f1eiro Baulo Carlos",
    "wof:placetype":"venue"
},
  "geometry": {"coordinates":[-8.8220100403,42.4838981628],"type":"Point"}
}