{
  "type": "Feature",
  "properties": {
    "iso:country":"ES",
    "sg:address":"Rua Real, 19",
    "sg:city":"Ponteareas",
    "sg:orig_category":"Peluquer\u00cdas, Peluquer\u00cda Mixta",
    "sg:phone":"+34 986 66 07 99",
    "sg:postcode":"36860",
    "sg:province":"Pontevedra",
    "wof:name":"Maracaibo Porri\u00f1o S.l.",
    "wof:placetype":"venue"
},
  "geometry": {"coordinates":[-8.5083293915,42.1775016785],"type":"Point"}
}