{
  "type": "Feature",
  "properties": {
    "iso:country":"ES",
    "sg:address":"Avda General Marva, 6",
    "sg:city":"Alacant",
    "sg:orig_category":"Promotores Constructores",
    "sg:phone":"+34 965 21 44 54",
    "sg:postcode":"03004",
    "sg:province":"Alicante",
    "wof:name":"Edi-plaza S.l.",
    "wof:placetype":"venue"
},
  "geometry": {"coordinates":[-0.4907589853,38.3468055725],"type":"Point"}
}