{
  "type": "Feature",
  "properties": {
    "addr:full":"Ptge Alt Del Turo, 15 Barcelona Barcelona 08041",
    "addr:housenumber":"15",
    "addr:postcode":"08041",
    "addr:street":"Ptge Alt Del Turo",
    "iso:country":"ES",
    "sg:address":"Ptge Alt Del Turo, 15",
    "sg:city":"Barcelona",
    "sg:orig_category":"Enfermeras: Consultas, Atenci\u00d3n A Domicilio",
    "sg:phone":"+34 934 56 37 88",
    "sg:postcode":"08041",
    "sg:province":"Barcelona",
    "wof:name":"Ramos Terradas Odilia",
    "wof:placetype":"venue"
},
  "geometry": {"coordinates":[2.1719119549,41.4196357727],"type":"Point"}
}