{
  "type": "Feature",
  "properties": {
    "addr:full":"Avgd Prat De La Riba, 79 Lleida Lleida 25004",
    "addr:housenumber":"79",
    "addr:postcode":"25004",
    "addr:street":"La Riba",
    "iso:country":"ES",
    "sg:address":"Avgd Prat De La Riba, 79",
    "sg:city":"Lleida",
    "sg:orig_category":"Cl\u00cdnicas M\u00c9dicas",
    "sg:phone":"+34 973 24 06 52",
    "sg:postcode":"25004",
    "sg:province":"Lleida",
    "wof:name":"Institucion Leridana De Fertilidad",
    "wof:placetype":"venue"
},
  "geometry": {"coordinates":[0.6266670227,41.6222839355],"type":"Point"}
}