{
  "type": "Feature",
  "properties": {
    "iso:country":"ES",
    "sg:address":"Pase Pedro Simon Abril, 3",
    "sg:city":"Albacete",
    "sg:orig_category":"Laboratorios Farmac\u00c9uticos",
    "sg:phone":"+34 967 23 36 88",
    "sg:postcode":"02002",
    "sg:province":"Albacete",
    "wof:name":"Martinez Cuervas-mons Juan",
    "wof:placetype":"venue"
},
  "geometry": {"coordinates":[-1.8540610075,38.9950675964],"type":"Point"}
}