{
  "type": "Feature",
  "properties": {
    "iso:country":"ES",
    "sg:address":"Gta Descubrimiento, 2",
    "sg:city":"Valladolid",
    "sg:orig_category":"Agencias Y Agentes Comerciales, Representantes",
    "sg:phone":"+34 983 30 45 45",
    "sg:postcode":"47005",
    "sg:province":"Valladolid",
    "wof:name":"Gonzalez Martin Jesus",
    "wof:placetype":"venue"
},
  "geometry": {"coordinates":[-4.710504055,41.6552658081],"type":"Point"}
}