{
  "type": "Feature",
  "properties": {
    "iso:country":"ES",
    "sg:address":"Pje. San Antonio, 7",
    "sg:city":"Marmolejo",
    "sg:orig_category":"Caf\u00c9s, Bares, Cervecer\u00cdas",
    "sg:phone":"+34 953 54 00 97",
    "sg:postcode":"23770",
    "sg:province":"Ja\u00e9n",
    "wof:name":"Castro Garrido Rafael",
    "wof:placetype":"venue"
},
  "geometry": {"coordinates":[-4.1715269089,38.0454750061],"type":"Point"}
}