{
  "type": "Feature",
  "properties": {
    "iso:country":"ES",
    "sg:address":"Carr Tapis, 55",
    "sg:city":"Figueres",
    "sg:orig_category":"Fabricaci\u00d3n, Venta, Instalaci\u00d3n De R\u00d3tulos, De R\u00d3tulos Luminosos",
    "sg:phone":"+34 972 50 96 00",
    "sg:postcode":"17600",
    "sg:province":"Girona",
    "wof:name":"Sole Alegre Antonio",
    "wof:placetype":"venue"
},
  "geometry": {"coordinates":[2.9652218819,42.2712745667],"type":"Point"}
}