{
  "type": "Feature",
  "properties": {
    "addr:full":"C/ Girona, 43 Banyoles Girona 17820",
    "addr:housenumber":"43",
    "addr:postcode":"17820",
    "addr:street":"C / Girona",
    "iso:country":"ES",
    "sg:address":"C/ Girona, 43",
    "sg:city":"Banyoles",
    "sg:orig_category":"Orquestas De Variedades",
    "sg:phone":"+34 972 57 08 88",
    "sg:postcode":"17820",
    "sg:province":"Girona",
    "wof:name":"Ferrer Corbalan Joaquin",
    "wof:placetype":"venue"
},
  "geometry": {"coordinates":[2.7669270039,42.1173400879],"type":"Point"}
}