{
  "type": "Feature",
  "properties": {
    "iso:country":"ES",
    "sg:address":"Pol Industrial, 2",
    "sg:city":"Torreperogil",
    "sg:orig_category":"Fabricaci\u00d3n, Instalaci\u00d3n Y Reparaci\u00d3n De Bombas",
    "sg:phone":"+34 953 77 86 80",
    "sg:postcode":"23320",
    "sg:province":"Ja\u00e9n",
    "wof:name":"Perforaciones La Loma S.l.",
    "wof:placetype":"venue"
},
  "geometry": {"coordinates":[-3.2914140224,38.0347862244],"type":"Point"}
}