{
  "type": "Feature",
  "properties": {
    "addr:full":"Calle de Martinez De La Riva, 16 Madrid Madrid 28053",
    "addr:housenumber":"16",
    "addr:postcode":"madrid;28053",
    "addr:street":"Calle De Martinez De La Riva",
    "iso:country":"ES",
    "sg:address":"Calle de Martinez De La Riva, 16",
    "sg:city":"Madrid",
    "sg:orig_category":"Cl\u00cdnicas Dentales",
    "sg:phone":"+34 914 78 62 91",
    "sg:postcode":"28053",
    "sg:province":"Madrid",
    "wof:name":"Certro Dental De La Riva S.l.",
    "wof:placetype":"venue"
},
  "geometry": {"coordinates":[-3.6666710377,40.3943862915],"type":"Point"}
}