{
  "type": "Feature",
  "properties": {
    "iso:country":"ES",
    "sg:address":"Carrer de Josep Maria De Sagarra, 12",
    "sg:city":"Hospitalet Llobregat",
    "sg:orig_category":"Agentes, Concesionarios Y Sucursales De Veh\u00cdculos",
    "sg:phone":"+34 933 37 64 32",
    "sg:postcode":"08901",
    "sg:province":"Barcelona",
    "wof:name":"Faura Cano Francisco",
    "wof:placetype":"venue"
},
  "geometry": {"coordinates":[2.0994920731,41.3575057983],"type":"Point"}
}