{
  "type": "Feature",
  "properties": {
    "addr:full":"Calle de Castellon, 1 Gatova Valencia 46169",
    "addr:housenumber":"1",
    "addr:postcode":"46169",
    "addr:street":"Calle De Castellon",
    "iso:country":"ES",
    "sg:address":"Calle de Castellon, 1",
    "sg:city":"Gatova",
    "sg:orig_category":"Carnicer\u00cdas, Carnicer\u00cdas",
    "sg:phone":"+34 964 12 60 16",
    "sg:postcode":"46169",
    "sg:province":"Valencia",
    "wof:name":"Romero Sanchez Rafael",
    "wof:placetype":"venue"
},
  "geometry": {"coordinates":[-0.5214645267,39.770324707],"type":"Point"}
}