{
  "type": "Feature",
  "properties": {
    "iso:country":"ES",
    "sg:address":"Carrer de Sant Josep, 30",
    "sg:city":"Mataro",
    "sg:orig_category":"Inmobiliaria (agencias)",
    "sg:phone":"+34 937 90 43 42",
    "sg:postcode":"08302",
    "sg:province":"Barcelona",
    "wof:name":"Famcora S.l.",
    "wof:placetype":"venue"
},
  "geometry": {"coordinates":[2.4431788921,41.5395355225],"type":"Point"}
}