{
  "type": "Feature",
  "properties": {
    "iso:country":"ES",
    "sg:address":"Calle de General Vara De Rey, 81",
    "sg:city":"Logro\u00f1o",
    "sg:orig_category":"Agencias Y Agentes Comerciales, Representantes",
    "sg:phone":"+34 941 24 30 23",
    "sg:postcode":"26006",
    "sg:province":"La Rioja",
    "wof:name":"Victoriano Martinez Rufino",
    "wof:placetype":"venue"
},
  "geometry": {"coordinates":[-2.4473240376,42.4564208984],"type":"Point"}
}