{
  "type": "Feature",
  "properties": {
    "iso:country":"ES",
    "sg:address":"Ctra Mirador, S/n",
    "sg:city":"San Javier",
    "sg:orig_category":"Flores Y Plantas Naturales (al Por Mayor)",
    "sg:phone":"+34 968 19 07 88",
    "sg:postcode":"30730",
    "sg:province":"Murcia",
    "wof:name":"Berrex-plant S.a.",
    "wof:placetype":"venue"
},
  "geometry": {"coordinates":[-0.8044739962,37.8165397644],"type":"Point"}
}