{
  "type": "Feature",
  "properties": {
    "addr:full":"Calle de San Andres, 19 Almoradi Alicante 03160",
    "addr:housenumber":"19",
    "addr:postcode":"03160",
    "addr:street":"Calle De San Andres",
    "iso:country":"ES",
    "sg:address":"Calle de San Andres, 19",
    "sg:city":"Almoradi",
    "sg:orig_category":"Caf\u00c9s, Bares, Cervecer\u00cdas",
    "sg:phone":"+34 966 78 17 79",
    "sg:postcode":"03160",
    "sg:province":"Alicante",
    "wof:name":"Lopez Garcia Manuela",
    "wof:placetype":"venue"
},
  "geometry": {"coordinates":[-0.7896810174,38.1098060608],"type":"Point"}
}