{
  "type": "Feature",
  "properties": {
    "addr:full":"Ctra Nal Trescientos Cuarenta, 51 Pu\u00e7ol Valencia 46530",
    "addr:housenumber":"51",
    "addr:postcode":"46530",
    "addr:street":"Ctra Nal Trescientos Cuarenta",
    "iso:country":"ES",
    "sg:address":"Ctra Nal Trescientos Cuarenta, 51",
    "sg:city":"Pu\u00e7ol",
    "sg:classifiers":[
        {
            "category":"Professional",
            "subcategory":"Business Services",
            "type":"Services"
        }
    ],
    "sg:phone":"+34 961 42 14 97",
    "sg:postcode":"46530",
    "sg:province":"Valencia",
    "sg:tags":[
        "control",
        "asesor\u00cda",
        "organizaci\u00d3n",
        "la",
        "de",
        "gesti\u00d3n",
        "y"
    ],
    "sg:website":"www.sgaim.com",
    "wof:name":"Sga Information Management S.a.",
    "wof:placetype":"venue"
},
  "geometry": {"coordinates":[-0.3008790016,39.6156044006],"type":"Point"}
}