{
  "type": "Feature",
  "properties": {
    "iso:country":"ES",
    "sg:address":"Avda Cervantes, 1",
    "sg:city":"Malaga",
    "sg:orig_category":"Ense\u00d1anza, Formaci\u00d3n Profesional: Aprendizaje",
    "sg:phone":"+34 952 21 41 20",
    "sg:postcode":"29016",
    "sg:province":"M\u00e1laga",
    "sg:website":"www.malagaturismo.com",
    "wof:name":"Ayuntamiento De Malaga",
    "wof:placetype":"venue"
},
  "geometry": {"coordinates":[-4.4168000221,36.7196846008],"type":"Point"}
}