{
  "type": "Feature",
  "properties": {
    "iso:country":"ES",
    "sg:address":"Calle de Ramon Y Cajal, 5",
    "sg:city":"Donostia-san Sebastian",
    "sg:orig_category":"Maquinaria Para Industrias Diversas",
    "sg:phone":"+34 943 27 51 24",
    "sg:postcode":"20002",
    "sg:province":"Guip\u00f9zcoa",
    "wof:name":"Ganuza Aguirre Jose Luis",
    "wof:placetype":"venue"
},
  "geometry": {"coordinates":[-1.9755810499,43.3244667053],"type":"Point"}
}