{
  "type": "Feature",
  "properties": {
    "iso:country":"ES",
    "sg:address":"Carrer de Rector Joanico, 20",
    "sg:city":"S. Andreu Barca",
    "sg:orig_category":"Seguridad Social",
    "sg:phone":"+34 936 53 42 91",
    "sg:postcode":"08740",
    "sg:province":"Barcelona",
    "sg:website":"www.fremap.es",
    "wof:name":"Fremap Mutua De Accidentes De Trabajo Y Enfermedades Profesionalesde La Seguridad Social Numero 61",
    "wof:placetype":"venue"
},
  "geometry": {"coordinates":[1.9750499725,41.4473114014],"type":"Point"}
}