{
  "type": "Feature",
  "properties": {
    "addr:full":"Ctra. Nijar, 258 Almeria Almer\u00eda 04006",
    "addr:housenumber":"258",
    "addr:postcode":"04006",
    "addr:street":"Ctra. Nijar",
    "iso:country":"ES",
    "sg:address":"Ctra. Nijar, 258",
    "sg:city":"Almeria",
    "sg:orig_category":"Ense\u00d1anza: Profesiones Art\u00cdsticas",
    "sg:phone":"+34 950 22 16 19",
    "sg:postcode":"04006",
    "sg:province":"Almer\u00eda",
    "wof:name":"Fernandez Martinez Bernardo",
    "wof:placetype":"venue"
},
  "geometry": {"coordinates":[-2.4357988834,36.8436279297],"type":"Point"}
}