{
  "type": "Feature",
  "properties": {
    "addr:full":"Calle de Blas Infante, 2 Bollullos Mitacion Sevilla 41110",
    "addr:housenumber":"2",
    "addr:postcode":"41110",
    "addr:street":"Calle De Blas Infante",
    "iso:country":"ES",
    "sg:address":"Calle de Blas Infante, 2",
    "sg:city":"Bollullos Mitacion",
    "sg:orig_category":"M\u00c9dicos: Estomatolog\u00cda",
    "sg:phone":"+34 955 76 65 90",
    "sg:postcode":"41110",
    "sg:province":"Sevilla",
    "wof:name":"Chen Olmedo Veronica",
    "wof:placetype":"venue"
},
  "geometry": {"coordinates":[-6.138897419,37.3422966003],"type":"Point"}
}