{
  "type": "Feature",
  "properties": {
    "iso:country":"ES",
    "sg:address":"Pl. Cde Rodezno, 8",
    "sg:city":"Iru\u00f1a",
    "sg:orig_category":"Inmobiliaria (agencias)",
    "sg:phone":"+34 948 15 27 63",
    "sg:postcode":"31003",
    "sg:province":"Navarra",
    "wof:name":"Mercado Y Desarrollo De Terreno S.l.",
    "wof:placetype":"venue"
},
  "geometry": {"coordinates":[-1.6414630413,42.8112335205],"type":"Point"}
}