{
  "type": "Feature",
  "properties": {
    "addr:full":"Calle de Nazaret (de), 10 Fuenlabrada Madrid 28941",
    "addr:housenumber":"10",
    "addr:postcode":"28941",
    "addr:street":"Calle De Nazaret De",
    "iso:country":"ES",
    "sg:address":"Calle de Nazaret (de), 10",
    "sg:city":"Fuenlabrada",
    "sg:orig_category":"Peluquer\u00cdas, Peluquer\u00cda Mixta",
    "sg:phone":"+34 916 97 78 42",
    "sg:postcode":"28941",
    "sg:province":"Madrid",
    "wof:name":"Hernandez Macias Maria De Los Angeles",
    "wof:placetype":"venue"
},
  "geometry": {"coordinates":[-3.7982680798,40.28647995],"type":"Point"}
}