{
  "type": "Feature",
  "properties": {
    "iso:country":"ES",
    "sg:address":"Avda Valdelaparra (de), 27",
    "sg:city":"Alcobendas",
    "sg:orig_category":"Aparatos, Sistemas De Tele",
    "sg:phone":"+34 916 61 21 19",
    "sg:postcode":"28108",
    "sg:province":"Madrid",
    "wof:name":"Honeywell Security Espa\u00f1a S.a.",
    "wof:placetype":"venue"
},
  "geometry": {"coordinates":[-3.6466300488,40.5387420654],"type":"Point"}
}