{
  "type": "Feature",
  "properties": {
    "iso:country":"ES",
    "sg:address":"Rbla Nova, 91",
    "sg:city":"Mollet Valles",
    "sg:orig_category":"Molduras, Junquillos, Listones Y Molduras Perforadas",
    "sg:phone":"+34 935 70 14 85",
    "sg:postcode":"08100",
    "sg:province":"Barcelona",
    "wof:name":"Carrasco Esquina Juan Manuel",
    "wof:placetype":"venue"
},
  "geometry": {"coordinates":[2.2088840008,41.5412101746],"type":"Point"}
}