{
  "type": "Feature",
  "properties": {
    "addr:full":"Calle de Real, 29 Rueda Valladolid 47490",
    "addr:housenumber":"29",
    "addr:postcode":"47490",
    "addr:street":"Calle De Real;Valladolid",
    "iso:country":"ES",
    "sg:address":"Calle de Real, 29",
    "sg:city":"Rueda",
    "sg:orig_category":"Comerciantes Al Por Mayor De Vinos, Licores Y Alcoholes",
    "sg:phone":"+34 983 86 84 51",
    "sg:postcode":"47490",
    "sg:province":"Valladolid",
    "wof:name":"Cabezas Mayo Avelino",
    "wof:placetype":"venue"
},
  "geometry": {"coordinates":[-4.9601697922,41.4153022766],"type":"Point"}
}