{
  "type": "Feature",
  "properties": {
    "addr:full":"Crta. Gijon-sevilla, Km. 0626,2 Merida Badajoz 06800",
    "addr:postcode":"06800",
    "addr:street":"Crta. Gijon-Sevilla Km. 0626,2",
    "iso:country":"ES",
    "sg:address":"Crta. Gijon-sevilla, Km. 0626,2",
    "sg:city":"Merida",
    "sg:orig_category":"Refiner\u00cdas De Petr\u00d3leo",
    "sg:phone":"+34 924 37 19 19",
    "sg:postcode":"06800",
    "sg:province":"Badajoz",
    "wof:name":"Combustibles Merida Sociedad Cooperativa",
    "wof:placetype":"venue"
},
  "geometry": {"coordinates":[-6.3500027657,38.9179878235],"type":"Point"}
}