{
  "type": "Feature",
  "properties": {
    "addr:full":"Carrer de Zorrilla, S/n Reus Tarragona 43202",
    "addr:housenumber":"s / n",
    "addr:postcode":"43202",
    "addr:street":"Carrer De Zorrilla",
    "iso:country":"ES",
    "sg:address":"Carrer de Zorrilla, S/n",
    "sg:city":"Reus",
    "sg:orig_category":"Empleado Administrativo",
    "sg:phone":"+34 977 32 27 15",
    "sg:postcode":"43202",
    "sg:province":"Tarragona",
    "wof:name":"Centre Gestor Baix Camp S.l.",
    "wof:placetype":"venue"
},
  "geometry": {"coordinates":[1.0989400148,41.1587905884],"type":"Point"}
}