{
  "type": "Feature",
  "properties": {
    "iso:country":"ES",
    "sg:address":"Calle de Alvarez Sereix, 11",
    "sg:city":"Alacant",
    "sg:orig_category":"Doctores En Medicina",
    "sg:phone":"+34 965 20 65 41",
    "sg:postcode":"03001",
    "sg:province":"Alicante",
    "wof:name":"Gomez Guillen Fausto",
    "wof:placetype":"venue"
},
  "geometry": {"coordinates":[-0.4893324971,38.3459587097],"type":"Point"}
}