{
  "type": "Feature",
  "properties": {
    "iso:country":"ES",
    "sg:address":"Av Republica Argentina, 186",
    "sg:city":"Barcelona",
    "sg:orig_category":"Alquiler De V\u00cddeo",
    "sg:phone":"+34 934 18 88 99",
    "sg:postcode":"08023",
    "sg:province":"Barcelona",
    "wof:name":"V. Distribuciones S.l.",
    "wof:placetype":"venue"
},
  "geometry": {"coordinates":[2.1414830685,41.4118003845],"type":"Point"}
}