{
  "type": "Feature",
  "properties": {
    "addr:full":"Rua Valle Inclan, 1 Burela Lugo 27880",
    "addr:housenumber":"1",
    "addr:postcode":"27880",
    "addr:street":"Rua Valle Inclan",
    "iso:country":"ES",
    "sg:address":"Rua Valle Inclan, 1",
    "sg:city":"Burela",
    "sg:orig_category":"Agentes Generales De Seguros",
    "sg:phone":"+34 982 58 02 67",
    "sg:postcode":"27880",
    "sg:province":"Lugo",
    "wof:name":"Fernandez Ribera Carmen",
    "wof:placetype":"venue"
},
  "geometry": {"coordinates":[-7.3647089005,43.6566467285],"type":"Point"}
}