{
  "type": "Feature",
  "properties": {
    "iso:country":"ES",
    "sg:address":"Av Principat D'andorra (del), 17",
    "sg:city":"Salou",
    "sg:orig_category":"Art\u00cdculos De Regalo (al Por Menor)",
    "sg:phone":"+34 977 38 56 21",
    "sg:postcode":"43840",
    "sg:province":"Tarragona",
    "wof:name":"Pamies Martorell Jorge",
    "wof:placetype":"venue"
},
  "geometry": {"coordinates":[1.1442790031,41.0758514404],"type":"Point"}
}