{
  "type": "Feature",
  "properties": {
    "addr:full":"Calle de Gabriel Miro, 66 Santa Pola Alicante 03130",
    "addr:housenumber":"66",
    "addr:postcode":"03130",
    "addr:street":"Calle De Gabriel Miro",
    "iso:country":"ES",
    "sg:address":"Calle de Gabriel Miro, 66",
    "sg:city":"Santa Pola",
    "sg:orig_category":"Muebles Y Accesorios Para Cocinas Y Cuartos De Ba\u00d1o (al Por Menor)",
    "sg:phone":"+34 965 41 70 88",
    "sg:postcode":"03130",
    "sg:province":"Alicante",
    "wof:name":"Brotons Gomis Jose Antonio",
    "wof:placetype":"venue"
},
  "geometry": {"coordinates":[-0.5599539876,38.1936035156],"type":"Point"}
}