{
  "type": "Feature",
  "properties": {
    "addr:full":"Carrer de Taquigraf Garriga, 83 Barcelona Barcelona 08029",
    "addr:housenumber":"83",
    "addr:postcode":"08029",
    "addr:street":"Carrer De Taquigraf Garriga",
    "iso:country":"ES",
    "sg:address":"Carrer de Taquigraf Garriga, 83",
    "sg:city":"Barcelona",
    "sg:orig_category":"Peluquer\u00cdas, Peluquer\u00cda Mixta",
    "sg:phone":"+34 934 05 01 91",
    "sg:postcode":"08029",
    "sg:province":"Barcelona",
    "wof:name":"Perez Melgarejo Antonio",
    "wof:placetype":"venue"
},
  "geometry": {"coordinates":[2.1361150742,41.3884315491],"type":"Point"}
}