{
  "type": "Feature",
  "properties": {
    "addr:full":"Calle de Enrique Talg, S/n Puerto Cruz Santa Cruz De Tenerife 38400",
    "addr:housenumber":"s / n",
    "addr:postcode":"38400",
    "addr:street":"Calle De Enrique Talg;Cruz",
    "iso:country":"ES",
    "sg:address":"Calle de Enrique Talg, S/n",
    "sg:city":"Puerto Cruz",
    "sg:orig_category":"Peluqueros: De Se\u00d1oras",
    "sg:phone":"+34 922 37 51 20",
    "sg:postcode":"38400",
    "sg:province":"Santa Cruz De Tenerife",
    "wof:name":"Rodriguez Garcia Antonia Oliva",
    "wof:placetype":"venue"
},
  "geometry": {"coordinates":[-16.5458145142,28.416513443],"type":"Point"}
}