{
  "type": "Feature",
  "properties": {
    "iso:country":"ES",
    "sg:address":"Carrer de Esquadres, 11",
    "sg:city":"Hospitalet Llobregat",
    "sg:orig_category":"Empresas De Carpinter\u00cda",
    "sg:phone":"+34 932 61 11 48",
    "sg:postcode":"08901",
    "sg:province":"Barcelona",
    "wof:name":"Arasa Rosa Eduardo",
    "wof:placetype":"venue"
},
  "geometry": {"coordinates":[2.1083698273,41.3631706238],"type":"Point"}
}