{
  "type": "Feature",
  "properties": {
    "addr:full":"Avda San Amador, 27 Martos Ja\u00e9n 23600",
    "addr:housenumber":"27",
    "addr:postcode":"23600",
    "addr:street":"Avda San Amador;Jae\u0301N",
    "iso:country":"ES",
    "sg:address":"Avda San Amador, 27",
    "sg:city":"Martos",
    "sg:orig_category":"M\u00c9dicos: Estomatolog\u00cda",
    "sg:phone":"+34 953 55 17 99",
    "sg:postcode":"23600",
    "sg:province":"Ja\u00e9n",
    "wof:name":"Garcia Garrido Antonio",
    "wof:placetype":"venue"
},
  "geometry": {"coordinates":[-3.971211195,37.7204551697],"type":"Point"}
}