{
  "type": "Feature",
  "properties": {
    "iso:country":"ES",
    "sg:address":"Calle de Veintinueve De Diciembre, 55",
    "sg:city":"Tudela Duero",
    "sg:orig_category":"Delegados, Agentes De Tr\u00c1nsito, Auxiliares De Transporte Internacional",
    "sg:phone":"+34 983 52 03 59",
    "sg:postcode":"47320",
    "sg:province":"Valladolid",
    "wof:name":"Vela Arranz Pedro Luis",
    "wof:placetype":"venue"
},
  "geometry": {"coordinates":[-4.5823941231,41.5873565674],"type":"Point"}
}