{
  "type": "Feature",
  "properties": {
    "iso:country":"ES",
    "sg:address":"Calle de Hermanos Sanchez Del Rio, 5",
    "sg:city":"Haro",
    "sg:classifiers":[
        {
            "category":"Taxi",
            "type":"Transportation"
        }
    ],
    "sg:phone":"+34 941 31 01 07",
    "sg:postcode":"26200",
    "sg:province":"La Rioja",
    "wof:name":"Ayuntamiento De Haro",
    "wof:placetype":"venue"
},
  "geometry": {"coordinates":[-2.8460047245,42.5770797729],"type":"Point"}
}