{
  "type": "Feature",
  "properties": {
    "addr:full":"Avda La Libertad, 10 San Vicente De Barakaldo Vizcaya 48901",
    "addr:housenumber":"10",
    "addr:postcode":"48901",
    "addr:street":"Avda La Libertad",
    "iso:country":"ES",
    "sg:address":"Avda La Libertad, 10",
    "sg:city":"San Vicente De Barakaldo",
    "sg:orig_category":"Abogados",
    "sg:phone":"+34 944 37 70 52",
    "sg:postcode":"48901",
    "sg:province":"Vizcaya",
    "wof:name":"Mieza Arana Unai",
    "wof:placetype":"venue"
},
  "geometry": {"coordinates":[-2.9896502495,43.2958717346],"type":"Point"}
}