{
  "type": "Feature",
  "properties": {
    "addr:full":"Camino Viejo Simancas, S/n Valladolid Valladolid 47008",
    "addr:housenumber":"s / n",
    "addr:postcode":"47008",
    "addr:street":"Camino Viejo Simancas",
    "iso:country":"ES",
    "sg:address":"Camino Viejo Simancas, S/n",
    "sg:city":"Valladolid",
    "sg:orig_category":"Agencias De Viajes",
    "sg:phone":"+34 983 47 52 94",
    "sg:postcode":"47008",
    "sg:province":"Valladolid",
    "wof:name":"Viajes Eroski S.a.",
    "wof:placetype":"venue"
},
  "geometry": {"coordinates":[-4.7482089996,41.6258926392],"type":"Point"}
}