{
  "type": "Feature",
  "properties": {
    "addr:full":"Carrer de Independencia, 104 Hospitalet Llobregat Barcelona 08902",
    "addr:housenumber":"104",
    "addr:postcode":"08902",
    "addr:street":"Carrer De Independencia",
    "iso:country":"ES",
    "sg:address":"Carrer de Independencia, 104",
    "sg:city":"Hospitalet Llobregat",
    "sg:orig_category":"Transportes Por Carretera: Lotes Completos, Mercanc\u00cdas Diversas",
    "sg:phone":"+34 932 63 46 44",
    "sg:postcode":"08902",
    "sg:province":"Barcelona",
    "wof:name":"Dominguez Riveiro Abel",
    "wof:placetype":"venue"
},
  "geometry": {"coordinates":[2.1247119904,41.3607177734],"type":"Point"}
}