{
  "type": "Feature",
  "properties": {
    "addr:full":"Plaz San Lorenzo, 2 Sahagun Le\u00f3n 24320",
    "addr:housenumber":"2",
    "addr:postcode":"24320",
    "addr:street":"Plaz San Lorenzo;Leo\u0301N",
    "iso:country":"ES",
    "sg:address":"Plaz San Lorenzo, 2",
    "sg:city":"Sahagun",
    "sg:orig_category":"Iglesia Cat\u00d3lica",
    "sg:phone":"+34 987 78 08 84",
    "sg:postcode":"24320",
    "sg:province":"Le\u00f3n",
    "wof:name":"Parroquia De San Lorenzo",
    "wof:placetype":"venue"
},
  "geometry": {"coordinates":[-5.026113987,42.3711051941],"type":"Point"}
}