{
  "type": "Feature",
  "properties": {
    "iso:country":"ES",
    "sg:address":"Avda Federico Garcia Lorca, 238",
    "sg:city":"Almeria",
    "sg:orig_category":"Maquinaria Para Industrias Diversas",
    "sg:phone":"+34 950 24 64 34",
    "sg:postcode":"04008",
    "sg:province":"Almer\u00eda",
    "wof:name":"Guillermo Saez S.l.",
    "wof:placetype":"venue"
},
  "geometry": {"coordinates":[-2.4588696957,36.8457527161],"type":"Point"}
}