{
  "type": "Feature",
  "properties": {
    "iso:country":"ES",
    "sg:address":"Carrer de Antoni Roig (d'), 20",
    "sg:city":"Torredembarra",
    "sg:orig_category":"Peluquer\u00cdas, Peluquer\u00cda Mixta",
    "sg:phone":"+34 977 64 08 95",
    "sg:postcode":"43830",
    "sg:province":"Tarragona",
    "wof:name":"Valls Balleste Nuria",
    "wof:placetype":"venue"
},
  "geometry": {"coordinates":[1.3981440067,41.1445465088],"type":"Point"}
}