{
  "type": "Feature",
  "properties": {
    "addr:full":"Calle de Torrevieja, 14 Pola De Siero Asturias 33510",
    "addr:housenumber":"14",
    "addr:postcode":"33510",
    "addr:street":"Calle De Torrevieja",
    "iso:country":"ES",
    "sg:address":"Calle de Torrevieja, 14",
    "sg:city":"Pola De Siero",
    "sg:orig_category":"Alimentaci\u00d3n General (al Por Menor)",
    "sg:phone":"+34 985 72 40 67",
    "sg:postcode":"33510",
    "sg:province":"Asturias",
    "wof:name":"Alvarez Lagranda Ana Maria",
    "wof:placetype":"venue"
},
  "geometry": {"coordinates":[-5.6574091911,43.3911399841],"type":"Point"}
}