{
  "type": "Feature",
  "properties": {
    "iso:country":"ES",
    "sg:address":"Carrer de Valldargent, 50",
    "sg:city":"Palma",
    "sg:orig_category":"Agencias Y Agentes Comerciales, Representantes",
    "sg:phone":"+34 971 45 26 96",
    "sg:postcode":"07013",
    "sg:province":"Islas Baleares",
    "wof:name":"Confort Nostrum S.l.u.",
    "wof:placetype":"venue"
},
  "geometry": {"coordinates":[2.6372048855,39.5766067505],"type":"Point"}
}