{
  "type": "Feature",
  "properties": {
    "addr:full":"Los Pirralos, 45 Dos Hermanas Sevilla 41700",
    "addr:housenumber":"45",
    "addr:postcode":"41700",
    "addr:street":"Pirralos",
    "iso:country":"ES",
    "sg:address":"Los Pirralos, 45",
    "sg:city":"Dos Hermanas",
    "sg:orig_category":"Agencias De Viajes",
    "sg:phone":"+34 955 66 06 32",
    "sg:postcode":"41700",
    "sg:province":"Sevilla",
    "sg:website":"www.doshermanas.zafirotours.es",
    "wof:name":"Jesiva S.c.",
    "wof:placetype":"venue"
},
  "geometry": {"coordinates":[-5.9282941818,37.2787590027],"type":"Point"}
}