{
  "type": "Feature",
  "properties": {
    "iso:country":"ES",
    "sg:address":"Avda Federico Garcia Lorca, 77",
    "sg:city":"Almeria",
    "sg:orig_category":"Abogados",
    "sg:phone":"+34 950 23 62 96",
    "sg:postcode":"04004",
    "sg:province":"Almer\u00eda",
    "sg:website":"www.bufeteromera.com",
    "wof:name":"Bufete Romera S.l.",
    "wof:placetype":"venue"
},
  "geometry": {"coordinates":[-2.4592831135,36.8405685425],"type":"Point"}
}