{
  "type": "Feature",
  "properties": {
    "addr:full":"Carrer de Cavallers (dels), 12 Tarragona Tarragona 43003",
    "addr:housenumber":"12",
    "addr:postcode":"43003",
    "addr:street":"Carrer De Cavallers Dels",
    "iso:country":"ES",
    "sg:address":"Carrer de Cavallers (dels), 12",
    "sg:city":"Tarragona",
    "sg:orig_category":"Agencias Y Asesores De Publicidad",
    "sg:phone":"+34 977 24 48 70",
    "sg:postcode":"43003",
    "sg:province":"Tarragona",
    "wof:name":"Cruz Barros Elena",
    "wof:placetype":"venue"
},
  "geometry": {"coordinates":[1.2556979656,41.1177711487],"type":"Point"}
}