{
  "type": "Feature",
  "properties": {
    "addr:full":"Barr San Juan, 26 San Juan De Muskiz Vizcaya 48550",
    "addr:housenumber":"26",
    "addr:postcode":"48550",
    "addr:street":"San Juan",
    "iso:country":"ES",
    "sg:address":"Barr San Juan, 26",
    "sg:city":"San Juan De Muskiz",
    "sg:orig_category":"Empresas De Demolici\u00d3n",
    "sg:phone":"+34 946 70 69 46",
    "sg:postcode":"48550",
    "sg:province":"Vizcaya",
    "wof:name":"Barberan Goiri Antonio",
    "wof:placetype":"venue"
},
  "geometry": {"coordinates":[-3.122754097,43.3209648132],"type":"Point"}
}