{
  "type": "Feature",
  "properties": {
    "iso:country":"ES",
    "sg:address":"Avda Carballi\u00d1o (de), 8",
    "sg:city":"Beariz",
    "sg:orig_category":"Farmacias",
    "sg:phone":"+34 988 28 44 46",
    "sg:postcode":"32520",
    "sg:province":"Ourense",
    "wof:name":"Lamas Gulias Celso",
    "wof:placetype":"venue"
},
  "geometry": {"coordinates":[-8.2706699371,42.4750709534],"type":"Point"}
}