{
  "type": "Feature",
  "properties": {
    "addr:full":"Carrer de Sant Feliu, 36 Olot Girona 17800",
    "addr:housenumber":"36",
    "addr:postcode":"17800",
    "addr:street":"Carrer De Sant Feliu",
    "iso:country":"ES",
    "sg:address":"Carrer de Sant Feliu, 36",
    "sg:city":"Olot",
    "sg:orig_category":"Farmacias",
    "sg:phone":"+34 972 26 58 19",
    "sg:postcode":"17800",
    "sg:province":"Girona",
    "wof:name":"Faja Canadell Susana",
    "wof:placetype":"venue"
},
  "geometry": {"coordinates":[2.4704558849,42.1714553833],"type":"Point"}
}