{
  "type": "Feature",
  "properties": {
    "addr:full":"Avda La Estacion, 168 Ortuella Vizcaya 48530",
    "addr:housenumber":"168",
    "addr:postcode":"48530",
    "addr:street":"Avda La Estacion",
    "iso:country":"ES",
    "sg:address":"Avda La Estacion, 168",
    "sg:city":"Ortuella",
    "sg:orig_category":"Molduras, Junquillos, Listones Y Molduras Perforadas",
    "sg:phone":"+34 946 64 10 02",
    "sg:postcode":"48530",
    "sg:province":"Vizcaya",
    "wof:name":"Casanova Mendez Maria Jose",
    "wof:placetype":"venue"
},
  "geometry": {"coordinates":[-3.0609309673,43.3122177124],"type":"Point"}
}