{
  "type": "Feature",
  "properties": {
    "addr:full":"Calle de Monse\u00d1or Espinosa, 7 Orihuela Alicante 03300",
    "addr:housenumber":"7",
    "addr:postcode":"03300",
    "addr:street":"Calle De Monsen\u0303Or Espinosa",
    "iso:country":"ES",
    "sg:address":"Calle de Monse\u00d1or Espinosa, 7",
    "sg:city":"Orihuela",
    "sg:orig_category":"Promotores Constructores",
    "sg:phone":"+34 965 30 42 21",
    "sg:postcode":"03300",
    "sg:province":"Alicante",
    "wof:name":"Construcciones D Alexis S.l",
    "wof:placetype":"venue"
},
  "geometry": {"coordinates":[-0.9496049881,38.0826835632],"type":"Point"}
}