{
  "type": "Feature",
  "properties": {
    "addr:full":"Calle de Jose Simon De Lillo, 7 Pe\u00e7arroya-pueblonuevo C\u00f3rdoba 14200",
    "addr:housenumber":"7",
    "addr:postcode":"14200",
    "addr:street":"Calle De Jose Simon De Lillo;Co\u0301Rdoba",
    "iso:country":"ES",
    "sg:address":"Calle de Jose Simon De Lillo, 7",
    "sg:city":"Pe\u00e7arroya-pueblonuevo",
    "sg:orig_category":"Prot\u00c9sicos Dentales",
    "sg:phone":"+34 957 56 04 04",
    "sg:postcode":"14200",
    "sg:province":"C\u00f3rdoba",
    "wof:name":"Cordero Ruiz Antonio",
    "wof:placetype":"venue"
},
  "geometry": {"coordinates":[-5.2658519745,38.2994651794],"type":"Point"}
}