{
  "type": "Feature",
  "properties": {
    "iso:country":"ES",
    "sg:address":"Calle de Portillo Del Prado, 20",
    "sg:city":"Valladolid",
    "sg:orig_category":"Peluqueros: De Se\u00d1oras",
    "sg:phone":"+34 983 25 95 88",
    "sg:postcode":"47011",
    "sg:province":"Valladolid",
    "wof:name":"Alvarez Hernandez Elena",
    "wof:placetype":"venue"
},
  "geometry": {"coordinates":[-4.7173581123,41.6591377258],"type":"Point"}
}