{
  "type": "Feature",
  "properties": {
    "addr:full":"Avda Agua Marina, 68 Algeciras C\u00e1diz 11203",
    "addr:housenumber":"68;ca\u0301diz",
    "addr:postcode":"11203",
    "addr:street":"Avda Agua Marina",
    "iso:country":"ES",
    "sg:address":"Avda Agua Marina, 68",
    "sg:city":"Algeciras",
    "sg:orig_category":"Mec\u00c1nico Del Autom\u00d3vil",
    "sg:phone":"+34 956 66 80 61",
    "sg:postcode":"11203",
    "sg:province":"C\u00e1diz",
    "wof:name":"Morales Gil Jose",
    "wof:placetype":"venue"
},
  "geometry": {"coordinates":[-5.4666838646,36.1306610107],"type":"Point"}
}