{
  "type": "Feature",
  "properties": {
    "iso:country":"ES",
    "sg:address":"Avda Artes (de Las), 7",
    "sg:city":"Playa De Mogan",
    "sg:orig_category":"Zapatos (al Por Menor)",
    "sg:phone":"+34 928 56 53 59",
    "sg:postcode":"35138",
    "sg:province":"Las Palmas",
    "wof:name":"Calnava S.l.",
    "wof:placetype":"venue"
},
  "geometry": {"coordinates":[-13.8894538879,28.6940307617],"type":"Point"}
}