{
  "type": "Feature",
  "properties": {
    "iso:country":"ES",
    "sg:address":"Psaj Aranzazu, 6",
    "sg:city":"Malaga",
    "sg:orig_category":"Molduras, Junquillos, Listones Y Molduras Perforadas",
    "sg:phone":"+34 952 30 99 10",
    "sg:postcode":"29010",
    "sg:province":"M\u00e1laga",
    "wof:name":"Corrales Godoy Miguel",
    "wof:placetype":"venue"
},
  "geometry": {"coordinates":[-4.4369258881,36.7232170105],"type":"Point"}
}