{
  "type": "Feature",
  "properties": {
    "iso:country":"ES",
    "sg:address":"Carr Pere Cavasequia, 23",
    "sg:city":"Lleida",
    "sg:classifiers":[
        {
            "category":"Autos & Motor Vehicles",
            "subcategory":"Automobile Sales",
            "type":"Retail Goods"
        }
    ],
    "sg:phone":"+34 973 24 95 06",
    "sg:postcode":"25005",
    "sg:province":"Lleida",
    "wof:name":"Jove Vera Rosa",
    "wof:placetype":"venue"
},
  "geometry": {"coordinates":[0.6369540095,41.6218032837],"type":"Point"}
}