{
  "type": "Feature",
  "properties": {
    "iso:country":"ES",
    "sg:address":"Carrer de Falciot, 47",
    "sg:city":"Can Palet De Vista Alegre",
    "sg:orig_category":"Frutas, Legumbres Frescas Y Tempranas (al Por Menor)",
    "sg:phone":"+34 936 97 35 93",
    "sg:postcode":"08224",
    "sg:province":"Barcelona",
    "wof:name":"Cobos Sillero Maria",
    "wof:placetype":"venue"
},
  "geometry": {"coordinates":[1.9906500578,41.5405235291],"type":"Point"}
}