{
  "type": "Feature",
  "properties": {
    "iso:country":"ES",
    "sg:address":"Rua Peregrino (do), 48",
    "sg:city":"Sarria",
    "sg:classifiers":[
        {
            "category":"Autos & Motor Vehicles",
            "subcategory":"Automobile Sales",
            "type":"Retail Goods"
        }
    ],
    "sg:phone":"+34 982 53 11 65",
    "sg:postcode":"27600",
    "sg:province":"Lugo",
    "wof:name":"Fermar-autoescuela Alberto S.l.l",
    "wof:placetype":"venue"
},
  "geometry": {"coordinates":[-7.4125490189,42.7762184143],"type":"Point"}
}