{
  "type": "Feature",
  "properties": {
    "iso:country":"ES",
    "sg:address":"Rua Pontevedra, 5",
    "sg:city":"Cambados",
    "sg:orig_category":"Asesor\u00cda Sobre Comunicaci\u00d3n De Empresas",
    "sg:phone":"+34 986 54 27 51",
    "sg:postcode":"36630",
    "sg:province":"Pontevedra",
    "wof:name":"Pi\u00f1eiro Oubi\u00f1a Fernando",
    "wof:placetype":"venue"
},
  "geometry": {"coordinates":[-8.8137540817,42.5147743225],"type":"Point"}
}