{
  "type": "Feature",
  "properties": {
    "iso:country":"ES",
    "sg:address":"Calle de San Antonio, S/n",
    "sg:city":"Montehermoso",
    "sg:orig_category":"Conservas De Legumbres (fabricaci\u00d3n, Al Por Mayor)",
    "sg:phone":"+34 927 43 02 91",
    "sg:postcode":"10810",
    "sg:province":"C\u00e1ceres",
    "wof:name":"Poldo Torre S.l.",
    "wof:placetype":"venue"
},
  "geometry": {"coordinates":[-6.3504490852,40.0901565552],"type":"Point"}
}