{
  "type": "Feature",
  "properties": {
    "addr:full":"Calle de Obispo Almarcha, 23 Le\u00f3n Le\u00f3n 24006",
    "addr:housenumber":"23",
    "addr:postcode":"24006",
    "addr:street":"Calle De Obispo Almarcha;Leo\u0301N",
    "iso:country":"ES",
    "sg:address":"Calle de Obispo Almarcha, 23",
    "sg:city":"Le\u00f3n",
    "sg:orig_category":"Peluqueros: De Se\u00d1oras",
    "sg:phone":"+34 987 21 39 57",
    "sg:postcode":"24006",
    "sg:province":"Le\u00f3n",
    "wof:name":"Carbajo De Paz Maria Concepcion",
    "wof:placetype":"venue"
},
  "geometry": {"coordinates":[-5.5619292259,42.5979347229],"type":"Point"}
}