{
  "type": "Feature",
  "properties": {
    "iso:country":"ES",
    "sg:address":"Calle de Gabiria, 2",
    "sg:city":"Irun",
    "sg:orig_category":"Coches Y Camiones",
    "sg:phone":"+34 943 63 03 03",
    "sg:postcode":"20305",
    "sg:province":"Guip\u00f9zcoa",
    "wof:name":"Euro D.f.",
    "wof:placetype":"venue"
},
  "geometry": {"coordinates":[-1.8253079653,43.3286094666],"type":"Point"}
}