{
  "type": "Feature",
  "properties": {
    "addr:full":"Avda Mar Mediterraneo (del), 110 Valdemoro Madrid 28340",
    "addr:housenumber":"110",
    "addr:postcode":"28340",
    "addr:street":"Avda Mar Mediterraneo Del",
    "iso:country":"ES",
    "sg:address":"Avda Mar Mediterraneo (del), 110",
    "sg:city":"Valdemoro",
    "sg:orig_category":"Zapatos (al Por Menor)",
    "sg:phone":"+34 918 01 93 34",
    "sg:postcode":"28340",
    "sg:province":"Madrid",
    "wof:name":"Perez Romera Patricia",
    "wof:placetype":"venue"
},
  "geometry": {"coordinates":[-3.6844329834,40.1809539795],"type":"Point"}
}