{
  "type": "Feature",
  "properties": {
    "addr:full":"Carr Pau Casals, 1 Vidreres Girona 17411",
    "addr:housenumber":"1",
    "addr:postcode":"17411",
    "addr:street":"Carr Pau Casals",
    "iso:country":"ES",
    "sg:address":"Carr Pau Casals, 1",
    "sg:city":"Vidreres",
    "sg:orig_category":"Muebles, Minoristas",
    "sg:phone":"+34 972 85 00 06",
    "sg:postcode":"17411",
    "sg:province":"Girona",
    "wof:name":"Carrillo Boschdemont S.c.",
    "wof:placetype":"venue"
},
  "geometry": {"coordinates":[2.7789371014,41.7893447876],"type":"Point"}
}