{
  "type": "Feature",
  "properties": {
    "addr:full":"Carrer de Francesc Izard, S/n Sabadell Barcelona 08208",
    "addr:housenumber":"s",
    "addr:postcode":"08208",
    "addr:street":"Carrer De Francesc Izard;/ N",
    "iso:country":"ES",
    "sg:address":"Carrer de Francesc Izard, S/n",
    "sg:city":"Sabadell",
    "sg:orig_category":"Centros Pms (psico",
    "sg:phone":"+34 937 23 33 13",
    "sg:postcode":"08208",
    "sg:province":"Barcelona",
    "wof:name":"Centre De Telecomunicaciones De Catalunya",
    "wof:placetype":"venue"
},
  "geometry": {"coordinates":[2.1123900414,41.5549201965],"type":"Point"}
}