{
  "type": "Feature",
  "properties": {
    "iso:country":"ES",
    "sg:address":"Avda Santuario, 35",
    "sg:city":"Altura",
    "sg:orig_category":"Supermercados Y Hipermercados",
    "sg:phone":"+34 964 14 64 49",
    "sg:postcode":"12410",
    "sg:province":"Castell\u00f3n",
    "wof:name":"Autoservicio San Fulgencio S.l.",
    "wof:placetype":"venue"
},
  "geometry": {"coordinates":[-0.5139542222,39.8492889404],"type":"Point"}
}