{
  "type": "Feature",
  "properties": {
    "iso:country":"ES",
    "sg:address":"Avda Colon, 9",
    "sg:city":"Badajoz",
    "sg:orig_category":"Perfumer\u00cda (al Por Menor)",
    "sg:phone":"+34 924 23 15 91",
    "sg:postcode":"06005",
    "sg:province":"Badajoz",
    "wof:name":"Escobar Zorro Nicolas",
    "wof:placetype":"venue"
},
  "geometry": {"coordinates":[-6.976913929,38.8756027222],"type":"Point"}
}