{
  "type": "Feature",
  "properties": {
    "iso:country":"ES",
    "sg:address":"Rond Segovia, 2",
    "sg:city":"Madrid",
    "sg:orig_category":"M\u00c9dicos: Ginecolog\u00cda Y Obstetricia",
    "sg:phone":"+34 913 65 17 28",
    "sg:postcode":"28005",
    "sg:province":"Madrid",
    "wof:name":"Roldan Rodriguez Marin Antonio Jesus",
    "wof:placetype":"venue"
},
  "geometry": {"coordinates":[-3.7092499733,40.413860321],"type":"Point"}
}