{
  "type": "Feature",
  "properties": {
    "iso:country":"ES",
    "sg:address":"Errotazar, 23",
    "sg:city":"Iru\u00f1a",
    "sg:orig_category":"Herradores, Herreros",
    "sg:phone":"+34 948 12 83 73",
    "sg:postcode":"31014",
    "sg:province":"Navarra",
    "wof:name":"Talleres Marcotegui S. L.",
    "wof:placetype":"venue"
},
  "geometry": {"coordinates":[-1.6435990334,42.8284645081],"type":"Point"}
}