{
  "type": "Feature",
  "properties": {
    "iso:country":"ES",
    "sg:address":"Av Rei En Jaume, Km. 0005,5",
    "sg:city":"Cardedeu",
    "sg:orig_category":"Instalaci\u00d3n, Reparaci\u00d3n De Calefacci\u00d3n Por Gas",
    "sg:phone":"+34 938 46 17 43",
    "sg:postcode":"08440",
    "sg:province":"Barcelona",
    "wof:name":"Terrades Domenech Andreu",
    "wof:placetype":"venue"
},
  "geometry": {"coordinates":[2.3567531109,41.6367912292],"type":"Point"}
}