{
  "type": "Feature",
  "properties": {
    "addr:full":"Calle de Rodriguez Jaldon, 1 Carmona Sevilla 41410",
    "addr:housenumber":"1",
    "addr:postcode":"41410",
    "addr:street":"Calle De Rodriguez Jaldon",
    "iso:country":"ES",
    "sg:address":"Calle de Rodriguez Jaldon, 1",
    "sg:city":"Carmona",
    "sg:orig_category":"Pescader\u00cdas (al Por Menor)",
    "sg:phone":"+34 954 14 44 32",
    "sg:postcode":"41410",
    "sg:province":"Sevilla",
    "wof:name":"Ferruzola Perez Felipe",
    "wof:placetype":"venue"
},
  "geometry": {"coordinates":[-5.6467399597,37.4634437561],"type":"Point"}
}