{
  "type": "Feature",
  "properties": {
    "iso:country":"ES",
    "sg:address":"Calle de San Miguel, 1",
    "sg:city":"Zaragoza",
    "sg:orig_category":"Abogados",
    "sg:phone":"+34 976 22 28 92",
    "sg:postcode":"50001",
    "sg:province":"Zaragoza",
    "wof:name":"Del Rio Garcia Bego\u00f1a",
    "wof:placetype":"venue"
},
  "geometry": {"coordinates":[-0.8813380003,41.6513824463],"type":"Point"}
}