{
  "type": "Feature",
  "properties": {
    "iso:country":"ES",
    "sg:address":"Pas Sota Muralla, 13",
    "sg:city":"Barcelona",
    "sg:orig_category":"Bazares, Art\u00cdculos De Limpieza Y De Cocina (al Por Menor)",
    "sg:phone":"+34 933 10 21 70",
    "sg:postcode":"08003",
    "sg:province":"Barcelona",
    "wof:name":"Agrupacion Bazar El Regalo S.a.",
    "wof:placetype":"venue"
},
  "geometry": {"coordinates":[2.1839668751,41.3816604614],"type":"Point"}
}