{
  "type": "Feature",
  "properties": {
    "iso:country":"ES",
    "sg:address":"Calle de San Antonio, 22",
    "sg:city":"Albacete",
    "sg:orig_category":"Electrodom\u00c9sticos (al Por Menor)",
    "sg:phone":"+34 967 52 23 40",
    "sg:postcode":"02001",
    "sg:province":"Albacete",
    "wof:name":"Garrido Tercero Miguel",
    "wof:placetype":"venue"
},
  "geometry": {"coordinates":[-1.8537130356,38.9970474243],"type":"Point"}
}