{
  "type": "Feature",
  "properties": {
    "iso:country":"ES",
    "sg:address":"Calle de Errekatxu, 8",
    "sg:city":"Barakaldo",
    "sg:orig_category":"Ropa Para Ni\u00d1os (al Por Menor)",
    "sg:phone":"+34 944 78 10 72",
    "sg:postcode":"48902",
    "sg:province":"Vizcaya",
    "wof:name":"Bego\u00f1a Tello Morcillo-corre Caminos",
    "wof:placetype":"venue"
},
  "geometry": {"coordinates":[-2.9990410805,43.2950592041],"type":"Point"}
}