{
  "type": "Feature",
  "properties": {
    "addr:full":"Pol Ind Can Massaguer, 15 Sta. Agnes Malanyanes Barcelona 08430",
    "addr:housenumber":"15",
    "addr:postcode":"08430",
    "addr:street":"Ind;Massaguer",
    "iso:country":"ES",
    "sg:address":"Pol Ind Can Massaguer, 15",
    "sg:city":"Sta. Agnes Malanyanes",
    "sg:orig_category":"Ropa Para Ni\u00d1os (al Por Menor)",
    "sg:phone":"+34 938 42 31 04",
    "sg:postcode":"08430",
    "sg:province":"Barcelona",
    "wof:name":"Karpi Confeccion S.l.",
    "wof:placetype":"venue"
},
  "geometry": {"coordinates":[2.3250501156,41.5845298767],"type":"Point"}
}