{
  "type": "Feature",
  "properties": {
    "addr:full":"Calle de Barrichuelo, 17 Epila Zaragoza 50290",
    "addr:housenumber":"17",
    "addr:postcode":"50290",
    "addr:street":"Calle De Barrichuelo",
    "iso:country":"ES",
    "sg:address":"Calle de Barrichuelo, 17",
    "sg:city":"Epila",
    "sg:orig_category":"Transportes Por V\u00cdas Navegables",
    "sg:phone":"+34 976 60 37 20",
    "sg:postcode":"50290",
    "sg:province":"Zaragoza",
    "wof:name":"Egea Bernal Manuel",
    "wof:placetype":"venue"
},
  "geometry": {"coordinates":[-1.2802823782,41.5983695984],"type":"Point"}
}