{
  "type": "Feature",
  "properties": {
    "addr:full":"Calle de Obispo San Juan De Rivera, 9 Badajoz Badajoz 06002",
    "addr:housenumber":"9",
    "addr:postcode":"06002",
    "addr:street":"Calle De Obispo San;Rivera",
    "iso:country":"ES",
    "sg:address":"Calle de Obispo San Juan De Rivera, 9",
    "sg:city":"Badajoz",
    "sg:orig_category":"Inmobiliaria (agencias)",
    "sg:phone":"+34 924 22 05 40",
    "sg:postcode":"06002",
    "sg:province":"Badajoz",
    "wof:name":"Promotora Conquistadores S.a.",
    "wof:placetype":"venue"
},
  "geometry": {"coordinates":[-6.9711785316,38.8774337769],"type":"Point"}
}