{
  "type": "Feature",
  "properties": {
    "addr:full":"Avda Entrevias, 52 Madrid Madrid 28053",
    "addr:housenumber":"52",
    "addr:postcode":"madrid;28053",
    "addr:street":"Avda Entrevias",
    "iso:country":"ES",
    "sg:address":"Avda Entrevias, 52",
    "sg:city":"Madrid",
    "sg:orig_category":"Limpieza Con Chorro De Arena Y Con Granalla, Pulido",
    "sg:phone":"+34 917 85 83 44",
    "sg:postcode":"28053",
    "sg:province":"Madrid",
    "wof:name":"Sanchez Ruiz Francisco Javier",
    "wof:placetype":"venue"
},
  "geometry": {"coordinates":[-3.6692640781,40.3821678162],"type":"Point"}
}