{
  "type": "Feature",
  "properties": {
    "addr:full":"Euskadi Etorbidea, 3 Pasai S. Pedro Guip\u00f9zcoa 20110",
    "addr:housenumber":"3",
    "addr:postcode":"20110",
    "addr:street":"Euskadi Etorbidea;Guipu\u0300Zcoa",
    "iso:country":"ES",
    "sg:address":"Euskadi Etorbidea, 3",
    "sg:city":"Pasai S. Pedro",
    "sg:orig_category":"Librer\u00cdas",
    "sg:phone":"+34 943 39 03 16",
    "sg:postcode":"20110",
    "sg:province":"Guip\u00f9zcoa",
    "wof:name":"Lopez Alzugarai Felicidad",
    "wof:placetype":"venue"
},
  "geometry": {"coordinates":[-1.9300839901,43.3229217529],"type":"Point"}
}