{
  "type": "Feature",
  "properties": {
    "addr:full":"Calle de Pablo Iglesias, 1 Magacela Badajoz 06468",
    "addr:housenumber":"1",
    "addr:postcode":"06468",
    "addr:street":"Calle De Pablo Iglesias",
    "iso:country":"ES",
    "sg:address":"Calle de Pablo Iglesias, 1",
    "sg:city":"Magacela",
    "sg:orig_category":"Electrodom\u00c9sticos (al Por Menor)",
    "sg:phone":"+34 924 85 31 85",
    "sg:postcode":"06468",
    "sg:province":"Badajoz",
    "wof:name":"Izquierdo Fernandez Diego",
    "wof:placetype":"venue"
},
  "geometry": {"coordinates":[-5.7348151207,38.8969192505],"type":"Point"}
}