{
  "type": "Feature",
  "properties": {
    "addr:full":"Concepcion Arenal, 10 Massanassa Valencia 46470",
    "addr:housenumber":"10",
    "addr:postcode":"46470",
    "addr:street":"Concepcion Arenal",
    "iso:country":"ES",
    "sg:address":"Concepcion Arenal, 10",
    "sg:city":"Massanassa",
    "sg:orig_category":"Perfumer\u00cda (al Por Menor)",
    "sg:phone":"+34 961 25 06 76",
    "sg:postcode":"46470",
    "sg:province":"Valencia",
    "wof:name":"Hinarejos Saiz Ana Maria",
    "wof:placetype":"venue"
},
  "geometry": {"coordinates":[-0.3996959925,39.414604187],"type":"Point"}
}