{
  "type": "Feature",
  "properties": {
    "addr:full":"Carr Marques De Caceres, 35 Eliana Valencia 46183",
    "addr:housenumber":"35",
    "addr:postcode":"46183",
    "addr:street":"Carr Marques De Caceres",
    "iso:country":"ES",
    "sg:address":"Carr Marques De Caceres, 35",
    "sg:city":"Eliana",
    "sg:orig_category":"Institutos De Belleza",
    "sg:phone":"+34 962 74 42 05",
    "sg:postcode":"46183",
    "sg:province":"Valencia",
    "wof:name":"Eva Y Teresa S.l.",
    "wof:placetype":"venue"
},
  "geometry": {"coordinates":[-0.5311620235,39.56590271],"type":"Point"}
}