{
  "type": "Feature",
  "properties": {
    "addr:full":"Avda Ejercito (del), 10 Puerto De Santa Maria C\u00e1diz 11500",
    "addr:postcode":"11500",
    "addr:street":"Avda Ejercito Del 10 Puerto De Santa;Ca\u0301Diz",
    "iso:country":"ES",
    "sg:address":"Avda Ejercito (del), 10",
    "sg:city":"Puerto De Santa Maria",
    "sg:orig_category":"Formaci\u00d3n Continuada (variada)",
    "sg:phone":"+34 956 54 13 52",
    "sg:postcode":"11500",
    "sg:province":"C\u00e1diz",
    "wof:name":"Gordillo Alcalde Maria Del Pilar",
    "wof:placetype":"venue"
},
  "geometry": {"coordinates":[-6.2352781296,36.5944328308],"type":"Point"}
}