{
  "type": "Feature",
  "properties": {
    "iso:country":"ES",
    "sg:address":"Avda Arias De Velasco, S/n",
    "sg:city":"Marbella",
    "sg:orig_category":"Alimentaci\u00d3n General (al Por Menor)",
    "sg:phone":"+34 952 82 32 50",
    "sg:postcode":"29600",
    "sg:province":"M\u00e1laga",
    "wof:name":"Sanchez Parra Jose",
    "wof:placetype":"venue"
},
  "geometry": {"coordinates":[-4.8837471008,36.5166435242],"type":"Point"}
}