{
  "type": "Feature",
  "properties": {
    "addr:full":"Calle de Asturias, 2 Torres Cotillas Murcia 30565",
    "addr:housenumber":"2",
    "addr:postcode":"30565",
    "addr:street":"Calle De Asturias",
    "iso:country":"ES",
    "sg:address":"Calle de Asturias, 2",
    "sg:city":"Torres Cotillas",
    "sg:orig_category":"Electricidad: Instaladores",
    "sg:phone":"+34 968 38 70 76",
    "sg:postcode":"30565",
    "sg:province":"Murcia",
    "wof:name":"Bermudez Argumedo Juan Manuel",
    "wof:placetype":"venue"
},
  "geometry": {"coordinates":[-1.2431089878,38.0194511414],"type":"Point"}
}