{
  "type": "Feature",
  "properties": {
    "addr:full":"Calle de Ciutat De Melilla, 1 Valencia Valencia 46017",
    "addr:housenumber":"1",
    "addr:postcode":"46017",
    "addr:street":"Calle De Ciutat De Melilla",
    "iso:country":"ES",
    "sg:address":"Calle de Ciutat De Melilla, 1",
    "sg:city":"Valencia",
    "sg:orig_category":"Inmobiliaria (agencias)",
    "sg:phone":"+34 963 77 01 82",
    "sg:postcode":"46017",
    "sg:province":"Valencia",
    "wof:name":"Garpe Gestion S.l.",
    "wof:placetype":"venue"
},
  "geometry": {"coordinates":[-0.3915728927,39.4574966431],"type":"Point"}
}