{
  "type": "Feature",
  "properties": {
    "iso:country":"ES",
    "sg:address":"Carrer de Bon Pastor, 3",
    "sg:city":"Barcelona",
    "sg:orig_category":"M\u00c9dicos: Cirug\u00cda General",
    "sg:phone":"+34 932 09 41 41",
    "sg:postcode":"08021",
    "sg:province":"Barcelona",
    "wof:name":"Gajo Reyero Ramon",
    "wof:placetype":"venue"
},
  "geometry": {"coordinates":[2.1497468948,41.3945121765],"type":"Point"}
}