{
  "type": "Feature",
  "properties": {
    "iso:country":"ES",
    "sg:address":"Calle de Francisco Sancha, 8",
    "sg:city":"Madrid",
    "sg:orig_category":"Inform\u00c1tica: Material Y Suministros",
    "sg:phone":"+34 913 58 18 56",
    "sg:postcode":"28034",
    "sg:province":"Madrid",
    "wof:name":"Coalba Energia S.a.",
    "wof:placetype":"venue"
},
  "geometry": {"coordinates":[-3.6874411106,40.4869804382],"type":"Point"}
}