{
  "type": "Feature",
  "properties": {
    "addr:full":"Calle de Merced (la), S/n Linares Ja\u00e9n 23700",
    "addr:postcode":"23700",
    "addr:street":"Calle De Merced La S / N;Jae\u0301N",
    "iso:country":"ES",
    "sg:address":"Calle de Merced (la), S/n",
    "sg:city":"Linares",
    "sg:orig_category":"Ingeniero",
    "sg:phone":"+34 953 65 18 54",
    "sg:postcode":"23700",
    "sg:province":"Ja\u00e9n",
    "wof:name":"Ictel C.b",
    "wof:placetype":"venue"
},
  "geometry": {"coordinates":[-3.6298439503,38.0896339417],"type":"Point"}
}