{
  "type": "Feature",
  "properties": {
    "addr:full":"Calle de Feria San Isidro Labrador, S/n Fuengirola M\u00e1laga 29640",
    "addr:housenumber":"s / n",
    "addr:postcode":"29640",
    "addr:street":"Calle De;Ma\u0301Laga",
    "iso:country":"ES",
    "sg:address":"Calle de Feria San Isidro Labrador, S/n",
    "sg:city":"Fuengirola",
    "sg:orig_category":"Importaci\u00d3n",
    "sg:phone":"+34 952 19 91 48",
    "sg:postcode":"29640",
    "sg:province":"M\u00e1laga",
    "wof:name":"Nordic Spain Trade S.l.",
    "wof:placetype":"venue"
},
  "geometry": {"coordinates":[-4.6214313507,36.5476989746],"type":"Point"}
}