{
  "type": "Feature",
  "properties": {
    "addr:full":"Calle de Pabostria, 4 Zaragoza Zaragoza 50001",
    "addr:housenumber":"4",
    "addr:postcode":"50001",
    "addr:street":"Calle De Pabostria",
    "iso:country":"ES",
    "sg:address":"Calle de Pabostria, 4",
    "sg:city":"Zaragoza",
    "sg:orig_category":"Grafistas",
    "sg:phone":"+34 976 29 72 61",
    "sg:postcode":"50001",
    "sg:province":"Zaragoza",
    "sg:website":"www.estudiocamaleon.com",
    "wof:name":"Estudio Camaleon S.c.",
    "wof:placetype":"venue"
},
  "geometry": {"coordinates":[-0.8761069775,41.6541938782],"type":"Point"}
}