{
  "type": "Feature",
  "properties": {
    "addr:full":"Avda El Minero, S/n Gallarta Vizcaya 48500",
    "addr:housenumber":"s",
    "addr:postcode":"48500",
    "addr:street":"Avda El Minero;/ N",
    "iso:country":"ES",
    "sg:address":"Avda El Minero, S/n",
    "sg:city":"Gallarta",
    "sg:orig_category":"Sanatorios M\u00c9dico",
    "sg:phone":"+34 946 36 20 11",
    "sg:postcode":"48500",
    "sg:province":"Vizcaya",
    "wof:name":"Servicio Vasco De Salud",
    "wof:placetype":"venue"
},
  "geometry": {"coordinates":[-3.0730679035,43.3121757507],"type":"Point"}
}