{
  "type": "Feature",
  "properties": {
    "iso:country":"ES",
    "sg:address":"Calle de Anaca, 28",
    "sg:city":"Irun",
    "sg:orig_category":"Persianas Interiores, Exteriores",
    "sg:phone":"+34 943 61 34 66",
    "sg:postcode":"20301",
    "sg:province":"Guip\u00f9zcoa",
    "wof:name":"Toldos Beti-idor S.l.",
    "wof:placetype":"venue"
},
  "geometry": {"coordinates":[-1.8055349588,43.3408432007],"type":"Point"}
}