{
  "type": "Feature",
  "properties": {
    "iso:country":"ES",
    "sg:address":"Calle de Peru, 9",
    "sg:city":"Valladolid",
    "sg:orig_category":"Mec\u00c1nico Del Autom\u00d3vil",
    "sg:phone":"+34 983 30 16 99",
    "sg:postcode":"47004",
    "sg:province":"Valladolid",
    "wof:name":"Empresa Carrion S. A.",
    "wof:placetype":"venue"
},
  "geometry": {"coordinates":[-4.7272481918,41.6472740173],"type":"Point"}
}