{
  "type": "Feature",
  "properties": {
    "iso:country":"ES",
    "sg:address":"Mcdo Pl Barcelona, S/n",
    "sg:city":"Elche",
    "sg:orig_category":"Carnicer\u00cdas, Carnicer\u00cdas",
    "sg:phone":"+34 965 46 93 15",
    "sg:postcode":"03206",
    "sg:province":"Alicante",
    "wof:name":"Rodriguez Berna Manuel",
    "wof:placetype":"venue"
},
  "geometry": {"coordinates":[-0.7061319947,38.2717590332],"type":"Point"}
}