{
  "type": "Feature",
  "properties": {
    "iso:country":"ES",
    "sg:address":"Calle de San Emilio, 20",
    "sg:city":"Madrid",
    "sg:orig_category":"Venta, Instalaci\u00d3n De Calefacci\u00d3n",
    "sg:phone":"+34 913 56 17 52",
    "sg:postcode":"28017",
    "sg:province":"Madrid",
    "wof:name":"Fontaneria Ropri S.l.",
    "wof:placetype":"venue"
},
  "geometry": {"coordinates":[-3.6592540741,40.42735672],"type":"Point"}
}