{
  "type": "Feature",
  "properties": {
    "iso:country":"ES",
    "sg:address":"Carrer de Banys Nous, 21",
    "sg:city":"Barcelona",
    "sg:orig_category":"Compraventa De Antig\u00dcedades",
    "sg:phone":"+34 933 18 14 44",
    "sg:postcode":"08002",
    "sg:province":"Barcelona",
    "wof:name":"Sandoval Sarrias Olga",
    "wof:placetype":"venue"
},
  "geometry": {"coordinates":[2.174382925,41.3830528259],"type":"Point"}
}