{
  "type": "Feature",
  "properties": {
    "addr:full":"Calle de Facaracas, 6 Galdar Las Palmas 35460",
    "addr:housenumber":"6",
    "addr:postcode":"35460",
    "addr:street":"Calle De Facaracas",
    "iso:country":"ES",
    "sg:address":"Calle de Facaracas, 6",
    "sg:city":"Galdar",
    "sg:orig_category":"M\u00c9dicos: Radioterapia (radioterapia Como Opci\u00d3n Oncol\u00d3gica)",
    "sg:phone":"+34 928 55 20 97",
    "sg:postcode":"35460",
    "sg:province":"Las Palmas",
    "wof:name":"Centro Radiologico Galdar S.c.p.",
    "wof:placetype":"venue"
},
  "geometry": {"coordinates":[-15.6555528641,28.1444473267],"type":"Point"}
}