{
  "type": "Feature",
  "properties": {
    "addr:full":"Calle de Coscoja, S/n Encinar Del Alberche Madrid 28630",
    "addr:housenumber":"s / n",
    "addr:postcode":"28630",
    "addr:street":"Calle De Coscoja",
    "iso:country":"ES",
    "sg:address":"Calle de Coscoja, S/n",
    "sg:city":"Encinar Del Alberche",
    "sg:classifiers":[
        {
            "category":"Sports & Exercise",
            "subcategory":"Golf",
            "type":"Entertainment"
        }
    ],
    "sg:phone":"+34 918 67 45 16",
    "sg:postcode":"28630",
    "sg:province":"Madrid",
    "sg:tags":[
        "y",
        "de",
        "campos",
        "clases"
    ],
    "wof:name":"Club De Golf Encinar",
    "wof:placetype":"venue"
},
  "geometry": {"coordinates":[-4.3527569771,40.2775344849],"type":"Point"}
}