{
  "type": "Feature",
  "properties": {
    "iso:country":"ES",
    "sg:address":"Calle de Autonomia, 41",
    "sg:city":"Bilbao",
    "sg:orig_category":"Panader\u00cdas, Panader\u00cdas",
    "sg:phone":"+34 944 43 98 47",
    "sg:postcode":"48012",
    "sg:province":"Vizcaya",
    "wof:name":"Jose Antonio Carrasco Maroto Y Otro C.b.",
    "wof:placetype":"venue"
},
  "geometry": {"coordinates":[-2.9424521923,43.257598877],"type":"Point"}
}