{
  "type": "Feature",
  "properties": {
    "iso:country":"ES",
    "sg:address":"Calle de Claudio Coello, 18",
    "sg:city":"Madrid",
    "sg:orig_category":"Importaci\u00d3n",
    "sg:phone":"+34 915 77 99 43",
    "sg:postcode":"28001",
    "sg:province":"Madrid",
    "wof:name":"Pepe Jeans S. L.",
    "wof:placetype":"venue"
},
  "geometry": {"coordinates":[-3.6869606972,40.4225845337],"type":"Point"}
}