{
  "type": "Feature",
  "properties": {
    "addr:full":"Partida Sant Honorat, S/n Solsona Lleida 25280",
    "addr:housenumber":"s / n",
    "addr:postcode":"25280",
    "addr:street":"Partida Sant Honorat",
    "iso:country":"ES",
    "sg:address":"Partida Sant Honorat, S/n",
    "sg:city":"Solsona",
    "sg:orig_category":"Venta, Instalaci\u00d3n De Calefacci\u00d3n",
    "sg:phone":"+34 973 48 15 85",
    "sg:postcode":"25280",
    "sg:province":"Lleida",
    "wof:name":"Instalaciones Lumisol S.l.",
    "wof:placetype":"venue"
},
  "geometry": {"coordinates":[1.5206480026,41.9950942993],"type":"Point"}
}