{
  "type": "Feature",
  "properties": {
    "iso:country":"ES",
    "sg:address":"Carr Poeta Ruyra, 13",
    "sg:city":"Hostalric",
    "sg:orig_category":"Carnicer\u00cdas, Carnicer\u00cdas",
    "sg:phone":"+34 972 86 47 54",
    "sg:postcode":"17450",
    "sg:province":"Girona",
    "wof:name":"Marti Massaguer Juan",
    "wof:placetype":"venue"
},
  "geometry": {"coordinates":[2.6305301189,41.7464103699],"type":"Point"}
}