{
  "type": "Feature",
  "properties": {
    "addr:full":"Calle de Pio Xii, 34 Palmas De Gran Canaria Las Palmas 35005",
    "addr:housenumber":"34",
    "addr:postcode":"35005",
    "addr:street":"Calle De Pio Xii",
    "iso:country":"ES",
    "sg:address":"Calle de Pio Xii, 34",
    "sg:city":"Palmas De Gran Canaria",
    "sg:orig_category":"Internados & Ense\u00d1anza Privada",
    "sg:phone":"+34 928 29 00 01",
    "sg:postcode":"35005",
    "sg:province":"Las Palmas",
    "wof:name":"Colegio Teresiano",
    "wof:placetype":"venue"
},
  "geometry": {"coordinates":[-15.4328794479,28.1278057098],"type":"Point"}
}