{
  "type": "Feature",
  "properties": {
    "iso:country":"ES",
    "sg:address":"Boa\u00f1a Arriba (castriz), S/n",
    "sg:city":"Boa\u00e7a De Arriba",
    "sg:orig_category":"Agricultores, Agricultores",
    "sg:phone":"+34 981 89 49 01",
    "sg:postcode":"15848",
    "sg:province":"A Coru\u00f1a",
    "wof:name":"Sat Rial S.l",
    "wof:placetype":"venue"
},
  "geometry": {"coordinates":[-8.7996873856,43.0711250305],"type":"Point"}
}