{
  "type": "Feature",
  "properties": {
    "iso:country":"ES",
    "sg:address":"Pol Ind Red, S/n",
    "sg:city":"Alcala Guadaira",
    "sg:orig_category":"Construcciones Met\u00c1licas",
    "sg:phone":"+34 955 63 46 62",
    "sg:postcode":"41500",
    "sg:province":"Sevilla",
    "wof:name":"Tuberias Industriales Y Caldereria S.a.",
    "wof:placetype":"venue"
},
  "geometry": {"coordinates":[-5.8398590088,37.3383140564],"type":"Point"}
}