{
  "type": "Feature",
  "properties": {
    "iso:country":"ES",
    "sg:address":"Calle de Esperanza Macarena, 26",
    "sg:city":"Madrid",
    "sg:orig_category":"Empresas De Carpinter\u00cda",
    "sg:phone":"+34 917 95 67 71",
    "sg:postcode":"28021",
    "sg:province":"Madrid",
    "wof:name":"Ortiz Nadales Francisco",
    "wof:placetype":"venue"
},
  "geometry": {"coordinates":[-3.6902370453,40.3492774963],"type":"Point"}
}