{
  "type": "Feature",
  "properties": {
    "addr:full":"Calle de Enriqueta Lozano, 13 Granada Granada 18009",
    "addr:housenumber":"13",
    "addr:postcode":"18009",
    "addr:street":"Calle De Enriqueta Lozano",
    "iso:country":"ES",
    "sg:address":"Calle de Enriqueta Lozano, 13",
    "sg:city":"Granada",
    "sg:orig_category":"Contables",
    "sg:phone":"+34 958 22 25 53",
    "sg:postcode":"18009",
    "sg:province":"Granada",
    "wof:name":"Monasterio Alvarez Enrique",
    "wof:placetype":"venue"
},
  "geometry": {"coordinates":[-3.5958650112,37.1718559265],"type":"Point"}
}