{
  "type": "Feature",
  "properties": {
    "addr:full":"Carrer de Violant Hongria R Arago, 33 Barcelona Barcelona 08028",
    "addr:housenumber":"hongria;33",
    "addr:postcode":"08028",
    "addr:street":"Carrer De Violant;R Arago",
    "iso:country":"ES",
    "sg:address":"Carrer de Violant Hongria R Arago, 33",
    "sg:city":"Barcelona",
    "sg:orig_category":"Agencias Y Agentes Comerciales, Representantes",
    "sg:phone":"+34 933 30 57 08",
    "sg:postcode":"08028",
    "sg:province":"Barcelona",
    "wof:name":"Chacon Perez Juan",
    "wof:placetype":"venue"
},
  "geometry": {"coordinates":[2.1281220913,41.3780784607],"type":"Point"}
}