{
  "type": "Feature",
  "properties": {
    "iso:country":"ES",
    "sg:address":"Poli Talluntxe / Talluntze Industrialdea, S/n",
    "sg:city":"Noain",
    "sg:orig_category":"Calefacci\u00d3n Central: Material (fabricaci\u00d3n, Al Por Mayor)",
    "sg:phone":"+34 948 31 20 42",
    "sg:postcode":"31110",
    "sg:province":"Navarra",
    "wof:name":"Laster Industrial S.l.",
    "wof:placetype":"venue"
},
  "geometry": {"coordinates":[-1.6338239908,42.7598800659],"type":"Point"}
}