{
  "type": "Feature",
  "properties": {
    "addr:full":"Avda Partenon, 10 Madrid Madrid 28042",
    "addr:housenumber":"10",
    "addr:postcode":"madrid;28042",
    "addr:street":"Avda Partenon",
    "iso:country":"ES",
    "sg:address":"Avda Partenon, 10",
    "sg:city":"Madrid",
    "sg:orig_category":"Servicios De Telecomunicaciones",
    "sg:phone":"+34 917 21 18 48",
    "sg:postcode":"28042",
    "sg:province":"Madrid",
    "sg:website":"www.auditel.es",
    "wof:name":"Audiovisuales Y Telecomunicacion S.a.",
    "wof:placetype":"venue"
},
  "geometry": {"coordinates":[-3.6166512966,40.4635276794],"type":"Point"}
}