{
  "type": "Feature",
  "properties": {
    "iso:country":"ES",
    "sg:address":"Carr Ciutadans, 6",
    "sg:city":"Girona",
    "sg:orig_category":"Tapicer\u00cdas",
    "sg:phone":"+34 972 20 14 97",
    "sg:postcode":"17004",
    "sg:province":"Girona",
    "wof:name":"Ferrer Rosell Joan",
    "wof:placetype":"venue"
},
  "geometry": {"coordinates":[2.8251440525,41.9834671021],"type":"Point"}
}