{
  "type": "Feature",
  "properties": {
    "addr:full":"Calle de Trabuco, 13 Sevilla Sevilla 41015",
    "addr:housenumber":"13",
    "addr:postcode":"41015",
    "addr:street":"Calle De Trabuco",
    "iso:country":"ES",
    "sg:address":"Calle de Trabuco, 13",
    "sg:city":"Sevilla",
    "sg:orig_category":"Mec\u00c1nico Del Autom\u00d3vil",
    "sg:phone":"+34 954 37 21 83",
    "sg:postcode":"41015",
    "sg:province":"Sevilla",
    "wof:name":"Grima Ruiz Salvador",
    "wof:placetype":"venue"
},
  "geometry": {"coordinates":[-5.9756832123,37.4300422668],"type":"Point"}
}