{
  "type": "Feature",
  "properties": {
    "iso:country":"ES",
    "sg:address":"Cost San Domingos (de), 2",
    "sg:city":"Santiago De Compostela",
    "sg:orig_category":"Museos",
    "sg:phone":"+34 981 58 36 20",
    "sg:postcode":"15704",
    "sg:province":"La Coru\u00f1a",
    "wof:name":"Museo Do Pobo Galego",
    "wof:placetype":"venue"
},
  "geometry": {"coordinates":[-8.5396575928,42.8823928833],"type":"Point"}
}