{
  "type": "Feature",
  "properties": {
    "addr:full":"Urb El Prado, S/n Merida Badajoz 06800",
    "addr:housenumber":"s / n",
    "addr:postcode":"06800",
    "addr:street":"Urb El Prado",
    "iso:country":"ES",
    "sg:address":"Urb El Prado, S/n",
    "sg:city":"Merida",
    "sg:orig_category":"Transportes Por V\u00cdas Navegables",
    "sg:phone":"+34 924 37 17 18",
    "sg:postcode":"06800",
    "sg:province":"Badajoz",
    "wof:name":"Extreme\u00f1a De Camiones S.a.l.",
    "wof:placetype":"venue"
},
  "geometry": {"coordinates":[-6.3501191139,38.9179382324],"type":"Point"}
}