{
  "type": "Feature",
  "properties": {
    "addr:full":"Carr Pau, La, 35 Ciutadella Menorca Islas Baleares 07760",
    "addr:housenumber":"35",
    "addr:postcode":"07760",
    "addr:street":"Carr Pau La",
    "iso:country":"ES",
    "sg:address":"Carr Pau, La, 35",
    "sg:city":"Ciutadella Menorca",
    "sg:orig_category":"Confecci\u00d3n De Zapatos",
    "sg:phone":"+34 971 38 55 51",
    "sg:postcode":"07760",
    "sg:province":"Islas Baleares",
    "wof:name":"Anglada Anglada Jaime",
    "wof:placetype":"venue"
},
  "geometry": {"coordinates":[3.8407480717,39.9978561401],"type":"Point"}
}