{
  "type": "Feature",
  "properties": {
    "iso:country":"ES",
    "sg:address":"Rbla Felip Pedrell (de), 7",
    "sg:city":"Tortosa",
    "sg:orig_category":"Frutas Y Legumbres Frescas (al Por Mayor)",
    "sg:phone":"+34 977 44 08 94",
    "sg:postcode":"43500",
    "sg:province":"Tarragona",
    "wof:name":"Frutas Barbera S.l.",
    "wof:placetype":"venue"
},
  "geometry": {"coordinates":[0.522521019,40.8165397644],"type":"Point"}
}