{
  "type": "Feature",
  "properties": {
    "iso:country":"ES",
    "sg:address":"Pase Alameda, 56",
    "sg:city":"Valencia",
    "sg:orig_category":"Promotores Constructores",
    "sg:phone":"+34 963 30 11 83",
    "sg:postcode":"46023",
    "sg:province":"Valencia",
    "wof:name":"Suelo E Infraestructuras S.l.",
    "wof:placetype":"venue"
},
  "geometry": {"coordinates":[-0.3578000069,39.4637527466],"type":"Point"}
}