{
  "type": "Feature",
  "properties": {
    "iso:country":"ES",
    "sg:address":"Calle de La Paz, 53",
    "sg:city":"Almoradi",
    "sg:orig_category":"Ingenier\u00cda, Centros De Estudios (diversos)",
    "sg:phone":"+34 966 78 16 62",
    "sg:postcode":"03160",
    "sg:province":"Alicante",
    "wof:name":"Garcia Martinez Jose Luis",
    "wof:placetype":"venue"
},
  "geometry": {"coordinates":[-0.7853000164,38.1103096008],"type":"Point"}
}