{
  "type": "Feature",
  "properties": {
    "addr:full":"Praz Constitucion, 33 Cee La Coru\u00f1a 15270",
    "addr:housenumber":"33",
    "addr:postcode":"15270",
    "addr:street":"Constitucion;La",
    "iso:country":"ES",
    "sg:address":"Praz Constitucion, 33",
    "sg:city":"Cee",
    "sg:orig_category":"Peluqueros: De Se\u00d1oras",
    "sg:phone":"+34 981 74 50 96",
    "sg:postcode":"15270",
    "sg:province":"La Coru\u00f1a",
    "wof:name":"Cervi\u00f1o Araujo Susana",
    "wof:placetype":"venue"
},
  "geometry": {"coordinates":[-9.1889944077,42.9551506042],"type":"Point"}
}