{
  "type": "Feature",
  "properties": {
    "addr:full":"Calle de Valverde, 8 Fuente Obejuna C\u00f3rdoba 14290",
    "addr:housenumber":"8",
    "addr:postcode":"14290",
    "addr:street":"Calle De Valverde",
    "iso:country":"ES",
    "sg:address":"Calle de Valverde, 8",
    "sg:city":"Fuente Obejuna",
    "sg:orig_category":"Electrodom\u00c9sticos (al Por Menor)",
    "sg:phone":"+34 957 58 48 23",
    "sg:postcode":"14290",
    "sg:province":"C\u00f3rdoba",
    "wof:name":"Esquina Lujan Rafael",
    "wof:placetype":"venue"
},
  "geometry": {"coordinates":[-5.4179368019,38.2656822205],"type":"Point"}
}