{
  "type": "Feature",
  "properties": {
    "addr:full":"Calle de San Salvador, S/n Plano Huesca 22338",
    "addr:housenumber":"s",
    "addr:postcode":"22338",
    "addr:street":"Calle De San Salvador;/ N",
    "iso:country":"ES",
    "sg:address":"Calle de San Salvador, S/n",
    "sg:city":"Plano",
    "sg:orig_category":"Venta, Instalaci\u00d3n De Cocinas",
    "sg:phone":"+34 974 34 10 06",
    "sg:postcode":"22338",
    "sg:province":"Huesca",
    "wof:name":"Lanau Puyuelo Carmen",
    "wof:placetype":"venue"
},
  "geometry": {"coordinates":[0.1614879966,42.4416465759],"type":"Point"}
}