{
  "type": "Feature",
  "properties": {
    "iso:country":"ES",
    "sg:address":"Ctra Barrio Nuevo, 13",
    "sg:city":"Barrio Nuevo",
    "sg:orig_category":"Alimentaci\u00d3n General (al Por Mayor)",
    "sg:phone":"+34 956 44 55 49",
    "sg:postcode":"11149",
    "sg:province":"C\u00e1diz",
    "wof:name":"Carlos Romero Mora-figueroa S.l.",
    "wof:placetype":"venue"
},
  "geometry": {"coordinates":[-6.0707631111,36.34116745],"type":"Point"}
}