{
  "type": "Feature",
  "properties": {
    "iso:country":"ES",
    "sg:address":"Erdiko Kalea, 52",
    "sg:city":"Arrasate",
    "sg:orig_category":"Peluquer\u00cdas, Peluquer\u00cda Mixta",
    "sg:phone":"+34 943 79 88 32",
    "sg:postcode":"20500",
    "sg:province":"Guip\u00f9zcoa",
    "wof:name":"Sanchez Ropero Victoriana",
    "wof:placetype":"venue"
},
  "geometry": {"coordinates":[-2.4914569855,43.0650291443],"type":"Point"}
}