{
  "type": "Feature",
  "properties": {
    "iso:country":"ES",
    "sg:address":"Calle de Mendez Nu\u00d1ez, 1",
    "sg:city":"Huelva",
    "sg:orig_category":"Mercer\u00cda, Lencer\u00cda (al Por Menor)",
    "sg:phone":"+34 959 25 83 69",
    "sg:postcode":"21001",
    "sg:province":"Huelva",
    "wof:name":"Tebar Calleja Maria De Los Angeles",
    "wof:placetype":"venue"
},
  "geometry": {"coordinates":[-6.9517269135,37.2576217651],"type":"Point"}
}