{
  "type": "Feature",
  "properties": {
    "addr:full":"Calle de Doctor Fleming, S/n Vinaros Castell\u00f3n 12500",
    "addr:housenumber":"s / n",
    "addr:postcode":"12500",
    "addr:street":"Calle De Doctor Fleming",
    "iso:country":"ES",
    "sg:address":"Calle de Doctor Fleming, S/n",
    "sg:city":"Vinaros",
    "sg:orig_category":"Asociaciones Y Clubs Deportivos",
    "sg:phone":"+34 964 45 66 61",
    "sg:postcode":"12500",
    "sg:province":"Castell\u00f3n",
    "wof:name":"De Groot  Frank Willem",
    "wof:placetype":"venue"
},
  "geometry": {"coordinates":[0.4739249945,40.4698104858],"type":"Point"}
}