{
  "type": "Feature",
  "properties": {
    "iso:country":"ES",
    "sg:address":"Calle de Gabriel Y Galan, 98",
    "sg:city":"Montijo",
    "sg:orig_category":"Plomeros",
    "sg:phone":"+34 924 45 58 17",
    "sg:postcode":"06480",
    "sg:province":"Badajoz",
    "wof:name":"Calleja Garcia Diego",
    "wof:placetype":"venue"
},
  "geometry": {"coordinates":[-6.6170239449,38.910736084],"type":"Point"}
}