{
  "type": "Feature",
  "properties": {
    "iso:country":"ES",
    "sg:address":"Pl. Iglesia, 1",
    "sg:city":"Grao Gandia",
    "sg:orig_category":"Telas Y Sedas (al Por Menor)",
    "sg:phone":"+34 962 84 01 07",
    "sg:postcode":"46730",
    "sg:province":"Valencia",
    "wof:name":"Borreda Castao Joaquin",
    "wof:placetype":"venue"
},
  "geometry": {"coordinates":[-0.1664949954,38.9994888306],"type":"Point"}
}