{
  "type": "Feature",
  "properties": {
    "iso:country":"ES",
    "sg:address":"Calle de Umbria, 3",
    "sg:city":"Fuente Obejuna",
    "sg:orig_category":"Asilos De Ancianos. Centros Privados",
    "sg:phone":"+34 957 58 40 80",
    "sg:postcode":"14290",
    "sg:province":"C\u00f3rdoba",
    "wof:name":"Residencia De Ancianos Los Angeles",
    "wof:placetype":"venue"
},
  "geometry": {"coordinates":[-5.418489933,38.2675704956],"type":"Point"}
}