{
  "type": "Feature",
  "properties": {
    "iso:country":"ES",
    "sg:address":"Calle de Santo Domingo, 27",
    "sg:city":"Columbrianos",
    "sg:orig_category":"Ingenier\u00cda, Centros De Estudios (diversos)",
    "sg:phone":"+34 987 40 90 83",
    "sg:postcode":"24490",
    "sg:province":"Le\u00f3n",
    "wof:name":"Anadon Blanco Javier",
    "wof:placetype":"venue"
},
  "geometry": {"coordinates":[-6.6110453606,42.5751266479],"type":"Point"}
}