{
  "type": "Feature",
  "properties": {
    "addr:full":"Calle de Alicante, 11 Arganda Madrid 28500",
    "addr:housenumber":"11",
    "addr:postcode":"28500",
    "addr:street":"Calle De Alicante",
    "iso:country":"ES",
    "sg:address":"Calle de Alicante, 11",
    "sg:city":"Arganda",
    "sg:orig_category":"Chapister\u00cda",
    "sg:phone":"+34 918 75 70 42",
    "sg:postcode":"28500",
    "sg:province":"Madrid",
    "wof:name":"Reparaciones Motor Carvi S.l.",
    "wof:placetype":"venue"
},
  "geometry": {"coordinates":[-3.4587433338,40.307598114],"type":"Point"}
}