{
  "type": "Feature",
  "properties": {
    "addr:full":"Calle de General Ricardos, 132 Madrid Madrid 28019",
    "addr:housenumber":"132",
    "addr:postcode":"28019",
    "addr:street":"Calle De General Ricardos",
    "iso:country":"ES",
    "sg:address":"Calle de General Ricardos, 132",
    "sg:city":"Madrid",
    "sg:orig_category":"Quincaller\u00cda (fabricaci\u00d3n)",
    "sg:phone":"+34 914 72 57 54",
    "sg:postcode":"28019",
    "sg:province":"Madrid",
    "wof:name":"Tecfime S.a.",
    "wof:placetype":"venue"
},
  "geometry": {"coordinates":[-3.7278606892,40.3910751343],"type":"Point"}
}