{
  "type": "Feature",
  "properties": {
    "addr:full":"Calle de Manuel Gullon, 1 Astorga Le\u00f3n 24700",
    "addr:housenumber":"1",
    "addr:postcode":"24700",
    "addr:street":"Calle De Manuel Gullon;Leo\u0301N",
    "iso:country":"ES",
    "sg:address":"Calle de Manuel Gullon, 1",
    "sg:city":"Astorga",
    "sg:orig_category":"Farmacias",
    "sg:phone":"+34 987 60 25 67",
    "sg:postcode":"24700",
    "sg:province":"Le\u00f3n",
    "wof:name":"Quintana Garcia Rosalina",
    "wof:placetype":"venue"
},
  "geometry": {"coordinates":[-6.0542759895,42.454788208],"type":"Point"}
}