{
  "type": "Feature",
  "properties": {
    "iso:country":"ES",
    "sg:address":"Carrer de Fernando Pessoa, 21",
    "sg:city":"Barcelona",
    "sg:orig_category":"Inform\u00c1tica Equipo Y Programas (al Por Mayor)",
    "sg:phone":"+34 932 74 54 00",
    "sg:postcode":"08030",
    "sg:province":"Barcelona",
    "sg:website":"www.printreport.es",
    "wof:name":"Printreport S.l.",
    "wof:placetype":"venue"
},
  "geometry": {"coordinates":[2.1933050156,41.4381790161],"type":"Point"}
}