{
  "type": "Feature",
  "properties": {
    "addr:full":"Ctra Bassella, 20 Solsona Lleida 25280",
    "addr:housenumber":"20",
    "addr:postcode":"25280",
    "addr:street":"Ctra Bassella",
    "iso:country":"ES",
    "sg:address":"Ctra Bassella, 20",
    "sg:city":"Solsona",
    "sg:orig_category":"Inmobiliaria (agencias)",
    "sg:phone":"+34 973 48 36 51",
    "sg:postcode":"25280",
    "sg:province":"Lleida",
    "wof:name":"Ciosa S.l.",
    "wof:placetype":"venue"
},
  "geometry": {"coordinates":[1.5186560154,41.9962844849],"type":"Point"}
}