{
  "type": "Feature",
  "properties": {
    "addr:full":"Calle de Corregidor Nicolas Isidro, 16 Malaga M\u00e1laga 29...",
    "addr:housenumber":"16;29 ...",
    "addr:street":"Calle De Corregidor Nicolas Isidro;Ma\u0301Laga",
    "iso:country":"ES",
    "sg:address":"Calle de Corregidor Nicolas Isidro, 16",
    "sg:city":"Malaga",
    "sg:orig_category":"M\u00c9dicos: An\u00c1lisis Cl\u00cdnicos",
    "sg:phone":"+34 952 04 50 00",
    "sg:postcode":"29...",
    "sg:province":"M\u00e1laga",
    "wof:name":"Clinica El Angel S.a.",
    "wof:placetype":"venue"
},
  "geometry": {"coordinates":[-4.4531049728,36.7151641846],"type":"Point"}
}