{
  "type": "Feature",
  "properties": {
    "iso:country":"ES",
    "sg:address":"Calle de Cardenal Benlloch, 15",
    "sg:city":"Tavernes Blanques",
    "sg:orig_category":"Peluqueros: De Se\u00d1oras",
    "sg:phone":"+34 961 85 20 60",
    "sg:postcode":"46016",
    "sg:province":"Valencia",
    "wof:name":"Garcia Cuellar Francisco Javier",
    "wof:placetype":"venue"
},
  "geometry": {"coordinates":[-0.3647648096,39.5102348328],"type":"Point"}
}