{
  "type": "Feature",
  "properties": {
    "addr:full":"Rua Alfonso Senra, 152 Ordes La Coru\u00f1a 15680",
    "addr:housenumber":"152",
    "addr:postcode":"15680",
    "addr:street":"Rua Alfonso Senra;La Corun\u0303A",
    "iso:country":"ES",
    "sg:address":"Rua Alfonso Senra, 152",
    "sg:city":"Ordes",
    "sg:orig_category":"Contenedores (mercanc\u00cdas)",
    "sg:phone":"+34 981 68 04 27",
    "sg:postcode":"15680",
    "sg:province":"La Coru\u00f1a",
    "wof:name":"Rio Guillin Fernando Del",
    "wof:placetype":"venue"
},
  "geometry": {"coordinates":[-8.408205986,43.0747375488],"type":"Point"}
}