{
  "type": "Feature",
  "properties": {
    "iso:country":"ES",
    "sg:address":"C/ Oscar Espla, 37",
    "sg:city":"Elche",
    "sg:orig_category":"Abogados",
    "sg:phone":"+34 965 46 33 11",
    "sg:postcode":"03201",
    "sg:province":"Alicante",
    "wof:name":"Salazar Vives Julian",
    "wof:placetype":"venue"
},
  "geometry": {"coordinates":[-0.7043600082,38.2687683105],"type":"Point"}
}