{
  "type": "Feature",
  "properties": {
    "iso:country":"ES",
    "sg:address":"Calle de Diego De Velazquez, 33",
    "sg:city":"Velez-malaga",
    "sg:orig_category":"Chapister\u00cda",
    "sg:phone":"+34 952 50 33 00",
    "sg:postcode":"29700",
    "sg:province":"M\u00e1laga",
    "wof:name":"Alonso Perez Leandro",
    "wof:placetype":"venue"
},
  "geometry": {"coordinates":[-4.141140461,36.7639465332],"type":"Point"}
}