{
  "type": "Feature",
  "properties": {
    "iso:country":"ES",
    "sg:address":"Zumacal, 199",
    "sg:city":"Bre\u00f1a Baja",
    "sg:orig_category":"Venta, Montaje De Neum\u00c1ticos",
    "sg:phone":"+34 922 43 43 00",
    "sg:postcode":"38712",
    "sg:province":"Santa Cruz De Tenerife",
    "sg:website":"www.vultesa.com",
    "wof:name":"Vultesa S. L.",
    "wof:placetype":"venue"
},
  "geometry": {"coordinates":[-17.7786369324,28.6571426392],"type":"Point"}
}