{
  "type": "Feature",
  "properties": {
    "iso:country":"ES",
    "sg:address":"Calle de Monasterio De Las Descalzas Reales, 27",
    "sg:city":"Zaragoza",
    "sg:orig_category":"Venta, Alquiler De Plataformas Y Barquillas Elevadoras",
    "sg:phone":"+34 976 47 07 71",
    "sg:postcode":"50014",
    "sg:province":"Zaragoza",
    "wof:name":"Araplat Van, S.l",
    "wof:placetype":"venue"
},
  "geometry": {"coordinates":[-0.8617969751,41.6759757996],"type":"Point"}
}