{
  "type": "Feature",
  "properties": {
    "addr:full":"Carrer de Ferran Casablancas, 106 Sabadell Barcelona 08201",
    "addr:housenumber":"106",
    "addr:postcode":"08201",
    "addr:street":"Carrer De Ferran Casablancas",
    "iso:country":"ES",
    "sg:address":"Carrer de Ferran Casablancas, 106",
    "sg:city":"Sabadell",
    "sg:orig_category":"Inmobiliaria (agencias)",
    "sg:phone":"+34 937 25 11 06",
    "sg:postcode":"08201",
    "sg:province":"Barcelona",
    "sg:website":"www.inmocolonial.com",
    "wof:name":"Inmobiliaria Colonial S.a.",
    "wof:placetype":"venue"
},
  "geometry": {"coordinates":[2.1067380905,41.5416755676],"type":"Point"}
}