{
  "type": "Feature",
  "properties": {
    "addr:full":"Calle de Gil Polo, 8 Valencia Valencia 46003",
    "addr:housenumber":"8",
    "addr:postcode":"46003",
    "addr:street":"Calle De Gil Polo",
    "iso:country":"ES",
    "sg:address":"Calle de Gil Polo, 8",
    "sg:city":"Valencia",
    "sg:orig_category":"Renovaci\u00d3n Inmobiliaria",
    "sg:phone":"+34 963 92 55 40",
    "sg:postcode":"46003",
    "sg:province":"Valencia",
    "wof:name":"Sociedad Anonima Municipal Actuaciones Urbanas De Valencia",
    "wof:placetype":"venue"
},
  "geometry": {"coordinates":[-0.3770110011,39.4781303406],"type":"Point"}
}