{
  "type": "Feature",
  "properties": {
    "addr:full":"Carrer de Gran De Gracia, 36 Barcelona Barcelona 08012",
    "addr:housenumber":"36",
    "addr:postcode":"08012",
    "addr:street":"Carrer De Gran De Gracia",
    "iso:country":"ES",
    "sg:address":"Carrer de Gran De Gracia, 36",
    "sg:city":"Barcelona",
    "sg:orig_category":"Caf\u00c9s, Bares, Cervecer\u00cdas",
    "sg:phone":"+34 934 15 18 24",
    "sg:postcode":"08012",
    "sg:province":"Barcelona",
    "wof:name":"Londistance S.l.",
    "wof:placetype":"venue"
},
  "geometry": {"coordinates":[2.1568629742,41.3988265991],"type":"Point"}
}