{
  "type": "Feature",
  "properties": {
    "iso:country":"ES",
    "sg:address":"Zona S. Marcos, S/n",
    "sg:city":"Errenteria",
    "sg:orig_category":"Asilos De Ancianos. Centros Privados",
    "sg:phone":"+34 943 34 43 46",
    "sg:postcode":"20100",
    "sg:province":"Guip\u00f9zcoa",
    "wof:name":"Gerontologico De Renteria S.l.",
    "wof:placetype":"venue"
},
  "geometry": {"coordinates":[-1.9151209593,43.310295105],"type":"Point"}
}