{
  "type": "Feature",
  "properties": {
    "addr:full":"Calle de Cordoba, 35 Fuengirola M\u00e1laga 29640",
    "addr:housenumber":"35",
    "addr:postcode":"29640",
    "addr:street":"Calle De Cordoba;Ma\u0301Laga",
    "iso:country":"ES",
    "sg:address":"Calle de Cordoba, 35",
    "sg:city":"Fuengirola",
    "sg:orig_category":"Agencias De Viajes",
    "sg:phone":"+34 952 19 70 68",
    "sg:postcode":"29640",
    "sg:province":"M\u00e1laga",
    "sg:website":"www.viajes.elcorteingles.es",
    "wof:name":"Viajes El Corte Ingles S.a.",
    "wof:placetype":"venue"
},
  "geometry": {"coordinates":[-4.6263570786,36.5397720337],"type":"Point"}
}