{
  "type": "Feature",
  "properties": {
    "addr:full":"Carrer de Prudenci, 25 Sabadell Barcelona 08206",
    "addr:housenumber":"25",
    "addr:postcode":"08206",
    "addr:street":"Carrer De Prudenci",
    "iso:country":"ES",
    "sg:address":"Carrer de Prudenci, 25",
    "sg:city":"Sabadell",
    "sg:orig_category":"Cl\u00cdnicas Dentales",
    "sg:phone":"+34 937 23 31 13",
    "sg:postcode":"08206",
    "sg:province":"Barcelona",
    "wof:name":"Centro Medico Can Rull S.l.",
    "wof:placetype":"venue"
},
  "geometry": {"coordinates":[2.0851969719,41.5550117493],"type":"Point"}
}