{
  "type": "Feature",
  "properties": {
    "iso:country":"ES",
    "sg:address":"Calle de Cerradillo, S/n",
    "sg:city":"Illueca",
    "sg:orig_category":"Confecci\u00d3n De Zapatos",
    "sg:phone":"+34 976 82 16 81",
    "sg:postcode":"50250",
    "sg:province":"Zaragoza",
    "wof:name":"Sladan Manufactures S.l.",
    "wof:placetype":"venue"
},
  "geometry": {"coordinates":[-1.6229670048,41.5345230103],"type":"Point"}
}