{
  "type": "Feature",
  "properties": {
    "addr:full":"Calle de San Pedro, 1 Ma\u00f1eru Navarra 31130",
    "addr:housenumber":"1",
    "addr:postcode":"31130",
    "addr:street":"Calle De San Pedro",
    "iso:country":"ES",
    "sg:address":"Calle de San Pedro, 1",
    "sg:city":"Ma\u00f1eru",
    "sg:orig_category":"Iglesia Cat\u00d3lica",
    "sg:phone":"+34 948 34 02 13",
    "sg:postcode":"31130",
    "sg:province":"Navarra",
    "wof:name":"Parroquia De San Pedro",
    "wof:placetype":"venue"
},
  "geometry": {"coordinates":[-1.8624689579,42.6699295044],"type":"Point"}
}