{
  "type": "Feature",
  "properties": {
    "addr:full":"Calle de Vegafria, 51 Valladolid Valladolid 47013",
    "addr:housenumber":"51",
    "addr:postcode":"47013",
    "addr:street":"Calle De Vegafria",
    "iso:country":"ES",
    "sg:address":"Calle de Vegafria, 51",
    "sg:city":"Valladolid",
    "sg:orig_category":"Guarder\u00cdas",
    "sg:phone":"+34 983 27 49 11",
    "sg:postcode":"47013",
    "sg:province":"Valladolid",
    "wof:name":"Escuela Infantil La Delicia C.b.",
    "wof:placetype":"venue"
},
  "geometry": {"coordinates":[-4.7254810333,41.6380767822],"type":"Point"}
}