{
  "type": "Feature",
  "properties": {
    "addr:full":"Pl. Jaume I El Conqueridor, 10 Sedavi Valencia 46910",
    "addr:housenumber":"10",
    "addr:postcode":"46910",
    "addr:street":"Pl.;Conqueridor",
    "iso:country":"ES",
    "sg:address":"Pl. Jaume I El Conqueridor, 10",
    "sg:city":"Sedavi",
    "sg:orig_category":"Abogados",
    "sg:phone":"+34 963 75 08 43",
    "sg:postcode":"46910",
    "sg:province":"Valencia",
    "wof:name":"Ruiz Monrabal Vicente",
    "wof:placetype":"venue"
},
  "geometry": {"coordinates":[-0.3861230016,39.424911499],"type":"Point"}
}