{
  "type": "Feature",
  "properties": {
    "iso:country":"ES",
    "sg:address":"Calle de Larga, S/n",
    "sg:city":"Villamayor",
    "sg:orig_category":"\u00c1rboles Frutales",
    "sg:phone":"+34 923 28 63 25",
    "sg:postcode":"37185",
    "sg:province":"Salamanca",
    "sg:website":"www.viverostenderosl.com",
    "wof:name":"Viveros Tendero S.l.",
    "wof:placetype":"venue"
},
  "geometry": {"coordinates":[-5.6947197914,41.0002937317],"type":"Point"}
}