{
  "type": "Feature",
  "properties": {
    "addr:full":"Carrer de Villarroel, 25 Barcelona Barcelona 08011",
    "addr:housenumber":"25",
    "addr:postcode":"08011",
    "addr:street":"Carrer De Villarroel",
    "iso:country":"ES",
    "sg:address":"Carrer de Villarroel, 25",
    "sg:city":"Barcelona",
    "sg:orig_category":"Artes Gr\u00c1ficas, Artes Pl\u00c1sticas (curso)",
    "sg:phone":"+34 934 24 89 79",
    "sg:postcode":"08011",
    "sg:province":"Barcelona",
    "wof:name":"Graficas Lluis S.l.",
    "wof:placetype":"venue"
},
  "geometry": {"coordinates":[2.1616446972,41.3815155029],"type":"Point"}
}