{
  "type": "Feature",
  "properties": {
    "iso:country":"ES",
    "sg:address":"Carrer de Major, 35",
    "sg:city":"Santa Barbara",
    "sg:orig_category":"Enfermeras: Consultas, Atenci\u00d3n A Domicilio",
    "sg:phone":"+34 977 71 80 89",
    "sg:postcode":"43570",
    "sg:province":"Tarragona",
    "wof:name":"Bertomeu Canalda Margarida",
    "wof:placetype":"venue"
},
  "geometry": {"coordinates":[0.4931690097,40.7146873474],"type":"Point"}
}