{
  "type": "Feature",
  "properties": {
    "iso:country":"ES",
    "sg:address":"Part. Rojals, S/n",
    "sg:city":"Reus",
    "sg:orig_category":"Armer\u00cdas",
    "sg:phone":"+34 977 77 06 54",
    "sg:postcode":"43206",
    "sg:province":"Tarragona",
    "wof:name":"Ballestas Reus S.l.",
    "wof:placetype":"venue"
},
  "geometry": {"coordinates":[1.1039400101,41.1745300293],"type":"Point"}
}