{
  "type": "Feature",
  "properties": {
    "addr:full":"Av Pau, De Sa, 13 Sant Lluis Islas Baleares 07710",
    "addr:housenumber":"13",
    "addr:postcode":"07710",
    "addr:street":"Av Pau De Sa",
    "iso:country":"ES",
    "sg:address":"Av Pau, De Sa, 13",
    "sg:city":"Sant Lluis",
    "sg:orig_category":"Telas Y Sedas (al Por Menor)",
    "sg:phone":"+34 971 15 10 10",
    "sg:postcode":"07710",
    "sg:province":"Islas Baleares",
    "wof:name":"Menorca Textils S.c",
    "wof:placetype":"venue"
},
  "geometry": {"coordinates":[4.2598414421,39.84998703],"type":"Point"}
}