{
  "type": "Feature",
  "properties": {
    "iso:country":"ES",
    "sg:address":"Calle de Miguel Villanueva, 6",
    "sg:city":"Logro\u00f1o",
    "sg:orig_category":"Abogados",
    "sg:phone":"+34 941 24 14 11",
    "sg:postcode":"26001",
    "sg:province":"La Rioja",
    "wof:name":"Sanz Ezquerro Maria Celia",
    "wof:placetype":"venue"
},
  "geometry": {"coordinates":[-2.4455580711,42.4640007019],"type":"Point"}
}