{
  "type": "Feature",
  "properties": {
    "addr:full":"Calle de Sendeja, 5 Bilbao Vizcaya 48007",
    "addr:housenumber":"5",
    "addr:postcode":"48007",
    "addr:street":"Calle De Sendeja",
    "iso:country":"ES",
    "sg:address":"Calle de Sendeja, 5",
    "sg:city":"Bilbao",
    "sg:orig_category":"Bares, Piano",
    "sg:phone":"+34 944 45 09 13",
    "sg:postcode":"48007",
    "sg:province":"Vizcaya",
    "wof:name":"Laser Bilbao S.l.",
    "wof:placetype":"venue"
},
  "geometry": {"coordinates":[-2.922878027,43.2629432678],"type":"Point"}
}