{
  "type": "Feature",
  "properties": {
    "iso:country":"ES",
    "sg:address":"Plaz Iglesia, 1",
    "sg:city":"Alcala De Xivert",
    "sg:orig_category":"Asesor\u00cda De Formaci\u00d3n Y Gesti\u00d3n De Personal",
    "sg:phone":"+34 964 15 01 55",
    "sg:postcode":"12570",
    "sg:province":"Castell\u00f3n",
    "wof:name":"Gabitec Socio Laboral S.l.",
    "wof:placetype":"venue"
},
  "geometry": {"coordinates":[0.2378000021,40.2983894348],"type":"Point"}
}