{
  "type": "Feature",
  "properties": {
    "iso:country":"ES",
    "sg:address":"Calle de Arcos, 50",
    "sg:city":"Jerez De La Frontera",
    "sg:orig_category":"Abogados",
    "sg:phone":"+34 956 34 06 28",
    "sg:postcode":"11401",
    "sg:province":"C\u00e1diz",
    "wof:name":"Soto Garcia Cristina",
    "wof:placetype":"venue"
},
  "geometry": {"coordinates":[-6.1315450668,36.6838569641],"type":"Point"}
}