{
  "type": "Feature",
  "properties": {
    "addr:full":"Calle de Irlanda, 3 Torre-pacheco Murcia 30700",
    "addr:housenumber":"3",
    "addr:postcode":"30700",
    "addr:street":"Calle De Irlanda",
    "iso:country":"ES",
    "sg:address":"Calle de Irlanda, 3",
    "sg:city":"Torre-pacheco",
    "sg:orig_category":"Negocio De Materiales De Construcci\u00d3n",
    "sg:phone":"+34 968 57 72 85",
    "sg:postcode":"30700",
    "sg:province":"Murcia",
    "wof:name":"Proyectos Inmobiliarios Mascali S.l.",
    "wof:placetype":"venue"
},
  "geometry": {"coordinates":[-0.9400151968,37.7379302979],"type":"Point"}
}