{
  "type": "Feature",
  "properties": {
    "iso:country":"ES",
    "sg:address":"Ventorrillo, 6",
    "sg:city":"Bonrepos Mirambell",
    "sg:orig_category":"Pirotecnia (espect\u00c1culos)",
    "sg:phone":"+34 961 85 42 74",
    "sg:postcode":"46131",
    "sg:province":"Valencia",
    "wof:name":"Lopez Chinillach Enrique",
    "wof:placetype":"venue"
},
  "geometry": {"coordinates":[-0.3644300103,39.5170822144],"type":"Point"}
}