{
  "type": "Feature",
  "properties": {
    "addr:full":"Rua Doctor Loureiro Crespo, 29 Pontevedra Pontevedra 36004",
    "addr:housenumber":"29",
    "addr:postcode":"36004",
    "addr:street":"Rua Doctor Loureiro Crespo",
    "iso:country":"ES",
    "sg:address":"Rua Doctor Loureiro Crespo, 29",
    "sg:city":"Pontevedra",
    "sg:orig_category":"Muebles Y Accesorios Para Cocinas Y Cuartos De Ba\u00d1o (al Por Menor)",
    "sg:phone":"+34 986 84 34 69",
    "sg:postcode":"36004",
    "sg:province":"Pontevedra",
    "wof:name":"Epoca Decoracion S.l.",
    "wof:placetype":"venue"
},
  "geometry": {"coordinates":[-8.6348381042,42.428604126],"type":"Point"}
}