{
  "type": "Feature",
  "properties": {
    "iso:country":"ES",
    "sg:address":"Carrer de Florida, 166",
    "sg:city":"Hospitalet Llobregat",
    "sg:orig_category":"Ebanister\u00cda",
    "sg:phone":"+34 934 40 39 94",
    "sg:postcode":"08905",
    "sg:province":"Barcelona",
    "wof:name":"Rodriguez Guzman Enrique",
    "wof:placetype":"venue"
},
  "geometry": {"coordinates":[2.108987093,41.3691825867],"type":"Point"}
}