{
  "type": "Feature",
  "properties": {
    "iso:country":"ES",
    "sg:address":"Carrer de Clemencia Isaura, 5",
    "sg:city":"Sabadell",
    "sg:orig_category":"Prot\u00c9sicos Dentales",
    "sg:phone":"+34 937 12 03 36",
    "sg:postcode":"08204",
    "sg:province":"Barcelona",
    "wof:name":"Laboratorio Dental Ansio S.c.p",
    "wof:placetype":"venue"
},
  "geometry": {"coordinates":[2.1160950661,41.5296821594],"type":"Point"}
}