{
  "type": "Feature",
  "properties": {
    "iso:country":"ES",
    "sg:address":"Carrer de Gran De Gracia, 11",
    "sg:city":"Barcelona",
    "sg:orig_category":"Peluquer\u00cdas, Peluquer\u00cda Mixta",
    "sg:phone":"+34 934 16 18 95",
    "sg:postcode":"08012",
    "sg:province":"Barcelona",
    "wof:name":"Graciacap S.l.",
    "wof:placetype":"venue"
},
  "geometry": {"coordinates":[2.1570920944,41.3980827332],"type":"Point"}
}