{
  "type": "Feature",
  "properties": {
    "iso:country":"ES",
    "sg:address":"Rua Albarran (de), 21",
    "sg:city":"Trabanca Badi\u00e7a",
    "sg:orig_category":"Electricidad: Equipos Industriales, Componentes (fabricaci\u00d3n)",
    "sg:phone":"+34 986 50 27 11",
    "sg:postcode":"36613",
    "sg:province":"Pontevedra",
    "wof:name":"Digamel Arousa S.l.",
    "wof:placetype":"venue"
},
  "geometry": {"coordinates":[-8.7695436478,42.6105308533],"type":"Point"}
}