{
  "type": "Feature",
  "properties": {
    "addr:full":"Calle de Real De La Jara (el), 6 Sevilla Sevilla 41008",
    "addr:housenumber":"6",
    "addr:postcode":"41008",
    "addr:street":"Calle De Real De La Jara El",
    "iso:country":"ES",
    "sg:address":"Calle de Real De La Jara (el), 6",
    "sg:city":"Sevilla",
    "sg:orig_category":"Centros Empresariales",
    "sg:phone":"+34 954 94 57 68",
    "sg:postcode":"41008",
    "sg:province":"Sevilla",
    "wof:name":"Moreno Bautista Mario",
    "wof:placetype":"venue"
},
  "geometry": {"coordinates":[-5.9745001793,37.4095573425],"type":"Point"}
}