{
  "type": "Feature",
  "properties": {
    "iso:country":"ES",
    "sg:address":"Cno Membrio (zona Industrial), S/n",
    "sg:city":"San Vicente Alcantara",
    "sg:orig_category":"Madera Para Construcci\u00d3n E Industria",
    "sg:phone":"+34 924 41 20 50",
    "sg:postcode":"06500",
    "sg:province":"Badajoz",
    "wof:name":"Zurro Miron Y Redondo S.l.",
    "wof:placetype":"venue"
},
  "geometry": {"coordinates":[-6.9702835083,38.8785972595],"type":"Point"}
}