{
  "type": "Feature",
  "properties": {
    "addr:full":"Calle de Velazquez, 27 Rua De Valdeorras Ourense 32350",
    "addr:housenumber":"27",
    "addr:postcode":"32350",
    "addr:street":"Calle De Velazquez;Rua De",
    "iso:country":"ES",
    "sg:address":"Calle de Velazquez, 27",
    "sg:city":"Rua De Valdeorras",
    "sg:orig_category":"Molduras, Junquillos, Listones Y Molduras Perforadas",
    "sg:phone":"+34 988 31 20 84",
    "sg:postcode":"32350",
    "sg:province":"Ourense",
    "wof:name":"Ginzo David Maria Del Carmen",
    "wof:placetype":"venue"
},
  "geometry": {"coordinates":[-7.1205739975,42.392490387],"type":"Point"}
}