{
  "type": "Feature",
  "properties": {
    "iso:country":"ES",
    "sg:address":"Calle de Papatos, 9",
    "sg:city":"Fuentesauco",
    "sg:orig_category":"Bibliotecas, Mediatecas",
    "sg:phone":"+34 980 60 09 20",
    "sg:postcode":"49400",
    "sg:province":"Zamora",
    "wof:name":"Ayuntamiento De Fuentesauco",
    "wof:placetype":"venue"
},
  "geometry": {"coordinates":[-5.4882678986,41.2406005859],"type":"Point"}
}