{
  "type": "Feature",
  "properties": {
    "iso:country":"ES",
    "sg:address":"Ctra Granada, S/n",
    "sg:city":"Jaen",
    "sg:orig_category":"Pompas F\u00danebres, Inhumaciones Y Cremaciones",
    "sg:phone":"+34 953 23 93 50",
    "sg:postcode":"23001",
    "sg:province":"Ja\u00e9n",
    "wof:name":"Benigno Gomez Estevez S.l.",
    "wof:placetype":"venue"
},
  "geometry": {"coordinates":[-3.7864840031,37.7691955566],"type":"Point"}
}