{
  "type": "Feature",
  "properties": {
    "iso:country":"ES",
    "sg:address":"Avda Noria (de La), 8",
    "sg:city":"Molina Segura",
    "sg:orig_category":"Formaci\u00d3n Continuada (variada)",
    "sg:phone":"+34 968 64 50 00",
    "sg:postcode":"30500",
    "sg:province":"Murcia",
    "wof:name":"Fernandez Sanchez Ana Maria",
    "wof:placetype":"venue"
},
  "geometry": {"coordinates":[-1.2141499519,38.0550994873],"type":"Point"}
}