{
  "type": "Feature",
  "properties": {
    "addr:full":"Avda Reyes Catolicos De Los, 24 Fraga Huesca 22520",
    "addr:housenumber":"24",
    "addr:postcode":"22520",
    "addr:street":"Avda Reyes Catolicos De Los",
    "iso:country":"ES",
    "sg:address":"Avda Reyes Catolicos De Los, 24",
    "sg:city":"Fraga",
    "sg:orig_category":"Ropa Para Beb\u00c9s Y Ni\u00d1os (confecci\u00d3n, Al Por Mayor)",
    "sg:phone":"+34 974 45 37 36",
    "sg:postcode":"22520",
    "sg:province":"Huesca",
    "wof:name":"Vila Casas Maria",
    "wof:placetype":"venue"
},
  "geometry": {"coordinates":[0.3479360044,41.5213813782],"type":"Point"}
}