{
  "type": "Feature",
  "properties": {
    "iso:country":"ES",
    "sg:address":"Carr Mare De Deu De Montiel (de La), 34",
    "sg:city":"Lliria",
    "sg:orig_category":"Pensiones Familiares",
    "sg:phone":"+34 962 79 37 35",
    "sg:postcode":"46160",
    "sg:province":"Valencia",
    "wof:name":"Cifre Garcia Josefina",
    "wof:placetype":"venue"
},
  "geometry": {"coordinates":[-0.5918740034,39.6224899292],"type":"Point"}
}