{
  "type": "Feature",
  "properties": {
    "addr:full":"Calle de Capitan Haya, 9 Madrid Madrid 28020",
    "addr:housenumber":"9",
    "addr:postcode":"madrid;28020",
    "addr:street":"Calle De Capitan Haya",
    "iso:country":"ES",
    "sg:address":"Calle de Capitan Haya, 9",
    "sg:city":"Madrid",
    "sg:orig_category":"Agencias De Viajes",
    "sg:phone":"+34 915 56 12 43",
    "sg:postcode":"28020",
    "sg:province":"Madrid",
    "sg:website":"www.viajestejedor.es",
    "wof:name":"Viajes Tejedor S. A.",
    "wof:placetype":"venue"
},
  "geometry": {"coordinates":[-3.6924910545,40.455871582],"type":"Point"}
}