{
  "type": "Feature",
  "properties": {
    "iso:country":"ES",
    "sg:address":"Carrer de Iradier, 16",
    "sg:city":"Barcelona",
    "sg:classifiers":[
        {
            "category":"Professional",
            "subcategory":"Research",
            "type":"Services"
        }
    ],
    "sg:phone":"+34 934 18 56 82",
    "sg:postcode":"08017",
    "sg:province":"Barcelona",
    "sg:tags":[
        "mercado",
        "de",
        "estudios"
    ],
    "wof:name":"C B Tres Consultores S.l.",
    "wof:placetype":"venue"
},
  "geometry": {"coordinates":[2.1257379055,41.404384613],"type":"Point"}
}