{
  "type": "Feature",
  "properties": {
    "iso:country":"ES",
    "sg:address":"Calle de Jose Montalvo, 2",
    "sg:city":"Madrid",
    "sg:orig_category":"Panader\u00cdas, Panader\u00cdas",
    "sg:phone":"+34 914 71 08 44",
    "sg:postcode":"28019",
    "sg:province":"Madrid",
    "wof:name":"Arenas Mora Jose",
    "wof:placetype":"venue"
},
  "geometry": {"coordinates":[-3.734005928,40.3979911804],"type":"Point"}
}