{
  "type": "Feature",
  "properties": {
    "iso:country":"ES",
    "sg:address":"Pla\u00c7 Porta Del Sol, 9",
    "sg:city":"Ca\u00d1ada",
    "sg:orig_category":"Inmobiliaria (agencias)",
    "sg:phone":"+34 961 32 06 07",
    "sg:postcode":"46182",
    "sg:province":"Valencia",
    "sg:website":"www.bluedec.com",
    "wof:name":"Iba\u00f1ez Alca\u00f1iz Salvador",
    "wof:placetype":"venue"
},
  "geometry": {"coordinates":[-0.8098580837,38.675239563],"type":"Point"}
}