{
  "type": "Feature",
  "properties": {
    "addr:full":"Carrer de Joan Gamper, 8 Barcelona Barcelona 08014",
    "addr:housenumber":"8",
    "addr:postcode":"08014",
    "addr:street":"Carrer De Joan Gamper",
    "iso:country":"ES",
    "sg:address":"Carrer de Joan Gamper, 8",
    "sg:city":"Barcelona",
    "sg:orig_category":"Fabricaci\u00d3n De Papeles Especiales Y Para Usos T\u00c9cnicos",
    "sg:phone":"+34 934 30 14 63",
    "sg:postcode":"08014",
    "sg:province":"Barcelona",
    "wof:name":"Tecnoform S.c.c.l.",
    "wof:placetype":"venue"
},
  "geometry": {"coordinates":[2.1344630718,41.3868980408],"type":"Point"}
}