{
  "type": "Feature",
  "properties": {
    "iso:country":"ES",
    "sg:address":"Calle de Maiquez, 10",
    "sg:city":"Madrid",
    "sg:orig_category":"Peluqueros: De Se\u00d1oras",
    "sg:phone":"+34 915 04 48 47",
    "sg:postcode":"28009",
    "sg:province":"Madrid",
    "wof:name":"Imagen Y Perfil Estilistas",
    "wof:placetype":"venue"
},
  "geometry": {"coordinates":[-3.6729640961,40.42212677],"type":"Point"}
}