{
  "type": "Feature",
  "properties": {
    "addr:full":"Emilio Luque, 40 La Orotava Santa Cruz De Tenerife 38300",
    "addr:housenumber":"40",
    "addr:postcode":"38300",
    "addr:street":"Luque",
    "iso:country":"ES",
    "sg:address":"Emilio Luque, 40",
    "sg:city":"La Orotava",
    "sg:orig_category":"Procuradores",
    "sg:phone":"+34 922 32 20 44",
    "sg:postcode":"38300",
    "sg:province":"Santa Cruz De Tenerife",
    "wof:name":"Gonzalez Martin Juan Pedro",
    "wof:placetype":"venue"
},
  "geometry": {"coordinates":[-16.5189990997,28.3903846741],"type":"Point"}
}