{
  "type": "Feature",
  "properties": {
    "iso:country":"ES",
    "sg:address":"Calle de Irun, 23",
    "sg:city":"Madrid",
    "sg:orig_category":"Intercambios, Trueques",
    "sg:phone":"+34 915 59 55 52",
    "sg:postcode":"28008",
    "sg:province":"Madrid",
    "wof:name":"Telecafe S.l.",
    "wof:placetype":"venue"
},
  "geometry": {"coordinates":[-3.7185878754,40.4227714539],"type":"Point"}
}