{
  "type": "Feature",
  "properties": {
    "iso:country":"ES",
    "sg:address":"Calle de Caridad, 1",
    "sg:city":"Valladolid",
    "sg:orig_category":"Abogados",
    "sg:phone":"+34 983 37 92 54",
    "sg:postcode":"47001",
    "sg:province":"Valladolid",
    "wof:name":"Arroyo Gurdiel Javier",
    "wof:placetype":"venue"
},
  "geometry": {"coordinates":[-4.730304718,41.6516494751],"type":"Point"}
}