{
  "type": "Feature",
  "properties": {
    "iso:country":"ES",
    "sg:address":"Calle de Melchor Fernandez Almagro, 46",
    "sg:city":"Madrid",
    "sg:orig_category":"Reposter\u00cdas",
    "sg:phone":"+34 917 38 32 59",
    "sg:postcode":"28029",
    "sg:province":"Madrid",
    "wof:name":"Cheng  Jiamnin",
    "wof:placetype":"venue"
},
  "geometry": {"coordinates":[-3.7041909695,40.4768943787],"type":"Point"}
}