{
  "type": "Feature",
  "properties": {
    "iso:country":"ES",
    "sg:address":"Carrer de Rafael De Casanova, 44",
    "sg:city":"Molins Rei",
    "sg:orig_category":"Confecci\u00d3n De Ropa Interior",
    "sg:phone":"+34 936 80 11 99",
    "sg:postcode":"08750",
    "sg:province":"Barcelona",
    "wof:name":"Bassons Industrias De La Confeccion S.a.",
    "wof:placetype":"venue"
},
  "geometry": {"coordinates":[2.0167319775,41.4120635986],"type":"Point"}
}