{
  "type": "Feature",
  "properties": {
    "iso:country":"ES",
    "sg:address":"Carrer de Girona, 13",
    "sg:city":"Barbera Valles",
    "sg:orig_category":"Alimentaci\u00d3n General (al Por Menor)",
    "sg:phone":"+34 937 29 27 01",
    "sg:postcode":"08210",
    "sg:province":"Barcelona",
    "wof:name":"Boada Borrell Francisco",
    "wof:placetype":"venue"
},
  "geometry": {"coordinates":[2.1265099049,41.5098228455],"type":"Point"}
}