{
  "type": "Feature",
  "properties": {
    "addr:full":"Calle de Juan De Juanes, 7 Mislata Valencia 46920",
    "addr:housenumber":"7",
    "addr:postcode":"46920",
    "addr:street":"Calle De Juan De Juanes",
    "iso:country":"ES",
    "sg:address":"Calle de Juan De Juanes, 7",
    "sg:city":"Mislata",
    "sg:orig_category":"Plomeros",
    "sg:phone":"+34 963 79 45 07",
    "sg:postcode":"46920",
    "sg:province":"Valencia",
    "wof:name":"Escribano Parre\u00f1o Asuncion",
    "wof:placetype":"venue"
},
  "geometry": {"coordinates":[-0.4157679975,39.4706687927],"type":"Point"}
}