{
  "type": "Feature",
  "properties": {
    "iso:country":"ES",
    "sg:address":"Avda Ategorrieta De, 81",
    "sg:city":"Donostia-san Sebastian",
    "sg:orig_category":"Plomeros",
    "sg:phone":"+34 943 27 52 47",
    "sg:postcode":"20013",
    "sg:province":"Guip\u00f9zcoa",
    "wof:name":"Caballero Santana Jesus",
    "wof:placetype":"venue"
},
  "geometry": {"coordinates":[-1.9598679543,43.3218002319],"type":"Point"}
}