{
  "type": "Feature",
  "properties": {
    "addr:full":"Calle de Auso Y Monzo, 1 Alacant Alicante 03006",
    "addr:housenumber":"1",
    "addr:postcode":"03006",
    "addr:street":"Calle De Auso Y Monzo",
    "iso:country":"ES",
    "sg:address":"Calle de Auso Y Monzo, 1",
    "sg:city":"Alacant",
    "sg:orig_category":"Electricidad, Electr\u00d3nica: Suministros (al Por Menor)",
    "sg:phone":"+34 965 10 64 71",
    "sg:postcode":"03006",
    "sg:province":"Alicante",
    "wof:name":"Rodriguez Y Agullo S.l.",
    "wof:placetype":"venue"
},
  "geometry": {"coordinates":[-0.5037757158,38.3462753296],"type":"Point"}
}