{
  "type": "Feature",
  "properties": {
    "iso:country":"ES",
    "sg:address":"Carr Puigverd, 21",
    "sg:city":"Lleida",
    "sg:orig_category":"Fabricaci\u00d3n De Juguetes Autom\u00c1ticos",
    "sg:phone":"+34 973 21 20 63",
    "sg:postcode":"25001",
    "sg:province":"Lleida",
    "wof:name":"Servimatic Recreativos S.l.",
    "wof:placetype":"venue"
},
  "geometry": {"coordinates":[0.6438750029,41.6020431519],"type":"Point"}
}