{
  "type": "Feature",
  "properties": {
    "addr:full":"Rua San Pedro, 21 Lugo Lugo 27001",
    "addr:housenumber":"21",
    "addr:postcode":"27001",
    "addr:street":"Rua San Pedro",
    "iso:country":"ES",
    "sg:address":"Rua San Pedro, 21",
    "sg:city":"Lugo",
    "sg:orig_category":"Textil",
    "sg:phone":"+34 982 22 62 06",
    "sg:postcode":"27001",
    "sg:province":"Lugo",
    "wof:name":"Lopez Barreiro Ramon",
    "wof:placetype":"venue"
},
  "geometry": {"coordinates":[-7.5535130501,43.0104408264],"type":"Point"}
}