{
  "type": "Feature",
  "properties": {
    "addr:full":"Avda Ciudad De Barcelona, 152 Madrid Madrid 28007",
    "addr:housenumber":"152",
    "addr:postcode":"28007",
    "addr:street":"Avda Ciudad De Barcelona",
    "iso:country":"ES",
    "sg:address":"Avda Ciudad De Barcelona, 152",
    "sg:city":"Madrid",
    "sg:orig_category":"Alimentaci\u00d3n General (al Por Menor)",
    "sg:phone":"+34 915 02 05 94",
    "sg:postcode":"28007",
    "sg:province":"Madrid",
    "sg:website":"www.montepinoseleccion.es",
    "wof:name":"Montepinos S A F S.l.",
    "wof:placetype":"venue"
},
  "geometry": {"coordinates":[-3.6778581142,40.4026908875],"type":"Point"}
}