{
  "type": "Feature",
  "properties": {
    "iso:country":"ES",
    "sg:address":"Plaz Nuestra Se\u00d1ora De La Palma, 3",
    "sg:city":"Algeciras",
    "sg:orig_category":"Promotores Constructores",
    "sg:phone":"+34 956 63 02 51",
    "sg:postcode":"11201",
    "sg:province":"C\u00e1diz",
    "wof:name":"Comunidad De Propietarios Edificio Torroja",
    "wof:placetype":"venue"
},
  "geometry": {"coordinates":[-5.4449062347,36.1290397644],"type":"Point"}
}