{
  "type": "Feature",
  "properties": {
    "addr:full":"Calle de Alberto Duce, 9 Zaragoza Zaragoza 50015",
    "addr:housenumber":"9",
    "addr:postcode":"50015",
    "addr:street":"Calle De Alberto Duce",
    "iso:country":"ES",
    "sg:address":"Calle de Alberto Duce, 9",
    "sg:city":"Zaragoza",
    "sg:orig_category":"Peluquer\u00cdas, Peluquer\u00cda Mixta",
    "sg:phone":"+34 976 52 70 34",
    "sg:postcode":"50015",
    "sg:province":"Zaragoza",
    "wof:name":"Haro Martinez Juan Miguel",
    "wof:placetype":"venue"
},
  "geometry": {"coordinates":[-0.8872575164,41.6722793579],"type":"Point"}
}