{
  "type": "Feature",
  "properties": {
    "iso:country":"ES",
    "sg:address":"Alcazares, S/n",
    "sg:city":"Santiago Ribera",
    "sg:orig_category":"Aguas (distribuci\u00d3n, Servicios)",
    "sg:phone":"+34 968 57 21 82",
    "sg:postcode":"30720",
    "sg:province":"Murcia",
    "wof:name":"Aquagest Region De Murcia",
    "wof:placetype":"venue"
},
  "geometry": {"coordinates":[-0.8182777762,37.7742118835],"type":"Point"}
}