{
  "type": "Feature",
  "properties": {
    "iso:country":"ES",
    "sg:address":"Avda La Rioja, 12",
    "sg:city":"Haro",
    "sg:orig_category":"Cajas De Ahorro",
    "sg:phone":"+34 941 31 21 27",
    "sg:postcode":"26200",
    "sg:province":"La Rioja",
    "sg:website":"www.cajarioja.es",
    "wof:name":"Caja De Ahorros De La Rioja",
    "wof:placetype":"venue"
},
  "geometry": {"coordinates":[-2.8522911072,42.5739974976],"type":"Point"}
}