{
  "type": "Feature",
  "properties": {
    "iso:country":"ES",
    "sg:address":"Calle de Cefeo, 50",
    "sg:city":"Alacant",
    "sg:orig_category":"Asociaciones Y Clubs Deportivos",
    "sg:phone":"+34 965 28 03 39",
    "sg:postcode":"03006",
    "sg:province":"Alicante",
    "wof:name":"Promociones Gym Alicante S.l.",
    "wof:placetype":"venue"
},
  "geometry": {"coordinates":[-0.5123767853,38.3473892212],"type":"Point"}
}