{
  "type": "Feature",
  "properties": {
    "addr:full":"Martin Soler(pol Ind Saladas), 17 Torrellano Alicante 03320",
    "addr:housenumber":"17",
    "addr:postcode":"03320",
    "addr:street":"Pol Ind Saladas",
    "iso:country":"ES",
    "sg:address":"Martin Soler(pol Ind Saladas), 17",
    "sg:city":"Torrellano",
    "sg:orig_category":"Comercio De Piezas De Recambio Y De Accesorios De Veh\u00cdculos, Veh\u00cdculos Industriales",
    "sg:phone":"+34 965 68 12 55",
    "sg:postcode":"03320",
    "sg:province":"Alicante",
    "wof:name":"Talleres Accemotor S.l.",
    "wof:placetype":"venue"
},
  "geometry": {"coordinates":[-0.5883839726,38.2929649353],"type":"Point"}
}