{
  "type": "Feature",
  "properties": {
    "addr:full":"Av Fco Salzillo(pol Ind Oeste), 22 S. Gines Murcia 30169",
    "addr:housenumber":"22",
    "addr:postcode":"30169",
    "addr:street":"Av Fco Salzillo Pol Ind Oeste;S. Gines",
    "iso:country":"ES",
    "sg:address":"Av Fco Salzillo(pol Ind Oeste), 22",
    "sg:city":"S. Gines",
    "sg:orig_category":"Cajas Para Embalar",
    "sg:phone":"+34 968 82 68 57",
    "sg:postcode":"30169",
    "sg:province":"Murcia",
    "wof:name":"Cajamar",
    "wof:placetype":"venue"
},
  "geometry": {"coordinates":[-1.177366972,37.9589958191],"type":"Point"}
}