{
  "type": "Feature",
  "properties": {
    "addr:full":"Pol. Ind. Villaverde, S/n Ricla Zaragoza 50270",
    "addr:housenumber":"s / n",
    "addr:postcode":"50270",
    "addr:street":"Ricla",
    "iso:country":"ES",
    "sg:address":"Pol. Ind. Villaverde, S/n",
    "sg:city":"Ricla",
    "sg:orig_category":"Productos Fitosanitarios (negocio, Aplicaci\u00d3n)",
    "sg:phone":"+34 976 81 86 41",
    "sg:postcode":"50270",
    "sg:province":"Zaragoza",
    "wof:name":"Fitosanitarios Plo S.l.",
    "wof:placetype":"venue"
},
  "geometry": {"coordinates":[-1.4035539627,41.503528595],"type":"Point"}
}