{
  "type": "Feature",
  "properties": {
    "addr:full":"Avda Reyes Catolicos, 76 Cuenca Cuenca 16003",
    "addr:housenumber":"76",
    "addr:postcode":"16003",
    "addr:street":"Avda Reyes Catolicos",
    "iso:country":"ES",
    "sg:address":"Avda Reyes Catolicos, 76",
    "sg:city":"Cuenca",
    "sg:orig_category":"Distribuci\u00d3n De Petr\u00d3leo Y Derivados",
    "sg:phone":"+34 969 23 13 67",
    "sg:postcode":"16003",
    "sg:province":"Cuenca",
    "wof:name":"Las Flores S.a.",
    "wof:placetype":"venue"
},
  "geometry": {"coordinates":[-2.1388549805,40.0585594177],"type":"Point"}
}