{
  "type": "Feature",
  "properties": {
    "addr:full":"Calle de Nuestra Se\u00d1ora De Yerga, 1 Autol La Rioja 26560",
    "addr:housenumber":"1",
    "addr:postcode":"26560",
    "addr:street":"Calle De Nuestra Sen\u0303Ora;Yerga;Rioja",
    "iso:country":"ES",
    "sg:address":"Calle de Nuestra Se\u00d1ora De Yerga, 1",
    "sg:city":"Autol",
    "sg:orig_category":"Bisuter\u00cda, Joyer\u00cda, Relojer\u00cda (al Por Menor)",
    "sg:phone":"+34 941 39 05 01",
    "sg:postcode":"26560",
    "sg:province":"La Rioja",
    "wof:name":"Joyeria Turmalina S.l.",
    "wof:placetype":"venue"
},
  "geometry": {"coordinates":[-2.0053379536,42.2137184143],"type":"Point"}
}