{
  "type": "Feature",
  "properties": {
    "iso:country":"ES",
    "sg:address":"Calle de Zacatin, 1",
    "sg:city":"Loja",
    "sg:orig_category":"Ense\u00d1anza: Profesiones Art\u00cdsticas",
    "sg:phone":"+34 958 32 13 58",
    "sg:postcode":"18300",
    "sg:province":"Granada",
    "wof:name":"Martinez Maroto Juan Gerardo",
    "wof:placetype":"venue"
},
  "geometry": {"coordinates":[-4.1503190994,37.1663551331],"type":"Point"}
}