{
  "type": "Feature",
  "properties": {
    "iso:country":"ES",
    "sg:address":"Av Sant Julia, 240",
    "sg:city":"Granollers",
    "sg:orig_category":"Pintura, Barniz, Productos Asimilables (fabricaci\u00d3n, Al Por Mayor)",
    "sg:phone":"+34 938 40 25 43",
    "sg:postcode":"08403",
    "sg:province":"Barcelona",
    "wof:name":"Pintados R.m. S.l.",
    "wof:placetype":"venue"
},
  "geometry": {"coordinates":[2.2728719711,41.5773124695],"type":"Point"}
}