{
  "type": "Feature",
  "properties": {
    "iso:country":"ES",
    "sg:address":"Avda Libertad, S/n",
    "sg:city":"Dos Hermanas",
    "sg:orig_category":"Empresas De Hormig\u00d3n, Hormig\u00d3n Armado Y Pretensado",
    "sg:phone":"+34 955 66 44 64",
    "sg:postcode":"41700",
    "sg:province":"Sevilla",
    "wof:name":"Prefabricados Mesa S.a.",
    "wof:placetype":"venue"
},
  "geometry": {"coordinates":[-5.9494991302,37.3009414673],"type":"Point"}
}