{
  "type": "Feature",
  "properties": {
    "addr:full":"Avda Ejercito Espa\u00d1ol (del), 42 Barbastro Huesca 22300",
    "addr:housenumber":"42",
    "addr:postcode":"22300",
    "addr:street":"Avda Ejercito Espan\u0303Ol Del",
    "iso:country":"ES",
    "sg:address":"Avda Ejercito Espa\u00d1ol (del), 42",
    "sg:city":"Barbastro",
    "sg:orig_category":"Tintes (fabricaci\u00d3n, Al Por Mayor)",
    "sg:phone":"+34 974 31 14 47",
    "sg:postcode":"22300",
    "sg:province":"Huesca",
    "wof:name":"Cabrerizo Muzas Jose Maria",
    "wof:placetype":"venue"
},
  "geometry": {"coordinates":[0.1167960018,42.0355796814],"type":"Point"}
}