{
  "type": "Feature",
  "properties": {
    "addr:full":"Carrer de Roger De Flor, 250 Barcelona Barcelona 08025",
    "addr:housenumber":"250",
    "addr:postcode":"08025",
    "addr:street":"Carrer De Roger De Flor",
    "iso:country":"ES",
    "sg:address":"Carrer de Roger De Flor, 250",
    "sg:city":"Barcelona",
    "sg:orig_category":"Molduras, Junquillos, Listones Y Molduras Perforadas",
    "sg:phone":"+34 934 57 98 66",
    "sg:postcode":"08025",
    "sg:province":"Barcelona",
    "wof:name":"Gordon Gonzalez Jose Manuel",
    "wof:placetype":"venue"
},
  "geometry": {"coordinates":[2.1685330868,41.402141571],"type":"Point"}
}