{
  "type": "Feature",
  "properties": {
    "iso:country":"ES",
    "sg:address":"Ctra Sta Creu Calafell-barcelona, 132",
    "sg:city":"Segur Calafell",
    "sg:orig_category":"Inmobiliaria (agencias)",
    "sg:phone":"+34 977 16 33 37",
    "sg:postcode":"43882",
    "sg:province":"Tarragona",
    "wof:name":"Zafra Zafra Encarnacion",
    "wof:placetype":"venue"
},
  "geometry": {"coordinates":[1.6087783575,41.1939125061],"type":"Point"}
}