{
  "type": "Feature",
  "properties": {
    "addr:full":"Calle de Mesones, 15 Azuaga Badajoz 06920",
    "addr:housenumber":"15",
    "addr:postcode":"06920",
    "addr:street":"Calle De Mesones",
    "iso:country":"ES",
    "sg:address":"Calle de Mesones, 15",
    "sg:city":"Azuaga",
    "sg:orig_category":"Abogados",
    "sg:phone":"+34 924 89 21 34",
    "sg:postcode":"06920",
    "sg:province":"Badajoz",
    "wof:name":"Morillo Montero De Espinosa Victor Manuel",
    "wof:placetype":"venue"
},
  "geometry": {"coordinates":[-5.6714630127,38.2567329407],"type":"Point"}
}