{
  "type": "Feature",
  "properties": {
    "iso:country":"ES",
    "sg:address":"Calle de Charco, 17",
    "sg:city":"Rota",
    "sg:orig_category":"Laboratorios Y Cl\u00cdnicas Veterinarias",
    "sg:phone":"+34 956 81 20 75",
    "sg:postcode":"11520",
    "sg:province":"C\u00e1diz",
    "wof:name":"Ma\u00f1a Zafra Antonio",
    "wof:placetype":"venue"
},
  "geometry": {"coordinates":[-6.3591532707,36.6190986633],"type":"Point"}
}