{
  "type": "Feature",
  "properties": {
    "iso:country":"ES",
    "sg:address":"Calle de Nu\u00d1ez De Balboa, 28",
    "sg:city":"Madrid",
    "sg:orig_category":"Publicidad (soportes Y Gesti\u00d3n)",
    "sg:phone":"+34 915 77 78 11",
    "sg:postcode":"28001",
    "sg:province":"Madrid",
    "wof:name":"Regalex S.l.",
    "wof:placetype":"venue"
},
  "geometry": {"coordinates":[-3.6825859547,40.4253349304],"type":"Point"}
}