{
  "type": "Feature",
  "properties": {
    "addr:full":"Avda Miguel De Cervantes, 7 Ecija Sevilla 41400",
    "addr:housenumber":"7",
    "addr:postcode":"41400",
    "addr:street":"Avda Miguel De Cervantes",
    "iso:country":"ES",
    "sg:address":"Avda Miguel De Cervantes, 7",
    "sg:city":"Ecija",
    "sg:orig_category":"Electrodom\u00c9sticos (al Por Menor)",
    "sg:phone":"+34 954 83 09 72",
    "sg:postcode":"41400",
    "sg:province":"Sevilla",
    "wof:name":"Serrano Zurita Rafael",
    "wof:placetype":"venue"
},
  "geometry": {"coordinates":[-5.0790200233,37.5405387878],"type":"Point"}
}