{
  "type": "Feature",
  "properties": {
    "addr:full":"Pol Ind Plazaola Mzana A, S/n Aizoain Navarra 31195",
    "addr:housenumber":"s",
    "addr:postcode":"31195",
    "addr:street":"/ N",
    "iso:country":"ES",
    "sg:address":"Pol Ind Plazaola Mzana A, S/n",
    "sg:city":"Aizoain",
    "sg:orig_category":"Frutas Y Legumbres Frescas (al Por Mayor)",
    "sg:phone":"+34 948 35 05 36",
    "sg:postcode":"31195",
    "sg:province":"Navarra",
    "wof:name":"Legumbres Merino S.l.",
    "wof:placetype":"venue"
},
  "geometry": {"coordinates":[-1.6867979765,42.8470611572],"type":"Point"}
}