{
  "type": "Feature",
  "properties": {
    "addr:full":"Calle de Jose M Blecua (miralbueno), 3 Zaragoza Zaragoza 50011",
    "addr:housenumber":"3",
    "addr:postcode":"50011",
    "addr:street":"Calle De Jose M Blecua Miralbueno",
    "iso:country":"ES",
    "sg:address":"Calle de Jose M Blecua (miralbueno), 3",
    "sg:city":"Zaragoza",
    "sg:orig_category":"Centros Empresariales",
    "sg:phone":"+34 976 34 48 53",
    "sg:postcode":"50011",
    "sg:province":"Zaragoza",
    "wof:name":"Escolano Bravo Jesus",
    "wof:placetype":"venue"
},
  "geometry": {"coordinates":[-0.9308069944,41.6579780579],"type":"Point"}
}