{
  "type": "Feature",
  "properties": {
    "addr:full":"Calle de Etruria, 7 Madrid Madrid 28022",
    "addr:housenumber":"7",
    "addr:postcode":"madrid;28022",
    "addr:street":"Calle De Etruria",
    "iso:country":"ES",
    "sg:address":"Calle de Etruria, 7",
    "sg:city":"Madrid",
    "sg:orig_category":"Quincaller\u00cda (al Por Menor)",
    "sg:phone":"+34 917 41 71 48",
    "sg:postcode":"28022",
    "sg:province":"Madrid",
    "wof:name":"Santiago Rodriguez Argimiro",
    "wof:placetype":"venue"
},
  "geometry": {"coordinates":[-3.6118609905,40.4359970093],"type":"Point"}
}