{
  "type": "Feature",
  "properties": {
    "addr:full":"Cmno Arana Bidea, 30 Berango Vizcaya 48640",
    "addr:housenumber":"30",
    "addr:postcode":"48640",
    "addr:street":"Cmno Arana Bidea",
    "iso:country":"ES",
    "sg:address":"Cmno Arana Bidea, 30",
    "sg:city":"Berango",
    "sg:orig_category":"Productos Qu\u00cdmicos (fabricaci\u00d3n, Al Por Mayor)",
    "sg:phone":"+34 946 68 12 11",
    "sg:postcode":"48640",
    "sg:province":"Vizcaya",
    "wof:name":"Arachem S. A.",
    "wof:placetype":"venue"
},
  "geometry": {"coordinates":[-2.9825558662,43.353427887],"type":"Point"}
}