{
  "type": "Feature",
  "properties": {
    "addr:full":"Carrer de Sort (de La), 10 Torredembarra Tarragona 43830",
    "addr:housenumber":"10",
    "addr:postcode":"43830",
    "addr:street":"Carrer De Sort De La",
    "iso:country":"ES",
    "sg:address":"Carrer de Sort (de La), 10",
    "sg:city":"Torredembarra",
    "sg:orig_category":"Administradores De Bienes Y Delegados De Comunidades De Propietarios",
    "sg:phone":"+34 977 64 10 66",
    "sg:postcode":"43830",
    "sg:province":"Tarragona",
    "wof:name":"Administracion Y Serveis La Sort C.b.",
    "wof:placetype":"venue"
},
  "geometry": {"coordinates":[1.3975356817,41.1442527771],"type":"Point"}
}