{
  "type": "Feature",
  "properties": {
    "addr:full":"Calle de Olivo, 1 Don Benito Badajoz 06400",
    "addr:housenumber":"1",
    "addr:postcode":"06400",
    "addr:street":"Calle De Olivo",
    "iso:country":"ES",
    "sg:address":"Calle de Olivo, 1",
    "sg:city":"Don Benito",
    "sg:orig_category":"Promotores Constructores",
    "sg:phone":"+34 924 81 28 06",
    "sg:postcode":"06400",
    "sg:province":"Badajoz",
    "wof:name":"Casado Quintero Jose Luis",
    "wof:placetype":"venue"
},
  "geometry": {"coordinates":[-5.8695821762,38.9555549622],"type":"Point"}
}