{
  "type": "Feature",
  "properties": {
    "addr:full":"Carr Joan Baget, 11 Lleida Lleida 25003",
    "addr:housenumber":"11",
    "addr:postcode":"25003",
    "addr:street":"Carr Joan Baget",
    "iso:country":"ES",
    "sg:address":"Carr Joan Baget, 11",
    "sg:city":"Lleida",
    "sg:orig_category":"Mec\u00c1nico Del Autom\u00d3vil",
    "sg:phone":"+34 973 26 67 51",
    "sg:postcode":"25003",
    "sg:province":"Lleida",
    "wof:name":"Autoservei Garatge Bueria S.l.",
    "wof:placetype":"venue"
},
  "geometry": {"coordinates":[0.6201187968,41.6161804199],"type":"Point"}
}