{
  "type": "Feature",
  "properties": {
    "iso:country":"ES",
    "sg:address":"Carrer de Cavallers (dels), 4",
    "sg:city":"Tarragona",
    "sg:classifiers":[
        {
            "category":"Arts & Performance",
            "subcategory":"Art Gallery",
            "type":"Entertainment"
        }
    ],
    "sg:phone":"+34 977 22 40 98",
    "sg:postcode":"43003",
    "sg:province":"Tarragona",
    "sg:tags":[
        "arte",
        "de",
        "galer\u00cdas"
    ],
    "sg:website":"www.forvm-chantalgrande.com",
    "wof:name":"Balsells Sole David",
    "wof:placetype":"venue"
},
  "geometry": {"coordinates":[1.2564760447,41.1174430847],"type":"Point"}
}