{
  "type": "Feature",
  "properties": {
    "addr:full":"Calle de Marceliano Santa Maria, 6 Madrid Madrid 28036",
    "addr:housenumber":"6",
    "addr:postcode":"28036",
    "addr:street":"Calle De Marceliano Santa Maria",
    "iso:country":"ES",
    "sg:address":"Calle de Marceliano Santa Maria, 6",
    "sg:city":"Madrid",
    "sg:orig_category":"Caf\u00c9s, Bares, Cervecer\u00cdas",
    "sg:phone":"+34 915 64 48 81",
    "sg:postcode":"28036",
    "sg:province":"Madrid",
    "wof:name":"Nova Gonzalez Vicente",
    "wof:placetype":"venue"
},
  "geometry": {"coordinates":[-3.6882390976,40.4509315491],"type":"Point"}
}