{
  "type": "Feature",
  "properties": {
    "iso:country":"ES",
    "sg:address":"Calle de Cerrajon, 1",
    "sg:city":"Alcorcon",
    "sg:orig_category":"Aparcamientos (infraestructuras, Accesorios)",
    "sg:phone":"+34 916 44 00 02",
    "sg:postcode":"28921",
    "sg:province":"Madrid",
    "wof:name":"A P C C Sociedad Cooperativa Limitada",
    "wof:placetype":"venue"
},
  "geometry": {"coordinates":[-3.8312089443,40.3437423706],"type":"Point"}
}