{
  "type": "Feature",
  "properties": {
    "addr:full":"Ctra Venta Vieja, 53 Santa Maria Aguila Almer\u00eda 04710",
    "addr:housenumber":"53",
    "addr:postcode":"04710",
    "addr:street":"Ctra Venta Vieja;Almeri\u0301A",
    "iso:country":"ES",
    "sg:address":"Ctra Venta Vieja, 53",
    "sg:city":"Santa Maria Aguila",
    "sg:orig_category":"Arquitectos",
    "sg:phone":"+34 950 58 22 31",
    "sg:postcode":"04710",
    "sg:province":"Almer\u00eda",
    "wof:name":"Alferez Maldonado Juan Jose",
    "wof:placetype":"venue"
},
  "geometry": {"coordinates":[-2.7804851532,36.7805290222],"type":"Point"}
}