{
  "type": "Feature",
  "properties": {
    "iso:country":"ES",
    "sg:address":"Avda Republica Argentina, 24",
    "sg:city":"Le\u00f3n",
    "sg:orig_category":"Agencias De Viajes",
    "sg:phone":"+34 987 21 06 99",
    "sg:postcode":"24004",
    "sg:province":"Le\u00f3n",
    "wof:name":"Perez Gonzalez Maria Benilde",
    "wof:placetype":"venue"
},
  "geometry": {"coordinates":[-5.5743308067,42.5953292847],"type":"Point"}
}