{
  "type": "Feature",
  "properties": {
    "iso:country":"ES",
    "sg:address":"Calle de Garachico, S/n",
    "sg:city":"Villafranqueza - Palamo",
    "sg:orig_category":"Cerrajer\u00cda, Ferrallista",
    "sg:phone":"+34 965 18 18 48",
    "sg:postcode":"03112",
    "sg:province":"Alicante",
    "wof:name":"Morena Prades Luis De La",
    "wof:placetype":"venue"
},
  "geometry": {"coordinates":[-0.4690259993,38.4094772339],"type":"Point"}
}