{
  "type": "Feature",
  "properties": {
    "addr:full":"Calle de Jovellanos, 12 Sevilla Sevilla 41004",
    "addr:housenumber":"12",
    "addr:postcode":"41004",
    "addr:street":"Calle De Jovellanos",
    "iso:country":"ES",
    "sg:address":"Calle de Jovellanos, 12",
    "sg:city":"Sevilla",
    "sg:orig_category":"Asesor\u00cda Sobre Comunicaci\u00d3n De Empresas",
    "sg:phone":"+34 954 22 82 09",
    "sg:postcode":"41004",
    "sg:province":"Sevilla",
    "wof:name":"Investigacion Desarrollo Y Asesoramiento S.l.",
    "wof:placetype":"venue"
},
  "geometry": {"coordinates":[-5.9949388504,37.3900642395],"type":"Point"}
}