{
  "type": "Feature",
  "properties": {
    "addr:full":"Calle de Camarin, 5 Ciudad Real Ciudad Real 13002",
    "addr:housenumber":"5",
    "addr:postcode":"13002",
    "addr:street":"Calle De Camarin",
    "iso:country":"ES",
    "sg:address":"Calle de Camarin, 5",
    "sg:city":"Ciudad Real",
    "sg:orig_category":"Abogados",
    "sg:phone":"+34 926 23 20 66",
    "sg:postcode":"13002",
    "sg:province":"Ciudad Real",
    "wof:name":"Garcia-minguillan Molina Jesus",
    "wof:placetype":"venue"
},
  "geometry": {"coordinates":[-3.9304656982,38.9872665405],"type":"Point"}
}