{
  "type": "Feature",
  "properties": {
    "addr:full":"Luga Campotejar Alta, S/n Campotejar Alta Murcia 30627",
    "addr:housenumber":"s / n",
    "addr:postcode":"30627",
    "iso:country":"ES",
    "sg:address":"Luga Campotejar Alta, S/n",
    "sg:city":"Campotejar Alta",
    "sg:orig_category":"Comerciantes Al Por Mayor De Vinos, Licores Y Alcoholes",
    "sg:phone":"+34 968 61 62 05",
    "sg:postcode":"30627",
    "sg:province":"Murcia",
    "wof:name":"Pastor Perez Rafael",
    "wof:placetype":"venue"
},
  "geometry": {"coordinates":[-1.1555140018,38.1296195984],"type":"Point"}
}