{
  "type": "Feature",
  "properties": {
    "addr:full":"Calle de Hilera, 11 Malaga M\u00e1laga 29007",
    "addr:housenumber":"11",
    "addr:postcode":"29007",
    "addr:street":"Calle De Hilera;Ma\u0301Laga",
    "iso:country":"ES",
    "sg:address":"Calle de Hilera, 11",
    "sg:city":"Malaga",
    "sg:orig_category":"Muebles, Minoristas",
    "sg:phone":"+34 952 28 16 64",
    "sg:postcode":"29007",
    "sg:province":"M\u00e1laga",
    "sg:website":"www.treku.es",
    "wof:name":"Obogar S.l.",
    "wof:placetype":"venue"
},
  "geometry": {"coordinates":[-4.4331221581,36.719329834],"type":"Point"}
}