{
  "type": "Feature",
  "properties": {
    "iso:country":"ES",
    "sg:address":"Ctra Barcelona, 44",
    "sg:city":"Centre Urba",
    "sg:orig_category":"Agencias Y Agentes Comerciales, Representantes",
    "sg:phone":"+34 972 70 18 68",
    "sg:postcode":"17500",
    "sg:province":"Girona",
    "wof:name":"Colomer Boixes Arnau",
    "wof:placetype":"venue"
},
  "geometry": {"coordinates":[2.1959049702,42.1965866089],"type":"Point"}
}