{
  "type": "Feature",
  "properties": {
    "addr:full":"Grup Arriberri, 6 Donostia-san Sebastian Guip\u00f9zcoa 20017",
    "addr:housenumber":"6",
    "addr:postcode":"20017",
    "addr:street":"Arriberri",
    "iso:country":"ES",
    "sg:address":"Grup Arriberri, 6",
    "sg:city":"Donostia-san Sebastian",
    "sg:orig_category":"Restaurantes",
    "sg:phone":"+34 943 35 79 51",
    "sg:postcode":"20017",
    "sg:province":"Guip\u00f9zcoa",
    "wof:name":"Agustin Herrero Germana",
    "wof:placetype":"venue"
},
  "geometry": {"coordinates":[-1.9285449982,43.3174858093],"type":"Point"}
}