{
  "type": "Feature",
  "properties": {
    "iso:country":"ES",
    "sg:address":"Calle de Mayor (garrapinillos), 13",
    "sg:city":"Garrapinillos",
    "sg:orig_category":"Peluqueros: De Se\u00d1oras",
    "sg:phone":"+34 976 78 11 38",
    "sg:postcode":"50190",
    "sg:province":"Zaragoza",
    "wof:name":"Hermanas Crespo Castillo S.c.",
    "wof:placetype":"venue"
},
  "geometry": {"coordinates":[-1.0247139931,41.6755256653],"type":"Point"}
}