{
  "type": "Feature",
  "properties": {
    "iso:country":"ES",
    "sg:address":"Calle de San Miguel, 13",
    "sg:city":"Arevalo",
    "sg:orig_category":"Art\u00cdculos De Regalo (al Por Menor)",
    "sg:phone":"+34 920 30 37 76",
    "sg:postcode":"05200",
    "sg:province":"\u00c1vila",
    "wof:name":"Roysandis S.l.",
    "wof:placetype":"venue"
},
  "geometry": {"coordinates":[-4.7221398354,41.0661888123],"type":"Point"}
}