{
  "type": "Feature",
  "properties": {
    "iso:country":"ES",
    "sg:address":"Calle de Eskalantegi, 9",
    "sg:city":"Pasai Antxo",
    "sg:orig_category":"Molduras, Junquillos, Listones Y Molduras Perforadas",
    "sg:phone":"+34 943 52 56 96",
    "sg:postcode":"20110",
    "sg:province":"Guip\u00f9zcoa",
    "wof:name":"Arrieta Maiza Maria Pilar",
    "wof:placetype":"venue"
},
  "geometry": {"coordinates":[-1.9191697836,43.318813324],"type":"Point"}
}