{
  "type": "Feature",
  "properties": {
    "iso:country":"ES",
    "sg:address":"Calle de General Vara De Rey, 31",
    "sg:city":"Logro\u00f1o",
    "sg:orig_category":"Arquitectos",
    "sg:phone":"+34 941 24 35 54",
    "sg:postcode":"26002",
    "sg:province":"La Rioja",
    "wof:name":"Barrio Gomez Jose Miguel",
    "wof:placetype":"venue"
},
  "geometry": {"coordinates":[-2.4466691017,42.4585189819],"type":"Point"}
}