{
  "type": "Feature",
  "properties": {
    "iso:country":"ES",
    "sg:address":"Carrer de Baronessa De Malda, 49",
    "sg:city":"Esplugues Llobregat",
    "sg:orig_category":"Materias Pl\u00c1sticas: Productos De Consumo Masivo (fabricaci\u00d3n, Al Por Mayor)",
    "sg:phone":"+34 933 71 51 10",
    "sg:postcode":"08950",
    "sg:province":"Barcelona",
    "wof:name":"Bolsas Cafi S.l.",
    "wof:placetype":"venue"
},
  "geometry": {"coordinates":[2.0796260834,41.3721923828],"type":"Point"}
}