{
  "type": "Feature",
  "properties": {
    "addr:full":"Calle de Buenaventura I\u00d1iguez, 4 Sang\u00fcesa Navarra 31400",
    "addr:housenumber":"4",
    "addr:postcode":"31400",
    "addr:street":"Calle De Buenaventura In\u0303Iguez",
    "iso:country":"ES",
    "sg:address":"Calle de Buenaventura I\u00d1iguez, 4",
    "sg:city":"Sang\u00fcesa",
    "sg:orig_category":"Agencias De Viajes",
    "sg:phone":"+34 948 87 12 78",
    "sg:postcode":"31400",
    "sg:province":"Navarra",
    "wof:name":"Mui\u00f1os Ripalda Lidia",
    "wof:placetype":"venue"
},
  "geometry": {"coordinates":[-1.281440258,42.5762138367],"type":"Point"}
}