{
  "type": "Feature",
  "properties": {
    "iso:country":"ES",
    "sg:address":"La Luna, 1",
    "sg:city":"Carpio Tajo",
    "sg:orig_category":"Cerrajer\u00cda, Ferrallista",
    "sg:phone":"+34 925 75 71 17",
    "sg:postcode":"45533",
    "sg:province":"Toledo",
    "wof:name":"Rodriguez Vidal Albino",
    "wof:placetype":"venue"
},
  "geometry": {"coordinates":[-4.4551930428,39.8891029358],"type":"Point"}
}