{
  "type": "Feature",
  "properties": {
    "iso:country":"ES",
    "sg:address":"Carrer de Rossello, 40",
    "sg:city":"Barcelona",
    "sg:orig_category":"Reposter\u00cdas",
    "sg:phone":"+34 934 30 10 19",
    "sg:postcode":"08029",
    "sg:province":"Barcelona",
    "wof:name":"Camps Aibar S.l.",
    "wof:placetype":"venue"
},
  "geometry": {"coordinates":[2.1468861103,41.3852424622],"type":"Point"}
}