{
  "type": "Feature",
  "properties": {
    "addr:full":"Carr Canonigo Cebrian, 1 Xativa Valencia 46800",
    "addr:housenumber":"1",
    "addr:postcode":"46800",
    "addr:street":"Carr Canonigo Cebrian",
    "iso:country":"ES",
    "sg:address":"Carr Canonigo Cebrian, 1",
    "sg:city":"Xativa",
    "sg:orig_category":"Art\u00cdculos Funerarios (al Por Menor)",
    "sg:phone":"+34 962 28 22 86",
    "sg:postcode":"46800",
    "sg:province":"Valencia",
    "wof:name":"Funeraria Cerda S.l.",
    "wof:placetype":"venue"
},
  "geometry": {"coordinates":[-0.5228790045,38.9883613586],"type":"Point"}
}