{
  "type": "Feature",
  "properties": {
    "iso:country":"ES",
    "sg:address":"Calle de Olla, 34",
    "sg:city":"Constantina",
    "sg:orig_category":"Contenedores (mercanc\u00cdas)",
    "sg:phone":"+34 955 88 13 14",
    "sg:postcode":"41450",
    "sg:province":"Sevilla",
    "wof:name":"Blanco Gonzalez Manuel",
    "wof:placetype":"venue"
},
  "geometry": {"coordinates":[-5.6204800606,37.8777351379],"type":"Point"}
}