{
  "type": "Feature",
  "properties": {
    "iso:country":"ES",
    "sg:address":"Calle de Fuencarral, 43",
    "sg:city":"Madrid",
    "sg:orig_category":"Psic\u00d3logos",
    "sg:phone":"+34 915 23 05 89",
    "sg:postcode":"28004",
    "sg:province":"Madrid",
    "wof:name":"Serrano Ribeiro Manuel Antonio",
    "wof:placetype":"venue"
},
  "geometry": {"coordinates":[-3.700824976,40.4229621887],"type":"Point"}
}