{
  "type": "Feature",
  "properties": {
    "addr:full":"Carr Mallorca, 33 Ciutadella Menorca Islas Baleares 07760",
    "addr:housenumber":"33",
    "addr:postcode":"07760",
    "addr:street":"Carr Mallorca",
    "iso:country":"ES",
    "sg:address":"Carr Mallorca, 33",
    "sg:city":"Ciutadella Menorca",
    "sg:orig_category":"Cajas De Ahorro",
    "sg:phone":"+34 971 48 22 68",
    "sg:postcode":"07760",
    "sg:province":"Islas Baleares",
    "wof:name":"Caixa D'estalvis I Pensions De Barcelona",
    "wof:placetype":"venue"
},
  "geometry": {"coordinates":[3.8416149616,40.0027542114],"type":"Point"}
}