{
  "type": "Feature",
  "properties": {
    "addr:full":"Calle de Benito Gutierrez, 25 Madrid Madrid 28008",
    "addr:housenumber":"25",
    "addr:postcode":"madrid;28008",
    "addr:street":"Calle De Benito Gutierrez",
    "iso:country":"ES",
    "sg:address":"Calle de Benito Gutierrez, 25",
    "sg:city":"Madrid",
    "sg:orig_category":"Farmacias",
    "sg:phone":"+34 915 44 02 19",
    "sg:postcode":"28008",
    "sg:province":"Madrid",
    "wof:name":"Palmaz Arenas Victoria",
    "wof:placetype":"venue"
},
  "geometry": {"coordinates":[-3.7197730541,40.4313774109],"type":"Point"}
}