{
  "type": "Feature",
  "properties": {
    "iso:country":"ES",
    "sg:address":"Calle de Jose M. Salaberria, 7",
    "sg:city":"Donostia-san Sebastian",
    "sg:orig_category":"Ingeniero",
    "sg:phone":"+34 943 46 27 95",
    "sg:postcode":"20010",
    "sg:province":"Guip\u00f9zcoa",
    "wof:name":"Mujica Larreta Salvador",
    "wof:placetype":"venue"
},
  "geometry": {"coordinates":[-1.9811010361,43.3086166382],"type":"Point"}
}