{
  "type": "Feature",
  "properties": {
    "addr:full":"Poligono Industrial, 3 Agoitz Navarra 31430",
    "addr:housenumber":"3",
    "addr:postcode":"31430",
    "addr:street":"Industrial",
    "iso:country":"ES",
    "sg:address":"Poligono Industrial, 3",
    "sg:city":"Agoitz",
    "sg:orig_category":"Material Y Equipo Para Panader\u00cdas Y Pasteler\u00cdas",
    "sg:phone":"+34 948 33 41 52",
    "sg:postcode":"31430",
    "sg:province":"Navarra",
    "wof:name":"Ogidiko S.l.",
    "wof:placetype":"venue"
},
  "geometry": {"coordinates":[-1.3753689528,42.7824897766],"type":"Point"}
}