{
  "type": "Feature",
  "properties": {
    "addr:full":"Calle de Cervera, Km. 0001,8 Talavera Reina Toledo 45600",
    "addr:postcode":"45600",
    "addr:street":"Calle De Cervera Km. 0001,8",
    "iso:country":"ES",
    "sg:address":"Calle de Cervera, Km. 0001,8",
    "sg:city":"Talavera Reina",
    "sg:orig_category":"Electricidad: Equipos Industriales, Componentes (fabricaci\u00d3n)",
    "sg:phone":"+34 925 81 82 49",
    "sg:postcode":"45600",
    "sg:province":"Toledo",
    "sg:website":"www.paginasamarillas.es",
    "wof:name":"Suministros Electricos Morales S.a.",
    "wof:placetype":"venue"
},
  "geometry": {"coordinates":[-4.8321590424,39.9661254883],"type":"Point"}
}