{
  "type": "Feature",
  "properties": {
    "addr:full":"Avda Sierra Pambley, 56 Villablino Le\u00f3n 24100",
    "addr:housenumber":"56",
    "addr:postcode":"24100",
    "addr:street":"Avda Sierra Pambley",
    "iso:country":"ES",
    "sg:address":"Avda Sierra Pambley, 56",
    "sg:city":"Villablino",
    "sg:orig_category":"Venta, Montaje De Neum\u00c1ticos",
    "sg:phone":"+34 987 47 16 37",
    "sg:postcode":"24100",
    "sg:province":"Le\u00f3n",
    "wof:name":"Menendez Perez Alipio",
    "wof:placetype":"venue"
},
  "geometry": {"coordinates":[-6.3163490295,42.9398651123],"type":"Point"}
}