{
  "type": "Feature",
  "properties": {
    "addr:full":"Av La Pobla De Vallbona, 39 Eliana Valencia 46183",
    "addr:housenumber":"39",
    "addr:postcode":"46183",
    "addr:street":"Av La Pobla De Vallbona",
    "iso:country":"ES",
    "sg:address":"Av La Pobla De Vallbona, 39",
    "sg:city":"Eliana",
    "sg:orig_category":"Agencias Y Agentes Comerciales, Representantes",
    "sg:phone":"+34 962 74 00 91",
    "sg:postcode":"46183",
    "sg:province":"Valencia",
    "wof:name":"Dudson Ltd.sl.",
    "wof:placetype":"venue"
},
  "geometry": {"coordinates":[-0.5293890238,39.5677680969],"type":"Point"}
}