{
  "type": "Feature",
  "properties": {
    "addr:full":"Calle de Galveston, 9 Marbella M\u00e1laga 29600",
    "addr:housenumber":"9",
    "addr:postcode":"29600",
    "addr:street":"Calle De Galveston;Ma\u0301Laga",
    "iso:country":"ES",
    "sg:address":"Calle de Galveston, 9",
    "sg:city":"Marbella",
    "sg:orig_category":"Papeler\u00cdas, Librer\u00cdas",
    "sg:phone":"+34 952 86 05 54",
    "sg:postcode":"29600",
    "sg:province":"M\u00e1laga",
    "wof:name":"Papeleria Los Arcos S.l.",
    "wof:placetype":"venue"
},
  "geometry": {"coordinates":[-4.8809080124,36.5145301819],"type":"Point"}
}