{
  "type": "Feature",
  "properties": {
    "addr:full":"Carrer de Pla Del Cos, S/n Navarcles Barcelona 08270",
    "addr:housenumber":"s / n",
    "addr:postcode":"08270",
    "addr:street":"Carrer De Pla Del Cos",
    "iso:country":"ES",
    "sg:address":"Carrer de Pla Del Cos, S/n",
    "sg:city":"Navarcles",
    "sg:orig_category":"Muebles",
    "sg:phone":"+34 938 31 06 75",
    "sg:postcode":"08270",
    "sg:province":"Barcelona",
    "wof:name":"Fusteria Industrial Vilaro S.l",
    "wof:placetype":"venue"
},
  "geometry": {"coordinates":[1.9140900373,41.7533760071],"type":"Point"}
}