{
  "type": "Feature",
  "properties": {
    "iso:country":"ES",
    "sg:address":"Calle de Luis Lopez Oses, 22",
    "sg:city":"Arenas -areeta",
    "sg:orig_category":"Estancos",
    "sg:phone":"+34 944 63 91 72",
    "sg:postcode":"48930",
    "sg:province":"Vizcaya",
    "wof:name":"Anguisola Rojo Maria Elena",
    "wof:placetype":"venue"
},
  "geometry": {"coordinates":[-3.0061910152,43.3305397034],"type":"Point"}
}