{
  "type": "Feature",
  "properties": {
    "iso:country":"ES",
    "sg:address":"C/ Jorge Juan, 41",
    "sg:city":"Elche",
    "sg:orig_category":"M\u00c9dicos: Estomatolog\u00cda",
    "sg:phone":"+34 966 66 08 61",
    "sg:postcode":"03201",
    "sg:province":"Alicante",
    "wof:name":"Paredes Osado Manuel",
    "wof:placetype":"venue"
},
  "geometry": {"coordinates":[-0.7059509754,38.2679100037],"type":"Point"}
}