{
  "type": "Feature",
  "properties": {
    "addr:full":"Calle de Oviedo, 14 Fuenlabrada Madrid 28942",
    "addr:housenumber":"14",
    "addr:postcode":"28942",
    "addr:street":"Calle De Oviedo",
    "iso:country":"ES",
    "sg:address":"Calle de Oviedo, 14",
    "sg:city":"Fuenlabrada",
    "sg:orig_category":"Radiocomunicaciones, Telefon\u00cda M\u00d3vil, Radiomensajer\u00cda: Servicios, Comercializaci\u00d3n",
    "sg:phone":"+34 916 08 04 72",
    "sg:postcode":"28942",
    "sg:province":"Madrid",
    "wof:name":"Idemudia  Prince Nelson",
    "wof:placetype":"venue"
},
  "geometry": {"coordinates":[-3.8077719212,40.2987136841],"type":"Point"}
}