{
  "type": "Feature",
  "properties": {
    "addr:full":"Piago, S/n Piago Lugo 27154",
    "addr:postcode":"27154",
    "addr:street":"Piago S / N",
    "iso:country":"ES",
    "sg:address":"Piago, S/n",
    "sg:city":"Piago",
    "sg:orig_category":"Empresas De Electricidad En General",
    "sg:phone":"+34 982 39 36 22",
    "sg:postcode":"27154",
    "sg:province":"Lugo",
    "wof:name":"Enel Viesgo Servicios S.l.",
    "wof:placetype":"venue"
},
  "geometry": {"coordinates":[-7.5895152092,43.069480896],"type":"Point"}
}