{
  "type": "Feature",
  "properties": {
    "iso:country":"ES",
    "sg:address":"Calle de Adriano, 39",
    "sg:city":"Sevilla",
    "sg:orig_category":"Agencias Y Agentes Comerciales, Representantes",
    "sg:phone":"+34 954 21 46 90",
    "sg:postcode":"41001",
    "sg:province":"Sevilla",
    "wof:name":"Cadenas Cousinou Carlos",
    "wof:placetype":"venue"
},
  "geometry": {"coordinates":[-5.9996595383,37.3866500854],"type":"Point"}
}