{
  "type": "Feature",
  "properties": {
    "iso:country":"ES",
    "sg:address":"Avda Galicia, 103",
    "sg:city":"Vegadeo",
    "sg:orig_category":"Forjas Y Altos Hornos",
    "sg:phone":"+34 985 63 41 53",
    "sg:postcode":"33770",
    "sg:province":"Asturias",
    "wof:name":"Fernandez Suarez Jesus",
    "wof:placetype":"venue"
},
  "geometry": {"coordinates":[-7.0518341064,43.4643669128],"type":"Point"}
}