{
  "type": "Feature",
  "properties": {
    "addr:full":"Av Illice, 65 Torrellano Alicante 03320",
    "addr:housenumber":"65",
    "addr:postcode":"03320",
    "addr:street":"Av Illice",
    "iso:country":"ES",
    "sg:address":"Av Illice, 65",
    "sg:city":"Torrellano",
    "sg:orig_category":"Inform\u00c1tica (estudios, Servicios, Asesor\u00cda, Formaci\u00d3n)",
    "sg:phone":"+34 965 68 29 50",
    "sg:postcode":"03320",
    "sg:province":"Alicante",
    "sg:website":"www.globalnetcb.com",
    "wof:name":"Glob@lnet Cb",
    "wof:placetype":"venue"
},
  "geometry": {"coordinates":[-0.585909009,38.2940063477],"type":"Point"}
}