{
  "type": "Feature",
  "properties": {
    "addr:full":"Urb Cuesta Del Aguila, S/n Cruz Del Portillo Toledo 45593",
    "addr:postcode":"45593",
    "addr:street":"Urb Cuesta Del Aguila S / N Cruz Del Portillo",
    "iso:country":"ES",
    "sg:address":"Urb Cuesta Del Aguila, S/n",
    "sg:city":"Cruz Del Portillo",
    "sg:orig_category":"Caf\u00c9s, Bares, Cervecer\u00cdas",
    "sg:phone":"+34 925 49 34 65",
    "sg:postcode":"45593",
    "sg:province":"Toledo",
    "wof:name":"Garcia Delgado Juan",
    "wof:placetype":"venue"
},
  "geometry": {"coordinates":[-4.0194129944,39.9406776428],"type":"Point"}
}