{
  "type": "Feature",
  "properties": {
    "iso:country":"ES",
    "sg:address":"Carrer de Bonsoms, 3",
    "sg:city":"Barcelona",
    "sg:orig_category":"Fabricaci\u00d3n De Mobiliario Met\u00c1lico",
    "sg:phone":"+34 934 40 26 21",
    "sg:postcode":"08028",
    "sg:province":"Barcelona",
    "wof:name":"Plame S. A.",
    "wof:placetype":"venue"
},
  "geometry": {"coordinates":[2.1275589466,41.37241745],"type":"Point"}
}