{
  "type": "Feature",
  "properties": {
    "iso:country":"ES",
    "sg:address":"Calle de Instituto, 3",
    "sg:city":"Soria",
    "sg:orig_category":"Estilistas Y Estudios De Estilo De Corte Y Confecci\u00d3n",
    "sg:phone":"+34 975 21 16 12",
    "sg:postcode":"42002",
    "sg:province":"Soria",
    "wof:name":"Martinez Sanchez Antonio",
    "wof:placetype":"venue"
},
  "geometry": {"coordinates":[-2.466490984,41.764415741],"type":"Point"}
}