{
  "type": "Feature",
  "properties": {
    "iso:country":"ES",
    "sg:address":"Calle de Nestor De La Torre, 12",
    "sg:city":"Palmas De Gran Canaria",
    "sg:orig_category":"Casas De Reposo Y Convalecencia",
    "sg:phone":"+34 928 24 42 94",
    "sg:postcode":"35006",
    "sg:province":"Las Palmas",
    "wof:name":"Orden Hospitalaria De San Juan De Dios",
    "wof:placetype":"venue"
},
  "geometry": {"coordinates":[-15.4306926727,28.1338996887],"type":"Point"}
}