{
  "type": "Feature",
  "properties": {
    "addr:full":"Calle de Cronista Rey Diaz, 1 Cordoba C\u00f3rdoba 14006",
    "addr:housenumber":"1",
    "addr:postcode":"14006",
    "addr:street":"Calle De Cronista Rey Diaz;Co\u0301Rdoba",
    "iso:country":"ES",
    "sg:address":"Calle de Cronista Rey Diaz, 1",
    "sg:city":"Cordoba",
    "sg:orig_category":"Producci\u00d3n, Distribuci\u00d3n De Electricidad",
    "sg:phone":"+34 957 40 22 17",
    "sg:postcode":"14006",
    "sg:province":"C\u00f3rdoba",
    "wof:name":"Sanchez Ysbert S.l.",
    "wof:placetype":"venue"
},
  "geometry": {"coordinates":[-4.781914711,37.8942146301],"type":"Point"}
}