{
  "type": "Feature",
  "properties": {
    "addr:full":"Avda Chapi, 6 Elda Alicante 03600",
    "addr:housenumber":"6",
    "addr:postcode":"03600",
    "addr:street":"Avda Chapi",
    "iso:country":"ES",
    "sg:address":"Avda Chapi, 6",
    "sg:city":"Elda",
    "sg:orig_category":"Cajas De Ahorro",
    "sg:phone":"+34 965 39 58 10",
    "sg:postcode":"03600",
    "sg:province":"Alicante",
    "sg:website":"www.cajamurcia.es",
    "wof:name":"Caja De Ahorros De Murcia",
    "wof:placetype":"venue"
},
  "geometry": {"coordinates":[-0.7925639749,38.4725494385],"type":"Point"}
}