{
  "type": "Feature",
  "properties": {
    "addr:full":"Carretera De Pradoluengo, S/n Villasur Herreros Burgos 09199",
    "addr:housenumber":"s / n",
    "addr:postcode":"09199",
    "addr:street":"Carretera De Pradoluengo",
    "iso:country":"ES",
    "sg:address":"Carretera De Pradoluengo, S/n",
    "sg:city":"Villasur Herreros",
    "sg:orig_category":"Administraciones Regionales, Departamentales Y Locales",
    "sg:phone":"+34 947 42 92 52",
    "sg:postcode":"09199",
    "sg:province":"Burgos",
    "wof:name":"Ayuntamiento De Villasur De Herreros",
    "wof:placetype":"venue"
},
  "geometry": {"coordinates":[-3.6997311115,42.3408737183],"type":"Point"}
}