{
  "type": "Feature",
  "properties": {
    "addr:full":"Calle de Santa Rosa De Lima, 21 Santa Cruz De Tenerife Santa Cruz De Tenerife 38002",
    "addr:housenumber":"21",
    "addr:postcode":"38002",
    "addr:street":"Calle De Santa Rosa De Lima",
    "iso:country":"ES",
    "sg:address":"Calle de Santa Rosa De Lima, 21",
    "sg:city":"Santa Cruz De Tenerife",
    "sg:orig_category":"Importaci\u00d3n",
    "sg:phone":"+34 922 24 11 58",
    "sg:postcode":"38002",
    "sg:province":"Santa Cruz De Tenerife",
    "wof:name":"Kismat Traders S. A.",
    "wof:placetype":"venue"
},
  "geometry": {"coordinates":[-16.2494697571,28.470621109],"type":"Point"}
}