{
  "type": "Feature",
  "properties": {
    "addr:full":"Carrer de Paraires, 13 Palma Islas Baleares 07001",
    "addr:housenumber":"13",
    "addr:postcode":"07001",
    "addr:street":"Carrer De Paraires",
    "iso:country":"ES",
    "sg:address":"Carrer de Paraires, 13",
    "sg:city":"Palma",
    "sg:orig_category":"Complementos De Vestir (al Por Menor)",
    "sg:phone":"+34 971 71 79 36",
    "sg:postcode":"07001",
    "sg:province":"Islas Baleares",
    "wof:name":"Arias Fashion S.l.",
    "wof:placetype":"venue"
},
  "geometry": {"coordinates":[2.6472992897,39.5706176758],"type":"Point"}
}