{
  "type": "Feature",
  "properties": {
    "addr:full":"Calle de Jose Benlliure, 294 Valencia Valencia 46011",
    "addr:housenumber":"294",
    "addr:postcode":"46011",
    "addr:street":"Calle De Jose Benlliure",
    "iso:country":"ES",
    "sg:address":"Calle de Jose Benlliure, 294",
    "sg:city":"Valencia",
    "sg:orig_category":"Chapister\u00cda",
    "sg:phone":"+34 963 55 16 59",
    "sg:postcode":"46011",
    "sg:province":"Valencia",
    "wof:name":"Crespo Mauri Angel Jose",
    "wof:placetype":"venue"
},
  "geometry": {"coordinates":[-0.3292149901,39.4729118347],"type":"Point"}
}