{
  "type": "Feature",
  "properties": {
    "iso:country":"ES",
    "sg:address":"Pl Pere San, S/n",
    "sg:city":"S. Cugat Valles",
    "sg:orig_category":"Carnicer\u00cdas, Carnicer\u00cdas",
    "sg:phone":"+34 935 89 05 58",
    "sg:postcode":"08172",
    "sg:province":"Barcelona",
    "wof:name":"Vila Sanchez Miquel",
    "wof:placetype":"venue"
},
  "geometry": {"coordinates":[2.0822649002,41.4730415344],"type":"Point"}
}