{
  "type": "Feature",
  "properties": {
    "iso:country":"ES",
    "sg:address":"Cra. Canoves, S/n",
    "sg:city":"Cardedeu",
    "sg:orig_category":"Carnicer\u00cdas, Carnicer\u00cdas",
    "sg:phone":"+34 938 46 10 00",
    "sg:postcode":"08440",
    "sg:province":"Barcelona",
    "wof:name":"Bayle Albaz Mercedes",
    "wof:placetype":"venue"
},
  "geometry": {"coordinates":[2.3571050167,41.6474952698],"type":"Point"}
}