{
  "type": "Feature",
  "properties": {
    "addr:full":"Calle de Barnuevo Marin, 76 Bonete Albacete 02691",
    "addr:housenumber":"76",
    "addr:postcode":"02691",
    "addr:street":"Calle De Barnuevo Marin",
    "iso:country":"ES",
    "sg:address":"Calle de Barnuevo Marin, 76",
    "sg:city":"Bonete",
    "sg:orig_category":"Zapatos: Material, Suministros, Accesorios (fabricaci\u00d3n, Al Por Mayor)",
    "sg:phone":"+34 967 33 43 13",
    "sg:postcode":"02691",
    "sg:province":"Albacete",
    "wof:name":"Marroquinerias Y Aparatos Benider S.l.",
    "wof:placetype":"venue"
},
  "geometry": {"coordinates":[-1.3083684444,38.8759689331],"type":"Point"}
}