{
  "type": "Feature",
  "properties": {
    "iso:country":"ES",
    "sg:address":"Calle de Teniente Benitez, S/n",
    "sg:city":"Cuenca",
    "sg:orig_category":"Ense\u00d1anza, Formaci\u00d3n Profesional: Aprendizaje",
    "sg:phone":"+34 969 24 00 47",
    "sg:postcode":"16003",
    "sg:province":"Cuenca",
    "wof:name":"Diputacion Provincial De Cuenca",
    "wof:placetype":"venue"
},
  "geometry": {"coordinates":[-2.140912056,40.0617179871],"type":"Point"}
}