{
  "type": "Feature",
  "properties": {
    "addr:full":"Ctra Avila (de), 2 Gotarrendura \u00c1vila 05163",
    "addr:postcode":"05163",
    "addr:street":"Ctra Avila De 2 Gotarrendura A\u0301Vila",
    "iso:country":"ES",
    "sg:address":"Ctra Avila (de), 2",
    "sg:city":"Gotarrendura",
    "sg:orig_category":"Internados & Ense\u00d1anza Privada",
    "sg:phone":"+34 920 26 90 08",
    "sg:postcode":"05163",
    "sg:province":"\u00c1vila",
    "wof:name":"Reverendas Madres Esclavas De La Virgen Dolorosa",
    "wof:placetype":"venue"
},
  "geometry": {"coordinates":[-4.7396159172,40.8250350952],"type":"Point"}
}