{
  "type": "Feature",
  "properties": {
    "iso:country":"ES",
    "sg:address":"Calle de Clemente Saenz, 8",
    "sg:city":"Soria",
    "sg:orig_category":"Ingeniero",
    "sg:phone":"+34 975 22 69 90",
    "sg:postcode":"42002",
    "sg:province":"Soria",
    "wof:name":"Cabrerizo De Leon Santiago",
    "wof:placetype":"venue"
},
  "geometry": {"coordinates":[-2.466794014,41.7683525085],"type":"Point"}
}