{
  "type": "Feature",
  "properties": {
    "iso:country":"ES",
    "sg:address":"Avda Nueve De Octubre, 118",
    "sg:city":"Puerto",
    "sg:orig_category":"Confecci\u00d3n (fabricaci\u00d3n, Al Por Mayor)",
    "sg:phone":"+34 962 67 69 36",
    "sg:postcode":"46520",
    "sg:province":"Valencia",
    "wof:name":"Risue\u00f1o Moreno Antonio",
    "wof:placetype":"venue"
},
  "geometry": {"coordinates":[-0.2273710072,39.6623649597],"type":"Point"}
}