{
  "type": "Feature",
  "properties": {
    "addr:full":"Vereda Del Rayo, S/n Dos Hermanas Sevilla 41700",
    "addr:housenumber":"s",
    "addr:postcode":"41700",
    "addr:street":"Vereda Del Rayo;/ N Dos",
    "iso:country":"ES",
    "sg:address":"Vereda Del Rayo, S/n",
    "sg:city":"Dos Hermanas",
    "sg:orig_category":"Panader\u00cdas, Panader\u00cdas",
    "sg:phone":"+34 955 66 91 20",
    "sg:postcode":"41700",
    "sg:province":"Sevilla",
    "wof:name":"Marchan Bellido Cristina",
    "wof:placetype":"venue"
},
  "geometry": {"coordinates":[-5.9480690956,37.2811851501],"type":"Point"}
}