{
  "type": "Feature",
  "properties": {
    "addr:full":"Colonia Jordana, S/n S. Joan Abadesses Girona 17860",
    "addr:housenumber":"s",
    "addr:postcode":"17860",
    "addr:street":"Jordana;/ N S. Joan Abadesses",
    "iso:country":"ES",
    "sg:address":"Colonia Jordana, S/n",
    "sg:city":"S. Joan Abadesses",
    "sg:orig_category":"Electricidad, Electr\u00d3nica: Material Y Suministros (al Por Mayor)",
    "sg:phone":"+34 972 72 20 28",
    "sg:postcode":"17860",
    "sg:province":"Girona",
    "wof:name":"Tecnologia Electronica Del Ripolles S.l.",
    "wof:placetype":"venue"
},
  "geometry": {"coordinates":[2.2605309486,42.2263069153],"type":"Point"}
}