{
  "type": "Feature",
  "properties": {
    "addr:full":"Carrer de Agricultura, 67 Terrassa Barcelona 08223",
    "addr:housenumber":"67",
    "addr:postcode":"08223",
    "addr:street":"Carrer De Agricultura",
    "iso:country":"ES",
    "sg:address":"Carrer de Agricultura, 67",
    "sg:city":"Terrassa",
    "sg:orig_category":"Alquiler De V\u00cddeo",
    "sg:phone":"+34 937 31 12 54",
    "sg:postcode":"08223",
    "sg:province":"Barcelona",
    "wof:name":"Brunet Riera Xavier",
    "wof:placetype":"venue"
},
  "geometry": {"coordinates":[2.0246291161,41.5573959351],"type":"Point"}
}