{
  "type": "Feature",
  "properties": {
    "addr:full":"Avda Bueu, 9 Cangas Pontevedra 36940",
    "addr:housenumber":"9",
    "addr:postcode":"36940",
    "addr:street":"Avda Bueu",
    "iso:country":"ES",
    "sg:address":"Avda Bueu, 9",
    "sg:city":"Cangas",
    "sg:orig_category":"Fotocopias, Reprograf\u00cda",
    "sg:phone":"+34 986 30 52 96",
    "sg:postcode":"36940",
    "sg:province":"Pontevedra",
    "wof:name":"Copyted Morrazo Sl",
    "wof:placetype":"venue"
},
  "geometry": {"coordinates":[-8.7863855362,42.2588920593],"type":"Point"}
}