{
  "type": "Feature",
  "properties": {
    "iso:country":"ES",
    "sg:address":"Calle de Galicia, 2",
    "sg:city":"Villamoros De Las Regueras",
    "sg:orig_category":"Agricultores, Agricultores",
    "sg:phone":"+34 987 30 78 77",
    "sg:postcode":"24007",
    "sg:province":"Le\u00f3n",
    "wof:name":"Moran Fernandez Ana Belen",
    "wof:placetype":"venue"
},
  "geometry": {"coordinates":[-5.5357499123,42.6195907593],"type":"Point"}
}