{
  "type": "Feature",
  "properties": {
    "iso:country":"ES",
    "sg:address":"Calle de Panama, 4",
    "sg:city":"Zaragoza",
    "sg:orig_category":"Ingenier\u00cda, Centros De Estudios (diversos)",
    "sg:phone":"+34 976 33 51 92",
    "sg:postcode":"50012",
    "sg:province":"Zaragoza",
    "sg:website":"www.serrranoconsultores.com",
    "wof:name":"Serrano Faradues Miguel",
    "wof:placetype":"venue"
},
  "geometry": {"coordinates":[-0.9186789989,41.6471786499],"type":"Point"}
}