{
  "type": "Feature",
  "properties": {
    "iso:country":"ES",
    "sg:address":"Avda Asturias, 24",
    "sg:city":"Guardo",
    "sg:orig_category":"Caf\u00c9s, Bares, Cervecer\u00cdas",
    "sg:phone":"+34 979 85 00 32",
    "sg:postcode":"34880",
    "sg:province":"Palencia",
    "wof:name":"Iba\u00f1ez Monge Alvaro",
    "wof:placetype":"venue"
},
  "geometry": {"coordinates":[-4.8439221382,42.7909164429],"type":"Point"}
}