{
  "type": "Feature",
  "properties": {
    "addr:full":"Praz Porto Pesqueiro-lonxa, 40 Vigo Pontevedra 36202",
    "addr:housenumber":"40",
    "addr:postcode":"36202",
    "addr:street":"Pesqueiro-Lonxa",
    "iso:country":"ES",
    "sg:address":"Praz Porto Pesqueiro-lonxa, 40",
    "sg:city":"Vigo",
    "sg:orig_category":"Caf\u00c9s, Bares, Cervecer\u00cdas",
    "sg:phone":"+34 986 20 16 77",
    "sg:postcode":"36202",
    "sg:province":"Pontevedra",
    "wof:name":"Portel Eixo Atlantico S.r.l.",
    "wof:placetype":"venue"
},
  "geometry": {"coordinates":[-8.7320985794,42.2364654541],"type":"Point"}
}