{
  "type": "Feature",
  "properties": {
    "addr:full":"Plaz Solobarria, 1 Arizgoiti Vizcaya 48970",
    "addr:housenumber":"1",
    "addr:postcode":"48970",
    "addr:street":"Plaz Solobarria",
    "iso:country":"ES",
    "sg:address":"Plaz Solobarria, 1",
    "sg:city":"Arizgoiti",
    "sg:orig_category":"Centros Empresariales",
    "sg:phone":"+34 944 40 33 77",
    "sg:postcode":"48970",
    "sg:province":"Vizcaya",
    "wof:name":"Asociacion De Comerciantes De Basauri",
    "wof:placetype":"venue"
},
  "geometry": {"coordinates":[-2.8838863373,43.2386817932],"type":"Point"}
}