{
  "type": "Feature",
  "properties": {
    "addr:full":"Avda Cantabria, 73 Burgos Burgos 09006",
    "addr:housenumber":"73",
    "addr:postcode":"09006",
    "addr:street":"Avda Cantabria",
    "iso:country":"ES",
    "sg:address":"Avda Cantabria, 73",
    "sg:city":"Burgos",
    "sg:orig_category":"Sociedades, Compa\u00d1\u00cdas Aseguradoras",
    "sg:phone":"+34 947 27 66 27",
    "sg:postcode":"09006",
    "sg:province":"Burgos",
    "wof:name":"Caja Circulo Correduria De Seguros S.a.",
    "wof:placetype":"venue"
},
  "geometry": {"coordinates":[-3.6912789345,42.3534240723],"type":"Point"}
}