{
  "type": "Feature",
  "properties": {
    "iso:country":"ES",
    "sg:address":"Carrer de Horta, 16",
    "sg:city":"Sabadell",
    "sg:orig_category":"Construcci\u00d3n Mec\u00c1nica",
    "sg:phone":"+34 937 12 28 51",
    "sg:postcode":"08203",
    "sg:province":"Barcelona",
    "wof:name":"Camec S.l.",
    "wof:placetype":"venue"
},
  "geometry": {"coordinates":[2.1044809818,41.5332756042],"type":"Point"}
}