{
  "type": "Feature",
  "properties": {
    "iso:country":"ES",
    "sg:address":"Calle de Estrada, 3",
    "sg:city":"Palencia",
    "sg:orig_category":"Molduras, Junquillos, Listones Y Molduras Perforadas",
    "sg:phone":"+34 979 72 49 32",
    "sg:postcode":"34002",
    "sg:province":"Palencia",
    "wof:name":"Rodrigo Cosio Maria Pilar",
    "wof:placetype":"venue"
},
  "geometry": {"coordinates":[-4.5295200348,42.0076904297],"type":"Point"}
}