{
  "type": "Feature",
  "properties": {
    "iso:country":"ES",
    "sg:address":"Calle de Pedro Laborde, 15",
    "sg:city":"Madrid",
    "sg:orig_category":"Molduras, Junquillos, Listones Y Molduras Perforadas",
    "sg:phone":"+34 913 03 14 64",
    "sg:postcode":"28038",
    "sg:province":"Madrid",
    "wof:name":"Soria Soria Eduardo",
    "wof:placetype":"venue"
},
  "geometry": {"coordinates":[-3.6478512287,40.3887443542],"type":"Point"}
}