{
  "type": "Feature",
  "properties": {
    "iso:country":"ES",
    "sg:address":"Pol. Veintiseis, S/n",
    "sg:city":"Vallelado",
    "sg:orig_category":"Gastronom\u00cda: Especialidades Regionales Y Extranjeras (producci\u00d3n, Al Por Mayor)",
    "sg:phone":"+34 921 15 02 39",
    "sg:postcode":"40213",
    "sg:province":"Segovia",
    "wof:name":"Baeza San Miguel Bego\u00d1a",
    "wof:placetype":"venue"
},
  "geometry": {"coordinates":[-4.4269690514,41.4046897888],"type":"Point"}
}