{
  "type": "Feature",
  "properties": {
    "addr:full":"Urbz Sierra Nevada, S/n Guadix Granada 18500",
    "addr:postcode":"18500",
    "addr:street":"Nevada S / N",
    "iso:country":"ES",
    "sg:address":"Urbz Sierra Nevada, S/n",
    "sg:city":"Guadix",
    "sg:classifiers":[
        {
            "category":"Autos & Motor Vehicles",
            "subcategory":"Automobile Sales",
            "type":"Retail Goods"
        }
    ],
    "sg:phone":"+34 958 66 22 68",
    "sg:postcode":"18500",
    "sg:province":"Granada",
    "wof:name":"Accironda S.l.",
    "wof:placetype":"venue"
},
  "geometry": {"coordinates":[-3.0776567459,37.4068832397],"type":"Point"}
}