{
  "type": "Feature",
  "properties": {
    "addr:full":"Bo. Puxeiros, 2 Mos Pontevedra 36416",
    "addr:housenumber":"2",
    "addr:postcode":"36416",
    "addr:street":"Bo. Puxeiros",
    "iso:country":"ES",
    "sg:address":"Bo. Puxeiros, 2",
    "sg:city":"Mos",
    "sg:orig_category":"Mercer\u00cda, Lencer\u00cda (al Por Menor)",
    "sg:phone":"+34 986 48 74 76",
    "sg:postcode":"36416",
    "sg:province":"Pontevedra",
    "wof:name":"Gradin Bastos Maria Dolores",
    "wof:placetype":"venue"
},
  "geometry": {"coordinates":[-8.6504888535,42.2080383301],"type":"Point"}
}