{
  "type": "Feature",
  "properties": {
    "addr:full":"Calle de Rojas Zorrilla, 18 Sevilla Sevilla 41007",
    "addr:housenumber":"18",
    "addr:postcode":"41007",
    "addr:street":"Calle De Rojas Zorrilla",
    "iso:country":"ES",
    "sg:address":"Calle de Rojas Zorrilla, 18",
    "sg:city":"Sevilla",
    "sg:orig_category":"Detectives, Agentes Investigadores Privados",
    "sg:phone":"+34 954 57 94 07",
    "sg:postcode":"41007",
    "sg:province":"Sevilla",
    "sg:website":"www.walkersdetectives.com",
    "wof:name":"Ostos Jimenez Fernando Maria",
    "wof:placetype":"venue"
},
  "geometry": {"coordinates":[-5.9674811363,37.3888130188],"type":"Point"}
}