{
  "type": "Feature",
  "properties": {
    "iso:country":"ES",
    "sg:address":"Calle de Juan Antonio Fernandez, 10",
    "sg:city":"Tudela",
    "sg:orig_category":"Parques De Atracciones Y Centros De Esparcimiento",
    "sg:phone":"+34 948 82 28 95",
    "sg:postcode":"31500",
    "sg:province":"Navarra",
    "sg:website":"www.valisa.es",
    "wof:name":"Valisa Internacional S.a.",
    "wof:placetype":"venue"
},
  "geometry": {"coordinates":[-1.6013200283,42.0584373474],"type":"Point"}
}