{
  "type": "Feature",
  "properties": {
    "addr:full":"Avda Castrelos, 80 Vigo Pontevedra 36210",
    "addr:housenumber":"80",
    "addr:postcode":"36210",
    "addr:street":"Avda Castrelos",
    "iso:country":"ES",
    "sg:address":"Avda Castrelos, 80",
    "sg:city":"Vigo",
    "sg:orig_category":"Cl\u00cdnicas Dentales",
    "sg:phone":"+34 986 29 83 39",
    "sg:postcode":"36210",
    "sg:province":"Pontevedra",
    "wof:name":"Martinez Baggini Silvia Beatriz",
    "wof:placetype":"venue"
},
  "geometry": {"coordinates":[-8.7325630188,42.2166595459],"type":"Point"}
}