{
  "type": "Feature",
  "properties": {
    "addr:full":"El Mirador, 1 Huercal-overa Almer\u00eda 04600",
    "addr:housenumber":"1",
    "addr:postcode":"04600",
    "addr:street":"El Mirador;Almeri\u0301A",
    "iso:country":"ES",
    "sg:address":"El Mirador, 1",
    "sg:city":"Huercal-overa",
    "sg:orig_category":"Ropa Y Art\u00cdculos Pre",
    "sg:phone":"+34 950 47 06 06",
    "sg:postcode":"04600",
    "sg:province":"Almer\u00eda",
    "wof:name":"Benitez Garcia Francisco",
    "wof:placetype":"venue"
},
  "geometry": {"coordinates":[-1.943696022,37.3923072815],"type":"Point"}
}