{
  "type": "Feature",
  "properties": {
    "addr:full":"Calle de Cervantes, 47 Ejido Almer\u00eda 04700",
    "addr:housenumber":"47 ejido",
    "addr:postcode":"04700",
    "addr:street":"Calle De Cervantes;Almeri\u0301A",
    "iso:country":"ES",
    "sg:address":"Calle de Cervantes, 47",
    "sg:city":"Ejido",
    "sg:orig_category":"Asesor\u00cda Sobre Comunicaci\u00d3n De Empresas",
    "sg:phone":"+34 950 48 78 52",
    "sg:postcode":"04700",
    "sg:province":"Almer\u00eda",
    "wof:name":"Gaitan Ibarra Gador",
    "wof:placetype":"venue"
},
  "geometry": {"coordinates":[-2.8173806667,36.7738609314],"type":"Point"}
}