{
  "type": "Feature",
  "properties": {
    "iso:country":"ES",
    "sg:address":"Calle de Clavel, 10",
    "sg:city":"Sanlucar Mayor",
    "sg:orig_category":"Transportes Por V\u00cdas Navegables",
    "sg:phone":"+34 955 70 05 66",
    "sg:postcode":"41800",
    "sg:province":"Sevilla",
    "wof:name":"Lopez Raya Maria Teresa",
    "wof:placetype":"venue"
},
  "geometry": {"coordinates":[-6.198887825,37.3840293884],"type":"Point"}
}