{
  "type": "Feature",
  "properties": {
    "iso:country":"ES",
    "sg:address":"Calle de Algorta, 25",
    "sg:city":"Madrid",
    "sg:orig_category":"Arte, Cultura, Edici\u00d3n",
    "sg:phone":"+34 914 72 26 93",
    "sg:postcode":"28019",
    "sg:province":"Madrid",
    "sg:website":"www.elobservatorio.net",
    "wof:name":"El Observatorio Musical S.l.",
    "wof:placetype":"venue"
},
  "geometry": {"coordinates":[-3.7312631607,40.3921432495],"type":"Point"}
}