{
  "type": "Feature",
  "properties": {
    "iso:country":"ES",
    "sg:address":"Plaz Martin Ya\u00d1ez, 8",
    "sg:city":"Zalamea Serena",
    "sg:orig_category":"Librer\u00cdas",
    "sg:phone":"+34 924 77 55 32",
    "sg:postcode":"06430",
    "sg:province":"Badajoz",
    "wof:name":"Pozo Pozo Granada",
    "wof:placetype":"venue"
},
  "geometry": {"coordinates":[-5.6559262276,38.649646759],"type":"Point"}
}