{
  "type": "Feature",
  "properties": {
    "addr:full":"Calle de Trinidad Grund, 2 Malaga M\u00e1laga 29001",
    "addr:housenumber":"2",
    "addr:postcode":"29001",
    "addr:street":"Calle De Trinidad Grund;Ma\u0301Laga",
    "iso:country":"ES",
    "sg:address":"Calle de Trinidad Grund, 2",
    "sg:city":"Malaga",
    "sg:orig_category":"Arquitectos",
    "sg:phone":"+34 952 21 94 21",
    "sg:postcode":"29001",
    "sg:province":"M\u00e1laga",
    "wof:name":"Rodriguez Grajales Clemente",
    "wof:placetype":"venue"
},
  "geometry": {"coordinates":[-4.4209752083,36.7175483704],"type":"Point"}
}