{
  "type": "Feature",
  "properties": {
    "addr:full":"Carrer de Gallecs, 17 Mollet Valles Barcelona 08100",
    "addr:housenumber":"17",
    "addr:postcode":"08100",
    "addr:street":"Carrer De Gallecs",
    "iso:country":"ES",
    "sg:address":"Carrer de Gallecs, 17",
    "sg:city":"Mollet Valles",
    "sg:orig_category":"Carnicer\u00cdas, Carnicer\u00cdas",
    "sg:phone":"+34 935 93 74 55",
    "sg:postcode":"08100",
    "sg:province":"Barcelona",
    "wof:name":"Hernandez Rodriguez Ramon",
    "wof:placetype":"venue"
},
  "geometry": {"coordinates":[2.2100930214,41.5441589355],"type":"Point"}
}