{
  "type": "Feature",
  "properties": {
    "addr:full":"Carr Pla Amunt, 18 Pla D'amont Girona 17160",
    "addr:housenumber":"18",
    "addr:postcode":"17160",
    "addr:street":"Carr Pla Amunt",
    "iso:country":"ES",
    "sg:address":"Carr Pla Amunt, 18",
    "sg:city":"Pla D'amont",
    "sg:orig_category":"Semiller\u00cdas",
    "sg:phone":"+34 972 42 21 27",
    "sg:postcode":"17160",
    "sg:province":"Girona",
    "wof:name":"Terres Torrent S.l.",
    "wof:placetype":"venue"
},
  "geometry": {"coordinates":[2.8187398911,41.9808616638],"type":"Point"}
}