{
  "type": "Feature",
  "properties": {
    "addr:full":"Avda Monrepos (de), S/n Hostal Ipies Huesca 22621",
    "addr:housenumber":"/ n",
    "addr:postcode":"22621",
    "addr:street":"Avda Monrepos De S",
    "iso:country":"ES",
    "sg:address":"Avda Monrepos (de), S/n",
    "sg:city":"Hostal Ipies",
    "sg:orig_category":"Distribuci\u00d3n De Petr\u00d3leo Y Derivados",
    "sg:phone":"+34 974 49 69 06",
    "sg:postcode":"22621",
    "sg:province":"Huesca",
    "sg:website":"www.cepsa.es",
    "wof:name":"Portal De Serrablo S.l.",
    "wof:placetype":"venue"
},
  "geometry": {"coordinates":[-0.376951009,42.4408950806],"type":"Point"}
}