{
  "type": "Feature",
  "properties": {
    "iso:country":"ES",
    "sg:address":"Carrer de Sant Miquel, 207",
    "sg:city":"Deltebre",
    "sg:orig_category":"Molduras, Junquillos, Listones Y Molduras Perforadas",
    "sg:phone":"+34 977 48 99 02",
    "sg:postcode":"43580",
    "sg:province":"Tarragona",
    "wof:name":"Braojos Garcia Rosario",
    "wof:placetype":"venue"
},
  "geometry": {"coordinates":[0.7268099785,40.7200698853],"type":"Point"}
}