{
  "type": "Feature",
  "properties": {
    "addr:full":"Avgd Francesc Macia, 15 Lleida Lleida 25007",
    "addr:housenumber":"15",
    "addr:postcode":"25007",
    "addr:street":"Macia",
    "iso:country":"ES",
    "sg:address":"Avgd Francesc Macia, 15",
    "sg:city":"Lleida",
    "sg:orig_category":"Loter\u00cda Y T\u00d3mbola",
    "sg:phone":"+34 973 22 00 02",
    "sg:postcode":"25007",
    "sg:province":"Lleida",
    "wof:name":"Serrano Biosca Rosa Maria",
    "wof:placetype":"venue"
},
  "geometry": {"coordinates":[0.6279299855,41.6157798767],"type":"Point"}
}