{
  "type": "Feature",
  "properties": {
    "iso:country":"ES",
    "sg:address":"Carrer de Pau, 31",
    "sg:city":"Manresa",
    "sg:orig_category":"Panader\u00cdas, Panader\u00cdas",
    "sg:phone":"+34 938 77 23 68",
    "sg:postcode":"08243",
    "sg:province":"Barcelona",
    "wof:name":"Forn De Cabrianes S.l.",
    "wof:placetype":"venue"
},
  "geometry": {"coordinates":[1.8337579966,41.7379684448],"type":"Point"}
}