{
  "type": "Feature",
  "properties": {
    "addr:full":"Calle de Alvaro Mendez, 2 Rota C\u00e1diz 11520",
    "addr:housenumber":"2",
    "addr:postcode":"11520",
    "addr:street":"Calle De Alvaro Mendez;Ca\u0301Diz",
    "iso:country":"ES",
    "sg:address":"Calle de Alvaro Mendez, 2",
    "sg:city":"Rota",
    "sg:orig_category":"Molduras, Junquillos, Listones Y Molduras Perforadas",
    "sg:phone":"+34 956 81 04 07",
    "sg:postcode":"11520",
    "sg:province":"C\u00e1diz",
    "wof:name":"Cortines Sanchez Angel",
    "wof:placetype":"venue"
},
  "geometry": {"coordinates":[-6.3579740524,36.6185302734],"type":"Point"}
}