{
  "type": "Feature",
  "properties": {
    "addr:full":"Calle de Clara Del Rey, 42 Madrid Madrid 28002",
    "addr:housenumber":"42",
    "addr:postcode":"madrid;28002",
    "addr:street":"Calle De Clara Del Rey",
    "iso:country":"ES",
    "sg:address":"Calle de Clara Del Rey, 42",
    "sg:city":"Madrid",
    "sg:orig_category":"Estancos",
    "sg:phone":"+34 914 16 75 51",
    "sg:postcode":"28002",
    "sg:province":"Madrid",
    "wof:name":"Barreda Alvarez Benito",
    "wof:placetype":"venue"
},
  "geometry": {"coordinates":[-3.6682400703,40.4447364807],"type":"Point"}
}