{
  "type": "Feature",
  "properties": {
    "iso:country":"ES",
    "sg:address":"La Ribera, 23",
    "sg:city":"Priego Cordoba",
    "sg:orig_category":"Telas Y Sedas (al Por Menor)",
    "sg:phone":"+34 957 54 06 88",
    "sg:postcode":"14800",
    "sg:province":"C\u00f3rdoba",
    "wof:name":"Calvo Lopez Jose",
    "wof:placetype":"venue"
},
  "geometry": {"coordinates":[-4.1934070587,37.4389915466],"type":"Point"}
}