{
  "type": "Feature",
  "properties": {
    "iso:country":"ES",
    "sg:address":"Calle de Maria Rosa Molas, 15",
    "sg:city":"Castellon",
    "sg:orig_category":"Muebles Y Accesorios Para Cocinas Y Cuartos De Ba\u00d1o (al Por Menor)",
    "sg:phone":"+34 964 22 38 64",
    "sg:postcode":"12004",
    "sg:province":"Castell\u00f3n",
    "wof:name":"Jld Dos Ambients Castello S.l.l.",
    "wof:placetype":"venue"
},
  "geometry": {"coordinates":[-0.0340000018,39.9949188232],"type":"Point"}
}