{
  "type": "Feature",
  "properties": {
    "iso:country":"ES",
    "sg:address":"Calle de Mateos Gago, 14",
    "sg:city":"Sevilla",
    "sg:orig_category":"Farmacias",
    "sg:phone":"+34 954 22 54 67",
    "sg:postcode":"41004",
    "sg:province":"Sevilla",
    "wof:name":"Rodriguez Ca\u00f1as Maria Jesus",
    "wof:placetype":"venue"
},
  "geometry": {"coordinates":[-5.9909291267,37.386089325],"type":"Point"}
}