{
  "type": "Feature",
  "properties": {
    "addr:full":"Carrer de Santander, 101 Barcelona Barcelona 08030",
    "addr:housenumber":"101",
    "addr:postcode":"08030",
    "addr:street":"Carrer De Santander",
    "iso:country":"ES",
    "sg:address":"Carrer de Santander, 101",
    "sg:city":"Barcelona",
    "sg:orig_category":"Servidores Y Editores De Bases De Datos",
    "sg:phone":"+34 932 78 22 48",
    "sg:postcode":"08030",
    "sg:province":"Barcelona",
    "sg:website":"www.isecauditors.com",
    "wof:name":"Internet Security Auditors S.l.",
    "wof:placetype":"venue"
},
  "geometry": {"coordinates":[2.2066791058,41.4333076477],"type":"Point"}
}