{
  "type": "Feature",
  "properties": {
    "iso:country":"ES",
    "sg:address":"Avda Malaga, 85",
    "sg:city":"Cala Moral",
    "sg:orig_category":"M\u00c9dicos: An\u00c1lisis Cl\u00cdnicos",
    "sg:phone":"+34 952 40 73 92",
    "sg:postcode":"29720",
    "sg:province":"M\u00e1laga",
    "wof:name":"Osorio Diaz Fuensanta",
    "wof:placetype":"venue"
},
  "geometry": {"coordinates":[-4.3098249435,36.7154006958],"type":"Point"}
}