{
  "type": "Feature",
  "properties": {
    "addr:full":"Ctra De Miranda, S/n Berbinzana Navarra 31252",
    "addr:housenumber":"s / n",
    "addr:postcode":"31252",
    "addr:street":"Ctra De Miranda",
    "iso:country":"ES",
    "sg:address":"Ctra De Miranda, S/n",
    "sg:city":"Berbinzana",
    "sg:orig_category":"Producci\u00d3n, Venta De Productos De Agricultura Biol\u00d3gica",
    "sg:phone":"+34 948 72 22 83",
    "sg:postcode":"31252",
    "sg:province":"Navarra",
    "wof:name":"Cooperativa Agricola De Berbinzana",
    "wof:placetype":"venue"
},
  "geometry": {"coordinates":[-1.8347289562,42.5271186829],"type":"Point"}
}