{
  "type": "Feature",
  "properties": {
    "iso:country":"ES",
    "sg:address":"Carrer de Rossello, 224",
    "sg:city":"Barcelona",
    "sg:orig_category":"Ropa De Casa (fabricaci\u00d3n, Al Por Mayor)",
    "sg:phone":"+34 932 15 11 03",
    "sg:postcode":"08008",
    "sg:province":"Barcelona",
    "sg:website":"www.textura-interiors.com",
    "wof:name":"Textil Textura S.l.",
    "wof:placetype":"venue"
},
  "geometry": {"coordinates":[2.1596999168,41.3949127197],"type":"Point"}
}