{
  "type": "Feature",
  "properties": {
    "iso:country":"ES",
    "sg:address":"Espirito Sto.(cecebre), 11",
    "sg:city":"Cambre",
    "sg:orig_category":"Ingenier\u00cda, Centros De Estudios (diversos)",
    "sg:phone":"+34 981 67 67 90",
    "sg:postcode":"15650",
    "sg:province":"La Coru\u00f1a",
    "wof:name":"Construcciones Pan Y Diaz S. L.",
    "wof:placetype":"venue"
},
  "geometry": {"coordinates":[-8.3069343567,43.2885551453],"type":"Point"}
}