{
  "type": "Feature",
  "properties": {
    "iso:country":"ES",
    "sg:address":"C/ Leon Sanchez Saez, 17",
    "sg:city":"Elche",
    "sg:orig_category":"Perfumer\u00cda Y Cosm\u00c9tica (fabricaci\u00d3n, Al Por Mayor)",
    "sg:phone":"+34 965 43 25 11",
    "sg:postcode":"03205",
    "sg:province":"Alicante",
    "wof:name":"Makeup Movie S.l.",
    "wof:placetype":"venue"
},
  "geometry": {"coordinates":[-0.7124890089,38.2662582397],"type":"Point"}
}