{
  "type": "Feature",
  "properties": {
    "iso:country":"ES",
    "sg:address":"Calle de Jose Ramos Y Guillen, 3",
    "sg:city":"Malaga",
    "sg:orig_category":"Asociaciones, Organismos Culturales Y Socioeducativos",
    "sg:phone":"+34 952 30 84 84",
    "sg:postcode":"29010",
    "sg:province":"M\u00e1laga",
    "wof:name":"Pe\u00f1a Cultural Recreativa La Palma",
    "wof:placetype":"venue"
},
  "geometry": {"coordinates":[-4.4709968567,36.7225151062],"type":"Point"}
}