{
  "type": "Feature",
  "properties": {
    "iso:country":"ES",
    "sg:address":"Avda Numancia, 24",
    "sg:city":"Arnedo",
    "sg:orig_category":"Doctores En Medicina",
    "sg:phone":"+34 941 38 01 82",
    "sg:postcode":"26580",
    "sg:province":"La Rioja",
    "wof:name":"Perez Gomez Francisco Javier",
    "wof:placetype":"venue"
},
  "geometry": {"coordinates":[-2.1156320572,42.2215232849],"type":"Point"}
}