{
  "type": "Feature",
  "properties": {
    "addr:full":"Praga(p I Mas De Tous), 7 Pobla Vallbona Valencia 46185",
    "addr:postcode":"46185",
    "addr:street":"Pobla",
    "iso:country":"ES",
    "sg:address":"Praga(p I Mas De Tous), 7",
    "sg:city":"Pobla Vallbona",
    "sg:orig_category":"Artes Gr\u00c1ficas, Artes Pl\u00c1sticas (curso)",
    "sg:phone":"+34 962 76 33 86",
    "sg:postcode":"46185",
    "sg:province":"Valencia",
    "wof:name":"Irajac S.l.",
    "wof:placetype":"venue"
},
  "geometry": {"coordinates":[-0.5320240259,39.5886878967],"type":"Point"}
}