{
  "type": "Feature",
  "properties": {
    "iso:country":"ES",
    "sg:address":"Pe\u00f1a Careses, 44",
    "sg:city":"Lugo",
    "sg:orig_category":"Venta, Alquiler, Mantenimiento De Calderas",
    "sg:phone":"+34 985 26 51 13",
    "sg:postcode":"33192",
    "sg:province":"Asturias",
    "wof:name":"Tramerca S.l.",
    "wof:placetype":"venue"
},
  "geometry": {"coordinates":[-5.7745718956,43.4596939087],"type":"Point"}
}