{
  "type": "Feature",
  "properties": {
    "iso:country":"ES",
    "sg:address":"Luga Rio De Quintas, 20",
    "sg:city":"Rio De Quintas",
    "sg:orig_category":"Empresarios",
    "sg:phone":"+34 981 17 12 04",
    "sg:postcode":"15170",
    "sg:province":"La Coru\u00f1a",
    "wof:name":"Asistencia Electrica Coru\u00f1a S.l.",
    "wof:placetype":"venue"
},
  "geometry": {"coordinates":[-8.3848657608,42.8390884399],"type":"Point"}
}