{
  "type": "Feature",
  "properties": {
    "iso:country":"ES",
    "sg:address":"Carrer de Plato, 6",
    "sg:city":"Barcelona",
    "sg:orig_category":"Elementos Para Suelos Prefabricados",
    "sg:phone":"+34 934 14 00 54",
    "sg:postcode":"08021",
    "sg:province":"Barcelona",
    "wof:name":"Espacio S.a.",
    "wof:placetype":"venue"
},
  "geometry": {"coordinates":[2.1408410072,41.3994750977],"type":"Point"}
}