{
  "type": "Feature",
  "properties": {
    "iso:country":"ES",
    "sg:address":"Fuero Del Trabajo, S/n",
    "sg:city":"Burgos",
    "sg:orig_category":"Goma: Productos De Uso Industrial (fabricaci\u00d3n, Al Por Mayor)",
    "sg:phone":"+34 947 48 15 35",
    "sg:postcode":"09007",
    "sg:province":"Burgos",
    "wof:name":"Vulcanizados Santamaria S.l.",
    "wof:placetype":"venue"
},
  "geometry": {"coordinates":[-3.6428365707,42.3625259399],"type":"Point"}
}