{
  "type": "Feature",
  "properties": {
    "addr:full":"Calle de Paniagua, 23 Sotogrande C\u00e1diz 11310",
    "addr:housenumber":"23",
    "addr:postcode":"11310",
    "addr:street":"Calle De Paniagua;Ca\u0301Diz",
    "iso:country":"ES",
    "sg:address":"Calle de Paniagua, 23",
    "sg:city":"Sotogrande",
    "sg:orig_category":"Arquitectos",
    "sg:phone":"+34 956 78 50 90",
    "sg:postcode":"11310",
    "sg:province":"C\u00e1diz",
    "wof:name":"Gp23 Arquitectos S.l",
    "wof:placetype":"venue"
},
  "geometry": {"coordinates":[-5.3037362099,36.2896766663],"type":"Point"}
}