{
  "type": "Feature",
  "properties": {
    "addr:full":"Pg Puig (el), 2 Manlleu Barcelona 08560",
    "addr:housenumber":"2",
    "addr:postcode":"08560",
    "addr:street":"Pg Puig El",
    "iso:country":"ES",
    "sg:address":"Pg Puig (el), 2",
    "sg:city":"Manlleu",
    "sg:orig_category":"Peluquer\u00cdas, Peluquer\u00cda Mixta",
    "sg:phone":"+34 938 50 62 68",
    "sg:postcode":"08560",
    "sg:province":"Barcelona",
    "wof:name":"Imatgemma S.c.p.",
    "wof:placetype":"venue"
},
  "geometry": {"coordinates":[2.2873859406,42.0045280457],"type":"Point"}
}