{
  "type": "Feature",
  "properties": {
    "iso:country":"ES",
    "sg:address":"Rond Roureda, 3",
    "sg:city":"Sabadell",
    "sg:orig_category":"Molduras, Junquillos, Listones Y Molduras Perforadas",
    "sg:phone":"+34 937 17 42 51",
    "sg:postcode":"08207",
    "sg:province":"Barcelona",
    "wof:name":"Garcia Moreno Piedad",
    "wof:placetype":"venue"
},
  "geometry": {"coordinates":[2.0853769779,41.5692901611],"type":"Point"}
}