{
  "type": "Feature",
  "properties": {
    "iso:country":"ES",
    "sg:address":"Aoiz-agoitz Kalea, 6",
    "sg:city":"Iru\u00f1a",
    "sg:orig_category":"Ense\u00d1anza, Formaci\u00d3n Profesional: Aprendizaje",
    "sg:phone":"+34 948 15 19 09",
    "sg:postcode":"31004",
    "sg:province":"Navarra",
    "wof:name":"Opnatel",
    "wof:placetype":"venue"
},
  "geometry": {"coordinates":[-1.6322449446,42.8101577759],"type":"Point"}
}