{
  "type": "Feature",
  "properties": {
    "addr:full":"Carrer de Duero, 40 Terrassa Barcelona 08223",
    "addr:housenumber":"40",
    "addr:postcode":"08223",
    "addr:street":"Carrer De Duero",
    "iso:country":"ES",
    "sg:address":"Carrer de Duero, 40",
    "sg:city":"Terrassa",
    "sg:orig_category":"Metalurgia: Maquinaria Y Equipos",
    "sg:phone":"+34 937 31 93 74",
    "sg:postcode":"08223",
    "sg:province":"Barcelona",
    "wof:name":"Hernandez Freixa Josep",
    "wof:placetype":"venue"
},
  "geometry": {"coordinates":[2.0311889648,41.5558013916],"type":"Point"}
}