{
  "type": "Feature",
  "properties": {
    "iso:country":"ES",
    "sg:address":"C/ Cid Campeador, 16",
    "sg:city":"Manacor",
    "sg:orig_category":"Empresas De Carpinter\u00cda De Madera",
    "sg:phone":"+34 971 55 01 45",
    "sg:postcode":"07500",
    "sg:province":"Islas Baleares",
    "wof:name":"Bordoy Caldentey S.l.",
    "wof:placetype":"venue"
},
  "geometry": {"coordinates":[3.2006180286,39.5688247681],"type":"Point"}
}