{
  "type": "Feature",
  "properties": {
    "iso:country":"ES",
    "sg:address":"Rua Carballeira, 21",
    "sg:city":"Cambados",
    "sg:orig_category":"Psic\u00d3logos",
    "sg:phone":"+34 986 52 45 10",
    "sg:postcode":"36630",
    "sg:province":"Pontevedra",
    "wof:name":"Salvado Pena Maria Andrea",
    "wof:placetype":"venue"
},
  "geometry": {"coordinates":[-8.8121595383,42.5154495239],"type":"Point"}
}