{
  "type": "Feature",
  "properties": {
    "addr:full":"Calle de Constitucion, 2 Santo Tome Ja\u00e9n 23311",
    "addr:housenumber":"2",
    "addr:postcode":"23311",
    "addr:street":"Calle De Constitucion",
    "iso:country":"ES",
    "sg:address":"Calle de Constitucion, 2",
    "sg:city":"Santo Tome",
    "sg:orig_category":"M\u00c9dicos: Estomatolog\u00cda",
    "sg:phone":"+34 953 73 62 86",
    "sg:postcode":"23311",
    "sg:province":"Ja\u00e9n",
    "wof:name":"Garcia Saez Carmen",
    "wof:placetype":"venue"
},
  "geometry": {"coordinates":[-3.0990235806,38.0275726318],"type":"Point"}
}