{
  "type": "Feature",
  "properties": {
    "iso:country":"ES",
    "sg:address":"Secretario, 1",
    "sg:city":"El Campello",
    "sg:orig_category":"Inmobiliaria (agencias)",
    "sg:phone":"+34 965 63 61 87",
    "sg:postcode":"03560",
    "sg:province":"Alicante",
    "wof:name":"Balfron S.a",
    "wof:placetype":"venue"
},
  "geometry": {"coordinates":[-0.3912590146,38.4225158691],"type":"Point"}
}