{
  "type": "Feature",
  "properties": {
    "iso:country":"ES",
    "sg:address":"Carrer de Giner De Los Rios, 29",
    "sg:city":"Guardamar Segura",
    "sg:orig_category":"Inmobiliaria (agencias)",
    "sg:phone":"+34 966 72 63 16",
    "sg:postcode":"03140",
    "sg:province":"Alicante",
    "wof:name":"Comunidad De Propietarios Edif Parqueluz",
    "wof:placetype":"venue"
},
  "geometry": {"coordinates":[-0.6535009742,38.0796356201],"type":"Point"}
}