{
  "type": "Feature",
  "properties": {
    "addr:full":"Calle de Santa Paula, 23 Granada Granada 18001",
    "addr:housenumber":"23",
    "addr:postcode":"18001",
    "addr:street":"Calle De Santa Paula",
    "iso:country":"ES",
    "sg:address":"Calle de Santa Paula, 23",
    "sg:city":"Granada",
    "sg:orig_category":"Ense\u00d1anza, Formaci\u00d3n Profesional: Aprendizaje",
    "sg:phone":"+34 958 80 43 85",
    "sg:postcode":"18001",
    "sg:province":"Granada",
    "wof:name":"Federacion Andaluza De Hockey",
    "wof:placetype":"venue"
},
  "geometry": {"coordinates":[-3.6005029678,37.1788902283],"type":"Point"}
}