{
  "type": "Feature",
  "properties": {
    "iso:country":"ES",
    "sg:address":"Pla\u00c7 Pau Casals, S/n",
    "sg:city":"Balaguer",
    "sg:orig_category":"Molduras, Junquillos, Listones Y Molduras Perforadas",
    "sg:phone":"+34 973 44 59 33",
    "sg:postcode":"25600",
    "sg:province":"Lleida",
    "wof:name":"La Rosaleda S.c.p.",
    "wof:placetype":"venue"
},
  "geometry": {"coordinates":[0.8078740239,41.7893180847],"type":"Point"}
}