{
  "type": "Feature",
  "properties": {
    "addr:full":"Calle de Fatima, 16 Albacete Albacete 02004",
    "addr:housenumber":"16",
    "addr:postcode":"02004",
    "addr:street":"Calle De Fatima",
    "iso:country":"ES",
    "sg:address":"Calle de Fatima, 16",
    "sg:city":"Albacete",
    "sg:orig_category":"Mec\u00c1nico Del Autom\u00d3vil",
    "sg:phone":"+34 967 51 02 73",
    "sg:postcode":"02004",
    "sg:province":"Albacete",
    "wof:name":"Lopez Escobar Fernando",
    "wof:placetype":"venue"
},
  "geometry": {"coordinates":[-1.8651829958,38.9934196472],"type":"Point"}
}