{
  "type": "Feature",
  "properties": {
    "iso:country":"ES",
    "sg:address":"Calle de Leon Xiii, 22",
    "sg:city":"Zaragoza",
    "sg:orig_category":"Lencer\u00cda Femenina, Corseter\u00cda, Trajes De Ba\u00d1o (al Por Menor)",
    "sg:phone":"+34 976 21 92 98",
    "sg:postcode":"50008",
    "sg:province":"Zaragoza",
    "wof:name":"Blasco Grauliana Angeles",
    "wof:placetype":"venue"
},
  "geometry": {"coordinates":[-0.882848978,41.6453475952],"type":"Point"}
}