{
  "type": "Feature",
  "properties": {
    "addr:full":"Carrer de Anselm Clave, 62 Granollers Barcelona 08401",
    "addr:housenumber":"62",
    "addr:postcode":"08401",
    "addr:street":"Carrer De Anselm Clave",
    "iso:country":"ES",
    "sg:address":"Carrer de Anselm Clave, 62",
    "sg:city":"Granollers",
    "sg:orig_category":"Centros M\u00c9dicos Y Sociales, Dispensarios",
    "sg:phone":"+34 938 70 56 98",
    "sg:postcode":"08401",
    "sg:province":"Barcelona",
    "wof:name":"Canal Montane Julio",
    "wof:placetype":"venue"
},
  "geometry": {"coordinates":[2.2883880138,41.6063652039],"type":"Point"}
}