{
  "type": "Feature",
  "properties": {
    "addr:full":"Avda Partenon, 8 Madrid Madrid 28042",
    "addr:housenumber":"8",
    "addr:postcode":"madrid;28042",
    "addr:street":"Avda Partenon",
    "iso:country":"ES",
    "sg:address":"Avda Partenon, 8",
    "sg:city":"Madrid",
    "sg:orig_category":"Electr\u00d3nica Profesional: Material Y Componentes (al Por Mayor)",
    "sg:phone":"+34 917 21 07 62",
    "sg:postcode":"28042",
    "sg:province":"Madrid",
    "wof:name":"Future Electronics Distribucion Spain S.l.",
    "wof:placetype":"venue"
},
  "geometry": {"coordinates":[-3.6172308922,40.4632949829],"type":"Point"}
}