{
  "type": "Feature",
  "properties": {
    "addr:full":"Calle de Blanca, S/n Molina Segura Murcia 30500",
    "addr:housenumber":"s",
    "addr:postcode":"30500",
    "addr:street":"Calle De Blanca;/ N Molina",
    "iso:country":"ES",
    "sg:address":"Calle de Blanca, S/n",
    "sg:city":"Molina Segura",
    "sg:orig_category":"Comercio De Hierro",
    "sg:phone":"+34 968 25 20 68",
    "sg:postcode":"30500",
    "sg:province":"Murcia",
    "wof:name":"Hierros Y Suministros Martinez C.b.",
    "wof:placetype":"venue"
},
  "geometry": {"coordinates":[-1.1843403578,38.0378913879],"type":"Point"}
}