{
  "type": "Feature",
  "properties": {
    "addr:full":"Avda Marin, 6 Cangas Pontevedra 36940",
    "addr:housenumber":"6",
    "addr:postcode":"36940",
    "addr:street":"Avda Marin",
    "iso:country":"ES",
    "sg:address":"Avda Marin, 6",
    "sg:city":"Cangas",
    "sg:orig_category":"Droguer\u00cdas (al Por Menor)",
    "sg:phone":"+34 986 30 04 03",
    "sg:postcode":"36940",
    "sg:province":"Pontevedra",
    "wof:name":"Gomez Rodal Jesus",
    "wof:placetype":"venue"
},
  "geometry": {"coordinates":[-8.7793283463,42.2646560669],"type":"Point"}
}