{
  "type": "Feature",
  "properties": {
    "iso:country":"ES",
    "sg:address":"Calle de Jose Maria Martinez Sanchez Arjona, 50",
    "sg:city":"Sevilla",
    "sg:orig_category":"Ropa Para Se\u00d1oras Y Caballeros (al Por Menor)",
    "sg:phone":"+34 954 99 00 48",
    "sg:postcode":"41010",
    "sg:province":"Sevilla",
    "wof:name":"Wu  Xue Yan",
    "wof:placetype":"venue"
},
  "geometry": {"coordinates":[-6.002904892,37.3782615662],"type":"Point"}
}