{
  "type": "Feature",
  "properties": {
    "iso:country":"ES",
    "sg:address":"Calle de Don Hernando De Aragon, 1",
    "sg:city":"Zaragoza",
    "sg:orig_category":"Abogados",
    "sg:phone":"+34 976 23 28 07",
    "sg:postcode":"50001",
    "sg:province":"Zaragoza",
    "wof:name":"Mateo Ayala Eladio",
    "wof:placetype":"venue"
},
  "geometry": {"coordinates":[-0.8764513731,41.6520996094],"type":"Point"}
}