{
  "type": "Feature",
  "properties": {
    "iso:country":"ES",
    "sg:address":"Carr Industria, 19",
    "sg:city":"Tremp",
    "sg:orig_category":"Material Y Herramientas Agr\u00cdcolas",
    "sg:phone":"+34 973 65 23 46",
    "sg:postcode":"25620",
    "sg:province":"Lleida",
    "wof:name":"Ibars Nayach S.l.",
    "wof:placetype":"venue"
},
  "geometry": {"coordinates":[0.8930749893,42.1685028076],"type":"Point"}
}