{
  "type": "Feature",
  "properties": {
    "iso:country":"ES",
    "sg:address":"Avda Laguna (de La), 4",
    "sg:city":"Chipiona",
    "sg:orig_category":"T\u00c9cnicos Veterinarios",
    "sg:phone":"+34 956 37 31 21",
    "sg:postcode":"11550",
    "sg:province":"C\u00e1diz",
    "wof:name":"Ristori Sola Angel Maria",
    "wof:placetype":"venue"
},
  "geometry": {"coordinates":[-6.4354491234,36.7230300903],"type":"Point"}
}