{
  "type": "Feature",
  "properties": {
    "addr:full":"Carrer de Bartomeu Llull, 1 Palma Islas Baleares 07004",
    "addr:housenumber":"1",
    "addr:postcode":"07004",
    "addr:street":"Carrer De Bartomeu Llull",
    "iso:country":"ES",
    "sg:address":"Carrer de Bartomeu Llull, 1",
    "sg:city":"Palma",
    "sg:orig_category":"Transporte En General",
    "sg:phone":"+34 971 75 07 67",
    "sg:postcode":"07004",
    "sg:province":"Islas Baleares",
    "wof:name":"Inmuebles E Inversiones 2002 S.l.",
    "wof:placetype":"venue"
},
  "geometry": {"coordinates":[2.6558749676,39.5913391113],"type":"Point"}
}