{
  "type": "Feature",
  "properties": {
    "iso:country":"ES",
    "sg:address":"Calle de Osuna, 2",
    "sg:city":"Alcala Guadaira",
    "sg:orig_category":"Alimentaci\u00d3n General (al Por Menor)",
    "sg:phone":"+34 954 10 15 03",
    "sg:postcode":"41500",
    "sg:province":"Sevilla",
    "wof:name":"Diaz Munoz Lorenzo",
    "wof:placetype":"venue"
},
  "geometry": {"coordinates":[-5.8417739868,37.3466758728],"type":"Point"}
}