{
  "type": "Feature",
  "properties": {
    "iso:country":"ES",
    "sg:address":"Carrer de Llull, 191",
    "sg:city":"Barcelona",
    "sg:orig_category":"Molduras, Junquillos, Listones Y Molduras Perforadas",
    "sg:phone":"+34 933 00 44 65",
    "sg:postcode":"08005",
    "sg:province":"Barcelona",
    "wof:name":"Serrano Canales Angeles",
    "wof:placetype":"venue"
},
  "geometry": {"coordinates":[2.2024040222,41.4013938904],"type":"Point"}
}