{
  "type": "Feature",
  "properties": {
    "iso:country":"ES",
    "sg:address":"Calle de Cerro Del Casta\u00d1ar, 72",
    "sg:city":"Madrid",
    "sg:orig_category":"Caf\u00c9s, Bares, Cervecer\u00cdas",
    "sg:phone":"+34 913 72 00 58",
    "sg:postcode":"28034",
    "sg:province":"Madrid",
    "wof:name":"Mirasierra S. A.",
    "wof:placetype":"venue"
},
  "geometry": {"coordinates":[-3.7137124538,40.4929466248],"type":"Point"}
}