{
  "type": "Feature",
  "properties": {
    "iso:country":"ES",
    "sg:address":"Calle de Molino (el), 5",
    "sg:city":"Bidankoze",
    "sg:classifiers":[
        {
            "category":"Taxi",
            "type":"Transportation"
        }
    ],
    "sg:phone":"+34 948 47 70 13",
    "sg:postcode":"31413",
    "sg:province":"Navarra",
    "wof:name":"Maria Jose Hualde Mainz",
    "wof:placetype":"venue"
},
  "geometry": {"coordinates":[-1.0146540403,42.8023071289],"type":"Point"}
}