{
  "type": "Feature",
  "properties": {
    "addr:full":"Avda Reyes Catolicos, 18 Burgos Burgos 09005",
    "addr:housenumber":"18",
    "addr:postcode":"09005",
    "addr:street":"Avda Reyes Catolicos",
    "iso:country":"ES",
    "sg:address":"Avda Reyes Catolicos, 18",
    "sg:city":"Burgos",
    "sg:orig_category":"Estancos",
    "sg:phone":"+34 947 22 99 11",
    "sg:postcode":"09005",
    "sg:province":"Burgos",
    "wof:name":"Gallo Manjon Maria Del Carmen",
    "wof:placetype":"venue"
},
  "geometry": {"coordinates":[-3.693764925,42.3467597961],"type":"Point"}
}