{
  "type": "Feature",
  "properties": {
    "iso:country":"ES",
    "sg:address":"Ibarkurutze Plaza, 5",
    "sg:city":"Eibar",
    "sg:orig_category":"Fabricaci\u00d3n De Mobiliario Met\u00c1lico",
    "sg:phone":"+34 943 20 37 15",
    "sg:postcode":"20600",
    "sg:province":"Guip\u00f9zcoa",
    "wof:name":"Martinez Sanllorente Carlos",
    "wof:placetype":"venue"
},
  "geometry": {"coordinates":[-2.4668180943,43.1858863831],"type":"Point"}
}