{
  "type": "Feature",
  "properties": {
    "addr:full":"Avda Castilla, 1 Betanzos La Coru\u00f1a 15300",
    "addr:housenumber":"1",
    "addr:postcode":"15300",
    "addr:street":"Avda Castilla;La",
    "iso:country":"ES",
    "sg:address":"Avda Castilla, 1",
    "sg:city":"Betanzos",
    "sg:orig_category":"Peluqueros: De Se\u00d1oras",
    "sg:phone":"+34 981 77 16 54",
    "sg:postcode":"15300",
    "sg:province":"La Coru\u00f1a",
    "wof:name":"Sanchez Garcia Maria Luisa",
    "wof:placetype":"venue"
},
  "geometry": {"coordinates":[-8.2110843658,43.2798805237],"type":"Point"}
}