{
  "type": "Feature",
  "properties": {
    "iso:country":"ES",
    "sg:address":"Calle de Alvaro De Menda\u00d1o, 36",
    "sg:city":"Playa De Arinaga",
    "sg:orig_category":"Agencias Y Asesores De Publicidad",
    "sg:phone":"+34 928 18 10 56",
    "sg:postcode":"35118",
    "sg:province":"Las Palmas",
    "wof:name":"Ediagora S.l.",
    "wof:placetype":"venue"
},
  "geometry": {"coordinates":[-15.3927698135,27.8557987213],"type":"Point"}
}