{
  "type": "Feature",
  "properties": {
    "iso:country":"ES",
    "sg:address":"Calle de Doctor Velazquez, 25",
    "sg:city":"Segorbe",
    "sg:orig_category":"Inform\u00c1tica (estudios, Servicios, Asesor\u00cda, Formaci\u00d3n)",
    "sg:phone":"+34 964 71 10 78",
    "sg:postcode":"12400",
    "sg:province":"Castell\u00f3n",
    "wof:name":"Infobit Informatica S.l.",
    "wof:placetype":"venue"
},
  "geometry": {"coordinates":[-0.4873530865,39.8487243652],"type":"Point"}
}