{
  "type": "Feature",
  "properties": {
    "addr:full":"Pl Doctor Salo, 2 Berga-ciudad Barcelona 08600",
    "addr:postcode":"08600",
    "addr:street":"Pl Doctor Salo;Berga-Ciudad",
    "iso:country":"ES",
    "sg:address":"Pl Doctor Salo, 2",
    "sg:city":"Berga-ciudad",
    "sg:orig_category":"Partidos Pol\u00cdticos",
    "sg:phone":"+34 938 21 09 62",
    "sg:postcode":"08600",
    "sg:province":"Barcelona",
    "wof:name":"Esquerra Republicana De Catalunya",
    "wof:placetype":"venue"
},
  "geometry": {"coordinates":[1.846683979,42.1042366028],"type":"Point"}
}