{
  "type": "Feature",
  "properties": {
    "iso:country":"ES",
    "sg:address":"Avda Gasteiz, 68",
    "sg:city":"Vitoria-gasteiz",
    "sg:orig_category":"Peluqueros: De Se\u00d1oras",
    "sg:phone":"+34 945 24 12 26",
    "sg:postcode":"01012",
    "sg:province":"\u00c1lava",
    "wof:name":"Fernandez De Landa Jauregui Maria Victoria",
    "wof:placetype":"venue"
},
  "geometry": {"coordinates":[-2.6801350117,42.8517074585],"type":"Point"}
}