{
  "type": "Feature",
  "properties": {
    "addr:full":"Calle de Capitan Mendizabal, 20 Santurtzi Vizcaya 48980",
    "addr:housenumber":"20",
    "addr:postcode":"48980",
    "addr:street":"Calle De Capitan Mendizabal",
    "iso:country":"ES",
    "sg:address":"Calle de Capitan Mendizabal, 20",
    "sg:city":"Santurtzi",
    "sg:orig_category":"Asesor\u00cda Fiscal Y Jur\u00cddica",
    "sg:phone":"+34 944 62 51 94",
    "sg:postcode":"48980",
    "sg:province":"Vizcaya",
    "wof:name":"Audinor Asesores, S.l.",
    "wof:placetype":"venue"
},
  "geometry": {"coordinates":[-3.0347292423,43.3317527771],"type":"Point"}
}