{
  "type": "Feature",
  "properties": {
    "addr:full":"Carrer de Ali Bei, 12 Barcelona Barcelona 08010",
    "addr:housenumber":"12",
    "addr:postcode":"08010",
    "addr:street":"Carrer De Ali Bei",
    "iso:country":"ES",
    "sg:address":"Carrer de Ali Bei, 12",
    "sg:city":"Barcelona",
    "sg:orig_category":"Mec\u00c1nico Del Autom\u00d3vil",
    "sg:phone":"+34 932 46 69 90",
    "sg:postcode":"08010",
    "sg:province":"Barcelona",
    "wof:name":"Valles Murciano Juan",
    "wof:placetype":"venue"
},
  "geometry": {"coordinates":[2.1788470745,41.3918838501],"type":"Point"}
}