{
  "type": "Feature",
  "properties": {
    "addr:full":"Carrer de Sant Francesc, 55 Terrassa Barcelona 08221",
    "addr:housenumber":"55",
    "addr:postcode":"08221",
    "addr:street":"Carrer De Sant Francesc",
    "iso:country":"ES",
    "sg:address":"Carrer de Sant Francesc, 55",
    "sg:city":"Terrassa",
    "sg:orig_category":"Masajistas Kinesiterapeutas",
    "sg:phone":"+34 937 31 05 63",
    "sg:postcode":"08221",
    "sg:province":"Barcelona",
    "wof:name":"Carbonell Cruz Laureana",
    "wof:placetype":"venue"
},
  "geometry": {"coordinates":[2.0132129192,41.5585136414],"type":"Point"}
}