{
  "type": "Feature",
  "properties": {
    "iso:country":"ES",
    "sg:address":"Calle de Real / Errege Kalea, 33",
    "sg:city":"Noain",
    "sg:orig_category":"Mec\u00c1nico Del Autom\u00d3vil",
    "sg:phone":"+34 948 31 70 55",
    "sg:postcode":"31110",
    "sg:province":"Navarra",
    "wof:name":"Colmenero Murias J.a. Y Luque Ramos J. S.cv.",
    "wof:placetype":"venue"
},
  "geometry": {"coordinates":[-1.6338239908,42.7598800659],"type":"Point"}
}