{
  "type": "Feature",
  "properties": {
    "addr:full":"Avda Constitucion, 102 Gijon Asturias 33207",
    "addr:housenumber":"102",
    "addr:postcode":"33207",
    "addr:street":"Avda Constitucion",
    "iso:country":"ES",
    "sg:address":"Avda Constitucion, 102",
    "sg:city":"Gijon",
    "sg:orig_category":"Electrodom\u00c9sticos (al Por Menor)",
    "sg:phone":"+34 985 14 82 46",
    "sg:postcode":"33207",
    "sg:province":"Asturias",
    "wof:name":"Longino Antu\u00f1a Diaz",
    "wof:placetype":"venue"
},
  "geometry": {"coordinates":[-5.6675891876,43.5352592468],"type":"Point"}
}