{
  "type": "Feature",
  "properties": {
    "addr:full":"Carrer de Judici, 1 Barcelona Barcelona 08003",
    "addr:housenumber":"1",
    "addr:postcode":"08003",
    "addr:street":"Carrer De Judici",
    "iso:country":"ES",
    "sg:address":"Carrer de Judici, 1",
    "sg:city":"Barcelona",
    "sg:orig_category":"Reposter\u00cdas",
    "sg:phone":"+34 932 21 87 38",
    "sg:postcode":"08003",
    "sg:province":"Barcelona",
    "wof:name":"Montsito S.l.",
    "wof:placetype":"venue"
},
  "geometry": {"coordinates":[2.1889519691,41.3765411377],"type":"Point"}
}