{
  "type": "Feature",
  "properties": {
    "addr:full":"Calle de Perez Galdos, 13 Alginet Valencia 46230",
    "addr:housenumber":"13",
    "addr:postcode":"46230",
    "addr:street":"Calle De Perez Galdos",
    "iso:country":"ES",
    "sg:address":"Calle de Perez Galdos, 13",
    "sg:city":"Alginet",
    "sg:orig_category":"Heladeros",
    "sg:phone":"+34 961 75 35 83",
    "sg:postcode":"46230",
    "sg:province":"Valencia",
    "wof:name":"Josefina Espi E Hijos C.b.",
    "wof:placetype":"venue"
},
  "geometry": {"coordinates":[-0.4715979993,39.267162323],"type":"Point"}
}