{
  "type": "Feature",
  "properties": {
    "addr:full":"Calle de Henri Dunant, 23 Madrid Madrid 28036",
    "addr:housenumber":"23",
    "addr:postcode":"madrid;28036",
    "addr:street":"Calle De Henri Dunant",
    "iso:country":"ES",
    "sg:address":"Calle de Henri Dunant, 23",
    "sg:city":"Madrid",
    "sg:orig_category":"Abogados",
    "sg:phone":"+34 913 43 18 30",
    "sg:postcode":"28036",
    "sg:province":"Madrid",
    "wof:name":"Equity Labour Abogados S.l.i.",
    "wof:placetype":"venue"
},
  "geometry": {"coordinates":[-3.6834280491,40.4600982666],"type":"Point"}
}