{
  "type": "Feature",
  "properties": {
    "iso:country":"ES",
    "sg:address":"Carr Badia, 4",
    "sg:city":"Ca'n Picafort",
    "sg:orig_category":"Caf\u00c9s, Bares, Cervecer\u00cdas",
    "sg:phone":"+34 971 85 02 49",
    "sg:postcode":"07458",
    "sg:province":"Islas Baleares",
    "wof:name":"Font Ribot Miguel",
    "wof:placetype":"venue"
},
  "geometry": {"coordinates":[2.9117100239,39.6136398315],"type":"Point"}
}