{
  "type": "Feature",
  "properties": {
    "addr:full":"Carrer de Munt, 49 S. Andreu Llavaneres Barcelona 08392",
    "addr:housenumber":"49",
    "addr:postcode":"08392",
    "addr:street":"Carrer De Munt;S. Andreu Llavaneres Barcelona",
    "iso:country":"ES",
    "sg:address":"Carrer de Munt, 49",
    "sg:city":"S. Andreu Llavaneres",
    "sg:orig_category":"Urbanistas",
    "sg:phone":"+34 937 93 01 10",
    "sg:postcode":"08392",
    "sg:province":"Barcelona",
    "wof:name":"Kibou Consulting Sl",
    "wof:placetype":"venue"
},
  "geometry": {"coordinates":[2.4815030098,41.573387146],"type":"Point"}
}