{
  "type": "Feature",
  "properties": {
    "iso:country":"ES",
    "sg:address":"Calle de Muelle, S/n",
    "sg:city":"Castropol",
    "sg:orig_category":"Clubes Y Asociaciones Deportivas Y De Actividades Invernales Y De Monta\u00d1a",
    "sg:phone":"+34 985 63 50 35",
    "sg:postcode":"33760",
    "sg:province":"Asturias",
    "sg:website":"www.iespana.es/remocastrolpol",
    "wof:name":"Club De Mar De Castropol",
    "wof:placetype":"venue"
},
  "geometry": {"coordinates":[-7.0311379433,43.5280418396],"type":"Point"}
}