{
  "type": "Feature",
  "properties": {
    "addr:full":"Calle de San Pedro Y San Felices, 15 Burgos Burgos 09001",
    "addr:housenumber":"15",
    "addr:postcode":"09001",
    "addr:street":"Calle De San;Felices",
    "iso:country":"ES",
    "sg:address":"Calle de San Pedro Y San Felices, 15",
    "sg:city":"Burgos",
    "sg:orig_category":"Transportes Por V\u00cdas Navegables",
    "sg:phone":"+34 947 20 38 41",
    "sg:postcode":"09001",
    "sg:province":"Burgos",
    "wof:name":"Hermoso Mena Jose Antonio",
    "wof:placetype":"venue"
},
  "geometry": {"coordinates":[-3.704087019,42.3328742981],"type":"Point"}
}