{
  "type": "Feature",
  "properties": {
    "iso:country":"ES",
    "sg:address":"Avda Lerida (de), 35",
    "sg:city":"Monzon",
    "sg:orig_category":"Fabricaci\u00d3n, Importaci\u00d3n De Material Y Sistemas De Telecomunicaciones",
    "sg:phone":"+34 974 41 69 66",
    "sg:postcode":"22400",
    "sg:province":"Huesca",
    "wof:name":"B.t. Cel.lular Audio Catalunya S.l.",
    "wof:placetype":"venue"
},
  "geometry": {"coordinates":[0.1972949952,41.9097976685],"type":"Point"}
}