{
  "type": "Feature",
  "properties": {
    "iso:country":"ES",
    "sg:address":"Carr Alemanya, 17",
    "sg:city":"Badalona",
    "sg:orig_category":"Textil",
    "sg:phone":"+34 934 65 15 04",
    "sg:postcode":"08917",
    "sg:province":"Barcelona",
    "wof:name":"Rustic London S.l.",
    "wof:placetype":"venue"
},
  "geometry": {"coordinates":[2.2208199501,41.4580497742],"type":"Point"}
}