{
  "type": "Feature",
  "properties": {
    "addr:full":"Unic, S/n Farrera Lleida 25595",
    "addr:housenumber":"s / n",
    "addr:postcode":"25595",
    "addr:street":"Unic",
    "iso:country":"ES",
    "sg:address":"Unic, S/n",
    "sg:city":"Farrera",
    "sg:orig_category":"Administraciones Regionales, Departamentales Y Locales",
    "sg:phone":"+34 973 62 21 06",
    "sg:postcode":"25595",
    "sg:province":"Lleida",
    "wof:name":"Ajuntament De Farrera",
    "wof:placetype":"venue"
},
  "geometry": {"coordinates":[1.2712956667,42.4973182678],"type":"Point"}
}