{
  "type": "Feature",
  "properties": {
    "addr:full":"Calle de Madrid, 12 Leganes Madrid 28911",
    "addr:housenumber":"12",
    "addr:postcode":"28911",
    "addr:street":"Calle De Madrid",
    "iso:country":"ES",
    "sg:address":"Calle de Madrid, 12",
    "sg:city":"Leganes",
    "sg:orig_category":"Asociaciones Y Clubs Deportivos",
    "sg:phone":"+34 916 80 98 81",
    "sg:postcode":"28911",
    "sg:province":"Madrid",
    "wof:name":"Gimnasio Avenue S.l.",
    "wof:placetype":"venue"
},
  "geometry": {"coordinates":[-3.765417099,40.3300285339],"type":"Point"}
}