{
  "type": "Feature",
  "properties": {
    "iso:country":"ES",
    "sg:address":"Avda Oporto, 65",
    "sg:city":"Madrid",
    "sg:orig_category":"Tiendas De Grano, Frutas Y Legumbres Secas (al Por Menor)",
    "sg:phone":"+34 915 60 81 01",
    "sg:postcode":"28019",
    "sg:province":"Madrid",
    "wof:name":"Cuesta De La Cruz Lidio",
    "wof:placetype":"venue"
},
  "geometry": {"coordinates":[-3.728801012,40.3865737915],"type":"Point"}
}