{
  "type": "Feature",
  "properties": {
    "addr:full":"Lugar Tarahal, 6 Ba\u00f1aderos-san Andres Las Palmas 35414",
    "addr:housenumber":"6",
    "addr:postcode":"35414",
    "addr:street":"Lugar Tarahal;Andres Las",
    "iso:country":"ES",
    "sg:address":"Lugar Tarahal, 6",
    "sg:city":"Ba\u00f1aderos-san Andres",
    "sg:orig_category":"Muebles Y Accesorios Para Cocinas Y Cuartos De Ba\u00d1o (al Por Menor)",
    "sg:phone":"+34 928 62 78 04",
    "sg:postcode":"35414",
    "sg:province":"Las Palmas",
    "wof:name":"Guillen Hernandez Manuel",
    "wof:placetype":"venue"
},
  "geometry": {"coordinates":[-15.5317401886,28.146730423],"type":"Point"}
}