{
  "type": "Feature",
  "properties": {
    "iso:country":"ES",
    "sg:address":"Calle de Lira, 4",
    "sg:city":"Madrid",
    "sg:orig_category":"Agencias Y Agentes Comerciales, Representantes",
    "sg:phone":"+34 915 74 27 55",
    "sg:postcode":"28007",
    "sg:province":"Madrid",
    "wof:name":"Ferrer Lucia\u00f1ez Belen",
    "wof:placetype":"venue"
},
  "geometry": {"coordinates":[-3.6695640087,40.408290863],"type":"Point"}
}