{
  "type": "Feature",
  "properties": {
    "iso:country":"ES",
    "sg:address":"Luis Vives, 3",
    "sg:city":"Puig",
    "sg:orig_category":"Estudios, Instalaci\u00d3n De Climatizaci\u00d3n",
    "sg:phone":"+34 961 47 14 85",
    "sg:postcode":"46540",
    "sg:province":"Valencia",
    "wof:name":"Indufred Climatitzacio S.l.l.",
    "wof:placetype":"venue"
},
  "geometry": {"coordinates":[-0.3024260104,39.5906257629],"type":"Point"}
}