{
  "type": "Feature",
  "properties": {
    "iso:country":"ES",
    "sg:address":"Pg Lluis Companys, 23",
    "sg:city":"S. Pere Ribes",
    "sg:orig_category":"Promotores Constructores",
    "sg:phone":"+34 938 96 22 82",
    "sg:postcode":"08810",
    "sg:province":"Barcelona",
    "wof:name":"Consher Mata S.l.",
    "wof:placetype":"venue"
},
  "geometry": {"coordinates":[1.7682859898,41.2593078613],"type":"Point"}
}