{
  "type": "Feature",
  "properties": {
    "addr:full":"Mundin(s. Xiao), S/n Montoxo La Coru\u00f1a 15359",
    "addr:housenumber":"s / n",
    "addr:postcode":"15359",
    "addr:street":"Mundin;Xiao;La Corun\u0303A",
    "iso:country":"ES",
    "sg:address":"Mundin(s. Xiao), S/n",
    "sg:city":"Montoxo",
    "sg:orig_category":"Confecci\u00d3n (fabricaci\u00d3n, Al Por Mayor)",
    "sg:phone":"+34 981 48 04 06",
    "sg:postcode":"15359",
    "sg:province":"La Coru\u00f1a",
    "wof:name":"Coloro S.l.",
    "wof:placetype":"venue"
},
  "geometry": {"coordinates":[-7.9857058525,43.6447105408],"type":"Point"}
}