{
  "type": "Feature",
  "properties": {
    "addr:full":"Calle de Concha Espina, S/n Cabez\u00f3n Sal Cantabria 39500",
    "addr:housenumber":"s / n",
    "addr:postcode":"39500",
    "addr:street":"Calle De Concha Espina",
    "iso:country":"ES",
    "sg:address":"Calle de Concha Espina, S/n",
    "sg:city":"Cabez\u00f3n Sal",
    "sg:orig_category":"Mec\u00c1nico Del Autom\u00d3vil",
    "sg:phone":"+34 942 70 05 16",
    "sg:postcode":"39500",
    "sg:province":"Cantabria",
    "wof:name":"Rosendo Callejo Juan",
    "wof:placetype":"venue"
},
  "geometry": {"coordinates":[-4.2356123924,43.3096656799],"type":"Point"}
}