{
  "type": "Feature",
  "properties": {
    "iso:country":"ES",
    "sg:address":"Carrer de Moles (d'en), 4",
    "sg:city":"Mataro",
    "sg:orig_category":"Institutos De Belleza",
    "sg:phone":"+34 937 90 74 78",
    "sg:postcode":"08302",
    "sg:province":"Barcelona",
    "wof:name":"Bruguera Codina Adelaida",
    "wof:placetype":"venue"
},
  "geometry": {"coordinates":[2.4432959557,41.5398254395],"type":"Point"}
}