{
  "type": "Feature",
  "properties": {
    "iso:country":"ES",
    "sg:address":"Los Alcornoques, 5",
    "sg:city":"Santander",
    "sg:orig_category":"Farmacias",
    "sg:phone":"+34 942 32 03 66",
    "sg:postcode":"39011",
    "sg:province":"Cantabria",
    "wof:name":"De La Maza Huidobro Mercedes",
    "wof:placetype":"venue"
},
  "geometry": {"coordinates":[-3.8546149731,43.4571609497],"type":"Point"}
}