{
  "type": "Feature",
  "properties": {
    "addr:full":"Carrer de Greco, 1 Palma Islas Baleares 07009",
    "addr:housenumber":"1",
    "addr:postcode":"07009",
    "addr:street":"Carrer De Greco",
    "iso:country":"ES",
    "sg:address":"Carrer de Greco, 1",
    "sg:city":"Palma",
    "sg:orig_category":"Estancos",
    "sg:phone":"+34 971 47 32 76",
    "sg:postcode":"07009",
    "sg:province":"Islas Baleares",
    "wof:name":"Suau Rossello Guillermo",
    "wof:placetype":"venue"
},
  "geometry": {"coordinates":[2.686289072,39.5955162048],"type":"Point"}
}