{
  "type": "Feature",
  "properties": {
    "addr:full":"Rbla Just Oliveras, 6 Hospitalet Llobregat Barcelona 08901",
    "addr:housenumber":"6",
    "addr:postcode":"08901",
    "addr:street":"Rbla Just Oliveras",
    "iso:country":"ES",
    "sg:address":"Rbla Just Oliveras, 6",
    "sg:city":"Hospitalet Llobregat",
    "sg:orig_category":"Zapatos (al Por Menor)",
    "sg:phone":"+34 933 37 81 68",
    "sg:postcode":"08901",
    "sg:province":"Barcelona",
    "wof:name":"Fernandez Martin Vanesa",
    "wof:placetype":"venue"
},
  "geometry": {"coordinates":[2.1019508839,41.3605804443],"type":"Point"}
}