{
  "type": "Feature",
  "properties": {
    "iso:country":"ES",
    "sg:address":"Calle de Arcedianos, 6",
    "sg:city":"Sig\u00fcenza",
    "sg:orig_category":"Administradores De Bienes Y Delegados De Comunidades De Propietarios",
    "sg:phone":"+34 949 39 32 64",
    "sg:postcode":"19250",
    "sg:province":"Guadalajara",
    "wof:name":"Torres Riascos Jair",
    "wof:placetype":"venue"
},
  "geometry": {"coordinates":[-2.6410090923,41.065990448],"type":"Point"}
}