{
  "type": "Feature",
  "properties": {
    "iso:country":"ES",
    "sg:address":"Calle de Postas, 10",
    "sg:city":"Madrid",
    "sg:orig_category":"Confecci\u00d3n De Uniformes",
    "sg:phone":"+34 915 31 86 91",
    "sg:postcode":"28012",
    "sg:province":"Madrid",
    "sg:website":"www.vallesa.com",
    "wof:name":"Vallesa S.l.",
    "wof:placetype":"venue"
},
  "geometry": {"coordinates":[-3.7056589127,40.4161376953],"type":"Point"}
}