{
  "type": "Feature",
  "properties": {
    "iso:country":"ES",
    "sg:address":"Poligono Industrial De Bayas, S/n",
    "sg:city":"Miranda Ebro",
    "sg:orig_category":"Negocio De Madera",
    "sg:phone":"+34 947 31 48 30",
    "sg:postcode":"09200",
    "sg:province":"Burgos",
    "wof:name":"Maderas Vitores S.a.",
    "wof:placetype":"venue"
},
  "geometry": {"coordinates":[-2.916533947,42.6962852478],"type":"Point"}
}