{
  "type": "Feature",
  "properties": {
    "addr:full":"Av Palmeres, 14 Magaluf Islas Baleares 07181",
    "addr:housenumber":"14",
    "addr:postcode":"07181",
    "addr:street":"Av Palmeres",
    "iso:country":"ES",
    "sg:address":"Av Palmeres, 14",
    "sg:city":"Magaluf",
    "sg:orig_category":"Organismos De Turismo",
    "sg:phone":"+34 971 13 21 75",
    "sg:postcode":"07181",
    "sg:province":"Islas Baleares",
    "wof:name":"Sociedad De Servicios De La Asoc.hoteleros Palmanova Magalluf S.l.",
    "wof:placetype":"venue"
},
  "geometry": {"coordinates":[2.5301640034,39.5084838867],"type":"Point"}
}