{
  "type": "Feature",
  "properties": {
    "iso:country":"ES",
    "sg:address":"Calle de Loiola, 4",
    "sg:city":"Donostia-san Sebastian",
    "sg:orig_category":"Cl\u00cdnicas Dentales",
    "sg:phone":"+34 943 42 42 00",
    "sg:postcode":"20005",
    "sg:province":"Guip\u00f9zcoa",
    "wof:name":"Antin Mendizabal Ramon",
    "wof:placetype":"venue"
},
  "geometry": {"coordinates":[-1.9831357002,43.3188095093],"type":"Point"}
}