{
  "type": "Feature",
  "properties": {
    "addr:full":"Plaz Alcolea, 18 Cartagena Murcia 30201",
    "addr:housenumber":"18",
    "addr:postcode":"30201",
    "addr:street":"Alcolea",
    "iso:country":"ES",
    "sg:address":"Plaz Alcolea, 18",
    "sg:city":"Cartagena",
    "sg:orig_category":"Agencias Y Agentes Comerciales, Representantes",
    "sg:phone":"+34 968 50 85 39",
    "sg:postcode":"30201",
    "sg:province":"Murcia",
    "wof:name":"Baraza Laliga Pedro Antonio",
    "wof:placetype":"venue"
},
  "geometry": {"coordinates":[-0.8610739708,37.719329834],"type":"Point"}
}