{
  "type": "Feature",
  "properties": {
    "iso:country":"ES",
    "sg:address":"Avda Carabanchel Alto, 112",
    "sg:city":"Madrid",
    "sg:orig_category":"Empresas De Desmonte",
    "sg:phone":"+34 915 08 93 82",
    "sg:postcode":"28044",
    "sg:province":"Madrid",
    "wof:name":"Servicio De Obras Mtnb S.l.",
    "wof:placetype":"venue"
},
  "geometry": {"coordinates":[-3.753549099,40.3662109375],"type":"Point"}
}