{
  "type": "Feature",
  "properties": {
    "iso:country":"ES",
    "sg:address":"Avda Golf, 24",
    "sg:city":"Mijas Costa",
    "sg:orig_category":"Molduras, Junquillos, Listones Y Molduras Perforadas",
    "sg:phone":"+34 952 93 27 62",
    "sg:postcode":"29649",
    "sg:province":"M\u00e1laga",
    "wof:name":"Cruz Merida Salvador",
    "wof:placetype":"venue"
},
  "geometry": {"coordinates":[-4.7050890923,36.4985466003],"type":"Point"}
}