{
  "type": "Feature",
  "properties": {
    "iso:country":"ES",
    "sg:address":"Calle de General Yag\u00fce, 64",
    "sg:city":"Madrid",
    "sg:orig_category":"M\u00c9dicos: Dermatolog\u00cda Y Venereolog\u00cda",
    "sg:phone":"+34 915 70 99 29",
    "sg:postcode":"28020",
    "sg:province":"Madrid",
    "wof:name":"Nu\u00f1ez-torron Freijo Marcial",
    "wof:placetype":"venue"
},
  "geometry": {"coordinates":[-3.7004289627,40.4573822021],"type":"Point"}
}