{
  "type": "Feature",
  "properties": {
    "addr:full":"Carrer de Prats De Mollo, 2 Barcelona Barcelona 08021",
    "addr:housenumber":"2",
    "addr:postcode":"08021",
    "addr:street":"Carrer De Prats De Mollo",
    "iso:country":"ES",
    "sg:address":"Carrer de Prats De Mollo, 2",
    "sg:city":"Barcelona",
    "sg:orig_category":"Agentes, Concesionarios Y Sucursales De Veh\u00cdculos",
    "sg:phone":"+34 932 01 54 44",
    "sg:postcode":"08021",
    "sg:province":"Barcelona",
    "wof:name":"Motorsol S.a.",
    "wof:placetype":"venue"
},
  "geometry": {"coordinates":[2.1365818977,41.4011878967],"type":"Point"}
}