{
  "type": "Feature",
  "properties": {
    "addr:full":"Rua Nova, 40 Santiago De Compostela A Coru\u00f1a 15705",
    "addr:housenumber":"40",
    "addr:postcode":"15705",
    "addr:street":"Rua Nova;Corun\u0303A",
    "iso:country":"ES",
    "sg:address":"Rua Nova, 40",
    "sg:city":"Santiago De Compostela",
    "sg:orig_category":"Artesan\u00cda",
    "sg:phone":"+34 981 58 97 76",
    "sg:postcode":"15705",
    "sg:province":"A Coru\u00f1a",
    "wof:name":"Soto Albores Miguel",
    "wof:placetype":"venue"
},
  "geometry": {"coordinates":[-8.5440578461,42.8781890869],"type":"Point"}
}