{
  "type": "Feature",
  "properties": {
    "iso:country":"ES",
    "sg:address":"Calle de Villardondiego, 30",
    "sg:city":"Madrid",
    "sg:orig_category":"Electricidad: Instaladores",
    "sg:phone":"+34 917 76 30 51",
    "sg:postcode":"28032",
    "sg:province":"Madrid",
    "wof:name":"Marcos Mu\u00f1oz Arturo",
    "wof:placetype":"venue"
},
  "geometry": {"coordinates":[-3.6084110737,40.4064941406],"type":"Point"}
}