{
  "type": "Feature",
  "properties": {
    "addr:full":"Ctra Sant Adria Del Besos-la Roca, Km. 0015,9 Montornes Centre Barcelona 08170",
    "addr:postcode":"08170",
    "addr:street":"Ctra Sant Adria Del Besos-La Roca Km. 0015,9;Barcelona",
    "iso:country":"ES",
    "sg:address":"Ctra Sant Adria Del Besos-la Roca, Km. 0015,9",
    "sg:city":"Montornes Centre",
    "sg:orig_category":"Goma: Productos De Uso Industrial (fabricaci\u00d3n, Al Por Mayor)",
    "sg:phone":"+34 935 68 29 61",
    "sg:postcode":"08170",
    "sg:province":"Barcelona",
    "wof:name":"Intercauchos Del Valles",
    "wof:placetype":"venue"
},
  "geometry": {"coordinates":[2.2635569572,41.542514801],"type":"Point"}
}