{
  "type": "Feature",
  "properties": {
    "iso:country":"ES",
    "sg:address":"Calle de Rio San Pedro, 10",
    "sg:city":"Oviedo",
    "sg:orig_category":"Muebles, Minoristas",
    "sg:phone":"+34 985 29 36 47",
    "sg:postcode":"33001",
    "sg:province":"Asturias",
    "wof:name":"Garcia Fernandez Antonino Jorge Luis",
    "wof:placetype":"venue"
},
  "geometry": {"coordinates":[-5.851776123,43.3672065735],"type":"Point"}
}