{
  "type": "Feature",
  "properties": {
    "iso:country":"ES",
    "sg:address":"Carrer de Selva, 18",
    "sg:city":"Barcelona",
    "sg:orig_category":"Electrodom\u00c9sticos (al Por Menor)",
    "sg:phone":"+34 933 50 59 77",
    "sg:postcode":"08016",
    "sg:province":"Barcelona",
    "wof:name":"Bohigas Baeta Rafael",
    "wof:placetype":"venue"
},
  "geometry": {"coordinates":[2.1766970158,41.4376907349],"type":"Point"}
}