{
  "type": "Feature",
  "properties": {
    "iso:country":"ES",
    "sg:address":"Calle de Torrejon, 17",
    "sg:city":"Ajalvir",
    "sg:orig_category":"Ferreter\u00cda (diversos)",
    "sg:phone":"+34 918 84 35 24",
    "sg:postcode":"28864",
    "sg:province":"Madrid",
    "wof:name":"Hafele Herrajes Espa\u00f1a S.l.",
    "wof:placetype":"venue"
},
  "geometry": {"coordinates":[-3.4817490578,40.5320587158],"type":"Point"}
}