{
  "type": "Feature",
  "properties": {
    "addr:full":"Carr Miquel Sora, De, 6 Mao Islas Baleares 07702",
    "addr:housenumber":"6",
    "addr:postcode":"07702",
    "addr:street":"Carr Miquel Sora De",
    "iso:country":"ES",
    "sg:address":"Carr Miquel Sora, De, 6",
    "sg:city":"Mao",
    "sg:orig_category":"Inform\u00c1tica, Ofim\u00c1tica (estudios, Asesor\u00cda, Ingenier\u00cda, Formaci\u00d3n)",
    "sg:phone":"+34 971 35 11 29",
    "sg:postcode":"07702",
    "sg:province":"Islas Baleares",
    "wof:name":"Memory Soft S.a.",
    "wof:placetype":"venue"
},
  "geometry": {"coordinates":[4.2668747902,39.8824386597],"type":"Point"}
}