{
  "type": "Feature",
  "properties": {
    "addr:full":"Calle de Padre Vicent, 12 Castellon Castell\u00f3n 12004",
    "addr:housenumber":"12",
    "addr:postcode":"12004",
    "addr:street":"Calle De Padre Vicent",
    "iso:country":"ES",
    "sg:address":"Calle de Padre Vicent, 12",
    "sg:city":"Castellon",
    "sg:orig_category":"Cerrajer\u00cda, Ferrallista",
    "sg:phone":"+34 964 22 61 27",
    "sg:postcode":"12004",
    "sg:province":"Castell\u00f3n",
    "wof:name":"Cortes Valls Luis Antonio",
    "wof:placetype":"venue"
},
  "geometry": {"coordinates":[-0.035321001,39.9903640747],"type":"Point"}
}