{
  "type": "Feature",
  "properties": {
    "iso:country":"ES",
    "sg:address":"Carrer de Josep Miret, 25",
    "sg:city":"Barcelona",
    "sg:orig_category":"Mec\u00c1nica Y Herramientas De Precisi\u00d3n",
    "sg:phone":"+34 933 14 19 88",
    "sg:postcode":"08020",
    "sg:province":"Barcelona",
    "wof:name":"Rivas Vazquez Celso",
    "wof:placetype":"venue"
},
  "geometry": {"coordinates":[2.1988830566,41.4224586487],"type":"Point"}
}