{
  "type": "Feature",
  "properties": {
    "addr:full":"Calle de Agustin Lara, 9 Valencia Valencia 46019",
    "addr:housenumber":"9",
    "addr:postcode":"46019",
    "addr:street":"Calle De Agustin Lara",
    "iso:country":"ES",
    "sg:address":"Calle de Agustin Lara, 9",
    "sg:city":"Valencia",
    "sg:orig_category":"Iglesia Cat\u00d3lica",
    "sg:phone":"+34 963 66 73 54",
    "sg:postcode":"46019",
    "sg:province":"Valencia",
    "wof:name":"Parroquia San Jeronimo",
    "wof:placetype":"venue"
},
  "geometry": {"coordinates":[-0.3719409108,39.4937133789],"type":"Point"}
}