{
  "type": "Feature",
  "properties": {
    "addr:full":"Avda. Constitucion, 15 Moreda Asturias 33670",
    "addr:housenumber":"15",
    "addr:postcode":"33670",
    "addr:street":"Avda. Constitucion",
    "iso:country":"ES",
    "sg:address":"Avda. Constitucion, 15",
    "sg:city":"Moreda",
    "sg:orig_category":"Quincaller\u00cda (al Por Menor)",
    "sg:phone":"+34 985 48 01 13",
    "sg:postcode":"33670",
    "sg:province":"Asturias",
    "wof:name":"Gonzalez Diaz Lourdes",
    "wof:placetype":"venue"
},
  "geometry": {"coordinates":[-5.7376289368,43.1678504944],"type":"Point"}
}