{
  "type": "Feature",
  "properties": {
    "iso:country":"ES",
    "sg:address":"Calle de Carretera De Castro, 8",
    "sg:city":"Cordoba",
    "sg:classifiers":[
        {
            "category":"Manufacturing",
            "subcategory":"Building Materials",
            "type":"Manufacturing & Wholesale Goods"
        }
    ],
    "sg:phone":"+34 957 29 54 80",
    "sg:postcode":"14009",
    "sg:province":"C\u00f3rdoba",
    "sg:tags":[
        "de",
        "industrial",
        "alquiler"
    ],
    "wof:name":"Sanchez Tobaruela Concepcion",
    "wof:placetype":"venue"
},
  "geometry": {"coordinates":[-4.7768201828,37.8723106384],"type":"Point"}
}