{
  "type": "Feature",
  "properties": {
    "addr:full":"Plaz Juan Carlos I, 5 Salteras Sevilla 41909",
    "addr:housenumber":"5",
    "addr:postcode":"41909",
    "addr:street":"Plaz Juan Carlos I",
    "iso:country":"ES",
    "sg:address":"Plaz Juan Carlos I, 5",
    "sg:city":"Salteras",
    "sg:orig_category":"Institutos De Belleza",
    "sg:phone":"+34 955 70 80 48",
    "sg:postcode":"41909",
    "sg:province":"Sevilla",
    "wof:name":"Vazquez Vega Maria Angeles",
    "wof:placetype":"venue"
},
  "geometry": {"coordinates":[-6.1111650467,37.4191436768],"type":"Point"}
}