{
  "type": "Feature",
  "properties": {
    "iso:country":"ES",
    "sg:address":"Calle de Duero (del), 19",
    "sg:city":"Mejorada Campo",
    "sg:orig_category":"Puertas De Acorde\u00d3n Y Flexibles",
    "sg:phone":"+34 916 68 01 25",
    "sg:postcode":"28840",
    "sg:province":"Madrid",
    "wof:name":"Innovaciones Tecnicas De La Madera S.l.",
    "wof:placetype":"venue"
},
  "geometry": {"coordinates":[-3.4859125614,40.3865661621],"type":"Point"}
}