{
  "type": "Feature",
  "properties": {
    "addr:full":"Av. Jose Antonio, 34 Avila \u00c1vila 05001",
    "addr:housenumber":"34",
    "addr:postcode":"05001",
    "addr:street":"Av. Jose Antonio;A\u0301Vila",
    "iso:country":"ES",
    "sg:address":"Av. Jose Antonio, 34",
    "sg:city":"Avila",
    "sg:orig_category":"Frutas Y Legumbres Frescas (al Por Mayor)",
    "sg:phone":"+34 920 22 02 28",
    "sg:postcode":"05001",
    "sg:province":"\u00c1vila",
    "wof:name":"Aceitunas Avila S.l.",
    "wof:placetype":"venue"
},
  "geometry": {"coordinates":[-4.684633255,40.6570701599],"type":"Point"}
}