{
  "type": "Feature",
  "properties": {
    "addr:full":"Calle de Cantareros, 16 Antequera M\u00e1laga 29200",
    "addr:housenumber":"16",
    "addr:postcode":"29200",
    "addr:street":"Calle De Cantareros",
    "iso:country":"ES",
    "sg:address":"Calle de Cantareros, 16",
    "sg:city":"Antequera",
    "sg:orig_category":"Agencias Y Agentes Comerciales, Representantes",
    "sg:phone":"+34 952 70 32 88",
    "sg:postcode":"29200",
    "sg:province":"M\u00e1laga",
    "wof:name":"Can Aereus S.l",
    "wof:placetype":"venue"
},
  "geometry": {"coordinates":[-4.5531749725,37.0215797424],"type":"Point"}
}