{
  "type": "Feature",
  "properties": {
    "addr:full":"Carr Ferrocarril D'alcoi, 80 Gandia Valencia 46700",
    "addr:housenumber":"80",
    "addr:postcode":"46700",
    "addr:street":"Carr Ferrocarril D'Alcoi;Valencia",
    "iso:country":"ES",
    "sg:address":"Carr Ferrocarril D'alcoi, 80",
    "sg:city":"Gandia",
    "sg:orig_category":"Agencias Y Agentes Comerciales, Representantes",
    "sg:phone":"+34 962 95 13 85",
    "sg:postcode":"46700",
    "sg:province":"Valencia",
    "wof:name":"Schugt Hoyer Elisabeth",
    "wof:placetype":"venue"
},
  "geometry": {"coordinates":[-0.1838040054,38.9700546265],"type":"Point"}
}