{
  "type": "Feature",
  "properties": {
    "iso:country":"ES",
    "sg:address":"Pazos, 14",
    "sg:city":"Pazos",
    "sg:orig_category":"Empresas De Limpieza",
    "sg:phone":"+34 986 67 27 05",
    "sg:postcode":"36141",
    "sg:province":"Pontevedra",
    "wof:name":"Carvar Del Valle Maria",
    "wof:placetype":"venue"
},
  "geometry": {"coordinates":[-8.528380394,42.2909584045],"type":"Point"}
}