{
  "type": "Feature",
  "properties": {
    "addr:full":"Calle de Claudio Coello, 31 San Lorenzo De El Escorial Madrid 28200",
    "addr:housenumber":"31",
    "addr:postcode":"28200",
    "addr:street":"Calle De Claudio Coello",
    "iso:country":"ES",
    "sg:address":"Calle de Claudio Coello, 31",
    "sg:city":"San Lorenzo De El Escorial",
    "sg:orig_category":"Electrodom\u00c9sticos (al Por Menor)",
    "sg:phone":"+34 918 90 44 16",
    "sg:postcode":"28200",
    "sg:province":"Madrid",
    "wof:name":"Videotelco S. L.",
    "wof:placetype":"venue"
},
  "geometry": {"coordinates":[-4.1457600594,40.5936355591],"type":"Point"}
}