{
  "type": "Feature",
  "properties": {
    "addr:full":"Baixador Vallvidrera, S/n Barcelona Barcelona 08017",
    "addr:housenumber":"s / n",
    "addr:postcode":"08017",
    "addr:street":"Vallvidrera",
    "iso:country":"ES",
    "sg:address":"Baixador Vallvidrera, S/n",
    "sg:city":"Barcelona",
    "sg:orig_category":"Centros De Educaci\u00d3n Especial",
    "sg:phone":"+34 932 04 92 10",
    "sg:postcode":"08017",
    "sg:province":"Barcelona",
    "wof:name":"Ajuntament De Barcelona",
    "wof:placetype":"venue"
},
  "geometry": {"coordinates":[2.097288847,41.4197845459],"type":"Point"}
}