{
  "type": "Feature",
  "properties": {
    "addr:full":"Calle de Diputado L.jimenez Morel, S/n Alacant Alicante 03014",
    "addr:housenumber":"s / n",
    "addr:postcode":"03014",
    "addr:street":"Calle De Diputado L.Jimenez Morel",
    "iso:country":"ES",
    "sg:address":"Calle de Diputado L.jimenez Morel, S/n",
    "sg:city":"Alacant",
    "sg:orig_category":"Peluqueros: De Se\u00d1oras",
    "sg:phone":"+34 965 24 45 23",
    "sg:postcode":"03014",
    "sg:province":"Alicante",
    "wof:name":"De La Puerta Palomino Palmira",
    "wof:placetype":"venue"
},
  "geometry": {"coordinates":[-0.4804914892,38.3697052002],"type":"Point"}
}