{
  "type": "Feature",
  "properties": {
    "addr:full":"Avda Lorca, 129 Sangonera Seca Murcia 30835",
    "addr:housenumber":"129",
    "addr:postcode":"30835",
    "addr:street":"Avda Lorca",
    "iso:country":"ES",
    "sg:address":"Avda Lorca, 129",
    "sg:city":"Sangonera Seca",
    "sg:orig_category":"Lateros",
    "sg:phone":"+34 968 80 50 73",
    "sg:postcode":"30835",
    "sg:province":"Murcia",
    "wof:name":"Metales Y Derivados Xxi S.l.",
    "wof:placetype":"venue"
},
  "geometry": {"coordinates":[-1.2283860445,37.9600410461],"type":"Point"}
}