{
  "type": "Feature",
  "properties": {
    "addr:full":"Carrer de Marti I Alsina, 1 Barcelona Barcelona 08031",
    "addr:housenumber":"1",
    "addr:postcode":"08031",
    "addr:street":"Carrer De Marti I Alsina",
    "iso:country":"ES",
    "sg:address":"Carrer de Marti I Alsina, 1",
    "sg:city":"Barcelona",
    "sg:orig_category":"Sales (al Por Mayor)",
    "sg:phone":"+34 933 57 11 16",
    "sg:postcode":"08031",
    "sg:province":"Barcelona",
    "wof:name":"Universo Natural S.l.l.",
    "wof:placetype":"venue"
},
  "geometry": {"coordinates":[2.1604619026,41.4318122864],"type":"Point"}
}