{
  "type": "Feature",
  "properties": {
    "addr:full":"Calle de Doctor Romagosa, 11 Valencia Valencia 46002",
    "addr:housenumber":"11",
    "addr:postcode":"46002",
    "addr:street":"Calle De Doctor Romagosa",
    "iso:country":"ES",
    "sg:address":"Calle de Doctor Romagosa, 11",
    "sg:city":"Valencia",
    "sg:orig_category":"Abogados",
    "sg:phone":"+34 963 50 90 90",
    "sg:postcode":"46002",
    "sg:province":"Valencia",
    "wof:name":"Badimon Foix Prieto, Estudio Juridico C.b.",
    "wof:placetype":"venue"
},
  "geometry": {"coordinates":[-0.3724524975,39.4704170227],"type":"Point"}
}