{
  "type": "Feature",
  "properties": {
    "iso:country":"ES",
    "sg:address":"Carr Botanico Cavanilles, 8",
    "sg:city":"Oliva",
    "sg:orig_category":"Molduras, Junquillos, Listones Y Molduras Perforadas",
    "sg:phone":"+34 962 83 80 30",
    "sg:postcode":"46780",
    "sg:province":"Valencia",
    "wof:name":"Blasco Lazaro Irineo",
    "wof:placetype":"venue"
},
  "geometry": {"coordinates":[-0.1229790002,38.9225845337],"type":"Point"}
}