{
  "type": "Feature",
  "properties": {
    "addr:full":"Carrer de Major, 23 Serra D'almos Tarragona 43746",
    "addr:housenumber":"23",
    "addr:postcode":"43746",
    "addr:street":"Carrer De Major",
    "iso:country":"ES",
    "sg:address":"Carrer de Major, 23",
    "sg:city":"Serra D'almos",
    "sg:orig_category":"Productores Recolectores, Venta Directa De Vinos",
    "sg:phone":"+34 977 41 81 25",
    "sg:postcode":"43746",
    "sg:province":"Tarragona",
    "wof:name":"Cooperativa Agricola Y Caja Rural",
    "wof:placetype":"venue"
},
  "geometry": {"coordinates":[1.2789340019,41.1215934753],"type":"Point"}
}