{
  "type": "Feature",
  "properties": {
    "addr:full":"Plaz Espa\u00d1a (de), 9 Medina-sidonia C\u00e1diz 11170",
    "addr:postcode":"11170",
    "addr:street":"Plaz;Medina-Sidonia Ca\u0301Diz",
    "iso:country":"ES",
    "sg:address":"Plaz Espa\u00d1a (de), 9",
    "sg:city":"Medina-sidonia",
    "sg:orig_category":"Inmobiliaria (agencias)",
    "sg:phone":"+34 956 41 13 55",
    "sg:postcode":"11170",
    "sg:province":"C\u00e1diz",
    "wof:name":"Hogar Sol 2000 S.l.",
    "wof:placetype":"venue"
},
  "geometry": {"coordinates":[-5.9276151657,36.4568939209],"type":"Point"}
}