{
  "type": "Feature",
  "properties": {
    "addr:full":"Ctra Madrid-coru\u00d1a, S/n Tordesillas Valladolid 47100",
    "addr:housenumber":"s / n",
    "addr:postcode":"47100",
    "addr:street":"Ctra Madrid-Corun\u0303A",
    "iso:country":"ES",
    "sg:address":"Ctra Madrid-coru\u00d1a, S/n",
    "sg:city":"Tordesillas",
    "sg:orig_category":"Venta, Montaje De Neum\u00c1ticos",
    "sg:phone":"+34 983 77 17 41",
    "sg:postcode":"47100",
    "sg:province":"Valladolid",
    "wof:name":"Hermanos Martinez Garcia Cb",
    "wof:placetype":"venue"
},
  "geometry": {"coordinates":[-5.000743866,41.497543335],"type":"Point"}
}