{
  "type": "Feature",
  "properties": {
    "iso:country":"ES",
    "sg:address":"Calle de Hilarion Eslava, 13",
    "sg:city":"Madrid",
    "sg:orig_category":"Colorantes, Colores Y Pigmentos (fabricaci\u00d3n, Al Por Mayor)",
    "sg:phone":"+34 915 43 62 37",
    "sg:postcode":"28015",
    "sg:province":"Madrid",
    "wof:name":"Fernandez Rodriguez Dolores",
    "wof:placetype":"venue"
},
  "geometry": {"coordinates":[-3.7169780731,40.4329414368],"type":"Point"}
}