{
  "type": "Feature",
  "properties": {
    "iso:country":"ES",
    "sg:address":"Uno, 28",
    "sg:city":"Bu\u00f1ol",
    "sg:orig_category":"M\u00c1rmoles, Granitos Y Piedras Naturales",
    "sg:phone":"+34 962 50 31 84",
    "sg:postcode":"46360",
    "sg:province":"Valencia",
    "wof:name":"Marmoles Fayos Y Perello S.c.p.",
    "wof:placetype":"venue"
},
  "geometry": {"coordinates":[-0.7807189822,39.4275932312],"type":"Point"}
}