{
  "type": "Feature",
  "properties": {
    "iso:country":"ES",
    "sg:address":"Rua Concepcion Arenal, 57",
    "sg:city":"Lugo",
    "sg:classifiers":[
        {
            "category":"Cinema",
            "subcategory":"Movie Theater",
            "type":"Entertainment"
        }
    ],
    "sg:phone":"+34 982 24 37 19",
    "sg:postcode":"27004",
    "sg:province":"Lugo",
    "sg:tags":[
        "salas",
        "de",
        "cine"
    ],
    "wof:name":"Grupo Fotocinematografico Fonmi\u00f1a",
    "wof:placetype":"venue"
},
  "geometry": {"coordinates":[-7.5616688728,43.0142631531],"type":"Point"}
}