{
  "type": "Feature",
  "properties": {
    "iso:country":"ES",
    "sg:address":"Carr Marcel.li Gene, 24",
    "sg:city":"Vilanova I La Geltru",
    "sg:orig_category":"Pintura Industrial (trabajos De)",
    "sg:phone":"+34 938 14 01 31",
    "sg:postcode":"08800",
    "sg:province":"Barcelona",
    "wof:name":"Pintasit S.l.",
    "wof:placetype":"venue"
},
  "geometry": {"coordinates":[1.7344009876,41.2298660278],"type":"Point"}
}