{
  "type": "Feature",
  "properties": {
    "addr:full":"Manuel Rodriguez Manolete, 2 Montilla C\u00f3rdoba 14550",
    "addr:housenumber":"2",
    "addr:postcode":"14550",
    "addr:street":"Manuel Rodriguez Manolete;Co\u0301Rdoba",
    "iso:country":"ES",
    "sg:address":"Manuel Rodriguez Manolete, 2",
    "sg:city":"Montilla",
    "sg:orig_category":"Electricidad: Instaladores",
    "sg:phone":"+34 957 65 47 01",
    "sg:postcode":"14550",
    "sg:province":"C\u00f3rdoba",
    "wof:name":"Herrador Cobos Miguel",
    "wof:placetype":"venue"
},
  "geometry": {"coordinates":[-4.6404590607,37.58177948],"type":"Point"}
}