{
  "type": "Feature",
  "properties": {
    "iso:country":"ES",
    "sg:address":"Plaz Puerta De Jerez, 4",
    "sg:city":"Sevilla",
    "sg:orig_category":"Delegados, Agentes De Tr\u00c1nsito, Auxiliares De Transporte Internacional",
    "sg:phone":"+34 954 21 69 91",
    "sg:postcode":"41001",
    "sg:province":"Sevilla",
    "wof:name":"Asociacion Empresarial De Agencias De Transportes Carga Completa",
    "wof:placetype":"venue"
},
  "geometry": {"coordinates":[-5.9936928749,37.3823280334],"type":"Point"}
}