{
  "type": "Feature",
  "properties": {
    "iso:country":"ES",
    "sg:address":"Currelos, S/n",
    "sg:city":"Currelos",
    "sg:orig_category":"Fabricaci\u00d3n De Productos L\u00c1cteos Y Derivados",
    "sg:phone":"+34 982 45 03 07",
    "sg:postcode":"27543",
    "sg:province":"Lugo",
    "wof:name":"Leira Scg",
    "wof:placetype":"venue"
},
  "geometry": {"coordinates":[-7.6479578018,42.6783103943],"type":"Point"}
}