{
  "type": "Feature",
  "properties": {
    "addr:full":"Calle de Olimpico Francisco Fernandez Ochoa, S/n Alcorcon Madrid 28923",
    "addr:housenumber":"s / n",
    "addr:postcode":"28923",
    "addr:street":"Calle De Olimpico Francisco Fernandez Ochoa",
    "iso:country":"ES",
    "sg:address":"Calle de Olimpico Francisco Fernandez Ochoa, S/n",
    "sg:city":"Alcorcon",
    "sg:orig_category":"Arreglo, Instalaci\u00d3n Y Acondicionamiento De Talleres",
    "sg:phone":"+34 916 44 43 69",
    "sg:postcode":"28923",
    "sg:province":"Madrid",
    "wof:name":"Ayuntamiento De Alcorcon",
    "wof:placetype":"venue"
},
  "geometry": {"coordinates":[-3.8161017895,40.3413963318],"type":"Point"}
}