{
  "type": "Feature",
  "properties": {
    "iso:country":"ES",
    "sg:address":"Torrelarragoiti Parcela 5, 2 H",
    "sg:city":"Zamudio",
    "sg:orig_category":"Parques Para Contenedores",
    "sg:phone":"+34 944 52 09 16",
    "sg:postcode":"48170",
    "sg:province":"Vizcaya",
    "wof:name":"Carrocerias Aitor Sl",
    "wof:placetype":"venue"
},
  "geometry": {"coordinates":[-2.8633139133,43.280834198],"type":"Point"}
}