{
  "type": "Feature",
  "properties": {
    "iso:country":"ES",
    "sg:address":"Calle de Corella, 7",
    "sg:city":"Segorbe",
    "sg:orig_category":"Barbacoas Y Accesorios",
    "sg:phone":"+34 964 71 03 97",
    "sg:postcode":"12400",
    "sg:province":"Castell\u00f3n",
    "wof:name":"Perez Catalan Maria Trinidad",
    "wof:placetype":"venue"
},
  "geometry": {"coordinates":[-0.4892952144,39.8519210815],"type":"Point"}
}