{
  "type": "Feature",
  "properties": {
    "iso:country":"ES",
    "sg:address":"Calle de Madrid, 8",
    "sg:city":"Santander",
    "sg:orig_category":"Administradores De Bienes Y Delegados De Comunidades De Propietarios",
    "sg:phone":"+34 942 31 26 92",
    "sg:postcode":"39009",
    "sg:province":"Cantabria",
    "wof:name":"Gama Administracion Y Servicios S.l.",
    "wof:placetype":"venue"
},
  "geometry": {"coordinates":[-3.81072402,43.4574050903],"type":"Point"}
}