{
  "type": "Feature",
  "properties": {
    "iso:country":"ES",
    "sg:address":"Ctra Boadilla-majadahonda (de), 46",
    "sg:city":"Boadilla Del Monte",
    "sg:orig_category":"Inform\u00c1tica (estudios, Servicios, Asesor\u00cda, Formaci\u00d3n)",
    "sg:phone":"+34 916 32 21 11",
    "sg:postcode":"28660",
    "sg:province":"Madrid",
    "sg:website":"www.girasl.com",
    "wof:name":"Gestion Informatica Del Automovil S.l.",
    "wof:placetype":"venue"
},
  "geometry": {"coordinates":[-3.8803789616,40.4084815979],"type":"Point"}
}