{
  "type": "Feature",
  "properties": {
    "iso:country":"ES",
    "sg:address":"Vgen Buen Acuerdo, 43",
    "sg:city":"Zaragoza",
    "sg:orig_category":"Muebles",
    "sg:phone":"+34 976 47 43 27",
    "sg:postcode":"50014",
    "sg:province":"Zaragoza",
    "wof:name":"Ferrer Sanmartin Alvaro",
    "wof:placetype":"venue"
},
  "geometry": {"coordinates":[-0.861040175,41.6785888672],"type":"Point"}
}