{
  "type": "Feature",
  "properties": {
    "iso:country":"ES",
    "sg:address":"Calle de Miguel Indurain, 11",
    "sg:city":"Maracena",
    "sg:orig_category":"Impuestos, Tesoro P\u00dablico",
    "sg:phone":"+34 958 41 50 69",
    "sg:postcode":"18200",
    "sg:province":"Granada",
    "wof:name":"Montes E Hijo C.b.",
    "wof:placetype":"venue"
},
  "geometry": {"coordinates":[-3.6268639565,37.2102813721],"type":"Point"}
}