{
  "type": "Feature",
  "properties": {
    "addr:full":"Poli Noain-esquiroz/noain-esquiroz Industrialdea, S/n Noain Navarra 31110",
    "addr:housenumber":"s",
    "addr:postcode":"31110",
    "addr:street":"Industrialdea;/ N",
    "iso:country":"ES",
    "sg:address":"Poli Noain-esquiroz/noain-esquiroz Industrialdea, S/n",
    "sg:city":"Noain",
    "sg:orig_category":"Empresas De Carpinter\u00cda Met\u00c1lica",
    "sg:phone":"+34 948 31 71 00",
    "sg:postcode":"31110",
    "sg:province":"Navarra",
    "wof:name":"Gabasan S.l.",
    "wof:placetype":"venue"
},
  "geometry": {"coordinates":[-1.5935460329,42.7209968567],"type":"Point"}
}