{
  "type": "Feature",
  "properties": {
    "iso:country":"ES",
    "sg:address":"Carrer de Llull, 63",
    "sg:city":"Barcelona",
    "sg:orig_category":"Mec\u00c1nico Del Autom\u00d3vil",
    "sg:phone":"+34 933 00 26 67",
    "sg:postcode":"08005",
    "sg:province":"Barcelona",
    "wof:name":"Morlans Lopez Maria Teresa Mercedes",
    "wof:placetype":"venue"
},
  "geometry": {"coordinates":[2.1929318905,41.3944168091],"type":"Point"}
}