{
  "type": "Feature",
  "properties": {
    "addr:full":"Cra. Cornella A Fogars De Tordera, 33 S. Vicen\u00e7 Montalt Barcelona 08394",
    "addr:housenumber":"33",
    "addr:postcode":"08394",
    "addr:street":"Tordera;S. Vicenc\u0327 Montalt Barcelona",
    "iso:country":"ES",
    "sg:address":"Cra. Cornella A Fogars De Tordera, 33",
    "sg:city":"S. Vicen\u00e7 Montalt",
    "sg:orig_category":"Ahumados Y Salazones",
    "sg:phone":"+34 937 91 36 80",
    "sg:postcode":"08394",
    "sg:province":"Barcelona",
    "sg:website":"www.carpie.es",
    "wof:name":"Carlos Piernas Del Amor S.l.",
    "wof:placetype":"venue"
},
  "geometry": {"coordinates":[2.5097959042,41.5818634033],"type":"Point"}
}