{
  "type": "Feature",
  "properties": {
    "addr:full":"C/ Sant Antoni, De, 14 S. Antoni Portmany Islas Baleares 07820",
    "addr:housenumber":"14",
    "addr:postcode":"07820",
    "addr:street":"C / Sant Antoni De",
    "iso:country":"ES",
    "sg:address":"C/ Sant Antoni, De, 14",
    "sg:city":"S. Antoni Portmany",
    "sg:orig_category":"Ropa Para Beb\u00c9s Y Ni\u00d1os (confecci\u00d3n, Al Por Mayor)",
    "sg:phone":"+34 971 34 07 49",
    "sg:postcode":"07820",
    "sg:province":"Islas Baleares",
    "wof:name":"Xicu C.b.",
    "wof:placetype":"venue"
},
  "geometry": {"coordinates":[1.3011090755,38.9820594788],"type":"Point"}
}