{
  "type": "Feature",
  "properties": {
    "iso:country":"ES",
    "sg:address":"Pase Flores (de Las), 42",
    "sg:city":"Coslada",
    "sg:orig_category":"Mudanzas",
    "sg:phone":"+34 916 71 06 79",
    "sg:postcode":"28820",
    "sg:province":"Madrid",
    "wof:name":"Mudanzas Alce S. A.",
    "wof:placetype":"venue"
},
  "geometry": {"coordinates":[-3.5645070076,40.4260902405],"type":"Point"}
}