{
  "type": "Feature",
  "properties": {
    "addr:full":"Calle de Galicia, 13 Ciudad Quesada Alicante 03170",
    "addr:housenumber":"13",
    "addr:postcode":"03170",
    "addr:street":"Calle De Galicia",
    "iso:country":"ES",
    "sg:address":"Calle de Galicia, 13",
    "sg:city":"Ciudad Quesada",
    "sg:orig_category":"Promotores Constructores",
    "sg:phone":"+34 966 71 73 26",
    "sg:postcode":"03170",
    "sg:province":"Alicante",
    "wof:name":"Mitsegal S.l.",
    "wof:placetype":"venue"
},
  "geometry": {"coordinates":[-0.7269973159,38.0622901917],"type":"Point"}
}