{
  "type": "Feature",
  "properties": {
    "addr:full":"Avda Ramon Carande, 15 Sevilla Sevilla 41013",
    "addr:housenumber":"15",
    "addr:postcode":"41013",
    "addr:street":"Avda Ramon Carande",
    "iso:country":"ES",
    "sg:address":"Avda Ramon Carande, 15",
    "sg:city":"Sevilla",
    "sg:orig_category":"M\u00c9dicos: Estomatolog\u00cda",
    "sg:phone":"+34 954 62 67 06",
    "sg:postcode":"41013",
    "sg:province":"Sevilla",
    "wof:name":"Queralto Hernandez Jose",
    "wof:placetype":"venue"
},
  "geometry": {"coordinates":[-5.9785571098,37.3736343384],"type":"Point"}
}