{
  "type": "Feature",
  "properties": {
    "addr:full":"Calle de Torrelaguna, 10 Alcala Henares Madrid 28806",
    "addr:housenumber":"10",
    "addr:postcode":"28806",
    "addr:street":"Calle De Torrelaguna",
    "iso:country":"ES",
    "sg:address":"Calle de Torrelaguna, 10",
    "sg:city":"Alcala Henares",
    "sg:orig_category":"Muebles Y Accesorios Para Cocinas Y Cuartos De Ba\u00d1o (al Por Menor)",
    "sg:phone":"+34 918 82 87 55",
    "sg:postcode":"28806",
    "sg:province":"Madrid",
    "wof:name":"Blanco Hoyuelos Cristina",
    "wof:placetype":"venue"
},
  "geometry": {"coordinates":[-3.3707740307,40.4881591797],"type":"Point"}
}