{
  "type": "Feature",
  "properties": {
    "addr:full":"Rua Choupana (da), 21 Santiago De Compostela La Coru\u00f1a 15706",
    "addr:housenumber":"21",
    "addr:postcode":"15706",
    "addr:street":"Rua Choupana Da;Corun\u0303A",
    "iso:country":"ES",
    "sg:address":"Rua Choupana (da), 21",
    "sg:city":"Santiago De Compostela",
    "sg:orig_category":"Prot\u00c9sicos Dentales",
    "sg:phone":"+34 981 52 26 51",
    "sg:postcode":"15706",
    "sg:province":"La Coru\u00f1a",
    "wof:name":"Saenz-diez Belin Jose Maria",
    "wof:placetype":"venue"
},
  "geometry": {"coordinates":[-8.5610818863,42.8680381775],"type":"Point"}
}