{
  "type": "Feature",
  "properties": {
    "addr:full":"Avgd Pius Xii, 27 Lleida Lleida 25003",
    "addr:housenumber":"27",
    "addr:postcode":"25003",
    "iso:country":"ES",
    "sg:address":"Avgd Pius Xii, 27",
    "sg:city":"Lleida",
    "sg:orig_category":"Muebles, Minoristas",
    "sg:phone":"+34 973 26 14 59",
    "sg:postcode":"25003",
    "sg:province":"Lleida",
    "wof:name":"Moscatel Fis Isaac",
    "wof:placetype":"venue"
},
  "geometry": {"coordinates":[0.612737,41.6136779785],"type":"Point"}
}