{
  "type": "Feature",
  "properties": {
    "addr:full":"Stos. Piedra, 15 Quatretonda Valencia 46837",
    "addr:housenumber":"15",
    "addr:postcode":"46837",
    "addr:street":"Piedra",
    "iso:country":"ES",
    "sg:address":"Stos. Piedra, 15",
    "sg:city":"Quatretonda",
    "sg:orig_category":"Relojer\u00cda (al Por Menor, Reparaci\u00d3n)",
    "sg:phone":"+34 962 26 45 50",
    "sg:postcode":"46837",
    "sg:province":"Valencia",
    "wof:name":"Oltra Cara\u00f1ana Emilio",
    "wof:placetype":"venue"
},
  "geometry": {"coordinates":[-0.4039700031,38.94739151],"type":"Point"}
}