{
  "type": "Feature",
  "properties": {
    "addr:full":"Calle de Diego De Ria\u00d1o, 5 Sevilla Sevilla 41004",
    "addr:housenumber":"5",
    "addr:postcode":"41004",
    "addr:street":"Calle De Diego De Rian\u0303O",
    "iso:country":"ES",
    "sg:address":"Calle de Diego De Ria\u00d1o, 5",
    "sg:city":"Sevilla",
    "sg:orig_category":"Sociedades, Compa\u00d1\u00cdas Aseguradoras",
    "sg:phone":"+34 954 53 94 92",
    "sg:postcode":"41004",
    "sg:province":"Sevilla",
    "sg:website":"www.mgs.es",
    "wof:name":"Mutua General Seguros",
    "wof:placetype":"venue"
},
  "geometry": {"coordinates":[-5.9847798347,37.3798522949],"type":"Point"}
}