{
  "type": "Feature",
  "properties": {
    "iso:country":"ES",
    "sg:address":"Pase Delicias, 78",
    "sg:city":"Santa Lucia",
    "sg:orig_category":"Electricidad, Electr\u00d3nica: Material Y Suministros (al Por Mayor)",
    "sg:phone":"+34 968 12 33 01",
    "sg:postcode":"30202",
    "sg:province":"Murcia",
    "wof:name":"Lopez Mu\u00f1oz Carmelo",
    "wof:placetype":"venue"
},
  "geometry": {"coordinates":[-1.1302499771,37.9829597473],"type":"Point"}
}