{
  "type": "Feature",
  "properties": {
    "addr:full":"Avda Vincenti, 5 Cangas Pontevedra 36940",
    "addr:housenumber":"5",
    "addr:postcode":"36940",
    "addr:street":"Avda Vincenti",
    "iso:country":"ES",
    "sg:address":"Avda Vincenti, 5",
    "sg:city":"Cangas",
    "sg:orig_category":"Confecci\u00d3n De Trajes Para Se\u00d1oras",
    "sg:phone":"+34 986 30 11 27",
    "sg:postcode":"36940",
    "sg:province":"Pontevedra",
    "wof:name":"Garcia Garcia-bravo Indalecio Miguel De Los Angele",
    "wof:placetype":"venue"
},
  "geometry": {"coordinates":[-8.7839727402,42.3253364563],"type":"Point"}
}