{
  "type": "Feature",
  "properties": {
    "addr:full":"Lintzirin Poligonoa, 3 Arragua Guip\u00f9zcoa 20180",
    "addr:housenumber":"3",
    "addr:postcode":"20180",
    "addr:street":"Lintzirin Poligonoa;Guipu\u0300Zcoa",
    "iso:country":"ES",
    "sg:address":"Lintzirin Poligonoa, 3",
    "sg:city":"Arragua",
    "sg:orig_category":"Producci\u00d3n, Distribuci\u00d3n De Gas Butano Y Propano",
    "sg:phone":"+34 943 49 19 69",
    "sg:postcode":"20180",
    "sg:province":"Guip\u00f9zcoa",
    "wof:name":"Repsol Ypf S.a.",
    "wof:placetype":"venue"
},
  "geometry": {"coordinates":[-1.8629590273,43.2992401123],"type":"Point"}
}