{
  "type": "Feature",
  "properties": {
    "iso:country":"ES",
    "sg:address":"Carrer de Miquel Marti I Pol, 1",
    "sg:city":"Prat Llobregat",
    "sg:orig_category":"Papeler\u00cdas, Librer\u00cdas",
    "sg:phone":"+34 934 78 41 64",
    "sg:postcode":"08820",
    "sg:province":"Barcelona",
    "wof:name":"Barros Araujo Vicenta",
    "wof:placetype":"venue"
},
  "geometry": {"coordinates":[2.1051659584,41.3276138306],"type":"Point"}
}