{
  "type": "Feature",
  "properties": {
    "addr:full":"Calle de Barrios, S/n Fuenlabrada Madrid 28947",
    "addr:housenumber":"s / n",
    "addr:postcode":"28947",
    "addr:street":"Calle De Barrios",
    "iso:country":"ES",
    "sg:address":"Calle de Barrios, S/n",
    "sg:city":"Fuenlabrada",
    "sg:orig_category":"Empresas De Carpinter\u00cda Met\u00c1lica",
    "sg:phone":"+34 916 42 08 92",
    "sg:postcode":"28947",
    "sg:province":"Madrid",
    "wof:name":"Inoxidables M.c.r. S.a.",
    "wof:placetype":"venue"
},
  "geometry": {"coordinates":[-3.7476704121,40.2565231323],"type":"Point"}
}