{
  "type": "Feature",
  "properties": {
    "iso:country":"ES",
    "sg:address":"Doctor Juaristi, 1",
    "sg:city":"Iru\u00f1a",
    "sg:orig_category":"Centros De Educaci\u00d3n Especial",
    "sg:phone":"+34 948 17 56 13",
    "sg:postcode":"31012",
    "sg:province":"Navarra",
    "wof:name":"Ayuntamiento De Pamplona",
    "wof:placetype":"venue"
},
  "geometry": {"coordinates":[-1.6661047935,42.8202209473],"type":"Point"}
}