{
  "type": "Feature",
  "properties": {
    "addr:full":"Calle de Maestro Francisco Vallejos, 8 Torrevieja Alicante 03180",
    "addr:housenumber":"8",
    "addr:postcode":"03180",
    "addr:street":"Calle De Maestro Francisco Vallejos",
    "iso:country":"ES",
    "sg:address":"Calle de Maestro Francisco Vallejos, 8",
    "sg:city":"Torrevieja",
    "sg:orig_category":"Tintes (fabricaci\u00d3n, Al Por Mayor)",
    "sg:phone":"+34 966 70 49 17",
    "sg:postcode":"03180",
    "sg:province":"Alicante",
    "wof:name":"Lopez Samper Josefa Maria",
    "wof:placetype":"venue"
},
  "geometry": {"coordinates":[-0.6822088957,37.9782333374],"type":"Point"}
}