{
  "type": "Feature",
  "properties": {
    "addr:full":"Calle de Galileo, 25 Madrid Madrid 28015",
    "addr:housenumber":"25",
    "addr:postcode":"madrid;28015",
    "addr:street":"Calle De Galileo",
    "iso:country":"ES",
    "sg:address":"Calle de Galileo, 25",
    "sg:city":"Madrid",
    "sg:orig_category":"Procuradores",
    "sg:phone":"+34 914 47 09 01",
    "sg:postcode":"28015",
    "sg:province":"Madrid",
    "wof:name":"Vazquez Guillen Argimiro",
    "wof:placetype":"venue"
},
  "geometry": {"coordinates":[-3.7104051113,40.4323768616],"type":"Point"}
}