{
  "type": "Feature",
  "properties": {
    "addr:full":"Urbanizacion Villas Blancas, 1 Los Belones Murcia 30385",
    "addr:housenumber":"1",
    "addr:postcode":"30385",
    "addr:street":"Villas Blancas;Los",
    "iso:country":"ES",
    "sg:address":"Urbanizacion Villas Blancas, 1",
    "sg:city":"Los Belones",
    "sg:orig_category":"Confecci\u00d3n (fabricaci\u00d3n, Al Por Mayor)",
    "sg:phone":"+34 968 13 73 87",
    "sg:postcode":"30385",
    "sg:province":"Murcia",
    "wof:name":"Perez Hernandez Rosendo",
    "wof:placetype":"venue"
},
  "geometry": {"coordinates":[-0.7349190116,37.6258811951],"type":"Point"}
}