{
  "type": "Feature",
  "properties": {
    "iso:country":"ES",
    "sg:address":"Calle de Doctor Borrull, 7",
    "sg:city":"Javea",
    "sg:orig_category":"Estancos",
    "sg:phone":"+34 965 79 44 97",
    "sg:postcode":"03730",
    "sg:province":"Alicante",
    "wof:name":"Pastor Segarra Amparo",
    "wof:placetype":"venue"
},
  "geometry": {"coordinates":[0.1599459052,38.7877655029],"type":"Point"}
}