{
  "type": "Feature",
  "properties": {
    "iso:country":"ES",
    "sg:address":"Calle de Untzueta, 1",
    "sg:orig_category":"Reposter\u00cdas",
    "sg:phone":"+34 946 72 47 30",
    "sg:postcode":"01400",
    "sg:province":"\u00c1lava",
    "wof:name":"Obrador Daje S.c.",
    "wof:placetype":"venue"
},
  "geometry": {"coordinates":[-2.9647090435,43.1417808533],"type":"Point"}
}