{
  "type": "Feature",
  "properties": {
    "addr:full":"Lugar De Senra, S/n Ortigueira La Coru\u00f1a 15330",
    "addr:housenumber":"s / n",
    "addr:postcode":"15330",
    "addr:street":"Lugar De Senra;La Corun\u0303A",
    "iso:country":"ES",
    "sg:address":"Lugar De Senra, S/n",
    "sg:city":"Ortigueira",
    "sg:orig_category":"Iglesia Cat\u00d3lica",
    "sg:phone":"+34 981 40 08 47",
    "sg:postcode":"15330",
    "sg:province":"La Coru\u00f1a",
    "wof:name":"Parroquia De Senra",
    "wof:placetype":"venue"
},
  "geometry": {"coordinates":[-7.8530597687,43.6817398071],"type":"Point"}
}