{
  "type": "Feature",
  "properties": {
    "addr:full":"Calle de Argentina, S/n Vitoria-gasteiz \u00c1lava 01009",
    "addr:housenumber":"s / n",
    "addr:postcode":"01009",
    "addr:street":"Calle De Argentina",
    "iso:country":"ES",
    "sg:address":"Calle de Argentina, S/n",
    "sg:city":"Vitoria-gasteiz",
    "sg:orig_category":"Iglesia Cat\u00d3lica",
    "sg:phone":"+34 945 24 36 58",
    "sg:postcode":"01009",
    "sg:province":"\u00c1lava",
    "wof:name":"Parroquia De San Andres",
    "wof:placetype":"venue"
},
  "geometry": {"coordinates":[-2.6838214397,42.8537368774],"type":"Point"}
}