{
  "type": "Feature",
  "properties": {
    "iso:country":"ES",
    "sg:address":"Carrer de Banys, 8",
    "sg:city":"Garriga",
    "sg:orig_category":"Peluquer\u00cdas, Peluquer\u00cda Mixta",
    "sg:phone":"+34 938 71 57 24",
    "sg:postcode":"08530",
    "sg:province":"Barcelona",
    "wof:name":"Forcada Torra Jacint",
    "wof:placetype":"venue"
},
  "geometry": {"coordinates":[2.2857530117,41.6815910339],"type":"Point"}
}