{
  "type": "Feature",
  "properties": {
    "iso:country":"ES",
    "sg:address":"Av Girona, 82",
    "sg:city":"Olot",
    "sg:orig_category":"Hilaturas (fibras Naturales Diversas)",
    "sg:phone":"+34 972 26 43 97",
    "sg:postcode":"17800",
    "sg:province":"Girona",
    "wof:name":"Ridafil S. A.",
    "wof:placetype":"venue"
},
  "geometry": {"coordinates":[2.4983389378,42.1884040833],"type":"Point"}
}