{
  "type": "Feature",
  "properties": {
    "iso:country":"ES",
    "sg:address":"Av Ferrocarril, S/n",
    "sg:city":"Elche",
    "sg:orig_category":"Confecci\u00d3n De Zapatos",
    "sg:phone":"+34 965 42 53 94",
    "sg:postcode":"03202",
    "sg:province":"Alicante",
    "wof:name":"Sirach Sport S.l.",
    "wof:placetype":"venue"
},
  "geometry": {"coordinates":[-0.692456007,38.2723884583],"type":"Point"}
}