{
  "type": "Feature",
  "properties": {
    "addr:full":"Plaz Nueva, 30 Almaraz C\u00e1ceres 10350",
    "addr:housenumber":"30",
    "addr:postcode":"10350",
    "addr:street":"Plaz Nueva;Ca\u0301Ceres",
    "iso:country":"ES",
    "sg:address":"Plaz Nueva, 30",
    "sg:city":"Almaraz",
    "sg:orig_category":"Carnicer\u00cdas, Carnicer\u00cdas",
    "sg:phone":"+34 927 54 40 40",
    "sg:postcode":"10350",
    "sg:province":"C\u00e1ceres",
    "wof:name":"Gomez David Esteban",
    "wof:placetype":"venue"
},
  "geometry": {"coordinates":[-5.6808218956,39.8129959106],"type":"Point"}
}