{
  "type": "Feature",
  "properties": {
    "addr:full":"Calle de Colon, 4 Benimuslem Valencia 46611",
    "addr:housenumber":"4",
    "addr:postcode":"46611",
    "addr:street":"Calle De Colon",
    "iso:country":"ES",
    "sg:address":"Calle de Colon, 4",
    "sg:city":"Benimuslem",
    "sg:classifiers":[
        {
            "category":"Casinos & Gambling",
            "type":"Entertainment"
        }
    ],
    "sg:phone":"+34 962 44 00 89",
    "sg:postcode":"46611",
    "sg:province":"Valencia",
    "sg:tags":[
        "locale",
        "de",
        "juego"
    ],
    "wof:name":"Lopez Moreno Maria Consuelo",
    "wof:placetype":"venue"
},
  "geometry": {"coordinates":[-0.4926638901,39.1313247681],"type":"Point"}
}