{
  "type": "Feature",
  "properties": {
    "iso:country":"ES",
    "sg:address":"Carr Calvari, S/n",
    "sg:city":"Artesa Segre",
    "sg:orig_category":"Quincaller\u00cda (al Por Menor)",
    "sg:phone":"+34 973 40 04 58",
    "sg:postcode":"25730",
    "sg:province":"Lleida",
    "wof:name":"Capell Sole Montserrat",
    "wof:placetype":"venue"
},
  "geometry": {"coordinates":[1.0498579741,41.8959960938],"type":"Point"}
}