{
  "type": "Feature",
  "properties": {
    "iso:country":"ES",
    "sg:address":"Calle de Dr. Norberto Acebal, 1",
    "sg:city":"Barakaldo",
    "sg:orig_category":"Pescader\u00cdas (al Por Menor)",
    "sg:phone":"+34 944 90 24 73",
    "sg:postcode":"48903",
    "sg:province":"Vizcaya",
    "wof:name":"Pedro Lambarri Iba\u00f1ez",
    "wof:placetype":"venue"
},
  "geometry": {"coordinates":[-2.9964568615,43.2843818665],"type":"Point"}
}