{
  "type": "Feature",
  "properties": {
    "addr:full":"Calle de Hortal (el), 3 Arcos Navarra 31210",
    "addr:postcode":"31210",
    "addr:street":"Calle De Hortal El",
    "iso:country":"ES",
    "sg:address":"Calle de Hortal (el), 3",
    "sg:city":"Arcos",
    "sg:classifiers":[
        {
            "category":"Taxi",
            "type":"Transportation"
        }
    ],
    "sg:phone":"+34 948 64 07 64",
    "sg:postcode":"31210",
    "sg:province":"Navarra",
    "wof:name":"Anto\u00f1ana Ancin Arturo",
    "wof:placetype":"venue"
},
  "geometry": {"coordinates":[-2.1945366859,42.5687675476],"type":"Point"}
}