{
  "type": "Feature",
  "properties": {
    "iso:country":"ES",
    "sg:address":"Corti\u00f1as De Abaixo, S/n",
    "sg:city":"Corti\u00e7as De Abaixo",
    "sg:orig_category":"Iglesia Cat\u00d3lica",
    "sg:phone":"+34 986 54 23 86",
    "sg:postcode":"36634",
    "sg:province":"Pontevedra",
    "wof:name":"Parroquia De Corbillon",
    "wof:placetype":"venue"
},
  "geometry": {"coordinates":[-8.811788559,42.52526474],"type":"Point"}
}