{
  "type": "Feature",
  "properties": {
    "iso:country":"ES",
    "sg:address":"Av Catalunya, 22",
    "sg:city":"Tarragona",
    "sg:orig_category":"Masajistas Kinesiterapeutas",
    "sg:phone":"+34 977 21 99 70",
    "sg:postcode":"43002",
    "sg:province":"Tarragona",
    "wof:name":"Caballe Caballe Maurici",
    "wof:placetype":"venue"
},
  "geometry": {"coordinates":[1.2517830133,41.1205558777],"type":"Point"}
}