{
  "type": "Feature",
  "properties": {
    "addr:full":"Avda La Estacion, 44 Ortuella Vizcaya 48530",
    "addr:housenumber":"44",
    "addr:postcode":"48530",
    "addr:street":"Avda La Estacion",
    "iso:country":"ES",
    "sg:address":"Avda La Estacion, 44",
    "sg:city":"Ortuella",
    "sg:orig_category":"Sonorizaci\u00d3n, Iluminaci\u00d3n Para Cine, Teatro Y Discotecas (al Por Mayor, Al Por Menor)",
    "sg:phone":"+34 946 64 11 53",
    "sg:postcode":"48530",
    "sg:province":"Vizcaya",
    "wof:name":"Baskoson S.l.",
    "wof:placetype":"venue"
},
  "geometry": {"coordinates":[-3.0591111183,43.3113441467],"type":"Point"}
}