{
  "type": "Feature",
  "properties": {
    "addr:full":"Carr Sant Joan Baptista, 8 Ciutadella Menorca Islas Baleares 07760",
    "addr:housenumber":"8",
    "addr:postcode":"07760",
    "addr:street":"Carr Sant Joan Baptista",
    "iso:country":"ES",
    "sg:address":"Carr Sant Joan Baptista, 8",
    "sg:city":"Ciutadella Menorca",
    "sg:orig_category":"Molduras, Junquillos, Listones Y Molduras Perforadas",
    "sg:phone":"+34 971 48 44 98",
    "sg:postcode":"07760",
    "sg:province":"Islas Baleares",
    "wof:name":"Tom Tom Junior S.l.l.",
    "wof:placetype":"venue"
},
  "geometry": {"coordinates":[3.8391160965,40.0003433228],"type":"Point"}
}