{
  "type": "Feature",
  "properties": {
    "addr:full":"San Anton, 1 Iru\u00f1a Navarra 31001",
    "addr:housenumber":"1",
    "addr:postcode":"31001",
    "addr:street":"San Anton",
    "iso:country":"ES",
    "sg:address":"San Anton, 1",
    "sg:city":"Iru\u00f1a",
    "sg:orig_category":"Telas Y Sedas (al Por Menor)",
    "sg:phone":"+34 948 22 52 40",
    "sg:postcode":"31001",
    "sg:province":"Navarra",
    "wof:name":"Almacenes Numancia S. L.",
    "wof:placetype":"venue"
},
  "geometry": {"coordinates":[-1.6454341412,42.8166656494],"type":"Point"}
}