{
  "type": "Feature",
  "properties": {
    "iso:country":"ES",
    "sg:address":"Ctra. Palma, S/n",
    "sg:city":"Sencelles",
    "sg:orig_category":"Procuradores",
    "sg:phone":"+34 971 87 28 83",
    "sg:postcode":"07140",
    "sg:province":"Islas Baleares",
    "wof:name":"Company Chacopino Bartolome",
    "wof:placetype":"venue"
},
  "geometry": {"coordinates":[2.8922901154,39.6391181946],"type":"Point"}
}