{
  "type": "Feature",
  "properties": {
    "addr:full":"Calle de Lomo De La Cruz, 23 Palmas De Gran Canaria Las Palmas 35014",
    "addr:postcode":"35014",
    "addr:street":"Calle De Lomo De La Cruz 23",
    "iso:country":"ES",
    "sg:address":"Calle de Lomo De La Cruz, 23",
    "sg:city":"Palmas De Gran Canaria",
    "sg:orig_category":"Fabricaci\u00d3n, Distribuci\u00d3n De Material Para La Climatizaci\u00d3n, Aireaci\u00d3n Y Ventilaci\u00d3n",
    "sg:phone":"+34 928 42 43 11",
    "sg:postcode":"35014",
    "sg:province":"Las Palmas",
    "wof:name":"Instalaciones Carla Perdomo S.l.",
    "wof:placetype":"venue"
},
  "geometry": {"coordinates":[-15.4330606461,28.1174850464],"type":"Point"}
}