{
  "type": "Feature",
  "properties": {
    "iso:country":"ES",
    "sg:address":"Carr Mestre Sagrera, 38",
    "sg:city":"Palafrugell",
    "sg:orig_category":"Electrodom\u00c9sticos (al Por Menor)",
    "sg:phone":"+34 972 30 22 58",
    "sg:postcode":"17200",
    "sg:province":"Girona",
    "wof:name":"Quicor S.l.",
    "wof:placetype":"venue"
},
  "geometry": {"coordinates":[3.155559063,41.9200553894],"type":"Point"}
}