{
  "type": "Feature",
  "properties": {
    "iso:country":"ES",
    "sg:address":"Carr Industria, 21",
    "sg:city":"S. Guim Freixenet",
    "sg:orig_category":"Forjas Y Altos Hornos",
    "sg:phone":"+34 973 55 60 57",
    "sg:postcode":"25270",
    "sg:province":"Lleida",
    "wof:name":"Vilella Escriba Jaime",
    "wof:placetype":"venue"
},
  "geometry": {"coordinates":[1.3964250088,41.6603088379],"type":"Point"}
}