{
  "type": "Feature",
  "properties": {
    "addr:full":"Avda Ciudad De Huelva, S/n Punta Umbria Huelva 21100",
    "addr:housenumber":"s / n",
    "addr:postcode":"21100",
    "addr:street":"Avda Ciudad De Huelva",
    "iso:country":"ES",
    "sg:address":"Avda Ciudad De Huelva, S/n",
    "sg:city":"Punta Umbria",
    "sg:orig_category":"Inmobiliaria (agencias)",
    "sg:phone":"+34 959 31 16 78",
    "sg:postcode":"21100",
    "sg:province":"Huelva",
    "wof:name":"Punta Turistica S.a.",
    "wof:placetype":"venue"
},
  "geometry": {"coordinates":[-6.9710879326,37.1820526123],"type":"Point"}
}