{
  "type": "Feature",
  "properties": {
    "addr:full":"Avda Novelda, 7 Villena Alicante 03400",
    "addr:housenumber":"7",
    "addr:postcode":"03400",
    "addr:street":"Avda Novelda",
    "iso:country":"ES",
    "sg:address":"Avda Novelda, 7",
    "sg:city":"Villena",
    "sg:orig_category":"Empresas De Portes Y Mensajer\u00cda",
    "sg:phone":"+34 965 80 82 28",
    "sg:postcode":"03400",
    "sg:province":"Alicante",
    "wof:name":"A.a.v.v. Parque De La Banda Municipal De Musica",
    "wof:placetype":"venue"
},
  "geometry": {"coordinates":[-0.861077,38.628811],"type":"Point"}
}