{
  "type": "Feature",
  "properties": {
    "addr:full":"Ctra. Gualchos, S/n Castell De Ferro Granada 18740",
    "addr:housenumber":"s / n",
    "addr:postcode":"18740",
    "addr:street":"Ctra. Gualchos",
    "iso:country":"ES",
    "sg:address":"Ctra. Gualchos, S/n",
    "sg:city":"Castell De Ferro",
    "sg:orig_category":"Frutas Y Legumbres Frescas (al Por Mayor)",
    "sg:phone":"+34 958 65 63 77",
    "sg:postcode":"18740",
    "sg:province":"Granada",
    "wof:name":"Sociedad Cooperativa Andaluza Hermanos Perez Castillo",
    "wof:placetype":"venue"
},
  "geometry": {"coordinates":[-3.3619859219,36.7227973938],"type":"Point"}
}