{
  "type": "Feature",
  "properties": {
    "iso:country":"ES",
    "sg:address":"Ptda Els Palmars, 1209",
    "sg:city":"Denia",
    "sg:orig_category":"Restaurantes",
    "sg:phone":"+34 965 78 48 64",
    "sg:postcode":"03700",
    "sg:province":"Alicante",
    "wof:name":"Cova Del Mero S.c.",
    "wof:placetype":"venue"
},
  "geometry": {"coordinates":[0.1039630026,38.8354949951],"type":"Point"}
}