{
  "type": "Feature",
  "properties": {
    "addr:full":"Av Onze De Setembre, 10 Olot Girona 17800",
    "addr:housenumber":"10",
    "addr:postcode":"17800",
    "addr:street":"Av Onze De Setembre",
    "iso:country":"ES",
    "sg:address":"Av Onze De Setembre, 10",
    "sg:city":"Olot",
    "sg:orig_category":"Fabricaci\u00d3n De Art\u00cdculos Y Ornamentos Religiosos",
    "sg:phone":"+34 972 26 03 83",
    "sg:postcode":"17800",
    "sg:province":"Girona",
    "wof:name":"Sucarrats Busquets Torrento Y Cia S. A.",
    "wof:placetype":"venue"
},
  "geometry": {"coordinates":[2.4928650856,42.1821708679],"type":"Point"}
}