{
  "type": "Feature",
  "properties": {
    "addr:full":"Rua Paraguay, 5 Vigo Pontevedra 36204",
    "addr:housenumber":"5",
    "addr:postcode":"36204",
    "addr:street":"Rua Paraguay",
    "iso:country":"ES",
    "sg:address":"Rua Paraguay, 5",
    "sg:city":"Vigo",
    "sg:orig_category":"Asesor\u00cdas Y Estudios Financieros",
    "sg:phone":"+34 986 41 76 25",
    "sg:postcode":"36204",
    "sg:province":"Pontevedra",
    "wof:name":"Vasquez Vidal Aurora",
    "wof:placetype":"venue"
},
  "geometry": {"coordinates":[-8.7161207199,42.2330169678],"type":"Point"}
}