{
  "type": "Feature",
  "properties": {
    "iso:country":"ES",
    "sg:address":"Cortijo Cherino, S/n",
    "sg:city":"Almogia",
    "sg:orig_category":"Producci\u00d3n, Venta De Productos De Agricultura Biol\u00d3gica",
    "sg:phone":"+34 952 43 00 74",
    "sg:postcode":"29150",
    "sg:province":"M\u00e1laga",
    "wof:name":"Agro Corchera Alisoso S. A.",
    "wof:placetype":"venue"
},
  "geometry": {"coordinates":[-4.5418143272,36.8460960388],"type":"Point"}
}