{
  "type": "Feature",
  "properties": {
    "iso:country":"ES",
    "sg:address":"Calle de Prado (el), 46",
    "sg:city":"Luque",
    "sg:orig_category":"Alimentaci\u00d3n General (al Por Mayor)",
    "sg:phone":"+34 957 66 70 67",
    "sg:postcode":"14880",
    "sg:province":"C\u00f3rdoba",
    "wof:name":"Rabadan Perez Francisco",
    "wof:placetype":"venue"
},
  "geometry": {"coordinates":[-4.2788491249,37.555393219],"type":"Point"}
}