{
  "type": "Feature",
  "properties": {
    "addr:full":"Carrer de Angel Guimera, 3 Playa De Calafell Tarragona 43820",
    "addr:housenumber":"3",
    "addr:postcode":"43820",
    "addr:street":"Carrer De Angel Guimera",
    "iso:country":"ES",
    "sg:address":"Carrer de Angel Guimera, 3",
    "sg:city":"Playa De Calafell",
    "sg:orig_category":"Dibujantes (diversos)",
    "sg:phone":"+34 977 69 40 77",
    "sg:postcode":"43820",
    "sg:province":"Tarragona",
    "wof:name":"Chacopino Fabre Joaquin",
    "wof:placetype":"venue"
},
  "geometry": {"coordinates":[1.5748260021,41.1875953674],"type":"Point"}
}