{
  "type": "Feature",
  "properties": {
    "addr:full":"Calle de Pe\u00d1a (de La), 18 Algete Madrid 28110",
    "addr:housenumber":"18",
    "addr:postcode":"28110",
    "addr:street":"Calle De Pen\u0303A De La",
    "iso:country":"ES",
    "sg:address":"Calle de Pe\u00d1a (de La), 18",
    "sg:city":"Algete",
    "sg:orig_category":"Cerrajer\u00cda, Ferrallista",
    "sg:phone":"+34 916 29 22 41",
    "sg:postcode":"28110",
    "sg:province":"Madrid",
    "wof:name":"Jun-car C.b.",
    "wof:placetype":"venue"
},
  "geometry": {"coordinates":[-3.4969620705,40.5978813171],"type":"Point"}
}