{
  "type": "Feature",
  "properties": {
    "addr:full":"Calle de Esteve Victoria, 10 Valencia Valencia 46006",
    "addr:housenumber":"10",
    "addr:postcode":"46006",
    "addr:street":"Calle De Esteve Victoria",
    "iso:country":"ES",
    "sg:address":"Calle de Esteve Victoria, 10",
    "sg:city":"Valencia",
    "sg:orig_category":"Electricidad: Instaladores",
    "sg:phone":"+34 963 33 23 97",
    "sg:postcode":"46006",
    "sg:province":"Valencia",
    "wof:name":"Integral Valenciana De Servicios Electricos S.l.",
    "wof:placetype":"venue"
},
  "geometry": {"coordinates":[-0.372303009,39.4575843811],"type":"Point"}
}