{
  "type": "Feature",
  "properties": {
    "iso:country":"ES",
    "sg:address":"Rua Rias Baixas, 17",
    "sg:city":"Sarria",
    "sg:orig_category":"Escayola Y Productos De Escayola (fabricaci\u00d3n, Al Por Mayor)",
    "sg:phone":"+34 982 53 10 77",
    "sg:postcode":"27600",
    "sg:province":"Lugo",
    "wof:name":"Revetimientos Hermanos Torre S. L.",
    "wof:placetype":"venue"
},
  "geometry": {"coordinates":[-7.4121251106,42.7802734375],"type":"Point"}
}