{
  "type": "Feature",
  "properties": {
    "iso:country":"ES",
    "sg:address":"Calle de Doctor Jimenez Diaz, S/n",
    "sg:city":"Santa Maria De Gracia",
    "sg:orig_category":"Florister\u00cdas",
    "sg:phone":"+34 968 23 10 02",
    "sg:postcode":"30008",
    "sg:province":"Murcia",
    "wof:name":"Borja Jimenez Jose",
    "wof:placetype":"venue"
},
  "geometry": {"coordinates":[-1.1298867464,37.9834747314],"type":"Point"}
}