{
  "type": "Feature",
  "properties": {
    "addr:full":"Bassa Roja Sa, 4 Eivissa Islas Baleares 07800",
    "addr:housenumber":"4",
    "addr:postcode":"07800",
    "iso:country":"ES",
    "sg:address":"Bassa Roja Sa, 4",
    "sg:city":"Eivissa",
    "sg:orig_category":"Guarder\u00cdas",
    "sg:phone":"+34 971 30 43 63",
    "sg:postcode":"07800",
    "sg:province":"Islas Baleares",
    "wof:name":"Boned Ribas Catalina",
    "wof:placetype":"venue"
},
  "geometry": {"coordinates":[1.4167430401,38.9065361023],"type":"Point"}
}