{
  "type": "Feature",
  "properties": {
    "addr:full":"Carr Fra Vicent Nicolau, 2 Eivissa Islas Baleares 07800",
    "addr:housenumber":"2",
    "addr:postcode":"07800",
    "addr:street":"Carr Fra Vicent Nicolau",
    "iso:country":"ES",
    "sg:address":"Carr Fra Vicent Nicolau, 2",
    "sg:city":"Eivissa",
    "sg:orig_category":"Ropa Para Se\u00d1oras Y Caballeros (al Por Menor)",
    "sg:phone":"+34 971 19 41 61",
    "sg:postcode":"07800",
    "sg:province":"Islas Baleares",
    "wof:name":"Torres Ribas Maria Cristina",
    "wof:placetype":"venue"
},
  "geometry": {"coordinates":[1.4291599989,38.9109077454],"type":"Point"}
}