{
  "type": "Feature",
  "properties": {
    "iso:country":"ES",
    "sg:address":"Calle de Antonio Acu\u00d1a, 18",
    "sg:city":"Madrid",
    "sg:orig_category":"Molduras, Junquillos, Listones Y Molduras Perforadas",
    "sg:phone":"+34 914 31 37 80",
    "sg:postcode":"28009",
    "sg:province":"Madrid",
    "wof:name":"Nieda Gutierrez Julio",
    "wof:placetype":"venue"
},
  "geometry": {"coordinates":[-3.6790230274,40.4211235046],"type":"Point"}
}