{
  "type": "Feature",
  "properties": {
    "addr:full":"Calle de Cantarranas, 30 Herrera Duque Badajoz 06670",
    "addr:housenumber":"30",
    "addr:postcode":"06670",
    "addr:street":"Calle De Cantarranas",
    "iso:country":"ES",
    "sg:address":"Calle de Cantarranas, 30",
    "sg:city":"Herrera Duque",
    "sg:orig_category":"Ense\u00d1anza: Profesiones Art\u00cdsticas",
    "sg:phone":"+34 924 65 09 27",
    "sg:postcode":"06670",
    "sg:province":"Badajoz",
    "wof:name":"Casco Manzano Rafael",
    "wof:placetype":"venue"
},
  "geometry": {"coordinates":[-5.0486245155,39.1674804688],"type":"Point"}
}