{
  "type": "Feature",
  "properties": {
    "iso:country":"ES",
    "sg:address":"Granadinas Las, 1",
    "sg:city":"Almaden Plata",
    "sg:orig_category":"Panader\u00cdas, Panader\u00cdas",
    "sg:phone":"+34 954 73 55 07",
    "sg:postcode":"41240",
    "sg:province":"Sevilla",
    "wof:name":"Panificadora Nuestra Se\u00f1ora De Gracia",
    "wof:placetype":"venue"
},
  "geometry": {"coordinates":[-6.0820550919,37.8727340698],"type":"Point"}
}