{
  "type": "Feature",
  "properties": {
    "addr:full":"Plaz Gran Maestre, 2 Fuente Maestre Badajoz 06360",
    "addr:housenumber":"2",
    "addr:postcode":"06360",
    "addr:street":"Maestre",
    "iso:country":"ES",
    "sg:address":"Plaz Gran Maestre, 2",
    "sg:city":"Fuente Maestre",
    "sg:orig_category":"Droguer\u00cdas (al Por Menor)",
    "sg:phone":"+34 924 53 04 03",
    "sg:postcode":"06360",
    "sg:province":"Badajoz",
    "wof:name":"Mu\u00f1oz Zambrano Maria Gloria",
    "wof:placetype":"venue"
},
  "geometry": {"coordinates":[-6.442150116,38.5292739868],"type":"Point"}
}