{
  "type": "Feature",
  "properties": {
    "addr:full":"Carr Barris I Buixo, 25 Palafrugell Girona 17200",
    "addr:housenumber":"25",
    "addr:postcode":"17200",
    "addr:street":"Carr Barris I Buixo",
    "iso:country":"ES",
    "sg:address":"Carr Barris I Buixo, 25",
    "sg:city":"Palafrugell",
    "sg:orig_category":"Centros Comerciales Y Grandes Tiendas",
    "sg:phone":"+34 972 30 50 87",
    "sg:postcode":"17200",
    "sg:province":"Girona",
    "wof:name":"Platja Ferro Josep",
    "wof:placetype":"venue"
},
  "geometry": {"coordinates":[3.1679029465,41.9150047302],"type":"Point"}
}