{
  "type": "Feature",
  "properties": {
    "addr:full":"Los Colegios, 6 B. Magdalena Le\u00f3n 24120",
    "addr:housenumber":"6 b.",
    "addr:postcode":"24120",
    "addr:street":"Colegios;Magdalena Leo\u0301N",
    "iso:country":"ES",
    "sg:address":"Los Colegios, 6",
    "sg:city":"B. Magdalena",
    "sg:orig_category":"Centros Empresariales",
    "sg:phone":"+34 987 58 16 15",
    "sg:postcode":"24120",
    "sg:province":"Le\u00f3n",
    "wof:name":"Dominguez Chamorro Julian",
    "wof:placetype":"venue"
},
  "geometry": {"coordinates":[-5.8100237846,42.7811889648],"type":"Point"}
}