{
  "type": "Feature",
  "properties": {
    "addr:full":"Plaz Ayuntamiento, 2 Meira Lugo 27240",
    "addr:housenumber":"2",
    "addr:postcode":"27240",
    "addr:street":"Ayuntamiento",
    "iso:country":"ES",
    "sg:address":"Plaz Ayuntamiento, 2",
    "sg:city":"Meira",
    "sg:orig_category":"Droguer\u00cdas (al Por Menor)",
    "sg:phone":"+34 982 33 06 09",
    "sg:postcode":"27240",
    "sg:province":"Lugo",
    "wof:name":"Carrera Lopez Elia",
    "wof:placetype":"venue"
},
  "geometry": {"coordinates":[-7.294479847,43.2133827209],"type":"Point"}
}