{
  "type": "Feature",
  "properties": {
    "iso:country":"ES",
    "sg:address":"Calle de Villaescusa, 50",
    "sg:city":"Madrid",
    "sg:orig_category":"Confecci\u00d3n De Trajes Para Se\u00d1oras",
    "sg:phone":"+34 913 27 06 80",
    "sg:postcode":"28017",
    "sg:province":"Madrid",
    "wof:name":"Presto Moda S.l.",
    "wof:placetype":"venue"
},
  "geometry": {"coordinates":[-3.6335790157,40.4213600159],"type":"Point"}
}