{
  "type": "Feature",
  "properties": {
    "iso:country":"ES",
    "sg:address":"Av Vall, 16",
    "sg:city":"S. Pau Seguries",
    "sg:orig_category":"Asociaciones Y Clubs Deportivos",
    "sg:phone":"+34 972 74 73 14",
    "sg:postcode":"17864",
    "sg:province":"Girona",
    "wof:name":"Lage Meilan Manuel",
    "wof:placetype":"venue"
},
  "geometry": {"coordinates":[2.3659880161,42.2611694336],"type":"Point"}
}