{
  "type": "Feature",
  "properties": {
    "addr:full":"Calle de Marianista Cubillo, 7 Cadiz C\u00e1diz 11008",
    "addr:housenumber":"7",
    "addr:postcode":"11008",
    "addr:street":"Calle De Marianista Cubillo",
    "iso:country":"ES",
    "sg:address":"Calle de Marianista Cubillo, 7",
    "sg:city":"Cadiz",
    "sg:orig_category":"Aparcamientos (infraestructuras, Accesorios)",
    "sg:phone":"+34 956 27 80 92",
    "sg:postcode":"11008",
    "sg:province":"C\u00e1diz",
    "wof:name":"Fernandez Perez Antonio",
    "wof:placetype":"venue"
},
  "geometry": {"coordinates":[-6.2825298309,36.5142440796],"type":"Point"}
}