{
  "type": "Feature",
  "properties": {
    "iso:country":"ES",
    "sg:address":"Carrer de Protectora, 3",
    "sg:city":"Palma",
    "sg:orig_category":"Inmobiliaria (agencias)",
    "sg:phone":"+34 971 22 76 55",
    "sg:postcode":"07012",
    "sg:province":"Islas Baleares",
    "wof:name":"Shortscuts Property Search S.l",
    "wof:placetype":"venue"
},
  "geometry": {"coordinates":[2.6440289021,39.5712242126],"type":"Point"}
}