{
  "type": "Feature",
  "properties": {
    "addr:full":"Calle de Orense, 69 Madrid Madrid 28020",
    "addr:housenumber":"69",
    "addr:postcode":"madrid;28020",
    "addr:street":"Calle De Orense",
    "iso:country":"ES",
    "sg:address":"Calle de Orense, 69",
    "sg:city":"Madrid",
    "sg:classifiers":[
        {
            "category":"Banks & Credit Unions",
            "subcategory":"Bureau De Change",
            "type":"Services"
        }
    ],
    "sg:phone":"+34 915 21 10 24",
    "sg:postcode":"28020",
    "sg:province":"Madrid",
    "sg:tags":[
        "organismos",
        "control"
    ],
    "sg:website":"www.certum.es",
    "wof:name":"Certum Control Tecnico De La Edificacion S.a.",
    "wof:placetype":"venue"
},
  "geometry": {"coordinates":[-3.6946299076,40.4582252502],"type":"Point"}
}