{
  "type": "Feature",
  "properties": {
    "addr:full":"Calle de Casota, 8 Paiporta Valencia 46200",
    "addr:housenumber":"8",
    "addr:postcode":"46200",
    "addr:street":"Calle De Casota",
    "iso:country":"ES",
    "sg:address":"Calle de Casota, 8",
    "sg:city":"Paiporta",
    "sg:orig_category":"Caf\u00c9s, Bares, Cervecer\u00cdas",
    "sg:phone":"+34 963 97 66 67",
    "sg:postcode":"46200",
    "sg:province":"Valencia",
    "wof:name":"Gomez Gonzalez Antonio",
    "wof:placetype":"venue"
},
  "geometry": {"coordinates":[-0.4181357026,39.4254570007],"type":"Point"}
}