{
  "type": "Feature",
  "properties": {
    "iso:country":"ES",
    "sg:address":"Calle de Comunidad De Murcia, S/n",
    "sg:city":"Laguna Duero",
    "sg:orig_category":"Quincaller\u00cda (al Por Menor)",
    "sg:phone":"+34 983 54 00 32",
    "sg:postcode":"47140",
    "sg:province":"Valladolid",
    "wof:name":"Ignacio Rodriguez S.a.",
    "wof:placetype":"venue"
},
  "geometry": {"coordinates":[-4.7179083824,41.5777244568],"type":"Point"}
}