{
  "type": "Feature",
  "properties": {
    "addr:full":"Calle de Marruecos, S/n Playa Del Ingles Las Palmas 35100",
    "addr:housenumber":"s / n",
    "addr:postcode":"35100",
    "addr:street":"Calle De Marruecos",
    "iso:country":"ES",
    "sg:address":"Calle de Marruecos, S/n",
    "sg:city":"Playa Del Ingles",
    "sg:orig_category":"Bancos",
    "sg:phone":"+34 928 76 08 50",
    "sg:postcode":"35100",
    "sg:province":"Las Palmas",
    "sg:website":"www.gruposantander.es",
    "wof:name":"Bt Espa\u00d1a Compa\u00d1ia De Servicios Globales De Telecomunicaciones S.a.u.",
    "wof:placetype":"venue"
},
  "geometry": {"coordinates":[-15.5691404343,27.758108139],"type":"Point"}
}