{
  "type": "Feature",
  "properties": {
    "addr:full":"Carrer de Miquel Torello I Pages, 1113 Molins Rei Barcelona 08750",
    "addr:postcode":"1113;08750",
    "addr:street":"Carrer De Miquel Torello I Pages;Barcelona",
    "iso:country":"ES",
    "sg:address":"Carrer de Miquel Torello I Pages, 1113",
    "sg:city":"Molins Rei",
    "sg:orig_category":"Librer\u00cdas",
    "sg:phone":"+34 936 68 12 48",
    "sg:postcode":"08750",
    "sg:province":"Barcelona",
    "wof:name":"Sociedad General Espa\u00d1ola De Libreria Diarios Y Revistas",
    "wof:placetype":"venue"
},
  "geometry": {"coordinates":[2.0299201012,41.3975982666],"type":"Point"}
}