{
  "type": "Feature",
  "properties": {
    "addr:full":"Calle de Toro, 20 Salamanca Salamanca 37002",
    "addr:housenumber":"20",
    "addr:postcode":"37002",
    "addr:street":"Calle De Toro",
    "iso:country":"ES",
    "sg:address":"Calle de Toro, 20",
    "sg:city":"Salamanca",
    "sg:orig_category":"Caf\u00c9s, Bares, Cervecer\u00cdas",
    "sg:phone":"+34 923 26 89 24",
    "sg:postcode":"37002",
    "sg:province":"Salamanca",
    "wof:name":"Erasmus Bruin Cafe Sl",
    "wof:placetype":"venue"
},
  "geometry": {"coordinates":[-5.6628332138,40.9660415649],"type":"Point"}
}