{
  "type": "Feature",
  "properties": {
    "iso:country":"ES",
    "sg:address":"Calle de Wences Moreno, 14",
    "sg:city":"Salamanca",
    "sg:orig_category":"Sociedades, Compa\u00d1\u00cdas Aseguradoras",
    "sg:phone":"+34 923 24 23 92",
    "sg:postcode":"37007",
    "sg:province":"Salamanca",
    "wof:name":"Seguros Daesma S.l.",
    "wof:placetype":"venue"
},
  "geometry": {"coordinates":[-5.6662659645,40.9703674316],"type":"Point"}
}