{
  "type": "Feature",
  "properties": {
    "iso:country":"ES",
    "sg:address":"Avda Portugal, 37",
    "sg:city":"Martina",
    "sg:orig_category":"Reposter\u00cdas",
    "sg:phone":"+34 987 41 06 72",
    "sg:postcode":"24400",
    "sg:province":"Le\u00f3n",
    "wof:name":"Nietos De Abel S.l.",
    "wof:placetype":"venue"
},
  "geometry": {"coordinates":[-6.5983390808,42.5483360291],"type":"Point"}
}