{
  "type": "Feature",
  "properties": {
    "iso:country":"ES",
    "sg:address":"Calle de Polvoranca, 15",
    "sg:city":"Getafe",
    "sg:orig_category":"Ropa De Hogar (al Por Menor)",
    "sg:phone":"+34 916 82 53 18",
    "sg:postcode":"28901",
    "sg:province":"Madrid",
    "wof:name":"Carrero Iniesta Gregorio",
    "wof:placetype":"venue"
},
  "geometry": {"coordinates":[-3.7339971066,40.3045654297],"type":"Point"}
}