{
  "type": "Feature",
  "properties": {
    "addr:full":"Calle de Miguel Caballero, S/n Puebla De Soto Murcia 30836",
    "addr:housenumber":"s / n",
    "addr:postcode":"30836",
    "addr:street":"Calle De Miguel Caballero",
    "iso:country":"ES",
    "sg:address":"Calle de Miguel Caballero, S/n",
    "sg:city":"Puebla De Soto",
    "sg:orig_category":"Asilos De Ancianos. Centros Privados",
    "sg:phone":"+34 968 89 11 98",
    "sg:postcode":"30836",
    "sg:province":"Murcia",
    "wof:name":"Club De La Tercera Edad De Puebla De Soto",
    "wof:placetype":"venue"
},
  "geometry": {"coordinates":[-1.1973990202,37.9774589539],"type":"Point"}
}