{
  "type": "Feature",
  "properties": {
    "iso:country":"ES",
    "sg:address":"Calle de Pintor Balaca, 1",
    "sg:city":"Cartagena",
    "sg:orig_category":"Doctores En Medicina",
    "sg:phone":"+34 968 52 12 41",
    "sg:postcode":"30205",
    "sg:province":"Murcia",
    "wof:name":"Valle Perez Miguel Angel De",
    "wof:placetype":"venue"
},
  "geometry": {"coordinates":[-0.9920139909,37.6083106995],"type":"Point"}
}