{
  "type": "Feature",
  "properties": {
    "iso:country":"ES",
    "sg:address":"Barr San Roman Corban, 2",
    "sg:city":"San Roman",
    "sg:orig_category":"Reposter\u00cdas",
    "sg:phone":"+34 942 33 01 03",
    "sg:postcode":"39012",
    "sg:province":"Cantabria",
    "wof:name":"Corazones De Sobrino S.l.",
    "wof:placetype":"venue"
},
  "geometry": {"coordinates":[-3.8420140743,43.4636726379],"type":"Point"}
}