{
  "type": "Feature",
  "properties": {
    "iso:country":"ES",
    "sg:address":"Carrer de Diputacio, 453",
    "sg:city":"Barcelona",
    "sg:orig_category":"Asociaciones, Organismos Culturales Y Socioeducativos",
    "sg:phone":"+34 932 65 86 12",
    "sg:postcode":"08013",
    "sg:province":"Barcelona",
    "wof:name":"Centro Andaluz Comarca De Linares",
    "wof:placetype":"venue"
},
  "geometry": {"coordinates":[2.1801869869,41.4004211426],"type":"Point"}
}