{
  "type": "Feature",
  "properties": {
    "addr:full":"Carr Arraval, 125 Mao Islas Baleares 07701",
    "addr:housenumber":"125",
    "addr:postcode":"07701",
    "addr:street":"Carr Arraval",
    "iso:country":"ES",
    "sg:address":"Carr Arraval, 125",
    "sg:city":"Mao",
    "sg:orig_category":"Agencias Y Agentes Comerciales, Representantes",
    "sg:phone":"+34 971 36 23 78",
    "sg:postcode":"07701",
    "sg:province":"Islas Baleares",
    "wof:name":"Cabiro Villalonga Emilio",
    "wof:placetype":"venue"
},
  "geometry": {"coordinates":[4.2650399208,39.8893814087],"type":"Point"}
}