{
  "type": "Feature",
  "properties": {
    "iso:country":"ES",
    "sg:address":"Calle de Segovia, 4",
    "sg:city":"Avila",
    "sg:orig_category":"Venta, Instalaci\u00d3n De Calefacci\u00d3n",
    "sg:phone":"+34 920 25 58 39",
    "sg:postcode":"05005",
    "sg:province":"\u00c1vila",
    "wof:name":"Instalaciones Gas Avila S.l.",
    "wof:placetype":"venue"
},
  "geometry": {"coordinates":[-4.691090107,40.6600494385],"type":"Point"}
}