{
  "type": "Feature",
  "properties": {
    "iso:country":"ES",
    "sg:address":"Calle de Manuel Segarra Ribes, 1",
    "sg:city":"Castellon",
    "sg:orig_category":"Alquiler De V\u00cddeo",
    "sg:phone":"+34 964 22 38 63",
    "sg:postcode":"12005",
    "sg:province":"Castell\u00f3n",
    "wof:name":"Tendes De L'horta Nord S.l.",
    "wof:placetype":"venue"
},
  "geometry": {"coordinates":[-0.0297400001,39.9624290466],"type":"Point"}
}