{
  "type": "Feature",
  "properties": {
    "addr:full":"Lu. Nietos De Miranda, S/n Miranda Murcia 30319",
    "addr:housenumber":"s / n",
    "addr:postcode":"30319",
    "iso:country":"ES",
    "sg:address":"Lu. Nietos De Miranda, S/n",
    "sg:city":"Miranda",
    "sg:orig_category":"Mec\u00c1nico Del Autom\u00d3vil",
    "sg:phone":"+34 968 16 16 67",
    "sg:postcode":"30319",
    "sg:province":"Murcia",
    "wof:name":"Murcia Nicolas Carmelo",
    "wof:placetype":"venue"
},
  "geometry": {"coordinates":[-1.0148609877,37.6664352417],"type":"Point"}
}