{
  "type": "Feature",
  "properties": {
    "addr:full":"Calle de Mar, 43 Valencia Valencia 46003",
    "addr:housenumber":"43",
    "addr:postcode":"46003",
    "addr:street":"Calle De Mar",
    "iso:country":"ES",
    "sg:address":"Calle de Mar, 43",
    "sg:city":"Valencia",
    "sg:orig_category":"Peluquer\u00cdas, Peluquer\u00cda Mixta",
    "sg:phone":"+34 963 92 23 61",
    "sg:postcode":"46003",
    "sg:province":"Valencia",
    "wof:name":"Pamblanco Alepuz Vicenta",
    "wof:placetype":"venue"
},
  "geometry": {"coordinates":[-0.3713360131,39.4735336304],"type":"Point"}
}