{
  "type": "Feature",
  "properties": {
    "iso:country":"ES",
    "sg:address":"Calle de Lealtad, 4",
    "sg:city":"Santander",
    "sg:orig_category":"Cajas De Ahorro",
    "sg:phone":"+34 942 31 89 70",
    "sg:postcode":"39002",
    "sg:province":"Cantabria",
    "wof:name":"Caixa D'estalvis De Catalunya",
    "wof:placetype":"venue"
},
  "geometry": {"coordinates":[-3.808588028,43.4625053406],"type":"Point"}
}