{
  "type": "Feature",
  "properties": {
    "addr:full":"Calle de Santa Ana, 11 Jimena Frontera C\u00e1diz 11330",
    "addr:housenumber":"11",
    "addr:postcode":"11330",
    "addr:street":"Calle De Santa Ana",
    "iso:country":"ES",
    "sg:address":"Calle de Santa Ana, 11",
    "sg:city":"Jimena Frontera",
    "sg:orig_category":"Molduras, Junquillos, Listones Y Molduras Perforadas",
    "sg:phone":"+34 956 64 01 22",
    "sg:postcode":"11330",
    "sg:province":"C\u00e1diz",
    "wof:name":"Perez Sanchez Francisco",
    "wof:placetype":"venue"
},
  "geometry": {"coordinates":[-5.4548020363,36.4377174377],"type":"Point"}
}