{
  "type": "Feature",
  "properties": {
    "addr:full":"Ctra Reus-riudoms, Km. 0003,0 Riudoms Tarragona 43330",
    "addr:postcode":"43330",
    "addr:street":"Ctra Reus-Riudoms Km. 0003,0",
    "iso:country":"ES",
    "sg:address":"Ctra Reus-riudoms, Km. 0003,0",
    "sg:city":"Riudoms",
    "sg:orig_category":"Alimentaci\u00d3n General (al Por Mayor)",
    "sg:phone":"+34 977 85 10 91",
    "sg:postcode":"43330",
    "sg:province":"Tarragona",
    "wof:name":"Distribucions D'alimentacio Sanga S.l.",
    "wof:placetype":"venue"
},
  "geometry": {"coordinates":[1.0541909933,41.1382713318],"type":"Point"}
}