{
  "type": "Feature",
  "properties": {
    "iso:country":"ES",
    "sg:address":"Cra. Balaguer, S/n",
    "sg:city":"Anglesola",
    "sg:orig_category":"Alimentaci\u00d3n General (al Por Mayor)",
    "sg:phone":"+34 973 30 83 03",
    "sg:postcode":"25320",
    "sg:province":"Lleida",
    "wof:name":"Sociedad Agraria De Transformacion 883",
    "wof:placetype":"venue"
},
  "geometry": {"coordinates":[1.0829449892,41.6596260071],"type":"Point"}
}