{
  "type": "Feature",
  "properties": {
    "iso:country":"ES",
    "sg:address":"Avda J. Solis Ruiz, 21",
    "sg:city":"Cabra",
    "sg:orig_category":"Alquiler De V\u00cddeo",
    "sg:phone":"+34 957 52 09 76",
    "sg:postcode":"14940",
    "sg:province":"C\u00f3rdoba",
    "wof:name":"Rascon Sabariego Jose",
    "wof:placetype":"venue"
},
  "geometry": {"coordinates":[-4.4425888062,37.4736709595],"type":"Point"}
}