{
  "type": "Feature",
  "properties": {
    "iso:country":"ES",
    "sg:address":"Calle de Lorenzo Prestamero, 1",
    "sg:city":"Vitoria-gasteiz",
    "sg:orig_category":"M\u00c1rmoles, Granitos Y Piedras Naturales",
    "sg:phone":"+34 945 26 08 31",
    "sg:postcode":"01013",
    "sg:province":"\u00c1lava",
    "wof:name":"I\u00f1iguez De Heredia Lopez De Uralde Ignacio",
    "wof:placetype":"venue"
},
  "geometry": {"coordinates":[-2.6718370914,42.8558502197],"type":"Point"}
}