{
  "type": "Feature",
  "properties": {
    "addr:full":"Carrer de Sant Guillem, 2 Barcelona Barcelona 08006",
    "addr:housenumber":"2",
    "addr:postcode":"08006",
    "addr:street":"Carrer De Sant Guillem",
    "iso:country":"ES",
    "sg:address":"Carrer de Sant Guillem, 2",
    "sg:city":"Barcelona",
    "sg:orig_category":"Plomeros",
    "sg:phone":"+34 932 00 51 21",
    "sg:postcode":"08006",
    "sg:province":"Barcelona",
    "wof:name":"Uriach Orovitg Jaume",
    "wof:placetype":"venue"
},
  "geometry": {"coordinates":[2.1465709209,41.4025344849],"type":"Point"}
}