{
  "type": "Feature",
  "properties": {
    "iso:country":"ES",
    "sg:address":"Calle de Gines Simon Romera, 10",
    "sg:city":"Puerto Lumbreras",
    "sg:orig_category":"Empresas De Carpinter\u00cda De Madera",
    "sg:phone":"+34 968 40 09 67",
    "sg:postcode":"30890",
    "sg:province":"Murcia",
    "wof:name":"Carpinteria Framafer S.l.",
    "wof:placetype":"venue"
},
  "geometry": {"coordinates":[-1.8088309765,37.5661315918],"type":"Point"}
}