{
  "type": "Feature",
  "properties": {
    "iso:country":"ES",
    "sg:address":"Calle de Secundino Esnaola, 40",
    "sg:city":"Donostia-san Sebastian",
    "sg:orig_category":"Fabricaci\u00d3n, Venta De Cuadros, Accesorios Para Enmarcar",
    "sg:phone":"+34 943 27 65 98",
    "sg:postcode":"20001",
    "sg:province":"Guip\u00f9zcoa",
    "wof:name":"Alvarado Bolea Lucia",
    "wof:placetype":"venue"
},
  "geometry": {"coordinates":[-1.971457243,43.3246192932],"type":"Point"}
}