{
  "type": "Feature",
  "properties": {
    "iso:country":"ES",
    "sg:address":"Calle de Afrodita, 3",
    "sg:city":"Valdemoro",
    "sg:orig_category":"Administradores De Bienes Y Delegados De Comunidades De Propietarios",
    "sg:phone":"+34 918 65 73 48",
    "sg:postcode":"28340",
    "sg:province":"Madrid",
    "wof:name":"Asesoria Y Fincas El Reston S.l.",
    "wof:placetype":"venue"
},
  "geometry": {"coordinates":[-3.6806929111,40.180809021],"type":"Point"}
}