{
  "type": "Feature",
  "properties": {
    "iso:country":"ES",
    "sg:address":"Calle de Reina Do\u00d1a Germana, 5",
    "sg:city":"Valencia",
    "sg:orig_category":"M\u00c9dicos: Pediatr\u00cda. Enfermedades De Los Ni\u00d1os",
    "sg:phone":"+34 963 73 89 94",
    "sg:postcode":"46005",
    "sg:province":"Valencia",
    "wof:name":"Moneva Hernandis Daniel",
    "wof:placetype":"venue"
},
  "geometry": {"coordinates":[-0.366151005,39.4639358521],"type":"Point"}
}