{
  "type": "Feature",
  "properties": {
    "addr:full":"Carr Concordia (de La), 4 Manises Valencia 46940",
    "addr:postcode":"46940",
    "addr:street":"Carr Concordia De La 4",
    "iso:country":"ES",
    "sg:address":"Carr Concordia (de La), 4",
    "sg:city":"Manises",
    "sg:orig_category":"Cristaler\u00cdas",
    "sg:phone":"+34 961 54 51 49",
    "sg:postcode":"46940",
    "sg:province":"Valencia",
    "wof:name":"Unvisa Valencia S.a.",
    "wof:placetype":"venue"
},
  "geometry": {"coordinates":[-0.4614830017,39.4902153015],"type":"Point"}
}