{
  "type": "Feature",
  "properties": {
    "iso:country":"ES",
    "sg:address":"Carrer de L'escorial, 174",
    "sg:city":"Barcelona",
    "sg:classifiers":[
        {
            "category":"Professional",
            "subcategory":"Management & Consulting",
            "type":"Services"
        }
    ],
    "sg:phone":"+34 932 84 57 70",
    "sg:postcode":"08024",
    "sg:province":"Barcelona",
    "sg:tags":[
        "asesor\u00cda",
        "en",
        "marketing"
    ],
    "wof:name":"Prisma Suport Al Marketing S.a.",
    "wof:placetype":"venue"
},
  "geometry": {"coordinates":[2.1581468582,41.4106674194],"type":"Point"}
}