{
  "type": "Feature",
  "properties": {
    "iso:country":"ES",
    "sg:address":"Can Manyoles, 75",
    "sg:city":"Alaro",
    "sg:orig_category":"Arquitectos",
    "sg:phone":"+34 971 51 85 03",
    "sg:postcode":"07340",
    "sg:province":"Islas Baleares",
    "wof:name":"Amengual Ramon Miquel",
    "wof:placetype":"venue"
},
  "geometry": {"coordinates":[2.7933411598,39.7068443298],"type":"Point"}
}