{
  "type": "Feature",
  "properties": {
    "iso:country":"ES",
    "sg:address":"Carr Cervantes, 79",
    "sg:city":"Badalona",
    "sg:orig_category":"Limpieza Industrial",
    "sg:phone":"+34 933 87 45 84",
    "sg:postcode":"08912",
    "sg:province":"Barcelona",
    "wof:name":"Limpiezas Industriales Badalona C.b.",
    "wof:placetype":"venue"
},
  "geometry": {"coordinates":[2.2400479317,41.4399909973],"type":"Point"}
}