{
  "type": "Feature",
  "properties": {
    "addr:full":"Calle de Heros, 28 Bilbao Vizcaya 48009",
    "addr:housenumber":"28",
    "addr:postcode":"48009",
    "addr:street":"Calle De Heros",
    "iso:country":"ES",
    "sg:address":"Calle de Heros, 28",
    "sg:city":"Bilbao",
    "sg:orig_category":"Inmobiliaria (agencias)",
    "sg:phone":"+34 944 24 19 05",
    "sg:postcode":"48009",
    "sg:province":"Vizcaya",
    "wof:name":"Inmobiliaria Mepas S.a.",
    "wof:placetype":"venue"
},
  "geometry": {"coordinates":[-2.9328689575,43.263999939],"type":"Point"}
}