{
  "type": "Feature",
  "properties": {
    "iso:country":"ES",
    "sg:address":"Calle de Dolores Perez Cerralbo, 11",
    "sg:city":"Moron Frontera",
    "sg:orig_category":"Molduras, Junquillos, Listones Y Molduras Perforadas",
    "sg:phone":"+34 954 85 06 03",
    "sg:postcode":"41530",
    "sg:province":"Sevilla",
    "wof:name":"Benitez Cala Raul",
    "wof:placetype":"venue"
},
  "geometry": {"coordinates":[-5.4608640671,37.1216621399],"type":"Point"}
}