{
  "type": "Feature",
  "properties": {
    "iso:country":"ES",
    "sg:address":"Calle de Rosales, 13",
    "sg:city":"Valencia",
    "sg:orig_category":"Curtidos, Curtidos En Blanco",
    "sg:phone":"+34 963 49 78 14",
    "sg:postcode":"46025",
    "sg:province":"Valencia",
    "wof:name":"Anybra S.l.",
    "wof:placetype":"venue"
},
  "geometry": {"coordinates":[-0.3878841996,39.4903755188],"type":"Point"}
}