{
  "type": "Feature",
  "properties": {
    "iso:country":"ES",
    "sg:address":"A Casti\u00f1eira, 2",
    "sg:city":"Casti\u00d1eira",
    "sg:orig_category":"Piedra Natural",
    "sg:phone":"+34 982 16 46 31",
    "sg:postcode":"27286",
    "sg:province":"Lugo",
    "wof:name":"Vali\u00f1a Lopez Jose Maria",
    "wof:placetype":"venue"
},
  "geometry": {"coordinates":[-7.2723321915,43.0619354248],"type":"Point"}
}