{
  "type": "Feature",
  "properties": {
    "iso:country":"ES",
    "sg:address":"Avda Mestra Victoria Miguez (da), 129",
    "sg:city":"Santiago De Compostela",
    "sg:orig_category":"Venta, Montaje De Neum\u00c1ticos",
    "sg:phone":"+34 981 52 25 95",
    "sg:postcode":"15706",
    "sg:province":"La Coru\u00f1a",
    "wof:name":"Pinaque S.l.",
    "wof:placetype":"venue"
},
  "geometry": {"coordinates":[-8.5664587021,42.8709602356],"type":"Point"}
}