{
  "type": "Feature",
  "properties": {
    "iso:country":"ES",
    "sg:address":"Carr Corona, S/n",
    "sg:city":"Almenara",
    "sg:orig_category":"Explotaci\u00d3n De Canteras",
    "sg:phone":"+34 962 13 61 90",
    "sg:postcode":"12590",
    "sg:province":"Castell\u00f3n",
    "wof:name":"Lafarge Aridos Y Hormigones S.a.",
    "wof:placetype":"venue"
},
  "geometry": {"coordinates":[-0.2252819985,39.7522544861],"type":"Point"}
}