{
  "type": "Feature",
  "properties": {
    "addr:full":"Avda Nuestra Se\u00d1ora De Fatima, 86 Madrid Madrid 28047",
    "addr:housenumber":"86",
    "addr:postcode":"madrid;28047",
    "addr:street":"Avda Nuestra Sen\u0303Ora De Fatima",
    "iso:country":"ES",
    "sg:address":"Avda Nuestra Se\u00d1ora De Fatima, 86",
    "sg:city":"Madrid",
    "sg:orig_category":"Arquitectos",
    "sg:phone":"+34 914 62 94 15",
    "sg:postcode":"28047",
    "sg:province":"Madrid",
    "wof:name":"Blazquez Morales Antonio",
    "wof:placetype":"venue"
},
  "geometry": {"coordinates":[-3.7484309673,40.3808021545],"type":"Point"}
}