{
  "type": "Feature",
  "properties": {
    "iso:country":"ES",
    "sg:address":"Calle de Nicanor Pi\u00d1ole, 1",
    "sg:city":"Arriondas",
    "sg:orig_category":"Mercer\u00cda, Lencer\u00cda (al Por Menor)",
    "sg:phone":"+34 985 84 05 98",
    "sg:postcode":"33540",
    "sg:province":"Asturias",
    "wof:name":"Martin Moreno Segundo",
    "wof:placetype":"venue"
},
  "geometry": {"coordinates":[-5.1852741241,43.3902168274],"type":"Point"}
}