{
  "type": "Feature",
  "properties": {
    "iso:country":"ES",
    "sg:address":"Plaz Solobarria, 2",
    "sg:city":"Arizgoiti",
    "sg:orig_category":"Alquiler De V\u00cddeo",
    "sg:phone":"+34 944 49 70 86",
    "sg:postcode":"48970",
    "sg:province":"Vizcaya",
    "wof:name":"Euro Video Y Ocio S.l.",
    "wof:placetype":"venue"
},
  "geometry": {"coordinates":[-2.8848919868,43.238155365],"type":"Point"}
}