{
  "type": "Feature",
  "properties": {
    "iso:country":"ES",
    "sg:address":"Disseminat Barri Creu, S/n",
    "sg:city":"Avia",
    "sg:orig_category":"Cr\u00cda De Animales",
    "sg:phone":"+34 938 23 00 28",
    "sg:postcode":"08610",
    "sg:province":"Barcelona",
    "wof:name":"Figuls S.a.",
    "wof:placetype":"venue"
},
  "geometry": {"coordinates":[1.8156909943,42.0801963806],"type":"Point"}
}