{
  "type": "Feature",
  "properties": {
    "iso:country":"ES",
    "sg:address":"Avda Andalucia, 4",
    "sg:city":"S. Bartolome Torre",
    "sg:orig_category":"Electricidad: Instaladores",
    "sg:phone":"+34 959 38 63 52",
    "sg:postcode":"21510",
    "sg:province":"Huelva",
    "wof:name":"Onucom San Gartolome S.l.l.",
    "wof:placetype":"venue"
},
  "geometry": {"coordinates":[-7.1070542336,37.4466705322],"type":"Point"}
}