{
  "type": "Feature",
  "properties": {
    "iso:country":"ES",
    "sg:address":"Calle de Coimbra, 6",
    "sg:city":"Zaragoza",
    "sg:orig_category":"M\u00c9dicos: Cirug\u00cda Urol\u00d3gica",
    "sg:phone":"+34 976 41 11 56",
    "sg:postcode":"50008",
    "sg:province":"Zaragoza",
    "wof:name":"Salanueva Ferrer Jesus Maria",
    "wof:placetype":"venue"
},
  "geometry": {"coordinates":[-0.8767156005,41.6476020813],"type":"Point"}
}