{
  "type": "Feature",
  "properties": {
    "addr:full":"Avda Luis Gonzalez Taboada, 20 Lalin Pontevedra 36500",
    "addr:housenumber":"20",
    "addr:postcode":"36500",
    "addr:street":"Avda Luis Gonzalez Taboada",
    "iso:country":"ES",
    "sg:address":"Avda Luis Gonzalez Taboada, 20",
    "sg:city":"Lalin",
    "sg:orig_category":"Ropa Para Ni\u00d1os (al Por Menor)",
    "sg:phone":"+34 986 79 20 80",
    "sg:postcode":"36500",
    "sg:province":"Pontevedra",
    "wof:name":"Mini-mercado Dulcinea S.l.",
    "wof:placetype":"venue"
},
  "geometry": {"coordinates":[-8.1124477386,42.6578216553],"type":"Point"}
}