{
  "type": "Feature",
  "properties": {
    "addr:full":"Calle de Etreros, S/n Sangarcia Segovia 40134",
    "addr:housenumber":"s",
    "addr:postcode":"40134",
    "addr:street":"Calle De Etreros;/ N Sangarcia Segovia",
    "iso:country":"ES",
    "sg:address":"Calle de Etreros, S/n",
    "sg:city":"Sangarcia",
    "sg:orig_category":"Producci\u00d3n, Comercio De Cereales",
    "sg:phone":"+34 921 17 80 11",
    "sg:postcode":"40134",
    "sg:province":"Segovia",
    "wof:name":"Cid Gordo Antonio",
    "wof:placetype":"venue"
},
  "geometry": {"coordinates":[-4.4157299995,40.9479103088],"type":"Point"}
}