{
  "type": "Feature",
  "properties": {
    "iso:country":"ES",
    "sg:address":"Calle de Rio Duero, 12",
    "sg:city":"San Vicente Del Raspeig-sant Vicent Del Raspeig",
    "sg:orig_category":"Aparatos E Instalaci\u00d3n De Regad\u00cdos",
    "sg:phone":"+34 965 66 24 46",
    "sg:postcode":"03690",
    "sg:province":"Alicante",
    "sg:website":"www.viverosferpas.com",
    "wof:name":"Fernandez Bartolome Juan",
    "wof:placetype":"venue"
},
  "geometry": {"coordinates":[-0.507965982,38.3926544189],"type":"Point"}
}