{
  "type": "Feature",
  "properties": {
    "addr:full":"Pl De Los Tajillos, 16 Torremolinos M\u00e1laga 29620",
    "addr:housenumber":"16",
    "addr:postcode":"29620",
    "addr:street":"Pl De Los Tajillos;Ma\u0301Laga",
    "iso:country":"ES",
    "sg:address":"Pl De Los Tajillos, 16",
    "sg:city":"Torremolinos",
    "sg:orig_category":"Asesor\u00cda Fiscal Y Jur\u00cddica",
    "sg:phone":"+34 952 37 27 82",
    "sg:postcode":"29620",
    "sg:province":"M\u00e1laga",
    "wof:name":"Moreno Camara Alonso",
    "wof:placetype":"venue"
},
  "geometry": {"coordinates":[-4.4964032173,36.6232833862],"type":"Point"}
}