{
  "type": "Feature",
  "properties": {
    "iso:country":"ES",
    "sg:address":"Carr Maestro Serrano, 1",
    "sg:city":"Canals",
    "sg:orig_category":"Loter\u00cda Y T\u00d3mbola",
    "sg:phone":"+34 962 24 15 27",
    "sg:postcode":"46650",
    "sg:province":"Valencia",
    "wof:name":"Ferrus Martinez Salvador",
    "wof:placetype":"venue"
},
  "geometry": {"coordinates":[-0.5854989886,38.964881897],"type":"Point"}
}