{
  "type": "Feature",
  "properties": {
    "addr:full":"Carrer de Ricard Ankerman, 17 Palma Islas Baleares 07006",
    "addr:housenumber":"17",
    "addr:postcode":"07006",
    "addr:street":"Carrer De Ricard Ankerman",
    "iso:country":"ES",
    "sg:address":"Carrer de Ricard Ankerman, 17",
    "sg:city":"Palma",
    "sg:orig_category":"Encuadernaci\u00d3n E Impresi\u00d3n De Folletos",
    "sg:phone":"+34 971 46 67 19",
    "sg:postcode":"07006",
    "sg:province":"Islas Baleares",
    "wof:name":"Gonzalez Gonzalez Antonio",
    "wof:placetype":"venue"
},
  "geometry": {"coordinates":[2.659719944,39.568107605],"type":"Point"}
}