{
  "type": "Feature",
  "properties": {
    "iso:country":"ES",
    "sg:address":"Calle de Alcalde Sainz De Baranda, 19",
    "sg:city":"Madrid",
    "sg:orig_category":"Ingeniero",
    "sg:phone":"+34 915 73 68 45",
    "sg:postcode":"28009",
    "sg:province":"Madrid",
    "wof:name":"Marino Martin Juan Luis",
    "wof:placetype":"venue"
},
  "geometry": {"coordinates":[-3.67557621,40.4169654846],"type":"Point"}
}