{
  "type": "Feature",
  "properties": {
    "addr:full":"Calle de Padre Vi\u00d1as, 65 Valencia Valencia 46019",
    "addr:housenumber":"65",
    "addr:postcode":"46019",
    "addr:street":"Calle De Padre Vin\u0303As",
    "iso:country":"ES",
    "sg:address":"Calle de Padre Vi\u00d1as, 65",
    "sg:city":"Valencia",
    "sg:orig_category":"Internados & Ense\u00d1anza Privada",
    "sg:phone":"+34 963 66 27 42",
    "sg:postcode":"46019",
    "sg:province":"Valencia",
    "wof:name":"Colegio Mercerator S.l.",
    "wof:placetype":"venue"
},
  "geometry": {"coordinates":[-0.3708199859,39.4939956665],"type":"Point"}
}