{
  "type": "Feature",
  "properties": {
    "addr:full":"Calle de Ramon Y Cajal, 6 Langreo Asturias 33900",
    "addr:housenumber":"6",
    "addr:postcode":"33900",
    "addr:street":"Calle De Ramon Y Cajal",
    "iso:country":"ES",
    "sg:address":"Calle de Ramon Y Cajal, 6",
    "sg:city":"Langreo",
    "sg:orig_category":"Material Y Suministros Para Imprenta E Industrias Gr\u00c1ficas",
    "sg:phone":"+34 985 69 29 48",
    "sg:postcode":"33900",
    "sg:province":"Asturias",
    "wof:name":"Alvarez Alvarez Marcial",
    "wof:placetype":"venue"
},
  "geometry": {"coordinates":[-5.6797528267,43.29296875],"type":"Point"}
}