{
  "type": "Feature",
  "properties": {
    "iso:country":"ES",
    "sg:address":"Avgd Gran Via, De La, 22",
    "sg:city":"Soller",
    "sg:orig_category":"Promotores Constructores",
    "sg:phone":"+34 971 63 47 74",
    "sg:postcode":"07100",
    "sg:province":"Islas Baleares",
    "wof:name":"Andro Deluxe Design Sl",
    "wof:placetype":"venue"
},
  "geometry": {"coordinates":[2.7083287239,39.7749633789],"type":"Point"}
}