{
  "type": "Feature",
  "properties": {
    "addr:full":"Calle de Ricardo Ortiz, 98 Madrid Madrid 28017",
    "addr:housenumber":"98",
    "addr:postcode":"madrid;28017",
    "addr:street":"Calle De Ricardo Ortiz",
    "iso:country":"ES",
    "sg:address":"Calle de Ricardo Ortiz, 98",
    "sg:city":"Madrid",
    "sg:orig_category":"Agencias Y Asesores De Publicidad",
    "sg:phone":"+34 917 25 29 98",
    "sg:postcode":"28017",
    "sg:province":"Madrid",
    "wof:name":"Rojo 4 S.a.",
    "wof:placetype":"venue"
},
  "geometry": {"coordinates":[-3.657679081,40.4231681824],"type":"Point"}
}