{
  "type": "Feature",
  "properties": {
    "addr:full":"Calle de Trinidad, 100 Castellon Castell\u00f3n 12002",
    "addr:housenumber":"100",
    "addr:postcode":"12002",
    "addr:street":"Calle De Trinidad",
    "iso:country":"ES",
    "sg:address":"Calle de Trinidad, 100",
    "sg:city":"Castellon",
    "sg:orig_category":"Ropa Para Ni\u00d1os (al Por Menor)",
    "sg:phone":"+34 964 03 68 20",
    "sg:postcode":"12002",
    "sg:province":"Castell\u00f3n",
    "wof:name":"Viciano Rubert Vicenta Luisa",
    "wof:placetype":"venue"
},
  "geometry": {"coordinates":[-0.0417400002,39.9835395813],"type":"Point"}
}