{
  "type": "Feature",
  "properties": {
    "iso:country":"ES",
    "sg:address":"C/ Lluis Braille, 15",
    "sg:city":"Alcoi",
    "sg:orig_category":"Electrodom\u00c9sticos (al Por Menor)",
    "sg:phone":"+34 965 52 23 04",
    "sg:postcode":"03802",
    "sg:province":"Alicante",
    "wof:name":"Martin Nacher Salvador Jorge",
    "wof:placetype":"venue"
},
  "geometry": {"coordinates":[-0.4861580133,38.6976470947],"type":"Point"}
}