{
  "type": "Feature",
  "properties": {
    "addr:full":"Calle de Toledo, 6 Manzanares Ciudad Real 13200",
    "addr:housenumber":"6",
    "addr:postcode":"13200",
    "addr:street":"Calle De Toledo",
    "iso:country":"ES",
    "sg:address":"Calle de Toledo, 6",
    "sg:city":"Manzanares",
    "sg:orig_category":"Panader\u00cdas, Panader\u00cdas",
    "sg:phone":"+34 926 61 04 15",
    "sg:postcode":"13200",
    "sg:province":"Ciudad Real",
    "wof:name":"Romera Bellon Jose Maria",
    "wof:placetype":"venue"
},
  "geometry": {"coordinates":[-3.3695940971,39.0013198853],"type":"Point"}
}