{
  "type": "Feature",
  "properties": {
    "addr:full":"Calle de Salomon, 8 Malaga M\u00e1laga 29013",
    "addr:housenumber":"8",
    "addr:postcode":"29013",
    "addr:street":"Calle De Salomon;Ma\u0301Laga",
    "iso:country":"ES",
    "sg:address":"Calle de Salomon, 8",
    "sg:city":"Malaga",
    "sg:classifiers":[
        {
            "category":"Government",
            "subcategory":"Post Office",
            "type":"Public Place"
        }
    ],
    "sg:phone":"+34 952 26 21 46",
    "sg:postcode":"29013",
    "sg:province":"M\u00e1laga",
    "sg:tags":[
        "de",
        "yoga",
        "clases"
    ],
    "wof:name":"Gran Fraternidad Universal L. S. E.",
    "wof:placetype":"venue"
},
  "geometry": {"coordinates":[-4.4240589142,36.7275543213],"type":"Point"}
}