{
  "type": "Feature",
  "properties": {
    "addr:full":"Calle de Circunvalacion, S/n Paredes Nava Palencia 34300",
    "addr:postcode":"34300",
    "addr:street":"Calle De Circunvalacion S / N",
    "iso:country":"ES",
    "sg:address":"Calle de Circunvalacion, S/n",
    "sg:city":"Paredes Nava",
    "sg:orig_category":"Construcciones Met\u00c1licas",
    "sg:phone":"+34 979 83 02 00",
    "sg:postcode":"34300",
    "sg:province":"Palencia",
    "wof:name":"Urbano De Jesus S.l.",
    "wof:placetype":"venue"
},
  "geometry": {"coordinates":[-4.6899290085,42.1562957764],"type":"Point"}
}