{
  "type": "Feature",
  "properties": {
    "addr:full":"Plaz Marina (de La), 10 Colmenar Viejo Madrid 28770",
    "addr:postcode":"28770",
    "iso:country":"ES",
    "sg:address":"Plaz Marina (de La), 10",
    "sg:city":"Colmenar Viejo",
    "sg:orig_category":"Zapatos (al Por Menor)",
    "sg:phone":"+34 918 46 29 00",
    "sg:postcode":"28770",
    "sg:province":"Madrid",
    "wof:name":"Gonzalez Botella Jose Antonio",
    "wof:placetype":"venue"
},
  "geometry": {"coordinates":[-3.7699229717,40.6656646729],"type":"Point"}
}