{
  "type": "Feature",
  "properties": {
    "iso:country":"ES",
    "sg:address":"Calle de Constitucion, 2",
    "sg:city":"Madrigueras",
    "sg:orig_category":"Discapacitados",
    "sg:phone":"+34 967 54 53 09",
    "sg:postcode":"02230",
    "sg:province":"Albacete",
    "wof:name":"Asociacion Minusvalidos De Madrigueras",
    "wof:placetype":"venue"
},
  "geometry": {"coordinates":[-1.803057313,39.2324562073],"type":"Point"}
}