{
  "type": "Feature",
  "properties": {
    "iso:country":"ES",
    "sg:address":"Calle de Aguila, S/n",
    "sg:city":"Pampaneira",
    "sg:orig_category":"Fabricaci\u00d3n De Telas Y Sedas",
    "sg:phone":"+34 958 76 30 41",
    "sg:postcode":"18411",
    "sg:province":"Granada",
    "wof:name":"Carrascosa Martin Mercedes",
    "wof:placetype":"venue"
},
  "geometry": {"coordinates":[-3.3604836464,36.9400253296],"type":"Point"}
}