{
  "type": "Feature",
  "properties": {
    "addr:full":"Pol Ind Las Lagunillas, 11 La Carlota C\u00f3rdoba 14100",
    "addr:housenumber":"11",
    "addr:postcode":"14100",
    "addr:street":"Lagunillas",
    "iso:country":"ES",
    "sg:address":"Pol Ind Las Lagunillas, 11",
    "sg:city":"La Carlota",
    "sg:orig_category":"Construcciones Met\u00c1licas",
    "sg:phone":"+34 957 30 19 90",
    "sg:postcode":"14100",
    "sg:province":"C\u00f3rdoba",
    "wof:name":"Dobao Heis Alfonso",
    "wof:placetype":"venue"
},
  "geometry": {"coordinates":[-4.9374890327,37.6685142517],"type":"Point"}
}