{
  "type": "Feature",
  "properties": {
    "addr:full":"Calle de Cid El, 47 Palmas De Gran Canaria Las Palmas 35010",
    "addr:postcode":"35010",
    "addr:street":"Calle De Cid El",
    "iso:country":"ES",
    "sg:address":"Calle de Cid El, 47",
    "sg:city":"Palmas De Gran Canaria",
    "sg:orig_category":"Pescader\u00cdas (al Por Menor)",
    "sg:phone":"+34 928 27 43 46",
    "sg:postcode":"35010",
    "sg:province":"Las Palmas",
    "wof:name":"Freiremar Comercial S.a.",
    "wof:placetype":"venue"
},
  "geometry": {"coordinates":[-15.4370212555,28.1332931519],"type":"Point"}
}