{
  "type": "Feature",
  "properties": {
    "iso:country":"ES",
    "sg:address":"Rua Mondariz, S/n",
    "sg:city":"Vigo",
    "sg:orig_category":"Pescader\u00cdas (al Por Menor)",
    "sg:phone":"+34 986 24 51 72",
    "sg:postcode":"36209",
    "sg:province":"Pontevedra",
    "wof:name":"Fernandez Rdriguez Jesus",
    "wof:placetype":"venue"
},
  "geometry": {"coordinates":[-8.747089386,42.2172050476],"type":"Point"}
}