{
  "type": "Feature",
  "properties": {
    "addr:full":"Calle de Pepin Rivero, 2 Coru\u00d1a La Coru\u00f1a 15011",
    "addr:housenumber":"2",
    "addr:postcode":"15011",
    "addr:street":"Calle De Pepin Rivero;La Corun\u0303A",
    "iso:country":"ES",
    "sg:address":"Calle de Pepin Rivero, 2",
    "sg:city":"Coru\u00d1a",
    "sg:orig_category":"Promotores Constructores",
    "sg:phone":"+34 981 25 27 80",
    "sg:postcode":"15011",
    "sg:province":"La Coru\u00f1a",
    "wof:name":"Orro Sanchez Antonia",
    "wof:placetype":"venue"
},
  "geometry": {"coordinates":[-8.4231157303,43.3709526062],"type":"Point"}
}