{
  "type": "Feature",
  "properties": {
    "addr:full":"Calle de Eras, 23 Fuenlabrada Madrid 28944",
    "addr:housenumber":"23",
    "addr:postcode":"28944",
    "addr:street":"Calle De Eras",
    "iso:country":"ES",
    "sg:address":"Calle de Eras, 23",
    "sg:city":"Fuenlabrada",
    "sg:orig_category":"Centros De Educaci\u00d3n Especial",
    "sg:phone":"+34 916 06 93 04",
    "sg:postcode":"28944",
    "sg:province":"Madrid",
    "wof:name":"Escuela Infantil Luna S.l.",
    "wof:placetype":"venue"
},
  "geometry": {"coordinates":[-3.7918400764,40.2764701843],"type":"Point"}
}