{
  "type": "Feature",
  "properties": {
    "addr:full":"Plaz Huerto Sogueros, 3 Castellon Castell\u00f3n 12001",
    "addr:housenumber":"3",
    "addr:postcode":"12001",
    "addr:street":"Plaz Huerto Sogueros;Castello\u0301N",
    "iso:country":"ES",
    "sg:address":"Plaz Huerto Sogueros, 3",
    "sg:city":"Castellon",
    "sg:orig_category":"Asistencia Y Seguros De Automovilistas Y Turistas",
    "sg:phone":"+34 964 20 30 11",
    "sg:postcode":"12001",
    "sg:province":"Castell\u00f3n",
    "wof:name":"Reial Automobil Club De Catalunya",
    "wof:placetype":"venue"
},
  "geometry": {"coordinates":[-0.0414360017,39.986000061],"type":"Point"}
}