{
  "type": "Feature",
  "properties": {
    "iso:country":"ES",
    "sg:address":"Calle de Orense, 29",
    "sg:city":"Madrid",
    "sg:orig_category":"M\u00c9dicos: Oftalmolog\u00cda",
    "sg:phone":"+34 915 97 03 85",
    "sg:postcode":"28020",
    "sg:province":"Madrid",
    "wof:name":"Sebastian De Erice Sanchez-oca\u00f1a Maria",
    "wof:placetype":"venue"
},
  "geometry": {"coordinates":[-3.6952440739,40.4519233704],"type":"Point"}
}