{
  "type": "Feature",
  "properties": {
    "addr:full":"Barr Monte San Miguel, 29 Monte Cantabria 39012",
    "addr:housenumber":"29",
    "addr:postcode":"39012",
    "addr:street":"San Miguel",
    "iso:country":"ES",
    "sg:address":"Barr Monte San Miguel, 29",
    "sg:city":"Monte",
    "sg:orig_category":"Electricidad: Instaladores",
    "sg:phone":"+34 942 32 15 32",
    "sg:postcode":"39012",
    "sg:province":"Cantabria",
    "wof:name":"Bolado Echevarria Paulino",
    "wof:placetype":"venue"
},
  "geometry": {"coordinates":[-3.8325300217,43.4711952209],"type":"Point"}
}