{
  "type": "Feature",
  "properties": {
    "addr:full":"Cacedo, 20 Cacedo Lugo 27421",
    "addr:housenumber":"20",
    "addr:postcode":"27421",
    "addr:street":"Cacedo",
    "iso:country":"ES",
    "sg:address":"Cacedo, 20",
    "sg:city":"Cacedo",
    "sg:orig_category":"Productores Recolectores, Venta Directa De Vinos",
    "sg:phone":"+34 982 15 29 81",
    "sg:postcode":"27421",
    "sg:province":"Lugo",
    "wof:name":"Verao Perez Jose Ramon",
    "wof:placetype":"venue"
},
  "geometry": {"coordinates":[-7.5907440186,42.4154701233],"type":"Point"}
}