{
  "type": "Feature",
  "properties": {
    "addr:full":"Avda Habana (de La), 26 Ourense Ourense 32003",
    "addr:housenumber":"26",
    "addr:postcode":"32003",
    "addr:street":"Avda Habana De La",
    "iso:country":"ES",
    "sg:address":"Avda Habana (de La), 26",
    "sg:city":"Ourense",
    "sg:orig_category":"Procuradores",
    "sg:phone":"+34 988 37 02 46",
    "sg:postcode":"32003",
    "sg:province":"Ourense",
    "wof:name":"Perez Perez Federico",
    "wof:placetype":"venue"
},
  "geometry": {"coordinates":[-7.865363121,42.3426208496],"type":"Point"}
}