{
  "type": "Feature",
  "properties": {
    "iso:country":"ES",
    "sg:address":"Calle de San Jose, S/n",
    "sg:city":"Linea De La Concepcion",
    "sg:orig_category":"M\u00c9dicos: Ginecolog\u00cda Y Obstetricia",
    "sg:phone":"+34 956 76 44 43",
    "sg:postcode":"11300",
    "sg:province":"C\u00e1diz",
    "wof:name":"Mozo Vergara Manuel",
    "wof:placetype":"venue"
},
  "geometry": {"coordinates":[-5.3471140862,36.1640892029],"type":"Point"}
}