{
  "type": "Feature",
  "properties": {
    "iso:country":"ES",
    "sg:address":"Calle de Virgen De Africa, 30",
    "sg:city":"Ibi",
    "sg:orig_category":"Fabricaci\u00d3n De Moldes Y Modelos",
    "sg:phone":"+34 965 55 39 84",
    "sg:postcode":"03440",
    "sg:province":"Alicante",
    "wof:name":"Soldaduras Sanjuan S.l.",
    "wof:placetype":"venue"
},
  "geometry": {"coordinates":[-0.5806407928,38.6182403564],"type":"Point"}
}