{
  "type": "Feature",
  "properties": {
    "addr:full":"Calle de Monte Esquinza, 41 Madrid Madrid 28010",
    "addr:housenumber":"41",
    "addr:postcode":"madrid;28010",
    "addr:street":"Calle De Monte Esquinza",
    "iso:country":"ES",
    "sg:address":"Calle de Monte Esquinza, 41",
    "sg:city":"Madrid",
    "sg:orig_category":"Inform\u00c1tica: Consultores",
    "sg:phone":"+34 913 91 30 44",
    "sg:postcode":"28010",
    "sg:province":"Madrid",
    "wof:name":"Ca\u00f1a Multimedia Group",
    "wof:placetype":"venue"
},
  "geometry": {"coordinates":[-3.6920080185,40.4304161072],"type":"Point"}
}