{
  "type": "Feature",
  "properties": {
    "addr:full":"Pla\u00c7 Barranquet (del), 8 Manises Valencia 46940",
    "addr:postcode":"46940",
    "iso:country":"ES",
    "sg:address":"Pla\u00c7 Barranquet (del), 8",
    "sg:city":"Manises",
    "sg:orig_category":"Comercio De Hierro",
    "sg:phone":"+34 961 52 46 33",
    "sg:postcode":"46940",
    "sg:province":"Valencia",
    "wof:name":"Ferros",
    "wof:placetype":"venue"
},
  "geometry": {"coordinates":[-0.461488992,39.4922943115],"type":"Point"}
}