{
  "type": "Feature",
  "properties": {
    "addr:full":"Calle de Valle De Ordesa, S/n Monzon Huesca 22400",
    "addr:housenumber":"s / n",
    "addr:postcode":"22400",
    "addr:street":"Calle De Valle De Ordesa",
    "iso:country":"ES",
    "sg:address":"Calle de Valle De Ordesa, S/n",
    "sg:city":"Monzon",
    "sg:orig_category":"Electricidad: Instaladores",
    "sg:phone":"+34 974 40 48 04",
    "sg:postcode":"22400",
    "sg:province":"Huesca",
    "wof:name":"Servicios Electricos Y De Comunicacion Monzon S.l.",
    "wof:placetype":"venue"
},
  "geometry": {"coordinates":[0.180855006,41.9249000549],"type":"Point"}
}