{
  "type": "Feature",
  "properties": {
    "addr:full":"Carr Madrid, 60 Eivissa Islas Baleares 07800",
    "addr:housenumber":"60",
    "addr:postcode":"07800",
    "addr:street":"Carr Madrid",
    "iso:country":"ES",
    "sg:address":"Carr Madrid, 60",
    "sg:city":"Eivissa",
    "sg:orig_category":"Electromec\u00c1nica",
    "sg:phone":"+34 971 31 40 61",
    "sg:postcode":"07800",
    "sg:province":"Islas Baleares",
    "wof:name":"Munar Escandell Juan",
    "wof:placetype":"venue"
},
  "geometry": {"coordinates":[1.4296790361,38.9124794006],"type":"Point"}
}