{
  "type": "Feature",
  "properties": {
    "iso:country":"ES",
    "sg:address":"Goribar Auzoa, 16",
    "sg:city":"Goribar",
    "sg:orig_category":"Serrer\u00cdas De Madera",
    "sg:phone":"+34 943 78 09 58",
    "sg:postcode":"20560",
    "sg:province":"Guip\u00f9zcoa",
    "wof:name":"Serreria Barren-zelai S.l.",
    "wof:placetype":"venue"
},
  "geometry": {"coordinates":[-2.4079990387,43.0313835144],"type":"Point"}
}