{
  "type": "Feature",
  "properties": {
    "addr:full":"Pase Estacion (la), 51 Jaen Ja\u00e9n 23007",
    "addr:postcode":"23007",
    "addr:street":"Jae\u0301N",
    "iso:country":"ES",
    "sg:address":"Pase Estacion (la), 51",
    "sg:city":"Jaen",
    "sg:orig_category":"Muebles, Minoristas",
    "sg:phone":"+34 953 25 35 20",
    "sg:postcode":"23007",
    "sg:province":"Ja\u00e9n",
    "wof:name":"Cocistylo S.l.",
    "wof:placetype":"venue"
},
  "geometry": {"coordinates":[-3.7895879745,37.7782325745],"type":"Point"}
}