{
  "type": "Feature",
  "properties": {
    "addr:full":"Calle de Do\u00d1a Maria Coronel, 10 Sevilla Sevilla 41003",
    "addr:housenumber":"10",
    "addr:postcode":"41003",
    "addr:street":"Calle De Don\u0303A Maria Coronel",
    "iso:country":"ES",
    "sg:address":"Calle de Do\u00d1a Maria Coronel, 10",
    "sg:city":"Sevilla",
    "sg:orig_category":"Clases De M\u00dasica Y Canto",
    "sg:phone":"+34 954 22 13 33",
    "sg:postcode":"41003",
    "sg:province":"Sevilla",
    "sg:website":"www.arteaula.com",
    "wof:name":"Musicaula S.c.",
    "wof:placetype":"venue"
},
  "geometry": {"coordinates":[-5.9896593094,37.3929634094],"type":"Point"}
}