{
  "type": "Feature",
  "properties": {
    "addr:full":"Calle de Nicolas De Las Pe\u00d1as, 3 Beniel Murcia 30130",
    "addr:housenumber":"3",
    "addr:postcode":"30130",
    "addr:street":"Calle De Nicolas De Las Pen\u0303As",
    "iso:country":"ES",
    "sg:address":"Calle de Nicolas De Las Pe\u00d1as, 3",
    "sg:city":"Beniel",
    "sg:orig_category":"Molduras, Junquillos, Listones Y Molduras Perforadas",
    "sg:phone":"+34 968 60 03 71",
    "sg:postcode":"30130",
    "sg:province":"Murcia",
    "wof:name":"Garcia Martinez Jose",
    "wof:placetype":"venue"
},
  "geometry": {"coordinates":[-1.002581954,38.0459976196],"type":"Point"}
}