{
  "type": "Feature",
  "properties": {
    "addr:full":"Avda Argentina, 5 Maracena Granada 18200",
    "addr:housenumber":"5",
    "addr:postcode":"18200",
    "addr:street":"Avda Argentina",
    "iso:country":"ES",
    "sg:address":"Avda Argentina, 5",
    "sg:city":"Maracena",
    "sg:orig_category":"Alimentaci\u00d3n General (al Por Menor)",
    "sg:phone":"+34 958 42 16 65",
    "sg:postcode":"18200",
    "sg:province":"Granada",
    "wof:name":"Fernandez Hervas Rosa Maria",
    "wof:placetype":"venue"
},
  "geometry": {"coordinates":[-3.6394989491,37.2092018127],"type":"Point"}
}