{
  "type": "Feature",
  "properties": {
    "iso:country":"ES",
    "sg:address":"Carrer de Montseny, 131",
    "sg:city":"Hospitalet Llobregat",
    "sg:orig_category":"Electrodom\u00c9sticos (al Por Menor)",
    "sg:phone":"+34 934 48 50 10",
    "sg:postcode":"08904",
    "sg:province":"Barcelona",
    "wof:name":"Masood  Muhammad",
    "wof:placetype":"venue"
},
  "geometry": {"coordinates":[2.1194529533,41.3699188232],"type":"Point"}
}