{
  "type": "Feature",
  "properties": {
    "iso:country":"ES",
    "sg:address":"Calle de Republica Argentina, 2",
    "sg:city":"Ponferrada",
    "sg:orig_category":"Muebles, Minoristas",
    "sg:phone":"+34 987 41 08 99",
    "sg:postcode":"24400",
    "sg:province":"Le\u00f3n",
    "wof:name":"Diz Gomez Odilo",
    "wof:placetype":"venue"
},
  "geometry": {"coordinates":[-6.6007847786,42.548324585],"type":"Point"}
}