{
  "type": "Feature",
  "properties": {
    "addr:full":"Pla\u00c7 Mercat (del), S/n Algemesi Valencia 46680",
    "addr:housenumber":"/ n",
    "addr:postcode":"46680",
    "addr:street":"S",
    "iso:country":"ES",
    "sg:address":"Pla\u00c7 Mercat (del), S/n",
    "sg:city":"Algemesi",
    "sg:orig_category":"Carnicer\u00cdas, Carnicer\u00cdas",
    "sg:phone":"+34 962 42 37 50",
    "sg:postcode":"46680",
    "sg:province":"Valencia",
    "wof:name":"V.r.and B. 99 S.l.",
    "wof:placetype":"venue"
},
  "geometry": {"coordinates":[-0.4313729107,39.2159690857],"type":"Point"}
}