{
  "type": "Feature",
  "properties": {
    "addr:full":"Calle de Angeles, 8 Sevilla Sevilla 41004",
    "addr:housenumber":"8",
    "addr:postcode":"41004",
    "addr:street":"Calle De Angeles",
    "iso:country":"ES",
    "sg:address":"Calle de Angeles, 8",
    "sg:city":"Sevilla",
    "sg:orig_category":"Ingeniero",
    "sg:phone":"+34 954 22 87 04",
    "sg:postcode":"41004",
    "sg:province":"Sevilla",
    "wof:name":"Roca Ramirez Manuel",
    "wof:placetype":"venue"
},
  "geometry": {"coordinates":[-5.9906353951,37.3863525391],"type":"Point"}
}