{
  "type": "Feature",
  "properties": {
    "iso:country":"ES",
    "sg:address":"Trva 2 Gaiteira, 4",
    "sg:city":"Coru\u00d1a",
    "sg:orig_category":"Ense\u00d1anza: Peluquer\u00cda Est\u00c9tica",
    "sg:phone":"+34 981 13 91 79",
    "sg:postcode":"15009",
    "sg:province":"La Coru\u00f1a",
    "wof:name":"Rial Ba\u00f1a Monica",
    "wof:placetype":"venue"
},
  "geometry": {"coordinates":[-8.3952102661,43.3400611877],"type":"Point"}
}