{
  "type": "Feature",
  "properties": {
    "iso:country":"ES",
    "sg:address":"Afueras, S/n",
    "sg:city":"Villanueva Huerva",
    "sg:orig_category":"Ba\u00d1os Y Duchas P\u00dablicos",
    "sg:phone":"+34 976 14 34 35",
    "sg:postcode":"50153",
    "sg:province":"Zaragoza",
    "wof:name":"Ayuntamiento De Villanueva Del Huerva",
    "wof:placetype":"venue"
},
  "geometry": {"coordinates":[-1.0365929604,41.3519592285],"type":"Point"}
}