{
  "type": "Feature",
  "properties": {
    "addr:full":"Calle de Mayor, 124 Tobarra Albacete 02500",
    "addr:housenumber":"124",
    "addr:postcode":"02500",
    "addr:street":"Calle De Mayor",
    "iso:country":"ES",
    "sg:address":"Calle de Mayor, 124",
    "sg:city":"Tobarra",
    "sg:orig_category":"Mercer\u00cda, Lencer\u00cda (al Por Menor)",
    "sg:phone":"+34 967 32 89 76",
    "sg:postcode":"02500",
    "sg:province":"Albacete",
    "wof:name":"Arteseros Garcia Jorge Juan",
    "wof:placetype":"venue"
},
  "geometry": {"coordinates":[-1.6893219948,38.5917930603],"type":"Point"}
}