{
  "type": "Feature",
  "properties": {
    "iso:country":"ES",
    "sg:address":"Cra. Corbera, Km. 0005,0",
    "sg:city":"La Palma De Cervello",
    "sg:orig_category":"Metacrilato: Art\u00cdculos (fabricaci\u00d3n Y Al Por Mayor)",
    "sg:phone":"+34 936 88 16 19",
    "sg:postcode":"08756",
    "sg:province":"Barcelona",
    "sg:website":"www.plasticos-quimol.com",
    "wof:name":"Plasticos Quimol S.l.",
    "wof:placetype":"venue"
},
  "geometry": {"coordinates":[1.9652750492,41.4137763977],"type":"Point"}
}