{
  "type": "Feature",
  "properties": {
    "iso:country":"ES",
    "sg:address":"C/ Jose Diez Mora, 53",
    "sg:city":"Elche",
    "sg:orig_category":"Electromec\u00c1nica",
    "sg:phone":"+34 965 44 97 11",
    "sg:postcode":"03205",
    "sg:province":"Alicante",
    "wof:name":"Naharro Sanchez Juan",
    "wof:placetype":"venue"
},
  "geometry": {"coordinates":[-0.7131490111,38.2704582214],"type":"Point"}
}