{
  "type": "Feature",
  "properties": {
    "iso:country":"ES",
    "sg:address":"Pl Vila, 19",
    "sg:city":"Sant Vicen\u00c7 Dels Horts",
    "sg:orig_category":"Herboristas (al Por Menor)",
    "sg:phone":"+34 936 56 50 67",
    "sg:postcode":"08620",
    "sg:province":"Barcelona",
    "wof:name":"Bernal Hernandez Manuel",
    "wof:placetype":"venue"
},
  "geometry": {"coordinates":[2.0102651119,41.3935241699],"type":"Point"}
}