{
  "type": "Feature",
  "properties": {
    "iso:country":"ES",
    "sg:address":"Carrer de Llibertat, 17",
    "sg:city":"Palma",
    "sg:orig_category":"Empresas De Carpinter\u00cda Met\u00c1lica",
    "sg:phone":"+34 971 73 76 31",
    "sg:postcode":"07013",
    "sg:province":"Islas Baleares",
    "wof:name":"Covas Cantallops Vicente",
    "wof:placetype":"venue"
},
  "geometry": {"coordinates":[2.6346681118,39.577003479],"type":"Point"}
}