{
  "type": "Feature",
  "properties": {
    "addr:full":"Avda Madrid, 1 Adrada \u00c1vila 05430",
    "addr:housenumber":"1",
    "addr:postcode":"05430",
    "addr:street":"Avda Madrid",
    "iso:country":"ES",
    "sg:address":"Avda Madrid, 1",
    "sg:city":"Adrada",
    "sg:orig_category":"Negocio De Materiales De Construcci\u00d3n",
    "sg:phone":"+34 918 67 04 51",
    "sg:postcode":"05430",
    "sg:province":"\u00c1vila",
    "wof:name":"Carlos Rivas E Hijos S.l.",
    "wof:placetype":"venue"
},
  "geometry": {"coordinates":[-4.629696846,40.3013534546],"type":"Point"}
}