{
  "type": "Feature",
  "properties": {
    "iso:country":"ES",
    "sg:address":"Avda Constitucion, 10",
    "sg:city":"Villa Don Fadrique",
    "sg:orig_category":"Carnicer\u00cdas, Carnicer\u00cdas",
    "sg:phone":"+34 925 19 54 42",
    "sg:postcode":"45850",
    "sg:province":"Toledo",
    "wof:name":"Carpintero Tello Alejandro",
    "wof:placetype":"venue"
},
  "geometry": {"coordinates":[-3.2279889584,39.6153907776],"type":"Point"}
}