{
  "type": "Feature",
  "properties": {
    "addr:full":"Rond General Mitre, 27 Barcelona Barcelona 08017",
    "addr:housenumber":"27",
    "addr:postcode":"08017",
    "iso:country":"ES",
    "sg:address":"Rond General Mitre, 27",
    "sg:city":"Barcelona",
    "sg:orig_category":"Peluquer\u00cdas, Peluquer\u00cda Mixta",
    "sg:phone":"+34 932 80 59 30",
    "sg:postcode":"08017",
    "sg:province":"Barcelona",
    "wof:name":"Nuevo Lastra Ana Maria",
    "wof:placetype":"venue"
},
  "geometry": {"coordinates":[2.1322569847,41.393901825],"type":"Point"}
}