{
  "type": "Feature",
  "properties": {
    "iso:country":"ES",
    "sg:address":"Calle de Cerro (del), 47",
    "sg:city":"Navas Del Marques",
    "sg:orig_category":"Muebles Y Accesorios Para Cocinas Y Cuartos De Ba\u00d1o (al Por Menor)",
    "sg:phone":"+34 918 97 00 45",
    "sg:postcode":"05230",
    "sg:province":"\u00c1vila",
    "wof:name":"Incorisa S.l.",
    "wof:placetype":"venue"
},
  "geometry": {"coordinates":[-4.3322014809,40.5962409973],"type":"Point"}
}