{
  "type": "Feature",
  "properties": {
    "iso:country":"ES",
    "sg:address":"Avda Duque De Arcos, 15",
    "sg:city":"Arcos Frontera",
    "sg:orig_category":"Imprenta",
    "sg:phone":"+34 956 70 09 21",
    "sg:postcode":"11630",
    "sg:province":"C\u00e1diz",
    "wof:name":"Garcia Nieto Jesus",
    "wof:placetype":"venue"
},
  "geometry": {"coordinates":[-5.817152977,36.7501678467],"type":"Point"}
}