{
  "type": "Feature",
  "properties": {
    "iso:country":"ES",
    "sg:address":"Pase Canalejas, 104",
    "sg:city":"Salamanca",
    "sg:orig_category":"Fabricaci\u00d3n, Instalaci\u00d3n De Armarios",
    "sg:phone":"+34 923 26 99 52",
    "sg:postcode":"37001",
    "sg:province":"Salamanca",
    "wof:name":"Cobaleda Martin Jose Ignacio",
    "wof:placetype":"venue"
},
  "geometry": {"coordinates":[-5.6585187912,40.9633102417],"type":"Point"}
}