{
  "type": "Feature",
  "properties": {
    "addr:full":"Urb Castillo Caleta De Fuste, S/n Caleta De Fuste Las Palmas 35610",
    "addr:housenumber":"/ n",
    "addr:postcode":"35610",
    "addr:street":"Urb Castillo Caleta;Fuste S;Palmas",
    "iso:country":"ES",
    "sg:address":"Urb Castillo Caleta De Fuste, S/n",
    "sg:city":"Caleta De Fuste",
    "sg:classifiers":[
        {
            "category":"Personal",
            "subcategory":"Barber",
            "type":"Services"
        }
    ],
    "sg:phone":"+34 928 16 00 64",
    "sg:postcode":"35610",
    "sg:province":"Las Palmas",
    "sg:tags":[
        "caballeros",
        "de",
        "peluqueros"
    ],
    "sg:website":"www.jerezpeluqueros.com",
    "wof:name":"Jerez Pe\u00d1a S.l.",
    "wof:placetype":"venue"
},
  "geometry": {"coordinates":[-13.863199234,28.3980941772],"type":"Point"}
}