{
  "type": "Feature",
  "properties": {
    "iso:country":"ES",
    "sg:address":"Calle de Isabel Mendez, 16",
    "sg:city":"Madrid",
    "sg:orig_category":"Asesor\u00cdas Y Estudios Financieros",
    "sg:phone":"+34 914 39 92 32",
    "sg:postcode":"28038",
    "sg:province":"Madrid",
    "wof:name":"Parra Maudes Cristina",
    "wof:placetype":"venue"
},
  "geometry": {"coordinates":[-3.662058115,40.3973236084],"type":"Point"}
}