{
  "type": "Feature",
  "properties": {
    "iso:country":"ES",
    "sg:address":"Gta Ingeniero La Cierva, S/n",
    "sg:city":"Cadiz",
    "sg:orig_category":"Heladeros",
    "sg:phone":"+34 956 25 14 53",
    "sg:postcode":"11010",
    "sg:province":"C\u00e1diz",
    "wof:name":"Sanchez Cuenca Otilia",
    "wof:placetype":"venue"
},
  "geometry": {"coordinates":[-6.2768731117,36.5051879883],"type":"Point"}
}