{
  "type": "Feature",
  "properties": {
    "iso:country":"ES",
    "sg:address":"Santamaria-andre Mari Kalea, 12",
    "sg:city":"Ordizia",
    "sg:orig_category":"Peluquer\u00cdas",
    "sg:phone":"+34 943 88 89 77",
    "sg:postcode":"20240",
    "sg:province":"Guip\u00f9zcoa",
    "wof:name":"Requerey Serrano Irene",
    "wof:placetype":"venue"
},
  "geometry": {"coordinates":[-2.1773040295,43.0538711548],"type":"Point"}
}