{
  "type": "Feature",
  "properties": {
    "iso:country":"ES",
    "sg:address":"Av Notari Alemany, S/n",
    "sg:city":"Magaluf",
    "sg:orig_category":"Fabricaci\u00d3n, Distribuci\u00d3n De Discos, V\u00cddeodiscos Y Musicassettes",
    "sg:phone":"+34 971 13 12 85",
    "sg:postcode":"07181",
    "sg:province":"Islas Baleares",
    "wof:name":"Roca Gibert Maria Angeles",
    "wof:placetype":"venue"
},
  "geometry": {"coordinates":[2.5319979191,39.5045471191],"type":"Point"}
}