{
  "type": "Feature",
  "properties": {
    "addr:full":"Calle de Luis Montoto, 130 Sevilla Sevilla 41005",
    "addr:housenumber":"130",
    "addr:postcode":"41005",
    "addr:street":"Calle De Luis Montoto",
    "iso:country":"ES",
    "sg:address":"Calle de Luis Montoto, 130",
    "sg:city":"Sevilla",
    "sg:orig_category":"Zapatos (al Por Menor)",
    "sg:phone":"+34 954 57 60 57",
    "sg:postcode":"41005",
    "sg:province":"Sevilla",
    "sg:website":"www.pilarburgos.com",
    "wof:name":"Bertozzi S.a.",
    "wof:placetype":"venue"
},
  "geometry": {"coordinates":[-5.9701418877,37.387298584],"type":"Point"}
}