{
  "type": "Feature",
  "properties": {
    "iso:country":"ES",
    "sg:address":"Vado Del Alamo, 1",
    "sg:city":"Alora",
    "sg:orig_category":"Panader\u00cdas, Pasteler\u00cdas, Boller\u00cda Industriale (fabricaci\u00d3n, Al Por Mayor)",
    "sg:phone":"+34 952 49 61 77",
    "sg:postcode":"29500",
    "sg:province":"M\u00e1laga",
    "wof:name":"Industria Confiteria Perota S.l.",
    "wof:placetype":"venue"
},
  "geometry": {"coordinates":[-4.6967186928,36.872303009],"type":"Point"}
}