{
  "type": "Feature",
  "properties": {
    "addr:full":"Calle de Ruiz De Alda, S/n Selaya Cantabria 39696",
    "addr:housenumber":"s / n",
    "addr:postcode":"39696",
    "addr:street":"Calle De Ruiz De Alda",
    "iso:country":"ES",
    "sg:address":"Calle de Ruiz De Alda, S/n",
    "sg:city":"Selaya",
    "sg:orig_category":"Quincaller\u00cda (al Por Mayor)",
    "sg:phone":"+34 942 59 10 90",
    "sg:postcode":"39696",
    "sg:province":"Cantabria",
    "wof:name":"Ocejo Cobo Francisco",
    "wof:placetype":"venue"
},
  "geometry": {"coordinates":[-3.806730032,43.2161598206],"type":"Point"}
}