{
  "type": "Feature",
  "properties": {
    "iso:country":"ES",
    "sg:address":"Crta. De Villarrubia, Km. 0002,0",
    "sg:city":"Manzanares",
    "sg:orig_category":"Aparatos E Instalaci\u00d3n De Regad\u00cdos",
    "sg:phone":"+34 926 69 60 30",
    "sg:postcode":"13200",
    "sg:province":"Ciudad Real",
    "wof:name":"Inmopen De La Mancha S.l.",
    "wof:placetype":"venue"
},
  "geometry": {"coordinates":[-3.373128891,38.994140625],"type":"Point"}
}