{
  "type": "Feature",
  "properties": {
    "addr:full":"Rua San Francisco, 8 Cambados Pontevedra 36630",
    "addr:housenumber":"8",
    "addr:postcode":"36630",
    "addr:street":"Rua San Francisco",
    "iso:country":"ES",
    "sg:address":"Rua San Francisco, 8",
    "sg:city":"Cambados",
    "sg:orig_category":"Farmacias",
    "sg:phone":"+34 986 52 60 41",
    "sg:postcode":"36630",
    "sg:province":"Pontevedra",
    "wof:name":"Mari\u00d1a Farma S.c",
    "wof:placetype":"venue"
},
  "geometry": {"coordinates":[-8.7817115784,42.2641181946],"type":"Point"}
}