{
  "type": "Feature",
  "properties": {
    "iso:country":"ES",
    "sg:address":"Calle de Gabiria, 54",
    "sg:city":"Irun",
    "sg:orig_category":"Material Ferroviario",
    "sg:phone":"+34 943 53 66 78",
    "sg:postcode":"20305",
    "sg:province":"Guip\u00f9zcoa",
    "wof:name":"Talleres Ago S.l.",
    "wof:placetype":"venue"
},
  "geometry": {"coordinates":[-1.8278019428,43.3265647888],"type":"Point"}
}