{
  "type": "Feature",
  "properties": {
    "addr:full":"Av Sant Julia, 148 Granollers Barcelona 08403",
    "addr:housenumber":"148",
    "addr:postcode":"08403",
    "addr:street":"Av Sant Julia",
    "iso:country":"ES",
    "sg:address":"Av Sant Julia, 148",
    "sg:city":"Granollers",
    "sg:orig_category":"Alquiler De Veh\u00cdculos: Turismos Y Utilitarios",
    "sg:phone":"+34 938 40 48 00",
    "sg:postcode":"08403",
    "sg:province":"Barcelona",
    "wof:name":"Fraikin S.a.",
    "wof:placetype":"venue"
},
  "geometry": {"coordinates":[2.2740049362,41.5879974365],"type":"Point"}
}