{
  "type": "Feature",
  "properties": {
    "addr:full":"Carr Bailen, 2 Girona Girona 17002",
    "addr:housenumber":"2",
    "addr:postcode":"17002",
    "addr:street":"Carr Bailen",
    "iso:country":"ES",
    "sg:address":"Carr Bailen, 2",
    "sg:city":"Girona",
    "sg:orig_category":"Abogados",
    "sg:phone":"+34 972 22 89 69",
    "sg:postcode":"17002",
    "sg:province":"Girona",
    "wof:name":"Alsina Conesa Marta",
    "wof:placetype":"venue"
},
  "geometry": {"coordinates":[2.8183329105,41.980052948],"type":"Point"}
}