{
  "type": "Feature",
  "properties": {
    "addr:full":"Barr Osma, S/n Osma Vizcaya 48269",
    "addr:housenumber":"s / n",
    "addr:postcode":"48269",
    "iso:country":"ES",
    "sg:address":"Barr Osma, S/n",
    "sg:city":"Osma",
    "sg:orig_category":"Vinos Y Licores (venta Al Por Menor)",
    "sg:phone":"+34 943 17 51 18",
    "sg:postcode":"48269",
    "sg:province":"Vizcaya",
    "wof:name":"Disherlop S.l",
    "wof:placetype":"venue"
},
  "geometry": {"coordinates":[-2.5300109386,43.1897888184],"type":"Point"}
}