{
  "type": "Feature",
  "properties": {
    "addr:full":"Ctra Vic, 21 Manresa Barcelona 08241",
    "addr:housenumber":"21",
    "addr:postcode":"08241",
    "addr:street":"Ctra Vic",
    "iso:country":"ES",
    "sg:address":"Ctra Vic, 21",
    "sg:city":"Manresa",
    "sg:orig_category":"Animales (al Por Menor)",
    "sg:phone":"+34 938 72 09 71",
    "sg:postcode":"08241",
    "sg:province":"Barcelona",
    "wof:name":"Fornells Costa Josep",
    "wof:placetype":"venue"
},
  "geometry": {"coordinates":[1.8262269497,41.7261924744],"type":"Point"}
}