{
  "type": "Feature",
  "properties": {
    "iso:country":"ES",
    "sg:address":"Psaj Avenencia, 12",
    "sg:city":"Madrid",
    "sg:orig_category":"Venta, Instalaci\u00d3n, Reparaci\u00d3n De Antenas Para Televisi\u00d3n",
    "sg:phone":"+34 913 18 23 25",
    "sg:postcode":"28041",
    "sg:province":"Madrid",
    "wof:name":"Cavisat Digital S.a.",
    "wof:placetype":"venue"
},
  "geometry": {"coordinates":[-3.6872758865,40.3579368591],"type":"Point"}
}