{
  "type": "Feature",
  "properties": {
    "addr:full":"Avda Guardia Civil, 8 S. Clemente Cuenca 16600",
    "addr:housenumber":"8",
    "addr:postcode":"16600",
    "addr:street":"Avda Guardia Civil;Clemente",
    "iso:country":"ES",
    "sg:address":"Avda Guardia Civil, 8",
    "sg:city":"S. Clemente",
    "sg:orig_category":"Escayola Y Productos De Escayola (fabricaci\u00d3n, Al Por Mayor)",
    "sg:phone":"+34 969 30 09 96",
    "sg:postcode":"16600",
    "sg:province":"Cuenca",
    "wof:name":"Escayolas Ignacio S.l",
    "wof:placetype":"venue"
},
  "geometry": {"coordinates":[-2.4270188808,39.3993186951],"type":"Point"}
}