{
  "type": "Feature",
  "properties": {
    "iso:country":"ES",
    "sg:address":"Carrer de Calderon De La Barca, 75",
    "sg:city":"Barcelona",
    "sg:orig_category":"Construcciones Met\u00c1licas",
    "sg:phone":"+34 933 57 36 51",
    "sg:postcode":"08032",
    "sg:province":"Barcelona",
    "wof:name":"Construcciones Casado S.a.",
    "wof:placetype":"venue"
},
  "geometry": {"coordinates":[2.1566441059,41.4211921692],"type":"Point"}
}