{
  "type": "Feature",
  "properties": {
    "iso:country":"ES",
    "sg:address":"Avda Baron De Warsage, 16",
    "sg:city":"Calatayud",
    "sg:orig_category":"Rectificaci\u00d3n, Mecanizado, Fresado",
    "sg:phone":"+34 976 88 00 93",
    "sg:postcode":"50300",
    "sg:province":"Zaragoza",
    "wof:name":"Arturo Gines S.cv.",
    "wof:placetype":"venue"
},
  "geometry": {"coordinates":[-1.6363551617,41.3536453247],"type":"Point"}
}