{
  "type": "Feature",
  "properties": {
    "addr:full":"M. Deu Angels, 5 Berga Barcelona 08600",
    "addr:housenumber":"5",
    "addr:postcode":"08600",
    "addr:street":"M.",
    "iso:country":"ES",
    "sg:address":"M. Deu Angels, 5",
    "sg:city":"Berga",
    "sg:orig_category":"Ense\u00d1anza: Costura",
    "sg:phone":"+34 938 21 01 52",
    "sg:postcode":"08600",
    "sg:province":"Barcelona",
    "wof:name":"Camprubi Zaragoza Maria Dolores",
    "wof:placetype":"venue"
},
  "geometry": {"coordinates":[1.8460960388,42.1036682129],"type":"Point"}
}