{
  "type": "Feature",
  "properties": {
    "addr:full":"Calle de Botanico Rivas Mateo, S/n Caceres C\u00e1ceres 10001",
    "addr:postcode":"10001",
    "addr:street":"Calle De Botanico Rivas Mateo S / N;Ca\u0301Ceres",
    "iso:country":"ES",
    "sg:address":"Calle de Botanico Rivas Mateo, S/n",
    "sg:city":"Caceres",
    "sg:orig_category":"Asociaciones, Organismos Culturales Y Socioeducativos",
    "sg:phone":"+34 927 24 32 11",
    "sg:postcode":"10001",
    "sg:province":"C\u00e1ceres",
    "wof:name":"Circulo La Concordia",
    "wof:placetype":"venue"
},
  "geometry": {"coordinates":[-6.3817892075,39.4735641479],"type":"Point"}
}