{
  "type": "Feature",
  "properties": {
    "iso:country":"ES",
    "sg:address":"Av Ave Maria, 16",
    "sg:city":"Escala",
    "sg:orig_category":"Panader\u00cdas, Panader\u00cdas",
    "sg:phone":"+34 972 77 60 34",
    "sg:postcode":"17130",
    "sg:province":"Girona",
    "wof:name":"Peraferrer Palau Miquel",
    "wof:placetype":"venue"
},
  "geometry": {"coordinates":[3.1346230507,42.1233673096],"type":"Point"}
}