{
  "type": "Feature",
  "properties": {
    "iso:country":"ES",
    "sg:address":"Calle de Sabino Arana, 12",
    "sg:city":"Santurtzi",
    "sg:orig_category":"Zapatos (al Por Menor)",
    "sg:phone":"+34 944 61 73 71",
    "sg:postcode":"48980",
    "sg:province":"Vizcaya",
    "wof:name":"Baroja Ruiz De Azua Alfredo",
    "wof:placetype":"venue"
},
  "geometry": {"coordinates":[-3.0343749523,43.3302726746],"type":"Point"}
}