{
  "type": "Feature",
  "properties": {
    "iso:country":"ES",
    "sg:address":"Calle de Maestra, 139",
    "sg:city":"Mancha Real",
    "sg:orig_category":"Electrodom\u00c9sticos (al Por Menor)",
    "sg:phone":"+34 953 35 03 11",
    "sg:postcode":"23100",
    "sg:province":"Ja\u00e9n",
    "wof:name":"Romero Gonzalez Antonio",
    "wof:placetype":"venue"
},
  "geometry": {"coordinates":[-3.6082599163,37.7866249084],"type":"Point"}
}