{
  "type": "Feature",
  "properties": {
    "addr:full":"Ctro Cial Miramar, S/n Fuengirola M\u00e1laga 29640",
    "addr:housenumber":"s / n",
    "addr:postcode":"29640",
    "addr:street":"Ma\u0301Laga",
    "iso:country":"ES",
    "sg:address":"Ctro Cial Miramar, S/n",
    "sg:city":"Fuengirola",
    "sg:classifiers":[
        {
            "category":"Cinema",
            "subcategory":"Movie Theater",
            "type":"Entertainment"
        }
    ],
    "sg:phone":"+34 952 19 75 92",
    "sg:postcode":"29640",
    "sg:province":"M\u00e1laga",
    "sg:tags":[
        "salas",
        "de",
        "cine"
    ],
    "wof:name":"Cinesur Circuito Sanchez Ramade S.l.",
    "wof:placetype":"venue"
},
  "geometry": {"coordinates":[-4.6330537796,36.5426368713],"type":"Point"}
}