{
  "type": "Feature",
  "properties": {
    "addr:full":"Carrer de Moscu, 50 Mas D'en Bosch Tarragona 43850",
    "addr:housenumber":"50",
    "addr:postcode":"43850",
    "addr:street":"Carrer De Moscu",
    "iso:country":"ES",
    "sg:address":"Carrer de Moscu, 50",
    "sg:city":"Mas D'en Bosch",
    "sg:orig_category":"Organismos De Reclutamiento",
    "sg:phone":"+34 977 36 41 93",
    "sg:postcode":"43850",
    "sg:province":"Tarragona",
    "wof:name":"Consulting Financer Lleida 2002 S.l",
    "wof:placetype":"venue"
},
  "geometry": {"coordinates":[1.2540999651,41.1169281006],"type":"Point"}
}