{
  "type": "Feature",
  "properties": {
    "iso:country":"ES",
    "sg:address":"Avda Alto De Las Atalayas, 201",
    "sg:city":"Cabezo Torres",
    "sg:orig_category":"Mec\u00c1nico Del Autom\u00d3vil",
    "sg:phone":"+34 968 30 50 59",
    "sg:postcode":"30110",
    "sg:province":"Murcia",
    "wof:name":"Garcia Ortega Carmelo",
    "wof:placetype":"venue"
},
  "geometry": {"coordinates":[-1.1273206472,38.0268630981],"type":"Point"}
}