{
  "type": "Feature",
  "properties": {
    "addr:full":"Avda Valladolid, 29 Soria Soria 42001",
    "addr:housenumber":"29",
    "addr:postcode":"42001",
    "addr:street":"Avda Valladolid",
    "iso:country":"ES",
    "sg:address":"Avda Valladolid, 29",
    "sg:city":"Soria",
    "sg:orig_category":"Arquitectos",
    "sg:phone":"+34 975 23 10 70",
    "sg:postcode":"42001",
    "sg:province":"Soria",
    "wof:name":"Calonge-ruiz Arquitectos S.l.",
    "wof:placetype":"venue"
},
  "geometry": {"coordinates":[-2.4773631096,41.7660369873],"type":"Point"}
}