{
  "type": "Feature",
  "properties": {
    "iso:country":"ES",
    "sg:address":"Calle de Mayor, 20",
    "sg:city":"Pilar Horadada",
    "sg:orig_category":"Cajas Para Embalar",
    "sg:phone":"+34 965 35 10 75",
    "sg:postcode":"03190",
    "sg:province":"Alicante",
    "wof:name":"Caja Rural Central De Orihuela",
    "wof:placetype":"venue"
},
  "geometry": {"coordinates":[-0.7922689915,37.8650016785],"type":"Point"}
}