{
  "type": "Feature",
  "properties": {
    "addr:full":"Calle de Mendez Nu\u00d1ez, 24 Minas Riotinto Huelva 21660",
    "addr:housenumber":"24",
    "addr:postcode":"21660",
    "addr:street":"Calle De Mendez Nun\u0303Ez",
    "iso:country":"ES",
    "sg:address":"Calle de Mendez Nu\u00d1ez, 24",
    "sg:city":"Minas Riotinto",
    "sg:orig_category":"Bisuter\u00cda, Joyer\u00cda, Relojer\u00cda (al Por Menor)",
    "sg:phone":"+34 959 59 02 76",
    "sg:postcode":"21660",
    "sg:province":"Huelva",
    "wof:name":"Martinez Pachon Ernesto Jesus",
    "wof:placetype":"venue"
},
  "geometry": {"coordinates":[-6.5925068855,37.6930084229],"type":"Point"}
}