{
  "type": "Feature",
  "properties": {
    "iso:country":"ES",
    "sg:address":"Calle de San Isidro Labrador, 9",
    "sg:city":"Novallas",
    "sg:orig_category":"Empresas De Carpinter\u00cda",
    "sg:phone":"+34 976 19 82 86",
    "sg:postcode":"50510",
    "sg:province":"Zaragoza",
    "wof:name":"Serrano Serrano Carmelo",
    "wof:placetype":"venue"
},
  "geometry": {"coordinates":[-1.6950340271,41.9472770691],"type":"Point"}
}