{
  "type": "Feature",
  "properties": {
    "addr:full":"Calle de General Franco, 9 Portomarin Lugo 27170",
    "addr:housenumber":"9",
    "addr:postcode":"27170",
    "addr:street":"Calle De General Franco",
    "iso:country":"ES",
    "sg:address":"Calle de General Franco, 9",
    "sg:city":"Portomarin",
    "sg:orig_category":"Electrodom\u00c9sticos (al Por Menor)",
    "sg:phone":"+34 982 54 50 20",
    "sg:postcode":"27170",
    "sg:province":"Lugo",
    "wof:name":"Rodriguez Vazquez Arcadio",
    "wof:placetype":"venue"
},
  "geometry": {"coordinates":[-7.6159482002,42.8070297241],"type":"Point"}
}