{
  "type": "Feature",
  "properties": {
    "iso:country":"ES",
    "sg:address":"Ctra Boadilla, Km. 0007,0",
    "sg:city":"Majadahonda",
    "sg:orig_category":"Refiner\u00cdas De Petr\u00d3leo",
    "sg:phone":"+34 916 34 29 86",
    "sg:postcode":"28220",
    "sg:province":"Madrid",
    "wof:name":"Servicios Del Carralero S.a.",
    "wof:placetype":"venue"
},
  "geometry": {"coordinates":[-3.8698990345,40.4642486572],"type":"Point"}
}