{
  "type": "Feature",
  "properties": {
    "addr:full":"Ctra. Priego, S/n Alcala Real Ja\u00e9n 23680",
    "addr:postcode":"23680",
    "addr:street":"Ctra. Priego S / N;Jae\u0301N",
    "iso:country":"ES",
    "sg:address":"Ctra. Priego, S/n",
    "sg:city":"Alcala Real",
    "sg:orig_category":"Promotores Constructores",
    "sg:phone":"+34 953 58 53 81",
    "sg:postcode":"23680",
    "sg:province":"Ja\u00e9n",
    "wof:name":"Materiales De Construccion Antonio Perez S.l.",
    "wof:placetype":"venue"
},
  "geometry": {"coordinates":[-3.9252989292,37.4653282166],"type":"Point"}
}