{
  "type": "Feature",
  "properties": {
    "addr:full":"Calle de Valle Niza, 59 Malaga M\u00e1laga 29196",
    "addr:housenumber":"59",
    "addr:postcode":"29196",
    "addr:street":"Calle De Valle Niza;Ma\u0301Laga",
    "iso:country":"ES",
    "sg:address":"Calle de Valle Niza, 59",
    "sg:city":"Malaga",
    "sg:orig_category":"Equipo De Refrigeraci\u00d3n Industrial",
    "sg:phone":"+34 952 06 70 60",
    "sg:postcode":"29196",
    "sg:province":"M\u00e1laga",
    "wof:name":"Premierfri S.l.",
    "wof:placetype":"venue"
},
  "geometry": {"coordinates":[-4.4990677834,36.6963729858],"type":"Point"}
}