{
  "type": "Feature",
  "properties": {
    "iso:country":"ES",
    "sg:address":"Calle de Capuchinos, 36",
    "sg:city":"Malaga",
    "sg:orig_category":"Alimentaci\u00d3n General (al Por Menor)",
    "sg:phone":"+34 952 25 38 00",
    "sg:postcode":"29013",
    "sg:province":"M\u00e1laga",
    "wof:name":"Jurado Mateos Antonio",
    "wof:placetype":"venue"
},
  "geometry": {"coordinates":[-4.4214482307,36.7284965515],"type":"Point"}
}