{
  "type": "Feature",
  "properties": {
    "addr:full":"Calle de Mayor, 51 Burlada Navarra 31600",
    "addr:housenumber":"51",
    "addr:postcode":"31600",
    "addr:street":"Calle De Mayor",
    "iso:country":"ES",
    "sg:address":"Calle de Mayor, 51",
    "sg:city":"Burlada",
    "sg:orig_category":"Comunidades Religiosas",
    "sg:phone":"+34 948 14 21 00",
    "sg:postcode":"31600",
    "sg:province":"Navarra",
    "wof:name":"Siervas De Maria Ministras De Los Enfermos",
    "wof:placetype":"venue"
},
  "geometry": {"coordinates":[-1.6140830517,42.8271102905],"type":"Point"}
}