{
  "type": "Feature",
  "properties": {
    "addr:full":"Calle de San Antonio, 4 Oviedo Asturias 33003",
    "addr:housenumber":"4",
    "addr:postcode":"33003",
    "addr:street":"Calle De San Antonio",
    "iso:country":"ES",
    "sg:address":"Calle de San Antonio, 4",
    "sg:city":"Oviedo",
    "sg:orig_category":"Papeler\u00cdas, Librer\u00cdas",
    "sg:phone":"+34 985 21 72 90",
    "sg:postcode":"33003",
    "sg:province":"Asturias",
    "wof:name":"Bermejo Gonzalez Rosario",
    "wof:placetype":"venue"
},
  "geometry": {"coordinates":[-5.8441867828,43.3611717224],"type":"Point"}
}