{
  "type": "Feature",
  "properties": {
    "iso:country":"ES",
    "sg:address":"Calle de Uribitarte, 22",
    "sg:city":"Bilbao",
    "sg:orig_category":"Artes Gr\u00c1ficas, Artes Pl\u00c1sticas (curso)",
    "sg:phone":"+34 944 24 16 52",
    "sg:postcode":"48001",
    "sg:province":"Vizcaya",
    "sg:website":"www.gyragendas.com",
    "wof:name":"Agendas Dise\u00f1o Y Regalos G & R S.l.",
    "wof:placetype":"venue"
},
  "geometry": {"coordinates":[-2.9297094345,43.2663383484],"type":"Point"}
}