{
  "type": "Feature",
  "properties": {
    "iso:country":"ES",
    "sg:address":"Carr Conradors, S/n",
    "sg:city":"Cabaneta",
    "sg:orig_category":"Panader\u00cdas, Pasteler\u00cdas, Boller\u00cda Industriale (fabricaci\u00d3n, Al Por Mayor)",
    "sg:phone":"+34 971 60 41 49",
    "sg:postcode":"07141",
    "sg:province":"Islas Baleares",
    "sg:website":"www.postrestuduri.com",
    "wof:name":"Postres Tuduri S.l.",
    "wof:placetype":"venue"
},
  "geometry": {"coordinates":[2.7445349693,39.6195487976],"type":"Point"}
}