{
  "type": "Feature",
  "properties": {
    "addr:full":"Calle de Oviedo, 1 Burgos Burgos 09002",
    "addr:housenumber":"1",
    "addr:postcode":"09002",
    "addr:street":"Calle De Oviedo",
    "iso:country":"ES",
    "sg:address":"Calle de Oviedo, 1",
    "sg:city":"Burgos",
    "sg:orig_category":"Inmobiliaria (agencias)",
    "sg:phone":"+34 947 20 42 26",
    "sg:postcode":"09002",
    "sg:province":"Burgos",
    "wof:name":"Garsan Inmobiliaria S.a.",
    "wof:placetype":"venue"
},
  "geometry": {"coordinates":[-3.6999590397,42.3381462097],"type":"Point"}
}