{
  "type": "Feature",
  "properties": {
    "iso:country":"ES",
    "sg:address":"C/ Hospital, 16",
    "sg:city":"Elche",
    "sg:orig_category":"Caf\u00c9s, Bares, Cervecer\u00cdas",
    "sg:phone":"+34 965 42 47 78",
    "sg:postcode":"03203",
    "sg:province":"Alicante",
    "wof:name":"Rada Business S.l.",
    "wof:placetype":"venue"
},
  "geometry": {"coordinates":[-0.6964989901,38.2654685974],"type":"Point"}
}