{
  "type": "Feature",
  "properties": {
    "addr:full":"Carr Muralla, 10 Vilanova I La Geltru Barcelona 08800",
    "addr:housenumber":"10",
    "addr:postcode":"08800",
    "addr:street":"Carr Muralla",
    "iso:country":"ES",
    "sg:address":"Carr Muralla, 10",
    "sg:city":"Vilanova I La Geltru",
    "sg:orig_category":"Diplomas Diversos",
    "sg:phone":"+34 938 93 96 01",
    "sg:postcode":"08800",
    "sg:province":"Barcelona",
    "wof:name":"Ripoll Pedragosa Francesc",
    "wof:placetype":"venue"
},
  "geometry": {"coordinates":[1.7282810211,41.2251930237],"type":"Point"}
}