{
  "type": "Feature",
  "properties": {
    "iso:country":"ES",
    "sg:address":"Avda Canarias, 416",
    "sg:city":"Vecindario",
    "sg:orig_category":"Cl\u00cdnicas M\u00c9dicas",
    "sg:phone":"+34 928 12 21 91",
    "sg:postcode":"35110",
    "sg:province":"Las Palmas",
    "wof:name":"Clinica Iguazu-mareari S.l.",
    "wof:placetype":"venue"
},
  "geometry": {"coordinates":[-15.447394371,27.841375351],"type":"Point"}
}