{
  "type": "Feature",
  "properties": {
    "iso:country":"ES",
    "sg:address":"Calle de Harrobi, 3",
    "sg:city":"Beto\u00f1o",
    "sg:orig_category":"Mec\u00c1nico Del Autom\u00d3vil",
    "sg:phone":"+34 945 26 48 81",
    "sg:postcode":"01013",
    "sg:province":"\u00c1lava",
    "wof:name":"Autocontrol Diagnosis S.l.",
    "wof:placetype":"venue"
},
  "geometry": {"coordinates":[-2.6550021172,42.864276886],"type":"Point"}
}