{
  "type": "Feature",
  "properties": {
    "addr:full":"Pantano Santolea, S/n Castellote Teruel 44560",
    "addr:housenumber":"/ n",
    "addr:postcode":"44560",
    "addr:street":"Santolea S",
    "iso:country":"ES",
    "sg:address":"Pantano Santolea, S/n",
    "sg:city":"Castellote",
    "sg:orig_category":"Electricidad: Instaladores",
    "sg:phone":"+34 978 88 75 60",
    "sg:postcode":"44560",
    "sg:province":"Teruel",
    "wof:name":"Hidroelectrica Del Guadalope",
    "wof:placetype":"venue"
},
  "geometry": {"coordinates":[-0.3181439936,40.7997589111],"type":"Point"}
}