{
  "type": "Feature",
  "properties": {
    "iso:country":"ES",
    "sg:address":"Ptge Ametllers, 2",
    "sg:city":"Esplugues Llobregat",
    "sg:orig_category":"Molduras, Junquillos, Listones Y Molduras Perforadas",
    "sg:phone":"+34 933 72 32 56",
    "sg:postcode":"08950",
    "sg:province":"Barcelona",
    "wof:name":"Lopez Campos Jose Antonio",
    "wof:placetype":"venue"
},
  "geometry": {"coordinates":[2.0850970745,41.3715782166],"type":"Point"}
}