{
  "type": "Feature",
  "properties": {
    "addr:full":"Rua Rosalia De Castro, 7 Vimianzo A Coru\u00f1a 15120",
    "addr:housenumber":"7",
    "addr:postcode":"15120",
    "addr:street":"Rua Rosalia De Castro;Corun\u0303A",
    "iso:country":"ES",
    "sg:address":"Rua Rosalia De Castro, 7",
    "sg:city":"Vimianzo",
    "sg:orig_category":"Molduras, Junquillos, Listones Y Molduras Perforadas",
    "sg:phone":"+34 981 71 66 57",
    "sg:postcode":"15120",
    "sg:province":"A Coru\u00f1a",
    "wof:name":"Sistelcom-telemensaje S.a.",
    "wof:placetype":"venue"
},
  "geometry": {"coordinates":[-9.0345630646,43.1105003357],"type":"Point"}
}