{
  "type": "Feature",
  "properties": {
    "iso:country":"ES",
    "sg:address":"Calle de Bolado El, S/n",
    "sg:city":"Grado",
    "sg:orig_category":"Material Y Herramientas Agr\u00cdcolas",
    "sg:phone":"+34 985 75 00 17",
    "sg:postcode":"33820",
    "sg:province":"Asturias",
    "wof:name":"Rodriguez Rodriguez Benigno",
    "wof:placetype":"venue"
},
  "geometry": {"coordinates":[-6.0723614693,43.3870925903],"type":"Point"}
}