{
  "type": "Feature",
  "properties": {
    "iso:country":"ES",
    "sg:address":"A Ribeira, 69",
    "sg:city":"Ribeira",
    "sg:orig_category":"Pintura, Barniz, Productos Asimilables (fabricaci\u00d3n, Al Por Mayor)",
    "sg:phone":"+34 986 31 40 39",
    "sg:postcode":"36955",
    "sg:province":"Pontevedra",
    "wof:name":"Fernandez Pintura Y Decoracion S.l.",
    "wof:placetype":"venue"
},
  "geometry": {"coordinates":[-8.7183160782,42.2899627686],"type":"Point"}
}