{
  "type": "Feature",
  "properties": {
    "addr:full":"Calle de Bergara, 23 Donostia-san Sebastian Guip\u00f9zcoa 20005",
    "addr:housenumber":"23",
    "addr:postcode":"20005",
    "addr:street":"Calle De Bergara",
    "iso:country":"ES",
    "sg:address":"Calle de Bergara, 23",
    "sg:city":"Donostia-san Sebastian",
    "sg:orig_category":"Abogados",
    "sg:phone":"+34 943 46 29 95",
    "sg:postcode":"20005",
    "sg:province":"Guip\u00f9zcoa",
    "wof:name":"Coullaut-valera Ari\u00f1o Carlos",
    "wof:placetype":"venue"
},
  "geometry": {"coordinates":[-1.9796880484,43.3184204102],"type":"Point"}
}