{
  "type": "Feature",
  "properties": {
    "addr:full":"Calle de Facundo Perezagua, 1 Putxeta Vizcaya 48540",
    "addr:housenumber":"1",
    "addr:postcode":"48540",
    "addr:street":"Calle De Facundo Perezagua",
    "iso:country":"ES",
    "sg:address":"Calle de Facundo Perezagua, 1",
    "sg:city":"Putxeta",
    "sg:orig_category":"Asociaciones Y Clubs Deportivos",
    "sg:phone":"+34 946 36 87 60",
    "sg:postcode":"48540",
    "sg:province":"Vizcaya",
    "wof:name":"Informacion Y Gestion Telematica S.l.",
    "wof:placetype":"venue"
},
  "geometry": {"coordinates":[-3.1058120728,43.3131942749],"type":"Point"}
}