{
  "type": "Feature",
  "properties": {
    "iso:country":"ES",
    "sg:address":"Calle de Tejeria, 14",
    "sg:city":"Donostia-san Sebastian",
    "sg:orig_category":"Molduras, Junquillos, Listones Y Molduras Perforadas",
    "sg:phone":"+34 943 28 20 19",
    "sg:postcode":"20012",
    "sg:province":"Guip\u00f9zcoa",
    "wof:name":"Jose Antonio Mu\u00f1oz Gaztelu.",
    "wof:placetype":"venue"
},
  "geometry": {"coordinates":[-1.9719170332,43.3169403076],"type":"Point"}
}