{
  "type": "Feature",
  "properties": {
    "iso:country":"ES",
    "sg:address":"Pl. 19 Octubre, S/n",
    "sg:city":"Oviedo",
    "sg:orig_category":"Pescader\u00cdas (al Por Menor)",
    "sg:phone":"+34 985 73 80 11",
    "sg:postcode":"33009",
    "sg:province":"Asturias",
    "wof:name":"Rodriguez Gomez Manuel Angel",
    "wof:placetype":"venue"
},
  "geometry": {"coordinates":[-5.8475308418,43.3626899719],"type":"Point"}
}