{
  "type": "Feature",
  "properties": {
    "iso:country":"ES",
    "sg:address":"Calle de Jaime Balmes, 1",
    "sg:city":"Le\u00f3n",
    "sg:orig_category":"Fabricaci\u00d3n, Importaci\u00d3n, Venta De Material De Telefon\u00cda, Peritelefon\u00cda",
    "sg:phone":"+34 987 27 01 26",
    "sg:postcode":"24007",
    "sg:province":"Le\u00f3n",
    "wof:name":"Arteaga Castro Santiago",
    "wof:placetype":"venue"
},
  "geometry": {"coordinates":[-5.5684223175,42.6062011719],"type":"Point"}
}