{
  "type": "Feature",
  "properties": {
    "addr:full":"Calle de Jaime Balmes, 1 Le\u00f3n Le\u00f3n 24007",
    "addr:housenumber":"1",
    "addr:postcode":"24007",
    "addr:street":"Calle De Jaime Balmes;Leo\u0301N",
    "iso:country":"ES",
    "sg:address":"Calle de Jaime Balmes, 1",
    "sg:city":"Le\u00f3n",
    "sg:orig_category":"Fabricaci\u00d3n, Importaci\u00d3n, Venta De Material De Telefon\u00cda, Peritelefon\u00cda",
    "sg:phone":"+34 987 27 01 26",
    "sg:postcode":"24007",
    "sg:province":"Le\u00f3n",
    "wof:name":"Arteaga Castro Santiago",
    "wof:placetype":"venue"
},
  "geometry": {"coordinates":[-5.5684223175,42.6062011719],"type":"Point"}
}