{
  "type": "Feature",
  "properties": {
    "iso:country":"ES",
    "sg:address":"Avda Ferrocarril, 27",
    "sg:city":"Ponferrada",
    "sg:orig_category":"Suministros Y Materiales Industriales",
    "sg:phone":"+34 987 42 99 24",
    "sg:postcode":"24400",
    "sg:province":"Le\u00f3n",
    "wof:name":"Herramientas Industrial Ponferrada",
    "wof:placetype":"venue"
},
  "geometry": {"coordinates":[-6.6029849052,42.5452728271],"type":"Point"}
}