{
  "type": "Feature",
  "properties": {
    "addr:full":"Calle de Dr Layna Serrano, 22 Guadalajara Guadalajara 19002",
    "addr:housenumber":"22",
    "addr:postcode":"19002",
    "addr:street":"Calle De Dr Layna Serrano",
    "iso:country":"ES",
    "sg:address":"Calle de Dr Layna Serrano, 22",
    "sg:city":"Guadalajara",
    "sg:orig_category":"Institutos De Belleza",
    "sg:phone":"+34 949 25 58 88",
    "sg:postcode":"19002",
    "sg:province":"Guadalajara",
    "wof:name":"Villarino Hernandez S.l.",
    "wof:placetype":"venue"
},
  "geometry": {"coordinates":[-3.1635270119,40.624671936],"type":"Point"}
}