{
  "type": "Feature",
  "properties": {
    "addr:full":"Carrer de Ample, 127 Terrassa Barcelona 08226",
    "addr:housenumber":"127",
    "addr:postcode":"08226",
    "addr:street":"Carrer De Ample",
    "iso:country":"ES",
    "sg:address":"Carrer de Ample, 127",
    "sg:city":"Terrassa",
    "sg:orig_category":"Peluqueros: De Se\u00d1oras",
    "sg:phone":"+34 937 35 10 27",
    "sg:postcode":"08226",
    "sg:province":"Barcelona",
    "wof:name":"Marquez Guil Jose",
    "wof:placetype":"venue"
},
  "geometry": {"coordinates":[2.0182569027,41.5729560852],"type":"Point"}
}