{
  "type": "Feature",
  "properties": {
    "addr:full":"Calle de Dolores Cortes, 17 Malaga M\u00e1laga 29014",
    "addr:housenumber":"17",
    "addr:postcode":"29014",
    "addr:street":"Calle De Dolores Cortes;Ma\u0301Laga",
    "iso:country":"ES",
    "sg:address":"Calle de Dolores Cortes, 17",
    "sg:city":"Malaga",
    "sg:orig_category":"Platos Preparados Refrigerados (fabricaci\u00d3n, Al Por Mayor)",
    "sg:phone":"+34 952 25 49 51",
    "sg:postcode":"29014",
    "sg:province":"M\u00e1laga",
    "wof:name":"Marin Ponferrada Juan Antonio",
    "wof:placetype":"venue"
},
  "geometry": {"coordinates":[-4.4218854904,36.7484359741],"type":"Point"}
}