{
  "type": "Feature",
  "properties": {
    "iso:country":"ES",
    "sg:address":"Calle de Mancilla, 80",
    "sg:city":"Osuna",
    "sg:orig_category":"Mec\u00c1nico Del Autom\u00d3vil",
    "sg:phone":"+34 954 81 11 41",
    "sg:postcode":"41640",
    "sg:province":"Sevilla",
    "wof:name":"Romero Perez Rafael",
    "wof:placetype":"venue"
},
  "geometry": {"coordinates":[-5.1114768982,37.2356071472],"type":"Point"}
}