{
  "type": "Feature",
  "properties": {
    "iso:country":"ES",
    "sg:address":"Carrer de Bages, 56",
    "sg:city":"Terrassa",
    "sg:orig_category":"Calzados Ortop\u00c9dicos",
    "sg:phone":"+34 937 86 12 94",
    "sg:postcode":"08223",
    "sg:province":"Barcelona",
    "wof:name":"A.f.l.franquicias Sl",
    "wof:placetype":"venue"
},
  "geometry": {"coordinates":[2.0224914551,41.5525627136],"type":"Point"}
}