{
  "type": "Feature",
  "properties": {
    "iso:country":"ES",
    "sg:address":"Carrer de Joan De Saridakis, 4",
    "sg:city":"Sant Agusti",
    "sg:orig_category":"Limpieza Industrial",
    "sg:phone":"+34 971 40 40 26",
    "sg:postcode":"07015",
    "sg:province":"Islas Baleares",
    "wof:name":"Bbilbertz  Erika",
    "wof:placetype":"venue"
},
  "geometry": {"coordinates":[2.6126310825,39.5525741577],"type":"Point"}
}