{
  "type": "Feature",
  "properties": {
    "addr:full":"Carr Repos, 4 Igualada Barcelona 08700",
    "addr:housenumber":"4",
    "addr:postcode":"08700",
    "addr:street":"Carr Repos",
    "iso:country":"ES",
    "sg:address":"Carr Repos, 4",
    "sg:city":"Igualada",
    "sg:orig_category":"Ingeniero",
    "sg:phone":"+34 938 05 32 38",
    "sg:postcode":"08700",
    "sg:province":"Barcelona",
    "wof:name":"Freixas Bartoli Joaquim",
    "wof:placetype":"venue"
},
  "geometry": {"coordinates":[1.6155569553,41.5781898499],"type":"Point"}
}