{
  "type": "Feature",
  "properties": {
    "iso:country":"ES",
    "sg:address":"Carrer de Casp, 25",
    "sg:city":"Barcelona",
    "sg:orig_category":"Restaurantes De Empresas Y Colectivos",
    "sg:phone":"+34 933 01 34 35",
    "sg:postcode":"08010",
    "sg:province":"Barcelona",
    "wof:name":"F. Roca S.l.",
    "wof:placetype":"venue"
},
  "geometry": {"coordinates":[2.1712739468,41.3899841309],"type":"Point"}
}