{
  "type": "Feature",
  "properties": {
    "iso:country":"ES",
    "sg:address":"Ctra. Vitoria, S/n",
    "sg:city":"Fuenmayor",
    "sg:orig_category":"F\u00c1bricas De Ladrillo Y Tejas",
    "sg:phone":"+34 941 45 02 34",
    "sg:postcode":"26360",
    "sg:province":"La Rioja",
    "wof:name":"Tejeria Salaverri S.l.",
    "wof:placetype":"venue"
},
  "geometry": {"coordinates":[-2.5609819889,42.4635887146],"type":"Point"}
}