{
  "type": "Feature",
  "properties": {
    "addr:full":"Pg Sant Joan, 27 Barcelona Barcelona 08010",
    "addr:housenumber":"27",
    "addr:postcode":"08010",
    "addr:street":"Pg Sant Joan",
    "iso:country":"ES",
    "sg:address":"Pg Sant Joan, 27",
    "sg:city":"Barcelona",
    "sg:orig_category":"Papeler\u00cdas, Librer\u00cdas",
    "sg:phone":"+34 932 65 13 21",
    "sg:postcode":"08010",
    "sg:province":"Barcelona",
    "wof:name":"Marsay Fabuel Concepcion De",
    "wof:placetype":"venue"
},
  "geometry": {"coordinates":[2.1774969101,41.3932228088],"type":"Point"}
}