{
  "type": "Feature",
  "properties": {
    "addr:full":"Calle de Pino (el), S/n Miraverde Santa Cruz De Tenerife 38670",
    "addr:postcode":"38670",
    "addr:street":"Calle De Pino El S / N Miraverde",
    "iso:country":"ES",
    "sg:address":"Calle de Pino (el), S/n",
    "sg:city":"Miraverde",
    "sg:orig_category":"Promotores Constructores",
    "sg:phone":"+34 922 71 31 80",
    "sg:postcode":"38670",
    "sg:province":"Santa Cruz De Tenerife",
    "wof:name":"Urbanizacion Playa Fa\u00f1abe S.a.",
    "wof:placetype":"venue"
},
  "geometry": {"coordinates":[-16.724899292,28.1215400696],"type":"Point"}
}