{
  "type": "Feature",
  "properties": {
    "addr:full":"Calle de Carmelitas (las), 4 Orihuela Alicante 03300",
    "addr:housenumber":"4",
    "addr:postcode":"03300",
    "addr:street":"Calle De Carmelitas Las",
    "iso:country":"ES",
    "sg:address":"Calle de Carmelitas (las), 4",
    "sg:city":"Orihuela",
    "sg:orig_category":"Psic\u00d3logos",
    "sg:phone":"+34 966 74 13 75",
    "sg:postcode":"03300",
    "sg:province":"Alicante",
    "wof:name":"Carrillo Ca\u00f1izares Maria Dolores",
    "wof:placetype":"venue"
},
  "geometry": {"coordinates":[-0.9424874783,38.0819969177],"type":"Point"}
}