{
  "type": "Feature",
  "properties": {
    "addr:full":"Carr Bisbe Guitart, 27 Seu D'urgell Lleida 25700",
    "addr:housenumber":"27",
    "addr:postcode":"25700",
    "addr:street":"Carr Bisbe Guitart",
    "iso:country":"ES",
    "sg:address":"Carr Bisbe Guitart, 27",
    "sg:city":"Seu D'urgell",
    "sg:orig_category":"Arquitectos",
    "sg:phone":"+34 973 36 04 93",
    "sg:postcode":"25700",
    "sg:province":"Lleida",
    "wof:name":"Terrier Illa Christine",
    "wof:placetype":"venue"
},
  "geometry": {"coordinates":[0.6120280027,41.6164169312],"type":"Point"}
}