{
  "type": "Feature",
  "properties": {
    "addr:full":"Calle de Estrella La Polar, S/n Sevilla Sevilla 41008",
    "addr:housenumber":"s / n",
    "addr:postcode":"41008",
    "addr:street":"Calle De Estrella La",
    "iso:country":"ES",
    "sg:address":"Calle de Estrella La Polar, S/n",
    "sg:city":"Sevilla",
    "sg:orig_category":"Centros De Educaci\u00d3n Especial",
    "sg:phone":"+34 954 94 56 56",
    "sg:postcode":"41008",
    "sg:province":"Sevilla",
    "wof:name":"Junta De Andalucia Consejeria De Educacion",
    "wof:placetype":"venue"
},
  "geometry": {"coordinates":[-5.9706587791,37.420715332],"type":"Point"}
}