{
  "type": "Feature",
  "properties": {
    "iso:country":"ES",
    "sg:address":"Calle de Arroyo, 8",
    "sg:city":"Torrejon Velasco",
    "sg:orig_category":"Fabricaci\u00d3n De Juguetes Autom\u00c1ticos",
    "sg:phone":"+34 918 16 11 06",
    "sg:postcode":"28990",
    "sg:province":"Madrid",
    "wof:name":"Automatico Centro Norte",
    "wof:placetype":"venue"
},
  "geometry": {"coordinates":[-3.7743005753,40.185256958],"type":"Point"}
}