{
  "type": "Feature",
  "properties": {
    "addr:full":"Calle de Mondragon, 2 Malaga M\u00e1laga 29014",
    "addr:housenumber":"2",
    "addr:postcode":"29014",
    "addr:street":"Calle De Mondragon;Ma\u0301Laga",
    "iso:country":"ES",
    "sg:address":"Calle de Mondragon, 2",
    "sg:city":"Malaga",
    "sg:orig_category":"Doctores En Medicina",
    "sg:phone":"+34 952 25 55 48",
    "sg:postcode":"29014",
    "sg:province":"M\u00e1laga",
    "wof:name":"Delgado Caballero Felipe",
    "wof:placetype":"venue"
},
  "geometry": {"coordinates":[-4.4232339859,36.7442054749],"type":"Point"}
}