{
  "type": "Feature",
  "properties": {
    "iso:country":"ES",
    "sg:address":"Calle de Almeria (de), 4",
    "sg:city":"Humanes De Madrid",
    "sg:orig_category":"Suministros Para Hoteles",
    "sg:phone":"+34 916 90 99 81",
    "sg:postcode":"28970",
    "sg:province":"Madrid",
    "wof:name":"Hostelfri S. L.",
    "wof:placetype":"venue"
},
  "geometry": {"coordinates":[-3.8180930614,40.2747535706],"type":"Point"}
}