{
  "type": "Feature",
  "properties": {
    "iso:country":"ES",
    "sg:address":"Carrer de Montflorit, 89",
    "sg:city":"Gava",
    "sg:orig_category":"Telas Y Sedas (al Por Menor)",
    "sg:phone":"+34 936 62 11 15",
    "sg:postcode":"08850",
    "sg:province":"Barcelona",
    "wof:name":"Aranda Lopez Asuncion",
    "wof:placetype":"venue"
},
  "geometry": {"coordinates":[1.9995783567,41.3046951294],"type":"Point"}
}