{
  "type": "Feature",
  "properties": {
    "iso:country":"ES",
    "sg:address":"Pol. Ginesteres, S/n",
    "sg:city":"Collbato",
    "sg:orig_category":"Carros Elevadores, Carros De Operaciones Portuarias",
    "sg:phone":"+34 937 77 93 44",
    "sg:postcode":"08293",
    "sg:province":"Barcelona",
    "wof:name":"Carretillas Collbato S.l.",
    "wof:placetype":"venue"
},
  "geometry": {"coordinates":[1.8315320015,41.5642318726],"type":"Point"}
}