{
  "type": "Feature",
  "properties": {
    "addr:full":"Carrer de Almeria, 116 Olesa Montserrat Barcelona 08640",
    "addr:housenumber":"116",
    "addr:postcode":"08640",
    "addr:street":"Carrer De Almeria",
    "iso:country":"ES",
    "sg:address":"Carrer de Almeria, 116",
    "sg:city":"Olesa Montserrat",
    "sg:orig_category":"Arquitectos",
    "sg:phone":"+34 937 78 66 28",
    "sg:postcode":"08640",
    "sg:province":"Barcelona",
    "wof:name":"Sismatec S.c.p.",
    "wof:placetype":"venue"
},
  "geometry": {"coordinates":[1.886070013,41.549911499],"type":"Point"}
}