{
  "type": "Feature",
  "properties": {
    "addr:full":"Mercat Sants, 49 Barcelona Barcelona 08014",
    "addr:housenumber":"49",
    "addr:postcode":"08014",
    "iso:country":"ES",
    "sg:address":"Mercat Sants, 49",
    "sg:city":"Barcelona",
    "sg:orig_category":"Mercer\u00cda, Lencer\u00cda (al Por Menor)",
    "sg:phone":"+34 933 30 95 95",
    "sg:postcode":"08014",
    "sg:province":"Barcelona",
    "wof:name":"Pons Iba\u00f1ez Joan",
    "wof:placetype":"venue"
},
  "geometry": {"coordinates":[2.1381518841,41.3753204346],"type":"Point"}
}