{
  "type": "Feature",
  "properties": {
    "iso:country":"ES",
    "sg:address":"Ctra. Aldeaencabo, S/n",
    "sg:city":"Escalona",
    "sg:orig_category":"Molduras, Junquillos, Listones Y Molduras Perforadas",
    "sg:phone":"+34 925 78 03 94",
    "sg:postcode":"45910",
    "sg:province":"Toledo",
    "wof:name":"Herrera Ortega Jaime",
    "wof:placetype":"venue"
},
  "geometry": {"coordinates":[-4.406703949,40.1707496643],"type":"Point"}
}