{
  "type": "Feature",
  "properties": {
    "addr:full":"Calle de Pablo Neruda, 32 Fortuna Murcia 30620",
    "addr:housenumber":"32",
    "addr:postcode":"30620",
    "addr:street":"Calle De Pablo Neruda",
    "iso:country":"ES",
    "sg:address":"Calle de Pablo Neruda, 32",
    "sg:city":"Fortuna",
    "sg:orig_category":"Alimentaci\u00d3n General (al Por Menor)",
    "sg:phone":"+34 968 68 64 70",
    "sg:postcode":"30620",
    "sg:province":"Murcia",
    "wof:name":"Martinez Gonzalez Jose",
    "wof:placetype":"venue"
},
  "geometry": {"coordinates":[-1.1266050339,38.1800918579],"type":"Point"}
}