{
  "type": "Feature",
  "properties": {
    "iso:country":"ES",
    "sg:address":"Calle de Alcala, 330",
    "sg:city":"Madrid",
    "sg:orig_category":"Ropa Para Se\u00d1oras Y Caballeros (al Por Menor)",
    "sg:phone":"+34 913 67 55 46",
    "sg:postcode":"28027",
    "sg:province":"Madrid",
    "sg:website":"www.pullbear.com",
    "wof:name":"Pull & Bear Espa\u00f1a S.a.",
    "wof:placetype":"venue"
},
  "geometry": {"coordinates":[-3.6467614174,40.4337348938],"type":"Point"}
}