{
  "type": "Feature",
  "properties": {
    "addr:full":"Avda Constitucion, 260 Torrejon Ardoz Madrid 28850",
    "addr:housenumber":"260",
    "addr:postcode":"28850",
    "addr:street":"Avda Constitucion",
    "iso:country":"ES",
    "sg:address":"Avda Constitucion, 260",
    "sg:city":"Torrejon Ardoz",
    "sg:orig_category":"Tapicer\u00cdas",
    "sg:phone":"+34 916 75 80 79",
    "sg:postcode":"28850",
    "sg:province":"Madrid",
    "sg:website":"www.kurko.es",
    "wof:name":"Distribuciones Kurko S. A.",
    "wof:placetype":"venue"
},
  "geometry": {"coordinates":[-3.4386761189,40.4659194946],"type":"Point"}
}