{
  "type": "Feature",
  "properties": {
    "addr:full":"Anejo De Los Tablones, S/n Los Tablones Granada 18418",
    "addr:housenumber":"/ n",
    "addr:postcode":"18418",
    "addr:street":"Tablones S;Los Tablones",
    "iso:country":"ES",
    "sg:address":"Anejo De Los Tablones, S/n",
    "sg:city":"Los Tablones",
    "sg:orig_category":"Hormigonados",
    "sg:phone":"+34 958 78 57 74",
    "sg:postcode":"18418",
    "sg:province":"Granada",
    "wof:name":"Hormigones Lastra S.l.",
    "wof:placetype":"venue"
},
  "geometry": {"coordinates":[-3.42801404,36.9265174866],"type":"Point"}
}