{
  "type": "Feature",
  "properties": {
    "iso:country":"ES",
    "sg:address":"Calle de De San Anton Viejo, 1",
    "sg:city":"Benavente",
    "sg:orig_category":"Supermercados Y Hipermercados",
    "sg:phone":"+34 980 63 53 90",
    "sg:postcode":"49600",
    "sg:province":"Zamora",
    "wof:name":"Merkaprecio S.a.",
    "wof:placetype":"venue"
},
  "geometry": {"coordinates":[-5.6773509979,42.0072517395],"type":"Point"}
}