{
  "type": "Feature",
  "properties": {
    "iso:country":"ES",
    "sg:address":"Pigara, 9",
    "sg:city":"O Temple",
    "sg:orig_category":"Maquinaria Para Industrias Diversas",
    "sg:phone":"+34 981 65 33 89",
    "sg:postcode":"15679",
    "sg:province":"La Coru\u00f1a",
    "sg:website":"www.bizerba.com",
    "wof:name":"Balanzas Y Sistemas Bizerba S. A.",
    "wof:placetype":"venue"
},
  "geometry": {"coordinates":[-8.3568944931,43.3201942444],"type":"Point"}
}