{
  "type": "Feature",
  "properties": {
    "addr:full":"Avda Fisic Garcia Moliner, 18 Sant Mateu Castell\u00f3n 12170",
    "addr:housenumber":"18",
    "addr:postcode":"12170",
    "addr:street":"Avda Fisic Garcia Moliner",
    "iso:country":"ES",
    "sg:address":"Avda Fisic Garcia Moliner, 18",
    "sg:city":"Sant Mateu",
    "sg:orig_category":"Plomeros",
    "sg:phone":"+34 964 41 66 10",
    "sg:postcode":"12170",
    "sg:province":"Castell\u00f3n",
    "wof:name":"Instalaciones Ferreres Beltran S.l.",
    "wof:placetype":"venue"
},
  "geometry": {"coordinates":[0.1820629984,40.4624595642],"type":"Point"}
}