{
  "type": "Feature",
  "properties": {
    "iso:country":"ES",
    "sg:address":"Calle de Sangenis, 33",
    "sg:city":"Zaragoza",
    "sg:orig_category":"Molduras, Junquillos, Listones Y Molduras Perforadas",
    "sg:phone":"+34 976 53 00 18",
    "sg:postcode":"50010",
    "sg:province":"Zaragoza",
    "wof:name":"Picatapas Sociedad",
    "wof:placetype":"venue"
},
  "geometry": {"coordinates":[-0.9035720229,41.65102005],"type":"Point"}
}