{
  "type": "Feature",
  "properties": {
    "addr:full":"Calle de Vera De Bidasoa, 14 Irun Guip\u00f9zcoa 20301",
    "addr:housenumber":"14",
    "addr:postcode":"20301",
    "addr:street":"Calle De Vera De Bidasoa;Guipu\u0300Zcoa",
    "iso:country":"ES",
    "sg:address":"Calle de Vera De Bidasoa, 14",
    "sg:city":"Irun",
    "sg:orig_category":"Agencias Y Asesores De Publicidad",
    "sg:phone":"+34 943 61 36 92",
    "sg:postcode":"20301",
    "sg:province":"Guip\u00f9zcoa",
    "sg:website":"www.ushuaiamc.com",
    "wof:name":"Ushuaia Sl",
    "wof:placetype":"venue"
},
  "geometry": {"coordinates":[-1.799448967,43.3442001343],"type":"Point"}
}