{
  "type": "Feature",
  "properties": {
    "iso:country":"ES",
    "sg:address":"Pl. Ntra. Sra. Remedios, 1",
    "sg:city":"Estepa",
    "sg:orig_category":"Iglesia Cat\u00d3lica",
    "sg:phone":"+34 954 82 03 09",
    "sg:postcode":"41560",
    "sg:province":"Sevilla",
    "wof:name":"Parroquia Santa Maria De La Asuncion",
    "wof:placetype":"venue"
},
  "geometry": {"coordinates":[-4.8780741692,37.2938766479],"type":"Point"}
}