{
  "type": "Feature",
  "properties": {
    "iso:country":"ES",
    "sg:address":"Calle de Barrio Nuevo, 16",
    "sg:city":"Torrejoncillo",
    "sg:orig_category":"Quincaller\u00cda (al Por Menor)",
    "sg:phone":"+34 927 30 30 65",
    "sg:postcode":"10830",
    "sg:province":"C\u00e1ceres",
    "wof:name":"Nu\u00f1ez Gomez Vicente Jesus",
    "wof:placetype":"venue"
},
  "geometry": {"coordinates":[-6.4651284218,39.8946342468],"type":"Point"}
}