{
  "type": "Feature",
  "properties": {
    "addr:full":"Av Ignasi Wallis, 27 Eivissa Islas Baleares 07800",
    "addr:housenumber":"27",
    "addr:postcode":"07800",
    "addr:street":"Av Ignasi Wallis",
    "iso:country":"ES",
    "sg:address":"Av Ignasi Wallis, 27",
    "sg:city":"Eivissa",
    "sg:orig_category":"Administradores De Bienes Y Delegados De Comunidades De Propietarios",
    "sg:phone":"+34 971 31 79 85",
    "sg:postcode":"07800",
    "sg:province":"Islas Baleares",
    "wof:name":"Administracion De Comunidades M & G C",
    "wof:placetype":"venue"
},
  "geometry": {"coordinates":[1.431256175,38.910697937],"type":"Point"}
}