{
  "type": "Feature",
  "properties": {
    "addr:full":"Calle de San Agustin, 1 Antequera M\u00e1laga 29200",
    "addr:housenumber":"1",
    "addr:postcode":"29200",
    "addr:street":"Calle De San Agustin",
    "iso:country":"ES",
    "sg:address":"Calle de San Agustin, 1",
    "sg:city":"Antequera",
    "sg:orig_category":"Restaurantes",
    "sg:phone":"+34 952 70 30 31",
    "sg:postcode":"29200",
    "sg:province":"M\u00e1laga",
    "wof:name":"Escuela De Hosteleria La Espuela De Antequera S.l.",
    "wof:placetype":"venue"
},
  "geometry": {"coordinates":[-4.5606927872,37.0174217224],"type":"Point"}
}