{
  "type": "Feature",
  "properties": {
    "iso:country":"ES",
    "sg:address":"Calle de Esteban Salazar Chapela, 18",
    "sg:city":"Malaga",
    "sg:orig_category":"Fabricaci\u00d3n De Distribuidores Autom\u00c1ticos",
    "sg:phone":"+34 952 23 03 21",
    "sg:postcode":"29004",
    "sg:province":"M\u00e1laga",
    "wof:name":"Implanex S.l.",
    "wof:placetype":"venue"
},
  "geometry": {"coordinates":[-4.4745006561,36.6916885376],"type":"Point"}
}