{
  "type": "Feature",
  "properties": {
    "iso:country":"ES",
    "sg:address":"Carrer de Balmes, 319",
    "sg:city":"Barcelona",
    "sg:orig_category":"M\u00c9dicos: Medicina Interna",
    "sg:phone":"+34 932 12 25 47",
    "sg:postcode":"08006",
    "sg:province":"Barcelona",
    "wof:name":"Tomasa Torrellardona Antonio",
    "wof:placetype":"venue"
},
  "geometry": {"coordinates":[2.1441380978,41.4027862549],"type":"Point"}
}