{
  "type": "Feature",
  "properties": {
    "iso:country":"ES",
    "sg:address":"S. Sebastia, 11",
    "sg:city":"Palafrugell",
    "sg:orig_category":"Zapatos (al Por Menor)",
    "sg:phone":"+34 972 61 24 74",
    "sg:postcode":"17200",
    "sg:province":"Girona",
    "wof:name":"Cama Rivas Francesc",
    "wof:placetype":"venue"
},
  "geometry": {"coordinates":[3.1597599983,41.9181594849],"type":"Point"}
}