{
  "type": "Feature",
  "properties": {
    "addr:full":"Lastrilla, S/n Trescasas Segovia 40194",
    "addr:housenumber":"s / n",
    "addr:postcode":"40194",
    "addr:street":"Lastrilla",
    "iso:country":"ES",
    "sg:address":"Lastrilla, S/n",
    "sg:city":"Trescasas",
    "sg:orig_category":"Caf\u00c9s, Bares, Cervecer\u00cdas",
    "sg:phone":"+34 921 40 77 55",
    "sg:postcode":"40194",
    "sg:province":"Segovia",
    "wof:name":"Perez Garcia Maria Azucena",
    "wof:placetype":"venue"
},
  "geometry": {"coordinates":[-4.0600042343,40.9310340881],"type":"Point"}
}