{
  "type": "Feature",
  "properties": {
    "iso:country":"ES",
    "sg:address":"Ctra. Palma-arta, Km. 0048,8",
    "sg:city":"Manacor",
    "sg:orig_category":"Porcelanas, Azulejos (fabricaci\u00d3n, Al Por Mayor)",
    "sg:phone":"+34 971 55 06 38",
    "sg:postcode":"07500",
    "sg:province":"Islas Baleares",
    "sg:website":"www.materialdeconstruccio.com",
    "wof:name":"Materiales De Construccion Galmes S.a.",
    "wof:placetype":"venue"
},
  "geometry": {"coordinates":[3.1796910763,39.573474884],"type":"Point"}
}