{
  "type": "Feature",
  "properties": {
    "iso:country":"ES",
    "sg:address":"Calle de Costa Rica, S/n",
    "sg:city":"Alcantarilla",
    "sg:orig_category":"Fabricaci\u00d3n De Bolsos Y Bolsos De Tela",
    "sg:phone":"+34 968 80 44 90",
    "sg:postcode":"30820",
    "sg:province":"Murcia",
    "wof:name":"Rodriguez Yelo Vicente",
    "wof:placetype":"venue"
},
  "geometry": {"coordinates":[-1.2378226519,37.9573783875],"type":"Point"}
}