{
  "type": "Feature",
  "properties": {
    "addr:full":"Carrer de Penedes, 46 Prat Llobregat Barcelona 08820",
    "addr:housenumber":"46",
    "addr:postcode":"08820",
    "addr:street":"Carrer De Penedes;Llobregat",
    "iso:country":"ES",
    "sg:address":"Carrer de Penedes, 46",
    "sg:city":"Prat Llobregat",
    "sg:orig_category":"Aparatos, Material Y Suministros Para Laboratorios",
    "sg:phone":"+34 934 78 71 61",
    "sg:postcode":"08820",
    "sg:province":"Barcelona",
    "sg:website":"www.instruanalitica.com",
    "wof:name":"Instrumentacion Analitica S.a",
    "wof:placetype":"venue"
},
  "geometry": {"coordinates":[2.0899980068,41.3276939392],"type":"Point"}
}