{
  "type": "Feature",
  "properties": {
    "iso:country":"ES",
    "sg:address":"Calle de Toledo, 15",
    "sg:city":"Mora",
    "sg:orig_category":"Telas Y Sedas (al Por Menor)",
    "sg:phone":"+34 925 30 06 29",
    "sg:postcode":"45400",
    "sg:province":"Toledo",
    "wof:name":"Gomez Gonzalez Maria De Los Reyes",
    "wof:placetype":"venue"
},
  "geometry": {"coordinates":[-3.7739229202,39.6851959229],"type":"Point"}
}