{
  "type": "Feature",
  "properties": {
    "iso:country":"ES",
    "sg:address":"C/ Juan Ramon Jimenez, 2",
    "sg:city":"Elche",
    "sg:orig_category":"Electrodom\u00c9sticos (al Por Menor)",
    "sg:phone":"+34 965 45 37 85",
    "sg:postcode":"03203",
    "sg:province":"Alicante",
    "wof:name":"Gonzalvez Y Congost S.l.",
    "wof:placetype":"venue"
},
  "geometry": {"coordinates":[-0.6991810203,38.2633247375],"type":"Point"}
}