{
  "type": "Feature",
  "properties": {
    "addr:full":"Avda Doctor Rafael Gonzalez, 19 Arrecife Las Palmas 35500",
    "addr:housenumber":"19",
    "addr:postcode":"35500",
    "addr:street":"Avda Doctor Rafael Gonzalez",
    "iso:country":"ES",
    "sg:address":"Avda Doctor Rafael Gonzalez, 19",
    "sg:city":"Arrecife",
    "sg:orig_category":"Asociaciones, Organismos Culturales Y Socioeducativos",
    "sg:phone":"+34 928 80 62 61",
    "sg:postcode":"35500",
    "sg:province":"Las Palmas",
    "wof:name":"Circulo Mercantil De Arrecife",
    "wof:placetype":"venue"
},
  "geometry": {"coordinates":[-13.5537290573,28.9578266144],"type":"Point"}
}