{
  "type": "Feature",
  "properties": {
    "addr:full":"Calle de Luis I, 2 Madrid Madrid 28031",
    "addr:housenumber":"2",
    "addr:postcode":"28031",
    "addr:street":"Calle De Luis I",
    "iso:country":"ES",
    "sg:address":"Calle de Luis I, 2",
    "sg:city":"Madrid",
    "sg:orig_category":"Maquinaria Para Industrias Diversas",
    "sg:phone":"+34 917 77 76 78",
    "sg:postcode":"28031",
    "sg:province":"Madrid",
    "wof:name":"Reparaciones Hidraulicas Y Nuevos Equipos S.l.",
    "wof:placetype":"venue"
},
  "geometry": {"coordinates":[-3.6395320892,40.3770561218],"type":"Point"}
}