{
  "type": "Feature",
  "properties": {
    "iso:country":"ES",
    "sg:address":"Bard Torno (el), S/n",
    "sg:city":"Chiclana De La Frontera",
    "sg:orig_category":"Transportes Por Carretera: Lotes Completos, Mercanc\u00cdas Diversas",
    "sg:phone":"+34 956 40 15 15",
    "sg:postcode":"11130",
    "sg:province":"C\u00e1diz",
    "wof:name":"Batista Bello Alfonso",
    "wof:placetype":"venue"
},
  "geometry": {"coordinates":[-6.1830239296,36.3790245056],"type":"Point"}
}