{
  "type": "Feature",
  "properties": {
    "addr:full":"Afores, S/n S. Esteve Sesrovires Barcelona 08635",
    "addr:housenumber":"s",
    "addr:postcode":"08635",
    "addr:street":"Afores;/ N S. Esteve Sesrovires Barcelona",
    "iso:country":"ES",
    "sg:address":"Afores, S/n",
    "sg:city":"S. Esteve Sesrovires",
    "sg:classifiers":[
        {
            "category":"Food & Beverages",
            "subcategory":"Candy",
            "type":"Retail Goods"
        }
    ],
    "sg:phone":"+34 937 71 40 62",
    "sg:postcode":"08635",
    "sg:province":"Barcelona",
    "sg:tags":[
        "confiter\u00cdas",
        "y",
        "de",
        "fabricaci\u00d3n",
        "chocolate"
    ],
    "wof:name":"Sociedad Anonima Chupa Chups",
    "wof:placetype":"venue"
},
  "geometry": {"coordinates":[1.8731199503,41.4965515137],"type":"Point"}
}