{
  "type": "Feature",
  "properties": {
    "addr:full":"Calle de Anaca, 44 Irun Guip\u00f9zcoa 20301",
    "addr:housenumber":"44",
    "addr:postcode":"20301",
    "addr:street":"Calle De Anaca;Guipu\u0300Zcoa",
    "iso:country":"ES",
    "sg:address":"Calle de Anaca, 44",
    "sg:city":"Irun",
    "sg:orig_category":"Promotores Constructores",
    "sg:phone":"+34 943 61 51 59",
    "sg:postcode":"20301",
    "sg:province":"Guip\u00f9zcoa",
    "wof:name":"Construcciones Lefesa S.l.",
    "wof:placetype":"venue"
},
  "geometry": {"coordinates":[-1.8089660406,43.3410377502],"type":"Point"}
}