{
  "type": "Feature",
  "properties": {
    "iso:country":"ES",
    "sg:address":"O Outeiro, 21",
    "sg:city":"Moreira",
    "sg:orig_category":"Peritos Mar\u00cdtimos",
    "sg:phone":"+34 986 57 20 41",
    "sg:postcode":"36688",
    "sg:province":"Pontevedra",
    "wof:name":"Pi\u00f1eiro Pena Ramiro",
    "wof:placetype":"venue"
},
  "geometry": {"coordinates":[-8.4677591324,42.6931114197],"type":"Point"}
}