{
  "type": "Feature",
  "properties": {
    "iso:country":"ES",
    "sg:address":"Calle de Colon, 57",
    "sg:city":"Costa De Madrid",
    "sg:orig_category":"Fabricaci\u00d3n, Venta, Instalaci\u00d3n De R\u00d3tulos, De R\u00d3tulos Luminosos",
    "sg:phone":"+34 918 62 80 11",
    "sg:postcode":"28680",
    "sg:province":"Madrid",
    "wof:name":"Rotulos Adhesivos S.a.",
    "wof:placetype":"venue"
},
  "geometry": {"coordinates":[-4.3622512817,40.3900527954],"type":"Point"}
}