{
  "type": "Feature",
  "properties": {
    "addr:full":"Calle de Askatasun Bidea, 30 Bermeo Vizcaya 48370",
    "addr:housenumber":"30",
    "addr:postcode":"48370",
    "addr:street":"Calle De Askatasun Bidea",
    "iso:country":"ES",
    "sg:address":"Calle de Askatasun Bidea, 30",
    "sg:city":"Bermeo",
    "sg:orig_category":"Puertas Y Portales",
    "sg:phone":"+34 946 18 77 78",
    "sg:postcode":"48370",
    "sg:province":"Vizcaya",
    "wof:name":"Lejarzabal, S.l",
    "wof:placetype":"venue"
},
  "geometry": {"coordinates":[-2.727067709,43.4175643921],"type":"Point"}
}