{
  "type": "Feature",
  "properties": {
    "addr:full":"Plaz Romano (del), 2 Valdemoro Madrid 28340",
    "addr:postcode":"28340",
    "iso:country":"ES",
    "sg:address":"Plaz Romano (del), 2",
    "sg:city":"Valdemoro",
    "sg:orig_category":"Construcciones Met\u00c1licas",
    "sg:phone":"+34 918 95 33 36",
    "sg:postcode":"28340",
    "sg:province":"Madrid",
    "wof:name":"Bordallo Romero Esteban",
    "wof:placetype":"venue"
},
  "geometry": {"coordinates":[-3.6738090515,40.1909751892],"type":"Point"}
}