{
  "type": "Feature",
  "properties": {
    "iso:country":"ES",
    "sg:address":"Av Onze De Setembre, 6",
    "sg:city":"S. Pere Ribes",
    "sg:orig_category":"Asesor\u00cda Fiscal Y Jur\u00cddica",
    "sg:phone":"+34 938 96 48 44",
    "sg:postcode":"08810",
    "sg:province":"Barcelona",
    "wof:name":"Sp Assessoria S.l.",
    "wof:placetype":"venue"
},
  "geometry": {"coordinates":[1.7722949982,41.2599143982],"type":"Point"}
}