{
  "type": "Feature",
  "properties": {
    "addr:full":"Calle de Concepcion, 82 Campo Criptana Ciudad Real 13610",
    "addr:housenumber":"82",
    "addr:postcode":"13610",
    "addr:street":"Calle De Concepcion;Criptana",
    "iso:country":"ES",
    "sg:address":"Calle de Concepcion, 82",
    "sg:city":"Campo Criptana",
    "sg:orig_category":"Tubos Y Tuber\u00cdas De Goma Y Pl\u00c1stico (fabricaci\u00d3n, Al Por Mayor)",
    "sg:phone":"+34 926 56 05 98",
    "sg:postcode":"13610",
    "sg:province":"Ciudad Real",
    "wof:name":"Don Melitino S.l",
    "wof:placetype":"venue"
},
  "geometry": {"coordinates":[-3.1166388988,39.4016990662],"type":"Point"}
}