{
  "type": "Feature",
  "properties": {
    "iso:country":"ES",
    "sg:address":"Carrer de Energia, 5",
    "sg:city":"Mataro",
    "sg:orig_category":"Fabricaci\u00d3n De Su\u00c9ters Y Chalecos De Punto",
    "sg:phone":"+34 937 90 62 50",
    "sg:postcode":"08304",
    "sg:province":"Barcelona",
    "wof:name":"Matfil S.c.p.",
    "wof:placetype":"venue"
},
  "geometry": {"coordinates":[2.4535989761,41.5508918762],"type":"Point"}
}