{
  "type": "Feature",
  "properties": {
    "iso:country":"ES",
    "sg:address":"Pase Berio De, 13",
    "sg:city":"Donostia-san Sebastian",
    "sg:orig_category":"Fotocopias, Reprograf\u00cda",
    "sg:phone":"+34 943 31 02 01",
    "sg:postcode":"20018",
    "sg:province":"Guip\u00f9zcoa",
    "wof:name":"Cortezon Salazar Jose Antonio",
    "wof:placetype":"venue"
},
  "geometry": {"coordinates":[-2.0029520988,43.2836837769],"type":"Point"}
}