{
  "type": "Feature",
  "properties": {
    "addr:full":"Avda Constitucion, 120 Cistierna Le\u00f3n 24800",
    "addr:housenumber":"120",
    "addr:postcode":"24800",
    "addr:street":"Avda Constitucion;Leo\u0301N",
    "iso:country":"ES",
    "sg:address":"Avda Constitucion, 120",
    "sg:city":"Cistierna",
    "sg:orig_category":"Procuradores",
    "sg:phone":"+34 987 70 14 09",
    "sg:postcode":"24800",
    "sg:province":"Le\u00f3n",
    "wof:name":"Fernandez Rey Yolanda",
    "wof:placetype":"venue"
},
  "geometry": {"coordinates":[-5.1288819313,42.8051834106],"type":"Point"}
}