{
  "type": "Feature",
  "properties": {
    "iso:country":"ES",
    "sg:address":"Gta Veintitres De Junio, 5",
    "sg:city":"Malagon",
    "sg:orig_category":"Productores Recolectores, Venta Directa De Vinos",
    "sg:phone":"+34 926 80 10 62",
    "sg:postcode":"13420",
    "sg:province":"Ciudad Real",
    "wof:name":"Bodegas Herbasa S. A. T. Limitada",
    "wof:placetype":"venue"
},
  "geometry": {"coordinates":[-3.8552429676,39.1720504761],"type":"Point"}
}