{
  "type": "Feature",
  "properties": {
    "addr:full":"Calle de Pio Xii, 40 Oropesa Castell\u00f3n 12594",
    "addr:housenumber":"40",
    "addr:postcode":"12594",
    "addr:street":"Calle De Pio Xii",
    "iso:country":"ES",
    "sg:address":"Calle de Pio Xii, 40",
    "sg:city":"Oropesa",
    "sg:orig_category":"Administradores De Bienes Y Delegados De Comunidades De Propietarios",
    "sg:phone":"+34 964 31 31 21",
    "sg:postcode":"12594",
    "sg:province":"Castell\u00f3n",
    "wof:name":"Casanova Sastriques Javier",
    "wof:placetype":"venue"
},
  "geometry": {"coordinates":[0.1385360062,40.0918579102],"type":"Point"}
}