{
  "type": "Feature",
  "properties": {
    "addr:full":"Calle de Leopoldo Alas Clarin, 51 Madrid Madrid 28035",
    "addr:housenumber":"51",
    "addr:postcode":"madrid;28035",
    "addr:street":"Calle De Leopoldo Alas Clarin",
    "iso:country":"ES",
    "sg:address":"Calle de Leopoldo Alas Clarin, 51",
    "sg:city":"Madrid",
    "sg:orig_category":"Venta, Instalaci\u00d3n De Cocinas",
    "sg:phone":"+34 913 73 51 33",
    "sg:postcode":"28035",
    "sg:province":"Madrid",
    "wof:name":"Nablos S.l.",
    "wof:placetype":"venue"
},
  "geometry": {"coordinates":[-3.732927084,40.4814338684],"type":"Point"}
}