{
  "type": "Feature",
  "properties": {
    "iso:country":"ES",
    "sg:address":"Pase Deleite (del), S/n",
    "sg:city":"Aranjuez",
    "sg:orig_category":"Supermercados Y Hipermercados",
    "sg:phone":"+34 918 91 32 63",
    "sg:postcode":"28300",
    "sg:province":"Madrid",
    "wof:name":"Arancedis S.l.",
    "wof:placetype":"venue"
},
  "geometry": {"coordinates":[-3.6155354977,40.0249671936],"type":"Point"}
}