{
  "type": "Feature",
  "properties": {
    "iso:country":"ES",
    "sg:address":"Calle de Ximenez De Enciso, 35",
    "sg:city":"Sevilla",
    "sg:orig_category":"Abogados",
    "sg:phone":"+34 954 56 48 68",
    "sg:postcode":"41004",
    "sg:province":"Sevilla",
    "wof:name":"Benitez Madro\u00f1al Maria Luisa",
    "wof:placetype":"venue"
},
  "geometry": {"coordinates":[-5.9892940521,37.3861503601],"type":"Point"}
}