{
  "type": "Feature",
  "properties": {
    "iso:country":"ES",
    "sg:address":"Carrer de Bizet, 49",
    "sg:city":"Rubi",
    "sg:orig_category":"Protecci\u00d3n Contra Robo (material E Instalaci\u00d3n)",
    "sg:phone":"+34 935 86 20 24",
    "sg:postcode":"08191",
    "sg:province":"Barcelona",
    "wof:name":"Solga S.a.",
    "wof:placetype":"venue"
},
  "geometry": {"coordinates":[2.0240600109,41.4733390808],"type":"Point"}
}