{
  "type": "Feature",
  "properties": {
    "iso:country":"ES",
    "sg:address":"G.v. Puig De Teix, S/n",
    "sg:city":"Santa Pon\u00c7a",
    "sg:orig_category":"Peluquer\u00cdas, Peluquer\u00cda Mixta",
    "sg:phone":"+34 971 13 42 63",
    "sg:postcode":"07180",
    "sg:province":"Islas Baleares",
    "wof:name":"Salon De Peluqueria Sabadello",
    "wof:placetype":"venue"
},
  "geometry": {"coordinates":[2.4985899925,39.5253143311],"type":"Point"}
}