{
  "type": "Feature",
  "properties": {
    "iso:country":"ES",
    "sg:address":"Calle de Alboraya, 14",
    "sg:city":"Valencia",
    "sg:orig_category":"Asociaciones Y Clubs Deportivos",
    "sg:phone":"+34 963 61 39 42",
    "sg:postcode":"46010",
    "sg:province":"Valencia",
    "wof:name":"Caldesidi S.a.",
    "wof:placetype":"venue"
},
  "geometry": {"coordinates":[-0.3711090088,39.4808959961],"type":"Point"}
}