{
  "type": "Feature",
  "properties": {
    "iso:country":"ES",
    "sg:address":"Carrer de Industria, 106",
    "sg:city":"Barriada Nova",
    "sg:orig_category":"Aspiradoras Industriales",
    "sg:phone":"+34 938 46 45 75",
    "sg:postcode":"08420",
    "sg:province":"Barcelona",
    "wof:name":"Montaje Del Tubo S.l.",
    "wof:placetype":"venue"
},
  "geometry": {"coordinates":[2.2780098915,41.6220703125],"type":"Point"}
}