{
  "type": "Feature",
  "properties": {
    "iso:country":"ES",
    "sg:address":"Pla\u00c7 Esglesia, S/n",
    "sg:city":"Torres Segre",
    "sg:orig_category":"Ense\u00d1anza, Formaci\u00d3n Profesional: Aprendizaje",
    "sg:phone":"+34 973 79 60 05",
    "sg:postcode":"25170",
    "sg:province":"Lleida",
    "wof:name":"Ajuntament De Torres De Segre",
    "wof:placetype":"venue"
},
  "geometry": {"coordinates":[0.6257824898,41.614151001],"type":"Point"}
}