{
  "type": "Feature",
  "properties": {
    "iso:country":"ES",
    "sg:address":"Calle de Jose Antonio Primo Rivera, 7",
    "sg:city":"Algeciras",
    "sg:orig_category":"Arquitectos",
    "sg:phone":"+34 956 66 36 53",
    "sg:postcode":"11201",
    "sg:province":"C\u00e1diz",
    "wof:name":"Aldana Almagro Antonio",
    "wof:placetype":"venue"
},
  "geometry": {"coordinates":[-5.4465374947,36.1302909851],"type":"Point"}
}