{
  "type": "Feature",
  "properties": {
    "addr:full":"Calle de Fuencarral, 80 Madrid Madrid 28004",
    "addr:housenumber":"80",
    "addr:postcode":"madrid;28004",
    "addr:street":"Calle De Fuencarral",
    "iso:country":"ES",
    "sg:address":"Calle de Fuencarral, 80",
    "sg:city":"Madrid",
    "sg:orig_category":"Estancos",
    "sg:phone":"+34 915 22 71 52",
    "sg:postcode":"28004",
    "sg:province":"Madrid",
    "wof:name":"Donoso Perez-cabrero Francisco",
    "wof:placetype":"venue"
},
  "geometry": {"coordinates":[-3.7011189461,40.4261894226],"type":"Point"}
}