{
  "type": "Feature",
  "properties": {
    "iso:country":"ES",
    "sg:address":"Carrer de Pare Artigas, 72",
    "sg:city":"Viladecans",
    "sg:orig_category":"Comercio De Piezas De Recambio Y De Accesorios De Veh\u00cdculos, Veh\u00cdculos Industriales",
    "sg:phone":"+34 936 37 96 19",
    "sg:postcode":"08840",
    "sg:province":"Barcelona",
    "wof:name":"Palomo Navarro Jose",
    "wof:placetype":"venue"
},
  "geometry": {"coordinates":[2.0150880814,41.320110321],"type":"Point"}
}