{
  "type": "Feature",
  "properties": {
    "addr:full":"Calle de Ostoki, 10 Ansoain Navarra 31013",
    "addr:housenumber":"10",
    "addr:postcode":"31013",
    "addr:street":"Calle De Ostoki",
    "iso:country":"ES",
    "sg:address":"Calle de Ostoki, 10",
    "sg:city":"Ansoain",
    "sg:orig_category":"Ropa Para Se\u00d1oras (al Por Menor)",
    "sg:phone":"+34 948 14 31 90",
    "sg:postcode":"31013",
    "sg:province":"Navarra",
    "wof:name":"Atienza Jimenez Presentacion Garcia Marcos Raquel S.i.",
    "wof:placetype":"venue"
},
  "geometry": {"coordinates":[-1.6414607763,42.8316574097],"type":"Point"}
}