{
  "type": "Feature",
  "properties": {
    "addr:full":"Calle de Estacion, 78 Mendavia Navarra 31587",
    "addr:housenumber":"78",
    "addr:postcode":"31587",
    "addr:street":"Calle De Estacion",
    "iso:country":"ES",
    "sg:address":"Calle de Estacion, 78",
    "sg:city":"Mendavia",
    "sg:orig_category":"Transportes Por Carretera: Lotes Completos, Mercanc\u00cdas Diversas",
    "sg:phone":"+34 948 68 51 33",
    "sg:postcode":"31587",
    "sg:province":"Navarra",
    "wof:name":"Gonzalez Martinez De Espronceda Juan Cruz",
    "wof:placetype":"venue"
},
  "geometry": {"coordinates":[-2.2009499073,42.4406433105],"type":"Point"}
}