{
  "type": "Feature",
  "properties": {
    "iso:country":"ES",
    "sg:address":"Pase Extremadura, 18",
    "sg:city":"Madrid",
    "sg:orig_category":"Centros De Adelgazamiento Y De Est\u00c9tica",
    "sg:phone":"+34 915 26 72 53",
    "sg:postcode":"28011",
    "sg:province":"Madrid",
    "wof:name":"Garrido Sanabria Pilar",
    "wof:placetype":"venue"
},
  "geometry": {"coordinates":[-3.726320982,40.4139480591],"type":"Point"}
}