{
  "type": "Feature",
  "properties": {
    "iso:country":"ES",
    "sg:address":"Arangutxi Kalea, 33",
    "sg:city":"Jundiz",
    "sg:orig_category":"Controles De Edificaci\u00d3n (construcci\u00d3n, Seguridad)",
    "sg:phone":"+34 945 21 33 74",
    "sg:postcode":"01015",
    "sg:province":"\u00c1lava",
    "wof:name":"Promociones Y Servicios Topograficos Gaztelan S.l.",
    "wof:placetype":"venue"
},
  "geometry": {"coordinates":[-2.7263889313,42.8406524658],"type":"Point"}
}