{
  "type": "Feature",
  "properties": {
    "addr:full":"Carrer de Angel Guimera, 3 Vendrell Tarragona 43700",
    "addr:housenumber":"3",
    "addr:postcode":"43700",
    "addr:street":"Carrer De Angel Guimera",
    "iso:country":"ES",
    "sg:address":"Carrer de Angel Guimera, 3",
    "sg:city":"Vendrell",
    "sg:orig_category":"Importaci\u00d3n, Exportaci\u00d3n Y Comercios De Productos Textiles",
    "sg:phone":"+34 977 66 33 12",
    "sg:postcode":"43700",
    "sg:province":"Tarragona",
    "wof:name":"Nuvias Y Nuvis Angela Angelo S.l.",
    "wof:placetype":"venue"
},
  "geometry": {"coordinates":[1.5346390009,41.2219543457],"type":"Point"}
}