{
  "type": "Feature",
  "properties": {
    "addr:full":"Carrer de Ramon Y Cajal, 5 Palma Islas Baleares 07011",
    "addr:housenumber":"5",
    "addr:postcode":"07011",
    "addr:street":"Carrer De Ramon Y Cajal",
    "iso:country":"ES",
    "sg:address":"Carrer de Ramon Y Cajal, 5",
    "sg:city":"Palma",
    "sg:orig_category":"Sociedades, Compa\u00d1\u00cdas Aseguradoras",
    "sg:phone":"+34 971 77 40 33",
    "sg:postcode":"07011",
    "sg:province":"Islas Baleares",
    "wof:name":"Zurich Espa\u00d1a S.a.",
    "wof:placetype":"venue"
},
  "geometry": {"coordinates":[2.6428177357,39.5758895874],"type":"Point"}
}