{
  "type": "Feature",
  "properties": {
    "addr:full":"Avda Perez Galdos, 5 Bu\u00f1ol Valencia 46360",
    "addr:housenumber":"5",
    "addr:postcode":"46360",
    "addr:street":"Avda Perez Galdos",
    "iso:country":"ES",
    "sg:address":"Avda Perez Galdos, 5",
    "sg:city":"Bu\u00f1ol",
    "sg:orig_category":"Albergues",
    "sg:phone":"+34 962 50 09 23",
    "sg:postcode":"46360",
    "sg:province":"Valencia",
    "wof:name":"Posada Venta Pilar S.l.",
    "wof:placetype":"venue"
},
  "geometry": {"coordinates":[-0.7928389907,39.4266357422],"type":"Point"}
}