{
  "type": "Feature",
  "properties": {
    "addr:full":"Calle de Virgen De La Palma, 14 Cadiz C\u00e1diz 11002",
    "addr:housenumber":"14",
    "addr:postcode":"11002",
    "addr:street":"Calle De Virgen De La Palma",
    "iso:country":"ES",
    "sg:address":"Calle de Virgen De La Palma, 14",
    "sg:city":"Cadiz",
    "sg:orig_category":"Equipo De Refrigeraci\u00d3n Industrial",
    "sg:phone":"+34 956 22 19 98",
    "sg:postcode":"11002",
    "sg:province":"C\u00e1diz",
    "wof:name":"Jose Canto Fernandez Y Juan Carlos Canto Manteca Cdad",
    "wof:placetype":"venue"
},
  "geometry": {"coordinates":[-6.302628994,36.5296096802],"type":"Point"}
}