{
  "type": "Feature",
  "properties": {
    "addr:full":"Badalona(cala De Bou), 4 S. Agusti Vedra Islas Baleares 07839",
    "addr:housenumber":"4",
    "addr:postcode":"07839",
    "addr:street":"Bou;S. Agusti",
    "iso:country":"ES",
    "sg:address":"Badalona(cala De Bou), 4",
    "sg:city":"S. Agusti Vedra",
    "sg:orig_category":"Tintorer\u00cdas, Limpieza En Seco",
    "sg:phone":"+34 971 34 55 21",
    "sg:postcode":"07839",
    "sg:province":"Islas Baleares",
    "wof:name":"Lavanderia Orosol S.l.",
    "wof:placetype":"venue"
},
  "geometry": {"coordinates":[1.3025970459,38.8642692566],"type":"Point"}
}