{
  "type": "Feature",
  "properties": {
    "addr:full":"Carr Josep Fabrega I Pou, 75 Palamos Girona 17230",
    "addr:housenumber":"75",
    "addr:postcode":"17230",
    "addr:street":"Carr Josep Fabrega I Pou",
    "iso:country":"ES",
    "sg:address":"Carr Josep Fabrega I Pou, 75",
    "sg:city":"Palamos",
    "sg:orig_category":"Asistencia Domiciliaria",
    "sg:phone":"+34 972 31 88 11",
    "sg:postcode":"17230",
    "sg:province":"Girona",
    "wof:name":"Adfis S.c.c.l",
    "wof:placetype":"venue"
},
  "geometry": {"coordinates":[3.1333222389,41.8487510681],"type":"Point"}
}