{
  "type": "Feature",
  "properties": {
    "iso:country":"ES",
    "sg:address":"Pl Nadal, S/n",
    "sg:city":"Barcelona",
    "sg:orig_category":"Librer\u00cdas",
    "sg:phone":"+34 933 46 14 64",
    "sg:postcode":"08030",
    "sg:province":"Barcelona",
    "wof:name":"Martinez Montoliu Montserrat",
    "wof:placetype":"venue"
},
  "geometry": {"coordinates":[2.1884651184,41.4290313721],"type":"Point"}
}