{
  "type": "Feature",
  "properties": {
    "iso:country":"ES",
    "sg:address":"Calle de Puerto De Alazores, 18",
    "sg:city":"Madrid",
    "sg:orig_category":"Comunidades Religiosas",
    "sg:phone":"+34 913 80 15 96",
    "sg:postcode":"28031",
    "sg:province":"Madrid",
    "wof:name":"Hijas De Maria Auxiliadora Prov V Camino",
    "wof:placetype":"venue"
},
  "geometry": {"coordinates":[-3.6255600452,40.3789520264],"type":"Point"}
}