{
  "type": "Feature",
  "properties": {
    "addr:full":"Carrer de Rambla, 19 Santa Perpetua De Mogoda Barcelona 08130",
    "addr:housenumber":"19",
    "addr:postcode":"08130",
    "addr:street":"Carrer De Rambla",
    "iso:country":"ES",
    "sg:address":"Carrer de Rambla, 19",
    "sg:city":"Santa Perpetua De Mogoda",
    "sg:orig_category":"Bancos",
    "sg:phone":"+34 935 60 43 05",
    "sg:postcode":"08130",
    "sg:province":"Barcelona",
    "sg:website":"www.bancopopular.es",
    "wof:name":"Banco Popular Espa\u00f1ol S.a.",
    "wof:placetype":"venue"
},
  "geometry": {"coordinates":[2.1809749603,41.5350189209],"type":"Point"}
}