{
  "type": "Feature",
  "properties": {
    "addr:full":"Carr Prosperitat, De, 24 Soller Islas Baleares 07100",
    "addr:housenumber":"24",
    "addr:postcode":"07100",
    "addr:street":"Carr Prosperitat De",
    "iso:country":"ES",
    "sg:address":"Carr Prosperitat, De, 24",
    "sg:city":"Soller",
    "sg:orig_category":"Negocio De Materiales De Construcci\u00d3n",
    "sg:phone":"+34 971 63 10 53",
    "sg:postcode":"07100",
    "sg:province":"Islas Baleares",
    "wof:name":"Ca'n Capo S.a.",
    "wof:placetype":"venue"
},
  "geometry": {"coordinates":[2.7099320889,39.7688484192],"type":"Point"}
}