{
  "type": "Feature",
  "properties": {
    "iso:country":"ES",
    "sg:address":"Calle de Cruz Del Mar, 37",
    "sg:city":"Giles",
    "sg:orig_category":"Empresas De Carpinter\u00cda",
    "sg:phone":"+34 928 67 52 31",
    "sg:postcode":"35010",
    "sg:province":"Las Palmas",
    "wof:name":"Delgado Martin Gines",
    "wof:placetype":"venue"
},
  "geometry": {"coordinates":[-15.4741954803,28.116186142],"type":"Point"}
}