{
  "type": "Feature",
  "properties": {
    "iso:country":"ES",
    "sg:address":"Calle de Malpica, 49",
    "sg:city":"Miguelturra",
    "sg:orig_category":"Agentes Generales De Seguros",
    "sg:phone":"+34 926 24 09 85",
    "sg:postcode":"13170",
    "sg:province":"Ciudad Real",
    "wof:name":"Rodrigo Rodrigo Josefa",
    "wof:placetype":"venue"
},
  "geometry": {"coordinates":[-3.8847789764,38.9660797119],"type":"Point"}
}