{
  "type": "Feature",
  "properties": {
    "iso:country":"ES",
    "sg:address":"Rond Subira, 7",
    "sg:city":"Reus",
    "sg:orig_category":"Empresas De Carpinter\u00cda",
    "sg:phone":"+34 977 75 55 18",
    "sg:postcode":"43205",
    "sg:province":"Tarragona",
    "wof:name":"Morillo Lucas Marcos",
    "wof:placetype":"venue"
},
  "geometry": {"coordinates":[1.1087169647,41.1495895386],"type":"Point"}
}