{
  "type": "Feature",
  "properties": {
    "iso:country":"ES",
    "sg:address":"Calle de Maestro Arrieta, 38",
    "sg:city":"Castellon",
    "sg:orig_category":"Caf\u00c9s, Bares, Cervecer\u00cdas",
    "sg:phone":"+34 964 24 09 29",
    "sg:postcode":"12006",
    "sg:province":"Castell\u00f3n",
    "wof:name":"Kin Dol\u00e7or S.l.",
    "wof:placetype":"venue"
},
  "geometry": {"coordinates":[-0.1292939931,40.0168533325],"type":"Point"}
}