{
  "type": "Feature",
  "properties": {
    "iso:country":"ES",
    "sg:address":"Calle de Pelayo, 3",
    "sg:city":"Novelda",
    "sg:orig_category":"Venta, Alquiler De V\u00cddeo",
    "sg:phone":"+34 965 60 57 63",
    "sg:postcode":"03660",
    "sg:province":"Alicante",
    "wof:name":"Gomez Beltran Pedro",
    "wof:placetype":"venue"
},
  "geometry": {"coordinates":[-0.765846014,38.3857460022],"type":"Point"}
}