{
  "type": "Feature",
  "properties": {
    "iso:country":"ES",
    "sg:address":"Calle de Ramal (el), 1",
    "sg:city":"Orotava",
    "sg:orig_category":"Agentes, Concesionarios Y Sucursales De Veh\u00cdculos",
    "sg:phone":"+34 922 33 05 71",
    "sg:postcode":"38300",
    "sg:province":"Santa Cruz De Tenerife",
    "wof:name":"Marrero Rodriguez Jose Manuel",
    "wof:placetype":"venue"
},
  "geometry": {"coordinates":[-16.5189990997,28.3903846741],"type":"Point"}
}