{
  "type": "Feature",
  "properties": {
    "iso:country":"ES",
    "sg:address":"Pl Constitucio, 7",
    "sg:city":"Cambrils",
    "sg:orig_category":"M\u00c9dicos: An\u00c1lisis Cl\u00cdnicos",
    "sg:phone":"+34 977 36 06 53",
    "sg:postcode":"43850",
    "sg:province":"Tarragona",
    "wof:name":"Laboratori Doctor Vidal-general Lab S.l.",
    "wof:placetype":"venue"
},
  "geometry": {"coordinates":[1.0611100197,41.0672683716],"type":"Point"}
}