{
  "type": "Feature",
  "properties": {
    "addr:full":"Rua 8 De Marzo Dia Da Muller Traballadora, 1 Redondela Pontevedra 36800",
    "addr:housenumber":"1",
    "addr:postcode":"36800",
    "addr:street":"Rua 8 De",
    "iso:country":"ES",
    "sg:address":"Rua 8 De Marzo Dia Da Muller Traballadora, 1",
    "sg:city":"Redondela",
    "sg:orig_category":"Fotograf\u00cda Y Cine: Aparatos, Pel\u00cdculas Y Accesorios (al Por Menor)",
    "sg:phone":"+34 986 40 29 07",
    "sg:postcode":"36800",
    "sg:province":"Pontevedra",
    "wof:name":"Bastos Miguez Sandra",
    "wof:placetype":"venue"
},
  "geometry": {"coordinates":[-8.6110639572,42.2805900574],"type":"Point"}
}