{
  "type": "Feature",
  "properties": {
    "iso:country":"ES",
    "sg:address":"Rua Vilar (do), 4",
    "sg:city":"Santiago De Compostela",
    "sg:orig_category":"Artesan\u00cda",
    "sg:phone":"+34 981 58 56 32",
    "sg:postcode":"15705",
    "sg:province":"La Coru\u00f1a",
    "wof:name":"Maside Medina Rosa Maria",
    "wof:placetype":"venue"
},
  "geometry": {"coordinates":[-8.5441665649,42.8797836304],"type":"Point"}
}