{
  "type": "Feature",
  "properties": {
    "iso:country":"ES",
    "sg:address":"Carrer de Cabrera, 20",
    "sg:city":"Palma",
    "sg:orig_category":"Electricidad: Instaladores",
    "sg:phone":"+34 971 24 07 69",
    "sg:postcode":"07007",
    "sg:province":"Islas Baleares",
    "wof:name":"Electrica Bon Llum S.l.",
    "wof:placetype":"venue"
},
  "geometry": {"coordinates":[2.6724200249,39.5702285767],"type":"Point"}
}