{
  "type": "Feature",
  "properties": {
    "addr:full":"Calle de Tibi, 4 Ibi Alicante 03440",
    "addr:housenumber":"4",
    "addr:postcode":"03440",
    "addr:street":"Calle De Tibi",
    "iso:country":"ES",
    "sg:address":"Calle de Tibi, 4",
    "sg:city":"Ibi",
    "sg:orig_category":"Institutos De Belleza",
    "sg:phone":"+34 965 55 18 33",
    "sg:postcode":"03440",
    "sg:province":"Alicante",
    "wof:name":"Moda E Imagen De Ibi S.l.",
    "wof:placetype":"venue"
},
  "geometry": {"coordinates":[-0.5765050054,38.6238899231],"type":"Point"}
}