{
  "type": "Feature",
  "properties": {
    "iso:country":"ES",
    "sg:address":"Calle de Benalmadena, 9",
    "sg:city":"Fuengirola",
    "sg:orig_category":"Empresas De Carpinter\u00cda De Madera",
    "sg:phone":"+34 952 47 39 92",
    "sg:postcode":"29640",
    "sg:province":"M\u00e1laga",
    "wof:name":"Belmonte Lozano Juan Manuel",
    "wof:placetype":"venue"
},
  "geometry": {"coordinates":[-4.6142921448,36.5562438965],"type":"Point"}
}