{
  "type": "Feature",
  "properties": {
    "addr:full":"Miguel Servet, S/n Cadrete Zaragoza 50420",
    "addr:housenumber":"s",
    "addr:postcode":"50420",
    "addr:street":"Miguel Servet;/ N Cadrete",
    "iso:country":"ES",
    "sg:address":"Miguel Servet, S/n",
    "sg:city":"Cadrete",
    "sg:orig_category":"Empresas De Carpinter\u00cda De Madera",
    "sg:phone":"+34 976 12 68 34",
    "sg:postcode":"50420",
    "sg:province":"Zaragoza",
    "wof:name":"Carpinteria Orense S.l.",
    "wof:placetype":"venue"
},
  "geometry": {"coordinates":[-0.9601830244,41.5556411743],"type":"Point"}
}