{
  "type": "Feature",
  "properties": {
    "iso:country":"ES",
    "sg:address":"Cami Miralpeix, 31",
    "sg:city":"Sitges",
    "sg:orig_category":"Inmobiliaria (agencias)",
    "sg:phone":"+34 938 14 65 05",
    "sg:postcode":"08870",
    "sg:province":"Barcelona",
    "wof:name":"Tanrasac S.l.",
    "wof:placetype":"venue"
},
  "geometry": {"coordinates":[1.7729350328,41.2297554016],"type":"Point"}
}