{
  "type": "Feature",
  "properties": {
    "addr:full":"Carrer de Cid Campeador, 13 Terrassa Barcelona 08225",
    "addr:housenumber":"13",
    "addr:postcode":"08225",
    "addr:street":"Carrer De Cid Campeador",
    "iso:country":"ES",
    "sg:address":"Carrer de Cid Campeador, 13",
    "sg:city":"Terrassa",
    "sg:orig_category":"Andamiajes Y Escaleras De Mano (fabricaci\u00d3n, Al Por Mayor)",
    "sg:phone":"+34 937 80 56 27",
    "sg:postcode":"08225",
    "sg:province":"Barcelona",
    "wof:name":"T.a.j. Sucias S.l.",
    "wof:placetype":"venue"
},
  "geometry": {"coordinates":[2.0021491051,41.5761108398],"type":"Point"}
}