{
  "type": "Feature",
  "properties": {
    "iso:country":"ES",
    "sg:address":"Calle de Pe\u00d1a De Francia, 23",
    "sg:city":"Salamanca",
    "sg:orig_category":"Dibujantes (diversos)",
    "sg:phone":"+34 923 23 07 19",
    "sg:postcode":"37007",
    "sg:province":"Salamanca",
    "wof:name":"Lopez Pulido Felix",
    "wof:placetype":"venue"
},
  "geometry": {"coordinates":[-5.6751890182,40.9709396362],"type":"Point"}
}