{
  "type": "Feature",
  "properties": {
    "iso:country":"ES",
    "sg:address":"Calle de Romero Robledo, 26",
    "sg:city":"Madrid",
    "sg:orig_category":"Empresarios Y Productoras De Espect\u00c1culos",
    "sg:phone":"+34 915 49 09 21",
    "sg:postcode":"28008",
    "sg:province":"Madrid",
    "wof:name":"Peris Ohrt Cristina",
    "wof:placetype":"venue"
},
  "geometry": {"coordinates":[-3.7229480743,40.4311027527],"type":"Point"}
}