{
  "type": "Feature",
  "properties": {
    "addr:full":"Avda Juan Andres, 14 Madrid Madrid 28035",
    "addr:housenumber":"14",
    "addr:postcode":"madrid;28035",
    "addr:street":"Avda Juan Andres",
    "iso:country":"ES",
    "sg:address":"Avda Juan Andres, 14",
    "sg:city":"Madrid",
    "sg:orig_category":"Filtros Y Elementos Filtradores",
    "sg:phone":"+34 913 86 05 78",
    "sg:postcode":"28035",
    "sg:province":"Madrid",
    "wof:name":"Peiro S.a.",
    "wof:placetype":"venue"
},
  "geometry": {"coordinates":[-3.7228500843,40.4674949646],"type":"Point"}
}