{
  "type": "Feature",
  "properties": {
    "addr:full":"Carr Salvador Giner, 33 Godella Valencia 46110",
    "addr:housenumber":"33",
    "addr:postcode":"46110",
    "addr:street":"Carr Salvador Giner",
    "iso:country":"ES",
    "sg:address":"Carr Salvador Giner, 33",
    "sg:city":"Godella",
    "sg:orig_category":"Reposter\u00cdas",
    "sg:phone":"+34 963 63 87 60",
    "sg:postcode":"46110",
    "sg:province":"Valencia",
    "wof:name":"Esteve Pelechano Joaquin",
    "wof:placetype":"venue"
},
  "geometry": {"coordinates":[-0.4074189961,39.5173683167],"type":"Point"}
}