{
  "type": "Feature",
  "properties": {
    "addr:full":"Calle de Real, 1 Villar Olalla Cuenca 16196",
    "addr:housenumber":"1",
    "addr:postcode":"16196",
    "addr:street":"Calle De Real",
    "iso:country":"ES",
    "sg:address":"Calle de Real, 1",
    "sg:city":"Villar Olalla",
    "sg:orig_category":"Seguridad Social",
    "sg:phone":"+34 969 26 72 20",
    "sg:postcode":"16196",
    "sg:province":"Cuenca",
    "wof:name":"Ayuntamiento De Villar De Olalla-casa Tutelada",
    "wof:placetype":"venue"
},
  "geometry": {"coordinates":[-2.2591607571,40.045589447],"type":"Point"}
}