{
  "type": "Feature",
  "properties": {
    "iso:country":"ES",
    "sg:address":"Plaz Mercado, 4",
    "sg:city":"Huerta Valdecarabanos",
    "sg:orig_category":"Producci\u00d3n, Venta De Productos De Agricultura Biol\u00d3gica",
    "sg:phone":"+34 925 12 91 06",
    "sg:postcode":"45750",
    "sg:province":"Toledo",
    "wof:name":"Aniceto Fernandez Y Asociados S.l.",
    "wof:placetype":"venue"
},
  "geometry": {"coordinates":[-3.6120996475,39.8645362854],"type":"Point"}
}