{
  "type": "Feature",
  "properties": {
    "iso:country":"ES",
    "sg:address":"Carrer de Folgueroles, 34",
    "sg:city":"Barcelona",
    "sg:orig_category":"Electrodom\u00c9sticos (fabricaci\u00d3n, Al Por Mayor)",
    "sg:phone":"+34 934 17 36 98",
    "sg:postcode":"08022",
    "sg:province":"Barcelona",
    "wof:name":"Soler Gamero Alejandro",
    "wof:placetype":"venue"
},
  "geometry": {"coordinates":[2.1367509365,41.407535553],"type":"Point"}
}