{
  "type": "Feature",
  "properties": {
    "addr:full":"Ladruga, 8 Ladruga Lugo 27614",
    "addr:housenumber":"8",
    "addr:postcode":"27614",
    "addr:street":"Ladruga",
    "iso:country":"ES",
    "sg:address":"Ladruga, 8",
    "sg:city":"Ladruga",
    "sg:orig_category":"Muebles, Minoristas",
    "sg:phone":"+34 982 53 24 51",
    "sg:postcode":"27614",
    "sg:province":"Lugo",
    "sg:website":"www.mueblesceleiro.com",
    "wof:name":"Muebles Celeiro S.l.",
    "wof:placetype":"venue"
},
  "geometry": {"coordinates":[-7.3574109077,42.8505249023],"type":"Point"}
}