{
  "type": "Feature",
  "properties": {
    "addr:full":"Avda A\u00d1orga De, 17 A\u00d1orga Guip\u00f9zcoa 20009",
    "addr:housenumber":"17",
    "addr:postcode":"20009",
    "addr:street":"Avda An\u0303Orga De;Guipu\u0300Zcoa",
    "iso:country":"ES",
    "sg:address":"Avda A\u00d1orga De, 17",
    "sg:city":"A\u00d1orga",
    "sg:orig_category":"Hielo Artificial (fabricaci\u00d3n, Distribuci\u00d3n)",
    "sg:phone":"+34 943 37 30 52",
    "sg:postcode":"20009",
    "sg:province":"Guip\u00f9zcoa",
    "wof:name":"Helados Y Postres S.a.",
    "wof:placetype":"venue"
},
  "geometry": {"coordinates":[-1.9951775074,43.2911338806],"type":"Point"}
}