{
  "type": "Feature",
  "properties": {
    "iso:country":"ES",
    "sg:address":"Psaj Colon (de), 1",
    "sg:city":"Valdemoro",
    "sg:orig_category":"Juegos Y Juguetes (al Por Menor)",
    "sg:phone":"+34 918 95 18 58",
    "sg:postcode":"28340",
    "sg:province":"Madrid",
    "wof:name":"Rincon Revuelta Maria",
    "wof:placetype":"venue"
},
  "geometry": {"coordinates":[-3.6738090515,40.1909751892],"type":"Point"}
}