{
  "type": "Feature",
  "properties": {
    "addr:full":"Carrer de Lleida, 116 Prat Llobregat Barcelona 08820",
    "addr:housenumber":"116",
    "addr:postcode":"08820",
    "addr:street":"Carrer De Lleida;Llobregat",
    "iso:country":"ES",
    "sg:address":"Carrer de Lleida, 116",
    "sg:city":"Prat Llobregat",
    "sg:orig_category":"Zapatos (al Por Menor)",
    "sg:phone":"+34 934 78 60 68",
    "sg:postcode":"08820",
    "sg:province":"Barcelona",
    "wof:name":"Vega Pitarch Francisco Javier",
    "wof:placetype":"venue"
},
  "geometry": {"coordinates":[2.0982420444,41.3232917786],"type":"Point"}
}