{
  "type": "Feature",
  "properties": {
    "iso:country":"ES",
    "sg:address":"Carrer de Santa Maria, 1",
    "sg:city":"Santa Perpetua De Mogoda",
    "sg:orig_category":"Molduras, Junquillos, Listones Y Molduras Perforadas",
    "sg:phone":"+34 935 60 03 01",
    "sg:postcode":"08130",
    "sg:province":"Barcelona",
    "wof:name":"Figueras Termens Juan",
    "wof:placetype":"venue"
},
  "geometry": {"coordinates":[2.1798560619,41.5345649719],"type":"Point"}
}