{
  "type": "Feature",
  "properties": {
    "addr:full":"Av Alcudia, 30 Inca Islas Baleares 07300",
    "addr:housenumber":"30",
    "addr:postcode":"07300",
    "addr:street":"Av Alcudia",
    "iso:country":"ES",
    "sg:address":"Av Alcudia, 30",
    "sg:city":"Inca",
    "sg:orig_category":"Peluquer\u00cdas, Peluquer\u00cda Mixta",
    "sg:phone":"+34 971 50 26 95",
    "sg:postcode":"07300",
    "sg:province":"Islas Baleares",
    "wof:name":"Amer Vicens Maria",
    "wof:placetype":"venue"
},
  "geometry": {"coordinates":[2.9147818089,39.7229728699],"type":"Point"}
}