{
  "type": "Feature",
  "properties": {
    "iso:country":"ES",
    "sg:address":"Calle de Temprado, 15",
    "sg:city":"Teruel",
    "sg:orig_category":"Conservatorios",
    "sg:phone":"+34 978 61 75 20",
    "sg:postcode":"44001",
    "sg:province":"Teruel",
    "wof:name":"Conservatorio Profesional De Musica D. G. A. Teruel",
    "wof:placetype":"venue"
},
  "geometry": {"coordinates":[-1.1087629795,40.344127655],"type":"Point"}
}