{
  "type": "Feature",
  "properties": {
    "addr:full":"Butiplaya, 7 Mijas Costa M\u00e1laga 29649",
    "addr:housenumber":"7",
    "addr:postcode":"29649",
    "addr:street":"Butiplaya",
    "iso:country":"ES",
    "sg:address":"Butiplaya, 7",
    "sg:city":"Mijas Costa",
    "sg:orig_category":"Mec\u00c1nico Del Autom\u00d3vil",
    "sg:phone":"+34 952 49 39 97",
    "sg:postcode":"29649",
    "sg:province":"M\u00e1laga",
    "wof:name":"Auto Quick 24h S.l.",
    "wof:placetype":"venue"
},
  "geometry": {"coordinates":[-4.6411604881,36.5099143982],"type":"Point"}
}