{
  "type": "Feature",
  "properties": {
    "iso:country":"ES",
    "sg:address":"Ctra. De Alhama, 30",
    "sg:city":"Churriana Vega",
    "sg:orig_category":"Mec\u00c1nico Del Autom\u00d3vil",
    "sg:phone":"+34 958 55 17 42",
    "sg:postcode":"18194",
    "sg:province":"Granada",
    "wof:name":"Morata Ligero Jose Manuel",
    "wof:placetype":"venue"
},
  "geometry": {"coordinates":[-3.6773679256,37.1503562927],"type":"Point"}
}