{
  "type": "Feature",
  "properties": {
    "addr:full":"Cmno Casa De La Vega, 29 Burgos Burgos 09007",
    "addr:housenumber":"29",
    "addr:postcode":"09007",
    "addr:street":"Cmno Casa De La Vega",
    "iso:country":"ES",
    "sg:address":"Cmno Casa De La Vega, 29",
    "sg:city":"Burgos",
    "sg:orig_category":"Carnicer\u00cdas, Carnicer\u00cdas",
    "sg:phone":"+34 947 23 16 68",
    "sg:postcode":"09007",
    "sg:province":"Burgos",
    "wof:name":"Industrias Alimentarias Gonzalez Garcia S.l.",
    "wof:placetype":"venue"
},
  "geometry": {"coordinates":[-3.669904232,42.3569869995],"type":"Point"}
}