{
  "type": "Feature",
  "properties": {
    "addr:full":"Avda Caldas (das), 9 Ourense Ourense 32001",
    "addr:postcode":"32001",
    "addr:street":"Avda Caldas Das",
    "iso:country":"ES",
    "sg:address":"Avda Caldas (das), 9",
    "sg:city":"Ourense",
    "sg:orig_category":"Cajas De Ahorro",
    "sg:phone":"+34 988 21 73 28",
    "sg:postcode":"32001",
    "sg:province":"Ourense",
    "wof:name":"Caixa D'estalvis I Pensions De Barcelona",
    "wof:placetype":"venue"
},
  "geometry": {"coordinates":[-7.8691821098,42.3471755981],"type":"Point"}
}