{
  "type": "Feature",
  "properties": {
    "iso:country":"ES",
    "sg:address":"Calle de Gil Albert, 2",
    "sg:city":"Almeria",
    "sg:orig_category":"Fabricaci\u00d3n, Venta De Cuadros, Accesorios Para Enmarcar",
    "sg:phone":"+34 950 25 41 61",
    "sg:postcode":"04008",
    "sg:province":"Almer\u00eda",
    "wof:name":"Garcia Valverde Juan Jose",
    "wof:placetype":"venue"
},
  "geometry": {"coordinates":[-2.4588580132,36.8517837524],"type":"Point"}
}