{
  "type": "Feature",
  "properties": {
    "iso:country":"ES",
    "sg:address":"Carrer de Mare De Deu Dels Angels, 40",
    "sg:city":"Santa Coloma De Gramenet",
    "sg:orig_category":"Barnizadores",
    "sg:phone":"+34 933 85 95 53",
    "sg:postcode":"08921",
    "sg:province":"Barcelona",
    "wof:name":"Ruiz Pe\u00f1a Pascual",
    "wof:placetype":"venue"
},
  "geometry": {"coordinates":[2.201695919,41.4521217346],"type":"Point"}
}