{
  "type": "Feature",
  "properties": {
    "iso:country":"ES",
    "sg:address":"Ptda Fredats, 2",
    "sg:city":"Denia",
    "sg:classifiers":[
        {
            "category":"Taxi",
            "type":"Transportation"
        }
    ],
    "sg:phone":"+34 965 78 10 11",
    "sg:postcode":"03700",
    "sg:province":"Alicante",
    "wof:name":"Agrupacion Radio Taxi Denia",
    "wof:placetype":"venue"
},
  "geometry": {"coordinates":[0.0840215012,38.8309745789],"type":"Point"}
}