{
  "type": "Feature",
  "properties": {
    "addr:full":"Calle de Melendez Valdes, 9 Badajoz Badajoz 06002",
    "addr:housenumber":"9",
    "addr:postcode":"06002",
    "addr:street":"Calle De Melendez Valdes",
    "iso:country":"ES",
    "sg:address":"Calle de Melendez Valdes, 9",
    "sg:city":"Badajoz",
    "sg:orig_category":"Molduras, Junquillos, Listones Y Molduras Perforadas",
    "sg:phone":"+34 924 22 09 13",
    "sg:postcode":"06002",
    "sg:province":"Badajoz",
    "wof:name":"Puentes Maestre Ana Isabel",
    "wof:placetype":"venue"
},
  "geometry": {"coordinates":[-6.9707913399,38.8787193298],"type":"Point"}
}