{
  "type": "Feature",
  "properties": {
    "addr:full":"Calle de Salazar, 5 Orotava Santa Cruz De Tenerife 38300",
    "addr:housenumber":"5",
    "addr:postcode":"38300",
    "addr:street":"Calle De Salazar",
    "iso:country":"ES",
    "sg:address":"Calle de Salazar, 5",
    "sg:city":"Orotava",
    "sg:orig_category":"Obras Y Organismos Sociales",
    "sg:phone":"+34 922 33 18 94",
    "sg:postcode":"38300",
    "sg:province":"Santa Cruz De Tenerife",
    "wof:name":"Hermanas De La Compa\u00d1ia De La Cruz",
    "wof:placetype":"venue"
},
  "geometry": {"coordinates":[-16.5258655548,28.3863925934],"type":"Point"}
}