{
  "type": "Feature",
  "properties": {
    "iso:country":"ES",
    "sg:address":"Calle de Alta, 7",
    "sg:city":"Puebla Alfinden",
    "sg:orig_category":"Carnicer\u00cdas, Carnicer\u00cdas",
    "sg:phone":"+34 976 10 71 39",
    "sg:postcode":"50171",
    "sg:province":"Zaragoza",
    "wof:name":"Tejero Asin Maria Luisa",
    "wof:placetype":"venue"
},
  "geometry": {"coordinates":[-0.7505819201,41.6324768066],"type":"Point"}
}