{
  "type": "Feature",
  "properties": {
    "addr:full":"Pase Palmeras Las, 7 Huelva Huelva 21002",
    "addr:postcode":"21002",
    "addr:street":"Las",
    "iso:country":"ES",
    "sg:address":"Pase Palmeras Las, 7",
    "sg:city":"Huelva",
    "sg:orig_category":"Fabricaci\u00d3n, Distribuci\u00d3n De Material Para La Climatizaci\u00d3n, Aireaci\u00d3n Y Ventilaci\u00d3n",
    "sg:phone":"+34 959 26 20 28",
    "sg:postcode":"21002",
    "sg:province":"Huelva",
    "wof:name":"Hidracor S.l.",
    "wof:placetype":"venue"
},
  "geometry": {"coordinates":[-6.9544529915,37.2631263733],"type":"Point"}
}