{
  "type": "Feature",
  "properties": {
    "addr:full":"Calle de Jose Mardones, 5 Vitoria-gasteiz \u00c1lava 01003",
    "addr:housenumber":"5",
    "addr:postcode":"01003",
    "addr:street":"Calle De Jose Mardones",
    "iso:country":"ES",
    "sg:address":"Calle de Jose Mardones, 5",
    "sg:city":"Vitoria-gasteiz",
    "sg:orig_category":"Institutos De Belleza",
    "sg:phone":"+34 945 27 69 83",
    "sg:postcode":"01003",
    "sg:province":"\u00c1lava",
    "wof:name":"Salon Saruh S.c.",
    "wof:placetype":"venue"
},
  "geometry": {"coordinates":[-2.6633310318,42.845375061],"type":"Point"}
}