{
  "type": "Feature",
  "properties": {
    "addr:full":"Calle de Vitoria, 171 Burgos Burgos 09007",
    "addr:housenumber":"171",
    "addr:postcode":"09007",
    "addr:street":"Calle De Vitoria",
    "iso:country":"ES",
    "sg:address":"Calle de Vitoria, 171",
    "sg:city":"Burgos",
    "sg:orig_category":"Agencias Y Agentes Comerciales, Representantes",
    "sg:phone":"+34 947 22 44 32",
    "sg:postcode":"09007",
    "sg:province":"Burgos",
    "wof:name":"Tamayo Negrete Gregorio",
    "wof:placetype":"venue"
},
  "geometry": {"coordinates":[-3.6665949821,42.3542556763],"type":"Point"}
}