{
  "type": "Feature",
  "properties": {
    "iso:country":"ES",
    "sg:address":"Calle de Tridente, 10",
    "sg:city":"Alacant",
    "sg:orig_category":"Carnes De Carnicer\u00cda (al Por Mayor)",
    "sg:phone":"+34 965 26 65 94",
    "sg:postcode":"03540",
    "sg:province":"Alicante",
    "wof:name":"Bellido Sarmiento Bonifacio",
    "wof:placetype":"venue"
},
  "geometry": {"coordinates":[-0.4232330024,38.3583869934],"type":"Point"}
}