{
  "type": "Feature",
  "properties": {
    "addr:full":"Calle de General Yag\u00fce, 4 Madrid Madrid 28020",
    "addr:housenumber":"4",
    "addr:postcode":"28020",
    "addr:street":"Calle De General Yaguee",
    "iso:country":"ES",
    "sg:address":"Calle de General Yag\u00fce, 4",
    "sg:city":"Madrid",
    "sg:orig_category":"Confecci\u00d3n De Trajes Para Se\u00d1oras",
    "sg:phone":"+34 915 55 59 33",
    "sg:postcode":"28020",
    "sg:province":"Madrid",
    "wof:name":"Hassan Israel Esther",
    "wof:placetype":"venue"
},
  "geometry": {"coordinates":[-3.6913230419,40.4563331604],"type":"Point"}
}