{
  "type": "Feature",
  "properties": {
    "addr:full":"Calle de Aramis, 17 Madrid Madrid 28011",
    "addr:housenumber":"17",
    "addr:postcode":"madrid;28011",
    "addr:street":"Calle De Aramis",
    "iso:country":"ES",
    "sg:address":"Calle de Aramis, 17",
    "sg:city":"Madrid",
    "sg:orig_category":"Edici\u00d3n, Venta De Partituras Musicales",
    "sg:phone":"+34 914 64 64 83",
    "sg:postcode":"28011",
    "sg:province":"Madrid",
    "wof:name":"Perez Pareja Esther",
    "wof:placetype":"venue"
},
  "geometry": {"coordinates":[-3.7302052975,40.4079093933],"type":"Point"}
}