{
  "type": "Feature",
  "properties": {
    "iso:country":"ES",
    "sg:address":"Rua Ronda Don Bosco, 3",
    "sg:city":"Vigo",
    "sg:orig_category":"Farmacias",
    "sg:phone":"+34 986 43 84 08",
    "sg:postcode":"36202",
    "sg:province":"Pontevedra",
    "wof:name":"Gonzalez Pena Carlos",
    "wof:placetype":"venue"
},
  "geometry": {"coordinates":[-8.7248411179,42.2353019714],"type":"Point"}
}