{
  "type": "Feature",
  "properties": {
    "addr:full":"Avda Madrid, 25 Zaragoza Zaragoza 50004",
    "addr:housenumber":"25",
    "addr:postcode":"50004",
    "addr:street":"Avda Madrid",
    "iso:country":"ES",
    "sg:address":"Avda Madrid, 25",
    "sg:city":"Zaragoza",
    "sg:orig_category":"Muebles Y Accesorios Para Cocinas Y Cuartos De Ba\u00d1o (al Por Menor)",
    "sg:phone":"+34 976 44 75 75",
    "sg:postcode":"50004",
    "sg:province":"Zaragoza",
    "sg:website":"www.dibus.net",
    "wof:name":"Dibus Aragon S.l.",
    "wof:placetype":"venue"
},
  "geometry": {"coordinates":[-0.8952789903,41.6557693481],"type":"Point"}
}