{
  "type": "Feature",
  "properties": {
    "iso:country":"ES",
    "sg:address":"Calle de Tradiciones (de Las), 1",
    "sg:city":"Chiclana De La Frontera",
    "sg:orig_category":"Contenedores (mercanc\u00cdas)",
    "sg:phone":"+34 956 40 83 77",
    "sg:postcode":"11130",
    "sg:province":"C\u00e1diz",
    "wof:name":"Crespo Mota Antonio",
    "wof:placetype":"venue"
},
  "geometry": {"coordinates":[-6.1447038651,36.4212188721],"type":"Point"}
}