{
  "type": "Feature",
  "properties": {
    "addr:full":"Calle de Golgota, 16 Sevilla Sevilla 41007",
    "addr:housenumber":"16",
    "addr:postcode":"41007",
    "addr:street":"Calle De Golgota",
    "iso:country":"ES",
    "sg:address":"Calle de Golgota, 16",
    "sg:city":"Sevilla",
    "sg:orig_category":"Textil",
    "sg:phone":"+34 954 57 70 99",
    "sg:postcode":"41007",
    "sg:province":"Sevilla",
    "wof:name":"El Taller De Costura Mister Miss S.l.l.",
    "wof:placetype":"venue"
},
  "geometry": {"coordinates":[-5.9697751999,37.3913154602],"type":"Point"}
}