{
  "type": "Feature",
  "properties": {
    "iso:country":"ES",
    "sg:address":"Carrer de Mossen Jacint Verdaguer, 90",
    "sg:city":"Cornella Llobregat",
    "sg:orig_category":"Molduras, Junquillos, Listones Y Molduras Perforadas",
    "sg:phone":"+34 934 74 30 13",
    "sg:postcode":"08940",
    "sg:province":"Barcelona",
    "wof:name":"Guijo Mateos Francisco Javier",
    "wof:placetype":"venue"
},
  "geometry": {"coordinates":[2.0746428967,41.3536109924],"type":"Point"}
}