{
  "type": "Feature",
  "properties": {
    "iso:country":"ES",
    "sg:address":"Calle de Francisco A\u00d1on, 40",
    "sg:city":"Coru\u00d1a",
    "sg:orig_category":"Institutos De Belleza",
    "sg:phone":"+34 981 27 88 60",
    "sg:postcode":"15010",
    "sg:province":"La Coru\u00f1a",
    "wof:name":"Perez Deben Monica",
    "wof:placetype":"venue"
},
  "geometry": {"coordinates":[-8.4189767838,43.3645095825],"type":"Point"}
}