{
  "type": "Feature",
  "properties": {
    "addr:full":"Av Paral.lel, 171 Barcelona Barcelona 08004",
    "addr:housenumber":"171",
    "addr:postcode":"08004",
    "addr:street":"Av Paral.Lel",
    "iso:country":"ES",
    "sg:address":"Av Paral.lel, 171",
    "sg:city":"Barcelona",
    "sg:orig_category":"Marketing Directo",
    "sg:phone":"+34 933 25 86 32",
    "sg:postcode":"08004",
    "sg:province":"Barcelona",
    "sg:website":"www.editermedical.com",
    "wof:name":"Editermed S.l",
    "wof:placetype":"venue"
},
  "geometry": {"coordinates":[2.1555399895,41.3749885559],"type":"Point"}
}