{
  "type": "Feature",
  "properties": {
    "addr:full":"Calle de San Roque, 62 Valencia Valencia 46015",
    "addr:housenumber":"62",
    "addr:postcode":"46015",
    "addr:street":"Calle De San Roque",
    "iso:country":"ES",
    "sg:address":"Calle de San Roque, 62",
    "sg:city":"Valencia",
    "sg:orig_category":"Organismos Y Centros De Vacaciones Y Esparcimiento Para Ni\u00d1os Y Adolescentes",
    "sg:phone":"+34 963 48 06 86",
    "sg:postcode":"46015",
    "sg:province":"Valencia",
    "wof:name":"Pauet Animacion S.l.",
    "wof:placetype":"venue"
},
  "geometry": {"coordinates":[-0.3940860033,39.4905967712],"type":"Point"}
}