{
  "type": "Feature",
  "properties": {
    "addr:full":"N. Monturiol (po Ind Plans D'arau), 5 Pobla Claramunt Barcelona 08787",
    "addr:housenumber":"5",
    "addr:postcode":"08787",
    "addr:street":"N. Monturiol;D'Arau",
    "iso:country":"ES",
    "sg:address":"N. Monturiol (po Ind Plans D'arau), 5",
    "sg:city":"Pobla Claramunt",
    "sg:orig_category":"Barnizadores",
    "sg:phone":"+34 938 08 71 41",
    "sg:postcode":"08787",
    "sg:province":"Barcelona",
    "wof:name":"M. Arrue S. L.",
    "wof:placetype":"venue"
},
  "geometry": {"coordinates":[1.5248030424,41.5180282593],"type":"Point"}
}