{
  "type": "Feature",
  "properties": {
    "iso:country":"ES",
    "sg:address":"Calle de Santiago Ramon Y Cajal, 12",
    "sg:city":"Corrales",
    "sg:orig_category":"Promotores Constructores",
    "sg:phone":"+34 942 83 40 26",
    "sg:postcode":"39400",
    "sg:province":"Cantabria",
    "wof:name":"Tello  Sergio",
    "wof:placetype":"venue"
},
  "geometry": {"coordinates":[-4.0670180321,43.2667922974],"type":"Point"}
}