{
  "type": "Feature",
  "properties": {
    "iso:country":"ES",
    "sg:address":"Calle de San Sebastian, S/n",
    "sg:city":"Jimena",
    "sg:orig_category":"Negocio De Materiales De Construcci\u00d3n",
    "sg:phone":"+34 953 35 71 83",
    "sg:postcode":"23530",
    "sg:province":"Ja\u00e9n",
    "wof:name":"Moreno Ruiz Diego",
    "wof:placetype":"venue"
},
  "geometry": {"coordinates":[-3.4821848869,37.8436355591],"type":"Point"}
}