{
  "type": "Feature",
  "properties": {
    "iso:country":"ES",
    "sg:address":"Ctra Rubi, 72",
    "sg:city":"Mira-sol",
    "sg:orig_category":"Agentes Y Bufetes De Negocio",
    "sg:phone":"+34 936 75 95 84",
    "sg:postcode":"08173",
    "sg:province":"Barcelona",
    "wof:name":"Agrupacion Mutua Del Comercio Y La Industria",
    "wof:placetype":"venue"
},
  "geometry": {"coordinates":[2.0583388805,41.4800453186],"type":"Point"}
}