{
  "type": "Feature",
  "properties": {
    "addr:full":"Calle de Martinez Monta\u00d1es, 2 Santiponce Sevilla 41970",
    "addr:housenumber":"2",
    "addr:postcode":"41970",
    "addr:street":"Calle De Martinez Montan\u0303Es",
    "iso:country":"ES",
    "sg:address":"Calle de Martinez Monta\u00d1es, 2",
    "sg:city":"Santiponce",
    "sg:orig_category":"Asociaciones Y Clubs Deportivos",
    "sg:phone":"+34 955 99 82 74",
    "sg:postcode":"41970",
    "sg:province":"Sevilla",
    "wof:name":"Garcia Burguillos Antonio Ignacio",
    "wof:placetype":"venue"
},
  "geometry": {"coordinates":[-6.0445342064,37.4332427979],"type":"Point"}
}