{
  "type": "Feature",
  "properties": {
    "addr:full":"Avda San Luis Gonzaga, 7 Puerto De Santa Maria C\u00e1diz 11500",
    "addr:housenumber":"7",
    "addr:postcode":"11500",
    "addr:street":"Avda San Luis Gonzaga;Ca\u0301Diz",
    "iso:country":"ES",
    "sg:address":"Avda San Luis Gonzaga, 7",
    "sg:city":"Puerto De Santa Maria",
    "sg:orig_category":"Cl\u00cdnicas M\u00c9dicas",
    "sg:phone":"+34 956 87 04 78",
    "sg:postcode":"11500",
    "sg:province":"C\u00e1diz",
    "wof:name":"Policlinica Luis Gonzaga S.l.",
    "wof:placetype":"venue"
},
  "geometry": {"coordinates":[-6.2351560593,36.5977554321],"type":"Point"}
}