{
  "type": "Feature",
  "properties": {
    "addr:full":"Calle de Ni\u00d1o Jesus, 2 Yecla Murcia 30510",
    "addr:housenumber":"2",
    "addr:postcode":"30510",
    "addr:street":"Calle De Nin\u0303O Jesus",
    "iso:country":"ES",
    "sg:address":"Calle de Ni\u00d1o Jesus, 2",
    "sg:city":"Yecla",
    "sg:orig_category":"Confecci\u00d3n (fabricaci\u00d3n, Al Por Mayor)",
    "sg:phone":"+34 968 75 06 54",
    "sg:postcode":"30510",
    "sg:province":"Murcia",
    "wof:name":"Viuda De Juan Palao Azorin S.l.",
    "wof:placetype":"venue"
},
  "geometry": {"coordinates":[-1.1162548065,38.6128349304],"type":"Point"}
}