{
  "type": "Feature",
  "properties": {
    "addr:full":"Carrer de Badalona, 18 Hospitalet Llobregat Barcelona 08902",
    "addr:housenumber":"18",
    "addr:postcode":"08902",
    "addr:street":"Carrer De Badalona",
    "iso:country":"ES",
    "sg:address":"Carrer de Badalona, 18",
    "sg:city":"Hospitalet Llobregat",
    "sg:orig_category":"Agencias Y Agentes Comerciales, Representantes",
    "sg:phone":"+34 934 22 15 02",
    "sg:postcode":"08902",
    "sg:province":"Barcelona",
    "wof:name":"Garcia Fernandez Jose Luis",
    "wof:placetype":"venue"
},
  "geometry": {"coordinates":[2.1228649616,41.3630638123],"type":"Point"}
}