{
  "type": "Feature",
  "properties": {
    "iso:country":"ES",
    "sg:address":"Calle de Cervantes, 12",
    "sg:city":"Monzon",
    "sg:orig_category":"M\u00c9dicos: Estomatolog\u00cda",
    "sg:phone":"+34 974 40 40 57",
    "sg:postcode":"22400",
    "sg:province":"Huesca",
    "wof:name":"Cucalon Irache Maria Eloisa",
    "wof:placetype":"venue"
},
  "geometry": {"coordinates":[0.196815297,41.9128112793],"type":"Point"}
}