{
  "type": "Feature",
  "properties": {
    "iso:country":"ES",
    "sg:address":"Calle de Abtao, 5",
    "sg:city":"Madrid",
    "sg:orig_category":"Peluquer\u00cdas, Peluquer\u00cda Mixta",
    "sg:phone":"+34 915 01 94 93",
    "sg:postcode":"28007",
    "sg:province":"Madrid",
    "wof:name":"Maria Bordallo S.l.",
    "wof:placetype":"venue"
},
  "geometry": {"coordinates":[-3.6768753529,40.4034347534],"type":"Point"}
}