{
  "type": "Feature",
  "properties": {
    "iso:country":"ES",
    "sg:address":"Av Generalitat, 48",
    "sg:city":"Viladecans",
    "sg:orig_category":"Escayola Y Productos De Escayola (fabricaci\u00d3n, Al Por Mayor)",
    "sg:phone":"+34 936 58 02 98",
    "sg:postcode":"08840",
    "sg:province":"Barcelona",
    "wof:name":"Escayolas Hnos.ayala S.l.",
    "wof:placetype":"venue"
},
  "geometry": {"coordinates":[2.020211935,41.3153533936],"type":"Point"}
}