{
  "type": "Feature",
  "properties": {
    "iso:country":"ES",
    "sg:address":"Rua Doutor Castro, 3",
    "sg:city":"Lugo",
    "sg:orig_category":"Complementos De Vestir (al Por Menor)",
    "sg:phone":"+34 982 24 30 91",
    "sg:postcode":"27001",
    "sg:province":"Lugo",
    "wof:name":"Castro Fernandez Nancy",
    "wof:placetype":"venue"
},
  "geometry": {"coordinates":[-7.5563549995,43.0100784302],"type":"Point"}
}