{
  "type": "Feature",
  "properties": {
    "addr:full":"Calle de General Sueiro, 21 Zaragoza Zaragoza 50008",
    "addr:housenumber":"21",
    "addr:postcode":"50008",
    "addr:street":"Calle De General Sueiro",
    "iso:country":"ES",
    "sg:address":"Calle de General Sueiro, 21",
    "sg:city":"Zaragoza",
    "sg:orig_category":"Fabricaci\u00d3n De Art\u00cdculos Para Papeler\u00cdas",
    "sg:phone":"+34 976 46 84 68",
    "sg:postcode":"50008",
    "sg:province":"Zaragoza",
    "wof:name":"Colortech Publicaciones Digitales D'arago S.a.l.",
    "wof:placetype":"venue"
},
  "geometry": {"coordinates":[-0.8821120262,41.6453514099],"type":"Point"}
}