{
  "type": "Feature",
  "properties": {
    "iso:country":"ES",
    "sg:address":"Pl Joan Fuster, 4",
    "sg:city":"Sollana",
    "sg:orig_category":"Aguas (distribuci\u00d3n, Servicios)",
    "sg:phone":"+34 961 74 10 53",
    "sg:postcode":"46430",
    "sg:province":"Valencia",
    "wof:name":"Empresa General Valenciana Del Agua S.a.",
    "wof:placetype":"venue"
},
  "geometry": {"coordinates":[-0.3837789893,39.2798690796],"type":"Point"}
}