{
  "type": "Feature",
  "properties": {
    "iso:country":"ES",
    "sg:address":"Calle de Coroneles (de Los), S/n",
    "sg:city":"Sese\u00f1a",
    "sg:orig_category":"Art\u00cdculos De Limpieza Y De Cocina (fabricaci\u00d3n, Al Por Mayor)",
    "sg:phone":"+34 918 08 80 09",
    "sg:postcode":"45223",
    "sg:province":"Toledo",
    "wof:name":"Quimitol Centro S.l",
    "wof:placetype":"venue"
},
  "geometry": {"coordinates":[-3.6971199512,40.1031494141],"type":"Point"}
}