{
  "type": "Feature",
  "properties": {
    "iso:country":"ES",
    "sg:address":"Rua Alfredo Bra\u00d1as (de), 11",
    "sg:city":"Santiago De Compostela",
    "sg:orig_category":"Zapater\u00cdas",
    "sg:phone":"+34 981 59 18 96",
    "sg:postcode":"15701",
    "sg:province":"La Coru\u00f1a",
    "wof:name":"Iglesias Junquera Rosa Blanca",
    "wof:placetype":"venue"
},
  "geometry": {"coordinates":[-8.5473737717,42.8746757507],"type":"Point"}
}