{
  "type": "Feature",
  "properties": {
    "iso:country":"ES",
    "sg:address":"Avda Rosalia De Castro, 32",
    "sg:city":"Santa Uxia De Ribeira",
    "sg:orig_category":"Abogados",
    "sg:phone":"+34 981 87 51 59",
    "sg:postcode":"15960",
    "sg:province":"La Coru\u00f1a",
    "wof:name":"Mendez Torres Manuel",
    "wof:placetype":"venue"
},
  "geometry": {"coordinates":[-8.9933519363,42.554359436],"type":"Point"}
}