{
  "type": "Feature",
  "properties": {
    "iso:country":"ES",
    "sg:address":"Rbla Rambla, 9",
    "sg:city":"Sabadell",
    "sg:orig_category":"Molduras, Junquillos, Listones Y Molduras Perforadas",
    "sg:phone":"+34 937 25 01 27",
    "sg:postcode":"08202",
    "sg:province":"Barcelona",
    "wof:name":"Bar Mundial",
    "wof:placetype":"venue"
},
  "geometry": {"coordinates":[2.1095089912,41.5459709167],"type":"Point"}
}