{
  "type": "Feature",
  "properties": {
    "addr:full":"Av Maresme (del), 313 Mataro Barcelona 08301",
    "addr:postcode":"08301",
    "addr:street":"Av;Del 313 Mataro Barcelona",
    "iso:country":"ES",
    "sg:address":"Av Maresme (del), 313",
    "sg:city":"Mataro",
    "sg:orig_category":"Promotores Constructores",
    "sg:phone":"+34 937 96 47 20",
    "sg:postcode":"08301",
    "sg:province":"Barcelona",
    "wof:name":"Chacosa Construccions S. A.",
    "wof:placetype":"venue"
},
  "geometry": {"coordinates":[2.4488580227,41.5365371704],"type":"Point"}
}