{
  "type": "Feature",
  "properties": {
    "iso:country":"ES",
    "sg:address":"Carrer de Tous I Maroto, 10",
    "sg:city":"Palma",
    "sg:orig_category":"Artesan\u00cda",
    "sg:phone":"+34 971 71 86 54",
    "sg:postcode":"07001",
    "sg:province":"Islas Baleares",
    "wof:name":"Esquadra Art S.l.",
    "wof:placetype":"venue"
},
  "geometry": {"coordinates":[2.648015976,39.5699577332],"type":"Point"}
}