{
  "type": "Feature",
  "properties": {
    "addr:full":"Ctra. Toledo-avila, 49 Escalona Toledo 45910",
    "addr:housenumber":"49",
    "addr:postcode":"45910",
    "addr:street":"Ctra. Toledo-Avila",
    "iso:country":"ES",
    "sg:address":"Ctra. Toledo-avila, 49",
    "sg:city":"Escalona",
    "sg:orig_category":"Distribuci\u00d3n De Petr\u00d3leo Y Derivados",
    "sg:phone":"+34 925 78 24 35",
    "sg:postcode":"45910",
    "sg:province":"Toledo",
    "wof:name":"Energeticos De La Mancha S.a.",
    "wof:placetype":"venue"
},
  "geometry": {"coordinates":[-4.4054641724,40.1705665588],"type":"Point"}
}