{
  "type": "Feature",
  "properties": {
    "addr:full":"Calle de Bierzo, 19 Salamanca Salamanca 37006",
    "addr:housenumber":"19",
    "addr:postcode":"37006",
    "addr:street":"Calle De Bierzo",
    "iso:country":"ES",
    "sg:address":"Calle de Bierzo, 19",
    "sg:city":"Salamanca",
    "sg:orig_category":"Carnicer\u00cdas, Carnicer\u00cdas",
    "sg:phone":"+34 923 12 18 46",
    "sg:postcode":"37006",
    "sg:province":"Salamanca",
    "wof:name":"Santos De Vega Benjamin",
    "wof:placetype":"venue"
},
  "geometry": {"coordinates":[-5.6652569771,40.980014801],"type":"Point"}
}