{
  "type": "Feature",
  "properties": {
    "iso:country":"ES",
    "sg:address":"Calle de Febo, 11",
    "sg:city":"Valdemoro",
    "sg:orig_category":"Alquiler De V\u00cddeo",
    "sg:phone":"+34 918 09 24 37",
    "sg:postcode":"28340",
    "sg:province":"Madrid",
    "wof:name":"Operacion Tr Al Cubo S.l.",
    "wof:placetype":"venue"
},
  "geometry": {"coordinates":[-3.6866769791,40.1821365356],"type":"Point"}
}