{
  "type": "Feature",
  "properties": {
    "iso:country":"ES",
    "sg:address":"Calle de Pardo, 1",
    "sg:city":"Villanueva Serena",
    "sg:orig_category":"Institutos De Belleza",
    "sg:phone":"+34 924 84 39 53",
    "sg:postcode":"06700",
    "sg:province":"Badajoz",
    "wof:name":"Benitez Cano Raul",
    "wof:placetype":"venue"
},
  "geometry": {"coordinates":[-5.8067979813,38.9745368958],"type":"Point"}
}