{
  "type": "Feature",
  "properties": {
    "iso:country":"ES",
    "sg:address":"Carrer de Urgell, 19",
    "sg:city":"Prat Llobregat",
    "sg:orig_category":"Comercio, Reparaci\u00d3n De Motocicletas, Bicicletas Y Piezas Sueltas",
    "sg:phone":"+34 934 78 52 70",
    "sg:postcode":"08820",
    "sg:province":"Barcelona",
    "wof:name":"Gomez Vilaseca Jordi",
    "wof:placetype":"venue"
},
  "geometry": {"coordinates":[2.0907180309,41.3253479004],"type":"Point"}
}