{
  "type": "Feature",
  "properties": {
    "addr:full":"Avda Benacazon (p I Autopista), 273 Bollullos Mitacion Sevilla 41110",
    "addr:housenumber":"273",
    "addr:postcode":"41110",
    "addr:street":"Avda Benacazon P;Autopista",
    "iso:country":"ES",
    "sg:address":"Avda Benacazon (p I Autopista), 273",
    "sg:city":"Bollullos Mitacion",
    "sg:orig_category":"Bibliotecas, Mediatecas",
    "sg:phone":"+34 954 99 94 64",
    "sg:postcode":"41110",
    "sg:province":"Sevilla",
    "sg:website":"www.ironmountain.es",
    "wof:name":"Iron Mountain Espa\u00f1a S. A.",
    "wof:placetype":"venue"
},
  "geometry": {"coordinates":[-6.1373138428,37.3355293274],"type":"Point"}
}