{
  "type": "Feature",
  "properties": {
    "iso:country":"ES",
    "sg:address":"Calle de Totana, 8",
    "sg:city":"Librilla",
    "sg:orig_category":"Cristaler\u00cdas",
    "sg:phone":"+34 968 65 91 54",
    "sg:postcode":"30892",
    "sg:province":"Murcia",
    "wof:name":"Martinez Pagan Jose",
    "wof:placetype":"venue"
},
  "geometry": {"coordinates":[-1.3568290472,37.8844490051],"type":"Point"}
}