{
  "type": "Feature",
  "properties": {
    "iso:country":"ES",
    "sg:address":"Ctra N-seiscientos Treinta(p I Casar De Caceres), Km. 0212,0",
    "sg:city":"Casar Caceres",
    "sg:orig_category":"Fabricaci\u00d3n De Enlosados, Soler\u00cdas",
    "sg:phone":"+34 927 29 03 74",
    "sg:postcode":"10190",
    "sg:province":"C\u00e1ceres",
    "wof:name":"Ceramicas Gaya Sa",
    "wof:placetype":"venue"
},
  "geometry": {"coordinates":[-6.4156990051,39.5572166443],"type":"Point"}
}