{
  "type": "Feature",
  "properties": {
    "iso:country":"ES",
    "sg:address":"Calle de Patio Del Casta\u00d1o, 1",
    "sg:city":"Palencia",
    "sg:orig_category":"M\u00c9dicos: Gastroenterolog\u00cda Y Hepatolog\u00cda (aparato Digestivo)",
    "sg:phone":"+34 979 74 09 35",
    "sg:postcode":"34001",
    "sg:province":"Palencia",
    "wof:name":"Alonso Del Campo Eladio",
    "wof:placetype":"venue"
},
  "geometry": {"coordinates":[-4.5338630676,42.0106811523],"type":"Point"}
}