{
  "type": "Feature",
  "properties": {
    "addr:full":"Ctra Cardedeu, Km. 0001,5 Corro D'avall Barcelona 08520",
    "addr:postcode":"08520",
    "addr:street":"Ctra Cardedeu Km. 0001,5;D'Avall Barcelona",
    "iso:country":"ES",
    "sg:address":"Ctra Cardedeu, Km. 0001,5",
    "sg:city":"Corro D'avall",
    "sg:orig_category":"Muebles, Minoristas",
    "sg:phone":"+34 938 49 37 66",
    "sg:postcode":"08520",
    "sg:province":"Barcelona",
    "sg:website":"www.merkamueble.com",
    "wof:name":"Ortega Muebles S.a.",
    "wof:placetype":"venue"
},
  "geometry": {"coordinates":[2.2953824997,41.6182250977],"type":"Point"}
}