{
  "type": "Feature",
  "properties": {
    "addr:full":"Avenida Poligono, S/n Ferrol La Coru\u00f1a 15404",
    "addr:postcode":"15404",
    "addr:street":"Avenida Poligono S / N;La Corun\u0303A",
    "iso:country":"ES",
    "sg:address":"Avenida Poligono, S/n",
    "sg:city":"Ferrol",
    "sg:orig_category":"Comercio De Piezas De Recambio Y De Accesorios De Veh\u00cdculos, Veh\u00cdculos Industriales",
    "sg:phone":"+34 981 32 50 51",
    "sg:postcode":"15404",
    "sg:province":"La Coru\u00f1a",
    "wof:name":"Auto Recambios Torreiro S.l.",
    "wof:placetype":"venue"
},
  "geometry": {"coordinates":[-8.2273387909,43.4868507385],"type":"Point"}
}