{
  "type": "Feature",
  "properties": {
    "addr:full":"Plaza Maestro Selma, 8 Burriana Castell\u00f3n 12530",
    "addr:postcode":"12530",
    "addr:street":"Castello\u0301N",
    "iso:country":"ES",
    "sg:address":"Plaza Maestro Selma, 8",
    "sg:city":"Burriana",
    "sg:orig_category":"M\u00c9dicos: Cirug\u00cda Ortop\u00c9dica Y Traumatolog\u00cda",
    "sg:phone":"+34 964 51 23 85",
    "sg:postcode":"12530",
    "sg:province":"Castell\u00f3n",
    "wof:name":"Guinot Feliu Serafin",
    "wof:placetype":"venue"
},
  "geometry": {"coordinates":[-0.0852660015,39.8894195557],"type":"Point"}
}