{
  "type": "Feature",
  "properties": {
    "addr:full":"Carrer de Lepant, 173 Barcelona Barcelona 08013",
    "addr:housenumber":"173",
    "addr:postcode":"08013",
    "addr:street":"Carrer De Lepant",
    "iso:country":"ES",
    "sg:address":"Carrer de Lepant, 173",
    "sg:city":"Barcelona",
    "sg:orig_category":"Asesor\u00cda Sobre Comunicaci\u00d3n De Empresas",
    "sg:phone":"+34 932 46 34 08",
    "sg:postcode":"08013",
    "sg:province":"Barcelona",
    "wof:name":"A.r.l. Consultores Asesores S.l.",
    "wof:placetype":"venue"
},
  "geometry": {"coordinates":[2.1827902794,41.3997955322],"type":"Point"}
}