{
  "type": "Feature",
  "properties": {
    "iso:country":"ES",
    "sg:address":"Calle de Clemente Jordan, 13",
    "sg:city":"Puente De Arucas",
    "sg:orig_category":"Agencias Y Agentes Comerciales, Representantes",
    "sg:phone":"+34 928 60 23 35",
    "sg:postcode":"35400",
    "sg:province":"Las Palmas",
    "wof:name":"Guerra Jimenez Miriam",
    "wof:placetype":"venue"
},
  "geometry": {"coordinates":[-15.5177078247,28.1138076782],"type":"Point"}
}