{
  "type": "Feature",
  "properties": {
    "addr:full":"Avda Real De Madrid, 18 Valencia Valencia 46017",
    "addr:housenumber":"18",
    "addr:postcode":"46017",
    "addr:street":"Avda Real De Madrid",
    "iso:country":"ES",
    "sg:address":"Avda Real De Madrid, 18",
    "sg:city":"Valencia",
    "sg:orig_category":"Peluqueros: De Se\u00d1oras",
    "sg:phone":"+34 963 75 66 40",
    "sg:postcode":"46017",
    "sg:province":"Valencia",
    "wof:name":"Castillo Sevilla Jaime",
    "wof:placetype":"venue"
},
  "geometry": {"coordinates":[-0.3907139897,39.435295105],"type":"Point"}
}