{
  "type": "Feature",
  "properties": {
    "iso:country":"ES",
    "sg:address":"Calle de Carcaba, S/n",
    "sg:city":"Saelices Mayorga",
    "sg:orig_category":"Agricultura: Abastecimiento Y Cosechado (negocio)",
    "sg:phone":"+34 983 78 51 32",
    "sg:postcode":"47689",
    "sg:province":"Valladolid",
    "wof:name":"Redondo Del Amo Tomas",
    "wof:placetype":"venue"
},
  "geometry": {"coordinates":[-5.2070198059,42.2111206055],"type":"Point"}
}