{
  "type": "Feature",
  "properties": {
    "iso:country":"ES",
    "sg:address":"Carrer de Joan Prim, 130",
    "sg:city":"Granollers",
    "sg:orig_category":"Librer\u00cdas",
    "sg:phone":"+34 938 46 75 90",
    "sg:postcode":"08402",
    "sg:province":"Barcelona",
    "wof:name":"Molins Viaplana Marina",
    "wof:placetype":"venue"
},
  "geometry": {"coordinates":[2.2904109955,41.6129341125],"type":"Point"}
}