{
  "type": "Feature",
  "properties": {
    "iso:country":"ES",
    "sg:address":"Poli Industrial Calle de A, S/n",
    "sg:city":"Fernan Nu\u00e7ez",
    "sg:orig_category":"Carnicer\u00cdas, Carnicer\u00cdas",
    "sg:phone":"+34 957 38 01 54",
    "sg:postcode":"14520",
    "sg:province":"C\u00f3rdoba",
    "wof:name":"Maisal Alimentacion Sl",
    "wof:placetype":"venue"
},
  "geometry": {"coordinates":[-4.7239189148,37.6722068787],"type":"Point"}
}