{
  "type": "Feature",
  "properties": {
    "addr:full":"Carrer de Consell De Cent, 230 Barcelona Barcelona 08011",
    "addr:housenumber":"230",
    "addr:postcode":"08011",
    "addr:street":"Carrer De Consell De Cent",
    "iso:country":"ES",
    "sg:address":"Carrer de Consell De Cent, 230",
    "sg:city":"Barcelona",
    "sg:orig_category":"Goma: Productos De Consumo, De Hogar, Higi\u00c9nicos (fabricaci\u00d3n)",
    "sg:phone":"+34 934 53 88 36",
    "sg:postcode":"08011",
    "sg:province":"Barcelona",
    "wof:name":"Bernal Duran Simona",
    "wof:placetype":"venue"
},
  "geometry": {"coordinates":[2.1595098972,41.3862571716],"type":"Point"}
}