{
  "type": "Feature",
  "properties": {
    "addr:full":"Avda Segovia, 3 Hontoria Segovia 40195",
    "addr:housenumber":"3",
    "addr:postcode":"40195",
    "addr:street":"Avda Segovia",
    "iso:country":"ES",
    "sg:address":"Avda Segovia, 3",
    "sg:city":"Hontoria",
    "sg:orig_category":"M\u00c1rmoles, Granitos Y Piedras Naturales",
    "sg:phone":"+34 921 43 83 91",
    "sg:postcode":"40195",
    "sg:province":"Segovia",
    "wof:name":"Marmoles Cerezo S.a.",
    "wof:placetype":"venue"
},
  "geometry": {"coordinates":[-4.1085691452,40.9115142822],"type":"Point"}
}