{
  "type": "Feature",
  "properties": {
    "iso:country":"ES",
    "sg:address":"Carrer de Verges Pauli (de), 27",
    "sg:city":"Tortosa",
    "sg:orig_category":"Electricidad: Instaladores",
    "sg:phone":"+34 977 44 81 57",
    "sg:postcode":"43500",
    "sg:province":"Tarragona",
    "wof:name":"Euro Tecnics Electronica S.l.",
    "wof:placetype":"venue"
},
  "geometry": {"coordinates":[0.5199859738,40.8045768738],"type":"Point"}
}