{
  "type": "Feature",
  "properties": {
    "iso:country":"ES",
    "sg:address":"Errekarte Kalea, 5",
    "sg:city":"Beasain",
    "sg:orig_category":"Empresas De Desmonte",
    "sg:phone":"+34 943 88 41 51",
    "sg:postcode":"20200",
    "sg:province":"Guip\u00f9zcoa",
    "wof:name":"Garmendia Iriarte Jose Luis",
    "wof:placetype":"venue"
},
  "geometry": {"coordinates":[-2.2131335735,43.0476531982],"type":"Point"}
}