{
  "type": "Feature",
  "properties": {
    "iso:country":"ES",
    "sg:address":"Calle de Atarazanas, 7",
    "sg:city":"Malaga",
    "sg:orig_category":"Asesor\u00cda Fiscal Y Jur\u00cddica",
    "sg:phone":"+34 952 21 91 20",
    "sg:postcode":"29005",
    "sg:province":"M\u00e1laga",
    "wof:name":"Atarazanas V & M Asesores Consultores S.l.",
    "wof:placetype":"venue"
},
  "geometry": {"coordinates":[-4.4235816002,36.7182540894],"type":"Point"}
}