{
  "type": "Feature",
  "properties": {
    "addr:full":"Carrer de Baygual, 2 Sabadell Barcelona 08204",
    "addr:housenumber":"2",
    "addr:postcode":"08204",
    "addr:street":"Carrer De Baygual",
    "iso:country":"ES",
    "sg:address":"Carrer de Baygual, 2",
    "sg:city":"Sabadell",
    "sg:orig_category":"Centros De Educaci\u00d3n Especial",
    "sg:phone":"+34 937 10 56 94",
    "sg:postcode":"08204",
    "sg:province":"Barcelona",
    "wof:name":"Ceip La Romanica",
    "wof:placetype":"venue"
},
  "geometry": {"coordinates":[2.125412941,41.5278282166],"type":"Point"}
}