{
  "type": "Feature",
  "properties": {
    "addr:full":"Plaz Espa\u00d1a, S/n Rozas De Madrid Madrid 28230",
    "addr:housenumber":"s",
    "addr:postcode":"28230",
    "addr:street":"Plaz Espan\u0303A;/ N Rozas",
    "iso:country":"ES",
    "sg:address":"Plaz Espa\u00d1a, S/n",
    "sg:city":"Rozas De Madrid",
    "sg:orig_category":"M\u00c9dicos: Estomatolog\u00cda",
    "sg:phone":"+34 916 36 08 61",
    "sg:postcode":"28230",
    "sg:province":"Madrid",
    "wof:name":"Ruiz Desachy Alejandra Teresita",
    "wof:placetype":"venue"
},
  "geometry": {"coordinates":[-3.8913800716,40.5247497559],"type":"Point"}
}