{
  "type": "Feature",
  "properties": {
    "addr:full":"Rua Gondomar, 5 Gaifar Pontevedra 36340",
    "addr:housenumber":"5",
    "addr:postcode":"36340",
    "addr:street":"Rua Gondomar",
    "iso:country":"ES",
    "sg:address":"Rua Gondomar, 5",
    "sg:city":"Gaifar",
    "sg:orig_category":"Controles De Edificaci\u00d3n (construcci\u00d3n, Seguridad)",
    "sg:phone":"+34 986 36 80 85",
    "sg:postcode":"36340",
    "sg:province":"Pontevedra",
    "wof:name":"Promociones Valentin Veiga S.l.",
    "wof:placetype":"venue"
},
  "geometry": {"coordinates":[-8.8266677856,42.1491203308],"type":"Point"}
}