{
  "type": "Feature",
  "properties": {
    "addr:full":"Calle de Barcelona, 1 Alcala Guadaira Sevilla 41500",
    "addr:housenumber":"1",
    "addr:postcode":"41500",
    "addr:street":"Calle De Barcelona",
    "iso:country":"ES",
    "sg:address":"Calle de Barcelona, 1",
    "sg:city":"Alcala Guadaira",
    "sg:orig_category":"Agencias Y Asesores De Publicidad",
    "sg:phone":"+34 955 68 51 58",
    "sg:postcode":"41500",
    "sg:province":"Sevilla",
    "wof:name":"Pe\u00f1a Blanco Francisco Javier",
    "wof:placetype":"venue"
},
  "geometry": {"coordinates":[-5.839381218,37.3339576721],"type":"Point"}
}