{
  "type": "Feature",
  "properties": {
    "addr:full":"Calle de Fernandez De La Hoz, 61 Madrid Madrid 28003",
    "addr:housenumber":"61",
    "addr:postcode":"madrid;28003",
    "addr:street":"Calle De Fernandez De La Hoz",
    "iso:country":"ES",
    "sg:address":"Calle de Fernandez De La Hoz, 61",
    "sg:city":"Madrid",
    "sg:orig_category":"Agencias Y Agentes Comerciales, Representantes",
    "sg:phone":"+34 915 34 00 86",
    "sg:postcode":"28003",
    "sg:province":"Madrid",
    "wof:name":"Gyalui Casado Luz",
    "wof:placetype":"venue"
},
  "geometry": {"coordinates":[-3.694370985,40.4407844543],"type":"Point"}
}