{
  "type": "Feature",
  "properties": {
    "addr:full":"Carrer de Mossen Quinti Mallofre, 40 Barcelona Barcelona 08030",
    "addr:housenumber":"40",
    "addr:postcode":"08030",
    "addr:street":"Carrer De Mossen Quinti Mallofre",
    "iso:country":"ES",
    "sg:address":"Carrer de Mossen Quinti Mallofre, 40",
    "sg:city":"Barcelona",
    "sg:orig_category":"Electricidad: Instaladores",
    "sg:phone":"+34 933 11 38 15",
    "sg:postcode":"08030",
    "sg:province":"Barcelona",
    "wof:name":"Digasa Instalaciones S.l.",
    "wof:placetype":"venue"
},
  "geometry": {"coordinates":[2.1947999001,41.430557251],"type":"Point"}
}