{
  "type": "Feature",
  "properties": {
    "addr:full":"Plaz Constitucion (la), 47 Camponaraya Le\u00f3n 24410",
    "addr:housenumber":"47",
    "addr:postcode":"24410",
    "addr:street":"Constitucion La",
    "iso:country":"ES",
    "sg:address":"Plaz Constitucion (la), 47",
    "sg:city":"Camponaraya",
    "sg:orig_category":"Bancos",
    "sg:phone":"+34 987 46 30 39",
    "sg:postcode":"24410",
    "sg:province":"Le\u00f3n",
    "sg:website":"www.banesto.es",
    "wof:name":"Banco Espa\u00f1ol De Credito S.a.",
    "wof:placetype":"venue"
},
  "geometry": {"coordinates":[-6.6667189598,42.5784492493],"type":"Point"}
}