{
  "type": "Feature",
  "properties": {
    "iso:country":"ES",
    "sg:address":"Calle de Pere Bonfill, 3",
    "sg:city":"Valencia",
    "sg:orig_category":"Pintura, Barniz, Productos Asimilables (fabricaci\u00d3n, Al Por Mayor)",
    "sg:phone":"+34 963 91 82 75",
    "sg:postcode":"46008",
    "sg:province":"Valencia",
    "wof:name":"Mongay S. A.",
    "wof:placetype":"venue"
},
  "geometry": {"coordinates":[-0.384920001,39.4776077271],"type":"Point"}
}