{
  "type": "Feature",
  "properties": {
    "iso:country":"ES",
    "sg:address":"Afueras, S/n",
    "sg:city":"Hervas",
    "sg:orig_category":"Empresas De Hormig\u00d3n, Hormig\u00d3n Armado Y Pretensado",
    "sg:phone":"+34 927 48 12 06",
    "sg:postcode":"10700",
    "sg:province":"C\u00e1ceres",
    "wof:name":"Hergilsan S.l.",
    "wof:placetype":"venue"
},
  "geometry": {"coordinates":[-5.8459339142,40.2736587524],"type":"Point"}
}