{
  "type": "Feature",
  "properties": {
    "iso:country":"ES",
    "sg:address":"Calle de Navacerrada, 10",
    "sg:city":"Segovia",
    "sg:orig_category":"Promotores Constructores",
    "sg:phone":"+34 921 43 26 62",
    "sg:postcode":"40006",
    "sg:province":"Segovia",
    "wof:name":"Mariano Rico S.l.",
    "wof:placetype":"venue"
},
  "geometry": {"coordinates":[-4.1126241684,40.9262619019],"type":"Point"}
}