{
  "type": "Feature",
  "properties": {
    "addr:full":"Carrer de Lleialtat, 11 Esplugues Llobregat Barcelona 08950",
    "addr:housenumber":"11",
    "addr:postcode":"08950",
    "addr:street":"Carrer De Lleialtat",
    "iso:country":"ES",
    "sg:address":"Carrer de Lleialtat, 11",
    "sg:city":"Esplugues Llobregat",
    "sg:orig_category":"Zapatos (al Por Menor)",
    "sg:phone":"+34 933 71 00 25",
    "sg:postcode":"08950",
    "sg:province":"Barcelona",
    "wof:name":"Sucesores De Joaquin Teruel S.l.",
    "wof:placetype":"venue"
},
  "geometry": {"coordinates":[2.092345953,41.3760871887],"type":"Point"}
}