{
  "type": "Feature",
  "properties": {
    "addr:full":"Calle de Azorin, 14 Cabrerizos Salamanca 37193",
    "addr:housenumber":"14",
    "addr:postcode":"37193",
    "addr:street":"Calle De Azorin",
    "iso:country":"ES",
    "sg:address":"Calle de Azorin, 14",
    "sg:city":"Cabrerizos",
    "sg:orig_category":"Pescader\u00cdas (al Por Menor)",
    "sg:phone":"+34 923 20 92 98",
    "sg:postcode":"37193",
    "sg:province":"Salamanca",
    "wof:name":"Pescaderia Cabrerizos S.l.",
    "wof:placetype":"venue"
},
  "geometry": {"coordinates":[-5.6113529205,40.9774475098],"type":"Point"}
}