{
  "type": "Feature",
  "properties": {
    "iso:country":"ES",
    "sg:address":"Carrer de Industria, 2",
    "sg:city":"Santa Perpetua De Mogoda",
    "sg:orig_category":"Herramientas Manuales (fabricaci\u00d3n, Al Por Mayor)",
    "sg:phone":"+34 935 74 71 33",
    "sg:postcode":"08130",
    "sg:province":"Barcelona",
    "wof:name":"Bea Hispania S.a.",
    "wof:placetype":"venue"
},
  "geometry": {"coordinates":[2.1813030243,41.537979126],"type":"Point"}
}