{
  "type": "Feature",
  "properties": {
    "iso:country":"ES",
    "sg:address":"Calle de Juan De Herrera, 62",
    "sg:city":"Puertollano",
    "sg:orig_category":"Mec\u00c1nico Del Autom\u00d3vil",
    "sg:phone":"+34 926 42 69 42",
    "sg:postcode":"13500",
    "sg:province":"Ciudad Real",
    "wof:name":"G Y B Puertomotor S.l.",
    "wof:placetype":"venue"
},
  "geometry": {"coordinates":[-4.0990948677,38.6819725037],"type":"Point"}
}