{
  "type": "Feature",
  "properties": {
    "iso:country":"ES",
    "sg:address":"Calle de Italia, 6",
    "sg:city":"Haro",
    "sg:orig_category":"Servicios Gsm",
    "sg:phone":"+34 941 30 48 50",
    "sg:postcode":"26200",
    "sg:province":"La Rioja",
    "wof:name":"Amatel Telecomunicaciones",
    "wof:placetype":"venue"
},
  "geometry": {"coordinates":[-2.8509144783,42.5752105713],"type":"Point"}
}