{
  "type": "Feature",
  "properties": {
    "iso:country":"ES",
    "sg:address":"Ctra Aljorra, 1",
    "sg:city":"Albujon",
    "sg:orig_category":"Electricidad: Instalaciones Industriales",
    "sg:phone":"+34 968 16 02 79",
    "sg:postcode":"30330",
    "sg:province":"Murcia",
    "wof:name":"Clujisa S.l.",
    "wof:placetype":"venue"
},
  "geometry": {"coordinates":[-1.0485290289,37.7183456421],"type":"Point"}
}