{
  "type": "Feature",
  "properties": {
    "addr:full":"Bo Larrauri, S/n Larrauri-markaida Vizcaya 48100",
    "addr:housenumber":"s / n",
    "addr:postcode":"48100",
    "addr:street":"Larrauri",
    "iso:country":"ES",
    "sg:address":"Bo Larrauri, S/n",
    "sg:city":"Larrauri-markaida",
    "sg:orig_category":"Cr\u00cda De Animales",
    "sg:phone":"+34 946 74 10 18",
    "sg:postcode":"48100",
    "sg:province":"Vizcaya",
    "wof:name":"Lamas Gonzalez Antonio",
    "wof:placetype":"venue"
},
  "geometry": {"coordinates":[-2.8507039547,43.3569412231],"type":"Point"}
}