{
  "type": "Feature",
  "properties": {
    "iso:country":"ES",
    "sg:address":"Calle de Capitan Haya, 30",
    "sg:city":"Madrid",
    "sg:orig_category":"Fabricaci\u00d3n, Importaci\u00d3n, Venta De Material De Telefon\u00cda, Peritelefon\u00cda",
    "sg:phone":"+34 915 56 11 28",
    "sg:postcode":"28020",
    "sg:province":"Madrid",
    "sg:website":"www.dactel.es",
    "wof:name":"B.a.c.negocios S.l.",
    "wof:placetype":"venue"
},
  "geometry": {"coordinates":[-3.6920263767,40.4589157104],"type":"Point"}
}