{
  "type": "Feature",
  "properties": {
    "iso:country":"ES",
    "sg:address":"Calle de Alberto Conti (de), 7",
    "sg:city":"Mostoles",
    "sg:orig_category":"Puertas Y Portales",
    "sg:phone":"+34 916 13 00 89",
    "sg:postcode":"28935",
    "sg:province":"Madrid",
    "wof:name":"A.c.u. S.l. Cerrajeria",
    "wof:placetype":"venue"
},
  "geometry": {"coordinates":[-3.8852014542,40.3271980286],"type":"Point"}
}