{
  "type": "Feature",
  "properties": {
    "iso:country":"ES",
    "sg:address":"Pase Castellana, 123",
    "sg:city":"Madrid",
    "sg:orig_category":"Abogados",
    "sg:phone":"+34 915 55 17 43",
    "sg:postcode":"28046",
    "sg:province":"Madrid",
    "wof:name":"Asesoria De Cobro Y Gestion S.l.",
    "wof:placetype":"venue"
},
  "geometry": {"coordinates":[-3.6905791759,40.4578323364],"type":"Point"}
}