{
  "type": "Feature",
  "properties": {
    "addr:full":"Calle de Cavanilles, 2 Villaviciosa Asturias 33300",
    "addr:housenumber":"2",
    "addr:postcode":"33300",
    "addr:street":"Calle De Cavanilles",
    "iso:country":"ES",
    "sg:address":"Calle de Cavanilles, 2",
    "sg:city":"Villaviciosa",
    "sg:orig_category":"Albergues Sociales",
    "sg:phone":"+34 985 89 15 52",
    "sg:postcode":"33300",
    "sg:province":"Asturias",
    "wof:name":"Promociones Rivero Cueto S. A.",
    "wof:placetype":"venue"
},
  "geometry": {"coordinates":[-5.4515724182,43.5030212402],"type":"Point"}
}