{
  "type": "Feature",
  "properties": {
    "iso:country":"ES",
    "sg:address":"Jos\u00e9 Zorrilla, 3",
    "sg:city":"Quintanilla Onesimo",
    "sg:orig_category":"Venta, Instalaci\u00d3n De Calefacci\u00d3n",
    "sg:phone":"+34 983 68 01 73",
    "sg:postcode":"47350",
    "sg:province":"Valladolid",
    "wof:name":"Garcia White Santiago",
    "wof:placetype":"venue"
},
  "geometry": {"coordinates":[-4.3594341278,41.6268730164],"type":"Point"}
}