{
  "type": "Feature",
  "properties": {
    "addr:full":"Zintaduiko Jarduera Gunea, 9 Zorita De La Loma Vizcaya 48130",
    "addr:housenumber":"9",
    "addr:postcode":"48130",
    "addr:street":"Gunea",
    "iso:country":"ES",
    "sg:address":"Zintaduiko Jarduera Gunea, 9",
    "sg:city":"Zorita De La Loma",
    "sg:orig_category":"Distribuci\u00d3n De Petr\u00d3leo Y Derivados",
    "sg:phone":"+34 946 19 45 80",
    "sg:postcode":"48130",
    "sg:province":"Vizcaya",
    "wof:name":"Urlaster Serbitzuak",
    "wof:placetype":"venue"
},
  "geometry": {"coordinates":[-2.8128499985,43.4266433716],"type":"Point"}
}