{
  "type": "Feature",
  "properties": {
    "addr:full":"Libertad, 68 Algete Madrid 28110",
    "addr:housenumber":"68",
    "addr:postcode":"28110",
    "addr:street":"Libertad",
    "iso:country":"ES",
    "sg:address":"Libertad, 68",
    "sg:city":"Algete",
    "sg:classifiers":[
        {
            "category":"Professional",
            "subcategory":"Management & Consulting",
            "type":"Services"
        }
    ],
    "sg:phone":"+34 916 28 70 86",
    "sg:postcode":"28110",
    "sg:province":"Madrid",
    "sg:tags":[
        "asesor\u00cda",
        "en",
        "marketing"
    ],
    "wof:name":"Marketing & Bussines Tools S.l.",
    "wof:placetype":"venue"
},
  "geometry": {"coordinates":[-3.5391569138,40.6088180542],"type":"Point"}
}