{
  "type": "Feature",
  "properties": {
    "iso:country":"ES",
    "sg:address":"Carr Londres, 2",
    "sg:city":"Badalona",
    "sg:orig_category":"Bordado, Marcado A Medida",
    "sg:phone":"+34 934 60 17 29",
    "sg:postcode":"08914",
    "sg:province":"Barcelona",
    "wof:name":"Cveuropa S.l.",
    "wof:placetype":"venue"
},
  "geometry": {"coordinates":[2.2208299637,41.4419174194],"type":"Point"}
}