{
  "type": "Feature",
  "properties": {
    "addr:full":"Calle de Pedro Bra\u00d1a, S/n Candas Asturias 33430",
    "addr:housenumber":"s / n",
    "addr:postcode":"33430",
    "addr:street":"Calle De Pedro Bran\u0303A",
    "iso:country":"ES",
    "sg:address":"Calle de Pedro Bra\u00d1a, S/n",
    "sg:city":"Candas",
    "sg:orig_category":"Transportes Ferroviarios",
    "sg:phone":"+34 985 88 46 21",
    "sg:postcode":"33430",
    "sg:province":"Asturias",
    "wof:name":"Ferrocarriles Espa\u00f1oles De Via Estrecha",
    "wof:placetype":"venue"
},
  "geometry": {"coordinates":[-5.7678160667,43.5865020752],"type":"Point"}
}