{
  "type": "Feature",
  "properties": {
    "addr:full":"Carrer de Joaquim Mensa, 26 Cervello Barcelona 08758",
    "addr:housenumber":"26",
    "addr:postcode":"08758",
    "addr:street":"Carrer De Joaquim Mensa;Barcelona",
    "iso:country":"ES",
    "sg:address":"Carrer de Joaquim Mensa, 26",
    "sg:city":"Cervello",
    "sg:orig_category":"Caf\u00c9s, Bares, Cervecer\u00cdas",
    "sg:phone":"+34 936 84 18 43",
    "sg:postcode":"08758",
    "sg:province":"Barcelona",
    "wof:name":"Castillo Pons Jose Maria",
    "wof:placetype":"venue"
},
  "geometry": {"coordinates":[1.9522249699,41.394744873],"type":"Point"}
}