{
  "type": "Feature",
  "properties": {
    "iso:country":"ES",
    "sg:address":"Calle de Burriana, 39",
    "sg:city":"Onda",
    "sg:orig_category":"Construcciones Prefabricadas Y Desmontables",
    "sg:phone":"+34 964 60 24 70",
    "sg:postcode":"12200",
    "sg:province":"Castell\u00f3n",
    "wof:name":"Chiva Catalan Joaquin",
    "wof:placetype":"venue"
},
  "geometry": {"coordinates":[-0.2599149942,39.9613685608],"type":"Point"}
}