{
  "type": "Feature",
  "properties": {
    "iso:country":"ES",
    "sg:address":"Calle de Teodoro Iriarte Reinoso, 1",
    "sg:city":"Zaragoza",
    "sg:orig_category":"Plomeros",
    "sg:phone":"+34 976 33 93 67",
    "sg:postcode":"50010",
    "sg:province":"Zaragoza",
    "wof:name":"Olmos Gregorio Angel",
    "wof:placetype":"venue"
},
  "geometry": {"coordinates":[-0.9030119777,41.6551513672],"type":"Point"}
}