{
  "type": "Feature",
  "properties": {
    "iso:country":"ES",
    "sg:address":"Calle de Bravo Murillo, 174",
    "sg:city":"Madrid",
    "sg:orig_category":"Cajas De Ahorro",
    "sg:phone":"+34 915 70 78 77",
    "sg:postcode":"28020",
    "sg:province":"Madrid",
    "wof:name":"Unicaja",
    "wof:placetype":"venue"
},
  "geometry": {"coordinates":[-3.7028501034,40.4537811279],"type":"Point"}
}