{
  "type": "Feature",
  "properties": {
    "addr:full":"Calle de Casualidad, 1 Algar Murcia 30366",
    "addr:housenumber":"1",
    "addr:postcode":"30366",
    "addr:street":"Calle De Casualidad",
    "iso:country":"ES",
    "sg:address":"Calle de Casualidad, 1",
    "sg:city":"Algar",
    "sg:orig_category":"Droguer\u00cdas (al Por Menor)",
    "sg:phone":"+34 968 13 57 78",
    "sg:postcode":"30366",
    "sg:province":"Murcia",
    "wof:name":"Olmo Galian Ana Luisa",
    "wof:placetype":"venue"
},
  "geometry": {"coordinates":[-0.8655878901,37.6448287964],"type":"Point"}
}