{
  "type": "Feature",
  "properties": {
    "addr:full":"Rbla Sant Francesc, 21 Vilafranca Penedes Barcelona 08720",
    "addr:housenumber":"21",
    "addr:postcode":"08720",
    "addr:street":"Rbla Sant Francesc;Penedes Barcelona",
    "iso:country":"ES",
    "sg:address":"Rbla Sant Francesc, 21",
    "sg:city":"Vilafranca Penedes",
    "sg:orig_category":"M\u00c9dicos: Foniatr\u00cda Y Logopedia",
    "sg:phone":"+34 938 18 01 92",
    "sg:postcode":"08720",
    "sg:province":"Barcelona",
    "wof:name":"Psilog Gabinet Logopedic I Psicologic Infantil I Adult S.c.p.",
    "wof:placetype":"venue"
},
  "geometry": {"coordinates":[1.698505044,41.345413208],"type":"Point"}
}