{
  "type": "Feature",
  "properties": {
    "addr:full":"Can Soberano, 59 Premia De Dalt Barcelona 08338",
    "addr:housenumber":"59",
    "addr:postcode":"08338",
    "addr:street":"Barcelona",
    "iso:country":"ES",
    "sg:address":"Can Soberano, 59",
    "sg:city":"Premia De Dalt",
    "sg:orig_category":"Reposter\u00cdas",
    "sg:phone":"+34 937 51 62 10",
    "sg:postcode":"08338",
    "sg:province":"Barcelona",
    "wof:name":"Alcala Bravo Concepcion",
    "wof:placetype":"venue"
},
  "geometry": {"coordinates":[2.3447687626,41.4972000122],"type":"Point"}
}