{
  "type": "Feature",
  "properties": {
    "iso:country":"ES",
    "sg:address":"Calle de La Paz, 28",
    "sg:city":"San Vicente De Barakaldo",
    "sg:orig_category":"Aparatos, Material Y Suministros Para Laboratorios",
    "sg:phone":"+34 944 99 85 80",
    "sg:postcode":"48903",
    "sg:province":"Vizcaya",
    "wof:name":"Redondo Inyesto Jose Ignacio",
    "wof:placetype":"venue"
},
  "geometry": {"coordinates":[-2.988038063,43.2823295593],"type":"Point"}
}