{
  "type": "Feature",
  "properties": {
    "iso:country":"ES",
    "sg:address":"Calle de Figurillas, 11",
    "sg:city":"Cortijo De Maza-el Olivar",
    "sg:orig_category":"Promotores Constructores",
    "sg:phone":"+34 952 62 10 80",
    "sg:postcode":"29140",
    "sg:province":"M\u00e1laga",
    "wof:name":"Narucola S.l.",
    "wof:placetype":"venue"
},
  "geometry": {"coordinates":[-4.4945521355,36.6522789001],"type":"Point"}
}