{
  "type": "Feature",
  "properties": {
    "iso:country":"ES",
    "sg:address":"Calle de Conchas, 7",
    "sg:city":"Miranda Ebro",
    "sg:orig_category":"Molduras, Junquillos, Listones Y Molduras Perforadas",
    "sg:phone":"+34 947 31 39 12",
    "sg:postcode":"09200",
    "sg:province":"Burgos",
    "wof:name":"Roman Martin Simon",
    "wof:placetype":"venue"
},
  "geometry": {"coordinates":[-2.9372775555,42.6883125305],"type":"Point"}
}