{
  "type": "Feature",
  "properties": {
    "iso:country":"ES",
    "sg:address":"Carr Ramon Castejon, 2",
    "sg:city":"Lleida",
    "sg:orig_category":"Deportes Diversos",
    "sg:phone":"+34 973 24 48 60",
    "sg:postcode":"25007",
    "sg:province":"Lleida",
    "wof:name":"Federacion Catalana De Futbol",
    "wof:placetype":"venue"
},
  "geometry": {"coordinates":[0.6318920255,41.6179618835],"type":"Point"}
}