{
  "type": "Feature",
  "properties": {
    "addr:full":"Calle de Sierra De Aralar, 24 Donostia-san Sebastian Guip\u00f9zcoa 20014",
    "addr:housenumber":"24",
    "addr:postcode":"20014",
    "addr:street":"Calle De Sierra De Aralar",
    "iso:country":"ES",
    "sg:address":"Calle de Sierra De Aralar, 24",
    "sg:city":"Donostia-san Sebastian",
    "sg:orig_category":"Arenas, Guijarros Y Granulados",
    "sg:phone":"+34 943 45 89 17",
    "sg:postcode":"20014",
    "sg:province":"Guip\u00f9zcoa",
    "wof:name":"Transportes Y Containers Easo S. A.",
    "wof:placetype":"venue"
},
  "geometry": {"coordinates":[-1.9663710594,43.3128204346],"type":"Point"}
}