{
  "type": "Feature",
  "properties": {
    "iso:country":"ES",
    "sg:address":"Calle de Domingo Ram, 35",
    "sg:city":"Zaragoza",
    "sg:orig_category":"Electricidad: Instaladores",
    "sg:phone":"+34 976 32 89 90",
    "sg:postcode":"50017",
    "sg:province":"Zaragoza",
    "wof:name":"Inelva S.l.",
    "wof:placetype":"venue"
},
  "geometry": {"coordinates":[-0.9049246907,41.6483840942],"type":"Point"}
}