{
  "type": "Feature",
  "properties": {
    "iso:country":"ES",
    "sg:address":"Plaz Sol (del), 7",
    "sg:city":"Alcorcon",
    "sg:orig_category":"Electricidad: Equipos Industriales, Componentes (fabricaci\u00d3n)",
    "sg:phone":"+34 916 41 06 98",
    "sg:postcode":"28922",
    "sg:province":"Madrid",
    "wof:name":"Cm Electrica S.l.",
    "wof:placetype":"venue"
},
  "geometry": {"coordinates":[-3.8242239952,40.3513946533],"type":"Point"}
}