{
  "type": "Feature",
  "properties": {
    "iso:country":"ES",
    "sg:address":"Calle de Moreno Nieto, 53",
    "sg:city":"Campanario",
    "sg:orig_category":"Promotores Constructores",
    "sg:phone":"+34 924 83 12 00",
    "sg:postcode":"06460",
    "sg:province":"Badajoz",
    "wof:name":"Hermanos Gallardo Cascos Y Otro Cdad",
    "wof:placetype":"venue"
},
  "geometry": {"coordinates":[-5.6114091873,38.8667106628],"type":"Point"}
}