{
  "type": "Feature",
  "properties": {
    "addr:full":"Carrer de Nabril Baix, 38 Alforja Tarragona 43365",
    "addr:housenumber":"38",
    "addr:postcode":"43365",
    "addr:street":"Carrer De Nabril Baix",
    "iso:country":"ES",
    "sg:address":"Carrer de Nabril Baix, 38",
    "sg:city":"Alforja",
    "sg:orig_category":"T\u00c9cnicos Veterinarios",
    "sg:phone":"+34 977 81 61 15",
    "sg:postcode":"43365",
    "sg:province":"Tarragona",
    "wof:name":"Yolanda Saludes S.l.",
    "wof:placetype":"venue"
},
  "geometry": {"coordinates":[0.9743210077,41.2102851868],"type":"Point"}
}