{
  "type": "Feature",
  "properties": {
    "iso:country":"ES",
    "sg:address":"Carrer de Trafalgar, 33",
    "sg:city":"Barcelona",
    "sg:orig_category":"Organismos De Reclutamiento",
    "sg:phone":"+34 932 68 39 82",
    "sg:postcode":"08010",
    "sg:province":"Barcelona",
    "sg:website":"www.inter-management.com",
    "wof:name":"Intermanagement Iberica Consulting Sl",
    "wof:placetype":"venue"
},
  "geometry": {"coordinates":[2.1767990589,41.3898429871],"type":"Point"}
}