{
  "type": "Feature",
  "properties": {
    "iso:country":"ES",
    "sg:address":"Avda Portugal, 37",
    "sg:city":"Cadiz",
    "sg:orig_category":"Herboristas (al Por Menor)",
    "sg:phone":"+34 956 25 40 97",
    "sg:postcode":"11008",
    "sg:province":"C\u00e1diz",
    "wof:name":"Ynsadiet S.a.",
    "wof:placetype":"venue"
},
  "geometry": {"coordinates":[-6.2791609764,36.5144386292],"type":"Point"}
}