{
  "type": "Feature",
  "properties": {
    "iso:country":"ES",
    "sg:address":"Carrer de Mestre Chapi, 16",
    "sg:city":"Monovar",
    "sg:orig_category":"Peluqueros: De Se\u00d1oras",
    "sg:phone":"+34 965 47 14 12",
    "sg:postcode":"03640",
    "sg:province":"Alicante",
    "wof:name":"Poveda Mira Inmaculada",
    "wof:placetype":"venue"
},
  "geometry": {"coordinates":[-0.8321849704,38.4380569458],"type":"Point"}
}