{
  "type": "Feature",
  "properties": {
    "iso:country":"ES",
    "sg:address":"G.v. Marques Del Turia, 41",
    "sg:city":"Valencia",
    "sg:orig_category":"Cooperativas Agr\u00cdcolas",
    "sg:phone":"+34 963 50 93 90",
    "sg:postcode":"46005",
    "sg:province":"Valencia",
    "wof:name":"Bancofar S.a.",
    "wof:placetype":"venue"
},
  "geometry": {"coordinates":[-0.3699940145,39.4668273926],"type":"Point"}
}