{
  "type": "Feature",
  "properties": {
    "iso:country":"ES",
    "sg:address":"Calle de San Bartolome, 25",
    "sg:city":"Donostia-san Sebastian",
    "sg:orig_category":"Bares, Piano",
    "sg:phone":"+34 943 47 00 24",
    "sg:postcode":"20007",
    "sg:province":"Guip\u00f9zcoa",
    "wof:name":"Rodriguez Sanchez Ignacio",
    "wof:placetype":"venue"
},
  "geometry": {"coordinates":[-1.9867709875,43.3148269653],"type":"Point"}
}