{
  "type": "Feature",
  "properties": {
    "addr:full":"Calle de Pisuerga, 6 Aranda Duero Burgos 09400",
    "addr:housenumber":"6",
    "addr:postcode":"09400",
    "addr:street":"Calle De Pisuerga",
    "iso:country":"ES",
    "sg:address":"Calle de Pisuerga, 6",
    "sg:city":"Aranda Duero",
    "sg:orig_category":"Iglesia Cat\u00d3lica",
    "sg:phone":"+34 947 50 86 50",
    "sg:postcode":"09400",
    "sg:province":"Burgos",
    "wof:name":"Parroquia De San Jose",
    "wof:placetype":"venue"
},
  "geometry": {"coordinates":[-3.6928389072,41.660030365],"type":"Point"}
}