{
  "type": "Feature",
  "properties": {
    "iso:country":"ES",
    "sg:address":"Calle de Principe De Asturias, S/n",
    "sg:city":"Campo Abajo",
    "sg:orig_category":"Tapicer\u00cdas",
    "sg:phone":"+34 968 75 08 75",
    "sg:postcode":"30510",
    "sg:province":"Murcia",
    "wof:name":"Preparado De La Tapiceria S.l.",
    "wof:placetype":"venue"
},
  "geometry": {"coordinates":[-1.1149940491,38.6145591736],"type":"Point"}
}