{
  "type": "Feature",
  "properties": {
    "iso:country":"ES",
    "sg:address":"Cmno Castralvo, 3",
    "sg:city":"Teruel",
    "sg:orig_category":"Arquitectos",
    "sg:phone":"+34 978 61 77 20",
    "sg:postcode":"44002",
    "sg:province":"Teruel",
    "wof:name":"Lacasa Salas Fernando",
    "wof:placetype":"venue"
},
  "geometry": {"coordinates":[-1.1008909941,40.3329124451],"type":"Point"}
}