{
  "type": "Feature",
  "properties": {
    "iso:country":"ES",
    "sg:address":"Carrer de Maignon, 11",
    "sg:city":"Barcelona",
    "sg:orig_category":"Molduras, Junquillos, Listones Y Molduras Perforadas",
    "sg:phone":"+34 934 15 95 88",
    "sg:postcode":"08024",
    "sg:province":"Barcelona",
    "wof:name":"Monleon Anton Piedad",
    "wof:placetype":"venue"
},
  "geometry": {"coordinates":[2.1506230831,41.4088363647],"type":"Point"}
}