{
  "type": "Feature",
  "properties": {
    "iso:country":"ES",
    "sg:address":"Plaz Arias Gonzalo, 6",
    "sg:city":"Zamora",
    "sg:orig_category":"Oficinas De Turismo, Asociaciones De Iniciativa",
    "sg:phone":"+34 980 53 36 94",
    "sg:postcode":"49001",
    "sg:province":"Zamora",
    "sg:website":"www.ayto-zamora.org",
    "wof:name":"Inzatur S.l.",
    "wof:placetype":"venue"
},
  "geometry": {"coordinates":[-5.7524580956,41.4991836548],"type":"Point"}
}