{
  "type": "Feature",
  "properties": {
    "iso:country":"ES",
    "sg:address":"Avgd Francesc Tarrega, 44",
    "sg:city":"Villarreal",
    "sg:orig_category":"Ingeniero",
    "sg:phone":"+34 964 52 60 60",
    "sg:postcode":"12540",
    "sg:province":"Castell\u00f3n",
    "sg:website":"www.indesgrupo.com",
    "wof:name":"Desarrollo Industrial Aplicado S.l.",
    "wof:placetype":"venue"
},
  "geometry": {"coordinates":[-0.0952939987,39.9453048706],"type":"Point"}
}