{
  "type": "Feature",
  "properties": {
    "iso:country":"ES",
    "sg:address":"Ctra Malpartida Caceres(p I Las Arenas), Km. 0007,0",
    "sg:city":"Malpartida Caceres",
    "sg:orig_category":"Piedra Natural",
    "sg:phone":"+34 927 27 65 50",
    "sg:postcode":"10910",
    "sg:province":"C\u00e1ceres",
    "wof:name":"Trenado Mu\u00f1oz Pedro",
    "wof:placetype":"venue"
},
  "geometry": {"coordinates":[-6.5076742172,39.4432449341],"type":"Point"}
}