{
  "type": "Feature",
  "properties": {
    "iso:country":"ES",
    "sg:address":"Carrer de Serbia, 18",
    "sg:city":"Barcelona",
    "sg:orig_category":"Bisuteros (fabricaci\u00d3n, Al Por Mayor)",
    "sg:phone":"+34 934 50 13 71",
    "sg:postcode":"08041",
    "sg:province":"Barcelona",
    "wof:name":"Comecial Z.r.c. S.a.",
    "wof:placetype":"venue"
},
  "geometry": {"coordinates":[2.1709849834,41.4181861877],"type":"Point"}
}