{
  "type": "Feature",
  "properties": {
    "addr:full":"Calle de Francos, 16 Jerez De La Frontera C\u00e1diz 11403",
    "addr:housenumber":"16",
    "addr:postcode":"11403",
    "addr:street":"Calle De Francos",
    "iso:country":"ES",
    "sg:address":"Calle de Francos, 16",
    "sg:city":"Jerez De La Frontera",
    "sg:orig_category":"M\u00c9dicos: Gastroenterolog\u00cda Y Hepatolog\u00cda (aparato Digestivo)",
    "sg:phone":"+34 956 34 73 05",
    "sg:postcode":"11403",
    "sg:province":"C\u00e1diz",
    "wof:name":"Ruiz-badanelli Marcano Miguel",
    "wof:placetype":"venue"
},
  "geometry": {"coordinates":[-6.1391282082,36.6847877502],"type":"Point"}
}