{
  "type": "Feature",
  "properties": {
    "iso:country":"ES",
    "sg:address":"Constitucion, S/n",
    "sg:city":"Arroyo Ojanco",
    "sg:orig_category":"Ense\u00d1anza, Formaci\u00d3n Profesional: Aprendizaje",
    "sg:phone":"+34 953 42 02 43",
    "sg:postcode":"23340",
    "sg:province":"Ja\u00e9n",
    "wof:name":"Ayuntamiento De Arroyo Del Ojanco",
    "wof:placetype":"venue"
},
  "geometry": {"coordinates":[-2.8993759155,38.3191833496],"type":"Point"}
}