{
  "type": "Feature",
  "properties": {
    "iso:country":"ES",
    "sg:address":"Calle de Pe\u00d1icas, 15",
    "sg:city":"Roda",
    "sg:orig_category":"Peluqueros: De Se\u00d1oras",
    "sg:phone":"+34 967 44 10 48",
    "sg:postcode":"02630",
    "sg:province":"Albacete",
    "wof:name":"Carrilero Fernandez Carmen",
    "wof:placetype":"venue"
},
  "geometry": {"coordinates":[-2.1571860313,39.2074432373],"type":"Point"}
}