{
  "type": "Feature",
  "properties": {
    "iso:country":"ES",
    "sg:address":"Disseminat, S/n",
    "sg:city":"Granollers",
    "sg:orig_category":"Confecci\u00d3n De Trajes Para Se\u00d1oras",
    "sg:phone":"+34 938 61 90 00",
    "sg:postcode":"08...",
    "sg:province":"Barcelona",
    "sg:website":"www.pinkie.com",
    "wof:name":"Dimodes S.a.",
    "wof:placetype":"venue"
},
  "geometry": {"coordinates":[2.2889099121,41.6079521179],"type":"Point"}
}