{
  "type": "Feature",
  "properties": {
    "iso:country":"ES",
    "sg:address":"Avda Albufera, 240",
    "sg:city":"Madrid",
    "sg:orig_category":"Molduras, Junquillos, Listones Y Molduras Perforadas",
    "sg:phone":"+34 913 80 82 39",
    "sg:postcode":"28038",
    "sg:province":"Madrid",
    "wof:name":"Sierra Ortega Angel",
    "wof:placetype":"venue"
},
  "geometry": {"coordinates":[-3.6469480991,40.3902168274],"type":"Point"}
}