{
  "type": "Feature",
  "properties": {
    "addr:full":"Avda Antonio Mairena, 28 Alcala Guadaira Sevilla 41500",
    "addr:housenumber":"28",
    "addr:postcode":"41500",
    "addr:street":"Avda Antonio Mairena",
    "iso:country":"ES",
    "sg:address":"Avda Antonio Mairena, 28",
    "sg:city":"Alcala Guadaira",
    "sg:orig_category":"Negocio De Materiales De Construcci\u00d3n",
    "sg:phone":"+34 955 68 40 44",
    "sg:postcode":"41500",
    "sg:province":"Sevilla",
    "wof:name":"Dise\u00f1o Y Ceramica Saavedra S.c.",
    "wof:placetype":"venue"
},
  "geometry": {"coordinates":[-5.8397550583,37.3382072449],"type":"Point"}
}