{
  "type": "Feature",
  "properties": {
    "addr:full":"Prol Avenida Santander, S/n Noja Cantabria 39180",
    "addr:housenumber":"s / n",
    "addr:postcode":"39180",
    "addr:street":"Prol Avenida Santander",
    "iso:country":"ES",
    "sg:address":"Prol Avenida Santander, S/n",
    "sg:city":"Noja",
    "sg:orig_category":"Electrodom\u00c9sticos (al Por Menor)",
    "sg:phone":"+34 942 63 03 64",
    "sg:postcode":"39180",
    "sg:province":"Cantabria",
    "wof:name":"Barrojo S.l.",
    "wof:placetype":"venue"
},
  "geometry": {"coordinates":[-3.5296189785,43.4792633057],"type":"Point"}
}