{
  "type": "Feature",
  "properties": {
    "iso:country":"ES",
    "sg:address":"Cmno Juncales (los), 11",
    "sg:city":"Valencia De Don Juan",
    "sg:orig_category":"Mec\u00c1nico Del Autom\u00d3vil",
    "sg:phone":"+34 987 75 22 64",
    "sg:postcode":"24200",
    "sg:province":"Le\u00f3n",
    "wof:name":"Villoria Hermanos S.l.",
    "wof:placetype":"venue"
},
  "geometry": {"coordinates":[-5.513985157,42.2942237854],"type":"Point"}
}