{
  "type": "Feature",
  "properties": {
    "iso:country":"ES",
    "sg:address":"Calle de San Jose, 35",
    "sg:city":"Torre Mar",
    "sg:orig_category":"Supermercados Y Hipermercados",
    "sg:phone":"+34 952 54 52 08",
    "sg:postcode":"29740",
    "sg:province":"M\u00e1laga",
    "wof:name":"Diaz Ramos Francisco",
    "wof:placetype":"venue"
},
  "geometry": {"coordinates":[-4.4186091423,36.7216186523],"type":"Point"}
}