{
  "type": "Feature",
  "properties": {
    "addr:full":"Calle de Deposito Aguas, 5 Alba Tormes Salamanca 37800",
    "addr:housenumber":"5",
    "addr:postcode":"37800",
    "addr:street":"Calle De Deposito Aguas",
    "iso:country":"ES",
    "sg:address":"Calle de Deposito Aguas, 5",
    "sg:city":"Alba Tormes",
    "sg:orig_category":"Mec\u00c1nico Del Autom\u00d3vil",
    "sg:phone":"+34 923 30 04 11",
    "sg:postcode":"37800",
    "sg:province":"Salamanca",
    "wof:name":"Reyes Fernandez Benito",
    "wof:placetype":"venue"
},
  "geometry": {"coordinates":[-5.5110549927,40.8249778748],"type":"Point"}
}