{
  "type": "Feature",
  "properties": {
    "addr:full":"Av Masnou, 27 Hospitalet Llobregat Barcelona 08905",
    "addr:housenumber":"27",
    "addr:postcode":"08905",
    "addr:street":"Av Masnou",
    "iso:country":"ES",
    "sg:address":"Av Masnou, 27",
    "sg:city":"Hospitalet Llobregat",
    "sg:orig_category":"Estancos",
    "sg:phone":"+34 934 37 47 46",
    "sg:postcode":"08905",
    "sg:province":"Barcelona",
    "wof:name":"Gracia Oller Maria Asuncion",
    "wof:placetype":"venue"
},
  "geometry": {"coordinates":[2.1063530445,41.370426178],"type":"Point"}
}