{
  "type": "Feature",
  "properties": {
    "iso:country":"ES",
    "sg:address":"Avda Valencia, 157",
    "sg:city":"Castellon",
    "sg:orig_category":"Venta Y Colocaci\u00d3n De Techos, Falsos Techos",
    "sg:phone":"+34 964 34 18 47",
    "sg:postcode":"12005",
    "sg:province":"Castell\u00f3n",
    "wof:name":"Plafonds Cloisons Esols Techniques S.l",
    "wof:placetype":"venue"
},
  "geometry": {"coordinates":[-0.0512389988,39.9737892151],"type":"Point"}
}