{
  "type": "Feature",
  "properties": {
    "addr:full":"Calle de Honda, 49 Macotera Salamanca 37310",
    "addr:housenumber":"49",
    "addr:postcode":"37310",
    "addr:street":"Calle De Honda",
    "iso:country":"ES",
    "sg:address":"Calle de Honda, 49",
    "sg:city":"Macotera",
    "sg:orig_category":"Lanas (al Por Mayor)",
    "sg:phone":"+34 923 55 52 07",
    "sg:postcode":"37310",
    "sg:province":"Salamanca",
    "wof:name":"Garcia Casado Segismundo",
    "wof:placetype":"venue"
},
  "geometry": {"coordinates":[-5.2883958817,40.8314971924],"type":"Point"}
}