{
  "type": "Feature",
  "properties": {
    "iso:country":"ES",
    "sg:address":"Ctra Vallderiolf, 2",
    "sg:city":"Torreta",
    "sg:orig_category":"Equitaci\u00d3n Y Centros De H\u00cdpica",
    "sg:phone":"+34 938 42 09 61",
    "sg:postcode":"08430",
    "sg:province":"Barcelona",
    "wof:name":"Patau Vilapri\u00f1o Francisco",
    "wof:placetype":"venue"
},
  "geometry": {"coordinates":[2.3250501156,41.5845298767],"type":"Point"}
}