{
  "type": "Feature",
  "properties": {
    "iso:country":"ES",
    "sg:address":"Ctra Cabezarrubias (b), S/n",
    "sg:city":"Brazatortas",
    "sg:orig_category":"Cooperativas Agr\u00cdcolas",
    "sg:phone":"+34 926 47 10 33",
    "sg:postcode":"13450",
    "sg:province":"Ciudad Real",
    "wof:name":"Cooperativa Agricola Cristo De Orense",
    "wof:placetype":"venue"
},
  "geometry": {"coordinates":[-4.2962288857,38.6601333618],"type":"Point"}
}