{
  "type": "Feature",
  "properties": {
    "iso:country":"ES",
    "sg:address":"Calle de Alfonso Xiii, 21",
    "sg:city":"Callosa Segura",
    "sg:orig_category":"Fabricaci\u00d3n De Jabones, Detergentes Y Lej\u00cdas",
    "sg:phone":"+34 965 31 14 67",
    "sg:postcode":"03360",
    "sg:province":"Alicante",
    "wof:name":"Hernandez Fernandez Mariano",
    "wof:placetype":"venue"
},
  "geometry": {"coordinates":[-0.8850083947,38.1155357361],"type":"Point"}
}