{
  "type": "Feature",
  "properties": {
    "iso:country":"ES",
    "sg:address":"Carr Sant Cristofol, 16",
    "sg:city":"Figueres",
    "sg:orig_category":"Asesor\u00cda Fiscal Y Jur\u00cddica",
    "sg:phone":"+34 972 50 04 31",
    "sg:postcode":"17600",
    "sg:province":"Girona",
    "wof:name":"Marti Cairo Jordi",
    "wof:placetype":"venue"
},
  "geometry": {"coordinates":[2.9642100334,42.2671890259],"type":"Point"}
}