{
  "type": "Feature",
  "properties": {
    "addr:full":"Ctra Calafell, 29 Vendrell Tarragona 43700",
    "addr:housenumber":"29",
    "addr:postcode":"43700",
    "addr:street":"Ctra Calafell",
    "iso:country":"ES",
    "sg:address":"Ctra Calafell, 29",
    "sg:city":"Vendrell",
    "sg:orig_category":"Muebles, Minoristas",
    "sg:phone":"+34 977 66 67 53",
    "sg:postcode":"43700",
    "sg:province":"Tarragona",
    "wof:name":"Heras Bascu\u00f1ana Jesus De Las",
    "wof:placetype":"venue"
},
  "geometry": {"coordinates":[1.5408730507,41.22240448],"type":"Point"}
}