{
  "type": "Feature",
  "properties": {
    "iso:country":"ES",
    "sg:address":"Carrer de Independencia, 323",
    "sg:city":"Barcelona",
    "sg:orig_category":"Molduras, Junquillos, Listones Y Molduras Perforadas",
    "sg:phone":"+34 933 47 46 84",
    "sg:postcode":"08026",
    "sg:province":"Barcelona",
    "wof:name":"Faouzi Bannany Zahra",
    "wof:placetype":"venue"
},
  "geometry": {"coordinates":[2.180934906,41.4094696045],"type":"Point"}
}