{
  "type": "Feature",
  "properties": {
    "iso:country":"ES",
    "sg:address":"Carr Vista Alegre, 40",
    "sg:city":"Sueca",
    "sg:orig_category":"Contenedores (mercanc\u00cdas)",
    "sg:phone":"+34 961 71 23 69",
    "sg:postcode":"46410",
    "sg:province":"Valencia",
    "wof:name":"Nelos-trans S.l.",
    "wof:placetype":"venue"
},
  "geometry": {"coordinates":[-0.3076440096,39.2027435303],"type":"Point"}
}