{
  "type": "Feature",
  "properties": {
    "iso:country":"ES",
    "sg:address":"Rua Almirante Brown, 19",
    "sg:city":"Melide",
    "sg:orig_category":"Ense\u00d1anza: Peluquer\u00cda Est\u00c9tica",
    "sg:phone":"+34 981 50 59 03",
    "sg:postcode":"15800",
    "sg:province":"La Coru\u00f1a",
    "wof:name":"Rodriguez Barbeiro Carmen",
    "wof:placetype":"venue"
},
  "geometry": {"coordinates":[-8.0105047226,42.9143600464],"type":"Point"}
}