{
  "type": "Feature",
  "properties": {
    "addr:full":"Ctra. Son Servera, Km. 0011,6 Capdepera Islas Baleares 07580",
    "addr:postcode":"07580",
    "addr:street":"Ctra. Son Servera Km. 0011,6",
    "iso:country":"ES",
    "sg:address":"Ctra. Son Servera, Km. 0011,6",
    "sg:city":"Capdepera",
    "sg:orig_category":"Jardiner\u00cdas, Vegetales, Art\u00cdculos De Jardiner\u00cda (al Por Menor)",
    "sg:phone":"+34 971 56 32 13",
    "sg:postcode":"07580",
    "sg:province":"Islas Baleares",
    "wof:name":"Zones Verdes S.l.",
    "wof:placetype":"venue"
},
  "geometry": {"coordinates":[3.419775486,39.6759338379],"type":"Point"}
}