{
  "type": "Feature",
  "properties": {
    "addr:full":"F. Honrubia, S/n Talavera Reina Toledo 45600",
    "addr:housenumber":"s / n",
    "addr:postcode":"45600",
    "iso:country":"ES",
    "sg:address":"F. Honrubia, S/n",
    "sg:city":"Talavera Reina",
    "sg:orig_category":"Construcciones Met\u00c1licas",
    "sg:phone":"+34 925 81 94 87",
    "sg:postcode":"45600",
    "sg:province":"Toledo",
    "wof:name":"Alfredo Vazquez Gonzalez S.l.",
    "wof:placetype":"venue"
},
  "geometry": {"coordinates":[-4.0244760513,39.8567771912],"type":"Point"}
}