{
  "type": "Feature",
  "properties": {
    "addr:full":"Calle de Santa Ana, 7 Arenas -areeta Vizcaya 48930",
    "addr:housenumber":"7;areeta",
    "addr:postcode":"48930",
    "addr:street":"Calle De Santa Ana",
    "iso:country":"ES",
    "sg:address":"Calle de Santa Ana, 7",
    "sg:city":"Arenas -areeta",
    "sg:orig_category":"Asesor\u00cda Sobre Comunicaci\u00d3n De Empresas",
    "sg:phone":"+34 944 80 53 80",
    "sg:postcode":"48930",
    "sg:province":"Vizcaya",
    "wof:name":"Partners Consulting Pais Vasco S.l.",
    "wof:placetype":"venue"
},
  "geometry": {"coordinates":[-3.0122509003,43.3242950439],"type":"Point"}
}