{
  "type": "Feature",
  "properties": {
    "iso:country":"ES",
    "sg:address":"Rua Emilia Pardo Bazan, 47",
    "sg:city":"Allariz",
    "sg:orig_category":"M\u00c9dicos: Estomatolog\u00cda",
    "sg:phone":"+34 988 44 03 53",
    "sg:postcode":"32660",
    "sg:province":"Ourense",
    "wof:name":"Grande Grande Hermitas",
    "wof:placetype":"venue"
},
  "geometry": {"coordinates":[-7.7992691994,42.1880683899],"type":"Point"}
}