{
  "type": "Feature",
  "properties": {
    "iso:country":"ES",
    "sg:address":"Carrer de Margarida Xirgu, 5",
    "sg:city":"Viladecans",
    "sg:orig_category":"Decoraci\u00d3n: Instalaci\u00d3n Y Talleres",
    "sg:phone":"+34 936 37 91 50",
    "sg:postcode":"08840",
    "sg:province":"Barcelona",
    "sg:website":"www.andrea-egea.terra.es",
    "wof:name":"Andrea&egea S.l",
    "wof:placetype":"venue"
},
  "geometry": {"coordinates":[2.0057229996,41.3102836609],"type":"Point"}
}