{
  "type": "Feature",
  "properties": {
    "addr:full":"Calle de Padre Damian, 44 Madrid Madrid 28036",
    "addr:housenumber":"44",
    "addr:postcode":"madrid;28036",
    "addr:street":"Calle De Padre Damian",
    "iso:country":"ES",
    "sg:address":"Calle de Padre Damian, 44",
    "sg:city":"Madrid",
    "sg:orig_category":"M\u00c9dicos: Estomatolog\u00cda",
    "sg:phone":"+34 913 50 01 17",
    "sg:postcode":"28036",
    "sg:province":"Madrid",
    "sg:website":"www.paginasamarillas.es",
    "wof:name":"Fernandez-palacios Martinez Pedro Manuel",
    "wof:placetype":"venue"
},
  "geometry": {"coordinates":[-3.685297966,40.4596748352],"type":"Point"}
}