{
  "type": "Feature",
  "properties": {
    "iso:country":"ES",
    "sg:address":"Carrer de Asturies, 15",
    "sg:city":"Barcelona",
    "sg:orig_category":"Ropa Para Se\u00d1oras (al Por Menor)",
    "sg:phone":"+34 932 17 92 99",
    "sg:postcode":"08012",
    "sg:province":"Barcelona",
    "wof:name":"Mateo Calsina Maria Dolores",
    "wof:placetype":"venue"
},
  "geometry": {"coordinates":[2.1532959938,41.402961731],"type":"Point"}
}