{
  "type": "Feature",
  "properties": {
    "addr:full":"Balvis, 1 Cari\u00f1o La Coru\u00f1a 15360",
    "addr:housenumber":"1",
    "addr:postcode":"15360",
    "addr:street":"Balvis;La Corun\u0303A",
    "iso:country":"ES",
    "sg:address":"Balvis, 1",
    "sg:city":"Cari\u00f1o",
    "sg:orig_category":"Conservas De Pescados Y Salazones Mar\u00cdtimos (fabricaci\u00d3n, Al Por Mayor)",
    "sg:phone":"+34 981 40 56 66",
    "sg:postcode":"15360",
    "sg:province":"La Coru\u00f1a",
    "wof:name":"Modesto Carrodeguas S.l.",
    "wof:placetype":"venue"
},
  "geometry": {"coordinates":[-7.8690891266,43.7409934998],"type":"Point"}
}