{
  "type": "Feature",
  "properties": {
    "iso:country":"ES",
    "sg:address":"Calle de Ca\u00d1ada (la), S/n",
    "sg:city":"Pajara",
    "sg:orig_category":"Transportes Por V\u00cdas Navegables",
    "sg:phone":"+34 928 16 14 71",
    "sg:postcode":"35628",
    "sg:province":"Las Palmas",
    "wof:name":"Cabrera Santana Eugenio",
    "wof:placetype":"venue"
},
  "geometry": {"coordinates":[-14.1077251434,28.3503513336],"type":"Point"}
}