{
  "type": "Feature",
  "properties": {
    "addr:full":"Rua Riveiro, 12 Perillo La Coru\u00f1a 15172",
    "addr:housenumber":"12",
    "addr:postcode":"15172",
    "addr:street":"Rua Riveiro;Perillo La Corun\u0303A",
    "iso:country":"ES",
    "sg:address":"Rua Riveiro, 12",
    "sg:city":"Perillo",
    "sg:orig_category":"M\u00c9dicos: Gastroenterolog\u00cda Y Hepatolog\u00cda (aparato Digestivo)",
    "sg:phone":"+34 981 63 51 41",
    "sg:postcode":"15172",
    "sg:province":"La Coru\u00f1a",
    "wof:name":"Pollan Rey Matias",
    "wof:placetype":"venue"
},
  "geometry": {"coordinates":[-8.3740053177,43.3324584961],"type":"Point"}
}