{
  "type": "Feature",
  "properties": {
    "iso:country":"ES",
    "sg:address":"Rbla Sant Sebastia, 27",
    "sg:city":"Santa Coloma De Gramenet",
    "sg:orig_category":"Institutos De Belleza",
    "sg:phone":"+34 934 66 84 56",
    "sg:postcode":"08921",
    "sg:province":"Barcelona",
    "wof:name":"Depiline Center Desos",
    "wof:placetype":"venue"
},
  "geometry": {"coordinates":[2.2117710114,41.4508743286],"type":"Point"}
}