{
  "type": "Feature",
  "properties": {
    "addr:full":"Calle de Madre Soledad Torres Acosta, 8 Jaen Ja\u00e9n 23001",
    "addr:housenumber":"8;jae\u0301n",
    "addr:postcode":"23001",
    "addr:street":"Calle De Madre Soledad Torres Acosta",
    "iso:country":"ES",
    "sg:address":"Calle de Madre Soledad Torres Acosta, 8",
    "sg:city":"Jaen",
    "sg:orig_category":"Zapatos (al Por Menor)",
    "sg:phone":"+34 953 27 38 24",
    "sg:postcode":"23001",
    "sg:province":"Ja\u00e9n",
    "wof:name":"Calzados Tetuan S.l.",
    "wof:placetype":"venue"
},
  "geometry": {"coordinates":[-3.7888119221,37.769241333],"type":"Point"}
}