{
  "type": "Feature",
  "properties": {
    "addr:full":"Avda Concepcion Arenal, 212 Praia Pontevedra 36950",
    "addr:housenumber":"212",
    "addr:postcode":"36950",
    "addr:street":"Avda Concepcion Arenal",
    "iso:country":"ES",
    "sg:address":"Avda Concepcion Arenal, 212",
    "sg:city":"Praia",
    "sg:orig_category":"Estancos",
    "sg:phone":"+34 986 31 02 32",
    "sg:postcode":"36950",
    "sg:province":"Pontevedra",
    "wof:name":"Curras Vazquez Jose Angel",
    "wof:placetype":"venue"
},
  "geometry": {"coordinates":[-8.738442421,42.2772254944],"type":"Point"}
}