{
  "type": "Feature",
  "properties": {
    "iso:country":"ES",
    "sg:address":"Avda Federico Garcia Lorca, 43",
    "sg:city":"Almeria",
    "sg:orig_category":"Administraci\u00d3n En Agricultura",
    "sg:phone":"+34 950 27 37 21",
    "sg:postcode":"04004",
    "sg:province":"Almer\u00eda",
    "wof:name":"Deruse  Joe",
    "wof:placetype":"venue"
},
  "geometry": {"coordinates":[-2.4605789185,36.8383102417],"type":"Point"}
}