{
  "type": "Feature",
  "properties": {
    "iso:country":"ES",
    "sg:address":"Calle de Benaque, 14",
    "sg:city":"Malaga",
    "sg:orig_category":"Chapister\u00cda",
    "sg:phone":"+34 952 23 19 67",
    "sg:postcode":"29004",
    "sg:province":"M\u00e1laga",
    "wof:name":"Hermanos Doblas Sanchez S.l.",
    "wof:placetype":"venue"
},
  "geometry": {"coordinates":[-4.4680490494,36.6844863892],"type":"Point"}
}