{
  "type": "Feature",
  "properties": {
    "addr:full":"Rbla Prim, 145 Barcelona Barcelona 08020",
    "addr:housenumber":"145",
    "addr:postcode":"08020",
    "addr:street":"Rbla Prim",
    "iso:country":"ES",
    "sg:address":"Rbla Prim, 145",
    "sg:city":"Barcelona",
    "sg:orig_category":"Renovaci\u00d3n Inmobiliaria",
    "sg:phone":"+34 932 78 02 36",
    "sg:postcode":"08020",
    "sg:province":"Barcelona",
    "wof:name":"Sanchez Fajardo Francisco Javier",
    "wof:placetype":"venue"
},
  "geometry": {"coordinates":[2.2059431076,41.4209976196],"type":"Point"}
}