{
  "type": "Feature",
  "properties": {
    "addr:full":"Rond Sant Antoni, 43 Barcelona Barcelona 08011",
    "addr:housenumber":"43",
    "addr:postcode":"08011",
    "addr:street":"Sant Antoni",
    "iso:country":"ES",
    "sg:address":"Rond Sant Antoni, 43",
    "sg:city":"Barcelona",
    "sg:orig_category":"Dibujantes (diversos)",
    "sg:phone":"+34 933 25 19 42",
    "sg:postcode":"08011",
    "sg:province":"Barcelona",
    "wof:name":"Fernandez Vidal Sebastian",
    "wof:placetype":"venue"
},
  "geometry": {"coordinates":[2.1634631157,41.3827781677],"type":"Point"}
}