{
  "type": "Feature",
  "properties": {
    "iso:country":"ES",
    "sg:address":"Calle de Sancho Ramirez, S/n",
    "sg:city":"Sabi\u00f1anigo",
    "sg:orig_category":"Producci\u00d3n, Distribuci\u00d3n De Electricidad",
    "sg:phone":"+34 974 48 24 29",
    "sg:postcode":"22600",
    "sg:province":"Huesca",
    "wof:name":"Gesmotec S.l.",
    "wof:placetype":"venue"
},
  "geometry": {"coordinates":[-0.3626289964,42.5197639465],"type":"Point"}
}