{
  "type": "Feature",
  "properties": {
    "iso:country":"ES",
    "sg:address":"Praj Carretera De Jumilla, S/n",
    "sg:city":"Campo Abajo",
    "sg:orig_category":"Tapicer\u00cdas",
    "sg:phone":"+34 968 79 45 70",
    "sg:postcode":"30...",
    "sg:province":"Murcia",
    "sg:website":"www.pheo-design.com",
    "wof:name":"Piel Confort S.l.",
    "wof:placetype":"venue"
},
  "geometry": {"coordinates":[-1.284348011,38.0133514404],"type":"Point"}
}