{
  "type": "Feature",
  "properties": {
    "addr:full":"Calle de San Gerardo, 10 Monte Vedat Valencia 46901",
    "addr:housenumber":"10",
    "addr:postcode":"46901",
    "addr:street":"Calle De San Gerardo;Vedat",
    "iso:country":"ES",
    "sg:address":"Calle de San Gerardo, 10",
    "sg:city":"Monte Vedat",
    "sg:orig_category":"Empresas De Pintura Y Revestimientos",
    "sg:phone":"+34 961 55 10 13",
    "sg:postcode":"46901",
    "sg:province":"Valencia",
    "wof:name":"Hernandez Ribes Vicente",
    "wof:placetype":"venue"
},
  "geometry": {"coordinates":[-0.4895339906,39.4135513306],"type":"Point"}
}