{
  "type": "Feature",
  "properties": {
    "iso:country":"ES",
    "sg:address":"Carrer de Gran De Gracia, 93",
    "sg:city":"Barcelona",
    "sg:orig_category":"Doctores En Medicina",
    "sg:phone":"+34 932 17 93 30",
    "sg:postcode":"08012",
    "sg:province":"Barcelona",
    "wof:name":"Pons Cisquella Carme",
    "wof:placetype":"venue"
},
  "geometry": {"coordinates":[2.1541450024,41.4008636475],"type":"Point"}
}