{
  "type": "Feature",
  "properties": {
    "addr:full":"Calle de Real, 31 Camarena Toledo 45180",
    "addr:housenumber":"31",
    "addr:postcode":"45180",
    "addr:street":"Calle De Real",
    "iso:country":"ES",
    "sg:address":"Calle de Real, 31",
    "sg:city":"Camarena",
    "sg:orig_category":"Equitaci\u00d3n: Guarnicioner\u00cda, Equipo (al Por Menor)",
    "sg:phone":"+34 918 17 43 97",
    "sg:postcode":"45180",
    "sg:province":"Toledo",
    "wof:name":"Lucas Benito Antonio",
    "wof:placetype":"venue"
},
  "geometry": {"coordinates":[-4.1235589981,40.0907897949],"type":"Point"}
}