{
  "type": "Feature",
  "properties": {
    "addr:full":"Avda Galicia (de), 47 Monforte De Lemos Lugo 27400",
    "addr:housenumber":"47",
    "addr:postcode":"27400",
    "addr:street":"Avda Galicia De",
    "iso:country":"ES",
    "sg:address":"Avda Galicia (de), 47",
    "sg:city":"Monforte De Lemos",
    "sg:orig_category":"Ingeniero",
    "sg:phone":"+34 982 40 23 63",
    "sg:postcode":"27400",
    "sg:province":"Lugo",
    "wof:name":"Perez Vazquez Victoriano",
    "wof:placetype":"venue"
},
  "geometry": {"coordinates":[-7.5102138519,42.5178565979],"type":"Point"}
}