{
  "type": "Feature",
  "properties": {
    "iso:country":"ES",
    "sg:address":"Plaz Martin Salinas, 4",
    "sg:city":"Rafal",
    "sg:orig_category":"Farmacias",
    "sg:phone":"+34 966 75 22 47",
    "sg:postcode":"03369",
    "sg:province":"Alicante",
    "wof:name":"Cayuela Sanchis Mariano",
    "wof:placetype":"venue"
},
  "geometry": {"coordinates":[-0.8497470021,38.1041259766],"type":"Point"}
}