{
  "type": "Feature",
  "properties": {
    "addr:full":"Calle de Pedro Lorca, 29 Torrevieja Alicante 03180",
    "addr:housenumber":"29",
    "addr:postcode":"03180",
    "addr:street":"Calle De Pedro Lorca",
    "iso:country":"ES",
    "sg:address":"Calle de Pedro Lorca, 29",
    "sg:city":"Torrevieja",
    "sg:orig_category":"Arquitectos",
    "sg:phone":"+34 965 71 78 21",
    "sg:postcode":"03180",
    "sg:province":"Alicante",
    "wof:name":"Garcia Molina Tasaciones S.l.",
    "wof:placetype":"venue"
},
  "geometry": {"coordinates":[-0.6790549755,37.9766998291],"type":"Point"}
}