{
  "type": "Feature",
  "properties": {
    "iso:country":"ES",
    "sg:address":"Av Sant Ferran, 18",
    "sg:city":"Palma",
    "sg:orig_category":"Tintes (fabricaci\u00d3n, Al Por Mayor)",
    "sg:phone":"+34 971 73 65 02",
    "sg:postcode":"07011",
    "sg:province":"Islas Baleares",
    "wof:name":"Meyicahi S.l.",
    "wof:placetype":"venue"
},
  "geometry": {"coordinates":[2.6377921104,39.5801353455],"type":"Point"}
}