{
  "type": "Feature",
  "properties": {
    "iso:country":"ES",
    "sg:address":"Pase Quince De Mayo, 2",
    "sg:city":"Madrid",
    "sg:orig_category":"Asesor\u00cda Sobre Comunicaci\u00d3n De Empresas",
    "sg:phone":"+34 915 60 45 67",
    "sg:postcode":"28019",
    "sg:province":"Madrid",
    "wof:name":"Merino De La Fuente Asesores, S L",
    "wof:placetype":"venue"
},
  "geometry": {"coordinates":[-3.716917038,40.3973922729],"type":"Point"}
}