{
  "type": "Feature",
  "properties": {
    "iso:country":"ES",
    "sg:address":"Carrer de Josep Pinyol, 4",
    "sg:city":"Granollers",
    "sg:orig_category":"Asesor\u00cda Fiscal Y Jur\u00cddica",
    "sg:phone":"+34 938 79 15 94",
    "sg:postcode":"08402",
    "sg:province":"Barcelona",
    "wof:name":"Gabinete De Gestion Artigas Chamizo Scp",
    "wof:placetype":"venue"
},
  "geometry": {"coordinates":[2.2907650471,41.6040802002],"type":"Point"}
}