{
  "type": "Feature",
  "properties": {
    "iso:country":"ES",
    "sg:address":"Avda Santiago Bernabeu, 6",
    "sg:city":"Santa Pola",
    "sg:orig_category":"Estancos",
    "sg:phone":"+34 965 41 51 14",
    "sg:postcode":"03130",
    "sg:province":"Alicante",
    "wof:name":"Valero Halegua Federico Emilio",
    "wof:placetype":"venue"
},
  "geometry": {"coordinates":[-0.5433989763,38.1896057129],"type":"Point"}
}