{
  "type": "Feature",
  "properties": {
    "addr:full":"Calle de Justo Basanta (de), 4 Mejorada Campo Madrid 28840",
    "addr:housenumber":"4",
    "addr:postcode":"28840",
    "addr:street":"Calle De Justo Basanta De",
    "iso:country":"ES",
    "sg:address":"Calle de Justo Basanta (de), 4",
    "sg:city":"Mejorada Campo",
    "sg:orig_category":"Plomeros",
    "sg:phone":"+34 916 79 15 18",
    "sg:postcode":"28840",
    "sg:province":"Madrid",
    "wof:name":"Peralta Sanchez Jose Antonio",
    "wof:placetype":"venue"
},
  "geometry": {"coordinates":[-3.4918570518,40.3959541321],"type":"Point"}
}