{
  "type": "Feature",
  "properties": {
    "iso:country":"ES",
    "sg:address":"Avda Cesareo Alierta, 17",
    "sg:city":"Zaragoza",
    "sg:orig_category":"Frutas Y Legumbres Secas (al Por Mayor)",
    "sg:phone":"+34 976 42 20 31",
    "sg:postcode":"50008",
    "sg:province":"Zaragoza",
    "wof:name":"Frutos Secos El Rincon S. L.",
    "wof:placetype":"venue"
},
  "geometry": {"coordinates":[-0.8767920136,41.6445236206],"type":"Point"}
}