{
  "type": "Feature",
  "properties": {
    "addr:full":"Calle de Santa Virgilia, 14 Madrid Madrid 28033",
    "addr:housenumber":"14",
    "addr:postcode":"madrid;28033",
    "addr:street":"Calle De Santa Virgilia",
    "iso:country":"ES",
    "sg:address":"Calle de Santa Virgilia, 14",
    "sg:city":"Madrid",
    "sg:orig_category":"Pescader\u00cdas (al Por Menor)",
    "sg:phone":"+34 917 64 37 79",
    "sg:postcode":"28033",
    "sg:province":"Madrid",
    "wof:name":"Bacalaos Islas Faroe S.l.",
    "wof:placetype":"venue"
},
  "geometry": {"coordinates":[-3.6420736313,40.476776123],"type":"Point"}
}