{
  "type": "Feature",
  "properties": {
    "addr:full":"Pl Palmeres, 9 Barcelona Barcelona 08030",
    "addr:housenumber":"9",
    "addr:postcode":"08030",
    "addr:street":"Pl Palmeres",
    "iso:country":"ES",
    "sg:address":"Pl Palmeres, 9",
    "sg:city":"Barcelona",
    "sg:orig_category":"Farmacias",
    "sg:phone":"+34 933 46 55 01",
    "sg:postcode":"08030",
    "sg:province":"Barcelona",
    "wof:name":"Almirall Ferran Blanca",
    "wof:placetype":"venue"
},
  "geometry": {"coordinates":[2.1858065128,41.4327659607],"type":"Point"}
}