{
  "type": "Feature",
  "properties": {
    "iso:country":"ES",
    "sg:address":"Calle de Comunicaciones (las), S/n",
    "sg:city":"Alacant",
    "sg:orig_category":"Autom\u00d3viles Y Camiones",
    "sg:phone":"+34 965 11 32 89",
    "sg:postcode":"03008",
    "sg:province":"Alicante",
    "wof:name":"Auto Carrascosa S.l.",
    "wof:placetype":"venue"
},
  "geometry": {"coordinates":[-0.5176464915,38.3358802795],"type":"Point"}
}