{
  "type": "Feature",
  "properties": {
    "iso:country":"ES",
    "sg:address":"Calle de Pilarica, 34",
    "sg:city":"Valladolid",
    "sg:orig_category":"Televisi\u00d3n, V\u00cddeo: Aparatos Y Accesorios (venta)",
    "sg:phone":"+34 983 21 17 25",
    "sg:postcode":"47011",
    "sg:province":"Valladolid",
    "wof:name":"Sancho Berzosa Emilio",
    "wof:placetype":"venue"
},
  "geometry": {"coordinates":[-4.7066340446,41.6529045105],"type":"Point"}
}