{
  "type": "Feature",
  "properties": {
    "addr:full":"Ctra Marmoles (de Los), S/n Arrecife Las Palmas 35500",
    "addr:postcode":"35500",
    "addr:street":"Ctra Marmoles De Los S / N",
    "iso:country":"ES",
    "sg:address":"Ctra Marmoles (de Los), S/n",
    "sg:city":"Arrecife",
    "sg:orig_category":"Ferreter\u00cda (diversos)",
    "sg:phone":"+34 928 80 06 16",
    "sg:postcode":"35500",
    "sg:province":"Las Palmas",
    "sg:website":"www.recuperadoracanaria.com",
    "wof:name":"Recuperadora Canaria De Chatarra Y Metales S. L.",
    "wof:placetype":"venue"
},
  "geometry": {"coordinates":[-13.5436439514,28.9689598083],"type":"Point"}
}