{
  "type": "Feature",
  "properties": {
    "iso:country":"ES",
    "sg:address":"Calle de Lasaga Larreta, 9",
    "sg:city":"Torrelavega",
    "sg:orig_category":"Ense\u00d1anza Variada",
    "sg:phone":"+34 942 80 02 82",
    "sg:postcode":"39300",
    "sg:province":"Cantabria",
    "wof:name":"Centro De Estudios Cossio S.l.",
    "wof:placetype":"venue"
},
  "geometry": {"coordinates":[-4.0523791313,43.3499031067],"type":"Point"}
}