{
  "type": "Feature",
  "properties": {
    "iso:country":"ES",
    "sg:address":"Avgd Vicente Ferri, 34",
    "sg:city":"Canals",
    "sg:orig_category":"Fotograf\u00cda Art\u00cdstica Y Retratos",
    "sg:phone":"+34 962 24 11 52",
    "sg:postcode":"46650",
    "sg:province":"Valencia",
    "wof:name":"Artacho Ramirez Enrique",
    "wof:placetype":"venue"
},
  "geometry": {"coordinates":[-0.5863870978,38.9645957947],"type":"Point"}
}