{
  "type": "Feature",
  "properties": {
    "addr:full":"Carr D'hernan Cortes, 16 Benicarlo Castell\u00f3n 12580",
    "addr:housenumber":"16",
    "addr:postcode":"12580",
    "addr:street":"Carr D'Hernan Cortes",
    "iso:country":"ES",
    "sg:address":"Carr D'hernan Cortes, 16",
    "sg:city":"Benicarlo",
    "sg:orig_category":"Peluqueros: De Se\u00d1oras",
    "sg:phone":"+34 964 47 01 36",
    "sg:postcode":"12580",
    "sg:province":"Castell\u00f3n",
    "wof:name":"Bas Forner Juan",
    "wof:placetype":"venue"
},
  "geometry": {"coordinates":[0.4264410138,40.4173049927],"type":"Point"}
}