{
  "type": "Feature",
  "properties": {
    "addr:full":"Av Castell De Barbera, 13 Barbera Valles Barcelona 08210",
    "addr:housenumber":"13",
    "addr:postcode":"08210",
    "addr:street":"Av Castell De Barbera",
    "iso:country":"ES",
    "sg:address":"Av Castell De Barbera, 13",
    "sg:city":"Barbera Valles",
    "sg:orig_category":"Construcciones Met\u00c1licas",
    "sg:phone":"+34 937 18 06 25",
    "sg:postcode":"08210",
    "sg:province":"Barcelona",
    "wof:name":"R. M. Metalisteria S. L.",
    "wof:placetype":"venue"
},
  "geometry": {"coordinates":[2.146559,41.5237998962],"type":"Point"}
}