{
  "type": "Feature",
  "properties": {
    "addr:full":"Carrer de Jaume Casanovas, 6 Prat Llobregat Barcelona 08820",
    "addr:housenumber":"6",
    "addr:postcode":"08820",
    "addr:street":"Carrer De Jaume Casanovas;Llobregat",
    "iso:country":"ES",
    "sg:address":"Carrer de Jaume Casanovas, 6",
    "sg:city":"Prat Llobregat",
    "sg:orig_category":"Panader\u00cdas, Panader\u00cdas",
    "sg:phone":"+34 933 79 02 67",
    "sg:postcode":"08820",
    "sg:province":"Barcelona",
    "wof:name":"Elias Colome Jaime",
    "wof:placetype":"venue"
},
  "geometry": {"coordinates":[2.0927929878,41.3301391602],"type":"Point"}
}