{
  "type": "Feature",
  "properties": {
    "addr:full":"Calle de Gomez De La Lama, 3 Camas Sevilla 41900",
    "addr:housenumber":"3",
    "addr:postcode":"41900",
    "addr:street":"Calle De Gomez De La Lama",
    "iso:country":"ES",
    "sg:address":"Calle de Gomez De La Lama, 3",
    "sg:city":"Camas",
    "sg:orig_category":"Arenas, Guijarros Y Granulados",
    "sg:phone":"+34 954 33 61 37",
    "sg:postcode":"41900",
    "sg:province":"Sevilla",
    "wof:name":"Transasur S.l.",
    "wof:placetype":"venue"
},
  "geometry": {"coordinates":[-6.0354390144,37.4011192322],"type":"Point"}
}