{
  "type": "Feature",
  "properties": {
    "iso:country":"ES",
    "sg:address":"Calle de Teresa Lopez, 43",
    "sg:city":"Pto. Rosario",
    "sg:orig_category":"Promotores Constructores",
    "sg:phone":"+34 928 85 18 58",
    "sg:postcode":"35600",
    "sg:province":"Las Palmas",
    "wof:name":"Promociones Endoal S.l.",
    "wof:placetype":"venue"
},
  "geometry": {"coordinates":[-13.8648433685,28.5062122345],"type":"Point"}
}