{
  "type": "Feature",
  "properties": {
    "iso:country":"ES",
    "sg:address":"Poli La Pedrera, 5",
    "sg:city":"Benissa",
    "sg:orig_category":"Venta, Montaje De Neum\u00c1ticos",
    "sg:phone":"+34 965 73 02 36",
    "sg:postcode":"03720",
    "sg:province":"Alicante",
    "wof:name":"A.g.f. S.l.",
    "wof:placetype":"venue"
},
  "geometry": {"coordinates":[0.0279866997,38.6844329834],"type":"Point"}
}