{
  "type": "Feature",
  "properties": {
    "iso:country":"ES",
    "sg:address":"Av Passeig Del Comtat, 6",
    "sg:city":"Cocentaina",
    "sg:orig_category":"Armas Y Municiones (fabricaci\u00d3n, Al Por Mayor)",
    "sg:phone":"+34 965 59 03 69",
    "sg:postcode":"03820",
    "sg:province":"Alicante",
    "wof:name":"Serrano Lillo Antonio",
    "wof:placetype":"venue"
},
  "geometry": {"coordinates":[-0.4387629926,38.7515029907],"type":"Point"}
}