{
  "type": "Feature",
  "properties": {
    "iso:country":"ES",
    "sg:address":"Carrer de Aribau, 230",
    "sg:city":"Barcelona",
    "sg:orig_category":"Arquitectos",
    "sg:phone":"+34 934 14 16 91",
    "sg:postcode":"08006",
    "sg:province":"Barcelona",
    "wof:name":"Alegre Rossello Santiago",
    "wof:placetype":"venue"
},
  "geometry": {"coordinates":[2.1502995491,41.395236969],"type":"Point"}
}