{
  "type": "Feature",
  "properties": {
    "addr:full":"Calle de Alcalde Rafael Diaz, 17 Arucas Las Palmas 35400",
    "addr:housenumber":"17",
    "addr:postcode":"35400",
    "addr:street":"Calle De Alcalde Rafael Diaz",
    "iso:country":"ES",
    "sg:address":"Calle de Alcalde Rafael Diaz, 17",
    "sg:city":"Arucas",
    "sg:orig_category":"Agencias Y Agentes Comerciales, Representantes",
    "sg:phone":"+34 928 62 29 00",
    "sg:postcode":"35400",
    "sg:province":"Las Palmas",
    "wof:name":"Suarez Perez Andres",
    "wof:placetype":"venue"
},
  "geometry": {"coordinates":[-15.5253305435,28.1220760345],"type":"Point"}
}