{
  "type": "Feature",
  "properties": {
    "addr:full":"Calle de Zabaleta, 1 Donostia-san Sebastian Guip\u00f9zcoa 20002",
    "addr:housenumber":"1",
    "addr:postcode":"20002",
    "addr:street":"Calle De Zabaleta",
    "iso:country":"ES",
    "sg:address":"Calle de Zabaleta, 1",
    "sg:city":"Donostia-san Sebastian",
    "sg:orig_category":"Abogados Especialistas En Derecho Penal",
    "sg:phone":"+34 943 32 61 02",
    "sg:postcode":"20002",
    "sg:province":"Guip\u00f9zcoa",
    "sg:website":"www.iurarech.com",
    "wof:name":"Macho Pe\u00f1a Miren",
    "wof:placetype":"venue"
},
  "geometry": {"coordinates":[-1.9769979715,43.3226737976],"type":"Point"}
}