{
  "type": "Feature",
  "properties": {
    "addr:full":"Calle de Don Jaime I, 48 Zaragoza Zaragoza 50001",
    "addr:housenumber":"48",
    "addr:postcode":"50001",
    "addr:street":"Calle De Don Jaime I",
    "iso:country":"ES",
    "sg:address":"Calle de Don Jaime I, 48",
    "sg:city":"Zaragoza",
    "sg:orig_category":"Bazares, Art\u00cdculos De Limpieza Y De Cocina (al Por Menor)",
    "sg:phone":"+34 976 29 27 36",
    "sg:postcode":"50001",
    "sg:province":"Zaragoza",
    "wof:name":"Multi100 S.l.",
    "wof:placetype":"venue"
},
  "geometry": {"coordinates":[-0.8770546913,41.6548156738],"type":"Point"}
}