{
  "type": "Feature",
  "properties": {
    "addr:full":"Carrer de General Alvarez De Castr, 1 Barcelona Barcelona 08003",
    "addr:housenumber":"1",
    "addr:postcode":"08003",
    "addr:street":"Carrer De General Alvarez De Castr",
    "iso:country":"ES",
    "sg:address":"Carrer de General Alvarez De Castr, 1",
    "sg:city":"Barcelona",
    "sg:orig_category":"Zapatos (al Por Menor)",
    "sg:phone":"+34 933 19 94 57",
    "sg:postcode":"08003",
    "sg:province":"Barcelona",
    "wof:name":"Sanchez Sierra Silvestre",
    "wof:placetype":"venue"
},
  "geometry": {"coordinates":[2.1780099869,41.38671875],"type":"Point"}
}