{
  "type": "Feature",
  "properties": {
    "addr:full":"Veza, 33 Madrid Madrid 28029",
    "addr:housenumber":"33",
    "addr:postcode":"madrid;28029",
    "addr:street":"Veza",
    "iso:country":"ES",
    "sg:address":"Veza, 33",
    "sg:city":"Madrid",
    "sg:orig_category":"Abogados",
    "sg:phone":"+34 913 23 10 17",
    "sg:postcode":"28029",
    "sg:province":"Madrid",
    "wof:name":"Parrondo Ortega Alberto",
    "wof:placetype":"venue"
},
  "geometry": {"coordinates":[-3.6979990005,40.4661178589],"type":"Point"}
}