{
  "type": "Feature",
  "properties": {
    "addr:full":"Calle de Serrano, 125 Madrid Madrid 28006",
    "addr:housenumber":"125",
    "addr:postcode":"28006",
    "addr:street":"Calle De Serrano",
    "iso:country":"ES",
    "sg:address":"Calle de Serrano, 125",
    "sg:city":"Madrid",
    "sg:orig_category":"Iglesia Cat\u00d3lica",
    "sg:phone":"+34 915 63 20 24",
    "sg:postcode":"28006",
    "sg:province":"Madrid",
    "wof:name":"Iglesia Espiritu Santo",
    "wof:placetype":"venue"
},
  "geometry": {"coordinates":[-3.6860589981,40.4419059753],"type":"Point"}
}