{
  "type": "Feature",
  "properties": {
    "iso:country":"ES",
    "sg:address":"Carrer de Pau Miralda, 43",
    "sg:city":"Manresa",
    "sg:orig_category":"Calderer\u00cda",
    "sg:phone":"+34 938 73 19 97",
    "sg:postcode":"08243",
    "sg:province":"Barcelona",
    "wof:name":"Sercametal S.l.",
    "wof:placetype":"venue"
},
  "geometry": {"coordinates":[1.8493440151,41.708366394],"type":"Point"}
}