{
  "type": "Feature",
  "properties": {
    "iso:country":"ES",
    "sg:address":"Pase Madrid (de), S/n",
    "sg:city":"Boadilla Del Monte",
    "sg:orig_category":"Negocio De Materiales De Construcci\u00d3n",
    "sg:phone":"+34 916 33 45 12",
    "sg:postcode":"28660",
    "sg:province":"Madrid",
    "wof:name":"Ayuntamiento De Boadilla Del Monte",
    "wof:placetype":"venue"
},
  "geometry": {"coordinates":[-3.8683331013,40.4010314941],"type":"Point"}
}