{
  "type": "Feature",
  "properties": {
    "iso:country":"ES",
    "sg:address":"Calle de Principe De Vergara, 210",
    "sg:city":"Madrid",
    "sg:orig_category":"Inmobiliaria (agencias)",
    "sg:phone":"+34 915 61 58 04",
    "sg:postcode":"28002",
    "sg:province":"Madrid",
    "wof:name":"Zusimo S.a.",
    "wof:placetype":"venue"
},
  "geometry": {"coordinates":[-3.6775774956,40.4513702393],"type":"Point"}
}