{
  "type": "Feature",
  "properties": {
    "addr:full":"Calle de Plata, 3 Moraleja Enmedio Madrid 28950",
    "addr:housenumber":"3",
    "addr:postcode":"28950",
    "addr:street":"Calle De Plata",
    "iso:country":"ES",
    "sg:address":"Calle de Plata, 3",
    "sg:city":"Moraleja Enmedio",
    "sg:orig_category":"Mec\u00c1nico Del Autom\u00d3vil",
    "sg:phone":"+34 916 09 44 75",
    "sg:postcode":"28950",
    "sg:province":"Madrid",
    "wof:name":"Horrillo Pizarro Diego",
    "wof:placetype":"venue"
},
  "geometry": {"coordinates":[-3.8492529392,40.262462616],"type":"Point"}
}