{
  "type": "Feature",
  "properties": {
    "addr:full":"Carrer de Gran De Sant Andreu, 383 Barcelona Barcelona 08030",
    "addr:housenumber":"383",
    "addr:postcode":"08030",
    "addr:street":"Carrer De Gran De Sant Andreu",
    "iso:country":"ES",
    "sg:address":"Carrer de Gran De Sant Andreu, 383",
    "sg:city":"Barcelona",
    "sg:orig_category":"Colchones (fabricaci\u00d3n, Al Por Mayor, Al Por Menor)",
    "sg:phone":"+34 933 46 22 53",
    "sg:postcode":"08030",
    "sg:province":"Barcelona",
    "wof:name":"Solsona 2000 S.l.",
    "wof:placetype":"venue"
},
  "geometry": {"coordinates":[2.1885910034,41.4389953613],"type":"Point"}
}