{
  "type": "Feature",
  "properties": {
    "addr:full":"Pla\u00c7 Manuel Bertrand, 3 Mollerussa Lleida 25230",
    "addr:housenumber":"3",
    "addr:postcode":"25230",
    "addr:street":"Manuel Bertrand",
    "iso:country":"ES",
    "sg:address":"Pla\u00c7 Manuel Bertrand, 3",
    "sg:city":"Mollerussa",
    "sg:orig_category":"\u00d3pticos Optometristas (al Por Menor)",
    "sg:phone":"+34 973 60 37 76",
    "sg:postcode":"25230",
    "sg:province":"Lleida",
    "wof:name":"Prosub-10 S.l.",
    "wof:placetype":"venue"
},
  "geometry": {"coordinates":[0.8936949968,41.6300392151],"type":"Point"}
}