{
  "type": "Feature",
  "properties": {
    "addr:full":"Ctra Gurb, S/n Vic Barcelona 08500",
    "addr:housenumber":"s",
    "addr:postcode":"08500",
    "addr:street":"Ctra Gurb;/ N",
    "iso:country":"ES",
    "sg:address":"Ctra Gurb, S/n",
    "sg:city":"Vic",
    "sg:orig_category":"Vinos Y Licores (venta Al Por Menor)",
    "sg:phone":"+34 938 86 12 47",
    "sg:postcode":"08500",
    "sg:province":"Barcelona",
    "wof:name":"Panades & Alemany S.c.",
    "wof:placetype":"venue"
},
  "geometry": {"coordinates":[2.2478690147,41.9363708496],"type":"Point"}
}