{
  "type": "Feature",
  "properties": {
    "addr:full":"Ctra Madrid-irun, Km. 0153,0 Fuentespina Burgos 09470",
    "addr:postcode":"09470",
    "addr:street":"Ctra Madrid-Irun Km. 0153,0",
    "iso:country":"ES",
    "sg:address":"Ctra Madrid-irun, Km. 0153,0",
    "sg:city":"Fuentespina",
    "sg:orig_category":"Lavado, Limpieza De Veh\u00cdculos",
    "sg:phone":"+34 947 50 39 01",
    "sg:postcode":"09470",
    "sg:province":"Burgos",
    "sg:website":"www.inicia.es/de/lphsl",
    "wof:name":"Lorenzo Pe\u00f1a E Hijos S.l.",
    "wof:placetype":"venue"
},
  "geometry": {"coordinates":[-3.6870539188,41.6330718994],"type":"Point"}
}