{
  "type": "Feature",
  "properties": {
    "addr:full":"Calle de San Jose, 37 Linea De La Concepcion C\u00e1diz 11300",
    "addr:housenumber":"37",
    "addr:postcode":"11300",
    "addr:street":"Calle De San;Ca\u0301Diz",
    "iso:country":"ES",
    "sg:address":"Calle de San Jose, 37",
    "sg:city":"Linea De La Concepcion",
    "sg:orig_category":"Empresas De Limpieza",
    "sg:phone":"+34 956 17 09 12",
    "sg:postcode":"11300",
    "sg:province":"C\u00e1diz",
    "wof:name":"Limpiezas En General La Linea S.l.",
    "wof:placetype":"venue"
},
  "geometry": {"coordinates":[-5.3469810486,36.165435791],"type":"Point"}
}