{
  "type": "Feature",
  "properties": {
    "addr:full":"Calle de Elizondo, 2 Bilbao Vizcaya 48004",
    "addr:housenumber":"2",
    "addr:postcode":"48004",
    "addr:street":"Calle De Elizondo",
    "iso:country":"ES",
    "sg:address":"Calle de Elizondo, 2",
    "sg:city":"Bilbao",
    "sg:orig_category":"Bisuter\u00cda, Joyer\u00cda, Relojer\u00cda (al Por Menor)",
    "sg:phone":"+34 944 11 90 39",
    "sg:postcode":"48004",
    "sg:province":"Vizcaya",
    "wof:name":"Francisca Sanchez Fernandez (joyeria Sanchez)",
    "wof:placetype":"venue"
},
  "geometry": {"coordinates":[-2.9108080864,43.2534255981],"type":"Point"}
}