{
  "type": "Feature",
  "properties": {
    "addr:full":"Calle de Capuletti, 64 Valladolid Valladolid 47008",
    "addr:housenumber":"64",
    "addr:postcode":"47008",
    "addr:street":"Calle De Capuletti",
    "iso:country":"ES",
    "sg:address":"Calle de Capuletti, 64",
    "sg:city":"Valladolid",
    "sg:orig_category":"Venta, Localizaci\u00d3n, Reparaci\u00d3n De Material E Instrumental M\u00c9dico",
    "sg:phone":"+34 983 24 70 27",
    "sg:postcode":"47008",
    "sg:province":"Valladolid",
    "wof:name":"Fidotec S.l.",
    "wof:placetype":"venue"
},
  "geometry": {"coordinates":[-4.7506437302,41.6078987122],"type":"Point"}
}