{
  "type": "Feature",
  "properties": {
    "addr:full":"Carretera De Gomara-monteagudo, S/n Seron Nagima Soria 42127",
    "addr:housenumber":"s / n",
    "addr:postcode":"42127",
    "addr:street":"Carretera De Gomara-Monteagudo;Seron Nagima",
    "iso:country":"ES",
    "sg:address":"Carretera De Gomara-monteagudo, S/n",
    "sg:city":"Seron Nagima",
    "sg:orig_category":"Producci\u00d3n De Abonos Y De Fertilizantes",
    "sg:phone":"+34 975 30 70 12",
    "sg:postcode":"42127",
    "sg:province":"Soria",
    "wof:name":"Latorre Hernandez Jose Juan",
    "wof:placetype":"venue"
},
  "geometry": {"coordinates":[-2.2299690247,41.5737915039],"type":"Point"}
}