{
  "type": "Feature",
  "properties": {
    "addr:full":"Calle de Pizarro, 5 Quintanar Orden Toledo 45800",
    "addr:housenumber":"5",
    "addr:postcode":"45800",
    "addr:street":"Calle De Pizarro",
    "iso:country":"ES",
    "sg:address":"Calle de Pizarro, 5",
    "sg:city":"Quintanar Orden",
    "sg:orig_category":"Peluquer\u00cdas, Peluquer\u00cda Mixta",
    "sg:phone":"+34 925 18 21 24",
    "sg:postcode":"45800",
    "sg:province":"Toledo",
    "wof:name":"Garcia Escudero Rosa",
    "wof:placetype":"venue"
},
  "geometry": {"coordinates":[-3.0419209003,39.5952796936],"type":"Point"}
}