{
  "type": "Feature",
  "properties": {
    "iso:country":"ES",
    "sg:address":"Calle de General Barroso, 65",
    "sg:city":"Valencia",
    "sg:orig_category":"Droguer\u00cdas (al Por Menor)",
    "sg:phone":"+34 963 77 27 48",
    "sg:postcode":"46017",
    "sg:province":"Valencia",
    "wof:name":"Rodriguez Torres Jose Antonio",
    "wof:placetype":"venue"
},
  "geometry": {"coordinates":[-0.3923319876,39.450466156],"type":"Point"}
}