{
  "type": "Feature",
  "properties": {
    "addr:full":"Calle de Cervantes, 10 Merida Badajoz 06800",
    "addr:housenumber":"10",
    "addr:postcode":"06800",
    "addr:street":"Calle De Cervantes",
    "iso:country":"ES",
    "sg:address":"Calle de Cervantes, 10",
    "sg:city":"Merida",
    "sg:orig_category":"Ropa Para Se\u00d1oras Y Caballeros (al Por Menor)",
    "sg:phone":"+34 924 31 90 68",
    "sg:postcode":"06800",
    "sg:province":"Badajoz",
    "wof:name":"Hiralmer S.l.",
    "wof:placetype":"venue"
},
  "geometry": {"coordinates":[-6.385160923,38.8867416382],"type":"Point"}
}