{
  "type": "Feature",
  "properties": {
    "addr:full":"Finca San Pedro, S/n Humilladero M\u00e1laga 29531",
    "addr:housenumber":"/ n",
    "addr:postcode":"29531",
    "addr:street":"San Pedro S",
    "iso:country":"ES",
    "sg:address":"Finca San Pedro, S/n",
    "sg:city":"Humilladero",
    "sg:orig_category":"Agricultura: Abastecimiento Y Cosechado (negocio)",
    "sg:phone":"+34 952 11 17 19",
    "sg:postcode":"29531",
    "sg:province":"M\u00e1laga",
    "wof:name":"Vergara Palomino Joaquin",
    "wof:placetype":"venue"
},
  "geometry": {"coordinates":[-4.7001290321,37.1147956848],"type":"Point"}
}