{
  "type": "Feature",
  "properties": {
    "addr:full":"Calle de Cantalejo, 6 Madrid Madrid 28035",
    "addr:housenumber":"6",
    "addr:postcode":"28035",
    "addr:street":"Calle De Cantalejo",
    "iso:country":"ES",
    "sg:address":"Calle de Cantalejo, 6",
    "sg:city":"Madrid",
    "sg:orig_category":"Agencias Y Agentes Comerciales, Representantes",
    "sg:phone":"+34 913 16 06 39",
    "sg:postcode":"28035",
    "sg:province":"Madrid",
    "wof:name":"Perez Perez Jose",
    "wof:placetype":"venue"
},
  "geometry": {"coordinates":[-3.7403225899,40.4750595093],"type":"Point"}
}