{
  "type": "Feature",
  "properties": {
    "addr:full":"Calle de Serafin Escalante, 10 Torrelavega Cantabria 39300",
    "addr:housenumber":"10",
    "addr:postcode":"39300",
    "addr:street":"Calle De Serafin Escalante",
    "iso:country":"ES",
    "sg:address":"Calle de Serafin Escalante, 10",
    "sg:city":"Torrelavega",
    "sg:orig_category":"Asesor\u00cda Fiscal Y Jur\u00cddica",
    "sg:phone":"+34 942 80 06 10",
    "sg:postcode":"39300",
    "sg:province":"Cantabria",
    "wof:name":"Gonzalez Gomez Antonio",
    "wof:placetype":"venue"
},
  "geometry": {"coordinates":[-4.0487370491,43.3493041992],"type":"Point"}
}