{
  "type": "Feature",
  "properties": {
    "addr:full":"Amadeo, 4 Arta Islas Baleares 07570",
    "addr:housenumber":"4",
    "addr:postcode":"07570",
    "addr:street":"Amadeo;Islas Baleares",
    "iso:country":"ES",
    "sg:address":"Amadeo, 4",
    "sg:city":"Arta",
    "sg:orig_category":"Cer\u00c1micas: Material Y Suministros",
    "sg:phone":"+34 971 83 62 59",
    "sg:postcode":"07570",
    "sg:province":"Islas Baleares",
    "wof:name":"Roig Cladera S.l.",
    "wof:placetype":"venue"
},
  "geometry": {"coordinates":[3.326939106,39.7053108215],"type":"Point"}
}