{
  "type": "Feature",
  "properties": {
    "addr:full":"Av Onze De Setembre, 32 Sant Joan De Palamos Girona 17230",
    "addr:housenumber":"32",
    "addr:postcode":"17230",
    "addr:street":"Av Onze De Setembre",
    "iso:country":"ES",
    "sg:address":"Av Onze De Setembre, 32",
    "sg:city":"Sant Joan De Palamos",
    "sg:orig_category":"Papeler\u00cdas, Librer\u00cdas",
    "sg:phone":"+34 972 60 18 18",
    "sg:postcode":"17230",
    "sg:province":"Girona",
    "wof:name":"Espinola Romero Amalia Isabel",
    "wof:placetype":"venue"
},
  "geometry": {"coordinates":[3.1288158894,41.8485679626],"type":"Point"}
}