{
  "type": "Feature",
  "properties": {
    "addr:full":"Calle de Acuerdo, 40 Madrid Madrid 28015",
    "addr:housenumber":"40",
    "addr:postcode":"madrid;28015",
    "addr:street":"Calle De Acuerdo",
    "iso:country":"ES",
    "sg:address":"Calle de Acuerdo, 40",
    "sg:city":"Madrid",
    "sg:orig_category":"Fotocopias, Reprograf\u00cda",
    "sg:phone":"+34 914 48 68 09",
    "sg:postcode":"28015",
    "sg:province":"Madrid",
    "wof:name":"Esteban Gonzalez Maria Angeles",
    "wof:placetype":"venue"
},
  "geometry": {"coordinates":[-3.7080230713,40.4279708862],"type":"Point"}
}