{
  "type": "Feature",
  "properties": {
    "iso:country":"ES",
    "sg:address":"Veza, 7",
    "sg:city":"Madrid",
    "sg:orig_category":"Oficinas: Suministros Para (fabricaci\u00d3n, Al Por Mayor)",
    "sg:phone":"+34 913 14 20 57",
    "sg:postcode":"28029",
    "sg:province":"Madrid",
    "sg:website":"www.ofimovil.es",
    "wof:name":"Ofimundo Comunicaciones S.l.",
    "wof:placetype":"venue"
},
  "geometry": {"coordinates":[-3.6963610649,40.4655952454],"type":"Point"}
}