{
  "type": "Feature",
  "properties": {
    "iso:country":"ES",
    "sg:address":"Calle de Goya, 29",
    "sg:city":"Sari\u00f1ena",
    "sg:orig_category":"Producci\u00d3n, Distribuci\u00d3n De Electricidad",
    "sg:phone":"+34 974 57 00 53",
    "sg:postcode":"22200",
    "sg:province":"Huesca",
    "wof:name":"Hernandez Hernandez Santiago",
    "wof:placetype":"venue"
},
  "geometry": {"coordinates":[-0.158536002,41.7930717468],"type":"Point"}
}