{
  "type": "Feature",
  "properties": {
    "iso:country":"ES",
    "sg:address":"Calle de Posito, 3",
    "sg:city":"Almu\u00f1ecar",
    "sg:orig_category":"Ropa Para Ni\u00d1os (al Por Menor)",
    "sg:phone":"+34 958 63 16 99",
    "sg:postcode":"18690",
    "sg:province":"Granada",
    "wof:name":"Rivas Jimenez Maria Gracia",
    "wof:placetype":"venue"
},
  "geometry": {"coordinates":[-3.6911079884,36.7339401245],"type":"Point"}
}