{
  "type": "Feature",
  "properties": {
    "iso:country":"ES",
    "sg:address":"Calle de San Vicente, 19",
    "sg:city":"Getafe",
    "sg:orig_category":"Guarder\u00cdas",
    "sg:phone":"+34 916 81 90 87",
    "sg:postcode":"28901",
    "sg:province":"Madrid",
    "wof:name":"Arjiz Tresguerras Maria Del Carmen",
    "wof:placetype":"venue"
},
  "geometry": {"coordinates":[-3.7258942127,40.3084983826],"type":"Point"}
}