{
  "type": "Feature",
  "properties": {
    "iso:country":"ES",
    "sg:address":"Plaz Fructuoso Muerza, 6",
    "sg:city":"S. Adrian",
    "sg:orig_category":"Notarios",
    "sg:phone":"+34 948 67 08 53",
    "sg:postcode":"31570",
    "sg:province":"Navarra",
    "wof:name":"Otao Martinez-portillo Luis Miguel",
    "wof:placetype":"venue"
},
  "geometry": {"coordinates":[-1.9341859818,42.3346481323],"type":"Point"}
}