{
  "type": "Feature",
  "properties": {
    "iso:country":"ES",
    "sg:address":"Calle de Nuestra Sra Del Pilar (de), 1",
    "sg:city":"Alcobendas",
    "sg:orig_category":"Carnicer\u00cdas, Carnicer\u00cdas",
    "sg:phone":"+34 916 53 66 08",
    "sg:postcode":"28100",
    "sg:province":"Madrid",
    "sg:website":"www.biocarnes.es",
    "wof:name":"Tecnicas Industriales Intensivas, Sl.",
    "wof:placetype":"venue"
},
  "geometry": {"coordinates":[-3.6331369877,40.5414390564],"type":"Point"}
}