{
  "type": "Feature",
  "properties": {
    "iso:country":"ES",
    "sg:address":"Finca El Moscadero, S/n",
    "sg:city":"Llano Bureba",
    "sg:orig_category":"Agricultores, Agricultores",
    "sg:phone":"+34 947 56 33 35",
    "sg:postcode":"09246",
    "sg:province":"Burgos",
    "wof:name":"Consorcio De Promocion Agropecuaria Provincial",
    "wof:placetype":"venue"
},
  "geometry": {"coordinates":[-3.3914239407,42.6456680298],"type":"Point"}
}