{
  "type": "Feature",
  "properties": {
    "addr:full":"Calle de Lamuza, 23 Llodio \u00c1lava 01400",
    "addr:housenumber":"23",
    "addr:postcode":"01400",
    "addr:street":"Calle De Lamuza",
    "iso:country":"ES",
    "sg:address":"Calle de Lamuza, 23",
    "sg:city":"Llodio",
    "sg:orig_category":"M\u00c9dicos: Medicina Manual",
    "sg:phone":"+34 946 72 64 77",
    "sg:postcode":"01400",
    "sg:province":"\u00c1lava",
    "wof:name":"Ortiz Lazurtegui Miren Bego\u00f1a",
    "wof:placetype":"venue"
},
  "geometry": {"coordinates":[-2.9676640034,43.1462631226],"type":"Point"}
}