{
  "type": "Feature",
  "properties": {
    "addr:full":"Calle de Baja Fuente, 15 Pegalajar Ja\u00e9n 23110",
    "addr:housenumber":"15",
    "addr:postcode":"23110",
    "addr:street":"Calle De Baja Fuente;Jae\u0301N",
    "iso:country":"ES",
    "sg:address":"Calle de Baja Fuente, 15",
    "sg:city":"Pegalajar",
    "sg:orig_category":"Cajas De Ahorro",
    "sg:phone":"+34 953 36 00 09",
    "sg:postcode":"23110",
    "sg:province":"Ja\u00e9n",
    "sg:website":"www.cajagranada.es",
    "wof:name":"Cajagranada",
    "wof:placetype":"venue"
},
  "geometry": {"coordinates":[-3.6467878819,37.7400283813],"type":"Point"}
}