{
  "type": "Feature",
  "properties": {
    "iso:country":"ES",
    "sg:address":"Pla\u00c7 Born, Des, S/n",
    "sg:city":"Ciutadella Menorca",
    "sg:orig_category":"Centros De Educaci\u00d3n Especial",
    "sg:phone":"+34 971 38 06 32",
    "sg:postcode":"07760",
    "sg:province":"Islas Baleares",
    "wof:name":"Co%egi Public Joan Benejam",
    "wof:placetype":"venue"
},
  "geometry": {"coordinates":[3.8416149616,40.0027542114],"type":"Point"}
}