{
  "type": "Feature",
  "properties": {
    "addr:full":"Ca\u00f1ota, 25 Ca\u00d1ota Pontevedra 36157",
    "addr:housenumber":"25",
    "addr:postcode":"36157",
    "addr:street":"Can\u0303Ota",
    "iso:country":"ES",
    "sg:address":"Ca\u00f1ota, 25",
    "sg:city":"Ca\u00d1ota",
    "sg:orig_category":"Cerrajer\u00cda, Ferrallista",
    "sg:phone":"+34 986 87 09 44",
    "sg:postcode":"36157",
    "sg:province":"Pontevedra",
    "wof:name":"Aluminios Campano S.l.",
    "wof:placetype":"venue"
},
  "geometry": {"coordinates":[-8.6480531693,42.4336204529],"type":"Point"}
}