{
  "type": "Feature",
  "properties": {
    "iso:country":"ES",
    "sg:address":"Avgd De Daniel Gil, 57",
    "sg:city":"Ontinyent",
    "sg:orig_category":"Electricidad: Instaladores",
    "sg:phone":"+34 962 38 71 54",
    "sg:postcode":"46870",
    "sg:province":"Valencia",
    "wof:name":"Electricidad Clariano S.l.",
    "wof:placetype":"venue"
},
  "geometry": {"coordinates":[-0.600350976,38.8203926086],"type":"Point"}
}