{
  "type": "Feature",
  "properties": {
    "addr:full":"Calle de Malcampo, 14 Madrid Madrid 28002",
    "addr:housenumber":"14",
    "addr:postcode":"madrid;28002",
    "addr:street":"Calle De Malcampo",
    "iso:country":"ES",
    "sg:address":"Calle de Malcampo, 14",
    "sg:city":"Madrid",
    "sg:orig_category":"Promotores Constructores",
    "sg:phone":"+34 915 19 53 14",
    "sg:postcode":"28002",
    "sg:province":"Madrid",
    "wof:name":"Arquitectalia S.l.",
    "wof:placetype":"venue"
},
  "geometry": {"coordinates":[-3.6737554073,40.4455986023],"type":"Point"}
}