{
  "type": "Feature",
  "properties": {
    "iso:country":"ES",
    "sg:address":"C/ Major, 2",
    "sg:city":"Salt",
    "sg:orig_category":"Inmobiliaria (agencias)",
    "sg:phone":"+34 972 40 20 63",
    "sg:postcode":"17190",
    "sg:province":"Girona",
    "wof:name":"Inmobiliaria Espigul S.l.",
    "wof:placetype":"venue"
},
  "geometry": {"coordinates":[2.7822699547,41.9725914001],"type":"Point"}
}