{
  "type": "Feature",
  "properties": {
    "iso:country":"ES",
    "sg:address":"Carr Calaf, 9",
    "sg:city":"Igualada",
    "sg:orig_category":"Institutos De Belleza",
    "sg:phone":"+34 938 04 62 02",
    "sg:postcode":"08700",
    "sg:province":"Barcelona",
    "wof:name":"Pons Claramunt Ivet",
    "wof:placetype":"venue"
},
  "geometry": {"coordinates":[1.6165210009,41.5866317749],"type":"Point"}
}