{
  "type": "Feature",
  "properties": {
    "addr:full":"Cmno Pinto, Km. 0001,0 Parla Madrid 28980",
    "addr:postcode":"28980",
    "addr:street":"Cmno Pinto Km. 0001,0",
    "iso:country":"ES",
    "sg:address":"Cmno Pinto, Km. 0001,0",
    "sg:city":"Parla",
    "sg:orig_category":"Ropa Para Se\u00d1oras (al Por Menor)",
    "sg:phone":"+34 916 99 68 78",
    "sg:postcode":"28980",
    "sg:province":"Madrid",
    "wof:name":"Boutique Denas S.l.",
    "wof:placetype":"venue"
},
  "geometry": {"coordinates":[-3.7734539509,40.237449646],"type":"Point"}
}