{
  "type": "Feature",
  "properties": {
    "iso:country":"ES",
    "sg:address":"Plaz Reyes Catolicos, 15",
    "sg:city":"Marbella",
    "sg:orig_category":"Perfumer\u00cda Y Cosm\u00c9tica (fabricaci\u00d3n, Al Por Mayor)",
    "sg:phone":"+34 952 86 88 88",
    "sg:postcode":"29600",
    "sg:province":"M\u00e1laga",
    "wof:name":"Laboratorio Fergo S.l",
    "wof:placetype":"venue"
},
  "geometry": {"coordinates":[-4.8869690895,36.510597229],"type":"Point"}
}