{
  "type": "Feature",
  "properties": {
    "iso:country":"ES",
    "sg:address":"Calle de Gravina, 8",
    "sg:city":"Grao",
    "sg:orig_category":"Artes Gr\u00c1ficas, Artes Pl\u00c1sticas: Material Y Suministros (al Por Menor)",
    "sg:phone":"+34 964 28 35 01",
    "sg:postcode":"12100",
    "sg:province":"Castell\u00f3n",
    "wof:name":"Mu\u00f1oz Corrales Manuela",
    "wof:placetype":"venue"
},
  "geometry": {"coordinates":[0.0141955996,39.9747123718],"type":"Point"}
}