{
  "type": "Feature",
  "properties": {
    "iso:country":"ES",
    "sg:address":"Avda Cesareo Alierta, 31",
    "sg:city":"Zaragoza",
    "sg:orig_category":"Bisuteros (fabricaci\u00d3n, Al Por Mayor)",
    "sg:phone":"+34 976 59 94 80",
    "sg:postcode":"50008",
    "sg:province":"Zaragoza",
    "sg:website":"www.kuuz.net",
    "wof:name":"Amate Alejos Francisco Javier",
    "wof:placetype":"venue"
},
  "geometry": {"coordinates":[-0.8757513165,41.6429176331],"type":"Point"}
}