{
  "type": "Feature",
  "properties": {
    "iso:country":"ES",
    "sg:address":"Calle de Obispo Rabadan, 23",
    "sg:city":"Palmas De Gran Canaria",
    "sg:orig_category":"Ropa Para Ni\u00d1os (al Por Menor)",
    "sg:phone":"+34 928 36 43 67",
    "sg:postcode":"35003",
    "sg:province":"Las Palmas",
    "wof:name":"Afonso Gonzalez Maria Guadalupe",
    "wof:placetype":"venue"
},
  "geometry": {"coordinates":[-15.4207401276,28.1119556427],"type":"Point"}
}