{
  "type": "Feature",
  "properties": {
    "addr:full":"Calle de Arrieta Emilio, 6 Bilbao Vizcaya 48012",
    "addr:housenumber":"6",
    "addr:postcode":"48012",
    "addr:street":"Calle De Arrieta Emilio",
    "iso:country":"ES",
    "sg:address":"Calle de Arrieta Emilio, 6",
    "sg:city":"Bilbao",
    "sg:orig_category":"Alimentaci\u00d3n General (al Por Menor)",
    "sg:phone":"+34 944 22 30 08",
    "sg:postcode":"48012",
    "sg:province":"Vizcaya",
    "wof:name":"Gaitzerdi Teatro S.l.",
    "wof:placetype":"venue"
},
  "geometry": {"coordinates":[-2.9389111996,43.2522659302],"type":"Point"}
}