{
  "type": "Feature",
  "properties": {
    "addr:full":"Av Alacant, 84 Ondara Alicante 03760",
    "addr:housenumber":"84",
    "addr:postcode":"03760",
    "addr:street":"Alacant",
    "iso:country":"ES",
    "sg:address":"Av Alacant, 84",
    "sg:city":"Ondara",
    "sg:orig_category":"Carnicer\u00cdas, Carnicer\u00cdas",
    "sg:phone":"+34 966 47 63 72",
    "sg:postcode":"03760",
    "sg:province":"Alicante",
    "wof:name":"Carnes Pere Pere S.l.",
    "wof:placetype":"venue"
},
  "geometry": {"coordinates":[0.0219930001,38.822013855],"type":"Point"}
}