{
  "type": "Feature",
  "properties": {
    "iso:country":"ES",
    "sg:address":"Carr Alcala De Chivert, 29",
    "sg:city":"Mas Dels Frares",
    "sg:orig_category":"Jardiner\u00cdas, Vegetales, Art\u00cdculos De Jardiner\u00cda (al Por Menor)",
    "sg:phone":"+34 964 39 47 97",
    "sg:postcode":"12560",
    "sg:province":"Castell\u00f3n",
    "wof:name":"Campos Llobregat Guillermo Ivan",
    "wof:placetype":"venue"
},
  "geometry": {"coordinates":[0.0590550005,40.0523414612],"type":"Point"}
}