{
  "type": "Feature",
  "properties": {
    "iso:country":"ES",
    "sg:address":"Carrer de Constitucio, 118",
    "sg:city":"Barcelona",
    "sg:orig_category":"Alimentaci\u00d3n General (al Por Menor)",
    "sg:phone":"+34 933 32 58 48",
    "sg:postcode":"08014",
    "sg:province":"Barcelona",
    "wof:name":"Montbrio Marce Jose",
    "wof:placetype":"venue"
},
  "geometry": {"coordinates":[2.133936882,41.3694953918],"type":"Point"}
}