{
  "type": "Feature",
  "properties": {
    "iso:country":"ES",
    "sg:address":"Via Dos Castillas (de Las), 33",
    "sg:city":"Pozuelo De Alarcon",
    "sg:orig_category":"Electrodom\u00c9sticos (al Por Menor)",
    "sg:phone":"+34 915 59 42 20",
    "sg:postcode":"28224",
    "sg:province":"Madrid",
    "sg:website":"www.albatroscaterring.com",
    "wof:name":"Albatros Catering S.l.",
    "wof:placetype":"venue"
},
  "geometry": {"coordinates":[-3.7855107784,40.4401626587],"type":"Point"}
}