{
  "type": "Feature",
  "properties": {
    "addr:full":"Cmno Zabalegui, S/n Zulueta Navarra 31470",
    "addr:housenumber":"s / n",
    "addr:postcode":"31470",
    "addr:street":"Cmno Zabalegui",
    "iso:country":"ES",
    "sg:address":"Cmno Zabalegui, S/n",
    "sg:city":"Zulueta",
    "sg:orig_category":"Ferreter\u00cda (diversos)",
    "sg:phone":"+34 948 31 70 79",
    "sg:postcode":"31470",
    "sg:province":"Navarra",
    "wof:name":"C.a.t.zulueta S.l.",
    "wof:placetype":"venue"
},
  "geometry": {"coordinates":[-1.5478279591,42.7379150391],"type":"Point"}
}