{
  "type": "Feature",
  "properties": {
    "addr:full":"Calle de Esperanto, 18 Benidorm Alicante 03500",
    "addr:housenumber":"18",
    "addr:postcode":"03500",
    "addr:street":"Calle De Esperanto",
    "iso:country":"ES",
    "sg:address":"Calle de Esperanto, 18",
    "sg:city":"Benidorm",
    "sg:orig_category":"Inmobiliaria (agencias)",
    "sg:phone":"+34 966 81 27 67",
    "sg:postcode":"03500",
    "sg:province":"Alicante",
    "sg:website":"www.villasdelsur.com",
    "wof:name":"Grupo Inmobiliario Villas Del Sur S.l.",
    "wof:placetype":"venue"
},
  "geometry": {"coordinates":[-0.1217890009,38.5405731201],"type":"Point"}
}