{
  "type": "Feature",
  "properties": {
    "iso:country":"ES",
    "sg:address":"Rond Pedro Iv, 29",
    "sg:city":"Burriana",
    "sg:orig_category":"Carnicer\u00cdas, Carnicer\u00cdas",
    "sg:phone":"+34 964 51 38 27",
    "sg:postcode":"12530",
    "sg:province":"Castell\u00f3n",
    "wof:name":"Vilar Vidal Vicente Ramon",
    "wof:placetype":"venue"
},
  "geometry": {"coordinates":[-0.0852660015,39.8894195557],"type":"Point"}
}