{
  "type": "Feature",
  "properties": {
    "addr:full":"Carr Fatima, 3 Limits Girona 17709",
    "addr:housenumber":"3",
    "addr:postcode":"17709",
    "addr:street":"Carr Fatima",
    "iso:country":"ES",
    "sg:address":"Carr Fatima, 3",
    "sg:city":"Limits",
    "sg:orig_category":"Deportes Y Programas De Aventura",
    "sg:phone":"+34 972 55 55 23",
    "sg:postcode":"17709",
    "sg:province":"Girona",
    "wof:name":"Els Limits Mestral S.a.",
    "wof:placetype":"venue"
},
  "geometry": {"coordinates":[2.8643319607,42.4608459473],"type":"Point"}
}