{
  "type": "Feature",
  "properties": {
    "addr:full":"Grup Paz (la), 40 Vilalba Lugo 27800",
    "addr:postcode":"27800",
    "iso:country":"ES",
    "sg:address":"Grup Paz (la), 40",
    "sg:city":"Vilalba",
    "sg:orig_category":"Transportes Por V\u00cdas Navegables",
    "sg:phone":"+34 982 51 00 56",
    "sg:postcode":"27800",
    "sg:province":"Lugo",
    "wof:name":"Montenegro Rey Dolores",
    "wof:placetype":"venue"
},
  "geometry": {"coordinates":[-7.6808657646,43.2923164368],"type":"Point"}
}