{
  "type": "Feature",
  "properties": {
    "addr:full":"Kale Nagusia, 60 Azkoitia Guip\u00f9zcoa 20720",
    "addr:housenumber":"60",
    "addr:postcode":"20720",
    "addr:street":"Kale Nagusia;Guipu\u0300Zcoa",
    "iso:country":"ES",
    "sg:address":"Kale Nagusia, 60",
    "sg:city":"Azkoitia",
    "sg:orig_category":"Carnicer\u00cdas, Carnicer\u00cdas",
    "sg:phone":"+34 943 85 30 92",
    "sg:postcode":"20720",
    "sg:province":"Guip\u00f9zcoa",
    "wof:name":"Victor Larra\u00f1aga Aramendi",
    "wof:placetype":"venue"
},
  "geometry": {"coordinates":[-2.3134639263,43.1762886047],"type":"Point"}
}