{
  "type": "Feature",
  "properties": {
    "iso:country":"ES",
    "sg:address":"Pg Manuel Girona, 16",
    "sg:city":"Barcelona",
    "sg:classifiers":[
        {
            "category":"Autos & Motor Vehicles",
            "subcategory":"Automobile Sales",
            "type":"Retail Goods"
        }
    ],
    "sg:phone":"+34 932 04 51 54",
    "sg:postcode":"08034",
    "sg:province":"Barcelona",
    "sg:website":"www.mayordegracia.com",
    "wof:name":"Vallejo Caro Jose Rafael",
    "wof:placetype":"venue"
},
  "geometry": {"coordinates":[2.1214621067,41.3901596069],"type":"Point"}
}