{
  "type": "Feature",
  "properties": {
    "addr:full":"Calle de Puerta Osuna, 77 Arahal Sevilla 41600",
    "addr:housenumber":"77",
    "addr:postcode":"41600",
    "addr:street":"Calle De Puerta Osuna",
    "iso:country":"ES",
    "sg:address":"Calle de Puerta Osuna, 77",
    "sg:city":"Arahal",
    "sg:orig_category":"Molduras, Junquillos, Listones Y Molduras Perforadas",
    "sg:phone":"+34 954 84 03 02",
    "sg:postcode":"41600",
    "sg:province":"Sevilla",
    "wof:name":"Baco Fria Bernardo",
    "wof:placetype":"venue"
},
  "geometry": {"coordinates":[-5.5409827232,37.2613830566],"type":"Point"}
}