{
  "type": "Feature",
  "properties": {
    "addr:full":"Ctra. Jaen, 20 Albacete Albacete 02006",
    "addr:housenumber":"20",
    "addr:postcode":"02006",
    "addr:street":"Ctra. Jaen",
    "iso:country":"ES",
    "sg:address":"Ctra. Jaen, 20",
    "sg:city":"Albacete",
    "sg:orig_category":"Caf\u00c9s, Bares, Cervecer\u00cdas",
    "sg:phone":"+34 967 23 62 72",
    "sg:postcode":"02006",
    "sg:province":"Albacete",
    "wof:name":"Jimenez Cerdan Natalia",
    "wof:placetype":"venue"
},
  "geometry": {"coordinates":[-1.8730750084,38.9939079285],"type":"Point"}
}