{
  "type": "Feature",
  "properties": {
    "iso:country":"ES",
    "sg:address":"Calle de Doctor Jose Juan Megias, 2",
    "sg:city":"Palmas De Gran Canaria",
    "sg:orig_category":"M\u00c9dicos: Cirug\u00cda Pl\u00c1stica, Reconstructiva Y Est\u00c9tica",
    "sg:phone":"+34 928 23 07 15",
    "sg:postcode":"35005",
    "sg:province":"Las Palmas",
    "wof:name":"Deniz Hernandez Victor",
    "wof:placetype":"venue"
},
  "geometry": {"coordinates":[-15.42923069,28.1264076233],"type":"Point"}
}