{
  "type": "Feature",
  "properties": {
    "addr:full":"Calle de Panaderos, 28 Valladolid Valladolid 47004",
    "addr:housenumber":"28",
    "addr:postcode":"47004",
    "addr:street":"Calle De Panaderos",
    "iso:country":"ES",
    "sg:address":"Calle de Panaderos, 28",
    "sg:city":"Valladolid",
    "sg:orig_category":"Centros De Educaci\u00d3n Especial",
    "sg:phone":"+34 983 30 92 43",
    "sg:postcode":"47004",
    "sg:province":"Valladolid",
    "wof:name":"Colegio Publico De Infantil Y Primaria Cardenal Mendoza",
    "wof:placetype":"venue"
},
  "geometry": {"coordinates":[-4.7230520248,41.6467971802],"type":"Point"}
}