{
  "type": "Feature",
  "properties": {
    "addr:full":"Calle de Mercedes (las), 21 Arenas -areeta Vizcaya 48930",
    "addr:housenumber":"21;areeta",
    "addr:postcode":"48930",
    "addr:street":"Calle De Mercedes Las",
    "iso:country":"ES",
    "sg:address":"Calle de Mercedes (las), 21",
    "sg:city":"Arenas -areeta",
    "sg:orig_category":"Complementos De Vestir (al Por Menor)",
    "sg:phone":"+34 944 80 12 71",
    "sg:postcode":"48930",
    "sg:province":"Vizcaya",
    "sg:website":"www.benetton.com",
    "wof:name":"Bencom Retail Susursal En Espa\u00d1a",
    "wof:placetype":"venue"
},
  "geometry": {"coordinates":[-3.0135979652,43.3267822266],"type":"Point"}
}