{
  "type": "Feature",
  "properties": {
    "addr:full":"Pase Principe Asturias, 59 Tobarra Albacete 02500",
    "addr:housenumber":"59",
    "addr:postcode":"02500",
    "addr:street":"Asturias",
    "iso:country":"ES",
    "sg:address":"Pase Principe Asturias, 59",
    "sg:city":"Tobarra",
    "sg:orig_category":"Peluquer\u00cdas, Peluquer\u00cda Mixta",
    "sg:phone":"+34 967 32 84 86",
    "sg:postcode":"02500",
    "sg:province":"Albacete",
    "wof:name":"Navarro Alca\u00f1iz Jose",
    "wof:placetype":"venue"
},
  "geometry": {"coordinates":[-1.6881289482,38.5952568054],"type":"Point"}
}