{
  "type": "Feature",
  "properties": {
    "iso:country":"ES",
    "sg:address":"Avda Trujillos, S/n",
    "sg:city":"Montillana",
    "sg:orig_category":"Empresas De Desmonte",
    "sg:phone":"+34 958 39 22 29",
    "sg:postcode":"18566",
    "sg:province":"Granada",
    "wof:name":"Bolivar Bolivar Miguel",
    "wof:placetype":"venue"
},
  "geometry": {"coordinates":[-3.676858902,37.4998245239],"type":"Point"}
}