{
  "type": "Feature",
  "properties": {
    "addr:full":"Av Sant Francesc, 19 Girona Girona 17001",
    "addr:housenumber":"19",
    "addr:postcode":"17001",
    "addr:street":"Av Sant Francesc",
    "iso:country":"ES",
    "sg:address":"Av Sant Francesc, 19",
    "sg:city":"Girona",
    "sg:orig_category":"Organismos De Turismo",
    "sg:phone":"+34 972 22 15 70",
    "sg:postcode":"17001",
    "sg:province":"Girona",
    "wof:name":"Patronat De Turisme Costa Brava Girona S.a.",
    "wof:placetype":"venue"
},
  "geometry": {"coordinates":[2.8214290142,41.9823112488],"type":"Point"}
}