{
  "type": "Feature",
  "properties": {
    "iso:country":"ES",
    "sg:address":"Calle de Santa Trinitat, 6",
    "sg:city":"Carpesa",
    "sg:orig_category":"Muebles, Minoristas",
    "sg:phone":"+34 961 85 05 09",
    "sg:postcode":"46016",
    "sg:province":"Valencia",
    "wof:name":"Muebles Bayarri C.b.",
    "wof:placetype":"venue"
},
  "geometry": {"coordinates":[-0.377169013,39.5163116455],"type":"Point"}
}