{
  "type": "Feature",
  "properties": {
    "iso:country":"ES",
    "sg:address":"Calle de San Marcelo, 22",
    "sg:city":"Madrid",
    "sg:orig_category":"Contables",
    "sg:phone":"+34 914 03 87 06",
    "sg:postcode":"28017",
    "sg:province":"Madrid",
    "wof:name":"Romero Delgado Maria",
    "wof:placetype":"venue"
},
  "geometry": {"coordinates":[-3.6571509838,40.426864624],"type":"Point"}
}