{
  "type": "Feature",
  "properties": {
    "addr:full":"Grup Edificio Compostela, 59 Sevilla Sevilla 41020",
    "addr:housenumber":"59",
    "addr:postcode":"41020",
    "iso:country":"ES",
    "sg:address":"Grup Edificio Compostela, 59",
    "sg:city":"Sevilla",
    "sg:orig_category":"Asesor\u00cda Sobre Comunicaci\u00d3n De Empresas",
    "sg:phone":"+34 954 40 67 00",
    "sg:postcode":"41020",
    "sg:province":"Sevilla",
    "wof:name":"Cantos Pereira Consultores S.c.a",
    "wof:placetype":"venue"
},
  "geometry": {"coordinates":[-5.9333291054,37.4165763855],"type":"Point"}
}