{
  "type": "Feature",
  "properties": {
    "iso:country":"ES",
    "sg:address":"Trva Bouzas Servicio Portuario, 81",
    "sg:city":"Vigo",
    "sg:orig_category":"Navegaci\u00d3n (equipos Fluviales)",
    "sg:phone":"+34 986 20 06 65",
    "sg:postcode":"36208",
    "sg:province":"Pontevedra",
    "wof:name":"Alay Ondo S.l.",
    "wof:placetype":"venue"
},
  "geometry": {"coordinates":[-8.7550001144,42.2251739502],"type":"Point"}
}