{
  "type": "Feature",
  "properties": {
    "iso:country":"ES",
    "sg:address":"Calle de Martires, 1",
    "sg:city":"Calahorra",
    "sg:orig_category":"Abogados",
    "sg:phone":"+34 941 14 66 45",
    "sg:postcode":"26500",
    "sg:province":"La Rioja",
    "wof:name":"Martinez Portillo Subero Luis",
    "wof:placetype":"venue"
},
  "geometry": {"coordinates":[-1.9630119801,42.3024368286],"type":"Point"}
}