{
  "type": "Feature",
  "properties": {
    "addr:full":"Romero, 2 Peguera Islas Baleares 07160",
    "addr:housenumber":"2",
    "addr:postcode":"07160",
    "addr:street":"Romero",
    "iso:country":"ES",
    "sg:address":"Romero, 2",
    "sg:city":"Peguera",
    "sg:orig_category":"Promotores Constructores",
    "sg:phone":"+34 971 68 52 45",
    "sg:postcode":"07160",
    "sg:province":"Islas Baleares",
    "wof:name":"Pascual Chacon Y Alonso Martinez S.l.",
    "wof:placetype":"venue"
},
  "geometry": {"coordinates":[2.4442300797,39.5373725891],"type":"Point"}
}