{
  "type": "Feature",
  "properties": {
    "iso:country":"ES",
    "sg:address":"Carrer de Arquimedes, 16",
    "sg:city":"Barbera Valles",
    "sg:orig_category":"Escayola Y Productos De Escayola (fabricaci\u00d3n, Al Por Mayor)",
    "sg:phone":"+34 937 18 24 71",
    "sg:postcode":"08210",
    "sg:province":"Barcelona",
    "wof:name":"Eurocomercial Yesera Del Valles S.l.",
    "wof:placetype":"venue"
},
  "geometry": {"coordinates":[2.1313750744,41.5104141235],"type":"Point"}
}