{
  "type": "Feature",
  "properties": {
    "iso:country":"ES",
    "sg:address":"Calle de Morrones, 6",
    "sg:city":"Majadahonda",
    "sg:orig_category":"Centros Empresariales",
    "sg:phone":"+34 916 34 40 26",
    "sg:postcode":"28220",
    "sg:province":"Madrid",
    "wof:name":"Transmigas Construcciones S.a.",
    "wof:placetype":"venue"
},
  "geometry": {"coordinates":[-3.8748531342,40.4718208313],"type":"Point"}
}