{
  "type": "Feature",
  "properties": {
    "iso:country":"ES",
    "sg:address":"Av Sant Julia, S/n",
    "sg:city":"Granollers",
    "sg:orig_category":"Fabricaci\u00d3n De Moldes Y Modelos",
    "sg:phone":"+34 938 49 60 66",
    "sg:postcode":"08403",
    "sg:province":"Barcelona",
    "sg:website":"www.tallinsa.com",
    "wof:name":"Tallin S.a.",
    "wof:placetype":"venue"
},
  "geometry": {"coordinates":[2.2729549408,41.576335907],"type":"Point"}
}