{
  "type": "Feature",
  "properties": {
    "iso:country":"ES",
    "sg:address":"Calle de Silvano Izquierdo, 1",
    "sg:city":"Astudillo",
    "sg:orig_category":"Notarios",
    "sg:phone":"+34 979 82 21 90",
    "sg:postcode":"34450",
    "sg:province":"Palencia",
    "wof:name":"Amengua Villalonga Miguel",
    "wof:placetype":"venue"
},
  "geometry": {"coordinates":[-4.294936657,42.1914710999],"type":"Point"}
}