{
  "type": "Feature",
  "properties": {
    "iso:country":"ES",
    "sg:address":"Martires, 15",
    "sg:city":"Pobla Mafumet",
    "sg:orig_category":"Electricidad: Instaladores",
    "sg:phone":"+34 977 84 04 18",
    "sg:postcode":"43140",
    "sg:province":"Tarragona",
    "wof:name":"Giralt Vallve Martin",
    "wof:placetype":"venue"
},
  "geometry": {"coordinates":[1.2094299793,41.1871566772],"type":"Point"}
}