{
  "type": "Feature",
  "properties": {
    "addr:full":"Comandante Herrera, S/n San Pedro Gaillos Segovia 40389",
    "addr:housenumber":"s / n",
    "addr:postcode":"40389",
    "addr:street":"Comandante Herrera",
    "iso:country":"ES",
    "sg:address":"Comandante Herrera, S/n",
    "sg:city":"San Pedro Gaillos",
    "sg:orig_category":"Iglesia Cat\u00d3lica",
    "sg:phone":"+34 921 53 10 06",
    "sg:postcode":"40389",
    "sg:province":"Segovia",
    "wof:name":"Obispado Segovia",
    "wof:placetype":"venue"
},
  "geometry": {"coordinates":[-3.8089439869,41.2269515991],"type":"Point"}
}