{
  "type": "Feature",
  "properties": {
    "addr:full":"Calle de Diego De Vargas, 22 Madrid Madrid 28022",
    "addr:housenumber":"22",
    "addr:postcode":"madrid;28022",
    "addr:street":"Calle De Diego De Vargas",
    "iso:country":"ES",
    "sg:address":"Calle de Diego De Vargas, 22",
    "sg:city":"Madrid",
    "sg:orig_category":"Farmacias (repartici\u00d3n Y Al Por Mayor)",
    "sg:phone":"+34 913 20 83 01",
    "sg:postcode":"28022",
    "sg:province":"Madrid",
    "wof:name":"Azul De Distribuciones Andaluzas S.l.",
    "wof:placetype":"venue"
},
  "geometry": {"coordinates":[-3.6127030849,40.4487113953],"type":"Point"}
}