{
  "type": "Feature",
  "properties": {
    "iso:country":"ES",
    "sg:address":"Calle de San Antonio Abad, 55",
    "sg:city":"Zaragoza",
    "sg:orig_category":"Empresas De Carpinter\u00cda",
    "sg:phone":"+34 976 33 95 98",
    "sg:postcode":"50010",
    "sg:province":"Zaragoza",
    "wof:name":"Lainez Felipe Sergio",
    "wof:placetype":"venue"
},
  "geometry": {"coordinates":[-0.9077051282,41.6547279358],"type":"Point"}
}