{
  "type": "Feature",
  "properties": {
    "iso:country":"ES",
    "sg:address":"Calle de Marques De La Valdavia (del), 63",
    "sg:city":"Alcobendas",
    "sg:orig_category":"Sociedades, Compa\u00d1\u00cdas Aseguradoras",
    "sg:phone":"+34 916 57 46 40",
    "sg:postcode":"28100",
    "sg:province":"Madrid",
    "sg:website":"www.mmtseguros.es",
    "wof:name":"Mutua Mmt Seguros",
    "wof:placetype":"venue"
},
  "geometry": {"coordinates":[-3.6421730518,40.5441856384],"type":"Point"}
}