{
  "type": "Feature",
  "properties": {
    "iso:country":"ES",
    "sg:address":"Calle de Limon Verde, 34",
    "sg:city":"Algete",
    "sg:orig_category":"Centros Empresariales",
    "sg:phone":"+34 916 28 26 15",
    "sg:postcode":"28110",
    "sg:province":"Madrid",
    "wof:name":"Romero Salinas Blanca Ines",
    "wof:placetype":"venue"
},
  "geometry": {"coordinates":[-3.4984519482,40.5984191895],"type":"Point"}
}