{
  "type": "Feature",
  "properties": {
    "addr:full":"Cabezo San Agustin, S/n Cehegin Murcia 30430",
    "addr:postcode":"30430",
    "addr:street":"San Agustin S / N",
    "iso:country":"ES",
    "sg:address":"Cabezo San Agustin, S/n",
    "sg:city":"Cehegin",
    "sg:orig_category":"Contenedores (mercanc\u00cdas)",
    "sg:phone":"+34 968 74 18 11",
    "sg:postcode":"30430",
    "sg:province":"Murcia",
    "wof:name":"Caparros Gimenez Ramon",
    "wof:placetype":"venue"
},
  "geometry": {"coordinates":[-1.791424036,38.0908889771],"type":"Point"}
}