{
  "type": "Feature",
  "properties": {
    "iso:country":"ES",
    "sg:address":"Calle de San Fernando, 1",
    "sg:city":"Santisteban Puerto",
    "sg:orig_category":"Telas Y Sedas (al Por Menor)",
    "sg:phone":"+34 953 40 20 56",
    "sg:postcode":"23250",
    "sg:province":"Ja\u00e9n",
    "wof:name":"Rubio Sevilla Jose",
    "wof:placetype":"venue"
},
  "geometry": {"coordinates":[-3.2065770626,38.2491340637],"type":"Point"}
}