{
  "type": "Feature",
  "properties": {
    "iso:country":"ES",
    "sg:address":"Calle de Heroes Alcazar De Toledo, 6",
    "sg:city":"Valladolid",
    "sg:orig_category":"Zapatos (al Por Menor)",
    "sg:phone":"+34 983 34 34 39",
    "sg:postcode":"47001",
    "sg:province":"Valladolid",
    "wof:name":"Uribarri Quintana Francisco De Borja",
    "wof:placetype":"venue"
},
  "geometry": {"coordinates":[-4.7293791771,41.6507301331],"type":"Point"}
}