{
  "type": "Feature",
  "properties": {
    "iso:country":"ES",
    "sg:address":"Calle de Covarrubias, 6",
    "sg:city":"Burgos",
    "sg:orig_category":"Asesor\u00cda De Formaci\u00d3n Y Gesti\u00d3n De Personal",
    "sg:phone":"+34 947 27 37 76",
    "sg:postcode":"09002",
    "sg:province":"Burgos",
    "wof:name":"Chavarino Torre Fuente S.l.",
    "wof:placetype":"venue"
},
  "geometry": {"coordinates":[-3.6724648476,42.3253631592],"type":"Point"}
}