{
  "type": "Feature",
  "properties": {
    "addr:full":"Estacion, 12 Tuilla Asturias 33935",
    "addr:housenumber":"12",
    "addr:postcode":"33935",
    "addr:street":"Estacion;Asturias",
    "iso:country":"ES",
    "sg:address":"Estacion, 12",
    "sg:city":"Tuilla",
    "sg:orig_category":"Peluqueros: De Se\u00d1oras",
    "sg:phone":"+34 985 65 10 34",
    "sg:postcode":"33935",
    "sg:province":"Asturias",
    "wof:name":"Gonzalez Gonzalez Maria Luisa",
    "wof:placetype":"venue"
},
  "geometry": {"coordinates":[-5.6429262161,43.3284378052],"type":"Point"}
}