{
  "type": "Feature",
  "properties": {
    "iso:country":"ES",
    "sg:address":"Cno Loma De San Julian, S/n",
    "sg:city":"Malaga",
    "sg:orig_category":"Bebidas",
    "sg:phone":"+34 952 24 93 00",
    "sg:postcode":"29...",
    "sg:province":"M\u00e1laga",
    "wof:name":"Refrescos Envasados Del Sur S.a.",
    "wof:placetype":"venue"
},
  "geometry": {"coordinates":[-4.476662159,36.6685714722],"type":"Point"}
}