{
  "type": "Feature",
  "properties": {
    "addr:full":"Pase Zorrilla, 3 Valladolid Valladolid 47007",
    "addr:housenumber":"3",
    "addr:postcode":"47007",
    "addr:street":"Zorrilla",
    "iso:country":"ES",
    "sg:address":"Pase Zorrilla, 3",
    "sg:city":"Valladolid",
    "sg:orig_category":"Prot\u00c9sicos Dentales",
    "sg:phone":"+34 983 27 00 04",
    "sg:postcode":"47007",
    "sg:province":"Valladolid",
    "wof:name":"Mardones Ugidos Jose Maria",
    "wof:placetype":"venue"
},
  "geometry": {"coordinates":[-4.734787941,41.6437759399],"type":"Point"}
}