{
  "type": "Feature",
  "properties": {
    "addr:full":"Calle de Ramon Gomez Sempere, 17 Alacant Alicante 03008",
    "addr:housenumber":"17",
    "addr:postcode":"03008",
    "addr:street":"Calle De Ramon Gomez Sempere",
    "iso:country":"ES",
    "sg:address":"Calle de Ramon Gomez Sempere, 17",
    "sg:city":"Alacant",
    "sg:orig_category":"Cajas De Ahorro",
    "sg:phone":"+34 965 10 66 64",
    "sg:postcode":"03008",
    "sg:province":"Alicante",
    "wof:name":"Caja De Ahorros Del Mediterraneo",
    "wof:placetype":"venue"
},
  "geometry": {"coordinates":[-0.5171380043,38.3277549744],"type":"Point"}
}