{
  "type": "Feature",
  "properties": {
    "addr:full":"Calle de Gara\u00d1a\u00d1a, S/n Costa Del Silencio Santa Cruz De Tenerife 38630",
    "addr:housenumber":"s / n",
    "addr:postcode":"38630",
    "addr:street":"Calle De Garan\u0303An\u0303A",
    "iso:country":"ES",
    "sg:address":"Calle de Gara\u00d1a\u00d1a, S/n",
    "sg:city":"Costa Del Silencio",
    "sg:orig_category":"Fisioterapia",
    "sg:phone":"+34 922 78 52 04",
    "sg:postcode":"38630",
    "sg:province":"Santa Cruz De Tenerife",
    "wof:name":"Robson  David",
    "wof:placetype":"venue"
},
  "geometry": {"coordinates":[-16.6499900818,28.0154495239],"type":"Point"}
}