{
  "type": "Feature",
  "properties": {
    "addr:full":"Plaz Ventas, 13 Bu\u00f1ol Valencia 46360",
    "addr:housenumber":"13",
    "addr:postcode":"46360",
    "addr:street":"Plaz Ventas",
    "iso:country":"ES",
    "sg:address":"Plaz Ventas, 13",
    "sg:city":"Bu\u00f1ol",
    "sg:orig_category":"Estancos",
    "sg:phone":"+34 962 50 23 16",
    "sg:postcode":"46360",
    "sg:province":"Valencia",
    "wof:name":"Egea Temporal Maria Amparo",
    "wof:placetype":"venue"
},
  "geometry": {"coordinates":[-0.7906309962,39.4240646362],"type":"Point"}
}