{
  "type": "Feature",
  "properties": {
    "addr:full":"Carrer de Sindicat, 5 Palma Islas Baleares 07002",
    "addr:housenumber":"5",
    "addr:postcode":"07002",
    "addr:street":"Carrer De Sindicat",
    "iso:country":"ES",
    "sg:address":"Carrer de Sindicat, 5",
    "sg:city":"Palma",
    "sg:orig_category":"Perfumer\u00cda (al Por Menor)",
    "sg:phone":"+34 971 72 25 26",
    "sg:postcode":"07002",
    "sg:province":"Islas Baleares",
    "wof:name":"Inversiones Muller S.a.",
    "wof:placetype":"venue"
},
  "geometry": {"coordinates":[2.6522819996,39.5709724426],"type":"Point"}
}