{
  "type": "Feature",
  "properties": {
    "iso:country":"ES",
    "sg:address":"Calle de Jose Arcones Gil, 15",
    "sg:city":"Madrid",
    "sg:orig_category":"Ingeniero",
    "sg:phone":"+34 913 67 57 09",
    "sg:postcode":"28017",
    "sg:province":"Madrid",
    "sg:website":"www.paisajismo.com",
    "wof:name":"Alida Ingenieria Del Medio S.l.",
    "wof:placetype":"venue"
},
  "geometry": {"coordinates":[-3.6389703751,40.4359588623],"type":"Point"}
}