{
  "type": "Feature",
  "properties": {
    "addr:full":"Av Cardenal Vidal I Barraquer, 47 Reus Tarragona 43205",
    "addr:housenumber":"47",
    "addr:postcode":"43205",
    "addr:street":"Av Cardenal Vidal I Barraquer",
    "iso:country":"ES",
    "sg:address":"Av Cardenal Vidal I Barraquer, 47",
    "sg:city":"Reus",
    "sg:orig_category":"Librer\u00cdas",
    "sg:phone":"+34 977 75 52 14",
    "sg:postcode":"43205",
    "sg:province":"Tarragona",
    "wof:name":"Figueras Masso Jose Maria",
    "wof:placetype":"venue"
},
  "geometry": {"coordinates":[1.1081479788,41.1479568481],"type":"Point"}
}