{
  "type": "Feature",
  "properties": {
    "iso:country":"ES",
    "sg:address":"Calle de Victor De La Serna, 28",
    "sg:city":"Madrid",
    "sg:classifiers":[
        {
            "category":"Personal",
            "subcategory":"Barber",
            "type":"Services"
        }
    ],
    "sg:phone":"+34 915 19 71 75",
    "sg:postcode":"28016",
    "sg:province":"Madrid",
    "sg:tags":[
        "caballeros",
        "de",
        "peluqueros"
    ],
    "wof:name":"Mu\u00f1oz Martin Jorge",
    "wof:placetype":"venue"
},
  "geometry": {"coordinates":[-3.6714169979,40.4540290833],"type":"Point"}
}