{
  "type": "Feature",
  "properties": {
    "iso:country":"ES",
    "sg:address":"Av Raval Del Carme, 43",
    "sg:city":"Tarrega",
    "sg:orig_category":"Contenedores (mercanc\u00cdas)",
    "sg:phone":"+34 973 31 02 22",
    "sg:postcode":"25300",
    "sg:province":"Lleida",
    "wof:name":"Gatnau Giribet Ramon",
    "wof:placetype":"venue"
},
  "geometry": {"coordinates":[1.1422100067,41.6498565674],"type":"Point"}
}