{
  "type": "Feature",
  "properties": {
    "addr:full":"Plaz Mayor, 12 Palencia Palencia 34001",
    "addr:housenumber":"12",
    "addr:postcode":"34001",
    "addr:street":"Plaz Mayor",
    "iso:country":"ES",
    "sg:address":"Plaz Mayor, 12",
    "sg:city":"Palencia",
    "sg:orig_category":"Caf\u00c9s, Bares, Cervecer\u00cdas",
    "sg:phone":"+34 979 75 28 92",
    "sg:postcode":"34001",
    "sg:province":"Palencia",
    "wof:name":"Gil De Vena Mariano",
    "wof:placetype":"venue"
},
  "geometry": {"coordinates":[-4.5340390205,42.0125083923],"type":"Point"}
}