{
  "type": "Feature",
  "properties": {
    "addr:full":"Carrer de Reis Catolics, S/n Sabadell Barcelona 08204",
    "addr:housenumber":"s",
    "addr:postcode":"08204",
    "addr:street":"Carrer De Reis Catolics;/ N",
    "iso:country":"ES",
    "sg:address":"Carrer de Reis Catolics, S/n",
    "sg:city":"Sabadell",
    "sg:orig_category":"Carnicer\u00cdas, Carnicer\u00cdas",
    "sg:phone":"+34 937 11 82 52",
    "sg:postcode":"08204",
    "sg:province":"Barcelona",
    "wof:name":"Ramasisa S.l.",
    "wof:placetype":"venue"
},
  "geometry": {"coordinates":[2.1135950089,41.5263214111],"type":"Point"}
}