{
  "type": "Feature",
  "properties": {
    "addr:full":"Cmno Ronda (de), 83 Granada Granada 18004",
    "addr:housenumber":"83",
    "addr:postcode":"18004",
    "addr:street":"Cmno Ronda De",
    "iso:country":"ES",
    "sg:address":"Cmno Ronda (de), 83",
    "sg:city":"Granada",
    "sg:orig_category":"Fabricaci\u00d3n, Venta De Productos Base Farmac\u00c9uticos",
    "sg:phone":"+34 958 25 48 43",
    "sg:postcode":"18004",
    "sg:province":"Granada",
    "wof:name":"Nu\u00f1ez Gonzalez Fernando",
    "wof:placetype":"venue"
},
  "geometry": {"coordinates":[-3.6063909531,37.1707420349],"type":"Point"}
}