{
  "type": "Feature",
  "properties": {
    "iso:country":"ES",
    "sg:address":"Calle de Doctor Gomez Ulla, 2",
    "sg:city":"Madrid",
    "sg:orig_category":"Tintes (fabricaci\u00d3n, Al Por Mayor)",
    "sg:phone":"+34 917 26 22 67",
    "sg:postcode":"28028",
    "sg:province":"Madrid",
    "wof:name":"Mu\u00f1oz Ballesteros Jose",
    "wof:placetype":"venue"
},
  "geometry": {"coordinates":[-3.6677763462,40.4299659729],"type":"Point"}
}