{
  "type": "Feature",
  "properties": {
    "iso:country":"ES",
    "sg:address":"Carr Tenor Alonso, 58",
    "sg:city":"Godella",
    "sg:orig_category":"Caf\u00c9s, Bares, Cervecer\u00cdas",
    "sg:phone":"+34 963 64 65 95",
    "sg:postcode":"46110",
    "sg:province":"Valencia",
    "wof:name":"Carot Arago Manuel",
    "wof:placetype":"venue"
},
  "geometry": {"coordinates":[-0.4115790129,39.5183105469],"type":"Point"}
}