{
  "type": "Feature",
  "properties": {
    "iso:country":"ES",
    "sg:address":"Garc\u00eda Moreno, 2",
    "sg:city":"Orgiva",
    "sg:orig_category":"Zapatos (al Por Menor)",
    "sg:phone":"+34 958 78 53 92",
    "sg:postcode":"18400",
    "sg:province":"Granada",
    "wof:name":"Castillo Galvez Juan",
    "wof:placetype":"venue"
},
  "geometry": {"coordinates":[-3.4239830971,36.901348114],"type":"Point"}
}