{
  "type": "Feature",
  "properties": {
    "iso:country":"ES",
    "sg:address":"Avda Canarias, 403",
    "sg:city":"Vecindario",
    "sg:orig_category":"Abogados",
    "sg:phone":"+34 928 75 73 22",
    "sg:postcode":"35110",
    "sg:province":"Las Palmas",
    "wof:name":"Rodriguez Romero Manuel",
    "wof:placetype":"venue"
},
  "geometry": {"coordinates":[-15.4472551346,27.8410434723],"type":"Point"}
}