{
  "type": "Feature",
  "properties": {
    "addr:full":"Calle de Alkolea, S/n Donostia-san Sebastian Guip\u00f9zcoa 20012",
    "addr:housenumber":"s / n",
    "addr:postcode":"20012",
    "addr:street":"Calle De Alkolea",
    "iso:country":"ES",
    "sg:address":"Calle de Alkolea, S/n",
    "sg:city":"Donostia-san Sebastian",
    "sg:orig_category":"M\u00c9dicos: Oftalmolog\u00cda",
    "sg:phone":"+34 943 27 26 99",
    "sg:postcode":"20012",
    "sg:province":"Guip\u00f9zcoa",
    "sg:website":"www.oftalmoquiron.com",
    "wof:name":"Centro Oftalmologico De Guipuzcoa S. A.",
    "wof:placetype":"venue"
},
  "geometry": {"coordinates":[-1.9730600119,43.3154716492],"type":"Point"}
}