{
  "type": "Feature",
  "properties": {
    "iso:country":"ES",
    "sg:address":"Plaz Do\u00d1a Ines De Osorio, 6",
    "sg:city":"Palencia",
    "sg:orig_category":"Carnicer\u00cdas, Carnicer\u00cdas",
    "sg:phone":"+34 979 70 16 09",
    "sg:postcode":"34001",
    "sg:province":"Palencia",
    "wof:name":"Jose Martin Luengo De Los Bueis Y Maria Lourdes Rodriguez Luengo Cdad",
    "wof:placetype":"venue"
},
  "geometry": {"coordinates":[-4.5359492302,42.0121688843],"type":"Point"}
}