{
  "type": "Feature",
  "properties": {
    "addr:full":"Avda San Lorenzo, 123 Monte Vedat Valencia 46901",
    "addr:housenumber":"123",
    "addr:postcode":"46901",
    "addr:street":"Avda San Lorenzo;Vedat",
    "iso:country":"ES",
    "sg:address":"Avda San Lorenzo, 123",
    "sg:city":"Monte Vedat",
    "sg:orig_category":"Peluquer\u00cdas, Peluquer\u00cda Mixta",
    "sg:phone":"+34 961 55 38 26",
    "sg:postcode":"46901",
    "sg:province":"Valencia",
    "wof:name":"Martinez Sanchez Teresa",
    "wof:placetype":"venue"
},
  "geometry": {"coordinates":[-0.4893130064,39.421081543],"type":"Point"}
}