{
  "type": "Feature",
  "properties": {
    "addr:full":"Carrer de La Rambla, 18 Barcelona Barcelona 08002",
    "addr:housenumber":"18",
    "addr:postcode":"08002",
    "addr:street":"Carrer De La Rambla",
    "iso:country":"ES",
    "sg:address":"Carrer de La Rambla, 18",
    "sg:city":"Barcelona",
    "sg:orig_category":"Equipo Y Material Deportivo Y De Actividades Invernales Y De Monta\u00d1a",
    "sg:phone":"+34 933 02 32 95",
    "sg:postcode":"08002",
    "sg:province":"Barcelona",
    "wof:name":"Club Lleuresport",
    "wof:placetype":"venue"
},
  "geometry": {"coordinates":[2.1764090061,41.3777656555],"type":"Point"}
}