{
  "type": "Feature",
  "properties": {
    "addr:full":"Calle de Lopez De Hoyos, 141 Madrid Madrid 28002",
    "addr:housenumber":"141",
    "addr:postcode":"28002",
    "addr:street":"Calle De Lopez De Hoyos",
    "iso:country":"ES",
    "sg:address":"Calle de Lopez De Hoyos, 141",
    "sg:city":"Madrid",
    "sg:orig_category":"Edici\u00d3n De Diarios, Revistas, Boletines",
    "sg:phone":"+34 917 44 03 95",
    "sg:postcode":"28002",
    "sg:province":"Madrid",
    "wof:name":"Bgo Editores S.l.",
    "wof:placetype":"venue"
},
  "geometry": {"coordinates":[-3.6693489552,40.4475402832],"type":"Point"}
}