{
  "type": "Feature",
  "properties": {
    "addr:full":"Ctra Comarcal, S/n S. Celoni Barcelona 08470",
    "addr:postcode":"08470",
    "addr:street":"Ctra Comarcal S / N S. Celoni Barcelona",
    "iso:country":"ES",
    "sg:address":"Ctra Comarcal, S/n",
    "sg:city":"S. Celoni",
    "sg:orig_category":"Comercio De Piezas De Recambio Y De Accesorios De Veh\u00cdculos, Veh\u00cdculos Industriales",
    "sg:phone":"+34 938 67 62 22",
    "sg:postcode":"08470",
    "sg:province":"Barcelona",
    "wof:name":"Range Motors S.l.",
    "wof:placetype":"venue"
},
  "geometry": {"coordinates":[2.463572979,41.7227363586],"type":"Point"}
}