{
  "type": "Feature",
  "properties": {
    "iso:country":"ES",
    "sg:address":"Avda Portugal (de), 184",
    "sg:city":"Ourense",
    "sg:orig_category":"Molduras, Junquillos, Listones Y Molduras Perforadas",
    "sg:phone":"+34 988 25 52 40",
    "sg:postcode":"32002",
    "sg:province":"Ourense",
    "wof:name":"Losada Conde Jose Alfonso",
    "wof:placetype":"venue"
},
  "geometry": {"coordinates":[-7.8693161011,42.3301048279],"type":"Point"}
}