{
  "type": "Feature",
  "properties": {
    "addr:full":"Av Meridiana, 382 Barcelona Barcelona 08030",
    "addr:housenumber":"382",
    "addr:postcode":"08030",
    "addr:street":"Meridiana",
    "iso:country":"ES",
    "sg:address":"Av Meridiana, 382",
    "sg:city":"Barcelona",
    "sg:orig_category":"M\u00c9dicos: Endocrinolog\u00cda Y Metabolismo",
    "sg:phone":"+34 933 11 73 02",
    "sg:postcode":"08030",
    "sg:province":"Barcelona",
    "wof:name":"Catala Berenguer Jose",
    "wof:placetype":"venue"
},
  "geometry": {"coordinates":[2.1837749481,41.4296607971],"type":"Point"}
}