{
  "type": "Feature",
  "properties": {
    "addr:full":"Calle de Villaverde, 28 Sevilla Sevilla 41006",
    "addr:housenumber":"28",
    "addr:postcode":"41006",
    "addr:street":"Calle De Villaverde",
    "iso:country":"ES",
    "sg:address":"Calle de Villaverde, 28",
    "sg:city":"Sevilla",
    "sg:orig_category":"Fabricaci\u00d3n De Cervezas",
    "sg:phone":"+34 954 64 37 81",
    "sg:postcode":"41006",
    "sg:province":"Sevilla",
    "wof:name":"Varon Aparicio Juan De Dios",
    "wof:placetype":"venue"
},
  "geometry": {"coordinates":[-5.9428224564,37.3707199097],"type":"Point"}
}