{
  "type": "Feature",
  "properties": {
    "iso:country":"ES",
    "sg:address":"Plaz Princi Jerez, 12",
    "sg:city":"Jerez De La Frontera",
    "sg:orig_category":"Farmacias",
    "sg:phone":"+34 956 34 19 13",
    "sg:postcode":"11406",
    "sg:province":"C\u00e1diz",
    "wof:name":"Botella Montolla Maria De Los Angeles",
    "wof:placetype":"venue"
},
  "geometry": {"coordinates":[-6.116918087,36.6822319031],"type":"Point"}
}