{
  "type": "Feature",
  "properties": {
    "addr:full":"San Lorentzo Auzoa, 60 O\u00f1ati Guip\u00f9zcoa 20560",
    "addr:housenumber":"60",
    "addr:postcode":"20560",
    "addr:street":"San Lorentzo Auzoa;Guipu\u0300Zcoa",
    "iso:country":"ES",
    "sg:address":"San Lorentzo Auzoa, 60",
    "sg:city":"O\u00f1ati",
    "sg:orig_category":"Fabricaci\u00d3n, Distribuci\u00d3n De Material Para La Climatizaci\u00d3n, Aireaci\u00d3n Y Ventilaci\u00d3n",
    "sg:phone":"+34 943 78 35 24",
    "sg:postcode":"20560",
    "sg:province":"Guip\u00f9zcoa",
    "sg:website":"www.hotzrefrigeracion.com",
    "wof:name":"Hotz Refrigeracion S.l.",
    "wof:placetype":"venue"
},
  "geometry": {"coordinates":[-2.4041359425,43.0341758728],"type":"Point"}
}