{
  "type": "Feature",
  "properties": {
    "addr:full":"Avda Malestroit, 4 Ramales Victoria Cantabria 39800",
    "addr:housenumber":"4",
    "addr:postcode":"39800",
    "addr:street":"Avda Malestroit",
    "iso:country":"ES",
    "sg:address":"Avda Malestroit, 4",
    "sg:city":"Ramales Victoria",
    "sg:orig_category":"Confiter\u00cdas, Chocolater\u00cdas (al Por Menor)",
    "sg:phone":"+34 942 64 61 25",
    "sg:postcode":"39800",
    "sg:province":"Cantabria",
    "wof:name":"Cascon Maza Maria Teresa",
    "wof:placetype":"venue"
},
  "geometry": {"coordinates":[-3.442991972,43.2613754272],"type":"Point"}
}