{
  "type": "Feature",
  "properties": {
    "iso:country":"ES",
    "sg:address":"Calle de Virgen De La Cabeza, 73",
    "sg:city":"Valencia",
    "sg:orig_category":"Perfumer\u00cda (al Por Menor)",
    "sg:phone":"+34 963 77 61 39",
    "sg:postcode":"46014",
    "sg:province":"Valencia",
    "wof:name":"Gabaldon Sanchez Juan Carlos",
    "wof:placetype":"venue"
},
  "geometry": {"coordinates":[-0.3996190131,39.4636955261],"type":"Point"}
}