{
  "type": "Feature",
  "properties": {
    "addr:full":"Calle de Aguetol, 8 Madrid Madrid 28042",
    "addr:housenumber":"8",
    "addr:postcode":"madrid;28042",
    "addr:street":"Calle De Aguetol",
    "iso:country":"ES",
    "sg:address":"Calle de Aguetol, 8",
    "sg:city":"Madrid",
    "sg:orig_category":"Fabricaci\u00d3n De Muebles",
    "sg:phone":"+34 913 29 20 91",
    "sg:postcode":"28042",
    "sg:province":"Madrid",
    "wof:name":"Cocinas Noble S.l.",
    "wof:placetype":"venue"
},
  "geometry": {"coordinates":[-3.5834813118,40.4702796936],"type":"Point"}
}