{
  "type": "Feature",
  "properties": {
    "iso:country":"ES",
    "sg:address":"Calle de Ciudad De Santander, 11",
    "sg:city":"Cadiz",
    "sg:orig_category":"Electrodom\u00c9sticos (al Por Menor)",
    "sg:phone":"+34 956 28 00 95",
    "sg:postcode":"11007",
    "sg:province":"C\u00e1diz",
    "wof:name":"Unibox Sur S.l.",
    "wof:placetype":"venue"
},
  "geometry": {"coordinates":[-6.2828822136,36.5200881958],"type":"Point"}
}