{
  "type": "Feature",
  "properties": {
    "addr:full":"Calle de Plata, 51 Valladolid Valladolid 47012",
    "addr:housenumber":"51",
    "addr:postcode":"47012",
    "addr:street":"Calle De Plata",
    "iso:country":"ES",
    "sg:address":"Calle de Plata, 51",
    "sg:city":"Valladolid",
    "sg:orig_category":"Centros Comerciales Y Grandes Tiendas",
    "sg:phone":"+34 983 21 26 07",
    "sg:postcode":"47012",
    "sg:province":"Valladolid",
    "wof:name":"Multiprecio Barrero Sl",
    "wof:placetype":"venue"
},
  "geometry": {"coordinates":[-4.7086100578,41.6162338257],"type":"Point"}
}