{
  "type": "Feature",
  "properties": {
    "addr:full":"Arenal, 80 Javea Alicante 03730",
    "addr:housenumber":"80",
    "addr:postcode":"03730",
    "addr:street":"Arenal",
    "iso:country":"ES",
    "sg:address":"Arenal, 80",
    "sg:city":"Javea",
    "sg:orig_category":"Agencias Y Asesores De Publicidad",
    "sg:phone":"+34 966 46 84 34",
    "sg:postcode":"03730",
    "sg:province":"Alicante",
    "sg:website":"www.prografixlevante.com",
    "wof:name":"Prografix Levante S.l",
    "wof:placetype":"venue"
},
  "geometry": {"coordinates":[0.1668650061,38.7890739441],"type":"Point"}
}