{
  "type": "Feature",
  "properties": {
    "iso:country":"ES",
    "sg:address":"Carrer de Creu Del Pedro, 17",
    "sg:city":"S. Just Desvern",
    "sg:orig_category":"Asilos De Ancianos. Centros Privados",
    "sg:phone":"+34 933 72 56 04",
    "sg:postcode":"08960",
    "sg:province":"Barcelona",
    "wof:name":"Residencia Quidam S.l.",
    "wof:placetype":"venue"
},
  "geometry": {"coordinates":[2.0793230534,41.3865776062],"type":"Point"}
}