{
  "type": "Feature",
  "properties": {
    "iso:country":"ES",
    "sg:address":"Carr Jaume Balmes, 9",
    "sg:city":"Balaguer",
    "sg:orig_category":"Molduras, Junquillos, Listones Y Molduras Perforadas",
    "sg:phone":"+34 973 44 61 04",
    "sg:postcode":"25600",
    "sg:province":"Lleida",
    "wof:name":"Infante Vazquez Antonio",
    "wof:placetype":"venue"
},
  "geometry": {"coordinates":[0.8099889755,41.7942466736],"type":"Point"}
}