{
  "type": "Feature",
  "properties": {
    "addr:full":"Zelata Kalea, 4 Lazkao Guip\u00f9zcoa 20210",
    "addr:housenumber":"4",
    "addr:postcode":"20210",
    "addr:street":"Zelata Kalea;Guipu\u0300Zcoa",
    "iso:country":"ES",
    "sg:address":"Zelata Kalea, 4",
    "sg:city":"Lazkao",
    "sg:orig_category":"Ropa Para Se\u00d1oras Y Caballeros (al Por Menor)",
    "sg:phone":"+34 943 16 21 83",
    "sg:postcode":"20210",
    "sg:province":"Guip\u00f9zcoa",
    "wof:name":"Garmendia Mugica Nekane",
    "wof:placetype":"venue"
},
  "geometry": {"coordinates":[-2.1873590946,43.0314903259],"type":"Point"}
}