{
  "type": "Feature",
  "properties": {
    "addr:full":"Carrer de Sant Josep, 36 Mataro Barcelona 08302",
    "addr:housenumber":"36",
    "addr:postcode":"08302",
    "addr:street":"Carrer De Sant Josep",
    "iso:country":"ES",
    "sg:address":"Carrer de Sant Josep, 36",
    "sg:city":"Mataro",
    "sg:orig_category":"Disfraces",
    "sg:phone":"+34 937 96 02 99",
    "sg:postcode":"08302",
    "sg:province":"Barcelona",
    "sg:website":"www.botigamimosa.com",
    "wof:name":"Majo Clavell Maria Assumpta",
    "wof:placetype":"venue"
},
  "geometry": {"coordinates":[2.4429700375,41.5395355225],"type":"Point"}
}