{
  "type": "Feature",
  "properties": {
    "iso:country":"ES",
    "sg:address":"Calle de Fernandez De Los Rios, 26",
    "sg:city":"Madrid",
    "sg:orig_category":"Panader\u00cdas, Panader\u00cdas",
    "sg:phone":"+34 914 48 70 95",
    "sg:postcode":"28015",
    "sg:province":"Madrid",
    "wof:name":"La Oriental 2002 S.l.",
    "wof:placetype":"venue"
},
  "geometry": {"coordinates":[-3.706964016,40.4350242615],"type":"Point"}
}