{
  "type": "Feature",
  "properties": {
    "iso:country":"ES",
    "sg:address":"Hegokalea, S/n",
    "sg:city":"Zumaia",
    "sg:orig_category":"Rectificaci\u00d3n, Mecanizado, Fresado",
    "sg:phone":"+34 943 86 12 59",
    "sg:postcode":"20750",
    "sg:province":"Guip\u00f9zcoa",
    "wof:name":"Mecanizados Etxabe S.l.",
    "wof:placetype":"venue"
},
  "geometry": {"coordinates":[-2.2583589554,43.2942314148],"type":"Point"}
}