{
  "type": "Feature",
  "properties": {
    "addr:full":"Calle de Hernani, 37 Madrid Madrid 28020",
    "addr:housenumber":"37",
    "addr:postcode":"madrid;28020",
    "addr:street":"Calle De Hernani",
    "iso:country":"ES",
    "sg:address":"Calle de Hernani, 37",
    "sg:city":"Madrid",
    "sg:orig_category":"Tintes (fabricaci\u00d3n, Al Por Mayor)",
    "sg:phone":"+34 915 34 03 34",
    "sg:postcode":"28020",
    "sg:province":"Madrid",
    "wof:name":"Fuente Molinero Luis",
    "wof:placetype":"venue"
},
  "geometry": {"coordinates":[-3.7000870705,40.448261261],"type":"Point"}
}