{
  "type": "Feature",
  "properties": {
    "addr:full":"Carrer de Pi I Margall, 47 Hospitalet Llobregat Barcelona 08902",
    "addr:housenumber":"47",
    "addr:postcode":"08902",
    "addr:street":"Carrer De Pi I Margall",
    "iso:country":"ES",
    "sg:address":"Carrer de Pi I Margall, 47",
    "sg:city":"Hospitalet Llobregat",
    "sg:orig_category":"Aparcamientos (infraestructuras, Accesorios)",
    "sg:phone":"+34 934 22 22 20",
    "sg:postcode":"08902",
    "sg:province":"Barcelona",
    "wof:name":"Guasch Sin Jorge",
    "wof:placetype":"venue"
},
  "geometry": {"coordinates":[2.1233808994,41.3644981384],"type":"Point"}
}