{
  "type": "Feature",
  "properties": {
    "addr:full":"Calle de Real, 60 Utrera Sevilla 41710",
    "addr:housenumber":"60",
    "addr:postcode":"41710",
    "addr:street":"Calle De Real",
    "iso:country":"ES",
    "sg:address":"Calle de Real, 60",
    "sg:city":"Utrera",
    "sg:orig_category":"Caf\u00c9s, Bares, Cervecer\u00cdas",
    "sg:phone":"+34 954 86 16 00",
    "sg:postcode":"41710",
    "sg:province":"Sevilla",
    "wof:name":"Utrephone S.l.",
    "wof:placetype":"venue"
},
  "geometry": {"coordinates":[-5.7836308479,37.1897735596],"type":"Point"}
}