{
  "type": "Feature",
  "properties": {
    "addr:full":"Crt. G. Sevilla, 139 Almendralejo Badajoz 06200",
    "addr:housenumber":"139",
    "addr:postcode":"06200",
    "addr:street":"Crt. G. Sevilla",
    "iso:country":"ES",
    "sg:address":"Crt. G. Sevilla, 139",
    "sg:city":"Almendralejo",
    "sg:orig_category":"Agentes, Concesionarios Y Sucursales De Veh\u00cdculos",
    "sg:phone":"+34 924 66 46 51",
    "sg:postcode":"06200",
    "sg:province":"Badajoz",
    "wof:name":"Talleres Galicia S.a.",
    "wof:placetype":"venue"
},
  "geometry": {"coordinates":[-6.3891019821,38.6721000671],"type":"Point"}
}