{
  "type": "Feature",
  "properties": {
    "addr:full":"Carrer de Vidrieria, 14 Palma Islas Baleares 07001",
    "addr:housenumber":"14",
    "addr:postcode":"07001",
    "addr:street":"Carrer De Vidrieria",
    "iso:country":"ES",
    "sg:address":"Carrer de Vidrieria, 14",
    "sg:city":"Palma",
    "sg:orig_category":"Agencias Y Agentes Comerciales, Representantes",
    "sg:phone":"+34 971 72 15 62",
    "sg:postcode":"07001",
    "sg:province":"Islas Baleares",
    "wof:name":"Ramon Beltran Guillermo",
    "wof:placetype":"venue"
},
  "geometry": {"coordinates":[2.6517729759,39.5702552795],"type":"Point"}
}