{
  "type": "Feature",
  "properties": {
    "iso:country":"ES",
    "sg:address":"Rond General Mitre, 150",
    "sg:city":"Barcelona",
    "sg:orig_category":"Psic\u00d3logos",
    "sg:phone":"+34 932 09 75 33",
    "sg:postcode":"08006",
    "sg:province":"Barcelona",
    "wof:name":"Homs Vich Joan",
    "wof:placetype":"venue"
},
  "geometry": {"coordinates":[2.1393260956,41.4036178589],"type":"Point"}
}