{
  "type": "Feature",
  "properties": {
    "iso:country":"ES",
    "sg:address":"Calle de Juan De Velasco, 4 A",
    "sg:city":"Vitoria-gasteiz",
    "sg:orig_category":"Cl\u00cdnicas Dentales",
    "sg:phone":"+34 945 17 56 73",
    "sg:postcode":"01010",
    "sg:province":"\u00c1lava",
    "wof:name":"Dental San Antonio 3, S.l.",
    "wof:placetype":"venue"
},
  "geometry": {"coordinates":[-2.6998240948,42.8534507751],"type":"Point"}
}