{
  "type": "Feature",
  "properties": {
    "addr:full":"Calle de San Jose De Calasanz, 20 Valencia Valencia 46008",
    "addr:housenumber":"20",
    "addr:postcode":"46008",
    "addr:street":"Calle De San;De Calasanz",
    "iso:country":"ES",
    "sg:address":"Calle de San Jose De Calasanz, 20",
    "sg:city":"Valencia",
    "sg:orig_category":"Delegados, Agentes De Tr\u00c1nsito, Auxiliares De Transporte Internacional",
    "sg:phone":"+34 963 85 45 66",
    "sg:postcode":"46008",
    "sg:province":"Valencia",
    "wof:name":"Transportes Aramat S.l.",
    "wof:placetype":"venue"
},
  "geometry": {"coordinates":[-0.3884170055,39.4667778015],"type":"Point"}
}