{
  "type": "Feature",
  "properties": {
    "iso:country":"ES",
    "sg:address":"Pol. Industrial, S/n",
    "sg:city":"Celra",
    "sg:orig_category":"Productos Qu\u00cdmicos (fabricaci\u00d3n, Al Por Mayor)",
    "sg:phone":"+34 972 49 23 20",
    "sg:postcode":"17460",
    "sg:province":"Girona",
    "wof:name":"Protein S. A.",
    "wof:placetype":"venue"
},
  "geometry": {"coordinates":[2.8719749451,42.0266799927],"type":"Point"}
}