{
  "type": "Feature",
  "properties": {
    "addr:full":"Calle de Reja, 2 Salamanca Salamanca 37001",
    "addr:housenumber":"2",
    "addr:postcode":"37001",
    "addr:street":"Calle De Reja",
    "iso:country":"ES",
    "sg:address":"Calle de Reja, 2",
    "sg:city":"Salamanca",
    "sg:orig_category":"M\u00c9dicos: Psiquiatr\u00cda",
    "sg:phone":"+34 923 27 12 10",
    "sg:postcode":"37001",
    "sg:province":"Salamanca",
    "wof:name":"Ramos Castellanos Jose Luis",
    "wof:placetype":"venue"
},
  "geometry": {"coordinates":[-5.6599187851,40.9655532837],"type":"Point"}
}