{
  "type": "Feature",
  "properties": {
    "iso:country":"ES",
    "sg:address":"Avda Francia (de), S/n",
    "sg:city":"Playa Del Ingles",
    "sg:orig_category":"Bisuter\u00cda, Joyer\u00cda, Relojer\u00cda (al Por Menor)",
    "sg:phone":"+34 928 76 20 98",
    "sg:postcode":"35100",
    "sg:province":"Las Palmas",
    "wof:name":"Laguna Santos Candelaria",
    "wof:placetype":"venue"
},
  "geometry": {"coordinates":[-15.5795240402,27.7507400513],"type":"Point"}
}