{
  "type": "Feature",
  "properties": {
    "addr:full":"Carrer de Petrarca, 17 Sabadell Barcelona 08206",
    "addr:housenumber":"17",
    "addr:postcode":"08206",
    "addr:street":"Carrer De Petrarca",
    "iso:country":"ES",
    "sg:address":"Carrer de Petrarca, 17",
    "sg:city":"Sabadell",
    "sg:orig_category":"Inmobiliaria (agencias)",
    "sg:phone":"+34 937 16 21 72",
    "sg:postcode":"08206",
    "sg:province":"Barcelona",
    "wof:name":"Canmasada Proyectos Inmobiliarios S.l.",
    "wof:placetype":"venue"
},
  "geometry": {"coordinates":[2.08664608,41.555809021],"type":"Point"}
}