{
  "type": "Feature",
  "properties": {
    "addr:full":"Calle de Rio De Janeiro, 32 Barrosa C\u00e1diz 11130",
    "addr:housenumber":"32",
    "addr:postcode":"11130",
    "addr:street":"Calle De Rio De Janeiro;Ca\u0301Diz",
    "iso:country":"ES",
    "sg:address":"Calle de Rio De Janeiro, 32",
    "sg:city":"Barrosa",
    "sg:orig_category":"Centros De Coordinaci\u00d3n",
    "sg:phone":"+34 956 49 44 52",
    "sg:postcode":"11130",
    "sg:province":"C\u00e1diz",
    "wof:name":"Comercial Codisal Burgos S.l.",
    "wof:placetype":"venue"
},
  "geometry": {"coordinates":[-6.1447038651,36.4212188721],"type":"Point"}
}