{
  "type": "Feature",
  "properties": {
    "iso:country":"ES",
    "sg:address":"Luga Poligono Industrial De Roces, S/n",
    "sg:city":"Gijon",
    "sg:orig_category":"Venta, Instalaci\u00d3n De Material De Aireaci\u00d3n Y De Ventilaci\u00d3n",
    "sg:phone":"+34 985 16 81 03",
    "sg:postcode":"33211",
    "sg:province":"Asturias",
    "wof:name":"Alejandro Rubio Instalaciones Electricas S. L.",
    "wof:placetype":"venue"
},
  "geometry": {"coordinates":[-5.6852426529,43.5228233337],"type":"Point"}
}