{
  "type": "Feature",
  "properties": {
    "addr:full":"Carrer de Miquel Tort, 2 Molins Rei Barcelona 08750",
    "addr:housenumber":"2",
    "addr:postcode":"08750",
    "addr:street":"Carrer De Miquel Tort;Barcelona",
    "iso:country":"ES",
    "sg:address":"Carrer de Miquel Tort, 2",
    "sg:city":"Molins Rei",
    "sg:orig_category":"Muebles, Minoristas",
    "sg:phone":"+34 936 68 33 45",
    "sg:postcode":"08750",
    "sg:province":"Barcelona",
    "wof:name":"Gardes Bonet Jose Maria",
    "wof:placetype":"venue"
},
  "geometry": {"coordinates":[2.0179746151,41.4110679626],"type":"Point"}
}