{
  "type": "Feature",
  "properties": {
    "iso:country":"ES",
    "sg:address":"Carr Torreta, 7",
    "sg:city":"Silla",
    "sg:orig_category":"Panader\u00cdas, Panader\u00cdas",
    "sg:phone":"+34 961 20 17 75",
    "sg:postcode":"46460",
    "sg:province":"Valencia",
    "wof:name":"Hermanos Rosalen Milla S.l.",
    "wof:placetype":"venue"
},
  "geometry": {"coordinates":[-0.4096859992,39.3610496521],"type":"Point"}
}