{
  "type": "Feature",
  "properties": {
    "iso:country":"ES",
    "sg:address":"Carr Segarra, 28",
    "sg:city":"Solsona",
    "sg:classifiers":[
        {
            "category":"Taxi",
            "type":"Transportation"
        }
    ],
    "sg:phone":"+34 973 48 11 31",
    "sg:postcode":"25280",
    "sg:province":"Lleida",
    "wof:name":"Bores Ferrer Ramon",
    "wof:placetype":"venue"
},
  "geometry": {"coordinates":[1.5195260048,42.0008392334],"type":"Point"}
}