{
  "type": "Feature",
  "properties": {
    "iso:country":"ES",
    "sg:address":"Carrer de Eivissa, 3",
    "sg:city":"Palma",
    "sg:orig_category":"Molduras, Junquillos, Listones Y Molduras Perforadas",
    "sg:phone":"+34 971 73 71 91",
    "sg:postcode":"07011",
    "sg:province":"Islas Baleares",
    "wof:name":"Carmona Martinez Victorina",
    "wof:placetype":"venue"
},
  "geometry": {"coordinates":[2.6430039406,39.5748786926],"type":"Point"}
}