{
  "type": "Feature",
  "properties": {
    "iso:country":"ES",
    "sg:address":"Calle de Garcia De Paredes, 86",
    "sg:city":"Madrid",
    "sg:orig_category":"Caf\u00c9s, Bares, Cervecer\u00cdas",
    "sg:phone":"+34 913 19 88 80",
    "sg:postcode":"28010",
    "sg:province":"Madrid",
    "wof:name":"Benito Mateos Segundo",
    "wof:placetype":"venue"
},
  "geometry": {"coordinates":[-3.6916759014,40.4364356995],"type":"Point"}
}