{
  "type": "Feature",
  "properties": {
    "iso:country":"ES",
    "sg:address":"Cra. Abrera A Manresa, S/n",
    "sg:city":"Olesa Montserrat",
    "sg:orig_category":"M\u00c1rmoles, Granitos Y Piedras Naturales",
    "sg:phone":"+34 937 78 05 16",
    "sg:postcode":"08640",
    "sg:province":"Barcelona",
    "wof:name":"Marmoleria Catalana S. A.",
    "wof:placetype":"venue"
},
  "geometry": {"coordinates":[1.8930729628,41.536895752],"type":"Point"}
}