{
  "type": "Feature",
  "properties": {
    "iso:country":"ES",
    "sg:address":"Rua Ramon Puga, 83",
    "sg:city":"Ourense",
    "sg:orig_category":"Comunidades Religiosas",
    "sg:phone":"+34 988 25 30 02",
    "sg:postcode":"32005",
    "sg:province":"Ourense",
    "wof:name":"Compa\u00f1ia De Las Hijas De La Caridad De San Vicente De Paul Provinci",
    "wof:placetype":"venue"
},
  "geometry": {"coordinates":[-7.8556981087,42.3267097473],"type":"Point"}
}