{
  "type": "Feature",
  "properties": {
    "addr:full":"Calle de San Emilio, 70 Madrid Madrid 28017",
    "addr:housenumber":"70",
    "addr:postcode":"madrid;28017",
    "addr:street":"Calle De San Emilio",
    "iso:country":"ES",
    "sg:address":"Calle de San Emilio, 70",
    "sg:city":"Madrid",
    "sg:orig_category":"Molduras, Junquillos, Listones Y Molduras Perforadas",
    "sg:phone":"+34 914 03 74 97",
    "sg:postcode":"28017",
    "sg:province":"Madrid",
    "wof:name":"Pe\u00f1a De Orte Miguel",
    "wof:placetype":"venue"
},
  "geometry": {"coordinates":[-3.6591081619,40.4279785156],"type":"Point"}
}