{
  "type": "Feature",
  "properties": {
    "iso:country":"ES",
    "sg:address":"Calle de Pintor Lorenzo Casanova, 15",
    "sg:city":"Alacant",
    "sg:orig_category":"Delegados, Agentes De Tr\u00c1nsito, Auxiliares De Transporte Internacional",
    "sg:phone":"+34 965 92 31 58",
    "sg:postcode":"03003",
    "sg:province":"Alicante",
    "wof:name":"Asociacion De Transitarios Expedidores Internacionales Y Asimiladores A.t.e.i.a.",
    "wof:placetype":"venue"
},
  "geometry": {"coordinates":[-0.4896992147,38.3419914246],"type":"Point"}
}