{
  "type": "Feature",
  "properties": {
    "addr:full":"Plaz Mercado Del, 12 Zamora Zamora 49003",
    "addr:postcode":"49003",
    "iso:country":"ES",
    "sg:address":"Plaz Mercado Del, 12",
    "sg:city":"Zamora",
    "sg:orig_category":"Procuradores",
    "sg:phone":"+34 980 50 91 72",
    "sg:postcode":"49003",
    "sg:province":"Zamora",
    "wof:name":"Robledo Navais Francisco Tomas",
    "wof:placetype":"venue"
},
  "geometry": {"coordinates":[-5.7457342148,41.5033302307],"type":"Point"}
}