{
  "type": "Feature",
  "properties": {
    "addr:full":"Av Catalunya, 77 Cervera Lleida 25200",
    "addr:housenumber":"77",
    "addr:postcode":"25200",
    "addr:street":"Av Catalunya",
    "iso:country":"ES",
    "sg:address":"Av Catalunya, 77",
    "sg:city":"Cervera",
    "sg:orig_category":"Mec\u00c1nico Del Autom\u00d3vil",
    "sg:phone":"+34 973 53 08 34",
    "sg:postcode":"25200",
    "sg:province":"Lleida",
    "wof:name":"Garatge Carcasona S.cv.",
    "wof:placetype":"venue"
},
  "geometry": {"coordinates":[1.2686543465,41.6708221436],"type":"Point"}
}