{
  "type": "Feature",
  "properties": {
    "addr:full":"Avia. Colmenar Vjo., Km. 0022,0 Tres Cantos Madrid 28760",
    "addr:postcode":"28760",
    "addr:street":"Vjo. Km. 0022,0",
    "iso:country":"ES",
    "sg:address":"Avia. Colmenar Vjo., Km. 0022,0",
    "sg:city":"Tres Cantos",
    "sg:orig_category":"Platos Preparados Refrigerados (fabricaci\u00d3n, Al Por Mayor)",
    "sg:phone":"+34 918 03 29 74",
    "sg:postcode":"28760",
    "sg:province":"Madrid",
    "wof:name":"Gastronomic S.a.",
    "wof:placetype":"venue"
},
  "geometry": {"coordinates":[-3.7115690708,40.5986709595],"type":"Point"}
}