{
  "type": "Feature",
  "properties": {
    "iso:country":"ES",
    "sg:address":"Calle de De Gabriel, 5",
    "sg:city":"Badajoz",
    "sg:orig_category":"Fabricaci\u00d3n De Acumuladores Y De Pilas El\u00c9ctricas",
    "sg:phone":"+34 924 22 00 96",
    "sg:postcode":"06001",
    "sg:province":"Badajoz",
    "wof:name":"Dimape S.l.",
    "wof:placetype":"venue"
},
  "geometry": {"coordinates":[-6.9729571342,38.8790359497],"type":"Point"}
}