{
  "type": "Feature",
  "properties": {
    "addr:full":"Orfeo Catala, 9 Cardedeu Barcelona 08440",
    "addr:postcode":"08440",
    "iso:country":"ES",
    "sg:address":"Orfeo Catala, 9",
    "sg:city":"Cardedeu",
    "sg:orig_category":"Tubos Y Tuber\u00cdas De Goma Y Pl\u00c1stico (fabricaci\u00d3n, Al Por Mayor)",
    "sg:phone":"+34 938 71 37 55",
    "sg:postcode":"08440",
    "sg:province":"Barcelona",
    "sg:website":"www.precableados.com",
    "wof:name":"Electroflex P M Iberica S.l.",
    "wof:placetype":"venue"
},
  "geometry": {"coordinates":[2.3603100777,41.6399612427],"type":"Point"}
}