{
  "type": "Feature",
  "properties": {
    "addr:full":"Calle de Valderribas, 48 Madrid Madrid 28007",
    "addr:housenumber":"48",
    "addr:postcode":"madrid;28007",
    "addr:street":"Calle De Valderribas",
    "iso:country":"ES",
    "sg:address":"Calle de Valderribas, 48",
    "sg:city":"Madrid",
    "sg:orig_category":"Caf\u00c9s, Bares, Cervecer\u00cdas",
    "sg:phone":"+34 915 01 71 95",
    "sg:postcode":"28007",
    "sg:province":"Madrid",
    "wof:name":"Villar Monta\u00f1a Alfonso",
    "wof:placetype":"venue"
},
  "geometry": {"coordinates":[-3.6726179123,40.4028358459],"type":"Point"}
}