{
  "type": "Feature",
  "properties": {
    "iso:country":"ES",
    "sg:address":"Avda Roma, 19",
    "sg:city":"Le\u00f3n",
    "sg:orig_category":"Molduras, Junquillos, Listones Y Molduras Perforadas",
    "sg:phone":"+34 987 24 39 98",
    "sg:postcode":"24001",
    "sg:province":"Le\u00f3n",
    "wof:name":"Folgueras Llamas Jose Luis",
    "wof:placetype":"venue"
},
  "geometry": {"coordinates":[-5.5769128799,42.5978775024],"type":"Point"}
}