{
  "type": "Feature",
  "properties": {
    "addr:full":"Calle de Edificio Velasco, 81 Irun Guip\u00f9zcoa 20303",
    "addr:housenumber":"81",
    "addr:postcode":"20303",
    "addr:street":"Calle De Edificio Velasco;Guipu\u0300Zcoa",
    "iso:country":"ES",
    "sg:address":"Calle de Edificio Velasco, 81",
    "sg:city":"Irun",
    "sg:orig_category":"Adhesivos (fabricaci\u00d3n, Al Por Mayor)",
    "sg:phone":"+34 943 63 23 33",
    "sg:postcode":"20303",
    "sg:province":"Guip\u00f9zcoa",
    "wof:name":"A.i.b. Serigrafia, S.l.",
    "wof:placetype":"venue"
},
  "geometry": {"coordinates":[-1.7902339697,43.3395233154],"type":"Point"}
}