{
  "type": "Feature",
  "properties": {
    "addr:full":"Ctra. Pago Humo, Km. 0003,5 Chiclana C\u00e1diz 11130",
    "addr:postcode":"11130",
    "addr:street":"Ctra. Pago Humo Km. 0003,5",
    "iso:country":"ES",
    "sg:address":"Ctra. Pago Humo, Km. 0003,5",
    "sg:city":"Chiclana",
    "sg:orig_category":"Supermercados Y Hipermercados",
    "sg:phone":"+34 956 23 09 15",
    "sg:postcode":"11130",
    "sg:province":"C\u00e1diz",
    "wof:name":"Autoservicios Los Chiclaneros S.l.",
    "wof:placetype":"venue"
},
  "geometry": {"coordinates":[-6.1281404495,36.4074440002],"type":"Point"}
}