{
  "type": "Feature",
  "properties": {
    "iso:country":"ES",
    "sg:address":"Calle de Elcano, 25",
    "sg:city":"Bilbao",
    "sg:orig_category":"Expertos Contables, Revisores De Cuentas",
    "sg:phone":"+34 944 21 54 47",
    "sg:postcode":"48008",
    "sg:province":"Vizcaya",
    "wof:name":"Test Auditores S.l.",
    "wof:placetype":"venue"
},
  "geometry": {"coordinates":[-2.9326109886,43.2592468262],"type":"Point"}
}