{
  "type": "Feature",
  "properties": {
    "iso:country":"ES",
    "sg:address":"Rua Horreo (do), 19",
    "sg:city":"Santiago De Compostela",
    "sg:orig_category":"Fabricaci\u00d3n, Venta De Cuadros, Accesorios Para Enmarcar",
    "sg:phone":"+34 981 58 04 27",
    "sg:postcode":"15702",
    "sg:province":"La Coru\u00f1a",
    "wof:name":"Mui\u00f1o Fernandez Jose",
    "wof:placetype":"venue"
},
  "geometry": {"coordinates":[-8.5438861847,42.8758049011],"type":"Point"}
}