{
  "type": "Feature",
  "properties": {
    "iso:country":"ES",
    "sg:address":"Calle de Goles, 32",
    "sg:city":"Sevilla",
    "sg:orig_category":"Arquitectos",
    "sg:phone":"+34 954 90 51 93",
    "sg:postcode":"41002",
    "sg:province":"Sevilla",
    "wof:name":"Astorga Morano Juan",
    "wof:placetype":"venue"
},
  "geometry": {"coordinates":[-6.0012040138,37.3949317932],"type":"Point"}
}