{
  "type": "Feature",
  "properties": {
    "addr:full":"Calle de Alcalde Parrondo, 4 Pola De Siero Asturias 33510",
    "addr:housenumber":"4",
    "addr:postcode":"33510",
    "addr:street":"Calle De Alcalde Parrondo",
    "iso:country":"ES",
    "sg:address":"Calle de Alcalde Parrondo, 4",
    "sg:city":"Pola De Siero",
    "sg:orig_category":"Agencias De Viajes",
    "sg:phone":"+34 985 72 64 72",
    "sg:postcode":"33510",
    "sg:province":"Asturias",
    "sg:website":"www.viajeselcorteingles.es",
    "wof:name":"Viajes El Corte Ingles S.a.",
    "wof:placetype":"venue"
},
  "geometry": {"coordinates":[-5.6617031097,43.3909339905],"type":"Point"}
}