{
  "type": "Feature",
  "properties": {
    "addr:full":"Carr Girona, 5 Balaguer Lleida 25600",
    "addr:housenumber":"5",
    "addr:postcode":"25600",
    "addr:street":"Carr Girona",
    "iso:country":"ES",
    "sg:address":"Carr Girona, 5",
    "sg:city":"Balaguer",
    "sg:orig_category":"Laboratorios Y Trabajos De Fotograf\u00cda, V\u00cddeo Y Cine",
    "sg:phone":"+34 973 44 92 36",
    "sg:postcode":"25600",
    "sg:province":"Lleida",
    "sg:website":"www.cliplapfotografia.com",
    "wof:name":"Jesus Bitria Rafael",
    "wof:placetype":"venue"
},
  "geometry": {"coordinates":[0.8126980066,41.7897186279],"type":"Point"}
}