{
  "type": "Feature",
  "properties": {
    "iso:country":"ES",
    "sg:address":"Calle de Burgos, 7",
    "sg:city":"San Juan De Aznalfarache",
    "sg:orig_category":"Art\u00cdculos De Regalo (al Por Menor)",
    "sg:phone":"+34 954 76 93 80",
    "sg:postcode":"41920",
    "sg:province":"Sevilla",
    "wof:name":"Bezard Contreras Maria Del Carmen",
    "wof:placetype":"venue"
},
  "geometry": {"coordinates":[-6.0364742279,37.3570823669],"type":"Point"}
}