{
  "type": "Feature",
  "properties": {
    "iso:country":"ES",
    "sg:address":"Carr Illa, 6",
    "sg:city":"Port Selva",
    "sg:orig_category":"Reposter\u00cdas",
    "sg:phone":"+34 972 38 70 23",
    "sg:postcode":"17489",
    "sg:province":"Girona",
    "wof:name":"Que Bo S.c.",
    "wof:placetype":"venue"
},
  "geometry": {"coordinates":[3.1865150928,42.3239517212],"type":"Point"}
}