{
  "type": "Feature",
  "properties": {
    "iso:country":"ES",
    "sg:address":"Calle de Espa\u00d1a, 10",
    "sg:city":"Yecla",
    "sg:orig_category":"\u00d3ptica: Instrumentos (fabricaci\u00d3n)",
    "sg:phone":"+34 968 75 28 26",
    "sg:postcode":"30510",
    "sg:province":"Murcia",
    "wof:name":"Perez Ruiz Maria Dolores",
    "wof:placetype":"venue"
},
  "geometry": {"coordinates":[-1.1157189608,38.6138687134],"type":"Point"}
}