{
  "type": "Feature",
  "properties": {
    "addr:full":"Calle de Condado De Trevi\u00d1o, 72 Miranda Ebro Burgos 09200",
    "addr:housenumber":"72",
    "addr:postcode":"09200",
    "addr:street":"Calle De Condado De Trevin\u0303O",
    "iso:country":"ES",
    "sg:address":"Calle de Condado De Trevi\u00d1o, 72",
    "sg:city":"Miranda Ebro",
    "sg:orig_category":"Parques De Atracciones Y Centros De Esparcimiento",
    "sg:phone":"+34 947 33 54 37",
    "sg:postcode":"09200",
    "sg:province":"Burgos",
    "wof:name":"Recreativos Saul S. A.",
    "wof:placetype":"venue"
},
  "geometry": {"coordinates":[-2.9395394325,42.687210083],"type":"Point"}
}