{
  "type": "Feature",
  "properties": {
    "addr:full":"Carr Vapor, 7 Palamos Girona 17230",
    "addr:housenumber":"7",
    "addr:postcode":"17230",
    "addr:street":"Carr Vapor",
    "iso:country":"ES",
    "sg:address":"Carr Vapor, 7",
    "sg:city":"Palamos",
    "sg:orig_category":"Molduras, Junquillos, Listones Y Molduras Perforadas",
    "sg:phone":"+34 972 31 62 77",
    "sg:postcode":"17230",
    "sg:province":"Girona",
    "wof:name":"Zimmermann Garces Andres Miguel",
    "wof:placetype":"venue"
},
  "geometry": {"coordinates":[3.1282567978,41.8452262878],"type":"Point"}
}