{
  "type": "Feature",
  "properties": {
    "addr:full":"Calle de Zurbaran, S/n Fuensalida Toledo 45510",
    "addr:housenumber":"s",
    "addr:postcode":"45510",
    "addr:street":"Calle De Zurbaran;/ N",
    "iso:country":"ES",
    "sg:address":"Calle de Zurbaran, S/n",
    "sg:city":"Fuensalida",
    "sg:orig_category":"Farmacias",
    "sg:phone":"+34 925 73 21 12",
    "sg:postcode":"45510",
    "sg:province":"Toledo",
    "wof:name":"Jimenez Crespo Angela",
    "wof:placetype":"venue"
},
  "geometry": {"coordinates":[-4.2108640671,40.0507087708],"type":"Point"}
}