{
  "type": "Feature",
  "properties": {
    "addr:full":"G.v. Hortaleza, 78 Madrid Madrid 28043",
    "addr:housenumber":"78",
    "addr:postcode":"madrid;28043",
    "iso:country":"ES",
    "sg:address":"G.v. Hortaleza, 78",
    "sg:city":"Madrid",
    "sg:orig_category":"Sociedades, Compa\u00d1\u00cdas Aseguradoras",
    "sg:phone":"+34 913 88 70 10",
    "sg:postcode":"28043",
    "sg:province":"Madrid",
    "wof:name":"Mutua Valenciana Automovilista Seguros A Prima Fija",
    "wof:placetype":"venue"
},
  "geometry": {"coordinates":[-3.7057740688,40.42029953],"type":"Point"}
}