{
  "type": "Feature",
  "properties": {
    "iso:country":"ES",
    "sg:address":"Trva Constitucion (la), S/n",
    "sg:city":"Sahagun",
    "sg:orig_category":"Alimentaci\u00d3n General (al Por Mayor)",
    "sg:phone":"+34 987 78 03 60",
    "sg:postcode":"24320",
    "sg:province":"Le\u00f3n",
    "wof:name":"Pastrana Agricentro S.l.",
    "wof:placetype":"venue"
},
  "geometry": {"coordinates":[-5.026403904,42.3693161011],"type":"Point"}
}