{
  "type": "Feature",
  "properties": {
    "iso:country":"ES",
    "sg:address":"Pase Castellana, 216",
    "sg:city":"Madrid",
    "sg:orig_category":"Inmobiliaria (agencias)",
    "sg:phone":"+34 913 44 95 39",
    "sg:postcode":"28046",
    "sg:province":"Madrid",
    "wof:name":"Desarrollo Urbanistico Chamartin",
    "wof:placetype":"venue"
},
  "geometry": {"coordinates":[-3.6889820099,40.4352073669],"type":"Point"}
}