{
  "type": "Feature",
  "properties": {
    "iso:country":"ES",
    "sg:address":"Avda Doctor Fleming, S/n",
    "sg:city":"Ecija",
    "sg:orig_category":"Laboratorios Y Trabajos De Fotograf\u00cda, V\u00cddeo Y Cine",
    "sg:phone":"+34 955 90 20 11",
    "sg:postcode":"41400",
    "sg:province":"Sevilla",
    "wof:name":"Fajardo Garcia Maria Jose",
    "wof:placetype":"venue"
},
  "geometry": {"coordinates":[-5.0731348991,37.5422210693],"type":"Point"}
}