{
  "type": "Feature",
  "properties": {
    "iso:country":"ES",
    "sg:address":"Plaz Mayor, 11",
    "sg:city":"Esquivias",
    "sg:orig_category":"Farmacias",
    "sg:phone":"+34 925 52 00 67",
    "sg:postcode":"45221",
    "sg:province":"Toledo",
    "sg:website":"www paginasamarillas.es",
    "wof:name":"Farmacia Dorrego C.b.",
    "wof:placetype":"venue"
},
  "geometry": {"coordinates":[-3.7652959824,40.1040229797],"type":"Point"}
}