{
  "type": "Feature",
  "properties": {
    "addr:full":"Ctra Manlleu, Km. 0000,1 Vic Barcelona 08500",
    "addr:postcode":"08500",
    "addr:street":"Ctra Manlleu Km. 0000,1",
    "iso:country":"ES",
    "sg:address":"Ctra Manlleu, Km. 0000,1",
    "sg:city":"Vic",
    "sg:orig_category":"Ropa Para Se\u00d1oras Y Caballeros (al Por Menor)",
    "sg:phone":"+34 938 89 24 64",
    "sg:postcode":"08500",
    "sg:province":"Barcelona",
    "wof:name":"Guitart Castellvi Jose",
    "wof:placetype":"venue"
},
  "geometry": {"coordinates":[2.2551670074,41.9344520569],"type":"Point"}
}