{
  "type": "Feature",
  "properties": {
    "iso:country":"ES",
    "sg:address":"Calle de Padre Jose Maria, 1",
    "sg:city":"Madrid",
    "sg:orig_category":"Peluqueros: De Se\u00d1oras",
    "sg:phone":"+34 913 18 23 27",
    "sg:postcode":"28041",
    "sg:province":"Madrid",
    "wof:name":"Mingorance Saez Jorge",
    "wof:placetype":"venue"
},
  "geometry": {"coordinates":[-3.699338913,40.3671188354],"type":"Point"}
}