{
  "type": "Feature",
  "properties": {
    "iso:country":"ES",
    "sg:address":"Calle de Ribera Del Sena, S/n",
    "sg:city":"Madrid",
    "sg:orig_category":"Ingenier\u00cda, Centros De Estudios (diversos)",
    "sg:phone":"+34 917 21 32 40",
    "sg:postcode":"28042",
    "sg:province":"Madrid",
    "wof:name":"Calle 30 S.a.",
    "wof:placetype":"venue"
},
  "geometry": {"coordinates":[-3.6180040836,40.4619865417],"type":"Point"}
}