{
  "type": "Feature",
  "properties": {
    "addr:full":"Avda Juan Carlos I, 8 Corralejo Las Palmas 35660",
    "addr:housenumber":"8",
    "addr:postcode":"35660",
    "addr:street":"Avda Juan Carlos I",
    "iso:country":"ES",
    "sg:address":"Avda Juan Carlos I, 8",
    "sg:city":"Corralejo",
    "sg:orig_category":"Caf\u00c9s, Bares, Cervecer\u00cdas",
    "sg:phone":"+34 928 53 75 76",
    "sg:postcode":"35660",
    "sg:province":"Las Palmas",
    "wof:name":"Hierro Estevez Pedro",
    "wof:placetype":"venue"
},
  "geometry": {"coordinates":[-13.8692493439,28.7350444794],"type":"Point"}
}