{
  "type": "Feature",
  "properties": {
    "addr:full":"Rbla Principal, 124 Vilanova I La Geltru Barcelona 08800",
    "addr:housenumber":"124",
    "addr:postcode":"08800",
    "addr:street":"Rbla Principal",
    "iso:country":"ES",
    "sg:address":"Rbla Principal, 124",
    "sg:city":"Vilanova I La Geltru",
    "sg:orig_category":"Farmacias",
    "sg:phone":"+34 938 14 29 59",
    "sg:postcode":"08800",
    "sg:province":"Barcelona",
    "wof:name":"Farmacia Rodriguez Lobato S.c.p",
    "wof:placetype":"venue"
},
  "geometry": {"coordinates":[1.726369977,41.2211456299],"type":"Point"}
}