{
  "type": "Feature",
  "properties": {
    "addr:full":"Calle de Maestro Sosa, 37 Valencia Valencia 46007",
    "addr:housenumber":"37",
    "addr:postcode":"46007",
    "addr:street":"Calle De Maestro Sosa",
    "iso:country":"ES",
    "sg:address":"Calle de Maestro Sosa, 37",
    "sg:city":"Valencia",
    "sg:orig_category":"Empresas De Carpinter\u00cda De Madera",
    "sg:phone":"+34 963 41 27 38",
    "sg:postcode":"46007",
    "sg:province":"Valencia",
    "wof:name":"Navarro Martinez Jose",
    "wof:placetype":"venue"
},
  "geometry": {"coordinates":[-0.3834550083,39.4610748291],"type":"Point"}
}