{
  "type": "Feature",
  "properties": {
    "iso:country":"ES",
    "sg:address":"Calle de Alba\u00d1iles, 1",
    "sg:city":"Rota",
    "sg:orig_category":"Empresas De Carpinter\u00cda De Madera",
    "sg:phone":"+34 956 81 36 49",
    "sg:postcode":"11520",
    "sg:province":"C\u00e1diz",
    "wof:name":"Carpinteria Izquierdo Y Moreno S.l.l.",
    "wof:placetype":"venue"
},
  "geometry": {"coordinates":[-6.3657712936,36.6343536377],"type":"Point"}
}