{
  "type": "Feature",
  "properties": {
    "iso:country":"ES",
    "sg:address":"Carrer de Montserrat Caballe (de), 2",
    "sg:city":"Pineda",
    "sg:orig_category":"Empresas De Limpieza",
    "sg:phone":"+34 977 37 30 00",
    "sg:postcode":"43480",
    "sg:province":"Tarragona",
    "wof:name":"Ideal Clean S.l.u.",
    "wof:placetype":"venue"
},
  "geometry": {"coordinates":[1.1441899538,41.1080245972],"type":"Point"}
}