{
  "type": "Feature",
  "properties": {
    "addr:full":"Crt Madrid-alicante, Km. 0172,0 El Provencio Cuenca 16670",
    "addr:postcode":"16670",
    "addr:street":"Madrid-Alicante Km. 0172,0",
    "iso:country":"ES",
    "sg:address":"Crt Madrid-alicante, Km. 0172,0",
    "sg:city":"El Provencio",
    "sg:orig_category":"Expositores",
    "sg:phone":"+34 967 16 61 74",
    "sg:postcode":"16670",
    "sg:province":"Cuenca",
    "wof:name":"Central De Manipulacion S.l.",
    "wof:placetype":"venue"
},
  "geometry": {"coordinates":[-2.5704939365,39.3758201599],"type":"Point"}
}