{
  "type": "Feature",
  "properties": {
    "addr:full":"Calle de Anzofe, 115 Palmas De Gran Canaria Las Palmas 35009",
    "addr:housenumber":"115",
    "addr:postcode":"35009",
    "addr:street":"Calle De Anzofe",
    "iso:country":"ES",
    "sg:address":"Calle de Anzofe, 115",
    "sg:city":"Palmas De Gran Canaria",
    "sg:orig_category":"Sindicatos De Trabajadores",
    "sg:phone":"+34 928 46 16 57",
    "sg:postcode":"35009",
    "sg:province":"Las Palmas",
    "wof:name":"Organizacion De Estibadores Portuarios",
    "wof:placetype":"venue"
},
  "geometry": {"coordinates":[-15.4220895767,28.1507453918],"type":"Point"}
}