{
  "type": "Feature",
  "properties": {
    "addr:full":"Av Paral.lel, 114 Barcelona Barcelona 08015",
    "addr:housenumber":"114",
    "addr:postcode":"08015",
    "addr:street":"Av Paral.Lel",
    "iso:country":"ES",
    "sg:address":"Av Paral.lel, 114",
    "sg:city":"Barcelona",
    "sg:orig_category":"Agencias Y Agentes Comerciales, Representantes",
    "sg:phone":"+34 934 42 87 91",
    "sg:postcode":"08015",
    "sg:province":"Barcelona",
    "wof:name":"Alabart Ferre Jaime",
    "wof:placetype":"venue"
},
  "geometry": {"coordinates":[2.1638758183,41.3749694824],"type":"Point"}
}