{
  "type": "Feature",
  "properties": {
    "iso:country":"ES",
    "sg:address":"Pase Cuellar, 53",
    "sg:city":"Zaragoza",
    "sg:orig_category":"Colchones (fabricaci\u00d3n, Al Por Mayor, Al Por Menor)",
    "sg:phone":"+34 976 37 90 86",
    "sg:postcode":"50007",
    "sg:province":"Zaragoza",
    "wof:name":"Retaule, S.l.",
    "wof:placetype":"venue"
},
  "geometry": {"coordinates":[-0.8844090104,41.6357383728],"type":"Point"}
}