{
  "type": "Feature",
  "properties": {
    "iso:country":"ES",
    "sg:address":"Cra Santa Creu De Calafell, 3",
    "sg:city":"Gava",
    "sg:orig_category":"Electricidad, Electr\u00d3nica: Suministros (al Por Menor)",
    "sg:phone":"+34 936 38 41 44",
    "sg:postcode":"08850",
    "sg:province":"Barcelona",
    "wof:name":"Uniproduk S.a.",
    "wof:placetype":"venue"
},
  "geometry": {"coordinates":[2.0113990307,41.3063163757],"type":"Point"}
}