{
  "type": "Feature",
  "properties": {
    "iso:country":"ES",
    "sg:address":"Gta Carrasco, 32",
    "sg:city":"Benidorm",
    "sg:orig_category":"Carnicer\u00cdas, Carnicer\u00cdas",
    "sg:phone":"+34 965 86 86 42",
    "sg:postcode":"03500",
    "sg:province":"Alicante",
    "wof:name":"Espasa Tomas Domingo",
    "wof:placetype":"venue"
},
  "geometry": {"coordinates":[-0.1740590036,38.5364303589],"type":"Point"}
}