{
  "type": "Feature",
  "properties": {
    "iso:country":"ES",
    "sg:address":"Calle de Tejeda, 17",
    "sg:city":"Cazuela",
    "sg:orig_category":"Fabricaci\u00d3n, Importaci\u00d3n, Venta De Material De Telefon\u00cda, Peritelefon\u00cda",
    "sg:phone":"+34 928 67 55 85",
    "sg:postcode":"35018",
    "sg:province":"Las Palmas",
    "wof:name":"Macrotelsa S.l.",
    "wof:placetype":"venue"
},
  "geometry": {"coordinates":[-15.4784650803,28.0919818878],"type":"Point"}
}