{
  "type": "Feature",
  "properties": {
    "iso:country":"ES",
    "sg:address":"Calle de Cabanes, 7",
    "sg:city":"Oropesa",
    "sg:orig_category":"Reposter\u00cdas",
    "sg:phone":"+34 964 31 29 11",
    "sg:postcode":"12594",
    "sg:province":"Castell\u00f3n",
    "wof:name":"Oro-pan S.d.",
    "wof:placetype":"venue"
},
  "geometry": {"coordinates":[0.1385155022,40.0933074951],"type":"Point"}
}