{
  "type": "Feature",
  "properties": {
    "addr:full":"Calle de Maria Cristina, 1 Ciudad Real Ciudad Real 13001",
    "addr:housenumber":"1",
    "addr:postcode":"13001",
    "addr:street":"Calle De Maria Cristina",
    "iso:country":"ES",
    "sg:address":"Calle de Maria Cristina, 1",
    "sg:city":"Ciudad Real",
    "sg:orig_category":"Lencer\u00cda Femenina, Corseter\u00cda, Trajes De Ba\u00d1o (al Por Menor)",
    "sg:phone":"+34 926 25 01 80",
    "sg:postcode":"13001",
    "sg:province":"Ciudad Real",
    "wof:name":"Rosas Rodriguez Maria Elena",
    "wof:placetype":"venue"
},
  "geometry": {"coordinates":[-3.9285309315,38.9861831665],"type":"Point"}
}