{
  "type": "Feature",
  "properties": {
    "addr:full":"Calle de General Moscardo, 5 Madrid Madrid 28020",
    "addr:housenumber":"5",
    "addr:postcode":"28020",
    "addr:street":"Calle De General Moscardo",
    "iso:country":"ES",
    "sg:address":"Calle de General Moscardo, 5",
    "sg:city":"Madrid",
    "sg:orig_category":"Empresarios",
    "sg:phone":"+34 915 76 93 24",
    "sg:postcode":"28020",
    "sg:province":"Madrid",
    "sg:website":"www.colegiosmundounido.es",
    "wof:name":"Colegios Del Mundo Unido",
    "wof:placetype":"venue"
},
  "geometry": {"coordinates":[-3.6972448826,40.4472770691],"type":"Point"}
}