{
  "type": "Feature",
  "properties": {
    "addr:full":"Carrer de Sant Pere Mitja, 12 Barcelona Barcelona 08003",
    "addr:housenumber":"12",
    "addr:postcode":"08003",
    "addr:street":"Carrer De Sant;Mitja",
    "iso:country":"ES",
    "sg:address":"Carrer de Sant Pere Mitja, 12",
    "sg:city":"Barcelona",
    "sg:classifiers":[
        {
            "category":"Personal",
            "subcategory":"Barber",
            "type":"Services"
        }
    ],
    "sg:phone":"+34 933 19 06 59",
    "sg:postcode":"08003",
    "sg:province":"Barcelona",
    "sg:tags":[
        "caballeros",
        "de",
        "peluqueros"
    ],
    "wof:name":"Vazquez Garcia Manuel",
    "wof:placetype":"venue"
},
  "geometry": {"coordinates":[2.1768898964,41.3872070312],"type":"Point"}
}