{
  "type": "Feature",
  "properties": {
    "iso:country":"ES",
    "sg:address":"Calle de Vivero, 16",
    "sg:city":"Almendralejo",
    "sg:orig_category":"Promotores Constructores",
    "sg:phone":"+34 924 66 10 42",
    "sg:postcode":"06200",
    "sg:province":"Badajoz",
    "wof:name":"Garcia Barriga Jose",
    "wof:placetype":"venue"
},
  "geometry": {"coordinates":[-6.4156007767,38.6830406189],"type":"Point"}
}