{
  "type": "Feature",
  "properties": {
    "addr:full":"C/ Escola (l'), 12 Alcoi Alicante 03801",
    "addr:housenumber":"12",
    "addr:postcode":"03801",
    "addr:street":"C / Escola L '",
    "iso:country":"ES",
    "sg:address":"C/ Escola (l'), 12",
    "sg:city":"Alcoi",
    "sg:orig_category":"Empresas De Pintura Y Revestimientos",
    "sg:phone":"+34 965 54 10 07",
    "sg:postcode":"03801",
    "sg:province":"Alicante",
    "wof:name":"Rodriguez Rios Cleto",
    "wof:placetype":"venue"
},
  "geometry": {"coordinates":[-0.4742360115,38.6984062195],"type":"Point"}
}