{
  "type": "Feature",
  "properties": {
    "iso:country":"ES",
    "sg:address":"Calle de Enrique Martinez, 9",
    "sg:city":"Gijon",
    "sg:orig_category":"Alquiler De Casas Y Habitaciones Amuebladas",
    "sg:phone":"+34 985 33 63 85",
    "sg:postcode":"33205",
    "sg:province":"Asturias",
    "wof:name":"Maria Inmaculada Servicio Domestico Lopez Vicuna",
    "wof:placetype":"venue"
},
  "geometry": {"coordinates":[-5.6533718109,43.5366287231],"type":"Point"}
}