{
  "type": "Feature",
  "properties": {
    "iso:country":"ES",
    "sg:address":"Calle de Padre Consolacion, 17",
    "sg:city":"Zaragoza",
    "sg:orig_category":"Peluqueros: De Se\u00d1oras",
    "sg:phone":"+34 976 43 43 09",
    "sg:postcode":"50003",
    "sg:province":"Zaragoza",
    "wof:name":"Marzo Navarro Encarnacion",
    "wof:placetype":"venue"
},
  "geometry": {"coordinates":[-0.8975819945,41.6616668701],"type":"Point"}
}