{
  "type": "Feature",
  "properties": {
    "iso:country":"ES",
    "sg:address":"Calle de Carrera, 8",
    "sg:city":"Luque",
    "sg:orig_category":"Centros De Coordinaci\u00d3n",
    "sg:phone":"+34 957 66 70 86",
    "sg:postcode":"14880",
    "sg:province":"C\u00f3rdoba",
    "wof:name":"Asesores De Luque S.l",
    "wof:placetype":"venue"
},
  "geometry": {"coordinates":[-4.2783813477,37.5589828491],"type":"Point"}
}