{
  "type": "Feature",
  "properties": {
    "addr:full":"Calle de Antonio Pino Perez, 6 Paso Santa Cruz De Tenerife 38750",
    "addr:housenumber":"6",
    "addr:postcode":"38750",
    "addr:street":"Calle De Antonio Pino Perez",
    "iso:country":"ES",
    "sg:address":"Calle de Antonio Pino Perez, 6",
    "sg:city":"Paso",
    "sg:orig_category":"Abogados",
    "sg:phone":"+34 922 48 60 62",
    "sg:postcode":"38750",
    "sg:province":"Santa Cruz De Tenerife",
    "wof:name":"Yanez Lopez Maria Jesus",
    "wof:placetype":"venue"
},
  "geometry": {"coordinates":[-17.8820228577,28.6518478394],"type":"Point"}
}