{
  "type": "Feature",
  "properties": {
    "addr:full":"Calle de Alfonso Xiii, 25 Noblejas Toledo 45350",
    "addr:housenumber":"25",
    "addr:postcode":"45350",
    "addr:street":"Calle De Alfonso Xiii",
    "iso:country":"ES",
    "sg:address":"Calle de Alfonso Xiii, 25",
    "sg:city":"Noblejas",
    "sg:orig_category":"Peluqueros: De Se\u00d1oras",
    "sg:phone":"+34 925 14 01 34",
    "sg:postcode":"45350",
    "sg:province":"Toledo",
    "wof:name":"Ballesteros Ruiperez Rita",
    "wof:placetype":"venue"
},
  "geometry": {"coordinates":[-3.4429445267,39.9777641296],"type":"Point"}
}