{
  "type": "Feature",
  "properties": {
    "addr:full":"Carr Salinas-villanueva Trabuco, Km. 0003,0 Archidona M\u00e1laga 29300",
    "addr:postcode":"29300",
    "addr:street":"Carr Salinas-Villanueva Trabuco Km. 0003,0;Ma\u0301Laga",
    "iso:country":"ES",
    "sg:address":"Carr Salinas-villanueva Trabuco, Km. 0003,0",
    "sg:city":"Archidona",
    "sg:orig_category":"Escayola Y Productos De Escayola (fabricaci\u00d3n, Al Por Mayor)",
    "sg:phone":"+34 952 71 44 10",
    "sg:postcode":"29300",
    "sg:province":"M\u00e1laga",
    "wof:name":"Yesos Las Lagunas S.a.",
    "wof:placetype":"venue"
},
  "geometry": {"coordinates":[-4.3311719894,37.0326042175],"type":"Point"}
}