{
  "type": "Feature",
  "properties": {
    "addr:full":"Calle de La Arboleda, 1 Briviesca Burgos 09240",
    "addr:housenumber":"1",
    "addr:postcode":"09240",
    "addr:street":"Calle De La Arboleda",
    "iso:country":"ES",
    "sg:address":"Calle de La Arboleda, 1",
    "sg:city":"Briviesca",
    "sg:orig_category":"Frutas Y Legumbres Frescas (al Por Mayor)",
    "sg:phone":"+34 947 59 10 88",
    "sg:postcode":"09240",
    "sg:province":"Burgos",
    "wof:name":"Olarte Martinez Pedro",
    "wof:placetype":"venue"
},
  "geometry": {"coordinates":[-3.3208739758,42.5481147766],"type":"Point"}
}