{
  "type": "Feature",
  "properties": {
    "iso:country":"ES",
    "sg:address":"Calle de Princesa, 28",
    "sg:city":"Madrid",
    "sg:orig_category":"Estancos",
    "sg:phone":"+34 915 42 07 93",
    "sg:postcode":"28008",
    "sg:province":"Madrid",
    "wof:name":"Mu\u00f1oz Garcia Juan Manuel",
    "wof:placetype":"venue"
},
  "geometry": {"coordinates":[-3.7141499519,40.4278106689],"type":"Point"}
}