{
  "type": "Feature",
  "properties": {
    "addr:full":"Carr Aigueta, 146 Bisbal D'emporda Girona 17100",
    "addr:housenumber":"146",
    "addr:postcode":"17100",
    "addr:street":"Carr Aigueta",
    "iso:country":"ES",
    "sg:address":"Carr Aigueta, 146",
    "sg:city":"Bisbal D'emporda",
    "sg:orig_category":"Art\u00cdculos De Regalo (al Por Menor)",
    "sg:phone":"+34 972 64 32 32",
    "sg:postcode":"17100",
    "sg:province":"Girona",
    "wof:name":"Puig Ballo Maria Teresa",
    "wof:placetype":"venue"
},
  "geometry": {"coordinates":[2.8187398911,41.9808616638],"type":"Point"}
}