{
  "type": "Feature",
  "properties": {
    "addr:full":"G.v. Corts Catalanes, 393 Barcelona Barcelona 08015",
    "addr:housenumber":"393",
    "addr:postcode":"08015",
    "addr:street":"Catalanes",
    "iso:country":"ES",
    "sg:address":"G.v. Corts Catalanes, 393",
    "sg:city":"Barcelona",
    "sg:orig_category":"Fabricaci\u00d3n E Instalaci\u00d3n De Cocinas Profesionales",
    "sg:phone":"+34 934 25 48 34",
    "sg:postcode":"08015",
    "sg:province":"Barcelona",
    "wof:name":"Santiago I Tomas Blanco S.l.",
    "wof:placetype":"venue"
},
  "geometry": {"coordinates":[2.1508040428,41.3767356873],"type":"Point"}
}