{
  "type": "Feature",
  "properties": {
    "addr:full":"Calle de Cabeza, 2 Horcajo Santiago Cuenca 16410",
    "addr:housenumber":"2",
    "addr:postcode":"16410",
    "addr:street":"Calle De Cabeza;Cuenca",
    "iso:country":"ES",
    "sg:address":"Calle de Cabeza, 2",
    "sg:city":"Horcajo Santiago",
    "sg:orig_category":"Supermercados Y Hipermercados",
    "sg:phone":"+34 969 12 80 08",
    "sg:postcode":"16410",
    "sg:province":"Cuenca",
    "wof:name":"Merca Horcajo S.l.",
    "wof:placetype":"venue"
},
  "geometry": {"coordinates":[-3.0007185936,39.8417930603],"type":"Point"}
}