{
  "type": "Feature",
  "properties": {
    "addr:full":"Calle de Cabrilleros, 9 Gijon Asturias 33213",
    "addr:housenumber":"9",
    "addr:postcode":"33213",
    "addr:street":"Calle De Cabrilleros",
    "iso:country":"ES",
    "sg:address":"Calle de Cabrilleros, 9",
    "sg:city":"Gijon",
    "sg:orig_category":"Confecci\u00d3n (fabricaci\u00d3n, Al Por Mayor)",
    "sg:phone":"+34 985 31 41 14",
    "sg:postcode":"33213",
    "sg:province":"Asturias",
    "sg:website":"www.temardecoracion.com",
    "wof:name":"Temar Decoracion S.l.",
    "wof:placetype":"venue"
},
  "geometry": {"coordinates":[-5.7032842636,43.5406036377],"type":"Point"}
}