{
  "type": "Feature",
  "properties": {
    "iso:country":"ES",
    "sg:address":"Avda Andalucia, 25",
    "sg:city":"Castellar",
    "sg:orig_category":"Cajas De Ahorro",
    "sg:phone":"+34 953 46 07 46",
    "sg:postcode":"23260",
    "sg:province":"Ja\u00e9n",
    "sg:website":"www.unicaja.es",
    "wof:name":"Unicaja",
    "wof:placetype":"venue"
},
  "geometry": {"coordinates":[-3.1303319931,38.255279541],"type":"Point"}
}