{
  "type": "Feature",
  "properties": {
    "iso:country":"ES",
    "sg:address":"Avda Alcalde Jose Aranda, 20",
    "sg:city":"Alcorcon",
    "sg:orig_category":"Estudios, Instalaci\u00d3n De Climatizaci\u00d3n",
    "sg:phone":"+34 914 86 12 41",
    "sg:postcode":"28923",
    "sg:province":"Madrid",
    "sg:website":"www.infomadel.com",
    "wof:name":"Madel Air Technical Diffusion S.a.",
    "wof:placetype":"venue"
},
  "geometry": {"coordinates":[-3.8210690022,40.3416900635],"type":"Point"}
}