{
  "type": "Feature",
  "properties": {
    "iso:country":"ES",
    "sg:address":"Avda Carmen Morcillo, 5",
    "sg:city":"Gojar",
    "sg:orig_category":"Cl\u00cdnicas Dentales",
    "sg:phone":"+34 958 50 86 30",
    "sg:postcode":"18150",
    "sg:province":"Granada",
    "wof:name":"Gomez Moreno Geraldo",
    "wof:placetype":"venue"
},
  "geometry": {"coordinates":[-3.6032791138,37.1053009033],"type":"Point"}
}