{
  "type": "Feature",
  "properties": {
    "iso:country":"ES",
    "sg:address":"Calle de Torre, 14",
    "sg:city":"Coru\u00d1a",
    "sg:orig_category":"Cl\u00cdnicas Dentales",
    "sg:phone":"+34 981 20 51 08",
    "sg:postcode":"15002",
    "sg:province":"La Coru\u00f1a",
    "wof:name":"Crespo Conti\u00f1as Maria Cristina",
    "wof:placetype":"venue"
},
  "geometry": {"coordinates":[-8.5979213715,42.8414230347],"type":"Point"}
}