{
  "type": "Feature",
  "properties": {
    "addr:full":"Carr Aviacion, 64 Manises Valencia 46940",
    "addr:housenumber":"64",
    "addr:postcode":"46940",
    "addr:street":"Carr Aviacion",
    "iso:country":"ES",
    "sg:address":"Carr Aviacion, 64",
    "sg:city":"Manises",
    "sg:orig_category":"Alquiler De Veh\u00cdculos: Turismos Y Utilitarios",
    "sg:phone":"+34 961 53 90 42",
    "sg:postcode":"46940",
    "sg:province":"Valencia",
    "wof:name":"Sol-mar Alquiler De Vehiculos S.l.",
    "wof:placetype":"venue"
},
  "geometry": {"coordinates":[-0.461488992,39.4922943115],"type":"Point"}
}