{
  "type": "Feature",
  "properties": {
    "iso:country":"ES",
    "sg:address":"Carrer de Pintor Velazquez, 35",
    "sg:city":"Crevillent",
    "sg:classifiers":[
        {
            "category":"Personal",
            "subcategory":"Barber",
            "type":"Services"
        }
    ],
    "sg:phone":"+34 965 40 57 61",
    "sg:postcode":"03330",
    "sg:province":"Alicante",
    "sg:tags":[
        "caballeros",
        "de",
        "peluqueros"
    ],
    "wof:name":"Belmonte Riquelme Jose",
    "wof:placetype":"venue"
},
  "geometry": {"coordinates":[-0.805588007,38.2452430725],"type":"Point"}
}