{
  "type": "Feature",
  "properties": {
    "iso:country":"ES",
    "sg:address":"Calle de Callosa D'en Sarria, 12",
    "sg:city":"Valencia",
    "sg:orig_category":"Centros M\u00c9dicos Y Sociales, Dispensarios",
    "sg:phone":"+34 963 42 31 80",
    "sg:postcode":"46007",
    "sg:province":"Valencia",
    "wof:name":"Clinica Doctor Lopez Casquero Sl",
    "wof:placetype":"venue"
},
  "geometry": {"coordinates":[-0.3867748082,39.4605064392],"type":"Point"}
}