{
  "type": "Feature",
  "properties": {
    "iso:country":"ES",
    "sg:address":"Calle de Juana Jimenez, 5",
    "sg:city":"Cervera Del Rio Alhama",
    "sg:orig_category":"Distribuci\u00d3n De Petr\u00d3leo Y Derivados",
    "sg:phone":"+34 941 19 87 77",
    "sg:postcode":"26520",
    "sg:province":"La Rioja",
    "wof:name":"Navagal S.l.",
    "wof:placetype":"venue"
},
  "geometry": {"coordinates":[-1.9524509907,42.0082015991],"type":"Point"}
}