{
  "type": "Feature",
  "properties": {
    "iso:country":"ES",
    "sg:address":"Afores, S/n",
    "sg:city":"Ogassa",
    "sg:orig_category":"Arenas, Guijarros Y Granulados",
    "sg:phone":"+34 972 72 07 36",
    "sg:postcode":"17861",
    "sg:province":"Girona",
    "wof:name":"Arids Ogassa S.l.",
    "wof:placetype":"venue"
},
  "geometry": {"coordinates":[2.2531929016,42.2634849548],"type":"Point"}
}