{
  "type": "Feature",
  "properties": {
    "addr:full":"Carr Major, 23 Albuixech Valencia 46550",
    "addr:housenumber":"23",
    "addr:postcode":"46550",
    "addr:street":"Carr Major",
    "iso:country":"ES",
    "sg:address":"Carr Major, 23",
    "sg:city":"Albuixech",
    "sg:orig_category":"Asilos De Ancianos. Centros Privados",
    "sg:phone":"+34 961 40 13 83",
    "sg:postcode":"46550",
    "sg:province":"Valencia",
    "wof:name":"Asociacion Democratica Provincial De Jubilados Y Pensionistas De Valencia",
    "wof:placetype":"venue"
},
  "geometry": {"coordinates":[-0.3228754997,39.5445098877],"type":"Point"}
}