{
  "type": "Feature",
  "properties": {
    "iso:country":"ES",
    "sg:address":"Rua Fernandez Areal, S/n",
    "sg:city":"Porri\u00f1o",
    "sg:orig_category":"Centros P\u00dablicos De Formaci\u00d3n Profesional Y T\u00c9cnica",
    "sg:phone":"+34 986 34 40 40",
    "sg:postcode":"36400",
    "sg:province":"Pontevedra",
    "wof:name":"Ilustre Colegio Provincial De Abogados",
    "wof:placetype":"venue"
},
  "geometry": {"coordinates":[-8.6191139221,42.1589012146],"type":"Point"}
}