{
  "type": "Feature",
  "properties": {
    "iso:country":"ES",
    "sg:address":"Calle de San Jose, 9",
    "sg:city":"Villanueva Ariscal",
    "sg:orig_category":"Mercer\u00cda, Lencer\u00cda (al Por Menor)",
    "sg:phone":"+34 955 71 30 71",
    "sg:postcode":"41808",
    "sg:province":"Sevilla",
    "wof:name":"Granados Rosa Maria De Los Angeles",
    "wof:placetype":"venue"
},
  "geometry": {"coordinates":[-6.1403222084,37.3960990906],"type":"Point"}
}