{
  "type": "Feature",
  "properties": {
    "addr:full":"Plaz General Prim, 1 Guadalajara Guadalajara 19001",
    "addr:housenumber":"1",
    "addr:postcode":"19001",
    "addr:street":"Prim",
    "iso:country":"ES",
    "sg:address":"Plaz General Prim, 1",
    "sg:city":"Guadalajara",
    "sg:orig_category":"Herboristas (al Por Menor)",
    "sg:phone":"+34 949 21 61 56",
    "sg:postcode":"19001",
    "sg:province":"Guadalajara",
    "wof:name":"Nu\u00f1ez Fisac Eduardo",
    "wof:placetype":"venue"
},
  "geometry": {"coordinates":[-3.1652770042,40.6336364746],"type":"Point"}
}