{
  "type": "Feature",
  "properties": {
    "iso:country":"ES",
    "sg:address":"Metro, S/n",
    "sg:city":"S. Agustin-playa Ingles",
    "sg:orig_category":"Molduras, Junquillos, Listones Y Molduras Perforadas",
    "sg:phone":"+34 928 76 73 05",
    "sg:postcode":"35100",
    "sg:province":"Las Palmas",
    "wof:name":"Oniche  Elena",
    "wof:placetype":"venue"
},
  "geometry": {"coordinates":[-15.4397096634,28.1302204132],"type":"Point"}
}