{
  "type": "Feature",
  "properties": {
    "iso:country":"ES",
    "sg:address":"Las Eras, 18",
    "sg:city":"Veguellina Orbigo",
    "sg:orig_category":"Empresas De Limpieza",
    "sg:phone":"+34 987 37 58 54",
    "sg:postcode":"24350",
    "sg:province":"Le\u00f3n",
    "wof:name":"Casta\u00f1osa Pellicena Jose Ignacio",
    "wof:placetype":"venue"
},
  "geometry": {"coordinates":[-5.8813700676,42.4405403137],"type":"Point"}
}