{
  "type": "Feature",
  "properties": {
    "addr:full":"Calle de Tarragona, 15 Getafe Madrid 28903",
    "addr:housenumber":"15",
    "addr:postcode":"28903",
    "addr:street":"Calle De Tarragona",
    "iso:country":"ES",
    "sg:address":"Calle de Tarragona, 15",
    "sg:city":"Getafe",
    "sg:orig_category":"Bisuter\u00cda, Joyer\u00cda, Relojer\u00cda (al Por Menor)",
    "sg:phone":"+34 916 83 79 29",
    "sg:postcode":"28903",
    "sg:province":"Madrid",
    "wof:name":"Gonzalez Alonso Concepcion",
    "wof:placetype":"venue"
},
  "geometry": {"coordinates":[-3.72073102,40.3105926514],"type":"Point"}
}