{
  "type": "Feature",
  "properties": {
    "addr:full":"Carrer de Covadonga, 25 Hospitalet Llobregat Barcelona 08906",
    "addr:housenumber":"25",
    "addr:postcode":"08906",
    "addr:street":"Carrer De Covadonga",
    "iso:country":"ES",
    "sg:address":"Carrer de Covadonga, 25",
    "sg:city":"Hospitalet Llobregat",
    "sg:orig_category":"Abogados",
    "sg:phone":"+34 934 38 76 86",
    "sg:postcode":"08906",
    "sg:province":"Barcelona",
    "wof:name":"Portella Marso Julian",
    "wof:placetype":"venue"
},
  "geometry": {"coordinates":[2.1025519371,41.375202179],"type":"Point"}
}