{
  "type": "Feature",
  "properties": {
    "addr:full":"Avda Eliseo Lerena, 33 Arnedo La Rioja 26580",
    "addr:housenumber":"33",
    "addr:postcode":"26580",
    "addr:street":"Avda Eliseo Lerena;Rioja",
    "iso:country":"ES",
    "sg:address":"Avda Eliseo Lerena, 33",
    "sg:city":"Arnedo",
    "sg:orig_category":"Muebles Y Accesorios Para Cocinas Y Cuartos De Ba\u00d1o (al Por Menor)",
    "sg:phone":"+34 941 38 03 81",
    "sg:postcode":"26580",
    "sg:province":"La Rioja",
    "wof:name":"Cervel Santa Cruz Aurelio",
    "wof:placetype":"venue"
},
  "geometry": {"coordinates":[-2.09947896,42.2230300903],"type":"Point"}
}