{
  "type": "Feature",
  "properties": {
    "addr:full":"Calle de Nicolas Belmonte, 1 Albacete Albacete 02001",
    "addr:housenumber":"1",
    "addr:postcode":"02001",
    "addr:street":"Calle De Nicolas Belmonte",
    "iso:country":"ES",
    "sg:address":"Calle de Nicolas Belmonte, 1",
    "sg:city":"Albacete",
    "sg:orig_category":"Peluquer\u00cdas, Peluquer\u00cda Mixta",
    "sg:phone":"+34 967 52 20 15",
    "sg:postcode":"02001",
    "sg:province":"Albacete",
    "wof:name":"Gonzalez  Marc Francois",
    "wof:placetype":"venue"
},
  "geometry": {"coordinates":[-1.8514410257,38.9926223755],"type":"Point"}
}