{
  "type": "Feature",
  "properties": {
    "iso:country":"ES",
    "sg:address":"Calle de Barrengoitia, 4",
    "sg:city":"Portugalete",
    "sg:orig_category":"Fabricaci\u00d3n, Distribuci\u00d3n De Material Para La Climatizaci\u00d3n, Aireaci\u00d3n Y Ventilaci\u00d3n",
    "sg:phone":"+34 944 72 06 27",
    "sg:postcode":"48920",
    "sg:province":"Vizcaya",
    "wof:name":"Instalaciones Anduri\u00f1a S.l.",
    "wof:placetype":"venue"
},
  "geometry": {"coordinates":[-3.0153543949,43.3168411255],"type":"Point"}
}