{
  "type": "Feature",
  "properties": {
    "addr:full":"Carrer de Governador Gonzalez, 6 Tarragona Tarragona 43001",
    "addr:housenumber":"6",
    "addr:postcode":"43001",
    "addr:street":"Carrer De Governador Gonzalez",
    "iso:country":"ES",
    "sg:address":"Carrer de Governador Gonzalez, 6",
    "sg:city":"Tarragona",
    "sg:orig_category":"Hosteler\u00cda, Empleados",
    "sg:phone":"+34 977 23 23 02",
    "sg:postcode":"43001",
    "sg:province":"Tarragona",
    "sg:website":"www.barcoimbra.com",
    "wof:name":"Gimenez Roig Jose",
    "wof:placetype":"venue"
},
  "geometry": {"coordinates":[1.2515660524,41.1148796082],"type":"Point"}
}