{
  "type": "Feature",
  "properties": {
    "addr:full":"Carr Recreo, 84 Vilanova I La Geltru Barcelona 08800",
    "addr:housenumber":"84",
    "addr:postcode":"08800",
    "addr:street":"Carr Recreo",
    "iso:country":"ES",
    "sg:address":"Carr Recreo, 84",
    "sg:city":"Vilanova I La Geltru",
    "sg:orig_category":"Sociedades, Compa\u00d1\u00cdas Aseguradoras",
    "sg:phone":"+34 938 14 30 29",
    "sg:postcode":"08800",
    "sg:province":"Barcelona",
    "sg:website":"www.fiatc.es",
    "wof:name":"Fiatc Mutua De Seguros S.a.",
    "wof:placetype":"venue"
},
  "geometry": {"coordinates":[1.7196860313,41.2231254578],"type":"Point"}
}