{
  "type": "Feature",
  "properties": {
    "addr:full":"Calle de Corral Del Agua, 11 Sevilla Sevilla 41008",
    "addr:housenumber":"11",
    "addr:postcode":"41008",
    "addr:street":"Calle De Corral Del Agua",
    "iso:country":"ES",
    "sg:address":"Calle de Corral Del Agua, 11",
    "sg:city":"Sevilla",
    "sg:orig_category":"Alimentaci\u00d3n General (al Por Menor)",
    "sg:phone":"+34 954 94 88 72",
    "sg:postcode":"41008",
    "sg:province":"Sevilla",
    "wof:name":"Castro Rio Antonio",
    "wof:placetype":"venue"
},
  "geometry": {"coordinates":[-5.972507,37.4200630188],"type":"Point"}
}