{
  "type": "Feature",
  "properties": {
    "addr:full":"Calle de Juan De Padilla, 22 Malaga M\u00e1laga 29008",
    "addr:housenumber":"22",
    "addr:postcode":"29008",
    "addr:street":"Calle De Juan De Padilla;Ma\u0301Laga",
    "iso:country":"ES",
    "sg:address":"Calle de Juan De Padilla, 22",
    "sg:city":"Malaga",
    "sg:orig_category":"Ingenier\u00cda, Centros De Estudios (diversos)",
    "sg:phone":"+34 952 21 17 99",
    "sg:postcode":"29008",
    "sg:province":"M\u00e1laga",
    "wof:name":"Nu\u00f1ez Esteban S.l.",
    "wof:placetype":"venue"
},
  "geometry": {"coordinates":[-4.4205369949,36.7232971191],"type":"Point"}
}