{
  "type": "Feature",
  "properties": {
    "addr:full":"Carrer de Violant Hongria R Arago, 128 Barcelona Barcelona 08028",
    "addr:housenumber":"hongria;128",
    "addr:postcode":"08028",
    "addr:street":"Carrer De Violant;R Arago",
    "iso:country":"ES",
    "sg:address":"Carrer de Violant Hongria R Arago, 128",
    "sg:city":"Barcelona",
    "sg:orig_category":"Caf\u00c9s, Bares, Cervecer\u00cdas",
    "sg:phone":"+34 934 90 29 31",
    "sg:postcode":"08028",
    "sg:province":"Barcelona",
    "wof:name":"Gal Gali 2003 S.l.",
    "wof:placetype":"venue"
},
  "geometry": {"coordinates":[2.1334059238,41.3797988892],"type":"Point"}
}