{
  "type": "Feature",
  "properties": {
    "iso:country":"ES",
    "sg:address":"Avda Constitucion, S/n",
    "sg:city":"Talavera Reina",
    "sg:orig_category":"Reposter\u00cdas",
    "sg:phone":"+34 925 82 33 45",
    "sg:postcode":"45600",
    "sg:province":"Toledo",
    "wof:name":"Boutique Del Pan Hermanos Robledo S.l.",
    "wof:placetype":"venue"
},
  "geometry": {"coordinates":[-4.8169140816,39.9629554749],"type":"Point"}
}