{
  "type": "Feature",
  "properties": {
    "addr:full":"Calle de Cami Reial, 158 Torrent Valencia 46900",
    "addr:housenumber":"158",
    "addr:postcode":"46900",
    "addr:street":"Calle De;Reial;Valencia",
    "iso:country":"ES",
    "sg:address":"Calle de Cami Reial, 158",
    "sg:city":"Torrent",
    "sg:orig_category":"Mec\u00c1nico Del Autom\u00d3vil",
    "sg:phone":"+34 961 56 05 05",
    "sg:postcode":"46900",
    "sg:province":"Valencia",
    "wof:name":"Veintor S.l.",
    "wof:placetype":"venue"
},
  "geometry": {"coordinates":[-0.5352355838,39.4127235413],"type":"Point"}
}