{
  "type": "Feature",
  "properties": {
    "addr:full":"Calle de Camino Real, 99 Colloto Asturias 33010",
    "addr:housenumber":"99",
    "addr:postcode":"33010",
    "addr:street":"Calle De Camino Real",
    "iso:country":"ES",
    "sg:address":"Calle de Camino Real, 99",
    "sg:city":"Colloto",
    "sg:orig_category":"M\u00c9dicos: Estomatolog\u00cda",
    "sg:phone":"+34 985 79 43 64",
    "sg:postcode":"33010",
    "sg:province":"Asturias",
    "wof:name":"Plasencia Amela Maria De La Paloma",
    "wof:placetype":"venue"
},
  "geometry": {"coordinates":[-5.7950024605,43.3780632019],"type":"Point"}
}