{
  "type": "Feature",
  "properties": {
    "addr:full":"Calle de Salvador Dali, 24 Velez-malaga M\u00e1laga 29700",
    "addr:housenumber":"24",
    "addr:postcode":"29700",
    "addr:street":"Calle De Salvador Dali",
    "iso:country":"ES",
    "sg:address":"Calle de Salvador Dali, 24",
    "sg:city":"Velez-malaga",
    "sg:orig_category":"Agentes, Concesionarios Y Sucursales De Veh\u00cdculos",
    "sg:phone":"+34 952 55 89 89",
    "sg:postcode":"29700",
    "sg:province":"M\u00e1laga",
    "wof:name":"Axarauto Axarquia S.l.",
    "wof:placetype":"venue"
},
  "geometry": {"coordinates":[-4.0982708931,36.7637672424],"type":"Point"}
}