{
  "type": "Feature",
  "properties": {
    "iso:country":"ES",
    "sg:address":"Calle de Guadalora, S/n",
    "sg:city":"Lora Rio",
    "sg:orig_category":"M\u00c9dicos: Estomatolog\u00cda",
    "sg:phone":"+34 955 80 20 97",
    "sg:postcode":"41440",
    "sg:province":"Sevilla",
    "wof:name":"Morillo Eslava Juan",
    "wof:placetype":"venue"
},
  "geometry": {"coordinates":[-5.5239038467,37.6594314575],"type":"Point"}
}