{
  "type": "Feature",
  "properties": {
    "iso:country":"ES",
    "sg:address":"Carrer de Sant Isidre (de), 60",
    "sg:city":"S. Carles Rapita",
    "sg:orig_category":"Ropa Para Se\u00d1oras Y Caballeros (al Por Menor)",
    "sg:phone":"+34 977 74 12 50",
    "sg:postcode":"43540",
    "sg:province":"Tarragona",
    "wof:name":"Clua Esteve Francisca",
    "wof:placetype":"venue"
},
  "geometry": {"coordinates":[0.590568006,40.6188545227],"type":"Point"}
}