{
  "type": "Feature",
  "properties": {
    "addr:full":"Calle de Asalto, 53 Zaragoza Zaragoza 50002",
    "addr:housenumber":"53",
    "addr:postcode":"50002",
    "addr:street":"Calle De Asalto",
    "iso:country":"ES",
    "sg:address":"Calle de Asalto, 53",
    "sg:city":"Zaragoza",
    "sg:orig_category":"Florister\u00cdas",
    "sg:phone":"+34 976 20 19 23",
    "sg:postcode":"50002",
    "sg:province":"Zaragoza",
    "wof:name":"Solans Pradera Marta",
    "wof:placetype":"venue"
},
  "geometry": {"coordinates":[-0.8718860149,41.6492004395],"type":"Point"}
}