{
  "type": "Feature",
  "properties": {
    "iso:country":"ES",
    "sg:address":"Calle de Madres Plaza De Mayo, 9",
    "sg:city":"Zaragoza",
    "sg:orig_category":"Venta, Alquiler De V\u00cddeo",
    "sg:phone":"+34 976 33 15 58",
    "sg:postcode":"50017",
    "sg:province":"Zaragoza",
    "sg:website":"www.iasainformatico.com",
    "wof:name":"Iasa Informatica S.l.",
    "wof:placetype":"venue"
},
  "geometry": {"coordinates":[-0.9143540263,41.6535987854],"type":"Point"}
}