{
  "type": "Feature",
  "properties": {
    "addr:full":"Tafalla, 1 Garvin C\u00e1ceres 10333",
    "addr:housenumber":"1",
    "addr:postcode":"10333",
    "addr:street":"Tafalla;Ca\u0301Ceres",
    "iso:country":"ES",
    "sg:address":"Tafalla, 1",
    "sg:city":"Garvin",
    "sg:orig_category":"Administraciones Regionales, Departamentales Y Locales",
    "sg:phone":"+34 927 55 30 52",
    "sg:postcode":"10333",
    "sg:province":"C\u00e1ceres",
    "wof:name":"Ayuntamiento De Garvin",
    "wof:placetype":"venue"
},
  "geometry": {"coordinates":[-5.3465380669,39.7195625305],"type":"Point"}
}