{
  "type": "Feature",
  "properties": {
    "addr:full":"C/ Paisses, De Ses, S/n S. Antoni Portmany Islas Baleares 07820",
    "addr:postcode":"07820",
    "addr:street":"C / Paisses De Ses S / N S. Antoni Portmany",
    "iso:country":"ES",
    "sg:address":"C/ Paisses, De Ses, S/n",
    "sg:city":"S. Antoni Portmany",
    "sg:orig_category":"Iglesia Cat\u00d3lica",
    "sg:phone":"+34 971 34 21 43",
    "sg:postcode":"07820",
    "sg:province":"Islas Baleares",
    "wof:name":"Obispado De Ibiza",
    "wof:placetype":"venue"
},
  "geometry": {"coordinates":[1.5188339949,39.1094055176],"type":"Point"}
}