{
  "type": "Feature",
  "properties": {
    "iso:country":"ES",
    "sg:address":"Carrer de Arago, 461",
    "sg:city":"Barcelona",
    "sg:orig_category":"Abogados",
    "sg:phone":"+34 932 32 60 36",
    "sg:postcode":"08013",
    "sg:province":"Barcelona",
    "wof:name":"Rubio Navarro Enrique",
    "wof:placetype":"venue"
},
  "geometry": {"coordinates":[2.1790649891,41.4030380249],"type":"Point"}
}