{
  "type": "Feature",
  "properties": {
    "addr:full":"Carr Aulet, 2 Cellera Ter Girona 17165",
    "addr:housenumber":"2",
    "addr:postcode":"17165",
    "addr:street":"Carr Aulet;Cellera Ter",
    "iso:country":"ES",
    "sg:address":"Carr Aulet, 2",
    "sg:city":"Cellera Ter",
    "sg:orig_category":"Compraventa De Antig\u00dcedades",
    "sg:phone":"+34 972 42 10 25",
    "sg:postcode":"17165",
    "sg:province":"Girona",
    "sg:website":"www.lluisdomenech.com",
    "wof:name":"Domenech Matillo Lluis",
    "wof:placetype":"venue"
},
  "geometry": {"coordinates":[2.6211791039,41.9696998596],"type":"Point"}
}