{
  "type": "Feature",
  "properties": {
    "iso:country":"ES",
    "sg:address":"Avda Agirre Lehendakaria, 36",
    "sg:city":"Urbi",
    "sg:orig_category":"Farmacias",
    "sg:phone":"+34 944 49 04 94",
    "sg:postcode":"48970",
    "sg:province":"Vizcaya",
    "wof:name":"Solaguren Elordui Izaskun",
    "wof:placetype":"venue"
},
  "geometry": {"coordinates":[-2.8794789314,43.2355804443],"type":"Point"}
}