{
  "type": "Feature",
  "properties": {
    "iso:country":"ES",
    "sg:address":"Carr Closa D'en Llop, S/n",
    "sg:city":"Escala",
    "sg:orig_category":"Mec\u00c1nico Del Autom\u00d3vil",
    "sg:phone":"+34 972 77 11 74",
    "sg:postcode":"17130",
    "sg:province":"Girona",
    "wof:name":"Lagares Zamora Juan",
    "wof:placetype":"venue"
},
  "geometry": {"coordinates":[3.1333498955,42.1271591187],"type":"Point"}
}