{
  "type": "Feature",
  "properties": {
    "addr:full":"Carr De Val Ncia, 14 Benicarlo Castell\u00f3n 12580",
    "addr:housenumber":"14",
    "addr:postcode":"12580",
    "addr:street":"Carr De Val Ncia",
    "iso:country":"ES",
    "sg:address":"Carr De Val Ncia, 14",
    "sg:city":"Benicarlo",
    "sg:orig_category":"M\u00c9dicos: Cirug\u00cda Pl\u00c1stica, Reconstructiva Y Est\u00c9tica",
    "sg:phone":"+34 964 46 09 90",
    "sg:postcode":"12580",
    "sg:province":"Castell\u00f3n",
    "wof:name":"Marala Belleza S.c.",
    "wof:placetype":"venue"
},
  "geometry": {"coordinates":[0.4042100012,40.4457893372],"type":"Point"}
}