{
  "type": "Feature",
  "properties": {
    "iso:country":"ES",
    "sg:address":"Avda Mestre Mateo (do), 4",
    "sg:city":"Santiago De Compostela",
    "sg:orig_category":"Ebanister\u00cda",
    "sg:phone":"+34 981 52 13 07",
    "sg:postcode":"15706",
    "sg:province":"La Coru\u00f1a",
    "wof:name":"Ebanisteria La Union S. L.",
    "wof:placetype":"venue"
},
  "geometry": {"coordinates":[-8.5636405945,42.8719062805],"type":"Point"}
}