{
  "type": "Feature",
  "properties": {
    "iso:country":"ES",
    "sg:address":"Calle de Artekalea, 16",
    "sg:city":"Gernika-lumo",
    "sg:orig_category":"Inmobiliaria (agencias)",
    "sg:phone":"+34 946 25 30 44",
    "sg:postcode":"48300",
    "sg:province":"Vizcaya",
    "wof:name":"Lur Estudio Inmobiliario S.l.",
    "wof:placetype":"venue"
},
  "geometry": {"coordinates":[-2.6785755157,43.3159332275],"type":"Point"}
}