{
  "type": "Feature",
  "properties": {
    "addr:full":"Pase Alameda, 31 Valencia Valencia 46023",
    "addr:housenumber":"31",
    "addr:postcode":"46023",
    "addr:street":"Alameda",
    "iso:country":"ES",
    "sg:address":"Pase Alameda, 31",
    "sg:city":"Valencia",
    "sg:orig_category":"Artesan\u00cda Y Trabajos Manuales: Suministros (al Por Menor)",
    "sg:phone":"+34 963 37 00 68",
    "sg:postcode":"46023",
    "sg:province":"Valencia",
    "sg:website":"ww.asadornoblezagaucha.com",
    "wof:name":"Artenoa S.l.",
    "wof:placetype":"venue"
},
  "geometry": {"coordinates":[-0.3481385112,39.4565696716],"type":"Point"}
}