{
  "type": "Feature",
  "properties": {
    "addr:full":"Calle de Lopez Se\u00d1a, 11 Laredo Cantabria 39770",
    "addr:housenumber":"11",
    "addr:postcode":"39770",
    "addr:street":"Calle De;Sen\u0303A",
    "iso:country":"ES",
    "sg:address":"Calle de Lopez Se\u00d1a, 11",
    "sg:city":"Laredo",
    "sg:orig_category":"Fabricaci\u00d3n De Sobres, Bolsas Y Fundas",
    "sg:phone":"+34 942 60 60 51",
    "sg:postcode":"39770",
    "sg:province":"Cantabria",
    "wof:name":"Salcines Ortiz Santos",
    "wof:placetype":"venue"
},
  "geometry": {"coordinates":[-3.4168350697,43.4108047485],"type":"Point"}
}