{
  "type": "Feature",
  "properties": {
    "iso:country":"ES",
    "sg:address":"Calle de Saladillo, 5",
    "sg:city":"Estepa",
    "sg:orig_category":"Electricidad: Instaladores",
    "sg:phone":"+34 954 82 07 29",
    "sg:postcode":"41560",
    "sg:province":"Sevilla",
    "wof:name":"Montajes Electricos Estepa S.c.",
    "wof:placetype":"venue"
},
  "geometry": {"coordinates":[-4.8792309761,37.2895698547],"type":"Point"}
}