{
  "type": "Feature",
  "properties": {
    "iso:country":"ES",
    "sg:address":"Avda Milagrosa, 2",
    "sg:city":"Carballo",
    "sg:orig_category":"Ropa Para Se\u00d1oras (al Por Menor)",
    "sg:phone":"+34 981 70 10 21",
    "sg:postcode":"15100",
    "sg:province":"La Coru\u00f1a",
    "wof:name":"Arijon Varela Jose",
    "wof:placetype":"venue"
},
  "geometry": {"coordinates":[-8.6872873306,43.2086906433],"type":"Point"}
}