{
  "type": "Feature",
  "properties": {
    "iso:country":"ES",
    "sg:address":"Calle de Juan Sebastian Bach, 21",
    "sg:city":"Tomillares",
    "sg:orig_category":"Inform\u00c1tica (estudios, Servicios, Asesor\u00cda, Formaci\u00d3n)",
    "sg:phone":"+34 952 41 72 03",
    "sg:postcode":"29130",
    "sg:province":"M\u00e1laga",
    "wof:name":"Innova Farmacias S.l.",
    "wof:placetype":"venue"
},
  "geometry": {"coordinates":[-4.5667190552,36.6618614197],"type":"Point"}
}