{
  "type": "Feature",
  "properties": {
    "addr:full":"Rua Aquilino Iglesia Alvari\u00d1o (poeta), 1 Lugo Lugo 27004",
    "addr:housenumber":"1",
    "addr:postcode":"27004",
    "addr:street":"Rua Aquilino Iglesia Alvarin\u0303O Poeta",
    "iso:country":"ES",
    "sg:address":"Rua Aquilino Iglesia Alvari\u00d1o (poeta), 1",
    "sg:city":"Lugo",
    "sg:orig_category":"Farmacias",
    "sg:phone":"+34 982 20 00 97",
    "sg:postcode":"27004",
    "sg:province":"Lugo",
    "wof:name":"De Frutos Del Rio Ana",
    "wof:placetype":"venue"
},
  "geometry": {"coordinates":[-7.5720891953,43.0170707703],"type":"Point"}
}