{
  "type": "Feature",
  "properties": {
    "iso:country":"ES",
    "sg:address":"Calle de Horno, 25",
    "sg:city":"Castillo De Villamalefa",
    "sg:orig_category":"Administraciones Regionales, Departamentales Y Locales",
    "sg:phone":"+34 964 37 50 01",
    "sg:postcode":"12123",
    "sg:province":"Castell\u00f3n",
    "wof:name":"Ayuntamiento De Castillo De Villamalefa Oficinas",
    "wof:placetype":"venue"
},
  "geometry": {"coordinates":[-0.37970981,40.1306228638],"type":"Point"}
}