{
  "type": "Feature",
  "properties": {
    "addr:full":"Carrer de Arago, 13 Santa Perpetua De Mogoda Barcelona 08130",
    "addr:housenumber":"13",
    "addr:postcode":"08130",
    "addr:street":"Carrer De Arago",
    "iso:country":"ES",
    "sg:address":"Carrer de Arago, 13",
    "sg:city":"Santa Perpetua De Mogoda",
    "sg:orig_category":"Limpieza Con Chorro De Arena Y Con Granalla, Pulido",
    "sg:phone":"+34 935 44 96 79",
    "sg:postcode":"08130",
    "sg:province":"Barcelona",
    "wof:name":"Garcia Llorente Antonio",
    "wof:placetype":"venue"
},
  "geometry": {"coordinates":[2.1772398949,41.5427360535],"type":"Point"}
}