{
  "type": "Feature",
  "properties": {
    "iso:country":"ES",
    "sg:address":"Calle de Antonio De Ulloa, 2",
    "sg:city":"Flota",
    "sg:orig_category":"Ense\u00d1anza Variada",
    "sg:phone":"+34 968 20 14 85",
    "sg:postcode":"30008",
    "sg:province":"Murcia",
    "wof:name":"Blasco Garcia Virginia",
    "wof:placetype":"venue"
},
  "geometry": {"coordinates":[-1.1302499771,37.9829597473],"type":"Point"}
}