{
  "type": "Feature",
  "properties": {
    "addr:full":"Calle de Cervantes, 3 Losar Vera C\u00e1ceres 10460",
    "addr:housenumber":"3",
    "addr:postcode":"10460",
    "addr:street":"Calle De Cervantes",
    "iso:country":"ES",
    "sg:address":"Calle de Cervantes, 3",
    "sg:city":"Losar Vera",
    "sg:orig_category":"Plomeros",
    "sg:phone":"+34 927 57 04 55",
    "sg:postcode":"10460",
    "sg:province":"C\u00e1ceres",
    "wof:name":"Vicente Luis Claudio",
    "wof:placetype":"venue"
},
  "geometry": {"coordinates":[-5.6058077812,40.1224632263],"type":"Point"}
}