{
  "type": "Feature",
  "properties": {
    "iso:country":"ES",
    "sg:address":"Carr Rutlla, 100",
    "sg:city":"Girona",
    "sg:orig_category":"Peluqueros: De Se\u00d1oras",
    "sg:phone":"+34 972 21 85 13",
    "sg:postcode":"17002",
    "sg:province":"Girona",
    "wof:name":"Serra Vall-llosera Leonor",
    "wof:placetype":"venue"
},
  "geometry": {"coordinates":[2.8223829269,41.9757080078],"type":"Point"}
}