{
  "type": "Feature",
  "properties": {
    "addr:full":"Carrer de Envalira, 21 Cunit Tarragona 43881",
    "addr:housenumber":"21",
    "addr:postcode":"43881",
    "addr:street":"Carrer De Envalira",
    "iso:country":"ES",
    "sg:address":"Carrer de Envalira, 21",
    "sg:city":"Cunit",
    "sg:orig_category":"Perfumer\u00cda Y Cosm\u00c9tica (fabricaci\u00d3n, Al Por Mayor)",
    "sg:phone":"+34 977 16 41 87",
    "sg:postcode":"43881",
    "sg:province":"Tarragona",
    "wof:name":"Campos Delcasso Sandra",
    "wof:placetype":"venue"
},
  "geometry": {"coordinates":[1.616664052,41.2079277039],"type":"Point"}
}