{
  "type": "Feature",
  "properties": {
    "addr:full":"Pg Sant Joan, 149 Manlleu Barcelona 08560",
    "addr:housenumber":"149",
    "addr:postcode":"08560",
    "addr:street":"Pg Sant Joan",
    "iso:country":"ES",
    "sg:address":"Pg Sant Joan, 149",
    "sg:city":"Manlleu",
    "sg:orig_category":"Inmobiliaria (agencias)",
    "sg:phone":"+34 938 50 68 00",
    "sg:postcode":"08560",
    "sg:province":"Barcelona",
    "wof:name":"Codol S.a.",
    "wof:placetype":"venue"
},
  "geometry": {"coordinates":[2.2837300301,42.0043907166],"type":"Point"}
}