{
  "type": "Feature",
  "properties": {
    "addr:full":"Carrer de Sol, 31 Pedreguer Alicante 03750",
    "addr:housenumber":"31",
    "addr:postcode":"03750",
    "addr:street":"Carrer De Sol",
    "iso:country":"ES",
    "sg:address":"Carrer de Sol, 31",
    "sg:city":"Pedreguer",
    "sg:orig_category":"Empresas De Carpinter\u00cda De Madera",
    "sg:phone":"+34 965 76 13 82",
    "sg:postcode":"03750",
    "sg:province":"Alicante",
    "wof:name":"Agulles Abella Jose Miguel",
    "wof:placetype":"venue"
},
  "geometry": {"coordinates":[0.0359854996,38.7938804626],"type":"Point"}
}