{
  "type": "Feature",
  "properties": {
    "addr:full":"Rua Arquitecto Alberto Baltar, 1 Vigo Pontevedra 36210",
    "addr:housenumber":"1",
    "addr:postcode":"36210",
    "addr:street":"Rua Arquitecto Alberto Baltar",
    "iso:country":"ES",
    "sg:address":"Rua Arquitecto Alberto Baltar, 1",
    "sg:city":"Vigo",
    "sg:orig_category":"Peluqueros: De Se\u00d1oras",
    "sg:phone":"+34 986 23 07 79",
    "sg:postcode":"36210",
    "sg:province":"Pontevedra",
    "wof:name":"Garrido Peluqueros S.l.",
    "wof:placetype":"venue"
},
  "geometry": {"coordinates":[-8.7360191345,42.2177772522],"type":"Point"}
}