{
  "type": "Feature",
  "properties": {
    "iso:country":"ES",
    "sg:address":"Carrer de Roger De Flor, 25",
    "sg:city":"Gava",
    "sg:orig_category":"Peluquer\u00cdas, Peluquer\u00cda Mixta",
    "sg:phone":"+34 936 62 35 09",
    "sg:postcode":"08850",
    "sg:province":"Barcelona",
    "wof:name":"Garcia Martinez Ana",
    "wof:placetype":"venue"
},
  "geometry": {"coordinates":[1.9972219467,41.3099517822],"type":"Point"}
}