{
  "type": "Feature",
  "properties": {
    "iso:country":"ES",
    "sg:address":"Avgd President Companys, 25",
    "sg:city":"Badalona",
    "sg:orig_category":"Promotores Constructores",
    "sg:phone":"+34 933 89 58 01",
    "sg:postcode":"08911",
    "sg:province":"Barcelona",
    "wof:name":"Promocions Mendez 44-54 S.l.",
    "wof:placetype":"venue"
},
  "geometry": {"coordinates":[2.2480740547,41.4537811279],"type":"Point"}
}