{
  "type": "Feature",
  "properties": {
    "addr:full":"Plaz Espa\u00d1a (de), 2 Bullas Murcia 30180",
    "addr:postcode":"30180",
    "addr:street":"Plaz",
    "iso:country":"ES",
    "sg:address":"Plaz Espa\u00d1a (de), 2",
    "sg:city":"Bullas",
    "sg:orig_category":"Administraciones Regionales, Departamentales Y Locales",
    "sg:phone":"+34 968 65 20 31",
    "sg:postcode":"30180",
    "sg:province":"Murcia",
    "sg:website":"www.bullas.net",
    "wof:name":"Ayuntamiento De Bullas",
    "wof:placetype":"venue"
},
  "geometry": {"coordinates":[-1.666893959,38.0503196716],"type":"Point"}
}