{
  "type": "Feature",
  "properties": {
    "iso:country":"ES",
    "sg:address":"Calle de Menendez Y Pelayo, 6",
    "sg:city":"Bu\u00f1ol",
    "sg:orig_category":"Alimentaci\u00d3n General (al Por Menor)",
    "sg:phone":"+34 962 50 16 99",
    "sg:postcode":"46360",
    "sg:province":"Valencia",
    "wof:name":"Iglesia Galan Jose Manuel",
    "wof:placetype":"venue"
},
  "geometry": {"coordinates":[-0.7910190225,39.4202880859],"type":"Point"}
}