{
  "type": "Feature",
  "properties": {
    "iso:country":"ES",
    "sg:address":"Carr Teulera, 42",
    "sg:city":"Santa Cristina D'aro",
    "sg:orig_category":"Inmobiliaria (agencias)",
    "sg:phone":"+34 972 83 51 82",
    "sg:postcode":"17246",
    "sg:province":"Girona",
    "sg:website":"www.inmodaisy.com",
    "wof:name":"Finca Reli S.l.",
    "wof:placetype":"venue"
},
  "geometry": {"coordinates":[2.8381810188,41.9668312073],"type":"Point"}
}