{
  "type": "Feature",
  "properties": {
    "addr:full":"Calle de Antonio Machado, 3 Tarancon Cuenca 16400",
    "addr:housenumber":"3",
    "addr:postcode":"16400",
    "addr:street":"Calle De Antonio Machado",
    "iso:country":"ES",
    "sg:address":"Calle de Antonio Machado, 3",
    "sg:city":"Tarancon",
    "sg:orig_category":"Cl\u00cdnicas M\u00c9dicas",
    "sg:phone":"+34 969 32 07 51",
    "sg:postcode":"16400",
    "sg:province":"Cuenca",
    "wof:name":"Garcia Martinez Jose Joaquin",
    "wof:placetype":"venue"
},
  "geometry": {"coordinates":[-3.0081450939,40.010974884],"type":"Point"}
}