{
  "type": "Feature",
  "properties": {
    "iso:country":"ES",
    "sg:address":"Avda Ancares, 25",
    "sg:city":"Vega Espinareda",
    "sg:orig_category":"Pescader\u00cdas (al Por Menor)",
    "sg:phone":"+34 987 56 87 52",
    "sg:postcode":"24430",
    "sg:province":"Le\u00f3n",
    "wof:name":"Alvarez Alvarez Felicitas",
    "wof:placetype":"venue"
},
  "geometry": {"coordinates":[-6.6522164345,42.7256240845],"type":"Point"}
}