{
  "type": "Feature",
  "properties": {
    "iso:country":"ES",
    "sg:address":"Carrer de Sant Antoni Maria Claret, 34",
    "sg:city":"Tarragona",
    "sg:orig_category":"Motocicletas (agentes, Concesionarios)",
    "sg:phone":"+34 977 24 45 29",
    "sg:postcode":"43002",
    "sg:province":"Tarragona",
    "wof:name":"Folch Endurance S.a.",
    "wof:placetype":"venue"
},
  "geometry": {"coordinates":[1.2453509569,41.1223258972],"type":"Point"}
}