{
  "type": "Feature",
  "properties": {
    "addr:full":"Grup Ganguren, 1 Ortuella Vizcaya 48530",
    "addr:housenumber":"1",
    "addr:postcode":"48530",
    "addr:street":"Ganguren",
    "iso:country":"ES",
    "sg:address":"Grup Ganguren, 1",
    "sg:city":"Ortuella",
    "sg:orig_category":"Comercio, Reparaci\u00d3n De Bicicletas, De Motocicletas, De Accesorios",
    "sg:phone":"+34 946 64 18 27",
    "sg:postcode":"48530",
    "sg:province":"Vizcaya",
    "wof:name":"Hermanos Portillo Construcciones Y Reformas,sl",
    "wof:placetype":"venue"
},
  "geometry": {"coordinates":[-3.0571398735,43.3119621277],"type":"Point"}
}