{
  "type": "Feature",
  "properties": {
    "addr:full":"Calle de San Esteban, 24 Sevilla Sevilla 41003",
    "addr:housenumber":"24",
    "addr:postcode":"41003",
    "addr:street":"Calle De San Esteban",
    "iso:country":"ES",
    "sg:address":"Calle de San Esteban, 24",
    "sg:city":"Sevilla",
    "sg:orig_category":"Alquiler De Bicicletas Y Motocicletas",
    "sg:phone":"+34 954 53 14 11",
    "sg:postcode":"41003",
    "sg:province":"Sevilla",
    "wof:name":"Astigarraga Garcia Enrique",
    "wof:placetype":"venue"
},
  "geometry": {"coordinates":[-5.9855465889,37.3896560669],"type":"Point"}
}