{
  "type": "Feature",
  "properties": {
    "addr:full":"Ctra Caravaca, Km. 0001,0 Cehegin Murcia 30430",
    "addr:postcode":"30430",
    "addr:street":"Ctra Caravaca Km. 0001,0",
    "iso:country":"ES",
    "sg:address":"Ctra Caravaca, Km. 0001,0",
    "sg:city":"Cehegin",
    "sg:orig_category":"Frutas Y Legumbres Frescas (al Por Mayor)",
    "sg:phone":"+34 968 74 18 74",
    "sg:postcode":"30430",
    "sg:province":"Murcia",
    "wof:name":"Frutas Hermanos Caparros Bustamante S.l.",
    "wof:placetype":"venue"
},
  "geometry": {"coordinates":[-1.796923995,38.0913162231],"type":"Point"}
}