{
  "type": "Feature",
  "properties": {
    "iso:country":"ES",
    "sg:address":"Pol Ind Mezquita, 410",
    "sg:city":"Vall Uixo",
    "sg:orig_category":"Producci\u00d3n De Abonos Y De Fertilizantes",
    "sg:phone":"+34 964 65 27 06",
    "sg:postcode":"12600",
    "sg:province":"Castell\u00f3n",
    "sg:website":"www.compo.es",
    "wof:name":"Compo Agricultura S.l.",
    "wof:placetype":"venue"
},
  "geometry": {"coordinates":[-0.2315589935,39.8232955933],"type":"Point"}
}