{
  "type": "Feature",
  "properties": {
    "addr:full":"Calle de Eskortealdea, S/n Garralda Navarra 31693",
    "addr:housenumber":"s",
    "addr:postcode":"31693",
    "addr:street":"Calle De Eskortealdea;/ N",
    "iso:country":"ES",
    "sg:address":"Calle de Eskortealdea, S/n",
    "sg:city":"Garralda",
    "sg:orig_category":"Trabajos De Soldaduras",
    "sg:phone":"+34 948 76 41 10",
    "sg:postcode":"31693",
    "sg:province":"Navarra",
    "wof:name":"Noain Erro Enrique",
    "wof:placetype":"venue"
},
  "geometry": {"coordinates":[-1.2896740437,42.9495735168],"type":"Point"}
}