{
  "type": "Feature",
  "properties": {
    "addr:full":"Calle de Encarnacion, 27 Bilbao Vizcaya 48006",
    "addr:housenumber":"27",
    "addr:postcode":"48006",
    "addr:street":"Calle De Encarnacion",
    "iso:country":"ES",
    "sg:address":"Calle de Encarnacion, 27",
    "sg:city":"Bilbao",
    "sg:orig_category":"Chapas Y Flejes De Acero",
    "sg:phone":"+34 944 33 68 05",
    "sg:postcode":"48006",
    "sg:province":"Vizcaya",
    "wof:name":"Angulo Y Angulo S. L.",
    "wof:placetype":"venue"
},
  "geometry": {"coordinates":[-2.9209558964,43.2542304993],"type":"Point"}
}