{
  "type": "Feature",
  "properties": {
    "addr:full":"El Roturo, 4 Villar De Arnedo La Rioja 26511",
    "addr:housenumber":"4",
    "addr:postcode":"26511",
    "addr:street":"Roturo;Rioja",
    "iso:country":"ES",
    "sg:address":"El Roturo, 4",
    "sg:city":"Villar De Arnedo",
    "sg:orig_category":"Confecci\u00d3n De Zapatos",
    "sg:phone":"+34 941 15 91 40",
    "sg:postcode":"26511",
    "sg:province":"La Rioja",
    "wof:name":"Calzados Zel's S.l.",
    "wof:placetype":"venue"
},
  "geometry": {"coordinates":[-2.0894799232,42.3183135986],"type":"Point"}
}