{
  "type": "Feature",
  "properties": {
    "iso:country":"ES",
    "sg:address":"Carr Francesc D'albranca, 15",
    "sg:city":"Migjorn Gran",
    "sg:orig_category":"Contables",
    "sg:phone":"+34 971 37 04 59",
    "sg:postcode":"07749",
    "sg:province":"Islas Baleares",
    "wof:name":"Gomila Pons Juana",
    "wof:placetype":"venue"
},
  "geometry": {"coordinates":[4.0494160652,39.9461326599],"type":"Point"}
}