{
  "type": "Feature",
  "properties": {
    "addr:full":"Calle de Pintores Puget, 4 Santa Eulalia Islas Baleares 07840",
    "addr:housenumber":"4",
    "addr:postcode":"07840",
    "addr:street":"Calle De Pintores Puget",
    "iso:country":"ES",
    "sg:address":"Calle de Pintores Puget, 4",
    "sg:city":"Santa Eulalia",
    "sg:orig_category":"Aguas (distribuci\u00d3n, Servicios)",
    "sg:phone":"+34 971 33 14 11",
    "sg:postcode":"07840",
    "sg:province":"Islas Baleares",
    "wof:name":"Aqualia Gestion Integral Del Agua S.a.",
    "wof:placetype":"venue"
},
  "geometry": {"coordinates":[1.5330593586,38.9836425781],"type":"Point"}
}