{
  "type": "Feature",
  "properties": {
    "addr:full":"Carrer de Mossen Juliana, 13 Barcelona Barcelona 08027",
    "addr:housenumber":"13",
    "addr:postcode":"08027",
    "addr:street":"Carrer De Mossen Juliana",
    "iso:country":"ES",
    "sg:address":"Carrer de Mossen Juliana, 13",
    "sg:city":"Barcelona",
    "sg:orig_category":"Aparcamientos (infraestructuras, Accesorios)",
    "sg:phone":"+34 933 52 25 58",
    "sg:postcode":"08027",
    "sg:province":"Barcelona",
    "wof:name":"Casas Trias Juan",
    "wof:placetype":"venue"
},
  "geometry": {"coordinates":[2.1898319721,41.4234352112],"type":"Point"}
}