{
  "type": "Feature",
  "properties": {
    "iso:country":"ES",
    "sg:address":"Calle de Rui Perez, 20",
    "sg:city":"Aviles",
    "sg:orig_category":"Mercer\u00cda, Lencer\u00cda (al Por Menor)",
    "sg:phone":"+34 985 56 39 00",
    "sg:postcode":"33402",
    "sg:province":"Asturias",
    "wof:name":"Garcia De La Fuente Maria Luisa",
    "wof:placetype":"venue"
},
  "geometry": {"coordinates":[-5.9230480194,43.5582046509],"type":"Point"}
}