{
  "type": "Feature",
  "properties": {
    "iso:country":"ES",
    "sg:address":"Carrer de Llibertat, 38",
    "sg:city":"S. Boi Llobregat",
    "sg:orig_category":"Alquiler De V\u00cddeo",
    "sg:phone":"+34 936 52 06 13",
    "sg:postcode":"08830",
    "sg:province":"Barcelona",
    "wof:name":"Vila Canalias Jose Antonio",
    "wof:placetype":"venue"
},
  "geometry": {"coordinates":[2.0308890343,41.3501205444],"type":"Point"}
}