{
  "type": "Feature",
  "properties": {
    "addr:full":"C/ Nord, 35 Ripollet Barcelona 08291",
    "addr:housenumber":"35",
    "addr:postcode":"08291",
    "addr:street":"C / Nord",
    "iso:country":"ES",
    "sg:address":"C/ Nord, 35",
    "sg:city":"Ripollet",
    "sg:orig_category":"Peluquer\u00cdas, Peluquer\u00cda Mixta",
    "sg:phone":"+34 935 86 39 05",
    "sg:postcode":"08291",
    "sg:province":"Barcelona",
    "wof:name":"Puig Glanadell Anna",
    "wof:placetype":"venue"
},
  "geometry": {"coordinates":[2.1559700966,41.501449585],"type":"Point"}
}