{
  "type": "Feature",
  "properties": {
    "iso:country":"ES",
    "sg:address":"Cmno Torrejon, Km. 0000,5",
    "sg:city":"Ajalvir",
    "sg:orig_category":"Art\u00cdculos De Limpieza Y De Cocina (fabricaci\u00d3n, Al Por Mayor)",
    "sg:phone":"+34 918 84 40 10",
    "sg:postcode":"28864",
    "sg:province":"Madrid",
    "wof:name":"Intercleaner S.l.",
    "wof:placetype":"venue"
},
  "geometry": {"coordinates":[-3.4845490456,40.5355567932],"type":"Point"}
}