{
  "type": "Feature",
  "properties": {
    "iso:country":"ES",
    "sg:address":"Carrer de Concepcion Arenal, 263",
    "sg:city":"Barcelona",
    "sg:orig_category":"Molduras, Junquillos, Listones Y Molduras Perforadas",
    "sg:phone":"+34 932 74 05 17",
    "sg:postcode":"08030",
    "sg:province":"Barcelona",
    "wof:name":"Morla Palacios Fernando",
    "wof:placetype":"venue"
},
  "geometry": {"coordinates":[2.184253931,41.431892395],"type":"Point"}
}