{
  "type": "Feature",
  "properties": {
    "iso:country":"ES",
    "sg:address":"Calle de Balsama\u00d1a, 13",
    "sg:city":"Castillo Bayuela",
    "sg:orig_category":"Cr\u00cda De Animales",
    "sg:phone":"+34 925 59 70 92",
    "sg:postcode":"45641",
    "sg:province":"Toledo",
    "wof:name":"El Moro Del Castillo S.l.",
    "wof:placetype":"venue"
},
  "geometry": {"coordinates":[-4.6852388382,40.1028518677],"type":"Point"}
}