{
  "type": "Feature",
  "properties": {
    "iso:country":"ES",
    "sg:address":"Carrer de Moscou, 26",
    "sg:city":"Barcelona",
    "sg:orig_category":"Arquitectos",
    "sg:phone":"+34 932 24 70 66",
    "sg:postcode":"08005",
    "sg:province":"Barcelona",
    "wof:name":"Riera Camps Asociados S.l.",
    "wof:placetype":"venue"
},
  "geometry": {"coordinates":[2.1944229603,41.3896102905],"type":"Point"}
}