{
  "type": "Feature",
  "properties": {
    "iso:country":"ES",
    "sg:address":"Carr Cartagena, 14",
    "sg:city":"Girona",
    "sg:orig_category":"Construcci\u00d3n Mec\u00c1nica",
    "sg:phone":"+34 972 24 12 42",
    "sg:postcode":"17005",
    "sg:province":"Girona",
    "wof:name":"Construcciones Mecanicas Duch S. A.",
    "wof:placetype":"venue"
},
  "geometry": {"coordinates":[2.8109529018,41.9666404724],"type":"Point"}
}