{
  "type": "Feature",
  "properties": {
    "addr:full":"Calle de Sobre Los Angeles, 3 Barbate C\u00e1diz 11160",
    "addr:housenumber":"3",
    "addr:postcode":"11160",
    "addr:street":"Calle De Sobre Los Angeles",
    "iso:country":"ES",
    "sg:address":"Calle de Sobre Los Angeles, 3",
    "sg:city":"Barbate",
    "sg:orig_category":"Alimentaci\u00d3n General (al Por Menor)",
    "sg:phone":"+34 956 43 22 04",
    "sg:postcode":"11160",
    "sg:province":"C\u00e1diz",
    "wof:name":"Correro Sevilla Salvador",
    "wof:placetype":"venue"
},
  "geometry": {"coordinates":[-5.9257941246,36.1882781982],"type":"Point"}
}