{
  "type": "Feature",
  "properties": {
    "addr:full":"Carrer de Providencia, 91 Barcelona Barcelona 08024",
    "addr:housenumber":"91",
    "addr:postcode":"08024",
    "addr:street":"Carrer De Providencia",
    "iso:country":"ES",
    "sg:address":"Carrer de Providencia, 91",
    "sg:city":"Barcelona",
    "sg:orig_category":"Comerciantes Al Por Mayor De Vinos, Licores Y Alcoholes",
    "sg:phone":"+34 932 13 06 51",
    "sg:postcode":"08024",
    "sg:province":"Barcelona",
    "wof:name":"Casas Julia Antonio",
    "wof:placetype":"venue"
},
  "geometry": {"coordinates":[2.1597878933,41.4084892273],"type":"Point"}
}