{
  "type": "Feature",
  "properties": {
    "iso:country":"ES",
    "sg:address":"Ctra Barcelona, 514",
    "sg:city":"Sabadell",
    "sg:orig_category":"M\u00c9dicos: Endocrinolog\u00cda Y Metabolismo",
    "sg:phone":"+34 937 10 52 42",
    "sg:postcode":"08204",
    "sg:province":"Barcelona",
    "wof:name":"Lopera Esteban Maria Isabel",
    "wof:placetype":"venue"
},
  "geometry": {"coordinates":[2.1163051128,41.5295906067],"type":"Point"}
}