{
  "type": "Feature",
  "properties": {
    "iso:country":"ES",
    "sg:address":"Carrer de Verge Del Pilar, 32",
    "sg:city":"Amposta",
    "sg:orig_category":"Peluquer\u00cdas, Peluquer\u00cda Mixta",
    "sg:phone":"+34 977 70 58 16",
    "sg:postcode":"43870",
    "sg:province":"Tarragona",
    "wof:name":"Caballe Cervellera Inmaculada",
    "wof:placetype":"venue"
},
  "geometry": {"coordinates":[0.575025022,40.7119178772],"type":"Point"}
}