{
  "type": "Feature",
  "properties": {
    "addr:full":"Carrer de Llibertat, 5 Castelldefels Barcelona 08860",
    "addr:housenumber":"5",
    "addr:postcode":"08860",
    "addr:street":"Carrer De Llibertat",
    "iso:country":"ES",
    "sg:address":"Carrer de Llibertat, 5",
    "sg:city":"Castelldefels",
    "sg:orig_category":"Art\u00cdculos De Regalo (al Por Menor)",
    "sg:phone":"+34 936 64 46 68",
    "sg:postcode":"08860",
    "sg:province":"Barcelona",
    "wof:name":"Lopez Solanas Isabel",
    "wof:placetype":"venue"
},
  "geometry": {"coordinates":[1.9771029949,41.2788887024],"type":"Point"}
}