{
  "type": "Feature",
  "properties": {
    "addr:full":"Carrer de Bisbe Palau, 16 Valls Tarragona 43800",
    "addr:housenumber":"16",
    "addr:postcode":"43800",
    "addr:street":"Carrer De Bisbe Palau",
    "iso:country":"ES",
    "sg:address":"Carrer de Bisbe Palau, 16",
    "sg:city":"Valls",
    "sg:orig_category":"Institutos De Belleza",
    "sg:phone":"+34 977 60 02 05",
    "sg:postcode":"43800",
    "sg:province":"Tarragona",
    "wof:name":"Barrios Blavi Ana",
    "wof:placetype":"venue"
},
  "geometry": {"coordinates":[1.2540689707,41.2879333496],"type":"Point"}
}