{
  "type": "Feature",
  "properties": {
    "addr:full":"Carrer de Diputacio, 35 S. Celoni Barcelona 08470",
    "addr:housenumber":"35",
    "addr:postcode":"08470",
    "addr:street":"Carrer De Diputacio;S. Celoni Barcelona",
    "iso:country":"ES",
    "sg:address":"Carrer de Diputacio, 35",
    "sg:city":"S. Celoni",
    "sg:orig_category":"Fabricaci\u00d3n, Importaci\u00d3n De L\u00c1mparas Y Bombillas",
    "sg:phone":"+34 938 67 09 90",
    "sg:postcode":"08470",
    "sg:province":"Barcelona",
    "wof:name":"Clos Puig Salvador",
    "wof:placetype":"venue"
},
  "geometry": {"coordinates":[2.4862599373,41.6881904602],"type":"Point"}
}