{
  "type": "Feature",
  "properties": {
    "addr:full":"Pol Ind, S/n Puerto Lumbreras Murcia 30890",
    "addr:housenumber":"s / n",
    "addr:postcode":"30890",
    "iso:country":"ES",
    "sg:address":"Pol Ind, S/n",
    "sg:city":"Puerto Lumbreras",
    "sg:orig_category":"Bebidas",
    "sg:phone":"+34 968 40 13 32",
    "sg:postcode":"30890",
    "sg:province":"Murcia",
    "wof:name":"Marin Lopez Jose",
    "wof:placetype":"venue"
},
  "geometry": {"coordinates":[-1.9274189472,37.6259460449],"type":"Point"}
}