{
  "type": "Feature",
  "properties": {
    "addr:full":"Avda Portus Illicitanus, 12 Santa Pola Alicante 03130",
    "addr:housenumber":"12",
    "addr:postcode":"03130",
    "addr:street":"Avda Portus Illicitanus",
    "iso:country":"ES",
    "sg:address":"Avda Portus Illicitanus, 12",
    "sg:city":"Santa Pola",
    "sg:orig_category":"Colchones (fabricaci\u00d3n, Al Por Mayor, Al Por Menor)",
    "sg:phone":"+34 965 41 49 94",
    "sg:postcode":"03130",
    "sg:province":"Alicante",
    "wof:name":"Belmar Lopez Ramon",
    "wof:placetype":"venue"
},
  "geometry": {"coordinates":[-0.5613110065,38.1939659119],"type":"Point"}
}