{
  "type": "Feature",
  "properties": {
    "iso:country":"ES",
    "sg:address":"Calle de Victor Pradera, 12",
    "sg:city":"Aceituna",
    "sg:classifiers":[
        {
            "category":"Taxi",
            "type":"Transportation"
        }
    ],
    "sg:phone":"+34 927 43 10 87",
    "sg:postcode":"10666",
    "sg:province":"C\u00e1ceres",
    "wof:name":"Garcia Perez Adriano",
    "wof:placetype":"venue"
},
  "geometry": {"coordinates":[-6.3328261375,40.1498527527],"type":"Point"}
}