{
  "type": "Feature",
  "properties": {
    "addr:full":"C/ Llobregat, 34 Ripollet Barcelona 08291",
    "addr:housenumber":"34",
    "addr:postcode":"08291",
    "addr:street":"C / Llobregat",
    "iso:country":"ES",
    "sg:address":"C/ Llobregat, 34",
    "sg:city":"Ripollet",
    "sg:orig_category":"Perfumer\u00cda Y Cosm\u00c9tica (fabricaci\u00d3n, Al Por Mayor)",
    "sg:phone":"+34 936 92 61 16",
    "sg:postcode":"08291",
    "sg:province":"Barcelona",
    "sg:website":"www.proquimiacosmetics.com",
    "wof:name":"Proquimia Cosmetics S.a.",
    "wof:placetype":"venue"
},
  "geometry": {"coordinates":[2.1569299698,41.4926986694],"type":"Point"}
}