{
  "type": "Feature",
  "properties": {
    "iso:country":"ES",
    "sg:address":"Calle de Fernando El Catolico, 6",
    "sg:city":"Alcala Real",
    "sg:orig_category":"Abogados",
    "sg:phone":"+34 953 58 03 92",
    "sg:postcode":"23680",
    "sg:province":"Ja\u00e9n",
    "wof:name":"Sanchez Becerra Francisco",
    "wof:placetype":"venue"
},
  "geometry": {"coordinates":[-3.921364069,37.4597854614],"type":"Point"}
}