{
  "type": "Feature",
  "properties": {
    "addr:full":"Rond Santa Maria, 4 Ciudad Real Ciudad Real 13002",
    "addr:housenumber":"4",
    "addr:postcode":"13002",
    "addr:street":"Santa Maria",
    "iso:country":"ES",
    "sg:address":"Rond Santa Maria, 4",
    "sg:city":"Ciudad Real",
    "sg:orig_category":"Promotores Constructores",
    "sg:phone":"+34 926 27 40 48",
    "sg:postcode":"13002",
    "sg:province":"Ciudad Real",
    "wof:name":"Empresa De Transformacion Agraria S.a.",
    "wof:placetype":"venue"
},
  "geometry": {"coordinates":[-3.9341979027,38.9871101379],"type":"Point"}
}