{
  "type": "Feature",
  "properties": {
    "addr:full":"Calle de Sierra De Maria, 22 Parador Hortichuelas Almer\u00eda 04720",
    "addr:housenumber":"22",
    "addr:postcode":"04720",
    "addr:street":"Calle De Sierra De Maria;Almeri\u0301A",
    "iso:country":"ES",
    "sg:address":"Calle de Sierra De Maria, 22",
    "sg:city":"Parador Hortichuelas",
    "sg:orig_category":"Alimentaci\u00d3n General (al Por Menor)",
    "sg:phone":"+34 950 34 08 33",
    "sg:postcode":"04720",
    "sg:province":"Almer\u00eda",
    "wof:name":"Avivar Lozano S.l.",
    "wof:placetype":"venue"
},
  "geometry": {"coordinates":[-2.6000013351,36.8054542542],"type":"Point"}
}