{
  "type": "Feature",
  "properties": {
    "addr:full":"Plaz Marlasca, 2 Guadalajara Guadalajara 19001",
    "addr:housenumber":"2",
    "addr:postcode":"19001",
    "addr:street":"Plaz Marlasca",
    "iso:country":"ES",
    "sg:address":"Plaz Marlasca, 2",
    "sg:city":"Guadalajara",
    "sg:orig_category":"Bancos",
    "sg:phone":"+34 949 24 70 76",
    "sg:postcode":"19001",
    "sg:province":"Guadalajara",
    "wof:name":"Bankinter S.a.",
    "wof:placetype":"venue"
},
  "geometry": {"coordinates":[-3.1647350788,40.6322364807],"type":"Point"}
}