{
  "type": "Feature",
  "properties": {
    "iso:country":"ES",
    "sg:address":"Calle de Gil Cordero, 4",
    "sg:city":"Caceres",
    "sg:orig_category":"Abogados",
    "sg:phone":"+34 927 22 58 48",
    "sg:postcode":"10001",
    "sg:province":"C\u00e1ceres",
    "wof:name":"Gonzalez Perez Feliciano",
    "wof:placetype":"venue"
},
  "geometry": {"coordinates":[-6.3797550201,39.4684715271],"type":"Point"}
}