{
  "type": "Feature",
  "properties": {
    "iso:country":"ES",
    "sg:address":"Calle de Zu\u00d1iga Rodriguez, 3",
    "sg:city":"Bejar",
    "sg:orig_category":"Agencias De Viajes",
    "sg:phone":"+34 923 40 07 71",
    "sg:postcode":"37700",
    "sg:province":"Salamanca",
    "wof:name":"Viajes Labrador S.l.",
    "wof:placetype":"venue"
},
  "geometry": {"coordinates":[-5.7626190186,40.3851509094],"type":"Point"}
}