{
  "type": "Feature",
  "properties": {
    "addr:full":"Calle de Dos Hermanas, 1 Le\u00f3n Le\u00f3n 24005",
    "addr:housenumber":"1",
    "addr:postcode":"24005",
    "addr:street":"Calle De Dos Hermanas;Leo\u0301N",
    "iso:country":"ES",
    "sg:address":"Calle de Dos Hermanas, 1",
    "sg:city":"Le\u00f3n",
    "sg:orig_category":"Peluquer\u00cdas, Peluquer\u00cda Mixta",
    "sg:phone":"+34 987 26 39 86",
    "sg:postcode":"24005",
    "sg:province":"Le\u00f3n",
    "wof:name":"Rueda Garcia Jovita",
    "wof:placetype":"venue"
},
  "geometry": {"coordinates":[-5.554669857,42.5806999207],"type":"Point"}
}