{
  "type": "Feature",
  "properties": {
    "addr:full":"Rua Ande, 14 Ande Pontevedra 36619",
    "addr:housenumber":"14",
    "addr:postcode":"36619",
    "addr:street":"Rua Ande",
    "iso:country":"ES",
    "sg:address":"Rua Ande, 14",
    "sg:city":"Ande",
    "sg:orig_category":"Hospitales",
    "sg:phone":"+34 986 56 80 00",
    "sg:postcode":"36619",
    "sg:province":"Pontevedra",
    "wof:name":"Sergas-fundacion Publica Hospital Comarcal Do Salnes",
    "wof:placetype":"venue"
},
  "geometry": {"coordinates":[-8.7645044327,42.5797958374],"type":"Point"}
}