{
  "type": "Feature",
  "properties": {
    "iso:country":"ES",
    "sg:address":"Carrer de Cardenal Rossell, 41",
    "sg:city":"Coll De'n Rabassa",
    "sg:classifiers":[
        {
            "category":"Autos & Motor Vehicles",
            "subcategory":"Automobile Sales",
            "type":"Retail Goods"
        }
    ],
    "sg:phone":"+34 971 26 04 21",
    "sg:postcode":"07007",
    "sg:province":"Islas Baleares",
    "wof:name":"Autoescuela Coll D'en Rabassa",
    "wof:placetype":"venue"
},
  "geometry": {"coordinates":[2.9117100239,39.6136398315],"type":"Point"}
}