{
  "type": "Feature",
  "properties": {
    "addr:full":"Avda Constitucion (de La), 12 Granada Granada 18012",
    "addr:housenumber":"12",
    "addr:postcode":"18012",
    "addr:street":"Avda Constitucion De La",
    "iso:country":"ES",
    "sg:address":"Avda Constitucion (de La), 12",
    "sg:city":"Granada",
    "sg:orig_category":"Caf\u00c9s, Bares, Cervecer\u00cdas",
    "sg:phone":"+34 958 20 40 89",
    "sg:postcode":"18012",
    "sg:province":"Granada",
    "wof:name":"Jimenez Granados Francisco Jose",
    "wof:placetype":"venue"
},
  "geometry": {"coordinates":[-3.6042466164,37.1842689514],"type":"Point"}
}