{
  "type": "Feature",
  "properties": {
    "iso:country":"ES",
    "sg:address":"Calle de Capitan Blanco Argibay, 186",
    "sg:city":"Madrid",
    "sg:orig_category":"Cristaler\u00cdas",
    "sg:phone":"+34 917 33 64 31",
    "sg:postcode":"28029",
    "sg:province":"Madrid",
    "wof:name":"A.l.v Centro Global Del Motor S.l.",
    "wof:placetype":"venue"
},
  "geometry": {"coordinates":[-3.707269907,40.4679832458],"type":"Point"}
}