{
  "type": "Feature",
  "properties": {
    "addr:full":"Calle de Valencia (de), 3 Fuenlabrada Madrid 28945",
    "addr:housenumber":"3",
    "addr:postcode":"28945",
    "addr:street":"Calle De Valencia De",
    "iso:country":"ES",
    "sg:address":"Calle de Valencia (de), 3",
    "sg:city":"Fuenlabrada",
    "sg:orig_category":"Reposter\u00cdas",
    "sg:phone":"+34 916 15 61 47",
    "sg:postcode":"28945",
    "sg:province":"Madrid",
    "wof:name":"Hornos Ricipan S.l.",
    "wof:placetype":"venue"
},
  "geometry": {"coordinates":[-3.7926640511,40.2907333374],"type":"Point"}
}