{
  "type": "Feature",
  "properties": {
    "addr:full":"Rua Rosalia De Castro (de), 32 Santa Catali\u00e7a De Armada La Coru\u00f1a 15840",
    "addr:housenumber":"32",
    "addr:postcode":"15840",
    "addr:street":"Rua Rosalia De Castro De;Corun\u0303A",
    "iso:country":"ES",
    "sg:address":"Rua Rosalia De Castro (de), 32",
    "sg:city":"Santa Catali\u00e7a De Armada",
    "sg:orig_category":"Librer\u00cdas",
    "sg:phone":"+34 981 88 03 67",
    "sg:postcode":"15840",
    "sg:province":"La Coru\u00f1a",
    "wof:name":"Ler Librerias S.l.",
    "wof:placetype":"venue"
},
  "geometry": {"coordinates":[-8.8163843155,43.0361595154],"type":"Point"}
}