{
  "type": "Feature",
  "properties": {
    "iso:country":"ES",
    "sg:address":"Carrer de Palma, 50",
    "sg:city":"Benidorm",
    "sg:orig_category":"Imprenta",
    "sg:phone":"+34 965 85 02 65",
    "sg:postcode":"03500",
    "sg:province":"Alicante",
    "wof:name":"Cebrian Sanchez Mariano",
    "wof:placetype":"venue"
},
  "geometry": {"coordinates":[-0.1303839982,38.5382080078],"type":"Point"}
}