{
  "type": "Feature",
  "properties": {
    "iso:country":"ES",
    "sg:address":"Calle de Esperanza, 29",
    "sg:city":"Dos Hermanas",
    "sg:orig_category":"Asociaciones Y Clubs Deportivos",
    "sg:phone":"+34 955 66 27 45",
    "sg:postcode":"41700",
    "sg:province":"Sevilla",
    "sg:website":"www.pacogin.com",
    "wof:name":"Martin Gonzalez Francisco",
    "wof:placetype":"venue"
},
  "geometry": {"coordinates":[-5.9224767685,37.2887649536],"type":"Point"}
}