{
  "type": "Feature",
  "properties": {
    "addr:full":"C/ Reverend Pare Huguet, S/n Ferreries Islas Baleares 07750",
    "addr:housenumber":"s / n",
    "addr:postcode":"07750",
    "addr:street":"C / Reverend Pare Huguet",
    "iso:country":"ES",
    "sg:address":"C/ Reverend Pare Huguet, S/n",
    "sg:city":"Ferreries",
    "sg:orig_category":"Internados & Ense\u00d1anza Privada",
    "sg:phone":"+34 971 37 31 90",
    "sg:postcode":"07750",
    "sg:province":"Islas Baleares",
    "wof:name":"Colegio San Francisco De Asis",
    "wof:placetype":"venue"
},
  "geometry": {"coordinates":[4.0133647919,39.9820594788],"type":"Point"}
}