{
  "type": "Feature",
  "properties": {
    "addr:full":"Ventin, S/n Biduido La Coru\u00f1a 15895",
    "addr:postcode":"15895",
    "addr:street":"Ventin S / N Biduido La Corun\u0303A",
    "iso:country":"ES",
    "sg:address":"Ventin, S/n",
    "sg:city":"Biduido",
    "sg:orig_category":"Muebles Y Accesorios Para Cocinas Y Cuartos De Ba\u00d1o (al Por Menor)",
    "sg:phone":"+34 981 52 46 60",
    "sg:postcode":"15895",
    "sg:province":"La Coru\u00f1a",
    "wof:name":"Carpinteria Smart S.l.",
    "wof:placetype":"venue"
},
  "geometry": {"coordinates":[-8.5794343948,42.8416137695],"type":"Point"}
}