{
  "type": "Feature",
  "properties": {
    "iso:country":"ES",
    "sg:address":"Ctra Ogassa, S/n",
    "sg:city":"Sant Joan De Les Abadesses",
    "sg:orig_category":"Fabricaci\u00d3n, Importaci\u00d3n De L\u00c1mparas Y Bombillas",
    "sg:phone":"+34 972 72 01 25",
    "sg:postcode":"17860",
    "sg:province":"Girona",
    "sg:website":"www.estiluz.com",
    "wof:name":"Estiluz S. A.",
    "wof:placetype":"venue"
},
  "geometry": {"coordinates":[2.2856469154,42.2377967834],"type":"Point"}
}