{
  "type": "Feature",
  "properties": {
    "iso:country":"ES",
    "sg:address":"Plaz Iglesia (de La), 2",
    "sg:city":"Torrelodones",
    "sg:orig_category":"Centros De Coordinaci\u00d3n",
    "sg:phone":"+34 918 59 13 59",
    "sg:postcode":"28250",
    "sg:province":"Madrid",
    "wof:name":"Carabel Y Associates S.l.",
    "wof:placetype":"venue"
},
  "geometry": {"coordinates":[-3.9636099339,40.5836601257],"type":"Point"}
}