{
  "type": "Feature",
  "properties": {
    "iso:country":"ES",
    "sg:address":"Ctra. Cabanillas, Km. 0002,3",
    "sg:city":"Guadalajara",
    "sg:orig_category":"Agricultura: Abastecimiento Y Cosechado (negocio)",
    "sg:phone":"+34 949 21 31 15",
    "sg:postcode":"19004",
    "sg:province":"Guadalajara",
    "wof:name":"Abajo Portillo Angel Alberto",
    "wof:placetype":"venue"
},
  "geometry": {"coordinates":[-3.181446,40.645683],"type":"Point"}
}