{
  "type": "Feature",
  "properties": {
    "iso:country":"ES",
    "sg:address":"Avda Belgica (de), 23",
    "sg:city":"Santa Cruz De Tenerife",
    "sg:orig_category":"Ingenier\u00cda, Centros De Estudios (diversos)",
    "sg:phone":"+34 922 22 57 12",
    "sg:postcode":"38007",
    "sg:province":"Santa Cruz De Tenerife",
    "wof:name":"Trujillo Armas Francisco Jose",
    "wof:placetype":"venue"
},
  "geometry": {"coordinates":[-16.267993927,28.4651985168],"type":"Point"}
}