{
  "type": "Feature",
  "properties": {
    "addr:full":"Pl Ajuntament, 20 S. Boi Llobregat Barcelona 08830",
    "addr:housenumber":"20",
    "addr:postcode":"08830",
    "addr:street":"Pl Ajuntament",
    "iso:country":"ES",
    "sg:address":"Pl Ajuntament, 20",
    "sg:city":"S. Boi Llobregat",
    "sg:orig_category":"Cobro De Pr\u00c9stamos",
    "sg:phone":"+34 936 52 11 70",
    "sg:postcode":"08830",
    "sg:province":"Barcelona",
    "sg:website":"www.orgt.diba.es",
    "wof:name":"Organisme Autonom Local De Gestio Tributaria",
    "wof:placetype":"venue"
},
  "geometry": {"coordinates":[2.0431399345,41.3471908569],"type":"Point"}
}