{
  "type": "Feature",
  "properties": {
    "iso:country":"ES",
    "sg:address":"Calle de Agintari Kalea, 9",
    "sg:city":"Tolosa",
    "sg:orig_category":"Molduras, Junquillos, Listones Y Molduras Perforadas",
    "sg:phone":"+34 943 67 28 78",
    "sg:postcode":"20400",
    "sg:province":"Guip\u00f9zcoa",
    "wof:name":"Olasagasti Hermanos C.b",
    "wof:placetype":"venue"
},
  "geometry": {"coordinates":[-2.0716090202,43.138381958],"type":"Point"}
}