{
  "type": "Feature",
  "properties": {
    "addr:full":"Calle de Tres De Abril, S/n Coria Rio Sevilla 41100",
    "addr:housenumber":"s / n",
    "addr:postcode":"41100",
    "addr:street":"Calle De Tres De Abril;Rio Sevilla",
    "iso:country":"ES",
    "sg:address":"Calle de Tres De Abril, S/n",
    "sg:city":"Coria Rio",
    "sg:classifiers":[
        {
            "category":"Taxi",
            "type":"Transportation"
        }
    ],
    "sg:phone":"+34 954 77 32 26",
    "sg:postcode":"41100",
    "sg:province":"Sevilla",
    "wof:name":"Ayuntamiento De Coria Del Rio",
    "wof:placetype":"venue"
},
  "geometry": {"coordinates":[-6.0518488884,37.2827949524],"type":"Point"}
}