{
  "type": "Feature",
  "properties": {
    "iso:country":"ES",
    "sg:address":"Via Montijo, Km. 0000,2",
    "sg:city":"Roca Sierra",
    "sg:orig_category":"Aceites Y Grasas Industriales (fabricaci\u00d3n, Al Por Mayor)",
    "sg:phone":"+34 924 40 63 46",
    "sg:postcode":"06190",
    "sg:province":"Badajoz",
    "wof:name":"Aceites Molina S.a.",
    "wof:placetype":"venue"
},
  "geometry": {"coordinates":[-6.6793355942,39.0770339966],"type":"Point"}
}