{
  "type": "Feature",
  "properties": {
    "addr:full":"Calle de Canal De Panama, 6 Madrid Madrid 28027",
    "addr:housenumber":"6",
    "addr:postcode":"28027",
    "addr:street":"Calle De Canal De Panama",
    "iso:country":"ES",
    "sg:address":"Calle de Canal De Panama, 6",
    "sg:city":"Madrid",
    "sg:orig_category":"Equitaci\u00d3n Y Centros De H\u00cdpica",
    "sg:phone":"+34 914 03 99 67",
    "sg:postcode":"28027",
    "sg:province":"Madrid",
    "wof:name":"El Corcel Equitacion S.l.",
    "wof:placetype":"venue"
},
  "geometry": {"coordinates":[-3.6510601044,40.4400787354],"type":"Point"}
}