{
  "type": "Feature",
  "properties": {
    "iso:country":"ES",
    "sg:address":"G.v. Corts Catalanes, 646",
    "sg:city":"Barcelona",
    "sg:orig_category":"Asociaciones, Organismos Culturales Y Socioeducativos",
    "sg:phone":"+34 933 02 41 12",
    "sg:postcode":"08007",
    "sg:province":"Barcelona",
    "wof:name":"Agrupacio Empleats Jubilats Pensionistes De La Caixa De Pensions",
    "wof:placetype":"venue"
},
  "geometry": {"coordinates":[2.1697945595,41.3903198242],"type":"Point"}
}