{
  "type": "Feature",
  "properties": {
    "addr:full":"Plaz Mayor, 8 Ciudad Rodrigo Salamanca 37500",
    "addr:housenumber":"8",
    "addr:postcode":"37500",
    "addr:street":"Plaz Mayor",
    "iso:country":"ES",
    "sg:address":"Plaz Mayor, 8",
    "sg:city":"Ciudad Rodrigo",
    "sg:orig_category":"Mercer\u00cda, Lencer\u00cda (al Por Menor)",
    "sg:phone":"+34 923 46 21 59",
    "sg:postcode":"37500",
    "sg:province":"Salamanca",
    "wof:name":"Villalon Garzon Maria De Los Milagros",
    "wof:placetype":"venue"
},
  "geometry": {"coordinates":[-6.5304489136,40.598865509],"type":"Point"}
}