{
  "type": "Feature",
  "properties": {
    "iso:country":"ES",
    "sg:address":"Rua Xan De Estivadas, 14",
    "sg:city":"Noia",
    "sg:orig_category":"Abogados",
    "sg:phone":"+34 981 82 01 21",
    "sg:postcode":"15200",
    "sg:province":"La Coru\u00f1a",
    "wof:name":"Blanco Ons Manuel",
    "wof:placetype":"venue"
},
  "geometry": {"coordinates":[-8.8884887695,42.7824401855],"type":"Point"}
}