{
  "type": "Feature",
  "properties": {
    "iso:country":"ES",
    "sg:address":"Llorenc Moya, 2",
    "sg:city":"Binissalem",
    "sg:orig_category":"Peluqueros: De Se\u00d1oras",
    "sg:phone":"+34 971 51 13 91",
    "sg:postcode":"07350",
    "sg:province":"Islas Baleares",
    "wof:name":"Pons Llabres Francisca",
    "wof:placetype":"venue"
},
  "geometry": {"coordinates":[2.8431079388,39.6867713928],"type":"Point"}
}