{
  "type": "Feature",
  "properties": {
    "addr:full":"Ctra Cuatro Caminos, 6 Barrio De Arriba Cantabria 39721",
    "addr:housenumber":"6",
    "addr:postcode":"39721",
    "addr:street":"Ctra Cuatro Caminos",
    "iso:country":"ES",
    "sg:address":"Ctra Cuatro Caminos, 6",
    "sg:city":"Barrio De Arriba",
    "sg:orig_category":"Empresas De Carpinter\u00cda Met\u00c1lica",
    "sg:phone":"+34 942 53 91 66",
    "sg:postcode":"39721",
    "sg:province":"Cantabria",
    "wof:name":"Torre Exposito Jesus",
    "wof:placetype":"venue"
},
  "geometry": {"coordinates":[-3.680672884,43.3418579102],"type":"Point"}
}