{
  "type": "Feature",
  "properties": {
    "addr:full":"Calle de Azafranal, 25 Salamanca Salamanca 37001",
    "addr:housenumber":"25",
    "addr:postcode":"37001",
    "addr:street":"Calle De Azafranal",
    "iso:country":"ES",
    "sg:address":"Calle de Azafranal, 25",
    "sg:city":"Salamanca",
    "sg:orig_category":"Ingeniero",
    "sg:phone":"+34 923 21 88 39",
    "sg:postcode":"37001",
    "sg:province":"Salamanca",
    "wof:name":"Ledesma Garcia Francisco",
    "wof:placetype":"venue"
},
  "geometry": {"coordinates":[-5.6610517502,40.9671516418],"type":"Point"}
}