{
  "type": "Feature",
  "properties": {
    "iso:country":"ES",
    "sg:address":"Grup Aldapeta, 1",
    "sg:city":"Bilbao",
    "sg:orig_category":"Suministros Y Materiales Industriales",
    "sg:phone":"+34 944 27 43 94",
    "sg:postcode":"48013",
    "sg:province":"Vizcaya",
    "wof:name":"Pertegaz S.l.",
    "wof:placetype":"venue"
},
  "geometry": {"coordinates":[-2.9731199741,43.2739219666],"type":"Point"}
}