{
  "type": "Feature",
  "properties": {
    "addr:full":"Ctra Comarcal, S/n Tardesillas Soria 42162",
    "addr:postcode":"42162",
    "addr:street":"Ctra Comarcal S / N",
    "iso:country":"ES",
    "sg:address":"Ctra Comarcal, S/n",
    "sg:city":"Tardesillas",
    "sg:orig_category":"Cooperativas Agr\u00cdcolas",
    "sg:phone":"+34 975 18 09 32",
    "sg:postcode":"42162",
    "sg:province":"Soria",
    "wof:name":"Copiso Soria Sociedad Cooperativa",
    "wof:placetype":"venue"
},
  "geometry": {"coordinates":[-2.4456140995,41.8151550293],"type":"Point"}
}