{
  "type": "Feature",
  "properties": {
    "addr:full":"Calle de Hornos (los), 43 Andujar Ja\u00e9n 23740",
    "addr:housenumber":"43",
    "addr:postcode":"23740",
    "addr:street":"Calle De Hornos Los",
    "iso:country":"ES",
    "sg:address":"Calle de Hornos (los), 43",
    "sg:city":"Andujar",
    "sg:orig_category":"Servicios Gsm",
    "sg:phone":"+34 953 50 33 39",
    "sg:postcode":"23740",
    "sg:province":"Ja\u00e9n",
    "wof:name":"Telecor S.a.",
    "wof:placetype":"venue"
},
  "geometry": {"coordinates":[-4.0491051674,38.0386161804],"type":"Point"}
}