{
  "type": "Feature",
  "properties": {
    "iso:country":"ES",
    "sg:address":"Monasterio Irache, 34",
    "sg:city":"Iru\u00f1a",
    "sg:orig_category":"Farmacias",
    "sg:phone":"+34 948 25 03 57",
    "sg:postcode":"31011",
    "sg:province":"Navarra",
    "wof:name":"Arbeloa Roch Maria Isabel",
    "wof:placetype":"venue"
},
  "geometry": {"coordinates":[-1.6618692875,42.8166503906],"type":"Point"}
}