{
  "type": "Feature",
  "properties": {
    "addr:full":"Carrer de Diamant, 72 Rubi Barcelona 08191",
    "addr:housenumber":"72",
    "addr:postcode":"08191",
    "addr:street":"Carrer De Diamant",
    "iso:country":"ES",
    "sg:address":"Carrer de Diamant, 72",
    "sg:city":"Rubi",
    "sg:orig_category":"Droguer\u00cdas (al Por Menor)",
    "sg:phone":"+34 936 97 23 66",
    "sg:postcode":"08191",
    "sg:province":"Barcelona",
    "wof:name":"Zafra Gallardo Jose Antonio",
    "wof:placetype":"venue"
},
  "geometry": {"coordinates":[2.0238447189,41.4881286621],"type":"Point"}
}