{
  "type": "Feature",
  "properties": {
    "iso:country":"ES",
    "sg:address":"Finca Villa Umbria, S/n",
    "sg:city":"Alcaraz",
    "sg:orig_category":"Ense\u00d1anza Agr\u00cdcola",
    "sg:phone":"+34 967 38 01 67",
    "sg:postcode":"02300",
    "sg:province":"Albacete",
    "sg:website":"www.granjaescualatalaya.com",
    "wof:name":"Atalaya De Alcaraz S.l.",
    "wof:placetype":"venue"
},
  "geometry": {"coordinates":[-2.50989151,38.720451355],"type":"Point"}
}