{
  "type": "Feature",
  "properties": {
    "addr:full":"Avda Diputacion (de La), 57 Castro Rio C\u00f3rdoba 14840",
    "addr:housenumber":"57",
    "addr:postcode":"14840",
    "addr:street":"Avda Diputacion De La;Rio Co\u0301Rdoba",
    "iso:country":"ES",
    "sg:address":"Avda Diputacion (de La), 57",
    "sg:city":"Castro Rio",
    "sg:orig_category":"Productos Fitosanitarios (negocio, Aplicaci\u00d3n)",
    "sg:phone":"+34 957 37 05 32",
    "sg:postcode":"14840",
    "sg:province":"C\u00f3rdoba",
    "wof:name":"Hermanos Jose Y Juan Lopez Sanchez C.b.",
    "wof:placetype":"venue"
},
  "geometry": {"coordinates":[-4.4871091843,37.6942405701],"type":"Point"}
}