{
  "type": "Feature",
  "properties": {
    "iso:country":"ES",
    "sg:address":"Calle de San Nicolas, 6",
    "sg:city":"Portugalete",
    "sg:orig_category":"Ropa Para Se\u00d1oras (al Por Menor)",
    "sg:phone":"+34 946 08 71 40",
    "sg:postcode":"48920",
    "sg:province":"Vizcaya",
    "wof:name":"Equipo De Confeccion 1  S.l.",
    "wof:placetype":"venue"
},
  "geometry": {"coordinates":[-3.0174338818,43.3165969849],"type":"Point"}
}