{
  "type": "Feature",
  "properties": {
    "iso:country":"ES",
    "sg:address":"Calle de Rey Don Jaime, 1",
    "sg:city":"Elda",
    "sg:orig_category":"Alimentaci\u00d3n Animal (fabricaci\u00d3n, Al Por Mayor)",
    "sg:phone":"+34 965 39 35 49",
    "sg:postcode":"03600",
    "sg:province":"Alicante",
    "wof:name":"Pico Poveda Javier",
    "wof:placetype":"venue"
},
  "geometry": {"coordinates":[-0.7956650257,38.4734954834],"type":"Point"}
}