{
  "type": "Feature",
  "properties": {
    "addr:full":"Send Jose Pablo Ulibarri, 3 Vitoria-gasteiz \u00c1lava 01002",
    "addr:housenumber":"3",
    "addr:postcode":"01002",
    "addr:street":"Send Jose Pablo Ulibarri",
    "iso:country":"ES",
    "sg:address":"Send Jose Pablo Ulibarri, 3",
    "sg:city":"Vitoria-gasteiz",
    "sg:orig_category":"Plomeros",
    "sg:phone":"+34 945 12 08 73",
    "sg:postcode":"01002",
    "sg:province":"\u00c1lava",
    "wof:name":"Golerava, S.a.",
    "wof:placetype":"venue"
},
  "geometry": {"coordinates":[-2.6623249054,42.8539733887],"type":"Point"}
}