{
  "type": "Feature",
  "properties": {
    "addr:full":"Urb. Pto. Rico, S/n Puerto Rico Las Palmas 35130",
    "addr:housenumber":"s / n",
    "addr:postcode":"35130",
    "addr:street":"Rico",
    "iso:country":"ES",
    "sg:address":"Urb. Pto. Rico, S/n",
    "sg:city":"Puerto Rico",
    "sg:classifiers":[
        {
            "category":"Autos & Motor Vehicles",
            "subcategory":"Automobile Sales",
            "type":"Retail Goods"
        }
    ],
    "sg:phone":"+34 928 56 11 91",
    "sg:postcode":"35130",
    "sg:province":"Las Palmas",
    "wof:name":"Autoescuela Vecindario S.l.",
    "wof:placetype":"venue"
},
  "geometry": {"coordinates":[-15.7186183929,27.7882995605],"type":"Point"}
}