{
  "type": "Feature",
  "properties": {
    "addr:full":"Calle de Manuel Garcia Matos, 5 Plasencia C\u00e1ceres 10600",
    "addr:housenumber":"5",
    "addr:postcode":"10600",
    "addr:street":"Calle De Manuel Garcia Matos;Ca\u0301Ceres",
    "iso:country":"ES",
    "sg:address":"Calle de Manuel Garcia Matos, 5",
    "sg:city":"Plasencia",
    "sg:orig_category":"Plomeros",
    "sg:phone":"+34 927 41 38 00",
    "sg:postcode":"10600",
    "sg:province":"C\u00e1ceres",
    "wof:name":"Ojalvo Gines Regino",
    "wof:placetype":"venue"
},
  "geometry": {"coordinates":[-6.0798888206,40.0417518616],"type":"Point"}
}