{
  "type": "Feature",
  "properties": {
    "iso:country":"ES",
    "sg:address":"Vidrieros, 6",
    "sg:city":"Boadilla",
    "sg:orig_category":"Inmobiliaria (agencias)",
    "sg:phone":"+34 916 32 63 50",
    "sg:postcode":"28660",
    "sg:province":"Madrid",
    "wof:name":"Teson Inmobiliaria S.a.",
    "wof:placetype":"venue"
},
  "geometry": {"coordinates":[-3.8452539444,40.3933639526],"type":"Point"}
}