{
  "type": "Feature",
  "properties": {
    "iso:country":"ES",
    "sg:address":"Pase Castellana, 179",
    "sg:city":"Madrid",
    "sg:orig_category":"Expertos Contables, Revisores De Cuentas",
    "sg:phone":"+34 915 71 50 13",
    "sg:postcode":"28046",
    "sg:province":"Madrid",
    "sg:website":"www.audimeba.es",
    "wof:name":"Audi-meba S.l.",
    "wof:placetype":"venue"
},
  "geometry": {"coordinates":[-3.6900355816,40.4631881714],"type":"Point"}
}