{
  "type": "Feature",
  "properties": {
    "addr:full":"Pol Ind Red, 39 Alcala Guadaira Sevilla 41500",
    "addr:postcode":"41500",
    "iso:country":"ES",
    "sg:address":"Pol Ind Red, 39",
    "sg:city":"Alcala Guadaira",
    "sg:orig_category":"Construcciones Navales Y Fluviales",
    "sg:phone":"+34 955 63 59 70",
    "sg:postcode":"41500",
    "sg:province":"Sevilla",
    "sg:website":"www.gamesa.es",
    "wof:name":"Easa Del Sur S.a.",
    "wof:placetype":"venue"
},
  "geometry": {"coordinates":[-5.8398590088,37.3383140564],"type":"Point"}
}