{
  "type": "Feature",
  "properties": {
    "addr:full":"Calle de Gerona, 23 Benidorm Alicante 03500",
    "addr:housenumber":"23",
    "addr:postcode":"03500",
    "addr:street":"Calle De Gerona",
    "iso:country":"ES",
    "sg:address":"Calle de Gerona, 23",
    "sg:city":"Benidorm",
    "sg:orig_category":"Parques De Atracciones Y Centros De Esparcimiento",
    "sg:phone":"+34 966 80 90 71",
    "sg:postcode":"03500",
    "sg:province":"Alicante",
    "wof:name":"Automaticos La Bolera S.l.",
    "wof:placetype":"venue"
},
  "geometry": {"coordinates":[-0.1167998984,38.5374336243],"type":"Point"}
}