{
  "type": "Feature",
  "properties": {
    "iso:country":"ES",
    "sg:address":"Carrer de Anoia, 9",
    "sg:city":"Terrassa",
    "sg:orig_category":"Materiales De Aislamiento T\u00c9rmico Y Ac\u00dastico",
    "sg:phone":"+34 937 86 22 61",
    "sg:postcode":"08223",
    "sg:province":"Barcelona",
    "wof:name":"Schlegel Taliana S. L.",
    "wof:placetype":"venue"
},
  "geometry": {"coordinates":[2.0305500031,41.5463562012],"type":"Point"}
}