{
  "type": "Feature",
  "properties": {
    "addr:full":"Ctra Nacional V, Km. 0343,5 Merida Badajoz 06800",
    "addr:postcode":"06800",
    "addr:street":"Ctra Nacional V Km. 0343,5",
    "iso:country":"ES",
    "sg:address":"Ctra Nacional V, Km. 0343,5",
    "sg:city":"Merida",
    "sg:orig_category":"Material Y Herramientas Agr\u00cdcolas",
    "sg:phone":"+34 924 37 16 16",
    "sg:postcode":"06800",
    "sg:province":"Badajoz",
    "wof:name":"Ramirez Molina Ciriaco",
    "wof:placetype":"venue"
},
  "geometry": {"coordinates":[-6.3464841843,38.916053772],"type":"Point"}
}