{
  "type": "Feature",
  "properties": {
    "iso:country":"ES",
    "sg:address":"Calle de Artekalea, 6",
    "sg:city":"Durango",
    "sg:orig_category":"Farmacias",
    "sg:phone":"+34 946 81 02 23",
    "sg:postcode":"48200",
    "sg:province":"Vizcaya",
    "wof:name":"Navarro Aranda Maria Jesus",
    "wof:placetype":"venue"
},
  "geometry": {"coordinates":[-2.6315104961,43.1674613953],"type":"Point"}
}