{
  "type": "Feature",
  "properties": {
    "iso:country":"ES",
    "sg:address":"Calle de Costa Rica, 2",
    "sg:city":"Toledo",
    "sg:orig_category":"Centros De Reservas Hoteleras",
    "sg:phone":"+34 925 22 03 71",
    "sg:postcode":"45004",
    "sg:province":"Toledo",
    "wof:name":"Entretenimiento Y Ocio 2000 S.l.",
    "wof:placetype":"venue"
},
  "geometry": {"coordinates":[-4.0315895081,39.8661842346],"type":"Point"}
}