{
  "type": "Feature",
  "properties": {
    "addr:full":"Calle de Morote, 8 Huescar Granada 18830",
    "addr:housenumber":"8",
    "addr:postcode":"18830",
    "addr:street":"Calle De Morote",
    "iso:country":"ES",
    "sg:address":"Calle de Morote, 8",
    "sg:city":"Huescar",
    "sg:orig_category":"Ropa Para Se\u00d1oras Y Caballeros (al Por Menor)",
    "sg:phone":"+34 958 74 08 56",
    "sg:postcode":"18830",
    "sg:province":"Granada",
    "wof:name":"Colmena Hernandez Jose",
    "wof:placetype":"venue"
},
  "geometry": {"coordinates":[-2.5408730507,37.8088531494],"type":"Point"}
}