{
  "type": "Feature",
  "properties": {
    "iso:country":"ES",
    "sg:address":"Carrer de Nou, 10",
    "sg:city":"Manresa",
    "sg:orig_category":"Agencias De Viajes",
    "sg:phone":"+34 938 72 76 83",
    "sg:postcode":"08241",
    "sg:province":"Barcelona",
    "wof:name":"Ocio & Class Viajes S.l.",
    "wof:placetype":"venue"
},
  "geometry": {"coordinates":[1.8252689838,41.7243423462],"type":"Point"}
}