{
  "type": "Feature",
  "properties": {
    "iso:country":"ES",
    "sg:address":"Carr S Francesc D'assis, 42",
    "sg:city":"Igualada",
    "sg:orig_category":"Sociedades, Compa\u00d1\u00cdas Aseguradoras",
    "sg:phone":"+34 938 03 67 47",
    "sg:postcode":"08700",
    "sg:province":"Barcelona",
    "wof:name":"B.r.c. 81 S.l.",
    "wof:placetype":"venue"
},
  "geometry": {"coordinates":[1.621645689,41.5827713013],"type":"Point"}
}