{
  "type": "Feature",
  "properties": {
    "addr:full":"Calle de Miguel Moya, 19 Malaga M\u00e1laga 29017",
    "addr:housenumber":"19",
    "addr:postcode":"29017",
    "addr:street":"Calle De Miguel Moya;Ma\u0301Laga",
    "iso:country":"ES",
    "sg:address":"Calle de Miguel Moya, 19",
    "sg:city":"Malaga",
    "sg:orig_category":"Alimentaci\u00d3n General (al Por Menor)",
    "sg:phone":"+34 952 29 00 47",
    "sg:postcode":"29017",
    "sg:province":"M\u00e1laga",
    "wof:name":"Merino Jimenez Miguel",
    "wof:placetype":"venue"
},
  "geometry": {"coordinates":[-4.3606581688,36.7203788757],"type":"Point"}
}