{
  "type": "Feature",
  "properties": {
    "iso:country":"ES",
    "sg:address":"Plaz Palmas De Gran Canaria (las), S/n",
    "sg:city":"Conil De La Frontera",
    "sg:orig_category":"T\u00c9cnicos Veterinarios",
    "sg:phone":"+34 956 44 29 42",
    "sg:postcode":"11140",
    "sg:province":"C\u00e1diz",
    "wof:name":"Consultorio Veterinario La Janda S.c.",
    "wof:placetype":"venue"
},
  "geometry": {"coordinates":[-6.0870790482,36.2767066956],"type":"Point"}
}