{
  "type": "Feature",
  "properties": {
    "addr:full":"Calle de San Sebastian (de), 3 Boadilla Del Monte Madrid 28660",
    "addr:postcode":"28660",
    "addr:street":"Calle De",
    "iso:country":"ES",
    "sg:address":"Calle de San Sebastian (de), 3",
    "sg:city":"Boadilla Del Monte",
    "sg:orig_category":"Zapatos (al Por Menor)",
    "sg:phone":"+34 916 33 28 12",
    "sg:postcode":"28660",
    "sg:province":"Madrid",
    "wof:name":"Gracia Carrera Toledano S.l.",
    "wof:placetype":"venue"
},
  "geometry": {"coordinates":[-3.8773350716,40.4057693481],"type":"Point"}
}