{
  "type": "Feature",
  "properties": {
    "addr:full":"Calle de Luis Oliver, 2 Marbella M\u00e1laga 29600",
    "addr:housenumber":"2",
    "addr:postcode":"29600",
    "addr:street":"Calle De Luis Oliver;Ma\u0301Laga",
    "iso:country":"ES",
    "sg:address":"Calle de Luis Oliver, 2",
    "sg:city":"Marbella",
    "sg:orig_category":"Ropa Para Se\u00d1oras (al Por Menor)",
    "sg:phone":"+34 952 77 26 11",
    "sg:postcode":"29600",
    "sg:province":"M\u00e1laga",
    "sg:website":"www.didierparakian.com",
    "wof:name":"Serrano Pomares Teresa",
    "wof:placetype":"venue"
},
  "geometry": {"coordinates":[-4.8888669014,36.5099906921],"type":"Point"}
}