{
  "type": "Feature",
  "properties": {
    "addr:full":"Avda Filipinas, 42 Madrid Madrid 28003",
    "addr:housenumber":"42",
    "addr:postcode":"madrid;28003",
    "addr:street":"Avda Filipinas",
    "iso:country":"ES",
    "sg:address":"Avda Filipinas, 42",
    "sg:city":"Madrid",
    "sg:orig_category":"Agencias Y Agentes Comerciales, Representantes",
    "sg:phone":"+34 915 53 53 63",
    "sg:postcode":"28003",
    "sg:province":"Madrid",
    "wof:name":"Perez Gutierrez Jose Manuel",
    "wof:placetype":"venue"
},
  "geometry": {"coordinates":[-3.7070109844,40.4410591125],"type":"Point"}
}