{
  "type": "Feature",
  "properties": {
    "iso:country":"ES",
    "sg:address":"Calle de Eskurtze, 12",
    "sg:city":"Bilbao",
    "sg:orig_category":"Publicidad (soportes Y Gesti\u00d3n)",
    "sg:phone":"+34 944 43 66 53",
    "sg:postcode":"48012",
    "sg:province":"Vizcaya",
    "wof:name":"Bilbo Sertam S.a.l.",
    "wof:placetype":"venue"
},
  "geometry": {"coordinates":[-2.9392108917,43.2523002625],"type":"Point"}
}