{
  "type": "Feature",
  "properties": {
    "iso:country":"ES",
    "sg:address":"Avda Monforte, 7",
    "sg:city":"Chantada",
    "sg:orig_category":"Asesor\u00cda Fiscal Y Jur\u00cddica",
    "sg:phone":"+34 982 44 18 18",
    "sg:postcode":"27500",
    "sg:province":"Lugo",
    "wof:name":"Mapfre Servicios De Informatica S.a.",
    "wof:placetype":"venue"
},
  "geometry": {"coordinates":[-7.7708630562,42.6091117859],"type":"Point"}
}