{
  "type": "Feature",
  "properties": {
    "addr:full":"Calle de Baron Alcahali, 52 Alcala De Xivert Castell\u00f3n 12570",
    "addr:housenumber":"52",
    "addr:postcode":"12570",
    "addr:street":"Calle De Baron Alcahali",
    "iso:country":"ES",
    "sg:address":"Calle de Baron Alcahali, 52",
    "sg:city":"Alcala De Xivert",
    "sg:orig_category":"Cooperativas Agr\u00cdcolas",
    "sg:phone":"+34 964 41 07 36",
    "sg:postcode":"12570",
    "sg:province":"Castell\u00f3n",
    "wof:name":"Cooperativa Agricola San Isidro",
    "wof:placetype":"venue"
},
  "geometry": {"coordinates":[0.2378000021,40.2983894348],"type":"Point"}
}