{
  "type": "Feature",
  "properties": {
    "iso:country":"ES",
    "sg:address":"Calle de Almacellas, 55",
    "sg:city":"Binefar",
    "sg:orig_category":"Caf\u00c9s, Bares, Cervecer\u00cdas",
    "sg:phone":"+34 974 42 79 47",
    "sg:postcode":"22500",
    "sg:province":"Huesca",
    "wof:name":"Binefar Hosteleros S.l.",
    "wof:placetype":"venue"
},
  "geometry": {"coordinates":[0.3115510941,41.8281440735],"type":"Point"}
}