{
  "type": "Feature",
  "properties": {
    "addr:full":"Calle de Cerezo, 25 Zaragoza Zaragoza 50003",
    "addr:housenumber":"25",
    "addr:postcode":"50003",
    "addr:street":"Calle De Cerezo",
    "iso:country":"ES",
    "sg:address":"Calle de Cerezo, 25",
    "sg:city":"Zaragoza",
    "sg:orig_category":"Molduras, Junquillos, Listones Y Molduras Perforadas",
    "sg:phone":"+34 976 44 14 89",
    "sg:postcode":"50003",
    "sg:province":"Zaragoza",
    "wof:name":"Lopez Bueno Javier",
    "wof:placetype":"venue"
},
  "geometry": {"coordinates":[-0.8877779245,41.6553878784],"type":"Point"}
}