{
  "type": "Feature",
  "properties": {
    "addr:full":"Plaz San Pedro, 5 Jaca Huesca 22700",
    "addr:housenumber":"5",
    "addr:postcode":"22700",
    "addr:street":"Plaz San Pedro",
    "iso:country":"ES",
    "sg:address":"Plaz San Pedro, 5",
    "sg:city":"Jaca",
    "sg:orig_category":"Almacenes Y Tiendas De Productos Variados",
    "sg:phone":"+34 974 36 04 94",
    "sg:postcode":"22700",
    "sg:province":"Huesca",
    "wof:name":"Langa Garcia Eliseo",
    "wof:placetype":"venue"
},
  "geometry": {"coordinates":[-0.5519520044,42.5658493042],"type":"Point"}
}