{
  "type": "Feature",
  "properties": {
    "iso:country":"ES",
    "sg:address":"Carrer de Industria, 135",
    "sg:city":"Barcelona",
    "sg:orig_category":"Artesan\u00cda",
    "sg:phone":"+34 934 50 05 56",
    "sg:postcode":"08025",
    "sg:province":"Barcelona",
    "wof:name":"Martinez Torres Maria Del Carmen",
    "wof:placetype":"venue"
},
  "geometry": {"coordinates":[2.1731464863,41.4086380005],"type":"Point"}
}