{
  "type": "Feature",
  "properties": {
    "addr:full":"Avda Doctor Severo Ochoa (del), S/n Alcobendas Madrid 28100",
    "addr:postcode":"28100",
    "addr:street":"Avda Doctor Severo Ochoa Del S / N",
    "iso:country":"ES",
    "sg:address":"Avda Doctor Severo Ochoa (del), S/n",
    "sg:city":"Alcobendas",
    "sg:orig_category":"Aparatos, Material Y Suministros Para Laboratorios",
    "sg:phone":"+34 916 62 44 69",
    "sg:postcode":"28100",
    "sg:province":"Madrid",
    "wof:name":"Tecnologia Para Diagnostico E Investigacion S. A.",
    "wof:placetype":"venue"
},
  "geometry": {"coordinates":[-3.6506590843,40.545539856],"type":"Point"}
}