{
  "type": "Feature",
  "properties": {
    "addr:full":"Carr Covadonga, 17 Algemesi Valencia 46680",
    "addr:housenumber":"17",
    "addr:postcode":"46680",
    "addr:street":"Carr Covadonga",
    "iso:country":"ES",
    "sg:address":"Carr Covadonga, 17",
    "sg:city":"Algemesi",
    "sg:orig_category":"Negocio De Materiales De Construcci\u00d3n",
    "sg:phone":"+34 962 42 11 16",
    "sg:postcode":"46680",
    "sg:province":"Valencia",
    "wof:name":"Azorin Verduch Comunidad De Bienes",
    "wof:placetype":"venue"
},
  "geometry": {"coordinates":[-0.4316939116,39.1906089783],"type":"Point"}
}