{
  "type": "Feature",
  "properties": {
    "iso:country":"ES",
    "sg:address":"Barr Artebizkarra, 2",
    "sg:city":"Mimetiz",
    "sg:orig_category":"Librer\u00cdas",
    "sg:phone":"+34 946 39 01 53",
    "sg:postcode":"48860",
    "sg:province":"Vizcaya",
    "wof:name":"Arechederra Puente Inmaculada",
    "wof:placetype":"venue"
},
  "geometry": {"coordinates":[-3.13621521,43.213142395],"type":"Point"}
}