{
  "type": "Feature",
  "properties": {
    "iso:country":"ES",
    "sg:address":"Av Primer De Maig, 5",
    "sg:city":"Ivars D'urgell",
    "sg:orig_category":"Iglesia Cat\u00d3lica",
    "sg:phone":"+34 973 58 00 85",
    "sg:postcode":"25260",
    "sg:province":"Lleida",
    "wof:name":"Iglesia Parroquial. Casa Rectoral",
    "wof:placetype":"venue"
},
  "geometry": {"coordinates":[0.6457189918,41.6027946472],"type":"Point"}
}