{
  "type": "Feature",
  "properties": {
    "iso:country":"ES",
    "sg:address":"Ctra. Sta. Barbara-la Senia, S/n",
    "sg:city":"La Galera",
    "sg:orig_category":"Frutas Y Legumbres Frescas (al Por Mayor)",
    "sg:phone":"+34 977 71 93 33",
    "sg:postcode":"43515",
    "sg:province":"Tarragona",
    "wof:name":"Citricos Torreblanca S.c.p.",
    "wof:placetype":"venue"
},
  "geometry": {"coordinates":[0.464320004,40.6839866638],"type":"Point"}
}