{
  "type": "Feature",
  "properties": {
    "iso:country":"ES",
    "sg:address":"Calle de San Francisco, 9",
    "sg:city":"Burgos",
    "sg:orig_category":"Tapiceros Y Tapiceros",
    "sg:phone":"+34 947 20 43 16",
    "sg:postcode":"09003",
    "sg:province":"Burgos",
    "wof:name":"Gonzalez Cubillo Roberto",
    "wof:placetype":"venue"
},
  "geometry": {"coordinates":[-3.7023849487,42.34425354],"type":"Point"}
}