{
  "type": "Feature",
  "properties": {
    "addr:full":"Carrer de Linares, 1 Sant Vicen\u00c7 Dels Horts Barcelona 08620",
    "addr:housenumber":"1",
    "addr:postcode":"08620",
    "addr:street":"Carrer De Linares",
    "iso:country":"ES",
    "sg:address":"Carrer de Linares, 1",
    "sg:city":"Sant Vicen\u00c7 Dels Horts",
    "sg:orig_category":"Molduras, Junquillos, Listones Y Molduras Perforadas",
    "sg:phone":"+34 936 56 57 06",
    "sg:postcode":"08620",
    "sg:province":"Barcelona",
    "wof:name":"Franquet Fernandez Jorge",
    "wof:placetype":"venue"
},
  "geometry": {"coordinates":[1.9968800545,41.3887290955],"type":"Point"}
}