{
  "type": "Feature",
  "properties": {
    "addr:full":"Calle de Mercado, 4 Aguilar Campoo Palencia 34800",
    "addr:housenumber":"4",
    "addr:postcode":"34800",
    "addr:street":"Calle De Mercado",
    "iso:country":"ES",
    "sg:address":"Calle de Mercado, 4",
    "sg:city":"Aguilar Campoo",
    "sg:orig_category":"\u00d3ptica: Instrumentos (fabricaci\u00d3n)",
    "sg:phone":"+34 979 12 36 60",
    "sg:postcode":"34800",
    "sg:province":"Palencia",
    "wof:name":"Escolano Calomarde Francisco",
    "wof:placetype":"venue"
},
  "geometry": {"coordinates":[-4.26252985,42.7937164307],"type":"Point"}
}