{
  "type": "Feature",
  "properties": {
    "addr:full":"Calle de Castelar, 75 Zaragoza Zaragoza 50013",
    "addr:housenumber":"75",
    "addr:postcode":"50013",
    "addr:street":"Calle De Castelar",
    "iso:country":"ES",
    "sg:address":"Calle de Castelar, 75",
    "sg:city":"Zaragoza",
    "sg:orig_category":"Chapister\u00cda",
    "sg:phone":"+34 976 41 19 20",
    "sg:postcode":"50013",
    "sg:province":"Zaragoza",
    "wof:name":"Pina Salvador Gregorio Angel",
    "wof:placetype":"venue"
},
  "geometry": {"coordinates":[-0.8696296215,41.6392059326],"type":"Point"}
}