{
  "type": "Feature",
  "properties": {
    "addr:full":"Calle de Obispo Alburquerque, 3 San Mateo Murcia 30800",
    "addr:housenumber":"3",
    "addr:postcode":"30800",
    "addr:street":"Calle De Obispo Alburquerque",
    "iso:country":"ES",
    "sg:address":"Calle de Obispo Alburquerque, 3",
    "sg:city":"San Mateo",
    "sg:orig_category":"Agentes Generales De Seguros",
    "sg:phone":"+34 968 47 08 58",
    "sg:postcode":"30800",
    "sg:province":"Murcia",
    "wof:name":"Martinez Lopez Pedro",
    "wof:placetype":"venue"
},
  "geometry": {"coordinates":[-1.6905640364,37.680557251],"type":"Point"}
}