{
  "type": "Feature",
  "properties": {
    "addr:full":"Ctra. Villamartin-el Bosque, S/n Prado Del Rey C\u00e1diz 11660",
    "addr:housenumber":"s / n",
    "addr:postcode":"11660",
    "addr:street":"Ctra. Villamartin-El Bosque",
    "iso:country":"ES",
    "sg:address":"Ctra. Villamartin-el Bosque, S/n",
    "sg:city":"Prado Del Rey",
    "sg:orig_category":"Centros De Educaci\u00d3n Especial",
    "sg:phone":"+34 956 72 30 30",
    "sg:postcode":"11660",
    "sg:province":"C\u00e1diz",
    "wof:name":"Junta De Andalucia",
    "wof:placetype":"venue"
},
  "geometry": {"coordinates":[-5.5557088852,36.7894134521],"type":"Point"}
}