{
  "type": "Feature",
  "properties": {
    "iso:country":"ES",
    "sg:address":"Lg Petos(furelos), S/n",
    "sg:city":"Petos",
    "sg:orig_category":"Mataderos Y Talleres De Despiezado",
    "sg:phone":"+34 981 50 53 04",
    "sg:postcode":"15800",
    "sg:province":"La Coru\u00f1a",
    "wof:name":"Carnicas Albino S.l.",
    "wof:placetype":"venue"
},
  "geometry": {"coordinates":[-8.0129041672,42.9135894775],"type":"Point"}
}