{
  "type": "Feature",
  "properties": {
    "addr:full":"Calle de Marcelino Alvarez, 52 Zaragoza Zaragoza 50012",
    "addr:housenumber":"52",
    "addr:postcode":"50012",
    "addr:street":"Calle De Marcelino Alvarez",
    "iso:country":"ES",
    "sg:address":"Calle de Marcelino Alvarez, 52",
    "sg:city":"Zaragoza",
    "sg:orig_category":"Controles De Edificaci\u00d3n (construcci\u00d3n, Seguridad)",
    "sg:phone":"+34 976 75 08 69",
    "sg:postcode":"50012",
    "sg:province":"Zaragoza",
    "wof:name":"Actividades Margalejo S.l.",
    "wof:placetype":"venue"
},
  "geometry": {"coordinates":[-0.9175521731,41.6302223206],"type":"Point"}
}