{
  "type": "Feature",
  "properties": {
    "addr:full":"Calle de San Vicente Martir, 23 Zaragoza Zaragoza 50008",
    "addr:housenumber":"23",
    "addr:postcode":"50008",
    "addr:street":"Calle De San Vicente Martir",
    "iso:country":"ES",
    "sg:address":"Calle de San Vicente Martir, 23",
    "sg:city":"Zaragoza",
    "sg:orig_category":"Procuradores",
    "sg:phone":"+34 976 22 07 72",
    "sg:postcode":"50008",
    "sg:province":"Zaragoza",
    "wof:name":"Bonet Perdigones Maria Pilar",
    "wof:placetype":"venue"
},
  "geometry": {"coordinates":[-0.8795989752,41.6456298828],"type":"Point"}
}