{
  "type": "Feature",
  "properties": {
    "iso:country":"ES",
    "sg:address":"Picara\u00f1a, S/n",
    "sg:city":"Picara\u00d1a",
    "sg:orig_category":"Molduras, Junquillos, Listones Y Molduras Perforadas",
    "sg:phone":"+34 981 80 31 81",
    "sg:postcode":"15980",
    "sg:province":"La Coru\u00f1a",
    "wof:name":"Garcia Ferreiro Josefa",
    "wof:placetype":"venue"
},
  "geometry": {"coordinates":[-8.6395921707,42.8004417419],"type":"Point"}
}