{
  "type": "Feature",
  "properties": {
    "addr:full":"Av Barbera, 408 Sabadell Barcelona 08204",
    "addr:housenumber":"408",
    "addr:postcode":"08204",
    "addr:street":"Av Barbera",
    "iso:country":"ES",
    "sg:address":"Av Barbera, 408",
    "sg:city":"Sabadell",
    "sg:orig_category":"Agencias De Viajes",
    "sg:phone":"+34 937 12 29 29",
    "sg:postcode":"08204",
    "sg:province":"Barcelona",
    "sg:website":"www.barceloviajes.com",
    "wof:name":"Viajes Barcelo S.l.",
    "wof:placetype":"venue"
},
  "geometry": {"coordinates":[2.1175889969,41.5294418335],"type":"Point"}
}