{
  "type": "Feature",
  "properties": {
    "addr:full":"Avda Landako Etorbidea, 7 Durango Vizcaya 48200",
    "addr:housenumber":"7",
    "addr:postcode":"48200",
    "addr:street":"Avda Landako Etorbidea",
    "iso:country":"ES",
    "sg:address":"Avda Landako Etorbidea, 7",
    "sg:city":"Durango",
    "sg:orig_category":"Quiropr\u00c1cticos",
    "sg:phone":"+34 946 20 05 15",
    "sg:postcode":"48200",
    "sg:province":"Vizcaya",
    "wof:name":"Garcia Leon Miren Bakarne",
    "wof:placetype":"venue"
},
  "geometry": {"coordinates":[-2.6327190399,43.1716842651],"type":"Point"}
}