{
  "type": "Feature",
  "properties": {
    "addr:full":"Calle de Azahar, S/n Coru\u00d1a La Coru\u00f1a 15008",
    "addr:housenumber":"s / n",
    "addr:postcode":"15008",
    "addr:street":"Calle De Azahar;La Corun\u0303A",
    "iso:country":"ES",
    "sg:address":"Calle de Azahar, S/n",
    "sg:city":"Coru\u00d1a",
    "sg:orig_category":"Asociaciones, Organismos Culturales Y Socioeducativos",
    "sg:phone":"+34 981 13 91 60",
    "sg:postcode":"15008",
    "sg:province":"La Coru\u00f1a",
    "wof:name":"Asociacion Cultural Tanxedoira",
    "wof:placetype":"venue"
},
  "geometry": {"coordinates":[-8.4036216736,43.3452644348],"type":"Point"}
}