{
  "type": "Feature",
  "properties": {
    "addr:full":"Cra. Nacional Ii, Km. 0458,1 Lleida Lleida 25001",
    "addr:postcode":"25001",
    "addr:street":"Km. 0458,1",
    "iso:country":"ES",
    "sg:address":"Cra. Nacional Ii, Km. 0458,1",
    "sg:city":"Lleida",
    "sg:orig_category":"Asesor\u00cda Para La Organizaci\u00d3n Y Gesti\u00d3n Del Transporte",
    "sg:phone":"+34 973 27 19 43",
    "sg:postcode":"25001",
    "sg:province":"Lleida",
    "wof:name":"Transmayoros S.l.",
    "wof:placetype":"venue"
},
  "geometry": {"coordinates":[0.6414020061,41.604057312],"type":"Point"}
}