{
  "type": "Feature",
  "properties": {
    "iso:country":"ES",
    "sg:address":"Carrer de Gayarre, 49",
    "sg:city":"Perello",
    "sg:orig_category":"Empresas De Carpinter\u00cda De Madera",
    "sg:phone":"+34 977 49 05 63",
    "sg:postcode":"43519",
    "sg:province":"Tarragona",
    "wof:name":"Marsal Serres Jose",
    "wof:placetype":"venue"
},
  "geometry": {"coordinates":[0.7109190226,40.8742141724],"type":"Point"}
}