{
  "type": "Feature",
  "properties": {
    "addr:full":"Calle de Mozart, 15 Madrid Madrid 28008",
    "addr:housenumber":"15",
    "addr:postcode":"madrid;28008",
    "addr:street":"Calle De Mozart",
    "iso:country":"ES",
    "sg:address":"Calle de Mozart, 15",
    "sg:city":"Madrid",
    "sg:orig_category":"Agencias Y Asesores De Publicidad",
    "sg:phone":"+34 915 48 57 38",
    "sg:postcode":"28008",
    "sg:province":"Madrid",
    "wof:name":"Formato Final S.l",
    "wof:placetype":"venue"
},
  "geometry": {"coordinates":[-3.723197937,40.4237480164],"type":"Point"}
}