{
  "type": "Feature",
  "properties": {
    "addr:full":"Ctra. Turegano, S/n Fuentepelayo Segovia 40260",
    "addr:housenumber":"s / n",
    "addr:postcode":"40260",
    "addr:street":"Ctra. Turegano",
    "iso:country":"ES",
    "sg:address":"Ctra. Turegano, S/n",
    "sg:city":"Fuentepelayo",
    "sg:orig_category":"Producci\u00d3n De Champi\u00d1ones",
    "sg:phone":"+34 921 57 40 70",
    "sg:postcode":"40260",
    "sg:province":"Segovia",
    "wof:name":"Setas Naturales S.l.",
    "wof:placetype":"venue"
},
  "geometry": {"coordinates":[-4.1764287949,41.2216300964],"type":"Point"}
}