{
  "type": "Feature",
  "properties": {
    "addr:full":"Calle de Doctor Galvez Ginachero, 6 Fuengirola M\u00e1laga 29640",
    "addr:housenumber":"6",
    "addr:postcode":"29640",
    "addr:street":"Calle De Doctor Galvez Ginachero;Ma\u0301Laga",
    "iso:country":"ES",
    "sg:address":"Calle de Doctor Galvez Ginachero, 6",
    "sg:city":"Fuengirola",
    "sg:orig_category":"Ropa Para Ni\u00d1os (al Por Menor)",
    "sg:phone":"+34 952 66 57 26",
    "sg:postcode":"29640",
    "sg:province":"M\u00e1laga",
    "wof:name":"Guirao Cejas Guillermo",
    "wof:placetype":"venue"
},
  "geometry": {"coordinates":[-4.6198248863,36.5439376831],"type":"Point"}
}