{
  "type": "Feature",
  "properties": {
    "iso:country":"ES",
    "sg:address":"Avda Castrelos, 75",
    "sg:city":"Vigo",
    "sg:orig_category":"Florister\u00cdas",
    "sg:phone":"+34 986 29 66 22",
    "sg:postcode":"36210",
    "sg:province":"Pontevedra",
    "wof:name":"Rodriguez Paz Jose Manuel",
    "wof:placetype":"venue"
},
  "geometry": {"coordinates":[-8.7319192886,42.2100868225],"type":"Point"}
}