{
  "type": "Feature",
  "properties": {
    "iso:country":"ES",
    "sg:address":"Calle de Santiago, 16",
    "sg:city":"Valladolid",
    "sg:orig_category":"Cl\u00cdnicas M\u00c9dicas",
    "sg:phone":"+34 983 34 30 00",
    "sg:postcode":"47001",
    "sg:province":"Valladolid",
    "wof:name":"Martierra S.a.",
    "wof:placetype":"venue"
},
  "geometry": {"coordinates":[-4.7290058136,41.6500015259],"type":"Point"}
}