{
  "type": "Feature",
  "properties": {
    "addr:full":"Pase Comenge, 18 Lalueza Huesca 22214",
    "addr:housenumber":"18",
    "addr:postcode":"22214",
    "addr:street":"Comenge",
    "iso:country":"ES",
    "sg:address":"Pase Comenge, 18",
    "sg:city":"Lalueza",
    "sg:orig_category":"Mercer\u00cda, Lencer\u00cda (al Por Menor)",
    "sg:phone":"+34 974 57 50 67",
    "sg:postcode":"22214",
    "sg:province":"Huesca",
    "wof:name":"Pena Alpin Miguel Angel",
    "wof:placetype":"venue"
},
  "geometry": {"coordinates":[-0.2614510059,41.8452949524],"type":"Point"}
}