{
  "type": "Feature",
  "properties": {
    "addr:full":"Calle de Meson, 53 Alozaina M\u00e1laga 29567",
    "addr:housenumber":"53",
    "addr:postcode":"29567",
    "addr:street":"Calle De Meson;Ma\u0301Laga",
    "iso:country":"ES",
    "sg:address":"Calle de Meson, 53",
    "sg:city":"Alozaina",
    "sg:orig_category":"Bazares, Art\u00cdculos De Limpieza Y De Cocina (al Por Menor)",
    "sg:phone":"+34 952 48 00 20",
    "sg:postcode":"29567",
    "sg:province":"M\u00e1laga",
    "wof:name":"Sanchez Pi\u00f1ero Francisca",
    "wof:placetype":"venue"
},
  "geometry": {"coordinates":[-4.8587489128,36.7277870178],"type":"Point"}
}