{
  "type": "Feature",
  "properties": {
    "iso:country":"ES",
    "sg:address":"Maestro Tarraga, 1",
    "sg:city":"Onil",
    "sg:orig_category":"Importaci\u00d3n",
    "sg:phone":"+34 965 56 51 00",
    "sg:postcode":"03430",
    "sg:province":"Alicante",
    "sg:website":"www.tsc.es/dollfactory",
    "wof:name":"The Doll Factory Europe S.l.",
    "wof:placetype":"venue"
},
  "geometry": {"coordinates":[-0.6657490134,38.630355835],"type":"Point"}
}