{
  "type": "Feature",
  "properties": {
    "addr:full":"Santa Soria, 22 Estella Navarra 31200",
    "addr:housenumber":"22",
    "addr:postcode":"31200",
    "addr:street":"Soria",
    "iso:country":"ES",
    "sg:address":"Santa Soria, 22",
    "sg:city":"Estella",
    "sg:orig_category":"Asilos De Ancianos. Centros Privados",
    "sg:phone":"+34 948 54 69 00",
    "sg:postcode":"31200",
    "sg:province":"Navarra",
    "wof:name":"Luz 3015 S.l.",
    "wof:placetype":"venue"
},
  "geometry": {"coordinates":[-2.0393199921,42.6807670593],"type":"Point"}
}