{
  "type": "Feature",
  "properties": {
    "iso:country":"ES",
    "sg:address":"Pol. Ind. Sesrovires, S/n",
    "sg:city":"S. Esteve Sesrovires",
    "sg:orig_category":"Negocio De Metales No Ferrosos",
    "sg:phone":"+34 937 71 53 07",
    "sg:postcode":"08635",
    "sg:province":"Barcelona",
    "wof:name":"International Bron-metal S. A.",
    "wof:placetype":"venue"
},
  "geometry": {"coordinates":[1.8731199503,41.4965515137],"type":"Point"}
}