{
  "type": "Feature",
  "properties": {
    "iso:country":"ES",
    "sg:address":"Calle de Montemayor, 1",
    "sg:city":"Cordoba",
    "sg:orig_category":"Bisuteros (fabricaci\u00d3n, Al Por Mayor)",
    "sg:phone":"+34 957 29 46 99",
    "sg:postcode":"14003",
    "sg:province":"C\u00f3rdoba",
    "wof:name":"Auprisa S.a.",
    "wof:placetype":"venue"
},
  "geometry": {"coordinates":[-4.7832827568,37.8832817078],"type":"Point"}
}