{
  "type": "Feature",
  "properties": {
    "addr:full":"Ctra Colunga De, S/n Lastres Asturias 33330",
    "addr:postcode":"33330",
    "addr:street":"Ctra Colunga De S / N Lastres Asturias",
    "iso:country":"ES",
    "sg:address":"Ctra Colunga De, S/n",
    "sg:city":"Lastres",
    "sg:orig_category":"Quincaller\u00cda (al Por Menor)",
    "sg:phone":"+34 985 85 04 31",
    "sg:postcode":"33330",
    "sg:province":"Asturias",
    "wof:name":"Tuero Marcilla Luisa Maria",
    "wof:placetype":"venue"
},
  "geometry": {"coordinates":[-5.2697310448,43.5140571594],"type":"Point"}
}