{
  "type": "Feature",
  "properties": {
    "addr:full":"Calle de San Andres, 42 Alburquerque Badajoz 06510",
    "addr:housenumber":"42",
    "addr:street":"Calle De San Andres",
    "iso:country":"ES",
    "sg:address":"Calle de San Andres, 42",
    "sg:city":"Alburquerque",
    "sg:orig_category":"M\u00c1rmoles, Granitos Y Piedras Naturales",
    "sg:phone":"+34 924 40 13 87",
    "sg:postcode":"06510",
    "sg:province":"Badajoz",
    "wof:name":"Ventura Folleco Andres",
    "wof:placetype":"venue"
},
  "geometry": {"coordinates":[-6.9990391731,39.2250595093],"type":"Point"}
}