{
  "type": "Feature",
  "properties": {
    "iso:country":"ES",
    "sg:address":"Calle de Concepcion Arenal, 3",
    "sg:city":"Barrio De Peral",
    "sg:orig_category":"Supermercados Y Hipermercados",
    "sg:phone":"+34 968 53 37 06",
    "sg:postcode":"30300",
    "sg:province":"Murcia",
    "wof:name":"Martinez Pastor Juan",
    "wof:placetype":"venue"
},
  "geometry": {"coordinates":[-0.9910330176,37.6290283203],"type":"Point"}
}