{
  "type": "Feature",
  "properties": {
    "addr:full":"Av Sant Ferran, 40 Palma Islas Baleares 07013",
    "addr:housenumber":"40",
    "addr:postcode":"07013",
    "addr:street":"Av Sant Ferran",
    "iso:country":"ES",
    "sg:address":"Av Sant Ferran, 40",
    "sg:city":"Palma",
    "sg:orig_category":"Sociedades, Compa\u00d1\u00cdas Aseguradoras",
    "sg:phone":"+34 971 28 55 35",
    "sg:postcode":"07013",
    "sg:province":"Islas Baleares",
    "sg:website":"www.giletasegurancess.cjd.net",
    "wof:name":"Gilet Vidal Jose Miguel",
    "wof:placetype":"venue"
},
  "geometry": {"coordinates":[2.6338510513,39.578125],"type":"Point"}
}