{
  "type": "Feature",
  "properties": {
    "addr:full":"Avda Nocedo, 36 Le\u00f3n Le\u00f3n 24007",
    "addr:housenumber":"36",
    "addr:postcode":"24007",
    "addr:street":"Avda Nocedo;Leo\u0301N",
    "iso:country":"ES",
    "sg:address":"Avda Nocedo, 36",
    "sg:city":"Le\u00f3n",
    "sg:orig_category":"Tiendas De Grano, Frutas Y Legumbres Secas (al Por Menor)",
    "sg:phone":"+34 987 23 40 36",
    "sg:postcode":"24007",
    "sg:province":"Le\u00f3n",
    "wof:name":"Alvarez Nistal Angel",
    "wof:placetype":"venue"
},
  "geometry": {"coordinates":[-5.5686678886,42.6060638428],"type":"Point"}
}