{
  "type": "Feature",
  "properties": {
    "addr:full":"Pase Colon, 45 Irun Guip\u00f9zcoa 20301",
    "addr:housenumber":"45",
    "addr:postcode":"20301",
    "addr:street":"Colon;Guipu\u0300Zcoa",
    "iso:country":"ES",
    "sg:address":"Pase Colon, 45",
    "sg:city":"Irun",
    "sg:orig_category":"Transportes Internacionales",
    "sg:phone":"+34 943 61 39 64",
    "sg:postcode":"20301",
    "sg:province":"Guip\u00f9zcoa",
    "wof:name":"Fernandez-rivera Vivanco Jesus",
    "wof:placetype":"venue"
},
  "geometry": {"coordinates":[-1.7902339697,43.3395233154],"type":"Point"}
}