{
  "type": "Feature",
  "properties": {
    "addr:full":"Carr Llitera, 8 Lleida Lleida 25004",
    "addr:housenumber":"8",
    "addr:postcode":"25004",
    "addr:street":"Carr Llitera",
    "iso:country":"ES",
    "sg:address":"Carr Llitera, 8",
    "sg:city":"Lleida",
    "sg:orig_category":"Negocio De Madera",
    "sg:phone":"+34 973 24 09 45",
    "sg:postcode":"25004",
    "sg:province":"Lleida",
    "wof:name":"Paris Mele Jose",
    "wof:placetype":"venue"
},
  "geometry": {"coordinates":[0.6200960279,41.6188659668],"type":"Point"}
}