{
  "type": "Feature",
  "properties": {
    "addr:full":"Maestro Trujillo, 5 Quesada Ja\u00e9n 23480",
    "addr:housenumber":"5",
    "addr:postcode":"23480",
    "addr:street":"Trujillo",
    "iso:country":"ES",
    "sg:address":"Maestro Trujillo, 5",
    "sg:city":"Quesada",
    "sg:orig_category":"Fotograf\u00cda Art\u00cdstica Y Retratos",
    "sg:phone":"+34 953 71 40 51",
    "sg:postcode":"23480",
    "sg:province":"Ja\u00e9n",
    "wof:name":"Perez Fernandez Antonio",
    "wof:placetype":"venue"
},
  "geometry": {"coordinates":[-3.0672140121,37.845615387],"type":"Point"}
}