{
  "type": "Feature",
  "properties": {
    "addr:full":"Ctra Valderas, 7 Villanueva Campo Zamora 49100",
    "addr:housenumber":"7",
    "addr:postcode":"49100",
    "addr:street":"Ctra Valderas",
    "iso:country":"ES",
    "sg:address":"Ctra Valderas, 7",
    "sg:city":"Villanueva Campo",
    "sg:orig_category":"Negocio De Materiales De Construcci\u00d3n",
    "sg:phone":"+34 980 66 62 49",
    "sg:postcode":"49100",
    "sg:province":"Zamora",
    "wof:name":"Legido De La Torre Nicolas",
    "wof:placetype":"venue"
},
  "geometry": {"coordinates":[-5.3572039604,42.0025634766],"type":"Point"}
}