{
  "type": "Feature",
  "properties": {
    "addr:full":"Carrer de Joan Prim, 270 Granollers Barcelona 08402",
    "addr:housenumber":"270",
    "addr:postcode":"08402",
    "addr:street":"Carrer De Joan Prim",
    "iso:country":"ES",
    "sg:address":"Carrer de Joan Prim, 270",
    "sg:city":"Granollers",
    "sg:orig_category":"Promotores Constructores",
    "sg:phone":"+34 938 40 27 70",
    "sg:postcode":"08402",
    "sg:province":"Barcelona",
    "wof:name":"Prosemar S.l.",
    "wof:placetype":"venue"
},
  "geometry": {"coordinates":[2.2915999889,41.616809845],"type":"Point"}
}