{
  "type": "Feature",
  "properties": {
    "iso:country":"ES",
    "sg:address":"Calle de Gabriel Miro, 32",
    "sg:city":"Torrevieja",
    "sg:orig_category":"Inmobiliaria (agencias)",
    "sg:phone":"+34 966 70 55 06",
    "sg:postcode":"03180",
    "sg:province":"Alicante",
    "wof:name":"Fernandez Sanchez Evelia",
    "wof:placetype":"venue"
},
  "geometry": {"coordinates":[-0.6873779893,37.9777297974],"type":"Point"}
}