{
  "type": "Feature",
  "properties": {
    "iso:country":"ES",
    "sg:address":"Calle de Campo De Criptana, 13",
    "sg:city":"Socuellamos",
    "sg:classifiers":[
        {
            "category":"Personal",
            "subcategory":"Barber",
            "type":"Services"
        }
    ],
    "sg:phone":"+34 926 53 27 39",
    "sg:postcode":"13630",
    "sg:province":"Ciudad Real",
    "sg:tags":[
        "caballeros",
        "de",
        "peluqueros"
    ],
    "wof:name":"Navarro Varea Jaime",
    "wof:placetype":"venue"
},
  "geometry": {"coordinates":[-2.8003630638,39.2857818604],"type":"Point"}
}