{
  "type": "Feature",
  "properties": {
    "addr:full":"Avda Republica Argentina, 2 Sevilla Sevilla 41011",
    "addr:housenumber":"2",
    "addr:postcode":"41011",
    "addr:street":"Avda Republica Argentina",
    "iso:country":"ES",
    "sg:address":"Avda Republica Argentina, 2",
    "sg:city":"Sevilla",
    "sg:orig_category":"M\u00c9dicos: Neumolog\u00cda",
    "sg:phone":"+34 954 27 33 00",
    "sg:postcode":"41011",
    "sg:province":"Sevilla",
    "wof:name":"Villa Arellano Francisco",
    "wof:placetype":"venue"
},
  "geometry": {"coordinates":[-5.9988088608,37.3794517517],"type":"Point"}
}