{
  "type": "Feature",
  "properties": {
    "iso:country":"ES",
    "sg:address":"Calle de Doctor J.j. Domine, 6",
    "sg:city":"Valencia",
    "sg:orig_category":"Delegados, Agentes De Tr\u00c1nsito, Auxiliares De Transporte Internacional",
    "sg:phone":"+34 963 67 87 98",
    "sg:postcode":"46011",
    "sg:province":"Valencia",
    "wof:name":"Transportes Leopoldo Romero S.l.",
    "wof:placetype":"venue"
},
  "geometry": {"coordinates":[-0.3327009976,39.4610366821],"type":"Point"}
}