{
  "type": "Feature",
  "properties": {
    "iso:country":"ES",
    "sg:address":"Canal, 2",
    "sg:city":"Camponaraya",
    "sg:orig_category":"Semiller\u00cdas",
    "sg:phone":"+34 987 46 33 67",
    "sg:postcode":"24410",
    "sg:province":"Le\u00f3n",
    "wof:name":"Novoa Amil Joaquina",
    "wof:placetype":"venue"
},
  "geometry": {"coordinates":[-6.6667189598,42.5784492493],"type":"Point"}
}