{
  "type": "Feature",
  "properties": {
    "addr:full":"Poligono Industrial Ii, S/n Guijuelo Salamanca 37770",
    "addr:housenumber":"s / n",
    "addr:postcode":"37770",
    "iso:country":"ES",
    "sg:address":"Poligono Industrial Ii, S/n",
    "sg:city":"Guijuelo",
    "sg:orig_category":"Charcuter\u00cdas (al Por Mayor)",
    "sg:phone":"+34 923 58 15 68",
    "sg:postcode":"37770",
    "sg:province":"Salamanca",
    "wof:name":"Arturo Sanchez E Hijos S.l.",
    "wof:placetype":"venue"
},
  "geometry": {"coordinates":[-5.6983981133,40.5857048035],"type":"Point"}
}