{
  "type": "Feature",
  "properties": {
    "iso:country":"ES",
    "sg:address":"Avda Navia, 10",
    "sg:city":"Becerrea",
    "sg:orig_category":"Asesor\u00cda Fiscal Y Jur\u00cddica",
    "sg:phone":"+34 982 36 03 76",
    "sg:postcode":"27640",
    "sg:province":"Lugo",
    "wof:name":"Pereira Fernandez Carlos",
    "wof:placetype":"venue"
},
  "geometry": {"coordinates":[-7.1622238159,42.8542518616],"type":"Point"}
}