{
  "type": "Feature",
  "properties": {
    "addr:full":"La Paz, 22 Zaragoza Zaragoza 50008",
    "addr:housenumber":"22",
    "addr:postcode":"50008",
    "addr:street":"La Paz",
    "iso:country":"ES",
    "sg:address":"La Paz, 22",
    "sg:city":"Zaragoza",
    "sg:orig_category":"Asociaciones Y Clubs Deportivos",
    "sg:phone":"+34 976 23 78 40",
    "sg:postcode":"50008",
    "sg:province":"Zaragoza",
    "sg:website":"www.gimnasioironsalfer.com",
    "wof:name":"Iron Salfer S. C.",
    "wof:placetype":"venue"
},
  "geometry": {"coordinates":[-0.8837230206,41.6423149109],"type":"Point"}
}