{
  "type": "Feature",
  "properties": {
    "iso:country":"ES",
    "sg:address":"Carr Ferran Rambla, 42",
    "sg:city":"Lleida",
    "sg:orig_category":"Abogados",
    "sg:phone":"+34 973 22 05 87",
    "sg:postcode":"25007",
    "sg:province":"Lleida",
    "wof:name":"Mases Estany Ignasi",
    "wof:placetype":"venue"
},
  "geometry": {"coordinates":[0.6301735044,41.6172561646],"type":"Point"}
}