{
  "type": "Feature",
  "properties": {
    "addr:full":"Carr Mare Nostrum, 52 Perello Valencia 46420",
    "addr:housenumber":"52",
    "addr:postcode":"46420",
    "addr:street":"Carr Mare Nostrum",
    "iso:country":"ES",
    "sg:address":"Carr Mare Nostrum, 52",
    "sg:city":"Perello",
    "sg:orig_category":"Hielo Artificial (fabricaci\u00d3n, Distribuci\u00d3n)",
    "sg:phone":"+34 961 77 06 14",
    "sg:postcode":"46420",
    "sg:province":"Valencia",
    "wof:name":"Vicente Mocholi Grau",
    "wof:placetype":"venue"
},
  "geometry": {"coordinates":[-0.2728460133,39.2749443054],"type":"Point"}
}