{
  "type": "Feature",
  "properties": {
    "iso:country":"ES",
    "sg:address":"Cm\u00d1o Feiranova, 79",
    "sg:city":"Feira Nova",
    "sg:orig_category":"Alimentaci\u00d3n General (al Por Menor)",
    "sg:phone":"+34 986 50 07 23",
    "sg:postcode":"36619",
    "sg:province":"Pontevedra",
    "wof:name":"Se\u00f1orans Romero Manuel",
    "wof:placetype":"venue"
},
  "geometry": {"coordinates":[-8.7645044327,42.5797958374],"type":"Point"}
}