{
  "type": "Feature",
  "properties": {
    "iso:country":"ES",
    "sg:address":"Calle de Elvira, 17",
    "sg:city":"Madrid",
    "sg:orig_category":"Farmacias",
    "sg:phone":"+34 915 74 16 77",
    "sg:postcode":"28028",
    "sg:province":"Madrid",
    "wof:name":"Jover Navalon Maria Desamparados",
    "wof:placetype":"venue"
},
  "geometry": {"coordinates":[-3.665211916,40.4222717285],"type":"Point"}
}