{
  "type": "Feature",
  "properties": {
    "iso:country":"ES",
    "sg:address":"Calle de Ramon Y Cajal, 60",
    "sg:city":"Mahora",
    "sg:orig_category":"Tractores Agr\u00cdcolas Y Remolques",
    "sg:phone":"+34 967 49 41 39",
    "sg:postcode":"02240",
    "sg:province":"Albacete",
    "wof:name":"Hermanos Garcia C.b.",
    "wof:placetype":"venue"
},
  "geometry": {"coordinates":[-1.7204790115,39.2124786377],"type":"Point"}
}