{
  "type": "Feature",
  "properties": {
    "addr:full":"Carretera De Alcaracejos, Km. 0128,0 Pozoblanco C\u00f3rdoba 14400",
    "addr:postcode":"14400",
    "addr:street":"Carretera De Alcaracejos Km. 0128,0;Co\u0301Rdoba",
    "iso:country":"ES",
    "sg:address":"Carretera De Alcaracejos, Km. 0128,0",
    "sg:city":"Pozoblanco",
    "sg:orig_category":"Cr\u00cda De Animales",
    "sg:phone":"+34 957 33 90 89",
    "sg:postcode":"14400",
    "sg:province":"C\u00f3rdoba",
    "wof:name":"Granja San Martin S.c.p.",
    "wof:placetype":"venue"
},
  "geometry": {"coordinates":[-4.8739800453,38.3794937134],"type":"Point"}
}