{
  "type": "Feature",
  "properties": {
    "iso:country":"ES",
    "sg:address":"Calle de Tamarindos, 1",
    "sg:city":"Arroyo De La Miel-benalmadena Costa",
    "sg:orig_category":"Importaci\u00d3n",
    "sg:phone":"+34 952 44 36 87",
    "sg:postcode":"29630",
    "sg:province":"M\u00e1laga",
    "wof:name":"Benhamu Corcias David",
    "wof:placetype":"venue"
},
  "geometry": {"coordinates":[-4.5179247856,36.597618103],"type":"Point"}
}