{
  "type": "Feature",
  "properties": {
    "addr:full":"Calle de Rincon De Los Cobos, 15 Huerta Del Raal Murcia 30139",
    "addr:housenumber":"15",
    "addr:postcode":"30139",
    "addr:street":"Calle De Rincon De Los Cobos",
    "iso:country":"ES",
    "sg:address":"Calle de Rincon De Los Cobos, 15",
    "sg:city":"Huerta Del Raal",
    "sg:orig_category":"Construcciones Met\u00c1licas",
    "sg:phone":"+34 968 60 05 97",
    "sg:postcode":"30139",
    "sg:province":"Murcia",
    "wof:name":"Estructuras Moparti.s.l.l.",
    "wof:placetype":"venue"
},
  "geometry": {"coordinates":[-1.0079319477,38.053894043],"type":"Point"}
}