{
  "type": "Feature",
  "properties": {
    "addr:full":"Avda Lugo (de), 6 Chantada Lugo 27500",
    "addr:housenumber":"6",
    "addr:postcode":"27500",
    "addr:street":"Avda Lugo De",
    "iso:country":"ES",
    "sg:address":"Avda Lugo (de), 6",
    "sg:city":"Chantada",
    "sg:orig_category":"Centros Empresariales",
    "sg:phone":"+34 982 46 20 20",
    "sg:postcode":"27500",
    "sg:province":"Lugo",
    "wof:name":"Asociacion Vitivinicola Ribeirao",
    "wof:placetype":"venue"
},
  "geometry": {"coordinates":[-7.7687158585,42.6167869568],"type":"Point"}
}