{
  "type": "Feature",
  "properties": {
    "addr:full":"Rond Batres (de), 32 Arganda Madrid 28500",
    "addr:postcode":"28500",
    "addr:street":"Rond",
    "iso:country":"ES",
    "sg:address":"Rond Batres (de), 32",
    "sg:city":"Arganda",
    "sg:orig_category":"Cl\u00cdnicas Dentales",
    "sg:phone":"+34 918 70 35 86",
    "sg:postcode":"28500",
    "sg:province":"Madrid",
    "wof:name":"Oral Salud S.l.",
    "wof:placetype":"venue"
},
  "geometry": {"coordinates":[-3.4406979084,40.2999954224],"type":"Point"}
}