{
  "type": "Feature",
  "properties": {
    "addr:full":"Carr Sagunt, 38 Palafrugell Girona 17200",
    "addr:housenumber":"38",
    "addr:postcode":"17200",
    "addr:street":"Carr Sagunt",
    "iso:country":"ES",
    "sg:address":"Carr Sagunt, 38",
    "sg:city":"Palafrugell",
    "sg:orig_category":"Alimentaci\u00d3n General (al Por Menor)",
    "sg:phone":"+34 972 30 14 99",
    "sg:postcode":"17200",
    "sg:province":"Girona",
    "wof:name":"Dispes Vigas Juan",
    "wof:placetype":"venue"
},
  "geometry": {"coordinates":[3.170156002,41.9158935547],"type":"Point"}
}