{
  "type": "Feature",
  "properties": {
    "addr:full":"Ptda Surrach, S/n Benicarlo Castell\u00f3n 12580",
    "addr:housenumber":"s",
    "addr:postcode":"12580",
    "addr:street":"Ptda Surrach;/ N;Castello\u0301N",
    "iso:country":"ES",
    "sg:address":"Ptda Surrach, S/n",
    "sg:city":"Benicarlo",
    "sg:orig_category":"Transportes Por Carretera: Lotes Completos, Mercanc\u00cdas Diversas",
    "sg:phone":"+34 964 46 74 95",
    "sg:postcode":"12580",
    "sg:province":"Castell\u00f3n",
    "sg:website":"www.santoscampos.com",
    "wof:name":"Transportes Santos Campos S.a.",
    "wof:placetype":"venue"
},
  "geometry": {"coordinates":[0.4042100012,40.4457893372],"type":"Point"}
}