{
  "type": "Feature",
  "properties": {
    "addr:full":"Bazkardo Plaza, 5 Andoain Guip\u00f9zcoa 20140",
    "addr:housenumber":"5",
    "addr:postcode":"20140",
    "addr:street":"Bazkardo Plaza;Guipu\u0300Zcoa",
    "iso:country":"ES",
    "sg:address":"Bazkardo Plaza, 5",
    "sg:city":"Andoain",
    "sg:orig_category":"Alimentaci\u00d3n General (al Por Menor)",
    "sg:phone":"+34 943 59 30 78",
    "sg:postcode":"20140",
    "sg:province":"Guip\u00f9zcoa",
    "wof:name":"Alimentacion Bazkardo, S.l.",
    "wof:placetype":"venue"
},
  "geometry": {"coordinates":[-2.0233960152,43.2229309082],"type":"Point"}
}