{
  "type": "Feature",
  "properties": {
    "iso:country":"ES",
    "sg:address":"Carretera De Coin-ronda, S/n",
    "sg:city":"Coin",
    "sg:orig_category":"Sanatorios M\u00c9dico",
    "sg:phone":"+34 952 45 30 03",
    "sg:postcode":"29100",
    "sg:province":"M\u00e1laga",
    "wof:name":"Servicio Andaluz De Salud",
    "wof:placetype":"venue"
},
  "geometry": {"coordinates":[-4.7622389793,36.6639595032],"type":"Point"}
}