{
  "type": "Feature",
  "properties": {
    "iso:country":"ES",
    "sg:address":"Carrer de Horta, 157",
    "sg:city":"Barcelona",
    "sg:orig_category":"Agencias Y Agentes Comerciales, Representantes",
    "sg:phone":"+34 934 29 92 68",
    "sg:postcode":"08032",
    "sg:province":"Barcelona",
    "wof:name":"Freixas Martinez Jose Oriol",
    "wof:placetype":"venue"
},
  "geometry": {"coordinates":[2.1568989754,41.4325256348],"type":"Point"}
}