{
  "type": "Feature",
  "properties": {
    "iso:country":"ES",
    "sg:address":"Calle de Juan Martin, 22",
    "sg:city":"Jodar",
    "sg:orig_category":"Cester\u00cda (fabricaci\u00d3n)",
    "sg:phone":"+34 953 78 50 38",
    "sg:postcode":"23500",
    "sg:province":"Ja\u00e9n",
    "wof:name":"Serrano Gamez Carmen",
    "wof:placetype":"venue"
},
  "geometry": {"coordinates":[-3.3524289131,37.8458328247],"type":"Point"}
}