{
  "type": "Feature",
  "properties": {
    "addr:full":"Ctra Zorrotza-kastrexana, 10 Bilbao Vizcaya 48013",
    "addr:housenumber":"10",
    "addr:postcode":"48013",
    "addr:street":"Ctra Zorrotza-Kastrexana",
    "iso:country":"ES",
    "sg:address":"Ctra Zorrotza-kastrexana, 10",
    "sg:city":"Bilbao",
    "sg:orig_category":"Inmobiliaria (agencias)",
    "sg:phone":"+34 944 27 81 82",
    "sg:postcode":"48013",
    "sg:province":"Vizcaya",
    "wof:name":"Consulting Kastrexana S.l.",
    "wof:placetype":"venue"
},
  "geometry": {"coordinates":[-2.9720449448,43.2757492065],"type":"Point"}
}