{
  "type": "Feature",
  "properties": {
    "iso:country":"ES",
    "sg:address":"Calle de Serrano, 5",
    "sg:city":"Badajoz",
    "sg:orig_category":"Guarda",
    "sg:phone":"+34 924 24 29 87",
    "sg:postcode":"06008",
    "sg:province":"Badajoz",
    "wof:name":"Gomez Peralta Rafael",
    "wof:placetype":"venue"
},
  "geometry": {"coordinates":[-6.962018013,38.8816604614],"type":"Point"}
}