{
  "type": "Feature",
  "properties": {
    "iso:country":"ES",
    "sg:address":"Carr Tordera, 47",
    "sg:city":"Blanes",
    "sg:orig_category":"Aceros Inoxidables",
    "sg:phone":"+34 972 35 40 00",
    "sg:postcode":"17300",
    "sg:province":"Girona",
    "wof:name":"Jerinox S.l.",
    "wof:placetype":"venue"
},
  "geometry": {"coordinates":[2.7795417309,41.6811981201],"type":"Point"}
}