{
  "type": "Feature",
  "properties": {
    "iso:country":"ES",
    "sg:address":"Avda Juan Xxiii, 62",
    "sg:city":"Grove",
    "sg:orig_category":"Serigraf\u00cda (material Y Suministros)",
    "sg:phone":"+34 986 73 31 55",
    "sg:postcode":"36980",
    "sg:province":"Pontevedra",
    "wof:name":"Blanco Rubirosa David",
    "wof:placetype":"venue"
},
  "geometry": {"coordinates":[-8.86282444,42.4956588745],"type":"Point"}
}