{
  "type": "Feature",
  "properties": {
    "addr:full":"Avda Almendros (de Los), 4 Cabanillas Campo Guadalajara 19171",
    "addr:housenumber":"4",
    "addr:postcode":"19171",
    "addr:street":"Avda Almendros De Los",
    "iso:country":"ES",
    "sg:address":"Avda Almendros (de Los), 4",
    "sg:city":"Cabanillas Campo",
    "sg:orig_category":"Alimentaci\u00d3n General (al Por Menor)",
    "sg:phone":"+34 949 32 44 97",
    "sg:postcode":"19171",
    "sg:province":"Guadalajara",
    "wof:name":"Sociedad Anonima De Supermercados Y Autoservicios",
    "wof:placetype":"venue"
},
  "geometry": {"coordinates":[-3.2317419052,40.6438217163],"type":"Point"}
}