{
  "type": "Feature",
  "properties": {
    "iso:country":"ES",
    "sg:address":"Pol Ind Magdalena, S/n",
    "sg:city":"Castello Plana",
    "sg:orig_category":"Suministros Y Materiales Industriales",
    "sg:phone":"+34 964 25 34 88",
    "sg:postcode":"12004",
    "sg:province":"Castell\u00f3n",
    "sg:website":"www.motores-industriales.com",
    "wof:name":"Tierra Unida S.l.",
    "wof:placetype":"venue"
},
  "geometry": {"coordinates":[-0.0441690013,40.0043563843],"type":"Point"}
}