{
  "type": "Feature",
  "properties": {
    "iso:country":"ES",
    "sg:address":"Carrer de Ramon Muntaner, 1",
    "sg:city":"Gava",
    "sg:orig_category":"Empresas De Desmonte",
    "sg:phone":"+34 936 35 50 35",
    "sg:postcode":"08850",
    "sg:province":"Barcelona",
    "wof:name":"Excaserga S.l.",
    "wof:placetype":"venue"
},
  "geometry": {"coordinates":[1.9972699881,41.3029785156],"type":"Point"}
}