{
  "type": "Feature",
  "properties": {
    "addr:full":"Calle de Charco Prieto, 7 Mancha Blanca Las Palmas 35560",
    "addr:housenumber":"7",
    "addr:postcode":"35560",
    "addr:street":"Calle De Charco Prieto;Blanca",
    "iso:country":"ES",
    "sg:address":"Calle de Charco Prieto, 7",
    "sg:city":"Mancha Blanca",
    "sg:orig_category":"Productores Recolectores, Venta Directa De Vinos",
    "sg:phone":"+34 928 84 07 37",
    "sg:postcode":"35560",
    "sg:province":"Las Palmas",
    "wof:name":"Bodegas Reymar S.l.",
    "wof:placetype":"venue"
},
  "geometry": {"coordinates":[-13.6885166168,29.0418300629],"type":"Point"}
}