{
  "type": "Feature",
  "properties": {
    "addr:full":"Calle de Oca\u00d1a, 2 Toledo Toledo 45004",
    "addr:housenumber":"2",
    "addr:postcode":"45004",
    "addr:street":"Calle De Ocan\u0303A",
    "iso:country":"ES",
    "sg:address":"Calle de Oca\u00d1a, 2",
    "sg:city":"Toledo",
    "sg:orig_category":"Abogados",
    "sg:phone":"+34 925 25 29 94",
    "sg:postcode":"45004",
    "sg:province":"Toledo",
    "wof:name":"Ruiz Bermudez Mario",
    "wof:placetype":"venue"
},
  "geometry": {"coordinates":[-4.0280299187,39.8656234741],"type":"Point"}
}