{
  "type": "Feature",
  "properties": {
    "addr:full":"Avda Cumbres Las (cerrado Elviria), 1 Elviria M\u00e1laga 29604",
    "addr:housenumber":"1",
    "addr:postcode":"29604",
    "addr:street":"Avda Cumbres Las;Elviria Ma\u0301Laga",
    "iso:country":"ES",
    "sg:address":"Avda Cumbres Las (cerrado Elviria), 1",
    "sg:city":"Elviria",
    "sg:orig_category":"Arquitectos",
    "sg:phone":"+34 952 83 24 48",
    "sg:postcode":"29604",
    "sg:province":"M\u00e1laga",
    "wof:name":"Milenium Arquitectura S.l.",
    "wof:placetype":"venue"
},
  "geometry": {"coordinates":[-4.7816491127,36.5002708435],"type":"Point"}
}