{
  "type": "Feature",
  "properties": {
    "iso:country":"ES",
    "sg:address":"Rua Capitan Eloy, 18",
    "sg:city":"Ourense",
    "sg:orig_category":"Limpieza Industrial",
    "sg:phone":"+34 988 21 71 33",
    "sg:postcode":"32003",
    "sg:province":"Ourense",
    "sg:website":"www.eurolimp.es",
    "wof:name":"Construcciones Isidoro Varela Varela Sl",
    "wof:placetype":"venue"
},
  "geometry": {"coordinates":[-7.865085125,42.339302063],"type":"Point"}
}