{
  "type": "Feature",
  "properties": {
    "addr:full":"Poli Las Capellanias, S/n Caceres C\u00e1ceres 10005",
    "addr:housenumber":"s",
    "addr:postcode":"10005",
    "addr:street":"/ N;Ca\u0301Ceres",
    "iso:country":"ES",
    "sg:address":"Poli Las Capellanias, S/n",
    "sg:city":"Caceres",
    "sg:orig_category":"Agencias Y Agentes Comerciales, Representantes",
    "sg:phone":"+34 927 23 06 44",
    "sg:postcode":"10005",
    "sg:province":"C\u00e1ceres",
    "wof:name":"Antonio Mari\u00f1o Sl",
    "wof:placetype":"venue"
},
  "geometry": {"coordinates":[-6.5356450081,39.3445549011],"type":"Point"}
}