{
  "type": "Feature",
  "properties": {
    "iso:country":"ES",
    "sg:address":"Plaz Capellania (la), 10",
    "sg:city":"Puebla",
    "sg:orig_category":"Plomeros",
    "sg:phone":"+34 968 55 90 68",
    "sg:postcode":"30395",
    "sg:province":"Murcia",
    "wof:name":"Perez Martinez Maria Dolores",
    "wof:placetype":"venue"
},
  "geometry": {"coordinates":[-0.9203090072,37.717918396],"type":"Point"}
}