{
  "type": "Feature",
  "properties": {
    "iso:country":"ES",
    "sg:address":"Av Flors (les), 10",
    "sg:city":"S. Joan Despi",
    "sg:orig_category":"Laboratorios Farmac\u00c9uticos",
    "sg:phone":"+34 934 80 67 00",
    "sg:postcode":"08...",
    "sg:province":"Barcelona",
    "sg:website":"www.reigjofre.com",
    "wof:name":"Laboratorio Reig Jofre S.a.",
    "wof:placetype":"venue"
},
  "geometry": {"coordinates":[2.0717830658,41.3659286499],"type":"Point"}
}