{
  "type": "Feature",
  "properties": {
    "iso:country":"ES",
    "sg:address":"Pg Florida, 10",
    "sg:city":"Santa Perpetua De Mogoda",
    "sg:orig_category":"Inmobiliaria (agencias)",
    "sg:phone":"+34 935 44 37 39",
    "sg:postcode":"08130",
    "sg:province":"Barcelona",
    "wof:name":"Fincas Santa Perpetua S.c.p.",
    "wof:placetype":"venue"
},
  "geometry": {"coordinates":[2.1844100952,41.531879425],"type":"Point"}
}