{
  "type": "Feature",
  "properties": {
    "addr:full":"Pase Playa (la), S/n Alcala De Los Gazules C\u00e1diz 11180",
    "addr:housenumber":"s",
    "addr:postcode":"11180",
    "addr:street":"/ N",
    "iso:country":"ES",
    "sg:address":"Pase Playa (la), S/n",
    "sg:city":"Alcala De Los Gazules",
    "sg:orig_category":"Comercio De Piezas De Recambio Y De Accesorios De Veh\u00cdculos, Veh\u00cdculos Industriales",
    "sg:phone":"+34 956 42 00 33",
    "sg:postcode":"11180",
    "sg:province":"C\u00e1diz",
    "wof:name":"Valades Sanchez Juan",
    "wof:placetype":"venue"
},
  "geometry": {"coordinates":[-5.723033905,36.4609298706],"type":"Point"}
}