{
  "type": "Feature",
  "properties": {
    "iso:country":"ES",
    "sg:address":"Pl. San J. Cadena, 2",
    "sg:city":"Iru\u00f1a",
    "sg:orig_category":"Peluqueros: De Se\u00d1oras",
    "sg:phone":"+34 948 27 33 55",
    "sg:postcode":"31008",
    "sg:province":"Navarra",
    "wof:name":"Solano Sebastian Carolina",
    "wof:placetype":"venue"
},
  "geometry": {"coordinates":[-1.6571689844,42.8113250732],"type":"Point"}
}