{
  "type": "Feature",
  "properties": {
    "addr:full":"Calle de Maria De Molina, 22 Valladolid Valladolid 47001",
    "addr:housenumber":"22",
    "addr:postcode":"47001",
    "addr:street":"Calle De Maria De Molina",
    "iso:country":"ES",
    "sg:address":"Calle de Maria De Molina, 22",
    "sg:city":"Valladolid",
    "sg:orig_category":"Monedas, Medallas",
    "sg:phone":"+34 983 34 09 30",
    "sg:postcode":"47001",
    "sg:province":"Valladolid",
    "wof:name":"Moreda Blanco Juan Antonio",
    "wof:placetype":"venue"
},
  "geometry": {"coordinates":[-4.7304420471,41.6493225098],"type":"Point"}
}