{
  "type": "Feature",
  "properties": {
    "iso:country":"ES",
    "sg:address":"Ctra. Jerez-rota, Km. 0005,0",
    "sg:city":"Menesteo",
    "sg:orig_category":"Sindicatos De Trabajadores",
    "sg:phone":"+34 956 54 91 16",
    "sg:postcode":"11500",
    "sg:province":"C\u00e1diz",
    "wof:name":"Federacion De Servicios Publicos De Ugt",
    "wof:placetype":"venue"
},
  "geometry": {"coordinates":[-6.2197542191,36.6056632996],"type":"Point"}
}