{
  "type": "Feature",
  "properties": {
    "iso:country":"ES",
    "sg:address":"Carrer de Sant Elies, 16",
    "sg:city":"Barcelona",
    "sg:orig_category":"Relojer\u00cda (al Por Menor, Reparaci\u00d3n)",
    "sg:phone":"+34 932 00 87 78",
    "sg:postcode":"08006",
    "sg:province":"Barcelona",
    "wof:name":"Franco Cayuela Antonio",
    "wof:placetype":"venue"
},
  "geometry": {"coordinates":[2.1446330547,41.4014472961],"type":"Point"}
}