{
  "type": "Feature",
  "properties": {
    "addr:full":"Plaz Constitucion (la), 6 Cambil Ja\u00e9n 23120",
    "addr:housenumber":"6",
    "addr:postcode":"23120",
    "addr:street":"Constitucion La",
    "iso:country":"ES",
    "sg:address":"Plaz Constitucion (la), 6",
    "sg:city":"Cambil",
    "sg:orig_category":"Cajas Para Embalar",
    "sg:phone":"+34 953 30 00 77",
    "sg:postcode":"23120",
    "sg:province":"Ja\u00e9n",
    "wof:name":"Caja Rural De Jaen",
    "wof:placetype":"venue"
},
  "geometry": {"coordinates":[-3.564399004,37.6802139282],"type":"Point"}
}