{
  "type": "Feature",
  "properties": {
    "iso:country":"ES",
    "sg:address":"Av Catalunya, 4",
    "sg:city":"Flix",
    "sg:orig_category":"Molduras, Junquillos, Listones Y Molduras Perforadas",
    "sg:phone":"+34 977 41 10 16",
    "sg:postcode":"43750",
    "sg:province":"Tarragona",
    "wof:name":"Loba Peralt Tomas Lluis",
    "wof:placetype":"venue"
},
  "geometry": {"coordinates":[0.5506160259,41.2308425903],"type":"Point"}
}