{
  "type": "Feature",
  "properties": {
    "iso:country":"ES",
    "sg:address":"Calle de Ramon Y Cajal, 6",
    "sg:city":"Donostia-san Sebastian",
    "sg:orig_category":"Art\u00cdculos De Decoraci\u00d3n",
    "sg:phone":"+34 943 32 60 07",
    "sg:postcode":"20002",
    "sg:province":"Guip\u00f9zcoa",
    "wof:name":"Rodriguez Diez Ignacio",
    "wof:placetype":"venue"
},
  "geometry": {"coordinates":[-1.9759119749,43.324344635],"type":"Point"}
}