{
  "type": "Feature",
  "properties": {
    "iso:country":"ES",
    "sg:address":"B. Al Puerto, S/n",
    "sg:city":"Lastres",
    "sg:orig_category":"Organizaciones Internacionales",
    "sg:phone":"+34 985 85 05 11",
    "sg:postcode":"33330",
    "sg:province":"Asturias",
    "wof:name":"Cruz Roja Espa\u00d1ola",
    "wof:placetype":"venue"
},
  "geometry": {"coordinates":[-5.2697310448,43.5140571594],"type":"Point"}
}