{
  "type": "Feature",
  "properties": {
    "addr:full":"Calle de Potosi, 43 Caceres C\u00e1ceres 10005",
    "addr:housenumber":"43",
    "addr:postcode":"10005",
    "addr:street":"Calle De Potosi;Ca\u0301Ceres",
    "iso:country":"ES",
    "sg:address":"Calle de Potosi, 43",
    "sg:city":"Caceres",
    "sg:orig_category":"Arquitectos",
    "sg:phone":"+34 927 23 44 03",
    "sg:postcode":"10005",
    "sg:province":"C\u00e1ceres",
    "wof:name":"Etayo Sanchez Elena",
    "wof:placetype":"venue"
},
  "geometry": {"coordinates":[-6.3782258034,39.453792572],"type":"Point"}
}