{
  "type": "Feature",
  "properties": {
    "iso:country":"ES",
    "sg:address":"Av Sarria, 6",
    "sg:city":"Barcelona",
    "sg:orig_category":"Aparcamientos (infraestructuras, Accesorios)",
    "sg:phone":"+34 933 21 68 38",
    "sg:postcode":"08029",
    "sg:province":"Barcelona",
    "wof:name":"Fornes Fiol Joaquim",
    "wof:placetype":"venue"
},
  "geometry": {"coordinates":[2.1466910839,41.3901596069],"type":"Point"}
}