{
  "type": "Feature",
  "properties": {
    "iso:country":"ES",
    "sg:address":"Calle de Clara Campoamor, 3",
    "sg:city":"Gijon",
    "sg:orig_category":"Maquinaria Para Industrias Diversas",
    "sg:phone":"+34 985 14 02 05",
    "sg:postcode":"33210",
    "sg:province":"Asturias",
    "wof:name":"Cristalerias Cardin S.l",
    "wof:placetype":"venue"
},
  "geometry": {"coordinates":[-5.6693120003,43.5257225037],"type":"Point"}
}