{
  "type": "Feature",
  "properties": {
    "iso:country":"ES",
    "sg:address":"Carrer de Calaceit, 8",
    "sg:city":"Viladecans",
    "sg:orig_category":"Cl\u00cdnicas Dentales",
    "sg:phone":"+34 936 58 73 03",
    "sg:postcode":"08840",
    "sg:province":"Barcelona",
    "wof:name":"Densana S.l.",
    "wof:placetype":"venue"
},
  "geometry": {"coordinates":[2.0191149712,41.3212127686],"type":"Point"}
}