{
  "type": "Feature",
  "properties": {
    "iso:country":"ES",
    "sg:address":"Calle de Princesa, 16",
    "sg:city":"Madrid",
    "sg:orig_category":"Psic\u00d3logos",
    "sg:phone":"+34 915 42 91 81",
    "sg:postcode":"28008",
    "sg:province":"Madrid",
    "wof:name":"Aceves Mellado Octavio Fernando",
    "wof:placetype":"venue"
},
  "geometry": {"coordinates":[-3.713167429,40.4263191223],"type":"Point"}
}