{
  "type": "Feature",
  "properties": {
    "iso:country":"ES",
    "sg:address":"Plaz Espa\u00d1a, 4",
    "sg:city":"Valderrobres",
    "sg:orig_category":"Pescader\u00cdas (al Por Menor)",
    "sg:phone":"+34 978 85 00 64",
    "sg:postcode":"44580",
    "sg:province":"Teruel",
    "wof:name":"Gamundi Albesa Jose",
    "wof:placetype":"venue"
},
  "geometry": {"coordinates":[0.1307796985,40.8575592041],"type":"Point"}
}