{
  "type": "Feature",
  "properties": {
    "iso:country":"ES",
    "sg:address":"Pla\u00c7 Anselm Clave, 4",
    "sg:city":"Igualada",
    "sg:orig_category":"Molduras, Junquillos, Listones Y Molduras Perforadas",
    "sg:phone":"+34 938 03 54 61",
    "sg:postcode":"08700",
    "sg:province":"Barcelona",
    "wof:name":"Vila Pujols Manel",
    "wof:placetype":"venue"
},
  "geometry": {"coordinates":[1.6199610233,41.5837516785],"type":"Point"}
}