{
  "type": "Feature",
  "properties": {
    "iso:country":"ES",
    "sg:address":"Pol Ind Plasencia, 41",
    "sg:city":"Plasencia",
    "sg:orig_category":"Empresas De Desmonte",
    "sg:phone":"+34 927 42 58 80",
    "sg:postcode":"10600",
    "sg:province":"C\u00e1ceres",
    "wof:name":"Excavaciones Y Desmontes Placentinos S.a.l.",
    "wof:placetype":"venue"
},
  "geometry": {"coordinates":[-6.0985279083,40.0253601074],"type":"Point"}
}