{
  "type": "Feature",
  "properties": {
    "iso:country":"ES",
    "sg:address":"Avda Eufemiano Jurado, S/n",
    "sg:city":"Palmas De Gran Canaria",
    "sg:orig_category":"Electricidad: Instaladores",
    "sg:phone":"+34 928 31 31 60",
    "sg:postcode":"35001",
    "sg:province":"Las Palmas",
    "wof:name":"Lasso Dorta Instalaciones Electricas S.l.",
    "wof:placetype":"venue"
},
  "geometry": {"coordinates":[-15.4172592163,28.0962257385],"type":"Point"}
}