{
  "type": "Feature",
  "properties": {
    "iso:country":"ES",
    "sg:address":"Rua Maria, 177",
    "sg:city":"Ferrol",
    "sg:orig_category":"Empresas De Carpinter\u00cda De Madera",
    "sg:phone":"+34 981 35 10 88",
    "sg:postcode":"15401",
    "sg:province":"La Coru\u00f1a",
    "wof:name":"Parquet Albanese S.l.",
    "wof:placetype":"venue"
},
  "geometry": {"coordinates":[-8.2386217117,43.4822998047],"type":"Point"}
}