{
  "type": "Feature",
  "properties": {
    "addr:full":"Calle de Ermodo Kalea, 27 Durango Vizcaya 48200",
    "addr:housenumber":"27",
    "addr:postcode":"48200",
    "addr:street":"Calle De Ermodo Kalea",
    "iso:country":"ES",
    "sg:address":"Calle de Ermodo Kalea, 27",
    "sg:city":"Durango",
    "sg:orig_category":"Zapatos (al Por Menor)",
    "sg:phone":"+34 946 81 94 38",
    "sg:postcode":"48200",
    "sg:province":"Vizcaya",
    "wof:name":"Gallastegui Martinez Maria",
    "wof:placetype":"venue"
},
  "geometry": {"coordinates":[-2.6329948902,43.1708259583],"type":"Point"}
}