{
  "type": "Feature",
  "properties": {
    "addr:full":"Pla\u00c7 Llaurador, 15 Villarreal Castell\u00f3n 12540",
    "addr:housenumber":"15",
    "addr:postcode":"12540",
    "addr:street":"Llaurador",
    "iso:country":"ES",
    "sg:address":"Pla\u00c7 Llaurador, 15",
    "sg:city":"Villarreal",
    "sg:orig_category":"Electricidad Veh\u00cdculo",
    "sg:phone":"+34 964 52 13 26",
    "sg:postcode":"12540",
    "sg:province":"Castell\u00f3n",
    "wof:name":"Quintana Gozalbo Miguel Angel",
    "wof:placetype":"venue"
},
  "geometry": {"coordinates":[-0.0952939987,39.9453048706],"type":"Point"}
}