{
  "type": "Feature",
  "properties": {
    "addr:full":"Avda Moncayo, S/n S. Martin Virgen Moncayo Zaragoza 50584",
    "addr:housenumber":"s",
    "addr:postcode":"50584",
    "addr:street":"Avda Moncayo;/ N S. Martin;Moncayo",
    "iso:country":"ES",
    "sg:address":"Avda Moncayo, S/n",
    "sg:city":"S. Martin Virgen Moncayo",
    "sg:orig_category":"Venta, Instalaci\u00d3n De Cocinas",
    "sg:phone":"+34 976 19 21 26",
    "sg:postcode":"50584",
    "sg:province":"Zaragoza",
    "wof:name":"Calvo Flores Ricardo",
    "wof:placetype":"venue"
},
  "geometry": {"coordinates":[-1.7928249836,41.835811615],"type":"Point"}
}