{
  "type": "Feature",
  "properties": {
    "addr:full":"Avda Rey Don Jaime, 74 Castellon Castell\u00f3n 12001",
    "addr:housenumber":"74",
    "addr:postcode":"12001",
    "addr:street":"Avda Rey Don Jaime",
    "iso:country":"ES",
    "sg:address":"Avda Rey Don Jaime, 74",
    "sg:city":"Castellon",
    "sg:orig_category":"Asesor\u00cdas En Comunicaci\u00d3n",
    "sg:phone":"+34 964 34 02 52",
    "sg:postcode":"12001",
    "sg:province":"Castell\u00f3n",
    "sg:website":"www.garbellco.com",
    "wof:name":"Garbell Comunicacio S.l.",
    "wof:placetype":"venue"
},
  "geometry": {"coordinates":[-0.0398387983,39.9870452881],"type":"Point"}
}