{
  "type": "Feature",
  "properties": {
    "addr:full":"Proc R Dguez M, 10 Niebla Huelva 21840",
    "addr:housenumber":"10",
    "addr:postcode":"21840",
    "addr:street":"R Dguez M",
    "iso:country":"ES",
    "sg:address":"Proc R Dguez M, 10",
    "sg:city":"Niebla",
    "sg:orig_category":"Caf\u00c9s, Bares, Cervecer\u00cdas",
    "sg:phone":"+34 959 36 21 02",
    "sg:postcode":"21840",
    "sg:province":"Huelva",
    "wof:name":"Cafeteria Pub Vulcano Uno S.l.",
    "wof:placetype":"venue"
},
  "geometry": {"coordinates":[-6.6775889397,37.3641014099],"type":"Point"}
}