{
  "type": "Feature",
  "properties": {
    "iso:country":"ES",
    "sg:address":"Calle de Rio Ardoz, 30",
    "sg:city":"Torrejon Ardoz",
    "sg:orig_category":"Fabricaci\u00d3n, Venta, Instalaci\u00d3n De R\u00d3tulos, De R\u00d3tulos Luminosos",
    "sg:phone":"+34 916 77 70 17",
    "sg:postcode":"28850",
    "sg:province":"Madrid",
    "wof:name":"Ineled Electronica S.l.",
    "wof:placetype":"venue"
},
  "geometry": {"coordinates":[-3.4692900181,40.4512748718],"type":"Point"}
}