{
  "type": "Feature",
  "properties": {
    "iso:country":"ES",
    "sg:address":"Avda Constitucion, 11",
    "sg:city":"Bollullos Par Condado",
    "sg:orig_category":"Electricidad: Instaladores",
    "sg:phone":"+34 959 40 85 00",
    "sg:postcode":"21710",
    "sg:province":"Huelva",
    "wof:name":"Iglesias Rosado Sara",
    "wof:placetype":"venue"
},
  "geometry": {"coordinates":[-6.5372772217,37.3394927979],"type":"Point"}
}