{
  "type": "Feature",
  "properties": {
    "addr:full":"Carrer de Sant Agusti (de), 8 Tarragona Tarragona 43003",
    "addr:postcode":"43003",
    "addr:street":"Carrer De Sant Agusti De 8",
    "iso:country":"ES",
    "sg:address":"Carrer de Sant Agusti (de), 8",
    "sg:city":"Tarragona",
    "sg:orig_category":"Perfumer\u00cda (al Por Menor)",
    "sg:phone":"+34 977 23 79 28",
    "sg:postcode":"43003",
    "sg:province":"Tarragona",
    "wof:name":"Fernan's S. A.",
    "wof:placetype":"venue"
},
  "geometry": {"coordinates":[1.2548520565,41.1152534485],"type":"Point"}
}