{
  "type": "Feature",
  "properties": {
    "iso:country":"ES",
    "sg:address":"Calle de Real, 150",
    "sg:city":"Castilleja Cuesta",
    "sg:orig_category":"M\u00c9dicos: Estomatolog\u00cda",
    "sg:phone":"+34 954 16 31 64",
    "sg:postcode":"41950",
    "sg:province":"Sevilla",
    "wof:name":"Mata Reche Rafael",
    "wof:placetype":"venue"
},
  "geometry": {"coordinates":[-6.057820797,37.3853797913],"type":"Point"}
}