{
  "type": "Feature",
  "properties": {
    "addr:full":"Pol Ind Can Massaguer, 40 Sta. Agnes Malanyanes Barcelona 08430",
    "addr:housenumber":"40",
    "addr:postcode":"08430",
    "addr:street":"Ind;Massaguer",
    "iso:country":"ES",
    "sg:address":"Pol Ind Can Massaguer, 40",
    "sg:city":"Sta. Agnes Malanyanes",
    "sg:orig_category":"Fabricaci\u00d3n De Su\u00c9ters Y Chalecos De Punto",
    "sg:phone":"+34 938 42 31 48",
    "sg:postcode":"08430",
    "sg:province":"Barcelona",
    "wof:name":"Noeco S.a.",
    "wof:placetype":"venue"
},
  "geometry": {"coordinates":[2.3250501156,41.5845298767],"type":"Point"}
}