{
  "type": "Feature",
  "properties": {
    "iso:country":"ES",
    "sg:address":"Calle de Doctor Aquilino Hurle, 4",
    "sg:city":"Gijon",
    "sg:orig_category":"Peluqueros: De Se\u00d1oras",
    "sg:phone":"+34 985 33 32 82",
    "sg:postcode":"33203",
    "sg:province":"Asturias",
    "wof:name":"Martinez Menendez Magdalena",
    "wof:placetype":"venue"
},
  "geometry": {"coordinates":[-5.6492791176,43.5372009277],"type":"Point"}
}