{
  "type": "Feature",
  "properties": {
    "iso:country":"ES",
    "sg:address":"Ctra Granada, 80",
    "sg:city":"Purullena",
    "sg:orig_category":"Museos",
    "sg:phone":"+34 958 69 01 81",
    "sg:postcode":"18519",
    "sg:province":"Granada",
    "wof:name":"Requena Martinez Francisco Carmelo",
    "wof:placetype":"venue"
},
  "geometry": {"coordinates":[-3.1853890419,37.3167686462],"type":"Point"}
}