{
  "type": "Feature",
  "properties": {
    "addr:full":"Carrer de Rogent, 19 Barcelona Barcelona 08026",
    "addr:housenumber":"19",
    "addr:postcode":"08026",
    "addr:street":"Carrer De Rogent",
    "iso:country":"ES",
    "sg:address":"Carrer de Rogent, 19",
    "sg:city":"Barcelona",
    "sg:orig_category":"Ropa Para Se\u00d1oras (al Por Menor)",
    "sg:phone":"+34 932 65 47 05",
    "sg:postcode":"08026",
    "sg:province":"Barcelona",
    "wof:name":"Carmen Xxi S.l.",
    "wof:placetype":"venue"
},
  "geometry": {"coordinates":[2.1854178905,41.4088439941],"type":"Point"}
}