{
  "type": "Feature",
  "properties": {
    "iso:country":"ES",
    "sg:address":"Carrer de Montmany, 35",
    "sg:city":"Barcelona",
    "sg:orig_category":"Ense\u00d1anza: Profesiones Art\u00cdsticas",
    "sg:phone":"+34 932 19 55 39",
    "sg:postcode":"08012",
    "sg:province":"Barcelona",
    "wof:name":"Ago2 Fotografia I Serveis S.l.",
    "wof:placetype":"venue"
},
  "geometry": {"coordinates":[2.159604311,41.4047241211],"type":"Point"}
}