{
  "type": "Feature",
  "properties": {
    "addr:full":"Calle de Major Sant Agusti, 67 Alzira Valencia 46600",
    "addr:housenumber":"67",
    "addr:postcode":"46600",
    "addr:street":"Calle De Major;Agusti",
    "iso:country":"ES",
    "sg:address":"Calle de Major Sant Agusti, 67",
    "sg:city":"Alzira",
    "sg:orig_category":"Molduras, Junquillos, Listones Y Molduras Perforadas",
    "sg:phone":"+34 962 40 56 19",
    "sg:postcode":"46600",
    "sg:province":"Valencia",
    "wof:name":"Eurotel Sur S L",
    "wof:placetype":"venue"
},
  "geometry": {"coordinates":[-0.4367370009,39.1481170654],"type":"Point"}
}