{
  "type": "Feature",
  "properties": {
    "addr:full":"Rua Eidos, 9 Redondela Pontevedra 36800",
    "addr:housenumber":"9",
    "addr:postcode":"36800",
    "addr:street":"Rua Eidos",
    "iso:country":"ES",
    "sg:address":"Rua Eidos, 9",
    "sg:city":"Redondela",
    "sg:orig_category":"Contenedores (mercanc\u00cdas)",
    "sg:phone":"+34 986 40 00 48",
    "sg:postcode":"36800",
    "sg:province":"Pontevedra",
    "wof:name":"Miguelez Miguelez Manuel",
    "wof:placetype":"venue"
},
  "geometry": {"coordinates":[-8.6058092117,42.2839584351],"type":"Point"}
}