{
  "type": "Feature",
  "properties": {
    "iso:country":"ES",
    "sg:address":"Calle de German Perez Carrasco, 48",
    "sg:city":"Madrid",
    "sg:orig_category":"Quincaller\u00cda (al Por Menor)",
    "sg:phone":"+34 913 68 43 76",
    "sg:postcode":"28027",
    "sg:province":"Madrid",
    "wof:name":"Pascual Garcia Juan Antonio",
    "wof:placetype":"venue"
},
  "geometry": {"coordinates":[-3.6437504292,40.436126709],"type":"Point"}
}