{
  "type": "Feature",
  "properties": {
    "iso:country":"ES",
    "sg:address":"Calle de Virrey Poveda, 16",
    "sg:city":"Petrer",
    "sg:orig_category":"Caf\u00c9s, Bares, Cervecer\u00cdas",
    "sg:phone":"+34 966 95 03 26",
    "sg:postcode":"03610",
    "sg:province":"Alicante",
    "wof:name":"Cuesta Rodriguez Fracisco Jose",
    "wof:placetype":"venue"
},
  "geometry": {"coordinates":[-0.7768880129,38.4820327759],"type":"Point"}
}