{
  "type": "Feature",
  "properties": {
    "addr:full":"Rosalia De Castro, 1 O Temple La Coru\u00f1a 15679",
    "addr:housenumber":"1 o",
    "addr:postcode":"15679",
    "addr:street":"Rosalia De Castro;La Corun\u0303A",
    "iso:country":"ES",
    "sg:address":"Rosalia De Castro, 1",
    "sg:city":"O Temple",
    "sg:orig_category":"Estudios, Instalaci\u00d3n De Climatizaci\u00d3n",
    "sg:phone":"+34 981 66 18 42",
    "sg:postcode":"15679",
    "sg:province":"La Coru\u00f1a",
    "wof:name":"Climatizacion Y Servicios S.coop.",
    "wof:placetype":"venue"
},
  "geometry": {"coordinates":[-8.3562135696,43.3193054199],"type":"Point"}
}