{
  "type": "Feature",
  "properties": {
    "addr:full":"Plaz Ayuntamiento (del), S/n Villalba Alta Teruel 44161",
    "addr:housenumber":"/ n",
    "addr:postcode":"44161",
    "addr:street":"S",
    "iso:country":"ES",
    "sg:address":"Plaz Ayuntamiento (del), S/n",
    "sg:city":"Villalba Alta",
    "sg:orig_category":"Ense\u00d1anza, Formaci\u00d3n Profesional: Aprendizaje",
    "sg:phone":"+34 978 77 52 36",
    "sg:postcode":"44161",
    "sg:province":"Teruel",
    "wof:name":"Ayuntamiento De Villalba Alta",
    "wof:placetype":"venue"
},
  "geometry": {"coordinates":[-1.1069096327,40.3441085815],"type":"Point"}
}