{
  "type": "Feature",
  "properties": {
    "iso:country":"ES",
    "sg:address":"Calle de Escosura, 19",
    "sg:city":"Madrid",
    "sg:orig_category":"Laboratorios Y Cl\u00cdnicas Veterinarias",
    "sg:phone":"+34 914 47 69 52",
    "sg:postcode":"28015",
    "sg:province":"Madrid",
    "wof:name":"Nuevo Zoo.c.b",
    "wof:placetype":"venue"
},
  "geometry": {"coordinates":[-3.706818819,40.4356498718],"type":"Point"}
}