{
  "type": "Feature",
  "properties": {
    "addr:full":"Pase General Martinez Campos, 26 Madrid Madrid 28010",
    "addr:housenumber":"26",
    "addr:postcode":"madrid;28010",
    "iso:country":"ES",
    "sg:address":"Pase General Martinez Campos, 26",
    "sg:city":"Madrid",
    "sg:orig_category":"Ropa Para Se\u00d1oras (al Por Menor)",
    "sg:phone":"+34 913 10 74 07",
    "sg:postcode":"28010",
    "sg:province":"Madrid",
    "sg:website":"www.webkarisma.com",
    "wof:name":"Loferit C.b",
    "wof:placetype":"venue"
},
  "geometry": {"coordinates":[-3.694425106,40.4349746704],"type":"Point"}
}