{
  "type": "Feature",
  "properties": {
    "iso:country":"ES",
    "sg:address":"Calle de Huelva, 29",
    "sg:city":"Miravalle Los Montecillos",
    "sg:orig_category":"Bricolaje, Herramientas (al Por Menor)",
    "sg:phone":"+34 952 45 19 94",
    "sg:postcode":"29100",
    "sg:province":"M\u00e1laga",
    "wof:name":"Lucena Sanchez Jose",
    "wof:placetype":"venue"
},
  "geometry": {"coordinates":[-4.750248909,36.6516609192],"type":"Point"}
}