{
  "type": "Feature",
  "properties": {
    "addr:full":"Praz Pedra, 2 Vigo Pontevedra 36202",
    "addr:housenumber":"2",
    "addr:postcode":"36202",
    "addr:street":"Pedra",
    "iso:country":"ES",
    "sg:address":"Praz Pedra, 2",
    "sg:city":"Vigo",
    "sg:orig_category":"Mercer\u00cda, Lencer\u00cda (al Por Menor)",
    "sg:phone":"+34 986 43 72 69",
    "sg:postcode":"36202",
    "sg:province":"Pontevedra",
    "wof:name":"Perez Pombal Maria Josefa",
    "wof:placetype":"venue"
},
  "geometry": {"coordinates":[-8.7332239151,42.2212409973],"type":"Point"}
}