{
  "type": "Feature",
  "properties": {
    "iso:country":"ES",
    "sg:address":"Calle de Hurtado De Amezaga, 4",
    "sg:city":"Bilbao",
    "sg:orig_category":"Ropa De Hogar (al Por Menor)",
    "sg:phone":"+34 944 23 73 61",
    "sg:postcode":"48008",
    "sg:province":"Vizcaya",
    "wof:name":"Herur S.a.",
    "wof:placetype":"venue"
},
  "geometry": {"coordinates":[-2.9282610416,43.2607574463],"type":"Point"}
}