{
  "type": "Feature",
  "properties": {
    "iso:country":"ES",
    "sg:address":"Avda Pilar, 42",
    "sg:city":"Don Benito",
    "sg:orig_category":"Ropa Para Ni\u00d1os (al Por Menor)",
    "sg:phone":"+34 924 80 48 92",
    "sg:postcode":"06400",
    "sg:province":"Badajoz",
    "wof:name":"Gallego Garcia Jose Antonio",
    "wof:placetype":"venue"
},
  "geometry": {"coordinates":[-5.8733639717,38.9556503296],"type":"Point"}
}