{
  "type": "Feature",
  "properties": {
    "addr:full":"Calle de Q, 22 Mutiloabeiti Navarra 31192",
    "addr:housenumber":"22",
    "addr:postcode":"31192",
    "addr:street":"Calle De Q",
    "iso:country":"ES",
    "sg:address":"Calle de Q, 22",
    "sg:city":"Mutiloabeiti",
    "sg:orig_category":"Chapister\u00cda",
    "sg:phone":"+34 948 15 02 21",
    "sg:postcode":"31192",
    "sg:province":"Navarra",
    "wof:name":"Ordoqui Belza Jose Ignacio",
    "wof:placetype":"venue"
},
  "geometry": {"coordinates":[-1.6288169622,42.7861862183],"type":"Point"}
}