{
  "type": "Feature",
  "properties": {
    "iso:country":"ES",
    "sg:address":"Carrer de Pere Costa, 25",
    "sg:city":"Barcelona",
    "sg:orig_category":"Ense\u00d1anza: Profesiones Art\u00cdsticas",
    "sg:phone":"+34 934 35 91 96",
    "sg:postcode":"08024",
    "sg:province":"Barcelona",
    "wof:name":"Sayas Labrid Agustin",
    "wof:placetype":"venue"
},
  "geometry": {"coordinates":[2.168309927,41.413936615],"type":"Point"}
}