{
  "type": "Feature",
  "properties": {
    "iso:country":"ES",
    "sg:address":"Carr Marques De Caldes De Montbui, 81",
    "sg:city":"Girona",
    "sg:orig_category":"Dibujantes (diversos)",
    "sg:phone":"+34 972 21 50 13",
    "sg:postcode":"17003",
    "sg:province":"Girona",
    "wof:name":"Maquet 3 S.c",
    "wof:placetype":"venue"
},
  "geometry": {"coordinates":[2.8195168972,41.9688911438],"type":"Point"}
}