{
  "type": "Feature",
  "properties": {
    "addr:full":"Calle de Ancha, 4 Cadiz C\u00e1diz 11001",
    "addr:housenumber":"4",
    "addr:postcode":"11001",
    "addr:street":"Calle De Ancha",
    "iso:country":"ES",
    "sg:address":"Calle de Ancha, 4",
    "sg:city":"Cadiz",
    "sg:orig_category":"Juegos Y Juguetes (al Por Menor)",
    "sg:phone":"+34 956 22 39 53",
    "sg:postcode":"11001",
    "sg:province":"C\u00e1diz",
    "sg:website":"www.imaginarium.es",
    "wof:name":"Suma S.c.",
    "wof:placetype":"venue"
},
  "geometry": {"coordinates":[-6.2983088493,36.5343589783],"type":"Point"}
}