{
  "type": "Feature",
  "properties": {
    "addr:full":"Luga Carretera Madrid-valencia, Km. 0141,5 Cervera Del Llano Cuenca 16444",
    "addr:postcode":"16444",
    "addr:street":"Carretera Madrid-Valencia Km. 0141,5",
    "iso:country":"ES",
    "sg:address":"Luga Carretera Madrid-valencia, Km. 0141,5",
    "sg:city":"Cervera Del Llano",
    "sg:orig_category":"Distribuci\u00d3n De Petr\u00d3leo Y Derivados",
    "sg:phone":"+34 969 29 40 45",
    "sg:postcode":"16444",
    "sg:province":"Cuenca",
    "wof:name":"Santoyo Hermanos S. L.",
    "wof:placetype":"venue"
},
  "geometry": {"coordinates":[-2.4188089371,39.7832946777],"type":"Point"}
}