{
  "type": "Feature",
  "properties": {
    "iso:country":"ES",
    "sg:address":"Calle de Anuncibai, 19",
    "sg:city":"Llodio",
    "sg:orig_category":"Empresas De Desmonte",
    "sg:phone":"+34 946 72 41 58",
    "sg:postcode":"01400",
    "sg:province":"\u00c1lava",
    "wof:name":"Excavaciones Vitorica S.l.",
    "wof:placetype":"venue"
},
  "geometry": {"coordinates":[-2.9415163994,43.1423301697],"type":"Point"}
}