{
  "type": "Feature",
  "properties": {
    "addr:full":"Calle de Pablo Iglesias (de), 41 G\u00fcimar Santa Cruz De Tenerife 38500",
    "addr:housenumber":"41",
    "addr:postcode":"38500",
    "addr:street":"Calle De Pablo Iglesias De",
    "iso:country":"ES",
    "sg:address":"Calle de Pablo Iglesias (de), 41",
    "sg:city":"G\u00fcimar",
    "sg:orig_category":"Reposter\u00cdas",
    "sg:phone":"+34 922 51 30 45",
    "sg:postcode":"38500",
    "sg:province":"Santa Cruz De Tenerife",
    "wof:name":"Mostrador De Pan S.l.",
    "wof:placetype":"venue"
},
  "geometry": {"coordinates":[-16.4136390686,28.3153800964],"type":"Point"}
}