{
  "type": "Feature",
  "properties": {
    "addr:full":"Calle de Rio Ter (del), 2 Nogal Madrid 28110",
    "addr:housenumber":"2",
    "addr:postcode":"28110",
    "addr:street":"Calle De Rio Ter Del",
    "iso:country":"ES",
    "sg:address":"Calle de Rio Ter (del), 2",
    "sg:city":"Nogal",
    "sg:orig_category":"V\u00c1lvulas",
    "sg:phone":"+34 916 29 19 78",
    "sg:postcode":"28110",
    "sg:province":"Madrid",
    "wof:name":"Hoerbiger Iberica S.a.",
    "wof:placetype":"venue"
},
  "geometry": {"coordinates":[-3.4999940395,40.5979003906],"type":"Point"}
}