{
  "type": "Feature",
  "properties": {
    "iso:country":"ES",
    "sg:address":"Ctra Madrid N-iv, S/n",
    "sg:city":"Cordoba",
    "sg:orig_category":"Aguas (distribuci\u00d3n, Servicios)",
    "sg:phone":"+34 957 32 53 06",
    "sg:postcode":"14014",
    "sg:province":"C\u00f3rdoba",
    "wof:name":"Empresa Provincial De Aguas De Cordoba",
    "wof:placetype":"venue"
},
  "geometry": {"coordinates":[-4.6691141129,37.9341316223],"type":"Point"}
}