{
  "type": "Feature",
  "properties": {
    "addr:full":"Urbz La Magdalena (el Polvorin), 9 Sanfuentes Vizcaya 48500",
    "addr:housenumber":"9",
    "addr:postcode":"48500",
    "addr:street":"Polvorin",
    "iso:country":"ES",
    "sg:address":"Urbz La Magdalena (el Polvorin), 9",
    "sg:city":"Sanfuentes",
    "sg:orig_category":"Centros Empresariales",
    "sg:phone":"+34 946 36 21 64",
    "sg:postcode":"48500",
    "sg:province":"Vizcaya",
    "wof:name":"Nu\u00f1ez Pardo Lazaro",
    "wof:placetype":"venue"
},
  "geometry": {"coordinates":[-3.075783968,43.3152046204],"type":"Point"}
}