{
  "type": "Feature",
  "properties": {
    "iso:country":"ES",
    "sg:address":"Calle de San Jose, S/n",
    "sg:city":"Ubeda",
    "sg:orig_category":"Autob\u00das (explotaci\u00d3n Y Servicios De)",
    "sg:phone":"+34 953 75 00 26",
    "sg:postcode":"23400",
    "sg:province":"Ja\u00e9n",
    "wof:name":"Anonima Alsina Graells",
    "wof:placetype":"venue"
},
  "geometry": {"coordinates":[-3.3782172203,38.0127410889],"type":"Point"}
}