{
  "type": "Feature",
  "properties": {
    "iso:country":"ES",
    "sg:address":"Cavanas, 11",
    "sg:city":"Nerja",
    "sg:orig_category":"Complementos De Vestir (al Por Menor)",
    "sg:phone":"+34 952 52 62 19",
    "sg:postcode":"29780",
    "sg:province":"M\u00e1laga",
    "wof:name":"Urbano Cuart Miguel Ernesto",
    "wof:placetype":"venue"
},
  "geometry": {"coordinates":[-3.877779007,36.7450714111],"type":"Point"}
}