{
  "type": "Feature",
  "properties": {
    "iso:country":"ES",
    "sg:address":"Olaz-chipi, 3",
    "sg:city":"Huarte",
    "sg:orig_category":"Rectificaci\u00d3n, Mecanizado, Fresado",
    "sg:phone":"+34 948 33 13 22",
    "sg:postcode":"31620",
    "sg:province":"Navarra",
    "sg:website":"www.atondoa.com",
    "wof:name":"Talleres Atondoa S.l.",
    "wof:placetype":"venue"
},
  "geometry": {"coordinates":[-1.5996609926,42.8290290833],"type":"Point"}
}