{
  "type": "Feature",
  "properties": {
    "addr:full":"Dr. Gomez Lucena, 2 Coin M\u00e1laga 29100",
    "addr:housenumber":"2",
    "addr:postcode":"29100",
    "addr:street":"Coin Ma\u0301Laga",
    "iso:country":"ES",
    "sg:address":"Dr. Gomez Lucena, 2",
    "sg:city":"Coin",
    "sg:orig_category":"Porcelanas, Azulejos (fabricaci\u00d3n, Al Por Mayor)",
    "sg:phone":"+34 952 45 32 21",
    "sg:postcode":"29100",
    "sg:province":"M\u00e1laga",
    "wof:name":"Alcantara Vargas Antonia",
    "wof:placetype":"venue"
},
  "geometry": {"coordinates":[-4.7569956779,36.6617279053],"type":"Point"}
}