{
  "type": "Feature",
  "properties": {
    "addr:full":"Calle de Castor, 27 Alacant Alicante 03007",
    "addr:housenumber":"27",
    "addr:postcode":"03007",
    "addr:street":"Calle De Castor",
    "iso:country":"ES",
    "sg:address":"Calle de Castor, 27",
    "sg:city":"Alacant",
    "sg:orig_category":"Estudios, Instalaci\u00d3n De Climatizaci\u00d3n",
    "sg:phone":"+34 965 10 58 77",
    "sg:postcode":"03007",
    "sg:province":"Alicante",
    "wof:name":"Eurofrio Centeno S.l.",
    "wof:placetype":"venue"
},
  "geometry": {"coordinates":[-0.5139501095,38.3426208496],"type":"Point"}
}