{
  "type": "Feature",
  "properties": {
    "iso:country":"ES",
    "sg:address":"Congostras, 23",
    "sg:city":"Congostras",
    "sg:orig_category":"Asociaciones, Organismos Culturales Y Socioeducativos",
    "sg:phone":"+34 981 36 83 97",
    "sg:postcode":"15597",
    "sg:province":"A Coru\u00f1a",
    "wof:name":"Sociedad Cultural Y Recreativa A Pombi\u00f1a",
    "wof:placetype":"venue"
},
  "geometry": {"coordinates":[-8.163939476,43.5220413208],"type":"Point"}
}