{
  "type": "Feature",
  "properties": {
    "iso:country":"ES",
    "sg:address":"Poble Espanyol, S/n",
    "sg:city":"Barcelona",
    "sg:orig_category":"Cer\u00c1mica Art\u00cdstica Y Decorativa",
    "sg:phone":"+34 934 25 53 91",
    "sg:postcode":"08038",
    "sg:province":"Barcelona",
    "wof:name":"Gabarro Roig Xavier",
    "wof:placetype":"venue"
},
  "geometry": {"coordinates":[2.1470000744,41.3689994812],"type":"Point"}
}