{
  "type": "Feature",
  "properties": {
    "addr:full":"Calle de Carnicerias, 11 Talavera Reina Toledo 45600",
    "addr:housenumber":"11",
    "addr:postcode":"45600",
    "addr:street":"Calle De Carnicerias",
    "iso:country":"ES",
    "sg:address":"Calle de Carnicerias, 11",
    "sg:city":"Talavera Reina",
    "sg:orig_category":"Electrodom\u00c9sticos (al Por Menor)",
    "sg:phone":"+34 925 82 12 74",
    "sg:postcode":"45600",
    "sg:province":"Toledo",
    "wof:name":"Gutierrez Del Pozo Juan Carlos",
    "wof:placetype":"venue"
},
  "geometry": {"coordinates":[-4.8295750618,39.9598121643],"type":"Point"}
}