{
  "type": "Feature",
  "properties": {
    "addr:full":"Pase Autonomias (de Las), 4 Huesca Huesca 22004",
    "addr:postcode":"22004",
    "iso:country":"ES",
    "sg:address":"Pase Autonomias (de Las), 4",
    "sg:city":"Huesca",
    "sg:orig_category":"Centros P\u00dablicos De Formaci\u00d3n Profesional Y T\u00c9cnica",
    "sg:phone":"+34 974 24 13 35",
    "sg:postcode":"22004",
    "sg:province":"Huesca",
    "wof:name":"Colegio Oficial De Ingenieros Tecnicos Agricolas De Aragon",
    "wof:placetype":"venue"
},
  "geometry": {"coordinates":[-0.4177680016,42.1380386353],"type":"Point"}
}