{
  "type": "Feature",
  "properties": {
    "addr:full":"Avda Villajoyosa, 2 Alacant Alicante 03016",
    "addr:housenumber":"2",
    "addr:postcode":"03016",
    "addr:street":"Avda Villajoyosa",
    "iso:country":"ES",
    "sg:address":"Avda Villajoyosa, 2",
    "sg:city":"Alacant",
    "sg:orig_category":"Transportes Ferroviarios",
    "sg:phone":"+34 965 26 29 30",
    "sg:postcode":"03016",
    "sg:province":"Alicante",
    "sg:website":"www.fgv.es",
    "wof:name":"Ferrocarrils De La Generalitat Valenciana",
    "wof:placetype":"venue"
},
  "geometry": {"coordinates":[-0.4804739952,38.3440856934],"type":"Point"}
}