{
  "type": "Feature",
  "properties": {
    "iso:country":"ES",
    "sg:address":"Calle de Jose Del Hierro, 25",
    "sg:city":"Madrid",
    "sg:orig_category":"Farmacias",
    "sg:phone":"+34 913 67 26 78",
    "sg:postcode":"28027",
    "sg:province":"Madrid",
    "wof:name":"Luque Pe\u00f1a Maria Angustias",
    "wof:placetype":"venue"
},
  "geometry": {"coordinates":[-3.6453998089,40.4396286011],"type":"Point"}
}