{
  "type": "Feature",
  "properties": {
    "addr:full":"Av Fabregada, 3 Hospitalet Llobregat Barcelona 08907",
    "addr:housenumber":"3",
    "addr:postcode":"08907",
    "addr:street":"Av Fabregada",
    "iso:country":"ES",
    "sg:address":"Av Fabregada, 3",
    "sg:city":"Hospitalet Llobregat",
    "sg:orig_category":"Fabricaci\u00d3n De Sobres, Bolsas Y Fundas",
    "sg:phone":"+34 933 35 43 12",
    "sg:postcode":"08907",
    "sg:province":"Barcelona",
    "wof:name":"Cobopal Sl",
    "wof:placetype":"venue"
},
  "geometry": {"coordinates":[2.1103239059,41.3559761047],"type":"Point"}
}