{
  "type": "Feature",
  "properties": {
    "iso:country":"ES",
    "sg:address":"Calle de San Pablo, 14",
    "sg:city":"Burgos",
    "sg:orig_category":"Inform\u00c1tica: Material Y Suministros",
    "sg:phone":"+34 947 20 03 38",
    "sg:postcode":"09002",
    "sg:province":"Burgos",
    "wof:name":"Universitas Informatica S.l.",
    "wof:placetype":"venue"
},
  "geometry": {"coordinates":[-3.6991620064,42.3379096985],"type":"Point"}
}