{
  "type": "Feature",
  "properties": {
    "addr:full":"Ctra Badajoz Granada, Km. 0075,0 Zafra Badajoz 06300",
    "addr:postcode":"06300",
    "addr:street":"Ctra Badajoz Granada Km. 0075,0",
    "iso:country":"ES",
    "sg:address":"Ctra Badajoz Granada, Km. 0075,0",
    "sg:city":"Zafra",
    "sg:orig_category":"Fabricaci\u00d3n De Motores El\u00c9ctricos",
    "sg:phone":"+34 924 55 05 50",
    "sg:postcode":"06300",
    "sg:province":"Badajoz",
    "wof:name":"Deutz Diter S.a.",
    "wof:placetype":"venue"
},
  "geometry": {"coordinates":[-6.4118800163,38.4264526367],"type":"Point"}
}