{
  "type": "Feature",
  "properties": {
    "addr:full":"Calle de Arco Iris, 7 Moraleja Vino Zamora 49150",
    "addr:housenumber":"7",
    "addr:postcode":"49150",
    "addr:street":"Calle De Arco Iris;Zamora",
    "iso:country":"ES",
    "sg:address":"Calle de Arco Iris, 7",
    "sg:city":"Moraleja Vino",
    "sg:orig_category":"Asesor\u00cdas En Comunicaci\u00d3n",
    "sg:phone":"+34 980 57 12 21",
    "sg:postcode":"49150",
    "sg:province":"Zamora",
    "wof:name":"Alvarez Perez Felipe",
    "wof:placetype":"venue"
},
  "geometry": {"coordinates":[-5.7462787628,41.5033454895],"type":"Point"}
}