{
  "type": "Feature",
  "properties": {
    "addr:full":"Carrer de Enten\u00c7a, 80 Barcelona Barcelona 08015",
    "addr:housenumber":"80",
    "addr:postcode":"08015",
    "addr:street":"Carrer De Entenc\u0327A",
    "iso:country":"ES",
    "sg:address":"Carrer de Enten\u00c7a, 80",
    "sg:city":"Barcelona",
    "sg:orig_category":"Papeler\u00cdas, Librer\u00cdas",
    "sg:phone":"+34 934 23 69 99",
    "sg:postcode":"08015",
    "sg:province":"Barcelona",
    "wof:name":"La Imprenta Ecologica I El Full Natural S.l.",
    "wof:placetype":"venue"
},
  "geometry": {"coordinates":[2.1511309147,41.37940979],"type":"Point"}
}