{
  "type": "Feature",
  "properties": {
    "iso:country":"ES",
    "sg:address":"Rua Aureliano Ferreiro, 53",
    "sg:city":"Maceda",
    "sg:orig_category":"Florister\u00cdas",
    "sg:phone":"+34 988 46 33 27",
    "sg:postcode":"32700",
    "sg:province":"Ourense",
    "wof:name":"Gonzalez Gonzalez Maria Fina",
    "wof:placetype":"venue"
},
  "geometry": {"coordinates":[-7.6516032219,42.2659225464],"type":"Point"}
}