{
  "type": "Feature",
  "properties": {
    "addr:full":"Calle de Pisuerga, 1 Palencia Palencia 34003",
    "addr:housenumber":"1",
    "addr:postcode":"34003",
    "addr:street":"Calle De Pisuerga",
    "iso:country":"ES",
    "sg:address":"Calle de Pisuerga, 1",
    "sg:city":"Palencia",
    "sg:orig_category":"Material Y Herramientas Agr\u00cdcolas",
    "sg:phone":"+34 979 71 01 33",
    "sg:postcode":"34003",
    "sg:province":"Palencia",
    "wof:name":"Mota Recambios Y Maquinaria Agricola S.l.",
    "wof:placetype":"venue"
},
  "geometry": {"coordinates":[-4.5189929008,42.0148239136],"type":"Point"}
}