{
  "type": "Feature",
  "properties": {
    "addr:full":"Calle de Jesus Del Gran Poder, 37 Avila \u00c1vila 05003",
    "addr:housenumber":"37",
    "addr:postcode":"05003",
    "addr:street":"Calle De Jesus Del Gran Poder;A\u0301Vila",
    "iso:country":"ES",
    "sg:address":"Calle de Jesus Del Gran Poder, 37",
    "sg:city":"Avila",
    "sg:orig_category":"Frutas, Legumbres Frescas Y Tempranas (al Por Menor)",
    "sg:phone":"+34 920 25 04 49",
    "sg:postcode":"05003",
    "sg:province":"\u00c1vila",
    "wof:name":"Jimenez Garcia Luis",
    "wof:placetype":"venue"
},
  "geometry": {"coordinates":[-4.693251133,40.6517295837],"type":"Point"}
}