{
  "type": "Feature",
  "properties": {
    "iso:country":"ES",
    "sg:address":"Carrer de Sant Iscle, 31",
    "sg:city":"Barcelona",
    "sg:orig_category":"Droguer\u00cdas (al Por Menor)",
    "sg:phone":"+34 934 07 01 28",
    "sg:postcode":"08031",
    "sg:province":"Barcelona",
    "wof:name":"Romero Las Heras Basilides",
    "wof:placetype":"venue"
},
  "geometry": {"coordinates":[2.1730639935,41.4317131042],"type":"Point"}
}