{
  "type": "Feature",
  "properties": {
    "iso:country":"ES",
    "sg:address":"Calle de Costa Rica, 24",
    "sg:city":"Madrid",
    "sg:orig_category":"Asesor\u00cda De Formaci\u00d3n Y Gesti\u00d3n De Personal",
    "sg:phone":"+34 913 59 06 68",
    "sg:postcode":"28016",
    "sg:province":"Madrid",
    "wof:name":"Epal Asesores S.l.",
    "wof:placetype":"venue"
},
  "geometry": {"coordinates":[-3.6730144024,40.4584388733],"type":"Point"}
}