{
  "type": "Feature",
  "properties": {
    "iso:country":"ES",
    "sg:address":"Ctra Valdeavero (de), 5",
    "sg:city":"Azuqueca Henares",
    "sg:orig_category":"Empresas De Carpinter\u00cda De Madera",
    "sg:phone":"+34 949 26 07 50",
    "sg:postcode":"19200",
    "sg:province":"Guadalajara",
    "wof:name":"Brico Decoracion Azuqueca S.l.",
    "wof:placetype":"venue"
},
  "geometry": {"coordinates":[-3.2655460835,40.5684623718],"type":"Point"}
}