{
  "type": "Feature",
  "properties": {
    "addr:full":"Calle de Macias Picavea, 4 Santander Cantabria 39003",
    "addr:housenumber":"4",
    "addr:postcode":"39003",
    "addr:street":"Calle De Macias Picavea",
    "iso:country":"ES",
    "sg:address":"Calle de Macias Picavea, 4",
    "sg:city":"Santander",
    "sg:orig_category":"Chapister\u00cda",
    "sg:phone":"+34 942 22 99 06",
    "sg:postcode":"39003",
    "sg:province":"Cantabria",
    "wof:name":"Bueno Perez Jose Luis",
    "wof:placetype":"venue"
},
  "geometry": {"coordinates":[-3.8021979332,43.4652290344],"type":"Point"}
}