{
  "type": "Feature",
  "properties": {
    "addr:full":"Pl Pius Xii, S/n Hospitalet Llobregat Barcelona 08902",
    "addr:housenumber":"s / n",
    "addr:postcode":"08902",
    "addr:street":"Pius Xii",
    "iso:country":"ES",
    "sg:address":"Pl Pius Xii, S/n",
    "sg:city":"Hospitalet Llobregat",
    "sg:orig_category":"Ense\u00d1anza Secundaria: Colegios Y Escuelas Privadas",
    "sg:phone":"+34 933 31 45 98",
    "sg:postcode":"08902",
    "sg:province":"Barcelona",
    "wof:name":"Centre De Telecomunicaciones De Catalunya",
    "wof:placetype":"venue"
},
  "geometry": {"coordinates":[2.1273701191,41.3652458191],"type":"Point"}
}