{
  "type": "Feature",
  "properties": {
    "iso:country":"ES",
    "sg:address":"Calle de Batalla Del Salado, 30",
    "sg:city":"Madrid",
    "sg:orig_category":"Aparcamientos (infraestructuras, Accesorios)",
    "sg:phone":"+34 915 39 30 35",
    "sg:postcode":"28045",
    "sg:province":"Madrid",
    "wof:name":"Ca\u00f1as Ca\u00f1as Angel",
    "wof:placetype":"venue"
},
  "geometry": {"coordinates":[-3.6962661743,40.400177002],"type":"Point"}
}