{
  "type": "Feature",
  "properties": {
    "addr:full":"Praz Galicia (de), 33 Sarria Lugo 27600",
    "addr:postcode":"27600",
    "iso:country":"ES",
    "sg:address":"Praz Galicia (de), 33",
    "sg:city":"Sarria",
    "sg:orig_category":"Imprenta",
    "sg:phone":"+34 982 53 50 41",
    "sg:postcode":"27600",
    "sg:province":"Lugo",
    "wof:name":"Lopez Rodriguez Carlos",
    "wof:placetype":"venue"
},
  "geometry": {"coordinates":[-7.4135627747,42.7805595398],"type":"Point"}
}