{
  "type": "Feature",
  "properties": {
    "iso:country":"ES",
    "sg:address":"Rua Joaquin Loriga, 4",
    "sg:city":"Vigo",
    "sg:orig_category":"Confiter\u00cdas, Chocolater\u00cdas (al Por Menor)",
    "sg:phone":"+34 986 43 41 70",
    "sg:postcode":"36203",
    "sg:province":"Pontevedra",
    "wof:name":"Novo Gonzalez Joaquin Angel",
    "wof:placetype":"venue"
},
  "geometry": {"coordinates":[-8.7215013504,42.2347335815],"type":"Point"}
}