{
  "type": "Feature",
  "properties": {
    "addr:full":"Ctra. Madrid, Km. 0221,0 Los Rabanos Soria 42191",
    "addr:postcode":"42191",
    "addr:street":"Ctra. Madrid Km. 0221,0 Los Rabanos",
    "iso:country":"ES",
    "sg:address":"Ctra. Madrid, Km. 0221,0",
    "sg:city":"Los Rabanos",
    "sg:orig_category":"Distribuci\u00d3n De Petr\u00d3leo Y Derivados",
    "sg:phone":"+34 975 22 99 46",
    "sg:postcode":"42191",
    "sg:province":"Soria",
    "sg:website":"www.cepsa.es",
    "wof:name":"Cedipsa Compa\u00d1ia Espa\u00d1ola Distribuidora De Petroleos S.a.",
    "wof:placetype":"venue"
},
  "geometry": {"coordinates":[-2.4215390682,41.6024513245],"type":"Point"}
}