{
  "type": "Feature",
  "properties": {
    "iso:country":"ES",
    "sg:address":"Calle de Ovalle, 10",
    "sg:city":"Salamanca",
    "sg:orig_category":"Material Y Suministros Para Peluquer\u00cda",
    "sg:phone":"+34 923 22 29 91",
    "sg:postcode":"37004",
    "sg:province":"Salamanca",
    "wof:name":"Ca\u00f1ibano Perez Francisco",
    "wof:placetype":"venue"
},
  "geometry": {"coordinates":[-5.6559319496,40.971496582],"type":"Point"}
}