{
  "type": "Feature",
  "properties": {
    "iso:country":"ES",
    "sg:address":"Av. Ciutat Lompoc, 192",
    "sg:city":"Inca",
    "sg:orig_category":"M\u00c9dicos: Estomatolog\u00cda",
    "sg:phone":"+34 971 50 41 69",
    "sg:postcode":"07300",
    "sg:province":"Islas Baleares",
    "wof:name":"Especialidades Odontologicas Inca S.l.",
    "wof:placetype":"venue"
},
  "geometry": {"coordinates":[2.9208989143,39.7179527283],"type":"Point"}
}