{
  "type": "Feature",
  "properties": {
    "iso:country":"ES",
    "sg:address":"C/ Estrella, De L', 11",
    "sg:city":"S. Antoni Portmany",
    "sg:orig_category":"Pizzer\u00cdas",
    "sg:phone":"+34 971 34 85 78",
    "sg:postcode":"07820",
    "sg:province":"Islas Baleares",
    "wof:name":"Antonio Lattansi Roberto",
    "wof:placetype":"venue"
},
  "geometry": {"coordinates":[1.3004798889,38.9816703796],"type":"Point"}
}