{
  "type": "Feature",
  "properties": {
    "iso:country":"ES",
    "sg:address":"Calle de San Andres, 23",
    "sg:city":"Almoradi",
    "sg:orig_category":"Negocio De Enlosados, Soler\u00cdas",
    "sg:phone":"+34 966 78 12 33",
    "sg:postcode":"03160",
    "sg:province":"Alicante",
    "wof:name":"Quiles Perez Herminia",
    "wof:placetype":"venue"
},
  "geometry": {"coordinates":[-0.7895140052,38.1099128723],"type":"Point"}
}