{
  "type": "Feature",
  "properties": {
    "addr:full":"Av Reis Catolics, 9 Olot Girona 17800",
    "addr:housenumber":"9",
    "addr:postcode":"17800",
    "addr:street":"Av Reis Catolics",
    "iso:country":"ES",
    "sg:address":"Av Reis Catolics, 9",
    "sg:city":"Olot",
    "sg:orig_category":"Droguer\u00cdas (al Por Menor)",
    "sg:phone":"+34 972 27 42 85",
    "sg:postcode":"17800",
    "sg:province":"Girona",
    "sg:website":"www.schlecker.com",
    "wof:name":"Schlecker S.a.",
    "wof:placetype":"venue"
},
  "geometry": {"coordinates":[2.4825980663,42.1810874939],"type":"Point"}
}