{
  "type": "Feature",
  "properties": {
    "addr:full":"Via Augusta, 59 Barcelona Barcelona 08006",
    "addr:housenumber":"59",
    "addr:postcode":"08006",
    "addr:street":"Via Augusta",
    "iso:country":"ES",
    "sg:address":"Via Augusta, 59",
    "sg:city":"Barcelona",
    "sg:orig_category":"Conservas De Legumbres (fabricaci\u00d3n, Al Por Mayor)",
    "sg:phone":"+34 932 37 39 38",
    "sg:postcode":"08006",
    "sg:province":"Barcelona",
    "sg:website":"www.helios.es",
    "wof:name":"Dulces Y Conservas Helios S. A.",
    "wof:placetype":"venue"
},
  "geometry": {"coordinates":[2.1518421173,41.399772644],"type":"Point"}
}