{
  "type": "Feature",
  "properties": {
    "addr:full":"Pase Conde De Sepulveda (del), 15 Segovia Segovia 40002",
    "addr:housenumber":"15",
    "addr:postcode":"40002",
    "addr:street":"Conde;Sepulveda Del",
    "iso:country":"ES",
    "sg:address":"Pase Conde De Sepulveda (del), 15",
    "sg:city":"Segovia",
    "sg:orig_category":"Muebles Y Accesorios Para Cocinas Y Cuartos De Ba\u00d1o (al Por Menor)",
    "sg:phone":"+34 921 42 94 34",
    "sg:postcode":"40002",
    "sg:province":"Segovia",
    "sg:website":"www.paginasamarillas.es",
    "wof:name":"Pascual Izquierdo Moises",
    "wof:placetype":"venue"
},
  "geometry": {"coordinates":[-4.116795063,40.9407958984],"type":"Point"}
}