{
  "type": "Feature",
  "properties": {
    "iso:country":"ES",
    "sg:address":"Carrer de Hortensia (l'), 37",
    "sg:city":"Mas D'en Gall",
    "sg:orig_category":"Electricidad: Instaladores",
    "sg:phone":"+34 937 70 82 86",
    "sg:postcode":"08292",
    "sg:province":"Barcelona",
    "wof:name":"Sanchez Moyano David",
    "wof:placetype":"venue"
},
  "geometry": {"coordinates":[2.1469190121,41.3699874878],"type":"Point"}
}