{
  "type": "Feature",
  "properties": {
    "addr:full":"Calle de Perez Galdos, 36 Bilbao Vizcaya 48010",
    "addr:housenumber":"36",
    "addr:postcode":"48010",
    "addr:street":"Calle De Perez Galdos",
    "iso:country":"ES",
    "sg:address":"Calle de Perez Galdos, 36",
    "sg:city":"Bilbao",
    "sg:orig_category":"Bricolaje, Herramientas (al Por Menor)",
    "sg:phone":"+34 944 02 08 02",
    "sg:postcode":"48010",
    "sg:province":"Vizcaya",
    "wof:name":"(bricolage  Olana) Maite Zubieta",
    "wof:placetype":"venue"
},
  "geometry": {"coordinates":[-2.9459209442,43.2599487305],"type":"Point"}
}