{
  "type": "Feature",
  "properties": {
    "addr:full":"Avda Constitucion, 4 Cervera Del Rio Alhama La Rioja 26520",
    "addr:housenumber":"4",
    "addr:postcode":"26520",
    "addr:street":"Avda Constitucion;Alhama;Rioja",
    "iso:country":"ES",
    "sg:address":"Avda Constitucion, 4",
    "sg:city":"Cervera Del Rio Alhama",
    "sg:orig_category":"Farmacias",
    "sg:phone":"+34 941 17 70 70",
    "sg:postcode":"26520",
    "sg:province":"La Rioja",
    "wof:name":"Escribano Castro Rufino",
    "wof:placetype":"venue"
},
  "geometry": {"coordinates":[-1.9522140026,42.0069198608],"type":"Point"}
}