{
  "type": "Feature",
  "properties": {
    "addr:full":"Calle de Castillo, 4 Campo Criptana Ciudad Real 13610",
    "addr:housenumber":"4",
    "addr:postcode":"13610",
    "addr:street":"Calle De Castillo;Criptana",
    "iso:country":"ES",
    "sg:address":"Calle de Castillo, 4",
    "sg:city":"Campo Criptana",
    "sg:orig_category":"Papeler\u00cdas, Librer\u00cdas",
    "sg:phone":"+34 926 56 05 27",
    "sg:postcode":"13610",
    "sg:province":"Ciudad Real",
    "wof:name":"Viarim S.l.",
    "wof:placetype":"venue"
},
  "geometry": {"coordinates":[-3.1225280762,39.4024925232],"type":"Point"}
}