{
  "type": "Feature",
  "properties": {
    "addr:full":"Calle de Elche, 66 Santa Pola Alicante 03130",
    "addr:housenumber":"66",
    "addr:postcode":"03130",
    "addr:street":"Calle De Elche",
    "iso:country":"ES",
    "sg:address":"Calle de Elche, 66",
    "sg:city":"Santa Pola",
    "sg:orig_category":"Inmobiliaria (agencias)",
    "sg:phone":"+34 966 69 21 13",
    "sg:postcode":"03130",
    "sg:province":"Alicante",
    "wof:name":"Hijos De Jaen Larrieu S.l.",
    "wof:placetype":"venue"
},
  "geometry": {"coordinates":[-0.559263885,38.1956520081],"type":"Point"}
}