{
  "type": "Feature",
  "properties": {
    "addr:full":"Calle de Laguna, 16 Madrid Madrid 28025",
    "addr:housenumber":"16",
    "addr:postcode":"madrid;28025",
    "addr:street":"Calle De Laguna",
    "iso:country":"ES",
    "sg:address":"Calle de Laguna, 16",
    "sg:city":"Madrid",
    "sg:orig_category":"Librer\u00cdas",
    "sg:phone":"+34 914 62 18 43",
    "sg:postcode":"28025",
    "sg:province":"Madrid",
    "wof:name":"Garcia Cabrero Julio",
    "wof:placetype":"venue"
},
  "geometry": {"coordinates":[-3.7423241138,40.391418457],"type":"Point"}
}