{
  "type": "Feature",
  "properties": {
    "iso:country":"ES",
    "sg:address":"Plaz Constitucion (la), S/n",
    "sg:city":"Maracena",
    "sg:orig_category":"Bancos",
    "sg:phone":"+34 958 42 02 01",
    "sg:postcode":"18200",
    "sg:province":"Granada",
    "sg:website":"www.banesto.es",
    "wof:name":"Banco Espa\u00f1ol De Credito S.a.",
    "wof:placetype":"venue"
},
  "geometry": {"coordinates":[-3.6344840527,37.2073097229],"type":"Point"}
}