{
  "type": "Feature",
  "properties": {
    "iso:country":"ES",
    "sg:address":"Carr Joaquim Sostres, 60",
    "sg:city":"Sort",
    "sg:orig_category":"Notarios",
    "sg:phone":"+34 973 62 13 10",
    "sg:postcode":"25560",
    "sg:province":"Lleida",
    "wof:name":"Hernandez Ruiz Maria Cristina",
    "wof:placetype":"venue"
},
  "geometry": {"coordinates":[1.1276350021,42.4102973938],"type":"Point"}
}