{
  "type": "Feature",
  "properties": {
    "iso:country":"ES",
    "sg:address":"Avda Alcoy, 17",
    "sg:city":"Alacant",
    "sg:orig_category":"Bisuter\u00cda, Joyer\u00cda, Relojer\u00cda (al Por Menor)",
    "sg:phone":"+34 965 24 36 56",
    "sg:postcode":"03004",
    "sg:province":"Alicante",
    "wof:name":"Jimenez Luque Carmen",
    "wof:placetype":"venue"
},
  "geometry": {"coordinates":[-0.4860689938,38.3529014587],"type":"Point"}
}