{
  "type": "Feature",
  "properties": {
    "addr:full":"Calle de San Juan Bosco, 24 Alacant Alicante 03005",
    "addr:housenumber":"24",
    "addr:postcode":"03005",
    "addr:street":"Calle De San Juan Bosco",
    "iso:country":"ES",
    "sg:address":"Calle de San Juan Bosco, 24",
    "sg:city":"Alacant",
    "sg:orig_category":"Procuradores",
    "sg:phone":"+34 965 92 25 53",
    "sg:postcode":"03005",
    "sg:province":"Alicante",
    "wof:name":"Pamblanco Sanchez Jose Luis",
    "wof:placetype":"venue"
},
  "geometry": {"coordinates":[-0.4942620099,38.3458518982],"type":"Point"}
}