{
  "type": "Feature",
  "properties": {
    "iso:country":"ES",
    "sg:address":"Ctra Torreblanca-mairena, Km. 0002,8",
    "sg:city":"Alcala Guadaira",
    "sg:classifiers":[
        {
            "category":"Manufacturing",
            "subcategory":"Metals",
            "type":"Manufacturing & Wholesale Goods"
        }
    ],
    "sg:phone":"+34 955 63 19 72",
    "sg:postcode":"41500",
    "sg:province":"Sevilla",
    "sg:tags":[
        "en",
        "fundiciones"
    ],
    "wof:name":"Fundicion Andaluza De Metales S. A.",
    "wof:placetype":"venue"
},
  "geometry": {"coordinates":[-5.8398590088,37.3383140564],"type":"Point"}
}