{
  "type": "Feature",
  "properties": {
    "iso:country":"ES",
    "sg:address":"Calle de Portuetxe, 53",
    "sg:city":"Donostia-san Sebastian",
    "sg:orig_category":"Grafistas",
    "sg:phone":"+34 943 29 15 00",
    "sg:postcode":"20018",
    "sg:province":"Guip\u00f9zcoa",
    "wof:name":"Signos De Identidad S.l.",
    "wof:placetype":"venue"
},
  "geometry": {"coordinates":[-2.0161669254,43.3012313843],"type":"Point"}
}