{
  "type": "Feature",
  "properties": {
    "iso:country":"ES",
    "sg:address":"Carrer de Sant Felix, 11",
    "sg:city":"Vilafranca Penedes",
    "sg:orig_category":"Pescader\u00cdas (al Por Menor)",
    "sg:phone":"+34 938 90 06 39",
    "sg:postcode":"08720",
    "sg:province":"Barcelona",
    "wof:name":"Ca\u00f1amero Capdevila Joan",
    "wof:placetype":"venue"
},
  "geometry": {"coordinates":[1.6952140331,41.3453063965],"type":"Point"}
}