{
  "type": "Feature",
  "properties": {
    "addr:full":"Estd Uri, 4 Andra Mari Vizcaya 48993",
    "addr:housenumber":"4",
    "addr:postcode":"48993",
    "addr:street":"Andra Mari Vizcaya",
    "iso:country":"ES",
    "sg:address":"Estd Uri, 4",
    "sg:city":"Andra Mari",
    "sg:orig_category":"Maquinaria Para Industrias Diversas",
    "sg:phone":"+34 944 91 40 48",
    "sg:postcode":"48993",
    "sg:province":"Vizcaya",
    "wof:name":"Badiola Mallavia Francisco Javier",
    "wof:placetype":"venue"
},
  "geometry": {"coordinates":[-2.7541499138,43.2982711792],"type":"Point"}
}