{
  "type": "Feature",
  "properties": {
    "iso:country":"ES",
    "sg:address":"O Mui\u00f1o, 18",
    "sg:city":"Cobres",
    "sg:orig_category":"Muebles Y Accesorios Para Cocinas Y Cuartos De Ba\u00d1o (al Por Menor)",
    "sg:phone":"+34 986 67 21 10",
    "sg:postcode":"36141",
    "sg:province":"Pontevedra",
    "wof:name":"Calvar Rosendo Casilda",
    "wof:placetype":"venue"
},
  "geometry": {"coordinates":[-8.6366939545,42.3592987061],"type":"Point"}
}