{
  "type": "Feature",
  "properties": {
    "iso:country":"ES",
    "sg:address":"Avda Acacias (las), 21",
    "sg:city":"Jerez De La Frontera",
    "sg:orig_category":"M\u00c9dicos: Ginecolog\u00cda Y Obstetricia",
    "sg:phone":"+34 956 30 92 82",
    "sg:postcode":"11407",
    "sg:province":"C\u00e1diz",
    "wof:name":"Delgado Izquierdo Francisco",
    "wof:placetype":"venue"
},
  "geometry": {"coordinates":[-6.1381111145,36.7024841309],"type":"Point"}
}