{
  "type": "Feature",
  "properties": {
    "addr:full":"Calle de Concha General, 12 Bilbao Vizcaya 48008",
    "addr:housenumber":"12",
    "addr:postcode":"48008",
    "addr:street":"Calle De Concha General",
    "iso:country":"ES",
    "sg:address":"Calle de Concha General, 12",
    "sg:city":"Bilbao",
    "sg:orig_category":"Psic\u00d3logos",
    "sg:phone":"+34 944 44 93 04",
    "sg:postcode":"48008",
    "sg:province":"Vizcaya",
    "wof:name":"Albora Bide, C.b.",
    "wof:placetype":"venue"
},
  "geometry": {"coordinates":[-2.9319541454,43.2600097656],"type":"Point"}
}