{
  "type": "Feature",
  "properties": {
    "iso:country":"ES",
    "sg:address":"Calle de Batalla Del Salado, 30",
    "sg:city":"Tarifa",
    "sg:orig_category":"Ropa Para Ni\u00d1os (al Por Menor)",
    "sg:phone":"+34 956 68 08 77",
    "sg:postcode":"11380",
    "sg:province":"C\u00e1diz",
    "wof:name":"Bellini Ferrer Eduardo",
    "wof:placetype":"venue"
},
  "geometry": {"coordinates":[-5.6060948372,36.0161132812],"type":"Point"}
}