{
  "type": "Feature",
  "properties": {
    "iso:country":"ES",
    "sg:address":"Carrer de Emili Botey Alsina, 10",
    "sg:city":"Granollers",
    "sg:orig_category":"Comercio De Mobiliario De Oficina",
    "sg:phone":"+34 938 61 30 98",
    "sg:postcode":"08402",
    "sg:province":"Barcelona",
    "wof:name":"Ofidirecta Granollers S.l.",
    "wof:placetype":"venue"
},
  "geometry": {"coordinates":[2.2878749371,41.597442627],"type":"Point"}
}