{
  "type": "Feature",
  "properties": {
    "addr:full":"Avda Valencia, 80 Pe\u00f1iscola Castell\u00f3n 12598",
    "addr:housenumber":"80",
    "addr:postcode":"12598",
    "addr:street":"Avda Valencia;Castello\u0301N",
    "iso:country":"ES",
    "sg:address":"Avda Valencia, 80",
    "sg:city":"Pe\u00f1iscola",
    "sg:orig_category":"Molduras, Junquillos, Listones Y Molduras Perforadas",
    "sg:phone":"+34 964 48 94 52",
    "sg:postcode":"12598",
    "sg:province":"Castell\u00f3n",
    "wof:name":"Lorente Paris Antonio",
    "wof:placetype":"venue"
},
  "geometry": {"coordinates":[-0.0456800014,39.9851417542],"type":"Point"}
}