{
  "type": "Feature",
  "properties": {
    "iso:country":"ES",
    "sg:address":"General Del Sur, Km. 0007,0",
    "sg:city":"Taco",
    "sg:orig_category":"Muebles, Minoristas",
    "sg:phone":"+34 922 61 76 59",
    "sg:postcode":"38108",
    "sg:province":"Santa Cruz De Tenerife",
    "wof:name":"C.b. Isabel Machin E Hijos",
    "wof:placetype":"venue"
},
  "geometry": {"coordinates":[-16.2957706451,28.4491081238],"type":"Point"}
}