{
  "type": "Feature",
  "properties": {
    "addr:full":"Calle de Tesifonte Gallego, 7 Albacete Albacete 02002",
    "addr:housenumber":"7",
    "addr:postcode":"02002",
    "addr:street":"Calle De Tesifonte Gallego",
    "iso:country":"ES",
    "sg:address":"Calle de Tesifonte Gallego, 7",
    "sg:city":"Albacete",
    "sg:orig_category":"Fotograf\u00cda Y Cine: Aparatos, Pel\u00cdculas Y Accesorios (al Por Menor)",
    "sg:phone":"+34 967 21 83 65",
    "sg:postcode":"02002",
    "sg:province":"Albacete",
    "wof:name":"Jupoma S.l.",
    "wof:placetype":"venue"
},
  "geometry": {"coordinates":[-1.8553270102,38.9924278259],"type":"Point"}
}