{
  "type": "Feature",
  "properties": {
    "iso:country":"ES",
    "sg:address":"Maquina, 16",
    "sg:city":"Gava",
    "sg:orig_category":"Transportes Por V\u00cdas Navegables",
    "sg:phone":"+34 936 62 71 50",
    "sg:postcode":"08850",
    "sg:province":"Barcelona",
    "wof:name":"Transportes Y Logistica Fernandez S.l.",
    "wof:placetype":"venue"
},
  "geometry": {"coordinates":[2.0098409653,41.2956161499],"type":"Point"}
}