{
  "type": "Feature",
  "properties": {
    "iso:country":"ES",
    "sg:address":"Ctra Alicante, Km. 0002,4",
    "sg:city":"Ibi",
    "sg:orig_category":"Trabajos De Perforaciones, Sondeos, Construcci\u00d3n De Pozos",
    "sg:phone":"+34 965 55 07 34",
    "sg:postcode":"03440",
    "sg:province":"Alicante",
    "wof:name":"Gruas Y Perforaciones La Ibense Sl",
    "wof:placetype":"venue"
},
  "geometry": {"coordinates":[-0.5886539817,38.6124305725],"type":"Point"}
}