{
  "type": "Feature",
  "properties": {
    "iso:country":"ES",
    "sg:address":"Calle de Salvador Rueda, S/n",
    "sg:city":"Nerja",
    "sg:orig_category":"Pescader\u00cdas (al Por Menor)",
    "sg:phone":"+34 952 52 60 84",
    "sg:postcode":"29780",
    "sg:province":"M\u00e1laga",
    "wof:name":"Do\u00f1a Rojas Jose",
    "wof:placetype":"venue"
},
  "geometry": {"coordinates":[-3.8712749481,36.7628669739],"type":"Point"}
}