{
  "type": "Feature",
  "properties": {
    "iso:country":"ES",
    "sg:address":"Crri Torre Molina, 89",
    "sg:city":"Torre Molina",
    "sg:orig_category":"Empresas De Carpinter\u00cda De Madera",
    "sg:phone":"+34 968 29 89 33",
    "sg:postcode":"30009",
    "sg:province":"Murcia",
    "wof:name":"Antonio Serrano Nicolas S.l.",
    "wof:placetype":"venue"
},
  "geometry": {"coordinates":[-1.2109922171,38.0509223938],"type":"Point"}
}