{
  "type": "Feature",
  "properties": {
    "iso:country":"ES",
    "sg:address":"Avda Doctor M. Carriche, 9",
    "sg:city":"Leganes",
    "sg:orig_category":"Organizaci\u00d3n De Actos, Seminarios Y Congresos",
    "sg:phone":"+34 916 94 68 24",
    "sg:postcode":"28913",
    "sg:province":"Madrid",
    "wof:name":"Ilik  Haci",
    "wof:placetype":"venue"
},
  "geometry": {"coordinates":[-3.770827055,40.331451416],"type":"Point"}
}