{
  "type": "Feature",
  "properties": {
    "iso:country":"ES",
    "sg:address":"Avda Buenos Aires, 18",
    "sg:city":"Pontevedra",
    "sg:orig_category":"Promotores Constructores",
    "sg:phone":"+34 986 86 38 52",
    "sg:postcode":"36002",
    "sg:province":"Pontevedra",
    "wof:name":"Aplyreform S.l.",
    "wof:placetype":"venue"
},
  "geometry": {"coordinates":[-8.6406841278,42.4339065552],"type":"Point"}
}