{
  "type": "Feature",
  "properties": {
    "iso:country":"ES",
    "sg:address":"Calle de Estacion (la), 4",
    "sg:city":"Quintana Redonda",
    "sg:orig_category":"Reposter\u00cdas",
    "sg:phone":"+34 975 30 80 78",
    "sg:postcode":"42291",
    "sg:province":"Soria",
    "wof:name":"Plaza Carretero Felix",
    "wof:placetype":"venue"
},
  "geometry": {"coordinates":[-2.6145529747,41.6388778687],"type":"Point"}
}