{
  "type": "Feature",
  "properties": {
    "addr:full":"Calle de Bidebarri, 2 Getxo Vizcaya 48990",
    "addr:housenumber":"2",
    "addr:postcode":"48990",
    "addr:street":"Calle De Bidebarri",
    "iso:country":"ES",
    "sg:address":"Calle de Bidebarri, 2",
    "sg:city":"Getxo",
    "sg:orig_category":"Servicio De Salud",
    "sg:phone":"+34 944 30 29 60",
    "sg:postcode":"48990",
    "sg:province":"Vizcaya",
    "wof:name":"Maria Bego\u00f1a Lopez Calleja",
    "wof:placetype":"venue"
},
  "geometry": {"coordinates":[-3.0092315674,43.352355957],"type":"Point"}
}