{
  "type": "Feature",
  "properties": {
    "addr:full":"Carrer de Ciutat De Balaguer, 39 Barcelona Barcelona 08022",
    "addr:housenumber":"39",
    "addr:postcode":"08022",
    "addr:street":"Carrer De Ciutat De Balaguer",
    "iso:country":"ES",
    "sg:address":"Carrer de Ciutat De Balaguer, 39",
    "sg:city":"Barcelona",
    "sg:orig_category":"Cl\u00cdnicas M\u00c9dicas",
    "sg:phone":"+34 932 54 08 26",
    "sg:postcode":"08022",
    "sg:province":"Barcelona",
    "wof:name":"Conlaser Servicios Integrales S.l.",
    "wof:placetype":"venue"
},
  "geometry": {"coordinates":[2.1347270012,41.4037132263],"type":"Point"}
}