{
  "type": "Feature",
  "properties": {
    "addr:full":"Carrer de Regall, S/n Vall D'alba Castell\u00f3n 12194",
    "addr:housenumber":"s / n",
    "addr:postcode":"12194",
    "addr:street":"Carrer De Regall",
    "iso:country":"ES",
    "sg:address":"Carrer de Regall, S/n",
    "sg:city":"Vall D'alba",
    "sg:orig_category":"Estilistas Y Estudios De Estilo De Corte Y Confecci\u00d3n",
    "sg:phone":"+34 964 33 08 06",
    "sg:postcode":"12194",
    "sg:province":"Castell\u00f3n",
    "wof:name":"Confecciones Plana Alta Giver S.l.",
    "wof:placetype":"venue"
},
  "geometry": {"coordinates":[-0.0519389994,39.985408783],"type":"Point"}
}