{
  "type": "Feature",
  "properties": {
    "iso:country":"ES",
    "sg:address":"Fogainers, S/n",
    "sg:city":"P. I. El Oliveral",
    "sg:orig_category":"Juegos Y Juguetes (al Por Menor)",
    "sg:phone":"+34 961 66 70 60",
    "sg:postcode":"46190",
    "sg:province":"Valencia",
    "wof:name":"Almacenes Marti S.l.",
    "wof:placetype":"venue"
},
  "geometry": {"coordinates":[-0.3637185097,39.4238967896],"type":"Point"}
}