{
  "type": "Feature",
  "properties": {
    "iso:country":"ES",
    "sg:address":"Avda. Lugo, 5",
    "sg:city":"Pobra Do Brollon",
    "sg:orig_category":"Electricidad: Instaladores",
    "sg:phone":"+34 982 43 01 52",
    "sg:postcode":"27334",
    "sg:province":"Lugo",
    "wof:name":"Sanchez Rivera Antonio",
    "wof:placetype":"venue"
},
  "geometry": {"coordinates":[-7.4457578659,42.5691146851],"type":"Point"}
}