{
  "type": "Feature",
  "properties": {
    "addr:full":"Pase Casares De, 155 Donostia-san Sebastian Guip\u00f9zcoa 20017",
    "addr:housenumber":"155",
    "addr:postcode":"20017",
    "iso:country":"ES",
    "sg:address":"Pase Casares De, 155",
    "sg:city":"Donostia-san Sebastian",
    "sg:orig_category":"Centros De Educaci\u00d3n Especial",
    "sg:phone":"+34 943 35 32 34",
    "sg:postcode":"20017",
    "sg:province":"Guip\u00f9zcoa",
    "wof:name":"Gobierno Vasco-eusko Jaurlaritza",
    "wof:placetype":"venue"
},
  "geometry": {"coordinates":[-1.9283790588,43.3184623718],"type":"Point"}
}