{
  "type": "Feature",
  "properties": {
    "addr:full":"Av Cortes Valencianas, 96 Albal Valencia 46470",
    "addr:housenumber":"96",
    "addr:postcode":"46470",
    "addr:street":"Av Cortes Valencianas",
    "iso:country":"ES",
    "sg:address":"Av Cortes Valencianas, 96",
    "sg:city":"Albal",
    "sg:orig_category":"Librer\u00cdas",
    "sg:phone":"+34 961 26 02 19",
    "sg:postcode":"46470",
    "sg:province":"Valencia",
    "wof:name":"Mu\u00f1oz Bort Francisca",
    "wof:placetype":"venue"
},
  "geometry": {"coordinates":[-0.4068570137,39.3961105347],"type":"Point"}
}