{
  "type": "Feature",
  "properties": {
    "iso:country":"ES",
    "sg:address":"Cerde\u00f1o, 6",
    "sg:city":"Cerde\u00d1o",
    "sg:orig_category":"Empresarios",
    "sg:phone":"+34 985 29 79 90",
    "sg:postcode":"33010",
    "sg:province":"Asturias",
    "wof:name":"Seryobra S. L.",
    "wof:placetype":"venue"
},
  "geometry": {"coordinates":[-5.7993540764,43.3772239685],"type":"Point"}
}