{
  "type": "Feature",
  "properties": {
    "addr:full":"Zuberoa Kalea, 12 Zarautz Guip\u00f9zcoa 20800",
    "addr:housenumber":"12",
    "addr:postcode":"20800",
    "addr:street":"Zuberoa Kalea;Guipu\u0300Zcoa",
    "iso:country":"ES",
    "sg:address":"Zuberoa Kalea, 12",
    "sg:city":"Zarautz",
    "sg:orig_category":"Productos Refractarios (fabricaci\u00d3n, Al Por Mayor)",
    "sg:phone":"+34 943 83 37 89",
    "sg:postcode":"20800",
    "sg:province":"Guip\u00f9zcoa",
    "wof:name":"Magnesitas Navarras S. A.",
    "wof:placetype":"venue"
},
  "geometry": {"coordinates":[-2.1715369225,43.2799873352],"type":"Point"}
}