{
  "type": "Feature",
  "properties": {
    "addr:full":"Calle de Carretas, 5 Madrid Madrid 28012",
    "addr:housenumber":"5",
    "addr:postcode":"28012",
    "addr:street":"Calle De Carretas",
    "iso:country":"ES",
    "sg:address":"Calle de Carretas, 5",
    "sg:city":"Madrid",
    "sg:orig_category":"Ropa Para Caballeros (al Por Menor)",
    "sg:phone":"+34 915 21 08 31",
    "sg:postcode":"28012",
    "sg:province":"Madrid",
    "sg:website":"www.often.com",
    "wof:name":"Pull & Bear Espa\u00f1a S.a.",
    "wof:placetype":"venue"
},
  "geometry": {"coordinates":[-3.703250885,40.4164237976],"type":"Point"}
}