{
  "type": "Feature",
  "properties": {
    "addr:full":"Avda Ciudad De Barcelona, 120 Madrid Madrid 28007",
    "addr:housenumber":"120",
    "addr:postcode":"28007",
    "addr:street":"Avda Ciudad De Barcelona",
    "iso:country":"ES",
    "sg:address":"Avda Ciudad De Barcelona, 120",
    "sg:city":"Madrid",
    "sg:orig_category":"Peluqueros: De Se\u00d1oras",
    "sg:phone":"+34 915 51 93 63",
    "sg:postcode":"28007",
    "sg:province":"Madrid",
    "wof:name":"Navarro Garcia Dolores",
    "wof:placetype":"venue"
},
  "geometry": {"coordinates":[-3.6818990707,40.4046058655],"type":"Point"}
}