{
  "type": "Feature",
  "properties": {
    "iso:country":"ES",
    "sg:address":"Calle de Ulpiano Gonzalez, 11",
    "sg:city":"Cuba",
    "sg:orig_category":"Cr\u00cda De Cerdos",
    "sg:phone":"+34 964 18 00 50",
    "sg:postcode":"44141",
    "sg:province":"Teruel",
    "wof:name":"Carceller S.c.",
    "wof:placetype":"venue"
},
  "geometry": {"coordinates":[-0.3423460126,40.5890464783],"type":"Point"}
}