{
  "type": "Feature",
  "properties": {
    "iso:country":"ES",
    "sg:address":"Carrer de Puigcerda, 292",
    "sg:city":"Barcelona",
    "sg:orig_category":"Molduras, Junquillos, Listones Y Molduras Perforadas",
    "sg:phone":"+34 932 78 06 64",
    "sg:postcode":"08020",
    "sg:province":"Barcelona",
    "wof:name":"Gwang  Bin",
    "wof:placetype":"venue"
},
  "geometry": {"coordinates":[2.2002530098,41.4239654541],"type":"Point"}
}