{
  "type": "Feature",
  "properties": {
    "iso:country":"ES",
    "sg:address":"Avda Manantiales De Los, 3",
    "sg:city":"Torremolinos",
    "sg:orig_category":"Estancos",
    "sg:phone":"+34 952 38 20 93",
    "sg:postcode":"29620",
    "sg:province":"M\u00e1laga",
    "wof:name":"Serrano Varela Maria Del Socorro",
    "wof:placetype":"venue"
},
  "geometry": {"coordinates":[-4.500210762,36.6246871948],"type":"Point"}
}