{
  "type": "Feature",
  "properties": {
    "addr:full":"Rbla Sant Sebastia, 73 Santa Coloma De Gramenet Barcelona 08921",
    "addr:housenumber":"73",
    "addr:postcode":"08921",
    "addr:street":"Rbla Sant Sebastia",
    "iso:country":"ES",
    "sg:address":"Rbla Sant Sebastia, 73",
    "sg:city":"Santa Coloma De Gramenet",
    "sg:orig_category":"Charcuter\u00cdas (al Por Mayor)",
    "sg:phone":"+34 933 85 70 33",
    "sg:postcode":"08921",
    "sg:province":"Barcelona",
    "wof:name":"Distribuciones Bravo S.a.",
    "wof:placetype":"venue"
},
  "geometry": {"coordinates":[2.2150599957,41.4510002136],"type":"Point"}
}