{
  "type": "Feature",
  "properties": {
    "addr:full":"Rua Redondo, 76 Samil Pontevedra 36212",
    "addr:housenumber":"76",
    "addr:postcode":"36212",
    "addr:street":"Rua Redondo",
    "iso:country":"ES",
    "sg:address":"Rua Redondo, 76",
    "sg:city":"Samil",
    "sg:orig_category":"Agencias Y Agentes Comerciales, Representantes",
    "sg:phone":"+34 986 24 00 46",
    "sg:postcode":"36212",
    "sg:province":"Pontevedra",
    "wof:name":"Costas Alonso Clara",
    "wof:placetype":"venue"
},
  "geometry": {"coordinates":[-8.7656679153,42.2123451233],"type":"Point"}
}