{
  "type": "Feature",
  "properties": {
    "addr:full":"Plaz Leandro Mayoral, 16 Tardajos Burgos 09130",
    "addr:housenumber":"16",
    "addr:postcode":"09130",
    "addr:street":"Mayoral",
    "iso:country":"ES",
    "sg:address":"Plaz Leandro Mayoral, 16",
    "sg:city":"Tardajos",
    "sg:orig_category":"Iglesia Cat\u00d3lica",
    "sg:phone":"+34 947 45 10 32",
    "sg:postcode":"09130",
    "sg:province":"Burgos",
    "wof:name":"Parroquia De La Asuncion",
    "wof:placetype":"venue"
},
  "geometry": {"coordinates":[-3.8184070587,42.3491859436],"type":"Point"}
}