{
  "type": "Feature",
  "properties": {
    "addr:full":"Plaz Euskadi, 8 Zumarraga Guip\u00f9zcoa 20700",
    "addr:housenumber":"8",
    "addr:postcode":"20700",
    "addr:street":"Plaz Euskadi;Guipu\u0300Zcoa",
    "iso:country":"ES",
    "sg:address":"Plaz Euskadi, 8",
    "sg:city":"Zumarraga",
    "sg:orig_category":"Panader\u00cdas, Panader\u00cdas",
    "sg:phone":"+34 943 72 05 44",
    "sg:postcode":"20700",
    "sg:province":"Guip\u00f9zcoa",
    "wof:name":"Temprano Plazaola Alberto",
    "wof:placetype":"venue"
},
  "geometry": {"coordinates":[-2.3144950867,43.0902366638],"type":"Point"}
}