{
  "type": "Feature",
  "properties": {
    "addr:full":"Cabrera, 125 Cales Mallorca Islas Baleares 07689",
    "addr:housenumber":"125",
    "addr:postcode":"07689",
    "addr:street":"Cabrera;Mallorca",
    "iso:country":"ES",
    "sg:address":"Cabrera, 125",
    "sg:city":"Cales Mallorca",
    "sg:orig_category":"Guarder\u00cdas",
    "sg:phone":"+34 971 83 39 00",
    "sg:postcode":"07689",
    "sg:province":"Islas Baleares",
    "wof:name":"Asociacion Propietarios De Calas De Mallorca",
    "wof:placetype":"venue"
},
  "geometry": {"coordinates":[3.2746891975,39.4657363892],"type":"Point"}
}