{
  "type": "Feature",
  "properties": {
    "addr:full":"Grup San Juan, 1 Leioa Vizcaya 48940",
    "addr:housenumber":"1",
    "addr:postcode":"48940",
    "addr:street":"San Juan",
    "iso:country":"ES",
    "sg:address":"Grup San Juan, 1",
    "sg:city":"Leioa",
    "sg:orig_category":"Molduras, Junquillos, Listones Y Molduras Perforadas",
    "sg:phone":"+34 944 02 29 14",
    "sg:postcode":"48940",
    "sg:province":"Vizcaya",
    "wof:name":"Domingo Encarnacion Martins",
    "wof:placetype":"venue"
},
  "geometry": {"coordinates":[-2.9829890728,43.3246192932],"type":"Point"}
}