{
  "type": "Feature",
  "properties": {
    "addr:full":"Calle de Arrabal, 69 Onil Alicante 03430",
    "addr:housenumber":"69",
    "addr:postcode":"03430",
    "addr:street":"Calle De Arrabal",
    "iso:country":"ES",
    "sg:address":"Calle de Arrabal, 69",
    "sg:city":"Onil",
    "sg:orig_category":"Carnicer\u00cdas, Carnicer\u00cdas",
    "sg:phone":"+34 965 56 44 99",
    "sg:postcode":"03430",
    "sg:province":"Alicante",
    "wof:name":"Pardo Estevan Jose",
    "wof:placetype":"venue"
},
  "geometry": {"coordinates":[-0.6692324281,38.6296730042],"type":"Point"}
}