{
  "type": "Feature",
  "properties": {
    "addr:full":"Av. Petroleo, 38 Leganes Madrid 28918",
    "addr:housenumber":"38",
    "addr:postcode":"28918",
    "addr:street":"Av. Petroleo",
    "iso:country":"ES",
    "sg:address":"Av. Petroleo, 38",
    "sg:city":"Leganes",
    "sg:orig_category":"Artes Gr\u00c1ficas, Artes Pl\u00c1sticas (curso)",
    "sg:phone":"+34 914 88 10 58",
    "sg:postcode":"28918",
    "sg:province":"Madrid",
    "wof:name":"M.p.o. Iberica S.a.",
    "wof:placetype":"venue"
},
  "geometry": {"coordinates":[-3.799487114,40.3524360657],"type":"Point"}
}