{
  "type": "Feature",
  "properties": {
    "addr:full":"Av Catalunya, 24 Colonia Del Palau Barcelona 08740",
    "addr:housenumber":"24",
    "addr:postcode":"08740",
    "addr:street":"Av Catalunya",
    "iso:country":"ES",
    "sg:address":"Av Catalunya, 24",
    "sg:city":"Colonia Del Palau",
    "sg:orig_category":"Quincaller\u00cda (al Por Menor)",
    "sg:phone":"+34 936 82 56 96",
    "sg:postcode":"08740",
    "sg:province":"Barcelona",
    "wof:name":"Vives Aznar Mari Carmen",
    "wof:placetype":"venue"
},
  "geometry": {"coordinates":[1.9690527916,41.4470596313],"type":"Point"}
}