{
  "type": "Feature",
  "properties": {
    "addr:full":"Calle de Guetaria, 110 Madrid Madrid 28041",
    "addr:housenumber":"110",
    "addr:postcode":"28041",
    "addr:street":"Calle De Guetaria",
    "iso:country":"ES",
    "sg:address":"Calle de Guetaria, 110",
    "sg:city":"Madrid",
    "sg:orig_category":"Materiales De Construcci\u00d3n (en General)",
    "sg:phone":"+34 913 41 03 30",
    "sg:postcode":"28041",
    "sg:province":"Madrid",
    "wof:name":"Cenmentos Especiales Y Morteros S.l.",
    "wof:placetype":"venue"
},
  "geometry": {"coordinates":[-3.715775013,40.3661003113],"type":"Point"}
}