{
  "type": "Feature",
  "properties": {
    "addr:full":"Gunxel(capela), 7 Gunxel La Coru\u00f1a 15613",
    "addr:housenumber":"7",
    "addr:postcode":"15613",
    "addr:street":"Capela;La Corun\u0303A",
    "iso:country":"ES",
    "sg:address":"Gunxel(capela), 7",
    "sg:city":"Gunxel",
    "sg:orig_category":"Cr\u00cda De Animales",
    "sg:phone":"+34 981 45 90 72",
    "sg:postcode":"15613",
    "sg:province":"La Coru\u00f1a",
    "wof:name":"Paz Calvo Francisco",
    "wof:placetype":"venue"
},
  "geometry": {"coordinates":[-8.0707349777,43.4355812073],"type":"Point"}
}