{
  "type": "Feature",
  "properties": {
    "iso:country":"ES",
    "sg:address":"A Comarca Ii Pol Ind, 9",
    "sg:city":"Barbatain",
    "sg:orig_category":"Electricidad: Instaladores",
    "sg:phone":"+34 948 31 29 25",
    "sg:postcode":"31191",
    "sg:province":"Navarra",
    "wof:name":"Sectrol S.l.",
    "wof:placetype":"venue"
},
  "geometry": {"coordinates":[-1.6518089771,42.7533912659],"type":"Point"}
}