{
  "type": "Feature",
  "properties": {
    "iso:country":"ES",
    "sg:address":"Carr Carme, 51",
    "sg:city":"Lleida",
    "sg:orig_category":"Venta, Reparaci\u00d3n De M\u00c1quinas De Coser, Planchadoras Y M\u00c1quinas De Tricotar",
    "sg:phone":"+34 973 23 81 65",
    "sg:postcode":"25007",
    "sg:province":"Lleida",
    "wof:name":"Bueno Garcia Angela",
    "wof:placetype":"venue"
},
  "geometry": {"coordinates":[0.6298099756,41.6186027527],"type":"Point"}
}