{
  "type": "Feature",
  "properties": {
    "iso:country":"ES",
    "sg:address":"Bari, 6",
    "sg:city":"Pol. Ind. Can Pelegri",
    "sg:orig_category":"Materias Pl\u00c1sticas: Productos De Consumo Masivo (fabricaci\u00d3n, Al Por Mayor)",
    "sg:phone":"+34 936 53 10 85",
    "sg:postcode":"08755",
    "sg:province":"Barcelona",
    "wof:name":"Ozballi Barcelona S.l.",
    "wof:placetype":"venue"
},
  "geometry": {"coordinates":[1.9784770012,41.4735145569],"type":"Point"}
}