{
  "type": "Feature",
  "properties": {
    "iso:country":"ES",
    "sg:address":"Carretera De Loja, S/n",
    "sg:city":"Priego Cordoba",
    "sg:orig_category":"Forjas Y Altos Hornos",
    "sg:phone":"+34 957 72 00 01",
    "sg:postcode":"14800",
    "sg:province":"C\u00f3rdoba",
    "wof:name":"Lopez Romero Rafael",
    "wof:placetype":"venue"
},
  "geometry": {"coordinates":[-4.1947641373,37.4358787537],"type":"Point"}
}