{
  "type": "Feature",
  "properties": {
    "iso:country":"ES",
    "sg:address":"Carrer de Francesc Pla (el Vigata), S/n",
    "sg:city":"Vic",
    "sg:orig_category":"Hospitales",
    "sg:phone":"+34 938 89 11 11",
    "sg:postcode":"08500",
    "sg:province":"Barcelona",
    "wof:name":"Consorci Hospitalari De Vic",
    "wof:placetype":"venue"
},
  "geometry": {"coordinates":[2.2568480968,41.9269294739],"type":"Point"}
}