{
  "type": "Feature",
  "properties": {
    "addr:full":"Pase San Jose, 300 Palmas De Gran Canaria Las Palmas 35016",
    "addr:postcode":"35016",
    "addr:street":"Jose 300",
    "iso:country":"ES",
    "sg:address":"Pase San Jose, 300",
    "sg:city":"Palmas De Gran Canaria",
    "sg:orig_category":"Comercio De Piezas De Recambio Y De Accesorios De Veh\u00cdculos, Veh\u00cdculos Industriales",
    "sg:phone":"+34 928 31 78 17",
    "sg:postcode":"35016",
    "sg:province":"Las Palmas",
    "wof:name":"Auto Repuestos M.torres E Hijos S.l.",
    "wof:placetype":"venue"
},
  "geometry": {"coordinates":[-15.4191713333,28.0852375031],"type":"Point"}
}