{
  "type": "Feature",
  "properties": {
    "iso:country":"ES",
    "sg:address":"Cant Santa Maria, S/n",
    "sg:city":"Vitoria-gasteiz",
    "sg:orig_category":"Asociaciones Humanitarias, De Cooperaci\u00d3n, De Acci\u00d3n Social",
    "sg:phone":"+34 945 26 60 28",
    "sg:postcode":"01001",
    "sg:province":"\u00c1lava",
    "wof:name":"Instituto Municipal De Bienestar Social-ctro. Dia Infantil",
    "wof:placetype":"venue"
},
  "geometry": {"coordinates":[-2.6722991467,42.8485374451],"type":"Point"}
}