{
  "type": "Feature",
  "properties": {
    "iso:country":"ES",
    "sg:address":"Carrer de Catalunya, 16",
    "sg:city":"Riudecols",
    "sg:orig_category":"Empresarios",
    "sg:phone":"+34 977 56 00 06",
    "sg:postcode":"43390",
    "sg:province":"Tarragona",
    "wof:name":"Olive Altes Antonio",
    "wof:placetype":"venue"
},
  "geometry": {"coordinates":[0.9776560068,41.1680793762],"type":"Point"}
}