{
  "type": "Feature",
  "properties": {
    "iso:country":"ES",
    "sg:address":"Calle de Pelayo, 16",
    "sg:city":"Malaga",
    "sg:orig_category":"Farmacias",
    "sg:phone":"+34 952 30 51 29",
    "sg:postcode":"29009",
    "sg:province":"M\u00e1laga",
    "wof:name":"Grana Gil Mercedes",
    "wof:placetype":"venue"
},
  "geometry": {"coordinates":[-4.4322710037,36.7227973938],"type":"Point"}
}