{
  "type": "Feature",
  "properties": {
    "addr:full":"Calle de Alonso Carbonell, 2 Madrid Madrid 28045",
    "addr:housenumber":"2",
    "addr:postcode":"28045",
    "addr:street":"Calle De Alonso Carbonell",
    "iso:country":"ES",
    "sg:address":"Calle de Alonso Carbonell, 2",
    "sg:city":"Madrid",
    "sg:orig_category":"Contenedores (mercanc\u00cdas)",
    "sg:phone":"+34 914 74 52 63",
    "sg:postcode":"28045",
    "sg:province":"Madrid",
    "wof:name":"Miro Pozo Esteban",
    "wof:placetype":"venue"
},
  "geometry": {"coordinates":[-3.696573019,40.3953475952],"type":"Point"}
}