{
  "type": "Feature",
  "properties": {
    "iso:country":"ES",
    "sg:address":"Pl Juan Ramon Jimenez, 8",
    "sg:city":"Puerto Sagunto",
    "sg:orig_category":"Comunidades Religiosas",
    "sg:phone":"+34 962 67 21 77",
    "sg:postcode":"46520",
    "sg:province":"Valencia",
    "wof:name":"Hermanas Carmelitas De La Caridad",
    "wof:placetype":"venue"
},
  "geometry": {"coordinates":[-0.2388100028,39.6720542908],"type":"Point"}
}