{
  "type": "Feature",
  "properties": {
    "addr:full":"Calle de Ramiro Arroyo, 2 Bejar Salamanca 37700",
    "addr:housenumber":"2",
    "addr:postcode":"37700",
    "addr:street":"Calle De Ramiro Arroyo",
    "iso:country":"ES",
    "sg:address":"Calle de Ramiro Arroyo, 2",
    "sg:city":"Bejar",
    "sg:orig_category":"Carnicer\u00cdas, Carnicer\u00cdas",
    "sg:phone":"+34 923 40 08 03",
    "sg:postcode":"37700",
    "sg:province":"Salamanca",
    "wof:name":"Fricarne-7 S.l.",
    "wof:placetype":"venue"
},
  "geometry": {"coordinates":[-5.7569189072,40.3869400024],"type":"Point"}
}