{
  "type": "Feature",
  "properties": {
    "addr:full":"Calle de Comuneros De Castilla, 24 Madrid Madrid 28019",
    "addr:housenumber":"24",
    "addr:postcode":"madrid;28019",
    "addr:street":"Calle De Comuneros De Castilla",
    "iso:country":"ES",
    "sg:address":"Calle de Comuneros De Castilla, 24",
    "sg:city":"Madrid",
    "sg:orig_category":"Ebanister\u00cda",
    "sg:phone":"+34 914 71 80 66",
    "sg:postcode":"28019",
    "sg:province":"Madrid",
    "wof:name":"Abade Sanchez Miguel Angel",
    "wof:placetype":"venue"
},
  "geometry": {"coordinates":[-3.720664,40.395908],"type":"Point"}
}