{
  "type": "Feature",
  "properties": {
    "addr:full":"C/ Diego Pascual Oliver, 34 Elche Alicante 03206",
    "addr:housenumber":"34",
    "addr:postcode":"03206",
    "addr:street":"C / Diego Pascual Oliver",
    "iso:country":"ES",
    "sg:address":"C/ Diego Pascual Oliver, 34",
    "sg:city":"Elche",
    "sg:orig_category":"Revestimiento De Suelos Industriales",
    "sg:phone":"+34 965 43 51 44",
    "sg:postcode":"03206",
    "sg:province":"Alicante",
    "wof:name":"Fratasados Elite S L",
    "wof:placetype":"venue"
},
  "geometry": {"coordinates":[-0.7145389915,38.2769470215],"type":"Point"}
}