{
  "type": "Feature",
  "properties": {
    "iso:country":"ES",
    "sg:address":"Carr Verge De Montserrat, 9",
    "sg:city":"Ponts",
    "sg:orig_category":"Transportes Por V\u00cdas Navegables",
    "sg:phone":"+34 973 46 03 97",
    "sg:postcode":"25740",
    "sg:province":"Lleida",
    "wof:name":"Seponts S.l.",
    "wof:placetype":"venue"
},
  "geometry": {"coordinates":[1.1850420237,41.9170303345],"type":"Point"}
}