{
  "type": "Feature",
  "properties": {
    "iso:country":"ES",
    "sg:address":"Calle de Sagra, 1",
    "sg:city":"Torrent",
    "sg:orig_category":"Quincaller\u00cda (al Por Menor)",
    "sg:phone":"+34 961 55 13 24",
    "sg:postcode":"46900",
    "sg:province":"Valencia",
    "wof:name":"Luis Lorente Royo Y Otros Cdad.",
    "wof:placetype":"venue"
},
  "geometry": {"coordinates":[-0.4649389982,39.4370613098],"type":"Point"}
}