{
  "type": "Feature",
  "properties": {
    "iso:country":"ES",
    "sg:address":"Calle de Santa Ana, 13",
    "sg:city":"Madridejos",
    "sg:orig_category":"Cl\u00cdnicas Dentales",
    "sg:phone":"+34 925 46 24 18",
    "sg:postcode":"45710",
    "sg:province":"Toledo",
    "wof:name":"Clinicas Odontologicas Saludent S.l.",
    "wof:placetype":"venue"
},
  "geometry": {"coordinates":[-3.5248761177,39.4669914246],"type":"Point"}
}