{
  "type": "Feature",
  "properties": {
    "addr:full":"Luga Llano De Las Mozas, 5 Tenoya Las Palmas 35018",
    "addr:housenumber":"5",
    "addr:postcode":"35018",
    "addr:street":"Mozas;Las Palmas",
    "iso:country":"ES",
    "sg:address":"Luga Llano De Las Mozas, 5",
    "sg:city":"Tenoya",
    "sg:orig_category":"Asociaciones Humanitarias, De Cooperaci\u00d3n, De Acci\u00d3n Social",
    "sg:phone":"+34 928 67 63 61",
    "sg:postcode":"35018",
    "sg:province":"Las Palmas",
    "wof:name":"Centro Reto La Esperanza",
    "wof:placetype":"venue"
},
  "geometry": {"coordinates":[-15.4784650803,28.0919818878],"type":"Point"}
}