{
  "type": "Feature",
  "properties": {
    "iso:country":"ES",
    "sg:address":"Ctra N-iv Madrid-cadiz, Km. 0117,0",
    "sg:city":"Madridejos",
    "sg:orig_category":"Art\u00cdculos De Madera (fabricaci\u00d3n Y Al Por Mayor)",
    "sg:phone":"+34 925 46 20 35",
    "sg:postcode":"45710",
    "sg:province":"Toledo",
    "wof:name":"Muebles Mofer S.l.",
    "wof:placetype":"venue"
},
  "geometry": {"coordinates":[-3.5295538902,39.4659385681],"type":"Point"}
}