{
  "type": "Feature",
  "properties": {
    "addr:full":"Calle de Antonio Gala, 35 Palacios Y Villafranca Sevilla 41720",
    "addr:housenumber":"35",
    "addr:postcode":"41720",
    "addr:street":"Calle De Antonio Gala",
    "iso:country":"ES",
    "sg:address":"Calle de Antonio Gala, 35",
    "sg:city":"Palacios Y Villafranca",
    "sg:orig_category":"Carnicer\u00cdas, Carnicer\u00cdas",
    "sg:phone":"+34 955 81 57 81",
    "sg:postcode":"41720",
    "sg:province":"Sevilla",
    "wof:name":"Ramos San Millan Jose Antonio",
    "wof:placetype":"venue"
},
  "geometry": {"coordinates":[-5.9308400154,37.1584892273],"type":"Point"}
}