{
  "type": "Feature",
  "properties": {
    "addr:full":"Carr Vila Antonia, 9 Lleida Lleida 25007",
    "addr:housenumber":"9",
    "addr:postcode":"25007",
    "addr:street":"Carr Vila Antonia",
    "iso:country":"ES",
    "sg:address":"Carr Vila Antonia, 9",
    "sg:city":"Lleida",
    "sg:orig_category":"Imprenta",
    "sg:phone":"+34 973 23 55 31",
    "sg:postcode":"25007",
    "sg:province":"Lleida",
    "sg:website":"www.astrea.es/ifregola",
    "wof:name":"Fregola Navarro Ignasi",
    "wof:placetype":"venue"
},
  "geometry": {"coordinates":[0.6320090294,41.6176795959],"type":"Point"}
}