{
  "type": "Feature",
  "properties": {
    "addr:full":"C/ Amilcar Barca, 5 Elche Alicante 03204",
    "addr:housenumber":"5",
    "addr:postcode":"03204",
    "addr:street":"C / Amilcar Barca",
    "iso:country":"ES",
    "sg:address":"C/ Amilcar Barca, 5",
    "sg:city":"Elche",
    "sg:orig_category":"Reposter\u00cdas",
    "sg:phone":"+34 966 63 23 93",
    "sg:postcode":"03204",
    "sg:province":"Alicante",
    "wof:name":"Mavepan S.l.",
    "wof:placetype":"venue"
},
  "geometry": {"coordinates":[-0.702057004,38.2537918091],"type":"Point"}
}