{
  "type": "Feature",
  "properties": {
    "iso:country":"ES",
    "sg:address":"Av Mare Deu De Montserrat, 74",
    "sg:city":"Barcelona",
    "sg:orig_category":"Carnicer\u00cdas, Carnicer\u00cdas",
    "sg:phone":"+34 932 10 60 51",
    "sg:postcode":"08024",
    "sg:province":"Barcelona",
    "wof:name":"Capdevila Su\u00f1er Pedro",
    "wof:placetype":"venue"
},
  "geometry": {"coordinates":[2.1652290821,41.414680481],"type":"Point"}
}