{
  "type": "Feature",
  "properties": {
    "addr:full":"Calle de Casas Blancas, S/n Mecina-bombaron Granada 18450",
    "addr:housenumber":"s / n",
    "addr:postcode":"18450",
    "addr:street":"Calle De Casas Blancas",
    "iso:country":"ES",
    "sg:address":"Calle de Casas Blancas, S/n",
    "sg:city":"Mecina-bombaron",
    "sg:orig_category":"Organismos De Turismo",
    "sg:phone":"+34 958 85 13 70",
    "sg:postcode":"18450",
    "sg:province":"Granada",
    "sg:website":"www.grancapitan.org",
    "wof:name":"Vacaciones Y Ocio Gran Capitan S.l.",
    "wof:placetype":"venue"
},
  "geometry": {"coordinates":[-3.1555531025,36.9807853699],"type":"Point"}
}