{
  "type": "Feature",
  "properties": {
    "iso:country":"ES",
    "sg:address":"Carrer de Emigrant, 28",
    "sg:city":"Hospitalet Llobregat",
    "sg:orig_category":"Alimentaci\u00d3n General (al Por Menor)",
    "sg:phone":"+34 932 61 16 41",
    "sg:postcode":"08906",
    "sg:province":"Barcelona",
    "wof:name":"Lopez Becerra Maruja",
    "wof:placetype":"venue"
},
  "geometry": {"coordinates":[2.0878739357,41.3651199341],"type":"Point"}
}