{
  "type": "Feature",
  "properties": {
    "iso:country":"ES",
    "sg:address":"Carrer de Francesc Moragas, 1",
    "sg:city":"S. Cugat Valles",
    "sg:orig_category":"Bancos",
    "sg:phone":"+34 936 74 03 99",
    "sg:postcode":"08172",
    "sg:province":"Barcelona",
    "wof:name":"Banco Vitalicio De Espa\u00d1a C.a.",
    "wof:placetype":"venue"
},
  "geometry": {"coordinates":[2.0823850632,41.471282959],"type":"Point"}
}