{
  "type": "Feature",
  "properties": {
    "iso:country":"ES",
    "sg:address":"Carrer de Murcia, 46",
    "sg:city":"Barcelona",
    "sg:orig_category":"Delegados, Agentes De Tr\u00c1nsito, Auxiliares De Transporte Internacional",
    "sg:phone":"+34 933 49 32 83",
    "sg:postcode":"08027",
    "sg:province":"Barcelona",
    "wof:name":"Sichar Salamero Jorge",
    "wof:placetype":"venue"
},
  "geometry": {"coordinates":[2.1899549961,41.4159202576],"type":"Point"}
}