{
  "type": "Feature",
  "properties": {
    "iso:country":"ES",
    "sg:address":"Grup Murueta Torre Auzunea, 5 H",
    "sg:city":"Durango",
    "sg:orig_category":"Promotores Constructores",
    "sg:phone":"+34 944 66 83 49",
    "sg:postcode":"48200",
    "sg:province":"Vizcaya",
    "wof:name":"Construcciones Cengotitabengoa S.l.",
    "wof:placetype":"venue"
},
  "geometry": {"coordinates":[-2.6117420197,43.194644928],"type":"Point"}
}