{
  "type": "Feature",
  "properties": {
    "addr:full":"Calle de Neptuno, 3 Granada Granada 18004",
    "addr:housenumber":"3",
    "addr:postcode":"18004",
    "addr:street":"Calle De Neptuno",
    "iso:country":"ES",
    "sg:address":"Calle de Neptuno, 3",
    "sg:city":"Granada",
    "sg:orig_category":"Panader\u00cdas, Panader\u00cdas",
    "sg:phone":"+34 958 26 47 58",
    "sg:postcode":"18004",
    "sg:province":"Granada",
    "wof:name":"Portellano Garcia Jorge",
    "wof:placetype":"venue"
},
  "geometry": {"coordinates":[-3.6063230038,37.1697425842],"type":"Point"}
}