{
  "type": "Feature",
  "properties": {
    "iso:country":"ES",
    "sg:address":"Calle de Portugal, 11",
    "sg:city":"Iscar",
    "sg:orig_category":"Florister\u00cdas",
    "sg:phone":"+34 983 61 11 98",
    "sg:postcode":"47420",
    "sg:province":"Valladolid",
    "wof:name":"Merlo De La Fuente Monica",
    "wof:placetype":"venue"
},
  "geometry": {"coordinates":[-4.5294542313,41.3645553589],"type":"Point"}
}