{
  "type": "Feature",
  "properties": {
    "addr:full":"Av Princep D'asturies, 1 Barcelona Barcelona 08012",
    "addr:housenumber":"1",
    "addr:postcode":"08012",
    "addr:street":"Av Princep D'Asturies",
    "iso:country":"ES",
    "sg:address":"Av Princep D'asturies, 1",
    "sg:city":"Barcelona",
    "sg:orig_category":"M\u00c9dicos: Cirug\u00cda Vascular",
    "sg:phone":"+34 932 37 42 58",
    "sg:postcode":"08012",
    "sg:province":"Barcelona",
    "wof:name":"Palou Monzo Jaime",
    "wof:placetype":"venue"
},
  "geometry": {"coordinates":[2.1511793137,41.401309967],"type":"Point"}
}