{
  "type": "Feature",
  "properties": {
    "iso:country":"ES",
    "sg:address":"Calle de Kareaga Behekoa, 24",
    "sg:city":"Basauri",
    "sg:orig_category":"Suministros Para Carrocer\u00cdas",
    "sg:phone":"+34 944 49 90 06",
    "sg:postcode":"48970",
    "sg:province":"Vizcaya",
    "wof:name":"Rufino Barrio Trece\u00f1o",
    "wof:placetype":"venue"
},
  "geometry": {"coordinates":[-2.893529892,43.2381820679],"type":"Point"}
}