{
  "type": "Feature",
  "properties": {
    "iso:country":"ES",
    "sg:address":"Calle de Puerto De Urkiola, 2",
    "sg:city":"Vitoria-gasteiz",
    "sg:orig_category":"Venta, Instalaci\u00d3n De Cocinas",
    "sg:phone":"+34 945 25 03 30",
    "sg:postcode":"01013",
    "sg:province":"\u00c1lava",
    "wof:name":"Roco Moreno Manuel",
    "wof:placetype":"venue"
},
  "geometry": {"coordinates":[-2.6702070236,42.8607978821],"type":"Point"}
}