{
  "type": "Feature",
  "properties": {
    "addr:full":"Calle de Agustin Varo, 11 Barbate C\u00e1diz 11160",
    "addr:housenumber":"11",
    "addr:postcode":"11160",
    "addr:street":"Calle De Agustin Varo",
    "iso:country":"ES",
    "sg:address":"Calle de Agustin Varo, 11",
    "sg:city":"Barbate",
    "sg:orig_category":"Florister\u00cdas",
    "sg:phone":"+34 956 43 48 98",
    "sg:postcode":"11160",
    "sg:province":"C\u00e1diz",
    "wof:name":"Benitez Varo Inmaculada",
    "wof:placetype":"venue"
},
  "geometry": {"coordinates":[-5.9205126762,36.1904220581],"type":"Point"}
}