{
  "type": "Feature",
  "properties": {
    "iso:country":"ES",
    "sg:address":"Calle de Cultura, 7",
    "sg:city":"Molina Segura",
    "sg:orig_category":"Estancos",
    "sg:phone":"+34 968 61 35 20",
    "sg:postcode":"30500",
    "sg:province":"Murcia",
    "wof:name":"Moreno Garcia Maximino",
    "wof:placetype":"venue"
},
  "geometry": {"coordinates":[-1.2111954689,38.0511703491],"type":"Point"}
}