{
  "type": "Feature",
  "properties": {
    "iso:country":"ES",
    "sg:address":"Calle de Pablo Morillo, 2",
    "sg:city":"Zamora",
    "sg:orig_category":"Agencias Y Asesores De Publicidad",
    "sg:phone":"+34 980 51 44 88",
    "sg:postcode":"49013",
    "sg:province":"Zamora",
    "wof:name":"Chao Bordell S.l",
    "wof:placetype":"venue"
},
  "geometry": {"coordinates":[-5.7417449951,41.50756073],"type":"Point"}
}