{
  "type": "Feature",
  "properties": {
    "addr:full":"Pase Maritimo Pablo Ruiz Picasso, 11 Malaga M\u00e1laga 29016",
    "addr:housenumber":"11",
    "addr:postcode":"29016",
    "addr:street":"Malaga Ma\u0301Laga",
    "iso:country":"ES",
    "sg:address":"Pase Maritimo Pablo Ruiz Picasso, 11",
    "sg:city":"Malaga",
    "sg:orig_category":"Caf\u00c9s, Bares, Cervecer\u00cdas",
    "sg:phone":"+34 952 22 97 71",
    "sg:postcode":"29016",
    "sg:province":"M\u00e1laga",
    "wof:name":"Mowbray Rodriguez Enrique",
    "wof:placetype":"venue"
},
  "geometry": {"coordinates":[-4.4063138962,36.7200164795],"type":"Point"}
}