{
  "type": "Feature",
  "properties": {
    "addr:full":"Rua Hersa, 2 Burgo A Coru\u00f1a 15670",
    "addr:housenumber":"2",
    "addr:postcode":"15670",
    "addr:street":"Rua Hersa;A Corun\u0303A",
    "iso:country":"ES",
    "sg:address":"Rua Hersa, 2",
    "sg:city":"Burgo",
    "sg:orig_category":"Frutas, Legumbres Frescas Y Tempranas (al Por Menor)",
    "sg:phone":"+34 981 66 66 06",
    "sg:postcode":"15670",
    "sg:province":"A Coru\u00f1a",
    "wof:name":"Verduras Frescas S.l.",
    "wof:placetype":"venue"
},
  "geometry": {"coordinates":[-8.3666353226,43.3148345947],"type":"Point"}
}