{
  "type": "Feature",
  "properties": {
    "iso:country":"ES",
    "sg:address":"Calle de Estrella, S/n",
    "sg:city":"Gijon",
    "sg:orig_category":"Asociaciones, Organismos Culturales Y Socioeducativos",
    "sg:phone":"+34 985 32 03 48",
    "sg:postcode":"33212",
    "sg:province":"Asturias",
    "wof:name":"Fundacion Municipal De Cultura Educacion Y Universidad Popular",
    "wof:placetype":"venue"
},
  "geometry": {"coordinates":[-5.6892838478,43.5412330627],"type":"Point"}
}