{
  "type": "Feature",
  "properties": {
    "iso:country":"ES",
    "sg:address":"Carr Sahara, Del, S/n",
    "sg:city":"Mao",
    "sg:orig_category":"Equipo Y Material Deportivo Y De Actividades Invernales Y De Monta\u00d1a",
    "sg:phone":"+34 971 36 25 35",
    "sg:postcode":"07703",
    "sg:province":"Islas Baleares",
    "wof:name":"Centro Deportivo Els Jardins S.l.",
    "wof:placetype":"venue"
},
  "geometry": {"coordinates":[4.265625,39.8903694153],"type":"Point"}
}