{
  "type": "Feature",
  "properties": {
    "addr:full":"Carrer de Occident, 50 Hospitalet Llobregat Barcelona 08904",
    "addr:housenumber":"50",
    "addr:postcode":"08904",
    "addr:street":"Carrer De Occident",
    "iso:country":"ES",
    "sg:address":"Carrer de Occident, 50",
    "sg:city":"Hospitalet Llobregat",
    "sg:orig_category":"Caf\u00c9s, Bares, Cervecer\u00cdas",
    "sg:phone":"+34 934 49 89 24",
    "sg:postcode":"08904",
    "sg:province":"Barcelona",
    "wof:name":"Alguero Grau Fernando",
    "wof:placetype":"venue"
},
  "geometry": {"coordinates":[2.1178340912,41.3739967346],"type":"Point"}
}