{
  "type": "Feature",
  "properties": {
    "iso:country":"ES",
    "sg:address":"Calle de Nueva, S/n",
    "sg:city":"Zaratan",
    "sg:orig_category":"Centros De Educaci\u00d3n Especial",
    "sg:phone":"+34 983 34 36 93",
    "sg:postcode":"47610",
    "sg:province":"Valladolid",
    "wof:name":"Colegio Publico Rural Agrupado De Villanubla",
    "wof:placetype":"venue"
},
  "geometry": {"coordinates":[-4.7820539474,41.6599388123],"type":"Point"}
}