{
  "type": "Feature",
  "properties": {
    "iso:country":"ES",
    "sg:address":"Calle de Nueva De San Anton, 14",
    "sg:city":"Granada",
    "sg:orig_category":"Abogados",
    "sg:phone":"+34 958 25 21 07",
    "sg:postcode":"18005",
    "sg:province":"Granada",
    "wof:name":"Oliveros Manzano Alberto",
    "wof:placetype":"venue"
},
  "geometry": {"coordinates":[-3.6008300781,37.1709022522],"type":"Point"}
}