{
  "type": "Feature",
  "properties": {
    "iso:country":"ES",
    "sg:address":"Carr Catalunya, 6",
    "sg:city":"Camprodon",
    "sg:orig_category":"Platos Preparados Refrigerados (fabricaci\u00d3n, Al Por Mayor)",
    "sg:phone":"+34 972 74 10 32",
    "sg:postcode":"17867",
    "sg:province":"Girona",
    "wof:name":"Guerrero Baena Dolores",
    "wof:placetype":"venue"
},
  "geometry": {"coordinates":[2.3654010296,42.3111228943],"type":"Point"}
}