{
  "type": "Feature",
  "properties": {
    "iso:country":"ES",
    "sg:address":"Calle de San Antonio De Padua, 28",
    "sg:city":"Madrid",
    "sg:orig_category":"Molduras, Junquillos, Listones Y Molduras Perforadas",
    "sg:phone":"+34 917 92 28 85",
    "sg:postcode":"28026",
    "sg:province":"Madrid",
    "wof:name":"Feito Fernandez Jaime",
    "wof:placetype":"venue"
},
  "geometry": {"coordinates":[-3.7016859055,40.3860702515],"type":"Point"}
}