{
  "type": "Feature",
  "properties": {
    "iso:country":"ES",
    "sg:address":"Pl Ajuntament (l'), 3",
    "sg:city":"Banyeres Mariola",
    "sg:orig_category":"Internados & Ense\u00d1anza Privada",
    "sg:phone":"+34 965 56 65 65",
    "sg:postcode":"03450",
    "sg:province":"Alicante",
    "wof:name":"Fundacion Ribera",
    "wof:placetype":"venue"
},
  "geometry": {"coordinates":[-0.6566650271,38.7166061401],"type":"Point"}
}