{
  "type": "Feature",
  "properties": {
    "addr:full":"Eusko Gudarien Kalea, 48 Orio Guip\u00f9zcoa 20810",
    "addr:housenumber":"48",
    "addr:postcode":"20810",
    "addr:street":"Eusko Gudarien Kalea;Guipu\u0300Zcoa",
    "iso:country":"ES",
    "sg:address":"Eusko Gudarien Kalea, 48",
    "sg:city":"Orio",
    "sg:orig_category":"Bebidas",
    "sg:phone":"+34 943 83 03 86",
    "sg:postcode":"20810",
    "sg:province":"Guip\u00f9zcoa",
    "wof:name":"Bodegas Errasti,  S.l.",
    "wof:placetype":"venue"
},
  "geometry": {"coordinates":[-2.1270968914,43.2793235779],"type":"Point"}
}