{
  "type": "Feature",
  "properties": {
    "addr:full":"Calle de Porvenir, 43 Zaragoza Zaragoza 50006",
    "addr:housenumber":"43",
    "addr:postcode":"50006",
    "addr:street":"Calle De Porvenir",
    "iso:country":"ES",
    "sg:address":"Calle de Porvenir, 43",
    "sg:city":"Zaragoza",
    "sg:orig_category":"Arquitectos",
    "sg:phone":"+34 976 25 22 70",
    "sg:postcode":"50006",
    "sg:province":"Zaragoza",
    "wof:name":"Navarro Algarate Jose Antonio",
    "wof:placetype":"venue"
},
  "geometry": {"coordinates":[-0.8898590207,41.6396026611],"type":"Point"}
}