{
  "type": "Feature",
  "properties": {
    "iso:country":"ES",
    "sg:address":"Calle de Huerta Ma\u00d1ana, 18",
    "sg:city":"Campo Criptana",
    "sg:orig_category":"Bazares, Art\u00cdculos De Limpieza Y De Cocina (al Por Menor)",
    "sg:phone":"+34 926 56 40 62",
    "sg:postcode":"13610",
    "sg:province":"Ciudad Real",
    "wof:name":"Feldiorean  Constantin Liviu",
    "wof:placetype":"venue"
},
  "geometry": {"coordinates":[-3.1355888844,39.4030418396],"type":"Point"}
}