{
  "type": "Feature",
  "properties": {
    "addr:full":"Hilarion Eslava, 1 Iru\u00f1a Navarra 31001",
    "addr:housenumber":"1",
    "addr:postcode":"31001",
    "addr:street":"Eslava",
    "iso:country":"ES",
    "sg:address":"Hilarion Eslava, 1",
    "sg:city":"Iru\u00f1a",
    "sg:orig_category":"Comit\u00c9s De Organizaci\u00d3n De Exposiciones, Ferias, Salones",
    "sg:phone":"+34 948 22 89 19",
    "sg:postcode":"31001",
    "sg:province":"Navarra",
    "wof:name":"Oficina De Congresos De Pamplona Convencion Bureau S.a.",
    "wof:placetype":"venue"
},
  "geometry": {"coordinates":[-1.6468470097,42.8171463013],"type":"Point"}
}