{
  "type": "Feature",
  "properties": {
    "addr:full":"Calle de Medico Antonio Pavia, 26 Aspe Alicante 03680",
    "addr:housenumber":"26",
    "addr:postcode":"03680",
    "addr:street":"Calle De Medico Antonio Pavia",
    "iso:country":"ES",
    "sg:address":"Calle de Medico Antonio Pavia, 26",
    "sg:city":"Aspe",
    "sg:orig_category":"Peluqueros: De Se\u00d1oras",
    "sg:phone":"+34 965 49 38 83",
    "sg:postcode":"03680",
    "sg:province":"Alicante",
    "wof:name":"Noeri Peluqueria S.l.",
    "wof:placetype":"venue"
},
  "geometry": {"coordinates":[-0.7662220001,38.3473396301],"type":"Point"}
}