{
  "type": "Feature",
  "properties": {
    "addr:full":"Carrer de Baix, 8 Cardedeu Barcelona 08440",
    "addr:housenumber":"8",
    "addr:postcode":"08440",
    "addr:street":"Carrer De Baix",
    "iso:country":"ES",
    "sg:address":"Carrer de Baix, 8",
    "sg:city":"Cardedeu",
    "sg:orig_category":"Carnicer\u00cdas, Carnicer\u00cdas",
    "sg:phone":"+34 938 46 10 42",
    "sg:postcode":"08440",
    "sg:province":"Barcelona",
    "wof:name":"Carbonell Vilabella Pedro",
    "wof:placetype":"venue"
},
  "geometry": {"coordinates":[2.3555281162,41.6380195618],"type":"Point"}
}