{
  "type": "Feature",
  "properties": {
    "iso:country":"ES",
    "sg:address":"Calle de Carretera, Km. 0504,0",
    "sg:city":"Fornillos Aliste",
    "sg:orig_category":"Negocio De Materiales De Construcci\u00d3n",
    "sg:phone":"+34 980 68 80 70",
    "sg:postcode":"49513",
    "sg:province":"Zamora",
    "wof:name":"Almacenes Volga S.l.",
    "wof:placetype":"venue"
},
  "geometry": {"coordinates":[-5.7462787628,41.5033454895],"type":"Point"}
}