{
  "type": "Feature",
  "properties": {
    "iso:country":"ES",
    "sg:address":"Pl Palacio, 1",
    "sg:city":"Elche",
    "sg:orig_category":"Asesor\u00cda Sobre Comunicaci\u00d3n De Empresas",
    "sg:phone":"+34 966 61 50 40",
    "sg:postcode":"03202",
    "sg:province":"Alicante",
    "wof:name":"Grupo Asesor Ros S. A.",
    "wof:placetype":"venue"
},
  "geometry": {"coordinates":[-0.6488505006,38.3253250122],"type":"Point"}
}