{
  "type": "Feature",
  "properties": {
    "addr:full":"Calle de Fuente Del Real, 45 Gijon Asturias 33209",
    "addr:housenumber":"45",
    "addr:postcode":"33209",
    "addr:street":"Calle De Fuente Del Real",
    "iso:country":"ES",
    "sg:address":"Calle de Fuente Del Real, 45",
    "sg:city":"Gijon",
    "sg:orig_category":"Ense\u00d1anza, Formaci\u00d3n Profesional: Aprendizaje",
    "sg:phone":"+34 985 99 06 61",
    "sg:postcode":"33209",
    "sg:province":"Asturias",
    "wof:name":"Elban Formacion S.l.l.",
    "wof:placetype":"venue"
},
  "geometry": {"coordinates":[-5.6594791412,43.5316772461],"type":"Point"}
}