{
  "type": "Feature",
  "properties": {
    "iso:country":"ES",
    "sg:address":"Calle de Langileria, 112",
    "sg:city":"Lamiako",
    "sg:orig_category":"Carnicer\u00cdas, Carnicer\u00cdas",
    "sg:phone":"+34 944 63 61 16",
    "sg:postcode":"48940",
    "sg:province":"Vizcaya",
    "wof:name":"Astola Lejona Juan Ignacio",
    "wof:placetype":"venue"
},
  "geometry": {"coordinates":[-3.0056922436,43.324054718],"type":"Point"}
}