{
  "type": "Feature",
  "properties": {
    "iso:country":"ES",
    "sg:address":"Carr Comer\u00c7, 38",
    "sg:city":"Lleida",
    "sg:orig_category":"Asesor\u00cdas Y Estudios Financieros",
    "sg:phone":"+34 973 24 82 92",
    "sg:postcode":"25007",
    "sg:province":"Lleida",
    "wof:name":"Embalumar Catalana S.l.",
    "wof:placetype":"venue"
},
  "geometry": {"coordinates":[0.6314849854,41.618221283],"type":"Point"}
}