{
  "type": "Feature",
  "properties": {
    "iso:country":"ES",
    "sg:address":"Calle de Tijarafe, 1",
    "sg:city":"Santa Ursula",
    "sg:orig_category":"Peluquer\u00cdas, Peluquer\u00cda Mixta",
    "sg:phone":"+34 922 30 46 09",
    "sg:postcode":"38390",
    "sg:province":"Santa Cruz De Tenerife",
    "wof:name":"C.b. Ilusion Peluqueras",
    "wof:placetype":"venue"
},
  "geometry": {"coordinates":[-16.4924697876,28.4250907898],"type":"Point"}
}