{
  "type": "Feature",
  "properties": {
    "addr:full":"Carr Ciudad Dario, 29 Alcudia Valencia 46250",
    "addr:housenumber":"29",
    "addr:postcode":"46250",
    "addr:street":"Carr Ciudad Dario",
    "iso:country":"ES",
    "sg:address":"Carr Ciudad Dario, 29",
    "sg:city":"Alcudia",
    "sg:orig_category":"Electricidad: Instaladores",
    "sg:phone":"+34 962 54 18 10",
    "sg:postcode":"46250",
    "sg:province":"Valencia",
    "wof:name":"Automatizacion Electrica Y Neumatica S.l.",
    "wof:placetype":"venue"
},
  "geometry": {"coordinates":[-0.5070289969,39.1940689087],"type":"Point"}
}