{
  "type": "Feature",
  "properties": {
    "addr:full":"Calle de San Jose De Calasanz, 9 Valencia Valencia 46008",
    "addr:housenumber":"9",
    "addr:postcode":"46008",
    "addr:street":"Calle De San;De Calasanz",
    "iso:country":"ES",
    "sg:address":"Calle de San Jose De Calasanz, 9",
    "sg:city":"Valencia",
    "sg:orig_category":"Comercio De Cuadros, L\u00c1minas Y Reproducciones De Obras De Arte",
    "sg:phone":"+34 963 82 19 14",
    "sg:postcode":"46008",
    "sg:province":"Valencia",
    "wof:name":"Betoret Kalfon Delfina",
    "wof:placetype":"venue"
},
  "geometry": {"coordinates":[-0.3876770139,39.4664344788],"type":"Point"}
}