{
  "type": "Feature",
  "properties": {
    "iso:country":"ES",
    "sg:address":"Rial Sa Clavella, 54",
    "sg:city":"Arenys Mar",
    "sg:orig_category":"Publicidad (soportes Y Gesti\u00d3n)",
    "sg:phone":"+34 937 95 80 62",
    "sg:postcode":"08350",
    "sg:province":"Barcelona",
    "wof:name":"Ample 24 Sccl.",
    "wof:placetype":"venue"
},
  "geometry": {"coordinates":[2.548217535,41.5804862976],"type":"Point"}
}