{
  "type": "Feature",
  "properties": {
    "addr:full":"Calle de San Jose, 5 Ubeda Ja\u00e9n 23400",
    "addr:housenumber":"5",
    "addr:postcode":"23400",
    "addr:street":"Calle De San Jose;Jae\u0301N",
    "iso:country":"ES",
    "sg:address":"Calle de San Jose, 5",
    "sg:city":"Ubeda",
    "sg:orig_category":"Pod\u00d3logos: Pedicuros",
    "sg:phone":"+34 953 75 67 78",
    "sg:postcode":"23400",
    "sg:province":"Ja\u00e9n",
    "wof:name":"Garrido Millan Petra",
    "wof:placetype":"venue"
},
  "geometry": {"coordinates":[-3.3782451153,38.0124015808],"type":"Point"}
}