{
  "type": "Feature",
  "properties": {
    "iso:country":"ES",
    "sg:address":"Avda Blas Infante, 20",
    "sg:city":"Coria Rio",
    "sg:orig_category":"Centros Empresariales",
    "sg:phone":"+34 954 77 62 89",
    "sg:postcode":"41100",
    "sg:province":"Sevilla",
    "wof:name":"Calero Consultores S.c.",
    "wof:placetype":"venue"
},
  "geometry": {"coordinates":[-6.057929039,37.2783889771],"type":"Point"}
}