{
  "type": "Feature",
  "properties": {
    "iso:country":"ES",
    "sg:address":"Carrer de Ramon J. Sender, 40",
    "sg:city":"Reus",
    "sg:orig_category":"Cajas De Ahorro",
    "sg:phone":"+34 977 77 25 83",
    "sg:postcode":"43204",
    "sg:province":"Tarragona",
    "wof:name":"Ruralcaja",
    "wof:placetype":"venue"
},
  "geometry": {"coordinates":[1.1123360395,41.1499710083],"type":"Point"}
}