{
  "type": "Feature",
  "properties": {
    "iso:country":"ES",
    "sg:address":"Calle de San Pedro, 2",
    "sg:city":"Caceres",
    "sg:orig_category":"Art\u00cdculos De Regalo (al Por Menor)",
    "sg:phone":"+34 927 22 31 93",
    "sg:postcode":"10003",
    "sg:province":"C\u00e1ceres",
    "wof:name":"Montesino Fernandez Antonio",
    "wof:placetype":"venue"
},
  "geometry": {"coordinates":[-6.3736491203,39.4734992981],"type":"Point"}
}