{
  "type": "Feature",
  "properties": {
    "iso:country":"ES",
    "sg:address":"Calle de Real Cia.gip.caracas, 11",
    "sg:city":"Donostia-san Sebastian",
    "sg:orig_category":"Inmobiliaria (agencias)",
    "sg:phone":"+34 943 47 43 93",
    "sg:postcode":"20011",
    "sg:province":"Guip\u00f9zcoa",
    "wof:name":"Perdiguero Otxoa Patxi Joseba",
    "wof:placetype":"venue"
},
  "geometry": {"coordinates":[-1.9716459513,43.3047294617],"type":"Point"}
}