{
  "type": "Feature",
  "properties": {
    "iso:country":"ES",
    "sg:address":"Avda Reyes Catolicos, S/n",
    "sg:city":"Chiclana De La Frontera",
    "sg:orig_category":"Cojinetes De Bolas, Agujas Y Rodillos (fabricaci\u00d3n, Al Por Mayor)",
    "sg:phone":"+34 956 53 58 48",
    "sg:postcode":"11130",
    "sg:province":"C\u00e1diz",
    "wof:name":"Rodriguez Capitan Isabel",
    "wof:placetype":"venue"
},
  "geometry": {"coordinates":[-6.1430988312,36.4142036438],"type":"Point"}
}