{
  "type": "Feature",
  "properties": {
    "addr:full":"Calle de Francisco Aritio, 117 Guadalajara Guadalajara 19004",
    "addr:housenumber":"117",
    "addr:postcode":"19004",
    "addr:street":"Calle De Francisco Aritio",
    "iso:country":"ES",
    "sg:address":"Calle de Francisco Aritio, 117",
    "sg:city":"Guadalajara",
    "sg:orig_category":"Fabricaci\u00d3n De Distribuidores Autom\u00c1ticos",
    "sg:phone":"+34 949 20 32 13",
    "sg:postcode":"19004",
    "sg:province":"Guadalajara",
    "sg:website":"jmrvending.com",
    "wof:name":"Mateo Ruiz Juan",
    "wof:placetype":"venue"
},
  "geometry": {"coordinates":[-3.197865963,40.6256599426],"type":"Point"}
}