{
  "type": "Feature",
  "properties": {
    "addr:full":"Avda Constitucion (la), 30 Segovia Segovia 40005",
    "addr:housenumber":"30",
    "addr:postcode":"40005",
    "addr:street":"Avda Constitucion La",
    "iso:country":"ES",
    "sg:address":"Avda Constitucion (la), 30",
    "sg:city":"Segovia",
    "sg:orig_category":"Cajas De Ahorro",
    "sg:phone":"+34 921 42 11 37",
    "sg:postcode":"40005",
    "sg:province":"Segovia",
    "sg:website":"www.cajasegovia.es",
    "wof:name":"Caja De Ahorros Y Monte De Piedad De Segovia",
    "wof:placetype":"venue"
},
  "geometry": {"coordinates":[-4.1122059822,40.9390563965],"type":"Point"}
}