{
  "type": "Feature",
  "properties": {
    "addr:full":"Calle de Pintor Barjola, S/n Almendralejo Badajoz 06200",
    "addr:housenumber":"s / n",
    "addr:postcode":"06200",
    "addr:street":"Calle De Pintor Barjola",
    "iso:country":"ES",
    "sg:address":"Calle de Pintor Barjola, S/n",
    "sg:city":"Almendralejo",
    "sg:orig_category":"Cristaler\u00cda: Suministros",
    "sg:phone":"+34 924 66 37 85",
    "sg:postcode":"06200",
    "sg:province":"Badajoz",
    "wof:name":"V.juvasa S.l.",
    "wof:placetype":"venue"
},
  "geometry": {"coordinates":[-6.4068241119,38.6845092773],"type":"Point"}
}