{
  "type": "Feature",
  "properties": {
    "iso:country":"ES",
    "sg:address":"Carrer de Llauradors, S/n",
    "sg:city":"Campello",
    "sg:orig_category":"Empresas De Carpinter\u00cda Met\u00c1lica",
    "sg:phone":"+34 965 63 41 52",
    "sg:postcode":"03560",
    "sg:province":"Alicante",
    "wof:name":"Forjas Y Carpinterias S.l.",
    "wof:placetype":"venue"
},
  "geometry": {"coordinates":[-0.403598994,38.4277610779],"type":"Point"}
}