{
  "type": "Feature",
  "properties": {
    "addr:full":"Cami Riera, Km. 0007,0 Riudarenes Girona 17421",
    "addr:postcode":"17421",
    "addr:street":"Riera Km. 0007,0",
    "iso:country":"ES",
    "sg:address":"Cami Riera, Km. 0007,0",
    "sg:city":"Riudarenes",
    "sg:orig_category":"Distribuci\u00d3n De Petr\u00d3leo Y Derivados",
    "sg:phone":"+34 972 16 82 27",
    "sg:postcode":"17421",
    "sg:province":"Girona",
    "wof:name":"Petit Marc Riudarenes S.l.",
    "wof:placetype":"venue"
},
  "geometry": {"coordinates":[2.7224509716,41.8221893311],"type":"Point"}
}