{
  "type": "Feature",
  "properties": {
    "addr:full":"Calle de Valdemoro, 11 Getafe Madrid 28901",
    "addr:housenumber":"11",
    "addr:postcode":"28901",
    "addr:street":"Calle De Valdemoro",
    "iso:country":"ES",
    "sg:address":"Calle de Valdemoro, 11",
    "sg:city":"Getafe",
    "sg:orig_category":"Cajas De Ahorro",
    "sg:phone":"+34 916 83 05 59",
    "sg:postcode":"28901",
    "sg:province":"Madrid",
    "sg:website":"www.lacaixa.es",
    "wof:name":"Caixa D'estalvis I Pensions De Barcelona",
    "wof:placetype":"venue"
},
  "geometry": {"coordinates":[-3.731662035,40.3015937805],"type":"Point"}
}