{
  "type": "Feature",
  "properties": {
    "iso:country":"ES",
    "sg:address":"Avda Portugal, 4",
    "sg:city":"Merida",
    "sg:orig_category":"Animales: Material Y Suministros Para (fabricaci\u00d3n, Al Por Mayor)",
    "sg:phone":"+34 924 37 36 99",
    "sg:postcode":"06800",
    "sg:province":"Badajoz",
    "wof:name":"Refru S.l.",
    "wof:placetype":"venue"
},
  "geometry": {"coordinates":[-6.3561148643,38.909828186],"type":"Point"}
}