{
  "type": "Feature",
  "properties": {
    "addr:full":"Calle de Encomienda De Palacios, 33 Madrid Madrid 28030",
    "addr:housenumber":"33",
    "addr:postcode":"madrid;28030",
    "addr:street":"Calle De Encomienda De Palacios",
    "iso:country":"ES",
    "sg:address":"Calle de Encomienda De Palacios, 33",
    "sg:city":"Madrid",
    "sg:orig_category":"Fabricaci\u00d3n De Juguetes Autom\u00c1ticos",
    "sg:phone":"+34 913 71 09 27",
    "sg:postcode":"28030",
    "sg:province":"Madrid",
    "wof:name":"Mimerca S.l.",
    "wof:placetype":"venue"
},
  "geometry": {"coordinates":[-3.6438810825,40.4007568359],"type":"Point"}
}