{
  "type": "Feature",
  "properties": {
    "addr:full":"Calle de Juan Barcelo, 27 Alcala De Xivert Castell\u00f3n 12570",
    "addr:housenumber":"27",
    "addr:postcode":"12570",
    "addr:street":"Calle De Juan Barcelo",
    "iso:country":"ES",
    "sg:address":"Calle de Juan Barcelo, 27",
    "sg:city":"Alcala De Xivert",
    "sg:orig_category":"Inmobiliaria (agencias)",
    "sg:phone":"+34 964 41 09 53",
    "sg:postcode":"12570",
    "sg:province":"Castell\u00f3n",
    "wof:name":"Sanz Roda Juan Francisco",
    "wof:placetype":"venue"
},
  "geometry": {"coordinates":[0.2378000021,40.2983894348],"type":"Point"}
}