{
  "type": "Feature",
  "properties": {
    "iso:country":"ES",
    "sg:address":"Pase Praia De Silgar, 54",
    "sg:city":"Sanxenxo",
    "sg:orig_category":"Inmobiliaria (agencias)",
    "sg:phone":"+34 986 72 01 06",
    "sg:postcode":"36960",
    "sg:province":"Pontevedra",
    "wof:name":"Cubreiro S.l.",
    "wof:placetype":"venue"
},
  "geometry": {"coordinates":[-8.8082103729,42.4006385803],"type":"Point"}
}