{
  "type": "Feature",
  "properties": {
    "iso:country":"ES",
    "sg:address":"Calle de Antonio Machin, S/n",
    "sg:city":"Sevilla",
    "sg:orig_category":"Prot\u00c9sicos Dentales",
    "sg:phone":"+34 954 38 94 30",
    "sg:postcode":"41009",
    "sg:province":"Sevilla",
    "wof:name":"Bilbao Sanchez Rocio Pilar",
    "wof:placetype":"venue"
},
  "geometry": {"coordinates":[-5.9846291542,37.4019317627],"type":"Point"}
}