{
  "type": "Feature",
  "properties": {
    "addr:full":"Calle de Mayor, 15 Balazote Albacete 02320",
    "addr:housenumber":"15",
    "addr:postcode":"02320",
    "addr:street":"Calle De Mayor",
    "iso:country":"ES",
    "sg:address":"Calle de Mayor, 15",
    "sg:city":"Balazote",
    "sg:orig_category":"Caf\u00c9s, Bares, Cervecer\u00cdas",
    "sg:phone":"+34 967 36 01 62",
    "sg:postcode":"02320",
    "sg:province":"Albacete",
    "wof:name":"Cafe Bar Mascara C.b.",
    "wof:placetype":"venue"
},
  "geometry": {"coordinates":[-2.1511359215,38.8840332031],"type":"Point"}
}