{
  "type": "Feature",
  "properties": {
    "iso:country":"ES",
    "sg:address":"Benasau, 9",
    "sg:city":"Elche",
    "sg:orig_category":"Lavado, Limpieza De Veh\u00cdculos",
    "sg:phone":"+34 965 43 18 22",
    "sg:postcode":"03005",
    "sg:province":"Alicante",
    "wof:name":"Wash Interprise S.l.",
    "wof:placetype":"venue"
},
  "geometry": {"coordinates":[-0.7213485241,38.2797470093],"type":"Point"}
}