{
  "type": "Feature",
  "properties": {
    "addr:full":"Carrer de Vilabella (dels), 16 Vic Barcelona 08500",
    "addr:housenumber":"16",
    "addr:postcode":"08500",
    "addr:street":"Carrer De Vilabella Dels",
    "iso:country":"ES",
    "sg:address":"Carrer de Vilabella (dels), 16",
    "sg:city":"Vic",
    "sg:orig_category":"Abogados",
    "sg:phone":"+34 938 89 41 88",
    "sg:postcode":"08500",
    "sg:province":"Barcelona",
    "wof:name":"Puigdecanet-comellas-punti S.c.p.",
    "wof:placetype":"venue"
},
  "geometry": {"coordinates":[2.2495200634,41.929019928],"type":"Point"}
}