{
  "type": "Feature",
  "properties": {
    "iso:country":"ES",
    "sg:address":"Carr D'hernan Cortes, 6",
    "sg:city":"Benicarlo",
    "sg:orig_category":"M\u00c1rmoles, Granitos Y Piedras Naturales",
    "sg:phone":"+34 964 46 23 33",
    "sg:postcode":"12580",
    "sg:province":"Castell\u00f3n",
    "wof:name":"Marmoles Benicarlo S.l.",
    "wof:placetype":"venue"
},
  "geometry": {"coordinates":[0.4261380136,40.4175186157],"type":"Point"}
}