{
  "type": "Feature",
  "properties": {
    "iso:country":"ES",
    "sg:address":"Plg. Industrial, S/n",
    "sg:city":"Herencia",
    "sg:orig_category":"Asesor\u00cdas",
    "sg:phone":"+34 926 57 47 20",
    "sg:postcode":"13640",
    "sg:province":"Ciudad Real",
    "wof:name":"Tecnove Security S.l.",
    "wof:placetype":"venue"
},
  "geometry": {"coordinates":[-3.3425738811,39.3777809143],"type":"Point"}
}