{
  "type": "Feature",
  "properties": {
    "iso:country":"ES",
    "sg:address":"Calle de Getaria, 21",
    "sg:city":"Donostia-san Sebastian",
    "sg:orig_category":"Bazares, Art\u00cdculos De Limpieza Y De Cocina (al Por Menor)",
    "sg:phone":"+34 943 42 60 00",
    "sg:postcode":"20005",
    "sg:province":"Guip\u00f9zcoa",
    "sg:website":"www.genevievelethu.com",
    "wof:name":"Alamac.7, S.l.",
    "wof:placetype":"venue"
},
  "geometry": {"coordinates":[-1.9803754091,43.3177261353],"type":"Point"}
}