{
  "type": "Feature",
  "properties": {
    "iso:country":"ES",
    "sg:address":"Calle de Marques De Quintanar, 4",
    "sg:city":"Baiona",
    "sg:orig_category":"Droguer\u00cdas (al Por Menor)",
    "sg:phone":"+34 986 35 64 77",
    "sg:postcode":"36300",
    "sg:province":"Pontevedra",
    "wof:name":"Hogarlin S.a.",
    "wof:placetype":"venue"
},
  "geometry": {"coordinates":[-97.78224945069999,45.7040786743],"type":"Point"}
}