{
  "type": "Feature",
  "properties": {
    "iso:country":"ES",
    "sg:address":"Carrer de Major, 16",
    "sg:city":"Nucia",
    "sg:orig_category":"Ense\u00d1anza, Formaci\u00d3n Profesional: Aprendizaje",
    "sg:phone":"+34 966 89 59 49",
    "sg:postcode":"03530",
    "sg:province":"Alicante",
    "wof:name":"Suma Gestion Tributaria Diputacion Alicante",
    "wof:placetype":"venue"
},
  "geometry": {"coordinates":[-0.122266002,38.6178817749],"type":"Point"}
}