{
  "type": "Feature",
  "properties": {
    "iso:country":"ES",
    "sg:address":"Carrer de Proven\u00c7a, 538",
    "sg:city":"Barcelona",
    "sg:orig_category":"Fabricaci\u00d3n De Sobres, Bolsas Y Fundas",
    "sg:phone":"+34 934 55 59 40",
    "sg:postcode":"08025",
    "sg:province":"Barcelona",
    "sg:website":"www.lupo.es",
    "wof:name":"Lupo Morenete S.l.",
    "wof:placetype":"venue"
},
  "geometry": {"coordinates":[2.179502964,41.4080543518],"type":"Point"}
}