{
  "type": "Feature",
  "properties": {
    "iso:country":"ES",
    "sg:address":"Carrer de Mestres Villa, 73",
    "sg:city":"Masnou",
    "sg:orig_category":"Empresas De Pintura Y Revestimientos",
    "sg:phone":"+34 935 55 21 29",
    "sg:postcode":"08320",
    "sg:province":"Barcelona",
    "wof:name":"Samper Cherto Jorge",
    "wof:placetype":"venue"
},
  "geometry": {"coordinates":[2.3209559917,41.4810066223],"type":"Point"}
}