{
  "type": "Feature",
  "properties": {
    "addr:full":"Avda Espa\u00d1a, 4 Albacete Albacete 02002",
    "addr:housenumber":"4",
    "addr:postcode":"02002",
    "addr:street":"Avda Espan\u0303A",
    "iso:country":"ES",
    "sg:address":"Avda Espa\u00d1a, 4",
    "sg:city":"Albacete",
    "sg:orig_category":"M\u00c9dicos: Cirug\u00cda Ortop\u00c9dica Y Traumatolog\u00cda",
    "sg:phone":"+34 967 23 45 79",
    "sg:postcode":"02002",
    "sg:province":"Albacete",
    "wof:name":"Selva Ferrandis Juan Ramon",
    "wof:placetype":"venue"
},
  "geometry": {"coordinates":[-1.8542339802,38.9863319397],"type":"Point"}
}