{
  "type": "Feature",
  "properties": {
    "iso:country":"ES",
    "sg:address":"Calle de Progreso, 17",
    "sg:city":"Andorra",
    "sg:orig_category":"Reposter\u00cdas",
    "sg:phone":"+34 978 84 40 23",
    "sg:postcode":"44500",
    "sg:province":"Teruel",
    "wof:name":"Gines Galve Ernesto",
    "wof:placetype":"venue"
},
  "geometry": {"coordinates":[-0.447059989,40.9762153625],"type":"Point"}
}