{
  "type": "Feature",
  "properties": {
    "iso:country":"ES",
    "sg:address":"Calle de Malva, S/n",
    "sg:city":"Sevilla",
    "sg:orig_category":"Chapister\u00cda",
    "sg:phone":"+34 954 95 36 20",
    "sg:postcode":"41008",
    "sg:province":"Sevilla",
    "wof:name":"Acosta Romero Jose",
    "wof:placetype":"venue"
},
  "geometry": {"coordinates":[-5.9712328911,37.4083557129],"type":"Point"}
}