{
  "type": "Feature",
  "properties": {
    "iso:country":"ES",
    "sg:address":"Carrer de Sant Bartomeu, 35",
    "sg:city":"Campello",
    "sg:orig_category":"Pr\u00c9stamos Personales E Hipotecarios",
    "sg:phone":"+34 965 63 67 66",
    "sg:postcode":"03560",
    "sg:province":"Alicante",
    "wof:name":"Rubiales Moreno Juan Carlos",
    "wof:placetype":"venue"
},
  "geometry": {"coordinates":[-0.3915469944,38.4238891602],"type":"Point"}
}