{
  "type": "Feature",
  "properties": {
    "iso:country":"ES",
    "sg:address":"Avda Iberoamerica, 24",
    "sg:city":"Alcala Real",
    "sg:orig_category":"Molduras, Junquillos, Listones Y Molduras Perforadas",
    "sg:phone":"+34 953 58 10 74",
    "sg:postcode":"23680",
    "sg:province":"Ja\u00e9n",
    "wof:name":"Tallon Mu\u00f1oz Jose",
    "wof:placetype":"venue"
},
  "geometry": {"coordinates":[-3.9240159988,37.4557342529],"type":"Point"}
}