{
  "type": "Feature",
  "properties": {
    "addr:full":"Calle de Fabricas, 2 Calamocha Teruel 44200",
    "addr:housenumber":"2",
    "addr:postcode":"44200",
    "addr:street":"Calle De Fabricas",
    "iso:country":"ES",
    "sg:address":"Calle de Fabricas, 2",
    "sg:city":"Calamocha",
    "sg:orig_category":"Carnicer\u00cdas, Carnicer\u00cdas",
    "sg:phone":"+34 978 73 17 01",
    "sg:postcode":"44200",
    "sg:province":"Teruel",
    "wof:name":"Industrias Alimenticias Jalonca S.l.",
    "wof:placetype":"venue"
},
  "geometry": {"coordinates":[-1.3013499975,40.9207572937],"type":"Point"}
}