{
  "type": "Feature",
  "properties": {
    "iso:country":"ES",
    "sg:address":"Lug. Fca. Soto Gutierrez, S/n",
    "sg:city":"Ciempozuelos",
    "sg:orig_category":"Explotaci\u00d3n De Canteras",
    "sg:phone":"+34 917 65 05 32",
    "sg:postcode":"28350",
    "sg:province":"Madrid",
    "wof:name":"Aridos Diez S.a.",
    "wof:placetype":"venue"
},
  "geometry": {"coordinates":[-3.6116495132,40.140296936],"type":"Point"}
}