{
  "type": "Feature",
  "properties": {
    "addr:full":"Avda Borbolla (la), 51 Sevilla Sevilla 41013",
    "addr:housenumber":"51",
    "addr:postcode":"41013",
    "addr:street":"Avda Borbolla La",
    "iso:country":"ES",
    "sg:address":"Avda Borbolla (la), 51",
    "sg:city":"Sevilla",
    "sg:orig_category":"Arquitectos",
    "sg:phone":"+34 954 23 49 27",
    "sg:postcode":"41013",
    "sg:province":"Sevilla",
    "wof:name":"Barroso De La Puerta Enrique",
    "wof:placetype":"venue"
},
  "geometry": {"coordinates":[-5.9852809906,37.3729095459],"type":"Point"}
}