{
  "type": "Feature",
  "properties": {
    "addr:full":"Calle de Aceiteria, 5 Huescar Granada 18830",
    "addr:housenumber":"5",
    "addr:postcode":"18830",
    "addr:street":"Calle De Aceiteria",
    "iso:country":"ES",
    "sg:address":"Calle de Aceiteria, 5",
    "sg:city":"Huescar",
    "sg:orig_category":"Electrodom\u00c9sticos (al Por Menor)",
    "sg:phone":"+34 958 74 20 96",
    "sg:postcode":"18830",
    "sg:province":"Granada",
    "wof:name":"Electro Vision Oscense S.l.",
    "wof:placetype":"venue"
},
  "geometry": {"coordinates":[-2.5387568474,37.8088874817],"type":"Point"}
}