{
  "type": "Feature",
  "properties": {
    "addr:full":"Dormitaleria, 14 Iru\u00f1a Navarra 31001",
    "addr:housenumber":"14",
    "addr:postcode":"31001",
    "addr:street":"Dormitaleria",
    "iso:country":"ES",
    "sg:address":"Dormitaleria, 14",
    "sg:city":"Iru\u00f1a",
    "sg:orig_category":"Centros Pms (psico",
    "sg:phone":"+34 948 20 68 31",
    "sg:postcode":"31001",
    "sg:province":"Navarra",
    "wof:name":"Bidari Formacion Y Asesoramiento",
    "wof:placetype":"venue"
},
  "geometry": {"coordinates":[-1.6414430141,42.8190727234],"type":"Point"}
}