{
  "type": "Feature",
  "properties": {
    "iso:country":"ES",
    "sg:address":"Vgen A. Santas, 6",
    "sg:city":"Salvaleon",
    "sg:orig_category":"Psic\u00d3logos",
    "sg:phone":"+34 924 75 29 29",
    "sg:postcode":"06174",
    "sg:province":"Badajoz",
    "wof:name":"Gonzalez Corrales Jose",
    "wof:placetype":"venue"
},
  "geometry": {"coordinates":[-6.7862138748,38.5085601807],"type":"Point"}
}