{
  "type": "Feature",
  "properties": {
    "addr:full":"Av Pau Claris, 8 Seu D'urgell Lleida 25700",
    "addr:housenumber":"8",
    "addr:postcode":"25700",
    "addr:street":"Av Pau Claris",
    "iso:country":"ES",
    "sg:address":"Av Pau Claris, 8",
    "sg:city":"Seu D'urgell",
    "sg:orig_category":"Cajas De Ahorro",
    "sg:phone":"+34 973 35 58 51",
    "sg:postcode":"25700",
    "sg:province":"Lleida",
    "wof:name":"Caja De Ahorros Del Mediterraneo",
    "wof:placetype":"venue"
},
  "geometry": {"coordinates":[0.6221050024,41.6223335266],"type":"Point"}
}