{
  "type": "Feature",
  "properties": {
    "iso:country":"ES",
    "sg:address":"Avda Alamos (los), 19",
    "sg:city":"Jerez De La Frontera",
    "sg:orig_category":"M\u00c9dicos: Cirug\u00cda Urol\u00d3gica",
    "sg:phone":"+34 956 18 40 08",
    "sg:postcode":"11407",
    "sg:province":"C\u00e1diz",
    "wof:name":"Gonzalez Monta\u00f1o Jose Maria",
    "wof:placetype":"venue"
},
  "geometry": {"coordinates":[-6.1361699104,36.7057495117],"type":"Point"}
}