{
  "type": "Feature",
  "properties": {
    "iso:country":"ES",
    "sg:address":"D Rufino Cano, S/n",
    "sg:city":"Gomezserracin",
    "sg:orig_category":"Farmacias",
    "sg:phone":"+34 921 16 81 33",
    "sg:postcode":"40240",
    "sg:province":"Segovia",
    "wof:name":"Tierno Martinez Adelaida",
    "wof:placetype":"venue"
},
  "geometry": {"coordinates":[-4.326048851,41.2883491516],"type":"Point"}
}