{
  "type": "Feature",
  "properties": {
    "iso:country":"ES",
    "sg:address":"Calle de San Luis Gonzaga, 5",
    "sg:city":"Cazalla Sierra",
    "sg:orig_category":"Internados & Ense\u00d1anza Privada",
    "sg:phone":"+34 954 88 40 66",
    "sg:postcode":"41370",
    "sg:province":"Sevilla",
    "wof:name":"Junta De Andalucia",
    "wof:placetype":"venue"
},
  "geometry": {"coordinates":[-5.7591872215,37.9289741516],"type":"Point"}
}