{
  "type": "Feature",
  "properties": {
    "addr:full":"Calle de Lope De Vega, 19 Santander Cantabria 39003",
    "addr:housenumber":"19",
    "addr:postcode":"39003",
    "addr:street":"Calle De Lope De Vega",
    "iso:country":"ES",
    "sg:address":"Calle de Lope De Vega, 19",
    "sg:city":"Santander",
    "sg:orig_category":"Fabricaci\u00d3n De Jabones, Detergentes Y Lej\u00cdas",
    "sg:phone":"+34 942 21 66 14",
    "sg:postcode":"39003",
    "sg:province":"Cantabria",
    "wof:name":"Fernandez Merino Jose Ramon",
    "wof:placetype":"venue"
},
  "geometry": {"coordinates":[-3.7999000549,43.4639053345],"type":"Point"}
}