{
  "type": "Feature",
  "properties": {
    "addr:full":"Avda Carlos Iii, 336 Aguadulce Almer\u00eda 04720",
    "addr:housenumber":"336",
    "addr:postcode":"04720",
    "addr:street":"Avda Carlos Iii;Almeri\u0301A",
    "iso:country":"ES",
    "sg:address":"Avda Carlos Iii, 336",
    "sg:city":"Aguadulce",
    "sg:orig_category":"Peluqueros: De Se\u00d1oras",
    "sg:phone":"+34 950 34 49 04",
    "sg:postcode":"04720",
    "sg:province":"Almer\u00eda",
    "wof:name":"Alferez Parron Visitacion",
    "wof:placetype":"venue"
},
  "geometry": {"coordinates":[-2.5757730007,36.8133239746],"type":"Point"}
}