{
  "type": "Feature",
  "properties": {
    "addr:full":"Rua Fraga, 84 Fene A Coru\u00f1a 15500",
    "addr:housenumber":"84",
    "addr:postcode":"15500",
    "addr:street":"Rua Fraga;Corun\u0303A",
    "iso:country":"ES",
    "sg:address":"Rua Fraga, 84",
    "sg:city":"Fene",
    "sg:orig_category":"Prot\u00c9sicos Dentales",
    "sg:phone":"+34 981 34 32 72",
    "sg:postcode":"15500",
    "sg:province":"A Coru\u00f1a",
    "wof:name":"Vizoso Menaya Susana",
    "wof:placetype":"venue"
},
  "geometry": {"coordinates":[-8.165060997,43.473690033],"type":"Point"}
}