{
  "type": "Feature",
  "properties": {
    "iso:country":"ES",
    "sg:address":"Urb Soto Marbella, S/n",
    "sg:city":"Ojen",
    "sg:classifiers":[
        {
            "category":"Sports & Exercise",
            "subcategory":"Golf",
            "type":"Entertainment"
        }
    ],
    "sg:phone":"+34 952 85 21 16",
    "sg:postcode":"29610",
    "sg:province":"M\u00e1laga",
    "sg:tags":[
        "y",
        "de",
        "campos",
        "clases"
    ],
    "wof:name":"Golf Gestion Integral S.l.",
    "wof:placetype":"venue"
},
  "geometry": {"coordinates":[-4.7470440865,36.5258903503],"type":"Point"}
}