{
  "type": "Feature",
  "properties": {
    "iso:country":"ES",
    "sg:address":"Ctra Alange, Km. 0001,0",
    "sg:city":"Merida",
    "sg:orig_category":"Audiovisuales (producci\u00d3n, Edici\u00d3n, Realizaci\u00d3n)",
    "sg:phone":"+34 924 37 15 75",
    "sg:postcode":"06800",
    "sg:province":"Badajoz",
    "sg:website":"www.iriseyex.com",
    "wof:name":"Iris Eyex Producciones Y Servicios Audiovisuales",
    "wof:placetype":"venue"
},
  "geometry": {"coordinates":[-6.3500027657,38.9179878235],"type":"Point"}
}