{
  "type": "Feature",
  "properties": {
    "iso:country":"ES",
    "sg:address":"Calle de Amparo, 9",
    "sg:city":"Madrid",
    "sg:orig_category":"Imprenta",
    "sg:phone":"+34 915 30 38 37",
    "sg:postcode":"28012",
    "sg:province":"Madrid",
    "wof:name":"Carrillo Melgar Damian",
    "wof:placetype":"venue"
},
  "geometry": {"coordinates":[-3.7039785385,40.4108390808],"type":"Point"}
}