{
  "type": "Feature",
  "properties": {
    "addr:full":"Plaz Salamero, 12 Zaragoza Zaragoza 50004",
    "addr:housenumber":"12",
    "addr:postcode":"50004",
    "addr:street":"Plaz Salamero",
    "iso:country":"ES",
    "sg:address":"Plaz Salamero, 12",
    "sg:city":"Zaragoza",
    "sg:orig_category":"Abogados",
    "sg:phone":"+34 976 22 76 77",
    "sg:postcode":"50004",
    "sg:province":"Zaragoza",
    "wof:name":"Lobato Burillo Maria Pilar",
    "wof:placetype":"venue"
},
  "geometry": {"coordinates":[-0.8846946955,41.6523399353],"type":"Point"}
}