{
  "type": "Feature",
  "properties": {
    "iso:country":"ES",
    "sg:address":"Calle de Moreras, 2",
    "sg:city":"Majadahonda",
    "sg:orig_category":"Laboratorios Y Trabajos De Fotograf\u00cda, V\u00cddeo Y Cine",
    "sg:phone":"+34 916 39 78 47",
    "sg:postcode":"28220",
    "sg:province":"Madrid",
    "wof:name":"Imagplus S.l.",
    "wof:placetype":"venue"
},
  "geometry": {"coordinates":[-3.8684110641,40.4532165527],"type":"Point"}
}