{
  "type": "Feature",
  "properties": {
    "addr:full":"Carr Ramon Marti I Alsina, 20 Badalona Barcelona 08911",
    "addr:housenumber":"20",
    "addr:postcode":"08911",
    "addr:street":"Carr Ramon Marti I Alsina",
    "iso:country":"ES",
    "sg:address":"Carr Ramon Marti I Alsina, 20",
    "sg:city":"Badalona",
    "sg:orig_category":"Maquinaria Para Industrias Diversas",
    "sg:phone":"+34 933 84 24 00",
    "sg:postcode":"08911",
    "sg:province":"Barcelona",
    "wof:name":"Mecanica Cairo S.l.",
    "wof:placetype":"venue"
},
  "geometry": {"coordinates":[2.2624499798,41.45885849],"type":"Point"}
}