{
  "type": "Feature",
  "properties": {
    "addr:full":"Calle de Radio, 18 Madrid Madrid 28019",
    "addr:housenumber":"18",
    "addr:postcode":"madrid;28019",
    "addr:street":"Calle De Radio",
    "iso:country":"ES",
    "sg:address":"Calle de Radio, 18",
    "sg:city":"Madrid",
    "sg:orig_category":"Loter\u00cda Y T\u00d3mbola",
    "sg:phone":"+34 915 69 33 23",
    "sg:postcode":"28019",
    "sg:province":"Madrid",
    "wof:name":"Sanchez Gonzalez Pedro",
    "wof:placetype":"venue"
},
  "geometry": {"coordinates":[-3.7224009037,40.3920936584],"type":"Point"}
}