{
  "type": "Feature",
  "properties": {
    "addr:full":"Calle de Camilo Jose Cela, 5 Barbate C\u00e1diz 11160",
    "addr:housenumber":"5",
    "addr:postcode":"11160",
    "addr:street":"Calle De Camilo Jose Cela",
    "iso:country":"ES",
    "sg:address":"Calle de Camilo Jose Cela, 5",
    "sg:city":"Barbate",
    "sg:orig_category":"Administradores De Bienes Y Delegados De Comunidades De Propietarios",
    "sg:phone":"+34 956 43 23 53",
    "sg:postcode":"11160",
    "sg:province":"C\u00e1diz",
    "wof:name":"Mera Marin Antonio",
    "wof:placetype":"venue"
},
  "geometry": {"coordinates":[-5.9187364578,36.193901062],"type":"Point"}
}