{
  "type": "Feature",
  "properties": {
    "addr:full":"Carrer de Sant Jaume, 49 Reus Tarragona 43201",
    "addr:housenumber":"49",
    "addr:postcode":"43201",
    "addr:street":"Carrer De Sant Jaume",
    "iso:country":"ES",
    "sg:address":"Carrer de Sant Jaume, 49",
    "sg:city":"Reus",
    "sg:orig_category":"Electricidad: Instaladores",
    "sg:phone":"+34 977 31 06 03",
    "sg:postcode":"43201",
    "sg:province":"Tarragona",
    "wof:name":"Marti Grant Ramon",
    "wof:placetype":"venue"
},
  "geometry": {"coordinates":[1.1062129736,41.1530990601],"type":"Point"}
}