{
  "type": "Feature",
  "properties": {
    "iso:country":"ES",
    "sg:address":"Avda Madrid, 48",
    "sg:city":"Zaragoza",
    "sg:orig_category":"Asesor\u00cda Sobre Comunicaci\u00d3n De Empresas",
    "sg:phone":"+34 976 31 67 59",
    "sg:postcode":"50010",
    "sg:province":"Zaragoza",
    "wof:name":"Asociacion De Infertilidad De Aragon",
    "wof:placetype":"venue"
},
  "geometry": {"coordinates":[-0.9026641846,41.6539535522],"type":"Point"}
}