{
  "type": "Feature",
  "properties": {
    "addr:full":"Calle de Tabares De Cala, 4 San Cristobal De La Laguna Santa Cruz De Tenerife 38201",
    "addr:housenumber":"4",
    "addr:postcode":"38201",
    "addr:street":"Calle De Tabares De Cala",
    "iso:country":"ES",
    "sg:address":"Calle de Tabares De Cala, 4",
    "sg:city":"San Cristobal De La Laguna",
    "sg:orig_category":"Ropa Para Se\u00d1oras (al Por Menor)",
    "sg:phone":"+34 922 25 86 06",
    "sg:postcode":"38201",
    "sg:province":"Santa Cruz De Tenerife",
    "wof:name":"Antonio Y Pedro Maestre Acevedo",
    "wof:placetype":"venue"
},
  "geometry": {"coordinates":[-16.3157482147,28.4877567291],"type":"Point"}
}