{
  "type": "Feature",
  "properties": {
    "iso:country":"ES",
    "sg:address":"Av Cubelles, 21",
    "sg:city":"Vilanova I La Geltru",
    "sg:orig_category":"Empresarios",
    "sg:phone":"+34 938 10 55 49",
    "sg:postcode":"08800",
    "sg:province":"Barcelona",
    "wof:name":"Sese Frasnedo S.l.",
    "wof:placetype":"venue"
},
  "geometry": {"coordinates":[1.7225450277,41.220741272],"type":"Point"}
}