{
  "type": "Feature",
  "properties": {
    "iso:country":"ES",
    "sg:address":"Calle de Antigona, 8",
    "sg:city":"Malaga",
    "sg:orig_category":"Perfumer\u00cda (al Por Menor)",
    "sg:phone":"+34 952 39 38 87",
    "sg:postcode":"29010",
    "sg:province":"M\u00e1laga",
    "wof:name":"Delgado Cortes Emilia",
    "wof:placetype":"venue"
},
  "geometry": {"coordinates":[-4.476544857,36.7209587097],"type":"Point"}
}