{
  "type": "Feature",
  "properties": {
    "addr:full":"Calle de Patricio Ferrandiz, 44 Denia Alicante 03700",
    "addr:housenumber":"44",
    "addr:postcode":"03700",
    "addr:street":"Calle De Patricio Ferrandiz",
    "iso:country":"ES",
    "sg:address":"Calle de Patricio Ferrandiz, 44",
    "sg:city":"Denia",
    "sg:orig_category":"Zapatos (al Por Menor)",
    "sg:phone":"+34 966 43 09 44",
    "sg:postcode":"03700",
    "sg:province":"Alicante",
    "wof:name":"Perles Orozco Veronica",
    "wof:placetype":"venue"
},
  "geometry": {"coordinates":[0.1082250029,38.8383178711],"type":"Point"}
}