{
  "type": "Feature",
  "properties": {
    "addr:full":"Calle de Bilbao, 42 Valencia Valencia 46009",
    "addr:housenumber":"42",
    "addr:postcode":"46009",
    "addr:street":"Calle De Bilbao",
    "iso:country":"ES",
    "sg:address":"Calle de Bilbao, 42",
    "sg:city":"Valencia",
    "sg:orig_category":"Cajas Para Embalar",
    "sg:phone":"+34 963 65 23 84",
    "sg:postcode":"46009",
    "sg:province":"Valencia",
    "sg:website":"www.ruralcaja.es",
    "wof:name":"Caja Rural Del Mediterraneo Ruralcaja S Coop De Credito",
    "wof:placetype":"venue"
},
  "geometry": {"coordinates":[-0.3717944026,39.4888839722],"type":"Point"}
}