{
  "type": "Feature",
  "properties": {
    "iso:country":"ES",
    "sg:address":"Calle de Marques De Vadillo, 5",
    "sg:city":"Soria",
    "sg:orig_category":"Informaci\u00d3n Financiera Y Comercial",
    "sg:phone":"+34 975 21 26 43",
    "sg:postcode":"42002",
    "sg:province":"Soria",
    "wof:name":"Delgado Y Beneitez, Notarios De Soria S.c.",
    "wof:placetype":"venue"
},
  "geometry": {"coordinates":[-2.4683051109,41.7641334534],"type":"Point"}
}