{
  "type": "Feature",
  "properties": {
    "addr:full":"El Ca\u00f1al, 1 Tortola De Henares Guadalajara 19198",
    "addr:housenumber":"1",
    "addr:postcode":"19198",
    "addr:street":"El Can\u0303Al",
    "iso:country":"ES",
    "sg:address":"El Ca\u00f1al, 1",
    "sg:city":"Tortola De Henares",
    "sg:orig_category":"Librer\u00cdas",
    "sg:phone":"+34 949 32 32 16",
    "sg:postcode":"19198",
    "sg:province":"Guadalajara",
    "wof:name":"Resa Lopez Jose Alberto",
    "wof:placetype":"venue"
},
  "geometry": {"coordinates":[-3.1267039776,40.70677948],"type":"Point"}
}