{
  "type": "Feature",
  "properties": {
    "iso:country":"ES",
    "sg:address":"Rbla Lluis Companys, 12",
    "sg:city":"Mas Duran",
    "sg:orig_category":"Inmobiliaria (agencias)",
    "sg:phone":"+34 937 21 94 16",
    "sg:postcode":"08192",
    "sg:province":"Barcelona",
    "wof:name":"Aguilar Melgarejo David",
    "wof:placetype":"venue"
},
  "geometry": {"coordinates":[2.1413440704,41.4899482727],"type":"Point"}
}