{
  "type": "Feature",
  "properties": {
    "addr:full":"Ctra Vic, 122 Manresa Barcelona 08241",
    "addr:housenumber":"122",
    "addr:postcode":"08241",
    "addr:street":"Ctra Vic",
    "iso:country":"ES",
    "sg:address":"Ctra Vic, 122",
    "sg:city":"Manresa",
    "sg:orig_category":"Telas Y Sedas (al Por Menor)",
    "sg:phone":"+34 938 73 02 13",
    "sg:postcode":"08241",
    "sg:province":"Barcelona",
    "wof:name":"Torralbo Cordon Javier",
    "wof:placetype":"venue"
},
  "geometry": {"coordinates":[1.8326029778,41.7300682068],"type":"Point"}
}