{
  "type": "Feature",
  "properties": {
    "addr:full":"Calle de Sicilia, 2 Granada Granada 18007",
    "addr:housenumber":"2",
    "addr:postcode":"18007",
    "addr:street":"Calle De Sicilia",
    "iso:country":"ES",
    "sg:address":"Calle de Sicilia, 2",
    "sg:city":"Granada",
    "sg:orig_category":"Ropa Para Se\u00d1oras Y Caballeros (al Por Menor)",
    "sg:phone":"+34 958 13 39 24",
    "sg:postcode":"18007",
    "sg:province":"Granada",
    "wof:name":"Rodriguez Sanchez Manuel",
    "wof:placetype":"venue"
},
  "geometry": {"coordinates":[-3.5982379913,37.1605644226],"type":"Point"}
}