{
  "type": "Feature",
  "properties": {
    "iso:country":"ES",
    "sg:address":"Calle de Lima, S/n",
    "sg:city":"Ejido",
    "sg:orig_category":"Animales (al Por Menor)",
    "sg:phone":"+34 950 48 34 89",
    "sg:postcode":"04700",
    "sg:province":"Almer\u00eda",
    "wof:name":"Ruiz Pe\u00f1a Antonio",
    "wof:placetype":"venue"
},
  "geometry": {"coordinates":[-2.8158740997,36.7807617188],"type":"Point"}
}