{
  "type": "Feature",
  "properties": {
    "addr:full":"Calle de Remiendos, 8 Menasalbas Toledo 45128",
    "addr:housenumber":"8",
    "addr:postcode":"45128",
    "addr:street":"Calle De Remiendos",
    "iso:country":"ES",
    "sg:address":"Calle de Remiendos, 8",
    "sg:city":"Menasalbas",
    "sg:orig_category":"Inform\u00c1tica, Ofim\u00c1tica (estudios, Asesor\u00cda, Ingenier\u00cda, Formaci\u00d3n)",
    "sg:phone":"+34 925 40 72 59",
    "sg:postcode":"45128",
    "sg:province":"Toledo",
    "wof:name":"Sanchez Escobar Agustin",
    "wof:placetype":"venue"
},
  "geometry": {"coordinates":[-4.2832422256,39.6413497925],"type":"Point"}
}