{
  "type": "Feature",
  "properties": {
    "addr:full":"Rbla Bobiles, 6 Martorell Barcelona 08760",
    "addr:housenumber":"6",
    "addr:postcode":"08760",
    "addr:street":"Rbla Bobiles",
    "iso:country":"ES",
    "sg:address":"Rbla Bobiles, 6",
    "sg:city":"Martorell",
    "sg:orig_category":"Cajas De Ahorro",
    "sg:phone":"+34 937 73 55 72",
    "sg:postcode":"08760",
    "sg:province":"Barcelona",
    "sg:website":"www.cajanavarra.es",
    "wof:name":"Caja De Ahorros Y Monte De Piedad De Navarra",
    "wof:placetype":"venue"
},
  "geometry": {"coordinates":[1.9169800282,41.4771957397],"type":"Point"}
}