{
  "type": "Feature",
  "properties": {
    "iso:country":"ES",
    "sg:address":"Rua Tangara\u00d1o (do), 6",
    "sg:city":"Ourense",
    "sg:orig_category":"Molduras, Junquillos, Listones Y Molduras Perforadas",
    "sg:phone":"+34 988 22 99 51",
    "sg:postcode":"32002",
    "sg:province":"Ourense",
    "wof:name":"Cruz Nacher Luis",
    "wof:placetype":"venue"
},
  "geometry": {"coordinates":[-7.8777217865,42.3269348145],"type":"Point"}
}