{
  "type": "Feature",
  "properties": {
    "iso:country":"ES",
    "sg:address":"Calle de Enrique Camacho Carrasco, 102",
    "sg:city":"Marchena",
    "sg:orig_category":"Empresas De Carpinter\u00cda Met\u00c1lica",
    "sg:phone":"+34 955 84 69 75",
    "sg:postcode":"41620",
    "sg:province":"Sevilla",
    "wof:name":"Talleres Seiva S.l.",
    "wof:placetype":"venue"
},
  "geometry": {"coordinates":[-5.4110131264,37.3242378235],"type":"Point"}
}