{
  "type": "Feature",
  "properties": {
    "iso:country":"ES",
    "sg:address":"Calle de Carrascales, 14",
    "sg:city":"Madrid",
    "sg:orig_category":"Empresas De Carpinter\u00cda Met\u00c1lica",
    "sg:phone":"+34 914 76 28 46",
    "sg:postcode":"28026",
    "sg:province":"Madrid",
    "wof:name":"Jimenez Fernandez Francisco",
    "wof:placetype":"venue"
},
  "geometry": {"coordinates":[-3.708304882,40.3813858032],"type":"Point"}
}