{
  "type": "Feature",
  "properties": {
    "iso:country":"ES",
    "sg:address":"Calle de Mayor, 7",
    "sg:city":"Castillonroy",
    "sg:orig_category":"Cajas Para Embalar",
    "sg:phone":"+34 974 43 40 43",
    "sg:postcode":"22572",
    "sg:province":"Huesca",
    "wof:name":"Caja Rural Aragonesa Y De Los Pirineos",
    "wof:placetype":"venue"
},
  "geometry": {"coordinates":[0.5134680271,41.8847541809],"type":"Point"}
}