{
  "type": "Feature",
  "properties": {
    "addr:full":"Calle de Constitucion, 10 Torrent Valencia 46900",
    "addr:housenumber":"10",
    "addr:postcode":"46900",
    "addr:street":"Calle De Constitucion;Valencia",
    "iso:country":"ES",
    "sg:address":"Calle de Constitucion, 10",
    "sg:city":"Torrent",
    "sg:orig_category":"Tintorer\u00cdas, Limpieza En Seco",
    "sg:phone":"+34 961 58 14 72",
    "sg:postcode":"46900",
    "sg:province":"Valencia",
    "wof:name":"Gomez Garrigues Ricardo",
    "wof:placetype":"venue"
},
  "geometry": {"coordinates":[-0.4740479887,39.4340629578],"type":"Point"}
}