{
  "type": "Feature",
  "properties": {
    "addr:full":"Calle de Macarena (de La), S/n Parla Madrid 28980",
    "addr:postcode":"28980",
    "addr:street":"Calle De Macarena De La S / N",
    "iso:country":"ES",
    "sg:address":"Calle de Macarena (de La), S/n",
    "sg:city":"Parla",
    "sg:orig_category":"Peluqueros: De Se\u00d1oras",
    "sg:phone":"+34 916 99 44 77",
    "sg:postcode":"28980",
    "sg:province":"Madrid",
    "wof:name":"Garcia Sanz Argelia",
    "wof:placetype":"venue"
},
  "geometry": {"coordinates":[-3.7666289806,40.2391052246],"type":"Point"}
}