{
  "type": "Feature",
  "properties": {
    "addr:full":"Avda Reina Victoria, 30 Madrid Madrid 28003",
    "addr:housenumber":"30",
    "addr:postcode":"madrid;28003",
    "addr:street":"Avda Reina Victoria",
    "iso:country":"ES",
    "sg:address":"Avda Reina Victoria, 30",
    "sg:city":"Madrid",
    "sg:orig_category":"Ortopedia General",
    "sg:phone":"+34 915 53 26 97",
    "sg:postcode":"28003",
    "sg:province":"Madrid",
    "wof:name":"Ojeda Bodas Roberto",
    "wof:placetype":"venue"
},
  "geometry": {"coordinates":[-3.7099421024,40.4472007751],"type":"Point"}
}