{
  "type": "Feature",
  "properties": {
    "iso:country":"ES",
    "sg:address":"Calle de Doctores Castroviejo, 31",
    "sg:city":"Logro\u00f1o",
    "sg:orig_category":"Arquitectos",
    "sg:phone":"+34 941 25 37 62",
    "sg:postcode":"26003",
    "sg:province":"La Rioja",
    "wof:name":"Gomez Diaz Ignacio Julian",
    "wof:placetype":"venue"
},
  "geometry": {"coordinates":[-2.4404942989,42.4624023438],"type":"Point"}
}