{
  "type": "Feature",
  "properties": {
    "iso:country":"ES",
    "sg:address":"Pase Federico G. Lorca, 10",
    "sg:city":"Donostia-san Sebastian",
    "sg:orig_category":"Psicoterapeutas",
    "sg:phone":"+34 943 01 10 80",
    "sg:postcode":"20012",
    "sg:province":"Guip\u00f9zcoa",
    "wof:name":"Bego\u00f1a Pumar Gonza\u00f1ez",
    "wof:placetype":"venue"
},
  "geometry": {"coordinates":[-1.9794000387,43.3173789978],"type":"Point"}
}