{
  "type": "Feature",
  "properties": {
    "addr:full":"Czad Toro, 60 Poligono Industrial Los Villares Salamanca 37184",
    "addr:housenumber":"60",
    "addr:postcode":"37184",
    "addr:street":"Toro;Industrial",
    "iso:country":"ES",
    "sg:address":"Czad Toro, 60",
    "sg:city":"Poligono Industrial Los Villares",
    "sg:orig_category":"Mobiliario M\u00c9dico Y Quir\u00dargico",
    "sg:phone":"+34 923 25 44 00",
    "sg:postcode":"37184",
    "sg:province":"Salamanca",
    "wof:name":"B.g.mobiliario Clinico S.l.",
    "wof:placetype":"venue"
},
  "geometry": {"coordinates":[-5.6469841003,41.0071716309],"type":"Point"}
}