{
  "type": "Feature",
  "properties": {
    "addr:full":"Calle de Libertad, 26 Torrejon Ardoz Madrid 28850",
    "addr:housenumber":"26",
    "addr:postcode":"28850",
    "addr:street":"Calle De Libertad",
    "iso:country":"ES",
    "sg:address":"Calle de Libertad, 26",
    "sg:city":"Torrejon Ardoz",
    "sg:orig_category":"M\u00c9dicos: Psiquiatr\u00cda",
    "sg:phone":"+34 916 76 08 96",
    "sg:postcode":"28850",
    "sg:province":"Madrid",
    "wof:name":"Cepsit Psicologos S.l",
    "wof:placetype":"venue"
},
  "geometry": {"coordinates":[-3.4806830883,40.4609489441],"type":"Point"}
}