{
  "type": "Feature",
  "properties": {
    "iso:country":"ES",
    "sg:address":"Jose Migel Iturriotz Kalea, 1",
    "sg:city":"Beasain",
    "sg:orig_category":"Caf\u00c9s, Bares, Cervecer\u00cdas",
    "sg:phone":"+34 943 88 15 67",
    "sg:postcode":"20200",
    "sg:province":"Guip\u00f9zcoa",
    "wof:name":"Teciruna S.l.",
    "wof:placetype":"venue"
},
  "geometry": {"coordinates":[-2.1945459843,43.0475273132],"type":"Point"}
}