{
  "type": "Feature",
  "properties": {
    "iso:country":"ES",
    "sg:address":"Avda Ejercitos Espa\u00d1oles, S/n",
    "sg:city":"Calpe",
    "sg:orig_category":"Peluquer\u00cdas, Peluquer\u00cda Mixta",
    "sg:phone":"+34 965 83 51 64",
    "sg:postcode":"03710",
    "sg:province":"Alicante",
    "wof:name":"Ballesteros Asensio Elena",
    "wof:placetype":"venue"
},
  "geometry": {"coordinates":[0.0594349988,38.6432914734],"type":"Point"}
}