{
  "type": "Feature",
  "properties": {
    "iso:country":"ES",
    "sg:address":"Calle de Industria, 32",
    "sg:city":"Madrid",
    "sg:orig_category":"Servicios Gsm",
    "sg:phone":"+34 902 30 01 20",
    "sg:postcode":"28011",
    "sg:province":"Madrid",
    "wof:name":"Vinzeo Technologies S.a.u.",
    "wof:placetype":"venue"
},
  "geometry": {"coordinates":[-3.729569912,40.4096336365],"type":"Point"}
}