{
  "type": "Feature",
  "properties": {
    "addr:full":"Calle de Solarillo De Gracia, 7 Granada Granada 18002",
    "addr:housenumber":"7",
    "addr:postcode":"18002",
    "addr:street":"Calle De Solarillo De Gracia",
    "iso:country":"ES",
    "sg:address":"Calle de Solarillo De Gracia, 7",
    "sg:city":"Granada",
    "sg:orig_category":"Ropa Para Se\u00d1oras (al Por Menor)",
    "sg:phone":"+34 958 25 49 89",
    "sg:postcode":"18002",
    "sg:province":"Granada",
    "wof:name":"Garcia Romero Inmaculada",
    "wof:placetype":"venue"
},
  "geometry": {"coordinates":[-3.6035590172,37.1725387573],"type":"Point"}
}