{
  "type": "Feature",
  "properties": {
    "addr:full":"Carrer de Irlanda, 2 Sabadell Barcelona 08205",
    "addr:housenumber":"2",
    "addr:postcode":"08205",
    "addr:street":"Carrer De Irlanda",
    "iso:country":"ES",
    "sg:address":"Carrer de Irlanda, 2",
    "sg:city":"Sabadell",
    "sg:orig_category":"Supermercados Y Hipermercados",
    "sg:phone":"+34 937 45 11 91",
    "sg:postcode":"08205",
    "sg:province":"Barcelona",
    "wof:name":"Cs Establiments De Proximitat S.l.",
    "wof:placetype":"venue"
},
  "geometry": {"coordinates":[2.0847110748,41.547000885],"type":"Point"}
}