{
  "type": "Feature",
  "properties": {
    "iso:country":"ES",
    "sg:address":"Carr Joan De La Cierva, 2",
    "sg:city":"Algemesi",
    "sg:orig_category":"Empresas De Carpinter\u00cda Met\u00c1lica",
    "sg:phone":"+34 962 42 33 60",
    "sg:postcode":"46680",
    "sg:province":"Valencia",
    "wof:name":"Crespo Hoyos Mariano",
    "wof:placetype":"venue"
},
  "geometry": {"coordinates":[-0.4333690107,39.1949996948],"type":"Point"}
}