{
  "type": "Feature",
  "properties": {
    "addr:full":"Ctra. Talavera, Km. 0032,0 Puente Arzobispo Toledo 45570",
    "addr:postcode":"45570",
    "addr:street":"Ctra. Talavera Km. 0032,0 Puente Arzobispo",
    "iso:country":"ES",
    "sg:address":"Ctra. Talavera, Km. 0032,0",
    "sg:city":"Puente Arzobispo",
    "sg:orig_category":"Molduras, Junquillos, Listones Y Molduras Perforadas",
    "sg:phone":"+34 925 43 62 11",
    "sg:postcode":"45570",
    "sg:province":"Toledo",
    "wof:name":"Ibars Delgado Jose",
    "wof:placetype":"venue"
},
  "geometry": {"coordinates":[-5.172039032,39.8030891418],"type":"Point"}
}