{
  "type": "Feature",
  "properties": {
    "iso:country":"ES",
    "sg:address":"Disseminat, 16",
    "sg:city":"Teia",
    "sg:orig_category":"Semiller\u00cdas",
    "sg:phone":"+34 935 55 26 50",
    "sg:postcode":"08329",
    "sg:province":"Barcelona",
    "wof:name":"Salvat Colomer Pedro",
    "wof:placetype":"venue"
},
  "geometry": {"coordinates":[2.3216049671,41.4981689453],"type":"Point"}
}