{
  "type": "Feature",
  "properties": {
    "addr:full":"Rua San Antoni\u00d1o, 8 Caeira Pontevedra 36005",
    "addr:housenumber":"8",
    "addr:postcode":"36005",
    "addr:street":"Rua San Antonin\u0303O",
    "iso:country":"ES",
    "sg:address":"Rua San Antoni\u00d1o, 8",
    "sg:city":"Caeira",
    "sg:orig_category":"Inmobiliaria (agencias)",
    "sg:phone":"+34 986 87 28 54",
    "sg:postcode":"36005",
    "sg:province":"Pontevedra",
    "wof:name":"J. Paz Andrade S.l.",
    "wof:placetype":"venue"
},
  "geometry": {"coordinates":[-8.6331739426,42.4493751526],"type":"Point"}
}