{
  "type": "Feature",
  "properties": {
    "addr:full":"Pg Sant Joan, 104 Barcelona Barcelona 08037",
    "addr:housenumber":"104",
    "addr:postcode":"08037",
    "addr:street":"Pg Sant Joan",
    "iso:country":"ES",
    "sg:address":"Pg Sant Joan, 104",
    "sg:city":"Barcelona",
    "sg:orig_category":"M\u00c9dicos: Oftalmolog\u00cda",
    "sg:phone":"+34 934 57 05 95",
    "sg:postcode":"08037",
    "sg:province":"Barcelona",
    "wof:name":"Deo Ridruejo Jose Maria",
    "wof:placetype":"venue"
},
  "geometry": {"coordinates":[2.169768095,41.3996620178],"type":"Point"}
}