{
  "type": "Feature",
  "properties": {
    "iso:country":"ES",
    "sg:address":"Avda Basagoiti, 37",
    "sg:city":"Algorta",
    "sg:classifiers":[
        {
            "category":"Arts & Performance",
            "subcategory":"Art Gallery",
            "type":"Entertainment"
        }
    ],
    "sg:phone":"+34 944 91 14 66",
    "sg:postcode":"48991",
    "sg:province":"Vizcaya",
    "sg:tags":[
        "arte",
        "de",
        "galer\u00cdas"
    ],
    "wof:name":"Monedero Adrian Milagros",
    "wof:placetype":"venue"
},
  "geometry": {"coordinates":[-3.0106225014,43.3475112915],"type":"Point"}
}