{
  "type": "Feature",
  "properties": {
    "iso:country":"ES",
    "sg:address":"Avda Canarias, 351",
    "sg:city":"Vecindario",
    "sg:orig_category":"Perfumer\u00cda (al Por Menor)",
    "sg:phone":"+34 928 14 95 78",
    "sg:postcode":"35110",
    "sg:province":"Las Palmas",
    "wof:name":"Hermanas Leon Doreste S.l.",
    "wof:placetype":"venue"
},
  "geometry": {"coordinates":[-15.4453582764,27.8441925049],"type":"Point"}
}