{
  "type": "Feature",
  "properties": {
    "addr:full":"Calle de Gardenia, 7 Sevilla Sevilla 41008",
    "addr:housenumber":"7",
    "addr:postcode":"41008",
    "addr:street":"Calle De Gardenia",
    "iso:country":"ES",
    "sg:address":"Calle de Gardenia, 7",
    "sg:city":"Sevilla",
    "sg:orig_category":"Molduras, Junquillos, Listones Y Molduras Perforadas",
    "sg:phone":"+34 954 35 47 47",
    "sg:postcode":"41008",
    "sg:province":"Sevilla",
    "wof:name":"Suarez Liebana Jose Manuel",
    "wof:placetype":"venue"
},
  "geometry": {"coordinates":[-5.9787278175,37.4065666199],"type":"Point"}
}