{
  "type": "Feature",
  "properties": {
    "iso:country":"ES",
    "sg:address":"Carr Major, 28",
    "sg:city":"Benetusser",
    "sg:orig_category":"Asilos De Ancianos. Centros Privados",
    "sg:phone":"+34 963 75 79 61",
    "sg:postcode":"46910",
    "sg:province":"Valencia",
    "wof:name":"Generalitat Valenciana",
    "wof:placetype":"venue"
},
  "geometry": {"coordinates":[-0.397356987,39.422958374],"type":"Point"}
}