{
  "type": "Feature",
  "properties": {
    "addr:full":"Ctra Barcelona, 13 Sabadell Barcelona 08201",
    "addr:housenumber":"13",
    "addr:postcode":"08201",
    "addr:street":"Ctra Barcelona",
    "iso:country":"ES",
    "sg:address":"Ctra Barcelona, 13",
    "sg:city":"Sabadell",
    "sg:orig_category":"Estancos",
    "sg:phone":"+34 937 26 07 36",
    "sg:postcode":"08201",
    "sg:province":"Barcelona",
    "wof:name":"Codina Arboles Juan",
    "wof:placetype":"venue"
},
  "geometry": {"coordinates":[2.1034400463,41.5430717468],"type":"Point"}
}