{
  "type": "Feature",
  "properties": {
    "iso:country":"ES",
    "sg:address":"Calle de Gremio De Los Caldereros (del), S/n",
    "sg:city":"Hontoria",
    "sg:orig_category":"Promotores Constructores",
    "sg:phone":"+34 921 43 16 40",
    "sg:postcode":"40195",
    "sg:province":"Segovia",
    "wof:name":"Forjados Rafsa S.l",
    "wof:placetype":"venue"
},
  "geometry": {"coordinates":[-4.108215332,40.9125480652],"type":"Point"}
}