{
  "type": "Feature",
  "properties": {
    "iso:country":"ES",
    "sg:address":"Finc Casa De La Parra, S/n",
    "sg:city":"Villar De Chinchilla",
    "sg:orig_category":"Arenas, Guijarros Y Granulados",
    "sg:phone":"+34 967 28 80 07",
    "sg:postcode":"02695",
    "sg:province":"Albacete",
    "wof:name":"Montpichel S.l.",
    "wof:placetype":"venue"
},
  "geometry": {"coordinates":[-1.5280989408,38.901424408],"type":"Point"}
}