{
  "type": "Feature",
  "properties": {
    "iso:country":"ES",
    "sg:address":"Av Portell De Granyana, 6",
    "sg:city":"Elche",
    "sg:orig_category":"Asesor\u00cda Fiscal Y Jur\u00cddica",
    "sg:phone":"+34 965 45 11 42",
    "sg:postcode":"03202",
    "sg:province":"Alicante",
    "wof:name":"Despacho Empresarial Helios S.l.",
    "wof:placetype":"venue"
},
  "geometry": {"coordinates":[-0.6963589787,38.2682762146],"type":"Point"}
}