{
  "type": "Feature",
  "properties": {
    "iso:country":"ES",
    "sg:address":"Calle de Esteban De Ponte, 5",
    "sg:city":"Garachico",
    "sg:orig_category":"Oficinas De Turismo, Asociaciones De Iniciativa",
    "sg:phone":"+34 922 13 34 61",
    "sg:postcode":"38450",
    "sg:province":"Santa Cruz De Tenerife",
    "wof:name":"Centro De Iniciativas Turisticas",
    "wof:placetype":"venue"
},
  "geometry": {"coordinates":[-16.7657318115,28.3729934692],"type":"Point"}
}