{
  "type": "Feature",
  "properties": {
    "iso:country":"ES",
    "sg:address":"Gonzalo De Berceo, 12",
    "sg:city":"Playas Telde",
    "sg:orig_category":"Productos Qu\u00cdmicos (fabricaci\u00d3n, Al Por Mayor)",
    "sg:phone":"+34 928 13 17 63",
    "sg:postcode":"35214",
    "sg:province":"Las Palmas",
    "wof:name":"Quimica Solican S.l.",
    "wof:placetype":"venue"
},
  "geometry": {"coordinates":[-15.3887634277,27.9937648773],"type":"Point"}
}