{
  "type": "Feature",
  "properties": {
    "addr:full":"Av Ametlla De Mar, 7 Benidorm Alicante 03500",
    "addr:housenumber":"7",
    "addr:postcode":"03500",
    "addr:street":"Av Ametlla De Mar",
    "iso:country":"ES",
    "sg:address":"Av Ametlla De Mar, 7",
    "sg:city":"Benidorm",
    "sg:orig_category":"M\u00c9dicos: Cirug\u00cda Ortop\u00c9dica Y Traumatolog\u00cda",
    "sg:phone":"+34 965 85 51 83",
    "sg:postcode":"03500",
    "sg:province":"Alicante",
    "sg:website":"www.miguel.noriega.ded.es",
    "wof:name":"Noriega Mac Arthur Miguel",
    "wof:placetype":"venue"
},
  "geometry": {"coordinates":[-0.1073250026,38.5354728699],"type":"Point"}
}