{
  "type": "Feature",
  "properties": {
    "iso:country":"ES",
    "sg:address":"Calle de Loma Del Colegial, 2",
    "sg:city":"Torremolinos",
    "sg:orig_category":"Quincaller\u00cda (al Por Menor)",
    "sg:phone":"+34 952 38 99 15",
    "sg:postcode":"29620",
    "sg:province":"M\u00e1laga",
    "wof:name":"Flores Y Flores Ferreteros S.l.",
    "wof:placetype":"venue"
},
  "geometry": {"coordinates":[-4.5036540031,36.62317276],"type":"Point"}
}