{
  "type": "Feature",
  "properties": {
    "addr:full":"Calle de Carracido, 6 Langreo Asturias 33900",
    "addr:housenumber":"6",
    "addr:postcode":"33900",
    "addr:street":"Calle De Carracido",
    "iso:country":"ES",
    "sg:address":"Calle de Carracido, 6",
    "sg:city":"Langreo",
    "sg:orig_category":"Farmacias",
    "sg:phone":"+34 985 67 87 12",
    "sg:postcode":"33900",
    "sg:province":"Asturias",
    "wof:name":"Garcia Uribelarrea Maria Adelina",
    "wof:placetype":"venue"
},
  "geometry": {"coordinates":[-5.6838340759,43.296207428],"type":"Point"}
}