{
  "type": "Feature",
  "properties": {
    "iso:country":"ES",
    "sg:address":"Calle de Trille, 25",
    "sg:city":"Cadiz",
    "sg:orig_category":"Confecci\u00d3n (fabricaci\u00d3n, Al Por Mayor)",
    "sg:phone":"+34 956 25 82 56",
    "sg:postcode":"11012",
    "sg:province":"C\u00e1diz",
    "wof:name":"Aguilar Ortega Antonio",
    "wof:placetype":"venue"
},
  "geometry": {"coordinates":[-6.2759075165,36.5121803284],"type":"Point"}
}