{
  "type": "Feature",
  "properties": {
    "addr:full":"Mente, 3 Mente Ourense 32610",
    "addr:housenumber":"3",
    "addr:postcode":"32610",
    "addr:street":"Mente",
    "iso:country":"ES",
    "sg:address":"Mente, 3",
    "sg:city":"Mente",
    "sg:orig_category":"Empresas De Carpinter\u00cda De Madera",
    "sg:phone":"+34 988 30 87 64",
    "sg:postcode":"32610",
    "sg:province":"Ourense",
    "wof:name":"Estevez Reigada Antonio",
    "wof:placetype":"venue"
},
  "geometry": {"coordinates":[-7.2231202126,41.9534721375],"type":"Point"}
}