{
  "type": "Feature",
  "properties": {
    "addr:full":"Ctra Madrid-cadiz(bellavista), 25 Sevilla Sevilla 41014",
    "addr:housenumber":"25",
    "addr:postcode":"41014",
    "addr:street":"Ctra Madrid-Cadiz Bellavista",
    "iso:country":"ES",
    "sg:address":"Ctra Madrid-cadiz(bellavista), 25",
    "sg:city":"Sevilla",
    "sg:orig_category":"Bancos",
    "sg:phone":"+34 954 68 09 24",
    "sg:postcode":"41014",
    "sg:province":"Sevilla",
    "wof:name":"Banco Espa\u00f1ol De Credito S.a.",
    "wof:placetype":"venue"
},
  "geometry": {"coordinates":[-5.9596791267,37.3278617859],"type":"Point"}
}