{
  "type": "Feature",
  "properties": {
    "addr:full":"Plaz Mercado, 48 Aldeanueva Camino C\u00e1ceres 10740",
    "addr:postcode":"10740",
    "addr:street":"Camino Ca\u0301Ceres",
    "iso:country":"ES",
    "sg:address":"Plaz Mercado, 48",
    "sg:city":"Aldeanueva Camino",
    "sg:orig_category":"Caf\u00c9s, Bares, Cervecer\u00cdas",
    "sg:phone":"+34 927 48 43 74",
    "sg:postcode":"10740",
    "sg:province":"C\u00e1ceres",
    "wof:name":"Rubio Dominguez Julia",
    "wof:placetype":"venue"
},
  "geometry": {"coordinates":[-5.9294190407,40.25989151],"type":"Point"}
}