{
  "type": "Feature",
  "properties": {
    "iso:country":"ES",
    "sg:address":"Calle de Vicente Cano, 14",
    "sg:city":"Plasencia",
    "sg:orig_category":"Doctores En Medicina",
    "sg:phone":"+34 927 41 63 06",
    "sg:postcode":"10600",
    "sg:province":"C\u00e1ceres",
    "wof:name":"Nuevo Sanchez Florencio",
    "wof:placetype":"venue"
},
  "geometry": {"coordinates":[-6.0912690163,40.0333404541],"type":"Point"}
}