{
  "type": "Feature",
  "properties": {
    "iso:country":"ES",
    "sg:address":"Bons, Km. 0015,0",
    "sg:city":"Larin",
    "sg:orig_category":"Distribuci\u00d3n De Petr\u00d3leo Y Derivados",
    "sg:phone":"+34 981 19 04 62",
    "sg:postcode":"15144",
    "sg:province":"La Coru\u00f1a",
    "wof:name":"Repsol Ypf S.a.",
    "wof:placetype":"venue"
},
  "geometry": {"coordinates":[-8.5672702789,43.3058357239],"type":"Point"}
}