{
  "type": "Feature",
  "properties": {
    "addr:full":"Barr Bekea, 8 Bekea Vizcaya 48960",
    "addr:housenumber":"8",
    "addr:postcode":"48960",
    "addr:street":"Bekea",
    "iso:country":"ES",
    "sg:address":"Barr Bekea, 8",
    "sg:city":"Bekea",
    "sg:orig_category":"Maquinaria Para Industrias Diversas",
    "sg:phone":"+34 944 57 25 00",
    "sg:postcode":"48960",
    "sg:province":"Vizcaya",
    "wof:name":"Manutencion Electro-hidraulica Del Norte S.l.",
    "wof:placetype":"venue"
},
  "geometry": {"coordinates":[-2.8470389843,43.2298049927],"type":"Point"}
}