{
  "type": "Feature",
  "properties": {
    "addr:full":"Carr Alfons El Benigne, 4 Silla Valencia 46460",
    "addr:housenumber":"4",
    "addr:postcode":"46460",
    "addr:street":"Carr Alfons El Benigne",
    "iso:country":"ES",
    "sg:address":"Carr Alfons El Benigne, 4",
    "sg:city":"Silla",
    "sg:orig_category":"Asesor\u00cda Sobre Comunicaci\u00d3n De Empresas",
    "sg:phone":"+34 961 20 33 23",
    "sg:postcode":"46460",
    "sg:province":"Valencia",
    "wof:name":"Lysuligth S.l.",
    "wof:placetype":"venue"
},
  "geometry": {"coordinates":[-0.4112589955,39.36901474],"type":"Point"}
}