{
  "type": "Feature",
  "properties": {
    "addr:full":"Pl. Constitucion, 1 Trigueros Huelva 21620",
    "addr:housenumber":"1",
    "addr:postcode":"21620",
    "addr:street":"Constitucion",
    "iso:country":"ES",
    "sg:address":"Pl. Constitucion, 1",
    "sg:city":"Trigueros",
    "sg:orig_category":"Molduras, Junquillos, Listones Y Molduras Perforadas",
    "sg:phone":"+34 959 30 51 73",
    "sg:postcode":"21620",
    "sg:province":"Huelva",
    "wof:name":"Marin Rebollo Antonio",
    "wof:placetype":"venue"
},
  "geometry": {"coordinates":[-6.8351888657,37.3828887939],"type":"Point"}
}