{
  "type": "Feature",
  "properties": {
    "addr:full":"Calle de Verde Meson, 2 Mengibar Ja\u00e9n 23620",
    "addr:housenumber":"2",
    "addr:postcode":"23620",
    "addr:street":"Calle De Verde Meson;Jae\u0301N",
    "iso:country":"ES",
    "sg:address":"Calle de Verde Meson, 2",
    "sg:city":"Mengibar",
    "sg:orig_category":"Molduras, Junquillos, Listones Y Molduras Perforadas",
    "sg:phone":"+34 953 37 14 00",
    "sg:postcode":"23620",
    "sg:province":"Ja\u00e9n",
    "wof:name":"Amate Zafra Francisco",
    "wof:placetype":"venue"
},
  "geometry": {"coordinates":[-3.8100132942,37.9686164856],"type":"Point"}
}