{
  "type": "Feature",
  "properties": {
    "addr:full":"Plaz Ayuntamiento, 1 Ademuz Valencia 46140",
    "addr:housenumber":"1",
    "addr:postcode":"46140",
    "addr:street":"Ayuntamiento",
    "iso:country":"ES",
    "sg:address":"Plaz Ayuntamiento, 1",
    "sg:city":"Ademuz",
    "sg:orig_category":"Administraciones Regionales, Departamentales Y Locales",
    "sg:phone":"+34 978 78 20 00",
    "sg:postcode":"46140",
    "sg:province":"Valencia",
    "wof:name":"Ayuntamiento De Ademuz",
    "wof:placetype":"venue"
},
  "geometry": {"coordinates":[-1.2568295002,40.0959892273],"type":"Point"}
}