{
  "type": "Feature",
  "properties": {
    "iso:country":"ES",
    "sg:address":"Calle de Isaac Peral, 29",
    "sg:city":"Pe\u00e7arroya-pueblonuevo",
    "sg:orig_category":"Alimentaci\u00d3n General (al Por Menor)",
    "sg:phone":"+34 957 56 04 96",
    "sg:postcode":"14200",
    "sg:province":"C\u00f3rdoba",
    "wof:name":"Cambron Amor Antonia",
    "wof:placetype":"venue"
},
  "geometry": {"coordinates":[-5.259496212,38.3008384705],"type":"Point"}
}