{
  "type": "Feature",
  "properties": {
    "addr:full":"Calle de Cron.vicent Beguer Esteve, 1 Torrent Valencia 46900",
    "addr:housenumber":"1",
    "addr:postcode":"46900",
    "addr:street":"Calle De Cron.Vicent Beguer Esteve;Valencia",
    "iso:country":"ES",
    "sg:address":"Calle de Cron.vicent Beguer Esteve, 1",
    "sg:city":"Torrent",
    "sg:orig_category":"Imprenta",
    "sg:phone":"+34 961 58 11 87",
    "sg:postcode":"46900",
    "sg:province":"Valencia",
    "wof:name":"Publieco Artes Graficas S.l.",
    "wof:placetype":"venue"
},
  "geometry": {"coordinates":[-0.5352355838,39.4127235413],"type":"Point"}
}