{
  "type": "Feature",
  "properties": {
    "iso:country":"ES",
    "sg:address":"Calle de Gonzalo De Berceo, 14",
    "sg:city":"Logro\u00f1o",
    "sg:orig_category":"Peluqueros: De Se\u00d1oras",
    "sg:phone":"+34 941 22 68 13",
    "sg:postcode":"26005",
    "sg:province":"La Rioja",
    "wof:name":"Gomez Sanz Eugenia",
    "wof:placetype":"venue"
},
  "geometry": {"coordinates":[-2.4560797215,42.4657897949],"type":"Point"}
}