{
  "type": "Feature",
  "properties": {
    "addr:full":"Bisbe Sever, 24 Ferreries Islas Baleares 07750",
    "addr:housenumber":"24",
    "addr:postcode":"07750",
    "addr:street":"Sever",
    "iso:country":"ES",
    "sg:address":"Bisbe Sever, 24",
    "sg:city":"Ferreries",
    "sg:orig_category":"Agricultores, Agricultores",
    "sg:phone":"+34 971 15 52 62",
    "sg:postcode":"07750",
    "sg:province":"Islas Baleares",
    "wof:name":"Barber Pons Juan",
    "wof:placetype":"venue"
},
  "geometry": {"coordinates":[4.0122542381,39.9835243225],"type":"Point"}
}