{
  "type": "Feature",
  "properties": {
    "iso:country":"ES",
    "sg:address":"Calle de Iglesia (la), 19",
    "sg:city":"Guardo",
    "sg:orig_category":"Cristaler\u00cdas",
    "sg:phone":"+34 979 85 02 04",
    "sg:postcode":"34880",
    "sg:province":"Palencia",
    "wof:name":"Cristaleria Abad S.l.",
    "wof:placetype":"venue"
},
  "geometry": {"coordinates":[-4.8415241241,42.7889442444],"type":"Point"}
}