{
  "type": "Feature",
  "properties": {
    "iso:country":"ES",
    "sg:address":"Calle de Valdivia, 7",
    "sg:city":"Salamanca",
    "sg:orig_category":"Arreglo, Reparaci\u00d3n, Piezas Sueltas De Televisi\u00d3n, V\u00cddeo, Hi",
    "sg:phone":"+34 923 24 57 01",
    "sg:postcode":"37004",
    "sg:province":"Salamanca",
    "wof:name":"Gudino Hernandez Santiago",
    "wof:placetype":"venue"
},
  "geometry": {"coordinates":[-5.6549110413,40.972328186],"type":"Point"}
}