{
  "type": "Feature",
  "properties": {
    "iso:country":"ES",
    "sg:address":"Avda Mozarabes (de Los), 19",
    "sg:city":"Cordoba",
    "sg:orig_category":"Electrodom\u00c9sticos (al Por Menor)",
    "sg:phone":"+34 957 41 11 89",
    "sg:postcode":"14011",
    "sg:province":"C\u00f3rdoba",
    "wof:name":"Cuesta Aragones Francisco",
    "wof:placetype":"venue"
},
  "geometry": {"coordinates":[-4.7872600555,37.8884048462],"type":"Point"}
}