{
  "type": "Feature",
  "properties": {
    "addr:full":"Ptda Llano San Jose, S/n Elche Alicante 03293",
    "addr:housenumber":"s / n",
    "addr:postcode":"03293",
    "addr:street":"Ptda Llano San Jose",
    "iso:country":"ES",
    "sg:address":"Ptda Llano San Jose, S/n",
    "sg:city":"Elche",
    "sg:orig_category":"Confecci\u00d3n De Zapatos",
    "sg:phone":"+34 965 43 15 13",
    "sg:postcode":"03293",
    "sg:province":"Alicante",
    "wof:name":"Calzados Perpas Sociedad Limitada",
    "wof:placetype":"venue"
},
  "geometry": {"coordinates":[-0.6995239854,38.2634811401],"type":"Point"}
}