{
  "type": "Feature",
  "properties": {
    "iso:country":"ES",
    "sg:address":"Carrer de Cartella, 173",
    "sg:city":"Barcelona",
    "sg:orig_category":"Electrodom\u00c9sticos (al Por Menor)",
    "sg:phone":"+34 934 29 95 54",
    "sg:postcode":"08031",
    "sg:province":"Barcelona",
    "wof:name":"Almape S.a.",
    "wof:placetype":"venue"
},
  "geometry": {"coordinates":[2.1651592255,41.4302024841],"type":"Point"}
}