{
  "type": "Feature",
  "properties": {
    "addr:full":"Calle de Domingo J Navarro, 1 Palmas De Gran Canaria Las Palmas 35002",
    "addr:housenumber":"1",
    "addr:postcode":"35002",
    "addr:street":"Calle De Domingo J Navarro",
    "iso:country":"ES",
    "sg:address":"Calle de Domingo J Navarro, 1",
    "sg:city":"Palmas De Gran Canaria",
    "sg:orig_category":"Inversiones",
    "sg:phone":"+34 928 36 71 30",
    "sg:postcode":"35002",
    "sg:province":"Las Palmas",
    "wof:name":"Inversiones Perez Benitez S.l.",
    "wof:placetype":"venue"
},
  "geometry": {"coordinates":[-15.4169855118,28.1072540283],"type":"Point"}
}