{
  "type": "Feature",
  "properties": {
    "iso:country":"ES",
    "sg:address":"Calle de Fernando El Catolico, 6",
    "sg:city":"Fuentes Ebro",
    "sg:orig_category":"Papeler\u00cdas, Librer\u00cdas",
    "sg:phone":"+34 976 16 02 55",
    "sg:postcode":"50740",
    "sg:province":"Zaragoza",
    "wof:name":"Porroche Miguel Teresa",
    "wof:placetype":"venue"
},
  "geometry": {"coordinates":[-0.6268740296,41.5112380981],"type":"Point"}
}