{
  "type": "Feature",
  "properties": {
    "iso:country":"ES",
    "sg:address":"Calle de Julian Duro, 10",
    "sg:city":"Langreo",
    "sg:orig_category":"Molduras, Junquillos, Listones Y Molduras Perforadas",
    "sg:phone":"+34 985 67 48 83",
    "sg:postcode":"33930",
    "sg:province":"Asturias",
    "wof:name":"Servicios Hosteleros C.b.",
    "wof:placetype":"venue"
},
  "geometry": {"coordinates":[-5.6893601418,43.3076133728],"type":"Point"}
}