{
  "type": "Feature",
  "properties": {
    "addr:full":"Calle de Francisco Javier Sauquillo (de), 2 Mostoles Madrid 28932",
    "addr:postcode":"28932",
    "addr:street":"Calle De Francisco Javier Sauquillo De 2 Mostoles",
    "iso:country":"ES",
    "sg:address":"Calle de Francisco Javier Sauquillo (de), 2",
    "sg:city":"Mostoles",
    "sg:orig_category":"Venta, Colocaci\u00d3n De Autoradios",
    "sg:phone":"+34 916 17 18 03",
    "sg:postcode":"28932",
    "sg:province":"Madrid",
    "wof:name":"Sportmovil Flr S.l.",
    "wof:placetype":"venue"
},
  "geometry": {"coordinates":[-3.855496645,40.3318595886],"type":"Point"}
}