{
  "type": "Feature",
  "properties": {
    "addr:full":"Calle de Museo, 1 Valencia Valencia 46003",
    "addr:housenumber":"1",
    "addr:postcode":"46003",
    "addr:street":"Calle De Museo",
    "iso:country":"ES",
    "sg:address":"Calle de Museo, 1",
    "sg:city":"Valencia",
    "sg:orig_category":"Escultores, Estatuarios E Imagineros",
    "sg:phone":"+34 963 92 31 21",
    "sg:postcode":"46003",
    "sg:province":"Valencia",
    "wof:name":"Marco Saturnino Angeles",
    "wof:placetype":"venue"
},
  "geometry": {"coordinates":[-0.3789390028,39.4792938232],"type":"Point"}
}