{
  "type": "Feature",
  "properties": {
    "iso:country":"ES",
    "sg:address":"Calle de Xana La, 1",
    "sg:city":"Entrego",
    "sg:orig_category":"Centros De Educaci\u00d3n Especial",
    "sg:phone":"+34 985 66 24 05",
    "sg:postcode":"33940",
    "sg:province":"Asturias",
    "wof:name":"Asociacion Discapacitados Psiquicos Rey Aurelio",
    "wof:placetype":"venue"
},
  "geometry": {"coordinates":[-5.6347455978,43.2877006531],"type":"Point"}
}