{
  "type": "Feature",
  "properties": {
    "addr:full":"Calle de San Miguel De Atxa, 4 Vitoria-gasteiz \u00c1lava 01010",
    "addr:housenumber":"4",
    "addr:postcode":"01010",
    "addr:street":"Calle De",
    "iso:country":"ES",
    "sg:address":"Calle de San Miguel De Atxa, 4",
    "sg:city":"Vitoria-gasteiz",
    "sg:orig_category":"Empresas De Carpinter\u00cda De Madera",
    "sg:phone":"+34 945 21 48 00",
    "sg:postcode":"01010",
    "sg:province":"\u00c1lava",
    "wof:name":"Carpinteria Couto S. L.",
    "wof:placetype":"venue"
},
  "geometry": {"coordinates":[-2.7098259926,42.8634986877],"type":"Point"}
}