{
  "type": "Feature",
  "properties": {
    "iso:country":"ES",
    "sg:address":"Calle de Santa Brigida, 9",
    "sg:city":"Ecija",
    "sg:orig_category":"Ferreter\u00cda Artesanal",
    "sg:phone":"+34 954 83 17 44",
    "sg:postcode":"41400",
    "sg:province":"Sevilla",
    "wof:name":"Dominguez Fari\u00f1a Francisco",
    "wof:placetype":"venue"
},
  "geometry": {"coordinates":[-5.0736441612,37.5393104553],"type":"Point"}
}