{
  "type": "Feature",
  "properties": {
    "iso:country":"ES",
    "sg:address":"Calle de Alcala, 142",
    "sg:city":"Madrid",
    "sg:orig_category":"Calzados Ortop\u00c9dicos",
    "sg:phone":"+34 914 01 84 88",
    "sg:postcode":"28009",
    "sg:province":"Madrid",
    "wof:name":"Herederos De Nemesio Lopez Bejarano C.b.",
    "wof:placetype":"venue"
},
  "geometry": {"coordinates":[-3.6702737808,40.4273376465],"type":"Point"}
}