{
  "type": "Feature",
  "properties": {
    "iso:country":"ES",
    "sg:address":"Calle de Puio, 4",
    "sg:city":"Donostia-san Sebastian",
    "sg:orig_category":"Servicios Gsm",
    "sg:phone":"+34 943 31 33 43",
    "sg:postcode":"20009",
    "sg:province":"Guip\u00f9zcoa",
    "sg:website":"www.ditelcom.es",
    "wof:name":"Didac Telecom S.l.",
    "wof:placetype":"venue"
},
  "geometry": {"coordinates":[-1.9861600399,43.3015899658],"type":"Point"}
}