{
  "type": "Feature",
  "properties": {
    "addr:full":"Carrer de Cabanyes, 48 Sabadell Barcelona 08203",
    "addr:housenumber":"48",
    "addr:postcode":"08203",
    "addr:street":"Carrer De Cabanyes",
    "iso:country":"ES",
    "sg:address":"Carrer de Cabanyes, 48",
    "sg:city":"Sabadell",
    "sg:orig_category":"Automatizaci\u00d3n De Procesos Industriales Y De Edificaci\u00d3n (estudios, Instalaci\u00d3n)",
    "sg:phone":"+34 937 12 43 48",
    "sg:postcode":"08203",
    "sg:province":"Barcelona",
    "wof:name":"Tecnos Automatizacion S.l.",
    "wof:placetype":"venue"
},
  "geometry": {"coordinates":[2.1062569618,41.5334472656],"type":"Point"}
}