{
  "type": "Feature",
  "properties": {
    "addr:full":"Calle de Fuente De Lima, 7 Madrid Madrid 28024",
    "addr:housenumber":"7",
    "addr:postcode":"madrid;28024",
    "addr:street":"Calle De Fuente De Lima",
    "iso:country":"ES",
    "sg:address":"Calle de Fuente De Lima, 7",
    "sg:city":"Madrid",
    "sg:orig_category":"Poller\u00cda Y Caza (al Por Menor)",
    "sg:phone":"+34 917 10 74 68",
    "sg:postcode":"28024",
    "sg:province":"Madrid",
    "wof:name":"Pradillo Alonso Maria Del Carmen",
    "wof:placetype":"venue"
},
  "geometry": {"coordinates":[-3.7837779522,40.3839149475],"type":"Point"}
}