{
  "type": "Feature",
  "properties": {
    "addr:full":"Rond San Antonio, 22 Yunquera Henares Guadalajara 19210",
    "addr:housenumber":"22",
    "addr:postcode":"19210",
    "addr:street":"San Antonio",
    "iso:country":"ES",
    "sg:address":"Rond San Antonio, 22",
    "sg:city":"Yunquera Henares",
    "sg:orig_category":"Empresas De Carpinter\u00cda",
    "sg:phone":"+34 949 82 05 72",
    "sg:postcode":"19210",
    "sg:province":"Guadalajara",
    "wof:name":"Dongil Martin Miguel",
    "wof:placetype":"venue"
},
  "geometry": {"coordinates":[-3.1650300026,40.7522735596],"type":"Point"}
}