{
  "type": "Feature",
  "properties": {
    "addr:full":"Carr General Weyler, 98 Badalona Barcelona 08912",
    "addr:housenumber":"98",
    "addr:postcode":"08912",
    "addr:street":"Carr General Weyler",
    "iso:country":"ES",
    "sg:address":"Carr General Weyler, 98",
    "sg:city":"Badalona",
    "sg:orig_category":"Artes Gr\u00c1ficas, Artes Pl\u00c1sticas (curso)",
    "sg:phone":"+34 933 83 71 55",
    "sg:postcode":"08912",
    "sg:province":"Barcelona",
    "wof:name":"Buenafuente Iglesias Josep",
    "wof:placetype":"venue"
},
  "geometry": {"coordinates":[2.2393300533,41.4415855408],"type":"Point"}
}