{
  "type": "Feature",
  "properties": {
    "addr:full":"Atv Madrid-toledo, 3 Illescas Toledo 45200",
    "addr:housenumber":"3",
    "addr:postcode":"45200",
    "addr:street":"Madrid-Toledo",
    "iso:country":"ES",
    "sg:address":"Atv Madrid-toledo, 3",
    "sg:city":"Illescas",
    "sg:orig_category":"Tapicer\u00cdas",
    "sg:phone":"+34 925 51 29 70",
    "sg:postcode":"45200",
    "sg:province":"Toledo",
    "wof:name":"Solo Sofas S.l.",
    "wof:placetype":"venue"
},
  "geometry": {"coordinates":[-3.8594288826,40.1091804504],"type":"Point"}
}