{
  "type": "Feature",
  "properties": {
    "addr:full":"Carrer de Montserrat, 10 S. Cugat Valles Barcelona 08172",
    "addr:housenumber":"10",
    "addr:postcode":"08172",
    "addr:street":"Carrer De Montserrat;Barcelona",
    "iso:country":"ES",
    "sg:address":"Carrer de Montserrat, 10",
    "sg:city":"S. Cugat Valles",
    "sg:orig_category":"Promotores Constructores",
    "sg:phone":"+34 936 74 00 12",
    "sg:postcode":"08172",
    "sg:province":"Barcelona",
    "wof:name":"Sibell Sant Cugat S.l.",
    "wof:placetype":"venue"
},
  "geometry": {"coordinates":[2.0883328915,41.4726829529],"type":"Point"}
}