{
  "type": "Feature",
  "properties": {
    "addr:full":"Calle de Ibarluze, 22 Galdakao Vizcaya 48960",
    "addr:housenumber":"22",
    "addr:postcode":"48960",
    "addr:street":"Calle De Ibarluze",
    "iso:country":"ES",
    "sg:address":"Calle de Ibarluze, 22",
    "sg:city":"Galdakao",
    "sg:orig_category":"Ense\u00d1anza: Costura",
    "sg:phone":"+34 944 56 56 66",
    "sg:postcode":"48960",
    "sg:province":"Vizcaya",
    "wof:name":"Ana Isabel Garcia Corral",
    "wof:placetype":"venue"
},
  "geometry": {"coordinates":[-2.8463687897,43.2290611267],"type":"Point"}
}