{
  "type": "Feature",
  "properties": {
    "addr:full":"Carrer de Freneria, 1 Barcelona Barcelona 08002",
    "addr:housenumber":"1",
    "addr:postcode":"08002",
    "addr:street":"Carrer De Freneria",
    "iso:country":"ES",
    "sg:address":"Carrer de Freneria, 1",
    "sg:city":"Barcelona",
    "sg:orig_category":"Porcelanas, Azulejos (fabricaci\u00d3n, Al Por Mayor)",
    "sg:phone":"+34 933 15 17 04",
    "sg:postcode":"08002",
    "sg:province":"Barcelona",
    "wof:name":"Garreta Sintas Marcel-li",
    "wof:placetype":"venue"
},
  "geometry": {"coordinates":[2.1774249077,41.3836250305],"type":"Point"}
}