{
  "type": "Feature",
  "properties": {
    "iso:country":"ES",
    "sg:address":"Rua Salvador De Madariaga, 1",
    "sg:city":"Lugo",
    "sg:orig_category":"M\u00c9dicos: Estomatolog\u00cda",
    "sg:phone":"+34 982 22 43 31",
    "sg:postcode":"27002",
    "sg:province":"Lugo",
    "wof:name":"Dozaclin S.l.",
    "wof:placetype":"venue"
},
  "geometry": {"coordinates":[-7.5554590225,43.0059814453],"type":"Point"}
}