{
  "type": "Feature",
  "properties": {
    "iso:country":"ES",
    "sg:address":"Ctra Terrassa, 20",
    "sg:city":"Sabadell",
    "sg:orig_category":"Asociaciones Y Clubs Deportivos",
    "sg:phone":"+34 937 27 77 57",
    "sg:postcode":"08201",
    "sg:province":"Barcelona",
    "wof:name":"Beom Je Kim",
    "wof:placetype":"venue"
},
  "geometry": {"coordinates":[2.1024639606,41.5439071655],"type":"Point"}
}