{
  "type": "Feature",
  "properties": {
    "addr:full":"Calle de Juan Xxiii, 37 Caceres C\u00e1ceres 10005",
    "addr:housenumber":"37",
    "addr:postcode":"10005",
    "addr:street":"Calle De Juan Xxiii;Ca\u0301Ceres",
    "iso:country":"ES",
    "sg:address":"Calle de Juan Xxiii, 37",
    "sg:city":"Caceres",
    "sg:orig_category":"Peluqueros: De Se\u00d1oras",
    "sg:phone":"+34 927 23 25 20",
    "sg:postcode":"10005",
    "sg:province":"C\u00e1ceres",
    "wof:name":"Pascual Cambero Juan",
    "wof:placetype":"venue"
},
  "geometry": {"coordinates":[-6.383878231,39.465763092],"type":"Point"}
}