{
  "type": "Feature",
  "properties": {
    "addr:full":"Av Lleo, S/n Reus Tarragona 43202",
    "addr:housenumber":"s / n",
    "addr:postcode":"43202",
    "addr:street":"Av Lleo",
    "iso:country":"ES",
    "sg:address":"Av Lleo, S/n",
    "sg:city":"Reus",
    "sg:orig_category":"Empresas De Pintura Y Revestimientos",
    "sg:phone":"+34 977 31 99 23",
    "sg:postcode":"43202",
    "sg:province":"Tarragona",
    "wof:name":"Alvarez Mu\u00f1oz Antonio",
    "wof:placetype":"venue"
},
  "geometry": {"coordinates":[1.0959769487,41.1628074646],"type":"Point"}
}