{
  "type": "Feature",
  "properties": {
    "iso:country":"ES",
    "sg:address":"Avda Castilla, 9",
    "sg:city":"Antilla",
    "sg:orig_category":"Mataderos Y Talleres De Despiezado",
    "sg:phone":"+34 959 48 13 85",
    "sg:postcode":"21449",
    "sg:province":"Huelva",
    "wof:name":"Comercial Andaluza De Carnes S.l.",
    "wof:placetype":"venue"
},
  "geometry": {"coordinates":[-7.2165207863,37.2065582275],"type":"Point"}
}