{
  "type": "Feature",
  "properties": {
    "addr:full":"Pase Extremadura, 128 Monesterio Badajoz 06260",
    "addr:housenumber":"128",
    "addr:postcode":"06260",
    "addr:street":"Extremadura",
    "iso:country":"ES",
    "sg:address":"Pase Extremadura, 128",
    "sg:city":"Monesterio",
    "sg:orig_category":"Electrodom\u00c9sticos (al Por Menor)",
    "sg:phone":"+34 924 51 60 86",
    "sg:postcode":"06260",
    "sg:province":"Badajoz",
    "wof:name":"Comercial Bautcar,s.a.",
    "wof:placetype":"venue"
},
  "geometry": {"coordinates":[-6.2733812332,38.0895690918],"type":"Point"}
}