{
  "type": "Feature",
  "properties": {
    "addr:full":"Calle de Residencia, 36 San Lorenzo De El Escorial Madrid 28200",
    "addr:housenumber":"36",
    "addr:postcode":"28200",
    "addr:street":"Calle De Residencia",
    "iso:country":"ES",
    "sg:address":"Calle de Residencia, 36",
    "sg:city":"San Lorenzo De El Escorial",
    "sg:orig_category":"Farmacias",
    "sg:phone":"+34 918 98 21 67",
    "sg:postcode":"28200",
    "sg:province":"Madrid",
    "wof:name":"Soria Laborda Jose Antonio",
    "wof:placetype":"venue"
},
  "geometry": {"coordinates":[-4.1425318718,40.5991859436],"type":"Point"}
}