{
  "type": "Feature",
  "properties": {
    "addr:full":"Calle de Constitucion, 16 Guadalajara Guadalajara 19003",
    "addr:postcode":"19003",
    "addr:street":"Calle De Constitucion 16",
    "iso:country":"ES",
    "sg:address":"Calle de Constitucion, 16",
    "sg:city":"Guadalajara",
    "sg:orig_category":"Guarder\u00cdas",
    "sg:phone":"+34 949 21 98 45",
    "sg:postcode":"19003",
    "sg:province":"Guadalajara",
    "wof:name":"Maria Gema Utrilla Rodriguez Y Otras Cdad.",
    "wof:placetype":"venue"
},
  "geometry": {"coordinates":[-3.1753799915,40.628692627],"type":"Point"}
}