{
  "type": "Feature",
  "properties": {
    "addr:full":"Calle de Pedro I De Aragon, 5 Huesca Huesca 22003",
    "addr:housenumber":"5",
    "addr:postcode":"22003",
    "addr:street":"Calle De Pedro I De Aragon",
    "iso:country":"ES",
    "sg:address":"Calle de Pedro I De Aragon, 5",
    "sg:city":"Huesca",
    "sg:orig_category":"Ropa Para Caballeros (al Por Menor)",
    "sg:phone":"+34 974 24 12 26",
    "sg:postcode":"22003",
    "sg:province":"Huesca",
    "wof:name":"Iniciativas Textiles Del Este S.l",
    "wof:placetype":"venue"
},
  "geometry": {"coordinates":[-0.4128189981,42.1395263672],"type":"Point"}
}