{
  "type": "Feature",
  "properties": {
    "addr:full":"Calle de Emilio Ferrari, 56 Madrid Madrid 28017",
    "addr:housenumber":"56",
    "addr:postcode":"madrid;28017",
    "addr:street":"Calle De Emilio Ferrari",
    "iso:country":"ES",
    "sg:address":"Calle de Emilio Ferrari, 56",
    "sg:city":"Madrid",
    "sg:orig_category":"Cajas De Ahorro",
    "sg:phone":"+34 913 67 73 10",
    "sg:postcode":"28017",
    "sg:province":"Madrid",
    "sg:website":"www.caixalaietana.es",
    "wof:name":"Caixa D'estalvis Laietana",
    "wof:placetype":"venue"
},
  "geometry": {"coordinates":[-3.6414299011,40.4313621521],"type":"Point"}
}