{
  "type": "Feature",
  "properties": {
    "addr:full":"Calle de Encarnacion, 17 Lepe Huelva 21440",
    "addr:housenumber":"17",
    "addr:postcode":"21440",
    "addr:street":"Calle De Encarnacion",
    "iso:country":"ES",
    "sg:address":"Calle de Encarnacion, 17",
    "sg:city":"Lepe",
    "sg:orig_category":"Centros De Coordinaci\u00d3n",
    "sg:phone":"+34 959 38 47 24",
    "sg:postcode":"21440",
    "sg:province":"Huelva",
    "wof:name":"Ingenieria Y Medicina Preventiva S.l.",
    "wof:placetype":"venue"
},
  "geometry": {"coordinates":[-7.2041726112,37.2557144165],"type":"Point"}
}