{
  "type": "Feature",
  "properties": {
    "addr:full":"Calle de Pidal, 13 Hornachos Badajoz 06228",
    "addr:housenumber":"13",
    "addr:postcode":"06228",
    "addr:street":"Calle De Pidal",
    "iso:country":"ES",
    "sg:address":"Calle de Pidal, 13",
    "sg:city":"Hornachos",
    "sg:orig_category":"Doctores En Medicina",
    "sg:phone":"+34 924 53 31 94",
    "sg:postcode":"06228",
    "sg:province":"Badajoz",
    "wof:name":"Rodriguez Revenga Miguel Angel",
    "wof:placetype":"venue"
},
  "geometry": {"coordinates":[-6.0721697807,38.5533332825],"type":"Point"}
}