{
  "type": "Feature",
  "properties": {
    "iso:country":"ES",
    "sg:address":"Calle de Maestro Guerrero, 4",
    "sg:city":"Valencia",
    "sg:orig_category":"Mec\u00c1nico Del Autom\u00d3vil",
    "sg:phone":"+34 963 82 09 92",
    "sg:postcode":"46008",
    "sg:province":"Valencia",
    "wof:name":"Talleres Vicente Fas S.l.",
    "wof:placetype":"venue"
},
  "geometry": {"coordinates":[-0.3919560015,39.4739837646],"type":"Point"}
}