{
  "type": "Feature",
  "properties": {
    "addr:full":"Av California, 66 Miami Playa Tarragona 43892",
    "addr:housenumber":"66",
    "addr:postcode":"43892",
    "addr:street":"Av California",
    "iso:country":"ES",
    "sg:address":"Av California, 66",
    "sg:city":"Miami Playa",
    "sg:orig_category":"Promotores Constructores",
    "sg:phone":"+34 977 81 08 74",
    "sg:postcode":"43892",
    "sg:province":"Tarragona",
    "wof:name":"Ortega Lozano S.l.",
    "wof:placetype":"venue"
},
  "geometry": {"coordinates":[0.9289289713,41.0104255676],"type":"Point"}
}