{
  "type": "Feature",
  "properties": {
    "iso:country":"ES",
    "sg:address":"Avda Reyes Catolicos, 93",
    "sg:city":"Villarrobledo",
    "sg:orig_category":"Imprenta",
    "sg:phone":"+34 967 14 09 08",
    "sg:postcode":"02600",
    "sg:province":"Albacete",
    "wof:name":"Papel Para Impresoras S.a.",
    "wof:placetype":"venue"
},
  "geometry": {"coordinates":[-2.5970170498,39.2674598694],"type":"Point"}
}