{
  "type": "Feature",
  "properties": {
    "addr:full":"Calle de Merced, 12 San Lorenzo Murcia 30001",
    "addr:housenumber":"12",
    "addr:postcode":"30001",
    "addr:street":"Calle De Merced",
    "iso:country":"ES",
    "sg:address":"Calle de Merced, 12",
    "sg:city":"San Lorenzo",
    "sg:orig_category":"Asociaciones Humanitarias, De Cooperaci\u00d3n, De Acci\u00d3n Social",
    "sg:phone":"+34 968 20 22 06",
    "sg:postcode":"30001",
    "sg:province":"Murcia",
    "wof:name":"Asociacion De Ayuda Al Enfermo Renal",
    "wof:placetype":"venue"
},
  "geometry": {"coordinates":[-1.1298867464,37.9834747314],"type":"Point"}
}