{
  "type": "Feature",
  "properties": {
    "iso:country":"ES",
    "sg:address":"Calle de Campi\u00d1a, 2",
    "sg:city":"Madrid",
    "sg:orig_category":"Molduras, Junquillos, Listones Y Molduras Perforadas",
    "sg:phone":"+34 915 07 45 85",
    "sg:postcode":"28053",
    "sg:province":"Madrid",
    "wof:name":"Vardi Telecom S.l.",
    "wof:placetype":"venue"
},
  "geometry": {"coordinates":[-3.6708788872,40.3794136047],"type":"Point"}
}