{
  "type": "Feature",
  "properties": {
    "addr:full":"Calle de General Pardi\u00d1as, 35 Madrid Madrid 28001",
    "addr:housenumber":"35",
    "addr:postcode":"madrid;28001",
    "addr:street":"Calle De General Pardin\u0303As",
    "iso:country":"ES",
    "sg:address":"Calle de General Pardi\u00d1as, 35",
    "sg:city":"Madrid",
    "sg:orig_category":"Florister\u00cdas",
    "sg:phone":"+34 914 31 51 23",
    "sg:postcode":"28001",
    "sg:province":"Madrid",
    "wof:name":"Floristeria Dicenta",
    "wof:placetype":"venue"
},
  "geometry": {"coordinates":[-3.6784665585,40.42735672],"type":"Point"}
}