{
  "type": "Feature",
  "properties": {
    "iso:country":"ES",
    "sg:address":"San Roque, 6",
    "sg:city":"Puebla Lillo",
    "sg:orig_category":"Venta, Instalaci\u00d3n De Calefacci\u00d3n",
    "sg:phone":"+34 987 73 13 30",
    "sg:postcode":"24855",
    "sg:province":"Le\u00f3n",
    "wof:name":"Fa.r.h.o. Fabrica De Radiadores Hermanos Ochoa S.l.",
    "wof:placetype":"venue"
},
  "geometry": {"coordinates":[-5.2745919228,43.0073623657],"type":"Point"}
}