{
  "type": "Feature",
  "properties": {
    "addr:full":"Calle de Jeronimo De Roda, 1 San Miguel Murcia 30005",
    "addr:housenumber":"1",
    "addr:postcode":"30005",
    "addr:street":"Calle De Jeronimo De Roda",
    "iso:country":"ES",
    "sg:address":"Calle de Jeronimo De Roda, 1",
    "sg:city":"San Miguel",
    "sg:orig_category":"Abogados",
    "sg:phone":"+34 968 27 40 03",
    "sg:postcode":"30005",
    "sg:province":"Murcia",
    "wof:name":"Barcelo Sempere Maria Dolores",
    "wof:placetype":"venue"
},
  "geometry": {"coordinates":[-1.1351480484,37.9886856079],"type":"Point"}
}