{
  "type": "Feature",
  "properties": {
    "addr:full":"Carrer de Sant Ramon Nonat, 2 Maravillas Islas Baleares 07610",
    "addr:housenumber":"2",
    "addr:postcode":"07610",
    "addr:street":"Carrer De Sant;Nonat",
    "iso:country":"ES",
    "sg:address":"Carrer de Sant Ramon Nonat, 2",
    "sg:city":"Maravillas",
    "sg:orig_category":"Iglesia Cat\u00d3lica",
    "sg:phone":"+34 971 26 28 93",
    "sg:postcode":"07610",
    "sg:province":"Islas Baleares",
    "wof:name":"Obispado De Mallorca",
    "wof:placetype":"venue"
},
  "geometry": {"coordinates":[2.7243249416,39.5336914062],"type":"Point"}
}