{
  "type": "Feature",
  "properties": {
    "iso:country":"ES",
    "sg:address":"Calle de John Lennon, 15",
    "sg:city":"Merida",
    "sg:orig_category":"Centros De Reservas Hoteleras",
    "sg:phone":"+34 924 30 36 43",
    "sg:postcode":"06800",
    "sg:province":"Badajoz",
    "wof:name":"Imagene Gestiones E Inversiones S.l",
    "wof:placetype":"venue"
},
  "geometry": {"coordinates":[-6.3450517654,38.9148483276],"type":"Point"}
}