{
  "type": "Feature",
  "properties": {
    "addr:full":"Ci. Del Carrilet, 108 S. Feliu Guixols Girona 17220",
    "addr:housenumber":"108",
    "addr:postcode":"17220",
    "addr:street":"S. Feliu Guixols",
    "iso:country":"ES",
    "sg:address":"Ci. Del Carrilet, 108",
    "sg:city":"S. Feliu Guixols",
    "sg:orig_category":"Agencias Y Agentes Comerciales, Representantes",
    "sg:phone":"+34 972 32 50 87",
    "sg:postcode":"17220",
    "sg:province":"Girona",
    "wof:name":"Eurovista Park S.l.",
    "wof:placetype":"venue"
},
  "geometry": {"coordinates":[3.0378599167,41.7843742371],"type":"Point"}
}