{
  "type": "Feature",
  "properties": {
    "addr:full":"Calle de Libertades (de Las), 24 Chiclana De La Frontera C\u00e1diz 11130",
    "addr:housenumber":"24",
    "addr:postcode":"11130",
    "addr:street":"Calle De Libertades De Las",
    "iso:country":"ES",
    "sg:address":"Calle de Libertades (de Las), 24",
    "sg:city":"Chiclana De La Frontera",
    "sg:orig_category":"Alimentaci\u00d3n General (al Por Mayor)",
    "sg:phone":"+34 956 53 53 65",
    "sg:postcode":"11130",
    "sg:province":"C\u00e1diz",
    "wof:name":"Piensos Y Cereales Jarasan S.l.",
    "wof:placetype":"venue"
},
  "geometry": {"coordinates":[-6.1267762184,36.4045982361],"type":"Point"}
}