{
  "type": "Feature",
  "properties": {
    "iso:country":"ES",
    "sg:address":"Calle de Santander, 11",
    "sg:city":"Alcala Guadaira",
    "sg:orig_category":"Ropa Para Se\u00d1oras (al Por Menor)",
    "sg:phone":"+34 955 61 30 90",
    "sg:postcode":"41500",
    "sg:province":"Sevilla",
    "wof:name":"Confecciones A V Import-export S.l.",
    "wof:placetype":"venue"
},
  "geometry": {"coordinates":[-5.8372168541,37.3371162415],"type":"Point"}
}