{
  "type": "Feature",
  "properties": {
    "addr:full":"Calle de Pinta, 12 Sevilla Sevilla 41008",
    "addr:housenumber":"12",
    "addr:postcode":"41008",
    "addr:street":"Calle De Pinta",
    "iso:country":"ES",
    "sg:address":"Calle de Pinta, 12",
    "sg:city":"Sevilla",
    "sg:orig_category":"Asociaciones, Organismos Culturales Y Socioeducativos",
    "sg:phone":"+34 954 41 65 14",
    "sg:postcode":"41008",
    "sg:province":"Sevilla",
    "wof:name":"Pe\u00f1a Sevillista El Fontanal",
    "wof:placetype":"venue"
},
  "geometry": {"coordinates":[-5.9767770767,37.3979148865],"type":"Point"}
}