{
  "type": "Feature",
  "properties": {
    "iso:country":"ES",
    "sg:address":"Carr General Brito, 10",
    "sg:city":"Lleida",
    "sg:orig_category":"Restaurantes",
    "sg:phone":"+34 973 23 19 42",
    "sg:postcode":"25007",
    "sg:province":"Lleida",
    "wof:name":"El Celleret Del Segre S.l.",
    "wof:placetype":"venue"
},
  "geometry": {"coordinates":[0.6326479912,41.6178894043],"type":"Point"}
}