{
  "type": "Feature",
  "properties": {
    "iso:country":"ES",
    "sg:address":"Calle de Joaquin Marquez, 9",
    "sg:city":"Madrid",
    "sg:orig_category":"Molduras, Junquillos, Listones Y Molduras Perforadas",
    "sg:phone":"+34 914 75 35 81",
    "sg:postcode":"28026",
    "sg:province":"Madrid",
    "wof:name":"Chapa Hernandez Mariano",
    "wof:placetype":"venue"
},
  "geometry": {"coordinates":[-3.7095720768,40.3850097656],"type":"Point"}
}