{
  "type": "Feature",
  "properties": {
    "addr:full":"Rbla Salvador Lluch, 12 Gava Barcelona 08850",
    "addr:housenumber":"12",
    "addr:postcode":"08850",
    "addr:street":"Rbla Salvador Lluch",
    "iso:country":"ES",
    "sg:address":"Rbla Salvador Lluch, 12",
    "sg:city":"Gava",
    "sg:orig_category":"Ropa Para Caballeros (al Por Menor)",
    "sg:phone":"+34 936 62 57 02",
    "sg:postcode":"08850",
    "sg:province":"Barcelona",
    "wof:name":"Legares Valles Javier",
    "wof:placetype":"venue"
},
  "geometry": {"coordinates":[2.0052509308,41.3055915833],"type":"Point"}
}