{
  "type": "Feature",
  "properties": {
    "addr:full":"Calle de Torrelaguna, 52 Sevilla Sevilla 41016",
    "addr:housenumber":"52",
    "addr:postcode":"41016",
    "addr:street":"Calle De Torrelaguna",
    "iso:country":"ES",
    "sg:address":"Calle de Torrelaguna, 52",
    "sg:city":"Sevilla",
    "sg:orig_category":"Abogados",
    "sg:phone":"+34 954 40 00 59",
    "sg:postcode":"41016",
    "sg:province":"Sevilla",
    "wof:name":"Cordoba Calderon Daniel",
    "wof:placetype":"venue"
},
  "geometry": {"coordinates":[-5.9067292213,37.3852996826],"type":"Point"}
}