{
  "type": "Feature",
  "properties": {
    "addr:full":"Barr Ventas, 35 Irun Guip\u00f9zcoa 20305",
    "addr:housenumber":"35",
    "addr:postcode":"20305",
    "addr:street":"Ventas;Guipu\u0300Zcoa",
    "iso:country":"ES",
    "sg:address":"Barr Ventas, 35",
    "sg:city":"Irun",
    "sg:orig_category":"Cerrajer\u00cda, Ferrallista",
    "sg:phone":"+34 943 63 42 23",
    "sg:postcode":"20305",
    "sg:province":"Guip\u00f9zcoa",
    "sg:website":"www.tesa.es",
    "wof:name":"Talleres De Escoriaza S.a.",
    "wof:placetype":"venue"
},
  "geometry": {"coordinates":[-1.7637690306,43.3425445557],"type":"Point"}
}