{
  "type": "Feature",
  "properties": {
    "iso:country":"ES",
    "sg:address":"Carr Santiago, 3",
    "sg:city":"Badalona",
    "sg:orig_category":"M\u00c9dicos: Medicina Interna",
    "sg:phone":"+34 933 87 13 46",
    "sg:postcode":"08918",
    "sg:province":"Barcelona",
    "wof:name":"Fabregat Garcia Ramon",
    "wof:placetype":"venue"
},
  "geometry": {"coordinates":[2.2190170288,41.4342880249],"type":"Point"}
}