{
  "type": "Feature",
  "properties": {
    "iso:country":"ES",
    "sg:address":"Calle de Prim, 58",
    "sg:city":"Bilbao",
    "sg:orig_category":"Electricidad Veh\u00cdculo",
    "sg:phone":"+34 944 05 66 16",
    "sg:postcode":"48006",
    "sg:province":"Vizcaya",
    "wof:name":"Morejon Rodriguez Asier",
    "wof:placetype":"venue"
},
  "geometry": {"coordinates":[-2.9145040512,43.2569541931],"type":"Point"}
}