{
  "type": "Feature",
  "properties": {
    "addr:full":"Carrer de Marques De Campo, 40 Denia Alicante 03700",
    "addr:housenumber":"40",
    "addr:postcode":"03700",
    "addr:street":"Carrer De Marques De Campo",
    "iso:country":"ES",
    "sg:address":"Carrer de Marques De Campo, 40",
    "sg:city":"Denia",
    "sg:orig_category":"Centros De Coordinaci\u00d3n",
    "sg:phone":"+34 966 42 65 96",
    "sg:postcode":"03700",
    "sg:province":"Alicante",
    "wof:name":"Intlprivate Trust & Consulting S.l.",
    "wof:placetype":"venue"
},
  "geometry": {"coordinates":[0.1092789993,38.8404541016],"type":"Point"}
}