{
  "type": "Feature",
  "properties": {
    "addr:full":"Calle de Olivo, 52 Villanueva Cordoba C\u00f3rdoba 14440",
    "addr:housenumber":"52;cordoba co\u0301rdoba",
    "addr:postcode":"14440",
    "addr:street":"Calle De Olivo",
    "iso:country":"ES",
    "sg:address":"Calle de Olivo, 52",
    "sg:city":"Villanueva Cordoba",
    "sg:orig_category":"Supermercados Y Hipermercados",
    "sg:phone":"+34 957 12 34 54",
    "sg:postcode":"14440",
    "sg:province":"C\u00f3rdoba",
    "wof:name":"Isabu E Hijos S.l.",
    "wof:placetype":"venue"
},
  "geometry": {"coordinates":[-4.6296610832,38.3253822327],"type":"Point"}
}