{
  "type": "Feature",
  "properties": {
    "iso:country":"ES",
    "sg:address":"Av Sarria, 67",
    "sg:city":"Barcelona",
    "sg:orig_category":"Construcciones Met\u00c1licas",
    "sg:phone":"+34 934 39 17 93",
    "sg:postcode":"08029",
    "sg:province":"Barcelona",
    "wof:name":"Estrumetal Aiguaviva S.l.",
    "wof:placetype":"venue"
},
  "geometry": {"coordinates":[2.1410000324,41.3907546997],"type":"Point"}
}