{
  "type": "Feature",
  "properties": {
    "addr:full":"Calle de Laguna Negra, S/n Vinuesa Soria 42150",
    "addr:housenumber":"s / n",
    "addr:postcode":"42150",
    "addr:street":"Calle De Laguna Negra",
    "iso:country":"ES",
    "sg:address":"Calle de Laguna Negra, S/n",
    "sg:city":"Vinuesa",
    "sg:orig_category":"Albergues",
    "sg:phone":"+34 975 37 83 54",
    "sg:postcode":"42150",
    "sg:province":"Soria",
    "wof:name":"Lopez Chinchilla Pedro Julio",
    "wof:placetype":"venue"
},
  "geometry": {"coordinates":[-2.761729002,41.9093589783],"type":"Point"}
}