{
  "type": "Feature",
  "properties": {
    "iso:country":"ES",
    "sg:address":"Carr Cristofol De Boleda, 1",
    "sg:city":"Lleida",
    "sg:orig_category":"Ropa Para Se\u00d1oras Y Caballeros (al Por Menor)",
    "sg:phone":"+34 973 27 38 20",
    "sg:postcode":"25006",
    "sg:province":"Lleida",
    "wof:name":"Pascual Villamazares Maria Asuncion",
    "wof:placetype":"venue"
},
  "geometry": {"coordinates":[0.6143019795,41.6189918518],"type":"Point"}
}