{
  "type": "Feature",
  "properties": {
    "iso:country":"ES",
    "sg:address":"Trva Sagarminaga, 44",
    "sg:city":"Bilbao",
    "sg:orig_category":"Aer\u00d3grafo",
    "sg:phone":"+34 944 73 09 47",
    "sg:postcode":"48004",
    "sg:province":"Vizcaya",
    "sg:website":"www.juanjobaron.com",
    "wof:name":"Baron Herrero Juan Jose",
    "wof:placetype":"venue"
},
  "geometry": {"coordinates":[-2.9119861126,43.2482185364],"type":"Point"}
}