{
  "type": "Feature",
  "properties": {
    "addr:full":"Carrer de Pla\u00c7a, S/n Premia Mar Barcelona 08330",
    "addr:housenumber":"s",
    "addr:postcode":"08330",
    "addr:street":"Carrer De Plac\u0327A;/ N",
    "iso:country":"ES",
    "sg:address":"Carrer de Pla\u00c7a, S/n",
    "sg:city":"Premia Mar",
    "sg:orig_category":"Bancos",
    "sg:phone":"+34 937 51 12 50",
    "sg:postcode":"08330",
    "sg:province":"Barcelona",
    "sg:website":"www.bancosabadell.com",
    "wof:name":"Banc Sabadell S.a.",
    "wof:placetype":"venue"
},
  "geometry": {"coordinates":[2.3534350395,41.4946899414],"type":"Point"}
}