{
  "type": "Feature",
  "properties": {
    "addr:full":"Urb Dehesa Campoamor, S/n Dehesa Campoamor Alicante 03189",
    "addr:housenumber":"s / n",
    "addr:postcode":"03189",
    "iso:country":"ES",
    "sg:address":"Urb Dehesa Campoamor, S/n",
    "sg:city":"Dehesa Campoamor",
    "sg:orig_category":"Heladeros",
    "sg:phone":"+34 965 32 05 35",
    "sg:postcode":"03189",
    "sg:province":"Alicante",
    "wof:name":"Garcia Munuera Maria Carmen",
    "wof:placetype":"venue"
},
  "geometry": {"coordinates":[-0.4810059965,38.3452033997],"type":"Point"}
}