{
  "type": "Feature",
  "properties": {
    "addr:full":"A, 13 Bara\u00f1ain Navarra 31010",
    "addr:housenumber":"13",
    "addr:postcode":"31010",
    "addr:street":"A",
    "iso:country":"ES",
    "sg:address":"A, 13",
    "sg:city":"Bara\u00f1ain",
    "sg:orig_category":"Aparatos, Sistemas De Tele",
    "sg:phone":"+34 948 18 12 85",
    "sg:postcode":"31010",
    "sg:province":"Navarra",
    "sg:website":"www.prosegur.es",
    "wof:name":"Prosegur Transportes De Valores S.a.",
    "wof:placetype":"venue"
},
  "geometry": {"coordinates":[-97.78224945069999,45.7040786743],"type":"Point"}
}