{
  "type": "Feature",
  "properties": {
    "iso:country":"ES",
    "sg:address":"Calle de Dos De Mayo, 16",
    "sg:city":"Alcantarilla",
    "sg:orig_category":"Bancos",
    "sg:phone":"+34 968 80 16 79",
    "sg:postcode":"30820",
    "sg:province":"Murcia",
    "wof:name":"Carrillo Hernandez Miguel",
    "wof:placetype":"venue"
},
  "geometry": {"coordinates":[-1.2213484049,37.9691581726],"type":"Point"}
}