{
  "type": "Feature",
  "properties": {
    "iso:country":"ES",
    "sg:address":"Pla\u00c7 Sant Joan, 2",
    "sg:city":"Lleida",
    "sg:orig_category":"Ropa Para Ni\u00d1os (al Por Menor)",
    "sg:phone":"+34 973 24 49 06",
    "sg:postcode":"25007",
    "sg:province":"Lleida",
    "sg:website":"www.bershka.com",
    "wof:name":"Bershka Bsr Espa\u00d1a S.a.",
    "wof:placetype":"venue"
},
  "geometry": {"coordinates":[0.6278700233,41.616355896],"type":"Point"}
}