{
  "type": "Feature",
  "properties": {
    "iso:country":"ES",
    "sg:address":"Calle de Sagunto, 67",
    "sg:city":"Cordoba",
    "sg:orig_category":"Importaci\u00d3n, Exportaci\u00d3n Y Comercios De Productos Textiles",
    "sg:phone":"+34 957 25 28 06",
    "sg:postcode":"14007",
    "sg:province":"C\u00f3rdoba",
    "wof:name":"Serrano Martinez Josefa Rosario",
    "wof:placetype":"venue"
},
  "geometry": {"coordinates":[-4.7598152161,37.8951034546],"type":"Point"}
}