{
  "type": "Feature",
  "properties": {
    "iso:country":"ES",
    "sg:address":"Calle de Renteria, 2",
    "sg:city":"Donostia-san Sebastian",
    "sg:orig_category":"Peluqueros: De Se\u00d1oras",
    "sg:phone":"+34 943 29 35 81",
    "sg:postcode":"20013",
    "sg:province":"Guip\u00f9zcoa",
    "wof:name":"San Miguel Bengoetxea Juan Jose",
    "wof:placetype":"venue"
},
  "geometry": {"coordinates":[-1.968157053,43.3223266602],"type":"Point"}
}