{
  "type": "Feature",
  "properties": {
    "addr:full":"Calle de Bilbao, 2 Castro Urdiales Cantabria 39700",
    "addr:housenumber":"2",
    "addr:postcode":"39700",
    "addr:street":"Calle De Bilbao",
    "iso:country":"ES",
    "sg:address":"Calle de Bilbao, 2",
    "sg:city":"Castro Urdiales",
    "sg:orig_category":"Inmobiliaria (agencias)",
    "sg:phone":"+34 942 86 16 11",
    "sg:postcode":"39700",
    "sg:province":"Cantabria",
    "wof:name":"Inmobiliaria Castro S.c.",
    "wof:placetype":"venue"
},
  "geometry": {"coordinates":[-3.21798563,43.3807144165],"type":"Point"}
}