{
  "type": "Feature",
  "properties": {
    "addr:full":"Plaz Virgen Del Rocio, 5 Aljaraque Huelva 21110",
    "addr:housenumber":"5",
    "addr:postcode":"21110",
    "addr:street":"Plaz Virgen Del Rocio",
    "iso:country":"ES",
    "sg:address":"Plaz Virgen Del Rocio, 5",
    "sg:city":"Aljaraque",
    "sg:orig_category":"Productos Alimentarios",
    "sg:phone":"+34 959 31 88 42",
    "sg:postcode":"21110",
    "sg:province":"Huelva",
    "wof:name":"Piensos Pozo S.c",
    "wof:placetype":"venue"
},
  "geometry": {"coordinates":[-7.0280418396,37.2695121765],"type":"Point"}
}