{
  "type": "Feature",
  "properties": {
    "addr:full":"Calle de Doctor Ebri, 3 Alcala De Xivert Castell\u00f3n 12570",
    "addr:housenumber":"3",
    "addr:postcode":"12570",
    "addr:street":"Calle De Doctor Ebri",
    "iso:country":"ES",
    "sg:address":"Calle de Doctor Ebri, 3",
    "sg:city":"Alcala De Xivert",
    "sg:orig_category":"Cerrajer\u00cda, Ferrallista",
    "sg:phone":"+34 964 41 07 40",
    "sg:postcode":"12570",
    "sg:province":"Castell\u00f3n",
    "wof:name":"Albalat Blanch Adolfo Tomas",
    "wof:placetype":"venue"
},
  "geometry": {"coordinates":[0.2234933972,40.3049354553],"type":"Point"}
}