{
  "type": "Feature",
  "properties": {
    "iso:country":"ES",
    "sg:address":"Q. Llano, 26",
    "sg:city":"Caniles",
    "sg:orig_category":"Empresas De Electricidad En General",
    "sg:phone":"+34 958 86 82 21",
    "sg:postcode":"18810",
    "sg:province":"Granada",
    "wof:name":"Electrica De Caniles S.l.",
    "wof:placetype":"venue"
},
  "geometry": {"coordinates":[-2.7215490341,37.4435958862],"type":"Point"}
}