{
  "type": "Feature",
  "properties": {
    "addr:full":"Carrer de Mallorca, 134 Barcelona Barcelona 08036",
    "addr:housenumber":"134",
    "addr:postcode":"08036",
    "addr:street":"Carrer De Mallorca",
    "iso:country":"ES",
    "sg:address":"Carrer de Mallorca, 134",
    "sg:city":"Barcelona",
    "sg:orig_category":"Relojer\u00cda (al Por Menor, Reparaci\u00d3n)",
    "sg:phone":"+34 934 53 07 80",
    "sg:postcode":"08036",
    "sg:province":"Barcelona",
    "sg:website":"www.herocat.com",
    "wof:name":"Herocat S.l.",
    "wof:placetype":"venue"
},
  "geometry": {"coordinates":[2.1537399292,41.3870048523],"type":"Point"}
}