{
  "type": "Feature",
  "properties": {
    "iso:country":"ES",
    "sg:address":"Aldea De Los Rios, S/n",
    "sg:city":"Guarroman",
    "sg:orig_category":"Comisarios",
    "sg:phone":"+34 953 61 51 26",
    "sg:postcode":"23210",
    "sg:province":"Ja\u00e9n",
    "wof:name":"Bustos Lopez Jose Antonio",
    "wof:placetype":"venue"
},
  "geometry": {"coordinates":[-3.6845591068,38.1842346191],"type":"Point"}
}