{
  "type": "Feature",
  "properties": {
    "addr:full":"Calle de Ruiz Zorrilla, 28 Algeciras C\u00e1diz 11203",
    "addr:housenumber":"28;ca\u0301diz",
    "addr:postcode":"11203",
    "addr:street":"Calle De Ruiz Zorrilla",
    "iso:country":"ES",
    "sg:address":"Calle de Ruiz Zorrilla, 28",
    "sg:city":"Algeciras",
    "sg:orig_category":"Inversiones",
    "sg:phone":"+34 956 66 09 61",
    "sg:postcode":"11203",
    "sg:province":"C\u00e1diz",
    "wof:name":"F.r.r. Inversiones S.l.",
    "wof:placetype":"venue"
},
  "geometry": {"coordinates":[-5.4518318176,36.1314315796],"type":"Point"}
}