{
  "type": "Feature",
  "properties": {
    "addr:full":"Pase Ubarburu De, 13 Donostia-san Sebastian Guip\u00f9zcoa 20014",
    "addr:housenumber":"13",
    "addr:postcode":"20014",
    "iso:country":"ES",
    "sg:address":"Pase Ubarburu De, 13",
    "sg:city":"Donostia-san Sebastian",
    "sg:orig_category":"Empresas De Carpinter\u00cda De Madera",
    "sg:phone":"+34 943 46 52 16",
    "sg:postcode":"20014",
    "sg:province":"Guip\u00f9zcoa",
    "wof:name":"Martin Garcia Manuel",
    "wof:placetype":"venue"
},
  "geometry": {"coordinates":[-1.9009970427,43.2548027039],"type":"Point"}
}