{
  "type": "Feature",
  "properties": {
    "iso:country":"ES",
    "sg:address":"Calle de Coronel Reig, 4",
    "sg:city":"Casetas",
    "sg:orig_category":"Perfumer\u00cda (al Por Menor)",
    "sg:phone":"+34 976 78 41 88",
    "sg:postcode":"50620",
    "sg:province":"Zaragoza",
    "wof:name":"Garcia Catan S.c.",
    "wof:placetype":"venue"
},
  "geometry": {"coordinates":[-1.0267848969,41.7184143066],"type":"Point"}
}