{
  "type": "Feature",
  "properties": {
    "iso:country":"ES",
    "sg:address":"Calle de Jeronimo Guijarro, 1",
    "sg:city":"San Anton",
    "sg:orig_category":"Publicidad (soportes Y Gesti\u00d3n)",
    "sg:phone":"+34 968 28 51 02",
    "sg:postcode":"30009",
    "sg:province":"Murcia",
    "wof:name":"Exclusivas De Publicidad Exterior Alegria S.l.",
    "wof:placetype":"venue"
},
  "geometry": {"coordinates":[-1.1382069588,37.9918670654],"type":"Point"}
}