{
  "type": "Feature",
  "properties": {
    "addr:full":"Carretera Cordoba-valencia, 113 Arroyo Ojanco Ja\u00e9n 23340",
    "addr:housenumber":"113",
    "addr:postcode":"23340",
    "addr:street":"Carretera Cordoba-Valencia;Jae\u0301N",
    "iso:country":"ES",
    "sg:address":"Carretera Cordoba-valencia, 113",
    "sg:city":"Arroyo Ojanco",
    "sg:orig_category":"Electrodom\u00c9sticos (al Por Menor)",
    "sg:phone":"+34 953 42 00 05",
    "sg:postcode":"23340",
    "sg:province":"Ja\u00e9n",
    "wof:name":"Equipamiento Y Decoracion Del Hogar Estilhogar S.l.",
    "wof:placetype":"venue"
},
  "geometry": {"coordinates":[-2.8958919048,38.3205451965],"type":"Point"}
}