{
  "type": "Feature",
  "properties": {
    "addr:full":"Carr Doctor Jose Peris, 5 Benetusser Valencia 46910",
    "addr:housenumber":"5",
    "addr:postcode":"46910",
    "addr:street":"Carr Doctor Jose Peris",
    "iso:country":"ES",
    "sg:address":"Carr Doctor Jose Peris, 5",
    "sg:city":"Benetusser",
    "sg:orig_category":"Promotores Constructores",
    "sg:phone":"+34 963 76 65 14",
    "sg:postcode":"46910",
    "sg:province":"Valencia",
    "wof:name":"Comunidad De Propietarios Doctor Jose Peris 5",
    "wof:placetype":"venue"
},
  "geometry": {"coordinates":[-0.3989030123,39.4208908081],"type":"Point"}
}