{
  "type": "Feature",
  "properties": {
    "iso:country":"ES",
    "sg:address":"Avda Marques De Santillana, 78",
    "sg:city":"Hinojosa Del Duque",
    "sg:orig_category":"Suministros Para Carrocer\u00cdas",
    "sg:phone":"+34 957 14 03 95",
    "sg:postcode":"14270",
    "sg:province":"C\u00f3rdoba",
    "wof:name":"Hijos De Jose Barbancho Gordillo S.c.a.",
    "wof:placetype":"venue"
},
  "geometry": {"coordinates":[-5.1409602165,38.498966217],"type":"Point"}
}