{
  "type": "Feature",
  "properties": {
    "iso:country":"ES",
    "sg:address":"Calle de Amazonas, 6",
    "sg:city":"Petrer",
    "sg:orig_category":"Confecci\u00d3n De Zapatos",
    "sg:phone":"+34 966 95 01 09",
    "sg:postcode":"03610",
    "sg:province":"Alicante",
    "wof:name":"Sticalza S.l.",
    "wof:placetype":"venue"
},
  "geometry": {"coordinates":[-0.766997695,38.4810371399],"type":"Point"}
}