{
  "type": "Feature",
  "properties": {
    "iso:country":"ES",
    "sg:address":"Rua Reveriano Soutullo, 10",
    "sg:city":"Ponteareas",
    "sg:orig_category":"Molduras, Junquillos, Listones Y Molduras Perforadas",
    "sg:phone":"+34 986 64 16 37",
    "sg:postcode":"36860",
    "sg:province":"Pontevedra",
    "wof:name":"Lorenzo Migue Monica",
    "wof:placetype":"venue"
},
  "geometry": {"coordinates":[-8.503698349,42.1736030579],"type":"Point"}
}