{
  "type": "Feature",
  "properties": {
    "addr:full":"Calle de Toledo, 19 Mora Toledo 45400",
    "addr:housenumber":"19",
    "addr:postcode":"45400",
    "addr:street":"Calle De Toledo",
    "iso:country":"ES",
    "sg:address":"Calle de Toledo, 19",
    "sg:city":"Mora",
    "sg:orig_category":"Art\u00cdculos Funerarios (al Por Menor)",
    "sg:phone":"+34 925 30 04 52",
    "sg:postcode":"45400",
    "sg:province":"Toledo",
    "wof:name":"Lillo Hidalgo Jesus",
    "wof:placetype":"venue"
},
  "geometry": {"coordinates":[-3.7738690376,39.6851806641],"type":"Point"}
}