{
  "type": "Feature",
  "properties": {
    "addr:full":"Calle de Alfonso I, 20 Zaragoza Zaragoza 50003",
    "addr:housenumber":"20",
    "addr:postcode":"50003",
    "addr:street":"Calle De Alfonso I",
    "iso:country":"ES",
    "sg:address":"Calle de Alfonso I, 20",
    "sg:city":"Zaragoza",
    "sg:orig_category":"Administradores De Bienes Y Delegados De Comunidades De Propietarios",
    "sg:phone":"+34 976 39 37 88",
    "sg:postcode":"50003",
    "sg:province":"Zaragoza",
    "wof:name":"Fincas Viela S.l.",
    "wof:placetype":"venue"
},
  "geometry": {"coordinates":[-0.8805835843,41.6545906067],"type":"Point"}
}