{
  "type": "Feature",
  "properties": {
    "iso:country":"ES",
    "sg:address":"Rua San Pedro, 21",
    "sg:city":"Lugo",
    "sg:orig_category":"Prot\u00c9sicos Dentales",
    "sg:phone":"+34 982 24 22 65",
    "sg:postcode":"27001",
    "sg:province":"Lugo",
    "wof:name":"Mundicast S.l",
    "wof:placetype":"venue"
},
  "geometry": {"coordinates":[-7.5535130501,43.0104408264],"type":"Point"}
}