{
  "type": "Feature",
  "properties": {
    "addr:full":"Calle de Bailen, 20 Tarifa C\u00e1diz 11380",
    "addr:housenumber":"20",
    "addr:postcode":"11380",
    "addr:street":"Calle De Bailen;Ca\u0301Diz",
    "iso:country":"ES",
    "sg:address":"Calle de Bailen, 20",
    "sg:city":"Tarifa",
    "sg:classifiers":[
        {
            "category":"Taxi",
            "type":"Transportation"
        }
    ],
    "sg:phone":"+34 956 68 50 76",
    "sg:postcode":"11380",
    "sg:province":"C\u00e1diz",
    "wof:name":"Garrido Ojeda Manuel",
    "wof:placetype":"venue"
},
  "geometry": {"coordinates":[-5.606523037,36.0141143799],"type":"Point"}
}