{
  "type": "Feature",
  "properties": {
    "iso:country":"ES",
    "sg:address":"Rua Doctor Fleming, 45",
    "sg:city":"Ourense",
    "sg:orig_category":"Discapacitados",
    "sg:phone":"+34 988 24 01 03",
    "sg:postcode":"32003",
    "sg:province":"Ourense",
    "wof:name":"Aspanas",
    "wof:placetype":"venue"
},
  "geometry": {"coordinates":[-7.8676505089,42.3391723633],"type":"Point"}
}