{
  "type": "Feature",
  "properties": {
    "iso:country":"ES",
    "sg:address":"Calle de Constitucion (de La), 42",
    "sg:city":"Alcobendas",
    "sg:orig_category":"\u00d3ptica: Instrumentos (fabricaci\u00d3n)",
    "sg:phone":"+34 916 54 30 34",
    "sg:postcode":"28100",
    "sg:province":"Madrid",
    "wof:name":"Caballero Gomez Angel",
    "wof:placetype":"venue"
},
  "geometry": {"coordinates":[-3.6368250847,40.5428085327],"type":"Point"}
}