{
  "type": "Feature",
  "properties": {
    "iso:country":"ES",
    "sg:address":"Calle de Sol, 4",
    "sg:city":"Quintanar Rey",
    "sg:orig_category":"Florister\u00cdas",
    "sg:phone":"+34 967 49 63 05",
    "sg:postcode":"16220",
    "sg:province":"Cuenca",
    "wof:name":"Rivillo Agudo Francisco",
    "wof:placetype":"venue"
},
  "geometry": {"coordinates":[-1.9303289652,39.3473358154],"type":"Point"}
}