{
  "type": "Feature",
  "properties": {
    "addr:full":"Ctra Ronda (de), S/n Vera Almer\u00eda 04620",
    "addr:housenumber":"/ n;almeri\u0301a",
    "addr:postcode":"04620",
    "addr:street":"Ctra Ronda De S",
    "iso:country":"ES",
    "sg:address":"Ctra Ronda (de), S/n",
    "sg:city":"Vera",
    "sg:orig_category":"Producci\u00d3n, Distribuci\u00d3n De Gas Butano Y Propano",
    "sg:phone":"+34 950 39 09 08",
    "sg:postcode":"04620",
    "sg:province":"Almer\u00eda",
    "wof:name":"Veragas S.l.",
    "wof:placetype":"venue"
},
  "geometry": {"coordinates":[-1.8617529869,37.2395858765],"type":"Point"}
}