{
  "type": "Feature",
  "properties": {
    "iso:country":"ES",
    "sg:address":"Calle de Velasquita Giraldez, 1",
    "sg:city":"Oviedo",
    "sg:orig_category":"Ense\u00d1anza, Formaci\u00d3n Profesional: Aprendizaje",
    "sg:phone":"+34 985 20 37 48",
    "sg:postcode":"33008",
    "sg:province":"Asturias",
    "wof:name":"Coordinadora De Organizaciones No Gubernamentales Del Principado De Astutias",
    "wof:placetype":"venue"
},
  "geometry": {"coordinates":[-5.8391871452,43.3527832031],"type":"Point"}
}