{
  "type": "Feature",
  "properties": {
    "addr:full":"Fozalguera, 6 Pruvia Asturias 33192",
    "addr:housenumber":"6",
    "addr:postcode":"33192",
    "addr:street":"Fozalguera",
    "iso:country":"ES",
    "sg:address":"Fozalguera, 6",
    "sg:city":"Pruvia",
    "sg:orig_category":"Molduras, Junquillos, Listones Y Molduras Perforadas",
    "sg:phone":"+34 985 26 27 69",
    "sg:postcode":"33192",
    "sg:province":"Asturias",
    "wof:name":"Fernandez Lopez Amador",
    "wof:placetype":"venue"
},
  "geometry": {"coordinates":[-5.7745718956,43.4596939087],"type":"Point"}
}