{
  "type": "Feature",
  "properties": {
    "iso:country":"ES",
    "sg:address":"Calle de Sant Jaume, 34",
    "sg:city":"Santa Eulalia",
    "sg:orig_category":"Centros Comerciales Y Grandes Tiendas",
    "sg:phone":"+34 971 31 97 58",
    "sg:postcode":"07840",
    "sg:province":"Islas Baleares",
    "wof:name":"Ventura  Malylene",
    "wof:placetype":"venue"
},
  "geometry": {"coordinates":[1.5305769444,38.9828681946],"type":"Point"}
}