{
  "type": "Feature",
  "properties": {
    "addr:full":"Avda Juan Carlos I, 53 Ibi Alicante 03440",
    "addr:housenumber":"53",
    "addr:postcode":"03440",
    "addr:street":"Avda Juan Carlos I",
    "iso:country":"ES",
    "sg:address":"Avda Juan Carlos I, 53",
    "sg:city":"Ibi",
    "sg:orig_category":"\u00d3ptica: Instrumentos (fabricaci\u00d3n)",
    "sg:phone":"+34 965 55 23 59",
    "sg:postcode":"03440",
    "sg:province":"Alicante",
    "wof:name":"Optica Pastor S.l.",
    "wof:placetype":"venue"
},
  "geometry": {"coordinates":[-0.5760089755,38.6218605042],"type":"Point"}
}