{
  "type": "Feature",
  "properties": {
    "addr:full":"Calle de Calderon De La Barca, 16 Merida Badajoz 06800",
    "addr:housenumber":"16",
    "addr:postcode":"06800",
    "addr:street":"Calle De Calderon De La Barca",
    "iso:country":"ES",
    "sg:address":"Calle de Calderon De La Barca, 16",
    "sg:city":"Merida",
    "sg:orig_category":"Empresas De Limpieza",
    "sg:phone":"+34 924 30 08 14",
    "sg:postcode":"06800",
    "sg:province":"Badajoz",
    "wof:name":"Madelim S.a.",
    "wof:placetype":"venue"
},
  "geometry": {"coordinates":[-6.3422422409,38.9136199951],"type":"Point"}
}