{
  "type": "Feature",
  "properties": {
    "iso:country":"ES",
    "sg:address":"Av Raiguer, S/n",
    "sg:city":"Inca",
    "sg:orig_category":"Centros De Educaci\u00d3n Especial",
    "sg:phone":"+34 971 50 29 89",
    "sg:postcode":"07300",
    "sg:province":"Islas Baleares",
    "wof:name":"Escuela De Educacion Infantil Toninaina",
    "wof:placetype":"venue"
},
  "geometry": {"coordinates":[2.9000101089,39.7197113037],"type":"Point"}
}