{
  "type": "Feature",
  "properties": {
    "addr:full":"Calle de Santo Toribio De Mogrovejo, 66 Le\u00f3n Le\u00f3n 24006",
    "addr:housenumber":"66",
    "addr:postcode":"24006",
    "addr:street":"Calle De Santo;Leo\u0301N Leo\u0301N",
    "iso:country":"ES",
    "sg:address":"Calle de Santo Toribio De Mogrovejo, 66",
    "sg:city":"Le\u00f3n",
    "sg:orig_category":"Chapister\u00cda",
    "sg:phone":"+34 987 25 51 15",
    "sg:postcode":"24006",
    "sg:province":"Le\u00f3n",
    "wof:name":"Merino Martinez Maria Luz",
    "wof:placetype":"venue"
},
  "geometry": {"coordinates":[-5.563202858,42.5927467346],"type":"Point"}
}