{
  "type": "Feature",
  "properties": {
    "iso:country":"ES",
    "sg:address":"Iglesia, 2",
    "sg:city":"Monovar",
    "sg:classifiers":[
        {
            "category":"Communications",
            "type":"Services"
        }
    ],
    "sg:phone":"+34 965 47 19 31",
    "sg:postcode":"03640",
    "sg:province":"Alicante",
    "sg:tags":[
        "televisiones",
        "y",
        "radio"
    ],
    "wof:name":"Comunicaciones Monovar S.l.",
    "wof:placetype":"venue"
},
  "geometry": {"coordinates":[-0.837635994,38.4364967346],"type":"Point"}
}