{
  "type": "Feature",
  "properties": {
    "iso:country":"ES",
    "sg:address":"Calle de Doctor Mazuchelli, 20",
    "sg:city":"Madrid",
    "sg:orig_category":"Edici\u00d3n De Diarios, Revistas, Boletines",
    "sg:phone":"+34 902 30 40 33",
    "sg:postcode":"28035",
    "sg:province":"Madrid",
    "sg:website":"www.tai.es",
    "wof:name":"Tai Editorial De Revistas Tecnicas S.a.",
    "wof:placetype":"venue"
},
  "geometry": {"coordinates":[-3.7260730267,40.4809455872],"type":"Point"}
}