{
  "type": "Feature",
  "properties": {
    "addr:full":"Calle de Fuentelviejo, 22 Madrid Madrid 28022",
    "addr:housenumber":"22",
    "addr:postcode":"madrid;28022",
    "addr:street":"Calle De Fuentelviejo",
    "iso:country":"ES",
    "sg:address":"Calle de Fuentelviejo, 22",
    "sg:city":"Madrid",
    "sg:orig_category":"Electricidad: Equipos Industriales, Componentes (fabricaci\u00d3n)",
    "sg:phone":"+34 913 12 00 70",
    "sg:postcode":"28022",
    "sg:province":"Madrid",
    "sg:website":"www.e-distronica.com",
    "wof:name":"Distronica S.a.",
    "wof:placetype":"venue"
},
  "geometry": {"coordinates":[-3.570663929,40.4482803345],"type":"Point"}
}