{
  "type": "Feature",
  "properties": {
    "iso:country":"ES",
    "sg:address":"Calle de Barrio Alto, 8",
    "sg:city":"Bargas",
    "sg:orig_category":"Asistencia Social",
    "sg:phone":"+34 925 39 50 63",
    "sg:postcode":"45593",
    "sg:province":"Toledo",
    "wof:name":"Ayuntamiento De Bargas",
    "wof:placetype":"venue"
},
  "geometry": {"coordinates":[-4.0184779167,39.9401512146],"type":"Point"}
}