{
  "type": "Feature",
  "properties": {
    "addr:full":"Av Cubelles, 6 Vilanova I La Geltru Barcelona 08800",
    "addr:housenumber":"6",
    "addr:postcode":"08800",
    "addr:street":"Av Cubelles",
    "iso:country":"ES",
    "sg:address":"Av Cubelles, 6",
    "sg:city":"Vilanova I La Geltru",
    "sg:orig_category":"Muebles, Minoristas",
    "sg:phone":"+34 938 15 60 03",
    "sg:postcode":"08800",
    "sg:province":"Barcelona",
    "wof:name":"Super Colchon S.l.",
    "wof:placetype":"venue"
},
  "geometry": {"coordinates":[1.72339499,41.2212715149],"type":"Point"}
}