{
  "type": "Feature",
  "properties": {
    "addr:full":"San Jose, 62 Benissa Alicante 03720",
    "addr:housenumber":"62",
    "addr:postcode":"03720",
    "addr:street":"San Jose",
    "iso:country":"ES",
    "sg:address":"San Jose, 62",
    "sg:city":"Benissa",
    "sg:orig_category":"Ense\u00d1anza: Profesiones Art\u00cdsticas",
    "sg:phone":"+34 965 73 32 40",
    "sg:postcode":"03720",
    "sg:province":"Alicante",
    "wof:name":"Estudi 62 Fotografia C.b",
    "wof:placetype":"venue"
},
  "geometry": {"coordinates":[0.0465550013,38.7148017883],"type":"Point"}
}