{
  "type": "Feature",
  "properties": {
    "iso:country":"ES",
    "sg:address":"Pase Espolon (el), 18",
    "sg:city":"Soria",
    "sg:orig_category":"Abogados",
    "sg:phone":"+34 975 22 61 79",
    "sg:postcode":"42001",
    "sg:province":"Soria",
    "wof:name":"Gassol Quilez Carmen",
    "wof:placetype":"venue"
},
  "geometry": {"coordinates":[-2.4691669941,41.7646598816],"type":"Point"}
}