{
  "type": "Feature",
  "properties": {
    "addr:full":"Calle de Descampado, 2 Najera La Rioja 26300",
    "addr:housenumber":"2",
    "addr:postcode":"26300",
    "addr:street":"Calle De Descampado;Rioja",
    "iso:country":"ES",
    "sg:address":"Calle de Descampado, 2",
    "sg:city":"Najera",
    "sg:orig_category":"Congelados: Productos Alimentarios (al Por Menor)",
    "sg:phone":"+34 941 36 30 67",
    "sg:postcode":"26300",
    "sg:province":"La Rioja",
    "wof:name":"Diego Fernandez Maria Valvanera",
    "wof:placetype":"venue"
},
  "geometry": {"coordinates":[-2.7343099117,42.4149971008],"type":"Point"}
}