{
  "type": "Feature",
  "properties": {
    "addr:full":"Calle de Gaitan, 43 Posadas C\u00f3rdoba 14730",
    "addr:housenumber":"43;co\u0301rdoba",
    "addr:postcode":"14730",
    "addr:street":"Calle De Gaitan",
    "iso:country":"ES",
    "sg:address":"Calle de Gaitan, 43",
    "sg:city":"Posadas",
    "sg:orig_category":"Asesor\u00cda Fiscal Y Jur\u00cddica",
    "sg:phone":"+34 957 63 05 02",
    "sg:postcode":"14730",
    "sg:province":"C\u00f3rdoba",
    "wof:name":"Sanchez Gomez Asesoramiento S.l.",
    "wof:placetype":"venue"
},
  "geometry": {"coordinates":[-97.78224945069999,45.7040786743],"type":"Point"}
}