{
  "type": "Feature",
  "properties": {
    "addr:full":"Calle de Jimenez Diaz, 5 Puerto De Sardina Las Palmas 35469",
    "addr:housenumber":"5",
    "addr:postcode":"35469",
    "addr:street":"Calle De Jimenez Diaz",
    "iso:country":"ES",
    "sg:address":"Calle de Jimenez Diaz, 5",
    "sg:city":"Puerto De Sardina",
    "sg:orig_category":"Ense\u00d1anza, Formaci\u00d3n Profesional: Aprendizaje",
    "sg:phone":"+34 928 88 00 02",
    "sg:postcode":"35469",
    "sg:province":"Las Palmas",
    "wof:name":"Pino Jimenez Cristobal Del",
    "wof:placetype":"venue"
},
  "geometry": {"coordinates":[-15.6906471252,28.1544513702],"type":"Point"}
}