{
  "type": "Feature",
  "properties": {
    "addr:full":"Gta Cigarreras, 1 Sevilla Sevilla 41011",
    "addr:housenumber":"1",
    "addr:postcode":"41011",
    "addr:street":"Cigarreras",
    "iso:country":"ES",
    "sg:address":"Gta Cigarreras, 1",
    "sg:city":"Sevilla",
    "sg:orig_category":"Agencias De Viajes",
    "sg:phone":"+34 954 28 41 00",
    "sg:postcode":"41011",
    "sg:province":"Sevilla",
    "sg:website":"www.traveldos.com",
    "wof:name":"Travel Dos Viajes-servirapid S.a.",
    "wof:placetype":"venue"
},
  "geometry": {"coordinates":[-5.9941868782,37.3746871948],"type":"Point"}
}