{
  "type": "Feature",
  "properties": {
    "iso:country":"ES",
    "sg:address":"Llidoner, 5",
    "sg:city":"Benirredra",
    "sg:orig_category":"Asilos De Ancianos. Centros Privados",
    "sg:phone":"+34 962 87 03 52",
    "sg:postcode":"46700",
    "sg:province":"Valencia",
    "wof:name":"Residencia Para Mayores Mediterranea S.l.",
    "wof:placetype":"venue"
},
  "geometry": {"coordinates":[-0.1930570006,38.9617042542],"type":"Point"}
}