{
  "type": "Feature",
  "properties": {
    "iso:country":"ES",
    "sg:address":"Calle de Pedro Cerbuna, 27",
    "sg:city":"Zaragoza",
    "sg:orig_category":"Empresas De Limpieza",
    "sg:phone":"+34 976 56 27 79",
    "sg:postcode":"50009",
    "sg:province":"Zaragoza",
    "wof:name":"Mantenimiento Y Limpiezas Aragon S.l.",
    "wof:placetype":"venue"
},
  "geometry": {"coordinates":[-0.8977919817,41.6397209167],"type":"Point"}
}