{
  "type": "Feature",
  "properties": {
    "addr:full":"Luga Hoya Grande, 4 Hoya Grande Las Palmas 35290",
    "addr:postcode":"35290",
    "iso:country":"ES",
    "sg:address":"Luga Hoya Grande, 4",
    "sg:city":"Hoya Grande",
    "sg:orig_category":"Abogados",
    "sg:phone":"+34 928 12 70 18",
    "sg:postcode":"35290",
    "sg:province":"Las Palmas",
    "wof:name":"Macias Del Toro Francisco",
    "wof:placetype":"venue"
},
  "geometry": {"coordinates":[-15.5732269287,27.9242973328],"type":"Point"}
}