{
  "type": "Feature",
  "properties": {
    "iso:country":"ES",
    "sg:address":"Ctra Mijas (de), S/n",
    "sg:city":"Coin",
    "sg:orig_category":"Fabricaci\u00d3n De Cervezas",
    "sg:phone":"+34 952 45 10 44",
    "sg:postcode":"29100",
    "sg:province":"M\u00e1laga",
    "wof:name":"Garcia Moron Jose",
    "wof:placetype":"venue"
},
  "geometry": {"coordinates":[-4.7533826828,36.6576461792],"type":"Point"}
}