{
  "type": "Feature",
  "properties": {
    "addr:full":"Calle de Labradores, 16 San Vicente Del Raspeig-sant Vicent Del Raspeig Alicante 03690",
    "addr:housenumber":"16",
    "addr:postcode":"03690",
    "addr:street":"Calle De Labradores",
    "iso:country":"ES",
    "sg:address":"Calle de Labradores, 16",
    "sg:city":"San Vicente Del Raspeig-sant Vicent Del Raspeig",
    "sg:orig_category":"Promotores Constructores",
    "sg:phone":"+34 965 66 10 34",
    "sg:postcode":"03690",
    "sg:province":"Alicante",
    "wof:name":"Construcciones Miguel Coronado S.l.",
    "wof:placetype":"venue"
},
  "geometry": {"coordinates":[-0.5201150179,38.3971290588],"type":"Point"}
}