{
  "type": "Feature",
  "properties": {
    "addr:full":"Calle de Zamora (de), 19 Fuenlabrada Madrid 28941",
    "addr:housenumber":"19",
    "addr:postcode":"28941",
    "addr:street":"Calle De Zamora De",
    "iso:country":"ES",
    "sg:address":"Calle de Zamora (de), 19",
    "sg:city":"Fuenlabrada",
    "sg:orig_category":"Asesor\u00cda Fiscal Y Jur\u00cddica",
    "sg:phone":"+34 914 92 14 14",
    "sg:postcode":"28941",
    "sg:province":"Madrid",
    "wof:name":"Ambar Proyectos Inmobiliarios S.l.",
    "wof:placetype":"venue"
},
  "geometry": {"coordinates":[-3.8019545078,40.2954788208],"type":"Point"}
}