{
  "type": "Feature",
  "properties": {
    "addr:full":"Bidekurutzeta Kalea, 5 Bergara Guip\u00f9zcoa 20570",
    "addr:housenumber":"5",
    "addr:postcode":"20570",
    "addr:street":"Bidekurutzeta Kalea;Guipu\u0300Zcoa",
    "iso:country":"ES",
    "sg:address":"Bidekurutzeta Kalea, 5",
    "sg:city":"Bergara",
    "sg:orig_category":"Calzados Ortop\u00c9dicos",
    "sg:phone":"+34 943 76 10 57",
    "sg:postcode":"20570",
    "sg:province":"Guip\u00f9zcoa",
    "wof:name":"Luis Maria Lonbide Gisasola",
    "wof:placetype":"venue"
},
  "geometry": {"coordinates":[-2.41406703,43.1144218445],"type":"Point"}
}