{
  "type": "Feature",
  "properties": {
    "addr:full":"Concordia-area, 5 Area Pontevedra 36379",
    "addr:housenumber":"5",
    "addr:postcode":"36379",
    "addr:street":"Concordia-Area",
    "iso:country":"ES",
    "sg:address":"Concordia-area, 5",
    "sg:city":"Area",
    "sg:orig_category":"Peluquer\u00cdas, Peluquer\u00cda Mixta",
    "sg:phone":"+34 986 35 34 91",
    "sg:postcode":"36379",
    "sg:province":"Pontevedra",
    "wof:name":"Cabral Chamorro Julia",
    "wof:placetype":"venue"
},
  "geometry": {"coordinates":[-8.8124990463,42.1194648743],"type":"Point"}
}