{
  "type": "Feature",
  "properties": {
    "iso:country":"ES",
    "sg:address":"Calle de Navacerrada, 5",
    "sg:city":"Segovia",
    "sg:orig_category":"Panader\u00cdas, Panader\u00cdas",
    "sg:phone":"+34 921 42 80 67",
    "sg:postcode":"40006",
    "sg:province":"Segovia",
    "wof:name":"Marcos Velasco Faustino",
    "wof:placetype":"venue"
},
  "geometry": {"coordinates":[-4.1134290695,40.9263648987],"type":"Point"}
}