{
  "type": "Feature",
  "properties": {
    "addr:full":"Carretera Del Salto De Cedillo, 6 Cedillo C\u00e1ceres 10513",
    "addr:housenumber":"6",
    "addr:postcode":"10513",
    "addr:street":"Carretera Del Salto De Cedillo;Ca\u0301Ceres",
    "iso:country":"ES",
    "sg:address":"Carretera Del Salto De Cedillo, 6",
    "sg:city":"Cedillo",
    "sg:classifiers":[
        {
            "category":"Taxi",
            "type":"Transportation"
        }
    ],
    "sg:phone":"+34 927 59 00 88",
    "sg:postcode":"10513",
    "sg:province":"C\u00e1ceres",
    "wof:name":"Trancon Garcia Ramon",
    "wof:placetype":"venue"
},
  "geometry": {"coordinates":[-7.5003390312,39.6515808105],"type":"Point"}
}