{
  "type": "Feature",
  "properties": {
    "addr:full":"Calle de Camino Del Alamo, S/n Valmojado Toledo 45940",
    "addr:postcode":"45940",
    "addr:street":"Calle De Camino Del Alamo S / N Valmojado",
    "iso:country":"ES",
    "sg:address":"Calle de Camino Del Alamo, S/n",
    "sg:city":"Valmojado",
    "sg:orig_category":"Hormigonados",
    "sg:phone":"+34 918 17 04 33",
    "sg:postcode":"45940",
    "sg:province":"Toledo",
    "wof:name":"Hormicemex S.a.",
    "wof:placetype":"venue"
},
  "geometry": {"coordinates":[-4.1002168655,40.2058181763],"type":"Point"}
}