{
  "type": "Feature",
  "properties": {
    "iso:country":"ES",
    "sg:address":"Calle de Puerta Obispo, 11",
    "sg:city":"Astorga",
    "sg:orig_category":"Colchones (fabricaci\u00d3n, Al Por Mayor, Al Por Menor)",
    "sg:phone":"+34 987 60 26 30",
    "sg:postcode":"24700",
    "sg:province":"Le\u00f3n",
    "wof:name":"Garcia Zumeta Yolanda",
    "wof:placetype":"venue"
},
  "geometry": {"coordinates":[-6.0589289665,42.4567604065],"type":"Point"}
}