{
  "type": "Feature",
  "properties": {
    "iso:country":"ES",
    "sg:address":"Calle de Paneras, 3",
    "sg:city":"Caceres",
    "sg:orig_category":"Ropa Y Accesorios",
    "sg:phone":"+34 927 21 33 99",
    "sg:postcode":"10003",
    "sg:province":"C\u00e1ceres",
    "wof:name":"Barriga Galan Maria Rosa",
    "wof:placetype":"venue"
},
  "geometry": {"coordinates":[-6.3727197647,39.4748420715],"type":"Point"}
}