{
  "type": "Feature",
  "properties": {
    "iso:country":"ES",
    "sg:address":"Olarreaga Auzoa, S/n",
    "sg:city":"Eitzaga",
    "sg:orig_category":"Comercio, Reparaci\u00d3n De Bicicletas, De Motocicletas, De Accesorios",
    "sg:phone":"+34 943 12 04 95",
    "sg:postcode":"48250",
    "sg:province":"Vizcaya",
    "wof:name":"Tomas Garcia Herrera Y Otros C.b",
    "wof:placetype":"venue"
},
  "geometry": {"coordinates":[-2.5471470356,43.1717758179],"type":"Point"}
}