{
  "type": "Feature",
  "properties": {
    "addr:full":"Calle de Donoso Cortes, 30 Quintana Serena Badajoz 06450",
    "addr:housenumber":"30",
    "addr:postcode":"06450",
    "addr:street":"Calle De Donoso Cortes",
    "iso:country":"ES",
    "sg:address":"Calle de Donoso Cortes, 30",
    "sg:city":"Quintana Serena",
    "sg:classifiers":[
        {
            "category":"Taxi",
            "type":"Transportation"
        }
    ],
    "sg:phone":"+34 924 78 63 05",
    "sg:postcode":"06450",
    "sg:province":"Badajoz",
    "wof:name":"Davila Gomez-coronado Diego",
    "wof:placetype":"venue"
},
  "geometry": {"coordinates":[-5.6754283905,38.7401008606],"type":"Point"}
}