{
  "type": "Feature",
  "properties": {
    "iso:country":"ES",
    "sg:address":"Av. Scho Fuerte, 69",
    "sg:city":"Iru\u00f1a",
    "sg:orig_category":"Fabricaci\u00d3n De Peines Y De Accesorios De Peluquer\u00cda",
    "sg:phone":"+34 948 17 19 78",
    "sg:postcode":"31007",
    "sg:province":"Navarra",
    "wof:name":"Gainzarain Calleja J.r.s. S.cv.",
    "wof:placetype":"venue"
},
  "geometry": {"coordinates":[-1.655954957,42.8097457886],"type":"Point"}
}