{
  "type": "Feature",
  "properties": {
    "iso:country":"ES",
    "sg:address":"Calle de Era (de La), 8",
    "sg:city":"Mejorada Campo",
    "sg:orig_category":"Caf\u00c9s, Bares, Cervecer\u00cdas",
    "sg:phone":"+34 916 68 24 25",
    "sg:postcode":"28840",
    "sg:province":"Madrid",
    "wof:name":"Magari\u00f1o Hosteleria Restauracion S.l.",
    "wof:placetype":"venue"
},
  "geometry": {"coordinates":[-3.4859468937,40.3989372253],"type":"Point"}
}