{
  "type": "Feature",
  "properties": {
    "addr:full":"Calle de San Fernando, 53 Alacant Alicante 03001",
    "addr:housenumber":"53",
    "addr:postcode":"03001",
    "addr:street":"Calle De San Fernando",
    "iso:country":"ES",
    "sg:address":"Calle de San Fernando, 53",
    "sg:city":"Alacant",
    "sg:orig_category":"Sindicatos Y Colegios Profesionales",
    "sg:phone":"+34 965 20 65 58",
    "sg:postcode":"03001",
    "sg:province":"Alicante",
    "wof:name":"Asociacion De La Prensa De Alicante",
    "wof:placetype":"venue"
},
  "geometry": {"coordinates":[-0.4868451953,38.3423118591],"type":"Point"}
}