{
  "type": "Feature",
  "properties": {
    "iso:country":"ES",
    "sg:address":"Avda Alfonso X El Sabio, 4",
    "sg:city":"Huerta De Monteagudo",
    "sg:orig_category":"Transportes Por V\u00cdas Navegables",
    "sg:phone":"+34 968 85 35 00",
    "sg:postcode":"30160",
    "sg:province":"Murcia",
    "wof:name":"Fcs Explotaciones S.l.",
    "wof:placetype":"venue"
},
  "geometry": {"coordinates":[-1.0985800028,38.0232849121],"type":"Point"}
}