{
  "type": "Feature",
  "properties": {
    "addr:full":"Muel Espa\u00d1a, S/n Ceuta Ceuta 51001",
    "addr:housenumber":"s",
    "addr:postcode":"51001",
    "addr:street":"Espan\u0303A;/ N",
    "iso:country":"ES",
    "sg:address":"Muel Espa\u00d1a, S/n",
    "sg:city":"Ceuta",
    "sg:orig_category":"Empresas Portuarias",
    "sg:phone":"+34 956 50 31 73",
    "sg:postcode":"51001",
    "sg:province":"Ceuta",
    "wof:name":"Portel",
    "wof:placetype":"venue"
},
  "geometry": {"coordinates":[-5.3302302361,35.8947601318],"type":"Point"}
}