{
  "type": "Feature",
  "properties": {
    "iso:country":"ES",
    "sg:address":"Pase Estacion (la), 42",
    "sg:city":"Jaen",
    "sg:orig_category":"Ortopedia General",
    "sg:phone":"+34 953 26 12 79",
    "sg:postcode":"23008",
    "sg:province":"Ja\u00e9n",
    "wof:name":"De La Casa Moreno Juan Francisco",
    "wof:placetype":"venue"
},
  "geometry": {"coordinates":[-3.7890191078,37.7757606506],"type":"Point"}
}