{
  "type": "Feature",
  "properties": {
    "addr:full":"Calle de Misericordia, 1 Cartaya Huelva 21450",
    "addr:housenumber":"1",
    "addr:postcode":"21450",
    "addr:street":"Calle De Misericordia",
    "iso:country":"ES",
    "sg:address":"Calle de Misericordia, 1",
    "sg:city":"Cartaya",
    "sg:orig_category":"Agentes Generales De Seguros",
    "sg:phone":"+34 959 39 11 28",
    "sg:postcode":"21450",
    "sg:province":"Huelva",
    "sg:website":"www.vitalicio.es",
    "wof:name":"Diaz Toscano Sebastian",
    "wof:placetype":"venue"
},
  "geometry": {"coordinates":[-7.1504769325,37.2826118469],"type":"Point"}
}