{
  "type": "Feature",
  "properties": {
    "addr:full":"Calle de Basoa, 1 Vitoria-gasteiz \u00c1lava 01012",
    "addr:housenumber":"1",
    "addr:postcode":"01012",
    "addr:street":"Calle De Basoa",
    "iso:country":"ES",
    "sg:address":"Calle de Basoa, 1",
    "sg:city":"Vitoria-gasteiz",
    "sg:orig_category":"Farmacias",
    "sg:phone":"+34 945 22 92 10",
    "sg:postcode":"01012",
    "sg:province":"\u00c1lava",
    "wof:name":"Moreno Moreno Juan",
    "wof:placetype":"venue"
},
  "geometry": {"coordinates":[-2.6766111851,42.8546829224],"type":"Point"}
}