{
  "type": "Feature",
  "properties": {
    "addr:full":"Calle de San Millan, 18 Logro\u00f1o La Rioja 26004",
    "addr:housenumber":"18",
    "addr:postcode":"26004",
    "addr:street":"Calle De San Millan;Rioja",
    "iso:country":"ES",
    "sg:address":"Calle de San Millan, 18",
    "sg:city":"Logro\u00f1o",
    "sg:orig_category":"Tapicer\u00cdas",
    "sg:phone":"+34 941 25 64 09",
    "sg:postcode":"26004",
    "sg:province":"La Rioja",
    "wof:name":"Bajo Blasco Manuel",
    "wof:placetype":"venue"
},
  "geometry": {"coordinates":[-2.4326393604,42.4658622742],"type":"Point"}
}