{
  "type": "Feature",
  "properties": {
    "iso:country":"ES",
    "sg:address":"Calle de Pastores (los), 53",
    "sg:city":"Tomelloso",
    "sg:orig_category":"Ingenier\u00cda, Centros De Estudios (diversos)",
    "sg:phone":"+34 926 50 28 98",
    "sg:postcode":"13700",
    "sg:province":"Ciudad Real",
    "sg:website":"www.analisisvinicos.com",
    "wof:name":"Analisis Vinicos S.l.",
    "wof:placetype":"venue"
},
  "geometry": {"coordinates":[-3.0106050968,39.1667137146],"type":"Point"}
}