{
  "type": "Feature",
  "properties": {
    "iso:country":"ES",
    "sg:address":"Calle de Clarin, 3",
    "sg:city":"Cangas Narcea",
    "sg:orig_category":"Imprenta",
    "sg:phone":"+34 985 81 20 56",
    "sg:postcode":"33800",
    "sg:province":"Asturias",
    "wof:name":"Imprenta Helmantica C.b.",
    "wof:placetype":"venue"
},
  "geometry": {"coordinates":[-6.5478730202,43.1768722534],"type":"Point"}
}