{
  "type": "Feature",
  "properties": {
    "iso:country":"ES",
    "sg:address":"Avda Vacceos (los), 5",
    "sg:city":"Palencia",
    "sg:orig_category":"Asesor\u00cda Fiscal Y Jur\u00cddica",
    "sg:phone":"+34 979 74 71 39",
    "sg:postcode":"34003",
    "sg:province":"Palencia",
    "sg:website":"www.astrib.telefonica.net",
    "wof:name":"Astrib.consultores De Empresa S.l.sdad.unipersonal",
    "wof:placetype":"venue"
},
  "geometry": {"coordinates":[-4.5303058624,42.0138244629],"type":"Point"}
}