{
  "type": "Feature",
  "properties": {
    "iso:country":"ES",
    "sg:address":"Calle de Flores De Negron, 11",
    "sg:city":"Lucena",
    "sg:classifiers":[
        {
            "category":"Autos & Motor Vehicles",
            "subcategory":"Automobile Sales",
            "type":"Retail Goods"
        }
    ],
    "sg:phone":"+34 957 59 03 56",
    "sg:postcode":"14900",
    "sg:province":"C\u00f3rdoba",
    "wof:name":"Gonzalez Garrot Juan Francisco",
    "wof:placetype":"venue"
},
  "geometry": {"coordinates":[-4.482416153,37.4089241028],"type":"Point"}
}