{
  "type": "Feature",
  "properties": {
    "iso:country":"ES",
    "sg:address":"Carr Alfara Del Patriarca, 5",
    "sg:city":"Betera",
    "sg:orig_category":"Fabricaci\u00d3n De Enlosados, Soler\u00cdas",
    "sg:phone":"+34 961 69 80 30",
    "sg:postcode":"46117",
    "sg:province":"Valencia",
    "wof:name":"Chapados Arocas S.l.",
    "wof:placetype":"venue"
},
  "geometry": {"coordinates":[-0.4534989893,39.5863494873],"type":"Point"}
}