{
  "type": "Feature",
  "properties": {
    "addr:full":"Calle de Alamos, 4 Utiel Valencia 46300",
    "addr:housenumber":"4",
    "addr:postcode":"46300",
    "addr:street":"Calle De Alamos",
    "iso:country":"ES",
    "sg:address":"Calle de Alamos, 4",
    "sg:city":"Utiel",
    "sg:classifiers":[
        {
            "category":"Communications",
            "type":"Services"
        }
    ],
    "sg:phone":"+34 962 16 82 38",
    "sg:postcode":"46300",
    "sg:province":"Valencia",
    "sg:tags":[
        "televisiones",
        "y",
        "radio"
    ],
    "wof:name":"Sociedad Espa\u00d1ola De Radiodifusion S A",
    "wof:placetype":"venue"
},
  "geometry": {"coordinates":[-1.2054350376,39.5664634705],"type":"Point"}
}