{
  "type": "Feature",
  "properties": {
    "addr:full":"Calle de Menendez Y Pelayo, 23 Palmas De Gran Canaria Las Palmas 35006",
    "addr:postcode":"35006",
    "addr:street":"Calle De Menendez Y Pelayo",
    "iso:country":"ES",
    "sg:address":"Calle de Menendez Y Pelayo, 23",
    "sg:city":"Palmas De Gran Canaria",
    "sg:orig_category":"Ingeniero",
    "sg:phone":"+34 928 29 07 51",
    "sg:postcode":"35006",
    "sg:province":"Las Palmas",
    "wof:name":"Montesdeoca Naranjo Julio Cesar",
    "wof:placetype":"venue"
},
  "geometry": {"coordinates":[-15.4317302704,28.1334915161],"type":"Point"}
}