{
  "type": "Feature",
  "properties": {
    "addr:full":"Carrer de Casp, 148 Barcelona Barcelona 08013",
    "addr:housenumber":"148",
    "addr:postcode":"08013",
    "addr:street":"Carrer De Casp",
    "iso:country":"ES",
    "sg:address":"Carrer de Casp, 148",
    "sg:city":"Barcelona",
    "sg:orig_category":"Comerciantes Al Por Mayor De Vinos, Licores Y Alcoholes",
    "sg:phone":"+34 932 65 47 86",
    "sg:postcode":"08013",
    "sg:province":"Barcelona",
    "wof:name":"Rives Pitman S. A.",
    "wof:placetype":"venue"
},
  "geometry": {"coordinates":[2.1800160408,41.3961715698],"type":"Point"}
}