{
  "type": "Feature",
  "properties": {
    "iso:country":"ES",
    "sg:address":"Calle de Paseo De La Ribera, 151",
    "sg:city":"Valtierra",
    "sg:orig_category":"Sociedades, Compa\u00d1\u00cdas Aseguradoras",
    "sg:phone":"+34 948 86 72 46",
    "sg:postcode":"31514",
    "sg:province":"Navarra",
    "wof:name":"Perez Anoz Saul Y Rodrigo Rodrigo Amelia",
    "wof:placetype":"venue"
},
  "geometry": {"coordinates":[-1.6343460083,42.1953735352],"type":"Point"}
}