{
  "type": "Feature",
  "properties": {
    "addr:full":"Mareo De Arriba, 17 La Pedrera Asturias 33390",
    "addr:housenumber":"17",
    "addr:postcode":"33390",
    "addr:street":"Mareo;Arriba;Asturias",
    "iso:country":"ES",
    "sg:address":"Mareo De Arriba, 17",
    "sg:city":"La Pedrera",
    "sg:orig_category":"Art\u00cdculos De Aluminio",
    "sg:phone":"+34 985 16 88 02",
    "sg:postcode":"33390",
    "sg:province":"Asturias",
    "wof:name":"Lopez Perez Jesus",
    "wof:placetype":"venue"
},
  "geometry": {"coordinates":[-5.6883621216,43.4970245361],"type":"Point"}
}