{
  "type": "Feature",
  "properties": {
    "iso:country":"ES",
    "sg:address":"Calle de Montesa, 16",
    "sg:city":"Madrid",
    "sg:orig_category":"Equitaci\u00d3n: Guarnicioner\u00cda, Equipo (al Por Menor)",
    "sg:phone":"+34 914 01 42 36",
    "sg:postcode":"28006",
    "sg:province":"Madrid",
    "wof:name":"Campuzano Brom Luis",
    "wof:placetype":"venue"
},
  "geometry": {"coordinates":[-3.6721429825,40.4279289246],"type":"Point"}
}