{
  "type": "Feature",
  "properties": {
    "addr:full":"Pase Sagrada (monzalbarba), 1 Monzalbarba Zaragoza 50120",
    "addr:housenumber":"1",
    "addr:postcode":"50120",
    "addr:street":"Sagrada Monzalbarba",
    "iso:country":"ES",
    "sg:address":"Pase Sagrada (monzalbarba), 1",
    "sg:city":"Monzalbarba",
    "sg:orig_category":"Carnes De Carnicer\u00cda (al Por Mayor)",
    "sg:phone":"+34 976 77 41 13",
    "sg:postcode":"50120",
    "sg:province":"Zaragoza",
    "wof:name":"Industrias Carnicas Carbonel S.l.",
    "wof:placetype":"venue"
},
  "geometry": {"coordinates":[-0.9511139989,41.723651886],"type":"Point"}
}