{
  "type": "Feature",
  "properties": {
    "addr:full":"Velazquez, 121 Madrid Madrid 28006",
    "addr:housenumber":"121",
    "addr:postcode":"28006",
    "addr:street":"Velazquez",
    "iso:country":"ES",
    "sg:address":"Velazquez, 121",
    "sg:city":"Madrid",
    "sg:orig_category":"Asociaciones Humanitarias, De Cooperaci\u00d3n, De Acci\u00d3n Social",
    "sg:phone":"+34 915 64 21 65",
    "sg:postcode":"28006",
    "sg:province":"Madrid",
    "wof:name":"Asociacion Cultural De Invalidos Militares De Espa\u00f1a",
    "wof:placetype":"venue"
},
  "geometry": {"coordinates":[-3.6832110882,40.437335968],"type":"Point"}
}