{
  "type": "Feature",
  "properties": {
    "iso:country":"ES",
    "sg:address":"Calle de Real, 52",
    "sg:city":"Valdepe\u00f1as",
    "sg:orig_category":"Productores Recolectores, Venta Directa De Vinos",
    "sg:phone":"+34 926 32 18 88",
    "sg:postcode":"13300",
    "sg:province":"Ciudad Real",
    "wof:name":"Bodegas Navarro Lopez S.l.",
    "wof:placetype":"venue"
},
  "geometry": {"coordinates":[-3.3832120895,38.7629623413],"type":"Point"}
}