{
  "type": "Feature",
  "properties": {
    "addr:full":"Avda Burgos, 64 Palmar  O Lugar De Don Juan Murcia 30120",
    "addr:housenumber":"64",
    "addr:postcode":"30120",
    "addr:street":"Avda Burgos;Lugar",
    "iso:country":"ES",
    "sg:address":"Avda Burgos, 64",
    "sg:city":"Palmar  O Lugar De Don Juan",
    "sg:orig_category":"Deportes Y Programas De Aventura",
    "sg:phone":"+34 968 88 90 58",
    "sg:postcode":"30120",
    "sg:province":"Murcia",
    "wof:name":"Sport Tres 2001 S.l.",
    "wof:placetype":"venue"
},
  "geometry": {"coordinates":[-1.1302490234,37.9829597473],"type":"Point"}
}