{
  "type": "Feature",
  "properties": {
    "addr:full":"Cubias, 5 S. Feliu Guixols Girona 17220",
    "addr:housenumber":"5",
    "addr:postcode":"17220",
    "addr:street":"Cubias;Feliu",
    "iso:country":"ES",
    "sg:address":"Cubias, 5",
    "sg:city":"S. Feliu Guixols",
    "sg:orig_category":"M\u00c9dicos: An\u00c1lisis Cl\u00cdnicos",
    "sg:phone":"+34 972 32 38 57",
    "sg:postcode":"17220",
    "sg:province":"Girona",
    "wof:name":"Bague Paretas Julia",
    "wof:placetype":"venue"
},
  "geometry": {"coordinates":[3.0378599167,41.7843742371],"type":"Point"}
}