{
  "type": "Feature",
  "properties": {
    "iso:country":"ES",
    "sg:address":"Carrer de Bolivia, 340",
    "sg:city":"Barcelona",
    "sg:orig_category":"Aguas (distribuci\u00d3n, Servicios)",
    "sg:phone":"+34 933 03 18 48",
    "sg:postcode":"08019",
    "sg:province":"Barcelona",
    "wof:name":"Fontaga S. A.",
    "wof:placetype":"venue"
},
  "geometry": {"coordinates":[2.2088060379,41.4160995483],"type":"Point"}
}