{
  "type": "Feature",
  "properties": {
    "iso:country":"ES",
    "sg:address":"Calle de Arquitecto Arnau, 30",
    "sg:city":"Valencia",
    "sg:orig_category":"Artesan\u00cda",
    "sg:phone":"+34 963 69 54 49",
    "sg:postcode":"46020",
    "sg:province":"Valencia",
    "wof:name":"Cotanda Sanchis Maria Jose",
    "wof:placetype":"venue"
},
  "geometry": {"coordinates":[-0.3564063907,39.4858779907],"type":"Point"}
}