{
  "type": "Feature",
  "properties": {
    "addr:full":"Calle de Polvoranca, 73 Alcorcon Madrid 28923",
    "addr:housenumber":"73",
    "addr:postcode":"28923",
    "addr:street":"Calle De Polvoranca",
    "iso:country":"ES",
    "sg:address":"Calle de Polvoranca, 73",
    "sg:city":"Alcorcon",
    "sg:orig_category":"Venta, Montaje De Neum\u00c1ticos",
    "sg:phone":"+34 916 43 57 52",
    "sg:postcode":"28923",
    "sg:province":"Madrid",
    "wof:name":"Neumaticos De Las Moras S.l.",
    "wof:placetype":"venue"
},
  "geometry": {"coordinates":[-3.8109669685,40.3362617493],"type":"Point"}
}