{
  "type": "Feature",
  "properties": {
    "addr:full":"Calle de Vatemar, 13 Bembibre Le\u00f3n 24300",
    "addr:housenumber":"13",
    "addr:postcode":"24300",
    "addr:street":"Calle De Vatemar;Leo\u0301N",
    "iso:country":"ES",
    "sg:address":"Calle de Vatemar, 13",
    "sg:city":"Bembibre",
    "sg:orig_category":"Telas Y Sedas (al Por Menor)",
    "sg:phone":"+34 987 51 01 70",
    "sg:postcode":"24300",
    "sg:province":"Le\u00f3n",
    "wof:name":"Vaquero Cabello Maria Victoria",
    "wof:placetype":"venue"
},
  "geometry": {"coordinates":[-6.4167661667,42.6174964905],"type":"Point"}
}