{
  "type": "Feature",
  "properties": {
    "iso:country":"ES",
    "sg:address":"Pase Menendez Pelayo, 55",
    "sg:city":"Castro Urdiales",
    "sg:orig_category":"Ahumados Y Salazones",
    "sg:phone":"+34 942 86 44 40",
    "sg:postcode":"39700",
    "sg:province":"Cantabria",
    "wof:name":"Salazones Y Anchoas Lolin S.a.",
    "wof:placetype":"venue"
},
  "geometry": {"coordinates":[-3.2150969505,43.3698730469],"type":"Point"}
}