{
  "type": "Feature",
  "properties": {
    "iso:country":"ES",
    "sg:address":"Calle de Joaquin Turina, 2",
    "sg:city":"Pozuelo De Alarcon",
    "sg:orig_category":"Producci\u00d3n De Abonos Y De Fertilizantes",
    "sg:phone":"+34 913 51 55 70",
    "sg:postcode":"28224",
    "sg:province":"Madrid",
    "wof:name":"Asociacion Comercial Espa\u00f1ola De Fertilizantes",
    "wof:placetype":"venue"
},
  "geometry": {"coordinates":[-3.8131253719,40.4562187195],"type":"Point"}
}