{
  "type": "Feature",
  "properties": {
    "iso:country":"ES",
    "sg:address":"Carrer de Josep Anselm Clave, 25",
    "sg:city":"Barcelona",
    "sg:orig_category":"Doctores En Medicina",
    "sg:phone":"+34 933 02 09 82",
    "sg:postcode":"08002",
    "sg:province":"Barcelona",
    "wof:name":"Nu\u00f1ez Tomas Juan Manuel",
    "wof:placetype":"venue"
},
  "geometry": {"coordinates":[2.1781740189,41.3778495789],"type":"Point"}
}