{
  "type": "Feature",
  "properties": {
    "addr:full":"Plaz Pisa (la), S/n Jerez De La Frontera C\u00e1diz 11404",
    "addr:postcode":"11404",
    "addr:street":"La S / N",
    "iso:country":"ES",
    "sg:address":"Plaz Pisa (la), S/n",
    "sg:city":"Jerez De La Frontera",
    "sg:orig_category":"Zapatos (al Por Menor)",
    "sg:phone":"+34 956 18 58 05",
    "sg:postcode":"11404",
    "sg:province":"C\u00e1diz",
    "wof:name":"Zambrano Gordillo Maribel",
    "wof:placetype":"venue"
},
  "geometry": {"coordinates":[-6.1553497314,36.7065124512],"type":"Point"}
}