{
  "type": "Feature",
  "properties": {
    "iso:country":"ES",
    "sg:address":"Cllo Campo Volantin, 15",
    "sg:city":"Bilbao",
    "sg:orig_category":"Tintorer\u00cdas, Limpieza En Seco",
    "sg:phone":"+34 944 01 40 74",
    "sg:postcode":"48007",
    "sg:province":"Vizcaya",
    "wof:name":"Bego\u00f1a Axpe Orive (lavanderia Tint.)",
    "wof:placetype":"venue"
},
  "geometry": {"coordinates":[-2.9253098965,43.2654037476],"type":"Point"}
}