{
  "type": "Feature",
  "properties": {
    "iso:country":"ES",
    "sg:address":"Calle de Hermosilla, 29",
    "sg:city":"Madrid",
    "sg:orig_category":"Asesor\u00cda Sobre Comunicaci\u00d3n De Empresas",
    "sg:phone":"+34 915 75 24 42",
    "sg:postcode":"28001",
    "sg:province":"Madrid",
    "wof:name":"Facaral S.l.",
    "wof:placetype":"venue"
},
  "geometry": {"coordinates":[-3.6846330166,40.4264945984],"type":"Point"}
}