{
  "type": "Feature",
  "properties": {
    "iso:country":"ES",
    "sg:address":"Avgd Antonio Almela, 4",
    "sg:city":"Alcudia",
    "sg:classifiers":[
        {
            "category":"Autos & Motor Vehicles",
            "subcategory":"Automobile Sales",
            "type":"Retail Goods"
        }
    ],
    "sg:phone":"+34 962 54 04 65",
    "sg:postcode":"46250",
    "sg:province":"Valencia",
    "wof:name":"Tarrago Torres Jose",
    "wof:placetype":"venue"
},
  "geometry": {"coordinates":[-0.5045599937,39.1985855103],"type":"Point"}
}