{
  "type": "Feature",
  "properties": {
    "iso:country":"ES",
    "sg:address":"Calle de Arjona, 11",
    "sg:city":"Sevilla",
    "sg:orig_category":"Quincaller\u00cda (al Por Menor)",
    "sg:phone":"+34 954 22 97 02",
    "sg:postcode":"41001",
    "sg:province":"Sevilla",
    "wof:name":"Isaias Sainz Y Cia",
    "wof:placetype":"venue"
},
  "geometry": {"coordinates":[-6.0022826195,37.3891220093],"type":"Point"}
}