{
  "type": "Feature",
  "properties": {
    "addr:full":"Crta Alcora, Km. 0016,0 Sant Joan Moro Castell\u00f3n 12130",
    "addr:postcode":"12130",
    "addr:street":"Crta Alcora Km. 0016,0",
    "iso:country":"ES",
    "sg:address":"Crta Alcora, Km. 0016,0",
    "sg:city":"Sant Joan Moro",
    "sg:orig_category":"Fabricaci\u00d3n De Enlosados, Soler\u00cdas",
    "sg:phone":"+34 964 70 00 00",
    "sg:postcode":"12130",
    "sg:province":"Castell\u00f3n",
    "wof:name":"Parthenon Ceramica S.l.",
    "wof:placetype":"venue"
},
  "geometry": {"coordinates":[-0.0456800014,39.9851417542],"type":"Point"}
}