{
  "type": "Feature",
  "properties": {
    "addr:full":"Afueras (p I De Talarrubias), 23 Talarrubias Badajoz 06640",
    "addr:housenumber":"23",
    "addr:postcode":"06640",
    "addr:street":"P I De Talarrubias",
    "iso:country":"ES",
    "sg:address":"Afueras (p I De Talarrubias), 23",
    "sg:city":"Talarrubias",
    "sg:orig_category":"Congelados: Productos Alimentarios (fabricaci\u00d3n, Al Por Mayor)",
    "sg:phone":"+34 924 63 14 64",
    "sg:postcode":"06640",
    "sg:province":"Badajoz",
    "wof:name":"Extreme\u00f1a De Congelados Y Helados S.l.",
    "wof:placetype":"venue"
},
  "geometry": {"coordinates":[-5.2343840599,39.0305633545],"type":"Point"}
}