{
  "type": "Feature",
  "properties": {
    "iso:country":"ES",
    "sg:address":"Rua Estrada (la), 6",
    "sg:city":"Pontevedra",
    "sg:orig_category":"Frutas, Legumbres Frescas Y Tempranas (al Por Menor)",
    "sg:phone":"+34 986 85 60 09",
    "sg:postcode":"36004",
    "sg:province":"Pontevedra",
    "wof:name":"Frucogal Frutera Comercial Gallega S.l.",
    "wof:placetype":"venue"
},
  "geometry": {"coordinates":[-8.6315164566,42.4267616272],"type":"Point"}
}