{
  "type": "Feature",
  "properties": {
    "addr:full":"Carrer de L'avio Plus Ultra, 3 Barcelona Barcelona 08017",
    "addr:housenumber":"3",
    "addr:postcode":"08017",
    "addr:street":"Carrer De;Ultra",
    "iso:country":"ES",
    "sg:address":"Carrer de L'avio Plus Ultra, 3",
    "sg:city":"Barcelona",
    "sg:orig_category":"Aparcamientos (infraestructuras, Accesorios)",
    "sg:phone":"+34 932 03 16 32",
    "sg:postcode":"08017",
    "sg:province":"Barcelona",
    "wof:name":"Estrada Sariola Jose",
    "wof:placetype":"venue"
},
  "geometry": {"coordinates":[2.1219358444,41.4003868103],"type":"Point"}
}