{
  "type": "Feature",
  "properties": {
    "iso:country":"ES",
    "sg:address":"Carr Torres De Sanui, 5",
    "sg:city":"Lleida",
    "sg:orig_category":"Peluquer\u00cdas, Peluquer\u00cda Mixta",
    "sg:phone":"+34 973 26 60 58",
    "sg:postcode":"25006",
    "sg:province":"Lleida",
    "wof:name":"Cuevas Montes De Oca Maria Luisa",
    "wof:placetype":"venue"
},
  "geometry": {"coordinates":[0.6192939878,41.6175575256],"type":"Point"}
}