{
  "type": "Feature",
  "properties": {
    "addr:full":"Calle de Alcalde Carro Verdejo, 2 Astorga Le\u00f3n 24700",
    "addr:housenumber":"2",
    "addr:postcode":"24700",
    "addr:street":"Calle De Alcalde Carro Verdejo;Leo\u0301N",
    "iso:country":"ES",
    "sg:address":"Calle de Alcalde Carro Verdejo, 2",
    "sg:city":"Astorga",
    "sg:orig_category":"Molduras, Junquillos, Listones Y Molduras Perforadas",
    "sg:phone":"+34 987 61 75 12",
    "sg:postcode":"24700",
    "sg:province":"Le\u00f3n",
    "wof:name":"Martinez Prieto Juan Antonio",
    "wof:placetype":"venue"
},
  "geometry": {"coordinates":[-6.0538077354,42.46118927],"type":"Point"}
}