{
  "type": "Feature",
  "properties": {
    "addr:full":"Ctra San Martin De Valdeiglesias, Km. 0002,2 Carretera De San Martin Madrid 28925",
    "addr:postcode":"28925",
    "addr:street":"Ctra San Martin De Valdeiglesias Km. 0002,2 Carretera De",
    "iso:country":"ES",
    "sg:address":"Ctra San Martin De Valdeiglesias, Km. 0002,2",
    "sg:city":"Carretera De San Martin",
    "sg:orig_category":"Fabricaci\u00d3n De Muebles",
    "sg:phone":"+34 916 10 74 87",
    "sg:postcode":"28925",
    "sg:province":"Madrid",
    "wof:name":"Paraiso Del Sofa",
    "wof:placetype":"venue"
},
  "geometry": {"coordinates":[-3.8353390694,40.3956756592],"type":"Point"}
}