{
  "type": "Feature",
  "properties": {
    "iso:country":"ES",
    "sg:address":"Plaz Iglesia, 12",
    "sg:city":"Cheste",
    "sg:classifiers":[
        {
            "category":"Utilities",
            "subcategory":"Natural Gas",
            "type":"Services"
        }
    ],
    "sg:phone":"+34 962 51 00 93",
    "sg:postcode":"46380",
    "sg:province":"Valencia",
    "sg:tags":[
        "te",
        "de",
        "salones"
    ],
    "wof:name":"Salon De Te Hms S.l.",
    "wof:placetype":"venue"
},
  "geometry": {"coordinates":[-0.6874480247,39.4945602417],"type":"Point"}
}