{
  "type": "Feature",
  "properties": {
    "iso:country":"ES",
    "sg:address":"Rbla Sant Domenec, 12",
    "sg:city":"Vic",
    "sg:orig_category":"Panader\u00cdas, Panader\u00cdas",
    "sg:phone":"+34 938 85 14 40",
    "sg:postcode":"08500",
    "sg:province":"Barcelona",
    "wof:name":"Pastisseries Masramon S.l.",
    "wof:placetype":"venue"
},
  "geometry": {"coordinates":[2.2529230118,41.9273796082],"type":"Point"}
}