{
  "type": "Feature",
  "properties": {
    "addr:full":"Avda Madrid, 7 Laguna Duero Valladolid 47140",
    "addr:housenumber":"7",
    "addr:postcode":"47140",
    "addr:street":"Avda Madrid",
    "iso:country":"ES",
    "sg:address":"Avda Madrid, 7",
    "sg:city":"Laguna Duero",
    "sg:orig_category":"Venta, Instalaci\u00d3n De Calefacci\u00d3n",
    "sg:phone":"+34 983 54 42 62",
    "sg:postcode":"47140",
    "sg:province":"Valladolid",
    "wof:name":"Florencio Damian Hernandez Y Basiliso Rojo Antolin Cdad",
    "wof:placetype":"venue"
},
  "geometry": {"coordinates":[-4.7193188667,41.5835494995],"type":"Point"}
}