{
  "type": "Feature",
  "properties": {
    "addr:full":"Carrer de Alemanya, 13 Mataro Barcelona 08303",
    "addr:housenumber":"13",
    "addr:postcode":"08303",
    "addr:street":"Carrer De Alemanya",
    "iso:country":"ES",
    "sg:address":"Carrer de Alemanya, 13",
    "sg:city":"Mataro",
    "sg:orig_category":"Disfraces",
    "sg:phone":"+34 937 58 88 36",
    "sg:postcode":"08303",
    "sg:province":"Barcelona",
    "wof:name":"Garcia Armengol Agustina",
    "wof:placetype":"venue"
},
  "geometry": {"coordinates":[2.4307160378,41.5461082458],"type":"Point"}
}