{
  "type": "Feature",
  "properties": {
    "iso:country":"ES",
    "sg:address":"Calle de Lara Perello, S/n",
    "sg:city":"Marbella",
    "sg:orig_category":"Plomeros",
    "sg:phone":"+34 952 77 79 11",
    "sg:postcode":"29600",
    "sg:province":"M\u00e1laga",
    "wof:name":"Julio Uceda S.l.",
    "wof:placetype":"venue"
},
  "geometry": {"coordinates":[-4.8875060081,36.5141639709],"type":"Point"}
}