{
  "type": "Feature",
  "properties": {
    "addr:full":"Calle de Labradores, 6 Valladolid Valladolid 47004",
    "addr:housenumber":"6",
    "addr:postcode":"47004",
    "addr:street":"Calle De Labradores",
    "iso:country":"ES",
    "sg:address":"Calle de Labradores, 6",
    "sg:city":"Valladolid",
    "sg:orig_category":"Asociaciones, Organismos Culturales Y Socioeducativos",
    "sg:phone":"+34 983 30 40 62",
    "sg:postcode":"47004",
    "sg:province":"Valladolid",
    "wof:name":"Casa Canaria",
    "wof:placetype":"venue"
},
  "geometry": {"coordinates":[-4.7206630707,41.647808075],"type":"Point"}
}