{
  "type": "Feature",
  "properties": {
    "addr:full":"Avda Galicia (de), 11 Monforte De Lemos Lugo 27400",
    "addr:housenumber":"11",
    "addr:postcode":"27400",
    "addr:street":"Avda Galicia De",
    "iso:country":"ES",
    "sg:address":"Avda Galicia (de), 11",
    "sg:city":"Monforte De Lemos",
    "sg:orig_category":"Inmobiliaria (agencias)",
    "sg:phone":"+34 982 40 05 00",
    "sg:postcode":"27400",
    "sg:province":"Lugo",
    "wof:name":"Construcciones Y Contratas Sanchez S.l.",
    "wof:placetype":"venue"
},
  "geometry": {"coordinates":[-7.5099949837,42.5176773071],"type":"Point"}
}