{
  "type": "Feature",
  "properties": {
    "addr:full":"Calle de Acibelas, 2 Valladolid Valladolid 47004",
    "addr:housenumber":"2",
    "addr:postcode":"47004",
    "addr:street":"Calle De Acibelas",
    "iso:country":"ES",
    "sg:address":"Calle de Acibelas, 2",
    "sg:city":"Valladolid",
    "sg:orig_category":"Institutos De Belleza",
    "sg:phone":"+34 983 39 51 17",
    "sg:postcode":"47004",
    "sg:province":"Valladolid",
    "wof:name":"Iglesias Gomez Lourdes",
    "wof:placetype":"venue"
},
  "geometry": {"coordinates":[-4.721932888,41.6471748352],"type":"Point"}
}