{
  "type": "Feature",
  "properties": {
    "iso:country":"ES",
    "sg:address":"Calle de Rafael Vargas Nevado, 64",
    "sg:city":"Villaviciosa Cordoba",
    "sg:orig_category":"Inform\u00c1tica (estudios, Servicios, Asesor\u00cda, Formaci\u00d3n)",
    "sg:phone":"+34 957 36 01 00",
    "sg:postcode":"14300",
    "sg:province":"C\u00f3rdoba",
    "wof:name":"Nevado Machuca Antonia",
    "wof:placetype":"venue"
},
  "geometry": {"coordinates":[-5.0143089294,38.0761260986],"type":"Point"}
}