{
  "type": "Feature",
  "properties": {
    "addr:full":"Avda Gran Via Rey Juan Carlos I, 12 Logro\u00f1o La Rioja 26002",
    "addr:housenumber":"12",
    "addr:postcode":"26002",
    "addr:street":"Avda Gran Via Rey Juan Carlos I;Rioja",
    "iso:country":"ES",
    "sg:address":"Avda Gran Via Rey Juan Carlos I, 12",
    "sg:city":"Logro\u00f1o",
    "sg:orig_category":"Ropa Para Ni\u00d1os (al Por Menor)",
    "sg:phone":"+34 941 20 71 44",
    "sg:postcode":"26002",
    "sg:province":"La Rioja",
    "sg:website":"www.neckandneck.com",
    "wof:name":"Neck Child S.a.",
    "wof:placetype":"venue"
},
  "geometry": {"coordinates":[-2.446639061,42.463394165],"type":"Point"}
}