{
  "type": "Feature",
  "properties": {
    "iso:country":"ES",
    "sg:address":"Calle de Almendro Del Paular, 24",
    "sg:city":"Pozuelo De Alarcon",
    "sg:orig_category":"Audiovisuales (producci\u00d3n, Edici\u00d3n, Realizaci\u00d3n)",
    "sg:phone":"+34 913 51 52 41",
    "sg:postcode":"28224",
    "sg:province":"Madrid",
    "wof:name":"Pozuelo Television S.l.",
    "wof:placetype":"venue"
},
  "geometry": {"coordinates":[-3.8042833805,40.4546699524],"type":"Point"}
}