{
  "type": "Feature",
  "properties": {
    "addr:full":"Plaz Constitucion (de La), 8 Almoguera Guadalajara 19115",
    "addr:housenumber":"8",
    "addr:postcode":"19115",
    "iso:country":"ES",
    "sg:address":"Plaz Constitucion (de La), 8",
    "sg:city":"Almoguera",
    "sg:orig_category":"Iglesia Cat\u00d3lica",
    "sg:phone":"+34 949 38 00 30",
    "sg:postcode":"19115",
    "sg:province":"Guadalajara",
    "wof:name":"Obispado De Siguenza-guadalajara",
    "wof:placetype":"venue"
},
  "geometry": {"coordinates":[-2.9810318947,40.2969017029],"type":"Point"}
}