{
  "type": "Feature",
  "properties": {
    "addr:full":"Plaza De Jose Bermudez De La Rubia, 4 Coin M\u00e1laga 29100",
    "addr:housenumber":"4",
    "addr:postcode":"29100",
    "addr:street":"Rubia;Ma\u0301Laga",
    "iso:country":"ES",
    "sg:address":"Plaza De Jose Bermudez De La Rubia, 4",
    "sg:city":"Coin",
    "sg:orig_category":"Alimentaci\u00d3n General (al Por Menor)",
    "sg:phone":"+34 952 45 07 26",
    "sg:postcode":"29100",
    "sg:province":"M\u00e1laga",
    "wof:name":"Barruezo Gutierrez Ramon",
    "wof:placetype":"venue"
},
  "geometry": {"coordinates":[-4.7591891289,36.6597213745],"type":"Point"}
}