{
  "type": "Feature",
  "properties": {
    "addr:full":"Avda Galicia, 23 Cambados Pontevedra 36630",
    "addr:housenumber":"23",
    "addr:postcode":"36630",
    "addr:street":"Avda Galicia",
    "iso:country":"ES",
    "sg:address":"Avda Galicia, 23",
    "sg:city":"Cambados",
    "sg:orig_category":"Electrodom\u00c9sticos (al Por Menor)",
    "sg:phone":"+34 986 54 27 00",
    "sg:postcode":"36630",
    "sg:province":"Pontevedra",
    "sg:website":"www.eotero.com",
    "wof:name":"Establecimientos Otero S.a.",
    "wof:placetype":"venue"
},
  "geometry": {"coordinates":[-8.8156642914,42.5111503601],"type":"Point"}
}