{
  "type": "Feature",
  "properties": {
    "iso:country":"ES",
    "sg:address":"Avda Cardenal Benlloch, 83",
    "sg:city":"Valencia",
    "sg:orig_category":"Ropa Para Se\u00d1oras (al Por Menor)",
    "sg:phone":"+34 963 69 54 31",
    "sg:postcode":"46021",
    "sg:province":"Valencia",
    "wof:name":"Lopez Beltran Amparo",
    "wof:placetype":"venue"
},
  "geometry": {"coordinates":[-0.3537429869,39.4731216431],"type":"Point"}
}