{
  "type": "Feature",
  "properties": {
    "iso:country":"ES",
    "sg:address":"Carr Ramon Y Cajal, 32",
    "sg:city":"Bellcaire D'urgell",
    "sg:orig_category":"Material Y Herramientas Agr\u00cdcolas",
    "sg:phone":"+34 973 58 64 01",
    "sg:postcode":"25337",
    "sg:province":"Lleida",
    "wof:name":"Coll Miralles Jose Maria",
    "wof:placetype":"venue"
},
  "geometry": {"coordinates":[0.9001649022,41.7606773376],"type":"Point"}
}