{
  "type": "Feature",
  "properties": {
    "iso:country":"ES",
    "sg:address":"Plaz Vigil De Qui\u00d1ones, 1",
    "sg:city":"Marbella",
    "sg:orig_category":"Enfermeras: Consultas, Atenci\u00d3n A Domicilio",
    "sg:phone":"+34 952 77 10 60",
    "sg:postcode":"29600",
    "sg:province":"M\u00e1laga",
    "wof:name":"Galvez Lavigne Jose Manuel",
    "wof:placetype":"venue"
},
  "geometry": {"coordinates":[-4.900812149,36.5126457214],"type":"Point"}
}