{
  "type": "Feature",
  "properties": {
    "iso:country":"ES",
    "sg:address":"Calle de Calvario-la Orotava (el), 32",
    "sg:city":"Orotava",
    "sg:orig_category":"Quincaller\u00cda (al Por Menor)",
    "sg:phone":"+34 922 32 30 73",
    "sg:postcode":"38300",
    "sg:province":"Santa Cruz De Tenerife",
    "sg:website":"www.todokasa.com",
    "wof:name":"Ferreteria Todokasa S. L.",
    "wof:placetype":"venue"
},
  "geometry": {"coordinates":[-16.5220127106,28.3927135468],"type":"Point"}
}