{
  "type": "Feature",
  "properties": {
    "iso:country":"ES",
    "sg:address":"Pase Chopera, 9",
    "sg:city":"Madrid",
    "sg:orig_category":"Inform\u00c1tica (estudios, Servicios, Asesor\u00cda, Formaci\u00d3n)",
    "sg:phone":"+34 915 17 68 69",
    "sg:postcode":"28045",
    "sg:province":"Madrid",
    "wof:name":"Fuentes Quiles Pedro",
    "wof:placetype":"venue"
},
  "geometry": {"coordinates":[-3.7012939453,40.3961791992],"type":"Point"}
}