{
  "type": "Feature",
  "properties": {
    "addr:full":"Ctra. De Alhama, S/n La Malaha Granada 18130",
    "addr:housenumber":"s / n",
    "addr:postcode":"18130",
    "addr:street":"Ctra. De Alhama",
    "iso:country":"ES",
    "sg:address":"Ctra. De Alhama, S/n",
    "sg:city":"La Malaha",
    "sg:orig_category":"Muebles Y Accesorios Para Cocinas Y Cuartos De Ba\u00d1o (al Por Menor)",
    "sg:phone":"+34 958 58 72 89",
    "sg:postcode":"18130",
    "sg:province":"Granada",
    "wof:name":"Gamiz Aznar Jose",
    "wof:placetype":"venue"
},
  "geometry": {"coordinates":[-97.78224945069999,45.7040786743],"type":"Point"}
}