{
  "type": "Feature",
  "properties": {
    "iso:country":"ES",
    "sg:address":"Calle de Calderon De La Barca, 15",
    "sg:city":"Santander",
    "sg:orig_category":"Promotores Constructores",
    "sg:phone":"+34 942 21 60 55",
    "sg:postcode":"39002",
    "sg:province":"Cantabria",
    "wof:name":"Promociones Y Construcciones Targo S.a.",
    "wof:placetype":"venue"
},
  "geometry": {"coordinates":[-3.8076591492,43.4596099854],"type":"Point"}
}