{
  "type": "Feature",
  "properties": {
    "addr:full":"Pl Eduard Torroja, S/n Barcelona Barcelona 08020",
    "addr:housenumber":"s / n",
    "addr:postcode":"08020",
    "addr:street":"Pl Eduard Torroja",
    "iso:country":"ES",
    "sg:address":"Pl Eduard Torroja, S/n",
    "sg:city":"Barcelona",
    "sg:orig_category":"Mutuas De Seguros",
    "sg:phone":"+34 933 08 62 77",
    "sg:postcode":"08020",
    "sg:province":"Barcelona",
    "wof:name":"Mutuam M.p.s.",
    "wof:placetype":"venue"
},
  "geometry": {"coordinates":[2.1975901127,41.4143600464],"type":"Point"}
}