{
  "type": "Feature",
  "properties": {
    "addr:full":"Calle de Legion, 10 Villafranca De Los Barros Badajoz 06220",
    "addr:housenumber":"10",
    "addr:postcode":"06220",
    "addr:street":"Calle De Legion",
    "iso:country":"ES",
    "sg:address":"Calle de Legion, 10",
    "sg:city":"Villafranca De Los Barros",
    "sg:orig_category":"Chapister\u00cda",
    "sg:phone":"+34 924 52 31 27",
    "sg:postcode":"06220",
    "sg:province":"Badajoz",
    "wof:name":"Saenz Hernandez Eusebio",
    "wof:placetype":"venue"
},
  "geometry": {"coordinates":[-6.3409790993,38.5649642944],"type":"Point"}
}