{
  "type": "Feature",
  "properties": {
    "iso:country":"ES",
    "sg:address":"Carrer de Arago, 44",
    "sg:city":"Palma",
    "sg:orig_category":"Loter\u00cda Y T\u00d3mbola",
    "sg:phone":"+34 971 24 49 48",
    "sg:postcode":"07005",
    "sg:province":"Islas Baleares",
    "wof:name":"Celia Servera Cristina",
    "wof:placetype":"venue"
},
  "geometry": {"coordinates":[2.6605870724,39.577003479],"type":"Point"}
}