{
  "type": "Feature",
  "properties": {
    "iso:country":"ES",
    "sg:address":"Ctra San Martin De Montalban, S/n",
    "sg:city":"Puebla Montalban",
    "sg:orig_category":"Hormig\u00d3n (m\u00c1quinas E Instalaci\u00d3n)",
    "sg:phone":"+34 925 78 95 21",
    "sg:postcode":"45516",
    "sg:province":"Toledo",
    "wof:name":"Hormisan 2010 S.a.",
    "wof:placetype":"venue"
},
  "geometry": {"coordinates":[-4.3588690758,39.8725013733],"type":"Point"}
}