{
  "type": "Feature",
  "properties": {
    "iso:country":"ES",
    "sg:address":"Carrer de Casanova, 193",
    "sg:city":"Barcelona",
    "sg:orig_category":"Agencias Y Asesores De Publicidad",
    "sg:phone":"+34 934 10 56 06",
    "sg:postcode":"08036",
    "sg:province":"Barcelona",
    "wof:name":"Agi S.l.",
    "wof:placetype":"venue"
},
  "geometry": {"coordinates":[2.1489880085,41.3927993774],"type":"Point"}
}