{
  "type": "Feature",
  "properties": {
    "iso:country":"ES",
    "sg:address":"Calle de Miguel Marrero Rodriguez, 6",
    "sg:city":"Arguineguin",
    "sg:orig_category":"Supermercados Y Hipermercados",
    "sg:phone":"+34 928 15 20 50",
    "sg:postcode":"35120",
    "sg:province":"Las Palmas",
    "wof:name":"Rodriguez Guedes Isabel",
    "wof:placetype":"venue"
},
  "geometry": {"coordinates":[-15.6833658218,27.7613582611],"type":"Point"}
}