{
  "type": "Feature",
  "properties": {
    "iso:country":"ES",
    "sg:address":"Psaj Doctor Serra, 12",
    "sg:city":"Valencia",
    "sg:orig_category":"Asesor\u00cda Fiscal Y Jur\u00cddica",
    "sg:phone":"+34 963 52 40 64",
    "sg:postcode":"46004",
    "sg:province":"Valencia",
    "wof:name":"Sanchis Gabinete De Asesores S.l.",
    "wof:placetype":"venue"
},
  "geometry": {"coordinates":[-0.3758620024,39.4657669067],"type":"Point"}
}