{
  "type": "Feature",
  "properties": {
    "iso:country":"ES",
    "sg:address":"Calle de Ezequiel Solana, 106",
    "sg:city":"Madrid",
    "sg:orig_category":"Supermercados Y Hipermercados",
    "sg:phone":"+34 913 68 03 80",
    "sg:postcode":"28017",
    "sg:province":"Madrid",
    "wof:name":"Comercial Hermanos Vallejo S. A.",
    "wof:placetype":"venue"
},
  "geometry": {"coordinates":[-3.6422829628,40.4270591736],"type":"Point"}
}