{
  "type": "Feature",
  "properties": {
    "addr:full":"Calle de Ventura Rodriguez, 6 Oviedo Asturias 33004",
    "addr:housenumber":"6",
    "addr:postcode":"33004",
    "addr:street":"Calle De Ventura Rodriguez",
    "iso:country":"ES",
    "sg:address":"Calle de Ventura Rodriguez, 6",
    "sg:city":"Oviedo",
    "sg:orig_category":"Edici\u00d3n De Diarios, Revistas, Boletines",
    "sg:phone":"+34 985 24 14 01",
    "sg:postcode":"33004",
    "sg:province":"Asturias",
    "wof:name":"Hercules Astur De Ediciones S.l.",
    "wof:placetype":"venue"
},
  "geometry": {"coordinates":[-5.8540468216,43.3640937805],"type":"Point"}
}