{
  "type": "Feature",
  "properties": {
    "addr:full":"Calle de Luna (la), 5 Pe\u00e7arroya-pueblonuevo C\u00f3rdoba 14200",
    "addr:housenumber":"5",
    "addr:postcode":"14200",
    "addr:street":"Calle De Luna La;Co\u0301Rdoba",
    "iso:country":"ES",
    "sg:address":"Calle de Luna (la), 5",
    "sg:city":"Pe\u00e7arroya-pueblonuevo",
    "sg:orig_category":"Bisuter\u00cda, Joyer\u00cda, Relojer\u00cda (al Por Menor)",
    "sg:phone":"+34 957 56 07 93",
    "sg:postcode":"14200",
    "sg:province":"C\u00f3rdoba",
    "wof:name":"Molina Garcia Clemente",
    "wof:placetype":"venue"
},
  "geometry": {"coordinates":[-5.2670240402,38.2995643616],"type":"Point"}
}