{
  "type": "Feature",
  "properties": {
    "addr:full":"Calle de Ricardo Rueda, S/n Benahadux Almer\u00eda 04410",
    "addr:housenumber":"s / n",
    "addr:postcode":"04410",
    "addr:street":"Calle De Ricardo Rueda",
    "iso:country":"ES",
    "sg:address":"Calle de Ricardo Rueda, S/n",
    "sg:city":"Benahadux",
    "sg:orig_category":"Peluquer\u00cdas, Peluquer\u00cda Mixta",
    "sg:phone":"+34 950 31 12 70",
    "sg:postcode":"04410",
    "sg:province":"Almer\u00eda",
    "wof:name":"Garcia Martinez Montserrat",
    "wof:placetype":"venue"
},
  "geometry": {"coordinates":[-2.4609239101,36.9276390076],"type":"Point"}
}