{
  "type": "Feature",
  "properties": {
    "addr:full":"Ptge Abat Llort, 1 Valls Tarragona 43800",
    "addr:housenumber":"1",
    "addr:postcode":"43800",
    "addr:street":"Ptge Abat Llort",
    "iso:country":"ES",
    "sg:address":"Ptge Abat Llort, 1",
    "sg:city":"Valls",
    "sg:orig_category":"Peluquer\u00cdas, Peluquer\u00cda Mixta",
    "sg:phone":"+34 977 60 04 60",
    "sg:postcode":"43800",
    "sg:province":"Tarragona",
    "wof:name":"Sagala Altes Eugenio",
    "wof:placetype":"venue"
},
  "geometry": {"coordinates":[1.2491179705,41.2872238159],"type":"Point"}
}