{
  "type": "Feature",
  "properties": {
    "addr:full":"Cmno Fuentecilla (de La), S/n Algete Madrid 28110",
    "addr:housenumber":"/ n",
    "addr:postcode":"28110",
    "addr:street":"Cmno Fuentecilla De La S",
    "iso:country":"ES",
    "sg:address":"Cmno Fuentecilla (de La), S/n",
    "sg:city":"Algete",
    "sg:orig_category":"Fabricaci\u00d3n, Instalaci\u00d3n Y Reparaci\u00d3n De Bombas",
    "sg:phone":"+34 918 48 88 00",
    "sg:postcode":"28110",
    "sg:province":"Madrid",
    "sg:website":"www.grundfos.com",
    "wof:name":"Bombas Grundfos Espa\u00d1a S.a.",
    "wof:placetype":"venue"
},
  "geometry": {"coordinates":[-3.5042099953,40.5942993164],"type":"Point"}
}