{
  "type": "Feature",
  "properties": {
    "addr:full":"Calle de Teneria, S/n Piedralaves \u00c1vila 05440",
    "addr:housenumber":"s / n",
    "addr:postcode":"05440",
    "addr:street":"Calle De Teneria",
    "iso:country":"ES",
    "sg:address":"Calle de Teneria, S/n",
    "sg:city":"Piedralaves",
    "sg:orig_category":"Grabados",
    "sg:phone":"+34 918 66 52 68",
    "sg:postcode":"05440",
    "sg:province":"\u00c1vila",
    "wof:name":"Galeano Arianes Angel",
    "wof:placetype":"venue"
},
  "geometry": {"coordinates":[-4.6959528923,40.320514679],"type":"Point"}
}