{
  "type": "Feature",
  "properties": {
    "addr:full":"Avgd Reis Catolics, 29 Silla Valencia 46460",
    "addr:housenumber":"29",
    "addr:postcode":"46460",
    "addr:street":"Catolics",
    "iso:country":"ES",
    "sg:address":"Avgd Reis Catolics, 29",
    "sg:city":"Silla",
    "sg:orig_category":"Reposter\u00cdas",
    "sg:phone":"+34 961 20 15 46",
    "sg:postcode":"46460",
    "sg:province":"Valencia",
    "wof:name":"Establecimientos Ferrando S.l.",
    "wof:placetype":"venue"
},
  "geometry": {"coordinates":[-0.417858988,39.3685531616],"type":"Point"}
}