{
  "type": "Feature",
  "properties": {
    "addr:full":"Avda Figueroa (de), 7 Santiago De Compostela A Coru\u00f1a 15705",
    "addr:housenumber":"7",
    "addr:postcode":"15705",
    "addr:street":"Avda Figueroa De;Corun\u0303A",
    "iso:country":"ES",
    "sg:address":"Avda Figueroa (de), 7",
    "sg:city":"Santiago De Compostela",
    "sg:orig_category":"Caf\u00c9s, Bares, Cervecer\u00cdas",
    "sg:phone":"+34 981 57 02 60",
    "sg:postcode":"15705",
    "sg:province":"A Coru\u00f1a",
    "wof:name":"Tele Renta S.l.",
    "wof:placetype":"venue"
},
  "geometry": {"coordinates":[-8.5460710526,42.8776321411],"type":"Point"}
}