{
  "type": "Feature",
  "properties": {
    "addr:full":"Pg Eres De Santa Llucia, 8 Elche Alicante 03202",
    "addr:housenumber":"8",
    "addr:postcode":"03202",
    "addr:street":"Pg Eres De Santa Llucia",
    "iso:country":"ES",
    "sg:address":"Pg Eres De Santa Llucia, 8",
    "sg:city":"Elche",
    "sg:orig_category":"Promotores Constructores",
    "sg:phone":"+34 966 61 52 39",
    "sg:postcode":"03202",
    "sg:province":"Alicante",
    "wof:name":"Primis Inversiones S.l.",
    "wof:placetype":"venue"
},
  "geometry": {"coordinates":[-0.6967449784,38.2677078247],"type":"Point"}
}