{
  "type": "Feature",
  "properties": {
    "addr:full":"Carrer de Aribau, 256 Barcelona Barcelona 08006",
    "addr:housenumber":"256",
    "addr:postcode":"08006",
    "addr:street":"Carrer De Aribau",
    "iso:country":"ES",
    "sg:address":"Carrer de Aribau, 256",
    "sg:city":"Barcelona",
    "sg:orig_category":"Asesor\u00cda Fiscal Y Jur\u00cddica",
    "sg:phone":"+34 934 14 34 32",
    "sg:postcode":"08006",
    "sg:province":"Barcelona",
    "wof:name":"Archs Asesoria Y Gestion S.l.",
    "wof:placetype":"venue"
},
  "geometry": {"coordinates":[2.1487810612,41.3964881897],"type":"Point"}
}