{
  "type": "Feature",
  "properties": {
    "addr:full":"Abejeras, 47 Iru\u00f1a Navarra 31007",
    "addr:housenumber":"47",
    "addr:postcode":"31007",
    "addr:street":"Abejeras",
    "iso:country":"ES",
    "sg:address":"Abejeras, 47",
    "sg:city":"Iru\u00f1a",
    "sg:orig_category":"Farmacias",
    "sg:phone":"+34 948 23 40 49",
    "sg:postcode":"31007",
    "sg:province":"Navarra",
    "wof:name":"Valentin Martinez Maria Del Mar",
    "wof:placetype":"venue"
},
  "geometry": {"coordinates":[-1.6472970247,42.8040046692],"type":"Point"}
}