{
  "type": "Feature",
  "properties": {
    "addr:full":"Ctra Cadiz Carretera A, Km. 0108,3 Algeciras C\u00e1diz 11206",
    "addr:postcode":"11206",
    "addr:street":"Ctra Cadiz Carretera A Km. 0108,3;Ca\u0301Diz",
    "iso:country":"ES",
    "sg:address":"Ctra Cadiz Carretera A, Km. 0108,3",
    "sg:city":"Algeciras",
    "sg:orig_category":"Electricidad: Instaladores",
    "sg:phone":"+34 956 66 47 12",
    "sg:postcode":"11206",
    "sg:province":"C\u00e1diz",
    "wof:name":"Montajes Electricos Algeciras S.a.",
    "wof:placetype":"venue"
},
  "geometry": {"coordinates":[-5.5359191895,36.1193008423],"type":"Point"}
}