{
  "type": "Feature",
  "properties": {
    "addr:full":"B La Venta, S/n Villasevil Cantabria 39698",
    "addr:housenumber":"s",
    "addr:postcode":"39698",
    "addr:street":"/ N",
    "iso:country":"ES",
    "sg:address":"B La Venta, S/n",
    "sg:city":"Villasevil",
    "sg:orig_category":"Centros De Educaci\u00d3n Especial",
    "sg:phone":"+34 942 59 65 18",
    "sg:postcode":"39698",
    "sg:province":"Cantabria",
    "wof:name":"Colegio Publico Francisco De Quevedo",
    "wof:placetype":"venue"
},
  "geometry": {"coordinates":[-3.9408938885,43.2369613647],"type":"Point"}
}