{
  "type": "Feature",
  "properties": {
    "addr:full":"Geraneos, 12 Mijas Costa M\u00e1laga 29649",
    "addr:housenumber":"12",
    "addr:postcode":"29649",
    "addr:street":"Geraneos",
    "iso:country":"ES",
    "sg:address":"Geraneos, 12",
    "sg:city":"Mijas Costa",
    "sg:orig_category":"Centros Empresariales",
    "sg:phone":"+34 952 47 67 11",
    "sg:postcode":"29649",
    "sg:province":"M\u00e1laga",
    "sg:website":"www.sermanweb.com",
    "wof:name":"Tobar Jimenez Gines Javier",
    "wof:placetype":"venue"
},
  "geometry": {"coordinates":[-4.7120189667,36.4914283752],"type":"Point"}
}