{
  "type": "Feature",
  "properties": {
    "iso:country":"ES",
    "sg:address":"Calle de Comercio, 2",
    "sg:city":"Sevilla",
    "sg:orig_category":"Suministros Y Materiales Industriales",
    "sg:phone":"+34 954 52 69 99",
    "sg:postcode":"41007",
    "sg:province":"Sevilla",
    "wof:name":"Mu\u00f1oz Y Bravo Suministros Industriales S.l.",
    "wof:placetype":"venue"
},
  "geometry": {"coordinates":[-5.9499006271,37.3898925781],"type":"Point"}
}