{
  "type": "Feature",
  "properties": {
    "addr:full":"Calle de Virgen (la), 10 Conil De La Frontera C\u00e1diz 11140",
    "addr:housenumber":"10",
    "addr:postcode":"11140",
    "addr:street":"Calle De Virgen La",
    "iso:country":"ES",
    "sg:address":"Calle de Virgen (la), 10",
    "sg:city":"Conil De La Frontera",
    "sg:orig_category":"Producci\u00d3n, Distribuci\u00d3n De Gas Butano Y Propano",
    "sg:phone":"+34 956 44 02 19",
    "sg:postcode":"11140",
    "sg:province":"C\u00e1diz",
    "wof:name":"Aragon Sanchez Y Guerrero S.l.",
    "wof:placetype":"venue"
},
  "geometry": {"coordinates":[-6.0882511139,36.2768707275],"type":"Point"}
}