{
  "type": "Feature",
  "properties": {
    "addr:full":"Calle de Mayor, 104 Alcantarilla Murcia 30820",
    "addr:housenumber":"104",
    "addr:postcode":"30820",
    "addr:street":"Calle De Mayor",
    "iso:country":"ES",
    "sg:address":"Calle de Mayor, 104",
    "sg:city":"Alcantarilla",
    "sg:orig_category":"Agencias Y Agentes Comerciales, Representantes",
    "sg:phone":"+34 968 80 11 14",
    "sg:postcode":"30820",
    "sg:province":"Murcia",
    "wof:name":"Martinez Navarro Gines",
    "wof:placetype":"venue"
},
  "geometry": {"coordinates":[-1.2130219936,37.9699783325],"type":"Point"}
}