{
  "type": "Feature",
  "properties": {
    "addr:full":"Carrer de Cienfuegos, 2 Barcelona Barcelona 08027",
    "addr:housenumber":"2",
    "addr:postcode":"08027",
    "addr:street":"Carrer De Cienfuegos",
    "iso:country":"ES",
    "sg:address":"Carrer de Cienfuegos, 2",
    "sg:city":"Barcelona",
    "sg:orig_category":"Doctores En Medicina",
    "sg:phone":"+34 933 51 27 00",
    "sg:postcode":"08027",
    "sg:province":"Barcelona",
    "wof:name":"Chica Xalmet Alberto Alejandro De La",
    "wof:placetype":"venue"
},
  "geometry": {"coordinates":[2.1855530739,41.4240684509],"type":"Point"}
}