{
  "type": "Feature",
  "properties": {
    "iso:country":"ES",
    "sg:address":"Ctra Cordoba-valencia, 3",
    "sg:city":"Villacarrillo",
    "sg:orig_category":"Charcuter\u00cdas (al Por Mayor)",
    "sg:phone":"+34 953 44 02 60",
    "sg:postcode":"23300",
    "sg:province":"Ja\u00e9n",
    "wof:name":"Martinez Mora Dolores",
    "wof:placetype":"venue"
},
  "geometry": {"coordinates":[-3.0878789425,38.1153488159],"type":"Point"}
}