{
  "type": "Feature",
  "properties": {
    "iso:country":"ES",
    "sg:address":"Calle de Perez Carrillo, 20",
    "sg:city":"Durcal",
    "sg:orig_category":"Zapatos (al Por Menor)",
    "sg:phone":"+34 958 78 19 27",
    "sg:postcode":"18650",
    "sg:province":"Granada",
    "wof:name":"Zapateria Candela Cb",
    "wof:placetype":"venue"
},
  "geometry": {"coordinates":[-3.5674893856,36.9885215759],"type":"Point"}
}