{
  "type": "Feature",
  "properties": {
    "addr:full":"Avgd Barcelona, 17 Lleida Lleida 25001",
    "addr:housenumber":"17",
    "addr:postcode":"25001",
    "iso:country":"ES",
    "sg:address":"Avgd Barcelona, 17",
    "sg:city":"Lleida",
    "sg:orig_category":"Mec\u00c1nico Del Autom\u00d3vil",
    "sg:phone":"+34 973 20 32 58",
    "sg:postcode":"25001",
    "sg:province":"Lleida",
    "wof:name":"Lleidamobil S.a.",
    "wof:placetype":"venue"
},
  "geometry": {"coordinates":[0.6233339906,41.6054992676],"type":"Point"}
}