{
  "type": "Feature",
  "properties": {
    "iso:country":"ES",
    "sg:address":"La Cerrajera, 59",
    "sg:city":"Cuenca",
    "sg:orig_category":"Reposter\u00cdas",
    "sg:phone":"+34 969 24 13 90",
    "sg:postcode":"16004",
    "sg:province":"Cuenca",
    "wof:name":"Articulos De Panaderia S.l.",
    "wof:placetype":"venue"
},
  "geometry": {"coordinates":[-2.1447222233,40.0526504517],"type":"Point"}
}