{
  "type": "Feature",
  "properties": {
    "iso:country":"ES",
    "sg:address":"Ctra Malpartida, S/n",
    "sg:city":"Plasencia",
    "sg:orig_category":"\u00c1rboles Frutales",
    "sg:phone":"+34 927 42 01 08",
    "sg:postcode":"10600",
    "sg:province":"C\u00e1ceres",
    "wof:name":"Becedas Torres Ricardo",
    "wof:placetype":"venue"
},
  "geometry": {"coordinates":[-6.1002988815,40.0150489807],"type":"Point"}
}