{
  "type": "Feature",
  "properties": {
    "iso:country":"ES",
    "sg:address":"Calle de Vicente Pulido, 34",
    "sg:city":"Santa Ana De Pusa",
    "sg:orig_category":"Peluquer\u00cdas, Peluquer\u00cda Mixta",
    "sg:phone":"+34 925 70 30 47",
    "sg:postcode":"45653",
    "sg:province":"Toledo",
    "wof:name":"Garcia Esteban Juana",
    "wof:placetype":"venue"
},
  "geometry": {"coordinates":[-4.7077889442,39.7611885071],"type":"Point"}
}