{
  "type": "Feature",
  "properties": {
    "iso:country":"ES",
    "sg:address":"Avda Jacinto Benavente, 27",
    "sg:city":"Valencia",
    "sg:orig_category":"Laboratorios Y Asesor\u00cda En Enolog\u00cda",
    "sg:phone":"+34 963 34 36 38",
    "sg:postcode":"46005",
    "sg:province":"Valencia",
    "wof:name":"Corbi Del Portillo Jose Vicente",
    "wof:placetype":"venue"
},
  "geometry": {"coordinates":[-0.3614799976,39.4644584656],"type":"Point"}
}