{
  "type": "Feature",
  "properties": {
    "addr:full":"Calle de Portugal, 14 Arrecife Las Palmas 35500",
    "addr:housenumber":"14",
    "addr:postcode":"35500",
    "addr:street":"Calle De Portugal",
    "iso:country":"ES",
    "sg:address":"Calle de Portugal, 14",
    "sg:city":"Arrecife",
    "sg:orig_category":"Inform\u00c1tica, Ofim\u00c1tica (estudios, Asesor\u00cda, Ingenier\u00cda, Formaci\u00d3n)",
    "sg:phone":"+34 928 81 63 36",
    "sg:postcode":"35500",
    "sg:province":"Las Palmas",
    "wof:name":"Grialnet Solutions S.l.",
    "wof:placetype":"venue"
},
  "geometry": {"coordinates":[-13.553360939,28.9620819092],"type":"Point"}
}