{
  "type": "Feature",
  "properties": {
    "addr:full":"Calle de Pedro Antonio De Alarcon, 9 Granada Granada 18005",
    "addr:housenumber":"9",
    "addr:postcode":"18005",
    "addr:street":"Calle De Pedro Antonio De Alarcon",
    "iso:country":"ES",
    "sg:address":"Calle de Pedro Antonio De Alarcon, 9",
    "sg:city":"Granada",
    "sg:orig_category":"Inmobiliaria (agencias)",
    "sg:phone":"+34 958 53 58 61",
    "sg:postcode":"18005",
    "sg:province":"Granada",
    "wof:name":"Granacasa Inmuebles S.l.",
    "wof:placetype":"venue"
},
  "geometry": {"coordinates":[-3.6038620472,37.16954422],"type":"Point"}
}