{
  "type": "Feature",
  "properties": {
    "iso:country":"ES",
    "sg:address":"Calle de Secundino Esnaola, 14",
    "sg:city":"Donostia-san Sebastian",
    "sg:orig_category":"M\u00c9dicos: Estomatolog\u00cda",
    "sg:phone":"+34 943 32 13 68",
    "sg:postcode":"20001",
    "sg:province":"Guip\u00f9zcoa",
    "wof:name":"Barrenechea Suso Leonardo",
    "wof:placetype":"venue"
},
  "geometry": {"coordinates":[-1.9734569788,43.3231239319],"type":"Point"}
}