{
  "type": "Feature",
  "properties": {
    "iso:country":"ES",
    "sg:address":"G.v. Corts Catalanes, 524",
    "sg:city":"Barcelona",
    "sg:orig_category":"Delegados, Agentes De Tr\u00c1nsito, Auxiliares De Transporte Internacional",
    "sg:phone":"+34 934 53 42 50",
    "sg:postcode":"08011",
    "sg:province":"Barcelona",
    "sg:website":"www.tamex.com",
    "wof:name":"Tamex Catalunya S.a.",
    "wof:placetype":"venue"
},
  "geometry": {"coordinates":[2.1590080261,41.3820419312],"type":"Point"}
}