{
  "type": "Feature",
  "properties": {
    "iso:country":"ES",
    "sg:address":"Carr Ponent, 140",
    "sg:city":"Badalona",
    "sg:orig_category":"Vinos Y Licores (venta Al Por Menor)",
    "sg:phone":"+34 933 83 23 55",
    "sg:postcode":"08912",
    "sg:province":"Barcelona",
    "wof:name":"Gomez Gergoles Daniel",
    "wof:placetype":"venue"
},
  "geometry": {"coordinates":[2.2343740463,41.4420585632],"type":"Point"}
}