{
  "type": "Feature",
  "properties": {
    "addr:full":"Calle de Allende Manuel, 18 Bilbao Vizcaya 48010",
    "addr:housenumber":"18",
    "addr:postcode":"48010",
    "addr:street":"Calle De Allende Manuel",
    "iso:country":"ES",
    "sg:address":"Calle de Allende Manuel, 18",
    "sg:city":"Bilbao",
    "sg:orig_category":"Caf\u00c9s, Bares, Cervecer\u00cdas",
    "sg:phone":"+34 944 43 98 62",
    "sg:postcode":"48010",
    "sg:province":"Vizcaya",
    "wof:name":"Gaizka Parcha De La Hoz Y Rodrigo Eugenio Andaur Valencia C.b.",
    "wof:placetype":"venue"
},
  "geometry": {"coordinates":[-2.9420492649,43.2594337463],"type":"Point"}
}