{
  "type": "Feature",
  "properties": {
    "addr:full":"Nostian, 9 Nostian La Coru\u00f1a 15008",
    "addr:housenumber":"9",
    "addr:postcode":"15008",
    "addr:street":"Nostian;La Corun\u0303A",
    "iso:country":"ES",
    "sg:address":"Nostian, 9",
    "sg:city":"Nostian",
    "sg:orig_category":"Farmacias (repartici\u00d3n Y Al Por Mayor)",
    "sg:phone":"+34 981 25 55 49",
    "sg:postcode":"15008",
    "sg:province":"La Coru\u00f1a",
    "wof:name":"Codex 2003 Sl",
    "wof:placetype":"venue"
},
  "geometry": {"coordinates":[-8.4512443542,43.3434753418],"type":"Point"}
}