{
  "type": "Feature",
  "properties": {
    "iso:country":"ES",
    "sg:address":"Diseminados Gausa, S/n",
    "sg:city":"Sagunt",
    "sg:orig_category":"Mec\u00c1nico Del Autom\u00d3vil",
    "sg:phone":"+34 962 66 15 28",
    "sg:postcode":"46500",
    "sg:province":"Valencia",
    "wof:name":"Turbina Sal",
    "wof:placetype":"venue"
},
  "geometry": {"coordinates":[-0.2783089876,39.6799659729],"type":"Point"}
}