{
  "type": "Feature",
  "properties": {
    "addr:full":"Calle de Cardenal Benlloch, 30 Mislata Valencia 46920",
    "addr:housenumber":"30",
    "addr:postcode":"46920",
    "addr:street":"Calle De Cardenal Benlloch",
    "iso:country":"ES",
    "sg:address":"Calle de Cardenal Benlloch, 30",
    "sg:city":"Mislata",
    "sg:orig_category":"Postigos, Persianas Y Celos\u00cdas",
    "sg:phone":"+34 963 79 29 79",
    "sg:postcode":"46920",
    "sg:province":"Valencia",
    "wof:name":"Diaz Castro Ana Maria",
    "wof:placetype":"venue"
},
  "geometry": {"coordinates":[-0.4165304005,39.4723625183],"type":"Point"}
}