{
  "type": "Feature",
  "properties": {
    "iso:country":"ES",
    "sg:address":"Carrer de Pilar, 36",
    "sg:city":"Premia Mar",
    "sg:orig_category":"Promotores Constructores",
    "sg:phone":"+34 937 51 59 74",
    "sg:postcode":"08330",
    "sg:province":"Barcelona",
    "wof:name":"Malik & Sons S.l.",
    "wof:placetype":"venue"
},
  "geometry": {"coordinates":[2.3561570644,41.493598938],"type":"Point"}
}