{
  "type": "Feature",
  "properties": {
    "addr:full":"Carrer de Pau (la), 14 S. Pere Ribes Barcelona 08810",
    "addr:housenumber":"14",
    "addr:postcode":"08810",
    "addr:street":"Carrer De Pau La;S. Pere Ribes Barcelona",
    "iso:country":"ES",
    "sg:address":"Carrer de Pau (la), 14",
    "sg:city":"S. Pere Ribes",
    "sg:orig_category":"Promotores Constructores",
    "sg:phone":"+34 938 96 10 86",
    "sg:postcode":"08810",
    "sg:province":"Barcelona",
    "wof:name":"Coll Broders S.l.",
    "wof:placetype":"venue"
},
  "geometry": {"coordinates":[1.7735990286,41.2612190247],"type":"Point"}
}