{
  "type": "Feature",
  "properties": {
    "addr:full":"Calle de Santo Domingo, 26 Sanlucar De Barrameda C\u00e1diz 11540",
    "addr:housenumber":"26",
    "addr:postcode":"11540",
    "addr:street":"Calle De Santo Domingo;Ca\u0301Diz",
    "iso:country":"ES",
    "sg:address":"Calle de Santo Domingo, 26",
    "sg:city":"Sanlucar De Barrameda",
    "sg:orig_category":"\u00d3ptica: Instrumentos (fabricaci\u00d3n)",
    "sg:phone":"+34 956 38 39 64",
    "sg:postcode":"11540",
    "sg:province":"C\u00e1diz",
    "wof:name":"Barbadillo Bidaurreta Soledad",
    "wof:placetype":"venue"
},
  "geometry": {"coordinates":[-6.3506832123,36.7799377441],"type":"Point"}
}