{
  "type": "Feature",
  "properties": {
    "addr:full":"Rua Xeneral Pardi\u00d1as (do), 15 Santiago De Compostela La Coru\u00f1a 15701",
    "addr:postcode":"15701",
    "addr:street":"Rua Xeneral;Corun\u0303A",
    "iso:country":"ES",
    "sg:address":"Rua Xeneral Pardi\u00d1as (do), 15",
    "sg:city":"Santiago De Compostela",
    "sg:orig_category":"Panader\u00cdas, Panader\u00cdas",
    "sg:phone":"+34 981 56 61 99",
    "sg:postcode":"15701",
    "sg:province":"La Coru\u00f1a",
    "wof:name":"Iglesias Garcia Manuel",
    "wof:placetype":"venue"
},
  "geometry": {"coordinates":[-8.5463380814,42.8753433228],"type":"Point"}
}