{
  "type": "Feature",
  "properties": {
    "iso:country":"ES",
    "sg:address":"Carrer de Isaac Peral, S/n",
    "sg:city":"Can Castells",
    "sg:orig_category":"Fabricaci\u00d3n De Muebles",
    "sg:phone":"+34 938 49 15 23",
    "sg:postcode":"08420",
    "sg:province":"Barcelona",
    "sg:website":"www.muebles-acsa.com",
    "wof:name":"Muebles Acsa S.l.",
    "wof:placetype":"venue"
},
  "geometry": {"coordinates":[2.2783401012,41.6220207214],"type":"Point"}
}