{
  "type": "Feature",
  "properties": {
    "addr:full":"Calle de Jaime De Gra\u00d1ana, 25 Jumilla Murcia 30520",
    "addr:housenumber":"25",
    "addr:postcode":"30520",
    "addr:street":"Calle De Jaime De Gran\u0303Ana",
    "iso:country":"ES",
    "sg:address":"Calle de Jaime De Gra\u00d1ana, 25",
    "sg:city":"Jumilla",
    "sg:orig_category":"Carnicer\u00cdas, Carnicer\u00cdas",
    "sg:phone":"+34 968 78 10 10",
    "sg:postcode":"30520",
    "sg:province":"Murcia",
    "wof:name":"Terol Ortiz Isidro",
    "wof:placetype":"venue"
},
  "geometry": {"coordinates":[-1.3177000284,38.4773292542],"type":"Point"}
}