{
  "type": "Feature",
  "properties": {
    "iso:country":"ES",
    "sg:address":"Carrer de Estires, 25",
    "sg:city":"Olot",
    "sg:orig_category":"Ingenier\u00cda, Centros De Estudios (industria)",
    "sg:phone":"+34 972 27 40 65",
    "sg:postcode":"17800",
    "sg:province":"Girona",
    "wof:name":"Comunitat Propietaris Carrer Estires 25",
    "wof:placetype":"venue"
},
  "geometry": {"coordinates":[2.4879710674,42.1849975586],"type":"Point"}
}