{
  "type": "Feature",
  "properties": {
    "addr:full":"Cerca(a Pedra), S/n Cerca La Coru\u00f1a 15360",
    "addr:housenumber":"s / n",
    "addr:postcode":"15360",
    "addr:street":"Cerca;Pedra;Cerca La Corun\u0303A",
    "iso:country":"ES",
    "sg:address":"Cerca(a Pedra), S/n",
    "sg:city":"Cerca",
    "sg:orig_category":"Asociaciones, Organismos Culturales Y Socioeducativos",
    "sg:phone":"+34 981 40 55 56",
    "sg:postcode":"15360",
    "sg:province":"La Coru\u00f1a",
    "wof:name":"Centro De La Tercera Edad San Antonio De La Piedra",
    "wof:placetype":"venue"
},
  "geometry": {"coordinates":[-7.8746237755,43.7365341187],"type":"Point"}
}