{
  "type": "Feature",
  "properties": {
    "iso:country":"ES",
    "sg:address":"Calle de Pizarro, 15",
    "sg:city":"Aranda Duero",
    "sg:orig_category":"Escayola Y Productos De Escayola (fabricaci\u00d3n, Al Por Mayor)",
    "sg:phone":"+34 947 50 69 84",
    "sg:postcode":"09400",
    "sg:province":"Burgos",
    "wof:name":"Hernando Garcia Gregorio",
    "wof:placetype":"venue"
},
  "geometry": {"coordinates":[-3.678550005,41.670539856],"type":"Point"}
}