{
  "type": "Feature",
  "properties": {
    "addr:full":"Calle de Telleria, 5 Barakaldo Vizcaya 48903",
    "addr:housenumber":"5",
    "addr:postcode":"48903",
    "addr:street":"Calle De Telleria",
    "iso:country":"ES",
    "sg:address":"Calle de Telleria, 5",
    "sg:city":"Barakaldo",
    "sg:orig_category":"Pescader\u00cdas (al Por Menor)",
    "sg:phone":"+34 944 90 21 93",
    "sg:postcode":"48903",
    "sg:province":"Vizcaya",
    "wof:name":"Diego Puente Gonzalez",
    "wof:placetype":"venue"
},
  "geometry": {"coordinates":[-2.9819979668,43.2826843262],"type":"Point"}
}