{
  "type": "Feature",
  "properties": {
    "addr:full":"Carrer de Cavalleria, 19 Manlleu Barcelona 08560",
    "addr:housenumber":"19",
    "addr:postcode":"08560",
    "addr:street":"Carrer De Cavalleria",
    "iso:country":"ES",
    "sg:address":"Carrer de Cavalleria, 19",
    "sg:city":"Manlleu",
    "sg:orig_category":"Carnicer\u00cdas, Carnicer\u00cdas",
    "sg:phone":"+34 938 51 05 93",
    "sg:postcode":"08560",
    "sg:province":"Barcelona",
    "wof:name":"Terradellas Delgar Josep",
    "wof:placetype":"venue"
},
  "geometry": {"coordinates":[2.2867341042,42.0007705688],"type":"Point"}
}