{
  "type": "Feature",
  "properties": {
    "iso:country":"ES",
    "sg:address":"Trv. Oseiro(oseiro), 141",
    "sg:city":"Arteixo",
    "sg:orig_category":"Plomeros",
    "sg:phone":"+34 981 60 06 06",
    "sg:postcode":"15141",
    "sg:province":"La Coru\u00f1a",
    "wof:name":"Figueroa Rama Victorino",
    "wof:placetype":"venue"
},
  "geometry": {"coordinates":[-8.483089447,43.3230514526],"type":"Point"}
}