{
  "type": "Feature",
  "properties": {
    "addr:full":"Avda Papagayo, 59 Castillo Del Aguila Las Palmas 35580",
    "addr:housenumber":"59",
    "addr:postcode":"35580",
    "addr:street":"Avda Papagayo;Del",
    "iso:country":"ES",
    "sg:address":"Avda Papagayo, 59",
    "sg:city":"Castillo Del Aguila",
    "sg:orig_category":"Pr\u00c1ctica De Vela, Navegaci\u00d3n Y Deportes N\u00c1uticos Y Acu\u00c1ticos",
    "sg:phone":"+34 928 51 91 41",
    "sg:postcode":"35580",
    "sg:province":"Las Palmas",
    "wof:name":"Jacobs  Peter",
    "wof:placetype":"venue"
},
  "geometry": {"coordinates":[-13.8307790756,28.8657550812],"type":"Point"}
}