{
  "type": "Feature",
  "properties": {
    "addr:full":"Calle de San Sebastian, 6 Marchena Sevilla 41620",
    "addr:housenumber":"6",
    "addr:postcode":"41620",
    "addr:street":"Calle De San Sebastian",
    "iso:country":"ES",
    "sg:address":"Calle de San Sebastian, 6",
    "sg:city":"Marchena",
    "sg:orig_category":"\u00d3ptica: Instrumentos (fabricaci\u00d3n)",
    "sg:phone":"+34 954 84 41 85",
    "sg:postcode":"41620",
    "sg:province":"Sevilla",
    "wof:name":"Toro Lopez Maria Angeles",
    "wof:placetype":"venue"
},
  "geometry": {"coordinates":[-5.4152665138,37.3286781311],"type":"Point"}
}