{
  "type": "Feature",
  "properties": {
    "addr:full":"Calle de Txurruka, 12 Donostia-san Sebastian Guip\u00f9zcoa 20004",
    "addr:housenumber":"12",
    "addr:postcode":"20004",
    "addr:street":"Calle De Txurruka",
    "iso:country":"ES",
    "sg:address":"Calle de Txurruka, 12",
    "sg:city":"Donostia-san Sebastian",
    "sg:orig_category":"Perfumer\u00cda (al Por Menor)",
    "sg:phone":"+34 943 42 22 67",
    "sg:postcode":"20004",
    "sg:province":"Guip\u00f9zcoa",
    "wof:name":"Perfumeria Luis Diaz S.l.",
    "wof:placetype":"venue"
},
  "geometry": {"coordinates":[-1.9820430279,43.3198623657],"type":"Point"}
}