{
  "type": "Feature",
  "properties": {
    "iso:country":"ES",
    "sg:address":"Caldereria, 3",
    "sg:city":"Estella",
    "sg:orig_category":"Zapatos (al Por Menor)",
    "sg:phone":"+34 948 54 65 61",
    "sg:postcode":"31200",
    "sg:province":"Navarra",
    "wof:name":"Arbeloa Suberbiola Isabel",
    "wof:placetype":"venue"
},
  "geometry": {"coordinates":[-2.0319728851,42.6726875305],"type":"Point"}
}