{
  "type": "Feature",
  "properties": {
    "addr:full":"Calle de Motrico, 13 San Fernando De Henares Madrid 28830",
    "addr:housenumber":"13",
    "addr:postcode":"28830",
    "addr:street":"Calle De Motrico",
    "iso:country":"ES",
    "sg:address":"Calle de Motrico, 13",
    "sg:city":"San Fernando De Henares",
    "sg:orig_category":"Empresas De Limpieza",
    "sg:phone":"+34 916 73 50 33",
    "sg:postcode":"28830",
    "sg:province":"Madrid",
    "wof:name":"Multiservicios El Pilar S.l.",
    "wof:placetype":"venue"
},
  "geometry": {"coordinates":[-3.5279839039,40.4190635681],"type":"Point"}
}