{
  "type": "Feature",
  "properties": {
    "iso:country":"ES",
    "sg:address":"Avda Jose Antonio, 14",
    "sg:city":"Suances",
    "sg:orig_category":"Alquiler De V\u00cddeo",
    "sg:phone":"+34 942 81 07 23",
    "sg:postcode":"39340",
    "sg:province":"Cantabria",
    "wof:name":"Gestion De Espacio Y Tiempo Sl",
    "wof:placetype":"venue"
},
  "geometry": {"coordinates":[-4.0404472351,43.4246063232],"type":"Point"}
}