{
  "type": "Feature",
  "properties": {
    "addr:full":"Calle de San Pedro De Alcantara, 9 Linea De La Concepcion C\u00e1diz 11300",
    "addr:housenumber":"9",
    "addr:postcode":"11300",
    "addr:street":"Calle De;Alcantara;Ca\u0301Diz",
    "iso:country":"ES",
    "sg:address":"Calle de San Pedro De Alcantara, 9",
    "sg:city":"Linea De La Concepcion",
    "sg:orig_category":"Molduras, Junquillos, Listones Y Molduras Perforadas",
    "sg:phone":"+34 956 76 51 22",
    "sg:postcode":"11300",
    "sg:province":"C\u00e1diz",
    "wof:name":"Sistelcom-telemensaje S.a.",
    "wof:placetype":"venue"
},
  "geometry": {"coordinates":[-5.3511381149,36.1638412476],"type":"Point"}
}