{
  "type": "Feature",
  "properties": {
    "addr:full":"Carrer de Mare De Deu De Montserrat, 54 Granollers Barcelona 08401",
    "addr:housenumber":"54",
    "addr:postcode":"08401",
    "addr:street":"Carrer De Mare De Deu De Montserrat",
    "iso:country":"ES",
    "sg:address":"Carrer de Mare De Deu De Montserrat, 54",
    "sg:city":"Granollers",
    "sg:orig_category":"Perfumer\u00cda (al Por Menor)",
    "sg:phone":"+34 938 70 87 62",
    "sg:postcode":"08401",
    "sg:province":"Barcelona",
    "wof:name":"Cabezas Romero Carmen",
    "wof:placetype":"venue"
},
  "geometry": {"coordinates":[2.2843909264,41.6000061035],"type":"Point"}
}