{
  "type": "Feature",
  "properties": {
    "iso:country":"ES",
    "sg:address":"Avda Portugal, 43",
    "sg:city":"Cadiz",
    "sg:orig_category":"Abogados",
    "sg:phone":"+34 956 27 77 28",
    "sg:postcode":"11008",
    "sg:province":"C\u00e1diz",
    "wof:name":"Huertas Calzado Rafael",
    "wof:placetype":"venue"
},
  "geometry": {"coordinates":[-6.2785110474,36.5144729614],"type":"Point"}
}