{
  "type": "Feature",
  "properties": {
    "addr:full":"Carr Sequial, 61 Sueca Valencia 46410",
    "addr:housenumber":"61",
    "addr:postcode":"46410",
    "addr:street":"Carr Sequial",
    "iso:country":"ES",
    "sg:address":"Carr Sequial, 61",
    "sg:city":"Sueca",
    "sg:orig_category":"Laboratorios Y Trabajos De Fotograf\u00cda, V\u00cddeo Y Cine",
    "sg:phone":"+34 961 70 08 34",
    "sg:postcode":"46410",
    "sg:province":"Valencia",
    "wof:name":"Distribuciones Fotograficas Toni S.l.",
    "wof:placetype":"venue"
},
  "geometry": {"coordinates":[-0.3102520108,39.2053260803],"type":"Point"}
}