{
  "type": "Feature",
  "properties": {
    "addr:full":"Calle de San Juan, 6 Parra Badajoz 06176",
    "addr:housenumber":"6",
    "addr:postcode":"06176",
    "addr:street":"Calle De San Juan",
    "iso:country":"ES",
    "sg:address":"Calle de San Juan, 6",
    "sg:city":"Parra",
    "sg:orig_category":"Asesor\u00cda Fiscal Y Jur\u00cddica",
    "sg:phone":"+34 924 68 26 17",
    "sg:postcode":"06176",
    "sg:province":"Badajoz",
    "wof:name":"Multigestion Salvatierra S.l.",
    "wof:placetype":"venue"
},
  "geometry": {"coordinates":[-6.6228318214,38.5267791748],"type":"Point"}
}