{
  "type": "Feature",
  "properties": {
    "iso:country":"ES",
    "sg:address":"C/ Victoria Kent, 33",
    "sg:city":"Elche",
    "sg:orig_category":"Farmacias",
    "sg:phone":"+34 966 66 70 42",
    "sg:postcode":"03206",
    "sg:province":"Alicante",
    "wof:name":"Pascual Torro Jose Antonio",
    "wof:placetype":"venue"
},
  "geometry": {"coordinates":[-0.705787003,38.2768287659],"type":"Point"}
}