{
  "type": "Feature",
  "properties": {
    "iso:country":"ES",
    "sg:address":"Prj. Guillen, 28",
    "sg:city":"Ca\u00f1ada San Urbano",
    "sg:orig_category":"Ebanister\u00cda",
    "sg:phone":"+34 950 52 02 44",
    "sg:postcode":"04120",
    "sg:province":"Almer\u00eda",
    "wof:name":"Molina Morales Juan Antonio",
    "wof:placetype":"venue"
},
  "geometry": {"coordinates":[-2.389688015,36.8369255066],"type":"Point"}
}