{
  "type": "Feature",
  "properties": {
    "iso:country":"ES",
    "sg:address":"Calle de Martires Concepcionistas, 5",
    "sg:city":"Madrid",
    "sg:orig_category":"Productos Qu\u00cdmicos (fabricaci\u00d3n, Al Por Mayor)",
    "sg:phone":"+34 914 01 60 95",
    "sg:postcode":"28006",
    "sg:province":"Madrid",
    "wof:name":"Laboratorios Odotek S.l.",
    "wof:placetype":"venue"
},
  "geometry": {"coordinates":[-3.6708319187,40.4277648926],"type":"Point"}
}