{
  "type": "Feature",
  "properties": {
    "iso:country":"ES",
    "sg:address":"Carrer de Mercaders, 1",
    "sg:city":"Sant Salvador",
    "sg:orig_category":"Molduras, Junquillos, Listones Y Molduras Perforadas",
    "sg:phone":"+34 977 52 28 01",
    "sg:postcode":"43130",
    "sg:province":"Tarragona",
    "wof:name":"Galcera Masdeu Juan",
    "wof:placetype":"venue"
},
  "geometry": {"coordinates":[1.2410039902,41.1608467102],"type":"Point"}
}