{
  "type": "Feature",
  "properties": {
    "addr:full":"Calle de Nardiz Tar Jon, 28 Bermeo Vizcaya 48370",
    "addr:housenumber":"28",
    "addr:postcode":"48370",
    "addr:street":"Calle De Nardiz Tar Jon",
    "iso:country":"ES",
    "sg:address":"Calle de Nardiz Tar Jon, 28",
    "sg:city":"Bermeo",
    "sg:orig_category":"Pescader\u00cdas (al Por Menor)",
    "sg:phone":"+34 946 88 26 49",
    "sg:postcode":"48370",
    "sg:province":"Vizcaya",
    "wof:name":"Bilbao Anduiza Arantza",
    "wof:placetype":"venue"
},
  "geometry": {"coordinates":[-2.7231318951,43.4200286865],"type":"Point"}
}