{
  "type": "Feature",
  "properties": {
    "addr:full":"Calle de Arenal, 26 Madrid Madrid 28013",
    "addr:housenumber":"26",
    "addr:postcode":"madrid;28013",
    "addr:street":"Calle De Arenal",
    "iso:country":"ES",
    "sg:address":"Calle de Arenal, 26",
    "sg:city":"Madrid",
    "sg:orig_category":"Estilistas Y Estudios De Estilo De Corte Y Confecci\u00d3n",
    "sg:phone":"+34 915 42 53 88",
    "sg:postcode":"28013",
    "sg:province":"Madrid",
    "wof:name":"Pelaez Puig Ricardo",
    "wof:placetype":"venue"
},
  "geometry": {"coordinates":[-3.7083418369,40.4177474976],"type":"Point"}
}