{
  "type": "Feature",
  "properties": {
    "iso:country":"ES",
    "sg:address":"Ctra Palma Del Rio (bda. Occidente), Km. 0003,0",
    "sg:city":"Cordoba",
    "sg:orig_category":"Bisuter\u00cda, Joyer\u00cda, Relojer\u00cda (al Por Menor)",
    "sg:phone":"+34 957 48 47 20",
    "sg:postcode":"14005",
    "sg:province":"C\u00f3rdoba",
    "wof:name":"Lopez Hermanos S.l.",
    "wof:placetype":"venue"
},
  "geometry": {"coordinates":[-4.8831849098,37.866859436],"type":"Point"}
}