{
  "type": "Feature",
  "properties": {
    "addr:full":"Avda Palencia, 25 Aguilar Campoo Palencia 34800",
    "addr:housenumber":"25",
    "addr:postcode":"34800",
    "addr:street":"Avda Palencia",
    "iso:country":"ES",
    "sg:address":"Avda Palencia, 25",
    "sg:city":"Aguilar Campoo",
    "sg:orig_category":"Ropa Para Se\u00d1oras Y Caballeros (al Por Menor)",
    "sg:phone":"+34 979 12 20 36",
    "sg:postcode":"34800",
    "sg:province":"Palencia",
    "wof:name":"Ruiz Argueso Aquilino",
    "wof:placetype":"venue"
},
  "geometry": {"coordinates":[-4.264898777,42.7938194275],"type":"Point"}
}