{
  "type": "Feature",
  "properties": {
    "addr:full":"Rbla Joaquim Vayreda, 63 Gava Barcelona 08850",
    "addr:housenumber":"63",
    "addr:postcode":"08850",
    "addr:street":"Rbla Joaquim Vayreda",
    "iso:country":"ES",
    "sg:address":"Rbla Joaquim Vayreda, 63",
    "sg:city":"Gava",
    "sg:orig_category":"Agencias De Viajes",
    "sg:phone":"+34 936 38 07 64",
    "sg:postcode":"08850",
    "sg:province":"Barcelona",
    "wof:name":"Viajes Iberia S.a.",
    "wof:placetype":"venue"
},
  "geometry": {"coordinates":[2.0070900917,41.3054924011],"type":"Point"}
}