{
  "type": "Feature",
  "properties": {
    "addr:full":"Carr Independencia, 159 Badalona Barcelona 08915",
    "addr:housenumber":"159",
    "addr:postcode":"08915",
    "addr:street":"Carr Independencia",
    "iso:country":"ES",
    "sg:address":"Carr Independencia, 159",
    "sg:city":"Badalona",
    "sg:orig_category":"Alquiler De V\u00cddeo",
    "sg:phone":"+34 933 87 73 24",
    "sg:postcode":"08915",
    "sg:province":"Barcelona",
    "wof:name":"Catala Ibaez Purificacion",
    "wof:placetype":"venue"
},
  "geometry": {"coordinates":[2.2418909073,41.4587059021],"type":"Point"}
}