{
  "type": "Feature",
  "properties": {
    "iso:country":"ES",
    "sg:address":"Carrer de Corsega, 382",
    "sg:city":"Barcelona",
    "sg:orig_category":"Molduras, Junquillos, Listones Y Molduras Perforadas",
    "sg:phone":"+34 934 58 98 22",
    "sg:postcode":"08037",
    "sg:province":"Barcelona",
    "wof:name":"Noguera Rimblas Juan",
    "wof:placetype":"venue"
},
  "geometry": {"coordinates":[2.163367033,41.3993911743],"type":"Point"}
}