{
  "type": "Feature",
  "properties": {
    "addr:full":"Calle de Soria, S/n Burgos Burgos 09004",
    "addr:housenumber":"s / n",
    "addr:postcode":"09004",
    "addr:street":"Calle De Soria",
    "iso:country":"ES",
    "sg:address":"Calle de Soria, S/n",
    "sg:city":"Burgos",
    "sg:orig_category":"Iglesia Cat\u00d3lica",
    "sg:phone":"+34 947 24 43 18",
    "sg:postcode":"09004",
    "sg:province":"Burgos",
    "wof:name":"Parroquia De San Martin De Porres",
    "wof:placetype":"venue"
},
  "geometry": {"coordinates":[-3.6911709309,42.3482894897],"type":"Point"}
}