{
  "type": "Feature",
  "properties": {
    "addr:full":"Calle de San Isidro, 14 Villena Alicante 03400",
    "addr:housenumber":"14",
    "addr:postcode":"03400",
    "addr:street":"Calle De San Isidro",
    "iso:country":"ES",
    "sg:address":"Calle de San Isidro, 14",
    "sg:city":"Villena",
    "sg:orig_category":"Empresas De Carpinter\u00cda Met\u00c1lica",
    "sg:phone":"+34 965 80 64 69",
    "sg:postcode":"03400",
    "sg:province":"Alicante",
    "wof:name":"Feri Hernandez Antonia",
    "wof:placetype":"venue"
},
  "geometry": {"coordinates":[-0.8680980206,38.637714386],"type":"Point"}
}