{
  "type": "Feature",
  "properties": {
    "iso:country":"ES",
    "sg:address":"Calle de Sierra De Los Filabres, 101",
    "sg:city":"Madrid",
    "sg:orig_category":"Molduras, Junquillos, Listones Y Molduras Perforadas",
    "sg:phone":"+34 914 37 99 94",
    "sg:postcode":"28038",
    "sg:province":"Madrid",
    "wof:name":"Santos Ca\u00f1o Antonio",
    "wof:placetype":"venue"
},
  "geometry": {"coordinates":[-3.6605000496,40.3965911865],"type":"Point"}
}