{
  "type": "Feature",
  "properties": {
    "iso:country":"ES",
    "sg:address":"Calle de Obispo Laplana, 8",
    "sg:city":"Zaragoza",
    "sg:orig_category":"Servicios De Telecomunicaciones",
    "sg:phone":"+34 976 42 99 40",
    "sg:postcode":"50002",
    "sg:province":"Zaragoza",
    "wof:name":"Chardoudi  Kamal",
    "wof:placetype":"venue"
},
  "geometry": {"coordinates":[-0.8627570271,41.6464920044],"type":"Point"}
}