{
  "type": "Feature",
  "properties": {
    "iso:country":"ES",
    "sg:address":"Avda Ciencias (las), 18",
    "sg:city":"Sevilla",
    "sg:orig_category":"Farmacias",
    "sg:phone":"+34 954 40 96 57",
    "sg:postcode":"41020",
    "sg:province":"Sevilla",
    "wof:name":"Perez Ruiz Macarena",
    "wof:placetype":"venue"
},
  "geometry": {"coordinates":[-5.9217672348,37.3954811096],"type":"Point"}
}