{
  "type": "Feature",
  "properties": {
    "iso:country":"ES",
    "sg:address":"Calle de Conde Garay, 35",
    "sg:city":"Osorno",
    "sg:orig_category":"C\u00c1maras De Comercio E Industria, Oficios, Agricultura",
    "sg:phone":"+34 979 81 70 05",
    "sg:postcode":"34460",
    "sg:province":"Palencia",
    "wof:name":"Camara Agraria Provincial De Palencia",
    "wof:placetype":"venue"
},
  "geometry": {"coordinates":[-4.3630948067,42.4079818726],"type":"Point"}
}