{
  "type": "Feature",
  "properties": {
    "iso:country":"ES",
    "sg:address":"Calle de Ubeda, 27",
    "sg:city":"Aljorra",
    "sg:orig_category":"Inmobiliaria (agencias)",
    "sg:phone":"+34 968 16 42 15",
    "sg:postcode":"30390",
    "sg:province":"Murcia",
    "wof:name":"Lisanros S L",
    "wof:placetype":"venue"
},
  "geometry": {"coordinates":[-1.0755300522,37.692905426],"type":"Point"}
}