{
  "type": "Feature",
  "properties": {
    "iso:country":"ES",
    "sg:address":"Federico Garcia Lorca, 15",
    "sg:city":"Alcudia",
    "sg:orig_category":"Agentes, Concesionarios Y Sucursales De Veh\u00cdculos",
    "sg:phone":"+34 962 99 75 34",
    "sg:postcode":"46250",
    "sg:province":"Valencia",
    "wof:name":"L'alcudia Motors S.l.l.",
    "wof:placetype":"venue"
},
  "geometry": {"coordinates":[-0.5035240054,39.2013397217],"type":"Point"}
}