{
  "type": "Feature",
  "properties": {
    "iso:country":"ES",
    "sg:address":"Av. Valladolid, 41",
    "sg:city":"Madrid",
    "sg:orig_category":"Aceros Inoxidables",
    "sg:phone":"+34 915 47 70 24",
    "sg:postcode":"28008",
    "sg:province":"Madrid",
    "wof:name":"Transformaciones Metalicas Del Noroeste",
    "wof:placetype":"venue"
},
  "geometry": {"coordinates":[-3.7295529842,40.4285507202],"type":"Point"}
}