{
  "type": "Feature",
  "properties": {
    "addr:full":"Calle de Urbasa, 11 Algorta Vizcaya 48993",
    "addr:housenumber":"11",
    "addr:postcode":"48993",
    "addr:street":"Calle De Urbasa",
    "iso:country":"ES",
    "sg:address":"Calle de Urbasa, 11",
    "sg:city":"Algorta",
    "sg:orig_category":"Agencias Y Asesores De Publicidad",
    "sg:phone":"+34 944 60 51 18",
    "sg:postcode":"48993",
    "sg:province":"Vizcaya",
    "wof:name":"Jade Comunicacion S.l.",
    "wof:placetype":"venue"
},
  "geometry": {"coordinates":[-3.0164060593,43.3564796448],"type":"Point"}
}