{
  "type": "Feature",
  "properties": {
    "iso:country":"ES",
    "sg:address":"Pg Suissa, 46",
    "sg:city":"Tona",
    "sg:classifiers":[
        {
            "category":"Manufacturing",
            "subcategory":"Metals",
            "type":"Manufacturing & Wholesale Goods"
        }
    ],
    "sg:phone":"+34 938 12 50 15",
    "sg:postcode":"08551",
    "sg:province":"Barcelona",
    "sg:tags":[
        "en",
        "fundiciones"
    ],
    "wof:name":"Fundiciones De Roda S. A.",
    "wof:placetype":"venue"
},
  "geometry": {"coordinates":[2.2199571133,41.8522224426],"type":"Point"}
}