{
  "type": "Feature",
  "properties": {
    "iso:country":"ES",
    "sg:address":"Calle de Manuel Franco Cubeiro, 32",
    "sg:city":"Torremolinos",
    "sg:orig_category":"Ropa Para Ni\u00d1os (al Por Menor)",
    "sg:phone":"+34 952 37 11 17",
    "sg:postcode":"29620",
    "sg:province":"M\u00e1laga",
    "wof:name":"Solis Y Carnero S.l.",
    "wof:placetype":"venue"
},
  "geometry": {"coordinates":[-4.5182561874,36.613571167],"type":"Point"}
}