{
  "type": "Feature",
  "properties": {
    "addr:full":"Calle de Zarzuela, S/n Navalmanzano Segovia 40280",
    "addr:housenumber":"s",
    "addr:postcode":"40280",
    "addr:street":"Calle De Zarzuela;/ N",
    "iso:country":"ES",
    "sg:address":"Calle de Zarzuela, S/n",
    "sg:city":"Navalmanzano",
    "sg:orig_category":"Empresas De Carpinter\u00cda",
    "sg:phone":"+34 921 57 53 68",
    "sg:postcode":"40280",
    "sg:province":"Segovia",
    "wof:name":"Mu\u00f1oz Martin Agustin",
    "wof:placetype":"venue"
},
  "geometry": {"coordinates":[-4.2549600601,41.2168731689],"type":"Point"}
}