{
  "type": "Feature",
  "properties": {
    "addr:full":"Calle de Eras, 10 Iscar Valladolid 47420",
    "addr:housenumber":"10",
    "addr:postcode":"47420",
    "addr:street":"Calle De Eras",
    "iso:country":"ES",
    "sg:address":"Calle de Eras, 10",
    "sg:city":"Iscar",
    "sg:orig_category":"Material Y Suministros Para Veterinarios",
    "sg:phone":"+34 983 61 20 22",
    "sg:postcode":"47420",
    "sg:province":"Valladolid",
    "wof:name":"Conasa S.l.",
    "wof:placetype":"venue"
},
  "geometry": {"coordinates":[-4.5278577805,41.358543396],"type":"Point"}
}