{
  "type": "Feature",
  "properties": {
    "addr:full":"Carr Major, 24 Felanitx Islas Baleares 07200",
    "addr:housenumber":"24",
    "addr:postcode":"07200",
    "addr:street":"Carr Major",
    "iso:country":"ES",
    "sg:address":"Carr Major, 24",
    "sg:city":"Felanitx",
    "sg:orig_category":"Molduras, Junquillos, Listones Y Molduras Perforadas",
    "sg:phone":"+34 971 58 00 08",
    "sg:postcode":"07200",
    "sg:province":"Islas Baleares",
    "wof:name":"Tur Mateu Gloria",
    "wof:placetype":"venue"
},
  "geometry": {"coordinates":[3.1379621029,39.4173583984],"type":"Point"}
}