{
  "type": "Feature",
  "properties": {
    "addr:full":"Carrer de Topete, 83 Terrassa Barcelona 08221",
    "addr:housenumber":"83",
    "addr:postcode":"08221",
    "addr:street":"Carrer De Topete",
    "iso:country":"ES",
    "sg:address":"Carrer de Topete, 83",
    "sg:city":"Terrassa",
    "sg:orig_category":"Armas Y Municiones (fabricaci\u00d3n, Al Por Mayor)",
    "sg:phone":"+34 937 86 37 27",
    "sg:postcode":"08221",
    "sg:province":"Barcelona",
    "wof:name":"Vito Segura Jose",
    "wof:placetype":"venue"
},
  "geometry": {"coordinates":[2.0172057152,41.5602836609],"type":"Point"}
}