{
  "type": "Feature",
  "properties": {
    "iso:country":"ES",
    "sg:address":"Calle de Jesus De Las Tres Caidas, 3",
    "sg:city":"Sevilla",
    "sg:orig_category":"Tapicer\u00cdas",
    "sg:phone":"+34 954 22 81 69",
    "sg:postcode":"41004",
    "sg:province":"Sevilla",
    "wof:name":"Carrera Maldonado Jose",
    "wof:placetype":"venue"
},
  "geometry": {"coordinates":[-5.9907469749,37.3899765015],"type":"Point"}
}