{
  "type": "Feature",
  "properties": {
    "iso:country":"ES",
    "sg:address":"Calle de Buen Aire, 67",
    "sg:city":"Camas",
    "sg:orig_category":"Centros Empresariales",
    "sg:phone":"+34 954 39 13 52",
    "sg:postcode":"41900",
    "sg:province":"Sevilla",
    "wof:name":"Gallardo Mayo Manuel",
    "wof:placetype":"venue"
},
  "geometry": {"coordinates":[-6.0415172577,37.4016265869],"type":"Point"}
}