{
  "type": "Feature",
  "properties": {
    "addr:full":"Calle de Lomo Guillen, 6 Santa Maria De Guia Las Palmas 35450",
    "addr:housenumber":"6",
    "addr:postcode":"35450",
    "addr:street":"Calle De Lomo Guillen",
    "iso:country":"ES",
    "sg:address":"Calle de Lomo Guillen, 6",
    "sg:city":"Santa Maria De Guia",
    "sg:orig_category":"Caf\u00c9s, Bares, Cervecer\u00cdas",
    "sg:phone":"+34 928 88 39 46",
    "sg:postcode":"35450",
    "sg:province":"Las Palmas",
    "wof:name":"Recreativos Aguiar S.l.",
    "wof:placetype":"venue"
},
  "geometry": {"coordinates":[-15.6324644089,28.1405525208],"type":"Point"}
}