{
  "type": "Feature",
  "properties": {
    "iso:country":"ES",
    "sg:address":"Calle de Correo, 18",
    "sg:city":"Bilbao",
    "sg:orig_category":"Caf\u00c9s, Bares, Cervecer\u00cdas",
    "sg:phone":"+34 944 16 02 89",
    "sg:postcode":"48005",
    "sg:province":"Vizcaya",
    "wof:name":"Garcia De Loma-osorio Ignacio",
    "wof:placetype":"venue"
},
  "geometry": {"coordinates":[-2.9235403538,43.2579803467],"type":"Point"}
}