{
  "type": "Feature",
  "properties": {
    "addr:full":"Avda Compromiso De Caspe, 38 Zaragoza Zaragoza 50002",
    "addr:housenumber":"38",
    "addr:postcode":"50002",
    "addr:street":"Avda Compromiso De Caspe",
    "iso:country":"ES",
    "sg:address":"Avda Compromiso De Caspe, 38",
    "sg:city":"Zaragoza",
    "sg:orig_category":"Farmacias",
    "sg:phone":"+34 976 42 87 95",
    "sg:postcode":"50002",
    "sg:province":"Zaragoza",
    "wof:name":"Martin Trullas Jesus",
    "wof:placetype":"venue"
},
  "geometry": {"coordinates":[-0.8664540052,41.6455574036],"type":"Point"}
}