{
  "type": "Feature",
  "properties": {
    "iso:country":"ES",
    "sg:address":"Calle de Nectar, 31",
    "sg:city":"Madrid",
    "sg:orig_category":"Medias Y Calcetines (al Por Menor)",
    "sg:phone":"+34 917 41 46 52",
    "sg:postcode":"28022",
    "sg:province":"Madrid",
    "wof:name":"Escribano Cabrera Maria Luisa",
    "wof:placetype":"venue"
},
  "geometry": {"coordinates":[-3.6124930382,40.4422035217],"type":"Point"}
}