{
  "type": "Feature",
  "properties": {
    "iso:country":"ES",
    "sg:address":"Calle de Juan Carlos I, S/n",
    "sg:city":"Villamor De Orbigo",
    "sg:orig_category":"Empresas De Pintura Y Revestimientos",
    "sg:phone":"+34 987 38 82 88",
    "sg:postcode":"24393",
    "sg:province":"Le\u00f3n",
    "wof:name":"Alvarez Alvarez Jose Luis",
    "wof:placetype":"venue"
},
  "geometry": {"coordinates":[-5.8754301071,42.4831161499],"type":"Point"}
}