{
  "type": "Feature",
  "properties": {
    "iso:country":"ES",
    "sg:address":"Calle de Trinidad Y Tobago, S/n",
    "sg:city":"Tablero",
    "sg:orig_category":"Asociaciones, Organismos Culturales Y Socioeducativos",
    "sg:phone":"+34 928 14 07 37",
    "sg:postcode":"35100",
    "sg:province":"Las Palmas",
    "wof:name":"Centro De Pensionistas Socios Y Jubilados El Pilar Del Tablero",
    "wof:placetype":"venue"
},
  "geometry": {"coordinates":[-15.6052036285,27.7721252441],"type":"Point"}
}