{
  "type": "Feature",
  "properties": {
    "iso:country":"ES",
    "sg:address":"Calle de Garzas, 10",
    "sg:city":"Pinto",
    "sg:orig_category":"Albergues",
    "sg:phone":"+34 916 92 69 71",
    "sg:postcode":"28320",
    "sg:province":"Madrid",
    "wof:name":"Tianyuan S.l.",
    "wof:placetype":"venue"
},
  "geometry": {"coordinates":[-3.7151501179,40.2479858398],"type":"Point"}
}