{
  "type": "Feature",
  "properties": {
    "iso:country":"ES",
    "sg:address":"Carrer de Clot, 190",
    "sg:city":"Barcelona",
    "sg:orig_category":"Molduras, Junquillos, Listones Y Molduras Perforadas",
    "sg:phone":"+34 933 40 71 48",
    "sg:postcode":"08027",
    "sg:province":"Barcelona",
    "wof:name":"Rodriguez Perez Antonio",
    "wof:placetype":"venue"
},
  "geometry": {"coordinates":[2.1904909611,41.4132881165],"type":"Point"}
}