{
  "type": "Feature",
  "properties": {
    "addr:full":"Grup Soledad (la), S/n Villafranca Cordoba C\u00f3rdoba 14420",
    "addr:postcode":"14420",
    "addr:street":"Grup Soledad La S / N",
    "iso:country":"ES",
    "sg:address":"Grup Soledad (la), S/n",
    "sg:city":"Villafranca Cordoba",
    "sg:orig_category":"Ense\u00d1anza, Formaci\u00d3n Profesional: Aprendizaje",
    "sg:phone":"+34 957 19 12 18",
    "sg:postcode":"14420",
    "sg:province":"C\u00f3rdoba",
    "wof:name":"Junta De Andalucia",
    "wof:placetype":"venue"
},
  "geometry": {"coordinates":[-4.7791519165,37.884727478],"type":"Point"}
}