{
  "type": "Feature",
  "properties": {
    "iso:country":"ES",
    "sg:address":"Ctra Mojonera, 5",
    "sg:city":"Norias De Daza",
    "sg:orig_category":"Ferreter\u00cda (diversos)",
    "sg:phone":"+34 950 58 75 08",
    "sg:postcode":"04716",
    "sg:province":"Almer\u00eda",
    "wof:name":"Desguace Baena",
    "wof:placetype":"venue"
},
  "geometry": {"coordinates":[-2.7462189198,36.7576293945],"type":"Point"}
}