{
  "type": "Feature",
  "properties": {
    "iso:country":"ES",
    "sg:address":"Calle de Virgen De La Paz, S/n",
    "sg:city":"Alacant",
    "sg:orig_category":"Empresas De Carpinter\u00cda",
    "sg:phone":"+34 965 17 02 61",
    "sg:postcode":"03009",
    "sg:province":"Alicante",
    "wof:name":"Garcia Jodar Francisco Jose",
    "wof:placetype":"venue"
},
  "geometry": {"coordinates":[-0.4982840121,38.3675231934],"type":"Point"}
}