{
  "type": "Feature",
  "properties": {
    "iso:country":"ES",
    "sg:address":"Plaz Santo Domingo (de), 7",
    "sg:city":"Arevalo",
    "sg:orig_category":"Ingeniero",
    "sg:phone":"+34 920 30 04 46",
    "sg:postcode":"05200",
    "sg:province":"\u00c1vila",
    "wof:name":"Agroquimicos Heriberto S.l.",
    "wof:placetype":"venue"
},
  "geometry": {"coordinates":[-4.7174062729,41.0337677002],"type":"Point"}
}