{
  "type": "Feature",
  "properties": {
    "iso:country":"ES",
    "sg:address":"Pl Rovira I Trias, S/n",
    "sg:city":"Barcelona",
    "sg:orig_category":"Librer\u00cdas",
    "sg:phone":"+34 932 19 34 74",
    "sg:postcode":"08024",
    "sg:province":"Barcelona",
    "wof:name":"Carta\u00f1a Copons Juan",
    "wof:placetype":"venue"
},
  "geometry": {"coordinates":[2.1582999229,41.4077339172],"type":"Point"}
}