{
  "type": "Feature",
  "properties": {
    "iso:country":"ES",
    "sg:address":"Calle de San Antonio Maria Claret, 12",
    "sg:city":"Zaragoza",
    "sg:orig_category":"Mec\u00c1nico Del Autom\u00d3vil",
    "sg:phone":"+34 976 56 66 61",
    "sg:postcode":"50005",
    "sg:province":"Zaragoza",
    "wof:name":"Nuevos Talleres El Carmen S.cv.",
    "wof:placetype":"venue"
},
  "geometry": {"coordinates":[-0.894339025,41.6457901001],"type":"Point"}
}