{
  "type": "Feature",
  "properties": {
    "iso:country":"ES",
    "sg:address":"Avda Europa, 15",
    "sg:city":"Alcala Real",
    "sg:orig_category":"Farmacias",
    "sg:phone":"+34 953 58 04 59",
    "sg:postcode":"23680",
    "sg:province":"Ja\u00e9n",
    "wof:name":"Tutau Gomez Farmaceuticos C.b.",
    "wof:placetype":"venue"
},
  "geometry": {"coordinates":[-3.9199988842,37.4580993652],"type":"Point"}
}