{
  "type": "Feature",
  "properties": {
    "iso:country":"ES",
    "sg:address":"Calle de Pedroches, 20",
    "sg:city":"Leganes",
    "sg:orig_category":"Ropa Para Se\u00d1oras Y Caballeros (al Por Menor)",
    "sg:phone":"+34 916 88 69 46",
    "sg:postcode":"28915",
    "sg:province":"Madrid",
    "wof:name":"Orme\u00f1o Maestro Monica",
    "wof:placetype":"venue"
},
  "geometry": {"coordinates":[-3.75426507,40.3358688354],"type":"Point"}
}