{
  "type": "Feature",
  "properties": {
    "addr:full":"Calle de Saenz Diez, 45 Ourense Ourense 32003",
    "addr:housenumber":"45",
    "addr:postcode":"32003",
    "addr:street":"Calle De Saenz Diez",
    "iso:country":"ES",
    "sg:address":"Calle de Saenz Diez, 45",
    "sg:city":"Ourense",
    "sg:orig_category":"Cl\u00cdnicas Dentales",
    "sg:phone":"+34 988 37 17 59",
    "sg:postcode":"32003",
    "sg:province":"Ourense",
    "wof:name":"Nogueira Enciso Julio Alfonso",
    "wof:placetype":"venue"
},
  "geometry": {"coordinates":[-7.8640241623,42.3439331055],"type":"Point"}
}