{
  "type": "Feature",
  "properties": {
    "addr:full":"Carrer de Ausias March, 7 S. Pere Ribes Barcelona 08810",
    "addr:housenumber":"7",
    "addr:postcode":"08810",
    "addr:street":"Carrer De Ausias March;S. Pere Ribes Barcelona",
    "iso:country":"ES",
    "sg:address":"Carrer de Ausias March, 7",
    "sg:city":"S. Pere Ribes",
    "sg:orig_category":"Agencias Y Asesores De Publicidad",
    "sg:phone":"+34 938 96 30 76",
    "sg:postcode":"08810",
    "sg:province":"Barcelona",
    "sg:website":"www.publi-skay.com",
    "wof:name":"Publiskay S.l.",
    "wof:placetype":"venue"
},
  "geometry": {"coordinates":[1.7753219604,41.2560043335],"type":"Point"}
}