{
  "type": "Feature",
  "properties": {
    "iso:country":"ES",
    "sg:address":"Calle de Cristo, 4",
    "sg:city":"Consuegra",
    "sg:classifiers":[
        {
            "category":"Casinos & Gambling",
            "type":"Entertainment"
        }
    ],
    "sg:phone":"+34 925 48 08 29",
    "sg:postcode":"45700",
    "sg:province":"Toledo",
    "sg:tags":[
        "locale",
        "de",
        "juego"
    ],
    "wof:name":"Casino De La Union",
    "wof:placetype":"venue"
},
  "geometry": {"coordinates":[-3.6070156097,39.4596862793],"type":"Point"}
}