{
  "type": "Feature",
  "properties": {
    "addr:full":"Carrer de Industria, 251 Barcelona Barcelona 08041",
    "addr:housenumber":"251",
    "addr:postcode":"08041",
    "addr:street":"Carrer De Industria",
    "iso:country":"ES",
    "sg:address":"Carrer de Industria, 251",
    "sg:city":"Barcelona",
    "sg:orig_category":"Cajas De Ahorro",
    "sg:phone":"+34 934 36 67 14",
    "sg:postcode":"08041",
    "sg:province":"Barcelona",
    "wof:name":"Caixa D'estalvis De Catalunya",
    "wof:placetype":"venue"
},
  "geometry": {"coordinates":[2.1788060665,41.4131546021],"type":"Point"}
}