{
  "type": "Feature",
  "properties": {
    "addr:full":"Avda Catalu\u00d1a, 36 Zaragoza Zaragoza 50014",
    "addr:housenumber":"36",
    "addr:postcode":"50014",
    "addr:street":"Avda Catalun\u0303A",
    "iso:country":"ES",
    "sg:address":"Avda Catalu\u00d1a, 36",
    "sg:city":"Zaragoza",
    "sg:orig_category":"Maquinaria Para Industrias Diversas",
    "sg:phone":"+34 976 20 32 74",
    "sg:postcode":"50014",
    "sg:province":"Zaragoza",
    "sg:website":"www.lepantozaragoza.com",
    "wof:name":"Productos Ruiz Alfaro S.l.",
    "wof:placetype":"venue"
},
  "geometry": {"coordinates":[-0.8695340157,41.6600189209],"type":"Point"}
}