{
  "type": "Feature",
  "properties": {
    "iso:country":"ES",
    "sg:address":"Luga Pereiro De Alen, S/n",
    "sg:city":"Pereiro De Aguiar",
    "sg:orig_category":"Promotores Constructores",
    "sg:phone":"+34 988 25 96 24",
    "sg:postcode":"32710",
    "sg:province":"Ourense",
    "wof:name":"Quintela Garcia Gerardo",
    "wof:placetype":"venue"
},
  "geometry": {"coordinates":[-7.7998161316,42.3454399109],"type":"Point"}
}