{
  "type": "Feature",
  "properties": {
    "addr:full":"Ctra Espinar, S/n Estacion De El Espinar Segovia 40400",
    "addr:postcode":"40400",
    "addr:street":"Ctra Espinar S / N Estacion De El;Segovia",
    "iso:country":"ES",
    "sg:address":"Ctra Espinar, S/n",
    "sg:city":"Estacion De El Espinar",
    "sg:orig_category":"Asociaciones, Organismos Culturales Y Socioeducativos",
    "sg:phone":"+34 921 18 82 67",
    "sg:postcode":"40400",
    "sg:province":"Segovia",
    "wof:name":"Asociacion Familiar San Antonio",
    "wof:placetype":"venue"
},
  "geometry": {"coordinates":[-4.1930236816,40.7409172058],"type":"Point"}
}