{
  "type": "Feature",
  "properties": {
    "addr:full":"Calle de San Pedro (de), 3 Albares Guadalajara 19112",
    "addr:postcode":"19112",
    "addr:street":"Calle De San",
    "iso:country":"ES",
    "sg:address":"Calle de San Pedro (de), 3",
    "sg:city":"Albares",
    "sg:orig_category":"Cajas Para Embalar",
    "sg:phone":"+34 949 38 05 75",
    "sg:postcode":"19112",
    "sg:province":"Guadalajara",
    "wof:name":"Caja Rural Provincial De Toledo",
    "wof:placetype":"venue"
},
  "geometry": {"coordinates":[-3.0108649731,40.307849884],"type":"Point"}
}