{
  "type": "Feature",
  "properties": {
    "iso:country":"ES",
    "sg:address":"Pg Enric Sanchis, S/n",
    "sg:city":"Barcelona",
    "sg:orig_category":"Iglesia Cat\u00d3lica",
    "sg:phone":"+34 933 13 58 89",
    "sg:postcode":"08030",
    "sg:province":"Barcelona",
    "wof:name":"Parroquia Del Buen Pastor",
    "wof:placetype":"venue"
},
  "geometry": {"coordinates":[2.2056899071,41.4344100952],"type":"Point"}
}