{
  "type": "Feature",
  "properties": {
    "iso:country":"ES",
    "sg:address":"Avda Trueba, 42",
    "sg:city":"Madrid",
    "sg:classifiers":[
        {
            "category":"Taxi",
            "type":"Transportation"
        }
    ],
    "sg:phone":"+34 913 67 41 51",
    "sg:postcode":"28017",
    "sg:province":"Madrid",
    "wof:name":"Rosero Medina Edison Arturo",
    "wof:placetype":"venue"
},
  "geometry": {"coordinates":[-3.6446108818,40.4285087585],"type":"Point"}
}