{
  "type": "Feature",
  "properties": {
    "iso:country":"ES",
    "sg:address":"Av Paral.lel, 131",
    "sg:city":"Barcelona",
    "sg:orig_category":"Farmacias",
    "sg:phone":"+34 932 89 21 90",
    "sg:postcode":"08004",
    "sg:province":"Barcelona",
    "wof:name":"Iglesias Huix Francesca",
    "wof:placetype":"venue"
},
  "geometry": {"coordinates":[2.158880949,41.3749389648],"type":"Point"}
}