{
  "type": "Feature",
  "properties": {
    "iso:country":"ES",
    "sg:address":"Calle de Octavio Cuartero, 23",
    "sg:city":"Albacete",
    "sg:orig_category":"Institutos De Belleza",
    "sg:phone":"+34 967 51 13 61",
    "sg:postcode":"02003",
    "sg:province":"Albacete",
    "wof:name":"Fernandez Garcia Milagros",
    "wof:placetype":"venue"
},
  "geometry": {"coordinates":[-1.8588010073,38.9910202026],"type":"Point"}
}