{
  "type": "Feature",
  "properties": {
    "iso:country":"ES",
    "sg:address":"Calle de Rio Salazar, 9",
    "sg:city":"Torremolinos",
    "sg:orig_category":"Empresas De Carpinter\u00cda De Madera",
    "sg:phone":"+34 952 05 18 76",
    "sg:postcode":"29620",
    "sg:province":"M\u00e1laga",
    "wof:name":"Rodriguez Lopez Diego",
    "wof:placetype":"venue"
},
  "geometry": {"coordinates":[-4.5015392303,36.6249389648],"type":"Point"}
}