{
  "type": "Feature",
  "properties": {
    "addr:full":"Calle de Reyes Catolicos, 14 Alcala Guadaira Sevilla 41500",
    "addr:housenumber":"14",
    "addr:postcode":"41500",
    "addr:street":"Calle De Reyes Catolicos",
    "iso:country":"ES",
    "sg:address":"Calle de Reyes Catolicos, 14",
    "sg:city":"Alcala Guadaira",
    "sg:orig_category":"Abogados",
    "sg:phone":"+34 955 68 60 01",
    "sg:postcode":"41500",
    "sg:province":"Sevilla",
    "wof:name":"Gabinete Juridico Campo De Beatas Scv",
    "wof:placetype":"venue"
},
  "geometry": {"coordinates":[-5.8533678055,37.3282470703],"type":"Point"}
}