{
  "type": "Feature",
  "properties": {
    "addr:full":"Calle de Pozo Nuevo, 20 Moron Frontera Sevilla 41530",
    "addr:housenumber":"20",
    "addr:postcode":"41530",
    "addr:street":"Calle De Pozo Nuevo",
    "iso:country":"ES",
    "sg:address":"Calle de Pozo Nuevo, 20",
    "sg:city":"Moron Frontera",
    "sg:orig_category":"Ense\u00d1anza: Profesiones Art\u00cdsticas",
    "sg:phone":"+34 955 85 03 27",
    "sg:postcode":"41530",
    "sg:province":"Sevilla",
    "wof:name":"Gomez Gonzalez Luis Alfredo",
    "wof:placetype":"venue"
},
  "geometry": {"coordinates":[-5.452600956,37.12159729],"type":"Point"}
}