{
  "type": "Feature",
  "properties": {
    "iso:country":"ES",
    "sg:address":"Escultor Ferreiro, 34",
    "sg:city":"Noia",
    "sg:orig_category":"Quincaller\u00cda (al Por Menor)",
    "sg:phone":"+34 981 82 01 15",
    "sg:postcode":"15200",
    "sg:province":"A Coru\u00f1a",
    "wof:name":"Seoane Gomez Antonio",
    "wof:placetype":"venue"
},
  "geometry": {"coordinates":[-8.8865699768,42.7837524414],"type":"Point"}
}