{
  "type": "Feature",
  "properties": {
    "addr:full":"Carr Felix De Los Rios, 38 Almenar Lleida 25126",
    "addr:housenumber":"38",
    "addr:postcode":"25126",
    "addr:street":"Carr Felix De Los Rios",
    "iso:country":"ES",
    "sg:address":"Carr Felix De Los Rios, 38",
    "sg:city":"Almenar",
    "sg:orig_category":"Empresarios",
    "sg:phone":"+34 973 77 04 69",
    "sg:postcode":"25126",
    "sg:province":"Lleida",
    "wof:name":"Farrus Oromi Juan",
    "wof:placetype":"venue"
},
  "geometry": {"coordinates":[0.5659199953,41.7966346741],"type":"Point"}
}