{
  "type": "Feature",
  "properties": {
    "addr:full":"Avda Ausias March, 53 Valencia Valencia 46013",
    "addr:housenumber":"53",
    "addr:postcode":"46013",
    "addr:street":"Avda Ausias March",
    "iso:country":"ES",
    "sg:address":"Avda Ausias March, 53",
    "sg:city":"Valencia",
    "sg:orig_category":"Comercio De Piezas De Recambio Y De Accesorios De Veh\u00cdculos, Veh\u00cdculos Industriales",
    "sg:phone":"+34 963 95 34 92",
    "sg:postcode":"46013",
    "sg:province":"Valencia",
    "wof:name":"Recambios Heras S.cv.",
    "wof:placetype":"venue"
},
  "geometry": {"coordinates":[-0.3715150058,39.4509811401],"type":"Point"}
}