{
  "type": "Feature",
  "properties": {
    "iso:country":"ES",
    "sg:address":"Plaz Cruz Latina, 33",
    "sg:city":"Madrid",
    "sg:orig_category":"Farmacias",
    "sg:phone":"+34 917 67 25 28",
    "sg:postcode":"28033",
    "sg:province":"Madrid",
    "wof:name":"Martinez Abreira Jesus",
    "wof:placetype":"venue"
},
  "geometry": {"coordinates":[-3.6597800255,40.4752120972],"type":"Point"}
}