{
  "type": "Feature",
  "properties": {
    "iso:country":"ES",
    "sg:address":"Carrer de Consell De Cent, 362",
    "sg:city":"Barcelona",
    "sg:orig_category":"Oficinas: Suministros Para (fabricaci\u00d3n, Al Por Mayor)",
    "sg:phone":"+34 934 87 77 00",
    "sg:postcode":"08009",
    "sg:province":"Barcelona",
    "wof:name":"Papereries Paraules S.l.",
    "wof:placetype":"venue"
},
  "geometry": {"coordinates":[2.1702771187,41.3943557739],"type":"Point"}
}