{
  "type": "Feature",
  "properties": {
    "iso:country":"ES",
    "sg:address":"Carrer de Sant Blai (de), 21",
    "sg:city":"Tortosa",
    "sg:orig_category":"Peluquer\u00cdas",
    "sg:phone":"+34 977 44 00 01",
    "sg:postcode":"43500",
    "sg:province":"Tarragona",
    "wof:name":"Colome Diaz Maria Luz",
    "wof:placetype":"venue"
},
  "geometry": {"coordinates":[0.5217949748,40.8109817505],"type":"Point"}
}