{
  "type": "Feature",
  "properties": {
    "addr:full":"Forja, 1 Puerto Sagunto Valencia 46520",
    "addr:housenumber":"1",
    "addr:postcode":"46520",
    "addr:street":"Forja",
    "iso:country":"ES",
    "sg:address":"Forja, 1",
    "sg:city":"Puerto Sagunto",
    "sg:orig_category":"Aguas (distribuci\u00d3n, Servicios)",
    "sg:phone":"+34 962 69 80 05",
    "sg:postcode":"46520",
    "sg:province":"Valencia",
    "sg:website":"www.aguadecortes.com",
    "wof:name":"Aguas De Cortes S.a.",
    "wof:placetype":"venue"
},
  "geometry": {"coordinates":[-0.2782787979,39.6801376343],"type":"Point"}
}