{
  "type": "Feature",
  "properties": {
    "iso:country":"ES",
    "sg:address":"Pg Maragall, 66",
    "sg:city":"Barcelona",
    "sg:orig_category":"Peluqueros: De Se\u00d1oras",
    "sg:phone":"+34 934 36 61 90",
    "sg:postcode":"08041",
    "sg:province":"Barcelona",
    "wof:name":"Roca Baro Mercedes",
    "wof:placetype":"venue"
},
  "geometry": {"coordinates":[2.1804890633,41.4172821045],"type":"Point"}
}