{
  "type": "Feature",
  "properties": {
    "iso:country":"ES",
    "sg:address":"Carr Gracia, 62",
    "sg:city":"Escala",
    "sg:orig_category":"Poli\u00c9ster",
    "sg:phone":"+34 972 77 13 58",
    "sg:postcode":"17130",
    "sg:province":"Girona",
    "wof:name":"Fibra Girona S.l.",
    "wof:placetype":"venue"
},
  "geometry": {"coordinates":[3.1321649551,42.1229934692],"type":"Point"}
}