{
  "type": "Feature",
  "properties": {
    "iso:country":"ES",
    "sg:address":"Calle de Cadenas De San Gregorio, 6",
    "sg:city":"Valladolid",
    "sg:orig_category":"Clubes Y Asociaciones Deportivas Y De Actividades Invernales Y De Monta\u00d1a",
    "sg:phone":"+34 983 25 62 22",
    "sg:postcode":"47011",
    "sg:province":"Valladolid",
    "wof:name":"Federacion Territorial De Atletismo De Castilla Leon",
    "wof:placetype":"venue"
},
  "geometry": {"coordinates":[-4.7234535217,41.6571578979],"type":"Point"}
}