{
  "type": "Feature",
  "properties": {
    "iso:country":"ES",
    "sg:address":"Ovi\u00f1ana, S/n",
    "sg:city":"Ovi\u00f1ana",
    "sg:orig_category":"Crust\u00c1ceos Y Almejas (al Por Mayor)",
    "sg:phone":"+34 985 59 60 95",
    "sg:postcode":"33156",
    "sg:province":"Asturias",
    "wof:name":"El Cuadrante C.b.",
    "wof:placetype":"venue"
},
  "geometry": {"coordinates":[-6.2376999855,43.5530014038],"type":"Point"}
}