{
  "type": "Feature",
  "properties": {
    "addr:full":"Calle de Lomo De La Viuda, 62 Tenoya Las Palmas 35018",
    "addr:housenumber":"62",
    "addr:postcode":"35018",
    "addr:street":"Calle De Lomo De La Viuda;Las Palmas",
    "iso:country":"ES",
    "sg:address":"Calle de Lomo De La Viuda, 62",
    "sg:city":"Tenoya",
    "sg:orig_category":"Bazares, Art\u00cdculos De Limpieza Y De Cocina (al Por Menor)",
    "sg:phone":"+34 928 67 48 66",
    "sg:postcode":"35018",
    "sg:province":"Las Palmas",
    "wof:name":"Trujillo Trujillo Juan",
    "wof:placetype":"venue"
},
  "geometry": {"coordinates":[-15.4950475693,28.1110363007],"type":"Point"}
}