{
  "type": "Feature",
  "properties": {
    "addr:full":"Ptor A. Povedano, S/n El Ca\u00f1uelo C\u00f3rdoba 14815",
    "addr:housenumber":"s / n",
    "addr:postcode":"14815",
    "addr:street":"Co\u0301Rdoba",
    "iso:country":"ES",
    "sg:address":"Ptor A. Povedano, S/n",
    "sg:city":"El Ca\u00f1uelo",
    "sg:orig_category":"Aceites Y Grasas Alimentarias (fabricaci\u00d3n, Al Por Mayor)",
    "sg:phone":"+34 957 70 50 01",
    "sg:postcode":"14815",
    "sg:province":"C\u00f3rdoba",
    "wof:name":"S.c.a. Agraria Ntra. Sra. De La Cabeza",
    "wof:placetype":"venue"
},
  "geometry": {"coordinates":[-4.1620240211,37.5083198547],"type":"Point"}
}