{
  "type": "Feature",
  "properties": {
    "addr:full":"La Ermita, S/n Virgen Camino Le\u00f3n 24198",
    "addr:postcode":"24198",
    "addr:street":"S / N Virgen Camino Leo\u0301N",
    "iso:country":"ES",
    "sg:address":"La Ermita, S/n",
    "sg:city":"Virgen Camino",
    "sg:orig_category":"Alquiler De Veh\u00cdculos: Turismos Y Utilitarios",
    "sg:phone":"+34 987 30 00 89",
    "sg:postcode":"24198",
    "sg:province":"Le\u00f3n",
    "wof:name":"Europcar Ib. S.a",
    "wof:placetype":"venue"
},
  "geometry": {"coordinates":[-5.6438441277,42.5845489502],"type":"Point"}
}