{
  "type": "Feature",
  "properties": {
    "iso:country":"ES",
    "sg:address":"Rua Ronda Don Bosco, 41",
    "sg:city":"Vigo",
    "sg:orig_category":"Oficinas: Suministros Para (fabricaci\u00d3n, Al Por Mayor)",
    "sg:phone":"+34 986 22 77 71",
    "sg:postcode":"36202",
    "sg:province":"Pontevedra",
    "wof:name":"Soto Alvarez Jose Antonio",
    "wof:placetype":"venue"
},
  "geometry": {"coordinates":[-8.7225008011,42.235168457],"type":"Point"}
}