{
  "type": "Feature",
  "properties": {
    "addr:full":"Ctra. General, S/n S. Roque Acebal Asturias 33596",
    "addr:postcode":"33596",
    "addr:street":"Ctra. General S / N S. Roque Acebal Asturias",
    "iso:country":"ES",
    "sg:address":"Ctra. General, S/n",
    "sg:city":"S. Roque Acebal",
    "sg:orig_category":"Venta, Instalaci\u00d3n De Calefacci\u00d3n",
    "sg:phone":"+34 985 41 74 63",
    "sg:postcode":"33596",
    "sg:province":"Asturias",
    "wof:name":"Instalaciones Martinez Sobrino",
    "wof:placetype":"venue"
},
  "geometry": {"coordinates":[-4.7163219452,43.4069786072],"type":"Point"}
}