{
  "type": "Feature",
  "properties": {
    "iso:country":"ES",
    "sg:address":"Calle de Nuestra Se\u00d1ora De Fatima, 5",
    "sg:city":"Burgos",
    "sg:orig_category":"Inform\u00c1tica: Material Y Suministros",
    "sg:phone":"+34 947 23 78 00",
    "sg:postcode":"09007",
    "sg:province":"Burgos",
    "wof:name":"Sistelbur S.l.",
    "wof:placetype":"venue"
},
  "geometry": {"coordinates":[-3.67522192,42.3510627747],"type":"Point"}
}