{
  "type": "Feature",
  "properties": {
    "addr:full":"Avda Santiago Galas, 5 Cabez\u00f3n Sal Cantabria 39500",
    "addr:housenumber":"5",
    "addr:postcode":"39500",
    "addr:street":"Avda Santiago Galas",
    "iso:country":"ES",
    "sg:address":"Avda Santiago Galas, 5",
    "sg:city":"Cabez\u00f3n Sal",
    "sg:orig_category":"Venta, Instalaci\u00d3n De Calefacci\u00d3n",
    "sg:phone":"+34 942 70 26 59",
    "sg:postcode":"39500",
    "sg:province":"Cantabria",
    "wof:name":"Electricidad Pajarin S.l.",
    "wof:placetype":"venue"
},
  "geometry": {"coordinates":[-4.2338829041,43.3083686829],"type":"Point"}
}