{
  "type": "Feature",
  "properties": {
    "iso:country":"ES",
    "sg:address":"Av Tres-cents U, 15",
    "sg:city":"Castelldefels",
    "sg:orig_category":"Clases De M\u00dasica Y Canto",
    "sg:phone":"+34 936 65 48 55",
    "sg:postcode":"08860",
    "sg:province":"Barcelona",
    "wof:name":"Vidal Samso Enrique",
    "wof:placetype":"venue"
},
  "geometry": {"coordinates":[1.9784450531,41.2793083191],"type":"Point"}
}