{
  "type": "Feature",
  "properties": {
    "iso:country":"ES",
    "sg:address":"Plaz Doctor Alvarez, S/n",
    "sg:city":"Almu\u00f1ecar",
    "sg:orig_category":"Delegados, Agentes De Tr\u00c1nsito, Auxiliares De Transporte Internacional",
    "sg:phone":"+34 958 88 03 17",
    "sg:postcode":"18690",
    "sg:province":"Granada",
    "wof:name":"Cecilia Martin Francisco",
    "wof:placetype":"venue"
},
  "geometry": {"coordinates":[-3.6916339397,36.736038208],"type":"Point"}
}