{
  "type": "Feature",
  "properties": {
    "iso:country":"ES",
    "sg:address":"Avda Reyes Catolicos, 33",
    "sg:city":"Burgos",
    "sg:orig_category":"Librer\u00cdas",
    "sg:phone":"+34 947 23 54 61",
    "sg:postcode":"09005",
    "sg:province":"Burgos",
    "wof:name":"Quintanilla Franco Santos",
    "wof:placetype":"venue"
},
  "geometry": {"coordinates":[-3.6946730614,42.3472328186],"type":"Point"}
}