{
  "type": "Feature",
  "properties": {
    "addr:full":"Av Sant Josep De Calassan\u00c7, 10 Casc Urba Barcelona 08328",
    "addr:housenumber":"10",
    "addr:postcode":"08328",
    "addr:street":"Av Sant Josep De Calassanc\u0327;Casc Urba",
    "iso:country":"ES",
    "sg:address":"Av Sant Josep De Calassan\u00c7, 10",
    "sg:city":"Casc Urba",
    "sg:orig_category":"Restaurantes Para Recepciones, Banquetes, Conferencias",
    "sg:phone":"+34 935 55 58 01",
    "sg:postcode":"08328",
    "sg:province":"Barcelona",
    "wof:name":"Colomer Valero S.l.",
    "wof:placetype":"venue"
},
  "geometry": {"coordinates":[2.2946848869,41.4925308228],"type":"Point"}
}