{
  "type": "Feature",
  "properties": {
    "addr:full":"Via Roma, 13 Salou Tarragona 43840",
    "addr:housenumber":"13",
    "addr:postcode":"43840",
    "addr:street":"Via Roma",
    "iso:country":"ES",
    "sg:address":"Via Roma, 13",
    "sg:city":"Salou",
    "sg:orig_category":"Bisuter\u00cda, Joyer\u00cda, Relojer\u00cda (al Por Menor)",
    "sg:phone":"+34 977 35 28 34",
    "sg:postcode":"43840",
    "sg:province":"Tarragona",
    "wof:name":"Marti Perez Monica",
    "wof:placetype":"venue"
},
  "geometry": {"coordinates":[1.1685880423,41.0659332275],"type":"Point"}
}