{
  "type": "Feature",
  "properties": {
    "iso:country":"ES",
    "sg:address":"Calle de Menendez Pelayo, 14",
    "sg:city":"Palencia",
    "sg:orig_category":"Perfumer\u00cda (al Por Menor)",
    "sg:phone":"+34 979 74 68 01",
    "sg:postcode":"34001",
    "sg:province":"Palencia",
    "wof:name":"Natalio De Fuentes S. A.",
    "wof:placetype":"venue"
},
  "geometry": {"coordinates":[-4.5344309807,42.0109176636],"type":"Point"}
}