{
  "type": "Feature",
  "properties": {
    "iso:country":"ES",
    "sg:address":"Avda Levante (de), 7",
    "sg:city":"Rivas Vaciamadrid",
    "sg:orig_category":"Peluqueros: De Se\u00d1oras",
    "sg:phone":"+34 916 70 36 53",
    "sg:postcode":"28529",
    "sg:province":"Madrid",
    "sg:website":"www.ana-bravo.com",
    "wof:name":"Paris-madrid Peluqueros S.l.",
    "wof:placetype":"venue"
},
  "geometry": {"coordinates":[-3.5099890232,40.3250198364],"type":"Point"}
}