{
  "type": "Feature",
  "properties": {
    "addr:full":"Calle de Diez Calixto, 2 Bilbao Vizcaya 48012",
    "addr:housenumber":"2",
    "addr:postcode":"48012",
    "addr:street":"Calle De Diez Calixto",
    "iso:country":"ES",
    "sg:address":"Calle de Diez Calixto, 2",
    "sg:city":"Bilbao",
    "sg:orig_category":"Fabricaci\u00d3n, Instalaci\u00d3n Y Reparaci\u00d3n De Bombas",
    "sg:phone":"+34 944 10 54 58",
    "sg:postcode":"48012",
    "sg:province":"Vizcaya",
    "wof:name":"Gordoniz Tecnica S.l.",
    "wof:placetype":"venue"
},
  "geometry": {"coordinates":[-2.9416294098,43.2566490173],"type":"Point"}
}