{
  "type": "Feature",
  "properties": {
    "iso:country":"ES",
    "sg:address":"Calle de Blanco, 44",
    "sg:city":"Puerto Cruz",
    "sg:orig_category":"Ingeniero",
    "sg:phone":"+34 922 38 37 06",
    "sg:postcode":"38400",
    "sg:province":"Santa Cruz De Tenerife",
    "wof:name":"Oramas Rosado Batolome Sergio",
    "wof:placetype":"venue"
},
  "geometry": {"coordinates":[-16.5509109497,28.412612915],"type":"Point"}
}