{
  "type": "Feature",
  "properties": {
    "iso:country":"ES",
    "sg:address":"Carrer de Pous, S/n",
    "sg:city":"S. Andreu Barca",
    "sg:orig_category":"Rectificaci\u00d3n, Mecanizado, Fresado",
    "sg:phone":"+34 936 82 04 14",
    "sg:postcode":"08740",
    "sg:province":"Barcelona",
    "wof:name":"Mecaferma S.l.",
    "wof:placetype":"venue"
},
  "geometry": {"coordinates":[1.9729809761,41.4531173706],"type":"Point"}
}