{
  "type": "Feature",
  "properties": {
    "iso:country":"ES",
    "sg:address":"Carrer de Enric Prat De La Riba, 267",
    "sg:city":"Hospitalet Llobregat",
    "sg:orig_category":"Peluqueros: De Se\u00d1oras",
    "sg:phone":"+34 933 38 86 57",
    "sg:postcode":"08901",
    "sg:province":"Barcelona",
    "wof:name":"Holgado Martinez Ana",
    "wof:placetype":"venue"
},
  "geometry": {"coordinates":[2.1044120789,41.3604431152],"type":"Point"}
}