{
  "type": "Feature",
  "properties": {
    "addr:full":"Carrer de Major, 92 S. Just Desvern Barcelona 08960",
    "addr:housenumber":"92",
    "addr:postcode":"08960",
    "addr:street":"Carrer De Major",
    "iso:country":"ES",
    "sg:address":"Carrer de Major, 92",
    "sg:city":"S. Just Desvern",
    "sg:orig_category":"Molduras, Junquillos, Listones Y Molduras Perforadas",
    "sg:phone":"+34 933 71 10 89",
    "sg:postcode":"08960",
    "sg:province":"Barcelona",
    "wof:name":"Lozano Loizaga Juan Manuel",
    "wof:placetype":"venue"
},
  "geometry": {"coordinates":[2.070964098,41.3796730042],"type":"Point"}
}