{
  "type": "Feature",
  "properties": {
    "addr:full":"Pau Casals, 6 El Morell Tarragona 43760",
    "addr:housenumber":"6",
    "addr:postcode":"43760",
    "addr:street":"Casals;El Morell",
    "iso:country":"ES",
    "sg:address":"Pau Casals, 6",
    "sg:city":"El Morell",
    "sg:orig_category":"Fabricaci\u00d3n, Venta De Cuadros, Accesorios Para Enmarcar",
    "sg:phone":"+34 977 84 07 58",
    "sg:postcode":"43760",
    "sg:province":"Tarragona",
    "wof:name":"Brido, Scp",
    "wof:placetype":"venue"
},
  "geometry": {"coordinates":[1.207859993,41.1918869019],"type":"Point"}
}