{
  "type": "Feature",
  "properties": {
    "iso:country":"ES",
    "sg:address":"Calle de San Bernardo, 81",
    "sg:city":"Madrid",
    "sg:orig_category":"Asesor\u00cda Fiscal Y Jur\u00cddica",
    "sg:phone":"+34 914 45 64 63",
    "sg:postcode":"28015",
    "sg:province":"Madrid",
    "wof:name":"Asesores De Impuestos S. A.",
    "wof:placetype":"venue"
},
  "geometry": {"coordinates":[-3.7063024044,40.4279136658],"type":"Point"}
}