{
  "type": "Feature",
  "properties": {
    "addr:full":"Avda Rufo G Rendueles, 1 Gijon Asturias 33203",
    "addr:housenumber":"1",
    "addr:postcode":"33203",
    "addr:street":"Avda Rufo G Rendueles",
    "iso:country":"ES",
    "sg:address":"Avda Rufo G Rendueles, 1",
    "sg:city":"Gijon",
    "sg:orig_category":"Caf\u00c9s, Bares, Cervecer\u00cdas",
    "sg:phone":"+34 985 36 45 64",
    "sg:postcode":"33203",
    "sg:province":"Asturias",
    "wof:name":"Llaneza Coto Maria Jesus",
    "wof:placetype":"venue"
},
  "geometry": {"coordinates":[-5.6485538483,43.5405082703],"type":"Point"}
}