{
  "type": "Feature",
  "properties": {
    "addr:full":"Calle de Doctor Mora Sanz, S/n Mislata Valencia 46920",
    "addr:housenumber":"s / n",
    "addr:postcode":"46920",
    "addr:street":"Calle De Doctor Mora Sanz",
    "iso:country":"ES",
    "sg:address":"Calle de Doctor Mora Sanz, S/n",
    "sg:city":"Mislata",
    "sg:orig_category":"Fabricaci\u00d3n De Instrumentos Y Accesorios Musicales",
    "sg:phone":"+34 963 79 37 51",
    "sg:postcode":"46920",
    "sg:province":"Valencia",
    "sg:website":"www.musicson.com",
    "wof:name":"Music-son S. L.",
    "wof:placetype":"venue"
},
  "geometry": {"coordinates":[-0.4290902913,39.4731864929],"type":"Point"}
}