{
  "type": "Feature",
  "properties": {
    "addr:full":"Calle de Conde Vallellano, S/n Carrizo Ribera Le\u00f3n 24270",
    "addr:housenumber":"s / n",
    "addr:postcode":"24270",
    "addr:street":"Calle De Conde Vallellano;Carrizo Ribera Leo\u0301N",
    "iso:country":"ES",
    "sg:address":"Calle de Conde Vallellano, S/n",
    "sg:city":"Carrizo Ribera",
    "sg:orig_category":"Electricidad: Instaladores",
    "sg:phone":"+34 987 35 71 63",
    "sg:postcode":"24270",
    "sg:province":"Le\u00f3n",
    "wof:name":"Rivero Anta Pedro",
    "wof:placetype":"venue"
},
  "geometry": {"coordinates":[-5.8323221207,42.5855522156],"type":"Point"}
}