{
  "type": "Feature",
  "properties": {
    "addr:full":"Cril Guerreros(s Y Zaraiche), 17 Murcia Murcia 30007",
    "addr:housenumber":"17",
    "addr:postcode":"30007",
    "iso:country":"ES",
    "sg:address":"Cril Guerreros(s Y Zaraiche), 17",
    "sg:city":"Murcia",
    "sg:orig_category":"Agencias Y Agentes Comerciales, Representantes",
    "sg:phone":"+34 968 23 48 20",
    "sg:postcode":"30007",
    "sg:province":"Murcia",
    "wof:name":"Laboratorios Normon S.a.",
    "wof:placetype":"venue"
},
  "geometry": {"coordinates":[-1.1230529547,37.9995918274],"type":"Point"}
}