{
  "type": "Feature",
  "properties": {
    "addr:full":"Ptge Col.legis, 3 Viladecans Barcelona 08840",
    "addr:housenumber":"3",
    "addr:postcode":"08840",
    "addr:street":"Ptge Col.Legis",
    "iso:country":"ES",
    "sg:address":"Ptge Col.legis, 3",
    "sg:city":"Viladecans",
    "sg:orig_category":"Plomeros",
    "sg:phone":"+34 936 58 17 86",
    "sg:postcode":"08840",
    "sg:province":"Barcelona",
    "wof:name":"Alarcon Gimenez Jose",
    "wof:placetype":"venue"
},
  "geometry": {"coordinates":[2.016690731,41.320224762],"type":"Point"}
}