{
  "type": "Feature",
  "properties": {
    "addr:full":"Carrer de Rafael Casanova, 67 Viladecans Barcelona 08840",
    "addr:housenumber":"67",
    "addr:postcode":"08840",
    "addr:street":"Carrer De Rafael Casanova",
    "iso:country":"ES",
    "sg:address":"Carrer de Rafael Casanova, 67",
    "sg:city":"Viladecans",
    "sg:orig_category":"Geolog\u00cda Y Geof\u00cdsica",
    "sg:phone":"+34 936 47 52 07",
    "sg:postcode":"08840",
    "sg:province":"Barcelona",
    "sg:website":"www.paginasamarillas.es",
    "wof:name":"Romera Flores Jose",
    "wof:placetype":"venue"
},
  "geometry": {"coordinates":[2.0262749195,41.3187828064],"type":"Point"}
}