{
  "type": "Feature",
  "properties": {
    "iso:country":"ES",
    "sg:address":"Calle de Delicias, 2",
    "sg:city":"S. Mateo Gallego",
    "sg:orig_category":"Peluquer\u00cdas, Peluquer\u00cda Mixta",
    "sg:phone":"+34 976 68 46 30",
    "sg:postcode":"50840",
    "sg:province":"Zaragoza",
    "wof:name":"Vicente Gonzalez Maria Jesus",
    "wof:placetype":"venue"
},
  "geometry": {"coordinates":[-0.7692090273,41.8344688416],"type":"Point"}
}