{
  "type": "Feature",
  "properties": {
    "addr:full":"Avda Estacion, 4 Requena Valencia 46340",
    "addr:housenumber":"4",
    "addr:postcode":"46340",
    "addr:street":"Avda Estacion",
    "iso:country":"ES",
    "sg:address":"Avda Estacion, 4",
    "sg:city":"Requena",
    "sg:orig_category":"Promotores Constructores",
    "sg:phone":"+34 962 30 44 23",
    "sg:postcode":"46340",
    "sg:province":"Valencia",
    "wof:name":"Promociones Av.valencia S.l.",
    "wof:placetype":"venue"
},
  "geometry": {"coordinates":[-1.1046409607,39.490032196],"type":"Point"}
}