{
  "type": "Feature",
  "properties": {
    "iso:country":"ES",
    "sg:address":"Ctra Alcoy-valencia, Km. 0797,0",
    "sg:city":"Cocentaina",
    "sg:orig_category":"Veh\u00cdculos De Ocasi\u00d3n",
    "sg:phone":"+34 965 59 22 66",
    "sg:postcode":"03820",
    "sg:province":"Alicante",
    "wof:name":"Automoviles Gomis S.a.",
    "wof:placetype":"venue"
},
  "geometry": {"coordinates":[-0.3934854865,38.7751045227],"type":"Point"}
}