{
  "type": "Feature",
  "properties": {
    "iso:country":"ES",
    "sg:address":"Manantial Agua, S/n",
    "sg:city":"Cinco Casas",
    "sg:orig_category":"Administraciones Regionales, Departamentales Y Locales",
    "sg:phone":"+34 926 69 91 13",
    "sg:postcode":"13720",
    "sg:province":"Ciudad Real",
    "wof:name":"Aguas Del Alcazar Empresa Municipal S.a.",
    "wof:placetype":"venue"
},
  "geometry": {"coordinates":[-3.2338526249,39.1726951599],"type":"Point"}
}