{
  "type": "Feature",
  "properties": {
    "addr:full":"Avda Paz, 14 Almendralejo Badajoz 06200",
    "addr:housenumber":"14",
    "addr:postcode":"06200",
    "addr:street":"Avda Paz",
    "iso:country":"ES",
    "sg:address":"Avda Paz, 14",
    "sg:city":"Almendralejo",
    "sg:orig_category":"Cl\u00cdnicas Dentales",
    "sg:phone":"+34 924 67 74 45",
    "sg:postcode":"06200",
    "sg:province":"Badajoz",
    "wof:name":"Lopez-navarrete Lopez Jose Maria",
    "wof:placetype":"venue"
},
  "geometry": {"coordinates":[-6.4127140045,38.6833648682],"type":"Point"}
}