{
  "type": "Feature",
  "properties": {
    "iso:country":"ES",
    "sg:address":"Avda Reyes Catolicos, 5",
    "sg:city":"Ceuta",
    "sg:orig_category":"Farmacias",
    "sg:phone":"+34 956 50 56 56",
    "sg:postcode":"51002",
    "sg:province":"Ceuta",
    "wof:name":"Rubia Rubio Manuel De La",
    "wof:placetype":"venue"
},
  "geometry": {"coordinates":[-5.3278570175,35.8833236694],"type":"Point"}
}