{
  "type": "Feature",
  "properties": {
    "addr:full":"Calle de Magallanes, 14 Alfafar Valencia 46910",
    "addr:housenumber":"14",
    "addr:postcode":"46910",
    "addr:street":"Calle De Magallanes",
    "iso:country":"ES",
    "sg:address":"Calle de Magallanes, 14",
    "sg:city":"Alfafar",
    "sg:orig_category":"Muebles, Minoristas",
    "sg:phone":"+34 963 76 12 75",
    "sg:postcode":"46910",
    "sg:province":"Valencia",
    "wof:name":"Brau Perez Jose Liberto",
    "wof:placetype":"venue"
},
  "geometry": {"coordinates":[-0.3921949863,39.4254837036],"type":"Point"}
}