{
  "type": "Feature",
  "properties": {
    "iso:country":"ES",
    "sg:address":"Ctra Su Eminencia, S/n",
    "sg:city":"Sevilla",
    "sg:orig_category":"Asesor\u00cda Sobre Comunicaci\u00d3n De Empresas",
    "sg:phone":"+34 954 93 32 19",
    "sg:postcode":"41006",
    "sg:province":"Sevilla",
    "wof:name":"Proyectos Asesoria Y Servicios S.a.",
    "wof:placetype":"venue"
},
  "geometry": {"coordinates":[-5.9573841095,37.3631248474],"type":"Point"}
}