{
  "type": "Feature",
  "properties": {
    "addr:full":"Avda Arquitecto Julio Carrilero, 51 Albacete Albacete 02005",
    "addr:housenumber":"51",
    "addr:postcode":"02005",
    "addr:street":"Avda Arquitecto Julio Carrilero",
    "iso:country":"ES",
    "sg:address":"Avda Arquitecto Julio Carrilero, 51",
    "sg:city":"Albacete",
    "sg:orig_category":"Plomeros",
    "sg:phone":"+34 967 22 98 61",
    "sg:postcode":"02005",
    "sg:province":"Albacete",
    "wof:name":"Iniesta Corcoles Fernando",
    "wof:placetype":"venue"
},
  "geometry": {"coordinates":[-1.8640596867,38.9989814758],"type":"Point"}
}