{
  "type": "Feature",
  "properties": {
    "iso:country":"ES",
    "sg:address":"Calle de Maria De Molina, 39",
    "sg:city":"Madrid",
    "sg:orig_category":"Sociedades Y Organismos Burs\u00c1tiles",
    "sg:phone":"+34 917 45 26 95",
    "sg:postcode":"28006",
    "sg:province":"Madrid",
    "wof:name":"Arcalia Patrimonios Agencia De Valores S.a.",
    "wof:placetype":"venue"
},
  "geometry": {"coordinates":[-3.6798713207,40.4375724792],"type":"Point"}
}