{
  "type": "Feature",
  "properties": {
    "iso:country":"ES",
    "sg:address":"Pla\u00c7 Marques De Camps, 17",
    "sg:city":"Girona",
    "sg:orig_category":"Abogados",
    "sg:phone":"+34 972 20 27 95",
    "sg:postcode":"17001",
    "sg:province":"Girona",
    "wof:name":"Cruz Puig Rosa",
    "wof:placetype":"venue"
},
  "geometry": {"coordinates":[2.8193929195,41.9822845459],"type":"Point"}
}