{
  "type": "Feature",
  "properties": {
    "addr:full":"Calle de San Juan Bosco, 32 Almeria Almer\u00eda 04005",
    "addr:housenumber":"32",
    "addr:postcode":"04005",
    "addr:street":"Calle De San Juan Bosco",
    "iso:country":"ES",
    "sg:address":"Calle de San Juan Bosco, 32",
    "sg:city":"Almeria",
    "sg:orig_category":"Farmacias",
    "sg:phone":"+34 950 26 85 30",
    "sg:postcode":"04005",
    "sg:province":"Almer\u00eda",
    "wof:name":"O\u00f1a Navarro Constanza De",
    "wof:placetype":"venue"
},
  "geometry": {"coordinates":[-2.4546079636,36.8425674438],"type":"Point"}
}