{
  "type": "Feature",
  "properties": {
    "addr:full":"Calle de Clavijo, 7 Montijo Badajoz 06480",
    "addr:housenumber":"7",
    "addr:postcode":"06480",
    "addr:street":"Calle De Clavijo",
    "iso:country":"ES",
    "sg:address":"Calle de Clavijo, 7",
    "sg:city":"Montijo",
    "sg:orig_category":"Zapatos (al Por Menor)",
    "sg:phone":"+34 924 45 68 78",
    "sg:postcode":"06480",
    "sg:province":"Badajoz",
    "wof:name":"Calzatodo Hegma S.l.",
    "wof:placetype":"venue"
},
  "geometry": {"coordinates":[-6.6176190376,38.9073791504],"type":"Point"}
}