{
  "type": "Feature",
  "properties": {
    "addr:full":"Calle de Cuart De Poblet, S/n Vilalba Lugo 27800",
    "addr:housenumber":"s / n",
    "addr:postcode":"27800",
    "addr:street":"Calle De Cuart De Poblet",
    "iso:country":"ES",
    "sg:address":"Calle de Cuart De Poblet, S/n",
    "sg:city":"Vilalba",
    "sg:orig_category":"Ense\u00d1anza Secundaria: Colegios Y Escuelas Privadas",
    "sg:phone":"+34 982 51 09 51",
    "sg:postcode":"27800",
    "sg:province":"Lugo",
    "wof:name":"Instituto Formacion Profesional",
    "wof:placetype":"venue"
},
  "geometry": {"coordinates":[-7.6825904846,43.2925949097],"type":"Point"}
}