{
  "type": "Feature",
  "properties": {
    "addr:full":"Poli Mugitegi-a, 3 Urretxu Guip\u00f9zcoa 20700",
    "addr:housenumber":"3",
    "addr:postcode":"20700",
    "addr:street":"Mugitegi-A;Guipu\u0300Zcoa",
    "iso:country":"ES",
    "sg:address":"Poli Mugitegi-a, 3",
    "sg:city":"Urretxu",
    "sg:orig_category":"Rectificaci\u00d3n, Mecanizado, Fresado",
    "sg:phone":"+34 943 72 59 23",
    "sg:postcode":"20700",
    "sg:province":"Guip\u00f9zcoa",
    "wof:name":"Talleres J.u. S.a.l.",
    "wof:placetype":"venue"
},
  "geometry": {"coordinates":[-2.3134770393,43.086730957],"type":"Point"}
}