{
  "type": "Feature",
  "properties": {
    "addr:full":"Pase Reina Cristina, 6 Madrid Madrid 28014",
    "addr:housenumber":"6",
    "addr:postcode":"28014",
    "addr:street":"Cristina",
    "iso:country":"ES",
    "sg:address":"Pase Reina Cristina, 6",
    "sg:city":"Madrid",
    "sg:orig_category":"Bazares, Art\u00cdculos De Limpieza Y De Cocina (al Por Menor)",
    "sg:phone":"+34 914 33 12 36",
    "sg:postcode":"28014",
    "sg:province":"Madrid",
    "wof:name":"Wang  Jian",
    "wof:placetype":"venue"
},
  "geometry": {"coordinates":[-3.6832938194,40.4067382812],"type":"Point"}
}