{
  "type": "Feature",
  "properties": {
    "addr:full":"Calle de Recoletos, 11 San Antonio Abad Murcia 30205",
    "addr:housenumber":"11",
    "addr:postcode":"30205",
    "addr:street":"Calle De Recoletos",
    "iso:country":"ES",
    "sg:address":"Calle de Recoletos, 11",
    "sg:city":"San Antonio Abad",
    "sg:orig_category":"Fabricaci\u00d3n, Distribuci\u00d3n De Material Para La Climatizaci\u00d3n, Aireaci\u00d3n Y Ventilaci\u00d3n",
    "sg:phone":"+34 968 53 14 80",
    "sg:postcode":"30205",
    "sg:province":"Murcia",
    "wof:name":"Refrigeracion Jose Mendez S.l",
    "wof:placetype":"venue"
},
  "geometry": {"coordinates":[-1.1302499771,37.9829597473],"type":"Point"}
}