{
  "type": "Feature",
  "properties": {
    "iso:country":"ES",
    "sg:address":"Carrer de Dante Alighieri, 177",
    "sg:city":"Barcelona",
    "sg:orig_category":"Animales (al Por Menor)",
    "sg:phone":"+34 934 07 17 31",
    "sg:postcode":"08032",
    "sg:province":"Barcelona",
    "wof:name":"Antunez Mateo Jose",
    "wof:placetype":"venue"
},
  "geometry": {"coordinates":[2.1529889107,41.4251899719],"type":"Point"}
}