{
  "type": "Feature",
  "properties": {
    "iso:country":"ES",
    "sg:address":"Calle de Toreno, 42",
    "sg:city":"Fuenlabrada",
    "sg:orig_category":"Quincaller\u00cda (al Por Menor)",
    "sg:phone":"+34 916 21 45 20",
    "sg:postcode":"28947",
    "sg:province":"Madrid",
    "wof:name":"Ferreteria Santa Engracia S. L.",
    "wof:placetype":"venue"
},
  "geometry": {"coordinates":[-3.7501370907,40.265411377],"type":"Point"}
}