{
  "type": "Feature",
  "properties": {
    "iso:country":"ES",
    "sg:address":"Calle de Carnero, 6",
    "sg:city":"Granada",
    "sg:orig_category":"Pintores",
    "sg:phone":"+34 958 22 36 61",
    "sg:postcode":"18010",
    "sg:province":"Granada",
    "wof:name":"Lopez Rodriguez Maria Trinidad",
    "wof:placetype":"venue"
},
  "geometry": {"coordinates":[-3.5933811665,37.1787033081],"type":"Point"}
}