{
  "type": "Feature",
  "properties": {
    "iso:country":"ES",
    "sg:address":"Calle de Arroyo, 2",
    "sg:city":"Villafranca Cordoba",
    "sg:orig_category":"Inform\u00c1tica Equipo Y Programas (al Por Mayor)",
    "sg:phone":"+34 957 19 07 41",
    "sg:postcode":"14420",
    "sg:province":"C\u00f3rdoba",
    "wof:name":"Galiot Erena Rosa",
    "wof:placetype":"venue"
},
  "geometry": {"coordinates":[-4.5470285416,37.9622840881],"type":"Point"}
}