{
  "type": "Feature",
  "properties": {
    "iso:country":"ES",
    "sg:address":"Calle de Modesto Lafuente, 90",
    "sg:city":"Madrid",
    "sg:orig_category":"Abogados",
    "sg:phone":"+34 915 35 33 07",
    "sg:postcode":"28003",
    "sg:province":"Madrid",
    "wof:name":"Agundez Leal Antonio",
    "wof:placetype":"venue"
},
  "geometry": {"coordinates":[-3.6956458092,40.446144104],"type":"Point"}
}