{
  "type": "Feature",
  "properties": {
    "addr:full":"Carrer de Comtal, 17 Barcelona Barcelona 08002",
    "addr:housenumber":"17",
    "addr:postcode":"08002",
    "addr:street":"Carrer De Comtal",
    "iso:country":"ES",
    "sg:address":"Carrer de Comtal, 17",
    "sg:city":"Barcelona",
    "sg:orig_category":"\u00d3ptica: Instrumentos (fabricaci\u00d3n)",
    "sg:phone":"+34 933 02 40 71",
    "sg:postcode":"08002",
    "sg:province":"Barcelona",
    "wof:name":"Optica Sanabre S.a.",
    "wof:placetype":"venue"
},
  "geometry": {"coordinates":[2.1735489368,41.3866462708],"type":"Point"}
}