{
  "type": "Feature",
  "properties": {
    "iso:country":"ES",
    "sg:address":"Rua Faisan, 5",
    "sg:city":"Vigo",
    "sg:orig_category":"Asesor\u00cda Sobre Comunicaci\u00d3n De Empresas",
    "sg:phone":"+34 986 37 20 63",
    "sg:postcode":"36205",
    "sg:province":"Pontevedra",
    "wof:name":"Estudio Contable Galicia S.l.",
    "wof:placetype":"venue"
},
  "geometry": {"coordinates":[-8.7085046768,42.2288513184],"type":"Point"}
}