{
  "type": "Feature",
  "properties": {
    "iso:country":"ES",
    "sg:address":"Calle de Vega (de La), 1",
    "sg:city":"Tarazona",
    "sg:orig_category":"Peluquer\u00cdas, Peluquer\u00cda Mixta",
    "sg:phone":"+34 976 64 03 37",
    "sg:postcode":"50500",
    "sg:province":"Zaragoza",
    "wof:name":"Dominguez Torres Maria Piedad",
    "wof:placetype":"venue"
},
  "geometry": {"coordinates":[-1.7225840092,41.9109306335],"type":"Point"}
}