{
  "type": "Feature",
  "properties": {
    "iso:country":"ES",
    "sg:address":"Rua Instituto, 26",
    "sg:city":"Ferrol",
    "sg:orig_category":"Negocio De Madera",
    "sg:phone":"+34 981 31 22 62",
    "sg:postcode":"15404",
    "sg:province":"La Coru\u00f1a",
    "wof:name":"Maderas Ferrol S.l.",
    "wof:placetype":"venue"
},
  "geometry": {"coordinates":[-8.2274503708,43.4891319275],"type":"Point"}
}