{
  "type": "Feature",
  "properties": {
    "iso:country":"ES",
    "sg:address":"Calle de Martinez Izquierdo, 26",
    "sg:city":"Molina",
    "sg:orig_category":"Marmolistas Funerarios",
    "sg:phone":"+34 949 83 25 60",
    "sg:postcode":"19300",
    "sg:province":"Guadalajara",
    "wof:name":"Alcocer Olmos Juan",
    "wof:placetype":"venue"
},
  "geometry": {"coordinates":[-1.8862299919,40.8437156677],"type":"Point"}
}