{
  "type": "Feature",
  "properties": {
    "iso:country":"ES",
    "sg:address":"Barranco Del Lobo, 3",
    "sg:city":"Alboy",
    "sg:orig_category":"Importaci\u00d3n",
    "sg:phone":"+34 962 22 93 36",
    "sg:postcode":"46800",
    "sg:province":"Valencia",
    "wof:name":"Hahn  Hasso Peter",
    "wof:placetype":"venue"
},
  "geometry": {"coordinates":[-0.5200830102,38.9934272766],"type":"Point"}
}