{
  "type": "Feature",
  "properties": {
    "addr:full":"Carr Camp Del Moli, 15 Solsona Lleida 25280",
    "addr:housenumber":"15",
    "addr:postcode":"25280",
    "addr:street":"Carr Camp Del Moli",
    "iso:country":"ES",
    "sg:address":"Carr Camp Del Moli, 15",
    "sg:city":"Solsona",
    "sg:orig_category":"Producci\u00d3n, Distribuci\u00d3n De Electricidad",
    "sg:phone":"+34 973 48 00 00",
    "sg:postcode":"25280",
    "sg:province":"Lleida",
    "wof:name":"Electra Del Cardener Sociedad Anonima",
    "wof:placetype":"venue"
},
  "geometry": {"coordinates":[1.5227190256,41.9930267334],"type":"Point"}
}