{
  "type": "Feature",
  "properties": {
    "addr:full":"Ctr Huete-tortuera, 7 Villanueva De Alcoron Guadalajara 19460",
    "addr:housenumber":"7",
    "addr:postcode":"19460",
    "addr:street":"Huete-Tortuera",
    "iso:country":"ES",
    "sg:address":"Ctr Huete-tortuera, 7",
    "sg:city":"Villanueva De Alcoron",
    "sg:orig_category":"Cajas De Ahorro",
    "sg:phone":"+34 949 81 60 06",
    "sg:postcode":"19460",
    "sg:province":"Guadalajara",
    "wof:name":"Caja De Ahorro Provincial De Guadalajara",
    "wof:placetype":"venue"
},
  "geometry": {"coordinates":[-2.251625061,40.6783218384],"type":"Point"}
}