{
  "type": "Feature",
  "properties": {
    "iso:country":"ES",
    "sg:address":"Calle de Bernia, 13",
    "sg:city":"Valencia",
    "sg:orig_category":"Discapacitados",
    "sg:phone":"+34 963 34 42 42",
    "sg:postcode":"46013",
    "sg:province":"Valencia",
    "wof:name":"Asociacion Espa\u00f1ola De Discapacitados",
    "wof:placetype":"venue"
},
  "geometry": {"coordinates":[-0.3729700148,39.4540405273],"type":"Point"}
}