{
  "type": "Feature",
  "properties": {
    "addr:full":"Calle de Gran Via, 23 Zaragoza Zaragoza 50006",
    "addr:housenumber":"23",
    "addr:postcode":"50006",
    "addr:street":"Calle De Gran Via",
    "iso:country":"ES",
    "sg:address":"Calle de Gran Via, 23",
    "sg:city":"Zaragoza",
    "sg:orig_category":"Abogados",
    "sg:phone":"+34 976 22 12 05",
    "sg:postcode":"50006",
    "sg:province":"Zaragoza",
    "wof:name":"Romeo Lagunas Manuel Jose",
    "wof:placetype":"venue"
},
  "geometry": {"coordinates":[-0.8886650205,41.6455421448],"type":"Point"}
}