{
  "type": "Feature",
  "properties": {
    "addr:full":"Calle de Mayor, 8 S. Esteban Gormaz Soria 42330",
    "addr:housenumber":"8",
    "addr:postcode":"42330",
    "addr:street":"Calle De Mayor",
    "iso:country":"ES",
    "sg:address":"Calle de Mayor, 8",
    "sg:city":"S. Esteban Gormaz",
    "sg:orig_category":"Cajas Para Embalar",
    "sg:phone":"+34 975 35 01 94",
    "sg:postcode":"42330",
    "sg:province":"Soria",
    "sg:website":"www.cajarural.com",
    "wof:name":"Caja Rural Provincial De Soria",
    "wof:placetype":"venue"
},
  "geometry": {"coordinates":[-3.2022271156,41.5733375549],"type":"Point"}
}