{
  "type": "Feature",
  "properties": {
    "iso:country":"ES",
    "sg:address":"Ctra Fataga, Km. 0006,0",
    "sg:city":"Fataga",
    "sg:orig_category":"Parques De Atracciones Y Centros De Esparcimiento",
    "sg:phone":"+34 928 17 22 95",
    "sg:postcode":"35108",
    "sg:province":"Las Palmas",
    "wof:name":"Mundo Aborigen S.a.",
    "wof:placetype":"venue"
},
  "geometry": {"coordinates":[-15.5638666153,27.8875045776],"type":"Point"}
}