{
  "type": "Feature",
  "properties": {
    "addr:full":"Avda Palma De Mallorca, 56 Torremolinos M\u00e1laga 29620",
    "addr:housenumber":"56",
    "addr:postcode":"29620",
    "addr:street":"Avda Palma De Mallorca;Ma\u0301Laga",
    "iso:country":"ES",
    "sg:address":"Avda Palma De Mallorca, 56",
    "sg:city":"Torremolinos",
    "sg:orig_category":"Agentes, Concesionarios Y Sucursales De Veh\u00cdculos",
    "sg:phone":"+34 952 38 71 22",
    "sg:postcode":"29620",
    "sg:province":"M\u00e1laga",
    "wof:name":"Ruiz Orfila Maria Jose",
    "wof:placetype":"venue"
},
  "geometry": {"coordinates":[-4.4998059273,36.618938446],"type":"Point"}
}