{
  "type": "Feature",
  "properties": {
    "iso:country":"ES",
    "sg:address":"Rua Igrexa, S/n",
    "sg:city":"Ferrol",
    "sg:orig_category":"Carnicer\u00cdas, Carnicer\u00cdas",
    "sg:phone":"+34 981 35 71 11",
    "sg:postcode":"15402",
    "sg:province":"A Coru\u00f1a",
    "wof:name":"Villasuso Paz Constantino",
    "wof:placetype":"venue"
},
  "geometry": {"coordinates":[-8.3034362793,43.5147666931],"type":"Point"}
}