{
  "type": "Feature",
  "properties": {
    "iso:country":"ES",
    "sg:address":"Calle de Jaime I, 24",
    "sg:city":"Onil",
    "sg:orig_category":"Juegos Y Juguetes (al Por Menor)",
    "sg:phone":"+34 965 56 45 20",
    "sg:postcode":"03430",
    "sg:province":"Alicante",
    "wof:name":"Industria Auxiliar Juema S.l.",
    "wof:placetype":"venue"
},
  "geometry": {"coordinates":[-0.6820089817,38.625831604],"type":"Point"}
}