{
  "type": "Feature",
  "properties": {
    "addr:full":"Plaz San Francisco, 10 Belorado Burgos 09250",
    "addr:housenumber":"10",
    "addr:postcode":"09250",
    "addr:street":"Plaz San Francisco",
    "iso:country":"ES",
    "sg:address":"Plaz San Francisco, 10",
    "sg:city":"Belorado",
    "sg:orig_category":"Florister\u00cdas",
    "sg:phone":"+34 947 58 00 47",
    "sg:postcode":"09250",
    "sg:province":"Burgos",
    "wof:name":"Calvo Sierra Gerardo",
    "wof:placetype":"venue"
},
  "geometry": {"coordinates":[-3.1912889481,42.418838501],"type":"Point"}
}