{
  "type": "Feature",
  "properties": {
    "iso:country":"ES",
    "sg:address":"Calle de Gipuzkoa, 14",
    "sg:city":"San Vicente De Barakaldo",
    "sg:orig_category":"Carnicer\u00cdas, Carnicer\u00cdas",
    "sg:phone":"+34 944 38 26 74",
    "sg:postcode":"48901",
    "sg:province":"Vizcaya",
    "wof:name":"Ortega Arenzana Victor Jose",
    "wof:placetype":"venue"
},
  "geometry": {"coordinates":[-2.9867269993,43.2948493958],"type":"Point"}
}