{
  "type": "Feature",
  "properties": {
    "iso:country":"ES",
    "sg:address":"Calle de Alcaide, 6",
    "sg:city":"Lucena",
    "sg:orig_category":"Administradores De Bienes Y Delegados De Comunidades De Propietarios",
    "sg:phone":"+34 957 50 18 72",
    "sg:postcode":"14900",
    "sg:province":"C\u00f3rdoba",
    "wof:name":"Huertas Salazar Angel Isaac",
    "wof:placetype":"venue"
},
  "geometry": {"coordinates":[-4.4855895042,37.4097824097],"type":"Point"}
}