{
  "type": "Feature",
  "properties": {
    "iso:country":"ES",
    "sg:address":"Calle de Trafalgar, S/n",
    "sg:city":"Guadalajara",
    "sg:orig_category":"Agentes, Concesionarios Y Sucursales De Veh\u00cdculos",
    "sg:phone":"+34 949 20 21 00",
    "sg:postcode":"19004",
    "sg:province":"Guadalajara",
    "wof:name":"Alcarre\u00f1a De Turismo S. A.",
    "wof:placetype":"venue"
},
  "geometry": {"coordinates":[-3.1896066666,40.6263084412],"type":"Point"}
}