{
  "type": "Feature",
  "properties": {
    "addr:full":"Avgd Castello, 28 Benicasim Castell\u00f3n 12560",
    "addr:housenumber":"28",
    "addr:postcode":"12560",
    "addr:street":"Castello",
    "iso:country":"ES",
    "sg:address":"Avgd Castello, 28",
    "sg:city":"Benicasim",
    "sg:orig_category":"Molduras, Junquillos, Listones Y Molduras Perforadas",
    "sg:phone":"+34 964 30 52 68",
    "sg:postcode":"12560",
    "sg:province":"Castell\u00f3n",
    "wof:name":"Sistelcom-telemensaje,s.a.",
    "wof:placetype":"venue"
},
  "geometry": {"coordinates":[0.0457400009,40.0510292053],"type":"Point"}
}