{
  "type": "Feature",
  "properties": {
    "iso:country":"ES",
    "sg:address":"Calle de Virgen Milagrosa, 7",
    "sg:city":"Irun",
    "sg:orig_category":"Alimentaci\u00d3n General (al Por Menor)",
    "sg:phone":"+34 943 63 25 54",
    "sg:postcode":"20304",
    "sg:province":"Guip\u00f9zcoa",
    "wof:name":"Comestibles Guerrero",
    "wof:placetype":"venue"
},
  "geometry": {"coordinates":[-1.787528038,43.3350639343],"type":"Point"}
}