{
  "type": "Feature",
  "properties": {
    "iso:country":"ES",
    "sg:address":"Rua Sanjurjo Badia, 107",
    "sg:city":"Vigo",
    "sg:orig_category":"Florister\u00cdas",
    "sg:phone":"+34 986 37 11 04",
    "sg:postcode":"36207",
    "sg:province":"Pontevedra",
    "wof:name":"Xardin Alvedo S.l.",
    "wof:placetype":"venue"
},
  "geometry": {"coordinates":[-8.7012586594,42.2463912964],"type":"Point"}
}