{
  "type": "Feature",
  "properties": {
    "iso:country":"ES",
    "sg:address":"Rbla S Isidre, 16",
    "sg:city":"Igualada",
    "sg:orig_category":"Sociedades, Compa\u00d1\u00cdas Aseguradoras",
    "sg:phone":"+34 938 04 43 47",
    "sg:postcode":"08700",
    "sg:province":"Barcelona",
    "wof:name":"Alex Julien S.l.",
    "wof:placetype":"venue"
},
  "geometry": {"coordinates":[1.6171473265,41.5795555115],"type":"Point"}
}