{
  "type": "Feature",
  "properties": {
    "iso:country":"ES",
    "sg:address":"Ptda Sant A Florida, 141",
    "sg:city":"Crevillente",
    "sg:orig_category":"Tapicer\u00cdas",
    "sg:phone":"+34 965 40 45 52",
    "sg:postcode":"03330",
    "sg:province":"Alicante",
    "wof:name":"Textil Penalva Martinez S.l.",
    "wof:placetype":"venue"
},
  "geometry": {"coordinates":[-0.8052690029,38.2463111877],"type":"Point"}
}