{
  "type": "Feature",
  "properties": {
    "addr:full":"Calle de Santa Maria Magdalena, 66 Dos Hermanas Sevilla 41700",
    "addr:housenumber":"66",
    "addr:postcode":"41700",
    "addr:street":"Calle De Santa;Magdalena",
    "iso:country":"ES",
    "sg:address":"Calle de Santa Maria Magdalena, 66",
    "sg:city":"Dos Hermanas",
    "sg:orig_category":"Colchones (fabricaci\u00d3n, Al Por Mayor, Al Por Menor)",
    "sg:phone":"+34 955 66 01 68",
    "sg:postcode":"41700",
    "sg:province":"Sevilla",
    "sg:website":"www.beds.es",
    "wof:name":"Rosado Exposito Guadalupe Maria",
    "wof:placetype":"venue"
},
  "geometry": {"coordinates":[-5.9270071983,37.2831001282],"type":"Point"}
}