{
  "type": "Feature",
  "properties": {
    "addr:full":"Carretera De Lobon, Km. 0000,4 Montijo Badajoz 06480",
    "addr:postcode":"06480",
    "addr:street":"Carretera De Lobon Km. 0000,4",
    "iso:country":"ES",
    "sg:address":"Carretera De Lobon, Km. 0000,4",
    "sg:city":"Montijo",
    "sg:orig_category":"Mec\u00c1nico Del Autom\u00d3vil",
    "sg:phone":"+34 924 45 61 01",
    "sg:postcode":"06480",
    "sg:province":"Badajoz",
    "wof:name":"Escorial Martin Segundo",
    "wof:placetype":"venue"
},
  "geometry": {"coordinates":[-6.6062841415,38.9077644348],"type":"Point"}
}