{
  "type": "Feature",
  "properties": {
    "addr:full":"Carr Vilafames, 1 Mas Dels Frares Castell\u00f3n 12560",
    "addr:housenumber":"1",
    "addr:postcode":"12560",
    "addr:street":"Carr Vilafames;Castello\u0301N",
    "iso:country":"ES",
    "sg:address":"Carr Vilafames, 1",
    "sg:city":"Mas Dels Frares",
    "sg:orig_category":"T\u00c9cnicos Veterinarios",
    "sg:phone":"+34 964 39 26 11",
    "sg:postcode":"12560",
    "sg:province":"Castell\u00f3n",
    "wof:name":"Martinez Bayarri Carlos",
    "wof:placetype":"venue"
},
  "geometry": {"coordinates":[0.0590550005,40.0523414612],"type":"Point"}
}