{
  "type": "Feature",
  "properties": {
    "addr:full":"Calle de Udaberria, 14 Getxo Vizcaya 48990",
    "addr:housenumber":"14",
    "addr:postcode":"48990",
    "addr:street":"Calle De Udaberria",
    "iso:country":"ES",
    "sg:address":"Calle de Udaberria, 14",
    "sg:city":"Getxo",
    "sg:orig_category":"Librer\u00cdas",
    "sg:phone":"+34 944 04 91 92",
    "sg:postcode":"48990",
    "sg:province":"Vizcaya",
    "wof:name":"Aiboa Plus, S.l.",
    "wof:placetype":"venue"
},
  "geometry": {"coordinates":[-3.0016863346,43.3428077698],"type":"Point"}
}