{
  "type": "Feature",
  "properties": {
    "addr:full":"Calle de Luis Martinez Kleiser, 2 Cuenca Cuenca 16002",
    "addr:housenumber":"2",
    "addr:postcode":"16002",
    "addr:street":"Calle De Luis Martinez Kleiser",
    "iso:country":"ES",
    "sg:address":"Calle de Luis Martinez Kleiser, 2",
    "sg:city":"Cuenca",
    "sg:orig_category":"Ense\u00d1anza, Formaci\u00d3n Profesional: Aprendizaje",
    "sg:phone":"+34 969 22 21 17",
    "sg:postcode":"16002",
    "sg:province":"Cuenca",
    "wof:name":"Ayuntamiento De Cuenca",
    "wof:placetype":"venue"
},
  "geometry": {"coordinates":[-2.1386671066,40.0729675293],"type":"Point"}
}