{
  "type": "Feature",
  "properties": {
    "iso:country":"ES",
    "sg:address":"Calle de Sierra, S/n",
    "sg:city":"Viso S. Juan",
    "sg:orig_category":"Promotores Constructores",
    "sg:phone":"+34 925 55 90 53",
    "sg:postcode":"45215",
    "sg:province":"Toledo",
    "wof:name":"Sanchez Rubio Maria Pilar",
    "wof:placetype":"venue"
},
  "geometry": {"coordinates":[-3.9196128845,40.1449546814],"type":"Point"}
}