{
  "type": "Feature",
  "properties": {
    "iso:country":"ES",
    "sg:address":"Calle de Prosperidad, 50",
    "sg:city":"Guarnizo",
    "sg:orig_category":"Carnicer\u00cdas, Carnicer\u00cdas",
    "sg:phone":"+34 942 54 01 19",
    "sg:postcode":"39611",
    "sg:province":"Cantabria",
    "wof:name":"Agudo Maza Milagros",
    "wof:placetype":"venue"
},
  "geometry": {"coordinates":[-3.8348882198,43.4046936035],"type":"Point"}
}