{
  "type": "Feature",
  "properties": {
    "iso:country":"ES",
    "sg:address":"Ctra Albaida, S/n",
    "sg:city":"Agullent",
    "sg:orig_category":"Hilaturas, Hilos Y Actividades Relacionadas",
    "sg:phone":"+34 962 90 75 72",
    "sg:postcode":"46890",
    "sg:province":"Valencia",
    "wof:name":"Tritexco S.l.",
    "wof:placetype":"venue"
},
  "geometry": {"coordinates":[-0.545050025,38.8259735107],"type":"Point"}
}