{
  "type": "Feature",
  "properties": {
    "iso:country":"ES",
    "sg:address":"Pase Imperial, 85",
    "sg:city":"Madrid",
    "sg:orig_category":"Inform\u00c1tica (estudios, Servicios, Asesor\u00cda, Formaci\u00d3n)",
    "sg:phone":"+34 913 64 57 51",
    "sg:postcode":"28005",
    "sg:province":"Madrid",
    "wof:name":"Lamee Software S.l.",
    "wof:placetype":"venue"
},
  "geometry": {"coordinates":[-3.7147669792,40.4010543823],"type":"Point"}
}