{
  "type": "Feature",
  "properties": {
    "addr:full":"Rbla Marina, 488 Hospitalet Llobregat Barcelona 08907",
    "addr:housenumber":"488",
    "addr:postcode":"08907",
    "addr:street":"Rbla Marina",
    "iso:country":"ES",
    "sg:address":"Rbla Marina, 488",
    "sg:city":"Hospitalet Llobregat",
    "sg:orig_category":"Agentes, Concesionarios Y Sucursales De Veh\u00cdculos",
    "sg:phone":"+34 933 37 87 50",
    "sg:postcode":"08907",
    "sg:province":"Barcelona",
    "sg:website":"www.starbravo.com",
    "wof:name":"J.f. Star Bravo Automoviles S.l.",
    "wof:placetype":"venue"
},
  "geometry": {"coordinates":[2.1089999676,41.3537101746],"type":"Point"}
}