{
  "type": "Feature",
  "properties": {
    "addr:full":"Cra. Dosrius, 254 Cardedeu Barcelona 08440",
    "addr:housenumber":"254",
    "addr:postcode":"08440",
    "iso:country":"ES",
    "sg:address":"Cra. Dosrius, 254",
    "sg:city":"Cardedeu",
    "sg:orig_category":"Cajas Y Embalajes De Cart\u00d3n Y Papel",
    "sg:phone":"+34 938 46 18 91",
    "sg:postcode":"08440",
    "sg:province":"Barcelona",
    "sg:website":"www.demco.es",
    "wof:name":"Demco S.a.",
    "wof:placetype":"venue"
},
  "geometry": {"coordinates":[2.3644580841,41.625328064],"type":"Point"}
}