{
  "type": "Feature",
  "properties": {
    "addr:full":"Rua Real, 139 Ferrol La Coru\u00f1a 15402",
    "addr:housenumber":"139",
    "addr:postcode":"15402",
    "addr:street":"Rua Real;La Corun\u0303A",
    "iso:country":"ES",
    "sg:address":"Rua Real, 139",
    "sg:city":"Ferrol",
    "sg:orig_category":"Art\u00cdculos De Regalo (al Por Menor)",
    "sg:phone":"+34 981 35 78 04",
    "sg:postcode":"15402",
    "sg:province":"La Coru\u00f1a",
    "wof:name":"Jose Manuel Gonzalez Acevedo S.l.",
    "wof:placetype":"venue"
},
  "geometry": {"coordinates":[-8.2344799042,43.4831771851],"type":"Point"}
}