{
  "type": "Feature",
  "properties": {
    "addr:full":"Calle de Calvo Sotelo, 18 Logro\u00f1o La Rioja 26003",
    "addr:housenumber":"18",
    "addr:postcode":"26003",
    "addr:street":"Calle De Calvo Sotelo;Rioja",
    "iso:country":"ES",
    "sg:address":"Calle de Calvo Sotelo, 18",
    "sg:city":"Logro\u00f1o",
    "sg:orig_category":"Muebles Y Accesorios Para Cocinas Y Cuartos De Ba\u00d1o (al Por Menor)",
    "sg:phone":"+34 941 25 23 20",
    "sg:postcode":"26003",
    "sg:province":"La Rioja",
    "sg:website":"www.scavolini.com",
    "wof:name":"Hermanos Garcia Manero S.c.",
    "wof:placetype":"venue"
},
  "geometry": {"coordinates":[-2.44237113,42.4640884399],"type":"Point"}
}