{
  "type": "Feature",
  "properties": {
    "iso:country":"ES",
    "sg:address":"Calle de La Libertad, 5",
    "sg:city":"Vitoria-gasteiz",
    "sg:orig_category":"Agentes Generales De Seguros",
    "sg:phone":"+34 945 12 15 68",
    "sg:postcode":"01002",
    "sg:province":"\u00c1lava",
    "wof:name":"Eguiluz Monge Jose Ramon",
    "wof:placetype":"venue"
},
  "geometry": {"coordinates":[-2.6674919128,42.8480644226],"type":"Point"}
}