{
  "type": "Feature",
  "properties": {
    "iso:country":"ES",
    "sg:address":"Carrer de Arx Lluis Salvador, 79",
    "sg:city":"Palma",
    "sg:orig_category":"Farmacias",
    "sg:phone":"+34 971 75 16 36",
    "sg:postcode":"07004",
    "sg:province":"Islas Baleares",
    "wof:name":"Bonnin Sanchez Teresa",
    "wof:placetype":"venue"
},
  "geometry": {"coordinates":[2.656760931,39.5839500427],"type":"Point"}
}