{
  "type": "Feature",
  "properties": {
    "addr:full":"Cami Serra, S/n Lli\u00e7a Amunt Barcelona 08186",
    "addr:postcode":"08186",
    "addr:street":"Serra S / N Llic\u0327A",
    "iso:country":"ES",
    "sg:address":"Cami Serra, S/n",
    "sg:city":"Lli\u00e7a Amunt",
    "sg:orig_category":"Animales (al Por Menor)",
    "sg:phone":"+34 938 41 78 86",
    "sg:postcode":"08186",
    "sg:province":"Barcelona",
    "sg:website":"www.helvet-can.com",
    "wof:name":"Schaer  Didier",
    "wof:placetype":"venue"
},
  "geometry": {"coordinates":[2.2382690907,41.612449646],"type":"Point"}
}