{
  "type": "Feature",
  "properties": {
    "addr:full":"Oroteanda Alta, 5 El Monte O Guargacho Santa Cruz De Tenerife 38639",
    "addr:housenumber":"5",
    "addr:postcode":"38639",
    "addr:street":"Alta",
    "iso:country":"ES",
    "sg:address":"Oroteanda Alta, 5",
    "sg:city":"El Monte O Guargacho",
    "sg:orig_category":"Inmobiliaria (agencias)",
    "sg:phone":"+34 922 73 53 18",
    "sg:postcode":"38639",
    "sg:province":"Santa Cruz De Tenerife",
    "wof:name":"Samorey S.l.",
    "wof:placetype":"venue"
},
  "geometry": {"coordinates":[-16.6115474701,28.0350246429],"type":"Point"}
}