{
  "type": "Feature",
  "properties": {
    "iso:country":"ES",
    "sg:address":"Carrer de Lluis Puigjaner, 18",
    "sg:city":"Olesa Montserrat",
    "sg:orig_category":"Centros Empresariales",
    "sg:phone":"+34 937 75 72 71",
    "sg:postcode":"08640",
    "sg:province":"Barcelona",
    "wof:name":"Mop Fashion Olesa S.l.",
    "wof:placetype":"venue"
},
  "geometry": {"coordinates":[1.8928469419,41.5433082581],"type":"Point"}
}