{
  "type": "Feature",
  "properties": {
    "addr:full":"Pg Fabra I Puig, 171 Barcelona Barcelona 08016",
    "addr:housenumber":"171",
    "addr:postcode":"08016",
    "addr:street":"Pg Fabra I Puig",
    "iso:country":"ES",
    "sg:address":"Pg Fabra I Puig, 171",
    "sg:city":"Barcelona",
    "sg:orig_category":"Confiter\u00cdas, Chocolater\u00cdas (al Por Menor)",
    "sg:phone":"+34 934 08 69 60",
    "sg:postcode":"08016",
    "sg:province":"Barcelona",
    "wof:name":"King Fruits S.l.",
    "wof:placetype":"venue"
},
  "geometry": {"coordinates":[2.1779999733,41.4302215576],"type":"Point"}
}