{
  "type": "Feature",
  "properties": {
    "addr:full":"Avda Alcalde J.elosegi, 84 Donostia-san Sebastian Guip\u00f9zcoa 20015",
    "addr:housenumber":"84",
    "addr:postcode":"20015",
    "addr:street":"Avda Alcalde J.Elosegi",
    "iso:country":"ES",
    "sg:address":"Avda Alcalde J.elosegi, 84",
    "sg:city":"Donostia-san Sebastian",
    "sg:orig_category":"Molduras, Junquillos, Listones Y Molduras Perforadas",
    "sg:phone":"+34 943 29 27 41",
    "sg:postcode":"20015",
    "sg:province":"Guip\u00f9zcoa",
    "wof:name":"Romero Ferreras Maria Mercedes",
    "wof:placetype":"venue"
},
  "geometry": {"coordinates":[-1.9487639666,43.3211898804],"type":"Point"}
}