{
  "type": "Feature",
  "properties": {
    "addr:full":"Carrer de Torras, 2 Castellar Valles Barcelona 08211",
    "addr:housenumber":"2",
    "addr:postcode":"08211",
    "addr:street":"Carrer De Torras",
    "iso:country":"ES",
    "sg:address":"Carrer de Torras, 2",
    "sg:city":"Castellar Valles",
    "sg:orig_category":"Farmacias",
    "sg:phone":"+34 937 14 52 89",
    "sg:postcode":"08211",
    "sg:province":"Barcelona",
    "wof:name":"Rodriguez Yanguela Tania",
    "wof:placetype":"venue"
},
  "geometry": {"coordinates":[2.0866599083,41.615650177],"type":"Point"}
}