{
  "type": "Feature",
  "properties": {
    "iso:country":"ES",
    "sg:address":"Ctra. Vegas, S/n",
    "sg:city":"Otero Herreros",
    "sg:orig_category":"Fabrica De Cer\u00c1micas",
    "sg:phone":"+34 921 48 32 71",
    "sg:postcode":"40422",
    "sg:province":"Segovia",
    "wof:name":"La Paloma Ceramica Y Gres S.l.",
    "wof:placetype":"venue"
},
  "geometry": {"coordinates":[-4.2063589096,40.8213500977],"type":"Point"}
}