{
  "type": "Feature",
  "properties": {
    "iso:country":"ES",
    "sg:address":"Plaz Chueca, 9",
    "sg:city":"Madrid",
    "sg:orig_category":"\u00d3ptica: Instrumentos (fabricaci\u00d3n)",
    "sg:phone":"+34 915 24 05 47",
    "sg:postcode":"28004",
    "sg:province":"Madrid",
    "wof:name":"Zelai Optika S.l.",
    "wof:placetype":"venue"
},
  "geometry": {"coordinates":[-3.6975092888,40.4226799011],"type":"Point"}
}