{
  "type": "Feature",
  "properties": {
    "iso:country":"ES",
    "sg:address":"Corral De Abaixo, 9",
    "sg:city":"Corral",
    "sg:orig_category":"Pintores",
    "sg:phone":"+34 981 76 65 19",
    "sg:postcode":"15218",
    "sg:province":"La Coru\u00f1a",
    "wof:name":"Costa Beiro Alfonso",
    "wof:placetype":"venue"
},
  "geometry": {"coordinates":[-8.9297332764,42.766494751],"type":"Point"}
}