{
  "type": "Feature",
  "properties": {
    "iso:country":"ES",
    "sg:address":"Ptda El Pla, S/n",
    "sg:city":"Ontinyent",
    "sg:orig_category":"Semiller\u00cdas",
    "sg:phone":"+34 962 13 55 55",
    "sg:postcode":"46870",
    "sg:province":"Valencia",
    "wof:name":"Viveros Gandia S C",
    "wof:placetype":"venue"
},
  "geometry": {"coordinates":[-0.6583330035,38.7977752686],"type":"Point"}
}