{
  "type": "Feature",
  "properties": {
    "addr:full":"Calle de Meseguer, 23 Alcazares Murcia 30710",
    "addr:housenumber":"23",
    "addr:postcode":"30710",
    "addr:street":"Calle De Meseguer",
    "iso:country":"ES",
    "sg:address":"Calle de Meseguer, 23",
    "sg:city":"Alcazares",
    "sg:orig_category":"Ense\u00d1anza Variada",
    "sg:phone":"+34 968 58 21 89",
    "sg:postcode":"30710",
    "sg:province":"Murcia",
    "wof:name":"Martinez Zapata Aurora",
    "wof:placetype":"venue"
},
  "geometry": {"coordinates":[-0.8551849723,37.7356376648],"type":"Point"}
}