{
  "type": "Feature",
  "properties": {
    "addr:full":"Carrer de Sant Pere, 21 Crevillent Alicante 03330",
    "addr:housenumber":"21",
    "addr:postcode":"03330",
    "addr:street":"Carrer De Sant Pere",
    "iso:country":"ES",
    "sg:address":"Carrer de Sant Pere, 21",
    "sg:city":"Crevillent",
    "sg:orig_category":"Bisuter\u00cda, Joyer\u00cda, Relojer\u00cda (al Por Menor)",
    "sg:phone":"+34 965 40 30 16",
    "sg:postcode":"03330",
    "sg:province":"Alicante",
    "wof:name":"Campillo Ceron Jose Manuel",
    "wof:placetype":"venue"
},
  "geometry": {"coordinates":[-0.804840982,38.247177124],"type":"Point"}
}