{
  "type": "Feature",
  "properties": {
    "iso:country":"ES",
    "sg:address":"Avda Madrid, S/n",
    "sg:city":"Carolina",
    "sg:orig_category":"Fabricaci\u00d3n De Muebles",
    "sg:phone":"+34 953 66 12 70",
    "sg:postcode":"23200",
    "sg:province":"Ja\u00e9n",
    "wof:name":"Mader Carolina S.l.",
    "wof:placetype":"venue"
},
  "geometry": {"coordinates":[-3.61028409,38.2766647339],"type":"Point"}
}