{
  "type": "Feature",
  "properties": {
    "iso:country":"ES",
    "sg:address":"Carrer de Ausias March, 13",
    "sg:city":"Palma",
    "sg:orig_category":"Electromec\u00c1nica",
    "sg:phone":"+34 971 75 31 27",
    "sg:postcode":"07003",
    "sg:province":"Islas Baleares",
    "wof:name":"Diauto C.b.",
    "wof:placetype":"venue"
},
  "geometry": {"coordinates":[2.6508760452,39.5821495056],"type":"Point"}
}