{
  "type": "Feature",
  "properties": {
    "addr:full":"Aitzkorri Kalea, 24 Legazpi Guip\u00f9zcoa 20230",
    "addr:housenumber":"24",
    "addr:postcode":"20230",
    "addr:street":"Aitzkorri Kalea;Guipu\u0300Zcoa",
    "iso:country":"ES",
    "sg:address":"Aitzkorri Kalea, 24",
    "sg:city":"Legazpi",
    "sg:orig_category":"Molduras, Junquillos, Listones Y Molduras Perforadas",
    "sg:phone":"+34 943 73 00 51",
    "sg:postcode":"20230",
    "sg:province":"Guip\u00f9zcoa",
    "wof:name":"Servicios Hosteleros Kotoi S.l",
    "wof:placetype":"venue"
},
  "geometry": {"coordinates":[-2.3357169628,43.0482215881],"type":"Point"}
}