{
  "type": "Feature",
  "properties": {
    "addr:full":"Calle de Feve, 11 Palanquinos Le\u00f3n 24225",
    "addr:housenumber":"11",
    "addr:postcode":"24225",
    "addr:street":"Calle De Feve;Leo\u0301N",
    "iso:country":"ES",
    "sg:address":"Calle de Feve, 11",
    "sg:city":"Palanquinos",
    "sg:orig_category":"Librer\u00cdas",
    "sg:phone":"+34 987 31 53 41",
    "sg:postcode":"24225",
    "sg:province":"Le\u00f3n",
    "wof:name":"Berdejo Francis Araceli",
    "wof:placetype":"venue"
},
  "geometry": {"coordinates":[-5.4807291031,42.4700965881],"type":"Point"}
}