{
  "type": "Feature",
  "properties": {
    "iso:country":"ES",
    "sg:address":"Calle de Maestro Argenta, 16",
    "sg:city":"Salamanca",
    "sg:orig_category":"Asilos De Ancianos. Centros Privados",
    "sg:phone":"+34 923 26 28 87",
    "sg:postcode":"37008",
    "sg:province":"Salamanca",
    "wof:name":"Club Pensionista San Jose La Vega",
    "wof:placetype":"venue"
},
  "geometry": {"coordinates":[-5.6604189873,40.9473419189],"type":"Point"}
}