{
  "type": "Feature",
  "properties": {
    "addr:full":"Calle de Arquitecto Vandelvira, 38 Albacete Albacete 02003",
    "addr:housenumber":"38",
    "addr:postcode":"02003",
    "addr:street":"Calle De Arquitecto Vandelvira",
    "iso:country":"ES",
    "sg:address":"Calle de Arquitecto Vandelvira, 38",
    "sg:city":"Albacete",
    "sg:orig_category":"Cajas Para Embalar",
    "sg:phone":"+34 967 51 04 50",
    "sg:postcode":"02003",
    "sg:province":"Albacete",
    "wof:name":"Caja Rural De Albacete",
    "wof:placetype":"venue"
},
  "geometry": {"coordinates":[-1.8634773493,38.9883995056],"type":"Point"}
}