{
  "type": "Feature",
  "properties": {
    "iso:country":"ES",
    "sg:address":"Luga Poligono Industrial Del Bierzo, S/n",
    "sg:city":"Toral De Los Vados",
    "sg:orig_category":"Conservas De Legumbres (fabricaci\u00d3n, Al Por Mayor)",
    "sg:phone":"+34 987 54 52 56",
    "sg:postcode":"24560",
    "sg:province":"Le\u00f3n",
    "sg:website":"www.pimientosbercianos.com",
    "wof:name":"Pimientos Bercianos S.l.",
    "wof:placetype":"venue"
},
  "geometry": {"coordinates":[-6.7822341919,42.5436286926],"type":"Point"}
}