{
  "type": "Feature",
  "properties": {
    "iso:country":"ES",
    "sg:address":"Avda Do\u00d1a Fermina, S/n",
    "sg:city":"Vigo",
    "sg:orig_category":"Ense\u00d1anza Secundaria: Colegios Y Escuelas Privadas",
    "sg:phone":"+34 986 37 51 11",
    "sg:postcode":"36207",
    "sg:province":"Pontevedra",
    "wof:name":"Instituto Bacharelato La Guia",
    "wof:placetype":"venue"
},
  "geometry": {"coordinates":[-8.7005815506,42.2540893555],"type":"Point"}
}