{
  "type": "Feature",
  "properties": {
    "addr:full":"Calle de Marina, S/n Cari\u00f1o A Coru\u00f1a 15360",
    "addr:housenumber":"s",
    "addr:postcode":"15360",
    "addr:street":"Calle De Marina;/ N;Corun\u0303A",
    "iso:country":"ES",
    "sg:address":"Calle de Marina, S/n",
    "sg:city":"Cari\u00f1o",
    "sg:orig_category":"Quincaller\u00cda (al Por Menor)",
    "sg:phone":"+34 981 40 50 47",
    "sg:postcode":"15360",
    "sg:province":"A Coru\u00f1a",
    "wof:name":"Trinquete Quiza Florencio",
    "wof:placetype":"venue"
},
  "geometry": {"coordinates":[-7.8681340218,43.7411804199],"type":"Point"}
}