{
  "type": "Feature",
  "properties": {
    "iso:country":"ES",
    "sg:address":"Calle de Dragaminas, S/n",
    "sg:city":"Palmones",
    "sg:orig_category":"Transporte En General",
    "sg:phone":"+34 956 67 81 36",
    "sg:postcode":"11379",
    "sg:province":"C\u00e1diz",
    "wof:name":"3 D.a. S.l.",
    "wof:placetype":"venue"
},
  "geometry": {"coordinates":[-5.435647,36.181309],"type":"Point"}
}