{
  "type": "Feature",
  "properties": {
    "iso:country":"ES",
    "sg:address":"Cra. Nacional Ii, Km. 0639,5",
    "sg:city":"Vilassar",
    "sg:orig_category":"Florister\u00cdas",
    "sg:phone":"+34 937 59 85 46",
    "sg:postcode":"08340",
    "sg:province":"Barcelona",
    "wof:name":"Flor Madegar S.l.",
    "wof:placetype":"venue"
},
  "geometry": {"coordinates":[2.3907299042,41.5019264221],"type":"Point"}
}