{
  "type": "Feature",
  "properties": {
    "iso:country":"ES",
    "sg:address":"Carrer de Jaume Huguet, 11",
    "sg:city":"Esplugues Llobregat",
    "sg:orig_category":"Vinos Y Licores (venta Al Por Menor)",
    "sg:phone":"+34 934 73 88 12",
    "sg:postcode":"08950",
    "sg:province":"Barcelona",
    "wof:name":"Planconsult S.l.",
    "wof:placetype":"venue"
},
  "geometry": {"coordinates":[2.0881569386,41.3852005005],"type":"Point"}
}