{
  "type": "Feature",
  "properties": {
    "addr:full":"Calle de Echarri, 9 Falces Navarra 31370",
    "addr:housenumber":"9",
    "addr:postcode":"31370",
    "addr:street":"Calle De Echarri",
    "iso:country":"ES",
    "sg:address":"Calle de Echarri, 9",
    "sg:city":"Falces",
    "sg:orig_category":"Molduras, Junquillos, Listones Y Molduras Perforadas",
    "sg:phone":"+34 948 73 41 27",
    "sg:postcode":"31370",
    "sg:province":"Navarra",
    "wof:name":"Iribarren Irisarri Martin",
    "wof:placetype":"venue"
},
  "geometry": {"coordinates":[-1.7963433266,42.388469696],"type":"Point"}
}