{
  "type": "Feature",
  "properties": {
    "iso:country":"ES",
    "sg:address":"Calle de Jesus Del Gran Poder, 26",
    "sg:city":"Ecija",
    "sg:orig_category":"Venta, Colocaci\u00d3n, Reparaci\u00d3n De Radiadores Para Veh\u00cdculos",
    "sg:phone":"+34 954 83 32 15",
    "sg:postcode":"41400",
    "sg:province":"Sevilla",
    "wof:name":"Enriquez Prieto Pedro",
    "wof:placetype":"venue"
},
  "geometry": {"coordinates":[-5.0662341118,37.5448989868],"type":"Point"}
}