{
  "type": "Feature",
  "properties": {
    "addr:full":"Calle de Estacion, 34 Miranda Ebro Burgos 09200",
    "addr:housenumber":"34",
    "addr:postcode":"09200",
    "addr:street":"Calle De Estacion",
    "iso:country":"ES",
    "sg:address":"Calle de Estacion, 34",
    "sg:city":"Miranda Ebro",
    "sg:orig_category":"Arquitectos",
    "sg:phone":"+34 947 31 08 78",
    "sg:postcode":"09200",
    "sg:province":"Burgos",
    "wof:name":"Estudio Dau S.a.",
    "wof:placetype":"venue"
},
  "geometry": {"coordinates":[-2.9446320534,42.6872177124],"type":"Point"}
}