{
  "type": "Feature",
  "properties": {
    "addr:full":"Calle de Pilar (el), 5 Santa Cruz De Tenerife Santa Cruz De Tenerife 38002",
    "addr:housenumber":"5",
    "addr:postcode":"38002",
    "addr:street":"Calle De Pilar El",
    "iso:country":"ES",
    "sg:address":"Calle de Pilar (el), 5",
    "sg:city":"Santa Cruz De Tenerife",
    "sg:orig_category":"Notarios",
    "sg:phone":"+34 922 24 22 58",
    "sg:postcode":"38002",
    "sg:province":"Santa Cruz De Tenerife",
    "wof:name":"Esteban Beltran Juan Jose",
    "wof:placetype":"venue"
},
  "geometry": {"coordinates":[-16.2512950897,28.4682312012],"type":"Point"}
}