{
  "type": "Feature",
  "properties": {
    "iso:country":"ES",
    "sg:address":"Carrer de Turo De La Trinitat, 31",
    "sg:city":"Barcelona",
    "sg:orig_category":"Panader\u00cdas, Panader\u00cdas",
    "sg:phone":"+34 932 74 29 65",
    "sg:postcode":"08033",
    "sg:province":"Barcelona",
    "wof:name":"Dialypa S.l.",
    "wof:placetype":"venue"
},
  "geometry": {"coordinates":[2.190210104,41.4501037598],"type":"Point"}
}