{
  "type": "Feature",
  "properties": {
    "addr:full":"Pla\u00c7 Tomas Raguer, 3 Centre Urba Girona 17500",
    "addr:housenumber":"3;urba",
    "addr:postcode":"17500",
    "addr:street":"Raguer",
    "iso:country":"ES",
    "sg:address":"Pla\u00c7 Tomas Raguer, 3",
    "sg:city":"Centre Urba",
    "sg:orig_category":"Molduras, Junquillos, Listones Y Molduras Perforadas",
    "sg:phone":"+34 972 70 00 19",
    "sg:postcode":"17500",
    "sg:province":"Girona",
    "wof:name":"Soler Salvans Marcos",
    "wof:placetype":"venue"
},
  "geometry": {"coordinates":[2.1959049702,42.1965866089],"type":"Point"}
}