{
  "type": "Feature",
  "properties": {
    "addr:full":"Pda Capsades, S/n Vinaros Castell\u00f3n 12500",
    "addr:housenumber":"s / n",
    "addr:postcode":"12500",
    "iso:country":"ES",
    "sg:address":"Pda Capsades, S/n",
    "sg:city":"Vinaros",
    "sg:orig_category":"Mayoristas E Intermediarios En Alcoholes",
    "sg:phone":"+34 964 40 16 68",
    "sg:postcode":"12500",
    "sg:province":"Castell\u00f3n",
    "wof:name":"Garcia Gri\u00f1o Jose",
    "wof:placetype":"venue"
},
  "geometry": {"coordinates":[0.4408037066,40.501701355],"type":"Point"}
}