{
  "type": "Feature",
  "properties": {
    "iso:country":"ES",
    "sg:address":"Carr Reina Victoria, 42",
    "sg:city":"Pobla",
    "sg:orig_category":"Fabricaci\u00d3n De Muebles De Cocina",
    "sg:phone":"+34 971 54 27 50",
    "sg:postcode":"07420",
    "sg:province":"Islas Baleares",
    "wof:name":"Nadal Marruntx S.l.",
    "wof:placetype":"venue"
},
  "geometry": {"coordinates":[3.025769949,39.7738304138],"type":"Point"}
}