{
  "type": "Feature",
  "properties": {
    "addr:full":"Calle de Padilla, 5 Valladolid Valladolid 47003",
    "addr:housenumber":"5",
    "addr:postcode":"47003",
    "addr:street":"Calle De Padilla",
    "iso:country":"ES",
    "sg:address":"Calle de Padilla, 5",
    "sg:city":"Valladolid",
    "sg:orig_category":"Caf\u00c9s, Bares, Cervecer\u00cdas",
    "sg:phone":"+34 983 26 67 46",
    "sg:postcode":"47003",
    "sg:province":"Valladolid",
    "wof:name":"Rocambole C.b.",
    "wof:placetype":"venue"
},
  "geometry": {"coordinates":[-4.7082448006,41.6675643921],"type":"Point"}
}