{
  "type": "Feature",
  "properties": {
    "iso:country":"ES",
    "sg:address":"Psaj Platero Leiva, 3",
    "sg:city":"Cordoba",
    "sg:orig_category":"Delegados, Agentes De Tr\u00c1nsito, Auxiliares De Transporte Internacional",
    "sg:phone":"+34 957 75 12 27",
    "sg:postcode":"14010",
    "sg:province":"C\u00f3rdoba",
    "wof:name":"Sanchez Aguilera Fernando",
    "wof:placetype":"venue"
},
  "geometry": {"coordinates":[-4.764509201,37.8784980774],"type":"Point"}
}