{
  "type": "Feature",
  "properties": {
    "addr:full":"Ctra Moraleja, S/n Nava Asuncion Segovia 40450",
    "addr:housenumber":"s / n",
    "addr:postcode":"40450",
    "addr:street":"Ctra Moraleja",
    "iso:country":"ES",
    "sg:address":"Ctra Moraleja, S/n",
    "sg:city":"Nava Asuncion",
    "sg:orig_category":"Acero: Productos Sider\u00dargicos Y Transformados (fabricaci\u00d3n, Negocio)",
    "sg:phone":"+34 921 58 02 12",
    "sg:postcode":"40450",
    "sg:province":"Segovia",
    "wof:name":"Hierros Hontoria S. A.",
    "wof:placetype":"venue"
},
  "geometry": {"coordinates":[-4.4882631302,41.1547355652],"type":"Point"}
}