{
  "type": "Feature",
  "properties": {
    "addr:full":"Calle de Virgen De Belen, 2 Orihuela Alicante 03300",
    "addr:housenumber":"2",
    "addr:postcode":"03300",
    "addr:street":"Calle De Virgen De Belen",
    "iso:country":"ES",
    "sg:address":"Calle de Virgen De Belen, 2",
    "sg:city":"Orihuela",
    "sg:orig_category":"Molduras, Junquillos, Listones Y Molduras Perforadas",
    "sg:phone":"+34 965 30 67 85",
    "sg:postcode":"03300",
    "sg:province":"Alicante",
    "wof:name":"Rodriguez Escamilla Carmen",
    "wof:placetype":"venue"
},
  "geometry": {"coordinates":[-0.9424080253,38.083152771],"type":"Point"}
}