{
  "type": "Feature",
  "properties": {
    "addr:full":"Carr Nord, 32 Lleida Lleida 25007",
    "addr:housenumber":"32",
    "addr:postcode":"25007",
    "addr:street":"Carr Nord",
    "iso:country":"ES",
    "sg:address":"Carr Nord, 32",
    "sg:city":"Lleida",
    "sg:orig_category":"Deportes Diversos",
    "sg:phone":"+34 973 24 06 68",
    "sg:postcode":"25007",
    "sg:province":"Lleida",
    "wof:name":"Club Escacs Lleida",
    "wof:placetype":"venue"
},
  "geometry": {"coordinates":[0.627129972,41.6145210266],"type":"Point"}
}