{
  "type": "Feature",
  "properties": {
    "addr:full":"Carrer de Nord, 20 Buvisa Barcelona 08329",
    "addr:housenumber":"20",
    "addr:postcode":"08329",
    "addr:street":"Carrer De Nord;Barcelona",
    "iso:country":"ES",
    "sg:address":"Carrer de Nord, 20",
    "sg:city":"Buvisa",
    "sg:orig_category":"Deportes N\u00c1uticos, Acu\u00c1ticos Y Subacu\u00c1ticos: Art\u00cdculos Y Equipo (al Por Menor)",
    "sg:phone":"+34 935 55 52 30",
    "sg:postcode":"08329",
    "sg:province":"Barcelona",
    "wof:name":"Ecamar Propulsores Marinos S.l.",
    "wof:placetype":"venue"
},
  "geometry": {"coordinates":[2.3216049671,41.4981689453],"type":"Point"}
}