{
  "type": "Feature",
  "properties": {
    "iso:country":"ES",
    "sg:address":"Calle de Martinez De La Riva, 114",
    "sg:city":"Madrid",
    "sg:orig_category":"Sociedades, Compa\u00d1\u00cdas Aseguradoras",
    "sg:phone":"+34 915 07 00 31",
    "sg:postcode":"28018",
    "sg:province":"Madrid",
    "wof:name":"Correduria De Seguros C.r.f. Rueda S.l.",
    "wof:placetype":"venue"
},
  "geometry": {"coordinates":[-3.664083004,40.3852767944],"type":"Point"}
}