{
  "type": "Feature",
  "properties": {
    "iso:country":"ES",
    "sg:address":"Carr Joanot Martorell, 28",
    "sg:city":"Quart Poblet",
    "sg:orig_category":"Marroquiner\u00cda (confecci\u00d3n)",
    "sg:phone":"+34 961 52 23 28",
    "sg:postcode":"46930",
    "sg:province":"Valencia",
    "wof:name":"Marti Segarra Rosa",
    "wof:placetype":"venue"
},
  "geometry": {"coordinates":[-0.443464011,39.4824104309],"type":"Point"}
}