{
  "type": "Feature",
  "properties": {
    "addr:full":"Pol Ind Plazaola Manzana D, 9 Aizoain Navarra 31195",
    "addr:housenumber":"manzana",
    "addr:postcode":"31195",
    "addr:street":"D;Navarra",
    "iso:country":"ES",
    "sg:address":"Pol Ind Plazaola Manzana D, 9",
    "sg:city":"Aizoain",
    "sg:orig_category":"Muebles",
    "sg:phone":"+34 948 30 37 97",
    "sg:postcode":"31195",
    "sg:province":"Navarra",
    "wof:name":"Apalauza Echarri Luis Miguel",
    "wof:placetype":"venue"
},
  "geometry": {"coordinates":[-1.6823375225,42.8511619568],"type":"Point"}
}