{
  "type": "Feature",
  "properties": {
    "addr:full":"Avda Menendez Pelayo, 3 Santa Cruz De Bezana Cantabria 39100",
    "addr:housenumber":"3",
    "addr:postcode":"39100",
    "addr:street":"Avda Menendez Pelayo",
    "iso:country":"ES",
    "sg:address":"Avda Menendez Pelayo, 3",
    "sg:city":"Santa Cruz De Bezana",
    "sg:orig_category":"Empresas De Carpinter\u00cda De Madera",
    "sg:phone":"+34 942 58 05 24",
    "sg:postcode":"39100",
    "sg:province":"Cantabria",
    "wof:name":"Mazo Grijuela Francisco Javier",
    "wof:placetype":"venue"
},
  "geometry": {"coordinates":[-3.9083800316,43.4606399536],"type":"Point"}
}