{
  "type": "Feature",
  "properties": {
    "addr:full":"Pla\u00c7 Mercat (del), 9 Algemesi Valencia 46680",
    "addr:postcode":"46680",
    "iso:country":"ES",
    "sg:address":"Pla\u00c7 Mercat (del), 9",
    "sg:city":"Algemesi",
    "sg:orig_category":"Supermercados Y Hipermercados",
    "sg:phone":"+34 962 48 13 94",
    "sg:postcode":"46680",
    "sg:province":"Valencia",
    "wof:name":"Consum Sociedad Cooperativa Limitada",
    "wof:placetype":"venue"
},
  "geometry": {"coordinates":[-0.4383490086,39.1962852478],"type":"Point"}
}