{
  "type": "Feature",
  "properties": {
    "iso:country":"ES",
    "sg:address":"Calle de San Jorge, 33",
    "sg:city":"Zaragoza",
    "sg:orig_category":"Plomeros",
    "sg:phone":"+34 976 29 01 56",
    "sg:postcode":"50001",
    "sg:province":"Zaragoza",
    "wof:name":"Fontaneros S. A.",
    "wof:placetype":"venue"
},
  "geometry": {"coordinates":[-0.8748080134,41.6513595581],"type":"Point"}
}