{
  "type": "Feature",
  "properties": {
    "addr:full":"Calle de Zaragoza, 24 Guadalajara Guadalajara 19005",
    "addr:postcode":"19005",
    "addr:street":"Calle De Zaragoza 24",
    "iso:country":"ES",
    "sg:address":"Calle de Zaragoza, 24",
    "sg:city":"Guadalajara",
    "sg:orig_category":"Ense\u00d1anza: Idiomas",
    "sg:phone":"+34 949 21 09 37",
    "sg:postcode":"19005",
    "sg:province":"Guadalajara",
    "wof:name":"Academia Universal Guadalajara S.%.",
    "wof:placetype":"venue"
},
  "geometry": {"coordinates":[-3.153845787,40.6363754272],"type":"Point"}
}