{
  "type": "Feature",
  "properties": {
    "iso:country":"ES",
    "sg:address":"Cno. Alqueria De Campaneta, 4",
    "sg:city":"Valencia",
    "sg:orig_category":"Artesan\u00cda",
    "sg:phone":"+34 961 85 46 69",
    "sg:postcode":"46019",
    "sg:province":"Valencia",
    "wof:name":"Torres Oriola Mario",
    "wof:placetype":"venue"
},
  "geometry": {"coordinates":[-0.3574840128,39.5228233337],"type":"Point"}
}