{
  "type": "Feature",
  "properties": {
    "addr:full":"Calle de Rodrigo De Caro, 23 Miranda Murcia 30319",
    "addr:housenumber":"23",
    "addr:postcode":"30319",
    "addr:street":"Calle De Rodrigo De Caro",
    "iso:country":"ES",
    "sg:address":"Calle de Rodrigo De Caro, 23",
    "sg:city":"Miranda",
    "sg:orig_category":"Molduras, Junquillos, Listones Y Molduras Perforadas",
    "sg:phone":"+34 968 16 96 35",
    "sg:postcode":"30319",
    "sg:province":"Murcia",
    "wof:name":"Angosto Hernandez Francisco",
    "wof:placetype":"venue"
},
  "geometry": {"coordinates":[-1.024335146,37.6826782227],"type":"Point"}
}