{
  "type": "Feature",
  "properties": {
    "addr:full":"Rua Jenaro De La Fuente, 7 Pardavila Pontevedra 36205",
    "addr:housenumber":"7",
    "addr:postcode":"36205",
    "addr:street":"Rua Jenaro De La Fuente",
    "iso:country":"ES",
    "sg:address":"Rua Jenaro De La Fuente, 7",
    "sg:city":"Pardavila",
    "sg:orig_category":"Platos Preparados Refrigerados (fabricaci\u00d3n, Al Por Mayor)",
    "sg:phone":"+34 986 25 15 06",
    "sg:postcode":"36205",
    "sg:province":"Pontevedra",
    "wof:name":"Sanchez Dominguez Severino",
    "wof:placetype":"venue"
},
  "geometry": {"coordinates":[-8.70246315,42.2290763855],"type":"Point"}
}