{
  "type": "Feature",
  "properties": {
    "iso:country":"ES",
    "sg:address":"Pol Industrial, 8",
    "sg:city":"Benissoda",
    "sg:orig_category":"Hilaturas, Hilos Y Actividades Relacionadas",
    "sg:phone":"+34 962 90 13 74",
    "sg:postcode":"46869",
    "sg:province":"Valencia",
    "wof:name":"Doblado Vidal Pla S.l.",
    "wof:placetype":"venue"
},
  "geometry": {"coordinates":[-0.4974539876,38.8378067017],"type":"Point"}
}