{
  "type": "Feature",
  "properties": {
    "iso:country":"ES",
    "sg:address":"Avda Cristobal De Murrieta, 15",
    "sg:city":"Santurtzi",
    "sg:orig_category":"Escayola Y Productos De Escayola (fabricaci\u00d3n, Al Por Mayor)",
    "sg:phone":"+34 944 93 79 48",
    "sg:postcode":"48980",
    "sg:province":"Vizcaya",
    "wof:name":"Escayolas Aurrera Sl",
    "wof:placetype":"venue"
},
  "geometry": {"coordinates":[-3.0402638912,43.3327636719],"type":"Point"}
}