{
  "type": "Feature",
  "properties": {
    "iso:country":"ES",
    "sg:address":"Calle de Mayor, 76",
    "sg:city":"Muniesa",
    "sg:orig_category":"Albergues",
    "sg:phone":"+34 978 81 01 71",
    "sg:postcode":"44780",
    "sg:province":"Teruel",
    "wof:name":"Hostal Rosamari S.c.",
    "wof:placetype":"venue"
},
  "geometry": {"coordinates":[-0.8111389875,41.0344200134],"type":"Point"}
}