{
  "type": "Feature",
  "properties": {
    "addr:full":"Calle de Coronel Ildefonso Valls De La Torre, 7 Arrecife Las Palmas 35500",
    "addr:housenumber":"7",
    "addr:postcode":"35500",
    "addr:street":"Calle De Coronel Ildefonso;La Torre",
    "iso:country":"ES",
    "sg:address":"Calle de Coronel Ildefonso Valls De La Torre, 7",
    "sg:city":"Arrecife",
    "sg:orig_category":"Peluqueros: De Se\u00d1oras",
    "sg:phone":"+34 928 80 21 12",
    "sg:postcode":"35500",
    "sg:province":"Las Palmas",
    "wof:name":"Gonzalez Betancort Agustin",
    "wof:placetype":"venue"
},
  "geometry": {"coordinates":[-13.5556325912,28.9589748383],"type":"Point"}
}