{
  "type": "Feature",
  "properties": {
    "addr:full":"Carr Domenec Cardenal, 3 Bellvis Lleida 25142",
    "addr:housenumber":"3",
    "addr:postcode":"25142",
    "addr:street":"Carr Domenec Cardenal",
    "iso:country":"ES",
    "sg:address":"Carr Domenec Cardenal, 3",
    "sg:city":"Bellvis",
    "sg:orig_category":"Forjas Y Altos Hornos",
    "sg:phone":"+34 973 71 63 90",
    "sg:postcode":"25142",
    "sg:province":"Lleida",
    "wof:name":"Merida Martinez Jose Antonio",
    "wof:placetype":"venue"
},
  "geometry": {"coordinates":[0.8143669963,41.6725845337],"type":"Point"}
}