{
  "type": "Feature",
  "properties": {
    "iso:country":"ES",
    "sg:address":"Calle de Secretario Padilla, 91",
    "sg:city":"Palmas De Gran Canaria",
    "sg:orig_category":"Confecci\u00d3n De Trajes Para Se\u00d1oras",
    "sg:phone":"+34 928 26 54 79",
    "sg:postcode":"35010",
    "sg:province":"Las Palmas",
    "wof:name":"Universal Union Enterprises S.l.",
    "wof:placetype":"venue"
},
  "geometry": {"coordinates":[-15.4420089722,28.1320800781],"type":"Point"}
}