{
  "type": "Feature",
  "properties": {
    "addr:full":"Carrer de Doctor Klein, 163 Cardedeu Barcelona 08440",
    "addr:housenumber":"163",
    "addr:postcode":"08440",
    "addr:street":"Carrer De Doctor Klein",
    "iso:country":"ES",
    "sg:address":"Carrer de Doctor Klein, 163",
    "sg:city":"Cardedeu",
    "sg:orig_category":"Empresas De Carpinter\u00cda De Madera",
    "sg:phone":"+34 938 46 16 03",
    "sg:postcode":"08440",
    "sg:province":"Barcelona",
    "wof:name":"Antoni Cortina S.l.",
    "wof:placetype":"venue"
},
  "geometry": {"coordinates":[2.362600565,41.6393966675],"type":"Point"}
}