{
  "type": "Feature",
  "properties": {
    "addr:full":"Calle de Algarve, 12 Jerez De La Frontera C\u00e1diz 11403",
    "addr:housenumber":"12",
    "addr:postcode":"11403",
    "addr:street":"Calle De Algarve",
    "iso:country":"ES",
    "sg:address":"Calle de Algarve, 12",
    "sg:city":"Jerez De La Frontera",
    "sg:orig_category":"Bisuter\u00cda, Joyer\u00cda, Relojer\u00cda (al Por Menor)",
    "sg:phone":"+34 956 34 36 25",
    "sg:postcode":"11403",
    "sg:province":"C\u00e1diz",
    "wof:name":"Monaco Y Vazquez S.a.",
    "wof:placetype":"venue"
},
  "geometry": {"coordinates":[-6.1374311447,36.6829681396],"type":"Point"}
}