{
  "type": "Feature",
  "properties": {
    "addr:full":"Calle de Ancha, 21 Yepes Toledo 45313",
    "addr:housenumber":"21",
    "addr:postcode":"45313",
    "addr:street":"Calle De Ancha",
    "iso:country":"ES",
    "sg:address":"Calle de Ancha, 21",
    "sg:city":"Yepes",
    "sg:orig_category":"Farmacias",
    "sg:phone":"+34 925 15 40 04",
    "sg:postcode":"45313",
    "sg:province":"Toledo",
    "wof:name":"Perez Vidal Maria Rosa",
    "wof:placetype":"venue"
},
  "geometry": {"coordinates":[-3.6243374348,39.9003868103],"type":"Point"}
}