{
  "type": "Feature",
  "properties": {
    "iso:country":"ES",
    "sg:address":"Calle de Ginzo De Limia, 56",
    "sg:city":"Madrid",
    "sg:orig_category":"Agencias De Viajes",
    "sg:phone":"+34 917 30 97 38",
    "sg:postcode":"28029",
    "sg:province":"Madrid",
    "sg:website":"www.viajescrisol.com",
    "wof:name":"Viajes Crisol",
    "wof:placetype":"venue"
},
  "geometry": {"coordinates":[-3.7045860291,40.4811897278],"type":"Point"}
}