{
  "type": "Feature",
  "properties": {
    "addr:full":"Calle de Calvo Sotelo, S/n Marin Pontevedra 36900",
    "addr:housenumber":"s / n",
    "addr:postcode":"36900",
    "addr:street":"Calle De Calvo Sotelo",
    "iso:country":"ES",
    "sg:address":"Calle de Calvo Sotelo, S/n",
    "sg:city":"Marin",
    "sg:orig_category":"Centros De Educaci\u00d3n Especial",
    "sg:phone":"+34 986 88 31 51",
    "sg:postcode":"36900",
    "sg:province":"Pontevedra",
    "wof:name":"Colexio Publico De Preescolar",
    "wof:placetype":"venue"
},
  "geometry": {"coordinates":[-8.6950397491,42.3926544189],"type":"Point"}
}