{
  "type": "Feature",
  "properties": {
    "addr:full":"Avda Enrique De Sena, 38 Santa Marta De Tormes Salamanca 37900",
    "addr:housenumber":"38",
    "addr:postcode":"37900",
    "addr:street":"Avda Enrique De Sena",
    "iso:country":"ES",
    "sg:address":"Avda Enrique De Sena, 38",
    "sg:city":"Santa Marta De Tormes",
    "sg:orig_category":"Venta, Instalaci\u00d3n, Reparaci\u00d3n De Antenas Para Televisi\u00d3n",
    "sg:phone":"+34 923 13 00 27",
    "sg:postcode":"37900",
    "sg:province":"Salamanca",
    "wof:name":"Hernandez Blanco Gregorio",
    "wof:placetype":"venue"
},
  "geometry": {"coordinates":[-5.628308773,40.9496612549],"type":"Point"}
}