{
  "type": "Feature",
  "properties": {
    "iso:country":"ES",
    "sg:address":"Avda Palma De Mallorca, 212",
    "sg:city":"Torremolinos",
    "sg:orig_category":"Inmobiliaria (agencias)",
    "sg:phone":"+34 952 05 31 03",
    "sg:postcode":"29620",
    "sg:province":"M\u00e1laga",
    "wof:name":"Jucarsol S.l.",
    "wof:placetype":"venue"
},
  "geometry": {"coordinates":[-4.502559185,36.6168022156],"type":"Point"}
}