{
  "type": "Feature",
  "properties": {
    "iso:country":"ES",
    "sg:address":"Carrer de Bartrina, 13",
    "sg:city":"Rubi",
    "sg:orig_category":"Alimentaci\u00d3n General (al Por Menor)",
    "sg:phone":"+34 935 87 20 70",
    "sg:postcode":"08191",
    "sg:province":"Barcelona",
    "wof:name":"Alimentacion Iglesias S.l.",
    "wof:placetype":"venue"
},
  "geometry": {"coordinates":[2.0371642113,41.4884872437],"type":"Point"}
}