{
  "type": "Feature",
  "properties": {
    "iso:country":"ES",
    "sg:address":"Grup Santa Margarita, 8",
    "sg:city":"Ortuella",
    "sg:orig_category":"Alimentaci\u00d3n General (al Por Menor)",
    "sg:phone":"+34 946 64 04 78",
    "sg:postcode":"48530",
    "sg:province":"Vizcaya",
    "wof:name":"Mengual Ruiz Ana Catalina",
    "wof:placetype":"venue"
},
  "geometry": {"coordinates":[-3.0463340282,43.3072128296],"type":"Point"}
}