{
  "type": "Feature",
  "properties": {
    "addr:full":"Pla\u00c7 Constitucio, De La, 1 Buger Islas Baleares 07311",
    "addr:housenumber":"1",
    "addr:postcode":"07311",
    "addr:street":"Plac\u0327 Constitucio De La",
    "iso:country":"ES",
    "sg:address":"Pla\u00c7 Constitucio, De La, 1",
    "sg:city":"Buger",
    "sg:orig_category":"Administraciones Regionales, Departamentales Y Locales",
    "sg:phone":"+34 971 51 61 46",
    "sg:postcode":"07311",
    "sg:province":"Islas Baleares",
    "wof:name":"Ajuntament De Buger",
    "wof:placetype":"venue"
},
  "geometry": {"coordinates":[2.9825558662,39.7631149292],"type":"Point"}
}