{
  "type": "Feature",
  "properties": {
    "addr:full":"Av. Scho Fuerte, S/n Iru\u00f1a Navarra 31011",
    "addr:postcode":"31011",
    "addr:street":"Av. Scho Fuerte S / N Irun\u0303A Navarra",
    "iso:country":"ES",
    "sg:address":"Av. Scho Fuerte, S/n",
    "sg:city":"Iru\u00f1a",
    "sg:orig_category":"Equipo Y Material Deportivo Y De Actividades Invernales Y De Monta\u00d1a",
    "sg:phone":"+34 948 17 22 55",
    "sg:postcode":"31011",
    "sg:province":"Navarra",
    "sg:website":"www.nmp.es/adsj-dke",
    "wof:name":"Agrupacion Deportiva San Juan",
    "wof:placetype":"venue"
},
  "geometry": {"coordinates":[-1.6578519344,42.8164863586],"type":"Point"}
}