{
  "type": "Feature",
  "properties": {
    "addr:full":"Calle de Conde Aranda, 5 Zaragoza Zaragoza 50004",
    "addr:housenumber":"5",
    "addr:postcode":"50004",
    "addr:street":"Calle De Conde Aranda",
    "iso:country":"ES",
    "sg:address":"Calle de Conde Aranda, 5",
    "sg:city":"Zaragoza",
    "sg:orig_category":"Abogados",
    "sg:phone":"+34 976 28 28 17",
    "sg:postcode":"50004",
    "sg:province":"Zaragoza",
    "wof:name":"Herrero Lozano Javier",
    "wof:placetype":"venue"
},
  "geometry": {"coordinates":[-0.8927813768,41.6560058594],"type":"Point"}
}