{
  "type": "Feature",
  "properties": {
    "addr:full":"Av Montseny, 13 Hostalric Girona 17450",
    "addr:housenumber":"13",
    "addr:postcode":"17450",
    "addr:street":"Av Montseny",
    "iso:country":"ES",
    "sg:address":"Av Montseny, 13",
    "sg:city":"Hostalric",
    "sg:orig_category":"Alimentaci\u00d3n General (al Por Menor)",
    "sg:phone":"+34 972 86 43 98",
    "sg:postcode":"17450",
    "sg:province":"Girona",
    "wof:name":"Pages Call Juan",
    "wof:placetype":"venue"
},
  "geometry": {"coordinates":[2.6253681183,41.7442588806],"type":"Point"}
}