{
  "type": "Feature",
  "properties": {
    "addr:full":"Calle de Ejercito Espa\u00d1ol, 21 Melilla Melilla 52001",
    "addr:housenumber":"21",
    "addr:postcode":"52001",
    "addr:street":"Calle De Ejercito Espan\u0303Ol",
    "iso:country":"ES",
    "sg:address":"Calle de Ejercito Espa\u00d1ol, 21",
    "sg:city":"Melilla",
    "sg:orig_category":"Estancos",
    "sg:phone":"+34 952 68 48 02",
    "sg:postcode":"52001",
    "sg:province":"Melilla",
    "wof:name":"Alonso Ortiz Antonio",
    "wof:placetype":"venue"
},
  "geometry": {"coordinates":[-2.9399600029,35.2940559387],"type":"Point"}
}