{
  "type": "Feature",
  "properties": {
    "addr:full":"Plaz Constitucion (la), 15 Roquetas Mar Almer\u00eda 04740",
    "addr:housenumber":"15",
    "addr:postcode":"04740",
    "addr:street":"Constitucion La",
    "iso:country":"ES",
    "sg:address":"Plaz Constitucion (la), 15",
    "sg:city":"Roquetas Mar",
    "sg:orig_category":"Cajas Para Embalar",
    "sg:phone":"+34 950 32 01 95",
    "sg:postcode":"04740",
    "sg:province":"Almer\u00eda",
    "sg:website":"www.cajamar.es",
    "wof:name":"Cajamar",
    "wof:placetype":"venue"
},
  "geometry": {"coordinates":[-2.6124989986,36.7638435364],"type":"Point"}
}