{
  "type": "Feature",
  "properties": {
    "addr:full":"La Palma, 1 Gran Tarajal Las Palmas 35620",
    "addr:housenumber":"1",
    "addr:postcode":"35620",
    "addr:street":"La Palma;Palmas",
    "iso:country":"ES",
    "sg:address":"La Palma, 1",
    "sg:city":"Gran Tarajal",
    "sg:orig_category":"Centros Empresariales",
    "sg:phone":"+34 928 16 25 35",
    "sg:postcode":"35620",
    "sg:province":"Las Palmas",
    "wof:name":"Gonzalez Ullen Jesus Manuel",
    "wof:placetype":"venue"
},
  "geometry": {"coordinates":[-14.0241603851,28.2093048096],"type":"Point"}
}