{
  "type": "Feature",
  "properties": {
    "iso:country":"ES",
    "sg:address":"Carrer de Miguel De Cervantes, 12",
    "sg:city":"Sant Feliu Llobregat",
    "sg:orig_category":"Fabrica De Cer\u00c1micas",
    "sg:phone":"+34 936 85 12 64",
    "sg:postcode":"08980",
    "sg:province":"Barcelona",
    "sg:website":"www.puiggros.com",
    "wof:name":"Puiggros Cardona Ramon",
    "wof:placetype":"venue"
},
  "geometry": {"coordinates":[2.0437779427,41.3799324036],"type":"Point"}
}