{
  "type": "Feature",
  "properties": {
    "addr:full":"Calle de Iberia, 37 Aguilas Murcia 30880",
    "addr:housenumber":"37",
    "addr:postcode":"30880",
    "addr:street":"Calle De Iberia",
    "iso:country":"ES",
    "sg:address":"Calle de Iberia, 37",
    "sg:city":"Aguilas",
    "sg:orig_category":"Peluquer\u00cdas, Peluquer\u00cda Mixta",
    "sg:phone":"+34 968 44 86 32",
    "sg:postcode":"30880",
    "sg:province":"Murcia",
    "wof:name":"Lopez Garcia Antonio",
    "wof:placetype":"venue"
},
  "geometry": {"coordinates":[-1.595500946,37.4003410339],"type":"Point"}
}