{
  "type": "Feature",
  "properties": {
    "addr:full":"Calle de Madrid, 20 Torrejon Ardoz Madrid 28850",
    "addr:housenumber":"20",
    "addr:postcode":"28850",
    "addr:street":"Calle De Madrid",
    "iso:country":"ES",
    "sg:address":"Calle de Madrid, 20",
    "sg:city":"Torrejon Ardoz",
    "sg:orig_category":"Bazares, Art\u00cdculos De Limpieza Y De Cocina (al Por Menor)",
    "sg:phone":"+34 916 77 77 91",
    "sg:postcode":"28850",
    "sg:province":"Madrid",
    "wof:name":"Lobo Rico Miguel",
    "wof:placetype":"venue"
},
  "geometry": {"coordinates":[-3.4785528183,40.4626541138],"type":"Point"}
}