{
  "type": "Feature",
  "properties": {
    "addr:full":"Carrer de Colomeres (les), 83 Gava Barcelona 08850",
    "addr:housenumber":"83",
    "addr:postcode":"08850",
    "addr:street":"Carrer De Colomeres Les",
    "iso:country":"ES",
    "sg:address":"Carrer de Colomeres (les), 83",
    "sg:city":"Gava",
    "sg:orig_category":"Mec\u00c1nico Del Autom\u00d3vil",
    "sg:phone":"+34 936 62 99 35",
    "sg:postcode":"08850",
    "sg:province":"Barcelona",
    "wof:name":"Ugalde Adan Andres",
    "wof:placetype":"venue"
},
  "geometry": {"coordinates":[2.0003509521,41.3054237366],"type":"Point"}
}