{
  "type": "Feature",
  "properties": {
    "iso:country":"ES",
    "sg:address":"Carr Pi, 81",
    "sg:city":"Blanes",
    "sg:orig_category":"Pescader\u00cdas (al Por Menor)",
    "sg:phone":"+34 972 35 16 42",
    "sg:postcode":"17300",
    "sg:province":"Girona",
    "wof:name":"Arenas Gibert Maria",
    "wof:placetype":"venue"
},
  "geometry": {"coordinates":[2.7881109715,41.6893844604],"type":"Point"}
}