{
  "type": "Feature",
  "properties": {
    "iso:country":"ES",
    "sg:address":"Carrer de Canyelles (de), 1",
    "sg:city":"Tarragona",
    "sg:orig_category":"Asesor\u00cda Fiscal Y Jur\u00cddica",
    "sg:phone":"+34 977 23 94 17",
    "sg:postcode":"43001",
    "sg:province":"Tarragona",
    "wof:name":"Vera Paredes Antoni",
    "wof:placetype":"venue"
},
  "geometry": {"coordinates":[1.2505700588,41.1164512634],"type":"Point"}
}