{
  "type": "Feature",
  "properties": {
    "addr:full":"Pol Ind La Ventilla, 36 Prado Del Rey C\u00e1diz 11660",
    "addr:housenumber":"36",
    "addr:postcode":"11660",
    "addr:street":"Ventilla",
    "iso:country":"ES",
    "sg:address":"Pol Ind La Ventilla, 36",
    "sg:city":"Prado Del Rey",
    "sg:orig_category":"Chapister\u00cda",
    "sg:phone":"+34 956 72 43 01",
    "sg:postcode":"11660",
    "sg:province":"C\u00e1diz",
    "wof:name":"Borrego Rodriguez Juan Luis",
    "wof:placetype":"venue"
},
  "geometry": {"coordinates":[-5.5557088852,36.7894134521],"type":"Point"}
}