{
  "type": "Feature",
  "properties": {
    "addr:full":"Calle de Goya, 1 Torres Cotillas Murcia 30565",
    "addr:housenumber":"1",
    "addr:postcode":"30565",
    "addr:street":"Calle De Goya",
    "iso:country":"ES",
    "sg:address":"Calle de Goya, 1",
    "sg:city":"Torres Cotillas",
    "sg:orig_category":"Fabricaci\u00d3n, Importaci\u00d3n De L\u00c1mparas Y Bombillas",
    "sg:phone":"+34 968 62 72 16",
    "sg:postcode":"30565",
    "sg:province":"Murcia",
    "wof:name":"Jimenez Sanchez Francisco Juan",
    "wof:placetype":"venue"
},
  "geometry": {"coordinates":[-1.2387429476,38.024356842],"type":"Point"}
}