{
  "type": "Feature",
  "properties": {
    "addr:full":"Ribas, 1 Alella Barcelona 08328",
    "addr:housenumber":"1",
    "addr:postcode":"08328",
    "addr:street":"Ribas",
    "iso:country":"ES",
    "sg:address":"Ribas, 1",
    "sg:city":"Alella",
    "sg:orig_category":"Flores Y Plantas Naturales (al Por Mayor)",
    "sg:phone":"+34 935 55 12 43",
    "sg:postcode":"08328",
    "sg:province":"Barcelona",
    "wof:name":"L'ensec S. A.",
    "wof:placetype":"venue"
},
  "geometry": {"coordinates":[2.292746067,41.4927978516],"type":"Point"}
}