{
  "type": "Feature",
  "properties": {
    "addr:full":"Avda Angel Romero, 11 Santa Cruz De Tenerife Santa Cruz De Tenerife 38009",
    "addr:housenumber":"11",
    "addr:postcode":"38009",
    "addr:street":"Avda Angel Romero",
    "iso:country":"ES",
    "sg:address":"Avda Angel Romero, 11",
    "sg:city":"Santa Cruz De Tenerife",
    "sg:orig_category":"Transporte En General",
    "sg:phone":"+34 922 21 76 36",
    "sg:postcode":"38009",
    "sg:province":"Santa Cruz De Tenerife",
    "wof:name":"Palau Echag\u00dce Jose",
    "wof:placetype":"venue"
},
  "geometry": {"coordinates":[-17.7755756378,28.6416091919],"type":"Point"}
}