{
  "type": "Feature",
  "properties": {
    "addr:full":"Pase Toyo (del), 136 Retamar Almer\u00eda 04130",
    "addr:housenumber":"136",
    "addr:postcode":"04130",
    "addr:street":"Retamar Almeri\u0301A",
    "iso:country":"ES",
    "sg:address":"Pase Toyo (del), 136",
    "sg:city":"Retamar",
    "sg:orig_category":"Inmobiliaria (agencias)",
    "sg:phone":"+34 950 20 82 20",
    "sg:postcode":"04130",
    "sg:province":"Almer\u00eda",
    "wof:name":"El Toyo Beach Grupo Inmobiliario S.l.",
    "wof:placetype":"venue"
},
  "geometry": {"coordinates":[-2.3529150486,36.8523406982],"type":"Point"}
}