{
  "type": "Feature",
  "properties": {
    "iso:country":"ES",
    "sg:address":"Calle de Real, 80",
    "sg:city":"Miguelturra",
    "sg:orig_category":"Cajas De Ahorro",
    "sg:phone":"+34 926 27 21 84",
    "sg:postcode":"13170",
    "sg:province":"Ciudad Real",
    "sg:website":"www.unicaja.es",
    "wof:name":"Unicaja",
    "wof:placetype":"venue"
},
  "geometry": {"coordinates":[-3.89407897,38.9677886963],"type":"Point"}
}