{
  "type": "Feature",
  "properties": {
    "addr:full":"Calle de Rosas, 1 Zaragoza Zaragoza 50009",
    "addr:housenumber":"1",
    "addr:postcode":"50009",
    "addr:street":"Calle De Rosas",
    "iso:country":"ES",
    "sg:address":"Calle de Rosas, 1",
    "sg:city":"Zaragoza",
    "sg:orig_category":"Administraciones Regionales, Departamentales Y Locales",
    "sg:phone":"+34 976 56 18 93",
    "sg:postcode":"50009",
    "sg:province":"Zaragoza",
    "wof:name":"Ayuntamiento De Zaragoza",
    "wof:placetype":"venue"
},
  "geometry": {"coordinates":[-0.9090129733,41.6304092407],"type":"Point"}
}