{
  "type": "Feature",
  "properties": {
    "addr:full":"Calle de Manzanares, S/n Antolinos Murcia 30740",
    "addr:housenumber":"s / n",
    "addr:postcode":"30740",
    "addr:street":"Calle De Manzanares",
    "iso:country":"ES",
    "sg:address":"Calle de Manzanares, S/n",
    "sg:city":"Antolinos",
    "sg:orig_category":"Asilos De Ancianos. Centros Privados",
    "sg:phone":"+34 968 18 38 47",
    "sg:postcode":"30740",
    "sg:province":"Murcia",
    "wof:name":"Edad Dorada Mensajeros De La Paz De Murcia",
    "wof:placetype":"venue"
},
  "geometry": {"coordinates":[-0.7932540178,37.8340911865],"type":"Point"}
}