{
  "type": "Feature",
  "properties": {
    "addr:full":"Rua Santiago De Guayaquil (de), 6 Santiago De Compostela La Coru\u00f1a 15702",
    "addr:housenumber":"6",
    "addr:postcode":"15702",
    "addr:street":"Rua Santiago De Guayaquil De;Corun\u0303A",
    "iso:country":"ES",
    "sg:address":"Rua Santiago De Guayaquil (de), 6",
    "sg:city":"Santiago De Compostela",
    "sg:orig_category":"Ingenier\u00cda, Centros De Estudios (diversos)",
    "sg:phone":"+34 981 58 87 38",
    "sg:postcode":"15702",
    "sg:province":"La Coru\u00f1a",
    "wof:name":"Comercial Palmeiro S.l",
    "wof:placetype":"venue"
},
  "geometry": {"coordinates":[-8.5439882278,42.8743019104],"type":"Point"}
}