{
  "type": "Feature",
  "properties": {
    "iso:country":"ES",
    "sg:address":"Calle de Valentin Sanz, 2",
    "sg:city":"Santa Cruz De Tenerife",
    "sg:orig_category":"Bisuter\u00cda, Joyer\u00cda, Relojer\u00cda (al Por Menor)",
    "sg:phone":"+34 922 24 31 97",
    "sg:postcode":"38003",
    "sg:province":"Santa Cruz De Tenerife",
    "wof:name":"Rodriguez Hernandez Miguel",
    "wof:placetype":"venue"
},
  "geometry": {"coordinates":[-16.2513179779,28.4656276703],"type":"Point"}
}