{
  "type": "Feature",
  "properties": {
    "iso:country":"ES",
    "sg:address":"Calle de Angel Guirao, 1",
    "sg:city":"Ceuti",
    "sg:orig_category":"Confiter\u00cdas, Chocolater\u00cdas (al Por Menor)",
    "sg:phone":"+34 968 69 03 11",
    "sg:postcode":"30562",
    "sg:province":"Murcia",
    "wof:name":"Conservas Mira S. A.",
    "wof:placetype":"venue"
},
  "geometry": {"coordinates":[-1.2715338469,38.079158783],"type":"Point"}
}