{
  "type": "Feature",
  "properties": {
    "iso:country":"ES",
    "sg:address":"Avda Mu\u00d1oz Grandes, 1",
    "sg:city":"Jaen",
    "sg:orig_category":"Fabricaci\u00d3n De Acumuladores Y De Pilas El\u00c9ctricas",
    "sg:phone":"+34 953 25 12 45",
    "sg:postcode":"23006",
    "sg:province":"Ja\u00e9n",
    "wof:name":"Sanchez Collado Fernando",
    "wof:placetype":"venue"
},
  "geometry": {"coordinates":[-3.7910969257,37.7771453857],"type":"Point"}
}