{
  "type": "Feature",
  "properties": {
    "addr:full":"Avda Villarrasa, 8 Rociana Condado Huelva 21720",
    "addr:housenumber":"8",
    "addr:postcode":"21720",
    "addr:street":"Avda Villarrasa",
    "iso:country":"ES",
    "sg:address":"Avda Villarrasa, 8",
    "sg:city":"Rociana Condado",
    "sg:orig_category":"Art\u00cdculos De Regalo (al Por Menor)",
    "sg:phone":"+34 959 41 62 32",
    "sg:postcode":"21720",
    "sg:province":"Huelva",
    "wof:name":"Caceres Raso Diego",
    "wof:placetype":"venue"
},
  "geometry": {"coordinates":[-6.5981302261,37.3097419739],"type":"Point"}
}