{
  "type": "Feature",
  "properties": {
    "addr:full":"Calle de Bernardos, S/n Villares Saz Cuenca 16442",
    "addr:housenumber":"s / n",
    "addr:postcode":"16442",
    "addr:street":"Calle De Bernardos",
    "iso:country":"ES",
    "sg:address":"Calle de Bernardos, S/n",
    "sg:city":"Villares Saz",
    "sg:orig_category":"Transportes Por V\u00cdas Navegables",
    "sg:phone":"+34 969 29 80 72",
    "sg:postcode":"16442",
    "sg:province":"Cuenca",
    "wof:name":"Mu\u00f1oz Hernaiz Jose Angel",
    "wof:placetype":"venue"
},
  "geometry": {"coordinates":[-2.50380373,39.8406677246],"type":"Point"}
}