{
  "type": "Feature",
  "properties": {
    "addr:full":"Calle de Albareda, 25 Palmas De Gran Canaria Las Palmas 35008",
    "addr:housenumber":"25",
    "addr:postcode":"35008",
    "addr:street":"Calle De Albareda",
    "iso:country":"ES",
    "sg:address":"Calle de Albareda, 25",
    "sg:city":"Palmas De Gran Canaria",
    "sg:orig_category":"Bisuter\u00cda, Joyer\u00cda, Relojer\u00cda (al Por Menor)",
    "sg:phone":"+34 928 26 14 77",
    "sg:postcode":"35008",
    "sg:province":"Las Palmas",
    "wof:name":"Curbelo Camejo Antonia",
    "wof:placetype":"venue"
},
  "geometry": {"coordinates":[-15.4306602478,28.1433944702],"type":"Point"}
}