{
  "type": "Feature",
  "properties": {
    "addr:full":"Av Prat De La Riba, 29 Tarragona Tarragona 43001",
    "addr:housenumber":"29",
    "addr:postcode":"43001",
    "addr:street":"Av Prat De La Riba",
    "iso:country":"ES",
    "sg:address":"Av Prat De La Riba, 29",
    "sg:city":"Tarragona",
    "sg:orig_category":"Molduras, Junquillos, Listones Y Molduras Perforadas",
    "sg:phone":"+34 977 21 10 24",
    "sg:postcode":"43001",
    "sg:province":"Tarragona",
    "wof:name":"Moreno Pozo Feliciano",
    "wof:placetype":"venue"
},
  "geometry": {"coordinates":[1.2465080023,41.1170272827],"type":"Point"}
}