{
  "type": "Feature",
  "properties": {
    "iso:country":"ES",
    "sg:address":"Goiballara, S/n",
    "sg:city":"Goiballara",
    "sg:orig_category":"Restaurantes",
    "sg:phone":"+34 943 69 02 51",
    "sg:postcode":"20159",
    "sg:province":"Guip\u00f9zcoa",
    "wof:name":"Aizpurua Soroa Jose Manuel",
    "wof:placetype":"venue"
},
  "geometry": {"coordinates":[-2.0742990971,43.1991958618],"type":"Point"}
}