{
  "type": "Feature",
  "properties": {
    "iso:country":"ES",
    "sg:address":"Barr Rio Dos Foles, 12",
    "sg:city":"Viveiro",
    "sg:orig_category":"Electricidad Veh\u00cdculo",
    "sg:phone":"+34 982 56 02 54",
    "sg:postcode":"27850",
    "sg:province":"Lugo",
    "wof:name":"Perez Coci\u00f1a Manuel",
    "wof:placetype":"venue"
},
  "geometry": {"coordinates":[-7.5923027992,43.6657371521],"type":"Point"}
}