{
  "type": "Feature",
  "properties": {
    "iso:country":"ES",
    "sg:address":"Avda Alcalde Caballero, S/n",
    "sg:city":"Zaragoza",
    "sg:orig_category":"Cooperativas Agr\u00cdcolas",
    "sg:phone":"+34 976 47 02 94",
    "sg:postcode":"50014",
    "sg:province":"Zaragoza",
    "wof:name":"Sociedad Cooperativa Del Campo De San Lamberto",
    "wof:placetype":"venue"
},
  "geometry": {"coordinates":[-0.8623539805,41.6738395691],"type":"Point"}
}