{
  "type": "Feature",
  "properties": {
    "addr:full":"Barr Bosque (el), 39 Loredo Cantabria 39140",
    "addr:housenumber":"39",
    "addr:postcode":"39140",
    "addr:street":"Bosque El",
    "iso:country":"ES",
    "sg:address":"Barr Bosque (el), 39",
    "sg:city":"Loredo",
    "sg:orig_category":"Arquitectos",
    "sg:phone":"+34 942 50 90 13",
    "sg:postcode":"39140",
    "sg:province":"Cantabria",
    "wof:name":"C.g.v. Arquitectos S.l.",
    "wof:placetype":"venue"
},
  "geometry": {"coordinates":[-3.739757061,43.4527320862],"type":"Point"}
}