{
  "type": "Feature",
  "properties": {
    "addr:full":"Plaz Castelao, 5 Rianxo La Coru\u00f1a 15920",
    "addr:housenumber":"5",
    "addr:postcode":"15920",
    "addr:street":"Plaz Castelao;La Corun\u0303A",
    "iso:country":"ES",
    "sg:address":"Plaz Castelao, 5",
    "sg:city":"Rianxo",
    "sg:orig_category":"Arquitectos",
    "sg:phone":"+34 981 86 64 89",
    "sg:postcode":"15920",
    "sg:province":"La Coru\u00f1a",
    "wof:name":"Losada Vicente Antonio",
    "wof:placetype":"venue"
},
  "geometry": {"coordinates":[-8.8172187805,42.6528091431],"type":"Point"}
}