{
  "type": "Feature",
  "properties": {
    "addr:full":"Carrer de Carles Roig (de), 16 Salou Tarragona 43840",
    "addr:housenumber":"16",
    "addr:postcode":"43840",
    "addr:street":"Carrer De Carles Roig De",
    "iso:country":"ES",
    "sg:address":"Carrer de Carles Roig (de), 16",
    "sg:city":"Salou",
    "sg:orig_category":"Enfermeras: Consultas, Atenci\u00d3n A Domicilio",
    "sg:phone":"+34 977 38 07 24",
    "sg:postcode":"43840",
    "sg:province":"Tarragona",
    "wof:name":"Garcia Ma\u00f1eru Alicia",
    "wof:placetype":"venue"
},
  "geometry": {"coordinates":[1.1255420446,41.0765533447],"type":"Point"}
}