{
  "type": "Feature",
  "properties": {
    "iso:country":"ES",
    "sg:address":"Calle de Mena Motina, 32",
    "sg:city":"Teruel",
    "sg:orig_category":"Empresas De Carpinter\u00cda De Madera",
    "sg:phone":"+34 978 61 12 49",
    "sg:postcode":"44003",
    "sg:province":"Teruel",
    "wof:name":"Carpinteria Mudejar S.l.",
    "wof:placetype":"venue"
},
  "geometry": {"coordinates":[-1.1017249823,40.3412208557],"type":"Point"}
}