{
  "type": "Feature",
  "properties": {
    "iso:country":"ES",
    "sg:address":"Calle de Arboleda, 23",
    "sg:city":"Getafe",
    "sg:orig_category":"Farmacias",
    "sg:phone":"+34 916 95 93 61",
    "sg:postcode":"28901",
    "sg:province":"Madrid",
    "wof:name":"Maria Alodia Gonzalez Gonzalez Y M. Madalena Colino Gonzalez C.b.",
    "wof:placetype":"venue"
},
  "geometry": {"coordinates":[-3.7261424065,40.3051567078],"type":"Point"}
}