{
  "type": "Feature",
  "properties": {
    "addr:full":"Calle de Torres (las), 10 Marchena Sevilla 41620",
    "addr:housenumber":"10",
    "addr:postcode":"41620",
    "addr:street":"Calle De Torres Las",
    "iso:country":"ES",
    "sg:address":"Calle de Torres (las), 10",
    "sg:city":"Marchena",
    "sg:orig_category":"Abogados",
    "sg:phone":"+34 954 84 40 32",
    "sg:postcode":"41620",
    "sg:province":"Sevilla",
    "wof:name":"Garcia Jimenez Ramon",
    "wof:placetype":"venue"
},
  "geometry": {"coordinates":[-5.41370821,37.3304252625],"type":"Point"}
}