{
  "type": "Feature",
  "properties": {
    "iso:country":"ES",
    "sg:address":"Queirua, S/n",
    "sg:city":"Queirua",
    "sg:orig_category":"Material Y Herramientas Agr\u00cdcolas",
    "sg:phone":"+34 981 68 10 44",
    "sg:postcode":"15689",
    "sg:province":"La Coru\u00f1a",
    "wof:name":"Morlan Castro Jose",
    "wof:placetype":"venue"
},
  "geometry": {"coordinates":[-8.4088382721,43.0253562927],"type":"Point"}
}