{
  "type": "Feature",
  "properties": {
    "addr:full":"Calle de Virgen De La Antigua, 11 Sevilla Sevilla 41011",
    "addr:housenumber":"11",
    "addr:postcode":"41011",
    "addr:street":"Calle De Virgen De La Antigua",
    "iso:country":"ES",
    "sg:address":"Calle de Virgen De La Antigua, 11",
    "sg:city":"Sevilla",
    "sg:orig_category":"Psic\u00d3logos",
    "sg:phone":"+34 954 45 01 25",
    "sg:postcode":"41011",
    "sg:province":"Sevilla",
    "wof:name":"Garcia-castrillon Armengou Frank",
    "wof:placetype":"venue"
},
  "geometry": {"coordinates":[-6.0002708435,37.3728713989],"type":"Point"}
}