{
  "type": "Feature",
  "properties": {
    "iso:country":"ES",
    "sg:address":"Calle de Ronda, S/n",
    "sg:city":"Carpio",
    "sg:orig_category":"Construcci\u00d3n De Edificios Residenciales Y No Residenciales",
    "sg:phone":"+34 983 86 31 45",
    "sg:postcode":"47470",
    "sg:province":"Valladolid",
    "wof:name":"Marcos Rodriguez Antonio",
    "wof:placetype":"venue"
},
  "geometry": {"coordinates":[-5.1110491753,41.2116203308],"type":"Point"}
}