{
  "type": "Feature",
  "properties": {
    "addr:full":"Calle de Rio Alhama, 1 Logro\u00f1o La Rioja 26006",
    "addr:housenumber":"1",
    "addr:postcode":"26006",
    "addr:street":"Calle De Rio Alhama;Rioja",
    "iso:country":"ES",
    "sg:address":"Calle de Rio Alhama, 1",
    "sg:city":"Logro\u00f1o",
    "sg:orig_category":"Centros De Educaci\u00d3n Especial",
    "sg:phone":"+34 941 23 22 09",
    "sg:postcode":"26006",
    "sg:province":"La Rioja",
    "wof:name":"Comunidad Autonoma De La Rioja",
    "wof:placetype":"venue"
},
  "geometry": {"coordinates":[-2.4267389774,42.4525413513],"type":"Point"}
}