{
  "type": "Feature",
  "properties": {
    "addr:full":"Carrer de Marques Senia, 32 Palma Islas Baleares 07014",
    "addr:housenumber":"32",
    "addr:postcode":"07014",
    "addr:street":"Carrer De Marques Senia",
    "iso:country":"ES",
    "sg:address":"Carrer de Marques Senia, 32",
    "sg:city":"Palma",
    "sg:orig_category":"Tintes (fabricaci\u00d3n, Al Por Mayor)",
    "sg:phone":"+34 971 73 40 98",
    "sg:postcode":"07014",
    "sg:province":"Islas Baleares",
    "wof:name":"Ramis Ramis Maria",
    "wof:placetype":"venue"
},
  "geometry": {"coordinates":[2.6304008961,39.5685920715],"type":"Point"}
}