{
  "type": "Feature",
  "properties": {
    "addr:full":"Carrer de Sant Crist, 23 Barcelona Barcelona 08014",
    "addr:housenumber":"23",
    "addr:postcode":"08014",
    "addr:street":"Carrer De Sant Crist",
    "iso:country":"ES",
    "sg:address":"Carrer de Sant Crist, 23",
    "sg:city":"Barcelona",
    "sg:orig_category":"Asesor\u00cda Para La Organizaci\u00d3n Y Gesti\u00d3n Del Transporte",
    "sg:phone":"+34 934 21 62 00",
    "sg:postcode":"08014",
    "sg:province":"Barcelona",
    "wof:name":"Transportes Guevara Sociedad Cooperativa Catalana Limitada",
    "wof:placetype":"venue"
},
  "geometry": {"coordinates":[2.1396288872,41.3746528625],"type":"Point"}
}