{
  "type": "Feature",
  "properties": {
    "iso:country":"ES",
    "sg:address":"Carrer de Marques Fontsanta, 6",
    "sg:city":"Palma",
    "sg:orig_category":"Prot\u00c9sicos Dentales",
    "sg:phone":"+34 971 46 11 03",
    "sg:postcode":"07005",
    "sg:province":"Islas Baleares",
    "wof:name":"Cerda Bagur Miguel",
    "wof:placetype":"venue"
},
  "geometry": {"coordinates":[2.6551849842,39.5756912231],"type":"Point"}
}