{
  "type": "Feature",
  "properties": {
    "addr:full":"Av. Platja D'aro, 275 S'agaro Girona 17248",
    "addr:housenumber":"275",
    "addr:postcode":"17248",
    "addr:street":"Av. Platja D'Aro",
    "iso:country":"ES",
    "sg:address":"Av. Platja D'aro, 275",
    "sg:city":"S'agaro",
    "sg:orig_category":"Veh\u00cdculos De Ocasi\u00d3n",
    "sg:phone":"+34 972 32 62 22",
    "sg:postcode":"17248",
    "sg:province":"Girona",
    "wof:name":"Western Team S.l.",
    "wof:placetype":"venue"
},
  "geometry": {"coordinates":[3.0486075878,41.7969818115],"type":"Point"}
}