{
  "type": "Feature",
  "properties": {
    "iso:country":"ES",
    "sg:address":"Calle de Flores, 2",
    "sg:city":"Zaragoza",
    "sg:orig_category":"Cervecer\u00cdas",
    "sg:phone":"+34 976 49 40 12",
    "sg:postcode":"50013",
    "sg:province":"Zaragoza",
    "wof:name":"Terruca Ruiz Jose Angel",
    "wof:placetype":"venue"
},
  "geometry": {"coordinates":[-0.8697980046,41.6395225525],"type":"Point"}
}