{
  "type": "Feature",
  "properties": {
    "iso:country":"ES",
    "sg:address":"Calle de Manuel Lasala, 2",
    "sg:city":"Zaragoza",
    "sg:orig_category":"Alquiler De Veh\u00cdculos: Turismos Y Utilitarios",
    "sg:phone":"+34 976 55 18 68",
    "sg:postcode":"50006",
    "sg:province":"Zaragoza",
    "wof:name":"Procas Diez Vicente",
    "wof:placetype":"venue"
},
  "geometry": {"coordinates":[-0.8904849887,41.6405029297],"type":"Point"}
}