{
  "type": "Feature",
  "properties": {
    "addr:full":"Calle de Santa Teresa De Jesus, 47 Zaragoza Zaragoza 50006",
    "addr:housenumber":"47",
    "addr:postcode":"50006",
    "addr:street":"Calle De Santa Teresa De Jesus",
    "iso:country":"ES",
    "sg:address":"Calle de Santa Teresa De Jesus, 47",
    "sg:city":"Zaragoza",
    "sg:orig_category":"Laboratorios",
    "sg:phone":"+34 976 30 69 10",
    "sg:postcode":"50006",
    "sg:province":"Zaragoza",
    "sg:website":"www.cagt.arrakis.es",
    "wof:name":"Citogen S.l.",
    "wof:placetype":"venue"
},
  "geometry": {"coordinates":[-0.8945559859,41.6388473511],"type":"Point"}
}