{
  "type": "Feature",
  "properties": {
    "addr:full":"Calle de Constitucion, 6 Altea Alicante 03590",
    "addr:housenumber":"6",
    "addr:postcode":"03590",
    "addr:street":"Calle De Constitucion",
    "iso:country":"ES",
    "sg:address":"Calle de Constitucion, 6",
    "sg:city":"Altea",
    "sg:orig_category":"M\u00c9dicos: Ginecolog\u00cda Y Obstetricia",
    "sg:phone":"+34 965 84 44 52",
    "sg:postcode":"03590",
    "sg:province":"Alicante",
    "wof:name":"Luengo Rodriguez De Ledesma Jose",
    "wof:placetype":"venue"
},
  "geometry": {"coordinates":[-0.0470930003,38.601398468],"type":"Point"}
}