{
  "type": "Feature",
  "properties": {
    "iso:country":"ES",
    "sg:address":"Crta Forestal Siles-s Espada, Km. 0011,0",
    "sg:city":"Siles",
    "sg:orig_category":"Explotaci\u00d3n De Bosques",
    "sg:phone":"+34 953 12 63 00",
    "sg:postcode":"23380",
    "sg:province":"Ja\u00e9n",
    "wof:name":"Explotaciones Siles S.l.",
    "wof:placetype":"venue"
},
  "geometry": {"coordinates":[-2.5846040249,38.389289856],"type":"Point"}
}