{
  "type": "Feature",
  "properties": {
    "iso:country":"ES",
    "sg:address":"Calle de Ignacio Ellacuria, 12",
    "sg:city":"Madrid",
    "sg:orig_category":"Aparatos De Medida, Control, Regulaci\u00d3n Y Detecci\u00d3n",
    "sg:phone":"+34 913 56 19 58",
    "sg:postcode":"28017",
    "sg:province":"Madrid",
    "sg:website":"www..tecnimetalsa.com",
    "wof:name":"Tecnicas De Medida Y Metalografia S. A.",
    "wof:placetype":"venue"
},
  "geometry": {"coordinates":[-3.6569356918,40.428604126],"type":"Point"}
}