{
  "type": "Feature",
  "properties": {
    "iso:country":"ES",
    "sg:address":"Calle de Coli Escalona, Leonardo, 48",
    "sg:city":"Sabi\u00f1anigo",
    "sg:orig_category":"Partidos Pol\u00cdticos",
    "sg:phone":"+34 974 48 31 64",
    "sg:postcode":"22600",
    "sg:province":"Huesca",
    "wof:name":"Partido Socialista Obrero Espa\u00f1ol",
    "wof:placetype":"venue"
},
  "geometry": {"coordinates":[-0.3670453131,42.5190353394],"type":"Point"}
}