{
  "type": "Feature",
  "properties": {
    "iso:country":"ES",
    "sg:address":"Calle de Zu\u00d1iga, 10",
    "sg:city":"Valladolid",
    "sg:orig_category":"Ropa Para Se\u00d1oras (al Por Menor)",
    "sg:phone":"+34 983 35 57 42",
    "sg:postcode":"47001",
    "sg:province":"Valladolid",
    "wof:name":"Sanz Andres Francisco Javier",
    "wof:placetype":"venue"
},
  "geometry": {"coordinates":[-4.7295260429,41.6505813599],"type":"Point"}
}