{
  "type": "Feature",
  "properties": {
    "iso:country":"ES",
    "sg:address":"Calle de Ricardo Del Arco, 20",
    "sg:city":"Huesca",
    "sg:orig_category":"M\u00c9dicos: Estomatolog\u00cda",
    "sg:phone":"+34 974 22 76 51",
    "sg:postcode":"22004",
    "sg:province":"Huesca",
    "wof:name":"Saso Bosque Maria Josefa",
    "wof:placetype":"venue"
},
  "geometry": {"coordinates":[-0.4184690118,42.1373405457],"type":"Point"}
}