{
  "type": "Feature",
  "properties": {
    "addr:full":"Calle de Ciudadela, 3 Bilbao Vizcaya 48002",
    "addr:housenumber":"3",
    "addr:postcode":"48002",
    "addr:street":"Calle De Ciudadela",
    "iso:country":"ES",
    "sg:address":"Calle de Ciudadela, 3",
    "sg:city":"Bilbao",
    "sg:orig_category":"Ropa Para Ni\u00d1os (al Por Menor)",
    "sg:phone":"+34 944 10 36 98",
    "sg:postcode":"48002",
    "sg:province":"Vizcaya",
    "wof:name":"Milagros Egido Molano",
    "wof:placetype":"venue"
},
  "geometry": {"coordinates":[-2.9454593658,43.2524795532],"type":"Point"}
}