{
  "type": "Feature",
  "properties": {
    "iso:country":"ES",
    "sg:address":"Vista Bella, S/n",
    "sg:city":"Campohermoso",
    "sg:orig_category":"Frutas Y Legumbres Frescas (al Por Mayor)",
    "sg:phone":"+34 950 38 60 85",
    "sg:postcode":"04110",
    "sg:province":"Almer\u00eda",
    "wof:name":"Union De Agricultores S.a.",
    "wof:placetype":"venue"
},
  "geometry": {"coordinates":[-2.1324241161,36.9409065247],"type":"Point"}
}