{
  "type": "Feature",
  "properties": {
    "iso:country":"ES",
    "sg:address":"Calle de Apolonio Morales, 21",
    "sg:city":"Madrid",
    "sg:orig_category":"Arquitectos",
    "sg:phone":"+34 913 59 98 69",
    "sg:postcode":"28036",
    "sg:province":"Madrid",
    "wof:name":"Toro Arevalo Gisele",
    "wof:placetype":"venue"
},
  "geometry": {"coordinates":[-3.6817348003,40.4635810852],"type":"Point"}
}