{
  "type": "Feature",
  "properties": {
    "addr:full":"Calle de Sancho Y Gil, 2 Zaragoza Zaragoza 50001",
    "addr:housenumber":"2",
    "addr:postcode":"50001",
    "addr:street":"Calle De Sancho Y Gil",
    "iso:country":"ES",
    "sg:address":"Calle de Sancho Y Gil, 2",
    "sg:city":"Zaragoza",
    "sg:orig_category":"Sociedades, Compa\u00d1\u00cdas Aseguradoras",
    "sg:phone":"+34 976 30 13 60",
    "sg:postcode":"50001",
    "sg:province":"Zaragoza",
    "wof:name":"Maz Mutua De Accidentes De Trabajo Y Enfermedades De La S.s. N 11",
    "wof:placetype":"venue"
},
  "geometry": {"coordinates":[-0.878238976,41.6499900818],"type":"Point"}
}