{
  "type": "Feature",
  "properties": {
    "addr:full":"Avda Madrid De, 30 Donostia-san Sebastian Guip\u00f9zcoa 20011",
    "addr:housenumber":"30",
    "addr:postcode":"20011",
    "addr:street":"Avda Madrid De",
    "iso:country":"ES",
    "sg:address":"Avda Madrid De, 30",
    "sg:city":"Donostia-san Sebastian",
    "sg:orig_category":"Molduras, Junquillos, Listones Y Molduras Perforadas",
    "sg:phone":"+34 943 45 15 47",
    "sg:postcode":"20011",
    "sg:province":"Guip\u00f9zcoa",
    "wof:name":"Call Phone S.l.",
    "wof:placetype":"venue"
},
  "geometry": {"coordinates":[-1.9756779671,43.3032112122],"type":"Point"}
}