{
  "type": "Feature",
  "properties": {
    "iso:country":"ES",
    "sg:address":"Carr Santa Rita, S/n",
    "sg:city":"Aldaia",
    "sg:orig_category":"Reposter\u00cdas",
    "sg:phone":"+34 961 51 09 87",
    "sg:postcode":"46960",
    "sg:province":"Valencia",
    "wof:name":"Maroto Ortu\u00f1o Margarita",
    "wof:placetype":"venue"
},
  "geometry": {"coordinates":[-0.4627639949,39.4674682617],"type":"Point"}
}