{
  "type": "Feature",
  "properties": {
    "addr:full":"Sol, 114 Sedavi Valencia 46910",
    "addr:housenumber":"114",
    "addr:postcode":"46910",
    "addr:street":"Sedavi",
    "iso:country":"ES",
    "sg:address":"Sol, 114",
    "sg:city":"Sedavi",
    "sg:orig_category":"Promotores Constructores",
    "sg:phone":"+34 963 75 47 94",
    "sg:postcode":"46910",
    "sg:province":"Valencia",
    "wof:name":"Albiach Baixauli Jose",
    "wof:placetype":"venue"
},
  "geometry": {"coordinates":[-0.3832513094,39.4259223938],"type":"Point"}
}