{
  "type": "Feature",
  "properties": {
    "addr:full":"Calle de Asuncion, 9 Villar De Peralonso Salamanca 37147",
    "addr:housenumber":"9",
    "addr:postcode":"37147",
    "addr:street":"Calle De Asuncion",
    "iso:country":"ES",
    "sg:address":"Calle de Asuncion, 9",
    "sg:city":"Villar De Peralonso",
    "sg:orig_category":"Iglesia Cat\u00d3lica",
    "sg:phone":"+34 923 51 80 18",
    "sg:postcode":"37147",
    "sg:province":"Salamanca",
    "wof:name":"Parroquia De La Asuncion",
    "wof:placetype":"venue"
},
  "geometry": {"coordinates":[-6.2223644257,41.0314369202],"type":"Point"}
}