{
  "type": "Feature",
  "properties": {
    "iso:country":"ES",
    "sg:address":"Calle de Ezequiel Solana, 6",
    "sg:city":"Madrid",
    "sg:orig_category":"Contables",
    "sg:phone":"+34 913 67 89 07",
    "sg:postcode":"28017",
    "sg:province":"Madrid",
    "wof:name":"Asesoria Integral De Empresas Castilla S.l.",
    "wof:placetype":"venue"
},
  "geometry": {"coordinates":[-3.6469938755,40.4332389832],"type":"Point"}
}