{
  "type": "Feature",
  "properties": {
    "addr:full":"Disem Rural, 92 Idiazabal Guip\u00f9zcoa 20213",
    "addr:housenumber":"92",
    "addr:postcode":"20213",
    "addr:street":"Disem Rural;Guipu\u0300Zcoa",
    "iso:country":"ES",
    "sg:address":"Disem Rural, 92",
    "sg:city":"Idiazabal",
    "sg:orig_category":"Producci\u00d3n De Abonos Y De Fertilizantes",
    "sg:phone":"+34 943 18 75 67",
    "sg:postcode":"20213",
    "sg:province":"Guip\u00f9zcoa",
    "wof:name":"Turbas Granja Fatima S.l.",
    "wof:placetype":"venue"
},
  "geometry": {"coordinates":[-2.1205339432,43.0957565308],"type":"Point"}
}