{
  "type": "Feature",
  "properties": {
    "iso:country":"ES",
    "sg:address":"Av Rei Jaume I, 107",
    "sg:city":"Santa Pon\u00c7a",
    "sg:orig_category":"Asesor\u00cda Fiscal Y Jur\u00cddica",
    "sg:phone":"+34 971 69 52 03",
    "sg:postcode":"07180",
    "sg:province":"Islas Baleares",
    "wof:name":"Forteza Gari Margarita",
    "wof:placetype":"venue"
},
  "geometry": {"coordinates":[2.4842739105,39.5160675049],"type":"Point"}
}