{
  "type": "Feature",
  "properties": {
    "addr:full":"Calle de Moros, 22 Gijon Asturias 33206",
    "addr:housenumber":"22",
    "addr:postcode":"33206",
    "addr:street":"Calle De Moros",
    "iso:country":"ES",
    "sg:address":"Calle de Moros, 22",
    "sg:city":"Gijon",
    "sg:orig_category":"Fabricaci\u00d3n, Venta De Productos Base Farmac\u00c9uticos",
    "sg:phone":"+34 985 35 04 62",
    "sg:postcode":"33206",
    "sg:province":"Asturias",
    "wof:name":"Garitano Elgueta Miren Amaia",
    "wof:placetype":"venue"
},
  "geometry": {"coordinates":[-5.6630249023,43.5409202576],"type":"Point"}
}