{
  "type": "Feature",
  "properties": {
    "iso:country":"ES",
    "sg:address":"Calle de Alvaro De Lugo, 7",
    "sg:city":"Medina Campo",
    "sg:orig_category":"Molduras, Junquillos, Listones Y Molduras Perforadas",
    "sg:phone":"+34 983 81 10 61",
    "sg:postcode":"47400",
    "sg:province":"Valladolid",
    "wof:name":"Bar Puerta El Sol C.b.",
    "wof:placetype":"venue"
},
  "geometry": {"coordinates":[-4.9166340828,41.3029251099],"type":"Point"}
}