{
  "type": "Feature",
  "properties": {
    "iso:country":"ES",
    "sg:address":"Carrer de Felipe De Paz, 12",
    "sg:city":"Barcelona",
    "sg:orig_category":"Inform\u00c1tica: Soportes De Informaci\u00d3n, Suministros & Accesorios",
    "sg:phone":"+34 934 90 17 42",
    "sg:postcode":"08028",
    "sg:province":"Barcelona",
    "wof:name":"Delangue  Nicole",
    "wof:placetype":"venue"
},
  "geometry": {"coordinates":[2.1253590584,41.3792724609],"type":"Point"}
}