{
  "type": "Feature",
  "properties": {
    "iso:country":"ES",
    "sg:address":"Calle de Industrial, 13",
    "sg:city":"Coru\u00d1a",
    "sg:orig_category":"Fabricaci\u00d3n De Capiteles",
    "sg:phone":"+34 981 14 54 64",
    "sg:postcode":"15005",
    "sg:province":"La Coru\u00f1a",
    "sg:website":"www.martincasal.com",
    "wof:name":"Manufacturas Martin Casal S. L.",
    "wof:placetype":"venue"
},
  "geometry": {"coordinates":[-8.4103546143,43.3611297607],"type":"Point"}
}