{
  "type": "Feature",
  "properties": {
    "iso:country":"ES",
    "sg:address":"Rua Isabel Ii, 11",
    "sg:city":"Cambados",
    "sg:orig_category":"Fotocopias, Reprograf\u00cda",
    "sg:phone":"+34 986 52 10 40",
    "sg:postcode":"36630",
    "sg:province":"Pontevedra",
    "wof:name":"Copistar C.b.",
    "wof:placetype":"venue"
},
  "geometry": {"coordinates":[-8.8142089844,42.514465332],"type":"Point"}
}