{
  "type": "Feature",
  "properties": {
    "addr:full":"Calle de Huelva, 3 Fuengirola M\u00e1laga 29640",
    "addr:housenumber":"3",
    "addr:postcode":"29640",
    "addr:street":"Calle De Huelva;Ma\u0301Laga",
    "iso:country":"ES",
    "sg:address":"Calle de Huelva, 3",
    "sg:city":"Fuengirola",
    "sg:orig_category":"Arreglo, Reparaci\u00d3n, Piezas Sueltas De Televisi\u00d3n, V\u00cddeo, Hi",
    "sg:phone":"+34 952 46 20 72",
    "sg:postcode":"29640",
    "sg:province":"M\u00e1laga",
    "wof:name":"Costajosol S.l.",
    "wof:placetype":"venue"
},
  "geometry": {"coordinates":[-4.6275420189,36.5394859314],"type":"Point"}
}