{
  "type": "Feature",
  "properties": {
    "iso:country":"ES",
    "sg:address":"Calle de Tejares, 6",
    "sg:city":"Albacete",
    "sg:orig_category":"Impuestos, Tesoro P\u00dablico",
    "sg:phone":"+34 967 52 45 17",
    "sg:postcode":"02002",
    "sg:province":"Albacete",
    "sg:website":"www.valmesa.es",
    "wof:name":"Valoraciones Mediterraneo S.a.",
    "wof:placetype":"venue"
},
  "geometry": {"coordinates":[-1.8539999723,38.9921302795],"type":"Point"}
}