{
  "type": "Feature",
  "properties": {
    "iso:country":"ES",
    "sg:address":"Avda Constitucion, 8",
    "sg:city":"Gijon",
    "sg:orig_category":"Abogados",
    "sg:phone":"+34 985 34 90 86",
    "sg:postcode":"33207",
    "sg:province":"Asturias",
    "wof:name":"Fano Herrero Florentino",
    "wof:placetype":"venue"
},
  "geometry": {"coordinates":[-5.6655569077,43.5371627808],"type":"Point"}
}