{
  "type": "Feature",
  "properties": {
    "addr:full":"Carrer de Segle Xx, 15 Barcelona Barcelona 08041",
    "addr:housenumber":"15",
    "addr:postcode":"08041",
    "addr:street":"Carrer De Segle Xx",
    "iso:country":"ES",
    "sg:address":"Carrer de Segle Xx, 15",
    "sg:city":"Barcelona",
    "sg:orig_category":"Comercio De Piezas De Recambio Y De Accesorios De Veh\u00cdculos, Veh\u00cdculos Industriales",
    "sg:phone":"+34 933 51 75 48",
    "sg:postcode":"08041",
    "sg:province":"Barcelona",
    "wof:name":"Guinardo S.l.",
    "wof:placetype":"venue"
},
  "geometry": {"coordinates":[2.1778490543,41.4225082397],"type":"Point"}
}