{
  "type": "Feature",
  "properties": {
    "addr:full":"Sis Quarts, 8 Onda Castell\u00f3n 12200",
    "addr:housenumber":"8",
    "addr:postcode":"12200",
    "addr:street":"Quarts;Castello\u0301N",
    "iso:country":"ES",
    "sg:address":"Sis Quarts, 8",
    "sg:city":"Onda",
    "sg:orig_category":"Suministros Y Materiales Industriales",
    "sg:phone":"+34 964 34 15 34",
    "sg:postcode":"12200",
    "sg:province":"Castell\u00f3n",
    "wof:name":"Pisa Productos Industriales S.l.",
    "wof:placetype":"venue"
},
  "geometry": {"coordinates":[-0.1967860013,39.9514389038],"type":"Point"}
}