{
  "type": "Feature",
  "properties": {
    "iso:country":"ES",
    "sg:address":"Calle de Relator, 96",
    "sg:city":"Sevilla",
    "sg:orig_category":"Cooperativas Agr\u00cdcolas",
    "sg:phone":"+34 954 90 06 60",
    "sg:postcode":"41003",
    "sg:province":"Sevilla",
    "wof:name":"Asociacion Centro De Iniciativas Para La Cooperacion Bata",
    "wof:placetype":"venue"
},
  "geometry": {"coordinates":[-5.9886879921,37.4005622864],"type":"Point"}
}