{
  "type": "Feature",
  "properties": {
    "iso:country":"ES",
    "sg:address":"Calle de Sucre, 15",
    "sg:city":"Palmas De Gran Canaria",
    "sg:orig_category":"Servicios De Telecomunicaciones",
    "sg:phone":"+34 928 47 54 47",
    "sg:postcode":"35008",
    "sg:province":"Las Palmas",
    "wof:name":"Avanzit Telecom S.l.",
    "wof:placetype":"venue"
},
  "geometry": {"coordinates":[-15.4126653671,28.1696929932],"type":"Point"}
}