{
  "type": "Feature",
  "properties": {
    "addr:full":"Calle de Empedrada, 10 Rambla C\u00f3rdoba 14540",
    "addr:housenumber":"10",
    "addr:postcode":"14540",
    "addr:street":"Calle De Empedrada;Co\u0301Rdoba",
    "iso:country":"ES",
    "sg:address":"Calle de Empedrada, 10",
    "sg:city":"Rambla",
    "sg:orig_category":"Abogados",
    "sg:phone":"+34 957 68 25 14",
    "sg:postcode":"14540",
    "sg:province":"C\u00f3rdoba",
    "wof:name":"Tallon Y Aguado Abogado Asesores S.l.",
    "wof:placetype":"venue"
},
  "geometry": {"coordinates":[-4.7395558357,37.6064414978],"type":"Point"}
}