{
  "type": "Feature",
  "properties": {
    "iso:country":"ES",
    "sg:address":"Praz Escritor Camilo Jose Cela, S/n",
    "sg:city":"Ferrol",
    "sg:orig_category":"Ense\u00d1anza, Formaci\u00d3n Profesional: Aprendizaje",
    "sg:phone":"+34 981 33 05 30",
    "sg:postcode":"15403",
    "sg:province":"A Coru\u00f1a",
    "wof:name":"Servicio Publico De Empleo Estatal-dron. Prov. La Coru?a",
    "wof:placetype":"venue"
},
  "geometry": {"coordinates":[-8.2273387909,43.4868507385],"type":"Point"}
}