{
  "type": "Feature",
  "properties": {
    "iso:country":"ES",
    "sg:address":"Carr Pere Frances, 25",
    "sg:city":"Eivissa",
    "sg:orig_category":"Peluqueros: De Se\u00d1oras",
    "sg:phone":"+34 971 31 50 60",
    "sg:postcode":"07800",
    "sg:province":"Islas Baleares",
    "wof:name":"Mu\u00f1oz Ripoll Catalina",
    "wof:placetype":"venue"
},
  "geometry": {"coordinates":[1.4314889908,38.9111442566],"type":"Point"}
}