{
  "type": "Feature",
  "properties": {
    "addr:full":"Calle de Viteri, 2 Errenteria Guip\u00f9zcoa 20100",
    "addr:housenumber":"2",
    "addr:postcode":"20100",
    "addr:street":"Calle De Viteri;Guipu\u0300Zcoa",
    "iso:country":"ES",
    "sg:address":"Calle de Viteri, 2",
    "sg:city":"Errenteria",
    "sg:orig_category":"Confiter\u00cdas, Chocolater\u00cdas (al Por Menor)",
    "sg:phone":"+34 943 52 47 44",
    "sg:postcode":"20100",
    "sg:province":"Guip\u00f9zcoa",
    "wof:name":"Gurruchaga Arriola Jaione",
    "wof:placetype":"venue"
},
  "geometry": {"coordinates":[-1.898630023,43.3131980896],"type":"Point"}
}