{
  "type": "Feature",
  "properties": {
    "addr:full":"Carr Joan Monjo March, 4 Santa Margalida Islas Baleares 07450",
    "addr:housenumber":"4",
    "addr:postcode":"07450",
    "addr:street":"Carr Joan Monjo March",
    "iso:country":"ES",
    "sg:address":"Carr Joan Monjo March, 4",
    "sg:city":"Santa Margalida",
    "sg:orig_category":"Telas (al Por Mayor)",
    "sg:phone":"+34 971 52 30 47",
    "sg:postcode":"07450",
    "sg:province":"Islas Baleares",
    "wof:name":"Aguilo Roca Rosalia",
    "wof:placetype":"venue"
},
  "geometry": {"coordinates":[3.1027071476,39.7021789551],"type":"Point"}
}