{
  "type": "Feature",
  "properties": {
    "addr:full":"Calle de Almansa, 23 Palmas De Gran Canaria Las Palmas 35010",
    "addr:housenumber":"23",
    "addr:postcode":"35010",
    "addr:street":"Calle De Almansa",
    "iso:country":"ES",
    "sg:address":"Calle de Almansa, 23",
    "sg:city":"Palmas De Gran Canaria",
    "sg:orig_category":"Transportes Por Carretera: Lotes Completos, Mercanc\u00cdas Diversas",
    "sg:phone":"+34 928 27 69 90",
    "sg:postcode":"35010",
    "sg:province":"Las Palmas",
    "wof:name":"Almacenes Guanarteme S.l.",
    "wof:placetype":"venue"
},
  "geometry": {"coordinates":[-15.4438295364,28.1302108765],"type":"Point"}
}