{
  "type": "Feature",
  "properties": {
    "iso:country":"ES",
    "sg:address":"Plaz Ensanche, 9",
    "sg:city":"Bilbao",
    "sg:orig_category":"Centros Empresariales",
    "sg:phone":"+34 944 23 01 72",
    "sg:postcode":"48009",
    "sg:province":"Vizcaya",
    "wof:name":"Ibarzabal&line Sl",
    "wof:placetype":"venue"
},
  "geometry": {"coordinates":[-2.9313149452,43.2642440796],"type":"Point"}
}