{
  "type": "Feature",
  "properties": {
    "addr:full":"Calle de Reyes De Navarra, 39 Vitoria-gasteiz \u00c1lava 01013",
    "addr:housenumber":"39",
    "addr:postcode":"01013",
    "addr:street":"Calle De Reyes De Navarra",
    "iso:country":"ES",
    "sg:address":"Calle de Reyes De Navarra, 39",
    "sg:city":"Vitoria-gasteiz",
    "sg:orig_category":"Art\u00cdculos De Aluminio",
    "sg:phone":"+34 945 25 33 19",
    "sg:postcode":"01013",
    "sg:province":"\u00c1lava",
    "wof:name":"Sopelana Alonso Julian",
    "wof:placetype":"venue"
},
  "geometry": {"coordinates":[-2.6699581146,42.8593177795],"type":"Point"}
}