{
  "type": "Feature",
  "properties": {
    "addr:full":"Ctra Mojonera A San Agustin, Km. 0005,0 Mojonera Almer\u00eda 04745",
    "addr:postcode":"04745",
    "addr:street":"Ctra Mojonera A San Agustin Km. 0005,0",
    "iso:country":"ES",
    "sg:address":"Ctra Mojonera A San Agustin, Km. 0005,0",
    "sg:city":"Mojonera",
    "sg:orig_category":"Agentes, Concesionarios Y Sucursales De Veh\u00cdculos",
    "sg:phone":"+34 950 33 13 90",
    "sg:postcode":"04745",
    "sg:province":"Almer\u00eda",
    "wof:name":"Juan Enrique S.l.",
    "wof:placetype":"venue"
},
  "geometry": {"coordinates":[-2.6811990738,36.7550849915],"type":"Point"}
}