{
  "type": "Feature",
  "properties": {
    "iso:country":"ES",
    "sg:address":"Calle de Bruno Abundez, 20",
    "sg:city":"Madrid",
    "sg:orig_category":"Cerrajer\u00cda, Ferrallista",
    "sg:phone":"+34 913 31 72 64",
    "sg:postcode":"28031",
    "sg:province":"Madrid",
    "wof:name":"Pu\u00f1al Braojos Jose Manuel",
    "wof:placetype":"venue"
},
  "geometry": {"coordinates":[-3.6304543018,40.3848381042],"type":"Point"}
}