{
  "type": "Feature",
  "properties": {
    "iso:country":"ES",
    "sg:address":"Carrer de Sant Antoni, 17",
    "sg:city":"Mataro",
    "sg:orig_category":"Traductores",
    "sg:phone":"+34 937 55 12 43",
    "sg:postcode":"08301",
    "sg:province":"Barcelona",
    "sg:website":"www.traduccions.org",
    "wof:name":"Fors Soriano Gemma",
    "wof:placetype":"venue"
},
  "geometry": {"coordinates":[2.4466331005,41.5374603271],"type":"Point"}
}