{
  "type": "Feature",
  "properties": {
    "addr:full":"Calle de La Ba\u00d1eza, 6 Madrid Madrid 28029",
    "addr:housenumber":"6",
    "addr:postcode":"28029",
    "addr:street":"Calle De La Ban\u0303Eza",
    "iso:country":"ES",
    "sg:address":"Calle de La Ba\u00d1eza, 6",
    "sg:city":"Madrid",
    "sg:orig_category":"Servicios De Telecomunicaciones",
    "sg:phone":"+34 917 31 98 68",
    "sg:postcode":"28029",
    "sg:province":"Madrid",
    "wof:name":"Suppies Ingenieros",
    "wof:placetype":"venue"
},
  "geometry": {"coordinates":[-3.7122490406,40.4766845703],"type":"Point"}
}