{
  "type": "Feature",
  "properties": {
    "iso:country":"ES",
    "sg:address":"Ctra. Coru\u00f1a, Km. 0039,8",
    "sg:city":"Collado Villalba",
    "sg:orig_category":"Empresas De Carpinter\u00cda De Madera",
    "sg:phone":"+34 918 50 48 12",
    "sg:postcode":"28400",
    "sg:province":"Madrid",
    "wof:name":"Almacenes Herrero De La Calle S.l.",
    "wof:placetype":"venue"
},
  "geometry": {"coordinates":[-4.0026865005,40.6325912476],"type":"Point"}
}