{
  "type": "Feature",
  "properties": {
    "addr:full":"San Nicolas, 58 Benissa Alicante 03720",
    "addr:housenumber":"58",
    "addr:postcode":"03720",
    "addr:street":"San Nicolas",
    "iso:country":"ES",
    "sg:address":"San Nicolas, 58",
    "sg:city":"Benissa",
    "sg:orig_category":"Transporte En General",
    "sg:phone":"+34 965 73 03 82",
    "sg:postcode":"03720",
    "sg:province":"Alicante",
    "wof:name":"Maria Ribes E Hijos S.l.",
    "wof:placetype":"venue"
},
  "geometry": {"coordinates":[0.047623001,38.7151451111],"type":"Point"}
}