{
  "type": "Feature",
  "properties": {
    "addr:full":"Trva Breton, 1 Pe\u00e7aranda De Bracamonte Salamanca 37300",
    "addr:housenumber":"1",
    "addr:postcode":"37300",
    "addr:street":"Trva Breton",
    "iso:country":"ES",
    "sg:address":"Trva Breton, 1",
    "sg:city":"Pe\u00e7aranda De Bracamonte",
    "sg:orig_category":"Carnicer\u00cdas, Carnicer\u00cdas",
    "sg:phone":"+34 923 54 15 70",
    "sg:postcode":"37300",
    "sg:province":"Salamanca",
    "wof:name":"Jamones J.j. Salamanca S.l.",
    "wof:placetype":"venue"
},
  "geometry": {"coordinates":[-5.2049207687,40.9015350342],"type":"Point"}
}