{
  "type": "Feature",
  "properties": {
    "addr:full":"Calle de San Isidro, S/n Losar Vera C\u00e1ceres 10460",
    "addr:housenumber":"s / n",
    "addr:postcode":"10460",
    "addr:street":"Calle De San Isidro",
    "iso:country":"ES",
    "sg:address":"Calle de San Isidro, S/n",
    "sg:city":"Losar Vera",
    "sg:orig_category":"Administraci\u00d3n En Agricultura",
    "sg:phone":"+34 927 57 01 43",
    "sg:postcode":"10460",
    "sg:province":"C\u00e1ceres",
    "wof:name":"Union De Peque\u00f1os Agricultores De Extremadura",
    "wof:placetype":"venue"
},
  "geometry": {"coordinates":[-5.6065220833,40.1208305359],"type":"Point"}
}