{
  "type": "Feature",
  "properties": {
    "addr:full":"Calle de Segobriga, 3 Cuenca Cuenca 16001",
    "addr:housenumber":"3",
    "addr:postcode":"16001",
    "addr:street":"Calle De Segobriga",
    "iso:country":"ES",
    "sg:address":"Calle de Segobriga, 3",
    "sg:city":"Cuenca",
    "sg:orig_category":"Agencias Y Asesores De Publicidad",
    "sg:phone":"+34 969 23 42 22",
    "sg:postcode":"16001",
    "sg:province":"Cuenca",
    "wof:name":"Fredy Publicidad S.l.",
    "wof:placetype":"venue"
},
  "geometry": {"coordinates":[-2.1324689388,40.0720748901],"type":"Point"}
}