{
  "type": "Feature",
  "properties": {
    "iso:country":"ES",
    "sg:address":"Carrer de Cristofol Despuig (de), 36",
    "sg:city":"Tortosa",
    "sg:orig_category":"Abogados",
    "sg:phone":"+34 977 44 80 33",
    "sg:postcode":"43500",
    "sg:province":"Tarragona",
    "wof:name":"Martinez Ferrer Maria Cinta",
    "wof:placetype":"venue"
},
  "geometry": {"coordinates":[0.5227739811,40.8087425232],"type":"Point"}
}