{
  "type": "Feature",
  "properties": {
    "iso:country":"ES",
    "sg:address":"Calle de Truchillas, 4",
    "sg:city":"Le\u00f3n",
    "sg:orig_category":"Peluquer\u00cdas, Peluquer\u00cda Mixta",
    "sg:phone":"+34 987 22 13 39",
    "sg:postcode":"24010",
    "sg:province":"Le\u00f3n",
    "wof:name":"Carmona Gamazo David Sergio",
    "wof:placetype":"venue"
},
  "geometry": {"coordinates":[-5.5892410278,42.6037864685],"type":"Point"}
}