{
  "type": "Feature",
  "properties": {
    "iso:country":"ES",
    "sg:address":"Calle de Silera (la), 13",
    "sg:city":"Rambla",
    "sg:orig_category":"Alfarer\u00cda",
    "sg:phone":"+34 957 68 22 94",
    "sg:postcode":"14540",
    "sg:province":"C\u00f3rdoba",
    "wof:name":"Fernandez Prieto Antonio",
    "wof:placetype":"venue"
},
  "geometry": {"coordinates":[-4.741560936,37.6084861755],"type":"Point"}
}