{
  "type": "Feature",
  "properties": {
    "iso:country":"ES",
    "sg:address":"Calle de Gustavo Dore, 1",
    "sg:city":"Malaga",
    "sg:orig_category":"Estudios, Instalaci\u00d3n De Climatizaci\u00d3n",
    "sg:phone":"+34 952 28 56 52",
    "sg:postcode":"29011",
    "sg:province":"M\u00e1laga",
    "wof:name":"Duct System S.l.",
    "wof:placetype":"venue"
},
  "geometry": {"coordinates":[-4.4372849464,36.733379364],"type":"Point"}
}