{
  "type": "Feature",
  "properties": {
    "iso:country":"ES",
    "sg:address":"Carrer de Notari Jesus Led, S/n",
    "sg:city":"Sentmenat",
    "sg:orig_category":"Reposter\u00cdas",
    "sg:phone":"+34 937 15 22 70",
    "sg:postcode":"08181",
    "sg:province":"Barcelona",
    "wof:name":"Cordon Cordon Enrique",
    "wof:placetype":"venue"
},
  "geometry": {"coordinates":[2.1413600445,41.6114768982],"type":"Point"}
}