{
  "type": "Feature",
  "properties": {
    "iso:country":"ES",
    "sg:address":"Calle de General Ricardos, 18",
    "sg:city":"Madrid",
    "sg:orig_category":"Cervecer\u00cdas",
    "sg:phone":"+34 914 71 69 90",
    "sg:postcode":"28019",
    "sg:province":"Madrid",
    "wof:name":"Sanchez Sanchez Domingo",
    "wof:placetype":"venue"
},
  "geometry": {"coordinates":[-3.7182900906,40.3965072632],"type":"Point"}
}