{
  "type": "Feature",
  "properties": {
    "iso:country":"ES",
    "sg:address":"Calle de Junquillo, Km. 0011,5",
    "sg:city":"Cabra",
    "sg:orig_category":"Maquinaria Para Industrias Diversas",
    "sg:phone":"+34 957 52 04 16",
    "sg:postcode":"14940",
    "sg:province":"C\u00f3rdoba",
    "wof:name":"Herrero Garcia Miguel",
    "wof:placetype":"venue"
},
  "geometry": {"coordinates":[-4.4481139183,37.4732246399],"type":"Point"}
}