{
  "type": "Feature",
  "properties": {
    "iso:country":"ES",
    "sg:address":"Avda Francia, 17",
    "sg:city":"Valencia",
    "sg:orig_category":"Fabricaci\u00d3n, Reparaci\u00d3n Y Mantenimiento De Construcciones Navales Y Fluviales",
    "sg:phone":"+34 963 30 75 23",
    "sg:postcode":"46023",
    "sg:province":"Valencia",
    "wof:name":"Abs Europe Limited Sucursal En Espa\u00f1a",
    "wof:placetype":"venue"
},
  "geometry": {"coordinates":[-0.351345,39.460258],"type":"Point"}
}