{
  "type": "Feature",
  "properties": {
    "iso:country":"ES",
    "sg:address":"Belvis(tabeaio), 17",
    "sg:city":"Belvis De Tabeaio",
    "sg:orig_category":"Ense\u00d1anza, Formaci\u00d3n Profesional: Aprendizaje",
    "sg:phone":"+34 981 67 16 44",
    "sg:postcode":"15175",
    "sg:province":"La Coru\u00f1a",
    "wof:name":"Concello De Carral",
    "wof:placetype":"venue"
},
  "geometry": {"coordinates":[-8.3558893204,43.2278442383],"type":"Point"}
}