{
  "type": "Feature",
  "properties": {
    "iso:country":"ES",
    "sg:address":"Av Ferreria (la), 45",
    "sg:city":"Terra Nostra",
    "sg:orig_category":"Empresas De Carpinter\u00cda",
    "sg:phone":"+34 935 64 61 09",
    "sg:postcode":"08110",
    "sg:province":"Barcelona",
    "wof:name":"Confortal S.l.",
    "wof:placetype":"venue"
},
  "geometry": {"coordinates":[2.1817660332,41.4890899658],"type":"Point"}
}