{
  "type": "Feature",
  "properties": {
    "addr:full":"Calle de Foces Del Rio Aller, 8 Gijon Asturias 33212",
    "addr:housenumber":"8",
    "addr:postcode":"33212",
    "addr:street":"Calle De Foces;Aller",
    "iso:country":"ES",
    "sg:address":"Calle de Foces Del Rio Aller, 8",
    "sg:city":"Gijon",
    "sg:orig_category":"Empresas De Carpinter\u00cda De Madera",
    "sg:phone":"+34 985 30 15 60",
    "sg:postcode":"33212",
    "sg:province":"Asturias",
    "wof:name":"Benito Sistemas De Carpinteria S.a.",
    "wof:placetype":"venue"
},
  "geometry": {"coordinates":[-5.6810688972,43.5384712219],"type":"Point"}
}