{
  "type": "Feature",
  "properties": {
    "addr:full":"Ctra Valverde, S/n Badajoz Badajoz 06010",
    "addr:housenumber":"s / n",
    "addr:postcode":"06010",
    "addr:street":"Ctra Valverde",
    "iso:country":"ES",
    "sg:address":"Ctra Valverde, S/n",
    "sg:city":"Badajoz",
    "sg:orig_category":"Fabricaci\u00d3n De Sobres, Bolsas Y Fundas",
    "sg:phone":"+34 924 26 00 42",
    "sg:postcode":"06010",
    "sg:province":"Badajoz",
    "wof:name":"La Casa De Los Bolsos Extreme\u00d1os S.l.",
    "wof:placetype":"venue"
},
  "geometry": {"coordinates":[-6.9720201492,38.8625411987],"type":"Point"}
}