{
  "type": "Feature",
  "properties": {
    "addr:full":"Avda Ca\u00d1amo (del), S/n San Jose Rinconada Sevilla 41300",
    "addr:housenumber":"/ n",
    "addr:postcode":"41300",
    "addr:street":"Avda Can\u0303Amo Del S",
    "iso:country":"ES",
    "sg:address":"Avda Ca\u00d1amo (del), S/n",
    "sg:city":"San Jose Rinconada",
    "sg:orig_category":"Ingeniero",
    "sg:phone":"+34 954 79 07 33",
    "sg:postcode":"41300",
    "sg:province":"Sevilla",
    "sg:website":"www.sosen.com",
    "wof:name":"Sociedad De Servicios Integrados S.a.",
    "wof:placetype":"venue"
},
  "geometry": {"coordinates":[-5.93516922,37.486530304],"type":"Point"}
}