{
  "type": "Feature",
  "properties": {
    "addr:full":"Avda Gomez Laguna, 24 Zaragoza Zaragoza 50009",
    "addr:housenumber":"24",
    "addr:postcode":"50009",
    "addr:street":"Avda Gomez Laguna",
    "iso:country":"ES",
    "sg:address":"Avda Gomez Laguna, 24",
    "sg:city":"Zaragoza",
    "sg:orig_category":"Contables",
    "sg:phone":"+34 976 75 54 20",
    "sg:postcode":"50009",
    "sg:province":"Zaragoza",
    "wof:name":"Asesoria Y Consultoria Universitas S.l.",
    "wof:placetype":"venue"
},
  "geometry": {"coordinates":[-0.9105098248,41.6417274475],"type":"Point"}
}