{
  "type": "Feature",
  "properties": {
    "addr:full":"Calle de Zubiaur Tar Kepa, 55 Bermeo Vizcaya 48370",
    "addr:housenumber":"55",
    "addr:postcode":"48370",
    "addr:street":"Calle De Zubiaur;Kepa",
    "iso:country":"ES",
    "sg:address":"Calle de Zubiaur Tar Kepa, 55",
    "sg:city":"Bermeo",
    "sg:orig_category":"Electricidad: Instaladores",
    "sg:phone":"+34 946 88 36 56",
    "sg:postcode":"48370",
    "sg:province":"Vizcaya",
    "wof:name":"Carpinteria Izaro S.a.",
    "wof:placetype":"venue"
},
  "geometry": {"coordinates":[-2.7324171066,43.4198493958],"type":"Point"}
}