{
  "type": "Feature",
  "properties": {
    "addr:full":"Calle de Aspe, 4 Alacant Alicante 03012",
    "addr:housenumber":"4",
    "addr:postcode":"03012",
    "addr:street":"Calle De Aspe",
    "iso:country":"ES",
    "sg:address":"Calle de Aspe, 4",
    "sg:city":"Alacant",
    "sg:orig_category":"Alquiler De Gr\u00daas",
    "sg:phone":"+34 965 24 93 93",
    "sg:postcode":"03012",
    "sg:province":"Alicante",
    "wof:name":"Gruas Asistencia Y Maquinaria S.l.",
    "wof:placetype":"venue"
},
  "geometry": {"coordinates":[-0.4834679067,38.356803894],"type":"Point"}
}