{
  "type": "Feature",
  "properties": {
    "addr:full":"Carrer de Calaf, 12 Barcelona Barcelona 08021",
    "addr:housenumber":"12",
    "addr:postcode":"08021",
    "addr:street":"Carrer De Calaf",
    "iso:country":"ES",
    "sg:address":"Carrer de Calaf, 12",
    "sg:city":"Barcelona",
    "sg:orig_category":"Frutas, Legumbres Frescas Y Tempranas (al Por Menor)",
    "sg:phone":"+34 932 09 21 28",
    "sg:postcode":"08021",
    "sg:province":"Barcelona",
    "wof:name":"Pladellorens Camps Maria Victoria",
    "wof:placetype":"venue"
},
  "geometry": {"coordinates":[2.1443359852,41.3977546692],"type":"Point"}
}