{
  "type": "Feature",
  "properties": {
    "iso:country":"ES",
    "sg:address":"Pase Estacion, S/n",
    "sg:city":"Ferrol",
    "sg:orig_category":"Autob\u00das (explotaci\u00d3n Y Servicios De)",
    "sg:phone":"+34 981 31 59 55",
    "sg:postcode":"15405",
    "sg:province":"La Coru\u00f1a",
    "wof:name":"Rias Altas S.a.",
    "wof:placetype":"venue"
},
  "geometry": {"coordinates":[-8.2314767838,43.4877433777],"type":"Point"}
}