{
  "type": "Feature",
  "properties": {
    "iso:country":"ES",
    "sg:address":"Calle de Carrequemada, 41",
    "sg:city":"Aranda Duero",
    "sg:orig_category":"Cr\u00cda De Animales",
    "sg:phone":"+34 947 50 15 76",
    "sg:postcode":"09400",
    "sg:province":"Burgos",
    "wof:name":"Barbero Sierra Juan",
    "wof:placetype":"venue"
},
  "geometry": {"coordinates":[-3.682571888,41.6720695496],"type":"Point"}
}