{
  "type": "Feature",
  "properties": {
    "iso:country":"ES",
    "sg:address":"Calle de Pe\u00d1as (las), S/n",
    "sg:city":"Au\u00d1on",
    "sg:orig_category":"Iglesias Evang\u00c9licas",
    "sg:phone":"+34 949 35 85 34",
    "sg:postcode":"19130",
    "sg:province":"Guadalajara",
    "wof:name":"Asociacion Evangelica Internacional",
    "wof:placetype":"venue"
},
  "geometry": {"coordinates":[-2.7914185524,40.5177879333],"type":"Point"}
}