{
  "type": "Feature",
  "properties": {
    "addr:full":"Calle de Altube, 23 Algorta Vizcaya 48993",
    "addr:housenumber":"23",
    "addr:postcode":"48993",
    "addr:street":"Calle De Altube",
    "iso:country":"ES",
    "sg:address":"Calle de Altube, 23",
    "sg:city":"Algorta",
    "sg:orig_category":"M\u00c1quinas, Material Y Suministros Para Cajas Y Embalajes",
    "sg:phone":"+34 944 60 96 15",
    "sg:postcode":"48993",
    "sg:province":"Vizcaya",
    "wof:name":"Flejenor S.l.",
    "wof:placetype":"venue"
},
  "geometry": {"coordinates":[-3.0155696869,43.3558311462],"type":"Point"}
}