{
  "type": "Feature",
  "properties": {
    "addr:full":"Font De La Teula, 7 Girona Girona 17007",
    "addr:housenumber":"7",
    "addr:postcode":"17007",
    "addr:street":"Teula",
    "iso:country":"ES",
    "sg:address":"Font De La Teula, 7",
    "sg:city":"Girona",
    "sg:orig_category":"Psic\u00d3logos",
    "sg:phone":"+34 972 41 10 31",
    "sg:postcode":"17007",
    "sg:province":"Girona",
    "wof:name":"Magaldi Perez Carmina",
    "wof:placetype":"venue"
},
  "geometry": {"coordinates":[2.8205149174,41.9948883057],"type":"Point"}
}