{
  "type": "Feature",
  "properties": {
    "iso:country":"ES",
    "sg:address":"Calle de Estrella, 9",
    "sg:city":"Madrigueras",
    "sg:orig_category":"Iglesia Cat\u00d3lica",
    "sg:phone":"+34 967 48 40 37",
    "sg:postcode":"02230",
    "sg:province":"Albacete",
    "wof:name":"Parroquia De San Pedro Y San Pablo",
    "wof:placetype":"venue"
},
  "geometry": {"coordinates":[-1.8023680449,39.2378158569],"type":"Point"}
}