{
  "type": "Feature",
  "properties": {
    "iso:country":"ES",
    "sg:address":"Calle de Ramon Y Cajal, 6",
    "sg:city":"Nava Rey",
    "sg:orig_category":"Florister\u00cdas",
    "sg:phone":"+34 983 85 01 24",
    "sg:postcode":"47500",
    "sg:province":"Valladolid",
    "wof:name":"Lozoya Garcia Bego\u00f1a",
    "wof:placetype":"venue"
},
  "geometry": {"coordinates":[-5.0809149742,41.3309135437],"type":"Point"}
}