{
  "type": "Feature",
  "properties": {
    "addr:full":"Calle de Fernandez Vallin, 2 Gijon Asturias 33205",
    "addr:housenumber":"2",
    "addr:postcode":"33205",
    "addr:street":"Calle De Fernandez Vallin",
    "iso:country":"ES",
    "sg:address":"Calle de Fernandez Vallin, 2",
    "sg:city":"Gijon",
    "sg:orig_category":"Art\u00cdculos De Regalo (al Por Menor)",
    "sg:phone":"+34 985 17 66 39",
    "sg:postcode":"33205",
    "sg:province":"Asturias",
    "wof:name":"Cheng  Jiantao",
    "wof:placetype":"venue"
},
  "geometry": {"coordinates":[-5.6621508598,43.5395851135],"type":"Point"}
}