{
  "type": "Feature",
  "properties": {
    "addr:full":"Carrer de Carme, 25 Barcelona Barcelona 08001",
    "addr:housenumber":"25",
    "addr:postcode":"08001",
    "addr:street":"Carrer De Carme",
    "iso:country":"ES",
    "sg:address":"Carrer de Carme, 25",
    "sg:city":"Barcelona",
    "sg:orig_category":"Pensiones Familiares",
    "sg:phone":"+34 933 01 44 84",
    "sg:postcode":"08001",
    "sg:province":"Barcelona",
    "wof:name":"Parides Hoteles S.l",
    "wof:placetype":"venue"
},
  "geometry": {"coordinates":[2.1704790592,41.3822784424],"type":"Point"}
}