{
  "type": "Feature",
  "properties": {
    "iso:country":"ES",
    "sg:address":"Ctra Andalucia (de), 109",
    "sg:city":"Aranjuez",
    "sg:orig_category":"Notarios",
    "sg:phone":"+34 918 92 53 97",
    "sg:postcode":"28300",
    "sg:province":"Madrid",
    "wof:name":"Calderon Alvarez Francisco",
    "wof:placetype":"venue"
},
  "geometry": {"coordinates":[-3.6054461002,40.0280075073],"type":"Point"}
}