{
  "type": "Feature",
  "properties": {
    "iso:country":"ES",
    "sg:address":"Praz Do Seixo, S/n",
    "sg:city":"Seijo",
    "sg:orig_category":"Negocio De Materiales De Construcci\u00d3n",
    "sg:phone":"+34 986 62 32 84",
    "sg:postcode":"36740",
    "sg:province":"Pontevedra",
    "wof:name":"Material De Construccion Pego S.l.",
    "wof:placetype":"venue"
},
  "geometry": {"coordinates":[-8.731048584,41.9869499207],"type":"Point"}
}