{
  "type": "Feature",
  "properties": {
    "iso:country":"ES",
    "sg:address":"Valladolid (p I Prado), S/n",
    "sg:city":"Merida",
    "sg:orig_category":"Herradores, Herreros, Carreteros",
    "sg:phone":"+34 924 37 86 07",
    "sg:postcode":"06800",
    "sg:province":"Badajoz",
    "wof:name":"Plasticos De Miguel S.l.u.",
    "wof:placetype":"venue"
},
  "geometry": {"coordinates":[-6.3807239532,38.926399231],"type":"Point"}
}