{
  "type": "Feature",
  "properties": {
    "addr:full":"Calle de Rafael Salgado, 36 Sevilla Sevilla 41013",
    "addr:housenumber":"36",
    "addr:postcode":"41013",
    "addr:street":"Calle De Rafael Salgado",
    "iso:country":"ES",
    "sg:address":"Calle de Rafael Salgado, 36",
    "sg:city":"Sevilla",
    "sg:orig_category":"Carnicer\u00cdas, Carnicer\u00cdas",
    "sg:phone":"+34 954 61 97 46",
    "sg:postcode":"41013",
    "sg:province":"Sevilla",
    "wof:name":"Galisteo Segura Rosario",
    "wof:placetype":"venue"
},
  "geometry": {"coordinates":[-5.9767928123,37.3598747253],"type":"Point"}
}