{
  "type": "Feature",
  "properties": {
    "addr:full":"Ctra. Jerez-sanlucar, Km. 0020,0 Jerez C\u00e1diz 11408",
    "addr:postcode":"11408",
    "addr:street":"Ctra. Jerez-Sanlucar Km. 0020,0",
    "iso:country":"ES",
    "sg:address":"Ctra. Jerez-sanlucar, Km. 0020,0",
    "sg:city":"Jerez",
    "sg:orig_category":"Transportes En Cisternas",
    "sg:phone":"+34 956 34 18 20",
    "sg:postcode":"11408",
    "sg:province":"C\u00e1diz",
    "wof:name":"Narbona Ortega Antonio",
    "wof:placetype":"venue"
},
  "geometry": {"coordinates":[-6.1592831612,36.6686592102],"type":"Point"}
}