{
  "type": "Feature",
  "properties": {
    "addr:full":"Calle de Alcala, 155 Madrid Madrid 28009",
    "addr:housenumber":"155",
    "addr:postcode":"28009",
    "addr:street":"Calle De Alcala",
    "iso:country":"ES",
    "sg:address":"Calle de Alcala, 155",
    "sg:city":"Madrid",
    "sg:classifiers":[
        {
            "category":"Government",
            "subcategory":"Post Office",
            "type":"Public Place"
        }
    ],
    "sg:phone":"+34 914 31 71 32",
    "sg:postcode":"28009",
    "sg:province":"Madrid",
    "sg:tags":[
        "de",
        "yoga",
        "clases"
    ],
    "wof:name":"Fraile Sanchez Miguel Alfonso",
    "wof:placetype":"venue"
},
  "geometry": {"coordinates":[-3.6747739315,40.425239563],"type":"Point"}
}