{
  "type": "Feature",
  "properties": {
    "addr:full":"Calle de Juan Van-halen, S/n Torrelodones Madrid 28250",
    "addr:housenumber":"s / n",
    "addr:postcode":"28250",
    "addr:street":"Calle De Juan Van-Halen",
    "iso:country":"ES",
    "sg:address":"Calle de Juan Van-halen, S/n",
    "sg:city":"Torrelodones",
    "sg:orig_category":"Sociedades, Compa\u00d1\u00cdas Aseguradoras",
    "sg:phone":"+34 918 59 48 81",
    "sg:postcode":"28250",
    "sg:province":"Madrid",
    "wof:name":"Mapfre Servicios De Informatica",
    "wof:placetype":"venue"
},
  "geometry": {"coordinates":[-3.9282140732,40.5769386292],"type":"Point"}
}