{
  "type": "Feature",
  "properties": {
    "addr:full":"Carr Sagasta, De, 29 Carcaixent Valencia 46740",
    "addr:housenumber":"29",
    "addr:postcode":"46740",
    "addr:street":"Carr Sagasta De",
    "iso:country":"ES",
    "sg:address":"Carr Sagasta, De, 29",
    "sg:city":"Carcaixent",
    "sg:orig_category":"Contenedores (mercanc\u00cdas)",
    "sg:phone":"+34 962 43 31 74",
    "sg:postcode":"46740",
    "sg:province":"Valencia",
    "wof:name":"Concepcion Castello Joaquin De La",
    "wof:placetype":"venue"
},
  "geometry": {"coordinates":[-0.4483090043,39.1195106506],"type":"Point"}
}