{
  "type": "Feature",
  "properties": {
    "addr:full":"Calle de Se\u00d1ora Bienvenida, 70 Torrelodones Madrid 28250",
    "addr:housenumber":"70",
    "addr:postcode":"28250",
    "addr:street":"Calle De Sen\u0303Ora Bienvenida",
    "iso:country":"ES",
    "sg:address":"Calle de Se\u00d1ora Bienvenida, 70",
    "sg:city":"Torrelodones",
    "sg:orig_category":"Traductores",
    "sg:phone":"+34 918 59 65 01",
    "sg:postcode":"28250",
    "sg:province":"Madrid",
    "wof:name":"Burton Parma S.l.",
    "wof:placetype":"venue"
},
  "geometry": {"coordinates":[-3.9229199886,40.5780906677],"type":"Point"}
}