{
  "type": "Feature",
  "properties": {
    "iso:country":"ES",
    "sg:address":"Plaz Corral De La Campana, 4",
    "sg:city":"Toledo",
    "sg:orig_category":"Abogados",
    "sg:phone":"+34 925 22 64 66",
    "sg:postcode":"45001",
    "sg:province":"Toledo",
    "wof:name":"Garcia-tizon Lopez Arturo",
    "wof:placetype":"venue"
},
  "geometry": {"coordinates":[-4.0212688446,39.8606414795],"type":"Point"}
}