{
  "type": "Feature",
  "properties": {
    "addr:full":"Calle de Sevilla, 3 Ejido Almer\u00eda 04700",
    "addr:housenumber":"3",
    "addr:postcode":"04700",
    "addr:street":"Calle De Sevilla;Almeri\u0301A",
    "iso:country":"ES",
    "sg:address":"Calle de Sevilla, 3",
    "sg:city":"Ejido",
    "sg:orig_category":"Agentes Generales De Seguros",
    "sg:phone":"+34 950 48 00 20",
    "sg:postcode":"04700",
    "sg:province":"Almer\u00eda",
    "wof:name":"Enciso Almendros Francisco",
    "wof:placetype":"venue"
},
  "geometry": {"coordinates":[-2.8167729378,36.772731781],"type":"Point"}
}