{
  "type": "Feature",
  "properties": {
    "addr:full":"Carrer de Numancia, 39 Barcelona Barcelona 08029",
    "addr:housenumber":"39",
    "addr:postcode":"08029",
    "addr:street":"Carrer De Numancia",
    "iso:country":"ES",
    "sg:address":"Carrer de Numancia, 39",
    "sg:city":"Barcelona",
    "sg:orig_category":"Lencer\u00cda Femenina, Corseter\u00cda, Trajes De Ba\u00d1o (al Por Menor)",
    "sg:phone":"+34 933 22 25 20",
    "sg:postcode":"08029",
    "sg:province":"Barcelona",
    "wof:name":"Cabre Rey Josefa",
    "wof:placetype":"venue"
},
  "geometry": {"coordinates":[2.139373064,41.3827362061],"type":"Point"}
}