{
  "type": "Feature",
  "properties": {
    "iso:country":"ES",
    "sg:address":"Torre, 2",
    "sg:city":"Espera",
    "sg:orig_category":"Revestimiento De Suelos Industriales",
    "sg:phone":"+34 956 72 01 78",
    "sg:postcode":"11648",
    "sg:province":"C\u00e1diz",
    "wof:name":"Zarco Iba\u00f1ez Antonio",
    "wof:placetype":"venue"
},
  "geometry": {"coordinates":[-5.8034586906,36.8714942932],"type":"Point"}
}