{
  "type": "Feature",
  "properties": {
    "iso:country":"ES",
    "sg:address":"Calle de Sor Virtudes Lopez, 11",
    "sg:city":"Union",
    "sg:orig_category":"Supermercados Y Hipermercados",
    "sg:phone":"+34 968 54 00 07",
    "sg:postcode":"30360",
    "sg:province":"Murcia",
    "wof:name":"Inmomerca S.a.",
    "wof:placetype":"venue"
},
  "geometry": {"coordinates":[-0.8724390268,37.6180114746],"type":"Point"}
}