{
  "type": "Feature",
  "properties": {
    "iso:country":"ES",
    "sg:address":"Urb Aloha Marbella, S/n",
    "sg:city":"Nueva Andalucia",
    "sg:orig_category":"Agencias Y Asesores De Publicidad",
    "sg:phone":"+34 952 81 33 30",
    "sg:postcode":"29660",
    "sg:province":"M\u00e1laga",
    "wof:name":"Rodriguez Coelho Cleomar",
    "wof:placetype":"venue"
},
  "geometry": {"coordinates":[-4.9596438408,36.504699707],"type":"Point"}
}