{
  "type": "Feature",
  "properties": {
    "iso:country":"ES",
    "sg:address":"Calle de Carlos Ramirez De Arellano, 21",
    "sg:city":"Melilla",
    "sg:orig_category":"Servicios Gsm",
    "sg:phone":"+34 952 68 02 87",
    "sg:postcode":"52004",
    "sg:province":"Melilla",
    "wof:name":"Mohamed Amar Said",
    "wof:placetype":"venue"
},
  "geometry": {"coordinates":[-2.9445095062,35.2915077209],"type":"Point"}
}