{
  "type": "Feature",
  "properties": {
    "addr:full":"Calle de Walt Whitman, 5 Malaga M\u00e1laga 29002",
    "addr:housenumber":"5",
    "addr:postcode":"29002",
    "addr:street":"Calle De Walt Whitman;Ma\u0301Laga",
    "iso:country":"ES",
    "sg:address":"Calle de Walt Whitman, 5",
    "sg:city":"Malaga",
    "sg:orig_category":"Transporte En General",
    "sg:phone":"+34 952 36 96 50",
    "sg:postcode":"29002",
    "sg:province":"M\u00e1laga",
    "wof:name":"Indra Empresarial Sl",
    "wof:placetype":"venue"
},
  "geometry": {"coordinates":[-4.4333758354,36.7158737183],"type":"Point"}
}