{
  "type": "Feature",
  "properties": {
    "addr:full":"Carrer de Saleta, 10 Barcelona Barcelona 08028",
    "addr:housenumber":"10",
    "addr:postcode":"08028",
    "addr:street":"Carrer De Saleta",
    "iso:country":"ES",
    "sg:address":"Carrer de Saleta, 10",
    "sg:city":"Barcelona",
    "sg:orig_category":"Internados & Ense\u00d1anza Privada",
    "sg:phone":"+34 933 39 62 77",
    "sg:postcode":"08028",
    "sg:province":"Barcelona",
    "wof:name":"Bone Girol Elena",
    "wof:placetype":"venue"
},
  "geometry": {"coordinates":[2.1334760189,41.3805351257],"type":"Point"}
}