{
  "type": "Feature",
  "properties": {
    "addr:full":"Av Del Mar, 2 Gava Barcelona 08850",
    "addr:housenumber":"2",
    "addr:postcode":"08850",
    "addr:street":"Av Del Mar",
    "iso:country":"ES",
    "sg:address":"Av Del Mar, 2",
    "sg:city":"Gava",
    "sg:orig_category":"Asociaciones Y Clubs Deportivos",
    "sg:phone":"+34 936 45 14 54",
    "sg:postcode":"08850",
    "sg:province":"Barcelona",
    "wof:name":"Martinez Molinero Maria Consuelo",
    "wof:placetype":"venue"
},
  "geometry": {"coordinates":[2.0167200565,41.2867202759],"type":"Point"}
}