{
  "type": "Feature",
  "properties": {
    "iso:country":"ES",
    "sg:address":"Ptda Puente, Km. 0000,6",
    "sg:city":"Todolella",
    "sg:orig_category":"Carnicer\u00cdas, Carnicer\u00cdas",
    "sg:phone":"+34 964 76 30 90",
    "sg:postcode":"12312",
    "sg:province":"Castell\u00f3n",
    "wof:name":"Jamones Alfredo Monfort S.l.",
    "wof:placetype":"venue"
},
  "geometry": {"coordinates":[-0.3399139941,40.6375236511],"type":"Point"}
}