{
  "type": "Feature",
  "properties": {
    "iso:country":"ES",
    "sg:address":"Calle de San Fermin, 10",
    "sg:city":"Cintruenigo",
    "sg:orig_category":"Venta, Montaje De Neum\u00c1ticos",
    "sg:phone":"+34 948 81 12 05",
    "sg:postcode":"31592",
    "sg:province":"Navarra",
    "wof:name":"Gomez Mateo Antonio",
    "wof:placetype":"venue"
},
  "geometry": {"coordinates":[-1.8059879541,42.0772285461],"type":"Point"}
}