{
  "type": "Feature",
  "properties": {
    "addr:full":"Calle de Tellagorri, 12 Bilbao Vizcaya 48012",
    "addr:housenumber":"12",
    "addr:postcode":"48012",
    "addr:street":"Calle De Tellagorri",
    "iso:country":"ES",
    "sg:address":"Calle de Tellagorri, 12",
    "sg:city":"Bilbao",
    "sg:orig_category":"Molduras, Junquillos, Listones Y Molduras Perforadas",
    "sg:phone":"+34 944 27 73 95",
    "sg:postcode":"48012",
    "sg:province":"Vizcaya",
    "wof:name":"Garcia Lopez Maria Pilar",
    "wof:placetype":"venue"
},
  "geometry": {"coordinates":[-2.9499590397,43.2566604614],"type":"Point"}
}