{
  "type": "Feature",
  "properties": {
    "addr:full":"Avda America, 15 Madrid Madrid 28002",
    "addr:housenumber":"15",
    "addr:postcode":"madrid;28002",
    "addr:street":"Avda America",
    "iso:country":"ES",
    "sg:address":"Avda America, 15",
    "sg:city":"Madrid",
    "sg:orig_category":"Teatros Y Salas De Espect\u00c1culos",
    "sg:phone":"+34 915 62 85 41",
    "sg:postcode":"28002",
    "sg:province":"Madrid",
    "wof:name":"Issaura Comercial 21 S.l.",
    "wof:placetype":"venue"
},
  "geometry": {"coordinates":[-3.6762430668,40.4386062622],"type":"Point"}
}