{
  "type": "Feature",
  "properties": {
    "addr:full":"Carrer de Pius Xii, 24 Cornella Llobregat Barcelona 08940",
    "addr:housenumber":"24",
    "addr:postcode":"08940",
    "addr:street":"Carrer De Pius Xii",
    "iso:country":"ES",
    "sg:address":"Carrer de Pius Xii, 24",
    "sg:city":"Cornella Llobregat",
    "sg:orig_category":"Agentes, Concesionarios Y Sucursales De Veh\u00cdculos",
    "sg:phone":"+34 933 77 82 52",
    "sg:postcode":"08940",
    "sg:province":"Barcelona",
    "wof:name":"Hispanomocion S.a.",
    "wof:placetype":"venue"
},
  "geometry": {"coordinates":[2.0672130585,41.3555107117],"type":"Point"}
}