{
  "type": "Feature",
  "properties": {
    "iso:country":"ES",
    "sg:address":"Calle de Eustasio Amilibia, 2",
    "sg:city":"Donostia-san Sebastian",
    "sg:orig_category":"Bares, Piano",
    "sg:phone":"+34 943 45 43 61",
    "sg:postcode":"20011",
    "sg:province":"Guip\u00f9zcoa",
    "wof:name":"Palacios Sanchez Julia",
    "wof:placetype":"venue"
},
  "geometry": {"coordinates":[-1.9757000208,43.306427002],"type":"Point"}
}