{
  "type": "Feature",
  "properties": {
    "iso:country":"ES",
    "sg:address":"Carrer de Premia De Mar, 8",
    "sg:city":"Masnou",
    "sg:orig_category":"Supermercados Y Hipermercados",
    "sg:phone":"+34 935 40 46 29",
    "sg:postcode":"08320",
    "sg:province":"Barcelona",
    "wof:name":"Super 4 Hermanos Ruiz S.a.",
    "wof:placetype":"venue"
},
  "geometry": {"coordinates":[2.3083999157,41.4770393372],"type":"Point"}
}