{
  "type": "Feature",
  "properties": {
    "addr:full":"Calle de Azucenas, 22 Madrid Madrid 28039",
    "addr:housenumber":"22",
    "addr:postcode":"madrid;28039",
    "addr:street":"Calle De Azucenas",
    "iso:country":"ES",
    "sg:address":"Calle de Azucenas, 22",
    "sg:city":"Madrid",
    "sg:orig_category":"Muebles Y Accesorios Para Cocinas Y Cuartos De Ba\u00d1o (al Por Menor)",
    "sg:phone":"+34 915 71 42 75",
    "sg:postcode":"28039",
    "sg:province":"Madrid",
    "wof:name":"Alvarez Hernandez Amparo",
    "wof:placetype":"venue"
},
  "geometry": {"coordinates":[-3.6986756325,40.4634780884],"type":"Point"}
}