{
  "type": "Feature",
  "properties": {
    "addr:full":"Ptge Mercantil, 2 Barcelona Barcelona 08003",
    "addr:housenumber":"2",
    "addr:postcode":"08003",
    "addr:street":"Ptge Mercantil",
    "iso:country":"ES",
    "sg:address":"Ptge Mercantil, 2",
    "sg:city":"Barcelona",
    "sg:orig_category":"Edici\u00d3n De Diarios, Revistas, Boletines",
    "sg:phone":"+34 933 10 03 16",
    "sg:postcode":"08003",
    "sg:province":"Barcelona",
    "wof:name":"Dalmau G. Editors S.l.",
    "wof:placetype":"venue"
},
  "geometry": {"coordinates":[2.1843690872,41.3860626221],"type":"Point"}
}