{
  "type": "Feature",
  "properties": {
    "iso:country":"ES",
    "sg:address":"Crta De Martos, 9",
    "sg:city":"Fuensanta Martos",
    "sg:orig_category":"Muebles, Minoristas",
    "sg:phone":"+34 953 56 54 64",
    "sg:postcode":"23610",
    "sg:province":"Ja\u00e9n",
    "wof:name":"Gonzalez E Hijos C.b.",
    "wof:placetype":"venue"
},
  "geometry": {"coordinates":[-3.9154150486,37.6455688477],"type":"Point"}
}