{
  "type": "Feature",
  "properties": {
    "addr:full":"Calle de Infantas (de Las), 27 Aranjuez Madrid 28300",
    "addr:housenumber":"27",
    "addr:postcode":"28300",
    "addr:street":"Calle De Infantas De Las",
    "iso:country":"ES",
    "sg:address":"Calle de Infantas (de Las), 27",
    "sg:city":"Aranjuez",
    "sg:orig_category":"Electrodom\u00c9sticos (al Por Menor)",
    "sg:phone":"+34 918 92 27 64",
    "sg:postcode":"28300",
    "sg:province":"Madrid",
    "wof:name":"Normavision S.l.",
    "wof:placetype":"venue"
},
  "geometry": {"coordinates":[-3.6011910439,40.0352210999],"type":"Point"}
}