{
  "type": "Feature",
  "properties": {
    "addr:full":"Calle de Jesus Y Maria, 27 Santa Cruz De Tenerife Santa Cruz De Tenerife 38004",
    "addr:housenumber":"27",
    "addr:postcode":"38004",
    "addr:street":"Calle De Jesus Y Maria",
    "iso:country":"ES",
    "sg:address":"Calle de Jesus Y Maria, 27",
    "sg:city":"Santa Cruz De Tenerife",
    "sg:orig_category":"Psic\u00d3logos",
    "sg:phone":"+34 922 53 12 73",
    "sg:postcode":"38004",
    "sg:province":"Santa Cruz De Tenerife",
    "wof:name":"Segura Munera Jose",
    "wof:placetype":"venue"
},
  "geometry": {"coordinates":[-16.2566814423,28.4699954987],"type":"Point"}
}