{
  "type": "Feature",
  "properties": {
    "iso:country":"ES",
    "sg:address":"Ctra Villaviciosa, 5",
    "sg:city":"Gijon",
    "sg:orig_category":"Supermercados Y Hipermercados",
    "sg:phone":"+34 985 33 62 10",
    "sg:postcode":"33203",
    "sg:province":"Asturias",
    "wof:name":"Cenco S.a.",
    "wof:placetype":"venue"
},
  "geometry": {"coordinates":[-5.645277977,43.5348396301],"type":"Point"}
}