{
  "type": "Feature",
  "properties": {
    "addr:full":"Ctra Palmar, 233 Murcia Murcia 30010",
    "addr:housenumber":"233",
    "addr:postcode":"30010",
    "addr:street":"Ctra Palmar",
    "iso:country":"ES",
    "sg:address":"Ctra Palmar, 233",
    "sg:city":"Murcia",
    "sg:orig_category":"Suministros Y Materiales Industriales",
    "sg:phone":"+34 968 26 00 34",
    "sg:postcode":"30010",
    "sg:province":"Murcia",
    "wof:name":"Sotomayor Yarza Francisco",
    "wof:placetype":"venue"
},
  "geometry": {"coordinates":[-1.1351189613,37.9738388062],"type":"Point"}
}