{
  "type": "Feature",
  "properties": {
    "iso:country":"ES",
    "sg:address":"Calle de Maria Moliner, 18",
    "sg:city":"Zaragoza",
    "sg:orig_category":"Imprenta",
    "sg:phone":"+34 976 25 86 71",
    "sg:postcode":"50007",
    "sg:province":"Zaragoza",
    "sg:website":"www.imprentairis.es",
    "wof:name":"Alfonso De Campos Desde 1965 S L L",
    "wof:placetype":"venue"
},
  "geometry": {"coordinates":[-0.8843564987,41.6394538879],"type":"Point"}
}