{
  "type": "Feature",
  "properties": {
    "addr:full":"Alam Urquijo, 58 Bilbao Vizcaya 48011",
    "addr:housenumber":"58",
    "addr:postcode":"48011",
    "addr:street":"Alam Urquijo",
    "iso:country":"ES",
    "sg:address":"Alam Urquijo, 58",
    "sg:city":"Bilbao",
    "sg:orig_category":"Electrodom\u00c9sticos (al Por Menor)",
    "sg:phone":"+34 944 41 20 47",
    "sg:postcode":"48011",
    "sg:province":"Vizcaya",
    "wof:name":"Gonzalez Gutierrez Luis",
    "wof:placetype":"venue"
},
  "geometry": {"coordinates":[-2.9407150745,43.2611656189],"type":"Point"}
}