{
  "type": "Feature",
  "properties": {
    "addr:full":"Calle de Gaitan, 19 Jerez De La Frontera C\u00e1diz 11403",
    "addr:housenumber":"19",
    "addr:postcode":"11403",
    "addr:street":"Calle De Gaitan",
    "iso:country":"ES",
    "sg:address":"Calle de Gaitan, 19",
    "sg:city":"Jerez De La Frontera",
    "sg:orig_category":"Producci\u00d3n, Distribuci\u00d3n De Gas Butano Y Propano",
    "sg:phone":"+34 956 33 10 74",
    "sg:postcode":"11403",
    "sg:province":"C\u00e1diz",
    "wof:name":"Recsa Empresa Concesionaria S. A.",
    "wof:placetype":"venue"
},
  "geometry": {"coordinates":[-6.138133049,36.688331604],"type":"Point"}
}