{
  "type": "Feature",
  "properties": {
    "addr:full":"Del Milliarium, 17 Merida Badajoz 06800",
    "addr:housenumber":"17",
    "addr:postcode":"06800",
    "iso:country":"ES",
    "sg:address":"Del Milliarium, 17",
    "sg:city":"Merida",
    "sg:orig_category":"Ingenier\u00cda, Centros De Estudios (industria)",
    "sg:phone":"+34 924 30 19 86",
    "sg:postcode":"06800",
    "sg:province":"Badajoz",
    "wof:name":"Arellano Obrero Jose Luis",
    "wof:placetype":"venue"
},
  "geometry": {"coordinates":[-6.3487710953,38.9294929504],"type":"Point"}
}