{
  "type": "Feature",
  "properties": {
    "addr:full":"Calle de Albeniz, 2 Alcala Henares Madrid 28806",
    "addr:housenumber":"2",
    "addr:postcode":"28806",
    "addr:street":"Calle De Albeniz",
    "iso:country":"ES",
    "sg:address":"Calle de Albeniz, 2",
    "sg:city":"Alcala Henares",
    "sg:orig_category":"Alimentaci\u00d3n General (al Por Menor)",
    "sg:phone":"+34 918 81 65 92",
    "sg:postcode":"28806",
    "sg:province":"Madrid",
    "wof:name":"Lopez Pardo Ana Maria",
    "wof:placetype":"venue"
},
  "geometry": {"coordinates":[-3.375831604,40.4892272949],"type":"Point"}
}