{
  "type": "Feature",
  "properties": {
    "addr:full":"Ctra. Madrid, Km. 0192,0 Almazan Soria 42200",
    "addr:postcode":"42200",
    "addr:street":"Ctra. Madrid Km. 0192,0",
    "iso:country":"ES",
    "sg:address":"Ctra. Madrid, Km. 0192,0",
    "sg:city":"Almazan",
    "sg:orig_category":"Maquinaria Para Industrias Diversas",
    "sg:phone":"+34 975 30 04 60",
    "sg:postcode":"42200",
    "sg:province":"Soria",
    "wof:name":"Agromecanica Soriana S A L",
    "wof:placetype":"venue"
},
  "geometry": {"coordinates":[-2.529059,41.479839],"type":"Point"}
}