{
  "type": "Feature",
  "properties": {
    "iso:country":"ES",
    "sg:address":"Ric. Delgado Vizcaino, 12",
    "sg:city":"Pozoblanco",
    "sg:orig_category":"Muebles Y Accesorios Para Cocinas Y Cuartos De Ba\u00d1o (al Por Menor)",
    "sg:phone":"+34 957 77 09 82",
    "sg:postcode":"14400",
    "sg:province":"C\u00f3rdoba",
    "wof:name":"Romero Gonzalez Miguel",
    "wof:placetype":"venue"
},
  "geometry": {"coordinates":[-4.8492288589,38.3810462952],"type":"Point"}
}