{
  "type": "Feature",
  "properties": {
    "addr:full":"Calle de Catalina Suarez, 15 Madrid Madrid 28007",
    "addr:housenumber":"15",
    "addr:postcode":"madrid;28007",
    "addr:street":"Calle De Catalina Suarez",
    "iso:country":"ES",
    "sg:address":"Calle de Catalina Suarez, 15",
    "sg:city":"Madrid",
    "sg:orig_category":"Agencias Y Agentes Comerciales, Representantes",
    "sg:phone":"+34 915 51 86 51",
    "sg:postcode":"28007",
    "sg:province":"Madrid",
    "wof:name":"Lopez Arranz Eugenio",
    "wof:placetype":"venue"
},
  "geometry": {"coordinates":[-3.6706798077,40.4026641846],"type":"Point"}
}