{
  "type": "Feature",
  "properties": {
    "iso:country":"ES",
    "sg:address":"Calle de Tomas Rodriguez Puertas (de), 42",
    "sg:city":"Alcobendas",
    "sg:orig_category":"Pintura, Barniz, Productos Asimilables (fabricaci\u00d3n, Al Por Mayor)",
    "sg:phone":"+34 916 54 87 23",
    "sg:postcode":"28100",
    "sg:province":"Madrid",
    "wof:name":"Pulido Navacerrada Luis",
    "wof:placetype":"venue"
},
  "geometry": {"coordinates":[-3.6328680515,40.5431137085],"type":"Point"}
}