{
  "type": "Feature",
  "properties": {
    "addr:full":"Carrer de Diputacio, 10 Piera Barcelona 08784",
    "addr:housenumber":"10",
    "addr:postcode":"08784",
    "addr:street":"Carrer De Diputacio",
    "iso:country":"ES",
    "sg:address":"Carrer de Diputacio, 10",
    "sg:city":"Piera",
    "sg:orig_category":"Alimentaci\u00d3n General (al Por Menor)",
    "sg:phone":"+34 937 76 12 08",
    "sg:postcode":"08784",
    "sg:province":"Barcelona",
    "wof:name":"Calvo Pe\u00f1a Jose",
    "wof:placetype":"venue"
},
  "geometry": {"coordinates":[1.7571899891,41.5194091797],"type":"Point"}
}