{
  "type": "Feature",
  "properties": {
    "iso:country":"ES",
    "sg:address":"Calle de Gayarre, 11",
    "sg:city":"Tudela",
    "sg:orig_category":"Asistencia Domiciliaria",
    "sg:phone":"+34 948 82 09 76",
    "sg:postcode":"31500",
    "sg:province":"Navarra",
    "wof:name":"Siervas De Maria Ministras De Los Enfermos Provincia De Catalu\u00d1a Curia Provincial",
    "wof:placetype":"venue"
},
  "geometry": {"coordinates":[-1.608708024,42.0621566772],"type":"Point"}
}