{
  "type": "Feature",
  "properties": {
    "addr:full":"Calle de Glorieta, 2 Mahora Albacete 02240",
    "addr:housenumber":"2",
    "addr:postcode":"02240",
    "addr:street":"Calle De Glorieta",
    "iso:country":"ES",
    "sg:address":"Calle de Glorieta, 2",
    "sg:city":"Mahora",
    "sg:orig_category":"Estancos",
    "sg:phone":"+34 967 49 40 06",
    "sg:postcode":"02240",
    "sg:province":"Albacete",
    "wof:name":"Martinez Lozano Antonio",
    "wof:placetype":"venue"
},
  "geometry": {"coordinates":[-1.7229089737,39.2092208862],"type":"Point"}
}