{
  "type": "Feature",
  "properties": {
    "iso:country":"ES",
    "sg:address":"Avda Jose Fari\u00d1a, 58",
    "sg:city":"Huelva",
    "sg:orig_category":"Fisioterapia",
    "sg:phone":"+34 959 22 33 84",
    "sg:postcode":"21006",
    "sg:province":"Huelva",
    "wof:name":"Sanchez Gil Eva Maria",
    "wof:placetype":"venue"
},
  "geometry": {"coordinates":[-6.9365620613,37.2608795166],"type":"Point"}
}