{
  "type": "Feature",
  "properties": {
    "iso:country":"ES",
    "sg:address":"Carrer de Reina Cristina, 1",
    "sg:city":"Barcelona",
    "sg:orig_category":"Farmacias",
    "sg:phone":"+34 933 10 54 61",
    "sg:postcode":"08003",
    "sg:province":"Barcelona",
    "wof:name":"Condal Espinal Rosa Maria",
    "wof:placetype":"venue"
},
  "geometry": {"coordinates":[2.1829960346,41.381313324],"type":"Point"}
}