{
  "type": "Feature",
  "properties": {
    "addr:full":"Calle de Virgen Del Pilar, 2 Almoradi Alicante 03160",
    "addr:housenumber":"2",
    "addr:postcode":"03160",
    "addr:street":"Calle De Virgen Del Pilar",
    "iso:country":"ES",
    "sg:address":"Calle de Virgen Del Pilar, 2",
    "sg:city":"Almoradi",
    "sg:orig_category":"Arquitectos",
    "sg:phone":"+34 966 78 09 08",
    "sg:postcode":"03160",
    "sg:province":"Alicante",
    "wof:name":"Vilella Soriano Arquitectura S.l.u",
    "wof:placetype":"venue"
},
  "geometry": {"coordinates":[-0.7914929986,38.1098709106],"type":"Point"}
}