{
  "type": "Feature",
  "properties": {
    "iso:country":"ES",
    "sg:address":"Avda Arcentales, 26",
    "sg:city":"Madrid",
    "sg:orig_category":"Fisioterapia",
    "sg:phone":"+34 917 75 95 44",
    "sg:postcode":"28022",
    "sg:province":"Madrid",
    "wof:name":"Encefis S.l.",
    "wof:placetype":"venue"
},
  "geometry": {"coordinates":[-3.6088581085,40.4348220825],"type":"Point"}
}