{
  "type": "Feature",
  "properties": {
    "iso:country":"ES",
    "sg:address":"Calle de General Alvarez De Castro, 10",
    "sg:city":"Madrid",
    "sg:orig_category":"Reparaciones Y Remolcado De Veh\u00cdculos",
    "sg:phone":"+34 914 48 57 18",
    "sg:postcode":"28010",
    "sg:province":"Madrid",
    "wof:name":"Lletget Lletget Rafael",
    "wof:placetype":"venue"
},
  "geometry": {"coordinates":[-3.7017660141,40.434715271],"type":"Point"}
}