{
  "type": "Feature",
  "properties": {
    "iso:country":"ES",
    "sg:address":"Rua Pizarro, 73",
    "sg:city":"Vigo",
    "sg:orig_category":"Electrodom\u00c9sticos (al Por Menor)",
    "sg:phone":"+34 986 41 35 85",
    "sg:postcode":"36204",
    "sg:province":"Pontevedra",
    "wof:name":"Nascimiento Proenca Manuel Do",
    "wof:placetype":"venue"
},
  "geometry": {"coordinates":[-8.7116136551,42.2314300537],"type":"Point"}
}