{
  "type": "Feature",
  "properties": {
    "iso:country":"ES",
    "sg:address":"Calle de Einstein (de), 7",
    "sg:city":"Tres Cantos",
    "sg:orig_category":"Electromedicina: Equipo",
    "sg:phone":"+34 918 03 66 68",
    "sg:postcode":"28760",
    "sg:province":"Madrid",
    "wof:name":"Biomed S.a.",
    "wof:placetype":"venue"
},
  "geometry": {"coordinates":[-3.7093849182,40.5918807983],"type":"Point"}
}