{
  "type": "Feature",
  "properties": {
    "iso:country":"ES",
    "sg:address":"Plaz Reina Victoria, 1",
    "sg:city":"Pinofranqueado",
    "sg:orig_category":"Ense\u00d1anza, Formaci\u00d3n Profesional: Aprendizaje",
    "sg:phone":"+34 927 67 41 81",
    "sg:postcode":"10630",
    "sg:province":"C\u00e1ceres",
    "wof:name":"Ayuntamiento De Pinofranqueado",
    "wof:placetype":"venue"
},
  "geometry": {"coordinates":[-6.3864426613,40.3163146973],"type":"Point"}
}