{
  "type": "Feature",
  "properties": {
    "addr:full":"Calle de Rozabella, 4 Matas-pinar-monte Rozas Madrid 28290",
    "addr:housenumber":"4",
    "addr:postcode":"28290",
    "addr:street":"Calle De Rozabella",
    "iso:country":"ES",
    "sg:address":"Calle de Rozabella, 4",
    "sg:city":"Matas-pinar-monte Rozas",
    "sg:orig_category":"Servicios Diversos",
    "sg:phone":"+34 916 40 49 49",
    "sg:postcode":"28290",
    "sg:province":"Madrid",
    "wof:name":"Telegate Communication Systems S.a.",
    "wof:placetype":"venue"
},
  "geometry": {"coordinates":[-3.8927268982,40.5398864746],"type":"Point"}
}