{
  "type": "Feature",
  "properties": {
    "iso:country":"ES",
    "sg:address":"Vilablareix, 4",
    "sg:city":"Montfulla",
    "sg:orig_category":"Tapiceros Y Tapiceros",
    "sg:phone":"+34 972 40 52 80",
    "sg:postcode":"17162",
    "sg:province":"Girona",
    "wof:name":"Antonio Ortiz Pintor-decorador S.l.",
    "wof:placetype":"venue"
},
  "geometry": {"coordinates":[2.7623336315,41.9700241089],"type":"Point"}
}