{
  "type": "Feature",
  "properties": {
    "iso:country":"ES",
    "sg:address":"Calle de San Francisco, 10",
    "sg:city":"Alacant",
    "sg:orig_category":"Producci\u00d3n, Distribuci\u00d3n De Electricidad",
    "sg:phone":"+34 965 21 60 85",
    "sg:postcode":"03001",
    "sg:province":"Alicante",
    "wof:name":"Fuentes Clement Martin",
    "wof:placetype":"venue"
},
  "geometry": {"coordinates":[-0.4844349921,38.3442306519],"type":"Point"}
}