{
  "type": "Feature",
  "properties": {
    "addr:full":"Pl Roma Piera I Arcal, 4 Premia Mar Barcelona 08330",
    "addr:housenumber":"4",
    "addr:postcode":"08330",
    "addr:street":"Pl;Arcal",
    "iso:country":"ES",
    "sg:address":"Pl Roma Piera I Arcal, 4",
    "sg:city":"Premia Mar",
    "sg:orig_category":"Puertas Y Portales",
    "sg:phone":"+34 937 52 24 22",
    "sg:postcode":"08330",
    "sg:province":"Barcelona",
    "wof:name":"Recambios Y Servicios Tecnicos S.l.",
    "wof:placetype":"venue"
},
  "geometry": {"coordinates":[2.3600459099,41.4919776917],"type":"Point"}
}