{
  "type": "Feature",
  "properties": {
    "iso:country":"ES",
    "sg:address":"Calle de Carlos Martin Alvarez, 11",
    "sg:city":"Madrid",
    "sg:orig_category":"Inmobiliaria (agencias)",
    "sg:phone":"+34 917 57 04 04",
    "sg:postcode":"28018",
    "sg:province":"Madrid",
    "wof:name":"Square Metre Xxi S.l.",
    "wof:placetype":"venue"
},
  "geometry": {"coordinates":[-3.6625001431,40.3906059265],"type":"Point"}
}