{
  "type": "Feature",
  "properties": {
    "addr:full":"Gta Cuatro Caminos, 9 Madrid Madrid 28020",
    "addr:housenumber":"9",
    "addr:postcode":"madrid;28020",
    "addr:street":"Gta Cuatro Caminos",
    "iso:country":"ES",
    "sg:address":"Gta Cuatro Caminos, 9",
    "sg:city":"Madrid",
    "sg:orig_category":"Estancos",
    "sg:phone":"+34 915 34 01 79",
    "sg:postcode":"28020",
    "sg:province":"Madrid",
    "wof:name":"Labra Martinez Rosario",
    "wof:placetype":"venue"
},
  "geometry": {"coordinates":[-3.703938961,40.4472732544],"type":"Point"}
}