{
  "type": "Feature",
  "properties": {
    "addr:full":"Calle de Concepcion Arenal, 19 Almeria Almer\u00eda 04001",
    "addr:housenumber":"19",
    "addr:postcode":"04001",
    "addr:street":"Calle De Concepcion Arenal",
    "iso:country":"ES",
    "sg:address":"Calle de Concepcion Arenal, 19",
    "sg:city":"Almeria",
    "sg:orig_category":"Ropa Para Ni\u00d1os (al Por Menor)",
    "sg:phone":"+34 950 27 23 76",
    "sg:postcode":"04001",
    "sg:province":"Almer\u00eda",
    "sg:website":"www.charanga.es",
    "wof:name":"Milla Med S.a.",
    "wof:placetype":"venue"
},
  "geometry": {"coordinates":[-2.4651317596,36.8406219482],"type":"Point"}
}