{
  "type": "Feature",
  "properties": {
    "iso:country":"ES",
    "sg:address":"Calle de Concepcion Arenal, 3",
    "sg:city":"Alcala Henares",
    "sg:orig_category":"Internados & Ense\u00d1anza Privada",
    "sg:phone":"+34 918 87 11 14",
    "sg:postcode":"28806",
    "sg:province":"Madrid",
    "wof:name":"Colegio San Ignacio",
    "wof:placetype":"venue"
},
  "geometry": {"coordinates":[-3.3657128811,40.4960594177],"type":"Point"}
}