{
  "type": "Feature",
  "properties": {
    "addr:full":"Pl Espanya (d'), 11 Gata Gorgos Alicante 03740",
    "addr:postcode":"03740",
    "addr:street":"Pl",
    "iso:country":"ES",
    "sg:address":"Pl Espanya (d'), 11",
    "sg:city":"Gata Gorgos",
    "sg:orig_category":"Artesan\u00cda",
    "sg:phone":"+34 965 75 72 80",
    "sg:postcode":"03740",
    "sg:province":"Alicante",
    "wof:name":"Mulet Boronat Maria",
    "wof:placetype":"venue"
},
  "geometry": {"coordinates":[0.0839079991,38.7759056091],"type":"Point"}
}