{
  "type": "Feature",
  "properties": {
    "addr:full":"Calle de Almirante Chicarro, 5 Viveiro Lugo 27850",
    "addr:housenumber":"5",
    "addr:postcode":"27850",
    "addr:street":"Calle De Almirante Chicarro",
    "iso:country":"ES",
    "sg:address":"Calle de Almirante Chicarro, 5",
    "sg:city":"Viveiro",
    "sg:orig_category":"Ingeniero",
    "sg:phone":"+34 982 56 29 52",
    "sg:postcode":"27850",
    "sg:province":"Lugo",
    "wof:name":"Bellas Pernas Hipolito",
    "wof:placetype":"venue"
},
  "geometry": {"coordinates":[-7.5957427025,43.6607666016],"type":"Point"}
}