{
  "type": "Feature",
  "properties": {
    "iso:country":"ES",
    "sg:address":"Huerta Palacio, 1",
    "sg:city":"Villanueva Vera",
    "sg:orig_category":"Imprenta",
    "sg:phone":"+34 927 56 71 66",
    "sg:postcode":"10470",
    "sg:province":"C\u00e1ceres",
    "wof:name":"La Bravia C.b.",
    "wof:placetype":"venue"
},
  "geometry": {"coordinates":[-5.4632539749,40.1316947937],"type":"Point"}
}