{
  "type": "Feature",
  "properties": {
    "addr:full":"Avda Alcalde Manuel De La Pinta, 15 Cadiz C\u00e1diz 11011",
    "addr:housenumber":"15",
    "addr:postcode":"11011",
    "addr:street":"Avda Alcalde Manuel De La Pinta",
    "iso:country":"ES",
    "sg:address":"Avda Alcalde Manuel De La Pinta, 15",
    "sg:city":"Cadiz",
    "sg:orig_category":"Alimentaci\u00d3n General (al Por Menor)",
    "sg:phone":"+34 956 27 89 68",
    "sg:postcode":"11011",
    "sg:province":"C\u00e1diz",
    "wof:name":"Perez Martinez Cesareo",
    "wof:placetype":"venue"
},
  "geometry": {"coordinates":[-6.2716369629,36.5028991699],"type":"Point"}
}