{
  "type": "Feature",
  "properties": {
    "addr:full":"Avda Toreros, 22 Madrid Madrid 28028",
    "addr:housenumber":"22",
    "addr:postcode":"madrid;28028",
    "addr:street":"Avda Toreros",
    "iso:country":"ES",
    "sg:address":"Avda Toreros, 22",
    "sg:city":"Madrid",
    "sg:orig_category":"Alimentaci\u00d3n General (al Por Menor)",
    "sg:phone":"+34 913 61 44 44",
    "sg:postcode":"28028",
    "sg:province":"Madrid",
    "wof:name":"Chen  Youcund",
    "wof:placetype":"venue"
},
  "geometry": {"coordinates":[-3.6680390835,40.4320449829],"type":"Point"}
}