{
  "type": "Feature",
  "properties": {
    "addr:full":"Calle de Puerto De Navacerrada, 4 Arroyomolinos Madrid 28939",
    "addr:housenumber":"4",
    "addr:postcode":"28939",
    "addr:street":"Calle De Puerto De Navacerrada",
    "iso:country":"ES",
    "sg:address":"Calle de Puerto De Navacerrada, 4",
    "sg:city":"Arroyomolinos",
    "sg:orig_category":"Asociaciones Y Clubs Deportivos",
    "sg:phone":"+34 916 47 98 23",
    "sg:postcode":"28939",
    "sg:province":"Madrid",
    "sg:website":"www.decimas.es",
    "wof:name":"Sport-street S. L.",
    "wof:placetype":"venue"
},
  "geometry": {"coordinates":[-3.9280011654,40.3007392883],"type":"Point"}
}