{
  "type": "Feature",
  "properties": {
    "addr:full":"Av Mediterrania, S/n Serres Girona 17411",
    "addr:housenumber":"s / n",
    "addr:postcode":"17411",
    "addr:street":"Av Mediterrania",
    "iso:country":"ES",
    "sg:address":"Av Mediterrania, S/n",
    "sg:city":"Serres",
    "sg:orig_category":"Centros De Educaci\u00d3n Especial",
    "sg:phone":"+34 972 85 08 08",
    "sg:postcode":"17411",
    "sg:province":"Girona",
    "wof:name":"Ajuntament De Vidreres",
    "wof:placetype":"venue"
},
  "geometry": {"coordinates":[2.8236999512,41.9817962646],"type":"Point"}
}