{
  "type": "Feature",
  "properties": {
    "iso:country":"ES",
    "sg:address":"Calle de Placido Pe\u00d1a, 121",
    "sg:city":"Vilalba",
    "sg:orig_category":"Empresas De Carpinter\u00cda Met\u00c1lica",
    "sg:phone":"+34 982 51 23 02",
    "sg:postcode":"27800",
    "sg:province":"Lugo",
    "wof:name":"Aluminios Villa-lugo S.l.",
    "wof:placetype":"venue"
},
  "geometry": {"coordinates":[-7.6810860634,43.3023948669],"type":"Point"}
}