{
  "type": "Feature",
  "properties": {
    "addr:full":"Calle de Real, 29 Utrera Sevilla 41710",
    "addr:housenumber":"29",
    "addr:postcode":"41710",
    "addr:street":"Calle De Real",
    "iso:country":"ES",
    "sg:address":"Calle de Real, 29",
    "sg:city":"Utrera",
    "sg:orig_category":"Farmacias",
    "sg:phone":"+34 954 86 18 40",
    "sg:postcode":"41710",
    "sg:province":"Sevilla",
    "wof:name":"Gonzalez Fernandez Rafael",
    "wof:placetype":"venue"
},
  "geometry": {"coordinates":[-5.7837529182,37.1886291504],"type":"Point"}
}