{
  "type": "Feature",
  "properties": {
    "addr:full":"Calle de Palestina, 1 Malaga M\u00e1laga 29007",
    "addr:housenumber":"1",
    "addr:postcode":"29007",
    "addr:street":"Calle De Palestina;Ma\u0301Laga",
    "iso:country":"ES",
    "sg:address":"Calle de Palestina, 1",
    "sg:city":"Malaga",
    "sg:orig_category":"Electromec\u00c1nica",
    "sg:phone":"+34 952 39 52 89",
    "sg:postcode":"29007",
    "sg:province":"M\u00e1laga",
    "sg:website":"www.bjc.es",
    "wof:name":"Fabrica Electrotecnica Josa S.a.",
    "wof:placetype":"venue"
},
  "geometry": {"coordinates":[-4.4395699501,36.7177581787],"type":"Point"}
}