{
  "type": "Feature",
  "properties": {
    "iso:country":"ES",
    "sg:address":"Calle de Fornillos, 10",
    "sg:city":"Madrid",
    "sg:orig_category":"Alimentaci\u00d3n General (al Por Menor)",
    "sg:phone":"+34 914 69 74 14",
    "sg:postcode":"28026",
    "sg:province":"Madrid",
    "wof:name":"Olalla Jurado De Herrera Rita Maria",
    "wof:placetype":"venue"
},
  "geometry": {"coordinates":[-3.7144999504,40.3825035095],"type":"Point"}
}