{
  "type": "Feature",
  "properties": {
    "addr:full":"Avda Canarias, 240 Vecindario Las Palmas 35110",
    "addr:housenumber":"240",
    "addr:postcode":"35110",
    "addr:street":"Avda Canarias;Las Palmas",
    "iso:country":"ES",
    "sg:address":"Avda Canarias, 240",
    "sg:city":"Vecindario",
    "sg:orig_category":"Distribuci\u00d3n De Petr\u00d3leo Y Derivados",
    "sg:phone":"+34 928 75 00 76",
    "sg:postcode":"35110",
    "sg:province":"Las Palmas",
    "wof:name":"Franco Armas Maria Del Carmen",
    "wof:placetype":"venue"
},
  "geometry": {"coordinates":[-15.4415330887,27.8506202698],"type":"Point"}
}