{
  "type": "Feature",
  "properties": {
    "iso:country":"ES",
    "sg:address":"Bronce, 16",
    "sg:city":"Borox",
    "sg:orig_category":"Art\u00cdculos De Decoraci\u00d3n",
    "sg:phone":"+34 925 52 70 21",
    "sg:postcode":"45222",
    "sg:province":"Toledo",
    "wof:name":"Nice House S.l.",
    "wof:placetype":"venue"
},
  "geometry": {"coordinates":[-3.6797940731,40.0390090942],"type":"Point"}
}