{
  "type": "Feature",
  "properties": {
    "iso:country":"ES",
    "sg:address":"Pl Catalunya, 15",
    "sg:city":"Olesa Montserrat",
    "sg:orig_category":"Centros De Adelgazamiento Y De Est\u00c9tica",
    "sg:phone":"+34 937 78 65 32",
    "sg:postcode":"08640",
    "sg:province":"Barcelona",
    "wof:name":"Vargas Baltanas Elisabet",
    "wof:placetype":"venue"
},
  "geometry": {"coordinates":[1.894718051,41.5411911011],"type":"Point"}
}