{
  "type": "Feature",
  "properties": {
    "addr:full":"San Saturnino, 16 Iru\u00f1a Navarra 31001",
    "addr:housenumber":"16",
    "addr:postcode":"31001",
    "addr:street":"Saturnino",
    "iso:country":"ES",
    "sg:address":"San Saturnino, 16",
    "sg:city":"Iru\u00f1a",
    "sg:orig_category":"Carnicer\u00cdas, Carnicer\u00cdas",
    "sg:phone":"+34 948 22 17 53",
    "sg:postcode":"31001",
    "sg:province":"Navarra",
    "wof:name":"Leranoz Gamio Jose Javier",
    "wof:placetype":"venue"
},
  "geometry": {"coordinates":[-1.6447610855,42.8182907104],"type":"Point"}
}