{
  "type": "Feature",
  "properties": {
    "addr:full":"Ctra Cardona Casas, Km. 0007,0 Montmajor Barcelona 08612",
    "addr:postcode":"08612",
    "addr:street":"Ctra Cardona Casas Km. 0007,0",
    "iso:country":"ES",
    "sg:address":"Ctra Cardona Casas, Km. 0007,0",
    "sg:city":"Montmajor",
    "sg:orig_category":"Gr\u00daas, Montacargas Y Elevadores Para Astilleros",
    "sg:phone":"+34 938 24 61 42",
    "sg:postcode":"08612",
    "sg:province":"Barcelona",
    "wof:name":"Aesa Eurogondolas S.l.",
    "wof:placetype":"venue"
},
  "geometry": {"coordinates":[1.7441475391,41.995677948],"type":"Point"}
}