{
  "type": "Feature",
  "properties": {
    "addr:full":"Calle de Maria Diaz De Haro Kalea, 3 Lekeitio Vizcaya 48280",
    "addr:housenumber":"3",
    "addr:postcode":"48280",
    "addr:street":"Calle De Maria Diaz De Haro Kalea",
    "iso:country":"ES",
    "sg:address":"Calle de Maria Diaz De Haro Kalea, 3",
    "sg:city":"Lekeitio",
    "sg:classifiers":[
        {
            "category":"Autos & Motor Vehicles",
            "subcategory":"Automobile Sales",
            "type":"Retail Goods"
        }
    ],
    "sg:phone":"+34 946 84 18 00",
    "sg:postcode":"48280",
    "sg:province":"Vizcaya",
    "wof:name":"Gipuzkoarena Heziketa S.l.l.",
    "wof:placetype":"venue"
},
  "geometry": {"coordinates":[-2.5047550201,43.3661308289],"type":"Point"}
}