{
  "type": "Feature",
  "properties": {
    "addr:full":"Calle de Paseo, 12 Carcar Navarra 31579",
    "addr:housenumber":"12",
    "addr:postcode":"31579",
    "addr:street":"Calle De Paseo",
    "iso:country":"ES",
    "sg:address":"Calle de Paseo, 12",
    "sg:city":"Carcar",
    "sg:orig_category":"Cadenas, Estaciones, Cableados Para Radio Y Televisi\u00d3n",
    "sg:phone":"+34 948 69 00 77",
    "sg:postcode":"31579",
    "sg:province":"Navarra",
    "wof:name":"Moreno Santos Luis",
    "wof:placetype":"venue"
},
  "geometry": {"coordinates":[-1.9782429934,42.3949165344],"type":"Point"}
}