{
  "type": "Feature",
  "properties": {
    "addr:full":"Calle de Santo Tomas, 24 Cadiz C\u00e1diz 11009",
    "addr:housenumber":"24",
    "addr:postcode":"11009",
    "addr:street":"Calle De Santo Tomas",
    "iso:country":"ES",
    "sg:address":"Calle de Santo Tomas, 24",
    "sg:city":"Cadiz",
    "sg:orig_category":"Material Y Suministros Para Dentistas, Cirujanos",
    "sg:phone":"+34 956 26 35 31",
    "sg:postcode":"11009",
    "sg:province":"C\u00e1diz",
    "wof:name":"Diaz Melero Emilio",
    "wof:placetype":"venue"
},
  "geometry": {"coordinates":[-6.2752118111,36.5088539124],"type":"Point"}
}