{
  "type": "Feature",
  "properties": {
    "addr:full":"Av Medico Stgo Vidal, 16 Sollana Valencia 46430",
    "addr:housenumber":"16",
    "addr:postcode":"46430",
    "addr:street":"Av Medico;Vidal",
    "iso:country":"ES",
    "sg:address":"Av Medico Stgo Vidal, 16",
    "sg:city":"Sollana",
    "sg:orig_category":"Parafarmacias",
    "sg:phone":"+34 961 74 07 35",
    "sg:postcode":"46430",
    "sg:province":"Valencia",
    "wof:name":"Domingo Blasco C.b.",
    "wof:placetype":"venue"
},
  "geometry": {"coordinates":[-0.3822239935,39.2773780823],"type":"Point"}
}