{
  "type": "Feature",
  "properties": {
    "addr:full":"Plaz Cervantes, 7 Alcala Henares Madrid 28801",
    "addr:housenumber":"7",
    "addr:postcode":"28801",
    "addr:street":"Plaz Cervantes",
    "iso:country":"ES",
    "sg:address":"Plaz Cervantes, 7",
    "sg:city":"Alcala Henares",
    "sg:orig_category":"Fabricaci\u00d3n, Importaci\u00d3n, Venta De Material De Telefon\u00cda, Peritelefon\u00cda",
    "sg:phone":"+34 918 82 08 73",
    "sg:postcode":"28801",
    "sg:province":"Madrid",
    "wof:name":"Vodafone Espa\u00d1a S.a.",
    "wof:placetype":"venue"
},
  "geometry": {"coordinates":[-3.3640007973,40.482624054],"type":"Point"}
}