{
  "type": "Feature",
  "properties": {
    "iso:country":"ES",
    "sg:address":"En Bosch, 36",
    "sg:city":"Lli\u00e7a Amunt",
    "sg:orig_category":"Distribuci\u00d3n De Petr\u00d3leo Y Derivados",
    "sg:phone":"+34 938 41 72 65",
    "sg:postcode":"08186",
    "sg:province":"Barcelona",
    "wof:name":"Jaucar Oil S.l.",
    "wof:placetype":"venue"
},
  "geometry": {"coordinates":[2.2349491119,41.6134567261],"type":"Point"}
}