{
  "type": "Feature",
  "properties": {
    "addr:full":"Estd Rua (da), Km. 0022,0 Viana Do Bolo Ourense 32550",
    "addr:postcode":"32550",
    "addr:street":"Rua Da Km. 0022,0",
    "iso:country":"ES",
    "sg:address":"Estd Rua (da), Km. 0022,0",
    "sg:city":"Viana Do Bolo",
    "sg:orig_category":"Mec\u00c1nico Del Autom\u00d3vil",
    "sg:phone":"+34 988 32 90 19",
    "sg:postcode":"32550",
    "sg:province":"Ourense",
    "wof:name":"Rodriguez Rodriguez Jose",
    "wof:placetype":"venue"
},
  "geometry": {"coordinates":[-7.1098628044,42.1833190918],"type":"Point"}
}