{
  "type": "Feature",
  "properties": {
    "iso:country":"ES",
    "sg:address":"Eibarko Txikito Kalea, 12",
    "sg:city":"Eibar",
    "sg:orig_category":"Fisioterapia",
    "sg:phone":"+34 943 12 14 80",
    "sg:postcode":"20600",
    "sg:province":"Guip\u00f9zcoa",
    "wof:name":"Lopez De Guere\u00f1u Urisabel Oscar",
    "wof:placetype":"venue"
},
  "geometry": {"coordinates":[-2.4713747501,43.1844863892],"type":"Point"}
}