{
  "type": "Feature",
  "properties": {
    "addr:full":"Ctra Ribes, 123 Corro D'avall Barcelona 08520",
    "addr:housenumber":"123",
    "addr:postcode":"08520",
    "addr:street":"Ctra Ribes;D'Avall Barcelona",
    "iso:country":"ES",
    "sg:address":"Ctra Ribes, 123",
    "sg:city":"Corro D'avall",
    "sg:orig_category":"Colorantes, Colores Y Pigmentos (fabricaci\u00d3n, Al Por Mayor)",
    "sg:phone":"+34 938 49 26 27",
    "sg:postcode":"08520",
    "sg:province":"Barcelona",
    "wof:name":"Agroquimica Del Valles S.l.",
    "wof:placetype":"venue"
},
  "geometry": {"coordinates":[2.2878687382,41.6696929932],"type":"Point"}
}