{
  "type": "Feature",
  "properties": {
    "addr:full":"Calle de Merida, S/n Badajoz Badajoz 06006",
    "addr:postcode":"06006",
    "addr:street":"Calle De Merida S / N",
    "iso:country":"ES",
    "sg:address":"Calle de Merida, S/n",
    "sg:city":"Badajoz",
    "sg:orig_category":"Panader\u00cdas, Panader\u00cdas",
    "sg:phone":"+34 924 27 63 11",
    "sg:postcode":"06006",
    "sg:province":"Badajoz",
    "wof:name":"Perez Garcia Francisco",
    "wof:placetype":"venue"
},
  "geometry": {"coordinates":[-6.9834389687,38.8858795166],"type":"Point"}
}