{
  "type": "Feature",
  "properties": {
    "addr:full":"Avda Xunqueira (a), S/n Reibon Pontevedra 36955",
    "addr:housenumber":"s",
    "addr:postcode":"36955",
    "addr:street":"Avda Xunqueira A;/ N",
    "iso:country":"ES",
    "sg:address":"Avda Xunqueira (a), S/n",
    "sg:city":"Reibon",
    "sg:orig_category":"Asociaciones Y Clubs Deportivos",
    "sg:phone":"+34 986 31 28 80",
    "sg:postcode":"36955",
    "sg:province":"Pontevedra",
    "wof:name":"Concello De Moa\u00d1a",
    "wof:placetype":"venue"
},
  "geometry": {"coordinates":[-8.7202234268,42.2883415222],"type":"Point"}
}