{
  "type": "Feature",
  "properties": {
    "iso:country":"ES",
    "sg:address":"Calle de Gustavo Adolfo Becquer, S/n",
    "sg:city":"Puerto Lumbreras",
    "sg:orig_category":"Electromec\u00c1nica",
    "sg:phone":"+34 968 40 25 21",
    "sg:postcode":"30890",
    "sg:province":"Murcia",
    "wof:name":"Talleres Joansa S.l.",
    "wof:placetype":"venue"
},
  "geometry": {"coordinates":[-1.8018740416,37.5681838989],"type":"Point"}
}