{
  "type": "Feature",
  "properties": {
    "addr:full":"Cno Membrio (zona Industrial), S/n San Vicente Alcantara Badajoz 06500",
    "addr:housenumber":"/ n",
    "addr:postcode":"06500",
    "addr:street":"Cno Membrio Zona Industrial S",
    "iso:country":"ES",
    "sg:address":"Cno Membrio (zona Industrial), S/n",
    "sg:city":"San Vicente Alcantara",
    "sg:orig_category":"M\u00c1rmoles, Granitos Y Piedras Naturales",
    "sg:phone":"+34 924 41 02 72",
    "sg:postcode":"06500",
    "sg:province":"Badajoz",
    "wof:name":"Marmoles Cu\u00d1o Guevara C.b.",
    "wof:placetype":"venue"
},
  "geometry": {"coordinates":[-7.1375741959,39.3639183044],"type":"Point"}
}