{
  "type": "Feature",
  "properties": {
    "iso:country":"ES",
    "sg:address":"Calle de Gremio De Los Canteros (del), S/n",
    "sg:city":"Hontoria",
    "sg:orig_category":"Imprenta",
    "sg:phone":"+34 921 41 29 07",
    "sg:postcode":"40195",
    "sg:province":"Segovia",
    "wof:name":"Imprenta Taller Imagen S.l.",
    "wof:placetype":"venue"
},
  "geometry": {"coordinates":[-4.1104226112,40.9057273865],"type":"Point"}
}