{
  "type": "Feature",
  "properties": {
    "iso:country":"ES",
    "sg:address":"Kontzezino Kalea, 14",
    "sg:city":"Arrasate",
    "sg:orig_category":"Molduras, Junquillos, Listones Y Molduras Perforadas",
    "sg:phone":"+34 943 71 29 94",
    "sg:postcode":"20500",
    "sg:province":"Guip\u00f9zcoa",
    "wof:name":"Alberto Matilla Uranga Y Otros , C.b",
    "wof:placetype":"venue"
},
  "geometry": {"coordinates":[-2.4913787842,43.0636291504],"type":"Point"}
}