{
  "type": "Feature",
  "properties": {
    "iso:country":"ES",
    "sg:address":"Plaz Balbino Garitaonandia Plaza, 2",
    "sg:city":"Durango",
    "sg:orig_category":"Asociaciones, Organismos Culturales Y Socioeducativos",
    "sg:phone":"+34 946 20 11 50",
    "sg:postcode":"48200",
    "sg:province":"Vizcaya",
    "wof:name":"Intxaurre Kultur Elkartea",
    "wof:placetype":"venue"
},
  "geometry": {"coordinates":[-2.6309731007,43.1655044556],"type":"Point"}
}