{
  "type": "Feature",
  "properties": {
    "addr:full":"Carr Olerdola, 37 Vilanova I La Geltru Barcelona 08800",
    "addr:housenumber":"37",
    "addr:postcode":"08800",
    "addr:street":"Carr Olerdola",
    "iso:country":"ES",
    "sg:address":"Carr Olerdola, 37",
    "sg:city":"Vilanova I La Geltru",
    "sg:orig_category":"Importaci\u00d3n",
    "sg:phone":"+34 938 10 55 18",
    "sg:postcode":"08800",
    "sg:province":"Barcelona",
    "wof:name":"Ags Brand Engineer Group S.l.",
    "wof:placetype":"venue"
},
  "geometry": {"coordinates":[1.7124441862,41.2187423706],"type":"Point"}
}