{
  "type": "Feature",
  "properties": {
    "iso:country":"ES",
    "sg:address":"Avda Flores, 17",
    "sg:city":"Carballo",
    "sg:orig_category":"Supermercados Y Hipermercados",
    "sg:phone":"+34 981 70 04 50",
    "sg:postcode":"15100",
    "sg:province":"La Coru\u00f1a",
    "wof:name":"Lorenzo Garcia Jesus",
    "wof:placetype":"venue"
},
  "geometry": {"coordinates":[-8.6989088058,43.2144393921],"type":"Point"}
}