{
  "type": "Feature",
  "properties": {
    "iso:country":"ES",
    "sg:address":"Santiago Apostol, 2",
    "sg:city":"Algemesi",
    "sg:orig_category":"Frutas, Legumbres Frescas Y Tempranas (al Por Menor)",
    "sg:phone":"+34 962 42 63 01",
    "sg:postcode":"46680",
    "sg:province":"Valencia",
    "wof:name":"Ortiz Martinez Jose",
    "wof:placetype":"venue"
},
  "geometry": {"coordinates":[-0.4330439866,39.1920776367],"type":"Point"}
}