{
  "type": "Feature",
  "properties": {
    "iso:country":"ES",
    "sg:address":"Calle de San Maximiliano, 8",
    "sg:city":"Madrid",
    "sg:orig_category":"Frutas, Legumbres Frescas Y Tempranas (al Por Menor)",
    "sg:phone":"+34 917 26 36 03",
    "sg:postcode":"28017",
    "sg:province":"Madrid",
    "wof:name":"Frutas Gonzalez Garzon S.l.",
    "wof:placetype":"venue"
},
  "geometry": {"coordinates":[-3.6557219028,40.4232063293],"type":"Point"}
}