{
  "type": "Feature",
  "properties": {
    "addr:full":"Pol Ind Polirrosa, 264 Huelva Huelva 21007",
    "addr:housenumber":"264",
    "addr:postcode":"21007",
    "addr:street":"Polirrosa",
    "iso:country":"ES",
    "sg:address":"Pol Ind Polirrosa, 264",
    "sg:city":"Huelva",
    "sg:orig_category":"Maquinaria Para Industrias Diversas",
    "sg:phone":"+34 959 23 30 02",
    "sg:postcode":"21007",
    "sg:province":"Huelva",
    "wof:name":"Gadisa Maquinaria S.l.",
    "wof:placetype":"venue"
},
  "geometry": {"coordinates":[-6.9495940208,37.256313324],"type":"Point"}
}