{
  "type": "Feature",
  "properties": {
    "iso:country":"ES",
    "sg:address":"S. Roque, S/n",
    "sg:city":"Fuentelespino De Moya",
    "sg:orig_category":"Material Y Herramientas Agr\u00cdcolas",
    "sg:phone":"+34 969 36 11 20",
    "sg:postcode":"16311",
    "sg:province":"Cuenca",
    "wof:name":"Navarro Laiguera Secundino",
    "wof:placetype":"venue"
},
  "geometry": {"coordinates":[-1.4686650038,39.9179344177],"type":"Point"}
}