{
  "type": "Feature",
  "properties": {
    "iso:country":"ES",
    "sg:address":"La Rasa, S/n",
    "sg:city":"Arenas-santiago",
    "sg:orig_category":"Bosques (trabajos, Asesor\u00cda, Gesti\u00d3n)",
    "sg:phone":"+34 985 73 59 42",
    "sg:postcode":"33936",
    "sg:province":"Asturias",
    "sg:website":"wwwviarsa.com",
    "wof:name":"Viarsa",
    "wof:placetype":"venue"
},
  "geometry": {"coordinates":[-5.6342859268,43.3494987488],"type":"Point"}
}