{
  "type": "Feature",
  "properties": {
    "iso:country":"ES",
    "sg:address":"Ctra Madres Las, 1",
    "sg:city":"Firgas",
    "sg:classifiers":[
        {
            "category":"Autos & Motor Vehicles",
            "subcategory":"Automobile Sales",
            "type":"Retail Goods"
        }
    ],
    "sg:phone":"+34 928 61 66 44",
    "sg:postcode":"35430",
    "sg:province":"Las Palmas",
    "wof:name":"Sosa Santana Victor",
    "wof:placetype":"venue"
},
  "geometry": {"coordinates":[-15.5629138947,28.1076831818],"type":"Point"}
}