{
  "type": "Feature",
  "properties": {
    "iso:country":"ES",
    "sg:address":"Calle de Rio Boeza, 11",
    "sg:city":"Bembibre",
    "sg:orig_category":"Enfermeras: Consultas, Atenci\u00d3n A Domicilio",
    "sg:phone":"+34 987 51 19 31",
    "sg:postcode":"24300",
    "sg:province":"Le\u00f3n",
    "wof:name":"Lopez Moran Luis",
    "wof:placetype":"venue"
},
  "geometry": {"coordinates":[-6.4182338715,42.6156654358],"type":"Point"}
}