{
  "type": "Feature",
  "properties": {
    "addr:full":"Calle de Salud, 1 Sonseca Toledo 45100",
    "addr:housenumber":"1",
    "addr:postcode":"45100",
    "addr:street":"Calle De Salud",
    "iso:country":"ES",
    "sg:address":"Calle de Salud, 1",
    "sg:city":"Sonseca",
    "sg:orig_category":"Maquinaria Y Herramientas Para Madera, Pvc, Aluminio Y Aperos (fabricaci\u00d3n, Comercio)",
    "sg:phone":"+34 925 38 28 12",
    "sg:postcode":"45100",
    "sg:province":"Toledo",
    "wof:name":"Francisco Valentin S.l.",
    "wof:placetype":"venue"
},
  "geometry": {"coordinates":[-3.9763090611,39.6739196777],"type":"Point"}
}