{
  "type": "Feature",
  "properties": {
    "iso:country":"ES",
    "sg:address":"Calle de Ilustracion, 3",
    "sg:city":"Madrid",
    "sg:orig_category":"Perfumer\u00cda (al Por Menor)",
    "sg:phone":"+34 915 47 91 24",
    "sg:postcode":"28008",
    "sg:province":"Madrid",
    "wof:name":"Blanco De La Vega Juan Luis",
    "wof:placetype":"venue"
},
  "geometry": {"coordinates":[-3.7164030075,40.421081543],"type":"Point"}
}