{
  "type": "Feature",
  "properties": {
    "iso:country":"ES",
    "sg:address":"Carr Ordines, 38",
    "sg:city":"Petra",
    "sg:orig_category":"Ense\u00d1anza: Profesiones Art\u00cdsticas",
    "sg:phone":"+34 971 56 11 67",
    "sg:postcode":"07520",
    "sg:province":"Islas Baleares",
    "wof:name":"Font Torrens Juan",
    "wof:placetype":"venue"
},
  "geometry": {"coordinates":[3.1115710735,39.6151847839],"type":"Point"}
}