{
  "type": "Feature",
  "properties": {
    "iso:country":"ES",
    "sg:address":"Carrer de Balcans, 90",
    "sg:city":"Sabadell",
    "sg:orig_category":"Delegados, Agentes De Tr\u00c1nsito, Auxiliares De Transporte Internacional",
    "sg:phone":"+34 937 16 25 16",
    "sg:postcode":"08207",
    "sg:province":"Barcelona",
    "wof:name":"Lara Macias Manuel",
    "wof:placetype":"venue"
},
  "geometry": {"coordinates":[2.089951992,41.5743637085],"type":"Point"}
}