{
  "type": "Feature",
  "properties": {
    "addr:full":"Calle de Gata, 10 Denia Alicante 03700",
    "addr:housenumber":"10",
    "addr:postcode":"03700",
    "addr:street":"Calle De Gata",
    "iso:country":"ES",
    "sg:address":"Calle de Gata, 10",
    "sg:city":"Denia",
    "sg:orig_category":"Textil",
    "sg:phone":"+34 965 78 12 47",
    "sg:postcode":"03700",
    "sg:province":"Alicante",
    "wof:name":"Madibo S.l.",
    "wof:placetype":"venue"
},
  "geometry": {"coordinates":[0.1114400029,38.8428153992],"type":"Point"}
}