{
  "type": "Feature",
  "properties": {
    "iso:country":"ES",
    "sg:address":"Calle de Moratin, 17",
    "sg:city":"Valencia",
    "sg:orig_category":"Notarios",
    "sg:phone":"+34 963 52 80 85",
    "sg:postcode":"46002",
    "sg:province":"Valencia",
    "wof:name":"Almazan Y Pascual Notarios C.b.",
    "wof:placetype":"venue"
},
  "geometry": {"coordinates":[-0.3755679131,39.4704666138],"type":"Point"}
}