{
  "type": "Feature",
  "properties": {
    "addr:full":"Calle de Queipo De Llano, 2 Santa Cruz De Paniagua C\u00e1ceres 10661",
    "addr:housenumber":"2",
    "addr:postcode":"10661",
    "addr:street":"Calle De Queipo De Llano;Ca\u0301Ceres",
    "iso:country":"ES",
    "sg:address":"Calle de Queipo De Llano, 2",
    "sg:city":"Santa Cruz De Paniagua",
    "sg:classifiers":[
        {
            "category":"Taxi",
            "type":"Transportation"
        }
    ],
    "sg:phone":"+34 927 67 76 00",
    "sg:postcode":"10661",
    "sg:province":"C\u00e1ceres",
    "wof:name":"Anton Batuecas Dativo",
    "wof:placetype":"venue"
},
  "geometry": {"coordinates":[-6.3415942192,40.1912727356],"type":"Point"}
}