{
  "type": "Feature",
  "properties": {
    "addr:full":"Calle de Do\u00d1a Perfecta, 213 Palmas De Gran Canaria Las Palmas 35012",
    "addr:housenumber":"213",
    "addr:postcode":"35012",
    "addr:street":"Calle De Don\u0303A Perfecta",
    "iso:country":"ES",
    "sg:address":"Calle de Do\u00d1a Perfecta, 213",
    "sg:city":"Palmas De Gran Canaria",
    "sg:orig_category":"Institutos De Belleza",
    "sg:phone":"+34 928 28 00 25",
    "sg:postcode":"35012",
    "sg:province":"Las Palmas",
    "wof:name":"Suarez Naranjo Josefa",
    "wof:placetype":"venue"
},
  "geometry": {"coordinates":[-15.4385929108,28.107213974],"type":"Point"}
}