{
  "type": "Feature",
  "properties": {
    "iso:country":"ES",
    "sg:address":"Plaz Mayor, 1",
    "sg:city":"Mandayona",
    "sg:orig_category":"Cajas De Ahorro",
    "sg:phone":"+34 949 30 50 23",
    "sg:postcode":"19294",
    "sg:province":"Guadalajara",
    "sg:website":"www.cajaguadalajara.biz",
    "wof:name":"Caja De Ahorro Provincial De Guadalajara",
    "wof:placetype":"venue"
},
  "geometry": {"coordinates":[-2.749174118,40.956401825],"type":"Point"}
}