{
  "type": "Feature",
  "properties": {
    "addr:full":"Calle de Academico Saraza, 3 Cordoba C\u00f3rdoba 14012",
    "addr:housenumber":"3",
    "addr:postcode":"14012",
    "addr:street":"Calle De Academico Saraza;Co\u0301Rdoba",
    "iso:country":"ES",
    "sg:address":"Calle de Academico Saraza, 3",
    "sg:city":"Cordoba",
    "sg:orig_category":"Florister\u00cdas",
    "sg:phone":"+34 957 40 20 03",
    "sg:postcode":"14012",
    "sg:province":"C\u00f3rdoba",
    "wof:name":"Pi\u00f1eiro Roldan Laura",
    "wof:placetype":"venue"
},
  "geometry": {"coordinates":[-4.7805848122,37.9088439941],"type":"Point"}
}