{
  "type": "Feature",
  "properties": {
    "iso:country":"ES",
    "sg:address":"Carrer de Joan Prim, 73",
    "sg:city":"Granollers",
    "sg:orig_category":"Institutos De Belleza",
    "sg:phone":"+34 938 46 86 92",
    "sg:postcode":"08401",
    "sg:province":"Barcelona",
    "wof:name":"Viu Fuentes S.l.",
    "wof:placetype":"venue"
},
  "geometry": {"coordinates":[2.2898244858,41.61170578],"type":"Point"}
}