{
  "type": "Feature",
  "properties": {
    "addr:full":"Calle de Tinerfe El Grande, 2 Adeje Santa Cruz De Tenerife 38670",
    "addr:housenumber":"2",
    "addr:postcode":"38670",
    "addr:street":"Calle De Tinerfe El Grande",
    "iso:country":"ES",
    "sg:address":"Calle de Tinerfe El Grande, 2",
    "sg:city":"Adeje",
    "sg:orig_category":"Bazares, Art\u00cdculos De Limpieza Y De Cocina (al Por Menor)",
    "sg:phone":"+34 922 78 03 01",
    "sg:postcode":"38670",
    "sg:province":"Santa Cruz De Tenerife",
    "wof:name":"Yanes Garcia Maria Del Mar",
    "wof:placetype":"venue"
},
  "geometry": {"coordinates":[-16.724899292,28.1215400696],"type":"Point"}
}