{
  "type": "Feature",
  "properties": {
    "iso:country":"ES",
    "sg:address":"Via Dos Castillas (de Las), 7",
    "sg:city":"Pozuelo De Alarcon",
    "sg:orig_category":"Abogados",
    "sg:phone":"+34 913 52 01 47",
    "sg:postcode":"28224",
    "sg:province":"Madrid",
    "wof:name":"Marcos Martin Lucas",
    "wof:placetype":"venue"
},
  "geometry": {"coordinates":[-3.8059060574,40.4313812256],"type":"Point"}
}