{
  "type": "Feature",
  "properties": {
    "iso:country":"ES",
    "sg:address":"Calle de Sagunto, 4",
    "sg:city":"Madrid",
    "sg:orig_category":"Electricidad Veh\u00cdculo",
    "sg:phone":"+34 914 46 92 97",
    "sg:postcode":"28010",
    "sg:province":"Madrid",
    "wof:name":"Cruz Generoso Juan",
    "wof:placetype":"venue"
},
  "geometry": {"coordinates":[-3.7001850605,40.4334487915],"type":"Point"}
}