{
  "type": "Feature",
  "properties": {
    "iso:country":"ES",
    "sg:address":"Calle de Don Juan De Austria, 27",
    "sg:city":"Malaga",
    "sg:orig_category":"Quiropr\u00c1cticos",
    "sg:phone":"+34 952 30 10 70",
    "sg:postcode":"29009",
    "sg:province":"M\u00e1laga",
    "wof:name":"Quiros S.c.",
    "wof:placetype":"venue"
},
  "geometry": {"coordinates":[-4.4288277626,36.7250900269],"type":"Point"}
}