{
  "type": "Feature",
  "properties": {
    "addr:full":"Calle de Jussepe Martinez, 4 Zaragoza Zaragoza 50003",
    "addr:housenumber":"4",
    "addr:postcode":"50003",
    "addr:street":"Calle De Jussepe Martinez",
    "iso:country":"ES",
    "sg:address":"Calle de Jussepe Martinez, 4",
    "sg:city":"Zaragoza",
    "sg:orig_category":"Molduras, Junquillos, Listones Y Molduras Perforadas",
    "sg:phone":"+34 976 39 59 39",
    "sg:postcode":"50003",
    "sg:province":"Zaragoza",
    "wof:name":"De Martino Gonzalo Dionisio",
    "wof:placetype":"venue"
},
  "geometry": {"coordinates":[-0.8802030087,41.6546516418],"type":"Point"}
}