{
  "type": "Feature",
  "properties": {
    "iso:country":"ES",
    "sg:address":"Avda Rodriguez Acosta, 8",
    "sg:city":"Motril",
    "sg:orig_category":"Carnicer\u00cdas, Carnicer\u00cdas",
    "sg:phone":"+34 958 60 47 14",
    "sg:postcode":"18600",
    "sg:province":"Granada",
    "wof:name":"Hidalgo Rodriguez Antonio",
    "wof:placetype":"venue"
},
  "geometry": {"coordinates":[-3.5149490833,36.7437705994],"type":"Point"}
}