{
  "type": "Feature",
  "properties": {
    "iso:country":"ES",
    "sg:address":"Ctra Carretera Carrion (poligono Industrial), 26",
    "sg:city":"Ciudad Real",
    "sg:orig_category":"Electricidad: Instaladores",
    "sg:phone":"+34 926 22 18 87",
    "sg:postcode":"13005",
    "sg:province":"Ciudad Real",
    "wof:name":"Instalaciones Electricas Pantaleon Gonzalez Carrion S.l.",
    "wof:placetype":"venue"
},
  "geometry": {"coordinates":[-3.9525969028,38.9611473083],"type":"Point"}
}