{
  "type": "Feature",
  "properties": {
    "addr:full":"Carrer de Jaume Ferran, 55 Palma Islas Baleares 07004",
    "addr:housenumber":"55",
    "addr:postcode":"07004",
    "addr:street":"Carrer De Jaume Ferran",
    "iso:country":"ES",
    "sg:address":"Carrer de Jaume Ferran, 55",
    "sg:city":"Palma",
    "sg:orig_category":"Cristaler\u00cdas",
    "sg:phone":"+34 971 20 31 07",
    "sg:postcode":"07004",
    "sg:province":"Islas Baleares",
    "wof:name":"Cristaleria Son Bruy S.l.",
    "wof:placetype":"venue"
},
  "geometry": {"coordinates":[2.6600470543,39.5844993591],"type":"Point"}
}