{
  "type": "Feature",
  "properties": {
    "addr:full":"Pase Santa Maria Del Aguila, 17 Santa Maria Aguila Almer\u00eda 04710",
    "addr:housenumber":"17",
    "addr:postcode":"04710",
    "addr:street":"Santa Maria Del Aguila;Almeri\u0301A",
    "iso:country":"ES",
    "sg:address":"Pase Santa Maria Del Aguila, 17",
    "sg:city":"Santa Maria Aguila",
    "sg:orig_category":"Bricolaje, Herramientas (al Por Menor)",
    "sg:phone":"+34 950 58 00 83",
    "sg:postcode":"04710",
    "sg:province":"Almer\u00eda",
    "wof:name":"Castaeda Gutierrez Jose Antonio",
    "wof:placetype":"venue"
},
  "geometry": {"coordinates":[-2.7738699913,36.7844047546],"type":"Point"}
}