{
  "type": "Feature",
  "properties": {
    "addr:full":"Rbla Onze De Setembre, 24 Cassa Selva Girona 17244",
    "addr:housenumber":"24",
    "addr:postcode":"17244",
    "addr:street":"Rbla Onze De Setembre",
    "iso:country":"ES",
    "sg:address":"Rbla Onze De Setembre, 24",
    "sg:city":"Cassa Selva",
    "sg:orig_category":"Venta, Instalaci\u00d3n De Cocinas",
    "sg:phone":"+34 972 46 17 05",
    "sg:postcode":"17244",
    "sg:province":"Girona",
    "wof:name":"Medina Perez Jose",
    "wof:placetype":"venue"
},
  "geometry": {"coordinates":[2.8766000271,41.8847312927],"type":"Point"}
}