{
  "type": "Feature",
  "properties": {
    "iso:country":"ES",
    "sg:address":"Carrer de Ildefons Cerda, 14",
    "sg:city":"S. Cugat Valles",
    "sg:orig_category":"Muebles, Minoristas",
    "sg:phone":"+34 935 90 68 20",
    "sg:postcode":"08172",
    "sg:province":"Barcelona",
    "sg:website":"www.versat.com",
    "wof:name":"Versat S.l.",
    "wof:placetype":"venue"
},
  "geometry": {"coordinates":[2.0911140442,41.4761543274],"type":"Point"}
}