{
  "type": "Feature",
  "properties": {
    "iso:country":"ES",
    "sg:address":"Calle de Arg\u00fcelles, 7",
    "sg:city":"Oviedo",
    "sg:orig_category":"Abogados",
    "sg:phone":"+34 985 22 97 09",
    "sg:postcode":"33003",
    "sg:province":"Asturias",
    "wof:name":"Velasco Garcia Esther",
    "wof:placetype":"venue"
},
  "geometry": {"coordinates":[-5.8483991623,43.3622741699],"type":"Point"}
}