{
  "type": "Feature",
  "properties": {
    "addr:full":"Calle de Duque De Rivas, 3 Madrid Madrid 28012",
    "addr:housenumber":"3",
    "addr:postcode":"28012",
    "addr:street":"Calle De Duque De Rivas",
    "iso:country":"ES",
    "sg:address":"Calle de Duque De Rivas, 3",
    "sg:city":"Madrid",
    "sg:orig_category":"Confecci\u00d3n (fabricaci\u00d3n, Al Por Mayor)",
    "sg:phone":"+34 913 69 45 94",
    "sg:postcode":"28012",
    "sg:province":"Madrid",
    "wof:name":"Cascales Hidalgo Jose",
    "wof:placetype":"venue"
},
  "geometry": {"coordinates":[-3.7063965797,40.4135894775],"type":"Point"}
}