{
  "type": "Feature",
  "properties": {
    "addr:full":"Carrer de Bisbe Aznar (del), 49 S. Carles Rapita Tarragona 43540",
    "addr:housenumber":"49",
    "addr:postcode":"43540",
    "addr:street":"Carrer De Bisbe Aznar Del;S. Carles Rapita",
    "iso:country":"ES",
    "sg:address":"Carrer de Bisbe Aznar (del), 49",
    "sg:city":"S. Carles Rapita",
    "sg:orig_category":"Inform\u00c1tica: Redes",
    "sg:phone":"+34 977 74 09 56",
    "sg:postcode":"43540",
    "sg:province":"Tarragona",
    "wof:name":"Germans Mateu Brunet Cdad.",
    "wof:placetype":"venue"
},
  "geometry": {"coordinates":[0.5963259935,40.6207122803],"type":"Point"}
}