{
  "type": "Feature",
  "properties": {
    "iso:country":"ES",
    "sg:address":"Calle de Serrano, 37",
    "sg:city":"Madrid",
    "sg:orig_category":"Inmobiliaria (agencias)",
    "sg:phone":"+34 914 31 14 31",
    "sg:postcode":"28001",
    "sg:province":"Madrid",
    "sg:website":"www.ebrosa.es",
    "wof:name":"Ebrosa S.a.",
    "wof:placetype":"venue"
},
  "geometry": {"coordinates":[-3.6874690056,40.428314209],"type":"Point"}
}