{
  "type": "Feature",
  "properties": {
    "iso:country":"ES",
    "sg:address":"Avda Francisco Ayala (de), 61",
    "sg:city":"Granada",
    "sg:orig_category":"Servidores Y Editores De Bases De Datos",
    "sg:phone":"+34 958 15 85 51",
    "sg:postcode":"18014",
    "sg:province":"Granada",
    "sg:website":"www.ocaofa.es",
    "wof:name":"Organizacion Y Distribucion Del Sofa S.l.",
    "wof:placetype":"venue"
},
  "geometry": {"coordinates":[-3.6183419228,37.1947212219],"type":"Point"}
}