{
  "type": "Feature",
  "properties": {
    "iso:country":"ES",
    "sg:address":"Trss Industrial, 75",
    "sg:city":"Hospitalet Llobregat",
    "sg:orig_category":"Transporte En General",
    "sg:phone":"+34 932 63 34 33",
    "sg:postcode":"08907",
    "sg:province":"Barcelona",
    "sg:website":"www.jet.es/dicasa/polistock.htm",
    "wof:name":"Inmobiliaria Pemahis S.a.",
    "wof:placetype":"venue"
},
  "geometry": {"coordinates":[2.1700499058,41.3857192993],"type":"Point"}
}