{
  "type": "Feature",
  "properties": {
    "addr:full":"Pg Caputxins (dels), 19 Valls Tarragona 43800",
    "addr:housenumber":"19",
    "addr:postcode":"43800",
    "addr:street":"Pg Caputxins Dels",
    "iso:country":"ES",
    "sg:address":"Pg Caputxins (dels), 19",
    "sg:city":"Valls",
    "sg:orig_category":"Promotores Constructores",
    "sg:phone":"+34 977 60 96 52",
    "sg:postcode":"43800",
    "sg:province":"Tarragona",
    "wof:name":"Construccions Vilaniu S.l.",
    "wof:placetype":"venue"
},
  "geometry": {"coordinates":[1.2516770363,41.2880744934],"type":"Point"}
}