{
  "type": "Feature",
  "properties": {
    "addr:full":"Avda Gines, 2 Bollullos Mitacion Sevilla 41110",
    "addr:housenumber":"2",
    "addr:postcode":"41110",
    "addr:street":"Avda Gines",
    "iso:country":"ES",
    "sg:address":"Avda Gines, 2",
    "sg:city":"Bollullos Mitacion",
    "sg:orig_category":"Panader\u00cdas, Panader\u00cdas",
    "sg:phone":"+34 955 77 65 25",
    "sg:postcode":"41110",
    "sg:province":"Sevilla",
    "sg:website":"www.confiteriafilella.com",
    "wof:name":"Hijos De Maria Del Carmen Filella S.l.",
    "wof:placetype":"venue"
},
  "geometry": {"coordinates":[-6.1422591209,37.3558616638],"type":"Point"}
}