{
  "type": "Feature",
  "properties": {
    "addr:full":"Calle de Fray Pedro De Cordoba, 16 Cordoba C\u00f3rdoba 14009",
    "addr:housenumber":"16",
    "addr:postcode":"14009",
    "addr:street":"Calle De Fray Pedro De Cordoba;Co\u0301Rdoba",
    "iso:country":"ES",
    "sg:address":"Calle de Fray Pedro De Cordoba, 16",
    "sg:city":"Cordoba",
    "sg:orig_category":"Compraventa De Antig\u00dcedades",
    "sg:phone":"+34 957 29 33 29",
    "sg:postcode":"14009",
    "sg:province":"C\u00f3rdoba",
    "wof:name":"Le\u00f1a Gomariz Antonio",
    "wof:placetype":"venue"
},
  "geometry": {"coordinates":[-4.7750320435,37.8739891052],"type":"Point"}
}