{
  "type": "Feature",
  "properties": {
    "iso:country":"ES",
    "sg:address":"Avda Guipuzcoa, 44",
    "sg:city":"Berriozar",
    "sg:orig_category":"Arquitectos",
    "sg:phone":"+34 948 30 94 09",
    "sg:postcode":"31013",
    "sg:province":"Navarra",
    "wof:name":"Solar Urrutia Jose Luis Del",
    "wof:placetype":"venue"
},
  "geometry": {"coordinates":[-1.6719150543,42.8354682922],"type":"Point"}
}