{
  "type": "Feature",
  "properties": {
    "addr:full":"Calle de Jaizkibel, 1 Errenteria Guip\u00f9zcoa 20100",
    "addr:housenumber":"1",
    "addr:postcode":"20100",
    "addr:street":"Calle De Jaizkibel;Guipu\u0300Zcoa",
    "iso:country":"ES",
    "sg:address":"Calle de Jaizkibel, 1",
    "sg:city":"Errenteria",
    "sg:orig_category":"Carnicer\u00cdas, Carnicer\u00cdas",
    "sg:phone":"+34 943 51 42 46",
    "sg:postcode":"20100",
    "sg:province":"Guip\u00f9zcoa",
    "wof:name":"Karlos Tamayo Izquierdo",
    "wof:placetype":"venue"
},
  "geometry": {"coordinates":[-1.9115149975,43.3113174438],"type":"Point"}
}