{
  "type": "Feature",
  "properties": {
    "addr:full":"Calle de Paloma (de La), S/n Fuenlabrada Madrid 28946",
    "addr:postcode":"28946",
    "addr:street":"Calle De Paloma De La S / N",
    "iso:country":"ES",
    "sg:address":"Calle de Paloma (de La), S/n",
    "sg:city":"Fuenlabrada",
    "sg:orig_category":"Artes Gr\u00c1ficas, Artes Pl\u00c1sticas (curso)",
    "sg:phone":"+34 916 42 21 60",
    "sg:postcode":"28946",
    "sg:province":"Madrid",
    "sg:website":"www.graficasroal.com",
    "wof:name":"Graficas Roal S.a.",
    "wof:placetype":"venue"
},
  "geometry": {"coordinates":[-3.763974905,40.2629814148],"type":"Point"}
}