{
  "type": "Feature",
  "properties": {
    "addr:full":"Carrer de Contralmirall Ferragut, 1 Magaluf Islas Baleares 07181",
    "addr:housenumber":"1",
    "addr:postcode":"07181",
    "addr:street":"Carrer De Contralmirall Ferragut",
    "iso:country":"ES",
    "sg:address":"Carrer de Contralmirall Ferragut, 1",
    "sg:city":"Magaluf",
    "sg:orig_category":"Cl\u00cdnicas M\u00c9dicas",
    "sg:phone":"+34 971 13 04 49",
    "sg:postcode":"07181",
    "sg:province":"Islas Baleares",
    "wof:name":"Tarongi Fuster Pablo",
    "wof:placetype":"venue"
},
  "geometry": {"coordinates":[2.5340280533,39.5069313049],"type":"Point"}
}