{
  "type": "Feature",
  "properties": {
    "addr:full":"Calle de Almodovar Del Rio, 55 Posadas C\u00f3rdoba 14730",
    "addr:housenumber":"55;co\u0301rdoba",
    "addr:postcode":"14730",
    "addr:street":"Calle De Almodovar Del Rio",
    "iso:country":"ES",
    "sg:address":"Calle de Almodovar Del Rio, 55",
    "sg:city":"Posadas",
    "sg:orig_category":"Transportes Por V\u00cdas Navegables",
    "sg:phone":"+34 957 63 14 35",
    "sg:postcode":"14730",
    "sg:province":"C\u00f3rdoba",
    "wof:name":"Ojeda Borja Laureano",
    "wof:placetype":"venue"
},
  "geometry": {"coordinates":[-5.1015925407,37.8014793396],"type":"Point"}
}