{
  "type": "Feature",
  "properties": {
    "addr:full":"Calle de Cristina Marugan, 1 Palencia Palencia 34003",
    "addr:housenumber":"1",
    "addr:postcode":"34003",
    "addr:street":"Calle De Cristina Marugan",
    "iso:country":"ES",
    "sg:address":"Calle de Cristina Marugan, 1",
    "sg:city":"Palencia",
    "sg:orig_category":"Mutuas De Seguros",
    "sg:phone":"+34 979 74 00 25",
    "sg:postcode":"34003",
    "sg:province":"Palencia",
    "wof:name":"Mutualidad P.s.san Ignacio",
    "wof:placetype":"venue"
},
  "geometry": {"coordinates":[-4.5332665443,42.0232620239],"type":"Point"}
}