{
  "type": "Feature",
  "properties": {
    "addr:full":"Plaz Mayor, 20 Valladolid Valladolid 47001",
    "addr:housenumber":"20",
    "addr:postcode":"47001",
    "addr:street":"Plaz Mayor",
    "iso:country":"ES",
    "sg:address":"Plaz Mayor, 20",
    "sg:city":"Valladolid",
    "sg:orig_category":"Ropa Para Se\u00d1oras (al Por Menor)",
    "sg:phone":"+34 983 34 28 06",
    "sg:postcode":"47001",
    "sg:province":"Valladolid",
    "wof:name":"Fernandez Mendez Balbino",
    "wof:placetype":"venue"
},
  "geometry": {"coordinates":[-4.7293109894,41.6520881653],"type":"Point"}
}