{
  "type": "Feature",
  "properties": {
    "addr:full":"Urb Puerto Pino, 28 Almeria Almer\u00eda 04007",
    "addr:housenumber":"28",
    "addr:postcode":"04007",
    "addr:street":"Urb;Pino",
    "iso:country":"ES",
    "sg:address":"Urb Puerto Pino, 28",
    "sg:city":"Almeria",
    "sg:orig_category":"M\u00c9dicos: Neurolog\u00cda",
    "sg:phone":"+34 950 27 28 20",
    "sg:postcode":"04007",
    "sg:province":"Almer\u00eda",
    "wof:name":"Villegas Sanchez Gustavo",
    "wof:placetype":"venue"
},
  "geometry": {"coordinates":[-2.4139039516,36.8265609741],"type":"Point"}
}