{
  "type": "Feature",
  "properties": {
    "iso:country":"ES",
    "sg:address":"Avda Alemania (de), S/n",
    "sg:city":"Playa Del Ingles",
    "sg:orig_category":"Molduras, Junquillos, Listones Y Molduras Perforadas",
    "sg:phone":"+34 928 76 27 94",
    "sg:postcode":"35100",
    "sg:province":"Las Palmas",
    "wof:name":"Vidakov  Herman",
    "wof:placetype":"venue"
},
  "geometry": {"coordinates":[-15.5737190247,27.7490711212],"type":"Point"}
}