{
  "type": "Feature",
  "properties": {
    "iso:country":"ES",
    "sg:address":"Carrer de Melio, 81",
    "sg:city":"Vilafranca Penedes",
    "sg:orig_category":"Zapatos (al Por Menor)",
    "sg:phone":"+34 938 17 40 29",
    "sg:postcode":"08720",
    "sg:province":"Barcelona",
    "wof:name":"Pijuan Voltas Jordi",
    "wof:placetype":"venue"
},
  "geometry": {"coordinates":[1.7063839436,41.3451156616],"type":"Point"}
}