{
  "type": "Feature",
  "properties": {
    "addr:full":"Calabanda(calo), 28 Calabanda La Coru\u00f1a 15129",
    "addr:housenumber":"28",
    "addr:postcode":"15129",
    "addr:street":"Calabanda Calo;La Corun\u0303A",
    "iso:country":"ES",
    "sg:address":"Calabanda(calo), 28",
    "sg:city":"Calabanda",
    "sg:orig_category":"Perreras, Pensiones Para Perros, Gatos Y Otros Animales",
    "sg:phone":"+34 981 72 50 66",
    "sg:postcode":"15129",
    "sg:province":"La Coru\u00f1a",
    "wof:name":"Garcia Cagiao Manuel",
    "wof:placetype":"venue"
},
  "geometry": {"coordinates":[-9.0328435898,43.1112251282],"type":"Point"}
}