{
  "type": "Feature",
  "properties": {
    "iso:country":"ES",
    "sg:address":"Ctra Xixona-alacant, Km. 0003,0",
    "sg:city":"Jijona",
    "sg:orig_category":"Confiter\u00cdas, Chocolater\u00cdas (al Por Menor)",
    "sg:phone":"+34 965 61 02 75",
    "sg:postcode":"03100",
    "sg:province":"Alicante",
    "sg:website":"www.elartesano.es",
    "wof:name":"Mira Y Llorens S. A.",
    "wof:placetype":"venue"
},
  "geometry": {"coordinates":[-0.4973269999,38.5448608398],"type":"Point"}
}