{
  "type": "Feature",
  "properties": {
    "iso:country":"ES",
    "sg:address":"Carrer de Sant Joan, 37",
    "sg:city":"Esparreguera",
    "sg:orig_category":"Venta, Instalaci\u00d3n De Calefacci\u00d3n",
    "sg:phone":"+34 937 77 77 14",
    "sg:postcode":"08292",
    "sg:province":"Barcelona",
    "wof:name":"Chimeneas Esparraguera S.l.",
    "wof:placetype":"venue"
},
  "geometry": {"coordinates":[1.8710449934,41.5367546082],"type":"Point"}
}