{
  "type": "Feature",
  "properties": {
    "iso:country":"ES",
    "sg:address":"Calle de Villajos, 6",
    "sg:city":"Consuegra",
    "sg:orig_category":"Agentes Generales De Seguros",
    "sg:phone":"+34 925 48 02 64",
    "sg:postcode":"45700",
    "sg:province":"Toledo",
    "wof:name":"Sca Ortiz & Rozalen S.l",
    "wof:placetype":"venue"
},
  "geometry": {"coordinates":[-3.6117930412,39.4649505615],"type":"Point"}
}