{
  "type": "Feature",
  "properties": {
    "iso:country":"ES",
    "sg:address":"Calle de Valle Inclan, 64",
    "sg:city":"Madrid",
    "sg:orig_category":"Inform\u00c1tica (estudios, Servicios, Asesor\u00cda, Formaci\u00d3n)",
    "sg:phone":"+34 915 09 51 27",
    "sg:postcode":"28044",
    "sg:province":"Madrid",
    "wof:name":"Computadores Programas Y Sistemas S.l.",
    "wof:placetype":"venue"
},
  "geometry": {"coordinates":[-3.7748270035,40.3768615723],"type":"Point"}
}