{
  "type": "Feature",
  "properties": {
    "iso:country":"ES",
    "sg:address":"Carr Isaac Peral, 16",
    "sg:city":"Burjassot",
    "sg:orig_category":"Carnicer\u00cdas, Carnicer\u00cdas",
    "sg:phone":"+34 963 63 90 73",
    "sg:postcode":"46100",
    "sg:province":"Valencia",
    "wof:name":"Fornes Lorenzo Juan Carlos",
    "wof:placetype":"venue"
},
  "geometry": {"coordinates":[-0.4166119993,39.5144386292],"type":"Point"}
}