{
  "type": "Feature",
  "properties": {
    "iso:country":"ES",
    "sg:address":"Ponte Carreira, S/n",
    "sg:city":"Gafoi-ponte Carreira",
    "sg:orig_category":"Pirotecnia (espect\u00c1culos)",
    "sg:phone":"+34 981 69 20 92",
    "sg:postcode":"15686",
    "sg:province":"La Coru\u00f1a",
    "wof:name":"Comercial Pontecarreira S.l.",
    "wof:placetype":"venue"
},
  "geometry": {"coordinates":[-8.3337287903,43.0459251404],"type":"Point"}
}