{
  "type": "Feature",
  "properties": {
    "addr:full":"Carrer de Rossello, 136 Barcelona Barcelona 08036",
    "addr:housenumber":"136",
    "addr:postcode":"08036",
    "addr:street":"Carrer De Rossello",
    "iso:country":"ES",
    "sg:address":"Carrer de Rossello, 136",
    "sg:city":"Barcelona",
    "sg:orig_category":"M\u00c9dicos: Endocrinolog\u00cda Y Metabolismo",
    "sg:phone":"+34 934 52 72 62",
    "sg:postcode":"08036",
    "sg:province":"Barcelona",
    "wof:name":"Riba Sicart Ana Maria",
    "wof:placetype":"venue"
},
  "geometry": {"coordinates":[2.1537060738,41.3903846741],"type":"Point"}
}