{
  "type": "Feature",
  "properties": {
    "iso:country":"ES",
    "sg:address":"Carrer de Muntaner, 269",
    "sg:city":"Barcelona",
    "sg:orig_category":"M\u00c9dicos: Estomatolog\u00cda",
    "sg:phone":"+34 932 09 67 49",
    "sg:postcode":"08021",
    "sg:province":"Barcelona",
    "wof:name":"Orriols Bordas Francisco De Asis",
    "wof:placetype":"venue"
},
  "geometry": {"coordinates":[2.1472890377,41.3956108093],"type":"Point"}
}