{
  "type": "Feature",
  "properties": {
    "iso:country":"ES",
    "sg:address":"Calle de Virgen De Gracia, 6",
    "sg:city":"Alacant",
    "sg:orig_category":"Inform\u00c1tica (estudios, Servicios, Asesor\u00cda, Formaci\u00d3n)",
    "sg:phone":"+34 965 16 44 93",
    "sg:postcode":"03016",
    "sg:province":"Alicante",
    "wof:name":"Pc-school S.l.",
    "wof:placetype":"venue"
},
  "geometry": {"coordinates":[-0.4698939919,38.3560676575],"type":"Point"}
}