{
  "type": "Feature",
  "properties": {
    "addr:full":"Calle de Parreta, 5 Xirivella Valencia 46950",
    "addr:housenumber":"5",
    "addr:postcode":"46950",
    "addr:street":"Calle De Parreta",
    "iso:country":"ES",
    "sg:address":"Calle de Parreta, 5",
    "sg:city":"Xirivella",
    "sg:orig_category":"Relojer\u00cda (al Por Menor, Reparaci\u00d3n)",
    "sg:phone":"+34 963 70 89 49",
    "sg:postcode":"46950",
    "sg:province":"Valencia",
    "wof:name":"Anaya Pulido Francisco",
    "wof:placetype":"venue"
},
  "geometry": {"coordinates":[-0.42810601,39.4658126831],"type":"Point"}
}