{
  "type": "Feature",
  "properties": {
    "iso:country":"ES",
    "sg:address":"Calle de Sampiro, 22",
    "sg:city":"Le\u00f3n",
    "sg:orig_category":"Centros P\u00dablicos De Formaci\u00d3n Profesional Y T\u00c9cnica",
    "sg:phone":"+34 987 27 13 14",
    "sg:postcode":"24001",
    "sg:province":"Le\u00f3n",
    "wof:name":"Colegio Oficial De Ingenieros De Caminos Canales Y Puertos De Madrid",
    "wof:placetype":"venue"
},
  "geometry": {"coordinates":[-5.5812082291,42.6005630493],"type":"Point"}
}