{
  "type": "Feature",
  "properties": {
    "addr:full":"Calle de Urano, 19 Pozuelo De Alarcon Madrid 28224",
    "addr:housenumber":"19",
    "addr:postcode":"28224",
    "addr:street":"Calle De Urano",
    "iso:country":"ES",
    "sg:address":"Calle de Urano, 19",
    "sg:city":"Pozuelo De Alarcon",
    "sg:orig_category":"Albergues",
    "sg:phone":"+34 913 51 97 37",
    "sg:postcode":"28224",
    "sg:province":"Madrid",
    "sg:website":"www.korisimport.com",
    "wof:name":"Rico Santiesteban Oscar",
    "wof:placetype":"venue"
},
  "geometry": {"coordinates":[-3.7922739983,40.442691803],"type":"Point"}
}