{
  "type": "Feature",
  "properties": {
    "iso:country":"ES",
    "sg:address":"Carr Combat, 18",
    "sg:city":"Cervera",
    "sg:orig_category":"Ense\u00d1anza: Profesiones Art\u00cdsticas",
    "sg:phone":"+34 973 53 02 55",
    "sg:postcode":"25200",
    "sg:province":"Lleida",
    "wof:name":"Gomez Grau Claudio",
    "wof:placetype":"venue"
},
  "geometry": {"coordinates":[1.2714600563,41.6712989807],"type":"Point"}
}