{
  "type": "Feature",
  "properties": {
    "iso:country":"ES",
    "sg:address":"Artesanos, S/n",
    "sg:city":"Boadilla",
    "sg:orig_category":"Librer\u00cdas",
    "sg:phone":"+34 916 33 00 94",
    "sg:postcode":"28660",
    "sg:province":"Madrid",
    "wof:name":"Quierete Natural S.l.",
    "wof:placetype":"venue"
},
  "geometry": {"coordinates":[-3.848099947,40.3922309875],"type":"Point"}
}