{
  "type": "Feature",
  "properties": {
    "addr:full":"Ctra. Villaralbo-villalazan, Km. 0007,5 Villaralbo Zamora 49159",
    "addr:postcode":"49159",
    "addr:street":"Ctra. Villaralbo-Villalazan Km. 0007,5",
    "iso:country":"ES",
    "sg:address":"Ctra. Villaralbo-villalazan, Km. 0007,5",
    "sg:city":"Villaralbo",
    "sg:orig_category":"Hormigonados",
    "sg:phone":"+34 980 56 92 36",
    "sg:postcode":"49159",
    "sg:province":"Zamora",
    "wof:name":"Tecnicas Alba S.a.",
    "wof:placetype":"venue"
},
  "geometry": {"coordinates":[-5.6848192215,41.4921798706],"type":"Point"}
}