{
  "type": "Feature",
  "properties": {
    "addr:full":"Calle de Jacinto Conesa, 46 Union Murcia 30360",
    "addr:housenumber":"46",
    "addr:postcode":"30360",
    "addr:street":"Calle De Jacinto Conesa",
    "iso:country":"ES",
    "sg:address":"Calle de Jacinto Conesa, 46",
    "sg:city":"Union",
    "sg:classifiers":[
        {
            "category":"Taxi",
            "type":"Transportation"
        }
    ],
    "sg:phone":"+34 968 56 03 63",
    "sg:postcode":"30360",
    "sg:province":"Murcia",
    "wof:name":"Carrion Torralba Ricardo",
    "wof:placetype":"venue"
},
  "geometry": {"coordinates":[-0.8795639873,37.6184310913],"type":"Point"}
}