{
  "type": "Feature",
  "properties": {
    "addr:full":"Carrer de Riera (la), 39 Cardedeu Barcelona 08440",
    "addr:housenumber":"39",
    "addr:postcode":"08440",
    "addr:street":"Carrer De Riera La",
    "iso:country":"ES",
    "sg:address":"Carrer de Riera (la), 39",
    "sg:city":"Cardedeu",
    "sg:orig_category":"Venta, Instalaci\u00d3n De Cocinas",
    "sg:phone":"+34 938 71 11 83",
    "sg:postcode":"08440",
    "sg:province":"Barcelona",
    "wof:name":"Intermobel Mobiliari I Interiorisme S.l.",
    "wof:placetype":"venue"
},
  "geometry": {"coordinates":[2.3526599407,41.636631012],"type":"Point"}
}