{
  "type": "Feature",
  "properties": {
    "addr:full":"Calle de Serrano, 61 Madrid Madrid 28006",
    "addr:housenumber":"61",
    "addr:postcode":"madrid;28006",
    "addr:street":"Calle De Serrano",
    "iso:country":"ES",
    "sg:address":"Calle de Serrano, 61",
    "sg:city":"Madrid",
    "sg:orig_category":"Art\u00cdculos De Regalo (al Por Menor)",
    "sg:phone":"+34 915 76 17 55",
    "sg:postcode":"28006",
    "sg:province":"Madrid",
    "sg:website":"www.partycity.com",
    "wof:name":"Party Fiesta S.a.",
    "wof:placetype":"venue"
},
  "geometry": {"coordinates":[-3.6869249344,40.4321975708],"type":"Point"}
}