{
  "type": "Feature",
  "properties": {
    "addr:full":"Tv. San J. Bosco, 7 Iru\u00f1a Navarra 31007",
    "addr:housenumber":"7",
    "addr:postcode":"31007",
    "addr:street":"Irun\u0303A Navarra",
    "iso:country":"ES",
    "sg:address":"Tv. San J. Bosco, 7",
    "sg:city":"Iru\u00f1a",
    "sg:orig_category":"Mec\u00c1nico Del Autom\u00d3vil",
    "sg:phone":"+34 948 26 91 23",
    "sg:postcode":"31007",
    "sg:province":"Navarra",
    "wof:name":"Talleres Alcar S. A.",
    "wof:placetype":"venue"
},
  "geometry": {"coordinates":[-1.6479300261,42.8058166504],"type":"Point"}
}