{
  "type": "Feature",
  "properties": {
    "addr:full":"Avda Santiago, 3 Negreira La Coru\u00f1a 15830",
    "addr:housenumber":"3",
    "addr:postcode":"15830",
    "addr:street":"Avda Santiago;La Corun\u0303A",
    "iso:country":"ES",
    "sg:address":"Avda Santiago, 3",
    "sg:city":"Negreira",
    "sg:orig_category":"Farmacias",
    "sg:phone":"+34 981 88 50 76",
    "sg:postcode":"15830",
    "sg:province":"La Coru\u00f1a",
    "wof:name":"Fabeiro Mosquera Jose Maria",
    "wof:placetype":"venue"
},
  "geometry": {"coordinates":[-8.7253732681,42.9113273621],"type":"Point"}
}