{
  "type": "Feature",
  "properties": {
    "iso:country":"ES",
    "sg:address":"Francisca Molina Flores, 4",
    "sg:city":"Garrucha",
    "sg:orig_category":"Contenedores (mercanc\u00cdas)",
    "sg:phone":"+34 950 13 33 93",
    "sg:postcode":"04630",
    "sg:province":"Almer\u00eda",
    "wof:name":"Wimo Eurocargo S.l",
    "wof:placetype":"venue"
},
  "geometry": {"coordinates":[-1.8293952942,37.1894836426],"type":"Point"}
}