{
  "type": "Feature",
  "properties": {
    "iso:country":"ES",
    "sg:address":"Calle de Santa Ana, 22",
    "sg:city":"Castuera",
    "sg:orig_category":"Agentes De Seguros",
    "sg:phone":"+34 924 77 38 18",
    "sg:postcode":"06420",
    "sg:province":"Badajoz",
    "wof:name":"Juan Jose Ortiz S.l.",
    "wof:placetype":"venue"
},
  "geometry": {"coordinates":[-5.5449924469,38.7228660583],"type":"Point"}
}