{
  "type": "Feature",
  "properties": {
    "addr:full":"Calle de Mayor, 48 S. Esteban Gormaz Soria 42330",
    "addr:housenumber":"48",
    "addr:postcode":"42330",
    "addr:street":"Calle De Mayor;S. Esteban Gormaz",
    "iso:country":"ES",
    "sg:address":"Calle de Mayor, 48",
    "sg:city":"S. Esteban Gormaz",
    "sg:orig_category":"Droguer\u00cdas (al Por Menor)",
    "sg:phone":"+34 975 35 02 86",
    "sg:postcode":"42330",
    "sg:province":"Soria",
    "wof:name":"Catalina Aguilera Jose Luis",
    "wof:placetype":"venue"
},
  "geometry": {"coordinates":[-3.2054040432,41.5743026733],"type":"Point"}
}