{
  "type": "Feature",
  "properties": {
    "addr:full":"Carrer de Corderia, 13 Palma Islas Baleares 07002",
    "addr:housenumber":"13",
    "addr:postcode":"07002",
    "addr:street":"Carrer De Corderia",
    "iso:country":"ES",
    "sg:address":"Carrer de Corderia, 13",
    "sg:city":"Palma",
    "sg:orig_category":"Muebles Y Decoraci\u00d3n De Jardines (fabricaci\u00d3n, Venta)",
    "sg:phone":"+34 971 71 12 43",
    "sg:postcode":"07002",
    "sg:province":"Islas Baleares",
    "wof:name":"Vidal Cerda Tomas",
    "wof:placetype":"venue"
},
  "geometry": {"coordinates":[2.6527340412,39.5704498291],"type":"Point"}
}