{
  "type": "Feature",
  "properties": {
    "iso:country":"ES",
    "sg:address":"Carrer de Girona, 1",
    "sg:city":"Sant Feliu Llobregat",
    "sg:orig_category":"Arreglo, Reparaci\u00d3n, Piezas Sueltas De Televisi\u00d3n, V\u00cddeo, Hi",
    "sg:phone":"+34 936 66 44 57",
    "sg:postcode":"08980",
    "sg:province":"Barcelona",
    "wof:name":"Montoliu Bendicho Joaquin",
    "wof:placetype":"venue"
},
  "geometry": {"coordinates":[2.0510520935,41.3824691772],"type":"Point"}
}