{
  "type": "Feature",
  "properties": {
    "iso:country":"ES",
    "sg:address":"Calle de Pinar, 5",
    "sg:city":"Irun",
    "sg:orig_category":"Cervecer\u00cdas",
    "sg:phone":"+34 943 61 75 31",
    "sg:postcode":"20301",
    "sg:province":"Guip\u00f9zcoa",
    "wof:name":"Call Phone S.l.",
    "wof:placetype":"venue"
},
  "geometry": {"coordinates":[-1.7996350527,43.3435020447],"type":"Point"}
}