{
  "type": "Feature",
  "properties": {
    "iso:country":"ES",
    "sg:address":"Cno Hondo, 9",
    "sg:city":"Anna",
    "sg:orig_category":"Extinci\u00d3n De Incendios: Material Y Suministros (fabricaci\u00d3n, Al Por Mayor)",
    "sg:phone":"+34 962 21 02 65",
    "sg:postcode":"46820",
    "sg:province":"Valencia",
    "wof:name":"Cuenfa S.l.",
    "wof:placetype":"venue"
},
  "geometry": {"coordinates":[-0.6475340128,39.0191268921],"type":"Point"}
}