{
  "type": "Feature",
  "properties": {
    "addr:full":"Carrer de Castell D'olimbroi, 32 Denia Alicante 03700",
    "addr:housenumber":"32",
    "addr:postcode":"03700",
    "addr:street":"Carrer De Castell D'Olimbroi",
    "iso:country":"ES",
    "sg:address":"Carrer de Castell D'olimbroi, 32",
    "sg:city":"Denia",
    "sg:orig_category":"Inmobiliaria (agencias)",
    "sg:phone":"+34 966 42 03 99",
    "sg:postcode":"03700",
    "sg:province":"Alicante",
    "wof:name":"Capital Y Mercat Costa Blanca S.l.",
    "wof:placetype":"venue"
},
  "geometry": {"coordinates":[0.1048989967,38.8424682617],"type":"Point"}
}