{
  "type": "Feature",
  "properties": {
    "iso:country":"ES",
    "sg:address":"Calle de Hernan Cortes, 4",
    "sg:city":"Villafranca De Los Barros",
    "sg:orig_category":"Zapatos (al Por Menor)",
    "sg:phone":"+34 924 52 02 81",
    "sg:postcode":"06220",
    "sg:province":"Badajoz",
    "wof:name":"Calzados Vazques E Hijos S.l.",
    "wof:placetype":"venue"
},
  "geometry": {"coordinates":[-6.3413090706,38.5619735718],"type":"Point"}
}