{
  "type": "Feature",
  "properties": {
    "addr:full":"C/ Nou, S/n Ripollet Barcelona 08291",
    "addr:housenumber":"s / n",
    "addr:postcode":"08291",
    "addr:street":"C / Nou",
    "iso:country":"ES",
    "sg:address":"C/ Nou, S/n",
    "sg:city":"Ripollet",
    "sg:orig_category":"Ropa Para Ni\u00d1os (al Por Menor)",
    "sg:phone":"+34 936 91 98 91",
    "sg:postcode":"08291",
    "sg:province":"Barcelona",
    "wof:name":"Saez Valls Maite",
    "wof:placetype":"venue"
},
  "geometry": {"coordinates":[2.1599349976,41.499584198],"type":"Point"}
}