{
  "type": "Feature",
  "properties": {
    "iso:country":"ES",
    "sg:address":"Calle de Alicante, 4",
    "sg:city":"Teruel",
    "sg:orig_category":"Tintes (fabricaci\u00d3n, Al Por Mayor)",
    "sg:phone":"+34 978 60 89 99",
    "sg:postcode":"44002",
    "sg:province":"Teruel",
    "wof:name":"Iba\u00f1ez Saez Consuelo",
    "wof:placetype":"venue"
},
  "geometry": {"coordinates":[-1.10300982,40.3359107971],"type":"Point"}
}