{
  "type": "Feature",
  "properties": {
    "iso:country":"ES",
    "sg:address":"Calle de Capitan Casado, 3",
    "sg:city":"Santa Cruz De Mudela",
    "sg:orig_category":"Farmacias",
    "sg:phone":"+34 926 34 21 07",
    "sg:postcode":"13730",
    "sg:province":"Ciudad Real",
    "wof:name":"Quero Laguna Antonio",
    "wof:placetype":"venue"
},
  "geometry": {"coordinates":[-3.466789484,38.6415290833],"type":"Point"}
}