{
  "type": "Feature",
  "properties": {
    "addr:full":"Calle de Senda Galiana (de La), S/n Coslada Madrid 28820",
    "addr:postcode":"28820",
    "addr:street":"Calle De Senda Galiana De La S / N",
    "iso:country":"ES",
    "sg:address":"Calle de Senda Galiana (de La), S/n",
    "sg:city":"Coslada",
    "sg:orig_category":"Carnes De Carnicer\u00cda (al Por Mayor)",
    "sg:phone":"+34 916 72 32 62",
    "sg:postcode":"28820",
    "sg:province":"Madrid",
    "wof:name":"Martinez Novella S.a.l.",
    "wof:placetype":"venue"
},
  "geometry": {"coordinates":[-3.5421490669,40.441280365],"type":"Point"}
}