{
  "type": "Feature",
  "properties": {
    "addr:full":"Carrer de Callao, 2 S. Feliu Guixols Girona 17220",
    "addr:housenumber":"2",
    "addr:postcode":"17220",
    "addr:street":"Carrer De Callao;Feliu",
    "iso:country":"ES",
    "sg:address":"Carrer de Callao, 2",
    "sg:city":"S. Feliu Guixols",
    "sg:orig_category":"Inmobiliaria (agencias)",
    "sg:phone":"+34 972 32 73 70",
    "sg:postcode":"17220",
    "sg:province":"Girona",
    "wof:name":"Finques Monestir 2003 S.l.",
    "wof:placetype":"venue"
},
  "geometry": {"coordinates":[3.026154995,41.780921936],"type":"Point"}
}