{
  "type": "Feature",
  "properties": {
    "iso:country":"ES",
    "sg:address":"Plaz Puerta De Avila, 16",
    "sg:city":"Bejar",
    "sg:orig_category":"Lencer\u00cda Femenina, Corseter\u00cda, Trajes De Ba\u00d1o (al Por Menor)",
    "sg:phone":"+34 923 41 01 67",
    "sg:postcode":"37700",
    "sg:province":"Salamanca",
    "wof:name":"Joya Huerta Moira",
    "wof:placetype":"venue"
},
  "geometry": {"coordinates":[-5.7647848129,40.3858680725],"type":"Point"}
}