{
  "type": "Feature",
  "properties": {
    "addr:full":"Av Generalitat, 32 Abrera Barcelona 08630",
    "addr:housenumber":"32",
    "addr:postcode":"08630",
    "addr:street":"Av Generalitat",
    "iso:country":"ES",
    "sg:address":"Av Generalitat, 32",
    "sg:city":"Abrera",
    "sg:orig_category":"Organizaciones Profesionales",
    "sg:phone":"+34 937 70 23 02",
    "sg:postcode":"08630",
    "sg:province":"Barcelona",
    "wof:name":"Necsus Serveis De Control Sl",
    "wof:placetype":"venue"
},
  "geometry": {"coordinates":[1.9006650448,41.5178451538],"type":"Point"}
}