{
  "type": "Feature",
  "properties": {
    "iso:country":"ES",
    "sg:address":"Calle de Primo De Rivera, 15",
    "sg:city":"Pe\u00f1iscola",
    "sg:orig_category":"Laboratorios Y Trabajos De Fotograf\u00cda, V\u00cddeo Y Cine",
    "sg:phone":"+34 964 48 00 41",
    "sg:postcode":"12598",
    "sg:province":"Castell\u00f3n",
    "wof:name":"Foto Riba S.l.",
    "wof:placetype":"venue"
},
  "geometry": {"coordinates":[0.4042269886,40.3594818115],"type":"Point"}
}