{
  "type": "Feature",
  "properties": {
    "iso:country":"ES",
    "sg:address":"Calle de San Jose, 17",
    "sg:city":"Valle Trapaga",
    "sg:orig_category":"Asociaciones Y Clubs Deportivos",
    "sg:phone":"+34 944 86 26 14",
    "sg:postcode":"48510",
    "sg:province":"Vizcaya",
    "wof:name":"A. J. Trapaga Gimnasio",
    "wof:placetype":"venue"
},
  "geometry": {"coordinates":[-3.0337910652,43.3028373718],"type":"Point"}
}