{
  "type": "Feature",
  "properties": {
    "addr:full":"Carrer de Sant Antoni, 6 Casc Antic Barcelona 08150",
    "addr:housenumber":"6",
    "addr:postcode":"08150",
    "addr:street":"Carrer De Sant Antoni",
    "iso:country":"ES",
    "sg:address":"Carrer de Sant Antoni, 6",
    "sg:city":"Casc Antic",
    "sg:orig_category":"Pescader\u00cdas (al Por Menor)",
    "sg:phone":"+34 935 62 12 50",
    "sg:postcode":"08150",
    "sg:province":"Barcelona",
    "wof:name":"Cristofol Arimany Joan",
    "wof:placetype":"venue"
},
  "geometry": {"coordinates":[2.2293000221,41.5678787231],"type":"Point"}
}