{
  "type": "Feature",
  "properties": {
    "iso:country":"ES",
    "sg:address":"Calle de Fuencarral, 55",
    "sg:city":"Madrid",
    "sg:orig_category":"Ropa Para Se\u00d1oras (al Por Menor)",
    "sg:phone":"+34 915 22 72 65",
    "sg:postcode":"28004",
    "sg:province":"Madrid",
    "wof:name":"Martin Redondo Carlos",
    "wof:placetype":"venue"
},
  "geometry": {"coordinates":[-3.7006902695,40.4241104126],"type":"Point"}
}