{
  "type": "Feature",
  "properties": {
    "iso:country":"ES",
    "sg:address":"Carr Recreo, 4",
    "sg:city":"Vilanova I La Geltru",
    "sg:orig_category":"Centros M\u00c9dicos Y Sociales, Dispensarios",
    "sg:phone":"+34 938 14 41 22",
    "sg:postcode":"08800",
    "sg:province":"Barcelona",
    "wof:name":"Procesos Y Embalajes Cano S.l.l.",
    "wof:placetype":"venue"
},
  "geometry": {"coordinates":[1.7242840528,41.2246208191],"type":"Point"}
}