{
  "type": "Feature",
  "properties": {
    "addr:full":"Avda Pais Valencia, 140 Torrent Valencia 46900",
    "addr:housenumber":"140",
    "addr:postcode":"46900",
    "addr:street":"Avda Pais Valencia;Valencia",
    "iso:country":"ES",
    "sg:address":"Avda Pais Valencia, 140",
    "sg:city":"Torrent",
    "sg:orig_category":"Arquitectos",
    "sg:phone":"+34 961 57 21 51",
    "sg:postcode":"46900",
    "sg:province":"Valencia",
    "wof:name":"Aznar Arquitectos S.l.",
    "wof:placetype":"venue"
},
  "geometry": {"coordinates":[-0.4842593074,39.4246749878],"type":"Point"}
}