{
  "type": "Feature",
  "properties": {
    "addr:full":"Carrer de Antonio Machado, 18 Castelldefels Barcelona 08860",
    "addr:housenumber":"18",
    "addr:postcode":"08860",
    "addr:street":"Carrer De Antonio Machado",
    "iso:country":"ES",
    "sg:address":"Carrer de Antonio Machado, 18",
    "sg:city":"Castelldefels",
    "sg:orig_category":"Ropa Para Se\u00d1oras Y Caballeros (al Por Menor)",
    "sg:phone":"+34 936 64 40 05",
    "sg:postcode":"08860",
    "sg:province":"Barcelona",
    "wof:name":"Jimenez Martinez Jose Maria",
    "wof:placetype":"venue"
},
  "geometry": {"coordinates":[1.9815809727,41.2866439819],"type":"Point"}
}