{
  "type": "Feature",
  "properties": {
    "iso:country":"ES",
    "sg:address":"Carr Roders, 1",
    "sg:city":"Cabaneta",
    "sg:orig_category":"Deportes N\u00c1uticos, Acu\u00c1ticos Y Subacu\u00c1ticos: Art\u00cdculos Y Equipo (al Por Menor)",
    "sg:phone":"+34 971 60 42 61",
    "sg:postcode":"07141",
    "sg:province":"Islas Baleares",
    "wof:name":"Construcciones Nauticas Vs S.l.",
    "wof:placetype":"venue"
},
  "geometry": {"coordinates":[2.741590023,39.6156005859],"type":"Point"}
}