{
  "type": "Feature",
  "properties": {
    "addr:full":"Calle de Sierra De Guadarrama, 16 Arganda Madrid 28500",
    "addr:housenumber":"16",
    "addr:postcode":"28500",
    "addr:street":"Calle De Sierra De Guadarrama",
    "iso:country":"ES",
    "sg:address":"Calle de Sierra De Guadarrama, 16",
    "sg:city":"Arganda",
    "sg:orig_category":"Mec\u00c1nico Del Autom\u00d3vil",
    "sg:phone":"+34 918 71 95 38",
    "sg:postcode":"28500",
    "sg:province":"Madrid",
    "wof:name":"Fernandez Soriano Jose Antonio",
    "wof:placetype":"venue"
},
  "geometry": {"coordinates":[-3.4760489464,40.3070602417],"type":"Point"}
}