{
  "type": "Feature",
  "properties": {
    "iso:country":"ES",
    "sg:address":"Av Can Pallas, 4",
    "sg:city":"Can Pallas-llobateras",
    "sg:orig_category":"Fisioterapia",
    "sg:phone":"+34 937 21 55 55",
    "sg:postcode":"08192",
    "sg:province":"Barcelona",
    "wof:name":"Fisiomed Sant Quirze S.l.",
    "wof:placetype":"venue"
},
  "geometry": {"coordinates":[2.0661990643,41.5389862061],"type":"Point"}
}