{
  "type": "Feature",
  "properties": {
    "iso:country":"ES",
    "sg:address":"Aguacate(urb Chorrico), 14",
    "sg:city":"Molina Segura",
    "sg:orig_category":"Inform\u00c1tica Equipo Y Programas (al Por Mayor)",
    "sg:phone":"+34 968 64 87 66",
    "sg:postcode":"30500",
    "sg:province":"Murcia",
    "sg:website":"www.metpatel.com",
    "wof:name":"Garcia Jimenez Jesus",
    "wof:placetype":"venue"
},
  "geometry": {"coordinates":[-1.1792830229,38.0622520447],"type":"Point"}
}