{
  "type": "Feature",
  "properties": {
    "iso:country":"ES",
    "sg:address":"Calle de Juan Ramon Jimenez, 39",
    "sg:city":"Bollullos Par Condado",
    "sg:orig_category":"Centros Empresariales",
    "sg:phone":"+34 959 41 10 68",
    "sg:postcode":"21710",
    "sg:province":"Huelva",
    "wof:name":"Toldos Do\u00d1ana S.l.",
    "wof:placetype":"venue"
},
  "geometry": {"coordinates":[-6.5403008461,37.3389930725],"type":"Point"}
}