{
  "type": "Feature",
  "properties": {
    "addr:full":"Calle de Cirilo Moreno, 18 Palmas De Gran Canaria Las Palmas 35007",
    "addr:postcode":"35007",
    "addr:street":"Calle De Cirilo Moreno 18",
    "iso:country":"ES",
    "sg:address":"Calle de Cirilo Moreno, 18",
    "sg:city":"Palmas De Gran Canaria",
    "sg:orig_category":"Loter\u00cda Y T\u00d3mbola",
    "sg:phone":"+34 928 26 05 53",
    "sg:postcode":"35007",
    "sg:province":"Las Palmas",
    "wof:name":"Viejo Rodriguez Francisco",
    "wof:placetype":"venue"
},
  "geometry": {"coordinates":[-15.4321813583,28.1367321014],"type":"Point"}
}