{
  "type": "Feature",
  "properties": {
    "addr:full":"Jaume Ii, 41 Montu\u00efri Islas Baleares 07230",
    "addr:housenumber":"41",
    "addr:postcode":"07230",
    "addr:street":"Jaume Ii",
    "iso:country":"ES",
    "sg:address":"Jaume Ii, 41",
    "sg:city":"Montu\u00efri",
    "sg:orig_category":"Turismo: Lugares, Circuitos Y Curiosidades",
    "sg:phone":"+34 971 64 62 23",
    "sg:postcode":"07230",
    "sg:province":"Islas Baleares",
    "wof:name":"Original Tour Mallorca S.l.",
    "wof:placetype":"venue"
},
  "geometry": {"coordinates":[2.981867075,39.5685424805],"type":"Point"}
}