{
  "type": "Feature",
  "properties": {
    "iso:country":"ES",
    "sg:address":"Calle de San Luis, 42",
    "sg:city":"Alcorcon",
    "sg:orig_category":"Plomeros",
    "sg:phone":"+34 916 41 03 95",
    "sg:postcode":"28921",
    "sg:province":"Madrid",
    "wof:name":"Oliveros Martinez Francisco Javier",
    "wof:placetype":"venue"
},
  "geometry": {"coordinates":[-3.8250730038,40.3457832336],"type":"Point"}
}