{
  "type": "Feature",
  "properties": {
    "iso:country":"ES",
    "sg:address":"Cmno Katuja-ibarra, 1",
    "sg:city":"Llodio",
    "sg:orig_category":"Charcuter\u00cdas (al Por Mayor)",
    "sg:phone":"+34 946 72 27 52",
    "sg:postcode":"01400",
    "sg:province":"\u00c1lava",
    "wof:name":"Embutidos Santamaria S.c.",
    "wof:placetype":"venue"
},
  "geometry": {"coordinates":[-2.9707520008,43.1333198547],"type":"Point"}
}