{
  "type": "Feature",
  "properties": {
    "addr:full":"Calle de Escuza Jose Maria, 27 Bilbao Vizcaya 48013",
    "addr:housenumber":"27",
    "addr:postcode":"48013",
    "addr:street":"Calle De Escuza Jose Maria",
    "iso:country":"ES",
    "sg:address":"Calle de Escuza Jose Maria, 27",
    "sg:city":"Bilbao",
    "sg:orig_category":"Pintura, Barniz, Productos Asimilables (fabricaci\u00d3n, Al Por Mayor)",
    "sg:phone":"+34 944 27 60 09",
    "sg:postcode":"48013",
    "sg:province":"Vizcaya",
    "wof:name":"Luis Andres Perez Maga\u00f1a",
    "wof:placetype":"venue"
},
  "geometry": {"coordinates":[-2.9457390308,43.2608909607],"type":"Point"}
}