{
  "type": "Feature",
  "properties": {
    "iso:country":"ES",
    "sg:address":"Calle de Bausa, 27",
    "sg:city":"Madrid",
    "sg:orig_category":"Ingenier\u00cda, Centros De Estudios (diversos)",
    "sg:phone":"+34 913 02 27 91",
    "sg:postcode":"28033",
    "sg:province":"Madrid",
    "wof:name":"Fractalia Hotel Systems S.l.",
    "wof:placetype":"venue"
},
  "geometry": {"coordinates":[-3.6689727306,40.4710731506],"type":"Point"}
}