{
  "type": "Feature",
  "properties": {
    "addr:full":"Calle de Zabaleta, 44 Donostia-san Sebastian Guip\u00f9zcoa 20002",
    "addr:housenumber":"44",
    "addr:postcode":"20002",
    "addr:street":"Calle De Zabaleta",
    "iso:country":"ES",
    "sg:address":"Calle de Zabaleta, 44",
    "sg:city":"Donostia-san Sebastian",
    "sg:orig_category":"Centros Pms (psico",
    "sg:phone":"+34 943 27 40 88",
    "sg:postcode":"20002",
    "sg:province":"Guip\u00f9zcoa",
    "wof:name":"Etxezarreta Arratibel Edurne",
    "wof:placetype":"venue"
},
  "geometry": {"coordinates":[-1.972424984,43.3255195618],"type":"Point"}
}