{
  "type": "Feature",
  "properties": {
    "addr:full":"Avda Prado, Del, 39 Ugena Toledo 45217",
    "addr:housenumber":"39",
    "addr:postcode":"45217",
    "addr:street":"Avda Prado Del",
    "iso:country":"ES",
    "sg:address":"Avda Prado, Del, 39",
    "sg:city":"Ugena",
    "sg:orig_category":"Empresarios Y Productoras De Espect\u00c1culos",
    "sg:phone":"+34 925 53 39 89",
    "sg:postcode":"45217",
    "sg:province":"Toledo",
    "wof:name":"Iniciativas Y Proyectos Culturales S.l.",
    "wof:placetype":"venue"
},
  "geometry": {"coordinates":[-3.877669096,40.1581344604],"type":"Point"}
}