{
  "type": "Feature",
  "properties": {
    "iso:country":"ES",
    "sg:address":"Calle de Maestro Ripolles, 46",
    "sg:city":"Castellon",
    "sg:classifiers":[
        {
            "category":"Personal",
            "subcategory":"Barber",
            "type":"Services"
        }
    ],
    "sg:phone":"+34 964 22 64 82",
    "sg:postcode":"12003",
    "sg:province":"Castell\u00f3n",
    "sg:tags":[
        "caballeros",
        "de",
        "peluqueros"
    ],
    "wof:name":"Caravaca Perez Angel",
    "wof:placetype":"venue"
},
  "geometry": {"coordinates":[-0.0077,39.9838409424],"type":"Point"}
}