{
  "type": "Feature",
  "properties": {
    "addr:full":"Calle de Cervantes, 12 Almendralejo Badajoz 06200",
    "addr:housenumber":"12",
    "addr:postcode":"06200",
    "addr:street":"Calle De Cervantes",
    "iso:country":"ES",
    "sg:address":"Calle de Cervantes, 12",
    "sg:city":"Almendralejo",
    "sg:orig_category":"Agencias Y Agentes Comerciales, Representantes",
    "sg:phone":"+34 924 66 02 67",
    "sg:postcode":"06200",
    "sg:province":"Badajoz",
    "wof:name":"Torres Soler Pedro",
    "wof:placetype":"venue"
},
  "geometry": {"coordinates":[-6.4072504044,38.6832962036],"type":"Point"}
}