{
  "type": "Feature",
  "properties": {
    "iso:country":"ES",
    "sg:address":"Avda Extremadura, 1",
    "sg:city":"Garrovilla",
    "sg:orig_category":"Iglesia Cat\u00d3lica",
    "sg:phone":"+34 924 33 50 41",
    "sg:postcode":"06870",
    "sg:province":"Badajoz",
    "wof:name":"Parroquia Nuestra Se\u00f1ora De La Asuncion",
    "wof:placetype":"venue"
},
  "geometry": {"coordinates":[-6.4764328003,38.9203414917],"type":"Point"}
}