{
  "type": "Feature",
  "properties": {
    "iso:country":"ES",
    "sg:address":"Calle de Sarrikobaso, 14",
    "sg:city":"Getxo",
    "sg:orig_category":"Empresas De Carpinter\u00cda De Madera",
    "sg:phone":"+34 944 30 86 60",
    "sg:postcode":"48990",
    "sg:province":"Vizcaya",
    "wof:name":"Aransar S.l.",
    "wof:placetype":"venue"
},
  "geometry": {"coordinates":[-3.0096006393,43.3531265259],"type":"Point"}
}