{
  "type": "Feature",
  "properties": {
    "addr:full":"Calle de Triste Condesa, 13 Arenas San Pedro \u00c1vila 05400",
    "addr:housenumber":"13",
    "addr:postcode":"05400",
    "addr:street":"Calle De Triste Condesa;A\u0301Vila",
    "iso:country":"ES",
    "sg:address":"Calle de Triste Condesa, 13",
    "sg:city":"Arenas San Pedro",
    "sg:orig_category":"Ropa Para Se\u00d1oras Y Caballeros (al Por Menor)",
    "sg:phone":"+34 920 37 13 62",
    "sg:postcode":"05400",
    "sg:province":"\u00c1vila",
    "wof:name":"Confecciones Le\u00d1o S.l.",
    "wof:placetype":"venue"
},
  "geometry": {"coordinates":[-5.0894508362,40.2098693848],"type":"Point"}
}