{
  "type": "Feature",
  "properties": {
    "addr:full":"Plaz Mayor, 16 Briviesca Burgos 09240",
    "addr:housenumber":"16",
    "addr:postcode":"09240",
    "addr:street":"Plaz Mayor",
    "iso:country":"ES",
    "sg:address":"Plaz Mayor, 16",
    "sg:city":"Briviesca",
    "sg:orig_category":"Imprenta",
    "sg:phone":"+34 947 59 38 00",
    "sg:postcode":"09240",
    "sg:province":"Burgos",
    "wof:name":"Diario De Burgos S.a.",
    "wof:placetype":"venue"
},
  "geometry": {"coordinates":[-3.3246610165,42.5496292114],"type":"Point"}
}