{
  "type": "Feature",
  "properties": {
    "addr:full":"Calle de Montes Del Sueve, 59 Oviedo Asturias 33012",
    "addr:housenumber":"59",
    "addr:postcode":"33012",
    "addr:street":"Calle De Montes Del Sueve",
    "iso:country":"ES",
    "sg:address":"Calle de Montes Del Sueve, 59",
    "sg:city":"Oviedo",
    "sg:orig_category":"Edici\u00d3n De Diarios, Revistas, Boletines",
    "sg:phone":"+34 985 29 81 03",
    "sg:postcode":"33012",
    "sg:province":"Asturias",
    "wof:name":"Ediciones Nobel S.a.",
    "wof:placetype":"venue"
},
  "geometry": {"coordinates":[-5.8596892357,43.3686637878],"type":"Point"}
}