{
  "type": "Feature",
  "properties": {
    "iso:country":"ES",
    "sg:address":"Calle de Virgen De La Vega, 3",
    "sg:city":"Haro",
    "sg:orig_category":"Librer\u00cdas",
    "sg:phone":"+34 941 31 15 58",
    "sg:postcode":"26200",
    "sg:province":"La Rioja",
    "wof:name":"Perez Saez Enrique",
    "wof:placetype":"venue"
},
  "geometry": {"coordinates":[-2.8476159573,42.5769309998],"type":"Point"}
}