{
  "type": "Feature",
  "properties": {
    "iso:country":"ES",
    "sg:address":"Carbo Es, 2",
    "sg:city":"Eivissa",
    "sg:orig_category":"Art\u00cdculos De Regalo (al Por Menor)",
    "sg:phone":"+34 971 31 51 27",
    "sg:postcode":"07800",
    "sg:province":"Islas Baleares",
    "wof:name":"Space Ibiza Clubwear C.b.",
    "wof:placetype":"venue"
},
  "geometry": {"coordinates":[1.4188899994,38.9061164856],"type":"Point"}
}