{
  "type": "Feature",
  "properties": {
    "addr:full":"Carr Ignasi Bastus, 28 Lleida Lleida 25001",
    "addr:housenumber":"28",
    "addr:postcode":"25001",
    "addr:street":"Carr Ignasi Bastus",
    "iso:country":"ES",
    "sg:address":"Carr Ignasi Bastus, 28",
    "sg:city":"Lleida",
    "sg:orig_category":"Venta, Instalaci\u00d3n De Cocinas",
    "sg:phone":"+34 973 20 45 28",
    "sg:postcode":"25001",
    "sg:province":"Lleida",
    "wof:name":"Aguila Zafra Maria Dolores",
    "wof:placetype":"venue"
},
  "geometry": {"coordinates":[0.6448976994,41.6057281494],"type":"Point"}
}