{
  "type": "Feature",
  "properties": {
    "addr:full":"Ctra. Nnal. Trescientos Cuarenta, Km. 0136,0 Sotogrande C\u00e1diz 11310",
    "addr:postcode":"11310",
    "addr:street":"Ctra. Nnal.;Cuarenta Km. 0136,0 Sotogrande Ca\u0301Diz",
    "iso:country":"ES",
    "sg:address":"Ctra. Nnal. Trescientos Cuarenta, Km. 0136,0",
    "sg:city":"Sotogrande",
    "sg:classifiers":[
        {
            "category":"Sports & Exercise",
            "subcategory":"Golf",
            "type":"Entertainment"
        }
    ],
    "sg:phone":"+34 956 79 60 28",
    "sg:postcode":"11310",
    "sg:province":"C\u00e1diz",
    "sg:tags":[
        "y",
        "de",
        "campos",
        "clases"
    ],
    "sg:website":"www.valderrama.com",
    "wof:name":"Club De Golf Valderrama",
    "wof:placetype":"venue"
},
  "geometry": {"coordinates":[-5.2829370499,36.2767448425],"type":"Point"}
}