{
  "type": "Feature",
  "properties": {
    "iso:country":"ES",
    "sg:address":"Calle de Marques De Los Velez, 7",
    "sg:city":"Velez-blanco",
    "sg:orig_category":"Aguas (distribuci\u00d3n, Servicios)",
    "sg:phone":"+34 950 41 56 50",
    "sg:postcode":"04830",
    "sg:province":"Almer\u00eda",
    "wof:name":"Aquagest Sur S A",
    "wof:placetype":"venue"
},
  "geometry": {"coordinates":[-2.0958554745,37.6952667236],"type":"Point"}
}