{
  "type": "Feature",
  "properties": {
    "addr:full":"Ctra Bilbao-plencia, 17 Erandio-goikoa Vizcaya 48950",
    "addr:housenumber":"17",
    "addr:postcode":"48950",
    "addr:street":"Ctra Bilbao-Plencia",
    "iso:country":"ES",
    "sg:address":"Ctra Bilbao-plencia, 17",
    "sg:city":"Erandio-goikoa",
    "sg:orig_category":"Papeler\u00cdas, Librer\u00cdas",
    "sg:phone":"+34 944 71 16 01",
    "sg:postcode":"48950",
    "sg:province":"Vizcaya",
    "wof:name":"Arte Y Calidad En Papel Artepapel S.a.",
    "wof:placetype":"venue"
},
  "geometry": {"coordinates":[-2.9493944645,43.2992858887],"type":"Point"}
}