{
  "type": "Feature",
  "properties": {
    "iso:country":"ES",
    "sg:address":"Calle de Camino De Membrilla, 8",
    "sg:city":"Manzanares",
    "sg:orig_category":"Maquinaria Para Industrias Diversas",
    "sg:phone":"+34 926 61 28 00",
    "sg:postcode":"13200",
    "sg:province":"Ciudad Real",
    "wof:name":"Cano Pe\u00f1a Pedro",
    "wof:placetype":"venue"
},
  "geometry": {"coordinates":[-3.3689830303,38.9924850464],"type":"Point"}
}