{
  "type": "Feature",
  "properties": {
    "iso:country":"ES",
    "sg:address":"Calle de Burgos, 8",
    "sg:city":"Santander",
    "sg:orig_category":"Discapacitados",
    "sg:phone":"+34 942 23 70 53",
    "sg:postcode":"39008",
    "sg:province":"Cantabria",
    "sg:website":"www.fundacionafim.org",
    "wof:name":"Fundacion Afim",
    "wof:placetype":"venue"
},
  "geometry": {"coordinates":[-3.8149237633,43.4614830017],"type":"Point"}
}