{
  "type": "Feature",
  "properties": {
    "addr:full":"Puerta De Palacio, 1 Roa Burgos 09300",
    "addr:housenumber":"1",
    "addr:postcode":"09300",
    "iso:country":"ES",
    "sg:address":"Puerta De Palacio, 1",
    "sg:city":"Roa",
    "sg:orig_category":"Barbacoas Y Accesorios",
    "sg:phone":"+34 947 54 02 14",
    "sg:postcode":"09300",
    "sg:province":"Burgos",
    "wof:name":"Asados Nazareno S.l.",
    "wof:placetype":"venue"
},
  "geometry": {"coordinates":[-3.9259421825,41.6971359253],"type":"Point"}
}