{
  "type": "Feature",
  "properties": {
    "addr:full":"Avda Sur (del), 64 Granada Granada 18014",
    "addr:postcode":"18014",
    "addr:street":"Avda;Del",
    "iso:country":"ES",
    "sg:address":"Avda Sur (del), 64",
    "sg:city":"Granada",
    "sg:orig_category":"Peluqueros: De Se\u00d1oras",
    "sg:phone":"+34 958 29 14 52",
    "sg:postcode":"18014",
    "sg:province":"Granada",
    "wof:name":"Perez Colacio Gracia",
    "wof:placetype":"venue"
},
  "geometry": {"coordinates":[-3.613697052,37.1881332397],"type":"Point"}
}