{
  "type": "Feature",
  "properties": {
    "iso:country":"ES",
    "sg:address":"Avda Fontes, 26",
    "sg:city":"Torre-pacheco",
    "sg:orig_category":"\u00d3ptica: Instrumentos (fabricaci\u00d3n)",
    "sg:phone":"+34 968 58 56 67",
    "sg:postcode":"30700",
    "sg:province":"Murcia",
    "wof:name":"Optica Maria Del Mar Garcia S.l.",
    "wof:placetype":"venue"
},
  "geometry": {"coordinates":[-1.1302490234,37.9829597473],"type":"Point"}
}