{
  "type": "Feature",
  "properties": {
    "addr:full":"Carr Sant Ramon, 52 Badalona Barcelona 08912",
    "addr:housenumber":"52",
    "addr:postcode":"08912",
    "addr:street":"Carr Sant Ramon",
    "iso:country":"ES",
    "sg:address":"Carr Sant Ramon, 52",
    "sg:city":"Badalona",
    "sg:orig_category":"Empresas De Carpinter\u00cda De Madera",
    "sg:phone":"+34 933 87 54 42",
    "sg:postcode":"08912",
    "sg:province":"Barcelona",
    "wof:name":"Ayet Ma\u00f1osa Francisco",
    "wof:placetype":"venue"
},
  "geometry": {"coordinates":[2.2412250042,41.4484062195],"type":"Point"}
}