{
  "type": "Feature",
  "properties": {
    "addr:full":"Calle de Lopez De Hoyos, 159 Madrid Madrid 28002",
    "addr:housenumber":"159",
    "addr:postcode":"28002",
    "addr:street":"Calle De Lopez De Hoyos",
    "iso:country":"ES",
    "sg:address":"Calle de Lopez De Hoyos, 159",
    "sg:city":"Madrid",
    "sg:orig_category":"Agencias De Viajes",
    "sg:phone":"+34 915 19 64 67",
    "sg:postcode":"28002",
    "sg:province":"Madrid",
    "wof:name":"Viajes Halcon S.a.",
    "wof:placetype":"venue"
},
  "geometry": {"coordinates":[-3.6673710346,40.4487953186],"type":"Point"}
}