{
  "type": "Feature",
  "properties": {
    "addr:full":"Carrer de Turina, 44 Sabadell Barcelona 08206",
    "addr:housenumber":"44",
    "addr:postcode":"08206",
    "addr:street":"Carrer De Turina",
    "iso:country":"ES",
    "sg:address":"Carrer de Turina, 44",
    "sg:city":"Sabadell",
    "sg:orig_category":"Asociaciones, Organismos Culturales Y Socioeducativos",
    "sg:phone":"+34 937 25 77 93",
    "sg:postcode":"08206",
    "sg:province":"Barcelona",
    "wof:name":"Associacio Juvenil Esquitx",
    "wof:placetype":"venue"
},
  "geometry": {"coordinates":[2.0835597515,41.5504455566],"type":"Point"}
}