{
  "type": "Feature",
  "properties": {
    "addr:full":"Calle de Doctor Antonio Cortes Llado, 1 Sevilla Sevilla 41004",
    "addr:housenumber":"1",
    "addr:postcode":"41004",
    "addr:street":"Calle De Doctor Antonio Cortes Llado",
    "iso:country":"ES",
    "sg:address":"Calle de Doctor Antonio Cortes Llado, 1",
    "sg:city":"Sevilla",
    "sg:orig_category":"Promotores Constructores",
    "sg:phone":"+34 954 41 35 63",
    "sg:postcode":"41004",
    "sg:province":"Sevilla",
    "wof:name":"Pefersan S. A.",
    "wof:placetype":"venue"
},
  "geometry": {"coordinates":[-5.9814815521,37.3774795532],"type":"Point"}
}