{
  "type": "Feature",
  "properties": {
    "addr:full":"A Brea, 39 Brea La Coru\u00f1a 15640",
    "addr:housenumber":"39",
    "addr:postcode":"15640",
    "addr:street":"Brea;La Corun\u0303A",
    "iso:country":"ES",
    "sg:address":"A Brea, 39",
    "sg:city":"Brea",
    "sg:orig_category":"Ortopedia General",
    "sg:phone":"+34 981 78 04 02",
    "sg:postcode":"15640",
    "sg:province":"La Coru\u00f1a",
    "wof:name":"Farmacias Matilla Romero S.l.",
    "wof:placetype":"venue"
},
  "geometry": {"coordinates":[-8.2682237625,43.2997894287],"type":"Point"}
}