{
  "type": "Feature",
  "properties": {
    "iso:country":"ES",
    "sg:address":"Calle de Doctor Balbino Povedano Ruiz, 11",
    "sg:city":"Priego Cordoba",
    "sg:orig_category":"Carnicer\u00cdas, Carnicer\u00cdas",
    "sg:phone":"+34 957 54 38 26",
    "sg:postcode":"14800",
    "sg:province":"C\u00f3rdoba",
    "wof:name":"Pulido Bermudez Jose",
    "wof:placetype":"venue"
},
  "geometry": {"coordinates":[-4.2014837265,37.4397125244],"type":"Point"}
}