{
  "type": "Feature",
  "properties": {
    "addr:full":"Calle de Mauricio Legendre, 15 Madrid Madrid 28046",
    "addr:housenumber":"15",
    "addr:postcode":"madrid;28046",
    "addr:street":"Calle De Mauricio Legendre",
    "iso:country":"ES",
    "sg:address":"Calle de Mauricio Legendre, 15",
    "sg:city":"Madrid",
    "sg:orig_category":"M\u00c9dicos: An\u00c1lisis Cl\u00cdnicos",
    "sg:phone":"+34 913 15 94 04",
    "sg:postcode":"28046",
    "sg:province":"Madrid",
    "wof:name":"Lopez Salcedo Antonio",
    "wof:placetype":"venue"
},
  "geometry": {"coordinates":[-3.6865155697,40.4705505371],"type":"Point"}
}