{
  "type": "Feature",
  "properties": {
    "addr:full":"Av Rey Jaime I, S/n Llanera Ranes Valencia 46814",
    "addr:housenumber":"s / n",
    "addr:postcode":"46814",
    "addr:street":"Av Rey Jaime I",
    "iso:country":"ES",
    "sg:address":"Av Rey Jaime I, S/n",
    "sg:city":"Llanera Ranes",
    "sg:orig_category":"Empresas De Desmonte",
    "sg:phone":"+34 962 92 80 82",
    "sg:postcode":"46814",
    "sg:province":"Valencia",
    "wof:name":"Quiles Alzamora Gabriel",
    "wof:placetype":"venue"
},
  "geometry": {"coordinates":[-0.5723490119,38.9887084961],"type":"Point"}
}