{
  "type": "Feature",
  "properties": {
    "iso:country":"ES",
    "sg:address":"Calle de Solarillo De Gracia, 5",
    "sg:city":"Granada",
    "sg:orig_category":"Abogados",
    "sg:phone":"+34 958 25 15 98",
    "sg:postcode":"18002",
    "sg:province":"Granada",
    "sg:website":"www.domech.net",
    "wof:name":"Domech Perez-garzon Antonio Ramon",
    "wof:placetype":"venue"
},
  "geometry": {"coordinates":[-3.6034190655,37.1724777222],"type":"Point"}
}