{
  "type": "Feature",
  "properties": {
    "addr:full":"Calle de Ruperto Escobar, 14 Umbrete Sevilla 41806",
    "addr:housenumber":"14",
    "addr:postcode":"41806",
    "addr:street":"Calle De Ruperto Escobar",
    "iso:country":"ES",
    "sg:address":"Calle de Ruperto Escobar, 14",
    "sg:city":"Umbrete",
    "sg:orig_category":"Arreglo, Reparaci\u00d3n, Piezas Sueltas De Televisi\u00d3n, V\u00cddeo, Hi",
    "sg:phone":"+34 955 71 57 57",
    "sg:postcode":"41806",
    "sg:province":"Sevilla",
    "wof:name":"Salado Navarro Ruperto",
    "wof:placetype":"venue"
},
  "geometry": {"coordinates":[-6.1555981636,37.3695526123],"type":"Point"}
}