{
  "type": "Feature",
  "properties": {
    "addr:full":"Calle de Alvarado, S/n Carchuna Granada 18730",
    "addr:housenumber":"s / n",
    "addr:postcode":"18730",
    "addr:street":"Calle De Alvarado",
    "iso:country":"ES",
    "sg:address":"Calle de Alvarado, S/n",
    "sg:city":"Carchuna",
    "sg:orig_category":"Agricultores, Agricultores",
    "sg:phone":"+34 958 62 31 46",
    "sg:postcode":"18730",
    "sg:province":"Granada",
    "wof:name":"Carchuna La Palma S.c.a.",
    "wof:placetype":"venue"
},
  "geometry": {"coordinates":[-3.4438300133,36.7021331787],"type":"Point"}
}