{
  "type": "Feature",
  "properties": {
    "iso:country":"ES",
    "sg:address":"Centro Comercial Bonaire, S/n",
    "sg:city":"Aldaia",
    "sg:orig_category":"Fabricaci\u00d3n, Importaci\u00d3n, Venta De Material De Telefon\u00cda, Peritelefon\u00cda",
    "sg:phone":"+34 961 57 92 97",
    "sg:postcode":"46960",
    "sg:province":"Valencia",
    "sg:website":"www.phonehouse.es",
    "wof:name":"Phone Warehouse S.a.",
    "wof:placetype":"venue"
},
  "geometry": {"coordinates":[-0.4853590131,39.4696578979],"type":"Point"}
}