{
  "type": "Feature",
  "properties": {
    "addr:full":"Avda Buhaira (la), 15 Sevilla Sevilla 41018",
    "addr:housenumber":"15",
    "addr:postcode":"41018",
    "addr:street":"Avda Buhaira La",
    "iso:country":"ES",
    "sg:address":"Avda Buhaira (la), 15",
    "sg:city":"Sevilla",
    "sg:orig_category":"Pr\u00c9stamos Personales E Hipotecarios",
    "sg:phone":"+34 954 53 48 14",
    "sg:postcode":"41018",
    "sg:province":"Sevilla",
    "wof:name":"Registro De La Propiedad",
    "wof:placetype":"venue"
},
  "geometry": {"coordinates":[-5.9789690971,37.3849601746],"type":"Point"}
}