{
  "type": "Feature",
  "properties": {
    "addr:full":"Calle de Alcazar (el), 4 Almeria Almer\u00eda 04006",
    "addr:housenumber":"4",
    "addr:postcode":"04006",
    "addr:street":"Calle De Alcazar El",
    "iso:country":"ES",
    "sg:address":"Calle de Alcazar (el), 4",
    "sg:city":"Almeria",
    "sg:orig_category":"Arquitectos",
    "sg:phone":"+34 950 26 32 90",
    "sg:postcode":"04006",
    "sg:province":"Almer\u00eda",
    "wof:name":"Alberca Proyectos S.l.",
    "wof:placetype":"venue"
},
  "geometry": {"coordinates":[-2.4511687756,36.8373908997],"type":"Point"}
}