{
  "type": "Feature",
  "properties": {
    "iso:country":"ES",
    "sg:address":"Carrer de B Pons I Fabregues, 18",
    "sg:city":"Palma",
    "sg:orig_category":"Hielo Artificial (fabricaci\u00d3n, Distribuci\u00d3n)",
    "sg:phone":"+34 971 27 22 73",
    "sg:postcode":"07007",
    "sg:province":"Islas Baleares",
    "wof:name":"Aznar Cortes Francisco",
    "wof:placetype":"venue"
},
  "geometry": {"coordinates":[2.6679201126,39.5726966858],"type":"Point"}
}