{
  "type": "Feature",
  "properties": {
    "iso:country":"ES",
    "sg:address":"Avgd Prat De La Riba, 39",
    "sg:city":"Lleida",
    "sg:orig_category":"Restaurantes",
    "sg:phone":"+34 973 23 81 97",
    "sg:postcode":"25008",
    "sg:province":"Lleida",
    "wof:name":"Miralles Saurte Ramon",
    "wof:placetype":"venue"
},
  "geometry": {"coordinates":[0.6236870289,41.6210823059],"type":"Point"}
}