{
  "type": "Feature",
  "properties": {
    "iso:country":"ES",
    "sg:address":"Calle de Astros, 40",
    "sg:city":"Cuellar",
    "sg:orig_category":"Trabajos De Perforaciones, Sondeos, Construcci\u00d3n De Pozos",
    "sg:phone":"+34 921 14 11 43",
    "sg:postcode":"40200",
    "sg:province":"Segovia",
    "wof:name":"Fraile Gutierrez Felix",
    "wof:placetype":"venue"
},
  "geometry": {"coordinates":[-4.3137793541,41.3960800171],"type":"Point"}
}