{
  "type": "Feature",
  "properties": {
    "iso:country":"ES",
    "sg:address":"Calle de Alsasua, 14",
    "sg:city":"Madrid",
    "sg:orig_category":"Maquinaria Para Industrias Diversas",
    "sg:phone":"+34 913 23 46 29",
    "sg:postcode":"28023",
    "sg:province":"Madrid",
    "wof:name":"Air Rail S.l.",
    "wof:placetype":"venue"
},
  "geometry": {"coordinates":[-3.8015429974,40.4643554688],"type":"Point"}
}