{
  "type": "Feature",
  "properties": {
    "addr:full":"Calle de Antonio Lopez Aguado, 20 Madrid Madrid 28029",
    "addr:housenumber":"20",
    "addr:postcode":"madrid;28029",
    "addr:street":"Calle De Antonio Lopez Aguado",
    "iso:country":"ES",
    "sg:address":"Calle de Antonio Lopez Aguado, 20",
    "sg:city":"Madrid",
    "sg:orig_category":"Peluquer\u00cdas, Peluquer\u00cda Mixta",
    "sg:phone":"+34 913 15 92 91",
    "sg:postcode":"28029",
    "sg:province":"Madrid",
    "wof:name":"Isabel Yuste S.l.",
    "wof:placetype":"venue"
},
  "geometry": {"coordinates":[-3.7021634579,40.4820137024],"type":"Point"}
}