{
  "type": "Feature",
  "properties": {
    "addr:full":"Garagartza Auzoa, 51 Garagartza Guip\u00f9zcoa 20509",
    "addr:housenumber":"51",
    "addr:postcode":"20509",
    "addr:street":"Garagartza Auzoa;Guipu\u0300Zcoa",
    "iso:country":"ES",
    "sg:address":"Garagartza Auzoa, 51",
    "sg:city":"Garagartza",
    "sg:orig_category":"Marketing Directo",
    "sg:phone":"+34 943 79 22 38",
    "sg:postcode":"20509",
    "sg:province":"Guip\u00f9zcoa",
    "wof:name":"Aizko S. A.",
    "wof:placetype":"venue"
},
  "geometry": {"coordinates":[-2.520637989,43.0691261292],"type":"Point"}
}