{
  "type": "Feature",
  "properties": {
    "iso:country":"ES",
    "sg:address":"Calle de Nu\u00d1o Rasura, 9",
    "sg:city":"Burgos",
    "sg:orig_category":"Panader\u00cdas, Panader\u00cdas",
    "sg:phone":"+34 947 20 55 52",
    "sg:postcode":"09003",
    "sg:province":"Burgos",
    "wof:name":"Confiteria Iba\u00f1ez S.l.",
    "wof:placetype":"venue"
},
  "geometry": {"coordinates":[-3.7048749924,42.3397026062],"type":"Point"}
}