{
  "type": "Feature",
  "properties": {
    "addr:full":"Calle de Capitan Esponera, 7 Zaragoza Zaragoza 50004",
    "addr:housenumber":"7",
    "addr:postcode":"50004",
    "addr:street":"Calle De Capitan Esponera",
    "iso:country":"ES",
    "sg:address":"Calle de Capitan Esponera, 7",
    "sg:city":"Zaragoza",
    "sg:orig_category":"Mec\u00c1nico Del Autom\u00d3vil",
    "sg:phone":"+34 976 23 43 35",
    "sg:postcode":"50004",
    "sg:province":"Zaragoza",
    "wof:name":"Esponera Motor S.l.l.",
    "wof:placetype":"venue"
},
  "geometry": {"coordinates":[-0.8897429705,41.6495246887],"type":"Point"}
}