{
  "type": "Feature",
  "properties": {
    "iso:country":"ES",
    "sg:address":"Calle de Claveles (los), S/n",
    "sg:city":"Buenavista Norte",
    "sg:orig_category":"Ense\u00d1anza, Formaci\u00d3n Profesional: Aprendizaje",
    "sg:phone":"+34 922 12 72 36",
    "sg:postcode":"38480",
    "sg:province":"Santa Cruz De Tenerife",
    "wof:name":"Cruz Roja Espa\u00f1ola",
    "wof:placetype":"venue"
},
  "geometry": {"coordinates":[-16.8493480682,28.370639801],"type":"Point"}
}