{
  "type": "Feature",
  "properties": {
    "addr:full":"Calle de Cubo, 3 Vitoria-gasteiz \u00c1lava 01001",
    "addr:housenumber":"3",
    "addr:postcode":"01001",
    "addr:street":"Calle De Cubo",
    "iso:country":"ES",
    "sg:address":"Calle de Cubo, 3",
    "sg:city":"Vitoria-gasteiz",
    "sg:orig_category":"Peluquer\u00cdas, Peluquer\u00cda Mixta",
    "sg:phone":"+34 945 13 64 10",
    "sg:postcode":"01001",
    "sg:province":"\u00c1lava",
    "wof:name":"Alonso Lopez De Gamiz Inmaculada",
    "wof:placetype":"venue"
},
  "geometry": {"coordinates":[-2.6714394093,42.8520965576],"type":"Point"}
}