{
  "type": "Feature",
  "properties": {
    "iso:country":"ES",
    "sg:address":"Calle de Gonzalo Sanchez Fuentes, 5",
    "sg:city":"Conil De La Frontera",
    "sg:orig_category":"Alquiler De V\u00cddeo",
    "sg:phone":"+34 956 44 18 61",
    "sg:postcode":"11140",
    "sg:province":"C\u00e1diz",
    "wof:name":"Arroyo Gestora S. A.",
    "wof:placetype":"venue"
},
  "geometry": {"coordinates":[-6.0785102844,36.3146133423],"type":"Point"}
}