{
  "type": "Feature",
  "properties": {
    "iso:country":"ES",
    "sg:address":"Avda Federico Garcia Lorca, 104",
    "sg:city":"Almeria",
    "sg:orig_category":"Asociaciones, Instituciones De Consumidores Y Usuarios",
    "sg:phone":"+34 950 26 93 50",
    "sg:postcode":"04005",
    "sg:province":"Almer\u00eda",
    "wof:name":"Federacion De Asociaciones De Consumidores Y Usuarios Andalucia",
    "wof:placetype":"venue"
},
  "geometry": {"coordinates":[-2.4579789639,36.8413047791],"type":"Point"}
}