{
  "type": "Feature",
  "properties": {
    "addr:full":"Carrer de Comte D'urgell, 228 Barcelona Barcelona 08036",
    "addr:housenumber":"228",
    "addr:postcode":"08036",
    "addr:street":"Carrer De Comte D'Urgell",
    "iso:country":"ES",
    "sg:address":"Carrer de Comte D'urgell, 228",
    "sg:city":"Barcelona",
    "sg:orig_category":"Agencias Y Agentes Comerciales, Representantes",
    "sg:phone":"+34 934 10 58 06",
    "sg:postcode":"08036",
    "sg:province":"Barcelona",
    "wof:name":"Casassayas Ricart Merce",
    "wof:placetype":"venue"
},
  "geometry": {"coordinates":[2.1491444111,41.3892555237],"type":"Point"}
}