{
  "type": "Feature",
  "properties": {
    "iso:country":"ES",
    "sg:address":"Cra. Olot, 14",
    "sg:city":"S. Feliu Pallerols",
    "sg:orig_category":"Triper\u00cdas",
    "sg:phone":"+34 972 44 43 26",
    "sg:postcode":"17174",
    "sg:province":"Girona",
    "wof:name":"Comercial De Subproductos S. A.",
    "wof:placetype":"venue"
},
  "geometry": {"coordinates":[2.5088319778,42.07862854],"type":"Point"}
}