{
  "type": "Feature",
  "properties": {
    "addr:full":"Avgd Escultor E. Galarza, 52 Picassent Valencia 46220",
    "addr:housenumber":"52",
    "addr:postcode":"46220",
    "addr:street":"Escultor;Galarza",
    "iso:country":"ES",
    "sg:address":"Avgd Escultor E. Galarza, 52",
    "sg:city":"Picassent",
    "sg:orig_category":"Supermercados Y Hipermercados",
    "sg:phone":"+34 961 23 12 01",
    "sg:postcode":"46220",
    "sg:province":"Valencia",
    "wof:name":"Fernandez Morcillo Miguel",
    "wof:placetype":"venue"
},
  "geometry": {"coordinates":[-0.4658600092,39.3581428528],"type":"Point"}
}