{
  "type": "Feature",
  "properties": {
    "iso:country":"ES",
    "sg:address":"Carrer de Santa Amelia, 27",
    "sg:city":"Barcelona",
    "sg:classifiers":[
        {
            "category":"Personal",
            "subcategory":"Barber",
            "type":"Services"
        }
    ],
    "sg:phone":"+34 932 05 66 16",
    "sg:postcode":"08034",
    "sg:province":"Barcelona",
    "sg:tags":[
        "caballeros",
        "de",
        "peluqueros"
    ],
    "wof:name":"Moreno Aguado Francisco",
    "wof:placetype":"venue"
},
  "geometry": {"coordinates":[2.1225299835,41.393497467],"type":"Point"}
}