{
  "type": "Feature",
  "properties": {
    "iso:country":"ES",
    "sg:address":"Carrer de Sant Quinti, 20",
    "sg:city":"Barcelona",
    "sg:orig_category":"Farmacias",
    "sg:phone":"+34 934 36 51 00",
    "sg:postcode":"08026",
    "sg:province":"Barcelona",
    "wof:name":"Villanueva Villalba Maria Pilar",
    "wof:placetype":"venue"
},
  "geometry": {"coordinates":[2.1793620586,41.4126930237],"type":"Point"}
}