{
  "type": "Feature",
  "properties": {
    "addr:full":"Calle de Herrero, 44 Castellon Castell\u00f3n 12005",
    "addr:housenumber":"44",
    "addr:postcode":"12005",
    "addr:street":"Calle De Herrero",
    "iso:country":"ES",
    "sg:address":"Calle de Herrero, 44",
    "sg:city":"Castellon",
    "sg:orig_category":"Agua",
    "sg:phone":"+34 964 03 76 03",
    "sg:postcode":"12005",
    "sg:province":"Castell\u00f3n",
    "wof:name":"Ingascal Cooperativa Valenciana Limitada",
    "wof:placetype":"venue"
},
  "geometry": {"coordinates":[-0.0407470018,39.980014801],"type":"Point"}
}