{
  "type": "Feature",
  "properties": {
    "addr:full":"Calle de Moreras, 2 Majadahonda Madrid 28220",
    "addr:housenumber":"2",
    "addr:postcode":"28220",
    "addr:street":"Calle De Moreras",
    "iso:country":"ES",
    "sg:address":"Calle de Moreras, 2",
    "sg:city":"Majadahonda",
    "sg:orig_category":"Ropa Para Caballeros (al Por Menor)",
    "sg:phone":"+34 916 38 54 04",
    "sg:postcode":"28220",
    "sg:province":"Madrid",
    "sg:website":"www.spf.com",
    "wof:name":"Cortefiel S.a.",
    "wof:placetype":"venue"
},
  "geometry": {"coordinates":[-3.8684110641,40.4532165527],"type":"Point"}
}