{
  "type": "Feature",
  "properties": {
    "iso:country":"ES",
    "sg:address":"Carrer de Marie Curie, 15",
    "sg:city":"Barbera Valles",
    "sg:orig_category":"Electrodom\u00c9sticos (al Por Menor)",
    "sg:phone":"+34 937 29 19 73",
    "sg:postcode":"08210",
    "sg:province":"Barcelona",
    "wof:name":"Media Markt Barcelona Video Tv Hifi Elek",
    "wof:placetype":"venue"
},
  "geometry": {"coordinates":[2.1305921078,41.5122413635],"type":"Point"}
}