{
  "type": "Feature",
  "properties": {
    "iso:country":"ES",
    "sg:address":"Trva Lominchar, 3",
    "sg:city":"Recas",
    "sg:orig_category":"Escayola Y Productos De Escayola (fabricaci\u00d3n, Al Por Mayor)",
    "sg:phone":"+34 925 52 22 09",
    "sg:postcode":"45211",
    "sg:province":"Toledo",
    "wof:name":"Zurita Del Cerro Gabriel",
    "wof:placetype":"venue"
},
  "geometry": {"coordinates":[-3.9915804863,40.056728363],"type":"Point"}
}