{
  "type": "Feature",
  "properties": {
    "iso:country":"ES",
    "sg:address":"E. Martin, 7",
    "sg:city":"Campillos",
    "sg:orig_category":"Promotores Constructores",
    "sg:phone":"+34 952 72 40 79",
    "sg:postcode":"29320",
    "sg:province":"M\u00e1laga",
    "wof:name":"Construcciones Ersaga Campillo S.l.",
    "wof:placetype":"venue"
},
  "geometry": {"coordinates":[-4.8634610176,37.0531158447],"type":"Point"}
}