{
  "type": "Feature",
  "properties": {
    "iso:country":"ES",
    "sg:address":"Avda Quel, 42",
    "sg:city":"Arnedo",
    "sg:orig_category":"Confecci\u00d3n De Zapatos",
    "sg:phone":"+34 941 38 33 66",
    "sg:postcode":"26580",
    "sg:province":"La Rioja",
    "wof:name":"Calzados Elba S. L.",
    "wof:placetype":"venue"
},
  "geometry": {"coordinates":[-2.0872631073,42.2298583984],"type":"Point"}
}