{
  "type": "Feature",
  "properties": {
    "iso:country":"ES",
    "sg:address":"C/ Fira, 2",
    "sg:city":"Elche",
    "sg:orig_category":"Centros P\u00dablicos De Formaci\u00d3n Profesional Y T\u00c9cnica",
    "sg:phone":"+34 966 61 52 34",
    "sg:postcode":"03203",
    "sg:province":"Alicante",
    "wof:name":"Colegio Oficial De Aparejadores Y Arquitectos Tecnicos De Alicante",
    "wof:placetype":"venue"
},
  "geometry": {"coordinates":[-0.698481977,38.2668991089],"type":"Point"}
}