{
  "type": "Feature",
  "properties": {
    "iso:country":"ES",
    "sg:address":"Calle de Pintor Racionero Castro, 2",
    "sg:city":"Cordoba",
    "sg:orig_category":"Vestidos De Se\u00d1ora (tallas Grandes)",
    "sg:phone":"+34 957 40 52 67",
    "sg:postcode":"14006",
    "sg:province":"C\u00f3rdoba",
    "wof:name":"Cebrian Castro Francisca",
    "wof:placetype":"venue"
},
  "geometry": {"coordinates":[-4.7770290375,37.8953552246],"type":"Point"}
}