{
  "type": "Feature",
  "properties": {
    "iso:country":"ES",
    "sg:address":"Calle de Dacil Vilar Borges, 3",
    "sg:city":"Santa Cruz De Tenerife",
    "sg:orig_category":"Asociaciones Humanitarias, De Cooperaci\u00d3n, De Acci\u00d3n Social",
    "sg:phone":"+34 922 64 50 72",
    "sg:postcode":"38010",
    "sg:province":"Santa Cruz De Tenerife",
    "wof:name":"Centro De La Tercera Edad Principes De Espa\u00f1a",
    "wof:placetype":"venue"
},
  "geometry": {"coordinates":[-16.2848300934,28.4553318024],"type":"Point"}
}