{
  "type": "Feature",
  "properties": {
    "iso:country":"ES",
    "sg:address":"Pl Pau Casals, 2",
    "sg:city":"Reus",
    "sg:orig_category":"Panader\u00cdas, Panader\u00cdas",
    "sg:phone":"+34 977 34 38 50",
    "sg:postcode":"43203",
    "sg:province":"Tarragona",
    "wof:name":"Nu\u00f1ez Rodriguez Cristobal",
    "wof:placetype":"venue"
},
  "geometry": {"coordinates":[1.107929945,41.1519889832],"type":"Point"}
}