{
  "type": "Feature",
  "properties": {
    "addr:full":"Calle de Riego De Agua, 7 Coru\u00d1a La Coru\u00f1a 15001",
    "addr:housenumber":"7",
    "addr:postcode":"15001",
    "addr:street":"Calle De Riego De Agua;La Corun\u0303A",
    "iso:country":"ES",
    "sg:address":"Calle de Riego De Agua, 7",
    "sg:city":"Coru\u00d1a",
    "sg:orig_category":"Centros De Coordinaci\u00d3n",
    "sg:phone":"+34 981 22 88 71",
    "sg:postcode":"15001",
    "sg:province":"La Coru\u00f1a",
    "wof:name":"Iglesias Dupla Asociados S.c.",
    "wof:placetype":"venue"
},
  "geometry": {"coordinates":[-8.3972043991,43.370426178],"type":"Point"}
}