{
  "type": "Feature",
  "properties": {
    "iso:country":"ES",
    "sg:address":"Calle de Zamacola, 51",
    "sg:city":"Bilbao",
    "sg:orig_category":"Panader\u00cdas, Panader\u00cdas",
    "sg:phone":"+34 944 15 12 87",
    "sg:postcode":"48003",
    "sg:province":"Vizcaya",
    "wof:name":"Nieto Iglesias Teresa",
    "wof:placetype":"venue"
},
  "geometry": {"coordinates":[-2.9249489307,43.2420921326],"type":"Point"}
}