{
  "type": "Feature",
  "properties": {
    "addr:full":"Calle de Chile, 21 Alcala Henares Madrid 28806",
    "addr:housenumber":"21",
    "addr:postcode":"28806",
    "addr:street":"Calle De Chile",
    "iso:country":"ES",
    "sg:address":"Calle de Chile, 21",
    "sg:city":"Alcala Henares",
    "sg:orig_category":"Chapister\u00cda",
    "sg:phone":"+34 918 89 56 89",
    "sg:postcode":"28806",
    "sg:province":"Madrid",
    "wof:name":"Fercoa S.a.",
    "wof:placetype":"venue"
},
  "geometry": {"coordinates":[-3.3958103657,40.5059394836],"type":"Point"}
}