{
  "type": "Feature",
  "properties": {
    "addr:full":"Ifar Kale, 4 Eibar Guip\u00f9zcoa 20600",
    "addr:housenumber":"4",
    "addr:postcode":"20600",
    "addr:street":"Kale;Guipu\u0300Zcoa",
    "iso:country":"ES",
    "sg:address":"Ifar Kale, 4",
    "sg:city":"Eibar",
    "sg:orig_category":"Tapicer\u00cdas",
    "sg:phone":"+34 943 20 82 78",
    "sg:postcode":"20600",
    "sg:province":"Guip\u00f9zcoa",
    "wof:name":"Juan Esteban Bolumburu Aguinaga",
    "wof:placetype":"venue"
},
  "geometry": {"coordinates":[-2.4884390831,43.1800117493],"type":"Point"}
}