{
  "type": "Feature",
  "properties": {
    "addr:full":"Calle de Mota Del Cuervo, 8 Madrid Madrid 28043",
    "addr:housenumber":"8",
    "addr:postcode":"madrid;28043",
    "addr:street":"Calle De Mota Del Cuervo",
    "iso:country":"ES",
    "sg:address":"Calle de Mota Del Cuervo, 8",
    "sg:city":"Madrid",
    "sg:orig_category":"Tapiceros Y Tapiceros",
    "sg:phone":"+34 913 00 09 29",
    "sg:postcode":"28043",
    "sg:province":"Madrid",
    "wof:name":"Aplicaciones De Pinturas Azofer S.l.",
    "wof:placetype":"venue"
},
  "geometry": {"coordinates":[-3.6347846985,40.464717865],"type":"Point"}
}