{
  "type": "Feature",
  "properties": {
    "addr:full":"Calle de Escritor Antonio Navarro Trujillo, 15 Malaga M\u00e1laga 29190",
    "addr:housenumber":"15",
    "addr:postcode":"29190",
    "addr:street":"Calle De Escritor Antonio Navarro Trujillo;Ma\u0301Laga",
    "iso:country":"ES",
    "sg:address":"Calle de Escritor Antonio Navarro Trujillo, 15",
    "sg:city":"Malaga",
    "sg:orig_category":"T\u00c9cnicos Veterinarios",
    "sg:phone":"+34 952 43 11 27",
    "sg:postcode":"29190",
    "sg:province":"M\u00e1laga",
    "wof:name":"Rodriguez Garcia Inmaculada",
    "wof:placetype":"venue"
},
  "geometry": {"coordinates":[-4.4787349701,36.739982605],"type":"Point"}
}