{
  "type": "Feature",
  "properties": {
    "addr:full":"Calle de Jaen, S/n Rincon Victoria M\u00e1laga 29730",
    "addr:housenumber":"s / n",
    "addr:postcode":"29730",
    "addr:street":"Calle De Jaen;Ma\u0301Laga",
    "iso:country":"ES",
    "sg:address":"Calle de Jaen, S/n",
    "sg:city":"Rincon Victoria",
    "sg:orig_category":"Mec\u00c1nico Del Autom\u00d3vil",
    "sg:phone":"+34 952 40 82 73",
    "sg:postcode":"29730",
    "sg:province":"M\u00e1laga",
    "wof:name":"Autorapid Motor S.l.l.",
    "wof:placetype":"venue"
},
  "geometry": {"coordinates":[-4.2843642235,36.7152633667],"type":"Point"}
}