{
  "type": "Feature",
  "properties": {
    "addr:full":"Calle de Garcia Vali\u00d1o, 4 Cantavieja Teruel 44140",
    "addr:housenumber":"4",
    "addr:postcode":"44140",
    "addr:street":"Calle De Garcia Valin\u0303O",
    "iso:country":"ES",
    "sg:address":"Calle de Garcia Vali\u00d1o, 4",
    "sg:city":"Cantavieja",
    "sg:orig_category":"Farmacias",
    "sg:phone":"+34 964 18 50 25",
    "sg:postcode":"44140",
    "sg:province":"Teruel",
    "wof:name":"Escorihuela Mestre Maria",
    "wof:placetype":"venue"
},
  "geometry": {"coordinates":[-0.4052900076,40.5262756348],"type":"Point"}
}