{
  "type": "Feature",
  "properties": {
    "iso:country":"ES",
    "sg:address":"Calle de Isaac Peral, 6",
    "sg:city":"Avila",
    "sg:orig_category":"Promotores Constructores",
    "sg:phone":"+34 920 25 16 21",
    "sg:postcode":"05001",
    "sg:province":"\u00c1vila",
    "wof:name":"Aldaja S.a.",
    "wof:placetype":"venue"
},
  "geometry": {"coordinates":[-4.6916637421,40.6557846069],"type":"Point"}
}