{
  "type": "Feature",
  "properties": {
    "addr:full":"Plaza Alfonso Xiii, S/n Fuentes De Ropel Zamora 49670",
    "addr:housenumber":"s / n",
    "addr:postcode":"49670",
    "addr:street":"Alfonso Xiii;Zamora",
    "iso:country":"ES",
    "sg:address":"Plaza Alfonso Xiii, S/n",
    "sg:city":"Fuentes De Ropel",
    "sg:orig_category":"Carnicer\u00cdas, Carnicer\u00cdas",
    "sg:phone":"+34 980 66 30 37",
    "sg:postcode":"49670",
    "sg:province":"Zamora",
    "wof:name":"Chonata Bastida Angelina",
    "wof:placetype":"venue"
},
  "geometry": {"coordinates":[-5.545003891,42.0030097961],"type":"Point"}
}