{
  "type": "Feature",
  "properties": {
    "addr:full":"Alam Menchiron (de), S/n San Mateo Murcia 30800",
    "addr:housenumber":"s / n",
    "addr:postcode":"30800",
    "iso:country":"ES",
    "sg:address":"Alam Menchiron (de), S/n",
    "sg:city":"San Mateo",
    "sg:orig_category":"Transportes Por V\u00cdas Navegables",
    "sg:phone":"+34 968 46 92 70",
    "sg:postcode":"30800",
    "sg:province":"Murcia",
    "wof:name":"Trapemusa S. A.",
    "wof:placetype":"venue"
},
  "geometry": {"coordinates":[-1.6905640364,37.680557251],"type":"Point"}
}