{
  "type": "Feature",
  "properties": {
    "addr:full":"Carrer de Balmes, 447 Barcelona Barcelona 08022",
    "addr:housenumber":"447",
    "addr:postcode":"08022",
    "addr:street":"Carrer De Balmes",
    "iso:country":"ES",
    "sg:address":"Carrer de Balmes, 447",
    "sg:city":"Barcelona",
    "sg:orig_category":"Ropa De Hogar (al Por Menor)",
    "sg:phone":"+34 932 12 28 08",
    "sg:postcode":"08022",
    "sg:province":"Barcelona",
    "sg:website":"www.textura-interiors.com",
    "wof:name":"Textil Textura S.l.",
    "wof:placetype":"venue"
},
  "geometry": {"coordinates":[2.1365859509,41.4099082947],"type":"Point"}
}