{
  "type": "Feature",
  "properties": {
    "iso:country":"ES",
    "sg:address":"Calle de Mamerto Alique, 10",
    "sg:city":"Huete",
    "sg:orig_category":"Farmacias",
    "sg:phone":"+34 969 37 13 32",
    "sg:postcode":"16500",
    "sg:province":"Cuenca",
    "wof:name":"Carrasco Onate Juan Pablo",
    "wof:placetype":"venue"
},
  "geometry": {"coordinates":[-2.6891160011,40.1446876526],"type":"Point"}
}