{
  "type": "Feature",
  "properties": {
    "iso:country":"ES",
    "sg:address":"Calle de Elbarren, 94",
    "sg:city":"Leitza",
    "sg:orig_category":"Carnicer\u00cdas, Carnicer\u00cdas",
    "sg:phone":"+34 948 51 04 67",
    "sg:postcode":"31880",
    "sg:province":"Navarra",
    "wof:name":"Jose Antonio Urquiola Cestau Y Otro S.i.",
    "wof:placetype":"venue"
},
  "geometry": {"coordinates":[-1.9140490294,43.0798912048],"type":"Point"}
}