{
  "type": "Feature",
  "properties": {
    "iso:country":"ES",
    "sg:address":"Calle de Santa Joaquina, 15",
    "sg:city":"Villafranca De Los Barros",
    "sg:orig_category":"Telas Y Sedas (al Por Menor)",
    "sg:phone":"+34 924 52 44 53",
    "sg:postcode":"06220",
    "sg:province":"Badajoz",
    "wof:name":"Negro Calleja Serafin",
    "wof:placetype":"venue"
},
  "geometry": {"coordinates":[-6.3438782692,38.5860748291],"type":"Point"}
}