{
  "type": "Feature",
  "properties": {
    "addr:full":"Calle de Orixe, 50 Bilbao Vizcaya 48015",
    "addr:housenumber":"50",
    "addr:postcode":"48015",
    "addr:street":"Calle De Orixe",
    "iso:country":"ES",
    "sg:address":"Calle de Orixe, 50",
    "sg:city":"Bilbao",
    "sg:orig_category":"Promotores Constructores",
    "sg:phone":"+34 944 75 28 47",
    "sg:postcode":"48015",
    "sg:province":"Vizcaya",
    "wof:name":"Murcanor, S.l.",
    "wof:placetype":"venue"
},
  "geometry": {"coordinates":[-2.9605050087,43.2830543518],"type":"Point"}
}