{
  "type": "Feature",
  "properties": {
    "iso:country":"ES",
    "sg:address":"Av Jaume Iii, 1",
    "sg:city":"Palma",
    "sg:orig_category":"Ropa Para Se\u00d1oras Y Caballeros (al Por Menor)",
    "sg:phone":"+34 971 71 52 75",
    "sg:postcode":"07012",
    "sg:province":"Islas Baleares",
    "sg:website":"www.loewe.com",
    "wof:name":"Loewe Hermanos S.a.c.",
    "wof:placetype":"venue"
},
  "geometry": {"coordinates":[2.6465981007,39.5714530945],"type":"Point"}
}