{
  "type": "Feature",
  "properties": {
    "addr:full":"Carrer de Ferran Puig, 13 Barcelona Barcelona 08023",
    "addr:housenumber":"13",
    "addr:postcode":"08023",
    "addr:street":"Carrer De Ferran Puig",
    "iso:country":"ES",
    "sg:address":"Carrer de Ferran Puig, 13",
    "sg:city":"Barcelona",
    "sg:orig_category":"Agencias Y Asesores De Publicidad",
    "sg:phone":"+34 932 53 08 58",
    "sg:postcode":"08023",
    "sg:province":"Barcelona",
    "sg:website":"www.procomunicacio.com",
    "wof:name":"Pro Comunicacion Integral 97 S.l.",
    "wof:placetype":"venue"
},
  "geometry": {"coordinates":[2.1459081173,41.4080734253],"type":"Point"}
}