{
  "type": "Feature",
  "properties": {
    "iso:country":"ES",
    "sg:address":"Avda Reina Victoria, 46",
    "sg:city":"Madrid",
    "sg:orig_category":"Panader\u00cdas, Panader\u00cdas",
    "sg:phone":"+34 915 33 58 83",
    "sg:postcode":"28003",
    "sg:province":"Madrid",
    "wof:name":"Rincon Yague Jose",
    "wof:placetype":"venue"
},
  "geometry": {"coordinates":[-3.7115130424,40.4468193054],"type":"Point"}
}