{
  "type": "Feature",
  "properties": {
    "iso:country":"ES",
    "sg:address":"V Bartolome Milla, S/n",
    "sg:city":"Cubo Sierra",
    "sg:classifiers":[
        {
            "category":"Real Estate",
            "subcategory":"Surveying",
            "type":"Services"
        }
    ],
    "sg:phone":"+34 975 25 22 69",
    "sg:postcode":"42167",
    "sg:province":"Soria",
    "sg:tags":[
        "de",
        "para",
        "la",
        "material",
        "bebidas",
        "y",
        "m\u00c1quinas",
        "industria"
    ],
    "wof:name":"Vendis Vending Distribuidor S.l",
    "wof:placetype":"venue"
},
  "geometry": {"coordinates":[-2.4160749912,41.9245491028],"type":"Point"}
}