{
  "type": "Feature",
  "properties": {
    "addr:full":"Carr Creueta, 33 Igualada Barcelona 08700",
    "addr:housenumber":"33",
    "addr:postcode":"08700",
    "addr:street":"Carr Creueta",
    "iso:country":"ES",
    "sg:address":"Carr Creueta, 33",
    "sg:city":"Igualada",
    "sg:orig_category":"Sonorizaci\u00d3n, Iluminaci\u00d3n Para Cine, Teatro Y Discotecas (al Por Mayor, Al Por Menor)",
    "sg:phone":"+34 938 04 72 53",
    "sg:postcode":"08700",
    "sg:province":"Barcelona",
    "sg:website":"www.jart.biz",
    "wof:name":"Rotes Santesmasses Jordi",
    "wof:placetype":"venue"
},
  "geometry": {"coordinates":[1.6104860306,41.5778884888],"type":"Point"}
}