{
  "type": "Feature",
  "properties": {
    "iso:country":"ES",
    "sg:address":"Avda Cantabria, 41",
    "sg:city":"Burgos",
    "sg:orig_category":"Asociaciones, Organismos Culturales Y Socioeducativos",
    "sg:phone":"+34 947 21 01 35",
    "sg:postcode":"09006",
    "sg:province":"Burgos",
    "sg:website":"www.cajaburgos.es",
    "wof:name":"Caja De Ahorros Municipal De Burgos",
    "wof:placetype":"venue"
},
  "geometry": {"coordinates":[-3.6892108917,42.349521637],"type":"Point"}
}