{
  "type": "Feature",
  "properties": {
    "addr:full":"Calle de Belen, 32 Tamaraceite Las Palmas 35018",
    "addr:housenumber":"32",
    "addr:postcode":"35018",
    "addr:street":"Calle De Belen;Palmas",
    "iso:country":"ES",
    "sg:address":"Calle de Belen, 32",
    "sg:city":"Tamaraceite",
    "sg:orig_category":"Agencias Y Agentes Comerciales, Representantes",
    "sg:phone":"+34 928 66 75 92",
    "sg:postcode":"35018",
    "sg:province":"Las Palmas",
    "wof:name":"Perez Garcia Asuncion",
    "wof:placetype":"venue"
},
  "geometry": {"coordinates":[-15.4727840424,28.0983428955],"type":"Point"}
}