{
  "type": "Feature",
  "properties": {
    "iso:country":"ES",
    "sg:address":"Calle de Rambla, 9",
    "sg:city":"Malaga",
    "sg:orig_category":"Mec\u00c1nico Del Autom\u00d3vil",
    "sg:phone":"+34 952 34 28 88",
    "sg:postcode":"29006",
    "sg:province":"M\u00e1laga",
    "wof:name":"Taller Los Cu\u00f1ados S.c.",
    "wof:placetype":"venue"
},
  "geometry": {"coordinates":[-4.4376392365,36.7139091492],"type":"Point"}
}