{
  "type": "Feature",
  "properties": {
    "addr:full":"Avda Maria Zambrano, S/n Getafe Madrid 28903",
    "addr:housenumber":"s / n",
    "addr:postcode":"28903",
    "addr:street":"Avda Maria Zambrano",
    "iso:country":"ES",
    "sg:address":"Avda Maria Zambrano, S/n",
    "sg:city":"Getafe",
    "sg:orig_category":"Cajas De Ahorro",
    "sg:phone":"+34 916 65 12 24",
    "sg:postcode":"28903",
    "sg:province":"Madrid",
    "sg:website":"www.caixacatalunya.es",
    "wof:name":"Caixa D'estalvis De Catalunya",
    "wof:placetype":"venue"
},
  "geometry": {"coordinates":[-3.7218739986,40.3256263733],"type":"Point"}
}