{
  "type": "Feature",
  "properties": {
    "addr:full":"Carrer de Capita Arenas, 28 Barcelona Barcelona 08034",
    "addr:housenumber":"28",
    "addr:postcode":"08034",
    "addr:street":"Carrer De Capita Arenas",
    "iso:country":"ES",
    "sg:address":"Carrer de Capita Arenas, 28",
    "sg:city":"Barcelona",
    "sg:orig_category":"M\u00c9dicos: Estomatolog\u00cda",
    "sg:phone":"+34 932 80 33 46",
    "sg:postcode":"08034",
    "sg:province":"Barcelona",
    "wof:name":"Brion  Jorge Hernan",
    "wof:placetype":"venue"
},
  "geometry": {"coordinates":[2.1259529591,41.3910140991],"type":"Point"}
}