{
  "type": "Feature",
  "properties": {
    "iso:country":"ES",
    "sg:address":"Carrer de Tomas Edison, 21",
    "sg:city":"Ondara",
    "sg:orig_category":"Transporte En General",
    "sg:phone":"+34 966 47 66 51",
    "sg:postcode":"03760",
    "sg:province":"Alicante",
    "wof:name":"Alfonso Perello Sl",
    "wof:placetype":"venue"
},
  "geometry": {"coordinates":[0.0213385001,38.8205490112],"type":"Point"}
}