{
  "type": "Feature",
  "properties": {
    "iso:country":"ES",
    "sg:address":"Avda Emilio Romero (de), 27",
    "sg:city":"Arevalo",
    "sg:orig_category":"Herboristas (al Por Menor)",
    "sg:phone":"+34 920 30 20 31",
    "sg:postcode":"05200",
    "sg:province":"\u00c1vila",
    "wof:name":"Garcia Mu\u00f1oz Virginia",
    "wof:placetype":"venue"
},
  "geometry": {"coordinates":[-4.7158231735,41.0568313599],"type":"Point"}
}