{
  "type": "Feature",
  "properties": {
    "addr:full":"Curros Enriquez(o Graxal), 17 O Temple La Coru\u00f1a 15679",
    "addr:housenumber":"17 o",
    "addr:postcode":"15679",
    "addr:street":"Curros Enriquez O Graxal;La Corun\u0303A",
    "iso:country":"ES",
    "sg:address":"Curros Enriquez(o Graxal), 17",
    "sg:city":"O Temple",
    "sg:orig_category":"Veh\u00cdculos De Ocasi\u00d3n",
    "sg:phone":"+34 981 66 47 00",
    "sg:postcode":"15679",
    "sg:province":"La Coru\u00f1a",
    "wof:name":"Sanchez Movil S.a.",
    "wof:placetype":"venue"
},
  "geometry": {"coordinates":[-8.3685693741,43.3172721863],"type":"Point"}
}