{
  "type": "Feature",
  "properties": {
    "addr:full":"Av Madrid, 10 Crevillent Alicante 03330",
    "addr:housenumber":"10",
    "addr:postcode":"03330",
    "addr:street":"Av Madrid",
    "iso:country":"ES",
    "sg:address":"Av Madrid, 10",
    "sg:city":"Crevillent",
    "sg:orig_category":"Agentes Generales De Seguros",
    "sg:phone":"+34 965 40 58 88",
    "sg:postcode":"03330",
    "sg:province":"Alicante",
    "wof:name":"Manchon Jimenez Pilar",
    "wof:placetype":"venue"
},
  "geometry": {"coordinates":[-0.8092560172,38.2466506958],"type":"Point"}
}