{
  "type": "Feature",
  "properties": {
    "iso:country":"ES",
    "sg:address":"Carr Llibertat, 48",
    "sg:city":"Vilanova I La Geltru",
    "sg:orig_category":"Asesor\u00cda Fiscal Y Jur\u00cddica",
    "sg:phone":"+34 938 10 61 29",
    "sg:postcode":"08800",
    "sg:province":"Barcelona",
    "wof:name":"Solfico S.l.",
    "wof:placetype":"venue"
},
  "geometry": {"coordinates":[1.7280730009,41.2205314636],"type":"Point"}
}