{
  "type": "Feature",
  "properties": {
    "iso:country":"ES",
    "sg:address":"Calle de Cisneros, 33",
    "sg:city":"Alcorcon",
    "sg:orig_category":"Asesor\u00cda Fiscal Y Jur\u00cddica",
    "sg:phone":"+34 914 86 00 86",
    "sg:postcode":"28922",
    "sg:province":"Madrid",
    "wof:name":"Asesolida S.l.",
    "wof:placetype":"venue"
},
  "geometry": {"coordinates":[-3.8314700127,40.345664978],"type":"Point"}
}