{
  "type": "Feature",
  "properties": {
    "iso:country":"ES",
    "sg:address":"Plaz Espa\u00d1a, 1",
    "sg:city":"Escurial",
    "sg:orig_category":"Administraciones Regionales, Departamentales Y Locales",
    "sg:phone":"+34 927 34 80 52",
    "sg:postcode":"10133",
    "sg:province":"C\u00e1ceres",
    "wof:name":"Ayuntamiento De Escurial",
    "wof:placetype":"venue"
},
  "geometry": {"coordinates":[-5.9092755318,39.1814231873],"type":"Point"}
}