{
  "type": "Feature",
  "properties": {
    "addr:full":"Carrer de Balmes, 417 Barcelona Barcelona 08022",
    "addr:housenumber":"417",
    "addr:postcode":"08022",
    "addr:street":"Carrer De Balmes",
    "iso:country":"ES",
    "sg:address":"Carrer de Balmes, 417",
    "sg:city":"Barcelona",
    "sg:orig_category":"Abogados",
    "sg:phone":"+34 934 18 84 22",
    "sg:postcode":"08022",
    "sg:province":"Barcelona",
    "wof:name":"Lliset Canelles Ana Isabel",
    "wof:placetype":"venue"
},
  "geometry": {"coordinates":[2.1379439831,41.4077529907],"type":"Point"}
}