{
  "type": "Feature",
  "properties": {
    "iso:country":"ES",
    "sg:address":"Avda Algorta (de), 14",
    "sg:city":"San Fernando De Henares",
    "sg:orig_category":"M\u00c9dicos: Estomatolog\u00cda",
    "sg:phone":"+34 916 71 02 72",
    "sg:postcode":"28830",
    "sg:province":"Madrid",
    "wof:name":"Garcia Capilla Maria Del Pilar",
    "wof:placetype":"venue"
},
  "geometry": {"coordinates":[-3.5270690918,40.4176445007],"type":"Point"}
}