{
  "type": "Feature",
  "properties": {
    "addr:full":"Calle de Mayor, 4 Torres Cotillas Murcia 30565",
    "addr:housenumber":"4",
    "addr:postcode":"30565",
    "addr:street":"Calle De Mayor",
    "iso:country":"ES",
    "sg:address":"Calle de Mayor, 4",
    "sg:city":"Torres Cotillas",
    "sg:orig_category":"Ense\u00d1anza: Profesiones Art\u00cdsticas",
    "sg:phone":"+34 968 62 81 83",
    "sg:postcode":"30565",
    "sg:province":"Murcia",
    "wof:name":"Lopez Hernandez Nieves",
    "wof:placetype":"venue"
},
  "geometry": {"coordinates":[-1.2409342527,38.0294799805],"type":"Point"}
}