{
  "type": "Feature",
  "properties": {
    "iso:country":"ES",
    "sg:address":"Calle de Ca\u00d1adas, 37",
    "sg:city":"Partija-santa Monica",
    "sg:orig_category":"Publicidad (soportes Y Gesti\u00d3n)",
    "sg:phone":"+34 914 99 29 02",
    "sg:postcode":"28529",
    "sg:province":"Madrid",
    "sg:website":"www.serigrafiasalsan.com",
    "wof:name":"Serigrafias Alsan S.l.",
    "wof:placetype":"venue"
},
  "geometry": {"coordinates":[-3.5102670193,40.314289093],"type":"Point"}
}