{
  "type": "Feature",
  "properties": {
    "addr:full":"Calle de Jaime I El Conquistador, 9 San Miguel Murcia 30008",
    "addr:housenumber":"9",
    "addr:postcode":"30008",
    "addr:street":"Calle De Jaime I El Conquistador",
    "iso:country":"ES",
    "sg:address":"Calle de Jaime I El Conquistador, 9",
    "sg:city":"San Miguel",
    "sg:orig_category":"M\u00c9dicos: Ginecolog\u00cda Y Obstetricia",
    "sg:phone":"+34 968 23 04 60",
    "sg:postcode":"30008",
    "sg:province":"Murcia",
    "wof:name":"Ballester Angosto Isidoro",
    "wof:placetype":"venue"
},
  "geometry": {"coordinates":[-1.131559968,37.9894981384],"type":"Point"}
}