{
  "type": "Feature",
  "properties": {
    "iso:country":"ES",
    "sg:address":"Pase Beltzeta, S/n",
    "sg:city":"Cizur Menor",
    "sg:orig_category":"Internados & Ense\u00d1anza Privada",
    "sg:phone":"+34 948 28 01 95",
    "sg:postcode":"31190",
    "sg:province":"Navarra",
    "wof:name":"Fomento De Centros De Ense\u00d1anza",
    "wof:placetype":"venue"
},
  "geometry": {"coordinates":[-1.6754239798,42.7882118225],"type":"Point"}
}