{
  "type": "Feature",
  "properties": {
    "iso:country":"ES",
    "sg:address":"Crt Almansa, S/n",
    "sg:city":"Fuente-alamo",
    "sg:orig_category":"Panader\u00cdas, Pasteler\u00cdas, Boller\u00cda Industriale (fabricaci\u00d3n, Al Por Mayor)",
    "sg:phone":"+34 967 32 13 66",
    "sg:postcode":"02651",
    "sg:province":"Albacete",
    "wof:name":"Ochando Ortu\u00f1o Maria Isabel",
    "wof:placetype":"venue"
},
  "geometry": {"coordinates":[-1.4325129986,38.6947288513],"type":"Point"}
}