{
  "type": "Feature",
  "properties": {
    "addr:full":"Ctra Convent Del, 14 Oliva Valencia 46780",
    "addr:housenumber":"14",
    "addr:postcode":"46780",
    "addr:street":"Ctra Convent Del",
    "iso:country":"ES",
    "sg:address":"Ctra Convent Del, 14",
    "sg:city":"Oliva",
    "sg:orig_category":"Mercer\u00cda, Lencer\u00cda (al Por Menor)",
    "sg:phone":"+34 962 85 01 45",
    "sg:postcode":"46780",
    "sg:province":"Valencia",
    "wof:name":"Soria Sebastia Francisca",
    "wof:placetype":"venue"
},
  "geometry": {"coordinates":[-0.1186380014,38.9208946228],"type":"Point"}
}