{
  "type": "Feature",
  "properties": {
    "addr:full":"Calle de Cardenal Ilundain, 3 Sevilla Sevilla 41013",
    "addr:housenumber":"3",
    "addr:postcode":"41013",
    "addr:street":"Calle De Cardenal Ilundain",
    "iso:country":"ES",
    "sg:address":"Calle de Cardenal Ilundain, 3",
    "sg:city":"Sevilla",
    "sg:orig_category":"Bisuter\u00cda, Joyer\u00cda, Relojer\u00cda (al Por Menor)",
    "sg:phone":"+34 954 61 40 48",
    "sg:postcode":"41013",
    "sg:province":"Sevilla",
    "wof:name":"Sanchez Lopez Amalia",
    "wof:placetype":"venue"
},
  "geometry": {"coordinates":[-5.9822826385,37.3642730713],"type":"Point"}
}