{
  "type": "Feature",
  "properties": {
    "iso:country":"ES",
    "sg:address":"Ctra Portugal (de), 34",
    "sg:city":"Lobios",
    "sg:orig_category":"Ense\u00d1anza, Formaci\u00d3n Profesional: Aprendizaje",
    "sg:phone":"+34 988 44 80 48",
    "sg:postcode":"32870",
    "sg:province":"Ourense",
    "wof:name":"Xunta De Galicia",
    "wof:placetype":"venue"
},
  "geometry": {"coordinates":[-8.0683431625,41.8540878296],"type":"Point"}
}