{
  "type": "Feature",
  "properties": {
    "addr:full":"Avda Taramundi, 7 Vegadeo Asturias 33770",
    "addr:housenumber":"7",
    "addr:postcode":"33770",
    "addr:street":"Avda Taramundi",
    "iso:country":"ES",
    "sg:address":"Avda Taramundi, 7",
    "sg:city":"Vegadeo",
    "sg:orig_category":"Asesor\u00cda De Formaci\u00d3n Y Gesti\u00d3n De Personal",
    "sg:phone":"+34 985 63 46 25",
    "sg:postcode":"33770",
    "sg:province":"Asturias",
    "wof:name":"Antu\u00f1a Asesores Sl",
    "wof:placetype":"venue"
},
  "geometry": {"coordinates":[-7.0500230789,43.4636917114],"type":"Point"}
}