{
  "type": "Feature",
  "properties": {
    "iso:country":"ES",
    "sg:address":"Avda Lugo (de), 39",
    "sg:city":"Monterroso",
    "sg:orig_category":"Molduras, Junquillos, Listones Y Molduras Perforadas",
    "sg:phone":"+34 982 37 72 32",
    "sg:postcode":"27560",
    "sg:province":"Lugo",
    "wof:name":"Teldelugo Comunicacion S.l.",
    "wof:placetype":"venue"
},
  "geometry": {"coordinates":[-7.8332290649,42.7924995422],"type":"Point"}
}