{
  "type": "Feature",
  "properties": {
    "addr:full":"Av Verge Montserrat, 172 Prat Llobregat Barcelona 08820",
    "addr:housenumber":"172",
    "addr:postcode":"08820",
    "addr:street":"Av Verge Montserrat;Llobregat",
    "iso:country":"ES",
    "sg:address":"Av Verge Montserrat, 172",
    "sg:city":"Prat Llobregat",
    "sg:orig_category":"Molduras, Junquillos, Listones Y Molduras Perforadas",
    "sg:phone":"+34 934 78 28 49",
    "sg:postcode":"08820",
    "sg:province":"Barcelona",
    "wof:name":"Segura Perez Indalecio",
    "wof:placetype":"venue"
},
  "geometry": {"coordinates":[2.0908439159,41.3244400024],"type":"Point"}
}