{
  "type": "Feature",
  "properties": {
    "addr:full":"Pg Mitja Llegua, 13 Alfas Pi Alicante 03580",
    "addr:housenumber":"13",
    "addr:postcode":"03580",
    "addr:street":"Pg Mitja Llegua",
    "iso:country":"ES",
    "sg:address":"Pg Mitja Llegua, 13",
    "sg:city":"Alfas Pi",
    "sg:orig_category":"Inmobiliaria (agencias)",
    "sg:phone":"+34 966 81 40 45",
    "sg:postcode":"03580",
    "sg:province":"Alicante",
    "wof:name":"3 X 3 Immo Management Gmdh",
    "wof:placetype":"venue"
},
  "geometry": {"coordinates":[-0.093755,38.56971],"type":"Point"}
}