{
  "type": "Feature",
  "properties": {
    "iso:country":"ES",
    "sg:address":"Av Francesc Macia, 80",
    "sg:city":"Olesa Montserrat",
    "sg:orig_category":"Peluquer\u00cdas, Peluquer\u00cda Mixta",
    "sg:phone":"+34 937 78 07 87",
    "sg:postcode":"08640",
    "sg:province":"Barcelona",
    "wof:name":"Vicente Hernandez Lidia",
    "wof:placetype":"venue"
},
  "geometry": {"coordinates":[1.8920190334,41.5427398682],"type":"Point"}
}