{
  "type": "Feature",
  "properties": {
    "iso:country":"ES",
    "sg:address":"Avda Constitucion De La, 6",
    "sg:city":"Arroyo De La Miel-benalmadena Costa",
    "sg:orig_category":"Notarios",
    "sg:phone":"+34 952 56 62 65",
    "sg:postcode":"29631",
    "sg:province":"M\u00e1laga",
    "wof:name":"Garcia Inda Nieves",
    "wof:placetype":"venue"
},
  "geometry": {"coordinates":[-4.5297665596,36.600353241],"type":"Point"}
}