{
  "type": "Feature",
  "properties": {
    "addr:full":"Pg Vilafranca, 4 Sitges Barcelona 08870",
    "addr:housenumber":"4",
    "addr:postcode":"08870",
    "addr:street":"Pg Vilafranca",
    "iso:country":"ES",
    "sg:address":"Pg Vilafranca, 4",
    "sg:city":"Sitges",
    "sg:orig_category":"Retoques De Vestidos",
    "sg:phone":"+34 938 11 10 56",
    "sg:postcode":"08870",
    "sg:province":"Barcelona",
    "sg:website":"www.alavora.com",
    "wof:name":"A La Vora Scp",
    "wof:placetype":"venue"
},
  "geometry": {"coordinates":[1.8057672977,41.2418785095],"type":"Point"}
}