{
  "type": "Feature",
  "properties": {
    "addr:full":"Carrer de Lima, 5 Barcelona Barcelona 08030",
    "addr:housenumber":"5",
    "addr:postcode":"08030",
    "addr:street":"Carrer De Lima",
    "iso:country":"ES",
    "sg:address":"Carrer de Lima, 5",
    "sg:city":"Barcelona",
    "sg:orig_category":"Bazares, Art\u00cdculos De Limpieza Y De Cocina (al Por Menor)",
    "sg:phone":"+34 933 11 94 14",
    "sg:postcode":"08030",
    "sg:province":"Barcelona",
    "wof:name":"Picaza Importaciones S.l",
    "wof:placetype":"venue"
},
  "geometry": {"coordinates":[2.2015841007,41.4395332336],"type":"Point"}
}