{
  "type": "Feature",
  "properties": {
    "addr:full":"Pare F. Coli, 4 Ripoll Girona 17500",
    "addr:housenumber":"4",
    "addr:postcode":"17500",
    "addr:street":"Coli",
    "iso:country":"ES",
    "sg:address":"Pare F. Coli, 4",
    "sg:city":"Ripoll",
    "sg:orig_category":"Art\u00cdculos De Regalo (al Por Menor)",
    "sg:phone":"+34 972 70 13 02",
    "sg:postcode":"17500",
    "sg:province":"Girona",
    "sg:website":"www.telefonica.net/web/flashripoll",
    "wof:name":"Gili Valenti Jose",
    "wof:placetype":"venue"
},
  "geometry": {"coordinates":[2.1908268929,42.200088501],"type":"Point"}
}