{
  "type": "Feature",
  "properties": {
    "addr:full":"Calle de San Marcial, 50 Donostia-san Sebastian Guip\u00f9zcoa 20005",
    "addr:housenumber":"50",
    "addr:postcode":"20005",
    "addr:street":"Calle De San Marcial",
    "iso:country":"ES",
    "sg:address":"Calle de San Marcial, 50",
    "sg:city":"Donostia-san Sebastian",
    "sg:orig_category":"Ropa Para Se\u00d1oras (al Por Menor)",
    "sg:phone":"+34 943 42 11 51",
    "sg:postcode":"20005",
    "sg:province":"Guip\u00f9zcoa",
    "wof:name":"Bregachorena Martinez Elisa",
    "wof:placetype":"venue"
},
  "geometry": {"coordinates":[-1.9842319489,43.3180732727],"type":"Point"}
}