{
  "type": "Feature",
  "properties": {
    "addr:full":"Pg Maragall, 19 Barcelona Barcelona 08026",
    "addr:housenumber":"19",
    "addr:postcode":"08026",
    "addr:street":"Pg Maragall",
    "iso:country":"ES",
    "sg:address":"Pg Maragall, 19",
    "sg:city":"Barcelona",
    "sg:orig_category":"Fabricaci\u00d3n, Importaci\u00d3n De L\u00c1mparas Y Bombillas",
    "sg:phone":"+34 934 36 26 62",
    "sg:postcode":"08026",
    "sg:province":"Barcelona",
    "wof:name":"Palau Mena Mariano",
    "wof:placetype":"venue"
},
  "geometry": {"coordinates":[2.1807870865,41.4142379761],"type":"Point"}
}