{
  "type": "Feature",
  "properties": {
    "addr:full":"Lienzo (pol Ind Hytasa), 4 Sevilla Sevilla 41005",
    "addr:housenumber":"4",
    "addr:postcode":"41005",
    "addr:street":"Lienzo;Hytasa",
    "iso:country":"ES",
    "sg:address":"Lienzo (pol Ind Hytasa), 4",
    "sg:city":"Sevilla",
    "sg:orig_category":"Artes Gr\u00c1ficas, Artes Pl\u00c1sticas (curso)",
    "sg:phone":"+34 954 93 40 55",
    "sg:postcode":"41005",
    "sg:province":"Sevilla",
    "wof:name":"Sevillaprint S.l.",
    "wof:placetype":"venue"
},
  "geometry": {"coordinates":[-5.9595842361,37.3687591553],"type":"Point"}
}