{
  "type": "Feature",
  "properties": {
    "addr:full":"Monasterio Irache, 20 Iru\u00f1a Navarra 31011",
    "addr:housenumber":"20",
    "addr:postcode":"31011",
    "addr:street":"Irache",
    "iso:country":"ES",
    "sg:address":"Monasterio Irache, 20",
    "sg:city":"Iru\u00f1a",
    "sg:orig_category":"Organismos Y Centros De Vacaciones Y Esparcimiento Para Ni\u00d1os Y Adolescentes",
    "sg:phone":"+34 948 19 95 54",
    "sg:postcode":"31011",
    "sg:province":"Navarra",
    "wof:name":"Don Volatin La Morea S.l",
    "wof:placetype":"venue"
},
  "geometry": {"coordinates":[-1.6587610245,42.81798172],"type":"Point"}
}