{
  "type": "Feature",
  "properties": {
    "iso:country":"ES",
    "sg:address":"Ctra San Juan, S/n",
    "sg:city":"Mutxamel",
    "sg:orig_category":"Inmobiliaria (agencias)",
    "sg:phone":"+34 965 95 02 39",
    "sg:postcode":"03110",
    "sg:province":"Alicante",
    "wof:name":"Espaiver Servicios Inmobiliarios S.l.u",
    "wof:placetype":"venue"
},
  "geometry": {"coordinates":[-0.4356719851,38.4123268127],"type":"Point"}
}