{
  "type": "Feature",
  "properties": {
    "iso:country":"ES",
    "sg:address":"Av Alcudia, 27",
    "sg:city":"Benissa",
    "sg:orig_category":"Fisioterapia",
    "sg:phone":"+34 965 73 34 01",
    "sg:postcode":"03720",
    "sg:province":"Alicante",
    "wof:name":"Capo Giner Juan Vicente",
    "wof:placetype":"venue"
},
  "geometry": {"coordinates":[0.0499479994,38.7133178711],"type":"Point"}
}