{
  "type": "Feature",
  "properties": {
    "addr:full":"Carrer de Cartagena, 227 Barcelona Barcelona 08013",
    "addr:housenumber":"227",
    "addr:postcode":"08013",
    "addr:street":"Carrer De Cartagena",
    "iso:country":"ES",
    "sg:address":"Carrer de Cartagena, 227",
    "sg:city":"Barcelona",
    "sg:orig_category":"Alquiler De V\u00cddeo",
    "sg:phone":"+34 932 65 19 95",
    "sg:postcode":"08013",
    "sg:province":"Barcelona",
    "wof:name":"Abello Mi\u00f1ano Ramon",
    "wof:placetype":"venue"
},
  "geometry": {"coordinates":[2.180136,41.406765],"type":"Point"}
}