{
  "type": "Feature",
  "properties": {
    "addr:full":"Barr San Antonio Elgezabal, S/n Euba Vizcaya 48290",
    "addr:postcode":"48290",
    "addr:street":"Elgezabal S / N",
    "iso:country":"ES",
    "sg:address":"Barr San Antonio Elgezabal, S/n",
    "sg:city":"Euba",
    "sg:orig_category":"Empresas De Impermeabilizaci\u00d3n",
    "sg:phone":"+34 946 73 02 92",
    "sg:postcode":"48290",
    "sg:province":"Vizcaya",
    "sg:website":"www.reponor.com",
    "wof:name":"Reponor S.a.",
    "wof:placetype":"venue"
},
  "geometry": {"coordinates":[-2.6911990643,43.1808815002],"type":"Point"}
}