{
  "type": "Feature",
  "properties": {
    "iso:country":"ES",
    "sg:address":"Pla\u00c7 Espanya, 20",
    "sg:city":"Inca",
    "sg:orig_category":"Panader\u00cdas, Panader\u00cdas",
    "sg:phone":"+34 971 50 12 44",
    "sg:postcode":"07300",
    "sg:province":"Islas Baleares",
    "wof:name":"Panaderia Y Pasteleria La Gloria S. A.",
    "wof:placetype":"venue"
},
  "geometry": {"coordinates":[2.9094700813,39.7212600708],"type":"Point"}
}