{
  "type": "Feature",
  "properties": {
    "iso:country":"ES",
    "sg:address":"Calle de Ave Maria, 20",
    "sg:city":"Ponferrada",
    "sg:orig_category":"Ropa Para Se\u00d1oras (al Por Menor)",
    "sg:phone":"+34 987 40 45 05",
    "sg:postcode":"24400",
    "sg:province":"Le\u00f3n",
    "wof:name":"Voces Garcia Elvira",
    "wof:placetype":"venue"
},
  "geometry": {"coordinates":[-6.6008501053,42.5481262207],"type":"Point"}
}