{
  "type": "Feature",
  "properties": {
    "iso:country":"ES",
    "sg:address":"Carr Aigua, 111",
    "sg:city":"Vilanova I La Geltru",
    "sg:orig_category":"Institutos De Belleza",
    "sg:phone":"+34 938 14 19 04",
    "sg:postcode":"08800",
    "sg:province":"Barcelona",
    "wof:name":"4 Estils S.c.p.",
    "wof:placetype":"venue"
},
  "geometry": {"coordinates":[1.718947,41.224285],"type":"Point"}
}