{
  "type": "Feature",
  "properties": {
    "addr:full":"Calle de Vergara, 21 Salamanca Salamanca 37003",
    "addr:housenumber":"21",
    "addr:postcode":"37003",
    "addr:street":"Calle De Vergara",
    "iso:country":"ES",
    "sg:address":"Calle de Vergara, 21",
    "sg:city":"Salamanca",
    "sg:orig_category":"Procuradores",
    "sg:phone":"+34 923 23 85 80",
    "sg:postcode":"37003",
    "sg:province":"Salamanca",
    "wof:name":"Rodriguez Lopez Jose Luis",
    "wof:placetype":"venue"
},
  "geometry": {"coordinates":[-5.6539030075,40.9636116028],"type":"Point"}
}