{
  "type": "Feature",
  "properties": {
    "addr:full":"Calle de Flores (las), 65 Linea De La Concepcion C\u00e1diz 11300",
    "addr:housenumber":"65",
    "addr:postcode":"11300",
    "addr:street":"Calle De Flores Las;Ca\u0301Diz",
    "iso:country":"ES",
    "sg:address":"Calle de Flores (las), 65",
    "sg:city":"Linea De La Concepcion",
    "sg:orig_category":"Formaci\u00d3n A Distancia, Por Correspondencia",
    "sg:phone":"+34 956 76 30 60",
    "sg:postcode":"11300",
    "sg:province":"C\u00e1diz",
    "wof:name":"Academia La Linea S.l.",
    "wof:placetype":"venue"
},
  "geometry": {"coordinates":[-5.3500041962,36.1657333374],"type":"Point"}
}