{
  "type": "Feature",
  "properties": {
    "addr:full":"Carrer de Sentmenat, 16 Sabadell Barcelona 08203",
    "addr:housenumber":"16",
    "addr:postcode":"08203",
    "addr:street":"Carrer De Sentmenat",
    "iso:country":"ES",
    "sg:address":"Carrer de Sentmenat, 16",
    "sg:city":"Sabadell",
    "sg:orig_category":"Complementos De Vestir (al Por Menor)",
    "sg:phone":"+34 937 25 35 51",
    "sg:postcode":"08203",
    "sg:province":"Barcelona",
    "wof:name":"Illanas Blanca Antonia",
    "wof:placetype":"venue"
},
  "geometry": {"coordinates":[2.117677927,41.5420913696],"type":"Point"}
}