{
  "type": "Feature",
  "properties": {
    "addr:full":"Calle de Reyes Leoneses, 28 Le\u00f3n Le\u00f3n 24008",
    "addr:housenumber":"28",
    "addr:postcode":"24008",
    "addr:street":"Calle De Reyes Leoneses;Leo\u0301N",
    "iso:country":"ES",
    "sg:address":"Calle de Reyes Leoneses, 28",
    "sg:city":"Le\u00f3n",
    "sg:orig_category":"Carnicer\u00cdas, Carnicer\u00cdas",
    "sg:phone":"+34 987 80 74 00",
    "sg:postcode":"24008",
    "sg:province":"Le\u00f3n",
    "wof:name":"Lopez Garcia Maria Eva",
    "wof:placetype":"venue"
},
  "geometry": {"coordinates":[-5.5866379738,42.610786438],"type":"Point"}
}