{
  "type": "Feature",
  "properties": {
    "iso:country":"ES",
    "sg:address":"Carrer de Portugal, 42",
    "sg:city":"Mollet Valles",
    "sg:orig_category":"Cerrajer\u00cda, Ferrallista",
    "sg:phone":"+34 935 93 99 01",
    "sg:postcode":"08100",
    "sg:province":"Barcelona",
    "wof:name":"Colome Sanchez Andres",
    "wof:placetype":"venue"
},
  "geometry": {"coordinates":[2.2152578831,41.5410079956],"type":"Point"}
}