{
  "type": "Feature",
  "properties": {
    "iso:country":"ES",
    "sg:address":"Avda Ejercito, 21",
    "sg:city":"Guadalajara",
    "sg:orig_category":"Muebles Y Accesorios Para Cocinas Y Cuartos De Ba\u00d1o (al Por Menor)",
    "sg:phone":"+34 949 22 63 37",
    "sg:postcode":"19004",
    "sg:province":"Guadalajara",
    "wof:name":"Del Olmo Romero De Avila Basilio",
    "wof:placetype":"venue"
},
  "geometry": {"coordinates":[-3.1791980267,40.6295890808],"type":"Point"}
}