{
  "type": "Feature",
  "properties": {
    "addr:full":"Carrer de Espronceda, 363 Barcelona Barcelona 08027",
    "addr:housenumber":"363",
    "addr:postcode":"08027",
    "addr:street":"Carrer De Espronceda",
    "iso:country":"ES",
    "sg:address":"Carrer de Espronceda, 363",
    "sg:city":"Barcelona",
    "sg:orig_category":"Farmacias",
    "sg:phone":"+34 933 52 37 60",
    "sg:postcode":"08027",
    "sg:province":"Barcelona",
    "wof:name":"Tico Amoros Jose",
    "wof:placetype":"venue"
},
  "geometry": {"coordinates":[2.1881160736,41.4176368713],"type":"Point"}
}