{
  "type": "Feature",
  "properties": {
    "addr:full":"Avda San Pablo (de), 31 Coslada Madrid 28820",
    "addr:housenumber":"31",
    "addr:postcode":"28820",
    "addr:street":"Avda San Pablo De",
    "iso:country":"ES",
    "sg:address":"Avda San Pablo (de), 31",
    "sg:city":"Coslada",
    "sg:orig_category":"Gr\u00daas, Montacargas Y Elevadores Para Astilleros",
    "sg:phone":"+34 914 85 00 04",
    "sg:postcode":"28820",
    "sg:province":"Madrid",
    "sg:website":"www.gruasassur.com",
    "wof:name":"Gutierrez Adan Enrique",
    "wof:placetype":"venue"
},
  "geometry": {"coordinates":[-3.5320630074,40.4383850098],"type":"Point"}
}