{
  "type": "Feature",
  "properties": {
    "iso:country":"ES",
    "sg:address":"Calle de Margarita Iturralde, 35",
    "sg:city":"Trujillo",
    "sg:orig_category":"Droguer\u00cdas (al Por Menor)",
    "sg:phone":"+34 927 32 06 80",
    "sg:postcode":"10200",
    "sg:province":"C\u00e1ceres",
    "wof:name":"Vazquez Fernandez Manuel",
    "wof:placetype":"venue"
},
  "geometry": {"coordinates":[-5.8801140785,39.4586181641],"type":"Point"}
}