{
  "type": "Feature",
  "properties": {
    "addr:full":"Plaz Galicia (de), 2 Mosteiro Lugo 27270",
    "addr:postcode":"27270",
    "addr:street":"Plaz",
    "iso:country":"ES",
    "sg:address":"Plaz Galicia (de), 2",
    "sg:city":"Mosteiro",
    "sg:orig_category":"Farmacias",
    "sg:phone":"+34 982 34 52 01",
    "sg:postcode":"27270",
    "sg:province":"Lugo",
    "wof:name":"Perez Rodriguez Fernando Javier",
    "wof:placetype":"venue"
},
  "geometry": {"coordinates":[-7.3522891998,43.1285438538],"type":"Point"}
}