{
  "type": "Feature",
  "properties": {
    "iso:country":"ES",
    "sg:address":"Calle de Jose Nogales, 3",
    "sg:city":"Aracena",
    "sg:orig_category":"Inform\u00c1tica (estudios, Servicios, Asesor\u00cda, Formaci\u00d3n)",
    "sg:phone":"+34 959 12 73 80",
    "sg:postcode":"21200",
    "sg:province":"Huelva",
    "wof:name":"Garcia Rufino Sergio",
    "wof:placetype":"venue"
},
  "geometry": {"coordinates":[-6.5603070259,37.8945541382],"type":"Point"}
}