{
  "type": "Feature",
  "properties": {
    "addr:full":"Plaz Honduras, 12 Valencia Valencia 46022",
    "addr:housenumber":"12",
    "addr:postcode":"46022",
    "addr:street":"Plaz Honduras",
    "iso:country":"ES",
    "sg:address":"Plaz Honduras, 12",
    "sg:city":"Valencia",
    "sg:orig_category":"Institutos De Belleza (productos Y Aparatos)",
    "sg:phone":"+34 963 72 70 48",
    "sg:postcode":"46022",
    "sg:province":"Valencia",
    "wof:name":"Montoro Simo Maruja",
    "wof:placetype":"venue"
},
  "geometry": {"coordinates":[-0.3439219892,39.4742698669],"type":"Point"}
}