{
  "type": "Feature",
  "properties": {
    "iso:country":"ES",
    "sg:address":"Rbla Badal, 141",
    "sg:city":"Barcelona",
    "sg:orig_category":"M\u00c9dicos: Estomatolog\u00cda",
    "sg:phone":"+34 934 32 34 26",
    "sg:postcode":"08028",
    "sg:province":"Barcelona",
    "wof:name":"Torres Salazar Julia",
    "wof:placetype":"venue"
},
  "geometry": {"coordinates":[2.1309080124,41.3735198975],"type":"Point"}
}