{
  "type": "Feature",
  "properties": {
    "iso:country":"ES",
    "sg:address":"Calle de Carrasco Alcalde, 13",
    "sg:city":"Herencia",
    "sg:orig_category":"Agricultura: Abastecimiento Y Cosechado (negocio)",
    "sg:phone":"+34 926 57 37 39",
    "sg:postcode":"13640",
    "sg:province":"Ciudad Real",
    "wof:name":"S.a.t. N 5836 Denominada Los Veinticuatro",
    "wof:placetype":"venue"
},
  "geometry": {"coordinates":[-3.3577070236,39.367061615],"type":"Point"}
}