{
  "type": "Feature",
  "properties": {
    "addr:full":"Pintor Maeztu, 6 Iru\u00f1a Navarra 31008",
    "addr:housenumber":"6",
    "addr:postcode":"31008",
    "addr:street":"Pintor Maeztu",
    "iso:country":"ES",
    "sg:address":"Pintor Maeztu, 6",
    "sg:city":"Iru\u00f1a",
    "sg:orig_category":"Arquitectos",
    "sg:phone":"+34 948 27 05 51",
    "sg:postcode":"31008",
    "sg:province":"Navarra",
    "wof:name":"Velazquez Arteaga German",
    "wof:placetype":"venue"
},
  "geometry": {"coordinates":[-1.6591049433,42.8071098328],"type":"Point"}
}