{
  "type": "Feature",
  "properties": {
    "addr:full":"Avda Medina Olmos, 38 Guadix Granada 18500",
    "addr:housenumber":"38",
    "addr:postcode":"18500",
    "addr:street":"Avda Medina Olmos",
    "iso:country":"ES",
    "sg:address":"Avda Medina Olmos, 38",
    "sg:city":"Guadix",
    "sg:orig_category":"Inmobiliaria (agencias)",
    "sg:phone":"+34 958 66 37 42",
    "sg:postcode":"18500",
    "sg:province":"Granada",
    "wof:name":"Inmobiliaria Argenta C.b.",
    "wof:placetype":"venue"
},
  "geometry": {"coordinates":[-3.1318490505,37.3002738953],"type":"Point"}
}