{
  "type": "Feature",
  "properties": {
    "iso:country":"ES",
    "sg:address":"Calle de Martirs (dels), 54",
    "sg:city":"Rafelbunyol",
    "sg:orig_category":"Supermercados Y Hipermercados",
    "sg:phone":"+34 961 41 30 04",
    "sg:postcode":"46138",
    "sg:province":"Valencia",
    "wof:name":"Mercat Rafel Sl",
    "wof:placetype":"venue"
},
  "geometry": {"coordinates":[-0.3362089992,39.5870513916],"type":"Point"}
}