{
  "type": "Feature",
  "properties": {
    "iso:country":"ES",
    "sg:address":"Calle de Capitan Hernandez Mira, 11",
    "sg:city":"Alacant",
    "sg:orig_category":"Agencias Y Agentes Comerciales, Representantes",
    "sg:phone":"+34 965 24 99 23",
    "sg:postcode":"03004",
    "sg:province":"Alicante",
    "wof:name":"Carratola Lillo Asuncion",
    "wof:placetype":"venue"
},
  "geometry": {"coordinates":[-0.4872210026,38.3527832031],"type":"Point"}
}