{
  "type": "Feature",
  "properties": {
    "addr:full":"Praz Maior, 9 Viana Do Bolo Ourense 32550",
    "addr:housenumber":"9",
    "addr:postcode":"32550",
    "addr:street":"Praz Maior",
    "iso:country":"ES",
    "sg:address":"Praz Maior, 9",
    "sg:city":"Viana Do Bolo",
    "sg:orig_category":"Farmacias",
    "sg:phone":"+34 988 34 00 69",
    "sg:postcode":"32550",
    "sg:province":"Ourense",
    "wof:name":"Raluy Rodriguez Maria Luisa",
    "wof:placetype":"venue"
},
  "geometry": {"coordinates":[-7.1098628044,42.1833190918],"type":"Point"}
}