{
  "type": "Feature",
  "properties": {
    "iso:country":"ES",
    "sg:address":"Calle de Real, 52",
    "sg:city":"Arganda",
    "sg:orig_category":"Peluquer\u00cdas, Peluquer\u00cda Mixta",
    "sg:phone":"+34 918 71 56 71",
    "sg:postcode":"28500",
    "sg:province":"Madrid",
    "wof:name":"Sanjose Jimenez Maria Teresa",
    "wof:placetype":"venue"
},
  "geometry": {"coordinates":[-3.4359641075,40.2999153137],"type":"Point"}
}