{
  "type": "Feature",
  "properties": {
    "addr:full":"Barr Musel, S/n Gijon Asturias 33290",
    "addr:housenumber":"s",
    "addr:postcode":"33290",
    "addr:street":"Musel;/ N",
    "iso:country":"ES",
    "sg:address":"Barr Musel, S/n",
    "sg:city":"Gijon",
    "sg:orig_category":"Crust\u00c1ceos Y Almejas (al Por Mayor)",
    "sg:phone":"+34 985 30 88 30",
    "sg:postcode":"33290",
    "sg:province":"Asturias",
    "wof:name":"Cetarea Tazones S.l.",
    "wof:placetype":"venue"
},
  "geometry": {"coordinates":[-5.7190551758,43.5478096008],"type":"Point"}
}