{
  "type": "Feature",
  "properties": {
    "iso:country":"ES",
    "sg:address":"Hendaia Kalea, 7",
    "sg:city":"Hondarribia",
    "sg:orig_category":"Estudios Y Construcci\u00d3n De Acuarios Y Viveros",
    "sg:phone":"+34 943 64 25 42",
    "sg:postcode":"20280",
    "sg:province":"Guip\u00f9zcoa",
    "wof:name":"Viveros Jaizkibel Mendia",
    "wof:placetype":"venue"
},
  "geometry": {"coordinates":[-1.789467454,43.361869812],"type":"Point"}
}