{
  "type": "Feature",
  "properties": {
    "iso:country":"ES",
    "sg:address":"Urb Hoya Patos, S/n",
    "sg:city":"Busot",
    "sg:orig_category":"Ropa Y Accesorios",
    "sg:phone":"+34 965 69 94 01",
    "sg:postcode":"03111",
    "sg:province":"Alicante",
    "wof:name":"Lorente Satoca Jose Maria",
    "wof:placetype":"venue"
},
  "geometry": {"coordinates":[-0.4268090129,38.4777984619],"type":"Point"}
}