{
  "type": "Feature",
  "properties": {
    "iso:country":"ES",
    "sg:address":"Rua Pintor Laxeiro, 17",
    "sg:city":"Lalin",
    "sg:orig_category":"Peluqueros: De Se\u00d1oras",
    "sg:phone":"+34 986 78 45 33",
    "sg:postcode":"36500",
    "sg:province":"Pontevedra",
    "wof:name":"Pichel Gonzalez Manuela",
    "wof:placetype":"venue"
},
  "geometry": {"coordinates":[-8.1109666824,42.6596488953],"type":"Point"}
}