{
  "type": "Feature",
  "properties": {
    "iso:country":"ES",
    "sg:address":"Carrer de Major, 3",
    "sg:city":"Santa Coloma De Gramenet",
    "sg:orig_category":"Centros Comerciales Y Grandes Tiendas",
    "sg:phone":"+34 934 66 45 12",
    "sg:postcode":"08921",
    "sg:province":"Barcelona",
    "wof:name":"Quiros Maldonado Dolores",
    "wof:placetype":"venue"
},
  "geometry": {"coordinates":[2.2026920319,41.4510002136],"type":"Point"}
}