{
  "type": "Feature",
  "properties": {
    "iso:country":"ES",
    "sg:address":"Av. B. Navarra, 22",
    "sg:city":"Iru\u00f1a",
    "sg:orig_category":"Caf\u00c9s, Bares, Cervecer\u00cdas",
    "sg:phone":"+34 948 24 81 66",
    "sg:postcode":"31004",
    "sg:province":"Navarra",
    "wof:name":"Fernandez Lanzas Gregorio",
    "wof:placetype":"venue"
},
  "geometry": {"coordinates":[-1.6437540054,42.81275177],"type":"Point"}
}