{
  "type": "Feature",
  "properties": {
    "iso:country":"ES",
    "sg:address":"Calle de Agustina De Aragon, 24",
    "sg:city":"Bola\u00e7os De Calatrava",
    "sg:orig_category":"Venta Al Preg\u00d3n",
    "sg:phone":"+34 926 87 02 88",
    "sg:postcode":"13260",
    "sg:province":"Ciudad Real",
    "wof:name":"Martin Ruiz Joaquin",
    "wof:placetype":"venue"
},
  "geometry": {"coordinates":[-3.3671889305,39.0026931763],"type":"Point"}
}