{
  "type": "Feature",
  "properties": {
    "iso:country":"ES",
    "sg:address":"Avda Tirajana (de), 15",
    "sg:city":"Playa Del Ingles",
    "sg:orig_category":"Supermercados Y Hipermercados",
    "sg:phone":"+34 928 76 54 73",
    "sg:postcode":"35100",
    "sg:province":"Las Palmas",
    "wof:name":"Suarez Perez Juan",
    "wof:placetype":"venue"
},
  "geometry": {"coordinates":[-15.5787067413,27.7560749054],"type":"Point"}
}