{
  "type": "Feature",
  "properties": {
    "iso:country":"ES",
    "sg:address":"Av Masnou, 3",
    "sg:city":"Hospitalet Llobregat",
    "sg:orig_category":"Fabricaci\u00d3n, Importaci\u00d3n De L\u00c1mparas Y Bombillas",
    "sg:phone":"+34 934 37 02 19",
    "sg:postcode":"08905",
    "sg:province":"Barcelona",
    "wof:name":"Celma Redorat Antonio",
    "wof:placetype":"venue"
},
  "geometry": {"coordinates":[2.105150938,41.3711242676],"type":"Point"}
}