{
  "type": "Feature",
  "properties": {
    "iso:country":"ES",
    "sg:address":"Calle de Marques De La Valdavia (del), 48",
    "sg:city":"Alcobendas",
    "sg:orig_category":"Zapatos (al Por Menor)",
    "sg:phone":"+34 916 63 65 23",
    "sg:postcode":"28100",
    "sg:province":"Madrid",
    "wof:name":"Grupo Zapatero S.l.",
    "wof:placetype":"venue"
},
  "geometry": {"coordinates":[-3.6389300823,40.5428733826],"type":"Point"}
}