{
  "type": "Feature",
  "properties": {
    "addr:full":"Pl Llibertat, 14 Barcelona Barcelona 08012",
    "addr:housenumber":"14",
    "addr:postcode":"08012",
    "addr:street":"Pl Llibertat",
    "iso:country":"ES",
    "sg:address":"Pl Llibertat, 14",
    "sg:city":"Barcelona",
    "sg:orig_category":"Perfumer\u00cda (al Por Menor)",
    "sg:phone":"+34 932 17 27 05",
    "sg:postcode":"08012",
    "sg:province":"Barcelona",
    "wof:name":"Ferrer Oliveras Antonio",
    "wof:placetype":"venue"
},
  "geometry": {"coordinates":[2.153012991,41.4000473022],"type":"Point"}
}