{
  "type": "Feature",
  "properties": {
    "addr:full":"Calle de Luis Fernandez Cabeza, 4 Mieres Asturias 33600",
    "addr:housenumber":"4",
    "addr:postcode":"33600",
    "addr:street":"Calle De Luis Fernandez Cabeza",
    "iso:country":"ES",
    "sg:address":"Calle de Luis Fernandez Cabeza, 4",
    "sg:city":"Mieres",
    "sg:orig_category":"Parafarmacias",
    "sg:phone":"+34 984 18 09 33",
    "sg:postcode":"33600",
    "sg:province":"Asturias",
    "sg:website":"www.farmarosa.es",
    "wof:name":"Comercial Asturiana De Parafarmacia S.l.",
    "wof:placetype":"venue"
},
  "geometry": {"coordinates":[-5.7737488747,43.2497138977],"type":"Point"}
}