{
  "type": "Feature",
  "properties": {
    "addr:full":"Calle de Milanos, 10 Pinto Madrid 28320",
    "addr:housenumber":"10",
    "addr:postcode":"28320",
    "addr:street":"Calle De Milanos",
    "iso:country":"ES",
    "sg:address":"Calle de Milanos, 10",
    "sg:city":"Pinto",
    "sg:orig_category":"Mec\u00c1nico Del Autom\u00d3vil",
    "sg:phone":"+34 916 91 54 13",
    "sg:postcode":"28320",
    "sg:province":"Madrid",
    "wof:name":"Clemente Hervas Francisco",
    "wof:placetype":"venue"
},
  "geometry": {"coordinates":[-3.7055740356,40.2507553101],"type":"Point"}
}