{
  "type": "Feature",
  "properties": {
    "addr:full":"Plaz San Fernando, 1 Iznatoraf Ja\u00e9n 23338",
    "addr:housenumber":"1",
    "addr:postcode":"23338",
    "addr:street":"Plaz San Fernando",
    "iso:country":"ES",
    "sg:address":"Plaz San Fernando, 1",
    "sg:city":"Iznatoraf",
    "sg:orig_category":"Cajas De Ahorro",
    "sg:phone":"+34 953 45 25 40",
    "sg:postcode":"23338",
    "sg:province":"Ja\u00e9n",
    "wof:name":"Unicaja",
    "wof:placetype":"venue"
},
  "geometry": {"coordinates":[-3.0326209068,38.157749176],"type":"Point"}
}