{
  "type": "Feature",
  "properties": {
    "iso:country":"ES",
    "sg:address":"Carrer de Major, 15",
    "sg:city":"Salou",
    "sg:orig_category":"Peluquer\u00cdas, Peluquer\u00cda Mixta",
    "sg:phone":"+34 977 38 15 02",
    "sg:postcode":"43840",
    "sg:province":"Tarragona",
    "wof:name":"Virgili Cardona Juan Manuel",
    "wof:placetype":"venue"
},
  "geometry": {"coordinates":[1.135226965,41.0766410828],"type":"Point"}
}