{
  "type": "Feature",
  "properties": {
    "iso:country":"ES",
    "sg:address":"Avda Andalucia, 2",
    "sg:city":"Begijar",
    "sg:orig_category":"Molduras, Junquillos, Listones Y Molduras Perforadas",
    "sg:phone":"+34 953 76 31 04",
    "sg:postcode":"23520",
    "sg:province":"Ja\u00e9n",
    "wof:name":"Prados Garate Manuel",
    "wof:placetype":"venue"
},
  "geometry": {"coordinates":[-3.5313448906,37.9852027893],"type":"Point"}
}