{
  "type": "Feature",
  "properties": {
    "addr:full":"Carrer de Girona, S/n Piera Barcelona 08784",
    "addr:housenumber":"s / n",
    "addr:postcode":"08784",
    "addr:street":"Carrer De Girona",
    "iso:country":"ES",
    "sg:address":"Carrer de Girona, S/n",
    "sg:city":"Piera",
    "sg:orig_category":"Material Y Herramientas Agr\u00cdcolas",
    "sg:phone":"+34 937 76 04 51",
    "sg:postcode":"08784",
    "sg:province":"Barcelona",
    "wof:name":"Rosell Biosca Andreu",
    "wof:placetype":"venue"
},
  "geometry": {"coordinates":[1.7530200481,41.5223197937],"type":"Point"}
}