{
  "type": "Feature",
  "properties": {
    "addr:full":"Carrer de Progres, 2 Gava Barcelona 08850",
    "addr:housenumber":"2",
    "addr:postcode":"08850",
    "addr:street":"Carrer De Progres",
    "iso:country":"ES",
    "sg:address":"Carrer de Progres, 2",
    "sg:city":"Gava",
    "sg:orig_category":"Agencias Y Agentes Comerciales, Representantes",
    "sg:phone":"+34 933 77 60 50",
    "sg:postcode":"08850",
    "sg:province":"Barcelona",
    "wof:name":"T.g. Promociones Representaciones S.a.",
    "wof:placetype":"venue"
},
  "geometry": {"coordinates":[2.0125100613,41.2997894287],"type":"Point"}
}