{
  "type": "Feature",
  "properties": {
    "iso:country":"ES",
    "sg:address":"Calle de Sol, 57",
    "sg:city":"Calahorra",
    "sg:orig_category":"Carnicer\u00cdas, Carnicer\u00cdas",
    "sg:phone":"+34 941 13 46 91",
    "sg:postcode":"26500",
    "sg:province":"La Rioja",
    "wof:name":"Cordon Perez Demetrio",
    "wof:placetype":"venue"
},
  "geometry": {"coordinates":[-1.9610370398,42.3029937744],"type":"Point"}
}