{
  "type": "Feature",
  "properties": {
    "iso:country":"ES",
    "sg:address":"Calle de Bellavista, 11",
    "sg:city":"Corte Peleas",
    "sg:orig_category":"Vinos Y Licores (venta Al Por Menor)",
    "sg:phone":"+34 924 69 33 52",
    "sg:postcode":"06196",
    "sg:province":"Badajoz",
    "wof:name":"Cimpaber S.l",
    "wof:placetype":"venue"
},
  "geometry": {"coordinates":[-6.6681084633,38.7242927551],"type":"Point"}
}