{
  "type": "Feature",
  "properties": {
    "iso:country":"ES",
    "sg:address":"Calle de Escuza Jose Maria, 29",
    "sg:city":"Bilbao",
    "sg:orig_category":"Confecci\u00d3n De Trajes Para Se\u00d1oras",
    "sg:phone":"+34 944 41 26 38",
    "sg:postcode":"48013",
    "sg:province":"Vizcaya",
    "wof:name":"Mieres Casado Maria Piedad",
    "wof:placetype":"venue"
},
  "geometry": {"coordinates":[-2.9457390308,43.2608909607],"type":"Point"}
}