{
  "type": "Feature",
  "properties": {
    "addr:full":"Carrer de Esglesia, 180 Calella Barcelona 08370",
    "addr:housenumber":"180",
    "addr:postcode":"08370",
    "addr:street":"Carrer De Esglesia",
    "iso:country":"ES",
    "sg:address":"Carrer de Esglesia, 180",
    "sg:city":"Calella",
    "sg:orig_category":"Peleter\u00cdas",
    "sg:phone":"+34 937 69 16 30",
    "sg:postcode":"08370",
    "sg:province":"Barcelona",
    "wof:name":"Duch Gomariz Ricardo",
    "wof:placetype":"venue"
},
  "geometry": {"coordinates":[2.6634790897,41.6150856018],"type":"Point"}
}