{
  "type": "Feature",
  "properties": {
    "addr:full":"Plaz Humilladero (del), 1 Granada Granada 18005",
    "addr:postcode":"18005",
    "addr:street":"Plaz;Del",
    "iso:country":"ES",
    "sg:address":"Plaz Humilladero (del), 1",
    "sg:city":"Granada",
    "sg:orig_category":"Arquitectos",
    "sg:phone":"+34 958 22 88 98",
    "sg:postcode":"18005",
    "sg:province":"Granada",
    "wof:name":"Garcia Lopez Manuel Gines",
    "wof:placetype":"venue"
},
  "geometry": {"coordinates":[-3.5964488983,37.1694564819],"type":"Point"}
}