{
  "type": "Feature",
  "properties": {
    "addr:full":"Calle de Ronda Colon, 4 Javea Alicante 03730",
    "addr:housenumber":"4",
    "addr:postcode":"03730",
    "addr:street":"Calle De Ronda Colon",
    "iso:country":"ES",
    "sg:address":"Calle de Ronda Colon, 4",
    "sg:city":"Javea",
    "sg:orig_category":"Farmacias",
    "sg:phone":"+34 965 79 10 99",
    "sg:postcode":"03730",
    "sg:province":"Alicante",
    "wof:name":"Belchi Arevalo Antonio",
    "wof:placetype":"venue"
},
  "geometry": {"coordinates":[0.1668650061,38.7890739441],"type":"Point"}
}