{
  "type": "Feature",
  "properties": {
    "iso:country":"ES",
    "sg:address":"Calle de Infanta Maria Teresa, 2",
    "sg:city":"Yecla",
    "sg:orig_category":"Caf\u00c9s, Bares, Cervecer\u00cdas",
    "sg:phone":"+34 968 79 47 01",
    "sg:postcode":"30510",
    "sg:province":"Murcia",
    "wof:name":"Aquarium 2000 S.l.",
    "wof:placetype":"venue"
},
  "geometry": {"coordinates":[-1.1082811356,38.6101226807],"type":"Point"}
}