{
  "type": "Feature",
  "properties": {
    "iso:country":"ES",
    "sg:address":"Calle de Bailen, 8",
    "sg:city":"Almendralejo",
    "sg:orig_category":"Agencias Y Agentes Comerciales, Representantes",
    "sg:phone":"+34 924 67 16 54",
    "sg:postcode":"06200",
    "sg:province":"Badajoz",
    "wof:name":"Zac-and-gon S.l.",
    "wof:placetype":"venue"
},
  "geometry": {"coordinates":[-6.4071688652,38.681640625],"type":"Point"}
}