{
  "type": "Feature",
  "properties": {
    "addr:full":"Arroyo Culebra, S/n Puertollano Ciudad Real 13500",
    "addr:housenumber":"s / n",
    "addr:postcode":"13500",
    "iso:country":"ES",
    "sg:address":"Arroyo Culebra, S/n",
    "sg:city":"Puertollano",
    "sg:orig_category":"Carb\u00d3n, Carb\u00d3n De Madera (al Por Mayor)",
    "sg:phone":"+34 926 42 77 50",
    "sg:postcode":"13500",
    "sg:province":"Ciudad Real",
    "wof:name":"Carbones Del Centro S. A.",
    "wof:placetype":"venue"
},
  "geometry": {"coordinates":[-4.4305090904,38.735748291],"type":"Point"}
}