{
  "type": "Feature",
  "properties": {
    "iso:country":"ES",
    "sg:address":"Calle de Rio Boeza, 11",
    "sg:city":"Bembibre",
    "sg:classifiers":[
        {
            "category":"Taxi",
            "type":"Transportation"
        }
    ],
    "sg:phone":"+34 987 51 14 77",
    "sg:postcode":"24300",
    "sg:province":"Le\u00f3n",
    "wof:name":"Yebra Gonzalez Dionisio",
    "wof:placetype":"venue"
},
  "geometry": {"coordinates":[-6.4182338715,42.6156654358],"type":"Point"}
}