{
  "type": "Feature",
  "properties": {
    "addr:full":"Carrer de Joan Maragall, 13 Cambrils Tarragona 43850",
    "addr:housenumber":"13",
    "addr:postcode":"43850",
    "addr:street":"Carrer De Joan Maragall",
    "iso:country":"ES",
    "sg:address":"Carrer de Joan Maragall, 13",
    "sg:city":"Cambrils",
    "sg:orig_category":"Reposter\u00cdas",
    "sg:phone":"+34 977 36 12 10",
    "sg:postcode":"43850",
    "sg:province":"Tarragona",
    "wof:name":"Maiva I Fills S.l.",
    "wof:placetype":"venue"
},
  "geometry": {"coordinates":[1.0485860109,41.0735702515],"type":"Point"}
}