{
  "type": "Feature",
  "properties": {
    "iso:country":"ES",
    "sg:address":"Calle de Campoamor, 2",
    "sg:city":"Salinas",
    "sg:orig_category":"Promotores Constructores",
    "sg:phone":"+34 985 51 86 87",
    "sg:postcode":"33405",
    "sg:province":"Asturias",
    "wof:name":"Obras Y Construcciones Roman Hermanos S.l.",
    "wof:placetype":"venue"
},
  "geometry": {"coordinates":[-5.9630446434,43.5749168396],"type":"Point"}
}