{
  "type": "Feature",
  "properties": {
    "iso:country":"ES",
    "sg:address":"Calle de Ferrer Del Rio, 6",
    "sg:city":"Madrid",
    "sg:orig_category":"Tiendas De Grano, Frutas Y Legumbres Secas (al Por Menor)",
    "sg:phone":"+34 913 55 37 94",
    "sg:postcode":"28028",
    "sg:province":"Madrid",
    "wof:name":"Galan Garcia Andres",
    "wof:placetype":"venue"
},
  "geometry": {"coordinates":[-3.6727249622,40.4337272644],"type":"Point"}
}