{
  "type": "Feature",
  "properties": {
    "iso:country":"ES",
    "sg:address":"Calle de Santa Cruz De Marcenado, 13",
    "sg:city":"Madrid",
    "sg:orig_category":"M\u00c9dicos: An\u00c1lisis Cl\u00cdnicos",
    "sg:phone":"+34 915 48 37 19",
    "sg:postcode":"28015",
    "sg:province":"Madrid",
    "wof:name":"Cotarelo Cuenllas Ricardo",
    "wof:placetype":"venue"
},
  "geometry": {"coordinates":[-3.7074959278,40.4286994934],"type":"Point"}
}