{
  "type": "Feature",
  "properties": {
    "iso:country":"ES",
    "sg:address":"Madrid, Km. 0389,7",
    "sg:city":"Espinardo",
    "sg:orig_category":"Servicios De Telecomunicaciones",
    "sg:phone":"+34 968 83 54 19",
    "sg:postcode":"30100",
    "sg:province":"Murcia",
    "wof:name":"Andreu Lopez Juan Jose",
    "wof:placetype":"venue"
},
  "geometry": {"coordinates":[-1.1512560844,38.0137634277],"type":"Point"}
}