{
  "type": "Feature",
  "properties": {
    "iso:country":"ES",
    "sg:address":"C/ Nou, 47",
    "sg:city":"Ripollet",
    "sg:orig_category":"Alimentaci\u00d3n General (al Por Menor)",
    "sg:phone":"+34 935 92 05 31",
    "sg:postcode":"08291",
    "sg:province":"Barcelona",
    "wof:name":"Corporacion Alimentaria Guissona S.a.",
    "wof:placetype":"venue"
},
  "geometry": {"coordinates":[2.1568899155,41.4980010986],"type":"Point"}
}