{
  "type": "Feature",
  "properties": {
    "iso:country":"ES",
    "sg:address":"Carrer de Joan D'austria, 1",
    "sg:city":"Terrassa",
    "sg:orig_category":"Carnicer\u00cdas, Carnicer\u00cdas",
    "sg:phone":"+34 937 80 29 72",
    "sg:postcode":"08223",
    "sg:province":"Barcelona",
    "wof:name":"Cobo Madrid Manuel",
    "wof:placetype":"venue"
},
  "geometry": {"coordinates":[2.0018072128,41.5686149597],"type":"Point"}
}