{
  "type": "Feature",
  "properties": {
    "iso:country":"ES",
    "sg:address":"Avda Garabolos (de), 9",
    "sg:city":"Lugo",
    "sg:orig_category":"Empresas De Desmonte",
    "sg:phone":"+34 982 21 36 01",
    "sg:postcode":"27003",
    "sg:province":"Lugo",
    "wof:name":"Excavaciones J. Carreira S.l.",
    "wof:placetype":"venue"
},
  "geometry": {"coordinates":[-7.5727419853,43.0286521912],"type":"Point"}
}