{
  "type": "Feature",
  "properties": {
    "addr:full":"Carrer de Narcis Monturiol, 1 Castelldefels Barcelona 08860",
    "addr:housenumber":"1",
    "addr:postcode":"08860",
    "addr:street":"Carrer De Narcis Monturiol",
    "iso:country":"ES",
    "sg:address":"Carrer de Narcis Monturiol, 1",
    "sg:city":"Castelldefels",
    "sg:orig_category":"Empresas De Carpinter\u00cda De Madera",
    "sg:phone":"+34 936 64 52 18",
    "sg:postcode":"08860",
    "sg:province":"Barcelona",
    "wof:name":"Torras Macias Juan",
    "wof:placetype":"venue"
},
  "geometry": {"coordinates":[1.9855719805,41.285194397],"type":"Point"}
}