{
  "type": "Feature",
  "properties": {
    "addr:full":"Calle de Margaritas, Las, S/n Siesta Islas Baleares 07840",
    "addr:housenumber":"/ n",
    "addr:postcode":"07840",
    "addr:street":"Calle De Margaritas Las S",
    "iso:country":"ES",
    "sg:address":"Calle de Margaritas, Las, S/n",
    "sg:city":"Siesta",
    "sg:orig_category":"Centros M\u00c9dicos Y Sociales, Dispensarios",
    "sg:phone":"+34 971 33 26 46",
    "sg:postcode":"07840",
    "sg:province":"Islas Baleares",
    "wof:name":"Kharsa Hamdan Abdel Wahab El",
    "wof:placetype":"venue"
},
  "geometry": {"coordinates":[1.5341850519,38.9850311279],"type":"Point"}
}