{
  "type": "Feature",
  "properties": {
    "addr:full":"Carrer de Dalt, 13 Sant Feliu Llobregat Barcelona 08980",
    "addr:housenumber":"13",
    "addr:postcode":"08980",
    "addr:street":"Carrer De Dalt",
    "iso:country":"ES",
    "sg:address":"Carrer de Dalt, 13",
    "sg:city":"Sant Feliu Llobregat",
    "sg:orig_category":"Semiller\u00cdas",
    "sg:phone":"+34 936 85 20 23",
    "sg:postcode":"08980",
    "sg:province":"Barcelona",
    "wof:name":"Invitro S.l",
    "wof:placetype":"venue"
},
  "geometry": {"coordinates":[2.0454490185,41.3828887939],"type":"Point"}
}