{
  "type": "Feature",
  "properties": {
    "iso:country":"ES",
    "sg:address":"Calle de Cristo De Medinaceli, 4",
    "sg:city":"Granada",
    "sg:orig_category":"Peluquer\u00cdas, Peluquer\u00cda Mixta",
    "sg:phone":"+34 958 52 12 89",
    "sg:postcode":"18002",
    "sg:province":"Granada",
    "wof:name":"Ia\u00f1ez Rodriguez Susana",
    "wof:placetype":"venue"
},
  "geometry": {"coordinates":[-3.6045517921,37.1713638306],"type":"Point"}
}