{
  "type": "Feature",
  "properties": {
    "addr:full":"Calle de Doctor Sumsi, 3 Valencia Valencia 46005",
    "addr:housenumber":"3",
    "addr:postcode":"46005",
    "addr:street":"Calle De Doctor Sumsi",
    "iso:country":"ES",
    "sg:address":"Calle de Doctor Sumsi, 3",
    "sg:city":"Valencia",
    "sg:orig_category":"Aparcamientos (infraestructuras, Accesorios)",
    "sg:phone":"+34 963 34 67 70",
    "sg:postcode":"46005",
    "sg:province":"Valencia",
    "wof:name":"Armumat S.l.",
    "wof:placetype":"venue"
},
  "geometry": {"coordinates":[-0.3691618145,39.4631996155],"type":"Point"}
}