{
  "type": "Feature",
  "properties": {
    "iso:country":"ES",
    "sg:address":"Carrer de Mariana Pineda, 4",
    "sg:city":"Barcelona",
    "sg:orig_category":"Institutos De Belleza",
    "sg:phone":"+34 932 18 35 73",
    "sg:postcode":"08012",
    "sg:province":"Barcelona",
    "wof:name":"Pubill Teixido Teresa",
    "wof:placetype":"venue"
},
  "geometry": {"coordinates":[2.1575219631,41.4007606506],"type":"Point"}
}