{
  "type": "Feature",
  "properties": {
    "iso:country":"ES",
    "sg:address":"Avgd Alcalde Porqueres, 2",
    "sg:city":"Lleida",
    "sg:orig_category":"M\u00c9dicos: An\u00c1lisis Cl\u00cdnicos",
    "sg:phone":"+34 973 23 94 85",
    "sg:postcode":"25008",
    "sg:province":"Lleida",
    "wof:name":"Anlisis Drs.massip/peremiquel",
    "wof:placetype":"venue"
},
  "geometry": {"coordinates":[0.6226816773,41.6206970215],"type":"Point"}
}