{
  "type": "Feature",
  "properties": {
    "addr:full":"Carrer de Muntaner, 62 Barcelona Barcelona 08011",
    "addr:housenumber":"62",
    "addr:postcode":"08011",
    "addr:street":"Carrer De Muntaner",
    "iso:country":"ES",
    "sg:address":"Carrer de Muntaner, 62",
    "sg:city":"Barcelona",
    "sg:orig_category":"Abogados",
    "sg:phone":"+34 934 51 69 79",
    "sg:postcode":"08011",
    "sg:province":"Barcelona",
    "wof:name":"Serrano Tuero Helena",
    "wof:placetype":"venue"
},
  "geometry": {"coordinates":[2.1592490673,41.3869438171],"type":"Point"}
}