{
  "type": "Feature",
  "properties": {
    "iso:country":"ES",
    "sg:address":"Calle de Alfahuir, 42",
    "sg:city":"Valencia",
    "sg:orig_category":"M\u00c9dicos: Neurolog\u00cda",
    "sg:phone":"+34 963 60 83 84",
    "sg:postcode":"46020",
    "sg:province":"Valencia",
    "wof:name":"Cruz Campos Guillermo Antonio",
    "wof:placetype":"venue"
},
  "geometry": {"coordinates":[-0.3636623025,39.4904060364],"type":"Point"}
}