{
  "type": "Feature",
  "properties": {
    "addr:full":"Rond Antoni Comas, 1 Mataro Barcelona 08303",
    "addr:housenumber":"1",
    "addr:postcode":"08303",
    "addr:street":"Rond Antoni Comas",
    "iso:country":"ES",
    "sg:address":"Rond Antoni Comas, 1",
    "sg:city":"Mataro",
    "sg:classifiers":[
        {
            "category":"Autos & Motor Vehicles",
            "subcategory":"Automobile Sales",
            "type":"Retail Goods"
        }
    ],
    "sg:phone":"+34 937 99 11 02",
    "sg:postcode":"08303",
    "sg:province":"Barcelona",
    "wof:name":"Autoescoles Freta S. C. Catalana Ltda.",
    "wof:placetype":"venue"
},
  "geometry": {"coordinates":[2.4326074123,41.5383453369],"type":"Point"}
}