{
  "type": "Feature",
  "properties": {
    "iso:country":"ES",
    "sg:address":"Pg Vilanova, 26",
    "sg:city":"Sitges",
    "sg:orig_category":"Sociedades, Compa\u00d1\u00cdas Aseguradoras",
    "sg:phone":"+34 938 94 09 48",
    "sg:postcode":"08870",
    "sg:province":"Barcelona",
    "wof:name":"Falco Esteva Antonio",
    "wof:placetype":"venue"
},
  "geometry": {"coordinates":[1.8048679829,41.2376937866],"type":"Point"}
}