{
  "type": "Feature",
  "properties": {
    "iso:country":"ES",
    "sg:address":"Don Tiburcio, 58",
    "sg:city":"Daimiel",
    "sg:orig_category":"Reposter\u00cdas",
    "sg:phone":"+34 926 85 44 16",
    "sg:postcode":"13250",
    "sg:province":"Ciudad Real",
    "wof:name":"Honrado Gonzalez Julian",
    "wof:placetype":"venue"
},
  "geometry": {"coordinates":[-3.6157410145,39.068069458],"type":"Point"}
}