{
  "type": "Feature",
  "properties": {
    "addr:full":"Calle de Garci-fernandez, 4 Huelva Huelva 21003",
    "addr:housenumber":"4",
    "addr:postcode":"21003",
    "addr:street":"Calle De Garci-Fernandez",
    "iso:country":"ES",
    "sg:address":"Calle de Garci-fernandez, 4",
    "sg:city":"Huelva",
    "sg:orig_category":"M\u00c9dicos: Otorrinolaringolog\u00cda",
    "sg:phone":"+34 959 24 55 96",
    "sg:postcode":"21003",
    "sg:province":"Huelva",
    "wof:name":"Gomez Moreno Araceli",
    "wof:placetype":"venue"
},
  "geometry": {"coordinates":[-6.9486317635,37.2549133301],"type":"Point"}
}