{
  "type": "Feature",
  "properties": {
    "addr:full":"Avda Estacion, 1 Pozoblanco C\u00f3rdoba 14400",
    "addr:housenumber":"1",
    "addr:postcode":"14400",
    "addr:street":"Avda Estacion",
    "iso:country":"ES",
    "sg:address":"Avda Estacion, 1",
    "sg:city":"Pozoblanco",
    "sg:orig_category":"Agencias Y Agentes Comerciales, Representantes",
    "sg:phone":"+34 957 77 34 05",
    "sg:postcode":"14400",
    "sg:province":"C\u00f3rdoba",
    "wof:name":"Vizcarro Castro Antonio",
    "wof:placetype":"venue"
},
  "geometry": {"coordinates":[-4.8538389206,38.3828239441],"type":"Point"}
}