{
  "type": "Feature",
  "properties": {
    "iso:country":"ES",
    "sg:address":"Carr President Macia, 139",
    "sg:city":"Palamos",
    "sg:orig_category":"Motocicletas (agentes, Concesionarios)",
    "sg:phone":"+34 972 60 14 44",
    "sg:postcode":"17230",
    "sg:province":"Girona",
    "wof:name":"Ferrer Maruny Nuria",
    "wof:placetype":"venue"
},
  "geometry": {"coordinates":[3.1208000183,41.8500099182],"type":"Point"}
}