{
  "type": "Feature",
  "properties": {
    "addr:full":"Carr Pi I Rallo, 7 Begur Girona 17255",
    "addr:housenumber":"7",
    "addr:postcode":"17255",
    "addr:street":"Carr Pi I Rallo",
    "iso:country":"ES",
    "sg:address":"Carr Pi I Rallo, 7",
    "sg:city":"Begur",
    "sg:orig_category":"Inmobiliaria (agencias)",
    "sg:phone":"+34 972 62 34 14",
    "sg:postcode":"17255",
    "sg:province":"Girona",
    "wof:name":"Promobegur S.l.",
    "wof:placetype":"venue"
},
  "geometry": {"coordinates":[3.2074611187,41.9548339844],"type":"Point"}
}