{
  "type": "Feature",
  "properties": {
    "addr:full":"Carr Corts Catalanes, 66 Lleida Lleida 25005",
    "addr:housenumber":"66",
    "addr:postcode":"25005",
    "addr:street":"Carr Corts Catalanes",
    "iso:country":"ES",
    "sg:address":"Carr Corts Catalanes, 66",
    "sg:city":"Lleida",
    "sg:orig_category":"Empresas De Pintura Y Revestimientos",
    "sg:phone":"+34 973 23 61 26",
    "sg:postcode":"25005",
    "sg:province":"Lleida",
    "wof:name":"Girones Franco Juan",
    "wof:placetype":"venue"
},
  "geometry": {"coordinates":[0.6229305267,41.6284942627],"type":"Point"}
}