{
  "type": "Feature",
  "properties": {
    "iso:country":"ES",
    "sg:address":"Calle de Padilla, 5",
    "sg:city":"Salamanca",
    "sg:orig_category":"Molduras, Junquillos, Listones Y Molduras Perforadas",
    "sg:phone":"+34 923 27 02 60",
    "sg:postcode":"37003",
    "sg:province":"Salamanca",
    "wof:name":"Espinazo Garcia Francisco",
    "wof:placetype":"venue"
},
  "geometry": {"coordinates":[-5.6573047638,40.9661369324],"type":"Point"}
}