{
  "type": "Feature",
  "properties": {
    "addr:full":"Urb Lunamar, 188 Elviria M\u00e1laga 29604",
    "addr:housenumber":"188",
    "addr:postcode":"29604",
    "addr:street":"Urb Lunamar;Ma\u0301Laga",
    "iso:country":"ES",
    "sg:address":"Urb Lunamar, 188",
    "sg:city":"Elviria",
    "sg:orig_category":"Asesor\u00cda Sobre Comunicaci\u00d3n De Empresas",
    "sg:phone":"+34 952 83 44 18",
    "sg:postcode":"29604",
    "sg:province":"M\u00e1laga",
    "wof:name":"Dos Peninsulas S.a.",
    "wof:placetype":"venue"
},
  "geometry": {"coordinates":[-4.7747840881,36.4966812134],"type":"Point"}
}