{
  "type": "Feature",
  "properties": {
    "iso:country":"ES",
    "sg:address":"Avgd Alfons Xiii, 117",
    "sg:city":"Badalona",
    "sg:orig_category":"Farmacias",
    "sg:phone":"+34 933 87 93 50",
    "sg:postcode":"08912",
    "sg:province":"Barcelona",
    "wof:name":"Casals Castro Rosa Maria",
    "wof:placetype":"venue"
},
  "geometry": {"coordinates":[2.2340478897,41.4424324036],"type":"Point"}
}