{
  "type": "Feature",
  "properties": {
    "addr:full":"Calle de El Calvario, S/n Balmaseda Vizcaya 48800",
    "addr:housenumber":"s / n",
    "addr:postcode":"48800",
    "addr:street":"Calle De El Calvario",
    "iso:country":"ES",
    "sg:address":"Calle de El Calvario, S/n",
    "sg:city":"Balmaseda",
    "sg:orig_category":"Peluquer\u00cdas, Peluquer\u00cda Mixta",
    "sg:phone":"+34 946 10 23 24",
    "sg:postcode":"48800",
    "sg:province":"Vizcaya",
    "wof:name":"Iraola Decos Juan Maria",
    "wof:placetype":"venue"
},
  "geometry": {"coordinates":[-3.1972200871,43.1932487488],"type":"Point"}
}