{
  "type": "Feature",
  "properties": {
    "addr:full":"Barr Santa Lucia, S/n Santiba\u00d1ez Cantabria 39509",
    "addr:postcode":"39509",
    "addr:street":"Lucia S / N",
    "iso:country":"ES",
    "sg:address":"Barr Santa Lucia, S/n",
    "sg:city":"Santiba\u00d1ez",
    "sg:orig_category":"Hilaturas, Hilos Y Actividades Relacionadas",
    "sg:phone":"+34 942 70 23 29",
    "sg:postcode":"39509",
    "sg:province":"Cantabria",
    "wof:name":"Textil Santanderina S.a.",
    "wof:placetype":"venue"
},
  "geometry": {"coordinates":[-4.2100739479,43.2973518372],"type":"Point"}
}