{
  "type": "Feature",
  "properties": {
    "addr:full":"Cno. Del Real, 13 Gallur Zaragoza 50650",
    "addr:housenumber":"13",
    "addr:postcode":"50650",
    "addr:street":"Cno. Del Real",
    "iso:country":"ES",
    "sg:address":"Cno. Del Real, 13",
    "sg:city":"Gallur",
    "sg:orig_category":"Conservas De Legumbres (fabricaci\u00d3n, Al Por Mayor)",
    "sg:phone":"+34 976 86 48 60",
    "sg:postcode":"50650",
    "sg:province":"Zaragoza",
    "wof:name":"Industrias Coquet S. A.",
    "wof:placetype":"venue"
},
  "geometry": {"coordinates":[-1.3145829439,41.8680229187],"type":"Point"}
}