{
  "type": "Feature",
  "properties": {
    "iso:country":"ES",
    "sg:address":"Calle de Tinte, 6",
    "sg:city":"Alcala Henares",
    "sg:orig_category":"Bisuter\u00cda, Joyer\u00cda, Relojer\u00cda (al Por Menor)",
    "sg:phone":"+34 918 82 70 96",
    "sg:postcode":"28801",
    "sg:province":"Madrid",
    "wof:name":"Sanchez Gutierrez Jose Maria",
    "wof:placetype":"venue"
},
  "geometry": {"coordinates":[-3.3643829823,40.4844284058],"type":"Point"}
}