{
  "type": "Feature",
  "properties": {
    "addr:full":"Rua Afonso X O Sabio, 1 Lugo Lugo 27002",
    "addr:housenumber":"1",
    "addr:postcode":"27002",
    "addr:street":"Rua Afonso X O Sabio",
    "iso:country":"ES",
    "sg:address":"Rua Afonso X O Sabio, 1",
    "sg:city":"Lugo",
    "sg:orig_category":"Librer\u00cdas",
    "sg:phone":"+34 982 25 02 01",
    "sg:postcode":"27002",
    "sg:province":"Lugo",
    "wof:name":"Saez Mancebo Javier",
    "wof:placetype":"venue"
},
  "geometry": {"coordinates":[-7.5550889969,42.9959983826],"type":"Point"}
}