{
  "type": "Feature",
  "properties": {
    "addr:full":"Vicent Blasco Iba\u00f1ez, 2 Sedavi Valencia 46910",
    "addr:housenumber":"2",
    "addr:postcode":"46910",
    "addr:street":"Iban\u0303Ez",
    "iso:country":"ES",
    "sg:address":"Vicent Blasco Iba\u00f1ez, 2",
    "sg:city":"Sedavi",
    "sg:orig_category":"Cl\u00cdnicas M\u00c9dicas",
    "sg:phone":"+34 963 75 50 50",
    "sg:postcode":"46910",
    "sg:province":"Valencia",
    "wof:name":"Baixauli Soria Carmen",
    "wof:placetype":"venue"
},
  "geometry": {"coordinates":[-0.3876489997,39.4255523682],"type":"Point"}
}