{
  "type": "Feature",
  "properties": {
    "addr:full":"Carrer de Ausias Marc, 4 Barcelona Barcelona 08010",
    "addr:housenumber":"4",
    "addr:postcode":"08010",
    "addr:street":"Carrer De Ausias Marc",
    "iso:country":"ES",
    "sg:address":"Carrer de Ausias Marc, 4",
    "sg:city":"Barcelona",
    "sg:orig_category":"Camiser\u00cda Y Ropa Interior Masculina (al Por Menor)",
    "sg:phone":"+34 934 12 31 36",
    "sg:postcode":"08010",
    "sg:province":"Barcelona",
    "wof:name":"Bluvert Difusion Sl",
    "wof:placetype":"venue"
},
  "geometry": {"coordinates":[2.1738750935,41.3898544312],"type":"Point"}
}