{
  "type": "Feature",
  "properties": {
    "iso:country":"ES",
    "sg:address":"Calle de Carril De Huete, Km. 0001,4",
    "sg:city":"Tarancon",
    "sg:orig_category":"Hormig\u00d3n Listo Para Usar",
    "sg:phone":"+34 969 32 02 22",
    "sg:postcode":"16400",
    "sg:province":"Cuenca",
    "wof:name":"Hormitan S.l.",
    "wof:placetype":"venue"
},
  "geometry": {"coordinates":[-2.9979581833,40.0026741028],"type":"Point"}
}