{
  "type": "Feature",
  "properties": {
    "addr:full":"Santas, S/n San Xurxo Touza Ourense 32691",
    "addr:housenumber":"s / n",
    "addr:postcode":"32691",
    "iso:country":"ES",
    "sg:address":"Santas, S/n",
    "sg:city":"San Xurxo Touza",
    "sg:orig_category":"Alimentaci\u00d3n General (al Por Mayor)",
    "sg:phone":"+34 988 43 64 13",
    "sg:postcode":"32691",
    "sg:province":"Ourense",
    "wof:name":"Valado Blanco Delmiro",
    "wof:placetype":"venue"
},
  "geometry": {"coordinates":[-7.8397169113,42.2497711182],"type":"Point"}
}