{
  "type": "Feature",
  "properties": {
    "addr:full":"Carrer de Amadeu Vives, 41 Hospitalet Llobregat Barcelona 08906",
    "addr:housenumber":"41",
    "addr:postcode":"08906",
    "addr:street":"Carrer De Amadeu Vives",
    "iso:country":"ES",
    "sg:address":"Carrer de Amadeu Vives, 41",
    "sg:city":"Hospitalet Llobregat",
    "sg:orig_category":"Artes Gr\u00c1ficas, Artes Pl\u00c1sticas (curso)",
    "sg:phone":"+34 934 38 68 09",
    "sg:postcode":"08906",
    "sg:province":"Barcelona",
    "wof:name":"Laser Grafic Blau Fort S.l.",
    "wof:placetype":"venue"
},
  "geometry": {"coordinates":[2.1026968956,41.3739967346],"type":"Point"}
}