{
  "type": "Feature",
  "properties": {
    "iso:country":"ES",
    "sg:address":"Carrer de Angel Guimera, 48",
    "sg:city":"S. Cugat Valles",
    "sg:orig_category":"Promotores Constructores",
    "sg:phone":"+34 936 74 40 12",
    "sg:postcode":"08172",
    "sg:province":"Barcelona",
    "wof:name":"Jimenez Jimenez Otilio",
    "wof:placetype":"venue"
},
  "geometry": {"coordinates":[2.0826699734,41.4645576477],"type":"Point"}
}