{
  "type": "Feature",
  "properties": {
    "iso:country":"ES",
    "sg:address":"Calle de Gudari Kalea, 12",
    "sg:city":"Tolosa",
    "sg:orig_category":"Frutas, Legumbres Frescas Y Tempranas (al Por Menor)",
    "sg:phone":"+34 943 65 13 46",
    "sg:postcode":"20400",
    "sg:province":"Guip\u00f9zcoa",
    "sg:website":"www.ekotolosa.com",
    "wof:name":"Eko Tolosa S.l.",
    "wof:placetype":"venue"
},
  "geometry": {"coordinates":[-2.0761220455,43.1334915161],"type":"Point"}
}