{
  "type": "Feature",
  "properties": {
    "iso:country":"ES",
    "sg:address":"Avda Eladio Perlado, 46",
    "sg:city":"Burgos",
    "sg:orig_category":"Ropa Para Se\u00d1oras (al Por Menor)",
    "sg:phone":"+34 947 22 98 78",
    "sg:postcode":"09007",
    "sg:province":"Burgos",
    "wof:name":"Internacional Comercio Trading S. L.",
    "wof:placetype":"venue"
},
  "geometry": {"coordinates":[-3.6671609879,42.3499336243],"type":"Point"}
}