{
  "type": "Feature",
  "properties": {
    "iso:country":"ES",
    "sg:address":"Plaz Mayor, 32",
    "sg:city":"Burgos",
    "sg:orig_category":"Organizaciones Profesionales",
    "sg:phone":"+34 947 20 98 81",
    "sg:postcode":"09003",
    "sg:province":"Burgos",
    "wof:name":"Ingenieria Asturiana Termoelectronica S.l.",
    "wof:placetype":"venue"
},
  "geometry": {"coordinates":[-3.7009689808,42.3413505554],"type":"Point"}
}