{
  "type": "Feature",
  "properties": {
    "addr:full":"Calle de Imeldo Seris, 37 Santa Cruz De Tenerife Santa Cruz De Tenerife 38003",
    "addr:housenumber":"37",
    "addr:postcode":"38003",
    "addr:street":"Calle De Imeldo Seris",
    "iso:country":"ES",
    "sg:address":"Calle de Imeldo Seris, 37",
    "sg:city":"Santa Cruz De Tenerife",
    "sg:orig_category":"Asesor\u00cda Fiscal Y Jur\u00cddica",
    "sg:phone":"+34 922 24 09 36",
    "sg:postcode":"38003",
    "sg:province":"Santa Cruz De Tenerife",
    "wof:name":"Nuria Morales S.l.",
    "wof:placetype":"venue"
},
  "geometry": {"coordinates":[-16.2513637543,28.4666461945],"type":"Point"}
}