{
  "type": "Feature",
  "properties": {
    "addr:full":"Avda Hermanos Felgueroso, 23 Gijon Asturias 33205",
    "addr:housenumber":"23",
    "addr:postcode":"33205",
    "addr:street":"Avda Hermanos Felgueroso",
    "iso:country":"ES",
    "sg:address":"Avda Hermanos Felgueroso, 23",
    "sg:city":"Gijon",
    "sg:orig_category":"Farmacias",
    "sg:phone":"+34 985 33 41 88",
    "sg:postcode":"33205",
    "sg:province":"Asturias",
    "wof:name":"Sanchez Suarez Jose Luis",
    "wof:placetype":"venue"
},
  "geometry": {"coordinates":[-5.65812397,43.5350265503],"type":"Point"}
}