{
  "type": "Feature",
  "properties": {
    "iso:country":"ES",
    "sg:address":"Calle de Juan Ramon Jimenez, 2",
    "sg:city":"Martos",
    "sg:orig_category":"Restaurantes",
    "sg:phone":"+34 953 55 03 37",
    "sg:postcode":"23600",
    "sg:province":"Ja\u00e9n",
    "wof:name":"Catering Pe\u00f1a-oliva, S.l.l",
    "wof:placetype":"venue"
},
  "geometry": {"coordinates":[-3.9711220264,37.7224693298],"type":"Point"}
}