{
  "type": "Feature",
  "properties": {
    "iso:country":"ES",
    "sg:address":"Ptge Mercat Del Fondo, S/n",
    "sg:city":"Santa Coloma De Gramenet",
    "sg:orig_category":"Frutas, Legumbres Frescas Y Tempranas (al Por Menor)",
    "sg:phone":"+34 934 68 12 71",
    "sg:postcode":"08922",
    "sg:province":"Barcelona",
    "wof:name":"Zu\u00f1iga Osuna Miguel",
    "wof:placetype":"venue"
},
  "geometry": {"coordinates":[2.2184698582,41.4496955872],"type":"Point"}
}