{
  "type": "Feature",
  "properties": {
    "iso:country":"ES",
    "sg:address":"Carrer de Ciclisme, 17",
    "sg:city":"Rubi",
    "sg:orig_category":"Ense\u00d1anza: Profesiones Art\u00cdsticas",
    "sg:phone":"+34 936 97 78 78",
    "sg:postcode":"08191",
    "sg:province":"Barcelona",
    "wof:name":"Estudios Nodom S.l.",
    "wof:placetype":"venue"
},
  "geometry": {"coordinates":[2.0377619267,41.5034103394],"type":"Point"}
}