{
  "type": "Feature",
  "properties": {
    "addr:full":"Calle de Gomez Salazar, 26 Le\u00f3n Le\u00f3n 24009",
    "addr:housenumber":"26",
    "addr:postcode":"24009",
    "addr:street":"Calle De Gomez Salazar;Leo\u0301N",
    "iso:country":"ES",
    "sg:address":"Calle de Gomez Salazar, 26",
    "sg:city":"Le\u00f3n",
    "sg:orig_category":"Iglesia Cat\u00d3lica",
    "sg:phone":"+34 987 20 86 59",
    "sg:postcode":"24009",
    "sg:province":"Le\u00f3n",
    "wof:name":"Parroquia San Francisco De La Vega",
    "wof:placetype":"venue"
},
  "geometry": {"coordinates":[-5.5845370293,42.5962638855],"type":"Point"}
}