{
  "type": "Feature",
  "properties": {
    "addr:full":"Calle de San Antonio, 63 Santa Cruz De Tenerife Santa Cruz De Tenerife 38001",
    "addr:housenumber":"63",
    "addr:postcode":"38001",
    "addr:street":"Calle De San Antonio",
    "iso:country":"ES",
    "sg:address":"Calle de San Antonio, 63",
    "sg:city":"Santa Cruz De Tenerife",
    "sg:orig_category":"Juristas",
    "sg:phone":"+34 922 28 49 77",
    "sg:postcode":"38001",
    "sg:province":"Santa Cruz De Tenerife",
    "wof:name":"Asesoria Laboral Del Castillo S.l.",
    "wof:placetype":"venue"
},
  "geometry": {"coordinates":[-16.2521629333,28.4734954834],"type":"Point"}
}