{
  "type": "Feature",
  "properties": {
    "addr:full":"Av Masnou, 10 Hospitalet Llobregat Barcelona 08905",
    "addr:housenumber":"10",
    "addr:postcode":"08905",
    "addr:street":"Av Masnou",
    "iso:country":"ES",
    "sg:address":"Av Masnou, 10",
    "sg:city":"Hospitalet Llobregat",
    "sg:orig_category":"Asesor\u00cda Sobre Comunicaci\u00d3n De Empresas",
    "sg:phone":"+34 934 37 62 14",
    "sg:postcode":"08905",
    "sg:province":"Barcelona",
    "wof:name":"Asesoria Y Proyectos Fro S.l.",
    "wof:placetype":"venue"
},
  "geometry": {"coordinates":[2.1065049171,41.3701934814],"type":"Point"}
}