{
  "type": "Feature",
  "properties": {
    "addr:full":"Avda Principe De Asturias, 51 Villaviciosa Odon Madrid 28670",
    "addr:housenumber":"51",
    "addr:postcode":"28670",
    "addr:street":"Avda Principe De Asturias;Odon",
    "iso:country":"ES",
    "sg:address":"Avda Principe De Asturias, 51",
    "sg:city":"Villaviciosa Odon",
    "sg:orig_category":"Cervecer\u00cdas",
    "sg:phone":"+34 916 16 32 24",
    "sg:postcode":"28670",
    "sg:province":"Madrid",
    "wof:name":"Gopdart Electronicos S.l.",
    "wof:placetype":"venue"
},
  "geometry": {"coordinates":[-3.8669540882,40.3543052673],"type":"Point"}
}