{
  "type": "Feature",
  "properties": {
    "addr:full":"Avda Parque De La Alamedilla, 2 Salamanca Salamanca 37003",
    "addr:housenumber":"2",
    "addr:postcode":"37003",
    "addr:street":"Avda Parque De La Alamedilla",
    "iso:country":"ES",
    "sg:address":"Avda Parque De La Alamedilla, 2",
    "sg:city":"Salamanca",
    "sg:orig_category":"Telas Para Tapizar, Cortinas, Pasamaner\u00cda (fabricaci\u00d3n, Al Por Mayor)",
    "sg:phone":"+34 923 27 20 89",
    "sg:postcode":"37003",
    "sg:province":"Salamanca",
    "wof:name":"Francisco De Cabo S.l.",
    "wof:placetype":"venue"
},
  "geometry": {"coordinates":[-5.6565971375,40.9683074951],"type":"Point"}
}