{
  "type": "Feature",
  "properties": {
    "iso:country":"ES",
    "sg:address":"Pase Delicias, S/n",
    "sg:city":"Villaverde Guadalimar",
    "sg:orig_category":"Centros De Educaci\u00d3n Especial",
    "sg:phone":"+34 967 43 40 42",
    "sg:postcode":"02460",
    "sg:province":"Albacete",
    "wof:name":"Cra Calar Del Mundo",
    "wof:placetype":"venue"
},
  "geometry": {"coordinates":[-2.5195789337,38.4563903809],"type":"Point"}
}