{
  "type": "Feature",
  "properties": {
    "addr:full":"Av Alacant, 66 Ondara Alicante 03760",
    "addr:housenumber":"66",
    "addr:postcode":"03760",
    "addr:street":"Alacant",
    "iso:country":"ES",
    "sg:address":"Av Alacant, 66",
    "sg:city":"Ondara",
    "sg:orig_category":"Fabricaci\u00d3n Y Venta De Volquetes Y Remolques",
    "sg:phone":"+34 966 47 72 15",
    "sg:postcode":"03760",
    "sg:province":"Alicante",
    "wof:name":"Josal C.b.",
    "wof:placetype":"venue"
},
  "geometry": {"coordinates":[0.0213610008,38.8227577209],"type":"Point"}
}