{
  "type": "Feature",
  "properties": {
    "addr:full":"Plaz Cervantes, 1 Miranda Ebro Burgos 09200",
    "addr:housenumber":"1",
    "addr:postcode":"09200",
    "addr:street":"Plaz Cervantes",
    "iso:country":"ES",
    "sg:address":"Plaz Cervantes, 1",
    "sg:city":"Miranda Ebro",
    "sg:orig_category":"Cajas De Ahorro",
    "sg:phone":"+34 947 34 77 40",
    "sg:postcode":"09200",
    "sg:province":"Burgos",
    "sg:website":"0487@cajaespana.es",
    "wof:name":"Caja Espa\u00f1a De Inversiones Caja De Ahorros Y Monte De Piedad",
    "wof:placetype":"venue"
},
  "geometry": {"coordinates":[-2.9524741173,42.6833839417],"type":"Point"}
}