{
  "type": "Feature",
  "properties": {
    "addr:full":"Calle de San Fernando, 12 Quintanar Orden Toledo 45800",
    "addr:housenumber":"12",
    "addr:postcode":"45800",
    "addr:street":"Calle De San Fernando",
    "iso:country":"ES",
    "sg:address":"Calle de San Fernando, 12",
    "sg:city":"Quintanar Orden",
    "sg:orig_category":"Alquiler De V\u00cddeo",
    "sg:phone":"+34 925 18 09 12",
    "sg:postcode":"45800",
    "sg:province":"Toledo",
    "wof:name":"Gonzalez  Daniela Carina",
    "wof:placetype":"venue"
},
  "geometry": {"coordinates":[-3.0446329117,39.5923347473],"type":"Point"}
}