{
  "type": "Feature",
  "properties": {
    "addr:full":"Calle de Bahia Blanca, 4 Malaga M\u00e1laga 29006",
    "addr:housenumber":"4",
    "addr:postcode":"29006",
    "addr:street":"Calle De Bahia Blanca;Ma\u0301Laga",
    "iso:country":"ES",
    "sg:address":"Calle de Bahia Blanca, 4",
    "sg:city":"Malaga",
    "sg:orig_category":"Seguridad En El Trabajo Y Prevenci\u00d3n De Riesgos Laborales",
    "sg:phone":"+34 952 35 74 45",
    "sg:postcode":"29006",
    "sg:province":"M\u00e1laga",
    "wof:name":"Corman Zona Sur S.a.",
    "wof:placetype":"venue"
},
  "geometry": {"coordinates":[-4.4750299454,36.7064628601],"type":"Point"}
}