{
  "type": "Feature",
  "properties": {
    "iso:country":"ES",
    "sg:address":"Plaz Constitucion (de La), 1",
    "sg:city":"Montemayor",
    "sg:orig_category":"C\u00c1maras De Comercio E Industria, Oficios, Agricultura",
    "sg:phone":"+34 957 38 40 17",
    "sg:postcode":"14530",
    "sg:province":"C\u00f3rdoba",
    "wof:name":"Camara Agraria Campina Sur",
    "wof:placetype":"venue"
},
  "geometry": {"coordinates":[-4.6990652084,37.6487998962],"type":"Point"}
}