{
  "type": "Feature",
  "properties": {
    "addr:full":"Av Riera, 13 S. Just Desvern Barcelona 08960",
    "addr:housenumber":"13",
    "addr:postcode":"08960",
    "addr:street":"Av Riera",
    "iso:country":"ES",
    "sg:address":"Av Riera, 13",
    "sg:city":"S. Just Desvern",
    "sg:orig_category":"Negocio De Metales No Ferrosos",
    "sg:phone":"+34 933 71 85 53",
    "sg:postcode":"08960",
    "sg:province":"Barcelona",
    "wof:name":"Valbruna Iberica S.l.",
    "wof:placetype":"venue"
},
  "geometry": {"coordinates":[2.0760960579,41.3924980164],"type":"Point"}
}