{
  "type": "Feature",
  "properties": {
    "iso:country":"ES",
    "sg:address":"Calle de Blanco, 1",
    "sg:city":"Puerto Cruz",
    "sg:orig_category":"Asesor\u00cda Sobre Comunicaci\u00d3n De Empresas",
    "sg:phone":"+34 922 38 23 80",
    "sg:postcode":"38400",
    "sg:province":"Santa Cruz De Tenerife",
    "wof:name":"Ebla Asesores S.c. Fiscal Contable",
    "wof:placetype":"venue"
},
  "geometry": {"coordinates":[-16.5503940582,28.4161205292],"type":"Point"}
}