{
  "type": "Feature",
  "properties": {
    "addr:full":"Calle de Arropieros, 7 Nerja M\u00e1laga 29780",
    "addr:housenumber":"7",
    "addr:postcode":"29780",
    "addr:street":"Calle De Arropieros",
    "iso:country":"ES",
    "sg:address":"Calle de Arropieros, 7",
    "sg:city":"Nerja",
    "sg:orig_category":"Promotores Constructores",
    "sg:phone":"+34 952 52 72 39",
    "sg:postcode":"29780",
    "sg:province":"M\u00e1laga",
    "wof:name":"Desarrollos Inmobiliarios Axarquia S.l.",
    "wof:placetype":"venue"
},
  "geometry": {"coordinates":[-3.8760876656,36.7480621338],"type":"Point"}
}