{
  "type": "Feature",
  "properties": {
    "addr:full":"Avda Fernandez Ladreda, 24 Segovia Segovia 40002",
    "addr:housenumber":"24",
    "addr:postcode":"40002",
    "addr:street":"Avda Fernandez Ladreda",
    "iso:country":"ES",
    "sg:address":"Avda Fernandez Ladreda, 24",
    "sg:city":"Segovia",
    "sg:orig_category":"Abogados",
    "sg:phone":"+34 921 46 17 75",
    "sg:postcode":"40002",
    "sg:province":"Segovia",
    "wof:name":"Sanz Castillo Jose Antonio",
    "wof:placetype":"venue"
},
  "geometry": {"coordinates":[-4.1201162338,40.9455413818],"type":"Point"}
}