{
  "type": "Feature",
  "properties": {
    "addr:full":"Calle de Beatos Mena Y Navarrete, 19 Logro\u00f1o La Rioja 26004",
    "addr:housenumber":"19",
    "addr:postcode":"26004",
    "addr:street":"Calle De Beatos Mena Y Navarrete;Rioja",
    "iso:country":"ES",
    "sg:address":"Calle de Beatos Mena Y Navarrete, 19",
    "sg:city":"Logro\u00f1o",
    "sg:orig_category":"Reposter\u00cdas",
    "sg:phone":"+34 941 24 67 22",
    "sg:postcode":"26004",
    "sg:province":"La Rioja",
    "wof:name":"Rubio Del Rio Miguel Angel",
    "wof:placetype":"venue"
},
  "geometry": {"coordinates":[-2.4317085743,42.4655570984],"type":"Point"}
}