{
  "type": "Feature",
  "properties": {
    "addr:full":"Carrer de Balmes, 209 Barcelona Barcelona 08006",
    "addr:housenumber":"209",
    "addr:postcode":"08006",
    "addr:street":"Carrer De Balmes",
    "iso:country":"ES",
    "sg:address":"Carrer de Balmes, 209",
    "sg:city":"Barcelona",
    "sg:orig_category":"Abogados",
    "sg:phone":"+34 934 15 72 28",
    "sg:postcode":"08006",
    "sg:province":"Barcelona",
    "wof:name":"Despatx Balmes 209 Scp",
    "wof:placetype":"venue"
},
  "geometry": {"coordinates":[2.1513040066,41.3980484009],"type":"Point"}
}