{
  "type": "Feature",
  "properties": {
    "iso:country":"ES",
    "sg:address":"Ctra Torija (de), Km. 0016,0",
    "sg:city":"Brihuega",
    "sg:orig_category":"Asociaciones, Organismos Culturales Y Socioeducativos",
    "sg:phone":"+34 949 28 06 23",
    "sg:postcode":"19400",
    "sg:province":"Guadalajara",
    "wof:name":"Fundacion Zendo Betania",
    "wof:placetype":"venue"
},
  "geometry": {"coordinates":[-2.8703289032,40.7592315674],"type":"Point"}
}