{
  "type": "Feature",
  "properties": {
    "addr:full":"Plaz Mayor, S/n Mariba\u00d1ez Sevilla 41727",
    "addr:housenumber":"s",
    "addr:postcode":"41727",
    "addr:street":"Plaz Mayor;/ N Mariban\u0303Ez",
    "iso:country":"ES",
    "sg:address":"Plaz Mayor, S/n",
    "sg:city":"Mariba\u00d1ez",
    "sg:orig_category":"Estancos",
    "sg:phone":"+34 955 89 62 26",
    "sg:postcode":"41727",
    "sg:province":"Sevilla",
    "wof:name":"Sierra Palacios Isabel Maria",
    "wof:placetype":"venue"
},
  "geometry": {"coordinates":[-5.8914427757,37.1339073181],"type":"Point"}
}