{
  "type": "Feature",
  "properties": {
    "addr:full":"Term. Sextil, S/n Lardero La Rioja 26140",
    "addr:housenumber":"s / n",
    "addr:postcode":"26140",
    "addr:street":"Sextil;Rioja",
    "iso:country":"ES",
    "sg:address":"Term. Sextil, S/n",
    "sg:city":"Lardero",
    "sg:orig_category":"Fabricaci\u00d3n De Muebles",
    "sg:phone":"+34 941 44 82 05",
    "sg:postcode":"26140",
    "sg:province":"La Rioja",
    "wof:name":"Manuel Pascual Salcedo Ramon S.a.",
    "wof:placetype":"venue"
},
  "geometry": {"coordinates":[-2.4627640247,42.4269752502],"type":"Point"}
}