{
  "type": "Feature",
  "properties": {
    "addr:full":"Avda General Mola (del), 166 Santa Cruz De Tenerife Santa Cruz De Tenerife 38007",
    "addr:housenumber":"166",
    "addr:postcode":"38007",
    "addr:street":"Avda General Mola Del",
    "iso:country":"ES",
    "sg:address":"Avda General Mola (del), 166",
    "sg:city":"Santa Cruz De Tenerife",
    "sg:orig_category":"Alimentaci\u00d3n General (al Por Menor)",
    "sg:phone":"+34 922 21 34 56",
    "sg:postcode":"38007",
    "sg:province":"Santa Cruz De Tenerife",
    "wof:name":"Rosa Diaz Genoveva De La Rosa",
    "wof:placetype":"venue"
},
  "geometry": {"coordinates":[-16.2713508606,28.4646968842],"type":"Point"}
}