{
  "type": "Feature",
  "properties": {
    "iso:country":"ES",
    "sg:address":"Pase Delicias, 106",
    "sg:city":"Madrid",
    "sg:orig_category":"Farmacias",
    "sg:phone":"+34 914 74 54 13",
    "sg:postcode":"28045",
    "sg:province":"Madrid",
    "wof:name":"Casarrubios Serrano Jose Luis",
    "wof:placetype":"venue"
},
  "geometry": {"coordinates":[-3.6946780682,40.3959274292],"type":"Point"}
}