{
  "type": "Feature",
  "properties": {
    "addr:full":"Av Catalunya (urb Pinalbert), 7 El Catllar Tarragona 43764",
    "addr:housenumber":"7",
    "addr:postcode":"43764",
    "addr:street":"Av Catalunya Urb Pinalbert",
    "iso:country":"ES",
    "sg:address":"Av Catalunya (urb Pinalbert), 7",
    "sg:city":"El Catllar",
    "sg:orig_category":"Centros Empresariales",
    "sg:phone":"+34 977 65 37 88",
    "sg:postcode":"43764",
    "sg:province":"Tarragona",
    "wof:name":"Catherall  Roger John",
    "wof:placetype":"venue"
},
  "geometry": {"coordinates":[1.3045899868,41.175983429],"type":"Point"}
}