{
  "type": "Feature",
  "properties": {
    "addr:full":"Calle de San Sebastian, 5 Hinojos Huelva 21740",
    "addr:housenumber":"5",
    "addr:postcode":"21740",
    "addr:street":"Calle De San Sebastian",
    "iso:country":"ES",
    "sg:address":"Calle de San Sebastian, 5",
    "sg:city":"Hinojos",
    "sg:orig_category":"Negocio De Materiales De Construcci\u00d3n",
    "sg:phone":"+34 959 45 96 67",
    "sg:postcode":"21740",
    "sg:province":"Huelva",
    "wof:name":"Perianez Garcia Juan Manuel",
    "wof:placetype":"venue"
},
  "geometry": {"coordinates":[-6.3799262047,37.2928504944],"type":"Point"}
}