{
  "type": "Feature",
  "properties": {
    "addr:full":"Calle de Sagunt, 50 Alzira Valencia 46600",
    "addr:housenumber":"50",
    "addr:postcode":"46600",
    "addr:street":"Calle De Sagunt",
    "iso:country":"ES",
    "sg:address":"Calle de Sagunt, 50",
    "sg:city":"Alzira",
    "sg:orig_category":"Veh\u00cdculos De Ocasi\u00d3n",
    "sg:phone":"+34 962 41 27 05",
    "sg:postcode":"46600",
    "sg:province":"Valencia",
    "wof:name":"Alcicar S. A.",
    "wof:placetype":"venue"
},
  "geometry": {"coordinates":[-0.4322103858,39.1480140686],"type":"Point"}
}