{
  "type": "Feature",
  "properties": {
    "addr:full":"Carr Sant Tomas, 48 Benicasim Castell\u00f3n 12560",
    "addr:housenumber":"48",
    "addr:postcode":"12560",
    "addr:street":"Carr Sant Tomas",
    "iso:country":"ES",
    "sg:address":"Carr Sant Tomas, 48",
    "sg:city":"Benicasim",
    "sg:orig_category":"M\u00c9dicos: Estomatolog\u00cda",
    "sg:phone":"+34 964 30 44 94",
    "sg:postcode":"12560",
    "sg:province":"Castell\u00f3n",
    "wof:name":"Aparici Simon Victorino",
    "wof:placetype":"venue"
},
  "geometry": {"coordinates":[0.0466559008,40.0530471802],"type":"Point"}
}