{
  "type": "Feature",
  "properties": {
    "addr:full":"Avgd Blasco Iba\u00d1ez, (de), S/n Carlet Valencia 46240",
    "addr:housenumber":"s",
    "addr:postcode":"46240",
    "addr:street":"/ N",
    "iso:country":"ES",
    "sg:address":"Avgd Blasco Iba\u00d1ez, (de), S/n",
    "sg:city":"Carlet",
    "sg:orig_category":"Centros De Educaci\u00d3n Especial",
    "sg:phone":"+34 962 53 10 30",
    "sg:postcode":"46240",
    "sg:province":"Valencia",
    "wof:name":"Generalitat Valenciana",
    "wof:placetype":"venue"
},
  "geometry": {"coordinates":[-0.5234889984,39.2276763916],"type":"Point"}
}