{
  "type": "Feature",
  "properties": {
    "iso:country":"ES",
    "sg:address":"Calle de Gladiadores, 5",
    "sg:city":"Consuegra",
    "sg:orig_category":"Confecci\u00d3n (fabricaci\u00d3n, Al Por Mayor)",
    "sg:phone":"+34 925 48 16 45",
    "sg:postcode":"45700",
    "sg:province":"Toledo",
    "wof:name":"Confecciones Oliveira S.l.",
    "wof:placetype":"venue"
},
  "geometry": {"coordinates":[-3.5994589329,39.4580307007],"type":"Point"}
}