{
  "type": "Feature",
  "properties": {
    "iso:country":"ES",
    "sg:address":"Calle de Antonia Ruiz Soro, 37",
    "sg:city":"Madrid",
    "sg:orig_category":"Ebanister\u00cda",
    "sg:phone":"+34 913 56 33 38",
    "sg:postcode":"28028",
    "sg:province":"Madrid",
    "wof:name":"Romero Tripiana Juan",
    "wof:placetype":"venue"
},
  "geometry": {"coordinates":[-3.6649518013,40.4383430481],"type":"Point"}
}