{
  "type": "Feature",
  "properties": {
    "addr:full":"Calle de Valencia, 19 Gijon Asturias 33210",
    "addr:housenumber":"19",
    "addr:postcode":"33210",
    "addr:street":"Calle De Valencia",
    "iso:country":"ES",
    "sg:address":"Calle de Valencia, 19",
    "sg:city":"Gijon",
    "sg:orig_category":"Molduras, Junquillos, Listones Y Molduras Perforadas",
    "sg:phone":"+34 985 14 61 84",
    "sg:postcode":"33210",
    "sg:province":"Asturias",
    "wof:name":"Noriega Tamargo Victor",
    "wof:placetype":"venue"
},
  "geometry": {"coordinates":[-5.6699662209,43.5276985168],"type":"Point"}
}