{
  "type": "Feature",
  "properties": {
    "iso:country":"ES",
    "sg:address":"Ptge Mozart, 13",
    "sg:city":"Sabadell",
    "sg:orig_category":"Agencias Y Agentes Comerciales, Representantes",
    "sg:phone":"+34 937 27 89 92",
    "sg:postcode":"08206",
    "sg:province":"Barcelona",
    "wof:name":"Serrano Rodriguez Montserrat",
    "wof:placetype":"venue"
},
  "geometry": {"coordinates":[2.0747048855,41.5592803955],"type":"Point"}
}