{
  "type": "Feature",
  "properties": {
    "addr:full":"Calle de Doctor Rojas Ballesteros, 2 Granada Granada 18012",
    "addr:housenumber":"2",
    "addr:postcode":"18012",
    "addr:street":"Calle De Doctor Rojas Ballesteros",
    "iso:country":"ES",
    "sg:address":"Calle de Doctor Rojas Ballesteros, 2",
    "sg:city":"Granada",
    "sg:orig_category":"Motocicletas (agentes, Concesionarios)",
    "sg:phone":"+34 958 17 02 67",
    "sg:postcode":"18012",
    "sg:province":"Granada",
    "wof:name":"Sanchez Cid Juan Ignacio",
    "wof:placetype":"venue"
},
  "geometry": {"coordinates":[-3.6069025993,37.1902809143],"type":"Point"}
}