{
  "type": "Feature",
  "properties": {
    "addr:full":"Carr Monturiol Narcis, 19 Cadaques Girona 17488",
    "addr:housenumber":"19",
    "addr:postcode":"17488",
    "addr:street":"Carr Monturiol Narcis",
    "iso:country":"ES",
    "sg:address":"Carr Monturiol Narcis, 19",
    "sg:city":"Cadaques",
    "sg:orig_category":"Empresas De Carpinter\u00cda De Madera",
    "sg:phone":"+34 972 25 80 07",
    "sg:postcode":"17488",
    "sg:province":"Girona",
    "wof:name":"Vila Torrens Joaquim",
    "wof:placetype":"venue"
},
  "geometry": {"coordinates":[3.2743530273,42.2883834839],"type":"Point"}
}