{
  "type": "Feature",
  "properties": {
    "addr:full":"Cmno Enmedio, 1 Puente Tocinos Murcia 30006",
    "addr:housenumber":"1",
    "addr:postcode":"30006",
    "addr:street":"Cmno Enmedio",
    "iso:country":"ES",
    "sg:address":"Cmno Enmedio, 1",
    "sg:city":"Puente Tocinos",
    "sg:orig_category":"Organizaci\u00d3n De Actos, Seminarios Y Congresos",
    "sg:phone":"+34 968 25 75 80",
    "sg:postcode":"30006",
    "sg:province":"Murcia",
    "wof:name":"Fernandez Perez Carmen",
    "wof:placetype":"venue"
},
  "geometry": {"coordinates":[-1.1008939743,37.9940185547],"type":"Point"}
}