{
  "type": "Feature",
  "properties": {
    "addr:full":"Calle de Pianista Amparo Iturbi, 60 Valencia Valencia 46006",
    "addr:housenumber":"60",
    "addr:postcode":"46006",
    "addr:street":"Calle De Pianista Amparo Iturbi",
    "iso:country":"ES",
    "sg:address":"Calle de Pianista Amparo Iturbi, 60",
    "sg:city":"Valencia",
    "sg:orig_category":"Electricidad: Equipos Industriales, Componentes (fabricaci\u00d3n)",
    "sg:phone":"+34 963 73 02 38",
    "sg:postcode":"46006",
    "sg:province":"Valencia",
    "wof:name":"Peque\u00d1o Material Electrico S.a.",
    "wof:placetype":"venue"
},
  "geometry": {"coordinates":[-0.3780190051,39.454158783],"type":"Point"}
}