{
  "type": "Feature",
  "properties": {
    "addr:full":"Calle de Sepulveda, 26 Madrid Madrid 28011",
    "addr:housenumber":"26",
    "addr:postcode":"madrid;28011",
    "addr:street":"Calle De Sepulveda",
    "iso:country":"ES",
    "sg:address":"Calle de Sepulveda, 26",
    "sg:city":"Madrid",
    "sg:orig_category":"Albergues",
    "sg:phone":"+34 914 70 18 63",
    "sg:postcode":"28011",
    "sg:province":"Madrid",
    "wof:name":"Prima Hosteleria S.l.",
    "wof:placetype":"venue"
},
  "geometry": {"coordinates":[-3.7380108833,40.4045829773],"type":"Point"}
}