{
  "type": "Feature",
  "properties": {
    "addr:full":"Ctra Pedroche-dos Torres, S/n Dos-torres C\u00f3rdoba 14460",
    "addr:postcode":"14460",
    "addr:street":"Ctra Pedroche-Dos Torres S / N Dos-Torres Co\u0301Rdoba",
    "iso:country":"ES",
    "sg:address":"Ctra Pedroche-dos Torres, S/n",
    "sg:city":"Dos-torres",
    "sg:orig_category":"Agricultura: Abastecimiento Y Cosechado (negocio)",
    "sg:phone":"+34 957 33 92 53",
    "sg:postcode":"14460",
    "sg:province":"C\u00f3rdoba",
    "wof:name":"Cooperativa Agropecuaria San Isidro",
    "wof:placetype":"venue"
},
  "geometry": {"coordinates":[-4.8952889442,38.4369010925],"type":"Point"}
}