{
  "type": "Feature",
  "properties": {
    "iso:country":"ES",
    "sg:address":"Carr Jaume Balmes, 25",
    "sg:city":"Quart Poblet",
    "sg:orig_category":"Asesor\u00cda Fiscal Y Jur\u00cddica",
    "sg:phone":"+34 961 54 74 07",
    "sg:postcode":"46930",
    "sg:province":"Valencia",
    "wof:name":"Gloria Soto Asesoria, Sl",
    "wof:placetype":"venue"
},
  "geometry": {"coordinates":[-0.4419890046,39.482711792],"type":"Point"}
}