{
  "type": "Feature",
  "properties": {
    "addr:full":"Calle de Humanitarias, 21 Madrid Madrid 28025",
    "addr:housenumber":"21",
    "addr:postcode":"madrid;28025",
    "addr:street":"Calle De Humanitarias",
    "iso:country":"ES",
    "sg:address":"Calle de Humanitarias, 21",
    "sg:city":"Madrid",
    "sg:orig_category":"Centros Empresariales",
    "sg:phone":"+34 914 61 85 01",
    "sg:postcode":"28025",
    "sg:province":"Madrid",
    "wof:name":"Gala Gala Maria Ines",
    "wof:placetype":"venue"
},
  "geometry": {"coordinates":[-3.7404470444,40.3878250122],"type":"Point"}
}