{
  "type": "Feature",
  "properties": {
    "addr:full":"Calle de Manuel Rojas Marcos, 26 Marchena Sevilla 41620",
    "addr:housenumber":"26",
    "addr:postcode":"41620",
    "addr:street":"Calle De Manuel Rojas Marcos",
    "iso:country":"ES",
    "sg:address":"Calle de Manuel Rojas Marcos, 26",
    "sg:city":"Marchena",
    "sg:orig_category":"Inmobiliaria (agencias)",
    "sg:phone":"+34 954 84 44 20",
    "sg:postcode":"41620",
    "sg:province":"Sevilla",
    "wof:name":"Guijarro Rustica Y Urbana S.l. Unipersonal",
    "wof:placetype":"venue"
},
  "geometry": {"coordinates":[-5.4168868065,37.3298530579],"type":"Point"}
}