{
  "type": "Feature",
  "properties": {
    "iso:country":"ES",
    "sg:address":"La Mina, 2",
    "sg:city":"Sese\u00f1a",
    "sg:orig_category":"Construcciones Met\u00c1licas",
    "sg:phone":"+34 918 08 82 55",
    "sg:postcode":"45223",
    "sg:province":"Toledo",
    "wof:name":"Bittal Sistemas Modulares S.l.",
    "wof:placetype":"venue"
},
  "geometry": {"coordinates":[-3.6779539585,40.1060447693],"type":"Point"}
}