{
  "type": "Feature",
  "properties": {
    "iso:country":"ES",
    "sg:address":"Calle de Obispo Salvador De Los Reyes, 57",
    "sg:city":"Malaga",
    "sg:orig_category":"Reposter\u00cdas",
    "sg:phone":"+34 952 26 30 47",
    "sg:postcode":"29014",
    "sg:province":"M\u00e1laga",
    "wof:name":"Panificadora Platero S.l.",
    "wof:placetype":"venue"
},
  "geometry": {"coordinates":[-4.423210144,36.765007019],"type":"Point"}
}