{
  "type": "Feature",
  "properties": {
    "iso:country":"ES",
    "sg:address":"Ocho De Septiembre, 1",
    "sg:city":"Lora Rio",
    "sg:orig_category":"Entrega Y Recogida (servicios)",
    "sg:phone":"+34 955 80 28 45",
    "sg:postcode":"41440",
    "sg:province":"Sevilla",
    "wof:name":"Hermanos Sanz Cepeda S.l.",
    "wof:placetype":"venue"
},
  "geometry": {"coordinates":[-5.5281639099,37.6591644287],"type":"Point"}
}