{
  "type": "Feature",
  "properties": {
    "addr:full":"Calle de Armi\u00d1an, 13 Ronda M\u00e1laga 29400",
    "addr:housenumber":"13",
    "addr:postcode":"29400",
    "addr:street":"Calle De Armin\u0303An;Ronda Ma\u0301Laga",
    "iso:country":"ES",
    "sg:address":"Calle de Armi\u00d1an, 13",
    "sg:city":"Ronda",
    "sg:orig_category":"Centros Empresariales",
    "sg:phone":"+34 952 87 49 58",
    "sg:postcode":"29400",
    "sg:province":"M\u00e1laga",
    "wof:name":"Fernandez Jimenez Antonio",
    "wof:placetype":"venue"
},
  "geometry": {"coordinates":[-5.1651034355,36.7382583618],"type":"Point"}
}