{
  "type": "Feature",
  "properties": {
    "addr:full":"Calle de Calvo Sotelo, 59 Logro\u00f1o La Rioja 26003",
    "addr:housenumber":"59",
    "addr:postcode":"26003",
    "addr:street":"Calle De Calvo Sotelo;Rioja",
    "iso:country":"ES",
    "sg:address":"Calle de Calvo Sotelo, 59",
    "sg:city":"Logro\u00f1o",
    "sg:orig_category":"Estancos",
    "sg:phone":"+34 941 23 03 67",
    "sg:postcode":"26003",
    "sg:province":"La Rioja",
    "wof:name":"Alonso Hierro Concepcion",
    "wof:placetype":"venue"
},
  "geometry": {"coordinates":[-2.4370007515,42.463848114],"type":"Point"}
}