{
  "type": "Feature",
  "properties": {
    "iso:country":"ES",
    "sg:address":"Pase Clara Campoamor, 11",
    "sg:city":"Mislata",
    "sg:orig_category":"Centros Empresariales",
    "sg:phone":"+34 963 83 73 75",
    "sg:postcode":"46920",
    "sg:province":"Valencia",
    "wof:name":"Alemany Orea Noelia",
    "wof:placetype":"venue"
},
  "geometry": {"coordinates":[-0.4182516038,39.4799499512],"type":"Point"}
}