{
  "type": "Feature",
  "properties": {
    "addr:full":"Calle de Menacho, 23 Badajoz Badajoz 06001",
    "addr:housenumber":"23",
    "addr:postcode":"06001",
    "addr:street":"Calle De Menacho",
    "iso:country":"ES",
    "sg:address":"Calle de Menacho, 23",
    "sg:city":"Badajoz",
    "sg:orig_category":"Ropa Para Se\u00d1oras (al Por Menor)",
    "sg:phone":"+34 924 22 25 00",
    "sg:postcode":"06001",
    "sg:province":"Badajoz",
    "wof:name":"Casaseca Casaseca Raquel",
    "wof:placetype":"venue"
},
  "geometry": {"coordinates":[-6.9738368988,38.8770751953],"type":"Point"}
}