{
  "type": "Feature",
  "properties": {
    "iso:country":"ES",
    "sg:address":"Calle de Cervera, 13",
    "sg:city":"Talavera Reina",
    "sg:orig_category":"Venta, Instalaci\u00d3n De Calefacci\u00d3n",
    "sg:phone":"+34 925 81 20 40",
    "sg:postcode":"45600",
    "sg:province":"Toledo",
    "wof:name":"Instalaciones Aurelio Plaza S.l.",
    "wof:placetype":"venue"
},
  "geometry": {"coordinates":[-4.8321018219,39.9663009644],"type":"Point"}
}