{
  "type": "Feature",
  "properties": {
    "addr:full":"Aguila, 1 Son Ferrer Islas Baleares 07182",
    "addr:postcode":"07182",
    "addr:street":"Aguila",
    "iso:country":"ES",
    "sg:address":"Aguila, 1",
    "sg:city":"Son Ferrer",
    "sg:orig_category":"Empresas De Carpinter\u00cda Met\u00c1lica",
    "sg:phone":"+34 971 23 09 88",
    "sg:postcode":"07182",
    "sg:province":"Islas Baleares",
    "wof:name":"Alumicerber S.l.l.",
    "wof:placetype":"venue"
},
  "geometry": {"coordinates":[2.5007221699,39.496887207],"type":"Point"}
}