{
  "type": "Feature",
  "properties": {
    "addr:full":"Avda Cruz Del Campo (la), 10 Sevilla Sevilla 41005",
    "addr:housenumber":"10",
    "addr:postcode":"41005",
    "addr:street":"Avda Cruz Del Campo La",
    "iso:country":"ES",
    "sg:address":"Avda Cruz Del Campo (la), 10",
    "sg:city":"Sevilla",
    "sg:orig_category":"Asociaciones Humanitarias, De Cooperaci\u00d3n, De Acci\u00d3n Social",
    "sg:phone":"+34 954 57 77 92",
    "sg:postcode":"41005",
    "sg:province":"Sevilla",
    "wof:name":"Asociacion Andaluza De Terapia Familiar",
    "wof:placetype":"venue"
},
  "geometry": {"coordinates":[-5.9652729034,37.3869552612],"type":"Point"}
}