{
  "type": "Feature",
  "properties": {
    "addr:full":"Carr Miralcamp, S/n Torregrossa Lleida 25141",
    "addr:housenumber":"s",
    "addr:postcode":"25141",
    "addr:street":"Carr Miralcamp;/ N",
    "iso:country":"ES",
    "sg:address":"Carr Miralcamp, S/n",
    "sg:city":"Torregrossa",
    "sg:orig_category":"Mec\u00c1nico Del Autom\u00d3vil",
    "sg:phone":"+34 973 17 10 10",
    "sg:postcode":"25141",
    "sg:province":"Lleida",
    "wof:name":"Cases Automocion S.l.u.",
    "wof:placetype":"venue"
},
  "geometry": {"coordinates":[0.8354049921,41.5819664001],"type":"Point"}
}