{
  "type": "Feature",
  "properties": {
    "addr:full":"Avda San Francisco Javier, 1 Sevilla Sevilla 41005",
    "addr:housenumber":"1",
    "addr:postcode":"41005",
    "addr:street":"Avda San Francisco Javier",
    "iso:country":"ES",
    "sg:address":"Avda San Francisco Javier, 1",
    "sg:city":"Sevilla",
    "sg:orig_category":"Agencias De Viajes",
    "sg:phone":"+34 954 65 66 00",
    "sg:postcode":"41005",
    "sg:province":"Sevilla",
    "wof:name":"Viajes Platon S.l.",
    "wof:placetype":"venue"
},
  "geometry": {"coordinates":[-5.9730682373,37.3821105957],"type":"Point"}
}