{
  "type": "Feature",
  "properties": {
    "iso:country":"ES",
    "sg:address":"Avda Barcelona, 4",
    "sg:city":"Jaen",
    "sg:orig_category":"Ingenier\u00cda, Centros De Estudios (diversos)",
    "sg:phone":"+34 953 25 80 52",
    "sg:postcode":"23006",
    "sg:province":"Ja\u00e9n",
    "wof:name":"Hurtado Parrilla Isaac",
    "wof:placetype":"venue"
},
  "geometry": {"coordinates":[-3.7987849712,37.7805900574],"type":"Point"}
}