{
  "type": "Feature",
  "properties": {
    "iso:country":"ES",
    "sg:address":"C. Buigas, 103",
    "sg:city":"Sta. Eulalia Ron\u00e7ana",
    "sg:orig_category":"Industria Qu\u00cdmica",
    "sg:phone":"+34 938 44 97 08",
    "sg:postcode":"08187",
    "sg:province":"Barcelona",
    "wof:name":"Cereria Maryam S.l.",
    "wof:placetype":"venue"
},
  "geometry": {"coordinates":[2.2300159931,41.6523895264],"type":"Point"}
}