{
  "type": "Feature",
  "properties": {
    "iso:country":"ES",
    "sg:address":"Calle de Claudio Moyano, 26",
    "sg:city":"Valladolid",
    "sg:orig_category":"Sociedades, Compa\u00d1\u00cdas Aseguradoras",
    "sg:phone":"+34 983 39 64 88",
    "sg:postcode":"47001",
    "sg:province":"Valladolid",
    "wof:name":"Santa Lucia S.a. Compa\u00d1ia De Seguros",
    "wof:placetype":"venue"
},
  "geometry": {"coordinates":[-4.7269201279,41.64894104],"type":"Point"}
}