{
  "type": "Feature",
  "properties": {
    "addr:full":"Carr Sant Josep, 6 Picanya Valencia 46210",
    "addr:housenumber":"6",
    "addr:postcode":"46210",
    "addr:street":"Carr Sant Josep",
    "iso:country":"ES",
    "sg:address":"Carr Sant Josep, 6",
    "sg:city":"Picanya",
    "sg:orig_category":"Electrodom\u00c9sticos (al Por Menor)",
    "sg:phone":"+34 961 59 17 71",
    "sg:postcode":"46210",
    "sg:province":"Valencia",
    "wof:name":"Rua Nemesio Maria Clara",
    "wof:placetype":"venue"
},
  "geometry": {"coordinates":[-0.4358580112,39.4345207214],"type":"Point"}
}