{
  "type": "Feature",
  "properties": {
    "addr:full":"Avda Badajoz, Km. 0095,5 Don Benito Badajoz 06400",
    "addr:postcode":"06400",
    "addr:street":"Avda Badajoz Km. 0095,5",
    "iso:country":"ES",
    "sg:address":"Avda Badajoz, Km. 0095,5",
    "sg:city":"Don Benito",
    "sg:orig_category":"Fabricaci\u00d3n De Muebles",
    "sg:phone":"+34 924 80 30 95",
    "sg:postcode":"06400",
    "sg:province":"Badajoz",
    "wof:name":"Gavesar Mobiliario S.l.",
    "wof:placetype":"venue"
},
  "geometry": {"coordinates":[-5.8750867844,38.9542579651],"type":"Point"}
}