{
  "type": "Feature",
  "properties": {
    "addr:full":"Calle de Carlos Iv, 8 Madrid Madrid 28037",
    "addr:housenumber":"8",
    "addr:postcode":"madrid;28037",
    "addr:street":"Calle De Carlos Iv",
    "iso:country":"ES",
    "sg:address":"Calle de Carlos Iv, 8",
    "sg:city":"Madrid",
    "sg:orig_category":"Cl\u00cdnicas M\u00c9dicas",
    "sg:phone":"+34 913 75 03 07",
    "sg:postcode":"28037",
    "sg:province":"Madrid",
    "wof:name":"Cubero Gonzalez Gladys S.l.",
    "wof:placetype":"venue"
},
  "geometry": {"coordinates":[-3.6179254055,40.4344482422],"type":"Point"}
}