{
  "type": "Feature",
  "properties": {
    "iso:country":"ES",
    "sg:address":"Calle de Ramiro I, 20",
    "sg:city":"Piedras Blancas",
    "sg:orig_category":"Panader\u00cdas, Panader\u00cdas",
    "sg:phone":"+34 985 50 73 27",
    "sg:postcode":"33450",
    "sg:province":"Asturias",
    "wof:name":"Emilio Vidal Conejo Roco Y Otros C.b.",
    "wof:placetype":"venue"
},
  "geometry": {"coordinates":[-5.9771051407,43.5605239868],"type":"Point"}
}