{
  "type": "Feature",
  "properties": {
    "addr:full":"Dema Entrevies, 6 Pinedes Tarragona 43006",
    "addr:housenumber":"6",
    "addr:postcode":"43006",
    "addr:street":"Entrevies",
    "iso:country":"ES",
    "sg:address":"Dema Entrevies, 6",
    "sg:city":"Pinedes",
    "sg:orig_category":"Empresas De Empaquetado, Embalajes Por Encargo",
    "sg:phone":"+34 977 55 47 41",
    "sg:postcode":"43006",
    "sg:province":"Tarragona",
    "wof:name":"Omya Clariana S.l.",
    "wof:placetype":"venue"
},
  "geometry": {"coordinates":[1.2209249735,41.1154441833],"type":"Point"}
}