{
  "type": "Feature",
  "properties": {
    "addr:full":"Calle de Serrano, 63 Madrid Madrid 28006",
    "addr:housenumber":"63",
    "addr:postcode":"madrid;28006",
    "addr:street":"Calle De Serrano",
    "iso:country":"ES",
    "sg:address":"Calle de Serrano, 63",
    "sg:city":"Madrid",
    "sg:orig_category":"Inmobiliaria (agencias)",
    "sg:phone":"+34 915 77 56 42",
    "sg:postcode":"28006",
    "sg:province":"Madrid",
    "sg:website":"www.ambassador-inmobiliaria.com",
    "wof:name":"Ambassador Real State S.l.",
    "wof:placetype":"venue"
},
  "geometry": {"coordinates":[-3.6867771149,40.4325218201],"type":"Point"}
}