{
  "type": "Feature",
  "properties": {
    "iso:country":"ES",
    "sg:address":"Calle de Ricardo Palma, 49",
    "sg:city":"Sevilla",
    "sg:orig_category":"Negocio De Materiales De Construcci\u00d3n",
    "sg:phone":"+34 954 63 09 48",
    "sg:postcode":"41006",
    "sg:province":"Sevilla",
    "wof:name":"Garcia Jimenez Juan Manuel",
    "wof:placetype":"venue"
},
  "geometry": {"coordinates":[-5.9462041855,37.3705444336],"type":"Point"}
}