{
  "type": "Feature",
  "properties": {
    "iso:country":"ES",
    "sg:address":"Avda Camelias, 67",
    "sg:city":"Vigo",
    "sg:orig_category":"Artes Gr\u00c1ficas, Artes Pl\u00c1sticas: Material Y Suministros (al Por Menor)",
    "sg:phone":"+34 986 42 12 37",
    "sg:postcode":"36211",
    "sg:province":"Pontevedra",
    "wof:name":"Tecnicas Del Mar Reunidas Sl",
    "wof:placetype":"venue"
},
  "geometry": {"coordinates":[-8.730340004,42.229057312],"type":"Point"}
}