{
  "type": "Feature",
  "properties": {
    "addr:full":"Calle de Puerto Neveros, S/n Nieves-el Lucero Madrid 28935",
    "addr:housenumber":"s / n",
    "addr:postcode":"28935",
    "addr:street":"Calle De Puerto Neveros;Nieves-El",
    "iso:country":"ES",
    "sg:address":"Calle de Puerto Neveros, S/n",
    "sg:city":"Nieves-el Lucero",
    "sg:orig_category":"Carnicer\u00cdas, Carnicer\u00cdas",
    "sg:phone":"+34 916 16 22 89",
    "sg:postcode":"28935",
    "sg:province":"Madrid",
    "wof:name":"Carnecerias H.m.s.l.",
    "wof:placetype":"venue"
},
  "geometry": {"coordinates":[-3.9280939102,40.3081817627],"type":"Point"}
}