{
  "type": "Feature",
  "properties": {
    "iso:country":"ES",
    "sg:address":"Pl Angels (dels), 5",
    "sg:city":"Montblanc",
    "sg:orig_category":"\u00d3ptica: Instrumentos (fabricaci\u00d3n)",
    "sg:phone":"+34 977 86 22 30",
    "sg:postcode":"43400",
    "sg:province":"Tarragona",
    "wof:name":"Sendra Potau Magi",
    "wof:placetype":"venue"
},
  "geometry": {"coordinates":[1.1626199484,41.3765945435],"type":"Point"}
}