{
  "type": "Feature",
  "properties": {
    "iso:country":"ES",
    "sg:address":"Carrer de Angel Ara\u00d1o, 32",
    "sg:city":"Viladecans",
    "sg:orig_category":"Arreglo, Reparaci\u00d3n, Piezas Sueltas De Televisi\u00d3n, V\u00cddeo, Hi",
    "sg:phone":"+34 936 58 58 53",
    "sg:postcode":"08840",
    "sg:province":"Barcelona",
    "wof:name":"Ramos Cabanillas Braulio",
    "wof:placetype":"venue"
},
  "geometry": {"coordinates":[2.0153620243,41.3200111389],"type":"Point"}
}