{
  "type": "Feature",
  "properties": {
    "iso:country":"ES",
    "sg:address":"Carrer de Erida, S/n",
    "sg:city":"Ardiaca",
    "sg:orig_category":"Supermercados Y Hipermercados",
    "sg:phone":"+34 977 36 44 68",
    "sg:postcode":"43850",
    "sg:province":"Tarragona",
    "wof:name":"Font Boronat Raul",
    "wof:placetype":"venue"
},
  "geometry": {"coordinates":[1.0611100197,41.0672683716],"type":"Point"}
}