{
  "type": "Feature",
  "properties": {
    "iso:country":"ES",
    "sg:address":"Ctra S. J. Rinconada, 88",
    "sg:city":"San Jose Rinconada",
    "sg:orig_category":"Sociedades, Compa\u00d1\u00cdas Aseguradoras",
    "sg:phone":"+34 955 79 09 00",
    "sg:postcode":"41300",
    "sg:province":"Sevilla",
    "wof:name":"Mapfre Servicios De Informatica S.a.",
    "wof:placetype":"venue"
},
  "geometry": {"coordinates":[-5.9434189796,37.443523407],"type":"Point"}
}