{
  "type": "Feature",
  "properties": {
    "iso:country":"ES",
    "sg:address":"Pase Florida, 47",
    "sg:city":"Madrid",
    "sg:orig_category":"Inmobiliaria (agencias)",
    "sg:phone":"+34 915 41 38 42",
    "sg:postcode":"28008",
    "sg:province":"Madrid",
    "wof:name":"Fernandez Garcia Juan Ignacio",
    "wof:placetype":"venue"
},
  "geometry": {"coordinates":[-3.7238709927,40.423374176],"type":"Point"}
}