{
  "type": "Feature",
  "properties": {
    "addr:full":"Rua Marques De Valterra, 15 Vigo Pontevedra 36202",
    "addr:housenumber":"15",
    "addr:postcode":"36202",
    "addr:street":"Rua Marques De Valterra",
    "iso:country":"ES",
    "sg:address":"Rua Marques De Valterra, 15",
    "sg:city":"Vigo",
    "sg:orig_category":"Venta, Montaje De Neum\u00c1ticos",
    "sg:phone":"+34 986 29 11 03",
    "sg:postcode":"36202",
    "sg:province":"Pontevedra",
    "wof:name":"Neumaticos Berbes S. L.",
    "wof:placetype":"venue"
},
  "geometry": {"coordinates":[-8.7322092056,42.2328681946],"type":"Point"}
}