{
  "type": "Feature",
  "properties": {
    "iso:country":"ES",
    "sg:address":"Calle de Huerta Chica, 31",
    "sg:city":"Zuera",
    "sg:orig_category":"Alimentaci\u00d3n General (al Por Menor)",
    "sg:phone":"+34 976 68 13 34",
    "sg:postcode":"50800",
    "sg:province":"Zaragoza",
    "wof:name":"Zufaria Instalaciones Sl",
    "wof:placetype":"venue"
},
  "geometry": {"coordinates":[-0.7870479822,41.8718185425],"type":"Point"}
}