{
  "type": "Feature",
  "properties": {
    "addr:full":"Calle de Puerto De Arlaban, 96 Madrid Madrid 28053",
    "addr:housenumber":"96",
    "addr:postcode":"madrid;28053",
    "addr:street":"Calle De Puerto De Arlaban",
    "iso:country":"ES",
    "sg:address":"Calle de Puerto De Arlaban, 96",
    "sg:city":"Madrid",
    "sg:orig_category":"Venta, Alquiler De Toldos",
    "sg:phone":"+34 914 78 05 16",
    "sg:postcode":"28053",
    "sg:province":"Madrid",
    "wof:name":"Sebastian Fernandez Placido",
    "wof:placetype":"venue"
},
  "geometry": {"coordinates":[-3.6694951057,40.3843231201],"type":"Point"}
}