{
  "type": "Feature",
  "properties": {
    "iso:country":"ES",
    "sg:address":"Calle de Centro Parroquial, 18",
    "sg:city":"Lodosa",
    "sg:orig_category":"Guarder\u00cdas",
    "sg:phone":"+34 948 69 36 27",
    "sg:postcode":"31580",
    "sg:province":"Navarra",
    "wof:name":"Ayuntamiento De Lodosa",
    "wof:placetype":"venue"
},
  "geometry": {"coordinates":[-2.0808842182,42.4226989746],"type":"Point"}
}