{
  "type": "Feature",
  "properties": {
    "iso:country":"ES",
    "sg:address":"Calle de Majuelo, 5",
    "sg:city":"Gines",
    "sg:orig_category":"Mec\u00c1nica Y Herramientas De Precisi\u00d3n",
    "sg:phone":"+34 954 71 51 73",
    "sg:postcode":"41960",
    "sg:province":"Sevilla",
    "sg:website":"www.centrotecnologia.com",
    "wof:name":"Centro Andaluz De Tecnologia Y Calidad S.l.u.",
    "wof:placetype":"venue"
},
  "geometry": {"coordinates":[-6.0736699104,37.3889045715],"type":"Point"}
}