{
  "type": "Feature",
  "properties": {
    "iso:country":"ES",
    "sg:address":"Pase Pamplona, 23",
    "sg:city":"Zaragoza",
    "sg:orig_category":"Ense\u00d1anza: Comercio, Gesti\u00d3n, Inform\u00c1tica",
    "sg:phone":"+34 976 21 51 87",
    "sg:postcode":"50004",
    "sg:province":"Zaragoza",
    "sg:website":"www.nett-formaci\u00f3n.net",
    "wof:name":"Nett Formacion",
    "wof:placetype":"venue"
},
  "geometry": {"coordinates":[-0.8874610066,41.6493759155],"type":"Point"}
}