{
  "type": "Feature",
  "properties": {
    "iso:country":"ES",
    "sg:address":"Ctra General Del Norte, 461",
    "sg:city":"Guamasa",
    "sg:orig_category":"Puertas Autom\u00c1ticas, Puertas De Garaje",
    "sg:phone":"+34 922 63 85 31",
    "sg:postcode":"38330",
    "sg:province":"Santa Cruz De Tenerife",
    "wof:name":"Pedro Corona S.a.",
    "wof:placetype":"venue"
},
  "geometry": {"coordinates":[-16.3748283386,28.4912605286],"type":"Point"}
}