{
  "type": "Feature",
  "properties": {
    "addr:full":"Pl J. R. Jimenez, S/n Rinconada Sevilla 41309",
    "addr:postcode":"41309",
    "addr:street":"Pl J. R. Jimenez S / N",
    "iso:country":"ES",
    "sg:address":"Pl J. R. Jimenez, S/n",
    "sg:city":"Rinconada",
    "sg:orig_category":"Ense\u00d1anza, Formaci\u00d3n Profesional: Aprendizaje",
    "sg:phone":"+34 955 79 37 78",
    "sg:postcode":"41309",
    "sg:province":"Sevilla",
    "wof:name":"Ayuntamiento De La Rinconada",
    "wof:placetype":"venue"
},
  "geometry": {"coordinates":[-5.9927000999,37.4076309204],"type":"Point"}
}