{
  "type": "Feature",
  "properties": {
    "addr:full":"Avda Diputacion, S/n San Sebastian De Los Ballesteros C\u00f3rdoba 14150",
    "addr:housenumber":"s / n",
    "addr:postcode":"14150",
    "addr:street":"Avda Diputacion;Co\u0301Rdoba",
    "iso:country":"ES",
    "sg:address":"Avda Diputacion, S/n",
    "sg:city":"San Sebastian De Los Ballesteros",
    "sg:orig_category":"Aceites Y Grasas Alimentarias (fabricaci\u00d3n, Al Por Mayor)",
    "sg:phone":"+34 957 30 91 97",
    "sg:postcode":"14150",
    "sg:province":"C\u00f3rdoba",
    "wof:name":"Cooperativa Olivarera San Sebastian",
    "wof:placetype":"venue"
},
  "geometry": {"coordinates":[-4.826526165,37.6518669128],"type":"Point"}
}