{
  "type": "Feature",
  "properties": {
    "iso:country":"ES",
    "sg:address":"Carrer de Maresme, 110",
    "sg:city":"Barcelona",
    "sg:orig_category":"Panader\u00cdas, Panader\u00cdas",
    "sg:phone":"+34 932 66 41 43",
    "sg:postcode":"08019",
    "sg:province":"Barcelona",
    "wof:name":"Caso Cobo Jose Luis",
    "wof:placetype":"venue"
},
  "geometry": {"coordinates":[2.2118170261,41.4154815674],"type":"Point"}
}