{
  "type": "Feature",
  "properties": {
    "iso:country":"ES",
    "sg:address":"Calle de Sagasta, 28",
    "sg:city":"Madrid",
    "sg:orig_category":"Molduras, Junquillos, Listones Y Molduras Perforadas",
    "sg:phone":"+34 914 46 70 42",
    "sg:postcode":"28004",
    "sg:province":"Madrid",
    "wof:name":"Sanz Bravo Jose Maria",
    "wof:placetype":"venue"
},
  "geometry": {"coordinates":[-3.6973969936,40.4278793335],"type":"Point"}
}