{
  "type": "Feature",
  "properties": {
    "addr:full":"Riera (la), 6 Mataro Barcelona 08301",
    "addr:postcode":"08301",
    "addr:street":"Riera La 6 Mataro Barcelona",
    "iso:country":"ES",
    "sg:address":"Riera (la), 6",
    "sg:city":"Mataro",
    "sg:orig_category":"Estilistas Y Estudios De Estilo De Corte Y Confecci\u00d3n",
    "sg:phone":"+34 937 90 40 84",
    "sg:postcode":"08301",
    "sg:province":"Barcelona",
    "wof:name":"Aledo Velasco Juan Carlos",
    "wof:placetype":"venue"
},
  "geometry": {"coordinates":[2.4449627399,41.5383682251],"type":"Point"}
}