{
  "type": "Feature",
  "properties": {
    "addr:full":"Camino Del Jueves, S/n Ogijares Granada 18151",
    "addr:housenumber":"s",
    "addr:postcode":"18151",
    "addr:street":"Camino Del Jueves;/ N Ogijares",
    "iso:country":"ES",
    "sg:address":"Camino Del Jueves, S/n",
    "sg:city":"Ogijares",
    "sg:orig_category":"Centros De Educaci\u00d3n Especial",
    "sg:phone":"+34 958 59 72 62",
    "sg:postcode":"18151",
    "sg:province":"Granada",
    "wof:name":"Junta De Andalucia",
    "wof:placetype":"venue"
},
  "geometry": {"coordinates":[-3.6047790051,37.1282157898],"type":"Point"}
}