{
  "type": "Feature",
  "properties": {
    "iso:country":"ES",
    "sg:address":"Ctra General Tajuya, 14",
    "sg:city":"Paso",
    "sg:orig_category":"Quincaller\u00cda (al Por Menor)",
    "sg:phone":"+34 922 48 61 14",
    "sg:postcode":"38750",
    "sg:province":"Santa Cruz De Tenerife",
    "wof:name":"Diaz Perez Jose Gregorio",
    "wof:placetype":"venue"
},
  "geometry": {"coordinates":[-17.8836021423,28.6484050751],"type":"Point"}
}