{
  "type": "Feature",
  "properties": {
    "addr:full":"Carrer de Blanquerna, 63 Palma Islas Baleares 07010",
    "addr:housenumber":"63",
    "addr:postcode":"07010",
    "addr:street":"Carrer De Blanquerna",
    "iso:country":"ES",
    "sg:address":"Carrer de Blanquerna, 63",
    "sg:city":"Palma",
    "sg:orig_category":"M\u00c9dicos: Estomatolog\u00cda",
    "sg:phone":"+34 971 20 62 67",
    "sg:postcode":"07010",
    "sg:province":"Islas Baleares",
    "wof:name":"Genovart Ribot Juan",
    "wof:placetype":"venue"
},
  "geometry": {"coordinates":[2.6487360001,39.5833587646],"type":"Point"}
}