{
  "type": "Feature",
  "properties": {
    "iso:country":"ES",
    "sg:address":"Avda Cesar Augusto, 115",
    "sg:city":"Zaragoza",
    "sg:orig_category":"Abogados",
    "sg:phone":"+34 976 28 06 68",
    "sg:postcode":"50003",
    "sg:province":"Zaragoza",
    "wof:name":"Gimenez Villanueva Carlos",
    "wof:placetype":"venue"
},
  "geometry": {"coordinates":[-0.8825179935,41.6568527222],"type":"Point"}
}