{
  "type": "Feature",
  "properties": {
    "addr:full":"Atva. Zaragoza-logro\u00f1o, Km. 0010,2 Utebo Zaragoza 50180",
    "addr:postcode":"50180",
    "addr:street":"Zaragoza-Logron\u0303O Km. 0010,2",
    "iso:country":"ES",
    "sg:address":"Atva. Zaragoza-logro\u00f1o, Km. 0010,2",
    "sg:city":"Utebo",
    "sg:orig_category":"Productos Qu\u00cdmicos (fabricaci\u00d3n, Al Por Mayor)",
    "sg:phone":"+34 976 78 82 24",
    "sg:postcode":"50180",
    "sg:province":"Zaragoza",
    "sg:website":"www.productosqp-quimicas.com",
    "wof:name":"Productos Q.p. S.a.",
    "wof:placetype":"venue"
},
  "geometry": {"coordinates":[-0.9998990297,41.7043800354],"type":"Point"}
}