{
  "type": "Feature",
  "properties": {
    "iso:country":"ES",
    "sg:address":"Calle de San Pedro, 32",
    "sg:city":"Lucena",
    "sg:orig_category":"M\u00c9dicos: Salud P\u00dablica",
    "sg:phone":"+34 957 51 04 01",
    "sg:postcode":"14900",
    "sg:province":"C\u00f3rdoba",
    "wof:name":"Serpremur S.l.",
    "wof:placetype":"venue"
},
  "geometry": {"coordinates":[-4.488503933,37.4077377319],"type":"Point"}
}