{
  "type": "Feature",
  "properties": {
    "iso:country":"ES",
    "sg:address":"Calle de Juan Xxiii, 19",
    "sg:city":"Santurtzi",
    "sg:orig_category":"Asesor\u00cda Sobre Comunicaci\u00d3n De Empresas",
    "sg:phone":"+34 944 83 92 51",
    "sg:postcode":"48980",
    "sg:province":"Vizcaya",
    "wof:name":"Asesoria Sirius S. L.",
    "wof:placetype":"venue"
},
  "geometry": {"coordinates":[-3.0347151756,43.3315658569],"type":"Point"}
}