{
  "type": "Feature",
  "properties": {
    "addr:full":"Calle de Eraso General, 12 Bilbao Vizcaya 48014",
    "addr:housenumber":"12",
    "addr:postcode":"48014",
    "addr:street":"Calle De Eraso General",
    "iso:country":"ES",
    "sg:address":"Calle de Eraso General, 12",
    "sg:city":"Bilbao",
    "sg:orig_category":"M\u00c9dicos: Estomatolog\u00cda",
    "sg:phone":"+34 944 05 38 78",
    "sg:postcode":"48014",
    "sg:province":"Vizcaya",
    "wof:name":"Clinica Dental, Ernesto Santaolalla Ayzagar,",
    "wof:placetype":"venue"
},
  "geometry": {"coordinates":[-2.9508728981,43.2706184387],"type":"Point"}
}