{
  "type": "Feature",
  "properties": {
    "addr:full":"Calle de Alonso Sanchez, 3 Huelva Huelva 21003",
    "addr:housenumber":"3",
    "addr:postcode":"21003",
    "addr:street":"Calle De Alonso Sanchez",
    "iso:country":"ES",
    "sg:address":"Calle de Alonso Sanchez, 3",
    "sg:city":"Huelva",
    "sg:orig_category":"Prot\u00c9sicos Dentales",
    "sg:phone":"+34 959 28 60 42",
    "sg:postcode":"21003",
    "sg:province":"Huelva",
    "wof:name":"Feria Limon Juan Jesus",
    "wof:placetype":"venue"
},
  "geometry": {"coordinates":[-6.9485650063,37.2541770935],"type":"Point"}
}