{
  "type": "Feature",
  "properties": {
    "addr:full":"Pol Ind El Monete, 110 Valverde Camino Huelva 21600",
    "addr:housenumber":"110",
    "addr:postcode":"21600",
    "addr:street":"Camino Huelva",
    "iso:country":"ES",
    "sg:address":"Pol Ind El Monete, 110",
    "sg:city":"Valverde Camino",
    "sg:orig_category":"Muebles, Minoristas",
    "sg:phone":"+34 959 55 37 24",
    "sg:postcode":"21600",
    "sg:province":"Huelva",
    "wof:name":"Muebles La Goleta S.l.",
    "wof:placetype":"venue"
},
  "geometry": {"coordinates":[-6.7534661293,37.576335907],"type":"Point"}
}