{
  "type": "Feature",
  "properties": {
    "iso:country":"ES",
    "sg:address":"Calle de Bureba, 6",
    "sg:city":"Leganes",
    "sg:classifiers":[
        {
            "category":"Autos & Motor Vehicles",
            "subcategory":"Automobile Sales",
            "type":"Retail Goods"
        }
    ],
    "sg:phone":"+34 916 87 84 89",
    "sg:postcode":"28915",
    "sg:province":"Madrid",
    "wof:name":"Autoescuela La Sagra",
    "wof:placetype":"venue"
},
  "geometry": {"coordinates":[-3.751224041,40.3330383301],"type":"Point"}
}