{
  "type": "Feature",
  "properties": {
    "iso:country":"ES",
    "sg:address":"Ptge Sant Mateu, 7",
    "sg:city":"Alcoi",
    "sg:orig_category":"Artes Gr\u00c1ficas, Artes Pl\u00c1sticas (curso)",
    "sg:phone":"+34 965 54 11 89",
    "sg:postcode":"03801",
    "sg:province":"Alicante",
    "wof:name":"Belda Martinez Francisco Jose",
    "wof:placetype":"venue"
},
  "geometry": {"coordinates":[-0.4747970104,38.695098877],"type":"Point"}
}