{
  "type": "Feature",
  "properties": {
    "addr:full":"Avda Valdecilla, 14 Santander Cantabria 39010",
    "addr:housenumber":"14",
    "addr:postcode":"39010",
    "addr:street":"Avda Valdecilla",
    "iso:country":"ES",
    "sg:address":"Avda Valdecilla, 14",
    "sg:city":"Santander",
    "sg:orig_category":"Distribuci\u00d3n De Petr\u00d3leo Y Derivados",
    "sg:phone":"+34 942 33 11 07",
    "sg:postcode":"39010",
    "sg:province":"Cantabria",
    "wof:name":"Estacion De Servicio Valdecilla",
    "wof:placetype":"venue"
},
  "geometry": {"coordinates":[-3.8100090027,43.4614982605],"type":"Point"}
}