{
  "type": "Feature",
  "properties": {
    "iso:country":"ES",
    "sg:address":"Calle de Juan Parras, 36",
    "sg:city":"Catarroja",
    "sg:orig_category":"Reposter\u00cdas",
    "sg:phone":"+34 961 26 22 35",
    "sg:postcode":"46470",
    "sg:province":"Valencia",
    "wof:name":"Yuste Sanz Santiago",
    "wof:placetype":"venue"
},
  "geometry": {"coordinates":[-0.4014990032,39.3976783752],"type":"Point"}
}