{
  "type": "Feature",
  "properties": {
    "iso:country":"ES",
    "sg:address":"Calle de Escuelas, 5",
    "sg:city":"Matapozuelos",
    "sg:orig_category":"Centros De Educaci\u00d3n Especial",
    "sg:phone":"+34 983 83 27 12",
    "sg:postcode":"47230",
    "sg:province":"Valladolid",
    "wof:name":"Colegio Rural Agrupado Rio Eresma",
    "wof:placetype":"venue"
},
  "geometry": {"coordinates":[-4.7898359299,41.4121513367],"type":"Point"}
}