{
  "type": "Feature",
  "properties": {
    "addr:full":"Avda Isabel De Moctezuma, 33 Caceres C\u00e1ceres 10005",
    "addr:housenumber":"33",
    "addr:postcode":"10005",
    "addr:street":"Avda Isabel De Moctezuma;Ca\u0301Ceres",
    "iso:country":"ES",
    "sg:address":"Avda Isabel De Moctezuma, 33",
    "sg:city":"Caceres",
    "sg:orig_category":"Materiales De Construcci\u00d3n, Herramientas",
    "sg:phone":"+34 927 24 46 07",
    "sg:postcode":"10005",
    "sg:province":"C\u00e1ceres",
    "wof:name":"Gomez Rivero Florencio",
    "wof:placetype":"venue"
},
  "geometry": {"coordinates":[-6.379160881,39.4614181519],"type":"Point"}
}