{
  "type": "Feature",
  "properties": {
    "iso:country":"ES",
    "sg:address":"Calle de San Isidro, 12",
    "sg:city":"Barrios",
    "sg:orig_category":"Supermercados Y Hipermercados",
    "sg:phone":"+34 956 62 31 04",
    "sg:postcode":"11370",
    "sg:province":"C\u00e1diz",
    "wof:name":"Supermercado Algeciras S.l.",
    "wof:placetype":"venue"
},
  "geometry": {"coordinates":[-5.4946498871,36.1863174438],"type":"Point"}
}