{
  "type": "Feature",
  "properties": {
    "addr:full":"Calle de Gran Via De Colon, 13 Granada Granada 18001",
    "addr:housenumber":"13",
    "addr:postcode":"18001",
    "addr:street":"Calle De Gran Via De Colon",
    "iso:country":"ES",
    "sg:address":"Calle de Gran Via De Colon, 13",
    "sg:city":"Granada",
    "sg:orig_category":"Fabricaci\u00d3n, Venta De Cuadros, Accesorios Para Enmarcar",
    "sg:phone":"+34 958 22 15 53",
    "sg:postcode":"18001",
    "sg:province":"Granada",
    "wof:name":"Hortal Marcos Miguel Angel",
    "wof:placetype":"venue"
},
  "geometry": {"coordinates":[-3.598500967,37.1772994995],"type":"Point"}
}