{
  "type": "Feature",
  "properties": {
    "addr:full":"Calle de Velez Malaga, 8 Malaga M\u00e1laga 29016",
    "addr:housenumber":"8",
    "addr:postcode":"29016",
    "addr:street":"Calle De Velez Malaga;Ma\u0301Laga",
    "iso:country":"ES",
    "sg:address":"Calle de Velez Malaga, 8",
    "sg:city":"Malaga",
    "sg:orig_category":"Bancos",
    "sg:phone":"+34 952 06 07 11",
    "sg:postcode":"29016",
    "sg:province":"M\u00e1laga",
    "wof:name":"Banco Popular Espa\u00f1ol S.a.",
    "wof:placetype":"venue"
},
  "geometry": {"coordinates":[-4.4109477997,36.7183418274],"type":"Point"}
}