{
  "type": "Feature",
  "properties": {
    "iso:country":"ES",
    "sg:address":"Avda Luis Braille, 14",
    "sg:city":"San Pedro Alcantara",
    "sg:orig_category":"Institutos De Belleza",
    "sg:phone":"+34 952 78 71 75",
    "sg:postcode":"29670",
    "sg:province":"M\u00e1laga",
    "wof:name":"Ramos Notario Francisco",
    "wof:placetype":"venue"
},
  "geometry": {"coordinates":[-4.9883098602,36.4825668335],"type":"Point"}
}