{
  "type": "Feature",
  "properties": {
    "iso:country":"ES",
    "sg:address":"Calle de Ansite, 22",
    "sg:city":"Cruce De Arinaga",
    "sg:orig_category":"\u00d3ptica: Instrumentos (fabricaci\u00d3n)",
    "sg:phone":"+34 928 18 31 31",
    "sg:postcode":"35118",
    "sg:province":"Las Palmas",
    "wof:name":"Artiles Estupi\u00f1an Maria Dolores",
    "wof:placetype":"venue"
},
  "geometry": {"coordinates":[-15.4299840927,27.8793811798],"type":"Point"}
}