{
  "type": "Feature",
  "properties": {
    "addr:full":"Avda General Marva, 7 Alacant Alicante 03005",
    "addr:housenumber":"7",
    "addr:postcode":"03005",
    "addr:street":"Avda General Marva",
    "iso:country":"ES",
    "sg:address":"Avda General Marva, 7",
    "sg:city":"Alacant",
    "sg:orig_category":"Arquitectos",
    "sg:phone":"+34 965 92 16 95",
    "sg:postcode":"03005",
    "sg:province":"Alicante",
    "sg:website":"www.grupoaranea.enet",
    "wof:name":"Territorio Aranea Sl",
    "wof:placetype":"venue"
},
  "geometry": {"coordinates":[-0.4914709926,38.3467330933],"type":"Point"}
}