{
  "type": "Feature",
  "properties": {
    "addr:full":"Avda Capuchinos, 63 Castellon Castell\u00f3n 12004",
    "addr:housenumber":"63",
    "addr:postcode":"12004",
    "addr:street":"Avda Capuchinos",
    "iso:country":"ES",
    "sg:address":"Avda Capuchinos, 63",
    "sg:city":"Castellon",
    "sg:orig_category":"Escuelas De Maternidad P\u00dablicas",
    "sg:phone":"+34 964 22 06 94",
    "sg:postcode":"12004",
    "sg:province":"Castell\u00f3n",
    "wof:name":"Espantaocells Sl",
    "wof:placetype":"venue"
},
  "geometry": {"coordinates":[-0.0333600007,39.9935150146],"type":"Point"}
}