{
  "type": "Feature",
  "properties": {
    "iso:country":"ES",
    "sg:address":"Rond Convento (del), S/n",
    "sg:city":"Ca\u00e7ete De Las Torres",
    "sg:orig_category":"Fabricaci\u00d3n De Harinas, S\u00c9molas, Productos De Elaboraci\u00d3n Del Grano",
    "sg:phone":"+34 957 18 30 73",
    "sg:postcode":"14660",
    "sg:province":"C\u00f3rdoba",
    "wof:name":"Industria Harinera San Miguel S.l.",
    "wof:placetype":"venue"
},
  "geometry": {"coordinates":[-4.3184690475,37.8673934937],"type":"Point"}
}