{
  "type": "Feature",
  "properties": {
    "addr:full":"Plaz Concepcion, 12 Villamalea Albacete 02270",
    "addr:housenumber":"12",
    "addr:postcode":"02270",
    "addr:street":"Plaz Concepcion",
    "iso:country":"ES",
    "sg:address":"Plaz Concepcion, 12",
    "sg:city":"Villamalea",
    "sg:orig_category":"Ropa Para Se\u00d1oras Y Caballeros (al Por Menor)",
    "sg:phone":"+34 967 48 61 61",
    "sg:postcode":"02270",
    "sg:province":"Albacete",
    "wof:name":"Jucar Jeans S.l.l.",
    "wof:placetype":"venue"
},
  "geometry": {"coordinates":[-1.5969090462,39.364200592],"type":"Point"}
}