{
  "type": "Feature",
  "properties": {
    "iso:country":"ES",
    "sg:address":"Pla\u00c7 Ajuntament, 6",
    "sg:city":"Figueres",
    "sg:orig_category":"Panader\u00cdas, Panader\u00cdas",
    "sg:phone":"+34 972 50 05 81",
    "sg:postcode":"17600",
    "sg:province":"Girona",
    "wof:name":"Lacasa Solanas Enrique",
    "wof:placetype":"venue"
},
  "geometry": {"coordinates":[2.9607179165,42.2671356201],"type":"Point"}
}