{
  "type": "Feature",
  "properties": {
    "addr:full":"Av Alcde L Uru\u00f1uela P. Congresos, S/n Sevilla Sevilla 41020",
    "addr:housenumber":"s / n",
    "addr:postcode":"41020",
    "addr:street":"Av Alcde L Urun\u0303Uela P. Congresos",
    "iso:country":"ES",
    "sg:address":"Av Alcde L Uru\u00f1uela P. Congresos, S/n",
    "sg:city":"Sevilla",
    "sg:orig_category":"Molduras, Junquillos, Listones Y Molduras Perforadas",
    "sg:phone":"+34 954 52 84 11",
    "sg:postcode":"41020",
    "sg:province":"Sevilla",
    "wof:name":"Explotacion Estacion De Servicio S.a.",
    "wof:placetype":"venue"
},
  "geometry": {"coordinates":[-5.9414181709,37.4022903442],"type":"Point"}
}