{
  "type": "Feature",
  "properties": {
    "addr:full":"Carrer de Gremi De Boters, 2 Poligon Industrial De Son Castello Islas Baleares 07009",
    "addr:housenumber":"2",
    "addr:postcode":"07009",
    "addr:street":"Carrer De Gremi De Boters;Islas",
    "iso:country":"ES",
    "sg:address":"Carrer de Gremi De Boters, 2",
    "sg:city":"Poligon Industrial De Son Castello",
    "sg:orig_category":"Mec\u00c1nico Del Autom\u00d3vil",
    "sg:phone":"+34 971 43 22 68",
    "sg:postcode":"07009",
    "sg:province":"Islas Baleares",
    "sg:website":"www.pginas-amarillas.es/on/line/tallermorey",
    "wof:name":"Talleres Morey S.l.",
    "wof:placetype":"venue"
},
  "geometry": {"coordinates":[2.6776249409,39.6072845459],"type":"Point"}
}