{
  "type": "Feature",
  "properties": {
    "iso:country":"ES",
    "sg:address":"Pol Ind Nevero, S/n",
    "sg:city":"Badajoz",
    "sg:orig_category":"Protecci\u00d3n Contra Robo (material E Instalaci\u00d3n)",
    "sg:phone":"+34 924 27 63 32",
    "sg:postcode":"06006",
    "sg:province":"Badajoz",
    "wof:name":"Instalaciones Y Seguridad Badajoz S.l.",
    "wof:placetype":"venue"
},
  "geometry": {"coordinates":[-7.0317192078,38.9165992737],"type":"Point"}
}