{
  "type": "Feature",
  "properties": {
    "addr:full":"Calle de Cervantes, 24 Casas De Fernando Alonso Cuenca 16610",
    "addr:housenumber":"24",
    "addr:postcode":"16610",
    "addr:street":"Calle De Cervantes",
    "iso:country":"ES",
    "sg:address":"Calle de Cervantes, 24",
    "sg:city":"Casas De Fernando Alonso",
    "sg:orig_category":"Centros De Educaci\u00d3n Especial",
    "sg:phone":"+34 969 38 31 49",
    "sg:postcode":"16610",
    "sg:province":"Cuenca",
    "wof:name":"Colegio Rural Agrupado Tomas Y Valiente",
    "wof:placetype":"venue"
},
  "geometry": {"coordinates":[-2.3291573524,39.3498840332],"type":"Point"}
}