{
  "type": "Feature",
  "properties": {
    "addr:full":"Carrer de Major, 6 Pego Alicante 03780",
    "addr:housenumber":"6",
    "addr:postcode":"03780",
    "addr:street":"Carrer De Major",
    "iso:country":"ES",
    "sg:address":"Carrer de Major, 6",
    "sg:city":"Pego",
    "sg:orig_category":"Fabricaci\u00d3n De Productos Textiles Sin Tejer",
    "sg:phone":"+34 965 57 02 63",
    "sg:postcode":"03780",
    "sg:province":"Alicante",
    "wof:name":"Confecciones Miralles C.b.",
    "wof:placetype":"venue"
},
  "geometry": {"coordinates":[-0.1172240004,38.8416442871],"type":"Point"}
}