{
  "type": "Feature",
  "properties": {
    "addr:full":"Carr Pi I Margall, 47 Lleida Lleida 25004",
    "addr:housenumber":"47",
    "addr:postcode":"25004",
    "addr:street":"Carr Pi I Margall",
    "iso:country":"ES",
    "sg:address":"Carr Pi I Margall, 47",
    "sg:city":"Lleida",
    "sg:orig_category":"Peluquer\u00cdas, Peluquer\u00cda Mixta",
    "sg:phone":"+34 973 23 03 17",
    "sg:postcode":"25004",
    "sg:province":"Lleida",
    "wof:name":"Marti Campisto Jovita",
    "wof:placetype":"venue"
},
  "geometry": {"coordinates":[0.626462996,41.6227226257],"type":"Point"}
}