{
  "type": "Feature",
  "properties": {
    "addr:full":"Calle de Francisco Rueda, 16 Pe\u00e7arroya-pueblonuevo C\u00f3rdoba 14200",
    "addr:housenumber":"16",
    "addr:postcode":"14200",
    "addr:street":"Calle De Francisco Rueda;Co\u0301Rdoba",
    "iso:country":"ES",
    "sg:address":"Calle de Francisco Rueda, 16",
    "sg:city":"Pe\u00e7arroya-pueblonuevo",
    "sg:orig_category":"Alimentaci\u00d3n General (al Por Menor)",
    "sg:phone":"+34 957 56 14 91",
    "sg:postcode":"14200",
    "sg:province":"C\u00f3rdoba",
    "wof:name":"Carrasco Aguado Francisco",
    "wof:placetype":"venue"
},
  "geometry": {"coordinates":[-5.2741441727,38.3066749573],"type":"Point"}
}