{
  "type": "Feature",
  "properties": {
    "iso:country":"ES",
    "sg:address":"C/ Arquebisbe Domenech, 19",
    "sg:city":"Alcoi",
    "sg:orig_category":"Turismo: Lugares, Circuitos Y Curiosidades",
    "sg:phone":"+34 965 33 01 12",
    "sg:postcode":"03804",
    "sg:province":"Alicante",
    "wof:name":"Masegosa S.l.",
    "wof:placetype":"venue"
},
  "geometry": {"coordinates":[-0.4639889896,38.7084083557],"type":"Point"}
}