{
  "type": "Feature",
  "properties": {
    "addr:full":"Avda Gomez Ferrer (doctor), 62 Catarroja Valencia 46470",
    "addr:housenumber":"62",
    "addr:postcode":"46470",
    "addr:street":"Avda Gomez Ferrer Doctor",
    "iso:country":"ES",
    "sg:address":"Avda Gomez Ferrer (doctor), 62",
    "sg:city":"Catarroja",
    "sg:orig_category":"Orquestas Cl\u00c1sicas, Asociaciones De M\u00dasica, Coros Y Corales",
    "sg:phone":"+34 961 27 43 39",
    "sg:postcode":"46470",
    "sg:province":"Valencia",
    "wof:name":"Union Musical De Catarroja",
    "wof:placetype":"venue"
},
  "geometry": {"coordinates":[-0.3983820081,39.4037513733],"type":"Point"}
}