{
  "type": "Feature",
  "properties": {
    "iso:country":"ES",
    "sg:address":"Santamaria-andre Mari Kalea, 35",
    "sg:city":"Ordizia",
    "sg:orig_category":"Droguer\u00cdas (al Por Menor)",
    "sg:phone":"+34 943 88 19 02",
    "sg:postcode":"20240",
    "sg:province":"Guip\u00f9zcoa",
    "wof:name":"Arrieta Arruabarrena Ignacio",
    "wof:placetype":"venue"
},
  "geometry": {"coordinates":[-2.1773040295,43.0538711548],"type":"Point"}
}