{
  "type": "Feature",
  "properties": {
    "addr:full":"Avda Andalucia, 18 Guillena Sevilla 41210",
    "addr:housenumber":"18",
    "addr:postcode":"41210",
    "addr:street":"Avda Andalucia",
    "iso:country":"ES",
    "sg:address":"Avda Andalucia, 18",
    "sg:city":"Guillena",
    "sg:orig_category":"Pod\u00d3logos: Pedicuros",
    "sg:phone":"+34 955 78 57 13",
    "sg:postcode":"41210",
    "sg:province":"Sevilla",
    "wof:name":"Aparicio Garcia Maria Del Rocio",
    "wof:placetype":"venue"
},
  "geometry": {"coordinates":[-6.0547485352,37.5398635864],"type":"Point"}
}