{
  "type": "Feature",
  "properties": {
    "addr:full":"Calle de Domingo Cuesta, 5 Motril Granada 18600",
    "addr:housenumber":"5",
    "addr:postcode":"18600",
    "addr:street":"Calle De Domingo Cuesta",
    "iso:country":"ES",
    "sg:address":"Calle de Domingo Cuesta, 5",
    "sg:city":"Motril",
    "sg:orig_category":"Infograf\u00cda",
    "sg:phone":"+34 958 82 32 90",
    "sg:postcode":"18600",
    "sg:province":"Granada",
    "wof:name":"Masegosa Botella Antonio Jose",
    "wof:placetype":"venue"
},
  "geometry": {"coordinates":[-3.5136005878,36.7471008301],"type":"Point"}
}