{
  "type": "Feature",
  "properties": {
    "iso:country":"ES",
    "sg:address":"Via Edison (de), 52",
    "sg:city":"Boisaca",
    "sg:orig_category":"Trabajos De Fotocomposici\u00d3n",
    "sg:phone":"+34 981 57 72 13",
    "sg:postcode":"15890",
    "sg:province":"La Coru\u00f1a",
    "wof:name":"4 Cromia S.l.",
    "wof:placetype":"venue"
},
  "geometry": {"coordinates":[-8.395969,43.37149],"type":"Point"}
}