{
  "type": "Feature",
  "properties": {
    "iso:country":"ES",
    "sg:address":"Calle de Fernando Guanarteme, 132",
    "sg:city":"Palmas De Gran Canaria",
    "sg:orig_category":"Muebles, Minoristas",
    "sg:phone":"+34 928 27 12 46",
    "sg:postcode":"35010",
    "sg:province":"Las Palmas",
    "wof:name":"Creaciones Cocinas S.l.",
    "wof:placetype":"venue"
},
  "geometry": {"coordinates":[-15.4413032532,28.1307353973],"type":"Point"}
}