{
  "type": "Feature",
  "properties": {
    "addr:full":"Carrer de Lluis Carulla, 62 Espluga Francoli Tarragona 43440",
    "addr:housenumber":"62",
    "addr:postcode":"43440",
    "addr:street":"Carrer De Lluis Carulla",
    "iso:country":"ES",
    "sg:address":"Carrer de Lluis Carulla, 62",
    "sg:city":"Espluga Francoli",
    "sg:orig_category":"Sociedades, Compa\u00d1\u00cdas Aseguradoras",
    "sg:phone":"+34 977 87 01 84",
    "sg:postcode":"43440",
    "sg:province":"Tarragona",
    "wof:name":"Reddis Conca S.l.",
    "wof:placetype":"venue"
},
  "geometry": {"coordinates":[1.0992749929,41.3950653076],"type":"Point"}
}