{
  "type": "Feature",
  "properties": {
    "iso:country":"ES",
    "sg:address":"Calle de Palma, 2",
    "sg:city":"Ciudad Real",
    "sg:orig_category":"Arreglo, Reparaci\u00d3n, Piezas Sueltas De Televisi\u00d3n, V\u00cddeo, Hi",
    "sg:phone":"+34 926 27 10 24",
    "sg:postcode":"13001",
    "sg:province":"Ciudad Real",
    "wof:name":"Colado Gomez Francisco",
    "wof:placetype":"venue"
},
  "geometry": {"coordinates":[-3.9269139767,38.9852638245],"type":"Point"}
}