{
  "type": "Feature",
  "properties": {
    "iso:country":"ES",
    "sg:address":"Av. Zaragoza, 25",
    "sg:city":"Iru\u00f1a",
    "sg:orig_category":"M\u00c9dicos: Estomatolog\u00cda",
    "sg:phone":"+34 948 24 11 47",
    "sg:postcode":"31005",
    "sg:province":"Navarra",
    "wof:name":"Artazcoz Artazcoz Maria Javier",
    "wof:placetype":"venue"
},
  "geometry": {"coordinates":[-1.643974781,42.8081283569],"type":"Point"}
}