{
  "type": "Feature",
  "properties": {
    "iso:country":"ES",
    "sg:address":"Calle de Casta\u00d1os, 22",
    "sg:city":"Alacant",
    "sg:orig_category":"Doctores En Medicina",
    "sg:phone":"+34 965 20 11 93",
    "sg:postcode":"03001",
    "sg:province":"Alicante",
    "wof:name":"Gomez Gimenez-giron Ramon",
    "wof:placetype":"venue"
},
  "geometry": {"coordinates":[-0.485370189,38.3452262878],"type":"Point"}
}