{
  "type": "Feature",
  "properties": {
    "addr:full":"Calle de Cervantes, 4 Utrera Sevilla 41710",
    "addr:housenumber":"4",
    "addr:postcode":"41710",
    "addr:street":"Calle De Cervantes",
    "iso:country":"ES",
    "sg:address":"Calle de Cervantes, 4",
    "sg:city":"Utrera",
    "sg:orig_category":"Electrodom\u00c9sticos (fabricaci\u00d3n, Al Por Mayor)",
    "sg:phone":"+34 955 86 00 72",
    "sg:postcode":"41710",
    "sg:province":"Sevilla",
    "wof:name":"Manuel Climent S.l.",
    "wof:placetype":"venue"
},
  "geometry": {"coordinates":[-5.7795138359,37.1814651489],"type":"Point"}
}