{
  "type": "Feature",
  "properties": {
    "addr:full":"Calle de Carlos Cervera, 18 Valencia Valencia 46006",
    "addr:housenumber":"18",
    "addr:postcode":"46006",
    "addr:street":"Calle De Carlos Cervera",
    "iso:country":"ES",
    "sg:address":"Calle de Carlos Cervera, 18",
    "sg:city":"Valencia",
    "sg:orig_category":"Mercer\u00cda, Lencer\u00cda (al Por Menor)",
    "sg:phone":"+34 963 74 70 21",
    "sg:postcode":"46006",
    "sg:province":"Valencia",
    "wof:name":"Marques Bea Leonardo",
    "wof:placetype":"venue"
},
  "geometry": {"coordinates":[-0.3726750016,39.4625816345],"type":"Point"}
}