{
  "type": "Feature",
  "properties": {
    "addr:full":"Calle de Vascos, 25 Madrid Madrid 28040",
    "addr:housenumber":"25",
    "addr:postcode":"madrid;28040",
    "addr:street":"Calle De Vascos",
    "iso:country":"ES",
    "sg:address":"Calle de Vascos, 25",
    "sg:city":"Madrid",
    "sg:orig_category":"Estilistas Y Estudios De Estilo De Corte Y Confecci\u00d3n",
    "sg:phone":"+34 915 33 54 79",
    "sg:postcode":"28040",
    "sg:province":"Madrid",
    "wof:name":"Besston Europa S.a.",
    "wof:placetype":"venue"
},
  "geometry": {"coordinates":[-3.7112770081,40.4486999512],"type":"Point"}
}