{
  "type": "Feature",
  "properties": {
    "iso:country":"ES",
    "sg:address":"Calle de Recinto Kalea, 1",
    "sg:city":"Ibero",
    "sg:orig_category":"Centros De Educaci\u00d3n Especial",
    "sg:phone":"+34 948 32 20 72",
    "sg:postcode":"31173",
    "sg:province":"Navarra",
    "wof:name":"Fundacion Caja Navarra",
    "wof:placetype":"venue"
},
  "geometry": {"coordinates":[-1.7800890207,42.812877655],"type":"Point"}
}