{
  "type": "Feature",
  "properties": {
    "iso:country":"ES",
    "sg:address":"Pase Russafa, 8",
    "sg:city":"Valencia",
    "sg:orig_category":"Sindicatos Y Colegios Profesionales",
    "sg:phone":"+34 963 94 43 75",
    "sg:postcode":"46002",
    "sg:province":"Valencia",
    "wof:name":"Asociacion Profesional De Empleados De Notaria",
    "wof:placetype":"venue"
},
  "geometry": {"coordinates":[-0.37531811,39.4684906006],"type":"Point"}
}