{
  "type": "Feature",
  "properties": {
    "iso:country":"ES",
    "sg:address":"Calle de Reina Fabiola, 16",
    "sg:city":"Zaragoza",
    "sg:orig_category":"Agencias Y Asesores De Publicidad",
    "sg:phone":"+34 976 59 77 26",
    "sg:postcode":"50008",
    "sg:province":"Zaragoza",
    "wof:name":"Publi-reto Sc",
    "wof:placetype":"venue"
},
  "geometry": {"coordinates":[-0.8739619851,41.6456451416],"type":"Point"}
}