{
  "type": "Feature",
  "properties": {
    "addr:full":"Gisastu Bide, 3 Eibar Guip\u00f9zcoa 20600",
    "addr:housenumber":"3",
    "addr:postcode":"20600",
    "addr:street":"Gisastu Bide;Guipu\u0300Zcoa",
    "iso:country":"ES",
    "sg:address":"Gisastu Bide, 3",
    "sg:city":"Eibar",
    "sg:orig_category":"Fabricaci\u00d3n Y Comercio De M\u00c1quinas",
    "sg:phone":"+34 943 12 05 00",
    "sg:postcode":"20600",
    "sg:province":"Guip\u00f9zcoa",
    "wof:name":"Talleres Aibe S.a.",
    "wof:placetype":"venue"
},
  "geometry": {"coordinates":[-2.4622480869,43.1862678528],"type":"Point"}
}