{
  "type": "Feature",
  "properties": {
    "addr:full":"Calle de Virrey Lopez Del Portillo, 3 Caparroso Navarra 31380",
    "addr:housenumber":"3",
    "addr:postcode":"31380",
    "addr:street":"Calle De Virrey Lopez Del Portillo",
    "iso:country":"ES",
    "sg:address":"Calle de Virrey Lopez Del Portillo, 3",
    "sg:city":"Caparroso",
    "sg:orig_category":"Bazares, Art\u00cdculos De Limpieza Y De Cocina (al Por Menor)",
    "sg:phone":"+34 948 73 06 74",
    "sg:postcode":"31380",
    "sg:province":"Navarra",
    "wof:name":"Cabero Hernandez Maria Rosario",
    "wof:placetype":"venue"
},
  "geometry": {"coordinates":[-1.646911025,42.3405952454],"type":"Point"}
}