{
  "type": "Feature",
  "properties": {
    "addr:full":"Calle de Pedro Miguel, 8 Sevilla Sevilla 41003",
    "addr:housenumber":"8",
    "addr:postcode":"41003",
    "addr:street":"Calle De Pedro Miguel",
    "iso:country":"ES",
    "sg:address":"Calle de Pedro Miguel, 8",
    "sg:city":"Sevilla",
    "sg:orig_category":"Asesor\u00cda Fiscal Y Jur\u00cddica",
    "sg:phone":"+34 954 91 58 21",
    "sg:postcode":"41003",
    "sg:province":"Sevilla",
    "wof:name":"Zarraga Guerrero Purificacion Lourdes",
    "wof:placetype":"venue"
},
  "geometry": {"coordinates":[-5.9900760651,37.3971748352],"type":"Point"}
}