{
  "type": "Feature",
  "properties": {
    "addr:full":"Aldapasoro Auzoa, 29 Etxarri-aranatz Navarra 31820",
    "addr:housenumber":"29",
    "addr:postcode":"31820",
    "addr:street":"Aldapasoro Auzoa",
    "iso:country":"ES",
    "sg:address":"Aldapasoro Auzoa, 29",
    "sg:city":"Etxarri-aranatz",
    "sg:orig_category":"Ferreter\u00cda (diversos)",
    "sg:phone":"+34 948 46 08 70",
    "sg:postcode":"31820",
    "sg:province":"Navarra",
    "wof:name":"Hierros Y Metales Joxan S.l.",
    "wof:placetype":"venue"
},
  "geometry": {"coordinates":[-2.0697770119,42.9053153992],"type":"Point"}
}