{
  "type": "Feature",
  "properties": {
    "iso:country":"ES",
    "sg:address":"Urbz Residencial Castilla, 46",
    "sg:city":"Argo\u00f1os",
    "sg:orig_category":"Postigos, Persianas Y Celos\u00cdas",
    "sg:phone":"+34 942 62 64 69",
    "sg:postcode":"39197",
    "sg:province":"Cantabria",
    "wof:name":"Fernandez Rodriguez Monica",
    "wof:placetype":"venue"
},
  "geometry": {"coordinates":[-3.4864890575,43.4572067261],"type":"Point"}
}