{
  "type": "Feature",
  "properties": {
    "addr:full":"Pda. Eral, 3 Termens Lleida 25670",
    "addr:housenumber":"3",
    "addr:postcode":"25670",
    "addr:street":"Termens Lleida",
    "iso:country":"ES",
    "sg:address":"Pda. Eral, 3",
    "sg:city":"Termens",
    "sg:orig_category":"Empresas De Desmonte",
    "sg:phone":"+34 973 18 00 86",
    "sg:postcode":"25670",
    "sg:province":"Lleida",
    "wof:name":"Voltes S.l.",
    "wof:placetype":"venue"
},
  "geometry": {"coordinates":[0.7865654826,41.7231216431],"type":"Point"}
}