{
  "type": "Feature",
  "properties": {
    "iso:country":"ES",
    "sg:address":"Carrer de Sant Pere, 4",
    "sg:city":"Playa De Calafell",
    "sg:orig_category":"Asesores De Gesti\u00d3n Del Patrimonio",
    "sg:phone":"+34 977 69 55 26",
    "sg:postcode":"43820",
    "sg:province":"Tarragona",
    "wof:name":"Fincas Acu\u00f1a S.l.",
    "wof:placetype":"venue"
},
  "geometry": {"coordinates":[1.5684100389,41.1977844238],"type":"Point"}
}