{
  "type": "Feature",
  "properties": {
    "iso:country":"ES",
    "sg:address":"Calle de Orden (la), S/n",
    "sg:city":"Yeste",
    "sg:orig_category":"Abogados",
    "sg:phone":"+34 967 43 13 39",
    "sg:postcode":"02480",
    "sg:province":"Albacete",
    "wof:name":"Lozano Roldan Manuel",
    "wof:placetype":"venue"
},
  "geometry": {"coordinates":[-2.3181610107,38.3681259155],"type":"Point"}
}