{
  "type": "Feature",
  "properties": {
    "iso:country":"ES",
    "sg:address":"Avda Buenos Aires, 33",
    "sg:city":"Utebo",
    "sg:orig_category":"Inmobiliaria (agencias)",
    "sg:phone":"+34 976 78 68 42",
    "sg:postcode":"50180",
    "sg:province":"Zaragoza",
    "wof:name":"Lujama S.a.",
    "wof:placetype":"venue"
},
  "geometry": {"coordinates":[-1.0032689571,41.7064285278],"type":"Point"}
}