{
  "type": "Feature",
  "properties": {
    "iso:country":"ES",
    "sg:address":"Camino De La Fresneda, S/n",
    "sg:city":"Campanillas",
    "sg:orig_category":"Ferreter\u00cda (diversos)",
    "sg:phone":"+34 952 43 31 68",
    "sg:postcode":"29590",
    "sg:province":"M\u00e1laga",
    "wof:name":"Olmedo Pelaez Andres",
    "wof:placetype":"venue"
},
  "geometry": {"coordinates":[-4.5224900246,36.7190055847],"type":"Point"}
}