{
  "type": "Feature",
  "properties": {
    "addr:full":"Calle de Romana, 15 Sevilla Sevilla 41020",
    "addr:housenumber":"15",
    "addr:postcode":"41020",
    "addr:street":"Calle De Romana",
    "iso:country":"ES",
    "sg:address":"Calle de Romana, 15",
    "sg:city":"Sevilla",
    "sg:orig_category":"Albergues",
    "sg:phone":"+34 954 67 06 11",
    "sg:postcode":"41020",
    "sg:province":"Sevilla",
    "wof:name":"Mali Business S.l.",
    "wof:placetype":"venue"
},
  "geometry": {"coordinates":[-5.9394907951,37.3937263489],"type":"Point"}
}