{
  "type": "Feature",
  "properties": {
    "iso:country":"ES",
    "sg:address":"Calle de Real, 69",
    "sg:city":"Torrenueva",
    "sg:orig_category":"Cajas Para Embalar",
    "sg:phone":"+34 926 34 10 51",
    "sg:postcode":"13740",
    "sg:province":"Ciudad Real",
    "wof:name":"Caja Rural De Ciudad Real",
    "wof:placetype":"venue"
},
  "geometry": {"coordinates":[-3.3653590679,38.6430091858],"type":"Point"}
}