{
  "type": "Feature",
  "properties": {
    "addr:full":"Calle de Salou, 1 Bilbao Vizcaya 48002",
    "addr:housenumber":"1",
    "addr:postcode":"48002",
    "addr:street":"Calle De Salou",
    "iso:country":"ES",
    "sg:address":"Calle de Salou, 1",
    "sg:city":"Bilbao",
    "sg:orig_category":"Mec\u00c1nico Del Autom\u00d3vil",
    "sg:phone":"+34 944 21 05 48",
    "sg:postcode":"48002",
    "sg:province":"Vizcaya",
    "wof:name":"Sahagun Yecora Mariano",
    "wof:placetype":"venue"
},
  "geometry": {"coordinates":[-2.9439480305,43.2519683838],"type":"Point"}
}