{
  "type": "Feature",
  "properties": {
    "addr:full":"Avda Padre Villoslada, 67 Baena C\u00f3rdoba 14850",
    "addr:housenumber":"67",
    "addr:postcode":"14850",
    "addr:street":"Avda Padre Villoslada",
    "iso:country":"ES",
    "sg:address":"Avda Padre Villoslada, 67",
    "sg:city":"Baena",
    "sg:orig_category":"Promotores Constructores",
    "sg:phone":"+34 957 69 18 17",
    "sg:postcode":"14850",
    "sg:province":"C\u00f3rdoba",
    "wof:name":"Agropecuaria Palasan S.l.",
    "wof:placetype":"venue"
},
  "geometry": {"coordinates":[-4.3140931129,37.6204490662],"type":"Point"}
}