{
  "type": "Feature",
  "properties": {
    "addr:full":"Calle de Molina, 61 Madrid Madrid 28029",
    "addr:housenumber":"61",
    "addr:postcode":"madrid;28029",
    "addr:street":"Calle De Molina",
    "iso:country":"ES",
    "sg:address":"Calle de Molina, 61",
    "sg:city":"Madrid",
    "sg:orig_category":"Parques De Atracciones Y Centros De Esparcimiento",
    "sg:phone":"+34 913 14 69 95",
    "sg:postcode":"28029",
    "sg:province":"Madrid",
    "wof:name":"Gestion De Archivos Peninsulares",
    "wof:placetype":"venue"
},
  "geometry": {"coordinates":[-3.7015960217,40.4711952209],"type":"Point"}
}