{
  "type": "Feature",
  "properties": {
    "addr:full":"Avda Rufo G Rendueles, 6 Gijon Asturias 33203",
    "addr:housenumber":"6",
    "addr:postcode":"33203",
    "addr:street":"Avda Rufo G Rendueles",
    "iso:country":"ES",
    "sg:address":"Avda Rufo G Rendueles, 6",
    "sg:city":"Gijon",
    "sg:orig_category":"Inform\u00c1tica: Material Y Suministros",
    "sg:phone":"+34 985 13 42 02",
    "sg:postcode":"33203",
    "sg:province":"Asturias",
    "sg:website":"www.green-soft.com",
    "wof:name":"Green Software S.l.",
    "wof:placetype":"venue"
},
  "geometry": {"coordinates":[-5.6486721039,43.5400810242],"type":"Point"}
}