{
  "type": "Feature",
  "properties": {
    "addr:full":"Calle de Republica Dominicana, 7 Palmas De Gran Canaria Las Palmas 35010",
    "addr:housenumber":"7",
    "addr:postcode":"35010",
    "addr:street":"Calle De Republica Dominicana",
    "iso:country":"ES",
    "sg:address":"Calle de Republica Dominicana, 7",
    "sg:city":"Palmas De Gran Canaria",
    "sg:orig_category":"Impuestos, Tesoro P\u00dablico",
    "sg:phone":"+34 928 22 08 82",
    "sg:postcode":"35010",
    "sg:province":"Las Palmas",
    "wof:name":"Sociedad Canaria De Comprobacion S.l.l.",
    "wof:placetype":"venue"
},
  "geometry": {"coordinates":[-15.4385585785,28.1331195831],"type":"Point"}
}