{
  "type": "Feature",
  "properties": {
    "iso:country":"ES",
    "sg:address":"Capitan Cortes, 41",
    "sg:city":"Rianxo",
    "sg:orig_category":"Molduras, Junquillos, Listones Y Molduras Perforadas",
    "sg:phone":"+34 981 86 02 86",
    "sg:postcode":"15920",
    "sg:province":"La Coru\u00f1a",
    "wof:name":"Rodriguez Queiruga Serafin",
    "wof:placetype":"venue"
},
  "geometry": {"coordinates":[-8.8172187805,42.6528091431],"type":"Point"}
}