{
  "type": "Feature",
  "properties": {
    "addr:full":"Ctra Arcos-bosque (el), Km. 0002,0 Arcos Frontera C\u00e1diz 11630",
    "addr:postcode":"11630",
    "addr:street":"Ctra Arcos-Bosque El Km. 0002,0 Arcos;Ca\u0301Diz",
    "iso:country":"ES",
    "sg:address":"Ctra Arcos-bosque (el), Km. 0002,0",
    "sg:city":"Arcos Frontera",
    "sg:orig_category":"Negocio De Materiales De Construcci\u00d3n",
    "sg:phone":"+34 956 70 84 09",
    "sg:postcode":"11630",
    "sg:province":"C\u00e1diz",
    "wof:name":"Materiales La Plata S.l.",
    "wof:placetype":"venue"
},
  "geometry": {"coordinates":[-5.8115739822,36.7515716553],"type":"Point"}
}