{
  "type": "Feature",
  "properties": {
    "addr:full":"Carrer de Tarragona (de), 14 Tortosa Tarragona 43500",
    "addr:housenumber":"14",
    "addr:postcode":"43500",
    "addr:street":"Carrer De Tarragona De",
    "iso:country":"ES",
    "sg:address":"Carrer de Tarragona (de), 14",
    "sg:city":"Tortosa",
    "sg:orig_category":"Ropa Para Caballeros (al Por Menor)",
    "sg:phone":"+34 977 50 08 55",
    "sg:postcode":"43500",
    "sg:province":"Tarragona",
    "wof:name":"Granell Vallespi Gemma",
    "wof:placetype":"venue"
},
  "geometry": {"coordinates":[0.5160350204,40.8138084412],"type":"Point"}
}