{
  "type": "Feature",
  "properties": {
    "addr:full":"Calle de Trasmallo, 26 Pto. Rosario Las Palmas 35600",
    "addr:housenumber":"26",
    "addr:postcode":"35600",
    "addr:street":"Calle De Trasmallo;Pto. Rosario Las",
    "iso:country":"ES",
    "sg:address":"Calle de Trasmallo, 26",
    "sg:city":"Pto. Rosario",
    "sg:orig_category":"Industria Qu\u00cdmica",
    "sg:phone":"+34 928 53 26 33",
    "sg:postcode":"35600",
    "sg:province":"Las Palmas",
    "sg:website":"www.proquimia.com",
    "wof:name":"Proquimia S.a.",
    "wof:placetype":"venue"
},
  "geometry": {"coordinates":[-13.8644685745,28.5023498535],"type":"Point"}
}