{
  "type": "Feature",
  "properties": {
    "iso:country":"ES",
    "sg:address":"Calle de Juan Crisostomo Arriaga, 5",
    "sg:city":"Palomares Rio",
    "sg:orig_category":"Partidos Pol\u00cdticos",
    "sg:phone":"+34 955 76 34 15",
    "sg:postcode":"41928",
    "sg:province":"Sevilla",
    "wof:name":"Partido Socialista Obrero Espa\u00f1ol",
    "wof:placetype":"venue"
},
  "geometry": {"coordinates":[-6.0600137711,37.3244018555],"type":"Point"}
}