{
  "type": "Feature",
  "properties": {
    "iso:country":"ES",
    "sg:address":"Avda Prim, 41",
    "sg:city":"Lora Rio",
    "sg:orig_category":"Muebles, Minoristas",
    "sg:phone":"+34 955 80 23 83",
    "sg:postcode":"41440",
    "sg:province":"Sevilla",
    "wof:name":"Muebles Garisol S.l.",
    "wof:placetype":"venue"
},
  "geometry": {"coordinates":[-5.5270152092,37.6608123779],"type":"Point"}
}