{
  "type": "Feature",
  "properties": {
    "addr:full":"Pase Deleite (del), 34 Aranjuez Madrid 28300",
    "addr:postcode":"28300",
    "iso:country":"ES",
    "sg:address":"Pase Deleite (del), 34",
    "sg:city":"Aranjuez",
    "sg:orig_category":"Sociedades, Compa\u00d1\u00cdas Aseguradoras",
    "sg:phone":"+34 918 92 05 32",
    "sg:postcode":"28300",
    "sg:province":"Madrid",
    "sg:website":"www.mapfre.es",
    "wof:name":"Mapfre Servicios De Informatica S.a.",
    "wof:placetype":"venue"
},
  "geometry": {"coordinates":[-3.6042790413,40.0360946655],"type":"Point"}
}