{
  "type": "Feature",
  "properties": {
    "iso:country":"ES",
    "sg:address":"Calle de Torrelodones, 19",
    "sg:city":"Galapagar",
    "sg:orig_category":"Institutos De Belleza",
    "sg:phone":"+34 918 58 32 79",
    "sg:postcode":"28260",
    "sg:province":"Madrid",
    "wof:name":"Belleza Elia S.a.",
    "wof:placetype":"venue"
},
  "geometry": {"coordinates":[-4.0014820099,40.5774002075],"type":"Point"}
}