{
  "type": "Feature",
  "properties": {
    "addr:full":"Avda Mediterraneo, S/n Cuenca Cuenca 16004",
    "addr:postcode":"16004",
    "addr:street":"Avda Mediterraneo S / N",
    "iso:country":"ES",
    "sg:address":"Avda Mediterraneo, S/n",
    "sg:city":"Cuenca",
    "sg:orig_category":"Tiendas De Grano, Frutas Y Legumbres Secas (al Por Menor)",
    "sg:phone":"+34 969 22 78 90",
    "sg:postcode":"16004",
    "sg:province":"Cuenca",
    "wof:name":"Productos Alimenticios Belros S.a.",
    "wof:placetype":"venue"
},
  "geometry": {"coordinates":[-2.126019001,40.057056427],"type":"Point"}
}