{
  "type": "Feature",
  "properties": {
    "iso:country":"ES",
    "sg:address":"Calle de Yecla, 12",
    "sg:city":"Sax",
    "sg:orig_category":"Marroquiner\u00cda (confecci\u00d3n)",
    "sg:phone":"+34 965 47 59 55",
    "sg:postcode":"03630",
    "sg:province":"Alicante",
    "wof:name":"Alarik S.l",
    "wof:placetype":"venue"
},
  "geometry": {"coordinates":[-0.8203468919,38.5364837646],"type":"Point"}
}