{
  "type": "Feature",
  "properties": {
    "iso:country":"ES",
    "sg:address":"Calle de Justiniano, 3",
    "sg:city":"Madrid",
    "sg:orig_category":"Compraventa De Antig\u00dcedades",
    "sg:phone":"+34 913 19 21 03",
    "sg:postcode":"28004",
    "sg:province":"Madrid",
    "wof:name":"Anticarte 2004 S.l.",
    "wof:placetype":"venue"
},
  "geometry": {"coordinates":[-3.6952733994,40.4257850647],"type":"Point"}
}