{
  "type": "Feature",
  "properties": {
    "iso:country":"ES",
    "sg:address":"Cta. Almendral, 8",
    "sg:city":"Calicasas",
    "sg:orig_category":"Alquiler De Veh\u00cdculos: Turismos Y Utilitarios",
    "sg:phone":"+34 958 40 96 03",
    "sg:postcode":"18290",
    "sg:province":"Granada",
    "wof:name":"Autocares Martin Corral S.l.",
    "wof:placetype":"venue"
},
  "geometry": {"coordinates":[-3.6205220222,37.2737960815],"type":"Point"}
}