{
  "type": "Feature",
  "properties": {
    "addr:full":"Calle de Virgen De Regla, 1 Sevilla Sevilla 41011",
    "addr:housenumber":"1",
    "addr:postcode":"41011",
    "addr:street":"Calle De Virgen De Regla",
    "iso:country":"ES",
    "sg:address":"Calle de Virgen De Regla, 1",
    "sg:city":"Sevilla",
    "sg:orig_category":"Promotores Constructores",
    "sg:phone":"+34 954 27 12 00",
    "sg:postcode":"41011",
    "sg:province":"Sevilla",
    "sg:website":"www.navicoas.com",
    "wof:name":"Industrial Comercial Aspe S. A.",
    "wof:placetype":"venue"
},
  "geometry": {"coordinates":[-5.9962849617,37.3775405884],"type":"Point"}
}