{
  "type": "Feature",
  "properties": {
    "iso:country":"ES",
    "sg:address":"Edisson (p I Jose Martin Mendez), S/n",
    "sg:city":"Estepona",
    "sg:orig_category":"Ense\u00d1anza, Formaci\u00d3n Profesional: Aprendizaje",
    "sg:phone":"+34 952 79 34 53",
    "sg:postcode":"29680",
    "sg:province":"M\u00e1laga",
    "wof:name":"Ayuntamiento De Estepona",
    "wof:placetype":"venue"
},
  "geometry": {"coordinates":[-5.1744904518,36.4435119629],"type":"Point"}
}