{
  "type": "Feature",
  "properties": {
    "addr:full":"Carrer de Estacio (de L'), 30 Aldea Tarragona 43896",
    "addr:housenumber":"30",
    "addr:postcode":"43896",
    "addr:street":"Carrer De Estacio De L '",
    "iso:country":"ES",
    "sg:address":"Carrer de Estacio (de L'), 30",
    "sg:city":"Aldea",
    "sg:orig_category":"Ropa Para Se\u00d1oras (al Por Menor)",
    "sg:phone":"+34 977 45 06 04",
    "sg:postcode":"43896",
    "sg:province":"Tarragona",
    "wof:name":"Esther Mayoral S.l.",
    "wof:placetype":"venue"
},
  "geometry": {"coordinates":[0.6252809763,40.7500076294],"type":"Point"}
}