{
  "type": "Feature",
  "properties": {
    "iso:country":"ES",
    "sg:address":"Avda Primero De Mayo, 48",
    "sg:city":"Palmas De Gran Canaria",
    "sg:orig_category":"Abogados",
    "sg:phone":"+34 928 38 51 48",
    "sg:postcode":"35002",
    "sg:province":"Las Palmas",
    "wof:name":"Redondo Rodriguez Miguel",
    "wof:placetype":"venue"
},
  "geometry": {"coordinates":[-15.4197721481,28.1057662964],"type":"Point"}
}