{
  "type": "Feature",
  "properties": {
    "iso:country":"ES",
    "sg:address":"Tras La Iglesia, S/n",
    "sg:city":"Vegadeo",
    "sg:orig_category":"Pescader\u00cdas (al Por Menor)",
    "sg:phone":"+34 985 47 62 35",
    "sg:postcode":"33770",
    "sg:province":"Asturias",
    "wof:name":"Fernandez Fernandez Fernando",
    "wof:placetype":"venue"
},
  "geometry": {"coordinates":[-7.0507240295,43.464225769],"type":"Point"}
}