{
  "type": "Feature",
  "properties": {
    "iso:country":"ES",
    "sg:address":"Urb. Nueva Andalucia, S/n",
    "sg:city":"Nueva Andalucia",
    "sg:classifiers":[
        {
            "category":"Sports & Exercise",
            "subcategory":"Golf",
            "type":"Entertainment"
        }
    ],
    "sg:phone":"+34 952 81 14 28",
    "sg:postcode":"29660",
    "sg:province":"M\u00e1laga",
    "sg:tags":[
        "y",
        "de",
        "campos",
        "clases"
    ],
    "wof:name":"Los Naranjos Campo De Golf S.l.",
    "wof:placetype":"venue"
},
  "geometry": {"coordinates":[-4.9541988373,36.5097084045],"type":"Point"}
}