{
  "type": "Feature",
  "properties": {
    "iso:country":"ES",
    "sg:address":"Calle de Victoria, 8",
    "sg:city":"Olvera",
    "sg:orig_category":"Farmacias",
    "sg:phone":"+34 956 13 07 01",
    "sg:postcode":"11690",
    "sg:province":"C\u00e1diz",
    "wof:name":"Arenas Morales Angel",
    "wof:placetype":"venue"
},
  "geometry": {"coordinates":[-5.263838768,36.9349517822],"type":"Point"}
}