{
  "type": "Feature",
  "properties": {
    "iso:country":"ES",
    "sg:address":"Calle de Calleja La, 8",
    "sg:city":"Valverde Camino",
    "sg:orig_category":"Cajas Para Embalar",
    "sg:phone":"+34 959 55 07 71",
    "sg:postcode":"21600",
    "sg:province":"Huelva",
    "sg:website":"www.ruralvia.com",
    "wof:name":"Caja Rural Del Sur Sociedad Cooperativa",
    "wof:placetype":"venue"
},
  "geometry": {"coordinates":[-6.7534661293,37.576335907],"type":"Point"}
}