{
  "type": "Feature",
  "properties": {
    "addr:full":"Calle de Camino De Albolote, 2 Maracena Granada 18200",
    "addr:housenumber":"2",
    "addr:postcode":"18200",
    "addr:street":"Calle De Camino De Albolote",
    "iso:country":"ES",
    "sg:address":"Calle de Camino De Albolote, 2",
    "sg:city":"Maracena",
    "sg:orig_category":"Centros Empresariales",
    "sg:phone":"+34 958 42 05 56",
    "sg:postcode":"18200",
    "sg:province":"Granada",
    "wof:name":"Martin Ortega Andres",
    "wof:placetype":"venue"
},
  "geometry": {"coordinates":[-3.6371071339,37.2142448425],"type":"Point"}
}