{
  "type": "Feature",
  "properties": {
    "addr:full":"Paseo Larrabarri Ibilbidea, 1 Derio Vizcaya 48160",
    "addr:housenumber":"1",
    "addr:postcode":"48160",
    "addr:street":"Paseo Larrabarri Ibilbidea",
    "iso:country":"ES",
    "sg:address":"Paseo Larrabarri Ibilbidea, 1",
    "sg:city":"Derio",
    "sg:orig_category":"Empresas De Carpinter\u00cda Met\u00c1lica",
    "sg:phone":"+34 944 54 15 78",
    "sg:postcode":"48160",
    "sg:province":"Vizcaya",
    "wof:name":"Carpinteria Metalica Derio, S.l.",
    "wof:placetype":"venue"
},
  "geometry": {"coordinates":[-2.8844189644,43.2914161682],"type":"Point"}
}