{
  "type": "Feature",
  "properties": {
    "addr:full":"Carrer de Placeta (la), 14 Roca Valles Barcelona 08430",
    "addr:housenumber":"14",
    "addr:postcode":"08430",
    "addr:street":"Carrer De Placeta La;Barcelona",
    "iso:country":"ES",
    "sg:address":"Carrer de Placeta (la), 14",
    "sg:city":"Roca Valles",
    "sg:orig_category":"Heladeros",
    "sg:phone":"+34 938 42 12 02",
    "sg:postcode":"08430",
    "sg:province":"Barcelona",
    "wof:name":"Heladeria El Cafe Scp",
    "wof:placetype":"venue"
},
  "geometry": {"coordinates":[2.3770260811,41.6025276184],"type":"Point"}
}