{
  "type": "Feature",
  "properties": {
    "addr:full":"Carrer de Santiago Rusi\u00d1ol (de), 69 Vila-seca Tarragona 43480",
    "addr:housenumber":"69",
    "addr:postcode":"43480",
    "addr:street":"Carrer De Santiago Rusin\u0303Ol De",
    "iso:country":"ES",
    "sg:address":"Carrer de Santiago Rusi\u00d1ol (de), 69",
    "sg:city":"Vila-seca",
    "sg:orig_category":"Ropa Para Beb\u00c9s Y Ni\u00d1os (confecci\u00d3n, Al Por Mayor)",
    "sg:phone":"+34 977 39 38 06",
    "sg:postcode":"43480",
    "sg:province":"Tarragona",
    "wof:name":"Pujals Marine S.l.",
    "wof:placetype":"venue"
},
  "geometry": {"coordinates":[1.1407200098,41.1111984253],"type":"Point"}
}