{
  "type": "Feature",
  "properties": {
    "addr:full":"Calle de San Lorenzo, 1 Huesca Huesca 22002",
    "addr:housenumber":"1",
    "addr:postcode":"22002",
    "addr:street":"Calle De San Lorenzo",
    "iso:country":"ES",
    "sg:address":"Calle de San Lorenzo, 1",
    "sg:city":"Huesca",
    "sg:orig_category":"M\u00c9dicos: Psiquiatr\u00cda",
    "sg:phone":"+34 974 22 01 72",
    "sg:postcode":"22002",
    "sg:province":"Huesca",
    "wof:name":"Domenech Coll Francisco",
    "wof:placetype":"venue"
},
  "geometry": {"coordinates":[-0.4062669873,42.1366691589],"type":"Point"}
}