{
  "type": "Feature",
  "properties": {
    "iso:country":"ES",
    "sg:address":"Calle de Marquesa Viuda De Aldama (de La), 17",
    "sg:city":"Alcobendas",
    "sg:orig_category":"Estancos",
    "sg:phone":"+34 916 51 60 66",
    "sg:postcode":"28100",
    "sg:province":"Madrid",
    "wof:name":"Barrado Casamayor Antonio Jose",
    "wof:placetype":"venue"
},
  "geometry": {"coordinates":[-3.6317501068,40.5414352417],"type":"Point"}
}