{
  "type": "Feature",
  "properties": {
    "addr:full":"Calle de Antonio Maura, 4 Madrid Madrid 28014",
    "addr:housenumber":"4",
    "addr:postcode":"28014",
    "addr:street":"Calle De Antonio Maura",
    "iso:country":"ES",
    "sg:address":"Calle de Antonio Maura, 4",
    "sg:city":"Madrid",
    "sg:orig_category":"Sociedades, Compa\u00d1\u00cdas Aseguradoras",
    "sg:phone":"+34 914 31 86 63",
    "sg:postcode":"28014",
    "sg:province":"Madrid",
    "wof:name":"Seguridad Global Del Automovil S.a.",
    "wof:placetype":"venue"
},
  "geometry": {"coordinates":[-3.691644907,40.4163894653],"type":"Point"}
}