{
  "type": "Feature",
  "properties": {
    "iso:country":"ES",
    "sg:address":"Avda Cristobal De Murrieta, 42",
    "sg:city":"Santurtzi",
    "sg:orig_category":"Fabricaci\u00d3n, Venta, Instalaci\u00d3n De R\u00d3tulos, De R\u00d3tulos Luminosos",
    "sg:phone":"+34 944 62 34 05",
    "sg:postcode":"48980",
    "sg:province":"Vizcaya",
    "wof:name":"Rotulos Santurce, Gonzalo Morales Gonzalez Y Marta Redondo Perez C.b.",
    "wof:placetype":"venue"
},
  "geometry": {"coordinates":[-3.0402638912,43.3327636719],"type":"Point"}
}