{
  "type": "Feature",
  "properties": {
    "addr:full":"Naranjo, S/n Aljaraque Huelva 21110",
    "addr:housenumber":"/ n",
    "addr:postcode":"21110",
    "addr:street":"Naranjo S",
    "iso:country":"ES",
    "sg:address":"Naranjo, S/n",
    "sg:city":"Aljaraque",
    "sg:orig_category":"Organizaci\u00d3n De Actos, Seminarios Y Congresos",
    "sg:phone":"+34 959 52 10 00",
    "sg:postcode":"21110",
    "sg:province":"Huelva",
    "wof:name":"El Paraiso De La Dehesa S.l.",
    "wof:placetype":"venue"
},
  "geometry": {"coordinates":[-7.0076241493,37.2893753052],"type":"Point"}
}