{
  "type": "Feature",
  "properties": {
    "iso:country":"ES",
    "sg:address":"Bloc Colombia, S/n",
    "sg:city":"Sant Pere I Sant Pau",
    "sg:orig_category":"Asociaciones, Organismos Culturales Y Socioeducativos",
    "sg:phone":"+34 977 20 21 46",
    "sg:postcode":"43007",
    "sg:province":"Tarragona",
    "wof:name":"Associacio De Gent Gran De Sant Pere I Sant Pau",
    "wof:placetype":"venue"
},
  "geometry": {"coordinates":[1.2519127131,41.138835907],"type":"Point"}
}