{
  "type": "Feature",
  "properties": {
    "addr:full":"Estda. De Vigo, 48 Ourense Ourense 32001",
    "addr:housenumber":"48",
    "addr:postcode":"32001",
    "addr:street":"Vigo",
    "iso:country":"ES",
    "sg:address":"Estda. De Vigo, 48",
    "sg:city":"Ourense",
    "sg:orig_category":"Fabricaci\u00d3n, Importaci\u00d3n, Venta De Material De Telefon\u00cda, Peritelefon\u00cda",
    "sg:phone":"+34 988 36 45 66",
    "sg:postcode":"32001",
    "sg:province":"Ourense",
    "wof:name":"Telefonica Data Espa\u00d1a S.a.",
    "wof:placetype":"venue"
},
  "geometry": {"coordinates":[-7.8814702034,42.3738327026],"type":"Point"}
}