{
  "type": "Feature",
  "properties": {
    "iso:country":"ES",
    "sg:address":"Pase Melancolicos, 3",
    "sg:city":"Madrid",
    "sg:orig_category":"Agencias Y Agentes Comerciales, Representantes",
    "sg:phone":"+34 913 66 03 75",
    "sg:postcode":"28005",
    "sg:province":"Madrid",
    "wof:name":"Perez Criado Antonio Vicente",
    "wof:placetype":"venue"
},
  "geometry": {"coordinates":[-3.7196390629,40.4081687927],"type":"Point"}
}