{
  "type": "Feature",
  "properties": {
    "iso:country":"ES",
    "sg:address":"Carr L'horta (de), 5",
    "sg:city":"Benetusser",
    "sg:orig_category":"Plomeros",
    "sg:phone":"+34 963 76 02 37",
    "sg:postcode":"46910",
    "sg:province":"Valencia",
    "wof:name":"Fontaneria Andres S.l.",
    "wof:placetype":"venue"
},
  "geometry": {"coordinates":[-0.3849132061,39.4209594727],"type":"Point"}
}