{
  "type": "Feature",
  "properties": {
    "iso:country":"ES",
    "sg:address":"Carrer de Numancia, 169",
    "sg:city":"Barcelona",
    "sg:orig_category":"Farmacias",
    "sg:phone":"+34 934 39 43 83",
    "sg:postcode":"08029",
    "sg:province":"Barcelona",
    "wof:name":"Boada Solsona Inmaculada",
    "wof:placetype":"venue"
},
  "geometry": {"coordinates":[2.1330060959,41.3890266418],"type":"Point"}
}