{
  "type": "Feature",
  "properties": {
    "iso:country":"ES",
    "sg:address":"Calle de Valencia, 25",
    "sg:city":"Placa",
    "sg:orig_category":"Empresas De Carpinter\u00cda",
    "sg:phone":"+34 987 40 53 00",
    "sg:postcode":"24400",
    "sg:province":"Le\u00f3n",
    "wof:name":"Aluminios Giron Rodriguez,s.l",
    "wof:placetype":"venue"
},
  "geometry": {"coordinates":[-5.5717520714,42.5998764038],"type":"Point"}
}