{
  "type": "Feature",
  "properties": {
    "iso:country":"ES",
    "sg:address":"Calle de General Varela, 35",
    "sg:city":"Madrid",
    "sg:orig_category":"Arquitectos",
    "sg:phone":"+34 914 25 23 99",
    "sg:postcode":"28020",
    "sg:province":"Madrid",
    "wof:name":"Esteban Polo Emma",
    "wof:placetype":"venue"
},
  "geometry": {"coordinates":[-3.6952149868,40.4583511353],"type":"Point"}
}