{
  "type": "Feature",
  "properties": {
    "addr:full":"Paseo Del Santo Cristo, 7 Huescar Granada 18830",
    "addr:housenumber":"7",
    "addr:postcode":"18830",
    "addr:street":"Paseo Del Santo Cristo",
    "iso:country":"ES",
    "sg:address":"Paseo Del Santo Cristo, 7",
    "sg:city":"Huescar",
    "sg:orig_category":"Molduras, Junquillos, Listones Y Molduras Perforadas",
    "sg:phone":"+34 958 74 07 60",
    "sg:postcode":"18830",
    "sg:province":"Granada",
    "wof:name":"Dengra Cabrera Tomas",
    "wof:placetype":"venue"
},
  "geometry": {"coordinates":[-2.5386500359,37.8087043762],"type":"Point"}
}