{
  "type": "Feature",
  "properties": {
    "addr:full":"Calle de Agustin Del Ca\u00d1izo, 2 Salamanca Salamanca 37007",
    "addr:housenumber":"2",
    "addr:postcode":"37007",
    "addr:street":"Calle De Agustin Del Can\u0303Izo",
    "iso:country":"ES",
    "sg:address":"Calle de Agustin Del Ca\u00d1izo, 2",
    "sg:city":"Salamanca",
    "sg:orig_category":"Mec\u00c1nico Del Autom\u00d3vil",
    "sg:phone":"+34 923 22 66 79",
    "sg:postcode":"37007",
    "sg:province":"Salamanca",
    "wof:name":"Garage Oeste S. L.",
    "wof:placetype":"venue"
},
  "geometry": {"coordinates":[-5.6673822403,40.971408844],"type":"Point"}
}