{
  "type": "Feature",
  "properties": {
    "iso:country":"ES",
    "sg:address":"Calle de Cristo De Los Afligidos, 26",
    "sg:city":"Utrera",
    "sg:orig_category":"Pod\u00d3logos: Pedicuros",
    "sg:phone":"+34 955 86 10 50",
    "sg:postcode":"41710",
    "sg:province":"Sevilla",
    "wof:name":"Corpas Matos Agustin",
    "wof:placetype":"venue"
},
  "geometry": {"coordinates":[-5.7850079536,37.1779747009],"type":"Point"}
}