{
  "type": "Feature",
  "properties": {
    "iso:country":"ES",
    "sg:address":"Ptor Crispin, 8",
    "sg:city":"Iru\u00f1a",
    "sg:orig_category":"Procuradores",
    "sg:phone":"+34 948 27 84 99",
    "sg:postcode":"31008",
    "sg:province":"Navarra",
    "wof:name":"Abaurrea Larrea Agueda",
    "wof:placetype":"venue"
},
  "geometry": {"coordinates":[-1.668781,42.81023],"type":"Point"}
}