{
  "type": "Feature",
  "properties": {
    "addr:full":"Calle de Borrego, 2 Plasencia C\u00e1ceres 10600",
    "addr:housenumber":"2",
    "addr:postcode":"10600",
    "addr:street":"Calle De Borrego;Ca\u0301Ceres",
    "iso:country":"ES",
    "sg:address":"Calle de Borrego, 2",
    "sg:city":"Plasencia",
    "sg:orig_category":"Empresas De Trabajos P\u00dablicos",
    "sg:phone":"+34 927 41 35 53",
    "sg:postcode":"10600",
    "sg:province":"C\u00e1ceres",
    "sg:website":"www.araplasa.net",
    "wof:name":"Cnes Araplasa S.a.",
    "wof:placetype":"venue"
},
  "geometry": {"coordinates":[-6.0879888535,40.0302200317],"type":"Point"}
}