{
  "type": "Feature",
  "properties": {
    "iso:country":"ES",
    "sg:address":"Carr Olimp, 6",
    "sg:city":"Platja D'alcudia",
    "sg:orig_category":"Laboratorios Y Trabajos De Fotograf\u00cda, V\u00cddeo Y Cine",
    "sg:phone":"+34 971 89 22 19",
    "sg:postcode":"07408",
    "sg:province":"Islas Baleares",
    "wof:name":"Bonafe  Desna Helen",
    "wof:placetype":"venue"
},
  "geometry": {"coordinates":[3.1114220619,39.8379974365],"type":"Point"}
}