{
  "type": "Feature",
  "properties": {
    "addr:full":"Calle de Mayor, 12 Burlada Navarra 31600",
    "addr:housenumber":"12",
    "addr:postcode":"31600",
    "addr:street":"Calle De Mayor",
    "iso:country":"ES",
    "sg:address":"Calle de Mayor, 12",
    "sg:city":"Burlada",
    "sg:orig_category":"Librer\u00cdas",
    "sg:phone":"+34 948 24 74 56",
    "sg:postcode":"31600",
    "sg:province":"Navarra",
    "wof:name":"Albes Huarte Maria Esther",
    "wof:placetype":"venue"
},
  "geometry": {"coordinates":[-1.6169857979,42.825252533],"type":"Point"}
}