{
  "type": "Feature",
  "properties": {
    "addr:full":"Calle de Nuestra Se\u00d1ora De Guadalupe, 5 Oliva Frontera Badajoz 06120",
    "addr:housenumber":"5",
    "addr:postcode":"06120",
    "addr:street":"Calle De Nuestra Sen\u0303Ora De Guadalupe",
    "iso:country":"ES",
    "sg:address":"Calle de Nuestra Se\u00d1ora De Guadalupe, 5",
    "sg:city":"Oliva Frontera",
    "sg:orig_category":"Fabrica De Charcuter\u00cda",
    "sg:phone":"+34 924 74 01 84",
    "sg:postcode":"06120",
    "sg:province":"Badajoz",
    "wof:name":"Productos Ibericos Barroso S.l.",
    "wof:placetype":"venue"
},
  "geometry": {"coordinates":[-6.9170508385,38.274143219],"type":"Point"}
}