{
  "type": "Feature",
  "properties": {
    "addr:full":"Calle de Mendez Nu\u00d1ez, 26 Cangas Pontevedra 36940",
    "addr:housenumber":"26",
    "addr:postcode":"36940",
    "addr:street":"Calle De Mendez Nun\u0303Ez",
    "iso:country":"ES",
    "sg:address":"Calle de Mendez Nu\u00d1ez, 26",
    "sg:city":"Cangas",
    "sg:orig_category":"Loter\u00cda Y T\u00d3mbola",
    "sg:phone":"+34 986 30 59 50",
    "sg:postcode":"36940",
    "sg:province":"Pontevedra",
    "wof:name":"Ferrero Gonzalez Loreto",
    "wof:placetype":"venue"
},
  "geometry": {"coordinates":[-8.7791318893,42.2641220093],"type":"Point"}
}