{
  "type": "Feature",
  "properties": {
    "addr:full":"Calle de Manuel Maria Iglesias, 3 Madrid Madrid 28043",
    "addr:housenumber":"3",
    "addr:postcode":"28043",
    "addr:street":"Calle De Manuel Maria Iglesias",
    "iso:country":"ES",
    "sg:address":"Calle de Manuel Maria Iglesias, 3",
    "sg:city":"Madrid",
    "sg:orig_category":"Audiovisuales (producci\u00d3n, Edici\u00d3n, Realizaci\u00d3n)",
    "sg:phone":"+34 915 19 36 30",
    "sg:postcode":"28043",
    "sg:province":"Madrid",
    "wof:name":"Levinver S.a.",
    "wof:placetype":"venue"
},
  "geometry": {"coordinates":[-3.654794693,40.4510574341],"type":"Point"}
}