{
  "type": "Feature",
  "properties": {
    "addr:full":"Calle de Robledillo, S/n Sonseca Toledo 45100",
    "addr:housenumber":"s / n",
    "addr:postcode":"45100",
    "addr:street":"Calle De Robledillo",
    "iso:country":"ES",
    "sg:address":"Calle de Robledillo, S/n",
    "sg:city":"Sonseca",
    "sg:orig_category":"Pintura Y Barniz (al Por Menor)",
    "sg:phone":"+34 925 38 15 45",
    "sg:postcode":"45100",
    "sg:province":"Toledo",
    "wof:name":"R & D A.moreno S.l.",
    "wof:placetype":"venue"
},
  "geometry": {"coordinates":[-3.980743885,39.6875267029],"type":"Point"}
}