{
  "type": "Feature",
  "properties": {
    "iso:country":"ES",
    "sg:address":"Calle de Alcala, 463",
    "sg:city":"Madrid",
    "sg:orig_category":"Cl\u00cdnicas Dentales",
    "sg:phone":"+34 913 93 13 76",
    "sg:postcode":"28027",
    "sg:province":"Madrid",
    "wof:name":"Clinica Dental Meyma",
    "wof:placetype":"venue"
},
  "geometry": {"coordinates":[-3.6336944103,40.4390678406],"type":"Point"}
}