{
  "type": "Feature",
  "properties": {
    "iso:country":"ES",
    "sg:address":"Ctra Cervera, Km. 0014,2",
    "sg:city":"Rincon Olivedo-casas",
    "sg:orig_category":"Distribuci\u00d3n De Petr\u00d3leo Y Derivados",
    "sg:phone":"+34 941 17 57 18",
    "sg:postcode":"26527",
    "sg:province":"La Rioja",
    "sg:website":"www.cepsa.es",
    "wof:name":"Estacion De Servicio Rio Linares S.l.",
    "wof:placetype":"venue"
},
  "geometry": {"coordinates":[-1.9084459543,42.0563621521],"type":"Point"}
}