{
  "type": "Feature",
  "properties": {
    "addr:full":"Carrer de Arcadi Balaguer, 53 Castelldefels Barcelona 08860",
    "addr:housenumber":"53",
    "addr:postcode":"08860",
    "addr:street":"Carrer De Arcadi Balaguer",
    "iso:country":"ES",
    "sg:address":"Carrer de Arcadi Balaguer, 53",
    "sg:city":"Castelldefels",
    "sg:orig_category":"Comercio De Muebles De Estilo Y Contempor\u00c1neos",
    "sg:phone":"+34 936 36 64 75",
    "sg:postcode":"08860",
    "sg:province":"Barcelona",
    "wof:name":"Jimenez Mallenco Maria Dolores",
    "wof:placetype":"venue"
},
  "geometry": {"coordinates":[1.9785569906,41.281375885],"type":"Point"}
}