{
  "type": "Feature",
  "properties": {
    "addr:full":"Calle de Comercio, S/n Alacant Alicante 03008",
    "addr:housenumber":"s / n",
    "addr:postcode":"03008",
    "addr:street":"Calle De Comercio",
    "iso:country":"ES",
    "sg:address":"Calle de Comercio, S/n",
    "sg:city":"Alacant",
    "sg:orig_category":"Ense\u00d1anza, Formaci\u00d3n Profesional: Aprendizaje",
    "sg:phone":"+34 965 11 29 15",
    "sg:postcode":"03008",
    "sg:province":"Alicante",
    "wof:name":"Agencia Estatal De Administracion Tributaria",
    "wof:placetype":"venue"
},
  "geometry": {"coordinates":[-0.5146837234,38.3356132507],"type":"Point"}
}