{
  "type": "Feature",
  "properties": {
    "addr:full":"Calle de Almona Del Campillo, 2 Granada Granada 18009",
    "addr:housenumber":"2",
    "addr:postcode":"18009",
    "addr:street":"Calle De Almona Del Campillo",
    "iso:country":"ES",
    "sg:address":"Calle de Almona Del Campillo, 2",
    "sg:city":"Granada",
    "sg:orig_category":"Grafistas",
    "sg:phone":"+34 958 22 39 52",
    "sg:postcode":"18009",
    "sg:province":"Granada",
    "sg:website":"www.wanadoo.com",
    "wof:name":"Aguilar Lozano Virginia",
    "wof:placetype":"venue"
},
  "geometry": {"coordinates":[-3.5990612507,37.172832489],"type":"Point"}
}