{
  "type": "Feature",
  "properties": {
    "addr:full":"Cmno Canaleja, S/n Madrid Madrid 28044",
    "addr:housenumber":"s / n",
    "addr:postcode":"28044",
    "addr:street":"Cmno Canaleja",
    "iso:country":"ES",
    "sg:address":"Cmno Canaleja, S/n",
    "sg:city":"Madrid",
    "sg:orig_category":"Material Ferroviario",
    "sg:phone":"+34 915 08 16 10",
    "sg:postcode":"28044",
    "sg:province":"Madrid",
    "wof:name":"Sistemas Electricos De Potencia S. A.",
    "wof:placetype":"venue"
},
  "geometry": {"coordinates":[-3.7965240479,40.363571167],"type":"Point"}
}