{
  "type": "Feature",
  "properties": {
    "iso:country":"ES",
    "sg:address":"Carrer de Roger De Flor, 12",
    "sg:city":"Gava",
    "sg:orig_category":"Puertas Y Portales",
    "sg:phone":"+34 936 33 67 04",
    "sg:postcode":"08850",
    "sg:province":"Barcelona",
    "wof:name":"Rodriguez Piedra Jesus",
    "wof:placetype":"venue"
},
  "geometry": {"coordinates":[1.9980549812,41.3100776672],"type":"Point"}
}