{
  "type": "Feature",
  "properties": {
    "iso:country":"ES",
    "sg:address":"Calle de Alfonso Pe\u00d1a, 14",
    "sg:city":"Valencia",
    "sg:orig_category":"Bisuteros (fabricaci\u00d3n, Al Por Mayor)",
    "sg:phone":"+34 963 47 82 73",
    "sg:postcode":"46009",
    "sg:province":"Valencia",
    "wof:name":"Horus Joyeros S.a.",
    "wof:placetype":"venue"
},
  "geometry": {"coordinates":[-0.3771413863,39.4902305603],"type":"Point"}
}