{
  "type": "Feature",
  "properties": {
    "iso:country":"ES",
    "sg:address":"Txikierdi Auzoa, 7",
    "sg:city":"Txikierdi",
    "sg:orig_category":"Ropa Para Ni\u00d1os (al Por Menor)",
    "sg:phone":"+34 943 37 65 75",
    "sg:postcode":"20170",
    "sg:province":"Guip\u00f9zcoa",
    "sg:website":"www.e-stradivarius.com",
    "wof:name":"Stradivarius Espa\u00f1a S.a.",
    "wof:placetype":"venue"
},
  "geometry": {"coordinates":[-2.0539140701,43.2733459473],"type":"Point"}
}