{
  "type": "Feature",
  "properties": {
    "iso:country":"ES",
    "sg:address":"Calle de San Francisco, 1",
    "sg:city":"Talavera Reina",
    "sg:orig_category":"Mercer\u00cda, Lencer\u00cda (al Por Menor)",
    "sg:phone":"+34 925 80 00 30",
    "sg:postcode":"45600",
    "sg:province":"Toledo",
    "wof:name":"Carrion Hesse Lourdes",
    "wof:placetype":"venue"
},
  "geometry": {"coordinates":[-4.8308458328,39.96043396],"type":"Point"}
}