{
  "type": "Feature",
  "properties": {
    "iso:country":"ES",
    "sg:address":"Calle de Porcuna, 43",
    "sg:city":"Valenzuela",
    "sg:classifiers":[
        {
            "category":"Taxi",
            "type":"Transportation"
        }
    ],
    "sg:phone":"+34 957 18 81 28",
    "sg:postcode":"14670",
    "sg:province":"C\u00f3rdoba",
    "wof:name":"Gutierrez Sanchez Cristobal",
    "wof:placetype":"venue"
},
  "geometry": {"coordinates":[-4.2194080353,37.7783927917],"type":"Point"}
}