{
  "type": "Feature",
  "properties": {
    "iso:country":"ES",
    "sg:address":"Ctra Rubi, 40",
    "sg:city":"Mira-sol",
    "sg:orig_category":"Aguas (distribuci\u00d3n, Servicios)",
    "sg:phone":"+34 935 89 84 95",
    "sg:postcode":"08173",
    "sg:province":"Barcelona",
    "wof:name":"Dirteca Barcelona Sl",
    "wof:placetype":"venue"
},
  "geometry": {"coordinates":[2.0622999668,41.4687690735],"type":"Point"}
}