{
  "type": "Feature",
  "properties": {
    "addr:full":"Sierra De Santa Ana, 7 San Javier Murcia 30730",
    "addr:housenumber":"7",
    "addr:postcode":"30730",
    "addr:street":"Santa Ana",
    "iso:country":"ES",
    "sg:address":"Sierra De Santa Ana, 7",
    "sg:city":"San Javier",
    "sg:orig_category":"Suministros Y Materiales Industriales",
    "sg:phone":"+34 968 19 05 10",
    "sg:postcode":"30730",
    "sg:province":"Murcia",
    "wof:name":"Sumnicar Mar Menor S.l.",
    "wof:placetype":"venue"
},
  "geometry": {"coordinates":[-0.8432379961,37.8077201843],"type":"Point"}
}