{
  "type": "Feature",
  "properties": {
    "addr:full":"Avda Madrid, 87 Zaragoza Zaragoza 50010",
    "addr:housenumber":"87",
    "addr:postcode":"50010",
    "addr:street":"Avda Madrid",
    "iso:country":"ES",
    "sg:address":"Avda Madrid, 87",
    "sg:city":"Zaragoza",
    "sg:orig_category":"Agencias De Trabajo Temporal",
    "sg:phone":"+34 976 33 28 28",
    "sg:postcode":"50010",
    "sg:province":"Zaragoza",
    "wof:name":"Flexiplan S.a.",
    "wof:placetype":"venue"
},
  "geometry": {"coordinates":[-0.899864018,41.6545257568],"type":"Point"}
}