{
  "type": "Feature",
  "properties": {
    "iso:country":"ES",
    "sg:address":"Avda. Pias-cruceiro, S/n",
    "sg:city":"Perlio",
    "sg:orig_category":"Agencias De Viajes",
    "sg:phone":"+34 981 49 29 15",
    "sg:postcode":"15500",
    "sg:province":"A Coru\u00f1a",
    "sg:website":"www.halconviajes.com",
    "wof:name":"Viajes Halcon S.a.",
    "wof:placetype":"venue"
},
  "geometry": {"coordinates":[-8.1644191742,43.4750747681],"type":"Point"}
}