{
  "type": "Feature",
  "properties": {
    "iso:country":"ES",
    "sg:address":"Calle de Musico Barbieri, 1",
    "sg:city":"Valencia",
    "sg:orig_category":"Platos Preparados Refrigerados (fabricaci\u00d3n, Al Por Mayor)",
    "sg:phone":"+34 963 57 87 03",
    "sg:postcode":"46018",
    "sg:province":"Valencia",
    "wof:name":"Calatayud Sanmartin Regina",
    "wof:placetype":"venue"
},
  "geometry": {"coordinates":[-0.3935700059,39.4609107971],"type":"Point"}
}