{
  "type": "Feature",
  "properties": {
    "addr:full":"Carrer de Constitucio, 94 Sant Feliu Llobregat Barcelona 08980",
    "addr:housenumber":"94",
    "addr:postcode":"08980",
    "addr:street":"Carrer De Constitucio",
    "iso:country":"ES",
    "sg:address":"Carrer de Constitucio, 94",
    "sg:city":"Sant Feliu Llobregat",
    "sg:orig_category":"Herramientas Manuales (fabricaci\u00d3n, Al Por Mayor)",
    "sg:phone":"+34 936 85 00 99",
    "sg:postcode":"08980",
    "sg:province":"Barcelona",
    "sg:website":"www.imcar.com",
    "wof:name":"Imcar Tools S. L.",
    "wof:placetype":"venue"
},
  "geometry": {"coordinates":[2.0405509472,41.3914680481],"type":"Point"}
}