{
  "type": "Feature",
  "properties": {
    "iso:country":"ES",
    "sg:address":"Pl Alcasser, 3",
    "sg:city":"Portals Nous",
    "sg:orig_category":"Cl\u00cdnicas Dentales",
    "sg:phone":"+34 971 67 76 47",
    "sg:postcode":"07181",
    "sg:province":"Islas Baleares",
    "wof:name":"Bondulich  Ina",
    "wof:placetype":"venue"
},
  "geometry": {"coordinates":[2.5727860928,39.5353507996],"type":"Point"}
}