{
  "type": "Feature",
  "properties": {
    "iso:country":"ES",
    "sg:address":"Plaz San Lorenzo, 1",
    "sg:city":"Sevilla",
    "sg:orig_category":"Restaurantes",
    "sg:phone":"+34 954 90 64 75",
    "sg:postcode":"41002",
    "sg:province":"Sevilla",
    "wof:name":"Restaurante Az-zait S.l.",
    "wof:placetype":"venue"
},
  "geometry": {"coordinates":[-5.9964818954,37.3968238831],"type":"Point"}
}