{
  "type": "Feature",
  "properties": {
    "addr:full":"Avda Europa, 19 Pozuelo De Alarcon Madrid 28224",
    "addr:housenumber":"19",
    "addr:postcode":"28224",
    "addr:street":"Avda Europa",
    "iso:country":"ES",
    "sg:address":"Avda Europa, 19",
    "sg:city":"Pozuelo De Alarcon",
    "sg:orig_category":"Promotores Constructores",
    "sg:phone":"+34 913 51 06 61",
    "sg:postcode":"28224",
    "sg:province":"Madrid",
    "sg:website":"www.urbis.es",
    "wof:name":"Inmobiliaria Urbis S.a.",
    "wof:placetype":"venue"
},
  "geometry": {"coordinates":[-3.7874910831,40.4409637451],"type":"Point"}
}