{
  "type": "Feature",
  "properties": {
    "addr:full":"Carr Alfred Pere\u00d1a, 53 Lleida Lleida 25004",
    "addr:housenumber":"53",
    "addr:postcode":"25004",
    "addr:street":"Carr Alfred Peren\u0303A",
    "iso:country":"ES",
    "sg:address":"Carr Alfred Pere\u00d1a, 53",
    "sg:city":"Lleida",
    "sg:orig_category":"Reposter\u00cdas",
    "sg:phone":"+34 973 23 45 01",
    "sg:postcode":"25004",
    "sg:province":"Lleida",
    "wof:name":"Olives Socias Jose Ramon",
    "wof:placetype":"venue"
},
  "geometry": {"coordinates":[0.6236850023,41.6221694946],"type":"Point"}
}