{
  "type": "Feature",
  "properties": {
    "iso:country":"ES",
    "sg:address":"Lola P Parres, 5",
    "sg:city":"Ronda",
    "sg:orig_category":"Farmacias",
    "sg:phone":"+34 952 87 11 98",
    "sg:postcode":"29400",
    "sg:province":"M\u00e1laga",
    "wof:name":"Delgado Vaena Teresa",
    "wof:placetype":"venue"
},
  "geometry": {"coordinates":[-5.1497511864,36.7526779175],"type":"Point"}
}