{
  "type": "Feature",
  "properties": {
    "iso:country":"ES",
    "sg:address":"Calle de Francisco Guzman, 20",
    "sg:city":"Illescas",
    "sg:orig_category":"Carnicer\u00cdas, Carnicer\u00cdas",
    "sg:phone":"+34 925 51 13 39",
    "sg:postcode":"45200",
    "sg:province":"Toledo",
    "wof:name":"Robles Ugena Braulio",
    "wof:placetype":"venue"
},
  "geometry": {"coordinates":[-3.8474318981,40.1240386963],"type":"Point"}
}