{
  "type": "Feature",
  "properties": {
    "addr:full":"Carr Bisbe Gonyalons, 55 Mao Islas Baleares 07703",
    "addr:housenumber":"55",
    "addr:postcode":"07703",
    "addr:street":"Carr Bisbe Gonyalons",
    "iso:country":"ES",
    "sg:address":"Carr Bisbe Gonyalons, 55",
    "sg:city":"Mao",
    "sg:orig_category":"Material Y Suministros Para Fotocopiadoras, Reprograf\u00cda",
    "sg:phone":"+34 971 36 39 33",
    "sg:postcode":"07703",
    "sg:province":"Islas Baleares",
    "wof:name":"Copiadoras De Menorca S. L.",
    "wof:placetype":"venue"
},
  "geometry": {"coordinates":[4.2570571899,39.8843307495],"type":"Point"}
}