{
  "type": "Feature",
  "properties": {
    "iso:country":"ES",
    "sg:address":"Carr S Simplici, 26",
    "sg:city":"Igualada",
    "sg:orig_category":"Cuchiller\u00cda (al Por Menor)",
    "sg:phone":"+34 938 03 45 92",
    "sg:postcode":"08700",
    "sg:province":"Barcelona",
    "wof:name":"Merino Ganiveteria C.b.",
    "wof:placetype":"venue"
},
  "geometry": {"coordinates":[1.6148209572,41.5789794922],"type":"Point"}
}