{
  "type": "Feature",
  "properties": {
    "iso:country":"ES",
    "sg:address":"Av Mossen Alcover, 61",
    "sg:city":"Manacor",
    "sg:orig_category":"Molduras, Junquillos, Listones Y Molduras Perforadas",
    "sg:phone":"+34 971 55 20 80",
    "sg:postcode":"07500",
    "sg:province":"Islas Baleares",
    "wof:name":"Obrador Mascaro Antonia",
    "wof:placetype":"venue"
},
  "geometry": {"coordinates":[3.2079091072,39.5633888245],"type":"Point"}
}