{
  "type": "Feature",
  "properties": {
    "addr:full":"Rua Alonso Ojeda, 17 Vigo Pontevedra 36207",
    "addr:housenumber":"17",
    "addr:postcode":"36207",
    "addr:street":"Rua Alonso Ojeda",
    "iso:country":"ES",
    "sg:address":"Rua Alonso Ojeda, 17",
    "sg:city":"Vigo",
    "sg:orig_category":"Mec\u00c1nico Del Autom\u00d3vil",
    "sg:phone":"+34 986 37 11 08",
    "sg:postcode":"36207",
    "sg:province":"Pontevedra",
    "sg:website":"www.renault.es",
    "wof:name":"Talleres Emilio Viana S.l.",
    "wof:placetype":"venue"
},
  "geometry": {"coordinates":[-8.6975622177,42.2498283386],"type":"Point"}
}