{
  "type": "Feature",
  "properties": {
    "iso:country":"ES",
    "sg:address":"Calle de Ganekogorta, 16",
    "sg:city":"Zaramillo",
    "sg:orig_category":"Confecci\u00d3n (fabricaci\u00d3n, Al Por Mayor)",
    "sg:phone":"+34 946 69 26 19",
    "sg:postcode":"48820",
    "sg:province":"Vizcaya",
    "wof:name":"Pavon Gomez Maria Gloria",
    "wof:placetype":"venue"
},
  "geometry": {"coordinates":[-3.0263431072,43.2210426331],"type":"Point"}
}