{
  "type": "Feature",
  "properties": {
    "iso:country":"ES",
    "sg:address":"Calle de Gonzalo De Berceo, 8",
    "sg:city":"Logro\u00f1o",
    "sg:orig_category":"Negocio De Madera",
    "sg:phone":"+34 941 20 44 45",
    "sg:postcode":"26005",
    "sg:province":"La Rioja",
    "wof:name":"Utisa Tableros Del Mediterraneo S.l.",
    "wof:placetype":"venue"
},
  "geometry": {"coordinates":[-2.4554231167,42.4656486511],"type":"Point"}
}