{
  "type": "Feature",
  "properties": {
    "iso:country":"ES",
    "sg:address":"Sant Maurici, 9",
    "sg:city":"Caldes Malavella",
    "sg:orig_category":"Inmobiliaria (agencias)",
    "sg:phone":"+34 972 47 13 08",
    "sg:postcode":"17455",
    "sg:province":"Girona",
    "sg:website":"www.inmorealstate.com",
    "wof:name":"Gestion Inmobiliaria Caldes 2001 Sl",
    "wof:placetype":"venue"
},
  "geometry": {"coordinates":[2.8048000336,41.8316307068],"type":"Point"}
}