{
  "type": "Feature",
  "properties": {
    "addr:full":"Pase Zarategi De, 77 Donostia-san Sebastian Guip\u00f9zcoa 20015",
    "addr:housenumber":"77",
    "addr:postcode":"20015",
    "iso:country":"ES",
    "sg:address":"Pase Zarategi De, 77",
    "sg:city":"Donostia-san Sebastian",
    "sg:orig_category":"Institutos De Belleza",
    "sg:phone":"+34 943 32 23 93",
    "sg:postcode":"20015",
    "sg:province":"Guip\u00f9zcoa",
    "wof:name":"Bon Perez Maria",
    "wof:placetype":"venue"
},
  "geometry": {"coordinates":[-1.9544949532,43.315322876],"type":"Point"}
}