{
  "type": "Feature",
  "properties": {
    "iso:country":"ES",
    "sg:address":"Calle de Do\u00d1a Maria Sanchez Pinto, 50",
    "sg:city":"Manchita",
    "sg:orig_category":"Apicultura",
    "sg:phone":"+34 924 36 58 40",
    "sg:postcode":"06478",
    "sg:province":"Badajoz",
    "wof:name":"Tamayo Retamar Jose",
    "wof:placetype":"venue"
},
  "geometry": {"coordinates":[-6.0234889984,38.8155021667],"type":"Point"}
}