{
  "type": "Feature",
  "properties": {
    "addr:full":"Calle de Rosario, 103 Albacete Albacete 02003",
    "addr:housenumber":"103",
    "addr:postcode":"02003",
    "addr:street":"Calle De Rosario",
    "iso:country":"ES",
    "sg:address":"Calle de Rosario, 103",
    "sg:city":"Albacete",
    "sg:orig_category":"Material Y Suministros Para Fotocopiadoras, Reprograf\u00cda",
    "sg:phone":"+34 967 50 52 05",
    "sg:postcode":"02003",
    "sg:province":"Albacete",
    "wof:name":"Sistemas Y Servicios De Oficina Calco S.l.",
    "wof:placetype":"venue"
},
  "geometry": {"coordinates":[-1.8601269722,38.9882926941],"type":"Point"}
}