{
  "type": "Feature",
  "properties": {
    "iso:country":"ES",
    "sg:address":"Pl Cuba, 8",
    "sg:city":"Mataro",
    "sg:orig_category":"Perfumer\u00cda (al Por Menor)",
    "sg:phone":"+34 937 99 85 48",
    "sg:postcode":"08302",
    "sg:province":"Barcelona",
    "wof:name":"Perfumeries Ma\u00f1ach S.a.",
    "wof:placetype":"venue"
},
  "geometry": {"coordinates":[2.4408910275,41.5375976562],"type":"Point"}
}