{
  "type": "Feature",
  "properties": {
    "addr:full":"Calle de Pablo Morillo, 18 Zamora Zamora 49013",
    "addr:housenumber":"18",
    "addr:postcode":"49013",
    "addr:street":"Calle De Pablo Morillo",
    "iso:country":"ES",
    "sg:address":"Calle de Pablo Morillo, 18",
    "sg:city":"Zamora",
    "sg:orig_category":"Granos Y Semillas (producci\u00d3n, Al Por Mayor)",
    "sg:phone":"+34 980 52 09 41",
    "sg:postcode":"49013",
    "sg:province":"Zamora",
    "sg:website":"www.arlesa.com",
    "wof:name":"Arlesa Semillas S.a.",
    "wof:placetype":"venue"
},
  "geometry": {"coordinates":[-5.740530014,41.5093307495],"type":"Point"}
}