{
  "type": "Feature",
  "properties": {
    "addr:full":"Calle de Ramiro De Maeztu, 13 Vitoria-gasteiz \u00c1lava 01008",
    "addr:housenumber":"13",
    "addr:postcode":"01008",
    "addr:street":"Calle De Ramiro De Maeztu",
    "iso:country":"ES",
    "sg:address":"Calle de Ramiro De Maeztu, 13",
    "sg:city":"Vitoria-gasteiz",
    "sg:orig_category":"M\u00c9dicos: Medicina General Orientada A La Acupuntura",
    "sg:phone":"+34 945 20 04 28",
    "sg:postcode":"01008",
    "sg:province":"\u00c1lava",
    "wof:name":"Lourdes Redondo (carfae)",
    "wof:placetype":"venue"
},
  "geometry": {"coordinates":[-2.6785080433,42.8488998413],"type":"Point"}
}