{
  "type": "Feature",
  "properties": {
    "iso:country":"ES",
    "sg:address":"Calle de San Vicente (de), 10",
    "sg:city":"Alcobendas",
    "sg:orig_category":"Radiocomunicaciones, Telefon\u00cda M\u00d3vil, Radiomensajer\u00cda: Servicios, Comercializaci\u00d3n",
    "sg:phone":"+34 916 52 02 26",
    "sg:postcode":"28100",
    "sg:province":"Madrid",
    "wof:name":"Dulzilandia Meza S.l.",
    "wof:placetype":"venue"
},
  "geometry": {"coordinates":[-3.6306068897,40.5436325073],"type":"Point"}
}