{
  "type": "Feature",
  "properties": {
    "addr:full":"Calle de Reina, 41 Valencia Valencia 46011",
    "addr:housenumber":"41",
    "addr:postcode":"46011",
    "addr:street":"Calle De Reina",
    "iso:country":"ES",
    "sg:address":"Calle de Reina, 41",
    "sg:city":"Valencia",
    "sg:orig_category":"M\u00c9dicos: An\u00c1lisis Cl\u00cdnicos",
    "sg:phone":"+34 963 67 24 19",
    "sg:postcode":"46011",
    "sg:province":"Valencia",
    "wof:name":"Perez Pastor Jose Luis",
    "wof:placetype":"venue"
},
  "geometry": {"coordinates":[-0.3293380141,39.4653282166],"type":"Point"}
}