{
  "type": "Feature",
  "properties": {
    "iso:country":"ES",
    "sg:address":"Carrer de Call, S/n",
    "sg:city":"Santa Eugenia De Berga",
    "sg:orig_category":"Asilos De Ancianos. Centros Privados",
    "sg:phone":"+34 938 83 21 23",
    "sg:postcode":"08507",
    "sg:province":"Barcelona",
    "wof:name":"Associacio Pensionistes Sta Eugenia",
    "wof:placetype":"venue"
},
  "geometry": {"coordinates":[2.283485651,41.9008636475],"type":"Point"}
}