{
  "type": "Feature",
  "properties": {
    "addr:full":"Calle de Carmen De Michelena, S/n Jaen Ja\u00e9n 23009",
    "addr:housenumber":"s / n;jae\u0301n",
    "addr:postcode":"23009",
    "addr:street":"Calle De Carmen De Michelena",
    "iso:country":"ES",
    "sg:address":"Calle de Carmen De Michelena, S/n",
    "sg:city":"Jaen",
    "sg:orig_category":"Art\u00cdculos De Decoraci\u00d3n (fabricaci\u00d3n Y Al Por Mayor)",
    "sg:phone":"+34 953 28 06 12",
    "sg:postcode":"23009",
    "sg:province":"Ja\u00e9n",
    "wof:name":"Paviter Y Salima S.l.",
    "wof:placetype":"venue"
},
  "geometry": {"coordinates":[-3.7828812599,37.7873458862],"type":"Point"}
}