{
  "type": "Feature",
  "properties": {
    "iso:country":"ES",
    "sg:address":"Hta. Santa Ana, S/n",
    "sg:city":"Jatar",
    "sg:orig_category":"Importaci\u00d3n",
    "sg:phone":"+34 958 35 91 05",
    "sg:postcode":"18127",
    "sg:province":"Granada",
    "wof:name":"Importaciones Jatar S.l.",
    "wof:placetype":"venue"
},
  "geometry": {"coordinates":[-3.8188650608,36.9488945007],"type":"Point"}
}