{
  "type": "Feature",
  "properties": {
    "iso:country":"ES",
    "sg:address":"Isla De Tabarca, 3",
    "sg:city":"Valdepastores",
    "sg:orig_category":"Pescader\u00cdas (al Por Menor)",
    "sg:phone":"+34 916 32 68 63",
    "sg:postcode":"28660",
    "sg:province":"Madrid",
    "wof:name":"Pamape S.l.",
    "wof:placetype":"venue"
},
  "geometry": {"coordinates":[-3.8812100887,40.4177627563],"type":"Point"}
}