{
  "type": "Feature",
  "properties": {
    "iso:country":"ES",
    "sg:address":"Ctra. Esparraguera A Olesa, Km. 6200,0",
    "sg:city":"Esparreguera",
    "sg:orig_category":"Empresas De Electricidad En General",
    "sg:phone":"+34 937 77 53 54",
    "sg:postcode":"08292",
    "sg:province":"Barcelona",
    "wof:name":"Red Electrica-subestacion Pierola",
    "wof:placetype":"venue"
},
  "geometry": {"coordinates":[1.867759943,41.5371665955],"type":"Point"}
}