{
  "type": "Feature",
  "properties": {
    "addr:full":"Carrer de Novell, 62 Barcelona Barcelona 08014",
    "addr:housenumber":"62",
    "addr:postcode":"08014",
    "addr:street":"Carrer De Novell",
    "iso:country":"ES",
    "sg:address":"Carrer de Novell, 62",
    "sg:city":"Barcelona",
    "sg:orig_category":"Comercio De Piezas De Recambio Y De Accesorios De Veh\u00cdculos, Veh\u00cdculos Industriales",
    "sg:phone":"+34 934 90 26 83",
    "sg:postcode":"08014",
    "sg:province":"Barcelona",
    "wof:name":"Comas Rosales Gil",
    "wof:placetype":"venue"
},
  "geometry": {"coordinates":[2.1338219643,41.3833732605],"type":"Point"}
}