{
  "type": "Feature",
  "properties": {
    "iso:country":"ES",
    "sg:address":"Leonardo Da Vinci, 62",
    "sg:city":"Palacios Y Villafranca",
    "sg:orig_category":"Plomeros",
    "sg:phone":"+34 955 81 63 79",
    "sg:postcode":"41720",
    "sg:province":"Sevilla",
    "wof:name":"Gavira Ayala Juan",
    "wof:placetype":"venue"
},
  "geometry": {"coordinates":[-5.9278187752,37.1667518616],"type":"Point"}
}