{
  "type": "Feature",
  "properties": {
    "iso:country":"ES",
    "sg:address":"Calle de Gato (el), 8",
    "sg:city":"Mocejon",
    "sg:orig_category":"Asesor\u00cda Sobre Comunicaci\u00d3n De Empresas",
    "sg:phone":"+34 925 36 05 78",
    "sg:postcode":"45270",
    "sg:province":"Toledo",
    "wof:name":"Aseguradores Y Asesores Contables S.l.",
    "wof:placetype":"venue"
},
  "geometry": {"coordinates":[-3.9181513786,39.940574646],"type":"Point"}
}