{
  "type": "Feature",
  "properties": {
    "iso:country":"ES",
    "sg:address":"Carr Figueres, 83",
    "sg:city":"Castello D'empuries",
    "sg:orig_category":"Plomeros",
    "sg:phone":"+34 972 25 03 35",
    "sg:postcode":"17486",
    "sg:province":"Girona",
    "wof:name":"Lopez Aranda Antonio",
    "wof:placetype":"venue"
},
  "geometry": {"coordinates":[3.1281700134,42.1158485413],"type":"Point"}
}