{
  "type": "Feature",
  "properties": {
    "addr:full":"Calle de La Florida, 32 Vitoria-gasteiz \u00c1lava 01005",
    "addr:housenumber":"32",
    "addr:postcode":"01005",
    "addr:street":"Calle De La Florida",
    "iso:country":"ES",
    "sg:address":"Calle de La Florida, 32",
    "sg:city":"Vitoria-gasteiz",
    "sg:orig_category":"M\u00c9dicos: Medicina General Orientada A La Homeopat\u00cda",
    "sg:phone":"+34 945 23 02 76",
    "sg:postcode":"01005",
    "sg:province":"\u00c1lava",
    "wof:name":"Saez Cordero Maria Victoria",
    "wof:placetype":"venue"
},
  "geometry": {"coordinates":[-2.6709690094,42.8428344727],"type":"Point"}
}