{
  "type": "Feature",
  "properties": {
    "iso:country":"ES",
    "sg:address":"Cra. Olot, S/n",
    "sg:city":"Manlleu",
    "sg:orig_category":"Molduras, Junquillos, Listones Y Molduras Perforadas",
    "sg:phone":"+34 938 51 40 55",
    "sg:postcode":"08560",
    "sg:province":"Barcelona",
    "wof:name":"Sadurni Pons Rosa",
    "wof:placetype":"venue"
},
  "geometry": {"coordinates":[2.2901299,42.0025444031],"type":"Point"}
}