{
  "type": "Feature",
  "properties": {
    "addr:full":"Ctra Nacional Ii, Km. 0486,0 Casc Antic Lleida 25241",
    "addr:postcode":"25241",
    "addr:street":"Ctra Nacional Ii Km. 0486,0 Casc",
    "iso:country":"ES",
    "sg:address":"Ctra Nacional Ii, Km. 0486,0",
    "sg:city":"Casc Antic",
    "sg:orig_category":"Suministros Para Carrocer\u00cdas",
    "sg:phone":"+34 973 60 25 09",
    "sg:postcode":"25241",
    "sg:province":"Lleida",
    "wof:name":"Maser Carrocerias S.l.",
    "wof:placetype":"venue"
},
  "geometry": {"coordinates":[0.6257824898,41.614151001],"type":"Point"}
}