{
  "type": "Feature",
  "properties": {
    "addr:full":"Cmno Pe\u00d1as (de Las), S/n Cari\u00f1ena Zaragoza 50400",
    "addr:postcode":"50400",
    "addr:street":"Cmno Pen\u0303As De Las S / N Carin\u0303Ena",
    "iso:country":"ES",
    "sg:address":"Cmno Pe\u00d1as (de Las), S/n",
    "sg:city":"Cari\u00f1ena",
    "sg:orig_category":"Florister\u00cdas",
    "sg:phone":"+34 976 62 03 02",
    "sg:postcode":"50400",
    "sg:province":"Zaragoza",
    "wof:name":"Talleres Tello Azcutia S.l.",
    "wof:placetype":"venue"
},
  "geometry": {"coordinates":[-1.2204350233,41.3379707336],"type":"Point"}
}