{
  "type": "Feature",
  "properties": {
    "addr:full":"Calle de Alces, 39 Alcazar S. Juan Ciudad Real 13600",
    "addr:housenumber":"39",
    "addr:postcode":"13600",
    "addr:street":"Calle De Alces;Alcazar S. Juan Ciudad Real",
    "iso:country":"ES",
    "sg:address":"Calle de Alces, 39",
    "sg:city":"Alcazar S. Juan",
    "sg:orig_category":"Fabricaci\u00d3n De Distribuidores Autom\u00c1ticos",
    "sg:phone":"+34 926 55 13 35",
    "sg:postcode":"13600",
    "sg:province":"Ciudad Real",
    "wof:name":"Blasco Maldonado Aurelio",
    "wof:placetype":"venue"
},
  "geometry": {"coordinates":[-3.2172403336,39.387676239],"type":"Point"}
}