{
  "type": "Feature",
  "properties": {
    "iso:country":"ES",
    "sg:address":"Calle de Guzman El Bueno, 39",
    "sg:city":"Madrid",
    "sg:orig_category":"Laboratorios Farmac\u00c9uticos",
    "sg:phone":"+34 915 43 66 19",
    "sg:postcode":"28015",
    "sg:province":"Madrid",
    "wof:name":"Lozano Huertas Cesareo",
    "wof:placetype":"venue"
},
  "geometry": {"coordinates":[-3.7134649754,40.4335861206],"type":"Point"}
}