{
  "type": "Feature",
  "properties": {
    "iso:country":"ES",
    "sg:address":"Calle de Mar De Kara, 5",
    "sg:city":"Madrid",
    "sg:classifiers":[
        {
            "category":"Autos & Motor Vehicles",
            "subcategory":"Automobile Sales",
            "type":"Retail Goods"
        }
    ],
    "sg:phone":"+34 913 81 51 82",
    "sg:postcode":"28033",
    "sg:province":"Madrid",
    "wof:name":"Alvarez De Paz Claudino",
    "wof:placetype":"venue"
},
  "geometry": {"coordinates":[-3.6441617012,40.471572876],"type":"Point"}
}