{
  "type": "Feature",
  "properties": {
    "iso:country":"ES",
    "sg:address":"Carretera De Villaturiel, 14",
    "sg:city":"Valdelafuente",
    "sg:orig_category":"Contenedores (mercanc\u00cdas)",
    "sg:phone":"+34 987 26 98 57",
    "sg:postcode":"24227",
    "sg:province":"Le\u00f3n",
    "wof:name":"Transportes Hilario Suarez S.l.",
    "wof:placetype":"venue"
},
  "geometry": {"coordinates":[-5.5144238472,42.5690765381],"type":"Point"}
}