{
  "type": "Feature",
  "properties": {
    "iso:country":"ES",
    "sg:address":"Bellotera, S/n",
    "sg:city":"Cullera",
    "sg:orig_category":"Empresas De Carpinter\u00cda De Madera",
    "sg:phone":"+34 961 73 19 08",
    "sg:postcode":"46400",
    "sg:province":"Valencia",
    "wof:name":"Fustecu S.l.",
    "wof:placetype":"venue"
},
  "geometry": {"coordinates":[-0.2588739991,39.1741714478],"type":"Point"}
}