{
  "type": "Feature",
  "properties": {
    "iso:country":"ES",
    "sg:address":"Calle de Greco, 2",
    "sg:city":"Salamanca",
    "sg:orig_category":"Bazares, Art\u00cdculos De Limpieza Y De Cocina (al Por Menor)",
    "sg:phone":"+34 923 22 43 65",
    "sg:postcode":"37004",
    "sg:province":"Salamanca",
    "wof:name":"Compleregalos S.l.",
    "wof:placetype":"venue"
},
  "geometry": {"coordinates":[-5.653637886,40.972026825],"type":"Point"}
}