{
  "type": "Feature",
  "properties": {
    "addr:full":"Calle de Martinez Simancas, 6 Toledo Toledo 45005",
    "addr:housenumber":"6",
    "addr:postcode":"45005",
    "addr:street":"Calle De Martinez Simancas",
    "iso:country":"ES",
    "sg:address":"Calle de Martinez Simancas, 6",
    "sg:city":"Toledo",
    "sg:orig_category":"Abogados",
    "sg:phone":"+34 925 22 44 86",
    "sg:postcode":"45005",
    "sg:province":"Toledo",
    "wof:name":"Romero Martin-caro Carlos Miguel",
    "wof:placetype":"venue"
},
  "geometry": {"coordinates":[-4.0369958878,39.8720703125],"type":"Point"}
}