{
  "type": "Feature",
  "properties": {
    "iso:country":"ES",
    "sg:address":"Calle de Alfonso Xi, 4",
    "sg:city":"Madrid",
    "sg:orig_category":"Asociaciones Humanitarias, De Cooperaci\u00d3n, De Acci\u00d3n Social",
    "sg:phone":"+34 915 31 35 77",
    "sg:postcode":"28014",
    "sg:province":"Madrid",
    "wof:name":"Confederacion De Federaciones Y Asociaciones De Viudas Hispania",
    "wof:placetype":"venue"
},
  "geometry": {"coordinates":[-3.6905269623,40.4190711975],"type":"Point"}
}