{
  "type": "Feature",
  "properties": {
    "addr:full":"Calle de Juan De Herrera, 24 Estepona M\u00e1laga 29680",
    "addr:housenumber":"24",
    "addr:postcode":"29680",
    "addr:street":"Calle De Juan De Herrera",
    "iso:country":"ES",
    "sg:address":"Calle de Juan De Herrera, 24",
    "sg:city":"Estepona",
    "sg:orig_category":"Empresas De Carpinter\u00cda De Madera",
    "sg:phone":"+34 952 80 21 33",
    "sg:postcode":"29680",
    "sg:province":"M\u00e1laga",
    "wof:name":"Vera Lopez Antonio",
    "wof:placetype":"venue"
},
  "geometry": {"coordinates":[-5.1678309441,36.4295310974],"type":"Point"}
}