{
  "type": "Feature",
  "properties": {
    "addr:full":"Crta. Bjoz-almdjo, Km. 0037,5 Badajoz Badajoz 06008",
    "addr:postcode":"06008",
    "addr:street":"Crta. Bjoz-Almdjo Km. 0037,5",
    "iso:country":"ES",
    "sg:address":"Crta. Bjoz-almdjo, Km. 0037,5",
    "sg:city":"Badajoz",
    "sg:orig_category":"Aceites Y Grasas Alimentarias (fabricaci\u00d3n, Al Por Mayor)",
    "sg:phone":"+34 924 14 04 76",
    "sg:postcode":"06008",
    "sg:province":"Badajoz",
    "wof:name":"Do\u00f1a Teresa S.a.",
    "wof:placetype":"venue"
},
  "geometry": {"coordinates":[-6.9430441856,38.8723373413],"type":"Point"}
}