{
  "type": "Feature",
  "properties": {
    "iso:country":"ES",
    "sg:address":"Calle de Santa Teresa, 39",
    "sg:city":"Fuentes De Andalucia",
    "sg:orig_category":"Bares, Piano",
    "sg:phone":"+34 954 83 79 25",
    "sg:postcode":"41420",
    "sg:province":"Sevilla",
    "wof:name":"Cabrera Rodriguez Jose Maria",
    "wof:placetype":"venue"
},
  "geometry": {"coordinates":[-5.3446249962,37.4608879089],"type":"Point"}
}