{
  "type": "Feature",
  "properties": {
    "iso:country":"ES",
    "sg:address":"Avda Ayora, 3",
    "sg:city":"Almansa",
    "sg:orig_category":"Electricidad, Electr\u00d3nica: Material Y Suministros (al Por Mayor)",
    "sg:phone":"+34 967 34 12 26",
    "sg:postcode":"02640",
    "sg:province":"Albacete",
    "wof:name":"Electro Almansa S.l.",
    "wof:placetype":"venue"
},
  "geometry": {"coordinates":[-1.1028850079,38.8706321716],"type":"Point"}
}