{
  "type": "Feature",
  "properties": {
    "iso:country":"ES",
    "sg:address":"Avda Bosques, 17",
    "sg:city":"Arteixo",
    "sg:orig_category":"Ense\u00d1anza: Profesiones Art\u00cdsticas",
    "sg:phone":"+34 981 63 39 50",
    "sg:postcode":"15142",
    "sg:province":"La Coru\u00f1a",
    "wof:name":"Estudio M Graphic Solutions S.l",
    "wof:placetype":"venue"
},
  "geometry": {"coordinates":[-8.5094585419,43.3042411804],"type":"Point"}
}