{
  "type": "Feature",
  "properties": {
    "iso:country":"ES",
    "sg:address":"Rua Nova, S/n",
    "sg:city":"Rubian",
    "sg:orig_category":"Restaurantes",
    "sg:phone":"+34 982 42 40 52",
    "sg:postcode":"27350",
    "sg:province":"Lugo",
    "wof:name":"Garcia Lopez Francisco",
    "wof:placetype":"venue"
},
  "geometry": {"coordinates":[-7.4779639244,42.6528358459],"type":"Point"}
}