{
  "type": "Feature",
  "properties": {
    "addr:full":"Rua Ramon Aller, 22 Lalin Pontevedra 36500",
    "addr:housenumber":"22",
    "addr:postcode":"36500",
    "addr:street":"Rua Ramon Aller",
    "iso:country":"ES",
    "sg:address":"Rua Ramon Aller, 22",
    "sg:city":"Lalin",
    "sg:orig_category":"Inform\u00c1tica, Ofim\u00c1tica (estudios, Asesor\u00cda, Ingenier\u00cda, Formaci\u00d3n)",
    "sg:phone":"+34 986 78 36 96",
    "sg:postcode":"36500",
    "sg:province":"Pontevedra",
    "wof:name":"Sistemas Informaticos Andion Y Mouri\u00f1o S.l.",
    "wof:placetype":"venue"
},
  "geometry": {"coordinates":[-8.1128444672,42.6615447998],"type":"Point"}
}