{
  "type": "Feature",
  "properties": {
    "addr:full":"Avda Federico Garcia Lorca, 20 Salobre\u00f1a Granada 18680",
    "addr:housenumber":"20",
    "addr:postcode":"18680",
    "addr:street":"Avda Federico Garcia Lorca",
    "iso:country":"ES",
    "sg:address":"Avda Federico Garcia Lorca, 20",
    "sg:city":"Salobre\u00f1a",
    "sg:orig_category":"Promotores Constructores",
    "sg:phone":"+34 958 61 71 48",
    "sg:postcode":"18680",
    "sg:province":"Granada",
    "wof:name":"Construcciones Perez Bueno E Hijos S.l.",
    "wof:placetype":"venue"
},
  "geometry": {"coordinates":[-3.5859520435,36.7411117554],"type":"Point"}
}