{
  "type": "Feature",
  "properties": {
    "iso:country":"ES",
    "sg:address":"Calle de Alfonso Xi, 32",
    "sg:city":"Alcala Real",
    "sg:orig_category":"Gastronom\u00cda: Especialidades Regionales (al Por Menor)",
    "sg:phone":"+34 953 58 17 62",
    "sg:postcode":"23680",
    "sg:province":"Ja\u00e9n",
    "wof:name":"Romero Villegas Mercedes",
    "wof:placetype":"venue"
},
  "geometry": {"coordinates":[-3.9240994453,37.4577331543],"type":"Point"}
}