{
  "type": "Feature",
  "properties": {
    "iso:country":"ES",
    "sg:address":"Avda Fraga Iribarne, 7",
    "sg:city":"Betanzos",
    "sg:orig_category":"Agentes, Concesionarios Y Sucursales De Veh\u00cdculos",
    "sg:phone":"+34 981 77 24 11",
    "sg:postcode":"15300",
    "sg:province":"A Coru\u00f1a",
    "wof:name":"Ventosa E Hijos S. A.",
    "wof:placetype":"venue"
},
  "geometry": {"coordinates":[-8.2186660767,43.275894165],"type":"Point"}
}