{
  "type": "Feature",
  "properties": {
    "addr:full":"Calle de Moreno De Vargas, 4 Merida Badajoz 06800",
    "addr:housenumber":"4",
    "addr:postcode":"06800",
    "addr:street":"Calle De Moreno De Vargas",
    "iso:country":"ES",
    "sg:address":"Calle de Moreno De Vargas, 4",
    "sg:city":"Merida",
    "sg:orig_category":"Diarios, Revistas Y Boletines (distribuidores)",
    "sg:phone":"+34 924 31 37 50",
    "sg:postcode":"06800",
    "sg:province":"Badajoz",
    "wof:name":"Torres Fonta Maria Bernabela",
    "wof:placetype":"venue"
},
  "geometry": {"coordinates":[-6.3442578316,38.9182510376],"type":"Point"}
}