{
  "type": "Feature",
  "properties": {
    "addr:full":"Calle de Nieves Cano, 63 Vitoria-gasteiz \u00c1lava 01007",
    "addr:housenumber":"63",
    "addr:postcode":"01007",
    "addr:street":"Calle De Nieves Cano",
    "iso:country":"ES",
    "sg:address":"Calle de Nieves Cano, 63",
    "sg:city":"Vitoria-gasteiz",
    "sg:orig_category":"Importaci\u00d3n",
    "sg:phone":"+34 945 15 01 51",
    "sg:postcode":"01007",
    "sg:province":"\u00c1lava",
    "wof:name":"Gimenez Alamillo Sole",
    "wof:placetype":"venue"
},
  "geometry": {"coordinates":[-2.6792690754,42.8392105103],"type":"Point"}
}