{
  "type": "Feature",
  "properties": {
    "addr:full":"Plaz Constitucion (de La), 12 Montemayor C\u00f3rdoba 14530",
    "addr:postcode":"14530",
    "iso:country":"ES",
    "sg:address":"Plaz Constitucion (de La), 12",
    "sg:city":"Montemayor",
    "sg:orig_category":"Cajas De Ahorro",
    "sg:phone":"+34 957 38 43 48",
    "sg:postcode":"14530",
    "sg:province":"C\u00f3rdoba",
    "wof:name":"Caja De Ahorros Y Monte De Piedad De Cordoba",
    "wof:placetype":"venue"
},
  "geometry": {"coordinates":[-4.6985411644,37.647151947],"type":"Point"}
}