{
  "type": "Feature",
  "properties": {
    "iso:country":"ES",
    "sg:address":"Calle de Omega, 48",
    "sg:city":"Madrid",
    "sg:orig_category":"Material Y Suministros Para Perforaciones, Sondeos",
    "sg:phone":"+34 913 71 96 13",
    "sg:postcode":"28032",
    "sg:province":"Madrid",
    "wof:name":"Sorando Rodriguez Ana Maria",
    "wof:placetype":"venue"
},
  "geometry": {"coordinates":[-3.6022748947,40.4001922607],"type":"Point"}
}