{
  "type": "Feature",
  "properties": {
    "addr:full":"Grup Zubiria Ybarra Tomas, 12 Bilbao Vizcaya 48007",
    "addr:housenumber":"12",
    "addr:postcode":"48007",
    "addr:street":"Tomas",
    "iso:country":"ES",
    "sg:address":"Grup Zubiria Ybarra Tomas, 12",
    "sg:city":"Bilbao",
    "sg:orig_category":"Asesor\u00cdas Y Estudios Financieros",
    "sg:phone":"+34 944 45 51 52",
    "sg:postcode":"48007",
    "sg:province":"Vizcaya",
    "wof:name":"Sunau Consultores Y Asesores S.l.l.",
    "wof:placetype":"venue"
},
  "geometry": {"coordinates":[-2.9171390533,43.265499115],"type":"Point"}
}