{
  "type": "Feature",
  "properties": {
    "iso:country":"ES",
    "sg:address":"Calle de Colon De Larreategui, 3",
    "sg:city":"Bilbao",
    "sg:orig_category":"Hosteler\u00cda, Empleados",
    "sg:phone":"+34 944 24 84 53",
    "sg:postcode":"48001",
    "sg:province":"Vizcaya",
    "wof:name":"Olabarria Rueda I\u00f1igo",
    "wof:placetype":"venue"
},
  "geometry": {"coordinates":[-2.9269125462,43.2623023987],"type":"Point"}
}