{
  "type": "Feature",
  "properties": {
    "addr:full":"Ctra Majadahonda (m-515), S/n Monteclaro-la Caba\u00e7a Madrid 28223",
    "addr:housenumber":"s",
    "addr:postcode":"28223",
    "addr:street":"Ctra Majadahonda M-515;/ N Monteclaro-La",
    "iso:country":"ES",
    "sg:address":"Ctra Majadahonda (m-515), S/n",
    "sg:city":"Monteclaro-la Caba\u00e7a",
    "sg:orig_category":"Asesor\u00cda Sobre Comunicaci\u00d3n De Empresas",
    "sg:phone":"+34 917 99 03 88",
    "sg:postcode":"28223",
    "sg:province":"Madrid",
    "sg:website":"www.aleco.org",
    "wof:name":"Aleco Europa S.l.",
    "wof:placetype":"venue"
},
  "geometry": {"coordinates":[-3.7003455162,40.4166908264],"type":"Point"}
}