{
  "type": "Feature",
  "properties": {
    "addr:full":"Calle de Abrucena, 54 Almeria Almer\u00eda 04007",
    "addr:housenumber":"54",
    "addr:postcode":"04007",
    "addr:street":"Calle De Abrucena",
    "iso:country":"ES",
    "sg:address":"Calle de Abrucena, 54",
    "sg:city":"Almeria",
    "sg:orig_category":"Supermercados Y Hipermercados",
    "sg:phone":"+34 950 26 38 69",
    "sg:postcode":"04007",
    "sg:province":"Almer\u00eda",
    "wof:name":"Superurci S.l.",
    "wof:placetype":"venue"
},
  "geometry": {"coordinates":[-2.4469070435,36.8281097412],"type":"Point"}
}