{
  "type": "Feature",
  "properties": {
    "addr:full":"Calle de Angel Guimera, 62 Valencia Valencia 46008",
    "addr:housenumber":"62",
    "addr:postcode":"46008",
    "addr:street":"Calle De Angel Guimera",
    "iso:country":"ES",
    "sg:address":"Calle de Angel Guimera, 62",
    "sg:city":"Valencia",
    "sg:orig_category":"Caf\u00c9s, Bares, Cervecer\u00cdas",
    "sg:phone":"+34 963 85 33 11",
    "sg:postcode":"46008",
    "sg:province":"Valencia",
    "wof:name":"Llano Andres Francisco",
    "wof:placetype":"venue"
},
  "geometry": {"coordinates":[-0.389973104,39.4693832397],"type":"Point"}
}