{
  "type": "Feature",
  "properties": {
    "addr:full":"Calle de Real, 6 Cartagena Murcia 30201",
    "addr:housenumber":"6",
    "addr:postcode":"30201",
    "addr:street":"Calle De Real",
    "iso:country":"ES",
    "sg:address":"Calle de Real, 6",
    "sg:city":"Cartagena",
    "sg:orig_category":"Caf\u00c9s, Bares, Cervecer\u00cdas",
    "sg:phone":"+34 968 52 98 18",
    "sg:postcode":"30201",
    "sg:province":"Murcia",
    "wof:name":"Cafeteria Francis Puerto S.l",
    "wof:placetype":"venue"
},
  "geometry": {"coordinates":[-0.9864929914,37.5990409851],"type":"Point"}
}