{
  "type": "Feature",
  "properties": {
    "iso:country":"ES",
    "sg:address":"Calle de Teniente Ochoa Olalla, 8",
    "sg:city":"Madrid",
    "sg:orig_category":"Fabricaci\u00d3n, Venta De Cuadros, Accesorios Para Enmarcar",
    "sg:phone":"+34 914 71 58 87",
    "sg:postcode":"28019",
    "sg:province":"Madrid",
    "wof:name":"Dominguez Iglesias Florencio",
    "wof:placetype":"venue"
},
  "geometry": {"coordinates":[-3.7328150272,40.3957672119],"type":"Point"}
}