{
  "type": "Feature",
  "properties": {
    "addr:full":"Calle de Herradores, 20 San Cristobal De La Laguna Santa Cruz De Tenerife 38204",
    "addr:housenumber":"20",
    "addr:postcode":"38204",
    "addr:street":"Calle De Herradores",
    "iso:country":"ES",
    "sg:address":"Calle de Herradores, 20",
    "sg:city":"San Cristobal De La Laguna",
    "sg:orig_category":"Ropa Para Se\u00d1oras (al Por Menor)",
    "sg:phone":"+34 922 63 33 70",
    "sg:postcode":"38204",
    "sg:province":"Santa Cruz De Tenerife",
    "wof:name":"Cubicuadro 2000 S.l.",
    "wof:placetype":"venue"
},
  "geometry": {"coordinates":[-16.3160438538,28.4870891571],"type":"Point"}
}