{
  "type": "Feature",
  "properties": {
    "addr:full":"Calle de Duque Severiano, 1 Cartagena Murcia 30205",
    "addr:housenumber":"1",
    "addr:postcode":"30205",
    "addr:street":"Calle De Duque Severiano",
    "iso:country":"ES",
    "sg:address":"Calle de Duque Severiano, 1",
    "sg:city":"Cartagena",
    "sg:orig_category":"Filatelia",
    "sg:phone":"+34 968 50 63 28",
    "sg:postcode":"30205",
    "sg:province":"Murcia",
    "wof:name":"Sanchez Alcaraz Antonio",
    "wof:placetype":"venue"
},
  "geometry": {"coordinates":[-0.9936609864,37.6101531982],"type":"Point"}
}