{
  "type": "Feature",
  "properties": {
    "addr:full":"Ctra. Andratx, S/n Peguera Islas Baleares 07160",
    "addr:housenumber":"s / n",
    "addr:postcode":"07160",
    "addr:street":"Ctra. Andratx",
    "iso:country":"ES",
    "sg:address":"Ctra. Andratx, S/n",
    "sg:city":"Peguera",
    "sg:orig_category":"Marroquiner\u00cda (confecci\u00d3n)",
    "sg:phone":"+34 971 68 68 44",
    "sg:postcode":"07160",
    "sg:province":"Islas Baleares",
    "wof:name":"Xu  Jun Rong",
    "wof:placetype":"venue"
},
  "geometry": {"coordinates":[2.4599046707,39.542301178],"type":"Point"}
}