{
  "type": "Feature",
  "properties": {
    "addr:full":"Calle de Carboneros, 14 Linea De La Concepcion C\u00e1diz 11300",
    "addr:housenumber":"14",
    "addr:postcode":"11300",
    "addr:street":"Calle De Carboneros;Ca\u0301Diz",
    "iso:country":"ES",
    "sg:address":"Calle de Carboneros, 14",
    "sg:city":"Linea De La Concepcion",
    "sg:orig_category":"Pod\u00d3logos: Pedicuros",
    "sg:phone":"+34 956 17 60 95",
    "sg:postcode":"11300",
    "sg:province":"C\u00e1diz",
    "wof:name":"Morales Guerrero Manuel",
    "wof:placetype":"venue"
},
  "geometry": {"coordinates":[-5.3507099152,36.161113739],"type":"Point"}
}