{
  "type": "Feature",
  "properties": {
    "addr:full":"Avda Blas Infante, S/n Alhaurin El Grande M\u00e1laga 29120",
    "addr:postcode":"29120",
    "addr:street":"Avda Blas Infante S / N",
    "iso:country":"ES",
    "sg:address":"Avda Blas Infante, S/n",
    "sg:city":"Alhaurin El Grande",
    "sg:orig_category":"Confecci\u00d3n De Ropa Interior",
    "sg:phone":"+34 952 49 11 17",
    "sg:postcode":"29120",
    "sg:province":"M\u00e1laga",
    "wof:name":"Aragon Plaza Isabel",
    "wof:placetype":"venue"
},
  "geometry": {"coordinates":[-4.6917982101,36.6372833252],"type":"Point"}
}