{
  "type": "Feature",
  "properties": {
    "iso:country":"ES",
    "sg:address":"Barr Aita Mari Auzategia, 18",
    "sg:city":"Zumaia",
    "sg:orig_category":"Perfumer\u00cda Y Cosm\u00c9tica (fabricaci\u00d3n, Al Por Mayor)",
    "sg:phone":"+34 943 86 16 59",
    "sg:postcode":"20750",
    "sg:province":"Guip\u00f9zcoa",
    "wof:name":"Arano Aizpurua Milagros",
    "wof:placetype":"venue"
},
  "geometry": {"coordinates":[-2.2590830326,43.2990760803],"type":"Point"}
}