{
  "type": "Feature",
  "properties": {
    "iso:country":"ES",
    "sg:address":"Calle de Molinos, 34",
    "sg:city":"Granada",
    "sg:orig_category":"Plomeros",
    "sg:phone":"+34 958 22 07 81",
    "sg:postcode":"18009",
    "sg:province":"Granada",
    "wof:name":"Norberto Rodriguez Francisco",
    "wof:placetype":"venue"
},
  "geometry": {"coordinates":[-3.5923540592,37.1724739075],"type":"Point"}
}