{
  "type": "Feature",
  "properties": {
    "addr:full":"Avda Ramon Pradera, 12 Valladolid Valladolid 47009",
    "addr:housenumber":"12",
    "addr:postcode":"47009",
    "addr:street":"Avda Ramon Pradera",
    "iso:country":"ES",
    "sg:address":"Avda Ramon Pradera, 12",
    "sg:city":"Valladolid",
    "sg:orig_category":"Industria Qu\u00cdmica",
    "sg:phone":"+34 983 37 82 86",
    "sg:postcode":"47009",
    "sg:province":"Valladolid",
    "wof:name":"Tratamientos De Residuos Sanitarios S.l.",
    "wof:placetype":"venue"
},
  "geometry": {"coordinates":[-4.7367949486,41.6571502686],"type":"Point"}
}