{
  "type": "Feature",
  "properties": {
    "iso:country":"ES",
    "sg:address":"Calle de General Espartero, 70",
    "sg:city":"Cieza",
    "sg:orig_category":"Carnicer\u00cdas, Carnicer\u00cdas",
    "sg:phone":"+34 968 76 20 65",
    "sg:postcode":"30530",
    "sg:province":"Murcia",
    "wof:name":"Alvarado Mendez Jose",
    "wof:placetype":"venue"
},
  "geometry": {"coordinates":[-1.4216239452,38.24010849],"type":"Point"}
}