{
  "type": "Feature",
  "properties": {
    "iso:country":"ES",
    "sg:address":"Calle de Martin De Saavedra, 7",
    "sg:city":"Cordoba",
    "sg:orig_category":"Promotores Constructores",
    "sg:phone":"+34 957 34 01 54",
    "sg:postcode":"14012",
    "sg:province":"C\u00f3rdoba",
    "wof:name":"Carmona Guerrero Jose",
    "wof:placetype":"venue"
},
  "geometry": {"coordinates":[-4.7840619087,37.9061164856],"type":"Point"}
}