{
  "type": "Feature",
  "properties": {
    "iso:country":"ES",
    "sg:address":"Rua San Roque, 17",
    "sg:city":"Xinzo De Limia",
    "sg:orig_category":"Carnicer\u00cdas, Carnicer\u00cdas",
    "sg:phone":"+34 988 46 26 60",
    "sg:postcode":"32630",
    "sg:province":"Ourense",
    "wof:name":"Iglesias Garcia Maria Jose",
    "wof:placetype":"venue"
},
  "geometry": {"coordinates":[-7.7260389328,42.0627403259],"type":"Point"}
}