{
  "type": "Feature",
  "properties": {
    "iso:country":"ES",
    "sg:address":"Carr Sequia (la), 40",
    "sg:city":"Cullera",
    "sg:orig_category":"Farmacias",
    "sg:phone":"+34 961 72 02 17",
    "sg:postcode":"46400",
    "sg:province":"Valencia",
    "wof:name":"Farmacia Margarita Y Juan Vallet Garcia C.b",
    "wof:placetype":"venue"
},
  "geometry": {"coordinates":[-0.2549650073,39.1649932861],"type":"Point"}
}