{
  "type": "Feature",
  "properties": {
    "iso:country":"ES",
    "sg:address":"Calle de Albatros, 3",
    "sg:city":"Alacant",
    "sg:orig_category":"Centros Empresariales",
    "sg:phone":"+34 965 26 75 22",
    "sg:postcode":"03540",
    "sg:province":"Alicante",
    "wof:name":"Luis Galindo Y Asociados",
    "wof:placetype":"venue"
},
  "geometry": {"coordinates":[-0.4143993855,38.3569602966],"type":"Point"}
}