{
  "type": "Feature",
  "properties": {
    "addr:full":"Calle de Lepanto, 1 Barco De Avila \u00c1vila 05600",
    "addr:housenumber":"1",
    "addr:postcode":"05600",
    "addr:street":"Calle De Lepanto;A\u0301Vila",
    "iso:country":"ES",
    "sg:address":"Calle de Lepanto, 1",
    "sg:city":"Barco De Avila",
    "sg:orig_category":"Colchones (fabricaci\u00d3n, Al Por Mayor, Al Por Menor)",
    "sg:phone":"+34 920 34 20 06",
    "sg:postcode":"05600",
    "sg:province":"\u00c1vila",
    "wof:name":"Alonso Martin Teresa",
    "wof:placetype":"venue"
},
  "geometry": {"coordinates":[-5.5219864845,40.3570404053],"type":"Point"}
}