{
  "type": "Feature",
  "properties": {
    "addr:full":"Ptge Joan Brillas, 14 Esplugues Llobregat Barcelona 08950",
    "addr:housenumber":"14",
    "addr:postcode":"08950",
    "addr:street":"Ptge Joan Brillas",
    "iso:country":"ES",
    "sg:address":"Ptge Joan Brillas, 14",
    "sg:city":"Esplugues Llobregat",
    "sg:orig_category":"Mec\u00c1nico Del Autom\u00d3vil",
    "sg:phone":"+34 933 71 65 98",
    "sg:postcode":"08950",
    "sg:province":"Barcelona",
    "wof:name":"Jimenez Zu\u00f1iga Antonio",
    "wof:placetype":"venue"
},
  "geometry": {"coordinates":[2.0806250572,41.3760147095],"type":"Point"}
}