{
  "type": "Feature",
  "properties": {
    "iso:country":"ES",
    "sg:address":"Carrer de Far, D'es (porto Petro), 5",
    "sg:city":"Porto Petro",
    "sg:orig_category":"Int\u00c9rpretes",
    "sg:phone":"+34 971 64 32 91",
    "sg:postcode":"07691",
    "sg:province":"Islas Baleares",
    "wof:name":"O Neil  Michael Jeffrey",
    "wof:placetype":"venue"
},
  "geometry": {"coordinates":[3.2090580463,39.3599433899],"type":"Point"}
}