{
  "type": "Feature",
  "properties": {
    "iso:country":"ES",
    "sg:address":"Calle de Lopez Abadia, 3",
    "sg:city":"Zaragoza",
    "sg:orig_category":"Promotores Constructores",
    "sg:phone":"+34 976 20 45 27",
    "sg:postcode":"50002",
    "sg:province":"Zaragoza",
    "wof:name":"Aurel Chiorean Radu",
    "wof:placetype":"venue"
},
  "geometry": {"coordinates":[-0.8669891953,41.6517295837],"type":"Point"}
}