{
  "type": "Feature",
  "properties": {
    "iso:country":"ES",
    "sg:address":"Carrer de Portes D'oriola, 11",
    "sg:city":"Crevillent",
    "sg:orig_category":"Muebles, Minoristas",
    "sg:phone":"+34 965 40 49 29",
    "sg:postcode":"03330",
    "sg:province":"Alicante",
    "wof:name":"Prieto Berna Jose Joaquin",
    "wof:placetype":"venue"
},
  "geometry": {"coordinates":[-0.8126829863,38.2444343567],"type":"Point"}
}