{
  "type": "Feature",
  "properties": {
    "addr:full":"Rua Salgueiral, 2 Redondela Pontevedra 36800",
    "addr:housenumber":"2",
    "addr:postcode":"36800",
    "addr:street":"Rua Salgueiral",
    "iso:country":"ES",
    "sg:address":"Rua Salgueiral, 2",
    "sg:city":"Redondela",
    "sg:orig_category":"Concepci\u00d3n Y Realizaci\u00d3n De Maquetas Profesionales Y Prototipos",
    "sg:phone":"+34 986 40 41 29",
    "sg:postcode":"36800",
    "sg:province":"Pontevedra",
    "wof:name":"Lago Blanco Miguel Angel",
    "wof:placetype":"venue"
},
  "geometry": {"coordinates":[-8.6113090515,42.2798805237],"type":"Point"}
}