{
  "type": "Feature",
  "properties": {
    "iso:country":"ES",
    "sg:address":"Calle de Marcelino Arana, 4",
    "sg:city":"Herrera Pisuerga",
    "sg:orig_category":"Iglesia Cat\u00d3lica",
    "sg:phone":"+34 979 13 04 80",
    "sg:postcode":"34400",
    "sg:province":"Palencia",
    "wof:name":"Parroquia De Santa Ana",
    "wof:placetype":"venue"
},
  "geometry": {"coordinates":[-4.3301439285,42.5948905945],"type":"Point"}
}