{
  "type": "Feature",
  "properties": {
    "addr:full":"Calle de De Cartagena, S/n Benavente Zamora 49600",
    "addr:housenumber":"s / n",
    "addr:postcode":"49600",
    "addr:street":"Calle De De Cartagena",
    "iso:country":"ES",
    "sg:address":"Calle de De Cartagena, S/n",
    "sg:city":"Benavente",
    "sg:orig_category":"Herboristas (al Por Menor)",
    "sg:phone":"+34 980 63 27 02",
    "sg:postcode":"49600",
    "sg:province":"Zamora",
    "wof:name":"Becares Gonzalo Florentina",
    "wof:placetype":"venue"
},
  "geometry": {"coordinates":[-5.6782541275,42.0037155151],"type":"Point"}
}