{
  "type": "Feature",
  "properties": {
    "iso:country":"ES",
    "sg:address":"Calle de Doctor Nacher, 58",
    "sg:city":"Chiva",
    "sg:orig_category":"Cajas Para Embalar",
    "sg:phone":"+34 962 52 10 25",
    "sg:postcode":"46370",
    "sg:province":"Valencia",
    "sg:website":"www.cajacampo.es",
    "wof:name":"Caja Campo",
    "wof:placetype":"venue"
},
  "geometry": {"coordinates":[-0.7168599963,39.4712295532],"type":"Point"}
}