{
  "type": "Feature",
  "properties": {
    "iso:country":"ES",
    "sg:address":"Avda Alcarria (de La), 10",
    "sg:city":"Alcala Henares",
    "sg:orig_category":"Muebles, Minoristas",
    "sg:phone":"+34 918 82 60 80",
    "sg:postcode":"28806",
    "sg:province":"Madrid",
    "wof:name":"Sasac Mobiliario S.l.",
    "wof:placetype":"venue"
},
  "geometry": {"coordinates":[-3.3637499809,40.4920654297],"type":"Point"}
}