{
  "type": "Feature",
  "properties": {
    "iso:country":"ES",
    "sg:address":"Poli Pol.indust. Cami Dels Frares, 16",
    "sg:city":"Lleida",
    "sg:orig_category":"Alimentaci\u00d3n General (al Por Mayor)",
    "sg:phone":"+34 973 25 73 10",
    "sg:postcode":"25191",
    "sg:province":"Lleida",
    "wof:name":"Aviram I Conill S.l.",
    "wof:placetype":"venue"
},
  "geometry": {"coordinates":[0.6630749702,41.6341972351],"type":"Point"}
}