{
  "type": "Feature",
  "properties": {
    "iso:country":"ES",
    "sg:address":"Kiriki Kalea, 2",
    "sg:city":"Zarautz",
    "sg:classifiers":[
        {
            "category":"Autos & Motor Vehicles",
            "subcategory":"Automobile Sales",
            "type":"Retail Goods"
        }
    ],
    "sg:phone":"+34 943 13 40 82",
    "sg:postcode":"20800",
    "sg:province":"Guip\u00f9zcoa",
    "wof:name":"Jolmar Autoeskola, S.l.",
    "wof:placetype":"venue"
},
  "geometry": {"coordinates":[-2.1761879921,43.2853317261],"type":"Point"}
}