{
  "type": "Feature",
  "properties": {
    "iso:country":"ES",
    "sg:address":"Carrer de Moratin, 106",
    "sg:city":"Sabadell",
    "sg:orig_category":"M\u00c1rmoles, Granitos Y Piedras Naturales",
    "sg:phone":"+34 937 26 29 95",
    "sg:postcode":"08206",
    "sg:province":"Barcelona",
    "wof:name":"Castro Cazorla Manuel Gerardo",
    "wof:placetype":"venue"
},
  "geometry": {"coordinates":[2.094810009,41.5466384888],"type":"Point"}
}