{
  "type": "Feature",
  "properties": {
    "iso:country":"ES",
    "sg:address":"Ctra Carretera Carrion (poligono Industrial), S/n",
    "sg:city":"Ciudad Real",
    "sg:orig_category":"Agentes, Concesionarios Y Sucursales De Veh\u00cdculos",
    "sg:phone":"+34 926 22 46 00",
    "sg:postcode":"13005",
    "sg:province":"Ciudad Real",
    "wof:name":"Abrego Automoviles S.a.",
    "wof:placetype":"venue"
},
  "geometry": {"coordinates":[-4.008256,38.981602],"type":"Point"}
}