{
  "type": "Feature",
  "properties": {
    "addr:full":"Alsina I Sensat, 8 El Masnou Barcelona 08320",
    "addr:housenumber":"8",
    "addr:postcode":"08320",
    "addr:street":"Alsina;Sensat",
    "iso:country":"ES",
    "sg:address":"Alsina I Sensat, 8",
    "sg:city":"El Masnou",
    "sg:orig_category":"Hielo Artificial (fabricaci\u00d3n, Distribuci\u00d3n)",
    "sg:phone":"+34 935 55 56 51",
    "sg:postcode":"08320",
    "sg:province":"Barcelona",
    "wof:name":"Lingua S.cv.",
    "wof:placetype":"venue"
},
  "geometry": {"coordinates":[2.3235640526,41.4803733826],"type":"Point"}
}