{
  "type": "Feature",
  "properties": {
    "addr:full":"Carrer de Bonaigua, 20 Sabadell Barcelona 08207",
    "addr:housenumber":"20",
    "addr:postcode":"08207",
    "addr:street":"Carrer De Bonaigua",
    "iso:country":"ES",
    "sg:address":"Carrer de Bonaigua, 20",
    "sg:city":"Sabadell",
    "sg:orig_category":"Platos Preparados Refrigerados (fabricaci\u00d3n, Al Por Mayor)",
    "sg:phone":"+34 937 17 80 83",
    "sg:postcode":"08207",
    "sg:province":"Barcelona",
    "wof:name":"Ferreteria Lampisteria Bonaigua S.l",
    "wof:placetype":"venue"
},
  "geometry": {"coordinates":[2.088463068,41.5692405701],"type":"Point"}
}