{
  "type": "Feature",
  "properties": {
    "addr:full":"Gralmo. Franco, 85 Endrinal Salamanca 37766",
    "addr:housenumber":"85",
    "addr:postcode":"37766",
    "iso:country":"ES",
    "sg:address":"Gralmo. Franco, 85",
    "sg:city":"Endrinal",
    "sg:orig_category":"Transportes Por Carretera: Lotes Completos, Mercanc\u00cdas Diversas",
    "sg:phone":"+34 923 15 00 59",
    "sg:postcode":"37766",
    "sg:province":"Salamanca",
    "wof:name":"Baratti Payan Adriana Noemi",
    "wof:placetype":"venue"
},
  "geometry": {"coordinates":[-5.782889843,40.6566314697],"type":"Point"}
}