{
  "type": "Feature",
  "properties": {
    "iso:country":"ES",
    "sg:address":"Pase Limonar, 32",
    "sg:city":"Malaga",
    "sg:orig_category":"Arquitectos",
    "sg:phone":"+34 952 22 46 07",
    "sg:postcode":"29016",
    "sg:province":"M\u00e1laga",
    "wof:name":"Medina Paez Juan Antonio",
    "wof:placetype":"venue"
},
  "geometry": {"coordinates":[-4.3981428146,36.7268753052],"type":"Point"}
}