{
  "type": "Feature",
  "properties": {
    "iso:country":"ES",
    "sg:address":"Calle de Portugal, S/n",
    "sg:city":"Gondomar",
    "sg:orig_category":"Sanatorios M\u00c9dico",
    "sg:phone":"+34 986 36 07 81",
    "sg:postcode":"36380",
    "sg:province":"Pontevedra",
    "wof:name":"Ayuntamiento De Gondomar",
    "wof:placetype":"venue"
},
  "geometry": {"coordinates":[-8.7619876862,42.1108131409],"type":"Point"}
}