{
  "type": "Feature",
  "properties": {
    "iso:country":"ES",
    "sg:address":"Esplanada, 17",
    "sg:city":"Ubeda",
    "sg:orig_category":"Iglesia Cat\u00d3lica",
    "sg:phone":"+34 953 75 10 61",
    "sg:postcode":"23400",
    "sg:province":"Ja\u00e9n",
    "wof:name":"Parroquia San Isidoro",
    "wof:placetype":"venue"
},
  "geometry": {"coordinates":[-3.3713839054,38.0111618042],"type":"Point"}
}