{
  "type": "Feature",
  "properties": {
    "iso:country":"ES",
    "sg:address":"Calle de Londres, 1",
    "sg:city":"Valladolid",
    "sg:orig_category":"Asilos De Ancianos. Centros Privados",
    "sg:phone":"+34 983 45 62 34",
    "sg:postcode":"47008",
    "sg:province":"Valladolid",
    "wof:name":"Sanidad Y Residencia Xxi S.a.",
    "wof:placetype":"venue"
},
  "geometry": {"coordinates":[-4.7683548927,41.6167297363],"type":"Point"}
}