{
  "type": "Feature",
  "properties": {
    "iso:country":"ES",
    "sg:address":"Carr Ample, 27",
    "sg:city":"Blanes",
    "sg:orig_category":"Carnicer\u00cdas, Carnicer\u00cdas",
    "sg:phone":"+34 972 33 00 97",
    "sg:postcode":"17300",
    "sg:province":"Girona",
    "wof:name":"Clusells Queldra Antonio",
    "wof:placetype":"venue"
},
  "geometry": {"coordinates":[2.7916579247,41.6746520996],"type":"Point"}
}