{
  "type": "Feature",
  "properties": {
    "addr:full":"Ptge Sant Bernat, 6 Barcelona Barcelona 08001",
    "addr:housenumber":"6",
    "addr:postcode":"08001",
    "addr:street":"Ptge Sant Bernat",
    "iso:country":"ES",
    "sg:address":"Ptge Sant Bernat, 6",
    "sg:city":"Barcelona",
    "sg:orig_category":"Arquitectos",
    "sg:phone":"+34 933 42 48 79",
    "sg:postcode":"08001",
    "sg:province":"Barcelona",
    "wof:name":"Roig Aviles Pau",
    "wof:placetype":"venue"
},
  "geometry": {"coordinates":[2.1649110317,41.3838310242],"type":"Point"}
}