{
  "type": "Feature",
  "properties": {
    "iso:country":"ES",
    "sg:address":"Calle de Isaac Peral, 1",
    "sg:city":"Avila",
    "sg:orig_category":"M\u00c9dicos: Estomatolog\u00cda",
    "sg:phone":"+34 920 25 21 49",
    "sg:postcode":"05001",
    "sg:province":"\u00c1vila",
    "wof:name":"Lopez Bartolome Maria Micaela",
    "wof:placetype":"venue"
},
  "geometry": {"coordinates":[-4.6916060448,40.6559333801],"type":"Point"}
}