{
  "type": "Feature",
  "properties": {
    "addr:full":"Calle de Juan Ramon Jimenez, 2 Carlota C\u00f3rdoba 14100",
    "addr:housenumber":"2",
    "addr:postcode":"14100",
    "addr:street":"Calle De Juan Ramon Jimenez;Co\u0301Rdoba",
    "iso:country":"ES",
    "sg:address":"Calle de Juan Ramon Jimenez, 2",
    "sg:city":"Carlota",
    "sg:orig_category":"Loter\u00cda Y T\u00d3mbola",
    "sg:phone":"+34 957 30 00 78",
    "sg:postcode":"14100",
    "sg:province":"C\u00f3rdoba",
    "wof:name":"Sanchez Abad Maria Jose",
    "wof:placetype":"venue"
},
  "geometry": {"coordinates":[-4.93379879,37.6733589172],"type":"Point"}
}