{
  "type": "Feature",
  "properties": {
    "addr:full":"Av Flors (les), 3 S. Joan Despi Barcelona 08970",
    "addr:postcode":"08970",
    "addr:street":"Av Flors Les 3 S. Joan Despi",
    "iso:country":"ES",
    "sg:address":"Av Flors (les), 3",
    "sg:city":"S. Joan Despi",
    "sg:orig_category":"Cajas De Ahorro",
    "sg:phone":"+34 934 77 39 11",
    "sg:postcode":"08970",
    "sg:province":"Barcelona",
    "wof:name":"Caixa D'estalvis De Catalunya",
    "wof:placetype":"venue"
},
  "geometry": {"coordinates":[2.0709750652,41.365486145],"type":"Point"}
}