{
  "type": "Feature",
  "properties": {
    "addr:full":"Calle de Villavieja, 1 Alacant Alicante 03002",
    "addr:housenumber":"1",
    "addr:postcode":"03002",
    "addr:street":"Calle De Villavieja",
    "iso:country":"ES",
    "sg:address":"Calle de Villavieja, 1",
    "sg:city":"Alacant",
    "sg:orig_category":"Museos",
    "sg:phone":"+34 965 14 09 59",
    "sg:postcode":"03002",
    "sg:province":"Alicante",
    "wof:name":"Patronato Municipal De La Cultura D'alacant",
    "wof:placetype":"venue"
},
  "geometry": {"coordinates":[-0.480031997,38.346206665],"type":"Point"}
}