{
  "type": "Feature",
  "properties": {
    "iso:country":"ES",
    "sg:address":"Avda Marconi, S/n",
    "sg:city":"Madrid",
    "sg:orig_category":"Suministros Y Materiales Industriales",
    "sg:phone":"+34 917 98 78 79",
    "sg:postcode":"28021",
    "sg:province":"Madrid",
    "wof:name":"Slind Parts S.a.",
    "wof:placetype":"venue"
},
  "geometry": {"coordinates":[-3.695168972,40.3340301514],"type":"Point"}
}