{
  "type": "Feature",
  "properties": {
    "iso:country":"ES",
    "sg:address":"Hondartza Kalea, 2",
    "sg:city":"Deba",
    "sg:orig_category":"Relojer\u00cda (al Por Menor, Reparaci\u00d3n)",
    "sg:phone":"+34 943 19 18 71",
    "sg:postcode":"20820",
    "sg:province":"Guip\u00f9zcoa",
    "wof:name":"Ballesteros Salom Pedro",
    "wof:placetype":"venue"
},
  "geometry": {"coordinates":[-2.3554708958,43.2941970825],"type":"Point"}
}