{
  "type": "Feature",
  "properties": {
    "iso:country":"ES",
    "sg:address":"Calle de Menendez Pidal, 12",
    "sg:city":"Quesada",
    "sg:orig_category":"Empresas De Desmonte",
    "sg:phone":"+34 953 71 40 66",
    "sg:postcode":"23480",
    "sg:province":"Ja\u00e9n",
    "wof:name":"Torreser S.l.",
    "wof:placetype":"venue"
},
  "geometry": {"coordinates":[-3.0693171024,37.8430480957],"type":"Point"}
}