{
  "type": "Feature",
  "properties": {
    "addr:full":"Cllo Peligros, 3 San Lorenzo Murcia 30001",
    "addr:housenumber":"3",
    "addr:postcode":"30001",
    "addr:street":"Peligros",
    "iso:country":"ES",
    "sg:address":"Cllo Peligros, 3",
    "sg:city":"San Lorenzo",
    "sg:orig_category":"Financiaci\u00d3n Y Cr\u00c9ditos",
    "sg:phone":"+34 900 46 01 75",
    "sg:postcode":"30001",
    "sg:province":"Murcia",
    "sg:website":"www.creditosehipotecas.com",
    "wof:name":"Proindiviso Hipotecas E Inmuebles S.l.",
    "wof:placetype":"venue"
},
  "geometry": {"coordinates":[-1.1302490234,37.9829597473],"type":"Point"}
}