{
  "type": "Feature",
  "properties": {
    "iso:country":"ES",
    "sg:address":"Carrer de Doctor Zamenhof, 2",
    "sg:city":"Rubi",
    "sg:orig_category":"Fabricaci\u00d3n De Su\u00c9ters Y Chalecos De Punto",
    "sg:phone":"+34 936 99 60 23",
    "sg:postcode":"08191",
    "sg:province":"Barcelona",
    "wof:name":"Debant Fontanet Joan",
    "wof:placetype":"venue"
},
  "geometry": {"coordinates":[2.0325300694,41.4974861145],"type":"Point"}
}