{
  "type": "Feature",
  "properties": {
    "addr:full":"Pg Sant Joan, 140 Barcelona Barcelona 08037",
    "addr:housenumber":"140",
    "addr:postcode":"08037",
    "addr:street":"Pg Sant Joan",
    "iso:country":"ES",
    "sg:address":"Pg Sant Joan, 140",
    "sg:city":"Barcelona",
    "sg:orig_category":"M\u00c9dicos: Foniatr\u00cda Y Logopedia",
    "sg:phone":"+34 934 59 16 22",
    "sg:postcode":"08037",
    "sg:province":"Barcelona",
    "wof:name":"Pamies Fabregat Maria Del Carmen",
    "wof:placetype":"venue"
},
  "geometry": {"coordinates":[2.1674931049,41.4013710022],"type":"Point"}
}