{
  "type": "Feature",
  "properties": {
    "iso:country":"ES",
    "sg:address":"Avda Ciudad De Barcelona, 144",
    "sg:city":"Madrid",
    "sg:orig_category":"Librer\u00cdas",
    "sg:phone":"+34 915 52 69 47",
    "sg:postcode":"28007",
    "sg:province":"Madrid",
    "wof:name":"Baro Fernandez Belen",
    "wof:placetype":"venue"
},
  "geometry": {"coordinates":[-3.6785399914,40.403087616],"type":"Point"}
}