{
  "type": "Feature",
  "properties": {
    "iso:country":"ES",
    "sg:address":"Rua Plazas (as), 14",
    "sg:city":"Vilanova",
    "sg:orig_category":"Asesor\u00cda Fiscal Y Jur\u00cddica",
    "sg:phone":"+34 982 12 12 07",
    "sg:postcode":"27760",
    "sg:province":"Lugo",
    "wof:name":"Arela Asesoria C. B.",
    "wof:placetype":"venue"
},
  "geometry": {"coordinates":[-7.2963733673,43.4700698853],"type":"Point"}
}