{
  "type": "Feature",
  "properties": {
    "iso:country":"ES",
    "sg:address":"Carr Coral, 11",
    "sg:city":"Port D'alcudia",
    "sg:orig_category":"M\u00c9dicos: Estomatolog\u00cda",
    "sg:phone":"+34 971 54 80 75",
    "sg:postcode":"07410",
    "sg:province":"Islas Baleares",
    "wof:name":"Plomer Serra Juana Maria",
    "wof:placetype":"venue"
},
  "geometry": {"coordinates":[3.1312530041,39.84349823],"type":"Point"}
}