{
  "type": "Feature",
  "properties": {
    "addr:full":"Calle de Zaragoza, 19 Guadalajara Guadalajara 19005",
    "addr:postcode":"19005",
    "addr:street":"Calle De Zaragoza 19",
    "iso:country":"ES",
    "sg:address":"Calle de Zaragoza, 19",
    "sg:city":"Guadalajara",
    "sg:orig_category":"Peluquer\u00cdas, Peluquer\u00cda Mixta",
    "sg:phone":"+34 949 21 71 57",
    "sg:postcode":"19005",
    "sg:province":"Guadalajara",
    "wof:name":"Sonia Martinez Ayuso Y Otra Cdad",
    "wof:placetype":"venue"
},
  "geometry": {"coordinates":[-3.1539947987,40.636264801],"type":"Point"}
}