{
  "type": "Feature",
  "properties": {
    "iso:country":"ES",
    "sg:address":"Muel Tomas Olabarri, 2",
    "sg:city":"Arenas -areeta",
    "sg:orig_category":"Construcciones Navales Y Fluviales",
    "sg:phone":"+34 944 63 48 11",
    "sg:postcode":"48930",
    "sg:province":"Vizcaya",
    "wof:name":"Maritima De Axpe S. A.",
    "wof:placetype":"venue"
},
  "geometry": {"coordinates":[-3.012814045,43.3212966919],"type":"Point"}
}