{
  "type": "Feature",
  "properties": {
    "iso:country":"ES",
    "sg:address":"Pase Ribalta, 16",
    "sg:city":"Castellon",
    "sg:orig_category":"Supermercados Y Hipermercados",
    "sg:phone":"+34 964 24 57 77",
    "sg:postcode":"12004",
    "sg:province":"Castell\u00f3n",
    "sg:website":"www.mercadona.es",
    "wof:name":"Mercadona S.a.",
    "wof:placetype":"venue"
},
  "geometry": {"coordinates":[-0.0279866997,40.0120239258],"type":"Point"}
}