{
  "type": "Feature",
  "properties": {
    "addr:full":"Calle de Sierra De Grazalema, S/n Malaga M\u00e1laga 29016",
    "addr:housenumber":"s / n",
    "addr:postcode":"29016",
    "addr:street":"Calle De Sierra De Grazalema;Ma\u0301Laga",
    "iso:country":"ES",
    "sg:address":"Calle de Sierra De Grazalema, S/n",
    "sg:city":"Malaga",
    "sg:orig_category":"Bancos",
    "sg:phone":"+34 952 22 59 40",
    "sg:postcode":"29016",
    "sg:province":"M\u00e1laga",
    "sg:website":"www.bancopopular.es",
    "wof:name":"Banco Popular Espa\u00f1ol",
    "wof:placetype":"venue"
},
  "geometry": {"coordinates":[-4.4029040337,36.7314109802],"type":"Point"}
}