{
  "type": "Feature",
  "properties": {
    "addr:full":"Av Principe Felipe De Borbon, Km. 0162,6 Las Pedro\u00f1eras Cuenca 16660",
    "addr:postcode":"16660",
    "addr:street":"Av Principe Felipe De Borbon Km. 0162,6 Las",
    "iso:country":"ES",
    "sg:address":"Av Principe Felipe De Borbon, Km. 0162,6",
    "sg:city":"Las Pedro\u00f1eras",
    "sg:orig_category":"Restaurantes",
    "sg:phone":"+34 967 16 03 30",
    "sg:postcode":"16660",
    "sg:province":"Cuenca",
    "wof:name":"Asencar S.l.",
    "wof:placetype":"venue"
},
  "geometry": {"coordinates":[-2.6387794018,39.4773025513],"type":"Point"}
}