{
  "type": "Feature",
  "properties": {
    "addr:full":"Navas De Tolosa, 5 Iru\u00f1a Navarra 31002",
    "addr:housenumber":"5",
    "addr:postcode":"31002",
    "addr:street":"Navas;Tolosa",
    "iso:country":"ES",
    "sg:address":"Navas De Tolosa, 5",
    "sg:city":"Iru\u00f1a",
    "sg:orig_category":"Plomeros",
    "sg:phone":"+34 948 22 72 44",
    "sg:postcode":"31002",
    "sg:province":"Navarra",
    "wof:name":"Ochoa Lacar Hermanos S. L.",
    "wof:placetype":"venue"
},
  "geometry": {"coordinates":[-1.6474839449,42.8150215149],"type":"Point"}
}