{
  "type": "Feature",
  "properties": {
    "addr:full":"Carrer de Rasa, 106 Terrassa Barcelona 08221",
    "addr:housenumber":"106",
    "addr:postcode":"08221",
    "addr:street":"Carrer De Rasa",
    "iso:country":"ES",
    "sg:address":"Carrer de Rasa, 106",
    "sg:city":"Terrassa",
    "sg:orig_category":"Frutas Y Legumbres Frescas (al Por Mayor)",
    "sg:phone":"+34 937 88 11 13",
    "sg:postcode":"08221",
    "sg:province":"Barcelona",
    "wof:name":"Alfaro Jimenez Ricardo",
    "wof:placetype":"venue"
},
  "geometry": {"coordinates":[2.0086784363,41.5639305115],"type":"Point"}
}