{
  "type": "Feature",
  "properties": {
    "iso:country":"ES",
    "sg:address":"La Constitucion, S/n",
    "sg:city":"Torla",
    "sg:orig_category":"Bazares, Art\u00cdculos De Limpieza Y De Cocina (al Por Menor)",
    "sg:phone":"+34 974 48 64 54",
    "sg:postcode":"22376",
    "sg:province":"Huesca",
    "sg:website":"www.ordesa.com/tienda",
    "wof:name":"Olivan Nerin Maria Mercedes",
    "wof:placetype":"venue"
},
  "geometry": {"coordinates":[-0.1121039987,42.627658844],"type":"Point"}
}