{
  "type": "Feature",
  "properties": {
    "addr:full":"Calle de Infancia, 6 Gijon Asturias 33207",
    "addr:housenumber":"6",
    "addr:postcode":"33207",
    "addr:street":"Calle De Infancia",
    "iso:country":"ES",
    "sg:address":"Calle de Infancia, 6",
    "sg:city":"Gijon",
    "sg:orig_category":"Comercio De Piezas De Recambio Y De Accesorios De Veh\u00cdculos, Veh\u00cdculos Industriales",
    "sg:phone":"+34 985 34 67 05",
    "sg:postcode":"33207",
    "sg:province":"Asturias",
    "wof:name":"Repuestos Gualsan S. A.",
    "wof:placetype":"venue"
},
  "geometry": {"coordinates":[-5.6663980484,43.5384712219],"type":"Point"}
}