{
  "type": "Feature",
  "properties": {
    "addr:full":"Trva Colombia, 5 Toledo Toledo 45004",
    "addr:housenumber":"5",
    "addr:postcode":"45004",
    "addr:street":"Trva Colombia",
    "iso:country":"ES",
    "sg:address":"Trva Colombia, 5",
    "sg:city":"Toledo",
    "sg:orig_category":"Muebles, Minoristas",
    "sg:phone":"+34 925 25 33 44",
    "sg:postcode":"45004",
    "sg:province":"Toledo",
    "wof:name":"Izquierdo Lopez Alejandro",
    "wof:placetype":"venue"
},
  "geometry": {"coordinates":[-4.0316691399,39.8676567078],"type":"Point"}
}