{
  "type": "Feature",
  "properties": {
    "iso:country":"ES",
    "sg:address":"El Muelle, S/n",
    "sg:city":"Puerto De Vega",
    "sg:orig_category":"Construcciones Navales Y Fluviales",
    "sg:phone":"+34 985 64 90 59",
    "sg:postcode":"33790",
    "sg:province":"Asturias",
    "wof:name":"Astilleros La Venecia S.l.",
    "wof:placetype":"venue"
},
  "geometry": {"coordinates":[-6.6459307671,43.5649147034],"type":"Point"}
}