{
  "type": "Feature",
  "properties": {
    "iso:country":"ES",
    "sg:address":"Calle de Calvario, 32",
    "sg:city":"Ezcaray",
    "sg:orig_category":"Herramientas Manuales (fabricaci\u00d3n, Al Por Mayor)",
    "sg:phone":"+34 941 35 40 19",
    "sg:postcode":"26280",
    "sg:province":"La Rioja",
    "wof:name":"Saurjo S.l.",
    "wof:placetype":"venue"
},
  "geometry": {"coordinates":[-3.0127708912,42.324924469],"type":"Point"}
}