{
  "type": "Feature",
  "properties": {
    "iso:country":"ES",
    "sg:address":"Calle de Almeria, 10",
    "sg:city":"Onda",
    "sg:orig_category":"Empresas De Desmonte",
    "sg:phone":"+34 964 60 17 36",
    "sg:postcode":"12200",
    "sg:province":"Castell\u00f3n",
    "wof:name":"Garcia Sanchez Juana",
    "wof:placetype":"venue"
},
  "geometry": {"coordinates":[-0.2576403916,39.9625205994],"type":"Point"}
}