{
  "type": "Feature",
  "properties": {
    "addr:full":"Barr Llao (el), S/n Llaos Cantabria 39547",
    "addr:postcode":"39547",
    "addr:street":"El S / N",
    "iso:country":"ES",
    "sg:address":"Barr Llao (el), S/n",
    "sg:city":"Llaos",
    "sg:orig_category":"Negocio De Madera",
    "sg:phone":"+34 942 71 02 18",
    "sg:postcode":"39547",
    "sg:province":"Cantabria",
    "wof:name":"Armando Alvarez S. A.",
    "wof:placetype":"venue"
},
  "geometry": {"coordinates":[-3.9878427982,43.1828384399],"type":"Point"}
}