{
  "type": "Feature",
  "properties": {
    "addr:full":"Avda Doctor Mara\u00d1on, 8 Puerto De Santa Maria C\u00e1diz 11500",
    "addr:housenumber":"8",
    "addr:postcode":"11500",
    "addr:street":"Avda Doctor Maran\u0303On;Ca\u0301Diz",
    "iso:country":"ES",
    "sg:address":"Avda Doctor Mara\u00d1on, 8",
    "sg:city":"Puerto De Santa Maria",
    "sg:orig_category":"Fabricaci\u00d3n, Importaci\u00d3n, Venta De Material De Telefon\u00cda, Peritelefon\u00cda",
    "sg:phone":"+34 956 86 05 99",
    "sg:postcode":"11500",
    "sg:province":"C\u00e1diz",
    "wof:name":"Garcia Requejo Maria Carmen",
    "wof:placetype":"venue"
},
  "geometry": {"coordinates":[-6.2405133247,36.5962257385],"type":"Point"}
}