{
  "type": "Feature",
  "properties": {
    "addr:full":"Avda Guadalquivir, S/n Cantillana Sevilla 41320",
    "addr:postcode":"41320",
    "addr:street":"Avda Guadalquivir S / N",
    "iso:country":"ES",
    "sg:address":"Avda Guadalquivir, S/n",
    "sg:city":"Cantillana",
    "sg:orig_category":"Empresas De Carpinter\u00cda Met\u00c1lica",
    "sg:phone":"+34 955 73 09 99",
    "sg:postcode":"41320",
    "sg:province":"Sevilla",
    "wof:name":"Pino Pe\u00f1a Jose",
    "wof:placetype":"venue"
},
  "geometry": {"coordinates":[-5.8265237808,37.6098403931],"type":"Point"}
}