{
  "type": "Feature",
  "properties": {
    "iso:country":"ES",
    "sg:address":"Rua Carreiro, 10",
    "sg:city":"Agui\u00f1o",
    "sg:orig_category":"Estancos",
    "sg:phone":"+34 981 84 00 76",
    "sg:postcode":"15965",
    "sg:province":"La Coru\u00f1a",
    "wof:name":"Perez Sampedro Cipriana",
    "wof:placetype":"venue"
},
  "geometry": {"coordinates":[-9.0167226791,42.5235595703],"type":"Point"}
}