{
  "type": "Feature",
  "properties": {
    "iso:country":"ES",
    "sg:address":"Avda Alay, S/n",
    "sg:city":"Arroyo De La Miel-benalmadena Costa",
    "sg:orig_category":"Medias Y Calcetines (al Por Menor)",
    "sg:phone":"+34 952 44 67 48",
    "sg:postcode":"29630",
    "sg:province":"M\u00e1laga",
    "wof:name":"Sarria Garcia San Miguel Delia",
    "wof:placetype":"venue"
},
  "geometry": {"coordinates":[-4.516644001,36.5980415344],"type":"Point"}
}