{
  "type": "Feature",
  "properties": {
    "iso:country":"ES",
    "sg:address":"Plaz San Vicente, 17",
    "sg:city":"Onil",
    "sg:orig_category":"Juegos Y Juguetes (al Por Menor)",
    "sg:phone":"+34 965 56 41 30",
    "sg:postcode":"03430",
    "sg:province":"Alicante",
    "wof:name":"Carrion Y Monllor S.l.",
    "wof:placetype":"venue"
},
  "geometry": {"coordinates":[-0.673289001,38.6250152588],"type":"Point"}
}