{
  "type": "Feature",
  "properties": {
    "addr:full":"Calle de Villanueva De Algaidas, 9 Malaga M\u00e1laga 29004",
    "addr:housenumber":"9",
    "addr:postcode":"29004",
    "addr:street":"Calle De Villanueva De Algaidas;Ma\u0301Laga",
    "iso:country":"ES",
    "sg:address":"Calle de Villanueva De Algaidas, 9",
    "sg:city":"Malaga",
    "sg:orig_category":"Ense\u00d1anza, Formaci\u00d3n Profesional: Aprendizaje",
    "sg:phone":"+34 952 23 39 49",
    "sg:postcode":"29004",
    "sg:province":"M\u00e1laga",
    "wof:name":"Junta De Andalucia",
    "wof:placetype":"venue"
},
  "geometry": {"coordinates":[-4.4555220604,36.6865768433],"type":"Point"}
}