{
  "type": "Feature",
  "properties": {
    "addr:full":"Carr Santa Margalida, De, 65 Arta Islas Baleares 07570",
    "addr:housenumber":"65",
    "addr:postcode":"07570",
    "addr:street":"Carr Santa Margalida De;Islas Baleares",
    "iso:country":"ES",
    "sg:address":"Carr Santa Margalida, De, 65",
    "sg:city":"Arta",
    "sg:orig_category":"Mec\u00c1nico Del Autom\u00d3vil",
    "sg:phone":"+34 971 83 60 12",
    "sg:postcode":"07570",
    "sg:province":"Islas Baleares",
    "wof:name":"Genovart Vives Miguel",
    "wof:placetype":"venue"
},
  "geometry": {"coordinates":[3.344520092,39.6917495728],"type":"Point"}
}