{
  "type": "Feature",
  "properties": {
    "addr:full":"Calle de Paternilla, S/n Benalup C\u00e1diz 11190",
    "addr:housenumber":"s",
    "addr:postcode":"11190",
    "addr:street":"Calle De Paternilla;/ N;Ca\u0301Diz",
    "iso:country":"ES",
    "sg:address":"Calle de Paternilla, S/n",
    "sg:city":"Benalup",
    "sg:orig_category":"Empresas De Carpinter\u00cda",
    "sg:phone":"+34 956 42 46 33",
    "sg:postcode":"11190",
    "sg:province":"C\u00e1diz",
    "wof:name":"Ruiz Sanchez Antonio",
    "wof:placetype":"venue"
},
  "geometry": {"coordinates":[-5.8142838478,36.3491210938],"type":"Point"}
}