{
  "type": "Feature",
  "properties": {
    "addr:full":"Calle de Sanchez Vera, 1 Cuenca Cuenca 16002",
    "addr:housenumber":"1",
    "addr:postcode":"16002",
    "addr:street":"Calle De Sanchez Vera",
    "iso:country":"ES",
    "sg:address":"Calle de Sanchez Vera, 1",
    "sg:city":"Cuenca",
    "sg:orig_category":"Fotograf\u00cda Art\u00cdstica Y Retratos",
    "sg:phone":"+34 969 23 12 88",
    "sg:postcode":"16002",
    "sg:province":"Cuenca",
    "wof:name":"Ballesteros Iglesias Maria Teresa",
    "wof:placetype":"venue"
},
  "geometry": {"coordinates":[-2.1367669106,40.0730514526],"type":"Point"}
}