{
  "type": "Feature",
  "properties": {
    "addr:full":"Avda Bierzo (el), S/n Dehesas Le\u00f3n 24390",
    "addr:housenumber":"/ n;leo\u0301n",
    "addr:postcode":"24390",
    "addr:street":"Avda Bierzo El S;Dehesas",
    "iso:country":"ES",
    "sg:address":"Avda Bierzo (el), S/n",
    "sg:city":"Dehesas",
    "sg:orig_category":"Reparaciones Y Remolcado De Veh\u00cdculos",
    "sg:phone":"+34 987 42 00 73",
    "sg:postcode":"24390",
    "sg:province":"Le\u00f3n",
    "wof:name":"Reparauto Tino S.l.",
    "wof:placetype":"venue"
},
  "geometry": {"coordinates":[-6.6728639603,42.5299263],"type":"Point"}
}