{
  "type": "Feature",
  "properties": {
    "addr:full":"Calle de San Francisco, 81 Bilbao Vizcaya 48003",
    "addr:housenumber":"81",
    "addr:postcode":"48003",
    "addr:street":"Calle De San Francisco",
    "iso:country":"ES",
    "sg:address":"Calle de San Francisco, 81",
    "sg:city":"Bilbao",
    "sg:orig_category":"Estancos",
    "sg:phone":"+34 944 10 04 39",
    "sg:postcode":"48003",
    "sg:province":"Vizcaya",
    "wof:name":"Olascoaga Villasante Rafael",
    "wof:placetype":"venue"
},
  "geometry": {"coordinates":[-2.9325668812,43.2569656372],"type":"Point"}
}