{
  "type": "Feature",
  "properties": {
    "iso:country":"ES",
    "sg:address":"Calle de Villamartin, 1",
    "sg:city":"Arahal",
    "sg:orig_category":"Cooperativas Agr\u00cdcolas",
    "sg:phone":"+34 954 84 01 13",
    "sg:postcode":"41600",
    "sg:province":"Sevilla",
    "wof:name":"Sociedad Cooperativa Andaluza Del Campo Arahalense",
    "wof:placetype":"venue"
},
  "geometry": {"coordinates":[-5.5504441261,37.2527770996],"type":"Point"}
}