{
  "type": "Feature",
  "properties": {
    "addr:full":"Calle de Ciudad De Cullera, S/n Sevilla Sevilla 41019",
    "addr:housenumber":"s / n",
    "addr:postcode":"41019",
    "addr:street":"Calle De Ciudad De Cullera",
    "iso:country":"ES",
    "sg:address":"Calle de Ciudad De Cullera, S/n",
    "sg:city":"Sevilla",
    "sg:orig_category":"Contenedores (mercanc\u00cdas)",
    "sg:phone":"+34 954 52 06 68",
    "sg:postcode":"41019",
    "sg:province":"Sevilla",
    "wof:name":"Albala Uber Rosa Maria",
    "wof:placetype":"venue"
},
  "geometry": {"coordinates":[-5.927072525,37.4114761353],"type":"Point"}
}