{
  "type": "Feature",
  "properties": {
    "addr:full":"G. Angel Hernandez, 5 Arjonilla Ja\u00e9n 23750",
    "addr:housenumber":"5",
    "addr:postcode":"23750",
    "addr:street":"G.;Hernandez",
    "iso:country":"ES",
    "sg:address":"G. Angel Hernandez, 5",
    "sg:city":"Arjonilla",
    "sg:orig_category":"Promotores Constructores",
    "sg:phone":"+34 953 52 01 74",
    "sg:postcode":"23750",
    "sg:province":"Ja\u00e9n",
    "wof:name":"Hernaprom S.l.",
    "wof:placetype":"venue"
},
  "geometry": {"coordinates":[-4.1041488647,37.9734535217],"type":"Point"}
}