{
  "type": "Feature",
  "properties": {
    "iso:country":"ES",
    "sg:address":"Calle de Tenerias, 10",
    "sg:city":"Calahorra",
    "sg:orig_category":"Medias Y Calcetines (al Por Menor)",
    "sg:phone":"+34 941 14 63 13",
    "sg:postcode":"26500",
    "sg:province":"La Rioja",
    "wof:name":"Calzados Tenerias S.l.",
    "wof:placetype":"venue"
},
  "geometry": {"coordinates":[-1.9542800188,42.3004074097],"type":"Point"}
}