{
  "type": "Feature",
  "properties": {
    "addr:full":"Carr Aigueta, 16 Bisbal D'emporda Girona 17100",
    "addr:housenumber":"16",
    "addr:postcode":"17100",
    "addr:street":"Carr Aigueta",
    "iso:country":"ES",
    "sg:address":"Carr Aigueta, 16",
    "sg:city":"Bisbal D'emporda",
    "sg:orig_category":"Agentes Generales De Seguros",
    "sg:phone":"+34 972 64 09 94",
    "sg:postcode":"17100",
    "sg:province":"Girona",
    "wof:name":"Esteva Rigol Mercedes",
    "wof:placetype":"venue"
},
  "geometry": {"coordinates":[2.8382959366,41.9895057678],"type":"Point"}
}