{
  "type": "Feature",
  "properties": {
    "addr:full":"Calle de Teniente Verde, S/n Budia Guadalajara 19133",
    "addr:housenumber":"s / n",
    "addr:postcode":"19133",
    "addr:street":"Calle De Teniente Verde",
    "iso:country":"ES",
    "sg:address":"Calle de Teniente Verde, S/n",
    "sg:city":"Budia",
    "sg:orig_category":"Centros De Educaci\u00d3n Especial",
    "sg:phone":"+34 949 28 35 56",
    "sg:postcode":"19133",
    "sg:province":"Guadalajara",
    "wof:name":"Direccion Provincial De Educacion Y Ciencia",
    "wof:placetype":"venue"
},
  "geometry": {"coordinates":[-2.7574689388,40.6269950867],"type":"Point"}
}