{
  "type": "Feature",
  "properties": {
    "addr:full":"Ptda Vallonga, S/n Alacant Alicante 03113",
    "addr:housenumber":"s / n",
    "addr:postcode":"03113",
    "addr:street":"Ptda Vallonga",
    "iso:country":"ES",
    "sg:address":"Ptda Vallonga, S/n",
    "sg:city":"Alacant",
    "sg:orig_category":"Hormigonados",
    "sg:phone":"+34 965 11 45 83",
    "sg:postcode":"03113",
    "sg:province":"Alicante",
    "wof:name":"Hormigones Del Vinalopo S. A.",
    "wof:placetype":"venue"
},
  "geometry": {"coordinates":[-0.5904179811,38.3435401917],"type":"Point"}
}