{
  "type": "Feature",
  "properties": {
    "addr:full":"Plaz Ostegieta, 2 Llodio \u00c1lava 01400",
    "addr:housenumber":"2",
    "addr:postcode":"01400",
    "addr:street":"Plaz Ostegieta",
    "iso:country":"ES",
    "sg:address":"Plaz Ostegieta, 2",
    "sg:city":"Llodio",
    "sg:orig_category":"Cajas De Ahorro",
    "sg:phone":"+34 946 72 77 30",
    "sg:postcode":"01400",
    "sg:province":"\u00c1lava",
    "sg:website":"www.cajalaboral.es",
    "wof:name":"Caja Laboral Popular",
    "wof:placetype":"venue"
},
  "geometry": {"coordinates":[-2.956923008,43.147857666],"type":"Point"}
}