{
  "type": "Feature",
  "properties": {
    "iso:country":"ES",
    "sg:address":"Carr Progres, 15",
    "sg:city":"Massamagrell",
    "sg:orig_category":"Bisuter\u00cda, Joyer\u00cda, Relojer\u00cda (al Por Menor)",
    "sg:phone":"+34 961 44 38 25",
    "sg:postcode":"46130",
    "sg:province":"Valencia",
    "wof:name":"Sanchez Llopis Justo",
    "wof:placetype":"venue"
},
  "geometry": {"coordinates":[-0.3329139948,39.5671310425],"type":"Point"}
}