{
  "type": "Feature",
  "properties": {
    "iso:country":"ES",
    "sg:address":"Calle de Brihuega, S/n",
    "sg:city":"San Juan De Aznalfarache",
    "sg:orig_category":"Asociaciones, Organismos Culturales Y Socioeducativos",
    "sg:phone":"+34 954 76 02 43",
    "sg:postcode":"41920",
    "sg:province":"Sevilla",
    "wof:name":"Asociacion De Mujeres Guadalajara",
    "wof:placetype":"venue"
},
  "geometry": {"coordinates":[-6.0276079178,37.3689613342],"type":"Point"}
}