{
  "type": "Feature",
  "properties": {
    "addr:full":"Atallo (magazos), S/n Atallo Lugo 27850",
    "addr:housenumber":"s / n",
    "addr:postcode":"27850",
    "addr:street":"Atallo Magazos",
    "iso:country":"ES",
    "sg:address":"Atallo (magazos), S/n",
    "sg:city":"Atallo",
    "sg:orig_category":"Vinos Y Licores (venta Al Por Menor)",
    "sg:phone":"+34 982 56 10 92",
    "sg:postcode":"27850",
    "sg:province":"Lugo",
    "wof:name":"Sociedad Anonima Moises",
    "wof:placetype":"venue"
},
  "geometry": {"coordinates":[-7.5959348679,43.6629714966],"type":"Point"}
}