{
  "type": "Feature",
  "properties": {
    "iso:country":"ES",
    "sg:address":"Calle de Amargura, 11",
    "sg:city":"Zamora",
    "sg:orig_category":"Librer\u00cdas",
    "sg:phone":"+34 980 51 04 39",
    "sg:postcode":"49013",
    "sg:province":"Zamora",
    "wof:name":"Nu\u00f1ez Belver Miguel Angel",
    "wof:placetype":"venue"
},
  "geometry": {"coordinates":[-5.7412352562,41.5094108582],"type":"Point"}
}