{
  "type": "Feature",
  "properties": {
    "iso:country":"ES",
    "sg:address":"Urb Sto Domingo, 19",
    "sg:city":"Puebla Guzman",
    "sg:orig_category":"Peluquer\u00cdas",
    "sg:phone":"+34 959 38 93 12",
    "sg:postcode":"21505",
    "sg:province":"Huelva",
    "wof:name":"Blanco Pereira Jose Enrique",
    "wof:placetype":"venue"
},
  "geometry": {"coordinates":[-6.9495902061,37.2563095093],"type":"Point"}
}