{
  "type": "Feature",
  "properties": {
    "iso:country":"ES",
    "sg:address":"Calle de Teniente Ochando, 6",
    "sg:city":"Arjona",
    "sg:orig_category":"Reposter\u00cdas",
    "sg:phone":"+34 953 52 32 89",
    "sg:postcode":"23760",
    "sg:province":"Ja\u00e9n",
    "wof:name":"Campos Quero Bonoso",
    "wof:placetype":"venue"
},
  "geometry": {"coordinates":[-4.0609068871,37.9375991821],"type":"Point"}
}