{
  "type": "Feature",
  "properties": {
    "iso:country":"ES",
    "sg:address":"Pol Ind L'estadi, S/n",
    "sg:city":"Castello Plana",
    "sg:orig_category":"Comercio, Reparaci\u00d3n De Bicicletas, De Motocicletas, De Accesorios",
    "sg:phone":"+34 964 25 18 16",
    "sg:postcode":"12004",
    "sg:province":"Castell\u00f3n",
    "wof:name":"Maquiver S. L.",
    "wof:placetype":"venue"
},
  "geometry": {"coordinates":[-0.0360242017,39.9860687256],"type":"Point"}
}