{
  "type": "Feature",
  "properties": {
    "iso:country":"ES",
    "sg:address":"Avda Tortosa, 7",
    "sg:city":"Alca\u00f1iz",
    "sg:orig_category":"Guarder\u00cdas",
    "sg:phone":"+34 978 83 34 24",
    "sg:postcode":"44600",
    "sg:province":"Teruel",
    "wof:name":"Ferrer Oliver S.cv.",
    "wof:placetype":"venue"
},
  "geometry": {"coordinates":[-0.1251289994,41.0550117493],"type":"Point"}
}