{
  "type": "Feature",
  "properties": {
    "addr:full":"Calle de Maestro Ortega, 13 Pedro\u00d1eras Cuenca 16660",
    "addr:housenumber":"13",
    "addr:postcode":"16660",
    "addr:street":"Calle De Maestro Ortega",
    "iso:country":"ES",
    "sg:address":"Calle de Maestro Ortega, 13",
    "sg:city":"Pedro\u00d1eras",
    "sg:orig_category":"Negocio De Materiales De Construcci\u00d3n",
    "sg:phone":"+34 967 16 06 18",
    "sg:postcode":"16660",
    "sg:province":"Cuenca",
    "wof:name":"Monederos Las Pedro\u00f1eras S.l.",
    "wof:placetype":"venue"
},
  "geometry": {"coordinates":[-2.6781830788,39.4495849609],"type":"Point"}
}