{
  "type": "Feature",
  "properties": {
    "addr:full":"Avda Europa, 12 Benidorm Alicante 03500",
    "addr:housenumber":"12",
    "addr:postcode":"03500",
    "addr:street":"Avda Europa",
    "iso:country":"ES",
    "sg:address":"Avda Europa, 12",
    "sg:city":"Benidorm",
    "sg:orig_category":"Peluquer\u00cdas, Peluquer\u00cda Mixta",
    "sg:phone":"+34 965 85 80 31",
    "sg:postcode":"03500",
    "sg:province":"Alicante",
    "wof:name":"Santacreu Sales Juan Jose",
    "wof:placetype":"venue"
},
  "geometry": {"coordinates":[-0.1203240007,38.539516449],"type":"Point"}
}