{
  "type": "Feature",
  "properties": {
    "addr:full":"Calle de Basozelai, S/n Arizgoiti Vizcaya 48970",
    "addr:housenumber":"s",
    "addr:postcode":"48970",
    "addr:street":"Calle De Basozelai;/ N",
    "iso:country":"ES",
    "sg:address":"Calle de Basozelai, S/n",
    "sg:city":"Arizgoiti",
    "sg:orig_category":"Internados & Ense\u00d1anza Privada",
    "sg:phone":"+34 944 49 20 38",
    "sg:postcode":"48970",
    "sg:province":"Vizcaya",
    "wof:name":"Colegio Basauri Cooperativa De Ense\u00f1anza",
    "wof:placetype":"venue"
},
  "geometry": {"coordinates":[-2.8970184326,43.2349205017],"type":"Point"}
}