{
  "type": "Feature",
  "properties": {
    "iso:country":"ES",
    "sg:address":"Avda Comuneros, 123",
    "sg:city":"Salamanca",
    "sg:orig_category":"Delegados, Agentes De Tr\u00c1nsito, Auxiliares De Transporte Internacional",
    "sg:phone":"+34 923 18 55 84",
    "sg:postcode":"37003",
    "sg:province":"Salamanca",
    "wof:name":"Barajas Posadas Mauricio",
    "wof:placetype":"venue"
},
  "geometry": {"coordinates":[-5.6481471062,40.9687080383],"type":"Point"}
}