{
  "type": "Feature",
  "properties": {
    "addr:full":"C/ Mario Pastor Sempere, 66 Elche Alicante 03206",
    "addr:housenumber":"66",
    "addr:postcode":"03206",
    "addr:street":"C / Mario Pastor Sempere",
    "iso:country":"ES",
    "sg:address":"C/ Mario Pastor Sempere, 66",
    "sg:city":"Elche",
    "sg:orig_category":"Peluqueros: De Se\u00d1oras",
    "sg:phone":"+34 965 44 95 87",
    "sg:postcode":"03206",
    "sg:province":"Alicante",
    "wof:name":"Cristina Lloris S.l.u",
    "wof:placetype":"venue"
},
  "geometry": {"coordinates":[-0.7073180079,38.2715568542],"type":"Point"}
}