{
  "type": "Feature",
  "properties": {
    "addr:full":"Calle de Manuel Garcia, S/n Coin M\u00e1laga 29100",
    "addr:postcode":"29100",
    "addr:street":"Calle De Manuel Garcia S / N Coin Ma\u0301Laga",
    "iso:country":"ES",
    "sg:address":"Calle de Manuel Garcia, S/n",
    "sg:city":"Coin",
    "sg:orig_category":"Servicios De Telecomunicaciones",
    "sg:phone":"+34 952 45 43 21",
    "sg:postcode":"29100",
    "sg:province":"M\u00e1laga",
    "wof:name":"Eurotel Sur",
    "wof:placetype":"venue"
},
  "geometry": {"coordinates":[-4.7535591125,36.659450531],"type":"Point"}
}