{
  "type": "Feature",
  "properties": {
    "iso:country":"ES",
    "sg:address":"Calle de Juan De La Cierva, 17",
    "sg:city":"Merida",
    "sg:orig_category":"Arquitectos",
    "sg:phone":"+34 924 37 26 66",
    "sg:postcode":"06800",
    "sg:province":"Badajoz",
    "wof:name":"Macias Diaz Manuel Angel",
    "wof:placetype":"venue"
},
  "geometry": {"coordinates":[-6.3333659172,38.9039726257],"type":"Point"}
}