{
  "type": "Feature",
  "properties": {
    "iso:country":"ES",
    "sg:address":"Avda Doctor Fleming, 4",
    "sg:city":"Le\u00f3n",
    "sg:orig_category":"Inmobiliaria (agencias)",
    "sg:phone":"+34 987 87 55 55",
    "sg:postcode":"24009",
    "sg:province":"Le\u00f3n",
    "wof:name":"Fincas Santos Grupo Inmobiliario S.l.",
    "wof:placetype":"venue"
},
  "geometry": {"coordinates":[-5.5848059654,42.589225769],"type":"Point"}
}