{
  "type": "Feature",
  "properties": {
    "iso:country":"ES",
    "sg:address":"Calle de Virgen Del Val, 44",
    "sg:city":"Madrid",
    "sg:orig_category":"Abogados",
    "sg:phone":"+34 914 05 23 08",
    "sg:postcode":"28027",
    "sg:province":"Madrid",
    "wof:name":"Pintado De Oyague Maria Jesus",
    "wof:placetype":"venue"
},
  "geometry": {"coordinates":[-3.6509549618,40.4392967224],"type":"Point"}
}