{
  "type": "Feature",
  "properties": {
    "addr:full":"Harizti Industrialdea, 1 Ihurre Guip\u00f9zcoa 20212",
    "addr:housenumber":"1",
    "addr:postcode":"20212",
    "addr:street":"Industrialdea;Guipu\u0300Zcoa",
    "iso:country":"ES",
    "sg:address":"Harizti Industrialdea, 1",
    "sg:city":"Ihurre",
    "sg:orig_category":"Lencer\u00cda Femenina, Corseter\u00cda, Trajes De Ba\u00d1o (al Por Menor)",
    "sg:phone":"+34 943 16 22 71",
    "sg:postcode":"20212",
    "sg:province":"Guip\u00f9zcoa",
    "wof:name":"Calvo Rodriguez Idoya",
    "wof:placetype":"venue"
},
  "geometry": {"coordinates":[-2.2013700008,43.0282554626],"type":"Point"}
}