{
  "type": "Feature",
  "properties": {
    "addr:full":"Paris, 8 Palmanova Islas Baleares 07181",
    "addr:postcode":"07181",
    "iso:country":"ES",
    "sg:address":"Paris, 8",
    "sg:city":"Palmanova",
    "sg:orig_category":"Molduras, Junquillos, Listones Y Molduras Perforadas",
    "sg:phone":"+34 971 68 30 10",
    "sg:postcode":"07181",
    "sg:province":"Islas Baleares",
    "wof:name":"O'neill'scp",
    "wof:placetype":"venue"
},
  "geometry": {"coordinates":[2.5309200287,39.5190963745],"type":"Point"}
}