{
  "type": "Feature",
  "properties": {
    "addr:full":"Urzainqui, 18 Iru\u00f1a Navarra 31014",
    "addr:housenumber":"18",
    "addr:postcode":"31014",
    "addr:street":"Urzainqui",
    "iso:country":"ES",
    "sg:address":"Urzainqui, 18",
    "sg:city":"Iru\u00f1a",
    "sg:orig_category":"Cester\u00cda (fabricaci\u00d3n)",
    "sg:phone":"+34 948 14 72 43",
    "sg:postcode":"31014",
    "sg:province":"Navarra",
    "wof:name":"Luquin Jimenez Hermanos S.l.",
    "wof:placetype":"venue"
},
  "geometry": {"coordinates":[-1.6457567215,42.8278045654],"type":"Point"}
}