{
  "type": "Feature",
  "properties": {
    "addr:full":"Calle de San Gregorio (de), 27 Galapagar Madrid 28260",
    "addr:postcode":"28260",
    "addr:street":"Calle De San;De;Galapagar",
    "iso:country":"ES",
    "sg:address":"Calle de San Gregorio (de), 27",
    "sg:city":"Galapagar",
    "sg:orig_category":"M\u00c9dicos: Estomatolog\u00cda",
    "sg:phone":"+34 918 58 40 31",
    "sg:postcode":"28260",
    "sg:province":"Madrid",
    "wof:name":"Aguilar Guerrero Jose Antonio",
    "wof:placetype":"venue"
},
  "geometry": {"coordinates":[-4.003057003,40.5795135498],"type":"Point"}
}