{
  "type": "Feature",
  "properties": {
    "addr:full":"Carr Poeta Marquina, S/n Figueres Girona 17600",
    "addr:housenumber":"s / n",
    "addr:postcode":"17600",
    "addr:street":"Carr Poeta Marquina",
    "iso:country":"ES",
    "sg:address":"Carr Poeta Marquina, S/n",
    "sg:city":"Figueres",
    "sg:orig_category":"Sindicatos De Trabajadores",
    "sg:phone":"+34 972 50 91 15",
    "sg:postcode":"17600",
    "sg:province":"Girona",
    "wof:name":"Unio General Treballadores Catalunya",
    "wof:placetype":"venue"
},
  "geometry": {"coordinates":[2.9566149712,42.2654533386],"type":"Point"}
}