{
  "type": "Feature",
  "properties": {
    "addr:full":"Av. America, 7 Alcorcon Madrid 28922",
    "addr:housenumber":"7",
    "addr:postcode":"28922",
    "addr:street":"Av. America",
    "iso:country":"ES",
    "sg:address":"Av. America, 7",
    "sg:city":"Alcorcon",
    "sg:orig_category":"Muebles, Minoristas",
    "sg:phone":"+34 914 88 07 37",
    "sg:postcode":"28922",
    "sg:province":"Madrid",
    "sg:website":"www.formas.es",
    "wof:name":"Muebles De Dise\u00f1o Propio S.l.",
    "wof:placetype":"venue"
},
  "geometry": {"coordinates":[-3.8312599659,40.3590583801],"type":"Point"}
}