{
  "type": "Feature",
  "properties": {
    "addr:full":"Calle de Juan Calzada Kalea, 13 Gernika-lumo Vizcaya 48300",
    "addr:housenumber":"13",
    "addr:postcode":"48300",
    "addr:street":"Calle De Juan Calzada Kalea",
    "iso:country":"ES",
    "sg:address":"Calle de Juan Calzada Kalea, 13",
    "sg:city":"Gernika-lumo",
    "sg:orig_category":"Psic\u00d3logos",
    "sg:phone":"+34 946 25 70 57",
    "sg:postcode":"48300",
    "sg:province":"Vizcaya",
    "wof:name":"Luis Rafael Ruiz Gonzalez",
    "wof:placetype":"venue"
},
  "geometry": {"coordinates":[-2.67821908,43.3129272461],"type":"Point"}
}