{
  "type": "Feature",
  "properties": {
    "iso:country":"ES",
    "sg:address":"Real, S/n",
    "sg:city":"Luzmela",
    "sg:orig_category":"Molduras, Junquillos, Listones Y Molduras Perforadas",
    "sg:phone":"+34 942 70 17 42",
    "sg:postcode":"39509",
    "sg:province":"Cantabria",
    "wof:name":"Gutierrez Del Anillo Gonzalez Julio",
    "wof:placetype":"venue"
},
  "geometry": {"coordinates":[-4.2100739479,43.2973518372],"type":"Point"}
}