{
  "type": "Feature",
  "properties": {
    "iso:country":"ES",
    "sg:address":"Avda Fernandez Ladreda, 11",
    "sg:city":"Segovia",
    "sg:orig_category":"Empresas De Vigilancia, Guardia Y Protecci\u00d3n",
    "sg:phone":"+34 921 44 42 30",
    "sg:postcode":"40001",
    "sg:province":"Segovia",
    "wof:name":"Vasbe S.l.",
    "wof:placetype":"venue"
},
  "geometry": {"coordinates":[-4.1184401512,40.9474411011],"type":"Point"}
}