{
  "type": "Feature",
  "properties": {
    "iso:country":"ES",
    "sg:address":"Avda Ricardo Carapeto Zambrano, 50",
    "sg:city":"Badajoz",
    "sg:orig_category":"Ense\u00d1anza Variada",
    "sg:phone":"+34 924 26 08 97",
    "sg:postcode":"06008",
    "sg:province":"Badajoz",
    "wof:name":"Marketing Promocional S.l.",
    "wof:placetype":"venue"
},
  "geometry": {"coordinates":[-6.9514760971,38.878288269],"type":"Point"}
}