{
  "type": "Feature",
  "properties": {
    "iso:country":"ES",
    "sg:address":"Av Mare Deu De Montserrat, 31",
    "sg:city":"Barcelona",
    "sg:orig_category":"Molduras, Junquillos, Listones Y Molduras Perforadas",
    "sg:phone":"+34 932 13 30 61",
    "sg:postcode":"08024",
    "sg:province":"Barcelona",
    "wof:name":"Cano Molina Eduardo",
    "wof:placetype":"venue"
},
  "geometry": {"coordinates":[2.1623818874,41.4142608643],"type":"Point"}
}