{
  "type": "Feature",
  "properties": {
    "iso:country":"ES",
    "sg:address":"Carrer de Vilamari, 105",
    "sg:city":"Barcelona",
    "sg:orig_category":"Fabricaci\u00d3n De Peines Y De Accesorios De Peluquer\u00cda",
    "sg:phone":"+34 934 19 60 85",
    "sg:postcode":"08029",
    "sg:province":"Barcelona",
    "sg:website":"www.mbpubli.com",
    "wof:name":"M Y B Publicaciones S.l.",
    "wof:placetype":"venue"
},
  "geometry": {"coordinates":[2.1451649666,41.3818359375],"type":"Point"}
}