{
  "type": "Feature",
  "properties": {
    "iso:country":"ES",
    "sg:address":"Calle de Chica, 6",
    "sg:city":"Vilvestre",
    "sg:orig_category":"Caf\u00c9s, Bares, Cervecer\u00cdas",
    "sg:phone":"+34 923 52 47 80",
    "sg:postcode":"37258",
    "sg:province":"Salamanca",
    "wof:name":"Gorjon Garcia Manuel",
    "wof:placetype":"venue"
},
  "geometry": {"coordinates":[-6.7253112793,41.1049957275],"type":"Point"}
}