{
  "type": "Feature",
  "properties": {
    "iso:country":"ES",
    "sg:address":"Calle de Carcagente, 11",
    "sg:city":"Valencia",
    "sg:orig_category":"Aparcamientos (infraestructuras, Accesorios)",
    "sg:phone":"+34 963 41 90 79",
    "sg:postcode":"46007",
    "sg:province":"Valencia",
    "wof:name":"Monzo Hermanos Parkings C.b.",
    "wof:placetype":"venue"
},
  "geometry": {"coordinates":[-0.3878636956,39.4579963684],"type":"Point"}
}