{
  "type": "Feature",
  "properties": {
    "addr:full":"Calle de Desierto De Las Palmas, 3 Castellon Castell\u00f3n 12006",
    "addr:housenumber":"3",
    "addr:postcode":"12006",
    "addr:street":"Calle De Desierto De Las Palmas;Castello\u0301N",
    "iso:country":"ES",
    "sg:address":"Calle de Desierto De Las Palmas, 3",
    "sg:city":"Castellon",
    "sg:orig_category":"Fabrica De Cer\u00c1micas",
    "sg:phone":"+34 964 25 73 86",
    "sg:postcode":"12006",
    "sg:province":"Castell\u00f3n",
    "sg:website":"www.gresrusticoebro.es",
    "wof:name":"Gres Rustico Ebro S.l.",
    "wof:placetype":"venue"
},
  "geometry": {"coordinates":[-0.0549388006,39.9727783203],"type":"Point"}
}