{
  "type": "Feature",
  "properties": {
    "addr:full":"Avda Manuel Suarez, 17 Navia Asturias 33710",
    "addr:housenumber":"17",
    "addr:postcode":"33710",
    "addr:street":"Avda Manuel Suarez",
    "iso:country":"ES",
    "sg:address":"Avda Manuel Suarez, 17",
    "sg:city":"Navia",
    "sg:orig_category":"Motocicletas (agentes, Concesionarios)",
    "sg:phone":"+34 985 63 03 96",
    "sg:postcode":"33710",
    "sg:province":"Asturias",
    "wof:name":"Garcia Rodriguez Jesus",
    "wof:placetype":"venue"
},
  "geometry": {"coordinates":[-6.7206392288,43.5394897461],"type":"Point"}
}