{
  "type": "Feature",
  "properties": {
    "iso:country":"ES",
    "sg:address":"Avda Badajoz, 50",
    "sg:city":"Madrid",
    "sg:orig_category":"\u00d3ptica: Instrumentos (fabricaci\u00d3n)",
    "sg:phone":"+34 914 04 09 08",
    "sg:postcode":"28027",
    "sg:province":"Madrid",
    "wof:name":"Optymed S.l.",
    "wof:placetype":"venue"
},
  "geometry": {"coordinates":[-3.653963089,40.4420890808],"type":"Point"}
}