{
  "type": "Feature",
  "properties": {
    "addr:full":"Ingeniero Vicente Gonzalez, S/n Huescar Granada 18830",
    "addr:postcode":"18830",
    "addr:street":"Ingeniero Vicente Gonzalez S / N",
    "iso:country":"ES",
    "sg:address":"Ingeniero Vicente Gonzalez, S/n",
    "sg:city":"Huescar",
    "sg:orig_category":"Electrodom\u00c9sticos (al Por Menor)",
    "sg:phone":"+34 958 74 06 36",
    "sg:postcode":"18830",
    "sg:province":"Granada",
    "wof:name":"Fuentes Martinez Jeronimo",
    "wof:placetype":"venue"
},
  "geometry": {"coordinates":[-2.5416789055,37.8055152893],"type":"Point"}
}