{
  "type": "Feature",
  "properties": {
    "iso:country":"ES",
    "sg:address":"Luga Perdiz La, S/n",
    "sg:city":"Gijon",
    "sg:orig_category":"Carnes De Carnicer\u00cda (al Por Mayor)",
    "sg:phone":"+34 985 16 70 90",
    "sg:postcode":"33209",
    "sg:province":"Asturias",
    "wof:name":"Asturiana De Carnes S.a.",
    "wof:placetype":"venue"
},
  "geometry": {"coordinates":[-5.6589412689,43.5241279602],"type":"Point"}
}