{
  "type": "Feature",
  "properties": {
    "iso:country":"ES",
    "sg:address":"Carrer de Endavallada, 15",
    "sg:city":"S. Cugat Valles",
    "sg:orig_category":"\u00d3ptica: Instrumentos (fabricaci\u00d3n)",
    "sg:phone":"+34 935 89 86 88",
    "sg:postcode":"08172",
    "sg:province":"Barcelona",
    "wof:name":"Opti-market S.l.",
    "wof:placetype":"venue"
},
  "geometry": {"coordinates":[2.0820419788,41.4723854065],"type":"Point"}
}