{
  "type": "Feature",
  "properties": {
    "addr:full":"Calle de Lourdes (de), 5 Fuenlabrada Madrid 28944",
    "addr:housenumber":"5",
    "addr:postcode":"28944",
    "addr:street":"Calle De Lourdes De",
    "iso:country":"ES",
    "sg:address":"Calle de Lourdes (de), 5",
    "sg:city":"Fuenlabrada",
    "sg:orig_category":"Empresas De Carpinter\u00cda",
    "sg:phone":"+34 916 00 01 26",
    "sg:postcode":"28944",
    "sg:province":"Madrid",
    "wof:name":"Garcia Ruiz Manuel",
    "wof:placetype":"venue"
},
  "geometry": {"coordinates":[-3.7973060608,40.2804870605],"type":"Point"}
}