{
  "type": "Feature",
  "properties": {
    "iso:country":"ES",
    "sg:address":"Calle de Francisco De Quevedo, 3",
    "sg:city":"Cabezo Torres",
    "sg:orig_category":"Peluquer\u00cdas, Peluquer\u00cda Mixta",
    "sg:phone":"+34 968 85 84 80",
    "sg:postcode":"30110",
    "sg:province":"Murcia",
    "wof:name":"Aragon Marin Natalia",
    "wof:placetype":"venue"
},
  "geometry": {"coordinates":[-1.1306883097,38.0251045227],"type":"Point"}
}