{
  "type": "Feature",
  "properties": {
    "addr:full":"Calle de Juan De Avila, 7 Santa Cruz De Tenerife Santa Cruz De Tenerife 38009",
    "addr:housenumber":"7",
    "addr:postcode":"38009",
    "addr:street":"Calle De Juan De Avila",
    "iso:country":"ES",
    "sg:address":"Calle de Juan De Avila, 7",
    "sg:city":"Santa Cruz De Tenerife",
    "sg:orig_category":"Mec\u00c1nico Del Autom\u00d3vil",
    "sg:phone":"+34 922 23 22 44",
    "sg:postcode":"38009",
    "sg:province":"Santa Cruz De Tenerife",
    "wof:name":"Bola\u00f1os Garcia Domingo",
    "wof:placetype":"venue"
},
  "geometry": {"coordinates":[-16.2744541168,28.4511680603],"type":"Point"}
}