{
  "type": "Feature",
  "properties": {
    "addr:full":"Ctra. Cornalvo, S/n Trujillanos Badajoz 06892",
    "addr:housenumber":"s",
    "addr:postcode":"06892",
    "addr:street":"Ctra. Cornalvo;/ N",
    "iso:country":"ES",
    "sg:address":"Ctra. Cornalvo, S/n",
    "sg:city":"Trujillanos",
    "sg:orig_category":"Agricultores, Agricultores",
    "sg:phone":"+34 924 12 31 36",
    "sg:postcode":"06892",
    "sg:province":"Badajoz",
    "wof:name":"Explotacion Agricola Ganadera Vi\u00f1era",
    "wof:placetype":"venue"
},
  "geometry": {"coordinates":[-6.2537488937,38.9547042847],"type":"Point"}
}