{
  "type": "Feature",
  "properties": {
    "addr:full":"Carrer de Argimon, 8 Barcelona Barcelona 08032",
    "addr:housenumber":"8",
    "addr:postcode":"08032",
    "addr:street":"Carrer De Argimon",
    "iso:country":"ES",
    "sg:address":"Carrer de Argimon, 8",
    "sg:city":"Barcelona",
    "sg:orig_category":"Peluqueros: De Se\u00d1oras",
    "sg:phone":"+34 933 58 39 15",
    "sg:postcode":"08032",
    "sg:province":"Barcelona",
    "wof:name":"Cespedes Perez Estrella",
    "wof:placetype":"venue"
},
  "geometry": {"coordinates":[2.1562979221,41.4280128479],"type":"Point"}
}