{
  "type": "Feature",
  "properties": {
    "iso:country":"ES",
    "sg:address":"Carrer de Lleida, S/n",
    "sg:city":"Deltebre",
    "sg:orig_category":"Chapister\u00cda",
    "sg:phone":"+34 977 48 70 47",
    "sg:postcode":"43580",
    "sg:province":"Tarragona",
    "wof:name":"Fornos Zaragoza Francisco",
    "wof:placetype":"venue"
},
  "geometry": {"coordinates":[0.7170000076,40.7242202759],"type":"Point"}
}