{
  "type": "Feature",
  "properties": {
    "addr:full":"Calle de Acequia, 14 Granada Granada 18008",
    "addr:housenumber":"14",
    "addr:postcode":"18008",
    "addr:street":"Calle De Acequia",
    "iso:country":"ES",
    "sg:address":"Calle de Acequia, 14",
    "sg:city":"Granada",
    "sg:orig_category":"Agencias Y Agentes Comerciales, Representantes",
    "sg:phone":"+34 958 13 55 50",
    "sg:postcode":"18008",
    "sg:province":"Granada",
    "wof:name":"Jolema S.l.",
    "wof:placetype":"venue"
},
  "geometry": {"coordinates":[-3.5821254253,37.1540565491],"type":"Point"}
}