{
  "type": "Feature",
  "properties": {
    "addr:full":"Urb. El Albero, S/n Mijas Costa M\u00e1laga 29649",
    "addr:housenumber":"s / n",
    "addr:postcode":"29649",
    "iso:country":"ES",
    "sg:address":"Urb. El Albero, S/n",
    "sg:city":"Mijas Costa",
    "sg:orig_category":"Agentes Generales De Seguros",
    "sg:phone":"+34 952 46 85 72",
    "sg:postcode":"29649",
    "sg:province":"M\u00e1laga",
    "wof:name":"Jimenez Vidales Juan Francisco",
    "wof:placetype":"venue"
},
  "geometry": {"coordinates":[-4.6310629845,36.5238952637],"type":"Point"}
}