{
  "type": "Feature",
  "properties": {
    "iso:country":"ES",
    "sg:address":"Carrer de Munt, 71",
    "sg:city":"S. Andreu Llavaneres",
    "sg:orig_category":"Discapacitados",
    "sg:phone":"+34 937 95 29 12",
    "sg:postcode":"08392",
    "sg:province":"Barcelona",
    "wof:name":"Casa Familiar San Francisco De Asis",
    "wof:placetype":"venue"
},
  "geometry": {"coordinates":[2.4808111191,41.5727386475],"type":"Point"}
}