{
  "type": "Feature",
  "properties": {
    "addr:full":"Calle de Pinsapo, 1 Rinconada Sevilla 41309",
    "addr:housenumber":"1",
    "addr:postcode":"41309",
    "addr:street":"Calle De Pinsapo",
    "iso:country":"ES",
    "sg:address":"Calle de Pinsapo, 1",
    "sg:city":"Rinconada",
    "sg:orig_category":"Alimentaci\u00d3n General (al Por Menor)",
    "sg:phone":"+34 955 79 72 17",
    "sg:postcode":"41309",
    "sg:province":"Sevilla",
    "wof:name":"Sanchez Ortega Juan Antonio",
    "wof:placetype":"venue"
},
  "geometry": {"coordinates":[-5.9793009758,37.4853858948],"type":"Point"}
}