{
  "type": "Feature",
  "properties": {
    "iso:country":"ES",
    "sg:address":"Av Tarragona, 7",
    "sg:city":"Vilafranca Penedes",
    "sg:orig_category":"Agentes Generales De Seguros",
    "sg:phone":"+34 938 17 29 99",
    "sg:postcode":"08720",
    "sg:province":"Barcelona",
    "wof:name":"Romeu Cardos Francisco",
    "wof:placetype":"venue"
},
  "geometry": {"coordinates":[1.6987849474,41.3444633484],"type":"Point"}
}