{
  "type": "Feature",
  "properties": {
    "iso:country":"ES",
    "sg:address":"Ptda Armanello, S/n",
    "sg:city":"Benidorm",
    "sg:orig_category":"Pr\u00c1ctica De Vela, Navegaci\u00d3n Y Deportes N\u00c1uticos Y Acu\u00c1ticos",
    "sg:phone":"+34 965 85 13 86",
    "sg:postcode":"03500",
    "sg:province":"Alicante",
    "sg:website":"www.surf.to/cableski",
    "wof:name":"Armas Cruz Humberto",
    "wof:placetype":"venue"
},
  "geometry": {"coordinates":[-0.130487293,38.50233078],"type":"Point"}
}