{
  "type": "Feature",
  "properties": {
    "addr:full":"C/ Noc (del), 29 Banyoles Girona 17820",
    "addr:postcode":"17820",
    "addr:street":"C / Noc Del",
    "iso:country":"ES",
    "sg:address":"C/ Noc (del), 29",
    "sg:city":"Banyoles",
    "sg:orig_category":"Venta, Instalaci\u00d3n De Calefacci\u00d3n",
    "sg:phone":"+34 972 57 13 33",
    "sg:postcode":"17820",
    "sg:province":"Girona",
    "wof:name":"Suministres Rigasa S.l.",
    "wof:placetype":"venue"
},
  "geometry": {"coordinates":[2.7771949768,42.1123085022],"type":"Point"}
}