{
  "type": "Feature",
  "properties": {
    "addr:full":"Partida Torreta Izquierda, 1 Elda Alicante 03600",
    "addr:housenumber":"1",
    "addr:postcode":"03600",
    "addr:street":"Partida Torreta Izquierda",
    "iso:country":"ES",
    "sg:address":"Partida Torreta Izquierda, 1",
    "sg:city":"Elda",
    "sg:orig_category":"Zapatos: Material, Suministros, Accesorios (fabricaci\u00d3n, Al Por Mayor)",
    "sg:phone":"+34 965 39 19 96",
    "sg:postcode":"03600",
    "sg:province":"Alicante",
    "wof:name":"Comercial Miver S. L.",
    "wof:placetype":"venue"
},
  "geometry": {"coordinates":[-0.7966089845,38.4770317078],"type":"Point"}
}