{
  "type": "Feature",
  "properties": {
    "addr:full":"La Iglesia, 57 Trobajo Camino Le\u00f3n 24010",
    "addr:housenumber":"57",
    "addr:postcode":"24010",
    "addr:street":"Iglesia;Camino Leo\u0301N",
    "iso:country":"ES",
    "sg:address":"La Iglesia, 57",
    "sg:city":"Trobajo Camino",
    "sg:orig_category":"Protecci\u00d3n Contra Robo (material E Instalaci\u00d3n)",
    "sg:phone":"+34 987 80 47 17",
    "sg:postcode":"24010",
    "sg:province":"Le\u00f3n",
    "wof:name":"Sistemas Industriales Seguridad Leon S.l.",
    "wof:placetype":"venue"
},
  "geometry": {"coordinates":[-5.5716600418,42.5981292725],"type":"Point"}
}