{
  "type": "Feature",
  "properties": {
    "addr:full":"Calle de Guadalajara, 77 Sevilla Sevilla 41014",
    "addr:housenumber":"77",
    "addr:postcode":"41014",
    "addr:street":"Calle De Guadalajara",
    "iso:country":"ES",
    "sg:address":"Calle de Guadalajara, 77",
    "sg:city":"Sevilla",
    "sg:orig_category":"Bisuter\u00cda, Joyer\u00cda, Relojer\u00cda (al Por Menor)",
    "sg:phone":"+34 954 68 08 49",
    "sg:postcode":"41014",
    "sg:province":"Sevilla",
    "wof:name":"Pacheco Gomez Teodoro",
    "wof:placetype":"venue"
},
  "geometry": {"coordinates":[-5.9670882225,37.3227462769],"type":"Point"}
}