{
  "type": "Feature",
  "properties": {
    "addr:full":"Calle de Cavite, 167 Valencia Valencia 46011",
    "addr:housenumber":"167",
    "addr:postcode":"46011",
    "addr:street":"Calle De Cavite",
    "iso:country":"ES",
    "sg:address":"Calle de Cavite, 167",
    "sg:city":"Valencia",
    "sg:orig_category":"M\u00c9dicos: Estomatolog\u00cda",
    "sg:phone":"+34 963 71 59 94",
    "sg:postcode":"46011",
    "sg:province":"Valencia",
    "wof:name":"Leandro Pla Angeles",
    "wof:placetype":"venue"
},
  "geometry": {"coordinates":[-0.3266828954,39.4830360413],"type":"Point"}
}