{
  "type": "Feature",
  "properties": {
    "iso:country":"ES",
    "sg:address":"Avda Baron De Warsage, 18",
    "sg:city":"Calatayud",
    "sg:orig_category":"Marmolistas Funerarios",
    "sg:phone":"+34 976 88 16 23",
    "sg:postcode":"50300",
    "sg:province":"Zaragoza",
    "wof:name":"Aguaviva Serrano Juan Fernando",
    "wof:placetype":"venue"
},
  "geometry": {"coordinates":[-1.6363551617,41.3536453247],"type":"Point"}
}