{
  "type": "Feature",
  "properties": {
    "addr:full":"Calle de Conde De Pe\u00d1alver, 62 Madrid Madrid 28006",
    "addr:housenumber":"62",
    "addr:postcode":"madrid;28006",
    "addr:street":"Calle De Conde De Pen\u0303Alver",
    "iso:country":"ES",
    "sg:address":"Calle de Conde De Pe\u00d1alver, 62",
    "sg:city":"Madrid",
    "sg:orig_category":"Librer\u00cdas",
    "sg:phone":"+34 913 09 01 83",
    "sg:postcode":"28006",
    "sg:province":"Madrid",
    "wof:name":"Fernandez Marques Enrique",
    "wof:placetype":"venue"
},
  "geometry": {"coordinates":[-3.6751971245,40.4310913086],"type":"Point"}
}