{
  "type": "Feature",
  "properties": {
    "addr:full":"Avgd Republica Argentina, 7 Xativa Valencia 46800",
    "addr:housenumber":"7",
    "addr:postcode":"46800",
    "addr:street":"Argentina",
    "iso:country":"ES",
    "sg:address":"Avgd Republica Argentina, 7",
    "sg:city":"Xativa",
    "sg:orig_category":"Pintores",
    "sg:phone":"+34 962 27 49 03",
    "sg:postcode":"46800",
    "sg:province":"Valencia",
    "wof:name":"Giner Valls Vicente",
    "wof:placetype":"venue"
},
  "geometry": {"coordinates":[-0.5200830102,38.9934272766],"type":"Point"}
}