{
  "type": "Feature",
  "properties": {
    "iso:country":"ES",
    "sg:address":"Avda Manuel De Falla, 5",
    "sg:city":"Logro\u00f1o",
    "sg:orig_category":"Promotores Constructores",
    "sg:phone":"+34 941 12 00 85",
    "sg:postcode":"26006",
    "sg:province":"La Rioja",
    "wof:name":"Asesoramiento Inmobiliario Roan S.a.",
    "wof:placetype":"venue"
},
  "geometry": {"coordinates":[-2.4769849777,42.4569129944],"type":"Point"}
}