{
  "type": "Feature",
  "properties": {
    "iso:country":"ES",
    "sg:address":"Ctra Granada, 48",
    "sg:city":"Almeria",
    "sg:orig_category":"Comercio De Piezas De Recambio Y De Accesorios De Veh\u00cdculos, Veh\u00cdculos Industriales",
    "sg:phone":"+34 950 14 17 20",
    "sg:postcode":"04009",
    "sg:province":"Almer\u00eda",
    "wof:name":"Delgado Salda\u00f1a Jose",
    "wof:placetype":"venue"
},
  "geometry": {"coordinates":[-2.4491360188,36.8555831909],"type":"Point"}
}