{
  "type": "Feature",
  "properties": {
    "addr:full":"Calle de Mayor, 105 Puente Tocinos Murcia 30006",
    "addr:housenumber":"105",
    "addr:postcode":"30006",
    "addr:street":"Calle De Mayor",
    "iso:country":"ES",
    "sg:address":"Calle de Mayor, 105",
    "sg:city":"Puente Tocinos",
    "sg:orig_category":"Ense\u00d1anza: Profesiones Art\u00cdsticas",
    "sg:phone":"+34 968 30 09 65",
    "sg:postcode":"30006",
    "sg:province":"Murcia",
    "wof:name":"Valle Dorado Antonio",
    "wof:placetype":"venue"
},
  "geometry": {"coordinates":[-1.1007783413,37.9940490723],"type":"Point"}
}