{
  "type": "Feature",
  "properties": {
    "iso:country":"ES",
    "sg:address":"Carrer de Girona, 4",
    "sg:city":"Barcelona",
    "sg:orig_category":"Hilaturas, Hilos Y Actividades Relacionadas",
    "sg:phone":"+34 932 65 94 50",
    "sg:postcode":"08010",
    "sg:province":"Barcelona",
    "wof:name":"Cumellas Marsa Joaquin",
    "wof:placetype":"venue"
},
  "geometry": {"coordinates":[2.1766889095,41.3908119202],"type":"Point"}
}