{
  "type": "Feature",
  "properties": {
    "iso:country":"ES",
    "sg:address":"Calle de La Inmaculada, 6",
    "sg:city":"San Vicente De Barakaldo",
    "sg:orig_category":"Venta, Alquiler De Toldos",
    "sg:phone":"+34 944 99 39 13",
    "sg:postcode":"48903",
    "sg:province":"Vizcaya",
    "wof:name":"Mora Romero Rosa",
    "wof:placetype":"venue"
},
  "geometry": {"coordinates":[-2.9847269058,43.283744812],"type":"Point"}
}