{
  "type": "Feature",
  "properties": {
    "iso:country":"ES",
    "sg:address":"Carrer de Major, 96",
    "sg:city":"Ulldecona",
    "sg:orig_category":"Mercer\u00cda, Lencer\u00cda (al Por Menor)",
    "sg:phone":"+34 977 72 02 40",
    "sg:postcode":"43550",
    "sg:province":"Tarragona",
    "wof:name":"Porcar Pallares Jose",
    "wof:placetype":"venue"
},
  "geometry": {"coordinates":[0.4471350014,40.5967521667],"type":"Point"}
}