{
  "type": "Feature",
  "properties": {
    "addr:full":"Calle de Caleruega, 1 Madrid Madrid 28033",
    "addr:housenumber":"1",
    "addr:postcode":"28033",
    "addr:street":"Calle De Caleruega",
    "iso:country":"ES",
    "sg:address":"Calle de Caleruega, 1",
    "sg:city":"Madrid",
    "sg:orig_category":"Bancos",
    "sg:phone":"+34 917 67 28 67",
    "sg:postcode":"28033",
    "sg:province":"Madrid",
    "wof:name":"Deutsche Bank S.a.e.",
    "wof:placetype":"venue"
},
  "geometry": {"coordinates":[-3.6689553261,40.4770011902],"type":"Point"}
}