{
  "type": "Feature",
  "properties": {
    "iso:country":"ES",
    "sg:address":"Pase Oria (de), 25",
    "sg:city":"San Fernando De Henares",
    "sg:orig_category":"Guarder\u00cdas",
    "sg:phone":"+34 916 73 94 83",
    "sg:postcode":"28830",
    "sg:province":"Madrid",
    "wof:name":"Ruiz Fernandez Mercedes",
    "wof:placetype":"venue"
},
  "geometry": {"coordinates":[-3.5353159904,40.4256858826],"type":"Point"}
}