{
  "type": "Feature",
  "properties": {
    "addr:full":"Calle de Diputacion, 5 Toledo Toledo 45004",
    "addr:housenumber":"5",
    "addr:postcode":"45004",
    "addr:street":"Calle De Diputacion",
    "iso:country":"ES",
    "sg:address":"Calle de Diputacion, 5",
    "sg:city":"Toledo",
    "sg:orig_category":"Discapacitados",
    "sg:phone":"+34 925 22 26 64",
    "sg:postcode":"45004",
    "sg:province":"Toledo",
    "wof:name":"Asociacion De Esclerosis Multiple De Toledo",
    "wof:placetype":"venue"
},
  "geometry": {"coordinates":[-4.0265431404,39.8648681641],"type":"Point"}
}