{
  "type": "Feature",
  "properties": {
    "addr:full":"Plaz Cruz Verde, 3 Madrid Madrid 28005",
    "addr:housenumber":"3",
    "addr:postcode":"28005",
    "addr:street":"Plaz;Verde",
    "iso:country":"ES",
    "sg:address":"Plaz Cruz Verde, 3",
    "sg:city":"Madrid",
    "sg:orig_category":"Arquitectos",
    "sg:phone":"+34 915 47 81 17",
    "sg:postcode":"28005",
    "sg:province":"Madrid",
    "wof:name":"Fernandez Gonzalez Maria Jesus",
    "wof:placetype":"venue"
},
  "geometry": {"coordinates":[-3.711591959,40.4139938354],"type":"Point"}
}