{
  "type": "Feature",
  "properties": {
    "iso:country":"ES",
    "sg:address":"Calle de Celestino Mendizabal, S/n",
    "sg:city":"Oviedo",
    "sg:orig_category":"Mec\u00c1nico Del Autom\u00d3vil",
    "sg:phone":"+34 985 11 60 50",
    "sg:postcode":"33011",
    "sg:province":"Asturias",
    "wof:name":"Florez Fernandez Felix",
    "wof:placetype":"venue"
},
  "geometry": {"coordinates":[-5.8274722099,43.3812294006],"type":"Point"}
}