{
  "type": "Feature",
  "properties": {
    "addr:full":"Calle de Corrales, 54 Morales Vino Zamora 49190",
    "addr:housenumber":"54",
    "addr:postcode":"49190",
    "addr:street":"Calle De Corrales;Zamora",
    "iso:country":"ES",
    "sg:address":"Calle de Corrales, 54",
    "sg:city":"Morales Vino",
    "sg:orig_category":"Bazares, Art\u00cdculos De Limpieza Y De Cocina (al Por Menor)",
    "sg:phone":"+34 980 57 40 48",
    "sg:postcode":"49190",
    "sg:province":"Zamora",
    "wof:name":"Miguel Monzalvez Eulalia",
    "wof:placetype":"venue"
},
  "geometry": {"coordinates":[-5.7310290337,41.4447021484],"type":"Point"}
}