{
  "type": "Feature",
  "properties": {
    "addr:full":"Carrer de Atlantida, 4 S. Adria Besos Barcelona 08930",
    "addr:housenumber":"4",
    "addr:postcode":"08930",
    "addr:street":"Carrer De Atlantida;Barcelona",
    "iso:country":"ES",
    "sg:address":"Carrer de Atlantida, 4",
    "sg:city":"S. Adria Besos",
    "sg:orig_category":"Empresas De Carpinter\u00cda",
    "sg:phone":"+34 933 81 60 08",
    "sg:postcode":"08930",
    "sg:province":"Barcelona",
    "wof:name":"Carpineria Metalica Domingo Jimenez S.l.",
    "wof:placetype":"venue"
},
  "geometry": {"coordinates":[2.2194590569,41.4313468933],"type":"Point"}
}