{
  "type": "Feature",
  "properties": {
    "addr:full":"Calle de Berlin, 6 Caceres C\u00e1ceres 10005",
    "addr:housenumber":"6",
    "addr:postcode":"10005",
    "addr:street":"Calle De Berlin;Ca\u0301Ceres",
    "iso:country":"ES",
    "sg:address":"Calle de Berlin, 6",
    "sg:city":"Caceres",
    "sg:orig_category":"M\u00c9dicos: Nefrolog\u00cda",
    "sg:phone":"+34 927 23 19 20",
    "sg:postcode":"10005",
    "sg:province":"C\u00e1ceres",
    "wof:name":"Marigliano Cozzolino Nicolas",
    "wof:placetype":"venue"
},
  "geometry": {"coordinates":[-6.3861508369,39.4696578979],"type":"Point"}
}