{
  "type": "Feature",
  "properties": {
    "addr:full":"Calle de Almansa, 58 Madrid Madrid 28039",
    "addr:housenumber":"58",
    "addr:postcode":"madrid;28039",
    "addr:street":"Calle De Almansa",
    "iso:country":"ES",
    "sg:address":"Calle de Almansa, 58",
    "sg:city":"Madrid",
    "sg:orig_category":"Laboratorios Dentales",
    "sg:phone":"+34 915 53 37 07",
    "sg:postcode":"28039",
    "sg:province":"Madrid",
    "wof:name":"Rubio Garcia Federico",
    "wof:placetype":"venue"
},
  "geometry": {"coordinates":[-3.7080829144,40.4489936829],"type":"Point"}
}