{
  "type": "Feature",
  "properties": {
    "addr:full":"Avda Libertador Simon Bolivar, 9 Portugalete Vizcaya 48920",
    "addr:housenumber":"9",
    "addr:postcode":"48920",
    "addr:street":"Avda Libertador Simon Bolivar",
    "iso:country":"ES",
    "sg:address":"Avda Libertador Simon Bolivar, 9",
    "sg:city":"Portugalete",
    "sg:orig_category":"\u00d3ptica: Instrumentos (fabricaci\u00d3n)",
    "sg:phone":"+34 944 62 78 68",
    "sg:postcode":"48920",
    "sg:province":"Vizcaya",
    "wof:name":"Angoitia Garcia Angela",
    "wof:placetype":"venue"
},
  "geometry": {"coordinates":[-3.0230174065,43.3200798035],"type":"Point"}
}