{
  "type": "Feature",
  "properties": {
    "addr:full":"Ptge Masoliver, 38 Barcelona Barcelona 08005",
    "addr:housenumber":"38",
    "addr:postcode":"08005",
    "addr:street":"Ptge Masoliver",
    "iso:country":"ES",
    "sg:address":"Ptge Masoliver, 38",
    "sg:city":"Barcelona",
    "sg:orig_category":"Relojer\u00cda (al Por Menor, Reparaci\u00d3n)",
    "sg:phone":"+34 933 09 99 44",
    "sg:postcode":"08005",
    "sg:province":"Barcelona",
    "wof:name":"Matroes S.a.",
    "wof:placetype":"venue"
},
  "geometry": {"coordinates":[2.1982629299,41.3992805481],"type":"Point"}
}