{
  "type": "Feature",
  "properties": {
    "addr:full":"Carr Formentera, S/n Alcudia Islas Baleares 07400",
    "addr:housenumber":"s / n",
    "addr:postcode":"07400",
    "addr:street":"Carr Formentera",
    "iso:country":"ES",
    "sg:address":"Carr Formentera, S/n",
    "sg:city":"Alcudia",
    "sg:orig_category":"Molduras, Junquillos, Listones Y Molduras Perforadas",
    "sg:phone":"+34 971 54 92 09",
    "sg:postcode":"07400",
    "sg:province":"Islas Baleares",
    "wof:name":"M.v.alcudia S.l.",
    "wof:placetype":"venue"
},
  "geometry": {"coordinates":[3.126650095,39.8549880981],"type":"Point"}
}