{
  "type": "Feature",
  "properties": {
    "addr:full":"Carrer de Falguera, 37 Sant Feliu Llobregat Barcelona 08980",
    "addr:housenumber":"37",
    "addr:postcode":"08980",
    "addr:street":"Carrer De Falguera",
    "iso:country":"ES",
    "sg:address":"Carrer de Falguera, 37",
    "sg:city":"Sant Feliu Llobregat",
    "sg:orig_category":"Asesor\u00cda Fiscal Y Jur\u00cddica",
    "sg:phone":"+34 936 85 05 70",
    "sg:postcode":"08980",
    "sg:province":"Barcelona",
    "wof:name":"Farres Narro Miguel",
    "wof:placetype":"venue"
},
  "geometry": {"coordinates":[2.0435750484,41.3816261292],"type":"Point"}
}