{
  "type": "Feature",
  "properties": {
    "iso:country":"ES",
    "sg:address":"Avda Damian Tellez Lafuente, 4",
    "sg:city":"Badajoz",
    "sg:orig_category":"Inmobiliaria (agencias)",
    "sg:phone":"+34 924 23 61 53",
    "sg:postcode":"06010",
    "sg:province":"Badajoz",
    "wof:name":"Promotora Pacense S.a.",
    "wof:placetype":"venue"
},
  "geometry": {"coordinates":[-6.973151207,38.8688964844],"type":"Point"}
}