{
  "type": "Feature",
  "properties": {
    "iso:country":"ES",
    "sg:address":"Calle de Jose Hernandez Alfonso, 8",
    "sg:city":"Santa Cruz De Tenerife",
    "sg:orig_category":"Muebles, Minoristas",
    "sg:phone":"+34 922 21 23 39",
    "sg:postcode":"38003",
    "sg:province":"Santa Cruz De Tenerife",
    "wof:name":"Muebles Correa S.l.",
    "wof:placetype":"venue"
},
  "geometry": {"coordinates":[-16.2526798248,28.4626121521],"type":"Point"}
}