{
  "type": "Feature",
  "properties": {
    "addr:full":"Calle de Palma Del Rio, 8 Sevilla Sevilla 41008",
    "addr:housenumber":"8",
    "addr:postcode":"41008",
    "addr:street":"Calle De Palma Del Rio",
    "iso:country":"ES",
    "sg:address":"Calle de Palma Del Rio, 8",
    "sg:city":"Sevilla",
    "sg:orig_category":"Doctores En Medicina",
    "sg:phone":"+34 954 35 18 48",
    "sg:postcode":"41008",
    "sg:province":"Sevilla",
    "wof:name":"Reina Gomez Antonio",
    "wof:placetype":"venue"
},
  "geometry": {"coordinates":[-5.9796929359,37.4024124146],"type":"Point"}
}