{
  "type": "Feature",
  "properties": {
    "addr:full":"Av Puig De Castellet, 45 Lloret Mar Girona 17310",
    "addr:housenumber":"45",
    "addr:postcode":"17310",
    "addr:street":"Av Puig De Castellet",
    "iso:country":"ES",
    "sg:address":"Av Puig De Castellet, 45",
    "sg:city":"Lloret Mar",
    "sg:orig_category":"Centros De Reservas Hoteleras",
    "sg:phone":"+34 972 36 60 14",
    "sg:postcode":"17310",
    "sg:province":"Girona",
    "sg:website":"www.hotelgoya.org",
    "wof:name":"Gayete Flores Carmen",
    "wof:placetype":"venue"
},
  "geometry": {"coordinates":[2.8447999954,41.7043838501],"type":"Point"}
}