{
  "type": "Feature",
  "properties": {
    "iso:country":"ES",
    "sg:address":"G.v. Marques Del Turia, 49",
    "sg:city":"Valencia",
    "sg:orig_category":"Ense\u00d1anza: Idiomas",
    "sg:phone":"+34 963 52 83 06",
    "sg:postcode":"46005",
    "sg:province":"Valencia",
    "wof:name":"Foreign Study League S. L.",
    "wof:placetype":"venue"
},
  "geometry": {"coordinates":[-0.368979007,39.4672279358],"type":"Point"}
}