{
  "type": "Feature",
  "properties": {
    "addr:full":"La Palma, S/n Herrera Pisuerga Palencia 34400",
    "addr:housenumber":"/ n",
    "addr:postcode":"34400",
    "addr:street":"Palma S",
    "iso:country":"ES",
    "sg:address":"La Palma, S/n",
    "sg:city":"Herrera Pisuerga",
    "sg:orig_category":"Molduras, Junquillos, Listones Y Molduras Perforadas",
    "sg:phone":"+34 979 13 04 51",
    "sg:postcode":"34400",
    "sg:province":"Palencia",
    "wof:name":"Ortiz Mu\u00f1oz Maria",
    "wof:placetype":"venue"
},
  "geometry": {"coordinates":[-4.3300042152,42.5925140381],"type":"Point"}
}