{
  "type": "Feature",
  "properties": {
    "iso:country":"ES",
    "sg:address":"Calle de Rioja, 5",
    "sg:city":"Benidorm",
    "sg:orig_category":"Inmobiliaria (agencias)",
    "sg:phone":"+34 966 83 13 73",
    "sg:postcode":"03500",
    "sg:province":"Alicante",
    "wof:name":"Spienska S.l. Unipersonal",
    "wof:placetype":"venue"
},
  "geometry": {"coordinates":[-0.129334107,38.5381889343],"type":"Point"}
}