{
  "type": "Feature",
  "properties": {
    "addr:full":"Calle de Flor De Pascua, 10 Acantilados De Los Gigantes Santa Cruz De Tenerife 38683",
    "addr:housenumber":"10",
    "addr:postcode":"38683",
    "addr:street":"Calle De Flor De Pascua",
    "iso:country":"ES",
    "sg:address":"Calle de Flor De Pascua, 10",
    "sg:city":"Acantilados De Los Gigantes",
    "sg:orig_category":"Inmobiliaria (agencias)",
    "sg:phone":"+34 922 86 12 75",
    "sg:postcode":"38683",
    "sg:province":"Santa Cruz De Tenerife",
    "wof:name":"Verde Leon Juan Miguel",
    "wof:placetype":"venue"
},
  "geometry": {"coordinates":[-16.8410358429,28.2435321808],"type":"Point"}
}