{
  "type": "Feature",
  "properties": {
    "addr:full":"Avda Miguel De Cervantes, 45 San Basilio Murcia 30009",
    "addr:housenumber":"45",
    "addr:postcode":"30009",
    "addr:street":"Avda Miguel De Cervantes",
    "iso:country":"ES",
    "sg:address":"Avda Miguel De Cervantes, 45",
    "sg:city":"San Basilio",
    "sg:orig_category":"Promotores Constructores",
    "sg:phone":"+34 968 29 65 96",
    "sg:postcode":"30009",
    "sg:province":"Murcia",
    "wof:name":"Grupo Urbanif Sl",
    "wof:placetype":"venue"
},
  "geometry": {"coordinates":[-1.1440390348,38.0012702942],"type":"Point"}
}