{
  "type": "Feature",
  "properties": {
    "iso:country":"ES",
    "sg:address":"Calle de Falperra, 27",
    "sg:city":"Coru\u00d1a",
    "sg:orig_category":"Fabricaci\u00d3n De Juguetes Autom\u00c1ticos",
    "sg:phone":"+34 981 23 79 28",
    "sg:postcode":"15005",
    "sg:province":"La Coru\u00f1a",
    "wof:name":"Recreativos Mabe S.l.",
    "wof:placetype":"venue"
},
  "geometry": {"coordinates":[-8.4070720673,43.3587799072],"type":"Point"}
}