{
  "type": "Feature",
  "properties": {
    "iso:country":"ES",
    "sg:address":"Ctra Ronda (de), 387",
    "sg:city":"Almeria",
    "sg:orig_category":"Muebles, Minoristas",
    "sg:phone":"+34 950 27 15 60",
    "sg:postcode":"04004",
    "sg:province":"Almer\u00eda",
    "wof:name":"Muebles Ebano Seleccion S.l.",
    "wof:placetype":"venue"
},
  "geometry": {"coordinates":[-2.4564709663,36.8360519409],"type":"Point"}
}