{
  "type": "Feature",
  "properties": {
    "addr:full":"Calle de Mayor, 17 Algue\u00f1a Alicante 03668",
    "addr:housenumber":"17",
    "addr:postcode":"03668",
    "addr:street":"Calle De Mayor;Alicante",
    "iso:country":"ES",
    "sg:address":"Calle de Mayor, 17",
    "sg:city":"Algue\u00f1a",
    "sg:orig_category":"Fabricaci\u00d3n, Importaci\u00d3n De Material Y Sistemas De Telecomunicaciones",
    "sg:phone":"+34 965 47 60 95",
    "sg:postcode":"03668",
    "sg:province":"Alicante",
    "wof:name":"Comercial Lamaran Iv S.l.",
    "wof:placetype":"venue"
},
  "geometry": {"coordinates":[-1.0026179552,38.3381652832],"type":"Point"}
}