{
  "type": "Feature",
  "properties": {
    "iso:country":"ES",
    "sg:address":"Enlace Parque, 15",
    "sg:city":"Padron",
    "sg:orig_category":"Empresas De Carpinter\u00cda",
    "sg:phone":"+34 981 81 23 84",
    "sg:postcode":"15900",
    "sg:province":"La Coru\u00f1a",
    "wof:name":"Complemento Del Aluminio S.l.l.",
    "wof:placetype":"venue"
},
  "geometry": {"coordinates":[-8.6597690582,42.7367782593],"type":"Point"}
}