{
  "type": "Feature",
  "properties": {
    "addr:full":"Calle de Geraneo, 23 Gojar Granada 18150",
    "addr:housenumber":"23",
    "addr:postcode":"18150",
    "addr:street":"Calle De Geraneo",
    "iso:country":"ES",
    "sg:address":"Calle de Geraneo, 23",
    "sg:city":"Gojar",
    "sg:orig_category":"Frutas Y Legumbres Frescas (al Por Mayor)",
    "sg:phone":"+34 958 59 73 68",
    "sg:postcode":"18150",
    "sg:province":"Granada",
    "wof:name":"Europea De Comercio Agricola X X I S.a.",
    "wof:placetype":"venue"
},
  "geometry": {"coordinates":[-3.5995531082,37.1153030396],"type":"Point"}
}