{
  "type": "Feature",
  "properties": {
    "iso:country":"ES",
    "sg:address":"Plaz Cruz Roja, 1",
    "sg:city":"San Juan",
    "sg:orig_category":"Arquitectos",
    "sg:phone":"+34 968 21 63 28",
    "sg:postcode":"30003",
    "sg:province":"Murcia",
    "wof:name":"Gonzalez Serna Antonio",
    "wof:placetype":"venue"
},
  "geometry": {"coordinates":[-1.1298867464,37.9834747314],"type":"Point"}
}