{
  "type": "Feature",
  "properties": {
    "addr:full":"Calle de Mercedes, 6 Valladolid Valladolid 47006",
    "addr:housenumber":"6",
    "addr:postcode":"47006",
    "addr:street":"Calle De Mercedes",
    "iso:country":"ES",
    "sg:address":"Calle de Mercedes, 6",
    "sg:city":"Valladolid",
    "sg:orig_category":"Alimentaci\u00d3n General (al Por Menor)",
    "sg:phone":"+34 983 23 20 03",
    "sg:postcode":"47006",
    "sg:province":"Valladolid",
    "wof:name":"Gutierrez Garcia Petra",
    "wof:placetype":"venue"
},
  "geometry": {"coordinates":[-4.7397069931,41.6401329041],"type":"Point"}
}