{
  "type": "Feature",
  "properties": {
    "iso:country":"ES",
    "sg:address":"Calle de Olivar, 15",
    "sg:city":"Villanueva Serena",
    "sg:orig_category":"Empresas De Pintura Y Revestimientos",
    "sg:phone":"+34 924 84 30 52",
    "sg:postcode":"06700",
    "sg:province":"Badajoz",
    "wof:name":"Corraliza Chamizo Pablo",
    "wof:placetype":"venue"
},
  "geometry": {"coordinates":[-5.7927408218,38.9731750488],"type":"Point"}
}