{
  "type": "Feature",
  "properties": {
    "iso:country":"ES",
    "sg:address":"Calle de Monteverdi, 16",
    "sg:city":"Villanueva De La Ca\u00e7ada",
    "sg:orig_category":"Pr\u00c1ctica Del Submarinismo Y De Deportes Y Actividades Subacu\u00c1ticos",
    "sg:phone":"+34 918 15 76 00",
    "sg:postcode":"28691",
    "sg:province":"Madrid",
    "wof:name":"Sanchez Soler Juan Carlos",
    "wof:placetype":"venue"
},
  "geometry": {"coordinates":[-3.9959759712,40.4405021667],"type":"Point"}
}