{
  "type": "Feature",
  "properties": {
    "iso:country":"ES",
    "sg:address":"Trva Gran Via, 31",
    "sg:city":"Fuente Alamo",
    "sg:orig_category":"Servicios De Telecomunicaciones",
    "sg:phone":"+34 968 59 77 97",
    "sg:postcode":"30320",
    "sg:province":"Murcia",
    "wof:name":"Newtelecom Cultural S.l:",
    "wof:placetype":"venue"
},
  "geometry": {"coordinates":[-1.1687190533,37.7235946655],"type":"Point"}
}