{
  "type": "Feature",
  "properties": {
    "iso:country":"ES",
    "sg:address":"Calle de Niebla, 46",
    "sg:city":"Sevilla",
    "sg:orig_category":"Bisuter\u00cda, Joyer\u00cda, Relojer\u00cda (al Por Menor)",
    "sg:phone":"+34 954 28 38 68",
    "sg:postcode":"41011",
    "sg:province":"Sevilla",
    "wof:name":"Taller De Joyeria Santamaria S.cv.",
    "wof:placetype":"venue"
},
  "geometry": {"coordinates":[-6.0016360283,37.3771820068],"type":"Point"}
}