{
  "type": "Feature",
  "properties": {
    "addr:full":"Rua Candil, 16 Vimianzo La Coru\u00f1a 15120",
    "addr:housenumber":"16",
    "addr:postcode":"15120",
    "addr:street":"Rua Candil;La Corun\u0303A",
    "iso:country":"ES",
    "sg:address":"Rua Candil, 16",
    "sg:city":"Vimianzo",
    "sg:orig_category":"Peluquer\u00cdas, Peluquer\u00cda Mixta",
    "sg:phone":"+34 981 71 70 49",
    "sg:postcode":"15120",
    "sg:province":"La Coru\u00f1a",
    "sg:website":"www.rizos.es",
    "wof:name":"Riveiro Perez Evaristo",
    "wof:placetype":"venue"
},
  "geometry": {"coordinates":[-9.0331249237,43.1104354858],"type":"Point"}
}