{
  "type": "Feature",
  "properties": {
    "iso:country":"ES",
    "sg:address":"Carrer de Aribau, 139",
    "sg:city":"Barcelona",
    "sg:orig_category":"Abogados",
    "sg:phone":"+34 934 14 64 82",
    "sg:postcode":"08036",
    "sg:province":"Barcelona",
    "wof:name":"Serra Selles Maria Teresa",
    "wof:placetype":"venue"
},
  "geometry": {"coordinates":[2.154309988,41.3920173645],"type":"Point"}
}