{
  "type": "Feature",
  "properties": {
    "addr:full":"Avda Marcelino Suarez, 34 Barco Ourense 32300",
    "addr:housenumber":"34",
    "addr:postcode":"32300",
    "addr:street":"Avda Marcelino Suarez",
    "iso:country":"ES",
    "sg:address":"Avda Marcelino Suarez, 34",
    "sg:city":"Barco",
    "sg:orig_category":"Bancos",
    "sg:phone":"+34 988 32 10 79",
    "sg:postcode":"32300",
    "sg:province":"Ourense",
    "sg:website":"www.gruposantander.es",
    "wof:name":"Bt Espa\u00d1a Compa\u00d1ia De Servicios Globales De Telecomunicaciones S.a.u.",
    "wof:placetype":"venue"
},
  "geometry": {"coordinates":[-6.9837059975,42.4104614258],"type":"Point"}
}