{
  "type": "Feature",
  "properties": {
    "iso:country":"ES",
    "sg:address":"Cra Laurea Miro, 163",
    "sg:city":"Sant Feliu Llobregat",
    "sg:orig_category":"Art\u00cdculos De Decoraci\u00d3n",
    "sg:phone":"+34 936 32 77 57",
    "sg:postcode":"08980",
    "sg:province":"Barcelona",
    "wof:name":"Palomares Fernandez Joana",
    "wof:placetype":"venue"
},
  "geometry": {"coordinates":[2.0455288887,41.3802452087],"type":"Point"}
}