{
  "type": "Feature",
  "properties": {
    "iso:country":"ES",
    "sg:address":"Rond Torrassa, 113",
    "sg:city":"Hospitalet Llobregat",
    "sg:orig_category":"\u00d3ptica: Instrumentos (fabricaci\u00d3n)",
    "sg:phone":"+34 934 31 12 39",
    "sg:postcode":"08903",
    "sg:province":"Barcelona",
    "wof:name":"Puyal Solans Pedro",
    "wof:placetype":"venue"
},
  "geometry": {"coordinates":[2.1250889301,41.3686828613],"type":"Point"}
}