{
  "type": "Feature",
  "properties": {
    "addr:full":"Calle de Edison, 14 Malaga M\u00e1laga 29006",
    "addr:housenumber":"14",
    "addr:postcode":"29006",
    "addr:street":"Calle De Edison;Ma\u0301Laga",
    "iso:country":"ES",
    "sg:address":"Calle de Edison, 14",
    "sg:city":"Malaga",
    "sg:orig_category":"Electricidad: Instaladores",
    "sg:phone":"+34 952 31 59 03",
    "sg:postcode":"29006",
    "sg:province":"M\u00e1laga",
    "wof:name":"Ele & M S.cv.",
    "wof:placetype":"venue"
},
  "geometry": {"coordinates":[-4.4359121323,36.7131233215],"type":"Point"}
}