{
  "type": "Feature",
  "properties": {
    "addr:full":"Calle de Gutierrez Herrero De, 36 Aviles Asturias 33402",
    "addr:housenumber":"36",
    "addr:postcode":"33402",
    "addr:street":"Calle De Gutierrez Herrero De",
    "iso:country":"ES",
    "sg:address":"Calle de Gutierrez Herrero De, 36",
    "sg:city":"Aviles",
    "sg:orig_category":"Caf\u00c9s, Bares, Cervecer\u00cdas",
    "sg:phone":"+34 985 51 11 18",
    "sg:postcode":"33402",
    "sg:province":"Asturias",
    "wof:name":"Rivas Arrojo Angela Maria",
    "wof:placetype":"venue"
},
  "geometry": {"coordinates":[-5.9176468849,43.5499382019],"type":"Point"}
}