{
  "type": "Feature",
  "properties": {
    "addr:full":"Praj Venta Del Barro, S/n Estacion Teruel 44510",
    "addr:housenumber":"s",
    "addr:postcode":"44510",
    "addr:street":"/ N Estacion Teruel",
    "iso:country":"ES",
    "sg:address":"Praj Venta Del Barro, S/n",
    "sg:city":"Estacion",
    "sg:orig_category":"Postigos, Persianas Y Celos\u00cdas",
    "sg:phone":"+34 978 82 63 62",
    "sg:postcode":"44510",
    "sg:province":"Teruel",
    "wof:name":"Aluscaspe S.l.",
    "wof:placetype":"venue"
},
  "geometry": {"coordinates":[-1.1069096327,40.3441085815],"type":"Point"}
}