{
  "type": "Feature",
  "properties": {
    "iso:country":"ES",
    "sg:address":"Carrer de Carme, 6",
    "sg:city":"Cambrils",
    "sg:orig_category":"Restaurantes",
    "sg:phone":"+34 977 36 18 60",
    "sg:postcode":"43850",
    "sg:province":"Tarragona",
    "wof:name":"Restaurant Cal Besso C.b.",
    "wof:placetype":"venue"
},
  "geometry": {"coordinates":[1.0619629622,41.0659866333],"type":"Point"}
}