{
  "type": "Feature",
  "properties": {
    "addr:full":"Calle de Francos Rodriguez, 50 Madrid Madrid 28039",
    "addr:housenumber":"50",
    "addr:postcode":"madrid;28039",
    "addr:street":"Calle De Francos Rodriguez",
    "iso:country":"ES",
    "sg:address":"Calle de Francos Rodriguez, 50",
    "sg:city":"Madrid",
    "sg:orig_category":"Estancos",
    "sg:phone":"+34 913 11 29 55",
    "sg:postcode":"28039",
    "sg:province":"Madrid",
    "wof:name":"Garcia Bravo Miguel Angel",
    "wof:placetype":"venue"
},
  "geometry": {"coordinates":[-3.7060239315,40.4567260742],"type":"Point"}
}