{
  "type": "Feature",
  "properties": {
    "iso:country":"ES",
    "sg:address":"Calle de Sin Casas, 8",
    "sg:city":"Loja",
    "sg:orig_category":"Farmacias",
    "sg:phone":"+34 958 32 01 01",
    "sg:postcode":"18300",
    "sg:province":"Granada",
    "wof:name":"Gomez Gallardo Fernando",
    "wof:placetype":"venue"
},
  "geometry": {"coordinates":[-4.209924221,37.1572685242],"type":"Point"}
}