{
  "type": "Feature",
  "properties": {
    "iso:country":"ES",
    "sg:address":"Carrer de Pujades, 12",
    "sg:city":"Barcelona",
    "sg:orig_category":"Frutas, Legumbres Frescas Y Tempranas (al Por Menor)",
    "sg:phone":"+34 932 21 80 43",
    "sg:postcode":"08018",
    "sg:province":"Barcelona",
    "wof:name":"Mu\u00f1oz Rodriguez Alfonso",
    "wof:placetype":"venue"
},
  "geometry": {"coordinates":[2.1878170967,41.3919754028],"type":"Point"}
}