{
  "type": "Feature",
  "properties": {
    "addr:full":"Avda Andalucia, 6 Alcaudete Ja\u00e9n 23660",
    "addr:housenumber":"6",
    "addr:postcode":"23660",
    "addr:street":"Avda Andalucia;Jae\u0301N",
    "iso:country":"ES",
    "sg:address":"Avda Andalucia, 6",
    "sg:city":"Alcaudete",
    "sg:orig_category":"Comercio De Piezas De Recambio Y De Accesorios De Veh\u00cdculos, Veh\u00cdculos Industriales",
    "sg:phone":"+34 953 56 12 58",
    "sg:postcode":"23660",
    "sg:province":"Ja\u00e9n",
    "wof:name":"Accesorios Leconal S.l.",
    "wof:placetype":"venue"
},
  "geometry": {"coordinates":[-4.1053938866,37.6613235474],"type":"Point"}
}