{
  "type": "Feature",
  "properties": {
    "addr:full":"Cust Nevera (la), S/n Cifuentes Guadalajara 19420",
    "addr:housenumber":"s",
    "addr:postcode":"19420",
    "addr:street":"/ N Cifuentes",
    "iso:country":"ES",
    "sg:address":"Cust Nevera (la), S/n",
    "sg:city":"Cifuentes",
    "sg:orig_category":"Cerrajer\u00cda, Ferrallista",
    "sg:phone":"+34 949 81 02 02",
    "sg:postcode":"19420",
    "sg:province":"Guadalajara",
    "wof:name":"Hermanos Hernando C.b.",
    "wof:placetype":"venue"
},
  "geometry": {"coordinates":[-2.6228859425,40.7881202698],"type":"Point"}
}