{
  "type": "Feature",
  "properties": {
    "iso:country":"ES",
    "sg:address":"Calle de Magdalena, S/n",
    "sg:city":"Ezcaroz",
    "sg:orig_category":"Maquinaria Para Industrias Diversas",
    "sg:phone":"+34 948 89 00 08",
    "sg:postcode":"31690",
    "sg:province":"Navarra",
    "wof:name":"Recalde Arozarena Nicasio",
    "wof:placetype":"venue"
},
  "geometry": {"coordinates":[-1.098713994,42.8909263611],"type":"Point"}
}