{
  "type": "Feature",
  "properties": {
    "addr:full":"Calle de Andalucia, 45 Almeria Almer\u00eda 04007",
    "addr:housenumber":"45",
    "addr:postcode":"04007",
    "addr:street":"Calle De Andalucia",
    "iso:country":"ES",
    "sg:address":"Calle de Andalucia, 45",
    "sg:city":"Almeria",
    "sg:orig_category":"Empresas De Pintura Y Revestimientos",
    "sg:phone":"+34 950 23 81 09",
    "sg:postcode":"04007",
    "sg:province":"Almer\u00eda",
    "wof:name":"Segura Gonzalez Antonia",
    "wof:placetype":"venue"
},
  "geometry": {"coordinates":[-2.452119112,36.8347892761],"type":"Point"}
}