{
  "type": "Feature",
  "properties": {
    "iso:country":"ES",
    "sg:address":"Calle de Vizcaya, S/n",
    "sg:city":"Armilla",
    "sg:orig_category":"Inform\u00c1tica: Material Y Suministros",
    "sg:phone":"+34 958 57 84 18",
    "sg:postcode":"18100",
    "sg:province":"Granada",
    "sg:website":"www.arminet.net",
    "wof:name":"Arminet Soluciones Informaticas S.l.",
    "wof:placetype":"venue"
},
  "geometry": {"coordinates":[-3.628436327,37.14112854],"type":"Point"}
}