{
  "type": "Feature",
  "properties": {
    "iso:country":"ES",
    "sg:address":"C/ Nou, 56",
    "sg:city":"Manacor",
    "sg:orig_category":"Alimentaci\u00d3n General (al Por Menor)",
    "sg:phone":"+34 971 55 97 57",
    "sg:postcode":"07500",
    "sg:province":"Islas Baleares",
    "wof:name":"Polanor 2000 S.l.",
    "wof:placetype":"venue"
},
  "geometry": {"coordinates":[3.2080669403,39.5669136047],"type":"Point"}
}