{
  "type": "Feature",
  "properties": {
    "iso:country":"ES",
    "sg:address":"Plaz Palomares, 22",
    "sg:city":"Trebujena",
    "sg:orig_category":"Molduras, Junquillos, Listones Y Molduras Perforadas",
    "sg:phone":"+34 956 16 53 58",
    "sg:postcode":"11560",
    "sg:province":"C\u00e1diz",
    "wof:name":"Pulido Hierro Antonio",
    "wof:placetype":"venue"
},
  "geometry": {"coordinates":[-6.1767439842,36.8717155457],"type":"Point"}
}