{
  "type": "Feature",
  "properties": {
    "addr:full":"Ctra Zufre, S/n Sta Olalla Cala Huelva 21260",
    "addr:housenumber":"s / n",
    "addr:postcode":"21260",
    "addr:street":"Ctra Zufre;Sta Olalla Cala",
    "iso:country":"ES",
    "sg:address":"Ctra Zufre, S/n",
    "sg:city":"Sta Olalla Cala",
    "sg:orig_category":"Garajes De Veh\u00cdculos",
    "sg:phone":"+34 959 50 70 07",
    "sg:postcode":"21260",
    "sg:province":"Huelva",
    "wof:name":"Agro Gomez Lopez S.l.",
    "wof:placetype":"venue"
},
  "geometry": {"coordinates":[-6.3074579239,37.9506568909],"type":"Point"}
}