{
  "type": "Feature",
  "properties": {
    "addr:full":"Calle de Doctor Fleming, 7 Zaragoza Zaragoza 50004",
    "addr:housenumber":"7",
    "addr:postcode":"50004",
    "addr:street":"Calle De Doctor Fleming",
    "iso:country":"ES",
    "sg:address":"Calle de Doctor Fleming, 7",
    "sg:city":"Zaragoza",
    "sg:orig_category":"Organizaciones Internacionales",
    "sg:phone":"+34 976 44 31 02",
    "sg:postcode":"50004",
    "sg:province":"Zaragoza",
    "sg:website":"www.padrinos.org",
    "wof:name":"Fundacion Juan Bonal",
    "wof:placetype":"venue"
},
  "geometry": {"coordinates":[-0.8894246817,41.6518478394],"type":"Point"}
}