{
  "type": "Feature",
  "properties": {
    "addr:full":"Calle de Felix Pizcueta, 18 Valencia Valencia 46004",
    "addr:housenumber":"18",
    "addr:postcode":"46004",
    "addr:street":"Calle De Felix Pizcueta",
    "iso:country":"ES",
    "sg:address":"Calle de Felix Pizcueta, 18",
    "sg:city":"Valencia",
    "sg:orig_category":"Peluquer\u00cdas, Peluquer\u00cda Mixta",
    "sg:phone":"+34 963 51 76 29",
    "sg:postcode":"46004",
    "sg:province":"Valencia",
    "wof:name":"Morales Borrego Jose Manuel",
    "wof:placetype":"venue"
},
  "geometry": {"coordinates":[-0.3727790117,39.4662246704],"type":"Point"}
}