{
  "type": "Feature",
  "properties": {
    "addr:full":"Ctra Bilbao-galdakao, 8 Doneztebe Vizcaya 48450",
    "addr:housenumber":"8",
    "addr:postcode":"48450",
    "addr:street":"Ctra Bilbao-Galdakao",
    "iso:country":"ES",
    "sg:address":"Ctra Bilbao-galdakao, 8",
    "sg:city":"Doneztebe",
    "sg:orig_category":"Bazares, Art\u00cdculos De Limpieza Y De Cocina (al Por Menor)",
    "sg:phone":"+34 944 40 97 73",
    "sg:postcode":"48450",
    "sg:province":"Vizcaya",
    "wof:name":"Electronica Marban S.l.",
    "wof:placetype":"venue"
},
  "geometry": {"coordinates":[-2.8930881023,43.2473907471],"type":"Point"}
}