{
  "type": "Feature",
  "properties": {
    "iso:country":"ES",
    "sg:address":"Calle de Valle Aureliano, 5",
    "sg:city":"Bilbao",
    "sg:orig_category":"Pod\u00d3logos: Pedicuros",
    "sg:phone":"+34 944 44 45 36",
    "sg:postcode":"48010",
    "sg:province":"Vizcaya",
    "wof:name":"Garcia Monzon Juan Ramon",
    "wof:placetype":"venue"
},
  "geometry": {"coordinates":[-2.9400529861,43.2591552734],"type":"Point"}
}