{
  "type": "Feature",
  "properties": {
    "iso:country":"ES",
    "sg:address":"Av Valencia, 87",
    "sg:city":"Molins Rei",
    "sg:orig_category":"Ortopedia General",
    "sg:phone":"+34 936 68 22 46",
    "sg:postcode":"08750",
    "sg:province":"Barcelona",
    "wof:name":"Manufacturas Jelineck S.l.",
    "wof:placetype":"venue"
},
  "geometry": {"coordinates":[2.0155520439,41.4094276428],"type":"Point"}
}