{
  "type": "Feature",
  "properties": {
    "addr:full":"Cruceiro, 18 Cruceiro Pontevedra 36800",
    "addr:housenumber":"18",
    "addr:postcode":"36800",
    "addr:street":"Cruceiro",
    "iso:country":"ES",
    "sg:address":"Cruceiro, 18",
    "sg:city":"Cruceiro",
    "sg:orig_category":"Contenedores (mercanc\u00cdas)",
    "sg:phone":"+34 986 40 07 21",
    "sg:postcode":"36800",
    "sg:province":"Pontevedra",
    "wof:name":"Villaverde Rodriguez Jose",
    "wof:placetype":"venue"
},
  "geometry": {"coordinates":[-8.6090641022,42.2820243835],"type":"Point"}
}