{
  "type": "Feature",
  "properties": {
    "iso:country":"ES",
    "sg:address":"Ptge Mercat Del Fondo, S/n",
    "sg:city":"Santa Coloma De Gramenet",
    "sg:orig_category":"Alimentaci\u00d3n General (al Por Menor)",
    "sg:phone":"+34 933 92 49 01",
    "sg:postcode":"08922",
    "sg:province":"Barcelona",
    "wof:name":"Garcia Alonso Juan",
    "wof:placetype":"venue"
},
  "geometry": {"coordinates":[2.2184698582,41.4496955872],"type":"Point"}
}