{
  "type": "Feature",
  "properties": {
    "iso:country":"ES",
    "sg:address":"Calle de Ricardo Gil, 21",
    "sg:city":"Carmen",
    "sg:orig_category":"Ense\u00d1anza: Comercio, Gesti\u00d3n, Inform\u00c1tica",
    "sg:phone":"+34 968 21 41 29",
    "sg:postcode":"30002",
    "sg:province":"Murcia",
    "sg:website":"www.deimultimedia.es",
    "wof:name":"Dei Multimedia S.l.",
    "wof:placetype":"venue"
},
  "geometry": {"coordinates":[-1.1288599968,37.981048584],"type":"Point"}
}