{
  "type": "Feature",
  "properties": {
    "addr:full":"Avda Vilaboa, S/n Vilaboa La Coru\u00f1a 15174",
    "addr:housenumber":"s / n",
    "addr:postcode":"15174",
    "addr:street":"Avda Vilaboa;La Corun\u0303A",
    "iso:country":"ES",
    "sg:address":"Avda Vilaboa, S/n",
    "sg:city":"Vilaboa",
    "sg:orig_category":"Confecci\u00d3n De Trajes Para Se\u00d1oras",
    "sg:phone":"+34 981 66 54 92",
    "sg:postcode":"15174",
    "sg:province":"La Coru\u00f1a",
    "wof:name":"Confevila S.cop.ltda.",
    "wof:placetype":"venue"
},
  "geometry": {"coordinates":[-8.3827590942,43.3096084595],"type":"Point"}
}