{
  "type": "Feature",
  "properties": {
    "addr:full":"Calle de Acebo, 16 Badajoz Badajoz 06011",
    "addr:housenumber":"16",
    "addr:postcode":"06011",
    "addr:street":"Calle De Acebo",
    "iso:country":"ES",
    "sg:address":"Calle de Acebo, 16",
    "sg:city":"Badajoz",
    "sg:orig_category":"Reposter\u00cdas",
    "sg:phone":"+34 924 24 80 69",
    "sg:postcode":"06011",
    "sg:province":"Badajoz",
    "sg:website":"www.frutascheloiespana.es",
    "wof:name":"Panificadora Hermanos Dominguez S.l.",
    "wof:placetype":"venue"
},
  "geometry": {"coordinates":[-6.9887900352,38.8563499451],"type":"Point"}
}