{
  "type": "Feature",
  "properties": {
    "addr:full":"La Sierra, 3 Granda Asturias 33199",
    "addr:housenumber":"3",
    "addr:postcode":"33199",
    "addr:street":"La Sierra",
    "iso:country":"ES",
    "sg:address":"La Sierra, 3",
    "sg:city":"Granda",
    "sg:orig_category":"Construcci\u00d3n De Edificios Residenciales Y No Residenciales",
    "sg:phone":"+34 985 79 23 40",
    "sg:postcode":"33199",
    "sg:province":"Asturias",
    "wof:name":"Construcciones Y Rehabilitaciones Tejerina S.l.",
    "wof:placetype":"venue"
},
  "geometry": {"coordinates":[-5.7986898422,43.3584632874],"type":"Point"}
}