{
  "type": "Feature",
  "properties": {
    "iso:country":"ES",
    "sg:address":"Ptda Madrigueres Nord, 33",
    "sg:city":"Denia",
    "sg:orig_category":"Inmobiliaria (agencias)",
    "sg:phone":"+34 965 78 39 01",
    "sg:postcode":"03700",
    "sg:province":"Alicante",
    "wof:name":"Mari Mari Clara",
    "wof:placetype":"venue"
},
  "geometry": {"coordinates":[0.0832099989,38.8369026184],"type":"Point"}
}