{
  "type": "Feature",
  "properties": {
    "iso:country":"ES",
    "sg:address":"Calle de Antonia Diaz, 24",
    "sg:city":"Marchena",
    "sg:orig_category":"Mercer\u00cda, Lencer\u00cda (al Por Menor)",
    "sg:phone":"+34 954 84 30 10",
    "sg:postcode":"41620",
    "sg:province":"Sevilla",
    "wof:name":"Ponce O\u00f1a Francisco Javier",
    "wof:placetype":"venue"
},
  "geometry": {"coordinates":[-5.4169926643,37.3285179138],"type":"Point"}
}