{
  "type": "Feature",
  "properties": {
    "addr:full":"Carrer de Cap Norfeu, 43 Roses Girona 17480",
    "addr:housenumber":"43",
    "addr:postcode":"17480",
    "addr:street":"Carrer De Cap Norfeu",
    "iso:country":"ES",
    "sg:address":"Carrer de Cap Norfeu, 43",
    "sg:city":"Roses",
    "sg:orig_category":"Florister\u00cdas",
    "sg:phone":"+34 972 25 72 99",
    "sg:postcode":"17480",
    "sg:province":"Girona",
    "wof:name":"Flors Mateu S.c.p.",
    "wof:placetype":"venue"
},
  "geometry": {"coordinates":[3.1813800335,42.2597808838],"type":"Point"}
}