{
  "type": "Feature",
  "properties": {
    "iso:country":"ES",
    "sg:address":"Ctra Hellin, 20",
    "sg:city":"Yeste",
    "sg:orig_category":"Art\u00cdculos Funerarios (al Por Menor)",
    "sg:phone":"+34 967 43 10 85",
    "sg:postcode":"02480",
    "sg:province":"Albacete",
    "wof:name":"Garcia Ruiz Juan",
    "wof:placetype":"venue"
},
  "geometry": {"coordinates":[-2.3159658909,38.3685264587],"type":"Point"}
}