{
  "type": "Feature",
  "properties": {
    "iso:country":"ES",
    "sg:address":"Plaz Catalu\u00d1a (de), S/n",
    "sg:city":"Jerez De La Frontera",
    "sg:orig_category":"Abogados",
    "sg:phone":"+34 956 33 62 17",
    "sg:postcode":"11402",
    "sg:province":"C\u00e1diz",
    "wof:name":"Luna Vargas Maria",
    "wof:placetype":"venue"
},
  "geometry": {"coordinates":[-6.1351799965,36.6897544861],"type":"Point"}
}