{
  "type": "Feature",
  "properties": {
    "addr:full":"Calle de Almazan, 14 Madrid Madrid 28011",
    "addr:housenumber":"14",
    "addr:postcode":"madrid;28011",
    "addr:street":"Calle De Almazan",
    "iso:country":"ES",
    "sg:address":"Calle de Almazan, 14",
    "sg:city":"Madrid",
    "sg:orig_category":"Promotores Constructores",
    "sg:phone":"+34 914 64 96 79",
    "sg:postcode":"28011",
    "sg:province":"Madrid",
    "wof:name":"Tejado Alonso Jose Manuel",
    "wof:placetype":"venue"
},
  "geometry": {"coordinates":[-3.7433223724,40.4053611755],"type":"Point"}
}