{
  "type": "Feature",
  "properties": {
    "addr:full":"Huesca, S/n Formigal Huesca 22640",
    "addr:housenumber":"s / n",
    "addr:postcode":"22640",
    "addr:street":"Huesca",
    "iso:country":"ES",
    "sg:address":"Huesca, S/n",
    "sg:city":"Formigal",
    "sg:orig_category":"Ense\u00d1anza: Profesiones Art\u00cdsticas",
    "sg:phone":"+34 974 49 01 98",
    "sg:postcode":"22640",
    "sg:province":"Huesca",
    "wof:name":"Mastral Lopez De Heredia Sara",
    "wof:placetype":"venue"
},
  "geometry": {"coordinates":[-0.3627589941,42.7743186951],"type":"Point"}
}