{
  "type": "Feature",
  "properties": {
    "addr:full":"Avda Jose Garate (de), 7 Coslada Madrid 28820",
    "addr:housenumber":"7",
    "addr:postcode":"28820",
    "addr:street":"Avda Jose Garate De",
    "iso:country":"ES",
    "sg:address":"Avda Jose Garate (de), 7",
    "sg:city":"Coslada",
    "sg:orig_category":"Mensajer\u00cda Express, Portes Internacionales",
    "sg:phone":"+34 916 72 67 21",
    "sg:postcode":"28820",
    "sg:province":"Madrid",
    "wof:name":"Transportes Y Servicios Urgentes S.a.",
    "wof:placetype":"venue"
},
  "geometry": {"coordinates":[-3.5469360352,40.4296188354],"type":"Point"}
}