{
  "type": "Feature",
  "properties": {
    "addr:full":"Calle de Carballino, 21 Alcorcon Madrid 28925",
    "addr:housenumber":"21",
    "addr:postcode":"28925",
    "addr:street":"Calle De Carballino",
    "iso:country":"ES",
    "sg:address":"Calle de Carballino, 21",
    "sg:city":"Alcorcon",
    "sg:orig_category":"Inform\u00c1tica, Ofim\u00c1tica (estudios, Asesor\u00cda, Ingenier\u00cda, Formaci\u00d3n)",
    "sg:phone":"+34 916 42 67 16",
    "sg:postcode":"28925",
    "sg:province":"Madrid",
    "wof:name":"Varela Calvo Carlos",
    "wof:placetype":"venue"
},
  "geometry": {"coordinates":[-3.809484005,40.35105896],"type":"Point"}
}