{
  "type": "Feature",
  "properties": {
    "iso:country":"ES",
    "sg:address":"Avda Cantabria, 75",
    "sg:city":"Burgos",
    "sg:orig_category":"Peluquer\u00cdas, Peluquer\u00cda Mixta",
    "sg:phone":"+34 947 23 41 34",
    "sg:postcode":"09006",
    "sg:province":"Burgos",
    "wof:name":"Alamo Gil Alberto Y Escalera Gregorio S.cv.",
    "wof:placetype":"venue"
},
  "geometry": {"coordinates":[-3.6896409988,42.3507194519],"type":"Point"}
}