{
  "type": "Feature",
  "properties": {
    "addr:full":"Carr Luis Vives, 56 Moncada Valencia 46113",
    "addr:housenumber":"56",
    "addr:postcode":"46113",
    "addr:street":"Carr Luis Vives",
    "iso:country":"ES",
    "sg:address":"Carr Luis Vives, 56",
    "sg:city":"Moncada",
    "sg:orig_category":"Agencias De Viajes",
    "sg:phone":"+34 961 39 05 30",
    "sg:postcode":"46113",
    "sg:province":"Valencia",
    "wof:name":"Soriano Catala Jose Manuel",
    "wof:placetype":"venue"
},
  "geometry": {"coordinates":[-0.3970220089,39.5457267761],"type":"Point"}
}