{
  "type": "Feature",
  "properties": {
    "addr:full":"Calle de Maidagan, 47 Andra Mari Vizcaya 48993",
    "addr:housenumber":"47",
    "addr:postcode":"48993",
    "addr:street":"Calle De Maidagan",
    "iso:country":"ES",
    "sg:address":"Calle de Maidagan, 47",
    "sg:city":"Andra Mari",
    "sg:orig_category":"Asesor\u00cda Sobre Comunicaci\u00d3n De Empresas",
    "sg:phone":"+34 944 60 48 54",
    "sg:postcode":"48993",
    "sg:province":"Vizcaya",
    "sg:website":"www.guk.info",
    "wof:name":"Hoyos Fitto Jesus Julio",
    "wof:placetype":"venue"
},
  "geometry": {"coordinates":[-2.7541499138,43.2982711792],"type":"Point"}
}