{
  "type": "Feature",
  "properties": {
    "addr:full":"Calle de Esperanza, S/n Alhaurin El Grande M\u00e1laga 29120",
    "addr:housenumber":"s",
    "addr:postcode":"29120",
    "addr:street":"Calle De Esperanza;/ N",
    "iso:country":"ES",
    "sg:address":"Calle de Esperanza, S/n",
    "sg:city":"Alhaurin El Grande",
    "sg:orig_category":"Centros Empresariales",
    "sg:phone":"+34 952 59 53 29",
    "sg:postcode":"29120",
    "sg:province":"M\u00e1laga",
    "wof:name":"Asociacion De Empresarios De Alhaurin El Grande",
    "wof:placetype":"venue"
},
  "geometry": {"coordinates":[-4.6818795204,36.6460533142],"type":"Point"}
}