{
  "type": "Feature",
  "properties": {
    "iso:country":"ES",
    "sg:address":"Calle de Cristobalina Fdez Alarcon, 1",
    "sg:city":"Antequera",
    "sg:orig_category":"Empresas De Pintura Y Revestimientos",
    "sg:phone":"+34 952 70 19 44",
    "sg:postcode":"29200",
    "sg:province":"M\u00e1laga",
    "wof:name":"Pinturas Nono S.l.",
    "wof:placetype":"venue"
},
  "geometry": {"coordinates":[-4.5211935043,36.9971008301],"type":"Point"}
}