{
  "type": "Feature",
  "properties": {
    "iso:country":"ES",
    "sg:address":"Av Bejar, 27",
    "sg:city":"Terrassa",
    "sg:orig_category":"Hilaturas, Hilos Y Actividades Relacionadas",
    "sg:phone":"+34 937 35 82 53",
    "sg:postcode":"08225",
    "sg:province":"Barcelona",
    "wof:name":"Martinez Pascual Virtudes",
    "wof:placetype":"venue"
},
  "geometry": {"coordinates":[2.0098400116,41.5798683167],"type":"Point"}
}