{
  "type": "Feature",
  "properties": {
    "iso:country":"ES",
    "sg:address":"Calle de Colon, 63",
    "sg:city":"Segorbe",
    "sg:orig_category":"Negocio De Materiales De Construcci\u00d3n",
    "sg:phone":"+34 964 71 11 77",
    "sg:postcode":"12400",
    "sg:province":"Castell\u00f3n",
    "wof:name":"R. Hervas S. A.",
    "wof:placetype":"venue"
},
  "geometry": {"coordinates":[-0.489549309,39.8522148132],"type":"Point"}
}