{
  "type": "Feature",
  "properties": {
    "addr:full":"Calle de Bancos De Bazan, 20 Colmenar Oreja Madrid 28380",
    "addr:housenumber":"20",
    "addr:postcode":"28380",
    "addr:street":"Calle De Bancos De Bazan",
    "iso:country":"ES",
    "sg:address":"Calle de Bancos De Bazan, 20",
    "sg:city":"Colmenar Oreja",
    "sg:orig_category":"Aceites Y Grasas Alimentarias (fabricaci\u00d3n, Al Por Mayor)",
    "sg:phone":"+34 918 94 31 95",
    "sg:postcode":"28380",
    "sg:province":"Madrid",
    "wof:name":"Sanz Galan Julian",
    "wof:placetype":"venue"
},
  "geometry": {"coordinates":[-3.3861539364,40.1091651917],"type":"Point"}
}