{
  "type": "Feature",
  "properties": {
    "iso:country":"ES",
    "sg:address":"Calle de Reyes De Navarra, 1",
    "sg:city":"Vitoria-gasteiz",
    "sg:orig_category":"Loter\u00cda Y T\u00d3mbola",
    "sg:phone":"+34 945 28 18 98",
    "sg:postcode":"01002",
    "sg:province":"\u00c1lava",
    "wof:name":"Lizarralde Zarate Bego\u00f1a",
    "wof:placetype":"venue"
},
  "geometry": {"coordinates":[-2.6659600735,42.8546714783],"type":"Point"}
}