{
  "type": "Feature",
  "properties": {
    "iso:country":"ES",
    "sg:address":"Avda Madrid (de), 81",
    "sg:city":"Granada",
    "sg:orig_category":"Bancos",
    "sg:phone":"+34 958 15 73 11",
    "sg:postcode":"18014",
    "sg:province":"Granada",
    "sg:website":"www.bancoatlantico.es",
    "wof:name":"Banc Sabadell S.a.",
    "wof:placetype":"venue"
},
  "geometry": {"coordinates":[-3.6088829041,37.1948432922],"type":"Point"}
}