{
  "type": "Feature",
  "properties": {
    "addr:full":"Avda Pirineos, 5 Barbastro Huesca 22300",
    "addr:housenumber":"5",
    "addr:postcode":"22300",
    "addr:street":"Avda Pirineos",
    "iso:country":"ES",
    "sg:address":"Avda Pirineos, 5",
    "sg:city":"Barbastro",
    "sg:orig_category":"M\u00c9dicos: Cirug\u00cda Urol\u00d3gica",
    "sg:phone":"+34 974 31 40 46",
    "sg:postcode":"22300",
    "sg:province":"Huesca",
    "wof:name":"Vallano Enrique Javier",
    "wof:placetype":"venue"
},
  "geometry": {"coordinates":[0.1286370009,42.0373077393],"type":"Point"}
}