{
  "type": "Feature",
  "properties": {
    "addr:full":"Calle de Somosierra, 24 Logro\u00f1o La Rioja 26002",
    "addr:housenumber":"24",
    "addr:postcode":"26002",
    "addr:street":"Calle De Somosierra;Rioja",
    "iso:country":"ES",
    "sg:address":"Calle de Somosierra, 24",
    "sg:city":"Logro\u00f1o",
    "sg:orig_category":"Fabricaci\u00d3n De Muebles",
    "sg:phone":"+34 941 20 50 69",
    "sg:postcode":"26002",
    "sg:province":"La Rioja",
    "wof:name":"Eurodecor 2000 S.l.",
    "wof:placetype":"venue"
},
  "geometry": {"coordinates":[-2.4499900341,42.4605560303],"type":"Point"}
}