{
  "type": "Feature",
  "properties": {
    "iso:country":"ES",
    "sg:address":"Calle de Diderot, 9",
    "sg:city":"Malaga",
    "sg:orig_category":"Venta, Instalaci\u00d3n, Reparaci\u00d3n De Antenas Para Televisi\u00d3n",
    "sg:phone":"+34 952 10 56 84",
    "sg:postcode":"29004",
    "sg:province":"M\u00e1laga",
    "wof:name":"Plaza Sistemas S.l.",
    "wof:placetype":"venue"
},
  "geometry": {"coordinates":[-4.4711561203,36.6925010681],"type":"Point"}
}