{
  "type": "Feature",
  "properties": {
    "addr:full":"Ctra. Pozuelo-boadilla Monte, Km. 0001,5 Caba\u00d1a Madrid 28223",
    "addr:postcode":"28223",
    "addr:street":"Ctra. Pozuelo-Boadilla Monte Km. 0001,5",
    "iso:country":"ES",
    "sg:address":"Ctra. Pozuelo-boadilla Monte, Km. 0001,5",
    "sg:city":"Caba\u00d1a",
    "sg:orig_category":"Negocio De Materiales De Construcci\u00d3n",
    "sg:phone":"+34 913 52 60 12",
    "sg:postcode":"28223",
    "sg:province":"Madrid",
    "wof:name":"Garcia Rodriguez Luis",
    "wof:placetype":"venue"
},
  "geometry": {"coordinates":[-3.8569438457,40.4182662964],"type":"Point"}
}