{
  "type": "Feature",
  "properties": {
    "addr:full":"R. Y Cajal, 27 Antequera M\u00e1laga 29200",
    "addr:housenumber":"27",
    "addr:postcode":"29200",
    "addr:street":"Y Cajal",
    "iso:country":"ES",
    "sg:address":"R. Y Cajal, 27",
    "sg:city":"Antequera",
    "sg:orig_category":"Asociaciones Y Clubs Deportivos",
    "sg:phone":"+34 952 84 00 66",
    "sg:postcode":"29200",
    "sg:province":"M\u00e1laga",
    "wof:name":"Perez Armenteros Ramon",
    "wof:placetype":"venue"
},
  "geometry": {"coordinates":[-4.5625538826,37.0200462341],"type":"Point"}
}