{
  "type": "Feature",
  "properties": {
    "iso:country":"ES",
    "sg:address":"Calle de Real De La Cruz Santa, 55",
    "sg:city":"Cruz Santa",
    "sg:orig_category":"Quincaller\u00cda (al Por Menor)",
    "sg:phone":"+34 922 34 12 09",
    "sg:postcode":"38413",
    "sg:province":"Santa Cruz De Tenerife",
    "wof:name":"Martin Diaz Fernando",
    "wof:placetype":"venue"
},
  "geometry": {"coordinates":[-16.5606460571,28.3570613861],"type":"Point"}
}