{
  "type": "Feature",
  "properties": {
    "iso:country":"ES",
    "sg:address":"Plaz Trilladores, S/n",
    "sg:city":"Montijo",
    "sg:orig_category":"Promotores Constructores",
    "sg:phone":"+34 924 45 00 77",
    "sg:postcode":"06480",
    "sg:province":"Badajoz",
    "wof:name":"Solido Montijo S.l.",
    "wof:placetype":"venue"
},
  "geometry": {"coordinates":[-6.6017708778,38.9111595154],"type":"Point"}
}