{
  "type": "Feature",
  "properties": {
    "iso:country":"ES",
    "sg:address":"Calle de Federico Sanchez Bedoya, 7",
    "sg:city":"Sevilla",
    "sg:orig_category":"Agencias Y Asesores De Publicidad",
    "sg:phone":"+34 954 22 84 61",
    "sg:postcode":"41001",
    "sg:province":"Sevilla",
    "wof:name":"Azycon S.l.",
    "wof:placetype":"venue"
},
  "geometry": {"coordinates":[-5.9950313568,37.3860588074],"type":"Point"}
}