{
  "type": "Feature",
  "properties": {
    "addr:full":"Volta 6, S/n S'horta Islas Baleares 07669",
    "addr:housenumber":"6 s / n",
    "addr:postcode":"07669",
    "addr:street":"Volta",
    "iso:country":"ES",
    "sg:address":"Volta 6, S/n",
    "sg:city":"S'horta",
    "sg:orig_category":"Empresarios",
    "sg:phone":"+34 971 18 35 34",
    "sg:postcode":"07669",
    "sg:province":"Islas Baleares",
    "wof:name":"Obras Y Rehabilitaciones Dargow S.l.",
    "wof:placetype":"venue"
},
  "geometry": {"coordinates":[2.9117100239,39.6136398315],"type":"Point"}
}