{
  "type": "Feature",
  "properties": {
    "iso:country":"ES",
    "sg:address":"Carrer de Begur, 37",
    "sg:city":"Barcelona",
    "sg:orig_category":"Fabricaci\u00d3n, Importaci\u00d3n De L\u00c1mparas Y Bombillas",
    "sg:phone":"+34 934 22 00 19",
    "sg:postcode":"08028",
    "sg:province":"Barcelona",
    "wof:name":"Instalaciones Casteras S.l.",
    "wof:placetype":"venue"
},
  "geometry": {"coordinates":[2.1301600933,41.3740844727],"type":"Point"}
}