{
  "type": "Feature",
  "properties": {
    "addr:full":"Calle de Archivo, 4 Madrid Madrid 28031",
    "addr:housenumber":"4",
    "addr:postcode":"28031",
    "addr:street":"Calle De Archivo",
    "iso:country":"ES",
    "sg:address":"Calle de Archivo, 4",
    "sg:city":"Madrid",
    "sg:orig_category":"Radiocomunicaciones, Telefon\u00cda M\u00d3vil, Radiomensajer\u00cda: Servicios, Comercializaci\u00d3n",
    "sg:phone":"+34 913 31 78 47",
    "sg:postcode":"28031",
    "sg:province":"Madrid",
    "wof:name":"Ca\u00f1ego Tena Ana Maria",
    "wof:placetype":"venue"
},
  "geometry": {"coordinates":[-3.6200976372,40.3808021545],"type":"Point"}
}