{
  "type": "Feature",
  "properties": {
    "iso:country":"ES",
    "sg:address":"Duraton, S/n",
    "sg:city":"El Olmo",
    "sg:orig_category":"Materiales De Construcci\u00d3n (en General)",
    "sg:phone":"+34 921 54 31 18",
    "sg:postcode":"40530",
    "sg:province":"Segovia",
    "wof:name":"Transportes Y Excavaciones Postigo S.a.",
    "wof:placetype":"venue"
},
  "geometry": {"coordinates":[-3.6720440388,41.3264808655],"type":"Point"}
}