{
  "type": "Feature",
  "properties": {
    "addr:full":"Plaz Espa\u00d1a, 35 Palacios Y Villafranca Sevilla 41720",
    "addr:housenumber":"35",
    "addr:postcode":"41720",
    "addr:street":"Plaz Espan\u0303A",
    "iso:country":"ES",
    "sg:address":"Plaz Espa\u00d1a, 35",
    "sg:city":"Palacios Y Villafranca",
    "sg:orig_category":"Inmobiliaria (agencias)",
    "sg:phone":"+34 955 81 58 41",
    "sg:postcode":"41720",
    "sg:province":"Sevilla",
    "wof:name":"Mauri\u00f1o Perez Francisco Javier",
    "wof:placetype":"venue"
},
  "geometry": {"coordinates":[-5.9241790771,37.1630935669],"type":"Point"}
}