{
  "type": "Feature",
  "properties": {
    "iso:country":"ES",
    "sg:address":"Calle de Luis Sauquillo, 127",
    "sg:city":"Fuenlabrada",
    "sg:orig_category":"Empresas De Carpinter\u00cda",
    "sg:phone":"+34 916 15 13 33",
    "sg:postcode":"28944",
    "sg:province":"Madrid",
    "wof:name":"Construcciones Metalicas Mu\u00d1oz S.l.",
    "wof:placetype":"venue"
},
  "geometry": {"coordinates":[-3.80834198,40.2712554932],"type":"Point"}
}