{
  "type": "Feature",
  "properties": {
    "addr:full":"Pase Castellana, 83 Madrid Madrid 28...",
    "addr:housenumber":"83;28 ...",
    "addr:postcode":"madrid",
    "addr:street":"Castellana;Madrid",
    "iso:country":"ES",
    "sg:address":"Pase Castellana, 83",
    "sg:city":"Madrid",
    "sg:orig_category":"Agencias Y Asesores De Publicidad",
    "sg:phone":"+34 915 55 84 11",
    "sg:postcode":"28...",
    "sg:province":"Madrid",
    "wof:name":"Publicis Comunicacion Espa\u00d1a S.a.",
    "wof:placetype":"venue"
},
  "geometry": {"coordinates":[-3.6917860508,40.4469108582],"type":"Point"}
}