{
  "type": "Feature",
  "properties": {
    "addr:full":"G.v. Corts Catalanes, 1144 Barcelona Barcelona 08020",
    "addr:postcode":"1144;08020",
    "addr:street":"Catalanes",
    "iso:country":"ES",
    "sg:address":"G.v. Corts Catalanes, 1144",
    "sg:city":"Barcelona",
    "sg:orig_category":"Molduras, Junquillos, Listones Y Molduras Perforadas",
    "sg:phone":"+34 933 14 59 10",
    "sg:postcode":"08020",
    "sg:province":"Barcelona",
    "wof:name":"Iglesias Diez Basilio",
    "wof:placetype":"venue"
},
  "geometry": {"coordinates":[2.2067489624,41.4175987244],"type":"Point"}
}