{
  "type": "Feature",
  "properties": {
    "addr:full":"Avda Primero De Mayo, 95 Palmar  O Lugar De Don Juan Murcia 30120",
    "addr:housenumber":"95",
    "addr:postcode":"30120",
    "addr:street":"Avda Primero De Mayo;Lugar",
    "iso:country":"ES",
    "sg:address":"Avda Primero De Mayo, 95",
    "sg:city":"Palmar  O Lugar De Don Juan",
    "sg:orig_category":"Distribuci\u00d3n De Petr\u00d3leo Y Derivados",
    "sg:phone":"+34 968 88 50 45",
    "sg:postcode":"30120",
    "sg:province":"Murcia",
    "wof:name":"Repsol Ypf S.a.",
    "wof:placetype":"venue"
},
  "geometry": {"coordinates":[-1.1164139509,37.9892501831],"type":"Point"}
}