{
  "type": "Feature",
  "properties": {
    "addr:full":"Lousende, S/n Lousende Lugo 27227",
    "addr:postcode":"27227",
    "addr:street":"Lousende S / N",
    "iso:country":"ES",
    "sg:address":"Lousende, S/n",
    "sg:city":"Lousende",
    "sg:orig_category":"Agricultores, Agricultores",
    "sg:phone":"+34 982 37 51 01",
    "sg:postcode":"27227",
    "sg:province":"Lugo",
    "wof:name":"Lodeiro Vazquez Concepcion",
    "wof:placetype":"venue"
},
  "geometry": {"coordinates":[-7.8045239449,43.0172843933],"type":"Point"}
}