{
  "type": "Feature",
  "properties": {
    "addr:full":"Calle de Arkitekto Kapelastegi, S/n Elorrio Vizcaya 48230",
    "addr:housenumber":"s",
    "addr:postcode":"48230",
    "addr:street":"Calle De Arkitekto Kapelastegi;/ N",
    "iso:country":"ES",
    "sg:address":"Calle de Arkitekto Kapelastegi, S/n",
    "sg:city":"Elorrio",
    "sg:orig_category":"Venta, Instalaci\u00d3n De Cocinas",
    "sg:phone":"+34 946 23 17 95",
    "sg:postcode":"48230",
    "sg:province":"Vizcaya",
    "wof:name":"Urrejola Eriz Juan Manuel",
    "wof:placetype":"venue"
},
  "geometry": {"coordinates":[-2.5396161079,43.1282615662],"type":"Point"}
}