{
  "type": "Feature",
  "properties": {
    "addr:full":"Rua Antonio Puga, 17 Ourense Ourense 32002",
    "addr:housenumber":"17",
    "addr:postcode":"32002",
    "addr:street":"Rua Antonio Puga",
    "iso:country":"ES",
    "sg:address":"Rua Antonio Puga, 17",
    "sg:city":"Ourense",
    "sg:orig_category":"Adhesivos (fabricaci\u00d3n, Al Por Mayor)",
    "sg:phone":"+34 988 22 13 68",
    "sg:postcode":"32002",
    "sg:province":"Ourense",
    "wof:name":"Graficas Orensanas S. L.",
    "wof:placetype":"venue"
},
  "geometry": {"coordinates":[-7.869383812,42.3410491943],"type":"Point"}
}