{
  "type": "Feature",
  "properties": {
    "iso:country":"ES",
    "sg:address":"Carrer de Roger De Flor, 130",
    "sg:city":"Barcelona",
    "sg:orig_category":"Electricidad: Instaladores",
    "sg:phone":"+34 932 31 23 56",
    "sg:postcode":"08013",
    "sg:province":"Barcelona",
    "wof:name":"Giron Blasco Fernando",
    "wof:placetype":"venue"
},
  "geometry": {"coordinates":[2.1764740944,41.3960342407],"type":"Point"}
}