{
  "type": "Feature",
  "properties": {
    "iso:country":"ES",
    "sg:address":"Calle de Tartessos, 1",
    "sg:city":"Sevilla",
    "sg:orig_category":"Bisuter\u00cda, Joyer\u00cda, Relojer\u00cda (al Por Menor)",
    "sg:phone":"+34 954 41 66 03",
    "sg:postcode":"41008",
    "sg:province":"Sevilla",
    "wof:name":"Jimenez Ligero Rafael",
    "wof:placetype":"venue"
},
  "geometry": {"coordinates":[-5.9725289345,37.3986549377],"type":"Point"}
}