{
  "type": "Feature",
  "properties": {
    "iso:country":"ES",
    "sg:address":"Barr Valles, S/n",
    "sg:city":"Valles",
    "sg:orig_category":"Agentes, Concesionarios Y Sucursales De Camiones Y Veh\u00cdculos Industriales",
    "sg:phone":"+34 942 82 18 30",
    "sg:postcode":"39590",
    "sg:province":"Cantabria",
    "wof:name":"Quality Truks S.a.",
    "wof:placetype":"venue"
},
  "geometry": {"coordinates":[-4.1317028999,43.3504219055],"type":"Point"}
}