{
  "type": "Feature",
  "properties": {
    "iso:country":"ES",
    "sg:address":"Avda Lugo, 22",
    "sg:city":"Cangas",
    "sg:orig_category":"Muebles Y Accesorios Para Cocinas Y Cuartos De Ba\u00d1o (al Por Menor)",
    "sg:phone":"+34 986 30 34 01",
    "sg:postcode":"36940",
    "sg:province":"Pontevedra",
    "wof:name":"Andes Electrodomesticos S.l",
    "wof:placetype":"venue"
},
  "geometry": {"coordinates":[-8.7840137482,42.2676429749],"type":"Point"}
}