{
  "type": "Feature",
  "properties": {
    "iso:country":"ES",
    "sg:address":"Calle de Jose Antonio Primo De Rivera, 79",
    "sg:city":"Arrecife",
    "sg:orig_category":"Bazares, Art\u00cdculos De Limpieza Y De Cocina (al Por Menor)",
    "sg:phone":"+34 928 80 74 34",
    "sg:postcode":"35500",
    "sg:province":"Las Palmas",
    "wof:name":"Gao  Xiuqin",
    "wof:placetype":"venue"
},
  "geometry": {"coordinates":[-13.5544710159,28.9593658447],"type":"Point"}
}