{
  "type": "Feature",
  "properties": {
    "addr:full":"Avda Pontevedra, 1 Ourense Ourense 32005",
    "addr:housenumber":"1",
    "addr:postcode":"32005",
    "addr:street":"Avda Pontevedra",
    "iso:country":"ES",
    "sg:address":"Avda Pontevedra, 1",
    "sg:city":"Ourense",
    "sg:orig_category":"Peluqueros: De Se\u00d1oras",
    "sg:phone":"+34 988 22 30 41",
    "sg:postcode":"32005",
    "sg:province":"Ourense",
    "wof:name":"Sanchez Varela Josefa",
    "wof:placetype":"venue"
},
  "geometry": {"coordinates":[-7.8642268181,42.335849762],"type":"Point"}
}