{
  "type": "Feature",
  "properties": {
    "iso:country":"ES",
    "sg:address":"Av Farga, 5",
    "sg:city":"Banyoles",
    "sg:orig_category":"Restaurantes",
    "sg:phone":"+34 972 57 33 00",
    "sg:postcode":"17820",
    "sg:province":"Girona",
    "wof:name":"Serbar Sl",
    "wof:placetype":"venue"
},
  "geometry": {"coordinates":[2.7776179314,42.1170463562],"type":"Point"}
}