{
  "type": "Feature",
  "properties": {
    "iso:country":"ES",
    "sg:address":"Calle de Reina Do\u00d1a Germana, 6",
    "sg:city":"Valencia",
    "sg:orig_category":"Ingeniero",
    "sg:phone":"+34 963 33 49 57",
    "sg:postcode":"46005",
    "sg:province":"Valencia",
    "wof:name":"Ordeig Fos Luis",
    "wof:placetype":"venue"
},
  "geometry": {"coordinates":[-0.3657610118,39.4637985229],"type":"Point"}
}