{
  "type": "Feature",
  "properties": {
    "addr:full":"Carrer de Dolors Granes, 84 Cardedeu Barcelona 08440",
    "addr:housenumber":"84",
    "addr:postcode":"08440",
    "addr:street":"Carrer De Dolors Granes",
    "iso:country":"ES",
    "sg:address":"Carrer de Dolors Granes, 84",
    "sg:city":"Cardedeu",
    "sg:orig_category":"Ropa Para Se\u00d1oras Y Caballeros (al Por Menor)",
    "sg:phone":"+34 938 46 14 72",
    "sg:postcode":"08440",
    "sg:province":"Barcelona",
    "wof:name":"Coca Mateu Domingo",
    "wof:placetype":"venue"
},
  "geometry": {"coordinates":[2.363368988,41.6406364441],"type":"Point"}
}