{
  "type": "Feature",
  "properties": {
    "iso:country":"ES",
    "sg:address":"Ctra. Salamanca, 24",
    "sg:city":"Plasencia",
    "sg:orig_category":"Empresas De Pintura Y Revestimientos",
    "sg:phone":"+34 927 41 34 83",
    "sg:postcode":"10600",
    "sg:province":"C\u00e1ceres",
    "wof:name":"Pintores Rodriguez Mani E Hijos S.l.",
    "wof:placetype":"venue"
},
  "geometry": {"coordinates":[-6.0905981064,40.036151886],"type":"Point"}
}