{
  "type": "Feature",
  "properties": {
    "addr:full":"Calle de Alameda, S/n Campillo Altobuey Cuenca 16210",
    "addr:housenumber":"s / n",
    "addr:postcode":"16210",
    "addr:street":"Calle De Alameda",
    "iso:country":"ES",
    "sg:address":"Calle de Alameda, S/n",
    "sg:city":"Campillo Altobuey",
    "sg:orig_category":"Iglesia Cat\u00d3lica",
    "sg:phone":"+34 969 33 70 33",
    "sg:postcode":"16210",
    "sg:province":"Cuenca",
    "wof:name":"Parroquia San Andres Apostol",
    "wof:placetype":"venue"
},
  "geometry": {"coordinates":[-1.7951177359,39.6122970581],"type":"Point"}
}