{
  "type": "Feature",
  "properties": {
    "iso:country":"ES",
    "sg:address":"Polig Industrial, S/n",
    "sg:city":"Lorqui",
    "sg:orig_category":"Materias Pl\u00c1sticas: Art\u00cdculos Para La Industria",
    "sg:phone":"+34 968 68 75 19",
    "sg:postcode":"30564",
    "sg:province":"Murcia",
    "sg:website":"www.arcasys.com",
    "wof:name":"Schoeller Arca Systems S.l.",
    "wof:placetype":"venue"
},
  "geometry": {"coordinates":[-1.2350000143,38.1045875549],"type":"Point"}
}