{
  "type": "Feature",
  "properties": {
    "iso:country":"ES",
    "sg:address":"Calle de Miguel De Cervantes, 13",
    "sg:city":"Calabazanos",
    "sg:orig_category":"Alquiler De Material Y De Programas Audiovisuales",
    "sg:phone":"+34 979 77 73 94",
    "sg:postcode":"34190",
    "sg:province":"Palencia",
    "wof:name":"Sonitur C.b.",
    "wof:placetype":"venue"
},
  "geometry": {"coordinates":[-4.5067677498,41.9488067627],"type":"Point"}
}