{
  "type": "Feature",
  "properties": {
    "iso:country":"ES",
    "sg:address":"Calle de Pablo Iglesias De, 7",
    "sg:city":"Aviles",
    "sg:orig_category":"Ense\u00d1anza Variada",
    "sg:phone":"+34 985 51 21 26",
    "sg:postcode":"33402",
    "sg:province":"Asturias",
    "wof:name":"Fernandez Conde Clara Isabel",
    "wof:placetype":"venue"
},
  "geometry": {"coordinates":[-5.9203519821,43.5542526245],"type":"Point"}
}