{
  "type": "Feature",
  "properties": {
    "addr:full":"Calle de Sevilla, 10 Jerez De La Frontera C\u00e1diz 11402",
    "addr:housenumber":"10",
    "addr:postcode":"11402",
    "addr:street":"Calle De Sevilla",
    "iso:country":"ES",
    "sg:address":"Calle de Sevilla, 10",
    "sg:city":"Jerez De La Frontera",
    "sg:orig_category":"Inmobiliaria (agencias)",
    "sg:phone":"+34 956 33 00 47",
    "sg:postcode":"11402",
    "sg:province":"C\u00e1diz",
    "sg:website":"www.unicasa.es",
    "wof:name":"Unica Xerez S.l.",
    "wof:placetype":"venue"
},
  "geometry": {"coordinates":[-6.1360192299,36.690071106],"type":"Point"}
}