{
  "type": "Feature",
  "properties": {
    "iso:country":"ES",
    "sg:address":"Calle de Luis Vives, 7",
    "sg:city":"Alcala Henares",
    "sg:orig_category":"Molduras, Junquillos, Listones Y Molduras Perforadas",
    "sg:phone":"+34 918 80 99 18",
    "sg:postcode":"28803",
    "sg:province":"Madrid",
    "wof:name":"Romero Pe\u00f1a Suirley",
    "wof:placetype":"venue"
},
  "geometry": {"coordinates":[-3.3683950901,40.4766387939],"type":"Point"}
}