{
  "type": "Feature",
  "properties": {
    "addr:full":"Arieta, 13 Estella Navarra 31200",
    "addr:housenumber":"13",
    "addr:postcode":"31200",
    "addr:street":"Arieta",
    "iso:country":"ES",
    "sg:address":"Arieta, 13",
    "sg:city":"Estella",
    "sg:orig_category":"Molduras, Junquillos, Listones Y Molduras Perforadas",
    "sg:phone":"+34 948 55 20 67",
    "sg:postcode":"31200",
    "sg:province":"Navarra",
    "wof:name":"Sistelcom-telemensaje S.a.",
    "wof:placetype":"venue"
},
  "geometry": {"coordinates":[-2.0425550938,42.6785736084],"type":"Point"}
}