{
  "type": "Feature",
  "properties": {
    "addr:full":"C/ Mare De Deu De Les Feixes, 12 Cerdanyola Valles Barcelona 08290",
    "addr:housenumber":"12",
    "addr:postcode":"08290",
    "addr:street":"C / Mare De Deu De Les Feixes;Valles Barcelona",
    "iso:country":"ES",
    "sg:address":"C/ Mare De Deu De Les Feixes, 12",
    "sg:city":"Cerdanyola Valles",
    "sg:orig_category":"Carnicer\u00cdas, Carnicer\u00cdas",
    "sg:phone":"+34 936 92 42 36",
    "sg:postcode":"08290",
    "sg:province":"Barcelona",
    "wof:name":"Carnisseria I Xarcuteria Vidal S.l.",
    "wof:placetype":"venue"
},
  "geometry": {"coordinates":[2.1421968937,41.4829025269],"type":"Point"}
}