{
  "type": "Feature",
  "properties": {
    "iso:country":"ES",
    "sg:address":"Plaz Espa\u00d1a, 2",
    "sg:city":"Callosa Segura",
    "sg:orig_category":"Loter\u00cda Y T\u00d3mbola",
    "sg:phone":"+34 966 75 65 48",
    "sg:postcode":"03360",
    "sg:province":"Alicante",
    "wof:name":"Manchon Esta\u00f1 Agustin",
    "wof:placetype":"venue"
},
  "geometry": {"coordinates":[-0.8776689768,38.1256752014],"type":"Point"}
}