{
  "type": "Feature",
  "properties": {
    "iso:country":"ES",
    "sg:address":"Calle de Pancho Cossio, 19",
    "sg:city":"Torrelavega",
    "sg:orig_category":"Empresas De Carpinter\u00cda Met\u00c1lica",
    "sg:phone":"+34 942 89 14 84",
    "sg:postcode":"39300",
    "sg:province":"Cantabria",
    "wof:name":"Roiz Gomez Rafael",
    "wof:placetype":"venue"
},
  "geometry": {"coordinates":[-4.0539679527,43.3517341614],"type":"Point"}
}