{
  "type": "Feature",
  "properties": {
    "iso:country":"ES",
    "sg:address":"Ctra Chipiona (de), Km. 0003,6",
    "sg:city":"Sanlucar De Barrameda",
    "sg:orig_category":"Aparatos E Instalaci\u00d3n De Regad\u00cdos",
    "sg:phone":"+34 956 36 22 91",
    "sg:postcode":"11540",
    "sg:province":"C\u00e1diz",
    "wof:name":"Agrocas S.l.",
    "wof:placetype":"venue"
},
  "geometry": {"coordinates":[-6.3649706841,36.7600860596],"type":"Point"}
}