{
  "type": "Feature",
  "properties": {
    "iso:country":"ES",
    "sg:address":"Rbla Muntanya, 18",
    "sg:city":"Barcelona",
    "sg:orig_category":"Contenedores (mercanc\u00cdas)",
    "sg:phone":"+34 934 08 62 94",
    "sg:postcode":"08041",
    "sg:province":"Barcelona",
    "wof:name":"Puber Trans S.l.",
    "wof:placetype":"venue"
},
  "geometry": {"coordinates":[2.1779301167,41.421913147],"type":"Point"}
}