{
  "type": "Feature",
  "properties": {
    "addr:full":"Rua Teluro, 1 Ourense Ourense 32004",
    "addr:housenumber":"1",
    "addr:postcode":"32004",
    "addr:street":"Rua Teluro",
    "iso:country":"ES",
    "sg:address":"Rua Teluro, 1",
    "sg:city":"Ourense",
    "sg:orig_category":"Institutos De Belleza",
    "sg:phone":"+34 988 25 24 02",
    "sg:postcode":"32004",
    "sg:province":"Ourense",
    "wof:name":"Celaa Prada Leticia",
    "wof:placetype":"venue"
},
  "geometry": {"coordinates":[-7.8606147766,42.3405036926],"type":"Point"}
}