{
  "type": "Feature",
  "properties": {
    "addr:full":"Calle de Isidoro Diaz, 2 Alcala Guadaira Sevilla 41500",
    "addr:housenumber":"2",
    "addr:postcode":"41500",
    "addr:street":"Calle De Isidoro Diaz",
    "iso:country":"ES",
    "sg:address":"Calle de Isidoro Diaz, 2",
    "sg:city":"Alcala Guadaira",
    "sg:orig_category":"Artesan\u00cda",
    "sg:phone":"+34 955 68 02 08",
    "sg:postcode":"41500",
    "sg:province":"Sevilla",
    "wof:name":"Portillo Martinez Antonio",
    "wof:placetype":"venue"
},
  "geometry": {"coordinates":[-5.8500490189,37.3356056213],"type":"Point"}
}