{
  "type": "Feature",
  "properties": {
    "iso:country":"ES",
    "sg:address":"Avda Montevideo Etorbidea, S/n",
    "sg:city":"Durango",
    "sg:orig_category":"Negocio De Materiales De Construcci\u00d3n",
    "sg:phone":"+34 946 21 52 84",
    "sg:postcode":"48200",
    "sg:province":"Vizcaya",
    "wof:name":"Lagoi S.l.",
    "wof:placetype":"venue"
},
  "geometry": {"coordinates":[-2.6263020039,43.1693611145],"type":"Point"}
}