{
  "type": "Feature",
  "properties": {
    "addr:full":"C/ Reconquesta, 54 Alcoi Alicante 03803",
    "addr:housenumber":"54",
    "addr:postcode":"03803",
    "addr:street":"C / Reconquesta",
    "iso:country":"ES",
    "sg:address":"C/ Reconquesta, 54",
    "sg:city":"Alcoi",
    "sg:orig_category":"Mec\u00c1nico Del Autom\u00d3vil",
    "sg:phone":"+34 965 52 48 60",
    "sg:postcode":"03803",
    "sg:province":"Alicante",
    "wof:name":"Canto Pargues Jose Luis",
    "wof:placetype":"venue"
},
  "geometry": {"coordinates":[-0.4809310138,38.7028160095],"type":"Point"}
}