{
  "type": "Feature",
  "properties": {
    "addr:full":"Barrio Nuevo, S/n Vallecillo Teruel 44123",
    "addr:housenumber":"s",
    "addr:postcode":"44123",
    "addr:street":"Barrio;/ N",
    "iso:country":"ES",
    "sg:address":"Barrio Nuevo, S/n",
    "sg:city":"Vallecillo",
    "sg:orig_category":"Agencias Y Agentes Comerciales, Representantes",
    "sg:phone":"+34 978 78 82 48",
    "sg:postcode":"44123",
    "sg:province":"Teruel",
    "wof:name":"Royuela Saez Enrique",
    "wof:placetype":"venue"
},
  "geometry": {"coordinates":[-1.4873689413,40.2484817505],"type":"Point"}
}