{
  "type": "Feature",
  "properties": {
    "addr:full":"Avda Europa (de), 18 Alcobendas Madrid 28...",
    "addr:housenumber":"18;28 ...",
    "addr:street":"Avda Europa De;Madrid",
    "iso:country":"ES",
    "sg:address":"Avda Europa (de), 18",
    "sg:city":"Alcobendas",
    "sg:orig_category":"Venta, Alquiler De Toldos",
    "sg:phone":"+34 916 63 28 50",
    "sg:postcode":"28...",
    "sg:province":"Madrid",
    "sg:website":"www.necso.es",
    "wof:name":"Acciona Infraestructuras S.a.",
    "wof:placetype":"venue"
},
  "geometry": {"coordinates":[-3.656031847,40.5159416199],"type":"Point"}
}