{
  "type": "Feature",
  "properties": {
    "addr:full":"Avda Tirso De Molina, 13 Valencia Valencia 46009",
    "addr:housenumber":"13",
    "addr:postcode":"46009",
    "addr:street":"Avda Tirso De Molina",
    "iso:country":"ES",
    "sg:address":"Avda Tirso De Molina, 13",
    "sg:city":"Valencia",
    "sg:orig_category":"Asociaciones Humanitarias, De Cooperaci\u00d3n, De Acci\u00d3n Social",
    "sg:phone":"+34 963 49 77 37",
    "sg:postcode":"46009",
    "sg:province":"Valencia",
    "wof:name":"Asociacion Valenciana De Ex-alcoholicos",
    "wof:placetype":"venue"
},
  "geometry": {"coordinates":[-0.392996192,39.4781913757],"type":"Point"}
}