{
  "type": "Feature",
  "properties": {
    "addr:full":"Ctra. Arenal, 31 Les Meravelles Islas Baleares 07610",
    "addr:housenumber":"31",
    "addr:postcode":"07610",
    "addr:street":"Ctra. Arenal;Les Meravelles",
    "iso:country":"ES",
    "sg:address":"Ctra. Arenal, 31",
    "sg:city":"Les Meravelles",
    "sg:orig_category":"Farmacias",
    "sg:phone":"+34 971 26 26 68",
    "sg:postcode":"07610",
    "sg:province":"Islas Baleares",
    "wof:name":"Soler Gaya Antonia",
    "wof:placetype":"venue"
},
  "geometry": {"coordinates":[2.7302498817,39.5303382874],"type":"Point"}
}