{
  "type": "Feature",
  "properties": {
    "iso:country":"ES",
    "sg:address":"Calle de Pinar, 1",
    "sg:city":"Pedrajas S. Esteban",
    "sg:orig_category":"Asociaciones, Organismos Culturales Y Socioeducativos",
    "sg:phone":"+34 983 60 55 04",
    "sg:postcode":"47430",
    "sg:province":"Valladolid",
    "sg:website":"www.pedrajas.es",
    "wof:name":"Ayuntamiento De Pedrajas De San Esteban",
    "wof:placetype":"venue"
},
  "geometry": {"coordinates":[-4.5822467804,41.3371543884],"type":"Point"}
}