{
  "type": "Feature",
  "properties": {
    "addr:full":"Calle de Grandeza Espa\u00d1ola, 5 Madrid Madrid 28011",
    "addr:housenumber":"5",
    "addr:postcode":"28011",
    "addr:street":"Calle De Grandeza Espan\u0303Ola",
    "iso:country":"ES",
    "sg:address":"Calle de Grandeza Espa\u00d1ola, 5",
    "sg:city":"Madrid",
    "sg:orig_category":"Mec\u00c1nico Del Autom\u00d3vil",
    "sg:phone":"+34 914 63 33 04",
    "sg:postcode":"28011",
    "sg:province":"Madrid",
    "wof:name":"Cuenca Zamarra Vicente",
    "wof:placetype":"venue"
},
  "geometry": {"coordinates":[-3.7309269905,40.4117965698],"type":"Point"}
}