{
  "type": "Feature",
  "properties": {
    "addr:full":"Calle de Jose Garrote Tobar, 12 Valladolid Valladolid 47014",
    "addr:housenumber":"12",
    "addr:postcode":"47014",
    "addr:street":"Calle De Jose Garrote Tobar",
    "iso:country":"ES",
    "sg:address":"Calle de Jose Garrote Tobar, 12",
    "sg:city":"Valladolid",
    "sg:orig_category":"Asesor\u00cda De Formaci\u00d3n Y Gesti\u00d3n De Personal",
    "sg:phone":"+34 983 33 71 32",
    "sg:postcode":"47014",
    "sg:province":"Valladolid",
    "wof:name":"Asel Consultores Damian S.l.",
    "wof:placetype":"venue"
},
  "geometry": {"coordinates":[-4.7580208778,41.6342658997],"type":"Point"}
}