{
  "type": "Feature",
  "properties": {
    "iso:country":"ES",
    "sg:address":"Calle de Rio Cares, 6",
    "sg:city":"Gijon",
    "sg:orig_category":"Molduras, Junquillos, Listones Y Molduras Perforadas",
    "sg:phone":"+34 985 38 89 16",
    "sg:postcode":"33210",
    "sg:province":"Asturias",
    "wof:name":"Pride Perez Angel",
    "wof:placetype":"venue"
},
  "geometry": {"coordinates":[-5.663775444,43.5200920105],"type":"Point"}
}