{
  "type": "Feature",
  "properties": {
    "addr:full":"Calle de Beraqueta, 15 Irun Guip\u00f9zcoa 20302",
    "addr:housenumber":"15",
    "addr:postcode":"20302",
    "addr:street":"Calle De Beraqueta;Guipu\u0300Zcoa",
    "iso:country":"ES",
    "sg:address":"Calle de Beraqueta, 15",
    "sg:city":"Irun",
    "sg:orig_category":"Muebles, Minoristas",
    "sg:phone":"+34 943 62 89 87",
    "sg:postcode":"20302",
    "sg:province":"Guip\u00f9zcoa",
    "sg:website":"www.ka-international.com",
    "wof:name":"Valdepesa Textil S.l.",
    "wof:placetype":"venue"
},
  "geometry": {"coordinates":[-1.7900110483,43.3400726318],"type":"Point"}
}