{
  "type": "Feature",
  "properties": {
    "iso:country":"ES",
    "sg:address":"Avda Tirajana (de), 19",
    "sg:city":"Playa Del Ingles",
    "sg:orig_category":"Molduras, Junquillos, Listones Y Molduras Perforadas",
    "sg:phone":"+34 928 76 05 75",
    "sg:postcode":"35100",
    "sg:province":"Las Palmas",
    "wof:name":"Mata Lezana Rodolfo De La",
    "wof:placetype":"venue"
},
  "geometry": {"coordinates":[-15.578909874,27.7570343018],"type":"Point"}
}