{
  "type": "Feature",
  "properties": {
    "iso:country":"ES",
    "sg:address":"Avda Reina Victoria Eugenia, 7",
    "sg:city":"Cartagena",
    "sg:orig_category":"M\u00c9dicos: Alergolog\u00cda",
    "sg:phone":"+34 968 52 31 00",
    "sg:postcode":"30204",
    "sg:province":"Murcia",
    "wof:name":"Ortiz Chaparro Jose",
    "wof:placetype":"venue"
},
  "geometry": {"coordinates":[-0.9908480048,37.6096725464],"type":"Point"}
}