{
  "type": "Feature",
  "properties": {
    "addr:full":"Carretera Mugia, S/n Ponte Do Porto A Coru\u00f1a 15122",
    "addr:housenumber":"s / n",
    "addr:postcode":"15122",
    "addr:street":"Carretera Mugia;Corun\u0303A",
    "iso:country":"ES",
    "sg:address":"Carretera Mugia, S/n",
    "sg:city":"Ponte Do Porto",
    "sg:orig_category":"Cr\u00cda De Animales",
    "sg:phone":"+34 981 73 00 55",
    "sg:postcode":"15122",
    "sg:province":"A Coru\u00f1a",
    "wof:name":"Santos Tajes Jose",
    "wof:placetype":"venue"
},
  "geometry": {"coordinates":[-9.1458740234,43.161190033],"type":"Point"}
}