{
  "type": "Feature",
  "properties": {
    "iso:country":"ES",
    "sg:address":"Palmar, 22",
    "sg:city":"Torrent",
    "sg:classifiers":[
        {
            "category":"Manufacturing",
            "subcategory":"Metals",
            "type":"Manufacturing & Wholesale Goods"
        }
    ],
    "sg:phone":"+34 961 56 53 24",
    "sg:postcode":"46900",
    "sg:province":"Valencia",
    "sg:tags":[
        "en",
        "fundiciones"
    ],
    "wof:name":"Recuperacion De Metales Busta S.l.",
    "wof:placetype":"venue"
},
  "geometry": {"coordinates":[-0.4819990098,39.4407997131],"type":"Point"}
}