{
  "type": "Feature",
  "properties": {
    "iso:country":"ES",
    "sg:address":"Pg Sanllehy, S/n",
    "sg:city":"Poligono",
    "sg:orig_category":"Promotores Constructores",
    "sg:phone":"+34 937 13 10 14",
    "sg:postcode":"08213",
    "sg:province":"Barcelona",
    "wof:name":"Corsan Corviam Construccion S.a.",
    "wof:placetype":"venue"
},
  "geometry": {"coordinates":[2.1570799351,41.5535011292],"type":"Point"}
}