{
  "type": "Feature",
  "properties": {
    "iso:country":"ES",
    "sg:address":"Calle de Salvador, El, 25",
    "sg:city":"Torrent",
    "sg:orig_category":"Empresas De Carpinter\u00cda Met\u00c1lica",
    "sg:phone":"+34 961 57 27 02",
    "sg:postcode":"46900",
    "sg:province":"Valencia",
    "wof:name":"Montesinos Fajardo Rogelio",
    "wof:placetype":"venue"
},
  "geometry": {"coordinates":[-0.4712759852,39.4347343445],"type":"Point"}
}