{
  "type": "Feature",
  "properties": {
    "addr:full":"Calle de Nuestra Se\u00d1ora De Valverde, 21 Madrid Madrid 28034",
    "addr:housenumber":"21",
    "addr:postcode":"madrid;28034",
    "addr:street":"Calle De Nuestra Sen\u0303Ora De Valverde",
    "iso:country":"ES",
    "sg:address":"Calle de Nuestra Se\u00d1ora De Valverde, 21",
    "sg:city":"Madrid",
    "sg:orig_category":"Librer\u00cdas",
    "sg:phone":"+34 917 34 10 41",
    "sg:postcode":"28034",
    "sg:province":"Madrid",
    "wof:name":"Libreria Fuencarral S. A.",
    "wof:placetype":"venue"
},
  "geometry": {"coordinates":[-3.6872570515,40.4932823181],"type":"Point"}
}