{
  "type": "Feature",
  "properties": {
    "iso:country":"ES",
    "sg:address":"Boqueron, 1",
    "sg:city":"Fuengirola",
    "sg:orig_category":"Cajas De Ahorro",
    "sg:phone":"+34 952 59 30 40",
    "sg:postcode":"29640",
    "sg:province":"M\u00e1laga",
    "sg:website":"www.cajamar.es",
    "wof:name":"Cajamar",
    "wof:placetype":"venue"
},
  "geometry": {"coordinates":[-4.6158590317,36.5511856079],"type":"Point"}
}