{
  "type": "Feature",
  "properties": {
    "iso:country":"ES",
    "sg:address":"Calle de Primicia, 35",
    "sg:city":"Cintruenigo",
    "sg:orig_category":"Alquiler De Casas Y Habitaciones Amuebladas",
    "sg:phone":"+34 948 81 53 23",
    "sg:postcode":"31592",
    "sg:province":"Navarra",
    "wof:name":"M\u00aa Eugenia Y Agueda Chivite Martinez S.c.",
    "wof:placetype":"venue"
},
  "geometry": {"coordinates":[-1.806581974,42.0832099915],"type":"Point"}
}