{
  "type": "Feature",
  "properties": {
    "iso:country":"ES",
    "sg:address":"C/ Joaquin Cartagena Baile, 102",
    "sg:city":"Elche",
    "sg:orig_category":"Confecci\u00d3n De Zapatos",
    "sg:phone":"+34 965 43 43 08",
    "sg:postcode":"03206",
    "sg:province":"Alicante",
    "wof:name":"Inselo S.l.",
    "wof:placetype":"venue"
},
  "geometry": {"coordinates":[-0.7095289826,38.2765884399],"type":"Point"}
}