{
  "type": "Feature",
  "properties": {
    "addr:full":"Calle de Poza Licenciado, 52 Bilbao Vizcaya 48013",
    "addr:housenumber":"52",
    "addr:postcode":"48013",
    "addr:street":"Calle De Poza Licenciado",
    "iso:country":"ES",
    "sg:address":"Calle de Poza Licenciado, 52",
    "sg:city":"Bilbao",
    "sg:orig_category":"Peleter\u00cdas",
    "sg:phone":"+34 944 41 77 33",
    "sg:postcode":"48013",
    "sg:province":"Vizcaya",
    "wof:name":"Peleteria Delmar Bilbao S.a.",
    "wof:placetype":"venue"
},
  "geometry": {"coordinates":[-2.9440889359,43.2629241943],"type":"Point"}
}