{
  "type": "Feature",
  "properties": {
    "addr:full":"Ceboli\u00f1o, S/n Ceboli\u00d1o Ourense 32004",
    "addr:postcode":"32004",
    "addr:street":"Cebolin\u0303O S / N",
    "iso:country":"ES",
    "sg:address":"Ceboli\u00f1o, S/n",
    "sg:city":"Ceboli\u00d1o",
    "sg:orig_category":"Asilos De Ancianos. Centros Privados",
    "sg:phone":"+34 988 25 03 60",
    "sg:postcode":"32004",
    "sg:province":"Ourense",
    "wof:name":"Fundacion San Rosendo",
    "wof:placetype":"venue"
},
  "geometry": {"coordinates":[-7.8252801895,42.3395385742],"type":"Point"}
}