{
  "type": "Feature",
  "properties": {
    "iso:country":"ES",
    "sg:address":"Calle de Virgen Del Losar, 75",
    "sg:city":"Puerto",
    "sg:classifiers":[
        {
            "category":"Autos & Motor Vehicles",
            "subcategory":"Automobile Sales",
            "type":"Retail Goods"
        }
    ],
    "sg:phone":"+34 962 67 38 72",
    "sg:postcode":"46520",
    "sg:province":"Valencia",
    "wof:name":"Latorre San Lucas Santiago Miguel",
    "wof:placetype":"venue"
},
  "geometry": {"coordinates":[-0.2150876969,39.66248703],"type":"Point"}
}