{
  "type": "Feature",
  "properties": {
    "addr:full":"Calle de Ramiro I, 2 Piedras Blancas Asturias 33450",
    "addr:housenumber":"2",
    "addr:postcode":"33450",
    "addr:street":"Calle De Ramiro I",
    "iso:country":"ES",
    "sg:address":"Calle de Ramiro I, 2",
    "sg:city":"Piedras Blancas",
    "sg:orig_category":"Bares, Piano",
    "sg:phone":"+34 985 53 33 97",
    "sg:postcode":"33450",
    "sg:province":"Asturias",
    "wof:name":"Fernandez Alvarez Ana Maria",
    "wof:placetype":"venue"
},
  "geometry": {"coordinates":[-5.9747958183,43.5610580444],"type":"Point"}
}