{
  "type": "Feature",
  "properties": {
    "iso:country":"ES",
    "sg:address":"Ptda Boixadors, 6",
    "sg:city":"Basses D'alpicat",
    "sg:orig_category":"Formaci\u00d3n Continuada (variada)",
    "sg:phone":"+34 973 24 62 81",
    "sg:postcode":"25191",
    "sg:province":"Lleida",
    "wof:name":"Fundacio Aspros",
    "wof:placetype":"venue"
},
  "geometry": {"coordinates":[0.5885509849,41.6478729248],"type":"Point"}
}