{
  "type": "Feature",
  "properties": {
    "addr:full":"Avda Generalisimo, 4 Bola\u00e7os De Calatrava Ciudad Real 13260",
    "addr:housenumber":"4",
    "addr:postcode":"13260",
    "addr:street":"Avda Generalisimo",
    "iso:country":"ES",
    "sg:address":"Avda Generalisimo, 4",
    "sg:city":"Bola\u00e7os De Calatrava",
    "sg:orig_category":"Autob\u00das (explotaci\u00d3n Y Servicios De)",
    "sg:phone":"+34 926 87 30 91",
    "sg:postcode":"13260",
    "sg:province":"Ciudad Real",
    "wof:name":"Bus Medina S.l.",
    "wof:placetype":"venue"
},
  "geometry": {"coordinates":[-3.6528038979,38.9070281982],"type":"Point"}
}