{
  "type": "Feature",
  "properties": {
    "iso:country":"ES",
    "sg:address":"C/ Alfons Xii, 18",
    "sg:city":"Banyoles",
    "sg:orig_category":"Abogados",
    "sg:phone":"+34 972 57 02 05",
    "sg:postcode":"17820",
    "sg:province":"Girona",
    "wof:name":"Ajuntament De Banyoles",
    "wof:placetype":"venue"
},
  "geometry": {"coordinates":[2.7634599209,42.1215782166],"type":"Point"}
}