{
  "type": "Feature",
  "properties": {
    "addr:full":"Calle de Santisimo, 4 Motril Granada 18600",
    "addr:housenumber":"4",
    "addr:postcode":"18600",
    "addr:street":"Calle De Santisimo",
    "iso:country":"ES",
    "sg:address":"Calle de Santisimo, 4",
    "sg:city":"Motril",
    "sg:orig_category":"Armas Y Municiones (fabricaci\u00d3n, Al Por Mayor)",
    "sg:phone":"+34 958 60 11 02",
    "sg:postcode":"18600",
    "sg:province":"Granada",
    "wof:name":"Martos Diaz Tomas",
    "wof:placetype":"venue"
},
  "geometry": {"coordinates":[-3.5119299889,36.7512397766],"type":"Point"}
}