{
  "type": "Feature",
  "properties": {
    "iso:country":"ES",
    "sg:address":"Carrer de Espronceda, 176",
    "sg:city":"Barcelona",
    "sg:orig_category":"Carnicer\u00cdas, Carnicer\u00cdas",
    "sg:phone":"+34 932 66 30 72",
    "sg:postcode":"08018",
    "sg:province":"Barcelona",
    "wof:name":"Carns Puigbo S.a.",
    "wof:placetype":"venue"
},
  "geometry": {"coordinates":[2.1993029118,41.4095916748],"type":"Point"}
}