{
  "type": "Feature",
  "properties": {
    "iso:country":"ES",
    "sg:address":"O Vao, S/n",
    "sg:city":"Pontevedra",
    "sg:orig_category":"Escayola Y Productos De Escayola (fabricaci\u00d3n, Al Por Mayor)",
    "sg:phone":"+34 986 87 13 18",
    "sg:postcode":"36157",
    "sg:province":"Pontevedra",
    "wof:name":"Gutierrez Salgado Emilio",
    "wof:placetype":"venue"
},
  "geometry": {"coordinates":[-8.6582126617,42.4889144897],"type":"Point"}
}