{
  "type": "Feature",
  "properties": {
    "addr:full":"Avda Constitucion (la), S/n Villamejil Le\u00f3n 24711",
    "addr:postcode":"24711",
    "addr:street":"Avda Constitucion La S / N;Leo\u0301N",
    "iso:country":"ES",
    "sg:address":"Avda Constitucion (la), S/n",
    "sg:city":"Villamejil",
    "sg:orig_category":"Venta, Instalaci\u00d3n De Calefacci\u00d3n",
    "sg:phone":"+34 987 60 50 73",
    "sg:postcode":"24711",
    "sg:province":"Le\u00f3n",
    "wof:name":"Garcia Villanueva Belarmino",
    "wof:placetype":"venue"
},
  "geometry": {"coordinates":[-6.0231189728,42.5625343323],"type":"Point"}
}