{
  "type": "Feature",
  "properties": {
    "iso:country":"ES",
    "sg:address":"Rua Castelao, S/n",
    "sg:city":"Milladoiro",
    "sg:orig_category":"Tintorer\u00cdas, Limpieza En Seco",
    "sg:phone":"+34 981 52 36 39",
    "sg:postcode":"15895",
    "sg:province":"A Coru\u00f1a",
    "wof:name":"Troiti\u00f1o Garcia Maria",
    "wof:placetype":"venue"
},
  "geometry": {"coordinates":[-8.5783472061,42.8416023254],"type":"Point"}
}