{
  "type": "Feature",
  "properties": {
    "iso:country":"ES",
    "sg:address":"Calle de Virgen De Guadalupe, 41",
    "sg:city":"Ubeda",
    "sg:orig_category":"M\u00c9dicos: Ginecolog\u00cda M\u00c9dica, Obstetricia",
    "sg:phone":"+34 953 79 09 35",
    "sg:postcode":"23400",
    "sg:province":"Ja\u00e9n",
    "wof:name":"Redondo Vega Luis Juan",
    "wof:placetype":"venue"
},
  "geometry": {"coordinates":[-3.3723189831,38.0158691406],"type":"Point"}
}