{
  "type": "Feature",
  "properties": {
    "iso:country":"ES",
    "sg:address":"Calle de San Juan De Letran, 5",
    "sg:city":"Malaga",
    "sg:orig_category":"Asesor\u00cdas Y Estudios Financieros",
    "sg:phone":"+34 952 12 19 25",
    "sg:postcode":"29012",
    "sg:province":"M\u00e1laga",
    "wof:name":"Parrondo Asesores S.l.",
    "wof:placetype":"venue"
},
  "geometry": {"coordinates":[-4.4181551933,36.723777771],"type":"Point"}
}