{
  "type": "Feature",
  "properties": {
    "iso:country":"ES",
    "sg:address":"Calle de Jose Ramos Borrero, S/n",
    "sg:city":"S. Fernando",
    "sg:orig_category":"Tintes (fabricaci\u00d3n, Al Por Mayor)",
    "sg:phone":"+34 956 59 20 84",
    "sg:postcode":"11100",
    "sg:province":"C\u00e1diz",
    "wof:name":"Bravo Ristori Carlos",
    "wof:placetype":"venue"
},
  "geometry": {"coordinates":[-6.2080340385,36.4549713135],"type":"Point"}
}