{
  "type": "Feature",
  "properties": {
    "iso:country":"ES",
    "sg:address":"Calle de Isabel La Catolica, 13",
    "sg:city":"Santander",
    "sg:orig_category":"Asesor\u00cda, Estudio Y Control Medioambiental",
    "sg:phone":"+34 942 23 49 00",
    "sg:postcode":"39007",
    "sg:province":"Cantabria",
    "sg:website":"www.fundacionosopardo.org",
    "wof:name":"Fundacion Oso Pardo Cantabrico",
    "wof:placetype":"venue"
},
  "geometry": {"coordinates":[-3.8143808842,43.4628105164],"type":"Point"}
}