{
  "type": "Feature",
  "properties": {
    "addr:full":"Llop Mari(urb. Marina Sant Jordi), 33 Ametlla Mar Tarragona 43860",
    "addr:housenumber":"33",
    "addr:postcode":"43860",
    "addr:street":"Urb. Marina Sant Jordi",
    "iso:country":"ES",
    "sg:address":"Llop Mari(urb. Marina Sant Jordi), 33",
    "sg:city":"Ametlla Mar",
    "sg:orig_category":"Promotores Constructores",
    "sg:phone":"+34 977 48 63 92",
    "sg:postcode":"43860",
    "sg:province":"Tarragona",
    "wof:name":"Marina Sant Jordi S.l.",
    "wof:placetype":"venue"
},
  "geometry": {"coordinates":[0.7992730141,40.8853607178],"type":"Point"}
}