{
  "type": "Feature",
  "properties": {
    "iso:country":"ES",
    "sg:address":"Ptda Cascalls, S/n",
    "sg:city":"Vilafames",
    "sg:orig_category":"Ferreter\u00cda (diversos)",
    "sg:phone":"+34 964 33 50 39",
    "sg:postcode":"12192",
    "sg:province":"Castell\u00f3n",
    "wof:name":"Hermanos Llorens C.b.",
    "wof:placetype":"venue"
},
  "geometry": {"coordinates":[-0.0640499964,40.1220092773],"type":"Point"}
}