{
  "type": "Feature",
  "properties": {
    "addr:full":"Calle de Venta (la), 57 Estacion Madrid 28400",
    "addr:housenumber":"57",
    "addr:postcode":"28400",
    "addr:street":"Calle De Venta La",
    "iso:country":"ES",
    "sg:address":"Calle de Venta (la), 57",
    "sg:city":"Estacion",
    "sg:orig_category":"Bronceado Por Rayos Uva",
    "sg:phone":"+34 918 51 36 39",
    "sg:postcode":"28400",
    "sg:province":"Madrid",
    "wof:name":"Kohan Starcman Liliana",
    "wof:placetype":"venue"
},
  "geometry": {"coordinates":[-4.1862940788,40.7417602539],"type":"Point"}
}