{
  "type": "Feature",
  "properties": {
    "iso:country":"ES",
    "sg:address":"Calle de L'horta, 12",
    "sg:city":"Torrent",
    "sg:orig_category":"Inform\u00c1tica Equipo Y Programas (al Por Mayor)",
    "sg:phone":"+34 961 57 45 66",
    "sg:postcode":"46900",
    "sg:province":"Valencia",
    "sg:website":"www.micronet.es",
    "wof:name":"Micronet S.a.",
    "wof:placetype":"venue"
},
  "geometry": {"coordinates":[-0.4734846056,39.4335441589],"type":"Point"}
}