{
  "type": "Feature",
  "properties": {
    "iso:country":"ES",
    "sg:address":"Av J Ortega Y Gasset (p I El Viso), 242",
    "sg:city":"Malaga",
    "sg:orig_category":"Quincaller\u00cda (al Por Menor)",
    "sg:phone":"+34 952 31 68 49",
    "sg:postcode":"29006",
    "sg:province":"M\u00e1laga",
    "wof:name":"Comercial Barragan S.l.",
    "wof:placetype":"venue"
},
  "geometry": {"coordinates":[-4.4731960297,36.7073326111],"type":"Point"}
}