{
  "type": "Feature",
  "properties": {
    "addr:full":"Calle de Biar, 22 Valderrobres Teruel 44580",
    "addr:housenumber":"22",
    "addr:postcode":"44580",
    "addr:street":"Calle De Biar",
    "iso:country":"ES",
    "sg:address":"Calle de Biar, 22",
    "sg:city":"Valderrobres",
    "sg:orig_category":"Promotores Constructores",
    "sg:phone":"+34 978 85 00 38",
    "sg:postcode":"44580",
    "sg:province":"Teruel",
    "wof:name":"Contrucciones Fernando Segurana S.l",
    "wof:placetype":"venue"
},
  "geometry": {"coordinates":[0.1512940973,40.8715400696],"type":"Point"}
}