{
  "type": "Feature",
  "properties": {
    "addr:full":"Pg Gracia, 103 Barcelona Barcelona 08008",
    "addr:housenumber":"103",
    "addr:postcode":"08008",
    "addr:street":"Pg Gracia",
    "iso:country":"ES",
    "sg:address":"Pg Gracia, 103",
    "sg:city":"Barcelona",
    "sg:orig_category":"Marketing Telef\u00d3nico",
    "sg:phone":"+34 932 08 25 81",
    "sg:postcode":"08008",
    "sg:province":"Barcelona",
    "wof:name":"Amicorp De Espa\u00f1a S.l.",
    "wof:placetype":"venue"
},
  "geometry": {"coordinates":[2.1602044106,41.3957214355],"type":"Point"}
}