{
  "type": "Feature",
  "properties": {
    "iso:country":"ES",
    "sg:address":"Calle de Rodio, 17",
    "sg:city":"Sevilla",
    "sg:orig_category":"Fotograf\u00cda Y Cine: Aparatos, Pel\u00cdculas Y Accesorios (fabricaci\u00d3n, Al Por Mayor)",
    "sg:phone":"+34 954 36 72 89",
    "sg:postcode":"41007",
    "sg:province":"Sevilla",
    "wof:name":"Arpiserra S.a.",
    "wof:placetype":"venue"
},
  "geometry": {"coordinates":[-5.9561185837,37.4074821472],"type":"Point"}
}