{
  "type": "Feature",
  "properties": {
    "addr:full":"Avda Fuenlabrada, 37 Leganes Madrid 28911",
    "addr:housenumber":"37",
    "addr:postcode":"28911",
    "addr:street":"Avda Fuenlabrada",
    "iso:country":"ES",
    "sg:address":"Avda Fuenlabrada, 37",
    "sg:city":"Leganes",
    "sg:orig_category":"Frutas, Legumbres Frescas Y Tempranas (al Por Menor)",
    "sg:phone":"+34 916 88 61 64",
    "sg:postcode":"28911",
    "sg:province":"Madrid",
    "wof:name":"Perera Berrio Fernando",
    "wof:placetype":"venue"
},
  "geometry": {"coordinates":[-3.7626340389,40.3296813965],"type":"Point"}
}