{
  "type": "Feature",
  "properties": {
    "addr:full":"Carrer de Gasometre (del), 20 Tarragona Tarragona 43001",
    "addr:housenumber":"20",
    "addr:postcode":"43001",
    "addr:street":"Carrer De Gasometre Del",
    "iso:country":"ES",
    "sg:address":"Carrer de Gasometre (del), 20",
    "sg:city":"Tarragona",
    "sg:orig_category":"Ense\u00d1ante, Direcci\u00d3n",
    "sg:phone":"+34 977 22 17 70",
    "sg:postcode":"43001",
    "sg:province":"Tarragona",
    "wof:name":"Duran Vidal Saturnino",
    "wof:placetype":"venue"
},
  "geometry": {"coordinates":[1.2493289709,41.1137886047],"type":"Point"}
}