{
  "type": "Feature",
  "properties": {
    "addr:full":"Calle de Mayor, 1 Fuentealbilla Albacete 02260",
    "addr:housenumber":"1",
    "addr:postcode":"02260",
    "addr:street":"Calle De Mayor",
    "iso:country":"ES",
    "sg:address":"Calle de Mayor, 1",
    "sg:city":"Fuentealbilla",
    "sg:orig_category":"Sales (al Por Mayor)",
    "sg:phone":"+34 967 47 21 09",
    "sg:postcode":"02260",
    "sg:province":"Albacete",
    "wof:name":"Almacenes De Fuentealbilla Lucy-sal S.l.",
    "wof:placetype":"venue"
},
  "geometry": {"coordinates":[-1.5495723486,39.2664756775],"type":"Point"}
}