{
  "type": "Feature",
  "properties": {
    "addr:full":"Carrer de Rogent, 44 Barcelona Barcelona 08026",
    "addr:housenumber":"44",
    "addr:postcode":"08026",
    "addr:street":"Carrer De Rogent",
    "iso:country":"ES",
    "sg:address":"Carrer de Rogent, 44",
    "sg:city":"Barcelona",
    "sg:orig_category":"\u00d3ptica: Instrumentos (fabricaci\u00d3n)",
    "sg:phone":"+34 932 32 25 58",
    "sg:postcode":"08026",
    "sg:province":"Barcelona",
    "wof:name":"Vilardell Llinas Maria Teresa",
    "wof:placetype":"venue"
},
  "geometry": {"coordinates":[2.1845610142,41.4093513489],"type":"Point"}
}