{
  "type": "Feature",
  "properties": {
    "iso:country":"ES",
    "sg:address":"Av Puig I Cadafalch, 10",
    "sg:city":"Argentona",
    "sg:orig_category":"Papeler\u00cdas, Librer\u00cdas",
    "sg:phone":"+34 937 56 17 16",
    "sg:postcode":"08310",
    "sg:province":"Barcelona",
    "wof:name":"Office Mataro S.l.",
    "wof:placetype":"venue"
},
  "geometry": {"coordinates":[2.4027459621,41.5540962219],"type":"Point"}
}