{
  "type": "Feature",
  "properties": {
    "addr:full":"Carrer de Major, 10 Amposta Tarragona 43870",
    "addr:housenumber":"10",
    "addr:postcode":"43870",
    "addr:street":"Carrer De Major",
    "iso:country":"ES",
    "sg:address":"Carrer de Major, 10",
    "sg:city":"Amposta",
    "sg:orig_category":"Inmobiliaria (agencias)",
    "sg:phone":"+34 977 70 05 78",
    "sg:postcode":"43870",
    "sg:province":"Tarragona",
    "wof:name":"Garcia Drago Manel",
    "wof:placetype":"venue"
},
  "geometry": {"coordinates":[0.5806840062,40.7130699158],"type":"Point"}
}