{
  "type": "Feature",
  "properties": {
    "iso:country":"ES",
    "sg:address":"Calle de Emeterio Cuadrado, 6",
    "sg:city":"Mula",
    "sg:orig_category":"Art\u00cdculos De Regalo (al Por Menor)",
    "sg:phone":"+34 968 66 05 28",
    "sg:postcode":"30170",
    "sg:province":"Murcia",
    "wof:name":"Gonzalez Lopez Antonio",
    "wof:placetype":"venue"
},
  "geometry": {"coordinates":[-1.4953689575,38.0392990112],"type":"Point"}
}