{
  "type": "Feature",
  "properties": {
    "addr:full":"Calle de Andalucia De Iznalloz, 33 Iznalloz Granada 18550",
    "addr:housenumber":"33",
    "addr:postcode":"18550",
    "addr:street":"Calle De Andalucia De Iznalloz",
    "iso:country":"ES",
    "sg:address":"Calle de Andalucia De Iznalloz, 33",
    "sg:city":"Iznalloz",
    "sg:orig_category":"Cajas De Ahorro",
    "sg:phone":"+34 958 38 40 28",
    "sg:postcode":"18550",
    "sg:province":"Granada",
    "sg:website":"www.caja-granada.es",
    "wof:name":"Cajagranada",
    "wof:placetype":"venue"
},
  "geometry": {"coordinates":[-3.5610260963,37.4360160828],"type":"Point"}
}