{
  "type": "Feature",
  "properties": {
    "iso:country":"ES",
    "sg:address":"Calle de Pez Espada, 23",
    "sg:city":"Torremolinos",
    "sg:orig_category":"Agencias De Viajes",
    "sg:phone":"+34 952 37 60 82",
    "sg:postcode":"29620",
    "sg:province":"M\u00e1laga",
    "wof:name":"Iberoservice S.a.",
    "wof:placetype":"venue"
},
  "geometry": {"coordinates":[-4.509335041,36.6065444946],"type":"Point"}
}