{
  "type": "Feature",
  "properties": {
    "iso:country":"ES",
    "sg:address":"Calle de Laskorain Kalea, S/n",
    "sg:city":"Tolosa",
    "sg:orig_category":"Ayuda En Tareas Dom\u00c9sticas, Ayuda A Domicilio",
    "sg:phone":"+34 943 65 38 21",
    "sg:postcode":"20400",
    "sg:province":"Guip\u00f9zcoa",
    "wof:name":"A.gestion Telefonica Oficinas Y Despachos S.l.",
    "wof:placetype":"venue"
},
  "geometry": {"coordinates":[-2.0739789009,43.134513855],"type":"Point"}
}