{
  "type": "Feature",
  "properties": {
    "addr:full":"Plaz Costa Del Sol, 15 Torremolinos M\u00e1laga 29620",
    "addr:housenumber":"15",
    "addr:postcode":"29620",
    "addr:street":"Plaz Costa Del Sol;Ma\u0301Laga",
    "iso:country":"ES",
    "sg:address":"Plaz Costa Del Sol, 15",
    "sg:city":"Torremolinos",
    "sg:orig_category":"Servicios De Telecomunicaciones",
    "sg:phone":"+34 952 38 13 71",
    "sg:postcode":"29620",
    "sg:province":"M\u00e1laga",
    "sg:website":"www.ditelcom.es",
    "wof:name":"Momin Internacional S.l.",
    "wof:placetype":"venue"
},
  "geometry": {"coordinates":[-4.4994988441,36.6252593994],"type":"Point"}
}