{
  "type": "Feature",
  "properties": {
    "addr:full":"Ctra. Nijar, 259 Ca\u00f1ada San Urbano Almer\u00eda 04120",
    "addr:housenumber":"259",
    "addr:postcode":"04120",
    "addr:street":"Ctra. Nijar;San;Almeri\u0301A",
    "iso:country":"ES",
    "sg:address":"Ctra. Nijar, 259",
    "sg:city":"Ca\u00f1ada San Urbano",
    "sg:orig_category":"Empresas De Carpinter\u00cda De Madera",
    "sg:phone":"+34 950 29 24 86",
    "sg:postcode":"04120",
    "sg:province":"Almer\u00eda",
    "wof:name":"Montoya Montoya Antonio",
    "wof:placetype":"venue"
},
  "geometry": {"coordinates":[-2.389688015,36.8369255066],"type":"Point"}
}