{
  "type": "Feature",
  "properties": {
    "addr:full":"Pl Major, 2 Rupit Barcelona 08569",
    "addr:housenumber":"2",
    "addr:postcode":"08569",
    "addr:street":"Pl Major",
    "iso:country":"ES",
    "sg:address":"Pl Major, 2",
    "sg:city":"Rupit",
    "sg:orig_category":"Art\u00cdculos Funerarios (al Por Menor)",
    "sg:phone":"+34 938 52 20 80",
    "sg:postcode":"08569",
    "sg:province":"Barcelona",
    "wof:name":"Caixa De Manlleu",
    "wof:placetype":"venue"
},
  "geometry": {"coordinates":[2.4647450447,42.0235786438],"type":"Point"}
}