{
  "type": "Feature",
  "properties": {
    "iso:country":"ES",
    "sg:address":"Calle de Mexico, 30",
    "sg:city":"Alacant",
    "sg:orig_category":"Reposter\u00cdas",
    "sg:phone":"+34 965 11 25 92",
    "sg:postcode":"03008",
    "sg:province":"Alicante",
    "wof:name":"Carpena Falco Francisco Jose",
    "wof:placetype":"venue"
},
  "geometry": {"coordinates":[-0.5076969862,38.3370018005],"type":"Point"}
}