{
  "type": "Feature",
  "properties": {
    "iso:country":"ES",
    "sg:address":"Calle de Santa Catalina, 17",
    "sg:city":"Higuera Real",
    "sg:orig_category":"Electrodom\u00c9sticos (al Por Menor)",
    "sg:phone":"+34 924 72 30 97",
    "sg:postcode":"06350",
    "sg:province":"Badajoz",
    "wof:name":"Electrodomesticos Rodriguez C.b.",
    "wof:placetype":"venue"
},
  "geometry": {"coordinates":[-6.6881937981,38.1411437988],"type":"Point"}
}