{
  "type": "Feature",
  "properties": {
    "addr:full":"Carrer de Vicari Joaquim Fus, 217 Palma Islas Baleares 07006",
    "addr:housenumber":"217",
    "addr:postcode":"07006",
    "addr:street":"Carrer De Vicari Joaquim Fus",
    "iso:country":"ES",
    "sg:address":"Carrer de Vicari Joaquim Fus, 217",
    "sg:city":"Palma",
    "sg:orig_category":"Agencias Y Asesores De Publicidad",
    "sg:phone":"+34 971 24 38 20",
    "sg:postcode":"07006",
    "sg:province":"Islas Baleares",
    "wof:name":"Ren Co Marketing S.l.",
    "wof:placetype":"venue"
},
  "geometry": {"coordinates":[2.6794729233,39.5567893982],"type":"Point"}
}