{
  "type": "Feature",
  "properties": {
    "iso:country":"ES",
    "sg:address":"Pase Chopera, 23",
    "sg:city":"Madrid",
    "sg:orig_category":"Tiendas De Grano, Frutas Y Legumbres Secas (al Por Menor)",
    "sg:phone":"+34 914 73 64 65",
    "sg:postcode":"28045",
    "sg:province":"Madrid",
    "wof:name":"Zhang  Xuefeng",
    "wof:placetype":"venue"
},
  "geometry": {"coordinates":[-3.7014131546,40.3956489563],"type":"Point"}
}