{
  "type": "Feature",
  "properties": {
    "addr:full":"Calle de Pontevedra, 11 Cordoba C\u00f3rdoba 14013",
    "addr:housenumber":"11",
    "addr:postcode":"14013",
    "addr:street":"Calle De Pontevedra;Co\u0301Rdoba",
    "iso:country":"ES",
    "sg:address":"Calle de Pontevedra, 11",
    "sg:city":"Cordoba",
    "sg:orig_category":"M\u00c9dicos: Estomatolog\u00cda",
    "sg:phone":"+34 957 29 36 79",
    "sg:postcode":"14013",
    "sg:province":"C\u00f3rdoba",
    "wof:name":"Morales Collado Maria Auxiliadora",
    "wof:placetype":"venue"
},
  "geometry": {"coordinates":[-4.7779350281,37.8677253723],"type":"Point"}
}