{
  "type": "Feature",
  "properties": {
    "iso:country":"ES",
    "sg:address":"Cmno Salabosque, S/n",
    "sg:city":"Aljucer",
    "sg:orig_category":"Maquinaria Para Industrias Diversas",
    "sg:phone":"+34 968 25 43 22",
    "sg:postcode":"30152",
    "sg:province":"Murcia",
    "wof:name":"Inadyr S. L.",
    "wof:placetype":"venue"
},
  "geometry": {"coordinates":[-1.1458209753,37.9578018188],"type":"Point"}
}