{
  "type": "Feature",
  "properties": {
    "iso:country":"ES",
    "sg:address":"Ctra Sant Hipolit, 25",
    "sg:city":"Vic",
    "sg:orig_category":"Metalurgia",
    "sg:phone":"+34 938 86 34 44",
    "sg:postcode":"08500",
    "sg:province":"Barcelona",
    "wof:name":"Ripoll I Fills S.l.",
    "wof:placetype":"venue"
},
  "geometry": {"coordinates":[2.2536580563,41.9407043457],"type":"Point"}
}