{
  "type": "Feature",
  "properties": {
    "iso:country":"ES",
    "sg:address":"Calle de Embajadores, 82",
    "sg:city":"Madrid",
    "sg:orig_category":"Molduras, Junquillos, Listones Y Molduras Perforadas",
    "sg:phone":"+34 915 17 59 44",
    "sg:postcode":"28012",
    "sg:province":"Madrid",
    "wof:name":"Alegre Sanchez Jacinto",
    "wof:placetype":"venue"
},
  "geometry": {"coordinates":[-3.7016158104,40.4037132263],"type":"Point"}
}