{
  "type": "Feature",
  "properties": {
    "addr:full":"Po. Born, 2 Binissalem Islas Baleares 07350",
    "addr:housenumber":"2",
    "addr:postcode":"07350",
    "addr:street":"Po. Born",
    "iso:country":"ES",
    "sg:address":"Po. Born, 2",
    "sg:city":"Binissalem",
    "sg:orig_category":"Cajas De Ahorro",
    "sg:phone":"+34 971 88 66 22",
    "sg:postcode":"07350",
    "sg:province":"Islas Baleares",
    "sg:website":"www.sanostra.es",
    "wof:name":"Caja De Ahorros Y Monte De Piedad De Las Baleares",
    "wof:placetype":"venue"
},
  "geometry": {"coordinates":[2.8421080112,39.6895713806],"type":"Point"}
}