{
  "type": "Feature",
  "properties": {
    "addr:full":"Calle de Pilar, 10 Fuente Maestre Badajoz 06360",
    "addr:housenumber":"10",
    "addr:postcode":"06360",
    "addr:street":"Calle De Pilar",
    "iso:country":"ES",
    "sg:address":"Calle de Pilar, 10",
    "sg:city":"Fuente Maestre",
    "sg:orig_category":"Bancos",
    "sg:phone":"+34 924 53 15 12",
    "sg:postcode":"06360",
    "sg:province":"Badajoz",
    "sg:website":"www.bancosimeon.es",
    "wof:name":"Banco Caixa Geral S.a.",
    "wof:placetype":"venue"
},
  "geometry": {"coordinates":[-6.4475259781,38.5259590149],"type":"Point"}
}