{
  "type": "Feature",
  "properties": {
    "addr:full":"Calle de Podabines, 6 Donostia-san Sebastian Guip\u00f9zcoa 20010",
    "addr:housenumber":"6",
    "addr:postcode":"20010",
    "addr:street":"Calle De Podabines",
    "iso:country":"ES",
    "sg:address":"Calle de Podabines, 6",
    "sg:city":"Donostia-san Sebastian",
    "sg:orig_category":"Peluquer\u00cdas, Peluquer\u00cda Mixta",
    "sg:phone":"+34 943 46 37 68",
    "sg:postcode":"20010",
    "sg:province":"Guip\u00f9zcoa",
    "wof:name":"Ayerbe Aguirre Maria Aranzazu",
    "wof:placetype":"venue"
},
  "geometry": {"coordinates":[-1.9797979593,43.3027648926],"type":"Point"}
}