{
  "type": "Feature",
  "properties": {
    "addr:full":"Calle de Maestro Millan Picazo, 7 Algeciras C\u00e1diz 11204",
    "addr:housenumber":"7;ca\u0301diz",
    "addr:postcode":"11204",
    "addr:street":"Calle De Maestro Millan Picazo",
    "iso:country":"ES",
    "sg:address":"Calle de Maestro Millan Picazo, 7",
    "sg:city":"Algeciras",
    "sg:orig_category":"Reposter\u00cdas",
    "sg:phone":"+34 956 66 81 52",
    "sg:postcode":"11204",
    "sg:province":"C\u00e1diz",
    "wof:name":"Ortega Mata Antonio",
    "wof:placetype":"venue"
},
  "geometry": {"coordinates":[-5.4494700432,36.1398925781],"type":"Point"}
}