{
  "type": "Feature",
  "properties": {
    "iso:country":"ES",
    "sg:address":"Carretera, S/n",
    "sg:city":"Odollo",
    "sg:orig_category":"Pizzer\u00cdas",
    "sg:phone":"+34 987 69 21 32",
    "sg:postcode":"24742",
    "sg:province":"Le\u00f3n",
    "wof:name":"Pizarras Expiz S.a.",
    "wof:placetype":"venue"
},
  "geometry": {"coordinates":[-6.5446491241,42.3402442932],"type":"Point"}
}