{
  "type": "Feature",
  "properties": {
    "addr:full":"Casal Novo, 31 Casal Novo Pontevedra 36099",
    "addr:housenumber":"31",
    "addr:postcode":"36099",
    "addr:street":"Casal Novo",
    "iso:country":"ES",
    "sg:address":"Casal Novo, 31",
    "sg:city":"Casal Novo",
    "sg:orig_category":"Asociaciones Y Clubs Deportivos",
    "sg:phone":"+34 986 87 35 12",
    "sg:postcode":"36099",
    "sg:province":"Pontevedra",
    "wof:name":"Club Orientacion Pontevedra",
    "wof:placetype":"venue"
},
  "geometry": {"coordinates":[-8.6428003311,42.4304618835],"type":"Point"}
}