{
  "type": "Feature",
  "properties": {
    "iso:country":"ES",
    "sg:address":"Ctra Novelda, S/n",
    "sg:city":"Monovar",
    "sg:orig_category":"Asociaciones Y Clubs Deportivos",
    "sg:phone":"+34 965 47 28 88",
    "sg:postcode":"03640",
    "sg:province":"Alicante",
    "wof:name":"Abad Martinez Josefa",
    "wof:placetype":"venue"
},
  "geometry": {"coordinates":[-0.840322,38.431576],"type":"Point"}
}