{
  "type": "Feature",
  "properties": {
    "addr:full":"Carrer de Mandoni, 10 Barcelona Barcelona 08004",
    "addr:housenumber":"10",
    "addr:postcode":"08004",
    "addr:street":"Carrer De Mandoni",
    "iso:country":"ES",
    "sg:address":"Carrer de Mandoni, 10",
    "sg:city":"Barcelona",
    "sg:orig_category":"Molduras, Junquillos, Listones Y Molduras Perforadas",
    "sg:phone":"+34 933 32 50 33",
    "sg:postcode":"08004",
    "sg:province":"Barcelona",
    "wof:name":"Alvarez Perez Jose",
    "wof:placetype":"venue"
},
  "geometry": {"coordinates":[2.1429569721,41.3690567017],"type":"Point"}
}