{
  "type": "Feature",
  "properties": {
    "iso:country":"ES",
    "sg:address":"Calle de Comunidad Valenciana, 21",
    "sg:city":"Almoradi",
    "sg:orig_category":"Agencias Y Asesores De Publicidad",
    "sg:phone":"+34 965 70 16 08",
    "sg:postcode":"03160",
    "sg:province":"Alicante",
    "wof:name":"Ediciones Gutierrez S.l.",
    "wof:placetype":"venue"
},
  "geometry": {"coordinates":[-0.7885341048,38.1096153259],"type":"Point"}
}