{
  "type": "Feature",
  "properties": {
    "iso:country":"ES",
    "sg:address":"Barr Zurbaranbarri, 10",
    "sg:city":"Bilbao",
    "sg:orig_category":"Molduras, Junquillos, Listones Y Molduras Perforadas",
    "sg:phone":"+34 944 46 10 69",
    "sg:postcode":"48007",
    "sg:province":"Vizcaya",
    "wof:name":"Bedoya Velarde Jose Angel",
    "wof:placetype":"venue"
},
  "geometry": {"coordinates":[-2.9123079777,43.2653388977],"type":"Point"}
}