{
  "type": "Feature",
  "properties": {
    "addr:full":"Calle de Democracia, 9 Valladolid Valladolid 47011",
    "addr:housenumber":"9",
    "addr:postcode":"47011",
    "addr:street":"Calle De Democracia",
    "iso:country":"ES",
    "sg:address":"Calle de Democracia, 9",
    "sg:city":"Valladolid",
    "sg:orig_category":"Institutos De Belleza",
    "sg:phone":"+34 983 26 40 10",
    "sg:postcode":"47011",
    "sg:province":"Valladolid",
    "wof:name":"Garcia Villalba Maria Paz",
    "wof:placetype":"venue"
},
  "geometry": {"coordinates":[-4.7199311256,41.658115387],"type":"Point"}
}