{
  "type": "Feature",
  "properties": {
    "addr:full":"Ortigueira, 25 Pontes Garcia Rodriguez La Coru\u00f1a 15320",
    "addr:housenumber":"25",
    "addr:postcode":"15320",
    "addr:street":"Ortigueira;Corun\u0303A",
    "iso:country":"ES",
    "sg:address":"Ortigueira, 25",
    "sg:city":"Pontes Garcia Rodriguez",
    "sg:orig_category":"Asociaciones Y Clubs Deportivos",
    "sg:phone":"+34 981 44 06 63",
    "sg:postcode":"15320",
    "sg:province":"La Coru\u00f1a",
    "wof:name":"Martinez Cupeiro Jose Carlos",
    "wof:placetype":"venue"
},
  "geometry": {"coordinates":[-7.8524842262,43.4529838562],"type":"Point"}
}