{
  "type": "Feature",
  "properties": {
    "addr:full":"Pg Maragall, 409 Barcelona Barcelona 08032",
    "addr:housenumber":"409",
    "addr:postcode":"08032",
    "addr:street":"Pg Maragall",
    "iso:country":"ES",
    "sg:address":"Pg Maragall, 409",
    "sg:city":"Barcelona",
    "sg:orig_category":"Cajas De Ahorro",
    "sg:phone":"+34 934 29 36 79",
    "sg:postcode":"08032",
    "sg:province":"Barcelona",
    "wof:name":"Caixa D'estalvis Del Penedes",
    "wof:placetype":"venue"
},
  "geometry": {"coordinates":[2.163009882,41.428691864],"type":"Point"}
}