{
  "type": "Feature",
  "properties": {
    "addr:full":"Cmno Pe\u00d1ascal, 23 Bilbao Vizcaya 48002",
    "addr:housenumber":"23",
    "addr:postcode":"48002",
    "addr:street":"Cmno Pen\u0303Ascal",
    "iso:country":"ES",
    "sg:address":"Cmno Pe\u00d1ascal, 23",
    "sg:city":"Bilbao",
    "sg:orig_category":"Alimentaci\u00d3n General (al Por Menor)",
    "sg:phone":"+34 944 43 02 15",
    "sg:postcode":"48002",
    "sg:province":"Vizcaya",
    "wof:name":"Jose Antonio Monje Salvidea",
    "wof:placetype":"venue"
},
  "geometry": {"coordinates":[-2.9498128891,43.2411804199],"type":"Point"}
}