{
  "type": "Feature",
  "properties": {
    "addr:full":"Calle de Sebastian Elcano, 6 Santurtzi Vizcaya 48980",
    "addr:housenumber":"6",
    "addr:postcode":"48980",
    "addr:street":"Calle De Sebastian Elcano",
    "iso:country":"ES",
    "sg:address":"Calle de Sebastian Elcano, 6",
    "sg:city":"Santurtzi",
    "sg:orig_category":"Molduras, Junquillos, Listones Y Molduras Perforadas",
    "sg:phone":"+34 944 83 19 36",
    "sg:postcode":"48980",
    "sg:province":"Vizcaya",
    "wof:name":"Hogar Del Pensionista San Juan Del Rompeolas",
    "wof:placetype":"venue"
},
  "geometry": {"coordinates":[-3.0469861031,43.33568573],"type":"Point"}
}