{
  "type": "Feature",
  "properties": {
    "addr:full":"Avda Ausias March, 13 Valencia Valencia 46006",
    "addr:housenumber":"13",
    "addr:postcode":"46006",
    "addr:street":"Avda Ausias March",
    "iso:country":"ES",
    "sg:address":"Avda Ausias March, 13",
    "sg:city":"Valencia",
    "sg:orig_category":"Comercio De Piezas De Recambio Y De Accesorios De Veh\u00cdculos, Veh\u00cdculos Industriales",
    "sg:phone":"+34 963 73 86 62",
    "sg:postcode":"46006",
    "sg:province":"Valencia",
    "wof:name":"Suministros Electricos Para Automoviles S.l.",
    "wof:placetype":"venue"
},
  "geometry": {"coordinates":[-0.3746309876,39.4557685852],"type":"Point"}
}