{
  "type": "Feature",
  "properties": {
    "addr:full":"Calle de Claustrilla, 5 Soria Soria 42003",
    "addr:housenumber":"5",
    "addr:postcode":"42003",
    "addr:street":"Calle De Claustrilla",
    "iso:country":"ES",
    "sg:address":"Calle de Claustrilla, 5",
    "sg:city":"Soria",
    "sg:orig_category":"Loter\u00cda Y T\u00d3mbola",
    "sg:phone":"+34 975 23 05 05",
    "sg:postcode":"42003",
    "sg:province":"Soria",
    "wof:name":"Perez Martinez Carmen",
    "wof:placetype":"venue"
},
  "geometry": {"coordinates":[-2.4677951336,41.7642707825],"type":"Point"}
}