{
  "type": "Feature",
  "properties": {
    "addr:full":"Rua Viana Do Bolo, 12 Ourense Ourense 32004",
    "addr:housenumber":"12",
    "addr:postcode":"32004",
    "addr:street":"Rua Viana;Bolo",
    "iso:country":"ES",
    "sg:address":"Rua Viana Do Bolo, 12",
    "sg:city":"Ourense",
    "sg:orig_category":"Prot\u00c9sicos Dentales",
    "sg:phone":"+34 988 22 69 42",
    "sg:postcode":"32004",
    "sg:province":"Ourense",
    "wof:name":"Coproden S. Coop Galega",
    "wof:placetype":"venue"
},
  "geometry": {"coordinates":[-7.8517131805,42.3386764526],"type":"Point"}
}