{
  "type": "Feature",
  "properties": {
    "iso:country":"ES",
    "sg:address":"Carrer de Plataner, 12",
    "sg:city":"Palma",
    "sg:orig_category":"Centros Empresariales",
    "sg:phone":"+34 971 47 49 33",
    "sg:postcode":"07008",
    "sg:province":"Islas Baleares",
    "wof:name":"Pe\u00d1alver Bonet Juan",
    "wof:placetype":"venue"
},
  "geometry": {"coordinates":[2.6858849525,39.5843887329],"type":"Point"}
}