{
  "type": "Feature",
  "properties": {
    "iso:country":"ES",
    "sg:address":"Lago, 6",
    "sg:city":"El Rompido",
    "sg:orig_category":"Arquitectos",
    "sg:phone":"+34 959 39 99 34",
    "sg:postcode":"21459",
    "sg:province":"Huelva",
    "wof:name":"Dise\u00f1o Arquitectura Y Decoracion",
    "wof:placetype":"venue"
},
  "geometry": {"coordinates":[-7.071059227,37.2135658264],"type":"Point"}
}