{
  "type": "Feature",
  "properties": {
    "addr:full":"Av Goles De L'ebre, 239 Deltebre Tarragona 43580",
    "addr:housenumber":"239",
    "addr:postcode":"43580",
    "addr:street":"Av Goles De L'Ebre",
    "iso:country":"ES",
    "sg:address":"Av Goles De L'ebre, 239",
    "sg:city":"Deltebre",
    "sg:orig_category":"Loter\u00cda Y T\u00d3mbola",
    "sg:phone":"+34 977 48 15 01",
    "sg:postcode":"43580",
    "sg:province":"Tarragona",
    "wof:name":"Paga Ortiga Juan Maria",
    "wof:placetype":"venue"
},
  "geometry": {"coordinates":[0.7387869954,40.7166786194],"type":"Point"}
}