{
  "type": "Feature",
  "properties": {
    "iso:country":"ES",
    "sg:address":"Calle de Margarita, 15",
    "sg:city":"Melones",
    "sg:orig_category":"Institutos De Belleza",
    "sg:phone":"+34 928 13 42 65",
    "sg:postcode":"35212",
    "sg:province":"Las Palmas",
    "wof:name":"Borzani Gatto Jorge Alberto",
    "wof:placetype":"venue"
},
  "geometry": {"coordinates":[-15.3836965561,28.0140953064],"type":"Point"}
}