{
  "type": "Feature",
  "properties": {
    "addr:full":"Calle de San Claudio, 150 Madrid Madrid 28038",
    "addr:housenumber":"150",
    "addr:postcode":"28038",
    "addr:street":"Calle De San Claudio",
    "iso:country":"ES",
    "sg:address":"Calle de San Claudio, 150",
    "sg:city":"Madrid",
    "sg:orig_category":"Poller\u00cda Y Caza (al Por Menor)",
    "sg:phone":"+34 917 77 36 75",
    "sg:postcode":"28038",
    "sg:province":"Madrid",
    "wof:name":"Cendrero Carde\u00f1osa Pedro Jesus",
    "wof:placetype":"venue"
},
  "geometry": {"coordinates":[-3.639662981,40.3890075684],"type":"Point"}
}