{
  "type": "Feature",
  "properties": {
    "addr:full":"Avda Almendros, 7 Benidorm Alicante 03500",
    "addr:housenumber":"7",
    "addr:postcode":"03500",
    "addr:street":"Avda Almendros",
    "iso:country":"ES",
    "sg:address":"Avda Almendros, 7",
    "sg:city":"Benidorm",
    "sg:orig_category":"Cajas De Ahorro",
    "sg:phone":"+34 966 80 90 30",
    "sg:postcode":"03500",
    "sg:province":"Alicante",
    "sg:website":"www.caixacatalunya.es",
    "wof:name":"Caixa D'estalvis De Catalunya",
    "wof:placetype":"venue"
},
  "geometry": {"coordinates":[-0.1740590036,38.5364303589],"type":"Point"}
}