{
  "type": "Feature",
  "properties": {
    "addr:full":"Calle de Almirante Arizmendi, 8 Irun Guip\u00f9zcoa 20302",
    "addr:housenumber":"8",
    "addr:postcode":"20302",
    "addr:street":"Calle De Almirante Arizmendi;Guipu\u0300Zcoa",
    "iso:country":"ES",
    "sg:address":"Calle de Almirante Arizmendi, 8",
    "sg:city":"Irun",
    "sg:orig_category":"Molduras, Junquillos, Listones Y Molduras Perforadas",
    "sg:phone":"+34 943 62 09 78",
    "sg:postcode":"20302",
    "sg:province":"Guip\u00f9zcoa",
    "wof:name":"Call Phone S.l.",
    "wof:placetype":"venue"
},
  "geometry": {"coordinates":[-1.7913533449,43.3405303955],"type":"Point"}
}