{
  "type": "Feature",
  "properties": {
    "addr:full":"Calle de Suecia (de), 3 Fuenlabrada Madrid 28942",
    "addr:housenumber":"3",
    "addr:postcode":"28942",
    "addr:street":"Calle De Suecia De",
    "iso:country":"ES",
    "sg:address":"Calle de Suecia (de), 3",
    "sg:city":"Fuenlabrada",
    "sg:orig_category":"Tiendas De Grano, Frutas Y Legumbres Secas (al Por Menor)",
    "sg:phone":"+34 916 08 03 62",
    "sg:postcode":"28942",
    "sg:province":"Madrid",
    "wof:name":"Gines Vizcaino Maria Rosa",
    "wof:placetype":"venue"
},
  "geometry": {"coordinates":[-3.8082959652,40.2899398804],"type":"Point"}
}