{
  "type": "Feature",
  "properties": {
    "iso:country":"ES",
    "sg:address":"Calle de Hermanas Moreno Pozuelo, 5",
    "sg:city":"Pozoblanco",
    "sg:orig_category":"Asociaciones Humanitarias, De Cooperaci\u00d3n, De Acci\u00d3n Social",
    "sg:phone":"+34 957 13 12 25",
    "sg:postcode":"14400",
    "sg:province":"C\u00f3rdoba",
    "wof:name":"Asoc Para La Rehabilitacion Y Resinsercion Integral De Toxicomanosel Buen Samaritano",
    "wof:placetype":"venue"
},
  "geometry": {"coordinates":[-4.8479795456,38.3790817261],"type":"Point"}
}