{
  "type": "Feature",
  "properties": {
    "iso:country":"ES",
    "sg:address":"Calle de Mayor, 1",
    "sg:city":"Fontanar",
    "sg:orig_category":"Empresas De Carpinter\u00cda De Madera",
    "sg:phone":"+34 949 33 02 23",
    "sg:postcode":"19290",
    "sg:province":"Guadalajara",
    "wof:name":"Gil Nu\u00f1ez Miguel Angel",
    "wof:placetype":"venue"
},
  "geometry": {"coordinates":[-3.1769781113,40.7289848328],"type":"Point"}
}