{
  "type": "Feature",
  "properties": {
    "addr:full":"Avda Republica De China, 28 Sevilla Sevilla 41020",
    "addr:housenumber":"28",
    "addr:postcode":"41020",
    "addr:street":"Avda Republica De China",
    "iso:country":"ES",
    "sg:address":"Avda Republica De China, 28",
    "sg:city":"Sevilla",
    "sg:orig_category":"Asociaciones Humanitarias, De Cooperaci\u00d3n, De Acci\u00d3n Social",
    "sg:phone":"+34 954 47 51 28",
    "sg:postcode":"41020",
    "sg:province":"Sevilla",
    "wof:name":"Federacion Andaluza De Asociaciones De Sordos",
    "wof:placetype":"venue"
},
  "geometry": {"coordinates":[-5.9171519279,37.4077835083],"type":"Point"}
}