{
  "type": "Feature",
  "properties": {
    "iso:country":"ES",
    "sg:address":"Calle de Esperanto, 16",
    "sg:city":"Malaga",
    "sg:orig_category":"Asesor\u00cda Sobre Comunicaci\u00d3n De Empresas",
    "sg:phone":"+34 952 28 10 78",
    "sg:postcode":"29007",
    "sg:province":"M\u00e1laga",
    "wof:name":"Barcelo Miro Fernando",
    "wof:placetype":"venue"
},
  "geometry": {"coordinates":[-4.4331521988,36.71925354],"type":"Point"}
}