{
  "type": "Feature",
  "properties": {
    "iso:country":"ES",
    "sg:address":"Calle de Enrique Dequidt Hevia, 15",
    "sg:city":"Coru\u00d1a",
    "sg:orig_category":"Asesor\u00cda De Formaci\u00d3n Y Gesti\u00d3n De Personal",
    "sg:phone":"+34 981 26 70 99",
    "sg:postcode":"15005",
    "sg:province":"La Coru\u00f1a",
    "wof:name":"Garcia Ruiz Francisco Javier",
    "wof:placetype":"venue"
},
  "geometry": {"coordinates":[-8.4092760086,43.3627281189],"type":"Point"}
}