{
  "type": "Feature",
  "properties": {
    "iso:country":"ES",
    "sg:address":"Rua Paraguay, 19",
    "sg:city":"Vigo",
    "sg:orig_category":"Inmobiliaria (agencias)",
    "sg:phone":"+34 986 41 14 78",
    "sg:postcode":"36204",
    "sg:province":"Pontevedra",
    "wof:name":"Alagoro Gestion Inmobiliaria E Informatica S.l.",
    "wof:placetype":"venue"
},
  "geometry": {"coordinates":[-8.7151594162,42.2325134277],"type":"Point"}
}