{
  "type": "Feature",
  "properties": {
    "iso:country":"ES",
    "sg:address":"Calle de Alvar Nu\u00d1ez Cabeza De Vaca, S/n",
    "sg:city":"Sevilla",
    "sg:orig_category":"Papeler\u00cdas, Librer\u00cdas",
    "sg:phone":"+34 954 25 43 92",
    "sg:postcode":"41007",
    "sg:province":"Sevilla",
    "wof:name":"Rodriguez Corchete Emilia",
    "wof:placetype":"venue"
},
  "geometry": {"coordinates":[-5.9549446106,37.3970184326],"type":"Point"}
}