{
  "type": "Feature",
  "properties": {
    "iso:country":"ES",
    "sg:address":"Avda Playa Paraiso, S/n",
    "sg:city":"Playa Paraiso",
    "sg:orig_category":"Alquiler De Veh\u00cdculos: Turismos Y Utilitarios",
    "sg:phone":"+34 922 74 15 25",
    "sg:postcode":"38678",
    "sg:province":"Santa Cruz De Tenerife",
    "wof:name":"Perez Pe\u00f1a Florencio Adan",
    "wof:placetype":"venue"
},
  "geometry": {"coordinates":[-16.7669334412,28.1203994751],"type":"Point"}
}