{
  "type": "Feature",
  "properties": {
    "addr:full":"Calle de Unzue Severo, S/n Bilbao Vizcaya 48002",
    "addr:housenumber":"/ n",
    "addr:postcode":"48002",
    "addr:street":"Calle De Unzue Severo S",
    "iso:country":"ES",
    "sg:address":"Calle de Unzue Severo, S/n",
    "sg:city":"Bilbao",
    "sg:orig_category":"Muebles Y Accesorios Para Cocinas Y Cuartos De Ba\u00d1o (al Por Menor)",
    "sg:phone":"+34 944 43 59 97",
    "sg:postcode":"48002",
    "sg:province":"Vizcaya",
    "wof:name":"Leyre S.a.",
    "wof:placetype":"venue"
},
  "geometry": {"coordinates":[-2.940943718,43.2509307861],"type":"Point"}
}