{
  "type": "Feature",
  "properties": {
    "addr:full":"Plaz Ezkurdi Plaza, 4 Durango Vizcaya 48200",
    "addr:housenumber":"4",
    "addr:postcode":"48200",
    "addr:street":"Plaz;Plaza",
    "iso:country":"ES",
    "sg:address":"Plaz Ezkurdi Plaza, 4",
    "sg:city":"Durango",
    "sg:orig_category":"Abogados",
    "sg:phone":"+34 944 66 92 43",
    "sg:postcode":"48200",
    "sg:province":"Vizcaya",
    "wof:name":"M\u00aa Dolores Aguirre Suarez",
    "wof:placetype":"venue"
},
  "geometry": {"coordinates":[-2.6334609985,43.1685066223],"type":"Point"}
}