{
  "type": "Feature",
  "properties": {
    "addr:full":"Avda Jose De Mora, 77 Baza Granada 18800",
    "addr:housenumber":"77",
    "addr:postcode":"18800",
    "addr:street":"Avda Jose De Mora",
    "iso:country":"ES",
    "sg:address":"Avda Jose De Mora, 77",
    "sg:city":"Baza",
    "sg:orig_category":"Universidades",
    "sg:phone":"+34 958 86 12 36",
    "sg:postcode":"18800",
    "sg:province":"Granada",
    "wof:name":"Patronato Asociado A La Uned",
    "wof:placetype":"venue"
},
  "geometry": {"coordinates":[-2.7683858871,37.4837379456],"type":"Point"}
}