{
  "type": "Feature",
  "properties": {
    "addr:full":"Calle de Diego De Leon, 39 Madrid Madrid 28006",
    "addr:housenumber":"39",
    "addr:postcode":"madrid;28006",
    "addr:street":"Calle De Diego De Leon",
    "iso:country":"ES",
    "sg:address":"Calle de Diego De Leon, 39",
    "sg:city":"Madrid",
    "sg:orig_category":"Doctores En Medicina",
    "sg:phone":"+34 914 11 72 72",
    "sg:postcode":"28006",
    "sg:province":"Madrid",
    "wof:name":"Bonino Mendez Luis",
    "wof:placetype":"venue"
},
  "geometry": {"coordinates":[-3.679874897,40.4349136353],"type":"Point"}
}