{
  "type": "Feature",
  "properties": {
    "iso:country":"ES",
    "sg:address":"Pase Mikeletegi De, 1",
    "sg:city":"Donostia-san Sebastian",
    "sg:orig_category":"Empresas De Electricidad En General",
    "sg:phone":"+34 943 00 57 00",
    "sg:postcode":"20...",
    "sg:province":"Guip\u00f9zcoa",
    "wof:name":"Iberdrola S.a.",
    "wof:placetype":"venue"
},
  "geometry": {"coordinates":[-1.9794000387,43.3173789978],"type":"Point"}
}