{
  "type": "Feature",
  "properties": {
    "iso:country":"ES",
    "sg:address":"Calle de Vasco Nu\u00d1ez De Balboa, S/n",
    "sg:city":"Marchamalo",
    "sg:orig_category":"Comercio De Piezas De Recambio Y De Accesorios De Veh\u00cdculos, Veh\u00cdculos Industriales",
    "sg:phone":"+34 949 25 09 28",
    "sg:postcode":"19180",
    "sg:province":"Guadalajara",
    "wof:name":"Mecanizados Marchamalo S.l.l",
    "wof:placetype":"venue"
},
  "geometry": {"coordinates":[-3.2014870644,40.6685218811],"type":"Point"}
}