{
  "type": "Feature",
  "properties": {
    "iso:country":"ES",
    "sg:address":"Calle de Dolores De La Rocha, 24",
    "sg:city":"Palmas De Gran Canaria",
    "sg:orig_category":"Asesor\u00cda Sobre Comunicaci\u00d3n De Empresas",
    "sg:phone":"+34 928 31 20 66",
    "sg:postcode":"35001",
    "sg:province":"Las Palmas",
    "wof:name":"Benitez Biscarri Enrique",
    "wof:placetype":"venue"
},
  "geometry": {"coordinates":[-15.4133605957,28.0971698761],"type":"Point"}
}