{
  "type": "Feature",
  "properties": {
    "iso:country":"ES",
    "sg:address":"Calle de Joaquin Costa, 21",
    "sg:city":"Valencia",
    "sg:orig_category":"Peluquer\u00cdas, Peluquer\u00cda Mixta",
    "sg:phone":"+34 963 95 36 58",
    "sg:postcode":"46005",
    "sg:province":"Valencia",
    "wof:name":"Gonzalez Padreda Maria Pilar",
    "wof:placetype":"venue"
},
  "geometry": {"coordinates":[-0.3668729961,39.4659843445],"type":"Point"}
}