{
  "type": "Feature",
  "properties": {
    "addr:full":"Avda Padre Isla, 13 Le\u00f3n Le\u00f3n 24002",
    "addr:housenumber":"13",
    "addr:postcode":"24002",
    "addr:street":"Avda Padre Isla;Leo\u0301N",
    "iso:country":"ES",
    "sg:address":"Avda Padre Isla, 13",
    "sg:city":"Le\u00f3n",
    "sg:orig_category":"Zapatos (al Por Menor)",
    "sg:phone":"+34 987 87 56 71",
    "sg:postcode":"24002",
    "sg:province":"Le\u00f3n",
    "wof:name":"Merkal Calzados S.l.",
    "wof:placetype":"venue"
},
  "geometry": {"coordinates":[-5.5731358528,42.5995063782],"type":"Point"}
}