{
  "type": "Feature",
  "properties": {
    "addr:full":"Ctra. Tarragona-san Sebastian, Km. 0162,7 Barbastro Huesca 22300",
    "addr:postcode":"22300",
    "addr:street":"Ctra. Tarragona-San Sebastian Km. 0162,7",
    "iso:country":"ES",
    "sg:address":"Ctra. Tarragona-san Sebastian, Km. 0162,7",
    "sg:city":"Barbastro",
    "sg:orig_category":"Refiner\u00cdas De Petr\u00d3leo",
    "sg:phone":"+34 974 31 48 64",
    "sg:postcode":"22300",
    "sg:province":"Huesca",
    "wof:name":"Kuwait Petroleum Espa\u00f1a S.a.",
    "wof:placetype":"venue"
},
  "geometry": {"coordinates":[0.1047969982,42.0337791443],"type":"Point"}
}