{
  "type": "Feature",
  "properties": {
    "addr:full":"Calle de Real, 24 Valdepe\u00f1as Ciudad Real 13300",
    "addr:housenumber":"24",
    "addr:postcode":"13300",
    "addr:street":"Calle De Real",
    "iso:country":"ES",
    "sg:address":"Calle de Real, 24",
    "sg:city":"Valdepe\u00f1as",
    "sg:orig_category":"Cuchiller\u00cda (al Por Menor)",
    "sg:phone":"+34 926 32 24 53",
    "sg:postcode":"13300",
    "sg:province":"Ciudad Real",
    "wof:name":"Gonzalez Vazquez Cesar",
    "wof:placetype":"venue"
},
  "geometry": {"coordinates":[-3.3831729889,38.7623825073],"type":"Point"}
}