{
  "type": "Feature",
  "properties": {
    "addr:full":"Calle de Fuencarral, 35 Madrid Madrid 28004",
    "addr:housenumber":"35",
    "addr:postcode":"madrid;28004",
    "addr:street":"Calle De Fuencarral",
    "iso:country":"ES",
    "sg:address":"Calle de Fuencarral, 35",
    "sg:city":"Madrid",
    "sg:orig_category":"Confecci\u00d3n (fabricaci\u00d3n, Al Por Mayor)",
    "sg:phone":"+34 915 32 11 14",
    "sg:postcode":"28004",
    "sg:province":"Madrid",
    "sg:website":"www.glam.es",
    "wof:name":"Dise\u00d1os Glam S.l.",
    "wof:placetype":"venue"
},
  "geometry": {"coordinates":[-3.7010440826,40.4222717285],"type":"Point"}
}