{
  "type": "Feature",
  "properties": {
    "addr:full":"Calle de Atletico De Madrid, 19 Madrid Madrid 28025",
    "addr:housenumber":"19",
    "addr:postcode":"madrid;28025",
    "addr:street":"Calle De Atletico;Madrid",
    "iso:country":"ES",
    "sg:address":"Calle de Atletico De Madrid, 19",
    "sg:city":"Madrid",
    "sg:orig_category":"Farmacias",
    "sg:phone":"+34 914 65 04 93",
    "sg:postcode":"28025",
    "sg:province":"Madrid",
    "wof:name":"Tejuca Carriedo Concepcion",
    "wof:placetype":"venue"
},
  "geometry": {"coordinates":[-3.7418498993,40.3757095337],"type":"Point"}
}