{
  "type": "Feature",
  "properties": {
    "addr:full":"Ctra. Francia, S/n Candanchu Huesca 22889",
    "addr:housenumber":"s / n",
    "addr:postcode":"22889",
    "addr:street":"Ctra. Francia",
    "iso:country":"ES",
    "sg:address":"Ctra. Francia, S/n",
    "sg:city":"Candanchu",
    "sg:orig_category":"Molduras, Junquillos, Listones Y Molduras Perforadas",
    "sg:phone":"+34 974 37 31 77",
    "sg:postcode":"22889",
    "sg:province":"Huesca",
    "wof:name":"Perez Primicia Aurea",
    "wof:placetype":"venue"
},
  "geometry": {"coordinates":[-0.5231779814,42.7850799561],"type":"Point"}
}