{
  "type": "Feature",
  "properties": {
    "iso:country":"ES",
    "sg:address":"Calle de Zaragoza, 1",
    "sg:city":"Candasnos",
    "sg:orig_category":"Restaurantes",
    "sg:phone":"+34 974 46 30 51",
    "sg:postcode":"22591",
    "sg:province":"Huesca",
    "wof:name":"Guiu Ballabriga Maria Jesus",
    "wof:placetype":"venue"
},
  "geometry": {"coordinates":[0.0586480014,41.5021591187],"type":"Point"}
}