{
  "type": "Feature",
  "properties": {
    "iso:country":"ES",
    "sg:address":"Calle de Olaguibel, 54",
    "sg:city":"Vitoria-gasteiz",
    "sg:orig_category":"Molduras, Junquillos, Listones Y Molduras Perforadas",
    "sg:phone":"+34 945 25 08 73",
    "sg:postcode":"01003",
    "sg:province":"\u00c1lava",
    "wof:name":"Jose Ramon Martinez De Aramayona",
    "wof:placetype":"venue"
},
  "geometry": {"coordinates":[-2.6640760899,42.8455314636],"type":"Point"}
}