{
  "type": "Feature",
  "properties": {
    "addr:full":"Antoiu Kalea, 38 Lesaka Navarra 31770",
    "addr:housenumber":"38",
    "addr:postcode":"31770",
    "addr:street":"Antoiu Kalea",
    "iso:country":"ES",
    "sg:address":"Antoiu Kalea, 38",
    "sg:city":"Lesaka",
    "sg:orig_category":"Asilos De Ancianos. Centros Privados",
    "sg:phone":"+34 948 63 71 54",
    "sg:postcode":"31770",
    "sg:province":"Navarra",
    "wof:name":"Residencia Andra Mari",
    "wof:placetype":"venue"
},
  "geometry": {"coordinates":[-1.7023589611,43.2470703125],"type":"Point"}
}