{
  "type": "Feature",
  "properties": {
    "addr:full":"Calle de Menendez Pelayo, 5 Gijon Asturias 33202",
    "addr:housenumber":"5",
    "addr:postcode":"33202",
    "addr:street":"Calle De Menendez Pelayo",
    "iso:country":"ES",
    "sg:address":"Calle de Menendez Pelayo, 5",
    "sg:city":"Gijon",
    "sg:orig_category":"Florister\u00cdas",
    "sg:phone":"+34 985 36 23 73",
    "sg:postcode":"33202",
    "sg:province":"Asturias",
    "wof:name":"Granda Menendez Vanesa",
    "wof:placetype":"venue"
},
  "geometry": {"coordinates":[-5.6523618698,43.538105011],"type":"Point"}
}