{
  "type": "Feature",
  "properties": {
    "addr:full":"Avda Barrio Nuevo, 24 Cangas Narcea Asturias 33800",
    "addr:housenumber":"24",
    "addr:postcode":"33800",
    "addr:street":"Avda Barrio Nuevo",
    "iso:country":"ES",
    "sg:address":"Avda Barrio Nuevo, 24",
    "sg:city":"Cangas Narcea",
    "sg:orig_category":"Electrodom\u00c9sticos (al Por Menor)",
    "sg:phone":"+34 985 81 25 54",
    "sg:postcode":"33800",
    "sg:province":"Asturias",
    "wof:name":"Alles Alvarez Francisco Amador",
    "wof:placetype":"venue"
},
  "geometry": {"coordinates":[-6.551923275,43.1746520996],"type":"Point"}
}