{
  "type": "Feature",
  "properties": {
    "iso:country":"ES",
    "sg:address":"Carrer de Villa, 29",
    "sg:city":"S. Cugat Valles",
    "sg:orig_category":"Cueros Y Pieles (al Por Mayor)",
    "sg:phone":"+34 935 90 80 71",
    "sg:postcode":"08173",
    "sg:province":"Barcelona",
    "wof:name":"Spain Interproducts S.l.",
    "wof:placetype":"venue"
},
  "geometry": {"coordinates":[2.0787220001,41.4662971497],"type":"Point"}
}