{
  "type": "Feature",
  "properties": {
    "iso:country":"ES",
    "sg:address":"Calle de San Anton, 2",
    "sg:city":"Alfaro",
    "sg:orig_category":"Partidos Pol\u00cdticos",
    "sg:phone":"+34 941 18 27 18",
    "sg:postcode":"26540",
    "sg:province":"La Rioja",
    "wof:name":"Partido Popular",
    "wof:placetype":"venue"
},
  "geometry": {"coordinates":[-1.7486383915,42.1792030334],"type":"Point"}
}