{
  "type": "Feature",
  "properties": {
    "iso:country":"ES",
    "sg:address":"Rua Marxion, 14",
    "sg:city":"Vilagarcia",
    "sg:orig_category":"M\u00c9dicos: Ginecolog\u00cda Y Obstetricia",
    "sg:phone":"+34 986 50 22 01",
    "sg:postcode":"36600",
    "sg:province":"Pontevedra",
    "wof:name":"Sieyro Rodriguez Luis",
    "wof:placetype":"venue"
},
  "geometry": {"coordinates":[-8.7632188797,42.5956382751],"type":"Point"}
}