{
  "type": "Feature",
  "properties": {
    "addr:full":"Calle de Salitre, 4 Cartagena Murcia 30205",
    "addr:housenumber":"4",
    "addr:postcode":"30205",
    "addr:street":"Calle De Salitre",
    "iso:country":"ES",
    "sg:address":"Calle de Salitre, 4",
    "sg:city":"Cartagena",
    "sg:orig_category":"Farmacias",
    "sg:phone":"+34 968 50 67 61",
    "sg:postcode":"30205",
    "sg:province":"Murcia",
    "wof:name":"Garcia Diaz Ambrosio",
    "wof:placetype":"venue"
},
  "geometry": {"coordinates":[-0.9890440106,37.605430603],"type":"Point"}
}