{
  "type": "Feature",
  "properties": {
    "addr:full":"Avda Italia (de), 1 Montilla C\u00f3rdoba 14550",
    "addr:housenumber":"1",
    "addr:postcode":"14550",
    "addr:street":"Avda Italia De;Co\u0301Rdoba",
    "iso:country":"ES",
    "sg:address":"Avda Italia (de), 1",
    "sg:city":"Montilla",
    "sg:orig_category":"Cooperativas Agr\u00cdcolas",
    "sg:phone":"+34 957 65 67 09",
    "sg:postcode":"14550",
    "sg:province":"C\u00f3rdoba",
    "wof:name":"Union De Agricultores Y Ganaderos De Cordoba",
    "wof:placetype":"venue"
},
  "geometry": {"coordinates":[-4.6390151978,37.5811882019],"type":"Point"}
}