{
  "type": "Feature",
  "properties": {
    "iso:country":"ES",
    "sg:address":"Plaz Zorita, S/n",
    "sg:city":"Alcala Henares",
    "sg:orig_category":"Zapatos (al Por Menor)",
    "sg:phone":"+34 918 83 15 47",
    "sg:postcode":"28805",
    "sg:province":"Madrid",
    "wof:name":"El Zafarrancho S.l.",
    "wof:placetype":"venue"
},
  "geometry": {"coordinates":[-3.3307089806,40.5036354065],"type":"Point"}
}