{
  "type": "Feature",
  "properties": {
    "iso:country":"ES",
    "sg:address":"Pase Habana, 137",
    "sg:city":"Madrid",
    "sg:orig_category":"M\u00c9dicos: Cirug\u00cda Pl\u00c1stica, Reconstructiva Y Est\u00c9tica",
    "sg:phone":"+34 913 59 47 31",
    "sg:postcode":"28036",
    "sg:province":"Madrid",
    "sg:website":"www.franciscoabril.com",
    "wof:name":"Abril Gonzalez Francisco",
    "wof:placetype":"venue"
},
  "geometry": {"coordinates":[-3.68083,40.460594],"type":"Point"}
}