{
  "type": "Feature",
  "properties": {
    "iso:country":"ES",
    "sg:address":"Calle de Lucrecia Arana, 10",
    "sg:city":"Haro",
    "sg:orig_category":"Abogados",
    "sg:phone":"+34 941 31 29 20",
    "sg:postcode":"26200",
    "sg:province":"La Rioja",
    "wof:name":"Abogados Olarte Arrieta S.l.",
    "wof:placetype":"venue"
},
  "geometry": {"coordinates":[-2.847376,42.575977],"type":"Point"}
}