{
  "type": "Feature",
  "properties": {
    "addr:full":"Pg Cervantes, 1 Pego Alicante 03780",
    "addr:housenumber":"1",
    "addr:postcode":"03780",
    "addr:street":"Pg Cervantes",
    "iso:country":"ES",
    "sg:address":"Pg Cervantes, 1",
    "sg:city":"Pego",
    "sg:orig_category":"Molduras, Junquillos, Listones Y Molduras Perforadas",
    "sg:phone":"+34 965 57 08 26",
    "sg:postcode":"03780",
    "sg:province":"Alicante",
    "wof:name":"Gonzalez Frau Felipe",
    "wof:placetype":"venue"
},
  "geometry": {"coordinates":[-0.1195529997,38.8399200439],"type":"Point"}
}