{
  "type": "Feature",
  "properties": {
    "addr:full":"Calle de Reverendo Manuel Puigcerver, 11 Pilar Horadada Alicante 03190",
    "addr:housenumber":"11",
    "addr:postcode":"03190",
    "addr:street":"Calle De Reverendo Manuel Puigcerver",
    "iso:country":"ES",
    "sg:address":"Calle de Reverendo Manuel Puigcerver, 11",
    "sg:city":"Pilar Horadada",
    "sg:orig_category":"Pod\u00d3logos: Pedicuros",
    "sg:phone":"+34 965 35 28 94",
    "sg:postcode":"03190",
    "sg:province":"Alicante",
    "wof:name":"Mero\u00f1o Rosique Francisco Jose",
    "wof:placetype":"venue"
},
  "geometry": {"coordinates":[-0.7913789749,37.8655014038],"type":"Point"}
}