{
  "type": "Feature",
  "properties": {
    "iso:country":"ES",
    "sg:address":"Carrer de Francesc Layret, 32",
    "sg:city":"Castellar Valles",
    "sg:orig_category":"Electricidad: Instaladores",
    "sg:phone":"+34 937 47 26 05",
    "sg:postcode":"08211",
    "sg:province":"Barcelona",
    "wof:name":"Canudas Gobern Marcel",
    "wof:placetype":"venue"
},
  "geometry": {"coordinates":[2.08396101,41.6133651733],"type":"Point"}
}