{
  "type": "Feature",
  "properties": {
    "addr:full":"Barr Carbonaire C/6, 46 Vall D'uixo Castell\u00f3n 12600",
    "addr:housenumber":"46",
    "addr:postcode":"12600",
    "addr:street":"C / 6",
    "iso:country":"ES",
    "sg:address":"Barr Carbonaire C/6, 46",
    "sg:city":"Vall D'uixo",
    "sg:orig_category":"Promotores Constructores",
    "sg:phone":"+34 964 69 26 55",
    "sg:postcode":"12600",
    "sg:province":"Castell\u00f3n",
    "wof:name":"Obras Y Reformas Hurconst S.l.",
    "wof:placetype":"venue"
},
  "geometry": {"coordinates":[-0.0482099988,39.992477417],"type":"Point"}
}