{
  "type": "Feature",
  "properties": {
    "addr:full":"Verge Carme, 18 Platja Aro Girona 17250",
    "addr:housenumber":"18",
    "addr:postcode":"17250",
    "addr:street":"Carme",
    "iso:country":"ES",
    "sg:address":"Verge Carme, 18",
    "sg:city":"Platja Aro",
    "sg:orig_category":"Hoteles",
    "sg:phone":"+34 972 81 71 00",
    "sg:postcode":"17250",
    "sg:province":"Girona",
    "wof:name":"Balmaa Juando Antonio",
    "wof:placetype":"venue"
},
  "geometry": {"coordinates":[3.0639550686,41.8142547607],"type":"Point"}
}