{
  "type": "Feature",
  "properties": {
    "addr:full":"Calle de Antonio Vico, 25 Malaga M\u00e1laga 29014",
    "addr:housenumber":"25",
    "addr:postcode":"29014",
    "addr:street":"Calle De Antonio Vico;Ma\u0301Laga",
    "iso:country":"ES",
    "sg:address":"Calle de Antonio Vico, 25",
    "sg:city":"Malaga",
    "sg:orig_category":"Estancos",
    "sg:phone":"+34 952 25 36 64",
    "sg:postcode":"29014",
    "sg:province":"M\u00e1laga",
    "wof:name":"Lopez Jimenez Luis Miguel",
    "wof:placetype":"venue"
},
  "geometry": {"coordinates":[-4.4212598801,36.7410850525],"type":"Point"}
}