{
  "type": "Feature",
  "properties": {
    "iso:country":"ES",
    "sg:address":"Plaz Cristo, 1",
    "sg:city":"Usagre",
    "sg:orig_category":"Agencias Y Agentes Comerciales, Representantes",
    "sg:phone":"+34 924 58 52 07",
    "sg:postcode":"06290",
    "sg:province":"Badajoz",
    "wof:name":"Valle Arias Antonio Luis",
    "wof:placetype":"venue"
},
  "geometry": {"coordinates":[-6.1691851616,38.3549804688],"type":"Point"}
}