{
  "type": "Feature",
  "properties": {
    "iso:country":"ES",
    "sg:address":"Pl Jaume I, 19",
    "sg:city":"Vilafranca Penedes",
    "sg:orig_category":"Carpinteros",
    "sg:phone":"+34 938 90 32 33",
    "sg:postcode":"08720",
    "sg:province":"Barcelona",
    "wof:name":"Secope S.l.",
    "wof:placetype":"venue"
},
  "geometry": {"coordinates":[1.6960619688,41.3470954895],"type":"Point"}
}