{
  "type": "Feature",
  "properties": {
    "addr:full":"Carrer de Horta, 130 Barcelona Barcelona 08032",
    "addr:housenumber":"130",
    "addr:postcode":"08032",
    "addr:street":"Carrer De Horta",
    "iso:country":"ES",
    "sg:address":"Carrer de Horta, 130",
    "sg:city":"Barcelona",
    "sg:orig_category":"Cerrajer\u00cda, Ferrallista",
    "sg:phone":"+34 934 27 09 70",
    "sg:postcode":"08032",
    "sg:province":"Barcelona",
    "wof:name":"Garcia Mu\u00f1oz Andres",
    "wof:placetype":"venue"
},
  "geometry": {"coordinates":[2.1578919888,41.4324874878],"type":"Point"}
}