{
  "type": "Feature",
  "properties": {
    "addr:full":"Ctra. N. 340, S/n Ejido Almer\u00eda 04700",
    "addr:housenumber":"340 s / n",
    "addr:postcode":"04700",
    "addr:street":"Ctra. N.;Ejido Almeri\u0301A",
    "iso:country":"ES",
    "sg:address":"Ctra. N. 340, S/n",
    "sg:city":"Ejido",
    "sg:orig_category":"Carnicer\u00cdas, Carnicer\u00cdas",
    "sg:phone":"+34 950 57 03 04",
    "sg:postcode":"04700",
    "sg:province":"Almer\u00eda",
    "wof:name":"Toresano Moreno Juan Jose",
    "wof:placetype":"venue"
},
  "geometry": {"coordinates":[-2.8176040649,36.7727012634],"type":"Point"}
}