{
  "type": "Feature",
  "properties": {
    "iso:country":"ES",
    "sg:address":"Calle de Moscatel, 10",
    "sg:city":"Arroyo De La Miel-benalmadena Costa",
    "sg:orig_category":"Agentes, Concesionarios Y Sucursales De Veh\u00cdculos",
    "sg:phone":"+34 952 44 57 28",
    "sg:postcode":"29631",
    "sg:province":"M\u00e1laga",
    "wof:name":"Autoreparaciones Arroyo S.l.",
    "wof:placetype":"venue"
},
  "geometry": {"coordinates":[-4.5325632095,36.6064224243],"type":"Point"}
}