{
  "type": "Feature",
  "properties": {
    "addr:full":"Av Argentina, 24 S. Andreu Barca Barcelona 08740",
    "addr:housenumber":"24",
    "addr:postcode":"08740",
    "addr:street":"Av Argentina;S. Andreu;Barcelona",
    "iso:country":"ES",
    "sg:address":"Av Argentina, 24",
    "sg:city":"S. Andreu Barca",
    "sg:orig_category":"Sociedades, Compa\u00d1\u00cdas Aseguradoras",
    "sg:phone":"+34 936 82 90 29",
    "sg:postcode":"08740",
    "sg:province":"Barcelona",
    "wof:name":"Linea Llar S.l.",
    "wof:placetype":"venue"
},
  "geometry": {"coordinates":[1.979755044,41.445148468],"type":"Point"}
}