{
  "type": "Feature",
  "properties": {
    "iso:country":"ES",
    "sg:address":"Pg Gracia, 53",
    "sg:city":"Barcelona",
    "sg:orig_category":"Complementos De Vestir (al Por Menor)",
    "sg:phone":"+34 934 87 07 05",
    "sg:postcode":"08007",
    "sg:province":"Barcelona",
    "wof:name":"No Mercy S.l.",
    "wof:placetype":"venue"
},
  "geometry": {"coordinates":[2.1640748978,41.3924407959],"type":"Point"}
}