{
  "type": "Feature",
  "properties": {
    "addr:full":"Carrer de Francesc Moragas, 73 Santa Coloma De Gramenet Barcelona 08922",
    "addr:housenumber":"73",
    "addr:postcode":"08922",
    "addr:street":"Carrer De Francesc Moragas",
    "iso:country":"ES",
    "sg:address":"Carrer de Francesc Moragas, 73",
    "sg:city":"Santa Coloma De Gramenet",
    "sg:orig_category":"Peluquer\u00cdas, Peluquer\u00cda Mixta",
    "sg:phone":"+34 933 85 97 24",
    "sg:postcode":"08922",
    "sg:province":"Barcelona",
    "wof:name":"Serrano Hervas Tomas",
    "wof:placetype":"venue"
},
  "geometry": {"coordinates":[2.2060639858,41.4480247498],"type":"Point"}
}