{
  "type": "Feature",
  "properties": {
    "addr:full":"Carrer de Doctor Fleming, 12 S. Quirze Valles Barcelona 08192",
    "addr:housenumber":"12",
    "addr:postcode":"08192",
    "addr:street":"Carrer De Doctor Fleming",
    "iso:country":"ES",
    "sg:address":"Carrer de Doctor Fleming, 12",
    "sg:city":"S. Quirze Valles",
    "sg:orig_category":"Suministros Para Hoteles",
    "sg:phone":"+34 937 21 08 90",
    "sg:postcode":"08192",
    "sg:province":"Barcelona",
    "sg:website":"www.axarnt.com/satocar2",
    "wof:name":"Satocar-2 S.l.",
    "wof:placetype":"venue"
},
  "geometry": {"coordinates":[2.0770950317,41.535243988],"type":"Point"}
}