{
  "type": "Feature",
  "properties": {
    "iso:country":"ES",
    "sg:address":"Calle de Nereidas, 4",
    "sg:city":"Cadiz",
    "sg:orig_category":"Farmacias",
    "sg:phone":"+34 956 27 48 82",
    "sg:postcode":"11011",
    "sg:province":"C\u00e1diz",
    "wof:name":"Farmacia In-playa C.b.",
    "wof:placetype":"venue"
},
  "geometry": {"coordinates":[-6.2726140022,36.4982452393],"type":"Point"}
}