{
  "type": "Feature",
  "properties": {
    "iso:country":"ES",
    "sg:address":"Calle de General Moscardo, 57",
    "sg:city":"Albujon",
    "sg:orig_category":"Farmacias",
    "sg:phone":"+34 968 55 00 56",
    "sg:postcode":"30330",
    "sg:province":"Murcia",
    "wof:name":"Sola Mendez Carmen",
    "wof:placetype":"venue"
},
  "geometry": {"coordinates":[-1.0475820303,37.7174072266],"type":"Point"}
}