{
  "type": "Feature",
  "properties": {
    "iso:country":"ES",
    "sg:address":"Trva San Bernardo, 6",
    "sg:city":"Villarrobledo",
    "sg:orig_category":"Laboratorios Y Trabajos De Fotograf\u00cda, V\u00cddeo Y Cine",
    "sg:phone":"+34 967 14 74 55",
    "sg:postcode":"02600",
    "sg:province":"Albacete",
    "wof:name":"Camacho Guillen Francisco",
    "wof:placetype":"venue"
},
  "geometry": {"coordinates":[-2.6055390835,39.264755249],"type":"Point"}
}