{
  "type": "Feature",
  "properties": {
    "addr:full":"Calle de Bekolarra, 4 Vitoria-gasteiz \u00c1lava 01010",
    "addr:housenumber":"4",
    "addr:postcode":"01010",
    "addr:street":"Calle De Bekolarra",
    "iso:country":"ES",
    "sg:address":"Calle de Bekolarra, 4",
    "sg:city":"Vitoria-gasteiz",
    "sg:orig_category":"Negocio De Madera",
    "sg:phone":"+34 945 24 60 00",
    "sg:postcode":"01010",
    "sg:province":"\u00c1lava",
    "wof:name":"Saez Oca Jesus Maria",
    "wof:placetype":"venue"
},
  "geometry": {"coordinates":[-2.71575737,42.8582038879],"type":"Point"}
}