{
  "type": "Feature",
  "properties": {
    "addr:full":"Calle de Mayor, 16 Fuentes Ebro Zaragoza 50740",
    "addr:housenumber":"16",
    "addr:postcode":"50740",
    "addr:street":"Calle De Mayor",
    "iso:country":"ES",
    "sg:address":"Calle de Mayor, 16",
    "sg:city":"Fuentes Ebro",
    "sg:orig_category":"Cajas De Ahorro",
    "sg:phone":"+34 976 16 05 80",
    "sg:postcode":"50740",
    "sg:province":"Zaragoza",
    "wof:name":"Caja De Ahorros De La Inmaculada",
    "wof:placetype":"venue"
},
  "geometry": {"coordinates":[-0.6294289827,41.5119094849],"type":"Point"}
}