{
  "type": "Feature",
  "properties": {
    "addr:full":"Purgatori (pol Ind Gavarra), 40 Centelles Barcelona 08540",
    "addr:housenumber":"40",
    "addr:postcode":"08540",
    "addr:street":"Gavarra",
    "iso:country":"ES",
    "sg:address":"Purgatori (pol Ind Gavarra), 40",
    "sg:city":"Centelles",
    "sg:orig_category":"M\u00c1quinas, Material Y Suministros Para Cajas Y Embalajes",
    "sg:phone":"+34 938 81 20 12",
    "sg:postcode":"08540",
    "sg:province":"Barcelona",
    "wof:name":"Officina Meccanica Sestese Espa\u00f1a S.l.",
    "wof:placetype":"venue"
},
  "geometry": {"coordinates":[2.2247700691,41.7899055481],"type":"Point"}
}