{
  "type": "Feature",
  "properties": {
    "iso:country":"ES",
    "sg:address":"Av Badalona, 8",
    "sg:city":"Mollet Valles",
    "sg:orig_category":"Molduras, Junquillos, Listones Y Molduras Perforadas",
    "sg:phone":"+34 935 70 29 33",
    "sg:postcode":"08100",
    "sg:province":"Barcelona",
    "wof:name":"Planas Safon Esther",
    "wof:placetype":"venue"
},
  "geometry": {"coordinates":[2.2096569538,41.5341567993],"type":"Point"}
}