{
  "type": "Feature",
  "properties": {
    "addr:full":"Calle de Hermanos Fernandez, 15 Mengibar Ja\u00e9n 23620",
    "addr:housenumber":"15",
    "addr:postcode":"23620",
    "addr:street":"Calle De Hermanos Fernandez;Jae\u0301N",
    "iso:country":"ES",
    "sg:address":"Calle de Hermanos Fernandez, 15",
    "sg:city":"Mengibar",
    "sg:orig_category":"Droguer\u00cdas (al Por Menor)",
    "sg:phone":"+34 953 37 07 32",
    "sg:postcode":"23620",
    "sg:province":"Ja\u00e9n",
    "wof:name":"Camacho Mimbrera Sebastian",
    "wof:placetype":"venue"
},
  "geometry": {"coordinates":[-3.8080019951,37.9695777893],"type":"Point"}
}