{
  "type": "Feature",
  "properties": {
    "iso:country":"ES",
    "sg:address":"Ctra Villamarchante, 61",
    "sg:city":"Riba-roja Turia",
    "sg:orig_category":"Colchones (fabricaci\u00d3n, Al Por Mayor, Al Por Menor)",
    "sg:phone":"+34 962 77 07 17",
    "sg:postcode":"46190",
    "sg:province":"Valencia",
    "wof:name":"Folgado Montaner Francisco Javier",
    "wof:placetype":"venue"
},
  "geometry": {"coordinates":[-0.5716459751,39.5446052551],"type":"Point"}
}