{
  "type": "Feature",
  "properties": {
    "iso:country":"ES",
    "sg:address":"Avda Breogan, 15",
    "sg:city":"Foz",
    "sg:orig_category":"Clubes, Asociaciones De Ocio",
    "sg:phone":"+34 982 14 05 62",
    "sg:postcode":"27780",
    "sg:province":"Lugo",
    "wof:name":"Boda Foz S.l.",
    "wof:placetype":"venue"
},
  "geometry": {"coordinates":[-7.2613739967,43.5743751526],"type":"Point"}
}