{
  "type": "Feature",
  "properties": {
    "iso:country":"ES",
    "sg:address":"I. De La Cartuja, S/n",
    "sg:city":"Sevilla",
    "sg:orig_category":"Marketing Telef\u00d3nico",
    "sg:phone":"+34 954 48 76 00",
    "sg:postcode":"41...",
    "sg:province":"Sevilla",
    "wof:name":"Servicios De Telemarketing S.a.",
    "wof:placetype":"venue"
},
  "geometry": {"coordinates":[-6.0018129349,37.3876953125],"type":"Point"}
}