{
  "type": "Feature",
  "properties": {
    "iso:country":"ES",
    "sg:address":"Av Santuari, 1",
    "sg:city":"S. Ramon",
    "sg:orig_category":"Supermercados Y Hipermercados",
    "sg:phone":"+34 973 52 43 60",
    "sg:postcode":"25215",
    "sg:province":"Lleida",
    "wof:name":"Vejer Sole Andres",
    "wof:placetype":"venue"
},
  "geometry": {"coordinates":[1.3667650223,41.7261962891],"type":"Point"}
}