{
  "type": "Feature",
  "properties": {
    "addr:full":"Calle de Orly, 2 Pozuelo De Alarcon Madrid 28224",
    "addr:housenumber":"2",
    "addr:postcode":"28224",
    "addr:street":"Calle De Orly",
    "iso:country":"ES",
    "sg:address":"Calle de Orly, 2",
    "sg:city":"Pozuelo De Alarcon",
    "sg:orig_category":"Sociedades, Compa\u00d1\u00cdas Aseguradoras",
    "sg:phone":"+34 917 15 19 65",
    "sg:postcode":"28224",
    "sg:province":"Madrid",
    "wof:name":"Revilla Y Asociados Correduria De Seguros S.l.",
    "wof:placetype":"venue"
},
  "geometry": {"coordinates":[-3.7948350906,40.4492416382],"type":"Point"}
}