{
  "type": "Feature",
  "properties": {
    "addr:full":"Calle de Labradores, S/n Atalaya Del Ca\u00e7avate Cuenca 16710",
    "addr:housenumber":"s / n",
    "addr:postcode":"16710",
    "addr:street":"Calle De Labradores",
    "iso:country":"ES",
    "sg:address":"Calle de Labradores, S/n",
    "sg:city":"Atalaya Del Ca\u00e7avate",
    "sg:orig_category":"Molduras, Junquillos, Listones Y Molduras Perforadas",
    "sg:phone":"+34 969 38 10 62",
    "sg:postcode":"16710",
    "sg:province":"Cuenca",
    "wof:name":"Martinez Checa Angel",
    "wof:placetype":"venue"
},
  "geometry": {"coordinates":[-2.2507989407,39.5176582336],"type":"Point"}
}