{
  "type": "Feature",
  "properties": {
    "addr:full":"Carrer de Mn. Cinto Verdaguer, 28 S. Vicen\u00e7 Castellet Barcelona 08295",
    "addr:housenumber":"28",
    "addr:postcode":"08295",
    "addr:street":"Carrer De Mn. Cinto Verdaguer;S. Vicenc\u0327;Barcelona",
    "iso:country":"ES",
    "sg:address":"Carrer de Mn. Cinto Verdaguer, 28",
    "sg:city":"S. Vicen\u00e7 Castellet",
    "sg:orig_category":"Peluquer\u00cdas, Peluquer\u00cda Mixta",
    "sg:phone":"+34 938 33 19 96",
    "sg:postcode":"08295",
    "sg:province":"Barcelona",
    "wof:name":"Linares Cortes Maria",
    "wof:placetype":"venue"
},
  "geometry": {"coordinates":[1.8649549484,41.6706199646],"type":"Point"}
}