{
  "type": "Feature",
  "properties": {
    "iso:country":"ES",
    "sg:address":"Calle de Amor De Dios, 4",
    "sg:city":"Sevilla",
    "sg:orig_category":"Ropa Para Se\u00d1oras (al Por Menor)",
    "sg:phone":"+34 954 90 75 80",
    "sg:postcode":"41002",
    "sg:province":"Sevilla",
    "wof:name":"Torre Isla Maria Pilar",
    "wof:placetype":"venue"
},
  "geometry": {"coordinates":[-5.9945812225,37.3938407898],"type":"Point"}
}