{
  "type": "Feature",
  "properties": {
    "addr:full":"Carrer de Arx Lluis Salvador, 104 Palma Islas Baleares 07004",
    "addr:housenumber":"104",
    "addr:postcode":"07004",
    "addr:street":"Carrer De Arx Lluis Salvador",
    "iso:country":"ES",
    "sg:address":"Carrer de Arx Lluis Salvador, 104",
    "sg:city":"Palma",
    "sg:orig_category":"Molduras, Junquillos, Listones Y Molduras Perforadas",
    "sg:phone":"+34 971 29 16 92",
    "sg:postcode":"07004",
    "sg:province":"Islas Baleares",
    "wof:name":"Guerrero Pascual Socorro",
    "wof:placetype":"venue"
},
  "geometry": {"coordinates":[2.657886982,39.5851974487],"type":"Point"}
}