{
  "type": "Feature",
  "properties": {
    "addr:full":"Avda Salis, 32 Irun Guip\u00f9zcoa 20304",
    "addr:housenumber":"32",
    "addr:postcode":"20304",
    "addr:street":"Avda Salis;Guipu\u0300Zcoa",
    "iso:country":"ES",
    "sg:address":"Avda Salis, 32",
    "sg:city":"Irun",
    "sg:orig_category":"Frutas, Legumbres Frescas Y Tempranas (al Por Menor)",
    "sg:phone":"+34 943 63 53 06",
    "sg:postcode":"20304",
    "sg:province":"Guip\u00f9zcoa",
    "wof:name":"Martin Rodriguez Angela",
    "wof:placetype":"venue"
},
  "geometry": {"coordinates":[-1.7879048586,43.3413238525],"type":"Point"}
}