{
  "type": "Feature",
  "properties": {
    "iso:country":"ES",
    "sg:address":"Calle de Almendralejo, 48",
    "sg:city":"Merida",
    "sg:orig_category":"Muebles, Minoristas",
    "sg:phone":"+34 924 31 39 99",
    "sg:postcode":"06800",
    "sg:province":"Badajoz",
    "wof:name":"Caprichos Decoracion S.l.",
    "wof:placetype":"venue"
},
  "geometry": {"coordinates":[-6.3467268944,38.9188499451],"type":"Point"}
}