{
  "type": "Feature",
  "properties": {
    "addr:full":"Carr Santo Domingo, 7 Olleria Valencia 46850",
    "addr:housenumber":"7",
    "addr:postcode":"46850",
    "addr:street":"Carr Santo Domingo",
    "iso:country":"ES",
    "sg:address":"Carr Santo Domingo, 7",
    "sg:city":"Olleria",
    "sg:orig_category":"Carnicer\u00cdas, Carnicer\u00cdas",
    "sg:phone":"+34 962 20 08 70",
    "sg:postcode":"46850",
    "sg:province":"Valencia",
    "wof:name":"Vicent Monpo Teresa",
    "wof:placetype":"venue"
},
  "geometry": {"coordinates":[-0.5478360057,38.9096603394],"type":"Point"}
}