{
  "type": "Feature",
  "properties": {
    "iso:country":"ES",
    "sg:address":"Plaz Generalisimo, 3",
    "sg:city":"Suances",
    "sg:orig_category":"Confecci\u00d3n De Botones",
    "sg:phone":"+34 942 81 03 90",
    "sg:postcode":"39340",
    "sg:province":"Cantabria",
    "wof:name":"Hoyal Pedrajo Jose Alberto",
    "wof:placetype":"venue"
},
  "geometry": {"coordinates":[-4.0418858528,43.4262542725],"type":"Point"}
}