{
  "type": "Feature",
  "properties": {
    "addr:full":"Av Sant Esteve, 23 Granollers Barcelona 08402",
    "addr:housenumber":"23",
    "addr:postcode":"08402",
    "addr:street":"Av Sant Esteve",
    "iso:country":"ES",
    "sg:address":"Av Sant Esteve, 23",
    "sg:city":"Granollers",
    "sg:orig_category":"Molduras, Junquillos, Listones Y Molduras Perforadas",
    "sg:phone":"+34 938 70 56 51",
    "sg:postcode":"08402",
    "sg:province":"Barcelona",
    "wof:name":"Jurado Jimenez Rafael",
    "wof:placetype":"venue"
},
  "geometry": {"coordinates":[2.2906079292,41.6041297913],"type":"Point"}
}