{
  "type": "Feature",
  "properties": {
    "addr:full":"Entrada La De Villa, 24 Maderuelo Segovia 40554",
    "addr:housenumber":"24",
    "addr:postcode":"40554",
    "addr:street":"Entrada La De Villa;Segovia",
    "iso:country":"ES",
    "sg:address":"Entrada La De Villa, 24",
    "sg:city":"Maderuelo",
    "sg:orig_category":"Empresas De Desmonte",
    "sg:phone":"+34 921 55 61 33",
    "sg:postcode":"40554",
    "sg:province":"Segovia",
    "wof:name":"Bayo Martin Santiago",
    "wof:placetype":"venue"
},
  "geometry": {"coordinates":[-3.5232789516,41.4851989746],"type":"Point"}
}