{
  "type": "Feature",
  "properties": {
    "iso:country":"ES",
    "sg:address":"Calle de Mu\u00d1oz Degrain, 16",
    "sg:city":"Oviedo",
    "sg:orig_category":"Asesor\u00cda Fiscal Y Jur\u00cddica",
    "sg:phone":"+34 985 27 01 26",
    "sg:postcode":"33007",
    "sg:province":"Asturias",
    "wof:name":"Ais Asesoria Ingenieria Y Servicios S.l.",
    "wof:placetype":"venue"
},
  "geometry": {"coordinates":[-5.8494634628,43.3555145264],"type":"Point"}
}