{
  "type": "Feature",
  "properties": {
    "iso:country":"ES",
    "sg:address":"Calle de Iglesia, 1",
    "sg:city":"Cantillana",
    "sg:orig_category":"Iglesia Cat\u00d3lica",
    "sg:phone":"+34 955 73 11 82",
    "sg:postcode":"41320",
    "sg:province":"Sevilla",
    "wof:name":"Parroquia Nuestra Se\u00f1ora De La Asuncion",
    "wof:placetype":"venue"
},
  "geometry": {"coordinates":[-5.8257889748,37.6053886414],"type":"Point"}
}