{
  "type": "Feature",
  "properties": {
    "addr:full":"Unic, S/n Aravell Lleida 25712",
    "addr:housenumber":"s / n",
    "addr:postcode":"25712",
    "addr:street":"Unic",
    "iso:country":"ES",
    "sg:address":"Unic, S/n",
    "sg:city":"Aravell",
    "sg:classifiers":[
        {
            "category":"Sports & Exercise",
            "subcategory":"Golf",
            "type":"Entertainment"
        }
    ],
    "sg:phone":"+34 973 36 00 66",
    "sg:postcode":"25712",
    "sg:province":"Lleida",
    "sg:tags":[
        "y",
        "de",
        "campos",
        "clases"
    ],
    "wof:name":"Aravell Golf S.l.",
    "wof:placetype":"venue"
},
  "geometry": {"coordinates":[1.4055212736,42.3599624634],"type":"Point"}
}