{
  "type": "Feature",
  "properties": {
    "addr:full":"Calle de Valle De Laciana, 1 Madrid Madrid 28034",
    "addr:housenumber":"1",
    "addr:postcode":"28034",
    "addr:street":"Calle De Valle De Laciana",
    "iso:country":"ES",
    "sg:address":"Calle de Valle De Laciana, 1",
    "sg:city":"Madrid",
    "sg:orig_category":"Guarder\u00cdas",
    "sg:phone":"+34 917 38 44 50",
    "sg:postcode":"28034",
    "sg:province":"Madrid",
    "wof:name":"Arana Gallardo Paloma",
    "wof:placetype":"venue"
},
  "geometry": {"coordinates":[-3.7049026489,40.4877815247],"type":"Point"}
}