{
  "type": "Feature",
  "properties": {
    "iso:country":"ES",
    "sg:address":"Luga San Roque-san Claudio, 15",
    "sg:city":"San Roque",
    "sg:orig_category":"Reposter\u00cdas",
    "sg:phone":"+34 985 78 08 68",
    "sg:postcode":"33191",
    "sg:province":"Asturias",
    "wof:name":"Rodriguez Gonzalez Paz Concepcion",
    "wof:placetype":"venue"
},
  "geometry": {"coordinates":[-5.9176192284,43.3596382141],"type":"Point"}
}