{
  "type": "Feature",
  "properties": {
    "iso:country":"ES",
    "sg:address":"C/ Ciutat De Sagunt, 8",
    "sg:city":"Paterna",
    "sg:orig_category":"Aceros Inoxidables",
    "sg:phone":"+34 961 32 57 06",
    "sg:postcode":"46988",
    "sg:province":"Valencia",
    "sg:website":"www.cunado.com",
    "wof:name":"Cu\u00f1ado Inoxidables S.a.",
    "wof:placetype":"venue"
},
  "geometry": {"coordinates":[-0.4582520127,39.5134887695],"type":"Point"}
}