{
  "type": "Feature",
  "properties": {
    "addr:full":"Ctra. Chipiona-sanlucar, Km. 0070,0 Chipiona C\u00e1diz 11550",
    "addr:postcode":"11550",
    "addr:street":"Ctra. Chipiona-Sanlucar Km. 0070,0",
    "iso:country":"ES",
    "sg:address":"Ctra. Chipiona-sanlucar, Km. 0070,0",
    "sg:city":"Chipiona",
    "sg:orig_category":"Delegados, Agentes De Tr\u00c1nsito, Auxiliares De Transporte Internacional",
    "sg:phone":"+34 956 37 70 49",
    "sg:postcode":"11550",
    "sg:province":"C\u00e1diz",
    "wof:name":"Aljutrans Cadiz S.l.",
    "wof:placetype":"venue"
},
  "geometry": {"coordinates":[-6.3649706841,36.7600860596],"type":"Point"}
}