{
  "type": "Feature",
  "properties": {
    "iso:country":"ES",
    "sg:address":"Calle de Presa (de La), 48",
    "sg:city":"San Fernando De Henares",
    "sg:orig_category":"Empresas De Limpieza",
    "sg:phone":"+34 916 71 44 38",
    "sg:postcode":"28830",
    "sg:province":"Madrid",
    "wof:name":"Lopez Cuevas Pablo",
    "wof:placetype":"venue"
},
  "geometry": {"coordinates":[-3.5285539627,40.4295730591],"type":"Point"}
}