{
  "type": "Feature",
  "properties": {
    "addr:full":"Carrer de Born, 6 Vendrell Tarragona 43700",
    "addr:housenumber":"6",
    "addr:postcode":"43700",
    "addr:street":"Carrer De Born",
    "iso:country":"ES",
    "sg:address":"Carrer de Born, 6",
    "sg:city":"Vendrell",
    "sg:orig_category":"Inmobiliaria (agencias)",
    "sg:phone":"+34 977 15 42 15",
    "sg:postcode":"43700",
    "sg:province":"Tarragona",
    "wof:name":"Les 7 Cases S.l.",
    "wof:placetype":"venue"
},
  "geometry": {"coordinates":[1.5366230011,41.2194061279],"type":"Point"}
}