{
  "type": "Feature",
  "properties": {
    "addr:full":"Calle de Alas, 24 Madrid Madrid 28042",
    "addr:housenumber":"24",
    "addr:postcode":"madrid;28042",
    "addr:street":"Calle De Alas",
    "iso:country":"ES",
    "sg:address":"Calle de Alas, 24",
    "sg:city":"Madrid",
    "sg:orig_category":"Promotores Constructores",
    "sg:phone":"+34 913 01 01 07",
    "sg:postcode":"28042",
    "sg:province":"Madrid",
    "wof:name":"Cuathex Interiores S.l.",
    "wof:placetype":"venue"
},
  "geometry": {"coordinates":[-3.5833961964,40.4727783203],"type":"Point"}
}