{
  "type": "Feature",
  "properties": {
    "addr:full":"Calle de Abogado Aranda, 20 Hinojosa Del Duque C\u00f3rdoba 14270",
    "addr:housenumber":"20",
    "addr:postcode":"14270",
    "addr:street":"Calle De Abogado Aranda;Co\u0301Rdoba",
    "iso:country":"ES",
    "sg:address":"Calle de Abogado Aranda, 20",
    "sg:city":"Hinojosa Del Duque",
    "sg:orig_category":"Supermercados Y Hipermercados",
    "sg:phone":"+34 957 14 00 46",
    "sg:postcode":"14270",
    "sg:province":"C\u00f3rdoba",
    "wof:name":"Hermanos Pozo C.b.",
    "wof:placetype":"venue"
},
  "geometry": {"coordinates":[-5.1478705406,38.4980812073],"type":"Point"}
}