{
  "type": "Feature",
  "properties": {
    "addr:full":"Avda Palomares, S/n Coria Rio Sevilla 41100",
    "addr:postcode":"41100",
    "addr:street":"Avda Palomares S / N",
    "iso:country":"ES",
    "sg:address":"Avda Palomares, S/n",
    "sg:city":"Coria Rio",
    "sg:orig_category":"Agentes, Concesionarios Y Sucursales De Veh\u00cdculos",
    "sg:phone":"+34 954 77 63 16",
    "sg:postcode":"41100",
    "sg:province":"Sevilla",
    "wof:name":"Hondi Motors S.a.",
    "wof:placetype":"venue"
},
  "geometry": {"coordinates":[-6.0547938347,37.2909202576],"type":"Point"}
}