{
  "type": "Feature",
  "properties": {
    "addr:full":"Avda Emigrantes (los), 26 Ecija Sevilla 41400",
    "addr:housenumber":"26",
    "addr:postcode":"41400",
    "addr:street":"Avda Emigrantes Los",
    "iso:country":"ES",
    "sg:address":"Avda Emigrantes (los), 26",
    "sg:city":"Ecija",
    "sg:orig_category":"Reparaciones Y Remolcado De Veh\u00cdculos",
    "sg:phone":"+34 955 90 12 15",
    "sg:postcode":"41400",
    "sg:province":"Sevilla",
    "wof:name":"Rodriguez Martos Antonio",
    "wof:placetype":"venue"
},
  "geometry": {"coordinates":[-5.0858130455,37.5436897278],"type":"Point"}
}