{
  "type": "Feature",
  "properties": {
    "iso:country":"ES",
    "sg:address":"Plaz Cervantes, 18",
    "sg:city":"Alcala Henares",
    "sg:orig_category":"Bisuter\u00cda, Joyer\u00cda, Relojer\u00cda (al Por Menor)",
    "sg:phone":"+34 918 80 23 79",
    "sg:postcode":"28801",
    "sg:province":"Madrid",
    "wof:name":"Jimenez Martin Adoracion Justa",
    "wof:placetype":"venue"
},
  "geometry": {"coordinates":[-3.3645646572,40.4824409485],"type":"Point"}
}