{
  "type": "Feature",
  "properties": {
    "iso:country":"ES",
    "sg:address":"Calle de Paseo Del Agua, S/n",
    "sg:city":"Brenes",
    "sg:orig_category":"Chapister\u00cda",
    "sg:phone":"+34 954 79 66 99",
    "sg:postcode":"41310",
    "sg:province":"Sevilla",
    "wof:name":"Frias Bautista Jose",
    "wof:placetype":"venue"
},
  "geometry": {"coordinates":[-5.8697390556,37.5507011414],"type":"Point"}
}