{
  "type": "Feature",
  "properties": {
    "addr:full":"Avda Profesor Peraza De Ayala, 7 Santa Cruz De Tenerife Santa Cruz De Tenerife 38001",
    "addr:housenumber":"7",
    "addr:postcode":"38001",
    "addr:street":"Avda Profesor Peraza De Ayala",
    "iso:country":"ES",
    "sg:address":"Avda Profesor Peraza De Ayala, 7",
    "sg:city":"Santa Cruz De Tenerife",
    "sg:orig_category":"Asesor\u00cda Fiscal Y Jur\u00cddica",
    "sg:phone":"+34 922 28 98 88",
    "sg:postcode":"38001",
    "sg:province":"Santa Cruz De Tenerife",
    "wof:name":"Borges Miquel Juan Jose",
    "wof:placetype":"venue"
},
  "geometry": {"coordinates":[-16.2538375854,28.4946174622],"type":"Point"}
}