{
  "type": "Feature",
  "properties": {
    "addr:full":"Avgd Marques De Campo, S/n Gandia Valencia 46700",
    "addr:housenumber":"s / n",
    "addr:postcode":"46700",
    "addr:street":"Valencia",
    "iso:country":"ES",
    "sg:address":"Avgd Marques De Campo, S/n",
    "sg:city":"Gandia",
    "sg:orig_category":"Autob\u00das (explotaci\u00d3n Y Servicios De)",
    "sg:phone":"+34 962 87 41 10",
    "sg:postcode":"46700",
    "sg:province":"Valencia",
    "wof:name":"Lineas Europeas De Autobuses S.a.",
    "wof:placetype":"venue"
},
  "geometry": {"coordinates":[-0.1913339943,38.960735321],"type":"Point"}
}