{
  "type": "Feature",
  "properties": {
    "addr:full":"Avgd Marti Pujol, 298 Badalona Barcelona 08911",
    "addr:housenumber":"298",
    "addr:postcode":"08911",
    "addr:street":"Pujol",
    "iso:country":"ES",
    "sg:address":"Avgd Marti Pujol, 298",
    "sg:city":"Badalona",
    "sg:orig_category":"Fabricaci\u00d3n, Importaci\u00d3n, Venta De Material De Telefon\u00cda, Peritelefon\u00cda",
    "sg:phone":"+34 934 64 22 22",
    "sg:postcode":"08911",
    "sg:province":"Barcelona",
    "wof:name":"Catphone Net S.l.",
    "wof:placetype":"venue"
},
  "geometry": {"coordinates":[2.2432370186,41.4531784058],"type":"Point"}
}