{
  "type": "Feature",
  "properties": {
    "iso:country":"ES",
    "sg:address":"Calle de Sampiro, 11",
    "sg:city":"Le\u00f3n",
    "sg:orig_category":"Prot\u00c9sicos Dentales",
    "sg:phone":"+34 987 22 87 03",
    "sg:postcode":"24001",
    "sg:province":"Le\u00f3n",
    "wof:name":"Testera Tovar Mariano Luis",
    "wof:placetype":"venue"
},
  "geometry": {"coordinates":[-5.5800538063,42.6001701355],"type":"Point"}
}