{
  "type": "Feature",
  "properties": {
    "iso:country":"ES",
    "sg:address":"Carr Son Madu, 25",
    "sg:city":"Campos",
    "sg:orig_category":"Electricidad: Instaladores",
    "sg:phone":"+34 971 65 00 74",
    "sg:postcode":"07630",
    "sg:province":"Islas Baleares",
    "wof:name":"Garcias Garcias Julian",
    "wof:placetype":"venue"
},
  "geometry": {"coordinates":[2.997559309,39.4272499084],"type":"Point"}
}