{
  "type": "Feature",
  "properties": {
    "addr:full":"Calle de Jesus Y Maria, 7 Madridejos Toledo 45710",
    "addr:housenumber":"7",
    "addr:postcode":"45710",
    "addr:street":"Calle De Jesus Y Maria",
    "iso:country":"ES",
    "sg:address":"Calle de Jesus Y Maria, 7",
    "sg:city":"Madridejos",
    "sg:orig_category":"Doctores En Medicina",
    "sg:phone":"+34 925 46 09 78",
    "sg:postcode":"45710",
    "sg:province":"Toledo",
    "wof:name":"Navas Garcia De Los Huertos Antonio",
    "wof:placetype":"venue"
},
  "geometry": {"coordinates":[-3.537553072,39.4675483704],"type":"Point"}
}