{
  "type": "Feature",
  "properties": {
    "iso:country":"ES",
    "sg:address":"D'empar Nadal, 12",
    "sg:city":"Cunit",
    "sg:orig_category":"Molduras, Junquillos, Listones Y Molduras Perforadas",
    "sg:phone":"+34 977 67 59 85",
    "sg:postcode":"43881",
    "sg:province":"Tarragona",
    "wof:name":"Jurado Zambrano Rosario",
    "wof:placetype":"venue"
},
  "geometry": {"coordinates":[1.6346479654,41.1967430115],"type":"Point"}
}