{
  "type": "Feature",
  "properties": {
    "iso:country":"ES",
    "sg:address":"Avda Portugal, 65",
    "sg:city":"Salamanca",
    "sg:orig_category":"Complementos De Vestir (al Por Menor)",
    "sg:phone":"+34 923 25 60 14",
    "sg:postcode":"37005",
    "sg:province":"Salamanca",
    "wof:name":"Cuellar Chaytur Claudia",
    "wof:placetype":"venue"
},
  "geometry": {"coordinates":[-5.6585130692,40.9715232849],"type":"Point"}
}