{
  "type": "Feature",
  "properties": {
    "iso:country":"ES",
    "sg:address":"Calle de El Prado, 8",
    "sg:city":"Vitoria-gasteiz",
    "sg:orig_category":"M\u00c9dicos: Pediatr\u00cda. Enfermedades De Los Ni\u00d1os",
    "sg:phone":"+34 945 25 19 95",
    "sg:postcode":"01005",
    "sg:province":"\u00c1lava",
    "wof:name":"Renteria Iza Ibone Elisabete",
    "wof:placetype":"venue"
},
  "geometry": {"coordinates":[-2.6742749214,42.8461303711],"type":"Point"}
}