{
  "type": "Feature",
  "properties": {
    "addr:full":"Av Barbera, 106 Sabadell Barcelona 08203",
    "addr:housenumber":"106",
    "addr:postcode":"08203",
    "addr:street":"Av Barbera",
    "iso:country":"ES",
    "sg:address":"Av Barbera, 106",
    "sg:city":"Sabadell",
    "sg:orig_category":"Cl\u00cdnicas Dentales",
    "sg:phone":"+34 937 12 02 77",
    "sg:postcode":"08203",
    "sg:province":"Barcelona",
    "wof:name":"Plandolit Armengol Antonio De",
    "wof:placetype":"venue"
},
  "geometry": {"coordinates":[2.1138060093,41.5364494324],"type":"Point"}
}