{
  "type": "Feature",
  "properties": {
    "iso:country":"ES",
    "sg:address":"Plaz Diputacion (de La), S/n",
    "sg:city":"Cabra",
    "sg:orig_category":"Distribuci\u00d3n De Petr\u00d3leo Y Derivados",
    "sg:phone":"+34 957 52 33 56",
    "sg:postcode":"14940",
    "sg:province":"C\u00f3rdoba",
    "sg:website":"www.cepsa.es",
    "wof:name":"Rivas Prieto Miguel",
    "wof:placetype":"venue"
},
  "geometry": {"coordinates":[-4.4467329979,37.4725837708],"type":"Point"}
}