{
  "type": "Feature",
  "properties": {
    "iso:country":"ES",
    "sg:address":"Calle de Carreteros, 14",
    "sg:city":"Antequera",
    "sg:orig_category":"Centros M\u00c9dicos Y Sociales, Dispensarios",
    "sg:phone":"+34 952 84 18 90",
    "sg:postcode":"29200",
    "sg:province":"M\u00e1laga",
    "wof:name":"Centro Medico Antequera S.l.",
    "wof:placetype":"venue"
},
  "geometry": {"coordinates":[-4.5619301796,37.0171470642],"type":"Point"}
}