{
  "type": "Feature",
  "properties": {
    "addr:full":"Calle de Larramendi, 1 Almoradi Alicante 03160",
    "addr:housenumber":"1",
    "addr:postcode":"03160",
    "addr:street":"Calle De Larramendi",
    "iso:country":"ES",
    "sg:address":"Calle de Larramendi, 1",
    "sg:city":"Almoradi",
    "sg:orig_category":"Ropa Para Ni\u00d1os (al Por Menor)",
    "sg:phone":"+34 966 78 02 74",
    "sg:postcode":"03160",
    "sg:province":"Alicante",
    "wof:name":"Juan Sanchez Maria",
    "wof:placetype":"venue"
},
  "geometry": {"coordinates":[-0.791779995,38.1086196899],"type":"Point"}
}