{
  "type": "Feature",
  "properties": {
    "iso:country":"ES",
    "sg:address":"Ctra Porzuna (c), Km. 0020,0",
    "sg:city":"Casas",
    "sg:orig_category":"Asociaciones Humanitarias, De Cooperaci\u00d3n, De Acci\u00d3n Social",
    "sg:phone":"+34 926 69 04 02",
    "sg:postcode":"13196",
    "sg:province":"Ciudad Real",
    "wof:name":"Fundacion Provincial Contra La Toxicomanias",
    "wof:placetype":"venue"
},
  "geometry": {"coordinates":[-4.0594539642,39.0516586304],"type":"Point"}
}