{
  "type": "Feature",
  "properties": {
    "iso:country":"ES",
    "sg:address":"C/ Ruperto Chapi, 56",
    "sg:city":"Elche",
    "sg:orig_category":"Confecci\u00d3n De Trajes Para Se\u00d1oras",
    "sg:phone":"+34 966 67 03 97",
    "sg:postcode":"03201",
    "sg:province":"Alicante",
    "wof:name":"Alarcon Salinas Soledad Pilar",
    "wof:placetype":"venue"
},
  "geometry": {"coordinates":[-0.7032070756,38.268196106],"type":"Point"}
}