{
  "type": "Feature",
  "properties": {
    "iso:country":"ES",
    "sg:address":"Calle de Palangre, 4",
    "sg:city":"Puerto Del Carmen",
    "sg:orig_category":"Cl\u00cdnicas M\u00c9dicas",
    "sg:phone":"+34 928 51 20 57",
    "sg:postcode":"35510",
    "sg:province":"Las Palmas",
    "wof:name":"Rodriguez Porrua Rafael",
    "wof:placetype":"venue"
},
  "geometry": {"coordinates":[-13.6662149429,28.9237804413],"type":"Point"}
}