{
  "type": "Feature",
  "properties": {
    "iso:country":"ES",
    "sg:address":"Mandabidea, 1",
    "sg:city":"Zarautz",
    "sg:orig_category":"Importaci\u00d3n",
    "sg:phone":"+34 943 13 46 49",
    "sg:postcode":"20800",
    "sg:province":"Guip\u00f9zcoa",
    "wof:name":"Angel Unzueta Barber Y Maria Galarza Garraza Cdad.",
    "wof:placetype":"venue"
},
  "geometry": {"coordinates":[-2.1670610905,43.2862052917],"type":"Point"}
}