{
  "type": "Feature",
  "properties": {
    "addr:full":"Senda Granada, 15 Espinardo Murcia 30100",
    "addr:housenumber":"15",
    "addr:postcode":"30100",
    "addr:street":"Granada",
    "iso:country":"ES",
    "sg:address":"Senda Granada, 15",
    "sg:city":"Espinardo",
    "sg:orig_category":"Alimentaci\u00d3n General (al Por Menor)",
    "sg:phone":"+34 968 83 36 57",
    "sg:postcode":"30100",
    "sg:province":"Murcia",
    "wof:name":"Gomez Rodenas Francisco",
    "wof:placetype":"venue"
},
  "geometry": {"coordinates":[-1.1574389935,38.0078887939],"type":"Point"}
}