{
  "type": "Feature",
  "properties": {
    "addr:full":"C/ Dr. Miquel Servet, 30 Inca Islas Baleares 07300",
    "addr:housenumber":"30",
    "addr:postcode":"07300",
    "addr:street":"C / Dr. Miquel Servet",
    "iso:country":"ES",
    "sg:address":"C/ Dr. Miquel Servet, 30",
    "sg:city":"Inca",
    "sg:orig_category":"Mec\u00c1nico Del Autom\u00d3vil",
    "sg:phone":"+34 971 50 09 99",
    "sg:postcode":"07300",
    "sg:province":"Islas Baleares",
    "wof:name":"Taller Mecanico Culilloos C.d.",
    "wof:placetype":"venue"
},
  "geometry": {"coordinates":[2.9091899395,39.7197418213],"type":"Point"}
}