{
  "type": "Feature",
  "properties": {
    "addr:full":"Carrer de Can Mollet, 23 Mollet Valles Barcelona 08100",
    "addr:housenumber":"23",
    "addr:postcode":"08100",
    "addr:street":"Carrer De Can Mollet",
    "iso:country":"ES",
    "sg:address":"Carrer de Can Mollet, 23",
    "sg:city":"Mollet Valles",
    "sg:classifiers":[
        {
            "category":"Casinos & Gambling",
            "type":"Entertainment"
        }
    ],
    "sg:phone":"+34 935 70 17 82",
    "sg:postcode":"08100",
    "sg:province":"Barcelona",
    "sg:tags":[
        "locale",
        "de",
        "juego"
    ],
    "wof:name":"Jara Zamora Rebeca",
    "wof:placetype":"venue"
},
  "geometry": {"coordinates":[2.2188849449,41.5441627502],"type":"Point"}
}