{
  "type": "Feature",
  "properties": {
    "iso:country":"ES",
    "sg:address":"Avda Galicia, 51",
    "sg:city":"Porri\u00f1o",
    "sg:orig_category":"Fabricaci\u00d3n De Muebles",
    "sg:phone":"+34 986 33 21 87",
    "sg:postcode":"36400",
    "sg:province":"Pontevedra",
    "wof:name":"Porfirio Gonzalez S.l.",
    "wof:placetype":"venue"
},
  "geometry": {"coordinates":[-8.6203079224,42.1651535034],"type":"Point"}
}