{
  "type": "Feature",
  "properties": {
    "iso:country":"ES",
    "sg:address":"Carrer de Barcelona, 49",
    "sg:city":"Mataro",
    "sg:orig_category":"Marroquiner\u00cda (confecci\u00d3n)",
    "sg:phone":"+34 937 90 30 54",
    "sg:postcode":"08301",
    "sg:province":"Barcelona",
    "wof:name":"Ruz Torres Francisco",
    "wof:placetype":"venue"
},
  "geometry": {"coordinates":[2.4464929104,41.5390090942],"type":"Point"}
}