{
  "type": "Feature",
  "properties": {
    "addr:full":"Calle de Felix Valverde Lillo, 17 Merida Badajoz 06800",
    "addr:housenumber":"17",
    "addr:postcode":"06800",
    "addr:street":"Calle De Felix Valverde Lillo",
    "iso:country":"ES",
    "sg:address":"Calle de Felix Valverde Lillo, 17",
    "sg:city":"Merida",
    "sg:orig_category":"Procuradores",
    "sg:phone":"+34 924 31 22 62",
    "sg:postcode":"06800",
    "sg:province":"Badajoz",
    "wof:name":"Perianes Carrasco Luis",
    "wof:placetype":"venue"
},
  "geometry": {"coordinates":[-6.3448896408,38.9177322388],"type":"Point"}
}