{
  "type": "Feature",
  "properties": {
    "addr:full":"Calle de Polvoranca, 50 Alcorcon Madrid 28921",
    "addr:housenumber":"50",
    "addr:postcode":"28921",
    "addr:street":"Calle De Polvoranca",
    "iso:country":"ES",
    "sg:address":"Calle de Polvoranca, 50",
    "sg:city":"Alcorcon",
    "sg:orig_category":"Muebles, Minoristas",
    "sg:phone":"+34 916 43 70 58",
    "sg:postcode":"28921",
    "sg:province":"Madrid",
    "wof:name":"Cruz Alvarez Agustin",
    "wof:placetype":"venue"
},
  "geometry": {"coordinates":[-3.823579073,40.3446006775],"type":"Point"}
}