{
  "type": "Feature",
  "properties": {
    "iso:country":"ES",
    "sg:address":"Almda S Anton, 33",
    "sg:city":"Cartagena",
    "sg:orig_category":"Seguridad En El Trabajo Y Prevenci\u00d3n De Riesgos Laborales",
    "sg:phone":"+34 968 33 01 99",
    "sg:postcode":"30205",
    "sg:province":"Murcia",
    "wof:name":"Clipresal S.l.",
    "wof:placetype":"venue"
},
  "geometry": {"coordinates":[-0.994148016,37.6115646362],"type":"Point"}
}