{
  "type": "Feature",
  "properties": {
    "addr:full":"Cra Piera, 2 Martorell Barcelona 08760",
    "addr:housenumber":"2",
    "addr:postcode":"08760",
    "addr:street":"Piera",
    "iso:country":"ES",
    "sg:address":"Cra Piera, 2",
    "sg:city":"Martorell",
    "sg:orig_category":"Fabricaci\u00d3n De Harinas, S\u00c9molas, Productos De Elaboraci\u00d3n Del Grano",
    "sg:phone":"+34 937 75 03 68",
    "sg:postcode":"08760",
    "sg:province":"Barcelona",
    "wof:name":"Antonia Vila S. A.",
    "wof:placetype":"venue"
},
  "geometry": {"coordinates":[1.9245824814,41.4787902832],"type":"Point"}
}