{
  "type": "Feature",
  "properties": {
    "iso:country":"ES",
    "sg:address":"Pg Sunyer, 25",
    "sg:city":"Reus",
    "sg:orig_category":"Inmobiliaria (agencias)",
    "sg:phone":"+34 977 32 07 98",
    "sg:postcode":"43202",
    "sg:province":"Tarragona",
    "wof:name":"Aragones Vidal Cecilia",
    "wof:placetype":"venue"
},
  "geometry": {"coordinates":[1.1019895077,41.1558036804],"type":"Point"}
}