{
  "type": "Feature",
  "properties": {
    "iso:country":"ES",
    "sg:address":"Luga Cortijo El, 2",
    "sg:city":"Corredoria",
    "sg:orig_category":"Transportes Por Carretera: Lotes Completos, Mercanc\u00cdas Diversas",
    "sg:phone":"+34 985 11 56 71",
    "sg:postcode":"33011",
    "sg:province":"Asturias",
    "wof:name":"Castro Alonso Jose",
    "wof:placetype":"venue"
},
  "geometry": {"coordinates":[-5.8311891556,43.3788986206],"type":"Point"}
}