{
  "type": "Feature",
  "properties": {
    "iso:country":"ES",
    "sg:address":"Calle de Pablo Coso Calero, 104",
    "sg:city":"Bormujos",
    "sg:orig_category":"Maquinaria Para Industrias Diversas",
    "sg:phone":"+34 955 72 33 63",
    "sg:postcode":"41930",
    "sg:province":"Sevilla",
    "wof:name":"Aljarafe Medio Ambiente S.l.",
    "wof:placetype":"venue"
},
  "geometry": {"coordinates":[-6.0755939484,37.3703651428],"type":"Point"}
}