{
  "type": "Feature",
  "properties": {
    "iso:country":"ES",
    "sg:address":"Calle de Almirante Bonifaz, 2",
    "sg:city":"S. Vicente Barquera",
    "sg:orig_category":"Peluquer\u00cdas, Peluquer\u00cda Mixta",
    "sg:phone":"+34 942 71 24 09",
    "sg:postcode":"39540",
    "sg:province":"Cantabria",
    "wof:name":"Arruzas Russell Ana Maria",
    "wof:placetype":"venue"
},
  "geometry": {"coordinates":[-4.0722279549,43.341545105],"type":"Point"}
}