{
  "type": "Feature",
  "properties": {
    "iso:country":"ES",
    "sg:address":"Carr Floridablanca, 31",
    "sg:city":"Badalona",
    "sg:orig_category":"Centros Comerciales Y Grandes Tiendas",
    "sg:phone":"+34 933 88 71 55",
    "sg:postcode":"08914",
    "sg:province":"Barcelona",
    "wof:name":"Merlos Gea Juan",
    "wof:placetype":"venue"
},
  "geometry": {"coordinates":[2.2247889042,41.4404907227],"type":"Point"}
}