{
  "type": "Feature",
  "properties": {
    "addr:full":"Calle de Era Honda, S/n Alcala Henares Madrid 28803",
    "addr:housenumber":"s / n",
    "addr:postcode":"28803",
    "addr:street":"Calle De Era Honda",
    "iso:country":"ES",
    "sg:address":"Calle de Era Honda, S/n",
    "sg:city":"Alcala Henares",
    "sg:orig_category":"Comercio De Piezas De Recambio Y De Accesorios De Veh\u00cdculos, Veh\u00cdculos Industriales",
    "sg:phone":"+34 918 89 21 17",
    "sg:postcode":"28803",
    "sg:province":"Madrid",
    "wof:name":"Repuestos Hermanos Cantero S.l.",
    "wof:placetype":"venue"
},
  "geometry": {"coordinates":[-3.3739840984,40.476890564],"type":"Point"}
}