{
  "type": "Feature",
  "properties": {
    "addr:full":"Rua Carballo (o), 2 Taboada Lugo 27550",
    "addr:housenumber":"2",
    "addr:postcode":"27550",
    "addr:street":"Rua Carballo O",
    "iso:country":"ES",
    "sg:address":"Rua Carballo (o), 2",
    "sg:city":"Taboada",
    "sg:orig_category":"Zapatos (al Por Menor)",
    "sg:phone":"+34 982 46 50 96",
    "sg:postcode":"27550",
    "sg:province":"Lugo",
    "wof:name":"Ansoar Abelairas Isabel",
    "wof:placetype":"venue"
},
  "geometry": {"coordinates":[-7.762752533,42.714931488],"type":"Point"}
}