{
  "type": "Feature",
  "properties": {
    "iso:country":"ES",
    "sg:address":"Av Aiguera, 7",
    "sg:city":"Benidorm",
    "sg:orig_category":"Procuradores",
    "sg:phone":"+34 965 86 26 03",
    "sg:postcode":"03500",
    "sg:province":"Alicante",
    "wof:name":"Bautista Diez De La Lastra Angel",
    "wof:placetype":"venue"
},
  "geometry": {"coordinates":[-0.1743289977,38.5408058167],"type":"Point"}
}