{
  "type": "Feature",
  "properties": {
    "iso:country":"ES",
    "sg:address":"Calle de Medina Del Campo, S/n",
    "sg:city":"Madrid",
    "sg:orig_category":"Chapister\u00cda",
    "sg:phone":"+34 915 09 37 68",
    "sg:postcode":"28024",
    "sg:province":"Madrid",
    "wof:name":"Perez Rey Juan Jose",
    "wof:placetype":"venue"
},
  "geometry": {"coordinates":[-3.7886838913,40.3796386719],"type":"Point"}
}