{
  "type": "Feature",
  "properties": {
    "addr:full":"Calle de Periodista Llorente, 2 Valencia Valencia 46009",
    "addr:housenumber":"2",
    "addr:postcode":"46009",
    "addr:street":"Calle De Periodista Llorente",
    "iso:country":"ES",
    "sg:address":"Calle de Periodista Llorente, 2",
    "sg:city":"Valencia",
    "sg:orig_category":"Pescader\u00cdas (al Por Menor)",
    "sg:phone":"+34 963 47 93 71",
    "sg:postcode":"46009",
    "sg:province":"Valencia",
    "wof:name":"Albert Ballester Maria Desamparados",
    "wof:placetype":"venue"
},
  "geometry": {"coordinates":[-0.3820092976,39.4841194153],"type":"Point"}
}