{
  "type": "Feature",
  "properties": {
    "addr:full":"Carr Prim, 18 Badalona Barcelona 08911",
    "addr:housenumber":"18",
    "addr:postcode":"08911",
    "addr:street":"Carr Prim",
    "iso:country":"ES",
    "sg:address":"Carr Prim, 18",
    "sg:city":"Badalona",
    "sg:orig_category":"Ense\u00d1ante, Direcci\u00d3n",
    "sg:phone":"+34 933 84 07 52",
    "sg:postcode":"08911",
    "sg:province":"Barcelona",
    "wof:name":"Vives Pedros Carmela",
    "wof:placetype":"venue"
},
  "geometry": {"coordinates":[2.2494134903,41.4540367126],"type":"Point"}
}