{
  "type": "Feature",
  "properties": {
    "addr:full":"Calle de Emigrantes (los), 4 Barrios C\u00e1diz 11370",
    "addr:postcode":"11370",
    "addr:street":"Calle De Emigrantes Los;Barrios Ca\u0301Diz",
    "iso:country":"ES",
    "sg:address":"Calle de Emigrantes (los), 4",
    "sg:city":"Barrios",
    "sg:orig_category":"Contenedores (mercanc\u00cdas)",
    "sg:phone":"+34 956 62 24 64",
    "sg:postcode":"11370",
    "sg:province":"C\u00e1diz",
    "wof:name":"Mu\u00f1oz Mu\u00f1oz Andres",
    "wof:placetype":"venue"
},
  "geometry": {"coordinates":[-5.4934859276,36.1835021973],"type":"Point"}
}