{
  "type": "Feature",
  "properties": {
    "iso:country":"ES",
    "sg:address":"G.v. Corts Catalanes, 608",
    "sg:city":"Barcelona",
    "sg:orig_category":"Inmobiliaria (agencias)",
    "sg:phone":"+34 933 42 54 50",
    "sg:postcode":"08007",
    "sg:province":"Barcelona",
    "wof:name":"Plusvalia Sl",
    "wof:placetype":"venue"
},
  "geometry": {"coordinates":[2.1659860611,41.3872871399],"type":"Point"}
}