{
  "type": "Feature",
  "properties": {
    "iso:country":"ES",
    "sg:address":"Calle de Virgen De Los Angeles, 49",
    "sg:city":"Javea",
    "sg:orig_category":"Arreglo, Reparaci\u00d3n, Piezas Sueltas De Televisi\u00d3n, V\u00cddeo, Hi",
    "sg:phone":"+34 965 79 58 09",
    "sg:postcode":"03730",
    "sg:province":"Alicante",
    "wof:name":"Rodriguez Rodriguez Angel",
    "wof:placetype":"venue"
},
  "geometry": {"coordinates":[0.161740005,38.7922401428],"type":"Point"}
}