{
  "type": "Feature",
  "properties": {
    "iso:country":"ES",
    "sg:address":"Avda Camara De La Industria, 23",
    "sg:city":"Mostoles",
    "sg:orig_category":"Reparaciones Y Remolcado De Veh\u00cdculos",
    "sg:phone":"+34 916 46 97 50",
    "sg:postcode":"28938",
    "sg:province":"Madrid",
    "wof:name":"Gruas Y Talleres La Pista S.l.",
    "wof:placetype":"venue"
},
  "geometry": {"coordinates":[-3.8746030331,40.3095779419],"type":"Point"}
}