{
  "type": "Feature",
  "properties": {
    "iso:country":"ES",
    "sg:address":"Calle de Foso, 5",
    "sg:city":"Alburquerque",
    "sg:orig_category":"Mec\u00c1nico Del Autom\u00d3vil",
    "sg:phone":"+34 924 40 03 64",
    "sg:postcode":"06510",
    "sg:province":"Badajoz",
    "wof:name":"Correa Chaparro Fernando",
    "wof:placetype":"venue"
},
  "geometry": {"coordinates":[-7.0059947968,39.2234420776],"type":"Point"}
}