{
  "type": "Feature",
  "properties": {
    "addr:full":"Vallehermoso, 87 Madrid Madrid 28003",
    "addr:housenumber":"87",
    "addr:postcode":"madrid;28003",
    "addr:street":"Vallehermoso",
    "iso:country":"ES",
    "sg:address":"Vallehermoso, 87",
    "sg:city":"Madrid",
    "sg:orig_category":"Electrodom\u00c9sticos (fabricaci\u00d3n, Al Por Mayor)",
    "sg:phone":"+34 915 34 47 91",
    "sg:postcode":"28003",
    "sg:province":"Madrid",
    "wof:name":"T-systems Itc Services Espa\u00d1a S.a.",
    "wof:placetype":"venue"
},
  "geometry": {"coordinates":[-3.708327055,40.4395980835],"type":"Point"}
}