{
  "type": "Feature",
  "properties": {
    "iso:country":"ES",
    "sg:address":"Carrer de Sant Francesc, 1",
    "sg:city":"Sitges",
    "sg:orig_category":"Bisuter\u00cda, Joyer\u00cda, Relojer\u00cda (al Por Menor)",
    "sg:phone":"+34 938 94 64 95",
    "sg:postcode":"08870",
    "sg:province":"Barcelona",
    "wof:name":"Roviralta Joiers S.c.p.",
    "wof:placetype":"venue"
},
  "geometry": {"coordinates":[1.809218049,41.2365722656],"type":"Point"}
}