{
  "type": "Feature",
  "properties": {
    "iso:country":"ES",
    "sg:address":"Toribio Etxebarria Kalea, 8",
    "sg:city":"Eibar",
    "sg:orig_category":"Asociaciones, Organismos Culturales Y Socioeducativos",
    "sg:phone":"+34 943 20 71 67",
    "sg:postcode":"20600",
    "sg:province":"Guip\u00f9zcoa",
    "wof:name":"Sociedad Cultural Recreativa Itxulambru",
    "wof:placetype":"venue"
},
  "geometry": {"coordinates":[-2.4724390507,43.1846961975],"type":"Point"}
}