{
  "type": "Feature",
  "properties": {
    "iso:country":"ES",
    "sg:address":"Atv Madrid-toledo, Km. 0032,5",
    "sg:city":"Illescas",
    "sg:orig_category":"Metalurgia",
    "sg:phone":"+34 925 54 08 74",
    "sg:postcode":"45200",
    "sg:province":"Toledo",
    "sg:website":"www.sc-herrajes.com",
    "wof:name":"Sistemas Y Complementos De Herrajes S.l.",
    "wof:placetype":"venue"
},
  "geometry": {"coordinates":[-3.8458640575,40.1230163574],"type":"Point"}
}