{
  "type": "Feature",
  "properties": {
    "iso:country":"ES",
    "sg:address":"Ctra Benzu, S/n",
    "sg:city":"Benzu",
    "sg:orig_category":"Promotores Constructores",
    "sg:phone":"+34 956 52 00 33",
    "sg:postcode":"51004",
    "sg:province":"Ceuta",
    "wof:name":"Corsan Corvian S.a.",
    "wof:placetype":"venue"
},
  "geometry": {"coordinates":[-5.3728599548,35.9160118103],"type":"Point"}
}