{
  "type": "Feature",
  "properties": {
    "iso:country":"ES",
    "sg:address":"Ctra S. Juan-rabida, Km. 0004,8",
    "sg:city":"Moguer",
    "sg:orig_category":"Semiller\u00cdas",
    "sg:phone":"+34 959 37 00 66",
    "sg:postcode":"21800",
    "sg:province":"Huelva",
    "wof:name":"Alfaro Olivares Manuel",
    "wof:placetype":"venue"
},
  "geometry": {"coordinates":[-6.8918390274,37.2244300842],"type":"Point"}
}