{
  "type": "Feature",
  "properties": {
    "addr:full":"Luga Poligono Industrial El Palmar, S/n Poligono Industrial El Palmar C\u00e1diz 11500",
    "addr:housenumber":"s / n",
    "addr:postcode":"11500",
    "addr:street":"Poligono Industrial El;Poligono Industrial",
    "iso:country":"ES",
    "sg:address":"Luga Poligono Industrial El Palmar, S/n",
    "sg:city":"Poligono Industrial El Palmar",
    "sg:orig_category":"Mudanzas",
    "sg:phone":"+34 956 54 00 41",
    "sg:postcode":"11500",
    "sg:province":"C\u00e1diz",
    "wof:name":"Mudanzas Vitosa S.a.",
    "wof:placetype":"venue"
},
  "geometry": {"coordinates":[-6.2197542191,36.6056632996],"type":"Point"}
}