{
  "type": "Feature",
  "properties": {
    "iso:country":"ES",
    "sg:address":"Calle de Monte Aya, 17",
    "sg:city":"Madrid",
    "sg:orig_category":"Peluquer\u00cdas, Peluquer\u00cda Mixta",
    "sg:phone":"+34 913 32 16 25",
    "sg:postcode":"28031",
    "sg:province":"Madrid",
    "wof:name":"Rumi Garcia Angel",
    "wof:placetype":"venue"
},
  "geometry": {"coordinates":[-3.6220009327,40.3775482178],"type":"Point"}
}