{
  "type": "Feature",
  "properties": {
    "addr:full":"Calle de Perez Galdos, 91 Arrecife Las Palmas 35500",
    "addr:housenumber":"91",
    "addr:postcode":"35500",
    "addr:street":"Calle De Perez Galdos",
    "iso:country":"ES",
    "sg:address":"Calle de Perez Galdos, 91",
    "sg:city":"Arrecife",
    "sg:orig_category":"Inmobiliaria (agencias)",
    "sg:phone":"+34 928 81 76 61",
    "sg:postcode":"35500",
    "sg:province":"Las Palmas",
    "sg:website":"www.inmobiliariacanarias.com",
    "wof:name":"Profira Canarias S.l.",
    "wof:placetype":"venue"
},
  "geometry": {"coordinates":[-13.5462932587,28.9648590088],"type":"Point"}
}