{
  "type": "Feature",
  "properties": {
    "iso:country":"ES",
    "sg:address":"Plaz Juan De Lima, 1",
    "sg:city":"Algeciras",
    "sg:orig_category":"Zapatos (al Por Menor)",
    "sg:phone":"+34 956 65 13 54",
    "sg:postcode":"11201",
    "sg:province":"C\u00e1diz",
    "wof:name":"Ordo\u00f1ez Gonzalez Antonio",
    "wof:placetype":"venue"
},
  "geometry": {"coordinates":[-5.4526491165,36.1276016235],"type":"Point"}
}