{
  "type": "Feature",
  "properties": {
    "iso:country":"ES",
    "sg:address":"Pl Fra Bernadi, 32",
    "sg:city":"Manlleu",
    "sg:orig_category":"Ingenier\u00cda, Centros De Estudios (diversos)",
    "sg:phone":"+34 938 51 13 08",
    "sg:postcode":"08560",
    "sg:province":"Barcelona",
    "wof:name":"Moyano Garcia Antonio",
    "wof:placetype":"venue"
},
  "geometry": {"coordinates":[2.2844669819,42.0004272461],"type":"Point"}
}