{
  "type": "Feature",
  "properties": {
    "addr:full":"Via Laietana, 24 Barcelona Barcelona 08003",
    "addr:housenumber":"24",
    "addr:postcode":"08003",
    "addr:street":"Via Laietana",
    "iso:country":"ES",
    "sg:address":"Via Laietana, 24",
    "sg:city":"Barcelona",
    "sg:orig_category":"Abogados",
    "sg:phone":"+34 933 10 32 19",
    "sg:postcode":"08003",
    "sg:province":"Barcelona",
    "wof:name":"De Dios Garrido Julian Carlos",
    "wof:placetype":"venue"
},
  "geometry": {"coordinates":[2.1784529686,41.38438797],"type":"Point"}
}