{
  "type": "Feature",
  "properties": {
    "iso:country":"ES",
    "sg:address":"Calle de Fray Luis De Leon, 4",
    "sg:city":"Valladolid",
    "sg:orig_category":"Internados & Ense\u00d1anza Privada",
    "sg:phone":"+34 983 30 53 20",
    "sg:postcode":"47002",
    "sg:province":"Valladolid",
    "wof:name":"Gestion De Centros Ecamsol S.l.",
    "wof:placetype":"venue"
},
  "geometry": {"coordinates":[-4.7240948677,41.6514778137],"type":"Point"}
}