{
  "type": "Feature",
  "properties": {
    "iso:country":"ES",
    "sg:address":"Calle de Francisco Aritio, 156",
    "sg:city":"Guadalajara",
    "sg:classifiers":[
        {
            "category":"Professional",
            "subcategory":"Business Services",
            "type":"Services"
        }
    ],
    "sg:phone":"+34 949 20 22 14",
    "sg:postcode":"19004",
    "sg:province":"Guadalajara",
    "sg:tags":[
        "control",
        "asesor\u00cda",
        "organizaci\u00d3n",
        "la",
        "de",
        "gesti\u00d3n",
        "y"
    ],
    "wof:name":"Vismar Develops S.l.",
    "wof:placetype":"venue"
},
  "geometry": {"coordinates":[-3.1992549896,40.6235923767],"type":"Point"}
}