{
  "type": "Feature",
  "properties": {
    "iso:country":"ES",
    "sg:address":"Calle de Leon, 3",
    "sg:city":"Valladolid",
    "sg:orig_category":"Electricidad: Instalaciones Industriales",
    "sg:phone":"+34 983 37 57 16",
    "sg:postcode":"47003",
    "sg:province":"Valladolid",
    "wof:name":"Electricidad Cernuda S.l.",
    "wof:placetype":"venue"
},
  "geometry": {"coordinates":[-4.7266449928,41.6556053162],"type":"Point"}
}