{
  "type": "Feature",
  "properties": {
    "iso:country":"ES",
    "sg:address":"Avda Porta Do Sol, 74",
    "sg:city":"Ribeira",
    "sg:orig_category":"Estudios Y Construcci\u00d3n De Acuarios Y Viveros",
    "sg:phone":"+34 986 31 55 54",
    "sg:postcode":"36955",
    "sg:province":"Pontevedra",
    "wof:name":"Asociacion De Productores Mejilloneros Rianosa",
    "wof:placetype":"venue"
},
  "geometry": {"coordinates":[-8.7234191895,42.2874412537],"type":"Point"}
}