{
  "type": "Feature",
  "properties": {
    "addr:full":"Calle de Recoletos, 10 Madrid Madrid 28001",
    "addr:housenumber":"10",
    "addr:postcode":"madrid;28001",
    "addr:street":"Calle De Recoletos",
    "iso:country":"ES",
    "sg:address":"Calle de Recoletos, 10",
    "sg:city":"Madrid",
    "sg:orig_category":"Asesor\u00cda Sobre Comunicaci\u00d3n De Empresas",
    "sg:phone":"+34 914 31 45 10",
    "sg:postcode":"28001",
    "sg:province":"Madrid",
    "wof:name":"Bernina Advisors S.l.",
    "wof:placetype":"venue"
},
  "geometry": {"coordinates":[-3.6904609203,40.4218711853],"type":"Point"}
}