{
  "type": "Feature",
  "properties": {
    "addr:full":"Calle de Jardines, 14 Linea De La Concepcion C\u00e1diz 11300",
    "addr:housenumber":"14",
    "addr:postcode":"11300",
    "addr:street":"Calle De Jardines;Ca\u0301Diz",
    "iso:country":"ES",
    "sg:address":"Calle de Jardines, 14",
    "sg:city":"Linea De La Concepcion",
    "sg:orig_category":"Art\u00cdculos De Regalo (al Por Menor)",
    "sg:phone":"+34 956 17 52 31",
    "sg:postcode":"11300",
    "sg:province":"C\u00e1diz",
    "wof:name":"Bazar Jardines S.l.u.",
    "wof:placetype":"venue"
},
  "geometry": {"coordinates":[-5.3486862183,36.1621627808],"type":"Point"}
}