{
  "type": "Feature",
  "properties": {
    "iso:country":"ES",
    "sg:address":"Calle de Angosta Del Carmen, 3",
    "sg:city":"Malaga",
    "sg:orig_category":"Edici\u00d3n De Diarios, Revistas, Boletines",
    "sg:phone":"+34 952 32 64 17",
    "sg:postcode":"29002",
    "sg:province":"M\u00e1laga",
    "sg:website":"www.edisurmultimedia.com",
    "wof:name":"Formas Ediciones Profesionales S. L.",
    "wof:placetype":"venue"
},
  "geometry": {"coordinates":[-4.4281010628,36.7152252197],"type":"Point"}
}