{
  "type": "Feature",
  "properties": {
    "addr:full":"Calle de Pe\u00d1uelas, 2 Madrid Madrid 28005",
    "addr:housenumber":"2",
    "addr:postcode":"28005",
    "addr:street":"Calle De Pen\u0303Uelas",
    "iso:country":"ES",
    "sg:address":"Calle de Pe\u00d1uelas, 2",
    "sg:city":"Madrid",
    "sg:orig_category":"Herboristas (al Por Menor)",
    "sg:phone":"+34 914 73 19 81",
    "sg:postcode":"28005",
    "sg:province":"Madrid",
    "wof:name":"Garcia Sanz Rosa Maria",
    "wof:placetype":"venue"
},
  "geometry": {"coordinates":[-3.7048790455,40.4040870667],"type":"Point"}
}