{
  "type": "Feature",
  "properties": {
    "addr:full":"Plaz Colon (de), 22 Cordoba C\u00f3rdoba 14001",
    "addr:postcode":"14001",
    "addr:street":"Co\u0301Rdoba",
    "iso:country":"ES",
    "sg:address":"Plaz Colon (de), 22",
    "sg:city":"Cordoba",
    "sg:orig_category":"Abogados",
    "sg:phone":"+34 957 48 70 29",
    "sg:postcode":"14001",
    "sg:province":"C\u00f3rdoba",
    "wof:name":"Tirado Tejedor Jose Miguel",
    "wof:placetype":"venue"
},
  "geometry": {"coordinates":[-4.7780199051,37.8912353516],"type":"Point"}
}