{
  "type": "Feature",
  "properties": {
    "iso:country":"ES",
    "sg:address":"Carrer de Extremadura, 8",
    "sg:city":"S. Joan Despi",
    "sg:orig_category":"Panader\u00cdas, Panader\u00cdas",
    "sg:phone":"+34 934 77 15 74",
    "sg:postcode":"08970",
    "sg:province":"Barcelona",
    "wof:name":"Guillem Esparraga Pedro",
    "wof:placetype":"venue"
},
  "geometry": {"coordinates":[2.0740931034,41.3691291809],"type":"Point"}
}