{
  "type": "Feature",
  "properties": {
    "addr:full":"Calle de Navas De Tolosa, S/n Priego Cordoba C\u00f3rdoba 14800",
    "addr:housenumber":"s / n",
    "addr:postcode":"14800",
    "addr:street":"Calle De Navas De Tolosa;Cordoba Co\u0301Rdoba",
    "iso:country":"ES",
    "sg:address":"Calle de Navas De Tolosa, S/n",
    "sg:city":"Priego Cordoba",
    "sg:orig_category":"Confecci\u00d3n (fabricaci\u00d3n, Al Por Mayor)",
    "sg:phone":"+34 957 70 16 19",
    "sg:postcode":"14800",
    "sg:province":"C\u00f3rdoba",
    "wof:name":"Bermudez Prados Juan",
    "wof:placetype":"venue"
},
  "geometry": {"coordinates":[-4.1931791306,37.433719635],"type":"Point"}
}