{
  "type": "Feature",
  "properties": {
    "addr:full":"Calle de Parque Ricardo Mur, 6 Casetas Zaragoza 50620",
    "addr:housenumber":"6",
    "addr:postcode":"50620",
    "addr:street":"Calle De Parque Ricardo Mur",
    "iso:country":"ES",
    "sg:address":"Calle de Parque Ricardo Mur, 6",
    "sg:city":"Casetas",
    "sg:orig_category":"Ingeniero",
    "sg:phone":"+34 976 77 10 42",
    "sg:postcode":"50620",
    "sg:province":"Zaragoza",
    "wof:name":"Semillas Mur S.l.",
    "wof:placetype":"venue"
},
  "geometry": {"coordinates":[-1.0303390026,41.7199440002],"type":"Point"}
}