{
  "type": "Feature",
  "properties": {
    "addr:full":"Carrer de General Josep Moragues, 29 Gava Barcelona 08850",
    "addr:housenumber":"29",
    "addr:postcode":"08850",
    "addr:street":"Carrer De General Josep Moragues",
    "iso:country":"ES",
    "sg:address":"Carrer de General Josep Moragues, 29",
    "sg:city":"Gava",
    "sg:orig_category":"Agencias Y Agentes Comerciales, Representantes",
    "sg:phone":"+34 936 38 42 88",
    "sg:postcode":"08850",
    "sg:province":"Barcelona",
    "wof:name":"Arruebo Petrus Veronica",
    "wof:placetype":"venue"
},
  "geometry": {"coordinates":[1.9930466413,41.298789978],"type":"Point"}
}