{
  "type": "Feature",
  "properties": {
    "iso:country":"ES",
    "sg:address":"Ctra Nal 332, S/n",
    "sg:city":"Vila Joiosa",
    "sg:orig_category":"Promotores Constructores",
    "sg:phone":"+34 965 89 24 49",
    "sg:postcode":"03570",
    "sg:province":"Alicante",
    "wof:name":"Cb Richard Ellis S.a.",
    "wof:placetype":"venue"
},
  "geometry": {"coordinates":[-0.2327190042,38.505821228],"type":"Point"}
}