{
  "type": "Feature",
  "properties": {
    "addr:full":"Plaz Agustin Bou, 4 Cullera Valencia 46400",
    "addr:housenumber":"4",
    "addr:postcode":"46400",
    "addr:street":"Agustin Bou",
    "iso:country":"ES",
    "sg:address":"Plaz Agustin Bou, 4",
    "sg:city":"Cullera",
    "sg:orig_category":"Bisuter\u00cda, Joyer\u00cda, Relojer\u00cda (al Por Menor)",
    "sg:phone":"+34 961 73 21 17",
    "sg:postcode":"46400",
    "sg:province":"Valencia",
    "wof:name":"Piqueras Vallet Mayra",
    "wof:placetype":"venue"
},
  "geometry": {"coordinates":[-0.2562240064,39.1653251648],"type":"Point"}
}