{
  "type": "Feature",
  "properties": {
    "iso:country":"ES",
    "sg:address":"Calle de Pozo, 7",
    "sg:city":"Puertollano",
    "sg:orig_category":"M\u00c9dicos: Estomatolog\u00cda",
    "sg:phone":"+34 926 44 10 61",
    "sg:postcode":"13500",
    "sg:province":"Ciudad Real",
    "wof:name":"Miguel Angel Lopez Cuadrado S.l.",
    "wof:placetype":"venue"
},
  "geometry": {"coordinates":[-4.1069698334,38.6903266907],"type":"Point"}
}