{
  "type": "Feature",
  "properties": {
    "addr:full":"Avda Jacinto Benavente, 18 Valencia Valencia 46005",
    "addr:housenumber":"18",
    "addr:postcode":"46005",
    "addr:street":"Avda Jacinto Benavente",
    "iso:country":"ES",
    "sg:address":"Avda Jacinto Benavente, 18",
    "sg:city":"Valencia",
    "sg:orig_category":"Cl\u00cdnicas M\u00c9dicas",
    "sg:phone":"+34 963 73 73 07",
    "sg:postcode":"46005",
    "sg:province":"Valencia",
    "wof:name":"Martin Gonzalez Victor",
    "wof:placetype":"venue"
},
  "geometry": {"coordinates":[-0.3627659976,39.4660224915],"type":"Point"}
}