{
  "type": "Feature",
  "properties": {
    "iso:country":"ES",
    "sg:address":"Calle de Elche De La Sierra, 44",
    "sg:city":"Puerto",
    "sg:orig_category":"Farmacias",
    "sg:phone":"+34 962 68 11 62",
    "sg:postcode":"46520",
    "sg:province":"Valencia",
    "wof:name":"Rosado Valdearcos Esteban Carlos",
    "wof:placetype":"venue"
},
  "geometry": {"coordinates":[-0.2276639938,39.6684799194],"type":"Point"}
}