{
  "type": "Feature",
  "properties": {
    "iso:country":"ES",
    "sg:address":"Calle de Canalejas, 13",
    "sg:city":"Palmas De Gran Canaria",
    "sg:orig_category":"Doctores En Medicina",
    "sg:phone":"+34 928 36 43 36",
    "sg:postcode":"35003",
    "sg:province":"Las Palmas",
    "wof:name":"Martinez Gomez Fermin",
    "wof:placetype":"venue"
},
  "geometry": {"coordinates":[-15.4198741913,28.1093196869],"type":"Point"}
}