{
  "type": "Feature",
  "properties": {
    "addr:full":"Calle de Marques De Zenete, 29 Valencia Valencia 46007",
    "addr:housenumber":"29",
    "addr:postcode":"46007",
    "addr:street":"Calle De Marques De Zenete",
    "iso:country":"ES",
    "sg:address":"Calle de Marques De Zenete, 29",
    "sg:city":"Valencia",
    "sg:orig_category":"Suministros Y Materiales Industriales",
    "sg:phone":"+34 963 10 71 50",
    "sg:postcode":"46007",
    "sg:province":"Valencia",
    "wof:name":"Permarin S.a.",
    "wof:placetype":"venue"
},
  "geometry": {"coordinates":[-0.3872280121,39.4642829895],"type":"Point"}
}