{
  "type": "Feature",
  "properties": {
    "addr:full":"Avda Menendez Pelayo, 38 Madrid Madrid 28007",
    "addr:housenumber":"38",
    "addr:postcode":"madrid;28007",
    "addr:street":"Avda Menendez Pelayo",
    "iso:country":"ES",
    "sg:address":"Avda Menendez Pelayo, 38",
    "sg:city":"Madrid",
    "sg:orig_category":"Administradores De Bienes Y Delegados De Comunidades De Propietarios",
    "sg:phone":"+34 915 51 98 71",
    "sg:postcode":"28007",
    "sg:province":"Madrid",
    "wof:name":"Mu\u00f1oz Jimenez Juan Carlos",
    "wof:placetype":"venue"
},
  "geometry": {"coordinates":[-3.6805810928,40.405090332],"type":"Point"}
}