{
  "type": "Feature",
  "properties": {
    "iso:country":"ES",
    "sg:address":"Carrer de Posada De Lluc, 8",
    "sg:city":"Palma",
    "sg:orig_category":"Fabrica, Negocio De Vidrieras, Productos Vidriados Y Espejos",
    "sg:phone":"+34 971 72 43 96",
    "sg:postcode":"07001",
    "sg:province":"Islas Baleares",
    "wof:name":"Rioja Palacios Olga",
    "wof:placetype":"venue"
},
  "geometry": {"coordinates":[2.6545379162,39.5694313049],"type":"Point"}
}