{
  "type": "Feature",
  "properties": {
    "addr:full":"Carrer de Hostal Del Pi, 4 Poligon Barcelones Barcelona 08630",
    "addr:housenumber":"4",
    "addr:postcode":"08630",
    "addr:street":"Carrer De Hostal Del Pi",
    "iso:country":"ES",
    "sg:address":"Carrer de Hostal Del Pi, 4",
    "sg:city":"Poligon Barcelones",
    "sg:orig_category":"Fabricaci\u00d3n De Muebles",
    "sg:phone":"+34 937 70 71 30",
    "sg:postcode":"08630",
    "sg:province":"Barcelona",
    "wof:name":"R.c. Sayez Mobiliari S.l.",
    "wof:placetype":"venue"
},
  "geometry": {"coordinates":[1.8992400169,41.5194091797],"type":"Point"}
}