{
  "type": "Feature",
  "properties": {
    "addr:full":"Avda Virgen De La Esperanza, 24 Sevilla Sevilla 41012",
    "addr:housenumber":"24",
    "addr:postcode":"41012",
    "addr:street":"Avda Virgen De La Esperanza",
    "iso:country":"ES",
    "sg:address":"Avda Virgen De La Esperanza, 24",
    "sg:city":"Sevilla",
    "sg:orig_category":"Audiovisuales (producci\u00d3n, Edici\u00d3n, Realizaci\u00d3n)",
    "sg:phone":"+34 954 24 07 83",
    "sg:postcode":"41012",
    "sg:province":"Sevilla",
    "wof:name":"Delgado Rodriguez-caso Isabel",
    "wof:placetype":"venue"
},
  "geometry": {"coordinates":[-5.9803647995,37.3490600586],"type":"Point"}
}