{
  "type": "Feature",
  "properties": {
    "addr:full":"Mar Menuda, 10 Tossa Mar Girona 17320",
    "addr:housenumber":"10",
    "addr:postcode":"17320",
    "addr:street":"Menuda",
    "iso:country":"ES",
    "sg:address":"Mar Menuda, 10",
    "sg:city":"Tossa Mar",
    "sg:orig_category":"Inmobiliaria (agencias)",
    "sg:phone":"+34 972 34 14 12",
    "sg:postcode":"17320",
    "sg:province":"Girona",
    "wof:name":"Casanovas Espel Jorge",
    "wof:placetype":"venue"
},
  "geometry": {"coordinates":[2.9298949242,41.7226753235],"type":"Point"}
}