{
  "type": "Feature",
  "properties": {
    "addr:full":"Calle de Limon, 32 Madrid Madrid 28015",
    "addr:housenumber":"32",
    "addr:postcode":"madrid;28015",
    "addr:street":"Calle De Limon",
    "iso:country":"ES",
    "sg:address":"Calle de Limon, 32",
    "sg:city":"Madrid",
    "sg:orig_category":"Molduras, Junquillos, Listones Y Molduras Perforadas",
    "sg:phone":"+34 915 42 54 23",
    "sg:postcode":"28015",
    "sg:province":"Madrid",
    "wof:name":"Ortega Iba\u00f1ez Jose Ramon",
    "wof:placetype":"venue"
},
  "geometry": {"coordinates":[-3.7100355625,40.4275360107],"type":"Point"}
}