{
  "type": "Feature",
  "properties": {
    "iso:country":"ES",
    "sg:address":"Calle de Mayor, 31",
    "sg:city":"Puente Tocinos",
    "sg:orig_category":"Decoraci\u00d3n: Instalaci\u00d3n Y Talleres",
    "sg:phone":"+34 968 23 06 82",
    "sg:postcode":"30006",
    "sg:province":"Murcia",
    "sg:website":"abellanros.com",
    "wof:name":"Abellan Ros Jose",
    "wof:placetype":"venue"
},
  "geometry": {"coordinates":[-1.106627,37.991848],"type":"Point"}
}