{
  "type": "Feature",
  "properties": {
    "iso:country":"ES",
    "sg:address":"Calle de Virgen De Las Vi\u00d1as, 16",
    "sg:city":"Madrid",
    "sg:classifiers":[
        {
            "category":"Autos & Motor Vehicles",
            "subcategory":"Automobile Sales",
            "type":"Retail Goods"
        }
    ],
    "sg:phone":"+34 913 31 75 59",
    "sg:postcode":"28031",
    "sg:province":"Madrid",
    "wof:name":"Autoescuela Santa Eugenia S.l.",
    "wof:placetype":"venue"
},
  "geometry": {"coordinates":[-3.6077256203,40.3807144165],"type":"Point"}
}