{
  "type": "Feature",
  "properties": {
    "addr:full":"Ctra Huesca, Km. 0515,5 Villanueva Gallego Zaragoza 50830",
    "addr:postcode":"50830",
    "addr:street":"Ctra Huesca Km. 0515,5",
    "iso:country":"ES",
    "sg:address":"Ctra Huesca, Km. 0515,5",
    "sg:city":"Villanueva Gallego",
    "sg:orig_category":"Hormigonados",
    "sg:phone":"+34 976 50 02 53",
    "sg:postcode":"50830",
    "sg:province":"Zaragoza",
    "wof:name":"Beton Catalan S.a.",
    "wof:placetype":"venue"
},
  "geometry": {"coordinates":[-0.8222020268,41.7705192566],"type":"Point"}
}