{
  "type": "Feature",
  "properties": {
    "addr:full":"Av Valencia, 2 Gandesa Tarragona 43780",
    "addr:housenumber":"2",
    "addr:postcode":"43780",
    "addr:street":"Av Valencia",
    "iso:country":"ES",
    "sg:address":"Av Valencia, 2",
    "sg:city":"Gandesa",
    "sg:orig_category":"Partidos Pol\u00cdticos",
    "sg:phone":"+34 977 42 08 66",
    "sg:postcode":"43780",
    "sg:province":"Tarragona",
    "wof:name":"Convergencia Democratica De Catalunya",
    "wof:placetype":"venue"
},
  "geometry": {"coordinates":[0.4386210144,41.0537414551],"type":"Point"}
}