{
  "type": "Feature",
  "properties": {
    "addr:full":"I\u00f1igo Arista, 14 Iru\u00f1a Navarra 31007",
    "addr:housenumber":"14",
    "addr:postcode":"31007",
    "addr:street":"Arista",
    "iso:country":"ES",
    "sg:address":"I\u00f1igo Arista, 14",
    "sg:city":"Iru\u00f1a",
    "sg:orig_category":"Peluquer\u00cdas, Peluquer\u00cda Mixta",
    "sg:phone":"+34 948 27 03 62",
    "sg:postcode":"31007",
    "sg:province":"Navarra",
    "wof:name":"Sebastian Martinez Maria Jose",
    "wof:placetype":"venue"
},
  "geometry": {"coordinates":[-1.6540859938,42.8072395325],"type":"Point"}
}