{
  "type": "Feature",
  "properties": {
    "iso:country":"ES",
    "sg:address":"Calle de Ponce De Leon, 7",
    "sg:city":"Santa Cruz De Tenerife",
    "sg:orig_category":"Telas Y Sedas (al Por Menor)",
    "sg:phone":"+34 922 65 28 16",
    "sg:postcode":"38010",
    "sg:province":"Santa Cruz De Tenerife",
    "wof:name":"Almacenes Abril S.l.",
    "wof:placetype":"venue"
},
  "geometry": {"coordinates":[-16.2817306519,28.452495575],"type":"Point"}
}