{
  "type": "Feature",
  "properties": {
    "iso:country":"ES",
    "sg:address":"Carr Puig Campana (el), 22",
    "sg:city":"Almafra",
    "sg:orig_category":"Confecci\u00d3n De Zapatos",
    "sg:phone":"+34 966 95 29 39",
    "sg:postcode":"03610",
    "sg:province":"Alicante",
    "wof:name":"Andrea Latina Sl",
    "wof:placetype":"venue"
},
  "geometry": {"coordinates":[-0.4810059965,38.3452033997],"type":"Point"}
}