{
  "type": "Feature",
  "properties": {
    "iso:country":"ES",
    "sg:address":"Rua Cardenal Rodrigo De Castro, 29",
    "sg:city":"Monforte De Lemos",
    "sg:orig_category":"Bisuter\u00cda, Joyer\u00cda, Relojer\u00cda (al Por Menor)",
    "sg:phone":"+34 982 40 17 92",
    "sg:postcode":"27420",
    "sg:province":"Lugo",
    "wof:name":"Perez Rodriguez Sabino",
    "wof:placetype":"venue"
},
  "geometry": {"coordinates":[-7.5264849663,42.496887207],"type":"Point"}
}