{
  "type": "Feature",
  "properties": {
    "addr:full":"Rua Eidos, 47 Redondela Pontevedra 36800",
    "addr:housenumber":"47",
    "addr:postcode":"36800",
    "addr:street":"Rua Eidos",
    "iso:country":"ES",
    "sg:address":"Rua Eidos, 47",
    "sg:city":"Redondela",
    "sg:orig_category":"Estilistas Y Estudios De Estilo De Corte Y Confecci\u00d3n",
    "sg:phone":"+34 986 40 80 24",
    "sg:postcode":"36800",
    "sg:province":"Pontevedra",
    "wof:name":"Gallega Internacional S.a.",
    "wof:placetype":"venue"
},
  "geometry": {"coordinates":[-8.6022481918,42.2854957581],"type":"Point"}
}