{
  "type": "Feature",
  "properties": {
    "addr:full":"Carrer de Cabrera, 17 Vic Barcelona 08500",
    "addr:housenumber":"17",
    "addr:postcode":"08500",
    "addr:street":"Carrer De Cabrera",
    "iso:country":"ES",
    "sg:address":"Carrer de Cabrera, 17",
    "sg:city":"Vic",
    "sg:orig_category":"Peluqueros: De Se\u00d1oras",
    "sg:phone":"+34 938 89 00 77",
    "sg:postcode":"08500",
    "sg:province":"Barcelona",
    "wof:name":"Pujols Urgelles Pilar",
    "wof:placetype":"venue"
},
  "geometry": {"coordinates":[2.2619600296,41.9322052002],"type":"Point"}
}