{
  "type": "Feature",
  "properties": {
    "addr:full":"Carrer de Finestrat, 18 Benidorm Alicante 03500",
    "addr:housenumber":"18",
    "addr:postcode":"03500",
    "addr:street":"Carrer De Finestrat",
    "iso:country":"ES",
    "sg:address":"Carrer de Finestrat, 18",
    "sg:city":"Benidorm",
    "sg:orig_category":"Lavado, Limpieza De Veh\u00cdculos",
    "sg:phone":"+34 966 80 11 51",
    "sg:postcode":"03500",
    "sg:province":"Alicante",
    "wof:name":"Finestrat 2000 Centro Lavado La Marina",
    "wof:placetype":"venue"
},
  "geometry": {"coordinates":[-0.1739459932,38.5365180969],"type":"Point"}
}