{
  "type": "Feature",
  "properties": {
    "addr:full":"Calle de Jardin, 15 Villarrobledo Albacete 02600",
    "addr:housenumber":"15",
    "addr:postcode":"02600",
    "addr:street":"Calle De Jardin",
    "iso:country":"ES",
    "sg:address":"Calle de Jardin, 15",
    "sg:city":"Villarrobledo",
    "sg:orig_category":"Adaptaciones, Acondicionamientos Especiales Para Veh\u00cdculos, Veh\u00cdculos Industriales",
    "sg:phone":"+34 967 14 67 75",
    "sg:postcode":"02600",
    "sg:province":"Albacete",
    "wof:name":"Perez Monje S.l.",
    "wof:placetype":"venue"
},
  "geometry": {"coordinates":[-2.5952889919,39.2624855042],"type":"Point"}
}