{
  "type": "Feature",
  "properties": {
    "addr:full":"Centro Comercial Bora-bora, S/n Los Cristianos Santa Cruz De Tenerife 38650",
    "addr:housenumber":"s / n",
    "addr:postcode":"38650",
    "iso:country":"ES",
    "sg:address":"Centro Comercial Bora-bora, S/n",
    "sg:city":"Los Cristianos",
    "sg:orig_category":"Bazares, Art\u00cdculos De Limpieza Y De Cocina (al Por Menor)",
    "sg:phone":"+34 922 79 13 51",
    "sg:postcode":"38650",
    "sg:province":"Santa Cruz De Tenerife",
    "wof:name":"Bhagu Gopwani Haresh",
    "wof:placetype":"venue"
},
  "geometry": {"coordinates":[-16.7228374481,28.0525436401],"type":"Point"}
}