{
  "type": "Feature",
  "properties": {
    "addr:full":"Calle de Pintor Escudero Espronceda, 14 Torrelavega Cantabria 39300",
    "addr:housenumber":"14",
    "addr:postcode":"39300",
    "addr:street":"Calle De Pintor Escudero Espronceda",
    "iso:country":"ES",
    "sg:address":"Calle de Pintor Escudero Espronceda, 14",
    "sg:city":"Torrelavega",
    "sg:orig_category":"M\u00c9dicos: Naturistas",
    "sg:phone":"+34 942 89 64 76",
    "sg:postcode":"39300",
    "sg:province":"Cantabria",
    "wof:name":"Teran De La Cruz Isidro",
    "wof:placetype":"venue"
},
  "geometry": {"coordinates":[-4.0506501198,43.3461112976],"type":"Point"}
}