{
  "type": "Feature",
  "properties": {
    "addr:full":"Plaz Puerta De Zamora, 4 Salamanca Salamanca 37005",
    "addr:housenumber":"4",
    "addr:postcode":"37005",
    "addr:street":"Puerta;Zamora",
    "iso:country":"ES",
    "sg:address":"Plaz Puerta De Zamora, 4",
    "sg:city":"Salamanca",
    "sg:orig_category":"Doctores En Medicina",
    "sg:phone":"+34 923 24 01 56",
    "sg:postcode":"37005",
    "sg:province":"Salamanca",
    "wof:name":"Garcia Vicente Manuel",
    "wof:placetype":"venue"
},
  "geometry": {"coordinates":[-5.6583042145,40.9937133789],"type":"Point"}
}