{
  "type": "Feature",
  "properties": {
    "addr:full":"Carrer de Baltasar Gracian, 3 Barcelona Barcelona 08016",
    "addr:housenumber":"3",
    "addr:postcode":"08016",
    "addr:street":"Carrer De Baltasar Gracian",
    "iso:country":"ES",
    "sg:address":"Carrer de Baltasar Gracian, 3",
    "sg:city":"Barcelona",
    "sg:orig_category":"Supermercados Y Hipermercados",
    "sg:phone":"+34 932 76 14 87",
    "sg:postcode":"08016",
    "sg:province":"Barcelona",
    "wof:name":"Supermercados Lopez Rodriguez S.l.",
    "wof:placetype":"venue"
},
  "geometry": {"coordinates":[2.1818480492,41.4400215149],"type":"Point"}
}