{
  "type": "Feature",
  "properties": {
    "iso:country":"ES",
    "sg:address":"Avda Maestros Espaderos, 4",
    "sg:city":"Toledo",
    "sg:orig_category":"Guarder\u00cdas",
    "sg:phone":"+34 925 22 86 74",
    "sg:postcode":"45005",
    "sg:province":"Toledo",
    "wof:name":"Parque Infantil El Saltamontes S.l.l.",
    "wof:placetype":"venue"
},
  "geometry": {"coordinates":[-4.0333709717,39.8684768677],"type":"Point"}
}