{
  "type": "Feature",
  "properties": {
    "iso:country":"ES",
    "sg:address":"Avda Salvador Allende, 14",
    "sg:city":"Abanilla",
    "sg:orig_category":"Promotores Constructores",
    "sg:phone":"+34 968 68 06 39",
    "sg:postcode":"30640",
    "sg:province":"Murcia",
    "wof:name":"Infraestructuras Del Sureste Infrasur S.l.",
    "wof:placetype":"venue"
},
  "geometry": {"coordinates":[-1.0384835005,38.2063484192],"type":"Point"}
}