{
  "type": "Feature",
  "properties": {
    "addr:full":"Villar De Abajo, 11 Tamon Asturias 33469",
    "addr:housenumber":"11",
    "addr:postcode":"33469",
    "addr:street":"Abajo;Asturias",
    "iso:country":"ES",
    "sg:address":"Villar De Abajo, 11",
    "sg:city":"Tamon",
    "sg:orig_category":"Poller\u00cda Y Caza (al Por Menor)",
    "sg:phone":"+34 985 50 54 18",
    "sg:postcode":"33469",
    "sg:province":"Asturias",
    "wof:name":"Avicola Carre\u00f1o S.l.",
    "wof:placetype":"venue"
},
  "geometry": {"coordinates":[-5.8119959831,43.5127182007],"type":"Point"}
}