{
  "type": "Feature",
  "properties": {
    "iso:country":"ES",
    "sg:address":"Carrer de Velazquez, 13",
    "sg:city":"Mataro",
    "sg:orig_category":"Instalaci\u00d3n, Reparaci\u00d3n De Calefacci\u00d3n El\u00c9ctrica",
    "sg:phone":"+34 937 98 32 84",
    "sg:postcode":"08302",
    "sg:province":"Barcelona",
    "wof:name":"Granes Fado Vicente",
    "wof:placetype":"venue"
},
  "geometry": {"coordinates":[2.4369111061,41.5391044617],"type":"Point"}
}