{
  "type": "Feature",
  "properties": {
    "iso:country":"ES",
    "sg:address":"Calle de Higueras, 61",
    "sg:city":"Madrid",
    "sg:orig_category":"Centros De Coordinaci\u00d3n",
    "sg:phone":"+34 914 70 00 01",
    "sg:postcode":"28047",
    "sg:province":"Madrid",
    "wof:name":"Gestoria Lucero Asesores De Empresa S.l.",
    "wof:placetype":"venue"
},
  "geometry": {"coordinates":[-3.7451210022,40.4032554626],"type":"Point"}
}