{
  "type": "Feature",
  "properties": {
    "addr:full":"Calle de Pasaman Alargunaren, 2 Pasai S. Pedro Guip\u00f9zcoa 20110",
    "addr:housenumber":"2",
    "addr:postcode":"20110",
    "addr:street":"Calle De Pasaman Alargunaren;Guipu\u0300Zcoa",
    "iso:country":"ES",
    "sg:address":"Calle de Pasaman Alargunaren, 2",
    "sg:city":"Pasai S. Pedro",
    "sg:orig_category":"Vinos Y Licores (venta Al Por Menor)",
    "sg:phone":"+34 943 39 01 58",
    "sg:postcode":"20110",
    "sg:province":"Guip\u00f9zcoa",
    "wof:name":"Garciandia Andueza Jose Maria",
    "wof:placetype":"venue"
},
  "geometry": {"coordinates":[-1.9259719849,43.3257904053],"type":"Point"}
}