{
  "type": "Feature",
  "properties": {
    "addr:full":"Atzeko Kalea, 26 O\u00f1ati Guip\u00f9zcoa 20560",
    "addr:housenumber":"26",
    "addr:postcode":"20560",
    "addr:street":"Atzeko Kalea;Guipu\u0300Zcoa",
    "iso:country":"ES",
    "sg:address":"Atzeko Kalea, 26",
    "sg:city":"O\u00f1ati",
    "sg:orig_category":"Caf\u00c9s, Bares, Cervecer\u00cdas",
    "sg:phone":"+34 943 78 35 53",
    "sg:postcode":"20560",
    "sg:province":"Guip\u00f9zcoa",
    "wof:name":"Miguel Angel Palacin I\u00f1urritegi",
    "wof:placetype":"venue"
},
  "geometry": {"coordinates":[-2.411413908,43.0313491821],"type":"Point"}
}