{
  "type": "Feature",
  "properties": {
    "addr:full":"Poli Poligono Industrial Amargacena, 13 Cordoba C\u00f3rdoba 14013",
    "addr:housenumber":"13",
    "addr:postcode":"14013",
    "addr:street":"Poligono Industrial Amargacena;Co\u0301Rdoba",
    "iso:country":"ES",
    "sg:address":"Poli Poligono Industrial Amargacena, 13",
    "sg:city":"Cordoba",
    "sg:orig_category":"Venta, Instalaci\u00d3n De Calefacci\u00d3n",
    "sg:phone":"+34 957 42 91 55",
    "sg:postcode":"14013",
    "sg:province":"C\u00f3rdoba",
    "wof:name":"Vertigas 2000 S.l",
    "wof:placetype":"venue"
},
  "geometry": {"coordinates":[-4.7784028053,37.8779411316],"type":"Point"}
}