{
  "type": "Feature",
  "properties": {
    "iso:country":"ES",
    "sg:address":"Major, 133",
    "sg:city":"Almacelles",
    "sg:orig_category":"Cr\u00cda De Animales",
    "sg:phone":"+34 973 74 01 89",
    "sg:postcode":"25100",
    "sg:province":"Lleida",
    "wof:name":"Pujol Sabate Francisco",
    "wof:placetype":"venue"
},
  "geometry": {"coordinates":[0.4432899952,41.7261390686],"type":"Point"}
}