{
  "type": "Feature",
  "properties": {
    "iso:country":"ES",
    "sg:address":"Carrer de Joan Batllori, 6",
    "sg:city":"Sant Feliu Llobregat",
    "sg:orig_category":"Restaurantes Para Recepciones, Banquetes, Conferencias",
    "sg:phone":"+34 936 66 11 94",
    "sg:postcode":"08980",
    "sg:province":"Barcelona",
    "wof:name":"Casino Sanfeliuense",
    "wof:placetype":"venue"
},
  "geometry": {"coordinates":[2.044424057,41.3815345764],"type":"Point"}
}