{
  "type": "Feature",
  "properties": {
    "addr:full":"Pol Ind Alberca, 1 La Nucia Alicante 03530",
    "addr:housenumber":"1",
    "addr:postcode":"03530",
    "addr:street":"Alberca",
    "iso:country":"ES",
    "sg:address":"Pol Ind Alberca, 1",
    "sg:city":"La Nucia",
    "sg:orig_category":"Centros De Coordinaci\u00d3n",
    "sg:phone":"+34 966 83 12 37",
    "sg:postcode":"03530",
    "sg:province":"Alicante",
    "sg:website":"www.bmb.es",
    "wof:name":"B M B Gestion Documental S.l.",
    "wof:placetype":"venue"
},
  "geometry": {"coordinates":[-0.1249789968,38.6157951355],"type":"Point"}
}