{
  "type": "Feature",
  "properties": {
    "addr:full":"Praz Porto Pesqueiro-lonxa, S/n Vigo Pontevedra 36202",
    "addr:housenumber":"s",
    "addr:postcode":"36202",
    "addr:street":"/ N",
    "iso:country":"ES",
    "sg:address":"Praz Porto Pesqueiro-lonxa, S/n",
    "sg:city":"Vigo",
    "sg:orig_category":"Distribuci\u00d3n De Petr\u00d3leo Y Derivados",
    "sg:phone":"+34 986 43 86 48",
    "sg:postcode":"36202",
    "sg:province":"Pontevedra",
    "wof:name":"J. B. Hermanos Dominguez S. L.",
    "wof:placetype":"venue"
},
  "geometry": {"coordinates":[-8.7320985794,42.2364654541],"type":"Point"}
}