{
  "type": "Feature",
  "properties": {
    "addr:full":"Calle de Atocha, 67 Madrid Madrid 28012",
    "addr:housenumber":"67",
    "addr:postcode":"madrid;28012",
    "addr:street":"Calle De Atocha",
    "iso:country":"ES",
    "sg:address":"Calle de Atocha, 67",
    "sg:city":"Madrid",
    "sg:orig_category":"Pod\u00d3logos: Pedicuros",
    "sg:phone":"+34 914 29 13 12",
    "sg:postcode":"28012",
    "sg:province":"Madrid",
    "wof:name":"Gomez Fontecha Lopez Ricardo",
    "wof:placetype":"venue"
},
  "geometry": {"coordinates":[-3.6990318298,40.4123382568],"type":"Point"}
}