{
  "type": "Feature",
  "properties": {
    "addr:full":"Av Ametlla De Mar, 2 Benidorm Alicante 03500",
    "addr:housenumber":"2",
    "addr:postcode":"03500",
    "addr:street":"Av Ametlla De Mar",
    "iso:country":"ES",
    "sg:address":"Av Ametlla De Mar, 2",
    "sg:city":"Benidorm",
    "sg:orig_category":"Iglesias Evang\u00c9licas",
    "sg:phone":"+34 966 80 92 01",
    "sg:postcode":"03500",
    "sg:province":"Alicante",
    "wof:name":"Iglesia Evangelica Holandesa De Benidorm",
    "wof:placetype":"venue"
},
  "geometry": {"coordinates":[-0.1743289977,38.5408058167],"type":"Point"}
}