{
  "type": "Feature",
  "properties": {
    "iso:country":"ES",
    "sg:address":"Carrer de Sant Antoni Maria Claret, 357",
    "sg:city":"Barcelona",
    "sg:orig_category":"Animales (al Por Menor)",
    "sg:phone":"+34 933 52 16 54",
    "sg:postcode":"08027",
    "sg:province":"Barcelona",
    "wof:name":"J.moral S.l.",
    "wof:placetype":"venue"
},
  "geometry": {"coordinates":[2.1870470047,41.4208068848],"type":"Point"}
}