{
  "type": "Feature",
  "properties": {
    "iso:country":"ES",
    "sg:address":"Calle de Guzman El Bueno, 70",
    "sg:city":"Madrid",
    "sg:orig_category":"Poller\u00cda Y Caza (al Por Menor)",
    "sg:phone":"+34 915 44 53 03",
    "sg:postcode":"28015",
    "sg:province":"Madrid",
    "wof:name":"Gomez Rodrigo Juan",
    "wof:placetype":"venue"
},
  "geometry": {"coordinates":[-3.7127480507,40.4383010864],"type":"Point"}
}