{
  "type": "Feature",
  "properties": {
    "iso:country":"ES",
    "sg:address":"Plaza De Gonzalez Fioris, 6",
    "sg:city":"Hervas",
    "sg:orig_category":"Oficinas De Turismo, Asociaciones De Iniciativa",
    "sg:phone":"+34 927 47 36 18",
    "sg:postcode":"10700",
    "sg:province":"C\u00e1ceres",
    "sg:website":"www.hervas.com",
    "wof:name":"Ayuntamiento De Hervas",
    "wof:placetype":"venue"
},
  "geometry": {"coordinates":[-5.863948822,40.2720451355],"type":"Point"}
}