{
  "type": "Feature",
  "properties": {
    "addr:full":"Carr Joan Llimona Gabarro, 39 Igualada Barcelona 08700",
    "addr:housenumber":"39",
    "addr:postcode":"08700",
    "addr:street":"Carr Joan Llimona Gabarro",
    "iso:country":"ES",
    "sg:address":"Carr Joan Llimona Gabarro, 39",
    "sg:city":"Igualada",
    "sg:orig_category":"Fabricaci\u00d3n De Su\u00c9ters Y Chalecos De Punto",
    "sg:phone":"+34 938 04 63 05",
    "sg:postcode":"08700",
    "sg:province":"Barcelona",
    "wof:name":"Bleumint S.l.",
    "wof:placetype":"venue"
},
  "geometry": {"coordinates":[1.6070040464,41.5818786621],"type":"Point"}
}