{
  "type": "Feature",
  "properties": {
    "iso:country":"ES",
    "sg:address":"Pl San Agatangelo, 11",
    "sg:city":"Elche",
    "sg:orig_category":"Abogados",
    "sg:phone":"+34 966 61 17 27",
    "sg:postcode":"03201",
    "sg:province":"Alicante",
    "wof:name":"Gonzalvez Valero Fernando",
    "wof:placetype":"venue"
},
  "geometry": {"coordinates":[-0.7069658041,38.2656898499],"type":"Point"}
}