{
  "type": "Feature",
  "properties": {
    "iso:country":"ES",
    "sg:address":"Avda Aragon (de), 37",
    "sg:city":"Teruel",
    "sg:orig_category":"Telas Y Sedas (al Por Menor)",
    "sg:phone":"+34 978 61 74 90",
    "sg:postcode":"44002",
    "sg:province":"Teruel",
    "wof:name":"Galindo Milian Joaquin",
    "wof:placetype":"venue"
},
  "geometry": {"coordinates":[-1.1057989597,40.3313484192],"type":"Point"}
}