{
  "type": "Feature",
  "properties": {
    "iso:country":"ES",
    "sg:address":"Calle de Adelfas Las, S/n",
    "sg:city":"Poligono Industrial De Arinaga",
    "sg:orig_category":"Comercio De Hierro",
    "sg:phone":"+34 928 18 26 25",
    "sg:postcode":"35118",
    "sg:province":"Las Palmas",
    "sg:website":"www.ronandez.com",
    "wof:name":"Ronandez S.a.",
    "wof:placetype":"venue"
},
  "geometry": {"coordinates":[-15.3927698135,27.8557987213],"type":"Point"}
}