{
  "type": "Feature",
  "properties": {
    "addr:full":"Calle de San Francisco, 14 Castro Urdiales Cantabria 39700",
    "addr:housenumber":"14",
    "addr:postcode":"39700",
    "addr:street":"Calle De San Francisco",
    "iso:country":"ES",
    "sg:address":"Calle de San Francisco, 14",
    "sg:city":"Castro Urdiales",
    "sg:orig_category":"Promotores Constructores",
    "sg:phone":"+34 942 86 13 04",
    "sg:postcode":"39700",
    "sg:province":"Cantabria",
    "wof:name":"Construcciones Echego S.l.",
    "wof:placetype":"venue"
},
  "geometry": {"coordinates":[-3.2200388908,43.3849563599],"type":"Point"}
}