{
  "type": "Feature",
  "properties": {
    "iso:country":"ES",
    "sg:address":"Calle de Claudio Coello, 62",
    "sg:city":"Tomelloso",
    "sg:orig_category":"Comercio De Piezas De Recambio Y De Accesorios De Veh\u00cdculos, Veh\u00cdculos Industriales",
    "sg:phone":"+34 926 50 18 70",
    "sg:postcode":"13700",
    "sg:province":"Ciudad Real",
    "wof:name":"Repuestos Royse S.l.",
    "wof:placetype":"venue"
},
  "geometry": {"coordinates":[-3.0257279873,39.1635322571],"type":"Point"}
}