{
  "type": "Feature",
  "properties": {
    "iso:country":"ES",
    "sg:address":"Plaz Espa\u00d1a, 3",
    "sg:city":"Alaquas",
    "sg:orig_category":"Sociedades, Compa\u00d1\u00cdas Aseguradoras",
    "sg:phone":"+34 961 98 60 03",
    "sg:postcode":"46970",
    "sg:province":"Valencia",
    "sg:website":"www.gestionseguros.com",
    "wof:name":"Correduria Tecnica De Seguros Gestion S.l.",
    "wof:placetype":"venue"
},
  "geometry": {"coordinates":[-0.4578439891,39.4546356201],"type":"Point"}
}