{
  "type": "Feature",
  "properties": {
    "addr:full":"Calle de Gavilanes (blq), 14 Madrid Madrid 28043",
    "addr:housenumber":"14",
    "addr:postcode":"madrid;28043",
    "addr:street":"Calle De Gavilanes Blq",
    "iso:country":"ES",
    "sg:address":"Calle de Gavilanes (blq), 14",
    "sg:city":"Madrid",
    "sg:orig_category":"Aguas (distribuci\u00d3n, Servicios)",
    "sg:phone":"+34 917 16 07 25",
    "sg:postcode":"28043",
    "sg:province":"Madrid",
    "sg:website":"www.aqualia.es",
    "wof:name":"Fomento De Construcciones Y Contratas S.a.",
    "wof:placetype":"venue"
},
  "geometry": {"coordinates":[-3.6471161842,40.4604415894],"type":"Point"}
}