{
  "type": "Feature",
  "properties": {
    "iso:country":"ES",
    "sg:address":"Calle de Santo Domingo, 21",
    "sg:city":"Alcazar S. Juan",
    "sg:orig_category":"Promotores Constructores",
    "sg:phone":"+34 926 54 02 84",
    "sg:postcode":"13600",
    "sg:province":"Ciudad Real",
    "wof:name":"Construcciones Quiralte E Hijos S.l.",
    "wof:placetype":"venue"
},
  "geometry": {"coordinates":[-3.2090539932,39.3879013062],"type":"Point"}
}