{
  "type": "Feature",
  "properties": {
    "addr:full":"Calle de San Isidro, 4 Peral Cuenca 16240",
    "addr:housenumber":"4",
    "addr:postcode":"16240",
    "addr:street":"Calle De San Isidro",
    "iso:country":"ES",
    "sg:address":"Calle de San Isidro, 4",
    "sg:city":"Peral",
    "sg:orig_category":"Plomeros",
    "sg:phone":"+34 969 33 94 29",
    "sg:postcode":"16240",
    "sg:province":"Cuenca",
    "wof:name":"Peralta Jimenez Salvador",
    "wof:placetype":"venue"
},
  "geometry": {"coordinates":[-1.8975419998,39.4971199036],"type":"Point"}
}