{
  "type": "Feature",
  "properties": {
    "iso:country":"ES",
    "sg:address":"Avda Marin, 24",
    "sg:city":"Estrada",
    "sg:orig_category":"M\u00c1rmoles, Granitos Y Piedras Naturales",
    "sg:phone":"+34 986 57 04 57",
    "sg:postcode":"36680",
    "sg:province":"Pontevedra",
    "wof:name":"Calvelo Rico Josefina",
    "wof:placetype":"venue"
},
  "geometry": {"coordinates":[-8.4975738525,42.685798645],"type":"Point"}
}