{
  "type": "Feature",
  "properties": {
    "iso:country":"ES",
    "sg:address":"Tiburzio Anitua Kalea, 7",
    "sg:city":"Eibar",
    "sg:orig_category":"Carnicer\u00cdas, Carnicer\u00cdas",
    "sg:phone":"+34 943 70 12 43",
    "sg:postcode":"20600",
    "sg:province":"Guip\u00f9zcoa",
    "wof:name":"Ramos Ruiz Carlos",
    "wof:placetype":"venue"
},
  "geometry": {"coordinates":[-2.4823639393,43.1833648682],"type":"Point"}
}