{
  "type": "Feature",
  "properties": {
    "addr:full":"Estafeta, 34 Iru\u00f1a Navarra 31001",
    "addr:housenumber":"34",
    "addr:postcode":"31001",
    "addr:street":"Estafeta",
    "iso:country":"ES",
    "sg:address":"Estafeta, 34",
    "sg:city":"Iru\u00f1a",
    "sg:orig_category":"Tatuajes",
    "sg:phone":"+34 948 22 95 07",
    "sg:postcode":"31001",
    "sg:province":"Navarra",
    "wof:name":"Palomar Gonzalez Monica",
    "wof:placetype":"venue"
},
  "geometry": {"coordinates":[-1.6421580315,42.8177375793],"type":"Point"}
}