{
  "type": "Feature",
  "properties": {
    "addr:full":"Urb Puesta De Sol, 10 Pedre\u00f1a Cantabria 39130",
    "addr:housenumber":"10",
    "addr:postcode":"39130",
    "addr:street":"Urb Puesta De Sol",
    "iso:country":"ES",
    "sg:address":"Urb Puesta De Sol, 10",
    "sg:city":"Pedre\u00f1a",
    "sg:orig_category":"Abogados",
    "sg:phone":"+34 942 50 10 21",
    "sg:postcode":"39130",
    "sg:province":"Cantabria",
    "wof:name":"Guzman Martinez Susana Carmen",
    "wof:placetype":"venue"
},
  "geometry": {"coordinates":[-3.7676358223,43.4447021484],"type":"Point"}
}