{
  "type": "Feature",
  "properties": {
    "addr:full":"Calle de Campomayor, 11 Merida Badajoz 06800",
    "addr:housenumber":"11",
    "addr:postcode":"06800",
    "addr:street":"Calle De Campomayor",
    "iso:country":"ES",
    "sg:address":"Calle de Campomayor, 11",
    "sg:city":"Merida",
    "sg:orig_category":"Delegados, Agentes De Tr\u00c1nsito, Auxiliares De Transporte Internacional",
    "sg:phone":"+34 924 37 36 70",
    "sg:postcode":"06800",
    "sg:province":"Badajoz",
    "wof:name":"Vizcaino Galan Fructuoso",
    "wof:placetype":"venue"
},
  "geometry": {"coordinates":[-6.3607039452,38.9085960388],"type":"Point"}
}