{
  "type": "Feature",
  "properties": {
    "iso:country":"ES",
    "sg:address":"Avda Joaquin Poveda, 3",
    "sg:city":"Petrer",
    "sg:orig_category":"Zapatos: Material, Suministros, Accesorios (fabricaci\u00d3n, Al Por Mayor)",
    "sg:phone":"+34 965 37 13 28",
    "sg:postcode":"03610",
    "sg:province":"Alicante",
    "wof:name":"Norba Sociedad Cooperativa",
    "wof:placetype":"venue"
},
  "geometry": {"coordinates":[-0.7740110159,38.4846801758],"type":"Point"}
}