{
  "type": "Feature",
  "properties": {
    "addr:full":"Rbla Badal, 141 Barcelona Barcelona 08028",
    "addr:housenumber":"141",
    "addr:postcode":"08028",
    "addr:street":"Rbla Badal",
    "iso:country":"ES",
    "sg:address":"Rbla Badal, 141",
    "sg:city":"Barcelona",
    "sg:orig_category":"Centros De Reservas Hoteleras",
    "sg:phone":"+34 932 98 16 60",
    "sg:postcode":"08028",
    "sg:province":"Barcelona",
    "wof:name":"Insigne Gestio Integral S.l.",
    "wof:placetype":"venue"
},
  "geometry": {"coordinates":[2.1309080124,41.3735198975],"type":"Point"}
}