{
  "type": "Feature",
  "properties": {
    "iso:country":"ES",
    "sg:address":"C/ Campos, 25",
    "sg:city":"Llucmajor",
    "sg:orig_category":"Promotores Constructores",
    "sg:phone":"+34 971 66 13 77",
    "sg:postcode":"07620",
    "sg:province":"Islas Baleares",
    "wof:name":"Nicolau Mulet Onofre",
    "wof:placetype":"venue"
},
  "geometry": {"coordinates":[2.8950800896,39.4905014038],"type":"Point"}
}