{
  "type": "Feature",
  "properties": {
    "addr:full":"C/ Progres, Del, 56 S. Antoni Portmany Islas Baleares 07820",
    "addr:housenumber":"56",
    "addr:postcode":"07820",
    "addr:street":"C / Progres Del",
    "iso:country":"ES",
    "sg:address":"C/ Progres, Del, 56",
    "sg:city":"S. Antoni Portmany",
    "sg:orig_category":"Caf\u00c9s, Bares, Cervecer\u00cdas",
    "sg:phone":"+34 971 34 76 32",
    "sg:postcode":"07820",
    "sg:province":"Islas Baleares",
    "wof:name":"Aguilar Amuedo Dolores",
    "wof:placetype":"venue"
},
  "geometry": {"coordinates":[1.3035714626,38.9811973572],"type":"Point"}
}