{
  "type": "Feature",
  "properties": {
    "addr:full":"Carrer de Francisco Giner, 6 Barcelona Barcelona 08012",
    "addr:housenumber":"6",
    "addr:postcode":"08012",
    "addr:street":"Carrer De Francisco Giner",
    "iso:country":"ES",
    "sg:address":"Carrer de Francisco Giner, 6",
    "sg:city":"Barcelona",
    "sg:orig_category":"Arquitectos",
    "sg:phone":"+34 932 17 51 25",
    "sg:postcode":"08012",
    "sg:province":"Barcelona",
    "wof:name":"Lagula Arquitectes S.l.",
    "wof:placetype":"venue"
},
  "geometry": {"coordinates":[2.1598510742,41.3987007141],"type":"Point"}
}