{
  "type": "Feature",
  "properties": {
    "addr:full":"Carrer de Josep Carner, 1 Granollers Barcelona 08402",
    "addr:housenumber":"1",
    "addr:postcode":"08402",
    "addr:street":"Carrer De Josep Carner",
    "iso:country":"ES",
    "sg:address":"Carrer de Josep Carner, 1",
    "sg:city":"Granollers",
    "sg:orig_category":"Psic\u00d3logos",
    "sg:phone":"+34 938 70 79 79",
    "sg:postcode":"08402",
    "sg:province":"Barcelona",
    "wof:name":"Recio Corral Josefa",
    "wof:placetype":"venue"
},
  "geometry": {"coordinates":[2.2938280106,41.6079216003],"type":"Point"}
}