{
  "type": "Feature",
  "properties": {
    "iso:country":"ES",
    "sg:address":"Carrer de Joan Marti, 62",
    "sg:city":"S. Boi Llobregat",
    "sg:orig_category":"Empresas De Pintura Y Revestimientos",
    "sg:phone":"+34 936 40 11 37",
    "sg:postcode":"08830",
    "sg:province":"Barcelona",
    "wof:name":"Lopez Ochavo Manuel",
    "wof:placetype":"venue"
},
  "geometry": {"coordinates":[2.0342180729,41.3497238159],"type":"Point"}
}