{
  "type": "Feature",
  "properties": {
    "addr:full":"Calle de Santa Teresa, 30 Meliana Valencia 46133",
    "addr:housenumber":"30",
    "addr:postcode":"46133",
    "addr:street":"Calle De Santa Teresa",
    "iso:country":"ES",
    "sg:address":"Calle de Santa Teresa, 30",
    "sg:city":"Meliana",
    "sg:orig_category":"Bares, Piano",
    "sg:phone":"+34 961 49 22 42",
    "sg:postcode":"46133",
    "sg:province":"Valencia",
    "wof:name":"Fernandez De Cordova Martin Juan Carlos",
    "wof:placetype":"venue"
},
  "geometry": {"coordinates":[-0.3456909955,39.5301704407],"type":"Point"}
}