{
  "type": "Feature",
  "properties": {
    "iso:country":"ES",
    "sg:address":"Calle de Santa Genoveva Torres, 30",
    "sg:city":"Valencia",
    "sg:orig_category":"Carnicer\u00cdas, Carnicer\u00cdas",
    "sg:phone":"+34 963 65 60 98",
    "sg:postcode":"46019",
    "sg:province":"Valencia",
    "wof:name":"Varea Martinez Maria Dolores",
    "wof:placetype":"venue"
},
  "geometry": {"coordinates":[-0.3653639853,39.4913597107],"type":"Point"}
}