{
  "type": "Feature",
  "properties": {
    "addr:full":"Turers, 23 Banyoles Girona 17820",
    "addr:housenumber":"23",
    "addr:postcode":"17820",
    "addr:street":"Turers",
    "iso:country":"ES",
    "sg:address":"Turers, 23",
    "sg:city":"Banyoles",
    "sg:orig_category":"Bisuter\u00cda, Joyer\u00cda, Relojer\u00cda (al Por Menor)",
    "sg:phone":"+34 972 57 04 00",
    "sg:postcode":"17820",
    "sg:province":"Girona",
    "wof:name":"Gratacos Boix Delfin",
    "wof:placetype":"venue"
},
  "geometry": {"coordinates":[2.7637600899,42.1179199219],"type":"Point"}
}