{
  "type": "Feature",
  "properties": {
    "iso:country":"ES",
    "sg:address":"Calle de Conde De Vilches, 16",
    "sg:city":"Madrid",
    "sg:orig_category":"Inform\u00c1tica Equipo Y Programas (al Por Mayor)",
    "sg:phone":"+34 917 24 92 00",
    "sg:postcode":"28...",
    "sg:province":"Madrid",
    "wof:name":"Microsistemas Lagasca S.a.",
    "wof:placetype":"venue"
},
  "geometry": {"coordinates":[-3.6694002151,40.4364776611],"type":"Point"}
}