{
  "type": "Feature",
  "properties": {
    "addr:full":"Calle de Escultor Gil Riquelme, S/n Molina Segura Murcia 30500",
    "addr:housenumber":"s",
    "addr:postcode":"30500",
    "addr:street":"Calle De Escultor Gil Riquelme;/ N Molina",
    "iso:country":"ES",
    "sg:address":"Calle de Escultor Gil Riquelme, S/n",
    "sg:city":"Molina Segura",
    "sg:orig_category":"Carnicer\u00cdas, Carnicer\u00cdas",
    "sg:phone":"+34 968 64 40 70",
    "sg:postcode":"30500",
    "sg:province":"Murcia",
    "wof:name":"Carniceria J.a. Y F. Martinez S.l.",
    "wof:placetype":"venue"
},
  "geometry": {"coordinates":[-1.2123340368,38.0531311035],"type":"Point"}
}