{
  "type": "Feature",
  "properties": {
    "addr:full":"Calle de San Cipriano, 63 Madrid Madrid 28032",
    "addr:housenumber":"63",
    "addr:postcode":"madrid;28032",
    "addr:street":"Calle De San",
    "iso:country":"ES",
    "sg:address":"Calle de San Cipriano, 63",
    "sg:city":"Madrid",
    "sg:orig_category":"Bancos",
    "sg:phone":"+34 917 75 33 20",
    "sg:postcode":"28032",
    "sg:province":"Madrid",
    "wof:name":"R Cable Y Telecomunicaciones Galicia S.a.",
    "wof:placetype":"venue"
},
  "geometry": {"coordinates":[-3.5982069969,40.4031143188],"type":"Point"}
}