{
  "type": "Feature",
  "properties": {
    "iso:country":"ES",
    "sg:address":"Carrer de Sallares I Pla, 57",
    "sg:city":"Sabadell",
    "sg:orig_category":"Centros M\u00c9dicos Y Sociales, Dispensarios",
    "sg:phone":"+34 937 25 55 77",
    "sg:postcode":"08202",
    "sg:province":"Barcelona",
    "wof:name":"Centro De Rehabilitacion Del Valles S.a.",
    "wof:placetype":"venue"
},
  "geometry": {"coordinates":[2.1130170822,41.5444641113],"type":"Point"}
}