{
  "type": "Feature",
  "properties": {
    "iso:country":"ES",
    "sg:address":"Cmno Cabue\u00d1es (somio), S/n",
    "sg:city":"Gijon",
    "sg:orig_category":"Electricidad: Equipos Industriales, Componentes (fabricaci\u00d3n)",
    "sg:phone":"+34 985 19 52 34",
    "sg:postcode":"33203",
    "sg:province":"Asturias",
    "wof:name":"Crady Electrica S.a.",
    "wof:placetype":"venue"
},
  "geometry": {"coordinates":[-5.6090569496,43.5285148621],"type":"Point"}
}