{
  "type": "Feature",
  "properties": {
    "iso:country":"ES",
    "sg:address":"Calle de Zapateros, 11",
    "sg:city":"Motril",
    "sg:orig_category":"Droguer\u00cdas (al Por Menor)",
    "sg:phone":"+34 958 60 13 32",
    "sg:postcode":"18600",
    "sg:province":"Granada",
    "wof:name":"Castillo Salazar Antonio",
    "wof:placetype":"venue"
},
  "geometry": {"coordinates":[-3.5196690559,36.7445602417],"type":"Point"}
}