{
  "type": "Feature",
  "properties": {
    "iso:country":"ES",
    "sg:address":"Calle de Gamonal, 6",
    "sg:city":"Vecindario",
    "sg:orig_category":"Asociaciones Y Clubs Deportivos",
    "sg:phone":"+34 928 79 15 29",
    "sg:postcode":"35110",
    "sg:province":"Las Palmas",
    "wof:name":"Antonio Delgado Francisco Javier",
    "wof:placetype":"venue"
},
  "geometry": {"coordinates":[-15.4412117004,27.8475551605],"type":"Point"}
}