{
  "type": "Feature",
  "properties": {
    "iso:country":"ES",
    "sg:address":"Av Jaume I, S/n",
    "sg:city":"Mollet Valles",
    "sg:orig_category":"Cajas De Ahorro",
    "sg:phone":"+34 935 44 56 20",
    "sg:postcode":"08100",
    "sg:province":"Barcelona",
    "wof:name":"Caixa D'estalvis De Catalunya",
    "wof:placetype":"venue"
},
  "geometry": {"coordinates":[2.2160050869,41.5432510376],"type":"Point"}
}