{
  "type": "Feature",
  "properties": {
    "iso:country":"ES",
    "sg:address":"Calle de Rafael Lucenqui, 16",
    "sg:city":"Badajoz",
    "sg:orig_category":"Carnicer\u00cdas, Carnicer\u00cdas",
    "sg:phone":"+34 924 23 63 05",
    "sg:postcode":"06004",
    "sg:province":"Badajoz",
    "wof:name":"Casaseca Diez Antonio",
    "wof:placetype":"venue"
},
  "geometry": {"coordinates":[-6.9752259254,38.8698158264],"type":"Point"}
}