{
  "type": "Feature",
  "properties": {
    "iso:country":"ES",
    "sg:address":"Calle de Zoa, 19",
    "sg:city":"Torrevieja",
    "sg:orig_category":"Cajas Para Embalar",
    "sg:phone":"+34 966 70 74 46",
    "sg:postcode":"03180",
    "sg:province":"Alicante",
    "wof:name":"Caja Rural Central De Orihuela",
    "wof:placetype":"venue"
},
  "geometry": {"coordinates":[-0.6772500277,37.9765357971],"type":"Point"}
}