{
  "type": "Feature",
  "properties": {
    "iso:country":"ES",
    "sg:address":"Carrer de Girona, 43",
    "sg:city":"S. Feliu Guixols",
    "sg:orig_category":"Agencias Y Asesores De Publicidad",
    "sg:phone":"+34 972 82 21 30",
    "sg:postcode":"17220",
    "sg:province":"Girona",
    "wof:name":"Verdaguer Tenas Isabel",
    "wof:placetype":"venue"
},
  "geometry": {"coordinates":[3.03064394,41.783706665],"type":"Point"}
}