{
  "type": "Feature",
  "properties": {
    "iso:country":"ES",
    "sg:address":"Villafranca A Vellosillo, S/n",
    "sg:city":"Torrecilla",
    "sg:orig_category":"Agricultura: Abastecimiento Y Cosechado (negocio)",
    "sg:phone":"+34 921 12 13 98",
    "sg:postcode":"40318",
    "sg:province":"Segovia",
    "wof:name":"Sociedad Agraria De Transformacion Gohersa",
    "wof:placetype":"venue"
},
  "geometry": {"coordinates":[-3.7441189289,41.2411384583],"type":"Point"}
}