{
  "type": "Feature",
  "properties": {
    "addr:full":"Calle de Ramon Y Cajal, 136 Villanueva Arzobispo Ja\u00e9n 23330",
    "addr:housenumber":"136",
    "addr:postcode":"23330",
    "addr:street":"Calle De Ramon Y Cajal",
    "iso:country":"ES",
    "sg:address":"Calle de Ramon Y Cajal, 136",
    "sg:city":"Villanueva Arzobispo",
    "sg:orig_category":"Molduras, Junquillos, Listones Y Molduras Perforadas",
    "sg:phone":"+34 953 45 22 87",
    "sg:postcode":"23330",
    "sg:province":"Ja\u00e9n",
    "wof:name":"Mora Marin Fernando",
    "wof:placetype":"venue"
},
  "geometry": {"coordinates":[-3.0003759861,38.165145874],"type":"Point"}
}