{
  "type": "Feature",
  "properties": {
    "addr:full":"Carrer de Joan Guell, 70 Barcelona Barcelona 08028",
    "addr:housenumber":"70",
    "addr:postcode":"08028",
    "addr:street":"Carrer De Joan Guell",
    "iso:country":"ES",
    "sg:address":"Carrer de Joan Guell, 70",
    "sg:city":"Barcelona",
    "sg:orig_category":"Molduras, Junquillos, Listones Y Molduras Perforadas",
    "sg:phone":"+34 933 30 71 35",
    "sg:postcode":"08028",
    "sg:province":"Barcelona",
    "wof:name":"Bosch Fernandez Raul",
    "wof:placetype":"venue"
},
  "geometry": {"coordinates":[2.1331551075,41.3796348572],"type":"Point"}
}