{
  "type": "Feature",
  "properties": {
    "addr:full":"Calle de Carmen (el), 25 Baeza Ja\u00e9n 23440",
    "addr:postcode":"23440",
    "addr:street":"Calle De Carmen El",
    "iso:country":"ES",
    "sg:address":"Calle de Carmen (el), 25",
    "sg:city":"Baeza",
    "sg:orig_category":"Electricidad: Instaladores",
    "sg:phone":"+34 953 74 06 39",
    "sg:postcode":"23440",
    "sg:province":"Ja\u00e9n",
    "wof:name":"Acero Frio Y Electricidad S.l.",
    "wof:placetype":"venue"
},
  "geometry": {"coordinates":[-3.4646699429,37.9931259155],"type":"Point"}
}