{
  "type": "Feature",
  "properties": {
    "iso:country":"ES",
    "sg:address":"Av M. Celayeta, 75",
    "sg:city":"Iru\u00f1a",
    "sg:orig_category":"Empresas De Vigilancia, Guardia Y Protecci\u00d3n",
    "sg:phone":"+34 948 13 62 68",
    "sg:postcode":"31014",
    "sg:province":"Navarra",
    "wof:name":"Proteccion Y Seguridad Tecnica S.a.",
    "wof:placetype":"venue"
},
  "geometry": {"coordinates":[-1.6437540054,42.81275177],"type":"Point"}
}