{
  "type": "Feature",
  "properties": {
    "iso:country":"ES",
    "sg:address":"Carrer de Abat Oliba, 66",
    "sg:city":"Manresa",
    "sg:orig_category":"Agencias Y Agentes Comerciales, Representantes",
    "sg:phone":"+34 938 77 03 35",
    "sg:postcode":"08242",
    "sg:province":"Barcelona",
    "wof:name":"Muns Vilaseca Eva",
    "wof:placetype":"venue"
},
  "geometry": {"coordinates":[1.8286340237,41.7352485657],"type":"Point"}
}