{
  "type": "Feature",
  "properties": {
    "iso:country":"ES",
    "sg:address":"Calle de Luxemburgo, 4",
    "sg:city":"Pozuelo De Alarcon",
    "sg:orig_category":"Ingeniero",
    "sg:phone":"+34 913 51 11 20",
    "sg:postcode":"28224",
    "sg:province":"Madrid",
    "wof:name":"Avante Soluciones Informaticas S.a.",
    "wof:placetype":"venue"
},
  "geometry": {"coordinates":[-3.8049652576,40.4324989319],"type":"Point"}
}