{
  "type": "Feature",
  "properties": {
    "addr:full":"Calle de Emperador Trajano, 17 Andujar Ja\u00e9n 23740",
    "addr:housenumber":"17",
    "addr:postcode":"23740",
    "addr:street":"Calle De Emperador Trajano",
    "iso:country":"ES",
    "sg:address":"Calle de Emperador Trajano, 17",
    "sg:city":"Andujar",
    "sg:orig_category":"Electrodom\u00c9sticos (al Por Menor)",
    "sg:phone":"+34 953 50 18 83",
    "sg:postcode":"23740",
    "sg:province":"Ja\u00e9n",
    "wof:name":"Ruiz Parra Francisco Jose",
    "wof:placetype":"venue"
},
  "geometry": {"coordinates":[-4.0492691994,38.0406494141],"type":"Point"}
}