{
  "type": "Feature",
  "properties": {
    "iso:country":"ES",
    "sg:address":"Avda Tierra Llana, Km. 0003,0",
    "sg:city":"Guntin",
    "sg:orig_category":"Electricidad: Instaladores",
    "sg:phone":"+34 982 51 19 05",
    "sg:postcode":"27810",
    "sg:province":"Lugo",
    "wof:name":"Cuba Cal Elias",
    "wof:placetype":"venue"
},
  "geometry": {"coordinates":[-7.6721467972,43.2896842957],"type":"Point"}
}