{
  "type": "Feature",
  "properties": {
    "addr:full":"Calle de Pellejo (del), 48 Valdepe\u00f1as Ciudad Real 13300",
    "addr:housenumber":"48",
    "addr:postcode":"13300",
    "addr:street":"Calle De Pellejo Del",
    "iso:country":"ES",
    "sg:address":"Calle de Pellejo (del), 48",
    "sg:city":"Valdepe\u00f1as",
    "sg:orig_category":"Imprenta",
    "sg:phone":"+34 926 32 14 66",
    "sg:postcode":"13300",
    "sg:province":"Ciudad Real",
    "wof:name":"Campos De La Piedra Alicia",
    "wof:placetype":"venue"
},
  "geometry": {"coordinates":[-3.3911440372,38.7782402039],"type":"Point"}
}