{
  "type": "Feature",
  "properties": {
    "iso:country":"ES",
    "sg:address":"Calle de Santo Tomas, 3",
    "sg:city":"Segovia",
    "sg:orig_category":"Fabricaci\u00d3n, Distribuci\u00d3n De Discos, V\u00cddeodiscos Y Musicassettes",
    "sg:phone":"+34 921 42 62 02",
    "sg:postcode":"40002",
    "sg:province":"Segovia",
    "wof:name":"Rueda Seibane Pedro",
    "wof:placetype":"venue"
},
  "geometry": {"coordinates":[-4.1184530258,40.9437217712],"type":"Point"}
}