{
  "type": "Feature",
  "properties": {
    "addr:full":"Calle de Godofredo Ortega Y Mu\u00d1oz, 58 Badajoz Badajoz 06011",
    "addr:housenumber":"58",
    "addr:postcode":"06011",
    "addr:street":"Calle De Godofredo Ortega Y Mun\u0303Oz",
    "iso:country":"ES",
    "sg:address":"Calle de Godofredo Ortega Y Mu\u00d1oz, 58",
    "sg:city":"Badajoz",
    "sg:orig_category":"M\u00c9dicos: Anestesiolog\u00cda Y Reanimaci\u00d3n Quir\u00dargica",
    "sg:phone":"+34 924 25 06 51",
    "sg:postcode":"06011",
    "sg:province":"Badajoz",
    "wof:name":"Sanchez Espinosa Fernando",
    "wof:placetype":"venue"
},
  "geometry": {"coordinates":[-6.9857192039,38.8671607971],"type":"Point"}
}