{
  "type": "Feature",
  "properties": {
    "addr:full":"Valle Aranguren, S/n Iru\u00f1a Navarra 31006",
    "addr:housenumber":"s / n",
    "addr:postcode":"31006",
    "addr:street":"Aranguren",
    "iso:country":"ES",
    "sg:address":"Valle Aranguren, S/n",
    "sg:city":"Iru\u00f1a",
    "sg:orig_category":"Materiales De Aislamiento T\u00c9rmico Y Ac\u00dastico",
    "sg:phone":"+34 948 23 58 62",
    "sg:postcode":"31006",
    "sg:province":"Navarra",
    "wof:name":"Aislamientos Aislem Tafalla S.l.",
    "wof:placetype":"venue"
},
  "geometry": {"coordinates":[-1.6299338341,42.8059120178],"type":"Point"}
}