{
  "type": "Feature",
  "properties": {
    "addr:full":"Corindo, 7 Burriana Castell\u00f3n 12530",
    "addr:housenumber":"7",
    "addr:postcode":"12530",
    "addr:street":"Corindo",
    "iso:country":"ES",
    "sg:address":"Corindo, 7",
    "sg:city":"Burriana",
    "sg:orig_category":"Empresas De Carpinter\u00cda Met\u00c1lica",
    "sg:phone":"+34 964 51 12 84",
    "sg:postcode":"12530",
    "sg:province":"Castell\u00f3n",
    "wof:name":"Sebastia Gasco Enrique",
    "wof:placetype":"venue"
},
  "geometry": {"coordinates":[-0.1016890034,39.8801994324],"type":"Point"}
}