{
  "type": "Feature",
  "properties": {
    "iso:country":"ES",
    "sg:address":"Calle de Ca\u00d1uelo, 7",
    "sg:city":"Tarazona",
    "sg:orig_category":"Molduras, Junquillos, Listones Y Molduras Perforadas",
    "sg:phone":"+34 976 64 00 16",
    "sg:postcode":"50500",
    "sg:province":"Zaragoza",
    "wof:name":"Sesma Ucar Jose",
    "wof:placetype":"venue"
},
  "geometry": {"coordinates":[-1.7251169682,41.9043960571],"type":"Point"}
}