{
  "type": "Feature",
  "properties": {
    "addr:full":"Ctra Torregrossa, S/n Mollerussa Lleida 25230",
    "addr:housenumber":"s / n",
    "addr:postcode":"25230",
    "addr:street":"Ctra Torregrossa",
    "iso:country":"ES",
    "sg:address":"Ctra Torregrossa, S/n",
    "sg:city":"Mollerussa",
    "sg:orig_category":"Centros De Educaci\u00d3n Especial",
    "sg:phone":"+34 973 60 25 01",
    "sg:postcode":"25230",
    "sg:province":"Lleida",
    "wof:name":"Ceip Pompeu Fabra",
    "wof:placetype":"venue"
},
  "geometry": {"coordinates":[0.8883200288,41.6262817383],"type":"Point"}
}