{
  "type": "Feature",
  "properties": {
    "addr:full":"Carrer de Huguet Des Far, S/n Santa Pon\u00c7a Islas Baleares 07180",
    "addr:housenumber":"s / n",
    "addr:postcode":"07180",
    "addr:street":"Carrer De Huguet Des Far",
    "iso:country":"ES",
    "sg:address":"Carrer de Huguet Des Far, S/n",
    "sg:city":"Santa Pon\u00c7a",
    "sg:orig_category":"Molduras, Junquillos, Listones Y Molduras Perforadas",
    "sg:phone":"+34 971 69 50 89",
    "sg:postcode":"07180",
    "sg:province":"Islas Baleares",
    "wof:name":"Valle Rodriguez Rosa Del",
    "wof:placetype":"venue"
},
  "geometry": {"coordinates":[2.4722878933,39.520450592],"type":"Point"}
}