{
  "type": "Feature",
  "properties": {
    "iso:country":"ES",
    "sg:address":"Calle de Farmaceutico Obdulio Fernandez, 10",
    "sg:city":"Burgos",
    "sg:orig_category":"Sociedades, Compa\u00d1\u00cdas Aseguradoras",
    "sg:phone":"+34 947 24 12 33",
    "sg:postcode":"09006",
    "sg:province":"Burgos",
    "sg:website":"www.fiatc.es",
    "wof:name":"Fiatc-mutua De Seguros Generales",
    "wof:placetype":"venue"
},
  "geometry": {"coordinates":[-3.6848697662,42.345413208],"type":"Point"}
}