{
  "type": "Feature",
  "properties": {
    "iso:country":"ES",
    "sg:address":"Calle de Nicolas Maquiavelo, 2",
    "sg:city":"Malaga",
    "sg:orig_category":"Telefon\u00cda: Instaladores Varios",
    "sg:phone":"+34 952 33 50 54",
    "sg:postcode":"29006",
    "sg:province":"M\u00e1laga",
    "wof:name":"Arias Graterol Edgar",
    "wof:placetype":"venue"
},
  "geometry": {"coordinates":[-4.4615917206,36.7101554871],"type":"Point"}
}