{
  "type": "Feature",
  "properties": {
    "addr:full":"Avda Benito Vigo, 117 Estrada Pontevedra 36680",
    "addr:housenumber":"117",
    "addr:postcode":"36680",
    "addr:street":"Avda Benito Vigo;Estrada Pontevedra",
    "iso:country":"ES",
    "sg:address":"Avda Benito Vigo, 117",
    "sg:city":"Estrada",
    "sg:orig_category":"Agentes, Concesionarios Y Sucursales De Veh\u00cdculos",
    "sg:phone":"+34 986 57 27 55",
    "sg:postcode":"36680",
    "sg:province":"Pontevedra",
    "wof:name":"Beyma Motor S.l",
    "wof:placetype":"venue"
},
  "geometry": {"coordinates":[-8.4853067398,42.6884307861],"type":"Point"}
}