{
  "type": "Feature",
  "properties": {
    "addr:full":"Calle de Ave Maria, 6 Madrid Madrid 28012",
    "addr:housenumber":"6",
    "addr:postcode":"28012",
    "addr:street":"Calle De Ave Maria",
    "iso:country":"ES",
    "sg:address":"Calle de Ave Maria, 6",
    "sg:city":"Madrid",
    "sg:orig_category":"Promotores Constructores",
    "sg:phone":"+34 914 29 06 71",
    "sg:postcode":"28012",
    "sg:province":"Madrid",
    "wof:name":"Ortiz Construcciones Y Proyectos S.a.",
    "wof:placetype":"venue"
},
  "geometry": {"coordinates":[-3.7002294064,40.4118728638],"type":"Point"}
}