{
  "type": "Feature",
  "properties": {
    "iso:country":"ES",
    "sg:address":"Calle de Rubens Marichal Lopez, 53",
    "sg:city":"Santa Cruz De Tenerife",
    "sg:orig_category":"Fisioterapia",
    "sg:phone":"+34 922 24 28 65",
    "sg:postcode":"38170",
    "sg:province":"Santa Cruz De Tenerife",
    "wof:name":"Gabinete Fisioterapeutico C & L",
    "wof:placetype":"venue"
},
  "geometry": {"coordinates":[-16.2571182251,28.477230072],"type":"Point"}
}