{
  "type": "Feature",
  "properties": {
    "addr:full":"Carrer de Pujades, 77 Barcelona Barcelona 08005",
    "addr:housenumber":"77",
    "addr:postcode":"08005",
    "addr:street":"Carrer De Pujades",
    "iso:country":"ES",
    "sg:address":"Carrer de Pujades, 77",
    "sg:city":"Barcelona",
    "sg:orig_category":"Papeler\u00cdas: Art\u00cdculos (al Por Mayor)",
    "sg:phone":"+34 934 85 02 06",
    "sg:postcode":"08005",
    "sg:province":"Barcelona",
    "wof:name":"Nadal 1987 S.l.",
    "wof:placetype":"venue"
},
  "geometry": {"coordinates":[2.1943171024,41.397064209],"type":"Point"}
}