{
  "type": "Feature",
  "properties": {
    "addr:full":"Carrer de Aribau, 172 Barcelona Barcelona 08036",
    "addr:housenumber":"172",
    "addr:postcode":"08036",
    "addr:street":"Carrer De Aribau",
    "iso:country":"ES",
    "sg:address":"Carrer de Aribau, 172",
    "sg:city":"Barcelona",
    "sg:orig_category":"M\u00c9dicos: Fisioterapia Y Rehabilitaci\u00d3n",
    "sg:phone":"+34 933 68 02 70",
    "sg:postcode":"08036",
    "sg:province":"Barcelona",
    "sg:website":"www.atlantida.net",
    "wof:name":"Atlantida Medica De Especialidades S. A.",
    "wof:placetype":"venue"
},
  "geometry": {"coordinates":[2.1533415318,41.3929481506],"type":"Point"}
}