{
  "type": "Feature",
  "properties": {
    "addr:full":"Avda Gran Via, 146 Vigo Pontevedra 36211",
    "addr:housenumber":"146",
    "addr:postcode":"36211",
    "addr:street":"Avda Gran Via",
    "iso:country":"ES",
    "sg:address":"Avda Gran Via, 146",
    "sg:city":"Vigo",
    "sg:orig_category":"Ingeniero",
    "sg:phone":"+34 902 19 75 95",
    "sg:postcode":"36211",
    "sg:province":"Pontevedra",
    "sg:website":"www.iterdata.com",
    "wof:name":"Iterdata Networks S.l.",
    "wof:placetype":"venue"
},
  "geometry": {"coordinates":[-8.72585392,42.2224769592],"type":"Point"}
}