{
  "type": "Feature",
  "properties": {
    "iso:country":"ES",
    "sg:address":"Avda Brasil (do), 10",
    "sg:city":"Santa Comba",
    "sg:orig_category":"Reposter\u00cdas",
    "sg:phone":"+34 981 88 10 70",
    "sg:postcode":"15840",
    "sg:province":"La Coru\u00f1a",
    "wof:name":"Gomez Bucci Rosana",
    "wof:placetype":"venue"
},
  "geometry": {"coordinates":[-8.8054885864,43.033416748],"type":"Point"}
}