{
  "type": "Feature",
  "properties": {
    "iso:country":"ES",
    "sg:address":"Calle de Reyes Huertas, 9",
    "sg:city":"Guadalupe",
    "sg:orig_category":"Cr\u00cda De Animales",
    "sg:phone":"+34 927 36 73 94",
    "sg:postcode":"10140",
    "sg:province":"C\u00e1ceres",
    "wof:name":"Td Extreme\u00f1a De Ganados S.l.",
    "wof:placetype":"venue"
},
  "geometry": {"coordinates":[-5.3244018555,39.4502105713],"type":"Point"}
}