{
  "type": "Feature",
  "properties": {
    "addr:full":"Ctra Gabino Bugallal, S/n Leiro Ourense 32420",
    "addr:housenumber":"s / n",
    "addr:postcode":"32420",
    "addr:street":"Ctra Gabino Bugallal",
    "iso:country":"ES",
    "sg:address":"Ctra Gabino Bugallal, S/n",
    "sg:city":"Leiro",
    "sg:orig_category":"Molduras, Junquillos, Listones Y Molduras Perforadas",
    "sg:phone":"+34 988 48 84 15",
    "sg:postcode":"32420",
    "sg:province":"Ourense",
    "wof:name":"Amil Gonzalez Jose Luis",
    "wof:placetype":"venue"
},
  "geometry": {"coordinates":[-8.1251430511,42.3694839478],"type":"Point"}
}