{
  "type": "Feature",
  "properties": {
    "addr:full":"Ctra. Aeropuerto, Km. 0003,5 Manises Valencia 46940",
    "addr:postcode":"46940",
    "addr:street":"Ctra. Aeropuerto Km. 0003,5",
    "iso:country":"ES",
    "sg:address":"Ctra. Aeropuerto, Km. 0003,5",
    "sg:city":"Manises",
    "sg:orig_category":"Mataderos Y Talleres De Despiezado",
    "sg:phone":"+34 961 54 77 05",
    "sg:postcode":"46940",
    "sg:province":"Valencia",
    "wof:name":"Carma Siglo Xxi S.a.",
    "wof:placetype":"venue"
},
  "geometry": {"coordinates":[-0.4693610072,39.4889907837],"type":"Point"}
}