{
  "type": "Feature",
  "properties": {
    "iso:country":"ES",
    "sg:address":"Calle de Castillo, 23",
    "sg:city":"Santa Cruz De Tenerife",
    "sg:orig_category":"Abogados",
    "sg:phone":"+34 922 15 11 51",
    "sg:postcode":"38002",
    "sg:province":"Santa Cruz De Tenerife",
    "wof:name":"Villaquiran Llinas Virginia Maria",
    "wof:placetype":"venue"
},
  "geometry": {"coordinates":[-16.2506275177,28.4671516418],"type":"Point"}
}