{
  "type": "Feature",
  "properties": {
    "addr:full":"Carrer de Enric Granados, 61 Barcelona Barcelona 08008",
    "addr:housenumber":"61",
    "addr:postcode":"08008",
    "addr:street":"Carrer De Enric Granados",
    "iso:country":"ES",
    "sg:address":"Carrer de Enric Granados, 61",
    "sg:city":"Barcelona",
    "sg:orig_category":"Psic\u00d3logos",
    "sg:phone":"+34 934 51 74 77",
    "sg:postcode":"08008",
    "sg:province":"Barcelona",
    "wof:name":"Cid Guimera Dolores",
    "wof:placetype":"venue"
},
  "geometry": {"coordinates":[2.1580290794,41.3909072876],"type":"Point"}
}