{
  "type": "Feature",
  "properties": {
    "addr:full":"Avda Segadas De Las, 7 Oviedo Asturias 33006",
    "addr:housenumber":"7",
    "addr:postcode":"33006",
    "addr:street":"Avda Segadas De Las",
    "iso:country":"ES",
    "sg:address":"Avda Segadas De Las, 7",
    "sg:city":"Oviedo",
    "sg:orig_category":"Art\u00cdculos De Madera (fabricaci\u00d3n Y Al Por Mayor)",
    "sg:phone":"+34 985 23 01 64",
    "sg:postcode":"33006",
    "sg:province":"Asturias",
    "wof:name":"Lorenzo Diaz Arsenio",
    "wof:placetype":"venue"
},
  "geometry": {"coordinates":[-5.8821821213,43.3510742188],"type":"Point"}
}