{
  "type": "Feature",
  "properties": {
    "addr:full":"Carrer de Francesc Bellapart, 3 Sabadell Barcelona 08208",
    "addr:housenumber":"3",
    "addr:postcode":"08208",
    "addr:street":"Carrer De Francesc Bellapart",
    "iso:country":"ES",
    "sg:address":"Carrer de Francesc Bellapart, 3",
    "sg:city":"Sabadell",
    "sg:orig_category":"Lavado, Limpieza De Veh\u00cdculos",
    "sg:phone":"+34 937 17 81 51",
    "sg:postcode":"08208",
    "sg:province":"Barcelona",
    "wof:name":"Auto Lavado Estadio S.l.",
    "wof:placetype":"venue"
},
  "geometry": {"coordinates":[2.0977931023,41.5583229065],"type":"Point"}
}