{
  "type": "Feature",
  "properties": {
    "addr:full":"Calle de Ercilla, 13 Bilbao Vizcaya 48009",
    "addr:housenumber":"13",
    "addr:postcode":"48009",
    "addr:street":"Calle De Ercilla",
    "iso:country":"ES",
    "sg:address":"Calle de Ercilla, 13",
    "sg:city":"Bilbao",
    "sg:orig_category":"Partidos Pol\u00cdticos",
    "sg:phone":"+34 944 24 16 06",
    "sg:postcode":"48009",
    "sg:province":"Vizcaya",
    "wof:name":"Partido Socialista Obrero Espa\u00f1ol",
    "wof:placetype":"venue"
},
  "geometry": {"coordinates":[-2.9324040413,43.2640533447],"type":"Point"}
}