{
  "type": "Feature",
  "properties": {
    "addr:full":"Ctra Nacional Ii, Km. 0016,0 Castellanas Madrid 28830",
    "addr:postcode":"28830",
    "addr:street":"Ctra Nacional Ii Km. 0016,0",
    "iso:country":"ES",
    "sg:address":"Ctra Nacional Ii, Km. 0016,0",
    "sg:city":"Castellanas",
    "sg:orig_category":"Animales (al Por Menor)",
    "sg:phone":"+34 916 73 05 72",
    "sg:postcode":"28830",
    "sg:province":"Madrid",
    "wof:name":"Sanabria Soto Aranzazu",
    "wof:placetype":"venue"
},
  "geometry": {"coordinates":[-3.5353159904,40.4256858826],"type":"Point"}
}