{
  "type": "Feature",
  "properties": {
    "iso:country":"ES",
    "sg:address":"Calle de Charcones (de Los), 20",
    "sg:city":"Navalcarnero",
    "sg:orig_category":"Fabricaci\u00d3n De Moldes Y Modelos",
    "sg:phone":"+34 918 11 23 76",
    "sg:postcode":"28600",
    "sg:province":"Madrid",
    "wof:name":"Matriceria Malu S.l.",
    "wof:placetype":"venue"
},
  "geometry": {"coordinates":[-4.0037503242,40.2896003723],"type":"Point"}
}