{
  "type": "Feature",
  "properties": {
    "iso:country":"ES",
    "sg:address":"Carrer de Optica, 11",
    "sg:city":"Polingons Industrials Santa Rita-agripina",
    "sg:classifiers":[
        {
            "category":"Professional",
            "subcategory":"Business Services",
            "type":"Services"
        }
    ],
    "sg:phone":"+34 937 72 35 58",
    "sg:postcode":"08755",
    "sg:province":"Barcelona",
    "sg:tags":[
        "control",
        "asesor\u00cda",
        "organizaci\u00d3n",
        "la",
        "de",
        "gesti\u00d3n",
        "y"
    ],
    "wof:name":"Estudios Y Desarrollos Nicoval S.l.",
    "wof:placetype":"venue"
},
  "geometry": {"coordinates":[1.9784770012,41.4735145569],"type":"Point"}
}