{
  "type": "Feature",
  "properties": {
    "addr:full":"Avda Conde De Guadalhorce, 2 Aviles Asturias 33401",
    "addr:housenumber":"2",
    "addr:postcode":"33401",
    "addr:street":"Avda Conde De Guadalhorce",
    "iso:country":"ES",
    "sg:address":"Avda Conde De Guadalhorce, 2",
    "sg:city":"Aviles",
    "sg:orig_category":"Fabricaci\u00d3n, Reparaci\u00d3n Y Mantenimiento De Construcciones Navales Y Fluviales",
    "sg:phone":"+34 985 56 57 29",
    "sg:postcode":"33401",
    "sg:province":"Asturias",
    "wof:name":"Gonzalez Rodriguez Manuel",
    "wof:placetype":"venue"
},
  "geometry": {"coordinates":[-5.922870636,43.570930481],"type":"Point"}
}