{
  "type": "Feature",
  "properties": {
    "addr:full":"La Palma, 1 Hornachuelos C\u00f3rdoba 14740",
    "addr:housenumber":"1",
    "addr:postcode":"14740",
    "addr:street":"La Palma",
    "iso:country":"ES",
    "sg:address":"La Palma, 1",
    "sg:city":"Hornachuelos",
    "sg:orig_category":"Art\u00cdculos Funerarios (al Por Menor)",
    "sg:phone":"+34 957 64 02 89",
    "sg:postcode":"14740",
    "sg:province":"C\u00f3rdoba",
    "wof:name":"Funeraria San Vicente S.l.",
    "wof:placetype":"venue"
},
  "geometry": {"coordinates":[-5.2433562279,37.8308143616],"type":"Point"}
}