{
  "type": "Feature",
  "properties": {
    "iso:country":"ES",
    "sg:address":"Calle de Jeronimo De Monsoriu, 41",
    "sg:city":"Valencia",
    "sg:orig_category":"Electricidad: Equipos Industriales, Componentes (fabricaci\u00d3n)",
    "sg:phone":"+34 963 31 95 00",
    "sg:postcode":"46022",
    "sg:province":"Valencia",
    "wof:name":"Comercial B.r.m.s.a.",
    "wof:placetype":"venue"
},
  "geometry": {"coordinates":[-0.3398079872,39.4653358459],"type":"Point"}
}