{
  "type": "Feature",
  "properties": {
    "addr:full":"Calle de Cristobal Colon, 29 Ayamonte Huelva 21400",
    "addr:housenumber":"29",
    "addr:postcode":"21400",
    "addr:street":"Calle De Cristobal Colon",
    "iso:country":"ES",
    "sg:address":"Calle de Cristobal Colon, 29",
    "sg:city":"Ayamonte",
    "sg:orig_category":"Asesor\u00cda Fiscal Y Jur\u00cddica",
    "sg:phone":"+34 959 47 06 16",
    "sg:postcode":"21400",
    "sg:province":"Huelva",
    "wof:name":"Rosa Lopez Francisco Jose",
    "wof:placetype":"venue"
},
  "geometry": {"coordinates":[-7.4084692001,37.2142753601],"type":"Point"}
}