{
  "type": "Feature",
  "properties": {
    "addr:full":"Vega De Llan, S/n Vega De Llan Asturias 33775",
    "addr:housenumber":"s / n",
    "addr:postcode":"33775",
    "addr:street":"Vega;Llan",
    "iso:country":"ES",
    "sg:address":"Vega De Llan, S/n",
    "sg:city":"Vega De Llan",
    "sg:orig_category":"Fabricaci\u00d3n De Productos L\u00c1cteos Y Derivados",
    "sg:phone":"+34 985 64 68 18",
    "sg:postcode":"33775",
    "sg:province":"Asturias",
    "wof:name":"Soc.coop.eo Leche R.l.",
    "wof:placetype":"venue"
},
  "geometry": {"coordinates":[-7.1083769798,43.3608856201],"type":"Point"}
}