{
  "type": "Feature",
  "properties": {
    "addr:full":"Calle de Francisco Del Pino, 24 Madrid Madrid 28021",
    "addr:housenumber":"24",
    "addr:postcode":"madrid;28021",
    "addr:street":"Calle De Francisco Del Pino",
    "iso:country":"ES",
    "sg:address":"Calle de Francisco Del Pino, 24",
    "sg:city":"Madrid",
    "sg:orig_category":"Ropa Para Se\u00d1oras Y Caballeros (al Por Menor)",
    "sg:phone":"+34 917 97 25 06",
    "sg:postcode":"28021",
    "sg:province":"Madrid",
    "wof:name":"Gallego Fuentelsaz Sotero",
    "wof:placetype":"venue"
},
  "geometry": {"coordinates":[-3.6892991066,40.3498916626],"type":"Point"}
}