{
  "type": "Feature",
  "properties": {
    "addr:full":"Carrer de Valencia (de), 11 Salou Tarragona 43840",
    "addr:housenumber":"11",
    "addr:postcode":"43840",
    "addr:street":"Carrer De Valencia De",
    "iso:country":"ES",
    "sg:address":"Carrer de Valencia (de), 11",
    "sg:city":"Salou",
    "sg:orig_category":"Florister\u00cdas",
    "sg:phone":"+34 977 38 12 77",
    "sg:postcode":"43840",
    "sg:province":"Tarragona",
    "wof:name":"Orte Sanchez Rafael",
    "wof:placetype":"venue"
},
  "geometry": {"coordinates":[1.1303360462,41.0770263672],"type":"Point"}
}