{
  "type": "Feature",
  "properties": {
    "iso:country":"ES",
    "sg:address":"Calle de Travieso, 10",
    "sg:city":"Palmas De Gran Canaria",
    "sg:orig_category":"Importaci\u00d3n",
    "sg:phone":"+34 928 36 11 90",
    "sg:postcode":"35002",
    "sg:province":"Las Palmas",
    "wof:name":"Socorro Tabacos S.a.",
    "wof:placetype":"venue"
},
  "geometry": {"coordinates":[-15.4163990021,28.1050491333],"type":"Point"}
}