{
  "type": "Feature",
  "properties": {
    "addr:full":"Calle de Somosierra, 6 Segovia Segovia 40006",
    "addr:housenumber":"6",
    "addr:postcode":"40006",
    "addr:street":"Calle De Somosierra",
    "iso:country":"ES",
    "sg:address":"Calle de Somosierra, 6",
    "sg:city":"Segovia",
    "sg:orig_category":"Ebanister\u00cda",
    "sg:phone":"+34 921 42 17 50",
    "sg:postcode":"40006",
    "sg:province":"Segovia",
    "wof:name":"Gil De Andres Jose Ignacio",
    "wof:placetype":"venue"
},
  "geometry": {"coordinates":[-4.1123681068,40.9272460938],"type":"Point"}
}