{
  "type": "Feature",
  "properties": {
    "iso:country":"ES",
    "sg:address":"Calle de Fuencarral, 74",
    "sg:city":"Madrid",
    "sg:orig_category":"Centros Empresariales",
    "sg:phone":"+34 915 22 33 47",
    "sg:postcode":"28004",
    "sg:province":"Madrid",
    "wof:name":"Rsd Consultores S.l.",
    "wof:placetype":"venue"
},
  "geometry": {"coordinates":[-3.7006640434,40.4251976013],"type":"Point"}
}