{
  "type": "Feature",
  "properties": {
    "addr:full":"Calle de Kanttoipe, 2 Ondarroa Vizcaya 48700",
    "addr:housenumber":"2",
    "addr:postcode":"48700",
    "addr:street":"Calle De Kanttoipe",
    "iso:country":"ES",
    "sg:address":"Calle de Kanttoipe, 2",
    "sg:city":"Ondarroa",
    "sg:orig_category":"Telas Y Sedas (al Por Menor)",
    "sg:phone":"+34 946 83 01 84",
    "sg:postcode":"48700",
    "sg:province":"Vizcaya",
    "wof:name":"Cortazar Arriola Gorka",
    "wof:placetype":"venue"
},
  "geometry": {"coordinates":[-2.4206318855,43.3200035095],"type":"Point"}
}