{
  "type": "Feature",
  "properties": {
    "addr:full":"Calle de Padre Damian, 1 Madrid Madrid 28036",
    "addr:housenumber":"1",
    "addr:postcode":"28036",
    "addr:street":"Calle De Padre Damian",
    "iso:country":"ES",
    "sg:address":"Calle de Padre Damian, 1",
    "sg:city":"Madrid",
    "sg:orig_category":"Supermercados Y Hipermercados",
    "sg:phone":"+34 914 57 96 82",
    "sg:postcode":"28036",
    "sg:province":"Madrid",
    "wof:name":"Caprabo S.a.",
    "wof:placetype":"venue"
},
  "geometry": {"coordinates":[-3.6873021126,40.4542999268],"type":"Point"}
}