{
  "type": "Feature",
  "properties": {
    "addr:full":"Carrer de Montsia, 13 Poligono Industrial Can Carner Barcelona 08211",
    "addr:housenumber":"13",
    "addr:postcode":"08211",
    "addr:street":"Carrer De Montsia;Poligono Industrial",
    "iso:country":"ES",
    "sg:address":"Carrer de Montsia, 13",
    "sg:city":"Poligono Industrial Can Carner",
    "sg:orig_category":"Inform\u00c1tica (estudios, Servicios, Asesor\u00cda, Formaci\u00d3n)",
    "sg:phone":"+34 937 14 46 08",
    "sg:postcode":"08211",
    "sg:province":"Barcelona",
    "sg:website":"www.farmont.net",
    "wof:name":"Farmont S.l.",
    "wof:placetype":"venue"
},
  "geometry": {"coordinates":[2.0857300758,41.6151885986],"type":"Point"}
}