{
  "type": "Feature",
  "properties": {
    "iso:country":"ES",
    "sg:address":"Plaz Espa\u00d1a, 2",
    "sg:city":"Helechosa De Los Montes",
    "sg:orig_category":"Administraciones Regionales, Departamentales Y Locales",
    "sg:phone":"+34 924 65 80 11",
    "sg:postcode":"06692",
    "sg:province":"Badajoz",
    "wof:name":"Ayuntamiento De Helechosa De Los Montes",
    "wof:placetype":"venue"
},
  "geometry": {"coordinates":[-4.9061198235,39.3087997437],"type":"Point"}
}