{
  "type": "Feature",
  "properties": {
    "addr:full":"Carr Zaragoza, 21 Villarreal Castell\u00f3n 12540",
    "addr:housenumber":"21",
    "addr:postcode":"12540",
    "addr:street":"Carr Zaragoza",
    "iso:country":"ES",
    "sg:address":"Carr Zaragoza, 21",
    "sg:city":"Villarreal",
    "sg:orig_category":"Molduras, Junquillos, Listones Y Molduras Perforadas",
    "sg:phone":"+34 964 52 49 50",
    "sg:postcode":"12540",
    "sg:province":"Castell\u00f3n",
    "wof:name":"Punzano Fuentes Antonio",
    "wof:placetype":"venue"
},
  "geometry": {"coordinates":[-0.0952939987,39.9453048706],"type":"Point"}
}