{
  "type": "Feature",
  "properties": {
    "iso:country":"ES",
    "sg:address":"Avda Habaneras (de Las), 73",
    "sg:city":"Torrevieja",
    "sg:orig_category":"Abogados",
    "sg:phone":"+34 966 70 68 66",
    "sg:postcode":"03180",
    "sg:province":"Alicante",
    "wof:name":"Nicolas M. Mirete Ruiz-abogados C.b.",
    "wof:placetype":"venue"
},
  "geometry": {"coordinates":[-0.6703959703,37.9804458618],"type":"Point"}
}