{
  "type": "Feature",
  "properties": {
    "addr:full":"Calle de Ovalle, 29 Salamanca Salamanca 37004",
    "addr:housenumber":"29",
    "addr:postcode":"37004",
    "addr:street":"Calle De Ovalle",
    "iso:country":"ES",
    "sg:address":"Calle de Ovalle, 29",
    "sg:city":"Salamanca",
    "sg:orig_category":"Fabricantes De Vendas",
    "sg:phone":"+34 923 22 19 48",
    "sg:postcode":"37004",
    "sg:province":"Salamanca",
    "wof:name":"Araujo Calvo Maria",
    "wof:placetype":"venue"
},
  "geometry": {"coordinates":[-5.6547689438,40.9720458984],"type":"Point"}
}