{
  "type": "Feature",
  "properties": {
    "addr:full":"Pino Santo, 109 Tarazona Sevilla 41300",
    "addr:housenumber":"109",
    "addr:postcode":"41300",
    "addr:street":"Santo",
    "iso:country":"ES",
    "sg:address":"Pino Santo, 109",
    "sg:city":"Tarazona",
    "sg:orig_category":"Suministros Y Materiales Industriales",
    "sg:phone":"+34 954 68 70 16",
    "sg:postcode":"41300",
    "sg:province":"Sevilla",
    "sg:website":"www.spray-cas.com",
    "wof:name":"Spraying Systems Spain S.l.",
    "wof:placetype":"venue"
},
  "geometry": {"coordinates":[-5.9507889748,37.4823112488],"type":"Point"}
}