{
  "type": "Feature",
  "properties": {
    "iso:country":"ES",
    "sg:address":"Ctra Zafra, Km. 0003,5",
    "sg:city":"Fuente Maestre",
    "sg:orig_category":"Panader\u00cdas, Panader\u00cdas",
    "sg:phone":"+34 924 12 40 03",
    "sg:postcode":"06360",
    "sg:province":"Badajoz",
    "wof:name":"Union Panadera Cacere\u00f1a S.a.",
    "wof:placetype":"venue"
},
  "geometry": {"coordinates":[-6.442150116,38.5292739868],"type":"Point"}
}