{
  "type": "Feature",
  "properties": {
    "addr:full":"Calle de Garci-fernandez, 9 Huelva Huelva 21003",
    "addr:housenumber":"9",
    "addr:postcode":"21003",
    "addr:street":"Calle De Garci-Fernandez",
    "iso:country":"ES",
    "sg:address":"Calle de Garci-fernandez, 9",
    "sg:city":"Huelva",
    "sg:orig_category":"Centros Comerciales Y Grandes Tiendas",
    "sg:phone":"+34 959 28 13 36",
    "sg:postcode":"21003",
    "sg:province":"Huelva",
    "sg:website":"www.designersguild.com",
    "wof:name":"Rodobosa S.l.",
    "wof:placetype":"venue"
},
  "geometry": {"coordinates":[-6.948568821,37.2546157837],"type":"Point"}
}