{
  "type": "Feature",
  "properties": {
    "addr:full":"L'aguila, 1 Cala D'or Islas Baleares 07660",
    "addr:housenumber":"1",
    "addr:postcode":"07660",
    "addr:street":"L'Aguila",
    "iso:country":"ES",
    "sg:address":"L'aguila, 1",
    "sg:city":"Cala D'or",
    "sg:orig_category":"Promotores Constructores",
    "sg:phone":"+34 971 65 95 53",
    "sg:postcode":"07660",
    "sg:province":"Islas Baleares",
    "wof:name":"Servicios Residenciales Desanz Sl",
    "wof:placetype":"venue"
},
  "geometry": {"coordinates":[2.9117100239,39.6136398315],"type":"Point"}
}