{
  "type": "Feature",
  "properties": {
    "iso:country":"ES",
    "sg:address":"Pase Habana, 40",
    "sg:city":"Madrid",
    "sg:orig_category":"Ropa Para Se\u00d1oras Y Caballeros (al Por Menor)",
    "sg:phone":"+34 915 63 93 22",
    "sg:postcode":"28036",
    "sg:province":"Madrid",
    "sg:website":"www.massimodutti.com",
    "wof:name":"Grupo Massimo Dutti S A",
    "wof:placetype":"venue"
},
  "geometry": {"coordinates":[-3.6868960857,40.4506111145],"type":"Point"}
}