{
  "type": "Feature",
  "properties": {
    "iso:country":"ES",
    "sg:address":"Calle de Huerta, 25",
    "sg:city":"Illescas",
    "sg:orig_category":"Pirotecnia (espect\u00c1culos)",
    "sg:phone":"+34 925 51 17 23",
    "sg:postcode":"45200",
    "sg:province":"Toledo",
    "wof:name":"Pirotecnia Humanes S.l.",
    "wof:placetype":"venue"
},
  "geometry": {"coordinates":[-3.852298975,40.1270561218],"type":"Point"}
}