{
  "type": "Feature",
  "properties": {
    "iso:country":"ES",
    "sg:address":"Calle de Algaba, 10",
    "sg:city":"Madrid",
    "sg:orig_category":"Molduras, Junquillos, Listones Y Molduras Perforadas",
    "sg:phone":"+34 915 25 57 47",
    "sg:postcode":"28019",
    "sg:province":"Madrid",
    "wof:name":"Gonzalez Ramos Catalina",
    "wof:placetype":"venue"
},
  "geometry": {"coordinates":[-3.7379612923,40.3920249939],"type":"Point"}
}