{
  "type": "Feature",
  "properties": {
    "addr:full":"Calle de Santiago, 4 Madrid Madrid 28013",
    "addr:housenumber":"4",
    "addr:postcode":"28013",
    "addr:street":"Calle De Santiago",
    "iso:country":"ES",
    "sg:address":"Calle de Santiago, 4",
    "sg:city":"Madrid",
    "sg:orig_category":"Art\u00cdculos De Decoraci\u00d3n",
    "sg:phone":"+34 915 47 61 35",
    "sg:postcode":"28013",
    "sg:province":"Madrid",
    "sg:website":"www.victimasdelceluloide.com",
    "wof:name":"Lopez Fuentes Emelia",
    "wof:placetype":"venue"
},
  "geometry": {"coordinates":[-3.7097792625,40.4162025452],"type":"Point"}
}