{
  "type": "Feature",
  "properties": {
    "addr:full":"Carr Barranquet, 12 Moraira Alicante 03724",
    "addr:housenumber":"12",
    "addr:postcode":"03724",
    "addr:street":"Carr Barranquet",
    "iso:country":"ES",
    "sg:address":"Carr Barranquet, 12",
    "sg:city":"Moraira",
    "sg:orig_category":"Bazares, Art\u00cdculos De Limpieza Y De Cocina (al Por Menor)",
    "sg:phone":"+34 966 49 16 14",
    "sg:postcode":"03724",
    "sg:province":"Alicante",
    "wof:name":"Fullano Fullano Juan",
    "wof:placetype":"venue"
},
  "geometry": {"coordinates":[0.1258890033,38.6994819641],"type":"Point"}
}