{
  "type": "Feature",
  "properties": {
    "addr:full":"Carrer de Puig I Cadafalch, 59 Manresa Barcelona 08243",
    "addr:housenumber":"59",
    "addr:postcode":"08243",
    "addr:street":"Carrer De Puig;Cadafalch",
    "iso:country":"ES",
    "sg:address":"Carrer de Puig I Cadafalch, 59",
    "sg:city":"Manresa",
    "sg:orig_category":"Promotores Constructores",
    "sg:phone":"+34 938 73 38 66",
    "sg:postcode":"08243",
    "sg:province":"Barcelona",
    "wof:name":"Gallardo Zamora Antonio",
    "wof:placetype":"venue"
},
  "geometry": {"coordinates":[1.8448610306,41.7207489014],"type":"Point"}
}