{
  "type": "Feature",
  "properties": {
    "iso:country":"ES",
    "sg:address":"Avda Barcelona, 30",
    "sg:city":"Guadalajara",
    "sg:orig_category":"Ense\u00d1anza Variada",
    "sg:phone":"+34 949 21 64 34",
    "sg:postcode":"19005",
    "sg:province":"Guadalajara",
    "wof:name":"Amez Laiz Carlos",
    "wof:placetype":"venue"
},
  "geometry": {"coordinates":[-3.1572031975,40.6353874207],"type":"Point"}
}