{
  "type": "Feature",
  "properties": {
    "addr:full":"Calle de Cardenal Cisneros, 18 Alcala Guadaira Sevilla 41500",
    "addr:housenumber":"18",
    "addr:postcode":"41500",
    "addr:street":"Calle De Cardenal Cisneros",
    "iso:country":"ES",
    "sg:address":"Calle de Cardenal Cisneros, 18",
    "sg:city":"Alcala Guadaira",
    "sg:orig_category":"Revestimiento Para Suelos Y Paredes (al Por Mayor)",
    "sg:phone":"+34 955 68 70 94",
    "sg:postcode":"41500",
    "sg:province":"Sevilla",
    "sg:website":"www.decorstone.net",
    "wof:name":"Revestimientos Decor Stones S.l.",
    "wof:placetype":"venue"
},
  "geometry": {"coordinates":[-5.837290287,37.3349304199],"type":"Point"}
}