{
  "type": "Feature",
  "properties": {
    "addr:full":"Calle de Reina, 243 Valencia Valencia 46011",
    "addr:housenumber":"243",
    "addr:postcode":"46011",
    "addr:street":"Calle De Reina",
    "iso:country":"ES",
    "sg:address":"Calle de Reina, 243",
    "sg:city":"Valencia",
    "sg:orig_category":"Farmacias",
    "sg:phone":"+34 963 71 10 17",
    "sg:postcode":"46011",
    "sg:province":"Valencia",
    "wof:name":"Farmacia Pastor Morales C.b.",
    "wof:placetype":"venue"
},
  "geometry": {"coordinates":[-0.328083992,39.4734268188],"type":"Point"}
}