{
  "type": "Feature",
  "properties": {
    "addr:full":"Avda Martin Urrutia, 66 Oronoz Navarra 31720",
    "addr:housenumber":"66",
    "addr:postcode":"31720",
    "addr:street":"Avda Martin Urrutia",
    "iso:country":"ES",
    "sg:address":"Avda Martin Urrutia, 66",
    "sg:city":"Oronoz",
    "sg:orig_category":"Cester\u00cda (fabricaci\u00d3n)",
    "sg:phone":"+34 948 59 21 21",
    "sg:postcode":"31720",
    "sg:province":"Navarra",
    "wof:name":"Copropietarios Casa Balangoberri Ii N\u00ba66",
    "wof:placetype":"venue"
},
  "geometry": {"coordinates":[-1.6105240583,43.1424446106],"type":"Point"}
}