{
  "type": "Feature",
  "properties": {
    "addr:full":"Carrer de Palencia, 39 Barcelona Barcelona 08027",
    "addr:housenumber":"39",
    "addr:postcode":"08027",
    "addr:street":"Carrer De Palencia",
    "iso:country":"ES",
    "sg:address":"Carrer de Palencia, 39",
    "sg:city":"Barcelona",
    "sg:orig_category":"Cine (distribuci\u00d3n)",
    "sg:phone":"+34 934 08 18 54",
    "sg:postcode":"08027",
    "sg:province":"Barcelona",
    "wof:name":"Odalas Films S.a.",
    "wof:placetype":"venue"
},
  "geometry": {"coordinates":[2.1906731129,41.4185676575],"type":"Point"}
}