{
  "type": "Feature",
  "properties": {
    "addr:full":"Calle de Argumosa, 5 Madrid Madrid 28012",
    "addr:housenumber":"5",
    "addr:postcode":"28012",
    "addr:street":"Calle De Argumosa",
    "iso:country":"ES",
    "sg:address":"Calle de Argumosa, 5",
    "sg:city":"Madrid",
    "sg:orig_category":"Dibujantes (diversos)",
    "sg:phone":"+34 915 30 89 15",
    "sg:postcode":"28012",
    "sg:province":"Madrid",
    "wof:name":"Caracol Story Board S.l.",
    "wof:placetype":"venue"
},
  "geometry": {"coordinates":[-3.7000629902,40.4083404541],"type":"Point"}
}