{
  "type": "Feature",
  "properties": {
    "iso:country":"ES",
    "sg:address":"Calle de Miguel Servet, 106",
    "sg:city":"Zaragoza",
    "sg:orig_category":"Electricidad: Instaladores",
    "sg:phone":"+34 976 41 45 80",
    "sg:postcode":"50013",
    "sg:province":"Zaragoza",
    "wof:name":"Ortiz Lopez Eugenio",
    "wof:placetype":"venue"
},
  "geometry": {"coordinates":[-0.869426012,41.6433906555],"type":"Point"}
}