{
  "type": "Feature",
  "properties": {
    "addr:full":"Calle de Montevideo (de), S/n Jerez De La Frontera C\u00e1diz 11407",
    "addr:postcode":"11407",
    "addr:street":"Calle De Montevideo De S / N",
    "iso:country":"ES",
    "sg:address":"Calle de Montevideo (de), S/n",
    "sg:city":"Jerez De La Frontera",
    "sg:orig_category":"Farmacias",
    "sg:phone":"+34 956 30 84 11",
    "sg:postcode":"11407",
    "sg:province":"C\u00e1diz",
    "wof:name":"Mas Bernad Jose Antonio",
    "wof:placetype":"venue"
},
  "geometry": {"coordinates":[-6.1234660149,36.703918457],"type":"Point"}
}