{
  "type": "Feature",
  "properties": {
    "addr:full":"Carrer de Sant Bonaventura, 18 Sitges Barcelona 08870",
    "addr:housenumber":"18",
    "addr:postcode":"08870",
    "addr:street":"Carrer De Sant Bonaventura",
    "iso:country":"ES",
    "sg:address":"Carrer de Sant Bonaventura, 18",
    "sg:city":"Sitges",
    "sg:orig_category":"Hilaturas, Hilos Y Actividades Relacionadas",
    "sg:phone":"+34 938 94 64 66",
    "sg:postcode":"08870",
    "sg:province":"Barcelona",
    "wof:name":"Peilo  Ramon",
    "wof:placetype":"venue"
},
  "geometry": {"coordinates":[1.8073270321,41.2372817993],"type":"Point"}
}