{
  "type": "Feature",
  "properties": {
    "iso:country":"ES",
    "sg:address":"Calle de Tesifonte Gallego, 5",
    "sg:city":"Albacete",
    "sg:orig_category":"Inmobiliaria (agencias)",
    "sg:phone":"+34 967 21 22 26",
    "sg:postcode":"02002",
    "sg:province":"Albacete",
    "sg:website":"www.roan.es",
    "wof:name":"Asesoramiento Inmobiliario Roan S.a.",
    "wof:placetype":"venue"
},
  "geometry": {"coordinates":[-1.855342865,38.9928283691],"type":"Point"}
}