{
  "type": "Feature",
  "properties": {
    "addr:full":"Calle de Antonio Rodriguez Villa, 5 Madrid Madrid 28002",
    "addr:housenumber":"5",
    "addr:postcode":"28002",
    "addr:street":"Calle De Antonio Rodriguez Villa",
    "iso:country":"ES",
    "sg:address":"Calle de Antonio Rodriguez Villa, 5",
    "sg:city":"Madrid",
    "sg:orig_category":"Importaci\u00d3n",
    "sg:phone":"+34 915 15 94 14",
    "sg:postcode":"28002",
    "sg:province":"Madrid",
    "wof:name":"Blue Backing S.l.",
    "wof:placetype":"venue"
},
  "geometry": {"coordinates":[-3.681415081,40.4437294006],"type":"Point"}
}