{
  "type": "Feature",
  "properties": {
    "addr:full":"Carrer de L'estany, 15 Barcelona Barcelona 08038",
    "addr:housenumber":"15",
    "addr:postcode":"08038",
    "addr:street":"Carrer De L'Estany",
    "iso:country":"ES",
    "sg:address":"Carrer de L'estany, 15",
    "sg:city":"Barcelona",
    "sg:orig_category":"Fabricaci\u00d3n De Juegos Y Juguetes",
    "sg:phone":"+34 932 23 86 70",
    "sg:postcode":"08038",
    "sg:province":"Barcelona",
    "wof:name":"Automatic S.a.",
    "wof:placetype":"venue"
},
  "geometry": {"coordinates":[2.1407825947,41.3549079895],"type":"Point"}
}