{
  "type": "Feature",
  "properties": {
    "addr:full":"Av Alcoi, 6 Benidorm Alicante 03500",
    "addr:housenumber":"6",
    "addr:postcode":"03500",
    "addr:street":"Av Alcoi",
    "iso:country":"ES",
    "sg:address":"Av Alcoi, 6",
    "sg:city":"Benidorm",
    "sg:orig_category":"Caf\u00c9s, Bares, Cervecer\u00cdas",
    "sg:phone":"+34 965 86 65 56",
    "sg:postcode":"03500",
    "sg:province":"Alicante",
    "wof:name":"Mc Fauld  Richard",
    "wof:placetype":"venue"
},
  "geometry": {"coordinates":[-0.1255549937,38.5356559753],"type":"Point"}
}