{
  "type": "Feature",
  "properties": {
    "iso:country":"ES",
    "sg:address":"Playa O Puerto (celeiro), 12",
    "sg:city":"Viveiro",
    "sg:orig_category":"Distribuci\u00d3n De Petr\u00d3leo Y Derivados",
    "sg:phone":"+34 982 55 14 06",
    "sg:postcode":"27863",
    "sg:province":"Lugo",
    "wof:name":"Galipez S.l.",
    "wof:placetype":"venue"
},
  "geometry": {"coordinates":[-7.5347719193,43.6102027893],"type":"Point"}
}