{
  "type": "Feature",
  "properties": {
    "iso:country":"ES",
    "sg:address":"Avda San Antonio, 25",
    "sg:city":"Etxebarri",
    "sg:orig_category":"Peluquer\u00cdas, Peluquer\u00cda Mixta",
    "sg:phone":"+34 944 26 07 92",
    "sg:postcode":"48450",
    "sg:province":"Vizcaya",
    "wof:name":"Lorena Parre\u00f1o Fernandez",
    "wof:placetype":"venue"
},
  "geometry": {"coordinates":[-2.8852760792,43.2482910156],"type":"Point"}
}