{
  "type": "Feature",
  "properties": {
    "addr:full":"Calle de Antonio Lopez, 57 Madrid Madrid 28019",
    "addr:housenumber":"57",
    "addr:postcode":"madrid;28019",
    "addr:street":"Calle De Antonio Lopez",
    "iso:country":"ES",
    "sg:address":"Calle de Antonio Lopez, 57",
    "sg:city":"Madrid",
    "sg:orig_category":"Caf\u00c9s, Bares, Cervecer\u00cdas",
    "sg:phone":"+34 915 69 32 23",
    "sg:postcode":"28019",
    "sg:province":"Madrid",
    "wof:name":"Arnaldo Lopez Alejandro",
    "wof:placetype":"venue"
},
  "geometry": {"coordinates":[-3.7090895176,40.3945617676],"type":"Point"}
}