{
  "type": "Feature",
  "properties": {
    "iso:country":"ES",
    "sg:address":"Avda Aragon, 18",
    "sg:city":"Alca\u00f1iz",
    "sg:orig_category":"Pod\u00d3logos: Pedicuros",
    "sg:phone":"+34 978 83 56 65",
    "sg:postcode":"44600",
    "sg:province":"Teruel",
    "wof:name":"Navarro Felez Rafael",
    "wof:placetype":"venue"
},
  "geometry": {"coordinates":[-0.1298830062,41.0496559143],"type":"Point"}
}