{
  "type": "Feature",
  "properties": {
    "addr:full":"Calle de Reina Sofia, 34 Martos Ja\u00e9n 23600",
    "addr:housenumber":"34",
    "addr:postcode":"23600",
    "addr:street":"Calle De Reina Sofia;Jae\u0301N",
    "iso:country":"ES",
    "sg:address":"Calle de Reina Sofia, 34",
    "sg:city":"Martos",
    "sg:orig_category":"M\u00c9dicos: Medicina Del Trabajo",
    "sg:phone":"+34 953 70 07 27",
    "sg:postcode":"23600",
    "sg:province":"Ja\u00e9n",
    "wof:name":"Molina Martos Eduardo",
    "wof:placetype":"venue"
},
  "geometry": {"coordinates":[-3.9724390507,37.714389801],"type":"Point"}
}