{
  "type": "Feature",
  "properties": {
    "addr:full":"El Pedroso, S/n Cabra C\u00f3rdoba 14940",
    "addr:postcode":"14940",
    "addr:street":"El Pedroso S / N",
    "iso:country":"ES",
    "sg:address":"El Pedroso, S/n",
    "sg:city":"Cabra",
    "sg:orig_category":"Flores Y Plantas Naturales (al Por Mayor)",
    "sg:phone":"+34 957 52 08 84",
    "sg:postcode":"14940",
    "sg:province":"C\u00f3rdoba",
    "wof:name":"Jurado De La Rosa Jose",
    "wof:placetype":"venue"
},
  "geometry": {"coordinates":[-4.438999176,37.4669494629],"type":"Point"}
}