{
  "type": "Feature",
  "properties": {
    "addr:full":"Carrer de Antonio Machado, 18 Barcelona Barcelona 08042",
    "addr:housenumber":"18",
    "addr:postcode":"08042",
    "addr:street":"Carrer De Antonio Machado",
    "iso:country":"ES",
    "sg:address":"Carrer de Antonio Machado, 18",
    "sg:city":"Barcelona",
    "sg:orig_category":"\u00d3ptica: Instrumentos (fabricaci\u00d3n)",
    "sg:phone":"+34 934 27 24 95",
    "sg:postcode":"08042",
    "sg:province":"Barcelona",
    "wof:name":"Brio Guibernau Montserrat",
    "wof:placetype":"venue"
},
  "geometry": {"coordinates":[2.1683540344,41.4434738159],"type":"Point"}
}