{
  "type": "Feature",
  "properties": {
    "iso:country":"ES",
    "sg:address":"Carr Barceloneta, 20",
    "sg:city":"Rapita",
    "sg:orig_category":"Producci\u00d3n De Abonos Y De Fertilizantes",
    "sg:phone":"+34 973 44 69 04",
    "sg:postcode":"25617",
    "sg:province":"Lleida",
    "wof:name":"Agrometodos S. A.",
    "wof:placetype":"venue"
},
  "geometry": {"coordinates":[0.844905,41.7827],"type":"Point"}
}