{
  "type": "Feature",
  "properties": {
    "addr:full":"Calle de Ingeniero Mari\u00d1o, 48 Guadalajara Guadalajara 19001",
    "addr:housenumber":"48",
    "addr:postcode":"19001",
    "addr:street":"Calle De Ingeniero Marin\u0303O",
    "iso:country":"ES",
    "sg:address":"Calle de Ingeniero Mari\u00d1o, 48",
    "sg:city":"Guadalajara",
    "sg:orig_category":"Material Y Herramientas Agr\u00cdcolas",
    "sg:phone":"+34 949 21 78 01",
    "sg:postcode":"19001",
    "sg:province":"Guadalajara",
    "wof:name":"Oca\u00f1a Lopez Jose Luis",
    "wof:placetype":"venue"
},
  "geometry": {"coordinates":[-3.166738987,40.6360702515],"type":"Point"}
}