{
  "type": "Feature",
  "properties": {
    "iso:country":"ES",
    "sg:address":"Carrer de Mercat, S/n",
    "sg:city":"S. Just Desvern",
    "sg:orig_category":"Poller\u00cda Y Caza (al Por Menor)",
    "sg:phone":"+34 934 73 03 28",
    "sg:postcode":"08960",
    "sg:province":"Barcelona",
    "wof:name":"Gomez Revilla Galo",
    "wof:placetype":"venue"
},
  "geometry": {"coordinates":[2.0774970055,41.3844451904],"type":"Point"}
}