{
  "type": "Feature",
  "properties": {
    "addr:full":"Avda Principe De Espa\u00d1a, 11 San Felipe Santa Cruz De Tenerife 38430",
    "addr:housenumber":"11",
    "addr:postcode":"38430",
    "addr:street":"Avda Principe De Espan\u0303A",
    "iso:country":"ES",
    "sg:address":"Avda Principe De Espa\u00d1a, 11",
    "sg:city":"San Felipe",
    "sg:orig_category":"Supermercados Y Hipermercados",
    "sg:phone":"+34 922 12 14 82",
    "sg:postcode":"38430",
    "sg:province":"Santa Cruz De Tenerife",
    "sg:website":"www.mercadona.es",
    "wof:name":"Mercadona S.a.",
    "wof:placetype":"venue"
},
  "geometry": {"coordinates":[-16.7110748291,28.3711853027],"type":"Point"}
}