{
  "type": "Feature",
  "properties": {
    "addr:full":"Carrer de Pujos, 34 Hospitalet Llobregat Barcelona 08904",
    "addr:housenumber":"34",
    "addr:postcode":"08904",
    "addr:street":"Carrer De Pujos",
    "iso:country":"ES",
    "sg:address":"Carrer de Pujos, 34",
    "sg:city":"Hospitalet Llobregat",
    "sg:orig_category":"Cajas De Ahorro",
    "sg:phone":"+34 933 33 78 83",
    "sg:postcode":"08904",
    "sg:province":"Barcelona",
    "wof:name":"Caixa D'estalvis Laietana",
    "wof:placetype":"venue"
},
  "geometry": {"coordinates":[2.1186199188,41.3734855652],"type":"Point"}
}