{
  "type": "Feature",
  "properties": {
    "addr:full":"Avda Oasis, 103 Ejido Almer\u00eda 04700",
    "addr:housenumber":"103",
    "addr:postcode":"04700",
    "addr:street":"Avda Oasis;Ejido Almeri\u0301A",
    "iso:country":"ES",
    "sg:address":"Avda Oasis, 103",
    "sg:city":"Ejido",
    "sg:orig_category":"Cl\u00cdnicas Dentales",
    "sg:phone":"+34 950 57 01 69",
    "sg:postcode":"04700",
    "sg:province":"Almer\u00eda",
    "wof:name":"Clinica Dental Doctor Caba S.l.",
    "wof:placetype":"venue"
},
  "geometry": {"coordinates":[-2.8010311127,36.7689781189],"type":"Point"}
}