{
  "type": "Feature",
  "properties": {
    "iso:country":"ES",
    "sg:address":"Carrer de Corderia, 17",
    "sg:city":"Palma",
    "sg:orig_category":"Zapater\u00cds Y Cordeler\u00cda",
    "sg:phone":"+34 971 72 42 77",
    "sg:postcode":"07002",
    "sg:province":"Islas Baleares",
    "wof:name":"Bernat Palou Juan",
    "wof:placetype":"venue"
},
  "geometry": {"coordinates":[2.6529319286,39.5705108643],"type":"Point"}
}