{
  "type": "Feature",
  "properties": {
    "addr:full":"Ctra Arnedo, 1 Quel La Rioja 26570",
    "addr:housenumber":"1",
    "addr:postcode":"26570",
    "addr:street":"Ctra Arnedo;Rioja",
    "iso:country":"ES",
    "sg:address":"Ctra Arnedo, 1",
    "sg:city":"Quel",
    "sg:orig_category":"Productores Recolectores, Venta Directa De Vinos",
    "sg:phone":"+34 941 39 23 75",
    "sg:postcode":"26570",
    "sg:province":"La Rioja",
    "sg:website":"www.bodegasontanon.com",
    "wof:name":"Bodegas Onta\u00f1on S.a.",
    "wof:placetype":"venue"
},
  "geometry": {"coordinates":[-2.0563650131,42.233341217],"type":"Point"}
}