{
  "type": "Feature",
  "properties": {
    "iso:country":"ES",
    "sg:address":"Calle de Castro Urdiales, 5",
    "sg:city":"Vitoria-gasteiz",
    "sg:orig_category":"Textil",
    "sg:phone":"+34 945 23 22 84",
    "sg:postcode":"01006",
    "sg:province":"\u00c1lava",
    "wof:name":"Almacenes Barrio Textiles 2000 S.l.",
    "wof:placetype":"venue"
},
  "geometry": {"coordinates":[-2.6655480862,42.8390884399],"type":"Point"}
}