{
  "type": "Feature",
  "properties": {
    "iso:country":"ES",
    "sg:address":"Av Pais Valencia, 11",
    "sg:city":"Alcoi",
    "sg:orig_category":"Tapiceros Y Tapiceros",
    "sg:phone":"+34 965 54 35 58",
    "sg:postcode":"03801",
    "sg:province":"Alicante",
    "wof:name":"Perez Monzo Angel Antonio",
    "wof:placetype":"venue"
},
  "geometry": {"coordinates":[-0.4754790068,38.6968765259],"type":"Point"}
}