{
  "type": "Feature",
  "properties": {
    "iso:country":"ES",
    "sg:address":"Calle de Sal, 2",
    "sg:city":"Madrid",
    "sg:orig_category":"Carnicer\u00cdas, Carnicer\u00cdas",
    "sg:phone":"+34 913 66 42 69",
    "sg:postcode":"28012",
    "sg:province":"Madrid",
    "wof:name":"Bartolome Alvarado Juan Manuel",
    "wof:placetype":"venue"
},
  "geometry": {"coordinates":[-3.706496954,40.4158821106],"type":"Point"}
}