{
  "type": "Feature",
  "properties": {
    "iso:country":"ES",
    "sg:address":"Calle de Pantano De Camarillas, 13",
    "sg:city":"Santa Maria De Gracia",
    "sg:orig_category":"Quincaller\u00cda (al Por Menor)",
    "sg:phone":"+34 968 29 98 15",
    "sg:postcode":"30009",
    "sg:province":"Murcia",
    "wof:name":"Gomez Martinez Pedro",
    "wof:placetype":"venue"
},
  "geometry": {"coordinates":[-1.1383689642,37.9936294556],"type":"Point"}
}