{
  "type": "Feature",
  "properties": {
    "addr:full":"Calle de Matadero, 46 Coru\u00d1a La Coru\u00f1a 15002",
    "addr:housenumber":"46",
    "addr:postcode":"15002",
    "addr:street":"Calle De Matadero;Corun\u0303A",
    "iso:country":"ES",
    "sg:address":"Calle de Matadero, 46",
    "sg:city":"Coru\u00d1a",
    "sg:orig_category":"Farmacias",
    "sg:phone":"+34 981 20 51 13",
    "sg:postcode":"15002",
    "sg:province":"La Coru\u00f1a",
    "wof:name":"Brion Diaz Maria De La Soledad",
    "wof:placetype":"venue"
},
  "geometry": {"coordinates":[-8.4041481018,43.3762168884],"type":"Point"}
}