{
  "type": "Feature",
  "properties": {
    "iso:country":"ES",
    "sg:address":"Avda Rabanales (de), 33",
    "sg:city":"Cordoba",
    "sg:orig_category":"Caf\u00c9s, Bares, Cervecer\u00cdas",
    "sg:phone":"+34 957 43 94 51",
    "sg:postcode":"14007",
    "sg:province":"C\u00f3rdoba",
    "wof:name":"Cafeteria Patricia S.l.",
    "wof:placetype":"venue"
},
  "geometry": {"coordinates":[-4.7574491501,37.8946113586],"type":"Point"}
}