{
  "type": "Feature",
  "properties": {
    "iso:country":"ES",
    "sg:address":"Calle de Norte, 16",
    "sg:city":"Pozuelo De Alarcon",
    "sg:orig_category":"Molduras, Junquillos, Listones Y Molduras Perforadas",
    "sg:phone":"+34 917 15 36 58",
    "sg:postcode":"28223",
    "sg:province":"Madrid",
    "wof:name":"Espiguz S.l.l",
    "wof:placetype":"venue"
},
  "geometry": {"coordinates":[-3.8146209717,40.4364471436],"type":"Point"}
}