{
  "type": "Feature",
  "properties": {
    "iso:country":"ES",
    "sg:address":"Calle de Rufino Ruiz Ceballos (malia\u00d1o), 1",
    "sg:city":"Malia\u00d1o",
    "sg:orig_category":"Transportes Por Carretera: Lotes Completos, Mercanc\u00cdas Diversas",
    "sg:phone":"+34 942 25 21 61",
    "sg:postcode":"39600",
    "sg:province":"Cantabria",
    "wof:name":"Gonzalez Gonzalez Jose Aquilino",
    "wof:placetype":"venue"
},
  "geometry": {"coordinates":[-3.8426980972,43.4236183167],"type":"Point"}
}