{
  "type": "Feature",
  "properties": {
    "iso:country":"ES",
    "sg:address":"Calle de Estacion, 2",
    "sg:city":"Mendavia",
    "sg:orig_category":"Internados & Ense\u00d1anza Privada",
    "sg:phone":"+34 948 68 50 63",
    "sg:postcode":"31587",
    "sg:province":"Navarra",
    "wof:name":"Hospital Colegio De Nuestra Se\u00f1ora De Los Dolores",
    "wof:placetype":"venue"
},
  "geometry": {"coordinates":[-2.1992909908,42.4436950684],"type":"Point"}
}