{
  "type": "Feature",
  "properties": {
    "addr:full":"Calle de Lujan Perez, 54 Palmas De Gran Canaria Las Palmas 35009",
    "addr:postcode":"35009",
    "addr:street":"Calle De Lujan Perez 54",
    "iso:country":"ES",
    "sg:address":"Calle de Lujan Perez, 54",
    "sg:city":"Palmas De Gran Canaria",
    "sg:orig_category":"Ense\u00d1anza: Profesiones Art\u00cdsticas",
    "sg:phone":"+34 928 46 40 20",
    "sg:postcode":"35009",
    "sg:province":"Las Palmas",
    "wof:name":"Mendoza Mendoza Gonzalo",
    "wof:placetype":"venue"
},
  "geometry": {"coordinates":[-15.4300041199,28.1504211426],"type":"Point"}
}