{
  "type": "Feature",
  "properties": {
    "addr:full":"Calle de Eduardo Vela, 17 Madrid Madrid 28023",
    "addr:housenumber":"17",
    "addr:postcode":"madrid;28023",
    "addr:street":"Calle De Eduardo Vela",
    "iso:country":"ES",
    "sg:address":"Calle de Eduardo Vela, 17",
    "sg:city":"Madrid",
    "sg:orig_category":"Electricidad: Instaladores",
    "sg:phone":"+34 913 57 92 10",
    "sg:postcode":"28023",
    "sg:province":"Madrid",
    "wof:name":"Electromecanica Regacho S.a.",
    "wof:placetype":"venue"
},
  "geometry": {"coordinates":[-3.7778398991,40.4616928101],"type":"Point"}
}