{
  "type": "Feature",
  "properties": {
    "addr:full":"Calle de Palomar, S/n Celadas Teruel 44194",
    "addr:postcode":"44194",
    "addr:street":"Calle De Palomar S / N",
    "iso:country":"ES",
    "sg:address":"Calle de Palomar, S/n",
    "sg:city":"Celadas",
    "sg:orig_category":"Cajas De Ahorro",
    "sg:phone":"+34 978 65 21 50",
    "sg:postcode":"44194",
    "sg:province":"Teruel",
    "wof:name":"Caja De Ahorros Y Monte De Piedad De Zaragoza Aragon Y Rioja",
    "wof:placetype":"venue"
},
  "geometry": {"coordinates":[-1.1501040459,40.4734344482],"type":"Point"}
}