{
  "type": "Feature",
  "properties": {
    "iso:country":"ES",
    "sg:address":"Calle de Parador Del Sol, 4",
    "sg:city":"Madrid",
    "sg:orig_category":"Peluqueros: De Se\u00d1oras",
    "sg:phone":"+34 914 60 26 30",
    "sg:postcode":"28019",
    "sg:province":"Madrid",
    "wof:name":"Trenas Guzman Ricardo",
    "wof:placetype":"venue"
},
  "geometry": {"coordinates":[-3.7091379166,40.3940429688],"type":"Point"}
}