{
  "type": "Feature",
  "properties": {
    "iso:country":"ES",
    "sg:address":"Avda Marques De Sotelo, 4",
    "sg:city":"Valencia",
    "sg:orig_category":"Arquitectos",
    "sg:phone":"+34 963 51 69 61",
    "sg:postcode":"46002",
    "sg:province":"Valencia",
    "wof:name":"Peiro Alonso Jose Esteban",
    "wof:placetype":"venue"
},
  "geometry": {"coordinates":[-0.3770709932,39.4689025879],"type":"Point"}
}