{
  "type": "Feature",
  "properties": {
    "iso:country":"ES",
    "sg:address":"Rond San Lorenzo, 4",
    "sg:city":"Melilla",
    "sg:orig_category":"Asesor\u00cda Fiscal Y Jur\u00cddica",
    "sg:phone":"+34 952 67 73 90",
    "sg:postcode":"52006",
    "sg:province":"Melilla",
    "wof:name":"Melilla Asesores Y Abogados S.l.",
    "wof:placetype":"venue"
},
  "geometry": {"coordinates":[-2.9383699894,35.2764587402],"type":"Point"}
}