{
  "type": "Feature",
  "properties": {
    "iso:country":"ES",
    "sg:address":"Calle de Marques De Pontejos, 8",
    "sg:city":"Coru\u00d1a",
    "sg:orig_category":"Agentes Generales De Seguros",
    "sg:phone":"+34 981 21 61 90",
    "sg:postcode":"15001",
    "sg:province":"La Coru\u00f1a",
    "wof:name":"Iglesias Martelo Luis",
    "wof:placetype":"venue"
},
  "geometry": {"coordinates":[-8.3988628387,43.3720321655],"type":"Point"}
}