{
  "type": "Feature",
  "properties": {
    "addr:full":"Calle de Marques De La Romana, 6 Guadalupe C\u00e1ceres 10140",
    "addr:housenumber":"6",
    "addr:postcode":"10140",
    "addr:street":"Calle De Marques De La Romana;Ca\u0301Ceres",
    "iso:country":"ES",
    "sg:address":"Calle de Marques De La Romana, 6",
    "sg:city":"Guadalupe",
    "sg:orig_category":"Artesan\u00cda Y Trabajos Manuales: Suministros (al Por Menor)",
    "sg:phone":"+34 927 15 43 21",
    "sg:postcode":"10140",
    "sg:province":"C\u00e1ceres",
    "wof:name":"Fuentes Carpallo Maria Del Carmen",
    "wof:placetype":"venue"
},
  "geometry": {"coordinates":[-5.3263969421,39.45287323],"type":"Point"}
}