{
  "type": "Feature",
  "properties": {
    "addr:full":"Calle de Padre Luis, 101 Santos De Maimona Badajoz 06230",
    "addr:housenumber":"101",
    "addr:postcode":"06230",
    "addr:street":"Calle De Padre Luis",
    "iso:country":"ES",
    "sg:address":"Calle de Padre Luis, 101",
    "sg:city":"Santos De Maimona",
    "sg:orig_category":"Cl\u00cdnicas Dentales",
    "sg:phone":"+34 924 54 49 58",
    "sg:postcode":"06230",
    "sg:province":"Badajoz",
    "wof:name":"Nazir Ismael Mohamed",
    "wof:placetype":"venue"
},
  "geometry": {"coordinates":[-6.3867087364,38.4496421814],"type":"Point"}
}