{
  "type": "Feature",
  "properties": {
    "iso:country":"ES",
    "sg:address":"Calle de Andra Mari, 1",
    "sg:city":"Muntsaratz",
    "sg:orig_category":"Maquinaria Para Industrias Diversas",
    "sg:phone":"+34 946 81 66 05",
    "sg:postcode":"48220",
    "sg:province":"Vizcaya",
    "wof:name":"Excavaciones Idirin S.l.",
    "wof:placetype":"venue"
},
  "geometry": {"coordinates":[-2.605840683,43.1458129883],"type":"Point"}
}