{
  "type": "Feature",
  "properties": {
    "addr:full":"Calle de Coca De La Pi\u00d1era, 6 Moron Frontera Sevilla 41530",
    "addr:housenumber":"6",
    "addr:postcode":"41530",
    "addr:street":"Calle De Coca De La Pin\u0303Era",
    "iso:country":"ES",
    "sg:address":"Calle de Coca De La Pi\u00d1era, 6",
    "sg:city":"Moron Frontera",
    "sg:orig_category":"Venta, Montaje De Neum\u00c1ticos",
    "sg:phone":"+34 954 85 15 06",
    "sg:postcode":"41530",
    "sg:province":"Sevilla",
    "wof:name":"Lopez Vega S.l.",
    "wof:placetype":"venue"
},
  "geometry": {"coordinates":[-5.4490542412,37.1275215149],"type":"Point"}
}