{
  "type": "Feature",
  "properties": {
    "iso:country":"ES",
    "sg:address":"Calle de Micaela Portilla, 3",
    "sg:city":"Vitoria-gasteiz",
    "sg:orig_category":"Cl\u00cdnicas Dentales",
    "sg:phone":"+34 945 14 51 14",
    "sg:postcode":"01008",
    "sg:province":"\u00c1lava",
    "wof:name":"Voltas Jurado Pablo",
    "wof:placetype":"venue"
},
  "geometry": {"coordinates":[-2.6826090813,42.8435783386],"type":"Point"}
}