{
  "type": "Feature",
  "properties": {
    "addr:full":"Ctra Tordesillas, 13 Toro Zamora 49800",
    "addr:housenumber":"13",
    "addr:postcode":"49800",
    "addr:street":"Ctra Tordesillas",
    "iso:country":"ES",
    "sg:address":"Ctra Tordesillas, 13",
    "sg:city":"Toro",
    "sg:orig_category":"Productores Recolectores, Venta Directa De Vinos",
    "sg:phone":"+34 980 69 03 47",
    "sg:postcode":"49800",
    "sg:province":"Zamora",
    "sg:website":"www.covitoro.com",
    "wof:name":"Bodega Cooperativa Vino De Toro",
    "wof:placetype":"venue"
},
  "geometry": {"coordinates":[-5.3810381889,41.5245513916],"type":"Point"}
}