{
  "type": "Feature",
  "properties": {
    "addr:full":"Calle de Soledad, 14 Barrios C\u00e1diz 11370",
    "addr:housenumber":"14",
    "addr:postcode":"11370",
    "addr:street":"Calle De Soledad;Ca\u0301Diz",
    "iso:country":"ES",
    "sg:address":"Calle de Soledad, 14",
    "sg:city":"Barrios",
    "sg:orig_category":"Reposter\u00cdas",
    "sg:phone":"+34 956 62 00 93",
    "sg:postcode":"11370",
    "sg:province":"C\u00e1diz",
    "wof:name":"Panaderia Hermanos Espinosa S.l.",
    "wof:placetype":"venue"
},
  "geometry": {"coordinates":[-5.4935631752,36.18384552],"type":"Point"}
}