{
  "type": "Feature",
  "properties": {
    "addr:full":"Rajolar, 3 Beniparrell Valencia 46469",
    "addr:housenumber":"3",
    "addr:postcode":"46469",
    "addr:street":"Rajolar",
    "iso:country":"ES",
    "sg:address":"Rajolar, 3",
    "sg:city":"Beniparrell",
    "sg:orig_category":"Edici\u00d3n De Diarios, Revistas, Boletines",
    "sg:phone":"+34 961 21 28 51",
    "sg:postcode":"46469",
    "sg:province":"Valencia",
    "wof:name":"C3m Textil Editores S.a.u.",
    "wof:placetype":"venue"
},
  "geometry": {"coordinates":[-0.4154820144,39.38489151],"type":"Point"}
}