{
  "type": "Feature",
  "properties": {
    "addr:full":"Calle de Alvarez Quintero, 22 Barrax Albacete 02639",
    "addr:housenumber":"22",
    "addr:postcode":"02639",
    "addr:street":"Calle De Alvarez Quintero",
    "iso:country":"ES",
    "sg:address":"Calle de Alvarez Quintero, 22",
    "sg:city":"Barrax",
    "sg:orig_category":"Molduras, Junquillos, Listones Y Molduras Perforadas",
    "sg:phone":"+34 967 36 45 48",
    "sg:postcode":"02639",
    "sg:province":"Albacete",
    "wof:name":"Garrido Cano Francisco",
    "wof:placetype":"venue"
},
  "geometry": {"coordinates":[-2.2011852264,39.0429916382],"type":"Point"}
}