{
  "type": "Feature",
  "properties": {
    "iso:country":"ES",
    "sg:address":"Calle de Santa Ana, 1",
    "sg:city":"Dos Hermanas",
    "sg:orig_category":"Obras Y Organismos Sociales",
    "sg:phone":"+34 955 66 91 60",
    "sg:postcode":"41700",
    "sg:province":"Sevilla",
    "wof:name":"Reverendas Dominicas Santisimo Sacrament",
    "wof:placetype":"venue"
},
  "geometry": {"coordinates":[-5.9210300446,37.2836112976],"type":"Point"}
}