{
  "type": "Feature",
  "properties": {
    "iso:country":"ES",
    "sg:address":"C/ Rutlla, 1",
    "sg:city":"Calonge",
    "sg:orig_category":"Molduras, Junquillos, Listones Y Molduras Perforadas",
    "sg:phone":"+34 972 65 24 30",
    "sg:postcode":"17251",
    "sg:province":"Girona",
    "wof:name":"Larrosa Lucena Antonio",
    "wof:placetype":"venue"
},
  "geometry": {"coordinates":[3.0742809772,41.8617172241],"type":"Point"}
}