{
  "type": "Feature",
  "properties": {
    "addr:full":"Calle de Calixto Iii, 8 Valencia Valencia 46008",
    "addr:housenumber":"8",
    "addr:postcode":"46008",
    "addr:street":"Calle De Calixto Iii",
    "iso:country":"ES",
    "sg:address":"Calle de Calixto Iii, 8",
    "sg:city":"Valencia",
    "sg:orig_category":"Molduras, Junquillos, Listones Y Molduras Perforadas",
    "sg:phone":"+34 963 84 30 57",
    "sg:postcode":"46008",
    "sg:province":"Valencia",
    "wof:name":"Bazan Garcia Benito",
    "wof:placetype":"venue"
},
  "geometry": {"coordinates":[-0.3886190057,39.4715766907],"type":"Point"}
}