{
  "type": "Feature",
  "properties": {
    "iso:country":"ES",
    "sg:address":"Carrer de Tortora, 20",
    "sg:city":"Can Palet De Vista Alegre",
    "sg:orig_category":"Promotores Constructores",
    "sg:phone":"+34 937 80 15 86",
    "sg:postcode":"08224",
    "sg:province":"Barcelona",
    "wof:name":"Reformas Y Construcciones Borrallo Sll",
    "wof:placetype":"venue"
},
  "geometry": {"coordinates":[1.9906500578,41.5405235291],"type":"Point"}
}