{
  "type": "Feature",
  "properties": {
    "addr:full":"Calle de Marques De Pickman, 51 Sevilla Sevilla 41005",
    "addr:housenumber":"51",
    "addr:postcode":"41005",
    "addr:street":"Calle De Marques De Pickman",
    "iso:country":"ES",
    "sg:address":"Calle de Marques De Pickman, 51",
    "sg:city":"Sevilla",
    "sg:orig_category":"Reposter\u00cdas",
    "sg:phone":"+34 954 58 07 04",
    "sg:postcode":"41005",
    "sg:province":"Sevilla",
    "wof:name":"Mendoza Catalu\u00f1a Ildefonso",
    "wof:placetype":"venue"
},
  "geometry": {"coordinates":[-5.9612550735,37.3812446594],"type":"Point"}
}