{
  "type": "Feature",
  "properties": {
    "iso:country":"ES",
    "sg:address":"Calle de Leganes, 1",
    "sg:city":"Getafe",
    "sg:orig_category":"Bancos",
    "sg:phone":"+34 916 65 25 04",
    "sg:postcode":"28901",
    "sg:province":"Madrid",
    "sg:website":"www.cajadeextremadura.es",
    "wof:name":"Caja De Ahorros Y Monte De Piedad De Extremadura",
    "wof:placetype":"venue"
},
  "geometry": {"coordinates":[-3.7311530113,40.3063468933],"type":"Point"}
}