{
  "type": "Feature",
  "properties": {
    "addr:full":"Calle de Matadero, 2 Hinojos Huelva 21740",
    "addr:housenumber":"2",
    "addr:postcode":"21740",
    "addr:street":"Calle De Matadero",
    "iso:country":"ES",
    "sg:address":"Calle de Matadero, 2",
    "sg:city":"Hinojos",
    "sg:orig_category":"Fabricaci\u00d3n De Muebles",
    "sg:phone":"+34 959 45 99 17",
    "sg:postcode":"21740",
    "sg:province":"Huelva",
    "wof:name":"Muebles Soledad De Hinojos S.l.",
    "wof:placetype":"venue"
},
  "geometry": {"coordinates":[-6.3752970695,37.2929878235],"type":"Point"}
}