{
  "type": "Feature",
  "properties": {
    "iso:country":"ES",
    "sg:address":"Carr Bonaire, 36",
    "sg:city":"Binissalem",
    "sg:orig_category":"Quincaller\u00cda (al Por Menor)",
    "sg:phone":"+34 971 88 66 08",
    "sg:postcode":"07350",
    "sg:province":"Islas Baleares",
    "wof:name":"Ferreteria Binissalem",
    "wof:placetype":"venue"
},
  "geometry": {"coordinates":[2.8455410004,39.6860847473],"type":"Point"}
}