{
  "type": "Feature",
  "properties": {
    "addr:full":"Poligon Industrial Ford, S/n Almussafes Valencia 46440",
    "addr:housenumber":"s / n",
    "addr:postcode":"46440",
    "iso:country":"ES",
    "sg:address":"Poligon Industrial Ford, S/n",
    "sg:city":"Almussafes",
    "sg:orig_category":"Construcciones Met\u00c1licas",
    "sg:phone":"+34 961 78 09 65",
    "sg:postcode":"46440",
    "sg:province":"Valencia",
    "sg:website":"www.villajos.com",
    "wof:name":"Talleres A.villajos S.l.",
    "wof:placetype":"venue"
},
  "geometry": {"coordinates":[-0.4122039974,39.2929763794],"type":"Point"}
}