{
  "type": "Feature",
  "properties": {
    "iso:country":"ES",
    "sg:address":"Rua Millara (da), 10",
    "sg:city":"Lugo",
    "sg:orig_category":"Expertos Contables, Revisores De Cuentas",
    "sg:phone":"+34 982 25 03 88",
    "sg:postcode":"27002",
    "sg:province":"Lugo",
    "wof:name":"Jarabo Esteban Ernesto",
    "wof:placetype":"venue"
},
  "geometry": {"coordinates":[-7.557656765,42.9934539795],"type":"Point"}
}