{
  "type": "Feature",
  "properties": {
    "addr:full":"Carr Santa Eugenia, 32 Girona Girona 17005",
    "addr:housenumber":"32",
    "addr:postcode":"17005",
    "addr:street":"Carr Santa Eugenia",
    "iso:country":"ES",
    "sg:address":"Carr Santa Eugenia, 32",
    "sg:city":"Girona",
    "sg:orig_category":"Carnicer\u00cdas, Carnicer\u00cdas",
    "sg:phone":"+34 972 21 69 71",
    "sg:postcode":"17005",
    "sg:province":"Girona",
    "wof:name":"Girobur S.c.",
    "wof:placetype":"venue"
},
  "geometry": {"coordinates":[2.8172659874,41.9818153381],"type":"Point"}
}