{
  "type": "Feature",
  "properties": {
    "iso:country":"ES",
    "sg:address":"Av Isidor Macabich, S/n",
    "sg:city":"Eivissa",
    "sg:orig_category":"Peleter\u00cdas",
    "sg:phone":"+34 971 30 33 18",
    "sg:postcode":"07800",
    "sg:province":"Islas Baleares",
    "wof:name":"Mari Roig Antonio",
    "wof:placetype":"venue"
},
  "geometry": {"coordinates":[1.423879981,38.9095001221],"type":"Point"}
}