{
  "type": "Feature",
  "properties": {
    "addr:full":"Avda Madrid, 40 Laguna Duero Valladolid 47140",
    "addr:housenumber":"40",
    "addr:postcode":"47140",
    "addr:street":"Avda Madrid",
    "iso:country":"ES",
    "sg:address":"Avda Madrid, 40",
    "sg:city":"Laguna Duero",
    "sg:orig_category":"Reposter\u00cdas",
    "sg:phone":"+34 983 54 25 78",
    "sg:postcode":"47140",
    "sg:province":"Valladolid",
    "wof:name":"Arribas Doncel S.l",
    "wof:placetype":"venue"
},
  "geometry": {"coordinates":[-4.726395607,41.6157798767],"type":"Point"}
}