{
  "type": "Feature",
  "properties": {
    "iso:country":"ES",
    "sg:address":"Calle de Don Pedro Infinito, 14",
    "sg:city":"Palmas De Gran Canaria",
    "sg:orig_category":"Supermercados Y Hipermercados",
    "sg:phone":"+34 928 25 52 42",
    "sg:postcode":"35012",
    "sg:province":"Las Palmas",
    "wof:name":"Rancho Gloria S.l.",
    "wof:placetype":"venue"
},
  "geometry": {"coordinates":[-15.4305505753,28.110868454],"type":"Point"}
}