{
  "type": "Feature",
  "properties": {
    "addr:full":"Calle de Caridad, 20 Hinojosa Del Duque C\u00f3rdoba 14270",
    "addr:housenumber":"20",
    "addr:postcode":"14270",
    "addr:street":"Calle De Caridad;Co\u0301Rdoba",
    "iso:country":"ES",
    "sg:address":"Calle de Caridad, 20",
    "sg:city":"Hinojosa Del Duque",
    "sg:orig_category":"Comercio, Reparaci\u00d3n De Motocicletas, Bicicletas Y Piezas Sueltas",
    "sg:phone":"+34 957 14 07 75",
    "sg:postcode":"14270",
    "sg:province":"C\u00f3rdoba",
    "wof:name":"Jurado Gomez Juan Jesus",
    "wof:placetype":"venue"
},
  "geometry": {"coordinates":[-5.1458516121,38.5012283325],"type":"Point"}
}