{
  "type": "Feature",
  "properties": {
    "iso:country":"ES",
    "sg:address":"Calle de Labayru, 6",
    "sg:city":"Bilbao",
    "sg:orig_category":"Cajas Registradoras, Terminales De Puntos De Venta",
    "sg:phone":"+34 944 44 40 12",
    "sg:postcode":"48012",
    "sg:province":"Vizcaya",
    "wof:name":"Laubisa S.l.",
    "wof:placetype":"venue"
},
  "geometry": {"coordinates":[-2.9381139278,43.2567100525],"type":"Point"}
}