{
  "type": "Feature",
  "properties": {
    "iso:country":"ES",
    "sg:address":"Calle de Anselmo Cifuentes, 12",
    "sg:city":"Gijon",
    "sg:orig_category":"Librer\u00cdas",
    "sg:phone":"+34 985 35 43 50",
    "sg:postcode":"33205",
    "sg:province":"Asturias",
    "wof:name":"Alvarez Rodriguez Maria Luz",
    "wof:placetype":"venue"
},
  "geometry": {"coordinates":[-5.6622915268,43.5382804871],"type":"Point"}
}