{
  "type": "Feature",
  "properties": {
    "addr:full":"Calle de San Vicente Ferrer, 4 Segovia Segovia 40002",
    "addr:housenumber":"4",
    "addr:postcode":"40002",
    "addr:street":"Calle De San Vicente Ferrer",
    "iso:country":"ES",
    "sg:address":"Calle de San Vicente Ferrer, 4",
    "sg:city":"Segovia",
    "sg:orig_category":"Inmobiliaria (agencias)",
    "sg:phone":"+34 921 42 48 58",
    "sg:postcode":"40002",
    "sg:province":"Segovia",
    "wof:name":"Construcciones Gomez Gomez S. A.",
    "wof:placetype":"venue"
},
  "geometry": {"coordinates":[-4.1166181564,40.9410476685],"type":"Point"}
}