{
  "type": "Feature",
  "properties": {
    "iso:country":"ES",
    "sg:address":"Calle de Quevedo, 13",
    "sg:city":"Bembibre",
    "sg:orig_category":"Alquiler De V\u00cddeo",
    "sg:phone":"+34 987 51 00 00",
    "sg:postcode":"24300",
    "sg:province":"Le\u00f3n",
    "wof:name":"Fernandez Prieto Genoveva",
    "wof:placetype":"venue"
},
  "geometry": {"coordinates":[-6.4140090942,42.6180343628],"type":"Point"}
}