{
  "type": "Feature",
  "properties": {
    "iso:country":"ES",
    "sg:address":"Pol Ind Las Acacias, 43",
    "sg:city":"Puente-genil",
    "sg:orig_category":"Promotores Constructores",
    "sg:phone":"+34 957 60 68 50",
    "sg:postcode":"14500",
    "sg:province":"C\u00f3rdoba",
    "wof:name":"Comunidad De Bienes Montajes Sanfra C.b",
    "wof:placetype":"venue"
},
  "geometry": {"coordinates":[-4.7779579163,37.3909187317],"type":"Point"}
}