{
  "type": "Feature",
  "properties": {
    "addr:full":"Calle de Veracruz, 2 Gasco Madrid 28250",
    "addr:housenumber":"2",
    "addr:postcode":"28250",
    "addr:street":"Calle De Veracruz",
    "iso:country":"ES",
    "sg:address":"Calle de Veracruz, 2",
    "sg:city":"Gasco",
    "sg:orig_category":"Organismos De Reclutamiento",
    "sg:phone":"+34 918 59 12 96",
    "sg:postcode":"28250",
    "sg:province":"Madrid",
    "wof:name":"Imacting S.l:",
    "wof:placetype":"venue"
},
  "geometry": {"coordinates":[-3.9527280331,40.5712471008],"type":"Point"}
}