{
  "type": "Feature",
  "properties": {
    "addr:full":"Carr Doctor Zamenhof, 43 Vilanova I La Geltru Barcelona 08800",
    "addr:housenumber":"43",
    "addr:postcode":"08800",
    "addr:street":"Carr Doctor Zamenhof",
    "iso:country":"ES",
    "sg:address":"Carr Doctor Zamenhof, 43",
    "sg:city":"Vilanova I La Geltru",
    "sg:orig_category":"Alquiler De V\u00cddeo",
    "sg:phone":"+34 938 15 98 56",
    "sg:postcode":"08800",
    "sg:province":"Barcelona",
    "wof:name":"Moncada Francisco Maria Luisa",
    "wof:placetype":"venue"
},
  "geometry": {"coordinates":[1.7104159594,41.2221221924],"type":"Point"}
}