{
  "type": "Feature",
  "properties": {
    "iso:country":"ES",
    "sg:address":"Calle de Daoiz Y Velarde, 18",
    "sg:city":"Le\u00f3n",
    "sg:orig_category":"Electrodom\u00c9sticos (al Por Menor)",
    "sg:phone":"+34 987 25 50 26",
    "sg:postcode":"24006",
    "sg:province":"Le\u00f3n",
    "wof:name":"Sierra Diez Jose",
    "wof:placetype":"venue"
},
  "geometry": {"coordinates":[-5.5630559921,42.5958480835],"type":"Point"}
}