{
  "type": "Feature",
  "properties": {
    "iso:country":"ES",
    "sg:address":"Calle de Carlos Ii, 5",
    "sg:city":"Fuente Alamo",
    "sg:orig_category":"Loter\u00cda Y T\u00d3mbola",
    "sg:phone":"+34 968 59 72 49",
    "sg:postcode":"30320",
    "sg:province":"Murcia",
    "wof:name":"Lorente Garcia Catalina",
    "wof:placetype":"venue"
},
  "geometry": {"coordinates":[-1.1685329676,37.7234039307],"type":"Point"}
}