{
  "type": "Feature",
  "properties": {
    "iso:country":"ES",
    "sg:address":"Avda Doctor Waksman, 62",
    "sg:city":"Valencia",
    "sg:orig_category":"Instalaci\u00d3n, Mantenimiento De Porteros Electr\u00d3nicos Y Controles De Acceso",
    "sg:phone":"+34 963 34 18 70",
    "sg:postcode":"46013",
    "sg:province":"Valencia",
    "wof:name":"Segarra Herreros Jesus Angel",
    "wof:placetype":"venue"
},
  "geometry": {"coordinates":[-0.3679969907,39.4550209045],"type":"Point"}
}