{
  "type": "Feature",
  "properties": {
    "addr:full":"C/ Sant Nicolau, 16 Alcoi Alicante 03801",
    "addr:housenumber":"16",
    "addr:postcode":"03801",
    "addr:street":"C / Sant Nicolau",
    "iso:country":"ES",
    "sg:address":"C/ Sant Nicolau, 16",
    "sg:city":"Alcoi",
    "sg:orig_category":"Bisuter\u00cda, Joyer\u00cda, Relojer\u00cda (al Por Menor)",
    "sg:phone":"+34 965 54 45 52",
    "sg:postcode":"03801",
    "sg:province":"Alicante",
    "wof:name":"Company Lopez Agustin",
    "wof:placetype":"venue"
},
  "geometry": {"coordinates":[-0.4731659889,38.6969871521],"type":"Point"}
}