{
  "type": "Feature",
  "properties": {
    "addr:full":"Calle de Ca\u00d1ada Real Soriana, 16 Vereda Real Soriana C\u00f3rdoba 14710",
    "addr:housenumber":"16",
    "addr:postcode":"14710",
    "addr:street":"Calle De Can\u0303Ada;Soriana;Co\u0301Rdoba",
    "iso:country":"ES",
    "sg:address":"Calle de Ca\u00d1ada Real Soriana, 16",
    "sg:city":"Vereda Real Soriana",
    "sg:orig_category":"Bancos",
    "sg:phone":"+34 957 45 81 87",
    "sg:postcode":"14710",
    "sg:province":"C\u00f3rdoba",
    "wof:name":"Bt Espa\u00d1a Compa\u00d1ia De Servicios Globales De Telecomunicaciones S.a.u.",
    "wof:placetype":"venue"
},
  "geometry": {"coordinates":[-4.9146289825,37.8490753174],"type":"Point"}
}