{
  "type": "Feature",
  "properties": {
    "addr:full":"Calle de Aldapa, 4 Getxo Vizcaya 48990",
    "addr:housenumber":"4",
    "addr:postcode":"48990",
    "addr:street":"Calle De Aldapa",
    "iso:country":"ES",
    "sg:address":"Calle de Aldapa, 4",
    "sg:city":"Getxo",
    "sg:orig_category":"Muebles, Minoristas",
    "sg:phone":"+34 944 30 37 29",
    "sg:postcode":"48990",
    "sg:province":"Vizcaya",
    "wof:name":"Muebles Aldapas, S.l.",
    "wof:placetype":"venue"
},
  "geometry": {"coordinates":[-2.9863398075,43.2988510132],"type":"Point"}
}