{
  "type": "Feature",
  "properties": {
    "addr:full":"Calle de Jose Maria Pereda, 31 Torrelavega Cantabria 39300",
    "addr:housenumber":"31",
    "addr:postcode":"39300",
    "addr:street":"Calle De Jose Maria Pereda",
    "iso:country":"ES",
    "sg:address":"Calle de Jose Maria Pereda, 31",
    "sg:city":"Torrelavega",
    "sg:orig_category":"Cajas Para Embalar",
    "sg:phone":"+34 942 80 01 99",
    "sg:postcode":"39300",
    "sg:province":"Cantabria",
    "sg:website":"www.ruralvia.com",
    "wof:name":"Caja Rural De Burgos",
    "wof:placetype":"venue"
},
  "geometry": {"coordinates":[-4.0494132042,43.3506851196],"type":"Point"}
}