{
  "type": "Feature",
  "properties": {
    "addr:full":"Calle de Ingeniero De La Cierva, 19 Barriada San Gines Murcia 30203",
    "addr:housenumber":"19",
    "addr:postcode":"30203",
    "addr:street":"Calle De Ingeniero;La Cierva",
    "iso:country":"ES",
    "sg:address":"Calle de Ingeniero De La Cierva, 19",
    "sg:city":"Barriada San Gines",
    "sg:orig_category":"Centros De Educaci\u00d3n Especial",
    "sg:phone":"+34 968 12 30 16",
    "sg:postcode":"30203",
    "sg:province":"Murcia",
    "wof:name":"Colegio Publico De E.g.b. Mastia",
    "wof:placetype":"venue"
},
  "geometry": {"coordinates":[-0.9793279767,37.6137199402],"type":"Point"}
}