{
  "type": "Feature",
  "properties": {
    "iso:country":"ES",
    "sg:address":"Llosa, 2",
    "sg:city":"Gijon",
    "sg:orig_category":"Materiales De Construcci\u00d3n (en General)",
    "sg:phone":"+34 985 31 05 08",
    "sg:postcode":"33211",
    "sg:province":"Asturias",
    "wof:name":"Jeycor Piedra S.l.",
    "wof:placetype":"venue"
},
  "geometry": {"coordinates":[-5.677781105,43.5259742737],"type":"Point"}
}