{
  "type": "Feature",
  "properties": {
    "addr:full":"Calle de Castello, 120 Madrid Madrid 28006",
    "addr:housenumber":"120",
    "addr:postcode":"28006",
    "addr:street":"Calle De Castello",
    "iso:country":"ES",
    "sg:address":"Calle de Castello, 120",
    "sg:city":"Madrid",
    "sg:orig_category":"Aparcamientos (infraestructuras, Accesorios)",
    "sg:phone":"+34 915 62 86 51",
    "sg:postcode":"28006",
    "sg:province":"Madrid",
    "wof:name":"Huerta Velasco Adela",
    "wof:placetype":"venue"
},
  "geometry": {"coordinates":[-3.6805911064,40.4367866516],"type":"Point"}
}