{
  "type": "Feature",
  "properties": {
    "iso:country":"ES",
    "sg:address":"Bo Elizalde, S/n",
    "sg:city":"Izurtza",
    "sg:orig_category":"Ferreter\u00cda (diversos)",
    "sg:phone":"+34 946 81 89 79",
    "sg:postcode":"48213",
    "sg:province":"Vizcaya",
    "wof:name":"Recuperaciones Y Troceados S. A. L.",
    "wof:placetype":"venue"
},
  "geometry": {"coordinates":[-2.6397910118,43.1560325623],"type":"Point"}
}