{
  "type": "Feature",
  "properties": {
    "iso:country":"ES",
    "sg:address":"Carretera Alberuela, S/n",
    "sg:city":"Bierge",
    "sg:orig_category":"Apicultura",
    "sg:phone":"+34 974 31 81 23",
    "sg:postcode":"22144",
    "sg:province":"Huesca",
    "wof:name":"Larrosa Ballarin Jose Antonio",
    "wof:placetype":"venue"
},
  "geometry": {"coordinates":[-0.0781790018,42.1644096375],"type":"Point"}
}