{
  "type": "Feature",
  "properties": {
    "iso:country":"ES",
    "sg:address":"Calle de Torpedero Tucuman, 20",
    "sg:city":"Madrid",
    "sg:orig_category":"Comunidades Religiosas",
    "sg:phone":"+34 913 45 20 69",
    "sg:postcode":"28016",
    "sg:province":"Madrid",
    "wof:name":"Carmelitas Misioneras Provincia De Santa Teresa De Jesus Curia Provincial",
    "wof:placetype":"venue"
},
  "geometry": {"coordinates":[-3.6722118855,40.4615974426],"type":"Point"}
}