{
  "type": "Feature",
  "properties": {
    "addr:full":"Calle de Agustina De Aragon, 2 Ceuta Ceuta 51001",
    "addr:housenumber":"2",
    "addr:postcode":"51001",
    "addr:street":"Calle De Agustina De Aragon",
    "iso:country":"ES",
    "sg:address":"Calle de Agustina De Aragon, 2",
    "sg:city":"Ceuta",
    "sg:orig_category":"Asesor\u00cda De Formaci\u00d3n Y Gesti\u00d3n De Personal",
    "sg:phone":"+34 956 51 47 18",
    "sg:postcode":"51001",
    "sg:province":"Ceuta",
    "wof:name":"Symbol Asesoramiento S.l.",
    "wof:placetype":"venue"
},
  "geometry": {"coordinates":[-5.3065290451,35.8879737854],"type":"Point"}
}