{
  "type": "Feature",
  "properties": {
    "iso:country":"ES",
    "sg:address":"Pl. Espa\u00f1a, S/n",
    "sg:city":"Estacion Ferrea",
    "sg:orig_category":"Obras Y Organismos Sociales",
    "sg:phone":"+34 956 61 21 20",
    "sg:postcode":"11368",
    "sg:province":"C\u00e1diz",
    "wof:name":"Coordinadora Comarcal De Asociaciones Drogodependencia Alternativa",
    "wof:placetype":"venue"
},
  "geometry": {"coordinates":[-5.4348340034,36.2152290344],"type":"Point"}
}