{
  "type": "Feature",
  "properties": {
    "addr:full":"Calle de Bolea, Km. 0034,0 Elche Sierra Albacete 02430",
    "addr:postcode":"02430",
    "addr:street":"Calle De Bolea Km. 0034,0;Sierra",
    "iso:country":"ES",
    "sg:address":"Calle de Bolea, Km. 0034,0",
    "sg:city":"Elche Sierra",
    "sg:orig_category":"Carb\u00d3n, Carb\u00d3n De Madera (al Por Mayor)",
    "sg:phone":"+34 967 41 07 61",
    "sg:postcode":"02430",
    "sg:province":"Albacete",
    "wof:name":"Sanchez Mendoza Jose Fermin",
    "wof:placetype":"venue"
},
  "geometry": {"coordinates":[-1.6613692045,38.5615997314],"type":"Point"}
}