{
  "type": "Feature",
  "properties": {
    "addr:full":"Avda Holanda, 13 Alacant Alicante 03540",
    "addr:housenumber":"13",
    "addr:postcode":"03540",
    "addr:street":"Avda Holanda",
    "iso:country":"ES",
    "sg:address":"Avda Holanda, 13",
    "sg:city":"Alacant",
    "sg:orig_category":"Reposter\u00cdas",
    "sg:phone":"+34 965 26 64 90",
    "sg:postcode":"03540",
    "sg:province":"Alicante",
    "wof:name":"Sesma Elurbe Gloria",
    "wof:placetype":"venue"
},
  "geometry": {"coordinates":[-0.4156689942,38.3681640625],"type":"Point"}
}