{
  "type": "Feature",
  "properties": {
    "addr:full":"Carrer de Parellades, 74 Sitges Barcelona 08870",
    "addr:housenumber":"74",
    "addr:postcode":"08870",
    "addr:street":"Carrer De Parellades",
    "iso:country":"ES",
    "sg:address":"Carrer de Parellades, 74",
    "sg:city":"Sitges",
    "sg:orig_category":"Bisuter\u00cda, Joyer\u00cda, Relojer\u00cda (al Por Menor)",
    "sg:phone":"+34 938 94 46 03",
    "sg:postcode":"08870",
    "sg:province":"Barcelona",
    "wof:name":"Fuste Cervera Juana",
    "wof:placetype":"venue"
},
  "geometry": {"coordinates":[1.806499958,41.236492157],"type":"Point"}
}