{
  "type": "Feature",
  "properties": {
    "iso:country":"ES",
    "sg:address":"Avda Doctor Clara, S/n",
    "sg:city":"Castellon",
    "sg:orig_category":"Cajas Para Embalar",
    "sg:phone":"+34 964 25 25 17",
    "sg:postcode":"12002",
    "sg:province":"Castell\u00f3n",
    "wof:name":"Caja Rural Del Mediterraneo Ruralcaja S Coop De Credito",
    "wof:placetype":"venue"
},
  "geometry": {"coordinates":[-0.0456789993,39.9851417542],"type":"Point"}
}