{
  "type": "Feature",
  "properties": {
    "addr:full":"Calle de Curro Malena, S/n Lebrija Sevilla 41740",
    "addr:housenumber":"s",
    "addr:postcode":"41740",
    "addr:street":"Calle De Curro Malena;/ N",
    "iso:country":"ES",
    "sg:address":"Calle de Curro Malena, S/n",
    "sg:city":"Lebrija",
    "sg:orig_category":"Molduras, Junquillos, Listones Y Molduras Perforadas",
    "sg:phone":"+34 955 97 50 12",
    "sg:postcode":"41740",
    "sg:province":"Sevilla",
    "wof:name":"Garcia Calvo Francisco",
    "wof:placetype":"venue"
},
  "geometry": {"coordinates":[-6.0639314651,36.9185295105],"type":"Point"}
}