{
  "type": "Feature",
  "properties": {
    "iso:country":"ES",
    "sg:address":"Calle de Jardin De La Duquesa, 14",
    "sg:city":"Madrid",
    "sg:orig_category":"Cerrajer\u00cda, Ferrallista",
    "sg:phone":"+34 917 76 43 53",
    "sg:postcode":"28032",
    "sg:province":"Madrid",
    "wof:name":"Cerrajeria Cubero S.l.",
    "wof:placetype":"venue"
},
  "geometry": {"coordinates":[-3.6043889523,40.4033660889],"type":"Point"}
}