{
  "type": "Feature",
  "properties": {
    "iso:country":"ES",
    "sg:address":"Avda Mencia De Velasco, 4",
    "sg:city":"Briviesca",
    "sg:orig_category":"Muebles, Minoristas",
    "sg:phone":"+34 947 59 18 77",
    "sg:postcode":"09240",
    "sg:province":"Burgos",
    "wof:name":"Muebles Santa Casilda S.l.",
    "wof:placetype":"venue"
},
  "geometry": {"coordinates":[-3.3205740452,42.5446014404],"type":"Point"}
}