{
  "type": "Feature",
  "properties": {
    "addr:full":"Calle de Ramon Gomez De La Serna, 99 Madrid Madrid 28035",
    "addr:housenumber":"99",
    "addr:postcode":"madrid;28035",
    "addr:street":"Calle De Ramon Gomez De La Serna",
    "iso:country":"ES",
    "sg:address":"Calle de Ramon Gomez De La Serna, 99",
    "sg:city":"Madrid",
    "sg:orig_category":"Farmacias",
    "sg:phone":"+34 913 16 66 18",
    "sg:postcode":"28035",
    "sg:province":"Madrid",
    "wof:name":"Montilla Quero Ana Maria",
    "wof:placetype":"venue"
},
  "geometry": {"coordinates":[-3.7258200645,40.4816322327],"type":"Point"}
}