{
  "type": "Feature",
  "properties": {
    "addr:full":"Calle de Covadonga, 2 Arriondas Asturias 33540",
    "addr:housenumber":"2",
    "addr:postcode":"33540",
    "addr:street":"Calle De Covadonga",
    "iso:country":"ES",
    "sg:address":"Calle de Covadonga, 2",
    "sg:city":"Arriondas",
    "sg:orig_category":"Transportes Por Carretera: Lotes Completos, Mercanc\u00cdas Diversas",
    "sg:phone":"+34 985 84 00 73",
    "sg:postcode":"33540",
    "sg:province":"Asturias",
    "wof:name":"Hijos De Gonzalez Valdes S.l.",
    "wof:placetype":"venue"
},
  "geometry": {"coordinates":[-5.1874713898,43.3889427185],"type":"Point"}
}