{
  "type": "Feature",
  "properties": {
    "addr:full":"Anzuela, S/n Urdiain Navarra 31810",
    "addr:housenumber":"/ n",
    "addr:postcode":"31810",
    "addr:street":"Anzuela S",
    "iso:country":"ES",
    "sg:address":"Anzuela, S/n",
    "sg:city":"Urdiain",
    "sg:orig_category":"Alimentaci\u00d3n General (al Por Mayor)",
    "sg:phone":"+34 948 56 25 56",
    "sg:postcode":"31810",
    "sg:province":"Navarra",
    "wof:name":"Artoa S.l.",
    "wof:placetype":"venue"
},
  "geometry": {"coordinates":[-2.1364359856,42.8871116638],"type":"Point"}
}