{
  "type": "Feature",
  "properties": {
    "addr:full":"Cra. Baqueira, 8 Arties Lleida 25599",
    "addr:housenumber":"8",
    "addr:postcode":"25599",
    "addr:street":"Baqueira",
    "iso:country":"ES",
    "sg:address":"Cra. Baqueira, 8",
    "sg:city":"Arties",
    "sg:orig_category":"Alquiler De Apartamentos",
    "sg:phone":"+34 973 64 42 89",
    "sg:postcode":"25599",
    "sg:province":"Lleida",
    "wof:name":"Apartaments Deth Camin Reiau",
    "wof:placetype":"venue"
},
  "geometry": {"coordinates":[0.8728759885,42.6987991333],"type":"Point"}
}