{
  "type": "Feature",
  "properties": {
    "addr:full":"Ctra Obispo, 67 Gijon Asturias 33210",
    "addr:housenumber":"67",
    "addr:postcode":"33210",
    "addr:street":"Ctra Obispo",
    "iso:country":"ES",
    "sg:address":"Ctra Obispo, 67",
    "sg:city":"Gijon",
    "sg:orig_category":"Mercer\u00cda, Lencer\u00cda (al Por Menor)",
    "sg:phone":"+34 985 38 76 17",
    "sg:postcode":"33210",
    "sg:province":"Asturias",
    "wof:name":"Garcia Fernandez Conrado",
    "wof:placetype":"venue"
},
  "geometry": {"coordinates":[-5.664867878,43.5211296082],"type":"Point"}
}