{
  "type": "Feature",
  "properties": {
    "iso:country":"ES",
    "sg:address":"Avda Golf, S/n",
    "sg:city":"Mijas Costa",
    "sg:orig_category":"Administradores De Bienes Y Delegados De Comunidades De Propietarios",
    "sg:phone":"+34 952 93 20 09",
    "sg:postcode":"29649",
    "sg:province":"M\u00e1laga",
    "wof:name":"Botet Administraciones S.l.",
    "wof:placetype":"venue"
},
  "geometry": {"coordinates":[-4.7050890923,36.4985466003],"type":"Point"}
}