{
  "type": "Feature",
  "properties": {
    "addr:full":"Calle de Padre Ignacio Ellacuria, 9 Laredo Cantabria 39770",
    "addr:housenumber":"9",
    "addr:postcode":"39770",
    "addr:street":"Calle De Padre Ignacio Ellacuria",
    "iso:country":"ES",
    "sg:address":"Calle de Padre Ignacio Ellacuria, 9",
    "sg:city":"Laredo",
    "sg:orig_category":"Promotores Constructores",
    "sg:phone":"+34 942 60 49 96",
    "sg:postcode":"39770",
    "sg:province":"Cantabria",
    "wof:name":"Horizonte Norsur Promociones Y Edificaciones S.l.",
    "wof:placetype":"venue"
},
  "geometry": {"coordinates":[-3.418448925,43.4095001221],"type":"Point"}
}