{
  "type": "Feature",
  "properties": {
    "addr:full":"Calle de Doctor Esquerdo, 12 Madrid Madrid 28028",
    "addr:housenumber":"12",
    "addr:postcode":"madrid;28028",
    "addr:street":"Calle De Doctor Esquerdo",
    "iso:country":"ES",
    "sg:address":"Calle de Doctor Esquerdo, 12",
    "sg:city":"Madrid",
    "sg:orig_category":"Fabricaci\u00d3n De Sobres, Bolsas Y Fundas",
    "sg:phone":"+34 914 02 05 73",
    "sg:postcode":"28028",
    "sg:province":"Madrid",
    "wof:name":"Sla Bolsos, Sl",
    "wof:placetype":"venue"
},
  "geometry": {"coordinates":[-3.6688671112,40.4261894226],"type":"Point"}
}