{
  "type": "Feature",
  "properties": {
    "iso:country":"ES",
    "sg:address":"Plaz Egido Luz, S/n",
    "sg:city":"Codosera",
    "sg:orig_category":"Administraciones Regionales, Departamentales Y Locales",
    "sg:phone":"+34 924 40 40 52",
    "sg:postcode":"06518",
    "sg:province":"Badajoz",
    "wof:name":"Ayuntamiento De La Codosera",
    "wof:placetype":"venue"
},
  "geometry": {"coordinates":[-7.1725745201,39.208152771],"type":"Point"}
}