{
  "type": "Feature",
  "properties": {
    "addr:full":"Calle de Pobla De Farnals, 53 Valencia Valencia 46022",
    "addr:housenumber":"53",
    "addr:postcode":"46022",
    "addr:street":"Calle De Pobla;Farnals",
    "iso:country":"ES",
    "sg:address":"Calle de Pobla De Farnals, 53",
    "sg:city":"Valencia",
    "sg:orig_category":"Alumbrados",
    "sg:phone":"+34 963 31 81 05",
    "sg:postcode":"46022",
    "sg:province":"Valencia",
    "wof:name":"Erco Iluminacion S.a.",
    "wof:placetype":"venue"
},
  "geometry": {"coordinates":[-0.3479120135,39.468624115],"type":"Point"}
}