{
  "type": "Feature",
  "properties": {
    "addr:full":"Calle de Mezo Kalea, 20 Erandio Vizcaya 48950",
    "addr:housenumber":"20",
    "addr:postcode":"48950",
    "addr:street":"Calle De Mezo Kalea",
    "iso:country":"ES",
    "sg:address":"Calle de Mezo Kalea, 20",
    "sg:city":"Erandio",
    "sg:orig_category":"Peluquer\u00cdas, Peluquer\u00cda Mixta",
    "sg:phone":"+34 944 67 32 53",
    "sg:postcode":"48950",
    "sg:province":"Vizcaya",
    "wof:name":"Peluqueria Nouvagen\u00b4s",
    "wof:placetype":"venue"
},
  "geometry": {"coordinates":[-2.9828515053,43.3159255981],"type":"Point"}
}