{
  "type": "Feature",
  "properties": {
    "addr:full":"Trva Balate, 3 Sang\u00fcesa Navarra 31400",
    "addr:housenumber":"3",
    "addr:postcode":"31400",
    "addr:street":"Trva Balate",
    "iso:country":"ES",
    "sg:address":"Trva Balate, 3",
    "sg:city":"Sang\u00fcesa",
    "sg:orig_category":"Fabricaci\u00d3n, Comercio De Flores Y Plantas Artificiales",
    "sg:phone":"+34 948 87 07 03",
    "sg:postcode":"31400",
    "sg:province":"Navarra",
    "wof:name":"Lorea S.a.t.",
    "wof:placetype":"venue"
},
  "geometry": {"coordinates":[-1.2811210155,42.5742492676],"type":"Point"}
}