{
  "type": "Feature",
  "properties": {
    "addr:full":"Partida La Sierra, S/n Castejon Puente Huesca 22310",
    "addr:housenumber":"/ n",
    "addr:postcode":"22310",
    "addr:street":"Partida La Sierra S;Castejon Puente",
    "iso:country":"ES",
    "sg:address":"Partida La Sierra, S/n",
    "sg:city":"Castejon Puente",
    "sg:orig_category":"Fabricaci\u00d3n Y Comercio De M\u00c1quinas",
    "sg:phone":"+34 974 41 69 30",
    "sg:postcode":"22310",
    "sg:province":"Huesca",
    "wof:name":"M.e.t.o. S.a.",
    "wof:placetype":"venue"
},
  "geometry": {"coordinates":[0.1586370021,41.9619064331],"type":"Point"}
}