{
  "type": "Feature",
  "properties": {
    "iso:country":"ES",
    "sg:address":"Calle de Morote, 1",
    "sg:city":"Huescar",
    "sg:orig_category":"Farmacias",
    "sg:phone":"+34 958 74 08 27",
    "sg:postcode":"18830",
    "sg:province":"Granada",
    "wof:name":"Nu\u00f1o Alvarez Rocio",
    "wof:placetype":"venue"
},
  "geometry": {"coordinates":[-2.5400705338,37.808807373],"type":"Point"}
}