{
  "type": "Feature",
  "properties": {
    "addr:full":"Calle de Mayor, S/n Canales Sierra La Rioja 26326",
    "addr:housenumber":"s",
    "addr:postcode":"26326",
    "addr:street":"Calle De Mayor;/ N Canales Sierra;Rioja",
    "iso:country":"ES",
    "sg:address":"Calle de Mayor, S/n",
    "sg:city":"Canales Sierra",
    "sg:orig_category":"Bancos",
    "sg:phone":"+34 941 37 60 53",
    "sg:postcode":"26326",
    "sg:province":"La Rioja",
    "wof:name":"Vicario Rubio Benito",
    "wof:placetype":"venue"
},
  "geometry": {"coordinates":[-2.8808579445,42.3107643127],"type":"Point"}
}