{
  "type": "Feature",
  "properties": {
    "addr:full":"Generalife, 39 Pto Sta Maria C\u00e1diz 11500",
    "addr:housenumber":"39",
    "addr:postcode":"11500",
    "addr:street":"Generalife;Ca\u0301Diz",
    "iso:country":"ES",
    "sg:address":"Generalife, 39",
    "sg:city":"Pto Sta Maria",
    "sg:orig_category":"Centros Empresariales",
    "sg:phone":"+34 956 86 11 50",
    "sg:postcode":"11500",
    "sg:province":"C\u00e1diz",
    "wof:name":"Gestimiza S.l.",
    "wof:placetype":"venue"
},
  "geometry": {"coordinates":[-6.2048988342,36.6245346069],"type":"Point"}
}