{
  "type": "Feature",
  "properties": {
    "addr:full":"Calle de Hernando Colon, 35 Sevilla Sevilla 41004",
    "addr:housenumber":"35",
    "addr:postcode":"41004",
    "addr:street":"Calle De Hernando Colon",
    "iso:country":"ES",
    "sg:address":"Calle de Hernando Colon, 35",
    "sg:city":"Sevilla",
    "sg:orig_category":"Art\u00cdculos De Regalo (al Por Menor)",
    "sg:phone":"+34 954 56 35 44",
    "sg:postcode":"41004",
    "sg:province":"Sevilla",
    "wof:name":"Vazquez Jimenez Enriqueta",
    "wof:placetype":"venue"
},
  "geometry": {"coordinates":[-5.9934492111,37.3874092102],"type":"Point"}
}