{
  "type": "Feature",
  "properties": {
    "iso:country":"ES",
    "sg:address":"Calle de Arcos, 23",
    "sg:city":"Sevilla",
    "sg:orig_category":"Comercio De Mobiliario De Oficina",
    "sg:phone":"+34 954 27 82 48",
    "sg:postcode":"41011",
    "sg:province":"Sevilla",
    "wof:name":"Agea Amador Jose Manuel",
    "wof:placetype":"venue"
},
  "geometry": {"coordinates":[-5.9992418289,37.3763961792],"type":"Point"}
}