{
  "type": "Feature",
  "properties": {
    "iso:country":"ES",
    "sg:address":"Calle de Iglesia, S/n",
    "sg:city":"Villaverde De Guare\u00e7a",
    "sg:orig_category":"Asilos De Ancianos. Centros Privados",
    "sg:phone":"+34 923 16 02 14",
    "sg:postcode":"37428",
    "sg:province":"Salamanca",
    "wof:name":"Residencia Tercera Edad Arfis S.l.",
    "wof:placetype":"venue"
},
  "geometry": {"coordinates":[-5.5256128311,41.0647087097],"type":"Point"}
}