{
  "type": "Feature",
  "properties": {
    "iso:country":"ES",
    "sg:address":"Av. Europa (pol Ind), S/n",
    "sg:city":"Constanti",
    "sg:orig_category":"Transportes Combinados Por Tren Y Carretera",
    "sg:phone":"+34 977 52 49 46",
    "sg:postcode":"43120",
    "sg:province":"Tarragona",
    "wof:name":"Mocatrans 2000 S.l.",
    "wof:placetype":"venue"
},
  "geometry": {"coordinates":[1.1627919674,41.1613731384],"type":"Point"}
}