{
  "type": "Feature",
  "properties": {
    "iso:country":"ES",
    "sg:address":"Calle de Francisco De Velasco, 10",
    "sg:city":"Baza",
    "sg:orig_category":"Empresas De Carpinter\u00cda De Madera",
    "sg:phone":"+34 958 70 45 12",
    "sg:postcode":"18800",
    "sg:province":"Granada",
    "wof:name":"Rojo Sanchez Jose Ramon",
    "wof:placetype":"venue"
},
  "geometry": {"coordinates":[-2.7718930244,37.4847450256],"type":"Point"}
}