{
  "type": "Feature",
  "properties": {
    "iso:country":"ES",
    "sg:address":"Av Pont, S/n",
    "sg:city":"Solsona",
    "sg:orig_category":"Producci\u00d3n, Distribuci\u00d3n De Electricidad",
    "sg:phone":"+34 973 48 07 08",
    "sg:postcode":"25280",
    "sg:province":"Lleida",
    "wof:name":"Vilaseca Gangolells Ramon",
    "wof:placetype":"venue"
},
  "geometry": {"coordinates":[1.5221300125,41.995059967],"type":"Point"}
}