{
  "type": "Feature",
  "properties": {
    "iso:country":"ES",
    "sg:address":"Po. Del Mar, S/n",
    "sg:city":"Palmanova",
    "sg:orig_category":"Farmacias",
    "sg:phone":"+34 971 68 18 01",
    "sg:postcode":"07181",
    "sg:province":"Islas Baleares",
    "wof:name":"Bisquerra Miralles Juan",
    "wof:placetype":"venue"
},
  "geometry": {"coordinates":[2.5391979218,39.5241355896],"type":"Point"}
}