{
  "type": "Feature",
  "properties": {
    "iso:country":"ES",
    "sg:address":"Calle de Marbella, 33",
    "sg:city":"Istan",
    "sg:orig_category":"Cajas Para Embalar",
    "sg:phone":"+34 952 86 98 84",
    "sg:postcode":"29611",
    "sg:province":"M\u00e1laga",
    "sg:website":"www.cajamar.es",
    "wof:name":"Cajamar",
    "wof:placetype":"venue"
},
  "geometry": {"coordinates":[-4.9487352371,36.5811920166],"type":"Point"}
}