{
  "type": "Feature",
  "properties": {
    "addr:full":"Carr Segre, 4 Girona Girona 17003",
    "addr:housenumber":"4",
    "addr:postcode":"17003",
    "addr:street":"Carr Segre",
    "iso:country":"ES",
    "sg:address":"Carr Segre, 4",
    "sg:city":"Girona",
    "sg:orig_category":"Venta, Instalaci\u00d3n De Calefacci\u00d3n",
    "sg:phone":"+34 972 22 52 94",
    "sg:postcode":"17003",
    "sg:province":"Girona",
    "wof:name":"Servi Tecnic Girona Sl",
    "wof:placetype":"venue"
},
  "geometry": {"coordinates":[2.8135089874,41.9665298462],"type":"Point"}
}