{
  "type": "Feature",
  "properties": {
    "addr:full":"Calle de San Andres, 66 Coru\u00d1a La Coru\u00f1a 15003",
    "addr:housenumber":"66",
    "addr:postcode":"15003",
    "addr:street":"Calle De San Andres;Corun\u0303A",
    "iso:country":"ES",
    "sg:address":"Calle de San Andres, 66",
    "sg:city":"Coru\u00d1a",
    "sg:orig_category":"Confecci\u00d3n (fabricaci\u00d3n, Al Por Mayor)",
    "sg:phone":"+34 981 21 41 93",
    "sg:postcode":"15003",
    "sg:province":"La Coru\u00f1a",
    "wof:name":"Herederos De Deogracias Ramon Perandones C.b.",
    "wof:placetype":"venue"
},
  "geometry": {"coordinates":[-8.404499054,43.3692703247],"type":"Point"}
}