{
  "type": "Feature",
  "properties": {
    "addr:full":"Calle de Rodriguez Paterna, 26 Logro\u00f1o La Rioja 26001",
    "addr:housenumber":"26",
    "addr:postcode":"26001",
    "addr:street":"Calle De Rodriguez Paterna;Rioja",
    "iso:country":"ES",
    "sg:address":"Calle de Rodriguez Paterna, 26",
    "sg:city":"Logro\u00f1o",
    "sg:orig_category":"Centros Pms (psico",
    "sg:phone":"+34 941 25 17 71",
    "sg:postcode":"26001",
    "sg:province":"La Rioja",
    "wof:name":"Comunidad Autonoma De La Rioja",
    "wof:placetype":"venue"
},
  "geometry": {"coordinates":[-2.4423348904,42.4679298401],"type":"Point"}
}