{
  "type": "Feature",
  "properties": {
    "iso:country":"ES",
    "sg:address":"Huertos, 49",
    "sg:city":"Orihuela",
    "sg:orig_category":"Arboricultura Y Producci\u00d3n De Frutas",
    "sg:phone":"+34 966 74 38 37",
    "sg:postcode":"03300",
    "sg:province":"Alicante",
    "wof:name":"Ballesta Rodriguez Antonio",
    "wof:placetype":"venue"
},
  "geometry": {"coordinates":[-0.9457809925,38.0793609619],"type":"Point"}
}