{
  "type": "Feature",
  "properties": {
    "iso:country":"ES",
    "sg:address":"Colonia Castellares, S/n",
    "sg:city":"Riaza",
    "sg:orig_category":"Carnicer\u00cdas, Carnicer\u00cdas",
    "sg:phone":"+34 921 55 05 77",
    "sg:postcode":"40500",
    "sg:province":"Segovia",
    "wof:name":"Mu\u00f1oz Jimenez Miguel Angel",
    "wof:placetype":"venue"
},
  "geometry": {"coordinates":[-3.4820048809,41.2783088684],"type":"Point"}
}