{
  "type": "Feature",
  "properties": {
    "addr:full":"Calle de Rector Viejo, 2 Bujalance C\u00f3rdoba 14650",
    "addr:housenumber":"2",
    "addr:postcode":"14650",
    "addr:street":"Calle De Rector Viejo",
    "iso:country":"ES",
    "sg:address":"Calle de Rector Viejo, 2",
    "sg:city":"Bujalance",
    "sg:orig_category":"Venta, Instalaci\u00d3n De Cocinas",
    "sg:phone":"+34 957 17 02 62",
    "sg:postcode":"14650",
    "sg:province":"C\u00f3rdoba",
    "wof:name":"Tello Villen Manuel",
    "wof:placetype":"venue"
},
  "geometry": {"coordinates":[-4.3845930099,37.8969459534],"type":"Point"}
}