{
  "type": "Feature",
  "properties": {
    "addr:full":"Calle de Corona De Aragon, 26 Barbastro Huesca 22300",
    "addr:housenumber":"26",
    "addr:postcode":"22300",
    "addr:street":"Calle De Corona De Aragon",
    "iso:country":"ES",
    "sg:address":"Calle de Corona De Aragon, 26",
    "sg:city":"Barbastro",
    "sg:orig_category":"Masajistas Kinesiterapeutas",
    "sg:phone":"+34 974 31 10 53",
    "sg:postcode":"22300",
    "sg:province":"Huesca",
    "wof:name":"Urban Leris Julia",
    "wof:placetype":"venue"
},
  "geometry": {"coordinates":[0.1280200034,42.0362510681],"type":"Point"}
}