{
  "type": "Feature",
  "properties": {
    "addr:full":"Carrer de Marques De Montoliu, S/n Tarragona Tarragona 43002",
    "addr:housenumber":"s / n",
    "addr:postcode":"43002",
    "addr:street":"Carrer De Marques De Montoliu",
    "iso:country":"ES",
    "sg:address":"Carrer de Marques De Montoliu, S/n",
    "sg:city":"Tarragona",
    "sg:orig_category":"Venta, Instalaci\u00d3n, Reparaci\u00d3n De Antenas Para Televisi\u00d3n",
    "sg:phone":"+34 977 23 89 02",
    "sg:postcode":"43002",
    "sg:province":"Tarragona",
    "wof:name":"Moix Montala Alfonso",
    "wof:placetype":"venue"
},
  "geometry": {"coordinates":[1.2479829788,41.1222496033],"type":"Point"}
}