{
  "type": "Feature",
  "properties": {
    "addr:full":"Carr Josep Llanza, 33 Vilanova I La Geltru Barcelona 08800",
    "addr:housenumber":"33",
    "addr:postcode":"08800",
    "addr:street":"Carr Josep Llanza",
    "iso:country":"ES",
    "sg:address":"Carr Josep Llanza, 33",
    "sg:city":"Vilanova I La Geltru",
    "sg:orig_category":"Peluquer\u00cdas, Peluquer\u00cda Mixta",
    "sg:phone":"+34 938 14 47 48",
    "sg:postcode":"08800",
    "sg:province":"Barcelona",
    "wof:name":"Vila Look S.l.",
    "wof:placetype":"venue"
},
  "geometry": {"coordinates":[1.7255569696,41.221370697],"type":"Point"}
}