{
  "type": "Feature",
  "properties": {
    "iso:country":"ES",
    "sg:address":"Calle de Codo (el), 3",
    "sg:city":"Humanes",
    "sg:orig_category":"Molduras, Junquillos, Listones Y Molduras Perforadas",
    "sg:phone":"+34 949 85 01 99",
    "sg:postcode":"19220",
    "sg:province":"Guadalajara",
    "wof:name":"Merino Rojo Francisco",
    "wof:placetype":"venue"
},
  "geometry": {"coordinates":[-3.155452013,40.8280143738],"type":"Point"}
}