{
  "type": "Feature",
  "properties": {
    "addr:full":"Ctra General Km 24, Km. 0024,0 Santa Maria De Guia Las Palmas 35450",
    "addr:housenumber":"km",
    "addr:postcode":"35450",
    "addr:street":"Ctra General;24 Km. 0024,0",
    "iso:country":"ES",
    "sg:address":"Ctra General Km 24, Km. 0024,0",
    "sg:city":"Santa Maria De Guia",
    "sg:orig_category":"Distribuci\u00d3n De Petr\u00d3leo Y Derivados",
    "sg:phone":"+34 928 55 31 40",
    "sg:postcode":"35450",
    "sg:province":"Las Palmas",
    "wof:name":"Ruiz Rodriguez Juan Manuel",
    "wof:placetype":"venue"
},
  "geometry": {"coordinates":[-15.6319208145,28.1403903961],"type":"Point"}
}