{
  "type": "Feature",
  "properties": {
    "iso:country":"ES",
    "sg:address":"Avda Candina, 28",
    "sg:city":"Santander",
    "sg:orig_category":"Fabricaci\u00d3n De Art\u00cdculos Para Papeler\u00cdas",
    "sg:phone":"+34 942 34 45 74",
    "sg:postcode":"39011",
    "sg:province":"Cantabria",
    "wof:name":"Cleman Asociados S.l.",
    "wof:placetype":"venue"
},
  "geometry": {"coordinates":[-3.8286790848,43.4530906677],"type":"Point"}
}