{
  "type": "Feature",
  "properties": {
    "addr:full":"Calle de Prim, 5 Algeciras C\u00e1diz 11201",
    "addr:housenumber":"5;ca\u0301diz",
    "addr:postcode":"11201",
    "addr:street":"Calle De Prim",
    "iso:country":"ES",
    "sg:address":"Calle de Prim, 5",
    "sg:city":"Algeciras",
    "sg:orig_category":"Radiocomunicaciones, Telefon\u00cda M\u00d3vil, Radiomensajer\u00cda: Servicios, Comercializaci\u00d3n",
    "sg:phone":"+34 956 66 80 72",
    "sg:postcode":"11201",
    "sg:province":"C\u00e1diz",
    "sg:website":"www.telyco.es",
    "wof:name":"Teleinformatica Y Comunicaciones S.a.",
    "wof:placetype":"venue"
},
  "geometry": {"coordinates":[-5.4469590187,36.1293144226],"type":"Point"}
}