{
  "type": "Feature",
  "properties": {
    "iso:country":"ES",
    "sg:address":"Calle de Madre De Dios, 56",
    "sg:city":"Logro\u00f1o",
    "sg:orig_category":"Psic\u00d3logos",
    "sg:phone":"+34 941 25 05 47",
    "sg:postcode":"26004",
    "sg:province":"La Rioja",
    "wof:name":"Reinares Garcia Fernando",
    "wof:placetype":"venue"
},
  "geometry": {"coordinates":[-2.431180954,42.468296051],"type":"Point"}
}