{
  "type": "Feature",
  "properties": {
    "iso:country":"ES",
    "sg:address":"Calle de Ispizua Tar Segundo, 2",
    "sg:city":"Bermeo",
    "sg:orig_category":"Panader\u00cdas, Panader\u00cdas",
    "sg:phone":"+34 946 88 50 31",
    "sg:postcode":"48370",
    "sg:province":"Vizcaya",
    "wof:name":"Atela Ibarlucea Julian",
    "wof:placetype":"venue"
},
  "geometry": {"coordinates":[-2.7481176853,43.4026641846],"type":"Point"}
}