{
  "type": "Feature",
  "properties": {
    "iso:country":"ES",
    "sg:address":"Cerdanyola, 2",
    "sg:city":"Ripollet",
    "sg:orig_category":"Montaje (empresas De)",
    "sg:phone":"+34 935 80 82 37",
    "sg:postcode":"08291",
    "sg:province":"Barcelona",
    "wof:name":"Eform 2000 S.l.",
    "wof:placetype":"venue"
},
  "geometry": {"coordinates":[2.1581029892,41.4984054565],"type":"Point"}
}