{
  "type": "Feature",
  "properties": {
    "addr:full":"Bard Sardinero (el), 2 Ceuta Ceuta 51002",
    "addr:postcode":"51002",
    "iso:country":"ES",
    "sg:address":"Bard Sardinero (el), 2",
    "sg:city":"Ceuta",
    "sg:orig_category":"Plomeros",
    "sg:phone":"+34 956 52 10 73",
    "sg:postcode":"51002",
    "sg:province":"Ceuta",
    "wof:name":"Alba Molina Francisco",
    "wof:placetype":"venue"
},
  "geometry": {"coordinates":[-5.3337802887,35.8868865967],"type":"Point"}
}