{
  "type": "Feature",
  "properties": {
    "addr:full":"Calle de Puerto De Canfranc, 41 Madrid Madrid 28038",
    "addr:housenumber":"41",
    "addr:postcode":"madrid;28038",
    "addr:street":"Calle De Puerto De Canfranc",
    "iso:country":"ES",
    "sg:address":"Calle de Puerto De Canfranc, 41",
    "sg:city":"Madrid",
    "sg:orig_category":"Confecci\u00d3n De Uniformes",
    "sg:phone":"+34 914 37 58 48",
    "sg:postcode":"28038",
    "sg:province":"Madrid",
    "wof:name":"Cicotex S.l.",
    "wof:placetype":"venue"
},
  "geometry": {"coordinates":[-3.6619110107,40.3989334106],"type":"Point"}
}