{
  "type": "Feature",
  "properties": {
    "addr:full":"Calle de Virgen Del Consuelo, 51 Alcolea Del Rio Sevilla 41449",
    "addr:housenumber":"51",
    "addr:postcode":"41449",
    "addr:street":"Calle De Virgen Del Consuelo",
    "iso:country":"ES",
    "sg:address":"Calle de Virgen Del Consuelo, 51",
    "sg:city":"Alcolea Del Rio",
    "sg:orig_category":"Hielo Artificial (fabricaci\u00d3n, Distribuci\u00d3n)",
    "sg:phone":"+34 955 64 43 16",
    "sg:postcode":"41449",
    "sg:province":"Sevilla",
    "wof:name":"Afrimesa",
    "wof:placetype":"venue"
},
  "geometry": {"coordinates":[-5.6638569832,37.6150627136],"type":"Point"}
}