{
  "type": "Feature",
  "properties": {
    "iso:country":"ES",
    "sg:address":"Pase Castellana, 143",
    "sg:city":"Madrid",
    "sg:orig_category":"Estancos",
    "sg:phone":"+34 915 79 35 04",
    "sg:postcode":"28046",
    "sg:province":"Madrid",
    "wof:name":"Herreros Robles Antonio",
    "wof:placetype":"venue"
},
  "geometry": {"coordinates":[-3.6904060841,40.4596366882],"type":"Point"}
}