{
  "type": "Feature",
  "properties": {
    "addr:full":"Avda San Diego, 47 Madrid Madrid 28053",
    "addr:housenumber":"47",
    "addr:postcode":"madrid;28053",
    "addr:street":"Avda San Diego",
    "iso:country":"ES",
    "sg:address":"Avda San Diego, 47",
    "sg:city":"Madrid",
    "sg:orig_category":"Radiocomunicaciones, Telefon\u00cda M\u00d3vil, Radiomensajer\u00cda: Servicios, Comercializaci\u00d3n",
    "sg:phone":"+34 914 78 09 46",
    "sg:postcode":"28053",
    "sg:province":"Madrid",
    "wof:name":"Gogovic Gogovic Mirjana",
    "wof:placetype":"venue"
},
  "geometry": {"coordinates":[-3.669449091,40.3880157471],"type":"Point"}
}