{
  "type": "Feature",
  "properties": {
    "iso:country":"ES",
    "sg:address":"Calle de Martinez Campos, 20",
    "sg:city":"Granada",
    "sg:orig_category":"Peluquer\u00cdas, Peluquer\u00cda Mixta",
    "sg:phone":"+34 958 25 12 50",
    "sg:postcode":"18002",
    "sg:province":"Granada",
    "wof:name":"Toledano Martinez Andres",
    "wof:placetype":"venue"
},
  "geometry": {"coordinates":[-3.6042335033,37.1716423035],"type":"Point"}
}