{
  "type": "Feature",
  "properties": {
    "iso:country":"ES",
    "sg:address":"Avda Carmen Amigo, 76",
    "sg:city":"Puebla Calzada",
    "sg:orig_category":"Electrodom\u00c9sticos (fabricaci\u00d3n, Al Por Mayor)",
    "sg:phone":"+34 924 45 20 50",
    "sg:postcode":"06490",
    "sg:province":"Badajoz",
    "wof:name":"Perez Caston Ramon",
    "wof:placetype":"venue"
},
  "geometry": {"coordinates":[-6.6286120415,38.8915519714],"type":"Point"}
}