{
  "type": "Feature",
  "properties": {
    "addr:full":"Calle de Madrid, 40 Alcantarilla Murcia 30820",
    "addr:housenumber":"40",
    "addr:postcode":"30820",
    "addr:street":"Calle De Madrid",
    "iso:country":"ES",
    "sg:address":"Calle de Madrid, 40",
    "sg:city":"Alcantarilla",
    "sg:orig_category":"Ropa De Hogar (al Por Menor)",
    "sg:phone":"+34 968 89 07 99",
    "sg:postcode":"30820",
    "sg:province":"Murcia",
    "wof:name":"D' Casa S.c.",
    "wof:placetype":"venue"
},
  "geometry": {"coordinates":[-1.2145080566,37.9733505249],"type":"Point"}
}