{
  "type": "Feature",
  "properties": {
    "addr:full":"Calle de Pere Ii El Cerimonios, S/n Valencia Valencia 46023",
    "addr:housenumber":"s / n",
    "addr:postcode":"46023",
    "addr:street":"Calle De Pere Ii El Cerimonios",
    "iso:country":"ES",
    "sg:address":"Calle de Pere Ii El Cerimonios, S/n",
    "sg:city":"Valencia",
    "sg:orig_category":"Ingenier\u00cda, Centros De Estudios (diversos)",
    "sg:phone":"+34 963 31 70 24",
    "sg:postcode":"46023",
    "sg:province":"Valencia",
    "sg:website":"www.pavisal.com",
    "wof:name":"Pavasal Empresa Constructora S.a.",
    "wof:placetype":"venue"
},
  "geometry": {"coordinates":[-0.3487640023,39.4630737305],"type":"Point"}
}