{
  "type": "Feature",
  "properties": {
    "iso:country":"ES",
    "sg:address":"As Quintans, S/n",
    "sg:city":"Quintans",
    "sg:orig_category":"Cerrajer\u00cda, Ferrallista",
    "sg:phone":"+34 986 54 24 64",
    "sg:postcode":"36633",
    "sg:province":"Pontevedra",
    "wof:name":"Saborido Cores Benito",
    "wof:placetype":"venue"
},
  "geometry": {"coordinates":[-8.7952222824,42.2552261353],"type":"Point"}
}