{
  "type": "Feature",
  "properties": {
    "iso:country":"ES",
    "sg:address":"Carrer de Riera, 37",
    "sg:city":"Pineda Mar",
    "sg:orig_category":"Agentes, Concesionarios Y Sucursales De Veh\u00cdculos",
    "sg:phone":"+34 937 62 66 60",
    "sg:postcode":"08397",
    "sg:province":"Barcelona",
    "wof:name":"Vehiculos Veymar S.a.",
    "wof:placetype":"venue"
},
  "geometry": {"coordinates":[2.6868801117,41.6273765564],"type":"Point"}
}