{
  "type": "Feature",
  "properties": {
    "iso:country":"ES",
    "sg:address":"Plaz Concepciones (las), S/n",
    "sg:city":"Le\u00f3n",
    "sg:orig_category":"Quincaller\u00cda (al Por Menor)",
    "sg:phone":"+34 987 25 05 17",
    "sg:postcode":"24003",
    "sg:province":"Le\u00f3n",
    "wof:name":"Yugueros Garcia Manuel Alfredo",
    "wof:placetype":"venue"
},
  "geometry": {"coordinates":[-5.5682911873,42.5982131958],"type":"Point"}
}