{
  "type": "Feature",
  "properties": {
    "addr:full":"C/ Joaquin Garcia Mora, 33 Elche Alicante 03206",
    "addr:housenumber":"33",
    "addr:postcode":"03206",
    "addr:street":"C / Joaquin Garcia Mora",
    "iso:country":"ES",
    "sg:address":"C/ Joaquin Garcia Mora, 33",
    "sg:city":"Elche",
    "sg:orig_category":"Chapister\u00cda",
    "sg:phone":"+34 965 46 76 05",
    "sg:postcode":"03206",
    "sg:province":"Alicante",
    "wof:name":"Jofruc S.l.",
    "wof:placetype":"venue"
},
  "geometry": {"coordinates":[-0.7117210031,38.2754631042],"type":"Point"}
}