{
  "type": "Feature",
  "properties": {
    "iso:country":"ES",
    "sg:address":"Carrer de Pere Iv, 66",
    "sg:city":"Barcelona",
    "sg:orig_category":"Soldadura, Equipo Y Herramental",
    "sg:phone":"+34 933 00 50 06",
    "sg:postcode":"08005",
    "sg:province":"Barcelona",
    "wof:name":"Pont Garcia Jose",
    "wof:placetype":"venue"
},
  "geometry": {"coordinates":[2.1926589012,41.3963737488],"type":"Point"}
}