{
  "type": "Feature",
  "properties": {
    "addr:full":"Rua Castelao, 1 Pontes Garcia Rodriguez A Coru\u00f1a 15320",
    "addr:housenumber":"1",
    "addr:postcode":"15320",
    "addr:street":"Rua Castelao;Corun\u0303A",
    "iso:country":"ES",
    "sg:address":"Rua Castelao, 1",
    "sg:city":"Pontes Garcia Rodriguez",
    "sg:orig_category":"Peluqueros: De Se\u00d1oras",
    "sg:phone":"+34 981 45 15 00",
    "sg:postcode":"15320",
    "sg:province":"A Coru\u00f1a",
    "wof:name":"Silva Vazquez Maria Hermitas",
    "wof:placetype":"venue"
},
  "geometry": {"coordinates":[-7.8529448509,43.44764328],"type":"Point"}
}