{
  "type": "Feature",
  "properties": {
    "addr:full":"Afores, S/n Mollo Girona 17868",
    "addr:housenumber":"s / n",
    "addr:postcode":"17868",
    "addr:street":"Afores",
    "iso:country":"ES",
    "sg:address":"Afores, S/n",
    "sg:city":"Mollo",
    "sg:orig_category":"Cr\u00cda De Animales",
    "sg:phone":"+34 972 74 12 00",
    "sg:postcode":"17868",
    "sg:province":"Girona",
    "wof:name":"Devesa De Santa Creu S.l.",
    "wof:placetype":"venue"
},
  "geometry": {"coordinates":[2.4043900967,42.3481445312],"type":"Point"}
}