{
  "type": "Feature",
  "properties": {
    "addr:full":"Carr Trinitat, 15 Portol Islas Baleares 07141",
    "addr:housenumber":"15",
    "addr:postcode":"07141",
    "addr:street":"Carr Trinitat;Islas",
    "iso:country":"ES",
    "sg:address":"Carr Trinitat, 15",
    "sg:city":"Portol",
    "sg:orig_category":"Peluqueros: De Se\u00d1oras",
    "sg:phone":"+34 971 60 30 65",
    "sg:postcode":"07141",
    "sg:province":"Islas Baleares",
    "wof:name":"Creus Colomar Maria Magdalena",
    "wof:placetype":"venue"
},
  "geometry": {"coordinates":[2.7445349693,39.6195487976],"type":"Point"}
}