{
  "type": "Feature",
  "properties": {
    "addr:full":"Carrer de Deia, 13 Barcelona Barcelona 08016",
    "addr:housenumber":"13",
    "addr:postcode":"08016",
    "addr:street":"Carrer De Deia",
    "iso:country":"ES",
    "sg:address":"Carrer de Deia, 13",
    "sg:city":"Barcelona",
    "sg:orig_category":"Ropa Para Se\u00d1oras Y Caballeros (al Por Menor)",
    "sg:phone":"+34 932 76 82 09",
    "sg:postcode":"08016",
    "sg:province":"Barcelona",
    "wof:name":"Solera Moda 2004 S.l.",
    "wof:placetype":"venue"
},
  "geometry": {"coordinates":[2.176445961,41.4330825806],"type":"Point"}
}