{
  "type": "Feature",
  "properties": {
    "iso:country":"ES",
    "sg:address":"Calle de Madrid, 55",
    "sg:city":"Humanes De Madrid",
    "sg:orig_category":"Cajas De Ahorro",
    "sg:phone":"+34 916 04 82 86",
    "sg:postcode":"28970",
    "sg:province":"Madrid",
    "wof:name":"Caja De Ahorros Y Monte De Piedad De Zaragoza Aragon Y Rioja",
    "wof:placetype":"venue"
},
  "geometry": {"coordinates":[-3.8287389278,40.2526397705],"type":"Point"}
}