{
  "type": "Feature",
  "properties": {
    "addr:full":"Rbla Catalunya, 43 Barcelona Barcelona 08007",
    "addr:housenumber":"43",
    "addr:postcode":"08007",
    "addr:street":"Rbla Catalunya",
    "iso:country":"ES",
    "sg:address":"Rbla Catalunya, 43",
    "sg:city":"Barcelona",
    "sg:orig_category":"Asesor\u00cda Fiscal Y Jur\u00cddica",
    "sg:phone":"+34 932 15 62 95",
    "sg:postcode":"08007",
    "sg:province":"Barcelona",
    "wof:name":"Brustenga Martinez Javier",
    "wof:placetype":"venue"
},
  "geometry": {"coordinates":[2.1645560265,41.3899612427],"type":"Point"}
}