{
  "type": "Feature",
  "properties": {
    "addr:full":"Pl Vila, 11 Martorell Barcelona 08760",
    "addr:housenumber":"11",
    "addr:postcode":"08760",
    "addr:street":"Pl Vila",
    "iso:country":"ES",
    "sg:address":"Pl Vila, 11",
    "sg:city":"Martorell",
    "sg:orig_category":"Farmacias",
    "sg:phone":"+34 937 75 18 97",
    "sg:postcode":"08760",
    "sg:province":"Barcelona",
    "wof:name":"Massaneda Rovira Joaquin",
    "wof:placetype":"venue"
},
  "geometry": {"coordinates":[1.9299119711,41.4744262695],"type":"Point"}
}