{
  "type": "Feature",
  "properties": {
    "addr:full":"Los Herreros-p I San Isidro, 4 Don Benito Badajoz 06400",
    "addr:housenumber":"4",
    "addr:postcode":"06400",
    "addr:street":"San Isidro",
    "iso:country":"ES",
    "sg:address":"Los Herreros-p I San Isidro, 4",
    "sg:city":"Don Benito",
    "sg:orig_category":"Mec\u00c1nico Del Autom\u00d3vil",
    "sg:phone":"+34 924 80 06 24",
    "sg:postcode":"06400",
    "sg:province":"Badajoz",
    "wof:name":"Talleres Aparicio Hermanos S.c.",
    "wof:placetype":"venue"
},
  "geometry": {"coordinates":[-5.8639888763,38.9548797607],"type":"Point"}
}