{
  "type": "Feature",
  "properties": {
    "addr:full":"Carrer de Rector Triado, 2 Barcelona Barcelona 08014",
    "addr:housenumber":"2",
    "addr:postcode":"08014",
    "addr:street":"Carrer De Rector Triado",
    "iso:country":"ES",
    "sg:address":"Carrer de Rector Triado, 2",
    "sg:city":"Barcelona",
    "sg:orig_category":"Art\u00cdculos De Decoraci\u00d3n",
    "sg:phone":"+34 934 23 43 69",
    "sg:postcode":"08014",
    "sg:province":"Barcelona",
    "sg:website":"www.llanosinteriorisme.com",
    "wof:name":"Study Decoracio Hi Tech S.l",
    "wof:placetype":"venue"
},
  "geometry": {"coordinates":[2.1457989216,41.375415802],"type":"Point"}
}