{
  "type": "Feature",
  "properties": {
    "addr:full":"Constitucion, 20 O Temple La Coru\u00f1a 15679",
    "addr:housenumber":"20 o",
    "addr:postcode":"15679",
    "addr:street":"Constitucion;La Corun\u0303A",
    "iso:country":"ES",
    "sg:address":"Constitucion, 20",
    "sg:city":"O Temple",
    "sg:orig_category":"Sociedades, Compa\u00d1\u00cdas Aseguradoras",
    "sg:phone":"+34 981 66 21 53",
    "sg:postcode":"15679",
    "sg:province":"La Coru\u00f1a",
    "wof:name":"Gonzalez Abeledo Miguel",
    "wof:placetype":"venue"
},
  "geometry": {"coordinates":[-8.3576717377,43.3193435669],"type":"Point"}
}