{
  "type": "Feature",
  "properties": {
    "iso:country":"ES",
    "sg:address":"Calle de Gonzalez Serrano, 2",
    "sg:city":"Badajoz",
    "sg:orig_category":"Ropa De Hogar (al Por Menor)",
    "sg:phone":"+34 924 27 22 54",
    "sg:postcode":"06006",
    "sg:province":"Badajoz",
    "wof:name":"Vedir Hogar S.a.l.",
    "wof:placetype":"venue"
},
  "geometry": {"coordinates":[-6.9838790894,38.8898887634],"type":"Point"}
}