{
  "type": "Feature",
  "properties": {
    "addr:full":"Carr Sant Francesc Assis, 33 Badalona Barcelona 08911",
    "addr:housenumber":"33",
    "addr:postcode":"08911",
    "addr:street":"Carr Sant Francesc Assis",
    "iso:country":"ES",
    "sg:address":"Carr Sant Francesc Assis, 33",
    "sg:city":"Badalona",
    "sg:orig_category":"Guarder\u00cdas",
    "sg:phone":"+34 933 84 00 39",
    "sg:postcode":"08911",
    "sg:province":"Barcelona",
    "wof:name":"Guarderia Rialles S.c.",
    "wof:placetype":"venue"
},
  "geometry": {"coordinates":[2.2493913174,41.4500923157],"type":"Point"}
}