{
  "type": "Feature",
  "properties": {
    "iso:country":"ES",
    "sg:address":"Plaz Hispanidad (de La), 1",
    "sg:city":"Cuenca",
    "sg:orig_category":"Peluquer\u00cdas, Peluquer\u00cda Mixta",
    "sg:phone":"+34 969 23 73 63",
    "sg:postcode":"16004",
    "sg:province":"Cuenca",
    "wof:name":"Chamon Y Roca S.l.",
    "wof:placetype":"venue"
},
  "geometry": {"coordinates":[-2.1362390518,40.0720710754],"type":"Point"}
}