{
  "type": "Feature",
  "properties": {
    "addr:full":"Pase Cuellar, 55 Zaragoza Zaragoza 50007",
    "addr:housenumber":"55",
    "addr:postcode":"50007",
    "iso:country":"ES",
    "sg:address":"Pase Cuellar, 55",
    "sg:city":"Zaragoza",
    "sg:orig_category":"Molduras, Junquillos, Listones Y Molduras Perforadas",
    "sg:phone":"+34 976 38 09 05",
    "sg:postcode":"50007",
    "sg:province":"Zaragoza",
    "wof:name":"Alonso Aberasturi Jose Vidal",
    "wof:placetype":"venue"
},
  "geometry": {"coordinates":[-0.8846430182,41.6355133057],"type":"Point"}
}