{
  "type": "Feature",
  "properties": {
    "iso:country":"ES",
    "sg:address":"Carrer de Sant Bartomeu, 58",
    "sg:city":"Campello",
    "sg:orig_category":"Sociedades, Compa\u00d1\u00cdas Aseguradoras",
    "sg:phone":"+34 965 63 16 16",
    "sg:postcode":"03560",
    "sg:province":"Alicante",
    "wof:name":"Knight Insurance Brokers S.a.",
    "wof:placetype":"venue"
},
  "geometry": {"coordinates":[-0.390888989,38.4253807068],"type":"Point"}
}