{
  "type": "Feature",
  "properties": {
    "addr:full":"Calle de Tierra De Barros, 3 Villanueva Serena Badajoz 06700",
    "addr:housenumber":"3",
    "addr:postcode":"06700",
    "addr:street":"Calle De Tierra;Barros",
    "iso:country":"ES",
    "sg:address":"Calle de Tierra De Barros, 3",
    "sg:city":"Villanueva Serena",
    "sg:orig_category":"Agencias Y Agentes Comerciales, Representantes",
    "sg:phone":"+34 924 84 32 05",
    "sg:postcode":"06700",
    "sg:province":"Badajoz",
    "wof:name":"Garcia Gallego Alfredo",
    "wof:placetype":"venue"
},
  "geometry": {"coordinates":[-5.8066940308,38.9718360901],"type":"Point"}
}