{
  "type": "Feature",
  "properties": {
    "iso:country":"ES",
    "sg:address":"Calle de Jose Maria Martorell, S/n",
    "sg:city":"Cordoba",
    "sg:orig_category":"Ropa Para Se\u00d1oras (al Por Menor)",
    "sg:phone":"+34 957 45 62 35",
    "sg:postcode":"14005",
    "sg:province":"C\u00f3rdoba",
    "wof:name":"Lopez Rosero Teresa",
    "wof:placetype":"venue"
},
  "geometry": {"coordinates":[-4.7968039513,37.8772315979],"type":"Point"}
}