{
  "type": "Feature",
  "properties": {
    "iso:country":"ES",
    "sg:address":"Leirado, S/n",
    "sg:city":"Leirado",
    "sg:orig_category":"Empresas De Electricidad En General",
    "sg:phone":"+34 988 48 28 02",
    "sg:postcode":"32814",
    "sg:province":"Ourense",
    "wof:name":"Hidroelectrica San Miguel S.a.",
    "wof:placetype":"venue"
},
  "geometry": {"coordinates":[-8.0899791718,42.1302108765],"type":"Point"}
}