{
  "type": "Feature",
  "properties": {
    "addr:full":"Av Marina, S/n S. Boi Llobregat Barcelona 08830",
    "addr:housenumber":"s",
    "addr:postcode":"08830",
    "addr:street":"Av Marina;/ N",
    "iso:country":"ES",
    "sg:address":"Av Marina, S/n",
    "sg:city":"S. Boi Llobregat",
    "sg:orig_category":"Ropa Para Se\u00d1oras (al Por Menor)",
    "sg:phone":"+34 936 54 81 08",
    "sg:postcode":"08830",
    "sg:province":"Barcelona",
    "wof:name":"Encuentro Modas S.a.",
    "wof:placetype":"venue"
},
  "geometry": {"coordinates":[2.0449779034,41.3480606079],"type":"Point"}
}