{
  "type": "Feature",
  "properties": {
    "addr:full":"Calle de Fartet, 6 Mar Azul Alicante 03730",
    "addr:housenumber":"6",
    "addr:postcode":"03730",
    "addr:street":"Calle De Fartet",
    "iso:country":"ES",
    "sg:address":"Calle de Fartet, 6",
    "sg:city":"Mar Azul",
    "sg:orig_category":"Inmobiliaria (agencias)",
    "sg:phone":"+34 966 47 16 64",
    "sg:postcode":"03730",
    "sg:province":"Alicante",
    "wof:name":"Margarita Javea S.l.",
    "wof:placetype":"venue"
},
  "geometry": {"coordinates":[0.1668650061,38.7890739441],"type":"Point"}
}