{
  "type": "Feature",
  "properties": {
    "iso:country":"ES",
    "sg:address":"Carrer de Tallers, 81",
    "sg:city":"Barcelona",
    "sg:orig_category":"Molduras, Junquillos, Listones Y Molduras Perforadas",
    "sg:phone":"+34 933 02 26 07",
    "sg:postcode":"08001",
    "sg:province":"Barcelona",
    "wof:name":"Balboa Cela Jaime",
    "wof:placetype":"venue"
},
  "geometry": {"coordinates":[2.1640338898,41.3852348328],"type":"Point"}
}