{
  "type": "Feature",
  "properties": {
    "addr:full":"Calle de Leopoldo Romeo, 30 Zaragoza Zaragoza 50002",
    "addr:housenumber":"30",
    "addr:postcode":"50002",
    "addr:street":"Calle De Leopoldo Romeo",
    "iso:country":"ES",
    "sg:address":"Calle de Leopoldo Romeo, 30",
    "sg:city":"Zaragoza",
    "sg:orig_category":"Art\u00cdculos Reciclados",
    "sg:phone":"+34 976 59 60 27",
    "sg:postcode":"50002",
    "sg:province":"Zaragoza",
    "sg:website":"www.hercatoner.com",
    "wof:name":"Hercatoner S.c",
    "wof:placetype":"venue"
},
  "geometry": {"coordinates":[-0.8657950163,41.6471290588],"type":"Point"}
}