{
  "type": "Feature",
  "properties": {
    "iso:country":"ES",
    "sg:address":"Calle de Hacienda De Pavones, S/n",
    "sg:city":"Madrid",
    "sg:orig_category":"Quincaller\u00cda (al Por Menor)",
    "sg:phone":"+34 917 72 33 11",
    "sg:postcode":"28030",
    "sg:province":"Madrid",
    "wof:name":"Cuesta Macias Alberto",
    "wof:placetype":"venue"
},
  "geometry": {"coordinates":[-3.6481039524,40.4046134949],"type":"Point"}
}