{
  "type": "Feature",
  "properties": {
    "iso:country":"ES",
    "sg:address":"Pi Y Margall, 27",
    "sg:city":"Massanassa",
    "sg:orig_category":"Marmolistas Funerarios",
    "sg:phone":"+34 961 25 01 33",
    "sg:postcode":"46470",
    "sg:province":"Valencia",
    "wof:name":"Vila Raga Juan Luis",
    "wof:placetype":"venue"
},
  "geometry": {"coordinates":[-0.3994829953,39.4108200073],"type":"Point"}
}