{
  "type": "Feature",
  "properties": {
    "iso:country":"ES",
    "sg:address":"Calle de Azkuene, 6",
    "sg:city":"Pasaia",
    "sg:orig_category":"Panader\u00cdas, Panader\u00cdas",
    "sg:phone":"+34 943 40 02 42",
    "sg:postcode":"20110",
    "sg:province":"Guip\u00f9zcoa",
    "wof:name":"Maite Cantero Rodriguez",
    "wof:placetype":"venue"
},
  "geometry": {"coordinates":[-1.9370224476,43.3228721619],"type":"Point"}
}