{
  "type": "Feature",
  "properties": {
    "addr:full":"Carrer de Joan Crespi, 26 Palma Islas Baleares 07014",
    "addr:housenumber":"26",
    "addr:postcode":"07014",
    "addr:street":"Carrer De Joan Crespi",
    "iso:country":"ES",
    "sg:address":"Carrer de Joan Crespi, 26",
    "sg:city":"Palma",
    "sg:orig_category":"Cajas De Ahorro",
    "sg:phone":"+34 971 73 82 40",
    "sg:postcode":"07014",
    "sg:province":"Islas Baleares",
    "sg:website":"www.lacaixa.es",
    "wof:name":"Caixa D'estalvis I Pensions De Barcelona",
    "wof:placetype":"venue"
},
  "geometry": {"coordinates":[2.6342699528,39.5747070312],"type":"Point"}
}