{
  "type": "Feature",
  "properties": {
    "addr:full":"Barr Arroxinas, 4 Luarca Asturias 33700",
    "addr:housenumber":"4",
    "addr:postcode":"33700",
    "addr:street":"Arroxinas",
    "iso:country":"ES",
    "sg:address":"Barr Arroxinas, 4",
    "sg:city":"Luarca",
    "sg:orig_category":"Empresas De Labores Complejas De Carga Y Descarga, Montaje Con Elevadores",
    "sg:phone":"+34 985 64 00 96",
    "sg:postcode":"33700",
    "sg:province":"Asturias",
    "wof:name":"Suboccidente S.c.",
    "wof:placetype":"venue"
},
  "geometry": {"coordinates":[-6.5366139412,43.5418891907],"type":"Point"}
}