{
  "type": "Feature",
  "properties": {
    "iso:country":"ES",
    "sg:address":"Calle de Tarragona, 30",
    "sg:city":"Torre-pacheco",
    "sg:orig_category":"Plomeros",
    "sg:phone":"+34 968 57 94 32",
    "sg:postcode":"30700",
    "sg:province":"Murcia",
    "wof:name":"Fonsantonio S.l.",
    "wof:placetype":"venue"
},
  "geometry": {"coordinates":[-1.1158390045,37.985912323],"type":"Point"}
}