{
  "type": "Feature",
  "properties": {
    "iso:country":"ES",
    "sg:address":"Cami Golmes, S/n",
    "sg:city":"Miralcamp",
    "sg:orig_category":"Cooperativas Agr\u00cdcolas",
    "sg:phone":"+34 973 60 29 00",
    "sg:postcode":"25242",
    "sg:province":"Lleida",
    "wof:name":"Miralcamp Fruits S.c.c.l.",
    "wof:placetype":"venue"
},
  "geometry": {"coordinates":[0.8800699711,41.6063842773],"type":"Point"}
}