{
  "type": "Feature",
  "properties": {
    "addr:full":"Carr Francesc Ciurana, 21 Girona Girona 17002",
    "addr:housenumber":"21",
    "addr:postcode":"17002",
    "addr:street":"Carr Francesc Ciurana",
    "iso:country":"ES",
    "sg:address":"Carr Francesc Ciurana, 21",
    "sg:city":"Girona",
    "sg:orig_category":"Administradores De Bienes Y Delegados De Comunidades De Propietarios",
    "sg:phone":"+34 972 21 49 26",
    "sg:postcode":"17002",
    "sg:province":"Girona",
    "wof:name":"Portulas Planells Maria Dolores",
    "wof:placetype":"venue"
},
  "geometry": {"coordinates":[2.8181190491,41.976776123],"type":"Point"}
}