{
  "type": "Feature",
  "properties": {
    "iso:country":"ES",
    "sg:address":"Calle de Alta, 62",
    "sg:city":"Santander",
    "sg:orig_category":"Estancos",
    "sg:phone":"+34 942 37 63 71",
    "sg:postcode":"39008",
    "sg:province":"Cantabria",
    "wof:name":"Fernandez Cieza Maria Dolores",
    "wof:placetype":"venue"
},
  "geometry": {"coordinates":[-3.8182954788,43.4588394165],"type":"Point"}
}