{
  "type": "Feature",
  "properties": {
    "iso:country":"ES",
    "sg:address":"Plaz Bilbao, 2",
    "sg:city":"Vitoria-gasteiz",
    "sg:classifiers":[
        {
            "category":"Autos & Motor Vehicles",
            "subcategory":"Automobile Sales",
            "type":"Retail Goods"
        }
    ],
    "sg:phone":"+34 945 25 37 66",
    "sg:postcode":"01002",
    "sg:province":"\u00c1lava",
    "wof:name":"Auto Escuela Salazar S.l.",
    "wof:placetype":"venue"
},
  "geometry": {"coordinates":[-2.6699819565,42.852142334],"type":"Point"}
}