{
  "type": "Feature",
  "properties": {
    "iso:country":"ES",
    "sg:address":"Carrer de Montseny, 174",
    "sg:city":"Hospitalet Llobregat",
    "sg:orig_category":"Tapicer\u00cdas",
    "sg:phone":"+34 934 49 33 36",
    "sg:postcode":"08904",
    "sg:province":"Barcelona",
    "wof:name":"Fernandez Monje Jose Manuel",
    "wof:placetype":"venue"
},
  "geometry": {"coordinates":[2.1175150871,41.369140625],"type":"Point"}
}