{
  "type": "Feature",
  "properties": {
    "addr:full":"Carrer de Moli, 57 Barcelona Barcelona 08016",
    "addr:housenumber":"57",
    "addr:postcode":"08016",
    "addr:street":"Carrer De Moli",
    "iso:country":"ES",
    "sg:address":"Carrer de Moli, 57",
    "sg:city":"Barcelona",
    "sg:orig_category":"Centros De Educaci\u00d3n Especial",
    "sg:phone":"+34 933 50 36 04",
    "sg:postcode":"08016",
    "sg:province":"Barcelona",
    "wof:name":"Ajuntament De Barcelona",
    "wof:placetype":"venue"
},
  "geometry": {"coordinates":[2.1809546947,41.4443664551],"type":"Point"}
}