{
  "type": "Feature",
  "properties": {
    "iso:country":"ES",
    "sg:address":"Carrer de Alfaz Del Pi, 25",
    "sg:city":"Cala",
    "sg:orig_category":"Fabricaci\u00d3n De Juegos Y Juguetes",
    "sg:phone":"+34 965 85 15 32",
    "sg:postcode":"03509",
    "sg:province":"Alicante",
    "wof:name":"Juguetes Pastor S.l.",
    "wof:placetype":"venue"
},
  "geometry": {"coordinates":[-0.1924789995,38.5512695312],"type":"Point"}
}