{
  "type": "Feature",
  "properties": {
    "iso:country":"ES",
    "sg:address":"Calle de Nueva De Jardines, S/n",
    "sg:city":"Albolote",
    "sg:orig_category":"Carnicer\u00cdas, Carnicer\u00cdas",
    "sg:phone":"+34 958 46 59 75",
    "sg:postcode":"18220",
    "sg:province":"Granada",
    "wof:name":"Autoservicio Matilde S.l.",
    "wof:placetype":"venue"
},
  "geometry": {"coordinates":[-3.6553556919,37.2307853699],"type":"Point"}
}