{
  "type": "Feature",
  "properties": {
    "addr:full":"Cigales, Km. 0003,0 Corcos Valladolid 47280",
    "addr:postcode":"47280",
    "addr:street":"Cigales Km. 0003,0 Corcos",
    "iso:country":"ES",
    "sg:address":"Cigales, Km. 0003,0",
    "sg:city":"Corcos",
    "sg:orig_category":"Productores Recolectores, Venta Directa De Vinos",
    "sg:phone":"+34 983 58 10 29",
    "sg:postcode":"47280",
    "sg:province":"Valladolid",
    "wof:name":"El Coto De Rioja S.a.",
    "wof:placetype":"venue"
},
  "geometry": {"coordinates":[-4.6920690536,41.8095283508],"type":"Point"}
}