{
  "type": "Feature",
  "properties": {
    "addr:full":"Okobio, 13 Belauntza Guip\u00f9zcoa 20491",
    "addr:housenumber":"13",
    "addr:postcode":"20491",
    "addr:street":"Okobio;Guipu\u0300Zcoa",
    "iso:country":"ES",
    "sg:address":"Okobio, 13",
    "sg:city":"Belauntza",
    "sg:orig_category":"Muebles",
    "sg:phone":"+34 943 67 52 91",
    "sg:postcode":"20491",
    "sg:province":"Guip\u00f9zcoa",
    "wof:name":"Industrias Belaunza S.a.",
    "wof:placetype":"venue"
},
  "geometry": {"coordinates":[-2.0537540913,43.1227455139],"type":"Point"}
}