{
  "type": "Feature",
  "properties": {
    "addr:full":"Plaz Mayor, 2 Elda Alicante 03600",
    "addr:housenumber":"2",
    "addr:postcode":"03600",
    "addr:street":"Plaz Mayor",
    "iso:country":"ES",
    "sg:address":"Plaz Mayor, 2",
    "sg:city":"Elda",
    "sg:orig_category":"Empresas De Vigilancia, Guardia Y Protecci\u00d3n",
    "sg:phone":"+34 966 98 02 83",
    "sg:postcode":"03600",
    "sg:province":"Alicante",
    "wof:name":"Seguridad Espa\u00d1ola Y Servicios S.l.",
    "wof:placetype":"venue"
},
  "geometry": {"coordinates":[-0.7941219807,38.4786262512],"type":"Point"}
}