{
  "type": "Feature",
  "properties": {
    "iso:country":"ES",
    "sg:address":"Avda Palencia, 51",
    "sg:city":"Valladolid",
    "sg:orig_category":"Carnicer\u00cdas, Carnicer\u00cdas",
    "sg:phone":"+34 983 26 42 86",
    "sg:postcode":"47010",
    "sg:province":"Valladolid",
    "wof:name":"Perez Olandia Francisco Javier",
    "wof:placetype":"venue"
},
  "geometry": {"coordinates":[-4.7155652046,41.662525177],"type":"Point"}
}