{
  "type": "Feature",
  "properties": {
    "iso:country":"ES",
    "sg:address":"Carrer de Frederic Mistral, S/n",
    "sg:city":"Palma",
    "sg:orig_category":"M\u00c9dicos: An\u00c1lisis Cl\u00cdnicos",
    "sg:phone":"+34 971 46 09 36",
    "sg:postcode":"07006",
    "sg:province":"Islas Baleares",
    "wof:name":"Laboratori Balear De Analisis S.l.",
    "wof:placetype":"venue"
},
  "geometry": {"coordinates":[2.6581509113,39.5725364685],"type":"Point"}
}