{
  "type": "Feature",
  "properties": {
    "iso:country":"ES",
    "sg:address":"Calle de Quart, 139",
    "sg:city":"Valencia",
    "sg:orig_category":"Abogados",
    "sg:phone":"+34 963 82 39 25",
    "sg:postcode":"46008",
    "sg:province":"Valencia",
    "wof:name":"Millan Marco Maria Carmen",
    "wof:placetype":"venue"
},
  "geometry": {"coordinates":[-0.3916310072,39.4743347168],"type":"Point"}
}