{
  "type": "Feature",
  "properties": {
    "iso:country":"ES",
    "sg:address":"Calle de Doctor Fleming, 9",
    "sg:city":"Aguilas",
    "sg:orig_category":"Asociaciones Y Clubs Deportivos",
    "sg:phone":"+34 968 41 31 54",
    "sg:postcode":"30880",
    "sg:province":"Murcia",
    "wof:name":"Juguetes Y Deportes Sanchez S.l.l.",
    "wof:placetype":"venue"
},
  "geometry": {"coordinates":[-1.5858191252,37.405872345],"type":"Point"}
}