{
  "type": "Feature",
  "properties": {
    "addr:full":"Calle de Pilar, 1 Zarza Badajoz 06830",
    "addr:postcode":"06830",
    "addr:street":"Calle De Pilar;Zarza",
    "iso:country":"ES",
    "sg:address":"Calle de Pilar, 1",
    "sg:city":"Zarza",
    "sg:orig_category":"Molduras, Junquillos, Listones Y Molduras Perforadas",
    "sg:phone":"+34 924 36 62 26",
    "sg:postcode":"06830",
    "sg:province":"Badajoz",
    "wof:name":"Gomez Almendro Ramona",
    "wof:placetype":"venue"
},
  "geometry": {"coordinates":[-6.2164092064,38.8193283081],"type":"Point"}
}