{
  "type": "Feature",
  "properties": {
    "addr:full":"Sotillo, 11 Castell De Ferro Granada 18740",
    "addr:housenumber":"11",
    "addr:postcode":"18740",
    "addr:street":"Sotillo",
    "iso:country":"ES",
    "sg:address":"Sotillo, 11",
    "sg:city":"Castell De Ferro",
    "sg:orig_category":"Frutas Y Legumbres Frescas (al Por Mayor)",
    "sg:phone":"+34 958 83 02 90",
    "sg:postcode":"18740",
    "sg:province":"Granada",
    "wof:name":"Agrocastell S.a.",
    "wof:placetype":"venue"
},
  "geometry": {"coordinates":[-3.3678133488,36.7275161743],"type":"Point"}
}