{
  "type": "Feature",
  "properties": {
    "iso:country":"ES",
    "sg:address":"Barriada Del Poeta Juan Rejano, S/n",
    "sg:city":"Puente-genil",
    "sg:orig_category":"Alimentaci\u00d3n General (al Por Menor)",
    "sg:phone":"+34 957 60 12 90",
    "sg:postcode":"14500",
    "sg:province":"C\u00f3rdoba",
    "wof:name":"Campa\u00f1a Luque Francisco",
    "wof:placetype":"venue"
},
  "geometry": {"coordinates":[-4.75476408,37.3979568481],"type":"Point"}
}