{
  "type": "Feature",
  "properties": {
    "addr:full":"Calle de Barco, 25 Madrid Madrid 28004",
    "addr:housenumber":"25",
    "addr:postcode":"madrid;28004",
    "addr:street":"Calle De Barco",
    "iso:country":"ES",
    "sg:address":"Calle de Barco, 25",
    "sg:city":"Madrid",
    "sg:orig_category":"Promotores Constructores",
    "sg:phone":"+34 915 21 22 21",
    "sg:postcode":"28004",
    "sg:province":"Madrid",
    "sg:website":"www.hermanosconejero.com",
    "wof:name":"Hermanos Conejero S.l.",
    "wof:placetype":"venue"
},
  "geometry": {"coordinates":[-3.7026228905,40.42212677],"type":"Point"}
}