{
  "type": "Feature",
  "properties": {
    "addr:full":"Calle de Mayor, 65 Lerin Navarra 31260",
    "addr:housenumber":"65",
    "addr:postcode":"31260",
    "addr:street":"Calle De Mayor",
    "iso:country":"ES",
    "sg:address":"Calle de Mayor, 65",
    "sg:city":"Lerin",
    "sg:classifiers":[
        {
            "category":"Professional",
            "subcategory":"Management & Consulting",
            "type":"Services"
        }
    ],
    "sg:phone":"+34 948 53 01 27",
    "sg:postcode":"31260",
    "sg:province":"Navarra",
    "sg:tags":[
        "asesor\u00cda",
        "en",
        "marketing"
    ],
    "wof:name":"Martinez Aroniz Maria Asuncion",
    "wof:placetype":"venue"
},
  "geometry": {"coordinates":[-1.973222971,42.4817352295],"type":"Point"}
}