{
  "type": "Feature",
  "properties": {
    "iso:country":"ES",
    "sg:address":"Calle de Acacias (las), 1",
    "sg:city":"Cordoba",
    "sg:orig_category":"Sociedades, Compa\u00d1\u00cdas Aseguradoras",
    "sg:phone":"+34 957 27 96 04",
    "sg:postcode":"14006",
    "sg:province":"C\u00f3rdoba",
    "wof:name":"Salbal S.l.",
    "wof:placetype":"venue"
},
  "geometry": {"coordinates":[-4.7835440636,37.8953094482],"type":"Point"}
}