{
  "type": "Feature",
  "properties": {
    "iso:country":"ES",
    "sg:address":"Lemayo, 3",
    "sg:city":"Laracha",
    "sg:orig_category":"Empresas De Desmonte",
    "sg:phone":"+34 981 60 60 03",
    "sg:postcode":"15145",
    "sg:province":"A Coru\u00f1a",
    "wof:name":"Sotelo Regueira Jose Antonio",
    "wof:placetype":"venue"
},
  "geometry": {"coordinates":[-8.5750217438,43.1730537415],"type":"Point"}
}