{
  "type": "Feature",
  "properties": {
    "addr:full":"Rua Algalia De Arriba (da), 2 Santiago De Compostela A Coru\u00f1a 15704",
    "addr:postcode":"15704",
    "addr:street":"Rua Algalia De;Da;Corun\u0303A",
    "iso:country":"ES",
    "sg:address":"Rua Algalia De Arriba (da), 2",
    "sg:city":"Santiago De Compostela",
    "sg:orig_category":"Arquitectos",
    "sg:phone":"+34 981 57 53 88",
    "sg:postcode":"15704",
    "sg:province":"A Coru\u00f1a",
    "wof:name":"Taller 8 Arquitectos S.c.",
    "wof:placetype":"venue"
},
  "geometry": {"coordinates":[-8.5422410965,42.8812065125],"type":"Point"}
}