{
  "type": "Feature",
  "properties": {
    "iso:country":"ES",
    "sg:address":"Avda Vegas Altas, 31",
    "sg:city":"Don Benito",
    "sg:orig_category":"Transporte En General",
    "sg:phone":"+34 924 80 80 68",
    "sg:postcode":"06400",
    "sg:province":"Badajoz",
    "wof:name":"Rubio Anes S.l.",
    "wof:placetype":"venue"
},
  "geometry": {"coordinates":[-5.8493008614,38.9621276855],"type":"Point"}
}