{
  "type": "Feature",
  "properties": {
    "iso:country":"ES",
    "sg:address":"Avda Jose Ortega Y Gasset, 124",
    "sg:city":"Malaga",
    "sg:orig_category":"Montaje (empresas De)",
    "sg:phone":"+34 952 34 85 95",
    "sg:postcode":"29006",
    "sg:province":"M\u00e1laga",
    "sg:website":"www.eigra.es",
    "wof:name":"Fluelec Eigra S.a.",
    "wof:placetype":"venue"
},
  "geometry": {"coordinates":[-4.4570999146,36.7090110779],"type":"Point"}
}