{
  "type": "Feature",
  "properties": {
    "addr:full":"Calle de Herminio Madinaveitia, 18 Bis Vitoria-gasteiz \u00c1lava 01006",
    "addr:housenumber":"18 bis",
    "addr:postcode":"01006",
    "addr:street":"Calle De Herminio Madinaveitia",
    "iso:country":"ES",
    "sg:address":"Calle de Herminio Madinaveitia, 18 Bis",
    "sg:city":"Vitoria-gasteiz",
    "sg:orig_category":"Artes Gr\u00c1ficas, Artes Pl\u00c1sticas (curso)",
    "sg:phone":"+34 945 00 03 81",
    "sg:postcode":"01006",
    "sg:province":"\u00c1lava",
    "wof:name":"Eusko Printing Service, S.l",
    "wof:placetype":"venue"
},
  "geometry": {"coordinates":[-2.6638000011,42.8350296021],"type":"Point"}
}