{
  "type": "Feature",
  "properties": {
    "addr:full":"Pase Zorrilla, 32 Valladolid Valladolid 47006",
    "addr:housenumber":"32",
    "addr:postcode":"47006",
    "addr:street":"Zorrilla",
    "iso:country":"ES",
    "sg:address":"Pase Zorrilla, 32",
    "sg:city":"Valladolid",
    "sg:orig_category":"Trajes Y Adornos De Boda (confecci\u00d3n, Al Por Menor)",
    "sg:phone":"+34 983 33 92 85",
    "sg:postcode":"47006",
    "sg:province":"Valladolid",
    "sg:website":"www.pronovias.com",
    "wof:name":"Financiera Pronovias S.a.",
    "wof:placetype":"venue"
},
  "geometry": {"coordinates":[-4.7335910797,41.6455192566],"type":"Point"}
}