{
  "type": "Feature",
  "properties": {
    "iso:country":"ES",
    "sg:address":"El Gramola, 3",
    "sg:city":"Gelves",
    "sg:orig_category":"Supermercados Y Hipermercados",
    "sg:phone":"+34 954 17 26 78",
    "sg:postcode":"41120",
    "sg:province":"Sevilla",
    "wof:name":"Aguilar Garcia Feliciano",
    "wof:placetype":"venue"
},
  "geometry": {"coordinates":[-6.0282196999,37.3281745911],"type":"Point"}
}