{
  "type": "Feature",
  "properties": {
    "addr:full":"Rond Sant Pere, 19 Barcelona Barcelona 08010",
    "addr:housenumber":"19",
    "addr:postcode":"08010",
    "addr:street":"Sant Pere",
    "iso:country":"ES",
    "sg:address":"Rond Sant Pere, 19",
    "sg:city":"Barcelona",
    "sg:orig_category":"Agencias De Viajes",
    "sg:phone":"+34 933 17 50 99",
    "sg:postcode":"08010",
    "sg:province":"Barcelona",
    "sg:website":"www.politours.com",
    "wof:name":"Poli-tours S. A",
    "wof:placetype":"venue"
},
  "geometry": {"coordinates":[2.1738159657,41.3894882202],"type":"Point"}
}