{
  "type": "Feature",
  "properties": {
    "iso:country":"ES",
    "sg:address":"Calle de San Roque, 21",
    "sg:city":"Alfafar",
    "sg:orig_category":"Carnicer\u00cdas, Carnicer\u00cdas",
    "sg:phone":"+34 963 75 01 25",
    "sg:postcode":"46910",
    "sg:province":"Valencia",
    "wof:name":"Lopez Cabello Clemente",
    "wof:placetype":"venue"
},
  "geometry": {"coordinates":[-0.387796998,39.421081543],"type":"Point"}
}