{
  "type": "Feature",
  "properties": {
    "addr:full":"Calle de Marques De La Ensenada, 1 Logro\u00f1o La Rioja 26003",
    "addr:housenumber":"1",
    "addr:postcode":"26003",
    "addr:street":"Calle De Marques De La Ensenada;Rioja",
    "iso:country":"ES",
    "sg:address":"Calle de Marques De La Ensenada, 1",
    "sg:city":"Logro\u00f1o",
    "sg:orig_category":"Laboratorios Y Trabajos De Fotograf\u00cda, V\u00cddeo Y Cine",
    "sg:phone":"+34 941 24 64 65",
    "sg:postcode":"26003",
    "sg:province":"La Rioja",
    "wof:name":"Landaluce Esteban Fernando",
    "wof:placetype":"venue"
},
  "geometry": {"coordinates":[-2.4374539852,42.4647521973],"type":"Point"}
}