{
  "type": "Feature",
  "properties": {
    "iso:country":"ES",
    "sg:address":"Carrer de Son Oliva, 17",
    "sg:city":"Palma",
    "sg:orig_category":"Mec\u00c1nico Del Autom\u00d3vil",
    "sg:phone":"+34 971 29 45 12",
    "sg:postcode":"07009",
    "sg:province":"Islas Baleares",
    "wof:name":"Leon Gallego Jose",
    "wof:placetype":"venue"
},
  "geometry": {"coordinates":[2.6613850594,39.5857772827],"type":"Point"}
}