{
  "type": "Feature",
  "properties": {
    "iso:country":"ES",
    "sg:address":"Pase Ezequiel Gonzalez, 29",
    "sg:city":"Segovia",
    "sg:orig_category":"Abogados",
    "sg:phone":"+34 921 46 15 01",
    "sg:postcode":"40002",
    "sg:province":"Segovia",
    "sg:website":"www.paginasamarillas.es",
    "wof:name":"Sanz Gomez Julian",
    "wof:placetype":"venue"
},
  "geometry": {"coordinates":[-4.1205067635,40.9441604614],"type":"Point"}
}