{
  "type": "Feature",
  "properties": {
    "iso:country":"ES",
    "sg:address":"Calle de Pozo De Las Nieves, 8",
    "sg:city":"Torrejon Ardoz",
    "sg:orig_category":"Agencias Y Asesores De Publicidad",
    "sg:phone":"+34 916 75 80 75",
    "sg:postcode":"28850",
    "sg:province":"Madrid",
    "wof:name":"11 Quick S.l.",
    "wof:placetype":"venue"
},
  "geometry": {"coordinates":[-3.466272,40.44825],"type":"Point"}
}