{
  "type": "Feature",
  "properties": {
    "addr:full":"Calle de Navas, 33 Zuera Zaragoza 50800",
    "addr:housenumber":"33",
    "addr:postcode":"50800",
    "addr:street":"Calle De Navas",
    "iso:country":"ES",
    "sg:address":"Calle de Navas, 33",
    "sg:city":"Zuera",
    "sg:orig_category":"Cajas De Ahorro",
    "sg:phone":"+34 976 68 02 35",
    "sg:postcode":"50800",
    "sg:province":"Zaragoza",
    "sg:website":"www.ruralvia.com",
    "wof:name":"Caja Rural Aragonesa Y De Los Pirineos",
    "wof:placetype":"venue"
},
  "geometry": {"coordinates":[-0.7883819938,41.8679122925],"type":"Point"}
}