{
  "type": "Feature",
  "properties": {
    "iso:country":"ES",
    "sg:address":"Plaz Doce De Octubre, S/n",
    "sg:city":"Huelva",
    "sg:orig_category":"Parques De Atracciones Y Centros De Esparcimiento",
    "sg:phone":"+34 959 28 00 65",
    "sg:postcode":"21001",
    "sg:province":"Huelva",
    "wof:name":"Atracciones La Cinta S.l.",
    "wof:placetype":"venue"
},
  "geometry": {"coordinates":[-6.95692873,37.2557411194],"type":"Point"}
}