{
  "type": "Feature",
  "properties": {
    "addr:full":"Emilia Pardo Bazan, S/n Valdemoro Madrid 28340",
    "addr:housenumber":"s / n",
    "addr:postcode":"28340",
    "addr:street":"Emilia Pardo Bazan",
    "iso:country":"ES",
    "sg:address":"Emilia Pardo Bazan, S/n",
    "sg:city":"Valdemoro",
    "sg:orig_category":"Inmobiliaria (agencias)",
    "sg:phone":"+34 918 94 92 07",
    "sg:postcode":"28340",
    "sg:province":"Madrid",
    "wof:name":"Bigeco S.a.",
    "wof:placetype":"venue"
},
  "geometry": {"coordinates":[-3.6902740002,40.1936416626],"type":"Point"}
}