{
  "type": "Feature",
  "properties": {
    "iso:country":"ES",
    "sg:address":"Calle de Victoria, 10",
    "sg:city":"San Javier",
    "sg:orig_category":"Asesor\u00cda Fiscal Y Jur\u00cddica",
    "sg:phone":"+34 968 19 23 73",
    "sg:postcode":"30730",
    "sg:province":"Murcia",
    "wof:name":"Aparicio Montoya Domingo",
    "wof:placetype":"venue"
},
  "geometry": {"coordinates":[-0.8336731791,37.8059387207],"type":"Point"}
}