{
  "type": "Feature",
  "properties": {
    "iso:country":"ES",
    "sg:address":"Calle de Cordoba, 31",
    "sg:city":"Antequera",
    "sg:orig_category":"Carnicer\u00cdas, Carnicer\u00cdas",
    "sg:phone":"+34 952 84 49 16",
    "sg:postcode":"29200",
    "sg:province":"M\u00e1laga",
    "wof:name":"Embutidos Luis Chacon S.l.",
    "wof:placetype":"venue"
},
  "geometry": {"coordinates":[-4.5619130135,37.0259246826],"type":"Point"}
}