{
  "type": "Feature",
  "properties": {
    "iso:country":"ES",
    "sg:address":"Calle de Ramon Pelayo, 19",
    "sg:city":"Colindres",
    "sg:orig_category":"Agentes Generales De Seguros",
    "sg:phone":"+34 942 65 16 25",
    "sg:postcode":"39750",
    "sg:province":"Cantabria",
    "wof:name":"Aja Seguros Y Administraciones S. L.",
    "wof:placetype":"venue"
},
  "geometry": {"coordinates":[-3.4478852749,43.3960762024],"type":"Point"}
}