{
  "type": "Feature",
  "properties": {
    "addr:full":"Calle de Hernan Cortes, S/n Santa Amalia Badajoz 06410",
    "addr:housenumber":"s / n",
    "addr:postcode":"06410",
    "addr:street":"Calle De Hernan Cortes",
    "iso:country":"ES",
    "sg:address":"Calle de Hernan Cortes, S/n",
    "sg:city":"Santa Amalia",
    "sg:orig_category":"Molduras, Junquillos, Listones Y Molduras Perforadas",
    "sg:phone":"+34 924 83 01 26",
    "sg:postcode":"06410",
    "sg:province":"Badajoz",
    "wof:name":"Rebollo Nieto Eusebio",
    "wof:placetype":"venue"
},
  "geometry": {"coordinates":[-6.008769989,39.0099105835],"type":"Point"}
}