{
  "type": "Feature",
  "properties": {
    "addr:full":"Calle de Mendez Nu\u00d1ez, 106 Santa Cruz De Tenerife Santa Cruz De Tenerife 38001",
    "addr:housenumber":"106",
    "addr:postcode":"38001",
    "addr:street":"Calle De Mendez Nun\u0303Ez",
    "iso:country":"ES",
    "sg:address":"Calle de Mendez Nu\u00d1ez, 106",
    "sg:city":"Santa Cruz De Tenerife",
    "sg:orig_category":"Agentes Generales De Seguros",
    "sg:phone":"+34 922 24 74 11",
    "sg:postcode":"38001",
    "sg:province":"Santa Cruz De Tenerife",
    "wof:name":"Pino Yanes Domingo Del",
    "wof:placetype":"venue"
},
  "geometry": {"coordinates":[-16.2499504089,28.4745521545],"type":"Point"}
}