{
  "type": "Feature",
  "properties": {
    "addr:full":"Avda Principe De Asturias, 5 Gijon Asturias 33212",
    "addr:housenumber":"5",
    "addr:postcode":"33212",
    "addr:street":"Avda Principe De Asturias",
    "iso:country":"ES",
    "sg:address":"Avda Principe De Asturias, 5",
    "sg:city":"Gijon",
    "sg:orig_category":"Electricidad: Equipos Industriales, Componentes (fabricaci\u00d3n)",
    "sg:phone":"+34 985 32 48 31",
    "sg:postcode":"33212",
    "sg:province":"Asturias",
    "wof:name":"Alvarez Beltran S.a.",
    "wof:placetype":"venue"
},
  "geometry": {"coordinates":[-5.6843547821,43.5344161987],"type":"Point"}
}