{
  "type": "Feature",
  "properties": {
    "iso:country":"ES",
    "sg:address":"P. Escuela, S/n",
    "sg:city":"Aldehuela Boveda",
    "sg:orig_category":"Centros De Educaci\u00d3n Especial",
    "sg:phone":"+34 923 44 50 12",
    "sg:postcode":"37460",
    "sg:province":"Salamanca",
    "wof:name":"Colegio Publico De Aldehuela De La Boveda",
    "wof:placetype":"venue"
},
  "geometry": {"coordinates":[-6.1305918694,40.9009666443],"type":"Point"}
}