{
  "type": "Feature",
  "properties": {
    "iso:country":"ES",
    "sg:address":"Calle de Neveria, 1",
    "sg:city":"Samper Calanda",
    "sg:orig_category":"Caf\u00c9s, Bares, Cervecer\u00cdas",
    "sg:phone":"+34 978 82 24 38",
    "sg:postcode":"44520",
    "sg:province":"Teruel",
    "wof:name":"Anton Las Cuevas Lucia",
    "wof:placetype":"venue"
},
  "geometry": {"coordinates":[-0.3889021873,41.1890487671],"type":"Point"}
}