{
  "type": "Feature",
  "properties": {
    "addr:full":"Crta. Murcia, 11 Hellin Albacete 02400",
    "addr:housenumber":"11",
    "addr:postcode":"02400",
    "addr:street":"Murcia",
    "iso:country":"ES",
    "sg:address":"Crta. Murcia, 11",
    "sg:city":"Hellin",
    "sg:orig_category":"Textil",
    "sg:phone":"+34 967 54 32 04",
    "sg:postcode":"02400",
    "sg:province":"Albacete",
    "sg:website":"www.rodenasyrivera.com",
    "wof:name":"Rodenas Y Rivera S.a.",
    "wof:placetype":"venue"
},
  "geometry": {"coordinates":[-1.6883339882,38.5069198608],"type":"Point"}
}