{
  "type": "Feature",
  "properties": {
    "iso:country":"ES",
    "sg:address":"Carrer de Rec (del), 5",
    "sg:city":"Montbrio Del Camp",
    "sg:orig_category":"Reposter\u00cdas",
    "sg:phone":"+34 977 82 60 81",
    "sg:postcode":"43340",
    "sg:province":"Tarragona",
    "wof:name":"Llaveria Flaquers S.l.",
    "wof:placetype":"venue"
},
  "geometry": {"coordinates":[1.0024700165,41.1211509705],"type":"Point"}
}