{
  "type": "Feature",
  "properties": {
    "iso:country":"ES",
    "sg:address":"Calle de Comendador Rolls, 4",
    "sg:city":"Cabeza Buey",
    "sg:orig_category":"Molduras, Junquillos, Listones Y Molduras Perforadas",
    "sg:phone":"+34 924 60 01 65",
    "sg:postcode":"06600",
    "sg:province":"Badajoz",
    "wof:name":"Luque Mu\u00f1oz-torrero Manuel",
    "wof:placetype":"venue"
},
  "geometry": {"coordinates":[-5.2171545029,38.7221565247],"type":"Point"}
}