{
  "type": "Feature",
  "properties": {
    "iso:country":"ES",
    "sg:address":"Ctra. Avila-toledo, Km. 0140,2",
    "sg:city":"Cebolla",
    "sg:orig_category":"Distribuci\u00d3n De Petr\u00d3leo Y Derivados",
    "sg:phone":"+34 925 86 64 93",
    "sg:postcode":"45550",
    "sg:province":"Toledo",
    "wof:name":"Farruco S. A.",
    "wof:placetype":"venue"
},
  "geometry": {"coordinates":[-4.5676598549,39.9334411621],"type":"Point"}
}