{
  "type": "Feature",
  "properties": {
    "addr:full":"Calle de Mallorca, 13 Melilla Melilla 52006",
    "addr:housenumber":"13",
    "addr:postcode":"52006",
    "addr:street":"Calle De Mallorca",
    "iso:country":"ES",
    "sg:address":"Calle de Mallorca, 13",
    "sg:city":"Melilla",
    "sg:orig_category":"Material Y Suministros Para Fotocopiadoras, Reprograf\u00cda",
    "sg:phone":"+34 952 67 46 94",
    "sg:postcode":"52006",
    "sg:province":"Melilla",
    "wof:name":"Puerto Santa-cruz Francisco Manuel",
    "wof:placetype":"venue"
},
  "geometry": {"coordinates":[-2.9436209202,35.2760696411],"type":"Point"}
}