{
  "type": "Feature",
  "properties": {
    "iso:country":"ES",
    "sg:address":"Av. Petroleo, 28",
    "sg:city":"Leganes",
    "sg:orig_category":"Alquiler De Veh\u00cdculos: Turismos Y Utilitarios",
    "sg:phone":"+34 916 12 71 23",
    "sg:postcode":"28918",
    "sg:province":"Madrid",
    "sg:website":"www.cevesa.es",
    "wof:name":"Compa\u00f1ia Europea De Viajeros De Espa\u00f1a S.a.",
    "wof:placetype":"venue"
},
  "geometry": {"coordinates":[-3.8001880646,40.3518257141],"type":"Point"}
}