{
  "type": "Feature",
  "properties": {
    "addr:full":"Al. Riofrio, S/n Bejar Salamanca 37700",
    "addr:housenumber":"s / n",
    "addr:postcode":"37700",
    "iso:country":"ES",
    "sg:address":"Al. Riofrio, S/n",
    "sg:city":"Bejar",
    "sg:orig_category":"Cerrajer\u00cda, Ferrallista",
    "sg:phone":"+34 923 40 15 60",
    "sg:postcode":"37700",
    "sg:province":"Salamanca",
    "wof:name":"Construcciones Metalicas Sanse S.l.",
    "wof:placetype":"venue"
},
  "geometry": {"coordinates":[-5.7562589645,40.3868560791],"type":"Point"}
}