{
  "type": "Feature",
  "properties": {
    "iso:country":"ES",
    "sg:address":"Carrer de Manacor, 40",
    "sg:city":"Palma",
    "sg:orig_category":"Agentes, Concesionarios Y Sucursales De Camiones Y Veh\u00cdculos Industriales",
    "sg:phone":"+34 971 46 85 49",
    "sg:postcode":"07006",
    "sg:province":"Islas Baleares",
    "wof:name":"Lluperauto S.l.",
    "wof:placetype":"venue"
},
  "geometry": {"coordinates":[2.6630990505,39.5712585449],"type":"Point"}
}