{
  "type": "Feature",
  "properties": {
    "iso:country":"ES",
    "sg:address":"P. Andaluces, 7",
    "sg:city":"Cantillana",
    "sg:orig_category":"Supermercados Y Hipermercados",
    "sg:phone":"+34 955 73 18 39",
    "sg:postcode":"41320",
    "sg:province":"Sevilla",
    "wof:name":"Auto Servicio Hermanos Barrios S.cv.",
    "wof:placetype":"venue"
},
  "geometry": {"coordinates":[-5.8252353668,37.6123046875],"type":"Point"}
}