{
  "type": "Feature",
  "properties": {
    "addr:full":"C\u00d1ad Aguilera, S/n Santovenia Pisuerga Valladolid 47155",
    "addr:housenumber":"s",
    "addr:postcode":"47155",
    "addr:street":"/ N Santovenia",
    "iso:country":"ES",
    "sg:address":"C\u00d1ad Aguilera, S/n",
    "sg:city":"Santovenia Pisuerga",
    "sg:orig_category":"Reparaci\u00d3n Y Restauraci\u00d3n De Objetos Diversos",
    "sg:phone":"+34 983 40 05 36",
    "sg:postcode":"47155",
    "sg:province":"Valladolid",
    "wof:name":"Castro Cordova Alvaro De",
    "wof:placetype":"venue"
},
  "geometry": {"coordinates":[-4.6879892349,41.6882209778],"type":"Point"}
}