{
  "type": "Feature",
  "properties": {
    "iso:country":"ES",
    "sg:address":"Barra\u00f1a, 128",
    "sg:city":"Boiro",
    "sg:orig_category":"Molduras, Junquillos, Listones Y Molduras Perforadas",
    "sg:phone":"+34 981 84 57 04",
    "sg:postcode":"15930",
    "sg:province":"La Coru\u00f1a",
    "wof:name":"Miron Arca Maria Del Carmen",
    "wof:placetype":"venue"
},
  "geometry": {"coordinates":[-8.8815193176,42.64012146],"type":"Point"}
}