{
  "type": "Feature",
  "properties": {
    "addr:full":"Calle de Mayor, 7 Munera Albacete 02612",
    "addr:housenumber":"7",
    "addr:postcode":"02612",
    "addr:street":"Calle De Mayor",
    "iso:country":"ES",
    "sg:address":"Calle de Mayor, 7",
    "sg:city":"Munera",
    "sg:orig_category":"Cajas De Ahorro",
    "sg:phone":"+34 967 37 20 42",
    "sg:postcode":"02612",
    "sg:province":"Albacete",
    "sg:website":"www.ccm.es",
    "wof:name":"Caja De Ahorros De Castilla La Mancha",
    "wof:placetype":"venue"
},
  "geometry": {"coordinates":[-2.479418993,39.0404396057],"type":"Point"}
}