{
  "type": "Feature",
  "properties": {
    "addr:full":"Calle de San Isidro, 5 Sonseca Toledo 45100",
    "addr:housenumber":"5",
    "addr:postcode":"45100",
    "addr:street":"Calle De San Isidro",
    "iso:country":"ES",
    "sg:address":"Calle de San Isidro, 5",
    "sg:city":"Sonseca",
    "sg:orig_category":"Fabricaci\u00d3n De Su\u00c9ters Y Chalecos De Punto",
    "sg:phone":"+34 925 38 12 83",
    "sg:postcode":"45100",
    "sg:province":"Toledo",
    "wof:name":"Dober Comunidad De Bienes",
    "wof:placetype":"venue"
},
  "geometry": {"coordinates":[-3.9684259892,39.6757164001],"type":"Point"}
}