{
  "type": "Feature",
  "properties": {
    "iso:country":"ES",
    "sg:address":"Avda Barcelona, 3",
    "sg:city":"Malaga",
    "sg:orig_category":"Cristaler\u00cdas",
    "sg:phone":"+34 952 39 13 79",
    "sg:postcode":"29009",
    "sg:province":"M\u00e1laga",
    "wof:name":"Lara Ruiz Juan Manuel",
    "wof:placetype":"venue"
},
  "geometry": {"coordinates":[-4.4317107201,36.7216949463],"type":"Point"}
}