{
  "type": "Feature",
  "properties": {
    "iso:country":"ES",
    "sg:address":"Calle de Matilde Hernandez, 90",
    "sg:city":"Madrid",
    "sg:orig_category":"Molduras, Junquillos, Listones Y Molduras Perforadas",
    "sg:phone":"+34 914 61 68 11",
    "sg:postcode":"28025",
    "sg:province":"Madrid",
    "wof:name":"Diaz  Jose Julio",
    "wof:placetype":"venue"
},
  "geometry": {"coordinates":[-3.7372090816,40.3867950439],"type":"Point"}
}