{
  "type": "Feature",
  "properties": {
    "iso:country":"ES",
    "sg:address":"Luga Carretera De Granada, 10",
    "sg:city":"Guadix",
    "sg:orig_category":"Alimentaci\u00d3n General (al Por Menor)",
    "sg:phone":"+34 958 66 40 90",
    "sg:postcode":"18500",
    "sg:province":"Granada",
    "wof:name":"Supergran S.a.",
    "wof:placetype":"venue"
},
  "geometry": {"coordinates":[-3.1343688965,37.303894043],"type":"Point"}
}