{
  "type": "Feature",
  "properties": {
    "addr:full":"Pase General Davila, 97 Santander Cantabria 39006",
    "addr:housenumber":"97",
    "addr:postcode":"39006",
    "addr:street":"Davila",
    "iso:country":"ES",
    "sg:address":"Pase General Davila, 97",
    "sg:city":"Santander",
    "sg:orig_category":"Fabricaci\u00d3n De Ventanas",
    "sg:phone":"+34 942 23 00 10",
    "sg:postcode":"39006",
    "sg:province":"Cantabria",
    "wof:name":"Industrias Arnaiz San Emeterio S.l.",
    "wof:placetype":"venue"
},
  "geometry": {"coordinates":[-3.8189668655,43.4647293091],"type":"Point"}
}