{
  "type": "Feature",
  "properties": {
    "iso:country":"ES",
    "sg:address":"Calle de Fernando Fernandez Martinez, 6",
    "sg:city":"Cordoba",
    "sg:orig_category":"Granos Y Semillas (producci\u00d3n, Al Por Mayor)",
    "sg:phone":"+34 957 25 63 56",
    "sg:postcode":"14007",
    "sg:province":"C\u00f3rdoba",
    "wof:name":"Lara Moreno Rafael",
    "wof:placetype":"venue"
},
  "geometry": {"coordinates":[-4.7618908882,37.8903541565],"type":"Point"}
}