{
  "type": "Feature",
  "properties": {
    "addr:full":"Calle de Doctor Sanchis Banus, 29 Madrid Madrid 28026",
    "addr:housenumber":"29",
    "addr:postcode":"madrid;28026",
    "addr:street":"Calle De Doctor Sanchis Banus",
    "iso:country":"ES",
    "sg:address":"Calle de Doctor Sanchis Banus, 29",
    "sg:city":"Madrid",
    "sg:orig_category":"Audiovisuales (producci\u00d3n, Edici\u00d3n, Realizaci\u00d3n)",
    "sg:phone":"+34 915 60 30 82",
    "sg:postcode":"28026",
    "sg:province":"Madrid",
    "wof:name":"Producciones Casablanca, S.l.",
    "wof:placetype":"venue"
},
  "geometry": {"coordinates":[-3.7094199657,40.387676239],"type":"Point"}
}