{
  "type": "Feature",
  "properties": {
    "addr:full":"Carrer de Alcolea, 110 Barcelona Barcelona 08014",
    "addr:housenumber":"110",
    "addr:postcode":"08014",
    "addr:street":"Carrer De Alcolea",
    "iso:country":"ES",
    "sg:address":"Carrer de Alcolea, 110",
    "sg:city":"Barcelona",
    "sg:orig_category":"Arreglo, Reparaci\u00d3n, Piezas Sueltas De Televisi\u00d3n, V\u00cddeo, Hi",
    "sg:phone":"+34 933 39 65 27",
    "sg:postcode":"08014",
    "sg:province":"Barcelona",
    "wof:name":"Muhammad  Sharif",
    "wof:placetype":"venue"
},
  "geometry": {"coordinates":[2.1350269318,41.3801651001],"type":"Point"}
}