{
  "type": "Feature",
  "properties": {
    "addr:full":"Calle de Manchester, 4 Madrid Madrid 28022",
    "addr:housenumber":"4",
    "addr:postcode":"28022",
    "addr:street":"Calle De Manchester",
    "iso:country":"ES",
    "sg:address":"Calle de Manchester, 4",
    "sg:city":"Madrid",
    "sg:orig_category":"Cajas De Ahorro",
    "sg:phone":"+34 913 13 58 40",
    "sg:postcode":"28022",
    "sg:province":"Madrid",
    "sg:website":"www.cajasegovia.es",
    "wof:name":"Caja De Ahorros Y Monte De Piedad De Segovia",
    "wof:placetype":"venue"
},
  "geometry": {"coordinates":[-3.6061370373,40.4292602539],"type":"Point"}
}