{
  "type": "Feature",
  "properties": {
    "iso:country":"ES",
    "sg:address":"Calle de Somosierra, 15",
    "sg:city":"Logro\u00f1o",
    "sg:orig_category":"Estancos",
    "sg:phone":"+34 941 24 03 83",
    "sg:postcode":"26002",
    "sg:province":"La Rioja",
    "wof:name":"Vallejo Ulecia Maria De Los Angeles",
    "wof:placetype":"venue"
},
  "geometry": {"coordinates":[-2.4478418827,42.459815979],"type":"Point"}
}