{
  "type": "Feature",
  "properties": {
    "addr:full":"I. Oleo, 11 Santander Cantabria 39011",
    "addr:housenumber":"11",
    "addr:postcode":"39011",
    "addr:street":"I. Oleo",
    "iso:country":"ES",
    "sg:address":"I. Oleo, 11",
    "sg:city":"Santander",
    "sg:orig_category":"Chapister\u00cda",
    "sg:phone":"+34 942 32 30 29",
    "sg:postcode":"39011",
    "sg:province":"Cantabria",
    "wof:name":"Somoza Vega Victor",
    "wof:placetype":"venue"
},
  "geometry": {"coordinates":[-3.8483219147,43.4389686584],"type":"Point"}
}