{
  "type": "Feature",
  "properties": {
    "addr:full":"Calle de Maestra Angeles Azpiazu, 5 Fuengirola M\u00e1laga 29640",
    "addr:housenumber":"5",
    "addr:postcode":"29640",
    "addr:street":"Calle De Maestra Angeles Azpiazu;Ma\u0301Laga",
    "iso:country":"ES",
    "sg:address":"Calle de Maestra Angeles Azpiazu, 5",
    "sg:city":"Fuengirola",
    "sg:orig_category":"Peluquer\u00cdas, Peluquer\u00cda Mixta",
    "sg:phone":"+34 952 47 26 41",
    "sg:postcode":"29640",
    "sg:province":"M\u00e1laga",
    "wof:name":"Greaves  Anita",
    "wof:placetype":"venue"
},
  "geometry": {"coordinates":[-4.622387886,36.5450019836],"type":"Point"}
}