{
  "type": "Feature",
  "properties": {
    "addr:full":"Calle de Nuria, 9 Madrid Madrid 28034",
    "addr:housenumber":"9",
    "addr:postcode":"madrid;28034",
    "addr:street":"Calle De Nuria",
    "iso:country":"ES",
    "sg:address":"Calle de Nuria, 9",
    "sg:city":"Madrid",
    "sg:orig_category":"Agricultores, Agricultores",
    "sg:phone":"+34 917 34 85 22",
    "sg:postcode":"28034",
    "sg:province":"Madrid",
    "wof:name":"Cinegetica Iberica S.l.",
    "wof:placetype":"venue"
},
  "geometry": {"coordinates":[-3.7037351131,40.4911231995],"type":"Point"}
}