{
  "type": "Feature",
  "properties": {
    "iso:country":"ES",
    "sg:address":"Calle de Piedras (las), 7",
    "sg:city":"Grazalema",
    "sg:orig_category":"Aguas (distribuci\u00d3n, Servicios)",
    "sg:phone":"+34 956 13 20 74",
    "sg:postcode":"11610",
    "sg:province":"C\u00e1diz",
    "wof:name":"Aguas Sierra De Cadiz S.a.",
    "wof:placetype":"venue"
},
  "geometry": {"coordinates":[-5.3667254448,36.7582244873],"type":"Point"}
}