{
  "type": "Feature",
  "properties": {
    "addr:full":"Calle de Clavel, 11 Andorra Teruel 44500",
    "addr:housenumber":"11",
    "addr:postcode":"44500",
    "addr:street":"Calle De Clavel",
    "iso:country":"ES",
    "sg:address":"Calle de Clavel, 11",
    "sg:city":"Andorra",
    "sg:orig_category":"Institutos De Belleza",
    "sg:phone":"+34 978 84 41 39",
    "sg:postcode":"44500",
    "sg:province":"Teruel",
    "wof:name":"Rosales Blasco Maria Jose",
    "wof:placetype":"venue"
},
  "geometry": {"coordinates":[-0.4487676024,40.978427887],"type":"Point"}
}