{
  "type": "Feature",
  "properties": {
    "iso:country":"ES",
    "sg:address":"Carrer de Concepcion Arenal, 94",
    "sg:city":"Barcelona",
    "sg:orig_category":"Prot\u00c9sicos Dentales",
    "sg:phone":"+34 933 52 31 68",
    "sg:postcode":"08027",
    "sg:province":"Barcelona",
    "wof:name":"Relao Serrano Pedro Luis",
    "wof:placetype":"venue"
},
  "geometry": {"coordinates":[2.184235096,41.4237632751],"type":"Point"}
}