{
  "type": "Feature",
  "properties": {
    "addr:full":"Avda Puerto (del), 1 Cadiz C\u00e1diz 11006",
    "addr:housenumber":"1",
    "addr:postcode":"11006",
    "addr:street":"Avda Puerto Del",
    "iso:country":"ES",
    "sg:address":"Avda Puerto (del), 1",
    "sg:city":"Cadiz",
    "sg:orig_category":"Edici\u00d3n De Diarios, Revistas, Boletines",
    "sg:phone":"+34 956 29 24 58",
    "sg:postcode":"11006",
    "sg:province":"C\u00e1diz",
    "wof:name":"Publicaciones Del Sur S.a.",
    "wof:placetype":"venue"
},
  "geometry": {"coordinates":[-6.2924180031,36.5345916748],"type":"Point"}
}