{
  "type": "Feature",
  "properties": {
    "iso:country":"ES",
    "sg:address":"Avda General Aviles, 15",
    "sg:city":"Valencia",
    "sg:orig_category":"Mec\u00c1nico Del Autom\u00d3vil",
    "sg:phone":"+34 963 49 71 48",
    "sg:postcode":"46015",
    "sg:province":"Valencia",
    "wof:name":"Automocio Aviles,s.l.",
    "wof:placetype":"venue"
},
  "geometry": {"coordinates":[-0.3923150897,39.4873352051],"type":"Point"}
}