{
  "type": "Feature",
  "properties": {
    "iso:country":"ES",
    "sg:address":"Avda Hermanos Maristas, 24",
    "sg:city":"Mimetiz",
    "sg:orig_category":"Aguas (distribuci\u00d3n, Servicios)",
    "sg:phone":"+34 946 39 01 32",
    "sg:postcode":"48860",
    "sg:province":"Vizcaya",
    "wof:name":"Auxiliar Tecnica Del Agua S.l.",
    "wof:placetype":"venue"
},
  "geometry": {"coordinates":[-3.1307470798,43.2134437561],"type":"Point"}
}