{
  "type": "Feature",
  "properties": {
    "iso:country":"ES",
    "sg:address":"Carrer de Sant Salvador, 72",
    "sg:city":"Caldes Montbui",
    "sg:orig_category":"Perfumer\u00cda Y Cosm\u00c9tica (fabricaci\u00d3n, Al Por Mayor)",
    "sg:phone":"+34 938 65 36 54",
    "sg:postcode":"08140",
    "sg:province":"Barcelona",
    "wof:name":"Budi Tusell Jose Maria",
    "wof:placetype":"venue"
},
  "geometry": {"coordinates":[2.166093111,41.6335754395],"type":"Point"}
}