{
  "type": "Feature",
  "properties": {
    "addr:full":"Carr Botines, 38 Palafrugell Girona 17200",
    "addr:housenumber":"38",
    "addr:postcode":"17200",
    "addr:street":"Carr Botines",
    "iso:country":"ES",
    "sg:address":"Carr Botines, 38",
    "sg:city":"Palafrugell",
    "sg:orig_category":"Electrodom\u00c9sticos (al Por Menor)",
    "sg:phone":"+34 972 61 20 60",
    "sg:postcode":"17200",
    "sg:province":"Girona",
    "sg:website":"www.olives-buixo.com",
    "wof:name":"Olives & Buixo S.l.",
    "wof:placetype":"venue"
},
  "geometry": {"coordinates":[3.1653439999,41.9157104492],"type":"Point"}
}