{
  "type": "Feature",
  "properties": {
    "iso:country":"ES",
    "sg:address":"Plaz Concordia (de La), 2",
    "sg:city":"Alcobendas",
    "sg:orig_category":"Asesor\u00cda Sobre Comunicaci\u00d3n De Empresas",
    "sg:phone":"+34 916 63 91 85",
    "sg:postcode":"28100",
    "sg:province":"Madrid",
    "wof:name":"Sec Economistas Consultores S.l.",
    "wof:placetype":"venue"
},
  "geometry": {"coordinates":[-3.6401491165,40.5451850891],"type":"Point"}
}