{
  "type": "Feature",
  "properties": {
    "addr:full":"Pg Maritim, 40 Malgrat Mar Barcelona 08380",
    "addr:housenumber":"40",
    "addr:postcode":"08380",
    "addr:street":"Pg Maritim",
    "iso:country":"ES",
    "sg:address":"Pg Maritim, 40",
    "sg:city":"Malgrat Mar",
    "sg:orig_category":"Tatuajes",
    "sg:phone":"+34 937 65 36 70",
    "sg:postcode":"08380",
    "sg:province":"Barcelona",
    "wof:name":"Dawson  Marie",
    "wof:placetype":"venue"
},
  "geometry": {"coordinates":[2.733383894,41.6385192871],"type":"Point"}
}