{
  "type": "Feature",
  "properties": {
    "addr:full":"Calle de Colon, 2 Caceres C\u00e1ceres 10004",
    "addr:housenumber":"2",
    "addr:postcode":"10004",
    "addr:street":"Calle De Colon;Ca\u0301Ceres",
    "iso:country":"ES",
    "sg:address":"Calle de Colon, 2",
    "sg:city":"Caceres",
    "sg:orig_category":"Alimentaci\u00d3n General (al Por Menor)",
    "sg:phone":"+34 927 22 62 47",
    "sg:postcode":"10004",
    "sg:province":"C\u00e1ceres",
    "wof:name":"Izquierdo Diaz Cristeta",
    "wof:placetype":"venue"
},
  "geometry": {"coordinates":[-6.3729906082,39.4706573486],"type":"Point"}
}