{
  "type": "Feature",
  "properties": {
    "addr:full":"Calle de Trujillo, 4 Hellin Albacete 02400",
    "addr:housenumber":"4",
    "addr:postcode":"02400",
    "addr:street":"Calle De Trujillo",
    "iso:country":"ES",
    "sg:address":"Calle de Trujillo, 4",
    "sg:city":"Hellin",
    "sg:orig_category":"Muebles Y Accesorios Para Cocinas Y Cuartos De Ba\u00d1o (al Por Menor)",
    "sg:phone":"+34 967 30 42 96",
    "sg:postcode":"02400",
    "sg:province":"Albacete",
    "wof:name":"J.v. Joval Sociedad Limitada",
    "wof:placetype":"venue"
},
  "geometry": {"coordinates":[-1.7003610134,38.5183448792],"type":"Point"}
}