{
  "type": "Feature",
  "properties": {
    "addr:full":"Calle de Sandalo, 5 Madrid Madrid 28042",
    "addr:housenumber":"5",
    "addr:postcode":"28042",
    "addr:street":"Calle De Sandalo",
    "iso:country":"ES",
    "sg:address":"Calle de Sandalo, 5",
    "sg:city":"Madrid",
    "sg:orig_category":"M\u00c9dicos: Otorrinolaringolog\u00cda",
    "sg:phone":"+34 917 41 10 21",
    "sg:postcode":"28042",
    "sg:province":"Madrid",
    "wof:name":"Soto Rivera Arturo",
    "wof:placetype":"venue"
},
  "geometry": {"coordinates":[-3.6158869267,40.4525032043],"type":"Point"}
}