{
  "type": "Feature",
  "properties": {
    "addr:full":"Carrer de Xifre, 66 Barcelona Barcelona 08026",
    "addr:housenumber":"66",
    "addr:postcode":"08026",
    "addr:street":"Carrer De Xifre",
    "iso:country":"ES",
    "sg:address":"Carrer de Xifre, 66",
    "sg:city":"Barcelona",
    "sg:orig_category":"Agencias Y Agentes Comerciales, Representantes",
    "sg:phone":"+34 933 47 93 14",
    "sg:postcode":"08026",
    "sg:province":"Barcelona",
    "wof:name":"Lahoz Lahoz Macario",
    "wof:placetype":"venue"
},
  "geometry": {"coordinates":[2.1819179058,41.4103012085],"type":"Point"}
}