{
  "type": "Feature",
  "properties": {
    "iso:country":"ES",
    "sg:address":"Calle de Amezketa De Los, 18",
    "sg:city":"Donostia-san Sebastian",
    "sg:orig_category":"Instalaci\u00d3n, Mantenimiento De Porteros Electr\u00d3nicos Y Controles De Acceso",
    "sg:phone":"+34 943 46 24 04",
    "sg:postcode":"20010",
    "sg:province":"Guip\u00f9zcoa",
    "wof:name":"Epelde Goldarecena Pedro Maria",
    "wof:placetype":"venue"
},
  "geometry": {"coordinates":[-1.9818671942,43.303565979],"type":"Point"}
}