{
  "type": "Feature",
  "properties": {
    "addr:full":"Calle de Navarra, 2 Pinto Madrid 28320",
    "addr:housenumber":"2",
    "addr:postcode":"28320",
    "addr:street":"Calle De Navarra;Pinto",
    "iso:country":"ES",
    "sg:address":"Calle de Navarra, 2",
    "sg:city":"Pinto",
    "sg:orig_category":"Cajas De Ahorro",
    "sg:phone":"+34 916 91 07 84",
    "sg:postcode":"28320",
    "sg:province":"Madrid",
    "wof:name":"Caixa D'estalvis I Pensions De Barcelona",
    "wof:placetype":"venue"
},
  "geometry": {"coordinates":[-3.6975591183,40.2491722107],"type":"Point"}
}