{
  "type": "Feature",
  "properties": {
    "addr:full":"Calle de San Francisco De Borja, 2 Valencia Valencia 46007",
    "addr:housenumber":"2",
    "addr:postcode":"46007",
    "addr:street":"Calle De San Francisco De Borja",
    "iso:country":"ES",
    "sg:address":"Calle de San Francisco De Borja, 2",
    "sg:city":"Valencia",
    "sg:orig_category":"Promotores Constructores",
    "sg:phone":"+34 963 84 04 07",
    "sg:postcode":"46007",
    "sg:province":"Valencia",
    "wof:name":"Edificios Y Construcciones De Valencia S.a.",
    "wof:placetype":"venue"
},
  "geometry": {"coordinates":[-0.3838230073,39.4659805298],"type":"Point"}
}