{
  "type": "Feature",
  "properties": {
    "iso:country":"ES",
    "sg:address":"M. Montija, S/n",
    "sg:city":"Villalonquejar",
    "sg:orig_category":"Empresas De Carpinter\u00cda De Madera",
    "sg:phone":"+34 947 29 82 46",
    "sg:postcode":"09001",
    "sg:province":"Burgos",
    "wof:name":"Garcia Tejedor Miguel Angel",
    "wof:placetype":"venue"
},
  "geometry": {"coordinates":[-3.7355909348,42.375667572],"type":"Point"}
}