{
  "type": "Feature",
  "properties": {
    "iso:country":"ES",
    "sg:address":"Ctra Palafrugell, 5",
    "sg:city":"Torroella Montgri",
    "sg:orig_category":"Afilado",
    "sg:phone":"+34 972 76 00 13",
    "sg:postcode":"17257",
    "sg:province":"Girona",
    "wof:name":"Afilados Ampurda S.l.",
    "wof:placetype":"venue"
},
  "geometry": {"coordinates":[3.1272518635,42.0376167297],"type":"Point"}
}