{
  "type": "Feature",
  "properties": {
    "iso:country":"ES",
    "sg:address":"Calle de Virgen Del Socorro, 58",
    "sg:city":"Alacant",
    "sg:orig_category":"Centros Empresariales",
    "sg:phone":"+34 965 15 03 00",
    "sg:postcode":"03002",
    "sg:province":"Alicante",
    "wof:name":"Federacion De Empresarios Del Metal De La Provincia De Alicante",
    "wof:placetype":"venue"
},
  "geometry": {"coordinates":[-0.4823389947,38.3463592529],"type":"Point"}
}