{
  "type": "Feature",
  "properties": {
    "iso:country":"ES",
    "sg:address":"Via Centro Comercial Costasol, 40",
    "sg:city":"Paraiso-barronal",
    "sg:orig_category":"Mec\u00c1nico Del Autom\u00d3vil",
    "sg:phone":"+34 952 88 84 34",
    "sg:postcode":"29680",
    "sg:province":"M\u00e1laga",
    "wof:name":"Moreno Garcia Maria",
    "wof:placetype":"venue"
},
  "geometry": {"coordinates":[-5.1452140808,36.4275817871],"type":"Point"}
}