{
  "type": "Feature",
  "properties": {
    "iso:country":"ES",
    "sg:address":"Mayor, 19",
    "sg:city":"Estella",
    "sg:orig_category":"Ropa De Hogar (al Por Menor)",
    "sg:phone":"+34 948 55 42 08",
    "sg:postcode":"31200",
    "sg:province":"Navarra",
    "wof:name":"Ugarte Zu\u00f1iga Francisco Javier",
    "wof:placetype":"venue"
},
  "geometry": {"coordinates":[-2.0323960781,42.6718177795],"type":"Point"}
}