{
  "type": "Feature",
  "properties": {
    "addr:full":"Calle de Breton De Los Herreros, 43 Madrid Madrid 28003",
    "addr:housenumber":"43",
    "addr:postcode":"madrid;28003",
    "addr:street":"Calle De Breton De Los Herreros",
    "iso:country":"ES",
    "sg:address":"Calle de Breton De Los Herreros, 43",
    "sg:city":"Madrid",
    "sg:orig_category":"Financiaci\u00d3n Y Cr\u00c9ditos",
    "sg:phone":"+34 913 95 24 81",
    "sg:postcode":"28003",
    "sg:province":"Madrid",
    "wof:name":"Gimenez Silva Eduardo",
    "wof:placetype":"venue"
},
  "geometry": {"coordinates":[-3.6965725422,40.439491272],"type":"Point"}
}