{
  "type": "Feature",
  "properties": {
    "iso:country":"ES",
    "sg:address":"Calle de Vicente Aleixandre, S/n",
    "sg:city":"Alhaurin Torre",
    "sg:orig_category":"Arquitectos",
    "sg:phone":"+34 952 41 19 99",
    "sg:postcode":"29130",
    "sg:province":"M\u00e1laga",
    "wof:name":"Hernandez White Pedro",
    "wof:placetype":"venue"
},
  "geometry": {"coordinates":[-4.5623788834,36.6624679565],"type":"Point"}
}