{
  "type": "Feature",
  "properties": {
    "iso:country":"ES",
    "sg:address":"Burundabide, 3",
    "sg:city":"Etxarri-aranatz",
    "sg:orig_category":"Farmacias",
    "sg:phone":"+34 948 46 20 09",
    "sg:postcode":"31820",
    "sg:province":"Navarra",
    "wof:name":"Bacaicoa Ormazabal Virginia",
    "wof:placetype":"venue"
},
  "geometry": {"coordinates":[-2.0664820671,42.9047698975],"type":"Point"}
}