{
  "type": "Feature",
  "properties": {
    "iso:country":"ES",
    "sg:address":"Rua Horreo (do), 23",
    "sg:city":"Santiago De Compostela",
    "sg:orig_category":"Ense\u00d1anza: Idiomas",
    "sg:phone":"+34 981 56 16 39",
    "sg:postcode":"15702",
    "sg:province":"La Coru\u00f1a",
    "wof:name":"Alianza Francesa De Espa\u00f1a",
    "wof:placetype":"venue"
},
  "geometry": {"coordinates":[-8.5440292358,42.8756256104],"type":"Point"}
}