{
  "type": "Feature",
  "properties": {
    "addr:full":"Calle de Diecinueve De Octubre, 39 San Pedro Alcantara M\u00e1laga 29670",
    "addr:housenumber":"39",
    "addr:postcode":"29670",
    "addr:street":"Calle De Diecinueve De Octubre",
    "iso:country":"ES",
    "sg:address":"Calle de Diecinueve De Octubre, 39",
    "sg:city":"San Pedro Alcantara",
    "sg:orig_category":"Alimentaci\u00d3n General (al Por Menor)",
    "sg:phone":"+34 952 78 83 52",
    "sg:postcode":"29670",
    "sg:province":"M\u00e1laga",
    "wof:name":"Palomo Gallego Maria Dolores",
    "wof:placetype":"venue"
},
  "geometry": {"coordinates":[-4.9887065887,36.4852256775],"type":"Point"}
}