{
  "type": "Feature",
  "properties": {
    "addr:full":"Fdo. Dguez. Garcia, S/n Sacedon Guadalajara 19120",
    "addr:postcode":"19120",
    "addr:street":"S / N Sacedon",
    "iso:country":"ES",
    "sg:address":"Fdo. Dguez. Garcia, S/n",
    "sg:city":"Sacedon",
    "sg:orig_category":"Empresas De Carpinter\u00cda Met\u00c1lica",
    "sg:phone":"+34 949 35 11 52",
    "sg:postcode":"19120",
    "sg:province":"Guadalajara",
    "wof:name":"Alucrisma De Sacedon S.l",
    "wof:placetype":"venue"
},
  "geometry": {"coordinates":[-2.718272686,40.4605102539],"type":"Point"}
}