{
  "type": "Feature",
  "properties": {
    "addr:full":"Calle de Periodista Jose M. Gomez, 7 Dos Hermanas Sevilla 41700",
    "addr:housenumber":"7",
    "addr:postcode":"41700",
    "addr:street":"Calle De Periodista Jose M. Gomez;Sevilla",
    "iso:country":"ES",
    "sg:address":"Calle de Periodista Jose M. Gomez, 7",
    "sg:city":"Dos Hermanas",
    "sg:orig_category":"Empresas De Carpinter\u00cda Met\u00c1lica",
    "sg:phone":"+34 955 67 70 34",
    "sg:postcode":"41700",
    "sg:province":"Sevilla",
    "wof:name":"David Caro S.l.u",
    "wof:placetype":"venue"
},
  "geometry": {"coordinates":[-5.928314209,37.2895393372],"type":"Point"}
}