{
  "type": "Feature",
  "properties": {
    "addr:full":"Crta Nal. 430, Km. 0246,6 Puebla D. Rodrigo Ciudad Real 13109",
    "addr:postcode":"13109",
    "addr:street":"Crta Nal. 430 Km. 0246,6 Puebla D. Rodrigo",
    "iso:country":"ES",
    "sg:address":"Crta Nal. 430, Km. 0246,6",
    "sg:city":"Puebla D. Rodrigo",
    "sg:orig_category":"Producci\u00d3n, Venta De Productos De Agricultura Biol\u00d3gica",
    "sg:phone":"+34 926 69 70 01",
    "sg:postcode":"13109",
    "sg:province":"Ciudad Real",
    "wof:name":"Bafimar S.a.",
    "wof:placetype":"venue"
},
  "geometry": {"coordinates":[-4.6181058884,39.0831871033],"type":"Point"}
}