{
  "type": "Feature",
  "properties": {
    "addr:full":"Calle de Cercas Bajas, 5 Vitoria-gasteiz \u00c1lava 01001",
    "addr:housenumber":"5",
    "addr:postcode":"01001",
    "addr:street":"Calle De Cercas Bajas",
    "iso:country":"ES",
    "sg:address":"Calle de Cercas Bajas, 5",
    "sg:city":"Vitoria-gasteiz",
    "sg:orig_category":"Deportes Diversos",
    "sg:phone":"+34 945 13 37 68",
    "sg:postcode":"01001",
    "sg:province":"\u00c1lava",
    "wof:name":"Federacion Alavesa De Ciclismo",
    "wof:placetype":"venue"
},
  "geometry": {"coordinates":[-2.6760458946,42.8482818604],"type":"Point"}
}