{
  "type": "Feature",
  "properties": {
    "iso:country":"ES",
    "sg:address":"Rosello (pol Ind Les Salines), 11",
    "sg:city":"Cubelles",
    "sg:orig_category":"Pintura Y Barniz (al Por Menor)",
    "sg:phone":"+34 938 95 23 07",
    "sg:postcode":"08880",
    "sg:province":"Barcelona",
    "wof:name":"Cubellas Color S.l:",
    "wof:placetype":"venue"
},
  "geometry": {"coordinates":[1.6501450539,41.2009239197],"type":"Point"}
}