{
  "type": "Feature",
  "properties": {
    "iso:country":"ES",
    "sg:address":"Rbla Just Oliveras, 27",
    "sg:city":"Hospitalet Llobregat",
    "sg:orig_category":"Caf\u00c9s, Bares, Cervecer\u00cdas",
    "sg:phone":"+34 932 61 00 69",
    "sg:postcode":"08901",
    "sg:province":"Barcelona",
    "wof:name":"Gil Cester Jose Antonio",
    "wof:placetype":"venue"
},
  "geometry": {"coordinates":[2.1009709835,41.3613929749],"type":"Point"}
}