{
  "type": "Feature",
  "properties": {
    "iso:country":"ES",
    "sg:address":"Calle de Heliodoro Fernandez, 25",
    "sg:city":"Colindres",
    "sg:orig_category":"Molduras, Junquillos, Listones Y Molduras Perforadas",
    "sg:phone":"+34 942 65 15 04",
    "sg:postcode":"39750",
    "sg:province":"Cantabria",
    "wof:name":"Redondo Diez Pablo",
    "wof:placetype":"venue"
},
  "geometry": {"coordinates":[-3.4525239468,43.3955841064],"type":"Point"}
}