{
  "type": "Feature",
  "properties": {
    "addr:full":"Avda Cantue\u00d1a (de La), 1 Fuenlabrada Madrid 28947",
    "addr:housenumber":"1",
    "addr:postcode":"28947",
    "addr:street":"Avda Cantuen\u0303A De La",
    "iso:country":"ES",
    "sg:address":"Avda Cantue\u00d1a (de La), 1",
    "sg:city":"Fuenlabrada",
    "sg:orig_category":"Agentes, Concesionarios Y Sucursales De Veh\u00cdculos",
    "sg:phone":"+34 916 42 20 55",
    "sg:postcode":"28947",
    "sg:province":"Madrid",
    "wof:name":"Julian Gomez Rodriguez S.a.",
    "wof:placetype":"venue"
},
  "geometry": {"coordinates":[-3.7612490654,40.2746543884],"type":"Point"}
}