{
  "type": "Feature",
  "properties": {
    "iso:country":"ES",
    "sg:address":"Cmno Castralvo, 5",
    "sg:city":"Teruel",
    "sg:orig_category":"Escayola Y Productos De Escayola (fabricaci\u00d3n, Al Por Mayor)",
    "sg:phone":"+34 978 60 03 73",
    "sg:postcode":"44002",
    "sg:province":"Teruel",
    "wof:name":"Mesado Martin Jose",
    "wof:placetype":"venue"
},
  "geometry": {"coordinates":[-1.1008620262,40.3326225281],"type":"Point"}
}