{
  "type": "Feature",
  "properties": {
    "addr:full":"Calle de Juan De Oca\u00d1a, 11 Mostoles Madrid 28931",
    "addr:housenumber":"11",
    "addr:postcode":"28931",
    "addr:street":"Calle De Juan De Ocan\u0303A",
    "iso:country":"ES",
    "sg:address":"Calle de Juan De Oca\u00d1a, 11",
    "sg:city":"Mostoles",
    "sg:orig_category":"M\u00c9dicos: Geriatr\u00cda, Gerontolog\u00cda (enfermedades De La Tercera Edad)",
    "sg:phone":"+34 916 14 65 17",
    "sg:postcode":"28931",
    "sg:province":"Madrid",
    "wof:name":"Centro De Dia De Mayores S.l.",
    "wof:placetype":"venue"
},
  "geometry": {"coordinates":[-3.8676650524,40.3233299255],"type":"Point"}
}