{
  "type": "Feature",
  "properties": {
    "addr:full":"Avda Lugo, 47 Friol Lugo 27220",
    "addr:housenumber":"47",
    "addr:postcode":"27220",
    "addr:street":"Avda Lugo",
    "iso:country":"ES",
    "sg:address":"Avda Lugo, 47",
    "sg:city":"Friol",
    "sg:orig_category":"Farmacias",
    "sg:phone":"+34 982 37 50 10",
    "sg:postcode":"27220",
    "sg:province":"Lugo",
    "wof:name":"Sagarra Prado Maria Dolores",
    "wof:placetype":"venue"
},
  "geometry": {"coordinates":[-7.7915530205,43.0297889709],"type":"Point"}
}