{
  "type": "Feature",
  "properties": {
    "iso:country":"ES",
    "sg:address":"Carrer de Mossen Jacint Verdaguer, 13",
    "sg:city":"Santa Coloma De Gramenet",
    "sg:orig_category":"Molduras, Junquillos, Listones Y Molduras Perforadas",
    "sg:phone":"+34 933 86 40 32",
    "sg:postcode":"08922",
    "sg:province":"Barcelona",
    "wof:name":"Alonso Alonso Jose Antonio",
    "wof:placetype":"venue"
},
  "geometry": {"coordinates":[2.2087664604,41.4452896118],"type":"Point"}
}