{
  "type": "Feature",
  "properties": {
    "iso:country":"ES",
    "sg:address":"Ctra Aguilas (de), S/n",
    "sg:city":"Casa De Las Monjas",
    "sg:orig_category":"Mec\u00c1nico Del Autom\u00d3vil",
    "sg:phone":"+34 968 48 23 29",
    "sg:postcode":"30813",
    "sg:province":"Murcia",
    "wof:name":"Auto-puria S.l.",
    "wof:placetype":"venue"
},
  "geometry": {"coordinates":[-1.1298867464,37.9834747314],"type":"Point"}
}