{
  "type": "Feature",
  "properties": {
    "iso:country":"ES",
    "sg:address":"Ctra Haro, 8",
    "sg:city":"Belorado",
    "sg:orig_category":"Electricidad Veh\u00cdculo",
    "sg:phone":"+34 947 58 06 49",
    "sg:postcode":"09250",
    "sg:province":"Burgos",
    "wof:name":"Silla Martinez Jose Miguel",
    "wof:placetype":"venue"
},
  "geometry": {"coordinates":[-3.1921889782,42.4212265015],"type":"Point"}
}