{
  "type": "Feature",
  "properties": {
    "iso:country":"ES",
    "sg:address":"Era, S/n",
    "sg:city":"Mahide",
    "sg:orig_category":"Contenedores (mercanc\u00cdas)",
    "sg:phone":"+34 980 68 33 19",
    "sg:postcode":"49522",
    "sg:province":"Zamora",
    "wof:name":"Fernandez Miguel Jesus",
    "wof:placetype":"venue"
},
  "geometry": {"coordinates":[-6.3315138817,41.848651886],"type":"Point"}
}