{
  "type": "Feature",
  "properties": {
    "addr:full":"Calle de Linneo, 3 Madrid Madrid 28005",
    "addr:housenumber":"3",
    "addr:postcode":"28005",
    "addr:street":"Calle De Linneo",
    "iso:country":"ES",
    "sg:address":"Calle de Linneo, 3",
    "sg:city":"Madrid",
    "sg:orig_category":"Arquitectos",
    "sg:phone":"+34 913 64 54 46",
    "sg:postcode":"28005",
    "sg:province":"Madrid",
    "wof:name":"Luis Feduchi S.l.",
    "wof:placetype":"venue"
},
  "geometry": {"coordinates":[-3.7202959061,40.4134407043],"type":"Point"}
}