{
  "type": "Feature",
  "properties": {
    "addr:full":"Avda Terra Cha, S/n Castro Lugo 27260",
    "addr:housenumber":"s",
    "addr:postcode":"27260",
    "addr:street":"Avda Terra Cha;/ N",
    "iso:country":"ES",
    "sg:address":"Avda Terra Cha, S/n",
    "sg:city":"Castro",
    "sg:orig_category":"Centros De Educaci\u00d3n Especial",
    "sg:phone":"+34 982 31 01 09",
    "sg:postcode":"27260",
    "sg:province":"Lugo",
    "wof:name":"Colexio Publico De Educacion Xeral Basica",
    "wof:placetype":"venue"
},
  "geometry": {"coordinates":[-7.4924440384,43.1429367065],"type":"Point"}
}