{
  "type": "Feature",
  "properties": {
    "iso:country":"ES",
    "sg:address":"Calle de Pintor Adrian Aldecoa, 7",
    "sg:city":"Vitoria-gasteiz",
    "sg:orig_category":"Organismos De Reclutamiento",
    "sg:phone":"+34 945 13 68 93",
    "sg:postcode":"01008",
    "sg:province":"\u00c1lava",
    "wof:name":"Instituto Psicologico Y Grafologico Del Pais Vasco S.c.",
    "wof:placetype":"venue"
},
  "geometry": {"coordinates":[-2.6850728989,42.8438224792],"type":"Point"}
}