{
  "type": "Feature",
  "properties": {
    "addr:full":"Cordoba-tarragona, 4 Pedro Mu\u00f1oz Ciudad Real 13620",
    "addr:housenumber":"4",
    "addr:postcode":"13620",
    "addr:street":"Cordoba-Tarragona;Pedro Mun\u0303Oz",
    "iso:country":"ES",
    "sg:address":"Cordoba-tarragona, 4",
    "sg:city":"Pedro Mu\u00f1oz",
    "sg:orig_category":"Metalurgia",
    "sg:phone":"+34 926 58 64 28",
    "sg:postcode":"13620",
    "sg:province":"Ciudad Real",
    "wof:name":"Containers Cisternas La Mancha S. A.",
    "wof:placetype":"venue"
},
  "geometry": {"coordinates":[-2.9435579777,39.4077987671],"type":"Point"}
}