{
  "type": "Feature",
  "properties": {
    "iso:country":"ES",
    "sg:address":"Avda Fuerteventura, S/n",
    "sg:city":"Corralejo Playa",
    "sg:orig_category":"Inmobiliaria (agencias)",
    "sg:phone":"+34 928 53 60 02",
    "sg:postcode":"35660",
    "sg:province":"Las Palmas",
    "wof:name":"Hernandez Artiles Antonia",
    "wof:placetype":"venue"
},
  "geometry": {"coordinates":[-13.8704042435,28.729019165],"type":"Point"}
}