{
  "type": "Feature",
  "properties": {
    "addr:full":"Calle de Jose Antonio, 2 Pradoluengo Burgos 09260",
    "addr:housenumber":"2",
    "addr:postcode":"09260",
    "addr:street":"Calle De Jose Antonio",
    "iso:country":"ES",
    "sg:address":"Calle de Jose Antonio, 2",
    "sg:city":"Pradoluengo",
    "sg:orig_category":"Molduras, Junquillos, Listones Y Molduras Perforadas",
    "sg:phone":"+34 947 58 65 82",
    "sg:postcode":"09260",
    "sg:province":"Burgos",
    "wof:name":"Hermanos Bustamante S.c",
    "wof:placetype":"venue"
},
  "geometry": {"coordinates":[-3.2022900581,42.3243026733],"type":"Point"}
}