{
  "type": "Feature",
  "properties": {
    "iso:country":"ES",
    "sg:address":"Carr Llibertat, 6",
    "sg:city":"Silla",
    "sg:orig_category":"Reposter\u00cdas",
    "sg:phone":"+34 961 21 14 75",
    "sg:postcode":"46460",
    "sg:province":"Valencia",
    "wof:name":"Forn De Clavijo S.l.",
    "wof:placetype":"venue"
},
  "geometry": {"coordinates":[-0.417858988,39.3685531616],"type":"Point"}
}