{
  "type": "Feature",
  "properties": {
    "iso:country":"ES",
    "sg:address":"Calle de Escalante, 136",
    "sg:city":"Valencia",
    "sg:orig_category":"Bisuter\u00cda, Joyer\u00cda, Relojer\u00cda (al Por Menor)",
    "sg:phone":"+34 963 71 39 66",
    "sg:postcode":"46011",
    "sg:province":"Valencia",
    "wof:name":"Cardoset S.l",
    "wof:placetype":"venue"
},
  "geometry": {"coordinates":[-0.3309000134,39.4670028687],"type":"Point"}
}