{
  "type": "Feature",
  "properties": {
    "addr:full":"Cmno Barrancon (del), 1 Campillo Altobuey Cuenca 16210",
    "addr:housenumber":"1",
    "addr:postcode":"16210",
    "addr:street":"Cmno Barrancon Del",
    "iso:country":"ES",
    "sg:address":"Cmno Barrancon (del), 1",
    "sg:city":"Campillo Altobuey",
    "sg:orig_category":"Empresas De Carpinter\u00cda De Madera",
    "sg:phone":"+34 969 33 82 06",
    "sg:postcode":"16210",
    "sg:province":"Cuenca",
    "wof:name":"Carpinteria Carpinsalo S.l",
    "wof:placetype":"venue"
},
  "geometry": {"coordinates":[-1.7936370373,39.6123847961],"type":"Point"}
}