{
  "type": "Feature",
  "properties": {
    "addr:full":"Avda Constitucion, 33 Torrejon Ardoz Madrid 28850",
    "addr:housenumber":"33",
    "addr:postcode":"28850",
    "addr:street":"Avda Constitucion",
    "iso:country":"ES",
    "sg:address":"Avda Constitucion, 33",
    "sg:city":"Torrejon Ardoz",
    "sg:orig_category":"Estancos",
    "sg:phone":"+34 916 75 25 87",
    "sg:postcode":"28850",
    "sg:province":"Madrid",
    "wof:name":"Salvador Folgado Josefa",
    "wof:placetype":"venue"
},
  "geometry": {"coordinates":[-3.4781739712,40.4562568665],"type":"Point"}
}