{
  "type": "Feature",
  "properties": {
    "addr:full":"Avda Maria Auxiliadora, 10 Ecija Sevilla 41400",
    "addr:housenumber":"10",
    "addr:postcode":"41400",
    "addr:street":"Avda Maria Auxiliadora",
    "iso:country":"ES",
    "sg:address":"Avda Maria Auxiliadora, 10",
    "sg:city":"Ecija",
    "sg:orig_category":"Material Y Suministros Para Peluquer\u00cda",
    "sg:phone":"+34 955 90 09 38",
    "sg:postcode":"41400",
    "sg:province":"Sevilla",
    "wof:name":"Diaz Castillero Elisabeth",
    "wof:placetype":"venue"
},
  "geometry": {"coordinates":[-5.0860528946,37.5423469543],"type":"Point"}
}