{
  "type": "Feature",
  "properties": {
    "iso:country":"ES",
    "sg:address":"Avgd Montserrat, 21",
    "sg:city":"Igualada",
    "sg:orig_category":"Empresas De Carpinter\u00cda",
    "sg:phone":"+34 938 04 56 02",
    "sg:postcode":"08700",
    "sg:province":"Barcelona",
    "wof:name":"Vidres Igualada S.l.",
    "wof:placetype":"venue"
},
  "geometry": {"coordinates":[1.6056779623,41.5870666504],"type":"Point"}
}