{
  "type": "Feature",
  "properties": {
    "iso:country":"ES",
    "sg:address":"Calle de Mariano Barbasan, 12",
    "sg:city":"Zaragoza",
    "sg:orig_category":"Molduras, Junquillos, Listones Y Molduras Perforadas",
    "sg:phone":"+34 976 35 30 60",
    "sg:postcode":"50006",
    "sg:province":"Zaragoza",
    "wof:name":"Monforte Puyo Manuel",
    "wof:placetype":"venue"
},
  "geometry": {"coordinates":[-0.8914206028,41.6422195435],"type":"Point"}
}