{
  "type": "Feature",
  "properties": {
    "addr:full":"Plaz Espa\u00d1a, S/n Lepe Huelva 21440",
    "addr:housenumber":"s / n",
    "addr:postcode":"21440",
    "addr:street":"Plaz Espan\u0303A",
    "iso:country":"ES",
    "sg:address":"Plaz Espa\u00d1a, S/n",
    "sg:city":"Lepe",
    "sg:orig_category":"Ropa Y Accesorios",
    "sg:phone":"+34 959 38 14 39",
    "sg:postcode":"21440",
    "sg:province":"Huelva",
    "wof:name":"Feria Ramirez Antonio Angel",
    "wof:placetype":"venue"
},
  "geometry": {"coordinates":[-7.2027211189,37.2544059753],"type":"Point"}
}