{
  "type": "Feature",
  "properties": {
    "iso:country":"ES",
    "sg:address":"Calle de Pepe Luces, S/n",
    "sg:city":"Alcala Guadaira",
    "sg:orig_category":"Peluquer\u00cdas, Peluquer\u00cda Mixta",
    "sg:phone":"+34 954 10 13 90",
    "sg:postcode":"41500",
    "sg:province":"Sevilla",
    "wof:name":"Bastida Burgos Alicia",
    "wof:placetype":"venue"
},
  "geometry": {"coordinates":[-5.8388237953,37.3398895264],"type":"Point"}
}