{
  "type": "Feature",
  "properties": {
    "iso:country":"ES",
    "sg:address":"Calle de Principe De Vergara, 185",
    "sg:city":"Madrid",
    "sg:orig_category":"Farmacias",
    "sg:phone":"+34 915 62 58 83",
    "sg:postcode":"28002",
    "sg:province":"Madrid",
    "wof:name":"Fernandez Alfonso Jose Manuel",
    "wof:placetype":"venue"
},
  "geometry": {"coordinates":[-3.6781671047,40.4478187561],"type":"Point"}
}