{
  "type": "Feature",
  "properties": {
    "iso:country":"ES",
    "sg:address":"Calle de Escultores, 7",
    "sg:city":"Salamanca",
    "sg:orig_category":"Mec\u00c1nico Del Autom\u00d3vil",
    "sg:phone":"+34 923 25 15 05",
    "sg:postcode":"37006",
    "sg:province":"Salamanca",
    "wof:name":"Garcia Abeledo Sebastian",
    "wof:placetype":"venue"
},
  "geometry": {"coordinates":[-5.6686382294,40.9743003845],"type":"Point"}
}