{
  "type": "Feature",
  "properties": {
    "iso:country":"ES",
    "sg:address":"Rua Leiras Pulpeiro, 2",
    "sg:city":"Ourense",
    "sg:orig_category":"Promotores Constructores",
    "sg:phone":"+34 988 39 91 10",
    "sg:postcode":"32005",
    "sg:province":"Ourense",
    "wof:name":"Alariz Promocions Inmobiliarias 2002 S.l.",
    "wof:placetype":"venue"
},
  "geometry": {"coordinates":[-7.8638095856,42.3255386353],"type":"Point"}
}