{
  "type": "Feature",
  "properties": {
    "addr:full":"Avda Fernando Calzadilla, 14 Badajoz Badajoz 06004",
    "addr:housenumber":"14",
    "addr:postcode":"06004",
    "addr:street":"Avda Fernando Calzadilla",
    "iso:country":"ES",
    "sg:address":"Avda Fernando Calzadilla, 14",
    "sg:city":"Badajoz",
    "sg:orig_category":"Ropa Para Se\u00d1oras (al Por Menor)",
    "sg:phone":"+34 924 23 84 06",
    "sg:postcode":"06004",
    "sg:province":"Badajoz",
    "wof:name":"Bejarano Moreno Antonia",
    "wof:placetype":"venue"
},
  "geometry": {"coordinates":[-6.973028183,38.8701629639],"type":"Point"}
}