{
  "type": "Feature",
  "properties": {
    "iso:country":"ES",
    "sg:address":"Carr Cappont, 8",
    "sg:city":"Lleida",
    "sg:orig_category":"Costureras",
    "sg:phone":"+34 973 21 11 71",
    "sg:postcode":"25001",
    "sg:province":"Lleida",
    "wof:name":"Hidalgo Lopez Amparo",
    "wof:placetype":"venue"
},
  "geometry": {"coordinates":[0.6302729845,41.6126403809],"type":"Point"}
}