{
  "type": "Feature",
  "properties": {
    "addr:full":"Avda Peru (del), 76 Roquetas Mar Almer\u00eda 04740",
    "addr:housenumber":"76",
    "addr:postcode":"04740",
    "addr:street":"Avda Peru Del;Mar Almeri\u0301A",
    "iso:country":"ES",
    "sg:address":"Avda Peru (del), 76",
    "sg:city":"Roquetas Mar",
    "sg:orig_category":"Cr\u00cda De Animales",
    "sg:phone":"+34 950 32 59 74",
    "sg:postcode":"04740",
    "sg:province":"Almer\u00eda",
    "wof:name":"Sovasama S.l.",
    "wof:placetype":"venue"
},
  "geometry": {"coordinates":[-2.6087288857,36.7623786926],"type":"Point"}
}