{
  "type": "Feature",
  "properties": {
    "addr:full":"Carrer de Sant Jaume, 17 Hostalets Balenya Barcelona 08550",
    "addr:housenumber":"17",
    "addr:postcode":"08550",
    "addr:street":"Carrer De Sant Jaume",
    "iso:country":"ES",
    "sg:address":"Carrer de Sant Jaume, 17",
    "sg:city":"Hostalets Balenya",
    "sg:orig_category":"Abrasivos Y Superabrasivos (fabricaci\u00d3n, Al Por Mayor)",
    "sg:phone":"+34 938 89 84 10",
    "sg:postcode":"08550",
    "sg:province":"Barcelona",
    "wof:name":"Honingtec S. A.",
    "wof:placetype":"venue"
},
  "geometry": {"coordinates":[2.2285120487,41.8086662292],"type":"Point"}
}