{
  "type": "Feature",
  "properties": {
    "addr:full":"Calle de Marqueses De Aledo, 34 Alcantarilla Murcia 30820",
    "addr:housenumber":"34",
    "addr:postcode":"30820",
    "addr:street":"Calle De Marqueses;Aledo",
    "iso:country":"ES",
    "sg:address":"Calle de Marqueses De Aledo, 34",
    "sg:city":"Alcantarilla",
    "sg:orig_category":"Internados & Ense\u00d1anza Privada",
    "sg:phone":"+34 968 80 63 29",
    "sg:postcode":"30820",
    "sg:province":"Murcia",
    "wof:name":"Colegio Sagrado Corazon De Jesus",
    "wof:placetype":"venue"
},
  "geometry": {"coordinates":[-1.2132669687,37.9763336182],"type":"Point"}
}