{
  "type": "Feature",
  "properties": {
    "addr:full":"Calle de Almesias, 46 Burriana Castell\u00f3n 12530",
    "addr:housenumber":"46",
    "addr:postcode":"12530",
    "addr:street":"Calle De Almesias",
    "iso:country":"ES",
    "sg:address":"Calle de Almesias, 46",
    "sg:city":"Burriana",
    "sg:orig_category":"Transportes Por V\u00cdas Navegables",
    "sg:phone":"+34 964 51 25 70",
    "sg:postcode":"12530",
    "sg:province":"Castell\u00f3n",
    "wof:name":"Cooperativa Industrial De Transportes San Blas",
    "wof:placetype":"venue"
},
  "geometry": {"coordinates":[-0.0851870999,39.8838119507],"type":"Point"}
}