{
  "type": "Feature",
  "properties": {
    "iso:country":"ES",
    "sg:address":"Calle de General Gonzalez, 56",
    "sg:city":"Canjayar",
    "sg:orig_category":"Electricidad: Instaladores",
    "sg:phone":"+34 950 51 04 30",
    "sg:postcode":"04450",
    "sg:province":"Almer\u00eda",
    "wof:name":"M\u00aa Del Pilar Carretero Vique",
    "wof:placetype":"venue"
},
  "geometry": {"coordinates":[-2.741202116,37.0108146667],"type":"Point"}
}