{
  "type": "Feature",
  "properties": {
    "iso:country":"ES",
    "sg:address":"Calle de Ronda De Gracia, 27",
    "sg:city":"Medina Campo",
    "sg:orig_category":"Venta, Instalaci\u00d3n De Calefacci\u00d3n",
    "sg:phone":"+34 983 81 13 70",
    "sg:postcode":"47400",
    "sg:province":"Valladolid",
    "wof:name":"Medifoncal Sociedad Cooperativa Limitada",
    "wof:placetype":"venue"
},
  "geometry": {"coordinates":[-4.9182419777,41.307598114],"type":"Point"}
}