{
  "type": "Feature",
  "properties": {
    "addr:full":"Calle de Puebla De Valverde, 2 Valencia Valencia 46014",
    "addr:housenumber":"2",
    "addr:postcode":"46014",
    "addr:street":"Calle De Puebla;Valverde",
    "iso:country":"ES",
    "sg:address":"Calle de Puebla De Valverde, 2",
    "sg:city":"Valencia",
    "sg:orig_category":"Peluqueros: De Se\u00d1oras",
    "sg:phone":"+34 963 58 06 34",
    "sg:postcode":"46014",
    "sg:province":"Valencia",
    "wof:name":"Satule S.l.",
    "wof:placetype":"venue"
},
  "geometry": {"coordinates":[-0.4012739956,39.4596252441],"type":"Point"}
}