{
  "type": "Feature",
  "properties": {
    "addr:full":"Avda Martinez De Velasco, 38 Huesca Huesca 22004",
    "addr:housenumber":"38",
    "addr:postcode":"22004",
    "addr:street":"Avda Martinez De Velasco",
    "iso:country":"ES",
    "sg:address":"Avda Martinez De Velasco, 38",
    "sg:city":"Huesca",
    "sg:orig_category":"Ortopedia General",
    "sg:phone":"+34 974 21 07 51",
    "sg:postcode":"22004",
    "sg:province":"Huesca",
    "wof:name":"Ortopedia Axis S.l.",
    "wof:placetype":"venue"
},
  "geometry": {"coordinates":[-0.4183099866,42.1322135925],"type":"Point"}
}