{
  "type": "Feature",
  "properties": {
    "addr:full":"Bo La Tijeruca, 79 Pontejos Cantabria 39618",
    "addr:housenumber":"79",
    "addr:postcode":"39618",
    "addr:street":"Bo La Tijeruca",
    "iso:country":"ES",
    "sg:address":"Bo La Tijeruca, 79",
    "sg:city":"Pontejos",
    "sg:orig_category":"Peluqueros: De Se\u00d1oras",
    "sg:phone":"+34 942 50 31 41",
    "sg:postcode":"39618",
    "sg:province":"Cantabria",
    "wof:name":"Oria  Maria Josefa",
    "wof:placetype":"venue"
},
  "geometry": {"coordinates":[-3.7996590137,43.4083633423],"type":"Point"}
}