{
  "type": "Feature",
  "properties": {
    "addr:full":"Carrer de Ciutat De Balaguer, 61 Barcelona Barcelona 08022",
    "addr:housenumber":"61",
    "addr:postcode":"08022",
    "addr:street":"Carrer De Ciutat De Balaguer",
    "iso:country":"ES",
    "sg:address":"Carrer de Ciutat De Balaguer, 61",
    "sg:city":"Barcelona",
    "sg:orig_category":"Aparcamientos (infraestructuras, Accesorios)",
    "sg:phone":"+34 934 17 30 17",
    "sg:postcode":"08022",
    "sg:province":"Barcelona",
    "wof:name":"Herreiz Roy Enrique",
    "wof:placetype":"venue"
},
  "geometry": {"coordinates":[2.1335361004,41.4047813416],"type":"Point"}
}