{
  "type": "Feature",
  "properties": {
    "addr:full":"Urb Casalot, S/n Miami Platja Tarragona 43892",
    "addr:housenumber":"s / n",
    "addr:postcode":"43892",
    "addr:street":"Urb Casalot",
    "iso:country":"ES",
    "sg:address":"Urb Casalot, S/n",
    "sg:city":"Miami Platja",
    "sg:orig_category":"Molduras, Junquillos, Listones Y Molduras Perforadas",
    "sg:phone":"+34 977 17 10 26",
    "sg:postcode":"43892",
    "sg:province":"Tarragona",
    "wof:name":"Alcaide Jimenez Javier",
    "wof:placetype":"venue"
},
  "geometry": {"coordinates":[0.9366844893,41.0129203796],"type":"Point"}
}