{
  "type": "Feature",
  "properties": {
    "iso:country":"ES",
    "sg:address":"Plaz Valgamedios, S/n",
    "sg:city":"Denia",
    "sg:orig_category":"Librer\u00cdas",
    "sg:phone":"+34 965 78 76 88",
    "sg:postcode":"03700",
    "sg:province":"Alicante",
    "wof:name":"Prensa Cotidiana S.l.",
    "wof:placetype":"venue"
},
  "geometry": {"coordinates":[0.1019949988,38.8394508362],"type":"Point"}
}