{
  "type": "Feature",
  "properties": {
    "addr:full":"Pg Anglada Camarasa, 9 Puerto De Pollen\u00c7a Islas Baleares 07470",
    "addr:housenumber":"9",
    "addr:postcode":"07470",
    "addr:street":"Pg Anglada Camarasa",
    "iso:country":"ES",
    "sg:address":"Pg Anglada Camarasa, 9",
    "sg:city":"Puerto De Pollen\u00c7a",
    "sg:orig_category":"Confecci\u00d3n (fabricaci\u00d3n, Al Por Mayor)",
    "sg:phone":"+34 971 86 50 89",
    "sg:postcode":"07470",
    "sg:province":"Islas Baleares",
    "wof:name":"Nofeju S.a.",
    "wof:placetype":"venue"
},
  "geometry": {"coordinates":[3.0821900368,39.9063034058],"type":"Point"}
}