{
  "type": "Feature",
  "properties": {
    "iso:country":"ES",
    "sg:address":"Calle de Zacatecas, 15",
    "sg:city":"Salto Del Negro",
    "sg:orig_category":"Venta, Localizaci\u00d3n, Reparaci\u00d3n De Material E Instrumental M\u00c9dico",
    "sg:phone":"+34 928 31 91 03",
    "sg:postcode":"35016",
    "sg:province":"Las Palmas",
    "wof:name":"Josefa Saura S.l.",
    "wof:placetype":"venue"
},
  "geometry": {"coordinates":[-15.4231595993,28.0637378693],"type":"Point"}
}