{
  "type": "Feature",
  "properties": {
    "addr:full":"Calle de Novelda, 40 San Vicente Del Raspeig-sant Vicent Del Raspeig Alicante 03690",
    "addr:housenumber":"40",
    "addr:postcode":"03690",
    "addr:street":"Calle De Novelda",
    "iso:country":"ES",
    "sg:address":"Calle de Novelda, 40",
    "sg:city":"San Vicente Del Raspeig-sant Vicent Del Raspeig",
    "sg:orig_category":"Centros Comerciales Y Grandes Tiendas",
    "sg:phone":"+34 965 66 43 91",
    "sg:postcode":"03690",
    "sg:province":"Alicante",
    "wof:name":"Recursos En La Red S.l.",
    "wof:placetype":"venue"
},
  "geometry": {"coordinates":[-0.5321090221,38.3983306885],"type":"Point"}
}