{
  "type": "Feature",
  "properties": {
    "addr:full":"Carr Guifre, 758 Badalona Barcelona 08918",
    "addr:housenumber":"758",
    "addr:postcode":"08918",
    "addr:street":"Carr Guifre",
    "iso:country":"ES",
    "sg:address":"Carr Guifre, 758",
    "sg:city":"Badalona",
    "sg:orig_category":"Molduras, Junquillos, Listones Y Molduras Perforadas",
    "sg:phone":"+34 934 60 00 50",
    "sg:postcode":"08918",
    "sg:province":"Barcelona",
    "wof:name":"Fernandez Fernandez Maria Josefa",
    "wof:placetype":"venue"
},
  "geometry": {"coordinates":[2.2304189205,41.4345474243],"type":"Point"}
}