{
  "type": "Feature",
  "properties": {
    "addr:full":"Pol Empresarium, 5 Cartuja Baja Zaragoza 50720",
    "addr:housenumber":"5",
    "addr:postcode":"50720",
    "addr:street":"Empresarium;Baja",
    "iso:country":"ES",
    "sg:address":"Pol Empresarium, 5",
    "sg:city":"Cartuja Baja",
    "sg:orig_category":"V\u00c1lvulas",
    "sg:phone":"+34 976 45 48 40",
    "sg:postcode":"50720",
    "sg:province":"Zaragoza",
    "wof:name":"Ringo Valvula S.l.l.",
    "wof:placetype":"venue"
},
  "geometry": {"coordinates":[-0.8236089945,41.602935791],"type":"Point"}
}