{
  "type": "Feature",
  "properties": {
    "iso:country":"ES",
    "sg:address":"Corall, 8",
    "sg:city":"Cadenas",
    "sg:orig_category":"Bisuteros (fabricaci\u00d3n, Al Por Mayor)",
    "sg:phone":"+34 971 26 86 88",
    "sg:postcode":"07608",
    "sg:province":"Islas Baleares",
    "wof:name":"Mulet Castell Pedro",
    "wof:placetype":"venue"
},
  "geometry": {"coordinates":[2.7552499771,39.5284156799],"type":"Point"}
}