{
  "type": "Feature",
  "properties": {
    "addr:full":"Calle de I\u00d1aki Deuna, 23 Ondarroa Vizcaya 48700",
    "addr:housenumber":"23",
    "addr:postcode":"48700",
    "addr:street":"Calle De In\u0303Aki Deuna",
    "iso:country":"ES",
    "sg:address":"Calle de I\u00d1aki Deuna, 23",
    "sg:city":"Ondarroa",
    "sg:orig_category":"Sociedades, Compa\u00d1\u00cdas Aseguradoras",
    "sg:phone":"+34 946 13 42 68",
    "sg:postcode":"48700",
    "sg:province":"Vizcaya",
    "sg:website":"www.segurosbilbao.com",
    "wof:name":"Artime Elu Koldobika",
    "wof:placetype":"venue"
},
  "geometry": {"coordinates":[-2.4257230759,43.3198928833],"type":"Point"}
}