{
  "type": "Feature",
  "properties": {
    "addr:full":"Pol Ind El Cruce, S/n Bailen Ja\u00e9n 23710",
    "addr:housenumber":"s",
    "addr:postcode":"23710",
    "addr:street":"El Cruce;/ N;Jae\u0301N",
    "iso:country":"ES",
    "sg:address":"Pol Ind El Cruce, S/n",
    "sg:city":"Bailen",
    "sg:orig_category":"Reparaciones Y Remolcado De Veh\u00cdculos",
    "sg:phone":"+34 953 67 31 15",
    "sg:postcode":"23710",
    "sg:province":"Ja\u00e9n",
    "wof:name":"Ozaez Gutierrez Francisco Luis",
    "wof:placetype":"venue"
},
  "geometry": {"coordinates":[-3.7829740047,38.0899047852],"type":"Point"}
}