{
  "type": "Feature",
  "properties": {
    "addr:full":"Calle de Avila, 7 Tiemblo \u00c1vila 05270",
    "addr:housenumber":"7",
    "addr:postcode":"05270",
    "addr:street":"Calle De Avila;A\u0301Vila",
    "iso:country":"ES",
    "sg:address":"Calle de Avila, 7",
    "sg:city":"Tiemblo",
    "sg:orig_category":"Supermercados Y Hipermercados",
    "sg:phone":"+34 918 62 50 77",
    "sg:postcode":"05270",
    "sg:province":"\u00c1vila",
    "wof:name":"Colino Reviejo Manuel",
    "wof:placetype":"venue"
},
  "geometry": {"coordinates":[-4.5002861023,40.4145774841],"type":"Point"}
}