{
  "type": "Feature",
  "properties": {
    "addr:full":"Avda Pais Valencia, 106 Torrent Valencia 46900",
    "addr:housenumber":"106",
    "addr:postcode":"46900",
    "addr:street":"Avda Pais Valencia;Valencia",
    "iso:country":"ES",
    "sg:address":"Avda Pais Valencia, 106",
    "sg:city":"Torrent",
    "sg:orig_category":"Sociedades, Compa\u00d1\u00cdas Aseguradoras",
    "sg:phone":"+34 961 59 50 44",
    "sg:postcode":"46900",
    "sg:province":"Valencia",
    "wof:name":"Mapfre Servicios De Informatica S.a.",
    "wof:placetype":"venue"
},
  "geometry": {"coordinates":[-0.4742250144,39.4307441711],"type":"Point"}
}