{
  "type": "Feature",
  "properties": {
    "addr:full":"Calle de Camino De Cantalobos, 1 Sevilla Sevilla 41008",
    "addr:housenumber":"1",
    "addr:postcode":"41008",
    "addr:street":"Calle De Camino De Cantalobos",
    "iso:country":"ES",
    "sg:address":"Calle de Camino De Cantalobos, 1",
    "sg:city":"Sevilla",
    "sg:orig_category":"Farmacias",
    "sg:phone":"+34 954 95 36 48",
    "sg:postcode":"41008",
    "sg:province":"Sevilla",
    "wof:name":"Carrasco Martinez-matamoros Macarena",
    "wof:placetype":"venue"
},
  "geometry": {"coordinates":[-5.9760808945,37.4135284424],"type":"Point"}
}