{
  "type": "Feature",
  "properties": {
    "iso:country":"ES",
    "sg:address":"Calle de Albert Einstein, 40",
    "sg:city":"Mi\u00e7ano Menor",
    "sg:orig_category":"Venta, Instalaci\u00d3n De Calefacci\u00d3n",
    "sg:phone":"+34 945 14 74 02",
    "sg:postcode":"01510",
    "sg:province":"\u00c1lava",
    "wof:name":"Giroa S.a.",
    "wof:placetype":"venue"
},
  "geometry": {"coordinates":[-2.6983869076,42.9099998474],"type":"Point"}
}