{
  "type": "Feature",
  "properties": {
    "addr:full":"Calle de Goya, 46 Madrid Madrid 28001",
    "addr:housenumber":"46",
    "addr:postcode":"madrid;28001",
    "addr:street":"Calle De Goya",
    "iso:country":"ES",
    "sg:address":"Calle de Goya, 46",
    "sg:city":"Madrid",
    "sg:orig_category":"M\u00c9dicos: Estomatolog\u00cda",
    "sg:phone":"+34 914 31 66 59",
    "sg:postcode":"28001",
    "sg:province":"Madrid",
    "wof:name":"Adan Del Rivero Maria Dolores",
    "wof:placetype":"venue"
},
  "geometry": {"coordinates":[-3.6792185307,40.4249343872],"type":"Point"}
}