{
  "type": "Feature",
  "properties": {
    "iso:country":"ES",
    "sg:address":"Carrer de Joan Munar, 13",
    "sg:city":"Palma",
    "sg:orig_category":"Plomeros",
    "sg:phone":"+34 971 75 40 71",
    "sg:postcode":"07004",
    "sg:province":"Islas Baleares",
    "wof:name":"Juan Tur Francisco",
    "wof:placetype":"venue"
},
  "geometry": {"coordinates":[2.657004118,39.579875946],"type":"Point"}
}