{
  "type": "Feature",
  "properties": {
    "addr:full":"Calle de Ruben Dario, 3 Vi\u00d1a Murcia 30800",
    "addr:housenumber":"3",
    "addr:postcode":"30800",
    "addr:street":"Calle De Ruben Dario",
    "iso:country":"ES",
    "sg:address":"Calle de Ruben Dario, 3",
    "sg:city":"Vi\u00d1a",
    "sg:orig_category":"Inform\u00c1tica: Mantenimiento Y Reparaci\u00d3n De Ordenadores",
    "sg:phone":"+34 968 47 34 67",
    "sg:postcode":"30800",
    "sg:province":"Murcia",
    "sg:website":"www.dorjansd.com",
    "wof:name":"Dorjan Sistemas Y Datos S.l.",
    "wof:placetype":"venue"
},
  "geometry": {"coordinates":[-1.6905640364,37.680557251],"type":"Point"}
}