{
  "type": "Feature",
  "properties": {
    "addr:full":"Calle de Duque De Rivas, 24 Le\u00f3n Le\u00f3n 24007",
    "addr:housenumber":"24",
    "addr:postcode":"24007",
    "addr:street":"Calle De Duque De Rivas;Leo\u0301N",
    "iso:country":"ES",
    "sg:address":"Calle de Duque De Rivas, 24",
    "sg:city":"Le\u00f3n",
    "sg:orig_category":"Muebles Y Accesorios Para Cocinas Y Cuartos De Ba\u00d1o (al Por Menor)",
    "sg:phone":"+34 987 22 87 83",
    "sg:postcode":"24007",
    "sg:province":"Le\u00f3n",
    "wof:name":"Cuarto De Ba\u00f1o S.l.",
    "wof:placetype":"venue"
},
  "geometry": {"coordinates":[-5.566163063,42.6074905396],"type":"Point"}
}