{
  "type": "Feature",
  "properties": {
    "iso:country":"ES",
    "sg:address":"Ctra. Plasencia Trujillo, Km. 0051,0",
    "sg:city":"Torrejon Rubio",
    "sg:orig_category":"Cr\u00cda De Animales",
    "sg:phone":"+34 927 19 91 30",
    "sg:postcode":"10694",
    "sg:province":"C\u00e1ceres",
    "wof:name":"Diaz Perez Francisco",
    "wof:placetype":"venue"
},
  "geometry": {"coordinates":[-6.0109138489,39.7684135437],"type":"Point"}
}