{
  "type": "Feature",
  "properties": {
    "addr:full":"Av Catalunya, 23 Tarragona Tarragona 43002",
    "addr:housenumber":"23",
    "addr:postcode":"43002",
    "addr:street":"Av Catalunya",
    "iso:country":"ES",
    "sg:address":"Av Catalunya, 23",
    "sg:city":"Tarragona",
    "sg:orig_category":"Centros Comerciales Y Grandes Tiendas",
    "sg:phone":"+34 977 22 26 55",
    "sg:postcode":"43002",
    "sg:province":"Tarragona",
    "wof:name":"Badet Sedo Roser",
    "wof:placetype":"venue"
},
  "geometry": {"coordinates":[1.2522829771,41.1205596924],"type":"Point"}
}