{
  "type": "Feature",
  "properties": {
    "iso:country":"ES",
    "sg:address":"Carrer de Angel Ara\u00d1o, 53",
    "sg:city":"Viladecans",
    "sg:orig_category":"Alimentaci\u00d3n General (al Por Mayor)",
    "sg:phone":"+34 936 58 86 03",
    "sg:postcode":"08840",
    "sg:province":"Barcelona",
    "wof:name":"Virgili Mercade Daniel",
    "wof:placetype":"venue"
},
  "geometry": {"coordinates":[2.0136620998,41.3184509277],"type":"Point"}
}