{
  "type": "Feature",
  "properties": {
    "addr:full":"Calle de Santiago Beyro, 8 Santa Cruz De Tenerife Santa Cruz De Tenerife 38007",
    "addr:housenumber":"8",
    "addr:postcode":"38007",
    "addr:street":"Calle De Santiago Beyro",
    "iso:country":"ES",
    "sg:address":"Calle de Santiago Beyro, 8",
    "sg:city":"Santa Cruz De Tenerife",
    "sg:orig_category":"Peluquer\u00cdas, Peluquer\u00cda Mixta",
    "sg:phone":"+34 922 21 85 88",
    "sg:postcode":"38007",
    "sg:province":"Santa Cruz De Tenerife",
    "wof:name":"Gil Molina Juan",
    "wof:placetype":"venue"
},
  "geometry": {"coordinates":[-16.2715988159,28.4652175903],"type":"Point"}
}