{
  "type": "Feature",
  "properties": {
    "iso:country":"ES",
    "sg:address":"Carrer de Muntaner, 90",
    "sg:city":"Barcelona",
    "sg:orig_category":"Agencias De Viajes",
    "sg:phone":"+34 934 53 90 04",
    "sg:postcode":"08011",
    "sg:province":"Barcelona",
    "wof:name":"Standing Tours S.a.",
    "wof:placetype":"venue"
},
  "geometry": {"coordinates":[2.1576199532,41.3881721497],"type":"Point"}
}