{
  "type": "Feature",
  "properties": {
    "iso:country":"ES",
    "sg:address":"Carrascal, 1",
    "sg:city":"Beniparrell",
    "sg:orig_category":"Productos Fitosanitarios (negocio, Aplicaci\u00d3n)",
    "sg:phone":"+34 961 20 06 58",
    "sg:postcode":"46469",
    "sg:province":"Valencia",
    "wof:name":"Agroquimicos Y Servicios S.l.",
    "wof:placetype":"venue"
},
  "geometry": {"coordinates":[-0.4069963992,39.3838043213],"type":"Point"}
}