{
  "type": "Feature",
  "properties": {
    "addr:full":"Calle de Jenaro Oraa, 15 Santurtzi Vizcaya 48980",
    "addr:housenumber":"15",
    "addr:postcode":"48980",
    "addr:street":"Calle De Jenaro Oraa",
    "iso:country":"ES",
    "sg:address":"Calle de Jenaro Oraa, 15",
    "sg:city":"Santurtzi",
    "sg:orig_category":"Sociedades, Compa\u00d1\u00cdas Aseguradoras",
    "sg:phone":"+34 944 83 14 11",
    "sg:postcode":"48980",
    "sg:province":"Vizcaya",
    "sg:website":"www.seguroslagunaro.com",
    "wof:name":"Seguros Lagun Aro S.a.",
    "wof:placetype":"venue"
},
  "geometry": {"coordinates":[-3.0312359333,43.3274078369],"type":"Point"}
}