{
  "type": "Feature",
  "properties": {
    "addr:full":"Carrer de Ciutat D'asuncion, 28 Barcelona Barcelona 08030",
    "addr:housenumber":"28",
    "addr:postcode":"08030",
    "addr:street":"Carrer De Ciutat D'Asuncion",
    "iso:country":"ES",
    "sg:address":"Carrer de Ciutat D'asuncion, 28",
    "sg:city":"Barcelona",
    "sg:orig_category":"Negocio De Madera",
    "sg:phone":"+34 933 11 38 12",
    "sg:postcode":"08030",
    "sg:province":"Barcelona",
    "wof:name":"Maderas San Pascual S.l.",
    "wof:placetype":"venue"
},
  "geometry": {"coordinates":[2.2003376484,41.4395751953],"type":"Point"}
}