{
  "type": "Feature",
  "properties": {
    "iso:country":"ES",
    "sg:address":"Carrer de Ovidi, 5",
    "sg:city":"Sabadell",
    "sg:orig_category":"Electricidad: Instalaciones Industriales",
    "sg:phone":"+34 937 17 33 24",
    "sg:postcode":"08206",
    "sg:province":"Barcelona",
    "wof:name":"Diazelec S.l.",
    "wof:placetype":"venue"
},
  "geometry": {"coordinates":[2.0873310566,41.5541915894],"type":"Point"}
}