{
  "type": "Feature",
  "properties": {
    "iso:country":"ES",
    "sg:address":"Calle de Colombia, 10",
    "sg:city":"Pinto",
    "sg:orig_category":"Reciclaje, Desguace De Veh\u00cdculos",
    "sg:phone":"+34 916 91 14 67",
    "sg:postcode":"28320",
    "sg:province":"Madrid",
    "wof:name":"Almorox Montero Francisco Javier",
    "wof:placetype":"venue"
},
  "geometry": {"coordinates":[-3.7021868229,40.2377281189],"type":"Point"}
}