{
  "type": "Feature",
  "properties": {
    "iso:country":"ES",
    "sg:address":"Calle de Aragon, 4",
    "sg:city":"Palencia",
    "sg:orig_category":"Reparaciones Y Remolcado De Veh\u00cdculos",
    "sg:phone":"+34 979 74 32 33",
    "sg:postcode":"34003",
    "sg:province":"Palencia",
    "wof:name":"Tejedor Alonso Marciano Antonio",
    "wof:placetype":"venue"
},
  "geometry": {"coordinates":[-4.5344800949,42.0213432312],"type":"Point"}
}