{
  "type": "Feature",
  "properties": {
    "iso:country":"ES",
    "sg:address":"Calle de Aurea Galindo, 53",
    "sg:city":"Linares",
    "sg:orig_category":"Empresas De Carpinter\u00cda Met\u00c1lica",
    "sg:phone":"+34 953 65 24 12",
    "sg:postcode":"23700",
    "sg:province":"Ja\u00e9n",
    "wof:name":"Castumetal S.c.a.",
    "wof:placetype":"venue"
},
  "geometry": {"coordinates":[-3.6427769661,38.0933265686],"type":"Point"}
}