{
  "type": "Feature",
  "properties": {
    "addr:full":"Carr Comte De Rossello, 4 Eivissa Islas Baleares 07800",
    "addr:housenumber":"4",
    "addr:postcode":"07800",
    "addr:street":"Carr Comte De Rossello",
    "iso:country":"ES",
    "sg:address":"Carr Comte De Rossello, 4",
    "sg:city":"Eivissa",
    "sg:orig_category":"Bisuter\u00cda, Joyer\u00cda, Relojer\u00cda (al Por Menor)",
    "sg:phone":"+34 971 31 17 28",
    "sg:postcode":"07800",
    "sg:province":"Islas Baleares",
    "wof:name":"Mackenzie Parkin Deirdre",
    "wof:placetype":"venue"
},
  "geometry": {"coordinates":[1.4350960255,38.9092674255],"type":"Point"}
}