{
  "type": "Feature",
  "properties": {
    "addr:full":"Calle de Monroy, 1 Salamanca Salamanca 37001",
    "addr:housenumber":"1",
    "addr:postcode":"37001",
    "addr:street":"Calle De Monroy",
    "iso:country":"ES",
    "sg:address":"Calle de Monroy, 1",
    "sg:city":"Salamanca",
    "sg:orig_category":"Asesor\u00cda De Formaci\u00d3n Y Gesti\u00d3n De Personal",
    "sg:phone":"+34 923 26 02 28",
    "sg:postcode":"37001",
    "sg:province":"Salamanca",
    "wof:name":"Sanchez De Bustos Arturo",
    "wof:placetype":"venue"
},
  "geometry": {"coordinates":[-5.6609721184,40.9678497314],"type":"Point"}
}