{
  "type": "Feature",
  "properties": {
    "addr:full":"Avda Ricardo Fuster De, S/n Salas Asturias 33860",
    "addr:postcode":"33860",
    "addr:street":"Avda Ricardo Fuster De S / N",
    "iso:country":"ES",
    "sg:address":"Avda Ricardo Fuster De, S/n",
    "sg:city":"Salas",
    "sg:orig_category":"Art\u00cdculos Funerarios (al Por Menor)",
    "sg:phone":"+34 985 83 02 46",
    "sg:postcode":"33860",
    "sg:province":"Asturias",
    "wof:name":"Diaz Ibardia Jose Maria",
    "wof:placetype":"venue"
},
  "geometry": {"coordinates":[-6.2606191635,43.4088745117],"type":"Point"}
}