{
  "type": "Feature",
  "properties": {
    "iso:country":"ES",
    "sg:address":"Estda. Ourense-santiago, 91",
    "sg:city":"Cambeo",
    "sg:orig_category":"Contenedores (mercanc\u00cdas)",
    "sg:phone":"+34 988 20 21 02",
    "sg:postcode":"32100",
    "sg:province":"Ourense",
    "wof:name":"Salgado Vazquez Manuel",
    "wof:placetype":"venue"
},
  "geometry": {"coordinates":[-7.852959156,42.3917961121],"type":"Point"}
}