{
  "type": "Feature",
  "properties": {
    "addr:full":"Bedavo, S/n Linares Asturias 33948",
    "addr:housenumber":"/ n",
    "addr:postcode":"33948",
    "addr:street":"Bedavo S",
    "iso:country":"ES",
    "sg:address":"Bedavo, S/n",
    "sg:city":"Linares",
    "sg:orig_category":"Negocio De Materiales De Construcci\u00d3n",
    "sg:phone":"+34 985 66 23 12",
    "sg:postcode":"33948",
    "sg:province":"Asturias",
    "wof:name":"Almacenes De Construccion La Florida S.l",
    "wof:placetype":"venue"
},
  "geometry": {"coordinates":[-6.0072278976,43.5733757019],"type":"Point"}
}