{
  "type": "Feature",
  "properties": {
    "addr:full":"Calle de Leganes (de), 6 Fuenlabrada Madrid 28945",
    "addr:housenumber":"6",
    "addr:postcode":"28945",
    "addr:street":"Calle De Leganes De",
    "iso:country":"ES",
    "sg:address":"Calle de Leganes (de), 6",
    "sg:city":"Fuenlabrada",
    "sg:orig_category":"M\u00c9dicos: Estomatolog\u00cda",
    "sg:phone":"+34 916 97 09 32",
    "sg:postcode":"28945",
    "sg:province":"Madrid",
    "wof:name":"Sanchis Lopez Julio",
    "wof:placetype":"venue"
},
  "geometry": {"coordinates":[-3.793749094,40.2845993042],"type":"Point"}
}