{
  "type": "Feature",
  "properties": {
    "addr:full":"Carrer de Corts, 6 Barcelona Barcelona 08028",
    "addr:housenumber":"6",
    "addr:postcode":"08028",
    "addr:street":"Carrer De Corts",
    "iso:country":"ES",
    "sg:address":"Carrer de Corts, 6",
    "sg:city":"Barcelona",
    "sg:orig_category":"Electrodom\u00c9sticos (al Por Menor)",
    "sg:phone":"+34 933 30 64 65",
    "sg:postcode":"08028",
    "sg:province":"Barcelona",
    "wof:name":"Sazatornil Yuste Jose Maria",
    "wof:placetype":"venue"
},
  "geometry": {"coordinates":[2.1293230057,41.3842582703],"type":"Point"}
}