{
  "type": "Feature",
  "properties": {
    "addr:full":"Calle de Elias Tormo, 31 Benimamet-beniferri Valencia 46035",
    "addr:housenumber":"31",
    "addr:postcode":"46035",
    "addr:street":"Calle De Elias Tormo",
    "iso:country":"ES",
    "sg:address":"Calle de Elias Tormo, 31",
    "sg:city":"Benimamet-beniferri",
    "sg:orig_category":"Marroquiner\u00cda (confecci\u00d3n)",
    "sg:phone":"+34 963 47 47 73",
    "sg:postcode":"46035",
    "sg:province":"Valencia",
    "wof:name":"Manufactura Vmd S.l.",
    "wof:placetype":"venue"
},
  "geometry": {"coordinates":[-0.4193739891,39.5004463196],"type":"Point"}
}