{
  "type": "Feature",
  "properties": {
    "addr:full":"Carr Tarragona, S/n Caldes Malavella Girona 17455",
    "addr:postcode":"17455",
    "addr:street":"Carr Tarragona S / N",
    "iso:country":"ES",
    "sg:address":"Carr Tarragona, S/n",
    "sg:city":"Caldes Malavella",
    "sg:orig_category":"Promotores Constructores",
    "sg:phone":"+34 972 48 00 93",
    "sg:postcode":"17455",
    "sg:province":"Girona",
    "wof:name":"Colome Dalmau Xavier",
    "wof:placetype":"venue"
},
  "geometry": {"coordinates":[2.8018240929,41.8385505676],"type":"Point"}
}