{
  "type": "Feature",
  "properties": {
    "iso:country":"ES",
    "sg:address":"Avda Juan De La Cierva, 55",
    "sg:city":"Getafe",
    "sg:orig_category":"Sociedades, Compa\u00d1\u00cdas Aseguradoras",
    "sg:phone":"+34 916 83 46 33",
    "sg:postcode":"28902",
    "sg:province":"Madrid",
    "wof:name":"Portilla Gestion Tecnica De Seguros Agencia De Seguros S.l.",
    "wof:placetype":"venue"
},
  "geometry": {"coordinates":[-3.7257521152,40.3110580444],"type":"Point"}
}