{
  "type": "Feature",
  "properties": {
    "iso:country":"ES",
    "sg:address":"Calle de Marcelino Alvarez, 10",
    "sg:city":"Madrid",
    "sg:orig_category":"Comercio De Piezas De Recambio Y De Accesorios De Veh\u00cdculos, Veh\u00cdculos Industriales",
    "sg:phone":"+34 914 04 61 52",
    "sg:postcode":"28017",
    "sg:province":"Madrid",
    "sg:website":"www.telefonica.net/web/carroceriassigloxxi",
    "wof:name":"Carrocerias Siglo Xxi S.l.",
    "wof:placetype":"venue"
},
  "geometry": {"coordinates":[-3.6541879177,40.4317474365],"type":"Point"}
}