{
  "type": "Feature",
  "properties": {
    "iso:country":"ES",
    "sg:address":"Calle de Juan Bautista Sacchetti, 4",
    "sg:city":"Madrid",
    "sg:orig_category":"Asesor\u00cda Sobre Comunicaci\u00d3n De Empresas",
    "sg:phone":"+34 915 59 06 76",
    "sg:postcode":"28014",
    "sg:province":"Madrid",
    "wof:name":"Integral Interface Internacional S.l.",
    "wof:placetype":"venue"
},
  "geometry": {"coordinates":[-3.6876330376,40.4069290161],"type":"Point"}
}