{
  "type": "Feature",
  "properties": {
    "iso:country":"ES",
    "sg:address":"Calle de Falcons, 1",
    "sg:city":"Onda",
    "sg:orig_category":"\u00d3ptica: Instrumentos (fabricaci\u00d3n)",
    "sg:phone":"+34 964 77 23 77",
    "sg:postcode":"12200",
    "sg:province":"Castell\u00f3n",
    "wof:name":"Opti-shop S.l.",
    "wof:placetype":"venue"
},
  "geometry": {"coordinates":[-0.2650279999,39.9632034302],"type":"Point"}
}