{
  "type": "Feature",
  "properties": {
    "addr:full":"Plaz Espa\u00d1a, 4 Don Benito Badajoz 06400",
    "addr:housenumber":"4",
    "addr:postcode":"06400",
    "addr:street":"Plaz Espan\u0303A",
    "iso:country":"ES",
    "sg:address":"Plaz Espa\u00d1a, 4",
    "sg:city":"Don Benito",
    "sg:orig_category":"Cervecer\u00cdas",
    "sg:phone":"+34 924 80 18 14",
    "sg:postcode":"06400",
    "sg:province":"Badajoz",
    "wof:name":"Eurotel-sur S.l.",
    "wof:placetype":"venue"
},
  "geometry": {"coordinates":[-5.8639888763,38.9548797607],"type":"Point"}
}