{
  "type": "Feature",
  "properties": {
    "addr:full":"Calle de Lugo, 2 Arzua La Coru\u00f1a 15810",
    "addr:housenumber":"2",
    "addr:postcode":"15810",
    "addr:street":"Calle De Lugo;La Corun\u0303A",
    "iso:country":"ES",
    "sg:address":"Calle de Lugo, 2",
    "sg:city":"Arzua",
    "sg:orig_category":"Servicios Diversos",
    "sg:phone":"+34 981 81 50 10",
    "sg:postcode":"15810",
    "sg:province":"La Coru\u00f1a",
    "wof:name":"Funeraria Atlantica S.l.",
    "wof:placetype":"venue"
},
  "geometry": {"coordinates":[-8.1636676788,42.9268379211],"type":"Point"}
}