{
  "type": "Feature",
  "properties": {
    "addr:full":"Calle de Soledad, 7 Campo Criptana Ciudad Real 13610",
    "addr:housenumber":"7",
    "addr:postcode":"13610",
    "addr:street":"Calle De Soledad;Criptana",
    "iso:country":"ES",
    "sg:address":"Calle de Soledad, 7",
    "sg:city":"Campo Criptana",
    "sg:orig_category":"Bisuter\u00cda, Joyer\u00cda, Relojer\u00cda (al Por Menor)",
    "sg:phone":"+34 926 56 00 93",
    "sg:postcode":"13610",
    "sg:province":"Ciudad Real",
    "wof:name":"Colinet Gonzalez Jose",
    "wof:placetype":"venue"
},
  "geometry": {"coordinates":[-3.1263189316,39.4056091309],"type":"Point"}
}