{
  "type": "Feature",
  "properties": {
    "iso:country":"ES",
    "sg:address":"Calle de Luchana, 39",
    "sg:city":"Madrid",
    "sg:orig_category":"Florister\u00cdas",
    "sg:phone":"+34 914 48 11 92",
    "sg:postcode":"28010",
    "sg:province":"Madrid",
    "sg:website":"www.florescambria.com",
    "wof:name":"Calvo Moreno Juan Jose",
    "wof:placetype":"venue"
},
  "geometry": {"coordinates":[-3.6982400417,40.4322967529],"type":"Point"}
}