{
  "type": "Feature",
  "properties": {
    "iso:country":"ES",
    "sg:address":"Calle de Doctor Prado Villapol, 103",
    "sg:city":"Vicedo",
    "sg:orig_category":"Comercio De Piezas De Recambio Y De Accesorios De Veh\u00cdculos, Veh\u00cdculos Industriales",
    "sg:phone":"+34 982 59 03 64",
    "sg:postcode":"27860",
    "sg:province":"Lugo",
    "wof:name":"Mari\u00f1a Mari\u00f1a Jose",
    "wof:placetype":"venue"
},
  "geometry": {"coordinates":[-7.6637530327,43.7321472168],"type":"Point"}
}