{
  "type": "Feature",
  "properties": {
    "iso:country":"ES",
    "sg:address":"Calle de Castilla (de), 6",
    "sg:city":"Mejorada Campo",
    "sg:orig_category":"Mec\u00c1nico Del Autom\u00d3vil",
    "sg:phone":"+34 916 79 34 77",
    "sg:postcode":"28840",
    "sg:province":"Madrid",
    "wof:name":"Del Pino Mu\u00f1oz Roberto",
    "wof:placetype":"venue"
},
  "geometry": {"coordinates":[-3.4838309288,40.3888092041],"type":"Point"}
}