{
  "type": "Feature",
  "properties": {
    "iso:country":"ES",
    "sg:address":"Calle de Virgen Del Pilar, 3",
    "sg:city":"Alcuescar",
    "sg:orig_category":"Quincaller\u00cda (al Por Menor)",
    "sg:phone":"+34 927 38 42 33",
    "sg:postcode":"10160",
    "sg:province":"C\u00e1ceres",
    "wof:name":"Pajuelo Montes Maria De Los Angeles",
    "wof:placetype":"venue"
},
  "geometry": {"coordinates":[-6.2327928543,39.1816062927],"type":"Point"}
}