{
  "type": "Feature",
  "properties": {
    "addr:full":"Carrer de Ferran Clua, 85 Hospitalet De L'infant Tarragona 43890",
    "addr:housenumber":"85",
    "addr:postcode":"43890",
    "addr:street":"Carrer De Ferran Clua",
    "iso:country":"ES",
    "sg:address":"Carrer de Ferran Clua, 85",
    "sg:city":"Hospitalet De L'infant",
    "sg:orig_category":"Empresarios",
    "sg:phone":"+34 977 82 07 01",
    "sg:postcode":"43890",
    "sg:province":"Tarragona",
    "wof:name":"Eurolar 2000 S.l.",
    "wof:placetype":"venue"
},
  "geometry": {"coordinates":[1.2455840111,41.1117019653],"type":"Point"}
}