{
  "type": "Feature",
  "properties": {
    "addr:full":"Calle de Sdo Soberats Antol, 21 Palma Islas Baleares 07010",
    "addr:housenumber":"21",
    "addr:postcode":"07010",
    "addr:street":"Calle De Sdo;Antol",
    "iso:country":"ES",
    "sg:address":"Calle de Sdo Soberats Antol, 21",
    "sg:city":"Palma",
    "sg:orig_category":"Molduras, Junquillos, Listones Y Molduras Perforadas",
    "sg:phone":"+34 971 20 78 23",
    "sg:postcode":"07010",
    "sg:province":"Islas Baleares",
    "wof:name":"Gaso Sala Jaime",
    "wof:placetype":"venue"
},
  "geometry": {"coordinates":[2.6484088898,39.5861091614],"type":"Point"}
}