{
  "type": "Feature",
  "properties": {
    "addr:full":"Ctra Mig, 33 Hospitalet Llobregat Barcelona 08907",
    "addr:housenumber":"33",
    "addr:postcode":"08907",
    "addr:street":"Ctra Mig",
    "iso:country":"ES",
    "sg:address":"Ctra Mig, 33",
    "sg:city":"Hospitalet Llobregat",
    "sg:orig_category":"Imprenta",
    "sg:phone":"+34 933 35 93 39",
    "sg:postcode":"08907",
    "sg:province":"Barcelona",
    "wof:name":"Matarin Oca\u00f1a Cecilio",
    "wof:placetype":"venue"
},
  "geometry": {"coordinates":[2.1131510735,41.3581886292],"type":"Point"}
}