{
  "type": "Feature",
  "properties": {
    "addr:full":"Calle de Alvarez De Castro, 5 Campo Criptana Ciudad Real 13610",
    "addr:housenumber":"5",
    "addr:postcode":"13610",
    "addr:street":"Calle De Alvarez De Castro;Criptana",
    "iso:country":"ES",
    "sg:address":"Calle de Alvarez De Castro, 5",
    "sg:city":"Campo Criptana",
    "sg:orig_category":"Material Y Herramientas Agr\u00cdcolas",
    "sg:phone":"+34 926 56 06 20",
    "sg:postcode":"13610",
    "sg:province":"Ciudad Real",
    "wof:name":"Sociedad Agraria De Transformacion 9763 Agricola Mecanica",
    "wof:placetype":"venue"
},
  "geometry": {"coordinates":[-3.1243391037,39.403339386],"type":"Point"}
}