{
  "type": "Feature",
  "properties": {
    "addr:full":"Calle de Manuel Cue, 11 Llanes Asturias 33500",
    "addr:housenumber":"11",
    "addr:postcode":"33500",
    "addr:street":"Calle De Manuel Cue",
    "iso:country":"ES",
    "sg:address":"Calle de Manuel Cue, 11",
    "sg:city":"Llanes",
    "sg:orig_category":"Restaurantes",
    "sg:phone":"+34 985 40 08 91",
    "sg:postcode":"33500",
    "sg:province":"Asturias",
    "wof:name":"Jimenez Moreno Rosa",
    "wof:placetype":"venue"
},
  "geometry": {"coordinates":[-4.7542619705,43.4202423096],"type":"Point"}
}