{
  "type": "Feature",
  "properties": {
    "addr:full":"Calle de Alcala, 174 Madrid Madrid 28028",
    "addr:housenumber":"174",
    "addr:postcode":"28028",
    "addr:street":"Calle De Alcala",
    "iso:country":"ES",
    "sg:address":"Calle de Alcala, 174",
    "sg:city":"Madrid",
    "sg:orig_category":"Tiendas De Grano, Frutas Y Legumbres Secas (al Por Menor)",
    "sg:phone":"+34 917 25 06 13",
    "sg:postcode":"28028",
    "sg:province":"Madrid",
    "wof:name":"Cui  Hong",
    "wof:placetype":"venue"
},
  "geometry": {"coordinates":[-3.6662404537,40.4293289185],"type":"Point"}
}