{
  "type": "Feature",
  "properties": {
    "iso:country":"ES",
    "sg:address":"Plaz Espa\u00d1a, 17",
    "sg:city":"Badajoz",
    "sg:orig_category":"Estancos",
    "sg:phone":"+34 924 22 17 62",
    "sg:postcode":"06002",
    "sg:province":"Badajoz",
    "wof:name":"Lledo Perez Alberto Diego",
    "wof:placetype":"venue"
},
  "geometry": {"coordinates":[-6.97016716,38.8787002563],"type":"Point"}
}