{
  "type": "Feature",
  "properties": {
    "iso:country":"ES",
    "sg:address":"Calle de Cirilo Amoros, 41",
    "sg:city":"Valencia",
    "sg:orig_category":"Bisuter\u00cda, Joyer\u00cda, Relojer\u00cda (al Por Menor)",
    "sg:phone":"+34 963 52 80 33",
    "sg:postcode":"46004",
    "sg:province":"Valencia",
    "sg:website":"www.joyeriaaurom.com",
    "wof:name":"Victoria Aurum S.l.",
    "wof:placetype":"venue"
},
  "geometry": {"coordinates":[-0.3711819947,39.467590332],"type":"Point"}
}