{
  "type": "Feature",
  "properties": {
    "addr:full":"Carrer de Madrazo, 96 Barcelona Barcelona 08021",
    "addr:housenumber":"96",
    "addr:postcode":"08021",
    "addr:street":"Carrer De Madrazo",
    "iso:country":"ES",
    "sg:address":"Carrer de Madrazo, 96",
    "sg:city":"Barcelona",
    "sg:orig_category":"Peluqueros: De Se\u00d1oras",
    "sg:phone":"+34 932 01 89 14",
    "sg:postcode":"08021",
    "sg:province":"Barcelona",
    "wof:name":"Peralta Ibars Ana Maria",
    "wof:placetype":"venue"
},
  "geometry": {"coordinates":[2.145250082,41.3975944519],"type":"Point"}
}