{
  "type": "Feature",
  "properties": {
    "addr:full":"Rbla Catalunya, 57 Barcelona Barcelona 08007",
    "addr:housenumber":"57",
    "addr:postcode":"08007",
    "addr:street":"Rbla Catalunya",
    "iso:country":"ES",
    "sg:address":"Rbla Catalunya, 57",
    "sg:city":"Barcelona",
    "sg:orig_category":"Agencias Y Agentes Comerciales, Representantes",
    "sg:phone":"+34 934 88 28 63",
    "sg:postcode":"08007",
    "sg:province":"Barcelona",
    "wof:name":"Fragance Resources S.a. Oficina De Representacion En Espa\u00f1a",
    "wof:placetype":"venue"
},
  "geometry": {"coordinates":[2.1635940075,41.3906784058],"type":"Point"}
}