{
  "type": "Feature",
  "properties": {
    "iso:country":"ES",
    "sg:address":"Avda Lugo, 106",
    "sg:city":"Melide",
    "sg:classifiers":[
        {
            "category":"Taxi",
            "type":"Transportation"
        }
    ],
    "sg:phone":"+34 981 50 59 33",
    "sg:postcode":"15800",
    "sg:province":"La Coru\u00f1a",
    "wof:name":"Espi\u00f1eira Gonzalez Emilio",
    "wof:placetype":"venue"
},
  "geometry": {"coordinates":[-8.005449295,42.9121551514],"type":"Point"}
}