{
  "type": "Feature",
  "properties": {
    "iso:country":"ES",
    "sg:address":"Domingo Elizondo, 4",
    "sg:city":"Agoitz",
    "sg:orig_category":"Farmacias",
    "sg:phone":"+34 948 33 65 25",
    "sg:postcode":"31430",
    "sg:province":"Navarra",
    "wof:name":"Lera Toston Maria Yolanda",
    "wof:placetype":"venue"
},
  "geometry": {"coordinates":[-1.3718889952,42.7860527039],"type":"Point"}
}