{
  "type": "Feature",
  "properties": {
    "iso:country":"ES",
    "sg:address":"Crri Chupa La, 7",
    "sg:city":"Malaga",
    "sg:orig_category":"Supermercados Y Hipermercados",
    "sg:phone":"+34 952 33 37 51",
    "sg:postcode":"29004",
    "sg:province":"M\u00e1laga",
    "wof:name":"Supermercado Altozano S.l.",
    "wof:placetype":"venue"
},
  "geometry": {"coordinates":[-4.474984169,36.6674613953],"type":"Point"}
}