{
  "type": "Feature",
  "properties": {
    "iso:country":"ES",
    "sg:address":"Avda Europa, 18",
    "sg:city":"Vista Alegre",
    "sg:orig_category":"M\u00c9dicos: Medicina General Orientada A La Homeopat\u00cda",
    "sg:phone":"+34 968 24 73 54",
    "sg:postcode":"30007",
    "sg:province":"Murcia",
    "wof:name":"Martinez Albarracin Maria Jose",
    "wof:placetype":"venue"
},
  "geometry": {"coordinates":[-1.0909589529,38.0099525452],"type":"Point"}
}