{
  "type": "Feature",
  "properties": {
    "iso:country":"ES",
    "sg:address":"Carr Via Punica, 40",
    "sg:city":"Eivissa",
    "sg:orig_category":"Escuelas De Maternidad P\u00dablicas",
    "sg:phone":"+34 971 30 46 14",
    "sg:postcode":"07800",
    "sg:province":"Islas Baleares",
    "sg:website":"www.escoletas.com",
    "wof:name":"Torres Roig Amelia",
    "wof:placetype":"venue"
},
  "geometry": {"coordinates":[1.4188899994,38.9061164856],"type":"Point"}
}