{
  "type": "Feature",
  "properties": {
    "iso:country":"ES",
    "sg:address":"Calle de Danzas, 5",
    "sg:city":"Valencia",
    "sg:orig_category":"Librer\u00cdas",
    "sg:phone":"+34 963 92 48 72",
    "sg:postcode":"46001",
    "sg:province":"Valencia",
    "wof:name":"Libreria Asociativa Sahiri S.c.",
    "wof:placetype":"venue"
},
  "geometry": {"coordinates":[-0.3787521124,39.4750709534],"type":"Point"}
}