{
  "type": "Feature",
  "properties": {
    "addr:full":"Calle de Monjas, 9 Lepe Huelva 21440",
    "addr:housenumber":"9",
    "addr:postcode":"21440",
    "addr:street":"Calle De Monjas",
    "iso:country":"ES",
    "sg:address":"Calle de Monjas, 9",
    "sg:city":"Lepe",
    "sg:orig_category":"Frutas Y Legumbres Frescas (al Por Mayor)",
    "sg:phone":"+34 959 38 22 69",
    "sg:postcode":"21440",
    "sg:province":"Huelva",
    "wof:name":"Fresdominguez S.l.",
    "wof:placetype":"venue"
},
  "geometry": {"coordinates":[-7.2014489174,37.2558059692],"type":"Point"}
}