{
  "type": "Feature",
  "properties": {
    "addr:full":"Rio Urrobi, 3 Iru\u00f1a Navarra 31005",
    "addr:postcode":"31005",
    "iso:country":"ES",
    "sg:address":"Rio Urrobi, 3",
    "sg:city":"Iru\u00f1a",
    "sg:orig_category":"Asociaciones, Organismos Culturales Y Socioeducativos",
    "sg:phone":"+34 948 24 67 09",
    "sg:postcode":"31005",
    "sg:province":"Navarra",
    "wof:name":"Asociacion Lagun-zaharrak",
    "wof:placetype":"venue"
},
  "geometry": {"coordinates":[-1.6425694227,42.8045654297],"type":"Point"}
}