{
  "type": "Feature",
  "properties": {
    "iso:country":"ES",
    "sg:address":"Calle de Leon Y Castillo, 26",
    "sg:city":"Palmas De Gran Canaria",
    "sg:orig_category":"Centros P\u00dablicos De Formaci\u00d3n Profesional Y T\u00c9cnica",
    "sg:phone":"+34 928 36 82 64",
    "sg:postcode":"35003",
    "sg:province":"Las Palmas",
    "wof:name":"Colegio Oficial De Ingenieros Agronomos De Madrid",
    "wof:placetype":"venue"
},
  "geometry": {"coordinates":[-15.4188508987,28.1109237671],"type":"Point"}
}