{
  "type": "Feature",
  "properties": {
    "iso:country":"ES",
    "sg:address":"Calle de Mayor Triana, 9",
    "sg:city":"Totana",
    "sg:orig_category":"Art\u00cdculos De Decoraci\u00d3n (fabricaci\u00d3n Y Al Por Mayor)",
    "sg:phone":"+34 968 42 02 31",
    "sg:postcode":"30850",
    "sg:province":"Murcia",
    "wof:name":"Guarinos Garcia Jose Maria",
    "wof:placetype":"venue"
},
  "geometry": {"coordinates":[-1.500970006,37.7711830139],"type":"Point"}
}