{
  "type": "Feature",
  "properties": {
    "addr:full":"Luga Diseminado La Veguetilla, 50 Vega S. Mateo Las Palmas 35328",
    "addr:housenumber":"50",
    "addr:postcode":"35328",
    "addr:street":"Luga Diseminado La Veguetilla;S. Mateo Las",
    "iso:country":"ES",
    "sg:address":"Luga Diseminado La Veguetilla, 50",
    "sg:city":"Vega S. Mateo",
    "sg:orig_category":"Ingeniero",
    "sg:phone":"+34 928 66 02 10",
    "sg:postcode":"35328",
    "sg:province":"Las Palmas",
    "wof:name":"Mederos Gil Francisco",
    "wof:placetype":"venue"
},
  "geometry": {"coordinates":[-15.5824928284,28.0158691406],"type":"Point"}
}