{
  "type": "Feature",
  "properties": {
    "iso:country":"ES",
    "sg:address":"Ctra Arenas (de), S/n",
    "sg:city":"Velez-malaga",
    "sg:orig_category":"Cerrajer\u00cda, Ferrallista",
    "sg:phone":"+34 952 50 09 37",
    "sg:postcode":"29700",
    "sg:province":"M\u00e1laga",
    "wof:name":"Mercabrico S.l.",
    "wof:placetype":"venue"
},
  "geometry": {"coordinates":[-4.0987210274,36.7790222168],"type":"Point"}
}