{
  "type": "Feature",
  "properties": {
    "iso:country":"ES",
    "sg:address":"Rua Manuel Rodriguez, 16",
    "sg:city":"Porri\u00f1o",
    "sg:orig_category":"Bisuter\u00cda, Joyer\u00cda, Relojer\u00cda (al Por Menor)",
    "sg:phone":"+34 986 33 03 29",
    "sg:postcode":"36400",
    "sg:province":"Pontevedra",
    "wof:name":"Joyeria Covelo S.l",
    "wof:placetype":"venue"
},
  "geometry": {"coordinates":[-8.6208705902,42.1594581604],"type":"Point"}
}