{
  "type": "Feature",
  "properties": {
    "iso:country":"ES",
    "sg:address":"Carrer de Asturies, 1",
    "sg:city":"S. Boi Llobregat",
    "sg:orig_category":"Cerrajer\u00cda, Ferrallista",
    "sg:phone":"+34 936 30 26 50",
    "sg:postcode":"08830",
    "sg:province":"Barcelona",
    "wof:name":"Construcciones Y Montajes Gems S.l.",
    "wof:placetype":"venue"
},
  "geometry": {"coordinates":[2.0487549305,41.3323631287],"type":"Point"}
}