{
  "type": "Feature",
  "properties": {
    "addr:full":"Calle de Balbino Marron, S/n Sevilla Sevilla 41018",
    "addr:housenumber":"s / n",
    "addr:postcode":"41018",
    "addr:street":"Calle De Balbino Marron",
    "iso:country":"ES",
    "sg:address":"Calle de Balbino Marron, S/n",
    "sg:city":"Sevilla",
    "sg:orig_category":"Servicios Gsm",
    "sg:phone":"+34 954 64 61 05",
    "sg:postcode":"41018",
    "sg:province":"Sevilla",
    "wof:name":"Telefonica Moviles Espa\u00f1a S.a.",
    "wof:placetype":"venue"
},
  "geometry": {"coordinates":[-5.9775137901,37.380065918],"type":"Point"}
}