{
  "type": "Feature",
  "properties": {
    "iso:country":"ES",
    "sg:address":"General Del Norte, 33",
    "sg:city":"Realejos, Los",
    "sg:orig_category":"Servicios Gsm",
    "sg:phone":"+34 922 35 39 41",
    "sg:postcode":"38410",
    "sg:province":"Santa Cruz De Tenerife",
    "wof:name":"Rodriguez Doniz Abraham Jose",
    "wof:placetype":"venue"
},
  "geometry": {"coordinates":[-16.5807914734,28.3678131104],"type":"Point"}
}