{
  "type": "Feature",
  "properties": {
    "iso:country":"ES",
    "sg:address":"Av Pau Casals, 3",
    "sg:city":"Barcelona",
    "sg:orig_category":"Estilistas Y Estudios De Estilo De Corte Y Confecci\u00d3n",
    "sg:phone":"+34 932 02 05 58",
    "sg:postcode":"08021",
    "sg:province":"Barcelona",
    "wof:name":"E. Furest S.a.",
    "wof:placetype":"venue"
},
  "geometry": {"coordinates":[2.1434168816,41.3929710388],"type":"Point"}
}