{
  "type": "Feature",
  "properties": {
    "addr:full":"Calle de Nicolas De Las Pe\u00d1as, 28 Beniel Murcia 30130",
    "addr:housenumber":"28",
    "addr:postcode":"30130",
    "addr:street":"Calle De Nicolas De Las Pen\u0303As",
    "iso:country":"ES",
    "sg:address":"Calle de Nicolas De Las Pe\u00d1as, 28",
    "sg:city":"Beniel",
    "sg:orig_category":"Supermercados Y Hipermercados",
    "sg:phone":"+34 968 60 06 64",
    "sg:postcode":"30130",
    "sg:province":"Murcia",
    "wof:name":"Emdico S.a.",
    "wof:placetype":"venue"
},
  "geometry": {"coordinates":[-1.0033400059,38.0475196838],"type":"Point"}
}