{
  "type": "Feature",
  "properties": {
    "addr:full":"Calle de Vicente Puchol, 19 Castellar-oliveral Valencia 46026",
    "addr:housenumber":"19",
    "addr:postcode":"46026",
    "addr:street":"Calle De Vicente Puchol",
    "iso:country":"ES",
    "sg:address":"Calle de Vicente Puchol, 19",
    "sg:city":"Castellar-oliveral",
    "sg:orig_category":"Mercer\u00cda, Lencer\u00cda (al Por Menor)",
    "sg:phone":"+34 963 96 11 87",
    "sg:postcode":"46026",
    "sg:province":"Valencia",
    "wof:name":"Rodrigo Vivo Vicente",
    "wof:placetype":"venue"
},
  "geometry": {"coordinates":[-0.3636260033,39.4283905029],"type":"Point"}
}