{
  "type": "Feature",
  "properties": {
    "iso:country":"ES",
    "sg:address":"Calle de Campo Santo, 1",
    "sg:city":"Alcorcon",
    "sg:orig_category":"Confecci\u00d3n De Botones",
    "sg:phone":"+34 916 19 11 19",
    "sg:postcode":"28922",
    "sg:province":"Madrid",
    "wof:name":"Eloplex S. A.",
    "wof:placetype":"venue"
},
  "geometry": {"coordinates":[-3.8295230865,40.3531188965],"type":"Point"}
}