{
  "type": "Feature",
  "properties": {
    "addr:full":"Carrer de Viladecans, 25 S. Boi Llobregat Barcelona 08830",
    "addr:housenumber":"25",
    "addr:postcode":"08830",
    "addr:street":"Carrer De Viladecans",
    "iso:country":"ES",
    "sg:address":"Carrer de Viladecans, 25",
    "sg:city":"S. Boi Llobregat",
    "sg:orig_category":"Transportes Frigor\u00cdficos",
    "sg:phone":"+34 936 30 12 35",
    "sg:postcode":"08830",
    "sg:province":"Barcelona",
    "wof:name":"Arrastres Y Servicios Sant Boi S.l.",
    "wof:placetype":"venue"
},
  "geometry": {"coordinates":[2.096247673,41.3280982971],"type":"Point"}
}