{
  "type": "Feature",
  "properties": {
    "iso:country":"ES",
    "sg:address":"Calle de Luis Doreste Silva, 6",
    "sg:city":"Palmas De Gran Canaria",
    "sg:orig_category":"Promotores Constructores",
    "sg:phone":"+34 928 24 44 96",
    "sg:postcode":"35004",
    "sg:province":"Las Palmas",
    "wof:name":"Perez Moreno S.a.",
    "wof:placetype":"venue"
},
  "geometry": {"coordinates":[-15.4200839996,28.1149730682],"type":"Point"}
}