{
  "type": "Feature",
  "properties": {
    "iso:country":"ES",
    "sg:address":"Calle de Mendez Nu\u00d1ez, 4",
    "sg:city":"Carolina",
    "sg:orig_category":"Bisuter\u00cda, Joyer\u00cda, Relojer\u00cda (al Por Menor)",
    "sg:phone":"+34 953 68 03 73",
    "sg:postcode":"23200",
    "sg:province":"Ja\u00e9n",
    "wof:name":"Rosa Garcia Jose Manuel",
    "wof:placetype":"venue"
},
  "geometry": {"coordinates":[-3.614440918,38.2746162415],"type":"Point"}
}