{
  "type": "Feature",
  "properties": {
    "iso:country":"ES",
    "sg:address":"Calle de Sierra De Aralar, 34",
    "sg:city":"Donostia-san Sebastian",
    "sg:orig_category":"Estancos",
    "sg:phone":"+34 943 45 25 49",
    "sg:postcode":"20014",
    "sg:province":"Guip\u00f9zcoa",
    "wof:name":"Odriozola Odriozola Maria Dolores",
    "wof:placetype":"venue"
},
  "geometry": {"coordinates":[-1.9659349918,43.3109512329],"type":"Point"}
}