{
  "type": "Feature",
  "properties": {
    "iso:country":"ES",
    "sg:address":"Calle de Sauce, 62",
    "sg:city":"Torrejon Ardoz",
    "sg:orig_category":"Trabajos De Soldaduras",
    "sg:phone":"+34 916 75 18 92",
    "sg:postcode":"28850",
    "sg:province":"Madrid",
    "wof:name":"Carmona Alonso Antonio",
    "wof:placetype":"venue"
},
  "geometry": {"coordinates":[-3.4538218975,40.4530029297],"type":"Point"}
}