{
  "type": "Feature",
  "properties": {
    "iso:country":"ES",
    "sg:address":"San Vicente, S/n",
    "sg:city":"San Vicente",
    "sg:orig_category":"Pizzer\u00cdas",
    "sg:phone":"+34 988 30 75 56",
    "sg:postcode":"32348",
    "sg:province":"Ourense",
    "wof:name":"Pizarras Gallegas S.a.",
    "wof:placetype":"venue"
},
  "geometry": {"coordinates":[-7.9335141182,42.1119728088],"type":"Point"}
}