{
  "type": "Feature",
  "properties": {
    "iso:country":"ES",
    "sg:address":"Carr Roger De Lluria, 5",
    "sg:city":"Platja D'aro",
    "sg:orig_category":"Promotores Constructores",
    "sg:phone":"+34 972 82 67 06",
    "sg:postcode":"17250",
    "sg:province":"Girona",
    "wof:name":"Constructora Illes Medes S.a.",
    "wof:placetype":"venue"
},
  "geometry": {"coordinates":[2.8187398911,41.9808616638],"type":"Point"}
}