{
  "type": "Feature",
  "properties": {
    "addr:full":"Calle de Olaguibel, 1 Vitoria-gasteiz \u00c1lava 01001",
    "addr:housenumber":"1",
    "addr:postcode":"01001",
    "addr:street":"Calle De Olaguibel",
    "iso:country":"ES",
    "sg:address":"Calle de Olaguibel, 1",
    "sg:city":"Vitoria-gasteiz",
    "sg:orig_category":"Electricidad: Equipos Industriales, Componentes (fabricaci\u00d3n)",
    "sg:phone":"+34 945 25 31 84",
    "sg:postcode":"01001",
    "sg:province":"\u00c1lava",
    "wof:name":"Rohde & Schwarz Espana S.a.",
    "wof:placetype":"venue"
},
  "geometry": {"coordinates":[-2.6710090637,42.8464889526],"type":"Point"}
}