{
  "type": "Feature",
  "properties": {
    "iso:country":"ES",
    "sg:address":"Carrer de Sant Agusti (de), 7",
    "sg:city":"Tarragona",
    "sg:orig_category":"Complementos De Vestir (al Por Menor)",
    "sg:phone":"+34 977 23 91 41",
    "sg:postcode":"43003",
    "sg:province":"Tarragona",
    "wof:name":"Masip Bastida Jordi",
    "wof:placetype":"venue"
},
  "geometry": {"coordinates":[1.2550820112,41.1158943176],"type":"Point"}
}