{
  "type": "Feature",
  "properties": {
    "iso:country":"ES",
    "sg:address":"Calle de Coso Alto, 7",
    "sg:city":"Huesca",
    "sg:orig_category":"Bisuter\u00cda, Joyer\u00cda, Relojer\u00cda (al Por Menor)",
    "sg:phone":"+34 974 22 80 62",
    "sg:postcode":"22003",
    "sg:province":"Huesca",
    "wof:name":"Sanchez Penilla Elena Elisa",
    "wof:placetype":"venue"
},
  "geometry": {"coordinates":[-0.4092789888,42.1376800537],"type":"Point"}
}