{
  "type": "Feature",
  "properties": {
    "iso:country":"ES",
    "sg:address":"Calle de Campo Real, 6",
    "sg:city":"Alcala Henares",
    "sg:orig_category":"Frutas Y Legumbres Frescas (al Por Mayor)",
    "sg:phone":"+34 918 80 25 87",
    "sg:postcode":"28806",
    "sg:province":"Madrid",
    "wof:name":"Frusana S.l.",
    "wof:placetype":"venue"
},
  "geometry": {"coordinates":[-3.378390789,40.4949569702],"type":"Point"}
}