{
  "type": "Feature",
  "properties": {
    "addr:full":"Carrer de Palencia, 9 Barcelona Barcelona 08027",
    "addr:housenumber":"9",
    "addr:postcode":"08027",
    "addr:street":"Carrer De Palencia",
    "iso:country":"ES",
    "sg:address":"Carrer de Palencia, 9",
    "sg:city":"Barcelona",
    "sg:orig_category":"Florister\u00cdas",
    "sg:phone":"+34 933 40 98 75",
    "sg:postcode":"08027",
    "sg:province":"Barcelona",
    "wof:name":"Manzano Garcia Andres",
    "wof:placetype":"venue"
},
  "geometry": {"coordinates":[2.1880047321,41.4163322449],"type":"Point"}
}