{
  "type": "Feature",
  "properties": {
    "iso:country":"ES",
    "sg:address":"Carrer de Reina Esclarmunda, 4",
    "sg:city":"Palma",
    "sg:orig_category":"Bisuter\u00cda, Joyer\u00cda, Relojer\u00cda (al Por Menor)",
    "sg:phone":"+34 971 71 09 07",
    "sg:postcode":"07003",
    "sg:province":"Islas Baleares",
    "wof:name":"Forteza Pomar Jose Luis",
    "wof:placetype":"venue"
},
  "geometry": {"coordinates":[2.6517119408,39.5764808655],"type":"Point"}
}