{
  "type": "Feature",
  "properties": {
    "addr:full":"Calle de Pilar, 1 Fuente Maestre Badajoz 06360",
    "addr:postcode":"06360",
    "addr:street":"Calle De Pilar;Fuente",
    "iso:country":"ES",
    "sg:address":"Calle de Pilar, 1",
    "sg:city":"Fuente Maestre",
    "sg:orig_category":"Venta, Instalaci\u00d3n De Calefacci\u00d3n",
    "sg:phone":"+34 924 53 04 37",
    "sg:postcode":"06360",
    "sg:province":"Badajoz",
    "wof:name":"Electrodomesticos La Flor C.b",
    "wof:placetype":"venue"
},
  "geometry": {"coordinates":[-6.4479489326,38.5259208679],"type":"Point"}
}