{
  "type": "Feature",
  "properties": {
    "addr:full":"Pg Ter, 36 Manlleu Barcelona 08560",
    "addr:housenumber":"36",
    "addr:postcode":"08560",
    "addr:street":"Pg Ter",
    "iso:country":"ES",
    "sg:address":"Pg Ter, 36",
    "sg:city":"Manlleu",
    "sg:orig_category":"Albergues",
    "sg:phone":"+34 938 51 01 10",
    "sg:postcode":"08560",
    "sg:province":"Barcelona",
    "wof:name":"Bola-bola Aromatics S.l.",
    "wof:placetype":"venue"
},
  "geometry": {"coordinates":[2.2836229801,41.9975662231],"type":"Point"}
}