{
  "type": "Feature",
  "properties": {
    "iso:country":"ES",
    "sg:address":"Rbla Badal, 40",
    "sg:city":"Barcelona",
    "sg:orig_category":"Reposter\u00cdas",
    "sg:phone":"+34 934 32 36 98",
    "sg:postcode":"08014",
    "sg:province":"Barcelona",
    "wof:name":"Sanchez-crespo Galan Josefa",
    "wof:placetype":"venue"
},
  "geometry": {"coordinates":[2.1346330643,41.3668403625],"type":"Point"}
}