{
  "type": "Feature",
  "properties": {
    "addr:full":"Cami Can Pepet, 23 Can Gonteres Barcelona 08225",
    "addr:housenumber":"23",
    "addr:postcode":"08225",
    "addr:street":"Can",
    "iso:country":"ES",
    "sg:address":"Cami Can Pepet, 23",
    "sg:city":"Can Gonteres",
    "sg:orig_category":"Inform\u00c1tica (estudios, Servicios, Asesor\u00cda, Formaci\u00d3n)",
    "sg:phone":"+34 937 33 00 64",
    "sg:postcode":"08225",
    "sg:province":"Barcelona",
    "wof:name":"Assessoria Informatica Meneses S.l.",
    "wof:placetype":"venue"
},
  "geometry": {"coordinates":[1.9818294048,41.5743560791],"type":"Point"}
}