{
  "type": "Feature",
  "properties": {
    "iso:country":"ES",
    "sg:address":"Calle de Sevilla, 26",
    "sg:city":"Jodar",
    "sg:orig_category":"Mec\u00c1nico Del Autom\u00d3vil",
    "sg:phone":"+34 953 78 69 06",
    "sg:postcode":"23500",
    "sg:province":"Ja\u00e9n",
    "wof:name":"Vilches Herrera Marco Jose",
    "wof:placetype":"venue"
},
  "geometry": {"coordinates":[-3.3544769287,37.8387145996],"type":"Point"}
}