{
  "type": "Feature",
  "properties": {
    "addr:full":"Calle de Caballero De Rodas, 75 Torrevieja Alicante 03180",
    "addr:housenumber":"75",
    "addr:postcode":"03180",
    "addr:street":"Calle De Caballero De Rodas",
    "iso:country":"ES",
    "sg:address":"Calle de Caballero De Rodas, 75",
    "sg:city":"Torrevieja",
    "sg:orig_category":"Informaci\u00d3n Financiera Y Comercial",
    "sg:phone":"+34 965 71 94 55",
    "sg:postcode":"03180",
    "sg:province":"Alicante",
    "wof:name":"Gestoria Casblanca S.l.",
    "wof:placetype":"venue"
},
  "geometry": {"coordinates":[-0.6795735955,37.9779853821],"type":"Point"}
}