{
  "type": "Feature",
  "properties": {
    "addr:full":"Calle de Moradas, 25 Valladolid Valladolid 47010",
    "addr:housenumber":"25",
    "addr:postcode":"47010",
    "addr:street":"Calle De Moradas",
    "iso:country":"ES",
    "sg:address":"Calle de Moradas, 25",
    "sg:city":"Valladolid",
    "sg:orig_category":"Reposter\u00cdas",
    "sg:phone":"+34 983 25 02 09",
    "sg:postcode":"47010",
    "sg:province":"Valladolid",
    "wof:name":"Robles Martin Milagros",
    "wof:placetype":"venue"
},
  "geometry": {"coordinates":[-4.7213120461,41.6617851257],"type":"Point"}
}