{
  "type": "Feature",
  "properties": {
    "iso:country":"ES",
    "sg:address":"Avda Madrid, 114",
    "sg:city":"Zaragoza",
    "sg:orig_category":"Lencer\u00cda Femenina, Corseter\u00cda, Trajes De Ba\u00d1o (al Por Menor)",
    "sg:phone":"+34 976 53 70 24",
    "sg:postcode":"50010",
    "sg:province":"Zaragoza",
    "wof:name":"Ceartex S.l.",
    "wof:placetype":"venue"
},
  "geometry": {"coordinates":[-0.9083480239,41.6526679993],"type":"Point"}
}