{
  "type": "Feature",
  "properties": {
    "iso:country":"ES",
    "sg:address":"Rua Ourense, S/n",
    "sg:city":"Cerdedo",
    "sg:orig_category":"Iglesia Cat\u00d3lica",
    "sg:phone":"+34 986 75 30 09",
    "sg:postcode":"36130",
    "sg:province":"Pontevedra",
    "wof:name":"Parroquia De San Juan",
    "wof:placetype":"venue"
},
  "geometry": {"coordinates":[-8.3890485764,42.5323982239],"type":"Point"}
}