{
  "type": "Feature",
  "properties": {
    "iso:country":"ES",
    "sg:address":"Avda Lugo, 1",
    "sg:city":"Cangas",
    "sg:orig_category":"Ba\u00d1os Y Duchas P\u00dablicos",
    "sg:phone":"+34 986 30 23 00",
    "sg:postcode":"36940",
    "sg:province":"Pontevedra",
    "sg:website":"www.acuagym.net",
    "wof:name":"Acua Gym C.b.",
    "wof:placetype":"venue"
},
  "geometry": {"coordinates":[-8.7857160568,42.2675132751],"type":"Point"}
}