{
  "type": "Feature",
  "properties": {
    "iso:country":"ES",
    "sg:address":"Rio Lobos, Ctra., S/n",
    "sg:city":"Galisteo",
    "sg:orig_category":"Autob\u00das (explotaci\u00d3n Y Servicios De)",
    "sg:phone":"+34 927 45 24 03",
    "sg:postcode":"10691",
    "sg:province":"C\u00e1ceres",
    "wof:name":"Autocares Eleno S.l.",
    "wof:placetype":"venue"
},
  "geometry": {"coordinates":[-6.2670040131,39.9761581421],"type":"Point"}
}