{
  "type": "Feature",
  "properties": {
    "addr:full":"Carrer de Unio, 17 Barcelona Barcelona 08001",
    "addr:housenumber":"17",
    "addr:postcode":"08001",
    "addr:street":"Carrer De Unio",
    "iso:country":"ES",
    "sg:address":"Carrer de Unio, 17",
    "sg:city":"Barcelona",
    "sg:orig_category":"Alimentaci\u00d3n General (al Por Menor)",
    "sg:phone":"+34 933 18 66 40",
    "sg:postcode":"08001",
    "sg:province":"Barcelona",
    "wof:name":"Viure Espinasa Ramon",
    "wof:placetype":"venue"
},
  "geometry": {"coordinates":[2.1730821133,41.3792037964],"type":"Point"}
}