{
  "type": "Feature",
  "properties": {
    "iso:country":"ES",
    "sg:address":"Calle de Fernando Remacha, 2",
    "sg:city":"Tudela",
    "sg:orig_category":"Fabricaci\u00d3n, Importaci\u00d3n, Venta De Material De Telefon\u00cda, Peritelefon\u00cda",
    "sg:phone":"+34 948 82 24 11",
    "sg:postcode":"31500",
    "sg:province":"Navarra",
    "wof:name":"Compa\u00d1ia De Telefonia De Aragon Sl",
    "wof:placetype":"venue"
},
  "geometry": {"coordinates":[-1.6009379625,42.0601615906],"type":"Point"}
}