{
  "type": "Feature",
  "properties": {
    "addr:full":"Cmno Vilecha, S/n Le\u00f3n Le\u00f3n 24009",
    "addr:housenumber":"s",
    "addr:postcode":"24009",
    "addr:street":"Cmno Vilecha;/ N Leo\u0301N Leo\u0301N",
    "iso:country":"ES",
    "sg:address":"Cmno Vilecha, S/n",
    "sg:city":"Le\u00f3n",
    "sg:orig_category":"Pescader\u00cdas (al Por Menor)",
    "sg:phone":"+34 987 26 18 45",
    "sg:postcode":"24009",
    "sg:province":"Le\u00f3n",
    "wof:name":"Pescallor S.l.",
    "wof:placetype":"venue"
},
  "geometry": {"coordinates":[-5.6094388962,42.5985641479],"type":"Point"}
}