{
  "type": "Feature",
  "properties": {
    "iso:country":"ES",
    "sg:address":"Calle de Alferez Jose Morente, 2",
    "sg:city":"Porcuna",
    "sg:orig_category":"Imprenta",
    "sg:phone":"+34 953 54 48 85",
    "sg:postcode":"23790",
    "sg:province":"Ja\u00e9n",
    "wof:name":"Puentes Palomares Juan",
    "wof:placetype":"venue"
},
  "geometry": {"coordinates":[-4.1872849464,37.8717308044],"type":"Point"}
}