{
  "type": "Feature",
  "properties": {
    "addr:full":"Calle de Alferez Jose Morente, 2 Porcuna Ja\u00e9n 23790",
    "addr:housenumber":"2",
    "addr:postcode":"23790",
    "addr:street":"Calle De Alferez Jose Morente",
    "iso:country":"ES",
    "sg:address":"Calle de Alferez Jose Morente, 2",
    "sg:city":"Porcuna",
    "sg:orig_category":"Imprenta",
    "sg:phone":"+34 953 54 48 85",
    "sg:postcode":"23790",
    "sg:province":"Ja\u00e9n",
    "wof:name":"Puentes Palomares Juan",
    "wof:placetype":"venue"
},
  "geometry": {"coordinates":[-4.1872849464,37.8717308044],"type":"Point"}
}