{
  "type": "Feature",
  "properties": {
    "iso:country":"ES",
    "sg:address":"Carrer de Kepler, 34",
    "sg:city":"Rubi",
    "sg:orig_category":"Agencias Y Agentes Comerciales, Representantes",
    "sg:phone":"+34 936 99 82 70",
    "sg:postcode":"08191",
    "sg:province":"Barcelona",
    "wof:name":"Bilbao Diego Francisco Javier",
    "wof:placetype":"venue"
},
  "geometry": {"coordinates":[2.0421159267,41.4908370972],"type":"Point"}
}