{
  "type": "Feature",
  "properties": {
    "addr:full":"Av. Barcelona, Km. 0009,2 Museros Valencia 46136",
    "addr:postcode":"46136",
    "addr:street":"Av. Barcelona Km. 0009,2",
    "iso:country":"ES",
    "sg:address":"Av. Barcelona, Km. 0009,2",
    "sg:city":"Museros",
    "sg:orig_category":"Agentes, Concesionarios Y Sucursales De Veh\u00cdculos",
    "sg:phone":"+34 961 45 21 01",
    "sg:postcode":"46136",
    "sg:province":"Valencia",
    "wof:name":"Automoviles Palmero S.l.",
    "wof:placetype":"venue"
},
  "geometry": {"coordinates":[-0.3402574062,39.553730011],"type":"Point"}
}