{
  "type": "Feature",
  "properties": {
    "iso:country":"ES",
    "sg:address":"Carrer de Mare Deu Dels Desemparats, 5",
    "sg:city":"Barcelona",
    "sg:orig_category":"M\u00dasica Diversa",
    "sg:phone":"+34 932 85 15 76",
    "sg:postcode":"08012",
    "sg:province":"Barcelona",
    "sg:website":"www.articulosdebaile.com",
    "wof:name":"Espacio Moda Baile Scp",
    "wof:placetype":"venue"
},
  "geometry": {"coordinates":[2.1594250202,41.4012908936],"type":"Point"}
}