{
  "type": "Feature",
  "properties": {
    "addr:full":"Calle de Cantueso, 47 Elda Alicante 03600",
    "addr:housenumber":"47",
    "addr:postcode":"03600",
    "addr:street":"Calle De Cantueso",
    "iso:country":"ES",
    "sg:address":"Calle de Cantueso, 47",
    "sg:city":"Elda",
    "sg:orig_category":"Inform\u00c1tica Equipo Y Programas (al Por Mayor)",
    "sg:phone":"+34 965 38 11 17",
    "sg:postcode":"03600",
    "sg:province":"Alicante",
    "wof:name":"Esfe Rama Software S.l.",
    "wof:placetype":"venue"
},
  "geometry": {"coordinates":[-0.7956156731,38.4929046631],"type":"Point"}
}