{
  "type": "Feature",
  "properties": {
    "iso:country":"ES",
    "sg:address":"Avda Monforte De Lemos, 145",
    "sg:city":"Madrid",
    "sg:orig_category":"Alimentaci\u00d3n General (al Por Menor)",
    "sg:phone":"+34 913 86 42 67",
    "sg:postcode":"28029",
    "sg:province":"Madrid",
    "wof:name":"Zhu  Zhuhua",
    "wof:placetype":"venue"
},
  "geometry": {"coordinates":[-3.7128648758,40.4775238037],"type":"Point"}
}