{
  "type": "Feature",
  "properties": {
    "addr:full":"Pase Espolon, 30 Burgos Burgos 09003",
    "addr:housenumber":"30",
    "addr:postcode":"09003",
    "addr:street":"Espolon",
    "iso:country":"ES",
    "sg:address":"Pase Espolon, 30",
    "sg:city":"Burgos",
    "sg:orig_category":"Estancos",
    "sg:phone":"+34 947 27 79 49",
    "sg:postcode":"09003",
    "sg:province":"Burgos",
    "wof:name":"Miguel Garcia Angeles",
    "wof:placetype":"venue"
},
  "geometry": {"coordinates":[-3.702092886,42.3402862549],"type":"Point"}
}