{
  "type": "Feature",
  "properties": {
    "iso:country":"ES",
    "sg:address":"Calle de Zamora, 63",
    "sg:city":"Salamanca",
    "sg:orig_category":"Librer\u00cdas",
    "sg:phone":"+34 923 21 28 78",
    "sg:postcode":"37002",
    "sg:province":"Salamanca",
    "wof:name":"Delgado Ruano Jose Luis",
    "wof:placetype":"venue"
},
  "geometry": {"coordinates":[-5.6639018059,40.9688568115],"type":"Point"}
}