{
  "type": "Feature",
  "properties": {
    "addr:full":"Calle de Jaudenes, 10 Ceuta Ceuta 51001",
    "addr:housenumber":"10",
    "addr:postcode":"51001",
    "addr:street":"Calle De Jaudenes",
    "iso:country":"ES",
    "sg:address":"Calle de Jaudenes, 10",
    "sg:city":"Ceuta",
    "sg:orig_category":"Art\u00cdculos De Regalo (al Por Menor)",
    "sg:phone":"+34 956 51 10 39",
    "sg:postcode":"51001",
    "sg:province":"Ceuta",
    "wof:name":"Teodoro Garcia Maria Rosa",
    "wof:placetype":"venue"
},
  "geometry": {"coordinates":[-5.3146429062,35.8873977661],"type":"Point"}
}