{
  "type": "Feature",
  "properties": {
    "addr:full":"Calle de Sagasta, 32 Madrid Madrid 28004",
    "addr:housenumber":"32",
    "addr:postcode":"madrid;28004",
    "addr:street":"Calle De Sagasta",
    "iso:country":"ES",
    "sg:address":"Calle de Sagasta, 32",
    "sg:city":"Madrid",
    "sg:orig_category":"Administradores De Bienes Y Delegados De Comunidades De Propietarios",
    "sg:phone":"+34 914 46 51 28",
    "sg:postcode":"28004",
    "sg:province":"Madrid",
    "wof:name":"Servicio Y Estudios De La Propiedad",
    "wof:placetype":"venue"
},
  "geometry": {"coordinates":[-3.6968729496,40.4277648926],"type":"Point"}
}