{
  "type": "Feature",
  "properties": {
    "addr:full":"Madeixes, 7 Ontinyent Valencia 46870",
    "addr:housenumber":"7",
    "addr:postcode":"46870",
    "addr:street":"Madeixes",
    "iso:country":"ES",
    "sg:address":"Madeixes, 7",
    "sg:city":"Ontinyent",
    "sg:orig_category":"Fabricaci\u00d3n De Productos Textiles Sin Tejer",
    "sg:phone":"+34 962 91 40 60",
    "sg:postcode":"46870",
    "sg:province":"Valencia",
    "wof:name":"Bordera Teixits S.l.",
    "wof:placetype":"venue"
},
  "geometry": {"coordinates":[-0.5867760181,38.826675415],"type":"Point"}
}