{
  "type": "Feature",
  "properties": {
    "addr:full":"Po. Inmaculada, 21 Estella Navarra 31200",
    "addr:housenumber":"21",
    "addr:postcode":"31200",
    "iso:country":"ES",
    "sg:address":"Po. Inmaculada, 21",
    "sg:city":"Estella",
    "sg:orig_category":"Florister\u00cdas",
    "sg:phone":"+34 948 55 26 24",
    "sg:postcode":"31200",
    "sg:province":"Navarra",
    "wof:name":"Ajona Barandalla Francisco Javier",
    "wof:placetype":"venue"
},
  "geometry": {"coordinates":[-2.02242136,42.6653747559],"type":"Point"}
}