{
  "type": "Feature",
  "properties": {
    "iso:country":"ES",
    "sg:address":"Calle de Nieto Bonal, 11",
    "sg:city":"Salamanca",
    "sg:orig_category":"Mec\u00c1nico Del Autom\u00d3vil",
    "sg:phone":"+34 923 22 73 43",
    "sg:postcode":"37007",
    "sg:province":"Salamanca",
    "wof:name":"Garcia Burgos Dimas",
    "wof:placetype":"venue"
},
  "geometry": {"coordinates":[-5.6681728363,40.9706001282],"type":"Point"}
}