{
  "type": "Feature",
  "properties": {
    "addr:full":"Calle de San Lorenzo, 5 Jerez De Los Caballeros Badajoz 06380",
    "addr:housenumber":"5",
    "addr:postcode":"06380",
    "addr:street":"Calle De San Lorenzo",
    "iso:country":"ES",
    "sg:address":"Calle de San Lorenzo, 5",
    "sg:city":"Jerez De Los Caballeros",
    "sg:orig_category":"Zapatos (al Por Menor)",
    "sg:phone":"+34 924 75 11 71",
    "sg:postcode":"06380",
    "sg:province":"Badajoz",
    "wof:name":"Sanchez Escudero Manuel",
    "wof:placetype":"venue"
},
  "geometry": {"coordinates":[-6.7787928581,38.3176422119],"type":"Point"}
}