{
  "type": "Feature",
  "properties": {
    "iso:country":"ES",
    "sg:address":"Carrer de Consell De Cent, 100",
    "sg:city":"Barcelona",
    "sg:orig_category":"Pesca Y Caza: Art\u00cdculos (al Por Menor)",
    "sg:phone":"+34 934 23 39 67",
    "sg:postcode":"08015",
    "sg:province":"Barcelona",
    "wof:name":"Paris Zulueta Carlos",
    "wof:placetype":"venue"
},
  "geometry": {"coordinates":[2.1515610218,41.3802604675],"type":"Point"}
}