{
  "type": "Feature",
  "properties": {
    "iso:country":"ES",
    "sg:address":"Cercado, 19",
    "sg:city":"Tias",
    "sg:orig_category":"Inmobiliaria (agencias)",
    "sg:phone":"+34 928 51 52 38",
    "sg:postcode":"35572",
    "sg:province":"Las Palmas",
    "wof:name":"Tara European Property Consultants S.l.",
    "wof:placetype":"venue"
},
  "geometry": {"coordinates":[-13.6521291733,28.9543895721],"type":"Point"}
}