{
  "type": "Feature",
  "properties": {
    "addr:full":"Carrer de Lluis Marti, 127 Palma Islas Baleares 07007",
    "addr:housenumber":"127",
    "addr:postcode":"07007",
    "addr:street":"Carrer De Lluis Marti",
    "iso:country":"ES",
    "sg:address":"Carrer de Lluis Marti, 127",
    "sg:city":"Palma",
    "sg:orig_category":"Papeler\u00cdas, Librer\u00cdas",
    "sg:phone":"+34 971 24 41 33",
    "sg:postcode":"07007",
    "sg:province":"Islas Baleares",
    "wof:name":"Escamdell Mari Maria Del Carmen",
    "wof:placetype":"venue"
},
  "geometry": {"coordinates":[2.6680688858,39.5723266602],"type":"Point"}
}