{
  "type": "Feature",
  "properties": {
    "addr:full":"Avgd Prat De La Riba, 3 Lleida Lleida 25...",
    "addr:housenumber":"3;25 ...",
    "addr:street":"La Riba;Lleida",
    "iso:country":"ES",
    "sg:address":"Avgd Prat De La Riba, 3",
    "sg:city":"Lleida",
    "sg:orig_category":"Seguridad Social",
    "sg:phone":"+34 973 70 07 00",
    "sg:postcode":"25...",
    "sg:province":"Lleida",
    "wof:name":"Instituto Nacional De La Seguridad Social-direccion Provincial De Lerida",
    "wof:placetype":"venue"
},
  "geometry": {"coordinates":[0.6200709939,41.6196327209],"type":"Point"}
}