{
  "type": "Feature",
  "properties": {
    "addr:full":"Carrer de Santiago Rusi\u00d1ol, 56 Reus Tarragona 43206",
    "addr:housenumber":"56",
    "addr:postcode":"43206",
    "addr:street":"Carrer De Santiago Rusin\u0303Ol",
    "iso:country":"ES",
    "sg:address":"Carrer de Santiago Rusi\u00d1ol, 56",
    "sg:city":"Reus",
    "sg:orig_category":"Charcuter\u00cdas (al Por Mayor)",
    "sg:phone":"+34 977 32 81 27",
    "sg:postcode":"43206",
    "sg:province":"Tarragona",
    "wof:name":"Criven S.a.",
    "wof:placetype":"venue"
},
  "geometry": {"coordinates":[1.1039400101,41.1745300293],"type":"Point"}
}