{
  "type": "Feature",
  "properties": {
    "iso:country":"ES",
    "sg:address":"Calle de Julio Palacios, 2",
    "sg:city":"Madrid",
    "sg:orig_category":"Farmacias",
    "sg:phone":"+34 917 33 72 31",
    "sg:postcode":"28029",
    "sg:province":"Madrid",
    "wof:name":"Hijazo Ugarte Edurne",
    "wof:placetype":"venue"
},
  "geometry": {"coordinates":[-3.6935710907,40.482585907],"type":"Point"}
}