{
  "type": "Feature",
  "properties": {
    "addr:full":"Carrer de Mateu Enric Llado, 34 Palma Islas Baleares 07002",
    "addr:housenumber":"34",
    "addr:postcode":"07002",
    "addr:street":"Carrer De Mateu Enric Llado",
    "iso:country":"ES",
    "sg:address":"Carrer de Mateu Enric Llado, 34",
    "sg:city":"Palma",
    "sg:orig_category":"Prot\u00c9sicos Dentales",
    "sg:phone":"+34 971 71 65 95",
    "sg:postcode":"07002",
    "sg:province":"Islas Baleares",
    "wof:name":"Corro Galan Juan Francisco",
    "wof:placetype":"venue"
},
  "geometry": {"coordinates":[2.655944109,39.5681991577],"type":"Point"}
}