{
  "type": "Feature",
  "properties": {
    "iso:country":"ES",
    "sg:address":"Avda Industria (de La), 26",
    "sg:city":"Tres Cantos",
    "sg:orig_category":"Agencias De Viajes",
    "sg:phone":"+34 918 04 96 07",
    "sg:postcode":"28760",
    "sg:province":"Madrid",
    "sg:website":"www.viajesiberia.com",
    "wof:name":"Viajes Iberia S.a.",
    "wof:placetype":"venue"
},
  "geometry": {"coordinates":[-3.6965699196,40.6103096008],"type":"Point"}
}