{
  "type": "Feature",
  "properties": {
    "iso:country":"ES",
    "sg:address":"Avgd Navarra, 15",
    "sg:city":"Lleida",
    "sg:orig_category":"Asociaciones Humanitarias, De Cooperaci\u00d3n, De Acci\u00d3n Social",
    "sg:phone":"+34 973 24 98 47",
    "sg:postcode":"25006",
    "sg:province":"Lleida",
    "wof:name":"Asociacion De Rehabilitacion Del Minusvalido",
    "wof:placetype":"venue"
},
  "geometry": {"coordinates":[0.615996182,41.6215667725],"type":"Point"}
}