{
  "type": "Feature",
  "properties": {
    "addr:full":"Rbla Marina, 185 Hospitalet Llobregat Barcelona 08907",
    "addr:housenumber":"185",
    "addr:postcode":"08907",
    "addr:street":"Rbla Marina",
    "iso:country":"ES",
    "sg:address":"Rbla Marina, 185",
    "sg:city":"Hospitalet Llobregat",
    "sg:orig_category":"Molduras, Junquillos, Listones Y Molduras Perforadas",
    "sg:phone":"+34 933 35 92 50",
    "sg:postcode":"08907",
    "sg:province":"Barcelona",
    "wof:name":"Fernandez Lopez Armando",
    "wof:placetype":"venue"
},
  "geometry": {"coordinates":[2.1099181175,41.3503723145],"type":"Point"}
}