{
  "type": "Feature",
  "properties": {
    "iso:country":"ES",
    "sg:address":"Mcdo Mayoristas, S/n",
    "sg:city":"Velez-malaga",
    "sg:orig_category":"Frutas Y Legumbres Frescas (al Por Mayor)",
    "sg:phone":"+34 952 50 22 00",
    "sg:postcode":"29700",
    "sg:province":"M\u00e1laga",
    "wof:name":"Matifrut S.l.",
    "wof:placetype":"venue"
},
  "geometry": {"coordinates":[-4.1004362106,36.7783088684],"type":"Point"}
}