{
  "type": "Feature",
  "properties": {
    "iso:country":"ES",
    "sg:address":"Avda Florida, 86",
    "sg:city":"Vigo",
    "sg:orig_category":"Ingeniero",
    "sg:phone":"+34 986 21 24 33",
    "sg:postcode":"36210",
    "sg:province":"Pontevedra",
    "wof:name":"Alonso Davila Emilio",
    "wof:placetype":"venue"
},
  "geometry": {"coordinates":[-8.7470531464,42.2109222412],"type":"Point"}
}