{
  "type": "Feature",
  "properties": {
    "addr:full":"Escourido, S/n Covas Lugo 27861",
    "addr:housenumber":"/ n",
    "addr:postcode":"27861",
    "addr:street":"Escourido S",
    "iso:country":"ES",
    "sg:address":"Escourido, S/n",
    "sg:city":"Covas",
    "sg:orig_category":"Mec\u00c1nico Del Autom\u00d3vil",
    "sg:phone":"+34 982 56 00 99",
    "sg:postcode":"27861",
    "sg:province":"Lugo",
    "wof:name":"Hermanos Ribera S. L.",
    "wof:placetype":"venue"
},
  "geometry": {"coordinates":[-7.6583218575,43.691734314],"type":"Point"}
}