{
  "type": "Feature",
  "properties": {
    "addr:full":"Calle de Julio Caro Baroja, 22 Madrid Madrid 28050",
    "addr:housenumber":"22",
    "addr:postcode":"madrid;28050",
    "addr:street":"Calle De Julio Caro Baroja",
    "iso:country":"ES",
    "sg:address":"Calle de Julio Caro Baroja, 22",
    "sg:city":"Madrid",
    "sg:orig_category":"Parques De Atracciones Y Centros De Esparcimiento",
    "sg:phone":"+34 916 50 79 03",
    "sg:postcode":"28050",
    "sg:province":"Madrid",
    "wof:name":"Open Park S.l",
    "wof:placetype":"venue"
},
  "geometry": {"coordinates":[-3.6460459232,40.5081977844],"type":"Point"}
}