{
  "type": "Feature",
  "properties": {
    "addr:full":"Fco. Nacher Pons, 22 Massanassa Valencia 46470",
    "addr:housenumber":"22",
    "addr:postcode":"46470",
    "addr:street":"Pons",
    "iso:country":"ES",
    "sg:address":"Fco. Nacher Pons, 22",
    "sg:city":"Massanassa",
    "sg:orig_category":"M\u00c1rmoles, Granitos Y Piedras Naturales",
    "sg:phone":"+34 961 25 02 08",
    "sg:postcode":"46470",
    "sg:province":"Valencia",
    "wof:name":"Corbi Minuesa Juan",
    "wof:placetype":"venue"
},
  "geometry": {"coordinates":[-0.3955030143,39.4099464417],"type":"Point"}
}