{
  "type": "Feature",
  "properties": {
    "addr:full":"Ctra. Vilafranca, Km. 0001,0 Porreres Islas Baleares 07260",
    "addr:postcode":"07260",
    "addr:street":"Ctra. Vilafranca Km. 0001,0",
    "iso:country":"ES",
    "sg:address":"Ctra. Vilafranca, Km. 0001,0",
    "sg:city":"Porreres",
    "sg:orig_category":"Producci\u00d3n, Venta De Productos De Agricultura Biol\u00d3gica",
    "sg:phone":"+34 971 16 66 06",
    "sg:postcode":"07260",
    "sg:province":"Islas Baleares",
    "wof:name":"Productors Illencs De Lactis Sat",
    "wof:placetype":"venue"
},
  "geometry": {"coordinates":[3.0226650238,39.5170059204],"type":"Point"}
}