{
  "type": "Feature",
  "properties": {
    "addr:full":"Barr Iurre Auzunea, 4 San Blas Guip\u00f9zcoa 20400",
    "addr:housenumber":"4",
    "addr:postcode":"20400",
    "addr:street":"Iurre Auzunea",
    "iso:country":"ES",
    "sg:address":"Barr Iurre Auzunea, 4",
    "sg:city":"San Blas",
    "sg:orig_category":"Electrodom\u00c9sticos (al Por Menor)",
    "sg:phone":"+34 943 67 03 23",
    "sg:postcode":"20400",
    "sg:province":"Guip\u00f9zcoa",
    "wof:name":"Silvestre Dominguez Guinaldo Y Otro C.b.",
    "wof:placetype":"venue"
},
  "geometry": {"coordinates":[-2.0789339542,43.1339912415],"type":"Point"}
}