{
  "type": "Feature",
  "properties": {
    "addr:full":"Calle de Rio Jarama (de), 38 Humanes De Madrid Madrid 28970",
    "addr:housenumber":"38",
    "addr:postcode":"28970",
    "addr:street":"Calle De Rio Jarama De",
    "iso:country":"ES",
    "sg:address":"Calle de Rio Jarama (de), 38",
    "sg:city":"Humanes De Madrid",
    "sg:orig_category":"Imprenta",
    "sg:phone":"+34 916 04 87 72",
    "sg:postcode":"28970",
    "sg:province":"Madrid",
    "wof:name":"Papeleria Imprenta De Diego S.l",
    "wof:placetype":"venue"
},
  "geometry": {"coordinates":[-3.8118479252,40.2641487122],"type":"Point"}
}