{
  "type": "Feature",
  "properties": {
    "addr:full":"Pase Ronda, 5 Coru\u00d1a La Coru\u00f1a 15011",
    "addr:housenumber":"5",
    "addr:postcode":"15011",
    "addr:street":"Ronda;La Corun\u0303A",
    "iso:country":"ES",
    "sg:address":"Pase Ronda, 5",
    "sg:city":"Coru\u00d1a",
    "sg:orig_category":"Bancos",
    "sg:phone":"+34 981 25 22 07",
    "sg:postcode":"15011",
    "sg:province":"La Coru\u00f1a",
    "wof:name":"Banco Vitalicio De Espa\u00f1a C.a.",
    "wof:placetype":"venue"
},
  "geometry": {"coordinates":[-8.416478157,43.3702545166],"type":"Point"}
}