{
  "type": "Feature",
  "properties": {
    "addr:full":"Rua Rio Salas, 29 Ourense Ourense 32001",
    "addr:postcode":"32001",
    "addr:street":"Rua;Salas",
    "iso:country":"ES",
    "sg:address":"Rua Rio Salas, 29",
    "sg:city":"Ourense",
    "sg:orig_category":"Mayoristas E Intermediarios En Alcoholes",
    "sg:phone":"+34 988 37 37 39",
    "sg:postcode":"32001",
    "sg:province":"Ourense",
    "wof:name":"Suminor 98 S.l.",
    "wof:placetype":"venue"
},
  "geometry": {"coordinates":[-7.8694720268,42.3547668457],"type":"Point"}
}