{
  "type": "Feature",
  "properties": {
    "iso:country":"ES",
    "sg:address":"Avda Pablo Neruda, 6",
    "sg:city":"Madrid",
    "sg:orig_category":"Caf\u00c9s, Bares, Cervecer\u00cdas",
    "sg:phone":"+34 917 77 32 35",
    "sg:postcode":"28038",
    "sg:province":"Madrid",
    "wof:name":"Castro Baena Jose",
    "wof:placetype":"venue"
},
  "geometry": {"coordinates":[-3.6403419971,40.3943862915],"type":"Point"}
}