{
  "type": "Feature",
  "properties": {
    "addr:full":"Carrer de Cirerer, 2 Can Carreras Barcelona 08415",
    "addr:housenumber":"2",
    "addr:postcode":"08415",
    "addr:street":"Carrer De Cirerer",
    "iso:country":"ES",
    "sg:address":"Carrer de Cirerer, 2",
    "sg:city":"Can Carreras",
    "sg:orig_category":"Escayola Y Productos De Escayola (fabricaci\u00d3n, Al Por Mayor)",
    "sg:phone":"+34 938 65 60 59",
    "sg:postcode":"08415",
    "sg:province":"Barcelona",
    "wof:name":"Merino Garcia Jose Maria",
    "wof:placetype":"venue"
},
  "geometry": {"coordinates":[2.1977660656,41.6689872742],"type":"Point"}
}