{
  "type": "Feature",
  "properties": {
    "addr:full":"Carrer de Treball, 25 Hospitalet Llobregat Barcelona 08901",
    "addr:housenumber":"25",
    "addr:postcode":"08901",
    "addr:street":"Carrer De Treball",
    "iso:country":"ES",
    "sg:address":"Carrer de Treball, 25",
    "sg:city":"Hospitalet Llobregat",
    "sg:orig_category":"Reposter\u00cdas",
    "sg:phone":"+34 933 37 43 01",
    "sg:postcode":"08901",
    "sg:province":"Barcelona",
    "wof:name":"Panificadora Camps Costa S. A.",
    "wof:placetype":"venue"
},
  "geometry": {"coordinates":[2.1171309948,41.3672027588],"type":"Point"}
}