{
  "type": "Feature",
  "properties": {
    "addr:full":"Avda Europa, 27 Guardamar Segura Alicante 03140",
    "addr:housenumber":"27",
    "addr:postcode":"03140",
    "addr:street":"Avda Europa",
    "iso:country":"ES",
    "sg:address":"Avda Europa, 27",
    "sg:city":"Guardamar Segura",
    "sg:orig_category":"Librer\u00cdas",
    "sg:phone":"+34 966 72 61 20",
    "sg:postcode":"03140",
    "sg:province":"Alicante",
    "wof:name":"Perez Ferrer Maria Jose",
    "wof:placetype":"venue"
},
  "geometry": {"coordinates":[-0.6540290117,38.086681366],"type":"Point"}
}