{
  "type": "Feature",
  "properties": {
    "addr:full":"Calle de Estacion, S/n Almanzora Almer\u00eda 04815",
    "addr:postcode":"04815",
    "addr:street":"Calle De Estacion S / N Almanzora Almeri\u0301A",
    "iso:country":"ES",
    "sg:address":"Calle de Estacion, S/n",
    "sg:city":"Almanzora",
    "sg:orig_category":"Cajas Para Embalar",
    "sg:phone":"+34 950 43 10 51",
    "sg:postcode":"04815",
    "sg:province":"Almer\u00eda",
    "wof:name":"Cajamar",
    "wof:placetype":"venue"
},
  "geometry": {"coordinates":[-2.136138916,37.347694397],"type":"Point"}
}