{
  "type": "Feature",
  "properties": {
    "addr:full":"Avda Canillejas A Vicalvaro, 135 Madrid Madrid 28022",
    "addr:housenumber":"135",
    "addr:postcode":"28022",
    "addr:street":"Avda Canillejas A Vicalvaro",
    "iso:country":"ES",
    "sg:address":"Avda Canillejas A Vicalvaro, 135",
    "sg:city":"Madrid",
    "sg:orig_category":"Empresarios",
    "sg:phone":"+34 913 13 02 62",
    "sg:postcode":"28022",
    "sg:province":"Madrid",
    "wof:name":"Fundacion Federico Fliedner",
    "wof:placetype":"venue"
},
  "geometry": {"coordinates":[-3.6112658978,40.4264144897],"type":"Point"}
}