{
  "type": "Feature",
  "properties": {
    "addr:full":"Calle de Miguel Hernandez, 8 Cullar-vega Granada 18195",
    "addr:housenumber":"8",
    "addr:postcode":"18195",
    "addr:street":"Calle De Miguel Hernandez",
    "iso:country":"ES",
    "sg:address":"Calle de Miguel Hernandez, 8",
    "sg:city":"Cullar-vega",
    "sg:orig_category":"Electrodom\u00c9sticos (al Por Menor)",
    "sg:phone":"+34 958 58 59 03",
    "sg:postcode":"18195",
    "sg:province":"Granada",
    "wof:name":"Jimenez Urbano Gabriel",
    "wof:placetype":"venue"
},
  "geometry": {"coordinates":[-3.6625890732,37.1629104614],"type":"Point"}
}