{
  "type": "Feature",
  "properties": {
    "iso:country":"ES",
    "sg:address":"Ctra Alicante-cartagena, 347",
    "sg:city":"Marina",
    "sg:orig_category":"Comerciantes Al Por Mayor De Vinos, Licores Y Alcoholes",
    "sg:phone":"+34 965 41 91 11",
    "sg:postcode":"03194",
    "sg:province":"Alicante",
    "wof:name":"Macia Amoros Juan Carmelo",
    "wof:placetype":"venue"
},
  "geometry": {"coordinates":[-0.4804700017,38.3440818787],"type":"Point"}
}