{
  "type": "Feature",
  "properties": {
    "addr:full":"Calle de Iglesia (la), 37 Horche Guadalajara 19140",
    "addr:housenumber":"37",
    "addr:postcode":"19140",
    "addr:street":"Calle De Iglesia La",
    "iso:country":"ES",
    "sg:address":"Calle de Iglesia (la), 37",
    "sg:city":"Horche",
    "sg:orig_category":"Peluqueros: De Se\u00d1oras",
    "sg:phone":"+34 949 29 10 27",
    "sg:postcode":"19140",
    "sg:province":"Guadalajara",
    "wof:name":"Fernandez Martinez Maia Antonina",
    "wof:placetype":"venue"
},
  "geometry": {"coordinates":[-3.0627150536,40.5659255981],"type":"Point"}
}