{
  "type": "Feature",
  "properties": {
    "addr:full":"Calle de Prebendado Pacheco, 4 Tegueste Casco Santa Cruz De Tenerife 38280",
    "addr:housenumber":"4",
    "addr:postcode":"38280",
    "addr:street":"Calle De Prebendado Pacheco",
    "iso:country":"ES",
    "sg:address":"Calle de Prebendado Pacheco, 4",
    "sg:city":"Tegueste Casco",
    "sg:orig_category":"Ropa Para Se\u00d1oras Y Caballeros (al Por Menor)",
    "sg:phone":"+34 922 54 09 16",
    "sg:postcode":"38280",
    "sg:province":"Santa Cruz De Tenerife",
    "wof:name":"C B Tentacion Macarena S L U",
    "wof:placetype":"venue"
},
  "geometry": {"coordinates":[-16.3369026184,28.5226173401],"type":"Point"}
}