{
  "type": "Feature",
  "properties": {
    "addr:full":"Calle de Maximiliano Thous, 3 Valencia Valencia 46009",
    "addr:housenumber":"3",
    "addr:postcode":"46009",
    "addr:street":"Calle De Maximiliano Thous",
    "iso:country":"ES",
    "sg:address":"Calle de Maximiliano Thous, 3",
    "sg:city":"Valencia",
    "sg:orig_category":"Pizzer\u00cdas",
    "sg:phone":"+34 963 68 80 79",
    "sg:postcode":"46009",
    "sg:province":"Valencia",
    "wof:name":"Pizza & Tradizione C.b.",
    "wof:placetype":"venue"
},
  "geometry": {"coordinates":[-0.3761641979,39.4881134033],"type":"Point"}
}