{
  "type": "Feature",
  "properties": {
    "iso:country":"ES",
    "sg:address":"Calle de Gil De Onta\u00d1on, 11",
    "sg:city":"Salamanca",
    "sg:orig_category":"Procuradores",
    "sg:phone":"+34 923 12 17 59",
    "sg:postcode":"37005",
    "sg:province":"Salamanca",
    "wof:name":"Alvarez Mu\u00f1oz Azucena",
    "wof:placetype":"venue"
},
  "geometry": {"coordinates":[-5.6622338295,40.9712524414],"type":"Point"}
}