{
  "type": "Feature",
  "properties": {
    "iso:country":"ES",
    "sg:address":"Txurrua, 3",
    "sg:city":"Plentzia",
    "sg:orig_category":"Asociaciones Y Clubs Deportivos",
    "sg:phone":"+34 946 77 08 77",
    "sg:postcode":"48620",
    "sg:province":"Vizcaya",
    "wof:name":"Club Kai-eder",
    "wof:placetype":"venue"
},
  "geometry": {"coordinates":[-2.9453520775,43.4083251953],"type":"Point"}
}