{
  "type": "Feature",
  "properties": {
    "iso:country":"ES",
    "sg:address":"Calle de Anboto, 5",
    "sg:city":"Amorebieta",
    "sg:orig_category":"Asesor\u00cda Fiscal Y Jur\u00cddica",
    "sg:phone":"+34 946 30 11 08",
    "sg:postcode":"48340",
    "sg:province":"Vizcaya",
    "wof:name":"Martinez Garrido Juan Carlos",
    "wof:placetype":"venue"
},
  "geometry": {"coordinates":[-2.7310621738,43.2175598145],"type":"Point"}
}