{
  "type": "Feature",
  "properties": {
    "addr:full":"Avda Ferrocarril, 8 Bilbao Vizcaya 48013",
    "addr:housenumber":"8",
    "addr:postcode":"48013",
    "addr:street":"Avda Ferrocarril",
    "iso:country":"ES",
    "sg:address":"Avda Ferrocarril, 8",
    "sg:city":"Bilbao",
    "sg:orig_category":"Artes Gr\u00c1ficas, Artes Pl\u00c1sticas (curso)",
    "sg:phone":"+34 944 27 18 00",
    "sg:postcode":"48013",
    "sg:province":"Vizcaya",
    "wof:name":"Horrika.net, S. L.",
    "wof:placetype":"venue"
},
  "geometry": {"coordinates":[-2.9451389313,43.2561187744],"type":"Point"}
}