{
  "type": "Feature",
  "properties": {
    "iso:country":"ES",
    "sg:address":"Calle de Brezal (el), 31",
    "sg:city":"Cruz Santa",
    "sg:orig_category":"Alimentaci\u00d3n General (al Por Menor)",
    "sg:phone":"+34 922 34 10 50",
    "sg:postcode":"38413",
    "sg:province":"Santa Cruz De Tenerife",
    "wof:name":"Rodriguez Martin Juan",
    "wof:placetype":"venue"
},
  "geometry": {"coordinates":[-16.5629730225,28.3764247894],"type":"Point"}
}