{
  "type": "Feature",
  "properties": {
    "addr:full":"Pase Delicias, 86 Madrid Madrid 28045",
    "addr:housenumber":"86",
    "addr:postcode":"madrid;28045",
    "addr:street":"Delicias",
    "iso:country":"ES",
    "sg:address":"Pase Delicias, 86",
    "sg:city":"Madrid",
    "sg:orig_category":"Aparcamientos (infraestructuras, Accesorios)",
    "sg:phone":"+34 915 27 11 45",
    "sg:postcode":"28045",
    "sg:province":"Madrid",
    "wof:name":"Herederos De Pedro Lucas S. A.",
    "wof:placetype":"venue"
},
  "geometry": {"coordinates":[-3.6944570541,40.3978843689],"type":"Point"}
}