{
  "type": "Feature",
  "properties": {
    "addr:full":"Generalisimo Franco, 14 Pe\u00f1aranda Duero Burgos 09410",
    "addr:housenumber":"14",
    "addr:postcode":"09410",
    "addr:street":"Pen\u0303Aranda Duero",
    "iso:country":"ES",
    "sg:address":"Generalisimo Franco, 14",
    "sg:city":"Pe\u00f1aranda Duero",
    "sg:orig_category":"Supermercados Y Hipermercados",
    "sg:phone":"+34 947 55 22 70",
    "sg:postcode":"09410",
    "sg:province":"Burgos",
    "wof:name":"Plaza Unsion Jose Aquilino",
    "wof:placetype":"venue"
},
  "geometry": {"coordinates":[-3.4278891087,41.7380714417],"type":"Point"}
}