{
  "type": "Feature",
  "properties": {
    "addr:full":"Avda Carlos Iii (de), 77 Cordoba C\u00f3rdoba 14014",
    "addr:housenumber":"77",
    "addr:postcode":"14014",
    "addr:street":"Avda Carlos Iii De;Co\u0301Rdoba",
    "iso:country":"ES",
    "sg:address":"Avda Carlos Iii (de), 77",
    "sg:city":"Cordoba",
    "sg:orig_category":"Alimentaci\u00d3n General (al Por Mayor)",
    "sg:phone":"+34 957 44 03 22",
    "sg:postcode":"14014",
    "sg:province":"C\u00f3rdoba",
    "wof:name":"Villar Romero Rafaela",
    "wof:placetype":"venue"
},
  "geometry": {"coordinates":[-4.7509689331,37.895652771],"type":"Point"}
}