{
  "type": "Feature",
  "properties": {
    "iso:country":"ES",
    "sg:address":"Pla\u00c7 Sitja, 21",
    "sg:city":"Vilagrassa",
    "sg:orig_category":"Agencias Y Agentes Comerciales, Representantes",
    "sg:phone":"+34 973 50 03 49",
    "sg:postcode":"25330",
    "sg:province":"Lleida",
    "wof:name":"Perez Martinez Jose Julian",
    "wof:placetype":"venue"
},
  "geometry": {"coordinates":[1.1063649654,41.6473388672],"type":"Point"}
}