{
  "type": "Feature",
  "properties": {
    "iso:country":"ES",
    "sg:address":"Plaz Espa\u00d1a, S/n",
    "sg:city":"Garlitos",
    "sg:orig_category":"Iglesia Cat\u00d3lica",
    "sg:phone":"+34 924 63 60 25",
    "sg:postcode":"06656",
    "sg:province":"Badajoz",
    "wof:name":"Parroquia De San Juan Bautista",
    "wof:placetype":"venue"
},
  "geometry": {"coordinates":[-5.0481939316,38.8823318481],"type":"Point"}
}