{
  "type": "Feature",
  "properties": {
    "iso:country":"ES",
    "sg:address":"Calle de Victoria, 53",
    "sg:city":"Moron Frontera",
    "sg:orig_category":"Electrodom\u00c9sticos (fabricaci\u00d3n, Al Por Mayor)",
    "sg:phone":"+34 954 85 14 83",
    "sg:postcode":"41530",
    "sg:province":"Sevilla",
    "wof:name":"Sevillano Y Mulero S.a.",
    "wof:placetype":"venue"
},
  "geometry": {"coordinates":[-5.456138134,37.1222076416],"type":"Point"}
}