{
  "type": "Feature",
  "properties": {
    "addr:full":"Carr Creus Velles, 80 Villarreal Castell\u00f3n 12540",
    "addr:housenumber":"80",
    "addr:postcode":"12540",
    "addr:street":"Carr Creus Velles",
    "iso:country":"ES",
    "sg:address":"Carr Creus Velles, 80",
    "sg:city":"Villarreal",
    "sg:orig_category":"Panader\u00cdas, Panader\u00cdas",
    "sg:phone":"+34 964 53 56 94",
    "sg:postcode":"12540",
    "sg:province":"Castell\u00f3n",
    "wof:name":"Gonzalez Colom S.l.",
    "wof:placetype":"venue"
},
  "geometry": {"coordinates":[-0.1050833017,39.9403648376],"type":"Point"}
}