{
  "type": "Feature",
  "properties": {
    "iso:country":"ES",
    "sg:address":"Calle de Puerta De Aguilar, 53",
    "sg:city":"Montilla",
    "sg:orig_category":"Arreglo, Reparaci\u00d3n, Piezas Sueltas De Televisi\u00d3n, V\u00cddeo, Hi",
    "sg:phone":"+34 957 65 12 40",
    "sg:postcode":"14550",
    "sg:province":"C\u00f3rdoba",
    "wof:name":"Raytel Electronica S.l.",
    "wof:placetype":"venue"
},
  "geometry": {"coordinates":[-4.641561985,37.5849113464],"type":"Point"}
}