{
  "type": "Feature",
  "properties": {
    "addr:full":"Carrer de Bisbe Sastre, 8 Palma Islas Baleares 07011",
    "addr:housenumber":"8",
    "addr:postcode":"07011",
    "addr:street":"Carrer De Bisbe Sastre",
    "iso:country":"ES",
    "sg:address":"Carrer de Bisbe Sastre, 8",
    "sg:city":"Palma",
    "sg:orig_category":"Ropa Para Se\u00d1oras Y Caballeros (al Por Menor)",
    "sg:phone":"+34 971 73 16 88",
    "sg:postcode":"07011",
    "sg:province":"Islas Baleares",
    "wof:name":"Roig Ribas Catalina",
    "wof:placetype":"venue"
},
  "geometry": {"coordinates":[2.6384570599,39.580947876],"type":"Point"}
}