{
  "type": "Feature",
  "properties": {
    "addr:full":"Calle de Bebricio, 60 Calahorra La Rioja 26500",
    "addr:housenumber":"60",
    "addr:postcode":"26500",
    "addr:street":"Calle De Bebricio",
    "iso:country":"ES",
    "sg:address":"Calle de Bebricio, 60",
    "sg:city":"Calahorra",
    "sg:orig_category":"Escayola Y Productos De Escayola (fabricaci\u00d3n, Al Por Mayor)",
    "sg:phone":"+34 941 13 54 90",
    "sg:postcode":"26500",
    "sg:province":"La Rioja",
    "wof:name":"Gay Sola Santiago",
    "wof:placetype":"venue"
},
  "geometry": {"coordinates":[-1.9698597193,42.3062019348],"type":"Point"}
}