{
  "type": "Feature",
  "properties": {
    "addr:full":"Calle de Real, 4 Parla Madrid 28980",
    "addr:housenumber":"4",
    "addr:postcode":"28980",
    "addr:street":"Calle De Real",
    "iso:country":"ES",
    "sg:address":"Calle de Real, 4",
    "sg:city":"Parla",
    "sg:orig_category":"Cajas De Ahorro",
    "sg:phone":"+34 916 98 94 14",
    "sg:postcode":"28980",
    "sg:province":"Madrid",
    "sg:website":"www.elmonte.es",
    "wof:name":"Monte De Piedad Y Caja De Ahorros De Huelva Y Sevilla",
    "wof:placetype":"venue"
},
  "geometry": {"coordinates":[-3.7716190815,40.2357788086],"type":"Point"}
}