{
  "type": "Feature",
  "properties": {
    "iso:country":"ES",
    "sg:address":"Calle de Rio Duero, 5",
    "sg:city":"San Javier",
    "sg:orig_category":"Producci\u00d3n, Venta De Productos De Agricultura Biol\u00d3gica",
    "sg:phone":"+34 968 57 33 38",
    "sg:postcode":"30730",
    "sg:province":"Murcia",
    "wof:name":"Agropozo-aledo S.l.",
    "wof:placetype":"venue"
},
  "geometry": {"coordinates":[-0.8244813085,37.8029556274],"type":"Point"}
}