{
  "type": "Feature",
  "properties": {
    "addr:full":"Calle de Ildefonso Marzo, 10 Malaga M\u00e1laga 29003",
    "addr:housenumber":"10",
    "addr:postcode":"29003",
    "addr:street":"Calle De Ildefonso Marzo;Ma\u0301Laga",
    "iso:country":"ES",
    "sg:address":"Calle de Ildefonso Marzo, 10",
    "sg:city":"Malaga",
    "sg:orig_category":"Alimentaci\u00d3n General (al Por Menor)",
    "sg:phone":"+34 952 35 18 04",
    "sg:postcode":"29003",
    "sg:province":"M\u00e1laga",
    "wof:name":"Youping  Li",
    "wof:placetype":"venue"
},
  "geometry": {"coordinates":[-4.4454388618,36.6983299255],"type":"Point"}
}