{
  "type": "Feature",
  "properties": {
    "iso:country":"ES",
    "sg:address":"Carr Arago, 100",
    "sg:city":"Eivissa",
    "sg:orig_category":"Electricidad: Instaladores",
    "sg:phone":"+34 971 30 76 38",
    "sg:postcode":"07800",
    "sg:province":"Islas Baleares",
    "wof:name":"Garcia Grandal Carlos",
    "wof:placetype":"venue"
},
  "geometry": {"coordinates":[1.4188899994,38.9061164856],"type":"Point"}
}