{
  "type": "Feature",
  "properties": {
    "iso:country":"ES",
    "sg:address":"Carr Hannover, 42",
    "sg:city":"Mao",
    "sg:orig_category":"Bisuter\u00cda, Joyer\u00cda, Relojer\u00cda (al Por Menor)",
    "sg:phone":"+34 971 35 26 71",
    "sg:postcode":"07703",
    "sg:province":"Islas Baleares",
    "wof:name":"Pons Rosello Lucrecia",
    "wof:placetype":"venue"
},
  "geometry": {"coordinates":[4.265625,39.8903694153],"type":"Point"}
}