{
  "type": "Feature",
  "properties": {
    "addr:full":"Urb Bahia Javea, 95 Javea Alicante 03730",
    "addr:housenumber":"95",
    "addr:postcode":"03730",
    "addr:street":"Urb Bahia Javea",
    "iso:country":"ES",
    "sg:address":"Urb Bahia Javea, 95",
    "sg:city":"Javea",
    "sg:orig_category":"Notarios",
    "sg:phone":"+34 966 46 30 89",
    "sg:postcode":"03730",
    "sg:province":"Alicante",
    "wof:name":"Turrell  Neil",
    "wof:placetype":"venue"
},
  "geometry": {"coordinates":[0.1570300013,38.7885093689],"type":"Point"}
}