{
  "type": "Feature",
  "properties": {
    "addr:full":"Calle de Leon Y Castillo, 379 Palmas De Gran Canaria Las Palmas 35007",
    "addr:housenumber":"379",
    "addr:postcode":"35007",
    "addr:street":"Calle De Leon Y Castillo",
    "iso:country":"ES",
    "sg:address":"Calle de Leon Y Castillo, 379",
    "sg:city":"Palmas De Gran Canaria",
    "sg:orig_category":"M\u00c9dicos: Ginecolog\u00cda Y Obstetricia",
    "sg:phone":"+34 928 26 31 46",
    "sg:postcode":"35007",
    "sg:province":"Las Palmas",
    "wof:name":"Gonzalez Cabrera Luis Rafael",
    "wof:placetype":"venue"
},
  "geometry": {"coordinates":[-15.4295854568,28.1364459991],"type":"Point"}
}