{
  "type": "Feature",
  "properties": {
    "iso:country":"ES",
    "sg:address":"Calle de San Deogracias, 43",
    "sg:city":"Madrid",
    "sg:orig_category":"Tapicer\u00cdas",
    "sg:phone":"+34 915 08 16 64",
    "sg:postcode":"28044",
    "sg:province":"Madrid",
    "wof:name":"Rodriguez Alcazar Francisco",
    "wof:placetype":"venue"
},
  "geometry": {"coordinates":[-3.7606990337,40.3701400757],"type":"Point"}
}