{
  "type": "Feature",
  "properties": {
    "iso:country":"ES",
    "sg:address":"Avda Rio Jalon, S/n",
    "sg:city":"Calatayud",
    "sg:orig_category":"Chapister\u00cda",
    "sg:phone":"+34 976 88 50 85",
    "sg:postcode":"50300",
    "sg:province":"Zaragoza",
    "wof:name":"Julian Gallego Miguel Angel",
    "wof:placetype":"venue"
},
  "geometry": {"coordinates":[-1.6342300177,41.3548545837],"type":"Point"}
}