{
  "type": "Feature",
  "properties": {
    "addr:full":"Calle de Leon Xiii, 12 Zaragoza Zaragoza 50008",
    "addr:housenumber":"12",
    "addr:postcode":"50008",
    "addr:street":"Calle De Leon Xiii",
    "iso:country":"ES",
    "sg:address":"Calle de Leon Xiii, 12",
    "sg:city":"Zaragoza",
    "sg:orig_category":"Cajas De Ahorro",
    "sg:phone":"+34 976 30 18 45",
    "sg:postcode":"50008",
    "sg:province":"Zaragoza",
    "wof:name":"Caja Laboral Popular",
    "wof:placetype":"venue"
},
  "geometry": {"coordinates":[-0.8818249702,41.6462287903],"type":"Point"}
}