{
  "type": "Feature",
  "properties": {
    "iso:country":"ES",
    "sg:address":"Plaz Gobernador Carlos Ruiz, 4",
    "sg:city":"Madrid",
    "sg:orig_category":"Iglesia Cat\u00d3lica",
    "sg:phone":"+34 914 77 03 96",
    "sg:postcode":"28053",
    "sg:province":"Madrid",
    "wof:name":"Parroquia De San Francisco De Asis",
    "wof:placetype":"venue"
},
  "geometry": {"coordinates":[-3.6619560719,40.3929290771],"type":"Point"}
}