{
  "type": "Feature",
  "properties": {
    "addr:full":"Calle de Montesa, 33 Valencia Valencia 46017",
    "addr:housenumber":"33",
    "addr:postcode":"46017",
    "addr:street":"Calle De Montesa",
    "iso:country":"ES",
    "sg:address":"Calle de Montesa, 33",
    "sg:city":"Valencia",
    "sg:orig_category":"Servicio De Salud",
    "sg:phone":"+34 963 78 71 15",
    "sg:postcode":"46017",
    "sg:province":"Valencia",
    "wof:name":"Ricardo T.nava S.l",
    "wof:placetype":"venue"
},
  "geometry": {"coordinates":[-0.3943459988,39.4553833008],"type":"Point"}
}