{
  "type": "Feature",
  "properties": {
    "iso:country":"ES",
    "sg:address":"Carrer de Providencia, 10",
    "sg:city":"Barcelona",
    "sg:orig_category":"Frutas, Legumbres Frescas Y Tempranas (al Por Menor)",
    "sg:phone":"+34 932 37 97 64",
    "sg:postcode":"08024",
    "sg:province":"Barcelona",
    "wof:name":"Anton Anton Gregorio",
    "wof:placetype":"venue"
},
  "geometry": {"coordinates":[2.1555986404,41.4057273865],"type":"Point"}
}