{
  "type": "Feature",
  "properties": {
    "addr:full":"Carrer de Alexander Fleming, 62 Mollet Valles Barcelona 08100",
    "addr:housenumber":"62",
    "addr:postcode":"08100",
    "addr:street":"Carrer De Alexander Fleming",
    "iso:country":"ES",
    "sg:address":"Carrer de Alexander Fleming, 62",
    "sg:city":"Mollet Valles",
    "sg:orig_category":"Inform\u00c1tica, Ofim\u00c1tica (estudios, Asesor\u00cda, Ingenier\u00cda, Formaci\u00d3n)",
    "sg:phone":"+34 935 70 05 62",
    "sg:postcode":"08100",
    "sg:province":"Barcelona",
    "sg:website":"www.registregrafic.com",
    "wof:name":"Registre Grafic S.l.",
    "wof:placetype":"venue"
},
  "geometry": {"coordinates":[2.2166249752,41.5438613892],"type":"Point"}
}