{
  "type": "Feature",
  "properties": {
    "iso:country":"ES",
    "sg:address":"Calle de Norberto Almandoz, 5",
    "sg:city":"Errenteria",
    "sg:orig_category":"Asistencia Y Seguros De Automovilistas Y Turistas",
    "sg:phone":"+34 943 34 44 11",
    "sg:postcode":"20100",
    "sg:province":"Guip\u00f9zcoa",
    "wof:name":"Asociacion Ayuda En Carretera De Guipuzcoa",
    "wof:placetype":"venue"
},
  "geometry": {"coordinates":[-1.9114342928,43.3105201721],"type":"Point"}
}