{
  "type": "Feature",
  "properties": {
    "addr:full":"Carrer de Providencia, 47 Vic Barcelona 08500",
    "addr:housenumber":"47",
    "addr:postcode":"08500",
    "addr:street":"Carrer De Providencia",
    "iso:country":"ES",
    "sg:address":"Carrer de Providencia, 47",
    "sg:city":"Vic",
    "sg:orig_category":"Reposter\u00cdas",
    "sg:phone":"+34 938 85 11 37",
    "sg:postcode":"08500",
    "sg:province":"Barcelona",
    "wof:name":"Casanova Selles Marie Chel",
    "wof:placetype":"venue"
},
  "geometry": {"coordinates":[2.2567551136,41.9208068848],"type":"Point"}
}