{
  "type": "Feature",
  "properties": {
    "addr:full":"Carrer de Sant Tomas, 49 Terrassa Barcelona 08222",
    "addr:housenumber":"49",
    "addr:postcode":"08222",
    "addr:street":"Carrer De Sant Tomas",
    "iso:country":"ES",
    "sg:address":"Carrer de Sant Tomas, 49",
    "sg:city":"Terrassa",
    "sg:orig_category":"Importaci\u00d3n",
    "sg:phone":"+34 937 31 64 41",
    "sg:postcode":"08222",
    "sg:province":"Barcelona",
    "sg:website":"www.donpiso.com",
    "wof:name":"Ferrovial Servicios Inmobiliarios S.l.",
    "wof:placetype":"venue"
},
  "geometry": {"coordinates":[2.0299990177,41.5655174255],"type":"Point"}
}