{
  "type": "Feature",
  "properties": {
    "iso:country":"ES",
    "sg:address":"Arqueologia, 28",
    "sg:city":"Sevilla",
    "sg:orig_category":"Electricidad: Instaladores",
    "sg:phone":"+34 954 90 61 70",
    "sg:postcode":"41008",
    "sg:province":"Sevilla",
    "wof:name":"Electricidad Macarena S.l.",
    "wof:placetype":"venue"
},
  "geometry": {"coordinates":[-5.9761390686,37.4279708862],"type":"Point"}
}