{
  "type": "Feature",
  "properties": {
    "addr:full":"Carrer de Sant Joan De Malta, 49 Barcelona Barcelona 08018",
    "addr:housenumber":"49",
    "addr:postcode":"08018",
    "addr:street":"Carrer De Sant Joan De Malta",
    "iso:country":"ES",
    "sg:address":"Carrer de Sant Joan De Malta, 49",
    "sg:city":"Barcelona",
    "sg:orig_category":"Alimentaci\u00d3n General (al Por Menor)",
    "sg:phone":"+34 933 07 51 36",
    "sg:postcode":"08018",
    "sg:province":"Barcelona",
    "wof:name":"Pla Aguilar Maria Dolores",
    "wof:placetype":"venue"
},
  "geometry": {"coordinates":[2.1926600933,41.4088096619],"type":"Point"}
}