{
  "type": "Feature",
  "properties": {
    "iso:country":"ES",
    "sg:address":"Calle de Julio Verne, S/n",
    "sg:city":"Talavera Reina",
    "sg:orig_category":"Transportes Por Carretera: Lotes Completos, Mercanc\u00cdas Diversas",
    "sg:phone":"+34 925 81 04 51",
    "sg:postcode":"45600",
    "sg:province":"Toledo",
    "wof:name":"Epifanio Rodriguez Martin S.l.",
    "wof:placetype":"venue"
},
  "geometry": {"coordinates":[-4.8326292038,39.9584884644],"type":"Point"}
}