{
  "type": "Feature",
  "properties": {
    "iso:country":"ES",
    "sg:address":"Calle de Ramirez, 8",
    "sg:city":"Palencia",
    "sg:orig_category":"Fabricaci\u00d3n, Venta De Cuadros, Accesorios Para Enmarcar",
    "sg:phone":"+34 979 70 08 32",
    "sg:postcode":"34005",
    "sg:province":"Palencia",
    "wof:name":"Espina Nieto Jesus",
    "wof:placetype":"venue"
},
  "geometry": {"coordinates":[-4.5362820625,42.0121307373],"type":"Point"}
}