{
  "type": "Feature",
  "properties": {
    "iso:country":"ES",
    "sg:address":"Calle de Cuzco, 3",
    "sg:city":"Palmas De Gran Canaria",
    "sg:orig_category":"Pintura, Barniz, Productos Asimilables (fabricaci\u00d3n, Al Por Mayor)",
    "sg:phone":"+34 928 46 70 65",
    "sg:postcode":"35008",
    "sg:province":"Las Palmas",
    "wof:name":"Quiva-color S.l.",
    "wof:placetype":"venue"
},
  "geometry": {"coordinates":[-15.4210824966,28.1545581818],"type":"Point"}
}