{
  "type": "Feature",
  "properties": {
    "iso:country":"ES",
    "sg:address":"Carrer de Pare Claret, 2",
    "sg:city":"Lloret Mar",
    "sg:orig_category":"Inmobiliaria (agencias)",
    "sg:phone":"+34 972 36 22 29",
    "sg:postcode":"17310",
    "sg:province":"Girona",
    "wof:name":"Vivienda Lloret S. L.",
    "wof:placetype":"venue"
},
  "geometry": {"coordinates":[2.8559062481,41.7027854919],"type":"Point"}
}