{
  "type": "Feature",
  "properties": {
    "addr:full":"Carrer de Consell De Cent, 419 Barcelona Barcelona 08009",
    "addr:housenumber":"419",
    "addr:postcode":"08009",
    "addr:street":"Carrer De Consell De Cent",
    "iso:country":"ES",
    "sg:address":"Carrer de Consell De Cent, 419",
    "sg:city":"Barcelona",
    "sg:orig_category":"Centros Empresariales",
    "sg:phone":"+34 932 65 41 50",
    "sg:postcode":"08009",
    "sg:province":"Barcelona",
    "wof:name":"Federacion Antipirateria",
    "wof:placetype":"venue"
},
  "geometry": {"coordinates":[2.1722090244,41.3961791992],"type":"Point"}
}