{
  "type": "Feature",
  "properties": {
    "iso:country":"ES",
    "sg:address":"Calle de Mayor, 43",
    "sg:city":"Guardo",
    "sg:orig_category":"Carnicer\u00cdas, Carnicer\u00cdas",
    "sg:phone":"+34 979 85 02 33",
    "sg:postcode":"34880",
    "sg:province":"Palencia",
    "wof:name":"Mu\u00f1oz De La Gala Celestino",
    "wof:placetype":"venue"
},
  "geometry": {"coordinates":[-4.842648983,42.7899208069],"type":"Point"}
}