{
  "type": "Feature",
  "properties": {
    "addr:full":"Avda Raza (la), 1 Sevilla Sevilla 41012",
    "addr:housenumber":"1",
    "addr:postcode":"41012",
    "addr:street":"Avda Raza La",
    "iso:country":"ES",
    "sg:address":"Avda Raza (la), 1",
    "sg:city":"Sevilla",
    "sg:orig_category":"Ense\u00d1anza Variada",
    "sg:phone":"+34 954 29 50 19",
    "sg:postcode":"41012",
    "sg:province":"Sevilla",
    "wof:name":"Cenautica S. A.",
    "wof:placetype":"venue"
},
  "geometry": {"coordinates":[-5.9892148972,37.3687515259],"type":"Point"}
}