{
  "type": "Feature",
  "properties": {
    "iso:country":"ES",
    "sg:address":"Plaz Sierra De Cerro Santo, 3",
    "sg:city":"Alcorcon",
    "sg:orig_category":"Animales (al Por Menor)",
    "sg:phone":"+34 916 12 49 07",
    "sg:postcode":"28923",
    "sg:province":"Madrid",
    "wof:name":"Diaz Hernando Carlos",
    "wof:placetype":"venue"
},
  "geometry": {"coordinates":[-3.8206479549,40.3476791382],"type":"Point"}
}