{
  "type": "Feature",
  "properties": {
    "iso:country":"ES",
    "sg:address":"Carrer de Montcada (de), 27",
    "sg:city":"Tortosa",
    "sg:orig_category":"Pe\u00d1as Y Asociaciones Varias",
    "sg:phone":"+34 977 44 58 97",
    "sg:postcode":"43500",
    "sg:province":"Tarragona",
    "wof:name":"Ajuntament De Tortosa",
    "wof:placetype":"venue"
},
  "geometry": {"coordinates":[0.5235522985,40.8130874634],"type":"Point"}
}