{
  "type": "Feature",
  "properties": {
    "iso:country":"ES",
    "sg:address":"Calle de Urbasa, 1",
    "sg:city":"Errenteria",
    "sg:orig_category":"Fisioterapia",
    "sg:phone":"+34 943 34 43 95",
    "sg:postcode":"20100",
    "sg:province":"Guip\u00f9zcoa",
    "wof:name":"Anto\u00f1ana Murillo, Nora",
    "wof:placetype":"venue"
},
  "geometry": {"coordinates":[-1.9018563032,43.3117599487],"type":"Point"}
}