{
  "type": "Feature",
  "properties": {
    "addr:full":"Rond Maleco, (del), 34 Carlet Valencia 46240",
    "addr:postcode":"46240",
    "addr:street":"Maleco",
    "iso:country":"ES",
    "sg:address":"Rond Maleco, (del), 34",
    "sg:city":"Carlet",
    "sg:orig_category":"Electricidad: Instaladores",
    "sg:phone":"+34 962 53 32 81",
    "sg:postcode":"46240",
    "sg:province":"Valencia",
    "sg:website":"www.inelecsa.es",
    "wof:name":"Ibor Masip Sociedad Limitada",
    "wof:placetype":"venue"
},
  "geometry": {"coordinates":[-0.5209739804,39.2250289917],"type":"Point"}
}