{
  "type": "Feature",
  "properties": {
    "addr:full":"Pase Larratxo De, 80 Donostia-san Sebastian Guip\u00f9zcoa 20017",
    "addr:housenumber":"80",
    "addr:postcode":"20017",
    "iso:country":"ES",
    "sg:address":"Pase Larratxo De, 80",
    "sg:city":"Donostia-san Sebastian",
    "sg:orig_category":"Ense\u00d1anza, Formaci\u00d3n Profesional: Aprendizaje",
    "sg:phone":"+34 943 35 00 35",
    "sg:postcode":"20017",
    "sg:province":"Guip\u00f9zcoa",
    "wof:name":"Hogar Maria Ward",
    "wof:placetype":"venue"
},
  "geometry": {"coordinates":[-1.9354269505,43.3165817261],"type":"Point"}
}