{
  "type": "Feature",
  "properties": {
    "iso:country":"ES",
    "sg:address":"Avda Gran Via, 160",
    "sg:city":"Vigo",
    "sg:orig_category":"Masajes",
    "sg:phone":"+34 986 42 19 23",
    "sg:postcode":"36211",
    "sg:province":"Pontevedra",
    "wof:name":"Mirones Oliva Joseba Koldobika",
    "wof:placetype":"venue"
},
  "geometry": {"coordinates":[-8.7279920578,42.2218399048],"type":"Point"}
}