{
  "type": "Feature",
  "properties": {
    "iso:country":"ES",
    "sg:address":"Pque Doctor Calatayud, 19",
    "sg:city":"Aspe",
    "sg:orig_category":"Bancos",
    "sg:phone":"+34 965 49 07 62",
    "sg:postcode":"03680",
    "sg:province":"Alicante",
    "wof:name":"Banco De Valencia S.a.",
    "wof:placetype":"venue"
},
  "geometry": {"coordinates":[-0.7678329945,38.3472557068],"type":"Point"}
}