{
  "type": "Feature",
  "properties": {
    "iso:country":"ES",
    "sg:address":"Avda Menendez Pelayo, 55",
    "sg:city":"Madrid",
    "sg:orig_category":"Maquinaria Para Industrias Diversas",
    "sg:phone":"+34 915 04 57 77",
    "sg:postcode":"28009",
    "sg:province":"Madrid",
    "wof:name":"Abian Fernandez Abrahan",
    "wof:placetype":"venue"
},
  "geometry": {"coordinates":[-3.678015,40.41618],"type":"Point"}
}