{
  "type": "Feature",
  "properties": {
    "addr:full":"Cust Saratxaguren, S/n Artziniega \u00c1lava 01474",
    "addr:housenumber":"s",
    "addr:postcode":"01474",
    "addr:street":"/ N Artziniega A\u0301Lava",
    "iso:country":"ES",
    "sg:address":"Cust Saratxaguren, S/n",
    "sg:city":"Artziniega",
    "sg:orig_category":"Mec\u00c1nico Del Autom\u00d3vil",
    "sg:phone":"+34 945 39 61 28",
    "sg:postcode":"01474",
    "sg:province":"\u00c1lava",
    "wof:name":"Luengas Urruela Santos",
    "wof:placetype":"venue"
},
  "geometry": {"coordinates":[-3.1292920113,43.122543335],"type":"Point"}
}