{
  "type": "Feature",
  "properties": {
    "addr:full":"Av Miraflores, 28 Hospitalet Llobregat Barcelona 08905",
    "addr:housenumber":"28",
    "addr:postcode":"08905",
    "addr:street":"Av Miraflores",
    "iso:country":"ES",
    "sg:address":"Av Miraflores, 28",
    "sg:city":"Hospitalet Llobregat",
    "sg:orig_category":"Inmobiliaria (agencias)",
    "sg:phone":"+34 934 40 19 21",
    "sg:postcode":"08905",
    "sg:province":"Barcelona",
    "wof:name":"Estudi Collblanc S.l.",
    "wof:placetype":"venue"
},
  "geometry": {"coordinates":[2.1104969978,41.3705711365],"type":"Point"}
}