{
  "type": "Feature",
  "properties": {
    "addr:full":"Calle de Doctor Chil, 7 Palmas De Gran Canaria Las Palmas 35001",
    "addr:housenumber":"7",
    "addr:postcode":"35001",
    "addr:street":"Calle De Doctor Chil",
    "iso:country":"ES",
    "sg:address":"Calle de Doctor Chil, 7",
    "sg:city":"Palmas De Gran Canaria",
    "sg:orig_category":"Abogados",
    "sg:phone":"+34 928 31 21 58",
    "sg:postcode":"35001",
    "sg:province":"Las Palmas",
    "wof:name":"Elejabeitia Goyarzun Mariano",
    "wof:placetype":"venue"
},
  "geometry": {"coordinates":[-15.4137010574,28.1000137329],"type":"Point"}
}