{
  "type": "Feature",
  "properties": {
    "iso:country":"ES",
    "sg:address":"Carr Llevamans, De's, S/n",
    "sg:city":"Cala Ratjada",
    "sg:orig_category":"Aparcamientos (infraestructuras, Accesorios)",
    "sg:phone":"+34 971 56 35 26",
    "sg:postcode":"07590",
    "sg:province":"Islas Baleares",
    "wof:name":"Reinhardt Mascuitzki Ma",
    "wof:placetype":"venue"
},
  "geometry": {"coordinates":[3.4621310234,39.7137680054],"type":"Point"}
}