{
  "type": "Feature",
  "properties": {
    "addr:full":"Av Riera, 26 S. Just Desvern Barcelona 08960",
    "addr:housenumber":"26",
    "addr:postcode":"08960",
    "addr:street":"Av Riera",
    "iso:country":"ES",
    "sg:address":"Av Riera, 26",
    "sg:city":"S. Just Desvern",
    "sg:orig_category":"Fabricaci\u00d3n, Venta, Instalaci\u00d3n De R\u00d3tulos, De R\u00d3tulos Luminosos",
    "sg:phone":"+34 933 71 97 46",
    "sg:postcode":"08960",
    "sg:province":"Barcelona",
    "sg:website":"www.spunto.com",
    "wof:name":"Essa Punt S. A.",
    "wof:placetype":"venue"
},
  "geometry": {"coordinates":[2.0782721043,41.3850669861],"type":"Point"}
}