{
  "type": "Feature",
  "properties": {
    "addr:full":"Calle de Martinez Campos, 17 Almeria Almer\u00eda 04002",
    "addr:housenumber":"17",
    "addr:postcode":"04002",
    "addr:street":"Calle De Martinez Campos",
    "iso:country":"ES",
    "sg:address":"Calle de Martinez Campos, 17",
    "sg:city":"Almeria",
    "sg:orig_category":"Periodistas Profesionales",
    "sg:phone":"+34 950 24 29 30",
    "sg:postcode":"04002",
    "sg:province":"Almer\u00eda",
    "wof:name":"Fernandez Gil Antonio",
    "wof:placetype":"venue"
},
  "geometry": {"coordinates":[-2.4646990299,36.8359794617],"type":"Point"}
}