{
  "type": "Feature",
  "properties": {
    "addr:full":"Calle de Illescas, 109 Madrid Madrid 28024",
    "addr:housenumber":"109",
    "addr:postcode":"28024",
    "addr:street":"Calle De Illescas",
    "iso:country":"ES",
    "sg:address":"Calle de Illescas, 109",
    "sg:city":"Madrid",
    "sg:orig_category":"Loter\u00cda Y T\u00d3mbola",
    "sg:phone":"+34 917 18 43 92",
    "sg:postcode":"28024",
    "sg:province":"Madrid",
    "wof:name":"Pesqueira Alonso Eduardo Ernesto",
    "wof:placetype":"venue"
},
  "geometry": {"coordinates":[-3.7612409592,40.3931503296],"type":"Point"}
}