{
  "type": "Feature",
  "properties": {
    "addr:full":"Calle de Arcos, 27 Sevilla Sevilla 41011",
    "addr:housenumber":"27",
    "addr:postcode":"41011",
    "addr:street":"Calle De Arcos",
    "iso:country":"ES",
    "sg:address":"Calle de Arcos, 27",
    "sg:city":"Sevilla",
    "sg:orig_category":"Promotores Constructores",
    "sg:phone":"+34 954 99 09 35",
    "sg:postcode":"41011",
    "sg:province":"Sevilla",
    "wof:name":"Armendariz",
    "wof:placetype":"venue"
},
  "geometry": {"coordinates":[-5.9990091324,37.3761024475],"type":"Point"}
}