{
  "type": "Feature",
  "properties": {
    "addr:full":"Carr Port, 53 Escala Girona 17130",
    "addr:housenumber":"53",
    "addr:postcode":"17130",
    "addr:street":"Carr Port",
    "iso:country":"ES",
    "sg:address":"Carr Port, 53",
    "sg:city":"Escala",
    "sg:orig_category":"Estancos",
    "sg:phone":"+34 972 77 16 23",
    "sg:postcode":"17130",
    "sg:province":"Girona",
    "wof:name":"Pellicer Arbusi Franca",
    "wof:placetype":"venue"
},
  "geometry": {"coordinates":[3.1321649551,42.1229934692],"type":"Point"}
}