{
  "type": "Feature",
  "properties": {
    "addr:full":"Calle de Lepanto, S/n Casalgordo Toledo 45109",
    "addr:housenumber":"s",
    "addr:postcode":"45109",
    "addr:street":"Calle De Lepanto;/ N Casalgordo",
    "iso:country":"ES",
    "sg:address":"Calle de Lepanto, S/n",
    "sg:city":"Casalgordo",
    "sg:orig_category":"Empresas De Carpinter\u00cda De Madera",
    "sg:phone":"+34 925 38 27 15",
    "sg:postcode":"45109",
    "sg:province":"Toledo",
    "wof:name":"Muebles Casalgordo S.a.l",
    "wof:placetype":"venue"
},
  "geometry": {"coordinates":[-3.9653220177,39.6415786743],"type":"Point"}
}