{
  "type": "Feature",
  "properties": {
    "addr:full":"Pla\u00c7 Creu De Quintana, 1 Moncada Valencia 46113",
    "addr:housenumber":"1",
    "addr:postcode":"46113",
    "addr:street":"Quintana",
    "iso:country":"ES",
    "sg:address":"Pla\u00c7 Creu De Quintana, 1",
    "sg:city":"Moncada",
    "sg:orig_category":"Bancos",
    "sg:phone":"+34 961 30 04 25",
    "sg:postcode":"46113",
    "sg:province":"Valencia",
    "wof:name":"Banco Espa\u00f1ol De Credito S.a.",
    "wof:placetype":"venue"
},
  "geometry": {"coordinates":[-0.3934890032,39.5455741882],"type":"Point"}
}