{
  "type": "Feature",
  "properties": {
    "iso:country":"ES",
    "sg:address":"Calle de Abapies (de), 3",
    "sg:city":"Chinchon",
    "sg:orig_category":"Bebidas",
    "sg:phone":"+34 918 94 01 61",
    "sg:postcode":"28370",
    "sg:province":"Madrid",
    "wof:name":"Lumijor S.l.",
    "wof:placetype":"venue"
},
  "geometry": {"coordinates":[-3.4252624512,40.1377639771],"type":"Point"}
}