{
  "type": "Feature",
  "properties": {
    "addr:full":"Calle de Virgen Del Pilar, 11 Montefrio Granada 18270",
    "addr:housenumber":"11",
    "addr:postcode":"18270",
    "addr:street":"Calle De Virgen Del Pilar",
    "iso:country":"ES",
    "sg:address":"Calle de Virgen Del Pilar, 11",
    "sg:city":"Montefrio",
    "sg:orig_category":"Negocio De Materiales De Construcci\u00d3n",
    "sg:phone":"+34 958 33 61 30",
    "sg:postcode":"18270",
    "sg:province":"Granada",
    "wof:name":"Rufinos C.b.",
    "wof:placetype":"venue"
},
  "geometry": {"coordinates":[-4.0031929016,37.3214454651],"type":"Point"}
}