{
  "type": "Feature",
  "properties": {
    "addr:full":"Avda Chapi, 54 Elda Alicante 03600",
    "addr:housenumber":"54",
    "addr:postcode":"03600",
    "addr:street":"Avda Chapi",
    "iso:country":"ES",
    "sg:address":"Avda Chapi, 54",
    "sg:city":"Elda",
    "sg:orig_category":"M\u00c1rmoles, Granitos Y Piedras Naturales",
    "sg:phone":"+34 965 38 70 14",
    "sg:postcode":"03600",
    "sg:province":"Alicante",
    "wof:name":"Marmocheck S.l.",
    "wof:placetype":"venue"
},
  "geometry": {"coordinates":[-0.7949240208,38.4739151001],"type":"Point"}
}