{
  "type": "Feature",
  "properties": {
    "iso:country":"ES",
    "sg:address":"Calle de Montevideo, 5",
    "sg:city":"Alcala Henares",
    "sg:orig_category":"Agentes, Concesionarios Y Sucursales De Camiones Y Veh\u00cdculos Industriales",
    "sg:phone":"+34 918 30 03 37",
    "sg:postcode":"28806",
    "sg:province":"Madrid",
    "sg:website":"www.lunasjumiglass.com",
    "wof:name":"Jumiglass S.l.l.",
    "wof:placetype":"venue"
},
  "geometry": {"coordinates":[-3.4076840878,40.5157814026],"type":"Point"}
}