{
  "type": "Feature",
  "properties": {
    "addr:full":"Calle de Mairena, 28 Alcala Guadaira Sevilla 41500",
    "addr:housenumber":"28",
    "addr:postcode":"41500",
    "addr:street":"Calle De Mairena",
    "iso:country":"ES",
    "sg:address":"Calle de Mairena, 28",
    "sg:city":"Alcala Guadaira",
    "sg:orig_category":"Mercer\u00cda, Lencer\u00cda (al Por Menor)",
    "sg:phone":"+34 955 68 70 72",
    "sg:postcode":"41500",
    "sg:province":"Sevilla",
    "wof:name":"Trigo Nu\u00f1ez Bernardo",
    "wof:placetype":"venue"
},
  "geometry": {"coordinates":[-5.842250824,37.3380241394],"type":"Point"}
}