{
  "type": "Feature",
  "properties": {
    "iso:country":"ES",
    "sg:address":"Calle de Calderon De La Barca, 19",
    "sg:city":"Gijon",
    "sg:orig_category":"Ebanister\u00cda",
    "sg:phone":"+34 985 36 99 99",
    "sg:postcode":"33204",
    "sg:province":"Asturias",
    "wof:name":"Diaz Valcarce Manuel",
    "wof:placetype":"venue"
},
  "geometry": {"coordinates":[-5.6500406265,43.5342407227],"type":"Point"}
}