{
  "type": "Feature",
  "properties": {
    "addr:full":"Casa, 1 Ve\u00efnat Sant Vicenc Barcelona 08490",
    "addr:postcode":"08490",
    "iso:country":"ES",
    "sg:address":"Casa, 1",
    "sg:city":"Ve\u00efnat Sant Vicenc",
    "sg:orig_category":"Empresas De Hormig\u00d3n, Hormig\u00d3n Armado Y Pretensado",
    "sg:phone":"+34 937 64 02 71",
    "sg:postcode":"08490",
    "sg:province":"Barcelona",
    "wof:name":"Torho S. A.",
    "wof:placetype":"venue"
},
  "geometry": {"coordinates":[2.7045199871,41.7052116394],"type":"Point"}
}