{
  "type": "Feature",
  "properties": {
    "iso:country":"ES",
    "sg:address":"Avda Estacion (de La), 40",
    "sg:city":"Puente-genil",
    "sg:orig_category":"T\u00c9cnicos Veterinarios",
    "sg:phone":"+34 957 60 02 34",
    "sg:postcode":"14500",
    "sg:province":"C\u00f3rdoba",
    "wof:name":"Perales Cosano Juan Manuel",
    "wof:placetype":"venue"
},
  "geometry": {"coordinates":[-4.760196209,37.393661499],"type":"Point"}
}