{
  "type": "Feature",
  "properties": {
    "iso:country":"ES",
    "sg:address":"Calle de Camarena, 320",
    "sg:city":"Madrid",
    "sg:orig_category":"\u00d3ptica: Instrumentos (fabricaci\u00d3n)",
    "sg:phone":"+34 917 17 88 85",
    "sg:postcode":"28047",
    "sg:province":"Madrid",
    "wof:name":"Opticas Poveda S.l.",
    "wof:placetype":"venue"
},
  "geometry": {"coordinates":[-3.7578356266,40.385433197],"type":"Point"}
}