{
  "type": "Feature",
  "properties": {
    "iso:country":"ES",
    "sg:address":"Calle de Doctor Rodriguez De La Fuente, 8",
    "sg:city":"Valencia",
    "sg:orig_category":"Organizaciones Internacionales",
    "sg:phone":"+34 963 46 33 74",
    "sg:postcode":"46019",
    "sg:province":"Valencia",
    "wof:name":"Asociacion La Casa Grande",
    "wof:placetype":"venue"
},
  "geometry": {"coordinates":[-0.3778299093,39.4958381653],"type":"Point"}
}