{
  "type": "Feature",
  "properties": {
    "iso:country":"ES",
    "sg:address":"Calle de Granada, 8",
    "sg:city":"Malaga",
    "sg:orig_category":"Ense\u00d1anza: Profesiones Art\u00cdsticas",
    "sg:phone":"+34 952 21 46 17",
    "sg:postcode":"29015",
    "sg:province":"M\u00e1laga",
    "wof:name":"Rodriguez Novoa Fernando",
    "wof:placetype":"venue"
},
  "geometry": {"coordinates":[-4.4212050438,36.7215423584],"type":"Point"}
}