{
  "type": "Feature",
  "properties": {
    "iso:country":"ES",
    "sg:address":"Urb Las Lagunillas, 11",
    "sg:city":"Coria",
    "sg:orig_category":"Cr\u00cda De Animales",
    "sg:phone":"+34 927 50 38 52",
    "sg:postcode":"10800",
    "sg:province":"C\u00e1ceres",
    "wof:name":"Estevez Silva Fernando",
    "wof:placetype":"venue"
},
  "geometry": {"coordinates":[-6.5274448395,39.9833068848],"type":"Point"}
}