{
  "type": "Feature",
  "properties": {
    "addr:full":"Calle de Ramblica (de La), S/n Totana Murcia 30850",
    "addr:postcode":"30850",
    "addr:street":"Calle De Ramblica De La S / N",
    "iso:country":"ES",
    "sg:address":"Calle de Ramblica (de La), S/n",
    "sg:city":"Totana",
    "sg:orig_category":"Cueros Y Pieles (al Por Mayor)",
    "sg:phone":"+34 968 42 45 22",
    "sg:postcode":"30850",
    "sg:province":"Murcia",
    "wof:name":"Curtidos Basa S.l.",
    "wof:placetype":"venue"
},
  "geometry": {"coordinates":[-1.5023490191,37.7749862671],"type":"Point"}
}