{
  "type": "Feature",
  "properties": {
    "addr:full":"Calle de Povoa, S/n Aranda Duero Burgos 09400",
    "addr:housenumber":"s / n",
    "addr:postcode":"09400",
    "addr:street":"Calle De Povoa",
    "iso:country":"ES",
    "sg:address":"Calle de Povoa, S/n",
    "sg:city":"Aranda Duero",
    "sg:orig_category":"Carnicer\u00cdas, Carnicer\u00cdas",
    "sg:phone":"+34 947 50 49 09",
    "sg:postcode":"09400",
    "sg:province":"Burgos",
    "wof:name":"Martin Gayubo S.a.l.",
    "wof:placetype":"venue"
},
  "geometry": {"coordinates":[-3.6889948845,41.6699256897],"type":"Point"}
}