{
  "type": "Feature",
  "properties": {
    "addr:full":"Avda Jesus Santos Rein, 2 Fuengirola M\u00e1laga 29640",
    "addr:housenumber":"2",
    "addr:postcode":"29640",
    "addr:street":"Avda Jesus Santos Rein;Ma\u0301Laga",
    "iso:country":"ES",
    "sg:address":"Avda Jesus Santos Rein, 2",
    "sg:city":"Fuengirola",
    "sg:orig_category":"Promotores Constructores",
    "sg:phone":"+34 952 47 74 55",
    "sg:postcode":"29640",
    "sg:province":"M\u00e1laga",
    "sg:website":"www.profasan.com",
    "wof:name":"Profasan S.a.",
    "wof:placetype":"venue"
},
  "geometry": {"coordinates":[-4.6186819077,36.5495567322],"type":"Point"}
}