{
  "type": "Feature",
  "properties": {
    "addr:full":"Calle de Potosi, 8 Madrid Madrid 28016",
    "addr:housenumber":"8",
    "addr:postcode":"madrid;28016",
    "addr:street":"Calle De Potosi",
    "iso:country":"ES",
    "sg:address":"Calle de Potosi, 8",
    "sg:city":"Madrid",
    "sg:orig_category":"Promotores Constructores",
    "sg:phone":"+34 914 57 77 54",
    "sg:postcode":"28016",
    "sg:province":"Madrid",
    "wof:name":"Perecos S.l.",
    "wof:placetype":"venue"
},
  "geometry": {"coordinates":[-3.6794800758,40.4566841125],"type":"Point"}
}