{
  "type": "Feature",
  "properties": {
    "iso:country":"ES",
    "sg:address":"Calle de Roda Arriba, 7",
    "sg:city":"Lora Rio",
    "sg:orig_category":"Ebanister\u00cda",
    "sg:phone":"+34 955 80 35 28",
    "sg:postcode":"41440",
    "sg:province":"Sevilla",
    "wof:name":"Martin Sanchez Manuel",
    "wof:placetype":"venue"
},
  "geometry": {"coordinates":[-5.528883934,37.6568603516],"type":"Point"}
}