{
  "type": "Feature",
  "properties": {
    "addr:full":"Fontan (parderrubias), S/n Fontan Pontevedra 36472",
    "addr:postcode":"36472",
    "addr:street":"Parderrubias S / N Fontan",
    "iso:country":"ES",
    "sg:address":"Fontan (parderrubias), S/n",
    "sg:city":"Fontan",
    "sg:orig_category":"Revestimiento De Suelos Industriales",
    "sg:phone":"+34 986 34 76 62",
    "sg:postcode":"36472",
    "sg:province":"Pontevedra",
    "wof:name":"Alvarez Fernandez Manuel",
    "wof:placetype":"venue"
},
  "geometry": {"coordinates":[-8.3368577957,42.1133918762],"type":"Point"}
}