{
  "type": "Feature",
  "properties": {
    "iso:country":"ES",
    "sg:address":"Calle de Valladolid, 14",
    "sg:city":"Parla",
    "sg:orig_category":"Centros Empresariales",
    "sg:phone":"+34 916 05 70 40",
    "sg:postcode":"28980",
    "sg:province":"Madrid",
    "wof:name":"Union Sindical Madrid Region De Comisiones Obreras",
    "wof:placetype":"venue"
},
  "geometry": {"coordinates":[-3.8148674965,40.2757873535],"type":"Point"}
}