{
  "type": "Feature",
  "properties": {
    "addr:full":"Carrer de Emili Caba\u00d1es, 2 Mataro Barcelona 08302",
    "addr:housenumber":"2",
    "addr:postcode":"08302",
    "addr:street":"Carrer De Emili Caban\u0303Es",
    "iso:country":"ES",
    "sg:address":"Carrer de Emili Caba\u00d1es, 2",
    "sg:city":"Mataro",
    "sg:orig_category":"Maquinaria Para Industrias Diversas",
    "sg:phone":"+34 937 98 75 10",
    "sg:postcode":"08302",
    "sg:province":"Barcelona",
    "wof:name":"Sanchez Domingo Ramon",
    "wof:placetype":"venue"
},
  "geometry": {"coordinates":[2.4384899139,41.540687561],"type":"Point"}
}