{
  "type": "Feature",
  "properties": {
    "iso:country":"ES",
    "sg:address":"Pg Hortsavinya, 5",
    "sg:city":"Creus",
    "sg:orig_category":"Planchado",
    "sg:phone":"+34 937 62 35 80",
    "sg:postcode":"08397",
    "sg:province":"Barcelona",
    "wof:name":"Arcos Aguilera Maria Antonia",
    "wof:placetype":"venue"
},
  "geometry": {"coordinates":[2.6446404457,41.6270523071],"type":"Point"}
}