{
  "type": "Feature",
  "properties": {
    "iso:country":"ES",
    "sg:address":"Carr Serra Llarga, 1",
    "sg:city":"Balaguer",
    "sg:orig_category":"Cerrajer\u00cda, Ferrallista",
    "sg:phone":"+34 973 44 56 59",
    "sg:postcode":"25600",
    "sg:province":"Lleida",
    "wof:name":"Calvis Torres Vicente",
    "wof:placetype":"venue"
},
  "geometry": {"coordinates":[0.8071600199,41.7896003723],"type":"Point"}
}