{
  "type": "Feature",
  "properties": {
    "iso:country":"ES",
    "sg:address":"Calle de Satsumas, 10",
    "sg:city":"Sevilla",
    "sg:orig_category":"Autob\u00das (explotaci\u00d3n Y Servicios De)",
    "sg:phone":"+34 954 52 18 20",
    "sg:postcode":"41006",
    "sg:province":"Sevilla",
    "wof:name":"Autocares Falcon Leon S.l",
    "wof:placetype":"venue"
},
  "geometry": {"coordinates":[-5.946644783,37.3853530884],"type":"Point"}
}