{
  "type": "Feature",
  "properties": {
    "addr:full":"Calle de San Antonio, 47 Marbella M\u00e1laga 29600",
    "addr:housenumber":"47",
    "addr:postcode":"29600",
    "addr:street":"Calle De San Antonio;Ma\u0301Laga",
    "iso:country":"ES",
    "sg:address":"Calle de San Antonio, 47",
    "sg:city":"Marbella",
    "sg:orig_category":"Fabricaci\u00d3n De Juguetes Autom\u00c1ticos",
    "sg:phone":"+34 952 86 39 57",
    "sg:postcode":"29600",
    "sg:province":"M\u00e1laga",
    "wof:name":"Tcs Spain S.a.",
    "wof:placetype":"venue"
},
  "geometry": {"coordinates":[-4.9888591766,36.4862213135],"type":"Point"}
}