{
  "type": "Feature",
  "properties": {
    "addr:full":"Pla\u00c7 Pla\u00c7a Del Mercat, 1 Alzira Valencia 46600",
    "addr:housenumber":"1",
    "addr:postcode":"46600",
    "addr:street":"Mercat",
    "iso:country":"ES",
    "sg:address":"Pla\u00c7 Pla\u00c7a Del Mercat, 1",
    "sg:city":"Alzira",
    "sg:orig_category":"Zapatos (al Por Menor)",
    "sg:phone":"+34 962 40 42 83",
    "sg:postcode":"46600",
    "sg:province":"Valencia",
    "wof:name":"Zapateria Guasp S.l.",
    "wof:placetype":"venue"
},
  "geometry": {"coordinates":[-0.4395977855,39.1504211426],"type":"Point"}
}