{
  "type": "Feature",
  "properties": {
    "iso:country":"ES",
    "sg:address":"Carrer de Jaume Ii, 8",
    "sg:city":"Novelda",
    "sg:orig_category":"Ropa Para Se\u00d1oras Y Caballeros (al Por Menor)",
    "sg:phone":"+34 965 60 39 83",
    "sg:postcode":"03660",
    "sg:province":"Alicante",
    "wof:name":"Vidal Rico Antonio",
    "wof:placetype":"venue"
},
  "geometry": {"coordinates":[-0.7672219872,38.3845214844],"type":"Point"}
}