{
  "type": "Feature",
  "properties": {
    "iso:country":"ES",
    "sg:address":"Calle de Maestro Albeniz, 17",
    "sg:city":"Sax",
    "sg:orig_category":"Agencias Y Asesores De Publicidad",
    "sg:phone":"+34 965 47 59 27",
    "sg:postcode":"03630",
    "sg:province":"Alicante",
    "wof:name":"Terpe Creacciones Publicitarias S.l.",
    "wof:placetype":"venue"
},
  "geometry": {"coordinates":[-0.8234670162,38.5332679749],"type":"Point"}
}