{
  "type": "Feature",
  "properties": {
    "addr:full":"Pl Del Sortidor, 10 Barcelona Barcelona 08004",
    "addr:housenumber":"10",
    "addr:postcode":"08004",
    "addr:street":"Pl Del Sortidor",
    "iso:country":"ES",
    "sg:address":"Pl Del Sortidor, 10",
    "sg:city":"Barcelona",
    "sg:orig_category":"Laboratorios Y Trabajos De Fotograf\u00cda, V\u00cddeo Y Cine",
    "sg:phone":"+34 934 42 72 71",
    "sg:postcode":"08004",
    "sg:province":"Barcelona",
    "wof:name":"Gas Sanz Angel",
    "wof:placetype":"venue"
},
  "geometry": {"coordinates":[2.1622200012,41.3721351624],"type":"Point"}
}