{
  "type": "Feature",
  "properties": {
    "addr:full":"Calle de Real, 37 Illescas Toledo 45200",
    "addr:housenumber":"37",
    "addr:postcode":"45200",
    "addr:street":"Calle De Real",
    "iso:country":"ES",
    "sg:address":"Calle de Real, 37",
    "sg:city":"Illescas",
    "sg:orig_category":"Inmobiliaria (agencias)",
    "sg:phone":"+34 925 53 23 76",
    "sg:postcode":"45200",
    "sg:province":"Toledo",
    "wof:name":"Su Casa Xxi Inmobiliaria La Sagra S.l.",
    "wof:placetype":"venue"
},
  "geometry": {"coordinates":[-3.8505005836,40.1241607666],"type":"Point"}
}