{
  "type": "Feature",
  "properties": {
    "iso:country":"ES",
    "sg:address":"Calle de Pintor Rosales, 10",
    "sg:city":"Logro\u00f1o",
    "sg:orig_category":"Locales Y Clases De Danza",
    "sg:phone":"+34 941 21 00 41",
    "sg:postcode":"26005",
    "sg:province":"La Rioja",
    "wof:name":"Salgado Frias Maria",
    "wof:placetype":"venue"
},
  "geometry": {"coordinates":[-2.4551858902,42.456741333],"type":"Point"}
}