{
  "type": "Feature",
  "properties": {
    "iso:country":"ES",
    "sg:address":"Calle de Martires, 11",
    "sg:city":"Almendralejo",
    "sg:orig_category":"Productores Recolectores, Venta Directa De Vinos",
    "sg:phone":"+34 924 66 14 56",
    "sg:postcode":"06200",
    "sg:province":"Badajoz",
    "wof:name":"Bernavalejo S.l.",
    "wof:placetype":"venue"
},
  "geometry": {"coordinates":[-6.4088959694,38.6810951233],"type":"Point"}
}