{
  "type": "Feature",
  "properties": {
    "addr:full":"Calle de Ayala, 12 Don Benito Badajoz 06400",
    "addr:housenumber":"12",
    "addr:postcode":"06400",
    "addr:street":"Calle De Ayala",
    "iso:country":"ES",
    "sg:address":"Calle de Ayala, 12",
    "sg:city":"Don Benito",
    "sg:orig_category":"Cl\u00cdnicas Dentales",
    "sg:phone":"+34 924 80 20 22",
    "sg:postcode":"06400",
    "sg:province":"Badajoz",
    "wof:name":"Clinica Dental Mariscal Andrade C.b.",
    "wof:placetype":"venue"
},
  "geometry": {"coordinates":[-5.859521389,38.9615249634],"type":"Point"}
}