{
  "type": "Feature",
  "properties": {
    "addr:full":"Calle de Juan Fernandez, 49 Cartagena Murcia 30204",
    "addr:housenumber":"49",
    "addr:postcode":"30204",
    "addr:street":"Calle De Juan Fernandez",
    "iso:country":"ES",
    "sg:address":"Calle de Juan Fernandez, 49",
    "sg:city":"Cartagena",
    "sg:orig_category":"Cajas De Ahorro",
    "sg:phone":"+34 968 53 51 51",
    "sg:postcode":"30204",
    "sg:province":"Murcia",
    "sg:website":"www.cajamurcia.es",
    "wof:name":"Caja De Ahorros De Murcia",
    "wof:placetype":"venue"
},
  "geometry": {"coordinates":[-0.9883300066,37.6130714417],"type":"Point"}
}