{
  "type": "Feature",
  "properties": {
    "iso:country":"ES",
    "sg:address":"Trav. Mayo, 19",
    "sg:city":"Navafria",
    "sg:orig_category":"Molduras, Junquillos, Listones Y Molduras Perforadas",
    "sg:phone":"+34 921 50 63 22",
    "sg:postcode":"40161",
    "sg:province":"Segovia",
    "wof:name":"Salvador Acebes Carmen",
    "wof:placetype":"venue"
},
  "geometry": {"coordinates":[-3.8256180286,41.0558280945],"type":"Point"}
}