{
  "type": "Feature",
  "properties": {
    "iso:country":"ES",
    "sg:address":"Manantial, S/n",
    "sg:city":"Arroyo Miel",
    "sg:orig_category":"Carnicer\u00cdas, Carnicer\u00cdas",
    "sg:phone":"+34 952 56 41 66",
    "sg:postcode":"29631",
    "sg:province":"M\u00e1laga",
    "wof:name":"Gonzalez Martin Mario",
    "wof:placetype":"venue"
},
  "geometry": {"coordinates":[-4.536687851,36.6011962891],"type":"Point"}
}