{
  "type": "Feature",
  "properties": {
    "addr:full":"Calle de Casta\u00d1o Bajo, 1 Casta\u00e7o Bajo Las Palmas 35300",
    "addr:housenumber":"1",
    "addr:postcode":"35300",
    "addr:street":"Calle De Castan\u0303O Bajo;Las",
    "iso:country":"ES",
    "sg:address":"Calle de Casta\u00d1o Bajo, 1",
    "sg:city":"Casta\u00e7o Bajo",
    "sg:orig_category":"Agentes, Concesionarios Y Sucursales De Veh\u00cdculos",
    "sg:phone":"+34 928 64 49 51",
    "sg:postcode":"35300",
    "sg:province":"Las Palmas",
    "wof:name":"Raimundo Martin Hernandez S.l.",
    "wof:placetype":"venue"
},
  "geometry": {"coordinates":[-15.4300060272,28.1248226166],"type":"Point"}
}