{
  "type": "Feature",
  "properties": {
    "addr:full":"Calle de Rio, S/n Mazuecos Guadalajara 19114",
    "addr:postcode":"19114",
    "addr:street":"Calle De Rio S / N Mazuecos",
    "iso:country":"ES",
    "sg:address":"Calle de Rio, S/n",
    "sg:city":"Mazuecos",
    "sg:orig_category":"Poller\u00cda Y Caza (al Por Menor)",
    "sg:phone":"+34 949 38 90 04",
    "sg:postcode":"19114",
    "sg:province":"Guadalajara",
    "wof:name":"Granja Mari Carmen S.l",
    "wof:placetype":"venue"
},
  "geometry": {"coordinates":[-3.0084118843,40.2617111206],"type":"Point"}
}