{
  "type": "Feature",
  "properties": {
    "iso:country":"ES",
    "sg:address":"Calle de General Diaz Porlier, 34",
    "sg:city":"Madrid",
    "sg:orig_category":"Pescader\u00cdas (al Por Menor)",
    "sg:phone":"+34 914 02 45 09",
    "sg:postcode":"28001",
    "sg:province":"Madrid",
    "wof:name":"Cortizo Rodriguez Ramon",
    "wof:placetype":"venue"
},
  "geometry": {"coordinates":[-3.6768000126,40.427898407],"type":"Point"}
}