{
  "type": "Feature",
  "properties": {
    "addr:full":"Calle de Ponce De Leon, 5 Aviles Asturias 33403",
    "addr:housenumber":"5",
    "addr:postcode":"33403",
    "addr:street":"Calle De Ponce De Leon",
    "iso:country":"ES",
    "sg:address":"Calle de Ponce De Leon, 5",
    "sg:city":"Aviles",
    "sg:orig_category":"Supermercados Y Hipermercados",
    "sg:phone":"+34 985 51 40 16",
    "sg:postcode":"33403",
    "sg:province":"Asturias",
    "wof:name":"Alimerka S.a.",
    "wof:placetype":"venue"
},
  "geometry": {"coordinates":[-5.9108562469,43.5387153625],"type":"Point"}
}