{
  "type": "Feature",
  "properties": {
    "addr:full":"Rua Abadia, 5 Olite Navarra 31390",
    "addr:housenumber":"5",
    "addr:postcode":"31390",
    "addr:street":"Rua Abadia",
    "iso:country":"ES",
    "sg:address":"Rua Abadia, 5",
    "sg:city":"Olite",
    "sg:orig_category":"Empresas De Pintura Y Revestimientos",
    "sg:phone":"+34 948 71 22 41",
    "sg:postcode":"31390",
    "sg:province":"Navarra",
    "wof:name":"Perez Izurriaga Angel Luis",
    "wof:placetype":"venue"
},
  "geometry": {"coordinates":[-1.648859024,42.4807395935],"type":"Point"}
}