{
  "type": "Feature",
  "properties": {
    "addr:full":"Calle de Ramon Gonzalez Alegre, 10 Flores Del Sil Le\u00f3n 24400",
    "addr:housenumber":"10",
    "addr:postcode":"24400",
    "addr:street":"Calle De Ramon Gonzalez Alegre",
    "iso:country":"ES",
    "sg:address":"Calle de Ramon Gonzalez Alegre, 10",
    "sg:city":"Flores Del Sil",
    "sg:orig_category":"Asociaciones Humanitarias, De Cooperaci\u00d3n, De Acci\u00d3n Social",
    "sg:phone":"+34 987 41 28 38",
    "sg:postcode":"24400",
    "sg:province":"Le\u00f3n",
    "wof:name":"Alzeimer Bierzo",
    "wof:placetype":"venue"
},
  "geometry": {"coordinates":[-6.6093249321,42.5481071472],"type":"Point"}
}