{
  "type": "Feature",
  "properties": {
    "iso:country":"ES",
    "sg:address":"Gustave Eiffel, 3",
    "sg:city":"Gijon",
    "sg:orig_category":"Maquinaria Para Industrias Diversas",
    "sg:phone":"+34 985 16 86 97",
    "sg:postcode":"33211",
    "sg:province":"Asturias",
    "wof:name":"Ulma C.y E. S.coop.",
    "wof:placetype":"venue"
},
  "geometry": {"coordinates":[-5.6863942146,43.5233383179],"type":"Point"}
}