{
  "type": "Feature",
  "properties": {
    "iso:country":"ES",
    "sg:address":"Plaz San Ramon, 2",
    "sg:city":"Casillas De Coria",
    "sg:orig_category":"M\u00c9dicos: Radioterapia (radioterapia Como Opci\u00d3n Oncol\u00d3gica)",
    "sg:phone":"+34 927 14 60 50",
    "sg:postcode":"10818",
    "sg:province":"C\u00e1ceres",
    "wof:name":"Sanchez Delgado Pedro",
    "wof:placetype":"venue"
},
  "geometry": {"coordinates":[-6.6363668442,39.9657974243],"type":"Point"}
}