{
  "type": "Feature",
  "properties": {
    "iso:country":"ES",
    "sg:address":"Carrer de Salvador Espriu, 93",
    "sg:city":"Barcelona",
    "sg:orig_category":"Psic\u00d3logos",
    "sg:phone":"+34 932 21 64 26",
    "sg:postcode":"08005",
    "sg:province":"Barcelona",
    "wof:name":"Compte Valls Luis Maria",
    "wof:placetype":"venue"
},
  "geometry": {"coordinates":[2.2016379833,41.3922958374],"type":"Point"}
}