{
  "type": "Feature",
  "properties": {
    "iso:country":"ES",
    "sg:address":"Calle de Nuestra Se\u00d1ora De Los Dolores, 46",
    "sg:city":"Sevilla",
    "sg:orig_category":"Asociaciones, Organismos Culturales Y Socioeducativos",
    "sg:phone":"+34 954 64 05 59",
    "sg:postcode":"41006",
    "sg:province":"Sevilla",
    "wof:name":"Hermandad Nuestra Se\u00f1ora De Los Dolores",
    "wof:placetype":"venue"
},
  "geometry": {"coordinates":[-5.9580149651,37.3712692261],"type":"Point"}
}