{
  "type": "Feature",
  "properties": {
    "iso:country":"ES",
    "sg:address":"Calle de Postigos, 27",
    "sg:city":"Marbella",
    "sg:orig_category":"Negocio De Enlosados, Soler\u00cdas",
    "sg:phone":"+34 952 77 10 47",
    "sg:postcode":"29600",
    "sg:province":"M\u00e1laga",
    "wof:name":"Garcia Sanchez Alonso",
    "wof:placetype":"venue"
},
  "geometry": {"coordinates":[-4.8844242096,36.5135765076],"type":"Point"}
}