{
  "type": "Feature",
  "properties": {
    "iso:country":"ES",
    "sg:address":"Plaz Playa De Aro, 3",
    "sg:city":"Teruel",
    "sg:orig_category":"Supermercados Y Hipermercados",
    "sg:phone":"+34 978 62 06 27",
    "sg:postcode":"44002",
    "sg:province":"Teruel",
    "wof:name":"Alvimar S. C. L.",
    "wof:placetype":"venue"
},
  "geometry": {"coordinates":[-1.1084802151,40.3319206238],"type":"Point"}
}