{
  "type": "Feature",
  "properties": {
    "addr:full":"Calle de San Fernando, 9 Cordoba C\u00f3rdoba 14003",
    "addr:housenumber":"9",
    "addr:postcode":"14003",
    "addr:street":"Calle De San Fernando;Co\u0301Rdoba",
    "iso:country":"ES",
    "sg:address":"Calle de San Fernando, 9",
    "sg:city":"Cordoba",
    "sg:orig_category":"Peluqueros: De Se\u00d1oras",
    "sg:phone":"+34 957 48 79 95",
    "sg:postcode":"14003",
    "sg:province":"C\u00f3rdoba",
    "wof:name":"Salon De Belleza Nicolas S.l.",
    "wof:placetype":"venue"
},
  "geometry": {"coordinates":[-4.7766990662,37.8829803467],"type":"Point"}
}