{
  "type": "Feature",
  "properties": {
    "addr:full":"Carrer de Mare De Deu De L'orito, 5 Xixona Alicante 03100",
    "addr:housenumber":"5",
    "addr:postcode":"03100",
    "addr:street":"Carrer De Mare De Deu;L'Orito",
    "iso:country":"ES",
    "sg:address":"Carrer de Mare De Deu De L'orito, 5",
    "sg:city":"Xixona",
    "sg:orig_category":"Institutos De Belleza",
    "sg:phone":"+34 965 61 31 82",
    "sg:postcode":"03100",
    "sg:province":"Alicante",
    "wof:name":"Pineda Garcia Catalina",
    "wof:placetype":"venue"
},
  "geometry": {"coordinates":[-0.5068824291,38.5469474792],"type":"Point"}
}