{
  "type": "Feature",
  "properties": {
    "iso:country":"ES",
    "sg:address":"Calle de Juan Xxiii, 19",
    "sg:city":"Huercal-overa",
    "sg:orig_category":"Tintes (fabricaci\u00d3n, Al Por Mayor)",
    "sg:phone":"+34 950 13 49 93",
    "sg:postcode":"04600",
    "sg:province":"Almer\u00eda",
    "wof:name":"Fraile Rivas Jose Vicente",
    "wof:placetype":"venue"
},
  "geometry": {"coordinates":[-1.9455900192,37.3925285339],"type":"Point"}
}