{
  "type": "Feature",
  "properties": {
    "addr:full":"Avda General Fanjul, 6 Madrid Madrid 28044",
    "addr:housenumber":"6",
    "addr:postcode":"28044",
    "addr:street":"Avda General Fanjul",
    "iso:country":"ES",
    "sg:address":"Avda General Fanjul, 6",
    "sg:city":"Madrid",
    "sg:orig_category":"Sociedades, Compa\u00d1\u00cdas Aseguradoras",
    "sg:phone":"+34 915 09 28 46",
    "sg:postcode":"28044",
    "sg:province":"Madrid",
    "wof:name":"Mariano Galan Y Asociados S.l.",
    "wof:placetype":"venue"
},
  "geometry": {"coordinates":[-3.7656929493,40.3843002319],"type":"Point"}
}