{
  "type": "Feature",
  "properties": {
    "addr:full":"Calle de Bastidor, 27 Ejido Almer\u00eda 04700",
    "addr:housenumber":"27 ejido",
    "addr:postcode":"04700",
    "addr:street":"Calle De Bastidor;Almeri\u0301A",
    "iso:country":"ES",
    "sg:address":"Calle de Bastidor, 27",
    "sg:city":"Ejido",
    "sg:orig_category":"Chapister\u00cda",
    "sg:phone":"+34 950 48 07 12",
    "sg:postcode":"04700",
    "sg:province":"Almer\u00eda",
    "wof:name":"Talleres Jose Luis S. C. A.",
    "wof:placetype":"venue"
},
  "geometry": {"coordinates":[-2.7910830975,36.7788696289],"type":"Point"}
}