{
  "type": "Feature",
  "properties": {
    "iso:country":"ES",
    "sg:address":"Calle de Mayor, 33",
    "sg:city":"Burgo Osma",
    "sg:orig_category":"Alimentaci\u00d3n General (al Por Menor)",
    "sg:phone":"+34 975 36 00 18",
    "sg:postcode":"42300",
    "sg:province":"Soria",
    "wof:name":"Alimentacion Consiberlan S.l.",
    "wof:placetype":"venue"
},
  "geometry": {"coordinates":[-3.0687708855,41.5863113403],"type":"Point"}
}