{
  "type": "Feature",
  "properties": {
    "iso:country":"ES",
    "sg:address":"Calle de Beraun, 25",
    "sg:city":"Errenteria",
    "sg:orig_category":"Dise\u00d1o Industrial",
    "sg:phone":"+34 943 52 40 53",
    "sg:postcode":"20100",
    "sg:province":"Guip\u00f9zcoa",
    "wof:name":"Estudel C.b.",
    "wof:placetype":"venue"
},
  "geometry": {"coordinates":[-1.9088089466,43.3093795776],"type":"Point"}
}