{
  "type": "Feature",
  "properties": {
    "iso:country":"ES",
    "sg:address":"Calle de Salvador (el), 10",
    "sg:city":"Roda",
    "sg:orig_category":"Caf\u00c9s, Bares, Cervecer\u00cdas",
    "sg:phone":"+34 967 44 13 04",
    "sg:postcode":"02630",
    "sg:province":"Albacete",
    "wof:name":"Garcia Garcia Juan Carlos",
    "wof:placetype":"venue"
},
  "geometry": {"coordinates":[-2.1608839035,39.2045860291],"type":"Point"}
}