{
  "type": "Feature",
  "properties": {
    "iso:country":"ES",
    "sg:address":"Carrer de Granollers, 12",
    "sg:city":"Vic",
    "sg:orig_category":"Confecci\u00d3n (fabricaci\u00d3n, Al Por Mayor)",
    "sg:phone":"+34 938 89 00 18",
    "sg:postcode":"08500",
    "sg:province":"Barcelona",
    "wof:name":"Trini Soler S.l.",
    "wof:placetype":"venue"
},
  "geometry": {"coordinates":[2.2567338943,41.9428215027],"type":"Point"}
}