{
  "type": "Feature",
  "properties": {
    "addr:full":"Carrer de Marina, 94 Barcelona Barcelona 08018",
    "addr:housenumber":"94",
    "addr:postcode":"08018",
    "addr:street":"Carrer De Marina",
    "iso:country":"ES",
    "sg:address":"Carrer de Marina, 94",
    "sg:city":"Barcelona",
    "sg:orig_category":"M\u00c9dicos: Estomatolog\u00cda",
    "sg:phone":"+34 933 09 69 39",
    "sg:postcode":"08018",
    "sg:province":"Barcelona",
    "wof:name":"Aparicio Gonzalez Carlos",
    "wof:placetype":"venue"
},
  "geometry": {"coordinates":[2.1884338856,41.3937301636],"type":"Point"}
}