{
  "type": "Feature",
  "properties": {
    "iso:country":"ES",
    "sg:address":"Carrer de Arago, 11",
    "sg:city":"Barcelona",
    "sg:orig_category":"Abogados",
    "sg:phone":"+34 932 26 82 44",
    "sg:postcode":"08015",
    "sg:province":"Barcelona",
    "wof:name":"Gabinet Muratet S.l.",
    "wof:placetype":"venue"
},
  "geometry": {"coordinates":[2.1463689804,41.3785476685],"type":"Point"}
}