{
  "type": "Feature",
  "properties": {
    "addr:full":"Calle de Abu Zeyan, 6 Denia Alicante 03700",
    "addr:housenumber":"6",
    "addr:postcode":"03700",
    "addr:street":"Calle De Abu Zeyan",
    "iso:country":"ES",
    "sg:address":"Calle de Abu Zeyan, 6",
    "sg:city":"Denia",
    "sg:orig_category":"Limpieza Con Chorro De Arena Y Con Granalla, Pulido",
    "sg:phone":"+34 965 78 44 98",
    "sg:postcode":"03700",
    "sg:province":"Alicante",
    "wof:name":"Mu\u00f1oz Baeza Mauricio",
    "wof:placetype":"venue"
},
  "geometry": {"coordinates":[0.0840215012,38.8309745789],"type":"Point"}
}