{
  "type": "Feature",
  "properties": {
    "iso:country":"ES",
    "sg:address":"Via Roma, 8",
    "sg:city":"Palma",
    "sg:orig_category":"M\u00c9dicos: An\u00c1lisis Cl\u00cdnicos",
    "sg:phone":"+34 971 71 83 17",
    "sg:postcode":"07012",
    "sg:province":"Islas Baleares",
    "wof:name":"Analisis Biologicos S.l.",
    "wof:placetype":"venue"
},
  "geometry": {"coordinates":[2.6469993591,39.5759506226],"type":"Point"}
}