{
  "type": "Feature",
  "properties": {
    "addr:full":"Avda Benito Galceran, 22 Viveiro Lugo 27850",
    "addr:housenumber":"22",
    "addr:postcode":"27850",
    "addr:street":"Avda Benito Galceran",
    "iso:country":"ES",
    "sg:address":"Avda Benito Galceran, 22",
    "sg:city":"Viveiro",
    "sg:orig_category":"Institutos De Belleza",
    "sg:phone":"+34 982 56 34 97",
    "sg:postcode":"27850",
    "sg:province":"Lugo",
    "wof:name":"Trastoy Bello Cristina",
    "wof:placetype":"venue"
},
  "geometry": {"coordinates":[-7.5926389694,43.6652984619],"type":"Point"}
}