{
  "type": "Feature",
  "properties": {
    "iso:country":"ES",
    "sg:address":"Calle de Carteros, 22",
    "sg:city":"Valencia",
    "sg:orig_category":"Internados & Ense\u00d1anza Privada",
    "sg:phone":"+34 963 77 06 69",
    "sg:postcode":"46017",
    "sg:province":"Valencia",
    "wof:name":"Carpio Barbera Asuncion",
    "wof:placetype":"venue"
},
  "geometry": {"coordinates":[-0.3880766928,39.4538154602],"type":"Point"}
}