{
  "type": "Feature",
  "properties": {
    "addr:full":"Avda Reyes Catolicos, 22 Burgos Burgos 09005",
    "addr:housenumber":"22",
    "addr:postcode":"09005",
    "addr:street":"Avda Reyes Catolicos",
    "iso:country":"ES",
    "sg:address":"Avda Reyes Catolicos, 22",
    "sg:city":"Burgos",
    "sg:orig_category":"Ense\u00d1ante, Direcci\u00d3n",
    "sg:phone":"+34 947 22 01 91",
    "sg:postcode":"09005",
    "sg:province":"Burgos",
    "wof:name":"Bordallo Alaiz Carlos Manuel",
    "wof:placetype":"venue"
},
  "geometry": {"coordinates":[-3.6933948994,42.3471069336],"type":"Point"}
}