{
  "type": "Feature",
  "properties": {
    "iso:country":"ES",
    "sg:address":"Avda Juan Carlos I, 46",
    "sg:city":"Fernan Nu\u00e7ez",
    "sg:orig_category":"Veh\u00cdculos De Ocasi\u00d3n",
    "sg:phone":"+34 957 38 02 08",
    "sg:postcode":"14520",
    "sg:province":"C\u00f3rdoba",
    "wof:name":"Miranda Llamas Antonio",
    "wof:placetype":"venue"
},
  "geometry": {"coordinates":[-4.7143359184,37.6636161804],"type":"Point"}
}