{
  "type": "Feature",
  "properties": {
    "iso:country":"ES",
    "sg:address":"Calle de Ramon Lujan, 63",
    "sg:city":"Madrid",
    "sg:orig_category":"Bisuter\u00cda, Joyer\u00cda, Relojer\u00cda (al Por Menor)",
    "sg:phone":"+34 914 75 28 13",
    "sg:postcode":"28026",
    "sg:province":"Madrid",
    "wof:name":"Sanz Santander Eustasio",
    "wof:placetype":"venue"
},
  "geometry": {"coordinates":[-3.7040739059,40.3841972351],"type":"Point"}
}