{
  "type": "Feature",
  "properties": {
    "iso:country":"ES",
    "sg:address":"Carr Santa Teresa, 14",
    "sg:city":"Pu\u00e7ol",
    "sg:orig_category":"Abogados",
    "sg:phone":"+34 961 42 32 27",
    "sg:postcode":"46530",
    "sg:province":"Valencia",
    "wof:name":"Serrulla Carceller Lourdes",
    "wof:placetype":"venue"
},
  "geometry": {"coordinates":[-0.3085449934,39.6161003113],"type":"Point"}
}