{
  "type": "Feature",
  "properties": {
    "iso:country":"ES",
    "sg:address":"Calle de Valencia (de), 17",
    "sg:city":"Fuenlabrada",
    "sg:orig_category":"Peluqueros: De Se\u00d1oras",
    "sg:phone":"+34 916 97 99 51",
    "sg:postcode":"28945",
    "sg:province":"Madrid",
    "wof:name":"Alonso Gomez Aurora",
    "wof:placetype":"venue"
},
  "geometry": {"coordinates":[-3.7921464443,40.292591095],"type":"Point"}
}