{
  "type": "Feature",
  "properties": {
    "iso:country":"ES",
    "sg:address":"Calle de Garibai, 36",
    "sg:city":"Donostia-san Sebastian",
    "sg:orig_category":"Asesor\u00cda Sobre Comunicaci\u00d3n De Empresas",
    "sg:phone":"+34 943 42 55 57",
    "sg:postcode":"20004",
    "sg:province":"Guip\u00f9zcoa",
    "wof:name":"Federacion Mercantil De Guipuzcoa",
    "wof:placetype":"venue"
},
  "geometry": {"coordinates":[-1.9826624393,43.319480896],"type":"Point"}
}