{
  "type": "Feature",
  "properties": {
    "addr:full":"Calle de Mayor, 47 Najera La Rioja 26300",
    "addr:housenumber":"47",
    "addr:postcode":"26300",
    "addr:street":"Calle De Mayor;Rioja",
    "iso:country":"ES",
    "sg:address":"Calle de Mayor, 47",
    "sg:city":"Najera",
    "sg:orig_category":"Estancos",
    "sg:phone":"+34 941 36 00 92",
    "sg:postcode":"26300",
    "sg:province":"La Rioja",
    "wof:name":"Fernandez Serrano Adolfo",
    "wof:placetype":"venue"
},
  "geometry": {"coordinates":[-2.7335910797,42.4171905518],"type":"Point"}
}