{
  "type": "Feature",
  "properties": {
    "iso:country":"ES",
    "sg:address":"Calle de Baco, 20",
    "sg:city":"Torrejon Ardoz",
    "sg:orig_category":"Contenedores (mercanc\u00cdas)",
    "sg:phone":"+34 916 56 22 17",
    "sg:postcode":"28850",
    "sg:province":"Madrid",
    "wof:name":"Transportes Almarza Pozo S.l.",
    "wof:placetype":"venue"
},
  "geometry": {"coordinates":[-3.4757428169,40.4464912415],"type":"Point"}
}