{
  "type": "Feature",
  "properties": {
    "iso:country":"ES",
    "sg:address":"C/ Pompeu Fabra, 2",
    "sg:city":"Guingueta",
    "sg:orig_category":"Panader\u00cdas, Panader\u00cdas",
    "sg:phone":"+34 972 88 10 98",
    "sg:postcode":"17520",
    "sg:province":"Girona",
    "wof:name":"Forn Moya S.l.",
    "wof:placetype":"venue"
},
  "geometry": {"coordinates":[1.9278999567,42.4336547852],"type":"Point"}
}