{
  "type": "Feature",
  "properties": {
    "iso:country":"ES",
    "sg:address":"Calle de Torres Miranda, 16",
    "sg:city":"Madrid",
    "sg:orig_category":"Bazares, Art\u00cdculos De Limpieza Y De Cocina (al Por Menor)",
    "sg:phone":"+34 914 74 21 44",
    "sg:postcode":"28045",
    "sg:province":"Madrid",
    "wof:name":"Trishul Import S.l.",
    "wof:placetype":"venue"
},
  "geometry": {"coordinates":[-3.6999740601,40.3981399536],"type":"Point"}
}