{
  "type": "Feature",
  "properties": {
    "iso:country":"ES",
    "sg:address":"C/ Menor, 10",
    "sg:city":"Alaior",
    "sg:orig_category":"Inmobiliaria (agencias)",
    "sg:phone":"+34 971 37 21 05",
    "sg:postcode":"07730",
    "sg:province":"Islas Baleares",
    "wof:name":"Triay Enrich Maria Del Mar",
    "wof:placetype":"venue"
},
  "geometry": {"coordinates":[4.1395559311,39.934211731],"type":"Point"}
}