{
  "type": "Feature",
  "properties": {
    "addr:full":"Ctra Guadarrama (de), Km. 0005,2 Galapagar Madrid 28260",
    "addr:postcode":"28260",
    "addr:street":"Ctra Guadarrama De Km. 0005,2",
    "iso:country":"ES",
    "sg:address":"Ctra Guadarrama (de), Km. 0005,2",
    "sg:city":"Galapagar",
    "sg:orig_category":"Semiller\u00cdas",
    "sg:phone":"+34 918 58 42 05",
    "sg:postcode":"28260",
    "sg:province":"Madrid",
    "wof:name":"Somolinos S.l.",
    "wof:placetype":"venue"
},
  "geometry": {"coordinates":[-4.0102529526,40.5761680603],"type":"Point"}
}