{
  "type": "Feature",
  "properties": {
    "addr:full":"Av El Textil, 34 Ontinyent Valencia 46870",
    "addr:housenumber":"34",
    "addr:postcode":"46870",
    "addr:street":"Av El Textil",
    "iso:country":"ES",
    "sg:address":"Av El Textil, 34",
    "sg:city":"Ontinyent",
    "sg:orig_category":"Telas (al Por Mayor)",
    "sg:phone":"+34 962 91 70 82",
    "sg:postcode":"46870",
    "sg:province":"Valencia",
    "sg:website":"www.textil.org/induflec",
    "wof:name":"Induflec S.l.",
    "wof:placetype":"venue"
},
  "geometry": {"coordinates":[-0.5998409986,38.8257369995],"type":"Point"}
}