{
  "type": "Feature",
  "properties": {
    "addr:full":"Calle de Huerto San Pedro El Real, S/n Cordoba C\u00f3rdoba 14003",
    "addr:housenumber":"s / n",
    "addr:postcode":"14003",
    "addr:street":"Calle De Huerto San Pedro El Real;Co\u0301Rdoba",
    "iso:country":"ES",
    "sg:address":"Calle de Huerto San Pedro El Real, S/n",
    "sg:city":"Cordoba",
    "sg:orig_category":"Fabricaci\u00d3n De Bolsos Y Bolsos De Tela",
    "sg:phone":"+34 957 47 48 23",
    "sg:postcode":"14003",
    "sg:province":"C\u00f3rdoba",
    "wof:name":"Abad Martin Jose Antonio",
    "wof:placetype":"venue"
},
  "geometry": {"coordinates":[-4.775972,37.882343],"type":"Point"}
}