{
  "type": "Feature",
  "properties": {
    "addr:full":"Calle de Oterin, S/n Acebedo Le\u00f3n 24996",
    "addr:housenumber":"s",
    "addr:postcode":"24996",
    "addr:street":"Calle De Oterin;/ N Acebedo Leo\u0301N",
    "iso:country":"ES",
    "sg:address":"Calle de Oterin, S/n",
    "sg:city":"Acebedo",
    "sg:orig_category":"Centros De Educaci\u00d3n Especial",
    "sg:phone":"+34 987 74 00 01",
    "sg:postcode":"24996",
    "sg:province":"Le\u00f3n",
    "wof:name":"C.r.a. De Ria\u00f1o",
    "wof:placetype":"venue"
},
  "geometry": {"coordinates":[-5.1165280342,43.0387878418],"type":"Point"}
}