{
  "type": "Feature",
  "properties": {
    "iso:country":"ES",
    "sg:address":"Calle de Rio Eo, 15",
    "sg:city":"Gijon",
    "sg:orig_category":"Alquiler De V\u00cddeo",
    "sg:phone":"+34 985 14 16 12",
    "sg:postcode":"33210",
    "sg:province":"Asturias",
    "wof:name":"Allendeastur S.l.",
    "wof:placetype":"venue"
},
  "geometry": {"coordinates":[-5.677052021,43.5258636475],"type":"Point"}
}