{
  "type": "Feature",
  "properties": {
    "addr:full":"Carr Canigo, 33 Puig De Sant Ramon Girona 17111",
    "addr:housenumber":"33",
    "addr:postcode":"17111",
    "addr:street":"Carr Canigo",
    "iso:country":"ES",
    "sg:address":"Carr Canigo, 33",
    "sg:city":"Puig De Sant Ramon",
    "sg:orig_category":"Centros Empresariales",
    "sg:phone":"+34 972 64 48 12",
    "sg:postcode":"17111",
    "sg:province":"Girona",
    "wof:name":"Mauri Rodriguez Arturo",
    "wof:placetype":"venue"
},
  "geometry": {"coordinates":[3.054970026,41.9602890015],"type":"Point"}
}