{
  "type": "Feature",
  "properties": {
    "iso:country":"ES",
    "sg:address":"Calle de Barrio Nuevo, 5",
    "sg:city":"Talavera Reina",
    "sg:orig_category":"Loter\u00cda Y T\u00d3mbola",
    "sg:phone":"+34 925 80 13 60",
    "sg:postcode":"45600",
    "sg:province":"Toledo",
    "wof:name":"Campos Rubalcaba Maria Del Carmen",
    "wof:placetype":"venue"
},
  "geometry": {"coordinates":[-4.8293423653,39.9623298645],"type":"Point"}
}