{
  "type": "Feature",
  "properties": {
    "iso:country":"ES",
    "sg:address":"Calle de Sepulveda (de), 6",
    "sg:city":"Alcobendas",
    "sg:orig_category":"Laboratorios Farmac\u00c9uticos",
    "sg:phone":"+34 916 61 42 38",
    "sg:postcode":"28108",
    "sg:province":"Madrid",
    "wof:name":"Novamed Laboratorios S.l.",
    "wof:placetype":"venue"
},
  "geometry": {"coordinates":[-3.6554989815,40.5267829895],"type":"Point"}
}