{
  "type": "Feature",
  "properties": {
    "iso:country":"ES",
    "sg:address":"Calle de Hernani, 13",
    "sg:city":"Madrid",
    "sg:orig_category":"Peluquer\u00cdas, Peluquer\u00cda Mixta",
    "sg:phone":"+34 915 53 20 42",
    "sg:postcode":"28020",
    "sg:province":"Madrid",
    "wof:name":"Peralta Peral Rafael",
    "wof:placetype":"venue"
},
  "geometry": {"coordinates":[-3.7024912834,40.4483718872],"type":"Point"}
}