{
  "type": "Feature",
  "properties": {
    "iso:country":"ES",
    "sg:address":"Atv Madrid-toledo, Km. 0032,8",
    "sg:city":"Illescas",
    "sg:orig_category":"Artes Gr\u00c1ficas, Artes Pl\u00c1sticas (curso)",
    "sg:phone":"+34 925 51 15 02",
    "sg:postcode":"45200",
    "sg:province":"Toledo",
    "wof:name":"Inmagrag S.l.",
    "wof:placetype":"venue"
},
  "geometry": {"coordinates":[-3.8458640575,40.1230163574],"type":"Point"}
}