{
  "type": "Feature",
  "properties": {
    "addr:full":"Avda Miguel Manche\u00d1o, 28 Arcos Frontera C\u00e1diz 11630",
    "addr:housenumber":"28",
    "addr:postcode":"11630",
    "addr:street":"Avda Miguel Manchen\u0303O",
    "iso:country":"ES",
    "sg:address":"Avda Miguel Manche\u00d1o, 28",
    "sg:city":"Arcos Frontera",
    "sg:orig_category":"Delegados, Agentes De Tr\u00c1nsito, Auxiliares De Transporte Internacional",
    "sg:phone":"+34 956 70 31 61",
    "sg:postcode":"11630",
    "sg:province":"C\u00e1diz",
    "wof:name":"Arcos Soluciones S.l.",
    "wof:placetype":"venue"
},
  "geometry": {"coordinates":[-5.815849781,36.7508163452],"type":"Point"}
}