{
  "type": "Feature",
  "properties": {
    "addr:full":"Calle de Albia De Castro, 3 Logro\u00f1o La Rioja 26003",
    "addr:housenumber":"3",
    "addr:postcode":"26003",
    "addr:street":"Calle De Albia De Castro;Rioja",
    "iso:country":"ES",
    "sg:address":"Calle de Albia De Castro, 3",
    "sg:city":"Logro\u00f1o",
    "sg:orig_category":"Centros Empresariales",
    "sg:phone":"+34 941 24 01 75",
    "sg:postcode":"26003",
    "sg:province":"La Rioja",
    "wof:name":"Vanesa Del Castillo Y Otra S.c.",
    "wof:placetype":"venue"
},
  "geometry": {"coordinates":[-2.4364700317,42.4642677307],"type":"Point"}
}