{
  "type": "Feature",
  "properties": {
    "addr:full":"Praz Angustias, S/n Ferrol La Coru\u00f1a 15403",
    "addr:housenumber":"s / n",
    "addr:postcode":"15403",
    "addr:street":"Praz Angustias;La Corun\u0303A",
    "iso:country":"ES",
    "sg:address":"Praz Angustias, S/n",
    "sg:city":"Ferrol",
    "sg:classifiers":[
        {
            "category":"Recreation",
            "type":"Entertainment"
        }
    ],
    "sg:phone":"+34 981 35 26 15",
    "sg:postcode":"15403",
    "sg:province":"La Coru\u00f1a",
    "sg:tags":[
        "caza",
        "pr\u00c1ctica",
        "la",
        "de",
        "pesca",
        "y"
    ],
    "wof:name":"Cofradia De Las Angustias",
    "wof:placetype":"venue"
},
  "geometry": {"coordinates":[-8.229596138,43.4833717346],"type":"Point"}
}