{
  "type": "Feature",
  "properties": {
    "addr:full":"Calle de Santa Maria, 8 Zaratan Valladolid 47610",
    "addr:housenumber":"8",
    "addr:postcode":"47610",
    "addr:street":"Calle De Santa Maria",
    "iso:country":"ES",
    "sg:address":"Calle de Santa Maria, 8",
    "sg:city":"Zaratan",
    "sg:orig_category":"Dibujantes (diversos)",
    "sg:phone":"+34 983 35 22 45",
    "sg:postcode":"47610",
    "sg:province":"Valladolid",
    "wof:name":"Garcia Garcia Mauricio",
    "wof:placetype":"venue"
},
  "geometry": {"coordinates":[-4.7843441963,41.659450531],"type":"Point"}
}