{
  "type": "Feature",
  "properties": {
    "addr:full":"Joan Cast. Guasch, 37 Pujols Islas Baleares 07871",
    "addr:housenumber":"37",
    "addr:postcode":"07871",
    "addr:street":"Guasch",
    "iso:country":"ES",
    "sg:address":"Joan Cast. Guasch, 37",
    "sg:city":"Pujols",
    "sg:orig_category":"Fabricaci\u00d3n, Venta, Instalaci\u00d3n De R\u00d3tulos, De R\u00d3tulos Luminosos",
    "sg:phone":"+34 971 32 88 72",
    "sg:postcode":"07871",
    "sg:province":"Islas Baleares",
    "wof:name":"Ferrer Mayans Jose",
    "wof:placetype":"venue"
},
  "geometry": {"coordinates":[1.4565550089,38.7221031189],"type":"Point"}
}