{
  "type": "Feature",
  "properties": {
    "iso:country":"ES",
    "sg:address":"Plaz Adelfas (las), 9",
    "sg:city":"San Andres",
    "sg:orig_category":"Alimentaci\u00d3n General (al Por Menor)",
    "sg:phone":"+34 922 59 12 85",
    "sg:postcode":"38120",
    "sg:province":"Santa Cruz De Tenerife",
    "wof:name":"Comunidad De Bienes Las Adelfas",
    "wof:placetype":"venue"
},
  "geometry": {"coordinates":[-16.1991291046,28.498884201],"type":"Point"}
}