{
  "type": "Feature",
  "properties": {
    "iso:country":"ES",
    "sg:address":"Ctra. General, 8",
    "sg:city":"Costa Del Silencio",
    "sg:orig_category":"Centros Empresariales",
    "sg:phone":"+34 922 73 10 92",
    "sg:postcode":"38630",
    "sg:province":"Santa Cruz De Tenerife",
    "wof:name":"Albornoz Siverio Angel Atilio",
    "wof:placetype":"venue"
},
  "geometry": {"coordinates":[-16.6419448853,28.0056381226],"type":"Point"}
}