{
  "type": "Feature",
  "properties": {
    "addr:full":"Sector Oleum, 44 Villa Rio C\u00f3rdoba 14640",
    "addr:housenumber":"44",
    "addr:postcode":"14640",
    "addr:street":"Sector Oleum;Rio Co\u0301Rdoba",
    "iso:country":"ES",
    "sg:address":"Sector Oleum, 44",
    "sg:city":"Villa Rio",
    "sg:orig_category":"Estudios, Instalaci\u00d3n De Climatizaci\u00d3n",
    "sg:phone":"+34 957 17 66 26",
    "sg:postcode":"14640",
    "sg:province":"C\u00f3rdoba",
    "sg:website":"www.tecniconfort.com",
    "wof:name":"Tecniconfort Juanjo S.l.",
    "wof:placetype":"venue"
},
  "geometry": {"coordinates":[-4.2970790863,37.9829101562],"type":"Point"}
}