{
  "type": "Feature",
  "properties": {
    "iso:country":"ES",
    "sg:address":"Cami Arenes (de Les), S/n",
    "sg:city":"Tortosa",
    "sg:orig_category":"Fabricaci\u00d3n De Moldes Y Modelos",
    "sg:phone":"+34 977 44 37 75",
    "sg:postcode":"43500",
    "sg:province":"Tarragona",
    "wof:name":"Plasticos Castella S.a.",
    "wof:placetype":"venue"
},
  "geometry": {"coordinates":[0.5217999816,40.7844200134],"type":"Point"}
}