{
  "type": "Feature",
  "properties": {
    "addr:full":"Avda Palmeras (de Las), S/n Villanueva Ariscal Sevilla 41808",
    "addr:postcode":"41808",
    "addr:street":"Avda Palmeras De Las S / N",
    "iso:country":"ES",
    "sg:address":"Avda Palmeras (de Las), S/n",
    "sg:city":"Villanueva Ariscal",
    "sg:orig_category":"Muebles Y Accesorios Para Cocinas Y Cuartos De Ba\u00d1o (al Por Menor)",
    "sg:phone":"+34 954 11 42 90",
    "sg:postcode":"41808",
    "sg:province":"Sevilla",
    "wof:name":"Muebles Casa Probo S.l.",
    "wof:placetype":"venue"
},
  "geometry": {"coordinates":[-6.1437211037,37.395149231],"type":"Point"}
}