{
  "type": "Feature",
  "properties": {
    "iso:country":"ES",
    "sg:address":"Calle de General Urrutia, 18",
    "sg:city":"Valencia",
    "sg:orig_category":"Fabricaci\u00d3n, Distribuci\u00d3n De Discos, V\u00cddeodiscos Y Musicassettes",
    "sg:phone":"+34 963 73 34 60",
    "sg:postcode":"46006",
    "sg:province":"Valencia",
    "sg:website":"www.houseofrock.tk",
    "wof:name":"Gonzalez Edo David",
    "wof:placetype":"venue"
},
  "geometry": {"coordinates":[-0.3655293882,39.4596595764],"type":"Point"}
}