{
  "type": "Feature",
  "properties": {
    "iso:country":"ES",
    "sg:address":"Calle de Madre De Dios, 16",
    "sg:city":"Logro\u00f1o",
    "sg:orig_category":"Tintorer\u00cdas, Limpieza En Seco",
    "sg:phone":"+34 941 24 49 83",
    "sg:postcode":"26004",
    "sg:province":"La Rioja",
    "wof:name":"Plaza Martinez Miguel Angel",
    "wof:placetype":"venue"
},
  "geometry": {"coordinates":[-2.436745882,42.4692306519],"type":"Point"}
}