{
  "type": "Feature",
  "properties": {
    "addr:full":"Calle de Real De Cartuja, 7 Granada Granada 18012",
    "addr:housenumber":"7",
    "addr:postcode":"18012",
    "addr:street":"Calle De Real De Cartuja",
    "iso:country":"ES",
    "sg:address":"Calle de Real De Cartuja, 7",
    "sg:city":"Granada",
    "sg:orig_category":"Doctores En Medicina",
    "sg:phone":"+34 958 27 33 14",
    "sg:postcode":"18012",
    "sg:province":"Granada",
    "wof:name":"Oyonarte Gomez Salvador Andres",
    "wof:placetype":"venue"
},
  "geometry": {"coordinates":[-3.6027469635,37.1861915588],"type":"Point"}
}