{
  "type": "Feature",
  "properties": {
    "iso:country":"ES",
    "sg:address":"Avda Salud (de La), 30",
    "sg:city":"Moralzarzal",
    "sg:orig_category":"Porcelanas, Azulejos (fabricaci\u00d3n, Al Por Mayor)",
    "sg:phone":"+34 918 57 79 67",
    "sg:postcode":"28411",
    "sg:province":"Madrid",
    "wof:name":"Jimenez Morato Maria Pilar",
    "wof:placetype":"venue"
},
  "geometry": {"coordinates":[-3.9699749947,40.6771736145],"type":"Point"}
}