{
  "type": "Feature",
  "properties": {
    "iso:country":"ES",
    "sg:address":"Avda Juan Carlos I, 35",
    "sg:city":"Torres Cotillas",
    "sg:orig_category":"Mec\u00c1nico Del Autom\u00d3vil",
    "sg:phone":"+34 968 62 34 64",
    "sg:postcode":"30565",
    "sg:province":"Murcia",
    "wof:name":"Lopez Munuera Jose Tomas",
    "wof:placetype":"venue"
},
  "geometry": {"coordinates":[-1.2452189922,38.0195732117],"type":"Point"}
}