{
  "type": "Feature",
  "properties": {
    "iso:country":"ES",
    "sg:address":"Calle de Cami Cebolla, 30",
    "sg:city":"Rafelbunyol",
    "sg:orig_category":"Fabricaci\u00d3n De Moldes Y Modelos",
    "sg:phone":"+34 961 41 21 85",
    "sg:postcode":"46138",
    "sg:province":"Valencia",
    "wof:name":"Sanvi E Hijas Matriceria Y Estampacion S.l.",
    "wof:placetype":"venue"
},
  "geometry": {"coordinates":[-0.3231950104,39.5863723755],"type":"Point"}
}