{
  "type": "Feature",
  "properties": {
    "addr:full":"Calle de Eras De San Francisco, 21 Torrijos Toledo 45500",
    "addr:housenumber":"21",
    "addr:postcode":"45500",
    "addr:street":"Calle De Eras De San Francisco",
    "iso:country":"ES",
    "sg:address":"Calle de Eras De San Francisco, 21",
    "sg:city":"Torrijos",
    "sg:orig_category":"Fabricaci\u00d3n De Cortinas Y Visillos",
    "sg:phone":"+34 925 77 13 82",
    "sg:postcode":"45500",
    "sg:province":"Toledo",
    "wof:name":"La Paloma Azul C.b.",
    "wof:placetype":"venue"
},
  "geometry": {"coordinates":[-4.2810292244,39.9793510437],"type":"Point"}
}