{
  "type": "Feature",
  "properties": {
    "addr:full":"Carr Dels Germans De Les Escoles Cristianes, 39 Benicarlo Castell\u00f3n 12580",
    "addr:housenumber":"39",
    "addr:postcode":"12580",
    "addr:street":"Carr Dels Germans De Les Escoles Cristianes",
    "iso:country":"ES",
    "sg:address":"Carr Dels Germans De Les Escoles Cristianes, 39",
    "sg:city":"Benicarlo",
    "sg:orig_category":"Cooperativas Agr\u00cdcolas",
    "sg:phone":"+34 964 46 18 41",
    "sg:postcode":"12580",
    "sg:province":"Castell\u00f3n",
    "wof:name":"Centro Aragones De Benicarlo",
    "wof:placetype":"venue"
},
  "geometry": {"coordinates":[0.4042100012,40.4457893372],"type":"Point"}
}