{
  "type": "Feature",
  "properties": {
    "iso:country":"ES",
    "sg:address":"Avda Manuel Siurot, S/n",
    "sg:city":"Sevilla",
    "sg:orig_category":"Florister\u00cdas",
    "sg:phone":"+34 954 62 47 52",
    "sg:postcode":"41013",
    "sg:province":"Sevilla",
    "wof:name":"Real Suarez Fernando",
    "wof:placetype":"venue"
},
  "geometry": {"coordinates":[-5.9841041565,37.3656959534],"type":"Point"}
}