{
  "type": "Feature",
  "properties": {
    "iso:country":"ES",
    "sg:address":"Calle de Carteros, 4",
    "sg:city":"Valencia",
    "sg:orig_category":"Panader\u00cdas, Panader\u00cdas",
    "sg:phone":"+34 963 57 35 48",
    "sg:postcode":"46007",
    "sg:province":"Valencia",
    "wof:name":"Lasso Sanchez Rafael",
    "wof:placetype":"venue"
},
  "geometry": {"coordinates":[-0.3870589137,39.4551124573],"type":"Point"}
}