{
  "type": "Feature",
  "properties": {
    "addr:full":"Punta De Lugar, S/n Cueva De Agreda Soria 42107",
    "addr:housenumber":"s / n",
    "addr:postcode":"42107",
    "addr:street":"Punta;Lugar",
    "iso:country":"ES",
    "sg:address":"Punta De Lugar, S/n",
    "sg:city":"Cueva De Agreda",
    "sg:orig_category":"Alquiler De Casas Y Habitaciones Amuebladas",
    "sg:phone":"+34 976 64 60 50",
    "sg:postcode":"42107",
    "sg:province":"Soria",
    "wof:name":"El Vallejuelo",
    "wof:placetype":"venue"
},
  "geometry": {"coordinates":[-1.8961429596,41.6645431519],"type":"Point"}
}