{
  "type": "Feature",
  "properties": {
    "addr:full":"Carrer de Cervantes, 83 Rubi Barcelona 08191",
    "addr:housenumber":"83",
    "addr:postcode":"08191",
    "addr:street":"Carrer De Cervantes",
    "iso:country":"ES",
    "sg:address":"Carrer de Cervantes, 83",
    "sg:city":"Rubi",
    "sg:orig_category":"Asociaciones Y Clubs Deportivos",
    "sg:phone":"+34 936 97 09 08",
    "sg:postcode":"08191",
    "sg:province":"Barcelona",
    "wof:name":"Montserrat Cebrian Maria Gloria",
    "wof:placetype":"venue"
},
  "geometry": {"coordinates":[2.0341510773,41.488155365],"type":"Point"}
}