{
  "type": "Feature",
  "properties": {
    "addr:full":"Carr Guadassuar, 64 Alcudia Valencia 46250",
    "addr:housenumber":"64",
    "addr:postcode":"46250",
    "addr:street":"Carr Guadassuar",
    "iso:country":"ES",
    "sg:address":"Carr Guadassuar, 64",
    "sg:city":"Alcudia",
    "sg:orig_category":"Electricidad: Instaladores",
    "sg:phone":"+34 962 54 11 30",
    "sg:postcode":"46250",
    "sg:province":"Valencia",
    "wof:name":"Electricidad L'alcudia S.l.",
    "wof:placetype":"venue"
},
  "geometry": {"coordinates":[-0.5070289969,39.1940689087],"type":"Point"}
}