{
  "type": "Feature",
  "properties": {
    "iso:country":"ES",
    "sg:address":"Calle de Mentrida, 46",
    "sg:city":"Valmojado",
    "sg:orig_category":"Fabricaci\u00d3n De Art\u00cdculos Y Equipos Deportivos Y De Ocio",
    "sg:phone":"+34 918 17 09 22",
    "sg:postcode":"45940",
    "sg:province":"Toledo",
    "wof:name":"Desarrollo De Equipos Militares S.l.",
    "wof:placetype":"venue"
},
  "geometry": {"coordinates":[-4.0940179825,40.2049980164],"type":"Point"}
}