{
  "type": "Feature",
  "properties": {
    "iso:country":"ES",
    "sg:address":"Av Bisbe Llompart, 30",
    "sg:city":"Inca",
    "sg:orig_category":"Cajas De Ahorro",
    "sg:phone":"+34 971 50 00 60",
    "sg:postcode":"07300",
    "sg:province":"Islas Baleares",
    "sg:website":"www.lacaixa.es",
    "wof:name":"Caixa D'estalvis I Pensions De Barcelona",
    "wof:placetype":"venue"
},
  "geometry": {"coordinates":[2.9086830616,39.7206916809],"type":"Point"}
}