{
  "type": "Feature",
  "properties": {
    "iso:country":"ES",
    "sg:address":"Extramuros, S/n",
    "sg:city":"Simancas",
    "sg:orig_category":"Asociaciones, Organismos Culturales Y Socioeducativos",
    "sg:phone":"+34 983 59 01 11",
    "sg:postcode":"47130",
    "sg:province":"Valladolid",
    "wof:name":"Centro Cultural Aldebaran",
    "wof:placetype":"venue"
},
  "geometry": {"coordinates":[-4.8235812187,41.5907974243],"type":"Point"}
}