{
  "type": "Feature",
  "properties": {
    "iso:country":"ES",
    "sg:address":"Avgd De Juan Sebastian Elcano, S/n",
    "sg:city":"Benicarlo",
    "sg:orig_category":"Electricidad Veh\u00cdculo",
    "sg:phone":"+34 964 46 11 44",
    "sg:postcode":"12580",
    "sg:province":"Castell\u00f3n",
    "wof:name":"Meseguer Pio Manuel",
    "wof:placetype":"venue"
},
  "geometry": {"coordinates":[0.4042100012,40.4457893372],"type":"Point"}
}