{
  "type": "Feature",
  "properties": {
    "addr:full":"Calle de Torpedero Tucuman, 14 Madrid Madrid 28016",
    "addr:housenumber":"14",
    "addr:postcode":"madrid;28016",
    "addr:street":"Calle De Torpedero Tucuman",
    "iso:country":"ES",
    "sg:address":"Calle de Torpedero Tucuman, 14",
    "sg:city":"Madrid",
    "sg:orig_category":"Centros Empresariales",
    "sg:phone":"+34 913 45 27 78",
    "sg:postcode":"28016",
    "sg:province":"Madrid",
    "wof:name":"Perez Gomez Carlos",
    "wof:placetype":"venue"
},
  "geometry": {"coordinates":[-3.6727490425,40.4617538452],"type":"Point"}
}