{
  "type": "Feature",
  "properties": {
    "addr:full":"Carr Costa Magdalena, 2 Lleida Lleida 25007",
    "addr:housenumber":"2",
    "addr:postcode":"25007",
    "addr:street":"Carr Costa Magdalena",
    "iso:country":"ES",
    "sg:address":"Carr Costa Magdalena, 2",
    "sg:city":"Lleida",
    "sg:orig_category":"Ingenier\u00cda, Centros De Estudios (diversos)",
    "sg:phone":"+34 973 72 70 14",
    "sg:postcode":"25007",
    "sg:province":"Lleida",
    "wof:name":"Kubic Consultoria Tecnica S.l.",
    "wof:placetype":"venue"
},
  "geometry": {"coordinates":[0.6285889745,41.6193237305],"type":"Point"}
}