{
  "type": "Feature",
  "properties": {
    "iso:country":"ES",
    "sg:address":"Calle de Victor Pe\u00d1asco (don), 57",
    "sg:city":"Tomelloso",
    "sg:orig_category":"Sociedades, Compa\u00d1\u00cdas Aseguradoras",
    "sg:phone":"+34 926 50 57 54",
    "sg:postcode":"13700",
    "sg:province":"Ciudad Real",
    "sg:website":"www.webmancha.com/ageseman",
    "wof:name":"Ageseman S.l.",
    "wof:placetype":"venue"
},
  "geometry": {"coordinates":[-3.0228462219,39.1551933289],"type":"Point"}
}