{
  "type": "Feature",
  "properties": {
    "iso:country":"ES",
    "sg:address":"Rua Sagasta, 1",
    "sg:city":"Pontevedra",
    "sg:orig_category":"M\u00c9dicos: Estomatolog\u00cda",
    "sg:phone":"+34 986 84 46 66",
    "sg:postcode":"36001",
    "sg:province":"Pontevedra",
    "wof:name":"Leiros De La Pe\u00f1a Alfonso",
    "wof:placetype":"venue"
},
  "geometry": {"coordinates":[-8.6419563293,42.4286994934],"type":"Point"}
}