{
  "type": "Feature",
  "properties": {
    "iso:country":"ES",
    "sg:address":"Calle de Moralejo, 27",
    "sg:city":"Aguilar De La Frontera",
    "sg:orig_category":"Notarios",
    "sg:phone":"+34 957 66 08 14",
    "sg:postcode":"14920",
    "sg:province":"C\u00f3rdoba",
    "wof:name":"Candil Bergillos Francisco",
    "wof:placetype":"venue"
},
  "geometry": {"coordinates":[-4.657638073,37.5158805847],"type":"Point"}
}