{
  "type": "Feature",
  "properties": {
    "iso:country":"ES",
    "sg:address":"Kale Nagusia, 5",
    "sg:city":"Legorreta",
    "sg:orig_category":"Reposter\u00cdas",
    "sg:phone":"+34 943 80 60 70",
    "sg:postcode":"20250",
    "sg:province":"Guip\u00f9zcoa",
    "wof:name":"Isabel Arregui Elosegui",
    "wof:placetype":"venue"
},
  "geometry": {"coordinates":[-2.1474490166,43.0848770142],"type":"Point"}
}