{
  "type": "Feature",
  "properties": {
    "addr:full":"Urb Vi\u00f1as, 1 Lora Rio Sevilla 41440",
    "addr:housenumber":"1",
    "addr:postcode":"41440",
    "addr:street":"Urb Vin\u0303As;Rio Sevilla",
    "iso:country":"ES",
    "sg:address":"Urb Vi\u00f1as, 1",
    "sg:city":"Lora Rio",
    "sg:orig_category":"Molduras, Junquillos, Listones Y Molduras Perforadas",
    "sg:phone":"+34 955 80 09 88",
    "sg:postcode":"41440",
    "sg:province":"Sevilla",
    "wof:name":"Cebagueba Rodriguez Antonio Jose",
    "wof:placetype":"venue"
},
  "geometry": {"coordinates":[-5.5281839371,37.659828186],"type":"Point"}
}