{
  "type": "Feature",
  "properties": {
    "iso:country":"ES",
    "sg:address":"Calle de Lima (de), 44",
    "sg:city":"Fuenlabrada",
    "sg:orig_category":"Inform\u00c1tica (estudios, Servicios, Asesor\u00cda, Formaci\u00d3n)",
    "sg:phone":"+34 916 15 28 46",
    "sg:postcode":"28945",
    "sg:province":"Madrid",
    "wof:name":"Sur Punto 4 S.l.",
    "wof:placetype":"venue"
},
  "geometry": {"coordinates":[-3.7889788151,40.2915649414],"type":"Point"}
}