{
  "type": "Feature",
  "properties": {
    "iso:country":"ES",
    "sg:address":"Rincon De Soto, 12",
    "sg:city":"Alfaro",
    "sg:orig_category":"Instalaci\u00d3n De Aspiraci\u00d3n De Gases Y Humos",
    "sg:phone":"+34 941 18 27 52",
    "sg:postcode":"26540",
    "sg:province":"La Rioja",
    "wof:name":"Multiservicios Planes S.l.",
    "wof:placetype":"venue"
},
  "geometry": {"coordinates":[-1.7652939558,42.1848106384],"type":"Point"}
}