{
  "type": "Feature",
  "properties": {
    "iso:country":"ES",
    "sg:address":"Carrer de Princep De Bergara, 70",
    "sg:city":"Hospitalet Llobregat",
    "sg:orig_category":"Arquitectos",
    "sg:phone":"+34 933 37 27 71",
    "sg:postcode":"08901",
    "sg:province":"Barcelona",
    "wof:name":"Padros Aguilar Ramon",
    "wof:placetype":"venue"
},
  "geometry": {"coordinates":[2.099752903,41.3569297791],"type":"Point"}
}