{
  "type": "Feature",
  "properties": {
    "iso:country":"ES",
    "sg:address":"Rua Benigno Quiroga, 118",
    "sg:city":"Sarria",
    "sg:orig_category":"Venta, Instalaci\u00d3n, Mantenimiento De Chimeneas De Interior Y Accesorios",
    "sg:phone":"+34 982 53 40 49",
    "sg:postcode":"27600",
    "sg:province":"Lugo",
    "wof:name":"Fernandez Lafuente Eloy",
    "wof:placetype":"venue"
},
  "geometry": {"coordinates":[-7.4128808975,42.7758865356],"type":"Point"}
}