{
  "type": "Feature",
  "properties": {
    "iso:country":"ES",
    "sg:address":"Carrer de Lluis Puigjaner, 23",
    "sg:city":"Olesa Montserrat",
    "sg:classifiers":[
        {
            "category":"Casinos & Gambling",
            "type":"Entertainment"
        }
    ],
    "sg:phone":"+34 937 78 19 78",
    "sg:postcode":"08640",
    "sg:province":"Barcelona",
    "sg:tags":[
        "locale",
        "de",
        "juego"
    ],
    "wof:name":"Xic Xic Park S.l.",
    "wof:placetype":"venue"
},
  "geometry": {"coordinates":[1.8917211294,41.5434417725],"type":"Point"}
}