{
  "type": "Feature",
  "properties": {
    "iso:country":"ES",
    "sg:address":"Gta Poeta Vicente Mojica, 5",
    "sg:city":"Alacant",
    "sg:orig_category":"Sindicatos De Trabajadores",
    "sg:phone":"+34 965 98 51 65",
    "sg:postcode":"03002",
    "sg:province":"Alicante",
    "wof:name":"Sindicat De Treballados De Le Ensenyamen",
    "wof:placetype":"venue"
},
  "geometry": {"coordinates":[-0.5000529885,38.3479118347],"type":"Point"}
}