{
  "type": "Feature",
  "properties": {
    "iso:country":"ES",
    "sg:address":"Calle de Noruega, 6",
    "sg:city":"Cristianos",
    "sg:orig_category":"Frutas, Legumbres Frescas Y Tempranas (al Por Menor)",
    "sg:phone":"+34 922 79 20 67",
    "sg:postcode":"38650",
    "sg:province":"Santa Cruz De Tenerife",
    "wof:name":"Jato Infante Jose Antonio",
    "wof:placetype":"venue"
},
  "geometry": {"coordinates":[-16.7212524414,28.0522556305],"type":"Point"}
}