{
  "type": "Feature",
  "properties": {
    "addr:full":"Carrer de Corsega, 479 Barcelona Barcelona 08025",
    "addr:housenumber":"479",
    "addr:postcode":"08025",
    "addr:street":"Carrer De Corsega",
    "iso:country":"ES",
    "sg:address":"Carrer de Corsega, 479",
    "sg:city":"Barcelona",
    "sg:orig_category":"Molduras, Junquillos, Listones Y Molduras Perforadas",
    "sg:phone":"+34 934 57 77 93",
    "sg:postcode":"08025",
    "sg:province":"Barcelona",
    "wof:name":"Ventosa Vives Juan",
    "wof:placetype":"venue"
},
  "geometry": {"coordinates":[2.1681001186,41.4032745361],"type":"Point"}
}