{
  "type": "Feature",
  "properties": {
    "addr:full":"Ctra. Malaga-almeria, Km. 0281,0 Torrox-costa M\u00e1laga 29793",
    "addr:postcode":"29793",
    "addr:street":"Ctra. Malaga-Almeria Km. 0281,0 Torrox-Costa Ma\u0301Laga",
    "iso:country":"ES",
    "sg:address":"Ctra. Malaga-almeria, Km. 0281,0",
    "sg:city":"Torrox-costa",
    "sg:orig_category":"Veh\u00cdculos De Ocasi\u00d3n",
    "sg:phone":"+34 952 96 72 42",
    "sg:postcode":"29793",
    "sg:province":"M\u00e1laga",
    "wof:name":"Carmelo Sigfrido Canni",
    "wof:placetype":"venue"
},
  "geometry": {"coordinates":[-3.9873039722,36.7375984192],"type":"Point"}
}