{
  "type": "Feature",
  "properties": {
    "addr:full":"Calle de Real, 31 Beas Guadix Granada 18516",
    "addr:housenumber":"31;guadix",
    "addr:postcode":"18516",
    "addr:street":"Calle De Real",
    "iso:country":"ES",
    "sg:address":"Calle de Real, 31",
    "sg:city":"Beas Guadix",
    "sg:orig_category":"Iglesia Cat\u00d3lica",
    "sg:phone":"+34 958 67 01 79",
    "sg:postcode":"18516",
    "sg:province":"Granada",
    "wof:name":"Parroquia Nuestra Se\u00f1ora De La Anunciacion",
    "wof:placetype":"venue"
},
  "geometry": {"coordinates":[-3.2057099342,37.2810745239],"type":"Point"}
}