{
  "type": "Feature",
  "properties": {
    "addr:full":"Carrer de Sant Frederic, 50 Barcelona Barcelona 08028",
    "addr:housenumber":"50",
    "addr:postcode":"08028",
    "addr:street":"Carrer De Sant Frederic",
    "iso:country":"ES",
    "sg:address":"Carrer de Sant Frederic, 50",
    "sg:city":"Barcelona",
    "sg:orig_category":"Laboratorios Y Cl\u00cdnicas Veterinarias",
    "sg:phone":"+34 934 48 20 90",
    "sg:postcode":"08028",
    "sg:province":"Barcelona",
    "wof:name":"Tonietti Veterinaria Bcn S.l.",
    "wof:placetype":"venue"
},
  "geometry": {"coordinates":[2.126502037,41.3727493286],"type":"Point"}
}