{
  "type": "Feature",
  "properties": {
    "iso:country":"ES",
    "sg:address":"Avda Andalucia, 5",
    "sg:city":"Garrucha",
    "sg:orig_category":"Inmobiliaria (agencias)",
    "sg:phone":"+34 950 13 23 97",
    "sg:postcode":"04630",
    "sg:province":"Almer\u00eda",
    "wof:name":"Ole Hispania S.l.",
    "wof:placetype":"venue"
},
  "geometry": {"coordinates":[-1.8235100508,37.1812286377],"type":"Point"}
}