{
  "type": "Feature",
  "properties": {
    "addr:full":"Calle de Beko Kale, 2 Mungia Vizcaya 48100",
    "addr:housenumber":"2",
    "addr:postcode":"48100",
    "addr:street":"Calle De Beko Kale",
    "iso:country":"ES",
    "sg:address":"Calle de Beko Kale, 2",
    "sg:city":"Mungia",
    "sg:orig_category":"Mec\u00c1nico Del Autom\u00d3vil",
    "sg:phone":"+34 946 74 96 05",
    "sg:postcode":"48100",
    "sg:province":"Vizcaya",
    "wof:name":"Talleres Elizondo S.l",
    "wof:placetype":"venue"
},
  "geometry": {"coordinates":[-2.8484640121,43.3542938232],"type":"Point"}
}