{
  "type": "Feature",
  "properties": {
    "iso:country":"ES",
    "sg:address":"Del Trigo, 9",
    "sg:city":"Sese\u00f1a",
    "sg:orig_category":"Mec\u00c1nico Del Autom\u00d3vil",
    "sg:phone":"+34 918 08 97 13",
    "sg:postcode":"45223",
    "sg:province":"Toledo",
    "wof:name":"Agudauto S.l.",
    "wof:placetype":"venue"
},
  "geometry": {"coordinates":[-3.6764104366,40.1072769165],"type":"Point"}
}