{
  "type": "Feature",
  "properties": {
    "iso:country":"ES",
    "sg:address":"Calle de Mercedes De Las, 16",
    "sg:city":"Torremolinos",
    "sg:orig_category":"Deportes Y Ocio: Art\u00cdculos Y Ropas (al Por Menor Y Accesorios)",
    "sg:phone":"+34 952 05 08 63",
    "sg:postcode":"29620",
    "sg:province":"M\u00e1laga",
    "wof:name":"Fumeke 14 S.l.",
    "wof:placetype":"venue"
},
  "geometry": {"coordinates":[-4.4970421791,36.6232681274],"type":"Point"}
}