{
  "type": "Feature",
  "properties": {
    "addr:full":"C/ Ciutat D'eibar, 9 Paterna Valencia 46988",
    "addr:housenumber":"9",
    "addr:postcode":"46988",
    "addr:street":"C / Ciutat D'Eibar",
    "iso:country":"ES",
    "sg:address":"C/ Ciutat D'eibar, 9",
    "sg:city":"Paterna",
    "sg:orig_category":"Maquinaria Para Industrias Diversas",
    "sg:phone":"+34 961 34 09 32",
    "sg:postcode":"46988",
    "sg:province":"Valencia",
    "wof:name":"Inlemar Construcciones Mecanicas S.l.",
    "wof:placetype":"venue"
},
  "geometry": {"coordinates":[-0.4761207104,39.5161781311],"type":"Point"}
}