{
  "type": "Feature",
  "properties": {
    "addr:full":"Ctra. Segovia, Km. 0023,0 Portillo Valladolid 47160",
    "addr:postcode":"47160",
    "addr:street":"Ctra. Segovia Km. 0023,0",
    "iso:country":"ES",
    "sg:address":"Ctra. Segovia, Km. 0023,0",
    "sg:city":"Portillo",
    "sg:orig_category":"Alfarer\u00cda",
    "sg:phone":"+34 983 55 68 64",
    "sg:postcode":"47160",
    "sg:province":"Valladolid",
    "wof:name":"Teresa Diaz Angel",
    "wof:placetype":"venue"
},
  "geometry": {"coordinates":[-4.5854678154,41.4795455933],"type":"Point"}
}