{
  "type": "Feature",
  "properties": {
    "iso:country":"ES",
    "sg:address":"Avda Isaac Peral, S/n",
    "sg:city":"Alhaurin Torre",
    "sg:orig_category":"Animales (al Por Menor)",
    "sg:phone":"+34 952 41 52 02",
    "sg:postcode":"29130",
    "sg:province":"M\u00e1laga",
    "wof:name":"Manpasur S.l.",
    "wof:placetype":"venue"
},
  "geometry": {"coordinates":[-4.5625343323,36.6661682129],"type":"Point"}
}