{
  "type": "Feature",
  "properties": {
    "iso:country":"ES",
    "sg:address":"Carrer de Estanislau Mateu Valls, 7",
    "sg:city":"Urbanitzacio Mas Carpa",
    "sg:orig_category":"Asociaciones Humanitarias, De Cooperaci\u00d3n, De Acci\u00d3n Social",
    "sg:phone":"+34 977 77 44 63",
    "sg:postcode":"43206",
    "sg:province":"Tarragona",
    "wof:name":"Sad Assistencial Comarques Meridionals S.l.",
    "wof:placetype":"venue"
},
  "geometry": {"coordinates":[1.129183054,41.1494560242],"type":"Point"}
}