{
  "type": "Feature",
  "properties": {
    "addr:full":"Calle de Arco De Avila, 26 Arevalo \u00c1vila 05200",
    "addr:housenumber":"26",
    "addr:postcode":"05200",
    "addr:street":"Calle De Arco De Avila",
    "iso:country":"ES",
    "sg:address":"Calle de Arco De Avila, 26",
    "sg:city":"Arevalo",
    "sg:orig_category":"Lavado, Limpieza De Veh\u00cdculos",
    "sg:phone":"+34 920 30 22 11",
    "sg:postcode":"05200",
    "sg:province":"\u00c1vila",
    "wof:name":"Gonzalez Marce\u00f1ido Angel",
    "wof:placetype":"venue"
},
  "geometry": {"coordinates":[-4.7186489105,41.0602416992],"type":"Point"}
}