{
  "type": "Feature",
  "properties": {
    "addr:full":"Calle de Obispo Cobos, 10 Ubeda Ja\u00e9n 23400",
    "addr:housenumber":"10",
    "addr:postcode":"23400",
    "addr:street":"Calle De Obispo Cobos;Jae\u0301N",
    "iso:country":"ES",
    "sg:address":"Calle de Obispo Cobos, 10",
    "sg:city":"Ubeda",
    "sg:orig_category":"Arquitectos",
    "sg:phone":"+34 953 79 50 99",
    "sg:postcode":"23400",
    "sg:province":"Ja\u00e9n",
    "wof:name":"Moya Jimenez Rocio",
    "wof:placetype":"venue"
},
  "geometry": {"coordinates":[-3.3741960526,38.0115394592],"type":"Point"}
}