{
  "type": "Feature",
  "properties": {
    "addr:full":"Avda Valencia, 4 Santa Pola Alicante 03130",
    "addr:housenumber":"4",
    "addr:postcode":"03130",
    "addr:street":"Avda Valencia",
    "iso:country":"ES",
    "sg:address":"Avda Valencia, 4",
    "sg:city":"Santa Pola",
    "sg:orig_category":"Deportes N\u00c1uticos, Acu\u00c1ticos Y Subacu\u00c1ticos: Art\u00cdculos Y Equipo (al Por Menor)",
    "sg:phone":"+34 965 41 60 24",
    "sg:postcode":"03130",
    "sg:province":"Alicante",
    "wof:name":"Martinez Macia Juan Manuel",
    "wof:placetype":"venue"
},
  "geometry": {"coordinates":[-0.5658040047,38.1930007935],"type":"Point"}
}