{
  "type": "Feature",
  "properties": {
    "iso:country":"ES",
    "sg:address":"Calle de Ines Chemida, 39",
    "sg:city":"Palmas De Gran Canaria",
    "sg:orig_category":"Arquitectos",
    "sg:phone":"+34 928 46 92 80",
    "sg:postcode":"35009",
    "sg:province":"Las Palmas",
    "wof:name":"Canto Prada Leopoldo",
    "wof:placetype":"venue"
},
  "geometry": {"coordinates":[-15.4296035767,28.1506214142],"type":"Point"}
}