{
  "type": "Feature",
  "properties": {
    "addr:full":"Albistur Kalea, 1 Lesaka Navarra 31770",
    "addr:housenumber":"1",
    "addr:postcode":"31770",
    "addr:street":"Albistur Kalea",
    "iso:country":"ES",
    "sg:address":"Albistur Kalea, 1",
    "sg:city":"Lesaka",
    "sg:orig_category":"Relojer\u00cda (al Por Menor, Reparaci\u00d3n)",
    "sg:phone":"+34 948 63 72 05",
    "sg:postcode":"31770",
    "sg:province":"Navarra",
    "wof:name":"Echarte Ubiria Jose Antonio",
    "wof:placetype":"venue"
},
  "geometry": {"coordinates":[-1.703938961,43.2471084595],"type":"Point"}
}