{
  "type": "Feature",
  "properties": {
    "addr:full":"Calle de Arturo Soria, 305 Madrid Madrid 28033",
    "addr:housenumber":"305",
    "addr:postcode":"28033",
    "addr:street":"Calle De Arturo Soria",
    "iso:country":"ES",
    "sg:address":"Calle de Arturo Soria, 305",
    "sg:city":"Madrid",
    "sg:orig_category":"Ense\u00d1ante, Direcci\u00d3n",
    "sg:phone":"+34 913 02 51 05",
    "sg:postcode":"28033",
    "sg:province":"Madrid",
    "wof:name":"Vermenouze Rodriguez Matilde",
    "wof:placetype":"venue"
},
  "geometry": {"coordinates":[-3.6690719128,40.4779510498],"type":"Point"}
}