{
  "type": "Feature",
  "properties": {
    "addr:full":"C/ Filet De Fora, 56 Elche Alicante 03203",
    "addr:housenumber":"56",
    "addr:postcode":"03203",
    "addr:street":"C / Filet De Fora",
    "iso:country":"ES",
    "sg:address":"C/ Filet De Fora, 56",
    "sg:city":"Elche",
    "sg:orig_category":"Promotores Constructores",
    "sg:phone":"+34 966 61 53 23",
    "sg:postcode":"03203",
    "sg:province":"Alicante",
    "wof:name":"Martinez Sanchez Francisco Javier",
    "wof:placetype":"venue"
},
  "geometry": {"coordinates":[-0.6961699724,38.2617073059],"type":"Point"}
}