{
  "type": "Feature",
  "properties": {
    "addr:full":"Calle de Ceramica, 65 Madrid Madrid 28038",
    "addr:housenumber":"65",
    "addr:postcode":"madrid;28038",
    "addr:street":"Calle De Ceramica",
    "iso:country":"ES",
    "sg:address":"Calle de Ceramica, 65",
    "sg:city":"Madrid",
    "sg:orig_category":"Empresas De Carpinter\u00cda",
    "sg:phone":"+34 915 01 27 42",
    "sg:postcode":"28038",
    "sg:province":"Madrid",
    "wof:name":"Aluminios De Sanchez Y Saez S.l",
    "wof:placetype":"venue"
},
  "geometry": {"coordinates":[-3.6555621624,40.4044151306],"type":"Point"}
}