{
  "type": "Feature",
  "properties": {
    "addr:full":"Calle de Santiago, 9 Madrid Madrid 28013",
    "addr:housenumber":"9",
    "addr:postcode":"madrid;28013",
    "addr:street":"Calle De Santiago",
    "iso:country":"ES",
    "sg:address":"Calle de Santiago, 9",
    "sg:city":"Madrid",
    "sg:orig_category":"Peluquer\u00cdas, Peluquer\u00cda Mixta",
    "sg:phone":"+34 915 41 12 02",
    "sg:postcode":"28013",
    "sg:province":"Madrid",
    "sg:website":"www.quecorte.com",
    "wof:name":"Fuentes Becerra Juan",
    "wof:placetype":"venue"
},
  "geometry": {"coordinates":[-3.710506916,40.4163360596],"type":"Point"}
}