{
  "type": "Feature",
  "properties": {
    "iso:country":"ES",
    "sg:address":"Carr Major, 56",
    "sg:city":"Soses",
    "sg:orig_category":"Plomeros",
    "sg:phone":"+34 973 79 71 26",
    "sg:postcode":"25181",
    "sg:province":"Lleida",
    "wof:name":"Marco Ribas Miguel",
    "wof:placetype":"venue"
},
  "geometry": {"coordinates":[0.4861930013,41.5321807861],"type":"Point"}
}