{
  "type": "Feature",
  "properties": {
    "addr:full":"Ctra Rubi, 332 Fonts Barcelona 08228",
    "addr:housenumber":"332",
    "addr:postcode":"08228",
    "addr:street":"Ctra Rubi;Barcelona",
    "iso:country":"ES",
    "sg:address":"Ctra Rubi, 332",
    "sg:city":"Fonts",
    "sg:orig_category":"Veh\u00cdculos De Ocasi\u00d3n",
    "sg:phone":"+34 937 86 48 05",
    "sg:postcode":"08228",
    "sg:province":"Barcelona",
    "wof:name":"Compra-venta J.s.s.l.",
    "wof:placetype":"venue"
},
  "geometry": {"coordinates":[2.0349860191,41.5328407288],"type":"Point"}
}