{
  "type": "Feature",
  "properties": {
    "iso:country":"ES",
    "sg:address":"Cruz De Barkazio, 3",
    "sg:city":"Iru\u00f1a",
    "sg:orig_category":"Mec\u00c1nico Del Autom\u00d3vil",
    "sg:phone":"+34 948 12 91 08",
    "sg:postcode":"31014",
    "sg:province":"Navarra",
    "wof:name":"Sanz Garcia Fermin",
    "wof:placetype":"venue"
},
  "geometry": {"coordinates":[-1.6470979452,42.8261909485],"type":"Point"}
}