{
  "type": "Feature",
  "properties": {
    "iso:country":"ES",
    "sg:address":"Calle de Buenos Aires, 1",
    "sg:city":"San Gregorio",
    "sg:orig_category":"Carnicer\u00cdas, Carnicer\u00cdas",
    "sg:phone":"+34 976 74 23 57",
    "sg:postcode":"50015",
    "sg:province":"Zaragoza",
    "wof:name":"Pastor Bollo Manuel",
    "wof:placetype":"venue"
},
  "geometry": {"coordinates":[-0.8639093041,41.6915664673],"type":"Point"}
}