{
  "type": "Feature",
  "properties": {
    "iso:country":"ES",
    "sg:address":"Calle de Matia, 46",
    "sg:city":"Donostia-san Sebastian",
    "sg:orig_category":"Reciclaje Y Tratamiento De Desechos Varios",
    "sg:phone":"+34 943 31 10 97",
    "sg:postcode":"20008",
    "sg:province":"Guip\u00f9zcoa",
    "wof:name":"Comercial Campos S.l.",
    "wof:placetype":"venue"
},
  "geometry": {"coordinates":[-2.0040669441,43.312877655],"type":"Point"}
}