{
  "type": "Feature",
  "properties": {
    "iso:country":"ES",
    "sg:address":"Calle de San Anton, 7",
    "sg:city":"Logro\u00f1o",
    "sg:orig_category":"Asesor\u00cdas Y Estudios Financieros",
    "sg:phone":"+34 941 25 51 54",
    "sg:postcode":"26002",
    "sg:province":"La Rioja",
    "wof:name":"Larrea Acebal Adolfo",
    "wof:placetype":"venue"
},
  "geometry": {"coordinates":[-2.4466938972,42.4625473022],"type":"Point"}
}