{
  "type": "Feature",
  "properties": {
    "addr:full":"Carrer de Gaieta Vinzia, 67 Mollet Valles Barcelona 08100",
    "addr:housenumber":"67",
    "addr:postcode":"08100",
    "addr:street":"Carrer De Gaieta Vinzia",
    "iso:country":"ES",
    "sg:address":"Carrer de Gaieta Vinzia, 67",
    "sg:city":"Mollet Valles",
    "sg:orig_category":"Empresas De Carpinter\u00cda",
    "sg:phone":"+34 935 70 06 06",
    "sg:postcode":"08100",
    "sg:province":"Barcelona",
    "wof:name":"Chacon Y Romero Scp",
    "wof:placetype":"venue"
},
  "geometry": {"coordinates":[2.210381031,41.5409011841],"type":"Point"}
}