{
  "type": "Feature",
  "properties": {
    "addr:full":"Calle de Juan Hernandez, S/n Gador Almer\u00eda 04560",
    "addr:postcode":"04560",
    "addr:street":"Calle De Juan Hernandez S / N Gador Almeri\u0301A",
    "iso:country":"ES",
    "sg:address":"Calle de Juan Hernandez, S/n",
    "sg:city":"Gador",
    "sg:orig_category":"Aguas (distribuci\u00d3n, Servicios)",
    "sg:phone":"+34 950 64 50 16",
    "sg:postcode":"04560",
    "sg:province":"Almer\u00eda",
    "wof:name":"Juarez Gonzalez Antonio",
    "wof:placetype":"venue"
},
  "geometry": {"coordinates":[-2.4932188988,36.9540939331],"type":"Point"}
}