{
  "type": "Feature",
  "properties": {
    "iso:country":"ES",
    "sg:address":"Calle de Profesor Tierno Galvan, S/n",
    "sg:city":"Herreruela",
    "sg:orig_category":"Transportes Por V\u00cdas Navegables",
    "sg:phone":"+34 927 37 16 02",
    "sg:postcode":"10560",
    "sg:province":"C\u00e1ceres",
    "wof:name":"Duran Rico Sebastian",
    "wof:placetype":"venue"
},
  "geometry": {"coordinates":[-6.9060378075,39.4618873596],"type":"Point"}
}