{
  "type": "Feature",
  "properties": {
    "addr:full":"Calle de Pablo Iglesias, 9 Zubia Granada 18140",
    "addr:housenumber":"9",
    "addr:postcode":"18140",
    "addr:street":"Calle De Pablo Iglesias",
    "iso:country":"ES",
    "sg:address":"Calle de Pablo Iglesias, 9",
    "sg:city":"Zubia",
    "sg:orig_category":"Ense\u00d1anza: Profesiones Art\u00cdsticas",
    "sg:phone":"+34 958 59 12 22",
    "sg:postcode":"18140",
    "sg:province":"Granada",
    "wof:name":"Zubia Color S.l.",
    "wof:placetype":"venue"
},
  "geometry": {"coordinates":[-3.565964222,37.1471977234],"type":"Point"}
}