{
  "type": "Feature",
  "properties": {
    "addr:full":"Calle de Valentin Sanz, 10 Santa Cruz De Tenerife Santa Cruz De Tenerife 38003",
    "addr:housenumber":"10",
    "addr:postcode":"38003",
    "addr:street":"Calle De Valentin Sanz",
    "iso:country":"ES",
    "sg:address":"Calle de Valentin Sanz, 10",
    "sg:city":"Santa Cruz De Tenerife",
    "sg:orig_category":"Asesor\u00cda Fiscal Y Jur\u00cddica",
    "sg:phone":"+34 922 29 21 92",
    "sg:postcode":"38003",
    "sg:province":"Santa Cruz De Tenerife",
    "sg:website":"www.beltranyanes.com",
    "wof:name":"Beltran Yanes Y Asociados S.l.",
    "wof:placetype":"venue"
},
  "geometry": {"coordinates":[-16.3326644897,28.4846744537],"type":"Point"}
}