{
  "type": "Feature",
  "properties": {
    "iso:country":"ES",
    "sg:address":"Poli Industrial Carmaday, 9",
    "sg:city":"Vall D'uixo",
    "sg:orig_category":"Construcciones Met\u00c1licas",
    "sg:phone":"+34 964 69 13 28",
    "sg:postcode":"12600",
    "sg:province":"Castell\u00f3n",
    "wof:name":"Construcciones Metalicas Alumvill S.l.",
    "wof:placetype":"venue"
},
  "geometry": {"coordinates":[-0.0482099988,39.992477417],"type":"Point"}
}