{
  "type": "Feature",
  "properties": {
    "iso:country":"ES",
    "sg:address":"Carrer de Antoni Gaudi, 4",
    "sg:city":"Reus",
    "sg:orig_category":"Agencias De Viajes",
    "sg:phone":"+34 977 32 61 16",
    "sg:postcode":"43202",
    "sg:province":"Tarragona",
    "sg:website":"www.sbdtravel com",
    "wof:name":"Sbd Travel Service S.a.",
    "wof:placetype":"venue"
},
  "geometry": {"coordinates":[1.1044100523,41.158996582],"type":"Point"}
}