{
  "type": "Feature",
  "properties": {
    "addr:full":"Calle de Agustina De Aragon, 18 Getafe Madrid 28903",
    "addr:housenumber":"18",
    "addr:postcode":"28903",
    "addr:street":"Calle De Agustina De Aragon",
    "iso:country":"ES",
    "sg:address":"Calle de Agustina De Aragon, 18",
    "sg:city":"Getafe",
    "sg:orig_category":"Asociaciones Humanitarias, De Cooperaci\u00d3n, De Acci\u00d3n Social",
    "sg:phone":"+34 916 95 13 04",
    "sg:postcode":"28903",
    "sg:province":"Madrid",
    "wof:name":"Apoyo Positivo",
    "wof:placetype":"venue"
},
  "geometry": {"coordinates":[-3.7140586376,40.3229408264],"type":"Point"}
}