{
  "type": "Feature",
  "properties": {
    "iso:country":"ES",
    "sg:address":"Pol Ind Majaravique, S/n",
    "sg:city":"San Jose Rinconada",
    "sg:orig_category":"Droguer\u00cdas (al Por Mayor)",
    "sg:phone":"+34 954 91 61 02",
    "sg:postcode":"41300",
    "sg:province":"Sevilla",
    "wof:name":"Virtudes Gon Calve Yolanda",
    "wof:placetype":"venue"
},
  "geometry": {"coordinates":[-5.9507889748,37.4823112488],"type":"Point"}
}