{
  "type": "Feature",
  "properties": {
    "iso:country":"ES",
    "sg:address":"Calle de Cascanueces, 10",
    "sg:city":"Madrid",
    "sg:orig_category":"Sociedades, Compa\u00d1\u00cdas Aseguradoras",
    "sg:phone":"+34 917 59 00 29",
    "sg:postcode":"28043",
    "sg:province":"Madrid",
    "wof:name":"Sermeint",
    "wof:placetype":"venue"
},
  "geometry": {"coordinates":[-3.6349959373,40.4555358887],"type":"Point"}
}