{
  "type": "Feature",
  "properties": {
    "addr:full":"Carrer de Pau Vergos, 7 Gava Barcelona 08850",
    "addr:housenumber":"7",
    "addr:postcode":"08850",
    "addr:street":"Carrer De Pau Vergos",
    "iso:country":"ES",
    "sg:address":"Carrer de Pau Vergos, 7",
    "sg:city":"Gava",
    "sg:orig_category":"Bares, Piano",
    "sg:phone":"+34 936 62 18 43",
    "sg:postcode":"08850",
    "sg:province":"Barcelona",
    "wof:name":"Bals Castillo Ramon",
    "wof:placetype":"venue"
},
  "geometry": {"coordinates":[2.0005130768,41.3010063171],"type":"Point"}
}