{
  "type": "Feature",
  "properties": {
    "iso:country":"ES",
    "sg:address":"Pla\u00c7 Abadia (l'), 1",
    "sg:city":"Picassent",
    "sg:orig_category":"Hornos Industriales",
    "sg:phone":"+34 961 23 14 62",
    "sg:postcode":"46220",
    "sg:province":"Valencia",
    "wof:name":"Forn Pastisseria L'abadia S.l.",
    "wof:placetype":"venue"
},
  "geometry": {"coordinates":[-0.4595290124,39.3631401062],"type":"Point"}
}