{
  "type": "Feature",
  "properties": {
    "iso:country":"ES",
    "sg:address":"Avda Ramon Y Cajal, 43",
    "sg:city":"Sevilla",
    "sg:orig_category":"Psic\u00d3logos",
    "sg:phone":"+34 954 92 37 78",
    "sg:postcode":"41005",
    "sg:province":"Sevilla",
    "wof:name":"Martin Irene Francisco Jose",
    "wof:placetype":"venue"
},
  "geometry": {"coordinates":[-5.9688310623,37.3754806519],"type":"Point"}
}