{
  "type": "Feature",
  "properties": {
    "iso:country":"ES",
    "sg:address":"Avda Cardenal Benlloch, 56",
    "sg:city":"Valencia",
    "sg:orig_category":"Asesor\u00cdas Y Estudios Financieros",
    "sg:phone":"+34 963 69 14 02",
    "sg:postcode":"46021",
    "sg:province":"Valencia",
    "wof:name":"Cubells Ortiz Antonio",
    "wof:placetype":"venue"
},
  "geometry": {"coordinates":[-0.3550420105,39.4698638916],"type":"Point"}
}