{
  "type": "Feature",
  "properties": {
    "addr:full":"Carrer de Marti, 44 Barcelona Barcelona 08024",
    "addr:housenumber":"44",
    "addr:postcode":"08024",
    "addr:street":"Carrer De Marti",
    "iso:country":"ES",
    "sg:address":"Carrer de Marti, 44",
    "sg:city":"Barcelona",
    "sg:orig_category":"Asociaciones Y Clubs Deportivos",
    "sg:phone":"+34 932 13 25 72",
    "sg:postcode":"08024",
    "sg:province":"Barcelona",
    "wof:name":"Escacs Vulca S.l.",
    "wof:placetype":"venue"
},
  "geometry": {"coordinates":[2.1566829681,41.4074554443],"type":"Point"}
}