{
  "type": "Feature",
  "properties": {
    "addr:full":"Calle de Salsipuedes, 20 Madrid Madrid 28021",
    "addr:housenumber":"20",
    "addr:postcode":"madrid;28021",
    "addr:street":"Calle De Salsipuedes",
    "iso:country":"ES",
    "sg:address":"Calle de Salsipuedes, 20",
    "sg:city":"Madrid",
    "sg:orig_category":"Carnicer\u00cdas, Carnicer\u00cdas",
    "sg:phone":"+34 917 98 65 26",
    "sg:postcode":"28021",
    "sg:province":"Madrid",
    "wof:name":"Bermejo Quiroga Javier",
    "wof:placetype":"venue"
},
  "geometry": {"coordinates":[-3.7045440674,40.3448600769],"type":"Point"}
}