{
  "type": "Feature",
  "properties": {
    "addr:full":"Calle de Mariucha, 24 Palmas De Gran Canaria Las Palmas 35012",
    "addr:housenumber":"24",
    "addr:postcode":"35012",
    "addr:street":"Calle De Mariucha",
    "iso:country":"ES",
    "sg:address":"Calle de Mariucha, 24",
    "sg:city":"Palmas De Gran Canaria",
    "sg:orig_category":"Alimentaci\u00d3n General (al Por Menor)",
    "sg:phone":"+34 928 25 59 02",
    "sg:postcode":"35012",
    "sg:province":"Las Palmas",
    "wof:name":"Quesada Sarmiento Antonia",
    "wof:placetype":"venue"
},
  "geometry": {"coordinates":[-15.4321775436,28.112165451],"type":"Point"}
}