{
  "type": "Feature",
  "properties": {
    "iso:country":"ES",
    "sg:address":"Calle de Jacinto, 54",
    "sg:city":"Girasoles",
    "sg:orig_category":"Artes Gr\u00c1ficas, Artes Pl\u00c1sticas (curso)",
    "sg:phone":"+34 955 99 77 33",
    "sg:postcode":"41907",
    "sg:province":"Sevilla",
    "sg:website":"www.ferrayoly.com",
    "wof:name":"Ferrayoly S.l.",
    "wof:placetype":"venue"
},
  "geometry": {"coordinates":[-6.0776147842,37.4170455933],"type":"Point"}
}