{
  "type": "Feature",
  "properties": {
    "addr:full":"Rua Principe, 53 Vigo Pontevedra 36202",
    "addr:housenumber":"53",
    "addr:postcode":"36202",
    "addr:street":"Rua Principe",
    "iso:country":"ES",
    "sg:address":"Rua Principe, 53",
    "sg:city":"Vigo",
    "sg:orig_category":"Ropa Para Se\u00d1oras (al Por Menor)",
    "sg:phone":"+34 986 22 97 09",
    "sg:postcode":"36202",
    "sg:province":"Pontevedra",
    "sg:website":"www.mango.com",
    "wof:name":"Punto Fa S.l.",
    "wof:placetype":"venue"
},
  "geometry": {"coordinates":[-8.7208948135,42.2363319397],"type":"Point"}
}