{
  "type": "Feature",
  "properties": {
    "addr:full":"Calle de Casares Quiroga, 16 Coru\u00d1a La Coru\u00f1a 15008",
    "addr:housenumber":"16",
    "addr:postcode":"15008",
    "addr:street":"Calle De Casares Quiroga;La Corun\u0303A",
    "iso:country":"ES",
    "sg:address":"Calle de Casares Quiroga, 16",
    "sg:city":"Coru\u00d1a",
    "sg:orig_category":"Cajas De Ahorro",
    "sg:phone":"+34 981 15 14 04",
    "sg:postcode":"15008",
    "sg:province":"La Coru\u00f1a",
    "wof:name":"Caixa D'estalvis I Pensions De Barcelona",
    "wof:placetype":"venue"
},
  "geometry": {"coordinates":[-8.4512443542,43.3434753418],"type":"Point"}
}