{
  "type": "Feature",
  "properties": {
    "iso:country":"ES",
    "sg:address":"Carr Ciutat De Lleida, 4",
    "sg:city":"Pont Suert",
    "sg:orig_category":"Perfumer\u00cda, Art\u00cdculos De Ba\u00d1o (fabricaci\u00d3n, Al Por Mayor)",
    "sg:phone":"+34 973 69 01 97",
    "sg:postcode":"25520",
    "sg:province":"Lleida",
    "wof:name":"Drogueria Perfumeria Regals Fornons",
    "wof:placetype":"venue"
},
  "geometry": {"coordinates":[0.7424060106,42.4047966003],"type":"Point"}
}