{
  "type": "Feature",
  "properties": {
    "addr:full":"Pase Violon (del), 10 Granada Granada 18006",
    "addr:postcode":"18006",
    "iso:country":"ES",
    "sg:address":"Pase Violon (del), 10",
    "sg:city":"Granada",
    "sg:orig_category":"Venta, Colocaci\u00d3n, Reparaci\u00d3n De Parabrisas, Techos Descapotables",
    "sg:phone":"+34 958 13 32 13",
    "sg:postcode":"18006",
    "sg:province":"Granada",
    "wof:name":"Cristalauto Lunas Del Automovil S.l.",
    "wof:placetype":"venue"
},
  "geometry": {"coordinates":[-3.6008489132,37.1661376953],"type":"Point"}
}