{
  "type": "Feature",
  "properties": {
    "addr:full":"Plaz Catalu\u00d1a, 6 Huesca Huesca 22004",
    "addr:housenumber":"6",
    "addr:postcode":"22004",
    "addr:street":"Plaz Catalun\u0303A",
    "iso:country":"ES",
    "sg:address":"Plaz Catalu\u00d1a, 6",
    "sg:city":"Huesca",
    "sg:orig_category":"M\u00c9dicos: Estomatolog\u00cda",
    "sg:phone":"+34 974 22 57 46",
    "sg:postcode":"22004",
    "sg:province":"Huesca",
    "wof:name":"Vi\u00f1uales Sampietro Esperanza",
    "wof:placetype":"venue"
},
  "geometry": {"coordinates":[-0.4408037066,42.1070098877],"type":"Point"}
}