{
  "type": "Feature",
  "properties": {
    "iso:country":"ES",
    "sg:address":"Calle de Orinoco, 3",
    "sg:city":"Palmas De Gran Canaria",
    "sg:orig_category":"Caf\u00c9s, Bares, Cervecer\u00cdas",
    "sg:phone":"+34 928 42 16 95",
    "sg:postcode":"35014",
    "sg:province":"Las Palmas",
    "wof:name":"Canarias De Explotacion De Telefonia S.l.",
    "wof:placetype":"venue"
},
  "geometry": {"coordinates":[-15.443277359,28.092754364],"type":"Point"}
}