{
  "type": "Feature",
  "properties": {
    "iso:country":"ES",
    "sg:address":"Avda Papagayo, 33",
    "sg:city":"Castillo Del Aguila",
    "sg:orig_category":"Bazares, Art\u00cdculos De Limpieza Y De Cocina (al Por Menor)",
    "sg:phone":"+34 928 34 93 95",
    "sg:postcode":"35580",
    "sg:province":"Las Palmas",
    "wof:name":"Kishinchand  Deepak",
    "wof:placetype":"venue"
},
  "geometry": {"coordinates":[-13.8307790756,28.8657550812],"type":"Point"}
}