{
  "type": "Feature",
  "properties": {
    "addr:full":"Doctor Mar\u00edn, 1 Hinojosos Cuenca 16417",
    "addr:housenumber":"1",
    "addr:postcode":"16417",
    "addr:street":"Doctor Mari\u0301N",
    "iso:country":"ES",
    "sg:address":"Doctor Mar\u00edn, 1",
    "sg:city":"Hinojosos",
    "sg:orig_category":"Farmacias",
    "sg:phone":"+34 969 12 94 23",
    "sg:postcode":"16417",
    "sg:province":"Cuenca",
    "wof:name":"Porras Rodriguez Jose Manuel",
    "wof:placetype":"venue"
},
  "geometry": {"coordinates":[-2.8284170628,39.6043014526],"type":"Point"}
}