{
  "type": "Feature",
  "properties": {
    "iso:country":"ES",
    "sg:address":"Calle de Tirant Lo Blanch, 22",
    "sg:city":"Valencia",
    "sg:orig_category":"Fabricaci\u00d3n, Venta, Instalaci\u00d3n De R\u00d3tulos, De R\u00d3tulos Luminosos",
    "sg:phone":"+34 963 74 72 91",
    "sg:postcode":"46013",
    "sg:province":"Valencia",
    "wof:name":"Gil Clemente Antonio",
    "wof:placetype":"venue"
},
  "geometry": {"coordinates":[-0.3693909943,39.4547805786],"type":"Point"}
}