{
  "type": "Feature",
  "properties": {
    "iso:country":"ES",
    "sg:address":"Calle de Islas Cies, 49",
    "sg:city":"Madrid",
    "sg:orig_category":"Acondicionamiento, Mantenimiento De Jardines Y Parques",
    "sg:phone":"+34 917 38 75 81",
    "sg:postcode":"28035",
    "sg:province":"Madrid",
    "wof:name":"Greenelan S.l.",
    "wof:placetype":"venue"
},
  "geometry": {"coordinates":[-3.7204499245,40.4797859192],"type":"Point"}
}