{
  "type": "Feature",
  "properties": {
    "addr:full":"Calle de Francos Rodriguez, 13 Madrid Madrid 28039",
    "addr:housenumber":"13",
    "addr:postcode":"madrid;28039",
    "addr:street":"Calle De Francos Rodriguez",
    "iso:country":"ES",
    "sg:address":"Calle de Francos Rodriguez, 13",
    "sg:city":"Madrid",
    "sg:orig_category":"Lencer\u00cda Femenina, Corseter\u00cda, Trajes De Ba\u00d1o (al Por Menor)",
    "sg:phone":"+34 914 50 12 01",
    "sg:postcode":"28039",
    "sg:province":"Madrid",
    "wof:name":"Lenceria Chariss S.l.",
    "wof:placetype":"venue"
},
  "geometry": {"coordinates":[-3.704464674,40.4559364319],"type":"Point"}
}