{
  "type": "Feature",
  "properties": {
    "addr:full":"Avda Cruz Roja Espa\u00d1ola (de La), 12 Cuenca Cuenca 16002",
    "addr:housenumber":"12",
    "addr:postcode":"16002",
    "addr:street":"Avda Cruz Roja Espan\u0303Ola De La",
    "iso:country":"ES",
    "sg:address":"Avda Cruz Roja Espa\u00d1ola (de La), 12",
    "sg:city":"Cuenca",
    "sg:orig_category":"Negocio De Materiales De Construcci\u00d3n",
    "sg:phone":"+34 969 21 47 40",
    "sg:postcode":"16002",
    "sg:province":"Cuenca",
    "wof:name":"Gabriel Barreda S.a.",
    "wof:placetype":"venue"
},
  "geometry": {"coordinates":[-2.1602768898,40.0748786926],"type":"Point"}
}