{
  "type": "Feature",
  "properties": {
    "addr:full":"Carr Pla D'avall, S/n Pla D'avall Girona 17160",
    "addr:housenumber":"s",
    "addr:postcode":"17160",
    "addr:street":"Carr Pla D'Avall;/ N Pla",
    "iso:country":"ES",
    "sg:address":"Carr Pla D'avall, S/n",
    "sg:city":"Pla D'avall",
    "sg:orig_category":"Agricultores, Agricultores",
    "sg:phone":"+34 972 42 00 21",
    "sg:postcode":"17160",
    "sg:province":"Girona",
    "wof:name":"Sat 347 Cat Sant Miquel D'angles",
    "wof:placetype":"venue"
},
  "geometry": {"coordinates":[2.8358230591,41.9957542419],"type":"Point"}
}