{
  "type": "Feature",
  "properties": {
    "iso:country":"ES",
    "sg:address":"Igrexa De Lara\u00f1o, S/n",
    "sg:city":"Lara\u00f1o",
    "sg:orig_category":"M\u00c1rmoles, Granitos Y Piedras Naturales",
    "sg:phone":"+34 981 52 00 01",
    "sg:postcode":"15896",
    "sg:province":"A Coru\u00f1a",
    "wof:name":"Sucomaga S.l.",
    "wof:placetype":"venue"
},
  "geometry": {"coordinates":[-8.6102218628,42.8763961792],"type":"Point"}
}