{
  "type": "Feature",
  "properties": {
    "iso:country":"ES",
    "sg:address":"Calle de Machaquito, 6",
    "sg:city":"Cordoba",
    "sg:orig_category":"Farmacias",
    "sg:phone":"+34 957 23 46 84",
    "sg:postcode":"14005",
    "sg:province":"C\u00f3rdoba",
    "wof:name":"Fernandez Mu\u00f1oz Jose Maria",
    "wof:placetype":"venue"
},
  "geometry": {"coordinates":[-4.7951011658,37.882938385],"type":"Point"}
}