{
  "type": "Feature",
  "properties": {
    "addr:full":"Calle de Juan Gutemberg, 2 Palmas De Gran Canaria Las Palmas 35013",
    "addr:housenumber":"2",
    "addr:postcode":"35013",
    "addr:street":"Calle De Juan Gutemberg",
    "iso:country":"ES",
    "sg:address":"Calle de Juan Gutemberg, 2",
    "sg:city":"Palmas De Gran Canaria",
    "sg:orig_category":"Reciclaje, Desguace De Veh\u00cdculos",
    "sg:phone":"+34 928 42 00 42",
    "sg:postcode":"35013",
    "sg:province":"Las Palmas",
    "wof:name":"Rodriguez Santiago Evaristo",
    "wof:placetype":"venue"
},
  "geometry": {"coordinates":[-15.4512310028,28.0942268372],"type":"Point"}
}