{
  "type": "Feature",
  "properties": {
    "addr:full":"Carr Sixto Camara, 14 Burjassot Valencia 46100",
    "addr:housenumber":"14",
    "addr:postcode":"46100",
    "addr:street":"Carr Sixto Camara",
    "iso:country":"ES",
    "sg:address":"Carr Sixto Camara, 14",
    "sg:city":"Burjassot",
    "sg:orig_category":"Fotocopias, Reprograf\u00cda",
    "sg:phone":"+34 963 90 23 06",
    "sg:postcode":"46100",
    "sg:province":"Valencia",
    "wof:name":"Aranda Laguarda Hector",
    "wof:placetype":"venue"
},
  "geometry": {"coordinates":[-0.415181309,39.5071334839],"type":"Point"}
}