{
  "type": "Feature",
  "properties": {
    "iso:country":"ES",
    "sg:address":"Avda Bruselas, 59",
    "sg:city":"Madrid",
    "sg:orig_category":"Empresarios",
    "sg:phone":"+34 917 26 84 44",
    "sg:postcode":"28028",
    "sg:province":"Madrid",
    "wof:name":"O.f.c. Obras S.l.",
    "wof:placetype":"venue"
},
  "geometry": {"coordinates":[-3.6631131172,40.4400634766],"type":"Point"}
}