{
  "type": "Feature",
  "properties": {
    "addr:full":"Plaz Coronel Pena, 4 Vilalba Lugo 27800",
    "addr:housenumber":"4",
    "addr:postcode":"27800",
    "addr:street":"Pena",
    "iso:country":"ES",
    "sg:address":"Plaz Coronel Pena, 4",
    "sg:city":"Vilalba",
    "sg:orig_category":"Molduras, Junquillos, Listones Y Molduras Perforadas",
    "sg:phone":"+34 982 51 09 07",
    "sg:postcode":"27800",
    "sg:province":"Lugo",
    "wof:name":"Lama Gonzalez Jose Luis",
    "wof:placetype":"venue"
},
  "geometry": {"coordinates":[-7.6831622124,43.2978248596],"type":"Point"}
}