{
  "type": "Feature",
  "properties": {
    "addr:full":"Carrer de Lepanto, S/n Cambrils Tarragona 43850",
    "addr:housenumber":"s / n",
    "addr:postcode":"43850",
    "addr:street":"Carrer De Lepanto",
    "iso:country":"ES",
    "sg:address":"Carrer de Lepanto, S/n",
    "sg:city":"Cambrils",
    "sg:orig_category":"Iglesia Cat\u00d3lica",
    "sg:phone":"+34 977 36 01 80",
    "sg:postcode":"43850",
    "sg:province":"Tarragona",
    "wof:name":"Arquebisbat De Tarragona",
    "wof:placetype":"venue"
},
  "geometry": {"coordinates":[1.0599638224,41.0664672852],"type":"Point"}
}