{
  "type": "Feature",
  "properties": {
    "addr:full":"Calle de Concepcion Arenal, 11 Miranda Ebro Burgos 09200",
    "addr:housenumber":"11",
    "addr:postcode":"09200",
    "addr:street":"Calle De Concepcion Arenal",
    "iso:country":"ES",
    "sg:address":"Calle de Concepcion Arenal, 11",
    "sg:city":"Miranda Ebro",
    "sg:orig_category":"Frutas, Legumbres Frescas Y Tempranas (al Por Menor)",
    "sg:phone":"+34 947 31 18 08",
    "sg:postcode":"09200",
    "sg:province":"Burgos",
    "wof:name":"Acebedo Sansegundo Benita",
    "wof:placetype":"venue"
},
  "geometry": {"coordinates":[-2.9413516521,42.6880836487],"type":"Point"}
}