{
  "type": "Feature",
  "properties": {
    "iso:country":"ES",
    "sg:address":"Rua Gerona, 12",
    "sg:city":"Vigo",
    "sg:orig_category":"Abogados",
    "sg:phone":"+34 986 23 16 97",
    "sg:postcode":"36211",
    "sg:province":"Pontevedra",
    "wof:name":"Castela Chavert Manuel",
    "wof:placetype":"venue"
},
  "geometry": {"coordinates":[-8.7300128937,42.2216110229],"type":"Point"}
}