{
  "type": "Feature",
  "properties": {
    "iso:country":"ES",
    "sg:address":"Carr Sant Esteve, 7",
    "sg:city":"Mao",
    "sg:orig_category":"Reposter\u00cdas",
    "sg:phone":"+34 971 36 29 28",
    "sg:postcode":"07703",
    "sg:province":"Islas Baleares",
    "wof:name":"Panaderia Pons S. A.",
    "wof:placetype":"venue"
},
  "geometry": {"coordinates":[4.2562718391,39.8882331848],"type":"Point"}
}