{
  "type": "Feature",
  "properties": {
    "iso:country":"ES",
    "sg:address":"Ctra Motril, 17",
    "sg:city":"Alhendin",
    "sg:classifiers":[
        {
            "category":"Manufacturing",
            "subcategory":"Building Materials",
            "type":"Manufacturing & Wholesale Goods"
        }
    ],
    "sg:phone":"+34 958 57 60 11",
    "sg:postcode":"18620",
    "sg:province":"Granada",
    "sg:tags":[
        "bebidas",
        "para",
        "la",
        "de",
        "y",
        "equipo",
        "industria"
    ],
    "wof:name":"Luis Espinosa S. A.",
    "wof:placetype":"venue"
},
  "geometry": {"coordinates":[-3.6415240765,37.1073913574],"type":"Point"}
}