{
  "type": "Feature",
  "properties": {
    "addr:full":"Pase Castellana, 179 Madrid Madrid 28046",
    "addr:housenumber":"179",
    "addr:postcode":"28046",
    "addr:street":"Castellana",
    "iso:country":"ES",
    "sg:address":"Pase Castellana, 179",
    "sg:city":"Madrid",
    "sg:orig_category":"M\u00c9dicos: Radioterapia (radioterapia Como Opci\u00d3n Oncol\u00d3gica)",
    "sg:phone":"+34 915 79 05 70",
    "sg:postcode":"28046",
    "sg:province":"Madrid",
    "wof:name":"Diagnostico Radiologico S.a.",
    "wof:placetype":"venue"
},
  "geometry": {"coordinates":[-3.6902189255,40.4630851746],"type":"Point"}
}