{
  "type": "Feature",
  "properties": {
    "addr:full":"Calle de Rosita, 10 Alcala Guadaira Sevilla 41500",
    "addr:housenumber":"10",
    "addr:postcode":"41500",
    "addr:street":"Calle De Rosita",
    "iso:country":"ES",
    "sg:address":"Calle de Rosita, 10",
    "sg:city":"Alcala Guadaira",
    "sg:orig_category":"Reposter\u00cdas",
    "sg:phone":"+34 955 68 49 68",
    "sg:postcode":"41500",
    "sg:province":"Sevilla",
    "wof:name":"Panaderia Pepe Portillo S.l.",
    "wof:placetype":"venue"
},
  "geometry": {"coordinates":[-5.8464689255,37.3333282471],"type":"Point"}
}