{
  "type": "Feature",
  "properties": {
    "addr:full":"Avda Alfonso Onceno, 9 Guadalupe C\u00e1ceres 10140",
    "addr:housenumber":"9",
    "addr:postcode":"10140",
    "addr:street":"Avda Alfonso Onceno;Ca\u0301Ceres",
    "iso:country":"ES",
    "sg:address":"Avda Alfonso Onceno, 9",
    "sg:city":"Guadalupe",
    "sg:orig_category":"Reposter\u00cdas",
    "sg:phone":"+34 927 36 74 77",
    "sg:postcode":"10140",
    "sg:province":"C\u00e1ceres",
    "wof:name":"Panificadora Doca C.b.",
    "wof:placetype":"venue"
},
  "geometry": {"coordinates":[-5.3281178474,39.4521064758],"type":"Point"}
}