{
  "type": "Feature",
  "properties": {
    "addr:full":"Calle de Cabezuela, 7 Plasencia C\u00e1ceres 10600",
    "addr:housenumber":"7",
    "addr:postcode":"10600",
    "addr:street":"Calle De Cabezuela;Ca\u0301Ceres",
    "iso:country":"ES",
    "sg:address":"Calle de Cabezuela, 7",
    "sg:city":"Plasencia",
    "sg:orig_category":"Alimentaci\u00d3n General (al Por Menor)",
    "sg:phone":"+34 927 41 03 12",
    "sg:postcode":"10600",
    "sg:province":"C\u00e1ceres",
    "wof:name":"Manzano Manzano Angel",
    "wof:placetype":"venue"
},
  "geometry": {"coordinates":[-6.081433773,40.0329170227],"type":"Point"}
}