{
  "type": "Feature",
  "properties": {
    "addr:full":"Ctra Polinya, Km. 0007,6 Sentmenat Barcelona 08181",
    "addr:postcode":"08181",
    "addr:street":"Ctra Polinya Km. 0007,6",
    "iso:country":"ES",
    "sg:address":"Ctra Polinya, Km. 0007,6",
    "sg:city":"Sentmenat",
    "sg:orig_category":"Promotores Constructores",
    "sg:phone":"+34 937 15 24 26",
    "sg:postcode":"08181",
    "sg:province":"Barcelona",
    "wof:name":"Imag S.l.",
    "wof:placetype":"venue"
},
  "geometry": {"coordinates":[2.1434240341,41.5949935913],"type":"Point"}
}