{
  "type": "Feature",
  "properties": {
    "iso:country":"ES",
    "sg:address":"Calle de Villarias, 10",
    "sg:city":"Bilbao",
    "sg:orig_category":"Abogados",
    "sg:phone":"+34 944 24 09 18",
    "sg:postcode":"48001",
    "sg:province":"Vizcaya",
    "wof:name":"Beldarrain Jaca Carmelo",
    "wof:placetype":"venue"
},
  "geometry": {"coordinates":[-2.9254999161,43.2619857788],"type":"Point"}
}