{
  "type": "Feature",
  "properties": {
    "iso:country":"ES",
    "sg:address":"Av Mil.lenari, 2",
    "sg:city":"Cambrils",
    "sg:orig_category":"Bisuter\u00cda, Joyer\u00cda, Relojer\u00cda (al Por Menor)",
    "sg:phone":"+34 977 79 42 94",
    "sg:postcode":"43850",
    "sg:province":"Tarragona",
    "wof:name":"Climent Brullas Antonio",
    "wof:placetype":"venue"
},
  "geometry": {"coordinates":[1.0495680571,41.075843811],"type":"Point"}
}