{
  "type": "Feature",
  "properties": {
    "addr:full":"Calle de Fuente Alamo, 17 Coru\u00d1a La Coru\u00f1a 15010",
    "addr:housenumber":"17",
    "addr:postcode":"15010",
    "addr:street":"Calle De Fuente Alamo;La Corun\u0303A",
    "iso:country":"ES",
    "sg:address":"Calle de Fuente Alamo, 17",
    "sg:city":"Coru\u00d1a",
    "sg:orig_category":"Colchones (fabricaci\u00d3n, Al Por Mayor, Al Por Menor)",
    "sg:phone":"+34 981 25 50 54",
    "sg:postcode":"15010",
    "sg:province":"La Coru\u00f1a",
    "wof:name":"Salcines Martinez Francisco",
    "wof:placetype":"venue"
},
  "geometry": {"coordinates":[-8.4191608429,43.3610839844],"type":"Point"}
}