{
  "type": "Feature",
  "properties": {
    "iso:country":"ES",
    "sg:address":"Rua Xaquin Losada, 8",
    "sg:city":"Carballi\u00f1o",
    "sg:orig_category":"Peluquer\u00cdas, Peluquer\u00cda Mixta",
    "sg:phone":"+34 988 27 34 26",
    "sg:postcode":"32500",
    "sg:province":"Ourense",
    "wof:name":"Gonzalez Gomez Ana Maria",
    "wof:placetype":"venue"
},
  "geometry": {"coordinates":[-8.0753564835,42.4305953979],"type":"Point"}
}