{
  "type": "Feature",
  "properties": {
    "addr:full":"Calle de Real, 105 Castilleja Cuesta Sevilla 41950",
    "addr:housenumber":"105",
    "addr:postcode":"41950",
    "addr:street":"Calle De Real",
    "iso:country":"ES",
    "sg:address":"Calle de Real, 105",
    "sg:city":"Castilleja Cuesta",
    "sg:orig_category":"Zapatos (al Por Menor)",
    "sg:phone":"+34 954 16 43 10",
    "sg:postcode":"41950",
    "sg:province":"Sevilla",
    "wof:name":"Vanadio 96 S.l.",
    "wof:placetype":"venue"
},
  "geometry": {"coordinates":[-6.0547361374,37.3857917786],"type":"Point"}
}