{
  "type": "Feature",
  "properties": {
    "addr:full":"Avda Sinforiano Madro\u00d1ero, 31 Badajoz Badajoz 06011",
    "addr:housenumber":"31",
    "addr:postcode":"06011",
    "addr:street":"Avda Sinforiano Madron\u0303Ero",
    "iso:country":"ES",
    "sg:address":"Avda Sinforiano Madro\u00d1ero, 31",
    "sg:city":"Badajoz",
    "sg:orig_category":"Seguridad Social",
    "sg:phone":"+34 924 22 24 81",
    "sg:postcode":"06011",
    "sg:province":"Badajoz",
    "wof:name":"Mutua Monta\u00f1esa-mutua De Accidentes De Trabajo Y Enfermedades Profesionales De La Seguridad Social N",
    "wof:placetype":"venue"
},
  "geometry": {"coordinates":[-6.9871587753,38.8681488037],"type":"Point"}
}