{
  "type": "Feature",
  "properties": {
    "iso:country":"ES",
    "sg:address":"Calle de Conde De Pe\u00d1alver, 61",
    "sg:city":"Madrid",
    "sg:orig_category":"Carnicer\u00cdas, Carnicer\u00cdas",
    "sg:phone":"+34 913 09 36 49",
    "sg:postcode":"28006",
    "sg:province":"Madrid",
    "wof:name":"Fernandez Garcia Samuel",
    "wof:placetype":"venue"
},
  "geometry": {"coordinates":[-3.675075531,40.433177948],"type":"Point"}
}