{
  "type": "Feature",
  "properties": {
    "iso:country":"ES",
    "sg:address":"Calle de Jose Luis De Arrese, 34",
    "sg:city":"Madrid",
    "sg:orig_category":"Molduras, Junquillos, Listones Y Molduras Perforadas",
    "sg:phone":"+34 914 05 30 00",
    "sg:postcode":"28017",
    "sg:province":"Madrid",
    "wof:name":"Diaz Arranz Francisco Javier",
    "wof:placetype":"venue"
},
  "geometry": {"coordinates":[-3.6518359184,40.4218177795],"type":"Point"}
}