{
  "type": "Feature",
  "properties": {
    "iso:country":"ES",
    "sg:address":"Calle de Santa Isabel, S/n",
    "sg:city":"Beas Segura",
    "sg:orig_category":"Asesor\u00cda Fiscal Y Jur\u00cddica",
    "sg:phone":"+34 953 45 80 41",
    "sg:postcode":"23280",
    "sg:province":"Ja\u00e9n",
    "wof:name":"Lopez Mu\u00f1oz Julian",
    "wof:placetype":"venue"
},
  "geometry": {"coordinates":[-2.8957929611,38.25440979],"type":"Point"}
}