{
  "type": "Feature",
  "properties": {
    "iso:country":"ES",
    "sg:address":"Calle de Gran Via, 13",
    "sg:city":"Riaza",
    "sg:orig_category":"Bordado, Marcado A Medida",
    "sg:phone":"+34 921 55 01 80",
    "sg:postcode":"40500",
    "sg:province":"Segovia",
    "wof:name":"Sanz Garcia Hermanos S.l.",
    "wof:placetype":"venue"
},
  "geometry": {"coordinates":[-3.4788510799,41.2785110474],"type":"Point"}
}