{
  "type": "Feature",
  "properties": {
    "iso:country":"ES",
    "sg:address":"Ctra Cabo La Nao Pla, 12",
    "sg:city":"Javea",
    "sg:orig_category":"Gastronom\u00cda: Especialidades Regionales Y Extranjeras (producci\u00d3n, Al Por Mayor)",
    "sg:phone":"+34 966 46 12 60",
    "sg:postcode":"03730",
    "sg:province":"Alicante",
    "wof:name":"Gamba  Giancamillo",
    "wof:placetype":"venue"
},
  "geometry": {"coordinates":[0.1570300013,38.7885093689],"type":"Point"}
}