{
  "type": "Feature",
  "properties": {
    "iso:country":"ES",
    "sg:address":"Avda Gabriel Miro, S/n",
    "sg:city":"Calpe",
    "sg:orig_category":"Supermercados Y Hipermercados",
    "sg:phone":"+34 965 83 79 70",
    "sg:postcode":"03710",
    "sg:province":"Alicante",
    "wof:name":"James Delaney Peter",
    "wof:placetype":"venue"
},
  "geometry": {"coordinates":[0.0467900001,38.6440048218],"type":"Point"}
}