{
  "type": "Feature",
  "properties": {
    "iso:country":"ES",
    "sg:address":"Calle de Costa Rica, 4",
    "sg:city":"Ogijares",
    "sg:orig_category":"Alquiler De V\u00cddeo",
    "sg:phone":"+34 958 50 94 76",
    "sg:postcode":"18151",
    "sg:province":"Granada",
    "wof:name":"Sanchez Morate Gonzalez De Vega Pedro",
    "wof:placetype":"venue"
},
  "geometry": {"coordinates":[-3.6029019356,37.1545066833],"type":"Point"}
}