{
  "type": "Feature",
  "properties": {
    "iso:country":"ES",
    "sg:address":"Avda Real, 1",
    "sg:city":"Le\u00f3n",
    "sg:orig_category":"Organismos De Investigaciones Cient\u00cdficas Y T\u00c9cnicas",
    "sg:phone":"+34 987 21 01 98",
    "sg:postcode":"24006",
    "sg:province":"Le\u00f3n",
    "wof:name":"Enermitec",
    "wof:placetype":"venue"
},
  "geometry": {"coordinates":[-5.5581688881,42.5985717773],"type":"Point"}
}