{
  "type": "Feature",
  "properties": {
    "addr:full":"Carrer de Gelida, 27 Vilafranca Penedes Barcelona 08720",
    "addr:housenumber":"27",
    "addr:postcode":"08720",
    "addr:street":"Carrer De Gelida;Penedes Barcelona",
    "iso:country":"ES",
    "sg:address":"Carrer de Gelida, 27",
    "sg:city":"Vilafranca Penedes",
    "sg:orig_category":"Cajas De Ahorro",
    "sg:phone":"+34 938 92 06 48",
    "sg:postcode":"08720",
    "sg:province":"Barcelona",
    "sg:website":"www.lacaixa.es",
    "wof:name":"Caixa D'estalvis I Pensions De Barcelona",
    "wof:placetype":"venue"
},
  "geometry": {"coordinates":[1.7029869556,41.3532752991],"type":"Point"}
}