{
  "type": "Feature",
  "properties": {
    "iso:country":"ES",
    "sg:address":"Calle de San Jorge, S/n",
    "sg:city":"Illar",
    "sg:orig_category":"Empresas De Carpinter\u00cda De Madera",
    "sg:phone":"+34 950 64 71 01",
    "sg:postcode":"04431",
    "sg:province":"Almer\u00eda",
    "wof:name":"Garrido Canton Jose",
    "wof:placetype":"venue"
},
  "geometry": {"coordinates":[-2.6375570297,36.9849014282],"type":"Point"}
}