{
  "type": "Feature",
  "properties": {
    "addr:full":"Calle de Cruz De Orea, 51 Cazorla Ja\u00e9n 23470",
    "addr:housenumber":"51",
    "addr:postcode":"23470",
    "addr:street":"Calle De Cruz De Orea",
    "iso:country":"ES",
    "sg:address":"Calle de Cruz De Orea, 51",
    "sg:city":"Cazorla",
    "sg:orig_category":"Asesores De Gesti\u00d3n Del Patrimonio",
    "sg:phone":"+34 953 71 02 11",
    "sg:postcode":"23470",
    "sg:province":"Ja\u00e9n",
    "wof:name":"Pedro Zafra Y Otro C.b.",
    "wof:placetype":"venue"
},
  "geometry": {"coordinates":[-3.0052998066,37.9122657776],"type":"Point"}
}