{
  "type": "Feature",
  "properties": {
    "iso:country":"ES",
    "sg:address":"Carrer de Malaga, 7",
    "sg:city":"Cornella Llobregat",
    "sg:orig_category":"Reciclaje, Tratamiento De Tejidos",
    "sg:phone":"+34 933 76 31 51",
    "sg:postcode":"08940",
    "sg:province":"Barcelona",
    "wof:name":"Lopez Reina Juan Manuel",
    "wof:placetype":"venue"
},
  "geometry": {"coordinates":[2.0725851059,41.3644065857],"type":"Point"}
}