{
  "type": "Feature",
  "properties": {
    "iso:country":"ES",
    "sg:address":"Carrer de Alfons Xii, 26",
    "sg:city":"Barcelona",
    "sg:orig_category":"Confiter\u00cdas, Chocolater\u00cdas (al Por Menor)",
    "sg:phone":"+34 934 15 52 79",
    "sg:postcode":"08006",
    "sg:province":"Barcelona",
    "wof:name":"Bombones Blasi S.l.",
    "wof:placetype":"venue"
},
  "geometry": {"coordinates":[2.1500980854,41.3982963562],"type":"Point"}
}