{
  "type": "Feature",
  "properties": {
    "iso:country":"ES",
    "sg:address":"Aliga Coronada, 21",
    "sg:city":"Torregassa",
    "sg:orig_category":"Centros Empresariales",
    "sg:phone":"+34 977 67 89 37",
    "sg:postcode":"43713",
    "sg:province":"Tarragona",
    "wof:name":"Barraachina Fernandez Monica",
    "wof:placetype":"venue"
},
  "geometry": {"coordinates":[1.5598800182,41.299495697],"type":"Point"}
}