{
  "type": "Feature",
  "properties": {
    "iso:country":"ES",
    "sg:address":"Calle de Arlanzon, 2",
    "sg:city":"Aranda Duero",
    "sg:orig_category":"Abogados",
    "sg:phone":"+34 947 50 81 48",
    "sg:postcode":"09400",
    "sg:province":"Burgos",
    "wof:name":"Arribas Miranda Enrique",
    "wof:placetype":"venue"
},
  "geometry": {"coordinates":[-3.6939547062,41.6623573303],"type":"Point"}
}