{
  "type": "Feature",
  "properties": {
    "addr:full":"Calle de San Juan, 8 Alcorcon Madrid 28921",
    "addr:housenumber":"8",
    "addr:postcode":"28921",
    "addr:street":"Calle De San Juan",
    "iso:country":"ES",
    "sg:address":"Calle de San Juan, 8",
    "sg:city":"Alcorcon",
    "sg:orig_category":"Cultos Diversos",
    "sg:phone":"+34 916 44 00 42",
    "sg:postcode":"28921",
    "sg:province":"Madrid",
    "wof:name":"Testigos Cristianos De Jehova",
    "wof:placetype":"venue"
},
  "geometry": {"coordinates":[-3.823964119,40.3438911438],"type":"Point"}
}