{
  "type": "Feature",
  "properties": {
    "addr:full":"Calle de Concordia, 15 Montiel Ciudad Real 13326",
    "addr:housenumber":"15",
    "addr:postcode":"13326",
    "addr:street":"Calle De Concordia",
    "iso:country":"ES",
    "sg:address":"Calle de Concordia, 15",
    "sg:city":"Montiel",
    "sg:orig_category":"Carnicer\u00cdas, Carnicer\u00cdas",
    "sg:phone":"+34 926 35 30 11",
    "sg:postcode":"13326",
    "sg:province":"Ciudad Real",
    "wof:name":"Garcia Garcia Juan Angel",
    "wof:placetype":"venue"
},
  "geometry": {"coordinates":[-2.863699913,38.6972236633],"type":"Point"}
}