{
  "type": "Feature",
  "properties": {
    "iso:country":"ES",
    "sg:address":"Calle de Viteri, 5",
    "sg:city":"Errenteria",
    "sg:orig_category":"Confecci\u00d3n De Trajes Para Se\u00d1oras",
    "sg:phone":"+34 943 51 70 45",
    "sg:postcode":"20100",
    "sg:province":"Guip\u00f9zcoa",
    "wof:name":"Maza Altuna Jose Alberto De La",
    "wof:placetype":"venue"
},
  "geometry": {"coordinates":[-1.8988519907,43.3130187988],"type":"Point"}
}