{
  "type": "Feature",
  "properties": {
    "iso:country":"ES",
    "sg:address":"Calle de Colon, 43",
    "sg:city":"Palencia",
    "sg:orig_category":"Librer\u00cdas",
    "sg:phone":"+34 979 74 52 93",
    "sg:postcode":"34002",
    "sg:province":"Palencia",
    "wof:name":"Elordi, Libreria De Viajes,sl.",
    "wof:placetype":"venue"
},
  "geometry": {"coordinates":[-4.5302867889,42.0066337585],"type":"Point"}
}