{
  "type": "Feature",
  "properties": {
    "iso:country":"ES",
    "sg:address":"Calle de Monasterio De Caaveiro, 5",
    "sg:city":"Coru\u00d1a",
    "sg:orig_category":"Alumbrados",
    "sg:phone":"+34 981 26 25 04",
    "sg:postcode":"15010",
    "sg:province":"La Coru\u00f1a",
    "wof:name":"Lledo Iluminacion S. A.",
    "wof:placetype":"venue"
},
  "geometry": {"coordinates":[-8.4251594543,43.3620758057],"type":"Point"}
}