{
  "type": "Feature",
  "properties": {
    "iso:country":"ES",
    "sg:address":"Rua Barcelona, 37",
    "sg:city":"Vigo",
    "sg:orig_category":"Herboristas (al Por Menor)",
    "sg:phone":"+34 986 41 19 07",
    "sg:postcode":"36203",
    "sg:province":"Pontevedra",
    "wof:name":"Fernandez Freire Maria Dolores",
    "wof:placetype":"venue"
},
  "geometry": {"coordinates":[-8.7232751846,42.2257575989],"type":"Point"}
}