{
  "type": "Feature",
  "properties": {
    "iso:country":"ES",
    "sg:address":"Calle de Adelaida Muro, 55",
    "sg:city":"Coru\u00d1a",
    "sg:orig_category":"Transporte En General",
    "sg:phone":"+34 981 20 47 64",
    "sg:postcode":"15002",
    "sg:province":"La Coru\u00f1a",
    "wof:name":"Barallobre Gomez Nieves",
    "wof:placetype":"venue"
},
  "geometry": {"coordinates":[-8.4046592712,43.3768081665],"type":"Point"}
}