{
  "type": "Feature",
  "properties": {
    "addr:full":"Rua Padre Don Rua, 8 Vigo Pontevedra 36203",
    "addr:postcode":"36203",
    "addr:street":"Rua Padre Don Rua 8",
    "iso:country":"ES",
    "sg:address":"Rua Padre Don Rua, 8",
    "sg:city":"Vigo",
    "sg:orig_category":"Promotores Constructores",
    "sg:phone":"+34 986 41 23 94",
    "sg:postcode":"36203",
    "sg:province":"Pontevedra",
    "wof:name":"Atlantico Construcciones Y Promociones S.l.",
    "wof:placetype":"venue"
},
  "geometry": {"coordinates":[-8.7194356918,42.2319755554],"type":"Point"}
}