{
  "type": "Feature",
  "properties": {
    "addr:full":"Calle de Doctor Benitez, 5 Jerez De Los Caballeros Badajoz 06380",
    "addr:housenumber":"5",
    "addr:postcode":"06380",
    "addr:street":"Calle De Doctor Benitez",
    "iso:country":"ES",
    "sg:address":"Calle de Doctor Benitez, 5",
    "sg:city":"Jerez De Los Caballeros",
    "sg:orig_category":"Estancos",
    "sg:phone":"+34 924 73 01 77",
    "sg:postcode":"06380",
    "sg:province":"Badajoz",
    "wof:name":"Ceballos-zu\u00f1iga Rodriguez Ramon",
    "wof:placetype":"venue"
},
  "geometry": {"coordinates":[-6.7716803551,38.3195877075],"type":"Point"}
}