{
  "type": "Feature",
  "properties": {
    "addr:full":"Espa\u00f1a, 146 Estepona M\u00e1laga 29680",
    "addr:housenumber":"146",
    "addr:postcode":"29680",
    "addr:street":"Espan\u0303A",
    "iso:country":"ES",
    "sg:address":"Espa\u00f1a, 146",
    "sg:city":"Estepona",
    "sg:orig_category":"Farmacias",
    "sg:phone":"+34 952 89 60 06",
    "sg:postcode":"29680",
    "sg:province":"M\u00e1laga",
    "wof:name":"Ortega Urbano Maria Del Carmen",
    "wof:placetype":"venue"
},
  "geometry": {"coordinates":[-5.1454668045,36.4240608215],"type":"Point"}
}