{
  "type": "Feature",
  "properties": {
    "addr:full":"C/ Antoni Riquer, D', 19 S. Antoni Portmany Islas Baleares 07820",
    "addr:housenumber":"19",
    "addr:postcode":"07820",
    "addr:street":"C / Antoni Riquer D '",
    "iso:country":"ES",
    "sg:address":"C/ Antoni Riquer, D', 19",
    "sg:city":"S. Antoni Portmany",
    "sg:orig_category":"Promotores Constructores",
    "sg:phone":"+34 971 34 69 08",
    "sg:postcode":"07820",
    "sg:province":"Islas Baleares",
    "wof:name":"Construcciones Ricardo Pineda S.l.",
    "wof:placetype":"venue"
},
  "geometry": {"coordinates":[2.9117100239,39.6136398315],"type":"Point"}
}