{
  "type": "Feature",
  "properties": {
    "addr:full":"Calle de Sevilla, 46 Valladolid Valladolid 47013",
    "addr:housenumber":"46",
    "addr:postcode":"47013",
    "addr:street":"Calle De Sevilla",
    "iso:country":"ES",
    "sg:address":"Calle de Sevilla, 46",
    "sg:city":"Valladolid",
    "sg:orig_category":"Ropa Para Se\u00d1oras Y Caballeros (al Por Menor)",
    "sg:phone":"+34 983 39 72 02",
    "sg:postcode":"47013",
    "sg:province":"Valladolid",
    "wof:name":"Moreno Gonzalez Antonio",
    "wof:placetype":"venue"
},
  "geometry": {"coordinates":[-4.7172641754,41.6420402527],"type":"Point"}
}