{
  "type": "Feature",
  "properties": {
    "addr:full":"Calle de Santa Virgilia, 16 Madrid Madrid 28033",
    "addr:housenumber":"16",
    "addr:postcode":"madrid;28033",
    "addr:street":"Calle De Santa Virgilia",
    "iso:country":"ES",
    "sg:address":"Calle de Santa Virgilia, 16",
    "sg:city":"Madrid",
    "sg:orig_category":"Calefacci\u00d3n Central: Material (fabricaci\u00d3n, Al Por Mayor)",
    "sg:phone":"+34 917 63 36 60",
    "sg:postcode":"28033",
    "sg:province":"Madrid",
    "wof:name":"Escal Calefaccion S.l.",
    "wof:placetype":"venue"
},
  "geometry": {"coordinates":[-3.6410079002,40.4765052795],"type":"Point"}
}