{
  "type": "Feature",
  "properties": {
    "iso:country":"ES",
    "sg:address":"Calle de Ernio, 3",
    "sg:city":"Errenteria",
    "sg:orig_category":"Empresas De Limpieza",
    "sg:phone":"+34 943 11 04 08",
    "sg:postcode":"20100",
    "sg:province":"Guip\u00f9zcoa",
    "wof:name":"Euskal Zerbitzuak Mantenim. Integral, Sl",
    "wof:placetype":"venue"
},
  "geometry": {"coordinates":[-1.9101376534,43.3132476807],"type":"Point"}
}