{
  "type": "Feature",
  "properties": {
    "iso:country":"ES",
    "sg:address":"Carrer de Pare Coll, 14",
    "sg:city":"Vic",
    "sg:orig_category":"Inform\u00c1tica: Material Y Suministros",
    "sg:phone":"+34 938 89 33 84",
    "sg:postcode":"08500",
    "sg:province":"Barcelona",
    "wof:name":"Deteinco S.l.",
    "wof:placetype":"venue"
},
  "geometry": {"coordinates":[2.2539219856,41.9334754944],"type":"Point"}
}