{
  "type": "Feature",
  "properties": {
    "iso:country":"ES",
    "sg:address":"O Carballal, 22",
    "sg:city":"Mondariz",
    "sg:orig_category":"M\u00c1rmoles, Granitos Y Piedras Naturales",
    "sg:phone":"+34 986 65 65 78",
    "sg:postcode":"36874",
    "sg:province":"Pontevedra",
    "wof:name":"Gonzalez Alonso Carlos",
    "wof:placetype":"venue"
},
  "geometry": {"coordinates":[-8.3536558151,42.1269035339],"type":"Point"}
}