{
  "type": "Feature",
  "properties": {
    "iso:country":"ES",
    "sg:address":"Polig. A Gandara, S/n",
    "sg:city":"Ferrol",
    "sg:orig_category":"Electricidad Veh\u00cdculo",
    "sg:phone":"+34 981 32 22 00",
    "sg:postcode":"15407",
    "sg:province":"La Coru\u00f1a",
    "wof:name":"Cendan Naveiras Antonio",
    "wof:placetype":"venue"
},
  "geometry": {"coordinates":[-8.1969175339,43.5052642822],"type":"Point"}
}