{
  "type": "Feature",
  "properties": {
    "addr:full":"Calle de Blandon, 1 Madrid Madrid 28025",
    "addr:housenumber":"1",
    "addr:postcode":"28025",
    "addr:street":"Calle De Blandon",
    "iso:country":"ES",
    "sg:address":"Calle de Blandon, 1",
    "sg:city":"Madrid",
    "sg:orig_category":"Puertas Y Portales",
    "sg:phone":"+34 914 62 48 15",
    "sg:postcode":"28025",
    "sg:province":"Madrid",
    "sg:website":"www.evasar.com}}",
    "wof:name":"Evasar S. A.",
    "wof:placetype":"venue"
},
  "geometry": {"coordinates":[-3.739137888,40.3890571594],"type":"Point"}
}