{
  "type": "Feature",
  "properties": {
    "addr:full":"Calle de Hamarretxeta, 15 Pasai Antxo Guip\u00f9zcoa 20110",
    "addr:housenumber":"15",
    "addr:postcode":"20110",
    "addr:street":"Calle De Hamarretxeta;Guipu\u0300Zcoa",
    "iso:country":"ES",
    "sg:address":"Calle de Hamarretxeta, 15",
    "sg:city":"Pasai Antxo",
    "sg:orig_category":"Abogados",
    "sg:phone":"+34 943 34 01 00",
    "sg:postcode":"20110",
    "sg:province":"Guip\u00f9zcoa",
    "wof:name":"Martinez Diaz Maria Del Coro",
    "wof:placetype":"venue"
},
  "geometry": {"coordinates":[-1.9172420502,43.3172874451],"type":"Point"}
}