{
  "type": "Feature",
  "properties": {
    "iso:country":"ES",
    "sg:address":"Avda Mendavia, 26",
    "sg:city":"Logro\u00f1o",
    "sg:orig_category":"Mec\u00c1nico Del Autom\u00d3vil",
    "sg:phone":"+34 941 23 10 00",
    "sg:postcode":"26006",
    "sg:province":"La Rioja",
    "wof:name":"Agro Industrial Riojana S. A.",
    "wof:placetype":"venue"
},
  "geometry": {"coordinates":[-2.4100322723,42.4727859497],"type":"Point"}
}