{
  "type": "Feature",
  "properties": {
    "iso:country":"ES",
    "sg:address":"Av Joan Miro, 354",
    "sg:city":"Sant Agusti",
    "sg:orig_category":"Panader\u00cdas, Panader\u00cdas",
    "sg:phone":"+34 971 40 09 04",
    "sg:postcode":"07015",
    "sg:province":"Islas Baleares",
    "wof:name":"Riera Ribas Vicente",
    "wof:placetype":"venue"
},
  "geometry": {"coordinates":[2.5969200134,39.5494041443],"type":"Point"}
}