{
  "type": "Feature",
  "properties": {
    "iso:country":"ES",
    "sg:address":"Ctra Malaga, S/n",
    "sg:city":"Algeciras",
    "sg:orig_category":"Pintura Y Barniz (al Por Menor)",
    "sg:phone":"+34 956 65 70 19",
    "sg:postcode":"11203",
    "sg:province":"C\u00e1diz",
    "wof:name":"Almacen De Pinturas Andalucia S.a.",
    "wof:placetype":"venue"
},
  "geometry": {"coordinates":[-5.4538025856,36.1343002319],"type":"Point"}
}