{
  "type": "Feature",
  "properties": {
    "iso:country":"ES",
    "sg:address":"Ca\u00f1ada Gallego, S/n",
    "sg:city":"Ca\u00f1ada Gallego",
    "sg:orig_category":"Alquiler De Casas Y Habitaciones Amuebladas",
    "sg:phone":"+34 968 15 88 33",
    "sg:postcode":"30876",
    "sg:province":"Murcia",
    "wof:name":"Galvez Morillas Alfonso",
    "wof:placetype":"venue"
},
  "geometry": {"coordinates":[-1.4863059521,37.5384941101],"type":"Point"}
}