{
  "type": "Feature",
  "properties": {
    "addr:full":"Rua Padres Franciscanos, 40 Tomadas Pontevedra 36379",
    "addr:housenumber":"40",
    "addr:postcode":"36379",
    "addr:street":"Rua Padres Franciscanos",
    "iso:country":"ES",
    "sg:address":"Rua Padres Franciscanos, 40",
    "sg:city":"Tomadas",
    "sg:orig_category":"Centros De Educaci\u00d3n Especial",
    "sg:phone":"+34 986 35 02 84",
    "sg:postcode":"36379",
    "sg:province":"Pontevedra",
    "wof:name":"C.e.i.p.carlos Casares",
    "wof:placetype":"venue"
},
  "geometry": {"coordinates":[-8.792509079,42.1199798584],"type":"Point"}
}