{
  "type": "Feature",
  "properties": {
    "addr:full":"Carretera Lloret-vidreras, Km. 0012,0 Lloret Mar Girona 17310",
    "addr:postcode":"17310",
    "addr:street":"Carretera Lloret-Vidreras Km. 0012,0 Lloret",
    "iso:country":"ES",
    "sg:address":"Carretera Lloret-vidreras, Km. 0012,0",
    "sg:city":"Lloret Mar",
    "sg:orig_category":"Hormigonados",
    "sg:phone":"+34 972 37 09 49",
    "sg:postcode":"17310",
    "sg:province":"Girona",
    "wof:name":"Suberolita S.a.",
    "wof:placetype":"venue"
},
  "geometry": {"coordinates":[2.846834898,41.6981697083],"type":"Point"}
}