{
  "type": "Feature",
  "properties": {
    "iso:country":"ES",
    "sg:address":"Calle de Ametzabide, 44",
    "sg:city":"Berreagamendi",
    "sg:orig_category":"Cintas Transportadoras",
    "sg:phone":"+34 946 74 61 83",
    "sg:postcode":"48100",
    "sg:province":"Vizcaya",
    "wof:name":"Bandas Transportadoras Del Norte S.a.",
    "wof:placetype":"venue"
},
  "geometry": {"coordinates":[-2.8400509357,43.3231582642],"type":"Point"}
}