{
  "type": "Feature",
  "properties": {
    "addr:full":"Kale Nagusia, 21 Legazpi Guip\u00f9zcoa 20230",
    "addr:housenumber":"21",
    "addr:postcode":"20230",
    "addr:street":"Kale Nagusia;Guipu\u0300Zcoa",
    "iso:country":"ES",
    "sg:address":"Kale Nagusia, 21",
    "sg:city":"Legazpi",
    "sg:orig_category":"Zapatos (al Por Menor)",
    "sg:phone":"+34 943 73 09 49",
    "sg:postcode":"20230",
    "sg:province":"Guip\u00f9zcoa",
    "wof:name":"Zapateria I\u00f1aki, Maria Aranzazu Aseginolaza Izagirre",
    "wof:placetype":"venue"
},
  "geometry": {"coordinates":[-2.332228899,43.0526123047],"type":"Point"}
}