{
  "type": "Feature",
  "properties": {
    "iso:country":"ES",
    "sg:address":"Calle de Santa Lucia, 10",
    "sg:city":"Valladolid",
    "sg:orig_category":"Arreglo, Reparaci\u00d3n, Piezas Sueltas De Televisi\u00d3n, V\u00cddeo, Hi",
    "sg:phone":"+34 983 29 51 04",
    "sg:postcode":"47005",
    "sg:province":"Valladolid",
    "wof:name":"Ganso Martin Jose Antonio",
    "wof:placetype":"venue"
},
  "geometry": {"coordinates":[-4.7176790237,41.6492385864],"type":"Point"}
}