{
  "type": "Feature",
  "properties": {
    "addr:full":"Ctra. Pte. Genil, Km. 0008,0 Jauja C\u00f3rdoba 14911",
    "addr:postcode":"14911",
    "addr:street":"Ctra. Pte. Genil Km. 0008,0;Co\u0301Rdoba",
    "iso:country":"ES",
    "sg:address":"Ctra. Pte. Genil, Km. 0008,0",
    "sg:city":"Jauja",
    "sg:orig_category":"Aceites Y Grasas Alimentarias (fabricaci\u00d3n, Al Por Mayor)",
    "sg:phone":"+34 957 33 40 16",
    "sg:postcode":"14911",
    "sg:province":"C\u00f3rdoba",
    "wof:name":"Explotaciones Agricolas Raban S.a.",
    "wof:placetype":"venue"
},
  "geometry": {"coordinates":[-4.6554641724,37.3033676147],"type":"Point"}
}