{
  "type": "Feature",
  "properties": {
    "addr:full":"Pol Ind Naviluz, 35 Huelva Huelva 21007",
    "addr:housenumber":"35",
    "addr:postcode":"21007",
    "addr:street":"Naviluz",
    "iso:country":"ES",
    "sg:address":"Pol Ind Naviluz, 35",
    "sg:city":"Huelva",
    "sg:orig_category":"Cajas Para Embalar",
    "sg:phone":"+34 959 22 67 27",
    "sg:postcode":"21007",
    "sg:province":"Huelva",
    "wof:name":"Caja Rural Del Sur Sociedad Cooperativa",
    "wof:placetype":"venue"
},
  "geometry": {"coordinates":[-6.9495940208,37.256313324],"type":"Point"}
}