{
  "type": "Feature",
  "properties": {
    "iso:country":"ES",
    "sg:address":"Calle de Alameda Las Llanas, 22",
    "sg:city":"Sestao",
    "sg:orig_category":"Mercer\u00cda, Lencer\u00cda (al Por Menor)",
    "sg:phone":"+34 944 95 49 86",
    "sg:postcode":"48910",
    "sg:province":"Vizcaya",
    "wof:name":"Felix Fragua Rodriguez",
    "wof:placetype":"venue"
},
  "geometry": {"coordinates":[-3.011131525,43.3117294312],"type":"Point"}
}