{
  "type": "Feature",
  "properties": {
    "iso:country":"ES",
    "sg:address":"C. Roig(pol Ind Cossos), 5",
    "sg:city":"Fortia",
    "sg:orig_category":"M\u00c1rmoles, Granitos Y Piedras Naturales",
    "sg:phone":"+34 972 53 43 17",
    "sg:postcode":"17469",
    "sg:province":"Girona",
    "wof:name":"Piedra Y Marmoles Alfaro S.l.",
    "wof:placetype":"venue"
},
  "geometry": {"coordinates":[2.9704549313,42.2177505493],"type":"Point"}
}