{
  "type": "Feature",
  "properties": {
    "addr:full":"Carrer de Pere Martell (de), 28 Tarragona Tarragona 43005",
    "addr:housenumber":"28",
    "addr:postcode":"43005",
    "addr:street":"Carrer De Pere Martell De",
    "iso:country":"ES",
    "sg:address":"Carrer de Pere Martell (de), 28",
    "sg:city":"Tarragona",
    "sg:orig_category":"Asesor\u00cda De Formaci\u00d3n Y Gesti\u00d3n De Personal",
    "sg:phone":"+34 977 24 70 33",
    "sg:postcode":"43005",
    "sg:province":"Tarragona",
    "wof:name":"Quantum Assessors Scp",
    "wof:placetype":"venue"
},
  "geometry": {"coordinates":[1.2442779541,41.115737915],"type":"Point"}
}