{
  "type": "Feature",
  "properties": {
    "iso:country":"ES",
    "sg:address":"Ctra Vadillo, 1",
    "sg:city":"Talveila",
    "sg:orig_category":"Papel (al Por Mayor)",
    "sg:phone":"+34 975 37 53 40",
    "sg:postcode":"42148",
    "sg:province":"Soria",
    "wof:name":"Perez Martinez Maria Jesus",
    "wof:placetype":"venue"
},
  "geometry": {"coordinates":[-3.0333669186,41.7962532043],"type":"Point"}
}