{
  "type": "Feature",
  "properties": {
    "iso:country":"ES",
    "sg:address":"Calle de Mariano Lui\u00d1a, 16",
    "sg:city":"Navia",
    "sg:orig_category":"Ropa Para Caballeros (al Por Menor)",
    "sg:phone":"+34 985 63 03 09",
    "sg:postcode":"33710",
    "sg:province":"Asturias",
    "wof:name":"Dados Moda C.b",
    "wof:placetype":"venue"
},
  "geometry": {"coordinates":[-6.7231588364,43.5393867493],"type":"Point"}
}