{
  "type": "Feature",
  "properties": {
    "addr:full":"Calle de Eduardo Zamacois, 9 Santa Cruz De Tenerife Santa Cruz De Tenerife 38005",
    "addr:housenumber":"9",
    "addr:postcode":"38005",
    "addr:street":"Calle De Eduardo Zamacois",
    "iso:country":"ES",
    "sg:address":"Calle de Eduardo Zamacois, 9",
    "sg:city":"Santa Cruz De Tenerife",
    "sg:classifiers":[
        {
            "category":"Personal",
            "subcategory":"Barber",
            "type":"Services"
        }
    ],
    "sg:phone":"+34 922 20 29 59",
    "sg:postcode":"38005",
    "sg:province":"Santa Cruz De Tenerife",
    "sg:tags":[
        "caballeros",
        "de",
        "peluqueros"
    ],
    "wof:name":"Coello Diaz Juan Jose",
    "wof:placetype":"venue"
},
  "geometry": {"coordinates":[-16.2617473602,28.4617729187],"type":"Point"}
}