{
  "type": "Feature",
  "properties": {
    "addr:full":"Calle de Pe\u00d1uelas, 34 Marbella M\u00e1laga 29600",
    "addr:housenumber":"34",
    "addr:postcode":"29600",
    "addr:street":"Calle De Pen\u0303Uelas;Ma\u0301Laga",
    "iso:country":"ES",
    "sg:address":"Calle de Pe\u00d1uelas, 34",
    "sg:city":"Marbella",
    "sg:orig_category":"Bancos",
    "sg:phone":"+34 952 77 36 08",
    "sg:postcode":"29600",
    "sg:province":"M\u00e1laga",
    "sg:website":"www.bancoatlantico.es",
    "wof:name":"Banc Sabadell S.a.",
    "wof:placetype":"venue"
},
  "geometry": {"coordinates":[-4.8808970451,36.5113449097],"type":"Point"}
}