{
  "type": "Feature",
  "properties": {
    "iso:country":"ES",
    "sg:address":"Calle de Joaquin Orozco, 15",
    "sg:city":"Alacant",
    "sg:orig_category":"Granos Y Semillas (producci\u00d3n, Al Por Mayor)",
    "sg:phone":"+34 965 92 20 44",
    "sg:postcode":"03006",
    "sg:province":"Alicante",
    "wof:name":"Vilmorin Iberica S. A.",
    "wof:placetype":"venue"
},
  "geometry": {"coordinates":[-0.498149991,38.3440246582],"type":"Point"}
}