{
  "type": "Feature",
  "properties": {
    "addr:full":"Carrer de Despuig, 4 Palma Islas Baleares 07013",
    "addr:housenumber":"4",
    "addr:postcode":"07013",
    "addr:street":"Carrer De Despuig",
    "iso:country":"ES",
    "sg:address":"Carrer de Despuig, 4",
    "sg:city":"Palma",
    "sg:orig_category":"Telas Y Sedas (al Por Menor)",
    "sg:phone":"+34 971 45 46 62",
    "sg:postcode":"07013",
    "sg:province":"Islas Baleares",
    "sg:website":"www.sattler-europe.com",
    "wof:name":"Ribot Ribot Bartolome",
    "wof:placetype":"venue"
},
  "geometry": {"coordinates":[2.6363530159,39.5756950378],"type":"Point"}
}