{
  "type": "Feature",
  "properties": {
    "iso:country":"ES",
    "sg:address":"Calle de Joaquin Sama Naharro, 6",
    "sg:city":"Cordoba",
    "sg:orig_category":"Centros De Salud",
    "sg:phone":"+34 957 40 44 83",
    "sg:postcode":"14006",
    "sg:province":"C\u00f3rdoba",
    "wof:name":"Lumpie Garcia Juan Leonardo",
    "wof:placetype":"venue"
},
  "geometry": {"coordinates":[-4.7853841782,37.8942947388],"type":"Point"}
}