{
  "type": "Feature",
  "properties": {
    "addr:full":"Avda Juan Pablo Ii, 2 Avila \u00c1vila 05002",
    "addr:housenumber":"2",
    "addr:postcode":"05002",
    "addr:street":"Avda Juan Pablo Ii;A\u0301Vila",
    "iso:country":"ES",
    "sg:address":"Avda Juan Pablo Ii, 2",
    "sg:city":"Avila",
    "sg:orig_category":"Fotograf\u00cda Art\u00cdstica Y Retratos",
    "sg:phone":"+34 920 22 30 05",
    "sg:postcode":"05002",
    "sg:province":"\u00c1vila",
    "wof:name":"Salva Fotografo S.l.",
    "wof:placetype":"venue"
},
  "geometry": {"coordinates":[-4.7009401321,40.6479415894],"type":"Point"}
}