{
  "type": "Feature",
  "properties": {
    "addr:full":"Pque Joyero (p I Pque Joyero), 89 Cordoba C\u00f3rdoba 14005",
    "addr:housenumber":"89",
    "addr:postcode":"14005",
    "addr:street":"P I Pque Joyero;Co\u0301Rdoba",
    "iso:country":"ES",
    "sg:address":"Pque Joyero (p I Pque Joyero), 89",
    "sg:city":"Cordoba",
    "sg:orig_category":"Dorados, Plater\u00cda (orfebrer\u00cda)",
    "sg:phone":"+34 957 49 04 26",
    "sg:postcode":"14005",
    "sg:province":"C\u00f3rdoba",
    "wof:name":"Rodriguez Aviles S.l.",
    "wof:placetype":"venue"
},
  "geometry": {"coordinates":[-4.8545742035,37.8489761353],"type":"Point"}
}