{
  "type": "Feature",
  "properties": {
    "iso:country":"ES",
    "sg:address":"Avda Virgen De La Vega, 1",
    "sg:city":"Moraleja",
    "sg:orig_category":"Farmacias",
    "sg:phone":"+34 927 51 52 72",
    "sg:postcode":"10840",
    "sg:province":"C\u00e1ceres",
    "wof:name":"Bueno Becerra Felipe",
    "wof:placetype":"venue"
},
  "geometry": {"coordinates":[-6.6611142159,40.0666694641],"type":"Point"}
}