{
  "type": "Feature",
  "properties": {
    "addr:full":"Pase Alcalde Sanchez Prados, 5 Ceuta Ceuta 51001",
    "addr:housenumber":"5",
    "addr:postcode":"51001",
    "addr:street":"Alcalde;Prados",
    "iso:country":"ES",
    "sg:address":"Pase Alcalde Sanchez Prados, 5",
    "sg:city":"Ceuta",
    "sg:orig_category":"Lencer\u00cda Femenina, Corseter\u00cda, Trajes De Ba\u00d1o (al Por Menor)",
    "sg:phone":"+34 956 51 78 46",
    "sg:postcode":"51001",
    "sg:province":"Ceuta",
    "wof:name":"Bentolila Hachuel Perla",
    "wof:placetype":"venue"
},
  "geometry": {"coordinates":[-5.3302302361,35.8947601318],"type":"Point"}
}