{
  "type": "Feature",
  "properties": {
    "iso:country":"ES",
    "sg:address":"Calle de Espa\u00d1a, 2",
    "sg:city":"Fuengirola",
    "sg:orig_category":"M\u00c9dicos: Estomatolog\u00cda",
    "sg:phone":"+34 952 47 58 97",
    "sg:postcode":"29640",
    "sg:province":"M\u00e1laga",
    "wof:name":"Portillo  Mario Roberto",
    "wof:placetype":"venue"
},
  "geometry": {"coordinates":[-4.6272587776,36.540687561],"type":"Point"}
}