{
  "type": "Feature",
  "properties": {
    "iso:country":"ES",
    "sg:address":"Avda Fernando Calzadilla, 23",
    "sg:city":"Badajoz",
    "sg:orig_category":"M\u00c9dicos: Nefrolog\u00cda",
    "sg:phone":"+34 924 23 67 09",
    "sg:postcode":"06004",
    "sg:province":"Badajoz",
    "wof:name":"Cruz Moreno Angel",
    "wof:placetype":"venue"
},
  "geometry": {"coordinates":[-6.9726858139,38.8700828552],"type":"Point"}
}