{
  "type": "Feature",
  "properties": {
    "addr:full":"Avda Ramon Y Cajal, 28 Fuengirola M\u00e1laga 29640",
    "addr:housenumber":"28",
    "addr:postcode":"29640",
    "addr:street":"Avda Ramon Y Cajal;Ma\u0301Laga",
    "iso:country":"ES",
    "sg:address":"Avda Ramon Y Cajal, 28",
    "sg:city":"Fuengirola",
    "sg:orig_category":"Ropa Para Se\u00d1oras Y Caballeros (al Por Menor)",
    "sg:phone":"+34 952 46 46 50",
    "sg:postcode":"29640",
    "sg:province":"M\u00e1laga",
    "wof:name":"Riadco Import-export S.l.",
    "wof:placetype":"venue"
},
  "geometry": {"coordinates":[-4.619166851,36.5459136963],"type":"Point"}
}