{
  "type": "Feature",
  "properties": {
    "addr:full":"Calle de Gueldera, S/n Pto. Rosario Las Palmas 35600",
    "addr:housenumber":"s / n",
    "addr:postcode":"35600",
    "addr:street":"Calle De Gueldera;Pto. Rosario Las",
    "iso:country":"ES",
    "sg:address":"Calle de Gueldera, S/n",
    "sg:city":"Pto. Rosario",
    "sg:orig_category":"Rejas Y Cortinas Met\u00c1licas",
    "sg:phone":"+34 928 34 46 26",
    "sg:postcode":"35600",
    "sg:province":"Las Palmas",
    "sg:website":"www.cmburgos.es",
    "wof:name":"Cierres Metalicos Canarias S.l.",
    "wof:placetype":"venue"
},
  "geometry": {"coordinates":[-13.8644685745,28.5023498535],"type":"Point"}
}