{
  "type": "Feature",
  "properties": {
    "addr:full":"Helbarrena Auzoa, 72 Helbarrena Guip\u00f9zcoa 20211",
    "addr:housenumber":"72",
    "addr:postcode":"20211",
    "addr:street":"Helbarrena Auzoa;Guipu\u0300Zcoa",
    "iso:country":"ES",
    "sg:address":"Helbarrena Auzoa, 72",
    "sg:city":"Helbarrena",
    "sg:orig_category":"Barbacoas Y Accesorios",
    "sg:phone":"+34 943 18 00 19",
    "sg:postcode":"20211",
    "sg:province":"Guip\u00f9zcoa",
    "wof:name":"Sanchez Paredes I\u00f1igo",
    "wof:placetype":"venue"
},
  "geometry": {"coordinates":[-2.176306963,43.0065307617],"type":"Point"}
}