{
  "type": "Feature",
  "properties": {
    "addr:full":"Avda Barcelona, 30 Malaga M\u00e1laga 29009",
    "addr:housenumber":"30",
    "addr:postcode":"29009",
    "addr:street":"Avda Barcelona;Ma\u0301Laga",
    "iso:country":"ES",
    "sg:address":"Avda Barcelona, 30",
    "sg:city":"Malaga",
    "sg:orig_category":"Cajas Para Embalar",
    "sg:phone":"+34 952 07 01 55",
    "sg:postcode":"29009",
    "sg:province":"M\u00e1laga",
    "wof:name":"Cajamar",
    "wof:placetype":"venue"
},
  "geometry": {"coordinates":[-4.4312300682,36.7247047424],"type":"Point"}
}