{
  "type": "Feature",
  "properties": {
    "iso:country":"ES",
    "sg:address":"Pol Can Famada, 22",
    "sg:city":"Banyoles",
    "sg:orig_category":"Empresas De Desmonte",
    "sg:phone":"+34 972 58 13 22",
    "sg:postcode":"17820",
    "sg:province":"Girona",
    "wof:name":"Excavacions Masdevall S.l.",
    "wof:placetype":"venue"
},
  "geometry": {"coordinates":[2.7649800777,42.1169548035],"type":"Point"}
}