{
  "type": "Feature",
  "properties": {
    "addr:full":"Calle de Alminares Del Genil, S/n Granada Granada 18006",
    "addr:housenumber":"s / n",
    "addr:postcode":"18006",
    "addr:street":"Calle De Alminares Del Genil",
    "iso:country":"ES",
    "sg:address":"Calle de Alminares Del Genil, S/n",
    "sg:city":"Granada",
    "sg:orig_category":"Frutas, Legumbres Frescas Y Tempranas (al Por Menor)",
    "sg:phone":"+34 958 81 32 11",
    "sg:postcode":"18006",
    "sg:province":"Granada",
    "wof:name":"Toro Padilla Juan-manuel",
    "wof:placetype":"venue"
},
  "geometry": {"coordinates":[-3.5958869457,37.1667938232],"type":"Point"}
}