{
  "type": "Feature",
  "properties": {
    "addr:full":"Calle de Cruz Blanca, 3 Vitoria-gasteiz \u00c1lava 01012",
    "addr:housenumber":"3",
    "addr:postcode":"01012",
    "addr:street":"Calle De Cruz Blanca",
    "iso:country":"ES",
    "sg:address":"Calle de Cruz Blanca, 3",
    "sg:city":"Vitoria-gasteiz",
    "sg:orig_category":"Peluqueros: De Se\u00d1oras",
    "sg:phone":"+34 945 20 05 46",
    "sg:postcode":"01012",
    "sg:province":"\u00c1lava",
    "sg:website":"www.paginasamarillas.es/estilistasgrecia\u00efn",
    "wof:name":"Fernandez Aguirregabiria Leyre",
    "wof:placetype":"venue"
},
  "geometry": {"coordinates":[-2.6777608395,42.8523101807],"type":"Point"}
}