{
  "type": "Feature",
  "properties": {
    "addr:full":"Carrer de Ramon Turro, 100 Barcelona Barcelona 08005",
    "addr:housenumber":"100",
    "addr:postcode":"08005",
    "addr:street":"Carrer De Ramon Turro",
    "iso:country":"ES",
    "sg:address":"Carrer de Ramon Turro, 100",
    "sg:city":"Barcelona",
    "sg:classifiers":[
        {
            "category":"Building & Trades",
            "subcategory":"Construction",
            "type":"Services"
        }
    ],
    "sg:phone":"+34 932 25 18 08",
    "sg:postcode":"08005",
    "sg:province":"Barcelona",
    "sg:tags":[
        "calefacci\u00d3n",
        "central",
        "para",
        "de",
        "fabricaci\u00d3n",
        "caldera"
    ],
    "wof:name":"Vapor Corwy S.l.",
    "wof:placetype":"venue"
},
  "geometry": {"coordinates":[2.1964020729,41.3948402405],"type":"Point"}
}