{
  "type": "Feature",
  "properties": {
    "addr:full":"Carrer de Carles Buigas, 61 Sant Feliu Llobregat Barcelona 08980",
    "addr:housenumber":"61",
    "addr:postcode":"08980",
    "addr:street":"Carrer De Carles Buigas",
    "iso:country":"ES",
    "sg:address":"Carrer de Carles Buigas, 61",
    "sg:city":"Sant Feliu Llobregat",
    "sg:orig_category":"Edici\u00d3n De Diarios, Revistas, Boletines",
    "sg:phone":"+34 936 66 38 85",
    "sg:postcode":"08980",
    "sg:province":"Barcelona",
    "wof:name":"Bibliogemma S.l.",
    "wof:placetype":"venue"
},
  "geometry": {"coordinates":[2.0525050163,41.3849411011],"type":"Point"}
}