{
  "type": "Feature",
  "properties": {
    "iso:country":"ES",
    "sg:address":"Plaz Cristo Del Rescate, 6",
    "sg:city":"San Juan",
    "sg:orig_category":"Arreglo, Reparaci\u00d3n, Piezas Sueltas De Televisi\u00d3n, V\u00cddeo, Hi",
    "sg:phone":"+34 968 21 04 70",
    "sg:postcode":"30003",
    "sg:province":"Murcia",
    "wof:name":"Martinez Ballester Jose Eduardo",
    "wof:placetype":"venue"
},
  "geometry": {"coordinates":[-1.1298867464,37.9834747314],"type":"Point"}
}