{
  "type": "Feature",
  "properties": {
    "addr:full":"Avda Antonio Machado, 108 Castilblanco De Los Arroyos Sevilla 41230",
    "addr:housenumber":"108",
    "addr:postcode":"41230",
    "addr:street":"Avda Antonio Machado",
    "iso:country":"ES",
    "sg:address":"Avda Antonio Machado, 108",
    "sg:city":"Castilblanco De Los Arroyos",
    "sg:orig_category":"Droguer\u00cdas (al Por Menor)",
    "sg:phone":"+34 955 73 48 03",
    "sg:postcode":"41230",
    "sg:province":"Sevilla",
    "wof:name":"Martin Cordero Adolfo",
    "wof:placetype":"venue"
},
  "geometry": {"coordinates":[-5.9859380722,37.6757621765],"type":"Point"}
}