{
  "type": "Feature",
  "properties": {
    "iso:country":"ES",
    "sg:address":"Avda Primero De Mayo, 43",
    "sg:city":"Palmas De Gran Canaria",
    "sg:orig_category":"Artes Gr\u00c1ficas, Artes Pl\u00c1sticas (curso)",
    "sg:phone":"+34 928 36 52 66",
    "sg:postcode":"35002",
    "sg:province":"Las Palmas",
    "wof:name":"Famarca S. L.",
    "wof:placetype":"venue"
},
  "geometry": {"coordinates":[-15.4202642441,28.1059780121],"type":"Point"}
}