{
  "type": "Feature",
  "properties": {
    "iso:country":"ES",
    "sg:address":"Carrer de Sant Isidre, 113",
    "sg:city":"Palleja",
    "sg:orig_category":"Electricidad, Electr\u00d3nica: Material Y Suministros (al Por Mayor)",
    "sg:phone":"+34 936 63 20 15",
    "sg:postcode":"08780",
    "sg:province":"Barcelona",
    "wof:name":"Sandoval Martinez Manuel",
    "wof:placetype":"venue"
},
  "geometry": {"coordinates":[1.9976799488,41.4258651733],"type":"Point"}
}