{
  "type": "Feature",
  "properties": {
    "addr:full":"Avda Andalucia, 111 Ayamonte Huelva 21400",
    "addr:housenumber":"111",
    "addr:postcode":"21400",
    "addr:street":"Avda Andalucia",
    "iso:country":"ES",
    "sg:address":"Avda Andalucia, 111",
    "sg:city":"Ayamonte",
    "sg:orig_category":"M\u00c9dicos: Ginecolog\u00cda Y Obstetricia",
    "sg:phone":"+34 959 47 15 00",
    "sg:postcode":"21400",
    "sg:province":"Huelva",
    "wof:name":"Centro Ginecologico Y Obstretico S.l.",
    "wof:placetype":"venue"
},
  "geometry": {"coordinates":[-7.4004788399,37.2147102356],"type":"Point"}
}