{
  "type": "Feature",
  "properties": {
    "iso:country":"ES",
    "sg:address":"Ptge Vila De Lloret, 124",
    "sg:city":"Blanes",
    "sg:orig_category":"Centros De Educaci\u00d3n Especial",
    "sg:phone":"+34 972 33 67 66",
    "sg:postcode":"17300",
    "sg:province":"Girona",
    "wof:name":"Grup Escolar Carles Faust",
    "wof:placetype":"venue"
},
  "geometry": {"coordinates":[2.7914509773,41.6791992188],"type":"Point"}
}