{
  "type": "Feature",
  "properties": {
    "addr:full":"Carrer de Topete, 34 Terrassa Barcelona 08221",
    "addr:housenumber":"34",
    "addr:postcode":"08221",
    "addr:street":"Carrer De Topete",
    "iso:country":"ES",
    "sg:address":"Carrer de Topete, 34",
    "sg:city":"Terrassa",
    "sg:orig_category":"Internados & Ense\u00d1anza Privada",
    "sg:phone":"+34 937 85 83 55",
    "sg:postcode":"08221",
    "sg:province":"Barcelona",
    "wof:name":"Agrupacio Pedagogica Tecnos Societat Cooperativa Catalana Limit",
    "wof:placetype":"venue"
},
  "geometry": {"coordinates":[2.0167798996,41.5616340637],"type":"Point"}
}