{
  "type": "Feature",
  "properties": {
    "addr:full":"Ptda Almajada, 165 Mutxamel Alicante 03110",
    "addr:housenumber":"165",
    "addr:postcode":"03110",
    "addr:street":"Ptda Almajada",
    "iso:country":"ES",
    "sg:address":"Ptda Almajada, 165",
    "sg:city":"Mutxamel",
    "sg:orig_category":"Promotores Constructores",
    "sg:phone":"+34 965 95 54 00",
    "sg:postcode":"03110",
    "sg:province":"Alicante",
    "sg:website":"www.silvereagle.es",
    "wof:name":"Seop Obras Y Proyectos S.l.",
    "wof:placetype":"venue"
},
  "geometry": {"coordinates":[-0.4448040128,38.4151039124],"type":"Point"}
}