{
  "type": "Feature",
  "properties": {
    "iso:country":"ES",
    "sg:address":"Mi\u00f1ano Mayor, 9",
    "sg:city":"Mi\u00e7ano Mayor",
    "sg:orig_category":"M\u00c9dicos: Medicina General",
    "sg:phone":"+34 945 29 83 03",
    "sg:postcode":"01510",
    "sg:province":"\u00c1lava",
    "sg:website":"www.cardgirus.com",
    "wof:name":"Cardgirus I.d.i. S.l.",
    "wof:placetype":"venue"
},
  "geometry": {"coordinates":[-2.6463301182,42.916557312],"type":"Point"}
}