{
  "type": "Feature",
  "properties": {
    "iso:country":"ES",
    "sg:address":"Calle de Do\u00d1ana (de), 46",
    "sg:city":"Humanes De Madrid",
    "sg:orig_category":"Arenas, Guijarros Y Granulados",
    "sg:phone":"+34 916 90 38 48",
    "sg:postcode":"28970",
    "sg:province":"Madrid",
    "wof:name":"Aridos Envasa S.l.",
    "wof:placetype":"venue"
},
  "geometry": {"coordinates":[-3.817368269,40.2700538635],"type":"Point"}
}