{
  "type": "Feature",
  "properties": {
    "iso:country":"ES",
    "sg:address":"Carrer de Sant Agusti, 5",
    "sg:city":"Barcelona",
    "sg:orig_category":"Estudios De Grabaci\u00d3n Sonora",
    "sg:phone":"+34 932 37 30 56",
    "sg:postcode":"08012",
    "sg:province":"Barcelona",
    "wof:name":"Edivox S.l.",
    "wof:placetype":"venue"
},
  "geometry": {"coordinates":[2.1609170437,41.3984069824],"type":"Point"}
}