{
  "type": "Feature",
  "properties": {
    "iso:country":"ES",
    "sg:address":"Calle de Velazquez, 42",
    "sg:city":"Madrid",
    "sg:orig_category":"Telas Para Tapizar, Cortinas, Pasamaner\u00cda (fabricaci\u00d3n, Al Por Mayor)",
    "sg:phone":"+34 915 75 50 99",
    "sg:postcode":"28001",
    "sg:province":"Madrid",
    "wof:name":"Gaston Y Daniela, S.a.",
    "wof:placetype":"venue"
},
  "geometry": {"coordinates":[-3.6838710308,40.4261169434],"type":"Point"}
}