{
  "type": "Feature",
  "properties": {
    "addr:full":"Carrer de Andorra, 19 S. Boi Llobregat Barcelona 08830",
    "addr:housenumber":"19",
    "addr:postcode":"08830",
    "addr:street":"Carrer De Andorra",
    "iso:country":"ES",
    "sg:address":"Carrer de Andorra, 19",
    "sg:city":"S. Boi Llobregat",
    "sg:orig_category":"Materias Pl\u00c1sticas: Material, Equipos Industriales",
    "sg:phone":"+34 936 52 56 80",
    "sg:postcode":"08830",
    "sg:province":"Barcelona",
    "sg:website":"www.alimatic.com",
    "wof:name":"Alimatic S.l.",
    "wof:placetype":"venue"
},
  "geometry": {"coordinates":[2.0418598652,41.3302993774],"type":"Point"}
}