{
  "type": "Feature",
  "properties": {
    "iso:country":"ES",
    "sg:address":"Calle de Aragon, 93",
    "sg:city":"Sevilla",
    "sg:orig_category":"Grabados",
    "sg:phone":"+34 954 63 14 70",
    "sg:postcode":"41006",
    "sg:province":"Sevilla",
    "sg:website":"www.unilaser.es.vg",
    "wof:name":"Unilaser Grabado Y Corte Laser S.l.u.",
    "wof:placetype":"venue"
},
  "geometry": {"coordinates":[-5.9604539871,37.3758926392],"type":"Point"}
}