{
  "type": "Feature",
  "properties": {
    "addr:full":"Calle de Padre Ignacio Ellacuria, 97 Laredo Cantabria 39770",
    "addr:housenumber":"97",
    "addr:postcode":"39770",
    "addr:street":"Calle De Padre Ignacio Ellacuria",
    "iso:country":"ES",
    "sg:address":"Calle de Padre Ignacio Ellacuria, 97",
    "sg:city":"Laredo",
    "sg:orig_category":"Mobiliario M\u00c9dico Y Quir\u00dargico",
    "sg:phone":"+34 942 60 59 24",
    "sg:postcode":"39770",
    "sg:province":"Cantabria",
    "wof:name":"Curvados C.m.c. S.a.",
    "wof:placetype":"venue"
},
  "geometry": {"coordinates":[-3.424405098,43.4075965881],"type":"Point"}
}