{
  "type": "Feature",
  "properties": {
    "addr:full":"Calle de Cristo, 16 Osuna Sevilla 41640",
    "addr:housenumber":"16",
    "addr:postcode":"41640",
    "addr:street":"Calle De Cristo",
    "iso:country":"ES",
    "sg:address":"Calle de Cristo, 16",
    "sg:city":"Osuna",
    "sg:orig_category":"Agencias Y Agentes Comerciales, Representantes",
    "sg:phone":"+34 954 81 20 17",
    "sg:postcode":"41640",
    "sg:province":"Sevilla",
    "wof:name":"Perez Martin Gerardo Antonio",
    "wof:placetype":"venue"
},
  "geometry": {"coordinates":[-5.1077303886,37.2382469177],"type":"Point"}
}