{
  "type": "Feature",
  "properties": {
    "iso:country":"ES",
    "sg:address":"Escollozes, S/n",
    "sg:city":"Fonz",
    "sg:orig_category":"Forjas Y Altos Hornos",
    "sg:phone":"+34 974 41 21 77",
    "sg:postcode":"22422",
    "sg:province":"Huesca",
    "wof:name":"Talleres Morancho Pallares S.l.",
    "wof:placetype":"venue"
},
  "geometry": {"coordinates":[0.252662003,42.0113563538],"type":"Point"}
}