{
  "type": "Feature",
  "properties": {
    "iso:country":"ES",
    "sg:address":"Cno. Pedac, 20",
    "sg:city":"Binissalem",
    "sg:orig_category":"Fabricaci\u00d3n, Instalaci\u00d3n De Armarios",
    "sg:phone":"+34 971 87 05 62",
    "sg:postcode":"07350",
    "sg:province":"Islas Baleares",
    "wof:name":"Sa Fusteria De Fora Vila S.l.",
    "wof:placetype":"venue"
},
  "geometry": {"coordinates":[2.8462650776,39.6886405945],"type":"Point"}
}