{
  "type": "Feature",
  "properties": {
    "addr:full":"Av Miraflores, 71 Hospitalet Llobregat Barcelona 08905",
    "addr:housenumber":"71",
    "addr:postcode":"08905",
    "addr:street":"Av Miraflores",
    "iso:country":"ES",
    "sg:address":"Av Miraflores, 71",
    "sg:city":"Hospitalet Llobregat",
    "sg:orig_category":"Inmobiliaria (agencias)",
    "sg:phone":"+34 933 34 45 50",
    "sg:postcode":"08905",
    "sg:province":"Barcelona",
    "wof:name":"Moreno Canales Rufino",
    "wof:placetype":"venue"
},
  "geometry": {"coordinates":[2.1081590652,41.3716888428],"type":"Point"}
}