{
  "type": "Feature",
  "properties": {
    "iso:country":"ES",
    "sg:address":"Plaz Portugalete, 4",
    "sg:city":"Valladolid",
    "sg:orig_category":"Agencias Y Agentes Comerciales, Representantes",
    "sg:phone":"+34 983 30 04 62",
    "sg:postcode":"47002",
    "sg:province":"Valladolid",
    "wof:name":"Gutierrez Mu\u00f1oz Mariano",
    "wof:placetype":"venue"
},
  "geometry": {"coordinates":[-4.7238650322,41.6534690857],"type":"Point"}
}