{
  "type": "Feature",
  "properties": {
    "iso:country":"ES",
    "sg:address":"Calle de Sevilla, 52",
    "sg:city":"Ejido",
    "sg:orig_category":"Ropa Para Beb\u00c9s Y Ni\u00d1os (confecci\u00d3n, Al Por Mayor)",
    "sg:phone":"+34 950 48 16 80",
    "sg:postcode":"04700",
    "sg:province":"Almer\u00eda",
    "wof:name":"Fornieles Lopez Soledad",
    "wof:placetype":"venue"
},
  "geometry": {"coordinates":[-2.8159089088,36.7703933716],"type":"Point"}
}