{
  "type": "Feature",
  "properties": {
    "addr:full":"Bruc (urb Can Fosalba), S/n Hostalets Pierola Barcelona 08781",
    "addr:housenumber":"s / n",
    "addr:postcode":"08781",
    "addr:street":"Urb Can Fosalba;Pierola Barcelona",
    "iso:country":"ES",
    "sg:address":"Bruc (urb Can Fosalba), S/n",
    "sg:city":"Hostalets Pierola",
    "sg:orig_category":"Agencias De Aduana",
    "sg:phone":"+34 937 71 05 00",
    "sg:postcode":"08781",
    "sg:province":"Barcelona",
    "wof:name":"Bercontres S.a",
    "wof:placetype":"venue"
},
  "geometry": {"coordinates":[1.765650034,41.5341262817],"type":"Point"}
}