{
  "type": "Feature",
  "properties": {
    "addr:full":"Calle de Salvador Dali, 79 Jumilla Murcia 30520",
    "addr:housenumber":"79",
    "addr:postcode":"30520",
    "addr:street":"Calle De Salvador Dali",
    "iso:country":"ES",
    "sg:address":"Calle de Salvador Dali, 79",
    "sg:city":"Jumilla",
    "sg:orig_category":"Promotores Constructores",
    "sg:phone":"+34 968 78 39 72",
    "sg:postcode":"30520",
    "sg:province":"Murcia",
    "wof:name":"Construcciones Y Contratas Palao Garcia S.l.",
    "wof:placetype":"venue"
},
  "geometry": {"coordinates":[-1.3151890039,38.4734306335],"type":"Point"}
}