{
  "type": "Feature",
  "properties": {
    "iso:country":"ES",
    "sg:address":"Plaz Plaza De Molinar, 2",
    "sg:city":"Sandamendi",
    "sg:orig_category":"Art\u00cdculos De Regalo (al Por Menor)",
    "sg:phone":"+34 946 79 93 90",
    "sg:postcode":"48192",
    "sg:province":"Vizcaya",
    "wof:name":"Aldama Pe\u00f1a Juan Luis",
    "wof:placetype":"venue"
},
  "geometry": {"coordinates":[-3.0741200447,43.1805000305],"type":"Point"}
}