{
  "type": "Feature",
  "properties": {
    "iso:country":"ES",
    "sg:address":"Joaquin Jarauta, 16",
    "sg:city":"Iru\u00f1a",
    "sg:orig_category":"Asociaciones, Organismos Culturales Y Socioeducativos",
    "sg:phone":"+34 948 22 52 18",
    "sg:postcode":"31001",
    "sg:province":"Navarra",
    "wof:name":"Pe\u00f1a Recreativa La Jarana",
    "wof:placetype":"venue"
},
  "geometry": {"coordinates":[-1.6457149982,42.8187637329],"type":"Point"}
}