{
  "type": "Feature",
  "properties": {
    "addr:full":"Carrer de Volta, 24 Terrassa Barcelona 08224",
    "addr:housenumber":"24",
    "addr:postcode":"08224",
    "addr:street":"Carrer De Volta",
    "iso:country":"ES",
    "sg:address":"Carrer de Volta, 24",
    "sg:city":"Terrassa",
    "sg:orig_category":"Quiropr\u00c1cticos",
    "sg:phone":"+34 937 88 41 12",
    "sg:postcode":"08224",
    "sg:province":"Barcelona",
    "wof:name":"Santaeulalia Moixi Josep",
    "wof:placetype":"venue"
},
  "geometry": {"coordinates":[2.0070309639,41.5636672974],"type":"Point"}
}