{
  "type": "Feature",
  "properties": {
    "iso:country":"ES",
    "sg:address":"Rua Cuntis, 14",
    "sg:city":"Ferrol",
    "sg:orig_category":"Abogados",
    "sg:phone":"+34 981 37 03 74",
    "sg:postcode":"15403",
    "sg:province":"La Coru\u00f1a",
    "wof:name":"Garcia De La Rocha Fojo Julio",
    "wof:placetype":"venue"
},
  "geometry": {"coordinates":[-8.2289009094,43.4869728088],"type":"Point"}
}