{
  "type": "Feature",
  "properties": {
    "iso:country":"ES",
    "sg:address":"Calle de Cuartel De Artilleria, 7",
    "sg:city":"Carmen",
    "sg:orig_category":"Formaci\u00d3n Continuada (variada)",
    "sg:phone":"+34 968 25 57 38",
    "sg:postcode":"30002",
    "sg:province":"Murcia",
    "wof:name":"Marco Medina Maria Jesus",
    "wof:placetype":"venue"
},
  "geometry": {"coordinates":[-1.1298867464,37.9834747314],"type":"Point"}
}