{
  "type": "Feature",
  "properties": {
    "iso:country":"ES",
    "sg:address":"Caddie Plaza Del - Plaza Caddie Del, 1",
    "sg:city":"Atsobakar",
    "sg:orig_category":"Asesor\u00cda, Estudio Y Control Medioambiental",
    "sg:phone":"+34 943 36 44 62",
    "sg:postcode":"20160",
    "sg:province":"Guip\u00f9zcoa",
    "wof:name":"Ekos Estudios Ambientales S.a.",
    "wof:placetype":"venue"
},
  "geometry": {"coordinates":[-2.020414114,43.2698173523],"type":"Point"}
}