{
  "type": "Feature",
  "properties": {
    "iso:country":"ES",
    "sg:address":"Calle de Compositor Ramon Medina, 16",
    "sg:city":"Cordoba",
    "sg:orig_category":"Material Y Herramientas Agr\u00cdcolas",
    "sg:phone":"+34 957 25 18 74",
    "sg:postcode":"14010",
    "sg:province":"C\u00f3rdoba",
    "wof:name":"Talleres Aurelio S.c.",
    "wof:placetype":"venue"
},
  "geometry": {"coordinates":[-4.761742115,37.8894615173],"type":"Point"}
}