{
  "type": "Feature",
  "properties": {
    "iso:country":"ES",
    "sg:address":"Calle de Perez Galdos, 6",
    "sg:city":"Miranda Ebro",
    "sg:orig_category":"Servicio De Salud",
    "sg:phone":"+34 947 32 47 11",
    "sg:postcode":"09200",
    "sg:province":"Burgos",
    "wof:name":"Almacenes Gadymar S. A.",
    "wof:placetype":"venue"
},
  "geometry": {"coordinates":[-2.9509818554,42.6857757568],"type":"Point"}
}