{
  "type": "Feature",
  "properties": {
    "addr:full":"Carrer de Sant Sebastia, 277 Sabadell Barcelona 08203",
    "addr:housenumber":"277",
    "addr:postcode":"08203",
    "addr:street":"Carrer De Sant Sebastia",
    "iso:country":"ES",
    "sg:address":"Carrer de Sant Sebastia, 277",
    "sg:city":"Sabadell",
    "sg:orig_category":"Ropa Para Ni\u00d1os (al Por Menor)",
    "sg:phone":"+34 937 10 75 51",
    "sg:postcode":"08203",
    "sg:province":"Barcelona",
    "wof:name":"M.c. Ferva S.l.",
    "wof:placetype":"venue"
},
  "geometry": {"coordinates":[2.1052279472,41.5337371826],"type":"Point"}
}