{
  "type": "Feature",
  "properties": {
    "addr:full":"Avda Mari\u00d1as, 307 Perillo La Coru\u00f1a 15172",
    "addr:housenumber":"307",
    "addr:postcode":"15172",
    "addr:street":"Avda Marin\u0303As;Perillo La Corun\u0303A",
    "iso:country":"ES",
    "sg:address":"Avda Mari\u00d1as, 307",
    "sg:city":"Perillo",
    "sg:orig_category":"Agentes, Concesionarios Y Sucursales De Veh\u00cdculos",
    "sg:phone":"+34 981 63 40 25",
    "sg:postcode":"15172",
    "sg:province":"La Coru\u00f1a",
    "wof:name":"Gadoc S.l.",
    "wof:placetype":"venue"
},
  "geometry": {"coordinates":[-8.3668327332,43.3291549683],"type":"Point"}
}