{
  "type": "Feature",
  "properties": {
    "iso:country":"ES",
    "sg:address":"Calle de Lozano De Torres, 9",
    "sg:city":"Malaga",
    "sg:orig_category":"Perfumer\u00cda Y Cosm\u00c9tica (fabricaci\u00d3n, Al Por Mayor)",
    "sg:phone":"+34 952 65 34 48",
    "sg:postcode":"29013",
    "sg:province":"M\u00e1laga",
    "wof:name":"Belleza Sur S.c.",
    "wof:placetype":"venue"
},
  "geometry": {"coordinates":[-4.416405201,36.7302017212],"type":"Point"}
}