{
  "type": "Feature",
  "properties": {
    "iso:country":"ES",
    "sg:address":"Pl Culla, 4",
    "sg:city":"Alfafar",
    "sg:orig_category":"Transportes A\u00c9reos",
    "sg:phone":"+34 963 17 35 22",
    "sg:postcode":"46910",
    "sg:province":"Valencia",
    "wof:name":"Air Sport Charters S.l.",
    "wof:placetype":"venue"
},
  "geometry": {"coordinates":[-0.3781557083,39.4165382385],"type":"Point"}
}