{
  "type": "Feature",
  "properties": {
    "addr:full":"Calle de Veintitres De Mayo, 75 Pto. Rosario Las Palmas 35600",
    "addr:housenumber":"75",
    "addr:postcode":"35600",
    "addr:street":"Calle De Veintitres De Mayo;Pto. Rosario Las",
    "iso:country":"ES",
    "sg:address":"Calle de Veintitres De Mayo, 75",
    "sg:city":"Pto. Rosario",
    "sg:orig_category":"Mec\u00c1nico Del Autom\u00d3vil",
    "sg:phone":"+34 928 53 17 44",
    "sg:postcode":"35600",
    "sg:province":"Las Palmas",
    "wof:name":"Gonzalez Fulgencio Andres",
    "wof:placetype":"venue"
},
  "geometry": {"coordinates":[-13.8636083603,28.4952087402],"type":"Point"}
}