{
  "type": "Feature",
  "properties": {
    "addr:full":"Trav Dalt, 125 Barcelona Barcelona 08024",
    "addr:housenumber":"125",
    "addr:postcode":"08024",
    "addr:street":"Trav Dalt",
    "iso:country":"ES",
    "sg:address":"Trav Dalt, 125",
    "sg:city":"Barcelona",
    "sg:orig_category":"Aparatos De Medida, Control, Regulaci\u00d3n Y Detecci\u00d3n",
    "sg:phone":"+34 932 84 47 64",
    "sg:postcode":"08024",
    "sg:province":"Barcelona",
    "wof:name":"Sepi\u00f1a Gimenez Enrique",
    "wof:placetype":"venue"
},
  "geometry": {"coordinates":[2.1592440605,41.4125213623],"type":"Point"}
}