{
  "type": "Feature",
  "properties": {
    "iso:country":"ES",
    "sg:address":"Plaz San Jose De Calasanz, S/n",
    "sg:city":"Bu\u00f1uel",
    "sg:orig_category":"Asociaciones Y Clubs Deportivos",
    "sg:phone":"+34 948 83 21 65",
    "sg:postcode":"31540",
    "sg:province":"Navarra",
    "wof:name":"Club Juvenil Sociedad Cooperativa",
    "wof:placetype":"venue"
},
  "geometry": {"coordinates":[-1.4449939728,41.98046875],"type":"Point"}
}