{
  "type": "Feature",
  "properties": {
    "addr:full":"Calle de Pascual Arbos, 38 Xirivella Valencia 46950",
    "addr:housenumber":"38",
    "addr:postcode":"46950",
    "addr:street":"Calle De Pascual Arbos",
    "iso:country":"ES",
    "sg:address":"Calle de Pascual Arbos, 38",
    "sg:city":"Xirivella",
    "sg:orig_category":"Agencias Y Agentes Comerciales, Representantes",
    "sg:phone":"+34 963 79 75 84",
    "sg:postcode":"46950",
    "sg:province":"Valencia",
    "wof:name":"Promociones Realsa S.l.",
    "wof:placetype":"venue"
},
  "geometry": {"coordinates":[-0.427060008,39.4643554688],"type":"Point"}
}