{
  "type": "Feature",
  "properties": {
    "addr:full":"Carr Bisbe Campins, 10 Pont D'inca Islas Baleares 07009",
    "addr:housenumber":"10",
    "addr:postcode":"07009",
    "addr:street":"Carr Bisbe Campins",
    "iso:country":"ES",
    "sg:address":"Carr Bisbe Campins, 10",
    "sg:city":"Pont D'inca",
    "sg:orig_category":"Molduras, Junquillos, Listones Y Molduras Perforadas",
    "sg:phone":"+34 971 60 18 05",
    "sg:postcode":"07009",
    "sg:province":"Islas Baleares",
    "wof:name":"Sistelcom-telemensaje S.a.",
    "wof:placetype":"venue"
},
  "geometry": {"coordinates":[2.9094939232,39.7217407227],"type":"Point"}
}