{
  "type": "Feature",
  "properties": {
    "addr:full":"Calle de San Roque, 2 Burgos Burgos 09006",
    "addr:housenumber":"2",
    "addr:postcode":"09006",
    "addr:street":"Calle De San Roque",
    "iso:country":"ES",
    "sg:address":"Calle de San Roque, 2",
    "sg:city":"Burgos",
    "sg:orig_category":"Venta, Colocaci\u00d3n, Reparaci\u00d3n De Radiadores Para Veh\u00cdculos",
    "sg:phone":"+34 947 22 52 19",
    "sg:postcode":"09006",
    "sg:province":"Burgos",
    "wof:name":"Serrano Alonso Gregorio",
    "wof:placetype":"venue"
},
  "geometry": {"coordinates":[-3.6804978848,42.3483543396],"type":"Point"}
}