{
  "type": "Feature",
  "properties": {
    "addr:full":"Rua Industria (da), 36 Lugo Lugo 27003",
    "addr:housenumber":"36",
    "addr:postcode":"27003",
    "addr:street":"Rua Industria Da",
    "iso:country":"ES",
    "sg:address":"Rua Industria (da), 36",
    "sg:city":"Lugo",
    "sg:orig_category":"Construcciones Met\u00c1licas",
    "sg:phone":"+34 982 20 92 41",
    "sg:postcode":"27003",
    "sg:province":"Lugo",
    "wof:name":"Metalico S. L.",
    "wof:placetype":"venue"
},
  "geometry": {"coordinates":[-7.5737228394,43.0478515625],"type":"Point"}
}