{
  "type": "Feature",
  "properties": {
    "addr:full":"Bda Santa Clara, 2 Barcelona Barcelona 08002",
    "addr:housenumber":"2",
    "addr:postcode":"08002",
    "addr:street":"Santa Clara",
    "iso:country":"ES",
    "sg:address":"Bda Santa Clara, 2",
    "sg:city":"Barcelona",
    "sg:orig_category":"Fabricaci\u00d3n, Venta De Cuadros, Accesorios Para Enmarcar",
    "sg:phone":"+34 933 19 98 89",
    "sg:postcode":"08002",
    "sg:province":"Barcelona",
    "wof:name":"Edicions Ciutat Vella S.l.",
    "wof:placetype":"venue"
},
  "geometry": {"coordinates":[2.1773679256,41.3838233948],"type":"Point"}
}