{
  "type": "Feature",
  "properties": {
    "iso:country":"ES",
    "sg:address":"Calle de Moyano, 5",
    "sg:city":"Castellon",
    "sg:orig_category":"Papeler\u00cdas, Librer\u00cdas",
    "sg:phone":"+34 964 23 07 68",
    "sg:postcode":"12002",
    "sg:province":"Castell\u00f3n",
    "wof:name":"Jodar Serrano Miguel",
    "wof:placetype":"venue"
},
  "geometry": {"coordinates":[-0.0376800001,39.9829368591],"type":"Point"}
}