{
  "type": "Feature",
  "properties": {
    "addr:full":"Praz Manuel Escuris, S/n Pobra Do Carami\u00e7al La Coru\u00f1a 15940",
    "addr:housenumber":"s",
    "addr:postcode":"15940",
    "addr:street":"Praz Manuel Escuris;/ N;Corun\u0303A",
    "iso:country":"ES",
    "sg:address":"Praz Manuel Escuris, S/n",
    "sg:city":"Pobra Do Carami\u00e7al",
    "sg:orig_category":"Lencer\u00cda Femenina, Corseter\u00cda, Trajes De Ba\u00d1o (al Por Menor)",
    "sg:phone":"+34 981 83 28 55",
    "sg:postcode":"15940",
    "sg:province":"La Coru\u00f1a",
    "wof:name":"Dominguez Romero Beatriz",
    "wof:placetype":"venue"
},
  "geometry": {"coordinates":[-8.9394426346,42.6065750122],"type":"Point"}
}