{
  "type": "Feature",
  "properties": {
    "addr:full":"Calle de Guatemala, 9 Vitoria-gasteiz \u00c1lava 01012",
    "addr:housenumber":"9",
    "addr:postcode":"01012",
    "addr:street":"Calle De Guatemala",
    "iso:country":"ES",
    "sg:address":"Calle de Guatemala, 9",
    "sg:city":"Vitoria-gasteiz",
    "sg:orig_category":"Platos Preparados Refrigerados (fabricaci\u00d3n, Al Por Mayor)",
    "sg:phone":"+34 945 26 04 84",
    "sg:postcode":"01012",
    "sg:province":"\u00c1lava",
    "wof:name":"Yang  Jun Yong",
    "wof:placetype":"venue"
},
  "geometry": {"coordinates":[-2.6757540703,42.859752655],"type":"Point"}
}