{
  "type": "Feature",
  "properties": {
    "addr:full":"Ctra Fuensalida, Km. 0001,8 Torrijos Toledo 45500",
    "addr:postcode":"45500",
    "addr:street":"Ctra Fuensalida Km. 0001,8",
    "iso:country":"ES",
    "sg:address":"Ctra Fuensalida, Km. 0001,8",
    "sg:city":"Torrijos",
    "sg:orig_category":"Inmobiliaria (agencias)",
    "sg:phone":"+34 925 76 40 72",
    "sg:postcode":"45500",
    "sg:province":"Toledo",
    "wof:name":"Golfmayor S.l.",
    "wof:placetype":"venue"
},
  "geometry": {"coordinates":[-4.2755231857,39.9964675903],"type":"Point"}
}