{
  "type": "Feature",
  "properties": {
    "addr:full":"Calle de Alegria, 5 Carpio Tajo Toledo 45533",
    "addr:housenumber":"5",
    "addr:postcode":"45533",
    "addr:street":"Calle De Alegria",
    "iso:country":"ES",
    "sg:address":"Calle de Alegria, 5",
    "sg:city":"Carpio Tajo",
    "sg:orig_category":"Mec\u00c1nico Del Autom\u00d3vil",
    "sg:phone":"+34 925 75 72 32",
    "sg:postcode":"45533",
    "sg:province":"Toledo",
    "wof:name":"Gonzalez Corral Juan Julian",
    "wof:placetype":"venue"
},
  "geometry": {"coordinates":[-4.4526467323,39.8917388916],"type":"Point"}
}