{
  "type": "Feature",
  "properties": {
    "iso:country":"ES",
    "sg:address":"Rua Doctor Teijeiro, 46",
    "sg:city":"Monforte De Lemos",
    "sg:orig_category":"Carnicer\u00cdas, Carnicer\u00cdas",
    "sg:phone":"+34 982 41 08 57",
    "sg:postcode":"27400",
    "sg:province":"Lugo",
    "wof:name":"Fernandez Gomez Jose Ramon",
    "wof:placetype":"venue"
},
  "geometry": {"coordinates":[-7.5128421783,42.5213813782],"type":"Point"}
}