{
  "type": "Feature",
  "properties": {
    "iso:country":"ES",
    "sg:address":"Trva Cuesta De Mostoles, 7",
    "sg:city":"Fuenlabrada",
    "sg:orig_category":"Ferreter\u00cda (diversos)",
    "sg:phone":"+34 916 07 00 68",
    "sg:postcode":"28942",
    "sg:province":"Madrid",
    "wof:name":"Cabeza Lopez Domingo",
    "wof:placetype":"venue"
},
  "geometry": {"coordinates":[-3.8153159618,40.2943840027],"type":"Point"}
}