{
  "type": "Feature",
  "properties": {
    "iso:country":"ES",
    "sg:address":"Carrer de Casa Nova (de La), 7",
    "sg:city":"Montornes Nord",
    "sg:orig_category":"Productos Refractarios (fabricaci\u00d3n, Al Por Mayor)",
    "sg:phone":"+34 935 72 15 57",
    "sg:postcode":"08170",
    "sg:province":"Barcelona",
    "wof:name":"Valls Carras S.l.",
    "wof:placetype":"venue"
},
  "geometry": {"coordinates":[2.2673149109,41.5512161255],"type":"Point"}
}