{
  "type": "Feature",
  "properties": {
    "addr:full":"Av Alcodar(pol Alcodar), S/n Gandia Valencia 46700",
    "addr:postcode":"46700",
    "addr:street":"Av Alcodar;Alcodar S / N;Valencia",
    "iso:country":"ES",
    "sg:address":"Av Alcodar(pol Alcodar), S/n",
    "sg:city":"Gandia",
    "sg:orig_category":"Plomeros",
    "sg:phone":"+34 962 87 84 08",
    "sg:postcode":"46700",
    "sg:province":"Valencia",
    "wof:name":"Fomento De Construcciones Y Contratas S.a.",
    "wof:placetype":"venue"
},
  "geometry": {"coordinates":[-0.1824589968,38.9810600281],"type":"Point"}
}