{
  "type": "Feature",
  "properties": {
    "addr:full":"Plaz Rafael Gibert, S/n Ceuta Ceuta 51001",
    "addr:housenumber":"s / n",
    "addr:postcode":"51001",
    "iso:country":"ES",
    "sg:address":"Plaz Rafael Gibert, S/n",
    "sg:city":"Ceuta",
    "sg:orig_category":"Ense\u00d1anza: Idiomas",
    "sg:phone":"+34 956 51 54 47",
    "sg:postcode":"51001",
    "sg:province":"Ceuta",
    "wof:name":"Seccion Filial Del Instituto De Idiomas De La Universidad De Granada",
    "wof:placetype":"venue"
},
  "geometry": {"coordinates":[-5.3302302361,35.8947601318],"type":"Point"}
}