{
  "type": "Feature",
  "properties": {
    "iso:country":"ES",
    "sg:address":"Calle de Aguadores, 10",
    "sg:city":"Santa Lucia",
    "sg:orig_category":"Grabadores (varios)",
    "sg:phone":"+34 968 52 30 76",
    "sg:postcode":"30202",
    "sg:province":"Murcia",
    "wof:name":"Perez Perez Francisco",
    "wof:placetype":"venue"
},
  "geometry": {"coordinates":[-1.1298867464,37.9834747314],"type":"Point"}
}