{
  "type": "Feature",
  "properties": {
    "iso:country":"ES",
    "sg:address":"Calle de Libertad, 33",
    "sg:city":"Valdemoro",
    "sg:orig_category":"Venta, Montaje De Neum\u00c1ticos",
    "sg:phone":"+34 918 95 58 07",
    "sg:postcode":"28340",
    "sg:province":"Madrid",
    "wof:name":"Auto Lavado Valdemoro S.l.",
    "wof:placetype":"venue"
},
  "geometry": {"coordinates":[-3.682888031,40.1906776428],"type":"Point"}
}