{
  "type": "Feature",
  "properties": {
    "iso:country":"ES",
    "sg:address":"Calle de Jauregieta, 15",
    "sg:city":"Etxalar",
    "sg:orig_category":"Transportes Por Carretera: Lotes Completos, Mercanc\u00cdas Diversas",
    "sg:phone":"+34 948 63 50 70",
    "sg:postcode":"31760",
    "sg:province":"Navarra",
    "wof:name":"Ansalas Ozkariz Juan Martin",
    "wof:placetype":"venue"
},
  "geometry": {"coordinates":[-1.6367297173,43.2330360413],"type":"Point"}
}