{
  "type": "Feature",
  "properties": {
    "iso:country":"ES",
    "sg:address":"Carrer de Joaquim Casas, 8",
    "sg:city":"Mataro",
    "sg:orig_category":"Cl\u00cdnicas Dentales",
    "sg:phone":"+34 937 41 53 81",
    "sg:postcode":"08303",
    "sg:province":"Barcelona",
    "wof:name":"D.m.d. 99 S.l.l.",
    "wof:placetype":"venue"
},
  "geometry": {"coordinates":[2.4333150387,41.5399971008],"type":"Point"}
}