{
  "type": "Feature",
  "properties": {
    "iso:country":"ES",
    "sg:address":"Calle de Saavedra, 44",
    "sg:city":"Gijon",
    "sg:orig_category":"Inmobiliaria (agencias)",
    "sg:phone":"+34 985 14 16 36",
    "sg:postcode":"33208",
    "sg:province":"Asturias",
    "wof:name":"Hevia Garcia Covadonga",
    "wof:placetype":"venue"
},
  "geometry": {"coordinates":[-5.6640691757,43.5331611633],"type":"Point"}
}