{
  "type": "Feature",
  "properties": {
    "addr:full":"Siderurgia, S/n Puerto Sagunto Valencia 46520",
    "addr:housenumber":"/ n",
    "addr:postcode":"46520",
    "addr:street":"Siderurgia S",
    "iso:country":"ES",
    "sg:address":"Siderurgia, S/n",
    "sg:city":"Puerto Sagunto",
    "sg:orig_category":"V\u00c1lvulas",
    "sg:phone":"+34 962 67 49 52",
    "sg:postcode":"46520",
    "sg:province":"Valencia",
    "wof:name":"Vicente Manuel Lopez S.l.",
    "wof:placetype":"venue"
},
  "geometry": {"coordinates":[-0.2240390033,39.6556510925],"type":"Point"}
}