{
  "type": "Feature",
  "properties": {
    "addr:full":"Calle de Empedrada, 26 Ecija Sevilla 41400",
    "addr:housenumber":"26",
    "addr:postcode":"41400",
    "addr:street":"Calle De Empedrada",
    "iso:country":"ES",
    "sg:address":"Calle de Empedrada, 26",
    "sg:city":"Ecija",
    "sg:orig_category":"Transportes Por Carretera: Lotes Completos, Mercanc\u00cdas Diversas",
    "sg:phone":"+34 954 83 08 18",
    "sg:postcode":"41400",
    "sg:province":"Sevilla",
    "wof:name":"Pastor Sotillos Ramona",
    "wof:placetype":"venue"
},
  "geometry": {"coordinates":[-5.0838389397,37.5369606018],"type":"Point"}
}