{
  "type": "Feature",
  "properties": {
    "iso:country":"ES",
    "sg:address":"Carrer de Aribau, 149",
    "sg:city":"Barcelona",
    "sg:orig_category":"Abogados",
    "sg:phone":"+34 933 21 71 94",
    "sg:postcode":"08036",
    "sg:province":"Barcelona",
    "wof:name":"Bufete Cano & Asociados S.l.",
    "wof:placetype":"venue"
},
  "geometry": {"coordinates":[2.1538848877,41.3924865723],"type":"Point"}
}