{
  "type": "Feature",
  "properties": {
    "addr:full":"Calle de San Juan De Dios, 38 Talavera Reina Toledo 45600",
    "addr:housenumber":"38",
    "addr:postcode":"45600",
    "addr:street":"Calle De San Juan;Dios",
    "iso:country":"ES",
    "sg:address":"Calle de San Juan De Dios, 38",
    "sg:city":"Talavera Reina",
    "sg:orig_category":"Molduras, Junquillos, Listones Y Molduras Perforadas",
    "sg:phone":"+34 925 81 57 30",
    "sg:postcode":"45600",
    "sg:province":"Toledo",
    "wof:name":"Carrasquilla Resino Ricardo",
    "wof:placetype":"venue"
},
  "geometry": {"coordinates":[-4.837228775,39.9628334045],"type":"Point"}
}