{
  "type": "Feature",
  "properties": {
    "iso:country":"ES",
    "sg:address":"Calle de Conde Aranda, 33",
    "sg:city":"Zaragoza",
    "sg:orig_category":"Inmobiliaria (agencias)",
    "sg:phone":"+34 976 28 30 94",
    "sg:postcode":"50004",
    "sg:province":"Zaragoza",
    "sg:website":"www.atiaranda.com",
    "wof:name":"Sanchez Lopez Ana Rosa",
    "wof:placetype":"venue"
},
  "geometry": {"coordinates":[-0.8875706196,41.6549415588],"type":"Point"}
}