{
  "type": "Feature",
  "properties": {
    "addr:full":"Ctra Cardona, 12 Manresa Barcelona 08242",
    "addr:housenumber":"12",
    "addr:postcode":"08242",
    "addr:street":"Ctra Cardona",
    "iso:country":"ES",
    "sg:address":"Ctra Cardona, 12",
    "sg:city":"Manresa",
    "sg:orig_category":"Florister\u00cdas",
    "sg:phone":"+34 938 72 15 81",
    "sg:postcode":"08242",
    "sg:province":"Barcelona",
    "wof:name":"Guarro Herrero M.dolores",
    "wof:placetype":"venue"
},
  "geometry": {"coordinates":[1.82239604,41.7256088257],"type":"Point"}
}