{
  "type": "Feature",
  "properties": {
    "addr:full":"Avda General Peron, 38 Madrid Madrid 28020",
    "addr:housenumber":"38",
    "addr:postcode":"madrid;28020",
    "addr:street":"Avda General Peron",
    "iso:country":"ES",
    "sg:address":"Avda General Peron, 38",
    "sg:city":"Madrid",
    "sg:orig_category":"Caf\u00c9s, Bares, Cervecer\u00cdas",
    "sg:phone":"+34 915 56 16 81",
    "sg:postcode":"28020",
    "sg:province":"Madrid",
    "wof:name":"Jiga S.l.",
    "wof:placetype":"venue"
},
  "geometry": {"coordinates":[-3.6922399998,40.4520950317],"type":"Point"}
}