{
  "type": "Feature",
  "properties": {
    "iso:country":"ES",
    "sg:address":"Carrer de Torre Iberica, 5",
    "sg:city":"Terrassa",
    "sg:orig_category":"Maquinaria Para Industrias Diversas",
    "sg:phone":"+34 937 89 26 70",
    "sg:postcode":"08224",
    "sg:province":"Barcelona",
    "wof:name":"Hanson  Christopher",
    "wof:placetype":"venue"
},
  "geometry": {"coordinates":[1.9906500578,41.5405235291],"type":"Point"}
}