{
  "type": "Feature",
  "properties": {
    "iso:country":"ES",
    "sg:address":"Calle de Osa De La Vega, 5",
    "sg:city":"Madrid",
    "sg:orig_category":"Panader\u00cdas, Panader\u00cdas",
    "sg:phone":"+34 917 06 96 03",
    "sg:postcode":"28044",
    "sg:province":"Madrid",
    "wof:name":"Lopez Lopez Raul",
    "wof:placetype":"venue"
},
  "geometry": {"coordinates":[-3.7746539116,40.3750953674],"type":"Point"}
}