{
  "type": "Feature",
  "properties": {
    "iso:country":"ES",
    "sg:address":"Calle de Infanta Do\u00d1a Teresa, 8",
    "sg:city":"Ponferrada",
    "sg:orig_category":"Servicio De Salud",
    "sg:phone":"+34 987 41 79 00",
    "sg:postcode":"24400",
    "sg:province":"Le\u00f3n",
    "wof:name":"Puerto Garcia Eugenio",
    "wof:placetype":"venue"
},
  "geometry": {"coordinates":[-6.5828537941,42.5490951538],"type":"Point"}
}