{
  "type": "Feature",
  "properties": {
    "addr:full":"Ctra. Extremadura, Km. 0027,8 Navalcarnero Madrid 28600",
    "addr:postcode":"28600",
    "addr:street":"Ctra. Extremadura Km. 0027,8",
    "iso:country":"ES",
    "sg:address":"Ctra. Extremadura, Km. 0027,8",
    "sg:city":"Navalcarnero",
    "sg:orig_category":"Establecimientos De Cura, Prevenci\u00d3n Y Readaptaci\u00d3n",
    "sg:phone":"+34 918 10 11 60",
    "sg:postcode":"28600",
    "sg:province":"Madrid",
    "wof:name":"Asociacion Punto Omega",
    "wof:placetype":"venue"
},
  "geometry": {"coordinates":[-5.2180314064,39.9071464539],"type":"Point"}
}