{
  "type": "Feature",
  "properties": {
    "iso:country":"ES",
    "sg:address":"Avda Juan Alfonso Batista, S/n",
    "sg:city":"Cristianos",
    "sg:orig_category":"Agencias De Viajes",
    "sg:phone":"+34 922 79 35 00",
    "sg:postcode":"38650",
    "sg:province":"Santa Cruz De Tenerife",
    "wof:name":"Admiral Travel Agencia De Viajes",
    "wof:placetype":"venue"
},
  "geometry": {"coordinates":[-16.7175559998,28.050901413],"type":"Point"}
}