{
  "type": "Feature",
  "properties": {
    "iso:country":"ES",
    "sg:address":"Urb Majada Marcial, 14",
    "sg:city":"Pto. Rosario",
    "sg:orig_category":"Agentes, Concesionarios Y Sucursales De Veh\u00cdculos",
    "sg:phone":"+34 928 53 17 35",
    "sg:postcode":"35600",
    "sg:province":"Las Palmas",
    "wof:name":"Venserauto S.l.",
    "wof:placetype":"venue"
},
  "geometry": {"coordinates":[-13.8644685745,28.5023498535],"type":"Point"}
}