{
  "type": "Feature",
  "properties": {
    "iso:country":"ES",
    "sg:address":"Pl Joaquim Folguera, S/n",
    "sg:city":"Barcelona",
    "sg:orig_category":"Librer\u00cdas",
    "sg:phone":"+34 932 11 53 04",
    "sg:postcode":"08022",
    "sg:province":"Barcelona",
    "wof:name":"Schonhofer Dusque Peter",
    "wof:placetype":"venue"
},
  "geometry": {"coordinates":[2.138864994,41.4058914185],"type":"Point"}
}