{
  "type": "Feature",
  "properties": {
    "addr:full":"Av Generalitat De Catalunya, 13 Sort Lleida 25560",
    "addr:housenumber":"13",
    "addr:postcode":"25560",
    "addr:street":"Av Generalitat De Catalunya",
    "iso:country":"ES",
    "sg:address":"Av Generalitat De Catalunya, 13",
    "sg:city":"Sort",
    "sg:orig_category":"Loter\u00cda Y T\u00d3mbola",
    "sg:phone":"+34 973 62 12 42",
    "sg:postcode":"25560",
    "sg:province":"Lleida",
    "sg:website":"www.labruixador.es",
    "wof:name":"Gali Vidal Rosa Maria",
    "wof:placetype":"venue"
},
  "geometry": {"coordinates":[1.1325337887,42.4144935608],"type":"Point"}
}