{
  "type": "Feature",
  "properties": {
    "addr:full":"Carretera Bilbao, Km. 0198,0 Hoznayo Cantabria 39716",
    "addr:postcode":"39716",
    "addr:street":"Carretera Bilbao Km. 0198,0",
    "iso:country":"ES",
    "sg:address":"Carretera Bilbao, Km. 0198,0",
    "sg:city":"Hoznayo",
    "sg:orig_category":"Asesor\u00cda Fiscal Y Jur\u00cddica",
    "sg:phone":"+34 942 52 44 42",
    "sg:postcode":"39716",
    "sg:province":"Cantabria",
    "wof:name":"Asesoria Norte S.cv.",
    "wof:placetype":"venue"
},
  "geometry": {"coordinates":[-3.7010340691,43.3901786804],"type":"Point"}
}