{
  "type": "Feature",
  "properties": {
    "iso:country":"ES",
    "sg:address":"Rua Alhondiga (da), 2",
    "sg:city":"Pontevedra",
    "sg:orig_category":"Ense\u00d1anza: Profesiones Art\u00cdsticas",
    "sg:phone":"+34 986 84 69 48",
    "sg:postcode":"36002",
    "sg:province":"Pontevedra",
    "wof:name":"Sociedad Filarmonica De Pontevedra",
    "wof:placetype":"venue"
},
  "geometry": {"coordinates":[-8.6464519501,42.4321708679],"type":"Point"}
}