{
  "type": "Feature",
  "properties": {
    "iso:country":"ES",
    "sg:address":"El Cercado, S/n",
    "sg:city":"Huercal Almeria",
    "sg:orig_category":"Cajas De Ahorro",
    "sg:phone":"+34 950 30 02 46",
    "sg:postcode":"04230",
    "sg:province":"Almer\u00eda",
    "wof:name":"Unicaja",
    "wof:placetype":"venue"
},
  "geometry": {"coordinates":[-2.4370388985,36.8798294067],"type":"Point"}
}