{
  "type": "Feature",
  "properties": {
    "addr:full":"Carrer de Carrasco I Formiguera, 42 Mataro Barcelona 08302",
    "addr:housenumber":"42",
    "addr:postcode":"08302",
    "addr:street":"Carrer De Carrasco I Formiguera",
    "iso:country":"ES",
    "sg:address":"Carrer de Carrasco I Formiguera, 42",
    "sg:city":"Mataro",
    "sg:orig_category":"Comercio De Piezas De Recambio Y De Accesorios De Veh\u00cdculos, Veh\u00cdculos Industriales",
    "sg:phone":"+34 937 58 63 32",
    "sg:postcode":"08302",
    "sg:province":"Barcelona",
    "wof:name":"Aurgi S.l.",
    "wof:placetype":"venue"
},
  "geometry": {"coordinates":[2.4274230003,41.5326652527],"type":"Point"}
}