{
  "type": "Feature",
  "properties": {
    "iso:country":"ES",
    "sg:address":"Ctra Pamplona-zaragoza, S/n",
    "sg:city":"Barasoain",
    "sg:orig_category":"Cooperativas Agr\u00cdcolas",
    "sg:phone":"+34 948 72 00 12",
    "sg:postcode":"31395",
    "sg:province":"Navarra",
    "wof:name":"Sociedad Cooperativa Cerealista Valdorba",
    "wof:placetype":"venue"
},
  "geometry": {"coordinates":[-1.5197240114,42.6444091797],"type":"Point"}
}