{
  "type": "Feature",
  "properties": {
    "addr:full":"Rua Pravia (da), 46 Vilalba Lugo 27800",
    "addr:postcode":"27800",
    "addr:street":"Rua Pravia Da",
    "iso:country":"ES",
    "sg:address":"Rua Pravia (da), 46",
    "sg:city":"Vilalba",
    "sg:orig_category":"Sindicatos Y Colegios Profesionales",
    "sg:phone":"+34 982 51 23 91",
    "sg:postcode":"27800",
    "sg:province":"Lugo",
    "wof:name":"A.d.s. Da Chaira",
    "wof:placetype":"venue"
},
  "geometry": {"coordinates":[-7.6331129074,43.2868766785],"type":"Point"}
}