{
  "type": "Feature",
  "properties": {
    "addr:full":"Avda Buenos Aires, 29 Ourense Ourense 32004",
    "addr:housenumber":"29",
    "addr:postcode":"32004",
    "addr:street":"Avda Buenos Aires",
    "iso:country":"ES",
    "sg:address":"Avda Buenos Aires, 29",
    "sg:city":"Ourense",
    "sg:orig_category":"Ense\u00d1anza Variada",
    "sg:phone":"+34 988 25 10 33",
    "sg:postcode":"32004",
    "sg:province":"Ourense",
    "wof:name":"Jose Luis Rodriguez Y Montserrat Barja S.c.",
    "wof:placetype":"venue"
},
  "geometry": {"coordinates":[-7.8616337776,42.3389511108],"type":"Point"}
}