{
  "type": "Feature",
  "properties": {
    "iso:country":"ES",
    "sg:address":"Trva Badajoz-valencia, 23",
    "sg:city":"Ossa Montiel",
    "sg:orig_category":"Colchones (fabricaci\u00d3n, Al Por Mayor, Al Por Menor)",
    "sg:phone":"+34 967 37 75 96",
    "sg:postcode":"02611",
    "sg:province":"Albacete",
    "wof:name":"De La Due\u00f1a Buendia S.l.",
    "wof:placetype":"venue"
},
  "geometry": {"coordinates":[-2.7472839355,38.9645500183],"type":"Point"}
}