{
  "type": "Feature",
  "properties": {
    "iso:country":"ES",
    "sg:address":"Calle de Muladies, S/n",
    "sg:city":"Malaga",
    "sg:orig_category":"Institutos De Belleza",
    "sg:phone":"+34 952 61 64 31",
    "sg:postcode":"29010",
    "sg:province":"M\u00e1laga",
    "wof:name":"Rivera Coca Rosa Maria",
    "wof:placetype":"venue"
},
  "geometry": {"coordinates":[-4.4436488152,36.7212409973],"type":"Point"}
}