{
  "type": "Feature",
  "properties": {
    "addr:full":"Calle de Santa Cecilia, 9 Jerez De La Frontera C\u00e1diz 11408",
    "addr:housenumber":"9",
    "addr:postcode":"11408",
    "addr:street":"Calle De Santa Cecilia",
    "iso:country":"ES",
    "sg:address":"Calle de Santa Cecilia, 9",
    "sg:city":"Jerez De La Frontera",
    "sg:orig_category":"Sociedades, Compa\u00d1\u00cdas Aseguradoras",
    "sg:phone":"+34 956 32 35 28",
    "sg:postcode":"11408",
    "sg:province":"C\u00e1diz",
    "wof:name":"Indemnizacion Consulting S.l.",
    "wof:placetype":"venue"
},
  "geometry": {"coordinates":[-6.1424098015,36.6746444702],"type":"Point"}
}