{
  "type": "Feature",
  "properties": {
    "iso:country":"ES",
    "sg:address":"Calle de Sapporo, 22",
    "sg:city":"Alcorcon",
    "sg:orig_category":"Maquinaria Para Industrias Diversas",
    "sg:phone":"+34 916 12 86 91",
    "sg:postcode":"28923",
    "sg:province":"Madrid",
    "wof:name":"Distribuciones Reymu S. L.",
    "wof:placetype":"venue"
},
  "geometry": {"coordinates":[-3.8147950172,40.3448295593],"type":"Point"}
}