{
  "type": "Feature",
  "properties": {
    "iso:country":"ES",
    "sg:address":"Carr Germans Reynes, 3",
    "sg:city":"Fornalutx",
    "sg:orig_category":"Empresas De Vigilancia, Guardia Y Protecci\u00d3n",
    "sg:phone":"+34 971 63 10 61",
    "sg:postcode":"07109",
    "sg:province":"Islas Baleares",
    "wof:name":"Lluc Alcari Securities",
    "wof:placetype":"venue"
},
  "geometry": {"coordinates":[2.741081953,39.7823600769],"type":"Point"}
}