{
  "type": "Feature",
  "properties": {
    "addr:full":"Calle de Doctor Esquerdo, 108 Madrid Madrid 28007",
    "addr:housenumber":"108",
    "addr:postcode":"28007",
    "addr:street":"Calle De Doctor Esquerdo",
    "iso:country":"ES",
    "sg:address":"Calle de Doctor Esquerdo, 108",
    "sg:city":"Madrid",
    "sg:orig_category":"Piedra Natural",
    "sg:phone":"+34 915 01 14 43",
    "sg:postcode":"28007",
    "sg:province":"Madrid",
    "sg:website":"www.tricalsa.com",
    "wof:name":"Triturados Calcicos S. A.",
    "wof:placetype":"venue"
},
  "geometry": {"coordinates":[-3.670181036,40.4089927673],"type":"Point"}
}