{
  "type": "Feature",
  "properties": {
    "addr:full":"Calle de Adrian Nodal, 4 Bargas Toledo 45593",
    "addr:housenumber":"4",
    "addr:postcode":"45593",
    "addr:street":"Calle De Adrian Nodal",
    "iso:country":"ES",
    "sg:address":"Calle de Adrian Nodal, 4",
    "sg:city":"Bargas",
    "sg:orig_category":"Farmacias",
    "sg:phone":"+34 925 49 34 84",
    "sg:postcode":"45593",
    "sg:province":"Toledo",
    "wof:name":"Parafarmacia Sanchez Ruiz",
    "wof:placetype":"venue"
},
  "geometry": {"coordinates":[-4.0192770958,39.9391746521],"type":"Point"}
}