{
  "type": "Feature",
  "properties": {
    "addr:full":"Psaj Pintor Cordoba, 3 Cordoba C\u00f3rdoba 14006",
    "addr:housenumber":"3",
    "addr:postcode":"14006",
    "addr:street":"Pintor Cordoba;Co\u0301Rdoba",
    "iso:country":"ES",
    "sg:address":"Psaj Pintor Cordoba, 3",
    "sg:city":"Cordoba",
    "sg:orig_category":"Agencias Y Agentes Comerciales, Representantes",
    "sg:phone":"+34 957 27 39 14",
    "sg:postcode":"14006",
    "sg:province":"C\u00f3rdoba",
    "wof:name":"Palomino Benavente Francisco Arturo",
    "wof:placetype":"venue"
},
  "geometry": {"coordinates":[-4.7776050568,37.8968734741],"type":"Point"}
}