{
  "type": "Feature",
  "properties": {
    "addr:full":"Calle de Nieremberg, 4 Madrid Madrid 28002",
    "addr:housenumber":"4",
    "addr:postcode":"28002",
    "addr:street":"Calle De Nieremberg",
    "iso:country":"ES",
    "sg:address":"Calle de Nieremberg, 4",
    "sg:city":"Madrid",
    "sg:orig_category":"Molduras, Junquillos, Listones Y Molduras Perforadas",
    "sg:phone":"+34 914 16 44 87",
    "sg:postcode":"28002",
    "sg:province":"Madrid",
    "wof:name":"Gutierrez Andreu Alfonso",
    "wof:placetype":"venue"
},
  "geometry": {"coordinates":[-3.6709771156,40.4470443726],"type":"Point"}
}