{
  "type": "Feature",
  "properties": {
    "iso:country":"ES",
    "sg:address":"Calle de Mirabel, 4",
    "sg:city":"Madrid",
    "sg:orig_category":"Estancos",
    "sg:phone":"+34 917 05 70 58",
    "sg:postcode":"28044",
    "sg:province":"Madrid",
    "wof:name":"Gonzalez Lobato Emilia",
    "wof:placetype":"venue"
},
  "geometry": {"coordinates":[-3.780258894,40.3780784607],"type":"Point"}
}