{
  "type": "Feature",
  "properties": {
    "addr:full":"Calle de Elias Zerolo, 3 San Cristobal De La Laguna Santa Cruz De Tenerife 38206",
    "addr:housenumber":"3",
    "addr:postcode":"38206",
    "addr:street":"Calle De Elias Zerolo",
    "iso:country":"ES",
    "sg:address":"Calle de Elias Zerolo, 3",
    "sg:city":"San Cristobal De La Laguna",
    "sg:orig_category":"Ingenier\u00cda, Centros De Estudios (diversos)",
    "sg:phone":"+34 922 26 50 76",
    "sg:postcode":"38206",
    "sg:province":"Santa Cruz De Tenerife",
    "wof:name":"Rodriguez Hernandez Jose Miguel",
    "wof:placetype":"venue"
},
  "geometry": {"coordinates":[-16.3246059418,28.4842815399],"type":"Point"}
}