{
  "type": "Feature",
  "properties": {
    "addr:full":"Calle de Veleta, 6 Rozas De Madrid Madrid 28230",
    "addr:housenumber":"6",
    "addr:postcode":"28230",
    "addr:street":"Calle De Veleta",
    "iso:country":"ES",
    "sg:address":"Calle de Veleta, 6",
    "sg:city":"Rozas De Madrid",
    "sg:orig_category":"Ingeniero",
    "sg:phone":"+34 916 39 36 99",
    "sg:postcode":"28230",
    "sg:province":"Madrid",
    "wof:name":"Sanchez Escandell Gregorio",
    "wof:placetype":"venue"
},
  "geometry": {"coordinates":[-3.8624970913,40.484172821],"type":"Point"}
}