{
  "type": "Feature",
  "properties": {
    "iso:country":"ES",
    "sg:address":"Carrer de Balmes, 363",
    "sg:city":"Barcelona",
    "sg:orig_category":"Comerciantes Al Por Mayor De Vinos, Licores Y Alcoholes",
    "sg:phone":"+34 934 17 34 16",
    "sg:postcode":"08006",
    "sg:province":"Barcelona",
    "wof:name":"Borras Marco Pedro",
    "wof:placetype":"venue"
},
  "geometry": {"coordinates":[2.1412041187,41.404094696],"type":"Point"}
}