{
  "type": "Feature",
  "properties": {
    "addr:full":"Carrer de Granada, 8 Creus Barcelona 08397",
    "addr:housenumber":"8",
    "addr:postcode":"08397",
    "addr:street":"Carrer De Granada",
    "iso:country":"ES",
    "sg:address":"Carrer de Granada, 8",
    "sg:city":"Creus",
    "sg:orig_category":"Empresas De Desmonte",
    "sg:phone":"+34 937 62 30 87",
    "sg:postcode":"08397",
    "sg:province":"Barcelona",
    "wof:name":"Excavaciones Pinemar S.l.",
    "wof:placetype":"venue"
},
  "geometry": {"coordinates":[2.6800789833,41.6260375977],"type":"Point"}
}