{
  "type": "Feature",
  "properties": {
    "addr:full":"Avda Sevilla (de), 84 Chipiona C\u00e1diz 11550",
    "addr:housenumber":"84",
    "addr:postcode":"11550",
    "addr:street":"Avda Sevilla De",
    "iso:country":"ES",
    "sg:address":"Avda Sevilla (de), 84",
    "sg:city":"Chipiona",
    "sg:orig_category":"Agencias Y Agentes Comerciales, Representantes",
    "sg:phone":"+34 956 37 40 75",
    "sg:postcode":"11550",
    "sg:province":"C\u00e1diz",
    "wof:name":"Behnstedt  Angelika",
    "wof:placetype":"venue"
},
  "geometry": {"coordinates":[-6.4388270378,36.7306251526],"type":"Point"}
}