{
  "type": "Feature",
  "properties": {
    "iso:country":"ES",
    "sg:address":"C/ Sant Lloren\u00c7, 4",
    "sg:city":"Alcoi",
    "sg:orig_category":"\u00d3ptica: Instrumentos (fabricaci\u00d3n)",
    "sg:phone":"+34 965 54 11 36",
    "sg:postcode":"03801",
    "sg:province":"Alicante",
    "wof:name":"Garrido Cardenal Maria Del Carmen",
    "wof:placetype":"venue"
},
  "geometry": {"coordinates":[-0.4732170105,38.6976661682],"type":"Point"}
}