{
  "type": "Feature",
  "properties": {
    "addr:full":"Carrer de Rogent, 17 Barcelona Barcelona 08026",
    "addr:housenumber":"17",
    "addr:postcode":"08026",
    "addr:street":"Carrer De Rogent",
    "iso:country":"ES",
    "sg:address":"Carrer de Rogent, 17",
    "sg:city":"Barcelona",
    "sg:orig_category":"Institutos De Belleza",
    "sg:phone":"+34 932 32 75 08",
    "sg:postcode":"08026",
    "sg:province":"Barcelona",
    "wof:name":"Iso Asensio Maria Luisa",
    "wof:placetype":"venue"
},
  "geometry": {"coordinates":[2.1855289936,41.4088020325],"type":"Point"}
}