{
  "type": "Feature",
  "properties": {
    "addr:full":"Ctra Villanueva, 15 Benavente Zamora 49600",
    "addr:housenumber":"15",
    "addr:postcode":"49600",
    "addr:street":"Ctra Villanueva",
    "iso:country":"ES",
    "sg:address":"Ctra Villanueva, 15",
    "sg:city":"Benavente",
    "sg:orig_category":"Postigos, Persianas Y Celos\u00cdas",
    "sg:phone":"+34 980 63 76 19",
    "sg:postcode":"49600",
    "sg:province":"Zamora",
    "wof:name":"Arribas Requejo Santiago",
    "wof:placetype":"venue"
},
  "geometry": {"coordinates":[-5.6703310013,41.9828224182],"type":"Point"}
}