{
  "type": "Feature",
  "properties": {
    "iso:country":"ES",
    "sg:address":"Calle de Ruiz Zorrilla, 21",
    "sg:city":"Castellon",
    "sg:orig_category":"Muebles",
    "sg:phone":"+34 964 21 00 42",
    "sg:postcode":"12001",
    "sg:province":"Castell\u00f3n",
    "wof:name":"Bellmunt Villarreal Manuel",
    "wof:placetype":"venue"
},
  "geometry": {"coordinates":[-0.0400919989,39.9850273132],"type":"Point"}
}