{
  "type": "Feature",
  "properties": {
    "iso:country":"ES",
    "sg:address":"Calle de Menendez Pelayo, 48",
    "sg:city":"Laredo",
    "sg:orig_category":"Empresas De Carpinter\u00cda De Madera",
    "sg:phone":"+34 942 61 01 68",
    "sg:postcode":"39770",
    "sg:province":"Cantabria",
    "wof:name":"Gomez Perez Celedonio",
    "wof:placetype":"venue"
},
  "geometry": {"coordinates":[-3.4128069878,43.4135169983],"type":"Point"}
}