{
  "type": "Feature",
  "properties": {
    "addr:full":"Calle de Pedro Manuel Segura, 1 Cella Teruel 44370",
    "addr:housenumber":"1",
    "addr:postcode":"44370",
    "addr:street":"Calle De Pedro Manuel Segura",
    "iso:country":"ES",
    "sg:address":"Calle de Pedro Manuel Segura, 1",
    "sg:city":"Cella",
    "sg:orig_category":"Molduras, Junquillos, Listones Y Molduras Perforadas",
    "sg:phone":"+34 978 65 00 73",
    "sg:postcode":"44370",
    "sg:province":"Teruel",
    "wof:name":"Lanzuela Gomez Leonardo",
    "wof:placetype":"venue"
},
  "geometry": {"coordinates":[-1.2882039547,40.4527244568],"type":"Point"}
}