{
  "type": "Feature",
  "properties": {
    "iso:country":"ES",
    "sg:address":"Calle de Puebla, 30",
    "sg:city":"Burgos",
    "sg:orig_category":"Ense\u00d1anza, Formaci\u00d3n Profesional: Aprendizaje",
    "sg:phone":"+34 947 25 02 25",
    "sg:postcode":"09004",
    "sg:province":"Burgos",
    "wof:name":"Comandancia De Obras R.m.pirenaica Occidental",
    "wof:placetype":"venue"
},
  "geometry": {"coordinates":[-3.697412014,42.3422470093],"type":"Point"}
}