{
  "type": "Feature",
  "properties": {
    "addr:full":"Calle de Ambeles, 40 Teruel Teruel 44001",
    "addr:housenumber":"40",
    "addr:postcode":"44001",
    "addr:street":"Calle De Ambeles",
    "iso:country":"ES",
    "sg:address":"Calle de Ambeles, 40",
    "sg:city":"Teruel",
    "sg:orig_category":"Psic\u00d3logos",
    "sg:phone":"+34 978 60 14 78",
    "sg:postcode":"44001",
    "sg:province":"Teruel",
    "wof:name":"Esteban Aparicio Belen",
    "wof:placetype":"venue"
},
  "geometry": {"coordinates":[-1.1050883532,40.3428268433],"type":"Point"}
}