{
  "type": "Feature",
  "properties": {
    "iso:country":"ES",
    "sg:address":"Carr Dolors, 10",
    "sg:city":"Vidreres",
    "sg:orig_category":"Cooperativas Agr\u00cdcolas",
    "sg:phone":"+34 972 85 03 80",
    "sg:postcode":"17411",
    "sg:province":"Girona",
    "wof:name":"Camara Agraria",
    "wof:placetype":"venue"
},
  "geometry": {"coordinates":[2.7813439369,41.7913513184],"type":"Point"}
}