{
  "type": "Feature",
  "properties": {
    "addr:full":"Calle de Rio Fresnedoso, 9 Poligono Sta M. De Benquerencia Toledo 45007",
    "addr:housenumber":"9 poligono",
    "addr:postcode":"45007",
    "addr:street":"Calle De Rio Fresnedoso;Sta M. De Benquerencia",
    "iso:country":"ES",
    "sg:address":"Calle de Rio Fresnedoso, 9",
    "sg:city":"Poligono Sta M. De Benquerencia",
    "sg:orig_category":"Peluqueros: De Se\u00d1oras",
    "sg:phone":"+34 925 23 01 95",
    "sg:postcode":"45007",
    "sg:province":"Toledo",
    "wof:name":"Diaz Saez Maria Jesus",
    "wof:placetype":"venue"
},
  "geometry": {"coordinates":[-3.94520998,39.8632125854],"type":"Point"}
}