{
  "type": "Feature",
  "properties": {
    "addr:full":"Carrer de Balmes, 339 Barcelona Barcelona 08006",
    "addr:housenumber":"339",
    "addr:postcode":"08006",
    "addr:street":"Carrer De Balmes",
    "iso:country":"ES",
    "sg:address":"Carrer de Balmes, 339",
    "sg:city":"Barcelona",
    "sg:orig_category":"Jardiner\u00cdas, Vegetales, Art\u00cdculos De Jardiner\u00cda (al Por Menor)",
    "sg:phone":"+34 934 17 04 86",
    "sg:postcode":"08006",
    "sg:province":"Barcelona",
    "sg:website":"www.jardineria-mitjans.net",
    "wof:name":"Jardineria Mitjans Catalunya S.l.",
    "wof:placetype":"venue"
},
  "geometry": {"coordinates":[2.1431350708,41.4030838013],"type":"Point"}
}