{
  "type": "Feature",
  "properties": {
    "iso:country":"ES",
    "sg:address":"Calle de Eugenio Tamayo, 4",
    "sg:city":"Oviedo",
    "sg:orig_category":"Arreglo, Reparaci\u00d3n, Piezas Sueltas De Televisi\u00d3n, V\u00cddeo, Hi",
    "sg:phone":"+34 985 29 39 39",
    "sg:postcode":"33011",
    "sg:province":"Asturias",
    "sg:website":"www.fade.es/tecnosat",
    "wof:name":"Montes Corzo Faustino Javier",
    "wof:placetype":"venue"
},
  "geometry": {"coordinates":[-5.8439488411,43.3706474304],"type":"Point"}
}