{
  "type": "Feature",
  "properties": {
    "iso:country":"ES",
    "sg:address":"Calle de Ronda Del Atardecer, 27",
    "sg:city":"Galeras Bajas",
    "sg:orig_category":"Inmobiliaria (agencias)",
    "sg:phone":"+34 965 84 09 62",
    "sg:postcode":"03590",
    "sg:province":"Alicante",
    "sg:website":"www.habitanea.com",
    "wof:name":"Habitanea S.l.",
    "wof:placetype":"venue"
},
  "geometry": {"coordinates":[-0.0522690006,38.601108551],"type":"Point"}
}