{
  "type": "Feature",
  "properties": {
    "iso:country":"ES",
    "sg:address":"Avda Doctor Severo Ochoa (del), 29",
    "sg:city":"Alcobendas",
    "sg:orig_category":"Metalurgia",
    "sg:phone":"+34 914 84 10 39",
    "sg:postcode":"28100",
    "sg:province":"Madrid",
    "sg:website":"www.grupobeer.com",
    "wof:name":"Debeer S.a.",
    "wof:placetype":"venue"
},
  "geometry": {"coordinates":[-3.6525568962,40.5415420532],"type":"Point"}
}