{
  "type": "Feature",
  "properties": {
    "iso:country":"ES",
    "sg:address":"R. Jardinito, S/n",
    "sg:city":"Cabra",
    "sg:orig_category":"M\u00c1rmoles, Granitos Y Piedras Naturales",
    "sg:phone":"+34 957 52 23 28",
    "sg:postcode":"14940",
    "sg:province":"C\u00f3rdoba",
    "wof:name":"Piedra Gutierrez S. A.",
    "wof:placetype":"venue"
},
  "geometry": {"coordinates":[-4.4387841225,37.4695053101],"type":"Point"}
}