{
  "type": "Feature",
  "properties": {
    "iso:country":"ES",
    "sg:address":"Pase Escuelas Pias (de Las), 25",
    "sg:city":"Santa Cruz De Tenerife",
    "sg:orig_category":"Instalaci\u00d3n De Sanitarios",
    "sg:phone":"+34 922 28 02 10",
    "sg:postcode":"38006",
    "sg:province":"Santa Cruz De Tenerife",
    "wof:name":"Granada Andaluci S.l.",
    "wof:placetype":"venue"
},
  "geometry": {"coordinates":[-16.2652893066,28.4761505127],"type":"Point"}
}