{
  "type": "Feature",
  "properties": {
    "addr:full":"Calle de Cabo Noval, 1 Logro\u00f1o La Rioja 26006",
    "addr:housenumber":"1",
    "addr:postcode":"26006",
    "addr:street":"Calle De Cabo Noval;Rioja",
    "iso:country":"ES",
    "sg:address":"Calle de Cabo Noval, 1",
    "sg:city":"Logro\u00f1o",
    "sg:orig_category":"Empresas De Limpieza",
    "sg:phone":"+34 941 25 98 44",
    "sg:postcode":"26006",
    "sg:province":"La Rioja",
    "wof:name":"Garcia Fernandez Fernando",
    "wof:placetype":"venue"
},
  "geometry": {"coordinates":[-2.4487454891,42.4719047546],"type":"Point"}
}