{
  "type": "Feature",
  "properties": {
    "addr:full":"Calle de Via Carpetana, 322 Madrid Madrid 28047",
    "addr:housenumber":"322",
    "addr:postcode":"28047",
    "addr:street":"Calle De Via Carpetana",
    "iso:country":"ES",
    "sg:address":"Calle de Via Carpetana, 322",
    "sg:city":"Madrid",
    "sg:orig_category":"Servicios Gsm",
    "sg:phone":"+34 914 62 34 47",
    "sg:postcode":"28047",
    "sg:province":"Madrid",
    "wof:name":"Sirotec Comunicaciones S.l.",
    "wof:placetype":"venue"
},
  "geometry": {"coordinates":[-3.7419250011,40.392364502],"type":"Point"}
}