{
  "type": "Feature",
  "properties": {
    "addr:full":"Pol Ind Norte, S/n Alginet Valencia 46230",
    "addr:housenumber":"s / n",
    "addr:postcode":"46230",
    "addr:street":"Ind Norte",
    "iso:country":"ES",
    "sg:address":"Pol Ind Norte, S/n",
    "sg:city":"Alginet",
    "sg:orig_category":"Contenedores (mercanc\u00cdas)",
    "sg:phone":"+34 961 75 40 91",
    "sg:postcode":"46230",
    "sg:province":"Valencia",
    "wof:name":"Servicios Combinados De Logistica Y Distribucion S.l.",
    "wof:placetype":"venue"
},
  "geometry": {"coordinates":[-0.470043987,39.2614898682],"type":"Point"}
}