{
  "type": "Feature",
  "properties": {
    "addr:full":"Calle de Oceano Atlantico, S/n Zaragoza Zaragoza 50012",
    "addr:housenumber":"s / n",
    "addr:postcode":"50012",
    "addr:street":"Calle De Oceano Atlantico",
    "iso:country":"ES",
    "sg:address":"Calle de Oceano Atlantico, S/n",
    "sg:city":"Zaragoza",
    "sg:orig_category":"Centros De Educaci\u00d3n Especial",
    "sg:phone":"+34 976 32 98 98",
    "sg:postcode":"50012",
    "sg:province":"Zaragoza",
    "wof:name":"Colegio Publico Hispanidad",
    "wof:placetype":"venue"
},
  "geometry": {"coordinates":[-0.9178940058,41.6468086243],"type":"Point"}
}