{
  "type": "Feature",
  "properties": {
    "iso:country":"ES",
    "sg:address":"Calle de Uhagon Felipe Alcalde, 1",
    "sg:city":"Bilbao",
    "sg:orig_category":"Obras Y Organismos Sociales",
    "sg:phone":"+34 944 44 30 88",
    "sg:postcode":"48010",
    "sg:province":"Vizcaya",
    "wof:name":"Asociacion De Mediacion Familiar Ados Jarri",
    "wof:placetype":"venue"
},
  "geometry": {"coordinates":[-2.9413208961,43.2591667175],"type":"Point"}
}