{
  "type": "Feature",
  "properties": {
    "iso:country":"ES",
    "sg:address":"Calle de Bodegas, 7",
    "sg:city":"Cisterniga",
    "sg:orig_category":"Farmacias",
    "sg:phone":"+34 983 40 11 55",
    "sg:postcode":"47193",
    "sg:province":"Valladolid",
    "wof:name":"Perez Lopez Susana",
    "wof:placetype":"venue"
},
  "geometry": {"coordinates":[-4.6847696304,41.6125526428],"type":"Point"}
}