{
  "type": "Feature",
  "properties": {
    "addr:full":"Carrer de Antoni Riera I Xam, 26 Palma Islas Baleares 07013",
    "addr:housenumber":"26",
    "addr:postcode":"07013",
    "addr:street":"Carrer De Antoni Riera I Xam",
    "iso:country":"ES",
    "sg:address":"Carrer de Antoni Riera I Xam, 26",
    "sg:city":"Palma",
    "sg:orig_category":"Molduras, Junquillos, Listones Y Molduras Perforadas",
    "sg:phone":"+34 971 28 07 58",
    "sg:postcode":"07013",
    "sg:province":"Islas Baleares",
    "wof:name":"Gil Gil Mario",
    "wof:placetype":"venue"
},
  "geometry": {"coordinates":[2.630284071,39.5804824829],"type":"Point"}
}