{
  "type": "Feature",
  "properties": {
    "addr:full":"Calle de Dibujante Falo, 6 Langreo Asturias 33900",
    "addr:housenumber":"6",
    "addr:postcode":"33900",
    "addr:street":"Calle De Dibujante Falo",
    "iso:country":"ES",
    "sg:address":"Calle de Dibujante Falo, 6",
    "sg:city":"Langreo",
    "sg:orig_category":"Cl\u00cdnicas Dentales",
    "sg:phone":"+34 985 67 54 21",
    "sg:postcode":"33900",
    "sg:province":"Asturias",
    "wof:name":"Clinica Dental San Pedro S.l.u",
    "wof:placetype":"venue"
},
  "geometry": {"coordinates":[-5.6956443787,43.310459137],"type":"Point"}
}