{
  "type": "Feature",
  "properties": {
    "iso:country":"ES",
    "sg:address":"Plaz Salvador, 11",
    "sg:city":"Sevilla",
    "sg:orig_category":"Trajes Y Adornos De Boda (confecci\u00d3n, Al Por Menor)",
    "sg:phone":"+34 954 22 90 22",
    "sg:postcode":"41004",
    "sg:province":"Sevilla",
    "wof:name":"Reyesol S.l.",
    "wof:placetype":"venue"
},
  "geometry": {"coordinates":[-5.9931540489,37.3903694153],"type":"Point"}
}