{
  "type": "Feature",
  "properties": {
    "addr:full":"Avda Carmen, 19 Buenavista De Valdavia Palencia 34472",
    "addr:housenumber":"19",
    "addr:postcode":"34472",
    "addr:street":"Avda Carmen",
    "iso:country":"ES",
    "sg:address":"Avda Carmen, 19",
    "sg:city":"Buenavista De Valdavia",
    "sg:orig_category":"Distribuci\u00d3n De Petr\u00d3leo Y Derivados",
    "sg:phone":"+34 979 89 50 14",
    "sg:postcode":"34472",
    "sg:province":"Palencia",
    "wof:name":"Jesus Carmelo Trece\u00f1o Diez Y Tomas Trece\u00f1o Diez C.b.",
    "wof:placetype":"venue"
},
  "geometry": {"coordinates":[-4.613047123,42.6353149414],"type":"Point"}
}