{
  "type": "Feature",
  "properties": {
    "addr:full":"Calle de Juan Agustin Palomar, 38 Camas Sevilla 41900",
    "addr:housenumber":"38",
    "addr:postcode":"41900",
    "addr:street":"Calle De Juan Agustin Palomar",
    "iso:country":"ES",
    "sg:address":"Calle de Juan Agustin Palomar, 38",
    "sg:city":"Camas",
    "sg:orig_category":"Art\u00cdculos De Aluminio",
    "sg:phone":"+34 955 98 10 83",
    "sg:postcode":"41900",
    "sg:province":"Sevilla",
    "wof:name":"Romero Duran Felipe",
    "wof:placetype":"venue"
},
  "geometry": {"coordinates":[-6.0333647728,37.4031295776],"type":"Point"}
}