{
  "type": "Feature",
  "properties": {
    "iso:country":"ES",
    "sg:address":"Carrer de Joan Bonet, 19",
    "sg:city":"Palma",
    "sg:orig_category":"Empresas De Carpinter\u00cda Met\u00c1lica",
    "sg:phone":"+34 971 29 11 25",
    "sg:postcode":"07004",
    "sg:province":"Islas Baleares",
    "wof:name":"Cristaleria Amanecer S.l.",
    "wof:placetype":"venue"
},
  "geometry": {"coordinates":[2.6585879326,39.5908546448],"type":"Point"}
}