{
  "type": "Feature",
  "properties": {
    "addr:full":"Calle de Fidias, 12 Malaga M\u00e1laga 29004",
    "addr:housenumber":"12",
    "addr:postcode":"29004",
    "addr:street":"Calle De Fidias;Ma\u0301Laga",
    "iso:country":"ES",
    "sg:address":"Calle de Fidias, 12",
    "sg:city":"Malaga",
    "sg:orig_category":"Empresas De Carpinter\u00cda De Madera",
    "sg:phone":"+34 952 24 11 63",
    "sg:postcode":"29004",
    "sg:province":"M\u00e1laga",
    "wof:name":"Juan Miranda S.l.",
    "wof:placetype":"venue"
},
  "geometry": {"coordinates":[-4.4639630318,36.6916847229],"type":"Point"}
}