{
  "type": "Feature",
  "properties": {
    "addr:full":"Calle de Almatriche, 162 Tenoya Las Palmas 35018",
    "addr:housenumber":"162",
    "addr:postcode":"35018",
    "addr:street":"Calle De Almatriche;Las Palmas",
    "iso:country":"ES",
    "sg:address":"Calle de Almatriche, 162",
    "sg:city":"Tenoya",
    "sg:orig_category":"Cr\u00cda De Animales",
    "sg:phone":"+34 928 67 44 64",
    "sg:postcode":"35018",
    "sg:province":"Las Palmas",
    "wof:name":"Medina Aleman Jose Ignacio",
    "wof:placetype":"venue"
},
  "geometry": {"coordinates":[-15.4594726562,28.0910129547],"type":"Point"}
}