{
  "type": "Feature",
  "properties": {
    "addr:full":"Carrer de Ramon Y Cajal, 82 Terrassa Barcelona 08222",
    "addr:housenumber":"82",
    "addr:postcode":"08222",
    "addr:street":"Carrer De Ramon Y Cajal",
    "iso:country":"ES",
    "sg:address":"Carrer de Ramon Y Cajal, 82",
    "sg:city":"Terrassa",
    "sg:orig_category":"Peluquer\u00cdas, Peluquer\u00cda Mixta",
    "sg:phone":"+34 937 84 16 46",
    "sg:postcode":"08222",
    "sg:province":"Barcelona",
    "wof:name":"Lopez Varo Nuria",
    "wof:placetype":"venue"
},
  "geometry": {"coordinates":[2.0247569084,41.5606422424],"type":"Point"}
}