{
  "type": "Feature",
  "properties": {
    "addr:full":"G.v. Corts Catalanes, 582 Barcelona Barcelona 08011",
    "addr:housenumber":"582",
    "addr:postcode":"08011",
    "addr:street":"Catalanes",
    "iso:country":"ES",
    "sg:address":"G.v. Corts Catalanes, 582",
    "sg:city":"Barcelona",
    "sg:orig_category":"Promotores Constructores",
    "sg:phone":"+34 934 51 23 41",
    "sg:postcode":"08011",
    "sg:province":"Barcelona",
    "wof:name":"Restaura S. L.",
    "wof:placetype":"venue"
},
  "geometry": {"coordinates":[2.1627140045,41.3848114014],"type":"Point"}
}