{
  "type": "Feature",
  "properties": {
    "addr:full":"Calle de Virgen De Guia, 6 Hinojosa Del Duque C\u00f3rdoba 14270",
    "addr:housenumber":"6",
    "addr:postcode":"14270",
    "addr:street":"Calle De Virgen De Guia;Co\u0301Rdoba",
    "iso:country":"ES",
    "sg:address":"Calle de Virgen De Guia, 6",
    "sg:city":"Hinojosa Del Duque",
    "sg:orig_category":"Cerrajer\u00cda, Ferrallista",
    "sg:phone":"+34 957 14 02 43",
    "sg:postcode":"14270",
    "sg:province":"C\u00f3rdoba",
    "wof:name":"Gil Acedo Baldomero",
    "wof:placetype":"venue"
},
  "geometry": {"coordinates":[-5.1387119293,38.4946022034],"type":"Point"}
}