{
  "type": "Feature",
  "properties": {
    "iso:country":"ES",
    "sg:address":"Calle de Laurel, 22",
    "sg:city":"Logro\u00f1o",
    "sg:orig_category":"Molduras, Junquillos, Listones Y Molduras Perforadas",
    "sg:phone":"+34 941 22 00 74",
    "sg:postcode":"26001",
    "sg:province":"La Rioja",
    "wof:name":"Ruiz Villanueva Jesus Felix",
    "wof:placetype":"venue"
},
  "geometry": {"coordinates":[-2.4489378929,42.4655380249],"type":"Point"}
}