{
  "type": "Feature",
  "properties": {
    "addr:full":"Carrer de Mas, 84 Hospitalet Llobregat Barcelona 08904",
    "addr:housenumber":"84",
    "addr:postcode":"08904",
    "addr:street":"Carrer De Mas",
    "iso:country":"ES",
    "sg:address":"Carrer de Mas, 84",
    "sg:city":"Hospitalet Llobregat",
    "sg:orig_category":"Cerrajer\u00cda, Ferrallista",
    "sg:phone":"+34 934 49 49 75",
    "sg:postcode":"08904",
    "sg:province":"Barcelona",
    "wof:name":"Pericas Torredeflot Francisco",
    "wof:placetype":"venue"
},
  "geometry": {"coordinates":[2.1196200848,41.3715171814],"type":"Point"}
}