{
  "type": "Feature",
  "properties": {
    "addr:full":"Calle de Villacampa, 10 Madrid Madrid 28031",
    "addr:housenumber":"10",
    "addr:postcode":"madrid;28031",
    "addr:street":"Calle De Villacampa",
    "iso:country":"ES",
    "sg:address":"Calle de Villacampa, 10",
    "sg:city":"Madrid",
    "sg:orig_category":"Inmobiliaria (agencias)",
    "sg:phone":"+34 913 03 01 37",
    "sg:postcode":"28031",
    "sg:province":"Madrid",
    "wof:name":"Torrejon Maya S.l.",
    "wof:placetype":"venue"
},
  "geometry": {"coordinates":[-3.6233963966,40.3796539307],"type":"Point"}
}