{
  "type": "Feature",
  "properties": {
    "iso:country":"ES",
    "sg:address":"Calle de Xativa, 21",
    "sg:city":"Valencia",
    "sg:orig_category":"Confecci\u00d3n De Sombreros Y Tocados",
    "sg:phone":"+34 963 51 22 45",
    "sg:postcode":"46002",
    "sg:province":"Valencia",
    "wof:name":"Albero Garcia Vicente",
    "wof:placetype":"venue"
},
  "geometry": {"coordinates":[-0.3758356869,39.4672927856],"type":"Point"}
}