{
  "type": "Feature",
  "properties": {
    "addr:full":"Calle de Obispo Bartolome Espejo, 6 Malaga M\u00e1laga 29014",
    "addr:housenumber":"6",
    "addr:postcode":"29014",
    "addr:street":"Calle De Obispo Bartolome Espejo;Ma\u0301Laga",
    "iso:country":"ES",
    "sg:address":"Calle de Obispo Bartolome Espejo, 6",
    "sg:city":"Malaga",
    "sg:orig_category":"Papeler\u00cdas, Librer\u00cdas",
    "sg:phone":"+34 952 26 95 61",
    "sg:postcode":"29014",
    "sg:province":"M\u00e1laga",
    "wof:name":"Rico Martin Antonio",
    "wof:placetype":"venue"
},
  "geometry": {"coordinates":[-4.4219841957,36.7350463867],"type":"Point"}
}