{
  "type": "Feature",
  "properties": {
    "iso:country":"ES",
    "sg:address":"Calle de Encarnacio, L', 49",
    "sg:city":"Burriana",
    "sg:orig_category":"Art\u00cdculos De Regalo (al Por Menor)",
    "sg:phone":"+34 964 57 07 34",
    "sg:postcode":"12530",
    "sg:province":"Castell\u00f3n",
    "wof:name":"Desvan De Inma,s.l.u.",
    "wof:placetype":"venue"
},
  "geometry": {"coordinates":[-0.0874700025,39.8906517029],"type":"Point"}
}