{
  "type": "Feature",
  "properties": {
    "iso:country":"ES",
    "sg:address":"Calle de Doctor Alberto Garcia Iba\u00d1ez, S/n",
    "sg:city":"Palmas De Gran Canaria",
    "sg:orig_category":"Centros De Educaci\u00d3n Especial",
    "sg:phone":"+34 928 20 26 35",
    "sg:postcode":"35011",
    "sg:province":"Las Palmas",
    "wof:name":"Gobierno De Canarias",
    "wof:placetype":"venue"
},
  "geometry": {"coordinates":[-15.4400148392,28.1168766022],"type":"Point"}
}