{
  "type": "Feature",
  "properties": {
    "addr:full":"Calle de General Alvarez De Castro, 9 Madrid Madrid 28010",
    "addr:housenumber":"9",
    "addr:postcode":"madrid;28010",
    "addr:street":"Calle De General Alvarez De Castro",
    "iso:country":"ES",
    "sg:address":"Calle de General Alvarez De Castro, 9",
    "sg:city":"Madrid",
    "sg:orig_category":"Agencias De Viajes",
    "sg:phone":"+34 914 47 17 70",
    "sg:postcode":"28010",
    "sg:province":"Madrid",
    "sg:website":"www.marsans.es",
    "wof:name":"Viajes Marsans S. A",
    "wof:placetype":"venue"
},
  "geometry": {"coordinates":[-3.7021670341,40.434928894],"type":"Point"}
}