{
  "type": "Feature",
  "properties": {
    "iso:country":"ES",
    "sg:address":"Carrer de Salvador I Vicente Perez Lledo, 6",
    "sg:city":"Mutxamel",
    "sg:orig_category":"Restaurantes",
    "sg:phone":"+34 965 95 29 12",
    "sg:postcode":"03110",
    "sg:province":"Alicante",
    "wof:name":"Riera Blasco Miguel Angel",
    "wof:placetype":"venue"
},
  "geometry": {"coordinates":[-0.4427889884,38.4124145508],"type":"Point"}
}