{
  "type": "Feature",
  "properties": {
    "iso:country":"ES",
    "sg:address":"Carrer de Ortega Y Gasset, 15",
    "sg:city":"Palma",
    "sg:orig_category":"Iglesias Evang\u00c9licas",
    "sg:phone":"+34 971 47 14 01",
    "sg:postcode":"07008",
    "sg:province":"Islas Baleares",
    "wof:name":"Iglesia Bautista Reformada",
    "wof:placetype":"venue"
},
  "geometry": {"coordinates":[2.6730630398,39.5821075439],"type":"Point"}
}