{
  "type": "Feature",
  "properties": {
    "addr:full":"Avda Andalucia, 15 Malaga M\u00e1laga 29002",
    "addr:housenumber":"15",
    "addr:postcode":"29002",
    "addr:street":"Avda Andalucia;Ma\u0301Laga",
    "iso:country":"ES",
    "sg:address":"Avda Andalucia, 15",
    "sg:city":"Malaga",
    "sg:orig_category":"M\u00c9dicos: Estomatolog\u00cda",
    "sg:phone":"+34 952 36 90 67",
    "sg:postcode":"29002",
    "sg:province":"M\u00e1laga",
    "wof:name":"Antonelli Gomez Roberto Nestor",
    "wof:placetype":"venue"
},
  "geometry": {"coordinates":[-4.4315023422,36.7168960571],"type":"Point"}
}