{
  "type": "Feature",
  "properties": {
    "iso:country":"ES",
    "sg:address":"Avda Valencia, 47",
    "sg:city":"Zaragoza",
    "sg:orig_category":"Librer\u00cdas",
    "sg:phone":"+34 976 35 52 17",
    "sg:postcode":"50005",
    "sg:province":"Zaragoza",
    "wof:name":"Iba\u00f1ez Lasmarias Maria Carmen",
    "wof:placetype":"venue"
},
  "geometry": {"coordinates":[-0.8977429867,41.6458473206],"type":"Point"}
}