{
  "type": "Feature",
  "properties": {
    "iso:country":"ES",
    "sg:address":"Camino De Bureta, S/n",
    "sg:city":"Pedrola",
    "sg:orig_category":"Construcciones Met\u00c1licas",
    "sg:phone":"+34 976 61 50 54",
    "sg:postcode":"50690",
    "sg:province":"Zaragoza",
    "wof:name":"Jose Manuel Galindo S.l.",
    "wof:placetype":"venue"
},
  "geometry": {"coordinates":[-1.2175040245,41.7832183838],"type":"Point"}
}