{
  "type": "Feature",
  "properties": {
    "iso:country":"ES",
    "sg:address":"Avda Arqueros, S/n",
    "sg:city":"Madrid",
    "sg:orig_category":"Guarder\u00cdas",
    "sg:phone":"+34 915 09 07 86",
    "sg:postcode":"28024",
    "sg:province":"Madrid",
    "wof:name":"Dehesa Del Principe S. L.",
    "wof:placetype":"venue"
},
  "geometry": {"coordinates":[-3.7940471172,40.3806610107],"type":"Point"}
}