{
  "type": "Feature",
  "properties": {
    "addr:full":"Rua Serra, 4 Pontevedra Pontevedra 36002",
    "addr:housenumber":"4",
    "addr:postcode":"36002",
    "addr:street":"Rua Serra",
    "iso:country":"ES",
    "sg:address":"Rua Serra, 4",
    "sg:city":"Pontevedra",
    "sg:orig_category":"Carnicer\u00cdas, Carnicer\u00cdas",
    "sg:phone":"+34 986 85 26 59",
    "sg:postcode":"36002",
    "sg:province":"Pontevedra",
    "wof:name":"Laya Varela Santiago",
    "wof:placetype":"venue"
},
  "geometry": {"coordinates":[-8.642906189,42.4340629578],"type":"Point"}
}