{
  "type": "Feature",
  "properties": {
    "addr:full":"Calle de Francia, 7 Vitoria-gasteiz \u00c1lava 01002",
    "addr:housenumber":"7",
    "addr:postcode":"01002",
    "addr:street":"Calle De Francia",
    "iso:country":"ES",
    "sg:address":"Calle de Francia, 7",
    "sg:city":"Vitoria-gasteiz",
    "sg:orig_category":"Alquiler De Apartamentos",
    "sg:phone":"+34 945 25 67 57",
    "sg:postcode":"01002",
    "sg:province":"\u00c1lava",
    "wof:name":"Arregui Lancha Juan Maria",
    "wof:placetype":"venue"
},
  "geometry": {"coordinates":[-2.6687498093,42.8495903015],"type":"Point"}
}