{
  "type": "Feature",
  "properties": {
    "iso:country":"ES",
    "sg:address":"Calle de Hermanos Barral, 3",
    "sg:city":"Segovia",
    "sg:orig_category":"Cl\u00cdnicas Dentales",
    "sg:phone":"+34 921 46 38 86",
    "sg:postcode":"40001",
    "sg:province":"Segovia",
    "wof:name":"Andres Fernandez Milagros",
    "wof:placetype":"venue"
},
  "geometry": {"coordinates":[-4.1203389168,40.9460678101],"type":"Point"}
}