{
  "type": "Feature",
  "properties": {
    "iso:country":"ES",
    "sg:address":"Rbla Passeig, 8",
    "sg:city":"Vic",
    "sg:orig_category":"Juegos Y Juguetes (al Por Menor)",
    "sg:phone":"+34 938 89 34 09",
    "sg:postcode":"08500",
    "sg:province":"Barcelona",
    "sg:website":"www.imaginarium.es",
    "wof:name":"Sole Gimeno Teresa",
    "wof:placetype":"venue"
},
  "geometry": {"coordinates":[2.2556419373,41.9305458069],"type":"Point"}
}