{
  "type": "Feature",
  "properties": {
    "addr:full":"Calle de Sancho Panza, 8 Granada Granada 18008",
    "addr:housenumber":"8",
    "addr:postcode":"18008",
    "addr:street":"Calle De Sancho Panza",
    "iso:country":"ES",
    "sg:address":"Calle de Sancho Panza, 8",
    "sg:city":"Granada",
    "sg:orig_category":"Caf\u00c9s, Bares, Cervecer\u00cdas",
    "sg:phone":"+34 958 12 26 65",
    "sg:postcode":"18008",
    "sg:province":"Granada",
    "wof:name":"Ramos Montilla Rafael",
    "wof:placetype":"venue"
},
  "geometry": {"coordinates":[-3.5885589123,37.1628837585],"type":"Point"}
}