{
  "type": "Feature",
  "properties": {
    "addr:full":"Calle de Poeta Llorente, 6 Pobla Vallbona Valencia 46185",
    "addr:housenumber":"6",
    "addr:postcode":"46185",
    "addr:street":"Calle De Poeta Llorente",
    "iso:country":"ES",
    "sg:address":"Calle de Poeta Llorente, 6",
    "sg:city":"Pobla Vallbona",
    "sg:orig_category":"Pintura Y Barniz (al Por Menor)",
    "sg:phone":"+34 962 76 14 23",
    "sg:postcode":"46185",
    "sg:province":"Valencia",
    "wof:name":"Pinturas Deima S.l.",
    "wof:placetype":"venue"
},
  "geometry": {"coordinates":[-0.5538725257,39.5928153992],"type":"Point"}
}