{
  "type": "Feature",
  "properties": {
    "addr:full":"Calle de Condesa De La Vega Del Pozo, 4 Guadalajara Guadalajara 19001",
    "addr:housenumber":"4",
    "addr:postcode":"19001",
    "addr:street":"Calle De Condesa De La;Del Pozo",
    "iso:country":"ES",
    "sg:address":"Calle de Condesa De La Vega Del Pozo, 4",
    "sg:city":"Guadalajara",
    "sg:orig_category":"Centros De Coordinaci\u00d3n",
    "sg:phone":"+34 949 22 04 96",
    "sg:postcode":"19001",
    "sg:province":"Guadalajara",
    "wof:name":"Aguado Taberne Maria Del Carmen",
    "wof:placetype":"venue"
},
  "geometry": {"coordinates":[-3.1644523144,40.6312675476],"type":"Point"}
}