{
  "type": "Feature",
  "properties": {
    "iso:country":"ES",
    "sg:address":"Av Baro, 12",
    "sg:city":"Barcelona",
    "sg:orig_category":"Estudios De Grabaci\u00d3n Sonora",
    "sg:phone":"+34 932 85 60 38",
    "sg:postcode":"08024",
    "sg:province":"Barcelona",
    "wof:name":"Internacional Sound Studio S.a.",
    "wof:placetype":"venue"
},
  "geometry": {"coordinates":[2.1614611149,41.4154014587],"type":"Point"}
}