{
  "type": "Feature",
  "properties": {
    "addr:full":"Calle de Virgen De La Esperanza, 32 Malaga M\u00e1laga 29007",
    "addr:housenumber":"32",
    "addr:postcode":"29007",
    "addr:street":"Calle De Virgen De La Esperanza;Ma\u0301Laga",
    "iso:country":"ES",
    "sg:address":"Calle de Virgen De La Esperanza, 32",
    "sg:city":"Malaga",
    "sg:orig_category":"Plomeros",
    "sg:phone":"+34 952 39 85 43",
    "sg:postcode":"29007",
    "sg:province":"M\u00e1laga",
    "wof:name":"Malague\u00f1a Hidraulico Sanitaria S.l.",
    "wof:placetype":"venue"
},
  "geometry": {"coordinates":[-4.4435558319,36.7195091248],"type":"Point"}
}