{
  "type": "Feature",
  "properties": {
    "addr:full":"Calle de Rio, 39 Priego Cordoba C\u00f3rdoba 14800",
    "addr:housenumber":"39",
    "addr:postcode":"14800",
    "addr:street":"Calle De Rio;Cordoba Co\u0301Rdoba",
    "iso:country":"ES",
    "sg:address":"Calle de Rio, 39",
    "sg:city":"Priego Cordoba",
    "sg:orig_category":"M\u00c9dicos: Naturistas",
    "sg:phone":"+34 957 54 00 03",
    "sg:postcode":"14800",
    "sg:province":"C\u00f3rdoba",
    "wof:name":"Sanchez Ordo\u00f1ez Maria Del Carmen",
    "wof:placetype":"venue"
},
  "geometry": {"coordinates":[-4.1951441765,37.436920166],"type":"Point"}
}