{
  "type": "Feature",
  "properties": {
    "iso:country":"ES",
    "sg:address":"Paseo Los Charcales, S/n",
    "sg:city":"Trevelez",
    "sg:orig_category":"Carnicer\u00cdas, Carnicer\u00cdas",
    "sg:phone":"+34 958 85 87 41",
    "sg:postcode":"18417",
    "sg:province":"Granada",
    "wof:name":"Antonio Alvarez Jamones S.l.",
    "wof:placetype":"venue"
},
  "geometry": {"coordinates":[-3.2684214115,37.0488243103],"type":"Point"}
}