{
  "type": "Feature",
  "properties": {
    "iso:country":"ES",
    "sg:address":"Calle de Amor De Dios, 1",
    "sg:city":"Cadiz",
    "sg:orig_category":"Iglesia Cat\u00d3lica",
    "sg:phone":"+34 956 26 12 65",
    "sg:postcode":"11009",
    "sg:province":"C\u00e1diz",
    "wof:name":"Parroquia Santo Tomas De Aquino",
    "wof:placetype":"venue"
},
  "geometry": {"coordinates":[-6.2752370834,36.5086936951],"type":"Point"}
}