{
  "type": "Feature",
  "properties": {
    "addr:full":"Calle de Palma, 15 Madrid Madrid 28004",
    "addr:housenumber":"15",
    "addr:postcode":"madrid;28004",
    "addr:street":"Calle De Palma",
    "iso:country":"ES",
    "sg:address":"Calle de Palma, 15",
    "sg:city":"Madrid",
    "sg:orig_category":"Dietistas",
    "sg:phone":"+34 914 47 80 13",
    "sg:postcode":"28004",
    "sg:province":"Madrid",
    "wof:name":"De Guillermo Cerezo Alberto",
    "wof:placetype":"venue"
},
  "geometry": {"coordinates":[-3.7027819157,40.4260787964],"type":"Point"}
}