{
  "type": "Feature",
  "properties": {
    "iso:country":"ES",
    "sg:address":"Finca El Roblillo, S/n",
    "sg:city":"La Losa",
    "sg:orig_category":"Cr\u00cda De Cerdos",
    "sg:phone":"+34 921 12 02 56",
    "sg:postcode":"40420",
    "sg:province":"Segovia",
    "wof:name":"Inversiones Y Productos Mams S.a.",
    "wof:placetype":"venue"
},
  "geometry": {"coordinates":[-4.1627058983,40.8536148071],"type":"Point"}
}