{
  "type": "Feature",
  "properties": {
    "iso:country":"ES",
    "sg:address":"Calle de Pascual Veiga, 25",
    "sg:city":"Coru\u00d1a",
    "sg:orig_category":"Comerciantes Al Por Mayor De Vinos, Licores Y Alcoholes",
    "sg:phone":"+34 981 27 28 09",
    "sg:postcode":"15010",
    "sg:province":"La Coru\u00f1a",
    "wof:name":"Bermudez Lousa Manuel",
    "wof:placetype":"venue"
},
  "geometry": {"coordinates":[-8.42091465,43.3632965088],"type":"Point"}
}