{
  "type": "Feature",
  "properties": {
    "iso:country":"ES",
    "sg:address":"Plaz Reverencia, 2",
    "sg:city":"Madrid",
    "sg:orig_category":"Peluquer\u00cdas, Peluquer\u00cda Mixta",
    "sg:phone":"+34 913 67 78 00",
    "sg:postcode":"28027",
    "sg:province":"Madrid",
    "wof:name":"Herrero Fernandez Maria Montserrat",
    "wof:placetype":"venue"
},
  "geometry": {"coordinates":[-3.6424748898,40.4369888306],"type":"Point"}
}