{
  "type": "Feature",
  "properties": {
    "iso:country":"ES",
    "sg:address":"Vilachai\u00f1o, S/n",
    "sg:city":"Vilachai\u00d1o",
    "sg:orig_category":"Agricultura: Abastecimiento Y Cosechado (negocio)",
    "sg:phone":"+34 981 80 92 67",
    "sg:postcode":"15886",
    "sg:province":"La Coru\u00f1a",
    "wof:name":"Agro Santa Lucia",
    "wof:placetype":"venue"
},
  "geometry": {"coordinates":[-8.3959693909,43.3714904785],"type":"Point"}
}