{
  "type": "Feature",
  "properties": {
    "iso:country":"ES",
    "sg:address":"Plaz Colon (de), 4",
    "sg:city":"Cordoba",
    "sg:orig_category":"Arquitectos",
    "sg:phone":"+34 957 48 84 73",
    "sg:postcode":"14001",
    "sg:province":"C\u00f3rdoba",
    "wof:name":"Moreno Ramirez Ana",
    "wof:placetype":"venue"
},
  "geometry": {"coordinates":[-4.7768778801,37.8887481689],"type":"Point"}
}