{
  "type": "Feature",
  "properties": {
    "addr:full":"Carrer de Girona, 78 Prat Llobregat Barcelona 08820",
    "addr:housenumber":"78",
    "addr:postcode":"08820",
    "addr:street":"Carrer De Girona;Llobregat",
    "iso:country":"ES",
    "sg:address":"Carrer de Girona, 78",
    "sg:city":"Prat Llobregat",
    "sg:orig_category":"Electricidad: Instaladores",
    "sg:phone":"+34 933 70 22 90",
    "sg:postcode":"08820",
    "sg:province":"Barcelona",
    "wof:name":"Proyectos E Instalaciones Gamez S.l.",
    "wof:placetype":"venue"
},
  "geometry": {"coordinates":[2.0908610821,41.3201637268],"type":"Point"}
}