{
  "type": "Feature",
  "properties": {
    "iso:country":"ES",
    "sg:address":"Avda San Lorenzo, 1",
    "sg:city":"Estepona",
    "sg:orig_category":"Oficinas De Turismo, Asociaciones De Iniciativa",
    "sg:phone":"+34 952 80 20 02",
    "sg:postcode":"29680",
    "sg:province":"M\u00e1laga",
    "sg:website":"www.pgb.es/estepona.es",
    "wof:name":"Ayuntamiento De Estepona",
    "wof:placetype":"venue"
},
  "geometry": {"coordinates":[-5.1477742195,36.423374176],"type":"Point"}
}