{
  "type": "Feature",
  "properties": {
    "iso:country":"ES",
    "sg:address":"Avda Antonio Garelly, S/n",
    "sg:city":"S. Vicente Barquera",
    "sg:orig_category":"Carnicer\u00cdas, Carnicer\u00cdas",
    "sg:phone":"+34 942 71 00 73",
    "sg:postcode":"39540",
    "sg:province":"Cantabria",
    "wof:name":"Alonso Herrero Felipe",
    "wof:placetype":"venue"
},
  "geometry": {"coordinates":[-4.3986606598,43.3847198486],"type":"Point"}
}