{
  "type": "Feature",
  "properties": {
    "addr:full":"Carr Xalo, 1 Benissa Alicante 03720",
    "addr:housenumber":"1",
    "addr:postcode":"03720",
    "addr:street":"Carr Xalo",
    "iso:country":"ES",
    "sg:address":"Carr Xalo, 1",
    "sg:city":"Benissa",
    "sg:orig_category":"Plomeros",
    "sg:phone":"+34 965 73 03 25",
    "sg:postcode":"03720",
    "sg:province":"Alicante",
    "wof:name":"Instalaciones Marcos Crespo, S.l.",
    "wof:placetype":"venue"
},
  "geometry": {"coordinates":[0.050774999,38.7144584656],"type":"Point"}
}