{
  "type": "Feature",
  "properties": {
    "iso:country":"ES",
    "sg:address":"Carrer de Arago, 327",
    "sg:city":"Barcelona",
    "sg:orig_category":"Tapiceros Y Tapiceros",
    "sg:phone":"+34 934 57 46 17",
    "sg:postcode":"08009",
    "sg:province":"Barcelona",
    "wof:name":"Gallardo Garcia Jose Francisco",
    "wof:placetype":"venue"
},
  "geometry": {"coordinates":[2.1701509953,41.3963241577],"type":"Point"}
}