{
  "type": "Feature",
  "properties": {
    "addr:full":"Ctra Logro\u00d1o, Km. 0002,0 Oyon-oion \u00c1lava 01320",
    "addr:postcode":"01320",
    "addr:street":"Ctra Logron\u0303O Km. 0002,0 Oyon-Oion A\u0301Lava",
    "iso:country":"ES",
    "sg:address":"Ctra Logro\u00d1o, Km. 0002,0",
    "sg:city":"Oyon-oion",
    "sg:orig_category":"Quincaller\u00cda (al Por Menor)",
    "sg:phone":"+34 945 60 13 29",
    "sg:postcode":"01320",
    "sg:province":"\u00c1lava",
    "wof:name":"Ferreteria La Inglesa S. A.",
    "wof:placetype":"venue"
},
  "geometry": {"coordinates":[-2.4377980232,42.5001602173],"type":"Point"}
}