{
  "type": "Feature",
  "properties": {
    "iso:country":"ES",
    "sg:address":"Fca. V. Gonzalia\u00f1ez, S/n",
    "sg:city":"Horcajo-medianero",
    "sg:orig_category":"Equitaci\u00d3n Y Centros De H\u00cdpica",
    "sg:phone":"+34 923 15 14 16",
    "sg:postcode":"37860",
    "sg:province":"Salamanca",
    "wof:name":"Sanchez Sanchez Francisco",
    "wof:placetype":"venue"
},
  "geometry": {"coordinates":[-5.4082489014,40.6417503357],"type":"Point"}
}