{
  "type": "Feature",
  "properties": {
    "iso:country":"ES",
    "sg:address":"Calle de Adriano Vi, 17",
    "sg:city":"Vitoria-gasteiz",
    "sg:orig_category":"Arquitectos",
    "sg:phone":"+34 945 22 85 78",
    "sg:postcode":"01008",
    "sg:province":"\u00c1lava",
    "wof:name":"Valdivielso Fernandez De Gobeo Jesus Javier",
    "wof:placetype":"venue"
},
  "geometry": {"coordinates":[-2.682626009,42.8474121094],"type":"Point"}
}