{
  "type": "Feature",
  "properties": {
    "addr:full":"Plaz Diaz Moreu, 2 Motril Granada 18600",
    "addr:housenumber":"2",
    "addr:postcode":"18600",
    "addr:street":"Plaz;Moreu",
    "iso:country":"ES",
    "sg:address":"Plaz Diaz Moreu, 2",
    "sg:city":"Motril",
    "sg:orig_category":"Zapatos (al Por Menor)",
    "sg:phone":"+34 958 60 83 23",
    "sg:postcode":"18600",
    "sg:province":"Granada",
    "wof:name":"Garcia Gonzalez Jose Antonio",
    "wof:placetype":"venue"
},
  "geometry": {"coordinates":[-3.519534111,36.7449531555],"type":"Point"}
}