{
  "type": "Feature",
  "properties": {
    "addr:full":"Calle de Forja (de La), 2 Tres Cantos Madrid 28760",
    "addr:housenumber":"2",
    "addr:postcode":"28760",
    "addr:street":"Calle De Forja De La",
    "iso:country":"ES",
    "sg:address":"Calle de Forja (de La), 2",
    "sg:city":"Tres Cantos",
    "sg:orig_category":"Gatos, Tornos Y Poleas A Motor, Hidr\u00c1ulicas Y Neum\u00c1ticas",
    "sg:phone":"+34 918 04 92 98",
    "sg:postcode":"28760",
    "sg:province":"Madrid",
    "sg:website":"www.sauer-danfoss.com",
    "wof:name":"Sauer-danfoss S.a.",
    "wof:placetype":"venue"
},
  "geometry": {"coordinates":[-3.6978440285,40.5980606079],"type":"Point"}
}