{
  "type": "Feature",
  "properties": {
    "addr:full":"Calle de San Valentin, 2 Baguena Teruel 44320",
    "addr:housenumber":"2",
    "addr:postcode":"44320",
    "addr:street":"Calle De San Valentin",
    "iso:country":"ES",
    "sg:address":"Calle de San Valentin, 2",
    "sg:city":"Baguena",
    "sg:orig_category":"Ense\u00d1anza, Formaci\u00d3n Profesional: Aprendizaje",
    "sg:phone":"+34 978 73 30 01",
    "sg:postcode":"44320",
    "sg:province":"Teruel",
    "wof:name":"Ayuntamiento De Baguena",
    "wof:placetype":"venue"
},
  "geometry": {"coordinates":[-1.3575509787,41.0401573181],"type":"Point"}
}