{
  "type": "Feature",
  "properties": {
    "addr:full":"Cmno Luceros (de Los), 26 Retamar Almer\u00eda 04130",
    "addr:housenumber":"26",
    "addr:postcode":"04130",
    "addr:street":"Cmno Luceros De Los;Almeri\u0301A",
    "iso:country":"ES",
    "sg:address":"Cmno Luceros (de Los), 26",
    "sg:city":"Retamar",
    "sg:orig_category":"Asociaciones Humanitarias, De Cooperaci\u00d3n, De Acci\u00d3n Social",
    "sg:phone":"+34 950 20 83 46",
    "sg:postcode":"04130",
    "sg:province":"Almer\u00eda",
    "wof:name":"Asociacion Comarcal De Minusvalidos Fisicos El Saliente",
    "wof:placetype":"venue"
},
  "geometry": {"coordinates":[-2.3044340611,36.8551445007],"type":"Point"}
}