{
  "type": "Feature",
  "properties": {
    "iso:country":"ES",
    "sg:address":"Rua Castelao, 137",
    "sg:city":"Grove",
    "sg:orig_category":"Arquitectos",
    "sg:phone":"+34 986 73 50 51",
    "sg:postcode":"36980",
    "sg:province":"Pontevedra",
    "wof:name":"Alvarez Perez Francisco",
    "wof:placetype":"venue"
},
  "geometry": {"coordinates":[-8.859295845,42.4915008545],"type":"Point"}
}