{
  "type": "Feature",
  "properties": {
    "iso:country":"ES",
    "sg:address":"Carretera Citores, S/n",
    "sg:city":"Sasamon",
    "sg:orig_category":"Quincaller\u00cda (al Por Menor)",
    "sg:phone":"+34 947 37 02 42",
    "sg:postcode":"09123",
    "sg:province":"Burgos",
    "wof:name":"Sabiniano Julian Miguel Y Otros S.cv.",
    "wof:placetype":"venue"
},
  "geometry": {"coordinates":[-4.0432810783,42.4154052734],"type":"Point"}
}