{
  "type": "Feature",
  "properties": {
    "addr:full":"Carrer de Pomaret, 114 Barcelona Barcelona 08017",
    "addr:housenumber":"114",
    "addr:postcode":"08017",
    "addr:street":"Carrer De Pomaret",
    "iso:country":"ES",
    "sg:address":"Carrer de Pomaret, 114",
    "sg:city":"Barcelona",
    "sg:orig_category":"Peritos Diversos",
    "sg:phone":"+34 934 18 65 06",
    "sg:postcode":"08017",
    "sg:province":"Barcelona",
    "wof:name":"Tarrago Goarre Silvia",
    "wof:placetype":"venue"
},
  "geometry": {"coordinates":[2.1203401089,41.408618927],"type":"Point"}
}