{
  "type": "Feature",
  "properties": {
    "addr:full":"Av Comarques Catalanes, 72 Mora D'ebre Tarragona 43740",
    "addr:housenumber":"72",
    "addr:postcode":"43740",
    "addr:street":"Av Comarques Catalanes",
    "iso:country":"ES",
    "sg:address":"Av Comarques Catalanes, 72",
    "sg:city":"Mora D'ebre",
    "sg:orig_category":"Mec\u00c1nico Del Autom\u00d3vil",
    "sg:phone":"+34 977 40 28 09",
    "sg:postcode":"43740",
    "sg:province":"Tarragona",
    "wof:name":"Tallers Galindo C.b.",
    "wof:placetype":"venue"
},
  "geometry": {"coordinates":[1.2540999651,41.1169281006],"type":"Point"}
}