{
  "type": "Feature",
  "properties": {
    "addr:full":"Calle de Orti Lara, 21 Marmolejo Ja\u00e9n 23770",
    "addr:housenumber":"21",
    "addr:postcode":"23770",
    "addr:street":"Calle De Orti Lara;Jae\u0301N",
    "iso:country":"ES",
    "sg:address":"Calle de Orti Lara, 21",
    "sg:city":"Marmolejo",
    "sg:classifiers":[
        {
            "category":"Cinema",
            "subcategory":"Movie Theater",
            "type":"Entertainment"
        }
    ],
    "sg:phone":"+34 953 54 00 57",
    "sg:postcode":"23770",
    "sg:province":"Ja\u00e9n",
    "sg:tags":[
        "salas",
        "de",
        "cine"
    ],
    "wof:name":"Lozano Medina Antonio",
    "wof:placetype":"venue"
},
  "geometry": {"coordinates":[-4.1691670418,38.0450019836],"type":"Point"}
}