{
  "type": "Feature",
  "properties": {
    "addr:full":"Trva Peregrina, 8 Bertamirans A Coru\u00f1a 15172",
    "addr:housenumber":"8",
    "addr:postcode":"15172",
    "addr:street":"Trva Peregrina;Corun\u0303A",
    "iso:country":"ES",
    "sg:address":"Trva Peregrina, 8",
    "sg:city":"Bertamirans",
    "sg:orig_category":"Traductores",
    "sg:phone":"+34 981 88 46 55",
    "sg:postcode":"15172",
    "sg:province":"A Coru\u00f1a",
    "wof:name":"Varela Vazquez Bego\u00f1a",
    "wof:placetype":"venue"
},
  "geometry": {"coordinates":[-8.6513900757,42.8615608215],"type":"Point"}
}