{
  "type": "Feature",
  "properties": {
    "addr:full":"Av Roma (de), 14 Tarragona Tarragona 43005",
    "addr:housenumber":"14",
    "addr:postcode":"43005",
    "addr:street":"Av Roma De",
    "iso:country":"ES",
    "sg:address":"Av Roma (de), 14",
    "sg:city":"Tarragona",
    "sg:orig_category":"Reposter\u00cdas",
    "sg:phone":"+34 977 22 71 52",
    "sg:postcode":"43005",
    "sg:province":"Tarragona",
    "wof:name":"Gimeno Royo Coronado",
    "wof:placetype":"venue"
},
  "geometry": {"coordinates":[1.2418119907,41.1181907654],"type":"Point"}
}