{
  "type": "Feature",
  "properties": {
    "addr:full":"Carrer de Ferran Sorts, 4 Cambrils Tarragona 43850",
    "addr:housenumber":"4",
    "addr:postcode":"43850",
    "addr:street":"Carrer De Ferran Sorts",
    "iso:country":"ES",
    "sg:address":"Carrer de Ferran Sorts, 4",
    "sg:city":"Cambrils",
    "sg:orig_category":"Abogados",
    "sg:phone":"+34 977 36 23 48",
    "sg:postcode":"43850",
    "sg:province":"Tarragona",
    "wof:name":"Sole Marti Montserrat",
    "wof:placetype":"venue"
},
  "geometry": {"coordinates":[1.0584199429,41.0655212402],"type":"Point"}
}