{
  "type": "Feature",
  "properties": {
    "addr:full":"Calle de Obispo Covarrubias, 14 Zaragoza Zaragoza 50005",
    "addr:housenumber":"14",
    "addr:postcode":"50005",
    "addr:street":"Calle De Obispo Covarrubias",
    "iso:country":"ES",
    "sg:address":"Calle de Obispo Covarrubias, 14",
    "sg:city":"Zaragoza",
    "sg:orig_category":"Peluquer\u00cdas, Peluquer\u00cda Mixta",
    "sg:phone":"+34 976 56 94 36",
    "sg:postcode":"50005",
    "sg:province":"Zaragoza",
    "wof:name":"Gonzalez Andres Anunciacion",
    "wof:placetype":"venue"
},
  "geometry": {"coordinates":[-0.8990179896,41.646270752],"type":"Point"}
}