{
  "type": "Feature",
  "properties": {
    "iso:country":"ES",
    "sg:address":"Avda Cantabria, 5",
    "sg:city":"Burgos",
    "sg:orig_category":"Muebles, Minoristas",
    "sg:phone":"+34 947 20 07 95",
    "sg:postcode":"09006",
    "sg:province":"Burgos",
    "wof:name":"Uriarte Ota\u00f1o S. A.",
    "wof:placetype":"venue"
},
  "geometry": {"coordinates":[-3.6867260933,42.3442878723],"type":"Point"}
}