{
  "type": "Feature",
  "properties": {
    "addr:full":"Calle de General Luis Alarcon De La Lastra, 9 Sevilla Sevilla 41006",
    "addr:housenumber":"9",
    "addr:postcode":"41006",
    "addr:street":"Calle De General Luis Alarcon De La Lastra",
    "iso:country":"ES",
    "sg:address":"Calle de General Luis Alarcon De La Lastra, 9",
    "sg:city":"Sevilla",
    "sg:orig_category":"Plomeros",
    "sg:phone":"+34 954 51 33 16",
    "sg:postcode":"41006",
    "sg:province":"Sevilla",
    "wof:name":"Pineda Cardenas Jose",
    "wof:placetype":"venue"
},
  "geometry": {"coordinates":[-5.9514808655,37.3851776123],"type":"Point"}
}