{
  "type": "Feature",
  "properties": {
    "addr:full":"C/ Na Saurina D'enten\u00c7a, 25 Alcoi Alicante 03803",
    "addr:housenumber":"25",
    "addr:postcode":"03803",
    "addr:street":"C /;\u0327A",
    "iso:country":"ES",
    "sg:address":"C/ Na Saurina D'enten\u00c7a, 25",
    "sg:city":"Alcoi",
    "sg:orig_category":"Molduras, Junquillos, Listones Y Molduras Perforadas",
    "sg:phone":"+34 965 33 10 66",
    "sg:postcode":"03803",
    "sg:province":"Alicante",
    "wof:name":"Martinez Gonzalez Daniel",
    "wof:placetype":"venue"
},
  "geometry": {"coordinates":[-0.4804809988,38.7012138367],"type":"Point"}
}