{
  "type": "Feature",
  "properties": {
    "addr:full":"Calle de Nicanor Del Campo, 1 Luarca Asturias 33700",
    "addr:housenumber":"1",
    "addr:postcode":"33700",
    "addr:street":"Calle De Nicanor Del Campo",
    "iso:country":"ES",
    "sg:address":"Calle de Nicanor Del Campo, 1",
    "sg:city":"Luarca",
    "sg:orig_category":"Administraciones De Trabajo Y Empleo",
    "sg:phone":"+34 985 64 27 93",
    "sg:postcode":"33700",
    "sg:province":"Asturias",
    "wof:name":"Servicio Publico De Empleo Estatal-dron. Prov. Asturias",
    "wof:placetype":"venue"
},
  "geometry": {"coordinates":[-6.5363588333,43.5415992737],"type":"Point"}
}