{
  "type": "Feature",
  "properties": {
    "iso:country":"ES",
    "sg:address":"Alam Urquijo, 22",
    "sg:city":"Bilbao",
    "sg:orig_category":"Productores Recolectores, Venta Directa De Vinos",
    "sg:phone":"+34 944 10 62 54",
    "sg:postcode":"48008",
    "sg:province":"Vizcaya",
    "sg:website":"www.bodegaberroja.com",
    "wof:name":"Berroja S. L",
    "wof:placetype":"venue"
},
  "geometry": {"coordinates":[-2.9340629578,43.2597885132],"type":"Point"}
}