{
  "type": "Feature",
  "properties": {
    "iso:country":"ES",
    "sg:address":"El Bergal, Km. 0051,0",
    "sg:city":"S. Adrian",
    "sg:orig_category":"Mec\u00c1nico Del Autom\u00d3vil",
    "sg:phone":"+34 948 67 01 50",
    "sg:postcode":"31570",
    "sg:province":"Navarra",
    "wof:name":"Automoviles Amador S.l.",
    "wof:placetype":"venue"
},
  "geometry": {"coordinates":[-1.6760691404,42.6953926086],"type":"Point"}
}