{
  "type": "Feature",
  "properties": {
    "addr:full":"Rua Pe\u00d1a Trevinca, 16 Ourense Ourense 32005",
    "addr:housenumber":"16",
    "addr:postcode":"32005",
    "addr:street":"Rua Pen\u0303A Trevinca",
    "iso:country":"ES",
    "sg:address":"Rua Pe\u00d1a Trevinca, 16",
    "sg:city":"Ourense",
    "sg:orig_category":"Muebles, Minoristas",
    "sg:phone":"+34 988 22 94 18",
    "sg:postcode":"32005",
    "sg:province":"Ourense",
    "wof:name":"Robleda Prieto Elias",
    "wof:placetype":"venue"
},
  "geometry": {"coordinates":[-7.8612241745,42.3338165283],"type":"Point"}
}