{
  "type": "Feature",
  "properties": {
    "iso:country":"ES",
    "sg:address":"Rua Orense, 1",
    "sg:city":"Barco",
    "sg:orig_category":"Abogados",
    "sg:phone":"+34 988 32 23 12",
    "sg:postcode":"32300",
    "sg:province":"Ourense",
    "wof:name":"Gonzalez Santos Maria Jesus",
    "wof:placetype":"venue"
},
  "geometry": {"coordinates":[-6.9837059975,42.4104614258],"type":"Point"}
}