{
  "type": "Feature",
  "properties": {
    "iso:country":"ES",
    "sg:address":"Calle de Lasierra Purroy, 26",
    "sg:city":"Zaragoza",
    "sg:orig_category":"Promotores Constructores",
    "sg:phone":"+34 976 37 57 65",
    "sg:postcode":"50007",
    "sg:province":"Zaragoza",
    "wof:name":"Maquinaria De Construcciones Andrea S.l.",
    "wof:placetype":"venue"
},
  "geometry": {"coordinates":[-0.8844580054,41.6314125061],"type":"Point"}
}