{
  "type": "Feature",
  "properties": {
    "addr:full":"Calle de Rollo, 10 Madrid Madrid 28005",
    "addr:housenumber":"10",
    "addr:postcode":"madrid;28005",
    "addr:street":"Calle De Rollo",
    "iso:country":"ES",
    "sg:address":"Calle de Rollo, 10",
    "sg:city":"Madrid",
    "sg:orig_category":"Copas, Insignias, Trofeos",
    "sg:phone":"+34 915 48 08 61",
    "sg:postcode":"28005",
    "sg:province":"Madrid",
    "wof:name":"Fernandez Gonzalez Carlos",
    "wof:placetype":"venue"
},
  "geometry": {"coordinates":[-3.7117130756,40.4139938354],"type":"Point"}
}