{
  "type": "Feature",
  "properties": {
    "iso:country":"ES",
    "sg:address":"Calle de Aligustre, 34",
    "sg:city":"Madrid",
    "sg:orig_category":"Agencias Y Asesores De Publicidad",
    "sg:phone":"+34 913 14 75 73",
    "sg:postcode":"28039",
    "sg:province":"Madrid",
    "wof:name":"Cofabric S.l.",
    "wof:placetype":"venue"
},
  "geometry": {"coordinates":[-3.7046809196,40.4666748047],"type":"Point"}
}