{
  "type": "Feature",
  "properties": {
    "iso:country":"ES",
    "sg:address":"Pza. Reloj, 7",
    "sg:city":"Alca\u00f1ices",
    "sg:orig_category":"Pescader\u00cdas (al Por Menor)",
    "sg:phone":"+34 980 68 02 53",
    "sg:postcode":"49500",
    "sg:province":"Zamora",
    "wof:name":"Gonzalez Fernandez Domingo",
    "wof:placetype":"venue"
},
  "geometry": {"coordinates":[-6.3479428291,41.6985855103],"type":"Point"}
}