{
  "type": "Feature",
  "properties": {
    "addr:full":"Plaz Gaspar Esteva, 1 Motril Granada 18600",
    "addr:housenumber":"1",
    "addr:postcode":"18600",
    "addr:street":"Plaz Gaspar Esteva",
    "iso:country":"ES",
    "sg:address":"Plaz Gaspar Esteva, 1",
    "sg:city":"Motril",
    "sg:orig_category":"Empresas Portuarias",
    "sg:phone":"+34 958 83 38 80",
    "sg:postcode":"18600",
    "sg:province":"Granada",
    "wof:name":"Lopez Cabarrocas Camilo",
    "wof:placetype":"venue"
},
  "geometry": {"coordinates":[-3.518488884,36.7454223633],"type":"Point"}
}