{
  "type": "Feature",
  "properties": {
    "addr:full":"Calle de Jose Eguino, 2 Irun Guip\u00f9zcoa 20302",
    "addr:housenumber":"2",
    "addr:postcode":"20302",
    "addr:street":"Calle De Jose Eguino;Guipu\u0300Zcoa",
    "iso:country":"ES",
    "sg:address":"Calle de Jose Eguino, 2",
    "sg:city":"Irun",
    "sg:orig_category":"Cl\u00cdnicas Dentales",
    "sg:phone":"+34 943 02 07 22",
    "sg:postcode":"20302",
    "sg:province":"Guip\u00f9zcoa",
    "wof:name":"Centro Odontologico Binai S.l.",
    "wof:placetype":"venue"
},
  "geometry": {"coordinates":[-1.7956229448,43.3375740051],"type":"Point"}
}