{
  "type": "Feature",
  "properties": {
    "addr:full":"Rua Maria, 82 Ferrol La Coru\u00f1a 15402",
    "addr:housenumber":"82",
    "addr:postcode":"15402",
    "addr:street":"Rua Maria;La Corun\u0303A",
    "iso:country":"ES",
    "sg:address":"Rua Maria, 82",
    "sg:city":"Ferrol",
    "sg:orig_category":"Caf\u00c9s, Bares, Cervecer\u00cdas",
    "sg:phone":"+34 981 35 54 95",
    "sg:postcode":"15402",
    "sg:province":"La Coru\u00f1a",
    "wof:name":"Rico Freire Jaime",
    "wof:placetype":"venue"
},
  "geometry": {"coordinates":[-8.2334756851,43.4847450256],"type":"Point"}
}