{
  "type": "Feature",
  "properties": {
    "addr:full":"Calle de Servando Batanero, 12 Madrid Madrid 28017",
    "addr:housenumber":"12",
    "addr:postcode":"madrid;28017",
    "addr:street":"Calle De Servando Batanero",
    "iso:country":"ES",
    "sg:address":"Calle de Servando Batanero, 12",
    "sg:city":"Madrid",
    "sg:orig_category":"Electricidad: Instaladores",
    "sg:phone":"+34 914 07 38 54",
    "sg:postcode":"28017",
    "sg:province":"Madrid",
    "wof:name":"Nuevas Alternativas De Instalaciones S.l.",
    "wof:placetype":"venue"
},
  "geometry": {"coordinates":[-3.64914608,40.4292907715],"type":"Point"}
}