{
  "type": "Feature",
  "properties": {
    "iso:country":"ES",
    "sg:address":"Calle de Santa Ana, S/n",
    "sg:city":"Villanueva Reina",
    "sg:orig_category":"Asilos De Ancianos. Centros Privados",
    "sg:phone":"+34 953 54 82 17",
    "sg:postcode":"23730",
    "sg:province":"Ja\u00e9n",
    "wof:name":"Federacion De Organizaciones Andaluzas De Mayores",
    "wof:placetype":"venue"
},
  "geometry": {"coordinates":[-3.9200239182,38.0041503906],"type":"Point"}
}