{
  "type": "Feature",
  "properties": {
    "addr:full":"Calle de Venida De La Virgen, 32 Almonte Huelva 21730",
    "addr:housenumber":"32",
    "addr:postcode":"21730",
    "addr:street":"Calle De Venida De La Virgen",
    "iso:country":"ES",
    "sg:address":"Calle de Venida De La Virgen, 32",
    "sg:city":"Almonte",
    "sg:orig_category":"Cajas De Ahorro",
    "sg:phone":"+34 959 45 03 19",
    "sg:postcode":"21730",
    "sg:province":"Huelva",
    "wof:name":"Monte Piedad Caja De Ahorros De Huelva Y Sevilla",
    "wof:placetype":"venue"
},
  "geometry": {"coordinates":[-6.5166931152,37.2610588074],"type":"Point"}
}