{
  "type": "Feature",
  "properties": {
    "iso:country":"ES",
    "sg:address":"Calle de Iglesia, 14",
    "sg:city":"Cantiveros",
    "sg:orig_category":"Sanatorios M\u00c9dico",
    "sg:phone":"+34 920 32 41 68",
    "sg:postcode":"05211",
    "sg:province":"\u00c1vila",
    "wof:name":"Ayuntamiento De Cantiveros",
    "wof:placetype":"venue"
},
  "geometry": {"coordinates":[-4.9555101395,40.9514656067],"type":"Point"}
}