{
  "type": "Feature",
  "properties": {
    "iso:country":"ES",
    "sg:address":"Avda Palencia, 11",
    "sg:city":"Guardo",
    "sg:orig_category":"Panader\u00cdas, Panader\u00cdas",
    "sg:phone":"+34 979 85 11 20",
    "sg:postcode":"34880",
    "sg:province":"Palencia",
    "wof:name":"Gonzalez Mancebo Luis Angel",
    "wof:placetype":"venue"
},
  "geometry": {"coordinates":[-4.843419075,42.7870330811],"type":"Point"}
}