{
  "type": "Feature",
  "properties": {
    "iso:country":"ES",
    "sg:address":"Calle de Anastasio Nieto, 27",
    "sg:city":"Collado Villalba",
    "sg:orig_category":"Chapister\u00cda",
    "sg:phone":"+34 918 50 59 45",
    "sg:postcode":"28400",
    "sg:province":"Madrid",
    "wof:name":"Talleres Brymotor S.l.",
    "wof:placetype":"venue"
},
  "geometry": {"coordinates":[-4.0051031113,40.6381263733],"type":"Point"}
}