{
  "type": "Feature",
  "properties": {
    "addr:full":"Ctra. Carolina, Km. 0015,0 Vilches Ja\u00e9n 23220",
    "addr:postcode":"23220",
    "addr:street":"Ctra. Carolina Km. 0015,0;Jae\u0301N",
    "iso:country":"ES",
    "sg:address":"Ctra. Carolina, Km. 0015,0",
    "sg:city":"Vilches",
    "sg:orig_category":"Aceites Y Grasas Alimentarias (fabricaci\u00d3n, Al Por Mayor)",
    "sg:phone":"+34 953 63 11 93",
    "sg:postcode":"23220",
    "sg:province":"Ja\u00e9n",
    "wof:name":"Almazara Gonzalez Y Martinez S.l.",
    "wof:placetype":"venue"
},
  "geometry": {"coordinates":[-3.5158448219,38.2163352966],"type":"Point"}
}