{
  "type": "Feature",
  "properties": {
    "iso:country":"ES",
    "sg:address":"Avda Brillante (del), 154",
    "sg:city":"Cordoba",
    "sg:orig_category":"Guarder\u00cdas",
    "sg:phone":"+34 957 40 29 40",
    "sg:postcode":"14012",
    "sg:province":"C\u00f3rdoba",
    "wof:name":"Jardin De Infancia Los Globos S.l.",
    "wof:placetype":"venue"
},
  "geometry": {"coordinates":[-4.8013963699,37.9164657593],"type":"Point"}
}