{
  "type": "Feature",
  "properties": {
    "addr:full":"Calle de Jose Cortina (de), 9 Colmenar Oreja Madrid 28380",
    "addr:postcode":"28380",
    "addr:street":"Calle De Jose Cortina De",
    "iso:country":"ES",
    "sg:address":"Calle de Jose Cortina (de), 9",
    "sg:city":"Colmenar Oreja",
    "sg:orig_category":"Copas, Insignias, Trofeos",
    "sg:phone":"+34 918 94 33 04",
    "sg:postcode":"28380",
    "sg:province":"Madrid",
    "wof:name":"Olivas Carpio Jose Francisco",
    "wof:placetype":"venue"
},
  "geometry": {"coordinates":[-3.3887760639,40.1075592041],"type":"Point"}
}