{
  "type": "Feature",
  "properties": {
    "iso:country":"ES",
    "sg:address":"Carrer de Corts, 5",
    "sg:city":"Barcelona",
    "sg:orig_category":"Carnicer\u00cdas, Carnicer\u00cdas",
    "sg:phone":"+34 934 90 54 88",
    "sg:postcode":"08028",
    "sg:province":"Barcelona",
    "wof:name":"Carenzo Moncalvo Mariana",
    "wof:placetype":"venue"
},
  "geometry": {"coordinates":[2.1292479038,41.3840522766],"type":"Point"}
}