{
  "type": "Feature",
  "properties": {
    "addr:full":"Calle de Almagro, 28 Madrid Madrid 28010",
    "addr:housenumber":"28",
    "addr:postcode":"madrid;28010",
    "addr:street":"Calle De Almagro",
    "iso:country":"ES",
    "sg:address":"Calle de Almagro, 28",
    "sg:city":"Madrid",
    "sg:orig_category":"Asociaciones, Organismos Culturales Y Socioeducativos",
    "sg:phone":"+34 913 08 45 88",
    "sg:postcode":"28010",
    "sg:province":"Madrid",
    "wof:name":"Asociacion Mujeres En La Musica",
    "wof:placetype":"venue"
},
  "geometry": {"coordinates":[-3.6932446957,40.4299278259],"type":"Point"}
}