{
  "type": "Feature",
  "properties": {
    "addr:full":"Carrer de Muntaner, 439 Barcelona Barcelona 08021",
    "addr:housenumber":"439",
    "addr:postcode":"08021",
    "addr:street":"Carrer De Muntaner",
    "iso:country":"ES",
    "sg:address":"Carrer de Muntaner, 439",
    "sg:city":"Barcelona",
    "sg:orig_category":"M\u00c9dicos: Dermatolog\u00cda Y Venereolog\u00cda",
    "sg:phone":"+34 932 01 27 68",
    "sg:postcode":"08021",
    "sg:province":"Barcelona",
    "wof:name":"Ferrandiz Foraster Carlos",
    "wof:placetype":"venue"
},
  "geometry": {"coordinates":[2.1400110722,41.4010658264],"type":"Point"}
}