{
  "type": "Feature",
  "properties": {
    "addr:full":"Avda Coru\u00d1a (da), 386 Lugo Lugo 27003",
    "addr:housenumber":"386",
    "addr:postcode":"27003",
    "addr:street":"Avda Corun\u0303A Da",
    "iso:country":"ES",
    "sg:address":"Avda Coru\u00d1a (da), 386",
    "sg:city":"Lugo",
    "sg:orig_category":"Agentes, Concesionarios Y Sucursales De Veh\u00cdculos",
    "sg:phone":"+34 982 21 61 20",
    "sg:postcode":"27003",
    "sg:province":"Lugo",
    "wof:name":"Automocion Lucense S. A.",
    "wof:placetype":"venue"
},
  "geometry": {"coordinates":[-7.5688371658,43.027885437],"type":"Point"}
}