{
  "type": "Feature",
  "properties": {
    "iso:country":"ES",
    "sg:address":"Pase Castellana, 192",
    "sg:city":"Madrid",
    "sg:orig_category":"Arquitectos",
    "sg:phone":"+34 913 59 34 96",
    "sg:postcode":"28046",
    "sg:province":"Madrid",
    "wof:name":"Rico Laredo Francisco Javier",
    "wof:placetype":"venue"
},
  "geometry": {"coordinates":[-3.6888489723,40.4613380432],"type":"Point"}
}