{
  "type": "Feature",
  "properties": {
    "addr:full":"Calle de Ingeniero Torroja Y Miret, S/n Cordoba C\u00f3rdoba 14013",
    "addr:housenumber":"s",
    "addr:postcode":"14013",
    "addr:street":"Calle De Ingeniero Torroja Y Miret;/ N;Co\u0301Rdoba",
    "iso:country":"ES",
    "sg:address":"Calle de Ingeniero Torroja Y Miret, S/n",
    "sg:city":"Cordoba",
    "sg:classifiers":[
        {
            "category":"Manufacturing",
            "subcategory":"Building Materials",
            "type":"Manufacturing & Wholesale Goods"
        }
    ],
    "sg:phone":"+34 957 29 48 48",
    "sg:postcode":"14013",
    "sg:province":"C\u00f3rdoba",
    "sg:tags":[
        "de",
        "industrial",
        "alquiler"
    ],
    "wof:name":"Comercial Agrocor S.a.l.",
    "wof:placetype":"venue"
},
  "geometry": {"coordinates":[-4.7942290306,37.8540039062],"type":"Point"}
}