{
  "type": "Feature",
  "properties": {
    "iso:country":"ES",
    "sg:address":"Ctra Barcelona, 36",
    "sg:city":"Viladecans",
    "sg:orig_category":"Veh\u00cdculos De Ocasi\u00d3n",
    "sg:phone":"+34 936 58 51 88",
    "sg:postcode":"08840",
    "sg:province":"Barcelona",
    "wof:name":"Autoviladecans Motors S.l.",
    "wof:placetype":"venue"
},
  "geometry": {"coordinates":[2.0262799263,41.3205604553],"type":"Point"}
}