{
  "type": "Feature",
  "properties": {
    "iso:country":"ES",
    "sg:address":"Av Des Llauradors(p I Montecristo), 29",
    "sg:city":"S. Rafel Creu",
    "sg:orig_category":"Agencias De Viajes",
    "sg:phone":"+34 971 30 73 63",
    "sg:postcode":"07816",
    "sg:province":"Islas Baleares",
    "wof:name":"Viajes Sidetours S.a.",
    "wof:placetype":"venue"
},
  "geometry": {"coordinates":[1.3828419447,39.0397987366],"type":"Point"}
}