{
  "type": "Feature",
  "properties": {
    "iso:country":"ES",
    "sg:address":"Carrer de Padilla, 163",
    "sg:city":"Barcelona",
    "sg:orig_category":"Peluquer\u00cdas, Peluquer\u00cda Mixta",
    "sg:phone":"+34 932 45 00 81",
    "sg:postcode":"08013",
    "sg:province":"Barcelona",
    "wof:name":"Ariso Gallego Soledad",
    "wof:placetype":"venue"
},
  "geometry": {"coordinates":[2.184056282,41.4005088806],"type":"Point"}
}