{
  "type": "Feature",
  "properties": {
    "iso:country":"ES",
    "sg:address":"Avda Santiago, 58",
    "sg:city":"Vista Alegre",
    "sg:orig_category":"Estancos",
    "sg:phone":"+34 968 23 39 11",
    "sg:postcode":"30007",
    "sg:province":"Murcia",
    "wof:name":"Fernandez Torralba Josefa",
    "wof:placetype":"venue"
},
  "geometry": {"coordinates":[-1.1252169609,38.0006790161],"type":"Point"}
}