{
  "type": "Feature",
  "properties": {
    "iso:country":"ES",
    "sg:address":"Ptda Malgovern, 18",
    "sg:city":"Torres De Sanui",
    "sg:orig_category":"Material Y Suministros Para Horticultura, Arboricultura",
    "sg:phone":"+34 973 26 10 39",
    "sg:postcode":"25192",
    "sg:province":"Lleida",
    "wof:name":"Callarriba Agricola S.c.p.",
    "wof:placetype":"venue"
},
  "geometry": {"coordinates":[0.5482299924,41.6239509583],"type":"Point"}
}