{
  "type": "Feature",
  "properties": {
    "iso:country":"ES",
    "sg:address":"Calle de Ni\u00d1a (la), 57",
    "sg:city":"Arrecife",
    "sg:orig_category":"Electricidad: Instaladores",
    "sg:phone":"+34 928 80 09 98",
    "sg:postcode":"35500",
    "sg:province":"Las Palmas",
    "wof:name":"Electrica Morales S.l.u.",
    "wof:placetype":"venue"
},
  "geometry": {"coordinates":[-13.5603647232,28.9695606232],"type":"Point"}
}