{
  "type": "Feature",
  "properties": {
    "iso:country":"ES",
    "sg:address":"Av Xativa (de), 29",
    "sg:city":"Cocentaina",
    "sg:orig_category":"Cojinetes De Bolas, Agujas Y Rodillos (fabricaci\u00d3n, Al Por Mayor)",
    "sg:phone":"+34 965 59 13 62",
    "sg:postcode":"03820",
    "sg:province":"Alicante",
    "wof:name":"Fenollar S. L.",
    "wof:placetype":"venue"
},
  "geometry": {"coordinates":[-0.4393289983,38.748298645],"type":"Point"}
}