{
  "type": "Feature",
  "properties": {
    "addr:full":"Avda Rascacielos, 21 Bara\u00f1ain Navarra 31010",
    "addr:housenumber":"21",
    "addr:postcode":"31010",
    "addr:street":"Avda Rascacielos",
    "iso:country":"ES",
    "sg:address":"Avda Rascacielos, 21",
    "sg:city":"Bara\u00f1ain",
    "sg:orig_category":"Peluquer\u00cdas, Peluquer\u00cda Mixta",
    "sg:phone":"+34 948 18 58 89",
    "sg:postcode":"31010",
    "sg:province":"Navarra",
    "wof:name":"Apecechea Salaverria Maria Arritokieta",
    "wof:placetype":"venue"
},
  "geometry": {"coordinates":[-1.6852040291,42.8049812317],"type":"Point"}
}