{
  "type": "Feature",
  "properties": {
    "iso:country":"ES",
    "sg:address":"Calle de Puerto Del Ponton, 23",
    "sg:city":"Prado Overa",
    "sg:orig_category":"Armaduras De Hormig\u00d3n",
    "sg:phone":"+34 913 41 30 16",
    "sg:postcode":"28919",
    "sg:province":"Madrid",
    "wof:name":"Estructuras Esmima S.l.",
    "wof:placetype":"venue"
},
  "geometry": {"coordinates":[-3.7468049526,40.3435096741],"type":"Point"}
}