{
  "type": "Feature",
  "properties": {
    "iso:country":"ES",
    "sg:address":"Calle de Silvano, 77",
    "sg:city":"Madrid",
    "sg:orig_category":"Art\u00cdculos De Regalo (al Por Menor)",
    "sg:phone":"+34 913 00 41 24",
    "sg:postcode":"28043",
    "sg:province":"Madrid",
    "sg:website":"www.tierranatural.com",
    "wof:name":"Yolman Y Asociados S.l.",
    "wof:placetype":"venue"
},
  "geometry": {"coordinates":[-3.6377625465,40.4627151489],"type":"Point"}
}