{
  "type": "Feature",
  "properties": {
    "addr:full":"Calle de Rio Chico, 36 Norias De Daza Almer\u00eda 04716",
    "addr:housenumber":"36",
    "addr:postcode":"04716",
    "addr:street":"Calle De Rio Chico;Almeri\u0301A",
    "iso:country":"ES",
    "sg:address":"Calle de Rio Chico, 36",
    "sg:city":"Norias De Daza",
    "sg:orig_category":"Molduras, Junquillos, Listones Y Molduras Perforadas",
    "sg:phone":"+34 950 58 72 87",
    "sg:postcode":"04716",
    "sg:province":"Almer\u00eda",
    "wof:name":"Bolzon  Eduardo",
    "wof:placetype":"venue"
},
  "geometry": {"coordinates":[-2.7523419857,36.758895874],"type":"Point"}
}