{
  "type": "Feature",
  "properties": {
    "addr:full":"Ctra Quintanar-alc., 25 Miguel Esteban Toledo 45830",
    "addr:housenumber":"25",
    "addr:postcode":"45830",
    "addr:street":"Ctra Quintanar-Alc.;Miguel Esteban",
    "iso:country":"ES",
    "sg:address":"Ctra Quintanar-alc., 25",
    "sg:city":"Miguel Esteban",
    "sg:orig_category":"Comercio, Reparaci\u00d3n De Motocicletas, Bicicletas Y Piezas Sueltas",
    "sg:phone":"+34 925 17 26 61",
    "sg:postcode":"45830",
    "sg:province":"Toledo",
    "wof:name":"Venta Y Reparaciones Pinto S.l.",
    "wof:placetype":"venue"
},
  "geometry": {"coordinates":[-3.0778141022,39.5287094116],"type":"Point"}
}