{
  "type": "Feature",
  "properties": {
    "iso:country":"ES",
    "sg:address":"Calle de Silicio, 48",
    "sg:city":"Torrejon Ardoz",
    "sg:orig_category":"Fabricaci\u00d3n, Alquiler, Venta De Encofrados",
    "sg:phone":"+34 916 77 11 26",
    "sg:postcode":"28850",
    "sg:province":"Madrid",
    "wof:name":"Unetra Systems Iberica S.l.",
    "wof:placetype":"venue"
},
  "geometry": {"coordinates":[-3.461771965,40.4478721619],"type":"Point"}
}