{
  "type": "Feature",
  "properties": {
    "iso:country":"ES",
    "sg:address":"Rtda Mas Gri, 8",
    "sg:city":"Girona",
    "sg:orig_category":"Inform\u00c1tica, Ofim\u00c1tica (estudios, Asesor\u00cda, Ingenier\u00cda, Formaci\u00d3n)",
    "sg:phone":"+34 972 42 60 92",
    "sg:postcode":"17003",
    "sg:province":"Girona",
    "wof:name":"Media Markt Girona Video-tv-elektro-computer-foto S.a.u.",
    "wof:placetype":"venue"
},
  "geometry": {"coordinates":[2.810477972,41.9609642029],"type":"Point"}
}