{
  "type": "Feature",
  "properties": {
    "addr:full":"Av Granvia, 159 Hospitalet Llobregat Barcelona 08...",
    "addr:housenumber":"159",
    "addr:street":"Av Granvia",
    "iso:country":"ES",
    "sg:address":"Av Granvia, 159",
    "sg:city":"Hospitalet Llobregat",
    "sg:orig_category":"Automatizaci\u00d3n De Procesos Industriales Y De Edificaci\u00d3n (estudios, Instalaci\u00d3n)",
    "sg:phone":"+34 932 61 64 00",
    "sg:postcode":"08...",
    "sg:province":"Barcelona",
    "wof:name":"Festo-pneumatic S.a.",
    "wof:placetype":"venue"
},
  "geometry": {"coordinates":[2.1186089516,41.3514099121],"type":"Point"}
}