{
  "type": "Feature",
  "properties": {
    "iso:country":"ES",
    "sg:address":"Avda Fabian Escribano, 13",
    "sg:city":"Beniajan",
    "sg:orig_category":"Cajas De Ahorro",
    "sg:phone":"+34 968 87 50 70",
    "sg:postcode":"30570",
    "sg:province":"Murcia",
    "wof:name":"Caja De Ahorros De Murcia",
    "wof:placetype":"venue"
},
  "geometry": {"coordinates":[-1.0718200207,37.9759292603],"type":"Point"}
}