{
  "type": "Feature",
  "properties": {
    "iso:country":"ES",
    "sg:address":"Carrer de Cano Antoni Sancho, 32",
    "sg:city":"Palma",
    "sg:orig_category":"Molduras, Junquillos, Listones Y Molduras Perforadas",
    "sg:phone":"+34 971 47 05 21",
    "sg:postcode":"07009",
    "sg:province":"Islas Baleares",
    "wof:name":"Pastor Carmona Maria Belen",
    "wof:placetype":"venue"
},
  "geometry": {"coordinates":[2.6784338951,39.5971565247],"type":"Point"}
}