{
  "type": "Feature",
  "properties": {
    "addr:full":"Crta. Vva. Cordoba, S/n Pozoblanco C\u00f3rdoba 14400",
    "addr:housenumber":"s / n",
    "addr:postcode":"14400",
    "addr:street":"Crta. Vva. Cordoba",
    "iso:country":"ES",
    "sg:address":"Crta. Vva. Cordoba, S/n",
    "sg:city":"Pozoblanco",
    "sg:orig_category":"Producci\u00d3n, Venta De Productos De Agricultura Biol\u00d3gica",
    "sg:phone":"+34 957 33 90 14",
    "sg:postcode":"14400",
    "sg:province":"C\u00f3rdoba",
    "wof:name":"Ortega Mu\u00f1oz Juana",
    "wof:placetype":"venue"
},
  "geometry": {"coordinates":[-4.8492288589,38.3810462952],"type":"Point"}
}