{
  "type": "Feature",
  "properties": {
    "iso:country":"ES",
    "sg:address":"Carrer de Sant Quirze, 55",
    "sg:city":"Sabadell",
    "sg:orig_category":"Reparaci\u00d3n Y Restauraci\u00d3n De Objetos Diversos",
    "sg:phone":"+34 937 25 66 53",
    "sg:postcode":"08201",
    "sg:province":"Barcelona",
    "wof:name":"Bonet Rebollo Isabel",
    "wof:placetype":"venue"
},
  "geometry": {"coordinates":[2.1058950424,41.5461807251],"type":"Point"}
}