{
  "type": "Feature",
  "properties": {
    "addr:full":"Avda Menendez Y Pelayo, 9 Valencia Valencia 46010",
    "addr:housenumber":"9",
    "addr:postcode":"46010",
    "addr:street":"Avda Menendez Y Pelayo",
    "iso:country":"ES",
    "sg:address":"Avda Menendez Y Pelayo, 9",
    "sg:city":"Valencia",
    "sg:orig_category":"Ingenier\u00cda, Centros De Estudios (diversos)",
    "sg:phone":"+34 963 61 29 94",
    "sg:postcode":"46010",
    "sg:province":"Valencia",
    "wof:name":"Bayo Villuendas Angel",
    "wof:placetype":"venue"
},
  "geometry": {"coordinates":[-0.3618429899,39.4797477722],"type":"Point"}
}