{
  "type": "Feature",
  "properties": {
    "addr:full":"Carrer de Creus, 17 Sant Feliu Llobregat Barcelona 08980",
    "addr:housenumber":"17",
    "addr:postcode":"08980",
    "addr:street":"Carrer De Creus",
    "iso:country":"ES",
    "sg:address":"Carrer de Creus, 17",
    "sg:city":"Sant Feliu Llobregat",
    "sg:orig_category":"Comercio, Reparaci\u00d3n De Bicicletas, De Motocicletas, De Accesorios",
    "sg:phone":"+34 936 66 58 04",
    "sg:postcode":"08980",
    "sg:province":"Barcelona",
    "wof:name":"Pujol Barcons Montserrat",
    "wof:placetype":"venue"
},
  "geometry": {"coordinates":[2.0442409515,41.3823890686],"type":"Point"}
}