{
  "type": "Feature",
  "properties": {
    "addr:full":"Avda Club Deportivo, 70 Logro\u00f1o La Rioja 26007",
    "addr:housenumber":"70",
    "addr:postcode":"26007",
    "addr:street":"Avda Club Deportivo;Rioja",
    "iso:country":"ES",
    "sg:address":"Avda Club Deportivo, 70",
    "sg:city":"Logro\u00f1o",
    "sg:orig_category":"Asociaciones Humanitarias, De Cooperaci\u00d3n, De Acci\u00d3n Social",
    "sg:phone":"+34 941 51 03 51",
    "sg:postcode":"26007",
    "sg:province":"La Rioja",
    "wof:name":"Emma Saenz Barrena Y Otra S.cv",
    "wof:placetype":"venue"
},
  "geometry": {"coordinates":[-2.4604370594,42.4580421448],"type":"Point"}
}