{
  "type": "Feature",
  "properties": {
    "addr:full":"Calle de Aldapeta, 5 Irun Guip\u00f9zcoa 20303",
    "addr:housenumber":"5",
    "addr:postcode":"20303",
    "addr:street":"Calle De Aldapeta;Guipu\u0300Zcoa",
    "iso:country":"ES",
    "sg:address":"Calle de Aldapeta, 5",
    "sg:city":"Irun",
    "sg:orig_category":"Electricidad: Instaladores",
    "sg:phone":"+34 943 63 03 96",
    "sg:postcode":"20303",
    "sg:province":"Guip\u00f9zcoa",
    "wof:name":"Arzak Barrasa Jose Manuel",
    "wof:placetype":"venue"
},
  "geometry": {"coordinates":[-1.7918561697,43.3390922546],"type":"Point"}
}