{
  "type": "Feature",
  "properties": {
    "iso:country":"ES",
    "sg:address":"Calle de Rollo, S/n",
    "sg:city":"Aldea Rey",
    "sg:orig_category":"Asociaciones Y Clubs Deportivos",
    "sg:phone":"+34 926 69 20 03",
    "sg:postcode":"13380",
    "sg:province":"Ciudad Real",
    "wof:name":"Comercial Navalonguilla C.b.",
    "wof:placetype":"venue"
},
  "geometry": {"coordinates":[-3.8448619843,38.7306976318],"type":"Point"}
}