{
  "type": "Feature",
  "properties": {
    "addr:full":"Calle de Antioco, 7 Ceuta Ceuta 51001",
    "addr:housenumber":"7",
    "addr:postcode":"51001",
    "addr:street":"Calle De Antioco",
    "iso:country":"ES",
    "sg:address":"Calle de Antioco, 7",
    "sg:city":"Ceuta",
    "sg:orig_category":"Empresas De Carpinter\u00cda Met\u00c1lica",
    "sg:phone":"+34 956 51 30 63",
    "sg:postcode":"51001",
    "sg:province":"Ceuta",
    "wof:name":"H.taboada S.a.",
    "wof:placetype":"venue"
},
  "geometry": {"coordinates":[-5.3102684021,35.8879928589],"type":"Point"}
}