{
  "type": "Feature",
  "properties": {
    "addr:full":"Carrer de Bilbao, 163 Barcelona Barcelona 08018",
    "addr:housenumber":"163",
    "addr:postcode":"08018",
    "addr:street":"Carrer De Bilbao",
    "iso:country":"ES",
    "sg:address":"Carrer de Bilbao, 163",
    "sg:city":"Barcelona",
    "sg:orig_category":"Promotores Constructores",
    "sg:phone":"+34 933 03 35 62",
    "sg:postcode":"08018",
    "sg:province":"Barcelona",
    "wof:name":"Mulco S.a.",
    "wof:placetype":"venue"
},
  "geometry": {"coordinates":[2.1969740391,41.4075584412],"type":"Point"}
}