{
  "type": "Feature",
  "properties": {
    "iso:country":"ES",
    "sg:address":"Pol Ind San Jorge, 3",
    "sg:city":"Torres Cotillas",
    "sg:orig_category":"Imprenta",
    "sg:phone":"+34 968 62 51 23",
    "sg:postcode":"30565",
    "sg:province":"Murcia",
    "wof:name":"Graficas Sanchez Asensio S.l.",
    "wof:placetype":"venue"
},
  "geometry": {"coordinates":[-1.2395490408,38.0263290405],"type":"Point"}
}