{
  "type": "Feature",
  "properties": {
    "addr:full":"Pl. Esglesia, S/n Ardevol Lleida 25287",
    "addr:housenumber":"s / n",
    "addr:postcode":"25287",
    "addr:street":"Pl. Esglesia",
    "iso:country":"ES",
    "sg:address":"Pl. Esglesia, S/n",
    "sg:city":"Ardevol",
    "sg:orig_category":"Iglesia Cat\u00d3lica",
    "sg:phone":"+34 973 47 30 10",
    "sg:postcode":"25287",
    "sg:province":"Lleida",
    "wof:name":"Bisbat De Solsona",
    "wof:placetype":"venue"
},
  "geometry": {"coordinates":[1.541105032,41.827419281],"type":"Point"}
}