{
  "type": "Feature",
  "properties": {
    "addr:full":"Calle de Villafranca, 4 Le\u00f3n Le\u00f3n 24001",
    "addr:housenumber":"4",
    "addr:postcode":"24001",
    "addr:street":"Calle De Villafranca;Leo\u0301N",
    "iso:country":"ES",
    "sg:address":"Calle de Villafranca, 4",
    "sg:city":"Le\u00f3n",
    "sg:orig_category":"Abogados",
    "sg:phone":"+34 987 21 04 59",
    "sg:postcode":"24001",
    "sg:province":"Le\u00f3n",
    "wof:name":"Alcoba Rodriguez Maria Carmen",
    "wof:placetype":"venue"
},
  "geometry": {"coordinates":[-5.5758953094,42.5963935852],"type":"Point"}
}