{
  "type": "Feature",
  "properties": {
    "addr:full":"Calle de San Francisco, 51 Villamartin C\u00e1diz 11650",
    "addr:housenumber":"51",
    "addr:postcode":"11650",
    "addr:street":"Calle De San Francisco;Ca\u0301Diz",
    "iso:country":"ES",
    "sg:address":"Calle de San Francisco, 51",
    "sg:city":"Villamartin",
    "sg:orig_category":"M\u00c1quinas De Coser Y De Hacer Punto (al Por Mayor)",
    "sg:phone":"+34 956 73 01 58",
    "sg:postcode":"11650",
    "sg:province":"C\u00e1diz",
    "wof:name":"Sanchez Barroso Andres",
    "wof:placetype":"venue"
},
  "geometry": {"coordinates":[-5.6407899857,36.8588294983],"type":"Point"}
}