{
  "type": "Feature",
  "properties": {
    "iso:country":"ES",
    "sg:address":"Calle de San Fernando, 7",
    "sg:city":"Quintanar Orden",
    "sg:orig_category":"Mercer\u00cda, Lencer\u00cda (al Por Menor)",
    "sg:phone":"+34 925 18 03 80",
    "sg:postcode":"45800",
    "sg:province":"Toledo",
    "wof:name":"Moreno Ramirez Miguel",
    "wof:placetype":"venue"
},
  "geometry": {"coordinates":[-3.0446720123,39.5917434692],"type":"Point"}
}