{
  "type": "Feature",
  "properties": {
    "addr:full":"Avda Majuelo (del), 22 Valdemoro Madrid 28340",
    "addr:housenumber":"22",
    "addr:postcode":"28340",
    "addr:street":"Avda Majuelo Del",
    "iso:country":"ES",
    "sg:address":"Avda Majuelo (del), 22",
    "sg:city":"Valdemoro",
    "sg:orig_category":"Fabricaci\u00d3n, Venta, Instalaci\u00d3n De R\u00d3tulos, De R\u00d3tulos Luminosos",
    "sg:phone":"+34 917 76 08 55",
    "sg:postcode":"28340",
    "sg:province":"Madrid",
    "wof:name":"Jm Rotulacion S.l.",
    "wof:placetype":"venue"
},
  "geometry": {"coordinates":[-3.6780900955,40.2083625793],"type":"Point"}
}