{
  "type": "Feature",
  "properties": {
    "addr:full":"Calle de Crevillente, 3 Valencia Valencia 46022",
    "addr:housenumber":"3",
    "addr:postcode":"46022",
    "addr:street":"Calle De Crevillente",
    "iso:country":"ES",
    "sg:address":"Calle de Crevillente, 3",
    "sg:city":"Valencia",
    "sg:orig_category":"Mec\u00c1nico Del Autom\u00d3vil",
    "sg:phone":"+34 963 71 90 29",
    "sg:postcode":"46022",
    "sg:province":"Valencia",
    "wof:name":"Tarin Sotomayor Enrique",
    "wof:placetype":"venue"
},
  "geometry": {"coordinates":[-0.3402073979,39.468296051],"type":"Point"}
}