{
  "type": "Feature",
  "properties": {
    "iso:country":"ES",
    "sg:address":"Avda Historiador Vicente Ramos, 3",
    "sg:city":"Alacant",
    "sg:orig_category":"\u00d3ptica: Instrumentos (fabricaci\u00d3n)",
    "sg:phone":"+34 965 15 72 40",
    "sg:postcode":"03540",
    "sg:province":"Alicante",
    "wof:name":"Prieto Hernandez Francisco",
    "wof:placetype":"venue"
},
  "geometry": {"coordinates":[-0.4310359955,38.3648338318],"type":"Point"}
}