{
  "type": "Feature",
  "properties": {
    "addr:full":"Avda Madrid (de), 22 Alcala Henares Madrid 28802",
    "addr:housenumber":"22",
    "addr:postcode":"28802",
    "addr:street":"Avda Madrid De",
    "iso:country":"ES",
    "sg:address":"Avda Madrid (de), 22",
    "sg:city":"Alcala Henares",
    "sg:orig_category":"Electricidad: Instaladores",
    "sg:phone":"+34 918 80 40 63",
    "sg:postcode":"28802",
    "sg:province":"Madrid",
    "wof:name":"Instalaciones Y Tecnologias Electronicas S.a.",
    "wof:placetype":"venue"
},
  "geometry": {"coordinates":[-3.3746519089,40.480594635],"type":"Point"}
}