{
  "type": "Feature",
  "properties": {
    "addr:full":"Calle de Italia, 30 Alacant Alicante 03003",
    "addr:housenumber":"30",
    "addr:postcode":"03003",
    "addr:street":"Calle De Italia",
    "iso:country":"ES",
    "sg:address":"Calle de Italia, 30",
    "sg:city":"Alacant",
    "sg:orig_category":"Bancos",
    "sg:phone":"+34 965 13 34 80",
    "sg:postcode":"03003",
    "sg:province":"Alicante",
    "wof:name":"Banco De Valencia S.a.",
    "wof:placetype":"venue"
},
  "geometry": {"coordinates":[-0.4926120043,38.3399543762],"type":"Point"}
}