{
  "type": "Feature",
  "properties": {
    "iso:country":"ES",
    "sg:address":"Carr Pins, 8",
    "sg:city":"Port D'alcudia",
    "sg:orig_category":"Inmobiliaria (agencias)",
    "sg:phone":"+34 971 54 84 45",
    "sg:postcode":"07410",
    "sg:province":"Islas Baleares",
    "sg:website":"www.confortrentals.com",
    "wof:name":"Inmobiliaria Mallorca Comfort Rentals S.l.",
    "wof:placetype":"venue"
},
  "geometry": {"coordinates":[3.1233201027,39.8516082764],"type":"Point"}
}