{
  "type": "Feature",
  "properties": {
    "addr:full":"Cinco-guadalmina Baja, S/n San Pedro Alcantara M\u00e1laga 29670",
    "addr:housenumber":"/ n",
    "addr:postcode":"29670",
    "addr:street":"S",
    "iso:country":"ES",
    "sg:address":"Cinco-guadalmina Baja, S/n",
    "sg:city":"San Pedro Alcantara",
    "sg:orig_category":"Inversiones",
    "sg:phone":"+34 952 88 54 55",
    "sg:postcode":"29670",
    "sg:province":"M\u00e1laga",
    "wof:name":"Malora De Actividasdes E Inversiones S.l.",
    "wof:placetype":"venue"
},
  "geometry": {"coordinates":[-5.003718853,36.4735946655],"type":"Point"}
}