{
  "type": "Feature",
  "properties": {
    "addr:full":"Plaz San Jeronimo Hermosilla, 12 Santo Domingo De La Calzada La Rioja 26250",
    "addr:housenumber":"12",
    "addr:postcode":"26250",
    "addr:street":"Plaz;Hermosilla;Rioja",
    "iso:country":"ES",
    "sg:address":"Plaz San Jeronimo Hermosilla, 12",
    "sg:city":"Santo Domingo De La Calzada",
    "sg:orig_category":"Transporte En General",
    "sg:phone":"+34 941 34 06 06",
    "sg:postcode":"26250",
    "sg:province":"La Rioja",
    "wof:name":"Miquel Alimentacio Grup S.a.",
    "wof:placetype":"venue"
},
  "geometry": {"coordinates":[-2.9540081024,42.4379844666],"type":"Point"}
}