{
  "type": "Feature",
  "properties": {
    "addr:full":"Calle de Danubio, 79 Jerez De La Frontera C\u00e1diz 11406",
    "addr:housenumber":"79",
    "addr:postcode":"11406",
    "addr:street":"Calle De Danubio",
    "iso:country":"ES",
    "sg:address":"Calle de Danubio, 79",
    "sg:city":"Jerez De La Frontera",
    "sg:orig_category":"Centros Empresariales",
    "sg:phone":"+34 956 33 38 66",
    "sg:postcode":"11406",
    "sg:province":"C\u00e1diz",
    "wof:name":"Safratex Sl",
    "wof:placetype":"venue"
},
  "geometry": {"coordinates":[-6.1094589233,36.6883773804],"type":"Point"}
}