{
  "type": "Feature",
  "properties": {
    "iso:country":"ES",
    "sg:address":"Carr Confraria De L'assumpcio (de La), 8",
    "sg:city":"Gandia",
    "sg:orig_category":"Agencias De Viajes",
    "sg:phone":"+34 962 95 02 56",
    "sg:postcode":"46700",
    "sg:province":"Valencia",
    "wof:name":"Gandia Turistic S.l.",
    "wof:placetype":"venue"
},
  "geometry": {"coordinates":[-0.1807609946,38.9668388367],"type":"Point"}
}