{
  "type": "Feature",
  "properties": {
    "addr:full":"Calle de Anibal, 2 Madrid Madrid 28020",
    "addr:housenumber":"2",
    "addr:postcode":"28020",
    "addr:street":"Calle De Anibal",
    "iso:country":"ES",
    "sg:address":"Calle de Anibal, 2",
    "sg:city":"Madrid",
    "sg:orig_category":"Centros Comerciales Y Grandes Tiendas",
    "sg:phone":"+34 914 25 02 99",
    "sg:postcode":"28020",
    "sg:province":"Madrid",
    "sg:website":"www.conarte.arrkis.es",
    "wof:name":"Pinedo Gascon Soledad",
    "wof:placetype":"venue"
},
  "geometry": {"coordinates":[-3.6939179897,40.4648590088],"type":"Point"}
}