{
  "type": "Feature",
  "properties": {
    "addr:full":"Calle de Ferraz, 49 Madrid Madrid 28008",
    "addr:housenumber":"49",
    "addr:postcode":"madrid;28008",
    "addr:street":"Calle De Ferraz",
    "iso:country":"ES",
    "sg:address":"Calle de Ferraz, 49",
    "sg:city":"Madrid",
    "sg:orig_category":"Centros Empresariales",
    "sg:phone":"+34 915 42 29 45",
    "sg:postcode":"28008",
    "sg:province":"Madrid",
    "wof:name":"Clinica Beltran Carrillo S.l.",
    "wof:placetype":"venue"
},
  "geometry": {"coordinates":[-3.7207829952,40.4295082092],"type":"Point"}
}