{
  "type": "Feature",
  "properties": {
    "iso:country":"ES",
    "sg:address":"Ctra Catral, Km. 0000,5",
    "sg:city":"Crevillente",
    "sg:orig_category":"Material Y Herramientas Agr\u00cdcolas",
    "sg:phone":"+34 965 40 17 12",
    "sg:postcode":"03330",
    "sg:province":"Alicante",
    "wof:name":"Monosembradora S.a.",
    "wof:placetype":"venue"
},
  "geometry": {"coordinates":[-0.8052690029,38.2463111877],"type":"Point"}
}