{
  "type": "Feature",
  "properties": {
    "iso:country":"ES",
    "sg:address":"Rda. Comunicacion, 20",
    "sg:city":"Madrid",
    "sg:orig_category":"Electricidad: Instaladores",
    "sg:phone":"+34 917 36 21 33",
    "sg:postcode":"28050",
    "sg:province":"Madrid",
    "wof:name":"Instalaciones Electricas Ciudad De Las Comunicaciones Cobra Espelsa",
    "wof:placetype":"venue"
},
  "geometry": {"coordinates":[-3.6605689526,40.5146255493],"type":"Point"}
}