{
  "type": "Feature",
  "properties": {
    "iso:country":"ES",
    "sg:address":"Calle de Barcelona, 10",
    "sg:city":"Carreras",
    "sg:orig_category":"Tapicer\u00cdas",
    "sg:phone":"+34 928 61 29 98",
    "sg:postcode":"35420",
    "sg:province":"Las Palmas",
    "wof:name":"Garcia Rodriguez Santiago",
    "wof:placetype":"venue"
},
  "geometry": {"coordinates":[-15.5840749741,28.115776062],"type":"Point"}
}