{
  "type": "Feature",
  "properties": {
    "iso:country":"ES",
    "sg:address":"Plaz Castilla Y Leon, 1",
    "sg:city":"Valladolid",
    "sg:orig_category":"Ense\u00d1anza Variada",
    "sg:phone":"+34 983 24 42 40",
    "sg:postcode":"47008",
    "sg:province":"Valladolid",
    "wof:name":"Cesna Producciones Audiovisuales S.l.",
    "wof:placetype":"venue"
},
  "geometry": {"coordinates":[-4.7516889572,41.6105194092],"type":"Point"}
}