{
  "type": "Feature",
  "properties": {
    "addr:full":"Ctra. Industrial, S/n Cadiz C\u00e1diz 11006",
    "addr:housenumber":"/ n",
    "addr:postcode":"11006",
    "addr:street":"Ctra. Industrial S",
    "iso:country":"ES",
    "sg:address":"Ctra. Industrial, S/n",
    "sg:city":"Cadiz",
    "sg:orig_category":"Agencias De Viajes",
    "sg:phone":"+34 956 20 55 50",
    "sg:postcode":"11006",
    "sg:province":"C\u00e1diz",
    "sg:website":"www.halconviajes.com",
    "wof:name":"Viajes Halcon S.a.",
    "wof:placetype":"venue"
},
  "geometry": {"coordinates":[-6.2902388573,36.5298614502],"type":"Point"}
}