{
  "type": "Feature",
  "properties": {
    "addr:full":"Avda Concepcion Arenal, S/n Praia Pontevedra 36950",
    "addr:housenumber":"s / n",
    "addr:postcode":"36950",
    "addr:street":"Avda Concepcion Arenal",
    "iso:country":"ES",
    "sg:address":"Avda Concepcion Arenal, S/n",
    "sg:city":"Praia",
    "sg:orig_category":"Estudios Y Construcci\u00d3n De Acuarios Y Viveros",
    "sg:phone":"+34 986 31 27 09",
    "sg:postcode":"36950",
    "sg:province":"Pontevedra",
    "wof:name":"Asociacion De Mejilloneros Ria De Vigo",
    "wof:placetype":"venue"
},
  "geometry": {"coordinates":[-8.6480531693,42.4336204529],"type":"Point"}
}