{
  "type": "Feature",
  "properties": {
    "iso:country":"ES",
    "sg:address":"Plaz San Jose, S/n",
    "sg:city":"Cadiz",
    "sg:orig_category":"Iglesia Cat\u00d3lica",
    "sg:phone":"+34 956 25 13 24",
    "sg:postcode":"11008",
    "sg:province":"C\u00e1diz",
    "wof:name":"Plazadesanjose",
    "wof:placetype":"venue"
},
  "geometry": {"coordinates":[-6.2811141014,36.5136451721],"type":"Point"}
}