{
  "type": "Feature",
  "properties": {
    "iso:country":"ES",
    "sg:address":"Calle de Indautxu, 3",
    "sg:city":"Bilbao",
    "sg:orig_category":"Ense\u00d1anza: Profesiones Art\u00cdsticas",
    "sg:phone":"+34 944 41 40 86",
    "sg:postcode":"48011",
    "sg:province":"Vizcaya",
    "wof:name":"Recio Morales Angel",
    "wof:placetype":"venue"
},
  "geometry": {"coordinates":[-2.9406399727,43.2613983154],"type":"Point"}
}