{
  "type": "Feature",
  "properties": {
    "addr:full":"Carretera De La Haba, S/n Villanueva Serena Badajoz 06700",
    "addr:housenumber":"s",
    "addr:postcode":"06700",
    "addr:street":"Carretera De La Haba;/ N Villanueva Serena",
    "iso:country":"ES",
    "sg:address":"Carretera De La Haba, S/n",
    "sg:city":"Villanueva Serena",
    "sg:orig_category":"Promotores Constructores",
    "sg:phone":"+34 924 84 91 77",
    "sg:postcode":"06700",
    "sg:province":"Badajoz",
    "wof:name":"Obras Y Construcciones Eusebio Gallego S.a.",
    "wof:placetype":"venue"
},
  "geometry": {"coordinates":[-5.7927408218,38.9731750488],"type":"Point"}
}