{
  "type": "Feature",
  "properties": {
    "iso:country":"ES",
    "sg:address":"Carr Pablo Iglesias, 54",
    "sg:city":"Burjassot",
    "sg:orig_category":"Empresas De Limpieza",
    "sg:phone":"+34 963 64 64 25",
    "sg:postcode":"46100",
    "sg:province":"Valencia",
    "wof:name":"Euroservicios De Valencia S.l.",
    "wof:placetype":"venue"
},
  "geometry": {"coordinates":[-0.4142400026,39.5111808777],"type":"Point"}
}