{
  "type": "Feature",
  "properties": {
    "addr:full":"Calle de Barbacana, S/n Due\u00f1as Palencia 34210",
    "addr:housenumber":"s",
    "addr:postcode":"34210",
    "addr:street":"Calle De Barbacana;/ N",
    "iso:country":"ES",
    "sg:address":"Calle de Barbacana, S/n",
    "sg:city":"Due\u00f1as",
    "sg:orig_category":"Centros De Educaci\u00d3n Especial",
    "sg:phone":"+34 979 78 00 95",
    "sg:postcode":"34210",
    "sg:province":"Palencia",
    "wof:name":"Grupo Escolar Reyes Catolicos",
    "wof:placetype":"venue"
},
  "geometry": {"coordinates":[-4.5490765572,41.8768005371],"type":"Point"}
}