{
  "type": "Feature",
  "properties": {
    "iso:country":"ES",
    "sg:address":"Cmno Ronda (de), 22",
    "sg:city":"Granada",
    "sg:orig_category":"Electrodom\u00c9sticos (al Por Menor)",
    "sg:phone":"+34 958 81 52 61",
    "sg:postcode":"18006",
    "sg:province":"Granada",
    "wof:name":"Ogaban Valero Rafael",
    "wof:placetype":"venue"
},
  "geometry": {"coordinates":[-3.6028280258,37.1654815674],"type":"Point"}
}