{
  "type": "Feature",
  "properties": {
    "addr:full":"Calle de Sangenis, 37 Zaragoza Zaragoza 50010",
    "addr:housenumber":"37",
    "addr:postcode":"50010",
    "addr:street":"Calle De Sangenis",
    "iso:country":"ES",
    "sg:address":"Calle de Sangenis, 37",
    "sg:city":"Zaragoza",
    "sg:orig_category":"Peluqueros: De Se\u00d1oras",
    "sg:phone":"+34 976 34 66 43",
    "sg:postcode":"50010",
    "sg:province":"Zaragoza",
    "wof:name":"Tirado Casteillro Veronica",
    "wof:placetype":"venue"
},
  "geometry": {"coordinates":[-0.9034579992,41.6507720947],"type":"Point"}
}