{
  "type": "Feature",
  "properties": {
    "addr:full":"Calle de Montes De Toledo (de Los), 4 Poligono De San Fernando De Henares Madrid 28830",
    "addr:housenumber":"4",
    "addr:postcode":"28830",
    "addr:street":"Calle De Montes De Toledo De Los",
    "iso:country":"ES",
    "sg:address":"Calle de Montes De Toledo (de Los), 4",
    "sg:city":"Poligono De San Fernando De Henares",
    "sg:orig_category":"Chapister\u00cda",
    "sg:phone":"+34 916 77 74 20",
    "sg:postcode":"28830",
    "sg:province":"Madrid",
    "wof:name":"Refialas S.l.",
    "wof:placetype":"venue"
},
  "geometry": {"coordinates":[-3.4998540878,40.4527015686],"type":"Point"}
}