{
  "type": "Feature",
  "properties": {
    "iso:country":"ES",
    "sg:address":"Pl Font, 4",
    "sg:city":"Palma",
    "sg:orig_category":"Maquinaria Para Industrias Diversas",
    "sg:phone":"+34 971 27 70 47",
    "sg:postcode":"07006",
    "sg:province":"Islas Baleares",
    "wof:name":"Llorens Alou Fernando",
    "wof:placetype":"venue"
},
  "geometry": {"coordinates":[2.6735789776,39.5604248047],"type":"Point"}
}