{
  "type": "Feature",
  "properties": {
    "iso:country":"ES",
    "sg:address":"Carrer de Tancat De La Quimica, S/n",
    "sg:city":"Esparreguera",
    "sg:orig_category":"Reciclaje Y Tratamiento De Desechos Varios",
    "sg:phone":"+34 937 70 94 14",
    "sg:postcode":"08292",
    "sg:province":"Barcelona",
    "wof:name":"Reciclajes Epa S.l.",
    "wof:placetype":"venue"
},
  "geometry": {"coordinates":[1.8127340078,41.5431747437],"type":"Point"}
}