{
  "type": "Feature",
  "properties": {
    "addr:full":"Calle de Juan A Melon, 1 Mogarraz Salamanca 37610",
    "addr:housenumber":"1",
    "addr:postcode":"37610",
    "addr:street":"Calle De Juan A Melon",
    "iso:country":"ES",
    "sg:address":"Calle de Juan A Melon, 1",
    "sg:city":"Mogarraz",
    "sg:orig_category":"Bancos",
    "sg:phone":"+34 923 41 81 28",
    "sg:postcode":"37610",
    "sg:province":"Salamanca",
    "wof:name":"Banco De Castilla",
    "wof:placetype":"venue"
},
  "geometry": {"coordinates":[-6.0536088943,40.4921607971],"type":"Point"}
}