{
  "type": "Feature",
  "properties": {
    "addr:full":"Ctra Aceeso A Alumina-aluminio, S/n Lieiro Lugo 27890",
    "addr:housenumber":"s",
    "addr:postcode":"27890",
    "addr:street":"Ctra Aceeso A Alumina-Aluminio;/ N",
    "iso:country":"ES",
    "sg:address":"Ctra Aceeso A Alumina-aluminio, S/n",
    "sg:city":"Lieiro",
    "sg:orig_category":"Montaje (empresas De)",
    "sg:phone":"+34 982 59 50 00",
    "sg:postcode":"27890",
    "sg:province":"Lugo",
    "wof:name":"Reparaciones Y Montajes Galicia S. A.",
    "wof:placetype":"venue"
},
  "geometry": {"coordinates":[-7.4429941177,43.6938285828],"type":"Point"}
}