{
  "type": "Feature",
  "properties": {
    "iso:country":"ES",
    "sg:address":"Pl Catalunya, 3",
    "sg:city":"Ulldecona",
    "sg:orig_category":"Peluqueros: De Se\u00d1oras",
    "sg:phone":"+34 977 72 11 90",
    "sg:postcode":"43550",
    "sg:province":"Tarragona",
    "wof:name":"Roig Vidal Montserrat",
    "wof:placetype":"venue"
},
  "geometry": {"coordinates":[0.4428859949,40.5969200134],"type":"Point"}
}