{
  "type": "Feature",
  "properties": {
    "addr:full":"Avda Plaza Toros, 12 Toledo Toledo 45003",
    "addr:housenumber":"12",
    "addr:postcode":"45003",
    "addr:street":"Avda Plaza Toros",
    "iso:country":"ES",
    "sg:address":"Avda Plaza Toros, 12",
    "sg:city":"Toledo",
    "sg:orig_category":"Promotores Constructores",
    "sg:phone":"+34 925 28 50 06",
    "sg:postcode":"45003",
    "sg:province":"Toledo",
    "wof:name":"Construcciones Tesafer S. A.",
    "wof:placetype":"venue"
},
  "geometry": {"coordinates":[-4.0241189003,39.8678474426],"type":"Point"}
}