{
  "type": "Feature",
  "properties": {
    "addr:full":"Avda Doctor Fleming, 24 Villaca\u00f1as Toledo 45860",
    "addr:housenumber":"24",
    "addr:postcode":"45860",
    "addr:street":"Avda Doctor Fleming",
    "iso:country":"ES",
    "sg:address":"Avda Doctor Fleming, 24",
    "sg:city":"Villaca\u00f1as",
    "sg:orig_category":"Asociaciones Y Clubs Deportivos",
    "sg:phone":"+34 925 20 16 85",
    "sg:postcode":"45860",
    "sg:province":"Toledo",
    "wof:name":"Paniagua Novillo Antonio",
    "wof:placetype":"venue"
},
  "geometry": {"coordinates":[-3.3447508812,39.616897583],"type":"Point"}
}