{
  "type": "Feature",
  "properties": {
    "addr:full":"Donostia Ibilbidea, 44 Astigarraga Guip\u00f9zcoa 20115",
    "addr:housenumber":"44",
    "addr:postcode":"20115",
    "addr:street":"Donostia Ibilbidea;Guipu\u0300Zcoa",
    "iso:country":"ES",
    "sg:address":"Donostia Ibilbidea, 44",
    "sg:city":"Astigarraga",
    "sg:orig_category":"Persianas Interiores, Exteriores",
    "sg:phone":"+34 943 55 76 64",
    "sg:postcode":"20115",
    "sg:province":"Guip\u00f9zcoa",
    "wof:name":"Iraola Iraola Jose Maria",
    "wof:placetype":"venue"
},
  "geometry": {"coordinates":[-1.951004982,43.2830696106],"type":"Point"}
}