{
  "type": "Feature",
  "properties": {
    "addr:full":"Carr Sant Lluis, 57 Balaguer Lleida 25600",
    "addr:housenumber":"57",
    "addr:postcode":"25600",
    "addr:street":"Carr Sant Lluis",
    "iso:country":"ES",
    "sg:address":"Carr Sant Lluis, 57",
    "sg:city":"Balaguer",
    "sg:orig_category":"Fotograf\u00cda Y Cine: Aparatos, Pel\u00cdculas Y Accesorios (al Por Menor)",
    "sg:phone":"+34 973 44 86 39",
    "sg:postcode":"25600",
    "sg:province":"Lleida",
    "wof:name":"Bonet Dalmau Jorge",
    "wof:placetype":"venue"
},
  "geometry": {"coordinates":[0.8071600199,41.7896003723],"type":"Point"}
}