{
  "type": "Feature",
  "properties": {
    "addr:full":"Rond Levante, 35 Vista Alegre Murcia 30008",
    "addr:housenumber":"35",
    "addr:postcode":"30008",
    "addr:street":"Rond Levante",
    "iso:country":"ES",
    "sg:address":"Rond Levante, 35",
    "sg:city":"Vista Alegre",
    "sg:orig_category":"Plomeros",
    "sg:phone":"+34 968 23 84 27",
    "sg:postcode":"30008",
    "sg:province":"Murcia",
    "wof:name":"Ireco Viviendas S.l.",
    "wof:placetype":"venue"
},
  "geometry": {"coordinates":[-1.1227610111,37.9911079407],"type":"Point"}
}