{
  "type": "Feature",
  "properties": {
    "iso:country":"ES",
    "sg:address":"Calle de Orihuela, 21",
    "sg:city":"Valencia",
    "sg:orig_category":"Estancos",
    "sg:phone":"+34 963 47 16 62",
    "sg:postcode":"46009",
    "sg:province":"Valencia",
    "wof:name":"Martinez Checa Elisa",
    "wof:placetype":"venue"
},
  "geometry": {"coordinates":[-0.3762528896,39.4846229553],"type":"Point"}
}