{
  "type": "Feature",
  "properties": {
    "iso:country":"ES",
    "sg:address":"Calle de Santa Maria La Vieja, 39",
    "sg:city":"Antequera",
    "sg:orig_category":"Ingeniero",
    "sg:phone":"+34 952 84 52 56",
    "sg:postcode":"29200",
    "sg:province":"M\u00e1laga",
    "wof:name":"Construcciones Prosemol S.l.",
    "wof:placetype":"venue"
},
  "geometry": {"coordinates":[-4.5616688728,37.0128860474],"type":"Point"}
}