{
  "type": "Feature",
  "properties": {
    "iso:country":"ES",
    "sg:address":"Pg Font Pudenta, 22",
    "sg:city":"Montcada Centre",
    "sg:orig_category":"Inform\u00c1tica (estudios, Servicios, Asesor\u00cda, Formaci\u00d3n)",
    "sg:phone":"+34 935 75 01 33",
    "sg:postcode":"08110",
    "sg:province":"Barcelona",
    "wof:name":"Sanchez-lafuente Latorre Carlos",
    "wof:placetype":"venue"
},
  "geometry": {"coordinates":[2.1819438934,41.4849662781],"type":"Point"}
}