{
  "type": "Feature",
  "properties": {
    "addr:full":"Calle de Condado De Trevi\u00d1o, 80 Miranda Ebro Burgos 09200",
    "addr:housenumber":"80",
    "addr:postcode":"09200",
    "addr:street":"Calle De Condado De Trevin\u0303O",
    "iso:country":"ES",
    "sg:address":"Calle de Condado De Trevi\u00d1o, 80",
    "sg:city":"Miranda Ebro",
    "sg:orig_category":"Molduras, Junquillos, Listones Y Molduras Perforadas",
    "sg:phone":"+34 947 31 10 60",
    "sg:postcode":"09200",
    "sg:province":"Burgos",
    "wof:name":"Lopez Ribas Elias Alberto",
    "wof:placetype":"venue"
},
  "geometry": {"coordinates":[-2.9387567043,42.6876831055],"type":"Point"}
}