{
  "type": "Feature",
  "properties": {
    "iso:country":"ES",
    "sg:address":"G.v. Fernando El Catolico, 59",
    "sg:city":"Valencia",
    "sg:orig_category":"Ropa Para Ni\u00d1os (al Por Menor)",
    "sg:phone":"+34 963 85 56 63",
    "sg:postcode":"46008",
    "sg:province":"Valencia",
    "wof:name":"Ferrer Ortega Pedro",
    "wof:placetype":"venue"
},
  "geometry": {"coordinates":[-0.3885770142,39.4747161865],"type":"Point"}
}