{
  "type": "Feature",
  "properties": {
    "iso:country":"ES",
    "sg:address":"Rond Nelle, 107",
    "sg:city":"Coru\u00d1a",
    "sg:orig_category":"Carnicer\u00cdas, Carnicer\u00cdas",
    "sg:phone":"+34 981 26 25 80",
    "sg:postcode":"15010",
    "sg:province":"La Coru\u00f1a",
    "wof:name":"Ferre\u00f1o Ferreiro Jose",
    "wof:placetype":"venue"
},
  "geometry": {"coordinates":[-8.4168376923,43.3623657227],"type":"Point"}
}