{
  "type": "Feature",
  "properties": {
    "iso:country":"ES",
    "sg:address":"Avda Salamanca, Km. 0124,0",
    "sg:city":"Valladolid",
    "sg:orig_category":"Ferreter\u00cda (diversos)",
    "sg:phone":"+34 983 35 54 97",
    "sg:postcode":"47014",
    "sg:province":"Valladolid",
    "wof:name":"Mongil Prieto Cipriano",
    "wof:placetype":"venue"
},
  "geometry": {"coordinates":[-4.7431540489,41.6445617676],"type":"Point"}
}