{
  "type": "Feature",
  "properties": {
    "iso:country":"ES",
    "sg:address":"Calle de Pinos, 3",
    "sg:city":"Malaga",
    "sg:orig_category":"Empresarios Y Productoras De Espect\u00c1culos",
    "sg:phone":"+34 952 25 29 18",
    "sg:postcode":"29012",
    "sg:province":"M\u00e1laga",
    "wof:name":"Producciones Infantiles Miguel Pino S.l.",
    "wof:placetype":"venue"
},
  "geometry": {"coordinates":[-4.4127440453,36.7265510559],"type":"Point"}
}