{
  "type": "Feature",
  "properties": {
    "addr:full":"Calle de Felipe Campos, 12 Madrid Madrid 28002",
    "addr:housenumber":"12",
    "addr:postcode":"madrid;28002",
    "addr:street":"Calle De Felipe Campos",
    "iso:country":"ES",
    "sg:address":"Calle de Felipe Campos, 12",
    "sg:city":"Madrid",
    "sg:orig_category":"Arquitectos",
    "sg:phone":"+34 915 61 68 81",
    "sg:postcode":"28002",
    "sg:province":"Madrid",
    "wof:name":"Ruiz Cabrero Gabriel",
    "wof:placetype":"venue"
},
  "geometry": {"coordinates":[-3.6799399853,40.443157196],"type":"Point"}
}