{
  "type": "Feature",
  "properties": {
    "addr:full":"Plaz Doctor Barraquer, 5 Sevilla Sevilla 41009",
    "addr:housenumber":"5",
    "addr:postcode":"41009",
    "addr:street":"Barraquer",
    "iso:country":"ES",
    "sg:address":"Plaz Doctor Barraquer, 5",
    "sg:city":"Sevilla",
    "sg:classifiers":[
        {
            "category":"Personal",
            "subcategory":"Barber",
            "type":"Services"
        }
    ],
    "sg:phone":"+34 954 38 89 91",
    "sg:postcode":"41009",
    "sg:province":"Sevilla",
    "sg:tags":[
        "caballeros",
        "de",
        "peluqueros"
    ],
    "wof:name":"Govea Dominguez Pedro",
    "wof:placetype":"venue"
},
  "geometry": {"coordinates":[-5.9892492294,37.407371521],"type":"Point"}
}