{
  "type": "Feature",
  "properties": {
    "addr:full":"Ctra Sevilla-lora, Km. 0038,0 Carmona Sevilla 41410",
    "addr:postcode":"41410",
    "addr:street":"Ctra Sevilla-Lora Km. 0038,0",
    "iso:country":"ES",
    "sg:address":"Ctra Sevilla-lora, Km. 0038,0",
    "sg:city":"Carmona",
    "sg:orig_category":"Agricultura: Abastecimiento Y Cosechado (negocio)",
    "sg:phone":"+34 955 95 30 85",
    "sg:postcode":"41410",
    "sg:province":"Sevilla",
    "wof:name":"Cotos Regables Del Guadalquivir S.l",
    "wof:placetype":"venue"
},
  "geometry": {"coordinates":[-5.6433792114,37.4708709717],"type":"Point"}
}