{
  "type": "Feature",
  "properties": {
    "addr:full":"Polig. Industrial, S/n Algeciras C\u00e1diz 11207",
    "addr:housenumber":"/ n;ca\u0301diz",
    "addr:postcode":"11207",
    "addr:street":"Industrial",
    "iso:country":"ES",
    "sg:address":"Polig. Industrial, S/n",
    "sg:city":"Algeciras",
    "sg:orig_category":"Transporte En General",
    "sg:phone":"+34 956 57 90 38",
    "sg:postcode":"11207",
    "sg:province":"C\u00e1diz",
    "sg:website":"www.arpt.es",
    "wof:name":"Algeciras Reefer Port",
    "wof:placetype":"venue"
},
  "geometry": {"coordinates":[-5.4620547295,36.0792160034],"type":"Point"}
}