{
  "type": "Feature",
  "properties": {
    "iso:country":"ES",
    "sg:address":"Calle de Alameda, S/n",
    "sg:city":"Ca\u00f1averal",
    "sg:orig_category":"Mec\u00c1nico Del Autom\u00d3vil",
    "sg:phone":"+34 927 30 03 57",
    "sg:postcode":"10820",
    "sg:province":"C\u00e1ceres",
    "wof:name":"Diaz Carballo Jose Julian",
    "wof:placetype":"venue"
},
  "geometry": {"coordinates":[-6.3863368034,39.7946510315],"type":"Point"}
}