{
  "type": "Feature",
  "properties": {
    "addr:full":"Pg Sant Joan, 233 Manlleu Barcelona 08560",
    "addr:housenumber":"233",
    "addr:postcode":"08560",
    "addr:street":"Pg Sant Joan",
    "iso:country":"ES",
    "sg:address":"Pg Sant Joan, 233",
    "sg:city":"Manlleu",
    "sg:orig_category":"Material Y Herramientas Agr\u00cdcolas",
    "sg:phone":"+34 938 51 04 95",
    "sg:postcode":"08560",
    "sg:province":"Barcelona",
    "wof:name":"Tallers Compar S.a.",
    "wof:placetype":"venue"
},
  "geometry": {"coordinates":[2.2810049057,42.0068206787],"type":"Point"}
}