{
  "type": "Feature",
  "properties": {
    "addr:full":"Carrer de Bartomeu Amat, 71 Terrassa Barcelona 08225",
    "addr:housenumber":"71",
    "addr:postcode":"08225",
    "addr:street":"Carrer De Bartomeu Amat",
    "iso:country":"ES",
    "sg:address":"Carrer de Bartomeu Amat, 71",
    "sg:city":"Terrassa",
    "sg:orig_category":"Centros Empresariales",
    "sg:phone":"+34 937 34 32 69",
    "sg:postcode":"08225",
    "sg:province":"Barcelona",
    "wof:name":"Freixa Obrador Maria",
    "wof:placetype":"venue"
},
  "geometry": {"coordinates":[2.0121450424,41.5720024109],"type":"Point"}
}