{
  "type": "Feature",
  "properties": {
    "addr:full":"Calle de Mariano Mu\u00d1oz Nogues, 5 Teruel Teruel 44001",
    "addr:housenumber":"5",
    "addr:postcode":"44001",
    "addr:street":"Calle De Mariano;Nogues",
    "iso:country":"ES",
    "sg:address":"Calle de Mariano Mu\u00d1oz Nogues, 5",
    "sg:city":"Teruel",
    "sg:orig_category":"Frutas, Legumbres Frescas Y Tempranas (al Por Menor)",
    "sg:phone":"+34 978 60 23 40",
    "sg:postcode":"44001",
    "sg:province":"Teruel",
    "wof:name":"Mateo Gomez Carlos",
    "wof:placetype":"venue"
},
  "geometry": {"coordinates":[-1.1073269844,40.3431167603],"type":"Point"}
}