{
  "type": "Feature",
  "properties": {
    "iso:country":"ES",
    "sg:address":"Calle de Zurbaran, 9",
    "sg:city":"Madrid",
    "sg:orig_category":"Arquitectos",
    "sg:phone":"+34 913 19 28 22",
    "sg:postcode":"28010",
    "sg:province":"Madrid",
    "wof:name":"Curiel Rozas Luis Maria",
    "wof:placetype":"venue"
},
  "geometry": {"coordinates":[-3.6941840649,40.4297523499],"type":"Point"}
}