{
  "type": "Feature",
  "properties": {
    "addr:full":"Calle de Bruselas, 16 Sevilla Sevilla 41012",
    "addr:housenumber":"16",
    "addr:postcode":"41012",
    "addr:street":"Calle De Bruselas",
    "iso:country":"ES",
    "sg:address":"Calle de Bruselas, 16",
    "sg:city":"Sevilla",
    "sg:orig_category":"Ingenier\u00cda, Centros De Estudios (diversos)",
    "sg:phone":"+34 954 23 94 00",
    "sg:postcode":"41012",
    "sg:province":"Sevilla",
    "wof:name":"Pastor Cubero Jose Antonio",
    "wof:placetype":"venue"
},
  "geometry": {"coordinates":[-5.9777321815,37.3475952148],"type":"Point"}
}