{
  "type": "Feature",
  "properties": {
    "addr:full":"Rua Esperanto, 15 Vigo Pontevedra 36204",
    "addr:housenumber":"15",
    "addr:postcode":"36204",
    "addr:street":"Rua Esperanto",
    "iso:country":"ES",
    "sg:address":"Rua Esperanto, 15",
    "sg:city":"Vigo",
    "sg:orig_category":"Organizaciones Internacionales",
    "sg:phone":"+34 986 41 71 26",
    "sg:postcode":"36204",
    "sg:province":"Pontevedra",
    "wof:name":"Aldeas Infantiles Sos De Galicia",
    "wof:placetype":"venue"
},
  "geometry": {"coordinates":[-8.7104854584,42.2328643799],"type":"Point"}
}