{
  "type": "Feature",
  "properties": {
    "addr:full":"Bohemia, S/n Manga Mar Menor Murcia 30380",
    "addr:housenumber":"s / n",
    "addr:postcode":"30380",
    "iso:country":"ES",
    "sg:address":"Bohemia, S/n",
    "sg:city":"Manga Mar Menor",
    "sg:orig_category":"Deportes N\u00c1uticos, Acu\u00c1ticos Y Subacu\u00c1ticos: Art\u00cdculos Y Equipo (al Por Menor)",
    "sg:phone":"+34 968 14 10 78",
    "sg:postcode":"30380",
    "sg:province":"Murcia",
    "wof:name":"Sanabria Lopez Maria Concepcion",
    "wof:placetype":"venue"
},
  "geometry": {"coordinates":[-0.7232689857,37.6627502441],"type":"Point"}
}