{
  "type": "Feature",
  "properties": {
    "addr:full":"Calle de Zamakoa, 23 Kurtzea Vizcaya 48960",
    "addr:housenumber":"23",
    "addr:postcode":"48960",
    "addr:street":"Calle De Zamakoa",
    "iso:country":"ES",
    "sg:address":"Calle de Zamakoa, 23",
    "sg:city":"Kurtzea",
    "sg:orig_category":"Maquinaria Neum\u00c1tica",
    "sg:phone":"+34 944 57 04 97",
    "sg:postcode":"48960",
    "sg:province":"Vizcaya",
    "sg:website":"www.sistemastecnicosdefijacion.com",
    "wof:name":"Sistemas Tecnicos De Fijacion S.l.",
    "wof:placetype":"venue"
},
  "geometry": {"coordinates":[-2.8428380489,43.2326660156],"type":"Point"}
}