{
  "type": "Feature",
  "properties": {
    "iso:country":"ES",
    "sg:address":"Calle de Herrera El Viejo, 11",
    "sg:city":"Sevilla",
    "sg:orig_category":"Fabricaci\u00d3n De Acumuladores Y De Pilas El\u00c9ctricas",
    "sg:phone":"+34 954 22 83 26",
    "sg:postcode":"41001",
    "sg:province":"Sevilla",
    "wof:name":"Suelcan S.l.",
    "wof:placetype":"venue"
},
  "geometry": {"coordinates":[-5.9991559982,37.3918113708],"type":"Point"}
}