{
  "type": "Feature",
  "properties": {
    "addr:full":"Ctra Vella (sant Celoni), 8 S. Celoni Barcelona 08470",
    "addr:housenumber":"8",
    "addr:postcode":"08470",
    "addr:street":"Ctra Vella;Celoni",
    "iso:country":"ES",
    "sg:address":"Ctra Vella (sant Celoni), 8",
    "sg:city":"S. Celoni",
    "sg:orig_category":"Comercio De Piezas De Recambio Y De Accesorios De Veh\u00cdculos, Veh\u00cdculos Industriales",
    "sg:phone":"+34 938 67 04 41",
    "sg:postcode":"08470",
    "sg:province":"Barcelona",
    "wof:name":"Martinez Bonamusa Jose Maria",
    "wof:placetype":"venue"
},
  "geometry": {"coordinates":[2.4885089397,41.6864547729],"type":"Point"}
}