{
  "type": "Feature",
  "properties": {
    "iso:country":"ES",
    "sg:address":"Carretera, S/n",
    "sg:city":"Ager",
    "sg:orig_category":"Tiendas De Grano, Frutas Y Legumbres Secas (al Por Menor)",
    "sg:phone":"+34 973 45 50 48",
    "sg:postcode":"25691",
    "sg:province":"Lleida",
    "wof:name":"Montardit Farre Agustin",
    "wof:placetype":"venue"
},
  "geometry": {"coordinates":[0.7641400099,42.0030517578],"type":"Point"}
}