{
  "type": "Feature",
  "properties": {
    "iso:country":"ES",
    "sg:address":"Avda San Jorge, 68",
    "sg:city":"Andorra",
    "sg:orig_category":"Molduras, Junquillos, Listones Y Molduras Perforadas",
    "sg:phone":"+34 978 84 33 43",
    "sg:postcode":"44500",
    "sg:province":"Teruel",
    "wof:name":"San Jorge 68 S.l.",
    "wof:placetype":"venue"
},
  "geometry": {"coordinates":[-0.4463739991,40.9772987366],"type":"Point"}
}