{
  "type": "Feature",
  "properties": {
    "iso:country":"ES",
    "sg:address":"Calle de Teniente General Chamorro Martinez, 82",
    "sg:city":"Martos",
    "sg:orig_category":"Comercio De Piezas De Recambio Y De Accesorios De Veh\u00cdculos, Veh\u00cdculos Industriales",
    "sg:phone":"+34 953 55 38 04",
    "sg:postcode":"23600",
    "sg:province":"Ja\u00e9n",
    "wof:name":"Repuestos Frama S.l.",
    "wof:placetype":"venue"
},
  "geometry": {"coordinates":[-3.9724559784,37.7242050171],"type":"Point"}
}