{
  "type": "Feature",
  "properties": {
    "addr:full":"Carr Pintor Sorolla, 14 Badalona Barcelona 08917",
    "addr:housenumber":"14",
    "addr:postcode":"08917",
    "addr:street":"Carr Pintor Sorolla",
    "iso:country":"ES",
    "sg:address":"Carr Pintor Sorolla, 14",
    "sg:city":"Badalona",
    "sg:orig_category":"Empresas De Carpinter\u00cda De Madera",
    "sg:phone":"+34 933 97 52 71",
    "sg:postcode":"08917",
    "sg:province":"Barcelona",
    "wof:name":"Fernandez Gimenez Andres",
    "wof:placetype":"venue"
},
  "geometry": {"coordinates":[2.2450649738,41.4503440857],"type":"Point"}
}