{
  "type": "Feature",
  "properties": {
    "iso:country":"ES",
    "sg:address":"Alfareros (p I Agruenco), S/n",
    "sg:city":"Puebla Vicar",
    "sg:orig_category":"Maquinaria Para Industrias Diversas",
    "sg:phone":"+34 950 55 36 12",
    "sg:postcode":"04738",
    "sg:province":"Almer\u00eda",
    "wof:name":"Agrotractora Rodriguez S.l.",
    "wof:placetype":"venue"
},
  "geometry": {"coordinates":[-2.6425154209,36.831451416],"type":"Point"}
}