{
  "type": "Feature",
  "properties": {
    "iso:country":"ES",
    "sg:address":"Carrer de Carrer de Europa, S/n",
    "sg:city":"Puerto Rico",
    "sg:orig_category":"Restaurantes",
    "sg:phone":"+34 928 56 23 82",
    "sg:postcode":"35130",
    "sg:province":"Las Palmas",
    "wof:name":"Pan  Xulong",
    "wof:placetype":"venue"
},
  "geometry": {"coordinates":[-13.9036235809,28.6303958893],"type":"Point"}
}