{
  "type": "Feature",
  "properties": {
    "iso:country":"ES",
    "sg:address":"Calle de Serrano, 17",
    "sg:city":"Madrid",
    "sg:orig_category":"Inmobiliaria (agencias)",
    "sg:phone":"+34 915 77 16 88",
    "sg:postcode":"28001",
    "sg:province":"Madrid",
    "wof:name":"Aedifica Dise\u00d1os Inmobiliarios S.l.",
    "wof:placetype":"venue"
},
  "geometry": {"coordinates":[-3.6878526211,40.4255065918],"type":"Point"}
}