{
  "type": "Feature",
  "properties": {
    "addr:full":"Carrer de Concepcion Arenal, 197 Barcelona Barcelona 08030",
    "addr:housenumber":"197",
    "addr:postcode":"08030",
    "addr:street":"Carrer De Concepcion Arenal",
    "iso:country":"ES",
    "sg:address":"Carrer de Concepcion Arenal, 197",
    "sg:city":"Barcelona",
    "sg:orig_category":"Bisuter\u00cda, Joyer\u00cda, Relojer\u00cda (al Por Menor)",
    "sg:phone":"+34 933 45 21 18",
    "sg:postcode":"08030",
    "sg:province":"Barcelona",
    "wof:name":"Herrerias Marquez Antonio",
    "wof:placetype":"venue"
},
  "geometry": {"coordinates":[2.1842930317,41.4290885925],"type":"Point"}
}