{
  "type": "Feature",
  "properties": {
    "addr:full":"Estda. Nacional 536, Km. 0043,0 Sobradelo Ourense 32330",
    "addr:postcode":"32330",
    "addr:street":"Nacional 536 Km. 0043,0",
    "iso:country":"ES",
    "sg:address":"Estda. Nacional 536, Km. 0043,0",
    "sg:city":"Sobradelo",
    "sg:orig_category":"Trabajos De Revestimiento De Fachadas",
    "sg:phone":"+34 988 33 52 43",
    "sg:postcode":"32330",
    "sg:province":"Ourense",
    "sg:website":"carbocooscuro.com",
    "wof:name":"Caborco Oscuro S. A.",
    "wof:placetype":"venue"
},
  "geometry": {"coordinates":[-6.9207801819,42.3918495178],"type":"Point"}
}