{
  "type": "Feature",
  "properties": {
    "iso:country":"ES",
    "sg:address":"Calle de Tampa, 7",
    "sg:city":"Malaga",
    "sg:orig_category":"Buzones De Correos",
    "sg:phone":"+34 952 30 80 03",
    "sg:postcode":"29007",
    "sg:province":"M\u00e1laga",
    "sg:website":"www.buzones-gavilan.com",
    "wof:name":"Buzones Gavilan S.l.",
    "wof:placetype":"venue"
},
  "geometry": {"coordinates":[-4.4361000061,36.7203025818],"type":"Point"}
}