{
  "type": "Feature",
  "properties": {
    "iso:country":"ES",
    "sg:address":"Gta Quevedo, 7",
    "sg:city":"Madrid",
    "sg:orig_category":"Inmobiliaria (agencias)",
    "sg:phone":"+34 914 47 22 05",
    "sg:postcode":"28015",
    "sg:province":"Madrid",
    "sg:website":"www.pisotienda.com",
    "wof:name":"Realizaciones De Pisotienda S.l.",
    "wof:placetype":"venue"
},
  "geometry": {"coordinates":[-3.7039980888,40.4336967468],"type":"Point"}
}