{
  "type": "Feature",
  "properties": {
    "iso:country":"ES",
    "sg:address":"Avda Infanta Cristina De Espa\u00d1a, 49",
    "sg:city":"Melilla",
    "sg:orig_category":"Alimentaci\u00d3n General (al Por Menor)",
    "sg:phone":"+34 952 67 70 74",
    "sg:postcode":"52006",
    "sg:province":"Melilla",
    "wof:name":"Mohand Moh Aicha",
    "wof:placetype":"venue"
},
  "geometry": {"coordinates":[-2.9383699894,35.2764587402],"type":"Point"}
}