{
  "type": "Feature",
  "properties": {
    "addr:full":"Calle de Hornos Caleros (de Los), 60 Avila \u00c1vila 05003",
    "addr:housenumber":"60",
    "addr:postcode":"05003",
    "addr:street":"Calle De Hornos Caleros De Los;A\u0301Vila",
    "iso:country":"ES",
    "sg:address":"Calle de Hornos Caleros (de Los), 60",
    "sg:city":"Avila",
    "sg:orig_category":"Chapister\u00cda",
    "sg:phone":"+34 920 22 23 05",
    "sg:postcode":"05003",
    "sg:province":"\u00c1vila",
    "wof:name":"Sanchez Hernandez Maximo Jesus",
    "wof:placetype":"venue"
},
  "geometry": {"coordinates":[-4.6759362221,40.6503448486],"type":"Point"}
}