{
  "type": "Feature",
  "properties": {
    "iso:country":"ES",
    "sg:address":"Calle de Corona De Aragon, 28",
    "sg:city":"Barbastro",
    "sg:orig_category":"Restaurantes",
    "sg:phone":"+34 974 31 53 53",
    "sg:postcode":"22300",
    "sg:province":"Huesca",
    "wof:name":"Bajoz Zafra Modesta",
    "wof:placetype":"venue"
},
  "geometry": {"coordinates":[0.1281581968,42.0360832214],"type":"Point"}
}