{
  "type": "Feature",
  "properties": {
    "iso:country":"ES",
    "sg:address":"Calle de Cartagena, 4",
    "sg:city":"Caravaca Cruz",
    "sg:classifiers":[
        {
            "category":"Tea Room",
            "subcategory":"None",
            "type":"Food & Drink"
        }
    ],
    "sg:phone":"+34 968 70 23 92",
    "sg:postcode":"30400",
    "sg:province":"Murcia",
    "sg:tags":[
        "snack"
    ],
    "wof:name":"Juan Francisco Garcia-talavera Correduria De Seguros S.l.",
    "wof:placetype":"venue"
},
  "geometry": {"coordinates":[-1.8609677553,38.1033287048],"type":"Point"}
}