{
  "type": "Feature",
  "properties": {
    "iso:country":"ES",
    "sg:address":"Calle de Caspe, 46",
    "sg:city":"Zaragoza",
    "sg:orig_category":"Comerciantes Al Por Mayor De Vinos, Licores Y Alcoholes",
    "sg:phone":"+34 976 33 26 40",
    "sg:postcode":"50017",
    "sg:province":"Zaragoza",
    "wof:name":"Mu\u00f1oz Aguinaliu Faustino",
    "wof:placetype":"venue"
},
  "geometry": {"coordinates":[-0.9075343013,41.6511154175],"type":"Point"}
}