{
  "type": "Feature",
  "properties": {
    "addr:full":"Ctra Andalucia, Km. 0035,5 Sese\u00e7a Nuevo Toledo 45224",
    "addr:postcode":"45224",
    "addr:street":"Ctra Andalucia Km. 0035,5 Sesec\u0327A",
    "iso:country":"ES",
    "sg:address":"Ctra Andalucia, Km. 0035,5",
    "sg:city":"Sese\u00e7a Nuevo",
    "sg:orig_category":"Institutos De Belleza (productos Y Aparatos)",
    "sg:phone":"+34 918 01 25 50",
    "sg:postcode":"45224",
    "sg:province":"Toledo",
    "sg:website":"www.abadiatrade.com",
    "wof:name":"Abadia Trade S.a.",
    "wof:placetype":"venue"
},
  "geometry": {"coordinates":[-4.024476,39.856777],"type":"Point"}
}