{
  "type": "Feature",
  "properties": {
    "addr:full":"Calle de Lerida, 8 Madrid Madrid 28020",
    "addr:housenumber":"8",
    "addr:postcode":"madrid;28020",
    "addr:street":"Calle De Lerida",
    "iso:country":"ES",
    "sg:address":"Calle de Lerida, 8",
    "sg:city":"Madrid",
    "sg:orig_category":"Agencias Y Agentes Comerciales, Representantes",
    "sg:phone":"+34 915 71 11 93",
    "sg:postcode":"28020",
    "sg:province":"Madrid",
    "wof:name":"Cohen Levy Mesod",
    "wof:placetype":"venue"
},
  "geometry": {"coordinates":[-3.7012250423,40.4520187378],"type":"Point"}
}