{
  "type": "Feature",
  "properties": {
    "addr:full":"Pase San Jose, 148 Palmas De Gran Canaria Las Palmas 35015",
    "addr:postcode":"35015",
    "addr:street":"Jose 148",
    "iso:country":"ES",
    "sg:address":"Pase San Jose, 148",
    "sg:city":"Palmas De Gran Canaria",
    "sg:orig_category":"Agentes, Concesionarios Y Sucursales De Veh\u00cdculos",
    "sg:phone":"+34 928 31 98 45",
    "sg:postcode":"35015",
    "sg:province":"Las Palmas",
    "wof:name":"Repuestos Reunidos S.l.",
    "wof:placetype":"venue"
},
  "geometry": {"coordinates":[-15.4232616425,28.095746994],"type":"Point"}
}