{
  "type": "Feature",
  "properties": {
    "iso:country":"ES",
    "sg:address":"Ctra. Esparraguera A Olesa, Km. 0001,8",
    "sg:city":"Esparreguera",
    "sg:orig_category":"Fabricaci\u00d3n De Cajas De Cart\u00d3n",
    "sg:phone":"+34 937 77 13 87",
    "sg:postcode":"08292",
    "sg:province":"Barcelona",
    "wof:name":"Envastub S.a.",
    "wof:placetype":"venue"
},
  "geometry": {"coordinates":[1.8127340078,41.5431747437],"type":"Point"}
}