{
  "type": "Feature",
  "properties": {
    "iso:country":"ES",
    "sg:address":"Avda Diputacion Provincial, 77",
    "sg:city":"Calanda",
    "sg:orig_category":"Fabricaci\u00d3n De Banderas Y De Banderines",
    "sg:phone":"+34 978 84 68 81",
    "sg:postcode":"44570",
    "sg:province":"Teruel",
    "wof:name":"La Industrial Velera Marsal S.a.",
    "wof:placetype":"venue"
},
  "geometry": {"coordinates":[-0.2226449996,40.9390411377],"type":"Point"}
}