{
  "type": "Feature",
  "properties": {
    "addr:full":"Plaz Espa\u00d1a, 1 Albatera Alicante 03340",
    "addr:housenumber":"1",
    "addr:postcode":"03340",
    "addr:street":"Plaz Espan\u0303A",
    "iso:country":"ES",
    "sg:address":"Plaz Espa\u00d1a, 1",
    "sg:city":"Albatera",
    "sg:orig_category":"Administraciones Regionales, Departamentales Y Locales",
    "sg:phone":"+34 965 48 50 00",
    "sg:postcode":"03340",
    "sg:province":"Alicante",
    "wof:name":"Ayuntamiento De Albatera",
    "wof:placetype":"venue"
},
  "geometry": {"coordinates":[-0.8696246147,38.1805992126],"type":"Point"}
}