{
  "type": "Feature",
  "properties": {
    "addr:full":"Carr Gibraltar, 10 Pai I Capellans Valencia 46930",
    "addr:housenumber":"10",
    "addr:postcode":"46930",
    "addr:street":"Carr Gibraltar",
    "iso:country":"ES",
    "sg:address":"Carr Gibraltar, 10",
    "sg:city":"Pai I Capellans",
    "sg:orig_category":"Agencias Y Asesores De Publicidad",
    "sg:phone":"+34 963 66 06 63",
    "sg:postcode":"46930",
    "sg:province":"Valencia",
    "wof:name":"Capicua Graphics Star S.l.",
    "wof:placetype":"venue"
},
  "geometry": {"coordinates":[-0.4419890046,39.482711792],"type":"Point"}
}