{
  "type": "Feature",
  "properties": {
    "addr:full":"Ctra. Velilla S. Antonio, Km. 0002,1 Mejorada Campo Madrid 28840",
    "addr:postcode":"28840",
    "addr:street":"Ctra. Velilla S. Antonio Km. 0002,1;Campo",
    "iso:country":"ES",
    "sg:address":"Ctra. Velilla S. Antonio, Km. 0002,1",
    "sg:city":"Mejorada Campo",
    "sg:orig_category":"Metalurgia",
    "sg:phone":"+34 916 79 39 15",
    "sg:postcode":"28840",
    "sg:province":"Madrid",
    "wof:name":"Fundemar S.l.",
    "wof:placetype":"venue"
},
  "geometry": {"coordinates":[-3.4838440418,40.3967437744],"type":"Point"}
}