{
  "type": "Feature",
  "properties": {
    "iso:country":"ES",
    "sg:address":"Calle de Juan Jose Rodrigo, 4",
    "sg:city":"Tomelloso",
    "sg:orig_category":"Inform\u00c1tica, Ofim\u00c1tica (estudios, Asesor\u00cda, Ingenier\u00cda, Formaci\u00d3n)",
    "sg:phone":"+34 926 50 31 31",
    "sg:postcode":"13700",
    "sg:province":"Ciudad Real",
    "wof:name":"Sicaman Nuevas Tecnologias",
    "wof:placetype":"venue"
},
  "geometry": {"coordinates":[-3.0218529701,39.1606903076],"type":"Point"}
}