{
  "type": "Feature",
  "properties": {
    "iso:country":"ES",
    "sg:address":"Avda Arqueros, 23",
    "sg:city":"Madrid",
    "sg:orig_category":"Artes Gr\u00c1ficas, Artes Pl\u00c1sticas: Material Y Suministros (al Por Menor)",
    "sg:phone":"+34 915 09 27 57",
    "sg:postcode":"28024",
    "sg:province":"Madrid",
    "wof:name":"Arquimas Romar S.l.",
    "wof:placetype":"venue"
},
  "geometry": {"coordinates":[-3.7949535847,40.3798942566],"type":"Point"}
}