{
  "type": "Feature",
  "properties": {
    "addr:full":"Plaz Rodriguez Montes, 12 Rinconada Sevilla 41309",
    "addr:housenumber":"12",
    "addr:postcode":"41309",
    "addr:street":"Plaz;Montes",
    "iso:country":"ES",
    "sg:address":"Plaz Rodriguez Montes, 12",
    "sg:city":"Rinconada",
    "sg:orig_category":"Alimentaci\u00d3n General (al Por Menor)",
    "sg:phone":"+34 955 79 72 99",
    "sg:postcode":"41309",
    "sg:province":"Sevilla",
    "wof:name":"Fernandez Herrera Manuel",
    "wof:placetype":"venue"
},
  "geometry": {"coordinates":[-5.9783678055,37.4873008728],"type":"Point"}
}