{
  "type": "Feature",
  "properties": {
    "iso:country":"ES",
    "sg:address":"Calle de Tejar (el), 11",
    "sg:city":"Orotava",
    "sg:orig_category":"Centros Empresariales",
    "sg:phone":"+34 922 32 45 60",
    "sg:postcode":"38300",
    "sg:province":"Santa Cruz De Tenerife",
    "wof:name":"Diaz Roson Yurena",
    "wof:placetype":"venue"
},
  "geometry": {"coordinates":[-16.5164146423,28.3942871094],"type":"Point"}
}