{
  "type": "Feature",
  "properties": {
    "iso:country":"ES",
    "sg:address":"Calle de Juan Suarez Carvajal, 28",
    "sg:city":"Talavera Reina",
    "sg:orig_category":"Empresas De Carpinter\u00cda De Madera",
    "sg:phone":"+34 925 82 41 91",
    "sg:postcode":"45600",
    "sg:province":"Toledo",
    "wof:name":"Fernandez Garcia Benjamin",
    "wof:placetype":"venue"
},
  "geometry": {"coordinates":[-4.8395881653,39.9609107971],"type":"Point"}
}