{
  "type": "Feature",
  "properties": {
    "iso:country":"ES",
    "sg:address":"Ctra Cordoba-almeria, Km. 0107,0",
    "sg:city":"Huelma",
    "sg:orig_category":"Fabricaci\u00d3n De Muebles",
    "sg:phone":"+34 953 39 13 33",
    "sg:postcode":"23560",
    "sg:province":"Ja\u00e9n",
    "wof:name":"Arias Diaz Antonio",
    "wof:placetype":"venue"
},
  "geometry": {"coordinates":[-3.4503295422,37.6473236084],"type":"Point"}
}