{
  "type": "Feature",
  "properties": {
    "addr:full":"Calle de Hilarion Eslava, 14 Madrid Madrid 28015",
    "addr:housenumber":"14",
    "addr:postcode":"madrid;28015",
    "addr:street":"Calle De Hilarion Eslava",
    "iso:country":"ES",
    "sg:address":"Calle de Hilarion Eslava, 14",
    "sg:city":"Madrid",
    "sg:classifiers":[
        {
            "category":"Autos & Motor Vehicles",
            "subcategory":"Automobile Sales",
            "type":"Retail Goods"
        }
    ],
    "sg:phone":"+34 915 44 49 98",
    "sg:postcode":"28015",
    "sg:province":"Madrid",
    "wof:name":"Centro De Formacion Vial V N\u00ba 1 S.l.",
    "wof:placetype":"venue"
},
  "geometry": {"coordinates":[-3.7165770531,40.4335861206],"type":"Point"}
}