{
  "type": "Feature",
  "properties": {
    "addr:full":"Calle de Sarasate, 8 Roquetas Mar Almer\u00eda 04740",
    "addr:housenumber":"8",
    "addr:postcode":"04740",
    "addr:street":"Calle De Sarasate",
    "iso:country":"ES",
    "sg:address":"Calle de Sarasate, 8",
    "sg:city":"Roquetas Mar",
    "sg:orig_category":"Iglesia Cat\u00d3lica",
    "sg:phone":"+34 950 32 03 03",
    "sg:postcode":"04740",
    "sg:province":"Almer\u00eda",
    "wof:name":"Hijas De Jesus",
    "wof:placetype":"venue"
},
  "geometry": {"coordinates":[-2.6126389503,36.7624320984],"type":"Point"}
}