{
  "type": "Feature",
  "properties": {
    "iso:country":"ES",
    "sg:address":"Paloma, 5",
    "sg:city":"El Palmar",
    "sg:orig_category":"Agencias Y Agentes Comerciales, Representantes",
    "sg:phone":"+34 968 88 18 23",
    "sg:postcode":"30120",
    "sg:province":"Murcia",
    "wof:name":"Abril Marin Jose",
    "wof:placetype":"venue"
},
  "geometry": {"coordinates":[-1.145769,37.940346],"type":"Point"}
}