{
  "type": "Feature",
  "properties": {
    "iso:country":"ES",
    "sg:address":"Calle de Ruise\u00d1or, 25",
    "sg:city":"Madridejos",
    "sg:orig_category":"Promotores Constructores",
    "sg:phone":"+34 925 46 17 30",
    "sg:postcode":"45710",
    "sg:province":"Toledo",
    "wof:name":"Cygni 61 S.l.",
    "wof:placetype":"venue"
},
  "geometry": {"coordinates":[-3.5252370834,39.4653778076],"type":"Point"}
}