{
  "type": "Feature",
  "properties": {
    "iso:country":"ES",
    "sg:address":"Carrer de Gorchs Llado, 16",
    "sg:city":"Barbera Valles",
    "sg:orig_category":"Ferreter\u00cda (diversos)",
    "sg:phone":"+34 937 18 68 05",
    "sg:postcode":"08210",
    "sg:province":"Barcelona",
    "wof:name":"Ferrelles De Lleida S.l.",
    "wof:placetype":"venue"
},
  "geometry": {"coordinates":[2.1271760464,41.5150566101],"type":"Point"}
}