{
  "type": "Feature",
  "properties": {
    "iso:country":"ES",
    "sg:address":"Calle de Ferrocarril, 20",
    "sg:city":"Valladolid",
    "sg:orig_category":"Abogados",
    "sg:phone":"+34 983 21 38 22",
    "sg:postcode":"47004",
    "sg:province":"Valladolid",
    "wof:name":"Fernandez Morillo Antonio Pedro",
    "wof:placetype":"venue"
},
  "geometry": {"coordinates":[-4.7235021591,41.6448631287],"type":"Point"}
}