{
  "type": "Feature",
  "properties": {
    "addr:full":"Granollers, 2 Pla Del Bon Aire Barcelona 08225",
    "addr:housenumber":"2",
    "addr:postcode":"08225",
    "addr:street":"Granollers",
    "iso:country":"ES",
    "sg:address":"Granollers, 2",
    "sg:city":"Pla Del Bon Aire",
    "sg:orig_category":"Alimentaci\u00d3n General (al Por Menor)",
    "sg:phone":"+34 937 35 02 98",
    "sg:postcode":"08225",
    "sg:province":"Barcelona",
    "wof:name":"Utiel Blanes Dolores",
    "wof:placetype":"venue"
},
  "geometry": {"coordinates":[1.9797079563,41.5738563538],"type":"Point"}
}