{
  "type": "Feature",
  "properties": {
    "iso:country":"ES",
    "sg:address":"Calle de Colon, 11",
    "sg:city":"Vecindario",
    "sg:orig_category":"Pescader\u00cdas (al Por Menor)",
    "sg:phone":"+34 928 75 12 53",
    "sg:postcode":"35110",
    "sg:province":"Las Palmas",
    "wof:name":"Perez Perez Pedro Serafin",
    "wof:placetype":"venue"
},
  "geometry": {"coordinates":[-15.4403123856,27.8499851227],"type":"Point"}
}