{
  "type": "Feature",
  "properties": {
    "iso:country":"ES",
    "sg:address":"Plaz San Agustin, 1",
    "sg:city":"San Andres",
    "sg:orig_category":"Internados & Ense\u00d1anza Privada",
    "sg:phone":"+34 968 29 19 76",
    "sg:postcode":"30005",
    "sg:province":"Murcia",
    "wof:name":"Colegio El Buen Pastor S.l.",
    "wof:placetype":"venue"
},
  "geometry": {"coordinates":[-1.1302499771,37.9829597473],"type":"Point"}
}