{
  "type": "Feature",
  "properties": {
    "iso:country":"ES",
    "sg:address":"Calle de Cervantes, 67",
    "sg:city":"Pilas",
    "sg:orig_category":"Persianas Interiores, Exteriores",
    "sg:phone":"+34 954 75 02 01",
    "sg:postcode":"41840",
    "sg:province":"Sevilla",
    "wof:name":"Gonzalez Diaz Antonio",
    "wof:placetype":"venue"
},
  "geometry": {"coordinates":[-6.2950973511,37.3046455383],"type":"Point"}
}