{
  "type": "Feature",
  "properties": {
    "addr:full":"Pg Muntanya, 90 Granollers Barcelona 08402",
    "addr:housenumber":"90",
    "addr:postcode":"08402",
    "addr:street":"Pg Muntanya",
    "iso:country":"ES",
    "sg:address":"Pg Muntanya, 90",
    "sg:city":"Granollers",
    "sg:orig_category":"Ingeniero",
    "sg:phone":"+34 938 79 35 90",
    "sg:postcode":"08402",
    "sg:province":"Barcelona",
    "wof:name":"Garrote Jurado Manuela",
    "wof:placetype":"venue"
},
  "geometry": {"coordinates":[2.2936611176,41.6083831787],"type":"Point"}
}