{
  "type": "Feature",
  "properties": {
    "iso:country":"ES",
    "sg:address":"Carrer de Pelai, 52",
    "sg:city":"Barcelona",
    "sg:orig_category":"Empresas De Portes Y Mensajer\u00cda",
    "sg:phone":"+34 934 12 63 69",
    "sg:postcode":"08001",
    "sg:province":"Barcelona",
    "wof:name":"Lbc Mundial Europa S.a.",
    "wof:placetype":"venue"
},
  "geometry": {"coordinates":[2.1687970161,41.3854484558],"type":"Point"}
}