{
  "type": "Feature",
  "properties": {
    "iso:country":"ES",
    "sg:address":"Calle de Fuentezuela (de La), 69",
    "sg:city":"Villamartin",
    "sg:orig_category":"Electricidad: Instaladores",
    "sg:phone":"+34 956 73 33 85",
    "sg:postcode":"11650",
    "sg:province":"C\u00e1diz",
    "wof:name":"Electrificaciones Gefindel,s.l.l",
    "wof:placetype":"venue"
},
  "geometry": {"coordinates":[-5.6440691948,36.8629989624],"type":"Point"}
}