{
  "type": "Feature",
  "properties": {
    "iso:country":"ES",
    "sg:address":"Carrer de (p I Store), S/n",
    "sg:city":"Sevilla",
    "sg:orig_category":"Empresas De Portes Y Mensajer\u00cda",
    "sg:phone":"+34 954 43 61 50",
    "sg:postcode":"41008",
    "sg:province":"Sevilla",
    "wof:name":"Andalupaq Express S.l.",
    "wof:placetype":"venue"
},
  "geometry": {"coordinates":[-5.9647536278,37.405921936],"type":"Point"}
}