{
  "type": "Feature",
  "properties": {
    "iso:country":"ES",
    "sg:address":"Calle de Doctor Sapena, 3",
    "sg:city":"Castalla",
    "sg:orig_category":"M\u00c1quinas De Coser Y De Hacer Punto (al Por Mayor)",
    "sg:phone":"+34 966 56 04 83",
    "sg:postcode":"03420",
    "sg:province":"Alicante",
    "wof:name":"Rico Perez Eva Maria",
    "wof:placetype":"venue"
},
  "geometry": {"coordinates":[-0.6724337935,38.5941886902],"type":"Point"}
}