{
  "type": "Feature",
  "properties": {
    "addr:full":"Calle de Maestro Valle, 22 Palmas De Gran Canaria Las Palmas 35005",
    "addr:postcode":"35005",
    "addr:street":"Calle De Maestro Valle 22",
    "iso:country":"ES",
    "sg:address":"Calle de Maestro Valle, 22",
    "sg:city":"Palmas De Gran Canaria",
    "sg:orig_category":"Inversiones",
    "sg:phone":"+34 928 24 01 71",
    "sg:postcode":"35005",
    "sg:province":"Las Palmas",
    "wof:name":"Inversiones Rial S.l.",
    "wof:placetype":"venue"
},
  "geometry": {"coordinates":[-15.432100296,28.1263313293],"type":"Point"}
}