{
  "type": "Feature",
  "properties": {
    "addr:full":"Calle de Raya De Velilla (de La), 4 Raya De Velilla Madrid 28840",
    "addr:postcode":"28840",
    "addr:street":"Calle De Raya De Velilla De La 4 Raya De",
    "iso:country":"ES",
    "sg:address":"Calle de Raya De Velilla (de La), 4",
    "sg:city":"Raya De Velilla",
    "sg:orig_category":"Empresas De Carpinter\u00cda De Madera",
    "sg:phone":"+34 916 68 28 00",
    "sg:postcode":"28840",
    "sg:province":"Madrid",
    "wof:name":"Moviarte S.l.",
    "wof:placetype":"venue"
},
  "geometry": {"coordinates":[-3.4838440418,40.3967437744],"type":"Point"}
}