{
  "type": "Feature",
  "properties": {
    "addr:full":"Carrer de Lliri, 7 Granollers Barcelona 08402",
    "addr:housenumber":"7",
    "addr:postcode":"08402",
    "addr:street":"Carrer De Lliri",
    "iso:country":"ES",
    "sg:address":"Carrer de Lliri, 7",
    "sg:city":"Granollers",
    "sg:orig_category":"Confecci\u00d3n De Trajes Para Se\u00d1oras",
    "sg:phone":"+34 938 79 11 84",
    "sg:postcode":"08402",
    "sg:province":"Barcelona",
    "wof:name":"Garcia Reche Montserrat",
    "wof:placetype":"venue"
},
  "geometry": {"coordinates":[2.2891139984,41.6058044434],"type":"Point"}
}