{
  "type": "Feature",
  "properties": {
    "addr:full":"G.v. Corts Catalanes, 439 Barcelona Barcelona 08015",
    "addr:housenumber":"439",
    "addr:postcode":"08015",
    "addr:street":"Catalanes",
    "iso:country":"ES",
    "sg:address":"G.v. Corts Catalanes, 439",
    "sg:city":"Barcelona",
    "sg:orig_category":"M\u00c9dicos: Ginecolog\u00cda M\u00c9dica, Obstetricia",
    "sg:phone":"+34 934 26 65 59",
    "sg:postcode":"08015",
    "sg:province":"Barcelona",
    "wof:name":"Tasco Sociedad Cooperativa Catalana De Responsabilidad Limitada",
    "wof:placetype":"venue"
},
  "geometry": {"coordinates":[2.1532709599,41.3785858154],"type":"Point"}
}