{
  "type": "Feature",
  "properties": {
    "iso:country":"ES",
    "sg:address":"Cmno Ronda (de), 114",
    "sg:city":"Granada",
    "sg:orig_category":"Promotores Constructores",
    "sg:phone":"+34 958 25 59 80",
    "sg:postcode":"18004",
    "sg:province":"Granada",
    "wof:name":"Construcciones Navarro Y Machado S.a.",
    "wof:placetype":"venue"
},
  "geometry": {"coordinates":[-3.6079719067,37.1741027832],"type":"Point"}
}