{
  "type": "Feature",
  "properties": {
    "iso:country":"ES",
    "sg:address":"Calle de Altozano, 24",
    "sg:city":"Villa Don Fadrique",
    "sg:orig_category":"Molduras, Junquillos, Listones Y Molduras Perforadas",
    "sg:phone":"+34 925 19 51 27",
    "sg:postcode":"45850",
    "sg:province":"Toledo",
    "wof:name":"Pascual Cidon Isaias",
    "wof:placetype":"venue"
},
  "geometry": {"coordinates":[-3.2158739567,39.6146888733],"type":"Point"}
}