{
  "type": "Feature",
  "properties": {
    "addr:full":"Carrer de Igualada, 48 Vilafranca Penedes Barcelona 08720",
    "addr:housenumber":"48",
    "addr:postcode":"08720",
    "addr:street":"Carrer De Igualada;Penedes Barcelona",
    "iso:country":"ES",
    "sg:address":"Carrer de Igualada, 48",
    "sg:city":"Vilafranca Penedes",
    "sg:orig_category":"Farmacias",
    "sg:phone":"+34 938 18 15 81",
    "sg:postcode":"08720",
    "sg:province":"Barcelona",
    "wof:name":"Cuadras Vidal Maria Antonia",
    "wof:placetype":"venue"
},
  "geometry": {"coordinates":[1.7036459446,41.3487434387],"type":"Point"}
}