{
  "type": "Feature",
  "properties": {
    "iso:country":"ES",
    "sg:address":"Latsunbe Auzoa, 7",
    "sg:city":"Hernani",
    "sg:orig_category":"Servicios Diversos",
    "sg:phone":"+34 943 33 10 20",
    "sg:postcode":"20120",
    "sg:province":"Guip\u00f9zcoa",
    "wof:name":"Funeraria Orbegozo S.l.",
    "wof:placetype":"venue"
},
  "geometry": {"coordinates":[-1.9752269983,43.2687721252],"type":"Point"}
}