{
  "type": "Feature",
  "properties": {
    "iso:country":"ES",
    "sg:address":"Carr Magnolies, 10",
    "sg:city":"Igualada",
    "sg:orig_category":"Confecci\u00d3n (fabricaci\u00d3n, Al Por Mayor)",
    "sg:phone":"+34 938 03 02 28",
    "sg:postcode":"08700",
    "sg:province":"Barcelona",
    "wof:name":"Kiper Logistic Nes S.l.",
    "wof:placetype":"venue"
},
  "geometry": {"coordinates":[1.6323828697,41.5807647705],"type":"Point"}
}