{
  "type": "Feature",
  "properties": {
    "addr:full":"Avda Rio Segura, 3 Carmen Murcia 30002",
    "addr:housenumber":"3",
    "addr:postcode":"30002",
    "addr:street":"Avda Rio Segura",
    "iso:country":"ES",
    "sg:address":"Avda Rio Segura, 3",
    "sg:city":"Carmen",
    "sg:orig_category":"Empresarios",
    "sg:phone":"+34 968 21 09 26",
    "sg:postcode":"30002",
    "sg:province":"Murcia",
    "wof:name":"Gestion Integral De Servicios Inmobiliarios 2000 S.l.",
    "wof:placetype":"venue"
},
  "geometry": {"coordinates":[-1.1302499771,37.9829597473],"type":"Point"}
}