{
  "type": "Feature",
  "properties": {
    "addr:full":"Rua Dr. Gonzalez Sierra, 1 Vigo Pontevedra 36211",
    "addr:housenumber":"1",
    "addr:postcode":"36211",
    "addr:street":"Rua Dr. Gonzalez Sierra",
    "iso:country":"ES",
    "sg:address":"Rua Dr. Gonzalez Sierra, 1",
    "sg:city":"Vigo",
    "sg:orig_category":"Bisuter\u00cda, Joyer\u00cda, Relojer\u00cda (al Por Menor)",
    "sg:phone":"+34 986 23 46 31",
    "sg:postcode":"36211",
    "sg:province":"Pontevedra",
    "wof:name":"A.r.s.longa J.m.g. S.l.",
    "wof:placetype":"venue"
},
  "geometry": {"coordinates":[-8.7317943573,42.2215270996],"type":"Point"}
}