{
  "type": "Feature",
  "properties": {
    "iso:country":"ES",
    "sg:address":"Calle de Alemania, 57",
    "sg:city":"Zuera",
    "sg:orig_category":"Productos Qu\u00cdmicos (fabricaci\u00d3n, Al Por Mayor)",
    "sg:phone":"+34 976 68 08 79",
    "sg:postcode":"50800",
    "sg:province":"Zaragoza",
    "wof:name":"Union Derivan.s.a.",
    "wof:placetype":"venue"
},
  "geometry": {"coordinates":[-0.7879765034,41.8926277161],"type":"Point"}
}