{
  "type": "Feature",
  "properties": {
    "addr:full":"Calle de Malecon, 12 Mazarron Murcia 30870",
    "addr:housenumber":"12",
    "addr:postcode":"30870",
    "addr:street":"Calle De Malecon",
    "iso:country":"ES",
    "sg:address":"Calle de Malecon, 12",
    "sg:city":"Mazarron",
    "sg:orig_category":"Loter\u00cda Y T\u00d3mbola",
    "sg:phone":"+34 968 59 01 50",
    "sg:postcode":"30870",
    "sg:province":"Murcia",
    "wof:name":"Navarro Lucas Catalina",
    "wof:placetype":"venue"
},
  "geometry": {"coordinates":[-1.3145270348,37.5989875793],"type":"Point"}
}