{
  "type": "Feature",
  "properties": {
    "iso:country":"ES",
    "sg:address":"Rua Progreso (do), 151",
    "sg:city":"Ourense",
    "sg:orig_category":"Abogados",
    "sg:phone":"+34 988 37 08 43",
    "sg:postcode":"32003",
    "sg:province":"Ourense",
    "wof:name":"X.b. Torres & Asociados S.l.",
    "wof:placetype":"venue"
},
  "geometry": {"coordinates":[-7.8677039146,42.3416938782],"type":"Point"}
}