{
  "type": "Feature",
  "properties": {
    "iso:country":"ES",
    "sg:address":"Avda Europa (de), 28",
    "sg:city":"Gines",
    "sg:orig_category":"Electrodom\u00c9sticos (al Por Menor)",
    "sg:phone":"+34 954 71 90 86",
    "sg:postcode":"41960",
    "sg:province":"Sevilla",
    "wof:name":"Stok Factory S.l.",
    "wof:placetype":"venue"
},
  "geometry": {"coordinates":[-6.0726041794,37.3845481873],"type":"Point"}
}