{
  "type": "Feature",
  "properties": {
    "iso:country":"ES",
    "sg:address":"Calle de Carril, S/n",
    "sg:city":"Bubion",
    "sg:orig_category":"Institutos M\u00c9dicos",
    "sg:phone":"+34 958 76 33 74",
    "sg:postcode":"18412",
    "sg:province":"Granada",
    "wof:name":"Servicio Andaluz De Salud",
    "wof:placetype":"venue"
},
  "geometry": {"coordinates":[-3.355191946,36.9488677979],"type":"Point"}
}