{
  "type": "Feature",
  "properties": {
    "iso:country":"ES",
    "sg:address":"Ctra Callosa, S/n",
    "sg:city":"Rafal",
    "sg:orig_category":"Zapater\u00cds Y Cordeler\u00cda",
    "sg:phone":"+34 966 75 20 99",
    "sg:postcode":"03369",
    "sg:province":"Alicante",
    "wof:name":"Cordeleria Siguenza S.coop.v",
    "wof:placetype":"venue"
},
  "geometry": {"coordinates":[-0.8546590209,38.1019706726],"type":"Point"}
}