{
  "type": "Feature",
  "properties": {
    "addr:full":"Pl Sant Joan, 6 Cardedeu Barcelona 08440",
    "addr:housenumber":"6",
    "addr:postcode":"08440",
    "addr:street":"Pl Sant Joan",
    "iso:country":"ES",
    "sg:address":"Pl Sant Joan, 6",
    "sg:city":"Cardedeu",
    "sg:orig_category":"Cajas De Ahorro",
    "sg:phone":"+34 938 44 45 03",
    "sg:postcode":"08440",
    "sg:province":"Barcelona",
    "wof:name":"Caixa De Girona",
    "wof:placetype":"venue"
},
  "geometry": {"coordinates":[2.3551700115,41.6379776001],"type":"Point"}
}