{
  "type": "Feature",
  "properties": {
    "iso:country":"ES",
    "sg:address":"Carrer de Garraf, 4",
    "sg:city":"Cornella Llobregat",
    "sg:orig_category":"M\u00c9dicos: Estomatolog\u00cda",
    "sg:phone":"+34 933 75 49 69",
    "sg:postcode":"08940",
    "sg:province":"Barcelona",
    "wof:name":"Bonilla Trujillo Maria Paz",
    "wof:placetype":"venue"
},
  "geometry": {"coordinates":[2.0708940029,41.3559417725],"type":"Point"}
}