{
  "type": "Feature",
  "properties": {
    "iso:country":"ES",
    "sg:address":"Ronda Dels Docks, 18",
    "sg:city":"Tortosa",
    "sg:orig_category":"Frutas Y Legumbres Frescas (al Por Mayor)",
    "sg:phone":"+34 977 44 11 99",
    "sg:postcode":"43500",
    "sg:province":"Tarragona",
    "wof:name":"Ventura Reves Jose",
    "wof:placetype":"venue"
},
  "geometry": {"coordinates":[0.5213069916,40.8078231812],"type":"Point"}
}