{
  "type": "Feature",
  "properties": {
    "addr:full":"Calle de Cochabamba, 1 Palmas De Gran Canaria Las Palmas 35008",
    "addr:housenumber":"1",
    "addr:postcode":"35008",
    "addr:street":"Calle De Cochabamba",
    "iso:country":"ES",
    "sg:address":"Calle de Cochabamba, 1",
    "sg:city":"Palmas De Gran Canaria",
    "sg:orig_category":"Distribuci\u00d3n De Petr\u00d3leo Y Derivados",
    "sg:phone":"+34 928 46 64 86",
    "sg:postcode":"35008",
    "sg:province":"Las Palmas",
    "wof:name":"Industrias Los Berrasales Sl",
    "wof:placetype":"venue"
},
  "geometry": {"coordinates":[-15.4188213348,28.1539897919],"type":"Point"}
}