{
  "type": "Feature",
  "properties": {
    "iso:country":"ES",
    "sg:address":"Avda Italia (de), S/n",
    "sg:city":"Playa Del Ingles",
    "sg:orig_category":"Farmacias",
    "sg:phone":"+34 928 76 21 83",
    "sg:postcode":"35100",
    "sg:province":"Las Palmas",
    "wof:name":"Ruano Aleman Maria Victoria",
    "wof:placetype":"venue"
},
  "geometry": {"coordinates":[-15.5667285919,27.7604503632],"type":"Point"}
}