{
  "type": "Feature",
  "properties": {
    "iso:country":"ES",
    "sg:address":"Eras Montalban, 2",
    "sg:city":"Teruel",
    "sg:orig_category":"Guarder\u00cdas",
    "sg:phone":"+34 978 60 86 53",
    "sg:postcode":"44003",
    "sg:province":"Teruel",
    "wof:name":"Concepcion Soriano Domingo Y Montserrat Domingo Barrera Cdad",
    "wof:placetype":"venue"
},
  "geometry": {"coordinates":[-1.1078549623,40.3486976624],"type":"Point"}
}