{
  "type": "Feature",
  "properties": {
    "addr:full":"Calle de Carteros, 80 Valencia Valencia 46017",
    "addr:housenumber":"80",
    "addr:postcode":"46017",
    "addr:street":"Calle De Carteros",
    "iso:country":"ES",
    "sg:address":"Calle de Carteros, 80",
    "sg:city":"Valencia",
    "sg:orig_category":"\u00d3ptica: Instrumentos (fabricaci\u00d3n)",
    "sg:phone":"+34 963 58 72 96",
    "sg:postcode":"46017",
    "sg:province":"Valencia",
    "wof:name":"Centros De Vision Catarroja S.l.",
    "wof:placetype":"venue"
},
  "geometry": {"coordinates":[-0.3895739019,39.4484024048],"type":"Point"}
}