{
  "type": "Feature",
  "properties": {
    "iso:country":"ES",
    "sg:address":"Calle de Orden Calatrava, 1",
    "sg:city":"Consuegra",
    "sg:orig_category":"Asociaciones Y Clubs Deportivos",
    "sg:phone":"+34 925 47 56 46",
    "sg:postcode":"45700",
    "sg:province":"Toledo",
    "wof:name":"Gimnasio Santa Cruz",
    "wof:placetype":"venue"
},
  "geometry": {"coordinates":[-3.6030669212,39.4615058899],"type":"Point"}
}