{
  "type": "Feature",
  "properties": {
    "iso:country":"ES",
    "sg:address":"Carrer de Carrer de Quinientos Uno, Km. 0099,5",
    "sg:city":"Iglesuela",
    "sg:orig_category":"Fabrica De Cer\u00c1micas",
    "sg:phone":"+34 925 59 72 49",
    "sg:postcode":"45633",
    "sg:province":"Toledo",
    "wof:name":"Registro Centro Formacion S.l.",
    "wof:placetype":"venue"
},
  "geometry": {"coordinates":[-4.7486991882,40.2333183289],"type":"Point"}
}