{
  "type": "Feature",
  "properties": {
    "iso:country":"ES",
    "sg:address":"Calle de Mayor, 13",
    "sg:city":"Guadalajara",
    "sg:orig_category":"Asesor\u00cda Fiscal Y Jur\u00cddica",
    "sg:phone":"+34 949 21 42 69",
    "sg:postcode":"19001",
    "sg:province":"Guadalajara",
    "wof:name":"Asesoria Alcarria S.l.",
    "wof:placetype":"venue"
},
  "geometry": {"coordinates":[-3.1663808823,40.6331253052],"type":"Point"}
}