{
  "type": "Feature",
  "properties": {
    "iso:country":"ES",
    "sg:address":"Calle de Luis De Morales, 32",
    "sg:city":"Sevilla",
    "sg:orig_category":"Propiedad Industrial: Patentes De Inventos, Marcas, Modelos, Dise\u00d1os",
    "sg:phone":"+34 954 53 11 29",
    "sg:postcode":"41018",
    "sg:province":"Sevilla",
    "wof:name":"Hispaten S.c.",
    "wof:placetype":"venue"
},
  "geometry": {"coordinates":[-5.9725461006,37.3867874146],"type":"Point"}
}