{
  "type": "Feature",
  "properties": {
    "addr:full":"Aldea Sampayo, S/n Barral Ourense 32232",
    "addr:housenumber":"s / n",
    "addr:postcode":"32232",
    "iso:country":"ES",
    "sg:address":"Aldea Sampayo, S/n",
    "sg:city":"Barral",
    "sg:orig_category":"Empresas De Electricidad En General",
    "sg:phone":"+34 988 47 17 50",
    "sg:postcode":"32232",
    "sg:province":"Ourense",
    "wof:name":"Tecnicas Y Servicios Energeticos De Galicia S.l.",
    "wof:placetype":"venue"
},
  "geometry": {"coordinates":[-8.0928001404,42.2942886353],"type":"Point"}
}