{
  "type": "Feature",
  "properties": {
    "addr:full":"Calle de Mayor, 4 Puebla Hijar Teruel 44510",
    "addr:housenumber":"4",
    "addr:postcode":"44510",
    "addr:street":"Calle De Mayor",
    "iso:country":"ES",
    "sg:address":"Calle de Mayor, 4",
    "sg:city":"Puebla Hijar",
    "sg:orig_category":"Molduras, Junquillos, Listones Y Molduras Perforadas",
    "sg:phone":"+34 978 82 65 33",
    "sg:postcode":"44510",
    "sg:province":"Teruel",
    "wof:name":"Palacios Calvo Sixto",
    "wof:placetype":"venue"
},
  "geometry": {"coordinates":[-0.4456360042,41.2127952576],"type":"Point"}
}