{
  "type": "Feature",
  "properties": {
    "iso:country":"ES",
    "sg:address":"Ctra Zaragoza Castellon, 82",
    "sg:city":"Quinto",
    "sg:orig_category":"Material Y Herramientas Agr\u00cdcolas",
    "sg:phone":"+34 976 17 60 69",
    "sg:postcode":"50770",
    "sg:province":"Zaragoza",
    "wof:name":"Agro-zaragoza S. A.",
    "wof:placetype":"venue"
},
  "geometry": {"coordinates":[-0.544691205,41.4199409485],"type":"Point"}
}