{
  "type": "Feature",
  "properties": {
    "addr:full":"Calle de Las Hilanderas, 29 Entrepinos Valladolid 47130",
    "addr:housenumber":"29",
    "addr:postcode":"47130",
    "addr:street":"Calle De Las Hilanderas",
    "iso:country":"ES",
    "sg:address":"Calle de Las Hilanderas, 29",
    "sg:city":"Entrepinos",
    "sg:orig_category":"Empresas De Limpieza",
    "sg:phone":"+34 983 59 09 39",
    "sg:postcode":"47130",
    "sg:province":"Valladolid",
    "wof:name":"Control Y Eficacia S.l.",
    "wof:placetype":"venue"
},
  "geometry": {"coordinates":[-4.8418688774,41.5700416565],"type":"Point"}
}