{
  "type": "Feature",
  "properties": {
    "addr:full":"Avda Paskual Abaroa Etorbidea, 3 Lekeitio Vizcaya 48280",
    "addr:housenumber":"3",
    "addr:postcode":"48280",
    "addr:street":"Avda Paskual Abaroa Etorbidea",
    "iso:country":"ES",
    "sg:address":"Avda Paskual Abaroa Etorbidea, 3",
    "sg:city":"Lekeitio",
    "sg:orig_category":"Abogados",
    "sg:phone":"+34 946 84 29 68",
    "sg:postcode":"48280",
    "sg:province":"Vizcaya",
    "wof:name":"Lekeitioko Udala",
    "wof:placetype":"venue"
},
  "geometry": {"coordinates":[-2.5054929256,43.3624382019],"type":"Point"}
}