{
  "type": "Feature",
  "properties": {
    "iso:country":"ES",
    "sg:address":"Cala Flores, S/n",
    "sg:city":"Cabo Palos",
    "sg:orig_category":"Promotores Constructores",
    "sg:phone":"+34 968 56 34 40",
    "sg:postcode":"30370",
    "sg:province":"Murcia",
    "wof:name":"Lozano Conesa Alejandro",
    "wof:placetype":"venue"
},
  "geometry": {"coordinates":[-1.1270929575,37.9735908508],"type":"Point"}
}