{
  "type": "Feature",
  "properties": {
    "addr:full":"Barr San Antonio, 24 Langreo Asturias 33900",
    "addr:housenumber":"24",
    "addr:postcode":"33900",
    "addr:street":"San Antonio",
    "iso:country":"ES",
    "sg:address":"Barr San Antonio, 24",
    "sg:city":"Langreo",
    "sg:orig_category":"Promotores Constructores",
    "sg:phone":"+34 985 67 62 13",
    "sg:postcode":"33900",
    "sg:province":"Asturias",
    "wof:name":"Moreno Menendez Maria Magdalena",
    "wof:placetype":"venue"
},
  "geometry": {"coordinates":[-5.6704487801,43.2859611511],"type":"Point"}
}