{
  "type": "Feature",
  "properties": {
    "iso:country":"ES",
    "sg:address":"Send Los Canonigos, 11",
    "sg:city":"Vitoria-gasteiz",
    "sg:orig_category":"Asesor\u00cda De Formaci\u00d3n Y Gesti\u00d3n De Personal",
    "sg:phone":"+34 945 25 72 44",
    "sg:postcode":"01002",
    "sg:province":"\u00c1lava",
    "wof:name":"Aser 51 S.c.",
    "wof:placetype":"venue"
},
  "geometry": {"coordinates":[-2.6623649597,42.85364151],"type":"Point"}
}