{
  "type": "Feature",
  "properties": {
    "iso:country":"ES",
    "sg:address":"C/ Arnedo, 14",
    "sg:city":"Elche",
    "sg:orig_category":"Confecci\u00d3n De Zapatos",
    "sg:phone":"+34 966 66 50 30",
    "sg:postcode":"03205",
    "sg:province":"Alicante",
    "wof:name":"Tdm Socks S.l.",
    "wof:placetype":"venue"
},
  "geometry": {"coordinates":[-0.7166770101,38.2830886841],"type":"Point"}
}