{
  "type": "Feature",
  "properties": {
    "addr:full":"Trva America 3, 13 Estrada Pontevedra 36680",
    "addr:housenumber":"3 13",
    "addr:postcode":"36680",
    "addr:street":"Trva America;Estrada Pontevedra",
    "iso:country":"ES",
    "sg:address":"Trva America 3, 13",
    "sg:city":"Estrada",
    "sg:orig_category":"Florister\u00cdas",
    "sg:phone":"+34 986 57 35 23",
    "sg:postcode":"36680",
    "sg:province":"Pontevedra",
    "wof:name":"Codesido Somoza Milagros",
    "wof:placetype":"venue"
},
  "geometry": {"coordinates":[-8.4957618713,42.6893882751],"type":"Point"}
}