{
  "type": "Feature",
  "properties": {
    "addr:full":"Carrer de Seneca, 26 Barcelona Barcelona 08006",
    "addr:housenumber":"26",
    "addr:postcode":"08006",
    "addr:street":"Carrer De Seneca",
    "iso:country":"ES",
    "sg:address":"Carrer de Seneca, 26",
    "sg:city":"Barcelona",
    "sg:orig_category":"Aparcamientos (infraestructuras, Accesorios)",
    "sg:phone":"+34 932 17 13 02",
    "sg:postcode":"08006",
    "sg:province":"Barcelona",
    "wof:name":"Nieves Garcia Primitivo",
    "wof:placetype":"venue"
},
  "geometry": {"coordinates":[2.1555879116,41.3966255188],"type":"Point"}
}