{
  "type": "Feature",
  "properties": {
    "addr:full":"Ctra Cabra, 54 Lucena C\u00f3rdoba 14900",
    "addr:housenumber":"54",
    "addr:postcode":"14900",
    "addr:street":"Ctra Cabra",
    "iso:country":"ES",
    "sg:address":"Ctra Cabra, 54",
    "sg:city":"Lucena",
    "sg:orig_category":"Promotores Constructores",
    "sg:phone":"+34 957 50 37 50",
    "sg:postcode":"14900",
    "sg:province":"C\u00f3rdoba",
    "wof:name":"Construcciones Granadal S.l.",
    "wof:placetype":"venue"
},
  "geometry": {"coordinates":[-4.4833388329,37.42137146],"type":"Point"}
}