{
  "type": "Feature",
  "properties": {
    "addr:full":"Carrer de Manuel Marine, 11 Cornella Llobregat Barcelona 08940",
    "addr:housenumber":"11",
    "addr:postcode":"08940",
    "addr:street":"Carrer De Manuel Marine",
    "iso:country":"ES",
    "sg:address":"Carrer de Manuel Marine, 11",
    "sg:city":"Cornella Llobregat",
    "sg:orig_category":"Internados & Ense\u00d1anza Privada",
    "sg:phone":"+34 933 76 19 49",
    "sg:postcode":"08940",
    "sg:province":"Barcelona",
    "wof:name":"Misioneras De La Institucion Claretiana",
    "wof:placetype":"venue"
},
  "geometry": {"coordinates":[2.0781109333,41.3657073975],"type":"Point"}
}