{
  "type": "Feature",
  "properties": {
    "addr:full":"Calle de Zamakoa, 10 Kurtzea Vizcaya 48960",
    "addr:housenumber":"10",
    "addr:postcode":"48960",
    "addr:street":"Calle De Zamakoa",
    "iso:country":"ES",
    "sg:address":"Calle de Zamakoa, 10",
    "sg:city":"Kurtzea",
    "sg:orig_category":"Farmacias",
    "sg:phone":"+34 944 56 49 04",
    "sg:postcode":"48960",
    "sg:province":"Vizcaya",
    "wof:name":"Perez Gabiola Maitane",
    "wof:placetype":"venue"
},
  "geometry": {"coordinates":[-2.8425610065,43.2315940857],"type":"Point"}
}