{
  "type": "Feature",
  "properties": {
    "iso:country":"ES",
    "sg:address":"Jaume I, 58",
    "sg:city":"Potries",
    "sg:orig_category":"Servidores Y Editores De Bases De Datos",
    "sg:phone":"+34 962 89 90 41",
    "sg:postcode":"46721",
    "sg:province":"Valencia",
    "wof:name":"Ofloin S.l.u.",
    "wof:placetype":"venue"
},
  "geometry": {"coordinates":[-0.1931989938,38.916431427],"type":"Point"}
}