{
  "type": "Feature",
  "properties": {
    "addr:full":"Calle de Cristo De Los Milagros, 1 Salamanca Salamanca 37001",
    "addr:housenumber":"1",
    "addr:postcode":"37001",
    "addr:street":"Calle De Cristo De Los Milagros",
    "iso:country":"ES",
    "sg:address":"Calle de Cristo De Los Milagros, 1",
    "sg:city":"Salamanca",
    "sg:orig_category":"Abogados",
    "sg:phone":"+34 923 26 78 54",
    "sg:postcode":"37001",
    "sg:province":"Salamanca",
    "wof:name":"Tocino Hernandez Cesar Manuel",
    "wof:placetype":"venue"
},
  "geometry": {"coordinates":[-5.6595978737,40.9681053162],"type":"Point"}
}