{
  "type": "Feature",
  "properties": {
    "addr:full":"Calle de Iran, 20 Jerez De La Frontera C\u00e1diz 11406",
    "addr:housenumber":"20",
    "addr:postcode":"11406",
    "addr:street":"Calle De Iran",
    "iso:country":"ES",
    "sg:address":"Calle de Iran, 20",
    "sg:city":"Jerez De La Frontera",
    "sg:orig_category":"Contenedores (mercanc\u00cdas)",
    "sg:phone":"+34 956 34 95 57",
    "sg:postcode":"11406",
    "sg:province":"C\u00e1diz",
    "wof:name":"Transportes Y Aridos Lomopardo Sl",
    "wof:placetype":"venue"
},
  "geometry": {"coordinates":[-6.1199889183,36.6760597229],"type":"Point"}
}