{
  "type": "Feature",
  "properties": {
    "iso:country":"ES",
    "sg:address":"Avda Constantino Lopez, 14",
    "sg:city":"Alhama Murcia",
    "sg:orig_category":"\u00d3ptica: Instrumentos (fabricaci\u00d3n)",
    "sg:phone":"+34 968 63 20 70",
    "sg:postcode":"30840",
    "sg:province":"Murcia",
    "wof:name":"Optilent Alhama S.l.",
    "wof:placetype":"venue"
},
  "geometry": {"coordinates":[-1.4278520346,37.8511657715],"type":"Point"}
}