{
  "type": "Feature",
  "properties": {
    "iso:country":"ES",
    "sg:address":"Calle de Roa De La Vega, 12",
    "sg:city":"Le\u00f3n",
    "sg:orig_category":"Inmobiliaria (agencias)",
    "sg:phone":"+34 987 22 11 55",
    "sg:postcode":"24002",
    "sg:province":"Le\u00f3n",
    "wof:name":"Inmobiliaria Ana Diaz S.l.",
    "wof:placetype":"venue"
},
  "geometry": {"coordinates":[-5.5768389702,42.6006393433],"type":"Point"}
}