{
  "type": "Feature",
  "properties": {
    "addr:full":"Carr Josep Maria Bulto, 5 Vilanova I La Geltru Barcelona 08800",
    "addr:housenumber":"5",
    "addr:postcode":"08800",
    "addr:street":"Carr Josep Maria Bulto",
    "iso:country":"ES",
    "sg:address":"Carr Josep Maria Bulto, 5",
    "sg:city":"Vilanova I La Geltru",
    "sg:orig_category":"Promotores Constructores",
    "sg:phone":"+34 938 93 37 59",
    "sg:postcode":"08800",
    "sg:province":"Barcelona",
    "wof:name":"Promociones-construcciones Garcia Guallrt S.l.",
    "wof:placetype":"venue"
},
  "geometry": {"coordinates":[1.7361730337,41.2253990173],"type":"Point"}
}