{
  "type": "Feature",
  "properties": {
    "addr:full":"Calle de Cura (el), 15 Colmenar M\u00e1laga 29170",
    "addr:postcode":"29170",
    "addr:street":"Calle De Cura El;Colmenar",
    "iso:country":"ES",
    "sg:address":"Calle de Cura (el), 15",
    "sg:city":"Colmenar",
    "sg:orig_category":"Notarios",
    "sg:phone":"+34 952 73 10 55",
    "sg:postcode":"29170",
    "sg:province":"M\u00e1laga",
    "wof:name":"Toro Ariza Alvaro",
    "wof:placetype":"venue"
},
  "geometry": {"coordinates":[-4.3348197937,36.9043312073],"type":"Point"}
}