{
  "type": "Feature",
  "properties": {
    "addr:full":"Calle de Becerro De Bengoa, 8 Palencia Palencia 34002",
    "addr:housenumber":"8",
    "addr:postcode":"34002",
    "addr:street":"Calle De Becerro De Bengoa",
    "iso:country":"ES",
    "sg:address":"Calle de Becerro De Bengoa, 8",
    "sg:city":"Palencia",
    "sg:orig_category":"Ropa Y Accesorios",
    "sg:phone":"+34 979 70 62 67",
    "sg:postcode":"34002",
    "sg:province":"Palencia",
    "wof:name":"Vaydi C.b.",
    "wof:placetype":"venue"
},
  "geometry": {"coordinates":[-4.5314397812,42.0087928772],"type":"Point"}
}