{
  "type": "Feature",
  "properties": {
    "iso:country":"ES",
    "sg:address":"Ribera, 56",
    "sg:city":"Huelva",
    "sg:orig_category":"Procuradores",
    "sg:phone":"+34 959 27 00 66",
    "sg:postcode":"21002",
    "sg:province":"Huelva",
    "wof:name":"Adolfo Caballero C.b.",
    "wof:placetype":"venue"
},
  "geometry": {"coordinates":[-6.8444328308,37.2784309387],"type":"Point"}
}