{
  "type": "Feature",
  "properties": {
    "iso:country":"ES",
    "sg:address":"Calle de Cardenal Mendoza, 11",
    "sg:city":"Sig\u00fcenza",
    "sg:orig_category":"Cajas De Ahorro",
    "sg:phone":"+34 949 39 04 58",
    "sg:postcode":"19250",
    "sg:province":"Guadalajara",
    "wof:name":"Caja De Ahorros Y Monte De Piedad De Zaragoza Aragon Y Rioja",
    "wof:placetype":"venue"
},
  "geometry": {"coordinates":[-2.6434168816,41.0679931641],"type":"Point"}
}