{
  "type": "Feature",
  "properties": {
    "iso:country":"ES",
    "sg:address":"Calle de Emilio Castelar, 4",
    "sg:city":"Algeciras",
    "sg:orig_category":"Dietistas",
    "sg:phone":"+34 956 63 30 71",
    "sg:postcode":"11201",
    "sg:province":"C\u00e1diz",
    "sg:website":"www.naturhouse.com",
    "wof:name":"Fernandez Paulete Maria Araceli",
    "wof:placetype":"venue"
},
  "geometry": {"coordinates":[-5.4515581131,36.1358566284],"type":"Point"}
}