{
  "type": "Feature",
  "properties": {
    "iso:country":"ES",
    "sg:address":"Calle de Bernal Diaz De Luco, 8",
    "sg:city":"Vitoria-gasteiz",
    "sg:orig_category":"Suministros Y Materiales Industriales",
    "sg:phone":"+34 945 26 26 33",
    "sg:postcode":"01013",
    "sg:province":"\u00c1lava",
    "wof:name":"Suministros Electronicos Vitoria S.l.",
    "wof:placetype":"venue"
},
  "geometry": {"coordinates":[-2.6703751087,42.8565444946],"type":"Point"}
}