{
  "type": "Feature",
  "properties": {
    "iso:country":"ES",
    "sg:address":"Plastic, 5",
    "sg:city":"Badalona",
    "sg:orig_category":"Maquinaria Para Industrias Diversas",
    "sg:phone":"+34 934 30 48 05",
    "sg:postcode":"08912",
    "sg:province":"Barcelona",
    "sg:website":"www.eurocont.com",
    "wof:name":"Eurocomercial De Nuevas Tecnologias S. L.",
    "wof:placetype":"venue"
},
  "geometry": {"coordinates":[2.2529549599,41.4620780945],"type":"Point"}
}