{
  "type": "Feature",
  "properties": {
    "addr:full":"Carrer de Galanes, 42 Reus Tarragona 43201",
    "addr:housenumber":"42",
    "addr:postcode":"43201",
    "addr:street":"Carrer De Galanes",
    "iso:country":"ES",
    "sg:address":"Carrer de Galanes, 42",
    "sg:city":"Reus",
    "sg:orig_category":"Mercer\u00cda, Lencer\u00cda (al Por Menor)",
    "sg:phone":"+34 977 77 12 16",
    "sg:postcode":"43201",
    "sg:province":"Tarragona",
    "wof:name":"Garola Salvat Jaime",
    "wof:placetype":"venue"
},
  "geometry": {"coordinates":[1.1104589701,41.1561126709],"type":"Point"}
}