{
  "type": "Feature",
  "properties": {
    "addr:full":"Avda Gutierrez Mellado, 200 Molina Segura Murcia 30500",
    "addr:housenumber":"200",
    "addr:postcode":"30500",
    "addr:street":"Avda Gutierrez Mellado",
    "iso:country":"ES",
    "sg:address":"Avda Gutierrez Mellado, 200",
    "sg:city":"Molina Segura",
    "sg:orig_category":"Imprenta",
    "sg:phone":"+34 968 64 42 42",
    "sg:postcode":"30500",
    "sg:province":"Murcia",
    "wof:name":"Jose Maria Contreras Garcia Y Otros C.b.",
    "wof:placetype":"venue"
},
  "geometry": {"coordinates":[-1.2060970068,38.0644187927],"type":"Point"}
}