{
  "type": "Feature",
  "properties": {
    "addr:full":"Ctra Manlleu, Km. 0800,0 Vic Barcelona 08500",
    "addr:postcode":"08500",
    "addr:street":"Ctra Manlleu Km. 0800,0",
    "iso:country":"ES",
    "sg:address":"Ctra Manlleu, Km. 0800,0",
    "sg:city":"Vic",
    "sg:orig_category":"Muebles, Minoristas",
    "sg:phone":"+34 938 86 92 04",
    "sg:postcode":"08500",
    "sg:province":"Barcelona",
    "sg:website":"www.muebleslafabrica.com",
    "wof:name":"Mukali S.l",
    "wof:placetype":"venue"
},
  "geometry": {"coordinates":[2.2546598911,41.9376487732],"type":"Point"}
}