{
  "type": "Feature",
  "properties": {
    "addr:full":"Carrer de Bartrina, 222 Terrassa Barcelona 08226",
    "addr:housenumber":"222",
    "addr:postcode":"08226",
    "addr:street":"Carrer De Bartrina",
    "iso:country":"ES",
    "sg:address":"Carrer de Bartrina, 222",
    "sg:city":"Terrassa",
    "sg:orig_category":"Confecci\u00d3n (fabricaci\u00d3n, Al Por Mayor)",
    "sg:phone":"+34 937 83 47 13",
    "sg:postcode":"08226",
    "sg:province":"Barcelona",
    "wof:name":"Aparicio & Salmeron S.c.p.",
    "wof:placetype":"venue"
},
  "geometry": {"coordinates":[2.0242490768,41.5730056763],"type":"Point"}
}