{
  "type": "Feature",
  "properties": {
    "addr:full":"Calle de Urbano X, 9 Carmona Sevilla 41410",
    "addr:housenumber":"9",
    "addr:postcode":"41410",
    "addr:street":"Calle De Urbano X",
    "iso:country":"ES",
    "sg:address":"Calle de Urbano X, 9",
    "sg:city":"Carmona",
    "sg:orig_category":"Lavado, Limpieza De Veh\u00cdculos",
    "sg:phone":"+34 954 14 14 22",
    "sg:postcode":"41410",
    "sg:province":"Sevilla",
    "wof:name":"Lavados Y Neumaticos Villa Rosa S.l.",
    "wof:placetype":"venue"
},
  "geometry": {"coordinates":[-5.6549258232,37.4643669128],"type":"Point"}
}