{
  "type": "Feature",
  "properties": {
    "addr:full":"Ctra Madrid, Km. 0061,0 Olias Rey Toledo 45280",
    "addr:postcode":"45280",
    "addr:street":"Ctra Madrid Km. 0061,0 Olias Rey",
    "iso:country":"ES",
    "sg:address":"Ctra Madrid, Km. 0061,0",
    "sg:city":"Olias Rey",
    "sg:orig_category":"Carnicer\u00cdas, Carnicer\u00cdas",
    "sg:phone":"+34 925 49 00 47",
    "sg:postcode":"45280",
    "sg:province":"Toledo",
    "wof:name":"Secaderos De Almaguer S.a.",
    "wof:placetype":"venue"
},
  "geometry": {"coordinates":[-3.9885389805,39.9435043335],"type":"Point"}
}