{
  "type": "Feature",
  "properties": {
    "addr:full":"Ctra. Tarragona-san Sebastian, Km. 0164,2 Barbastro Huesca 22300",
    "addr:postcode":"22300",
    "addr:street":"Ctra. Tarragona-San Sebastian Km. 0164,2",
    "iso:country":"ES",
    "sg:address":"Ctra. Tarragona-san Sebastian, Km. 0164,2",
    "sg:city":"Barbastro",
    "sg:orig_category":"Negocio De Madera",
    "sg:phone":"+34 974 31 12 08",
    "sg:postcode":"22300",
    "sg:province":"Huesca",
    "wof:name":"Daniel Fuster S.a.",
    "wof:placetype":"venue"
},
  "geometry": {"coordinates":[0.1047969982,42.0337791443],"type":"Point"}
}