{
  "type": "Feature",
  "properties": {
    "addr:full":"Rio, 83 Lorca Murcia 30812",
    "addr:housenumber":"83",
    "addr:postcode":"30812",
    "addr:street":"Rio",
    "iso:country":"ES",
    "sg:address":"Rio, 83",
    "sg:city":"Lorca",
    "sg:orig_category":"Empresas De Carpinter\u00cda De Madera",
    "sg:phone":"+34 968 43 93 54",
    "sg:postcode":"30812",
    "sg:province":"Murcia",
    "wof:name":"Muebles Oller S.l.",
    "wof:placetype":"venue"
},
  "geometry": {"coordinates":[-1.7981009483,37.9059028625],"type":"Point"}
}