{
  "type": "Feature",
  "properties": {
    "iso:country":"ES",
    "sg:address":"Rbla Turo, 15",
    "sg:city":"Turo Del Mar",
    "sg:orig_category":"Reposter\u00cdas",
    "sg:phone":"+34 934 69 08 31",
    "sg:postcode":"08390",
    "sg:province":"Barcelona",
    "wof:name":"Panificadora Montgat S.l.",
    "wof:placetype":"venue"
},
  "geometry": {"coordinates":[2.2786700726,41.4704208374],"type":"Point"}
}