{
  "type": "Feature",
  "properties": {
    "addr:full":"Estd Coru\u00d1a (da), 77 Lugo Lugo 27003",
    "addr:postcode":"27003",
    "iso:country":"ES",
    "sg:address":"Estd Coru\u00d1a (da), 77",
    "sg:city":"Lugo",
    "sg:orig_category":"Mec\u00c1nico Del Autom\u00d3vil",
    "sg:phone":"+34 982 21 61 88",
    "sg:postcode":"27003",
    "sg:province":"Lugo",
    "wof:name":"Martinez Rectificadora Lucense S. L.",
    "wof:placetype":"venue"
},
  "geometry": {"coordinates":[-7.5605587959,43.0171546936],"type":"Point"}
}