{
  "type": "Feature",
  "properties": {
    "iso:country":"ES",
    "sg:address":"Calle de Miguel Servet, 1",
    "sg:city":"Almansa",
    "sg:orig_category":"Materias Pl\u00c1sticas: Productos De Consumo Masivo (fabricaci\u00d3n, Al Por Mayor)",
    "sg:phone":"+34 967 34 20 19",
    "sg:postcode":"02640",
    "sg:province":"Albacete",
    "wof:name":"Comercial Quilez Almansa S.l.",
    "wof:placetype":"venue"
},
  "geometry": {"coordinates":[-1.1004159451,38.8772087097],"type":"Point"}
}