{
  "type": "Feature",
  "properties": {
    "addr:full":"Calle de Santo Entierro, 5 S. Fernando C\u00e1diz 11100",
    "addr:housenumber":"5",
    "addr:postcode":"11100",
    "addr:street":"Calle De Santo Entierro;S. Fernando Ca\u0301Diz",
    "iso:country":"ES",
    "sg:address":"Calle de Santo Entierro, 5",
    "sg:city":"S. Fernando",
    "sg:orig_category":"Empresas De Carpinter\u00cda",
    "sg:phone":"+34 956 59 11 98",
    "sg:postcode":"11100",
    "sg:province":"C\u00e1diz",
    "wof:name":"Aleu Peci Daniel",
    "wof:placetype":"venue"
},
  "geometry": {"coordinates":[-6.2074275017,36.4559822083],"type":"Point"}
}