{
  "type": "Feature",
  "properties": {
    "iso:country":"ES",
    "sg:address":"Estd A Ribadetea, S/n",
    "sg:city":"Ponte",
    "sg:orig_category":"Mudanzas",
    "sg:phone":"+34 986 64 22 97",
    "sg:postcode":"36860",
    "sg:province":"Pontevedra",
    "wof:name":"Lopez Gayoso S.l.",
    "wof:placetype":"venue"
},
  "geometry": {"coordinates":[-8.5163888931,42.1783599854],"type":"Point"}
}