{
  "type": "Feature",
  "properties": {
    "addr:full":"Av Maresme (del), 311 Mataro Barcelona 08301",
    "addr:postcode":"08301",
    "addr:street":"Av;Del 311",
    "iso:country":"ES",
    "sg:address":"Av Maresme (del), 311",
    "sg:city":"Mataro",
    "sg:orig_category":"Asociaciones Y Clubs Deportivos",
    "sg:phone":"+34 937 90 27 73",
    "sg:postcode":"08301",
    "sg:province":"Barcelona",
    "wof:name":"Casabella Gel Joan",
    "wof:placetype":"venue"
},
  "geometry": {"coordinates":[2.4487290382,41.5364227295],"type":"Point"}
}