{
  "type": "Feature",
  "properties": {
    "addr:full":"Calle de Santa Barbara, S/n Lumpiaque Zaragoza 50295",
    "addr:postcode":"50295",
    "addr:street":"Calle De Santa Barbara S / N Lumpiaque",
    "iso:country":"ES",
    "sg:address":"Calle de Santa Barbara, S/n",
    "sg:city":"Lumpiaque",
    "sg:orig_category":"Formaci\u00d3n Continuada (variada)",
    "sg:phone":"+34 976 60 16 42",
    "sg:postcode":"50295",
    "sg:province":"Zaragoza",
    "wof:name":"Roberto Alonso Bielsa S.cv.",
    "wof:placetype":"venue"
},
  "geometry": {"coordinates":[-1.3016699553,41.6278533936],"type":"Point"}
}