{
  "type": "Feature",
  "properties": {
    "iso:country":"ES",
    "sg:address":"Calle de Doctor Nieto, S/n",
    "sg:city":"Alacant",
    "sg:orig_category":"Ahumados Y Salazones",
    "sg:phone":"+34 965 24 45 54",
    "sg:postcode":"03013",
    "sg:province":"Alicante",
    "wof:name":"Herrero Carrera Mercedes",
    "wof:placetype":"venue"
},
  "geometry": {"coordinates":[-0.4798533916,38.3580513],"type":"Point"}
}