{
  "type": "Feature",
  "properties": {
    "addr:full":"Calle de Alcala Galiano, 1 Torraos Murcia 30563",
    "addr:housenumber":"1",
    "addr:postcode":"30563",
    "addr:street":"Calle De Alcala Galiano",
    "iso:country":"ES",
    "sg:address":"Calle de Alcala Galiano, 1",
    "sg:city":"Torraos",
    "sg:orig_category":"Heladeros",
    "sg:phone":"+34 968 69 37 50",
    "sg:postcode":"30563",
    "sg:province":"Murcia",
    "wof:name":"Martinez Garcia Monica",
    "wof:placetype":"venue"
},
  "geometry": {"coordinates":[-1.2815072536,38.0973739624],"type":"Point"}
}