{
  "type": "Feature",
  "properties": {
    "iso:country":"ES",
    "sg:address":"Calle de Berenguer Mallol, 11",
    "sg:city":"Valencia",
    "sg:orig_category":"Guarder\u00cdas",
    "sg:phone":"+34 963 31 12 68",
    "sg:postcode":"46022",
    "sg:province":"Valencia",
    "wof:name":"Maria Jesus Gomez Bertomeu-maria Carmen Morenza Tato Cdad",
    "wof:placetype":"venue"
},
  "geometry": {"coordinates":[-0.3449186087,39.4651641846],"type":"Point"}
}