{
  "type": "Feature",
  "properties": {
    "addr:full":"Calle de Poeta Mas Y Ros, 8 Valencia Valencia 46021",
    "addr:housenumber":"8",
    "addr:postcode":"46021",
    "addr:street":"Calle De Poeta Mas Y Ros",
    "iso:country":"ES",
    "sg:address":"Calle de Poeta Mas Y Ros, 8",
    "sg:city":"Valencia",
    "sg:orig_category":"Mec\u00c1nico Del Autom\u00d3vil",
    "sg:phone":"+34 963 93 07 82",
    "sg:postcode":"46021",
    "sg:province":"Valencia",
    "wof:name":"Belando Gomez Jose Maria",
    "wof:placetype":"venue"
},
  "geometry": {"coordinates":[-0.3514370024,39.4711914062],"type":"Point"}
}