{
  "type": "Feature",
  "properties": {
    "iso:country":"ES",
    "sg:address":"Mcdo San Jose, S/n",
    "sg:city":"Zaragoza",
    "sg:orig_category":"Pescader\u00cdas (al Por Menor)",
    "sg:phone":"+34 976 37 97 66",
    "sg:postcode":"50007",
    "sg:province":"Zaragoza",
    "wof:name":"Fernandez Gomez Jesus",
    "wof:placetype":"venue"
},
  "geometry": {"coordinates":[-0.8770939708,41.6374015808],"type":"Point"}
}