{
  "type": "Feature",
  "properties": {
    "iso:country":"ES",
    "sg:address":"Ctra Sonsoles, Km. 0005,0",
    "sg:city":"Avila",
    "sg:orig_category":"Hosteler\u00cda, Empleados",
    "sg:phone":"+34 920 22 73 76",
    "sg:postcode":"05002",
    "sg:province":"\u00c1vila",
    "wof:name":"Uniformes Y Patronajes Mostoles S.l.",
    "wof:placetype":"venue"
},
  "geometry": {"coordinates":[-4.6967940331,40.6423187256],"type":"Point"}
}