{
  "type": "Feature",
  "properties": {
    "iso:country":"ES",
    "sg:address":"Calle de Manuel R Alvarez, 2",
    "sg:city":"Gijon",
    "sg:orig_category":"Iglesia Cat\u00d3lica",
    "sg:phone":"+34 985 32 12 32",
    "sg:postcode":"33213",
    "sg:province":"Asturias",
    "wof:name":"Diocesis De Oviedo",
    "wof:placetype":"venue"
},
  "geometry": {"coordinates":[-5.6856150627,43.5289726257],"type":"Point"}
}