{
  "type": "Feature",
  "properties": {
    "iso:country":"ES",
    "sg:address":"Barr Udiarraga, 6",
    "sg:city":"Ugao-miraballes",
    "sg:orig_category":"Bisuter\u00cda, Joyer\u00cda, Relojer\u00cda (al Por Menor)",
    "sg:phone":"+34 946 48 01 22",
    "sg:postcode":"48490",
    "sg:province":"Vizcaya",
    "wof:name":"Luis Ignacio Eguiluz Andres",
    "wof:placetype":"venue"
},
  "geometry": {"coordinates":[-2.9015169144,43.1823997498],"type":"Point"}
}