{
  "type": "Feature",
  "properties": {
    "iso:country":"ES",
    "sg:address":"Calle de Palacio, 63",
    "sg:city":"Mirabel",
    "sg:orig_category":"Producci\u00d3n, Venta De Productos De Agricultura Biol\u00d3gica",
    "sg:phone":"+34 927 45 02 70",
    "sg:postcode":"10540",
    "sg:province":"C\u00e1ceres",
    "wof:name":"Sociedad Agraria De Transformacion Numero 2526",
    "wof:placetype":"venue"
},
  "geometry": {"coordinates":[-6.234249115,39.8591918945],"type":"Point"}
}