{
  "type": "Feature",
  "properties": {
    "addr:full":"Calle de Ramon Y Cajal, 6 Cabezo Torres Murcia 30110",
    "addr:housenumber":"6",
    "addr:postcode":"30110",
    "addr:street":"Calle De Ramon Y Cajal",
    "iso:country":"ES",
    "sg:address":"Calle de Ramon Y Cajal, 6",
    "sg:city":"Cabezo Torres",
    "sg:orig_category":"Cajas De Ahorro",
    "sg:phone":"+34 968 85 81 71",
    "sg:postcode":"30110",
    "sg:province":"Murcia",
    "wof:name":"Caja De Ahorros De Murcia",
    "wof:placetype":"venue"
},
  "geometry": {"coordinates":[-1.1324800253,38.0249443054],"type":"Point"}
}