{
  "type": "Feature",
  "properties": {
    "addr:full":"Calle de Paraisin (el), 4 Ponferrada Le\u00f3n 24400",
    "addr:housenumber":"4",
    "addr:postcode":"24400",
    "addr:street":"Calle De Paraisin El",
    "iso:country":"ES",
    "sg:address":"Calle de Paraisin (el), 4",
    "sg:city":"Ponferrada",
    "sg:orig_category":"Obras Y Organismos Sociales",
    "sg:phone":"+34 987 40 34 56",
    "sg:postcode":"24400",
    "sg:province":"Le\u00f3n",
    "wof:name":"Centro De Acogida De Transeuntes San Genadio",
    "wof:placetype":"venue"
},
  "geometry": {"coordinates":[-6.5916719437,42.5445213318],"type":"Point"}
}