{
  "type": "Feature",
  "properties": {
    "iso:country":"ES",
    "sg:address":"Carr Caritat, 50",
    "sg:city":"Palafrugell",
    "sg:orig_category":"Guarder\u00cdas",
    "sg:phone":"+34 972 30 10 42",
    "sg:postcode":"17200",
    "sg:province":"Girona",
    "wof:name":"Llar De Infants Santa Teresa",
    "wof:placetype":"venue"
},
  "geometry": {"coordinates":[3.1624929905,41.9168891907],"type":"Point"}
}