{
  "type": "Feature",
  "properties": {
    "iso:country":"ES",
    "sg:address":"Avda Marfagones, 21",
    "sg:city":"Canteras",
    "sg:orig_category":"Guarder\u00cdas",
    "sg:phone":"+34 968 55 36 89",
    "sg:postcode":"30394",
    "sg:province":"Murcia",
    "wof:name":"Garcia Garcia Juan",
    "wof:placetype":"venue"
},
  "geometry": {"coordinates":[-1.0433559418,37.6132278442],"type":"Point"}
}