{
  "type": "Feature",
  "properties": {
    "iso:country":"ES",
    "sg:address":"Calle de Corazon De Jesus, 8",
    "sg:city":"Javali Nuevo",
    "sg:orig_category":"Transportes Por V\u00cdas Navegables",
    "sg:phone":"+34 968 80 06 71",
    "sg:postcode":"30832",
    "sg:province":"Murcia",
    "wof:name":"Murcia Torrecilla Juan",
    "wof:placetype":"venue"
},
  "geometry": {"coordinates":[-1.2193779945,37.987449646],"type":"Point"}
}