{
  "type": "Feature",
  "properties": {
    "addr:full":"Carretera De Macharaviaya, S/n Rincon Victoria M\u00e1laga 29730",
    "addr:housenumber":"s / n",
    "addr:postcode":"29730",
    "addr:street":"Carretera De Macharaviaya;Ma\u0301Laga",
    "iso:country":"ES",
    "sg:address":"Carretera De Macharaviaya, S/n",
    "sg:city":"Rincon Victoria",
    "sg:orig_category":"Ingenier\u00cda, Centros De Estudios (diversos)",
    "sg:phone":"+34 952 42 56 60",
    "sg:postcode":"29730",
    "sg:province":"M\u00e1laga",
    "wof:name":"Queipo De Llano Lopez-cozar Fernando",
    "wof:placetype":"venue"
},
  "geometry": {"coordinates":[-4.2807641029,36.714641571],"type":"Point"}
}