{
  "type": "Feature",
  "properties": {
    "iso:country":"ES",
    "sg:address":"Avda Asturias, 39",
    "sg:city":"Guardo",
    "sg:orig_category":"Contenedores (mercanc\u00cdas)",
    "sg:phone":"+34 979 85 20 12",
    "sg:postcode":"34880",
    "sg:province":"Palencia",
    "wof:name":"Cobasguar Sociedad Cooperativa",
    "wof:placetype":"venue"
},
  "geometry": {"coordinates":[-4.8449988365,42.7927093506],"type":"Point"}
}