{
  "type": "Feature",
  "properties": {
    "iso:country":"ES",
    "sg:address":"Veguellina, 18",
    "sg:city":"Requejo De La Vega",
    "sg:orig_category":"Material Y Herramientas Agr\u00cdcolas",
    "sg:phone":"+34 987 64 06 32",
    "sg:postcode":"24763",
    "sg:province":"Le\u00f3n",
    "wof:name":"Agricola Del Orbigo S.l.",
    "wof:placetype":"venue"
},
  "geometry": {"coordinates":[-5.8850054741,42.311378479],"type":"Point"}
}