{
  "type": "Feature",
  "properties": {
    "addr:full":"Calle de Abajo De Santa Maria, 6 Viana Navarra 31230",
    "addr:housenumber":"6",
    "addr:postcode":"31230",
    "addr:street":"Calle De Abajo De Santa Maria",
    "iso:country":"ES",
    "sg:address":"Calle de Abajo De Santa Maria, 6",
    "sg:city":"Viana",
    "sg:orig_category":"Estancos",
    "sg:phone":"+34 948 64 50 29",
    "sg:postcode":"31230",
    "sg:province":"Navarra",
    "wof:name":"Ortigosa Arina Francisco",
    "wof:placetype":"venue"
},
  "geometry": {"coordinates":[-2.3717730045,42.5144424438],"type":"Point"}
}