{
  "type": "Feature",
  "properties": {
    "addr:full":"Calle de General Marti, 7 Toledo Toledo 45005",
    "addr:housenumber":"7",
    "addr:postcode":"45005",
    "addr:street":"Calle De General Marti",
    "iso:country":"ES",
    "sg:address":"Calle de General Marti, 7",
    "sg:city":"Toledo",
    "sg:orig_category":"Librer\u00cdas",
    "sg:phone":"+34 925 25 21 68",
    "sg:postcode":"45005",
    "sg:province":"Toledo",
    "wof:name":"Perez Perez Nicolas",
    "wof:placetype":"venue"
},
  "geometry": {"coordinates":[-4.0367431641,39.8719406128],"type":"Point"}
}