{
  "type": "Feature",
  "properties": {
    "iso:country":"ES",
    "sg:address":"Hortes, 3",
    "sg:city":"Portbou",
    "sg:orig_category":"Enfermeras: Consultas, Atenci\u00d3n A Domicilio",
    "sg:phone":"+34 972 39 04 76",
    "sg:postcode":"17497",
    "sg:province":"Girona",
    "wof:name":"Fernandez Nogueiro Maria Celia",
    "wof:placetype":"venue"
},
  "geometry": {"coordinates":[3.1613500118,42.4256286621],"type":"Point"}
}