{
  "type": "Feature",
  "properties": {
    "addr:full":"Calle de Almirante Lallemand, 96 Pto. Rosario Las Palmas 35600",
    "addr:housenumber":"96",
    "addr:postcode":"35600",
    "addr:street":"Calle De Almirante Lallemand;Pto. Rosario Las",
    "iso:country":"ES",
    "sg:address":"Calle de Almirante Lallemand, 96",
    "sg:city":"Pto. Rosario",
    "sg:orig_category":"Estudios, Instalaci\u00d3n De Climatizaci\u00d3n",
    "sg:phone":"+34 928 85 89 56",
    "sg:postcode":"35600",
    "sg:province":"Las Palmas",
    "wof:name":"Tecnotel De Canarias S.a.",
    "wof:placetype":"venue"
},
  "geometry": {"coordinates":[-13.8487663269,28.5016765594],"type":"Point"}
}