{
  "type": "Feature",
  "properties": {
    "addr:full":"Calle de Jesus, 52 Valencia Valencia 46007",
    "addr:housenumber":"52",
    "addr:postcode":"46007",
    "addr:street":"Calle De Jesus",
    "iso:country":"ES",
    "sg:address":"Calle de Jesus, 52",
    "sg:city":"Valencia",
    "sg:orig_category":"Inform\u00c1tica: Mantenimiento Y Reparaci\u00d3n De Ordenadores",
    "sg:phone":"+34 963 85 64 01",
    "sg:postcode":"46007",
    "sg:province":"Valencia",
    "sg:website":"www.tecmaser.es",
    "wof:name":"Tecmaser S.l.",
    "wof:placetype":"venue"
},
  "geometry": {"coordinates":[-0.3844720125,39.4652252197],"type":"Point"}
}