{
  "type": "Feature",
  "properties": {
    "iso:country":"ES",
    "sg:address":"Carr Sequia, 22",
    "sg:city":"Aitona",
    "sg:orig_category":"Agricultura: Abastecimiento Y Cosechado (negocio)",
    "sg:phone":"+34 973 79 46 39",
    "sg:postcode":"25182",
    "sg:province":"Lleida",
    "wof:name":"Sampietro Ibars Conrado",
    "wof:placetype":"venue"
},
  "geometry": {"coordinates":[0.4591509998,41.4937934875],"type":"Point"}
}