{
  "type": "Feature",
  "properties": {
    "addr:full":"Calle de Sagasta, 5 Sevilla Sevilla 41004",
    "addr:housenumber":"5",
    "addr:postcode":"41004",
    "addr:street":"Calle De Sagasta",
    "iso:country":"ES",
    "sg:address":"Calle de Sagasta, 5",
    "sg:city":"Sevilla",
    "sg:orig_category":"Complementos De Vestir (al Por Menor)",
    "sg:phone":"+34 954 22 53 83",
    "sg:postcode":"41004",
    "sg:province":"Sevilla",
    "sg:website":"www.galan-camiseria.com",
    "wof:name":"Galan Camiseria S.l.",
    "wof:placetype":"venue"
},
  "geometry": {"coordinates":[-5.9936580658,37.3900413513],"type":"Point"}
}