{
  "type": "Feature",
  "properties": {
    "addr:full":"Calle de Pelicano, 7 Valladolid Valladolid 47012",
    "addr:housenumber":"7",
    "addr:postcode":"47012",
    "addr:street":"Calle De Pelicano",
    "iso:country":"ES",
    "sg:address":"Calle de Pelicano, 7",
    "sg:city":"Valladolid",
    "sg:orig_category":"Carnicer\u00cdas, Carnicer\u00cdas",
    "sg:phone":"+34 983 29 58 14",
    "sg:postcode":"47012",
    "sg:province":"Valladolid",
    "wof:name":"Roman Amigo Domingo",
    "wof:placetype":"venue"
},
  "geometry": {"coordinates":[-4.7112197876,41.6475982666],"type":"Point"}
}