{
  "type": "Feature",
  "properties": {
    "addr:full":"Carr Major, 3 Vallfogona Balaguer Lleida 25680",
    "addr:housenumber":"3",
    "addr:postcode":"25680",
    "addr:street":"Carr Major",
    "iso:country":"ES",
    "sg:address":"Carr Major, 3",
    "sg:city":"Vallfogona Balaguer",
    "sg:orig_category":"Farmacias",
    "sg:phone":"+34 973 43 21 51",
    "sg:postcode":"25680",
    "sg:province":"Lleida",
    "wof:name":"Aiguabella Alenta Jose",
    "wof:placetype":"venue"
},
  "geometry": {"coordinates":[0.8056520224,41.7908401489],"type":"Point"}
}