{
  "type": "Feature",
  "properties": {
    "addr:full":"Calle de Valladolid, 6 Vitoria-gasteiz \u00c1lava 01002",
    "addr:housenumber":"6",
    "addr:postcode":"01002",
    "addr:street":"Calle De Valladolid",
    "iso:country":"ES",
    "sg:address":"Calle de Valladolid, 6",
    "sg:city":"Vitoria-gasteiz",
    "sg:orig_category":"Peluqueros: De Se\u00d1oras",
    "sg:phone":"+34 945 28 67 33",
    "sg:postcode":"01002",
    "sg:province":"\u00c1lava",
    "wof:name":"Pascual Quintas Maria Jesus",
    "wof:placetype":"venue"
},
  "geometry": {"coordinates":[-2.6636090279,42.8530006409],"type":"Point"}
}