{
  "type": "Feature",
  "properties": {
    "addr:full":"Carr Doctor Robert, 171 Badalona Barcelona 08915",
    "addr:housenumber":"171",
    "addr:postcode":"08915",
    "addr:street":"Carr Doctor Robert",
    "iso:country":"ES",
    "sg:address":"Carr Doctor Robert, 171",
    "sg:city":"Badalona",
    "sg:orig_category":"Frutas, Legumbres Frescas Y Tempranas (al Por Menor)",
    "sg:phone":"+34 933 99 58 37",
    "sg:postcode":"08915",
    "sg:province":"Barcelona",
    "wof:name":"Arquillo Reinoso Antonio",
    "wof:placetype":"venue"
},
  "geometry": {"coordinates":[2.2416927814,41.4615592957],"type":"Point"}
}