{
  "type": "Feature",
  "properties": {
    "addr:full":"Av Constitucio, 171 Castelldefels Barcelona 08860",
    "addr:housenumber":"171",
    "addr:postcode":"08860",
    "addr:street":"Av Constitucio",
    "iso:country":"ES",
    "sg:address":"Av Constitucio, 171",
    "sg:city":"Castelldefels",
    "sg:orig_category":"Ense\u00d1anza Secundaria: Colegios Y Escuelas Privadas",
    "sg:phone":"+34 936 65 79 54",
    "sg:postcode":"08860",
    "sg:province":"Barcelona",
    "wof:name":"Vegas Ortega Silvia",
    "wof:placetype":"venue"
},
  "geometry": {"coordinates":[1.9766190052,41.2773361206],"type":"Point"}
}