{
  "type": "Feature",
  "properties": {
    "iso:country":"ES",
    "sg:address":"Juan De Juanes, 2",
    "sg:city":"Playa Canet Berenguer",
    "sg:orig_category":"Publicidad (soportes Y Gesti\u00d3n)",
    "sg:phone":"+34 962 60 71 62",
    "sg:postcode":"46529",
    "sg:province":"Valencia",
    "wof:name":"Valero Rodriguez Manuel",
    "wof:placetype":"venue"
},
  "geometry": {"coordinates":[-0.210510999,39.6768836975],"type":"Point"}
}