{
  "type": "Feature",
  "properties": {
    "iso:country":"ES",
    "sg:address":"Carr Segria, 7",
    "sg:city":"Lleida",
    "sg:orig_category":"Televisi\u00d3n, V\u00cddeo: Aparatos Y Accesorios (venta)",
    "sg:phone":"+34 973 26 20 24",
    "sg:postcode":"25006",
    "sg:province":"Lleida",
    "wof:name":"Morell Llarden Jeronimo",
    "wof:placetype":"venue"
},
  "geometry": {"coordinates":[0.6158490181,41.6171951294],"type":"Point"}
}