{
  "type": "Feature",
  "properties": {
    "addr:full":"Calle de Adolfo Garcia Arbesu, 9 Langreo Asturias 33900",
    "addr:housenumber":"9",
    "addr:postcode":"33900",
    "addr:street":"Calle De Adolfo Garcia Arbesu",
    "iso:country":"ES",
    "sg:address":"Calle de Adolfo Garcia Arbesu, 9",
    "sg:city":"Langreo",
    "sg:orig_category":"Asociaciones Y Clubs Deportivos",
    "sg:phone":"+34 985 69 83 56",
    "sg:postcode":"33900",
    "sg:province":"Asturias",
    "sg:website":"www.langreomotorclub.com",
    "wof:name":"Escuderia Langreo Motor Club",
    "wof:placetype":"venue"
},
  "geometry": {"coordinates":[-5.6697893143,43.2877845764],"type":"Point"}
}