{
  "type": "Feature",
  "properties": {
    "addr:full":"Calle de Ramon Muntaner, 26 Xirivella Valencia 46950",
    "addr:housenumber":"26",
    "addr:postcode":"46950",
    "addr:street":"Calle De Ramon Muntaner",
    "iso:country":"ES",
    "sg:address":"Calle de Ramon Muntaner, 26",
    "sg:city":"Xirivella",
    "sg:orig_category":"Centros De Educaci\u00d3n Especial",
    "sg:phone":"+34 963 59 92 62",
    "sg:postcode":"46950",
    "sg:province":"Valencia",
    "wof:name":"Generalitat Valenciana",
    "wof:placetype":"venue"
},
  "geometry": {"coordinates":[-0.4292559922,39.4670562744],"type":"Point"}
}