{
  "type": "Feature",
  "properties": {
    "iso:country":"ES",
    "sg:address":"Calle de Escuelas Pias, 12",
    "sg:city":"Barbastro",
    "sg:orig_category":"Electricidad: Instaladores",
    "sg:phone":"+34 974 31 01 95",
    "sg:postcode":"22300",
    "sg:province":"Huesca",
    "wof:name":"Aguas Potables De Barbastro S. A.",
    "wof:placetype":"venue"
},
  "geometry": {"coordinates":[0.1246803999,42.0360870361],"type":"Point"}
}