{
  "type": "Feature",
  "properties": {
    "iso:country":"ES",
    "sg:address":"Carrer de Joan Maragall, 1",
    "sg:city":"Viladecans",
    "sg:orig_category":"Promotores Constructores",
    "sg:phone":"+34 936 58 10 09",
    "sg:postcode":"08840",
    "sg:province":"Barcelona",
    "wof:name":"Alcalaz Fores Jordi",
    "wof:placetype":"venue"
},
  "geometry": {"coordinates":[2.01395154,41.3107719421],"type":"Point"}
}