{
  "type": "Feature",
  "properties": {
    "iso:country":"ES",
    "sg:address":"Carrer de Major De Sarria, 86",
    "sg:city":"Barcelona",
    "sg:orig_category":"Art\u00cdculos De Decoraci\u00d3n",
    "sg:phone":"+34 932 03 11 53",
    "sg:postcode":"08017",
    "sg:province":"Barcelona",
    "wof:name":"Agusti Planas Rafael",
    "wof:placetype":"venue"
},
  "geometry": {"coordinates":[2.1222479343,41.3988113403],"type":"Point"}
}