{
  "type": "Feature",
  "properties": {
    "iso:country":"ES",
    "sg:address":"Arroyo, S/n",
    "sg:city":"La Pedrera",
    "sg:orig_category":"Asociaciones Y Clubs Deportivos",
    "sg:phone":"+34 985 16 79 21",
    "sg:postcode":"33392",
    "sg:province":"Asturias",
    "wof:name":"Sociedad Gijonesa De Tiro Olimpico",
    "wof:placetype":"venue"
},
  "geometry": {"coordinates":[-5.7052330971,43.5063514709],"type":"Point"}
}