{
  "type": "Feature",
  "properties": {
    "addr:full":"Carrer de Poeta Josep Punsola, 20 Mataro Barcelona 08304",
    "addr:housenumber":"20",
    "addr:postcode":"08304",
    "addr:street":"Carrer De Poeta Josep Punsola",
    "iso:country":"ES",
    "sg:address":"Carrer de Poeta Josep Punsola, 20",
    "sg:city":"Mataro",
    "sg:orig_category":"Bares, Piano",
    "sg:phone":"+34 937 90 19 74",
    "sg:postcode":"08304",
    "sg:province":"Barcelona",
    "wof:name":"Ahsain Sanhaji Mohammad",
    "wof:placetype":"venue"
},
  "geometry": {"coordinates":[2.4509811401,41.5481185913],"type":"Point"}
}