{
  "type": "Feature",
  "properties": {
    "addr:full":"Calle de Emperatriz Eugenia, 5 Granada Granada 18002",
    "addr:housenumber":"5",
    "addr:postcode":"18002",
    "addr:street":"Calle De Emperatriz Eugenia",
    "iso:country":"ES",
    "sg:address":"Calle de Emperatriz Eugenia, 5",
    "sg:city":"Granada",
    "sg:orig_category":"Inmobiliaria (agencias)",
    "sg:phone":"+34 958 20 41 65",
    "sg:postcode":"18002",
    "sg:province":"Granada",
    "wof:name":"Iberica De Gestion Inmobiliaria Y Arrendaticia S.l.",
    "wof:placetype":"venue"
},
  "geometry": {"coordinates":[-3.6065340042,37.1763267517],"type":"Point"}
}