{
  "type": "Feature",
  "properties": {
    "iso:country":"ES",
    "sg:address":"Calle de Luis Montoto, 105",
    "sg:city":"Sevilla",
    "sg:orig_category":"Agencias Y Agentes Comerciales, Representantes",
    "sg:phone":"+34 954 58 11 04",
    "sg:postcode":"41007",
    "sg:province":"Sevilla",
    "wof:name":"Mariano Diaz E Hijos S.l.",
    "wof:placetype":"venue"
},
  "geometry": {"coordinates":[-5.9707369804,37.3874664307],"type":"Point"}
}