{
  "type": "Feature",
  "properties": {
    "iso:country":"ES",
    "sg:address":"Bidebarrieta Kalea, 27 A",
    "sg:city":"Eibar",
    "sg:orig_category":"Art\u00cdculos De Decoraci\u00d3n",
    "sg:phone":"+34 943 20 01 51",
    "sg:postcode":"20600",
    "sg:province":"Guip\u00f9zcoa",
    "wof:name":"Fran Urquidi, S.l",
    "wof:placetype":"venue"
},
  "geometry": {"coordinates":[-2.4884390831,43.1800117493],"type":"Point"}
}