{
  "type": "Feature",
  "properties": {
    "addr:full":"Urbieta, 2 Estella Navarra 31200",
    "addr:housenumber":"2",
    "addr:postcode":"31200",
    "addr:street":"Urbieta",
    "iso:country":"ES",
    "sg:address":"Urbieta, 2",
    "sg:city":"Estella",
    "sg:orig_category":"Asociaciones Y Clubs Deportivos",
    "sg:phone":"+34 948 55 00 33",
    "sg:postcode":"31200",
    "sg:province":"Navarra",
    "wof:name":"Club Deportivo San Miguel",
    "wof:placetype":"venue"
},
  "geometry": {"coordinates":[-2.0387539864,42.6733818054],"type":"Point"}
}