{
  "type": "Feature",
  "properties": {
    "addr:full":"Calle de San Juan De Dios, 23 Talavera Reina Toledo 45600",
    "addr:housenumber":"23",
    "addr:postcode":"45600",
    "addr:street":"Calle De San Juan;Dios",
    "iso:country":"ES",
    "sg:address":"Calle de San Juan De Dios, 23",
    "sg:city":"Talavera Reina",
    "sg:orig_category":"Mercer\u00cda, Lencer\u00cda (al Por Menor)",
    "sg:phone":"+34 925 80 25 15",
    "sg:postcode":"45600",
    "sg:province":"Toledo",
    "wof:name":"Moreno Luengo Lorenzo",
    "wof:placetype":"venue"
},
  "geometry": {"coordinates":[-4.8362631798,39.9627113342],"type":"Point"}
}