{
  "type": "Feature",
  "properties": {
    "iso:country":"ES",
    "sg:address":"Av. Garabanxa, 17",
    "sg:city":"Sigueiro",
    "sg:orig_category":"Ropa Para Ni\u00d1os (al Por Menor)",
    "sg:phone":"+34 981 69 49 48",
    "sg:postcode":"15888",
    "sg:province":"La Coru\u00f1a",
    "wof:name":"Narlu Sigueiro S.l.",
    "wof:placetype":"venue"
},
  "geometry": {"coordinates":[-8.4332475662,42.9700546265],"type":"Point"}
}