{
  "type": "Feature",
  "properties": {
    "iso:country":"ES",
    "sg:address":"Avda Manzanares, 158",
    "sg:city":"Madrid",
    "sg:orig_category":"Farmacias",
    "sg:phone":"+34 914 69 75 35",
    "sg:postcode":"28019",
    "sg:province":"Madrid",
    "wof:name":"Rivas Martinez Y Oliva De Las Heras C.b.",
    "wof:placetype":"venue"
},
  "geometry": {"coordinates":[-3.7093629837,40.395866394],"type":"Point"}
}