{
  "type": "Feature",
  "properties": {
    "iso:country":"ES",
    "sg:address":"Calle de Casta\u00d1os, 23",
    "sg:city":"Alacant",
    "sg:orig_category":"Bisuter\u00cda, Joyer\u00cda, Relojer\u00cda (al Por Menor)",
    "sg:phone":"+34 965 21 24 05",
    "sg:postcode":"03001",
    "sg:province":"Alicante",
    "wof:name":"Anaya Valera Elena",
    "wof:placetype":"venue"
},
  "geometry": {"coordinates":[-0.4856215119,38.3457641602],"type":"Point"}
}