{
  "type": "Feature",
  "properties": {
    "addr:full":"Calle de Pintor Zuloaga, 33 Cadiz C\u00e1diz 11010",
    "addr:housenumber":"33",
    "addr:postcode":"11010",
    "addr:street":"Calle De Pintor Zuloaga",
    "iso:country":"ES",
    "sg:address":"Calle de Pintor Zuloaga, 33",
    "sg:city":"Cadiz",
    "sg:orig_category":"Comercio, Reparaci\u00d3n De Motocicletas, Bicicletas Y Piezas Sueltas",
    "sg:phone":"+34 956 25 90 58",
    "sg:postcode":"11010",
    "sg:province":"C\u00e1diz",
    "wof:name":"Herran Noriega Jesus De La",
    "wof:placetype":"venue"
},
  "geometry": {"coordinates":[-6.2738947868,36.5035667419],"type":"Point"}
}