{
  "type": "Feature",
  "properties": {
    "addr:full":"Avda R Marismas, 1 Pilas Sevilla 41840",
    "addr:housenumber":"1",
    "addr:postcode":"41840",
    "addr:street":"Avda R Marismas",
    "iso:country":"ES",
    "sg:address":"Avda R Marismas, 1",
    "sg:city":"Pilas",
    "sg:orig_category":"Equitaci\u00d3n: Guarnicioner\u00cda, Equipo (al Por Menor)",
    "sg:phone":"+34 954 75 07 77",
    "sg:postcode":"41840",
    "sg:province":"Sevilla",
    "wof:name":"Fuentes Maestros Guarnicioneros S.l.l.",
    "wof:placetype":"venue"
},
  "geometry": {"coordinates":[-6.3043088913,37.3053894043],"type":"Point"}
}