{
  "type": "Feature",
  "properties": {
    "addr:full":"Ctra Provincial, 98 Raviso Pontevedra 36204",
    "addr:postcode":"36204",
    "addr:street":"Ctra Provincial 98 Raviso",
    "iso:country":"ES",
    "sg:address":"Ctra Provincial, 98",
    "sg:city":"Raviso",
    "sg:orig_category":"M\u00c1rmoles, Granitos Y Piedras Naturales",
    "sg:phone":"+34 986 48 08 21",
    "sg:postcode":"36204",
    "sg:province":"Pontevedra",
    "wof:name":"Estevez Cortes Milagros",
    "wof:placetype":"venue"
},
  "geometry": {"coordinates":[-8.6428003311,42.4304618835],"type":"Point"}
}