{
  "type": "Feature",
  "properties": {
    "iso:country":"ES",
    "sg:address":"Carrer de Gran De Gracia, 205",
    "sg:city":"Barcelona",
    "sg:orig_category":"Papeler\u00cdas, Librer\u00cdas",
    "sg:phone":"+34 932 37 81 19",
    "sg:postcode":"08012",
    "sg:province":"Barcelona",
    "wof:name":"Valls Molina Maria Del Carmen",
    "wof:placetype":"venue"
},
  "geometry": {"coordinates":[2.1514968872,41.4042167664],"type":"Point"}
}