{
  "type": "Feature",
  "properties": {
    "iso:country":"ES",
    "sg:address":"Carr Catadau, 7",
    "sg:city":"Benifaio",
    "sg:orig_category":"Mec\u00c1nico Del Autom\u00d3vil",
    "sg:phone":"+34 961 79 52 90",
    "sg:postcode":"46450",
    "sg:province":"Valencia",
    "wof:name":"Canto Y Domenech S.l.",
    "wof:placetype":"venue"
},
  "geometry": {"coordinates":[-0.4229789972,39.2867202759],"type":"Point"}
}