{
  "type": "Feature",
  "properties": {
    "iso:country":"ES",
    "sg:address":"Calle de Doctor Juan Dominguez Perez, 19",
    "sg:city":"Palmas De Gran Canaria",
    "sg:orig_category":"Inform\u00c1tica (estudios, Servicios, Asesor\u00cda, Formaci\u00d3n)",
    "sg:phone":"+34 928 46 33 41",
    "sg:postcode":"35008",
    "sg:province":"Las Palmas",
    "wof:name":"Inprocan S.l.",
    "wof:placetype":"venue"
},
  "geometry": {"coordinates":[-15.4151639938,28.1567687988],"type":"Point"}
}