{
  "type": "Feature",
  "properties": {
    "addr:full":"Plaz Alta, 7 Algeciras C\u00e1diz 11201",
    "addr:housenumber":"7;ca\u0301diz",
    "addr:postcode":"11201",
    "addr:street":"Plaz Alta",
    "iso:country":"ES",
    "sg:address":"Plaz Alta, 7",
    "sg:city":"Algeciras",
    "sg:orig_category":"Administradores De Bienes Y Delegados De Comunidades De Propietarios",
    "sg:phone":"+34 956 65 51 22",
    "sg:postcode":"11201",
    "sg:province":"C\u00e1diz",
    "wof:name":"Gil Rojas Francisco",
    "wof:placetype":"venue"
},
  "geometry": {"coordinates":[-5.4526491165,36.1276016235],"type":"Point"}
}