{
  "type": "Feature",
  "properties": {
    "addr:full":"Pase Alcalde Sanchez Prados, 1 Ceuta Ceuta 51001",
    "addr:housenumber":"1",
    "addr:postcode":"51001",
    "addr:street":"Alcalde;Prados",
    "iso:country":"ES",
    "sg:address":"Pase Alcalde Sanchez Prados, 1",
    "sg:city":"Ceuta",
    "sg:classifiers":[
        {
            "category":"Communications",
            "type":"Services"
        }
    ],
    "sg:phone":"+34 856 20 00 65",
    "sg:postcode":"51001",
    "sg:province":"Ceuta",
    "sg:tags":[
        "televisiones",
        "y",
        "radio"
    ],
    "wof:name":"Onda Ceuta S.l.",
    "wof:placetype":"venue"
},
  "geometry": {"coordinates":[-5.3302302361,35.8947601318],"type":"Point"}
}