{
  "type": "Feature",
  "properties": {
    "addr:full":"Calle de Granxas, 35 Covas Lugo 27861",
    "addr:housenumber":"35",
    "addr:postcode":"27861",
    "addr:street":"Calle De Granxas",
    "iso:country":"ES",
    "sg:address":"Calle de Granxas, 35",
    "sg:city":"Covas",
    "sg:orig_category":"Asesor\u00cda Fiscal Y Jur\u00cddica",
    "sg:phone":"+34 982 56 19 79",
    "sg:postcode":"27861",
    "sg:province":"Lugo",
    "wof:name":"Franco Alvarez Xose",
    "wof:placetype":"venue"
},
  "geometry": {"coordinates":[-7.6092419624,43.6709785461],"type":"Point"}
}