{
  "type": "Feature",
  "properties": {
    "addr:full":"Carrer de Consell De Cent, 95 Barcelona Barcelona 08015",
    "addr:housenumber":"95",
    "addr:postcode":"08015",
    "addr:street":"Carrer De Consell De Cent",
    "iso:country":"ES",
    "sg:address":"Carrer de Consell De Cent, 95",
    "sg:city":"Barcelona",
    "sg:orig_category":"Maquinaria Para Industrias Diversas",
    "sg:phone":"+34 934 23 35 31",
    "sg:postcode":"08015",
    "sg:province":"Barcelona",
    "wof:name":"Reiblan S.c.p.",
    "wof:placetype":"venue"
},
  "geometry": {"coordinates":[2.1508529186,41.3801116943],"type":"Point"}
}