{
  "type": "Feature",
  "properties": {
    "iso:country":"ES",
    "sg:address":"Calle de Atleta Antonio Amoros, 47",
    "sg:city":"Caudete",
    "sg:orig_category":"Promotores Constructores",
    "sg:phone":"+34 965 82 73 39",
    "sg:postcode":"02660",
    "sg:province":"Albacete",
    "wof:name":"Comunidad De Propietarios Calle Echegaray 57 (ascensor",
    "wof:placetype":"venue"
},
  "geometry": {"coordinates":[-0.9848204851,38.7035522461],"type":"Point"}
}