{
  "type": "Feature",
  "properties": {
    "addr:full":"G.v. Corts Catalanes, 710 Barcelona Barcelona 08013",
    "addr:housenumber":"710",
    "addr:postcode":"08013",
    "addr:street":"Catalanes",
    "iso:country":"ES",
    "sg:address":"G.v. Corts Catalanes, 710",
    "sg:city":"Barcelona",
    "sg:orig_category":"Comerciantes Al Por Mayor De Vinos, Licores Y Alcoholes",
    "sg:phone":"+34 932 45 10 56",
    "sg:postcode":"08013",
    "sg:province":"Barcelona",
    "wof:name":"Gall Torruella Eulalia",
    "wof:placetype":"venue"
},
  "geometry": {"coordinates":[2.1769900322,41.3956604004],"type":"Point"}
}