{
  "type": "Feature",
  "properties": {
    "iso:country":"ES",
    "sg:address":"Carrer de Sant Pau, 2",
    "sg:city":"Sabadell",
    "sg:orig_category":"Cl\u00cdnicas Dentales",
    "sg:phone":"+34 937 25 05 61",
    "sg:postcode":"08201",
    "sg:province":"Barcelona",
    "wof:name":"Borrell Ribas Antonio",
    "wof:placetype":"venue"
},
  "geometry": {"coordinates":[2.1080260277,41.5458641052],"type":"Point"}
}