{
  "type": "Feature",
  "properties": {
    "iso:country":"ES",
    "sg:address":"Calle de Regidor Caballero Villamediana, S/n",
    "sg:city":"Fuente Obejuna",
    "sg:orig_category":"Ense\u00d1anza, Formaci\u00d3n Profesional: Aprendizaje",
    "sg:phone":"+34 957 58 40 40",
    "sg:postcode":"14290",
    "sg:province":"C\u00f3rdoba",
    "wof:name":"Juzgado De Paz",
    "wof:placetype":"venue"
},
  "geometry": {"coordinates":[-5.4192810059,38.2663078308],"type":"Point"}
}