{
  "type": "Feature",
  "properties": {
    "iso:country":"ES",
    "sg:address":"Calle de Serrablo (de), 57",
    "sg:city":"Sabi\u00f1anigo",
    "sg:orig_category":"Farmacias",
    "sg:phone":"+34 974 48 00 33",
    "sg:postcode":"22600",
    "sg:province":"Huesca",
    "wof:name":"Marrades Alegre Juan Carlos",
    "wof:placetype":"venue"
},
  "geometry": {"coordinates":[-0.3667579889,42.5183486938],"type":"Point"}
}