{
  "type": "Feature",
  "properties": {
    "addr:full":"Calle de Torres, 9 Valverde Leganes Badajoz 06130",
    "addr:housenumber":"9",
    "addr:postcode":"06130",
    "addr:street":"Calle De Torres",
    "iso:country":"ES",
    "sg:address":"Calle de Torres, 9",
    "sg:city":"Valverde Leganes",
    "sg:orig_category":"Empresas De Carpinter\u00cda De Madera",
    "sg:phone":"+34 924 49 62 02",
    "sg:postcode":"06130",
    "sg:province":"Badajoz",
    "wof:name":"Jorge Rastrollo Maria Josefa",
    "wof:placetype":"venue"
},
  "geometry": {"coordinates":[-6.9843354225,38.6719589233],"type":"Point"}
}