{
  "type": "Feature",
  "properties": {
    "iso:country":"ES",
    "sg:address":"Calle de Las Cercas, 2",
    "sg:city":"Briviesca",
    "sg:orig_category":"Comercio, Reparaci\u00d3n De Motocicletas, Bicicletas Y Piezas Sueltas",
    "sg:phone":"+34 947 59 01 58",
    "sg:postcode":"09240",
    "sg:province":"Burgos",
    "wof:name":"Riveiro Quiros Jose Alberto",
    "wof:placetype":"venue"
},
  "geometry": {"coordinates":[-3.3233389854,42.5479888916],"type":"Point"}
}