{
  "type": "Feature",
  "properties": {
    "addr:full":"Calle de Lledoner, 9 Meliana Valencia 46133",
    "addr:housenumber":"9",
    "addr:postcode":"46133",
    "addr:street":"Calle De Lledoner",
    "iso:country":"ES",
    "sg:address":"Calle de Lledoner, 9",
    "sg:city":"Meliana",
    "sg:orig_category":"Fabricaci\u00d3n De Su\u00c9ters Y Chalecos De Punto",
    "sg:phone":"+34 961 49 05 43",
    "sg:postcode":"46133",
    "sg:province":"Valencia",
    "wof:name":"Julia Peris Antonio",
    "wof:placetype":"venue"
},
  "geometry": {"coordinates":[-0.3500489891,39.527381897],"type":"Point"}
}