{
  "type": "Feature",
  "properties": {
    "iso:country":"ES",
    "sg:address":"Calle de Rio Cares, S/n",
    "sg:city":"Pola De Laviana",
    "sg:orig_category":"Supermercados Y Hipermercados",
    "sg:phone":"+34 985 61 16 39",
    "sg:postcode":"33980",
    "sg:province":"Asturias",
    "wof:name":"Merkaprecio S.a.",
    "wof:placetype":"venue"
},
  "geometry": {"coordinates":[-5.5631489754,43.2412185669],"type":"Point"}
}