{
  "type": "Feature",
  "properties": {
    "addr:full":"Calle de Castellon, 9 Santa Pola Alicante 03130",
    "addr:housenumber":"9",
    "addr:postcode":"03130",
    "addr:street":"Calle De Castellon",
    "iso:country":"ES",
    "sg:address":"Calle de Castellon, 9",
    "sg:city":"Santa Pola",
    "sg:orig_category":"Peluquer\u00cdas, Peluquer\u00cda Mixta",
    "sg:phone":"+34 966 69 20 17",
    "sg:postcode":"03130",
    "sg:province":"Alicante",
    "wof:name":"Gomez Luzon Benerada",
    "wof:placetype":"venue"
},
  "geometry": {"coordinates":[-0.5651643872,38.19272995],"type":"Point"}
}