{
  "type": "Feature",
  "properties": {
    "addr:full":"Calle de Trabudu, 2 Astrabudua Vizcaya 48950",
    "addr:housenumber":"2",
    "addr:postcode":"48950",
    "addr:street":"Calle De Trabudu",
    "iso:country":"ES",
    "sg:address":"Calle de Trabudu, 2",
    "sg:city":"Astrabudua",
    "sg:orig_category":"Supermercados Y Hipermercados",
    "sg:phone":"+34 944 67 35 29",
    "sg:postcode":"48950",
    "sg:province":"Vizcaya",
    "wof:name":"Eroski Sociedad Cooperativa",
    "wof:placetype":"venue"
},
  "geometry": {"coordinates":[-2.9831340313,43.3159561157],"type":"Point"}
}