{
  "type": "Feature",
  "properties": {
    "addr:full":"Calle de Nu\u00d1ez De Balboa, 17 Jaen Ja\u00e9n 23007",
    "addr:housenumber":"17;jae\u0301n",
    "addr:postcode":"23007",
    "addr:street":"Calle De Nun\u0303Ez De Balboa",
    "iso:country":"ES",
    "sg:address":"Calle de Nu\u00d1ez De Balboa, 17",
    "sg:city":"Jaen",
    "sg:orig_category":"Papeler\u00cdas, Librer\u00cdas",
    "sg:phone":"+34 953 25 77 14",
    "sg:postcode":"23007",
    "sg:province":"Ja\u00e9n",
    "wof:name":"Lopez Liebanas Jose",
    "wof:placetype":"venue"
},
  "geometry": {"coordinates":[-3.7935910225,37.7736244202],"type":"Point"}
}