{
  "type": "Feature",
  "properties": {
    "addr:full":"Avda Constitucion, 89 Torrejon Ardoz Madrid 28850",
    "addr:housenumber":"89",
    "addr:postcode":"28850",
    "addr:street":"Avda Constitucion",
    "iso:country":"ES",
    "sg:address":"Avda Constitucion, 89",
    "sg:city":"Torrejon Ardoz",
    "sg:orig_category":"Abogados",
    "sg:phone":"+34 916 75 52 88",
    "sg:postcode":"28850",
    "sg:province":"Madrid",
    "wof:name":"Heras Catalan Alfonso",
    "wof:placetype":"venue"
},
  "geometry": {"coordinates":[-3.4752290249,40.4568481445],"type":"Point"}
}