{
  "type": "Feature",
  "properties": {
    "iso:country":"ES",
    "sg:address":"Calle de Caravaca, 4",
    "sg:city":"Madrid",
    "sg:orig_category":"Peluqueros: De Se\u00d1oras",
    "sg:phone":"+34 915 27 43 27",
    "sg:postcode":"28012",
    "sg:province":"Madrid",
    "wof:name":"Gil Matos Jesus",
    "wof:placetype":"venue"
},
  "geometry": {"coordinates":[-3.7022819519,40.4091796875],"type":"Point"}
}