{
  "type": "Feature",
  "properties": {
    "iso:country":"ES",
    "sg:address":"Calle de Padre Manuel Fernandez, 19",
    "sg:city":"Jerez De La Frontera",
    "sg:orig_category":"Fabricaci\u00d3n, Venta, Instalaci\u00d3n De R\u00d3tulos, De R\u00d3tulos Luminosos",
    "sg:phone":"+34 956 32 33 78",
    "sg:postcode":"11408",
    "sg:province":"C\u00e1diz",
    "wof:name":"Luminosos Iglesias S.l.",
    "wof:placetype":"venue"
},
  "geometry": {"coordinates":[-6.1485929489,36.6848983765],"type":"Point"}
}