{
  "type": "Feature",
  "properties": {
    "iso:country":"ES",
    "sg:address":"Avda Libertad (de La), 15",
    "sg:city":"Colmenar Viejo",
    "sg:orig_category":"Sociedades, Compa\u00d1\u00cdas Aseguradoras",
    "sg:phone":"+34 918 46 37 79",
    "sg:postcode":"28770",
    "sg:province":"Madrid",
    "wof:name":"Nieto & Concha Asesores Asociados S.l.",
    "wof:placetype":"venue"
},
  "geometry": {"coordinates":[-3.7663440704,40.6621170044],"type":"Point"}
}