{
  "type": "Feature",
  "properties": {
    "iso:country":"ES",
    "sg:address":"Avda Val (do), 8",
    "sg:city":"Vilanova",
    "sg:orig_category":"Caf\u00c9s, Bares, Cervecer\u00cdas",
    "sg:phone":"+34 982 12 12 90",
    "sg:postcode":"27760",
    "sg:province":"Lugo",
    "wof:name":"Fernandez Rodriguez Manuel",
    "wof:placetype":"venue"
},
  "geometry": {"coordinates":[-7.2977337837,43.4696350098],"type":"Point"}
}