{
  "type": "Feature",
  "properties": {
    "iso:country":"ES",
    "sg:address":"Rua Montero Rios (de), 23",
    "sg:city":"Santiago De Compostela",
    "sg:orig_category":"Zapatos (al Por Menor)",
    "sg:phone":"+34 981 59 26 77",
    "sg:postcode":"15706",
    "sg:province":"La Coru\u00f1a",
    "wof:name":"Arias Vicente Ricardo",
    "wof:placetype":"venue"
},
  "geometry": {"coordinates":[-8.5494632721,42.8754692078],"type":"Point"}
}