{
  "type": "Feature",
  "properties": {
    "addr:full":"Av Sant Jordi, 8 Arbo\u00e7 Tarragona 43720",
    "addr:housenumber":"8",
    "addr:postcode":"43720",
    "addr:street":"Av Sant Jordi",
    "iso:country":"ES",
    "sg:address":"Av Sant Jordi, 8",
    "sg:city":"Arbo\u00e7",
    "sg:orig_category":"Reposter\u00cdas",
    "sg:phone":"+34 977 67 19 30",
    "sg:postcode":"43720",
    "sg:province":"Tarragona",
    "wof:name":"Rius Paricio Enric",
    "wof:placetype":"venue"
},
  "geometry": {"coordinates":[1.5990799665,41.2690467834],"type":"Point"}
}