{
  "type": "Feature",
  "properties": {
    "iso:country":"ES",
    "sg:address":"Calle de Tajo, 11",
    "sg:city":"Alameda Sagra",
    "sg:orig_category":"Servicios Gsm",
    "sg:phone":"+34 925 54 90 76",
    "sg:postcode":"45240",
    "sg:province":"Toledo",
    "wof:name":"Electrodomesticos Ruano Tardio S.l.",
    "wof:placetype":"venue"
},
  "geometry": {"coordinates":[-3.7915349007,40.0110855103],"type":"Point"}
}