{
  "type": "Feature",
  "properties": {
    "addr:full":"Carretera Alcolea Del Pinar, Km. 0365,0 Calanda Teruel 44570",
    "addr:postcode":"44570",
    "addr:street":"Carretera Alcolea Del Pinar Km. 0365,0",
    "iso:country":"ES",
    "sg:address":"Carretera Alcolea Del Pinar, Km. 0365,0",
    "sg:city":"Calanda",
    "sg:orig_category":"Molduras, Junquillos, Listones Y Molduras Perforadas",
    "sg:phone":"+34 978 84 78 04",
    "sg:postcode":"44570",
    "sg:province":"Teruel",
    "sg:website":"www.gilva.com",
    "wof:name":"Gilva S. A.",
    "wof:placetype":"venue"
},
  "geometry": {"coordinates":[-0.2323540002,40.9430961609],"type":"Point"}
}