{
  "type": "Feature",
  "properties": {
    "iso:country":"ES",
    "sg:address":"Carrer de Mare Jeanne Jugan, 2",
    "sg:city":"Palma",
    "sg:orig_category":"Asesor\u00cda Sobre Comunicaci\u00d3n De Empresas",
    "sg:phone":"+34 971 29 85 12",
    "sg:postcode":"07010",
    "sg:province":"Islas Baleares",
    "wof:name":"Escudero Comas Bartolome",
    "wof:placetype":"venue"
},
  "geometry": {"coordinates":[2.6461451054,39.5819015503],"type":"Point"}
}