{
  "type": "Feature",
  "properties": {
    "iso:country":"ES",
    "sg:address":"Calle de Puerta De Talavera, 1",
    "sg:city":"Plasencia",
    "sg:orig_category":"Laboratorios Y Cl\u00cdnicas Veterinarias",
    "sg:phone":"+34 927 41 15 21",
    "sg:postcode":"10600",
    "sg:province":"C\u00e1ceres",
    "wof:name":"Moreno Guisado Ulises",
    "wof:placetype":"venue"
},
  "geometry": {"coordinates":[-6.0891590118,40.0287094116],"type":"Point"}
}