{
  "type": "Feature",
  "properties": {
    "iso:country":"ES",
    "sg:address":"Calle de Salces Anselma De, 14",
    "sg:city":"Bilbao",
    "sg:orig_category":"Edici\u00d3n De Diarios, Revistas, Boletines",
    "sg:phone":"+34 944 00 16 27",
    "sg:postcode":"48007",
    "sg:province":"Vizcaya",
    "wof:name":"Etor Ostoa S.l.",
    "wof:placetype":"venue"
},
  "geometry": {"coordinates":[-2.923995018,43.2669677734],"type":"Point"}
}