{
  "type": "Feature",
  "properties": {
    "addr:full":"Calle de Claudio Coello, 16 Madrid Madrid 28001",
    "addr:housenumber":"16",
    "addr:postcode":"madrid;28001",
    "addr:street":"Calle De Claudio Coello",
    "iso:country":"ES",
    "sg:address":"Calle de Claudio Coello, 16",
    "sg:city":"Madrid",
    "sg:orig_category":"Art\u00cdculos De Decoraci\u00d3n",
    "sg:phone":"+34 915 77 91 55",
    "sg:postcode":"28001",
    "sg:province":"Madrid",
    "sg:website":"www.venini.com",
    "wof:name":"Alcolea Albero Fernando",
    "wof:placetype":"venue"
},
  "geometry": {"coordinates":[-3.6869935989,40.4223480225],"type":"Point"}
}