{
  "type": "Feature",
  "properties": {
    "iso:country":"ES",
    "sg:address":"Calle de Argumosa, 31",
    "sg:city":"Madrid",
    "sg:orig_category":"Florister\u00cdas",
    "sg:phone":"+34 915 39 23 26",
    "sg:postcode":"28012",
    "sg:province":"Madrid",
    "wof:name":"Gil Garcia De Blas Jose Maria",
    "wof:placetype":"venue"
},
  "geometry": {"coordinates":[-3.6974182129,40.4079246521],"type":"Point"}
}