{
  "type": "Feature",
  "properties": {
    "iso:country":"ES",
    "sg:address":"Pl Progres, 12",
    "sg:city":"Palma",
    "sg:orig_category":"Traductores",
    "sg:phone":"+34 971 73 45 55",
    "sg:postcode":"07013",
    "sg:province":"Islas Baleares",
    "wof:name":"Vaucelle  Patrice",
    "wof:placetype":"venue"
},
  "geometry": {"coordinates":[2.6364150047,39.5715904236],"type":"Point"}
}