{
  "type": "Feature",
  "properties": {
    "addr:full":"Avda San Fernando, 34 Rota C\u00e1diz 11520",
    "addr:housenumber":"34",
    "addr:postcode":"11520",
    "addr:street":"Avda San Fernando;Ca\u0301Diz",
    "iso:country":"ES",
    "sg:address":"Avda San Fernando, 34",
    "sg:city":"Rota",
    "sg:orig_category":"Albergues",
    "sg:phone":"+34 956 81 62 08",
    "sg:postcode":"11520",
    "sg:province":"C\u00e1diz",
    "wof:name":"Hostal La Giralda",
    "wof:placetype":"venue"
},
  "geometry": {"coordinates":[-6.3605308533,36.6222877502],"type":"Point"}
}