{
  "type": "Feature",
  "properties": {
    "addr:full":"Calle de Primero De Mayo, 13 Salamanca Salamanca 37004",
    "addr:housenumber":"13",
    "addr:postcode":"37004",
    "addr:street":"Calle De Primero De Mayo",
    "iso:country":"ES",
    "sg:address":"Calle de Primero De Mayo, 13",
    "sg:city":"Salamanca",
    "sg:orig_category":"Aceros Inoxidables",
    "sg:phone":"+34 923 25 55 18",
    "sg:postcode":"37004",
    "sg:province":"Salamanca",
    "wof:name":"Innovaciones En Comercio Y Manufacturas S.r.l.",
    "wof:placetype":"venue"
},
  "geometry": {"coordinates":[-5.6568641663,40.9700546265],"type":"Point"}
}