{
  "type": "Feature",
  "properties": {
    "addr:full":"Trva Aguasantas, 6 Jerez De Los Caballeros Badajoz 06380",
    "addr:housenumber":"6",
    "addr:postcode":"06380",
    "addr:street":"Trva Aguasantas",
    "iso:country":"ES",
    "sg:address":"Trva Aguasantas, 6",
    "sg:city":"Jerez De Los Caballeros",
    "sg:orig_category":"Carnicer\u00cdas, Carnicer\u00cdas",
    "sg:phone":"+34 924 73 00 45",
    "sg:postcode":"06380",
    "sg:province":"Badajoz",
    "wof:name":"Jamones Y Embutidos Jierrito Alejo S.l:",
    "wof:placetype":"venue"
},
  "geometry": {"coordinates":[-6.7760648727,38.3203735352],"type":"Point"}
}