{
  "type": "Feature",
  "properties": {
    "iso:country":"ES",
    "sg:address":"Calle de Caceres, 5",
    "sg:city":"Albacete",
    "sg:orig_category":"Alimentaci\u00d3n General (al Por Menor)",
    "sg:phone":"+34 967 23 09 90",
    "sg:postcode":"02006",
    "sg:province":"Albacete",
    "wof:name":"Juan Bautista Marco Lopez-miguel Marco Lopez Cdad.",
    "wof:placetype":"venue"
},
  "geometry": {"coordinates":[-1.873257041,38.9943313599],"type":"Point"}
}