{
  "type": "Feature",
  "properties": {
    "addr:full":"Calle de San Clemente, 1 Jaen Ja\u00e9n 23001",
    "addr:housenumber":"1;jae\u0301n",
    "addr:postcode":"23001",
    "addr:street":"Calle De San Clemente",
    "iso:country":"ES",
    "sg:address":"Calle de San Clemente, 1",
    "sg:city":"Jaen",
    "sg:classifiers":[
        {
            "category":"Autos & Motor Vehicles",
            "subcategory":"Automobile Sales",
            "type":"Retail Goods"
        }
    ],
    "sg:phone":"+34 953 24 25 09",
    "sg:postcode":"23001",
    "sg:province":"Ja\u00e9n",
    "wof:name":"Robles Moreno Salvador",
    "wof:placetype":"venue"
},
  "geometry": {"coordinates":[-3.7882530689,37.7676467896],"type":"Point"}
}