{
  "type": "Feature",
  "properties": {
    "iso:country":"ES",
    "sg:address":"Calle de Santapau, 2",
    "sg:city":"Torrecilla De Alca\u00e7iz",
    "sg:orig_category":"Carnicer\u00cdas, Carnicer\u00cdas",
    "sg:phone":"+34 978 85 24 05",
    "sg:postcode":"44640",
    "sg:province":"Teruel",
    "wof:name":"Velilla Sancho Antonio",
    "wof:placetype":"venue"
},
  "geometry": {"coordinates":[-0.085878998,40.9342918396],"type":"Point"}
}