{
  "type": "Feature",
  "properties": {
    "addr:full":"Pol Ind Munic Transv 4, 33 Tudela Navarra 31500",
    "addr:housenumber":"4",
    "addr:postcode":"31500",
    "addr:street":"Transv",
    "iso:country":"ES",
    "sg:address":"Pol Ind Munic Transv 4, 33",
    "sg:city":"Tudela",
    "sg:orig_category":"Promotores Constructores",
    "sg:phone":"+34 948 40 24 29",
    "sg:postcode":"31500",
    "sg:province":"Navarra",
    "wof:name":"Aisforma Tudela S.l.",
    "wof:placetype":"venue"
},
  "geometry": {"coordinates":[-1.4821481705,42.1872329712],"type":"Point"}
}