{
  "type": "Feature",
  "properties": {
    "addr:full":"Calle de Rafael Perez Del Alamo, 32 Loja Granada 18300",
    "addr:housenumber":"32 loja",
    "addr:postcode":"18300",
    "addr:street":"Calle De Rafael Perez Del Alamo",
    "iso:country":"ES",
    "sg:address":"Calle de Rafael Perez Del Alamo, 32",
    "sg:city":"Loja",
    "sg:orig_category":"Producci\u00d3n, Distribuci\u00d3n De Electricidad",
    "sg:phone":"+34 958 32 12 70",
    "sg:postcode":"18300",
    "sg:province":"Granada",
    "wof:name":"I.e.gomez Rogel S.l.",
    "wof:placetype":"venue"
},
  "geometry": {"coordinates":[-4.1455841064,37.1660232544],"type":"Point"}
}