{
  "type": "Feature",
  "properties": {
    "addr:full":"Ctra Sardina, Km. 0002,1 Puerto De Sardina Las Palmas 35469",
    "addr:postcode":"35469",
    "addr:street":"Ctra Sardina Km. 0002,1 Puerto De Sardina Las",
    "iso:country":"ES",
    "sg:address":"Ctra Sardina, Km. 0002,1",
    "sg:city":"Puerto De Sardina",
    "sg:orig_category":"Quincaller\u00cda (al Por Menor)",
    "sg:phone":"+34 928 55 27 85",
    "sg:postcode":"35469",
    "sg:province":"Las Palmas",
    "wof:name":"Materiales De Construccion Gil Chinea S.l.",
    "wof:placetype":"venue"
},
  "geometry": {"coordinates":[-15.6945705414,28.1516628265],"type":"Point"}
}