{
  "type": "Feature",
  "properties": {
    "iso:country":"ES",
    "sg:address":"Calle de Montanejos, S/n",
    "sg:city":"Castellon De La Plana",
    "sg:orig_category":"Electromec\u00c1nica",
    "sg:phone":"+34 964 25 14 74",
    "sg:postcode":"12005",
    "sg:province":"Castell\u00f3n",
    "wof:name":"Manteca Moragrega Carlos",
    "wof:placetype":"venue"
},
  "geometry": {"coordinates":[-0.0553690009,39.9678688049],"type":"Point"}
}