{
  "type": "Feature",
  "properties": {
    "addr:full":"Calle de Rincon De Luna, 1 Algeciras C\u00e1diz 11204",
    "addr:housenumber":"1;ca\u0301diz",
    "addr:postcode":"11204",
    "addr:street":"Calle De Rincon De Luna",
    "iso:country":"ES",
    "sg:address":"Calle de Rincon De Luna, 1",
    "sg:city":"Algeciras",
    "sg:orig_category":"Veh\u00cdculos De Ocasi\u00d3n",
    "sg:phone":"+34 956 65 41 32",
    "sg:postcode":"11204",
    "sg:province":"C\u00e1diz",
    "wof:name":"Multiauto S.l.",
    "wof:placetype":"venue"
},
  "geometry": {"coordinates":[-5.4574589729,36.1408195496],"type":"Point"}
}