{
  "type": "Feature",
  "properties": {
    "addr:full":"Calle de Doctor Sanchis Sivera, 18 Valencia Valencia 46008",
    "addr:housenumber":"18",
    "addr:postcode":"46008",
    "addr:street":"Calle De Doctor Sanchis Sivera",
    "iso:country":"ES",
    "sg:address":"Calle de Doctor Sanchis Sivera, 18",
    "sg:city":"Valencia",
    "sg:orig_category":"Expertos Contables, Revisores De Cuentas",
    "sg:phone":"+34 963 84 31 61",
    "sg:postcode":"46008",
    "sg:province":"Valencia",
    "wof:name":"Ibergrup Auditores S.a.",
    "wof:placetype":"venue"
},
  "geometry": {"coordinates":[-0.3868862987,39.4687042236],"type":"Point"}
}