{
  "type": "Feature",
  "properties": {
    "addr:full":"Carrer de Torrent D'en Baiell, 23 Sentmenat Barcelona 08181",
    "addr:housenumber":"23",
    "addr:postcode":"08181",
    "addr:street":"Carrer De Torrent D'En Baiell",
    "iso:country":"ES",
    "sg:address":"Carrer de Torrent D'en Baiell, 23",
    "sg:city":"Sentmenat",
    "sg:orig_category":"Construcciones Met\u00c1licas",
    "sg:phone":"+34 937 15 38 38",
    "sg:postcode":"08181",
    "sg:province":"Barcelona",
    "wof:name":"Creaciones Metalicas Sola S.l.",
    "wof:placetype":"venue"
},
  "geometry": {"coordinates":[2.1458630562,41.6122055054],"type":"Point"}
}