{
  "type": "Feature",
  "properties": {
    "addr:full":"Calle de Martires, 201 Roda Albacete 02630",
    "addr:housenumber":"201",
    "addr:postcode":"02630",
    "addr:street":"Calle De Martires",
    "iso:country":"ES",
    "sg:address":"Calle de Martires, 201",
    "sg:city":"Roda",
    "sg:orig_category":"Chapister\u00cda",
    "sg:phone":"+34 967 44 20 39",
    "sg:postcode":"02630",
    "sg:province":"Albacete",
    "wof:name":"Talleres Remo S.l.",
    "wof:placetype":"venue"
},
  "geometry": {"coordinates":[-2.1672620773,39.2101402283],"type":"Point"}
}