{
  "type": "Feature",
  "properties": {
    "iso:country":"ES",
    "sg:address":"Sector F, 33",
    "sg:city":"Urb. Mas Camarena",
    "sg:orig_category":"Embalajes",
    "sg:phone":"+34 961 68 60 55",
    "sg:postcode":"46117",
    "sg:province":"Valencia",
    "sg:website":"www.precygrap.com",
    "wof:name":"Jover Bou Juan Manuel",
    "wof:placetype":"venue"
},
  "geometry": {"coordinates":[-0.4597580135,39.556728363],"type":"Point"}
}