{
  "type": "Feature",
  "properties": {
    "addr:full":"Bordaberri, 16 Sorabilla Guip\u00f9zcoa 20140",
    "addr:housenumber":"16",
    "addr:postcode":"20140",
    "addr:street":"Bordaberri;Guipu\u0300Zcoa",
    "iso:country":"ES",
    "sg:address":"Bordaberri, 16",
    "sg:city":"Sorabilla",
    "sg:orig_category":"Otros Trabajos De Limpieza Y Mantenimiento (extracci\u00d3n De Polvo, Recogida De Amianto Y Desespumado)",
    "sg:phone":"+34 943 59 28 09",
    "sg:postcode":"20140",
    "sg:province":"Guip\u00f9zcoa",
    "wof:name":"Landa Lan S.a.",
    "wof:placetype":"venue"
},
  "geometry": {"coordinates":[-2.0200839043,43.2191047668],"type":"Point"}
}