{
  "type": "Feature",
  "properties": {
    "addr:full":"Urb Sant Jaume Mediterrani, S/n San Jaime Mediterraneo Islas Baleares 07730",
    "addr:housenumber":"s / n",
    "addr:postcode":"07730",
    "addr:street":"Urb Sant Jaume Mediterrani;San Jaime Mediterraneo Islas",
    "iso:country":"ES",
    "sg:address":"Urb Sant Jaume Mediterrani, S/n",
    "sg:city":"San Jaime Mediterraneo",
    "sg:orig_category":"Alquiler De Veh\u00cdculos: Turismos Y Utilitarios",
    "sg:phone":"+34 971 37 84 11",
    "sg:postcode":"07730",
    "sg:province":"Islas Baleares",
    "wof:name":"Betacar Menorca S.a.",
    "wof:placetype":"venue"
},
  "geometry": {"coordinates":[4.1400952339,39.930721283],"type":"Point"}
}