{
  "type": "Feature",
  "properties": {
    "iso:country":"ES",
    "sg:address":"Calle de Tabernas, 20",
    "sg:city":"Coru\u00d1a",
    "sg:orig_category":"Promotores Constructores",
    "sg:phone":"+34 981 22 63 00",
    "sg:postcode":"15001",
    "sg:province":"La Coru\u00f1a",
    "wof:name":"Milsa Trillo Galicia S.a.",
    "wof:placetype":"venue"
},
  "geometry": {"coordinates":[-8.3943099976,43.3690757751],"type":"Point"}
}