{
  "type": "Feature",
  "properties": {
    "iso:country":"ES",
    "sg:address":"Carrer de Plegamans, 2",
    "sg:city":"Palau-solita I Plegamans",
    "sg:orig_category":"Ense\u00d1anza: Idiomas",
    "sg:phone":"+34 938 64 94 12",
    "sg:postcode":"08184",
    "sg:province":"Barcelona",
    "wof:name":"Costello  Garry John",
    "wof:placetype":"venue"
},
  "geometry": {"coordinates":[2.1809549332,41.5883865356],"type":"Point"}
}