{
  "type": "Feature",
  "properties": {
    "addr:full":"Calle de Papatos, 16 Fuentesauco Zamora 49400",
    "addr:housenumber":"16",
    "addr:postcode":"49400",
    "addr:street":"Calle De Papatos;Zamora",
    "iso:country":"ES",
    "sg:address":"Calle de Papatos, 16",
    "sg:city":"Fuentesauco",
    "sg:orig_category":"Librer\u00cdas",
    "sg:phone":"+34 980 60 11 15",
    "sg:postcode":"49400",
    "sg:province":"Zamora",
    "wof:name":"Perez Tola Francisco",
    "wof:placetype":"venue"
},
  "geometry": {"coordinates":[-5.4882678986,41.2406005859],"type":"Point"}
}