{
  "type": "Feature",
  "properties": {
    "addr:full":"Avda Desiderio Rodriguez, 27 Torrevieja Alicante 03180",
    "addr:housenumber":"27",
    "addr:postcode":"03180",
    "addr:street":"Avda Desiderio Rodriguez",
    "iso:country":"ES",
    "sg:address":"Avda Desiderio Rodriguez, 27",
    "sg:city":"Torrevieja",
    "sg:orig_category":"Molduras, Junquillos, Listones Y Molduras Perforadas",
    "sg:phone":"+34 966 70 77 51",
    "sg:postcode":"03180",
    "sg:province":"Alicante",
    "wof:name":"Eurotel-sur S.l.",
    "wof:placetype":"venue"
},
  "geometry": {"coordinates":[-0.6536790133,38.0173606873],"type":"Point"}
}