{
  "type": "Feature",
  "properties": {
    "addr:full":"Ctra Palma, De, 26 Soller Islas Baleares 07100",
    "addr:housenumber":"26",
    "addr:postcode":"07100",
    "addr:street":"Ctra Palma De",
    "iso:country":"ES",
    "sg:address":"Ctra Palma, De, 26",
    "sg:city":"Soller",
    "sg:orig_category":"Artesanado",
    "sg:phone":"+34 971 63 47 92",
    "sg:postcode":"07100",
    "sg:province":"Islas Baleares",
    "wof:name":"Gallego Selles Francisco",
    "wof:placetype":"venue"
},
  "geometry": {"coordinates":[2.7026746273,39.7488594055],"type":"Point"}
}