{
  "type": "Feature",
  "properties": {
    "iso:country":"ES",
    "sg:address":"Las Majas De Goya, 3",
    "sg:city":"Zaragoza",
    "sg:orig_category":"Promotores Constructores",
    "sg:phone":"+34 976 73 36 91",
    "sg:postcode":"50018",
    "sg:province":"Zaragoza",
    "wof:name":"Comunidad De Propietarios Maja De Goya 1-11 Y Plaza Tantalos 1-2 Y Rafael Estevez Vilella 2-4",
    "wof:placetype":"venue"
},
  "geometry": {"coordinates":[-0.8746470213,41.6862792969],"type":"Point"}
}