{
  "type": "Feature",
  "properties": {
    "iso:country":"ES",
    "sg:address":"Partida Secanet, 28",
    "sg:city":"Torres",
    "sg:orig_category":"Promotores Constructores",
    "sg:phone":"+34 966 85 03 95",
    "sg:postcode":"03570",
    "sg:province":"Alicante",
    "wof:name":"Ana Pau S.l.",
    "wof:placetype":"venue"
},
  "geometry": {"coordinates":[-0.2034970969,38.5181427002],"type":"Point"}
}