{
  "type": "Feature",
  "properties": {
    "iso:country":"ES",
    "sg:address":"Carrer de Trasime, 16",
    "sg:city":"Arenal",
    "sg:orig_category":"Peluquer\u00cdas, Peluquer\u00cda Mixta",
    "sg:phone":"+34 971 26 68 31",
    "sg:postcode":"07600",
    "sg:province":"Islas Baleares",
    "wof:name":"Ramiro Garcia Esperanza",
    "wof:placetype":"venue"
},
  "geometry": {"coordinates":[2.751226902,39.5088844299],"type":"Point"}
}