{
  "type": "Feature",
  "properties": {
    "addr:full":"Calle de Amor De Dios, 14 Mairena Alcor Sevilla 41510",
    "addr:housenumber":"14",
    "addr:postcode":"41510",
    "addr:street":"Calle De Amor De Dios",
    "iso:country":"ES",
    "sg:address":"Calle de Amor De Dios, 14",
    "sg:city":"Mairena Alcor",
    "sg:orig_category":"M\u00c9dicos: Estomatolog\u00cda",
    "sg:phone":"+34 955 94 22 31",
    "sg:postcode":"41510",
    "sg:province":"Sevilla",
    "wof:name":"Vilches De La Paz Ernesto",
    "wof:placetype":"venue"
},
  "geometry": {"coordinates":[-5.755384922,37.370929718],"type":"Point"}
}