{
  "type": "Feature",
  "properties": {
    "iso:country":"ES",
    "sg:address":"Calle de Pollo Martin, 26",
    "sg:city":"Salamanca",
    "sg:orig_category":"Peluqueros: De Se\u00d1oras",
    "sg:phone":"+34 923 23 57 70",
    "sg:postcode":"37005",
    "sg:province":"Salamanca",
    "wof:name":"Alvarez Garcia Ascension",
    "wof:placetype":"venue"
},
  "geometry": {"coordinates":[-5.6592898369,40.9705200195],"type":"Point"}
}