{
  "type": "Feature",
  "properties": {
    "addr:full":"Calle de Juez Braulio Sena, 40 Carolina Ja\u00e9n 23200",
    "addr:housenumber":"40",
    "addr:postcode":"23200",
    "addr:street":"Calle De Juez Braulio Sena;Jae\u0301N",
    "iso:country":"ES",
    "sg:address":"Calle de Juez Braulio Sena, 40",
    "sg:city":"Carolina",
    "sg:orig_category":"Quincaller\u00cda (al Por Menor)",
    "sg:phone":"+34 953 66 09 97",
    "sg:postcode":"23200",
    "sg:province":"Ja\u00e9n",
    "wof:name":"Montes Lloreda Juana Maria",
    "wof:placetype":"venue"
},
  "geometry": {"coordinates":[-3.6130440235,38.2771720886],"type":"Point"}
}