{
  "type": "Feature",
  "properties": {
    "iso:country":"ES",
    "sg:address":"Pl Arbres (dels), 7",
    "sg:city":"Vila-rodona",
    "sg:orig_category":"Museos",
    "sg:phone":"+34 977 63 80 06",
    "sg:postcode":"43814",
    "sg:province":"Tarragona",
    "wof:name":"Ajuntament De Vila-rodona",
    "wof:placetype":"venue"
},
  "geometry": {"coordinates":[1.3586901426,41.3106536865],"type":"Point"}
}