{
  "type": "Feature",
  "properties": {
    "iso:country":"ES",
    "sg:address":"Avda San Martin De Valdeiglesia, 24",
    "sg:city":"Alcorcon",
    "sg:orig_category":"Electrodom\u00c9sticos (al Por Menor)",
    "sg:phone":"+34 916 11 21 16",
    "sg:postcode":"28922",
    "sg:province":"Madrid",
    "sg:website":"www.miro.es",
    "wof:name":"Establecimientos Miro S.l.",
    "wof:placetype":"venue"
},
  "geometry": {"coordinates":[-3.8209710121,40.3563041687],"type":"Point"}
}