{
  "type": "Feature",
  "properties": {
    "addr:full":"Avda Enrique Mederos, 13 Llanos De Aridane Santa Cruz De Tenerife 38760",
    "addr:housenumber":"13",
    "addr:postcode":"38760",
    "addr:street":"Avda Enrique Mederos",
    "iso:country":"ES",
    "sg:address":"Avda Enrique Mederos, 13",
    "sg:city":"Llanos De Aridane",
    "sg:orig_category":"Electrodom\u00c9sticos (al Por Menor)",
    "sg:phone":"+34 922 40 30 38",
    "sg:postcode":"38760",
    "sg:province":"Santa Cruz De Tenerife",
    "wof:name":"Comercial Antani S. L.",
    "wof:placetype":"venue"
},
  "geometry": {"coordinates":[-17.9085597992,28.6563796997],"type":"Point"}
}