{
  "type": "Feature",
  "properties": {
    "iso:country":"ES",
    "sg:address":"Calle de Sacerdote Angel Mu\u00d1oz, 18",
    "sg:city":"Almaden",
    "sg:orig_category":"Bares, Piano",
    "sg:phone":"+34 926 71 20 24",
    "sg:postcode":"13400",
    "sg:province":"Ciudad Real",
    "wof:name":"Puerto Arenas Lorenza",
    "wof:placetype":"venue"
},
  "geometry": {"coordinates":[-4.831949234,38.7756614685],"type":"Point"}
}