{
  "type": "Feature",
  "properties": {
    "addr:full":"Avda Reina Mercedes, 29 Sevilla Sevilla 41012",
    "addr:housenumber":"29",
    "addr:postcode":"41012",
    "addr:street":"Avda Reina Mercedes",
    "iso:country":"ES",
    "sg:address":"Avda Reina Mercedes, 29",
    "sg:city":"Sevilla",
    "sg:orig_category":"Ingenier\u00cda, Centros De Estudios (diversos)",
    "sg:phone":"+34 954 61 23 85",
    "sg:postcode":"41012",
    "sg:province":"Sevilla",
    "wof:name":"Fernandez De Cordova Lubian Fernando",
    "wof:placetype":"venue"
},
  "geometry": {"coordinates":[-5.9859790802,37.3598632812],"type":"Point"}
}