{
  "type": "Feature",
  "properties": {
    "iso:country":"ES",
    "sg:address":"Calle de Inmaculada Concepcion, 48",
    "sg:city":"Madrid",
    "sg:orig_category":"Pescader\u00cdas (al Por Menor)",
    "sg:phone":"+34 914 69 43 02",
    "sg:postcode":"28019",
    "sg:province":"Madrid",
    "wof:name":"Fejusa S.l.",
    "wof:placetype":"venue"
},
  "geometry": {"coordinates":[-3.7126719952,40.3912124634],"type":"Point"}
}