{
  "type": "Feature",
  "properties": {
    "iso:country":"ES",
    "sg:address":"Carrer de Gremi Teixidors, 36",
    "sg:city":"Poligon Industrial De Son Castello",
    "sg:orig_category":"Centros Empresariales",
    "sg:phone":"+34 971 43 37 56",
    "sg:postcode":"07009",
    "sg:province":"Islas Baleares",
    "wof:name":"Balear De Servicios Y Mto. Durango Mila",
    "wof:placetype":"venue"
},
  "geometry": {"coordinates":[2.6776249409,39.6072845459],"type":"Point"}
}