{
  "type": "Feature",
  "properties": {
    "addr:full":"Avda Enrique Mederos, 16 Llanos De Aridane Santa Cruz De Tenerife 38760",
    "addr:housenumber":"16",
    "addr:postcode":"38760",
    "addr:street":"Avda Enrique Mederos",
    "iso:country":"ES",
    "sg:address":"Avda Enrique Mederos, 16",
    "sg:city":"Llanos De Aridane",
    "sg:orig_category":"Ense\u00d1ante, Direcci\u00d3n",
    "sg:phone":"+34 922 46 20 74",
    "sg:postcode":"38760",
    "sg:province":"Santa Cruz De Tenerife",
    "wof:name":"Lorenzo Hernandez Antonio",
    "wof:placetype":"venue"
},
  "geometry": {"coordinates":[-17.9085597992,28.6563796997],"type":"Point"}
}