{
  "type": "Feature",
  "properties": {
    "iso:country":"ES",
    "sg:address":"Gamonal, 15",
    "sg:city":"Ejea Caballeros",
    "sg:orig_category":"Empresas De Desmonte",
    "sg:phone":"+34 976 66 22 71",
    "sg:postcode":"50600",
    "sg:province":"Zaragoza",
    "wof:name":"Excavaciones Arisa Sociedad Cooperativa",
    "wof:placetype":"venue"
},
  "geometry": {"coordinates":[-1.1263810396,42.1276893616],"type":"Point"}
}