{
  "type": "Feature",
  "properties": {
    "addr:full":"Calle de Gilet, 3 Valencia Valencia 46009",
    "addr:housenumber":"3",
    "addr:postcode":"46009",
    "addr:street":"Calle De Gilet",
    "iso:country":"ES",
    "sg:address":"Calle de Gilet, 3",
    "sg:city":"Valencia",
    "sg:orig_category":"Fabricaci\u00d3n, Importaci\u00d3n De L\u00c1mparas Y Bombillas",
    "sg:phone":"+34 963 40 53 48",
    "sg:postcode":"46009",
    "sg:province":"Valencia",
    "wof:name":"Decogar S.l.",
    "wof:placetype":"venue"
},
  "geometry": {"coordinates":[-0.3854880035,39.4867248535],"type":"Point"}
}