{
  "type": "Feature",
  "properties": {
    "addr:full":"Calle de Peso (el), 10 Logro\u00f1o La Rioja 26001",
    "addr:housenumber":"10",
    "addr:postcode":"26001",
    "addr:street":"Calle De Peso El;Rioja",
    "iso:country":"ES",
    "sg:address":"Calle de Peso (el), 10",
    "sg:city":"Logro\u00f1o",
    "sg:orig_category":"Frutas, Legumbres Frescas Y Tempranas (al Por Menor)",
    "sg:phone":"+34 941 20 02 13",
    "sg:postcode":"26001",
    "sg:province":"La Rioja",
    "wof:name":"Garcia Martinez Maria Concepcion",
    "wof:placetype":"venue"
},
  "geometry": {"coordinates":[-2.4475889206,42.465549469],"type":"Point"}
}