{
  "type": "Feature",
  "properties": {
    "iso:country":"ES",
    "sg:address":"Calle de Monasterio La Rabida, 22",
    "sg:city":"Aracena",
    "sg:orig_category":"M\u00c9dicos: An\u00c1lisis Cl\u00cdnicos",
    "sg:phone":"+34 959 12 82 50",
    "sg:postcode":"21200",
    "sg:province":"Huelva",
    "wof:name":"Laboratorios Nicb S.l.",
    "wof:placetype":"venue"
},
  "geometry": {"coordinates":[-6.5612440109,37.8929443359],"type":"Point"}
}