{
  "type": "Feature",
  "properties": {
    "addr:full":"Avda Cadiz (de), 1 Ubrique C\u00e1diz 11600",
    "addr:housenumber":"1",
    "addr:postcode":"11600",
    "addr:street":"Avda Cadiz De;Ca\u0301Diz",
    "iso:country":"ES",
    "sg:address":"Avda Cadiz (de), 1",
    "sg:city":"Ubrique",
    "sg:orig_category":"Marroquiner\u00cda (confecci\u00d3n)",
    "sg:phone":"+34 956 46 28 67",
    "sg:postcode":"11600",
    "sg:province":"C\u00e1diz",
    "wof:name":"Philipo Bas S.l.",
    "wof:placetype":"venue"
},
  "geometry": {"coordinates":[-5.4488692284,36.6773910522],"type":"Point"}
}