{
  "type": "Feature",
  "properties": {
    "addr:full":"Calle de Camino De San Antonio, 17 Motril Granada 18600",
    "addr:housenumber":"17",
    "addr:postcode":"18600",
    "addr:street":"Calle De Camino De San Antonio",
    "iso:country":"ES",
    "sg:address":"Calle de Camino De San Antonio, 17",
    "sg:city":"Motril",
    "sg:orig_category":"Discapacitados",
    "sg:phone":"+34 958 82 01 99",
    "sg:postcode":"18600",
    "sg:province":"Granada",
    "wof:name":"Federacion De Minusvalidos De La Costa Y Alpujarra Femicoal",
    "wof:placetype":"venue"
},
  "geometry": {"coordinates":[-3.5190234184,36.7465934753],"type":"Point"}
}