{
  "type": "Feature",
  "properties": {
    "addr:full":"Calle de Hombrados O\u00d1atibia, 4 Errenteria Guip\u00f9zcoa 20100",
    "addr:housenumber":"4",
    "addr:postcode":"20100",
    "addr:street":"Calle De Hombrados On\u0303Atibia;Guipu\u0300Zcoa",
    "iso:country":"ES",
    "sg:address":"Calle de Hombrados O\u00d1atibia, 4",
    "sg:city":"Errenteria",
    "sg:orig_category":"Empresas De Carpinter\u00cda",
    "sg:phone":"+34 943 52 06 43",
    "sg:postcode":"20100",
    "sg:province":"Guip\u00f9zcoa",
    "wof:name":"Talleres Ruma C.b.",
    "wof:placetype":"venue"
},
  "geometry": {"coordinates":[-1.8951699734,43.3077392578],"type":"Point"}
}