{
  "type": "Feature",
  "properties": {
    "iso:country":"ES",
    "sg:address":"Calle de Fika, 60",
    "sg:city":"Bilbao",
    "sg:orig_category":"Decoraci\u00d3n: Instalaci\u00d3n Y Talleres",
    "sg:phone":"+34 944 33 98 51",
    "sg:postcode":"48004",
    "sg:province":"Vizcaya",
    "wof:name":"Abdelhalim Yaafar Ashrlf",
    "wof:placetype":"venue"
},
  "geometry": {"coordinates":[-2.916993,43.252979],"type":"Point"}
}