{
  "type": "Feature",
  "properties": {
    "addr:full":"Avda Diaz Martinez Jesus, 3 Agreda Soria 42100",
    "addr:housenumber":"3",
    "addr:postcode":"42100",
    "addr:street":"Avda Diaz Martinez Jesus",
    "iso:country":"ES",
    "sg:address":"Avda Diaz Martinez Jesus, 3",
    "sg:city":"Agreda",
    "sg:orig_category":"Hilaturas (fibras Naturales Diversas)",
    "sg:phone":"+34 976 64 68 53",
    "sg:postcode":"42100",
    "sg:province":"Soria",
    "wof:name":"Lanas Y Pieles Ruiz C.b.",
    "wof:placetype":"venue"
},
  "geometry": {"coordinates":[-1.925418973,41.8540496826],"type":"Point"}
}