{
  "type": "Feature",
  "properties": {
    "addr:full":"Barri Carretera, S/n Llambilles Girona 17243",
    "addr:postcode":"17243",
    "addr:street":"Carretera S / N",
    "iso:country":"ES",
    "sg:address":"Barri Carretera, S/n",
    "sg:city":"Llambilles",
    "sg:orig_category":"Cerrajer\u00cda, Ferrallista",
    "sg:phone":"+34 972 46 80 93",
    "sg:postcode":"17243",
    "sg:province":"Girona",
    "wof:name":"Trias Vicens S.c.",
    "wof:placetype":"venue"
},
  "geometry": {"coordinates":[2.8570730686,41.9198265076],"type":"Point"}
}