{
  "type": "Feature",
  "properties": {
    "iso:country":"ES",
    "sg:address":"Calle de Aire, 87",
    "sg:city":"Aguilas",
    "sg:orig_category":"Molduras, Junquillos, Listones Y Molduras Perforadas",
    "sg:phone":"+34 968 41 13 67",
    "sg:postcode":"30880",
    "sg:province":"Murcia",
    "wof:name":"Perez Sanchez Maria",
    "wof:placetype":"venue"
},
  "geometry": {"coordinates":[-1.5745093822,37.4080085754],"type":"Point"}
}