{
  "type": "Feature",
  "properties": {
    "iso:country":"ES",
    "sg:address":"Calle de Armando Cotarelo, 1",
    "sg:city":"Vegadeo",
    "sg:orig_category":"Cajas De Ahorro",
    "sg:phone":"+34 985 47 67 26",
    "sg:postcode":"33770",
    "sg:province":"Asturias",
    "sg:website":"www.cajastur.es",
    "wof:name":"Caja De Ahorros De Asturias",
    "wof:placetype":"venue"
},
  "geometry": {"coordinates":[-7.0496053696,43.4642066956],"type":"Point"}
}