{
  "type": "Feature",
  "properties": {
    "addr:full":"Calle de Embajadores, 199 Madrid Madrid 28045",
    "addr:housenumber":"199",
    "addr:postcode":"28045",
    "addr:street":"Calle De Embajadores",
    "iso:country":"ES",
    "sg:address":"Calle de Embajadores, 199",
    "sg:city":"Madrid",
    "sg:orig_category":"Promotores Constructores",
    "sg:phone":"+34 915 06 21 68",
    "sg:postcode":"28045",
    "sg:province":"Madrid",
    "wof:name":"Sevillana De Proyectos Ven S.l.",
    "wof:placetype":"venue"
},
  "geometry": {"coordinates":[-3.6907579899,40.3878479004],"type":"Point"}
}