{
  "type": "Feature",
  "properties": {
    "addr:full":"Carr Coral, 14 Estartit Girona 17258",
    "addr:housenumber":"14",
    "addr:postcode":"17258",
    "addr:street":"Carr Coral",
    "iso:country":"ES",
    "sg:address":"Carr Coral, 14",
    "sg:city":"Estartit",
    "sg:orig_category":"M\u00c9dicos: Estomatolog\u00cda",
    "sg:phone":"+34 972 75 14 74",
    "sg:postcode":"17258",
    "sg:province":"Girona",
    "wof:name":"Vidal Estrany Narciso",
    "wof:placetype":"venue"
},
  "geometry": {"coordinates":[3.1878299713,42.0489959717],"type":"Point"}
}