{
  "type": "Feature",
  "properties": {
    "iso:country":"ES",
    "sg:address":"Urb. Valls Sant Mu\u00e7, S/n",
    "sg:city":"Rubi",
    "sg:orig_category":"Fabricaci\u00d3n De Juguetes Autom\u00c1ticos",
    "sg:phone":"+34 935 88 15 31",
    "sg:postcode":"08191",
    "sg:province":"Barcelona",
    "wof:name":"Borja Garcia Jose Antonio",
    "wof:placetype":"venue"
},
  "geometry": {"coordinates":[2.0281500816,41.4989509583],"type":"Point"}
}