{
  "type": "Feature",
  "properties": {
    "addr:full":"Avda Cristo Rey, 15 Ubeda Ja\u00e9n 23400",
    "addr:housenumber":"15",
    "addr:postcode":"23400",
    "addr:street":"Avda Cristo Rey;Jae\u0301N",
    "iso:country":"ES",
    "sg:address":"Avda Cristo Rey, 15",
    "sg:city":"Ubeda",
    "sg:orig_category":"M\u00c9dicos: Estomatolog\u00cda",
    "sg:phone":"+34 953 79 23 73",
    "sg:postcode":"23400",
    "sg:province":"Ja\u00e9n",
    "wof:name":"Garrido Palacios Maria Cruz",
    "wof:placetype":"venue"
},
  "geometry": {"coordinates":[-3.3782346249,38.0116004944],"type":"Point"}
}