{
  "type": "Feature",
  "properties": {
    "iso:country":"ES",
    "sg:address":"Avda Nuestra Se\u00d1ora Del Rocio, S/n",
    "sg:city":"Bonares",
    "sg:orig_category":"Panader\u00cdas, Panader\u00cdas",
    "sg:phone":"+34 959 36 63 61",
    "sg:postcode":"21830",
    "sg:province":"Huelva",
    "wof:name":"Cooperativa Panificadora San Francisco De Borja",
    "wof:placetype":"venue"
},
  "geometry": {"coordinates":[-6.6794548035,37.322593689],"type":"Point"}
}