{
  "type": "Feature",
  "properties": {
    "addr:full":"Pla\u00c7 Doctor Farinos, 2 Moncada Valencia 46113",
    "addr:housenumber":"2",
    "addr:postcode":"46113",
    "addr:street":"Doctor Farinos",
    "iso:country":"ES",
    "sg:address":"Pla\u00c7 Doctor Farinos, 2",
    "sg:city":"Moncada",
    "sg:orig_category":"Bancos",
    "sg:phone":"+34 961 30 11 28",
    "sg:postcode":"46113",
    "sg:province":"Valencia",
    "wof:name":"Deutsche Bank S.a.e.",
    "wof:placetype":"venue"
},
  "geometry": {"coordinates":[-0.3959240019,39.5443954468],"type":"Point"}
}