{
  "type": "Feature",
  "properties": {
    "iso:country":"ES",
    "sg:address":"Calle de Juan Bravo, 6",
    "sg:city":"Segovia",
    "sg:orig_category":"Mercer\u00cda, Lencer\u00cda (al Por Menor)",
    "sg:phone":"+34 921 46 34 58",
    "sg:postcode":"40001",
    "sg:province":"Segovia",
    "wof:name":"Rodriguez Enriquez Raquel",
    "wof:placetype":"venue"
},
  "geometry": {"coordinates":[-4.123041153,40.9490966797],"type":"Point"}
}