{
  "type": "Feature",
  "properties": {
    "addr:full":"Avda Juan Carlos I, 47 Corralejo Las Palmas 35660",
    "addr:housenumber":"47",
    "addr:postcode":"35660",
    "addr:street":"Avda Juan Carlos I",
    "iso:country":"ES",
    "sg:address":"Avda Juan Carlos I, 47",
    "sg:city":"Corralejo",
    "sg:orig_category":"Mercer\u00cda, Lencer\u00cda (al Por Menor)",
    "sg:phone":"+34 928 86 75 53",
    "sg:postcode":"35660",
    "sg:province":"Las Palmas",
    "wof:name":"Guerra Umpierez Carmen",
    "wof:placetype":"venue"
},
  "geometry": {"coordinates":[-13.8711128235,28.7386760712],"type":"Point"}
}