{
  "type": "Feature",
  "properties": {
    "addr:full":"Partida Serrano, 1 Torres Alicante 03570",
    "addr:housenumber":"1",
    "addr:postcode":"03570",
    "addr:street":"Partida Serrano;Alicante",
    "iso:country":"ES",
    "sg:address":"Partida Serrano, 1",
    "sg:city":"Torres",
    "sg:orig_category":"Empresas De Carpinter\u00cda",
    "sg:phone":"+34 966 85 24 71",
    "sg:postcode":"03570",
    "sg:province":"Alicante",
    "wof:name":"Aluminios Buti S.l.",
    "wof:placetype":"venue"
},
  "geometry": {"coordinates":[-0.2034970969,38.5181427002],"type":"Point"}
}