{
  "type": "Feature",
  "properties": {
    "iso:country":"ES",
    "sg:address":"Avda Filiberto Villalobos, 71",
    "sg:city":"Salamanca",
    "sg:orig_category":"Molduras, Junquillos, Listones Y Molduras Perforadas",
    "sg:phone":"+34 923 23 45 49",
    "sg:postcode":"37007",
    "sg:province":"Salamanca",
    "wof:name":"Sanchez Santiago Miguel",
    "wof:placetype":"venue"
},
  "geometry": {"coordinates":[-5.674405098,40.9701385498],"type":"Point"}
}