{
  "type": "Feature",
  "properties": {
    "iso:country":"ES",
    "sg:address":"Avda Carlos Pelaez, 18",
    "sg:city":"Navia",
    "sg:orig_category":"Material Y Suministros Para Fotocopiadoras, Reprograf\u00cda",
    "sg:phone":"+34 985 47 45 06",
    "sg:postcode":"33710",
    "sg:province":"Asturias",
    "wof:name":"Oroz Morillo Julio",
    "wof:placetype":"venue"
},
  "geometry": {"coordinates":[-6.720843792,43.5418243408],"type":"Point"}
}