{
  "type": "Feature",
  "properties": {
    "addr:full":"Calle de Tembleque, 108 Madrid Madrid 28024",
    "addr:housenumber":"108",
    "addr:postcode":"28024",
    "addr:street":"Calle De Tembleque",
    "iso:country":"ES",
    "sg:address":"Calle de Tembleque, 108",
    "sg:city":"Madrid",
    "sg:orig_category":"Carnicer\u00cdas, Carnicer\u00cdas",
    "sg:phone":"+34 917 11 65 16",
    "sg:postcode":"28024",
    "sg:province":"Madrid",
    "wof:name":"Gamo Ferrero Victor",
    "wof:placetype":"venue"
},
  "geometry": {"coordinates":[-3.761879921,40.3954086304],"type":"Point"}
}