{
  "type": "Feature",
  "properties": {
    "iso:country":"ES",
    "sg:address":"Avda Reyes Catolicos, 4",
    "sg:city":"Burgos",
    "sg:orig_category":"M\u00c9dicos: Estomatolog\u00cda",
    "sg:phone":"+34 947 27 47 56",
    "sg:postcode":"09004",
    "sg:province":"Burgos",
    "wof:name":"Badillo Hernando Eduardo",
    "wof:placetype":"venue"
},
  "geometry": {"coordinates":[-3.6960687637,42.3444824219],"type":"Point"}
}