{
  "type": "Feature",
  "properties": {
    "iso:country":"ES",
    "sg:address":"Mercat Galvany, S/n",
    "sg:city":"Barcelona",
    "sg:orig_category":"Pescader\u00cdas (al Por Menor)",
    "sg:phone":"+34 932 09 33 19",
    "sg:postcode":"08006",
    "sg:province":"Barcelona",
    "wof:name":"Gutierrez Conde Antonio",
    "wof:placetype":"venue"
},
  "geometry": {"coordinates":[2.1487078667,41.3999824524],"type":"Point"}
}