{
  "type": "Feature",
  "properties": {
    "iso:country":"ES",
    "sg:address":"Calle de Soler Bans, S/n",
    "sg:city":"Urrutias",
    "sg:orig_category":"Cajas Para Embalar",
    "sg:phone":"+34 968 13 49 71",
    "sg:postcode":"30368",
    "sg:province":"Murcia",
    "wof:name":"Cajamar",
    "wof:placetype":"venue"
},
  "geometry": {"coordinates":[-0.8292639852,37.6812705994],"type":"Point"}
}