{
  "type": "Feature",
  "properties": {
    "iso:country":"ES",
    "sg:address":"Urb Hawai Iv, S/n",
    "sg:city":"Manga Mar Menor",
    "sg:orig_category":"Servicios De Telecomunicaciones",
    "sg:phone":"+34 968 14 33 36",
    "sg:postcode":"30380",
    "sg:province":"Murcia",
    "wof:name":"Manzanares Monterde Pedro",
    "wof:placetype":"venue"
},
  "geometry": {"coordinates":[-0.7281540036,37.6686553955],"type":"Point"}
}