{
  "type": "Feature",
  "properties": {
    "addr:full":"Calle de Nuestra Se\u00d1ora De Las Candelas, 16 Malaga M\u00e1laga 29004",
    "addr:housenumber":"16",
    "addr:postcode":"29004",
    "addr:street":"Calle De Nuestra Sen\u0303Ora De Las Candelas;Ma\u0301Laga",
    "iso:country":"ES",
    "sg:address":"Calle de Nuestra Se\u00d1ora De Las Candelas, 16",
    "sg:city":"Malaga",
    "sg:orig_category":"Inmobiliaria (agencias)",
    "sg:phone":"+34 952 23 22 12",
    "sg:postcode":"29004",
    "sg:province":"M\u00e1laga",
    "wof:name":"Haspay Gomez Alberto",
    "wof:placetype":"venue"
},
  "geometry": {"coordinates":[-4.4495158195,36.6874313354],"type":"Point"}
}