{
  "type": "Feature",
  "properties": {
    "addr:full":"Pg Mar, De La, 16 S. Antoni Portmany Islas Baleares 07820",
    "addr:housenumber":"16",
    "addr:postcode":"07820",
    "addr:street":"Pg Mar De La",
    "iso:country":"ES",
    "sg:address":"Pg Mar, De La, 16",
    "sg:city":"S. Antoni Portmany",
    "sg:orig_category":"Administraciones Regionales, Departamentales Y Locales",
    "sg:phone":"+34 971 34 80 54",
    "sg:postcode":"07820",
    "sg:province":"Islas Baleares",
    "wof:name":"Ajuntament De Sant Antoni De Portmany",
    "wof:placetype":"venue"
},
  "geometry": {"coordinates":[1.3010474443,38.9786186218],"type":"Point"}
}