{
  "type": "Feature",
  "properties": {
    "iso:country":"ES",
    "sg:address":"Ctra Valverde, Km. 0017,5",
    "sg:city":"Badajoz",
    "sg:orig_category":"Agricultores, Agricultores",
    "sg:phone":"+34 924 14 01 19",
    "sg:postcode":"06010",
    "sg:province":"Badajoz",
    "wof:name":"Llanos De Herrera C.b.",
    "wof:placetype":"venue"
},
  "geometry": {"coordinates":[-6.9718742371,38.862613678],"type":"Point"}
}