{
  "type": "Feature",
  "properties": {
    "iso:country":"ES",
    "sg:address":"Cmno Ca\u00d1o Molinillo, 25",
    "sg:city":"Ogijares",
    "sg:orig_category":"Maquinaria Para Industrias Diversas",
    "sg:phone":"+34 958 59 72 79",
    "sg:postcode":"18151",
    "sg:province":"Granada",
    "wof:name":"Unirenta Maquinaria S.l.",
    "wof:placetype":"venue"
},
  "geometry": {"coordinates":[-3.6139099598,37.1187057495],"type":"Point"}
}