{
  "type": "Feature",
  "properties": {
    "iso:country":"ES",
    "sg:address":"Calle de Archer Marino, 41",
    "sg:city":"Bilbao",
    "sg:orig_category":"Mataderos Y Talleres De Despiezado",
    "sg:phone":"+34 944 90 57 00",
    "sg:postcode":"48013",
    "sg:province":"Vizcaya",
    "wof:name":"Burutxaga Harakintzak S.l.",
    "wof:placetype":"venue"
},
  "geometry": {"coordinates":[-2.9700567722,43.2499694824],"type":"Point"}
}