{
  "type": "Feature",
  "properties": {
    "iso:country":"ES",
    "sg:address":"Carrer de Bailen, 141",
    "sg:city":"Barcelona",
    "sg:orig_category":"M\u00c9dicos: Ginecolog\u00cda Y Obstetricia",
    "sg:phone":"+34 932 07 32 62",
    "sg:postcode":"08037",
    "sg:province":"Barcelona",
    "wof:name":"Viguer Rovira Pedro",
    "wof:placetype":"venue"
},
  "geometry": {"coordinates":[2.1670560837,41.3994178772],"type":"Point"}
}