{
  "type": "Feature",
  "properties": {
    "iso:country":"ES",
    "sg:address":"Solsones (parc Neg Mas Blau I), 2",
    "sg:city":"Prat Llobregat",
    "sg:orig_category":"Promotores Constructores",
    "sg:phone":"+34 934 78 66 66",
    "sg:postcode":"08820",
    "sg:province":"Barcelona",
    "sg:website":"www.drace.es",
    "wof:name":"Construcciones Especiales Y Dragados S.a.",
    "wof:placetype":"venue"
},
  "geometry": {"coordinates":[2.0752000809,41.3187103271],"type":"Point"}
}