{
  "type": "Feature",
  "properties": {
    "addr:full":"Pol Ind La Serna, S/n Esquivias Toledo 45221",
    "addr:postcode":"45221",
    "addr:street":"Serna S / N",
    "iso:country":"ES",
    "sg:address":"Pol Ind La Serna, S/n",
    "sg:city":"Esquivias",
    "sg:orig_category":"Moquetas, Alfombras (al Por Menor)",
    "sg:phone":"+34 925 52 07 40",
    "sg:postcode":"45221",
    "sg:province":"Toledo",
    "wof:name":"Alfombras Mas S.a.l.",
    "wof:placetype":"venue"
},
  "geometry": {"coordinates":[-3.7739868164,40.0942192078],"type":"Point"}
}