{
  "type": "Feature",
  "properties": {
    "iso:country":"ES",
    "sg:address":"Bari, 31",
    "sg:city":"Garrapinillos",
    "sg:orig_category":"Inform\u00c1tica: Consultores",
    "sg:phone":"+34 976 20 79 20",
    "sg:postcode":"50197",
    "sg:province":"Zaragoza",
    "wof:name":"Barrabes Internet S.l.",
    "wof:placetype":"venue"
},
  "geometry": {"coordinates":[-1.0269140005,41.6842803955],"type":"Point"}
}