{
  "type": "Feature",
  "properties": {
    "iso:country":"ES",
    "sg:address":"Calle de Ribera (la), 6",
    "sg:city":"Maracena",
    "sg:orig_category":"Promotores Constructores",
    "sg:phone":"+34 958 41 29 41",
    "sg:postcode":"18200",
    "sg:province":"Granada",
    "wof:name":"Construcciones Maracena S.l.",
    "wof:placetype":"venue"
},
  "geometry": {"coordinates":[-3.6383140087,37.2062301636],"type":"Point"}
}