{
  "type": "Feature",
  "properties": {
    "iso:country":"ES",
    "sg:address":"Calle de 18 De Julio, 14",
    "sg:city":"Astillero",
    "sg:orig_category":"Perfumer\u00cda (al Por Menor)",
    "sg:phone":"+34 942 54 03 43",
    "sg:postcode":"39610",
    "sg:province":"Cantabria",
    "wof:name":"Perez Herrero Francisco",
    "wof:placetype":"venue"
},
  "geometry": {"coordinates":[-3.8314042091,43.3990859985],"type":"Point"}
}