{
  "type": "Feature",
  "properties": {
    "addr:full":"Pl Ocho De Marzo, S/n Rioja Almer\u00eda 04260",
    "addr:postcode":"04260",
    "addr:street":"Pl Ocho De Marzo S / N Rioja Almeri\u0301A",
    "iso:country":"ES",
    "sg:address":"Pl Ocho De Marzo, S/n",
    "sg:city":"Rioja",
    "sg:orig_category":"Centros De Educaci\u00d3n Especial",
    "sg:phone":"+34 950 31 03 25",
    "sg:postcode":"04260",
    "sg:province":"Almer\u00eda",
    "wof:name":"Junta De Andalucia",
    "wof:placetype":"venue"
},
  "geometry": {"coordinates":[-2.4632639885,36.9451141357],"type":"Point"}
}