{
  "type": "Feature",
  "properties": {
    "addr:full":"Pl Forti, 5 Palma Islas Baleares 07011",
    "addr:housenumber":"5",
    "addr:postcode":"07011",
    "addr:street":"Pl Forti",
    "iso:country":"ES",
    "sg:address":"Pl Forti, 5",
    "sg:city":"Palma",
    "sg:orig_category":"Abogados",
    "sg:phone":"+34 971 73 77 78",
    "sg:postcode":"07011",
    "sg:province":"Islas Baleares",
    "wof:name":"Mayol Pujadas Bartolome",
    "wof:placetype":"venue"
},
  "geometry": {"coordinates":[2.6436901093,39.5761756897],"type":"Point"}
}