{
  "type": "Feature",
  "properties": {
    "addr:full":"Avda Puerto, 20 Pueblo Blanco Alicante 03730",
    "addr:housenumber":"20",
    "addr:postcode":"03730",
    "addr:street":"Avda Puerto",
    "iso:country":"ES",
    "sg:address":"Avda Puerto, 20",
    "sg:city":"Pueblo Blanco",
    "sg:orig_category":"Administradores De Bienes Y Delegados De Comunidades De Propietarios",
    "sg:phone":"+34 965 79 46 52",
    "sg:postcode":"03730",
    "sg:province":"Alicante",
    "wof:name":"Catala Perez Guillermo",
    "wof:placetype":"venue"
},
  "geometry": {"coordinates":[0.1570300013,38.7885093689],"type":"Point"}
}