{
  "type": "Feature",
  "properties": {
    "addr:full":"Calle de Arroyo De Las Pilillas, 40 Madrid Madrid 28030",
    "addr:housenumber":"40",
    "addr:postcode":"madrid;28030",
    "addr:street":"Calle De Arroyo De Las Pilillas",
    "iso:country":"ES",
    "sg:address":"Calle de Arroyo De Las Pilillas, 40",
    "sg:city":"Madrid",
    "sg:orig_category":"Reposter\u00cdas",
    "sg:phone":"+34 914 39 05 85",
    "sg:postcode":"28030",
    "sg:province":"Madrid",
    "wof:name":"Aguado Barbero Andres",
    "wof:placetype":"venue"
},
  "geometry": {"coordinates":[-3.6513237953,40.4080734253],"type":"Point"}
}