{
  "type": "Feature",
  "properties": {
    "addr:full":"Calle de Alemania, 4 Valladolid Valladolid 47007",
    "addr:housenumber":"4",
    "addr:postcode":"47007",
    "addr:street":"Calle De Alemania",
    "iso:country":"ES",
    "sg:address":"Calle de Alemania, 4",
    "sg:city":"Valladolid",
    "sg:orig_category":"Cerrajer\u00cda, Ferrallista",
    "sg:phone":"+34 983 22 20 38",
    "sg:postcode":"47007",
    "sg:province":"Valladolid",
    "wof:name":"Vergara Cardenal Enrique Jose",
    "wof:placetype":"venue"
},
  "geometry": {"coordinates":[-4.7361440659,41.6411781311],"type":"Point"}
}