{
  "type": "Feature",
  "properties": {
    "iso:country":"ES",
    "sg:address":"Dalia(urb Planas Del Rei), 12",
    "sg:city":"Pratdip",
    "sg:orig_category":"Panader\u00cdas, Pasteler\u00cdas, Boller\u00cda Industriale (fabricaci\u00d3n, Al Por Mayor)",
    "sg:phone":"+34 977 56 62 23",
    "sg:postcode":"43320",
    "sg:province":"Tarragona",
    "wof:name":"Resposteria Jostam S.l.",
    "wof:placetype":"venue"
},
  "geometry": {"coordinates":[0.8717070222,41.0512161255],"type":"Point"}
}