{
  "type": "Feature",
  "properties": {
    "iso:country":"ES",
    "sg:address":"Av Catalunya, 4",
    "sg:city":"Pinell De Brai",
    "sg:orig_category":"Centros De Educaci\u00d3n Especial",
    "sg:phone":"+34 977 42 62 16",
    "sg:postcode":"43594",
    "sg:province":"Tarragona",
    "wof:name":"Co%egi Public Cesar Martinell",
    "wof:placetype":"venue"
},
  "geometry": {"coordinates":[0.5150790215,41.0183410645],"type":"Point"}
}