{
  "type": "Feature",
  "properties": {
    "addr:full":"Calle de Huerta De Casta\u00d1eda, 18 Madrid Madrid 28011",
    "addr:housenumber":"18",
    "addr:postcode":"madrid;28011",
    "addr:street":"Calle De Huerta De Castan\u0303Eda",
    "iso:country":"ES",
    "sg:address":"Calle de Huerta De Casta\u00d1eda, 18",
    "sg:city":"Madrid",
    "sg:orig_category":"Ropa Para Se\u00d1oras (al Por Menor)",
    "sg:phone":"+34 914 64 11 06",
    "sg:postcode":"28011",
    "sg:province":"Madrid",
    "wof:name":"Mairal Ferrer Maria Teresa",
    "wof:placetype":"venue"
},
  "geometry": {"coordinates":[-3.7419090271,40.4067878723],"type":"Point"}
}