{
  "type": "Feature",
  "properties": {
    "iso:country":"ES",
    "sg:address":"Taburiente, S/n",
    "sg:city":"Sta Cruz Tenerife",
    "sg:orig_category":"Iglesia Cat\u00d3lica",
    "sg:phone":"+34 922 64 31 56",
    "sg:postcode":"38010",
    "sg:province":"Santa Cruz De Tenerife",
    "wof:name":"Parroquia San Pio X",
    "wof:placetype":"venue"
},
  "geometry": {"coordinates":[-16.2835941315,28.4490509033],"type":"Point"}
}