{
  "type": "Feature",
  "properties": {
    "iso:country":"ES",
    "sg:address":"Prolg Del Observatorio, 12",
    "sg:city":"Lalin",
    "sg:orig_category":"Restaurantes",
    "sg:phone":"+34 986 78 14 64",
    "sg:postcode":"36500",
    "sg:province":"Pontevedra",
    "wof:name":"Montoto Y Regueiro S.l.",
    "wof:placetype":"venue"
},
  "geometry": {"coordinates":[-8.1139307022,42.6615486145],"type":"Point"}
}