{
  "type": "Feature",
  "properties": {
    "addr:full":"Calle de Colchados, 1 Lucena C\u00f3rdoba 14900",
    "addr:housenumber":"1",
    "addr:postcode":"14900",
    "addr:street":"Calle De Colchados",
    "iso:country":"ES",
    "sg:address":"Calle de Colchados, 1",
    "sg:city":"Lucena",
    "sg:orig_category":"Fabricaci\u00d3n, Distribuci\u00d3n De Material Para La Climatizaci\u00d3n, Aireaci\u00d3n Y Ventilaci\u00d3n",
    "sg:phone":"+34 957 51 66 96",
    "sg:postcode":"14900",
    "sg:province":"C\u00f3rdoba",
    "wof:name":"Hofrical S.l.",
    "wof:placetype":"venue"
},
  "geometry": {"coordinates":[-4.4828672409,37.4126167297],"type":"Point"}
}