{
  "type": "Feature",
  "properties": {
    "iso:country":"ES",
    "sg:address":"Calle de Virgen Del Carmen, 8",
    "sg:city":"Llodio",
    "sg:orig_category":"Peluqueros: De Se\u00d1oras",
    "sg:phone":"+34 946 72 06 46",
    "sg:postcode":"01400",
    "sg:province":"\u00c1lava",
    "wof:name":"Arenas Ortega Esther",
    "wof:placetype":"venue"
},
  "geometry": {"coordinates":[-2.9593925476,43.1447906494],"type":"Point"}
}