{
  "type": "Feature",
  "properties": {
    "addr:full":"Calle de Luzarra, 3 Bilbao Vizcaya 48014",
    "addr:housenumber":"3",
    "addr:postcode":"48014",
    "addr:street":"Calle De Luzarra",
    "iso:country":"ES",
    "sg:address":"Calle de Luzarra, 3",
    "sg:city":"Bilbao",
    "sg:orig_category":"Ingenier\u00cda, Centros De Estudios (diversos)",
    "sg:phone":"+34 944 04 35 00",
    "sg:postcode":"48014",
    "sg:province":"Vizcaya",
    "wof:name":"Bilbaina De Proyectos, S.l.",
    "wof:placetype":"venue"
},
  "geometry": {"coordinates":[-2.9464349747,43.2721939087],"type":"Point"}
}