{
  "type": "Feature",
  "properties": {
    "addr:full":"Carrer de Sabino Arana, 6 Barcelona Barcelona 08028",
    "addr:housenumber":"6",
    "addr:postcode":"08028",
    "addr:street":"Carrer De Sabino Arana",
    "iso:country":"ES",
    "sg:address":"Carrer de Sabino Arana, 6",
    "sg:city":"Barcelona",
    "sg:orig_category":"Molduras, Junquillos, Listones Y Molduras Perforadas",
    "sg:phone":"+34 933 39 30 09",
    "sg:postcode":"08028",
    "sg:province":"Barcelona",
    "wof:name":"Castro Del Pino Jaime",
    "wof:placetype":"venue"
},
  "geometry": {"coordinates":[2.1262528896,41.3855934143],"type":"Point"}
}