{
  "type": "Feature",
  "properties": {
    "iso:country":"ES",
    "sg:address":"Barreiro, S/n",
    "sg:city":"Esgos",
    "sg:orig_category":"Zapater\u00cdas",
    "sg:phone":"+34 988 29 00 51",
    "sg:postcode":"32720",
    "sg:province":"Ourense",
    "wof:name":"Romasanta Touza Antonio",
    "wof:placetype":"venue"
},
  "geometry": {"coordinates":[-7.6978559494,42.3260421753],"type":"Point"}
}