{
  "type": "Feature",
  "properties": {
    "addr:full":"Calle de Fornillos, S/n Huesca Huesca 22006",
    "addr:housenumber":"s",
    "addr:postcode":"22006",
    "addr:street":"Calle De Fornillos;/ N",
    "iso:country":"ES",
    "sg:address":"Calle de Fornillos, S/n",
    "sg:city":"Huesca",
    "sg:orig_category":"Empresas De Carpinter\u00cda",
    "sg:phone":"+34 974 23 02 23",
    "sg:postcode":"22006",
    "sg:province":"Huesca",
    "wof:name":"Eurosca S.a.",
    "wof:placetype":"venue"
},
  "geometry": {"coordinates":[-0.4003289044,42.1462173462],"type":"Point"}
}