{
  "type": "Feature",
  "properties": {
    "addr:full":"Calle de Monaco, 6 Caceres C\u00e1ceres 10001",
    "addr:housenumber":"6",
    "addr:postcode":"10001",
    "addr:street":"Calle De Monaco;Ca\u0301Ceres",
    "iso:country":"ES",
    "sg:address":"Calle de Monaco, 6",
    "sg:city":"Caceres",
    "sg:classifiers":[
        {
            "category":"Autos & Motor Vehicles",
            "subcategory":"Automobile Sales",
            "type":"Retail Goods"
        }
    ],
    "sg:phone":"+34 927 22 42 00",
    "sg:postcode":"10001",
    "sg:province":"C\u00e1ceres",
    "wof:name":"Gutierrez Maestre Jose Luis",
    "wof:placetype":"venue"
},
  "geometry": {"coordinates":[-6.3816018105,39.4734230042],"type":"Point"}
}