{
  "type": "Feature",
  "properties": {
    "addr:full":"Ctra Saragossa, 1 Cabanes Castell\u00f3n 12180",
    "addr:housenumber":"1",
    "addr:postcode":"12180",
    "addr:street":"Ctra Saragossa",
    "iso:country":"ES",
    "sg:address":"Ctra Saragossa, 1",
    "sg:city":"Cabanes",
    "sg:orig_category":"Cerrajer\u00cda, Ferrallista",
    "sg:phone":"+34 964 33 20 37",
    "sg:postcode":"12180",
    "sg:province":"Castell\u00f3n",
    "wof:name":"Taller Cerrajeria Oliver S.l.",
    "wof:placetype":"venue"
},
  "geometry": {"coordinates":[0.0414079987,40.1589736938],"type":"Point"}
}