{
  "type": "Feature",
  "properties": {
    "addr:full":"Carrer de Madrazo, 145 Barcelona Barcelona 08021",
    "addr:housenumber":"145",
    "addr:postcode":"08021",
    "addr:street":"Carrer De Madrazo",
    "iso:country":"ES",
    "sg:address":"Carrer de Madrazo, 145",
    "sg:city":"Barcelona",
    "sg:orig_category":"Confecci\u00d3n De Trajes Para Se\u00d1oras",
    "sg:phone":"+34 932 00 09 25",
    "sg:postcode":"08021",
    "sg:province":"Barcelona",
    "wof:name":"Mabasegmon S.l",
    "wof:placetype":"venue"
},
  "geometry": {"coordinates":[2.1438210011,41.3961601257],"type":"Point"}
}