{
  "type": "Feature",
  "properties": {
    "iso:country":"ES",
    "sg:address":"Carr Jupiter, 9",
    "sg:city":"Lleida",
    "sg:orig_category":"Molduras, Junquillos, Listones Y Molduras Perforadas",
    "sg:phone":"+34 973 26 41 06",
    "sg:postcode":"25003",
    "sg:province":"Lleida",
    "wof:name":"Consuegra Abolafia Rafael",
    "wof:placetype":"venue"
},
  "geometry": {"coordinates":[0.6114529967,41.6118621826],"type":"Point"}
}