{
  "type": "Feature",
  "properties": {
    "addr:full":"Azkoitiko Industrialdea, 39 Azkoitia Guip\u00f9zcoa 20720",
    "addr:housenumber":"39",
    "addr:postcode":"20720",
    "addr:street":"Industrialdea;Guipu\u0300Zcoa",
    "iso:country":"ES",
    "sg:address":"Azkoitiko Industrialdea, 39",
    "sg:city":"Azkoitia",
    "sg:orig_category":"Cables Y Hilos El\u00c9ctricos (fabricaci\u00d3n, Al Por Mayor)",
    "sg:phone":"+34 943 85 17 29",
    "sg:postcode":"20720",
    "sg:province":"Guip\u00f9zcoa",
    "sg:website":"www.katea-legaia.net",
    "wof:name":"Katea Legaia S.l.l.",
    "wof:placetype":"venue"
},
  "geometry": {"coordinates":[-2.3231461048,43.1719055176],"type":"Point"}
}