{
  "type": "Feature",
  "properties": {
    "iso:country":"ES",
    "sg:address":"Ctra Marinaleda-matarredonda, Km. 0003,0",
    "sg:city":"Marinaleda",
    "sg:orig_category":"Conservas De Legumbres (fabricaci\u00d3n, Al Por Mayor)",
    "sg:phone":"+34 955 91 00 43",
    "sg:postcode":"41569",
    "sg:province":"Sevilla",
    "wof:name":"Marinaleda Sociedad Cooperativa Andaluza",
    "wof:placetype":"venue"
},
  "geometry": {"coordinates":[-4.9597640038,37.3715896606],"type":"Point"}
}