{
  "type": "Feature",
  "properties": {
    "addr:full":"Avda Jose Luis Arrese, 5 Valladolid Valladolid 47014",
    "addr:housenumber":"5",
    "addr:postcode":"47014",
    "addr:street":"Avda Jose Luis Arrese",
    "iso:country":"ES",
    "sg:address":"Avda Jose Luis Arrese, 5",
    "sg:city":"Valladolid",
    "sg:orig_category":"Estancos",
    "sg:phone":"+34 983 37 54 00",
    "sg:postcode":"47014",
    "sg:province":"Valladolid",
    "wof:name":"Soto Sanz Hermenegildo",
    "wof:placetype":"venue"
},
  "geometry": {"coordinates":[-4.7403302193,41.651134491],"type":"Point"}
}