{
  "type": "Feature",
  "properties": {
    "addr:full":"Calle de Cuesta, S/n Santander Cantabria 39002",
    "addr:housenumber":"s / n",
    "addr:postcode":"39002",
    "addr:street":"Calle De Cuesta",
    "iso:country":"ES",
    "sg:address":"Calle de Cuesta, S/n",
    "sg:city":"Santander",
    "sg:orig_category":"Loter\u00cda Y T\u00d3mbola",
    "sg:phone":"+34 942 36 24 64",
    "sg:postcode":"39002",
    "sg:province":"Cantabria",
    "wof:name":"Casanueva Casanueva Ana Rosa",
    "wof:placetype":"venue"
},
  "geometry": {"coordinates":[-3.8078200817,43.463684082],"type":"Point"}
}