{
  "type": "Feature",
  "properties": {
    "iso:country":"ES",
    "sg:address":"Carrer de J. Molins Parera, 32",
    "sg:city":"Palleja",
    "sg:orig_category":"Hormig\u00d3n (m\u00c1quinas E Instalaci\u00d3n)",
    "sg:phone":"+34 936 63 19 62",
    "sg:postcode":"08780",
    "sg:province":"Barcelona",
    "wof:name":"Transportes De Hormigon Del Llobregat S. C. C. L.",
    "wof:placetype":"venue"
},
  "geometry": {"coordinates":[1.9982470274,41.4171676636],"type":"Point"}
}