{
  "type": "Feature",
  "properties": {
    "iso:country":"ES",
    "sg:address":"Ctra Fuencarral (de), Km. 0014,5",
    "sg:city":"Alcobendas",
    "sg:orig_category":"Agentes, Concesionarios Y Sucursales De Veh\u00cdculos",
    "sg:phone":"+34 916 62 25 22",
    "sg:postcode":"28108",
    "sg:province":"Madrid",
    "wof:name":"Alcobendas Norte S.l.",
    "wof:placetype":"venue"
},
  "geometry": {"coordinates":[-3.6477079391,40.5307350159],"type":"Point"}
}