{
  "type": "Feature",
  "properties": {
    "iso:country":"ES",
    "sg:address":"Calle de Espino, 10",
    "sg:city":"Ciudad Real",
    "sg:orig_category":"Peluquer\u00cdas, Peluquer\u00cda Mixta",
    "sg:phone":"+34 926 25 14 11",
    "sg:postcode":"13003",
    "sg:province":"Ciudad Real",
    "wof:name":"Bravo Carretero Jose Antonio",
    "wof:placetype":"venue"
},
  "geometry": {"coordinates":[-3.9290409088,38.9912185669],"type":"Point"}
}