{
  "type": "Feature",
  "properties": {
    "addr:full":"Calle de Madro\u00d1o Del Paular, 3 Pozuelo De Alarcon Madrid 28224",
    "addr:housenumber":"3",
    "addr:postcode":"28224",
    "addr:street":"Calle De Madron\u0303O Del Paular",
    "iso:country":"ES",
    "sg:address":"Calle de Madro\u00d1o Del Paular, 3",
    "sg:city":"Pozuelo De Alarcon",
    "sg:orig_category":"Centros Empresariales",
    "sg:phone":"+34 913 52 77 67",
    "sg:postcode":"28224",
    "sg:province":"Madrid",
    "wof:name":"Numismata International Services",
    "wof:placetype":"venue"
},
  "geometry": {"coordinates":[-3.806194067,40.4550971985],"type":"Point"}
}