{
  "type": "Feature",
  "properties": {
    "addr:full":"Barr La Baluga, 20 Baluga Vizcaya 48190",
    "addr:housenumber":"20",
    "addr:postcode":"48190",
    "addr:street":"La Baluga",
    "iso:country":"ES",
    "sg:address":"Barr La Baluga, 20",
    "sg:city":"Baluga",
    "sg:classifiers":[
        {
            "category":"Taxi",
            "type":"Transportation"
        }
    ],
    "sg:phone":"+34 946 50 40 81",
    "sg:postcode":"48190",
    "sg:province":"Vizcaya",
    "wof:name":"Navea Madrazo Jose Antonio",
    "wof:placetype":"venue"
},
  "geometry": {"coordinates":[-3.1545369625,43.2622108459],"type":"Point"}
}