{
  "type": "Feature",
  "properties": {
    "iso:country":"ES",
    "sg:address":"Calle de Obispo Jesus Dominguez, 31",
    "sg:city":"Pilas",
    "sg:orig_category":"Asilos De Ancianos. Centros Privados",
    "sg:phone":"+34 954 75 03 40",
    "sg:postcode":"41840",
    "sg:province":"Sevilla",
    "wof:name":"Legion De Jesus",
    "wof:placetype":"venue"
},
  "geometry": {"coordinates":[-6.3036699295,37.302318573],"type":"Point"}
}