{
  "type": "Feature",
  "properties": {
    "addr:full":"Avda Portugal (de), 73 Mostoles Madrid 28934",
    "addr:housenumber":"73",
    "addr:postcode":"28934",
    "addr:street":"Avda Portugal De",
    "iso:country":"ES",
    "sg:address":"Avda Portugal (de), 73",
    "sg:city":"Mostoles",
    "sg:orig_category":"Mec\u00c1nico Del Autom\u00d3vil",
    "sg:phone":"+34 916 64 53 06",
    "sg:postcode":"28934",
    "sg:province":"Madrid",
    "wof:name":"Talleres Nemauto S.l.",
    "wof:placetype":"venue"
},
  "geometry": {"coordinates":[-3.8744659424,40.3207359314],"type":"Point"}
}