{
  "type": "Feature",
  "properties": {
    "iso:country":"ES",
    "sg:address":"Avda San Miguel, Km. 0001,0",
    "sg:city":"Iscar",
    "sg:orig_category":"Patatas (al Por Mayor)",
    "sg:phone":"+34 983 62 01 70",
    "sg:postcode":"47420",
    "sg:province":"Valladolid",
    "wof:name":"Iscarma 2005 S.l",
    "wof:placetype":"venue"
},
  "geometry": {"coordinates":[-4.5376338959,41.3601837158],"type":"Point"}
}