{
  "type": "Feature",
  "properties": {
    "iso:country":"ES",
    "sg:address":"Rbla Carme, 4",
    "sg:city":"Vic",
    "sg:orig_category":"Florister\u00cdas",
    "sg:phone":"+34 938 89 06 37",
    "sg:postcode":"08500",
    "sg:province":"Barcelona",
    "wof:name":"Simon Roig Maria Luisa",
    "wof:placetype":"venue"
},
  "geometry": {"coordinates":[2.2538709641,41.9310379028],"type":"Point"}
}