{
  "type": "Feature",
  "properties": {
    "addr:full":"Calle de Enologos, 4 Conil De La Frontera C\u00e1diz 11140",
    "addr:housenumber":"4",
    "addr:postcode":"11140",
    "addr:street":"Calle De Enologos",
    "iso:country":"ES",
    "sg:address":"Calle de Enologos, 4",
    "sg:city":"Conil De La Frontera",
    "sg:orig_category":"Cerrajer\u00cda, Ferrallista",
    "sg:phone":"+34 956 44 25 64",
    "sg:postcode":"11140",
    "sg:province":"C\u00e1diz",
    "wof:name":"Camacho Bermudez Tomas",
    "wof:placetype":"venue"
},
  "geometry": {"coordinates":[-6.089094162,36.2795181274],"type":"Point"}
}