{
  "type": "Feature",
  "properties": {
    "addr:full":"Calle de Gran Via, 56 Madrid Madrid 28013",
    "addr:housenumber":"56",
    "addr:postcode":"madrid;28013",
    "addr:street":"Calle De Gran Via",
    "iso:country":"ES",
    "sg:address":"Calle de Gran Via, 56",
    "sg:city":"Madrid",
    "sg:orig_category":"Lecher\u00cdas",
    "sg:phone":"+34 915 41 97 05",
    "sg:postcode":"28013",
    "sg:province":"Madrid",
    "wof:name":"Zaliki Productos S.l.",
    "wof:placetype":"venue"
},
  "geometry": {"coordinates":[-3.7077553272,40.4214057922],"type":"Point"}
}