{
  "type": "Feature",
  "properties": {
    "addr:full":"Ctra Piedrabuena, S/n Ciudad Real Ciudad Real 13197",
    "addr:housenumber":"s / n",
    "addr:postcode":"13197",
    "addr:street":"Ctra Piedrabuena",
    "iso:country":"ES",
    "sg:address":"Ctra Piedrabuena, S/n",
    "sg:city":"Ciudad Real",
    "sg:orig_category":"Almacenes Para Venta: Muebles Y Varios",
    "sg:phone":"+34 926 21 01 43",
    "sg:postcode":"13197",
    "sg:province":"Ciudad Real",
    "wof:name":"Asociacion Betel",
    "wof:placetype":"venue"
},
  "geometry": {"coordinates":[-3.9445614815,38.9766693115],"type":"Point"}
}