{
  "type": "Feature",
  "properties": {
    "addr:full":"Calle de Garcia De Paredes, 62 Madrid Madrid 28010",
    "addr:housenumber":"62",
    "addr:postcode":"madrid;28010",
    "addr:street":"Calle De Garcia De Paredes",
    "iso:country":"ES",
    "sg:address":"Calle de Garcia De Paredes, 62",
    "sg:city":"Madrid",
    "sg:orig_category":"Ingenier\u00cda, Centros De Estudios (diversos)",
    "sg:phone":"+34 914 48 39 15",
    "sg:postcode":"28010",
    "sg:province":"Madrid",
    "wof:name":"Giron Campos Federico",
    "wof:placetype":"venue"
},
  "geometry": {"coordinates":[-3.6956989765,40.4365272522],"type":"Point"}
}