{
  "type": "Feature",
  "properties": {
    "addr:full":"Calle de San Jose, 35 Cangas Pontevedra 36940",
    "addr:housenumber":"35",
    "addr:postcode":"36940",
    "addr:street":"Calle De San",
    "iso:country":"ES",
    "sg:address":"Calle de San Jose, 35",
    "sg:city":"Cangas",
    "sg:orig_category":"Promotores Constructores",
    "sg:phone":"+34 986 30 41 33",
    "sg:postcode":"36940",
    "sg:province":"Pontevedra",
    "wof:name":"Arquitectura Y Habitat S.l.",
    "wof:placetype":"venue"
},
  "geometry": {"coordinates":[-8.7838582993,42.2655220032],"type":"Point"}
}