{
  "type": "Feature",
  "properties": {
    "iso:country":"ES",
    "sg:address":"Ma\u00f1ueta, 18",
    "sg:city":"Iru\u00f1a",
    "sg:orig_category":"Cuchiller\u00cda (al Por Menor)",
    "sg:phone":"+34 948 22 29 97",
    "sg:postcode":"31001",
    "sg:province":"Navarra",
    "wof:name":"Caneda Morillas Ramon",
    "wof:placetype":"venue"
},
  "geometry": {"coordinates":[-1.6438430548,42.8191871643],"type":"Point"}
}