{
  "type": "Feature",
  "properties": {
    "addr:full":"Calle de San Bartolome, 54 Torredelcampo Ja\u00e9n 23640",
    "addr:housenumber":"54",
    "addr:postcode":"23640",
    "addr:street":"Calle De San Bartolome;Jae\u0301N",
    "iso:country":"ES",
    "sg:address":"Calle de San Bartolome, 54",
    "sg:city":"Torredelcampo",
    "sg:orig_category":"Electricidad: Instaladores",
    "sg:phone":"+34 953 41 07 77",
    "sg:postcode":"23640",
    "sg:province":"Ja\u00e9n",
    "wof:name":"Montajes Electricos Moral S.l.",
    "wof:placetype":"venue"
},
  "geometry": {"coordinates":[-3.8990879059,37.7743453979],"type":"Point"}
}