{
  "type": "Feature",
  "properties": {
    "addr:full":"Calle de Zubieta, 1 Donostia-san Sebastian Guip\u00f9zcoa 20007",
    "addr:housenumber":"1",
    "addr:postcode":"20007",
    "addr:street":"Calle De Zubieta",
    "iso:country":"ES",
    "sg:address":"Calle de Zubieta, 1",
    "sg:city":"Donostia-san Sebastian",
    "sg:orig_category":"Doctores En Medicina",
    "sg:phone":"+34 943 42 88 33",
    "sg:postcode":"20007",
    "sg:province":"Guip\u00f9zcoa",
    "wof:name":"Ubarrechena Uriarte Agustin",
    "wof:placetype":"venue"
},
  "geometry": {"coordinates":[-1.9846949577,43.3176040649],"type":"Point"}
}