{
  "type": "Feature",
  "properties": {
    "iso:country":"ES",
    "sg:address":"Calle de Santa Barbara, 1",
    "sg:city":"Totana",
    "sg:orig_category":"Trajes Y Adornos De Boda (confecci\u00d3n, Al Por Menor)",
    "sg:phone":"+34 968 42 44 51",
    "sg:postcode":"30850",
    "sg:province":"Murcia",
    "wof:name":"Sucesores De El Frances S.l.",
    "wof:placetype":"venue"
},
  "geometry": {"coordinates":[-1.5001752377,37.7711906433],"type":"Point"}
}