{
  "type": "Feature",
  "properties": {
    "iso:country":"ES",
    "sg:address":"Po. De La Mar, S/n",
    "sg:city":"Colonia S. Pere",
    "sg:orig_category":"Pr\u00c1ctica De Vela, Navegaci\u00d3n Y Deportes N\u00c1uticos Y Acu\u00c1ticos",
    "sg:phone":"+34 971 58 91 18",
    "sg:postcode":"07579",
    "sg:province":"Islas Baleares",
    "wof:name":"Club Nautico Colonia San Pedro",
    "wof:placetype":"venue"
},
  "geometry": {"coordinates":[3.3175799847,39.7534561157],"type":"Point"}
}