{
  "type": "Feature",
  "properties": {
    "iso:country":"ES",
    "sg:address":"Calle de Goya, 6",
    "sg:city":"Barakaldo",
    "sg:orig_category":"Muebles Y Accesorios Para Cocinas Y Cuartos De Ba\u00d1o (al Por Menor)",
    "sg:phone":"+34 944 01 49 66",
    "sg:postcode":"48902",
    "sg:province":"Vizcaya",
    "wof:name":"Maria Isabel Orue Barrenechea Y Otro  C.b.",
    "wof:placetype":"venue"
},
  "geometry": {"coordinates":[-2.9954538345,43.2952423096],"type":"Point"}
}