{
  "type": "Feature",
  "properties": {
    "addr:full":"Calle de Heliodoro Rodriguez Lopez, 2 Santa Cruz De Tenerife Santa Cruz De Tenerife 38005",
    "addr:housenumber":"2",
    "addr:postcode":"38005",
    "addr:street":"Calle De Heliodoro Rodriguez Lopez",
    "iso:country":"ES",
    "sg:address":"Calle de Heliodoro Rodriguez Lopez, 2",
    "sg:city":"Santa Cruz De Tenerife",
    "sg:orig_category":"Estancos",
    "sg:phone":"+34 922 22 77 17",
    "sg:postcode":"38005",
    "sg:province":"Santa Cruz De Tenerife",
    "wof:name":"Felipe Riverol Antonio",
    "wof:placetype":"venue"
},
  "geometry": {"coordinates":[-16.2618598938,28.4630393982],"type":"Point"}
}