{
  "type": "Feature",
  "properties": {
    "iso:country":"ES",
    "sg:address":"Moll Espanya, S/n",
    "sg:city":"Barcelona",
    "sg:orig_category":"Clubes Y Asociaciones Deportivas Y De Actividades Invernales Y De Monta\u00d1a",
    "sg:phone":"+34 932 21 78 80",
    "sg:postcode":"08039",
    "sg:province":"Barcelona",
    "wof:name":"Asamblea De Capitanes De Yate",
    "wof:placetype":"venue"
},
  "geometry": {"coordinates":[2.1832952499,41.3779945374],"type":"Point"}
}