{
  "type": "Feature",
  "properties": {
    "addr:full":"Abejeras, 10 Iru\u00f1a Navarra 31007",
    "addr:housenumber":"10",
    "addr:postcode":"31007",
    "addr:street":"Abejeras",
    "iso:country":"ES",
    "sg:address":"Abejeras, 10",
    "sg:city":"Iru\u00f1a",
    "sg:orig_category":"Ense\u00d1anza: Peluquer\u00cda Est\u00c9tica",
    "sg:phone":"+34 948 25 92 85",
    "sg:postcode":"31007",
    "sg:province":"Navarra",
    "wof:name":"Salida S.l.",
    "wof:placetype":"venue"
},
  "geometry": {"coordinates":[-1.6454670429,42.8071174622],"type":"Point"}
}