{
  "type": "Feature",
  "properties": {
    "iso:country":"ES",
    "sg:address":"Carrer de Alsina (de L'), 74",
    "sg:city":"Vilassar De Mar",
    "sg:orig_category":"Asesor\u00cda De Formaci\u00d3n Y Gesti\u00d3n De Personal",
    "sg:phone":"+34 937 50 25 64",
    "sg:postcode":"08340",
    "sg:province":"Barcelona",
    "wof:name":"Porto Barrios Adriano Ramon",
    "wof:placetype":"venue"
},
  "geometry": {"coordinates":[2.3872559071,41.5019874573],"type":"Point"}
}