{
  "type": "Feature",
  "properties": {
    "addr:full":"Zalain Auzoa, 8 Bera Navarra 31780",
    "addr:housenumber":"8",
    "addr:postcode":"31780",
    "addr:street":"Zalain Auzoa",
    "iso:country":"ES",
    "sg:address":"Zalain Auzoa, 8",
    "sg:city":"Bera",
    "sg:orig_category":"Rectificaci\u00d3n, Mecanizado, Fresado",
    "sg:phone":"+34 948 62 54 36",
    "sg:postcode":"31780",
    "sg:province":"Navarra",
    "wof:name":"Ubela S.l.",
    "wof:placetype":"venue"
},
  "geometry": {"coordinates":[-1.6813839674,43.2808914185],"type":"Point"}
}