{
  "type": "Feature",
  "properties": {
    "iso:country":"ES",
    "sg:address":"Calle de Resurreccion M. De Azkue, 3",
    "sg:city":"Arizgoiti",
    "sg:orig_category":"Molduras, Junquillos, Listones Y Molduras Perforadas",
    "sg:phone":"+34 944 49 10 04",
    "sg:postcode":"48970",
    "sg:province":"Vizcaya",
    "wof:name":"Zorroza Marcaida Roman",
    "wof:placetype":"venue"
},
  "geometry": {"coordinates":[-2.8845033646,43.2364387512],"type":"Point"}
}