{
  "type": "Feature",
  "properties": {
    "addr:full":"Ptda Matola, 138 Elche Alicante 03296",
    "addr:housenumber":"138",
    "addr:postcode":"03296",
    "addr:street":"Ptda Matola",
    "iso:country":"ES",
    "sg:address":"Ptda Matola, 138",
    "sg:city":"Elche",
    "sg:orig_category":"Filtros Y Elementos Filtradores",
    "sg:phone":"+34 966 63 21 22",
    "sg:postcode":"03296",
    "sg:province":"Alicante",
    "wof:name":"Soriano Sansano Jose",
    "wof:placetype":"venue"
},
  "geometry": {"coordinates":[-0.7447530031,38.227268219],"type":"Point"}
}