{
  "type": "Feature",
  "properties": {
    "iso:country":"ES",
    "sg:address":"Calle de Doctor Calleja, 9",
    "sg:city":"Torredelcampo",
    "sg:classifiers":[
        {
            "category":"Autos & Motor Vehicles",
            "subcategory":"Automobile Sales",
            "type":"Retail Goods"
        }
    ],
    "sg:phone":"+34 953 41 05 93",
    "sg:postcode":"23640",
    "sg:province":"Ja\u00e9n",
    "wof:name":"Autoescuela Pegalajar S.l.",
    "wof:placetype":"venue"
},
  "geometry": {"coordinates":[-3.8961751461,37.770942688],"type":"Point"}
}