{
  "type": "Feature",
  "properties": {
    "iso:country":"ES",
    "sg:address":"S. Salv. Predanies (urb El Pla), 1",
    "sg:city":"Prats",
    "sg:orig_category":"Alquiler De Veh\u00cdculos: Turismos Y Utilitarios",
    "sg:phone":"+34 972 89 00 73",
    "sg:postcode":"25721",
    "sg:province":"Lleida",
    "wof:name":"Consgarden-fontanals S.l.l.",
    "wof:placetype":"venue"
},
  "geometry": {"coordinates":[1.8370399475,42.3644599915],"type":"Point"}
}