{
  "type": "Feature",
  "properties": {
    "addr:full":"Avda Rioja De (la), 6 Logro\u00f1o La Rioja 26001",
    "addr:housenumber":"6",
    "addr:postcode":"26001",
    "addr:street":"Avda Rioja De La;Rioja",
    "iso:country":"ES",
    "sg:address":"Avda Rioja De (la), 6",
    "sg:city":"Logro\u00f1o",
    "sg:orig_category":"Ense\u00d1anza: Peluquer\u00cda Est\u00c9tica",
    "sg:phone":"+34 941 20 27 29",
    "sg:postcode":"26001",
    "sg:province":"La Rioja",
    "wof:name":"Carisma Imagen S.l.",
    "wof:placetype":"venue"
},
  "geometry": {"coordinates":[-2.4468820095,42.4648208618],"type":"Point"}
}