{
  "type": "Feature",
  "properties": {
    "addr:full":"Avgd Del Cami Nou, 188 Xirivella Valencia 46950",
    "addr:housenumber":"188",
    "addr:postcode":"46950",
    "addr:street":"Nou",
    "iso:country":"ES",
    "sg:address":"Avgd Del Cami Nou, 188",
    "sg:city":"Xirivella",
    "sg:orig_category":"Financiaci\u00d3n Y Cr\u00c9ditos",
    "sg:phone":"+34 963 70 70 59",
    "sg:postcode":"46950",
    "sg:province":"Valencia",
    "wof:name":"Caixa Popular Cooperativa De Credito Valenciana",
    "wof:placetype":"venue"
},
  "geometry": {"coordinates":[-0.4357610047,39.463809967],"type":"Point"}
}