{
  "type": "Feature",
  "properties": {
    "addr:full":"Rua Jesus Sanchez, 2 Cuntis Pontevedra 36670",
    "addr:housenumber":"2",
    "addr:postcode":"36670",
    "addr:street":"Rua Jesus Sanchez",
    "iso:country":"ES",
    "sg:address":"Rua Jesus Sanchez, 2",
    "sg:city":"Cuntis",
    "sg:orig_category":"Alimentaci\u00d3n General (al Por Mayor)",
    "sg:phone":"+34 986 54 81 31",
    "sg:postcode":"36670",
    "sg:province":"Pontevedra",
    "wof:name":"Cortes Castro Clara",
    "wof:placetype":"venue"
},
  "geometry": {"coordinates":[-8.5611791611,42.6424484253],"type":"Point"}
}