{
  "type": "Feature",
  "properties": {
    "iso:country":"ES",
    "sg:address":"Ctra. Abellas, S/n",
    "sg:city":"Gomesende",
    "sg:orig_category":"Cajas De Ahorro",
    "sg:phone":"+34 988 49 52 04",
    "sg:postcode":"32212",
    "sg:province":"Ourense",
    "sg:website":"www.caixagalicia.es",
    "wof:name":"Bt Espa\u00d1a Compa\u00d1ia De Servicios Globales De Telecomunicaciones S.a.u.",
    "wof:placetype":"venue"
},
  "geometry": {"coordinates":[-8.0884866714,42.1744384766],"type":"Point"}
}