{
  "type": "Feature",
  "properties": {
    "addr:full":"Pase Chopera (de La), 124 Alcobendas Madrid 28100",
    "addr:housenumber":"124",
    "addr:postcode":"28100",
    "addr:street":"Alcobendas",
    "iso:country":"ES",
    "sg:address":"Pase Chopera (de La), 124",
    "sg:city":"Alcobendas",
    "sg:orig_category":"Alquiler De V\u00cddeo",
    "sg:phone":"+34 916 62 36 54",
    "sg:postcode":"28100",
    "sg:province":"Madrid",
    "wof:name":"Saleh Elmansuri Ahmed",
    "wof:placetype":"venue"
},
  "geometry": {"coordinates":[-3.6522829533,40.5450248718],"type":"Point"}
}