{
  "type": "Feature",
  "properties": {
    "addr:full":"Calle de Germanias -urb Los Balcones, 35 Balcones Alicante 03186",
    "addr:housenumber":"35",
    "addr:postcode":"03186",
    "addr:street":"Calle De Germanias Urb Los Balcones",
    "iso:country":"ES",
    "sg:address":"Calle de Germanias -urb Los Balcones, 35",
    "sg:city":"Balcones",
    "sg:orig_category":"Aguas (distribuci\u00d3n, Servicios)",
    "sg:phone":"+34 966 79 85 60",
    "sg:postcode":"03186",
    "sg:province":"Alicante",
    "wof:name":"Ramon Ortega Maria Del Mar",
    "wof:placetype":"venue"
},
  "geometry": {"coordinates":[-0.7276489735,37.9641990662],"type":"Point"}
}