{
  "type": "Feature",
  "properties": {
    "addr:full":"Calle de Castello, 13 Madrid Madrid 28001",
    "addr:housenumber":"13",
    "addr:postcode":"madrid;28001",
    "addr:street":"Calle De Castello",
    "iso:country":"ES",
    "sg:address":"Calle de Castello, 13",
    "sg:city":"Madrid",
    "sg:orig_category":"Compraventa De Antig\u00dcedades",
    "sg:phone":"+34 914 31 64 83",
    "sg:postcode":"28001",
    "sg:province":"Madrid",
    "wof:name":"Zazo Morcillo Gonzalo",
    "wof:placetype":"venue"
},
  "geometry": {"coordinates":[-3.684514761,40.4404716492],"type":"Point"}
}