{
  "type": "Feature",
  "properties": {
    "iso:country":"ES",
    "sg:address":"Avda Venezuela (de), 78",
    "sg:city":"G\u00fcimar",
    "sg:orig_category":"Ropa Para Se\u00d1oras Y Caballeros (al Por Menor)",
    "sg:phone":"+34 922 51 03 06",
    "sg:postcode":"38500",
    "sg:province":"Santa Cruz De Tenerife",
    "wof:name":"Diaz Gonzalez Marta Dolores",
    "wof:placetype":"venue"
},
  "geometry": {"coordinates":[-16.4099159241,28.3160915375],"type":"Point"}
}