{
  "type": "Feature",
  "properties": {
    "iso:country":"ES",
    "sg:address":"Plaz Pau Casals (de), 2",
    "sg:city":"Partija-santa Monica",
    "sg:orig_category":"Ropa Para Se\u00d1oras Y Caballeros (al Por Menor)",
    "sg:phone":"+34 914 99 22 45",
    "sg:postcode":"28529",
    "sg:province":"Madrid",
    "wof:name":"Fernandez Fernandez Ismael",
    "wof:placetype":"venue"
},
  "geometry": {"coordinates":[-3.5102670193,40.314289093],"type":"Point"}
}