{
  "type": "Feature",
  "properties": {
    "iso:country":"ES",
    "sg:address":"Calle de Olmo, 4",
    "sg:city":"Almaden Plata",
    "sg:orig_category":"Organizaci\u00d3n De Actos, Seminarios Y Congresos",
    "sg:phone":"+34 954 73 50 58",
    "sg:postcode":"41240",
    "sg:province":"Sevilla",
    "wof:name":"Garcia Amador Carlos",
    "wof:placetype":"venue"
},
  "geometry": {"coordinates":[-6.0802202225,37.8723068237],"type":"Point"}
}