{
  "type": "Feature",
  "properties": {
    "addr:full":"Calle de Hotel Camacho, 1 Tacoronte Santa Cruz De Tenerife 38350",
    "addr:postcode":"38350",
    "addr:street":"Calle De;Camacho",
    "iso:country":"ES",
    "sg:address":"Calle de Hotel Camacho, 1",
    "sg:city":"Tacoronte",
    "sg:orig_category":"Cl\u00cdnicas M\u00c9dicas",
    "sg:phone":"+34 922 56 25 02",
    "sg:postcode":"38350",
    "sg:province":"Santa Cruz De Tenerife",
    "wof:name":"Digar Cuatro S.l.u.",
    "wof:placetype":"venue"
},
  "geometry": {"coordinates":[-16.4140319824,28.4769897461],"type":"Point"}
}