{
  "type": "Feature",
  "properties": {
    "addr:full":"Avda Colon, 14 Badajoz Badajoz 06005",
    "addr:housenumber":"14",
    "addr:postcode":"06005",
    "addr:street":"Avda Colon",
    "iso:country":"ES",
    "sg:address":"Avda Colon, 14",
    "sg:city":"Badajoz",
    "sg:orig_category":"Asistencia Y Consejos",
    "sg:phone":"+34 924 22 53 88",
    "sg:postcode":"06005",
    "sg:province":"Badajoz",
    "wof:name":"Hernandez Gragera Belen",
    "wof:placetype":"venue"
},
  "geometry": {"coordinates":[-6.9795489311,38.8740959167],"type":"Point"}
}