{
  "type": "Feature",
  "properties": {
    "iso:country":"ES",
    "sg:address":"Carrer de Llibertat, 25",
    "sg:city":"Palma",
    "sg:orig_category":"Inmobiliaria (agencias)",
    "sg:phone":"+34 971 45 15 25",
    "sg:postcode":"07013",
    "sg:province":"Islas Baleares",
    "sg:website":"www.expoinques.es",
    "wof:name":"Cartera Palma Noroeste S.l.",
    "wof:placetype":"venue"
},
  "geometry": {"coordinates":[2.6339759827,39.5774726868],"type":"Point"}
}