{
  "type": "Feature",
  "properties": {
    "addr:full":"Calle de Derechos, 29 Valencia Valencia 46001",
    "addr:housenumber":"29",
    "addr:postcode":"46001",
    "addr:street":"Calle De Derechos",
    "iso:country":"ES",
    "sg:address":"Calle de Derechos, 29",
    "sg:city":"Valencia",
    "sg:orig_category":"Restaurantes",
    "sg:phone":"+34 963 91 19 65",
    "sg:postcode":"46001",
    "sg:province":"Valencia",
    "wof:name":"Osteria Del Vicolo S.l.",
    "wof:placetype":"venue"
},
  "geometry": {"coordinates":[-0.3774591982,39.47397995],"type":"Point"}
}