{
  "type": "Feature",
  "properties": {
    "iso:country":"ES",
    "sg:address":"Barreiros, 47",
    "sg:city":"Rante",
    "sg:orig_category":"Pescader\u00cdas (al Por Menor)",
    "sg:phone":"+34 988 36 31 07",
    "sg:postcode":"32910",
    "sg:province":"Ourense",
    "wof:name":"Artic Fisch Company S.l.l",
    "wof:placetype":"venue"
},
  "geometry": {"coordinates":[-7.8716039658,42.2960510254],"type":"Point"}
}