{
  "type": "Feature",
  "properties": {
    "addr:full":"Avda Angel Guimera, 11 Santa Cruz De Tenerife Santa Cruz De Tenerife 38003",
    "addr:housenumber":"11",
    "addr:postcode":"38003",
    "addr:street":"Avda Angel Guimera",
    "iso:country":"ES",
    "sg:address":"Avda Angel Guimera, 11",
    "sg:city":"Santa Cruz De Tenerife",
    "sg:orig_category":"\u00d3ptica: Instrumentos (fabricaci\u00d3n)",
    "sg:phone":"+34 922 24 16 16",
    "sg:postcode":"38003",
    "sg:province":"Santa Cruz De Tenerife",
    "wof:name":"Garcia De La Cruz Luis",
    "wof:placetype":"venue"
},
  "geometry": {"coordinates":[-16.3326644897,28.4846744537],"type":"Point"}
}