{
  "type": "Feature",
  "properties": {
    "iso:country":"ES",
    "sg:address":"Festival Park, S/n",
    "sg:city":"Es Figueral",
    "sg:orig_category":"Asociaciones Y Clubs Deportivos",
    "sg:phone":"+34 971 60 54 63",
    "sg:postcode":"07141",
    "sg:province":"Islas Baleares",
    "wof:name":"Reebok Spain S.a.",
    "wof:placetype":"venue"
},
  "geometry": {"coordinates":[2.7445349693,39.6195487976],"type":"Point"}
}