{
  "type": "Feature",
  "properties": {
    "iso:country":"ES",
    "sg:address":"Av Magaluf, 14",
    "sg:city":"Magaluf",
    "sg:orig_category":"Zapatos (al Por Menor)",
    "sg:phone":"+34 971 13 08 78",
    "sg:postcode":"07181",
    "sg:province":"Islas Baleares",
    "wof:name":"Garcia Gorgoles Manuel",
    "wof:placetype":"venue"
},
  "geometry": {"coordinates":[2.5335900784,39.5068473816],"type":"Point"}
}