{
  "type": "Feature",
  "properties": {
    "addr:full":"Calle de Mu\u00d1oz Torrero, 5 Cabeza Buey Badajoz 06600",
    "addr:housenumber":"5",
    "addr:postcode":"06600",
    "addr:street":"Calle De Mun\u0303Oz Torrero",
    "iso:country":"ES",
    "sg:address":"Calle de Mu\u00d1oz Torrero, 5",
    "sg:city":"Cabeza Buey",
    "sg:orig_category":"Contenedores (mercanc\u00cdas)",
    "sg:phone":"+34 924 60 03 82",
    "sg:postcode":"06600",
    "sg:province":"Badajoz",
    "wof:name":"Cortes Murillo Miguel",
    "wof:placetype":"venue"
},
  "geometry": {"coordinates":[-5.2173609734,38.721824646],"type":"Point"}
}