{
  "type": "Feature",
  "properties": {
    "iso:country":"ES",
    "sg:address":"Av Cavall Bernat (del), S/n",
    "sg:city":"Platja D'aro",
    "sg:orig_category":"Restaurantes",
    "sg:phone":"+34 972 81 72 00",
    "sg:postcode":"17250",
    "sg:province":"Girona",
    "wof:name":"Acierta Apartamentos Group S.l",
    "wof:placetype":"venue"
},
  "geometry": {"coordinates":[3.067514658,41.8187065125],"type":"Point"}
}