{
  "type": "Feature",
  "properties": {
    "iso:country":"ES",
    "sg:address":"Calle de Montenegro, 3",
    "sg:city":"Teruel",
    "sg:orig_category":"Arquitectos",
    "sg:phone":"+34 978 61 19 59",
    "sg:postcode":"44002",
    "sg:province":"Teruel",
    "wof:name":"Chapa Villalba Juan Antonio",
    "wof:placetype":"venue"
},
  "geometry": {"coordinates":[-1.0983550549,40.329498291],"type":"Point"}
}