{
  "type": "Feature",
  "properties": {
    "iso:country":"ES",
    "sg:address":"Rua Castelao, 3",
    "sg:city":"Grove",
    "sg:orig_category":"Art\u00cdculos De Decoraci\u00d3n",
    "sg:phone":"+34 986 73 25 97",
    "sg:postcode":"36980",
    "sg:province":"Pontevedra",
    "wof:name":"Bambu C.b.",
    "wof:placetype":"venue"
},
  "geometry": {"coordinates":[-8.8586978912,42.4906616211],"type":"Point"}
}