{
  "type": "Feature",
  "properties": {
    "iso:country":"ES",
    "sg:address":"Calle de Cantotejio, 15",
    "sg:city":"Guijar",
    "sg:orig_category":"Empresarios",
    "sg:phone":"+34 921 50 03 28",
    "sg:postcode":"40185",
    "sg:province":"Segovia",
    "wof:name":"Pe\u00f1a De Andres Manuel De La",
    "wof:placetype":"venue"
},
  "geometry": {"coordinates":[-3.9126772881,41.1455230713],"type":"Point"}
}