{
  "type": "Feature",
  "properties": {
    "iso:country":"ES",
    "sg:address":"Calle de Xativa, 15",
    "sg:city":"Valencia",
    "sg:orig_category":"Sociedades, Compa\u00d1\u00cdas Aseguradoras",
    "sg:phone":"+34 963 94 11 12",
    "sg:postcode":"46002",
    "sg:province":"Valencia",
    "sg:website":"www.qualitybrokers.net",
    "wof:name":"Q & S Quality Brokers Correduria Seguros S.l",
    "wof:placetype":"venue"
},
  "geometry": {"coordinates":[-0.3763790131,39.4674873352],"type":"Point"}
}