{
  "type": "Feature",
  "properties": {
    "addr:full":"R. Pillado Mourelle, 5 Algete Madrid 28110",
    "addr:housenumber":"5",
    "addr:postcode":"28110",
    "addr:street":"Pillado Mourelle",
    "iso:country":"ES",
    "sg:address":"R. Pillado Mourelle, 5",
    "sg:city":"Algete",
    "sg:orig_category":"Maquinaria Para Industrias Diversas",
    "sg:phone":"+34 916 28 17 26",
    "sg:postcode":"28110",
    "sg:province":"Madrid",
    "wof:name":"Jiconsa S.l.",
    "wof:placetype":"venue"
},
  "geometry": {"coordinates":[-3.4999940395,40.5979003906],"type":"Point"}
}