{
  "type": "Feature",
  "properties": {
    "iso:country":"ES",
    "sg:address":"Calle de Saavedra Fajardo, 13",
    "sg:city":"Santa Eulalia",
    "sg:orig_category":"Ense\u00d1anza, Formaci\u00d3n Profesional: Aprendizaje",
    "sg:phone":"+34 968 21 47 59",
    "sg:postcode":"30001",
    "sg:province":"Murcia",
    "wof:name":"Aiqei Software S.l.",
    "wof:placetype":"venue"
},
  "geometry": {"coordinates":[-1.1272541285,37.9866218567],"type":"Point"}
}