{
  "type": "Feature",
  "properties": {
    "addr:full":"Rua Rosalia De Castro, 32 Lalin Pontevedra 36500",
    "addr:housenumber":"32",
    "addr:postcode":"36500",
    "addr:street":"Rua Rosalia De Castro",
    "iso:country":"ES",
    "sg:address":"Rua Rosalia De Castro, 32",
    "sg:city":"Lalin",
    "sg:orig_category":"Art\u00cdculos De Decoraci\u00d3n",
    "sg:phone":"+34 986 78 03 11",
    "sg:postcode":"36500",
    "sg:province":"Pontevedra",
    "wof:name":"Basalo Ya\u00f1ez Sebastian",
    "wof:placetype":"venue"
},
  "geometry": {"coordinates":[-8.1126394272,42.6608200073],"type":"Point"}
}