{
  "type": "Feature",
  "properties": {
    "addr:full":"Carr Camelia, 10 Palafrugell Girona 17200",
    "addr:housenumber":"10",
    "addr:postcode":"17200",
    "addr:street":"Carr Camelia",
    "iso:country":"ES",
    "sg:address":"Carr Camelia, 10",
    "sg:city":"Palafrugell",
    "sg:orig_category":"Empresas De Pintura Y Revestimientos",
    "sg:phone":"+34 972 30 13 53",
    "sg:postcode":"17200",
    "sg:province":"Girona",
    "wof:name":"Busquets Comas Juan",
    "wof:placetype":"venue"
},
  "geometry": {"coordinates":[3.169011116,41.9182472229],"type":"Point"}
}