{
  "type": "Feature",
  "properties": {
    "iso:country":"ES",
    "sg:address":"Carrer de Sant Benet, 9",
    "sg:city":"Mataro",
    "sg:orig_category":"Fabricaci\u00d3n De Muebles",
    "sg:phone":"+34 937 98 64 68",
    "sg:postcode":"08302",
    "sg:province":"Barcelona",
    "wof:name":"Josep Maria Costa S.l.",
    "wof:placetype":"venue"
},
  "geometry": {"coordinates":[2.4409940243,41.538394928],"type":"Point"}
}