{
  "type": "Feature",
  "properties": {
    "iso:country":"ES",
    "sg:address":"Calle de Virgen Del Carmen, 56",
    "sg:city":"Donostia-san Sebastian",
    "sg:orig_category":"Muebles, Minoristas",
    "sg:phone":"+34 943 32 22 28",
    "sg:postcode":"20012",
    "sg:province":"Guip\u00f9zcoa",
    "wof:name":"Easonense Mobiliario S.l.",
    "wof:placetype":"venue"
},
  "geometry": {"coordinates":[-1.966966033,43.3185577393],"type":"Point"}
}