{
  "type": "Feature",
  "properties": {
    "addr:full":"Avda Valladolid, 2 Valencia Valencia 46020",
    "addr:housenumber":"2",
    "addr:postcode":"46020",
    "addr:street":"Avda Valladolid",
    "iso:country":"ES",
    "sg:address":"Avda Valladolid, 2",
    "sg:city":"Valencia",
    "sg:orig_category":"Cajas De Ahorro",
    "sg:phone":"+34 963 39 03 17",
    "sg:postcode":"46020",
    "sg:province":"Valencia",
    "sg:website":"www.bbk.es",
    "wof:name":"Bilbao Bizkaia Kutxa",
    "wof:placetype":"venue"
},
  "geometry": {"coordinates":[-0.3613330126,39.4891281128],"type":"Point"}
}