{
  "type": "Feature",
  "properties": {
    "addr:full":"Carrer de Banys Nous, 4 Barcelona Barcelona 08002",
    "addr:housenumber":"4",
    "addr:postcode":"08002",
    "addr:street":"Carrer De Banys Nous",
    "iso:country":"ES",
    "sg:address":"Carrer de Banys Nous, 4",
    "sg:city":"Barcelona",
    "sg:orig_category":"Caf\u00c9s, Bares, Cervecer\u00cdas",
    "sg:phone":"+34 933 02 69 75",
    "sg:postcode":"08002",
    "sg:province":"Barcelona",
    "wof:name":"La Vaca Lechera S.l.",
    "wof:placetype":"venue"
},
  "geometry": {"coordinates":[2.174751997,41.3826026917],"type":"Point"}
}