{
  "type": "Feature",
  "properties": {
    "addr:full":"Carrer de Oriola, S/n Amposta Tarragona 43870",
    "addr:housenumber":"s / n",
    "addr:postcode":"43870",
    "addr:street":"Carrer De Oriola",
    "iso:country":"ES",
    "sg:address":"Carrer de Oriola, S/n",
    "sg:city":"Amposta",
    "sg:orig_category":"Fabricaci\u00d3n De Muebles",
    "sg:phone":"+34 977 70 92 00",
    "sg:postcode":"43870",
    "sg:province":"Tarragona",
    "wof:name":"Naturantaix",
    "wof:placetype":"venue"
},
  "geometry": {"coordinates":[0.5826650262,40.6891860962],"type":"Point"}
}