{
  "type": "Feature",
  "properties": {
    "iso:country":"ES",
    "sg:address":"Pasaje De Due\u00f1as, S/n",
    "sg:city":"Guadix",
    "sg:orig_category":"Promotores Constructores",
    "sg:phone":"+34 958 66 31 75",
    "sg:postcode":"18500",
    "sg:province":"Granada",
    "wof:name":"Yeste Rodriguez Antonio",
    "wof:placetype":"venue"
},
  "geometry": {"coordinates":[-3.1277263165,37.3163986206],"type":"Point"}
}