{
  "type": "Feature",
  "properties": {
    "addr:full":"Carr Alacant, 11 Pu\u00e7ol Valencia 46530",
    "addr:housenumber":"11",
    "addr:postcode":"46530",
    "addr:street":"Carr Alacant",
    "iso:country":"ES",
    "sg:address":"Carr Alacant, 11",
    "sg:city":"Pu\u00e7ol",
    "sg:orig_category":"Farmacias",
    "sg:phone":"+34 961 42 05 02",
    "sg:postcode":"46530",
    "sg:province":"Valencia",
    "wof:name":"Burgos Orti Amparo",
    "wof:placetype":"venue"
},
  "geometry": {"coordinates":[-0.3072350025,39.616443634],"type":"Point"}
}