{
  "type": "Feature",
  "properties": {
    "addr:full":"Via Emilio Ortu\u00d1o, 12 Benidorm Alicante 03500",
    "addr:housenumber":"12",
    "addr:postcode":"03500",
    "addr:street":"Via Emilio Ortun\u0303O",
    "iso:country":"ES",
    "sg:address":"Via Emilio Ortu\u00d1o, 12",
    "sg:city":"Benidorm",
    "sg:orig_category":"Art\u00cdculos De Regalo (al Por Menor)",
    "sg:phone":"+34 965 86 68 61",
    "sg:postcode":"03500",
    "sg:province":"Alicante",
    "wof:name":"Aran Balsells Basilio",
    "wof:placetype":"venue"
},
  "geometry": {"coordinates":[-0.1279238015,38.5378227234],"type":"Point"}
}