{
  "type": "Feature",
  "properties": {
    "iso:country":"ES",
    "sg:address":"Calle de Aurora, 41",
    "sg:city":"Llerena",
    "sg:orig_category":"Formaci\u00d3n Continuada (variada)",
    "sg:phone":"+34 924 87 25 79",
    "sg:postcode":"06900",
    "sg:province":"Badajoz",
    "wof:name":"Centro De Ense\u00f1anza Logos",
    "wof:placetype":"venue"
},
  "geometry": {"coordinates":[-6.0141539574,38.2385406494],"type":"Point"}
}