{
  "type": "Feature",
  "properties": {
    "iso:country":"ES",
    "sg:address":"Carrer de Unio, 15",
    "sg:city":"Palma",
    "sg:orig_category":"Panader\u00cdas, Panader\u00cdas",
    "sg:phone":"+34 971 71 16 34",
    "sg:postcode":"07001",
    "sg:province":"Islas Baleares",
    "wof:name":"Llull Mayol Jaime Andres",
    "wof:placetype":"venue"
},
  "geometry": {"coordinates":[2.6485319138,39.5716590881],"type":"Point"}
}