{
  "type": "Feature",
  "properties": {
    "iso:country":"ES",
    "sg:address":"Avda Dos De Mayo (del), 24",
    "sg:city":"Mostoles",
    "sg:orig_category":"Cuchiller\u00cda (al Por Menor)",
    "sg:phone":"+34 916 13 58 66",
    "sg:postcode":"28934",
    "sg:province":"Madrid",
    "wof:name":"Garcia Garcia Jose Antonio",
    "wof:placetype":"venue"
},
  "geometry": {"coordinates":[-3.8670079708,40.3209037781],"type":"Point"}
}