{
  "type": "Feature",
  "properties": {
    "iso:country":"ES",
    "sg:address":"Avda Atance (el), 20",
    "sg:city":"Guadalajara",
    "sg:orig_category":"Supermercados Y Hipermercados",
    "sg:phone":"+34 949 22 46 19",
    "sg:postcode":"19005",
    "sg:province":"Guadalajara",
    "sg:website":"www.mercadona.es",
    "wof:name":"Mercadona S.a.",
    "wof:placetype":"venue"
},
  "geometry": {"coordinates":[-3.1530740261,40.641254425],"type":"Point"}
}