{
  "type": "Feature",
  "properties": {
    "iso:country":"ES",
    "sg:address":"Ctra Sardina, Km. 0005,0",
    "sg:city":"Puerto De Sardina",
    "sg:orig_category":"Alimentaci\u00d3n General (al Por Menor)",
    "sg:phone":"+34 928 88 00 28",
    "sg:postcode":"35469",
    "sg:province":"Las Palmas",
    "wof:name":"Gonzalez Gonzalez Juan Modesto",
    "wof:placetype":"venue"
},
  "geometry": {"coordinates":[-15.6945705414,28.1516628265],"type":"Point"}
}