{
  "type": "Feature",
  "properties": {
    "iso:country":"ES",
    "sg:address":"Pase Imperial, 6",
    "sg:city":"Villamayor Santiago",
    "sg:orig_category":"Contenedores (mercanc\u00cdas)",
    "sg:phone":"+34 969 13 91 21",
    "sg:postcode":"16415",
    "sg:province":"Cuenca",
    "wof:name":"Ballestero Ca\u00f1ada Procopia",
    "wof:placetype":"venue"
},
  "geometry": {"coordinates":[-2.9234220982,39.7301254272],"type":"Point"}
}