{
  "type": "Feature",
  "properties": {
    "addr:full":"Rond Guinardo, 2 Barcelona Barcelona 08024",
    "addr:housenumber":"2",
    "addr:postcode":"08024",
    "addr:street":"Guinardo",
    "iso:country":"ES",
    "sg:address":"Rond Guinardo, 2",
    "sg:city":"Barcelona",
    "sg:orig_category":"Inmobiliaria (agencias)",
    "sg:phone":"+34 932 10 49 78",
    "sg:postcode":"08024",
    "sg:province":"Barcelona",
    "wof:name":"Inmozel S.l.",
    "wof:placetype":"venue"
},
  "geometry": {"coordinates":[2.1601409912,41.4122161865],"type":"Point"}
}