{
  "type": "Feature",
  "properties": {
    "iso:country":"ES",
    "sg:address":"Pol Ind El Cordovi, 9",
    "sg:city":"Benalua Guadix",
    "sg:orig_category":"Madera Para Chapado",
    "sg:phone":"+34 958 67 62 08",
    "sg:postcode":"18510",
    "sg:province":"Granada",
    "wof:name":"Maderas Benalua S.l.l",
    "wof:placetype":"venue"
},
  "geometry": {"coordinates":[-3.1669239998,37.3522415161],"type":"Point"}
}