{
  "type": "Feature",
  "properties": {
    "addr:full":"Av Graells, 7 S. Cugat Valles Barcelona 08173",
    "addr:housenumber":"7",
    "addr:postcode":"08173",
    "addr:street":"Av Graells;Barcelona",
    "iso:country":"ES",
    "sg:address":"Av Graells, 7",
    "sg:city":"S. Cugat Valles",
    "sg:orig_category":"Laboratorios Y Cl\u00cdnicas Veterinarias",
    "sg:phone":"+34 936 74 85 61",
    "sg:postcode":"08173",
    "sg:province":"Barcelona",
    "wof:name":"Toralles Chorrero Eudaldo",
    "wof:placetype":"venue"
},
  "geometry": {"coordinates":[2.1700499058,41.3857192993],"type":"Point"}
}