{
  "type": "Feature",
  "properties": {
    "addr:full":"Avda Terra Cha, 32 Castro Lugo 27260",
    "addr:housenumber":"32",
    "addr:postcode":"27260",
    "addr:street":"Avda Terra Cha",
    "iso:country":"ES",
    "sg:address":"Avda Terra Cha, 32",
    "sg:city":"Castro",
    "sg:orig_category":"T\u00c9cnicos Veterinarios",
    "sg:phone":"+34 982 31 03 03",
    "sg:postcode":"27260",
    "sg:province":"Lugo",
    "wof:name":"Comercial Lucense Ganadera S.a.",
    "wof:placetype":"venue"
},
  "geometry": {"coordinates":[-7.4930620193,43.1417922974],"type":"Point"}
}