{
  "type": "Feature",
  "properties": {
    "iso:country":"ES",
    "sg:address":"Pase Salamanca, 73",
    "sg:city":"Le\u00f3n",
    "sg:orig_category":"Agencias Y Agentes Comerciales, Representantes",
    "sg:phone":"+34 987 27 29 20",
    "sg:postcode":"24010",
    "sg:province":"Le\u00f3n",
    "wof:name":"Gonzalez Ferreras Jose Luis",
    "wof:placetype":"venue"
},
  "geometry": {"coordinates":[-5.5886220932,42.6057167053],"type":"Point"}
}