{
  "type": "Feature",
  "properties": {
    "iso:country":"ES",
    "sg:address":"Avda Republica Argentina, 30",
    "sg:city":"Le\u00f3n",
    "sg:orig_category":"Cl\u00cdnicas Dentales",
    "sg:phone":"+34 987 26 10 20",
    "sg:postcode":"24004",
    "sg:province":"Le\u00f3n",
    "wof:name":"Rodriguez Fernandez Jose Manuel",
    "wof:placetype":"venue"
},
  "geometry": {"coordinates":[-5.5758328438,42.5955505371],"type":"Point"}
}