{
  "type": "Feature",
  "properties": {
    "iso:country":"ES",
    "sg:address":"Avda Montejicar, 3",
    "sg:city":"Domingo Perez",
    "sg:orig_category":"Material Y Herramientas Agr\u00cdcolas",
    "sg:phone":"+34 958 39 06 13",
    "sg:postcode":"18567",
    "sg:province":"Granada",
    "wof:name":"Talleres Contreras Y Quijada C.b.",
    "wof:placetype":"venue"
},
  "geometry": {"coordinates":[-3.5093710423,37.4954414368],"type":"Point"}
}