{
  "type": "Feature",
  "properties": {
    "addr:full":"Psaj Francisco Gonzalez Panchon, 3 Cordoba C\u00f3rdoba 14004",
    "addr:housenumber":"3",
    "addr:postcode":"14004",
    "addr:street":"Francisco Gonzalez Panchon;Co\u0301Rdoba",
    "iso:country":"ES",
    "sg:address":"Psaj Francisco Gonzalez Panchon, 3",
    "sg:city":"Cordoba",
    "sg:orig_category":"Edici\u00d3n De Mapas, Gu\u00cdas Y Planos",
    "sg:phone":"+34 957 23 35 91",
    "sg:postcode":"14004",
    "sg:province":"C\u00f3rdoba",
    "wof:name":"Protoba S.l.",
    "wof:placetype":"venue"
},
  "geometry": {"coordinates":[-4.7784028053,37.8779411316],"type":"Point"}
}