{
  "type": "Feature",
  "properties": {
    "iso:country":"ES",
    "sg:address":"La Cruz, S/n",
    "sg:city":"Centenera Andaluz",
    "sg:orig_category":"Fabricaci\u00d3n De Material Y Sistemas De Se\u00d1alizaci\u00d3n De Carreteras, Urbanos Y De Obras",
    "sg:phone":"+34 975 18 11 50",
    "sg:postcode":"42211",
    "sg:province":"Soria",
    "wof:name":"P.g.b. Se\u00f1alizacion Urbana S.l.",
    "wof:placetype":"venue"
},
  "geometry": {"coordinates":[-2.7177639008,41.5069618225],"type":"Point"}
}