{
  "type": "Feature",
  "properties": {
    "addr:full":"Rua Combro, 113 Combro Pontevedra 36331",
    "addr:housenumber":"113",
    "addr:postcode":"36331",
    "addr:street":"Rua Combro",
    "iso:country":"ES",
    "sg:address":"Rua Combro, 113",
    "sg:city":"Combro",
    "sg:orig_category":"Prendas Y Chalecos De Punto (al Por Menor)",
    "sg:phone":"+34 986 46 06 62",
    "sg:postcode":"36331",
    "sg:province":"Pontevedra",
    "wof:name":"Dismart Martins S.l.",
    "wof:placetype":"venue"
},
  "geometry": {"coordinates":[-8.7708091736,42.1942863464],"type":"Point"}
}