{
  "type": "Feature",
  "properties": {
    "iso:country":"ES",
    "sg:address":"Rua Aduana, 23",
    "sg:city":"Carril",
    "sg:orig_category":"Administradores De Bienes Y Delegados De Comunidades De Propietarios",
    "sg:phone":"+34 986 50 23 39",
    "sg:postcode":"36610",
    "sg:province":"Pontevedra",
    "wof:name":"Logistica Y Tecnologia Del Mar",
    "wof:placetype":"venue"
},
  "geometry": {"coordinates":[-8.7765932083,42.6144371033],"type":"Point"}
}