{
  "type": "Feature",
  "properties": {
    "addr:full":"Ctra Orihuela, Km. 0002,0 Pilar Horadada Alicante 03190",
    "addr:postcode":"03190",
    "addr:street":"Ctra Orihuela Km. 0002,0",
    "iso:country":"ES",
    "sg:address":"Ctra Orihuela, Km. 0002,0",
    "sg:city":"Pilar Horadada",
    "sg:orig_category":"Empresas De Carpinter\u00cda De Madera",
    "sg:phone":"+34 965 35 11 40",
    "sg:postcode":"03190",
    "sg:province":"Alicante",
    "wof:name":"Sanchez Garcia Antonio",
    "wof:placetype":"venue"
},
  "geometry": {"coordinates":[-0.7898390293,37.8640213013],"type":"Point"}
}