{
  "type": "Feature",
  "properties": {
    "iso:country":"ES",
    "sg:address":"Calle de Q, S/n",
    "sg:city":"Mutiloabeiti",
    "sg:orig_category":"Serigraf\u00cda",
    "sg:phone":"+34 948 24 38 93",
    "sg:postcode":"31192",
    "sg:province":"Navarra",
    "wof:name":"Legarra Muruzabal Miguel Y Legasa Barberena Francisco S.cv.",
    "wof:placetype":"venue"
},
  "geometry": {"coordinates":[-1.6279239655,42.7859764099],"type":"Point"}
}