{
  "type": "Feature",
  "properties": {
    "addr:full":"Calle de Purificacion Bezos, 21 Arroyo De La Encomienda Valladolid 47195",
    "addr:housenumber":"21",
    "addr:postcode":"47195",
    "addr:street":"Calle De Purificacion Bezos",
    "iso:country":"ES",
    "sg:address":"Calle de Purificacion Bezos, 21",
    "sg:city":"Arroyo De La Encomienda",
    "sg:orig_category":"Hormigonados",
    "sg:phone":"+34 983 40 84 54",
    "sg:postcode":"47195",
    "sg:province":"Valladolid",
    "wof:name":"Imprexs Spa S.l.",
    "wof:placetype":"venue"
},
  "geometry": {"coordinates":[-4.7685709,41.6250343323],"type":"Point"}
}