{
  "type": "Feature",
  "properties": {
    "iso:country":"ES",
    "sg:address":"Calle de Joaquin Hoyos, 12",
    "sg:city":"Torrelavega",
    "sg:orig_category":"Laboratorios Y Trabajos De Fotograf\u00cda, V\u00cddeo Y Cine",
    "sg:phone":"+34 942 80 60 00",
    "sg:postcode":"39300",
    "sg:province":"Cantabria",
    "wof:name":"Fernandez Cabanas Pedro Antonio",
    "wof:placetype":"venue"
},
  "geometry": {"coordinates":[-4.0463981628,43.3496322632],"type":"Point"}
}