{
  "type": "Feature",
  "properties": {
    "addr:full":"Gonzalez Tablas, 4 Iru\u00f1a Navarra 31003",
    "addr:housenumber":"4",
    "addr:postcode":"31003",
    "addr:street":"Tablas",
    "iso:country":"ES",
    "sg:address":"Gonzalez Tablas, 4",
    "sg:city":"Iru\u00f1a",
    "sg:orig_category":"Arquitectos",
    "sg:phone":"+34 948 23 01 86",
    "sg:postcode":"31003",
    "sg:province":"Navarra",
    "wof:name":"Gesta Cilveti Miguel Enrique",
    "wof:placetype":"venue"
},
  "geometry": {"coordinates":[-1.6371680498,42.8094367981],"type":"Point"}
}