{
  "type": "Feature",
  "properties": {
    "iso:country":"ES",
    "sg:address":"Calle de Torres Miranda, 15",
    "sg:city":"Madrid",
    "sg:orig_category":"Loter\u00cda Y T\u00d3mbola",
    "sg:phone":"+34 914 73 19 44",
    "sg:postcode":"28045",
    "sg:province":"Madrid",
    "wof:name":"Mesonero Olmo Hortensia",
    "wof:placetype":"venue"
},
  "geometry": {"coordinates":[-3.6998639107,40.3980140686],"type":"Point"}
}