{
  "type": "Feature",
  "properties": {
    "addr:full":"Calle de Asistente Arjona, 6 Osuna Sevilla 41640",
    "addr:housenumber":"6",
    "addr:postcode":"41640",
    "addr:street":"Calle De Asistente Arjona",
    "iso:country":"ES",
    "sg:address":"Calle de Asistente Arjona, 6",
    "sg:city":"Osuna",
    "sg:orig_category":"Centros Comerciales Y Grandes Tiendas",
    "sg:phone":"+34 954 81 56 49",
    "sg:postcode":"41640",
    "sg:province":"Sevilla",
    "wof:name":"Asistente Arjona 6 Y 8 S.l.",
    "wof:placetype":"venue"
},
  "geometry": {"coordinates":[-5.1026206017,37.2367248535],"type":"Point"}
}