{
  "type": "Feature",
  "properties": {
    "addr:full":"Calle de Amor De Dios, 31 Sevilla Sevilla 41002",
    "addr:housenumber":"31",
    "addr:postcode":"41002",
    "addr:street":"Calle De Amor De Dios",
    "iso:country":"ES",
    "sg:address":"Calle de Amor De Dios, 31",
    "sg:city":"Sevilla",
    "sg:orig_category":"\u00d3ptica: Instrumentos (fabricaci\u00d3n)",
    "sg:phone":"+34 954 37 09 36",
    "sg:postcode":"41002",
    "sg:province":"Sevilla",
    "wof:name":"Gabra 99 S.l.",
    "wof:placetype":"venue"
},
  "geometry": {"coordinates":[-5.9944901466,37.3953971863],"type":"Point"}
}