{
  "type": "Feature",
  "properties": {
    "iso:country":"ES",
    "sg:address":"Calle de Hermosilla, 5",
    "sg:city":"Madrid",
    "sg:orig_category":"Ingenier\u00cda, Centros De Estudios (diversos)",
    "sg:phone":"+34 914 35 89 79",
    "sg:postcode":"28001",
    "sg:province":"Madrid",
    "wof:name":"Sebastian De Erice Sanchez-oca\u00f1a Francisco Javier",
    "wof:placetype":"venue"
},
  "geometry": {"coordinates":[-3.6884040833,40.4266815186],"type":"Point"}
}