{
  "type": "Feature",
  "properties": {
    "addr:full":"Avda Orovilla, 41 Madrid Madrid 28041",
    "addr:housenumber":"41",
    "addr:postcode":"madrid;28041",
    "addr:street":"Avda Orovilla",
    "iso:country":"ES",
    "sg:address":"Avda Orovilla, 41",
    "sg:city":"Madrid",
    "sg:orig_category":"Cajas De Ahorro",
    "sg:phone":"+34 913 17 05 25",
    "sg:postcode":"28041",
    "sg:province":"Madrid",
    "wof:name":"Caixa D'estalvis De Catalunya",
    "wof:placetype":"venue"
},
  "geometry": {"coordinates":[-3.6896278858,40.3609542847],"type":"Point"}
}