{
  "type": "Feature",
  "properties": {
    "iso:country":"ES",
    "sg:address":"Calle de Embajadores, 76",
    "sg:city":"Madrid",
    "sg:orig_category":"Asesor\u00cda Sobre Comunicaci\u00d3n De Empresas",
    "sg:phone":"+34 914 73 22 77",
    "sg:postcode":"28012",
    "sg:province":"Madrid",
    "wof:name":"Miguel Angel Ruiz Mateos S.l.",
    "wof:placetype":"venue"
},
  "geometry": {"coordinates":[-3.7020950317,40.404209137],"type":"Point"}
}