{
  "type": "Feature",
  "properties": {
    "addr:full":"Carrer de Llull, 27 Barcelona Barcelona 08005",
    "addr:housenumber":"27",
    "addr:postcode":"08005",
    "addr:street":"Carrer De Llull",
    "iso:country":"ES",
    "sg:address":"Carrer de Llull, 27",
    "sg:city":"Barcelona",
    "sg:orig_category":"Abrasivos Y Superabrasivos (fabricaci\u00d3n, Al Por Mayor)",
    "sg:phone":"+34 933 09 64 46",
    "sg:postcode":"08005",
    "sg:province":"Barcelona",
    "wof:name":"Abrasivos Comerciales S.l.",
    "wof:placetype":"venue"
},
  "geometry": {"coordinates":[2.191092,41.392906],"type":"Point"}
}