{
  "type": "Feature",
  "properties": {
    "iso:country":"ES",
    "sg:address":"Praz Cervantes, 5",
    "sg:city":"Celanova",
    "sg:orig_category":"Herboristas (al Por Menor)",
    "sg:phone":"+34 988 43 17 20",
    "sg:postcode":"32800",
    "sg:province":"Ourense",
    "wof:name":"Alen Lemos Alfredo",
    "wof:placetype":"venue"
},
  "geometry": {"coordinates":[-7.9865350723,42.1502799988],"type":"Point"}
}