{
  "type": "Feature",
  "properties": {
    "iso:country":"ES",
    "sg:address":"Urb San Jeronimo, 6",
    "sg:city":"San Jeronimo",
    "sg:orig_category":"Bazares, Art\u00cdculos De Limpieza Y De Cocina (al Por Menor)",
    "sg:phone":"+34 922 32 61 13",
    "sg:postcode":"38312",
    "sg:province":"Santa Cruz De Tenerife",
    "wof:name":"Bella Tradicion S.l.",
    "wof:placetype":"venue"
},
  "geometry": {"coordinates":[-16.5512580872,28.3783855438],"type":"Point"}
}