{
  "type": "Feature",
  "properties": {
    "addr:full":"Carrer de Can Mollet, 28 Mollet Valles Barcelona 08100",
    "addr:housenumber":"28",
    "addr:postcode":"08100",
    "addr:street":"Carrer De Can Mollet",
    "iso:country":"ES",
    "sg:address":"Carrer de Can Mollet, 28",
    "sg:city":"Mollet Valles",
    "sg:orig_category":"Venta, Colocaci\u00d3n, Reparaci\u00d3n De Parabrisas, Techos Descapotables",
    "sg:phone":"+34 935 79 09 13",
    "sg:postcode":"08100",
    "sg:province":"Barcelona",
    "wof:name":"Vtec Mollet S.l.",
    "wof:placetype":"venue"
},
  "geometry": {"coordinates":[2.2186949253,41.5437507629],"type":"Point"}
}