{
  "type": "Feature",
  "properties": {
    "iso:country":"ES",
    "sg:address":"Carrer de Fornaris, 59",
    "sg:city":"Palma",
    "sg:orig_category":"Empresas De Carpinter\u00cda De Madera",
    "sg:phone":"+34 971 24 43 50",
    "sg:postcode":"07007",
    "sg:province":"Islas Baleares",
    "wof:name":"Bauza Alomar Gabriel",
    "wof:placetype":"venue"
},
  "geometry": {"coordinates":[2.6722259521,39.5702781677],"type":"Point"}
}