{
  "type": "Feature",
  "properties": {
    "addr:full":"Calle de Carretera Betica, 18 San Jose Rinconada Sevilla 41300",
    "addr:housenumber":"18",
    "addr:postcode":"41300",
    "addr:street":"Calle De Carretera Betica",
    "iso:country":"ES",
    "sg:address":"Calle de Carretera Betica, 18",
    "sg:city":"San Jose Rinconada",
    "sg:orig_category":"Alquiler De V\u00cddeo",
    "sg:phone":"+34 954 79 15 78",
    "sg:postcode":"41300",
    "sg:province":"Sevilla",
    "wof:name":"Barranquero Perez Jose",
    "wof:placetype":"venue"
},
  "geometry": {"coordinates":[-5.9434189796,37.443523407],"type":"Point"}
}