{
  "type": "Feature",
  "properties": {
    "addr:full":"Calle de Federico Ballell, 1 Caceres C\u00e1ceres 10001",
    "addr:housenumber":"1",
    "addr:postcode":"10001",
    "addr:street":"Calle De Federico Ballell;Ca\u0301Ceres",
    "iso:country":"ES",
    "sg:address":"Calle de Federico Ballell, 1",
    "sg:city":"Caceres",
    "sg:orig_category":"Psic\u00d3logos",
    "sg:phone":"+34 927 24 74 53",
    "sg:postcode":"10001",
    "sg:province":"C\u00e1ceres",
    "wof:name":"Blazquez Andrada Maria Jesus",
    "wof:placetype":"venue"
},
  "geometry": {"coordinates":[-6.3781018257,39.4672050476],"type":"Point"}
}