{
  "type": "Feature",
  "properties": {
    "addr:full":"Calle de Zabaleta, 41 Madrid Madrid 28002",
    "addr:housenumber":"41",
    "addr:postcode":"madrid;28002",
    "addr:street":"Calle De Zabaleta",
    "iso:country":"ES",
    "sg:address":"Calle de Zabaleta, 41",
    "sg:city":"Madrid",
    "sg:orig_category":"Mec\u00c1nico Del Autom\u00d3vil",
    "sg:phone":"+34 914 16 64 83",
    "sg:postcode":"28002",
    "sg:province":"Madrid",
    "wof:name":"Cosmo Auto S.l.",
    "wof:placetype":"venue"
},
  "geometry": {"coordinates":[-3.6727519035,40.4431152344],"type":"Point"}
}