{
  "type": "Feature",
  "properties": {
    "iso:country":"ES",
    "sg:address":"Avda Castilla La Mancha, 1",
    "sg:city":"Calera Y Chozas",
    "sg:orig_category":"Supermercados Y Hipermercados",
    "sg:phone":"+34 925 84 62 00",
    "sg:postcode":"45595",
    "sg:province":"Toledo",
    "wof:name":"Gregocor S.l.",
    "wof:placetype":"venue"
},
  "geometry": {"coordinates":[-4.9894390106,39.8812904358],"type":"Point"}
}