{
  "type": "Feature",
  "properties": {
    "iso:country":"ES",
    "sg:address":"Praz Pio Xii, 5",
    "sg:city":"Lugo",
    "sg:orig_category":"Reposter\u00cdas",
    "sg:phone":"+34 982 24 46 05",
    "sg:postcode":"27001",
    "sg:province":"Lugo",
    "wof:name":"Gonzalez Diaz-becerra Maria Luisa",
    "wof:placetype":"venue"
},
  "geometry": {"coordinates":[-7.5558686256,43.0113105774],"type":"Point"}
}