{
  "type": "Feature",
  "properties": {
    "iso:country":"ES",
    "sg:address":"Calle de Callejon De Los Tiznaos, 7",
    "sg:city":"Cieza",
    "sg:orig_category":"Quincaller\u00cda (al Por Menor)",
    "sg:phone":"+34 968 76 19 17",
    "sg:postcode":"30530",
    "sg:province":"Murcia",
    "wof:name":"Dato Moreno Juan",
    "wof:placetype":"venue"
},
  "geometry": {"coordinates":[-1.4236116409,38.2392501831],"type":"Point"}
}