{
  "type": "Feature",
  "properties": {
    "iso:country":"ES",
    "sg:address":"San Juan Y Santiago, 22",
    "sg:city":"Montaverner",
    "sg:orig_category":"Insecticidas, Fumigaci\u00d3n",
    "sg:phone":"+34 962 29 76 23",
    "sg:postcode":"46892",
    "sg:province":"Valencia",
    "wof:name":"Agricolas De Servicios Y Tecnologias Aplicadas S.l.",
    "wof:placetype":"venue"
},
  "geometry": {"coordinates":[-0.4903523922,38.8848571777],"type":"Point"}
}