{
  "type": "Feature",
  "properties": {
    "iso:country":"ES",
    "sg:address":"Plaz Encuentro, 1",
    "sg:city":"Madrid",
    "sg:orig_category":"Comunidades Religiosas",
    "sg:phone":"+34 913 28 01 75",
    "sg:postcode":"28030",
    "sg:province":"Madrid",
    "wof:name":"Sociedad Del Sagrado Corazon De Jesus Provincia Centro Sur Curia Provincial",
    "wof:placetype":"venue"
},
  "geometry": {"coordinates":[-3.6517701149,40.4057502747],"type":"Point"}
}