{
  "type": "Feature",
  "properties": {
    "addr:full":"Calle de Don Ramon Areces, 2 Valdemoro Madrid 28340",
    "addr:housenumber":"2",
    "addr:postcode":"28340",
    "addr:street":"Calle De Don Ramon Areces",
    "iso:country":"ES",
    "sg:address":"Calle de Don Ramon Areces, 2",
    "sg:city":"Valdemoro",
    "sg:orig_category":"Reposter\u00cdas",
    "sg:phone":"+34 918 95 42 50",
    "sg:postcode":"28340",
    "sg:province":"Madrid",
    "wof:name":"Garcia Cuesta Leonor",
    "wof:placetype":"venue"
},
  "geometry": {"coordinates":[-3.6802339554,40.1931686401],"type":"Point"}
}