{
  "type": "Feature",
  "properties": {
    "addr:full":"Calle de San Juan, 14 Donostia-san Sebastian Guip\u00f9zcoa 20003",
    "addr:housenumber":"14",
    "addr:postcode":"20003",
    "addr:street":"Calle De San Juan",
    "iso:country":"ES",
    "sg:address":"Calle de San Juan, 14",
    "sg:city":"Donostia-san Sebastian",
    "sg:orig_category":"Organizaciones Internacionales",
    "sg:phone":"+34 943 42 08 18",
    "sg:postcode":"20003",
    "sg:province":"Guip\u00f9zcoa",
    "wof:name":"Instituto De Psicologia Integral Baraka",
    "wof:placetype":"venue"
},
  "geometry": {"coordinates":[-1.9844330549,43.3257522583],"type":"Point"}
}