{
  "type": "Feature",
  "properties": {
    "addr:full":"Calle de Abastos (de), 64 Aranjuez Madrid 28300",
    "addr:postcode":"28300",
    "addr:street":"Calle De",
    "iso:country":"ES",
    "sg:address":"Calle de Abastos (de), 64",
    "sg:city":"Aranjuez",
    "sg:orig_category":"Zapatos (al Por Menor)",
    "sg:phone":"+34 918 01 18 71",
    "sg:postcode":"28300",
    "sg:province":"Madrid",
    "wof:name":"Eszzinttela.s.l.l.",
    "wof:placetype":"venue"
},
  "geometry": {"coordinates":[-3.6029531956,40.0318756104],"type":"Point"}
}