{
  "type": "Feature",
  "properties": {
    "iso:country":"ES",
    "sg:address":"Rua Oviedo, S/n",
    "sg:city":"Meicende",
    "sg:orig_category":"Fabricaci\u00d3n, Instalaci\u00d3n De Armarios",
    "sg:phone":"+34 981 14 11 37",
    "sg:postcode":"15140",
    "sg:province":"La Coru\u00f1a",
    "wof:name":"Fernandez Baldomir Eloy",
    "wof:placetype":"venue"
},
  "geometry": {"coordinates":[-8.4483203888,43.3471298218],"type":"Point"}
}