{
  "type": "Feature",
  "properties": {
    "addr:full":"Avda Estacion (de La), 2 Villagonzalo-pedernales Burgos 09195",
    "addr:housenumber":"2",
    "addr:postcode":"09195",
    "addr:street":"Avda Estacion De La",
    "iso:country":"ES",
    "sg:address":"Avda Estacion (de La), 2",
    "sg:city":"Villagonzalo-pedernales",
    "sg:orig_category":"Electricidad: Equipos Industriales, Componentes (fabricaci\u00d3n)",
    "sg:phone":"+34 947 29 42 90",
    "sg:postcode":"09195",
    "sg:province":"Burgos",
    "wof:name":"Hager Sistemas S.a.",
    "wof:placetype":"venue"
},
  "geometry": {"coordinates":[-3.7336130142,42.3010635376],"type":"Point"}
}