{
  "type": "Feature",
  "properties": {
    "iso:country":"ES",
    "sg:address":"Calle de Libertad, 30",
    "sg:city":"Aliseda",
    "sg:orig_category":"Carnicer\u00cdas, Carnicer\u00cdas",
    "sg:phone":"+34 927 27 70 29",
    "sg:postcode":"10550",
    "sg:province":"C\u00e1ceres",
    "wof:name":"Embutidos Barriga Cb",
    "wof:placetype":"venue"
},
  "geometry": {"coordinates":[-6.6929430962,39.4211997986],"type":"Point"}
}