{
  "type": "Feature",
  "properties": {
    "addr:full":"Calle de Libertad, 30 Aliseda C\u00e1ceres 10550",
    "addr:housenumber":"30",
    "addr:postcode":"10550",
    "addr:street":"Calle De Libertad;Ca\u0301Ceres",
    "iso:country":"ES",
    "sg:address":"Calle de Libertad, 30",
    "sg:city":"Aliseda",
    "sg:orig_category":"Carnicer\u00cdas, Carnicer\u00cdas",
    "sg:phone":"+34 927 27 70 29",
    "sg:postcode":"10550",
    "sg:province":"C\u00e1ceres",
    "wof:name":"Embutidos Barriga Cb",
    "wof:placetype":"venue"
},
  "geometry": {"coordinates":[-6.6929430962,39.4211997986],"type":"Point"}
}