{
  "type": "Feature",
  "properties": {
    "addr:full":"Pl Catalunya, 35 S. Boi Llobregat Barcelona 08830",
    "addr:housenumber":"35",
    "addr:postcode":"08830",
    "addr:street":"Pl Catalunya",
    "iso:country":"ES",
    "sg:address":"Pl Catalunya, 35",
    "sg:city":"S. Boi Llobregat",
    "sg:orig_category":"Loter\u00cda Y T\u00d3mbola",
    "sg:phone":"+34 936 52 01 37",
    "sg:postcode":"08830",
    "sg:province":"Barcelona",
    "wof:name":"Ivern Pallas Jordi",
    "wof:placetype":"venue"
},
  "geometry": {"coordinates":[2.041367054,41.3409385681],"type":"Point"}
}