{
  "type": "Feature",
  "properties": {
    "iso:country":"ES",
    "sg:address":"Calle de Castilla La Vieja (de), 5",
    "sg:city":"Fuenlabrada",
    "sg:orig_category":"Centros Empresariales",
    "sg:phone":"+34 914 92 03 23",
    "sg:postcode":"28941",
    "sg:province":"Madrid",
    "wof:name":"Mora-fernandez Montes Julian Jesus",
    "wof:placetype":"venue"
},
  "geometry": {"coordinates":[-3.8010318279,40.2911300659],"type":"Point"}
}