{
  "type": "Feature",
  "properties": {
    "iso:country":"ES",
    "sg:address":"Casillas, S/n",
    "sg:city":"Casillas",
    "sg:orig_category":"Contenedores (mercanc\u00cdas)",
    "sg:phone":"+34 981 68 03 50",
    "sg:postcode":"15680",
    "sg:province":"La Coru\u00f1a",
    "wof:name":"Regueiro Moar Antonio",
    "wof:placetype":"venue"
},
  "geometry": {"coordinates":[-8.4072790146,43.0771408081],"type":"Point"}
}