{
  "type": "Feature",
  "properties": {
    "iso:country":"ES",
    "sg:address":"Av Carrilet, 64",
    "sg:city":"Castell D'aro",
    "sg:orig_category":"Mosquiteras",
    "sg:phone":"+34 972 82 29 69",
    "sg:postcode":"17249",
    "sg:province":"Girona",
    "sg:website":"www.perlum.com",
    "wof:name":"Perlum Persianas Y Puertas S.l.u.",
    "wof:placetype":"venue"
},
  "geometry": {"coordinates":[2.8271551132,41.988822937],"type":"Point"}
}