{
  "type": "Feature",
  "properties": {
    "iso:country":"ES",
    "sg:address":"Carr Pintor Sorolla, 28",
    "sg:city":"Benetusser",
    "sg:orig_category":"Electricidad: Instaladores",
    "sg:phone":"+34 963 75 46 19",
    "sg:postcode":"46910",
    "sg:province":"Valencia",
    "wof:name":"Rangel Del Amo Jose",
    "wof:placetype":"venue"
},
  "geometry": {"coordinates":[-0.3950400054,39.4223098755],"type":"Point"}
}