{
  "type": "Feature",
  "properties": {
    "addr:full":"Calle de Elfo, 76 Madrid Madrid 28027",
    "addr:housenumber":"76",
    "addr:postcode":"madrid;28027",
    "addr:street":"Calle De Elfo",
    "iso:country":"ES",
    "sg:address":"Calle de Elfo, 76",
    "sg:city":"Madrid",
    "sg:orig_category":"Dietistas",
    "sg:phone":"+34 913 68 00 20",
    "sg:postcode":"28027",
    "sg:province":"Madrid",
    "sg:website":"www.naturhouse.com",
    "wof:name":"Mcdiet C.b.",
    "wof:placetype":"venue"
},
  "geometry": {"coordinates":[-3.6463849545,40.4353256226],"type":"Point"}
}