{
  "type": "Feature",
  "properties": {
    "iso:country":"ES",
    "sg:address":"Calle de Poligono Industrial, 28",
    "sg:city":"Cabeza Buey",
    "sg:orig_category":"Fabricaci\u00d3n De Su\u00c9ters Y Chalecos De Punto",
    "sg:phone":"+34 924 63 21 51",
    "sg:postcode":"06600",
    "sg:province":"Badajoz",
    "wof:name":"Jose Barbarroja S.l.",
    "wof:placetype":"venue"
},
  "geometry": {"coordinates":[-5.2242388725,38.7196540833],"type":"Point"}
}