{
  "type": "Feature",
  "properties": {
    "iso:country":"ES",
    "sg:address":"Ctra Murcia, Km. 0043,0",
    "sg:city":"Crevillente",
    "sg:orig_category":"Carnicer\u00cdas, Carnicer\u00cdas",
    "sg:phone":"+34 965 40 41 91",
    "sg:postcode":"03330",
    "sg:province":"Alicante",
    "wof:name":"Jamoneras Crevillente S.l.u.",
    "wof:placetype":"venue"
},
  "geometry": {"coordinates":[-0.8052690029,38.2463111877],"type":"Point"}
}