{
  "type": "Feature",
  "properties": {
    "iso:country":"ES",
    "sg:address":"Plaz San Juan, 35",
    "sg:city":"Villanueva De Los Infantes",
    "sg:orig_category":"Molduras, Junquillos, Listones Y Molduras Perforadas",
    "sg:phone":"+34 926 36 13 72",
    "sg:postcode":"13320",
    "sg:province":"Ciudad Real",
    "wof:name":"Gomez Perez Antonio",
    "wof:placetype":"venue"
},
  "geometry": {"coordinates":[-3.0116250515,38.7341918945],"type":"Point"}
}