{
  "type": "Feature",
  "properties": {
    "addr:full":"Carr Industria, 12 Bisbal D'emporda Girona 17100",
    "addr:housenumber":"12",
    "addr:postcode":"17100",
    "addr:street":"Carr Industria",
    "iso:country":"ES",
    "sg:address":"Carr Industria, 12",
    "sg:city":"Bisbal D'emporda",
    "sg:orig_category":"Alfarer\u00cda",
    "sg:phone":"+34 972 64 09 54",
    "sg:postcode":"17100",
    "sg:province":"Girona",
    "wof:name":"Sala Mitja Carlos",
    "wof:placetype":"venue"
},
  "geometry": {"coordinates":[2.8056209087,41.9651374817],"type":"Point"}
}