{
  "type": "Feature",
  "properties": {
    "iso:country":"ES",
    "sg:address":"Calle de Mariano Jose De Larra, 8",
    "sg:city":"Colmenar Viejo",
    "sg:orig_category":"Escayola Y Productos De Escayola (fabricaci\u00d3n, Al Por Mayor)",
    "sg:phone":"+34 918 45 21 83",
    "sg:postcode":"28770",
    "sg:province":"Madrid",
    "wof:name":"Ramos Campuzano Manuel",
    "wof:placetype":"venue"
},
  "geometry": {"coordinates":[-3.7783279419,40.6576538086],"type":"Point"}
}