{
  "type": "Feature",
  "properties": {
    "iso:country":"ES",
    "sg:address":"Zuloaga Kalea, 11",
    "sg:city":"Portua",
    "sg:orig_category":"Carnicer\u00cdas, Carnicer\u00cdas",
    "sg:phone":"+34 943 64 18 60",
    "sg:postcode":"20280",
    "sg:province":"Guip\u00f9zcoa",
    "wof:name":"Albistur Echaide Jose Luis",
    "wof:placetype":"venue"
},
  "geometry": {"coordinates":[-1.7936060429,43.3682327271],"type":"Point"}
}