{
  "type": "Feature",
  "properties": {
    "addr:full":"Pase Ygareda, 42 Cabez\u00f3n Sal Cantabria 39500",
    "addr:housenumber":"42",
    "addr:postcode":"39500",
    "addr:street":"Ygareda",
    "iso:country":"ES",
    "sg:address":"Pase Ygareda, 42",
    "sg:city":"Cabez\u00f3n Sal",
    "sg:orig_category":"Imprenta",
    "sg:phone":"+34 942 70 00 73",
    "sg:postcode":"39500",
    "sg:province":"Cantabria",
    "wof:name":"Gonzalez Diaz Rafael Simon",
    "wof:placetype":"venue"
},
  "geometry": {"coordinates":[-4.2374691963,43.3085784912],"type":"Point"}
}