{
  "type": "Feature",
  "properties": {
    "iso:country":"ES",
    "sg:address":"Calle de Panaderos, 65",
    "sg:city":"Valladolid",
    "sg:orig_category":"Contenedores (mercanc\u00cdas)",
    "sg:phone":"+34 983 20 31 94",
    "sg:postcode":"47004",
    "sg:province":"Valladolid",
    "wof:name":"Due\u00f1as Sanz Abel",
    "wof:placetype":"venue"
},
  "geometry": {"coordinates":[-4.7221660614,41.6449012756],"type":"Point"}
}