{
  "type": "Feature",
  "properties": {
    "iso:country":"ES",
    "sg:address":"Av Industria, 70",
    "sg:city":"S. Just Desvern",
    "sg:orig_category":"Piscinas, Accesorios, Suministros (fabricaci\u00d3n, Al Por Mayor)",
    "sg:phone":"+34 934 80 22 13",
    "sg:postcode":"08960",
    "sg:province":"Barcelona",
    "wof:name":"Concepte Blau Piscinas Sl",
    "wof:placetype":"venue"
},
  "geometry": {"coordinates":[2.0733029842,41.3850364685],"type":"Point"}
}