{
  "type": "Feature",
  "properties": {
    "addr:full":"Avda Mejico (de), 10 Jerez De La Frontera C\u00e1diz 11405",
    "addr:postcode":"11405",
    "addr:street":"Avda Mejico De",
    "iso:country":"ES",
    "sg:address":"Avda Mejico (de), 10",
    "sg:city":"Jerez De La Frontera",
    "sg:orig_category":"Doctores En Medicina",
    "sg:phone":"+34 956 30 18 10",
    "sg:postcode":"11405",
    "sg:province":"C\u00e1diz",
    "wof:name":"Garcia Pagola Maria Angeles",
    "wof:placetype":"venue"
},
  "geometry": {"coordinates":[-6.1285557747,36.692741394],"type":"Point"}
}