{
  "type": "Feature",
  "properties": {
    "addr:full":"Calle de Lucena Del Puerto, 19 Huelva Huelva 21002",
    "addr:housenumber":"19",
    "addr:postcode":"21002",
    "addr:street":"Calle De Lucena Del Puerto",
    "iso:country":"ES",
    "sg:address":"Calle de Lucena Del Puerto, 19",
    "sg:city":"Huelva",
    "sg:orig_category":"Mec\u00c1nico Del Autom\u00d3vil",
    "sg:phone":"+34 959 24 42 35",
    "sg:postcode":"21002",
    "sg:province":"Huelva",
    "wof:name":"Taller Diesel Cismar S.l.",
    "wof:placetype":"venue"
},
  "geometry": {"coordinates":[-6.9571170807,37.2632217407],"type":"Point"}
}