{
  "type": "Feature",
  "properties": {
    "iso:country":"ES",
    "sg:address":"Calle de Venezuela, 4",
    "sg:city":"Valencia",
    "sg:orig_category":"Asociaciones Y Clubs Deportivos",
    "sg:phone":"+34 963 77 34 34",
    "sg:postcode":"46007",
    "sg:province":"Valencia",
    "wof:name":"Club Deportivo Zafranar",
    "wof:placetype":"venue"
},
  "geometry": {"coordinates":[-0.3899269998,39.456111908],"type":"Point"}
}