{
  "type": "Feature",
  "properties": {
    "addr:full":"Avda Osa Mayor, 40 Madrid Madrid 28023",
    "addr:housenumber":"40",
    "addr:postcode":"madrid;28023",
    "addr:street":"Avda Osa Mayor",
    "iso:country":"ES",
    "sg:address":"Avda Osa Mayor, 40",
    "sg:city":"Madrid",
    "sg:orig_category":"Arquitectos",
    "sg:phone":"+34 913 57 42 09",
    "sg:postcode":"28023",
    "sg:province":"Madrid",
    "wof:name":"De La Joya Ortiz Echag\u00fce Cesar",
    "wof:placetype":"venue"
},
  "geometry": {"coordinates":[-3.78053689,40.4593315125],"type":"Point"}
}