{
  "type": "Feature",
  "properties": {
    "iso:country":"ES",
    "sg:address":"Calle de Juan Ramon Jimenez, 4",
    "sg:city":"Campillos",
    "sg:classifiers":[
        {
            "category":"Taxi",
            "type":"Transportation"
        }
    ],
    "sg:phone":"+34 952 72 31 39",
    "sg:postcode":"29320",
    "sg:province":"M\u00e1laga",
    "wof:name":"Trigos Correro Andres",
    "wof:placetype":"venue"
},
  "geometry": {"coordinates":[-4.8566150665,37.0505714417],"type":"Point"}
}