{
  "type": "Feature",
  "properties": {
    "iso:country":"ES",
    "sg:address":"Calle de Reding, 19",
    "sg:city":"Malaga",
    "sg:orig_category":"Centros Empresariales",
    "sg:phone":"+34 952 21 33 37",
    "sg:postcode":"29016",
    "sg:province":"M\u00e1laga",
    "wof:name":"Jalikonke S.l.",
    "wof:placetype":"venue"
},
  "geometry": {"coordinates":[-4.4111189842,36.717502594],"type":"Point"}
}