{
  "type": "Feature",
  "properties": {
    "iso:country":"ES",
    "sg:address":"Calle de Merced La, 25",
    "sg:city":"Gijon",
    "sg:orig_category":"Confecci\u00d3n De Trajes Para Se\u00d1oras",
    "sg:phone":"+34 985 17 23 65",
    "sg:postcode":"33201",
    "sg:province":"Asturias",
    "wof:name":"Riesgo Feito Cayo",
    "wof:placetype":"venue"
},
  "geometry": {"coordinates":[-5.662112236,43.5417098999],"type":"Point"}
}