{
  "type": "Feature",
  "properties": {
    "iso:country":"ES",
    "sg:address":"Carrer de Montserrat, 14",
    "sg:city":"Vic",
    "sg:orig_category":"Prot\u00c9sicos Dentales",
    "sg:phone":"+34 938 89 23 58",
    "sg:postcode":"08500",
    "sg:province":"Barcelona",
    "wof:name":"Gallach Bau Pere",
    "wof:placetype":"venue"
},
  "geometry": {"coordinates":[2.2615909576,41.9286346436],"type":"Point"}
}