{
  "type": "Feature",
  "properties": {
    "iso:country":"ES",
    "sg:address":"Cda. Ralet, S/n",
    "sg:city":"Calafell",
    "sg:orig_category":"Supermercados Y Hipermercados",
    "sg:phone":"+34 977 69 58 35",
    "sg:postcode":"43820",
    "sg:province":"Tarragona",
    "wof:name":"Autoservei Vipla S.l.",
    "wof:placetype":"venue"
},
  "geometry": {"coordinates":[1.5543987751,41.2040290833],"type":"Point"}
}