{
  "type": "Feature",
  "properties": {
    "iso:country":"ES",
    "sg:address":"Carrer de Antonio Machado, 4",
    "sg:city":"Castelldefels",
    "sg:orig_category":"Cl\u00cdnicas Dentales",
    "sg:phone":"+34 936 36 32 42",
    "sg:postcode":"08860",
    "sg:province":"Barcelona",
    "wof:name":"Navarro Pe\u00f1a Emilio",
    "wof:placetype":"venue"
},
  "geometry": {"coordinates":[1.9811749458,41.2860870361],"type":"Point"}
}