{
  "type": "Feature",
  "properties": {
    "addr:full":"B, S/n P. I. El Romeral Valencia 46340",
    "addr:housenumber":"s / n",
    "addr:postcode":"46340",
    "addr:street":"P. I. El Romeral",
    "iso:country":"ES",
    "sg:address":"B, S/n",
    "sg:city":"P. I. El Romeral",
    "sg:orig_category":"Electricidad Veh\u00cdculo",
    "sg:phone":"+34 962 30 22 90",
    "sg:postcode":"46340",
    "sg:province":"Valencia",
    "wof:name":"Electricidad Del Automovil Jani S.l.l",
    "wof:placetype":"venue"
},
  "geometry": {"coordinates":[-1.0998990536,39.4906158447],"type":"Point"}
}