{
  "type": "Feature",
  "properties": {
    "addr:full":"Av Llibertat, 105 Elche Alicante 03201",
    "addr:housenumber":"105",
    "addr:postcode":"03201",
    "addr:street":"Av Llibertat",
    "iso:country":"ES",
    "sg:address":"Av Llibertat, 105",
    "sg:city":"Elche",
    "sg:orig_category":"Sociedades, Compa\u00d1\u00cdas Aseguradoras",
    "sg:phone":"+34 965 46 04 10",
    "sg:postcode":"03201",
    "sg:province":"Alicante",
    "sg:website":"www.iespana.es/surseguros",
    "wof:name":"Sempere Soto Raul",
    "wof:placetype":"venue"
},
  "geometry": {"coordinates":[-0.711090982,38.265411377],"type":"Point"}
}