{
  "type": "Feature",
  "properties": {
    "addr:full":"Calle de Cartagena, 166 Madrid Madrid 28002",
    "addr:housenumber":"166",
    "addr:postcode":"28002",
    "addr:street":"Calle De Cartagena",
    "iso:country":"ES",
    "sg:address":"Calle de Cartagena, 166",
    "sg:city":"Madrid",
    "sg:orig_category":"Mec\u00c1nico Del Autom\u00d3vil",
    "sg:phone":"+34 914 11 60 39",
    "sg:postcode":"28002",
    "sg:province":"Madrid",
    "wof:name":"Talleres Hergo Madrid S.l.",
    "wof:placetype":"venue"
},
  "geometry": {"coordinates":[-3.6768701077,40.4437446594],"type":"Point"}
}