{
  "type": "Feature",
  "properties": {
    "iso:country":"ES",
    "sg:address":"Carrer de Valldoreix, 29",
    "sg:city":"S. Cugat Valles",
    "sg:orig_category":"Bisuter\u00cda, Joyer\u00cda, Relojer\u00cda (al Por Menor)",
    "sg:phone":"+34 936 75 62 84",
    "sg:postcode":"08172",
    "sg:province":"Barcelona",
    "wof:name":"Brossons S.l",
    "wof:placetype":"venue"
},
  "geometry": {"coordinates":[2.0804820061,41.4700241089],"type":"Point"}
}