{
  "type": "Feature",
  "properties": {
    "addr:full":"Avda Primero De Mayo, 94 Puertollano Ciudad Real 13500",
    "addr:housenumber":"94",
    "addr:postcode":"13500",
    "addr:street":"Avda Primero De Mayo",
    "iso:country":"ES",
    "sg:address":"Avda Primero De Mayo, 94",
    "sg:city":"Puertollano",
    "sg:orig_category":"Pintura Y Barniz (al Por Menor)",
    "sg:phone":"+34 926 43 07 56",
    "sg:postcode":"13500",
    "sg:province":"Ciudad Real",
    "wof:name":"Industrias Juno S.a.",
    "wof:placetype":"venue"
},
  "geometry": {"coordinates":[-4.1048989296,38.6865501404],"type":"Point"}
}