{
  "type": "Feature",
  "properties": {
    "addr:full":"Avda Condes De San Isidro, 27 Fuengirola M\u00e1laga 29640",
    "addr:housenumber":"27",
    "addr:postcode":"29640",
    "addr:street":"Avda Condes De San Isidro;Ma\u0301Laga",
    "iso:country":"ES",
    "sg:address":"Avda Condes De San Isidro, 27",
    "sg:city":"Fuengirola",
    "sg:orig_category":"Art\u00cdculos De Regalo (al Por Menor)",
    "sg:phone":"+34 952 47 42 30",
    "sg:postcode":"29640",
    "sg:province":"M\u00e1laga",
    "wof:name":"Regalos Merino Corral S.l.",
    "wof:placetype":"venue"
},
  "geometry": {"coordinates":[-4.6263461113,36.5347137451],"type":"Point"}
}