{
  "type": "Feature",
  "properties": {
    "addr:full":"Carrer de Constitucio, 177 Barcelona Barcelona 08014",
    "addr:housenumber":"177",
    "addr:postcode":"08014",
    "addr:street":"Carrer De Constitucio",
    "iso:country":"ES",
    "sg:address":"Carrer de Constitucio, 177",
    "sg:city":"Barcelona",
    "sg:orig_category":"Construcciones Met\u00c1licas",
    "sg:phone":"+34 934 32 18 15",
    "sg:postcode":"08014",
    "sg:province":"Barcelona",
    "wof:name":"Bel Bosch Rosa Maria",
    "wof:placetype":"venue"
},
  "geometry": {"coordinates":[2.1320729256,41.3683509827],"type":"Point"}
}