{
  "type": "Feature",
  "properties": {
    "addr:full":"Calle de Rascafria, 42 Villaviciosa Odon Madrid 28670",
    "addr:housenumber":"42",
    "addr:postcode":"28670",
    "addr:street":"Calle De Rascafria;Odon",
    "iso:country":"ES",
    "sg:address":"Calle de Rascafria, 42",
    "sg:city":"Villaviciosa Odon",
    "sg:orig_category":"Carnicer\u00cdas, Carnicer\u00cdas",
    "sg:phone":"+34 916 16 35 16",
    "sg:postcode":"28670",
    "sg:province":"Madrid",
    "wof:name":"Menda\u00f1a Alonso Angel",
    "wof:placetype":"venue"
},
  "geometry": {"coordinates":[-3.9099678993,40.3525123596],"type":"Point"}
}