{
  "type": "Feature",
  "properties": {
    "addr:full":"Ptda La Ca\u00f1ada, S/n S. Vicente Raspeig Alicante 03690",
    "addr:housenumber":"s",
    "addr:postcode":"03690",
    "addr:street":"Ptda La Can\u0303Ada;/ N S. Vicente Raspeig",
    "iso:country":"ES",
    "sg:address":"Ptda La Ca\u00f1ada, S/n",
    "sg:city":"S. Vicente Raspeig",
    "sg:orig_category":"Poller\u00cda Y Caza (al Por Menor)",
    "sg:phone":"+34 965 66 33 02",
    "sg:postcode":"03690",
    "sg:province":"Alicante",
    "wof:name":"Alcozap Distribuciones S.l.",
    "wof:placetype":"venue"
},
  "geometry": {"coordinates":[-0.5111595988,38.4068145752],"type":"Point"}
}