{
  "type": "Feature",
  "properties": {
    "addr:full":"C/ Vila De Bilbao, S/n Paterna Valencia 46988",
    "addr:housenumber":"s / n",
    "addr:postcode":"46988",
    "addr:street":"C / Vila De Bilbao",
    "iso:country":"ES",
    "sg:address":"C/ Vila De Bilbao, S/n",
    "sg:city":"Paterna",
    "sg:orig_category":"Engranajes Y Elementos De Transmisi\u00d3n",
    "sg:phone":"+34 961 34 05 06",
    "sg:postcode":"46988",
    "sg:province":"Valencia",
    "wof:name":"Fellar S. A.",
    "wof:placetype":"venue"
},
  "geometry": {"coordinates":[-0.4600740075,39.516254425],"type":"Point"}
}