{
  "type": "Feature",
  "properties": {
    "iso:country":"ES",
    "sg:address":"Calle de Gorbea, 13",
    "sg:city":"Vitoria-gasteiz",
    "sg:orig_category":"Art\u00cdculos De Regalo (al Por Menor)",
    "sg:phone":"+34 945 20 00 79",
    "sg:postcode":"01012",
    "sg:province":"\u00c1lava",
    "wof:name":"Vazquez Fernandez Pilar",
    "wof:placetype":"venue"
},
  "geometry": {"coordinates":[-2.6799499989,42.8504562378],"type":"Point"}
}