{
  "type": "Feature",
  "properties": {
    "addr:full":"Calle de Trafalgar, 3 Langreo Asturias 33900",
    "addr:housenumber":"3",
    "addr:postcode":"33900",
    "addr:street":"Calle De Trafalgar",
    "iso:country":"ES",
    "sg:address":"Calle de Trafalgar, 3",
    "sg:city":"Langreo",
    "sg:orig_category":"Abogados",
    "sg:phone":"+34 985 69 10 51",
    "sg:postcode":"33900",
    "sg:province":"Asturias",
    "wof:name":"Braya Bejarano Benjamin",
    "wof:placetype":"venue"
},
  "geometry": {"coordinates":[-5.6851148605,43.2954978943],"type":"Point"}
}