{
  "type": "Feature",
  "properties": {
    "iso:country":"ES",
    "sg:address":"Carrer de Jaume Fabra, 16",
    "sg:city":"Barcelona",
    "sg:orig_category":"Molduras, Junquillos, Listones Y Molduras Perforadas",
    "sg:phone":"+34 933 25 04 46",
    "sg:postcode":"08004",
    "sg:province":"Barcelona",
    "wof:name":"Gonzalez Alvarez Ventura",
    "wof:placetype":"venue"
},
  "geometry": {"coordinates":[2.1595699787,41.3743972778],"type":"Point"}
}