{
  "type": "Feature",
  "properties": {
    "addr:full":"Calle de Santiago Lopez, 5 Cuenca Cuenca 16004",
    "addr:housenumber":"5",
    "addr:postcode":"16004",
    "addr:street":"Calle De Santiago Lopez",
    "iso:country":"ES",
    "sg:address":"Calle de Santiago Lopez, 5",
    "sg:city":"Cuenca",
    "sg:orig_category":"Organizaciones Internacionales",
    "sg:phone":"+34 969 22 38 23",
    "sg:postcode":"16004",
    "sg:province":"Cuenca",
    "sg:website":"www.aldeasinfantiles.es",
    "wof:name":"Aldeas Infantiles S.o.s. De Espa\u00d1a",
    "wof:placetype":"venue"
},
  "geometry": {"coordinates":[-2.1339821815,40.0700683594],"type":"Point"}
}