{
  "type": "Feature",
  "properties": {
    "iso:country":"ES",
    "sg:address":"Avda Doctor Meca, 4",
    "sg:city":"Puerto Mazarron",
    "sg:orig_category":"Inmobiliaria (agencias)",
    "sg:phone":"+34 968 15 36 27",
    "sg:postcode":"30860",
    "sg:province":"Murcia",
    "wof:name":"Jose De La Cruz Y Otros C.b",
    "wof:placetype":"venue"
},
  "geometry": {"coordinates":[-1.2593890429,37.5651397705],"type":"Point"}
}