{
  "type": "Feature",
  "properties": {
    "addr:full":"Calle de Libertad, 37 Madrid Madrid 28004",
    "addr:housenumber":"37",
    "addr:postcode":"madrid;28004",
    "addr:street":"Calle De Libertad",
    "iso:country":"ES",
    "sg:address":"Calle de Libertad, 37",
    "sg:city":"Madrid",
    "sg:orig_category":"Compraventa De Antig\u00dcedades",
    "sg:phone":"+34 915 32 70 37",
    "sg:postcode":"28004",
    "sg:province":"Madrid",
    "sg:website":"www.personal.telefonica.terra.es/web/casapostal",
    "wof:name":"Carrasco Marques Martin",
    "wof:placetype":"venue"
},
  "geometry": {"coordinates":[-3.6971049309,40.4225692749],"type":"Point"}
}