{
  "type": "Feature",
  "properties": {
    "iso:country":"ES",
    "sg:address":"Plaz Monta\u00d1eros Vetusta, 12",
    "sg:city":"Oviedo",
    "sg:orig_category":"Clubes Y Asociaciones Deportivas Y De Actividades Invernales Y De Monta\u00d1a",
    "sg:phone":"+34 985 29 65 62",
    "sg:postcode":"33011",
    "sg:province":"Asturias",
    "wof:name":"Club Voleibol Oviedo",
    "wof:placetype":"venue"
},
  "geometry": {"coordinates":[-5.8170027733,43.382232666],"type":"Point"}
}