{
  "type": "Feature",
  "properties": {
    "iso:country":"ES",
    "sg:address":"Carrer de Horts, 8",
    "sg:city":"Garriga",
    "sg:orig_category":"Electricidad Veh\u00cdculo",
    "sg:phone":"+34 938 71 76 57",
    "sg:postcode":"08530",
    "sg:province":"Barcelona",
    "wof:name":"Mauri Bote Miquel",
    "wof:placetype":"venue"
},
  "geometry": {"coordinates":[2.2841649055,41.6877250671],"type":"Point"}
}