{
  "type": "Feature",
  "properties": {
    "iso:country":"ES",
    "sg:address":"Avda Puerto, 49",
    "sg:city":"Casar Palomero",
    "sg:orig_category":"Transportes Por V\u00cdas Navegables",
    "sg:phone":"+34 927 43 61 69",
    "sg:postcode":"10640",
    "sg:province":"C\u00e1ceres",
    "wof:name":"Dominguez Caballero German",
    "wof:placetype":"venue"
},
  "geometry": {"coordinates":[-6.2565989494,40.2934608459],"type":"Point"}
}