{
  "type": "Feature",
  "properties": {
    "iso:country":"ES",
    "sg:address":"Calle de Fatas, 4",
    "sg:city":"Huesca",
    "sg:orig_category":"Arquitectos",
    "sg:phone":"+34 974 22 98 67",
    "sg:postcode":"22002",
    "sg:province":"Huesca",
    "wof:name":"Cabellud Lopez Angel",
    "wof:placetype":"venue"
},
  "geometry": {"coordinates":[-0.4072349966,42.1358337402],"type":"Point"}
}