{
  "type": "Feature",
  "properties": {
    "addr:full":"Calle de Metalurgicos, 11 Almansa Albacete 02640",
    "addr:housenumber":"11",
    "addr:postcode":"02640",
    "addr:street":"Calle De Metalurgicos",
    "iso:country":"ES",
    "sg:address":"Calle de Metalurgicos, 11",
    "sg:city":"Almansa",
    "sg:orig_category":"Fabricaci\u00d3n De Moldes Y Modelos",
    "sg:phone":"+34 967 31 18 81",
    "sg:postcode":"02640",
    "sg:province":"Albacete",
    "wof:name":"Goeding Espa\u00f1a S.l.",
    "wof:placetype":"venue"
},
  "geometry": {"coordinates":[-1.1094889641,38.8758888245],"type":"Point"}
}