{
  "type": "Feature",
  "properties": {
    "iso:country":"ES",
    "sg:address":"Calle de Marques De Boil, 2",
    "sg:city":"Cordoba",
    "sg:orig_category":"Asesor\u00cda Sobre Comunicaci\u00d3n De Empresas",
    "sg:phone":"+34 957 48 26 59",
    "sg:postcode":"14008",
    "sg:province":"C\u00f3rdoba",
    "wof:name":"Aseconsul S B V S.l.",
    "wof:placetype":"venue"
},
  "geometry": {"coordinates":[-4.7840461731,37.8874588013],"type":"Point"}
}