{
  "type": "Feature",
  "properties": {
    "addr:full":"Cmno Santa Agueda, 1 Casta\u00d1eta M\u00e1laga 29590",
    "addr:housenumber":"1",
    "addr:postcode":"29590",
    "addr:street":"Cmno Santa Agueda;Ma\u0301Laga",
    "iso:country":"ES",
    "sg:address":"Cmno Santa Agueda, 1",
    "sg:city":"Casta\u00d1eta",
    "sg:orig_category":"Estudios, Instalaci\u00d3n De Climatizaci\u00d3n",
    "sg:phone":"+34 952 62 61 27",
    "sg:postcode":"29590",
    "sg:province":"M\u00e1laga",
    "wof:name":"Ecoclima Aire Acondicionado S.l.",
    "wof:placetype":"venue"
},
  "geometry": {"coordinates":[-4.5224900246,36.7190055847],"type":"Point"}
}