{
  "type": "Feature",
  "properties": {
    "addr:full":"Avda Constitucion (de La), 113 Poligono Industrial Monte Boyal Toledo 45950",
    "addr:housenumber":"113",
    "addr:postcode":"45950",
    "addr:street":"Avda Constitucion De La;Industrial",
    "iso:country":"ES",
    "sg:address":"Avda Constitucion (de La), 113",
    "sg:city":"Poligono Industrial Monte Boyal",
    "sg:orig_category":"Transportes Por Carretera: Lotes Completos, Mercanc\u00cdas Diversas",
    "sg:phone":"+34 918 17 02 43",
    "sg:postcode":"45950",
    "sg:province":"Toledo",
    "sg:website":"www.planific.com",
    "wof:name":"Planific S.a.",
    "wof:placetype":"venue"
},
  "geometry": {"coordinates":[-4.0531868935,40.2130241394],"type":"Point"}
}