{
  "type": "Feature",
  "properties": {
    "addr:full":"Plaz San Nicolas, 3 Valencia Valencia 46001",
    "addr:postcode":"46001",
    "addr:street":"Plaz",
    "iso:country":"ES",
    "sg:address":"Plaz San Nicolas, 3",
    "sg:city":"Valencia",
    "sg:classifiers":[
        {
            "category":"Arts & Performance",
            "subcategory":"Art Gallery",
            "type":"Entertainment"
        }
    ],
    "sg:phone":"+34 963 92 42 38",
    "sg:postcode":"46001",
    "sg:province":"Valencia",
    "sg:tags":[
        "arte",
        "de",
        "galer\u00cdas"
    ],
    "sg:website":"www.galerianadir.com",
    "wof:name":"Guillen Orts Rosa",
    "wof:placetype":"venue"
},
  "geometry": {"coordinates":[-0.3793140054,39.4757881165],"type":"Point"}
}