{
  "type": "Feature",
  "properties": {
    "addr:full":"Carrer de Abell, 22 Canet Mar Barcelona 08360",
    "addr:housenumber":"22",
    "addr:postcode":"08360",
    "addr:street":"Carrer De Abell",
    "iso:country":"ES",
    "sg:address":"Carrer de Abell, 22",
    "sg:city":"Canet Mar",
    "sg:orig_category":"M\u00c9dicos: Neurolog\u00cda",
    "sg:phone":"+34 937 94 14 96",
    "sg:postcode":"08360",
    "sg:province":"Barcelona",
    "wof:name":"Titus Alvareda Felix",
    "wof:placetype":"venue"
},
  "geometry": {"coordinates":[2.5820600986,41.591053009],"type":"Point"}
}