{
  "type": "Feature",
  "properties": {
    "addr:full":"Poli Leones, S/n Pinseque Zaragoza 50298",
    "addr:housenumber":"s / n",
    "addr:postcode":"50298",
    "iso:country":"ES",
    "sg:address":"Poli Leones, S/n",
    "sg:city":"Pinseque",
    "sg:orig_category":"Instalaci\u00d3n, Reparaci\u00d3n De Ascensores Y Montacargas",
    "sg:phone":"+34 976 61 73 97",
    "sg:postcode":"50298",
    "sg:province":"Zaragoza",
    "wof:name":"Ascensores Asgar S.l.",
    "wof:placetype":"venue"
},
  "geometry": {"coordinates":[-1.0873551369,41.7256584167],"type":"Point"}
}