{
  "type": "Feature",
  "properties": {
    "addr:full":"Calle de Felipe Asenjo, 24 Fuenlabrada Madrid 28947",
    "addr:housenumber":"24",
    "addr:postcode":"28947",
    "addr:street":"Calle De Felipe Asenjo",
    "iso:country":"ES",
    "sg:address":"Calle de Felipe Asenjo, 24",
    "sg:city":"Fuenlabrada",
    "sg:orig_category":"Planchado",
    "sg:phone":"+34 916 21 44 28",
    "sg:postcode":"28947",
    "sg:province":"Madrid",
    "wof:name":"Sanchez Rivera Juan Jose",
    "wof:placetype":"venue"
},
  "geometry": {"coordinates":[-3.7441940308,40.2630767822],"type":"Point"}
}