{
  "type": "Feature",
  "properties": {
    "addr:full":"Crtj Cortijo El Vinculo, S/n Roquetas Mar Almer\u00eda 04740",
    "addr:housenumber":"s",
    "addr:postcode":"04740",
    "addr:street":"/ N Roquetas Mar Almeri\u0301A",
    "iso:country":"ES",
    "sg:address":"Crtj Cortijo El Vinculo, S/n",
    "sg:city":"Roquetas Mar",
    "sg:orig_category":"Material Y Suministros Para Horticultura, Arboricultura",
    "sg:phone":"+34 950 32 83 57",
    "sg:postcode":"04740",
    "sg:province":"Almer\u00eda",
    "wof:name":"Hortifilm S.l.",
    "wof:placetype":"venue"
},
  "geometry": {"coordinates":[-2.6124989986,36.7638435364],"type":"Point"}
}