{
  "type": "Feature",
  "properties": {
    "iso:country":"ES",
    "sg:address":"Avda Napoles, 58",
    "sg:city":"Eurovillas-las Villas",
    "sg:orig_category":"Impuestos, Tesoro P\u00dablico",
    "sg:phone":"+34 918 73 54 83",
    "sg:postcode":"28514",
    "sg:province":"Madrid",
    "wof:name":"Gabinete De Tasaciones Villareal S.l.",
    "wof:placetype":"venue"
},
  "geometry": {"coordinates":[-3.2538459301,40.3540039062],"type":"Point"}
}