{
  "type": "Feature",
  "properties": {
    "iso:country":"ES",
    "sg:address":"Calle de Victor Fragoso Del Toro, 53",
    "sg:city":"Villalobon",
    "sg:orig_category":"Reposter\u00cdas",
    "sg:phone":"+34 979 76 51 35",
    "sg:postcode":"34191",
    "sg:province":"Palencia",
    "wof:name":"Sanchez Perez Jose Luis Paulino",
    "wof:placetype":"venue"
},
  "geometry": {"coordinates":[-4.7797989845,41.9148826599],"type":"Point"}
}