{
  "type": "Feature",
  "properties": {
    "addr:full":"Av Matadepera, 138 Sabadell Barcelona 08207",
    "addr:housenumber":"138",
    "addr:postcode":"08207",
    "addr:street":"Av Matadepera",
    "iso:country":"ES",
    "sg:address":"Av Matadepera, 138",
    "sg:city":"Sabadell",
    "sg:orig_category":"Cajas De Ahorro",
    "sg:phone":"+34 937 24 33 55",
    "sg:postcode":"08207",
    "sg:province":"Barcelona",
    "sg:website":"www.caixagirona.es",
    "wof:name":"Caixa De Girona",
    "wof:placetype":"venue"
},
  "geometry": {"coordinates":[2.0882260799,41.5676002502],"type":"Point"}
}