{
  "type": "Feature",
  "properties": {
    "iso:country":"ES",
    "sg:address":"Afueras, S/n",
    "sg:city":"Cuacos Yuste",
    "sg:orig_category":"Molduras, Junquillos, Listones Y Molduras Perforadas",
    "sg:phone":"+34 927 17 20 42",
    "sg:postcode":"10430",
    "sg:province":"C\u00e1ceres",
    "wof:name":"Pinadero Perez Gregorio",
    "wof:placetype":"venue"
},
  "geometry": {"coordinates":[-5.7244129181,40.1061248779],"type":"Point"}
}