{
  "type": "Feature",
  "properties": {
    "addr:full":"Carrer de Tarragona, 141 Barcelona Barcelona 08015",
    "addr:housenumber":"141",
    "addr:postcode":"08015",
    "addr:street":"Carrer De Tarragona",
    "iso:country":"ES",
    "sg:address":"Carrer de Tarragona, 141",
    "sg:city":"Barcelona",
    "sg:orig_category":"Aparcamientos (infraestructuras, Accesorios)",
    "sg:phone":"+34 934 26 59 54",
    "sg:postcode":"08015",
    "sg:province":"Barcelona",
    "wof:name":"Josel, S.l.",
    "wof:placetype":"venue"
},
  "geometry": {"coordinates":[2.1458799839,41.3781013489],"type":"Point"}
}