{
  "type": "Feature",
  "properties": {
    "addr:full":"Plaz Castillo (el), 13 Andujar Ja\u00e9n 23740",
    "addr:postcode":"23740",
    "addr:street":"Plaz;El;Jae\u0301N",
    "iso:country":"ES",
    "sg:address":"Plaz Castillo (el), 13",
    "sg:city":"Andujar",
    "sg:orig_category":"Heladeros",
    "sg:phone":"+34 953 50 04 93",
    "sg:postcode":"23740",
    "sg:province":"Ja\u00e9n",
    "wof:name":"Duran Carmona Alfonso",
    "wof:placetype":"venue"
},
  "geometry": {"coordinates":[-4.0569849014,38.0395851135],"type":"Point"}
}