{
  "type": "Feature",
  "properties": {
    "iso:country":"ES",
    "sg:address":"Av Xixo, S/n",
    "sg:city":"Benidorm",
    "sg:orig_category":"Asesor\u00cdas Y Estudios Financieros",
    "sg:phone":"+34 965 85 94 93",
    "sg:postcode":"03500",
    "sg:province":"Alicante",
    "wof:name":"Salinas Gonzalez Jose",
    "wof:placetype":"venue"
},
  "geometry": {"coordinates":[-0.1437090039,38.5396690369],"type":"Point"}
}