{
  "type": "Feature",
  "properties": {
    "addr:full":"Avda Murcia, S/n Cabezo Torres Murcia 30110",
    "addr:housenumber":"s / n",
    "addr:postcode":"30110",
    "addr:street":"Avda Murcia;Cabezo",
    "iso:country":"ES",
    "sg:address":"Avda Murcia, S/n",
    "sg:city":"Cabezo Torres",
    "sg:orig_category":"Carnicer\u00cdas, Carnicer\u00cdas",
    "sg:phone":"+34 968 83 29 51",
    "sg:postcode":"30110",
    "sg:province":"Murcia",
    "wof:name":"Molina Laveda Antonio",
    "wof:placetype":"venue"
},
  "geometry": {"coordinates":[-1.1301239729,38.0205764771],"type":"Point"}
}