{
  "type": "Feature",
  "properties": {
    "iso:country":"ES",
    "sg:address":"Calle de Pedro Toro, S/n",
    "sg:city":"Santa Cristina De La Polvorosa",
    "sg:orig_category":"Abogados",
    "sg:phone":"+34 980 63 06 75",
    "sg:postcode":"49620",
    "sg:province":"Zamora",
    "wof:name":"Ayuntamiento Juzgado De Paz",
    "wof:placetype":"venue"
},
  "geometry": {"coordinates":[-5.7159466743,42.0007667542],"type":"Point"}
}