{
  "type": "Feature",
  "properties": {
    "addr:full":"Calle de Jose M. Salaberria, 51 Donostia-san Sebastian Guip\u00f9zcoa 20010",
    "addr:housenumber":"51",
    "addr:postcode":"20010",
    "addr:street":"Calle De Jose M. Salaberria",
    "iso:country":"ES",
    "sg:address":"Calle de Jose M. Salaberria, 51",
    "sg:city":"Donostia-san Sebastian",
    "sg:orig_category":"M\u00c9dicos: Oftalmolog\u00cda",
    "sg:phone":"+34 943 45 15 83",
    "sg:postcode":"20010",
    "sg:province":"Guip\u00f9zcoa",
    "wof:name":"Santamarina Rodero Sebastian",
    "wof:placetype":"venue"
},
  "geometry": {"coordinates":[-1.9799660444,43.3027381897],"type":"Point"}
}