{
  "type": "Feature",
  "properties": {
    "iso:country":"ES",
    "sg:address":"Carrer de Bacardi, 31",
    "sg:city":"Barcelona",
    "sg:orig_category":"Molduras, Junquillos, Listones Y Molduras Perforadas",
    "sg:phone":"+34 934 22 71 63",
    "sg:postcode":"08028",
    "sg:province":"Barcelona",
    "wof:name":"Meson 2010 S.l.",
    "wof:placetype":"venue"
},
  "geometry": {"coordinates":[2.1288371086,41.3731040955],"type":"Point"}
}