{
  "type": "Feature",
  "properties": {
    "iso:country":"ES",
    "sg:address":"Calle de San Jose, S/n",
    "sg:city":"Alcorcon",
    "sg:orig_category":"Frutas Y Legumbres Secas (al Por Mayor)",
    "sg:phone":"+34 916 11 16 20",
    "sg:postcode":"28921",
    "sg:province":"Madrid",
    "wof:name":"Perera Berrio Juan",
    "wof:placetype":"venue"
},
  "geometry": {"coordinates":[-3.8251290321,40.3509559631],"type":"Point"}
}