{
  "type": "Feature",
  "properties": {
    "addr:full":"Pol Ind Guadalquivir, S/n Andujar Ja\u00e9n 23740",
    "addr:postcode":"23740",
    "addr:street":"Ind Guadalquivir S / N;Jae\u0301N",
    "iso:country":"ES",
    "sg:address":"Pol Ind Guadalquivir, S/n",
    "sg:city":"Andujar",
    "sg:orig_category":"Cerrajer\u00cda, Ferrallista",
    "sg:phone":"+34 953 50 75 53",
    "sg:postcode":"23740",
    "sg:province":"Ja\u00e9n",
    "wof:name":"Luis Iglesias Olmo Y Dos Mas Cb",
    "wof:placetype":"venue"
},
  "geometry": {"coordinates":[-4.057518959,38.0386962891],"type":"Point"}
}