{
  "type": "Feature",
  "properties": {
    "addr:full":"Pase Castellana, 179 Madrid Madrid 28046",
    "addr:housenumber":"179",
    "addr:postcode":"28046",
    "addr:street":"Castellana",
    "iso:country":"ES",
    "sg:address":"Pase Castellana, 179",
    "sg:city":"Madrid",
    "sg:orig_category":"Controles De Edificaci\u00d3n (construcci\u00d3n, Seguridad)",
    "sg:phone":"+34 915 70 70 44",
    "sg:postcode":"28046",
    "sg:province":"Madrid",
    "wof:name":"Gonzalez Olano Guillermo",
    "wof:placetype":"venue"
},
  "geometry": {"coordinates":[-3.6900355816,40.4631881714],"type":"Point"}
}