{
  "type": "Feature",
  "properties": {
    "addr:full":"Calle de Garlopa, 4 Sevilla Sevilla 41020",
    "addr:housenumber":"4",
    "addr:postcode":"41020",
    "addr:street":"Calle De Garlopa",
    "iso:country":"ES",
    "sg:address":"Calle de Garlopa, 4",
    "sg:city":"Sevilla",
    "sg:orig_category":"Molduras, Junquillos, Listones Y Molduras Perforadas",
    "sg:phone":"+34 954 25 00 17",
    "sg:postcode":"41020",
    "sg:province":"Sevilla",
    "wof:name":"Placimi Importaciones S.l.",
    "wof:placetype":"venue"
},
  "geometry": {"coordinates":[-5.9333291054,37.4165763855],"type":"Point"}
}