{
  "type": "Feature",
  "properties": {
    "addr:full":"Calle de Espronceda, 16 Madrid Madrid 28003",
    "addr:housenumber":"16",
    "addr:postcode":"madrid;28003",
    "addr:street":"Calle De Espronceda",
    "iso:country":"ES",
    "sg:address":"Calle de Espronceda, 16",
    "sg:city":"Madrid",
    "sg:orig_category":"Agencias De Viajes",
    "sg:phone":"+34 914 42 32 83",
    "sg:postcode":"28003",
    "sg:province":"Madrid",
    "sg:website":"www.amadisexpress.net",
    "wof:name":"Viajes Amadis Express S. A.",
    "wof:placetype":"venue"
},
  "geometry": {"coordinates":[-3.6978449821,40.4405174255],"type":"Point"}
}