{
  "type": "Feature",
  "properties": {
    "addr:full":"Calle de Foso (del), 82 Aranjuez Madrid 28300",
    "addr:housenumber":"82",
    "addr:postcode":"28300",
    "addr:street":"Calle De Foso Del",
    "iso:country":"ES",
    "sg:address":"Calle de Foso (del), 82",
    "sg:city":"Aranjuez",
    "sg:orig_category":"Farmacias",
    "sg:phone":"+34 918 91 08 13",
    "sg:postcode":"28300",
    "sg:province":"Madrid",
    "wof:name":"Sanchez Mentrida C.b.",
    "wof:placetype":"venue"
},
  "geometry": {"coordinates":[-3.598238945,40.0324668884],"type":"Point"}
}