{
  "type": "Feature",
  "properties": {
    "addr:full":"Calle de Martinez Simancas, 1 Toledo Toledo 45005",
    "addr:housenumber":"1",
    "addr:postcode":"45005",
    "addr:street":"Calle De Martinez Simancas",
    "iso:country":"ES",
    "sg:address":"Calle de Martinez Simancas, 1",
    "sg:city":"Toledo",
    "sg:orig_category":"Sociedades, Compa\u00d1\u00cdas Aseguradoras",
    "sg:phone":"+34 925 22 11 42",
    "sg:postcode":"45005",
    "sg:province":"Toledo",
    "wof:name":"Limite S. A.",
    "wof:placetype":"venue"
},
  "geometry": {"coordinates":[-4.0374960899,39.8719291687],"type":"Point"}
}