{
  "type": "Feature",
  "properties": {
    "addr:full":"Calle de Cruz De La, 2 Fuengirola M\u00e1laga 29640",
    "addr:housenumber":"2",
    "addr:postcode":"29640",
    "addr:street":"Calle De Cruz De La;Ma\u0301Laga",
    "iso:country":"ES",
    "sg:address":"Calle de Cruz De La, 2",
    "sg:city":"Fuengirola",
    "sg:orig_category":"Tintorer\u00cdas, Limpieza En Seco",
    "sg:phone":"+34 952 47 74 48",
    "sg:postcode":"29640",
    "sg:province":"M\u00e1laga",
    "wof:name":"Eventos Tercer Milenio S.l.",
    "wof:placetype":"venue"
},
  "geometry": {"coordinates":[-4.6225252151,36.5388412476],"type":"Point"}
}