{
  "type": "Feature",
  "properties": {
    "addr:full":"Calle de Calanda, 21 Madrid Madrid 28043",
    "addr:housenumber":"21",
    "addr:postcode":"madrid;28043",
    "addr:street":"Calle De Calanda",
    "iso:country":"ES",
    "sg:address":"Calle de Calanda, 21",
    "sg:city":"Madrid",
    "sg:orig_category":"Art\u00cdculos De Regalo (al Por Menor)",
    "sg:phone":"+34 917 59 07 28",
    "sg:postcode":"28043",
    "sg:province":"Madrid",
    "wof:name":"Crisan Decor S.l.",
    "wof:placetype":"venue"
},
  "geometry": {"coordinates":[-3.6431910992,40.4621696472],"type":"Point"}
}