{
  "type": "Feature",
  "properties": {
    "iso:country":"ES",
    "sg:address":"Ctra. Soria Plasencia, Km. 0089,0",
    "sg:city":"La Colilla",
    "sg:orig_category":"Perfumer\u00cda, Art\u00cdculos De Ba\u00d1o (fabricaci\u00d3n, Al Por Mayor)",
    "sg:phone":"+34 920 26 97 60",
    "sg:postcode":"05192",
    "sg:province":"\u00c1vila",
    "wof:name":"Almacenes Pinto S. A.",
    "wof:placetype":"venue"
},
  "geometry": {"coordinates":[-4.7446832657,40.6403465271],"type":"Point"}
}