{
  "type": "Feature",
  "properties": {
    "addr:full":"Avda Mariano Ballester, 2 Alcazares Murcia 30710",
    "addr:housenumber":"2",
    "addr:postcode":"30710",
    "addr:street":"Avda Mariano Ballester",
    "iso:country":"ES",
    "sg:address":"Avda Mariano Ballester, 2",
    "sg:city":"Alcazares",
    "sg:orig_category":"Cooperativas Agr\u00cdcolas",
    "sg:phone":"+34 968 58 27 19",
    "sg:postcode":"30710",
    "sg:province":"Murcia",
    "wof:name":"Ibolele Eventos S.l.",
    "wof:placetype":"venue"
},
  "geometry": {"coordinates":[-0.8402889967,37.7543182373],"type":"Point"}
}