{
  "type": "Feature",
  "properties": {
    "iso:country":"ES",
    "sg:address":"Carrer de Arizala, 29",
    "sg:city":"Barcelona",
    "sg:orig_category":"Art\u00cdculos De Decoraci\u00d3n",
    "sg:phone":"+34 934 48 53 81",
    "sg:postcode":"08028",
    "sg:province":"Barcelona",
    "wof:name":"Vera & Guerrero S.l.",
    "wof:placetype":"venue"
},
  "geometry": {"coordinates":[2.1242940426,41.3772468567],"type":"Point"}
}