{
  "type": "Feature",
  "properties": {
    "iso:country":"ES",
    "sg:address":"Calle de Juan Sebastian Elcano, 41",
    "sg:city":"Albacete",
    "sg:orig_category":"Motocicletas (agentes, Concesionarios)",
    "sg:phone":"+34 967 22 23 82",
    "sg:postcode":"02005",
    "sg:province":"Albacete",
    "wof:name":"Andujar Del Hoyo Vicente",
    "wof:placetype":"venue"
},
  "geometry": {"coordinates":[-1.8619265556,38.998249054],"type":"Point"}
}