{
  "type": "Feature",
  "properties": {
    "addr:full":"Rbla Joaquim Ruyra, 46 Blanes Girona 17300",
    "addr:housenumber":"46",
    "addr:postcode":"17300",
    "addr:street":"Rbla Joaquim Ruyra",
    "iso:country":"ES",
    "sg:address":"Rbla Joaquim Ruyra, 46",
    "sg:city":"Blanes",
    "sg:orig_category":"Contenedores Para Transporte De Mercanc\u00cdas",
    "sg:phone":"+34 972 35 17 64",
    "sg:postcode":"17300",
    "sg:province":"Girona",
    "wof:name":"Contenidors Costa Brava S.l.",
    "wof:placetype":"venue"
},
  "geometry": {"coordinates":[2.7900729179,41.6733856201],"type":"Point"}
}