{
  "type": "Feature",
  "properties": {
    "addr:full":"Calle de Leon Y Castillo, 242 Palmas De Gran Canaria Las Palmas 35005",
    "addr:housenumber":"242",
    "addr:postcode":"35005",
    "addr:street":"Calle De Leon Y Castillo",
    "iso:country":"ES",
    "sg:address":"Calle de Leon Y Castillo, 242",
    "sg:city":"Palmas De Gran Canaria",
    "sg:orig_category":"Arquitectos",
    "sg:phone":"+34 928 29 21 61",
    "sg:postcode":"35005",
    "sg:province":"Las Palmas",
    "wof:name":"Gomez Gutierrez Alfonso",
    "wof:placetype":"venue"
},
  "geometry": {"coordinates":[-15.4275283813,28.1232662201],"type":"Point"}
}