{
  "type": "Feature",
  "properties": {
    "addr:full":"Ptda Teularet, Del, S/n Tavernes Valldigna Valencia 46760",
    "addr:housenumber":"/ n",
    "addr:postcode":"46760",
    "addr:street":"Ptda Teularet Del S",
    "iso:country":"ES",
    "sg:address":"Ptda Teularet, Del, S/n",
    "sg:city":"Tavernes Valldigna",
    "sg:orig_category":"Molduras, Junquillos, Listones Y Molduras Perforadas",
    "sg:phone":"+34 962 82 11 38",
    "sg:postcode":"46760",
    "sg:province":"Valencia",
    "wof:name":"Grau Albero Victor",
    "wof:placetype":"venue"
},
  "geometry": {"coordinates":[-0.2594090104,39.0749702454],"type":"Point"}
}