{
  "type": "Feature",
  "properties": {
    "addr:full":"Avda Andalucia, 47 Luisiana Sevilla 41430",
    "addr:housenumber":"47",
    "addr:postcode":"41430",
    "addr:street":"Avda Andalucia",
    "iso:country":"ES",
    "sg:address":"Avda Andalucia, 47",
    "sg:city":"Luisiana",
    "sg:orig_category":"Cajas Para Embalar",
    "sg:phone":"+34 955 90 73 53",
    "sg:postcode":"41430",
    "sg:province":"Sevilla",
    "wof:name":"Caja Rural Del Sur Sociedad Cooperativa",
    "wof:placetype":"venue"
},
  "geometry": {"coordinates":[-5.2481908798,37.5259094238],"type":"Point"}
}