{
  "type": "Feature",
  "properties": {
    "iso:country":"ES",
    "sg:address":"Casa N. Del Rincon, S/n",
    "sg:city":"Nava De Abajo",
    "sg:orig_category":"Asesor\u00cda Sobre Comunicaci\u00d3n De Empresas",
    "sg:phone":"+34 967 58 41 37",
    "sg:postcode":"02142",
    "sg:province":"Albacete",
    "wof:name":"Hacienda El Fontanar S.l.",
    "wof:placetype":"venue"
},
  "geometry": {"coordinates":[-1.9041090012,38.637134552],"type":"Point"}
}