{
  "type": "Feature",
  "properties": {
    "addr:full":"Pol Ind Estepar, 6 Castello Plana Castell\u00f3n 12005",
    "addr:housenumber":"6",
    "addr:postcode":"12005",
    "addr:street":"Estepar;Castello\u0301N",
    "iso:country":"ES",
    "sg:address":"Pol Ind Estepar, 6",
    "sg:city":"Castello Plana",
    "sg:orig_category":"Cer\u00c1micas: Material Y Suministros",
    "sg:phone":"+34 964 24 45 20",
    "sg:postcode":"12005",
    "sg:province":"Castell\u00f3n",
    "wof:name":"Tecno-tauce S.l.",
    "wof:placetype":"venue"
},
  "geometry": {"coordinates":[-0.0570270009,39.9575424194],"type":"Point"}
}