{
  "type": "Feature",
  "properties": {
    "iso:country":"ES",
    "sg:address":"Avda Ferrocarril, 3",
    "sg:city":"Ponferrada",
    "sg:orig_category":"Estancos",
    "sg:phone":"+34 987 40 24 26",
    "sg:postcode":"24400",
    "sg:province":"Le\u00f3n",
    "wof:name":"Borge Aparicio Maria Antonia",
    "wof:placetype":"venue"
},
  "geometry": {"coordinates":[-6.6043782234,42.5466156006],"type":"Point"}
}