{
  "type": "Feature",
  "properties": {
    "iso:country":"ES",
    "sg:address":"Carrer de Costa I Deu, 69",
    "sg:city":"Sabadell",
    "sg:orig_category":"Edici\u00d3n De Diarios, Revistas, Boletines",
    "sg:phone":"+34 937 12 26 73",
    "sg:postcode":"08205",
    "sg:province":"Barcelona",
    "wof:name":"Distribucion Y Ediciones Vilafranca S.l.",
    "wof:placetype":"venue"
},
  "geometry": {"coordinates":[2.0988719463,41.5302429199],"type":"Point"}
}