{
  "type": "Feature",
  "properties": {
    "iso:country":"ES",
    "sg:address":"Calle de Ripolles, S/n",
    "sg:city":"Albalate Arzobispo",
    "sg:classifiers":[
        {
            "category":"Casinos & Gambling",
            "type":"Entertainment"
        }
    ],
    "sg:phone":"+34 978 81 20 58",
    "sg:postcode":"44540",
    "sg:province":"Teruel",
    "sg:tags":[
        "locale",
        "de",
        "juego"
    ],
    "wof:name":"Casino Recreativo",
    "wof:placetype":"venue"
},
  "geometry": {"coordinates":[-0.5114049911,41.1214256287],"type":"Point"}
}