{
  "type": "Feature",
  "properties": {
    "iso:country":"ES",
    "sg:address":"Avda Diputacion, S/n",
    "sg:city":"Calpe",
    "sg:orig_category":"Zapatos (al Por Menor)",
    "sg:phone":"+34 965 83 83 50",
    "sg:postcode":"03710",
    "sg:province":"Alicante",
    "wof:name":"Ros Garcia Salvador",
    "wof:placetype":"venue"
},
  "geometry": {"coordinates":[0.0416899994,38.6459236145],"type":"Point"}
}