{
  "type": "Feature",
  "properties": {
    "addr:full":"Carr Federico Ribo, 4 Peramola Lleida 25790",
    "addr:housenumber":"4",
    "addr:postcode":"25790",
    "addr:street":"Carr Federico Ribo",
    "iso:country":"ES",
    "sg:address":"Carr Federico Ribo, 4",
    "sg:city":"Peramola",
    "sg:orig_category":"Cajas De Ahorro",
    "sg:phone":"+34 973 47 03 11",
    "sg:postcode":"25790",
    "sg:province":"Lleida",
    "wof:name":"Caixa D'estalvis De Catalunya",
    "wof:placetype":"venue"
},
  "geometry": {"coordinates":[1.2680109739,42.0573348999],"type":"Point"}
}