{
  "type": "Feature",
  "properties": {
    "iso:country":"ES",
    "sg:address":"Rava Santa Anna, 9",
    "sg:city":"Reus",
    "sg:orig_category":"Ropa Para Se\u00d1oras (al Por Menor)",
    "sg:phone":"+34 977 12 60 00",
    "sg:postcode":"43201",
    "sg:province":"Tarragona",
    "wof:name":"Vaiciulyte  Vilija",
    "wof:placetype":"venue"
},
  "geometry": {"coordinates":[1.1093209982,41.156124115],"type":"Point"}
}