{
  "type": "Feature",
  "properties": {
    "addr:full":"Pio Xi, 18 Trobajo Camino Le\u00f3n 24010",
    "addr:housenumber":"18",
    "addr:postcode":"24010",
    "addr:street":"Pio Xi;Camino Leo\u0301N",
    "iso:country":"ES",
    "sg:address":"Pio Xi, 18",
    "sg:city":"Trobajo Camino",
    "sg:orig_category":"Reposter\u00cdas",
    "sg:phone":"+34 987 80 14 46",
    "sg:postcode":"24010",
    "sg:province":"Le\u00f3n",
    "wof:name":"Fernandez Suarez Carlos-tomas",
    "wof:placetype":"venue"
},
  "geometry": {"coordinates":[-5.5716600418,42.5981292725],"type":"Point"}
}