{
  "type": "Feature",
  "properties": {
    "iso:country":"ES",
    "sg:address":"Carrer de Sunyer, 9",
    "sg:city":"Alcanar",
    "sg:orig_category":"Delegados, Agentes De Tr\u00c1nsito, Auxiliares De Transporte Internacional",
    "sg:phone":"+34 977 73 04 11",
    "sg:postcode":"43530",
    "sg:province":"Tarragona",
    "wof:name":"Sersatrans S.l.",
    "wof:placetype":"venue"
},
  "geometry": {"coordinates":[0.4815450013,40.5424613953],"type":"Point"}
}