{
  "type": "Feature",
  "properties": {
    "iso:country":"ES",
    "sg:address":"Plaz Cardenal Ferriz, 9",
    "sg:city":"Cocentaina",
    "sg:orig_category":"Carnicer\u00cdas, Carnicer\u00cdas",
    "sg:phone":"+34 966 50 09 92",
    "sg:postcode":"03820",
    "sg:province":"Alicante",
    "wof:name":"Abad Martinez Amelia",
    "wof:placetype":"venue"
},
  "geometry": {"coordinates":[-0.440804,38.725517],"type":"Point"}
}