{
  "type": "Feature",
  "properties": {
    "iso:country":"ES",
    "sg:address":"Carrer de Aribau, 230",
    "sg:city":"Barcelona",
    "sg:orig_category":"Teatros Y Salas De Espect\u00c1culos",
    "sg:phone":"+34 932 00 35 13",
    "sg:postcode":"08006",
    "sg:province":"Barcelona",
    "wof:name":"Gablama S.a.",
    "wof:placetype":"venue"
},
  "geometry": {"coordinates":[2.1503770351,41.3953361511],"type":"Point"}
}