{
  "type": "Feature",
  "properties": {
    "iso:country":"ES",
    "sg:address":"Carr Son Boi, De, 1",
    "sg:city":"Consell",
    "sg:orig_category":"Forjas Y Altos Hornos",
    "sg:phone":"+34 971 14 21 29",
    "sg:postcode":"07330",
    "sg:province":"Islas Baleares",
    "wof:name":"Deya Company Miguel",
    "wof:placetype":"venue"
},
  "geometry": {"coordinates":[2.8202500343,39.6667709351],"type":"Point"}
}