{
  "type": "Feature",
  "properties": {
    "addr:full":"Rua Leopoldo Calvo Sotelo, 65 Monforte De Lemos Lugo 27400",
    "addr:housenumber":"65",
    "addr:postcode":"27400",
    "addr:street":"Rua Leopoldo Calvo Sotelo",
    "iso:country":"ES",
    "sg:address":"Rua Leopoldo Calvo Sotelo, 65",
    "sg:city":"Monforte De Lemos",
    "sg:orig_category":"Ense\u00d1anza: Idiomas",
    "sg:phone":"+34 982 41 03 00",
    "sg:postcode":"27400",
    "sg:province":"Lugo",
    "wof:name":"Escuela Oficial De Idiomas De Monforte De Lemos",
    "wof:placetype":"venue"
},
  "geometry": {"coordinates":[-7.504817009,42.5278396606],"type":"Point"}
}