{
  "type": "Feature",
  "properties": {
    "addr:full":"Carrer de Giralda, 8 Castelldefels Barcelona 08860",
    "addr:housenumber":"8",
    "addr:postcode":"08860",
    "addr:street":"Carrer De Giralda",
    "iso:country":"ES",
    "sg:address":"Carrer de Giralda, 8",
    "sg:city":"Castelldefels",
    "sg:orig_category":"Asociaciones, Organismos Culturales Y Socioeducativos",
    "sg:phone":"+34 936 34 21 11",
    "sg:postcode":"08860",
    "sg:province":"Barcelona",
    "wof:name":"Ajuntament De Castelldefels",
    "wof:placetype":"venue"
},
  "geometry": {"coordinates":[1.9766546488,41.2894744873],"type":"Point"}
}