{
  "type": "Feature",
  "properties": {
    "iso:country":"ES",
    "sg:address":"Calle de Berlin, 12",
    "sg:city":"Torreciega",
    "sg:orig_category":"Negocio De Madera",
    "sg:phone":"+34 968 32 40 32",
    "sg:postcode":"30392",
    "sg:province":"Murcia",
    "wof:name":"Doorking S.l",
    "wof:placetype":"venue"
},
  "geometry": {"coordinates":[-0.9630479813,37.625957489],"type":"Point"}
}