{
  "type": "Feature",
  "properties": {
    "iso:country":"ES",
    "sg:address":"Rua Carmen, 2",
    "sg:city":"Negreira",
    "sg:orig_category":"Caf\u00c9s, Bares, Cervecer\u00cdas",
    "sg:phone":"+34 981 88 16 52",
    "sg:postcode":"15830",
    "sg:province":"La Coru\u00f1a",
    "wof:name":"Barbeira Negreira Nelida",
    "wof:placetype":"venue"
},
  "geometry": {"coordinates":[-8.7354192734,42.9100456238],"type":"Point"}
}