{
  "type": "Feature",
  "properties": {
    "addr:full":"Calle de Eskoriatza, S/n Vitoria-gasteiz \u00c1lava 01013",
    "addr:housenumber":"s / n",
    "addr:postcode":"01013",
    "addr:street":"Calle De Eskoriatza",
    "iso:country":"ES",
    "sg:address":"Calle de Eskoriatza, S/n",
    "sg:city":"Vitoria-gasteiz",
    "sg:orig_category":"Sindicatos De Trabajadores",
    "sg:phone":"+34 945 26 34 94",
    "sg:postcode":"01013",
    "sg:province":"\u00c1lava",
    "wof:name":"Sindicato Unificado De Policia-sup",
    "wof:placetype":"venue"
},
  "geometry": {"coordinates":[-2.6562490463,42.8576202393],"type":"Point"}
}