{
  "type": "Feature",
  "properties": {
    "iso:country":"ES",
    "sg:address":"Calle de 25 De Abril, 33",
    "sg:city":"Torrent",
    "sg:orig_category":"Empresas De Pintura Y Revestimientos",
    "sg:phone":"+34 961 55 39 42",
    "sg:postcode":"46900",
    "sg:province":"Valencia",
    "wof:name":"Aullana Gomez Enrique",
    "wof:placetype":"venue"
},
  "geometry": {"coordinates":[-0.4763033092,39.4344139099],"type":"Point"}
}