{
  "type": "Feature",
  "properties": {
    "iso:country":"ES",
    "sg:address":"Zelai Ondo Enparantza, 23",
    "sg:city":"Zarautz",
    "sg:orig_category":"Reposter\u00cdas",
    "sg:phone":"+34 943 13 39 74",
    "sg:postcode":"20800",
    "sg:province":"Guip\u00f9zcoa",
    "wof:name":"Mari Cruz Lopez Fernandez Y Otra C.b",
    "wof:placetype":"venue"
},
  "geometry": {"coordinates":[-2.168473959,43.2812385559],"type":"Point"}
}