{
  "type": "Feature",
  "properties": {
    "iso:country":"ES",
    "sg:address":"Cmno Pajarillas (de Las), 14",
    "sg:city":"Mostoles",
    "sg:orig_category":"Cerrajer\u00cda, Ferrallista",
    "sg:phone":"+34 916 14 49 16",
    "sg:postcode":"28935",
    "sg:province":"Madrid",
    "wof:name":"Del Barrio Serrano Miguel Angel",
    "wof:placetype":"venue"
},
  "geometry": {"coordinates":[-3.8953840733,40.3367500305],"type":"Point"}
}