{
  "type": "Feature",
  "properties": {
    "iso:country":"ES",
    "sg:address":"Calle de Conde De Torrepalma, 8",
    "sg:city":"Alcala Real",
    "sg:orig_category":"Contenedores (mercanc\u00cdas)",
    "sg:phone":"+34 953 58 18 23",
    "sg:postcode":"23680",
    "sg:province":"Ja\u00e9n",
    "wof:name":"Transportes Y Logistica Fuentes Cano Sl",
    "wof:placetype":"venue"
},
  "geometry": {"coordinates":[-3.9207239151,37.4572753906],"type":"Point"}
}