{
  "type": "Feature",
  "properties": {
    "addr:full":"Pla\u00c7 Pol Nadal I Mallol, 5 Port Selva Girona 17489",
    "addr:housenumber":"5",
    "addr:postcode":"17489",
    "addr:street":"Mallol",
    "iso:country":"ES",
    "sg:address":"Pla\u00c7 Pol Nadal I Mallol, 5",
    "sg:city":"Port Selva",
    "sg:orig_category":"Pescader\u00cdas (al Por Menor)",
    "sg:phone":"+34 972 38 70 54",
    "sg:postcode":"17489",
    "sg:province":"Girona",
    "wof:name":"Puigvert Pujaldon Maria Merced",
    "wof:placetype":"venue"
},
  "geometry": {"coordinates":[3.1865150928,42.3239517212],"type":"Point"}
}