{
  "type": "Feature",
  "properties": {
    "iso:country":"ES",
    "sg:address":"Sabande\u00f1os, 35",
    "sg:city":"Puerto Del Carmen",
    "sg:orig_category":"Asociaciones Humanitarias, De Cooperaci\u00d3n, De Acci\u00d3n Social",
    "sg:phone":"+34 928 51 55 41",
    "sg:postcode":"35510",
    "sg:province":"Las Palmas",
    "wof:name":"Branan, Michael John",
    "wof:placetype":"venue"
},
  "geometry": {"coordinates":[-13.6662998199,28.9243526459],"type":"Point"}
}