{
  "type": "Feature",
  "properties": {
    "iso:country":"ES",
    "sg:address":"Calle de Eskalantegi, 48",
    "sg:city":"Donostia-san Sebastian",
    "sg:orig_category":"Servicio De Salud",
    "sg:phone":"+34 943 52 08 28",
    "sg:postcode":"20017",
    "sg:province":"Guip\u00f9zcoa",
    "wof:name":"Idurre Elosegi Anton Y Otra C.b.",
    "wof:placetype":"venue"
},
  "geometry": {"coordinates":[-1.9189349413,43.3165817261],"type":"Point"}
}