{
  "type": "Feature",
  "properties": {
    "addr:full":"Carrer de Napols, 261 Barcelona Barcelona 08025",
    "addr:housenumber":"261",
    "addr:postcode":"08025",
    "addr:street":"Carrer De Napols",
    "iso:country":"ES",
    "sg:address":"Carrer de Napols, 261",
    "sg:city":"Barcelona",
    "sg:orig_category":"Papeler\u00cdas: Art\u00cdculos (al Por Mayor)",
    "sg:phone":"+34 934 57 11 00",
    "sg:postcode":"08025",
    "sg:province":"Barcelona",
    "wof:name":"Sarramia Rifa Joaquin",
    "wof:placetype":"venue"
},
  "geometry": {"coordinates":[2.1701691151,41.4021949768],"type":"Point"}
}