{
  "type": "Feature",
  "properties": {
    "addr:full":"Calle de Silos, 38 Alcala Guadaira Sevilla 41500",
    "addr:housenumber":"38",
    "addr:postcode":"41500",
    "addr:street":"Calle De Silos",
    "iso:country":"ES",
    "sg:address":"Calle de Silos, 38",
    "sg:city":"Alcala Guadaira",
    "sg:orig_category":"Abogados",
    "sg:phone":"+34 955 68 53 25",
    "sg:postcode":"41500",
    "sg:province":"Sevilla",
    "wof:name":"Gonzalez Rodriguez Andres",
    "wof:placetype":"venue"
},
  "geometry": {"coordinates":[-5.8481750488,37.3416023254],"type":"Point"}
}