{
  "type": "Feature",
  "properties": {
    "iso:country":"ES",
    "sg:address":"Avda Estacion (da), 19",
    "sg:city":"Barco",
    "sg:orig_category":"Promotores Constructores",
    "sg:phone":"+34 988 34 70 94",
    "sg:postcode":"32300",
    "sg:province":"Ourense",
    "wof:name":"Cdad De Propietraios De Rua Estacion 19-21",
    "wof:placetype":"venue"
},
  "geometry": {"coordinates":[-6.9855308533,42.4168624878],"type":"Point"}
}