{
  "type": "Feature",
  "properties": {
    "iso:country":"ES",
    "sg:address":"Calle de Lamiaco, 5",
    "sg:city":"Madrid",
    "sg:orig_category":"Negocio De Metales No Ferrosos",
    "sg:phone":"+34 913 07 78 78",
    "sg:postcode":"28023",
    "sg:province":"Madrid",
    "wof:name":"Valid S.a.",
    "wof:placetype":"venue"
},
  "geometry": {"coordinates":[-3.8204760551,40.4731750488],"type":"Point"}
}