{
  "type": "Feature",
  "properties": {
    "iso:country":"ES",
    "sg:address":"Calle de Siroco, S/n",
    "sg:city":"Dos Hermanas",
    "sg:orig_category":"Empresas De Carpinter\u00cda De Madera",
    "sg:phone":"+34 955 66 81 36",
    "sg:postcode":"41700",
    "sg:province":"Sevilla",
    "sg:website":"www.maderayarte.com",
    "wof:name":"Carpinteria Juan Jose S.l.",
    "wof:placetype":"venue"
},
  "geometry": {"coordinates":[-5.9222540855,37.2704391479],"type":"Point"}
}