{
  "type": "Feature",
  "properties": {
    "addr:full":"Plaz Ramon Y Cajal, 4 Brea De Aragon Zaragoza 50246",
    "addr:housenumber":"4",
    "addr:postcode":"50246",
    "addr:street":"Ramon Y Cajal",
    "iso:country":"ES",
    "sg:address":"Plaz Ramon Y Cajal, 4",
    "sg:city":"Brea De Aragon",
    "sg:orig_category":"Modistas",
    "sg:phone":"+34 976 82 40 03",
    "sg:postcode":"50246",
    "sg:province":"Zaragoza",
    "sg:website":"www.paruempresarial.com/calzadosgascon",
    "wof:name":"Dipagas S.l.l.",
    "wof:placetype":"venue"
},
  "geometry": {"coordinates":[-1.6027289629,41.5237083435],"type":"Point"}
}