{
  "type": "Feature",
  "properties": {
    "addr:full":"Carrer de Sant Fructuos, 12 Barcelona Barcelona 08004",
    "addr:housenumber":"12",
    "addr:postcode":"08004",
    "addr:street":"Carrer De Sant Fructuos",
    "iso:country":"ES",
    "sg:address":"Carrer de Sant Fructuos, 12",
    "sg:city":"Barcelona",
    "sg:orig_category":"Equipo De Refrigeraci\u00d3n Industrial",
    "sg:phone":"+34 934 23 98 57",
    "sg:postcode":"08004",
    "sg:province":"Barcelona",
    "wof:name":"Friger S. L.",
    "wof:placetype":"venue"
},
  "geometry": {"coordinates":[2.1477959156,41.3723907471],"type":"Point"}
}