{
  "type": "Feature",
  "properties": {
    "addr:full":"Carrer de Enten\u00c7a, 334 Barcelona Barcelona 08029",
    "addr:housenumber":"334",
    "addr:postcode":"08029",
    "addr:street":"Carrer De Entenc\u0327A",
    "iso:country":"ES",
    "sg:address":"Carrer de Enten\u00c7a, 334",
    "sg:city":"Barcelona",
    "sg:orig_category":"Organismos De Reclutamiento",
    "sg:phone":"+34 934 10 80 88",
    "sg:postcode":"08029",
    "sg:province":"Barcelona",
    "sg:website":"www.augere.es",
    "wof:name":"Brain Consultores S.a.",
    "wof:placetype":"venue"
},
  "geometry": {"coordinates":[2.1377420425,41.390422821],"type":"Point"}
}