{
  "type": "Feature",
  "properties": {
    "iso:country":"ES",
    "sg:address":"Calle de Fernando Pessoa, 5",
    "sg:city":"Madrid",
    "sg:orig_category":"Venta, Instalaci\u00d3n De Calefacci\u00d3n",
    "sg:phone":"+34 914 03 23 11",
    "sg:postcode":"28027",
    "sg:province":"Madrid",
    "wof:name":"Illescas Calor S. A.",
    "wof:placetype":"venue"
},
  "geometry": {"coordinates":[-3.653290987,40.4404678345],"type":"Point"}
}