{
  "type": "Feature",
  "properties": {
    "addr:full":"Rua Home Santo (do), 41 Santiago De Compostela La Coru\u00f1a 15703",
    "addr:housenumber":"41",
    "addr:postcode":"15703",
    "addr:street":"Rua Home Santo Do;Corun\u0303A",
    "iso:country":"ES",
    "sg:address":"Rua Home Santo (do), 41",
    "sg:city":"Santiago De Compostela",
    "sg:orig_category":"Cristaler\u00cdas",
    "sg:phone":"+34 981 58 62 20",
    "sg:postcode":"15703",
    "sg:province":"La Coru\u00f1a",
    "wof:name":"Novo Lopez Antonio",
    "wof:placetype":"venue"
},
  "geometry": {"coordinates":[-8.5341920853,42.8855476379],"type":"Point"}
}