{
  "type": "Feature",
  "properties": {
    "addr:full":"Av Aiguera, 1 Benidorm Alicante 03500",
    "addr:housenumber":"1",
    "addr:postcode":"03500",
    "addr:street":"Av Aiguera",
    "iso:country":"ES",
    "sg:address":"Av Aiguera, 1",
    "sg:city":"Benidorm",
    "sg:orig_category":"Aparcamientos (infraestructuras, Accesorios)",
    "sg:phone":"+34 965 86 64 93",
    "sg:postcode":"03500",
    "sg:province":"Alicante",
    "wof:name":"Aparcamientos Concertados S.a.",
    "wof:placetype":"venue"
},
  "geometry": {"coordinates":[-0.1300687045,38.5412712097],"type":"Point"}
}