{
  "type": "Feature",
  "properties": {
    "addr:full":"Carrer de Bogatell, 2 S. Adria Besos Barcelona 08930",
    "addr:housenumber":"2",
    "addr:postcode":"08930",
    "addr:street":"Carrer De Bogatell;Barcelona",
    "iso:country":"ES",
    "sg:address":"Carrer de Bogatell, 2",
    "sg:city":"S. Adria Besos",
    "sg:orig_category":"Juegos Y Juguetes (al Por Menor)",
    "sg:phone":"+34 933 81 66 02",
    "sg:postcode":"08930",
    "sg:province":"Barcelona",
    "wof:name":"Camps Casacuberta Maria Rosa",
    "wof:placetype":"venue"
},
  "geometry": {"coordinates":[2.2164599895,41.4331817627],"type":"Point"}
}