{
  "type": "Feature",
  "properties": {
    "addr:full":"P. Jose Jimenez, 5 Ejido Almer\u00eda 04700",
    "addr:postcode":"04700",
    "addr:street":"P. Jose Jimenez 5 Ejido Almeri\u0301A",
    "iso:country":"ES",
    "sg:address":"P. Jose Jimenez, 5",
    "sg:city":"Ejido",
    "sg:orig_category":"Zapatos (al Por Menor)",
    "sg:phone":"+34 950 57 04 61",
    "sg:postcode":"04700",
    "sg:province":"Almer\u00eda",
    "wof:name":"Lidue\u00d1a & Alferez S.l.l.",
    "wof:placetype":"venue"
},
  "geometry": {"coordinates":[-2.7580699921,36.7285690308],"type":"Point"}
}