{
  "type": "Feature",
  "properties": {
    "addr:full":"Calceteros, 12 Iru\u00f1a Navarra 31001",
    "addr:housenumber":"12",
    "addr:postcode":"31001",
    "addr:street":"Calceteros",
    "iso:country":"ES",
    "sg:address":"Calceteros, 12",
    "sg:city":"Iru\u00f1a",
    "sg:orig_category":"Panader\u00cdas, Panader\u00cdas",
    "sg:phone":"+34 948 22 11 24",
    "sg:postcode":"31001",
    "sg:province":"Navarra",
    "wof:name":"Liberri S.l.",
    "wof:placetype":"venue"
},
  "geometry": {"coordinates":[-1.6433739662,42.8181648254],"type":"Point"}
}