{
  "type": "Feature",
  "properties": {
    "addr:full":"Avda Eduardo Dato, 23 Sevilla Sevilla 41018",
    "addr:housenumber":"23",
    "addr:postcode":"41018",
    "addr:street":"Avda Eduardo Dato",
    "iso:country":"ES",
    "sg:address":"Avda Eduardo Dato, 23",
    "sg:city":"Sevilla",
    "sg:orig_category":"Inmobiliaria (agencias)",
    "sg:phone":"+34 954 53 56 47",
    "sg:postcode":"41018",
    "sg:province":"Sevilla",
    "wof:name":"Sanchez Martinez Delfina",
    "wof:placetype":"venue"
},
  "geometry": {"coordinates":[-5.9782438278,37.3839912415],"type":"Point"}
}