{
  "type": "Feature",
  "properties": {
    "addr:full":"El Padron, 10 Estepona M\u00e1laga 29680",
    "addr:housenumber":"10",
    "addr:postcode":"29680",
    "addr:street":"Padron",
    "iso:country":"ES",
    "sg:address":"El Padron, 10",
    "sg:city":"Estepona",
    "sg:orig_category":"Electricidad: Equipos Industriales, Componentes (fabricaci\u00d3n)",
    "sg:phone":"+34 952 80 62 57",
    "sg:postcode":"29680",
    "sg:province":"M\u00e1laga",
    "wof:name":"Sunmoon Composites S.l.l.",
    "wof:placetype":"venue"
},
  "geometry": {"coordinates":[-5.1128292084,36.4350738525],"type":"Point"}
}