{
  "type": "Feature",
  "properties": {
    "addr:full":"Pg Saralegui, 36 Puerto De Pollen\u00c7a Islas Baleares 07470",
    "addr:housenumber":"36",
    "addr:postcode":"07470",
    "addr:street":"Pg Saralegui",
    "iso:country":"ES",
    "sg:address":"Pg Saralegui, 36",
    "sg:city":"Puerto De Pollen\u00c7a",
    "sg:orig_category":"Perfumer\u00cda (al Por Menor)",
    "sg:phone":"+34 971 86 63 02",
    "sg:postcode":"07470",
    "sg:province":"Islas Baleares",
    "wof:name":"Socias Ripoll Rosa Maria",
    "wof:placetype":"venue"
},
  "geometry": {"coordinates":[3.0818340778,39.905380249],"type":"Point"}
}