{
  "type": "Feature",
  "properties": {
    "iso:country":"ES",
    "sg:address":"Carr M.carrasco Formiguera, 9",
    "sg:city":"Lleida",
    "sg:orig_category":"Fabricaci\u00d3n De Art\u00cdculos Para Papeler\u00cdas",
    "sg:phone":"+34 973 20 17 63",
    "sg:postcode":"25001",
    "sg:province":"Lleida",
    "wof:name":"Ilerpapel S.l.",
    "wof:placetype":"venue"
},
  "geometry": {"coordinates":[0.6372870207,41.604675293],"type":"Point"}
}