{
  "type": "Feature",
  "properties": {
    "addr:full":"Ctra Madrid, 33 Ventorrillos Murcia 30319",
    "addr:housenumber":"33",
    "addr:postcode":"30319",
    "addr:street":"Ctra Madrid",
    "iso:country":"ES",
    "sg:address":"Ctra Madrid, 33",
    "sg:city":"Ventorrillos",
    "sg:orig_category":"Promotores Constructores",
    "sg:phone":"+34 968 16 95 19",
    "sg:postcode":"30319",
    "sg:province":"Murcia",
    "wof:name":"Omir 2001 S.l.",
    "wof:placetype":"venue"
},
  "geometry": {"coordinates":[-1.0148609877,37.6664352417],"type":"Point"}
}