{
  "type": "Feature",
  "properties": {
    "addr:full":"Avda Americas (de Las), 9 Alcantarilla Murcia 30820",
    "addr:housenumber":"9",
    "addr:postcode":"30820",
    "addr:street":"Avda Americas De Las",
    "iso:country":"ES",
    "sg:address":"Avda Americas (de Las), 9",
    "sg:city":"Alcantarilla",
    "sg:orig_category":"Perfumer\u00cda Y Cosm\u00c9tica (fabricaci\u00d3n, Al Por Mayor)",
    "sg:phone":"+34 968 89 25 45",
    "sg:postcode":"30820",
    "sg:province":"Murcia",
    "wof:name":"Global Estetic S.l.",
    "wof:placetype":"venue"
},
  "geometry": {"coordinates":[-1.2024669647,37.9556083679],"type":"Point"}
}