{
  "type": "Feature",
  "properties": {
    "iso:country":"ES",
    "sg:address":"Carrer de Industria (la), 7",
    "sg:city":"S. Joan Despi",
    "sg:orig_category":"Cerrajer\u00cda, Ferrallista",
    "sg:phone":"+34 934 80 87 50",
    "sg:postcode":"08970",
    "sg:province":"Barcelona",
    "sg:website":"www.tallerescolmenero.com",
    "wof:name":"Talleres Colmenero S.l.",
    "wof:placetype":"venue"
},
  "geometry": {"coordinates":[2.0693631172,41.3669586182],"type":"Point"}
}