{
  "type": "Feature",
  "properties": {
    "iso:country":"ES",
    "sg:address":"Av Hispanitat, 4",
    "sg:city":"Alcoi",
    "sg:orig_category":"Papeler\u00cdas, Librer\u00cdas",
    "sg:phone":"+34 966 52 18 00",
    "sg:postcode":"03804",
    "sg:province":"Alicante",
    "wof:name":"Ferre Vilaplana Alberto",
    "wof:placetype":"venue"
},
  "geometry": {"coordinates":[-0.4696890116,38.7064857483],"type":"Point"}
}