{
  "type": "Feature",
  "properties": {
    "addr:full":"Avda Novelda, 267 Alacant Alicante 03009",
    "addr:housenumber":"267",
    "addr:postcode":"03009",
    "addr:street":"Avda Novelda",
    "iso:country":"ES",
    "sg:address":"Avda Novelda, 267",
    "sg:city":"Alacant",
    "sg:orig_category":"Electrodom\u00c9sticos (fabricaci\u00d3n, Al Por Mayor)",
    "sg:phone":"+34 965 17 09 91",
    "sg:postcode":"03009",
    "sg:province":"Alicante",
    "sg:website":"www.miro.es",
    "wof:name":"Establecimientos Miro S.l.",
    "wof:placetype":"venue"
},
  "geometry": {"coordinates":[-0.5009199977,38.3788261414],"type":"Point"}
}