{
  "type": "Feature",
  "properties": {
    "addr:full":"G.v. Fernando El Catolico, 27 Valencia Valencia 46008",
    "addr:housenumber":"27",
    "addr:postcode":"46008",
    "addr:street":"Fernando El Catolico",
    "iso:country":"ES",
    "sg:address":"G.v. Fernando El Catolico, 27",
    "sg:city":"Valencia",
    "sg:orig_category":"Bancos",
    "sg:phone":"+34 963 84 72 07",
    "sg:postcode":"46008",
    "sg:province":"Valencia",
    "sg:website":"www.bancopopular.es",
    "wof:name":"Banco Popular Espa\u00f1ol",
    "wof:placetype":"venue"
},
  "geometry": {"coordinates":[-0.3861530125,39.4713401794],"type":"Point"}
}