{
  "type": "Feature",
  "properties": {
    "addr:full":"Calle de General Riera, 17 Palma Islas Baleares 07010",
    "addr:housenumber":"17",
    "addr:postcode":"07010",
    "addr:street":"Calle De General Riera",
    "iso:country":"ES",
    "sg:address":"Calle de General Riera, 17",
    "sg:city":"Palma",
    "sg:orig_category":"Asilos De Ancianos. Centros Privados",
    "sg:phone":"+34 971 75 06 84",
    "sg:postcode":"07010",
    "sg:province":"Islas Baleares",
    "wof:name":"Hermanitas De Los Pobres",
    "wof:placetype":"venue"
},
  "geometry": {"coordinates":[2.6469900608,39.5819702148],"type":"Point"}
}