{
  "type": "Feature",
  "properties": {
    "iso:country":"ES",
    "sg:address":"Via Argentina, 16",
    "sg:city":"Pollen\u00e7a",
    "sg:orig_category":"Muebles, Minoristas",
    "sg:phone":"+34 971 53 02 85",
    "sg:postcode":"07460",
    "sg:province":"Islas Baleares",
    "wof:name":"Perello Cifre Gabriel",
    "wof:placetype":"venue"
},
  "geometry": {"coordinates":[3.0194559097,39.8762969971],"type":"Point"}
}