{
  "type": "Feature",
  "properties": {
    "iso:country":"ES",
    "sg:address":"Pase Pontones, 17",
    "sg:city":"Madrid",
    "sg:orig_category":"Deportes Y Ocio: Art\u00cdculos Y Ropas (al Por Menor Y Accesorios)",
    "sg:phone":"+34 915 17 25 69",
    "sg:postcode":"28005",
    "sg:province":"Madrid",
    "wof:name":"El Patin De Oro S. L",
    "wof:placetype":"venue"
},
  "geometry": {"coordinates":[-3.7139630318,40.4055290222],"type":"Point"}
}