{
  "type": "Feature",
  "properties": {
    "iso:country":"ES",
    "sg:address":"Calle de Juderia, 3",
    "sg:city":"Toro",
    "sg:orig_category":"Molduras, Junquillos, Listones Y Molduras Perforadas",
    "sg:phone":"+34 980 69 29 01",
    "sg:postcode":"49800",
    "sg:province":"Zamora",
    "wof:name":"Rosa Luis Miguel De La",
    "wof:placetype":"venue"
},
  "geometry": {"coordinates":[-5.3983588219,41.5225410461],"type":"Point"}
}