{
  "type": "Feature",
  "properties": {
    "addr:full":"Avda Reyes Catolicos, 1 Albolote Granada 18220",
    "addr:housenumber":"1",
    "addr:postcode":"18220",
    "addr:street":"Avda Reyes Catolicos",
    "iso:country":"ES",
    "sg:address":"Avda Reyes Catolicos, 1",
    "sg:city":"Albolote",
    "sg:orig_category":"Agencias Y Agentes Comerciales, Representantes",
    "sg:phone":"+34 958 46 89 96",
    "sg:postcode":"18220",
    "sg:province":"Granada",
    "wof:name":"Cuartero Lozano Francisca",
    "wof:placetype":"venue"
},
  "geometry": {"coordinates":[-3.6538929939,37.228187561],"type":"Point"}
}