{
  "type": "Feature",
  "properties": {
    "iso:country":"ES",
    "sg:address":"Calle de General Franco, S/n",
    "sg:city":"Alar Del Rey",
    "sg:orig_category":"Cajas De Ahorro",
    "sg:phone":"+34 979 13 31 16",
    "sg:postcode":"34480",
    "sg:province":"Palencia",
    "sg:website":"www.cajaespa\u00f1a.es",
    "wof:name":"Caja Espa\u00f1a De Inversiones Caja De Ahorros Y Monte De Piedad",
    "wof:placetype":"venue"
},
  "geometry": {"coordinates":[-4.31016922,42.6596107483],"type":"Point"}
}