{
  "type": "Feature",
  "properties": {
    "iso:country":"ES",
    "sg:address":"Calle de Pedro Del Toro, 5",
    "sg:city":"Sevilla",
    "sg:orig_category":"Agencias Y Asesores De Publicidad",
    "sg:phone":"+34 954 22 24 64",
    "sg:postcode":"41001",
    "sg:province":"Sevilla",
    "wof:name":"Marin Y Asociados Malaga S.l.",
    "wof:placetype":"venue"
},
  "geometry": {"coordinates":[-6.0002450943,37.3917961121],"type":"Point"}
}