{
  "type": "Feature",
  "properties": {
    "addr:full":"Carrer de Cardenal Vidal I Barraquer, 14 S. Boi Llobregat Barcelona 08830",
    "addr:housenumber":"14",
    "addr:postcode":"08830",
    "addr:street":"Carrer De Cardenal Vidal I Barraquer",
    "iso:country":"ES",
    "sg:address":"Carrer de Cardenal Vidal I Barraquer, 14",
    "sg:city":"S. Boi Llobregat",
    "sg:orig_category":"Alimentaci\u00d3n General (al Por Menor)",
    "sg:phone":"+34 936 40 08 28",
    "sg:postcode":"08830",
    "sg:province":"Barcelona",
    "wof:name":"Albalat Viader Jaime",
    "wof:placetype":"venue"
},
  "geometry": {"coordinates":[2.0381731987,41.3456535339],"type":"Point"}
}