{
  "type": "Feature",
  "properties": {
    "iso:country":"ES",
    "sg:address":"Carrer de Sant Tomas Aquino, 17",
    "sg:city":"Palma",
    "sg:orig_category":"Obras Y Organismos Sociales",
    "sg:phone":"+34 971 27 12 32",
    "sg:postcode":"07006",
    "sg:province":"Islas Baleares",
    "wof:name":"Mensajeros De La Paz",
    "wof:placetype":"venue"
},
  "geometry": {"coordinates":[2.676213026,39.5591201782],"type":"Point"}
}