{
  "type": "Feature",
  "properties": {
    "iso:country":"ES",
    "sg:address":"Carrer de Anselm Clave, 112",
    "sg:city":"Calella",
    "sg:orig_category":"Maquinaria Para Industrias Diversas",
    "sg:phone":"+34 937 69 53 85",
    "sg:postcode":"08370",
    "sg:province":"Barcelona",
    "wof:name":"Fontdegloria Rius Josep",
    "wof:placetype":"venue"
},
  "geometry": {"coordinates":[2.6630079746,41.613483429],"type":"Point"}
}