{
  "type": "Feature",
  "properties": {
    "iso:country":"ES",
    "sg:address":"Calle de Altos Del Duero, 4",
    "sg:city":"Le\u00f3n",
    "sg:orig_category":"Material Y Suministros Para Veterinarios",
    "sg:phone":"+34 987 24 51 41",
    "sg:postcode":"24008",
    "sg:province":"Le\u00f3n",
    "wof:name":"Casorto S. L.",
    "wof:placetype":"venue"
},
  "geometry": {"coordinates":[-5.5774812698,42.6160774231],"type":"Point"}
}