{
  "type": "Feature",
  "properties": {
    "iso:country":"ES",
    "sg:address":"Avda Roquetas, 86",
    "sg:city":"Roquetas Mar",
    "sg:orig_category":"Estancos",
    "sg:phone":"+34 950 32 41 44",
    "sg:postcode":"04740",
    "sg:province":"Almer\u00eda",
    "wof:name":"Murcia Gomez Amaya",
    "wof:placetype":"venue"
},
  "geometry": {"coordinates":[-2.6124989986,36.7638435364],"type":"Point"}
}