{
  "type": "Feature",
  "properties": {
    "iso:country":"ES",
    "sg:address":"Carr Cervantes, 116",
    "sg:city":"Badalona",
    "sg:orig_category":"Empresas De Carpinter\u00cda Met\u00c1lica",
    "sg:phone":"+34 933 99 15 06",
    "sg:postcode":"08912",
    "sg:province":"Barcelona",
    "wof:name":"Ca\u00f1ada Hoyos Juan Carlos",
    "wof:placetype":"venue"
},
  "geometry": {"coordinates":[2.2395429611,41.4406166077],"type":"Point"}
}