{
  "type": "Feature",
  "properties": {
    "iso:country":"ES",
    "sg:address":"Ptda. Planteas, S/n",
    "sg:city":"Vilamarxant",
    "sg:orig_category":"Empresas De Desmonte",
    "sg:phone":"+34 961 65 06 30",
    "sg:postcode":"46191",
    "sg:province":"Valencia",
    "wof:name":"Zanjas Urbanas De Servicios S.l",
    "wof:placetype":"venue"
},
  "geometry": {"coordinates":[-0.6488505006,39.5570449829],"type":"Point"}
}