{
  "type": "Feature",
  "properties": {
    "iso:country":"ES",
    "sg:address":"Bda El Cortado, 9",
    "sg:city":"Mengibar",
    "sg:orig_category":"Empresas De Carpinter\u00cda De Madera",
    "sg:phone":"+34 953 37 06 33",
    "sg:postcode":"23620",
    "sg:province":"Ja\u00e9n",
    "wof:name":"Frabrure S.l.",
    "wof:placetype":"venue"
},
  "geometry": {"coordinates":[-3.8023340702,37.9750289917],"type":"Point"}
}