{
  "type": "Feature",
  "properties": {
    "addr:full":"Calle de San Juan, 1 Artana Castell\u00f3n 12527",
    "addr:housenumber":"1",
    "addr:postcode":"12527",
    "addr:street":"Calle De San Juan;Castello\u0301N",
    "iso:country":"ES",
    "sg:address":"Calle de San Juan, 1",
    "sg:city":"Artana",
    "sg:orig_category":"Supermercados Y Hipermercados",
    "sg:phone":"+34 964 61 12 36",
    "sg:postcode":"12527",
    "sg:province":"Castell\u00f3n",
    "wof:name":"Llido Lara Jose Luis",
    "wof:placetype":"venue"
},
  "geometry": {"coordinates":[-0.2546119988,39.8906097412],"type":"Point"}
}