{
  "type": "Feature",
  "properties": {
    "iso:country":"ES",
    "sg:address":"Kurtzetxiki Plaza, 2",
    "sg:city":"Arrasate",
    "sg:orig_category":"Promotores Constructores",
    "sg:phone":"+34 943 08 17 57",
    "sg:postcode":"20500",
    "sg:province":"Guip\u00f9zcoa",
    "wof:name":"Canas Esteban , Melchor",
    "wof:placetype":"venue"
},
  "geometry": {"coordinates":[-2.4939239025,43.0611686707],"type":"Point"}
}