{
  "type": "Feature",
  "properties": {
    "addr:full":"Calle de Isla De Gran Canaria, 5 Guacimara Santa Cruz De Tenerife 38400",
    "addr:housenumber":"5",
    "addr:postcode":"38400",
    "addr:street":"Calle De Isla De Gran Canaria",
    "iso:country":"ES",
    "sg:address":"Calle de Isla De Gran Canaria, 5",
    "sg:city":"Guacimara",
    "sg:orig_category":"Centros M\u00c9dicos Y Sociales, Dispensarios",
    "sg:phone":"+34 922 38 41 23",
    "sg:postcode":"38400",
    "sg:province":"Santa Cruz De Tenerife",
    "wof:name":"Schill  Werner",
    "wof:placetype":"venue"
},
  "geometry": {"coordinates":[-16.5429458618,28.4070835114],"type":"Point"}
}