{
  "type": "Feature",
  "properties": {
    "addr:full":"Avda Garat Txomin, 1 Bilbao Vizcaya 48004",
    "addr:housenumber":"1",
    "addr:postcode":"48004",
    "addr:street":"Avda Garat Txomin",
    "iso:country":"ES",
    "sg:address":"Avda Garat Txomin, 1",
    "sg:city":"Bilbao",
    "sg:orig_category":"Lencer\u00cda Femenina, Corseter\u00cda, Trajes De Ba\u00d1o (al Por Menor)",
    "sg:phone":"+34 944 11 10 62",
    "sg:postcode":"48004",
    "sg:province":"Vizcaya",
    "wof:name":"Almacenes Egausua, S.l.",
    "wof:placetype":"venue"
},
  "geometry": {"coordinates":[-2.9098529816,43.2574157715],"type":"Point"}
}