{
  "type": "Feature",
  "properties": {
    "iso:country":"ES",
    "sg:address":"Calle de Batalla De Lepanto, 7",
    "sg:city":"Carlota",
    "sg:orig_category":"Mec\u00c1nico Del Autom\u00d3vil",
    "sg:phone":"+34 957 30 02 73",
    "sg:postcode":"14100",
    "sg:province":"C\u00f3rdoba",
    "wof:name":"Carloautos Lopez S.l.",
    "wof:placetype":"venue"
},
  "geometry": {"coordinates":[-4.9395461082,37.6681785583],"type":"Point"}
}