{
  "type": "Feature",
  "properties": {
    "addr:full":"Calle de Grillo, 6 Tarancon Cuenca 16400",
    "addr:housenumber":"6",
    "addr:postcode":"16400",
    "addr:street":"Calle De Grillo",
    "iso:country":"ES",
    "sg:address":"Calle de Grillo, 6",
    "sg:city":"Tarancon",
    "sg:orig_category":"Electricidad Veh\u00cdculo",
    "sg:phone":"+34 969 32 33 70",
    "sg:postcode":"16400",
    "sg:province":"Cuenca",
    "wof:name":"Enytelme S.l.l.",
    "wof:placetype":"venue"
},
  "geometry": {"coordinates":[-3.0068490505,40.0095672607],"type":"Point"}
}