{
  "type": "Feature",
  "properties": {
    "iso:country":"ES",
    "sg:address":"C/ Marques D'asprella, 4",
    "sg:city":"Elche",
    "sg:orig_category":"Cl\u00cdnicas M\u00c9dicas",
    "sg:phone":"+34 965 44 49 17",
    "sg:postcode":"03201",
    "sg:province":"Alicante",
    "sg:website":"www.avicorp.com/foguet",
    "wof:name":"Perez Chuffo Jose Maria",
    "wof:placetype":"venue"
},
  "geometry": {"coordinates":[-0.4891029894,38.3498764038],"type":"Point"}
}