{
  "type": "Feature",
  "properties": {
    "iso:country":"ES",
    "sg:address":"Avda Doctor Fedriani, 34",
    "sg:city":"Sevilla",
    "sg:orig_category":"Molduras, Junquillos, Listones Y Molduras Perforadas",
    "sg:phone":"+34 954 38 12 66",
    "sg:postcode":"41009",
    "sg:province":"Sevilla",
    "wof:name":"Moreno Bueno Jose",
    "wof:placetype":"venue"
},
  "geometry": {"coordinates":[-5.9833879471,37.4145965576],"type":"Point"}
}