{
  "type": "Feature",
  "properties": {
    "iso:country":"ES",
    "sg:address":"Calle de Angel Guimera, 44",
    "sg:city":"Valencia",
    "sg:orig_category":"Ropa Para Se\u00d1oras (al Por Menor)",
    "sg:phone":"+34 963 85 69 27",
    "sg:postcode":"46008",
    "sg:province":"Valencia",
    "wof:name":"Llopis Esteve Maria Luz",
    "wof:placetype":"venue"
},
  "geometry": {"coordinates":[-0.3884918094,39.4697532654],"type":"Point"}
}