{
  "type": "Feature",
  "properties": {
    "addr:full":"Calle de Chozas De La Sierra, 7 Madrid Madrid 28002",
    "addr:housenumber":"7",
    "addr:postcode":"madrid;28002",
    "addr:street":"Calle De Chozas De La Sierra",
    "iso:country":"ES",
    "sg:address":"Calle de Chozas De La Sierra, 7",
    "sg:city":"Madrid",
    "sg:orig_category":"Empresarios Y Productoras De Espect\u00c1culos",
    "sg:phone":"+34 914 13 77 31",
    "sg:postcode":"28002",
    "sg:province":"Madrid",
    "wof:name":"Man Producciones Management S.l.",
    "wof:placetype":"venue"
},
  "geometry": {"coordinates":[-3.6640238762,40.4477958679],"type":"Point"}
}