{
  "type": "Feature",
  "properties": {
    "addr:full":"Avda Navarra De, 44 Donostia-san Sebastian Guip\u00f9zcoa 20013",
    "addr:housenumber":"44",
    "addr:postcode":"20013",
    "addr:street":"Avda Navarra De",
    "iso:country":"ES",
    "sg:address":"Avda Navarra De, 44",
    "sg:city":"Donostia-san Sebastian",
    "sg:orig_category":"Inform\u00c1tica (estudios, Servicios, Asesor\u00cda, Formaci\u00d3n)",
    "sg:phone":"+34 943 27 37 11",
    "sg:postcode":"20013",
    "sg:province":"Guip\u00f9zcoa",
    "wof:name":"Asesores En Comunicacion Global Y Estrategia S.l.",
    "wof:placetype":"venue"
},
  "geometry": {"coordinates":[-1.9669148922,43.3227272034],"type":"Point"}
}