{
  "type": "Feature",
  "properties": {
    "iso:country":"ES",
    "sg:address":"Las Magnolias, 4",
    "sg:city":"S. Agustin-playa Ingles",
    "sg:orig_category":"Asesor\u00cda Sobre Comunicaci\u00d3n De Empresas",
    "sg:phone":"+34 928 76 46 31",
    "sg:postcode":"35100",
    "sg:province":"Las Palmas",
    "wof:name":"Bastad Inves S.l.",
    "wof:placetype":"venue"
},
  "geometry": {"coordinates":[-15.4397096634,28.1302204132],"type":"Point"}
}