{
  "type": "Feature",
  "properties": {
    "addr:full":"Riocalvo, 26 Negreiros Pontevedra 36546",
    "addr:housenumber":"26",
    "addr:postcode":"36546",
    "addr:street":"Riocalvo",
    "iso:country":"ES",
    "sg:address":"Riocalvo, 26",
    "sg:city":"Negreiros",
    "sg:orig_category":"Reciclaje, Desguace De Veh\u00cdculos",
    "sg:phone":"+34 986 58 01 75",
    "sg:postcode":"36546",
    "sg:province":"Pontevedra",
    "wof:name":"Lorenzo Rodriguez Luis Fernando",
    "wof:placetype":"venue"
},
  "geometry": {"coordinates":[-8.278670311,42.7603225708],"type":"Point"}
}