{
  "type": "Feature",
  "properties": {
    "addr:full":"Calle de Molino, 30 Provencio Cuenca 16670",
    "addr:housenumber":"30",
    "addr:postcode":"16670",
    "addr:street":"Calle De Molino",
    "iso:country":"ES",
    "sg:address":"Calle de Molino, 30",
    "sg:city":"Provencio",
    "sg:orig_category":"Asesor\u00cda Sobre Comunicaci\u00d3n De Empresas",
    "sg:phone":"+34 967 16 61 21",
    "sg:postcode":"16670",
    "sg:province":"Cuenca",
    "wof:name":"Gomez Moya S.l.",
    "wof:placetype":"venue"
},
  "geometry": {"coordinates":[-2.5704939365,39.3758201599],"type":"Point"}
}