{
  "type": "Feature",
  "properties": {
    "iso:country":"ES",
    "sg:address":"Calle de Carrera, 20",
    "sg:city":"Antequera",
    "sg:orig_category":"Empresarios",
    "sg:phone":"+34 952 84 25 95",
    "sg:postcode":"29200",
    "sg:province":"M\u00e1laga",
    "wof:name":"Esparraga Miranda Josefa",
    "wof:placetype":"venue"
},
  "geometry": {"coordinates":[-4.5553750992,37.0191993713],"type":"Point"}
}