{
  "type": "Feature",
  "properties": {
    "iso:country":"ES",
    "sg:address":"Avda Doctor Otero Ulloa, 146",
    "sg:city":"Seixo",
    "sg:orig_category":"Fabricaci\u00d3n, Reparaci\u00d3n Y Mantenimiento De Construcciones Navales Y Fluviales",
    "sg:phone":"+34 986 70 21 15",
    "sg:postcode":"36913",
    "sg:province":"Pontevedra",
    "wof:name":"Nautica Calvi\u00f1o S.c.",
    "wof:placetype":"venue"
},
  "geometry": {"coordinates":[-8.7334785461,42.3674240112],"type":"Point"}
}