{
  "type": "Feature",
  "properties": {
    "addr:full":"Plaz Cantabrico, 3 Punta Umbria Huelva 21100",
    "addr:housenumber":"3",
    "addr:postcode":"21100",
    "addr:street":"Plaz Cantabrico",
    "iso:country":"ES",
    "sg:address":"Plaz Cantabrico, 3",
    "sg:city":"Punta Umbria",
    "sg:orig_category":"Molduras, Junquillos, Listones Y Molduras Perforadas",
    "sg:phone":"+34 959 31 10 50",
    "sg:postcode":"21100",
    "sg:province":"Huelva",
    "wof:name":"Beltran Mingorance Francisco",
    "wof:placetype":"venue"
},
  "geometry": {"coordinates":[-6.9626097679,37.1757659912],"type":"Point"}
}