{
  "type": "Feature",
  "properties": {
    "addr:full":"Calle de Camino De Los Vinateros, 124 Madrid Madrid 28030",
    "addr:housenumber":"124",
    "addr:postcode":"28030",
    "addr:street":"Calle De Camino De Los Vinateros",
    "iso:country":"ES",
    "sg:address":"Calle de Camino De Los Vinateros, 124",
    "sg:city":"Madrid",
    "sg:orig_category":"Administradores De Bienes Y Delegados De Comunidades De Propietarios",
    "sg:phone":"+34 914 37 20 35",
    "sg:postcode":"28030",
    "sg:province":"Madrid",
    "wof:name":"Lozano Masipe S.l.",
    "wof:placetype":"venue"
},
  "geometry": {"coordinates":[-3.6446621418,40.4070281982],"type":"Point"}
}