{
  "type": "Feature",
  "properties": {
    "addr:full":"Mas Camarena, 50 Betera Valencia 46117",
    "addr:postcode":"46117",
    "iso:country":"ES",
    "sg:address":"Mas Camarena, 50",
    "sg:city":"Betera",
    "sg:orig_category":"Ingeniero",
    "sg:phone":"+34 961 68 78 75",
    "sg:postcode":"46117",
    "sg:province":"Valencia",
    "wof:name":"Polidur Iberica Resinas Sinteticas S.l.",
    "wof:placetype":"venue"
},
  "geometry": {"coordinates":[-0.46370399,39.5557746887],"type":"Point"}
}