{
  "type": "Feature",
  "properties": {
    "iso:country":"ES",
    "sg:address":"Carrer de Alfred Bonet, 6",
    "sg:city":"Palma",
    "sg:orig_category":"Asesor\u00cdas Y Estudios Financieros",
    "sg:phone":"+34 971 29 94 03",
    "sg:postcode":"07003",
    "sg:province":"Islas Baleares",
    "wof:name":"Rotger Canaves Martin",
    "wof:placetype":"venue"
},
  "geometry": {"coordinates":[2.646887064,39.5789108276],"type":"Point"}
}