{
  "type": "Feature",
  "properties": {
    "addr:full":"Estd Loiro (de), 53 Loiro Ourense 32890",
    "addr:postcode":"32890",
    "iso:country":"ES",
    "sg:address":"Estd Loiro (de), 53",
    "sg:city":"Loiro",
    "sg:orig_category":"Muebles, Minoristas",
    "sg:phone":"+34 988 38 33 38",
    "sg:postcode":"32890",
    "sg:province":"Ourense",
    "wof:name":"Raul Suarez S.l.",
    "wof:placetype":"venue"
},
  "geometry": {"coordinates":[-7.8872189522,42.3010559082],"type":"Point"}
}