{
  "type": "Feature",
  "properties": {
    "iso:country":"ES",
    "sg:address":"Calle de Virgen De Lluc, 12",
    "sg:city":"Madrid",
    "sg:orig_category":"Venta, Colocaci\u00d3n, Reparaci\u00d3n De Parabrisas, Techos Descapotables",
    "sg:phone":"+34 913 40 00 70",
    "sg:postcode":"28027",
    "sg:province":"Madrid",
    "wof:name":"Autocristal Norte S.l.",
    "wof:placetype":"venue"
},
  "geometry": {"coordinates":[-3.6546533108,40.4344825745],"type":"Point"}
}