{
  "type": "Feature",
  "properties": {
    "addr:full":"Carr Campos, S/n Felanitx Islas Baleares 07200",
    "addr:housenumber":"s / n",
    "addr:postcode":"07200",
    "addr:street":"Carr Campos",
    "iso:country":"ES",
    "sg:address":"Carr Campos, S/n",
    "sg:city":"Felanitx",
    "sg:orig_category":"Semiller\u00cdas",
    "sg:phone":"+34 971 82 75 02",
    "sg:postcode":"07200",
    "sg:province":"Islas Baleares",
    "wof:name":"Capo Artigues Francisca",
    "wof:placetype":"venue"
},
  "geometry": {"coordinates":[3.1013588905,39.4265365601],"type":"Point"}
}