{
  "type": "Feature",
  "properties": {
    "addr:full":"Avda Tirma (de), 13 Playa Del Ingles Las Palmas 35100",
    "addr:housenumber":"13",
    "addr:postcode":"35100",
    "addr:street":"Avda Tirma De",
    "iso:country":"ES",
    "sg:address":"Avda Tirma (de), 13",
    "sg:city":"Playa Del Ingles",
    "sg:orig_category":"Fabricaci\u00d3n De Telas Y Sedas",
    "sg:phone":"+34 928 76 87 56",
    "sg:postcode":"35100",
    "sg:province":"Las Palmas",
    "wof:name":"Tiempos Canarios S.l.",
    "wof:placetype":"venue"
},
  "geometry": {"coordinates":[-15.5718336105,27.7604866028],"type":"Point"}
}