{
  "type": "Feature",
  "properties": {
    "iso:country":"ES",
    "sg:address":"Avda Oasis, 115",
    "sg:city":"Ejido",
    "sg:orig_category":"Muebles, Minoristas",
    "sg:phone":"+34 950 57 03 77",
    "sg:postcode":"04700",
    "sg:province":"Almer\u00eda",
    "wof:name":"Muebles Santo Domingo S.l.",
    "wof:placetype":"venue"
},
  "geometry": {"coordinates":[-2.8010919094,36.7685050964],"type":"Point"}
}