{
  "type": "Feature",
  "properties": {
    "addr:full":"Calle de Real, 64 Yuncos Toledo 45210",
    "addr:housenumber":"64",
    "addr:postcode":"45210",
    "addr:street":"Calle De Real",
    "iso:country":"ES",
    "sg:address":"Calle de Real, 64",
    "sg:city":"Yuncos",
    "sg:orig_category":"Delegados, Agentes De Tr\u00c1nsito, Auxiliares De Transporte Internacional",
    "sg:phone":"+34 925 55 72 79",
    "sg:postcode":"45210",
    "sg:province":"Toledo",
    "wof:name":"Biencinto Gonzalez Gregorio",
    "wof:placetype":"venue"
},
  "geometry": {"coordinates":[-3.8714160919,40.0906562805],"type":"Point"}
}