{
  "type": "Feature",
  "properties": {
    "iso:country":"ES",
    "sg:address":"Crta. Tossa, 100",
    "sg:city":"Lloret Mar",
    "sg:orig_category":"Librer\u00cdas",
    "sg:phone":"+34 972 37 26 58",
    "sg:postcode":"17310",
    "sg:province":"Girona",
    "wof:name":"Comercial Atheneum S.l.",
    "wof:placetype":"venue"
},
  "geometry": {"coordinates":[2.8851099014,41.7117233276],"type":"Point"}
}