{
  "type": "Feature",
  "properties": {
    "iso:country":"ES",
    "sg:address":"Av Pau, De Sa, 136",
    "sg:city":"Sant Lluis",
    "sg:orig_category":"Sociedades, Compa\u00d1\u00cdas Aseguradoras",
    "sg:phone":"+34 971 15 08 28",
    "sg:postcode":"07710",
    "sg:province":"Islas Baleares",
    "wof:name":"Assegurances Sant Lluis S.l.",
    "wof:placetype":"venue"
},
  "geometry": {"coordinates":[4.2598414421,39.84998703],"type":"Point"}
}