{
  "type": "Feature",
  "properties": {
    "iso:country":"ES",
    "sg:address":"Plaz Lugo (de), 10",
    "sg:city":"Viveiro",
    "sg:orig_category":"Molduras, Junquillos, Listones Y Molduras Perforadas",
    "sg:phone":"+34 982 56 09 16",
    "sg:postcode":"27850",
    "sg:province":"Lugo",
    "wof:name":"Dorado Solloso Jose Manuel",
    "wof:placetype":"venue"
},
  "geometry": {"coordinates":[-7.5959348679,43.6629714966],"type":"Point"}
}