{
  "type": "Feature",
  "properties": {
    "iso:country":"ES",
    "sg:address":"Calle de Alvarez De Toledo, 5",
    "sg:city":"Ventosa",
    "sg:orig_category":"Agricultores, Agricultores",
    "sg:phone":"+34 969 37 58 37",
    "sg:postcode":"16843",
    "sg:province":"Cuenca",
    "wof:name":"Agropecuaria Perez Martinez S.a.t.",
    "wof:placetype":"venue"
},
  "geometry": {"coordinates":[-2.4319682121,40.2046089172],"type":"Point"}
}