{
  "type": "Feature",
  "properties": {
    "addr:full":"Av Fort De L'eau, 131 Mao Islas Baleares 07701",
    "addr:housenumber":"131",
    "addr:postcode":"07701",
    "addr:street":"Av Fort De L'Eau",
    "iso:country":"ES",
    "sg:address":"Av Fort De L'eau, 131",
    "sg:city":"Mao",
    "sg:orig_category":"Agencias De Viajes",
    "sg:phone":"+34 971 35 69 91",
    "sg:postcode":"07701",
    "sg:province":"Islas Baleares",
    "wof:name":"Viajes Menorca S.l.",
    "wof:placetype":"venue"
},
  "geometry": {"coordinates":[4.2730951309,39.8872108459],"type":"Point"}
}