{
  "type": "Feature",
  "properties": {
    "addr:full":"Pg Fabra I Puig, 278 Barcelona Barcelona 08031",
    "addr:housenumber":"278",
    "addr:postcode":"08031",
    "addr:street":"Pg Fabra I Puig",
    "iso:country":"ES",
    "sg:address":"Pg Fabra I Puig, 278",
    "sg:city":"Barcelona",
    "sg:orig_category":"Peluquer\u00cdas, Peluquer\u00cda Mixta",
    "sg:phone":"+34 934 29 30 14",
    "sg:postcode":"08031",
    "sg:province":"Barcelona",
    "wof:name":"Nieto Figueroa Olga",
    "wof:placetype":"venue"
},
  "geometry": {"coordinates":[2.1724710464,41.4304237366],"type":"Point"}
}