{
  "type": "Feature",
  "properties": {
    "iso:country":"ES",
    "sg:address":"Ctra. Ina, S/n",
    "sg:city":"El Torno",
    "sg:orig_category":"Agricultores, Agricultores",
    "sg:phone":"+34 956 23 71 60",
    "sg:postcode":"11594",
    "sg:province":"C\u00e1diz",
    "wof:name":"Blen S. A.",
    "wof:placetype":"venue"
},
  "geometry": {"coordinates":[-5.972589016,36.6206512451],"type":"Point"}
}