{
  "type": "Feature",
  "properties": {
    "addr:full":"Ctra Samalus, 35 Garriga Barcelona 08530",
    "addr:housenumber":"35",
    "addr:postcode":"08530",
    "addr:street":"Ctra Samalus",
    "iso:country":"ES",
    "sg:address":"Ctra Samalus, 35",
    "sg:city":"Garriga",
    "sg:orig_category":"Alimentaci\u00d3n General (al Por Menor)",
    "sg:phone":"+34 938 71 41 67",
    "sg:postcode":"08530",
    "sg:province":"Barcelona",
    "wof:name":"Sobrevia Viure Jose",
    "wof:placetype":"venue"
},
  "geometry": {"coordinates":[2.2934861183,41.6820030212],"type":"Point"}
}