{
  "type": "Feature",
  "properties": {
    "addr:full":"Carr Esglesia, (de L'), 9 Beniganim Valencia 46830",
    "addr:housenumber":"9",
    "addr:postcode":"46830",
    "addr:street":"Carr Esglesia De L '",
    "iso:country":"ES",
    "sg:address":"Carr Esglesia, (de L'), 9",
    "sg:city":"Beniganim",
    "sg:orig_category":"Panader\u00cdas, Pasteler\u00cdas, Boller\u00cda Industriale (fabricaci\u00d3n, Al Por Mayor)",
    "sg:phone":"+34 962 21 57 56",
    "sg:postcode":"46830",
    "sg:province":"Valencia",
    "wof:name":"Forn Del Real C.b.",
    "wof:placetype":"venue"
},
  "geometry": {"coordinates":[-0.4438039958,38.9444389343],"type":"Point"}
}