{
  "type": "Feature",
  "properties": {
    "addr:full":"Carrer de Solsona, 110 Terrassa Barcelona 08227",
    "addr:housenumber":"110",
    "addr:postcode":"08227",
    "addr:street":"Carrer De Solsona",
    "iso:country":"ES",
    "sg:address":"Carrer de Solsona, 110",
    "sg:city":"Terrassa",
    "sg:orig_category":"Peluquer\u00cdas, Peluquer\u00cda Mixta",
    "sg:phone":"+34 937 31 92 03",
    "sg:postcode":"08227",
    "sg:province":"Barcelona",
    "wof:name":"Garcia Andres Judhit",
    "wof:placetype":"venue"
},
  "geometry": {"coordinates":[2.0373950005,41.5746650696],"type":"Point"}
}