{
  "type": "Feature",
  "properties": {
    "addr:full":"Ctra Escriva, 21 Valencia Valencia 46007",
    "addr:housenumber":"21",
    "addr:postcode":"46007",
    "addr:street":"Ctra Escriva",
    "iso:country":"ES",
    "sg:address":"Ctra Escriva, 21",
    "sg:city":"Valencia",
    "sg:orig_category":"Bisuteros (fabricaci\u00d3n, Al Por Mayor)",
    "sg:phone":"+34 963 41 89 30",
    "sg:postcode":"46007",
    "sg:province":"Valencia",
    "wof:name":"Joyas Vivendi S.l.",
    "wof:placetype":"venue"
},
  "geometry": {"coordinates":[-0.3855279982,39.4579238892],"type":"Point"}
}