{
  "type": "Feature",
  "properties": {
    "iso:country":"ES",
    "sg:address":"Av Constitucio, 93",
    "sg:city":"Castelldefels",
    "sg:orig_category":"Muebles, Minoristas",
    "sg:phone":"+34 936 65 23 19",
    "sg:postcode":"08860",
    "sg:province":"Barcelona",
    "wof:name":"Ambit 93 S.l.",
    "wof:placetype":"venue"
},
  "geometry": {"coordinates":[1.9820659161,41.2824516296],"type":"Point"}
}