{
  "type": "Feature",
  "properties": {
    "addr:full":"Carretera De Orense-los Peares, S/n Peroxa Ourense 32150",
    "addr:housenumber":"s / n",
    "addr:postcode":"32150",
    "addr:street":"Carretera De Orense-Los Peares",
    "iso:country":"ES",
    "sg:address":"Carretera De Orense-los Peares, S/n",
    "sg:city":"Peroxa",
    "sg:orig_category":"Hoteles",
    "sg:phone":"+34 988 20 66 28",
    "sg:postcode":"32150",
    "sg:province":"Ourense",
    "wof:name":"Seoane Rodriguez Manuel",
    "wof:placetype":"venue"
},
  "geometry": {"coordinates":[-7.7943491936,42.439704895],"type":"Point"}
}