{
  "type": "Feature",
  "properties": {
    "iso:country":"ES",
    "sg:address":"Calle de Santa Lucia, 11",
    "sg:city":"Zaragoza",
    "sg:orig_category":"Carnicer\u00cdas, Carnicer\u00cdas",
    "sg:phone":"+34 976 43 47 03",
    "sg:postcode":"50003",
    "sg:province":"Zaragoza",
    "wof:name":"Exclusivas Barrabes S.cv.",
    "wof:placetype":"venue"
},
  "geometry": {"coordinates":[-0.8918030262,41.6579475403],"type":"Point"}
}