{
  "type": "Feature",
  "properties": {
    "addr:full":"Rua Perfectino Vieitez, 8 Carballi\u00f1o Ourense 32500",
    "addr:housenumber":"8",
    "addr:postcode":"32500",
    "addr:street":"Rua Perfectino Vieitez",
    "iso:country":"ES",
    "sg:address":"Rua Perfectino Vieitez, 8",
    "sg:city":"Carballi\u00f1o",
    "sg:orig_category":"Bisuter\u00cda, Joyer\u00cda, Relojer\u00cda (al Por Menor)",
    "sg:phone":"+34 988 53 06 44",
    "sg:postcode":"32500",
    "sg:province":"Ourense",
    "wof:name":"Gonzalez Otero Juan",
    "wof:placetype":"venue"
},
  "geometry": {"coordinates":[-8.0776538849,42.4302520752],"type":"Point"}
}