{
  "type": "Feature",
  "properties": {
    "iso:country":"ES",
    "sg:address":"Avda San Gregorio Ostiense, S/n",
    "sg:city":"Hormilleja",
    "sg:orig_category":"Serrer\u00cdas De Madera",
    "sg:phone":"+34 941 36 20 81",
    "sg:postcode":"26223",
    "sg:province":"La Rioja",
    "wof:name":"Azofra Lacalle Ignacio",
    "wof:placetype":"venue"
},
  "geometry": {"coordinates":[-2.7296469212,42.4551086426],"type":"Point"}
}