{
  "type": "Feature",
  "properties": {
    "addr:full":"Pase Ocharan Mazas, 18 Castro Urdiales Cantabria 39700",
    "addr:housenumber":"18",
    "addr:postcode":"39700",
    "addr:street":"Ocharan Mazas",
    "iso:country":"ES",
    "sg:address":"Pase Ocharan Mazas, 18",
    "sg:city":"Castro Urdiales",
    "sg:orig_category":"Publicidad (soportes Y Gesti\u00d3n)",
    "sg:phone":"+34 942 87 08 14",
    "sg:postcode":"39700",
    "sg:province":"Cantabria",
    "wof:name":"Promociones Same-2 S.l.",
    "wof:placetype":"venue"
},
  "geometry": {"coordinates":[-3.2153770924,43.3783683777],"type":"Point"}
}