{
  "type": "Feature",
  "properties": {
    "iso:country":"ES",
    "sg:address":"Plaz Mar Caribe (del), 5",
    "sg:city":"Coslada",
    "sg:orig_category":"Agentes, Concesionarios Y Sucursales De Veh\u00cdculos",
    "sg:phone":"+34 916 69 80 39",
    "sg:postcode":"28820",
    "sg:province":"Madrid",
    "sg:website":"www.impactsolebo.com",
    "wof:name":"Impact Solebo S.l.",
    "wof:placetype":"venue"
},
  "geometry": {"coordinates":[-3.5645070076,40.4260902405],"type":"Point"}
}