{
  "type": "Feature",
  "properties": {
    "iso:country":"ES",
    "sg:address":"Calle de Alcalde Jose Ramirez Bethencourt, 73",
    "sg:city":"Burrero",
    "sg:orig_category":"Supermercados Y Hipermercados",
    "sg:phone":"+34 928 73 85 23",
    "sg:postcode":"35240",
    "sg:province":"Las Palmas",
    "wof:name":"Escrisam Fami S.l.",
    "wof:placetype":"venue"
},
  "geometry": {"coordinates":[-15.3892221451,27.9076957703],"type":"Point"}
}