{
  "type": "Feature",
  "properties": {
    "iso:country":"ES",
    "sg:address":"El Ferrocarril, 4",
    "sg:city":"Camas",
    "sg:orig_category":"Gastronom\u00cda: Especialidades Regionales Y Extranjeras (producci\u00d3n, Al Por Mayor)",
    "sg:phone":"+34 954 39 57 62",
    "sg:postcode":"41900",
    "sg:province":"Sevilla",
    "wof:name":"Reina Cantizano Maria Angeles",
    "wof:placetype":"venue"
},
  "geometry": {"coordinates":[-6.0368289948,37.4029541016],"type":"Point"}
}