{
  "type": "Feature",
  "properties": {
    "iso:country":"ES",
    "sg:address":"Calle de Espoz Y Mina, 1",
    "sg:city":"Alacant",
    "sg:orig_category":"Asesor\u00cda Fiscal Y Jur\u00cddica",
    "sg:phone":"+34 965 20 40 77",
    "sg:postcode":"03012",
    "sg:province":"Alicante",
    "wof:name":"Molla Azorin Josefina",
    "wof:placetype":"venue"
},
  "geometry": {"coordinates":[-0.483096987,38.3528823853],"type":"Point"}
}