{
  "type": "Feature",
  "properties": {
    "iso:country":"ES",
    "sg:address":"Calle de Olimpiadas, 8",
    "sg:city":"Coca",
    "sg:orig_category":"Empresas De Carpinter\u00cda",
    "sg:phone":"+34 921 58 65 38",
    "sg:postcode":"40480",
    "sg:province":"Segovia",
    "wof:name":"Garcia Garcia Jose Antonio",
    "wof:placetype":"venue"
},
  "geometry": {"coordinates":[-4.5231590271,41.2097358704],"type":"Point"}
}