{
  "type": "Feature",
  "properties": {
    "addr:full":"Partida Collets, S/n Pe\u00f1arroya Tastavins Teruel 44709",
    "addr:housenumber":"s",
    "addr:postcode":"44709",
    "addr:street":"Partida Collets;/ N Pen\u0303Arroya",
    "iso:country":"ES",
    "sg:address":"Partida Collets, S/n",
    "sg:city":"Pe\u00f1arroya Tastavins",
    "sg:orig_category":"Agricultores, Agricultores",
    "sg:phone":"+34 978 76 90 06",
    "sg:postcode":"44709",
    "sg:province":"Teruel",
    "wof:name":"Granja Collets S.l.",
    "wof:placetype":"venue"
},
  "geometry": {"coordinates":[-1.1069096327,40.3441085815],"type":"Point"}
}