{
  "type": "Feature",
  "properties": {
    "iso:country":"ES",
    "sg:address":"Calle de I\u00d1aki Deuna, 3",
    "sg:city":"Ondarroa",
    "sg:orig_category":"Molduras, Junquillos, Listones Y Molduras Perforadas",
    "sg:phone":"+34 946 83 00 97",
    "sg:postcode":"48700",
    "sg:province":"Vizcaya",
    "wof:name":"Urruzuno Argoitia Maria Carmen",
    "wof:placetype":"venue"
},
  "geometry": {"coordinates":[-2.424519062,43.3203468323],"type":"Point"}
}