{
  "type": "Feature",
  "properties": {
    "iso:country":"ES",
    "sg:address":"Calle de Zaragoza, 1",
    "sg:city":"Linea De La Concepcion",
    "sg:orig_category":"Ense\u00d1anza, Formaci\u00d3n Profesional: Aprendizaje",
    "sg:phone":"+34 956 17 04 04",
    "sg:postcode":"11300",
    "sg:province":"C\u00e1diz",
    "wof:name":"Servicio Andaluz De Empleo",
    "wof:placetype":"venue"
},
  "geometry": {"coordinates":[-5.3475899696,36.1639556885],"type":"Point"}
}