{
  "type": "Feature",
  "properties": {
    "addr:full":"Pase Salamanca, 29 Le\u00f3n Le\u00f3n 24009",
    "addr:housenumber":"29",
    "addr:postcode":"24009",
    "addr:street":"Salamanca;Leo\u0301N",
    "iso:country":"ES",
    "sg:address":"Pase Salamanca, 29",
    "sg:city":"Le\u00f3n",
    "sg:orig_category":"Arquitectos",
    "sg:phone":"+34 987 27 18 27",
    "sg:postcode":"24009",
    "sg:province":"Le\u00f3n",
    "wof:name":"Gutierrez Casta\u00f1on Jose",
    "wof:placetype":"venue"
},
  "geometry": {"coordinates":[-5.5932388306,42.5811233521],"type":"Point"}
}