{
  "type": "Feature",
  "properties": {
    "addr:full":"Calle de Rosario, 36 Albacete Albacete 02001",
    "addr:housenumber":"36",
    "addr:postcode":"02001",
    "addr:street":"Calle De Rosario",
    "iso:country":"ES",
    "sg:address":"Calle de Rosario, 36",
    "sg:city":"Albacete",
    "sg:orig_category":"Cl\u00cdnicas Dentales",
    "sg:phone":"+34 967 22 22 42",
    "sg:postcode":"02001",
    "sg:province":"Albacete",
    "wof:name":"Gotor Carrilero Joaquin",
    "wof:placetype":"venue"
},
  "geometry": {"coordinates":[-1.8577510118,38.9928436279],"type":"Point"}
}