{
  "type": "Feature",
  "properties": {
    "addr:full":"Las Molineras, 20 Las Molineras Granada 18810",
    "addr:housenumber":"20",
    "addr:postcode":"18810",
    "addr:street":"Molineras",
    "iso:country":"ES",
    "sg:address":"Las Molineras, 20",
    "sg:city":"Las Molineras",
    "sg:orig_category":"Producci\u00d3n, Venta De Productos De Agricultura Biol\u00d3gica",
    "sg:phone":"+34 958 34 22 37",
    "sg:postcode":"18810",
    "sg:province":"Granada",
    "wof:name":"Casta\u00f1o Garcia Juan Antonio",
    "wof:placetype":"venue"
},
  "geometry": {"coordinates":[-2.7215490341,37.4435958862],"type":"Point"}
}