{
  "type": "Feature",
  "properties": {
    "iso:country":"ES",
    "sg:address":"D Poligono, S/n",
    "sg:city":"Soria",
    "sg:orig_category":"Veh\u00cdculos De Ocasi\u00d3n",
    "sg:phone":"+34 975 23 22 03",
    "sg:postcode":"42005",
    "sg:province":"Soria",
    "wof:name":"Rodatam Carrasco S.l.",
    "wof:placetype":"venue"
},
  "geometry": {"coordinates":[-2.4691669941,41.7646598816],"type":"Point"}
}