{
  "type": "Feature",
  "properties": {
    "addr:full":"Calle de Concha General, 19 Bilbao Vizcaya 48010",
    "addr:housenumber":"19",
    "addr:postcode":"48010",
    "addr:street":"Calle De Concha General",
    "iso:country":"ES",
    "sg:address":"Calle de Concha General, 19",
    "sg:city":"Bilbao",
    "sg:orig_category":"Edici\u00d3n De Diarios, Revistas, Boletines",
    "sg:phone":"+34 944 43 71 19",
    "sg:postcode":"48010",
    "sg:province":"Vizcaya",
    "wof:name":"Servicio Propiedad Inmobiliaria S. L.",
    "wof:placetype":"venue"
},
  "geometry": {"coordinates":[-2.9350209236,43.2586402893],"type":"Point"}
}