{
  "type": "Feature",
  "properties": {
    "addr:full":"Calle de Hiedra, 7 Madrid Madrid 28036",
    "addr:housenumber":"7",
    "addr:postcode":"madrid;28036",
    "addr:street":"Calle De Hiedra",
    "iso:country":"ES",
    "sg:address":"Calle de Hiedra, 7",
    "sg:city":"Madrid",
    "sg:orig_category":"Caf\u00c9s, Bares, Cervecer\u00cdas",
    "sg:phone":"+34 913 15 52 83",
    "sg:postcode":"28036",
    "sg:province":"Madrid",
    "wof:name":"Novo Res S.l.",
    "wof:placetype":"venue"
},
  "geometry": {"coordinates":[-3.682446003,40.4696464539],"type":"Point"}
}