{
  "type": "Feature",
  "properties": {
    "iso:country":"ES",
    "sg:address":"A. Alomar, S/n",
    "sg:city":"Cala Rajada",
    "sg:orig_category":"Hoteles",
    "sg:phone":"+34 971 56 59 66",
    "sg:postcode":"07590",
    "sg:province":"Islas Baleares",
    "wof:name":"Hostal Gili S.l.",
    "wof:placetype":"venue"
},
  "geometry": {"coordinates":[3.4608900547,39.7104988098],"type":"Point"}
}