{
  "type": "Feature",
  "properties": {
    "addr:full":"Calle de Libertad, 15 Cigales Valladolid 47270",
    "addr:housenumber":"15",
    "addr:postcode":"47270",
    "addr:street":"Calle De Libertad",
    "iso:country":"ES",
    "sg:address":"Calle de Libertad, 15",
    "sg:city":"Cigales",
    "sg:orig_category":"Alimentaci\u00d3n General (al Por Menor)",
    "sg:phone":"+34 983 58 05 56",
    "sg:postcode":"47270",
    "sg:province":"Valladolid",
    "wof:name":"Miguel Racimo Maria De Los Angeles",
    "wof:placetype":"venue"
},
  "geometry": {"coordinates":[-4.7019171715,41.7565116882],"type":"Point"}
}