{
  "type": "Feature",
  "properties": {
    "iso:country":"ES",
    "sg:address":"Avda Azabache, 10",
    "sg:city":"Cordoba",
    "sg:orig_category":"Aguas (distribuci\u00d3n, Servicios)",
    "sg:phone":"+34 957 43 62 40",
    "sg:postcode":"14014",
    "sg:province":"C\u00f3rdoba",
    "wof:name":"Empresa Municipal De Aguas De Cordoba S.a.",
    "wof:placetype":"venue"
},
  "geometry": {"coordinates":[-4.7497839928,37.8872909546],"type":"Point"}
}