{
  "type": "Feature",
  "properties": {
    "iso:country":"ES",
    "sg:address":"Carrer de Esteve Albert, 32",
    "sg:city":"Mataro",
    "sg:orig_category":"Centros Empresariales",
    "sg:phone":"+34 937 57 19 39",
    "sg:postcode":"08304",
    "sg:province":"Barcelona",
    "wof:name":"Franiluro S.l.",
    "wof:placetype":"venue"
},
  "geometry": {"coordinates":[2.4345309734,41.5437507629],"type":"Point"}
}