{
  "type": "Feature",
  "properties": {
    "addr:full":"Carrer de Berga, 16 Olost Barcelona 08516",
    "addr:housenumber":"16",
    "addr:postcode":"08516",
    "addr:street":"Carrer De Berga",
    "iso:country":"ES",
    "sg:address":"Carrer de Berga, 16",
    "sg:city":"Olost",
    "sg:orig_category":"Costureras",
    "sg:phone":"+34 938 88 01 72",
    "sg:postcode":"08516",
    "sg:province":"Barcelona",
    "wof:name":"Pons Culell Maria Del Carmen",
    "wof:placetype":"venue"
},
  "geometry": {"coordinates":[-97.78224945069999,45.7040786743],"type":"Point"}
}