{
  "type": "Feature",
  "properties": {
    "addr:full":"Carrer de Guadalhorce, 15 Terrassa Barcelona 08223",
    "addr:housenumber":"15",
    "addr:postcode":"08223",
    "addr:street":"Carrer De Guadalhorce",
    "iso:country":"ES",
    "sg:address":"Carrer de Guadalhorce, 15",
    "sg:city":"Terrassa",
    "sg:orig_category":"Asesor\u00cda De Formaci\u00d3n Y Gesti\u00d3n De Personal",
    "sg:phone":"+34 937 86 18 64",
    "sg:postcode":"08223",
    "sg:province":"Barcelona",
    "wof:name":"Arribas Carrasco Jose",
    "wof:placetype":"venue"
},
  "geometry": {"coordinates":[2.0271661282,41.5532989502],"type":"Point"}
}