{
  "type": "Feature",
  "properties": {
    "iso:country":"ES",
    "sg:address":"Calle de Misericordia, 5",
    "sg:city":"Ajalvir",
    "sg:orig_category":"Ebanister\u00cda",
    "sg:phone":"+34 918 84 35 72",
    "sg:postcode":"28864",
    "sg:province":"Madrid",
    "wof:name":"Gonzalez De La Cueva Juan Antonio",
    "wof:placetype":"venue"
},
  "geometry": {"coordinates":[-3.4847300053,40.5327224731],"type":"Point"}
}