{
  "type": "Feature",
  "properties": {
    "iso:country":"ES",
    "sg:address":"Calle de Padre Vitoria, 8",
    "sg:city":"Ciudad Rodrigo",
    "sg:orig_category":"Plomeros",
    "sg:phone":"+34 923 46 25 62",
    "sg:postcode":"37500",
    "sg:province":"Salamanca",
    "wof:name":"Martin Gomez Carlos",
    "wof:placetype":"venue"
},
  "geometry": {"coordinates":[-6.5275988579,40.6047515869],"type":"Point"}
}