{
  "type": "Feature",
  "properties": {
    "iso:country":"ES",
    "sg:address":"Donostia Ibilbidea, 104",
    "sg:city":"Astigarraga",
    "sg:orig_category":"Motocicletas (agentes, Concesionarios)",
    "sg:phone":"+34 943 33 34 79",
    "sg:postcode":"20115",
    "sg:province":"Guip\u00f9zcoa",
    "wof:name":"Sancha Perez Evaristo",
    "wof:placetype":"venue"
},
  "geometry": {"coordinates":[-1.9527029991,43.2826042175],"type":"Point"}
}