{
  "type": "Feature",
  "properties": {
    "iso:country":"ES",
    "sg:address":"Calle de Aurora, 11",
    "sg:city":"Zaragoza",
    "sg:orig_category":"Electromec\u00c1nica",
    "sg:phone":"+34 976 47 09 49",
    "sg:postcode":"50014",
    "sg:province":"Zaragoza",
    "wof:name":"Paricio Calvo Santiago",
    "wof:placetype":"venue"
},
  "geometry": {"coordinates":[-0.864282608,41.6638717651],"type":"Point"}
}