{
  "type": "Feature",
  "properties": {
    "addr:full":"Av Meridiana, 272 Barcelona Barcelona 08027",
    "addr:housenumber":"272",
    "addr:postcode":"08027",
    "addr:street":"Meridiana",
    "iso:country":"ES",
    "sg:address":"Av Meridiana, 272",
    "sg:city":"Barcelona",
    "sg:orig_category":"Laboratorios Y Trabajos De Fotograf\u00cda, V\u00cddeo Y Cine",
    "sg:phone":"+34 933 49 36 83",
    "sg:postcode":"08027",
    "sg:province":"Barcelona",
    "sg:website":"www.fotoprix.es",
    "wof:name":"Fotoprix S.a.",
    "wof:placetype":"venue"
},
  "geometry": {"coordinates":[2.186686039,41.4224472046],"type":"Point"}
}