{
  "type": "Feature",
  "properties": {
    "iso:country":"ES",
    "sg:address":"Calle de General Elorza, 75",
    "sg:city":"Oviedo",
    "sg:orig_category":"Grafistas",
    "sg:phone":"+34 985 21 52 91",
    "sg:postcode":"33002",
    "sg:province":"Asturias",
    "sg:website":"www.evohe.net",
    "wof:name":"Evohe Dise\u00f1o Y Distribuciones S.l.",
    "wof:placetype":"venue"
},
  "geometry": {"coordinates":[-5.8478193283,43.3669128418],"type":"Point"}
}