{
  "type": "Feature",
  "properties": {
    "iso:country":"ES",
    "sg:address":"Carrer de Benidorm, 7",
    "sg:city":"Reus",
    "sg:orig_category":"Empresas De Pintura Y Revestimientos",
    "sg:phone":"+34 977 75 38 52",
    "sg:postcode":"43205",
    "sg:province":"Tarragona",
    "wof:name":"Gala Torres Fausto",
    "wof:placetype":"venue"
},
  "geometry": {"coordinates":[1.1081809998,41.1471481323],"type":"Point"}
}