{
  "type": "Feature",
  "properties": {
    "iso:country":"ES",
    "sg:address":"Calle de Peruchal (la), 1",
    "sg:city":"Villablino",
    "sg:orig_category":"Fabrica De Charcuter\u00cda",
    "sg:phone":"+34 987 47 06 24",
    "sg:postcode":"24100",
    "sg:province":"Le\u00f3n",
    "wof:name":"Hernandez Alonso Jose",
    "wof:placetype":"venue"
},
  "geometry": {"coordinates":[-6.3153171539,42.9375839233],"type":"Point"}
}