{
  "type": "Feature",
  "properties": {
    "iso:country":"ES",
    "sg:address":"Calle de Chalanes, 7",
    "sg:city":"Valdepe\u00f1as",
    "sg:orig_category":"Contenedores (mercanc\u00cdas)",
    "sg:phone":"+34 926 32 21 86",
    "sg:postcode":"13300",
    "sg:province":"Ciudad Real",
    "wof:name":"Clemente Sanchez Antonio",
    "wof:placetype":"venue"
},
  "geometry": {"coordinates":[-3.3764090538,38.7571907043],"type":"Point"}
}