{
  "type": "Feature",
  "properties": {
    "addr:full":"Calle de Jose Maria Ligues, 5 Cintruenigo Navarra 31592",
    "addr:housenumber":"5",
    "addr:postcode":"31592",
    "addr:street":"Calle De Jose Maria Ligues",
    "iso:country":"ES",
    "sg:address":"Calle de Jose Maria Ligues, 5",
    "sg:city":"Cintruenigo",
    "sg:orig_category":"Promotores Constructores",
    "sg:phone":"+34 948 81 21 83",
    "sg:postcode":"31592",
    "sg:province":"Navarra",
    "sg:website":"www.casaverde-ti.com",
    "wof:name":"Casaverde Tecnicas Inmobiliarias",
    "wof:placetype":"venue"
},
  "geometry": {"coordinates":[-1.8064659834,42.0815467834],"type":"Point"}
}