{
  "type": "Feature",
  "properties": {
    "addr:full":"Calle de Fuente Carrantona, 33 Madrid Madrid 28030",
    "addr:housenumber":"33",
    "addr:postcode":"madrid;28030",
    "addr:street":"Calle De Fuente Carrantona",
    "iso:country":"ES",
    "sg:address":"Calle de Fuente Carrantona, 33",
    "sg:city":"Madrid",
    "sg:orig_category":"Guarder\u00cdas",
    "sg:phone":"+34 913 71 32 04",
    "sg:postcode":"28030",
    "sg:province":"Madrid",
    "wof:name":"Escuela Infantil Lago Como S.l.",
    "wof:placetype":"venue"
},
  "geometry": {"coordinates":[-3.6311230659,40.408416748],"type":"Point"}
}