{
  "type": "Feature",
  "properties": {
    "iso:country":"ES",
    "sg:address":"Carr Pare Gari, 48",
    "sg:city":"Vilanova I La Geltru",
    "sg:orig_category":"Peluquer\u00cdas, Peluquer\u00cda Mixta",
    "sg:phone":"+34 938 14 58 91",
    "sg:postcode":"08800",
    "sg:province":"Barcelona",
    "wof:name":"Guillen Gaona Sara",
    "wof:placetype":"venue"
},
  "geometry": {"coordinates":[1.7211500406,41.2228813171],"type":"Point"}
}