{
  "type": "Feature",
  "properties": {
    "addr:full":"Calle de Kadagua, 19 San Vicente De Barakaldo Vizcaya 48903",
    "addr:housenumber":"19",
    "addr:postcode":"48903",
    "addr:street":"Calle De Kadagua",
    "iso:country":"ES",
    "sg:address":"Calle de Kadagua, 19",
    "sg:city":"San Vicente De Barakaldo",
    "sg:orig_category":"Molduras, Junquillos, Listones Y Molduras Perforadas",
    "sg:phone":"+34 944 99 30 96",
    "sg:postcode":"48903",
    "sg:province":"Vizcaya",
    "wof:name":"Fernandez Alvarez Rosario",
    "wof:placetype":"venue"
},
  "geometry": {"coordinates":[-2.9789559841,43.2733230591],"type":"Point"}
}