{
  "type": "Feature",
  "properties": {
    "iso:country":"ES",
    "sg:address":"Calle de Rey Mudaffar, 1",
    "sg:city":"Badajoz",
    "sg:orig_category":"Laboratorios Y Cl\u00cdnicas Veterinarias",
    "sg:phone":"+34 924 27 36 23",
    "sg:postcode":"06006",
    "sg:province":"Badajoz",
    "wof:name":"Zamajon Lizarralde Javier",
    "wof:placetype":"venue"
},
  "geometry": {"coordinates":[-6.9815988541,38.8871612549],"type":"Point"}
}