{
  "type": "Feature",
  "properties": {
    "addr:full":"Calle de Bonillo (el), 31 Socuellamos Ciudad Real 13630",
    "addr:housenumber":"31",
    "addr:postcode":"13630",
    "addr:street":"Calle De Bonillo El",
    "iso:country":"ES",
    "sg:address":"Calle de Bonillo (el), 31",
    "sg:city":"Socuellamos",
    "sg:orig_category":"Transportes Por V\u00cdas Navegables",
    "sg:phone":"+34 926 53 00 69",
    "sg:postcode":"13630",
    "sg:province":"Ciudad Real",
    "wof:name":"Albi\u00f1ana Garcia Salvador",
    "wof:placetype":"venue"
},
  "geometry": {"coordinates":[-2.7875742912,39.2819366455],"type":"Point"}
}