{
  "type": "Feature",
  "properties": {
    "addr:full":"Calle de Sevilla, 93 Jimena Frontera C\u00e1diz 11330",
    "addr:housenumber":"93",
    "addr:postcode":"11330",
    "addr:street":"Calle De Sevilla",
    "iso:country":"ES",
    "sg:address":"Calle de Sevilla, 93",
    "sg:city":"Jimena Frontera",
    "sg:orig_category":"Sindicatos De Trabajadores",
    "sg:phone":"+34 956 64 10 81",
    "sg:postcode":"11330",
    "sg:province":"C\u00e1diz",
    "wof:name":"Union General De Trabajadores",
    "wof:placetype":"venue"
},
  "geometry": {"coordinates":[-5.4539427757,36.4352836609],"type":"Point"}
}