{
  "type": "Feature",
  "properties": {
    "addr:full":"Calle de Leopoldo Lugones, 3 Malaga M\u00e1laga 29004",
    "addr:housenumber":"3",
    "addr:postcode":"29004",
    "addr:street":"Calle De Leopoldo Lugones;Ma\u0301Laga",
    "iso:country":"ES",
    "sg:address":"Calle de Leopoldo Lugones, 3",
    "sg:city":"Malaga",
    "sg:orig_category":"Mudanzas",
    "sg:phone":"+34 952 24 63 66",
    "sg:postcode":"29004",
    "sg:province":"M\u00e1laga",
    "sg:website":"www.apex-es.com/lorena",
    "wof:name":"Luna Gonzalez Cristobal",
    "wof:placetype":"venue"
},
  "geometry": {"coordinates":[-4.4897580147,36.6935005188],"type":"Point"}
}