{
  "type": "Feature",
  "properties": {
    "iso:country":"ES",
    "sg:address":"Calle de Malaga, 2",
    "sg:city":"Pizarra",
    "sg:classifiers":[
        {
            "category":"Taxi",
            "type":"Transportation"
        }
    ],
    "sg:phone":"+34 952 48 31 75",
    "sg:postcode":"29560",
    "sg:province":"M\u00e1laga",
    "wof:name":"Cantarero Montero Joaquin",
    "wof:placetype":"venue"
},
  "geometry": {"coordinates":[-4.7073187828,36.7670288086],"type":"Point"}
}