{
  "type": "Feature",
  "properties": {
    "addr:full":"Ctra Marbella (de), S/n Coin M\u00e1laga 29100",
    "addr:postcode":"29100",
    "addr:street":"Ctra Marbella De S / N Coin Ma\u0301Laga",
    "iso:country":"ES",
    "sg:address":"Ctra Marbella (de), S/n",
    "sg:city":"Coin",
    "sg:orig_category":"Discapacitados",
    "sg:phone":"+34 952 45 17 95",
    "sg:postcode":"29100",
    "sg:province":"M\u00e1laga",
    "wof:name":"Asociacion Padres Ni\u00f1os Subnormales Coin Y Comarca",
    "wof:placetype":"venue"
},
  "geometry": {"coordinates":[-4.7625985146,36.6561126709],"type":"Point"}
}