{
  "type": "Feature",
  "properties": {
    "addr:full":"Avda Libertad De La, 30 Blimea Asturias 33960",
    "addr:housenumber":"30",
    "addr:postcode":"33960",
    "addr:street":"Avda Libertad De La;Asturias",
    "iso:country":"ES",
    "sg:address":"Avda Libertad De La, 30",
    "sg:city":"Blimea",
    "sg:orig_category":"Supermercados Y Hipermercados",
    "sg:phone":"+34 985 65 76 13",
    "sg:postcode":"33960",
    "sg:province":"Asturias",
    "wof:name":"Alimerka S.a.",
    "wof:placetype":"venue"
},
  "geometry": {"coordinates":[-5.5890450478,43.2727622986],"type":"Point"}
}