{
  "type": "Feature",
  "properties": {
    "addr:full":"Calle de Madre Soledad Torres Acosta, 7 Jaen Ja\u00e9n 23001",
    "addr:housenumber":"7;jae\u0301n",
    "addr:postcode":"23001",
    "addr:street":"Calle De Madre Soledad Torres Acosta",
    "iso:country":"ES",
    "sg:address":"Calle de Madre Soledad Torres Acosta, 7",
    "sg:city":"Jaen",
    "sg:orig_category":"Arquitectos",
    "sg:phone":"+34 953 24 01 16",
    "sg:postcode":"23001",
    "sg:province":"Ja\u00e9n",
    "wof:name":"Ca\u00f1ada Dorado Antonio Javier",
    "wof:placetype":"venue"
},
  "geometry": {"coordinates":[-3.7888588905,37.7689743042],"type":"Point"}
}