{
  "type": "Feature",
  "properties": {
    "iso:country":"ES",
    "sg:address":"Calle de Capitan Cortes, 48",
    "sg:city":"Sabiote",
    "sg:orig_category":"Carnicer\u00cdas, Carnicer\u00cdas",
    "sg:phone":"+34 953 77 40 47",
    "sg:postcode":"23410",
    "sg:province":"Ja\u00e9n",
    "wof:name":"Carniceria Pachin S.l.",
    "wof:placetype":"venue"
},
  "geometry": {"coordinates":[-3.3116390705,38.0681915283],"type":"Point"}
}