{
  "type": "Feature",
  "properties": {
    "iso:country":"ES",
    "sg:address":"Calle de Nueva, 28",
    "sg:city":"Elda",
    "sg:classifiers":[
        {
            "category":"Casinos & Gambling",
            "type":"Entertainment"
        }
    ],
    "sg:phone":"+34 965 38 09 80",
    "sg:postcode":"03600",
    "sg:province":"Alicante",
    "sg:tags":[
        "locale",
        "de",
        "juego"
    ],
    "wof:name":"Casino Eldense",
    "wof:placetype":"venue"
},
  "geometry": {"coordinates":[-0.7978389859,38.4774589539],"type":"Point"}
}