{
  "type": "Feature",
  "properties": {
    "addr:full":"Pase Urgoiti, 3 Arrigorriaga Vizcaya 48480",
    "addr:housenumber":"3",
    "addr:postcode":"48480",
    "addr:street":"Urgoiti",
    "iso:country":"ES",
    "sg:address":"Pase Urgoiti, 3",
    "sg:city":"Arrigorriaga",
    "sg:orig_category":"Ense\u00d1anza: Idiomas",
    "sg:phone":"+34 946 71 40 76",
    "sg:postcode":"48480",
    "sg:province":"Vizcaya",
    "wof:name":"Euskaraz Koop. E.",
    "wof:placetype":"venue"
},
  "geometry": {"coordinates":[-2.8884301186,43.2120018005],"type":"Point"}
}