{
  "type": "Feature",
  "properties": {
    "addr:full":"Calle de Cabo Carmona Chamizo, 94 Alcolea C\u00f3rdoba 14610",
    "addr:housenumber":"94",
    "addr:postcode":"14610",
    "addr:street":"Calle De Cabo Carmona Chamizo",
    "iso:country":"ES",
    "sg:address":"Calle de Cabo Carmona Chamizo, 94",
    "sg:city":"Alcolea",
    "sg:orig_category":"Alimentaci\u00d3n General (al Por Menor)",
    "sg:phone":"+34 957 32 01 67",
    "sg:postcode":"14610",
    "sg:province":"C\u00f3rdoba",
    "wof:name":"Velasco Moreno Carmen",
    "wof:placetype":"venue"
},
  "geometry": {"coordinates":[-4.6696691513,37.933380127],"type":"Point"}
}