{
  "type": "Feature",
  "properties": {
    "addr:full":"Juan Casta\u00f1eda(vaguada), 18 Cartagena Murcia 30393",
    "addr:housenumber":"18",
    "addr:postcode":"30393",
    "addr:street":"Juan Castan\u0303Eda Vaguada",
    "iso:country":"ES",
    "sg:address":"Juan Casta\u00f1eda(vaguada), 18",
    "sg:city":"Cartagena",
    "sg:orig_category":"Reposter\u00cdas",
    "sg:phone":"+34 968 31 58 00",
    "sg:postcode":"30393",
    "sg:province":"Murcia",
    "wof:name":"Panaderia Casablanca S.l.",
    "wof:placetype":"venue"
},
  "geometry": {"coordinates":[-1.0207890272,37.6163482666],"type":"Point"}
}