{
  "type": "Feature",
  "properties": {
    "addr:full":"Calle de Pergolesi, 19 Malaga M\u00e1laga 29016",
    "addr:housenumber":"19",
    "addr:postcode":"29016",
    "addr:street":"Calle De Pergolesi;Ma\u0301Laga",
    "iso:country":"ES",
    "sg:address":"Calle de Pergolesi, 19",
    "sg:city":"Malaga",
    "sg:orig_category":"M\u00c9dicos: Cirug\u00cda Ortop\u00c9dica Y Traumatolog\u00cda",
    "sg:phone":"+34 952 20 12 72",
    "sg:postcode":"29016",
    "sg:province":"M\u00e1laga",
    "wof:name":"Traumagil S.l.",
    "wof:placetype":"venue"
},
  "geometry": {"coordinates":[-4.3873348236,36.7270545959],"type":"Point"}
}