{
  "type": "Feature",
  "properties": {
    "addr:full":"Rua Calvo Sotelo, 34 Sarria Lugo 27600",
    "addr:housenumber":"34",
    "addr:postcode":"27600",
    "addr:street":"Rua Calvo Sotelo",
    "iso:country":"ES",
    "sg:address":"Rua Calvo Sotelo, 34",
    "sg:city":"Sarria",
    "sg:orig_category":"Mec\u00c1nico Del Autom\u00d3vil",
    "sg:phone":"+34 982 53 23 73",
    "sg:postcode":"27600",
    "sg:province":"Lugo",
    "wof:name":"Lousao S.l.",
    "wof:placetype":"venue"
},
  "geometry": {"coordinates":[-7.4162240028,42.7821578979],"type":"Point"}
}