{
  "type": "Feature",
  "properties": {
    "addr:full":"Rua Roldan, 9 Betanzos La Coru\u00f1a 15300",
    "addr:housenumber":"9",
    "addr:postcode":"15300",
    "addr:street":"Rua Roldan;La",
    "iso:country":"ES",
    "sg:address":"Rua Roldan, 9",
    "sg:city":"Betanzos",
    "sg:orig_category":"Inmobiliaria (agencias)",
    "sg:phone":"+34 981 77 36 88",
    "sg:postcode":"15300",
    "sg:province":"La Coru\u00f1a",
    "wof:name":"Inmobiliaria Calvi\u00f1o S.l.",
    "wof:placetype":"venue"
},
  "geometry": {"coordinates":[-8.2115631104,43.2813873291],"type":"Point"}
}