{
  "type": "Feature",
  "properties": {
    "iso:country":"ES",
    "sg:address":"Avda Juan Melgarejo, S/n",
    "sg:city":"Costa Oeste",
    "sg:orig_category":"Inmobiliaria (agencias)",
    "sg:phone":"+34 956 85 48 57",
    "sg:postcode":"11500",
    "sg:province":"C\u00e1diz",
    "wof:name":"Aurovas S.l.",
    "wof:placetype":"venue"
},
  "geometry": {"coordinates":[-6.29240942,36.5299415588],"type":"Point"}
}