{
  "type": "Feature",
  "properties": {
    "iso:country":"ES",
    "sg:address":"Rbla Sant Domenec, 8",
    "sg:city":"Vic",
    "sg:orig_category":"Mutuas De Seguros",
    "sg:phone":"+34 938 81 46 44",
    "sg:postcode":"08500",
    "sg:province":"Barcelona",
    "wof:name":"Mutua General De Catalunya De Previsio Social",
    "wof:placetype":"venue"
},
  "geometry": {"coordinates":[2.2527220249,41.9274787903],"type":"Point"}
}