{
  "type": "Feature",
  "properties": {
    "iso:country":"ES",
    "sg:address":"Ptda Seniades, S/n",
    "sg:city":"Cullera",
    "sg:orig_category":"Cooperativas Agr\u00cdcolas",
    "sg:phone":"+34 961 72 66 32",
    "sg:postcode":"46400",
    "sg:province":"Valencia",
    "wof:name":"Sdad. Cullercoop. Coop.v.",
    "wof:placetype":"venue"
},
  "geometry": {"coordinates":[-0.2562240064,39.1653251648],"type":"Point"}
}