{
  "type": "Feature",
  "properties": {
    "iso:country":"ES",
    "sg:address":"Avda Mancha, 15",
    "sg:city":"Pozohondo",
    "sg:orig_category":"Pensiones Familiares",
    "sg:phone":"+34 967 20 50 56",
    "sg:postcode":"02141",
    "sg:province":"Albacete",
    "wof:name":"Saez Garcia Maria Carmen",
    "wof:placetype":"venue"
},
  "geometry": {"coordinates":[-1.9110770226,38.7189178467],"type":"Point"}
}