{
  "type": "Feature",
  "properties": {
    "addr:full":"Av. Pedro Vaquer, 26 Palmanova Islas Baleares 07181",
    "addr:housenumber":"26",
    "addr:postcode":"07181",
    "addr:street":"Av. Pedro Vaquer",
    "iso:country":"ES",
    "sg:address":"Av. Pedro Vaquer, 26",
    "sg:city":"Palmanova",
    "sg:orig_category":"Discotecas Y Salas De Baile",
    "sg:phone":"+34 971 13 52 27",
    "sg:postcode":"07181",
    "sg:province":"Islas Baleares",
    "wof:name":"Holmstrom  Nalle Wilhelm",
    "wof:placetype":"venue"
},
  "geometry": {"coordinates":[2.5657799244,39.5388221741],"type":"Point"}
}