{
  "type": "Feature",
  "properties": {
    "iso:country":"ES",
    "sg:address":"Calle de Granados, 112",
    "sg:city":"Azuqueca Henares",
    "sg:classifiers":[
        {
            "category":"Banks & Credit Unions",
            "subcategory":"Bureau De Change",
            "type":"Services"
        }
    ],
    "sg:phone":"+34 949 26 20 55",
    "sg:postcode":"19200",
    "sg:province":"Guadalajara",
    "sg:tags":[
        "organismos",
        "control"
    ],
    "wof:name":"Mellado Moreno Mario",
    "wof:placetype":"venue"
},
  "geometry": {"coordinates":[-3.2625188828,40.5785064697],"type":"Point"}
}