{
  "type": "Feature",
  "properties": {
    "iso:country":"ES",
    "sg:address":"Calle de Rio Deba, 3",
    "sg:city":"Donostia-san Sebastian",
    "sg:orig_category":"Tapicer\u00cdas",
    "sg:phone":"+34 943 27 18 50",
    "sg:postcode":"20012",
    "sg:province":"Guip\u00f9zcoa",
    "wof:name":"Aizpuru Macazaga Antonio",
    "wof:placetype":"venue"
},
  "geometry": {"coordinates":[-1.9689308405,43.3166809082],"type":"Point"}
}