{
  "type": "Feature",
  "properties": {
    "iso:country":"ES",
    "sg:address":"La Virgen, 11",
    "sg:city":"Ingenio",
    "sg:orig_category":"Asociaciones, Organismos Culturales Y Socioeducativos",
    "sg:phone":"+34 928 78 65 68",
    "sg:postcode":"35250",
    "sg:province":"Las Palmas",
    "wof:name":"Fundacion Blas Sanchez",
    "wof:placetype":"venue"
},
  "geometry": {"coordinates":[-15.4450712204,27.9204292297],"type":"Point"}
}