{
  "type": "Feature",
  "properties": {
    "addr:full":"Calle de Eguia General, 28 Bilbao Vizcaya 48010",
    "addr:housenumber":"28",
    "addr:postcode":"48010",
    "addr:street":"Calle De Eguia General",
    "iso:country":"ES",
    "sg:address":"Calle de Eguia General, 28",
    "sg:city":"Bilbao",
    "sg:orig_category":"Venta, Montaje De Neum\u00c1ticos",
    "sg:phone":"+34 944 10 27 22",
    "sg:postcode":"48010",
    "sg:province":"Vizcaya",
    "wof:name":"Neumaticos Vizcaya S.l.",
    "wof:placetype":"venue"
},
  "geometry": {"coordinates":[-2.9448020458,43.2590255737],"type":"Point"}
}