{
  "type": "Feature",
  "properties": {
    "iso:country":"ES",
    "sg:address":"Calle de Mieres, 17",
    "sg:city":"Gijon",
    "sg:orig_category":"Obras Y Organismos Sociales",
    "sg:phone":"+34 985 39 93 11",
    "sg:postcode":"33208",
    "sg:province":"Asturias",
    "wof:name":"Asociacion Gijonesa De Caridad",
    "wof:placetype":"venue"
},
  "geometry": {"coordinates":[-5.6657395363,43.5362625122],"type":"Point"}
}