{
  "type": "Feature",
  "properties": {
    "addr:full":"Calle de Bolivia, 56-58 Zaragoza Zaragoza 50010",
    "addr:housenumber":"56-58",
    "addr:postcode":"50010",
    "addr:street":"Calle De Bolivia",
    "iso:country":"ES",
    "sg:address":"Calle de Bolivia, 56-58",
    "sg:city":"Zaragoza",
    "sg:orig_category":"Ropa Para Beb\u00c9s Y Ni\u00d1os (confecci\u00d3n, Al Por Mayor)",
    "sg:phone":"+34 976 33 00 35",
    "sg:postcode":"50010",
    "sg:province":"Zaragoza",
    "wof:name":"Oliveros Juste Andres",
    "wof:placetype":"venue"
},
  "geometry": {"coordinates":[-0.900329113,41.6513328552],"type":"Point"}
}