{
  "type": "Feature",
  "properties": {
    "iso:country":"ES",
    "sg:address":"Ctra Castellon, Km. 0013,0",
    "sg:city":"Burgo Ebro",
    "sg:orig_category":"Producci\u00d3n, Venta De Productos De Agricultura Biol\u00d3gica",
    "sg:phone":"+34 976 10 50 01",
    "sg:postcode":"50730",
    "sg:province":"Zaragoza",
    "wof:name":"Explotaciones Agricolas Santa Ana S.a.",
    "wof:placetype":"venue"
},
  "geometry": {"coordinates":[-0.7429590225,41.5727653503],"type":"Point"}
}