{
  "type": "Feature",
  "properties": {
    "iso:country":"ES",
    "sg:address":"Ctra \u00d1ora (la), 22",
    "sg:city":"Arboleja",
    "sg:orig_category":"Arquitectos",
    "sg:phone":"+34 968 28 34 04",
    "sg:postcode":"30009",
    "sg:province":"Murcia",
    "wof:name":"Martinez Hernandez Joaquin",
    "wof:placetype":"venue"
},
  "geometry": {"coordinates":[-1.1460089684,37.9893379211],"type":"Point"}
}