{
  "type": "Feature",
  "properties": {
    "addr:full":"Sta Teresa Jornet, S/n Merida Badajoz 06800",
    "addr:housenumber":"s",
    "addr:postcode":"06800",
    "addr:street":"Sta Teresa Jornet;/ N",
    "iso:country":"ES",
    "sg:address":"Sta Teresa Jornet, S/n",
    "sg:city":"Merida",
    "sg:orig_category":"Tapicer\u00cdas",
    "sg:phone":"+34 924 31 22 00",
    "sg:postcode":"06800",
    "sg:province":"Badajoz",
    "wof:name":"Coraliza Lozano Francisco Jose",
    "wof:placetype":"venue"
},
  "geometry": {"coordinates":[-6.3415088654,38.911026001],"type":"Point"}
}