{
  "type": "Feature",
  "properties": {
    "iso:country":"ES",
    "sg:address":"Calle de Marques De Teverga, 8",
    "sg:city":"Oviedo",
    "sg:orig_category":"M\u00c9dicos: Estomatolog\u00cda",
    "sg:phone":"+34 985 23 03 64",
    "sg:postcode":"33005",
    "sg:province":"Asturias",
    "wof:name":"Alvarez Alvarez Luis",
    "wof:placetype":"venue"
},
  "geometry": {"coordinates":[-5.8554606438,43.3621444702],"type":"Point"}
}