{
  "type": "Feature",
  "properties": {
    "iso:country":"ES",
    "sg:address":"Carr Virgen De Los Dolores, 17",
    "sg:city":"Barrio De Los Dolores",
    "sg:orig_category":"Alquiler De Veh\u00cdculos: Turismos Y Utilitarios",
    "sg:phone":"+34 961 30 91 90",
    "sg:postcode":"46113",
    "sg:province":"Valencia",
    "wof:name":"Hertocar S.l.",
    "wof:placetype":"venue"
},
  "geometry": {"coordinates":[-0.3948760033,39.5549926758],"type":"Point"}
}