{
  "type": "Feature",
  "properties": {
    "addr:full":"Carrer de Lluis Puigjaner, 6 Olesa Montserrat Barcelona 08640",
    "addr:housenumber":"6",
    "addr:postcode":"08640",
    "addr:street":"Carrer De Lluis Puigjaner;Barcelona",
    "iso:country":"ES",
    "sg:address":"Carrer de Lluis Puigjaner, 6",
    "sg:city":"Olesa Montserrat",
    "sg:orig_category":"Frutas, Legumbres Frescas Y Tempranas (al Por Menor)",
    "sg:phone":"+34 937 78 11 62",
    "sg:postcode":"08640",
    "sg:province":"Barcelona",
    "wof:name":"Campos Sarroca Maria Angeles",
    "wof:placetype":"venue"
},
  "geometry": {"coordinates":[1.8962249756,41.5419998169],"type":"Point"}
}