{
  "type": "Feature",
  "properties": {
    "addr:full":"Calle de Marcial, 7 Calatayud Zaragoza 50300",
    "addr:housenumber":"7",
    "addr:postcode":"50300",
    "addr:street":"Calle De Marcial",
    "iso:country":"ES",
    "sg:address":"Calle de Marcial, 7",
    "sg:city":"Calatayud",
    "sg:orig_category":"Telas Y Sedas (al Por Menor)",
    "sg:phone":"+34 976 88 43 02",
    "sg:postcode":"50300",
    "sg:province":"Zaragoza",
    "wof:name":"Cabello Andres Rosa Maria",
    "wof:placetype":"venue"
},
  "geometry": {"coordinates":[-1.6428309679,41.3533096313],"type":"Point"}
}