{
  "type": "Feature",
  "properties": {
    "addr:full":"Plaz Constitucion (la), 9 Icod De Los Vinos Santa Cruz De Tenerife 38430",
    "addr:housenumber":"9",
    "addr:postcode":"38430",
    "addr:street":"Constitucion La",
    "iso:country":"ES",
    "sg:address":"Plaz Constitucion (la), 9",
    "sg:city":"Icod De Los Vinos",
    "sg:orig_category":"Quincaller\u00cda (al Por Menor)",
    "sg:phone":"+34 922 81 07 81",
    "sg:postcode":"38430",
    "sg:province":"Santa Cruz De Tenerife",
    "wof:name":"Herederos Gregorio Socas Delgado C.b.",
    "wof:placetype":"venue"
},
  "geometry": {"coordinates":[-16.7204761505,28.3677654266],"type":"Point"}
}