{
  "type": "Feature",
  "properties": {
    "addr:full":"Calle de Goya (urb Casablanca), 3 Marbella M\u00e1laga 29600",
    "addr:housenumber":"3",
    "addr:postcode":"29600",
    "addr:street":"Calle De Goya Urb Casablanca;Ma\u0301Laga",
    "iso:country":"ES",
    "sg:address":"Calle de Goya (urb Casablanca), 3",
    "sg:city":"Marbella",
    "sg:orig_category":"Fabricaci\u00d3n, Distribuci\u00d3n De Discos, V\u00cddeodiscos Y Musicassettes",
    "sg:phone":"+34 952 82 26 46",
    "sg:postcode":"29600",
    "sg:province":"M\u00e1laga",
    "wof:name":"Castells Girard Tania",
    "wof:placetype":"venue"
},
  "geometry": {"coordinates":[-4.9098958969,36.5092658997],"type":"Point"}
}