{
  "type": "Feature",
  "properties": {
    "addr:full":"Avda Tres Cruces, 1 Valencia Valencia 46...",
    "addr:housenumber":"1",
    "addr:street":"Avda Tres Cruces;Valencia",
    "iso:country":"ES",
    "sg:address":"Avda Tres Cruces, 1",
    "sg:city":"Valencia",
    "sg:orig_category":"Hospitales",
    "sg:phone":"+34 961 97 20 00",
    "sg:postcode":"46...",
    "sg:province":"Valencia",
    "wof:name":"Consorcio Hospital General Universitario De Valencia",
    "wof:placetype":"venue"
},
  "geometry": {"coordinates":[-0.4039700031,39.4598846436],"type":"Point"}
}