{
  "type": "Feature",
  "properties": {
    "iso:country":"ES",
    "sg:address":"Calle de Correo, 18",
    "sg:city":"Bilbao",
    "sg:orig_category":"Confecci\u00d3n De Trajes Para Se\u00d1oras",
    "sg:phone":"+34 944 15 01 40",
    "sg:postcode":"48005",
    "sg:province":"Vizcaya",
    "wof:name":"Gorbea Gorbea Jose Miguel",
    "wof:placetype":"venue"
},
  "geometry": {"coordinates":[-2.9235403538,43.2579803467],"type":"Point"}
}