{
  "type": "Feature",
  "properties": {
    "addr:full":"Carrer de Formentera, 9 Barcelona Barcelona 08016",
    "addr:housenumber":"9",
    "addr:postcode":"08016",
    "addr:street":"Carrer De Formentera",
    "iso:country":"ES",
    "sg:address":"Carrer de Formentera, 9",
    "sg:city":"Barcelona",
    "sg:orig_category":"Empresas De Carpinter\u00cda De Madera",
    "sg:phone":"+34 933 50 51 95",
    "sg:postcode":"08016",
    "sg:province":"Barcelona",
    "wof:name":"Lopez Del Hierro Juan",
    "wof:placetype":"venue"
},
  "geometry": {"coordinates":[2.1842811108,41.4432258606],"type":"Point"}
}