{
  "type": "Feature",
  "properties": {
    "iso:country":"ES",
    "sg:address":"Carrer de L'agregacio, 36",
    "sg:city":"Barcelona",
    "sg:orig_category":"Asociaciones Humanitarias, De Cooperaci\u00d3n, De Acci\u00d3n Social",
    "sg:phone":"+34 934 35 36 84",
    "sg:postcode":"08041",
    "sg:province":"Barcelona",
    "wof:name":"A%egrare S.l.l.",
    "wof:placetype":"venue"
},
  "geometry": {"coordinates":[2.1760311127,41.4221763611],"type":"Point"}
}