{
  "type": "Feature",
  "properties": {
    "iso:country":"ES",
    "sg:address":"Calle de Angeles, 70",
    "sg:city":"Ares",
    "sg:orig_category":"Zapatos (al Por Menor)",
    "sg:phone":"+34 981 46 89 08",
    "sg:postcode":"15624",
    "sg:province":"La Coru\u00f1a",
    "wof:name":"Gundin Leira Maria De Los Angeles",
    "wof:placetype":"venue"
},
  "geometry": {"coordinates":[-8.2437286377,43.4275665283],"type":"Point"}
}