{
  "type": "Feature",
  "properties": {
    "addr:full":"Calle de Independencia, 26 Vitoria-gasteiz \u00c1lava 01005",
    "addr:housenumber":"26",
    "addr:postcode":"01005",
    "addr:street":"Calle De Independencia",
    "iso:country":"ES",
    "sg:address":"Calle de Independencia, 26",
    "sg:city":"Vitoria-gasteiz",
    "sg:orig_category":"Diarios, Revistas Y Boletines (distribuidores)",
    "sg:phone":"+34 945 25 23 34",
    "sg:postcode":"01005",
    "sg:province":"\u00c1lava",
    "wof:name":"Olaortua Ormachea Ane Miren",
    "wof:placetype":"venue"
},
  "geometry": {"coordinates":[-2.6696689129,42.8449783325],"type":"Point"}
}