{
  "type": "Feature",
  "properties": {
    "addr:full":"Calle de Alfonso X El Sabio, S/n Zaragoza Zaragoza 50006",
    "addr:housenumber":"s / n",
    "addr:postcode":"50006",
    "addr:street":"Calle De Alfonso X El Sabio",
    "iso:country":"ES",
    "sg:address":"Calle de Alfonso X El Sabio, S/n",
    "sg:city":"Zaragoza",
    "sg:orig_category":"Peluquer\u00cdas, Peluquer\u00cda Mixta",
    "sg:phone":"+34 976 27 96 77",
    "sg:postcode":"50006",
    "sg:province":"Zaragoza",
    "wof:name":"Yus Perez Ascension",
    "wof:placetype":"venue"
},
  "geometry": {"coordinates":[-0.8925390244,41.636756897],"type":"Point"}
}