{
  "type": "Feature",
  "properties": {
    "addr:full":"Pase Dos De Mayo, 2 Avila \u00c1vila 05001",
    "addr:housenumber":"2",
    "addr:postcode":"05001",
    "addr:street":"Dos De Mayo;A\u0301Vila",
    "iso:country":"ES",
    "sg:address":"Pase Dos De Mayo, 2",
    "sg:city":"Avila",
    "sg:orig_category":"Teatros Y Salas De Espect\u00c1culos",
    "sg:phone":"+34 920 25 30 36",
    "sg:postcode":"05001",
    "sg:province":"\u00c1vila",
    "wof:name":"Caja De Avila",
    "wof:placetype":"venue"
},
  "geometry": {"coordinates":[-4.6918849945,40.6569709778],"type":"Point"}
}