{
  "type": "Feature",
  "properties": {
    "addr:full":"Calle de Alcala, 221 Madrid Madrid 28028",
    "addr:housenumber":"221",
    "addr:postcode":"28028",
    "addr:street":"Calle De Alcala",
    "iso:country":"ES",
    "sg:address":"Calle de Alcala, 221",
    "sg:city":"Madrid",
    "sg:orig_category":"Droguer\u00cdas (al Por Menor)",
    "sg:phone":"+34 917 25 16 27",
    "sg:postcode":"28028",
    "sg:province":"Madrid",
    "wof:name":"Martinez Oliva Maria Concepcion",
    "wof:placetype":"venue"
},
  "geometry": {"coordinates":[-3.6655960083,40.4297027588],"type":"Point"}
}