{
  "type": "Feature",
  "properties": {
    "iso:country":"ES",
    "sg:address":"Calle de Conde De Torrefiel, 94",
    "sg:city":"Valencia",
    "sg:orig_category":"Carnicer\u00cdas, Carnicer\u00cdas",
    "sg:phone":"+34 963 66 18 18",
    "sg:postcode":"46019",
    "sg:province":"Valencia",
    "wof:name":"Gimenez Barrachina Francisco",
    "wof:placetype":"venue"
},
  "geometry": {"coordinates":[-0.377142489,39.4965133667],"type":"Point"}
}