{
  "type": "Feature",
  "properties": {
    "addr:full":"Ctra Madrid-cadiz(p I Estacion), Km. 0324,0 Andujar Ja\u00e9n 23740",
    "addr:postcode":"23740",
    "addr:street":"Ctra Madrid-Cadiz P;Estacion;0324,0;Jae\u0301N",
    "iso:country":"ES",
    "sg:address":"Ctra Madrid-cadiz(p I Estacion), Km. 0324,0",
    "sg:city":"Andujar",
    "sg:orig_category":"Aceites Y Grasas Alimentarias (fabricaci\u00d3n, Al Por Mayor)",
    "sg:phone":"+34 953 50 06 30",
    "sg:postcode":"23740",
    "sg:province":"Ja\u00e9n",
    "wof:name":"Aceites Sanfer S.l.",
    "wof:placetype":"venue"
},
  "geometry": {"coordinates":[-4.0286779404,38.2897567749],"type":"Point"}
}