{
  "type": "Feature",
  "properties": {
    "addr:full":"Carrer de Pamplona, 122 Barcelona Barcelona 08018",
    "addr:housenumber":"122",
    "addr:postcode":"08018",
    "addr:street":"Carrer De Pamplona",
    "iso:country":"ES",
    "sg:address":"Carrer de Pamplona, 122",
    "sg:city":"Barcelona",
    "sg:orig_category":"Electrodom\u00c9sticos (al Por Menor)",
    "sg:phone":"+34 933 00 71 15",
    "sg:postcode":"08018",
    "sg:province":"Barcelona",
    "wof:name":"Sole Otal Jose",
    "wof:placetype":"venue"
},
  "geometry": {"coordinates":[2.1880619526,41.3993339539],"type":"Point"}
}