{
  "type": "Feature",
  "properties": {
    "iso:country":"ES",
    "sg:address":"Calle de Manuel Carrillo Garcia, 10",
    "sg:city":"Cieza",
    "sg:orig_category":"Edici\u00d3n De Diarios, Revistas, Boletines",
    "sg:phone":"+34 968 45 58 02",
    "sg:postcode":"30530",
    "sg:province":"Murcia",
    "wof:name":"El Mirador De Cieza S.l.",
    "wof:placetype":"venue"
},
  "geometry": {"coordinates":[-1.4198280573,38.2415122986],"type":"Point"}
}