{
  "type": "Feature",
  "properties": {
    "addr:full":"Ctra Estepa-herrera, Km. 0004,0 Estepa Sevilla 41560",
    "addr:postcode":"41560",
    "addr:street":"Ctra Estepa-Herrera Km. 0004,0;Sevilla",
    "iso:country":"ES",
    "sg:address":"Ctra Estepa-herrera, Km. 0004,0",
    "sg:city":"Estepa",
    "sg:orig_category":"Frutas Y Legumbres Frescas (al Por Mayor)",
    "sg:phone":"+34 955 95 81 85",
    "sg:postcode":"41560",
    "sg:province":"Sevilla",
    "wof:name":"Estepaoliva S.l.",
    "wof:placetype":"venue"
},
  "geometry": {"coordinates":[-4.8780741692,37.2938766479],"type":"Point"}
}