{
  "type": "Feature",
  "properties": {
    "iso:country":"ES",
    "sg:address":"Calle de San Jose, 28",
    "sg:city":"Beal",
    "sg:orig_category":"Ingenier\u00cda, Centros De Estudios (diversos)",
    "sg:phone":"+34 968 54 68 01",
    "sg:postcode":"30382",
    "sg:province":"Murcia",
    "wof:name":"Asfaltos Bituminosos S.a.",
    "wof:placetype":"venue"
},
  "geometry": {"coordinates":[-0.8416869044,37.6343078613],"type":"Point"}
}