{
  "type": "Feature",
  "properties": {
    "iso:country":"ES",
    "sg:address":"Carrer de Arquitecte Sert, 22",
    "sg:city":"Palau-solita I Plegamans",
    "sg:orig_category":"Fabricaci\u00d3n De Art\u00cdculos Y Equipos Deportivos Y De Ocio",
    "sg:phone":"+34 938 64 43 57",
    "sg:postcode":"08184",
    "sg:province":"Barcelona",
    "wof:name":"Zasdar S.l.",
    "wof:placetype":"venue"
},
  "geometry": {"coordinates":[2.1781716347,41.5847091675],"type":"Point"}
}