{
  "type": "Feature",
  "properties": {
    "iso:country":"ES",
    "sg:address":"Calle de Chinchon, 8",
    "sg:city":"Valdemoro",
    "sg:orig_category":"Paletas",
    "sg:phone":"+34 918 01 90 35",
    "sg:postcode":"28340",
    "sg:province":"Madrid",
    "wof:name":"Gestion De Reciclados Adm S.l.l.",
    "wof:placetype":"venue"
},
  "geometry": {"coordinates":[-3.6781790257,40.2076759338],"type":"Point"}
}