{
  "type": "Feature",
  "properties": {
    "addr:full":"Calle de Alcalde Rodolfo Varona, 7 Santo Domingo De La Calzada La Rioja 26250",
    "addr:housenumber":"7",
    "addr:postcode":"26250",
    "addr:street":"Calle De Alcalde Rodolfo Varona;Calzada;Rioja",
    "iso:country":"ES",
    "sg:address":"Calle de Alcalde Rodolfo Varona, 7",
    "sg:city":"Santo Domingo De La Calzada",
    "sg:orig_category":"Telas Y Sedas (al Por Menor)",
    "sg:phone":"+34 941 34 08 80",
    "sg:postcode":"26250",
    "sg:province":"La Rioja",
    "wof:name":"Espinosa Gil Maria Teresa",
    "wof:placetype":"venue"
},
  "geometry": {"coordinates":[-2.9534926414,42.4396057129],"type":"Point"}
}