{
  "type": "Feature",
  "properties": {
    "addr:full":"Calle de Victoria (la) Finca Espa\u00d1a, 28 Finca Espa\u00e7a Santa Cruz De Tenerife 38320",
    "addr:housenumber":"28",
    "addr:postcode":"38320",
    "addr:street":"Calle De Victoria;Espan\u0303A",
    "iso:country":"ES",
    "sg:address":"Calle de Victoria (la) Finca Espa\u00d1a, 28",
    "sg:city":"Finca Espa\u00e7a",
    "sg:orig_category":"Agencias Y Agentes Comerciales, Representantes",
    "sg:phone":"+34 922 65 71 04",
    "sg:postcode":"38320",
    "sg:province":"Santa Cruz De Tenerife",
    "wof:name":"Rodriguez Paez Francisco",
    "wof:placetype":"venue"
},
  "geometry": {"coordinates":[-16.2880134583,28.468454361],"type":"Point"}
}