{
  "type": "Feature",
  "properties": {
    "iso:country":"ES",
    "sg:address":"Carr Nadal Meroles, 15",
    "sg:city":"Lleida",
    "sg:orig_category":"Centros De Adelgazamiento Y De Est\u00c9tica",
    "sg:phone":"+34 973 22 46 62",
    "sg:postcode":"25008",
    "sg:province":"Lleida",
    "wof:name":"Franch Trilla Josue",
    "wof:placetype":"venue"
},
  "geometry": {"coordinates":[0.621006012,41.6229629517],"type":"Point"}
}