{
  "type": "Feature",
  "properties": {
    "iso:country":"ES",
    "sg:address":"Calle de Almanzor, 30",
    "sg:city":"Cordoba",
    "sg:orig_category":"Dorados, Plater\u00cda (orfebrer\u00cda)",
    "sg:phone":"+34 957 29 01 26",
    "sg:postcode":"14003",
    "sg:province":"C\u00f3rdoba",
    "wof:name":"Diaz Roncero Francisco",
    "wof:placetype":"venue"
},
  "geometry": {"coordinates":[-4.7832517624,37.8806991577],"type":"Point"}
}