{
  "type": "Feature",
  "properties": {
    "addr:full":"Plaz Doctor Madinabeitia, 4 Alonsotegi Vizcaya 48810",
    "addr:housenumber":"4",
    "addr:postcode":"48810",
    "addr:street":"Madinabeitia",
    "iso:country":"ES",
    "sg:address":"Plaz Doctor Madinabeitia, 4",
    "sg:city":"Alonsotegi",
    "sg:orig_category":"Farmacias",
    "sg:phone":"+34 944 98 00 56",
    "sg:postcode":"48810",
    "sg:province":"Vizcaya",
    "wof:name":"Aznar Trigueros Jose Antonio",
    "wof:placetype":"venue"
},
  "geometry": {"coordinates":[-2.9881165028,43.245010376],"type":"Point"}
}