{
  "type": "Feature",
  "properties": {
    "addr:full":"Calle de Crisanta (do\u00d1a), 70 Tomelloso Ciudad Real 13700",
    "addr:housenumber":"70",
    "addr:postcode":"13700",
    "addr:street":"Calle De Crisanta Don\u0303A",
    "iso:country":"ES",
    "sg:address":"Calle de Crisanta (do\u00d1a), 70",
    "sg:city":"Tomelloso",
    "sg:orig_category":"Electrodom\u00c9sticos (al Por Menor)",
    "sg:phone":"+34 926 51 53 87",
    "sg:postcode":"13700",
    "sg:province":"Ciudad Real",
    "wof:name":"Electrodomesticos Anfe S.l.",
    "wof:placetype":"venue"
},
  "geometry": {"coordinates":[-3.0052940845,39.1665611267],"type":"Point"}
}