{
  "type": "Feature",
  "properties": {
    "iso:country":"ES",
    "sg:address":"Pl. Alqueria Nova, 14",
    "sg:city":"Xirivella",
    "sg:orig_category":"Agencias Y Agentes Comerciales, Representantes",
    "sg:phone":"+34 963 83 02 43",
    "sg:postcode":"46950",
    "sg:province":"Valencia",
    "wof:name":"Ruiz Amores Silvia",
    "wof:placetype":"venue"
},
  "geometry": {"coordinates":[-0.4176900089,39.467540741],"type":"Point"}
}