{
  "type": "Feature",
  "properties": {
    "addr:full":"Carrer de Bisbe Sastre, 6 Palma Islas Baleares 07011",
    "addr:housenumber":"6",
    "addr:postcode":"07011",
    "addr:street":"Carrer De Bisbe Sastre",
    "iso:country":"ES",
    "sg:address":"Carrer de Bisbe Sastre, 6",
    "sg:city":"Palma",
    "sg:orig_category":"Laboratorios Y Trabajos De Fotograf\u00cda, V\u00cddeo Y Cine",
    "sg:phone":"+34 971 45 37 85",
    "sg:postcode":"07011",
    "sg:province":"Islas Baleares",
    "wof:name":"Bernacer Blasco Joaquin",
    "wof:placetype":"venue"
},
  "geometry": {"coordinates":[2.6383609772,39.5808868408],"type":"Point"}
}