{
  "type": "Feature",
  "properties": {
    "addr:full":"Calle de Parque Del Castillejo, 2 Cisterniga Valladolid 47193",
    "addr:housenumber":"2",
    "addr:postcode":"47193",
    "addr:street":"Calle De Parque Del Castillejo",
    "iso:country":"ES",
    "sg:address":"Calle de Parque Del Castillejo, 2",
    "sg:city":"Cisterniga",
    "sg:orig_category":"Carnicer\u00cdas, Carnicer\u00cdas",
    "sg:phone":"+34 983 40 19 73",
    "sg:postcode":"47193",
    "sg:province":"Valladolid",
    "wof:name":"Carnicas Castillejo Sl",
    "wof:placetype":"venue"
},
  "geometry": {"coordinates":[-4.6852140427,41.6106910706],"type":"Point"}
}