{
  "type": "Feature",
  "properties": {
    "addr:full":"Calle de General Moscardo, 4 Facinas C\u00e1diz 11391",
    "addr:housenumber":"4",
    "addr:postcode":"11391",
    "addr:street":"Calle De General Moscardo;Ca\u0301Diz",
    "iso:country":"ES",
    "sg:address":"Calle de General Moscardo, 4",
    "sg:city":"Facinas",
    "sg:orig_category":"Carb\u00d3n, Carb\u00d3n De Madera (al Por Mayor)",
    "sg:phone":"+34 956 68 70 28",
    "sg:postcode":"11391",
    "sg:province":"C\u00e1diz",
    "wof:name":"Dominguez Garcia Manuel",
    "wof:placetype":"venue"
},
  "geometry": {"coordinates":[-5.6995887756,36.1427574158],"type":"Point"}
}