{
  "type": "Feature",
  "properties": {
    "iso:country":"ES",
    "sg:address":"Pl La Llum, 6",
    "sg:city":"Gandia",
    "sg:orig_category":"Ense\u00d1anza Variada",
    "sg:phone":"+34 962 87 27 68",
    "sg:postcode":"46700",
    "sg:province":"Valencia",
    "wof:name":"Generalitat Valenciana",
    "wof:placetype":"venue"
},
  "geometry": {"coordinates":[-0.1815903932,38.9804878235],"type":"Point"}
}