{
  "type": "Feature",
  "properties": {
    "iso:country":"ES",
    "sg:address":"Calle de Feria (la), S/n",
    "sg:city":"Coin",
    "sg:orig_category":"Institutos De Belleza",
    "sg:phone":"+34 952 45 38 01",
    "sg:postcode":"29100",
    "sg:province":"M\u00e1laga",
    "wof:name":"Urbaneja Solis Rocio",
    "wof:placetype":"venue"
},
  "geometry": {"coordinates":[-4.7588691711,36.6595039368],"type":"Point"}
}