{
  "type": "Feature",
  "properties": {
    "addr:full":"Calle de Jose Baldomir, 7 Coru\u00d1a La Coru\u00f1a 15010",
    "addr:housenumber":"7",
    "addr:postcode":"15010",
    "addr:street":"Calle De Jose Baldomir;La Corun\u0303A",
    "iso:country":"ES",
    "sg:address":"Calle de Jose Baldomir, 7",
    "sg:city":"Coru\u00d1a",
    "sg:orig_category":"Panader\u00cdas, Panader\u00cdas",
    "sg:phone":"+34 981 26 17 03",
    "sg:postcode":"15010",
    "sg:province":"La Coru\u00f1a",
    "wof:name":"Panaderia Claudio Hermida",
    "wof:placetype":"venue"
},
  "geometry": {"coordinates":[-8.4194202423,43.3635215759],"type":"Point"}
}