{
  "type": "Feature",
  "properties": {
    "iso:country":"ES",
    "sg:address":"Avda San Ignacio De Loyola, 64",
    "sg:city":"Barrio De Pinilla",
    "sg:orig_category":"Molduras, Junquillos, Listones Y Molduras Perforadas",
    "sg:phone":"+34 987 22 62 72",
    "sg:postcode":"24010",
    "sg:province":"Le\u00f3n",
    "wof:name":"Aller Fernandez Graciliano",
    "wof:placetype":"venue"
},
  "geometry": {"coordinates":[-5.5919389725,42.6063194275],"type":"Point"}
}