{
  "type": "Feature",
  "properties": {
    "iso:country":"ES",
    "sg:address":"Carr Arqueoleg Ballester (de L'), 17",
    "sg:city":"Albaida",
    "sg:orig_category":"Supermercados Y Hipermercados",
    "sg:phone":"+34 962 39 05 44",
    "sg:postcode":"46860",
    "sg:province":"Valencia",
    "wof:name":"Soler Pastor Joaquin",
    "wof:placetype":"venue"
},
  "geometry": {"coordinates":[-0.5165320039,38.8379859924],"type":"Point"}
}