{
  "type": "Feature",
  "properties": {
    "addr:full":"Avda Jose Antonio Vaca De Osma, 8 Barco De Avila \u00c1vila 05600",
    "addr:housenumber":"8",
    "addr:postcode":"05600",
    "addr:street":"Avda Jose Antonio Vaca De Osma;A\u0301Vila",
    "iso:country":"ES",
    "sg:address":"Avda Jose Antonio Vaca De Osma, 8",
    "sg:city":"Barco De Avila",
    "sg:orig_category":"Carnicer\u00cdas, Carnicer\u00cdas",
    "sg:phone":"+34 920 34 08 06",
    "sg:postcode":"05600",
    "sg:province":"\u00c1vila",
    "wof:name":"Martin Martin Fernando",
    "wof:placetype":"venue"
},
  "geometry": {"coordinates":[-5.521818161,40.3585357666],"type":"Point"}
}