{
  "type": "Feature",
  "properties": {
    "addr:full":"Av. Lago, 36 Enebral Madrid 28250",
    "addr:housenumber":"36",
    "addr:postcode":"28250",
    "addr:street":"Av. Lago",
    "iso:country":"ES",
    "sg:address":"Av. Lago, 36",
    "sg:city":"Enebral",
    "sg:orig_category":"Energ\u00cda Solar Y Nuevas Energ\u00cdas (equipo, Estudios)",
    "sg:phone":"+34 916 30 30 64",
    "sg:postcode":"28250",
    "sg:province":"Madrid",
    "wof:name":"Medina Valcarcel Enrique",
    "wof:placetype":"venue"
},
  "geometry": {"coordinates":[-3.9306790829,40.57654953],"type":"Point"}
}