{
  "type": "Feature",
  "properties": {
    "addr:full":"Calle de Tudela, 2 Mallen Zaragoza 50550",
    "addr:housenumber":"2",
    "addr:postcode":"50550",
    "addr:street":"Calle De Tudela",
    "iso:country":"ES",
    "sg:address":"Calle de Tudela, 2",
    "sg:city":"Mallen",
    "sg:orig_category":"Pescader\u00cdas (al Por Menor)",
    "sg:phone":"+34 976 85 00 18",
    "sg:postcode":"50550",
    "sg:province":"Zaragoza",
    "wof:name":"Marco Lazaro Isabel",
    "wof:placetype":"venue"
},
  "geometry": {"coordinates":[-1.420124054,41.9002532959],"type":"Point"}
}