{
  "type": "Feature",
  "properties": {
    "iso:country":"ES",
    "sg:address":"Calle de Luis Morote, 61",
    "sg:city":"Palmas De Gran Canaria",
    "sg:orig_category":"Teatros Y Salas De Espect\u00c1culos",
    "sg:phone":"+34 928 22 34 71",
    "sg:postcode":"35007",
    "sg:province":"Las Palmas",
    "wof:name":"Neon Dancing S.l.",
    "wof:placetype":"venue"
},
  "geometry": {"coordinates":[-15.4349918365,28.1412982941],"type":"Point"}
}