{
  "type": "Feature",
  "properties": {
    "addr:full":"Carr Camp Del Turia, 14 Alfinach Valencia 46530",
    "addr:housenumber":"14",
    "addr:postcode":"46530",
    "addr:street":"Carr Camp Del Turia",
    "iso:country":"ES",
    "sg:address":"Carr Camp Del Turia, 14",
    "sg:city":"Alfinach",
    "sg:orig_category":"Arboricultura Y Producci\u00d3n De Frutas",
    "sg:phone":"+34 961 46 47 19",
    "sg:postcode":"46530",
    "sg:province":"Valencia",
    "wof:name":"Best Fruit S. L. U.",
    "wof:placetype":"venue"
},
  "geometry": {"coordinates":[-0.3357189894,39.6305007935],"type":"Point"}
}