{
  "type": "Feature",
  "properties": {
    "addr:full":"Carrer de Francesc Santacana, 32 Martorell Barcelona 08760",
    "addr:housenumber":"32",
    "addr:postcode":"08760",
    "addr:street":"Carrer De Francesc Santacana",
    "iso:country":"ES",
    "sg:address":"Carrer de Francesc Santacana, 32",
    "sg:city":"Martorell",
    "sg:orig_category":"Congelados: Productos Alimentarios (al Por Menor)",
    "sg:phone":"+34 937 74 04 17",
    "sg:postcode":"08760",
    "sg:province":"Barcelona",
    "wof:name":"Naturgel Els Congelats S.l.",
    "wof:placetype":"venue"
},
  "geometry": {"coordinates":[1.9285039902,41.4741516113],"type":"Point"}
}