{
  "type": "Feature",
  "properties": {
    "iso:country":"ES",
    "sg:address":"Calle de Fontanares, 38",
    "sg:city":"Valencia",
    "sg:orig_category":"Confecciones De Art\u00cdculos De Punto",
    "sg:phone":"+34 963 78 32 50",
    "sg:postcode":"46007",
    "sg:province":"Valencia",
    "wof:name":"Almacenes Felgo S.l.",
    "wof:placetype":"venue"
},
  "geometry": {"coordinates":[-0.3924992979,39.4582176208],"type":"Point"}
}