{
  "type": "Feature",
  "properties": {
    "addr:full":"Calle de Vizcaya, S/n Palencia Palencia 34003",
    "addr:housenumber":"s / n",
    "addr:postcode":"34003",
    "addr:street":"Calle De Vizcaya",
    "iso:country":"ES",
    "sg:address":"Calle de Vizcaya, S/n",
    "sg:city":"Palencia",
    "sg:orig_category":"Mutuas De Seguros",
    "sg:phone":"+34 979 71 14 68",
    "sg:postcode":"34003",
    "sg:province":"Palencia",
    "sg:website":"www.mutuamur.es",
    "wof:name":"Ibermutuamur",
    "wof:placetype":"venue"
},
  "geometry": {"coordinates":[-4.5160989761,42.0025482178],"type":"Point"}
}