{
  "type": "Feature",
  "properties": {
    "addr:full":"Carrer de Bac De Roda, 85 Barcelona Barcelona 08005",
    "addr:housenumber":"85",
    "addr:postcode":"08005",
    "addr:street":"Carrer De Bac De Roda",
    "iso:country":"ES",
    "sg:address":"Carrer de Bac De Roda, 85",
    "sg:city":"Barcelona",
    "sg:orig_category":"Agentes, Concesionarios Y Sucursales De Veh\u00cdculos",
    "sg:phone":"+34 933 07 47 27",
    "sg:postcode":"08005",
    "sg:province":"Barcelona",
    "wof:name":"Hitcon S.l.",
    "wof:placetype":"venue"
},
  "geometry": {"coordinates":[2.2056529522,41.4061164856],"type":"Point"}
}