{
  "type": "Feature",
  "properties": {
    "addr:full":"Sabaters, 35 Ciutadella Menorca Islas Baleares 07760",
    "addr:housenumber":"35",
    "addr:postcode":"07760",
    "addr:street":"Sabaters",
    "iso:country":"ES",
    "sg:address":"Sabaters, 35",
    "sg:city":"Ciutadella Menorca",
    "sg:orig_category":"Marroquiner\u00cda (confecci\u00d3n)",
    "sg:phone":"+34 971 48 25 18",
    "sg:postcode":"07760",
    "sg:province":"Islas Baleares",
    "wof:name":"Complementos Tanino S.l.",
    "wof:placetype":"venue"
},
  "geometry": {"coordinates":[3.8554348946,40.0109863281],"type":"Point"}
}