{
  "type": "Feature",
  "properties": {
    "addr:full":"Calle de Don Carlos Romero, 28 Cordoba C\u00f3rdoba 14007",
    "addr:housenumber":"28",
    "addr:postcode":"14007",
    "addr:street":"Calle De Don Carlos Romero;Co\u0301Rdoba",
    "iso:country":"ES",
    "sg:address":"Calle de Don Carlos Romero, 28",
    "sg:city":"Cordoba",
    "sg:orig_category":"Mec\u00c1nico Del Autom\u00d3vil",
    "sg:phone":"+34 957 25 78 46",
    "sg:postcode":"14007",
    "sg:province":"C\u00f3rdoba",
    "wof:name":"Parra Ruz Manuel",
    "wof:placetype":"venue"
},
  "geometry": {"coordinates":[-4.762152195,37.8916244507],"type":"Point"}
}