{
  "type": "Feature",
  "properties": {
    "addr:full":"Carrer de Major, 18 Tarragona Tarragona 43003",
    "addr:housenumber":"18",
    "addr:postcode":"43003",
    "addr:street":"Carrer De Major",
    "iso:country":"ES",
    "sg:address":"Carrer de Major, 18",
    "sg:city":"Tarragona",
    "sg:orig_category":"Administradores De Bienes Y Delegados De Comunidades De Propietarios",
    "sg:phone":"+34 977 24 94 45",
    "sg:postcode":"43003",
    "sg:province":"Tarragona",
    "wof:name":"T.g.n.gestio S.l.",
    "wof:placetype":"venue"
},
  "geometry": {"coordinates":[1.2567529678,41.1177215576],"type":"Point"}
}