{
  "type": "Feature",
  "properties": {
    "addr:full":"Carrer de Joan Miro, 12 S. Cugat Valles Barcelona 08173",
    "addr:housenumber":"12",
    "addr:postcode":"08173",
    "addr:street":"Carrer De Joan Miro;S. Cugat Valles Barcelona",
    "iso:country":"ES",
    "sg:address":"Carrer de Joan Miro, 12",
    "sg:city":"S. Cugat Valles",
    "sg:orig_category":"Materias Pl\u00c1sticas: Art\u00cdculos Para La Industria",
    "sg:phone":"+34 935 89 54 56",
    "sg:postcode":"08173",
    "sg:province":"Barcelona",
    "wof:name":"Plasticos T-tres S.a.",
    "wof:placetype":"venue"
},
  "geometry": {"coordinates":[2.0712599754,41.475479126],"type":"Point"}
}