{
  "type": "Feature",
  "properties": {
    "addr:full":"Calle de Fray Jose De San Jacinto (de), 10 Villarejo Salvanes Madrid 28590",
    "addr:postcode":"28590",
    "addr:street":"Calle De Fray Jose De San;De;Villarejo",
    "iso:country":"ES",
    "sg:address":"Calle de Fray Jose De San Jacinto (de), 10",
    "sg:city":"Villarejo Salvanes",
    "sg:orig_category":"Aceites Y Grasas Alimentarias (fabricaci\u00d3n, Al Por Mayor)",
    "sg:phone":"+34 918 74 41 29",
    "sg:postcode":"28590",
    "sg:province":"Madrid",
    "wof:name":"Recespa\u00f1a S.c.",
    "wof:placetype":"venue"
},
  "geometry": {"coordinates":[-3.2836201191,40.1694488525],"type":"Point"}
}