{
  "type": "Feature",
  "properties": {
    "addr:full":"Rua Parrocha, 32 Recare Pontevedra 36313",
    "addr:housenumber":"32",
    "addr:postcode":"36313",
    "addr:street":"Rua Parrocha",
    "iso:country":"ES",
    "sg:address":"Rua Parrocha, 32",
    "sg:city":"Recare",
    "sg:orig_category":"M\u00c1quinas Y Material Para La Industria De La Alimentaci\u00d3n",
    "sg:phone":"+34 986 49 30 94",
    "sg:postcode":"36313",
    "sg:province":"Pontevedra",
    "wof:name":"Optimar Fodema S.a.",
    "wof:placetype":"venue"
},
  "geometry": {"coordinates":[-8.6853733063,42.2050933838],"type":"Point"}
}