{
  "type": "Feature",
  "properties": {
    "addr:full":"Calle de Victoria Kent, 18 Talavera Reina Toledo 45600",
    "addr:housenumber":"18",
    "addr:postcode":"45600",
    "addr:street":"Calle De Victoria Kent",
    "iso:country":"ES",
    "sg:address":"Calle de Victoria Kent, 18",
    "sg:city":"Talavera Reina",
    "sg:orig_category":"Cristaler\u00cdas",
    "sg:phone":"+34 925 81 36 36",
    "sg:postcode":"45600",
    "sg:province":"Toledo",
    "wof:name":"Unicristal S.a.l.",
    "wof:placetype":"venue"
},
  "geometry": {"coordinates":[-4.8326292038,39.9584884644],"type":"Point"}
}