{
  "type": "Feature",
  "properties": {
    "iso:country":"ES",
    "sg:address":"Avda Libertad De La, 7",
    "sg:city":"Donostia-san Sebastian",
    "sg:orig_category":"Asesor\u00cda Sobre Comunicaci\u00d3n De Empresas",
    "sg:phone":"+34 943 42 37 95",
    "sg:postcode":"20004",
    "sg:province":"Guip\u00f9zcoa",
    "wof:name":"Javier Perez Sorasu E I\u00f1aki Irure Gorostegui, S.l.",
    "wof:placetype":"venue"
},
  "geometry": {"coordinates":[-1.9802559614,43.3201446533],"type":"Point"}
}