{
  "type": "Feature",
  "properties": {
    "addr:full":"Avgd Jaime I, 30 Canals Valencia 46650",
    "addr:housenumber":"30",
    "addr:postcode":"46650",
    "addr:street":"Jaime I",
    "iso:country":"ES",
    "sg:address":"Avgd Jaime I, 30",
    "sg:city":"Canals",
    "sg:orig_category":"Sociedades, Compa\u00d1\u00cdas Aseguradoras",
    "sg:phone":"+34 962 24 60 40",
    "sg:postcode":"46650",
    "sg:province":"Valencia",
    "wof:name":"Seguros Catalana Occidente S.a. De Seguros Y Reaseguros",
    "wof:placetype":"venue"
},
  "geometry": {"coordinates":[-0.5832080245,38.9654884338],"type":"Point"}
}