{
  "type": "Feature",
  "properties": {
    "addr:full":"Avgd Ausias March, 10 Silla Valencia 46460",
    "addr:housenumber":"10",
    "addr:postcode":"46460",
    "addr:street":"March",
    "iso:country":"ES",
    "sg:address":"Avgd Ausias March, 10",
    "sg:city":"Silla",
    "sg:orig_category":"Supermercados Y Hipermercados",
    "sg:phone":"+34 961 20 32 62",
    "sg:postcode":"46460",
    "sg:province":"Valencia",
    "wof:name":"Consum Sociedad Cooperativa Limitada",
    "wof:placetype":"venue"
},
  "geometry": {"coordinates":[-0.4115729928,39.3580513],"type":"Point"}
}