{
  "type": "Feature",
  "properties": {
    "addr:full":"Calle de Mayor, 146 Garres Murcia 30158",
    "addr:housenumber":"146",
    "addr:postcode":"30158",
    "addr:street":"Calle De Mayor",
    "iso:country":"ES",
    "sg:address":"Calle de Mayor, 146",
    "sg:city":"Garres",
    "sg:orig_category":"Institutos De Belleza",
    "sg:phone":"+34 968 82 06 13",
    "sg:postcode":"30158",
    "sg:province":"Murcia",
    "wof:name":"Escribano Hernandez Maria Dolores",
    "wof:placetype":"venue"
},
  "geometry": {"coordinates":[-1.0902830362,37.9588890076],"type":"Point"}
}