{
  "type": "Feature",
  "properties": {
    "addr:full":"Ctra San Bartolome, 44 Argana Baja Las Palmas 35500",
    "addr:housenumber":"44",
    "addr:postcode":"35500",
    "addr:street":"Ctra San Bartolome",
    "iso:country":"ES",
    "sg:address":"Ctra San Bartolome, 44",
    "sg:city":"Argana Baja",
    "sg:orig_category":"Promotores Constructores",
    "sg:phone":"+34 928 81 07 83",
    "sg:postcode":"35500",
    "sg:province":"Las Palmas",
    "wof:name":"Barambio Delgado Liberato Antonio",
    "wof:placetype":"venue"
},
  "geometry": {"coordinates":[-13.5490036011,28.9582099915],"type":"Point"}
}