{
  "type": "Feature",
  "properties": {
    "addr:full":"Avda Pais Valencia (del), 28 Onda Castell\u00f3n 12200",
    "addr:postcode":"12200",
    "addr:street":"Avda Pais;Del;Castello\u0301N",
    "iso:country":"ES",
    "sg:address":"Avda Pais Valencia (del), 28",
    "sg:city":"Onda",
    "sg:orig_category":"Perfumer\u00cda (al Por Menor)",
    "sg:phone":"+34 964 60 08 38",
    "sg:postcode":"12200",
    "sg:province":"Castell\u00f3n",
    "wof:name":"Hijos De Regina Peris S.l.",
    "wof:placetype":"venue"
},
  "geometry": {"coordinates":[-0.2597509921,39.9653739929],"type":"Point"}
}