{
  "type": "Feature",
  "properties": {
    "addr:full":"Carrer de Lepant, 365 Barcelona Barcelona 08025",
    "addr:housenumber":"365",
    "addr:postcode":"08025",
    "addr:street":"Carrer De Lepant",
    "iso:country":"ES",
    "sg:address":"Carrer de Lepant, 365",
    "sg:city":"Barcelona",
    "sg:orig_category":"Reparaci\u00d3n Y Restauraci\u00d3n De Objetos Diversos",
    "sg:phone":"+34 934 55 00 39",
    "sg:postcode":"08025",
    "sg:province":"Barcelona",
    "wof:name":"Garcia Garces Benito",
    "wof:placetype":"venue"
},
  "geometry": {"coordinates":[2.1704471111,41.408996582],"type":"Point"}
}