{
  "type": "Feature",
  "properties": {
    "addr:full":"Calle de Alamo (del), 5 Galapagar Madrid 28260",
    "addr:housenumber":"5",
    "addr:postcode":"28260",
    "addr:street":"Calle De Alamo Del",
    "iso:country":"ES",
    "sg:address":"Calle de Alamo (del), 5",
    "sg:city":"Galapagar",
    "sg:orig_category":"Asociaciones Y Clubs Deportivos",
    "sg:phone":"+34 918 56 94 16",
    "sg:postcode":"28260",
    "sg:province":"Madrid",
    "wof:name":"Sancho Huesca, Maria Isabel 000464485k S",
    "wof:placetype":"venue"
},
  "geometry": {"coordinates":[-4.0018587112,40.5810012817],"type":"Point"}
}