{
  "type": "Feature",
  "properties": {
    "addr:full":"Ctra Rota (de), 1 Chipiona C\u00e1diz 11550",
    "addr:housenumber":"1",
    "addr:postcode":"11550",
    "addr:street":"Ctra Rota De",
    "iso:country":"ES",
    "sg:address":"Ctra Rota (de), 1",
    "sg:city":"Chipiona",
    "sg:orig_category":"Distribuci\u00d3n De Petr\u00d3leo Y Derivados",
    "sg:phone":"+34 956 37 19 20",
    "sg:postcode":"11550",
    "sg:province":"C\u00e1diz",
    "wof:name":"Pescados Marin Chipiona S.l.",
    "wof:placetype":"venue"
},
  "geometry": {"coordinates":[-6.4318070412,36.737449646],"type":"Point"}
}