{
  "type": "Feature",
  "properties": {
    "addr:full":"Calle de Jose Antonio, 19 Santiba\u00e7ez El Alto C\u00e1ceres 10859",
    "addr:housenumber":"19",
    "addr:postcode":"10859",
    "addr:street":"Calle De Jose Antonio",
    "iso:country":"ES",
    "sg:address":"Calle de Jose Antonio, 19",
    "sg:city":"Santiba\u00e7ez El Alto",
    "sg:classifiers":[
        {
            "category":"Taxi",
            "type":"Transportation"
        }
    ],
    "sg:phone":"+34 927 44 11 29",
    "sg:postcode":"10859",
    "sg:province":"C\u00e1ceres",
    "wof:name":"Gomez Bonilla Juan Justo",
    "wof:placetype":"venue"
},
  "geometry": {"coordinates":[-6.5474891663,40.1850204468],"type":"Point"}
}