{
  "type": "Feature",
  "properties": {
    "iso:country":"ES",
    "sg:address":"Avda Porto (do), 3",
    "sg:city":"Sanxenxo",
    "sg:orig_category":"Ropa Para Se\u00d1oras (al Por Menor)",
    "sg:phone":"+34 986 69 19 29",
    "sg:postcode":"36960",
    "sg:province":"Pontevedra",
    "wof:name":"El Soho C.b.",
    "wof:placetype":"venue"
},
  "geometry": {"coordinates":[-8.8072490692,42.3993873596],"type":"Point"}
}