{
  "type": "Feature",
  "properties": {
    "iso:country":"ES",
    "sg:address":"Avda. Frutales, 381",
    "sg:city":"Estepona",
    "sg:orig_category":"Venta, Instalaci\u00d3n, Reparaci\u00d3n De Antenas Para Televisi\u00d3n",
    "sg:phone":"+34 952 79 23 20",
    "sg:postcode":"29680",
    "sg:province":"M\u00e1laga",
    "wof:name":"Bb Satellite Installation S.l.",
    "wof:placetype":"venue"
},
  "geometry": {"coordinates":[-5.1452140808,36.4275817871],"type":"Point"}
}