{
  "type": "Feature",
  "properties": {
    "addr:full":"Avda Galicia, 10 Benavente Zamora 49600",
    "addr:housenumber":"10",
    "addr:postcode":"49600",
    "addr:street":"Avda Galicia",
    "iso:country":"ES",
    "sg:address":"Avda Galicia, 10",
    "sg:city":"Benavente",
    "sg:orig_category":"Farmacias",
    "sg:phone":"+34 980 63 01 20",
    "sg:postcode":"49600",
    "sg:province":"Zamora",
    "wof:name":"Monterrubio Urruchi Maria Paloma",
    "wof:placetype":"venue"
},
  "geometry": {"coordinates":[-5.6860990524,42.0077896118],"type":"Point"}
}