{
  "type": "Feature",
  "properties": {
    "addr:full":"Avda Nafarroa Etorbidea, 12 Tolosa Guip\u00f9zcoa 20400",
    "addr:housenumber":"12",
    "addr:postcode":"20400",
    "addr:street":"Avda Nafarroa Etorbidea;Guipu\u0300Zcoa",
    "iso:country":"ES",
    "sg:address":"Avda Nafarroa Etorbidea, 12",
    "sg:city":"Tolosa",
    "sg:orig_category":"Ropa Para Ni\u00d1os (al Por Menor)",
    "sg:phone":"+34 943 65 06 23",
    "sg:postcode":"20400",
    "sg:province":"Guip\u00f9zcoa",
    "wof:name":"Gonzalez Marcos Agueda",
    "wof:placetype":"venue"
},
  "geometry": {"coordinates":[-2.0789339542,43.1339912415],"type":"Point"}
}