{
  "type": "Feature",
  "properties": {
    "iso:country":"ES",
    "sg:address":"Poligono Industrial Las Horcas, S/n",
    "sg:city":"Alca\u00f1iz",
    "sg:orig_category":"Empresas De Carpinter\u00cda De Madera",
    "sg:phone":"+34 978 83 28 75",
    "sg:postcode":"44600",
    "sg:province":"Teruel",
    "wof:name":"Carfegi S.l",
    "wof:placetype":"venue"
},
  "geometry": {"coordinates":[-0.1331740022,41.0522842407],"type":"Point"}
}