{
  "type": "Feature",
  "properties": {
    "addr:full":"Calle de San Jose, 66 Gijon Asturias 33208",
    "addr:housenumber":"66",
    "addr:postcode":"33208",
    "addr:street":"Calle De San",
    "iso:country":"ES",
    "sg:address":"Calle de San Jose, 66",
    "sg:city":"Gijon",
    "sg:orig_category":"Electrodom\u00c9sticos (al Por Menor)",
    "sg:phone":"+34 985 14 22 30",
    "sg:postcode":"33208",
    "sg:province":"Asturias",
    "wof:name":"Lorido Salgado Jose Manuel",
    "wof:placetype":"venue"
},
  "geometry": {"coordinates":[-5.6639618874,43.534034729],"type":"Point"}
}