{
  "type": "Feature",
  "properties": {
    "addr:full":"Carrer de Mont Roig, 3 Barcelona Barcelona 08006",
    "addr:housenumber":"3",
    "addr:postcode":"08006",
    "addr:street":"Carrer De Mont Roig",
    "iso:country":"ES",
    "sg:address":"Carrer de Mont Roig, 3",
    "sg:city":"Barcelona",
    "sg:orig_category":"Productos Qu\u00cdmicos (fabricaci\u00d3n, Al Por Mayor)",
    "sg:phone":"+34 934 15 98 55",
    "sg:postcode":"08006",
    "sg:province":"Barcelona",
    "sg:website":"www.cpquimica.com",
    "wof:name":"C.p. Quimica S.l.",
    "wof:placetype":"venue"
},
  "geometry": {"coordinates":[2.1493029594,41.4052009583],"type":"Point"}
}