{
  "type": "Feature",
  "properties": {
    "iso:country":"ES",
    "sg:address":"Calle de Mayor, 48",
    "sg:city":"Laguardia",
    "sg:orig_category":"Financiaci\u00d3n Y Cr\u00c9ditos",
    "sg:phone":"+34 945 60 02 77",
    "sg:postcode":"01300",
    "sg:province":"\u00c1lava",
    "sg:website":"www.cajalaboral.es",
    "wof:name":"Caja Laboral Popular",
    "wof:placetype":"venue"
},
  "geometry": {"coordinates":[-2.5852389336,42.5539703369],"type":"Point"}
}