{
  "type": "Feature",
  "properties": {
    "addr:full":"Av Cova Solera, 17 Rubi Barcelona 08191",
    "addr:housenumber":"17",
    "addr:postcode":"08191",
    "addr:street":"Av Cova Solera",
    "iso:country":"ES",
    "sg:address":"Av Cova Solera, 17",
    "sg:city":"Rubi",
    "sg:orig_category":"Centros Empresariales",
    "sg:phone":"+34 935 86 21 26",
    "sg:postcode":"08191",
    "sg:province":"Barcelona",
    "wof:name":"Tepso Logistica S.l.",
    "wof:placetype":"venue"
},
  "geometry": {"coordinates":[2.0294249058,41.4830703735],"type":"Point"}
}