{
  "type": "Feature",
  "properties": {
    "iso:country":"ES",
    "sg:address":"C/ Concepcion Arenal, 95",
    "sg:city":"Elche",
    "sg:orig_category":"Cajas De Ahorro",
    "sg:phone":"+34 965 44 22 62",
    "sg:postcode":"03201",
    "sg:province":"Alicante",
    "wof:name":"Caixa D'estalvis I Pensions De Barcelona",
    "wof:placetype":"venue"
},
  "geometry": {"coordinates":[-0.7073889971,38.2624092102],"type":"Point"}
}