{
  "type": "Feature",
  "properties": {
    "addr:full":"Avda Andalucia (de), 75 Alcala Rio Sevilla 41200",
    "addr:housenumber":"75",
    "addr:postcode":"41200",
    "addr:street":"Avda Andalucia De",
    "iso:country":"ES",
    "sg:address":"Avda Andalucia (de), 75",
    "sg:city":"Alcala Rio",
    "sg:orig_category":"Forjas Y Altos Hornos",
    "sg:phone":"+34 955 65 12 99",
    "sg:postcode":"41200",
    "sg:province":"Sevilla",
    "wof:name":"Herreria Hermanos Gonzalez Velasco S.l.",
    "wof:placetype":"venue"
},
  "geometry": {"coordinates":[-5.9810700417,37.5193786621],"type":"Point"}
}