{
  "type": "Feature",
  "properties": {
    "addr:full":"Calle de Albert Einstein, 9 Vitoria-gasteiz \u00c1lava 01510",
    "addr:housenumber":"9",
    "addr:postcode":"01510",
    "addr:street":"Calle De Albert Einstein",
    "iso:country":"ES",
    "sg:address":"Calle de Albert Einstein, 9",
    "sg:city":"Vitoria-gasteiz",
    "sg:orig_category":"Metalurgia",
    "sg:phone":"+34 945 06 02 48",
    "sg:postcode":"01510",
    "sg:province":"\u00c1lava",
    "sg:website":"www.nitrogas.com",
    "wof:name":"Nitrogas, S.a. Sociedad Unipersonal",
    "wof:placetype":"venue"
},
  "geometry": {"coordinates":[-2.6683309078,42.9109191895],"type":"Point"}
}