{
  "type": "Feature",
  "properties": {
    "addr:full":"Prje. Asensao, S/n Cieza Murcia 30530",
    "addr:housenumber":"s / n",
    "addr:postcode":"30530",
    "iso:country":"ES",
    "sg:address":"Prje. Asensao, S/n",
    "sg:city":"Cieza",
    "sg:orig_category":"Productos Fitosanitarios (negocio, Aplicaci\u00d3n)",
    "sg:phone":"+34 968 77 33 40",
    "sg:postcode":"30530",
    "sg:province":"Murcia",
    "wof:name":"Agro-cieza S.l.",
    "wof:placetype":"venue"
},
  "geometry": {"coordinates":[-1.4821481705,38.2650794983],"type":"Point"}
}