{
  "type": "Feature",
  "properties": {
    "iso:country":"ES",
    "sg:address":"Ctra Madrid-cadiz, Km. 0569,9",
    "sg:city":"Dos Hermanas",
    "sg:orig_category":"Venta De Caravanas, Casas M\u00d3viles, Camping",
    "sg:phone":"+34 955 66 60 40",
    "sg:postcode":"41700",
    "sg:province":"Sevilla",
    "sg:website":"www.autocaravanasmontano.com",
    "wof:name":"Monta\u00f1o Martin Ana Maria",
    "wof:placetype":"venue"
},
  "geometry": {"coordinates":[-5.9281339645,37.2829055786],"type":"Point"}
}