{
  "type": "Feature",
  "properties": {
    "addr:full":"Plaz Bernales (de Los), 4 Aljorra Murcia 30390",
    "addr:housenumber":"4",
    "addr:postcode":"30390",
    "addr:street":"Plaz Bernales De Los",
    "iso:country":"ES",
    "sg:address":"Plaz Bernales (de Los), 4",
    "sg:city":"Aljorra",
    "sg:classifiers":[
        {
            "category":"Taxi",
            "type":"Transportation"
        }
    ],
    "sg:phone":"+34 968 55 83 32",
    "sg:postcode":"30390",
    "sg:province":"Murcia",
    "wof:name":"Sanchez Plazas Pedro",
    "wof:placetype":"venue"
},
  "geometry": {"coordinates":[-1.0707390308,37.6909942627],"type":"Point"}
}