{
  "type": "Feature",
  "properties": {
    "addr:full":"Cmno Cardon (el) Tejina, 3 Tejina Santa Cruz De Tenerife 38260",
    "addr:housenumber":"3",
    "addr:postcode":"38260",
    "addr:street":"Cmno Cardon El Tejina",
    "iso:country":"ES",
    "sg:address":"Cmno Cardon (el) Tejina, 3",
    "sg:city":"Tejina",
    "sg:orig_category":"Alimentaci\u00d3n General (al Por Menor)",
    "sg:phone":"+34 922 54 17 07",
    "sg:postcode":"38260",
    "sg:province":"Santa Cruz De Tenerife",
    "wof:name":"Martin Mendez Margarita",
    "wof:placetype":"venue"
},
  "geometry": {"coordinates":[-16.3609542847,28.5350093842],"type":"Point"}
}