{
  "type": "Feature",
  "properties": {
    "addr:full":"Cmno Villatobas, 3 Noblejas Toledo 45350",
    "addr:housenumber":"3",
    "addr:postcode":"45350",
    "addr:street":"Cmno Villatobas",
    "iso:country":"ES",
    "sg:address":"Cmno Villatobas, 3",
    "sg:city":"Noblejas",
    "sg:orig_category":"Empresas De Carpinter\u00cda",
    "sg:phone":"+34 925 14 05 53",
    "sg:postcode":"45350",
    "sg:province":"Toledo",
    "wof:name":"Trece\u00f1o Soriano Jose Luis",
    "wof:placetype":"venue"
},
  "geometry": {"coordinates":[-3.4328119755,39.9757766724],"type":"Point"}
}