{
  "type": "Feature",
  "properties": {
    "iso:country":"ES",
    "sg:address":"Calle de Hornos, 3",
    "sg:city":"Antequera",
    "sg:orig_category":"Plomeros",
    "sg:phone":"+34 952 84 42 64",
    "sg:postcode":"29200",
    "sg:province":"M\u00e1laga",
    "wof:name":"Higueras Moreno Jose Antonio",
    "wof:placetype":"venue"
},
  "geometry": {"coordinates":[-4.5586857796,37.0215492249],"type":"Point"}
}