{
  "type": "Feature",
  "properties": {
    "iso:country":"ES",
    "sg:address":"Calle de Venezuela, 18",
    "sg:city":"Valencia",
    "sg:orig_category":"Chapister\u00cda",
    "sg:phone":"+34 963 57 57 51",
    "sg:postcode":"46007",
    "sg:province":"Valencia",
    "wof:name":"Auto Talleres Venezuela S.l.",
    "wof:placetype":"venue"
},
  "geometry": {"coordinates":[-0.3894126117,39.4559211731],"type":"Point"}
}