{
  "type": "Feature",
  "properties": {
    "iso:country":"ES",
    "sg:address":"Calle de Mayor, 52",
    "sg:city":"Biar",
    "sg:orig_category":"Droguer\u00cdas (al Por Menor)",
    "sg:phone":"+34 965 81 01 34",
    "sg:postcode":"03410",
    "sg:province":"Alicante",
    "wof:name":"Molina Mataix Mateo",
    "wof:placetype":"venue"
},
  "geometry": {"coordinates":[-0.7638819814,38.6296844482],"type":"Point"}
}