{
  "type": "Feature",
  "properties": {
    "addr:full":"Calle de Gibraltar, 147 Linea De La Concepcion C\u00e1diz 11300",
    "addr:housenumber":"147",
    "addr:postcode":"11300",
    "addr:street":"Calle De Gibraltar;Ca\u0301Diz",
    "iso:country":"ES",
    "sg:address":"Calle de Gibraltar, 147",
    "sg:city":"Linea De La Concepcion",
    "sg:orig_category":"Cajas De Ahorro",
    "sg:phone":"+34 956 69 02 26",
    "sg:postcode":"11300",
    "sg:province":"C\u00e1diz",
    "wof:name":"Unicaja",
    "wof:placetype":"venue"
},
  "geometry": {"coordinates":[-5.340939045,36.1683044434],"type":"Point"}
}