{
  "type": "Feature",
  "properties": {
    "iso:country":"ES",
    "sg:address":"Calle de San Mario, 47",
    "sg:city":"Madrid",
    "sg:orig_category":"Molduras, Junquillos, Listones Y Molduras Perforadas",
    "sg:phone":"+34 914 75 10 09",
    "sg:postcode":"28041",
    "sg:province":"Madrid",
    "wof:name":"Mariscal Velasco Jose",
    "wof:placetype":"venue"
},
  "geometry": {"coordinates":[-3.6911878586,40.3779373169],"type":"Point"}
}