{
  "type": "Feature",
  "properties": {
    "addr:full":"U. Les Forques, S/n Vilafant Girona 17740",
    "addr:housenumber":"s / n",
    "addr:postcode":"17740",
    "iso:country":"ES",
    "sg:address":"U. Les Forques, S/n",
    "sg:city":"Vilafant",
    "sg:orig_category":"Centros De Educaci\u00d3n Especial",
    "sg:phone":"+34 972 51 34 80",
    "sg:postcode":"17740",
    "sg:province":"Girona",
    "wof:name":"Centre D'educacio Especial Mare De Deu Del Mont",
    "wof:placetype":"venue"
},
  "geometry": {"coordinates":[2.9358100891,42.2463035583],"type":"Point"}
}