{
  "type": "Feature",
  "properties": {
    "addr:full":"Calle de Natividad Morales Mu\u00d1oz, 29 San Jose Rinconada Sevilla 41300",
    "addr:housenumber":"29",
    "addr:postcode":"41300",
    "addr:street":"Calle De Natividad;Mun\u0303Oz",
    "iso:country":"ES",
    "sg:address":"Calle de Natividad Morales Mu\u00d1oz, 29",
    "sg:city":"San Jose Rinconada",
    "sg:orig_category":"Molduras, Junquillos, Listones Y Molduras Perforadas",
    "sg:phone":"+34 955 79 20 76",
    "sg:postcode":"41300",
    "sg:province":"Sevilla",
    "wof:name":"Rosado Melgar Juan",
    "wof:placetype":"venue"
},
  "geometry": {"coordinates":[-5.9434189796,37.443523407],"type":"Point"}
}