{
  "type": "Feature",
  "properties": {
    "iso:country":"ES",
    "sg:address":"Ctra Nal 340, Km. 1088,0",
    "sg:city":"L'aldea",
    "sg:orig_category":"Aparatos E Instalaci\u00d3n De Regad\u00cdos",
    "sg:phone":"+34 977 45 07 47",
    "sg:postcode":"43896",
    "sg:province":"Tarragona",
    "wof:name":"Exclusives Baix Ebre S.l.",
    "wof:placetype":"venue"
},
  "geometry": {"coordinates":[0.6109700203,40.7413101196],"type":"Point"}
}