{
  "type": "Feature",
  "properties": {
    "iso:country":"ES",
    "sg:address":"Calle de Santa Florentina, 20",
    "sg:city":"Cartagena",
    "sg:orig_category":"Peluqueros: De Se\u00d1oras",
    "sg:phone":"+34 968 12 43 66",
    "sg:postcode":"30201",
    "sg:province":"Murcia",
    "wof:name":"Mellado Vilar Margarita",
    "wof:placetype":"venue"
},
  "geometry": {"coordinates":[-0.9872949719,37.6039772034],"type":"Point"}
}