{
  "type": "Feature",
  "properties": {
    "addr:full":"Extramuros, S/n Rute C\u00f3rdoba 14960",
    "addr:postcode":"14960",
    "addr:street":"Extramuros S / N;Co\u0301Rdoba",
    "iso:country":"ES",
    "sg:address":"Extramuros, S/n",
    "sg:city":"Rute",
    "sg:orig_category":"Bares, Piano",
    "sg:phone":"+34 957 53 82 33",
    "sg:postcode":"14960",
    "sg:province":"C\u00f3rdoba",
    "wof:name":"Almacenes De Rute S. A.",
    "wof:placetype":"venue"
},
  "geometry": {"coordinates":[-4.3770704269,37.3233642578],"type":"Point"}
}