{
  "type": "Feature",
  "properties": {
    "iso:country":"ES",
    "sg:address":"Calle de Sherlock Holmes, 2",
    "sg:city":"Malaga",
    "sg:orig_category":"Montaje (empresas De)",
    "sg:phone":"+34 952 34 24 30",
    "sg:postcode":"29006",
    "sg:province":"M\u00e1laga",
    "wof:name":"Pedresqui Villena Antonio Jose",
    "wof:placetype":"venue"
},
  "geometry": {"coordinates":[-4.4608588219,36.7102584839],"type":"Point"}
}