{
  "type": "Feature",
  "properties": {
    "iso:country":"ES",
    "sg:address":"Avgd Doctor Fleming, 31",
    "sg:city":"Lleida",
    "sg:orig_category":"Asociaciones Y Clubs Deportivos",
    "sg:phone":"+34 973 26 61 95",
    "sg:postcode":"25006",
    "sg:province":"Lleida",
    "wof:name":"Barrachina Iba\u00f1ez Felix",
    "wof:placetype":"venue"
},
  "geometry": {"coordinates":[0.6144959927,41.6198692322],"type":"Point"}
}