{
  "type": "Feature",
  "properties": {
    "iso:country":"ES",
    "sg:address":"Avda Hermanos Bou, 200",
    "sg:city":"Castellon",
    "sg:orig_category":"Pintura, Barniz, Productos Asimilables (fabricaci\u00d3n, Al Por Mayor)",
    "sg:phone":"+34 964 22 40 62",
    "sg:postcode":"12003",
    "sg:province":"Castell\u00f3n",
    "sg:website":"www.pinturasgalindo.com",
    "wof:name":"Pinturas Galindo S.l.",
    "wof:placetype":"venue"
},
  "geometry": {"coordinates":[-0.0241129994,39.9811401367],"type":"Point"}
}