{
  "type": "Feature",
  "properties": {
    "iso:country":"ES",
    "sg:address":"C. Guetara (p I Villarrosa), 49",
    "sg:city":"Malaga",
    "sg:orig_category":"Cerrajer\u00cda, Ferrallista",
    "sg:phone":"+34 952 23 03 50",
    "sg:postcode":"29004",
    "sg:province":"M\u00e1laga",
    "wof:name":"Cerava Inx S.l.l.",
    "wof:placetype":"venue"
},
  "geometry": {"coordinates":[-4.4708991051,36.6735916138],"type":"Point"}
}