{
  "type": "Feature",
  "properties": {
    "iso:country":"ES",
    "sg:address":"Calle de Esperanza, 2",
    "sg:city":"Fuensanta -villa Ines",
    "sg:orig_category":"Muebles Y Accesorios Para Cocinas Y Cuartos De Ba\u00d1o (al Por Menor)",
    "sg:phone":"+34 950 14 21 68",
    "sg:postcode":"04230",
    "sg:province":"Almer\u00eda",
    "wof:name":"Romero Abad Jose",
    "wof:placetype":"venue"
},
  "geometry": {"coordinates":[-2.4384589195,36.8639602661],"type":"Point"}
}