{
  "type": "Feature",
  "properties": {
    "iso:country":"ES",
    "sg:address":"Calle de Santa Gema, 16",
    "sg:city":"S. Adrian",
    "sg:orig_category":"Loter\u00cda Y T\u00d3mbola",
    "sg:phone":"+34 948 69 65 85",
    "sg:postcode":"31570",
    "sg:province":"Navarra",
    "wof:name":"Martinez Parra Jose Luis",
    "wof:placetype":"venue"
},
  "geometry": {"coordinates":[-1.9355809689,42.3340415955],"type":"Point"}
}