{
  "type": "Feature",
  "properties": {
    "addr:full":"Calle de La Libertad, 6 Vitoria-gasteiz \u00c1lava 01002",
    "addr:housenumber":"6",
    "addr:postcode":"01002",
    "addr:street":"Calle De La Libertad",
    "iso:country":"ES",
    "sg:address":"Calle de La Libertad, 6",
    "sg:city":"Vitoria-gasteiz",
    "sg:orig_category":"Radiocomunicaciones, Telefon\u00cda M\u00d3vil, Radiomensajer\u00cda: Servicios, Comercializaci\u00d3n",
    "sg:phone":"+34 945 27 63 92",
    "sg:postcode":"01002",
    "sg:province":"\u00c1lava",
    "wof:name":"Distribu Card Phone S.l:",
    "wof:placetype":"venue"
},
  "geometry": {"coordinates":[-2.6672520638,42.847820282],"type":"Point"}
}