{
  "type": "Feature",
  "properties": {
    "addr:full":"Carrer de Girona, 11 Sant Feliu Llobregat Barcelona 08980",
    "addr:housenumber":"11",
    "addr:postcode":"08980",
    "addr:street":"Carrer De Girona",
    "iso:country":"ES",
    "sg:address":"Carrer de Girona, 11",
    "sg:city":"Sant Feliu Llobregat",
    "sg:orig_category":"Farmacias",
    "sg:phone":"+34 936 66 63 51",
    "sg:postcode":"08980",
    "sg:province":"Barcelona",
    "wof:name":"Calvo Gil Maria Encarnacion",
    "wof:placetype":"venue"
},
  "geometry": {"coordinates":[2.051651001,41.3832015991],"type":"Point"}
}