{
  "type": "Feature",
  "properties": {
    "addr:full":"C/ Agoders, 8 Tarrega Lleida 25300",
    "addr:housenumber":"8",
    "addr:postcode":"25300",
    "addr:street":"C / Agoders",
    "iso:country":"ES",
    "sg:address":"C/ Agoders, 8",
    "sg:city":"Tarrega",
    "sg:orig_category":"Agencias De Viajes",
    "sg:phone":"+34 973 50 14 82",
    "sg:postcode":"25300",
    "sg:province":"Lleida",
    "wof:name":"Viatges L'eixida Tours S.l.",
    "wof:placetype":"venue"
},
  "geometry": {"coordinates":[1.1400229931,41.6464881897],"type":"Point"}
}