{
  "type": "Feature",
  "properties": {
    "iso:country":"ES",
    "sg:address":"Carrer de Mercat (del), S/n",
    "sg:city":"Torredembarra",
    "sg:orig_category":"Comercio De Piezas De Recambio Y De Accesorios De Veh\u00cdculos, Veh\u00cdculos Industriales",
    "sg:phone":"+34 977 64 05 86",
    "sg:postcode":"43830",
    "sg:province":"Tarragona",
    "wof:name":"Torres Nuevo Antonio",
    "wof:placetype":"venue"
},
  "geometry": {"coordinates":[1.4026949406,41.1437759399],"type":"Point"}
}