{
  "type": "Feature",
  "properties": {
    "iso:country":"ES",
    "sg:address":"Calle de Angeles (de Los), 16",
    "sg:city":"Mengibar",
    "sg:orig_category":"Empresas De Pintura Y Revestimientos",
    "sg:phone":"+34 953 37 11 27",
    "sg:postcode":"23620",
    "sg:province":"Ja\u00e9n",
    "wof:name":"Bruno Sanchez Juan De Dios",
    "wof:placetype":"venue"
},
  "geometry": {"coordinates":[-3.7999830246,37.9687309265],"type":"Point"}
}