{
  "type": "Feature",
  "properties": {
    "iso:country":"ES",
    "sg:address":"Calle de Poeta Esteban De Villegas, 18",
    "sg:city":"Madrid",
    "sg:orig_category":"Edici\u00d3n De Diarios, Revistas, Boletines",
    "sg:phone":"+34 914 34 82 57",
    "sg:postcode":"28014",
    "sg:province":"Madrid",
    "wof:name":"Garcia Calvo Belen",
    "wof:placetype":"venue"
},
  "geometry": {"coordinates":[-3.6788868904,40.4081420898],"type":"Point"}
}