{
  "type": "Feature",
  "properties": {
    "iso:country":"ES",
    "sg:address":"Carr Andalucia, 16",
    "sg:city":"Villarreal",
    "sg:orig_category":"Fabricaci\u00d3n De Enlosados, Soler\u00cdas",
    "sg:phone":"+34 964 52 20 43",
    "sg:postcode":"12540",
    "sg:province":"Castell\u00f3n",
    "wof:name":"Azulejos Y Gres Vidal S.l.",
    "wof:placetype":"venue"
},
  "geometry": {"coordinates":[-0.0952939987,39.9453048706],"type":"Point"}
}