{
  "type": "Feature",
  "properties": {
    "addr:full":"Calle de Juan Alvargonzalez, 28 Gijon Asturias 33208",
    "addr:housenumber":"28",
    "addr:postcode":"33208",
    "addr:street":"Calle De Juan Alvargonzalez",
    "iso:country":"ES",
    "sg:address":"Calle de Juan Alvargonzalez, 28",
    "sg:city":"Gijon",
    "sg:orig_category":"Pescader\u00cdas (al Por Menor)",
    "sg:phone":"+34 985 38 51 90",
    "sg:postcode":"33208",
    "sg:province":"Asturias",
    "wof:name":"Gonzalez Busta Carmen",
    "wof:placetype":"venue"
},
  "geometry": {"coordinates":[-5.6685872078,43.5301322937],"type":"Point"}
}