{
  "type": "Feature",
  "properties": {
    "iso:country":"ES",
    "sg:address":"Carrer de Alt Camp, 2",
    "sg:city":"Altafulla",
    "sg:orig_category":"Ingenier\u00cda, Centros De Estudios (diversos)",
    "sg:phone":"+34 977 65 00 95",
    "sg:postcode":"43893",
    "sg:province":"Tarragona",
    "wof:name":"Oyaran Ingenieros S.l.",
    "wof:placetype":"venue"
},
  "geometry": {"coordinates":[1.3700000048,41.1447296143],"type":"Point"}
}