{
  "type": "Feature",
  "properties": {
    "addr:full":"Ctra. Gral. Sur, Km. 0023,0 Candelaria Santa Cruz De Tenerife 38530",
    "addr:postcode":"38530",
    "addr:street":"Ctra. Gral. Sur Km. 0023,0",
    "iso:country":"ES",
    "sg:address":"Ctra. Gral. Sur, Km. 0023,0",
    "sg:city":"Candelaria",
    "sg:orig_category":"Administradores De Bienes Y Delegados De Comunidades De Propietarios",
    "sg:phone":"+34 922 50 03 71",
    "sg:postcode":"38530",
    "sg:province":"Santa Cruz De Tenerife",
    "wof:name":"Gestiones Inmobiliarias Pico Birigoyo S.l.",
    "wof:placetype":"venue"
},
  "geometry": {"coordinates":[-16.3717498779,28.3555545807],"type":"Point"}
}