{
  "type": "Feature",
  "properties": {
    "iso:country":"ES",
    "sg:address":"Ctra Codosera, Km. 0004,0",
    "sg:city":"Alburquerque",
    "sg:orig_category":"Molduras, Junquillos, Listones Y Molduras Perforadas",
    "sg:phone":"+34 924 40 00 46",
    "sg:postcode":"06510",
    "sg:province":"Badajoz",
    "wof:name":"Rabazo Mu\u00f1oz Juan Antonio",
    "wof:placetype":"venue"
},
  "geometry": {"coordinates":[-7.0059947968,39.2234420776],"type":"Point"}
}