{
  "type": "Feature",
  "properties": {
    "iso:country":"ES",
    "sg:address":"Rua Convento (do), S/n",
    "sg:city":"Trasponte",
    "sg:orig_category":"Iglesia Cat\u00d3lica",
    "sg:phone":"+34 986 54 80 80",
    "sg:postcode":"36670",
    "sg:province":"Pontevedra",
    "wof:name":"Arzobispado De Santiago",
    "wof:placetype":"venue"
},
  "geometry": {"coordinates":[-8.5685653687,42.6358680725],"type":"Point"}
}