{
  "type": "Feature",
  "properties": {
    "addr:full":"Calle de Tahonas, 1 Valladolid Valladolid 47003",
    "addr:housenumber":"1",
    "addr:postcode":"47003",
    "addr:street":"Calle De Tahonas",
    "iso:country":"ES",
    "sg:address":"Calle de Tahonas, 1",
    "sg:city":"Valladolid",
    "sg:orig_category":"Arquitectos",
    "sg:phone":"+34 983 13 47 75",
    "sg:postcode":"47003",
    "sg:province":"Valladolid",
    "wof:name":"Jimenez Garcia Alberto",
    "wof:placetype":"venue"
},
  "geometry": {"coordinates":[-4.7285470963,41.6590499878],"type":"Point"}
}