{
  "type": "Feature",
  "properties": {
    "iso:country":"ES",
    "sg:address":"Valencia, S/n",
    "sg:city":"Puerto Rico",
    "sg:orig_category":"Bazares, Art\u00cdculos De Limpieza Y De Cocina (al Por Menor)",
    "sg:phone":"+34 928 56 11 52",
    "sg:postcode":"35130",
    "sg:province":"Las Palmas",
    "wof:name":"Suilan  Zhu",
    "wof:placetype":"venue"
},
  "geometry": {"coordinates":[-15.7144145966,27.7864627838],"type":"Point"}
}