{
  "type": "Feature",
  "properties": {
    "iso:country":"ES",
    "sg:address":"C. Calera Y Chozas, Km. 0010,0",
    "sg:city":"Alberche Caudillo",
    "sg:orig_category":"Transportes Urbanos Y Regionales Para Personas",
    "sg:phone":"+34 925 84 90 71",
    "sg:postcode":"45695",
    "sg:province":"Toledo",
    "wof:name":"Autocares Vilar S.a.",
    "wof:placetype":"venue"
},
  "geometry": {"coordinates":[-4.933303833,39.907951355],"type":"Point"}
}