{
  "type": "Feature",
  "properties": {
    "iso:country":"ES",
    "sg:address":"Calle de Pelayo, 8",
    "sg:city":"Zamora",
    "sg:orig_category":"Abogados",
    "sg:phone":"+34 980 67 00 27",
    "sg:postcode":"49014",
    "sg:province":"Zamora",
    "wof:name":"Perez Rodriguez Milagros",
    "wof:placetype":"venue"
},
  "geometry": {"coordinates":[-5.7432789803,41.506526947],"type":"Point"}
}