{
  "type": "Feature",
  "properties": {
    "addr:full":"Calle de Menorca, 37 Humanes De Madrid Madrid 28970",
    "addr:housenumber":"37",
    "addr:postcode":"28970",
    "addr:street":"Calle De Menorca",
    "iso:country":"ES",
    "sg:address":"Calle de Menorca, 37",
    "sg:city":"Humanes De Madrid",
    "sg:orig_category":"Asesor\u00cda Fiscal Y Jur\u00cddica",
    "sg:phone":"+34 916 04 18 71",
    "sg:postcode":"28970",
    "sg:province":"Madrid",
    "wof:name":"Cash Humanes S.l.",
    "wof:placetype":"venue"
},
  "geometry": {"coordinates":[-3.8238949776,40.2560310364],"type":"Point"}
}