{
  "type": "Feature",
  "properties": {
    "iso:country":"ES",
    "sg:address":"Calle de Higueras, 9",
    "sg:city":"Fromista",
    "sg:orig_category":"Servicios De Correos",
    "sg:phone":"+34 979 81 00 72",
    "sg:postcode":"34440",
    "sg:province":"Palencia",
    "wof:name":"Sociedad Estatal Correos Y Telegrafos S.a.",
    "wof:placetype":"venue"
},
  "geometry": {"coordinates":[-4.4037890434,42.2677154541],"type":"Point"}
}