{
  "type": "Feature",
  "properties": {
    "addr:full":"Avda Arcadio Pardi\u00d1as, 161 Burela Lugo 27880",
    "addr:housenumber":"161",
    "addr:postcode":"27880",
    "addr:street":"Avda Arcadio Pardin\u0303As",
    "iso:country":"ES",
    "sg:address":"Avda Arcadio Pardi\u00d1as, 161",
    "sg:city":"Burela",
    "sg:orig_category":"Ropa Para Ni\u00d1os (al Por Menor)",
    "sg:phone":"+34 982 58 61 31",
    "sg:postcode":"27880",
    "sg:province":"Lugo",
    "wof:name":"Moreda Perez Marianela",
    "wof:placetype":"venue"
},
  "geometry": {"coordinates":[-7.3563251495,43.6540489197],"type":"Point"}
}