{
  "type": "Feature",
  "properties": {
    "iso:country":"ES",
    "sg:address":"Carr Riu Magre, (del), 8",
    "sg:city":"Carlet",
    "sg:orig_category":"Promotores Constructores",
    "sg:phone":"+34 962 53 18 08",
    "sg:postcode":"46240",
    "sg:province":"Valencia",
    "wof:name":"Vidal Candel Vicente",
    "wof:placetype":"venue"
},
  "geometry": {"coordinates":[-0.5176360011,39.2231483459],"type":"Point"}
}