{
  "type": "Feature",
  "properties": {
    "iso:country":"ES",
    "sg:address":"Avda Constitucion, 8",
    "sg:city":"Gijon",
    "sg:orig_category":"Electrodom\u00c9sticos (al Por Menor)",
    "sg:phone":"+34 985 35 15 93",
    "sg:postcode":"33207",
    "sg:province":"Asturias",
    "wof:name":"Gonzalez Palacio Jose Alberto",
    "wof:placetype":"venue"
},
  "geometry": {"coordinates":[-5.6655569077,43.5371627808],"type":"Point"}
}