{
  "type": "Feature",
  "properties": {
    "addr:full":"Calle de Roa De La Vega, 14 Le\u00f3n Le\u00f3n 24002",
    "addr:housenumber":"14",
    "addr:postcode":"24002",
    "addr:street":"Calle De Roa De La Vega;Leo\u0301N",
    "iso:country":"ES",
    "sg:address":"Calle de Roa De La Vega, 14",
    "sg:city":"Le\u00f3n",
    "sg:orig_category":"Asesor\u00cda Sobre Comunicaci\u00d3n De Empresas",
    "sg:phone":"+34 987 24 55 22",
    "sg:postcode":"24002",
    "sg:province":"Le\u00f3n",
    "wof:name":"Casas Lozano Pedro",
    "wof:placetype":"venue"
},
  "geometry": {"coordinates":[-5.5771279335,42.6002693176],"type":"Point"}
}