{
  "type": "Feature",
  "properties": {
    "iso:country":"ES",
    "sg:address":"Conj. Estepona Garden, S/n",
    "sg:city":"Estepona",
    "sg:orig_category":"T\u00c9cnicos Veterinarios",
    "sg:phone":"+34 951 31 82 92",
    "sg:postcode":"29680",
    "sg:province":"M\u00e1laga",
    "wof:name":"Prieto Fernandez Antonio",
    "wof:placetype":"venue"
},
  "geometry": {"coordinates":[-5.1788620949,36.4150428772],"type":"Point"}
}