{
  "type": "Feature",
  "properties": {
    "addr:full":"Avda Ciudad De Barcelona, 218 Madrid Madrid 28007",
    "addr:housenumber":"218",
    "addr:postcode":"28007",
    "addr:street":"Avda Ciudad De Barcelona",
    "iso:country":"ES",
    "sg:address":"Avda Ciudad De Barcelona, 218",
    "sg:city":"Madrid",
    "sg:orig_category":"Abogados",
    "sg:phone":"+34 914 34 96 87",
    "sg:postcode":"28007",
    "sg:province":"Madrid",
    "wof:name":"Garcia Arenas Francisco",
    "wof:placetype":"venue"
},
  "geometry": {"coordinates":[-3.6708590984,40.3989944458],"type":"Point"}
}