{
  "type": "Feature",
  "properties": {
    "iso:country":"ES",
    "sg:address":"Plaz Fuente, 19",
    "sg:city":"Aguilafuente",
    "sg:orig_category":"Alimentaci\u00d3n General (al Por Menor)",
    "sg:phone":"+34 921 57 20 18",
    "sg:postcode":"40340",
    "sg:province":"Segovia",
    "wof:name":"Lopez Martin Doroteo",
    "wof:placetype":"venue"
},
  "geometry": {"coordinates":[-4.1121788025,41.2264862061],"type":"Point"}
}