{
  "type": "Feature",
  "properties": {
    "iso:country":"ES",
    "sg:address":"Avda Pablo Neruda, 134",
    "sg:city":"Madrid",
    "sg:orig_category":"Tintes (fabricaci\u00d3n, Al Por Mayor)",
    "sg:phone":"+34 913 03 60 32",
    "sg:postcode":"28018",
    "sg:province":"Madrid",
    "sg:website":"www.pressto.com",
    "wof:name":"Ca\u00f1a Santa S.l.",
    "wof:placetype":"venue"
},
  "geometry": {"coordinates":[-3.6579809189,40.3816184998],"type":"Point"}
}