{
  "type": "Feature",
  "properties": {
    "addr:full":"Avda Valencia, 10 Requena Valencia 46340",
    "addr:housenumber":"10",
    "addr:postcode":"46340",
    "addr:street":"Avda Valencia",
    "iso:country":"ES",
    "sg:address":"Avda Valencia, 10",
    "sg:city":"Requena",
    "sg:orig_category":"Promotores Constructores",
    "sg:phone":"+34 962 30 02 87",
    "sg:postcode":"46340",
    "sg:province":"Valencia",
    "wof:name":"Comunidad Propietarios Valencia 10",
    "wof:placetype":"venue"
},
  "geometry": {"coordinates":[-1.1024509668,39.4858169556],"type":"Point"}
}