{
  "type": "Feature",
  "properties": {
    "addr:full":"Avda Madrid, 8 Torrejon Ardoz Madrid 28850",
    "addr:housenumber":"8",
    "addr:postcode":"28850",
    "addr:street":"Avda Madrid",
    "iso:country":"ES",
    "sg:address":"Avda Madrid, 8",
    "sg:city":"Torrejon Ardoz",
    "sg:orig_category":"Inform\u00c1tica (estudios, Servicios, Asesor\u00cda, Formaci\u00d3n)",
    "sg:phone":"+34 916 75 15 30",
    "sg:postcode":"28850",
    "sg:province":"Madrid",
    "wof:name":"Romergo S.l.",
    "wof:placetype":"venue"
},
  "geometry": {"coordinates":[-3.4710299969,40.4639511108],"type":"Point"}
}