{
  "type": "Feature",
  "properties": {
    "addr:full":"Calle de Ancha, 67 Sanlucar De Barrameda C\u00e1diz 11540",
    "addr:housenumber":"67",
    "addr:postcode":"11540",
    "addr:street":"Calle De Ancha;Ca\u0301Diz",
    "iso:country":"ES",
    "sg:address":"Calle de Ancha, 67",
    "sg:city":"Sanlucar De Barrameda",
    "sg:orig_category":"Ense\u00d1anza: Profesiones Art\u00cdsticas",
    "sg:phone":"+34 956 38 21 15",
    "sg:postcode":"11540",
    "sg:province":"C\u00e1diz",
    "wof:name":"Salgado Garcia Jose Ramon",
    "wof:placetype":"venue"
},
  "geometry": {"coordinates":[-6.3520040512,36.779510498],"type":"Point"}
}