{
  "type": "Feature",
  "properties": {
    "addr:full":"Calle de Doctor Fleming, 46 Madrid Madrid 28036",
    "addr:housenumber":"46",
    "addr:postcode":"madrid;28036",
    "addr:street":"Calle De Doctor Fleming",
    "iso:country":"ES",
    "sg:address":"Calle de Doctor Fleming, 46",
    "sg:city":"Madrid",
    "sg:orig_category":"Arquitectos",
    "sg:phone":"+34 913 50 68 19",
    "sg:postcode":"28036",
    "sg:province":"Madrid",
    "wof:name":"Gestion Ordenacion Y Dise\u00f1o S. L.",
    "wof:placetype":"venue"
},
  "geometry": {"coordinates":[-3.6878356934,40.4613876343],"type":"Point"}
}