{
  "type": "Feature",
  "properties": {
    "addr:full":"Calle de Florencio Quintero, 16 Sevilla Sevilla 41009",
    "addr:housenumber":"16",
    "addr:postcode":"41009",
    "addr:street":"Calle De Florencio Quintero",
    "iso:country":"ES",
    "sg:address":"Calle de Florencio Quintero, 16",
    "sg:city":"Sevilla",
    "sg:orig_category":"Confecci\u00d3n De Trajes Para Se\u00d1oras",
    "sg:phone":"+34 954 37 07 77",
    "sg:postcode":"41009",
    "sg:province":"Sevilla",
    "wof:name":"Ortega Rabay Antonio",
    "wof:placetype":"venue"
},
  "geometry": {"coordinates":[-5.984732151,37.4020805359],"type":"Point"}
}