{
  "type": "Feature",
  "properties": {
    "iso:country":"ES",
    "sg:address":"Plaz Mayor, 4",
    "sg:city":"Burgos",
    "sg:orig_category":"Abogados",
    "sg:phone":"+34 947 26 52 46",
    "sg:postcode":"09003",
    "sg:province":"Burgos",
    "wof:name":"Gilam 2002 S.l",
    "wof:placetype":"venue"
},
  "geometry": {"coordinates":[-3.7015550137,42.3406295776],"type":"Point"}
}