{
  "type": "Feature",
  "properties": {
    "addr:full":"Carrer de Occident, S/n Hospitalet Llobregat Barcelona 08903",
    "addr:housenumber":"s",
    "addr:postcode":"08903",
    "addr:street":"Carrer De Occident;/ N",
    "iso:country":"ES",
    "sg:address":"Carrer de Occident, S/n",
    "sg:city":"Hospitalet Llobregat",
    "sg:orig_category":"Ropa Para Se\u00d1oras (al Por Menor)",
    "sg:phone":"+34 934 40 09 78",
    "sg:postcode":"08903",
    "sg:province":"Barcelona",
    "wof:name":"Pascual Montalban Maria Jose",
    "wof:placetype":"venue"
},
  "geometry": {"coordinates":[2.1197841167,41.3749771118],"type":"Point"}
}