{
  "type": "Feature",
  "properties": {
    "addr:full":"Calle de Flor De Acebo, 23 Valladolid Valladolid 47012",
    "addr:housenumber":"23",
    "addr:postcode":"47012",
    "addr:street":"Calle De Flor De Acebo",
    "iso:country":"ES",
    "sg:address":"Calle de Flor De Acebo, 23",
    "sg:city":"Valladolid",
    "sg:orig_category":"Dibujantes (diversos)",
    "sg:phone":"+34 983 29 50 27",
    "sg:postcode":"47012",
    "sg:province":"Valladolid",
    "wof:name":"Industrias Maxi S. A.",
    "wof:placetype":"venue"
},
  "geometry": {"coordinates":[-4.6938180923,41.6449966431],"type":"Point"}
}