{
  "type": "Feature",
  "properties": {
    "iso:country":"ES",
    "sg:address":"Avda Galdar (de), 60",
    "sg:city":"San Fernando",
    "sg:orig_category":"Art\u00cdculos De Decoraci\u00d3n",
    "sg:phone":"+34 928 76 44 95",
    "sg:postcode":"35100",
    "sg:province":"Las Palmas",
    "wof:name":"Decoracion Sur S. L.",
    "wof:placetype":"venue"
},
  "geometry": {"coordinates":[-15.5842504501,28.0904903412],"type":"Point"}
}