{
  "type": "Feature",
  "properties": {
    "addr:full":"Avda Montendre, 1 Onda Castell\u00f3n 12200",
    "addr:housenumber":"1",
    "addr:postcode":"12200",
    "addr:street":"Avda Montendre;Castello\u0301N",
    "iso:country":"ES",
    "sg:address":"Avda Montendre, 1",
    "sg:city":"Onda",
    "sg:orig_category":"Art\u00cdculos De Regalo (al Por Menor)",
    "sg:phone":"+34 964 60 53 78",
    "sg:postcode":"12200",
    "sg:province":"Castell\u00f3n",
    "wof:name":"Herrera Aguilella Dolores",
    "wof:placetype":"venue"
},
  "geometry": {"coordinates":[-0.262609005,39.9651603699],"type":"Point"}
}