{
  "type": "Feature",
  "properties": {
    "addr:full":"Avda Elda (de), 66 Petrer Alicante 03610",
    "addr:housenumber":"66",
    "addr:postcode":"03610",
    "addr:street":"Avda Elda De",
    "iso:country":"ES",
    "sg:address":"Avda Elda (de), 66",
    "sg:city":"Petrer",
    "sg:orig_category":"Peluquer\u00cdas, Peluquer\u00cda Mixta",
    "sg:phone":"+34 966 95 26 13",
    "sg:postcode":"03610",
    "sg:province":"Alicante",
    "wof:name":"Lozano Garrido Milagros",
    "wof:placetype":"venue"
},
  "geometry": {"coordinates":[-0.7812190056,38.4831428528],"type":"Point"}
}