{
  "type": "Feature",
  "properties": {
    "addr:full":"Av La Marina, S/n Benissa Alicante 03720",
    "addr:housenumber":"s / n",
    "addr:postcode":"03720",
    "addr:street":"Av La Marina",
    "iso:country":"ES",
    "sg:address":"Av La Marina, S/n",
    "sg:city":"Benissa",
    "sg:orig_category":"Cajas De Ahorro",
    "sg:phone":"+34 966 49 79 64",
    "sg:postcode":"03720",
    "sg:province":"Alicante",
    "wof:name":"Caja De Ahorros De Valencia Castellon Y Alicante",
    "wof:placetype":"venue"
},
  "geometry": {"coordinates":[0.0841030031,38.6644058228],"type":"Point"}
}