{
  "type": "Feature",
  "properties": {
    "addr:full":"Cra. Maella, S/n Batea Tarragona 43786",
    "addr:housenumber":"s / n",
    "addr:postcode":"43786",
    "iso:country":"ES",
    "sg:address":"Cra. Maella, S/n",
    "sg:city":"Batea",
    "sg:orig_category":"Chapister\u00cda",
    "sg:phone":"+34 977 43 06 91",
    "sg:postcode":"43786",
    "sg:province":"Tarragona",
    "wof:name":"Jardi Su\u00f1e Esteve",
    "wof:placetype":"venue"
},
  "geometry": {"coordinates":[0.3131969869,41.0934867859],"type":"Point"}
}