{
  "type": "Feature",
  "properties": {
    "addr:full":"Ctra Alicante-oca\u00f1a, Km. 0035,5 Petrer Alicante 03610",
    "addr:postcode":"03610",
    "addr:street":"Ctra Alicante-Ocan\u0303A Km. 0035,5",
    "iso:country":"ES",
    "sg:address":"Ctra Alicante-oca\u00f1a, Km. 0035,5",
    "sg:city":"Petrer",
    "sg:orig_category":"Peluquer\u00cdas",
    "sg:phone":"+34 965 37 36 36",
    "sg:postcode":"03610",
    "sg:province":"Alicante",
    "wof:name":"Mu\u00f1oz Arrogante Pablo",
    "wof:placetype":"venue"
},
  "geometry": {"coordinates":[-0.7859489918,38.489315033],"type":"Point"}
}