{
  "type": "Feature",
  "properties": {
    "addr:full":"Calle de Santuario De Rodanas, 1 Zaragoza Zaragoza 50002",
    "addr:housenumber":"1",
    "addr:postcode":"50002",
    "addr:street":"Calle De Santuario De Rodanas",
    "iso:country":"ES",
    "sg:address":"Calle de Santuario De Rodanas, 1",
    "sg:city":"Zaragoza",
    "sg:orig_category":"Producci\u00d3n, Venta De Productos De Agricultura Biol\u00d3gica",
    "sg:phone":"+34 976 42 18 52",
    "sg:postcode":"50002",
    "sg:province":"Zaragoza",
    "wof:name":"Baldovin Mallor Antonio",
    "wof:placetype":"venue"
},
  "geometry": {"coordinates":[-0.8666909933,41.6481971741],"type":"Point"}
}