{
  "type": "Feature",
  "properties": {
    "addr:full":"Horno Del, 5 Cullar-vega Granada 18195",
    "addr:postcode":"18195",
    "iso:country":"ES",
    "sg:address":"Horno Del, 5",
    "sg:city":"Cullar-vega",
    "sg:orig_category":"Empresas De Carpinter\u00cda",
    "sg:phone":"+34 958 58 69 95",
    "sg:postcode":"18195",
    "sg:province":"Granada",
    "wof:name":"Talleres Metalurgico Amigo S.l.",
    "wof:placetype":"venue"
},
  "geometry": {"coordinates":[-3.6728439331,37.1526565552],"type":"Point"}
}