{
  "type": "Feature",
  "properties": {
    "iso:country":"ES",
    "sg:address":"Plaz Jolea (la), 7",
    "sg:city":"Calatayud",
    "sg:orig_category":"Carnicer\u00cdas, Carnicer\u00cdas",
    "sg:phone":"+34 976 88 12 84",
    "sg:postcode":"50300",
    "sg:province":"Zaragoza",
    "wof:name":"Marin Yag\u00fce Antonio",
    "wof:placetype":"venue"
},
  "geometry": {"coordinates":[-1.6394540071,41.3522415161],"type":"Point"}
}