{
  "type": "Feature",
  "properties": {
    "addr:full":"Calle de Herradores, 24 Teba M\u00e1laga 29327",
    "addr:housenumber":"24",
    "addr:postcode":"29327",
    "addr:street":"Calle De Herradores",
    "iso:country":"ES",
    "sg:address":"Calle de Herradores, 24",
    "sg:city":"Teba",
    "sg:orig_category":"Bancos",
    "sg:phone":"+34 952 74 81 99",
    "sg:postcode":"29327",
    "sg:province":"M\u00e1laga",
    "sg:website":"www.batlantico.es",
    "wof:name":"Banc Sabadell S.a.",
    "wof:placetype":"venue"
},
  "geometry": {"coordinates":[-4.9187288284,36.9829788208],"type":"Point"}
}