{
  "type": "Feature",
  "properties": {
    "iso:country":"ES",
    "sg:address":"Avda Bilbao, 5",
    "sg:city":"Torrelavega",
    "sg:orig_category":"Material Y Herramientas Agr\u00cdcolas",
    "sg:phone":"+34 942 80 21 23",
    "sg:postcode":"39300",
    "sg:province":"Cantabria",
    "wof:name":"Rodriguez Fernandez Jose Maria",
    "wof:placetype":"venue"
},
  "geometry": {"coordinates":[-4.0435190201,43.3472213745],"type":"Point"}
}