{
  "type": "Feature",
  "properties": {
    "addr:full":"Calle de Almirante Lobo, 13 Sevilla Sevilla 41001",
    "addr:housenumber":"13",
    "addr:postcode":"41001",
    "addr:street":"Calle De Almirante Lobo",
    "iso:country":"ES",
    "sg:address":"Calle de Almirante Lobo, 13",
    "sg:city":"Sevilla",
    "sg:orig_category":"Bazares, Art\u00cdculos De Limpieza Y De Cocina (al Por Menor)",
    "sg:phone":"+34 954 22 30 91",
    "sg:postcode":"41001",
    "sg:province":"Sevilla",
    "wof:name":"Mostaza Aonso Raul",
    "wof:placetype":"venue"
},
  "geometry": {"coordinates":[-5.9942474365,37.3822746277],"type":"Point"}
}