{
  "type": "Feature",
  "properties": {
    "iso:country":"ES",
    "sg:address":"Calle de Germanells, 37",
    "sg:city":"Rafelbunyol",
    "sg:orig_category":"Agencias De Trabajo Temporal",
    "sg:phone":"+34 961 41 33 66",
    "sg:postcode":"46138",
    "sg:province":"Valencia",
    "wof:name":"Centro Especial De Empleo De Rafelbu\u00f1ol S.a.",
    "wof:placetype":"venue"
},
  "geometry": {"coordinates":[-0.3272840083,39.5889968872],"type":"Point"}
}