{
  "type": "Feature",
  "properties": {
    "addr:full":"Larra\u00f1eta Karrika, 8 Auritz Navarra 31640",
    "addr:housenumber":"8",
    "addr:postcode":"31640",
    "addr:street":"Larran\u0303Eta Karrika;Navarra",
    "iso:country":"ES",
    "sg:address":"Larra\u00f1eta Karrika, 8",
    "sg:city":"Auritz",
    "sg:orig_category":"Ingenier\u00cda, Centros De Estudios (diversos)",
    "sg:phone":"+34 948 76 00 83",
    "sg:postcode":"31640",
    "sg:province":"Navarra",
    "wof:name":"Construcciones Tiraplegui S. L.",
    "wof:placetype":"venue"
},
  "geometry": {"coordinates":[-1.3332680464,42.989780426],"type":"Point"}
}