{
  "type": "Feature",
  "properties": {
    "addr:full":"Calle de Real, 22 Valdepe\u00f1as Ciudad Real 13300",
    "addr:housenumber":"22",
    "addr:postcode":"13300",
    "addr:street":"Calle De Real",
    "iso:country":"ES",
    "sg:address":"Calle de Real, 22",
    "sg:city":"Valdepe\u00f1as",
    "sg:orig_category":"Fotograf\u00cda Art\u00cdstica Y Retratos",
    "sg:phone":"+34 926 32 19 76",
    "sg:postcode":"13300",
    "sg:province":"Ciudad Real",
    "wof:name":"Navarrete Garcia Antonio",
    "wof:placetype":"venue"
},
  "geometry": {"coordinates":[-3.3832089901,38.7622756958],"type":"Point"}
}