{
  "type": "Feature",
  "properties": {
    "addr:full":"Urbanizacion Parque Antena, S/n Estepona M\u00e1laga 29680",
    "addr:housenumber":"s / n",
    "addr:postcode":"29680",
    "iso:country":"ES",
    "sg:address":"Urbanizacion Parque Antena, S/n",
    "sg:city":"Estepona",
    "sg:orig_category":"Agencias Y Agentes Comerciales, Representantes",
    "sg:phone":"+34 952 80 23 17",
    "sg:postcode":"29680",
    "sg:province":"M\u00e1laga",
    "wof:name":"Gomez Mena Salvador",
    "wof:placetype":"venue"
},
  "geometry": {"coordinates":[-5.1452140808,36.4275817871],"type":"Point"}
}