{
  "type": "Feature",
  "properties": {
    "addr:full":"Calle de Mayor, 40 Corella Navarra 31591",
    "addr:housenumber":"40",
    "addr:postcode":"31591",
    "addr:street":"Calle De Mayor",
    "iso:country":"ES",
    "sg:address":"Calle de Mayor, 40",
    "sg:city":"Corella",
    "sg:orig_category":"Abogados",
    "sg:phone":"+34 948 78 13 59",
    "sg:postcode":"31591",
    "sg:province":"Navarra",
    "wof:name":"Arellano Rios Pilar",
    "wof:placetype":"venue"
},
  "geometry": {"coordinates":[-1.7856167555,42.1146469116],"type":"Point"}
}