{
  "type": "Feature",
  "properties": {
    "iso:country":"ES",
    "sg:address":"Carrer de Sant Marc, 26",
    "sg:city":"Barcelona",
    "sg:orig_category":"Material Y Suministros Para Peluquer\u00cda",
    "sg:phone":"+34 932 17 92 53",
    "sg:postcode":"08012",
    "sg:province":"Barcelona",
    "wof:name":"Tesseract Info S.l.",
    "wof:placetype":"venue"
},
  "geometry": {"coordinates":[2.1523330212,41.4006729126],"type":"Point"}
}