{
  "type": "Feature",
  "properties": {
    "addr:full":"Calle de Aguere, 14 Santa Cruz De Tenerife Santa Cruz De Tenerife 38005",
    "addr:housenumber":"14",
    "addr:postcode":"38005",
    "addr:street":"Calle De Aguere",
    "iso:country":"ES",
    "sg:address":"Calle de Aguere, 14",
    "sg:city":"Santa Cruz De Tenerife",
    "sg:orig_category":"Ense\u00d1anza: Comercio, Gesti\u00d3n, Inform\u00c1tica",
    "sg:phone":"+34 922 20 31 00",
    "sg:postcode":"38005",
    "sg:province":"Santa Cruz De Tenerife",
    "sg:website":"www.institutocibernos.com",
    "wof:name":"Formastur S.a",
    "wof:placetype":"venue"
},
  "geometry": {"coordinates":[-16.2521324158,28.4643115997],"type":"Point"}
}