{
  "type": "Feature",
  "properties": {
    "iso:country":"ES",
    "sg:address":"Carrer de Cami Antic De Vic, S/n",
    "sg:city":"Corro D'avall",
    "sg:orig_category":"Promotores Constructores",
    "sg:phone":"+34 938 40 54 54",
    "sg:postcode":"08520",
    "sg:province":"Barcelona",
    "wof:name":"Preformatex S.l.",
    "wof:placetype":"venue"
},
  "geometry": {"coordinates":[2.2962567806,41.6326560974],"type":"Point"}
}