{
  "type": "Feature",
  "properties": {
    "iso:country":"ES",
    "sg:address":"Calle de Segovia (de), 8",
    "sg:city":"Fuenlabrada",
    "sg:orig_category":"Alimentaci\u00d3n General (al Por Menor)",
    "sg:phone":"+34 916 85 60 11",
    "sg:postcode":"28941",
    "sg:province":"Madrid",
    "wof:name":"Luyfan S.l",
    "wof:placetype":"venue"
},
  "geometry": {"coordinates":[-3.8036050797,40.2912139893],"type":"Point"}
}