{
  "type": "Feature",
  "properties": {
    "iso:country":"ES",
    "sg:address":"Avda Planetario, 30",
    "sg:city":"Madrid",
    "sg:orig_category":"Carnes De Carnicer\u00cda (al Por Mayor)",
    "sg:phone":"+34 915 06 18 77",
    "sg:postcode":"28045",
    "sg:province":"Madrid",
    "wof:name":"Astrid Traiding Internacional S.l.",
    "wof:placetype":"venue"
},
  "geometry": {"coordinates":[-3.6852242947,40.3908081055],"type":"Point"}
}