{
  "type": "Feature",
  "properties": {
    "iso:country":"ES",
    "sg:address":"C/ Baixamar, 15",
    "sg:city":"Alaior",
    "sg:orig_category":"Electricidad: Instaladores",
    "sg:phone":"+34 971 37 18 75",
    "sg:postcode":"07730",
    "sg:province":"Islas Baleares",
    "wof:name":"Automatismos Menorca S.l",
    "wof:placetype":"venue"
},
  "geometry": {"coordinates":[4.1382350922,39.9342803955],"type":"Point"}
}