{
  "type": "Feature",
  "properties": {
    "iso:country":"ES",
    "sg:address":"Pase Goya (de), 15",
    "sg:city":"Mostoles",
    "sg:orig_category":"Trabajos De Perforaciones, Sondeos, Construcci\u00d3n De Pozos",
    "sg:phone":"+34 916 13 27 00",
    "sg:postcode":"28932",
    "sg:province":"Madrid",
    "wof:name":"Industrial De Sondeos S. A.",
    "wof:placetype":"venue"
},
  "geometry": {"coordinates":[-3.8649389744,40.3230667114],"type":"Point"}
}