{
  "type": "Feature",
  "properties": {
    "addr:full":"Rda. N. Monturiol, 25 Cabrera Mar Barcelona 08349",
    "addr:housenumber":"25",
    "addr:postcode":"08349",
    "addr:street":"N. Monturiol",
    "iso:country":"ES",
    "sg:address":"Rda. N. Monturiol, 25",
    "sg:city":"Cabrera Mar",
    "sg:orig_category":"Ferreter\u00cda (diversos)",
    "sg:phone":"+34 937 54 02 58",
    "sg:postcode":"08349",
    "sg:province":"Barcelona",
    "wof:name":"Hispano Italiana De Aluminio S.l",
    "wof:placetype":"venue"
},
  "geometry": {"coordinates":[2.4156479836,41.529964447],"type":"Point"}
}