{
  "type": "Feature",
  "properties": {
    "iso:country":"ES",
    "sg:address":"Av Pau Casals, 145",
    "sg:city":"Hospitalet Llobregat",
    "sg:orig_category":"Importaci\u00d3n",
    "sg:phone":"+34 932 63 15 49",
    "sg:postcode":"08907",
    "sg:province":"Barcelona",
    "wof:name":"Carine Trading S.l.",
    "wof:placetype":"venue"
},
  "geometry": {"coordinates":[2.1048998833,41.3587303162],"type":"Point"}
}