{
  "type": "Feature",
  "properties": {
    "iso:country":"ES",
    "sg:address":"Calle de Estrella Polar, 8",
    "sg:city":"Madrid",
    "sg:orig_category":"Tintes (fabricaci\u00d3n, Al Por Mayor)",
    "sg:phone":"+34 914 09 21 95",
    "sg:postcode":"28007",
    "sg:province":"Madrid",
    "wof:name":"Gonzalez Perez Francisco",
    "wof:placetype":"venue"
},
  "geometry": {"coordinates":[-3.6670458317,40.4107513428],"type":"Point"}
}