{
  "type": "Feature",
  "properties": {
    "addr:full":"Calle de Benidorm, 1 Madrid Madrid 28017",
    "addr:housenumber":"1",
    "addr:postcode":"28017",
    "addr:street":"Calle De Benidorm",
    "iso:country":"ES",
    "sg:address":"Calle de Benidorm, 1",
    "sg:city":"Madrid",
    "sg:orig_category":"Muebles, Minoristas",
    "sg:phone":"+34 917 25 14 92",
    "sg:postcode":"28017",
    "sg:province":"Madrid",
    "wof:name":"Gancedo Lopez Manuel",
    "wof:placetype":"venue"
},
  "geometry": {"coordinates":[-3.6571974754,40.4305953979],"type":"Point"}
}