{
  "type": "Feature",
  "properties": {
    "iso:country":"ES",
    "sg:address":"Calle de Conde De Benavente, 1",
    "sg:city":"Valladolid",
    "sg:orig_category":"Peluqueros: De Se\u00d1oras",
    "sg:phone":"+34 983 35 59 89",
    "sg:postcode":"47003",
    "sg:province":"Valladolid",
    "wof:name":"Moyano Torres Benita",
    "wof:placetype":"venue"
},
  "geometry": {"coordinates":[-4.7303090096,41.6581993103],"type":"Point"}
}