{
  "type": "Feature",
  "properties": {
    "iso:country":"ES",
    "sg:address":"Pl Espanya, 3",
    "sg:city":"Mataro",
    "sg:orig_category":"Inmobiliaria (agencias)",
    "sg:phone":"+34 937 90 29 90",
    "sg:postcode":"08301",
    "sg:province":"Barcelona",
    "wof:name":"Aguila Garcia Francisco",
    "wof:placetype":"venue"
},
  "geometry": {"coordinates":[2.4424426556,41.5447349548],"type":"Point"}
}