{
  "type": "Feature",
  "properties": {
    "iso:country":"ES",
    "sg:address":"Calle de Iris, 6",
    "sg:city":"Albacete",
    "sg:orig_category":"Aparcamientos (infraestructuras, Accesorios)",
    "sg:phone":"+34 967 21 77 96",
    "sg:postcode":"02005",
    "sg:province":"Albacete",
    "wof:name":"Gomez Gomez Anselmo",
    "wof:placetype":"venue"
},
  "geometry": {"coordinates":[-1.8539979458,38.9976081848],"type":"Point"}
}