{
  "type": "Feature",
  "properties": {
    "addr:full":"Calle de Castelao, 46 Malaga M\u00e1laga 29004",
    "addr:housenumber":"46",
    "addr:postcode":"29004",
    "addr:street":"Calle De Castelao;Ma\u0301Laga",
    "iso:country":"ES",
    "sg:address":"Calle de Castelao, 46",
    "sg:city":"Malaga",
    "sg:orig_category":"Fabricaci\u00d3n De Bibliotecas Y Estanter\u00cdas",
    "sg:phone":"+34 952 24 55 50",
    "sg:postcode":"29004",
    "sg:province":"M\u00e1laga",
    "sg:website":"www.mecalux.com",
    "wof:name":"Mecalux Servis S.a.",
    "wof:placetype":"venue"
},
  "geometry": {"coordinates":[-4.4842448235,36.695098877],"type":"Point"}
}