{
  "type": "Feature",
  "properties": {
    "iso:country":"ES",
    "sg:address":"Pl Santa Eulalia, 15",
    "sg:city":"Barcelona",
    "sg:orig_category":"Cobro De Pr\u00c9stamos",
    "sg:phone":"+34 934 29 78 19",
    "sg:postcode":"08031",
    "sg:province":"Barcelona",
    "wof:name":"Servicios Integrales De Informes Y Gesti",
    "wof:placetype":"venue"
},
  "geometry": {"coordinates":[2.1715619564,41.4291687012],"type":"Point"}
}