{
  "type": "Feature",
  "properties": {
    "addr:full":"Carretera, S/n Prullans Lleida 25727",
    "addr:postcode":"25727",
    "addr:street":"Carretera S / N",
    "iso:country":"ES",
    "sg:address":"Carretera, S/n",
    "sg:city":"Prullans",
    "sg:orig_category":"Agricultura: Abastecimiento Y Cosechado (negocio)",
    "sg:phone":"+34 973 29 30 84",
    "sg:postcode":"25727",
    "sg:province":"Lleida",
    "wof:name":"Escuder De Boet Jose Maria",
    "wof:placetype":"venue"
},
  "geometry": {"coordinates":[1.7381739616,42.3789787292],"type":"Point"}
}