{
  "type": "Feature",
  "properties": {
    "iso:country":"ES",
    "sg:address":"Calle de Areta, 22",
    "sg:orig_category":"Molduras, Junquillos, Listones Y Molduras Perforadas",
    "sg:phone":"+34 944 66 74 90",
    "sg:postcode":"01400",
    "sg:province":"\u00c1lava",
    "wof:name":"Juan Carlos Calavia Olmo",
    "wof:placetype":"venue"
},
  "geometry": {"coordinates":[-2.9495387077,43.148349762],"type":"Point"}
}