{
  "type": "Feature",
  "properties": {
    "iso:country":"ES",
    "sg:address":"Avda San Miguel De Chimisay, 224",
    "sg:city":"Taco",
    "sg:orig_category":"Comercio De Piezas De Recambio Y De Accesorios De Veh\u00cdculos, Veh\u00cdculos Industriales",
    "sg:phone":"+34 922 82 03 28",
    "sg:postcode":"38108",
    "sg:province":"Santa Cruz De Tenerife",
    "wof:name":"Gonzalez Suarez S.l.",
    "wof:placetype":"venue"
},
  "geometry": {"coordinates":[-16.2977790833,28.4525909424],"type":"Point"}
}