{
  "type": "Feature",
  "properties": {
    "iso:country":"ES",
    "sg:address":"Avda Aguirre Lehendakari, 157",
    "sg:city":"Bilbao",
    "sg:orig_category":"Ropa Para Caballeros (al Por Menor)",
    "sg:phone":"+34 944 02 60 16",
    "sg:postcode":"48015",
    "sg:province":"Vizcaya",
    "wof:name":"Bego\u00f1a Lasala Aldai (modas Aldai)",
    "wof:placetype":"venue"
},
  "geometry": {"coordinates":[-2.9614379406,43.2786712646],"type":"Point"}
}