{
  "type": "Feature",
  "properties": {
    "addr:full":"Rosende, S/n Pena Lugo 27637",
    "addr:housenumber":"s / n",
    "addr:postcode":"27637",
    "addr:street":"Rosende",
    "iso:country":"ES",
    "sg:address":"Rosende, S/n",
    "sg:city":"Pena",
    "sg:orig_category":"Cr\u00cda De Bovinos",
    "sg:phone":"+34 982 18 72 27",
    "sg:postcode":"27637",
    "sg:province":"Lugo",
    "wof:name":"Romepen S.a.t. Xuga 783",
    "wof:placetype":"venue"
},
  "geometry": {"coordinates":[-7.382338047,42.7135887146],"type":"Point"}
}