{
  "type": "Feature",
  "properties": {
    "iso:country":"ES",
    "sg:address":"Alam Boulevard Del, 25",
    "sg:city":"Donostia-san Sebastian",
    "sg:orig_category":"Asociaciones, Instituciones De Consumidores Y Usuarios",
    "sg:phone":"+34 943 42 39 93",
    "sg:postcode":"20003",
    "sg:province":"Guip\u00f9zcoa",
    "wof:name":"Asociacion Uribe-kosta De Usuarios Y Consumidores",
    "wof:placetype":"venue"
},
  "geometry": {"coordinates":[-1.9845780134,43.3215675354],"type":"Point"}
}