{
  "type": "Feature",
  "properties": {
    "addr:full":"Ctra Canya, La, 75 Olot Girona 17800",
    "addr:housenumber":"75",
    "addr:postcode":"17800",
    "addr:street":"Ctra Canya La",
    "iso:country":"ES",
    "sg:address":"Ctra Canya, La, 75",
    "sg:city":"Olot",
    "sg:orig_category":"Maquinaria Para Industrias Diversas",
    "sg:phone":"+34 972 26 17 75",
    "sg:postcode":"17800",
    "sg:province":"Girona",
    "wof:name":"Mecanisold S.l.",
    "wof:placetype":"venue"
},
  "geometry": {"coordinates":[2.5000550747,42.1915054321],"type":"Point"}
}