{
  "type": "Feature",
  "properties": {
    "iso:country":"ES",
    "sg:address":"Cra Nal Tres-cents Quaranta, Km. 1107,0",
    "sg:city":"El Perello",
    "sg:orig_category":"Mataderos De Poller\u00cda",
    "sg:phone":"+34 977 49 01 13",
    "sg:postcode":"43519",
    "sg:province":"Tarragona",
    "wof:name":"Baldo Pallares Sa.",
    "wof:placetype":"venue"
},
  "geometry": {"coordinates":[0.6962853074,40.8959846497],"type":"Point"}
}