{
  "type": "Feature",
  "properties": {
    "addr:full":"Calle de San Marcial, 1 Najera La Rioja 26300",
    "addr:housenumber":"1",
    "addr:postcode":"26300",
    "addr:street":"Calle De San Marcial;Rioja",
    "iso:country":"ES",
    "sg:address":"Calle de San Marcial, 1",
    "sg:city":"Najera",
    "sg:orig_category":"Carnicer\u00cdas, Carnicer\u00cdas",
    "sg:phone":"+34 941 36 27 21",
    "sg:postcode":"26300",
    "sg:province":"La Rioja",
    "wof:name":"Espiga Llerena Victorico",
    "wof:placetype":"venue"
},
  "geometry": {"coordinates":[-2.7349450588,42.4155349731],"type":"Point"}
}