{
  "type": "Feature",
  "properties": {
    "addr:full":"Ctra Palma Lloseta Pm-v-211, S/n Lloseta Islas Baleares 07360",
    "addr:housenumber":"s / n",
    "addr:postcode":"07360",
    "addr:street":"Ctra Palma;Pm-V-211",
    "iso:country":"ES",
    "sg:address":"Ctra Palma Lloseta Pm-v-211, S/n",
    "sg:city":"Lloseta",
    "sg:orig_category":"Cer\u00c1micas: Material Y Suministros",
    "sg:phone":"+34 971 51 90 61",
    "sg:postcode":"07360",
    "sg:province":"Islas Baleares",
    "sg:website":"pavilloseta.com",
    "wof:name":"Paviments Lloseta S.l.",
    "wof:placetype":"venue"
},
  "geometry": {"coordinates":[2.8661301136,39.7158584595],"type":"Point"}
}