{
  "type": "Feature",
  "properties": {
    "iso:country":"ES",
    "sg:address":"Calle de Hermanos Garcia Noblejas, 99",
    "sg:city":"Madrid",
    "sg:orig_category":"Servicio De Salud",
    "sg:phone":"+34 913 13 28 46",
    "sg:postcode":"28037",
    "sg:province":"Madrid",
    "wof:name":"Saneamientos F. Bejarano S. A.",
    "wof:placetype":"venue"
},
  "geometry": {"coordinates":[-3.6259050369,40.4237861633],"type":"Point"}
}