{
  "type": "Feature",
  "properties": {
    "addr:full":"Calle de Monjas De Santa Catalina, 4 Valencia Valencia 46002",
    "addr:housenumber":"4",
    "addr:postcode":"46002",
    "addr:street":"Calle De Monjas De Santa Catalina",
    "iso:country":"ES",
    "sg:address":"Calle de Monjas De Santa Catalina, 4",
    "sg:city":"Valencia",
    "sg:orig_category":"Inmobiliaria (agencias)",
    "sg:phone":"+34 963 94 34 05",
    "sg:postcode":"46002",
    "sg:province":"Valencia",
    "wof:name":"Asesoramiento Inmobiliario Roan S.a.",
    "wof:placetype":"venue"
},
  "geometry": {"coordinates":[-0.3718304038,39.4711990356],"type":"Point"}
}