{
  "type": "Feature",
  "properties": {
    "iso:country":"ES",
    "sg:address":"Ctra. B-motril, Km. 0329,0",
    "sg:city":"Jaen",
    "sg:orig_category":"Promotores Constructores",
    "sg:phone":"+34 953 28 13 06",
    "sg:postcode":"23009",
    "sg:province":"Ja\u00e9n",
    "wof:name":"Peninsular De Contratas S. A.",
    "wof:placetype":"venue"
},
  "geometry": {"coordinates":[-3.7480869293,37.8042449951],"type":"Point"}
}