{
  "type": "Feature",
  "properties": {
    "iso:country":"ES",
    "sg:address":"Calle de Villavieja, 2",
    "sg:city":"Madrid",
    "sg:orig_category":"\u00d3ptica: Instrumentos (fabricaci\u00d3n)",
    "sg:phone":"+34 914 63 43 54",
    "sg:postcode":"28011",
    "sg:province":"Madrid",
    "wof:name":"Loma Lozano Jose Luis",
    "wof:placetype":"venue"
},
  "geometry": {"coordinates":[-3.7473471165,40.406829834],"type":"Point"}
}