{
  "type": "Feature",
  "properties": {
    "addr:full":"Ignazio Iriarte Margolaria Kalea Azkoitia Guip\u00f9zcoa 20720",
    "addr:postcode":"20720",
    "addr:street":"Iriarte Margolaria Kalea;Guipu\u0300Zcoa",
    "iso:country":"ES",
    "sg:address":"Ignazio Iriarte Margolaria Kalea",
    "sg:city":"Azkoitia",
    "sg:orig_category":"Masajistas Kinesiterapeutas",
    "sg:phone":"+34 943 85 34 76",
    "sg:postcode":"20720",
    "sg:province":"Guip\u00f9zcoa",
    "wof:name":"Jose Ignacio Azpitarte Lizarralde",
    "wof:placetype":"venue"
},
  "geometry": {"coordinates":[-2.312032938,43.1784744263],"type":"Point"}
}