{
  "type": "Feature",
  "properties": {
    "addr:full":"Pl Sports, 2 Altea Alicante 03590",
    "addr:housenumber":"2",
    "addr:postcode":"03590",
    "iso:country":"ES",
    "sg:address":"Pl Sports, 2",
    "sg:city":"Altea",
    "sg:orig_category":"Peluquer\u00cdas, Peluquer\u00cda Mixta",
    "sg:phone":"+34 966 88 19 29",
    "sg:postcode":"03590",
    "sg:province":"Alicante",
    "wof:name":"Zaragozi Serrat Pedro Francisco",
    "wof:placetype":"venue"
},
  "geometry": {"coordinates":[-0.0279866997,38.6424942017],"type":"Point"}
}