{
  "type": "Feature",
  "properties": {
    "iso:country":"ES",
    "sg:address":"Carr Rectoria, 6",
    "sg:city":"S. Hilari Sacalm",
    "sg:orig_category":"Fotocopias, Reprograf\u00cda",
    "sg:phone":"+34 972 86 91 07",
    "sg:postcode":"17403",
    "sg:province":"Girona",
    "wof:name":"Garcia Ruiz Angeles",
    "wof:placetype":"venue"
},
  "geometry": {"coordinates":[2.5119540691,41.8778266907],"type":"Point"}
}