{
  "type": "Feature",
  "properties": {
    "iso:country":"ES",
    "sg:address":"Calle de Bierzo (del), 18",
    "sg:city":"Fuenlabrada",
    "sg:orig_category":"Calefacci\u00d3n Central: Material (fabricaci\u00d3n, Al Por Mayor)",
    "sg:phone":"+34 916 42 17 44",
    "sg:postcode":"28947",
    "sg:province":"Madrid",
    "wof:name":"Comercial Quemoil S. A.",
    "wof:placetype":"venue"
},
  "geometry": {"coordinates":[-3.7426435947,40.2693824768],"type":"Point"}
}