{
  "type": "Feature",
  "properties": {
    "iso:country":"ES",
    "sg:address":"Calle de Naves, 8",
    "sg:city":"Madrid",
    "sg:orig_category":"Alimentaci\u00d3n General (al Por Menor)",
    "sg:phone":"+34 914 73 77 84",
    "sg:postcode":"28005",
    "sg:province":"Madrid",
    "wof:name":"Taboada Prada Abelardo",
    "wof:placetype":"venue"
},
  "geometry": {"coordinates":[-3.7067425251,40.3986816406],"type":"Point"}
}