{
  "type": "Feature",
  "properties": {
    "addr:full":"Carrer de Proven\u00c7a, 529 Barcelona Barcelona 08025",
    "addr:housenumber":"529",
    "addr:postcode":"08025",
    "addr:street":"Carrer De Provenc\u0327A",
    "iso:country":"ES",
    "sg:address":"Carrer de Proven\u00c7a, 529",
    "sg:city":"Barcelona",
    "sg:orig_category":"Contenedores Para Transporte De Mercanc\u00cdas",
    "sg:phone":"+34 934 50 10 17",
    "sg:postcode":"08025",
    "sg:province":"Barcelona",
    "wof:name":"Transportes Felix Hermanos S.l.",
    "wof:placetype":"venue"
},
  "geometry": {"coordinates":[2.1792531013,41.4082489014],"type":"Point"}
}