{
  "type": "Feature",
  "properties": {
    "addr:full":"Cami Atall (l') Z.alcossebre, S/n Alcossebre Castell\u00f3n 12579",
    "addr:housenumber":"s",
    "addr:postcode":"12579",
    "addr:street":"Atall L ' Z.Alcossebre;/ N Alcossebre Castello\u0301N",
    "iso:country":"ES",
    "sg:address":"Cami Atall (l') Z.alcossebre, S/n",
    "sg:city":"Alcossebre",
    "sg:orig_category":"Reposter\u00cdas",
    "sg:phone":"+34 964 41 28 12",
    "sg:postcode":"12579",
    "sg:province":"Castell\u00f3n",
    "wof:name":"Ebri Bayarri Pascual",
    "wof:placetype":"venue"
},
  "geometry": {"coordinates":[0.2850950062,40.2547187805],"type":"Point"}
}