{
  "type": "Feature",
  "properties": {
    "addr:full":"Carr Gladiol, 31 Pont D'inca Islas Baleares 07009",
    "addr:housenumber":"31",
    "addr:postcode":"07009",
    "addr:street":"Carr Gladiol;Pont D'Inca",
    "iso:country":"ES",
    "sg:address":"Carr Gladiol, 31",
    "sg:city":"Pont D'inca",
    "sg:orig_category":"Farmacias",
    "sg:phone":"+34 971 60 80 47",
    "sg:postcode":"07009",
    "sg:province":"Islas Baleares",
    "wof:name":"Bosch Tugores Catalina",
    "wof:placetype":"venue"
},
  "geometry": {"coordinates":[2.9091899395,39.7197418213],"type":"Point"}
}