{
  "type": "Feature",
  "properties": {
    "addr:full":"Calle de Santa Clara, 32 Zamora Zamora 49014",
    "addr:housenumber":"32",
    "addr:postcode":"49014",
    "addr:street":"Calle De Santa Clara",
    "iso:country":"ES",
    "sg:address":"Calle de Santa Clara, 32",
    "sg:city":"Zamora",
    "sg:orig_category":"Arquitectos",
    "sg:phone":"+34 980 51 12 97",
    "sg:postcode":"49014",
    "sg:province":"Zamora",
    "wof:name":"Dc Arquitectos C.b.",
    "wof:placetype":"venue"
},
  "geometry": {"coordinates":[-5.7400140762,41.507850647],"type":"Point"}
}