{
  "type": "Feature",
  "properties": {
    "addr:full":"Avda Gomez Laguna, 28 Zaragoza Zaragoza 50009",
    "addr:housenumber":"28",
    "addr:postcode":"50009",
    "addr:street":"Avda Gomez Laguna",
    "iso:country":"ES",
    "sg:address":"Avda Gomez Laguna, 28",
    "sg:city":"Zaragoza",
    "sg:orig_category":"Cajas De Ahorro",
    "sg:phone":"+34 976 75 30 20",
    "sg:postcode":"50009",
    "sg:province":"Zaragoza",
    "wof:name":"Caja De Ahorros De Valencia Castellon Y Alicante",
    "wof:placetype":"venue"
},
  "geometry": {"coordinates":[-0.9133309722,41.641544342],"type":"Point"}
}