{
  "type": "Feature",
  "properties": {
    "iso:country":"ES",
    "sg:address":"Vertical Quinta, S/n",
    "sg:city":"Carbajosa Sagrada",
    "sg:orig_category":"Productos Qu\u00cdmicos (fabricaci\u00d3n, Al Por Mayor)",
    "sg:phone":"+34 923 19 11 66",
    "sg:postcode":"37188",
    "sg:province":"Salamanca",
    "wof:name":"Quimicasa 2002 S.l.",
    "wof:placetype":"venue"
},
  "geometry": {"coordinates":[-5.6566238403,40.9375114441],"type":"Point"}
}