{
  "type": "Feature",
  "properties": {
    "addr:full":"R. Casanoves, 4 Lloret Mar Girona 17310",
    "addr:housenumber":"4",
    "addr:postcode":"17310",
    "addr:street":"Casanoves",
    "iso:country":"ES",
    "sg:address":"R. Casanoves, 4",
    "sg:city":"Lloret Mar",
    "sg:orig_category":"Limpieza Con Chorro De Arena Y Con Granalla, Pulido",
    "sg:phone":"+34 972 36 24 95",
    "sg:postcode":"17310",
    "sg:province":"Girona",
    "wof:name":"Masnou Perez Javier",
    "wof:placetype":"venue"
},
  "geometry": {"coordinates":[2.846834898,41.6981697083],"type":"Point"}
}