{
  "type": "Feature",
  "properties": {
    "addr:full":"Calle de Periodista Jose L. De Cordoba, 7 Cordoba C\u00f3rdoba 14010",
    "addr:housenumber":"7",
    "addr:postcode":"14010",
    "addr:street":"Calle De Periodista Jose L. De Cordoba;Co\u0301Rdoba",
    "iso:country":"ES",
    "sg:address":"Calle de Periodista Jose L. De Cordoba, 7",
    "sg:city":"Cordoba",
    "sg:orig_category":"Ropa Para Se\u00d1oras Y Caballeros (al Por Menor)",
    "sg:phone":"+34 957 75 26 78",
    "sg:postcode":"14010",
    "sg:province":"C\u00f3rdoba",
    "wof:name":"Gil Arjona Ana Maria",
    "wof:placetype":"venue"
},
  "geometry": {"coordinates":[-4.7617111206,37.8777427673],"type":"Point"}
}