{
  "type": "Feature",
  "properties": {
    "iso:country":"ES",
    "sg:address":"Rua Medio, 13",
    "sg:city":"Rianxo",
    "sg:orig_category":"Bazares, Art\u00cdculos De Limpieza Y De Cocina (al Por Menor)",
    "sg:phone":"+34 981 86 61 78",
    "sg:postcode":"15920",
    "sg:province":"La Coru\u00f1a",
    "wof:name":"Figueira Gonzalez Delia",
    "wof:placetype":"venue"
},
  "geometry": {"coordinates":[-8.8185386658,42.6519088745],"type":"Point"}
}