{
  "type": "Feature",
  "properties": {
    "iso:country":"ES",
    "sg:address":"Calle de Libertad, 1",
    "sg:city":"Algeciras",
    "sg:orig_category":"Alimentaci\u00d3n General (al Por Menor)",
    "sg:phone":"+34 956 66 10 26",
    "sg:postcode":"11201",
    "sg:province":"C\u00e1diz",
    "wof:name":"Rios Calderon Mercedes",
    "wof:placetype":"venue"
},
  "geometry": {"coordinates":[-5.4490218163,36.1314506531],"type":"Point"}
}