{
  "type": "Feature",
  "properties": {
    "addr:full":"Calle de Postas, 11 Ciudad Real Ciudad Real 13001",
    "addr:housenumber":"11",
    "addr:postcode":"13001",
    "addr:street":"Calle De Postas",
    "iso:country":"ES",
    "sg:address":"Calle de Postas, 11",
    "sg:city":"Ciudad Real",
    "sg:orig_category":"Lencer\u00cda Femenina, Corseter\u00cda, Trajes De Ba\u00d1o (al Por Menor)",
    "sg:phone":"+34 926 21 16 41",
    "sg:postcode":"13001",
    "sg:province":"Ciudad Real",
    "wof:name":"Chinchilla Fernandez Enrique",
    "wof:placetype":"venue"
},
  "geometry": {"coordinates":[-3.9306609631,38.9844055176],"type":"Point"}
}