{
  "type": "Feature",
  "properties": {
    "iso:country":"ES",
    "sg:address":"Calle de Martinete, 3",
    "sg:city":"Arenas San Pedro",
    "sg:orig_category":"Mec\u00c1nico Del Autom\u00d3vil",
    "sg:phone":"+34 920 37 25 21",
    "sg:postcode":"05400",
    "sg:province":"\u00c1vila",
    "wof:name":"Delgado Racing S.l.",
    "wof:placetype":"venue"
},
  "geometry": {"coordinates":[-5.0934619904,40.2078285217],"type":"Point"}
}