{
  "type": "Feature",
  "properties": {
    "iso:country":"ES",
    "sg:address":"Carr Casernes, 37",
    "sg:city":"Vilanova I La Geltru",
    "sg:orig_category":"Promotores Constructores",
    "sg:phone":"+34 938 11 50 36",
    "sg:postcode":"08800",
    "sg:province":"Barcelona",
    "wof:name":"Equip Tecnic Catalunya S.l.",
    "wof:placetype":"venue"
},
  "geometry": {"coordinates":[1.727725029,41.2296676636],"type":"Point"}
}