{
  "type": "Feature",
  "properties": {
    "addr:full":"Calle de Gerardo Cordon, 36 Madrid Madrid 28017",
    "addr:housenumber":"36",
    "addr:postcode":"madrid;28017",
    "addr:street":"Calle De Gerardo Cordon",
    "iso:country":"ES",
    "sg:address":"Calle de Gerardo Cordon, 36",
    "sg:city":"Madrid",
    "sg:orig_category":"Venta, Instalaci\u00d3n, Reparaci\u00d3n De Antenas Para Televisi\u00d3n",
    "sg:phone":"+34 914 05 07 86",
    "sg:postcode":"28017",
    "sg:province":"Madrid",
    "wof:name":"Interantena S.l.",
    "wof:placetype":"venue"
},
  "geometry": {"coordinates":[-3.653897047,40.426612854],"type":"Point"}
}