{
  "type": "Feature",
  "properties": {
    "iso:country":"ES",
    "sg:address":"Pase Chopera (de La), 57",
    "sg:city":"Alcobendas",
    "sg:orig_category":"Florister\u00cdas",
    "sg:phone":"+34 916 61 76 04",
    "sg:postcode":"28100",
    "sg:province":"Madrid",
    "wof:name":"Escolar Moyano Maria Isabel",
    "wof:placetype":"venue"
},
  "geometry": {"coordinates":[-3.6434381008,40.5428123474],"type":"Point"}
}