{
  "type": "Feature",
  "properties": {
    "addr:full":"Carrer de Gran De Gracia, 254 Barcelona Barcelona 08012",
    "addr:housenumber":"254",
    "addr:postcode":"08012",
    "addr:street":"Carrer De Gran De Gracia",
    "iso:country":"ES",
    "sg:address":"Carrer de Gran De Gracia, 254",
    "sg:city":"Barcelona",
    "sg:orig_category":"Zapatos (al Por Menor)",
    "sg:phone":"+34 934 16 16 53",
    "sg:postcode":"08012",
    "sg:province":"Barcelona",
    "wof:name":"Romero Ripolles S.l.",
    "wof:placetype":"venue"
},
  "geometry": {"coordinates":[2.1509919167,41.4053573608],"type":"Point"}
}