{
  "type": "Feature",
  "properties": {
    "addr:full":"Calle de Lopez Gomez, 2 Valladolid Valladolid 47002",
    "addr:housenumber":"2",
    "addr:postcode":"47002",
    "addr:street":"Calle De Lopez Gomez",
    "iso:country":"ES",
    "sg:address":"Calle de Lopez Gomez, 2",
    "sg:city":"Valladolid",
    "sg:orig_category":"Ropa Para Caballeros (al Por Menor)",
    "sg:phone":"+34 983 21 37 55",
    "sg:postcode":"47002",
    "sg:province":"Valladolid",
    "wof:name":"Mehrgut Casares Dario",
    "wof:placetype":"venue"
},
  "geometry": {"coordinates":[-4.7240958214,41.6493034363],"type":"Point"}
}