{
  "type": "Feature",
  "properties": {
    "addr:full":"Calle de San Juan, 11 Meliana Valencia 46133",
    "addr:housenumber":"11",
    "addr:postcode":"46133",
    "addr:street":"Calle De San Juan",
    "iso:country":"ES",
    "sg:address":"Calle de San Juan, 11",
    "sg:city":"Meliana",
    "sg:orig_category":"Fotograf\u00cda Art\u00cdstica Y Retratos",
    "sg:phone":"+34 961 48 05 68",
    "sg:postcode":"46133",
    "sg:province":"Valencia",
    "wof:name":"Marquez Pellicer Diego",
    "wof:placetype":"venue"
},
  "geometry": {"coordinates":[-0.348304987,39.5279159546],"type":"Point"}
}