{
  "type": "Feature",
  "properties": {
    "addr:full":"Carrer de Rossello I Ca\u00c7ador, 13 Palma Islas Baleares 07004",
    "addr:housenumber":"13",
    "addr:postcode":"07004",
    "addr:street":"Carrer De Rossello;Cac\u0327Ador",
    "iso:country":"ES",
    "sg:address":"Carrer de Rossello I Ca\u00c7ador, 13",
    "sg:city":"Palma",
    "sg:orig_category":"Organismos De Reclutamiento",
    "sg:phone":"+34 971 75 11 49",
    "sg:postcode":"07004",
    "sg:province":"Islas Baleares",
    "wof:name":"Can Boscana S.l.",
    "wof:placetype":"venue"
},
  "geometry": {"coordinates":[2.6539430618,39.5816421509],"type":"Point"}
}