{
  "type": "Feature",
  "properties": {
    "iso:country":"ES",
    "sg:address":"Calle de Caleruega, 51",
    "sg:city":"Madrid",
    "sg:orig_category":"Asesor\u00cdas Y Estudios Financieros",
    "sg:phone":"+34 917 66 69 86",
    "sg:postcode":"28033",
    "sg:province":"Madrid",
    "wof:name":"Janices Perez Alejandro",
    "wof:placetype":"venue"
},
  "geometry": {"coordinates":[-3.6717627048,40.4811096191],"type":"Point"}
}