{
  "type": "Feature",
  "properties": {
    "iso:country":"ES",
    "sg:address":"Calle de Cuba, 54",
    "sg:city":"Valencia",
    "sg:orig_category":"Empresarios Y Productoras De Espect\u00c1culos",
    "sg:phone":"+34 963 41 36 81",
    "sg:postcode":"46006",
    "sg:province":"Valencia",
    "wof:name":"Tello Fresneda Alejandro",
    "wof:placetype":"venue"
},
  "geometry": {"coordinates":[-0.3757469952,39.4599075317],"type":"Point"}
}