{
  "type": "Feature",
  "properties": {
    "addr:full":"Calle de Filipinas, 12 Coru\u00d1a La Coru\u00f1a 15007",
    "addr:housenumber":"12",
    "addr:postcode":"15007",
    "addr:street":"Calle De Filipinas;La Corun\u0303A",
    "iso:country":"ES",
    "sg:address":"Calle de Filipinas, 12",
    "sg:city":"Coru\u00d1a",
    "sg:orig_category":"Peluqueros: De Se\u00d1oras",
    "sg:phone":"+34 981 23 87 97",
    "sg:postcode":"15007",
    "sg:province":"La Coru\u00f1a",
    "wof:name":"Calvete Gomez Delfina",
    "wof:placetype":"venue"
},
  "geometry": {"coordinates":[-8.4135112762,43.3519363403],"type":"Point"}
}