{
  "type": "Feature",
  "properties": {
    "iso:country":"ES",
    "sg:address":"Calle de Pedreras, 96",
    "sg:city":"Linea De La Concepcion",
    "sg:orig_category":"Flores Y Plantas Naturales (al Por Mayor)",
    "sg:phone":"+34 956 76 23 58",
    "sg:postcode":"11300",
    "sg:province":"C\u00e1diz",
    "wof:name":"Barrero Dominguez Francisco",
    "wof:placetype":"venue"
},
  "geometry": {"coordinates":[-5.3556261063,36.1666374207],"type":"Point"}
}