{
  "type": "Feature",
  "properties": {
    "iso:country":"ES",
    "sg:address":"Calle de Donoso Cortes, 16",
    "sg:city":"Siruela",
    "sg:orig_category":"Muebles, Minoristas",
    "sg:phone":"+34 924 62 60 88",
    "sg:postcode":"06650",
    "sg:province":"Badajoz",
    "wof:name":"Mu\u00f1oz Sanchez Alvaro",
    "wof:placetype":"venue"
},
  "geometry": {"coordinates":[-5.0509977341,38.9766426086],"type":"Point"}
}