{
  "type": "Feature",
  "properties": {
    "iso:country":"ES",
    "sg:address":"Carrer de Doctor Manuel Riera, 31",
    "sg:city":"Esplugues Llobregat",
    "sg:orig_category":"Ropa Para Se\u00d1oras Y Caballeros (al Por Menor)",
    "sg:phone":"+34 933 71 72 98",
    "sg:postcode":"08950",
    "sg:province":"Barcelona",
    "wof:name":"Andrey Jerez Jose",
    "wof:placetype":"venue"
},
  "geometry": {"coordinates":[2.086081028,41.3732299805],"type":"Point"}
}