{
  "type": "Feature",
  "properties": {
    "iso:country":"ES",
    "sg:address":"Oto\u00f1o, 11",
    "sg:city":"Rajamancera, Barriada",
    "sg:orig_category":"Agricultores, Agricultores",
    "sg:phone":"+34 956 16 23 92",
    "sg:postcode":"11400",
    "sg:province":"C\u00e1diz",
    "wof:name":"Enapa Glez&fdez S.l.",
    "wof:placetype":"venue"
},
  "geometry": {"coordinates":[-6.0565910339,36.645866394],"type":"Point"}
}