{
  "type": "Feature",
  "properties": {
    "iso:country":"ES",
    "sg:address":"Carr San Fabian, 61",
    "sg:city":"Canals",
    "sg:orig_category":"Reposter\u00cdas",
    "sg:phone":"+34 962 24 14 70",
    "sg:postcode":"46650",
    "sg:province":"Valencia",
    "wof:name":"Ribelles Llopis Jose",
    "wof:placetype":"venue"
},
  "geometry": {"coordinates":[-0.5807539821,38.9634361267],"type":"Point"}
}