{
  "type": "Feature",
  "properties": {
    "iso:country":"ES",
    "sg:address":"Sect Descubridores, 1",
    "sg:city":"Tres Cantos",
    "sg:orig_category":"Librer\u00cdas",
    "sg:phone":"+34 917 65 20 96",
    "sg:postcode":"28760",
    "sg:province":"Madrid",
    "wof:name":"Marquez Rello Julio",
    "wof:placetype":"venue"
},
  "geometry": {"coordinates":[-3.7147500515,40.6093902588],"type":"Point"}
}