{
  "type": "Feature",
  "properties": {
    "addr:full":"Calle de L'horteta, 32 Rafelbunyol Valencia 46138",
    "addr:housenumber":"32",
    "addr:postcode":"46138",
    "addr:street":"Calle De L'Horteta",
    "iso:country":"ES",
    "sg:address":"Calle de L'horteta, 32",
    "sg:city":"Rafelbunyol",
    "sg:orig_category":"Cromado Y Niquelado",
    "sg:phone":"+34 961 41 14 27",
    "sg:postcode":"46138",
    "sg:province":"Valencia",
    "wof:name":"Niquelados Valencia S.l.",
    "wof:placetype":"venue"
},
  "geometry": {"coordinates":[-0.3630670011,39.6022033691],"type":"Point"}
}