{
  "type": "Feature",
  "properties": {
    "addr:full":"Carr Benicanena, 15 Gandia Valencia 46700",
    "addr:housenumber":"15",
    "addr:postcode":"46700",
    "addr:street":"Carr Benicanena;Valencia",
    "iso:country":"ES",
    "sg:address":"Carr Benicanena, 15",
    "sg:city":"Gandia",
    "sg:orig_category":"Peluqueros: De Se\u00d1oras",
    "sg:phone":"+34 962 87 35 48",
    "sg:postcode":"46700",
    "sg:province":"Valencia",
    "wof:name":"Ochoa Almenara Maria Angeles",
    "wof:placetype":"venue"
},
  "geometry": {"coordinates":[-0.1913339943,38.960735321],"type":"Point"}
}