{
  "type": "Feature",
  "properties": {
    "iso:country":"ES",
    "sg:address":"Plaz Fernando El Catolico, 2",
    "sg:city":"Alagon",
    "sg:orig_category":"Molduras, Junquillos, Listones Y Molduras Perforadas",
    "sg:phone":"+34 976 61 14 74",
    "sg:postcode":"50630",
    "sg:province":"Zaragoza",
    "wof:name":"Alex S.cv.",
    "wof:placetype":"venue"
},
  "geometry": {"coordinates":[-1.1194025278,41.7691917419],"type":"Point"}
}