{
  "type": "Feature",
  "properties": {
    "iso:country":"ES",
    "sg:address":"Calle de Doctor Fernando Escobar, 12",
    "sg:city":"Granada",
    "sg:orig_category":"Tintorer\u00cdas, Limpieza En Seco",
    "sg:phone":"+34 958 27 77 90",
    "sg:postcode":"18012",
    "sg:province":"Granada",
    "wof:name":"Sedano Perez Juan",
    "wof:placetype":"venue"
},
  "geometry": {"coordinates":[-3.6090190411,37.1902618408],"type":"Point"}
}