{
  "type": "Feature",
  "properties": {
    "addr:full":"Carr Coll I Pujol, 150 Badalona Barcelona 08917",
    "addr:housenumber":"150",
    "addr:postcode":"08917",
    "addr:street":"Carr Coll I Pujol",
    "iso:country":"ES",
    "sg:address":"Carr Coll I Pujol, 150",
    "sg:city":"Badalona",
    "sg:orig_category":"Radiocomunicaciones, Telefon\u00cda M\u00d3vil, Radiomensajer\u00cda: Servicios, Comercializaci\u00d3n",
    "sg:phone":"+34 933 98 81 52",
    "sg:postcode":"08917",
    "sg:province":"Barcelona",
    "wof:name":"Singh Raheja Man Mohan",
    "wof:placetype":"venue"
},
  "geometry": {"coordinates":[2.2391450405,41.4516639709],"type":"Point"}
}