{
  "type": "Feature",
  "properties": {
    "iso:country":"ES",
    "sg:address":"Avda Paris, S/n",
    "sg:city":"Arenal",
    "sg:orig_category":"Peluqueros: De Se\u00d1oras",
    "sg:phone":"+34 965 79 39 69",
    "sg:postcode":"03730",
    "sg:province":"Alicante",
    "wof:name":"Ivars Cholbi Josefa",
    "wof:placetype":"venue"
},
  "geometry": {"coordinates":[0.1570300013,38.7885093689],"type":"Point"}
}