{
  "type": "Feature",
  "properties": {
    "addr:full":"Calle de Quintana, 12 Oviedo Asturias 33009",
    "addr:housenumber":"12",
    "addr:postcode":"33009",
    "addr:street":"Calle De Quintana",
    "iso:country":"ES",
    "sg:address":"Calle de Quintana, 12",
    "sg:city":"Oviedo",
    "sg:orig_category":"Florister\u00cdas",
    "sg:phone":"+34 985 21 82 25",
    "sg:postcode":"33009",
    "sg:province":"Asturias",
    "wof:name":"Flores Principado S.l.",
    "wof:placetype":"venue"
},
  "geometry": {"coordinates":[-5.847427845,43.3590393066],"type":"Point"}
}