{
  "type": "Feature",
  "properties": {
    "addr:full":"Calle de Zurbaran, 32 Quintana Serena Badajoz 06450",
    "addr:housenumber":"32",
    "addr:postcode":"06450",
    "addr:street":"Calle De Zurbaran",
    "iso:country":"ES",
    "sg:address":"Calle de Zurbaran, 32",
    "sg:city":"Quintana Serena",
    "sg:orig_category":"Mec\u00c1nico Del Autom\u00d3vil",
    "sg:phone":"+34 924 78 64 77",
    "sg:postcode":"06450",
    "sg:province":"Badajoz",
    "wof:name":"Quintana Cordero Fernando",
    "wof:placetype":"venue"
},
  "geometry": {"coordinates":[-5.6750850677,38.7456970215],"type":"Point"}
}