{
  "type": "Feature",
  "properties": {
    "addr:full":"Rua Frei Rosendo Salvado (de), 7 Santiago De Compostela La Coru\u00f1a 15701",
    "addr:housenumber":"7",
    "addr:postcode":"15701",
    "addr:street":"Rua Frei Rosendo Salvado De;Corun\u0303A",
    "iso:country":"ES",
    "sg:address":"Rua Frei Rosendo Salvado (de), 7",
    "sg:city":"Santiago De Compostela",
    "sg:orig_category":"Ropa Para Caballeros (al Por Menor)",
    "sg:phone":"+34 981 59 98 38",
    "sg:postcode":"15701",
    "sg:province":"La Coru\u00f1a",
    "wof:name":"Hnos.cierto",
    "wof:placetype":"venue"
},
  "geometry": {"coordinates":[-8.549943924,42.8738555908],"type":"Point"}
}