{
  "type": "Feature",
  "properties": {
    "addr:full":"Afores, S/n Vilamos Lleida 25551",
    "addr:housenumber":"s / n",
    "addr:postcode":"25551",
    "addr:street":"Afores",
    "iso:country":"ES",
    "sg:address":"Afores, S/n",
    "sg:city":"Vilamos",
    "sg:orig_category":"Zonas De Acampada, Aparcamiento Para Caravanas",
    "sg:phone":"+34 973 64 82 94",
    "sg:postcode":"25551",
    "sg:province":"Lleida",
    "wof:name":"Roge Aunos Juan Manuel",
    "wof:placetype":"venue"
},
  "geometry": {"coordinates":[0.7110700011,42.7552947998],"type":"Point"}
}