{
  "type": "Feature",
  "properties": {
    "addr:full":"Calle de Rancho (del), 14 Segovia Segovia 40005",
    "addr:housenumber":"14",
    "addr:postcode":"40005",
    "addr:street":"Calle De Rancho Del",
    "iso:country":"ES",
    "sg:address":"Calle de Rancho (del), 14",
    "sg:city":"Segovia",
    "sg:orig_category":"Profesiones M\u00c9dicas, Param\u00c9dicas",
    "sg:phone":"+34 921 44 21 93",
    "sg:postcode":"40005",
    "sg:province":"Segovia",
    "wof:name":"Escobar Jimenez Marta",
    "wof:placetype":"venue"
},
  "geometry": {"coordinates":[-4.1138281822,40.9397583008],"type":"Point"}
}