{
  "type": "Feature",
  "properties": {
    "iso:country":"ES",
    "sg:address":"Carr Castello, 12",
    "sg:city":"Puig",
    "sg:orig_category":"Sanatorios M\u00c9dico",
    "sg:phone":"+34 961 47 22 50",
    "sg:postcode":"46540",
    "sg:province":"Valencia",
    "wof:name":"Generalitat Valenciana",
    "wof:placetype":"venue"
},
  "geometry": {"coordinates":[-0.3007000089,39.5890083313],"type":"Point"}
}