{
  "type": "Feature",
  "properties": {
    "addr:full":"Irurtzun, 11 Lezo Guip\u00f9zcoa 20100",
    "addr:housenumber":"11",
    "addr:postcode":"20100",
    "addr:street":"Irurtzun;Guipu\u0300Zcoa",
    "iso:country":"ES",
    "sg:address":"Irurtzun, 11",
    "sg:city":"Lezo",
    "sg:orig_category":"Metalizados",
    "sg:phone":"+34 943 52 27 66",
    "sg:postcode":"20100",
    "sg:province":"Guip\u00f9zcoa",
    "wof:name":"Talleres Andiano S.l.",
    "wof:placetype":"venue"
},
  "geometry": {"coordinates":[-1.8809289932,43.3249435425],"type":"Point"}
}