{
  "type": "Feature",
  "properties": {
    "addr:full":"Calle de Duques De Najera, 76 Logro\u00f1o La Rioja 26005",
    "addr:housenumber":"76",
    "addr:postcode":"26005",
    "addr:street":"Calle De Duques De Najera;Rioja",
    "iso:country":"ES",
    "sg:address":"Calle de Duques De Najera, 76",
    "sg:city":"Logro\u00f1o",
    "sg:orig_category":"Inform\u00c1tica: Mantenimiento Y Reparaci\u00d3n De Ordenadores",
    "sg:phone":"+34 941 28 67 11",
    "sg:postcode":"26005",
    "sg:province":"La Rioja",
    "wof:name":"Geminis Telecomunicaciones S.c.",
    "wof:placetype":"venue"
},
  "geometry": {"coordinates":[-2.4588582516,42.4604568481],"type":"Point"}
}