{
  "type": "Feature",
  "properties": {
    "addr:full":"Calle de Actor Llorens, 22 Valencia Valencia 46021",
    "addr:housenumber":"22",
    "addr:postcode":"46021",
    "addr:street":"Calle De Actor Llorens",
    "iso:country":"ES",
    "sg:address":"Calle de Actor Llorens, 22",
    "sg:city":"Valencia",
    "sg:orig_category":"Enfermeras: Consultas, Atenci\u00d3n A Domicilio",
    "sg:phone":"+34 963 93 27 81",
    "sg:postcode":"46021",
    "sg:province":"Valencia",
    "wof:name":"Felipe Garcia Antonio",
    "wof:placetype":"venue"
},
  "geometry": {"coordinates":[-0.3549320102,39.4678535461],"type":"Point"}
}