{
  "type": "Feature",
  "properties": {
    "addr:full":"Calle de Pasaje Del Libro, 2 Adra Almer\u00eda 04770",
    "addr:housenumber":"2",
    "addr:postcode":"04770",
    "addr:street":"Calle De Pasaje Del Libro;Almeri\u0301A",
    "iso:country":"ES",
    "sg:address":"Calle de Pasaje Del Libro, 2",
    "sg:city":"Adra",
    "sg:orig_category":"\u00d3ptica: Instrumentos (fabricaci\u00d3n)",
    "sg:phone":"+34 950 40 18 50",
    "sg:postcode":"04770",
    "sg:province":"Almer\u00eda",
    "wof:name":"Optica Almeria S. A.",
    "wof:placetype":"venue"
},
  "geometry": {"coordinates":[-3.0152089596,36.7481689453],"type":"Point"}
}