{
  "type": "Feature",
  "properties": {
    "addr:full":"Carrer de Anselm Clave, 37 Granollers Barcelona 08402",
    "addr:housenumber":"37",
    "addr:postcode":"08402",
    "addr:street":"Carrer De Anselm Clave",
    "iso:country":"ES",
    "sg:address":"Carrer de Anselm Clave, 37",
    "sg:city":"Granollers",
    "sg:orig_category":"Abogados",
    "sg:phone":"+34 938 79 17 10",
    "sg:postcode":"08402",
    "sg:province":"Barcelona",
    "wof:name":"Nu\u00f1ez Bascu\u00f1ana Carmen",
    "wof:placetype":"venue"
},
  "geometry": {"coordinates":[2.288836956,41.6072845459],"type":"Point"}
}