{
  "type": "Feature",
  "properties": {
    "iso:country":"ES",
    "sg:address":"Rond Carmen (del), 4",
    "sg:city":"Caceres",
    "sg:orig_category":"Restaurantes",
    "sg:phone":"+34 927 24 50 00",
    "sg:postcode":"10002",
    "sg:province":"C\u00e1ceres",
    "wof:name":"Vaquero Cortes Guillermo",
    "wof:placetype":"venue"
},
  "geometry": {"coordinates":[-6.3747019768,39.4624404907],"type":"Point"}
}