{
  "type": "Feature",
  "properties": {
    "iso:country":"ES",
    "sg:address":"Ctra Malilla, 104",
    "sg:city":"Valencia",
    "sg:orig_category":"Agentes, Concesionarios Y Sucursales De Veh\u00cdculos",
    "sg:phone":"+34 963 33 22 63",
    "sg:postcode":"46026",
    "sg:province":"Valencia",
    "wof:name":"Talleres Antonio Vicente S.l.",
    "wof:placetype":"venue"
},
  "geometry": {"coordinates":[-0.3801580071,39.4460411072],"type":"Point"}
}