{
  "type": "Feature",
  "properties": {
    "iso:country":"ES",
    "sg:address":"Muelle De Poniente, S/n",
    "sg:city":"Motril",
    "sg:orig_category":"Restaurantes",
    "sg:phone":"+34 958 82 40 65",
    "sg:postcode":"18600",
    "sg:province":"Granada",
    "wof:name":"Correa Correa Dolores",
    "wof:placetype":"venue"
},
  "geometry": {"coordinates":[-3.523704052,36.7571716309],"type":"Point"}
}