{
  "type": "Feature",
  "properties": {
    "addr:full":"Convento, 2 Benirredra Valencia 46700",
    "addr:housenumber":"2",
    "addr:postcode":"46700",
    "addr:street":"Convento",
    "iso:country":"ES",
    "sg:address":"Convento, 2",
    "sg:city":"Benirredra",
    "sg:orig_category":"Internados & Ense\u00d1anza Privada",
    "sg:phone":"+34 962 86 24 87",
    "sg:postcode":"46700",
    "sg:province":"Valencia",
    "wof:name":"Esclavas Del Sagrado Corazon De Jesus",
    "wof:placetype":"venue"
},
  "geometry": {"coordinates":[-0.1911980063,38.9595718384],"type":"Point"}
}