{
  "type": "Feature",
  "properties": {
    "addr:full":"Rua Real, 47 Ferrol La Coru\u00f1a 15402",
    "addr:housenumber":"47",
    "addr:postcode":"15402",
    "addr:street":"Rua Real;La Corun\u0303A",
    "iso:country":"ES",
    "sg:address":"Rua Real, 47",
    "sg:city":"Ferrol",
    "sg:orig_category":"Alimentaci\u00d3n General (al Por Menor)",
    "sg:phone":"+34 981 35 57 82",
    "sg:postcode":"15402",
    "sg:province":"La Coru\u00f1a",
    "wof:name":"Rodriguez Campos Olegario",
    "wof:placetype":"venue"
},
  "geometry": {"coordinates":[-8.2306423187,43.4847831726],"type":"Point"}
}