{
  "type": "Feature",
  "properties": {
    "iso:country":"ES",
    "sg:address":"Calle de Merced, 37",
    "sg:city":"Coru\u00d1a",
    "sg:orig_category":"Florister\u00cdas",
    "sg:phone":"+34 981 29 54 04",
    "sg:postcode":"15009",
    "sg:province":"La Coru\u00f1a",
    "wof:name":"Iglesia Mato Teresa",
    "wof:placetype":"venue"
},
  "geometry": {"coordinates":[-8.3947505951,43.3529891968],"type":"Point"}
}