{
  "type": "Feature",
  "properties": {
    "iso:country":"ES",
    "sg:address":"Industria, S/n",
    "sg:city":"S. Marti Centelles",
    "sg:orig_category":"Engranajes Y Elementos De Transmisi\u00d3n",
    "sg:phone":"+34 938 44 23 03",
    "sg:postcode":"08592",
    "sg:province":"Barcelona",
    "wof:name":"Talleres Auxiliares Del Motor S.a.",
    "wof:placetype":"venue"
},
  "geometry": {"coordinates":[2.251983881,41.7635269165],"type":"Point"}
}