{
  "type": "Feature",
  "properties": {
    "iso:country":"ES",
    "sg:address":"Rbla Marina, 200",
    "sg:city":"Hospitalet Llobregat",
    "sg:orig_category":"Notarios",
    "sg:phone":"+34 933 36 37 12",
    "sg:postcode":"08907",
    "sg:province":"Barcelona",
    "wof:name":"Morales Limia Fernando",
    "wof:placetype":"venue"
},
  "geometry": {"coordinates":[2.1111810207,41.352558136],"type":"Point"}
}