{
  "type": "Feature",
  "properties": {
    "addr:full":"Calle de Poeta Verdaguer, 1 Castellon Castell\u00f3n 12002",
    "addr:housenumber":"1",
    "addr:postcode":"12002",
    "addr:street":"Calle De Poeta Verdaguer;Castello\u0301N",
    "iso:country":"ES",
    "sg:address":"Calle de Poeta Verdaguer, 1",
    "sg:city":"Castellon",
    "sg:orig_category":"Promotores Constructores",
    "sg:phone":"+34 964 25 58 12",
    "sg:postcode":"12002",
    "sg:province":"Castell\u00f3n",
    "wof:name":"Sanzforn S.l.",
    "wof:placetype":"venue"
},
  "geometry": {"coordinates":[-0.0396099985,39.9836006165],"type":"Point"}
}