{
  "type": "Feature",
  "properties": {
    "addr:full":"Ctra. Llubi, Km. 0002,0 Inca Islas Baleares 07300",
    "addr:postcode":"07300",
    "addr:street":"Ctra. Llubi Km. 0002,0",
    "iso:country":"ES",
    "sg:address":"Ctra. Llubi, Km. 0002,0",
    "sg:city":"Inca",
    "sg:orig_category":"Carb\u00d3n, Carb\u00d3n De Madera (al Por Mayor)",
    "sg:phone":"+34 971 88 10 28",
    "sg:postcode":"07300",
    "sg:province":"Islas Baleares",
    "wof:name":"Segui Martorell Bartolome",
    "wof:placetype":"venue"
},
  "geometry": {"coordinates":[2.9091899395,39.7197418213],"type":"Point"}
}