{
  "type": "Feature",
  "properties": {
    "iso:country":"ES",
    "sg:address":"Majada Marcial Uno, 71",
    "sg:city":"Pto. Rosario",
    "sg:orig_category":"Empresas De Carpinter\u00cda De Madera",
    "sg:phone":"+34 928 53 11 33",
    "sg:postcode":"35600",
    "sg:province":"Las Palmas",
    "wof:name":"Carpinteria Suardiaz S.l.l.",
    "wof:placetype":"venue"
},
  "geometry": {"coordinates":[-13.8644685745,28.5023498535],"type":"Point"}
}