{
  "type": "Feature",
  "properties": {
    "addr:full":"Carrer de Baronessa De Malda, 14 Esplugues Llobregat Barcelona 08950",
    "addr:housenumber":"14",
    "addr:postcode":"08950",
    "addr:street":"Carrer De Baronessa De Malda",
    "iso:country":"ES",
    "sg:address":"Carrer de Baronessa De Malda, 14",
    "sg:city":"Esplugues Llobregat",
    "sg:orig_category":"Madera Para Construcci\u00d3n E Industria",
    "sg:phone":"+34 933 71 62 10",
    "sg:postcode":"08950",
    "sg:province":"Barcelona",
    "wof:name":"Romero Hierro Ramon",
    "wof:placetype":"venue"
},
  "geometry": {"coordinates":[2.0815329552,41.374622345],"type":"Point"}
}