{
  "type": "Feature",
  "properties": {
    "iso:country":"ES",
    "sg:address":"Avda Camino De Lo Cortao (de), 10",
    "sg:city":"San Sebastian De Los Reyes",
    "sg:classifiers":[
        {
            "category":"Wholesale",
            "subcategory":"Construction Materials",
            "type":"Manufacturing & Wholesale Goods"
        }
    ],
    "sg:phone":"+34 916 23 86 49",
    "sg:postcode":"28700",
    "sg:province":"Madrid",
    "sg:tags":[
        "de",
        "embotellado"
    ],
    "sg:website":"www.teym.com",
    "wof:name":"Tecnicos De Embotellado Y Mantenimiento S.a.",
    "wof:placetype":"venue"
},
  "geometry": {"coordinates":[-3.6253190041,40.5473556519],"type":"Point"}
}