{
  "type": "Feature",
  "properties": {
    "iso:country":"ES",
    "sg:address":"Calle de Amor Hermoso, 59",
    "sg:city":"Madrid",
    "sg:orig_category":"Empresarios",
    "sg:phone":"+34 913 92 00 53",
    "sg:postcode":"28026",
    "sg:province":"Madrid",
    "wof:name":"Julvi 2 S.l.",
    "wof:placetype":"venue"
},
  "geometry": {"coordinates":[-3.7036137581,40.3838653564],"type":"Point"}
}