{
  "type": "Feature",
  "properties": {
    "iso:country":"ES",
    "sg:address":"Calle de Casablanca, 16",
    "sg:city":"Tomares",
    "sg:orig_category":"T\u00c9cnicos Veterinarios",
    "sg:phone":"+34 954 15 19 55",
    "sg:postcode":"41940",
    "sg:province":"Sevilla",
    "wof:name":"Tamayo Urea Genoveva",
    "wof:placetype":"venue"
},
  "geometry": {"coordinates":[-6.044011116,37.3706245422],"type":"Point"}
}