{
  "type": "Feature",
  "properties": {
    "addr:full":"Camino Viejo De La Fuensanta, S/n Alcaudete Ja\u00e9n 23660",
    "addr:housenumber":"s / n",
    "addr:postcode":"23660",
    "addr:street":"Camino Viejo De La Fuensanta;Jae\u0301N",
    "iso:country":"ES",
    "sg:address":"Camino Viejo De La Fuensanta, S/n",
    "sg:city":"Alcaudete",
    "sg:orig_category":"Asociaciones Y Clubs Deportivos",
    "sg:phone":"+34 953 56 02 98",
    "sg:postcode":"23660",
    "sg:province":"Ja\u00e9n",
    "wof:name":"Club Tenis De Alcaudete",
    "wof:placetype":"venue"
},
  "geometry": {"coordinates":[-4.0774388313,37.5869445801],"type":"Point"}
}