{
  "type": "Feature",
  "properties": {
    "iso:country":"ES",
    "sg:address":"Calle de Joaquin Turina, 2",
    "sg:city":"Pozuelo De Alarcon",
    "sg:orig_category":"Arquitectos",
    "sg:phone":"+34 913 51 63 42",
    "sg:postcode":"28224",
    "sg:province":"Madrid",
    "wof:name":"Zurainar S.l.",
    "wof:placetype":"venue"
},
  "geometry": {"coordinates":[-3.8131253719,40.4562187195],"type":"Point"}
}