{
  "type": "Feature",
  "properties": {
    "addr:full":"Carrer de Pla De Matabous, 22 Mas Rampinyo Barcelona 08110",
    "addr:housenumber":"22",
    "addr:postcode":"08110",
    "addr:street":"Carrer De Pla De Matabous",
    "iso:country":"ES",
    "sg:address":"Carrer de Pla De Matabous, 22",
    "sg:city":"Mas Rampinyo",
    "sg:orig_category":"Muebles, Minoristas",
    "sg:phone":"+34 935 64 28 50",
    "sg:postcode":"08110",
    "sg:province":"Barcelona",
    "wof:name":"Blue Self Storage S.l.",
    "wof:placetype":"venue"
},
  "geometry": {"coordinates":[2.1817660332,41.4890899658],"type":"Point"}
}