{
  "type": "Feature",
  "properties": {
    "iso:country":"ES",
    "sg:address":"Calle de Mayor, 26",
    "sg:city":"Reinosa",
    "sg:orig_category":"Confecci\u00d3n (fabricaci\u00d3n, Al Por Mayor)",
    "sg:phone":"+34 942 75 06 97",
    "sg:postcode":"39200",
    "sg:province":"Cantabria",
    "wof:name":"Calderon Arroba Luis Andres",
    "wof:placetype":"venue"
},
  "geometry": {"coordinates":[-4.1368432045,43.0011901855],"type":"Point"}
}