{
  "type": "Feature",
  "properties": {
    "iso:country":"ES",
    "sg:address":"Calle de Carlo Goldoni, 24",
    "sg:city":"Malaga",
    "sg:orig_category":"Bebidas",
    "sg:phone":"+34 952 24 20 10",
    "sg:postcode":"29004",
    "sg:province":"M\u00e1laga",
    "sg:website":"www.torres.es",
    "wof:name":"Miguel Torres S.a.",
    "wof:placetype":"venue"
},
  "geometry": {"coordinates":[-4.485710144,36.6968040466],"type":"Point"}
}