{
  "type": "Feature",
  "properties": {
    "iso:country":"ES",
    "sg:address":"Calle de Gran Via, 18",
    "sg:city":"Cehegin",
    "sg:orig_category":"Reposter\u00cdas",
    "sg:phone":"+34 968 74 27 41",
    "sg:postcode":"30430",
    "sg:province":"Murcia",
    "wof:name":"Moya Sanchez Martin",
    "wof:placetype":"venue"
},
  "geometry": {"coordinates":[-1.7970069647,38.0937156677],"type":"Point"}
}