{
  "type": "Feature",
  "properties": {
    "iso:country":"ES",
    "sg:address":"Carrer de Murcia, 12",
    "sg:city":"S. Boi Llobregat",
    "sg:orig_category":"Contenedores (mercanc\u00cdas)",
    "sg:phone":"+34 936 30 44 40",
    "sg:postcode":"08830",
    "sg:province":"Barcelona",
    "wof:name":"Transport Sast Secure S.l",
    "wof:placetype":"venue"
},
  "geometry": {"coordinates":[2.0438959599,41.3301124573],"type":"Point"}
}