{
  "type": "Feature",
  "properties": {
    "iso:country":"ES",
    "sg:address":"Rua Conde Torrecedeira, 31",
    "sg:city":"Vigo",
    "sg:orig_category":"Bisuter\u00cda, Joyer\u00cda, Relojer\u00cda (al Por Menor)",
    "sg:phone":"+34 986 29 18 37",
    "sg:postcode":"36202",
    "sg:province":"Pontevedra",
    "wof:name":"Veiga Romero Francisco Xavier",
    "wof:placetype":"venue"
},
  "geometry": {"coordinates":[-8.731344223,42.2331733704],"type":"Point"}
}