{
  "type": "Feature",
  "properties": {
    "addr:full":"Ctra General Santa Cruz Laguna, 319 Cuesta Santa Cruz De Tenerife 38320",
    "addr:housenumber":"319",
    "addr:postcode":"38320",
    "addr:street":"Ctra General;Cuesta Santa Cruz De",
    "iso:country":"ES",
    "sg:address":"Ctra General Santa Cruz Laguna, 319",
    "sg:city":"Cuesta",
    "sg:orig_category":"Agentes Generales De Seguros",
    "sg:phone":"+34 922 64 93 53",
    "sg:postcode":"38320",
    "sg:province":"Santa Cruz De Tenerife",
    "wof:name":"Banco Vitalicio De Espa\u00f1a",
    "wof:placetype":"venue"
},
  "geometry": {"coordinates":[-16.2815895081,28.466884613],"type":"Point"}
}