{
  "type": "Feature",
  "properties": {
    "iso:country":"ES",
    "sg:address":"Calle de Gomera, 24",
    "sg:city":"Gran Tarajal",
    "sg:orig_category":"Peluqueros: De Se\u00d1oras",
    "sg:phone":"+34 928 16 51 31",
    "sg:postcode":"35620",
    "sg:province":"Las Palmas",
    "wof:name":"Fernandez Urceira Samuel",
    "wof:placetype":"venue"
},
  "geometry": {"coordinates":[-14.024017334,28.2097129822],"type":"Point"}
}