{
  "type": "Feature",
  "properties": {
    "addr:full":"Calle de Silvio Abad (de), 14 San Sebastian De Los Reyes Madrid 28700",
    "addr:housenumber":"14",
    "addr:postcode":"28700",
    "addr:street":"Calle De Silvio Abad De",
    "iso:country":"ES",
    "sg:address":"Calle de Silvio Abad (de), 14",
    "sg:city":"San Sebastian De Los Reyes",
    "sg:orig_category":"Contenedores (mercanc\u00cdas)",
    "sg:phone":"+34 916 54 53 39",
    "sg:postcode":"28700",
    "sg:province":"Madrid",
    "wof:name":"Mu\u00f1oz Martin Jose",
    "wof:placetype":"venue"
},
  "geometry": {"coordinates":[-3.6270020008,40.5434074402],"type":"Point"}
}