{
  "type": "Feature",
  "properties": {
    "iso:country":"ES",
    "sg:address":"Rio Guadalete, 23",
    "sg:city":"Mijas Costa",
    "sg:orig_category":"Venta, Colocaci\u00d3n De Autoradios",
    "sg:phone":"+34 952 59 36 99",
    "sg:postcode":"29649",
    "sg:province":"M\u00e1laga",
    "wof:name":"Pi\u00f1ar Fernandez Samuel",
    "wof:placetype":"venue"
},
  "geometry": {"coordinates":[-4.7157039642,36.4931945801],"type":"Point"}
}