{
  "type": "Feature",
  "properties": {
    "iso:country":"ES",
    "sg:address":"Calle de Placentinos, 7",
    "sg:city":"Salamanca",
    "sg:orig_category":"Ense\u00d1anza: Idiomas",
    "sg:phone":"+34 923 21 56 13",
    "sg:postcode":"37008",
    "sg:province":"Salamanca",
    "wof:name":"Sanchez Blazquez Amparo",
    "wof:placetype":"venue"
},
  "geometry": {"coordinates":[-5.6685628891,40.9622383118],"type":"Point"}
}