{
  "type": "Feature",
  "properties": {
    "iso:country":"ES",
    "sg:address":"Calle de Barrancas, 2",
    "sg:city":"Burguillos Toledo",
    "sg:orig_category":"Peluquer\u00cdas, Peluquer\u00cda Mixta",
    "sg:phone":"+34 925 39 33 22",
    "sg:postcode":"45112",
    "sg:province":"Toledo",
    "wof:name":"Martinez De La Casa Sanchez Sagrario",
    "wof:placetype":"venue"
},
  "geometry": {"coordinates":[-3.9935801029,39.795539856],"type":"Point"}
}