{
  "type": "Feature",
  "properties": {
    "addr:full":"Calle de Manuel Medrano, 1 Guadalajara Guadalajara 19001",
    "addr:housenumber":"1",
    "addr:postcode":"19001",
    "addr:street":"Calle De Manuel Medrano",
    "iso:country":"ES",
    "sg:address":"Calle de Manuel Medrano, 1",
    "sg:city":"Guadalajara",
    "sg:classifiers":[
        {
            "category":"Government",
            "subcategory":"City Hall",
            "type":"Public Place"
        }
    ],
    "sg:phone":"+34 949 21 33 66",
    "sg:postcode":"19001",
    "sg:province":"Guadalajara",
    "sg:tags":[
        "el",
        "alquiler",
        "extranjero",
        "villa",
        "de",
        "en"
    ],
    "wof:name":"Inmobiliaria Alcarria C.b.",
    "wof:placetype":"venue"
},
  "geometry": {"coordinates":[-3.1685090065,40.6327285767],"type":"Point"}
}