{
  "type": "Feature",
  "properties": {
    "addr:full":"Calle de Fontiveros, 44 Granada Granada 18008",
    "addr:housenumber":"44",
    "addr:postcode":"18008",
    "addr:street":"Calle De Fontiveros",
    "iso:country":"ES",
    "sg:address":"Calle de Fontiveros, 44",
    "sg:city":"Granada",
    "sg:orig_category":"Farmacias",
    "sg:phone":"+34 958 81 66 12",
    "sg:postcode":"18008",
    "sg:province":"Granada",
    "wof:name":"Sancho Fornes Amparo",
    "wof:placetype":"venue"
},
  "geometry": {"coordinates":[-3.5940330029,37.1612472534],"type":"Point"}
}