{
  "type": "Feature",
  "properties": {
    "addr:full":"Calle de Tamarite De Litera, 5 Barbastro Huesca 22300",
    "addr:housenumber":"5",
    "addr:postcode":"22300",
    "addr:street":"Calle De Tamarite;Litera",
    "iso:country":"ES",
    "sg:address":"Calle de Tamarite De Litera, 5",
    "sg:city":"Barbastro",
    "sg:orig_category":"Instalaci\u00d3n, Reparaci\u00d3n De Ascensores Y Montacargas",
    "sg:phone":"+34 974 31 46 19",
    "sg:postcode":"22300",
    "sg:province":"Huesca",
    "wof:name":"Ascensors F. Sales S.l.",
    "wof:placetype":"venue"
},
  "geometry": {"coordinates":[0.1334767044,42.0328979492],"type":"Point"}
}