{
  "type": "Feature",
  "properties": {
    "iso:country":"ES",
    "sg:address":"Cm\u00d1o Cabreira (da), 1",
    "sg:city":"Ramallosa",
    "sg:orig_category":"Frutas Y Legumbres Frescas (al Por Mayor)",
    "sg:phone":"+34 986 35 35 76",
    "sg:postcode":"36379",
    "sg:province":"Pontevedra",
    "wof:name":"Frutas Nieves S. L.",
    "wof:placetype":"venue"
},
  "geometry": {"coordinates":[-8.8124990463,42.1194648743],"type":"Point"}
}