{
  "type": "Feature",
  "properties": {
    "addr:full":"Calle de Doctor Velazquez, 6 Segorbe Castell\u00f3n 12400",
    "addr:housenumber":"6",
    "addr:postcode":"12400",
    "addr:street":"Calle De Doctor Velazquez",
    "iso:country":"ES",
    "sg:address":"Calle de Doctor Velazquez, 6",
    "sg:city":"Segorbe",
    "sg:orig_category":"Bisuter\u00cda, Joyer\u00cda, Relojer\u00cda (al Por Menor)",
    "sg:phone":"+34 964 71 40 20",
    "sg:postcode":"12400",
    "sg:province":"Castell\u00f3n",
    "wof:name":"Cebrian Gil Jose Pedro",
    "wof:placetype":"venue"
},
  "geometry": {"coordinates":[-0.4876970053,39.8489341736],"type":"Point"}
}