{
  "type": "Feature",
  "properties": {
    "addr:full":"Calle de Wiesbaden, 6 Donostia-san Sebastian Guip\u00f9zcoa 20008",
    "addr:housenumber":"6",
    "addr:postcode":"20008",
    "addr:street":"Calle De Wiesbaden",
    "iso:country":"ES",
    "sg:address":"Calle de Wiesbaden, 6",
    "sg:city":"Donostia-san Sebastian",
    "sg:orig_category":"Pescader\u00cdas (al Por Menor)",
    "sg:phone":"+34 943 21 83 05",
    "sg:postcode":"20008",
    "sg:province":"Guip\u00f9zcoa",
    "wof:name":"Pescados Y Mariscos Conde Cdad",
    "wof:placetype":"venue"
},
  "geometry": {"coordinates":[-2.0052518845,43.3160171509],"type":"Point"}
}