{
  "type": "Feature",
  "properties": {
    "addr:full":"Avda Constitucion (la), 27 Bogarra Albacete 02130",
    "addr:housenumber":"27",
    "addr:postcode":"02130",
    "addr:street":"Avda Constitucion La",
    "iso:country":"ES",
    "sg:address":"Avda Constitucion (la), 27",
    "sg:city":"Bogarra",
    "sg:orig_category":"Centros De Educaci\u00d3n Especial",
    "sg:phone":"+34 967 29 00 72",
    "sg:postcode":"02130",
    "sg:province":"Albacete",
    "wof:name":"C.r.a. Almenara",
    "wof:placetype":"venue"
},
  "geometry": {"coordinates":[-2.2142879963,38.5829696655],"type":"Point"}
}