{
  "type": "Feature",
  "properties": {
    "iso:country":"ES",
    "sg:address":"Revixos, 9",
    "sg:city":"Sta.maria De Dodro",
    "sg:orig_category":"Cr\u00cda De Animales",
    "sg:phone":"+34 981 80 22 13",
    "sg:postcode":"15981",
    "sg:province":"La Coru\u00f1a",
    "wof:name":"Becerra Barreiro Jose",
    "wof:placetype":"venue"
},
  "geometry": {"coordinates":[-8.6862039566,42.7238616943],"type":"Point"}
}