{
  "type": "Feature",
  "properties": {
    "addr:full":"Calle de Alvaro De Bazan, S/n Guadix Granada 18500",
    "addr:housenumber":"s",
    "addr:postcode":"18500",
    "addr:street":"Calle De Alvaro De Bazan;/ N",
    "iso:country":"ES",
    "sg:address":"Calle de Alvaro De Bazan, S/n",
    "sg:city":"Guadix",
    "sg:orig_category":"Notarios",
    "sg:phone":"+34 958 66 05 41",
    "sg:postcode":"18500",
    "sg:province":"Granada",
    "wof:name":"Sebastian Lopez Julian Santiago De",
    "wof:placetype":"venue"
},
  "geometry": {"coordinates":[-3.1308040619,37.3007583618],"type":"Point"}
}