{
  "type": "Feature",
  "properties": {
    "addr:full":"Calle de Industria, 59 Valencia Valencia 46022",
    "addr:housenumber":"59",
    "addr:postcode":"46022",
    "addr:street":"Calle De Industria",
    "iso:country":"ES",
    "sg:address":"Calle de Industria, 59",
    "sg:city":"Valencia",
    "sg:orig_category":"Carnicer\u00cdas, Carnicer\u00cdas",
    "sg:phone":"+34 963 72 63 74",
    "sg:postcode":"46022",
    "sg:province":"Valencia",
    "wof:name":"Cardapa S. L.",
    "wof:placetype":"venue"
},
  "geometry": {"coordinates":[-0.3417789936,39.4682655334],"type":"Point"}
}