{
  "type": "Feature",
  "properties": {
    "addr:full":"Avda Cabo Noval, S/n Sanlucar De Barrameda C\u00e1diz 11540",
    "addr:housenumber":"s / n",
    "addr:postcode":"11540",
    "addr:street":"Avda Cabo Noval;Ca\u0301Diz",
    "iso:country":"ES",
    "sg:address":"Avda Cabo Noval, S/n",
    "sg:city":"Sanlucar De Barrameda",
    "sg:orig_category":"M\u00c9dicos: Gastroenterolog\u00cda Y Hepatolog\u00cda (aparato Digestivo)",
    "sg:phone":"+34 956 38 18 27",
    "sg:postcode":"11540",
    "sg:province":"C\u00e1diz",
    "wof:name":"Ruiz Guinaldo Ana",
    "wof:placetype":"venue"
},
  "geometry": {"coordinates":[-6.3521537781,36.7833633423],"type":"Point"}
}