{
  "type": "Feature",
  "properties": {
    "iso:country":"ES",
    "sg:address":"Calle de Julio Del Campo, 5",
    "sg:city":"Le\u00f3n",
    "sg:orig_category":"Centros Empresariales",
    "sg:phone":"+34 987 27 00 44",
    "sg:postcode":"24002",
    "sg:province":"Le\u00f3n",
    "wof:name":"Fernandez Martinez Ramon",
    "wof:placetype":"venue"
},
  "geometry": {"coordinates":[-5.5741062164,42.5998458862],"type":"Point"}
}