{
  "type": "Feature",
  "properties": {
    "addr:full":"Calle de Santa Engracia, 132 Madrid Madrid 28003",
    "addr:housenumber":"132",
    "addr:postcode":"28003",
    "addr:street":"Calle De Santa Engracia",
    "iso:country":"ES",
    "sg:address":"Calle de Santa Engracia, 132",
    "sg:city":"Madrid",
    "sg:orig_category":"Tapiceros Y Tapiceros",
    "sg:phone":"+34 914 41 52 07",
    "sg:postcode":"28003",
    "sg:province":"Madrid",
    "sg:website":"www.integralproforum.com",
    "wof:name":"Menendez Galeote Rafael",
    "wof:placetype":"venue"
},
  "geometry": {"coordinates":[-3.7018654346,40.4421653748],"type":"Point"}
}