{
  "type": "Feature",
  "properties": {
    "iso:country":"ES",
    "sg:address":"Rbla Catalunya, 14",
    "sg:city":"Barcelona",
    "sg:orig_category":"Peleter\u00cdas",
    "sg:phone":"+34 933 18 16 45",
    "sg:postcode":"08007",
    "sg:province":"Barcelona",
    "wof:name":"Solsona Ferre Maria Gemma",
    "wof:placetype":"venue"
},
  "geometry": {"coordinates":[2.1675560474,41.3881721497],"type":"Point"}
}