{
  "type": "Feature",
  "properties": {
    "addr:full":"Ctra Crevillente, Km. 0035,0 Torretas Alicante 03180",
    "addr:postcode":"03180",
    "addr:street":"Ctra Crevillente Km. 0035,0",
    "iso:country":"ES",
    "sg:address":"Ctra Crevillente, Km. 0035,0",
    "sg:city":"Torretas",
    "sg:orig_category":"Empresarios Y Productoras De Espect\u00c1culos",
    "sg:phone":"+34 965 71 56 11",
    "sg:postcode":"03180",
    "sg:province":"Alicante",
    "wof:name":"Parques Del Mediterraneo S. A.",
    "wof:placetype":"venue"
},
  "geometry": {"coordinates":[-0.6536790133,38.0173606873],"type":"Point"}
}