{
  "type": "Feature",
  "properties": {
    "addr:full":"Calle de Condado De Trevi\u00d1o, 75 Miranda Ebro Burgos 09200",
    "addr:housenumber":"75",
    "addr:postcode":"09200",
    "addr:street":"Calle De Condado De Trevin\u0303O",
    "iso:country":"ES",
    "sg:address":"Calle de Condado De Trevi\u00d1o, 75",
    "sg:city":"Miranda Ebro",
    "sg:orig_category":"Delegados, Agentes De Tr\u00c1nsito, Auxiliares De Transporte Internacional",
    "sg:phone":"+34 947 33 14 29",
    "sg:postcode":"09200",
    "sg:province":"Burgos",
    "wof:name":"Macho Macho Eduardo",
    "wof:placetype":"venue"
},
  "geometry": {"coordinates":[-2.9395647049,42.6872329712],"type":"Point"}
}