{
  "type": "Feature",
  "properties": {
    "addr:full":"Carrer de Sant Joan, S/n Molins Rei Barcelona 08750",
    "addr:postcode":"08750",
    "addr:street":"Carrer De Sant Joan S / N Molins",
    "iso:country":"ES",
    "sg:address":"Carrer de Sant Joan, S/n",
    "sg:city":"Molins Rei",
    "sg:orig_category":"Centros De Educaci\u00d3n Especial",
    "sg:phone":"+34 936 68 40 54",
    "sg:postcode":"08750",
    "sg:province":"Barcelona",
    "wof:name":"Ajuntament De Molins De Rei",
    "wof:placetype":"venue"
},
  "geometry": {"coordinates":[2.0225813389,41.4104652405],"type":"Point"}
}