{
  "type": "Feature",
  "properties": {
    "iso:country":"ES",
    "sg:address":"Calle de Londres, 12",
    "sg:city":"Torrejon Ardoz",
    "sg:orig_category":"Delegados, Agentes De Tr\u00c1nsito, Auxiliares De Transporte Internacional",
    "sg:phone":"+34 916 77 80 87",
    "sg:postcode":"28850",
    "sg:province":"Madrid",
    "wof:name":"Gonzalez Gismero Juan Carlos",
    "wof:placetype":"venue"
},
  "geometry": {"coordinates":[-3.4737069607,40.4599113464],"type":"Point"}
}