{
  "type": "Feature",
  "properties": {
    "iso:country":"ES",
    "sg:address":"Calle de Torre (la), 8",
    "sg:city":"Altura",
    "sg:orig_category":"Reposter\u00cdas",
    "sg:phone":"+34 964 14 62 33",
    "sg:postcode":"12410",
    "sg:province":"Castell\u00f3n",
    "wof:name":"Carot Portoles Miguel",
    "wof:placetype":"venue"
},
  "geometry": {"coordinates":[-0.5144039989,39.8478736877],"type":"Point"}
}