{
  "type": "Feature",
  "properties": {
    "addr:full":"Calle de San Cristobal, 11 Jerez De La Frontera C\u00e1diz 11403",
    "addr:housenumber":"11",
    "addr:postcode":"11403",
    "addr:street":"Calle De San Cristobal",
    "iso:country":"ES",
    "sg:address":"Calle de San Cristobal, 11",
    "sg:city":"Jerez De La Frontera",
    "sg:orig_category":"Asociaciones Y Clubs Deportivos",
    "sg:phone":"+34 956 32 60 16",
    "sg:postcode":"11403",
    "sg:province":"C\u00e1diz",
    "sg:website":"www.ari.es-sermasports",
    "wof:name":"Estrade Gallego Servando",
    "wof:placetype":"venue"
},
  "geometry": {"coordinates":[-6.1375727654,36.6842041016],"type":"Point"}
}