{
  "type": "Feature",
  "properties": {
    "addr:full":"Calle de Teso Inestal, S/n Poligono Industrial Los Villares Salamanca 37184",
    "addr:housenumber":"s / n",
    "addr:postcode":"37184",
    "addr:street":"Calle De Teso Inestal;Industrial",
    "iso:country":"ES",
    "sg:address":"Calle de Teso Inestal, S/n",
    "sg:city":"Poligono Industrial Los Villares",
    "sg:orig_category":"Promotores Constructores",
    "sg:phone":"+34 923 25 40 30",
    "sg:postcode":"37184",
    "sg:province":"Salamanca",
    "wof:name":"Construcciones Marcos Hernandez S.l.",
    "wof:placetype":"venue"
},
  "geometry": {"coordinates":[-5.6425638199,40.9895362854],"type":"Point"}
}