{
  "type": "Feature",
  "properties": {
    "addr:full":"Ctra Alcala Villar Del Olmo (de) M-204, Km. 0003,0 Villalbilla Madrid 28810",
    "addr:postcode":"28810",
    "addr:street":"Ctra Alcala;Km. 0003,0",
    "iso:country":"ES",
    "sg:address":"Ctra Alcala Villar Del Olmo (de) M-204, Km. 0003,0",
    "sg:city":"Villalbilla",
    "sg:orig_category":"Concepci\u00d3n Y Realizaci\u00d3n De Maquetas Profesionales Y Prototipos",
    "sg:phone":"+34 918 85 97 59",
    "sg:postcode":"28810",
    "sg:province":"Madrid",
    "wof:name":"Fuentes Santiago Raul",
    "wof:placetype":"venue"
},
  "geometry": {"coordinates":[-3.2428519726,40.3435897827],"type":"Point"}
}