{
  "type": "Feature",
  "properties": {
    "addr:full":"Ctra Carretera Nacional V, Km. 0253,7 Trujillo C\u00e1ceres 10200",
    "addr:postcode":"10200",
    "addr:street":"Ctra Carretera Nacional V Km. 0253,7;Ca\u0301Ceres",
    "iso:country":"ES",
    "sg:address":"Ctra Carretera Nacional V, Km. 0253,7",
    "sg:city":"Trujillo",
    "sg:orig_category":"Mec\u00c1nico Del Autom\u00d3vil",
    "sg:phone":"+34 927 32 05 55",
    "sg:postcode":"10200",
    "sg:province":"C\u00e1ceres",
    "wof:name":"Automociones Avis S.l.",
    "wof:placetype":"venue"
},
  "geometry": {"coordinates":[-5.8758888245,39.4581871033],"type":"Point"}
}