{
  "type": "Feature",
  "properties": {
    "iso:country":"ES",
    "sg:address":"Carr Orient, 20",
    "sg:city":"Palamos",
    "sg:orig_category":"Deportes N\u00c1uticos, Acu\u00c1ticos Y Subacu\u00c1ticos: Art\u00cdculos Y Equipo (al Por Menor)",
    "sg:phone":"+34 972 31 43 26",
    "sg:postcode":"17230",
    "sg:province":"Girona",
    "wof:name":"Nautica Avi\u00f1o S.l.",
    "wof:placetype":"venue"
},
  "geometry": {"coordinates":[3.1281549931,41.8493118286],"type":"Point"}
}