{
  "type": "Feature",
  "properties": {
    "addr:full":"Geranios, S/n Torrevieja Alicante 03180",
    "addr:housenumber":"s",
    "addr:postcode":"03180",
    "addr:street":"Geranios;/ N",
    "iso:country":"ES",
    "sg:address":"Geranios, S/n",
    "sg:city":"Torrevieja",
    "sg:orig_category":"Telefon\u00cda: Instaladores Varios",
    "sg:phone":"+34 966 70 47 02",
    "sg:postcode":"03180",
    "sg:province":"Alicante",
    "wof:name":"Fun Telecom S.l.",
    "wof:placetype":"venue"
},
  "geometry": {"coordinates":[-0.6558700204,38.0098381042],"type":"Point"}
}