{
  "type": "Feature",
  "properties": {
    "iso:country":"ES",
    "sg:address":"C/ Mallorca, 21",
    "sg:city":"Elche",
    "sg:orig_category":"Promotores Constructores",
    "sg:phone":"+34 966 61 53 17",
    "sg:postcode":"03203",
    "sg:province":"Alicante",
    "wof:name":"Mactoca Ilicitana Sl",
    "wof:placetype":"venue"
},
  "geometry": {"coordinates":[-0.6729360223,38.2698631287],"type":"Point"}
}