{
  "type": "Feature",
  "properties": {
    "addr:full":"Calle de Roque (el), 8 Corralejo Playa Las Palmas 35660",
    "addr:housenumber":"8",
    "addr:postcode":"35660",
    "addr:street":"Calle De Roque El;Playa Las Palmas",
    "iso:country":"ES",
    "sg:address":"Calle de Roque (el), 8",
    "sg:city":"Corralejo Playa",
    "sg:orig_category":"Bazares, Art\u00cdculos De Limpieza Y De Cocina (al Por Menor)",
    "sg:phone":"+34 928 53 72 36",
    "sg:postcode":"35660",
    "sg:province":"Las Palmas",
    "wof:name":"Hirani Bros S.l.",
    "wof:placetype":"venue"
},
  "geometry": {"coordinates":[-13.8664989471,28.7248458862],"type":"Point"}
}