{
  "type": "Feature",
  "properties": {
    "addr:full":"Llanete De Vilches, S/n Alcala Real Ja\u00e9n 23680",
    "addr:housenumber":"s / n",
    "addr:postcode":"23680",
    "addr:street":"Vilches;Jae\u0301N",
    "iso:country":"ES",
    "sg:address":"Llanete De Vilches, S/n",
    "sg:city":"Alcala Real",
    "sg:orig_category":"Electricidad Veh\u00cdculo",
    "sg:phone":"+34 953 58 04 61",
    "sg:postcode":"23680",
    "sg:province":"Ja\u00e9n",
    "wof:name":"Mesas Mata Salvador",
    "wof:placetype":"venue"
},
  "geometry": {"coordinates":[-3.7895176411,37.7657394409],"type":"Point"}
}