{
  "type": "Feature",
  "properties": {
    "addr:full":"Calle de Ercilla, 40 Bilbao Vizcaya 48011",
    "addr:housenumber":"40",
    "addr:postcode":"48011",
    "addr:street":"Calle De Ercilla",
    "iso:country":"ES",
    "sg:address":"Calle de Ercilla, 40",
    "sg:city":"Bilbao",
    "sg:orig_category":"Abogados",
    "sg:phone":"+34 944 27 65 69",
    "sg:postcode":"48011",
    "sg:province":"Vizcaya",
    "wof:name":"Era\u00f1a Rigual Javier",
    "wof:placetype":"venue"
},
  "geometry": {"coordinates":[-2.9392418861,43.2611541748],"type":"Point"}
}