{
  "type": "Feature",
  "properties": {
    "addr:full":"Av Estadi (de L'), 10 Tortosa Tarragona 43500",
    "addr:housenumber":"10",
    "addr:postcode":"43500",
    "addr:street":"Av Estadi De L '",
    "iso:country":"ES",
    "sg:address":"Av Estadi (de L'), 10",
    "sg:city":"Tortosa",
    "sg:orig_category":"M\u00c9dicos: Ginecolog\u00cda Y Obstetricia",
    "sg:phone":"+34 977 50 15 97",
    "sg:postcode":"43500",
    "sg:province":"Tarragona",
    "wof:name":"Pla Hierro Jose",
    "wof:placetype":"venue"
},
  "geometry": {"coordinates":[0.514195025,40.8114700317],"type":"Point"}
}