{
  "type": "Feature",
  "properties": {
    "iso:country":"ES",
    "sg:address":"Avda Espa\u00d1a, 206",
    "sg:city":"Estepona",
    "sg:orig_category":"Inmobiliaria (agencias)",
    "sg:phone":"+34 952 79 57 06",
    "sg:postcode":"29680",
    "sg:province":"M\u00e1laga",
    "wof:name":"Marin Ruiz Ana",
    "wof:placetype":"venue"
},
  "geometry": {"coordinates":[-5.1485967636,36.4217987061],"type":"Point"}
}