{
  "type": "Feature",
  "properties": {
    "addr:full":"Praz Abastos (de), S/n Ourense Ourense 32002",
    "addr:housenumber":"s",
    "addr:postcode":"32002",
    "addr:street":"/ N",
    "iso:country":"ES",
    "sg:address":"Praz Abastos (de), S/n",
    "sg:city":"Ourense",
    "sg:orig_category":"Carnicer\u00cdas, Carnicer\u00cdas",
    "sg:phone":"+34 988 23 47 40",
    "sg:postcode":"32002",
    "sg:province":"Ourense",
    "wof:name":"Iglesias Varela Luis",
    "wof:placetype":"venue"
},
  "geometry": {"coordinates":[-7.8661170006,42.3389396667],"type":"Point"}
}