{
  "type": "Feature",
  "properties": {
    "iso:country":"ES",
    "sg:address":"Carrer de Linne, 22",
    "sg:city":"Terrassa",
    "sg:orig_category":"Mec\u00c1nico Del Autom\u00d3vil",
    "sg:phone":"+34 937 80 23 35",
    "sg:postcode":"08224",
    "sg:province":"Barcelona",
    "wof:name":"Talleres Linneo C.b.",
    "wof:placetype":"venue"
},
  "geometry": {"coordinates":[2.0054340363,41.5541801453],"type":"Point"}
}