{
  "type": "Feature",
  "properties": {
    "addr:full":"Avda San Martin, 21 Cortiguera Le\u00f3n 24412",
    "addr:housenumber":"21",
    "addr:postcode":"24412",
    "addr:street":"Avda San Martin",
    "iso:country":"ES",
    "sg:address":"Avda San Martin, 21",
    "sg:city":"Cortiguera",
    "sg:orig_category":"Contenedores (mercanc\u00cdas)",
    "sg:phone":"+34 987 42 16 47",
    "sg:postcode":"24412",
    "sg:province":"Le\u00f3n",
    "wof:name":"Sanchez Alvarez Eladio",
    "wof:placetype":"venue"
},
  "geometry": {"coordinates":[-6.6369829178,42.6198806763],"type":"Point"}
}