{
  "type": "Feature",
  "properties": {
    "iso:country":"ES",
    "sg:address":"Avda Orihuela, 80",
    "sg:city":"Alacant",
    "sg:orig_category":"Veh\u00cdculos De Ocasi\u00d3n",
    "sg:phone":"+34 965 11 69 02",
    "sg:postcode":"03006",
    "sg:province":"Alicante",
    "wof:name":"Automoviles M. Lillo C.b.",
    "wof:placetype":"venue"
},
  "geometry": {"coordinates":[-0.5097749233,38.3446998596],"type":"Point"}
}