{
  "type": "Feature",
  "properties": {
    "iso:country":"ES",
    "sg:address":"Calle de Sor Angela De La Cruz, 26",
    "sg:city":"Madrid",
    "sg:orig_category":"Agencias Y Agentes Comerciales, Representantes",
    "sg:phone":"+34 914 25 16 60",
    "sg:postcode":"28020",
    "sg:province":"Madrid",
    "wof:name":"Lai  Qiulian",
    "wof:placetype":"venue"
},
  "geometry": {"coordinates":[-3.6961467266,40.4599990845],"type":"Point"}
}