{
  "type": "Feature",
  "properties": {
    "addr:full":"Calle de Carretera, S/n Tobed Zaragoza 50325",
    "addr:postcode":"50325",
    "addr:street":"Calle De Carretera S / N Tobed",
    "iso:country":"ES",
    "sg:address":"Calle de Carretera, S/n",
    "sg:city":"Tobed",
    "sg:orig_category":"Cr\u00cda De Cerdos",
    "sg:phone":"+34 976 62 88 64",
    "sg:postcode":"50325",
    "sg:province":"Zaragoza",
    "wof:name":"Aladren S.cv.",
    "wof:placetype":"venue"
},
  "geometry": {"coordinates":[-1.429289937,41.3714981079],"type":"Point"}
}