{
  "type": "Feature",
  "properties": {
    "iso:country":"ES",
    "sg:address":"Calle de Carlos Sainz (de), 43",
    "sg:city":"Leganes",
    "sg:orig_category":"Comercio De Piezas De Recambio Y De Accesorios De Veh\u00cdculos, Veh\u00cdculos Industriales",
    "sg:phone":"+34 916 89 43 39",
    "sg:postcode":"28914",
    "sg:province":"Madrid",
    "wof:name":"Seliauto S.a.",
    "wof:placetype":"venue"
},
  "geometry": {"coordinates":[-3.7710359097,40.3156204224],"type":"Point"}
}