{
  "type": "Feature",
  "properties": {
    "iso:country":"ES",
    "sg:address":"Irunlarrea, 27",
    "sg:city":"Iru\u00f1a",
    "sg:orig_category":"Loter\u00cda Y T\u00d3mbola",
    "sg:phone":"+34 948 19 03 55",
    "sg:postcode":"31008",
    "sg:province":"Navarra",
    "sg:website":"www.loteria21.com",
    "wof:name":"Sarasa Astrain Jesus",
    "wof:placetype":"venue"
},
  "geometry": {"coordinates":[-1.6727329493,42.8097229004],"type":"Point"}
}