{
  "type": "Feature",
  "properties": {
    "iso:country":"ES",
    "sg:address":"Bo. As Cocheiras, S/n",
    "sg:city":"Cocheiras",
    "sg:orig_category":"Papel (al Por Mayor)",
    "sg:phone":"+34 986 86 44 91",
    "sg:postcode":"36910",
    "sg:province":"Pontevedra",
    "wof:name":"Grupo Empresarial Ence S.a.",
    "wof:placetype":"venue"
},
  "geometry": {"coordinates":[-8.6879987717,42.3997993469],"type":"Point"}
}