{
  "type": "Feature",
  "properties": {
    "addr:full":"Avda Madrid (de), 26 Valdemoro Madrid 28340",
    "addr:housenumber":"26",
    "addr:postcode":"28340",
    "addr:street":"Avda Madrid De",
    "iso:country":"ES",
    "sg:address":"Avda Madrid (de), 26",
    "sg:city":"Valdemoro",
    "sg:orig_category":"Chapister\u00cda",
    "sg:phone":"+34 918 95 57 11",
    "sg:postcode":"28340",
    "sg:province":"Madrid",
    "sg:website":"www.maypersl.com",
    "wof:name":"Materiales Y Perforados S.l.",
    "wof:placetype":"venue"
},
  "geometry": {"coordinates":[-3.6844639778,40.212890625],"type":"Point"}
}