{
  "type": "Feature",
  "properties": {
    "addr:full":"Calle de Jose Luis Del Arco, 4 San Lorenzo De El Escorial Madrid 28200",
    "addr:housenumber":"4",
    "addr:postcode":"28200",
    "addr:street":"Calle De Jose Luis Del Arco",
    "iso:country":"ES",
    "sg:address":"Calle de Jose Luis Del Arco, 4",
    "sg:city":"San Lorenzo De El Escorial",
    "sg:orig_category":"Bares, Piano",
    "sg:phone":"+34 918 90 18 36",
    "sg:postcode":"28200",
    "sg:province":"Madrid",
    "wof:name":"Besgar S. L.",
    "wof:placetype":"venue"
},
  "geometry": {"coordinates":[-4.1386790276,40.5953636169],"type":"Point"}
}