{
  "type": "Feature",
  "properties": {
    "addr:full":"Calle de Armas, 11 Llerena Badajoz 06900",
    "addr:housenumber":"11",
    "addr:postcode":"06900",
    "addr:street":"Calle De Armas",
    "iso:country":"ES",
    "sg:address":"Calle de Armas, 11",
    "sg:city":"Llerena",
    "sg:orig_category":"Farmacias",
    "sg:phone":"+34 924 87 22 52",
    "sg:postcode":"06900",
    "sg:province":"Badajoz",
    "wof:name":"Diaz Arellano Jesus",
    "wof:placetype":"venue"
},
  "geometry": {"coordinates":[-6.0160069466,38.2371559143],"type":"Point"}
}