{
  "type": "Feature",
  "properties": {
    "iso:country":"ES",
    "sg:address":"Avda Alcalde Jose Aranda, 47",
    "sg:city":"Alcorcon",
    "sg:orig_category":"Promotores Constructores",
    "sg:phone":"+34 916 10 38 17",
    "sg:postcode":"28923",
    "sg:province":"Madrid",
    "wof:name":"Almagro Castro Encarnacion",
    "wof:placetype":"venue"
},
  "geometry": {"coordinates":[-3.8223695755,40.3433113098],"type":"Point"}
}