{
  "type": "Feature",
  "properties": {
    "iso:country":"ES",
    "sg:address":"Calle de Luzarra, 16",
    "sg:city":"Bilbao",
    "sg:orig_category":"Agencias De Viajes",
    "sg:phone":"+34 944 74 57 88",
    "sg:postcode":"48014",
    "sg:province":"Vizcaya",
    "sg:website":"www.mapatour.com/tierrajoven",
    "wof:name":"Mapa Tours S.a.",
    "wof:placetype":"venue"
},
  "geometry": {"coordinates":[-2.9471549988,43.2724761963],"type":"Point"}
}