{
  "type": "Feature",
  "properties": {
    "addr:full":"Calle de Manuel Perez Navarro, 4 Palmas De Gran Canaria Las Palmas 35014",
    "addr:housenumber":"4",
    "addr:postcode":"35014",
    "addr:street":"Calle De Manuel Perez Navarro",
    "iso:country":"ES",
    "sg:address":"Calle de Manuel Perez Navarro, 4",
    "sg:city":"Palmas De Gran Canaria",
    "sg:orig_category":"Librer\u00cdas",
    "sg:phone":"+34 928 38 47 07",
    "sg:postcode":"35014",
    "sg:province":"Las Palmas",
    "wof:name":"Quesada Del Rosario Josefa",
    "wof:placetype":"venue"
},
  "geometry": {"coordinates":[-15.4316043854,28.1053695679],"type":"Point"}
}