{
  "type": "Feature",
  "properties": {
    "iso:country":"ES",
    "sg:address":"Calle de Alhondiga (la), 15",
    "sg:city":"Sahagun",
    "sg:orig_category":"Molduras, Junquillos, Listones Y Molduras Perforadas",
    "sg:phone":"+34 987 78 07 51",
    "sg:postcode":"24320",
    "sg:province":"Le\u00f3n",
    "wof:name":"Martin Iba\u00f1ez Florencio",
    "wof:placetype":"venue"
},
  "geometry": {"coordinates":[-5.0296158791,42.3721733093],"type":"Point"}
}