{
  "type": "Feature",
  "properties": {
    "iso:country":"ES",
    "sg:address":"Calle de Virgen, 9",
    "sg:city":"Don Benito",
    "sg:orig_category":"Abogados",
    "sg:phone":"+34 924 80 44 38",
    "sg:postcode":"06400",
    "sg:province":"Badajoz",
    "wof:name":"Granados Fernandez De Arevalo Luis Gonzalo",
    "wof:placetype":"venue"
},
  "geometry": {"coordinates":[-5.8619861603,38.9514923096],"type":"Point"}
}