{
  "type": "Feature",
  "properties": {
    "iso:country":"ES",
    "sg:address":"Calle de Guiard Teofilo, 2",
    "sg:city":"Bilbao",
    "sg:orig_category":"Muebles, Minoristas",
    "sg:phone":"+34 944 41 77 84",
    "sg:postcode":"48011",
    "sg:province":"Vizcaya",
    "sg:website":"www.ka-international.com",
    "wof:name":"Valdepesa Textil S.l.",
    "wof:placetype":"venue"
},
  "geometry": {"coordinates":[-2.9387440681,43.2645606995],"type":"Point"}
}