{
  "type": "Feature",
  "properties": {
    "addr:full":"Calle de General Amor, 1 Palencia Palencia 34005",
    "addr:housenumber":"1",
    "addr:postcode":"34005",
    "addr:street":"Calle De General Amor",
    "iso:country":"ES",
    "sg:address":"Calle de General Amor, 1",
    "sg:city":"Palencia",
    "sg:orig_category":"Cristaler\u00cdas",
    "sg:phone":"+34 979 74 21 00",
    "sg:postcode":"34005",
    "sg:province":"Palencia",
    "sg:website":"www.paginasamarillas.es",
    "wof:name":"Perez Rebollar Serafin Samuel",
    "wof:placetype":"venue"
},
  "geometry": {"coordinates":[-4.5340681076,42.0092658997],"type":"Point"}
}