{
  "type": "Feature",
  "properties": {
    "iso:country":"ES",
    "sg:address":"Calle de Cartagena, 44",
    "sg:city":"Madrid",
    "sg:orig_category":"Venta, Montaje De Neum\u00c1ticos",
    "sg:phone":"+34 917 25 25 83",
    "sg:postcode":"28028",
    "sg:province":"Madrid",
    "wof:name":"Nermovil Tiendas S.l.",
    "wof:placetype":"venue"
},
  "geometry": {"coordinates":[-3.6700656414,40.4354248047],"type":"Point"}
}