{
  "type": "Feature",
  "properties": {
    "addr:full":"Calle de Valdemoro, 5 Ventorro Del Cano Madrid 28925",
    "addr:housenumber":"5",
    "addr:postcode":"28925",
    "addr:street":"Calle De Valdemoro",
    "iso:country":"ES",
    "sg:address":"Calle de Valdemoro, 5",
    "sg:city":"Ventorro Del Cano",
    "sg:orig_category":"T\u00c9cnicos Veterinarios",
    "sg:phone":"+34 916 33 29 14",
    "sg:postcode":"28925",
    "sg:province":"Madrid",
    "wof:name":"Perez Ruiz Jose Maria",
    "wof:placetype":"venue"
},
  "geometry": {"coordinates":[-3.8428459167,40.3912963867],"type":"Point"}
}