{
  "type": "Feature",
  "properties": {
    "addr:full":"Calle de General Yag\u00fce, 11 Madrid Madrid 28020",
    "addr:housenumber":"11",
    "addr:postcode":"madrid;28020",
    "addr:street":"Calle De General Yaguee",
    "iso:country":"ES",
    "sg:address":"Calle de General Yag\u00fce, 11",
    "sg:city":"Madrid",
    "sg:orig_category":"Molduras, Junquillos, Listones Y Molduras Perforadas",
    "sg:phone":"+34 915 55 29 18",
    "sg:postcode":"28020",
    "sg:province":"Madrid",
    "wof:name":"Hernandez Serrano Jose Luis Gaspar",
    "wof:placetype":"venue"
},
  "geometry": {"coordinates":[-3.6935977936,40.4563293457],"type":"Point"}
}