{
  "type": "Feature",
  "properties": {
    "iso:country":"ES",
    "sg:address":"Carr Panissars, 23",
    "sg:city":"Castello D'empuries",
    "sg:orig_category":"Trabajos De Perforaciones, Sondeos, Construcci\u00d3n De Pozos",
    "sg:phone":"+34 972 25 01 45",
    "sg:postcode":"17486",
    "sg:province":"Girona",
    "wof:name":"Batlle Tarres Jaume",
    "wof:placetype":"venue"
},
  "geometry": {"coordinates":[3.1170799732,42.139251709],"type":"Point"}
}