{
  "type": "Feature",
  "properties": {
    "addr:full":"Calle de Filiberto Villalobos, 215 Guijuelo Salamanca 37770",
    "addr:housenumber":"215",
    "addr:postcode":"37770",
    "addr:street":"Calle De Filiberto Villalobos",
    "iso:country":"ES",
    "sg:address":"Calle de Filiberto Villalobos, 215",
    "sg:city":"Guijuelo",
    "sg:orig_category":"Distribuci\u00d3n De Petr\u00d3leo Y Derivados",
    "sg:phone":"+34 923 58 11 48",
    "sg:postcode":"37770",
    "sg:province":"Salamanca",
    "wof:name":"Nieto Matas S.l.",
    "wof:placetype":"venue"
},
  "geometry": {"coordinates":[-5.6696791649,40.5658683777],"type":"Point"}
}