{
  "type": "Feature",
  "properties": {
    "addr:full":"Plaz Espa\u00d1a, 5 Riofrio \u00c1vila 05190",
    "addr:housenumber":"5",
    "addr:postcode":"05190",
    "addr:street":"Plaz Espan\u0303A;A\u0301Vila",
    "iso:country":"ES",
    "sg:address":"Plaz Espa\u00d1a, 5",
    "sg:city":"Riofrio",
    "sg:orig_category":"Administraciones Regionales, Departamentales Y Locales",
    "sg:phone":"+34 920 26 80 11",
    "sg:postcode":"05190",
    "sg:province":"\u00c1vila",
    "wof:name":"Ayuntamiento De Riofrio",
    "wof:placetype":"venue"
},
  "geometry": {"coordinates":[-4.7588043213,40.547077179],"type":"Point"}
}