{
  "type": "Feature",
  "properties": {
    "addr:full":"Atalaya, S/n Gelsa Zaragoza 50786",
    "addr:housenumber":"s / n",
    "addr:postcode":"50786",
    "addr:street":"Atalaya",
    "iso:country":"ES",
    "sg:address":"Atalaya, S/n",
    "sg:city":"Gelsa",
    "sg:orig_category":"Cogeneraci\u00d3n: Equipo Y Servicios",
    "sg:phone":"+34 976 17 68 97",
    "sg:postcode":"50786",
    "sg:province":"Zaragoza",
    "wof:name":"Tecnicas De Cogeneracion Del Gelsa S.l.",
    "wof:placetype":"venue"
},
  "geometry": {"coordinates":[-0.4555689991,41.4115943909],"type":"Point"}
}