{
  "type": "Feature",
  "properties": {
    "addr:full":"Calle de Bertendona, 1 Bilbao Vizcaya 48008",
    "addr:housenumber":"1",
    "addr:postcode":"48008",
    "addr:street":"Calle De Bertendona",
    "iso:country":"ES",
    "sg:address":"Calle de Bertendona, 1",
    "sg:city":"Bilbao",
    "sg:orig_category":"Comercio De Mobiliario De Oficina",
    "sg:phone":"+34 944 43 48 81",
    "sg:postcode":"48008",
    "sg:province":"Vizcaya",
    "sg:website":"www.emeuveonline.com}}",
    "wof:name":"Emeuve Mobiliario S. A.",
    "wof:placetype":"venue"
},
  "geometry": {"coordinates":[-2.9310588837,43.2592964172],"type":"Point"}
}