{
  "type": "Feature",
  "properties": {
    "addr:full":"Calle de Zacatena, 32 Daimiel Ciudad Real 13250",
    "addr:housenumber":"32",
    "addr:postcode":"13250",
    "addr:street":"Calle De Zacatena",
    "iso:country":"ES",
    "sg:address":"Calle de Zacatena, 32",
    "sg:city":"Daimiel",
    "sg:orig_category":"Molduras, Junquillos, Listones Y Molduras Perforadas",
    "sg:phone":"+34 926 85 43 87",
    "sg:postcode":"13250",
    "sg:province":"Ciudad Real",
    "wof:name":"Sanchez Pablo Lopez Romero Francisco",
    "wof:placetype":"venue"
},
  "geometry": {"coordinates":[-3.6177489758,39.0760803223],"type":"Point"}
}