{
  "type": "Feature",
  "properties": {
    "iso:country":"ES",
    "sg:address":"Calle de Marcelino Giner, 11",
    "sg:city":"Valencia",
    "sg:orig_category":"Laboratorios Y Trabajos De Fotograf\u00cda, V\u00cddeo Y Cine",
    "sg:phone":"+34 963 60 15 41",
    "sg:postcode":"46020",
    "sg:province":"Valencia",
    "wof:name":"Market-color S.l.",
    "wof:placetype":"venue"
},
  "geometry": {"coordinates":[-0.3560349941,39.485244751],"type":"Point"}
}