{
  "type": "Feature",
  "properties": {
    "iso:country":"ES",
    "sg:address":"Calle de Arces, 29",
    "sg:city":"Malaga",
    "sg:orig_category":"Inmobiliaria (agencias)",
    "sg:phone":"+34 952 29 61 61",
    "sg:postcode":"29018",
    "sg:province":"M\u00e1laga",
    "wof:name":"Cop 2010 Malaka Gestoria S.l.",
    "wof:placetype":"venue"
},
  "geometry": {"coordinates":[-4.3837590218,36.7320632935],"type":"Point"}
}