{
  "type": "Feature",
  "properties": {
    "addr:full":"Calle de San Antonio, 12 Arroyo De La Miel-benalmadena Costa M\u00e1laga 29631",
    "addr:housenumber":"12",
    "addr:postcode":"29631",
    "addr:street":"Calle De San Antonio;Ma\u0301Laga",
    "iso:country":"ES",
    "sg:address":"Calle de San Antonio, 12",
    "sg:city":"Arroyo De La Miel-benalmadena Costa",
    "sg:orig_category":"Papeler\u00cdas, Librer\u00cdas",
    "sg:phone":"+34 952 44 53 31",
    "sg:postcode":"29631",
    "sg:province":"M\u00e1laga",
    "wof:name":"Moreno Portillo Jose",
    "wof:placetype":"venue"
},
  "geometry": {"coordinates":[-4.5482521057,36.6017608643],"type":"Point"}
}