{
  "type": "Feature",
  "properties": {
    "addr:full":"Calle de Ramon Y Cajal, S/n Burujon Toledo 45519",
    "addr:housenumber":"s",
    "addr:postcode":"45519",
    "addr:street":"Calle De Ramon Y Cajal;/ N Burujon",
    "iso:country":"ES",
    "sg:address":"Calle de Ramon Y Cajal, S/n",
    "sg:city":"Burujon",
    "sg:orig_category":"Charcuter\u00cdas (al Por Mayor)",
    "sg:phone":"+34 925 75 61 49",
    "sg:postcode":"45519",
    "sg:province":"Toledo",
    "wof:name":"Carnicas Del Olmo S.l.",
    "wof:placetype":"venue"
},
  "geometry": {"coordinates":[-97.78224945069999,45.7040786743],"type":"Point"}
}