{
  "type": "Feature",
  "properties": {
    "iso:country":"ES",
    "sg:address":"Carrer de Pasteur, 54",
    "sg:city":"Terrassa",
    "sg:orig_category":"Peluquer\u00cdas, Peluquer\u00cda Mixta",
    "sg:phone":"+34 937 33 07 80",
    "sg:postcode":"08224",
    "sg:province":"Barcelona",
    "wof:name":"Signes Perruquer S.c.p",
    "wof:placetype":"venue"
},
  "geometry": {"coordinates":[2.0017681122,41.5669670105],"type":"Point"}
}