{
  "type": "Feature",
  "properties": {
    "iso:country":"ES",
    "sg:address":"C/ Almansa, 65",
    "sg:city":"Elche",
    "sg:orig_category":"Zapatos (al Por Mayor)",
    "sg:phone":"+34 966 67 26 50",
    "sg:postcode":"03291",
    "sg:province":"Alicante",
    "wof:name":"Shoekox S.l.",
    "wof:placetype":"venue"
},
  "geometry": {"coordinates":[-0.7210479975,38.2773399353],"type":"Point"}
}