{
  "type": "Feature",
  "properties": {
    "iso:country":"ES",
    "sg:address":"La Ribera, 31",
    "sg:city":"Priego Cordoba",
    "sg:orig_category":"Artes Gr\u00c1ficas, Artes Pl\u00c1sticas (curso)",
    "sg:phone":"+34 957 54 09 45",
    "sg:postcode":"14800",
    "sg:province":"C\u00f3rdoba",
    "wof:name":"Arroyo Moreno Alonso",
    "wof:placetype":"venue"
},
  "geometry": {"coordinates":[-4.1931734085,37.4392929077],"type":"Point"}
}