{
  "type": "Feature",
  "properties": {
    "addr:full":"Crta Azucarera-intelhorce (pi Gudalhorc), 126 Malaga M\u00e1laga 29004",
    "addr:housenumber":"126",
    "addr:postcode":"29004",
    "addr:street":"Crta Azucarera-Intelhorce Pi Gudalhorc;Ma\u0301Laga",
    "iso:country":"ES",
    "sg:address":"Crta Azucarera-intelhorce (pi Gudalhorc), 126",
    "sg:city":"Malaga",
    "sg:orig_category":"Pintura, Barniz, Productos Asimilables (fabricaci\u00d3n, Al Por Mayor)",
    "sg:phone":"+34 952 23 59 46",
    "sg:postcode":"29004",
    "sg:province":"M\u00e1laga",
    "wof:name":"Emeache S. A.",
    "wof:placetype":"venue"
},
  "geometry": {"coordinates":[-4.4931812286,36.6966972351],"type":"Point"}
}