{
  "type": "Feature",
  "properties": {
    "addr:full":"Carrer de Parlament, 58 Barcelona Barcelona 08015",
    "addr:housenumber":"58",
    "addr:postcode":"08015",
    "addr:street":"Carrer De Parlament",
    "iso:country":"ES",
    "sg:address":"Carrer de Parlament, 58",
    "sg:city":"Barcelona",
    "sg:orig_category":"Estancos",
    "sg:phone":"+34 934 41 27 31",
    "sg:postcode":"08015",
    "sg:province":"Barcelona",
    "wof:name":"Lois Ponce De Leon Elisa",
    "wof:placetype":"venue"
},
  "geometry": {"coordinates":[2.1642251015,41.3775100708],"type":"Point"}
}