{
  "type": "Feature",
  "properties": {
    "iso:country":"ES",
    "sg:address":"Avda Terra Cha, 161",
    "sg:city":"Castro",
    "sg:orig_category":"Maquinaria, Instalaci\u00d3n Y Equipo Para Garajes Y Estaciones De Servicio",
    "sg:phone":"+34 982 31 03 77",
    "sg:postcode":"27260",
    "sg:province":"Lugo",
    "wof:name":"Estacion De Servicio Rio Lea S.l.",
    "wof:placetype":"venue"
},
  "geometry": {"coordinates":[-7.4919791222,43.1373901367],"type":"Point"}
}