{
  "type": "Feature",
  "properties": {
    "addr:full":"Avda Ronda De Los Tejares, 19 Cordoba C\u00f3rdoba 14001",
    "addr:housenumber":"19",
    "addr:postcode":"14001",
    "addr:street":"Avda Ronda De Los Tejares;Co\u0301Rdoba",
    "iso:country":"ES",
    "sg:address":"Avda Ronda De Los Tejares, 19",
    "sg:city":"Cordoba",
    "sg:orig_category":"Empresarios",
    "sg:phone":"+34 957 47 33 08",
    "sg:postcode":"14001",
    "sg:province":"C\u00f3rdoba",
    "wof:name":"Fundacion Andaluza De Administradores De Fincas",
    "wof:placetype":"venue"
},
  "geometry": {"coordinates":[-4.7807631493,37.8883666992],"type":"Point"}
}