{
  "type": "Feature",
  "properties": {
    "addr:full":"Calle de Leon, 11 Fuenlabrada Madrid 28947",
    "addr:housenumber":"11",
    "addr:postcode":"28947",
    "addr:street":"Calle De Leon",
    "iso:country":"ES",
    "sg:address":"Calle de Leon, 11",
    "sg:city":"Fuenlabrada",
    "sg:orig_category":"Alimentaci\u00d3n Animal (fabricaci\u00d3n, Al Por Mayor)",
    "sg:phone":"+34 916 42 04 18",
    "sg:postcode":"28947",
    "sg:province":"Madrid",
    "wof:name":"Mcdog Pet Products S.l.",
    "wof:placetype":"venue"
},
  "geometry": {"coordinates":[-3.7436909676,40.2650032043],"type":"Point"}
}