{
  "type": "Feature",
  "properties": {
    "iso:country":"ES",
    "sg:address":"Calle de Gran Via, 64",
    "sg:city":"Salamanca",
    "sg:orig_category":"Procuradores",
    "sg:phone":"+34 923 26 82 25",
    "sg:postcode":"37001",
    "sg:province":"Salamanca",
    "wof:name":"Cuevas Casta\u00f1o Rafael",
    "wof:placetype":"venue"
},
  "geometry": {"coordinates":[-5.6620678902,40.9628791809],"type":"Point"}
}