{
  "type": "Feature",
  "properties": {
    "iso:country":"ES",
    "sg:address":"Ctra. Madrid-cadiz, Km. 0297,0",
    "sg:city":"Bailen",
    "sg:orig_category":"Alfarer\u00cda",
    "sg:phone":"+34 953 67 12 61",
    "sg:postcode":"23710",
    "sg:province":"Ja\u00e9n",
    "wof:name":"Carrion Cedron Manuel",
    "wof:placetype":"venue"
},
  "geometry": {"coordinates":[-3.7710540295,38.0965309143],"type":"Point"}
}