{
  "type": "Feature",
  "properties": {
    "addr:full":"Nueva, 2 Puigmoreno Teruel 44660",
    "addr:housenumber":"2",
    "addr:postcode":"44660",
    "addr:street":"Nueva",
    "iso:country":"ES",
    "sg:address":"Nueva, 2",
    "sg:city":"Puigmoreno",
    "sg:orig_category":"Agencias Y Agentes Comerciales, Representantes",
    "sg:phone":"+34 978 83 81 84",
    "sg:postcode":"44660",
    "sg:province":"Teruel",
    "wof:name":"Montoya Ortega Martirio",
    "wof:placetype":"venue"
},
  "geometry": {"coordinates":[-0.2500289977,41.1078109741],"type":"Point"}
}