{
  "type": "Feature",
  "properties": {
    "iso:country":"ES",
    "sg:address":"Pol Ind La Pelleria, 8",
    "sg:city":"Xeresa",
    "sg:orig_category":"Confecci\u00d3n De Zapatos",
    "sg:phone":"+34 962 89 56 77",
    "sg:postcode":"46790",
    "sg:province":"Valencia",
    "wof:name":"Gandimport S.l.",
    "wof:placetype":"venue"
},
  "geometry": {"coordinates":[-0.2175740004,39.0116996765],"type":"Point"}
}