{
  "type": "Feature",
  "properties": {
    "iso:country":"ES",
    "sg:address":"Calle de Andres Baquero, 9",
    "sg:city":"San Lorenzo",
    "sg:orig_category":"Abogados",
    "sg:phone":"+34 968 22 37 33",
    "sg:postcode":"30001",
    "sg:province":"Murcia",
    "wof:name":"Molina Jordana Belen",
    "wof:placetype":"venue"
},
  "geometry": {"coordinates":[-1.1298867464,37.9834747314],"type":"Point"}
}