{
  "type": "Feature",
  "properties": {
    "iso:country":"ES",
    "sg:address":"Carrer de Jacint Verdaguer, 7",
    "sg:city":"Pobla Mafumet",
    "sg:orig_category":"Alimentaci\u00d3n General (al Por Menor)",
    "sg:phone":"+34 977 84 04 56",
    "sg:postcode":"43140",
    "sg:province":"Tarragona",
    "wof:name":"Preixens Padrell Jose Maria",
    "wof:placetype":"venue"
},
  "geometry": {"coordinates":[1.2091890574,41.1875114441],"type":"Point"}
}