{
  "type": "Feature",
  "properties": {
    "addr:full":"Carrer de Sant Lloren\u00c7 Desmunts, 1 Vic Barcelona 08500",
    "addr:housenumber":"1",
    "addr:postcode":"08500",
    "addr:street":"Carrer De Sant Llorenc\u0327 Desmunts",
    "iso:country":"ES",
    "sg:address":"Carrer de Sant Lloren\u00c7 Desmunts, 1",
    "sg:city":"Vic",
    "sg:orig_category":"Fabricaci\u00d3n Y Venta De Volquetes Y Remolques",
    "sg:phone":"+34 938 89 25 89",
    "sg:postcode":"08500",
    "sg:province":"Barcelona",
    "sg:website":"www.sane.es",
    "wof:name":"Remolques Y Planchisteria Sa\u00f1e S.l.",
    "wof:placetype":"venue"
},
  "geometry": {"coordinates":[2.2774400711,41.9508285522],"type":"Point"}
}