{
  "type": "Feature",
  "properties": {
    "iso:country":"ES",
    "sg:address":"Calle de Trinidad, 24",
    "sg:city":"Lebrija",
    "sg:classifiers":[
        {
            "category":"Autos & Motor Vehicles",
            "subcategory":"Automobile Sales",
            "type":"Retail Goods"
        }
    ],
    "sg:phone":"+34 955 97 12 66",
    "sg:postcode":"41740",
    "sg:province":"Sevilla",
    "wof:name":"Cooperativa Sevillana De Autoescuela",
    "wof:placetype":"venue"
},
  "geometry": {"coordinates":[-6.078649044,36.9182739258],"type":"Point"}
}