{
  "type": "Feature",
  "properties": {
    "iso:country":"ES",
    "sg:address":"Crrd San Bartolome, 37",
    "sg:city":"Andujar",
    "sg:orig_category":"Asociaciones Ecologistas",
    "sg:phone":"+34 953 50 04 87",
    "sg:postcode":"23740",
    "sg:province":"Ja\u00e9n",
    "wof:name":"Comunidad De Regantes Del Pantano Del Rumblar",
    "wof:placetype":"venue"
},
  "geometry": {"coordinates":[-4.0595469475,38.0399971008],"type":"Point"}
}