{
  "type": "Feature",
  "properties": {
    "addr:full":"Carrer de Conca De Tremp, 36 Barcelona Barcelona 08032",
    "addr:housenumber":"36",
    "addr:postcode":"08032",
    "addr:street":"Carrer De Conca De Tremp",
    "iso:country":"ES",
    "sg:address":"Carrer de Conca De Tremp, 36",
    "sg:city":"Barcelona",
    "sg:orig_category":"Cajas De Ahorro",
    "sg:phone":"+34 934 20 37 97",
    "sg:postcode":"08032",
    "sg:province":"Barcelona",
    "sg:website":"www.lacaixa.es",
    "wof:name":"Caixa D'estalvis I Pensions De Barcelona",
    "wof:placetype":"venue"
},
  "geometry": {"coordinates":[2.1561760902,41.4226150513],"type":"Point"}
}