{
  "type": "Feature",
  "properties": {
    "addr:full":"San Bartolome, S/n Guadalupe C\u00e1ceres 10140",
    "addr:housenumber":"s / n",
    "addr:postcode":"10140",
    "addr:street":"San Bartolome;Ca\u0301Ceres",
    "iso:country":"ES",
    "sg:address":"San Bartolome, S/n",
    "sg:city":"Guadalupe",
    "sg:orig_category":"Plomeros",
    "sg:phone":"+34 927 36 74 66",
    "sg:postcode":"10140",
    "sg:province":"C\u00e1ceres",
    "wof:name":"Rodriguez Sierra Lorenzo",
    "wof:placetype":"venue"
},
  "geometry": {"coordinates":[-5.3265609741,39.4494514465],"type":"Point"}
}