{
  "type": "Feature",
  "properties": {
    "iso:country":"ES",
    "sg:address":"Rua Castelao, 12",
    "sg:city":"Barco",
    "sg:orig_category":"Suministros Y Materiales Industriales",
    "sg:phone":"+34 988 32 15 07",
    "sg:postcode":"32300",
    "sg:province":"Ourense",
    "wof:name":"Suministros Mecanicos De Valdeorras S.l.",
    "wof:placetype":"venue"
},
  "geometry": {"coordinates":[-6.9897179604,42.4174957275],"type":"Point"}
}