{
  "type": "Feature",
  "properties": {
    "iso:country":"ES",
    "sg:address":"Carrer de Major, 22",
    "sg:city":"Castelldefels",
    "sg:orig_category":"Electricidad: Instaladores",
    "sg:phone":"+34 936 36 69 69",
    "sg:postcode":"08860",
    "sg:province":"Barcelona",
    "wof:name":"Tecnogil Castelldefels S.l.",
    "wof:placetype":"venue"
},
  "geometry": {"coordinates":[1.9814800024,41.2831535339],"type":"Point"}
}