{
  "type": "Feature",
  "properties": {
    "iso:country":"ES",
    "sg:address":"Calle de Hesperides, 20",
    "sg:city":"Sevilla",
    "sg:orig_category":"Electrodom\u00c9sticos (al Por Menor)",
    "sg:phone":"+34 954 35 28 68",
    "sg:postcode":"41008",
    "sg:province":"Sevilla",
    "wof:name":"Remle S.a.",
    "wof:placetype":"venue"
},
  "geometry": {"coordinates":[-5.9653701782,37.4017372131],"type":"Point"}
}