{
  "type": "Feature",
  "properties": {
    "iso:country":"ES",
    "sg:address":"Calle de Pareja, General, 10",
    "sg:city":"Melilla",
    "sg:orig_category":"Panader\u00cdas, Panader\u00cdas",
    "sg:phone":"+34 952 68 17 11",
    "sg:postcode":"52001",
    "sg:province":"Melilla",
    "wof:name":"Montero Diaz Antonia",
    "wof:placetype":"venue"
},
  "geometry": {"coordinates":[-2.9413130283,35.2937355042],"type":"Point"}
}