{
  "type": "Feature",
  "properties": {
    "iso:country":"ES",
    "sg:address":"Carr Argenteria, 25",
    "sg:city":"Girona",
    "sg:orig_category":"Panader\u00cdas, Panader\u00cdas",
    "sg:phone":"+34 972 20 17 87",
    "sg:postcode":"17004",
    "sg:province":"Girona",
    "wof:name":"Faure Rura Tomas",
    "wof:placetype":"venue"
},
  "geometry": {"coordinates":[2.8245611191,41.9852333069],"type":"Point"}
}