{
  "type": "Feature",
  "properties": {
    "iso:country":"ES",
    "sg:address":"Avgd Juan Ramon Jimenez, 17",
    "sg:city":"Barri De Porta",
    "sg:orig_category":"Molduras, Junquillos, Listones Y Molduras Perforadas",
    "sg:phone":"+34 961 54 70 40",
    "sg:postcode":"46930",
    "sg:province":"Valencia",
    "wof:name":"Bar Ximo S.l.",
    "wof:placetype":"venue"
},
  "geometry": {"coordinates":[-0.4419890046,39.482711792],"type":"Point"}
}