{
  "type": "Feature",
  "properties": {
    "addr:full":"Carr Verge Del Remei (de La), 53 Albaida Valencia 46860",
    "addr:housenumber":"53",
    "addr:postcode":"46860",
    "addr:street":"Carr Verge Del Remei De La",
    "iso:country":"ES",
    "sg:address":"Carr Verge Del Remei (de La), 53",
    "sg:city":"Albaida",
    "sg:orig_category":"Sociedades, Compa\u00d1\u00cdas Aseguradoras",
    "sg:phone":"+34 962 90 06 91",
    "sg:postcode":"46860",
    "sg:province":"Valencia",
    "wof:name":"Mapfre Servicios De Informatica",
    "wof:placetype":"venue"
},
  "geometry": {"coordinates":[-0.5183359981,38.8379096985],"type":"Point"}
}