{
  "type": "Feature",
  "properties": {
    "addr:full":"Pase Colon, 5 Foz Lugo 27780",
    "addr:housenumber":"5",
    "addr:postcode":"27780",
    "addr:street":"Colon",
    "iso:country":"ES",
    "sg:address":"Pase Colon, 5",
    "sg:city":"Foz",
    "sg:orig_category":"Quincaller\u00cda (al Por Menor)",
    "sg:phone":"+34 982 14 01 03",
    "sg:postcode":"27780",
    "sg:province":"Lugo",
    "wof:name":"Almacenes Bahia S.l.",
    "wof:placetype":"venue"
},
  "geometry": {"coordinates":[-7.2505059242,43.5719680786],"type":"Point"}
}