{
  "type": "Feature",
  "properties": {
    "iso:country":"ES",
    "sg:address":"Soutelo De Arriba, S/n",
    "sg:city":"Soutelo De Arriba",
    "sg:orig_category":"Asociaciones Y Clubs Deportivos",
    "sg:phone":"+34 986 53 00 05",
    "sg:postcode":"36656",
    "sg:province":"Pontevedra",
    "wof:name":"Pi\u00f1eiro Sport S.l.",
    "wof:placetype":"venue"
},
  "geometry": {"coordinates":[-8.8089036942,42.5329551697],"type":"Point"}
}