{
  "type": "Feature",
  "properties": {
    "addr:full":"Carr Senyera (la), 27 Picanya Valencia 46210",
    "addr:housenumber":"27",
    "addr:postcode":"46210",
    "addr:street":"Carr Senyera La",
    "iso:country":"ES",
    "sg:address":"Carr Senyera (la), 27",
    "sg:city":"Picanya",
    "sg:orig_category":"Electricidad Veh\u00cdculo",
    "sg:phone":"+34 961 59 21 98",
    "sg:postcode":"46210",
    "sg:province":"Valencia",
    "wof:name":"Gomez Berlanga Jose",
    "wof:placetype":"venue"
},
  "geometry": {"coordinates":[-0.4321230054,39.4342460632],"type":"Point"}
}