{
  "type": "Feature",
  "properties": {
    "addr:full":"Santa Maria, S/n Covanera Burgos 09143",
    "addr:postcode":"09143",
    "addr:street":"Santa Maria S / N Covanera",
    "iso:country":"ES",
    "sg:address":"Santa Maria, S/n",
    "sg:city":"Covanera",
    "sg:orig_category":"Estudios Y Construcci\u00d3n De Acuarios Y Viveros",
    "sg:phone":"+34 947 15 00 51",
    "sg:postcode":"09143",
    "sg:province":"Burgos",
    "wof:name":"Peykov Todorov Ivan",
    "wof:placetype":"venue"
},
  "geometry": {"coordinates":[-3.8199799061,42.7097816467],"type":"Point"}
}