{
  "type": "Feature",
  "properties": {
    "addr:full":"Pase Salon (del), 3 Palencia Palencia 34002",
    "addr:postcode":"34002",
    "iso:country":"ES",
    "sg:address":"Pase Salon (del), 3",
    "sg:city":"Palencia",
    "sg:orig_category":"Procuradores",
    "sg:phone":"+34 979 75 18 74",
    "sg:postcode":"34002",
    "sg:province":"Palencia",
    "wof:name":"Arias Berrioategortua Maria",
    "wof:placetype":"venue"
},
  "geometry": {"coordinates":[-4.5302505493,42.0060653687],"type":"Point"}
}