{
  "type": "Feature",
  "properties": {
    "iso:country":"ES",
    "sg:address":"Av Joan Miro, 325",
    "sg:city":"Sant Agusti",
    "sg:orig_category":"Deportes Diversos",
    "sg:phone":"+34 971 70 20 88",
    "sg:postcode":"07015",
    "sg:province":"Islas Baleares",
    "wof:name":"Federacion Balear De Pesca",
    "wof:placetype":"venue"
},
  "geometry": {"coordinates":[2.5990569592,39.5504760742],"type":"Point"}
}