{
  "type": "Feature",
  "properties": {
    "addr:full":"Crta Isla Menor (p I Fuente Del Rey), Km. 0000,5 Dos Hermanas Sevilla 41700",
    "addr:postcode":"41700",
    "addr:street":"Crta Isla Menor P;Rey Km. 0000,5;Sevilla",
    "iso:country":"ES",
    "sg:address":"Crta Isla Menor (p I Fuente Del Rey), Km. 0000,5",
    "sg:city":"Dos Hermanas",
    "sg:orig_category":"Tintes (fabricaci\u00d3n, Al Por Mayor)",
    "sg:phone":"+34 954 69 32 22",
    "sg:postcode":"41700",
    "sg:province":"Sevilla",
    "wof:name":"Sun Chemical S.a.",
    "wof:placetype":"venue"
},
  "geometry": {"coordinates":[-5.9281339645,37.2829055786],"type":"Point"}
}