{
  "type": "Feature",
  "properties": {
    "iso:country":"ES",
    "sg:address":"Calle de Alto Del Leon, 12",
    "sg:city":"Madrid",
    "sg:orig_category":"Cajas De Ahorro",
    "sg:phone":"+34 913 28 14 12",
    "sg:postcode":"28038",
    "sg:province":"Madrid",
    "wof:name":"Caja De Avila",
    "wof:placetype":"venue"
},
  "geometry": {"coordinates":[-3.658321619,40.3993682861],"type":"Point"}
}