{
  "type": "Feature",
  "properties": {
    "iso:country":"ES",
    "sg:address":"Conj. Resid. Carihuela-playa, 61",
    "sg:city":"Torremolinos",
    "sg:orig_category":"Art\u00cdculos De Decoraci\u00d3n",
    "sg:phone":"+34 952 05 21 40",
    "sg:postcode":"29620",
    "sg:province":"M\u00e1laga",
    "wof:name":"Andycraft S.l.",
    "wof:placetype":"venue"
},
  "geometry": {"coordinates":[-4.5160393715,36.6265563965],"type":"Point"}
}