{
  "type": "Feature",
  "properties": {
    "iso:country":"ES",
    "sg:address":"Calle de Tablas, 16",
    "sg:city":"Granada",
    "sg:orig_category":"Agentes De Seguros",
    "sg:phone":"+34 958 26 55 10",
    "sg:postcode":"18002",
    "sg:province":"Granada",
    "wof:name":"Domingo Mir S.l.",
    "wof:placetype":"venue"
},
  "geometry": {"coordinates":[-3.6037321091,37.1758880615],"type":"Point"}
}