{
  "type": "Feature",
  "properties": {
    "iso:country":"ES",
    "sg:address":"Calle de Claudio Temprano, 16",
    "sg:city":"Moraleja",
    "sg:orig_category":"Producci\u00d3n, Distribuci\u00d3n De Gas Butano Y Propano",
    "sg:phone":"+34 927 14 73 98",
    "sg:postcode":"10840",
    "sg:province":"C\u00e1ceres",
    "wof:name":"Olivera Butano S.l.",
    "wof:placetype":"venue"
},
  "geometry": {"coordinates":[-6.6619582176,40.0670394897],"type":"Point"}
}