{
  "type": "Feature",
  "properties": {
    "addr:full":"Carrer de Sant Rafel, 11 Olot Girona 17800",
    "addr:housenumber":"11",
    "addr:postcode":"17800",
    "addr:street":"Carrer De Sant Rafel",
    "iso:country":"ES",
    "sg:address":"Carrer de Sant Rafel, 11",
    "sg:city":"Olot",
    "sg:orig_category":"Ropa Para Se\u00d1oras Y Caballeros (al Por Menor)",
    "sg:phone":"+34 972 26 11 61",
    "sg:postcode":"17800",
    "sg:province":"Girona",
    "wof:name":"Font Home-dona S.l.",
    "wof:placetype":"venue"
},
  "geometry": {"coordinates":[2.4875090122,42.1817054749],"type":"Point"}
}