{
  "type": "Feature",
  "properties": {
    "addr:full":"Avda Fronteras, 15 Torrejon Ardoz Madrid 28850",
    "addr:housenumber":"15",
    "addr:postcode":"28850",
    "addr:street":"Avda Fronteras",
    "iso:country":"ES",
    "sg:address":"Avda Fronteras, 15",
    "sg:city":"Torrejon Ardoz",
    "sg:orig_category":"Frutas, Legumbres Frescas Y Tempranas (al Por Menor)",
    "sg:phone":"+34 916 75 19 34",
    "sg:postcode":"28850",
    "sg:province":"Madrid",
    "wof:name":"Frutas Mary Luz S.l.",
    "wof:placetype":"venue"
},
  "geometry": {"coordinates":[-3.4837710857,40.4598846436],"type":"Point"}
}