{
  "type": "Feature",
  "properties": {
    "iso:country":"ES",
    "sg:address":"Calle de Vi\u00d1as (las), 52",
    "sg:city":"Santurtzi",
    "sg:orig_category":"Peluquer\u00cdas, Peluquer\u00cda Mixta",
    "sg:phone":"+34 944 83 19 17",
    "sg:postcode":"48980",
    "sg:province":"Vizcaya",
    "wof:name":"Peluqueria Estibaliz",
    "wof:placetype":"venue"
},
  "geometry": {"coordinates":[-3.0391829014,43.329460144],"type":"Point"}
}