{
  "type": "Feature",
  "properties": {
    "addr:full":"Pase Florida, S/n Madrid Madrid 28008",
    "addr:housenumber":"s / n",
    "addr:postcode":"28008",
    "iso:country":"ES",
    "sg:address":"Pase Florida, S/n",
    "sg:city":"Madrid",
    "sg:orig_category":"Aparcamientos (infraestructuras, Accesorios)",
    "sg:phone":"+34 917 58 01 00",
    "sg:postcode":"28008",
    "sg:province":"Madrid",
    "wof:name":"Principe Pio Gestion S.a.",
    "wof:placetype":"venue"
},
  "geometry": {"coordinates":[-3.7212738991,40.4230766296],"type":"Point"}
}