{
  "type": "Feature",
  "properties": {
    "addr:full":"Avda Infantes De Lara, 15 Salas De Los Infantes Burgos 09600",
    "addr:housenumber":"15",
    "addr:postcode":"09600",
    "addr:street":"Avda Infantes De Lara",
    "iso:country":"ES",
    "sg:address":"Avda Infantes De Lara, 15",
    "sg:city":"Salas De Los Infantes",
    "sg:orig_category":"Molduras, Junquillos, Listones Y Molduras Perforadas",
    "sg:phone":"+34 947 38 07 95",
    "sg:postcode":"09600",
    "sg:province":"Burgos",
    "wof:name":"Perez Moreno Jesus",
    "wof:placetype":"venue"
},
  "geometry": {"coordinates":[-3.2865879536,42.0223388672],"type":"Point"}
}