{
  "type": "Feature",
  "properties": {
    "addr:full":"Calle de Pamplona, 2 Villafranca Navarra 31330",
    "addr:housenumber":"2",
    "addr:postcode":"31330",
    "addr:street":"Calle De Pamplona",
    "iso:country":"ES",
    "sg:address":"Calle de Pamplona, 2",
    "sg:city":"Villafranca",
    "sg:orig_category":"Promotores Constructores",
    "sg:phone":"+34 948 84 53 04",
    "sg:postcode":"31330",
    "sg:province":"Navarra",
    "wof:name":"Construcciones Hermanos B.mu\u00f1oz S.l.",
    "wof:placetype":"venue"
},
  "geometry": {"coordinates":[-1.7453629971,42.2785758972],"type":"Point"}
}