{
  "type": "Feature",
  "properties": {
    "iso:country":"ES",
    "sg:address":"Calle de Buensuceso, 42",
    "sg:city":"Granada",
    "sg:orig_category":"Promotores Constructores",
    "sg:phone":"+34 958 26 25 91",
    "sg:postcode":"18002",
    "sg:province":"Granada",
    "wof:name":"Inmobiliaria Emilio Castro E Hijos S.a.",
    "wof:placetype":"venue"
},
  "geometry": {"coordinates":[-3.6050670147,37.1741371155],"type":"Point"}
}