{
  "type": "Feature",
  "properties": {
    "addr:full":"Avda San Adrian, 5 Bilbao Vizcaya 48003",
    "addr:housenumber":"5",
    "addr:postcode":"48003",
    "addr:street":"Avda San Adrian",
    "iso:country":"ES",
    "sg:address":"Avda San Adrian, 5",
    "sg:city":"Bilbao",
    "sg:orig_category":"Centros De Coordinaci\u00d3n",
    "sg:phone":"+34 944 21 11 47",
    "sg:postcode":"48003",
    "sg:province":"Vizcaya",
    "wof:name":"Jose Maria Varona Y Otra C.b.",
    "wof:placetype":"venue"
},
  "geometry": {"coordinates":[-2.9300079346,43.2463378906],"type":"Point"}
}