{
  "type": "Feature",
  "properties": {
    "addr:full":"Avda Abilio Calderon, 19 Due\u00f1as Palencia 34210",
    "addr:housenumber":"19",
    "addr:postcode":"34210",
    "addr:street":"Avda Abilio Calderon",
    "iso:country":"ES",
    "sg:address":"Avda Abilio Calderon, 19",
    "sg:city":"Due\u00f1as",
    "sg:orig_category":"Supermercados Y Hipermercados",
    "sg:phone":"+34 979 78 07 57",
    "sg:postcode":"34210",
    "sg:province":"Palencia",
    "wof:name":"Gelibel S.l.",
    "wof:placetype":"venue"
},
  "geometry": {"coordinates":[-4.5456790924,41.8751182556],"type":"Point"}
}