{
  "type": "Feature",
  "properties": {
    "iso:country":"ES",
    "sg:address":"Pase Fernandez Vallejo, 124",
    "sg:city":"Tanos",
    "sg:classifiers":[
        {
            "category":"Recreation",
            "type":"Entertainment"
        }
    ],
    "sg:phone":"+34 942 80 79 56",
    "sg:postcode":"39316",
    "sg:province":"Cantabria",
    "sg:tags":[
        "caza",
        "pr\u00c1ctica",
        "la",
        "de",
        "pesca",
        "y"
    ],
    "wof:name":"Sociedad De Caza La Bosca",
    "wof:placetype":"venue"
},
  "geometry": {"coordinates":[-4.044960022,43.3367385864],"type":"Point"}
}