{
  "type": "Feature",
  "properties": {
    "iso:country":"ES",
    "sg:address":"Avda Santa Marina, 265",
    "sg:city":"Alza",
    "sg:orig_category":"Transportes Por V\u00cdas Navegables",
    "sg:phone":"+34 986 48 80 31",
    "sg:postcode":"36318",
    "sg:province":"Pontevedra",
    "wof:name":"Alonso Doural Julio",
    "wof:placetype":"venue"
},
  "geometry": {"coordinates":[-8.6480531693,42.4336204529],"type":"Point"}
}