{
  "type": "Feature",
  "properties": {
    "iso:country":"ES",
    "sg:address":"Cra. Blanes (platja Fanals), 99",
    "sg:city":"Lloret Mar",
    "sg:orig_category":"Regalos, Souvenires (fabricaci\u00d3n, Al Por Mayor)",
    "sg:phone":"+34 972 37 00 13",
    "sg:postcode":"17310",
    "sg:province":"Girona",
    "wof:name":"Tarachandani  Priya",
    "wof:placetype":"venue"
},
  "geometry": {"coordinates":[2.846834898,41.6981697083],"type":"Point"}
}