{
  "type": "Feature",
  "properties": {
    "iso:country":"ES",
    "sg:address":"Rbla Bobiles, 16",
    "sg:city":"Martorell",
    "sg:orig_category":"Cajas De Ahorro",
    "sg:phone":"+34 937 75 27 68",
    "sg:postcode":"08760",
    "sg:province":"Barcelona",
    "wof:name":"Caixa De Girona",
    "wof:placetype":"venue"
},
  "geometry": {"coordinates":[1.9169800282,41.4771957397],"type":"Point"}
}