{
  "type": "Feature",
  "properties": {
    "addr:full":"Carrer de Licoristes, 26 Valls Tarragona 43800",
    "addr:housenumber":"26",
    "addr:postcode":"43800",
    "addr:street":"Carrer De Licoristes",
    "iso:country":"ES",
    "sg:address":"Carrer de Licoristes, 26",
    "sg:city":"Valls",
    "sg:orig_category":"Cr\u00cda De Cerdos",
    "sg:phone":"+34 977 61 28 16",
    "sg:postcode":"43800",
    "sg:province":"Tarragona",
    "wof:name":"Escorxador Frigorific Alt Camp S.l.",
    "wof:placetype":"venue"
},
  "geometry": {"coordinates":[1.2717380524,41.3125610352],"type":"Point"}
}