{
  "type": "Feature",
  "properties": {
    "addr:full":"Calle de Mendez Nu\u00d1ez, 2 Jerez De La Frontera C\u00e1diz 11401",
    "addr:housenumber":"2",
    "addr:postcode":"11401",
    "addr:street":"Calle De Mendez Nun\u0303Ez",
    "iso:country":"ES",
    "sg:address":"Calle de Mendez Nu\u00d1ez, 2",
    "sg:city":"Jerez De La Frontera",
    "sg:orig_category":"Organizaciones Internacionales",
    "sg:phone":"+34 956 32 38 26",
    "sg:postcode":"11401",
    "sg:province":"C\u00e1diz",
    "wof:name":"Asociacion Madre Coraje",
    "wof:placetype":"venue"
},
  "geometry": {"coordinates":[-6.1273040771,36.6789512634],"type":"Point"}
}