{
  "type": "Feature",
  "properties": {
    "iso:country":"ES",
    "sg:address":"Calle de Don Ramon De La Cruz, 31",
    "sg:city":"Madrid",
    "sg:orig_category":"Centros De Salud",
    "sg:phone":"+34 914 31 40 43",
    "sg:postcode":"28001",
    "sg:province":"Madrid",
    "sg:website":"www.o2centrowellness.com",
    "wof:name":"O2 Centro Wellness S.l.",
    "wof:placetype":"venue"
},
  "geometry": {"coordinates":[-3.6819844246,40.4290390015],"type":"Point"}
}