{
  "type": "Feature",
  "properties": {
    "iso:country":"ES",
    "sg:address":"Pseo. Constitucion, 24",
    "sg:city":"Almaraz",
    "sg:orig_category":"Supermercados Y Hipermercados",
    "sg:phone":"+34 927 54 51 55",
    "sg:postcode":"10350",
    "sg:province":"C\u00e1ceres",
    "wof:name":"Horno San Roque De Almaraz S.l.",
    "wof:placetype":"venue"
},
  "geometry": {"coordinates":[-5.6773509979,39.7912712097],"type":"Point"}
}