{
  "type": "Feature",
  "properties": {
    "iso:country":"ES",
    "sg:address":"Calle de San Antonio (de), 80",
    "sg:city":"Aranjuez",
    "sg:orig_category":"Lencer\u00cda Femenina, Corseter\u00cda, Trajes De Ba\u00d1o (al Por Menor)",
    "sg:phone":"+34 918 91 03 67",
    "sg:postcode":"28300",
    "sg:province":"Madrid",
    "wof:name":"Almacenes Toledo S.l.",
    "wof:placetype":"venue"
},
  "geometry": {"coordinates":[-3.6030113697,40.0334434509],"type":"Point"}
}