{
  "type": "Feature",
  "properties": {
    "addr:full":"Av. B. Navarra, 41 Iru\u00f1a Navarra 31002",
    "addr:housenumber":"41",
    "addr:postcode":"31002",
    "addr:street":"Av. B. Navarra",
    "iso:country":"ES",
    "sg:address":"Av. B. Navarra, 41",
    "sg:city":"Iru\u00f1a",
    "sg:orig_category":"Asesor\u00cda Sobre Comunicaci\u00d3n De Empresas",
    "sg:phone":"+34 948 21 35 43",
    "sg:postcode":"31002",
    "sg:province":"Navarra",
    "wof:name":"Gortari Garcia Luis Antonio",
    "wof:placetype":"venue"
},
  "geometry": {"coordinates":[-1.6331199408,42.8139648438],"type":"Point"}
}