{
  "type": "Feature",
  "properties": {
    "iso:country":"ES",
    "sg:address":"Calle de Badajoz, 73",
    "sg:city":"Santa Marta",
    "sg:classifiers":[
        {
            "category":"Personal",
            "subcategory":"Barber",
            "type":"Services"
        }
    ],
    "sg:phone":"+34 924 68 12 98",
    "sg:postcode":"06150",
    "sg:province":"Badajoz",
    "sg:tags":[
        "caballeros",
        "de",
        "peluqueros"
    ],
    "wof:name":"Rodriguez Murillo Jose",
    "wof:placetype":"venue"
},
  "geometry": {"coordinates":[-6.6324548721,38.6075286865],"type":"Point"}
}