{
  "type": "Feature",
  "properties": {
    "iso:country":"ES",
    "sg:address":"Pg Fabra I Puig, 480",
    "sg:city":"Barcelona",
    "sg:orig_category":"Maquinaria Para Industrias Diversas",
    "sg:phone":"+34 932 74 90 67",
    "sg:postcode":"08042",
    "sg:province":"Barcelona",
    "wof:name":"Mu\u00f1oz Valentin Francisco",
    "wof:placetype":"venue"
},
  "geometry": {"coordinates":[2.1661059856,41.4385643005],"type":"Point"}
}