{
  "type": "Feature",
  "properties": {
    "iso:country":"ES",
    "sg:address":"Carrer de Creus, 37",
    "sg:city":"Calella",
    "sg:orig_category":"Comerciantes Al Por Mayor De Vinos, Licores Y Alcoholes",
    "sg:phone":"+34 937 69 06 59",
    "sg:postcode":"08370",
    "sg:province":"Barcelona",
    "wof:name":"Sanchez Azor Joaquim",
    "wof:placetype":"venue"
},
  "geometry": {"coordinates":[2.6595458984,41.6135635376],"type":"Point"}
}