{
  "type": "Feature",
  "properties": {
    "iso:country":"ES",
    "sg:address":"Calle de Miguel Mayor, 3",
    "sg:city":"Madrid",
    "sg:orig_category":"Fabricaci\u00d3n, Venta De Cuadros, Accesorios Para Enmarcar",
    "sg:phone":"+34 915 65 51 87",
    "sg:postcode":"28019",
    "sg:province":"Madrid",
    "sg:website":"www.enmarcados.net",
    "wof:name":"Dise\u00f1os A-cu\u00f1a S.l.l.",
    "wof:placetype":"venue"
},
  "geometry": {"coordinates":[-3.7182381153,40.3891143799],"type":"Point"}
}