{
  "type": "Feature",
  "properties": {
    "iso:country":"ES",
    "sg:address":"Calle de Carteros (los), 98",
    "sg:city":"San Jose Rinconada",
    "sg:orig_category":"Internados & Ense\u00d1anza Privada",
    "sg:phone":"+34 954 79 00 40",
    "sg:postcode":"41300",
    "sg:province":"Sevilla",
    "wof:name":"Colegio Hermanas Doctrina Cristiana",
    "wof:placetype":"venue"
},
  "geometry": {"coordinates":[-5.9458184242,37.4798736572],"type":"Point"}
}