{
  "type": "Feature",
  "properties": {
    "addr:full":"Bo Carbonaire, 2 Vall Uixo Castell\u00f3n 12600",
    "addr:housenumber":"2",
    "addr:postcode":"12600",
    "addr:street":"Carbonaire;Castello\u0301N",
    "iso:country":"ES",
    "sg:address":"Bo Carbonaire, 2",
    "sg:city":"Vall Uixo",
    "sg:orig_category":"Fabricaci\u00d3n, Instalaci\u00d3n Y Reparaci\u00d3n De Bombas",
    "sg:phone":"+34 964 69 08 69",
    "sg:postcode":"12600",
    "sg:province":"Castell\u00f3n",
    "wof:name":"Serrano Picon Jose",
    "wof:placetype":"venue"
},
  "geometry": {"coordinates":[-0.2367690057,39.8276329041],"type":"Point"}
}