{
  "type": "Feature",
  "properties": {
    "addr:full":"Calle de Hermanos Garcia Noblejas, 39 Madrid Madrid 28037",
    "addr:housenumber":"39",
    "addr:postcode":"madrid;28037",
    "addr:street":"Calle De Hermanos Garcia Noblejas",
    "iso:country":"ES",
    "sg:address":"Calle de Hermanos Garcia Noblejas, 39",
    "sg:city":"Madrid",
    "sg:orig_category":"Diarios, Revistas Y Boletines (distribuidores)",
    "sg:phone":"+34 914 06 69 90",
    "sg:postcode":"28037",
    "sg:province":"Madrid",
    "wof:name":"Ediciones Muestras Y Motivos S.a.",
    "wof:placetype":"venue"
},
  "geometry": {"coordinates":[-3.6333940029,40.4318618774],"type":"Point"}
}