{
  "type": "Feature",
  "properties": {
    "addr:full":"Calle de Olaguibel, 50 Vitoria-gasteiz \u00c1lava 01003",
    "addr:housenumber":"50",
    "addr:postcode":"01003",
    "addr:street":"Calle De Olaguibel",
    "iso:country":"ES",
    "sg:address":"Calle de Olaguibel, 50",
    "sg:city":"Vitoria-gasteiz",
    "sg:orig_category":"Cl\u00cdnicas M\u00c9dicas",
    "sg:phone":"+34 945 28 36 86",
    "sg:postcode":"01003",
    "sg:province":"\u00c1lava",
    "wof:name":"Alba Villota Miguel Angel",
    "wof:placetype":"venue"
},
  "geometry": {"coordinates":[-2.6647188663,42.8456764221],"type":"Point"}
}