{
  "type": "Feature",
  "properties": {
    "addr:full":"Cra Mata (de), Km. 0003,7 Mataro Barcelona 08304",
    "addr:postcode":"08304",
    "addr:street":"0003,7;Barcelona",
    "iso:country":"ES",
    "sg:address":"Cra Mata (de), Km. 0003,7",
    "sg:city":"Mataro",
    "sg:orig_category":"Inversiones",
    "sg:phone":"+34 937 96 24 19",
    "sg:postcode":"08304",
    "sg:province":"Barcelona",
    "wof:name":"Comas Planas Y Cia Src",
    "wof:placetype":"venue"
},
  "geometry": {"coordinates":[2.4567639828,41.5536956787],"type":"Point"}
}