{
  "type": "Feature",
  "properties": {
    "iso:country":"ES",
    "sg:address":"Calle de Alcora, S/n",
    "sg:city":"Poligono Industrial",
    "sg:orig_category":"Cer\u00c1micas: Material Y Suministros",
    "sg:phone":"+34 964 50 75 00",
    "sg:postcode":"12550",
    "sg:province":"Castell\u00f3n",
    "sg:website":"www.pamesa.com",
    "wof:name":"Pamesa Ceramica S.l.",
    "wof:placetype":"venue"
},
  "geometry": {"coordinates":[-0.0360242017,39.9860687256],"type":"Point"}
}