{
  "type": "Feature",
  "properties": {
    "addr:full":"Sanguesa, 35 Iru\u00f1a Navarra 31005",
    "addr:housenumber":"35",
    "addr:postcode":"31005",
    "addr:street":"Sanguesa",
    "iso:country":"ES",
    "sg:address":"Sanguesa, 35",
    "sg:city":"Iru\u00f1a",
    "sg:orig_category":"Electricidad: Instaladores",
    "sg:phone":"+34 948 24 13 31",
    "sg:postcode":"31005",
    "sg:province":"Navarra",
    "wof:name":"Sabico Seguridad S.a.",
    "wof:placetype":"venue"
},
  "geometry": {"coordinates":[-1.6412169933,42.8064994812],"type":"Point"}
}