{
  "type": "Feature",
  "properties": {
    "iso:country":"ES",
    "sg:address":"C/ Mare De Deu De Montserrat, 36",
    "sg:city":"Inca",
    "sg:orig_category":"Ropa Para Caballeros (al Por Menor)",
    "sg:phone":"+34 971 50 23 32",
    "sg:postcode":"07300",
    "sg:province":"Islas Baleares",
    "wof:name":"Prat Segui Bartolome",
    "wof:placetype":"venue"
},
  "geometry": {"coordinates":[2.9131131172,39.7163276672],"type":"Point"}
}