{
  "type": "Feature",
  "properties": {
    "addr:full":"Carrer de Francesc Puget, 53 Manlleu Barcelona 08560",
    "addr:housenumber":"53",
    "addr:postcode":"08560",
    "addr:street":"Carrer De Francesc Puget",
    "iso:country":"ES",
    "sg:address":"Carrer de Francesc Puget, 53",
    "sg:city":"Manlleu",
    "sg:orig_category":"M\u00c1quinas Y Material Para La Industria De La Alimentaci\u00d3n",
    "sg:phone":"+34 938 50 63 87",
    "sg:postcode":"08560",
    "sg:province":"Barcelona",
    "sg:website":"www.jejorman.com",
    "wof:name":"J.e.jorman S.l.",
    "wof:placetype":"venue"
},
  "geometry": {"coordinates":[2.2844099998,42.0036239624],"type":"Point"}
}