{
  "type": "Feature",
  "properties": {
    "addr:full":"Carrer de Miquel Servet, 50 Roquetes Barcelona 08812",
    "addr:housenumber":"50",
    "addr:postcode":"08812",
    "addr:street":"Carrer De Miquel Servet",
    "iso:country":"ES",
    "sg:address":"Carrer de Miquel Servet, 50",
    "sg:city":"Roquetes",
    "sg:orig_category":"Mudanzas",
    "sg:phone":"+34 938 93 53 41",
    "sg:postcode":"08812",
    "sg:province":"Barcelona",
    "wof:name":"Carulla Puy Miguel",
    "wof:placetype":"venue"
},
  "geometry": {"coordinates":[1.7477229834,41.2274093628],"type":"Point"}
}