{
  "type": "Feature",
  "properties": {
    "addr:full":"Avda Independencia, 19 Zaragoza Zaragoza 50001",
    "addr:housenumber":"19",
    "addr:postcode":"50001",
    "addr:street":"Avda Independencia",
    "iso:country":"ES",
    "sg:address":"Avda Independencia, 19",
    "sg:city":"Zaragoza",
    "sg:orig_category":"Inmobiliaria (agencias)",
    "sg:phone":"+34 976 22 78 02",
    "sg:postcode":"50001",
    "sg:province":"Zaragoza",
    "wof:name":"Xaron S.a.",
    "wof:placetype":"venue"
},
  "geometry": {"coordinates":[-0.8812869787,41.6516609192],"type":"Point"}
}