{
  "type": "Feature",
  "properties": {
    "iso:country":"ES",
    "sg:address":"Calle de Arzubia, S/n",
    "sg:city":"Tra\u00e7a-matiena",
    "sg:orig_category":"Imprenta",
    "sg:phone":"+34 946 23 27 03",
    "sg:postcode":"48220",
    "sg:province":"Vizcaya",
    "wof:name":"Imprenta Abadi\u00f1o S.l.l.",
    "wof:placetype":"venue"
},
  "geometry": {"coordinates":[-2.6983869076,43.2204284668],"type":"Point"}
}