{
  "type": "Feature",
  "properties": {
    "iso:country":"ES",
    "sg:address":"Monte De Meda, S/n",
    "sg:city":"Monte Meda",
    "sg:orig_category":"Distribuci\u00d3n De Petr\u00d3leo Y Derivados",
    "sg:phone":"+34 982 22 54 08",
    "sg:postcode":"27210",
    "sg:province":"Lugo",
    "wof:name":"El Picato S.l.",
    "wof:placetype":"venue"
},
  "geometry": {"coordinates":[-7.6614279747,42.9045219421],"type":"Point"}
}