{
  "type": "Feature",
  "properties": {
    "addr:full":"Carrer de General Alvarez De Castr, 10 Barcelona Barcelona 08003",
    "addr:housenumber":"10",
    "addr:postcode":"08003",
    "addr:street":"Carrer De General Alvarez De Castr",
    "iso:country":"ES",
    "sg:address":"Carrer de General Alvarez De Castr, 10",
    "sg:city":"Barcelona",
    "sg:orig_category":"Agricultura: Abastecimiento Y Cosechado (negocio)",
    "sg:phone":"+34 933 10 58 89",
    "sg:postcode":"08003",
    "sg:province":"Barcelona",
    "wof:name":"O\u00f1ate Martinez Juan Pedro",
    "wof:placetype":"venue"
},
  "geometry": {"coordinates":[2.1776928902,41.3872108459],"type":"Point"}
}