{
  "type": "Feature",
  "properties": {
    "iso:country":"ES",
    "sg:address":"Calle de Doctor Jimenez Diaz, 4",
    "sg:city":"Sevilla",
    "sg:orig_category":"Molduras, Junquillos, Listones Y Molduras Perforadas",
    "sg:phone":"+34 954 35 40 81",
    "sg:postcode":"41008",
    "sg:province":"Sevilla",
    "wof:name":"Pertel S.cv.",
    "wof:placetype":"venue"
},
  "geometry": {"coordinates":[-5.9807915688,37.4038391113],"type":"Point"}
}