{
  "type": "Feature",
  "properties": {
    "addr:full":"Estd Vilanova (de), 21 Celanova Ourense 32800",
    "addr:postcode":"32800",
    "iso:country":"ES",
    "sg:address":"Estd Vilanova (de), 21",
    "sg:city":"Celanova",
    "sg:orig_category":"Mec\u00c1nico Del Autom\u00d3vil",
    "sg:phone":"+34 988 45 11 90",
    "sg:postcode":"32800",
    "sg:province":"Ourense",
    "wof:name":"Rodriguez Lopez Emilio",
    "wof:placetype":"venue"
},
  "geometry": {"coordinates":[-7.8338680267,42.6394233704],"type":"Point"}
}