{
  "type": "Feature",
  "properties": {
    "iso:country":"ES",
    "sg:address":"Avda Extremadura, 14",
    "sg:city":"Zarza",
    "sg:orig_category":"Contenedores (mercanc\u00cdas)",
    "sg:phone":"+34 924 36 63 03",
    "sg:postcode":"06830",
    "sg:province":"Badajoz",
    "wof:name":"Megias Cerrato Martin",
    "wof:placetype":"venue"
},
  "geometry": {"coordinates":[-6.2255878448,38.8160896301],"type":"Point"}
}