{
  "type": "Feature",
  "properties": {
    "addr:full":"Carrer de Major, 11 Cunit Tarragona 43881",
    "addr:housenumber":"11",
    "addr:postcode":"43881",
    "addr:street":"Carrer De Major",
    "iso:country":"ES",
    "sg:address":"Carrer de Major, 11",
    "sg:city":"Cunit",
    "sg:orig_category":"Inmobiliaria (agencias)",
    "sg:phone":"+34 977 67 59 99",
    "sg:postcode":"43881",
    "sg:province":"Tarragona",
    "wof:name":"Inmoplus, S.l.",
    "wof:placetype":"venue"
},
  "geometry": {"coordinates":[1.6352599859,41.1984481812],"type":"Point"}
}