{
  "type": "Feature",
  "properties": {
    "addr:full":"Carr Ballesteries, 19 Girona Girona 17003",
    "addr:housenumber":"19",
    "addr:postcode":"17003",
    "addr:street":"Carr Ballesteries",
    "iso:country":"ES",
    "sg:address":"Carr Ballesteries, 19",
    "sg:city":"Girona",
    "sg:orig_category":"Bazares, Art\u00cdculos De Limpieza Y De Cocina (al Por Menor)",
    "sg:phone":"+34 972 20 79 45",
    "sg:postcode":"17003",
    "sg:province":"Girona",
    "wof:name":"Gruartmoner Barber Conchita",
    "wof:placetype":"venue"
},
  "geometry": {"coordinates":[2.8187448978,41.9808616638],"type":"Point"}
}