{
  "type": "Feature",
  "properties": {
    "addr:full":"Merkatondoa, 1 Estella Navarra 31200",
    "addr:housenumber":"1",
    "addr:postcode":"31200",
    "addr:street":"Merkatondoa",
    "iso:country":"ES",
    "sg:address":"Merkatondoa, 1",
    "sg:city":"Estella",
    "sg:orig_category":"Cristaler\u00cdas",
    "sg:phone":"+34 948 55 44 55",
    "sg:postcode":"31200",
    "sg:province":"Navarra",
    "wof:name":"Perez Barredo Felipe",
    "wof:placetype":"venue"
},
  "geometry": {"coordinates":[-2.0301790237,42.6604194641],"type":"Point"}
}