{
  "type": "Feature",
  "properties": {
    "addr:full":"Calle de Pio V, S/n Orihuela Alicante 03300",
    "addr:housenumber":"/ n",
    "addr:postcode":"03300",
    "addr:street":"Calle De Pio V S",
    "iso:country":"ES",
    "sg:address":"Calle de Pio V, S/n",
    "sg:city":"Orihuela",
    "sg:orig_category":"Promotores Constructores",
    "sg:phone":"+34 966 74 12 28",
    "sg:postcode":"03300",
    "sg:province":"Alicante",
    "wof:name":"Obras Y Construcciones Del Levante S.l",
    "wof:placetype":"venue"
},
  "geometry": {"coordinates":[-0.9397680163,38.0874900818],"type":"Point"}
}