{
  "type": "Feature",
  "properties": {
    "addr:full":"Calle de Ramon Y Cajal, 42 Alberic Valencia 46260",
    "addr:housenumber":"42",
    "addr:postcode":"46260",
    "addr:street":"Calle De Ramon Y Cajal",
    "iso:country":"ES",
    "sg:address":"Calle de Ramon Y Cajal, 42",
    "sg:city":"Alberic",
    "sg:orig_category":"Agencias De Viajes",
    "sg:phone":"+34 962 44 20 55",
    "sg:postcode":"46260",
    "sg:province":"Valencia",
    "wof:name":"Viajes Amazona S.l.",
    "wof:placetype":"venue"
},
  "geometry": {"coordinates":[-0.520129025,39.1186790466],"type":"Point"}
}