{
  "type": "Feature",
  "properties": {
    "iso:country":"ES",
    "sg:address":"Madrid, Km. 0074,3",
    "sg:city":"Valsain",
    "sg:orig_category":"Barbacoas Y Accesorios",
    "sg:phone":"+34 921 47 19 29",
    "sg:postcode":"40109",
    "sg:province":"Segovia",
    "wof:name":"La Casa Del Bosque De Segovia S.l.(meson De Miguel",
    "wof:placetype":"venue"
},
  "geometry": {"coordinates":[-4.0267820358,40.8787117004],"type":"Point"}
}