{
  "type": "Feature",
  "properties": {
    "iso:country":"ES",
    "sg:address":"Calle de Azulares, 34",
    "sg:city":"Carcabuey",
    "sg:orig_category":"Empresas De Desmonte",
    "sg:phone":"+34 957 55 36 67",
    "sg:postcode":"14810",
    "sg:province":"C\u00f3rdoba",
    "wof:name":"Mu\u00f1oz Jurado Antonio",
    "wof:placetype":"venue"
},
  "geometry": {"coordinates":[-4.2789654732,37.4400939941],"type":"Point"}
}