{
  "type": "Feature",
  "properties": {
    "addr:full":"Plaza Gure Zumardia, 2 Pasaia Guip\u00f9zcoa 20110",
    "addr:housenumber":"2",
    "addr:postcode":"20110",
    "addr:street":"Gure Zumardia;Guipu\u0300Zcoa",
    "iso:country":"ES",
    "sg:address":"Plaza Gure Zumardia, 2",
    "sg:city":"Pasaia",
    "sg:orig_category":"Cl\u00cdnicas Dentales",
    "sg:phone":"+34 943 34 40 29",
    "sg:postcode":"20110",
    "sg:province":"Guip\u00f9zcoa",
    "wof:name":"Clinica Dental Pasaia (cristina Iriarte Frias)",
    "wof:placetype":"venue"
},
  "geometry": {"coordinates":[-1.9184139967,43.3176879883],"type":"Point"}
}