{
  "type": "Feature",
  "properties": {
    "addr:full":"Lago, 7 Iru\u00f1a Navarra 31016",
    "addr:housenumber":"7",
    "addr:postcode":"31016",
    "addr:street":"Lago",
    "iso:country":"ES",
    "sg:address":"Lago, 7",
    "sg:city":"Iru\u00f1a",
    "sg:orig_category":"Construcci\u00d3n De Edificios Residenciales Y No Residenciales",
    "sg:phone":"+34 948 31 15 61",
    "sg:postcode":"31016",
    "sg:province":"Navarra",
    "wof:name":"Excavaciones Arizko S.l.",
    "wof:placetype":"venue"
},
  "geometry": {"coordinates":[-1.6154739857,42.8092803955],"type":"Point"}
}