{
  "type": "Feature",
  "properties": {
    "addr:full":"C/ Josep M. Folch I Torres, 22 Tarrega Lleida 25300",
    "addr:housenumber":"22",
    "addr:postcode":"25300",
    "addr:street":"C / Josep M. Folch I Torres",
    "iso:country":"ES",
    "sg:address":"C/ Josep M. Folch I Torres, 22",
    "sg:city":"Tarrega",
    "sg:orig_category":"Producci\u00d3n, Distribuci\u00d3n De Electricidad",
    "sg:phone":"+34 973 50 15 63",
    "sg:postcode":"25300",
    "sg:province":"Lleida",
    "wof:name":"Molina Lopez Jose Maria",
    "wof:placetype":"venue"
},
  "geometry": {"coordinates":[1.1357109547,41.6558227539],"type":"Point"}
}