{
  "type": "Feature",
  "properties": {
    "iso:country":"ES",
    "sg:address":"Calle de Juan Vicente Zengotitabengoa, 2",
    "sg:city":"Berriz-olakueta",
    "sg:orig_category":"Reposter\u00cdas",
    "sg:phone":"+34 946 82 75 55",
    "sg:postcode":"48240",
    "sg:province":"Vizcaya",
    "wof:name":"Fernando Aldalur Maguregui Y Jose Duran Valencia Cdad",
    "wof:placetype":"venue"
},
  "geometry": {"coordinates":[-2.5752739906,43.1697235107],"type":"Point"}
}