{
  "type": "Feature",
  "properties": {
    "addr:full":"Calle de Caleruega, 108 Madrid Madrid 28033",
    "addr:housenumber":"108",
    "addr:postcode":"28033",
    "addr:street":"Calle De Caleruega",
    "iso:country":"ES",
    "sg:address":"Calle de Caleruega, 108",
    "sg:city":"Madrid",
    "sg:orig_category":"Fabricaci\u00d3n, Importaci\u00d3n De Material Y Sistemas De Telecomunicaciones",
    "sg:phone":"+34 913 83 25 25",
    "sg:postcode":"28033",
    "sg:province":"Madrid",
    "wof:name":"Laher Comunicaciones S.a.",
    "wof:placetype":"venue"
},
  "geometry": {"coordinates":[-3.6681344509,40.4821777344],"type":"Point"}
}