{
  "type": "Feature",
  "properties": {
    "iso:country":"ES",
    "sg:address":"Calle de Astorga, 65",
    "sg:city":"Ba\u00d1eza",
    "sg:orig_category":"Ludotecas",
    "sg:phone":"+34 987 65 56 71",
    "sg:postcode":"24750",
    "sg:province":"Le\u00f3n",
    "wof:name":"Osorio Casado Angel Andres",
    "wof:placetype":"venue"
},
  "geometry": {"coordinates":[-5.9004282951,42.3025093079],"type":"Point"}
}