{
  "type": "Feature",
  "properties": {
    "iso:country":"ES",
    "sg:address":"Calle de Tornero, S/n",
    "sg:city":"Cuervo De Sevilla",
    "sg:orig_category":"Negocio De Madera",
    "sg:phone":"+34 955 97 68 18",
    "sg:postcode":"41749",
    "sg:province":"Sevilla",
    "wof:name":"Gordillo Guijo Juan Jose",
    "wof:placetype":"venue"
},
  "geometry": {"coordinates":[-6.0342488289,36.8586540222],"type":"Point"}
}