{
  "type": "Feature",
  "properties": {
    "iso:country":"ES",
    "sg:address":"Calle de Prim, 24",
    "sg:city":"Carmona",
    "sg:orig_category":"Electrodom\u00c9sticos (al Por Menor)",
    "sg:phone":"+34 954 14 01 50",
    "sg:postcode":"41410",
    "sg:province":"Sevilla",
    "wof:name":"Fernandez Manzanar Enrique",
    "wof:placetype":"venue"
},
  "geometry": {"coordinates":[-5.6396069527,37.4715919495],"type":"Point"}
}