{
  "type": "Feature",
  "properties": {
    "addr:full":"Calle de Conde De Gondomar, 13 Cordoba C\u00f3rdoba 14003",
    "addr:housenumber":"13",
    "addr:postcode":"14003",
    "addr:street":"Calle De Conde De Gondomar;Co\u0301Rdoba",
    "iso:country":"ES",
    "sg:address":"Calle de Conde De Gondomar, 13",
    "sg:city":"Cordoba",
    "sg:orig_category":"Ropa Para Se\u00d1oras (al Por Menor)",
    "sg:phone":"+34 957 48 76 13",
    "sg:postcode":"14003",
    "sg:province":"C\u00f3rdoba",
    "sg:website":"www.zara.com",
    "wof:name":"Zara Espa\u00f1a S.a.",
    "wof:placetype":"venue"
},
  "geometry": {"coordinates":[-4.7812957764,37.8845100403],"type":"Point"}
}