{
  "type": "Feature",
  "properties": {
    "iso:country":"ES",
    "sg:address":"Rua San Pedro (de), 73",
    "sg:city":"Santiago De Compostela",
    "sg:orig_category":"Zapatos (al Por Menor)",
    "sg:phone":"+34 981 58 97 23",
    "sg:postcode":"15703",
    "sg:province":"A Coru\u00f1a",
    "wof:name":"Tato Casti\u00f1eiras Jose Maria",
    "wof:placetype":"venue"
},
  "geometry": {"coordinates":[-8.5371398926,42.881565094],"type":"Point"}
}