{
  "type": "Feature",
  "properties": {
    "addr:full":"Avda Galicia De, 25 Piedras Blancas Asturias 33450",
    "addr:housenumber":"25",
    "addr:postcode":"33450",
    "addr:street":"Avda Galicia De",
    "iso:country":"ES",
    "sg:address":"Avda Galicia De, 25",
    "sg:city":"Piedras Blancas",
    "sg:orig_category":"Farmacias",
    "sg:phone":"+34 985 53 23 12",
    "sg:postcode":"33450",
    "sg:province":"Asturias",
    "wof:name":"Martin Alvarez Hortensia",
    "wof:placetype":"venue"
},
  "geometry": {"coordinates":[-5.9806780815,43.5582847595],"type":"Point"}
}