{
  "type": "Feature",
  "properties": {
    "addr:full":"Zalain Auzoa, 17 Bera Navarra 31780",
    "addr:housenumber":"17",
    "addr:postcode":"31780",
    "addr:street":"Zalain Auzoa",
    "iso:country":"ES",
    "sg:address":"Zalain Auzoa, 17",
    "sg:city":"Bera",
    "sg:orig_category":"Fabricaci\u00d3n De Taburetes, Sillas Y Sillones",
    "sg:phone":"+34 948 63 08 01",
    "sg:postcode":"31780",
    "sg:province":"Navarra",
    "wof:name":"J.m.herliz S.l.",
    "wof:placetype":"venue"
},
  "geometry": {"coordinates":[-1.6813839674,43.2808914185],"type":"Point"}
}