{
  "type": "Feature",
  "properties": {
    "addr:full":"Calle de Valderrey, 31 Madrid Madrid 28035",
    "addr:housenumber":"31",
    "addr:postcode":"madrid;28035",
    "addr:street":"Calle De Valderrey",
    "iso:country":"ES",
    "sg:address":"Calle de Valderrey, 31",
    "sg:city":"Madrid",
    "sg:orig_category":"Inmobiliaria (agencias)",
    "sg:phone":"+34 913 73 13 33",
    "sg:postcode":"28035",
    "sg:province":"Madrid",
    "wof:name":"Promax Servicios Integrales S.l.",
    "wof:placetype":"venue"
},
  "geometry": {"coordinates":[-3.7188050747,40.4675178528],"type":"Point"}
}