{
  "type": "Feature",
  "properties": {
    "iso:country":"ES",
    "sg:address":"Avgd President Companys, 45",
    "sg:city":"Badalona",
    "sg:orig_category":"Psic\u00d3logos",
    "sg:phone":"+34 933 89 40 67",
    "sg:postcode":"08911",
    "sg:province":"Barcelona",
    "wof:name":"Ametller Moreo Francisco Javier",
    "wof:placetype":"venue"
},
  "geometry": {"coordinates":[2.2478377819,41.4548149109],"type":"Point"}
}