{
  "type": "Feature",
  "properties": {
    "iso:country":"ES",
    "sg:address":"Calle de Cebollera, 2",
    "sg:city":"Soria",
    "sg:orig_category":"Empresarios",
    "sg:phone":"+34 975 22 03 96",
    "sg:postcode":"42001",
    "sg:province":"Soria",
    "wof:name":"Llorente Sanz Pio",
    "wof:placetype":"venue"
},
  "geometry": {"coordinates":[-2.4763696194,41.7659416199],"type":"Point"}
}