{
  "type": "Feature",
  "properties": {
    "iso:country":"ES",
    "sg:address":"Filadores, 7",
    "sg:city":"Badalona",
    "sg:orig_category":"Vidrio, Fabricaci\u00d3n Y Comercio",
    "sg:phone":"+34 933 88 05 00",
    "sg:postcode":"08918",
    "sg:province":"Barcelona",
    "sg:website":"www.alglass.com",
    "wof:name":"Alglass S. A.",
    "wof:placetype":"venue"
},
  "geometry": {"coordinates":[2.2360844612,41.4337921143],"type":"Point"}
}