{
  "type": "Feature",
  "properties": {
    "addr:full":"Calle de Tubal, 8 Tafalla Navarra 31300",
    "addr:housenumber":"8",
    "addr:postcode":"31300",
    "addr:street":"Calle De Tubal",
    "iso:country":"ES",
    "sg:address":"Calle de Tubal, 8",
    "sg:city":"Tafalla",
    "sg:orig_category":"Art\u00cdculos Funerarios (al Por Menor)",
    "sg:phone":"+34 948 70 14 52",
    "sg:postcode":"31300",
    "sg:province":"Navarra",
    "wof:name":"Cipres Elizalde Pedro",
    "wof:placetype":"venue"
},
  "geometry": {"coordinates":[-1.6768939495,42.5276641846],"type":"Point"}
}