{
  "type": "Feature",
  "properties": {
    "addr:full":"Carrer de Josep Pla, 2 Martorell Barcelona 08760",
    "addr:housenumber":"2",
    "addr:postcode":"08760",
    "addr:street":"Carrer De Josep Pla",
    "iso:country":"ES",
    "sg:address":"Carrer de Josep Pla, 2",
    "sg:city":"Martorell",
    "sg:orig_category":"Congelados: Productos Alimentarios (al Por Menor)",
    "sg:phone":"+34 937 74 23 06",
    "sg:postcode":"08760",
    "sg:province":"Barcelona",
    "sg:website":"www.lasirena.es",
    "wof:name":"La Sirena Alimentacion Congelada S.l.u.",
    "wof:placetype":"venue"
},
  "geometry": {"coordinates":[1.9168549776,41.477684021],"type":"Point"}
}