{
  "type": "Feature",
  "properties": {
    "iso:country":"ES",
    "sg:address":"Calle de Chorretones, 4",
    "sg:city":"Cuellar",
    "sg:orig_category":"Inmobiliaria (agencias)",
    "sg:phone":"+34 921 14 47 96",
    "sg:postcode":"40200",
    "sg:province":"Segovia",
    "sg:website":"www.solcuellar.com",
    "wof:name":"C.b. Bermudez Maroto",
    "wof:placetype":"venue"
},
  "geometry": {"coordinates":[-4.3120064735,41.3992080688],"type":"Point"}
}