{
  "type": "Feature",
  "properties": {
    "iso:country":"ES",
    "sg:address":"Real, 4",
    "sg:city":"Cedeira",
    "sg:orig_category":"Quincaller\u00cda (al Por Menor)",
    "sg:phone":"+34 981 48 00 94",
    "sg:postcode":"15350",
    "sg:province":"La Coru\u00f1a",
    "wof:name":"Perez Garcia Manuel",
    "wof:placetype":"venue"
},
  "geometry": {"coordinates":[-8.0563573837,43.660697937],"type":"Point"}
}