{
  "type": "Feature",
  "properties": {
    "addr:full":"Calle de Ramon Llull, 31 Valencia Valencia 46021",
    "addr:housenumber":"31",
    "addr:postcode":"46021",
    "addr:street":"Calle De Ramon Llull",
    "iso:country":"ES",
    "sg:address":"Calle de Ramon Llull, 31",
    "sg:city":"Valencia",
    "sg:orig_category":"Librer\u00cdas",
    "sg:phone":"+34 963 89 02 62",
    "sg:postcode":"46021",
    "sg:province":"Valencia",
    "sg:website":"www.tirant.es",
    "wof:name":"Libros Tlb S.l.",
    "wof:placetype":"venue"
},
  "geometry": {"coordinates":[-0.346634388,39.4771881104],"type":"Point"}
}