{
  "type": "Feature",
  "properties": {
    "iso:country":"ES",
    "sg:address":"Avda Indianos (los), 22",
    "sg:city":"Santa Cruz Palma",
    "sg:orig_category":"Centros Empresariales",
    "sg:phone":"+34 922 41 38 83",
    "sg:postcode":"38700",
    "sg:province":"Santa Cruz De Tenerife",
    "wof:name":"Inversiones Farosas S.l",
    "wof:placetype":"venue"
},
  "geometry": {"coordinates":[-17.7704353333,28.6771087646],"type":"Point"}
}