{
  "type": "Feature",
  "properties": {
    "addr:full":"Carr San Antonio, 47 Aldaia Valencia 46960",
    "addr:housenumber":"47",
    "addr:postcode":"46960",
    "addr:street":"Carr San Antonio",
    "iso:country":"ES",
    "sg:address":"Carr San Antonio, 47",
    "sg:city":"Aldaia",
    "sg:orig_category":"Arquitectos",
    "sg:phone":"+34 961 50 45 63",
    "sg:postcode":"46960",
    "sg:province":"Valencia",
    "wof:name":"Mateu Navarro Enrique Antonio",
    "wof:placetype":"venue"
},
  "geometry": {"coordinates":[-0.4646419883,39.46534729],"type":"Point"}
}