{
  "type": "Feature",
  "properties": {
    "addr:full":"Calle de Lope De Rueda, 17 Almeria Almer\u00eda 04006",
    "addr:housenumber":"17",
    "addr:postcode":"04006",
    "addr:street":"Calle De Lope De Rueda",
    "iso:country":"ES",
    "sg:address":"Calle de Lope De Rueda, 17",
    "sg:city":"Almeria",
    "sg:orig_category":"Bricolaje, Herramientas (al Por Menor)",
    "sg:phone":"+34 950 23 79 83",
    "sg:postcode":"04006",
    "sg:province":"Almer\u00eda",
    "wof:name":"Bricotextil Almeria S.l.l.",
    "wof:placetype":"venue"
},
  "geometry": {"coordinates":[-2.4495849609,36.8390312195],"type":"Point"}
}