{
  "type": "Feature",
  "properties": {
    "addr:full":"Carrer de Doctor Pi I Molist, 11 Barcelona Barcelona 08031",
    "addr:housenumber":"11",
    "addr:postcode":"08031",
    "addr:street":"Carrer De Doctor Pi I Molist",
    "iso:country":"ES",
    "sg:address":"Carrer de Doctor Pi I Molist, 11",
    "sg:city":"Barcelona",
    "sg:orig_category":"Plomeros",
    "sg:phone":"+34 934 08 63 33",
    "sg:postcode":"08031",
    "sg:province":"Barcelona",
    "wof:name":"Dieguez Mosquera Jesus",
    "wof:placetype":"venue"
},
  "geometry": {"coordinates":[2.1738979816,41.4319343567],"type":"Point"}
}