{
  "type": "Feature",
  "properties": {
    "iso:country":"ES",
    "sg:address":"Carr Republica Argentina, 41",
    "sg:city":"Badalona",
    "sg:orig_category":"Asesor\u00cda De Comercio Exterior",
    "sg:phone":"+34 933 83 88 40",
    "sg:postcode":"08912",
    "sg:province":"Barcelona",
    "sg:website":"www.extecomed.com",
    "wof:name":"Extecomed S.l.",
    "wof:placetype":"venue"
},
  "geometry": {"coordinates":[2.241699934,41.442401886],"type":"Point"}
}