{
  "type": "Feature",
  "properties": {
    "iso:country":"ES",
    "sg:address":"Pg Mare De Deu Del Coll, 155",
    "sg:city":"Barcelona",
    "sg:orig_category":"Empresas De Pintura Y Revestimientos",
    "sg:phone":"+34 933 57 31 83",
    "sg:postcode":"08032",
    "sg:province":"Barcelona",
    "wof:name":"Abdon Berenguer Evaristo",
    "wof:placetype":"venue"
},
  "geometry": {"coordinates":[2.151004,41.4226],"type":"Point"}
}