{
  "type": "Feature",
  "properties": {
    "iso:country":"ES",
    "sg:address":"Plaz Ezkabazabal, 8",
    "sg:city":"Burlada",
    "sg:orig_category":"Asesor\u00cda Fiscal Y Jur\u00cddica",
    "sg:phone":"+34 948 13 42 57",
    "sg:postcode":"31600",
    "sg:province":"Navarra",
    "wof:name":"Hernandez Ortiz Sara",
    "wof:placetype":"venue"
},
  "geometry": {"coordinates":[-1.6152689457,42.8264541626],"type":"Point"}
}