{
  "type": "Feature",
  "properties": {
    "iso:country":"ES",
    "sg:address":"Plaz Parres Pi\u00d1era, S/n",
    "sg:city":"Posada",
    "sg:orig_category":"Peluquer\u00cdas, Peluquer\u00cda Mixta",
    "sg:phone":"+34 985 40 71 96",
    "sg:postcode":"33594",
    "sg:province":"Asturias",
    "sg:website":"www.tescas.com",
    "wof:name":"Tescas Cb.",
    "wof:placetype":"venue"
},
  "geometry": {"coordinates":[-4.8618822098,43.4186553955],"type":"Point"}
}