{
  "type": "Feature",
  "properties": {
    "iso:country":"ES",
    "sg:address":"Avda Ansaldo, 3",
    "sg:city":"Alacant",
    "sg:orig_category":"Psicoanalistas",
    "sg:phone":"+34 965 15 01 39",
    "sg:postcode":"03016",
    "sg:province":"Alicante",
    "wof:name":"Strada Bello Angel Oscar",
    "wof:placetype":"venue"
},
  "geometry": {"coordinates":[-0.4308210015,38.3639717102],"type":"Point"}
}