{
  "type": "Feature",
  "properties": {
    "addr:full":"Calle de Fernando El Catolico, 2 Huelva Huelva 21003",
    "addr:housenumber":"2",
    "addr:postcode":"21003",
    "addr:street":"Calle De Fernando El Catolico",
    "iso:country":"ES",
    "sg:address":"Calle de Fernando El Catolico, 2",
    "sg:city":"Huelva",
    "sg:orig_category":"Comunidades Religiosas",
    "sg:phone":"+34 959 24 01 20",
    "sg:postcode":"21003",
    "sg:province":"Huelva",
    "wof:name":"Centro Javier Orienta",
    "wof:placetype":"venue"
},
  "geometry": {"coordinates":[-6.9487991333,37.2566566467],"type":"Point"}
}