{
  "type": "Feature",
  "properties": {
    "iso:country":"ES",
    "sg:address":"Calle de San Roque, 16",
    "sg:city":"Sig\u00fcenza",
    "sg:orig_category":"Empresarios",
    "sg:phone":"+34 949 39 15 69",
    "sg:postcode":"19250",
    "sg:province":"Guadalajara",
    "wof:name":"Fundacion Internacional O'belen",
    "wof:placetype":"venue"
},
  "geometry": {"coordinates":[-2.6405990124,41.0700683594],"type":"Point"}
}