{
  "type": "Feature",
  "properties": {
    "addr:full":"Avda Portugal, 4 Aracena Huelva 21200",
    "addr:housenumber":"4",
    "addr:postcode":"21200",
    "addr:street":"Avda Portugal",
    "iso:country":"ES",
    "sg:address":"Avda Portugal, 4",
    "sg:city":"Aracena",
    "sg:orig_category":"Electricidad: Instaladores",
    "sg:phone":"+34 959 12 81 35",
    "sg:postcode":"21200",
    "sg:province":"Huelva",
    "wof:name":"Electrosierra Aracena S.l.",
    "wof:placetype":"venue"
},
  "geometry": {"coordinates":[-6.5606479645,37.8948822021],"type":"Point"}
}