{
  "type": "Feature",
  "properties": {
    "iso:country":"ES",
    "sg:address":"Rua Doutor Teixeiro (do), 39",
    "sg:city":"Santiago De Compostela",
    "sg:orig_category":"Agencias Y Agentes Comerciales, Representantes",
    "sg:phone":"+34 981 58 06 44",
    "sg:postcode":"15701",
    "sg:province":"La Coru\u00f1a",
    "wof:name":"Lopez Gutierrez Maximo",
    "wof:placetype":"venue"
},
  "geometry": {"coordinates":[-8.545630455,42.8735771179],"type":"Point"}
}