{
  "type": "Feature",
  "properties": {
    "addr:full":"Calle de Jose Del Hierro, 46 Madrid Madrid 28027",
    "addr:housenumber":"46",
    "addr:postcode":"madrid;28027",
    "addr:street":"Calle De Jose Del Hierro",
    "iso:country":"ES",
    "sg:address":"Calle de Jose Del Hierro, 46",
    "sg:city":"Madrid",
    "sg:orig_category":"Bancos",
    "sg:phone":"+34 913 68 20 60",
    "sg:postcode":"28027",
    "sg:province":"Madrid",
    "sg:website":"www.banesto.es",
    "wof:name":"Banco Espa\u00f1ol De Credito S.a.",
    "wof:placetype":"venue"
},
  "geometry": {"coordinates":[-3.6450519562,40.4395980835],"type":"Point"}
}