{
  "type": "Feature",
  "properties": {
    "addr:full":"Calle de San Sebastian, 7 Isla Cristina Huelva 21410",
    "addr:housenumber":"7",
    "addr:postcode":"21410",
    "addr:street":"Calle De San Sebastian",
    "iso:country":"ES",
    "sg:address":"Calle de San Sebastian, 7",
    "sg:city":"Isla Cristina",
    "sg:orig_category":"Guarder\u00cdas",
    "sg:phone":"+34 959 34 38 43",
    "sg:postcode":"21410",
    "sg:province":"Huelva",
    "wof:name":"Guarderia El Castillo,asociacion De Educacion Infantil Carrimar",
    "wof:placetype":"venue"
},
  "geometry": {"coordinates":[-7.3263001442,37.1951675415],"type":"Point"}
}