{
  "type": "Feature",
  "properties": {
    "addr:full":"Calle de Robradiza, 20 Romeral Toledo 45770",
    "addr:housenumber":"20",
    "addr:postcode":"45770",
    "addr:street":"Calle De Robradiza",
    "iso:country":"ES",
    "sg:address":"Calle de Robradiza, 20",
    "sg:city":"Romeral",
    "sg:orig_category":"Ense\u00d1ante, Direcci\u00d3n",
    "sg:phone":"+34 925 12 64 36",
    "sg:postcode":"45770",
    "sg:province":"Toledo",
    "wof:name":"Llorente Valladar Juan Jose",
    "wof:placetype":"venue"
},
  "geometry": {"coordinates":[-3.4356908798,39.7083244324],"type":"Point"}
}