{
  "type": "Feature",
  "properties": {
    "iso:country":"ES",
    "sg:address":"C/ Doctor Sapena, 30",
    "sg:city":"Elche",
    "sg:orig_category":"Venta, Alquiler Y Mantenimiento De Juegos De Sal\u00d3n O Casinos",
    "sg:phone":"+34 966 66 11 23",
    "sg:postcode":"03204",
    "sg:province":"Alicante",
    "wof:name":"Recreativos Levante S.l.",
    "wof:placetype":"venue"
},
  "geometry": {"coordinates":[-0.705057025,38.2620925903],"type":"Point"}
}