{
  "type": "Feature",
  "properties": {
    "addr:full":"Carrer de Major, 12 Tona Barcelona 08551",
    "addr:housenumber":"12",
    "addr:postcode":"08551",
    "addr:street":"Carrer De Major",
    "iso:country":"ES",
    "sg:address":"Carrer de Major, 12",
    "sg:city":"Tona",
    "sg:orig_category":"Ropa De Hogar (al Por Menor)",
    "sg:phone":"+34 938 87 08 52",
    "sg:postcode":"08551",
    "sg:province":"Barcelona",
    "wof:name":"Perez Flores Pablo",
    "wof:placetype":"venue"
},
  "geometry": {"coordinates":[2.2283689976,41.8508033752],"type":"Point"}
}