{
  "type": "Feature",
  "properties": {
    "addr:full":"Calle de Fernandez De Oviedo, 16 Madrid Madrid 28002",
    "addr:housenumber":"16",
    "addr:postcode":"madrid;28002",
    "addr:street":"Calle De Fernandez De Oviedo",
    "iso:country":"ES",
    "sg:address":"Calle de Fernandez De Oviedo, 16",
    "sg:city":"Madrid",
    "sg:orig_category":"Centros Empresariales",
    "sg:phone":"+34 914 13 84 98",
    "sg:postcode":"28002",
    "sg:province":"Madrid",
    "wof:name":"Niu Multiservicios S.l.",
    "wof:placetype":"venue"
},
  "geometry": {"coordinates":[-3.6717669964,40.4468955994],"type":"Point"}
}