{
  "type": "Feature",
  "properties": {
    "iso:country":"ES",
    "sg:address":"Av Alacant, 37",
    "sg:city":"Elche",
    "sg:orig_category":"Bancos",
    "sg:phone":"+34 965 45 58 44",
    "sg:postcode":"03202",
    "sg:province":"Alicante",
    "wof:name":"Banco Popular Espa\u00d1ol S.a.",
    "wof:placetype":"venue"
},
  "geometry": {"coordinates":[-0.6840739846,38.269317627],"type":"Point"}
}