{
  "type": "Feature",
  "properties": {
    "addr:full":"Carrer de Taxdirt, 57 Barcelona Barcelona 08025",
    "addr:housenumber":"57",
    "addr:postcode":"08025",
    "addr:street":"Carrer De Taxdirt",
    "iso:country":"ES",
    "sg:address":"Carrer de Taxdirt, 57",
    "sg:city":"Barcelona",
    "sg:orig_category":"Aislamiento El\u00c9ctrico",
    "sg:phone":"+34 933 47 04 55",
    "sg:postcode":"08025",
    "sg:province":"Barcelona",
    "wof:name":"Calorifugados Industriales S. L.",
    "wof:placetype":"venue"
},
  "geometry": {"coordinates":[2.1674330235,41.4101791382],"type":"Point"}
}