{
  "type": "Feature",
  "properties": {
    "iso:country":"ES",
    "sg:address":"Carrer de Merce, 10",
    "sg:city":"Poblenou",
    "sg:orig_category":"Mec\u00c1nico Del Autom\u00d3vil",
    "sg:phone":"+34 937 26 78 76",
    "sg:postcode":"08202",
    "sg:province":"Barcelona",
    "wof:name":"Parra Porcel Manuel",
    "wof:placetype":"venue"
},
  "geometry": {"coordinates":[2.1264369488,41.5601387024],"type":"Point"}
}