{
  "type": "Feature",
  "properties": {
    "addr:full":"Calle de Carmen, 2 Zaragoza Zaragoza 50005",
    "addr:housenumber":"2",
    "addr:postcode":"50005",
    "addr:street":"Calle De Carmen",
    "iso:country":"ES",
    "sg:address":"Calle de Carmen, 2",
    "sg:city":"Zaragoza",
    "sg:orig_category":"Supermercados Y Hipermercados",
    "sg:phone":"+34 976 21 51 42",
    "sg:postcode":"50005",
    "sg:province":"Zaragoza",
    "wof:name":"Supermercados Sabeco S.a.",
    "wof:placetype":"venue"
},
  "geometry": {"coordinates":[-0.8912349939,41.6474380493],"type":"Point"}
}