{
  "type": "Feature",
  "properties": {
    "iso:country":"ES",
    "sg:address":"Avda Eulogio Fernandez, S/n",
    "sg:city":"Barco",
    "sg:orig_category":"Pizzer\u00cdas",
    "sg:phone":"+34 988 32 01 09",
    "sg:postcode":"32300",
    "sg:province":"Ourense",
    "wof:name":"Garcia Oviedo Manuel",
    "wof:placetype":"venue"
},
  "geometry": {"coordinates":[-6.9897217751,42.4178886414],"type":"Point"}
}