{
  "type": "Feature",
  "properties": {
    "addr:full":"Avda Dos De Mayo (del), 39 Mostoles Madrid 28934",
    "addr:housenumber":"39",
    "addr:postcode":"28934",
    "addr:street":"Avda Dos De Mayo Del",
    "iso:country":"ES",
    "sg:address":"Avda Dos De Mayo (del), 39",
    "sg:city":"Mostoles",
    "sg:orig_category":"Sociedades, Compa\u00d1\u00cdas Aseguradoras",
    "sg:phone":"+34 916 18 98 94",
    "sg:postcode":"28934",
    "sg:province":"Madrid",
    "sg:website":"www.sanitas.com",
    "wof:name":"Segurmedi S.l.",
    "wof:placetype":"venue"
},
  "geometry": {"coordinates":[-3.8715109825,40.319896698],"type":"Point"}
}