{
  "type": "Feature",
  "properties": {
    "iso:country":"ES",
    "sg:address":"Calle de Real De San Juan, 55",
    "sg:city":"Palmas De Gran Canaria",
    "sg:orig_category":"Frutas, Legumbres Frescas Y Tempranas (al Por Menor)",
    "sg:phone":"+34 928 33 19 06",
    "sg:postcode":"35015",
    "sg:province":"Las Palmas",
    "wof:name":"Hernandez Mejias Jose Francisco",
    "wof:placetype":"venue"
},
  "geometry": {"coordinates":[-15.419503212,28.0982074738],"type":"Point"}
}