{
  "type": "Feature",
  "properties": {
    "addr:full":"Calle de Chinchon, 2 Ventorro Del Cano Madrid 28925",
    "addr:housenumber":"2",
    "addr:postcode":"28925",
    "addr:street":"Calle De Chinchon",
    "iso:country":"ES",
    "sg:address":"Calle de Chinchon, 2",
    "sg:city":"Ventorro Del Cano",
    "sg:orig_category":"Barnizadores",
    "sg:phone":"+34 916 32 04 27",
    "sg:postcode":"28925",
    "sg:province":"Madrid",
    "wof:name":"Lacados Y Barnizados S.l.",
    "wof:placetype":"venue"
},
  "geometry": {"coordinates":[-3.8358030319,40.3936958313],"type":"Point"}
}