{
  "type": "Feature",
  "properties": {
    "iso:country":"ES",
    "sg:address":"Zuberoa Kalea, 2",
    "sg:city":"Andoain",
    "sg:orig_category":"Molduras, Junquillos, Listones Y Molduras Perforadas",
    "sg:phone":"+34 943 59 29 55",
    "sg:postcode":"20140",
    "sg:province":"Guip\u00f9zcoa",
    "wof:name":"Ana  Jesus Orta Martiartu",
    "wof:placetype":"venue"
},
  "geometry": {"coordinates":[-2.0229525566,43.2201194763],"type":"Point"}
}