{
  "type": "Feature",
  "properties": {
    "iso:country":"ES",
    "sg:address":"Avda Ciclista Mariano Rojas, S/n",
    "sg:city":"Ranero",
    "sg:orig_category":"Trabajos De Asfalto, De Alquitr\u00c1n Y Asfalto",
    "sg:phone":"+34 968 28 40 71",
    "sg:postcode":"30009",
    "sg:province":"Murcia",
    "wof:name":"D G Asfaltos S.a.",
    "wof:placetype":"venue"
},
  "geometry": {"coordinates":[-1.1528439522,37.9883460999],"type":"Point"}
}