{
  "type": "Feature",
  "properties": {
    "iso:country":"ES",
    "sg:address":"Rua Greco, 4",
    "sg:city":"Sarria",
    "sg:orig_category":"Frutas, Legumbres Frescas Y Tempranas (al Por Menor)",
    "sg:phone":"+34 982 53 50 46",
    "sg:postcode":"27600",
    "sg:province":"Lugo",
    "wof:name":"Dapena Mendez Purificacion",
    "wof:placetype":"venue"
},
  "geometry": {"coordinates":[-7.4093141556,42.7827186584],"type":"Point"}
}