{
  "type": "Feature",
  "properties": {
    "addr:full":"Calle de Zabalbide, 92 Bilbao Vizcaya 48006",
    "addr:housenumber":"92",
    "addr:postcode":"48006",
    "addr:street":"Calle De Zabalbide",
    "iso:country":"ES",
    "sg:address":"Calle de Zabalbide, 92",
    "sg:city":"Bilbao",
    "sg:orig_category":"Internados & Ense\u00d1anza Privada",
    "sg:phone":"+34 944 12 89 31",
    "sg:postcode":"48006",
    "sg:province":"Vizcaya",
    "wof:name":"Union De Nuestra Se\u00f1ora De La Caridad",
    "wof:placetype":"venue"
},
  "geometry": {"coordinates":[-2.911826849,43.258441925],"type":"Point"}
}