{
  "type": "Feature",
  "properties": {
    "iso:country":"ES",
    "sg:address":"Avda San Vicente De Paul, 3",
    "sg:city":"Tamarite Litera",
    "sg:orig_category":"Ense\u00d1ante, Direcci\u00d3n",
    "sg:phone":"+34 974 42 03 66",
    "sg:postcode":"22550",
    "sg:province":"Huesca",
    "wof:name":"Capdevila Maga\u00f1a Modesto",
    "wof:placetype":"venue"
},
  "geometry": {"coordinates":[0.4191009998,41.8709030151],"type":"Point"}
}