{
  "type": "Feature",
  "properties": {
    "iso:country":"ES",
    "sg:address":"Calle de Marques De Larios, 7",
    "sg:city":"Malaga",
    "sg:orig_category":"Ropa Para Se\u00d1oras Y Caballeros (al Por Menor)",
    "sg:phone":"+34 952 60 39 03",
    "sg:postcode":"29015",
    "sg:province":"M\u00e1laga",
    "sg:website":"www.massimodutti.com",
    "wof:name":"Grupo Massimo Dutti S.a.",
    "wof:placetype":"venue"
},
  "geometry": {"coordinates":[-4.4213838577,36.7190895081],"type":"Point"}
}