{
  "type": "Feature",
  "properties": {
    "iso:country":"ES",
    "sg:address":"Calle de Somontin, 100",
    "sg:city":"Madrid",
    "sg:orig_category":"\u00d3ptica: Instrumentos (fabricaci\u00d3n)",
    "sg:phone":"+34 913 02 20 93",
    "sg:postcode":"28033",
    "sg:province":"Madrid",
    "wof:name":"Ramos Barba Milagros",
    "wof:placetype":"venue"
},
  "geometry": {"coordinates":[-3.6587688923,40.4785957336],"type":"Point"}
}