{
  "type": "Feature",
  "properties": {
    "addr:full":"Calle de San Sebastian, 11 Alhaurin El Grande M\u00e1laga 29120",
    "addr:housenumber":"11",
    "addr:postcode":"29120",
    "addr:street":"Calle De San Sebastian",
    "iso:country":"ES",
    "sg:address":"Calle de San Sebastian, 11",
    "sg:city":"Alhaurin El Grande",
    "sg:orig_category":"Alimentaci\u00d3n General (al Por Mayor)",
    "sg:phone":"+34 952 49 03 69",
    "sg:postcode":"29120",
    "sg:province":"M\u00e1laga",
    "wof:name":"Rueda Gonzalez Antonio",
    "wof:placetype":"venue"
},
  "geometry": {"coordinates":[-4.687748909,36.6445846558],"type":"Point"}
}