{
  "type": "Feature",
  "properties": {
    "iso:country":"ES",
    "sg:address":"Carretera De Granada-malaga, S/n",
    "sg:city":"Moraleda Zafayona",
    "sg:orig_category":"Compraventa De Antig\u00dcedades",
    "sg:phone":"+34 958 49 71 01",
    "sg:postcode":"18370",
    "sg:province":"Granada",
    "wof:name":"Solerconely S.l.",
    "wof:placetype":"venue"
},
  "geometry": {"coordinates":[-3.9661040306,37.1709251404],"type":"Point"}
}