{
  "type": "Feature",
  "properties": {
    "addr:full":"Carretera De Ronda-campillos, Km. 0004,0 Ronda M\u00e1laga 29400",
    "addr:postcode":"29400",
    "addr:street":"Carretera De Ronda-Campillos Km. 0004,0 Ronda Ma\u0301Laga",
    "iso:country":"ES",
    "sg:address":"Carretera De Ronda-campillos, Km. 0004,0",
    "sg:city":"Ronda",
    "sg:orig_category":"Agricultura: Abastecimiento Y Cosechado (negocio)",
    "sg:phone":"+34 952 87 28 84",
    "sg:postcode":"29400",
    "sg:province":"M\u00e1laga",
    "wof:name":"Campos Aberasturi Jose Antonio",
    "wof:placetype":"venue"
},
  "geometry": {"coordinates":[-5.1662788391,36.7417945862],"type":"Point"}
}