{
  "type": "Feature",
  "properties": {
    "addr:full":"Calle de Rosa Luxemburgo, 3 Madrid Madrid 28023",
    "addr:housenumber":"3",
    "addr:postcode":"28023",
    "addr:street":"Calle De Rosa Luxemburgo",
    "iso:country":"ES",
    "sg:address":"Calle de Rosa Luxemburgo, 3",
    "sg:city":"Madrid",
    "sg:orig_category":"Frutas, Legumbres Frescas Y Tempranas (al Por Menor)",
    "sg:phone":"+34 913 57 28 68",
    "sg:postcode":"28023",
    "sg:province":"Madrid",
    "wof:name":"Fricamar S.l.",
    "wof:placetype":"venue"
},
  "geometry": {"coordinates":[-3.7689259052,40.4504051208],"type":"Point"}
}