{
  "type": "Feature",
  "properties": {
    "iso:country":"ES",
    "sg:address":"Carrer de Mendez Nu\u00d1ez, 4",
    "sg:city":"Tarragona",
    "sg:orig_category":"Institutos De Belleza",
    "sg:phone":"+34 977 22 04 90",
    "sg:postcode":"43004",
    "sg:province":"Tarragona",
    "wof:name":"Manero Moncunill Montserrat",
    "wof:placetype":"venue"
},
  "geometry": {"coordinates":[1.2531599998,41.114906311],"type":"Point"}
}