{
  "type": "Feature",
  "properties": {
    "addr:full":"Avda Perez Galdos, 127 Valencia Valencia 46018",
    "addr:housenumber":"127",
    "addr:postcode":"46018",
    "addr:street":"Avda Perez Galdos",
    "iso:country":"ES",
    "sg:address":"Avda Perez Galdos, 127",
    "sg:city":"Valencia",
    "sg:orig_category":"Servicio De Salud",
    "sg:phone":"+34 963 82 01 29",
    "sg:postcode":"46018",
    "sg:province":"Valencia",
    "wof:name":"Fito Estelles Jose Jesus",
    "wof:placetype":"venue"
},
  "geometry": {"coordinates":[-0.3949460089,39.4735374451],"type":"Point"}
}