{
  "type": "Feature",
  "properties": {
    "addr:full":"Avda Madrid, Km. 0185,0 Laguna Duero Valladolid 47...",
    "addr:housenumber":"47 ...",
    "addr:street":"Avda Madrid Km. 0185,0 Laguna Duero Valladolid",
    "iso:country":"ES",
    "sg:address":"Avda Madrid, Km. 0185,0",
    "sg:city":"Laguna Duero",
    "sg:classifiers":[
        {
            "category":"Communications",
            "type":"Services"
        }
    ],
    "sg:phone":"+34 983 32 81 00",
    "sg:postcode":"47...",
    "sg:province":"Valladolid",
    "sg:tags":[
        "televisiones",
        "y",
        "radio"
    ],
    "wof:name":"Television Espa\u00d1ola S.a.",
    "wof:placetype":"venue"
},
  "geometry": {"coordinates":[-4.7260289192,41.5838012695],"type":"Point"}
}