{
  "type": "Feature",
  "properties": {
    "addr:full":"Calle de Santo Reino, 7 Jaen Ja\u00e9n 23001",
    "addr:housenumber":"7;jae\u0301n",
    "addr:postcode":"23001",
    "addr:street":"Calle De Santo Reino",
    "iso:country":"ES",
    "sg:address":"Calle de Santo Reino, 7",
    "sg:city":"Jaen",
    "sg:orig_category":"Sociedades, Compa\u00d1\u00cdas Aseguradoras",
    "sg:phone":"+34 953 22 94 28",
    "sg:postcode":"23001",
    "sg:province":"Ja\u00e9n",
    "sg:website":"www.fremap.es",
    "wof:name":"Fremap-mutua De Accidentes De Trabajo Y Enfermedad Profesionales De La Seguridad",
    "wof:placetype":"venue"
},
  "geometry": {"coordinates":[-3.7865540981,37.7720718384],"type":"Point"}
}