{
  "type": "Feature",
  "properties": {
    "addr:full":"Rua Urzaiz, 83 Vigo Pontevedra 36204",
    "addr:housenumber":"83",
    "addr:postcode":"36204",
    "addr:street":"Rua Urzaiz",
    "iso:country":"ES",
    "sg:address":"Rua Urzaiz, 83",
    "sg:city":"Vigo",
    "sg:orig_category":"Carnicer\u00cdas, Carnicer\u00cdas",
    "sg:phone":"+34 986 43 90 54",
    "sg:postcode":"36204",
    "sg:province":"Pontevedra",
    "wof:name":"Fernandez Alen Emilio Antonio",
    "wof:placetype":"venue"
},
  "geometry": {"coordinates":[-8.7123022079,42.2330360413],"type":"Point"}
}