{
  "type": "Feature",
  "properties": {
    "addr:full":"Calle de Askatasuna, 5 Gernika-lumo Vizcaya 48300",
    "addr:housenumber":"5",
    "addr:postcode":"48300",
    "addr:street":"Calle De Askatasuna",
    "iso:country":"ES",
    "sg:address":"Calle de Askatasuna, 5",
    "sg:city":"Gernika-lumo",
    "sg:orig_category":"Asesor\u00cda Sobre Comunicaci\u00d3n De Empresas",
    "sg:phone":"+34 946 25 76 43",
    "sg:postcode":"48300",
    "sg:province":"Vizcaya",
    "wof:name":"Casmarco, S.l.",
    "wof:placetype":"venue"
},
  "geometry": {"coordinates":[-2.6783030033,43.31092453],"type":"Point"}
}