{
  "type": "Feature",
  "properties": {
    "iso:country":"ES",
    "sg:address":"Calle de Fontanares, 10",
    "sg:city":"Valencia",
    "sg:orig_category":"Servicios Gsm",
    "sg:phone":"+34 963 58 12 44",
    "sg:postcode":"46007",
    "sg:province":"Valencia",
    "wof:name":"Lluchbacam S.l.",
    "wof:placetype":"venue"
},
  "geometry": {"coordinates":[-0.3924992979,39.4582176208],"type":"Point"}
}