{
  "type": "Feature",
  "properties": {
    "iso:country":"ES",
    "sg:address":"Calle de Nuestra Sra Del Pilar (de), 9",
    "sg:city":"Alcobendas",
    "sg:orig_category":"Agencias De Trabajo Temporal",
    "sg:phone":"+34 916 59 17 50",
    "sg:postcode":"28100",
    "sg:province":"Madrid",
    "wof:name":"Iman Temporing Ett S.l.",
    "wof:placetype":"venue"
},
  "geometry": {"coordinates":[-3.6330809593,40.5420074463],"type":"Point"}
}