{
  "type": "Feature",
  "properties": {
    "iso:country":"ES",
    "sg:address":"Calle de Picasso, 12",
    "sg:city":"Dos Hermanas",
    "sg:orig_category":"Molduras, Junquillos, Listones Y Molduras Perforadas",
    "sg:phone":"+34 955 67 85 44",
    "sg:postcode":"41700",
    "sg:province":"Sevilla",
    "wof:name":"Explotaciones Hoteleras Nazarenas S.l.",
    "wof:placetype":"venue"
},
  "geometry": {"coordinates":[-5.9123110771,37.2895927429],"type":"Point"}
}