{
  "type": "Feature",
  "properties": {
    "addr:full":"Carrer de Industria, 9 Xiol Barcelona 08185",
    "addr:housenumber":"9",
    "addr:postcode":"08185",
    "addr:street":"Carrer De Industria;Barcelona",
    "iso:country":"ES",
    "sg:address":"Carrer de Industria, 9",
    "sg:city":"Xiol",
    "sg:orig_category":"Chapister\u00cda",
    "sg:phone":"+34 938 43 71 25",
    "sg:postcode":"08185",
    "sg:province":"Barcelona",
    "wof:name":"Lancharro Gabilan Francisco Luis",
    "wof:placetype":"venue"
},
  "geometry": {"coordinates":[2.2324490547,41.5865364075],"type":"Point"}
}