{
  "type": "Feature",
  "properties": {
    "addr:full":"Avda Francia, 49 Valencia Valencia 46023",
    "addr:housenumber":"49",
    "addr:postcode":"46023",
    "addr:street":"Avda Francia",
    "iso:country":"ES",
    "sg:address":"Avda Francia, 49",
    "sg:city":"Valencia",
    "sg:orig_category":"M\u00c9dicos: Estomatolog\u00cda",
    "sg:phone":"+34 963 31 27 71",
    "sg:postcode":"46023",
    "sg:province":"Valencia",
    "wof:name":"Mulet Bono Silvia",
    "wof:placetype":"venue"
},
  "geometry": {"coordinates":[-0.3488790095,39.459690094],"type":"Point"}
}