{
  "type": "Feature",
  "properties": {
    "addr:full":"Carrer de Puig De Na Morisca, S/n Santa Pon\u00c7a Islas Baleares 07180",
    "addr:housenumber":"s / n",
    "addr:postcode":"07180",
    "addr:street":"Carrer De Puig De Na Morisca",
    "iso:country":"ES",
    "sg:address":"Carrer de Puig De Na Morisca, S/n",
    "sg:city":"Santa Pon\u00c7a",
    "sg:orig_category":"Centros De Educaci\u00d3n Especial",
    "sg:phone":"+34 971 69 92 47",
    "sg:postcode":"07180",
    "sg:province":"Islas Baleares",
    "wof:name":"Colegio Publico Puig De Sa Morisca",
    "wof:placetype":"venue"
},
  "geometry": {"coordinates":[2.4785399437,39.5062942505],"type":"Point"}
}