{
  "type": "Feature",
  "properties": {
    "iso:country":"ES",
    "sg:address":"Sampayo De Veiga, S/n",
    "sg:city":"Celanova",
    "sg:orig_category":"Promotores Constructores",
    "sg:phone":"+34 988 45 11 53",
    "sg:postcode":"32800",
    "sg:province":"Ourense",
    "wof:name":"Feijoo Rodriguez Maria Luisa",
    "wof:placetype":"venue"
},
  "geometry": {"coordinates":[-7.8338680267,42.6394233704],"type":"Point"}
}