{
  "type": "Feature",
  "properties": {
    "iso:country":"ES",
    "sg:address":"Calle de Alcalde Francisco Orejas, 8",
    "sg:city":"Aviles",
    "sg:orig_category":"Peluqueros: De Se\u00d1oras",
    "sg:phone":"+34 985 56 21 73",
    "sg:postcode":"33401",
    "sg:province":"Asturias",
    "wof:name":"Peluqueria Carmenes S. L.",
    "wof:placetype":"venue"
},
  "geometry": {"coordinates":[-5.9275689125,43.5562934875],"type":"Point"}
}