{
  "type": "Feature",
  "properties": {
    "addr:full":"Barrio Los Mesones, S/n Puentenansa Cantabria 39554",
    "addr:housenumber":"s",
    "addr:postcode":"39554",
    "addr:street":"Barrio Los;/ N",
    "iso:country":"ES",
    "sg:address":"Barrio Los Mesones, S/n",
    "sg:city":"Puentenansa",
    "sg:classifiers":[
        {
            "category":"Taxi",
            "type":"Transportation"
        }
    ],
    "sg:phone":"+34 942 72 80 52",
    "sg:postcode":"39554",
    "sg:province":"Cantabria",
    "wof:name":"Mazon Gonzalez Aurora",
    "wof:placetype":"venue"
},
  "geometry": {"coordinates":[-4.4067897797,43.2545547485],"type":"Point"}
}