{
  "type": "Feature",
  "properties": {
    "addr:full":"Calle de Atalaya (la), 8 Segovia Segovia 40006",
    "addr:housenumber":"8",
    "addr:postcode":"40006",
    "addr:street":"Calle De Atalaya La",
    "iso:country":"ES",
    "sg:address":"Calle de Atalaya (la), 8",
    "sg:city":"Segovia",
    "sg:orig_category":"Alfarer\u00cda",
    "sg:phone":"+34 921 42 21 09",
    "sg:postcode":"40006",
    "sg:province":"Segovia",
    "wof:name":"Alvarez Fernandez Andres",
    "wof:placetype":"venue"
},
  "geometry": {"coordinates":[-4.1133518219,40.9291687012],"type":"Point"}
}