{
  "type": "Feature",
  "properties": {
    "addr:full":"I. Don J. Manuel, 12 Almansa Albacete 02640",
    "addr:housenumber":"12",
    "addr:postcode":"02640",
    "addr:street":"I. Don J. Manuel",
    "iso:country":"ES",
    "sg:address":"I. Don J. Manuel, 12",
    "sg:city":"Almansa",
    "sg:orig_category":"Confecci\u00d3n De Zapatos",
    "sg:phone":"+34 967 31 15 18",
    "sg:postcode":"02640",
    "sg:province":"Albacete",
    "wof:name":"Calzados Michel S.a.",
    "wof:placetype":"venue"
},
  "geometry": {"coordinates":[-1.1022880077,38.8743247986],"type":"Point"}
}