{
  "type": "Feature",
  "properties": {
    "iso:country":"ES",
    "sg:address":"Av Canal, 173",
    "sg:city":"Prat Llobregat",
    "sg:orig_category":"Tintes (fabricaci\u00d3n, Al Por Mayor)",
    "sg:phone":"+34 933 70 90 96",
    "sg:postcode":"08820",
    "sg:province":"Barcelona",
    "wof:name":"Donda Voltolini Jorge Alberto",
    "wof:placetype":"venue"
},
  "geometry": {"coordinates":[2.0927679539,41.3246231079],"type":"Point"}
}