{
  "type": "Feature",
  "properties": {
    "iso:country":"ES",
    "sg:address":"Calle de Historiador Escolano, 5",
    "sg:city":"Castellon",
    "sg:orig_category":"Electricidad: Instaladores",
    "sg:phone":"+34 964 21 70 07",
    "sg:postcode":"12004",
    "sg:province":"Castell\u00f3n",
    "wof:name":"Sos Escrig Jose Juan",
    "wof:placetype":"venue"
},
  "geometry": {"coordinates":[-0.0414119996,39.9925918579],"type":"Point"}
}