{
  "type": "Feature",
  "properties": {
    "iso:country":"ES",
    "sg:address":"Calle de Sahagun, 16",
    "sg:city":"Alcorcon",
    "sg:orig_category":"Alimentaci\u00d3n General (al Por Menor)",
    "sg:phone":"+34 916 19 24 25",
    "sg:postcode":"28925",
    "sg:province":"Madrid",
    "wof:name":"Santos Atienza Salvador",
    "wof:placetype":"venue"
},
  "geometry": {"coordinates":[-3.8203780651,40.3545875549],"type":"Point"}
}