{
  "type": "Feature",
  "properties": {
    "iso:country":"ES",
    "sg:address":"Cra. Granollers-gerona, Km. 0008,0",
    "sg:city":"Cardedeu",
    "sg:orig_category":"Supermercados Y Hipermercados",
    "sg:phone":"+34 938 44 44 41",
    "sg:postcode":"08440",
    "sg:province":"Barcelona",
    "wof:name":"Grup Supeco Maxor S L",
    "wof:placetype":"venue"
},
  "geometry": {"coordinates":[2.3568429947,41.6367835999],"type":"Point"}
}