{
  "type": "Feature",
  "properties": {
    "iso:country":"ES",
    "sg:address":"Carrer de Berruguete, 100",
    "sg:city":"Barcelona",
    "sg:orig_category":"Venta, Localizaci\u00d3n, Reparaci\u00d3n De Material E Instrumental M\u00c9dico",
    "sg:phone":"+34 933 17 32 93",
    "sg:postcode":"08035",
    "sg:province":"Barcelona",
    "wof:name":"Fibre Medic S.a.",
    "wof:placetype":"venue"
},
  "geometry": {"coordinates":[2.1485290527,41.4333953857],"type":"Point"}
}