{
  "type": "Feature",
  "properties": {
    "addr:full":"Pl. Ind. Los Cerezos, 12 Mora Rubielos Teruel 44400",
    "addr:housenumber":"12",
    "addr:postcode":"44400",
    "addr:street":"Los Cerezos",
    "iso:country":"ES",
    "sg:address":"Pl. Ind. Los Cerezos, 12",
    "sg:city":"Mora Rubielos",
    "sg:orig_category":"Chapister\u00cda",
    "sg:phone":"+34 978 80 71 08",
    "sg:postcode":"44400",
    "sg:province":"Teruel",
    "wof:name":"Ros Toran S.l.",
    "wof:placetype":"venue"
},
  "geometry": {"coordinates":[-0.7552589774,40.2504005432],"type":"Point"}
}