{
  "type": "Feature",
  "properties": {
    "iso:country":"ES",
    "sg:address":"Calle de Federico Garcia Lorca, S/n",
    "sg:city":"Algeciras",
    "sg:orig_category":"Supermercados Y Hipermercados",
    "sg:phone":"+34 956 57 28 14",
    "sg:postcode":"11207",
    "sg:province":"C\u00e1diz",
    "wof:name":"Supermercados Algeciras S.l.",
    "wof:placetype":"venue"
},
  "geometry": {"coordinates":[-5.4530940056,36.1144485474],"type":"Point"}
}