{
  "type": "Feature",
  "properties": {
    "addr:full":"Calle de Juan Ramon Jimenez-a, 5 Melilla Melilla 52001",
    "addr:housenumber":"5",
    "addr:postcode":"52001",
    "addr:street":"Calle De Juan Ramon Jimenez-A",
    "iso:country":"ES",
    "sg:address":"Calle de Juan Ramon Jimenez-a, 5",
    "sg:city":"Melilla",
    "sg:orig_category":"Cl\u00cdnicas M\u00c9dicas",
    "sg:phone":"+34 952 68 62 66",
    "sg:postcode":"52001",
    "sg:province":"Melilla",
    "wof:name":"Cruz Roja Espa\u00f1ola-asamblea Provincial",
    "wof:placetype":"venue"
},
  "geometry": {"coordinates":[-2.9384961128,35.2966156006],"type":"Point"}
}