{
  "type": "Feature",
  "properties": {
    "addr:full":"Calle de Teodoro Alenda, 8 Aspe Alicante 03680",
    "addr:housenumber":"8",
    "addr:postcode":"03680",
    "addr:street":"Calle De Teodoro Alenda",
    "iso:country":"ES",
    "sg:address":"Calle de Teodoro Alenda, 8",
    "sg:city":"Aspe",
    "sg:orig_category":"Panader\u00cdas, Panader\u00cdas",
    "sg:phone":"+34 965 49 08 66",
    "sg:postcode":"03680",
    "sg:province":"Alicante",
    "wof:name":"Tallon Castillo Jose Maria",
    "wof:placetype":"venue"
},
  "geometry": {"coordinates":[-0.7681459785,38.345413208],"type":"Point"}
}