{
  "type": "Feature",
  "properties": {
    "iso:country":"ES",
    "sg:address":"Pg Ramon Berenguer Iii, S/n",
    "sg:city":"Mataro",
    "sg:orig_category":"Centros De Educaci\u00d3n Especial",
    "sg:phone":"+34 937 98 59 62",
    "sg:postcode":"08303",
    "sg:province":"Barcelona",
    "wof:name":"Colegio Nacional Tomas Vi\u00f1as",
    "wof:placetype":"venue"
},
  "geometry": {"coordinates":[2.4226949215,41.5361289978],"type":"Point"}
}