{
  "type": "Feature",
  "properties": {
    "iso:country":"ES",
    "sg:address":"Avda Kosme Bibanko Etxebarria, S/n",
    "sg:city":"Mimetiz",
    "sg:orig_category":"Zapatos (al Por Menor)",
    "sg:phone":"+34 946 39 16 17",
    "sg:postcode":"48860",
    "sg:province":"Vizcaya",
    "wof:name":"Beatriz Del Blanco Fernandez & Reberca Velarde Almirante",
    "wof:placetype":"venue"
},
  "geometry": {"coordinates":[-3.1336491108,43.2138938904],"type":"Point"}
}