{
  "type": "Feature",
  "properties": {
    "iso:country":"ES",
    "sg:address":"Calle de Lope De Vega, 3",
    "sg:city":"Cuatrovientos",
    "sg:orig_category":"Carnicer\u00cdas, Carnicer\u00cdas",
    "sg:phone":"+34 987 40 40 55",
    "sg:postcode":"24400",
    "sg:province":"Le\u00f3n",
    "wof:name":"Alvarez Alonso Severino",
    "wof:placetype":"venue"
},
  "geometry": {"coordinates":[-6.6229104996,42.5590286255],"type":"Point"}
}