{
  "type": "Feature",
  "properties": {
    "addr:full":"Calle de Canillas, 35 Madrid Madrid 28002",
    "addr:housenumber":"35",
    "addr:postcode":"madrid;28002",
    "addr:street":"Calle De Canillas",
    "iso:country":"ES",
    "sg:address":"Calle de Canillas, 35",
    "sg:city":"Madrid",
    "sg:orig_category":"Peluqueros: De Se\u00d1oras",
    "sg:phone":"+34 915 62 70 06",
    "sg:postcode":"28002",
    "sg:province":"Madrid",
    "sg:website":"www.hairdreams.com",
    "wof:name":"Garcia Reyes Rosario",
    "wof:placetype":"venue"
},
  "geometry": {"coordinates":[-3.6743781567,40.442489624],"type":"Point"}
}