{
  "type": "Feature",
  "properties": {
    "iso:country":"ES",
    "sg:address":"Salbatore Auzoa, 2",
    "sg:city":"Salbatore",
    "sg:orig_category":"Fabricaci\u00d3n De Mobiliario Met\u00c1lico",
    "sg:phone":"+34 943 88 21 00",
    "sg:postcode":"20200",
    "sg:province":"Guip\u00f9zcoa",
    "wof:name":"Caldereria Irurena S. A.",
    "wof:placetype":"venue"
},
  "geometry": {"coordinates":[-2.1944589615,43.0469207764],"type":"Point"}
}