{
  "type": "Feature",
  "properties": {
    "iso:country":"ES",
    "sg:address":"Poli Rubira Sola, S/n",
    "sg:city":"Macael",
    "sg:orig_category":"Empresas De Carpinter\u00cda Met\u00c1lica",
    "sg:phone":"+34 950 12 63 69",
    "sg:postcode":"04867",
    "sg:province":"Almer\u00eda",
    "wof:name":"Estructuras Macael",
    "wof:placetype":"venue"
},
  "geometry": {"coordinates":[-2.3024399281,37.3340568542],"type":"Point"}
}