{
  "type": "Feature",
  "properties": {
    "addr:full":"Calle de Castillo De Ucles, 8 Madrid Madrid 28037",
    "addr:housenumber":"8",
    "addr:postcode":"madrid;28037",
    "addr:street":"Calle De Castillo;Ucles",
    "iso:country":"ES",
    "sg:address":"Calle de Castillo De Ucles, 8",
    "sg:city":"Madrid",
    "sg:orig_category":"Inform\u00c1tica (estudios, Servicios, Asesor\u00cda, Formaci\u00d3n)",
    "sg:phone":"+34 913 75 74 10",
    "sg:postcode":"28037",
    "sg:province":"Madrid",
    "sg:website":"www.disoges.es",
    "wof:name":"Disoges S.l.",
    "wof:placetype":"venue"
},
  "geometry": {"coordinates":[-3.6276402473,40.4269294739],"type":"Point"}
}