{
  "type": "Feature",
  "properties": {
    "addr:full":"Av Llibertat, 22 Elche Alicante 03206",
    "addr:housenumber":"22",
    "addr:postcode":"03206",
    "addr:street":"Av Llibertat",
    "iso:country":"ES",
    "sg:address":"Av Llibertat, 22",
    "sg:city":"Elche",
    "sg:orig_category":"Fabricaci\u00d3n De Cortinas Y Visillos",
    "sg:phone":"+34 965 46 43 31",
    "sg:postcode":"03206",
    "sg:province":"Alicante",
    "wof:name":"Gines Cortinas S.l.",
    "wof:placetype":"venue"
},
  "geometry": {"coordinates":[-0.7030109763,38.2708396912],"type":"Point"}
}