{
  "type": "Feature",
  "properties": {
    "addr:full":"Rua Valle Inclan, 2 Ourense Ourense 32004",
    "addr:housenumber":"2",
    "addr:postcode":"32004",
    "addr:street":"Rua Valle Inclan",
    "iso:country":"ES",
    "sg:address":"Rua Valle Inclan, 2",
    "sg:city":"Ourense",
    "sg:orig_category":"Caf\u00c9s, Bares, Cervecer\u00cdas",
    "sg:phone":"+34 988 24 99 86",
    "sg:postcode":"32004",
    "sg:province":"Ourense",
    "wof:name":"Alonso Rodriguez Juan Manuel",
    "wof:placetype":"venue"
},
  "geometry": {"coordinates":[-7.861664772,42.3390007019],"type":"Point"}
}