{
  "type": "Feature",
  "properties": {
    "iso:country":"ES",
    "sg:address":"Carrer de Penedes, 3",
    "sg:city":"S. Andreu Llavaneres",
    "sg:orig_category":"Procuradores",
    "sg:phone":"+34 937 92 90 09",
    "sg:postcode":"08392",
    "sg:province":"Barcelona",
    "wof:name":"Mestres Coll Francesc",
    "wof:placetype":"venue"
},
  "geometry": {"coordinates":[2.4789459705,41.5705070496],"type":"Point"}
}