{
  "type": "Feature",
  "properties": {
    "addr:full":"Calle de Mayor, 53 Llano De Brujas Murcia 30161",
    "addr:housenumber":"53",
    "addr:postcode":"30161",
    "addr:street":"Calle De Mayor",
    "iso:country":"ES",
    "sg:address":"Calle de Mayor, 53",
    "sg:city":"Llano De Brujas",
    "sg:orig_category":"Molduras, Junquillos, Listones Y Molduras Perforadas",
    "sg:phone":"+34 968 81 10 60",
    "sg:postcode":"30161",
    "sg:province":"Murcia",
    "wof:name":"Alhama Nadal Juan",
    "wof:placetype":"venue"
},
  "geometry": {"coordinates":[-1.0705404282,38.0058059692],"type":"Point"}
}