{
  "type": "Feature",
  "properties": {
    "addr:full":"Pla\u00c7 Vila, 1 Vilanova I La Geltru Barcelona 08800",
    "addr:postcode":"08800",
    "iso:country":"ES",
    "sg:address":"Pla\u00c7 Vila, 1",
    "sg:city":"Vilanova I La Geltru",
    "sg:orig_category":"Relojer\u00cda (al Por Menor, Reparaci\u00d3n)",
    "sg:phone":"+34 938 93 00 89",
    "sg:postcode":"08800",
    "sg:province":"Barcelona",
    "wof:name":"Albi\u00f1ana Ferrando Roberto",
    "wof:placetype":"venue"
},
  "geometry": {"coordinates":[1.705232501,41.2381515503],"type":"Point"}
}