{
  "type": "Feature",
  "properties": {
    "addr:full":"Calle de Humanes, 9 Moraleja Enmedio Madrid 28950",
    "addr:housenumber":"9",
    "addr:postcode":"28950",
    "addr:street":"Calle De Humanes",
    "iso:country":"ES",
    "sg:address":"Calle de Humanes, 9",
    "sg:city":"Moraleja Enmedio",
    "sg:orig_category":"Cerrajer\u00cda, Ferrallista",
    "sg:phone":"+34 916 09 46 72",
    "sg:postcode":"28950",
    "sg:province":"Madrid",
    "wof:name":"Cerrajeria J.rojas S.l.",
    "wof:placetype":"venue"
},
  "geometry": {"coordinates":[-3.8576169014,40.2591514587],"type":"Point"}
}