{
  "type": "Feature",
  "properties": {
    "iso:country":"ES",
    "sg:address":"Calle de Marques De Santillana, 9",
    "sg:city":"Guadalajara",
    "sg:orig_category":"Pintura, Barniz, Productos Asimilables (fabricaci\u00d3n, Al Por Mayor)",
    "sg:phone":"+34 949 21 71 39",
    "sg:postcode":"19002",
    "sg:province":"Guadalajara",
    "wof:name":"Valdes Barahona Jose",
    "wof:placetype":"venue"
},
  "geometry": {"coordinates":[-3.1614809036,40.6279716492],"type":"Point"}
}