{
  "type": "Feature",
  "properties": {
    "addr:full":"Calle de Altamira, S/n Pueblo Nuevo C\u00e1diz 11360",
    "addr:housenumber":"s / n",
    "addr:postcode":"11360",
    "addr:street":"Calle De Altamira",
    "iso:country":"ES",
    "sg:address":"Calle de Altamira, S/n",
    "sg:city":"Pueblo Nuevo",
    "sg:orig_category":"Asesor\u00cda Fiscal Y Jur\u00cddica",
    "sg:phone":"+34 956 69 51 54",
    "sg:postcode":"11360",
    "sg:province":"C\u00e1diz",
    "wof:name":"C.t.c. Asociados S.c",
    "wof:placetype":"venue"
},
  "geometry": {"coordinates":[-5.3059587479,36.2952919006],"type":"Point"}
}