{
  "type": "Feature",
  "properties": {
    "addr:full":"Calle de Libertad, 7 Gijon Asturias 33206",
    "addr:housenumber":"7",
    "addr:postcode":"33206",
    "addr:street":"Calle De Libertad",
    "iso:country":"ES",
    "sg:address":"Calle de Libertad, 7",
    "sg:city":"Gijon",
    "sg:orig_category":"Peluqueros: De Se\u00d1oras",
    "sg:phone":"+34 985 35 34 39",
    "sg:postcode":"33206",
    "sg:province":"Asturias",
    "wof:name":"Perez Sorribas Jose Luis",
    "wof:placetype":"venue"
},
  "geometry": {"coordinates":[-5.6643190384,43.5410842896],"type":"Point"}
}