{
  "type": "Feature",
  "properties": {
    "iso:country":"ES",
    "sg:address":"Avda Gran Via, 19",
    "sg:city":"Caravaca Cruz",
    "sg:orig_category":"Molduras, Junquillos, Listones Y Molduras Perforadas",
    "sg:phone":"+34 968 70 85 84",
    "sg:postcode":"30400",
    "sg:province":"Murcia",
    "wof:name":"Lopez Reina Enrique",
    "wof:placetype":"venue"
},
  "geometry": {"coordinates":[-1.8619849682,38.1021194458],"type":"Point"}
}