{
  "type": "Feature",
  "properties": {
    "iso:country":"ES",
    "sg:address":"Francesc Mar, 1",
    "sg:city":"Altafulla",
    "sg:orig_category":"Inmobiliaria (agencias)",
    "sg:phone":"+34 977 65 00 97",
    "sg:postcode":"43893",
    "sg:province":"Tarragona",
    "wof:name":"Almirall Roig Nuria",
    "wof:placetype":"venue"
},
  "geometry": {"coordinates":[1.3789361715,41.1347198486],"type":"Point"}
}