{
  "type": "Feature",
  "properties": {
    "iso:country":"ES",
    "sg:address":"Pase Canalejas, 148",
    "sg:city":"Salamanca",
    "sg:orig_category":"Comercio, Reparaci\u00d3n De Motocicletas, Bicicletas Y Piezas Sueltas",
    "sg:phone":"+34 923 26 44 93",
    "sg:postcode":"37001",
    "sg:province":"Salamanca",
    "wof:name":"Martinez Gallego Antonio",
    "wof:placetype":"venue"
},
  "geometry": {"coordinates":[-5.6592440605,40.9616508484],"type":"Point"}
}