{
  "type": "Feature",
  "properties": {
    "iso:country":"ES",
    "sg:address":"Avda Motril, 1",
    "sg:city":"Salobre\u00f1a",
    "sg:orig_category":"Arquitectos",
    "sg:phone":"+34 958 61 08 84",
    "sg:postcode":"18680",
    "sg:province":"Granada",
    "wof:name":"Martinez Armada Jose Evaristo",
    "wof:placetype":"venue"
},
  "geometry": {"coordinates":[-3.5842061043,36.7456245422],"type":"Point"}
}