{
  "type": "Feature",
  "properties": {
    "addr:full":"Carrer de Pizarro, 6 Sant Feliu Llobregat Barcelona 08980",
    "addr:housenumber":"6",
    "addr:postcode":"08980",
    "addr:street":"Carrer De Pizarro",
    "iso:country":"ES",
    "sg:address":"Carrer de Pizarro, 6",
    "sg:city":"Sant Feliu Llobregat",
    "sg:orig_category":"Agentes Generales De Seguros",
    "sg:phone":"+34 936 85 14 33",
    "sg:postcode":"08980",
    "sg:province":"Barcelona",
    "wof:name":"Fernandez Moya Jose Manuel",
    "wof:placetype":"venue"
},
  "geometry": {"coordinates":[2.0455899239,41.3857536316],"type":"Point"}
}