{
  "type": "Feature",
  "properties": {
    "iso:country":"ES",
    "sg:address":"Calle de Cervantes, 10",
    "sg:city":"Bola\u00e7os De Calatrava",
    "sg:orig_category":"Muebles, Minoristas",
    "sg:phone":"+34 926 87 02 96",
    "sg:postcode":"13260",
    "sg:province":"Ciudad Real",
    "wof:name":"Camacho Gonzalez Juan",
    "wof:placetype":"venue"
},
  "geometry": {"coordinates":[-3.6709010601,38.9045181274],"type":"Point"}
}