{
  "type": "Feature",
  "properties": {
    "addr:full":"Rua Erin, 2 Pontevedra Pontevedra 36099",
    "addr:housenumber":"2",
    "addr:postcode":"36099",
    "addr:street":"Rua Erin",
    "iso:country":"ES",
    "sg:address":"Rua Erin, 2",
    "sg:city":"Pontevedra",
    "sg:orig_category":"Clubes, Asociaciones De Ocio",
    "sg:phone":"+34 986 86 47 57",
    "sg:postcode":"36099",
    "sg:province":"Pontevedra",
    "wof:name":"Migallas Teatro S.l.",
    "wof:placetype":"venue"
},
  "geometry": {"coordinates":[-8.6427993774,42.4304656982],"type":"Point"}
}