{
  "type": "Feature",
  "properties": {
    "iso:country":"ES",
    "sg:address":"Garcia K-hito, 1",
    "sg:city":"Villanueva Arzobispo",
    "sg:orig_category":"Venta, Montaje De Neum\u00c1ticos",
    "sg:phone":"+34 953 45 11 09",
    "sg:postcode":"23330",
    "sg:province":"Ja\u00e9n",
    "wof:name":"Fernandez-arroyo Sanchez Felix Cesar",
    "wof:placetype":"venue"
},
  "geometry": {"coordinates":[-3.005177021,38.172542572],"type":"Point"}
}