{
  "type": "Feature",
  "properties": {
    "addr:full":"Rua Remedios (dos), 27 Ourense Ourense 32002",
    "addr:housenumber":"27",
    "addr:postcode":"32002",
    "addr:street":"Rua Remedios Dos",
    "iso:country":"ES",
    "sg:address":"Rua Remedios (dos), 27",
    "sg:city":"Ourense",
    "sg:orig_category":"Quincaller\u00cda (al Por Menor)",
    "sg:phone":"+34 988 22 06 68",
    "sg:postcode":"32002",
    "sg:province":"Ourense",
    "wof:name":"Lemos Fernandez Jose Camilo",
    "wof:placetype":"venue"
},
  "geometry": {"coordinates":[-7.8744812012,42.3430862427],"type":"Point"}
}