{
  "type": "Feature",
  "properties": {
    "iso:country":"ES",
    "sg:address":"Germanies, 5",
    "sg:city":"Massanassa",
    "sg:orig_category":"Tapicer\u00cdas",
    "sg:phone":"+34 961 25 28 25",
    "sg:postcode":"46470",
    "sg:province":"Valencia",
    "wof:name":"Tapizados Garcia Pastor S.l.",
    "wof:placetype":"venue"
},
  "geometry": {"coordinates":[-0.4010930061,39.4107093811],"type":"Point"}
}