{
  "type": "Feature",
  "properties": {
    "addr:full":"Calle de Aguilar, 68 Puente-genil C\u00f3rdoba 14500",
    "addr:housenumber":"68",
    "addr:postcode":"14500",
    "addr:street":"Calle De Aguilar;Co\u0301Rdoba",
    "iso:country":"ES",
    "sg:address":"Calle de Aguilar, 68",
    "sg:city":"Puente-genil",
    "sg:orig_category":"Molduras, Junquillos, Listones Y Molduras Perforadas",
    "sg:phone":"+34 957 60 20 58",
    "sg:postcode":"14500",
    "sg:province":"C\u00f3rdoba",
    "wof:name":"Berral Rivas Eugenio",
    "wof:placetype":"venue"
},
  "geometry": {"coordinates":[-4.7739577293,37.3887557983],"type":"Point"}
}