{
  "type": "Feature",
  "properties": {
    "addr:full":"Calle de Antonio De Cabezon, 75 Madrid Madrid 28034",
    "addr:housenumber":"75",
    "addr:postcode":"madrid;28034",
    "addr:street":"Calle De Antonio De Cabezon",
    "iso:country":"ES",
    "sg:address":"Calle de Antonio De Cabezon, 75",
    "sg:city":"Madrid",
    "sg:orig_category":"Empresas De Carpinter\u00cda De Madera",
    "sg:phone":"+34 913 58 28 21",
    "sg:postcode":"28034",
    "sg:province":"Madrid",
    "wof:name":"Rodriguez Diaz Luis",
    "wof:placetype":"venue"
},
  "geometry": {"coordinates":[-3.6830201149,40.4994735718],"type":"Point"}
}