{
  "type": "Feature",
  "properties": {
    "addr:full":"Poligon Industrial Can Bas, 24 Can Bas Barcelona 08739",
    "addr:postcode":"08739",
    "iso:country":"ES",
    "sg:address":"Poligon Industrial Can Bas, 24",
    "sg:city":"Can Bas",
    "sg:orig_category":"Jardiner\u00cdas, Vegetales, Art\u00cdculos De Jardiner\u00cda (al Por Menor)",
    "sg:phone":"+34 938 99 46 09",
    "sg:postcode":"08739",
    "sg:province":"Barcelona",
    "sg:website":"www.rosaplanters.es",
    "wof:name":"Rosa Planters S.a.",
    "wof:placetype":"venue"
},
  "geometry": {"coordinates":[1.797145009,41.3847312927],"type":"Point"}
}