{
  "type": "Feature",
  "properties": {
    "iso:country":"ES",
    "sg:address":"Calle de San Juan De Avila, 11",
    "sg:city":"Almodovar Campo",
    "sg:orig_category":"Iglesia Cat\u00d3lica",
    "sg:phone":"+34 926 48 35 82",
    "sg:postcode":"13580",
    "sg:province":"Ciudad Real",
    "wof:name":"Parroquia Nuestra Se\u00f1ora De La Asuncion",
    "wof:placetype":"venue"
},
  "geometry": {"coordinates":[-4.178940773,38.7098503113],"type":"Point"}
}