{
  "type": "Feature",
  "properties": {
    "iso:country":"ES",
    "sg:address":"Calle de Lope De Vega, 19",
    "sg:city":"Herencia",
    "sg:orig_category":"Carnicer\u00cdas, Carnicer\u00cdas",
    "sg:phone":"+34 926 57 24 91",
    "sg:postcode":"13640",
    "sg:province":"Ciudad Real",
    "wof:name":"Juande Y Mari S L",
    "wof:placetype":"venue"
},
  "geometry": {"coordinates":[-3.3555181026,39.365814209],"type":"Point"}
}