{
  "type": "Feature",
  "properties": {
    "addr:full":"F P El Pali, 17 Bonares Huelva 21830",
    "addr:housenumber":"17",
    "addr:postcode":"21830",
    "addr:street":"Pali",
    "iso:country":"ES",
    "sg:address":"F P El Pali, 17",
    "sg:city":"Bonares",
    "sg:orig_category":"Plomeros",
    "sg:phone":"+34 959 36 60 91",
    "sg:postcode":"21830",
    "sg:province":"Huelva",
    "wof:name":"Perez Rodriguez Jose Manuel",
    "wof:placetype":"venue"
},
  "geometry": {"coordinates":[-6.6799907684,37.3241653442],"type":"Point"}
}