{
  "type": "Feature",
  "properties": {
    "iso:country":"ES",
    "sg:address":"Calle de Pedro De Dios, 6",
    "sg:city":"Alcolea",
    "sg:orig_category":"Reposter\u00cdas",
    "sg:phone":"+34 957 32 06 12",
    "sg:postcode":"14610",
    "sg:province":"C\u00f3rdoba",
    "wof:name":"Jimenez Jimenez Artesanos Del Pan S.l.",
    "wof:placetype":"venue"
},
  "geometry": {"coordinates":[-4.6731491089,37.9320755005],"type":"Point"}
}