{
  "type": "Feature",
  "properties": {
    "addr:full":"Calle de Perdiz (la), 210 Dominio De Fontenebro Madrid 28400",
    "addr:housenumber":"210",
    "addr:postcode":"28400",
    "addr:street":"Calle De Perdiz La",
    "iso:country":"ES",
    "sg:address":"Calle de Perdiz (la), 210",
    "sg:city":"Dominio De Fontenebro",
    "sg:orig_category":"Empresas De Desmonte",
    "sg:phone":"+34 918 50 67 95",
    "sg:postcode":"28400",
    "sg:province":"Madrid",
    "wof:name":"A.d. Excavaciones Y Voladuras S.l.",
    "wof:placetype":"venue"
},
  "geometry": {"coordinates":[-3.9671747684,40.6514701843],"type":"Point"}
}