{
  "type": "Feature",
  "properties": {
    "addr:full":"Avda Constitucion (de La), 12 Torrelavega Cantabria 39300",
    "addr:housenumber":"12",
    "addr:postcode":"39300",
    "addr:street":"Avda Constitucion De La",
    "iso:country":"ES",
    "sg:address":"Avda Constitucion (de La), 12",
    "sg:city":"Torrelavega",
    "sg:orig_category":"Ense\u00d1anza, Formaci\u00d3n Profesional: Aprendizaje",
    "sg:phone":"+34 942 80 02 52",
    "sg:postcode":"39300",
    "sg:province":"Cantabria",
    "wof:name":"Gobierno De Cantabria",
    "wof:placetype":"venue"
},
  "geometry": {"coordinates":[-4.0486950874,43.3459968567],"type":"Point"}
}