{
  "type": "Feature",
  "properties": {
    "addr:full":"Ctra Madrid, S/n Valverde La Rioja 26528",
    "addr:housenumber":"s / n",
    "addr:postcode":"26528",
    "addr:street":"Ctra Madrid;Rioja",
    "iso:country":"ES",
    "sg:address":"Ctra Madrid, S/n",
    "sg:city":"Valverde",
    "sg:orig_category":"Fabrica De Cer\u00c1micas",
    "sg:phone":"+34 941 19 81 61",
    "sg:postcode":"26528",
    "sg:province":"La Rioja",
    "wof:name":"Ceramicas Del Rio Alhama S.l.",
    "wof:placetype":"venue"
},
  "geometry": {"coordinates":[-1.8622200489,41.981136322],"type":"Point"}
}