{
  "type": "Feature",
  "properties": {
    "addr:full":"Calle de Moros, 39 Gijon Asturias 33206",
    "addr:housenumber":"39",
    "addr:postcode":"33206",
    "addr:street":"Calle De Moros",
    "iso:country":"ES",
    "sg:address":"Calle de Moros, 39",
    "sg:city":"Gijon",
    "sg:orig_category":"Psicoterapeutas",
    "sg:phone":"+34 985 17 27 52",
    "sg:postcode":"33206",
    "sg:province":"Asturias",
    "wof:name":"Instituto Psintesis De Dpsicoterapia Investigacion Y Docencia Para La Salud Mental",
    "wof:placetype":"venue"
},
  "geometry": {"coordinates":[-5.6629590988,43.5404624939],"type":"Point"}
}