{
  "type": "Feature",
  "properties": {
    "iso:country":"ES",
    "sg:address":"Avda Bilbao, 10",
    "sg:city":"Ortuella",
    "sg:orig_category":"Frutas, Legumbres Frescas Y Tempranas (al Por Menor)",
    "sg:phone":"+34 946 64 24 37",
    "sg:postcode":"48530",
    "sg:province":"Vizcaya",
    "wof:name":"Crespo Sanz Javier",
    "wof:placetype":"venue"
},
  "geometry": {"coordinates":[-3.05230093,43.3084182739],"type":"Point"}
}