{
  "type": "Feature",
  "properties": {
    "addr:full":"Calle de Zubieta, 14 Donostia-san Sebastian Guip\u00f9zcoa 20007",
    "addr:housenumber":"14",
    "addr:postcode":"20007",
    "addr:street":"Calle De Zubieta",
    "iso:country":"ES",
    "sg:address":"Calle de Zubieta, 14",
    "sg:city":"Donostia-san Sebastian",
    "sg:orig_category":"Doctores En Medicina",
    "sg:phone":"+34 943 42 87 50",
    "sg:postcode":"20007",
    "sg:province":"Guip\u00f9zcoa",
    "wof:name":"Arriola Iriondo Francisco Javier",
    "wof:placetype":"venue"
},
  "geometry": {"coordinates":[-1.9856988192,43.317035675],"type":"Point"}
}