{
  "type": "Feature",
  "properties": {
    "addr:full":"Calle de Sol (el), 3 Hellin Albacete 02400",
    "addr:housenumber":"3",
    "addr:postcode":"02400",
    "addr:street":"Calle De Sol El",
    "iso:country":"ES",
    "sg:address":"Calle de Sol (el), 3",
    "sg:city":"Hellin",
    "sg:orig_category":"Centros De Coordinaci\u00d3n",
    "sg:phone":"+34 967 30 45 24",
    "sg:postcode":"02400",
    "sg:province":"Albacete",
    "wof:name":"Zamorano Andres Francisco Jose",
    "wof:placetype":"venue"
},
  "geometry": {"coordinates":[-1.7014559507,38.5107383728],"type":"Point"}
}