{
  "type": "Feature",
  "properties": {
    "iso:country":"ES",
    "sg:address":"Calle de Cristo Baja, 21",
    "sg:city":"Torreperogil",
    "sg:orig_category":"Empresas De Carpinter\u00cda De Madera",
    "sg:phone":"+34 953 77 63 62",
    "sg:postcode":"23320",
    "sg:province":"Ja\u00e9n",
    "wof:name":"Villar Fernandez Manuel",
    "wof:placetype":"venue"
},
  "geometry": {"coordinates":[-3.2869029045,38.0337600708],"type":"Point"}
}