{
  "type": "Feature",
  "properties": {
    "addr:full":"Avda Mediterraneo (del), 94 Rincon Victoria M\u00e1laga 29730",
    "addr:housenumber":"94",
    "addr:postcode":"29730",
    "addr:street":"Avda Mediterraneo Del;Ma\u0301Laga",
    "iso:country":"ES",
    "sg:address":"Avda Mediterraneo (del), 94",
    "sg:city":"Rincon Victoria",
    "sg:orig_category":"Inmobiliaria (agencias)",
    "sg:phone":"+34 952 97 03 67",
    "sg:postcode":"29730",
    "sg:province":"M\u00e1laga",
    "wof:name":"Inversiones Danyser S.l.",
    "wof:placetype":"venue"
},
  "geometry": {"coordinates":[-4.2868151665,36.7152824402],"type":"Point"}
}