{
  "type": "Feature",
  "properties": {
    "iso:country":"ES",
    "sg:address":"Sol, 43",
    "sg:city":"Sedavi",
    "sg:orig_category":"Ense\u00d1ante, Direcci\u00d3n",
    "sg:phone":"+34 963 75 54 24",
    "sg:postcode":"46910",
    "sg:province":"Valencia",
    "wof:name":"Molina Garcia Alejandro",
    "wof:placetype":"venue"
},
  "geometry": {"coordinates":[-0.38429299,39.4245414734],"type":"Point"}
}