{
  "type": "Feature",
  "properties": {
    "iso:country":"ES",
    "sg:address":"Rua Enrique Lorenzo, 25",
    "sg:city":"Vigo",
    "sg:orig_category":"Administraci\u00d3n En El Medio Ambiente",
    "sg:phone":"+34 986 26 41 93",
    "sg:postcode":"36207",
    "sg:province":"Pontevedra",
    "wof:name":"Teixugo Sociedad Cooperativa Galega",
    "wof:placetype":"venue"
},
  "geometry": {"coordinates":[-8.6996793747,42.2492904663],"type":"Point"}
}