{
  "type": "Feature",
  "properties": {
    "addr:full":"Calle de Carmen, 21 Cabezo Torres Murcia 30110",
    "addr:housenumber":"21",
    "addr:postcode":"30110",
    "addr:street":"Calle De Carmen",
    "iso:country":"ES",
    "sg:address":"Calle de Carmen, 21",
    "sg:city":"Cabezo Torres",
    "sg:orig_category":"Sociedades, Compa\u00d1\u00cdas Aseguradoras",
    "sg:phone":"+34 968 89 97 31",
    "sg:postcode":"30110",
    "sg:province":"Murcia",
    "wof:name":"Sanchez Valverde Francisco",
    "wof:placetype":"venue"
},
  "geometry": {"coordinates":[-1.1244838238,38.0247535706],"type":"Point"}
}