{
  "type": "Feature",
  "properties": {
    "addr:full":"Calle de Azorin, 38 Torrent Valencia 46900",
    "addr:housenumber":"38",
    "addr:postcode":"46900",
    "addr:street":"Calle De Azorin;Valencia",
    "iso:country":"ES",
    "sg:address":"Calle de Azorin, 38",
    "sg:city":"Torrent",
    "sg:orig_category":"\u00d3ptica: Instrumentos (fabricaci\u00d3n)",
    "sg:phone":"+34 961 56 71 19",
    "sg:postcode":"46900",
    "sg:province":"Valencia",
    "wof:name":"Nova Visio Torrent S.l.",
    "wof:placetype":"venue"
},
  "geometry": {"coordinates":[-0.4787521064,39.4334983826],"type":"Point"}
}