{
  "type": "Feature",
  "properties": {
    "addr:full":"Calle de Jose Lopez Rodriguez, 9 S. Fernando C\u00e1diz 11100",
    "addr:housenumber":"9",
    "addr:postcode":"11100",
    "addr:street":"Calle De Jose Lopez Rodriguez;S. Fernando Ca\u0301Diz",
    "iso:country":"ES",
    "sg:address":"Calle de Jose Lopez Rodriguez, 9",
    "sg:city":"S. Fernando",
    "sg:orig_category":"Molduras, Junquillos, Listones Y Molduras Perforadas",
    "sg:phone":"+34 956 89 46 36",
    "sg:postcode":"11100",
    "sg:province":"C\u00e1diz",
    "wof:name":"Pua Traverso Joaquin",
    "wof:placetype":"venue"
},
  "geometry": {"coordinates":[-6.1990680695,36.4650840759],"type":"Point"}
}