{
  "type": "Feature",
  "properties": {
    "addr:full":"Calle de Sombrereria, 6 Burgos Burgos 09003",
    "addr:housenumber":"6",
    "addr:postcode":"09003",
    "addr:street":"Calle De Sombrereria",
    "iso:country":"ES",
    "sg:address":"Calle de Sombrereria, 6",
    "sg:city":"Burgos",
    "sg:orig_category":"Molduras, Junquillos, Listones Y Molduras Perforadas",
    "sg:phone":"+34 947 20 93 96",
    "sg:postcode":"09003",
    "sg:province":"Burgos",
    "wof:name":"Alonso Palacios Roberto",
    "wof:placetype":"venue"
},
  "geometry": {"coordinates":[-3.7028217316,42.3409843445],"type":"Point"}
}