{
  "type": "Feature",
  "properties": {
    "iso:country":"ES",
    "sg:address":"Avda Bilbao, 3",
    "sg:city":"Ortuella",
    "sg:orig_category":"T\u00c9cnicos Veterinarios",
    "sg:phone":"+34 946 35 36 55",
    "sg:postcode":"48530",
    "sg:province":"Vizcaya",
    "wof:name":"Llano Hernaiz Koldo Andoni",
    "wof:placetype":"venue"
},
  "geometry": {"coordinates":[-3.0514819622,43.3080787659],"type":"Point"}
}