{
  "type": "Feature",
  "properties": {
    "iso:country":"ES",
    "sg:address":"Calle de Juan Ramon Jimenez, 46",
    "sg:city":"Arjonilla",
    "sg:orig_category":"Material Y Herramientas Agr\u00cdcolas",
    "sg:phone":"+34 953 52 11 30",
    "sg:postcode":"23750",
    "sg:province":"Ja\u00e9n",
    "wof:name":"Talleres Hermanos Rueda Carmona C.b.",
    "wof:placetype":"venue"
},
  "geometry": {"coordinates":[-4.111137867,37.9737586975],"type":"Point"}
}