{
  "type": "Feature",
  "properties": {
    "addr:full":"Plaz Bartolome Peralbo, 1 Villaralto C\u00f3rdoba 14490",
    "addr:housenumber":"1",
    "addr:postcode":"14490",
    "addr:street":"Bartolome Peralbo",
    "iso:country":"ES",
    "sg:address":"Plaz Bartolome Peralbo, 1",
    "sg:city":"Villaralto",
    "sg:orig_category":"Cajas Para Embalar",
    "sg:phone":"+34 957 15 00 31",
    "sg:postcode":"14490",
    "sg:province":"C\u00f3rdoba",
    "sg:website":"www.cajacordoba.es",
    "wof:name":"Caja Rural De Cordoba",
    "wof:placetype":"venue"
},
  "geometry": {"coordinates":[-4.9840669632,38.4559707642],"type":"Point"}
}