{
  "type": "Feature",
  "properties": {
    "addr:full":"Calle de San Atilano, 8 Zamora Zamora 49003",
    "addr:housenumber":"8",
    "addr:postcode":"49003",
    "addr:street":"Calle De San Atilano",
    "iso:country":"ES",
    "sg:address":"Calle de San Atilano, 8",
    "sg:city":"Zamora",
    "sg:orig_category":"Telas Y Sedas (al Por Menor)",
    "sg:phone":"+34 980 53 19 17",
    "sg:postcode":"49003",
    "sg:province":"Zamora",
    "wof:name":"Toston Ferreras Dimas",
    "wof:placetype":"venue"
},
  "geometry": {"coordinates":[-5.7439599037,41.5038642883],"type":"Point"}
}