{
  "type": "Feature",
  "properties": {
    "iso:country":"ES",
    "sg:address":"Pol. Ind., 7",
    "sg:city":"Azuaga",
    "sg:orig_category":"Cerrajer\u00cda, Ferrallista",
    "sg:phone":"+34 924 89 26 77",
    "sg:postcode":"06920",
    "sg:province":"Badajoz",
    "wof:name":"Cerrajeria Azuague\u00f1a S.c.l.",
    "wof:placetype":"venue"
},
  "geometry": {"coordinates":[-5.679046154,38.2603721619],"type":"Point"}
}