{
  "type": "Feature",
  "properties": {
    "addr:full":"Carrer de Ancora (l'), 1 Altea Alicante 03590",
    "addr:housenumber":"1",
    "addr:postcode":"03590",
    "addr:street":"Carrer De Ancora L '",
    "iso:country":"ES",
    "sg:address":"Carrer de Ancora (l'), 1",
    "sg:city":"Altea",
    "sg:orig_category":"Empresas De Carpinter\u00cda De Madera",
    "sg:phone":"+34 965 84 47 65",
    "sg:postcode":"03590",
    "sg:province":"Alicante",
    "wof:name":"Agullo Cabrera Francisco",
    "wof:placetype":"venue"
},
  "geometry": {"coordinates":[-0.0718377009,38.562953949],"type":"Point"}
}