{
  "type": "Feature",
  "properties": {
    "iso:country":"ES",
    "sg:address":"Calle de Nu\u00d1ez Morgado, 3",
    "sg:city":"Madrid",
    "sg:orig_category":"Centros Empresariales",
    "sg:phone":"+34 913 23 56 08",
    "sg:postcode":"28036",
    "sg:province":"Madrid",
    "wof:name":"Jurisplus Ediciones Juridicas Online S.l.",
    "wof:placetype":"venue"
},
  "geometry": {"coordinates":[-3.685240984,40.4688339233],"type":"Point"}
}