{
  "type": "Feature",
  "properties": {
    "iso:country":"ES",
    "sg:address":"Calle de Klaudio Gallastegi, 1",
    "sg:city":"Elorrio",
    "sg:orig_category":"Polideportivos",
    "sg:phone":"+34 946 82 10 27",
    "sg:postcode":"48230",
    "sg:province":"Vizcaya",
    "wof:name":"Emtesport S.l.",
    "wof:placetype":"venue"
},
  "geometry": {"coordinates":[-2.5407700539,43.1305198669],"type":"Point"}
}