{
  "type": "Feature",
  "properties": {
    "iso:country":"ES",
    "sg:address":"Compostilla, 2",
    "sg:city":"Ponferrada",
    "sg:orig_category":"Empresarios",
    "sg:phone":"+34 987 40 35 92",
    "sg:postcode":"24400",
    "sg:province":"Le\u00f3n",
    "wof:name":"Fundacion Las Medulas",
    "wof:placetype":"venue"
},
  "geometry": {"coordinates":[-6.5981898308,42.5488624573],"type":"Point"}
}