{
  "type": "Feature",
  "properties": {
    "addr:full":"Avda Ribeira (da), 1 Foz Lugo 27780",
    "addr:housenumber":"1",
    "addr:postcode":"27780",
    "addr:street":"Avda Ribeira Da",
    "iso:country":"ES",
    "sg:address":"Avda Ribeira (da), 1",
    "sg:city":"Foz",
    "sg:orig_category":"Iglesia Cat\u00d3lica",
    "sg:phone":"+34 982 14 01 33",
    "sg:postcode":"27780",
    "sg:province":"Lugo",
    "wof:name":"Obispado De Mondo\u00d1edo-ferrol",
    "wof:placetype":"venue"
},
  "geometry": {"coordinates":[-7.2546539307,43.5672912598],"type":"Point"}
}