{
  "type": "Feature",
  "properties": {
    "addr:full":"Calle de Salitre, 8 Malaga M\u00e1laga 29002",
    "addr:housenumber":"8",
    "addr:postcode":"29002",
    "addr:street":"Calle De Salitre;Ma\u0301Laga",
    "iso:country":"ES",
    "sg:address":"Calle de Salitre, 8",
    "sg:city":"Malaga",
    "sg:orig_category":"Transportes Por Carretera: Lotes Completos, Mercanc\u00cdas Diversas",
    "sg:phone":"+34 952 32 41 42",
    "sg:postcode":"29002",
    "sg:province":"M\u00e1laga",
    "wof:name":"Ortega Perea Juan",
    "wof:placetype":"venue"
},
  "geometry": {"coordinates":[-4.426887989,36.7141952515],"type":"Point"}
}