{
  "type": "Feature",
  "properties": {
    "iso:country":"ES",
    "sg:address":"Carretera De Villarreal, Km. 0004,0",
    "sg:city":"Olivenza",
    "sg:orig_category":"Producci\u00d3n, Venta De Productos De Agricultura Biol\u00d3gica",
    "sg:phone":"+34 924 14 03 73",
    "sg:postcode":"06100",
    "sg:province":"Badajoz",
    "wof:name":"Figueroa Castro Jaime",
    "wof:placetype":"venue"
},
  "geometry": {"coordinates":[-7.0980839729,38.6843605042],"type":"Point"}
}