{
  "type": "Feature",
  "properties": {
    "iso:country":"ES",
    "sg:address":"Calle de Churruca, 4",
    "sg:city":"Alacant",
    "sg:orig_category":"Zapatos (al Por Menor)",
    "sg:phone":"+34 965 12 46 10",
    "sg:postcode":"03003",
    "sg:province":"Alicante",
    "wof:name":"Hurtado Carreres Antonio",
    "wof:placetype":"venue"
},
  "geometry": {"coordinates":[-0.4911535084,38.3390426636],"type":"Point"}
}