{
  "type": "Feature",
  "properties": {
    "addr:full":"Carrer de Pompeu Fabra, 86 Terrassa Barcelona 08226",
    "addr:housenumber":"86",
    "addr:postcode":"08226",
    "addr:street":"Carrer De Pompeu Fabra",
    "iso:country":"ES",
    "sg:address":"Carrer de Pompeu Fabra, 86",
    "sg:city":"Terrassa",
    "sg:orig_category":"Confecci\u00d3n : Material, Suministros Y Accesorios",
    "sg:phone":"+34 937 31 07 62",
    "sg:postcode":"08226",
    "sg:province":"Barcelona",
    "wof:name":"Fornitures Egara",
    "wof:placetype":"venue"
},
  "geometry": {"coordinates":[2.0241260529,41.5760536194],"type":"Point"}
}