{
  "type": "Feature",
  "properties": {
    "addr:full":"Avda Principe De Asturias, 43 Zamora Zamora 49029",
    "addr:housenumber":"43",
    "addr:postcode":"49029",
    "addr:street":"Avda Principe De Asturias",
    "iso:country":"ES",
    "sg:address":"Avda Principe De Asturias, 43",
    "sg:city":"Zamora",
    "sg:orig_category":"Alquiler De Casas Y Habitaciones Amuebladas",
    "sg:phone":"+34 980 52 21 50",
    "sg:postcode":"49029",
    "sg:province":"Zamora",
    "wof:name":"Atlanta Hotels S.l.",
    "wof:placetype":"venue"
},
  "geometry": {"coordinates":[-5.7365636826,41.5118942261],"type":"Point"}
}