{
  "type": "Feature",
  "properties": {
    "addr:full":"Rond Era Del Lucio, 4 Guardamar Segura Alicante 03140",
    "addr:housenumber":"4",
    "addr:postcode":"03140",
    "addr:street":"Era;Lucio",
    "iso:country":"ES",
    "sg:address":"Rond Era Del Lucio, 4",
    "sg:city":"Guardamar Segura",
    "sg:orig_category":"Laboratorios Y Cl\u00cdnicas Veterinarias",
    "sg:phone":"+34 965 72 78 17",
    "sg:postcode":"03140",
    "sg:province":"Alicante",
    "wof:name":"Clinica Veterinaria San Anton S.l.",
    "wof:placetype":"venue"
},
  "geometry": {"coordinates":[-0.6540290117,38.086681366],"type":"Point"}
}