{
  "type": "Feature",
  "properties": {
    "addr:full":"Calle de San Martin, 23 Valladolid Valladolid 47003",
    "addr:housenumber":"23",
    "addr:postcode":"47003",
    "addr:street":"Calle De San Martin",
    "iso:country":"ES",
    "sg:address":"Calle de San Martin, 23",
    "sg:city":"Valladolid",
    "sg:orig_category":"Art\u00cdculos De Regalo (al Por Menor)",
    "sg:phone":"+34 983 26 50 79",
    "sg:postcode":"47003",
    "sg:province":"Valladolid",
    "wof:name":"Mayordomo Arroyo Eustaquia",
    "wof:placetype":"venue"
},
  "geometry": {"coordinates":[-4.7222590446,41.6562309265],"type":"Point"}
}