{
  "type": "Feature",
  "properties": {
    "addr:full":"Calle de Emilio Castelar, 45 Novelda Alicante 03660",
    "addr:housenumber":"45",
    "addr:postcode":"03660",
    "addr:street":"Calle De Emilio Castelar",
    "iso:country":"ES",
    "sg:address":"Calle de Emilio Castelar, 45",
    "sg:city":"Novelda",
    "sg:orig_category":"Productos Qu\u00cdmicos (fabricaci\u00d3n, Al Por Mayor)",
    "sg:phone":"+34 965 60 28 31",
    "sg:postcode":"03660",
    "sg:province":"Alicante",
    "wof:name":"Rizo Chico De Guzman Wilfredo",
    "wof:placetype":"venue"
},
  "geometry": {"coordinates":[-0.7669119835,38.385055542],"type":"Point"}
}