{
  "type": "Feature",
  "properties": {
    "iso:country":"ES",
    "sg:address":"Calle de Toro, 22",
    "sg:city":"Madridanos",
    "sg:orig_category":"Suministros Y Colocaci\u00d3n De Canalones Para Aguas Pluviales",
    "sg:phone":"+34 980 57 66 15",
    "sg:postcode":"49157",
    "sg:province":"Zamora",
    "wof:name":"Asensio San Esteban David",
    "wof:placetype":"venue"
},
  "geometry": {"coordinates":[-5.6023640633,41.4797935486],"type":"Point"}
}