{
  "type": "Feature",
  "properties": {
    "iso:country":"ES",
    "sg:address":"Carrer de Carril, 15",
    "sg:city":"Can Sant Joan",
    "sg:orig_category":"Imprenta",
    "sg:phone":"+34 935 75 07 37",
    "sg:postcode":"08110",
    "sg:province":"Barcelona",
    "wof:name":"Graficas Rimont S.a.",
    "wof:placetype":"venue"
},
  "geometry": {"coordinates":[2.1859691143,41.4872894287],"type":"Point"}
}