{
  "type": "Feature",
  "properties": {
    "iso:country":"ES",
    "sg:address":"Calle de Veintiocho De Febrero, 28",
    "sg:city":"Moriles",
    "sg:orig_category":"Vinos Y Licores (venta Al Por Menor)",
    "sg:phone":"+34 957 53 71 06",
    "sg:postcode":"14510",
    "sg:province":"C\u00f3rdoba",
    "wof:name":"Cooperativa Olivarera Y Vitivinicola San Jeronimo",
    "wof:placetype":"venue"
},
  "geometry": {"coordinates":[-4.6114587784,37.4354095459],"type":"Point"}
}