{
  "type": "Feature",
  "properties": {
    "iso:country":"ES",
    "sg:address":"Avda Doctor Peset Aleixandre, 76",
    "sg:city":"Valencia",
    "sg:orig_category":"M\u00c1quinas De Coser Y De Hacer Punto (al Por Mayor)",
    "sg:phone":"+34 963 47 11 25",
    "sg:postcode":"46025",
    "sg:province":"Valencia",
    "wof:name":"Escriche Conejos Casimiro",
    "wof:placetype":"venue"
},
  "geometry": {"coordinates":[-0.3810150027,39.4906349182],"type":"Point"}
}