{
  "type": "Feature",
  "properties": {
    "addr:full":"Calle de Fuente, 36 Higuera Real Badajoz 06350",
    "addr:housenumber":"36",
    "addr:postcode":"06350",
    "addr:street":"Calle De Fuente",
    "iso:country":"ES",
    "sg:address":"Calle de Fuente, 36",
    "sg:city":"Higuera Real",
    "sg:orig_category":"Supermercados Y Hipermercados",
    "sg:phone":"+34 924 72 31 14",
    "sg:postcode":"06350",
    "sg:province":"Badajoz",
    "wof:name":"Dominguez Ruiz Jesus",
    "wof:placetype":"venue"
},
  "geometry": {"coordinates":[-6.689040184,38.1440429688],"type":"Point"}
}