{
  "type": "Feature",
  "properties": {
    "addr:full":"Calle de San Pedro, S/n Lezaun Navarra 31177",
    "addr:postcode":"31177",
    "addr:street":"Calle De San Pedro S / N Lezaun Navarra",
    "iso:country":"ES",
    "sg:address":"Calle de San Pedro, S/n",
    "sg:city":"Lezaun",
    "sg:orig_category":"Iglesia Cat\u00d3lica",
    "sg:phone":"+34 948 54 20 23",
    "sg:postcode":"31177",
    "sg:province":"Navarra",
    "wof:name":"Parroquia De San Pedro",
    "wof:placetype":"venue"
},
  "geometry": {"coordinates":[-1.9935070276,42.7767944336],"type":"Point"}
}