{
  "type": "Feature",
  "properties": {
    "iso:country":"ES",
    "sg:address":"Cami Piscina, S/n",
    "sg:city":"La Vilella Baixa",
    "sg:orig_category":"Ca\u00d1a, Mimbre Y Bamb\u00da",
    "sg:phone":"+34 977 83 94 28",
    "sg:postcode":"43374",
    "sg:province":"Tarragona",
    "sg:website":"www.viaplana.com",
    "wof:name":"Palmes Vilaplana S.l.",
    "wof:placetype":"venue"
},
  "geometry": {"coordinates":[0.7634770274,41.2205848694],"type":"Point"}
}