{
  "type": "Feature",
  "properties": {
    "iso:country":"ES",
    "sg:address":"Avda Juan Andres, 18",
    "sg:city":"Madrid",
    "sg:orig_category":"Alimentaci\u00d3n General (al Por Menor)",
    "sg:phone":"+34 913 16 10 93",
    "sg:postcode":"28035",
    "sg:province":"Madrid",
    "wof:name":"Nehme Zaidan Ali",
    "wof:placetype":"venue"
},
  "geometry": {"coordinates":[-3.7227039337,40.4678001404],"type":"Point"}
}