{
  "type": "Feature",
  "properties": {
    "addr:full":"Calle de Pedro Funes, 14 Porcuna Ja\u00e9n 23790",
    "addr:housenumber":"14",
    "addr:postcode":"23790",
    "addr:street":"Calle De Pedro Funes",
    "iso:country":"ES",
    "sg:address":"Calle de Pedro Funes, 14",
    "sg:city":"Porcuna",
    "sg:orig_category":"Empresas De Carpinter\u00cda Met\u00c1lica",
    "sg:phone":"+34 953 54 44 24",
    "sg:postcode":"23790",
    "sg:province":"Ja\u00e9n",
    "wof:name":"Diaz Callado Juan Francisco",
    "wof:placetype":"venue"
},
  "geometry": {"coordinates":[-4.1838459969,37.8739051819],"type":"Point"}
}