{
  "type": "Feature",
  "properties": {
    "iso:country":"ES",
    "sg:address":"Calle de Cortijo De Las Casillas, 10",
    "sg:city":"Sevilla",
    "sg:orig_category":"Ropa Para Se\u00d1oras Y Caballeros (al Por Menor)",
    "sg:phone":"+34 954 94 46 20",
    "sg:postcode":"41008",
    "sg:province":"Sevilla",
    "wof:name":"Cuevas Delgado Maria Rosalia",
    "wof:placetype":"venue"
},
  "geometry": {"coordinates":[-5.962823391,37.418888092],"type":"Point"}
}