{
  "type": "Feature",
  "properties": {
    "iso:country":"ES",
    "sg:address":"Calle de Jover, 13",
    "sg:city":"Castellon",
    "sg:orig_category":"Lencer\u00cda Femenina, Corseter\u00cda, Trajes De Ba\u00d1o (al Por Menor)",
    "sg:phone":"+34 964 23 83 67",
    "sg:postcode":"12002",
    "sg:province":"Castell\u00f3n",
    "wof:name":"Martinez Serra Carmen",
    "wof:placetype":"venue"
},
  "geometry": {"coordinates":[-0.0399559997,39.9811134338],"type":"Point"}
}