{
  "type": "Feature",
  "properties": {
    "addr:full":"Avda Media Legua, 20 Media Legua Murcia 30565",
    "addr:housenumber":"20",
    "addr:postcode":"30565",
    "addr:street":"Avda Media Legua",
    "iso:country":"ES",
    "sg:address":"Avda Media Legua, 20",
    "sg:city":"Media Legua",
    "sg:orig_category":"Agencias Y Agentes Comerciales, Representantes",
    "sg:phone":"+34 968 62 39 30",
    "sg:postcode":"30565",
    "sg:province":"Murcia",
    "wof:name":"Herpesa Comercial Ganadera S. L.",
    "wof:placetype":"venue"
},
  "geometry": {"coordinates":[-0.9454141259,37.6093254089],"type":"Point"}
}