{
  "type": "Feature",
  "properties": {
    "addr:full":"Calle de Rio Manzanares, 4 Alcala Henares Madrid 28803",
    "addr:housenumber":"4",
    "addr:postcode":"28803",
    "addr:street":"Calle De Rio Manzanares",
    "iso:country":"ES",
    "sg:address":"Calle de Rio Manzanares, 4",
    "sg:city":"Alcala Henares",
    "sg:orig_category":"Barquillos De Miel (fabricaci\u00d3n)",
    "sg:phone":"+34 918 82 53 59",
    "sg:postcode":"28803",
    "sg:province":"Madrid",
    "wof:name":"Mancomunidad De Propietarios Alcatorre",
    "wof:placetype":"venue"
},
  "geometry": {"coordinates":[-3.3645300865,40.4730300903],"type":"Point"}
}