{
  "type": "Feature",
  "properties": {
    "iso:country":"ES",
    "sg:address":"C/ Ramal, Des, 30",
    "sg:city":"Alaior",
    "sg:orig_category":"Bisuter\u00cda, Joyer\u00cda, Relojer\u00cda (al Por Menor)",
    "sg:phone":"+34 971 37 13 78",
    "sg:postcode":"07730",
    "sg:province":"Islas Baleares",
    "wof:name":"Relojeria Vinent S.l.",
    "wof:placetype":"venue"
},
  "geometry": {"coordinates":[4.1400952339,39.930721283],"type":"Point"}
}