{
  "type": "Feature",
  "properties": {
    "addr:full":"Calle de Montijo, 4 Catedral Murcia 30001",
    "addr:housenumber":"4",
    "addr:postcode":"30001",
    "addr:street":"Calle De Montijo",
    "iso:country":"ES",
    "sg:address":"Calle de Montijo, 4",
    "sg:city":"Catedral",
    "sg:orig_category":"Centros Empresariales",
    "sg:phone":"+34 968 22 28 71",
    "sg:postcode":"30001",
    "sg:province":"Murcia",
    "wof:name":"Cygea S.l.",
    "wof:placetype":"venue"
},
  "geometry": {"coordinates":[-1.1281930208,37.985710144],"type":"Point"}
}