{
  "type": "Feature",
  "properties": {
    "addr:full":"Cerde\u00f1o, 41 Cerde\u00d1o Asturias 33010",
    "addr:housenumber":"41",
    "addr:postcode":"33010",
    "addr:street":"Cerden\u0303O;Asturias",
    "iso:country":"ES",
    "sg:address":"Cerde\u00f1o, 41",
    "sg:city":"Cerde\u00d1o",
    "sg:orig_category":"Mec\u00c1nico Del Autom\u00d3vil",
    "sg:phone":"+34 985 29 76 05",
    "sg:postcode":"33010",
    "sg:province":"Asturias",
    "wof:name":"Comercio Y Asistencia S.a.",
    "wof:placetype":"venue"
},
  "geometry": {"coordinates":[-5.8143019676,43.3724250793],"type":"Point"}
}