{
  "type": "Feature",
  "properties": {
    "iso:country":"ES",
    "sg:address":"Carrer de Filharmonica (la), 1",
    "sg:city":"Altea",
    "sg:orig_category":"Doctores En Medicina",
    "sg:phone":"+34 965 84 05 20",
    "sg:postcode":"03590",
    "sg:province":"Alicante",
    "wof:name":"Ferrer Llopis Maria Vicenta",
    "wof:placetype":"venue"
},
  "geometry": {"coordinates":[-0.0484010018,38.599899292],"type":"Point"}
}