{
  "type": "Feature",
  "properties": {
    "iso:country":"ES",
    "sg:address":"Avda Gran Via Parque, 29",
    "sg:city":"Cordoba",
    "sg:orig_category":"Loter\u00cda Y T\u00d3mbola",
    "sg:phone":"+34 957 23 36 89",
    "sg:postcode":"14005",
    "sg:province":"C\u00f3rdoba",
    "wof:name":"Martin Morales Angela",
    "wof:placetype":"venue"
},
  "geometry": {"coordinates":[-4.7933249474,37.881439209],"type":"Point"}
}