{
  "type": "Feature",
  "properties": {
    "iso:country":"ES",
    "sg:address":"Calle de Ventura De La Vega, 2",
    "sg:city":"Sevilla",
    "sg:orig_category":"Ropa Para Se\u00d1oras (al Por Menor)",
    "sg:phone":"+34 954 63 01 52",
    "sg:postcode":"41005",
    "sg:province":"Sevilla",
    "wof:name":"Diana Mu\u00f1oz Cristina",
    "wof:placetype":"venue"
},
  "geometry": {"coordinates":[-5.971642971,37.3821334839],"type":"Point"}
}