{
  "type": "Feature",
  "properties": {
    "addr:full":"Calle de Comercio, 1 Huescar Granada 18830",
    "addr:housenumber":"1",
    "addr:postcode":"18830",
    "addr:street":"Calle De Comercio",
    "iso:country":"ES",
    "sg:address":"Calle de Comercio, 1",
    "sg:city":"Huescar",
    "sg:orig_category":"Carnicer\u00cdas, Carnicer\u00cdas",
    "sg:phone":"+34 958 74 02 24",
    "sg:postcode":"18830",
    "sg:province":"Granada",
    "wof:name":"Jimenez Diaz Pedro",
    "wof:placetype":"venue"
},
  "geometry": {"coordinates":[-2.5402071476,37.8093681335],"type":"Point"}
}