{
  "type": "Feature",
  "properties": {
    "iso:country":"ES",
    "sg:address":"Carrer de Estacio, 56",
    "sg:city":"Sabadell",
    "sg:orig_category":"Asesor\u00cda Sobre Comunicaci\u00d3n De Empresas",
    "sg:phone":"+34 937 26 24 67",
    "sg:postcode":"08202",
    "sg:province":"Barcelona",
    "wof:name":"Assessoria D Empreses Manuel Alvarez S.l.",
    "wof:placetype":"venue"
},
  "geometry": {"coordinates":[2.115090847,41.5471839905],"type":"Point"}
}