{
  "type": "Feature",
  "properties": {
    "addr:full":"Calle de Garcia De Paredes, 76 Madrid Madrid 28010",
    "addr:housenumber":"76",
    "addr:postcode":"madrid;28010",
    "addr:street":"Calle De Garcia De Paredes",
    "iso:country":"ES",
    "sg:address":"Calle de Garcia De Paredes, 76",
    "sg:city":"Madrid",
    "sg:orig_category":"Centros Comerciales Y Grandes Tiendas",
    "sg:phone":"+34 913 19 66 31",
    "sg:postcode":"28010",
    "sg:province":"Madrid",
    "wof:name":"Chen  Jie",
    "wof:placetype":"venue"
},
  "geometry": {"coordinates":[-3.6940159798,40.4365081787],"type":"Point"}
}