{
  "type": "Feature",
  "properties": {
    "addr:full":"Calle de Mar (la), 10 Colindres Cantabria 39750",
    "addr:housenumber":"10",
    "addr:postcode":"39750",
    "addr:street":"Calle De Mar La",
    "iso:country":"ES",
    "sg:address":"Calle de Mar (la), 10",
    "sg:city":"Colindres",
    "sg:orig_category":"Mec\u00c1nico Del Autom\u00d3vil",
    "sg:phone":"+34 942 65 16 23",
    "sg:postcode":"39750",
    "sg:province":"Cantabria",
    "wof:name":"Talleres Nazabal S.l",
    "wof:placetype":"venue"
},
  "geometry": {"coordinates":[-3.4540309906,43.3946685791],"type":"Point"}
}