{
  "type": "Feature",
  "properties": {
    "addr:full":"Calle de Pasaje San Francisco, 1 Alfaro La Rioja 26540",
    "addr:housenumber":"1",
    "addr:postcode":"26540",
    "addr:street":"Calle De Pasaje San Francisco;Rioja",
    "iso:country":"ES",
    "sg:address":"Calle de Pasaje San Francisco, 1",
    "sg:city":"Alfaro",
    "sg:orig_category":"Bancos",
    "sg:phone":"+34 941 18 47 84",
    "sg:postcode":"26540",
    "sg:province":"La Rioja",
    "sg:website":"www.cajalon.es",
    "wof:name":"Caja Rural De Aragon S.coop Credito",
    "wof:placetype":"venue"
},
  "geometry": {"coordinates":[-1.7496249676,42.1795768738],"type":"Point"}
}