{
  "type": "Feature",
  "properties": {
    "addr:full":"Pg Sant Albert, 16 Vallpineda Barcelona 08810",
    "addr:housenumber":"16",
    "addr:postcode":"08810",
    "addr:street":"Pg Sant Albert;Barcelona",
    "iso:country":"ES",
    "sg:address":"Pg Sant Albert, 16",
    "sg:city":"Vallpineda",
    "sg:orig_category":"Papel (al Por Mayor)",
    "sg:phone":"+34 938 94 29 04",
    "sg:postcode":"08810",
    "sg:province":"Barcelona",
    "wof:name":"Comercial Del Papel Vall-pi S. A.",
    "wof:placetype":"venue"
},
  "geometry": {"coordinates":[1.7983850241,41.2487602234],"type":"Point"}
}