{
  "type": "Feature",
  "properties": {
    "addr:full":"Rbla Prat, 27 Barcelona Barcelona 08012",
    "addr:housenumber":"27",
    "addr:postcode":"08012",
    "addr:street":"Rbla Prat",
    "iso:country":"ES",
    "sg:address":"Rbla Prat, 27",
    "sg:city":"Barcelona",
    "sg:orig_category":"Ingenier\u00cda, Centros De Estudios (diversos)",
    "sg:phone":"+34 934 15 01 71",
    "sg:postcode":"08012",
    "sg:province":"Barcelona",
    "wof:name":"De Diego Trepat Mauricio",
    "wof:placetype":"venue"
},
  "geometry": {"coordinates":[2.1513450146,41.4008102417],"type":"Point"}
}