{
  "type": "Feature",
  "properties": {
    "iso:country":"ES",
    "sg:address":"Avda Mediterraneo (del), 2",
    "sg:city":"Colmenar Viejo",
    "sg:orig_category":"Panader\u00cdas, Panader\u00cdas",
    "sg:phone":"+34 918 46 38 45",
    "sg:postcode":"28770",
    "sg:province":"Madrid",
    "wof:name":"Molpeceres Barranco Maria Veronica",
    "wof:placetype":"venue"
},
  "geometry": {"coordinates":[-3.7767300606,40.6681289673],"type":"Point"}
}