{
  "type": "Feature",
  "properties": {
    "addr:full":"Pla\u00c7 Independencia, 14 Girona Girona 17001",
    "addr:housenumber":"14",
    "addr:postcode":"17001",
    "addr:street":"Independencia",
    "iso:country":"ES",
    "sg:address":"Pla\u00c7 Independencia, 14",
    "sg:city":"Girona",
    "sg:orig_category":"Restaurantes",
    "sg:phone":"+34 972 21 36 71",
    "sg:postcode":"17001",
    "sg:province":"Girona",
    "wof:name":"Lloret Nuch Felix",
    "wof:placetype":"venue"
},
  "geometry": {"coordinates":[2.8239550591,41.9858779907],"type":"Point"}
}