{
  "type": "Feature",
  "properties": {
    "iso:country":"ES",
    "sg:address":"Calle de Camino De San Antonio, 10",
    "sg:city":"Motril",
    "sg:orig_category":"Marmolistas Funerarios",
    "sg:phone":"+34 958 60 93 37",
    "sg:postcode":"18600",
    "sg:province":"Granada",
    "wof:name":"Funalmu S.l.",
    "wof:placetype":"venue"
},
  "geometry": {"coordinates":[-3.5190234184,36.7465934753],"type":"Point"}
}