{
  "type": "Feature",
  "properties": {
    "addr:full":"Carrer de Laurea Miro, 237 Esplugues Llobregat Barcelona 08950",
    "addr:housenumber":"237",
    "addr:postcode":"08950",
    "addr:street":"Carrer De Laurea Miro",
    "iso:country":"ES",
    "sg:address":"Carrer de Laurea Miro, 237",
    "sg:city":"Esplugues Llobregat",
    "sg:orig_category":"Carnicer\u00cdas, Carnicer\u00cdas",
    "sg:phone":"+34 933 71 02 38",
    "sg:postcode":"08950",
    "sg:province":"Barcelona",
    "wof:name":"Moreno Lorente Maria De Los Remedios",
    "wof:placetype":"venue"
},
  "geometry": {"coordinates":[2.0869250298,41.3774414062],"type":"Point"}
}