{
  "type": "Feature",
  "properties": {
    "addr:full":"Calle de Navas De Tolosa, 3 Jaen Ja\u00e9n 23001",
    "addr:housenumber":"3;jae\u0301n",
    "addr:postcode":"23001",
    "addr:street":"Calle De Navas De Tolosa",
    "iso:country":"ES",
    "sg:address":"Calle de Navas De Tolosa, 3",
    "sg:city":"Jaen",
    "sg:orig_category":"Agencias Y Agentes Comerciales, Representantes",
    "sg:phone":"+34 953 27 35 56",
    "sg:postcode":"23001",
    "sg:province":"Ja\u00e9n",
    "wof:name":"Martos Lorente Francisco Javier",
    "wof:placetype":"venue"
},
  "geometry": {"coordinates":[-3.7875161171,37.7691841125],"type":"Point"}
}