{
  "type": "Feature",
  "properties": {
    "addr:full":"Ctra Bilbao-plencia, 31 Erandio-goikoa Vizcaya 48950",
    "addr:housenumber":"31",
    "addr:postcode":"48950",
    "addr:street":"Ctra Bilbao-Plencia",
    "iso:country":"ES",
    "sg:address":"Ctra Bilbao-plencia, 31",
    "sg:city":"Erandio-goikoa",
    "sg:orig_category":"Promotores Constructores",
    "sg:phone":"+34 944 53 50 17",
    "sg:postcode":"48950",
    "sg:province":"Vizcaya",
    "wof:name":"Codesport Euskadi S.l.",
    "wof:placetype":"venue"
},
  "geometry": {"coordinates":[-2.9477870464,43.302192688],"type":"Point"}
}