{
  "type": "Feature",
  "properties": {
    "addr:full":"Calle de Fino, 57 Tomillares M\u00e1laga 29130",
    "addr:housenumber":"57",
    "addr:postcode":"29130",
    "addr:street":"Calle De Fino;Ma\u0301Laga",
    "iso:country":"ES",
    "sg:address":"Calle de Fino, 57",
    "sg:city":"Tomillares",
    "sg:orig_category":"Organismos Y Centros De Vacaciones Y Esparcimiento Para Ni\u00d1os Y Adolescentes",
    "sg:phone":"+34 952 41 56 73",
    "sg:postcode":"29130",
    "sg:province":"M\u00e1laga",
    "wof:name":"Marquez Sierra Manuel Francisco",
    "wof:placetype":"venue"
},
  "geometry": {"coordinates":[-4.5667190552,36.6618614197],"type":"Point"}
}