{
  "type": "Feature",
  "properties": {
    "addr:full":"Ctra Brenes (p I El Malecon), Km. 0003,0 San Jose Rinconada Sevilla 41300",
    "addr:postcode":"41300",
    "addr:street":"Ctra Brenes P;El Malecon Km. 0003,0",
    "iso:country":"ES",
    "sg:address":"Ctra Brenes (p I El Malecon), Km. 0003,0",
    "sg:city":"San Jose Rinconada",
    "sg:orig_category":"Distribuci\u00d3n De Petr\u00d3leo Y Derivados",
    "sg:phone":"+34 954 79 00 50",
    "sg:postcode":"41300",
    "sg:province":"Sevilla",
    "sg:website":"www.cepsa.es",
    "wof:name":"Mogollon S.a.",
    "wof:placetype":"venue"
},
  "geometry": {"coordinates":[-5.9507889748,37.4823112488],"type":"Point"}
}