{
  "type": "Feature",
  "properties": {
    "addr:full":"Plaz Mayor, 13 Rueda Valladolid 47490",
    "addr:housenumber":"13",
    "addr:postcode":"47490",
    "addr:street":"Plaz Mayor;Valladolid",
    "iso:country":"ES",
    "sg:address":"Plaz Mayor, 13",
    "sg:city":"Rueda",
    "sg:orig_category":"Agencias Y Agentes Comerciales, Representantes",
    "sg:phone":"+34 983 86 83 87",
    "sg:postcode":"47490",
    "sg:province":"Valladolid",
    "wof:name":"Maria Jesus De La Hoz Monsalve S.l.",
    "wof:placetype":"venue"
},
  "geometry": {"coordinates":[-4.9602365494,41.4139404297],"type":"Point"}
}