{
  "type": "Feature",
  "properties": {
    "iso:country":"ES",
    "sg:address":"Carrer de Sant Antoni Maria Claret, 337",
    "sg:city":"Barcelona",
    "sg:orig_category":"Arquitectos",
    "sg:phone":"+34 934 08 03 02",
    "sg:postcode":"08027",
    "sg:province":"Barcelona",
    "wof:name":"Chaparro Mancebo Jose Manuel",
    "wof:placetype":"venue"
},
  "geometry": {"coordinates":[2.1860120296,41.4200782776],"type":"Point"}
}