{
  "type": "Feature",
  "properties": {
    "addr:full":"Carrer de Maestrat, 52 Terrassa Barcelona 08225",
    "addr:housenumber":"52",
    "addr:postcode":"08225",
    "addr:street":"Carrer De Maestrat",
    "iso:country":"ES",
    "sg:address":"Carrer de Maestrat, 52",
    "sg:city":"Terrassa",
    "sg:orig_category":"Laboratorios Y Cl\u00cdnicas Veterinarias",
    "sg:phone":"+34 937 35 39 48",
    "sg:postcode":"08225",
    "sg:province":"Barcelona",
    "wof:name":"Serveis Veterinaris De Terrassa S.l.",
    "wof:placetype":"venue"
},
  "geometry": {"coordinates":[2.0173799992,41.5760192871],"type":"Point"}
}