{
  "type": "Feature",
  "properties": {
    "addr:full":"La Rosa, 23 Sta Cruz Tenerife Santa Cruz De Tenerife 38002",
    "addr:housenumber":"23",
    "addr:postcode":"38002",
    "addr:street":"Rosa;Sta Cruz Tenerife",
    "iso:country":"ES",
    "sg:address":"La Rosa, 23",
    "sg:city":"Sta Cruz Tenerife",
    "sg:orig_category":"Papeler\u00cdas, Librer\u00cdas",
    "sg:phone":"+34 922 27 62 18",
    "sg:postcode":"38002",
    "sg:province":"Santa Cruz De Tenerife",
    "wof:name":"Papeleria Favego La Rosa S.l.",
    "wof:placetype":"venue"
},
  "geometry": {"coordinates":[-16.2499160767,28.4709224701],"type":"Point"}
}