{
  "type": "Feature",
  "properties": {
    "addr:full":"Calle de Moriones, 35 Torrevieja Alicante 03180",
    "addr:housenumber":"35",
    "addr:postcode":"03180",
    "addr:street":"Calle De Moriones",
    "iso:country":"ES",
    "sg:address":"Calle de Moriones, 35",
    "sg:city":"Torrevieja",
    "sg:orig_category":"Confecci\u00d3n De Zapatos",
    "sg:phone":"+34 966 70 56 60",
    "sg:postcode":"03180",
    "sg:province":"Alicante",
    "wof:name":"Calzados De Chaci S.l.",
    "wof:placetype":"venue"
},
  "geometry": {"coordinates":[-0.6536790133,38.0173606873],"type":"Point"}
}