{
  "type": "Feature",
  "properties": {
    "iso:country":"ES",
    "sg:address":"Lluvia, 5",
    "sg:city":"Leganes",
    "sg:orig_category":"Chapister\u00cda",
    "sg:phone":"+34 916 11 10 81",
    "sg:postcode":"28918",
    "sg:province":"Madrid",
    "wof:name":"Talleres Jumacar S.l.",
    "wof:placetype":"venue"
},
  "geometry": {"coordinates":[-3.7983469963,40.3463897705],"type":"Point"}
}