{
  "type": "Feature",
  "properties": {
    "iso:country":"ES",
    "sg:address":"Carrer de Ripoll, 4",
    "sg:city":"Vic",
    "sg:orig_category":"Ebanister\u00cda",
    "sg:phone":"+34 938 86 17 77",
    "sg:postcode":"08500",
    "sg:province":"Barcelona",
    "wof:name":"Ramon Pladevall S.l.",
    "wof:placetype":"venue"
},
  "geometry": {"coordinates":[2.2535469532,41.9457397461],"type":"Point"}
}