{
  "type": "Feature",
  "properties": {
    "addr:full":"Calle de Juan De Bilbao, 2 Donostia-san Sebastian Guip\u00f9zcoa 20003",
    "addr:housenumber":"2",
    "addr:postcode":"20003",
    "addr:street":"Calle De Juan De Bilbao",
    "iso:country":"ES",
    "sg:address":"Calle de Juan De Bilbao, 2",
    "sg:city":"Donostia-san Sebastian",
    "sg:orig_category":"Obras Y Organismos Sociales",
    "sg:phone":"+34 943 43 15 36",
    "sg:postcode":"20003",
    "sg:province":"Guip\u00f9zcoa",
    "wof:name":"Parroquia De San Vicente",
    "wof:placetype":"venue"
},
  "geometry": {"coordinates":[-1.98458004,43.3241958618],"type":"Point"}
}