{
  "type": "Feature",
  "properties": {
    "addr:full":"Rua Urzaiz, 60 Vigo Pontevedra 36201",
    "addr:housenumber":"60",
    "addr:postcode":"36201",
    "addr:street":"Rua Urzaiz",
    "iso:country":"ES",
    "sg:address":"Rua Urzaiz, 60",
    "sg:city":"Vigo",
    "sg:orig_category":"Asistencia Domiciliaria",
    "sg:phone":"+34 986 41 50 16",
    "sg:postcode":"36201",
    "sg:province":"Pontevedra",
    "wof:name":"Siervas De Jesus",
    "wof:placetype":"venue"
},
  "geometry": {"coordinates":[-8.7154598236,42.2339897156],"type":"Point"}
}