{
  "type": "Feature",
  "properties": {
    "iso:country":"ES",
    "sg:address":"Calle de Capitan Claudio Vazquez, 9",
    "sg:city":"Ceuta",
    "sg:orig_category":"Transportes Por Carretera: Lotes Completos, Mercanc\u00cdas Diversas",
    "sg:phone":"+34 956 50 84 07",
    "sg:postcode":"51002",
    "sg:province":"Ceuta",
    "wof:name":"Bunuar Kaddur Rabah",
    "wof:placetype":"venue"
},
  "geometry": {"coordinates":[-5.342941761,35.8851089478],"type":"Point"}
}