{
  "type": "Feature",
  "properties": {
    "iso:country":"ES",
    "sg:address":"Rua Licenciado Molina, 10",
    "sg:city":"Ourense",
    "sg:orig_category":"Empresas De Desmonte",
    "sg:phone":"+34 988 21 36 37",
    "sg:postcode":"32001",
    "sg:province":"Ourense",
    "wof:name":"Dominguez Pereira Manuel",
    "wof:placetype":"venue"
},
  "geometry": {"coordinates":[-7.8744039536,42.3541488647],"type":"Point"}
}