{
  "type": "Feature",
  "properties": {
    "iso:country":"ES",
    "sg:address":"Calle de Monjas (las), 5",
    "sg:city":"Casas-iba\u00e7ez",
    "sg:orig_category":"Asociaciones, Organismos Culturales Y Socioeducativos",
    "sg:phone":"+34 967 46 20 25",
    "sg:postcode":"02200",
    "sg:province":"Albacete",
    "wof:name":"Asociacion De Padres De Familia Azafran",
    "wof:placetype":"venue"
},
  "geometry": {"coordinates":[-1.8600701094,38.9976501465],"type":"Point"}
}