{
  "type": "Feature",
  "properties": {
    "addr:full":"Ctra Cabrejas Del Campo, S/n Gomara Soria 42120",
    "addr:housenumber":"s / n",
    "addr:postcode":"42120",
    "addr:street":"Ctra Cabrejas Del Campo",
    "iso:country":"ES",
    "sg:address":"Ctra Cabrejas Del Campo, S/n",
    "sg:city":"Gomara",
    "sg:orig_category":"Producci\u00d3n De Abonos Y De Fertilizantes",
    "sg:phone":"+34 975 38 03 96",
    "sg:postcode":"42120",
    "sg:province":"Soria",
    "wof:name":"Uriel Tovar Y Milla S.a.",
    "wof:placetype":"venue"
},
  "geometry": {"coordinates":[-2.2247591019,41.6239356995],"type":"Point"}
}