{
  "type": "Feature",
  "properties": {
    "addr:full":"Calle de Puentelarra, 18 Madrid Madrid 28031",
    "addr:housenumber":"18",
    "addr:postcode":"madrid;28031",
    "addr:street":"Calle De Puentelarra",
    "iso:country":"ES",
    "sg:address":"Calle de Puentelarra, 18",
    "sg:city":"Madrid",
    "sg:orig_category":"Formaci\u00d3n Continuada (variada)",
    "sg:phone":"+34 913 31 86 78",
    "sg:postcode":"28031",
    "sg:province":"Madrid",
    "wof:name":"Azcona Calvo Maria Isabel",
    "wof:placetype":"venue"
},
  "geometry": {"coordinates":[-3.6117339134,40.3813552856],"type":"Point"}
}