{
  "type": "Feature",
  "properties": {
    "iso:country":"ES",
    "sg:address":"Calle de Joaquin Gamon, 1",
    "sg:city":"Irun",
    "sg:orig_category":"Inmobiliaria (agencias)",
    "sg:phone":"+34 943 62 50 22",
    "sg:postcode":"20302",
    "sg:province":"Guip\u00f9zcoa",
    "sg:website":"www. inmobiliariacunado.com",
    "wof:name":"Cu\u00f1ado Olaizola Luis Ignacio",
    "wof:placetype":"venue"
},
  "geometry": {"coordinates":[-1.7909499407,43.3392677307],"type":"Point"}
}