{
  "type": "Feature",
  "properties": {
    "iso:country":"ES",
    "sg:address":"Afueras, S/n",
    "sg:city":"Alcala Del Obispo",
    "sg:orig_category":"Agricultores, Agricultores",
    "sg:phone":"+34 974 34 01 73",
    "sg:postcode":"22135",
    "sg:province":"Huesca",
    "wof:name":"Hermanos Lacarte Palus S.c.p.",
    "wof:placetype":"venue"
},
  "geometry": {"coordinates":[-0.2887189984,42.0775413513],"type":"Point"}
}