{
  "type": "Feature",
  "properties": {
    "iso:country":"ES",
    "sg:address":"Calle de Medico Rodriguez, 11",
    "sg:city":"Coru\u00d1a",
    "sg:orig_category":"M\u00c9dicos: Gastroenterolog\u00cda Y Hepatolog\u00cda (aparato Digestivo)",
    "sg:phone":"+34 981 26 18 94",
    "sg:postcode":"15004",
    "sg:province":"A Coru\u00f1a",
    "sg:website":"d",
    "wof:name":"Vazquez Iglesias Jose Luis",
    "wof:placetype":"venue"
},
  "geometry": {"coordinates":[-8.4100952148,43.3658905029],"type":"Point"}
}