{
  "type": "Feature",
  "properties": {
    "iso:country":"ES",
    "sg:address":"Calle de Arces, 37",
    "sg:city":"Malaga",
    "sg:orig_category":"M\u00c9dicos: Ginecolog\u00cda Y Obstetricia",
    "sg:phone":"+34 952 29 65 27",
    "sg:postcode":"29018",
    "sg:province":"M\u00e1laga",
    "wof:name":"Herrero Cantarero Jose Ramon",
    "wof:placetype":"venue"
},
  "geometry": {"coordinates":[-4.3845591545,36.7327270508],"type":"Point"}
}