{
  "type": "Feature",
  "properties": {
    "addr:full":"Av Salvador Trilles, S/n Sant Joan Moro Castell\u00f3n 12130",
    "addr:housenumber":"s / n",
    "addr:postcode":"12130",
    "addr:street":"Av Salvador Trilles",
    "iso:country":"ES",
    "sg:address":"Av Salvador Trilles, S/n",
    "sg:city":"Sant Joan Moro",
    "sg:orig_category":"Cerrajer\u00cda, Ferrallista",
    "sg:phone":"+34 964 32 81 76",
    "sg:postcode":"12130",
    "sg:province":"Castell\u00f3n",
    "wof:name":"Morofer S.l.",
    "wof:placetype":"venue"
},
  "geometry": {"coordinates":[-0.1363189965,40.0592765808],"type":"Point"}
}