{
  "type": "Feature",
  "properties": {
    "addr:full":"Carrer de Comtal, 26 Barcelona Barcelona 08002",
    "addr:housenumber":"26",
    "addr:postcode":"08002",
    "addr:street":"Carrer De Comtal",
    "iso:country":"ES",
    "sg:address":"Carrer de Comtal, 26",
    "sg:city":"Barcelona",
    "sg:orig_category":"Florister\u00cdas",
    "sg:phone":"+34 933 02 48 28",
    "sg:postcode":"08002",
    "sg:province":"Barcelona",
    "wof:name":"Cortiella Aleixandri Cristina",
    "wof:placetype":"venue"
},
  "geometry": {"coordinates":[2.1738049984,41.3865280151],"type":"Point"}
}