{
  "type": "Feature",
  "properties": {
    "addr:full":"Calle de Tejuela, 3 Alcala Real Ja\u00e9n 23680",
    "addr:housenumber":"3",
    "addr:postcode":"23680",
    "addr:street":"Calle De Tejuela;Jae\u0301N",
    "iso:country":"ES",
    "sg:address":"Calle de Tejuela, 3",
    "sg:city":"Alcala Real",
    "sg:orig_category":"Bisuter\u00cda, Joyer\u00cda, Relojer\u00cda (al Por Menor)",
    "sg:phone":"+34 953 58 09 91",
    "sg:postcode":"23680",
    "sg:province":"Ja\u00e9n",
    "wof:name":"Teba Hueltes Manuel",
    "wof:placetype":"venue"
},
  "geometry": {"coordinates":[-3.9252979755,37.4648933411],"type":"Point"}
}