{
  "type": "Feature",
  "properties": {
    "iso:country":"ES",
    "sg:address":"Fra J. Serra, 6",
    "sg:city":"Petra",
    "sg:orig_category":"Museos",
    "sg:phone":"+34 971 56 10 28",
    "sg:postcode":"07520",
    "sg:province":"Islas Baleares",
    "wof:name":"Museo Fray Junipero Serra",
    "wof:placetype":"venue"
},
  "geometry": {"coordinates":[3.1116600037,39.6119041443],"type":"Point"}
}