{
  "type": "Feature",
  "properties": {
    "iso:country":"ES",
    "sg:address":"Calle de Macabil, 14",
    "sg:city":"Villarrubia De Los Ojos",
    "sg:orig_category":"Molduras, Junquillos, Listones Y Molduras Perforadas",
    "sg:phone":"+34 926 89 61 74",
    "sg:postcode":"13670",
    "sg:province":"Ciudad Real",
    "wof:name":"La Palma C.b.",
    "wof:placetype":"venue"
},
  "geometry": {"coordinates":[-3.6072220802,39.2208251953],"type":"Point"}
}