{
  "type": "Feature",
  "properties": {
    "iso:country":"ES",
    "sg:address":"Calle de Alcalde Manuel Marin, 8",
    "sg:city":"Camas",
    "sg:orig_category":"Pescader\u00cdas (al Por Menor)",
    "sg:phone":"+34 955 98 11 05",
    "sg:postcode":"41900",
    "sg:province":"Sevilla",
    "wof:name":"Sanchez Marin Ventura",
    "wof:placetype":"venue"
},
  "geometry": {"coordinates":[-6.0350294113,37.400932312],"type":"Point"}
}