{
  "type": "Feature",
  "properties": {
    "addr:full":"Rua Faustino Santalices, 28 Bande Ourense 32840",
    "addr:housenumber":"28",
    "addr:postcode":"32840",
    "addr:street":"Rua Faustino Santalices",
    "iso:country":"ES",
    "sg:address":"Rua Faustino Santalices, 28",
    "sg:city":"Bande",
    "sg:orig_category":"Restaurantes",
    "sg:phone":"+34 988 44 30 63",
    "sg:postcode":"32840",
    "sg:province":"Ourense",
    "wof:name":"Vazquez Salgado Ricardo",
    "wof:placetype":"venue"
},
  "geometry": {"coordinates":[-7.9762649536,42.0318565369],"type":"Point"}
}