{
  "type": "Feature",
  "properties": {
    "addr:full":"Calle de Linares, 5 Valladolid Valladolid 47010",
    "addr:housenumber":"5",
    "addr:postcode":"47010",
    "addr:street":"Calle De Linares",
    "iso:country":"ES",
    "sg:address":"Calle de Linares, 5",
    "sg:city":"Valladolid",
    "sg:orig_category":"Alimentaci\u00d3n General (al Por Menor)",
    "sg:phone":"+34 983 25 12 97",
    "sg:postcode":"47010",
    "sg:province":"Valladolid",
    "wof:name":"Sanz Moreton Luciano",
    "wof:placetype":"venue"
},
  "geometry": {"coordinates":[-4.7190680504,41.660358429],"type":"Point"}
}