{
  "type": "Feature",
  "properties": {
    "addr:full":"Carrer de Juli Garreta, 27 Esplugues Llobregat Barcelona 08950",
    "addr:housenumber":"27",
    "addr:postcode":"08950",
    "addr:street":"Carrer De Juli Garreta",
    "iso:country":"ES",
    "sg:address":"Carrer de Juli Garreta, 27",
    "sg:city":"Esplugues Llobregat",
    "sg:orig_category":"M\u00c9dicos: Neumolog\u00cda",
    "sg:phone":"+34 934 73 31 95",
    "sg:postcode":"08950",
    "sg:province":"Barcelona",
    "wof:name":"Maldonado Diaz De Losada Jose",
    "wof:placetype":"venue"
},
  "geometry": {"coordinates":[2.0827200413,41.3726615906],"type":"Point"}
}