{
  "type": "Feature",
  "properties": {
    "iso:country":"ES",
    "sg:address":"Carrer de Cabanyes, 36",
    "sg:city":"Sabadell",
    "sg:orig_category":"Montaje (empresas De)",
    "sg:phone":"+34 937 11 89 64",
    "sg:postcode":"08203",
    "sg:province":"Barcelona",
    "wof:name":"Emypro S. A.",
    "wof:placetype":"venue"
},
  "geometry": {"coordinates":[2.1070780754,41.5336761475],"type":"Point"}
}