{
  "type": "Feature",
  "properties": {
    "iso:country":"ES",
    "sg:address":"Calle de Sor Maria De Agreda, 24",
    "sg:city":"Madrid",
    "sg:orig_category":"Alimentaci\u00d3n General (al Por Menor)",
    "sg:phone":"+34 913 77 47 13",
    "sg:postcode":"28017",
    "sg:province":"Madrid",
    "wof:name":"Fernandez Arranz Daniel",
    "wof:placetype":"venue"
},
  "geometry": {"coordinates":[-3.6493520737,40.4298286438],"type":"Point"}
}