{
  "type": "Feature",
  "properties": {
    "iso:country":"ES",
    "sg:address":"Calle de Granada, 271",
    "sg:city":"Almeria",
    "sg:orig_category":"Zapatos (al Por Menor)",
    "sg:phone":"+34 950 25 92 86",
    "sg:postcode":"04008",
    "sg:province":"Almer\u00eda",
    "wof:name":"Moya Gutierrez Carmen Maria",
    "wof:placetype":"venue"
},
  "geometry": {"coordinates":[-2.4600465298,36.8452377319],"type":"Point"}
}