{
  "type": "Feature",
  "properties": {
    "addr:full":"Calle de Especeria, 14 Malaga M\u00e1laga 29005",
    "addr:housenumber":"14",
    "addr:postcode":"29005",
    "addr:street":"Calle De Especeria;Ma\u0301Laga",
    "iso:country":"ES",
    "sg:address":"Calle de Especeria, 14",
    "sg:city":"Malaga",
    "sg:orig_category":"Inmobiliaria (agencias)",
    "sg:phone":"+34 952 12 19 20",
    "sg:postcode":"29005",
    "sg:province":"M\u00e1laga",
    "wof:name":"Union De Promociones Malaga 2002",
    "wof:placetype":"venue"
},
  "geometry": {"coordinates":[-4.4232001305,36.7210044861],"type":"Point"}
}