{
  "type": "Feature",
  "properties": {
    "iso:country":"ES",
    "sg:address":"Pl Font (de La), 24",
    "sg:city":"Tarragona",
    "sg:orig_category":"Restaurantes",
    "sg:phone":"+34 977 21 77 66",
    "sg:postcode":"43003",
    "sg:province":"Tarragona",
    "wof:name":"Murcia Perez Juan",
    "wof:placetype":"venue"
},
  "geometry": {"coordinates":[1.2557959557,41.1170692444],"type":"Point"}
}