{
  "type": "Feature",
  "properties": {
    "addr:full":"Av Catalunya, 10 Blanes Girona 17300",
    "addr:housenumber":"10",
    "addr:postcode":"17300",
    "addr:street":"Av Catalunya",
    "iso:country":"ES",
    "sg:address":"Av Catalunya, 10",
    "sg:city":"Blanes",
    "sg:orig_category":"Florister\u00cdas",
    "sg:phone":"+34 972 33 53 62",
    "sg:postcode":"17300",
    "sg:province":"Girona",
    "wof:name":"Florido Moles Monserrat",
    "wof:placetype":"venue"
},
  "geometry": {"coordinates":[2.7734410763,41.6672554016],"type":"Point"}
}