{
  "type": "Feature",
  "properties": {
    "iso:country":"ES",
    "sg:address":"Carretera Del Muelle, S/n",
    "sg:city":"Boiro",
    "sg:classifiers":[
        {
            "category":"Recreation",
            "type":"Entertainment"
        }
    ],
    "sg:phone":"+34 981 84 71 76",
    "sg:postcode":"15930",
    "sg:province":"La Coru\u00f1a",
    "sg:tags":[
        "caza",
        "pr\u00c1ctica",
        "la",
        "de",
        "pesca",
        "y"
    ],
    "wof:name":"Cofradia De Pescadores De Cabo De Cruz",
    "wof:placetype":"venue"
},
  "geometry": {"coordinates":[-8.8847093582,42.6471214294],"type":"Point"}
}