{
  "type": "Feature",
  "properties": {
    "addr:full":"Carrer de Cotlliure, 27 Palma Islas Baleares 07010",
    "addr:housenumber":"27",
    "addr:postcode":"07010",
    "addr:street":"Carrer De Cotlliure",
    "iso:country":"ES",
    "sg:address":"Carrer de Cotlliure, 27",
    "sg:city":"Palma",
    "sg:orig_category":"Molduras, Junquillos, Listones Y Molduras Perforadas",
    "sg:phone":"+34 971 20 92 22",
    "sg:postcode":"07010",
    "sg:province":"Islas Baleares",
    "wof:name":"Fiol Fernandez Francisco",
    "wof:placetype":"venue"
},
  "geometry": {"coordinates":[2.6470499039,39.5908813477],"type":"Point"}
}