{
  "type": "Feature",
  "properties": {
    "iso:country":"ES",
    "sg:address":"Avda Aixarte, 1",
    "sg:city":"Arrigorriaga",
    "sg:orig_category":"Plomeros",
    "sg:phone":"+34 946 71 01 71",
    "sg:postcode":"48480",
    "sg:province":"Vizcaya",
    "wof:name":"Garcia Ibargoitia Isidro",
    "wof:placetype":"venue"
},
  "geometry": {"coordinates":[-2.8894059658,43.205116272],"type":"Point"}
}