{
  "type": "Feature",
  "properties": {
    "addr:full":"Cmno Pego (el), 40 Villabuena Puente Zamora 49820",
    "addr:housenumber":"40",
    "addr:postcode":"49820",
    "addr:street":"Cmno Pego El;Puente Zamora",
    "iso:country":"ES",
    "sg:address":"Cmno Pego (el), 40",
    "sg:city":"Villabuena Puente",
    "sg:orig_category":"Contenedores (mercanc\u00cdas)",
    "sg:phone":"+34 980 60 65 33",
    "sg:postcode":"49820",
    "sg:province":"Zamora",
    "wof:name":"Barrio Acero Francisco Javier",
    "wof:placetype":"venue"
},
  "geometry": {"coordinates":[-5.4064941406,41.3804168701],"type":"Point"}
}