{
  "type": "Feature",
  "properties": {
    "iso:country":"ES",
    "sg:address":"Carr Palma, De La, 8",
    "sg:city":"Soller",
    "sg:orig_category":"Masajistas Kinesiterapeutas",
    "sg:phone":"+34 971 63 35 55",
    "sg:postcode":"07100",
    "sg:province":"Islas Baleares",
    "wof:name":"Reynes Trias Joan J.",
    "wof:placetype":"venue"
},
  "geometry": {"coordinates":[2.7147779465,39.7659072876],"type":"Point"}
}