{
  "type": "Feature",
  "properties": {
    "iso:country":"ES",
    "sg:address":"Calle de San Joaquin, 8",
    "sg:city":"Madrid",
    "sg:classifiers":[
        {
            "category":"Utilities",
            "subcategory":"Natural Gas",
            "type":"Services"
        }
    ],
    "sg:phone":"+34 915 31 16 15",
    "sg:postcode":"28004",
    "sg:province":"Madrid",
    "sg:tags":[
        "te",
        "de",
        "salones"
    ],
    "sg:website":"www.bomec-elpaladardelte.com",
    "wof:name":"Bomec Salon De Te",
    "wof:placetype":"venue"
},
  "geometry": {"coordinates":[-3.7012560368,40.4245109558],"type":"Point"}
}