{
  "type": "Feature",
  "properties": {
    "addr:full":"Avda Legion De (la), 15 Antequera M\u00e1laga 29200",
    "addr:housenumber":"15",
    "addr:postcode":"29200",
    "addr:street":"Avda Legion De La",
    "iso:country":"ES",
    "sg:address":"Avda Legion De (la), 15",
    "sg:city":"Antequera",
    "sg:orig_category":"Cristaler\u00cdas",
    "sg:phone":"+34 952 70 10 32",
    "sg:postcode":"29200",
    "sg:province":"M\u00e1laga",
    "wof:name":"Rosgu S.l.",
    "wof:placetype":"venue"
},
  "geometry": {"coordinates":[-4.5654029846,37.0194129944],"type":"Point"}
}