{
  "type": "Feature",
  "properties": {
    "iso:country":"ES",
    "sg:address":"Carrer de Castanyer, 10",
    "sg:city":"Barcelona",
    "sg:orig_category":"Tintes (fabricaci\u00d3n, Al Por Mayor)",
    "sg:phone":"+34 934 17 79 68",
    "sg:postcode":"08022",
    "sg:province":"Barcelona",
    "wof:name":"Torres Gonzalez Isabel",
    "wof:placetype":"venue"
},
  "geometry": {"coordinates":[2.1371510029,41.4066352844],"type":"Point"}
}