{
  "type": "Feature",
  "properties": {
    "iso:country":"ES",
    "sg:address":"Calle de Karranzairu, 8",
    "sg:city":"San Vicente De Barakaldo",
    "sg:orig_category":"Laboratorios Y Cl\u00cdnicas Veterinarias",
    "sg:phone":"+34 944 78 12 30",
    "sg:postcode":"48901",
    "sg:province":"Vizcaya",
    "wof:name":"Tejado Llorente Jose Ignacio",
    "wof:placetype":"venue"
},
  "geometry": {"coordinates":[-2.987404108,43.2967605591],"type":"Point"}
}