{
  "type": "Feature",
  "properties": {
    "iso:country":"ES",
    "sg:address":"Calle de Escuelas, 6",
    "sg:city":"Beniajan",
    "sg:orig_category":"Centros De Educaci\u00d3n Especial",
    "sg:phone":"+34 968 82 01 98",
    "sg:postcode":"30570",
    "sg:province":"Murcia",
    "wof:name":"Patronato Municipal Escuelas Infantiles",
    "wof:placetype":"venue"
},
  "geometry": {"coordinates":[-1.0717459917,37.9732437134],"type":"Point"}
}