{
  "type": "Feature",
  "properties": {
    "addr:full":"Calle de Gral Sanz Marques San Juan Puerto Rico, S/n Villaviciosa Odon Madrid 28670",
    "addr:housenumber":"s / n",
    "addr:postcode":"28670",
    "addr:street":"Calle De Gral Sanz Marques;Puerto Rico;Odon",
    "iso:country":"ES",
    "sg:address":"Calle de Gral Sanz Marques San Juan Puerto Rico, S/n",
    "sg:city":"Villaviciosa Odon",
    "sg:orig_category":"Asesor\u00cda Sobre Comunicaci\u00d3n De Empresas",
    "sg:phone":"+34 916 16 57 05",
    "sg:postcode":"28670",
    "sg:province":"Madrid",
    "wof:name":"J.mairata A.asociados S.a",
    "wof:placetype":"venue"
},
  "geometry": {"coordinates":[-3.9080140591,40.3641548157],"type":"Point"}
}