{
  "type": "Feature",
  "properties": {
    "iso:country":"ES",
    "sg:address":"Calle de San Leopoldo, 3",
    "sg:city":"Roquetas Mar",
    "sg:classifiers":[
        {
            "category":"Government",
            "subcategory":"City Hall",
            "type":"Public Place"
        }
    ],
    "sg:phone":"+34 950 32 46 66",
    "sg:postcode":"04740",
    "sg:province":"Almer\u00eda",
    "sg:tags":[
        "el",
        "alquiler",
        "extranjero",
        "villa",
        "de",
        "en"
    ],
    "wof:name":"Inmobiliaria Prosur E Hijos S.l.",
    "wof:placetype":"venue"
},
  "geometry": {"coordinates":[-2.6124989986,36.7638435364],"type":"Point"}
}