{
  "type": "Feature",
  "properties": {
    "addr:full":"Avda Schulz, 144 Gijon Asturias 33208",
    "addr:housenumber":"144",
    "addr:postcode":"33208",
    "addr:street":"Avda Schulz",
    "iso:country":"ES",
    "sg:address":"Avda Schulz, 144",
    "sg:city":"Gijon",
    "sg:orig_category":"Agentes Generales De Seguros",
    "sg:phone":"+34 985 38 04 13",
    "sg:postcode":"33208",
    "sg:province":"Asturias",
    "wof:name":"Tarno Garcia Juan Ramon",
    "wof:placetype":"venue"
},
  "geometry": {"coordinates":[-5.6661391258,43.5310401917],"type":"Point"}
}