{
  "type": "Feature",
  "properties": {
    "addr:full":"Rua Cesar Boente, 4 Pontevedra Pontevedra 36002",
    "addr:housenumber":"4",
    "addr:postcode":"36002",
    "addr:street":"Rua Cesar Boente",
    "iso:country":"ES",
    "sg:address":"Rua Cesar Boente, 4",
    "sg:city":"Pontevedra",
    "sg:orig_category":"Talleres: Ropa A Medida",
    "sg:phone":"+34 986 85 10 55",
    "sg:postcode":"36002",
    "sg:province":"Pontevedra",
    "wof:name":"Barcia Dominguez Manuel",
    "wof:placetype":"venue"
},
  "geometry": {"coordinates":[-8.6437339783,42.4332542419],"type":"Point"}
}