{
  "type": "Feature",
  "properties": {
    "iso:country":"ES",
    "sg:address":"Avda Alemania (de), 1",
    "sg:city":"Caceres",
    "sg:orig_category":"Carnicer\u00cdas, Carnicer\u00cdas",
    "sg:phone":"+34 927 21 44 41",
    "sg:postcode":"10001",
    "sg:province":"C\u00e1ceres",
    "wof:name":"Lancho Blazquez Miguel",
    "wof:placetype":"venue"
},
  "geometry": {"coordinates":[-6.3793888092,39.4679679871],"type":"Point"}
}