{
  "type": "Feature",
  "properties": {
    "addr:full":"Rua Varsovia (de), 12 Santiago De Compostela A Coru\u00f1a 15707",
    "addr:housenumber":"12",
    "addr:postcode":"15707",
    "addr:street":"Rua Varsovia De;Corun\u0303A",
    "iso:country":"ES",
    "sg:address":"Rua Varsovia (de), 12",
    "sg:city":"Santiago De Compostela",
    "sg:orig_category":"Asociaciones Y Clubs Deportivos",
    "sg:phone":"+34 981 57 73 14",
    "sg:postcode":"15707",
    "sg:province":"A Coru\u00f1a",
    "sg:website":"www.decimas.es",
    "wof:name":"Sport-street S. L.",
    "wof:placetype":"venue"
},
  "geometry": {"coordinates":[-8.5255126953,42.8828315735],"type":"Point"}
}