{
  "type": "Feature",
  "properties": {
    "iso:country":"ES",
    "sg:address":"Avda Valladolid, 17",
    "sg:city":"Palencia",
    "sg:orig_category":"Alquiler De V\u00cddeo",
    "sg:phone":"+34 979 71 08 65",
    "sg:postcode":"34004",
    "sg:province":"Palencia",
    "wof:name":"Video Club Goyo S.l.",
    "wof:placetype":"venue"
},
  "geometry": {"coordinates":[-4.5265340805,42.0011787415],"type":"Point"}
}