{
  "type": "Feature",
  "properties": {
    "addr:full":"Carrer de Torrijos, 11 Barcelona Barcelona 08012",
    "addr:housenumber":"11",
    "addr:postcode":"08012",
    "addr:street":"Carrer De Torrijos",
    "iso:country":"ES",
    "sg:address":"Carrer de Torrijos, 11",
    "sg:city":"Barcelona",
    "sg:orig_category":"Peluquer\u00cdas, Peluquer\u00cda Mixta",
    "sg:phone":"+34 932 19 66 77",
    "sg:postcode":"08012",
    "sg:province":"Barcelona",
    "wof:name":"Barcelo Perez Laura",
    "wof:placetype":"venue"
},
  "geometry": {"coordinates":[2.1592569351,41.4027862549],"type":"Point"}
}