{
  "type": "Feature",
  "properties": {
    "addr:full":"Carrer de Julia Alvarez, 5 Palma Islas Baleares 07004",
    "addr:housenumber":"5",
    "addr:postcode":"07004",
    "addr:street":"Carrer De Julia Alvarez",
    "iso:country":"ES",
    "sg:address":"Carrer de Julia Alvarez, 5",
    "sg:city":"Palma",
    "sg:orig_category":"Cajas De Ahorro",
    "sg:phone":"+34 971 49 84 13",
    "sg:postcode":"07004",
    "sg:province":"Islas Baleares",
    "sg:website":"www.sanostra.es",
    "wof:name":"Caja De Ahorros Y Monte De Piedad De Las Baleares",
    "wof:placetype":"venue"
},
  "geometry": {"coordinates":[2.6535749435,39.5797843933],"type":"Point"}
}