{
  "type": "Feature",
  "properties": {
    "addr:full":"Calle de Aragon, 20 Cabanillas Campo Guadalajara 19171",
    "addr:housenumber":"20",
    "addr:postcode":"19171",
    "addr:street":"Calle De Aragon",
    "iso:country":"ES",
    "sg:address":"Calle de Aragon, 20",
    "sg:city":"Cabanillas Campo",
    "sg:orig_category":"Seguros",
    "sg:phone":"+34 949 33 26 49",
    "sg:postcode":"19171",
    "sg:province":"Guadalajara",
    "wof:name":"Mapfre Servicios De Informatica S.a.",
    "wof:placetype":"venue"
},
  "geometry": {"coordinates":[-3.2346150875,40.6387672424],"type":"Point"}
}