{
  "type": "Feature",
  "properties": {
    "iso:country":"ES",
    "sg:address":"Ctra Cullar Vega (de), S/n",
    "sg:city":"Bobadilla",
    "sg:orig_category":"Empresas De Carpinter\u00cda De Madera",
    "sg:phone":"+34 958 20 29 95",
    "sg:postcode":"18015",
    "sg:province":"Granada",
    "wof:name":"Carpinteria Los Vados S.l.l.",
    "wof:placetype":"venue"
},
  "geometry": {"coordinates":[-3.673844099,37.1961631775],"type":"Point"}
}