{
  "type": "Feature",
  "properties": {
    "iso:country":"ES",
    "sg:address":"Calle de San Antonio, 25",
    "sg:city":"Estacion",
    "sg:orig_category":"Molduras, Junquillos, Listones Y Molduras Perforadas",
    "sg:phone":"+34 918 50 67 35",
    "sg:postcode":"28400",
    "sg:province":"Madrid",
    "wof:name":"Gonzalez Mendez Francisco",
    "wof:placetype":"venue"
},
  "geometry": {"coordinates":[-4.0109062195,40.6166267395],"type":"Point"}
}