{
  "type": "Feature",
  "properties": {
    "iso:country":"ES",
    "sg:address":"Pol Ind Poyo De Reva, S/n",
    "sg:city":"Riba-roja Turia",
    "sg:orig_category":"Madera Para Construcci\u00d3n E Industria",
    "sg:phone":"+34 961 66 70 58",
    "sg:postcode":"46190",
    "sg:province":"Valencia",
    "wof:name":"Tran Sabater S.a.",
    "wof:placetype":"venue"
},
  "geometry": {"coordinates":[-0.5698940158,39.5458450317],"type":"Point"}
}