{
  "type": "Feature",
  "properties": {
    "iso:country":"ES",
    "sg:address":"Carr Solades, 21",
    "sg:city":"Villarreal",
    "sg:orig_category":"M\u00c9dicos: Neumolog\u00cda",
    "sg:phone":"+34 964 52 08 99",
    "sg:postcode":"12540",
    "sg:province":"Castell\u00f3n",
    "wof:name":"Cortes Miro Jose Pascual",
    "wof:placetype":"venue"
},
  "geometry": {"coordinates":[-0.0952939987,39.9453048706],"type":"Point"}
}