{
  "type": "Feature",
  "properties": {
    "addr:full":"Calle de Canalejas, S/n Valencia Alcantara C\u00e1ceres 10500",
    "addr:housenumber":"s / n",
    "addr:postcode":"10500",
    "addr:street":"Calle De Canalejas;Alcantara Ca\u0301Ceres",
    "iso:country":"ES",
    "sg:address":"Calle de Canalejas, S/n",
    "sg:city":"Valencia Alcantara",
    "sg:orig_category":"Ense\u00d1anza, Formaci\u00d3n Profesional: Aprendizaje",
    "sg:phone":"+34 927 58 00 87",
    "sg:postcode":"10500",
    "sg:province":"C\u00e1ceres",
    "wof:name":"Direccion General De La Policia",
    "wof:placetype":"venue"
},
  "geometry": {"coordinates":[-7.2430539131,39.409614563],"type":"Point"}
}