{
  "type": "Feature",
  "properties": {
    "iso:country":"ES",
    "sg:address":"Calle de Alcala De Henares, 1",
    "sg:city":"Guadalajara",
    "sg:orig_category":"Molduras, Junquillos, Listones Y Molduras Perforadas",
    "sg:phone":"+34 949 22 20 28",
    "sg:postcode":"19003",
    "sg:province":"Guadalajara",
    "wof:name":"Perez Verdugo Francisco",
    "wof:placetype":"venue"
},
  "geometry": {"coordinates":[-3.1746430397,40.6301345825],"type":"Point"}
}