{
  "type": "Feature",
  "properties": {
    "iso:country":"ES",
    "sg:address":"Calle de Estanquillo, 2",
    "sg:city":"Puerta De Segura",
    "sg:orig_category":"Arquitectos",
    "sg:phone":"+34 953 48 70 41",
    "sg:postcode":"23360",
    "sg:province":"Ja\u00e9n",
    "wof:name":"Contraclave S.l.",
    "wof:placetype":"venue"
},
  "geometry": {"coordinates":[-2.7387928963,38.3557472229],"type":"Point"}
}