{
  "type": "Feature",
  "properties": {
    "addr:full":"Carrer de Tamarit I Gil (de), 6 Tortosa Tarragona 43500",
    "addr:postcode":"43500",
    "addr:street":"Carrer De Tamarit I Gil De",
    "iso:country":"ES",
    "sg:address":"Carrer de Tamarit I Gil (de), 6",
    "sg:city":"Tortosa",
    "sg:orig_category":"Electricidad: Instaladores",
    "sg:phone":"+34 977 50 41 19",
    "sg:postcode":"43500",
    "sg:province":"Tarragona",
    "wof:name":"Inta%acions Pallares S.l.",
    "wof:placetype":"venue"
},
  "geometry": {"coordinates":[0.5126799941,40.8176651001],"type":"Point"}
}