{
  "type": "Feature",
  "properties": {
    "iso:country":"ES",
    "sg:address":"Calle de Valdeperal, S/n",
    "sg:city":"Virgen Camino",
    "sg:orig_category":"Arreglo, Reparaci\u00d3n, Piezas Sueltas De Televisi\u00d3n, V\u00cddeo, Hi",
    "sg:phone":"+34 987 30 04 07",
    "sg:postcode":"24198",
    "sg:province":"Le\u00f3n",
    "wof:name":"Fierro Nicolas David",
    "wof:placetype":"venue"
},
  "geometry": {"coordinates":[-5.6392807961,42.5819282532],"type":"Point"}
}