{
  "type": "Feature",
  "properties": {
    "addr:full":"Afores, S/n Montferrer Lleida 25711",
    "addr:housenumber":"s / n",
    "addr:postcode":"25711",
    "addr:street":"Afores",
    "iso:country":"ES",
    "sg:address":"Afores, S/n",
    "sg:city":"Montferrer",
    "sg:orig_category":"Venta, Instalaci\u00d3n De Cocinas",
    "sg:phone":"+34 973 36 09 68",
    "sg:postcode":"25711",
    "sg:province":"Lleida",
    "wof:name":"Areny Grau Guillem",
    "wof:placetype":"venue"
},
  "geometry": {"coordinates":[1.3372823,42.3959007263],"type":"Point"}
}