{
  "type": "Feature",
  "properties": {
    "addr:full":"Calle de Sabina, 67 Puebla Alfinden Zaragoza 50171",
    "addr:housenumber":"67",
    "addr:postcode":"50171",
    "addr:street":"Calle De Sabina;Alfinden",
    "iso:country":"ES",
    "sg:address":"Calle de Sabina, 67",
    "sg:city":"Puebla Alfinden",
    "sg:orig_category":"Maquinaria Para Industrias Diversas",
    "sg:phone":"+34 976 10 78 87",
    "sg:postcode":"50171",
    "sg:province":"Zaragoza",
    "wof:name":"Turboship Servicios S.l.",
    "wof:placetype":"venue"
},
  "geometry": {"coordinates":[-0.7640075088,41.6423110962],"type":"Point"}
}