{
  "type": "Feature",
  "properties": {
    "iso:country":"ES",
    "sg:address":"Calle de Miguel Zubeldia, 20",
    "sg:city":"Seron",
    "sg:orig_category":"Empresas De Carpinter\u00cda De Madera",
    "sg:phone":"+34 950 42 61 31",
    "sg:postcode":"04890",
    "sg:province":"Almer\u00eda",
    "wof:name":"Sanchez Nieto Juan",
    "wof:placetype":"venue"
},
  "geometry": {"coordinates":[-2.5088489056,37.3436927795],"type":"Point"}
}