{
  "type": "Feature",
  "properties": {
    "iso:country":"ES",
    "sg:address":"Avda Reyes Catolicos, 96",
    "sg:city":"Villarrobledo",
    "sg:orig_category":"Negocio De Enlosados, Soler\u00cdas",
    "sg:phone":"+34 967 14 50 36",
    "sg:postcode":"02600",
    "sg:province":"Albacete",
    "wof:name":"Hijos De Mnuel Pati\u00f1o S.l.",
    "wof:placetype":"venue"
},
  "geometry": {"coordinates":[-2.5812571049,39.2839050293],"type":"Point"}
}