{
  "type": "Feature",
  "properties": {
    "iso:country":"ES",
    "sg:address":"Calle de Arabial, 81",
    "sg:city":"Granada",
    "sg:orig_category":"Ense\u00d1anza Superior Privada",
    "sg:phone":"+34 958 29 11 35",
    "sg:postcode":"18004",
    "sg:province":"Granada",
    "sg:website":"www.ugr.es/local/garnata",
    "wof:name":"Colegio Mayor Garnata",
    "wof:placetype":"venue"
},
  "geometry": {"coordinates":[-3.611679554,37.1771087646],"type":"Point"}
}