{
  "type": "Feature",
  "properties": {
    "iso:country":"ES",
    "sg:address":"Mcdo. Panaderos, S/n",
    "sg:city":"Valladolid",
    "sg:orig_category":"Frutas, Legumbres Frescas Y Tempranas (al Por Menor)",
    "sg:phone":"+34 983 29 40 95",
    "sg:postcode":"47004",
    "sg:province":"Valladolid",
    "wof:name":"Gonzalez Matesanz Carlos",
    "wof:placetype":"venue"
},
  "geometry": {"coordinates":[-4.7222938538,41.6443405151],"type":"Point"}
}