{
  "type": "Feature",
  "properties": {
    "addr:full":"Calle de Vicente Blasco Iba\u00d1ez, 28 Sestao Vizcaya 48910",
    "addr:housenumber":"28",
    "addr:postcode":"48910",
    "addr:street":"Calle De Vicente Blasco Iban\u0303Ez",
    "iso:country":"ES",
    "sg:address":"Calle de Vicente Blasco Iba\u00d1ez, 28",
    "sg:city":"Sestao",
    "sg:orig_category":"Ropa Para Ni\u00d1os (al Por Menor)",
    "sg:phone":"+34 944 96 56 41",
    "sg:postcode":"48910",
    "sg:province":"Vizcaya",
    "wof:name":"Parri\u00f1a Elias Jose Fermin",
    "wof:placetype":"venue"
},
  "geometry": {"coordinates":[-3.0022089481,43.3076591492],"type":"Point"}
}