{
  "type": "Feature",
  "properties": {
    "iso:country":"ES",
    "sg:address":"Calle de Bravo Murillo, 21",
    "sg:city":"Madrid",
    "sg:orig_category":"Peluqueros: De Se\u00d1oras",
    "sg:phone":"+34 914 48 87 21",
    "sg:postcode":"28015",
    "sg:province":"Madrid",
    "wof:name":"Arance Sanchez Magdalena",
    "wof:placetype":"venue"
},
  "geometry": {"coordinates":[-3.704349041,40.435546875],"type":"Point"}
}