{
  "type": "Feature",
  "properties": {
    "addr:full":"Avda Tirajana (de), 21 Playa Del Ingles Las Palmas 35100",
    "addr:housenumber":"21",
    "addr:postcode":"35100",
    "addr:street":"Avda Tirajana De",
    "iso:country":"ES",
    "sg:address":"Avda Tirajana (de), 21",
    "sg:city":"Playa Del Ingles",
    "sg:orig_category":"Caf\u00c9s, Bares, Cervecer\u00cdas",
    "sg:phone":"+34 928 76 41 93",
    "sg:postcode":"35100",
    "sg:province":"Las Palmas",
    "wof:name":"Keit Carrasco Brit",
    "wof:placetype":"venue"
},
  "geometry": {"coordinates":[-15.5790882111,27.7582702637],"type":"Point"}
}