{
  "type": "Feature",
  "properties": {
    "addr:full":"Calle de Alfonso Ferez, 12 Torres Cotillas Murcia 30565",
    "addr:housenumber":"12",
    "addr:postcode":"30565",
    "addr:street":"Calle De Alfonso Ferez",
    "iso:country":"ES",
    "sg:address":"Calle de Alfonso Ferez, 12",
    "sg:city":"Torres Cotillas",
    "sg:orig_category":"Abogados",
    "sg:phone":"+34 968 62 83 07",
    "sg:postcode":"30565",
    "sg:province":"Murcia",
    "wof:name":"Egea Almaida Joaquina",
    "wof:placetype":"venue"
},
  "geometry": {"coordinates":[-1.2420238256,38.0306854248],"type":"Point"}
}