{
  "type": "Feature",
  "properties": {
    "addr:full":"Calle de Pablo Iglesias, 12 Alacant Alicante 03004",
    "addr:housenumber":"12",
    "addr:postcode":"03004",
    "addr:street":"Calle De Pablo Iglesias",
    "iso:country":"ES",
    "sg:address":"Calle de Pablo Iglesias, 12",
    "sg:city":"Alacant",
    "sg:orig_category":"Electrodom\u00c9sticos (al Por Menor)",
    "sg:phone":"+34 965 20 39 83",
    "sg:postcode":"03004",
    "sg:province":"Alicante",
    "wof:name":"Riera Garcia Maria",
    "wof:placetype":"venue"
},
  "geometry": {"coordinates":[-0.4879519939,38.3476142883],"type":"Point"}
}