{
  "type": "Feature",
  "properties": {
    "iso:country":"ES",
    "sg:address":"Calle de Pintor Pablo Uranga, 17",
    "sg:city":"Vitoria-gasteiz",
    "sg:orig_category":"Prot\u00c9sicos Dentales",
    "sg:phone":"+34 945 20 05 69",
    "sg:postcode":"01008",
    "sg:province":"\u00c1lava",
    "wof:name":"Castresana Azcarraga Jorge",
    "wof:placetype":"venue"
},
  "geometry": {"coordinates":[-2.6863880157,42.845993042],"type":"Point"}
}