{
  "type": "Feature",
  "properties": {
    "iso:country":"ES",
    "sg:address":"Calle de Rioja, 86",
    "sg:city":"Leganes",
    "sg:orig_category":"Pescader\u00cdas (al Por Menor)",
    "sg:phone":"+34 916 88 85 74",
    "sg:postcode":"28915",
    "sg:province":"Madrid",
    "wof:name":"Vicente Moreno Fermin",
    "wof:placetype":"venue"
},
  "geometry": {"coordinates":[-3.7518880367,40.3309020996],"type":"Point"}
}