{
  "type": "Feature",
  "properties": {
    "addr:full":"Calle de Alcalde Rodolfo Varona, 1 Santo Domingo De La Calzada La Rioja 26250",
    "addr:housenumber":"1",
    "addr:postcode":"26250",
    "addr:street":"Calle De Alcalde Rodolfo Varona;Calzada;Rioja",
    "iso:country":"ES",
    "sg:address":"Calle de Alcalde Rodolfo Varona, 1",
    "sg:city":"Santo Domingo De La Calzada",
    "sg:orig_category":"Peluqueros: De Se\u00d1oras",
    "sg:phone":"+34 941 34 21 06",
    "sg:postcode":"26250",
    "sg:province":"La Rioja",
    "wof:name":"Carcamo Villar Maria Belen",
    "wof:placetype":"venue"
},
  "geometry": {"coordinates":[-2.9534521103,42.4399185181],"type":"Point"}
}