{
  "type": "Feature",
  "properties": {
    "iso:country":"ES",
    "sg:address":"Rond Calatrava, 18",
    "sg:city":"Ciudad Real",
    "sg:orig_category":"Inform\u00c1tica (estudios, Servicios, Asesor\u00cda, Formaci\u00d3n)",
    "sg:phone":"+34 926 25 55 99",
    "sg:postcode":"13003",
    "sg:province":"Ciudad Real",
    "wof:name":"Reguillo Moreno",
    "wof:placetype":"venue"
},
  "geometry": {"coordinates":[-3.9243309498,38.9899139404],"type":"Point"}
}