{
  "type": "Feature",
  "properties": {
    "addr:full":"Calle de Malaga (de), 1 Fuenlabrada Madrid 28945",
    "addr:housenumber":"1",
    "addr:postcode":"28945",
    "addr:street":"Calle De Malaga De",
    "iso:country":"ES",
    "sg:address":"Calle de Malaga (de), 1",
    "sg:city":"Fuenlabrada",
    "sg:orig_category":"Cl\u00cdnicas Dentales",
    "sg:phone":"+34 916 15 55 39",
    "sg:postcode":"28945",
    "sg:province":"Madrid",
    "wof:name":"Clisana Clinica Dental S.l.",
    "wof:placetype":"venue"
},
  "geometry": {"coordinates":[-3.7923429012,40.2880744934],"type":"Point"}
}