{
  "type": "Feature",
  "properties": {
    "addr:full":"Pl Quatre Cantons, 1 S. Cugat Valles Barcelona 08172",
    "addr:housenumber":"1",
    "addr:postcode":"08172",
    "addr:street":"Pl;Cantons;Barcelona",
    "iso:country":"ES",
    "sg:address":"Pl Quatre Cantons, 1",
    "sg:city":"S. Cugat Valles",
    "sg:orig_category":"Bancos",
    "sg:phone":"+34 936 74 14 04",
    "sg:postcode":"08172",
    "sg:province":"Barcelona",
    "wof:name":"Deutsche Bank S.a.e.",
    "wof:placetype":"venue"
},
  "geometry": {"coordinates":[2.0842399597,41.4679336548],"type":"Point"}
}