{
  "type": "Feature",
  "properties": {
    "addr:full":"Calle de Uria, 68 Oviedo Asturias 33003",
    "addr:housenumber":"68",
    "addr:postcode":"33003",
    "addr:street":"Calle De Uria",
    "iso:country":"ES",
    "sg:address":"Calle de Uria, 68",
    "sg:city":"Oviedo",
    "sg:orig_category":"Inmobiliaria (agencias)",
    "sg:phone":"+34 985 20 31 18",
    "sg:postcode":"33003",
    "sg:province":"Asturias",
    "wof:name":"Arquitecto Alfonso Torre S.l.",
    "wof:placetype":"venue"
},
  "geometry": {"coordinates":[-5.8534994125,43.3654899597],"type":"Point"}
}