{
  "type": "Feature",
  "properties": {
    "iso:country":"ES",
    "sg:address":"Calle de Lepanto, 20",
    "sg:city":"Monte Vedat",
    "sg:orig_category":"Producci\u00d3n, Venta De Productos De Agricultura Biol\u00d3gica",
    "sg:phone":"+34 961 57 37 94",
    "sg:postcode":"46901",
    "sg:province":"Valencia",
    "wof:name":"Agrodan S.a",
    "wof:placetype":"venue"
},
  "geometry": {"coordinates":[-0.476649791,39.4193840027],"type":"Point"}
}