{
  "type": "Feature",
  "properties": {
    "iso:country":"ES",
    "sg:address":"Carrer de Do\u00d1a Blanca, 114",
    "sg:city":"Manlleu",
    "sg:orig_category":"Fabrica De Charcuter\u00cda",
    "sg:phone":"+34 938 50 74 30",
    "sg:postcode":"08560",
    "sg:province":"Barcelona",
    "wof:name":"Fabrica D'embotits J.p.s.l.",
    "wof:placetype":"venue"
},
  "geometry": {"coordinates":[2.2822840214,42.0077972412],"type":"Point"}
}