{
  "type": "Feature",
  "properties": {
    "iso:country":"ES",
    "sg:address":"Ctra Tudela-tarazona, S/n",
    "sg:city":"Tudela",
    "sg:orig_category":"Guarder\u00cdas",
    "sg:phone":"+34 948 82 63 10",
    "sg:postcode":"31500",
    "sg:province":"Navarra",
    "wof:name":"Ayuntamiento De Tudela",
    "wof:placetype":"venue"
},
  "geometry": {"coordinates":[-1.6753686666,41.9952926636],"type":"Point"}
}