{
  "type": "Feature",
  "properties": {
    "addr:full":"Plaz Sauces (los), 1 Bara\u00f1ain Navarra 31010",
    "addr:postcode":"31010",
    "addr:street":"Plaz;Los;Baran\u0303Ain Navarra",
    "iso:country":"ES",
    "sg:address":"Plaz Sauces (los), 1",
    "sg:city":"Bara\u00f1ain",
    "sg:orig_category":"Edici\u00d3n De Diarios, Revistas, Boletines",
    "sg:phone":"+34 948 25 68 50",
    "sg:postcode":"31010",
    "sg:province":"Navarra",
    "sg:website":"www.eunsa.es",
    "wof:name":"Ediciones Universidad De Navarra",
    "wof:placetype":"venue"
},
  "geometry": {"coordinates":[-97.78224945069999,45.7040786743],"type":"Point"}
}