{
  "type": "Feature",
  "properties": {
    "iso:country":"ES",
    "sg:address":"Calle de San Antonio Maria Claret, 14",
    "sg:city":"Zaragoza",
    "sg:orig_category":"Mec\u00c1nico Del Autom\u00d3vil",
    "sg:phone":"+34 976 56 45 12",
    "sg:postcode":"50005",
    "sg:province":"Zaragoza",
    "wof:name":"Talleres Cusat S.l.",
    "wof:placetype":"venue"
},
  "geometry": {"coordinates":[-0.8943353295,41.6455841064],"type":"Point"}
}