{
  "type": "Feature",
  "properties": {
    "iso:country":"ES",
    "sg:address":"S. Agust\u00edn, 10",
    "sg:city":"Pedrajas S. Esteban",
    "sg:orig_category":"Frutas Y Legumbres Secas (al Por Mayor)",
    "sg:phone":"+34 983 62 56 18",
    "sg:postcode":"47430",
    "sg:province":"Valladolid",
    "wof:name":"Perez Martin Jose Luis",
    "wof:placetype":"venue"
},
  "geometry": {"coordinates":[-4.580698967,41.3408317566],"type":"Point"}
}