{
  "type": "Feature",
  "properties": {
    "iso:country":"ES",
    "sg:address":"Avda Teresa Pascual, S/n",
    "sg:city":"Benasal",
    "sg:orig_category":"Cooperativas Agr\u00cdcolas",
    "sg:phone":"+34 964 43 10 95",
    "sg:postcode":"12160",
    "sg:province":"Castell\u00f3n",
    "wof:name":"Cooperativa Agricola Benasalense",
    "wof:placetype":"venue"
},
  "geometry": {"coordinates":[-0.1375589967,40.3784103394],"type":"Point"}
}