{
  "type": "Feature",
  "properties": {
    "addr:full":"Calle de Nuevo Toledo, 19 Illescas Toledo 45200",
    "addr:housenumber":"19",
    "addr:postcode":"45200",
    "addr:street":"Calle De;Toledo",
    "iso:country":"ES",
    "sg:address":"Calle de Nuevo Toledo, 19",
    "sg:city":"Illescas",
    "sg:orig_category":"Carpinteros",
    "sg:phone":"+34 925 51 36 37",
    "sg:postcode":"45200",
    "sg:province":"Toledo",
    "wof:name":"P.v.c. Tres S.a.",
    "wof:placetype":"venue"
},
  "geometry": {"coordinates":[-3.8568089008,40.1154251099],"type":"Point"}
}