{
  "type": "Feature",
  "properties": {
    "iso:country":"ES",
    "sg:address":"Jardines, 4",
    "sg:city":"Pinos-puente",
    "sg:orig_category":"Inform\u00c1tica: Mantenimiento Y Reparaci\u00d3n De Ordenadores",
    "sg:phone":"+34 958 45 09 58",
    "sg:postcode":"18240",
    "sg:province":"Granada",
    "wof:name":"Espigares Sillero Jose",
    "wof:placetype":"venue"
},
  "geometry": {"coordinates":[-3.7521839142,37.2517814636],"type":"Point"}
}