{
  "type": "Feature",
  "properties": {
    "iso:country":"ES",
    "sg:address":"Ctra Matadepera, 197",
    "sg:city":"Terrassa",
    "sg:orig_category":"Bancos",
    "sg:phone":"+34 937 34 33 00",
    "sg:postcode":"08225",
    "sg:province":"Barcelona",
    "wof:name":"Banco Espa\u00d1ol De Credito S A",
    "wof:placetype":"venue"
},
  "geometry": {"coordinates":[2.0172119141,41.5757026672],"type":"Point"}
}