{
  "type": "Feature",
  "properties": {
    "iso:country":"ES",
    "sg:address":"Carrer de Barcelona, 68",
    "sg:city":"S. Feliu Codines",
    "sg:orig_category":"Aluminio Y Aleaciones (producci\u00d3n, Transformaci\u00d3n, Negocio)",
    "sg:phone":"+34 938 66 15 23",
    "sg:postcode":"08182",
    "sg:province":"Barcelona",
    "wof:name":"Aluminis Sant Feliu S.c.p.",
    "wof:placetype":"venue"
},
  "geometry": {"coordinates":[2.163040638,41.683807373],"type":"Point"}
}