{
  "type": "Feature",
  "properties": {
    "iso:country":"ES",
    "sg:address":"Carrer de Doctor Dou, 7",
    "sg:city":"Barcelona",
    "sg:orig_category":"Cer\u00c1mica Art\u00cdstica Y Decorativa",
    "sg:phone":"+34 933 17 69 06",
    "sg:postcode":"08001",
    "sg:province":"Barcelona",
    "sg:website":"www.ceramistescat.org",
    "wof:name":"Associacio Ceramistes De Catalunya",
    "wof:placetype":"venue"
},
  "geometry": {"coordinates":[2.1691265106,41.3822822571],"type":"Point"}
}