{
  "type": "Feature",
  "properties": {
    "iso:country":"ES",
    "sg:address":"Calle de Cardenal Almaraz, 4",
    "sg:city":"Palencia",
    "sg:orig_category":"Talleres: Ropa A Medida",
    "sg:phone":"+34 979 74 79 23",
    "sg:postcode":"34005",
    "sg:province":"Palencia",
    "wof:name":"Perez Alberdi Roberto",
    "wof:placetype":"venue"
},
  "geometry": {"coordinates":[-4.5354299545,42.0084686279],"type":"Point"}
}