{
  "type": "Feature",
  "properties": {
    "iso:country":"ES",
    "sg:address":"Calle de Reyes Benitez, 50",
    "sg:city":"Moron Frontera",
    "sg:orig_category":"Promotores Constructores",
    "sg:phone":"+34 954 85 28 92",
    "sg:postcode":"41530",
    "sg:province":"Sevilla",
    "wof:name":"Medina Torres S.l.",
    "wof:placetype":"venue"
},
  "geometry": {"coordinates":[-5.4520411491,37.117565155],"type":"Point"}
}