{
  "type": "Feature",
  "properties": {
    "addr:full":"Carrer de Consell De Cent, 432 Barcelona Barcelona 08013",
    "addr:housenumber":"432",
    "addr:postcode":"08013",
    "addr:street":"Carrer De Consell De Cent",
    "iso:country":"ES",
    "sg:address":"Carrer de Consell De Cent, 432",
    "sg:city":"Barcelona",
    "sg:orig_category":"Impresi\u00d3n Digital",
    "sg:phone":"+34 932 65 23 86",
    "sg:postcode":"08013",
    "sg:province":"Barcelona",
    "wof:name":"Migraf Digital S.l.",
    "wof:placetype":"venue"
},
  "geometry": {"coordinates":[2.174877882,41.3977928162],"type":"Point"}
}