{
  "type": "Feature",
  "properties": {
    "addr:full":"Calle de Rio Narcea, 30 Oviedo Asturias 33010",
    "addr:housenumber":"30",
    "addr:postcode":"33010",
    "addr:street":"Calle De Rio Narcea",
    "iso:country":"ES",
    "sg:address":"Calle de Rio Narcea, 30",
    "sg:city":"Oviedo",
    "sg:orig_category":"Mec\u00c1nico Del Autom\u00d3vil",
    "sg:phone":"+34 985 21 11 59",
    "sg:postcode":"33010",
    "sg:province":"Asturias",
    "wof:name":"Siero Asistencia S.l.",
    "wof:placetype":"venue"
},
  "geometry": {"coordinates":[-5.8227782249,43.3688468933],"type":"Point"}
}