{
  "type": "Feature",
  "properties": {
    "iso:country":"ES",
    "sg:address":"Calle de Eduardo Lucena, 2",
    "sg:city":"Cordoba",
    "sg:orig_category":"Diarios, Revistas Y Boletines (suscripciones)",
    "sg:phone":"+34 957 47 24 65",
    "sg:postcode":"14008",
    "sg:province":"C\u00f3rdoba",
    "wof:name":"Moreno Galvez Milagros",
    "wof:placetype":"venue"
},
  "geometry": {"coordinates":[-4.7810249329,37.886302948],"type":"Point"}
}