{
  "type": "Feature",
  "properties": {
    "iso:country":"ES",
    "sg:address":"Ctra Lorca, S/n",
    "sg:city":"Puerto Lumbreras",
    "sg:orig_category":"Veh\u00cdculos De Ocasi\u00d3n",
    "sg:phone":"+34 968 40 14 46",
    "sg:postcode":"30890",
    "sg:province":"Murcia",
    "wof:name":"Automurcia & Asociados Diaz Jordan S.l.",
    "wof:placetype":"venue"
},
  "geometry": {"coordinates":[-1.8079149723,37.5629501343],"type":"Point"}
}