{
  "type": "Feature",
  "properties": {
    "addr:full":"Pase Sagasta, 3 Zaragoza Zaragoza 50008",
    "addr:housenumber":"3",
    "addr:postcode":"50008",
    "iso:country":"ES",
    "sg:address":"Pase Sagasta, 3",
    "sg:city":"Zaragoza",
    "sg:orig_category":"Caf\u00c9s, Bares, Cervecer\u00cdas",
    "sg:phone":"+34 976 21 90 62",
    "sg:postcode":"50008",
    "sg:province":"Zaragoza",
    "wof:name":"Agustin Vera Fernando",
    "wof:placetype":"venue"
},
  "geometry": {"coordinates":[-0.8857334256,41.644367218],"type":"Point"}
}