{
  "type": "Feature",
  "properties": {
    "addr:full":"Pase Pintor Rosales, 82 Madrid Madrid 28008",
    "addr:housenumber":"82",
    "addr:postcode":"madrid;28008",
    "addr:street":"Pintor Rosales",
    "iso:country":"ES",
    "sg:address":"Pase Pintor Rosales, 82",
    "sg:city":"Madrid",
    "sg:orig_category":"Sociedades, Compa\u00d1\u00cdas Aseguradoras",
    "sg:phone":"+34 915 43 96 18",
    "sg:postcode":"28008",
    "sg:province":"Madrid",
    "wof:name":"Aon Re Iberia Correduria De Reaseguros S.a. Sociedad Unipersonal",
    "wof:placetype":"venue"
},
  "geometry": {"coordinates":[-3.7250509262,40.4323539734],"type":"Point"}
}