{
  "type": "Feature",
  "properties": {
    "addr:full":"Carrer de Doctor Marti I Julia, 82 Hospitalet Llobregat Barcelona 08903",
    "addr:housenumber":"82",
    "addr:postcode":"08903",
    "addr:street":"Carrer De Doctor Marti I Julia",
    "iso:country":"ES",
    "sg:address":"Carrer de Doctor Marti I Julia, 82",
    "sg:city":"Hospitalet Llobregat",
    "sg:orig_category":"Confecci\u00d3n De Ropa Interior",
    "sg:phone":"+34 934 48 43 31",
    "sg:postcode":"08903",
    "sg:province":"Barcelona",
    "wof:name":"El-do 2004",
    "wof:placetype":"venue"
},
  "geometry": {"coordinates":[2.1232099533,41.3728218079],"type":"Point"}
}