{
  "type": "Feature",
  "properties": {
    "addr:full":"Pol Ind Alboran, S/n Ceuta Ceuta 51003",
    "addr:housenumber":"s",
    "addr:postcode":"51003",
    "addr:street":"/ N",
    "iso:country":"ES",
    "sg:address":"Pol Ind Alboran, S/n",
    "sg:city":"Ceuta",
    "sg:orig_category":"Transporte En General",
    "sg:phone":"+34 956 50 91 30",
    "sg:postcode":"51003",
    "sg:province":"Ceuta",
    "wof:name":"Mimon Amar Mohamed",
    "wof:placetype":"venue"
},
  "geometry": {"coordinates":[-5.3508400917,35.879108429],"type":"Point"}
}