{
  "type": "Feature",
  "properties": {
    "iso:country":"ES",
    "sg:address":"Alam Recalde, 61",
    "sg:city":"Bilbao",
    "sg:orig_category":"Bancos",
    "sg:phone":"+34 944 22 23 07",
    "sg:postcode":"48010",
    "sg:province":"Vizcaya",
    "wof:name":"Hidalgo Cirion Nicolas",
    "wof:placetype":"venue"
},
  "geometry": {"coordinates":[-2.9368619919,43.2575874329],"type":"Point"}
}