{
  "type": "Feature",
  "properties": {
    "addr:full":"Calle de Arenal (el), 15 Noja Cantabria 39180",
    "addr:housenumber":"15",
    "addr:postcode":"39180",
    "addr:street":"Calle De Arenal El",
    "iso:country":"ES",
    "sg:address":"Calle de Arenal (el), 15",
    "sg:city":"Noja",
    "sg:classifiers":[
        {
            "category":"Taxi",
            "type":"Transportation"
        }
    ],
    "sg:phone":"+34 942 63 01 13",
    "sg:postcode":"39180",
    "sg:province":"Cantabria",
    "wof:name":"Viadero Carrera Nicasio",
    "wof:placetype":"venue"
},
  "geometry": {"coordinates":[-3.5202889442,43.4894943237],"type":"Point"}
}