{
  "type": "Feature",
  "properties": {
    "iso:country":"ES",
    "sg:address":"Calle de Gaztambide-carrera, 17",
    "sg:city":"Tudela",
    "sg:orig_category":"Bisuter\u00cda, Joyer\u00cda, Relojer\u00cda (al Por Menor)",
    "sg:phone":"+34 948 82 05 25",
    "sg:postcode":"31500",
    "sg:province":"Navarra",
    "wof:name":"Villar Crespo Luis",
    "wof:placetype":"venue"
},
  "geometry": {"coordinates":[-1.6035759449,42.0621376038],"type":"Point"}
}