{
  "type": "Feature",
  "properties": {
    "iso:country":"ES",
    "sg:address":"Calle de Eras, 42",
    "sg:city":"Encinas Reales",
    "sg:orig_category":"Perfumer\u00cda Y Cosm\u00c9tica (fabricaci\u00d3n, Al Por Mayor)",
    "sg:phone":"+34 957 59 71 59",
    "sg:postcode":"14913",
    "sg:province":"C\u00f3rdoba",
    "wof:name":"Italbeauty S.l.",
    "wof:placetype":"venue"
},
  "geometry": {"coordinates":[-4.4895515442,37.2732276917],"type":"Point"}
}