{
  "type": "Feature",
  "properties": {
    "addr:full":"Calle de Lopez Trigo, 29 Ayora Valencia 46620",
    "addr:housenumber":"29",
    "addr:postcode":"46620",
    "addr:street":"Calle De Lopez Trigo",
    "iso:country":"ES",
    "sg:address":"Calle de Lopez Trigo, 29",
    "sg:city":"Ayora",
    "sg:orig_category":"Fabricaci\u00d3n, Alquiler, Venta De Encofrados",
    "sg:phone":"+34 961 89 07 16",
    "sg:postcode":"46620",
    "sg:province":"Valencia",
    "wof:name":"Encoval Encofrados S.l:l.",
    "wof:placetype":"venue"
},
  "geometry": {"coordinates":[-1.0563739538,39.0630645752],"type":"Point"}
}