{
  "type": "Feature",
  "properties": {
    "iso:country":"ES",
    "sg:address":"Carrer de Castanyer, 30",
    "sg:city":"Barcelona",
    "sg:orig_category":"Molduras, Junquillos, Listones Y Molduras Perforadas",
    "sg:phone":"+34 934 18 54 62",
    "sg:postcode":"08022",
    "sg:province":"Barcelona",
    "wof:name":"Caceres Campos Francisco",
    "wof:placetype":"venue"
},
  "geometry": {"coordinates":[2.1394019127,41.407333374],"type":"Point"}
}