{
  "type": "Feature",
  "properties": {
    "addr:full":"Calle de Langreo, 4 Gijon Asturias 33206",
    "addr:housenumber":"4",
    "addr:postcode":"33206",
    "addr:street":"Calle De Langreo",
    "iso:country":"ES",
    "sg:address":"Calle de Langreo, 4",
    "sg:city":"Gijon",
    "sg:orig_category":"Inmobiliaria (agencias)",
    "sg:phone":"+34 985 34 13 03",
    "sg:postcode":"33206",
    "sg:province":"Asturias",
    "wof:name":"Felgueroso Villar Jose Luis",
    "wof:placetype":"venue"
},
  "geometry": {"coordinates":[-5.664411068,43.5407447815],"type":"Point"}
}