{
  "type": "Feature",
  "properties": {
    "addr:full":"Carrer de Alamos (los), 31 Mataro Barcelona 08301",
    "addr:housenumber":"31",
    "addr:postcode":"08301",
    "addr:street":"Carrer De Alamos Los",
    "iso:country":"ES",
    "sg:address":"Carrer de Alamos (los), 31",
    "sg:city":"Mataro",
    "sg:orig_category":"M\u00c9dicos: Estomatolog\u00cda",
    "sg:phone":"+34 937 96 21 53",
    "sg:postcode":"08301",
    "sg:province":"Barcelona",
    "wof:name":"Jorba Vives Marta",
    "wof:placetype":"venue"
},
  "geometry": {"coordinates":[2.4458420277,41.5451278687],"type":"Point"}
}