{
  "type": "Feature",
  "properties": {
    "iso:country":"ES",
    "sg:address":"Calle de Carmelitas, 27",
    "sg:city":"Ciudad Rodrigo",
    "sg:orig_category":"Ense\u00d1anza Secundaria: Colegios Y Escuelas Privadas",
    "sg:phone":"+34 923 48 05 04",
    "sg:postcode":"37500",
    "sg:province":"Salamanca",
    "wof:name":"Instituto De Bachillerato Fray Diego Tadeo Gonzalez",
    "wof:placetype":"venue"
},
  "geometry": {"coordinates":[-6.5253939629,40.6018486023],"type":"Point"}
}