{
  "type": "Feature",
  "properties": {
    "iso:country":"ES",
    "sg:address":"Calle de Juan Xxiii, 3",
    "sg:city":"Zaratan",
    "sg:orig_category":"Molduras, Junquillos, Listones Y Molduras Perforadas",
    "sg:phone":"+34 983 33 94 13",
    "sg:postcode":"47610",
    "sg:province":"Valladolid",
    "wof:name":"Baquero Cabrero Mercedes",
    "wof:placetype":"venue"
},
  "geometry": {"coordinates":[-4.783205986,41.6588363647],"type":"Point"}
}