{
  "type": "Feature",
  "properties": {
    "iso:country":"ES",
    "sg:address":"Carrer de Neptu, 14",
    "sg:city":"Barcelona",
    "sg:orig_category":"Bazares, Art\u00cdculos De Limpieza Y De Cocina (al Por Menor)",
    "sg:phone":"+34 932 37 73 50",
    "sg:postcode":"08006",
    "sg:province":"Barcelona",
    "wof:name":"Areas S.a.",
    "wof:placetype":"venue"
},
  "geometry": {"coordinates":[2.1548202038,41.3976898193],"type":"Point"}
}