{
  "type": "Feature",
  "properties": {
    "iso:country":"ES",
    "sg:address":"Calle de Montellano, 1",
    "sg:city":"Huelva",
    "sg:orig_category":"Agencias Y Agentes Comerciales, Representantes",
    "sg:phone":"+34 959 15 49 65",
    "sg:postcode":"21002",
    "sg:province":"Huelva",
    "wof:name":"Ortiz Valverde Manuel",
    "wof:placetype":"venue"
},
  "geometry": {"coordinates":[-6.9443159103,37.279800415],"type":"Point"}
}