{
  "type": "Feature",
  "properties": {
    "addr:full":"Calle de Venezuela, 22 Vitoria-gasteiz \u00c1lava 01012",
    "addr:housenumber":"22",
    "addr:postcode":"01012",
    "addr:street":"Calle De Venezuela",
    "iso:country":"ES",
    "sg:address":"Calle de Venezuela, 22",
    "sg:city":"Vitoria-gasteiz",
    "sg:orig_category":"Cajas De Ahorro",
    "sg:phone":"+34 945 28 57 66",
    "sg:postcode":"01012",
    "sg:province":"\u00c1lava",
    "wof:name":"Caja Vital",
    "wof:placetype":"venue"
},
  "geometry": {"coordinates":[-2.6785800457,42.8582229614],"type":"Point"}
}