{
  "type": "Feature",
  "properties": {
    "iso:country":"ES",
    "sg:address":"Avda Seneca, 2",
    "sg:city":"Madrid",
    "sg:orig_category":"Universidades",
    "sg:phone":"+34 914 52 04 00",
    "sg:postcode":"28...",
    "sg:province":"Madrid",
    "sg:website":"www.ucm.es",
    "wof:name":"Universidad Complutense De Madrid",
    "wof:placetype":"venue"
},
  "geometry": {"coordinates":[-3.7240519524,40.4372024536],"type":"Point"}
}