{
  "type": "Feature",
  "properties": {
    "addr:full":"Calle de Guerriller Romeu, S/n Alzira Valencia 46600",
    "addr:housenumber":"s",
    "addr:postcode":"46600",
    "addr:street":"Calle De Guerriller Romeu;/ N;Valencia",
    "iso:country":"ES",
    "sg:address":"Calle de Guerriller Romeu, S/n",
    "sg:city":"Alzira",
    "sg:orig_category":"Asilos De Ancianos. Centros Privados",
    "sg:phone":"+34 962 40 06 11",
    "sg:postcode":"46600",
    "sg:province":"Valencia",
    "wof:name":"Asociacion Sercoval",
    "wof:placetype":"venue"
},
  "geometry": {"coordinates":[-0.4394237101,39.1474533081],"type":"Point"}
}