{
  "type": "Feature",
  "properties": {
    "iso:country":"ES",
    "sg:address":"Av Generalitat, 5",
    "sg:city":"Santa Coloma De Gramenet",
    "sg:orig_category":"Ense\u00d1anza: Comercio, Gesti\u00d3n, Inform\u00c1tica",
    "sg:phone":"+34 933 85 64 11",
    "sg:postcode":"08922",
    "sg:province":"Barcelona",
    "wof:name":"Valls Bauza Carlos",
    "wof:placetype":"venue"
},
  "geometry": {"coordinates":[2.2099330425,41.4504432678],"type":"Point"}
}