{
  "type": "Feature",
  "properties": {
    "iso:country":"ES",
    "sg:address":"Carrer de Girona, 42",
    "sg:city":"S. Feliu Guixols",
    "sg:orig_category":"Inmobiliaria (agencias)",
    "sg:phone":"+34 972 32 03 28",
    "sg:postcode":"17220",
    "sg:province":"Girona",
    "sg:website":"www.donpiso.com",
    "wof:name":"Lobimatrix S.l.",
    "wof:placetype":"venue"
},
  "geometry": {"coordinates":[3.031069994,41.7835578918],"type":"Point"}
}