{
  "type": "Feature",
  "properties": {
    "addr:full":"Calle de Torrecilla, 9 San Jose Murcia 30817",
    "addr:housenumber":"9",
    "addr:postcode":"30817",
    "addr:street":"Calle De Torrecilla",
    "iso:country":"ES",
    "sg:address":"Calle de Torrecilla, 9",
    "sg:city":"San Jose",
    "sg:orig_category":"Empresas De Carpinter\u00cda De Madera",
    "sg:phone":"+34 968 46 73 19",
    "sg:postcode":"30817",
    "sg:province":"Murcia",
    "wof:name":"Carpilor S.c.",
    "wof:placetype":"venue"
},
  "geometry": {"coordinates":[-1.7245190144,37.6462936401],"type":"Point"}
}