{
  "type": "Feature",
  "properties": {
    "addr:full":"Calle de Sagasta, 34 Cartagena Murcia 30201",
    "addr:housenumber":"34",
    "addr:postcode":"30201",
    "addr:street":"Calle De Sagasta",
    "iso:country":"ES",
    "sg:address":"Calle de Sagasta, 34",
    "sg:city":"Cartagena",
    "sg:orig_category":"M\u00c9dicos: Oftalmolog\u00cda",
    "sg:phone":"+34 968 50 36 00",
    "sg:postcode":"30201",
    "sg:province":"Murcia",
    "wof:name":"Gutierrez Meca Maestre Dolores",
    "wof:placetype":"venue"
},
  "geometry": {"coordinates":[-1.0028640032,37.6411933899],"type":"Point"}
}