{
  "type": "Feature",
  "properties": {
    "iso:country":"ES",
    "sg:address":"Avda Rio Boladiez, 15",
    "sg:city":"Poligono Sta M. De Benquerencia",
    "sg:orig_category":"Aguas (distribuci\u00d3n, Servicios)",
    "sg:phone":"+34 925 23 36 54",
    "sg:postcode":"45007",
    "sg:province":"Toledo",
    "wof:name":"Ecosistemas Dosmil S.l.",
    "wof:placetype":"venue"
},
  "geometry": {"coordinates":[-3.9420568943,39.8666648865],"type":"Point"}
}