{
  "type": "Feature",
  "properties": {
    "iso:country":"ES",
    "sg:address":"Av Principal(pol Ind Oeste), S/n",
    "sg:city":"S. Gines",
    "sg:orig_category":"Fabricaci\u00d3n De Bibliotecas Y Estanter\u00cdas",
    "sg:phone":"+34 968 88 10 15",
    "sg:postcode":"30169",
    "sg:province":"Murcia",
    "wof:name":"Estanterias Majestic S.a.",
    "wof:placetype":"venue"
},
  "geometry": {"coordinates":[-1.1899290085,37.9529495239],"type":"Point"}
}