{
  "type": "Feature",
  "properties": {
    "iso:country":"ES",
    "sg:address":"Carrer de Joan Prim, 74",
    "sg:city":"Premia Mar",
    "sg:orig_category":"Lencer\u00cda Femenina, Corseter\u00cda, Trajes De Ba\u00d1o (al Por Menor)",
    "sg:phone":"+34 937 51 26 41",
    "sg:postcode":"08330",
    "sg:province":"Barcelona",
    "wof:name":"Garcia Cardero Maximina",
    "wof:placetype":"venue"
},
  "geometry": {"coordinates":[2.3578279018,41.4935913086],"type":"Point"}
}