{
  "type": "Feature",
  "properties": {
    "iso:country":"ES",
    "sg:address":"Calle de Pablo Picasso, 20",
    "sg:city":"Elda",
    "sg:orig_category":"Mec\u00c1nico Del Autom\u00d3vil",
    "sg:phone":"+34 965 39 52 08",
    "sg:postcode":"03600",
    "sg:province":"Alicante",
    "wof:name":"Pardo Morales Antonio",
    "wof:placetype":"venue"
},
  "geometry": {"coordinates":[-0.7886214256,38.4800758362],"type":"Point"}
}