{
  "type": "Feature",
  "properties": {
    "addr:full":"Calle de Salvador Manrique De Lara, 5 Palmas De Gran Canaria Las Palmas 35010",
    "addr:housenumber":"5",
    "addr:postcode":"35010",
    "addr:street":"Calle De Salvador Manrique De Lara",
    "iso:country":"ES",
    "sg:address":"Calle de Salvador Manrique De Lara, 5",
    "sg:city":"Palmas De Gran Canaria",
    "sg:orig_category":"Arquitectos",
    "sg:phone":"+34 928 22 72 33",
    "sg:postcode":"35010",
    "sg:province":"Las Palmas",
    "wof:name":"Garcia Viera Juan Francisco",
    "wof:placetype":"venue"
},
  "geometry": {"coordinates":[-15.4359149933,28.1308269501],"type":"Point"}
}