{
  "type": "Feature",
  "properties": {
    "iso:country":"ES",
    "sg:address":"Mare De Deu De Prat, 14",
    "sg:city":"S. Joan Abadesses",
    "sg:orig_category":"Escayola Y Productos De Escayola (fabricaci\u00d3n, Al Por Mayor)",
    "sg:phone":"+34 972 72 01 56",
    "sg:postcode":"17860",
    "sg:province":"Girona",
    "wof:name":"Tallant Orri Maria Dolors",
    "wof:placetype":"venue"
},
  "geometry": {"coordinates":[2.2800300121,42.235244751],"type":"Point"}
}