{
  "type": "Feature",
  "properties": {
    "iso:country":"ES",
    "sg:address":"Psaj Sancti-spiritus, 1",
    "sg:city":"Salamanca",
    "sg:orig_category":"Asociaciones Y Clubs Deportivos",
    "sg:phone":"+34 923 27 01 64",
    "sg:postcode":"37001",
    "sg:province":"Salamanca",
    "wof:name":"Pil Pack Carnero Garrote, S.l.",
    "wof:placetype":"venue"
},
  "geometry": {"coordinates":[-5.6600041389,40.96534729],"type":"Point"}
}