{
  "type": "Feature",
  "properties": {
    "iso:country":"ES",
    "sg:address":"Cruce De La Moraleda, S/n",
    "sg:city":"Moraleda Zafayona",
    "sg:orig_category":"Fabricaci\u00d3n De Enlosados, Soler\u00cdas",
    "sg:phone":"+34 958 44 32 52",
    "sg:postcode":"18370",
    "sg:province":"Granada",
    "wof:name":"Gomez Carrillo Salvador",
    "wof:placetype":"venue"
},
  "geometry": {"coordinates":[-3.9661040306,37.1709251404],"type":"Point"}
}