{
  "type": "Feature",
  "properties": {
    "addr:full":"Calle de Cardenal Herranz Casado, 11 Baena C\u00f3rdoba 14850",
    "addr:housenumber":"11",
    "addr:postcode":"14850",
    "addr:street":"Calle De Cardenal Herranz Casado",
    "iso:country":"ES",
    "sg:address":"Calle de Cardenal Herranz Casado, 11",
    "sg:city":"Baena",
    "sg:orig_category":"Panader\u00cdas, Panader\u00cdas",
    "sg:phone":"+34 957 67 02 18",
    "sg:postcode":"14850",
    "sg:province":"C\u00f3rdoba",
    "wof:name":"Tutau Trujillo Miguel",
    "wof:placetype":"venue"
},
  "geometry": {"coordinates":[-4.323964119,37.6170043945],"type":"Point"}
}