{
  "type": "Feature",
  "properties": {
    "iso:country":"ES",
    "sg:address":"Carr Mare Alberta, 42",
    "sg:city":"Pollen\u00e7a",
    "sg:orig_category":"Inmobiliaria (agencias)",
    "sg:phone":"+34 971 53 49 31",
    "sg:postcode":"07460",
    "sg:province":"Islas Baleares",
    "wof:name":"Thebest Villas Pollen\u00e7a S.l.",
    "wof:placetype":"venue"
},
  "geometry": {"coordinates":[3.0123579502,39.8740386963],"type":"Point"}
}