{
  "type": "Feature",
  "properties": {
    "iso:country":"ES",
    "sg:address":"Calle de Lepanto, 3",
    "sg:city":"San Miguel",
    "sg:orig_category":"Inmobiliaria (agencias)",
    "sg:phone":"+34 968 24 51 00",
    "sg:postcode":"30008",
    "sg:province":"Murcia",
    "sg:website":"www.inmobiliariadominguez.com",
    "wof:name":"Efcarre Oliver Maria Del Pilar",
    "wof:placetype":"venue"
},
  "geometry": {"coordinates":[-1.1305270195,37.9909095764],"type":"Point"}
}