{
  "type": "Feature",
  "properties": {
    "iso:country":"ES",
    "sg:address":"Calle de Plazuela (la), S/n",
    "sg:city":"Cazalla Sierra",
    "sg:orig_category":"Ense\u00d1anza, Formaci\u00d3n Profesional: Aprendizaje",
    "sg:phone":"+34 954 88 41 44",
    "sg:postcode":"41370",
    "sg:province":"Sevilla",
    "wof:name":"Instituto Nacional De La Seguridad Social",
    "wof:placetype":"venue"
},
  "geometry": {"coordinates":[-5.7597742081,37.9321289062],"type":"Point"}
}