{
  "type": "Feature",
  "properties": {
    "addr:full":"Calle de Moraza, 14 Donostia-san Sebastian Guip\u00f9zcoa 20006",
    "addr:housenumber":"14",
    "addr:postcode":"20006",
    "addr:street":"Calle De Moraza",
    "iso:country":"ES",
    "sg:address":"Calle de Moraza, 14",
    "sg:city":"Donostia-san Sebastian",
    "sg:orig_category":"Muebles, Minoristas",
    "sg:phone":"+34 943 46 04 33",
    "sg:postcode":"20006",
    "sg:province":"Guip\u00f9zcoa",
    "wof:name":"Landa Berasategui Santiago",
    "wof:placetype":"venue"
},
  "geometry": {"coordinates":[-1.9814749956,43.3144226074],"type":"Point"}
}