{
  "type": "Feature",
  "properties": {
    "addr:full":"Calle de Pinos Alta, 37 Madrid Madrid 28029",
    "addr:housenumber":"37",
    "addr:postcode":"madrid;28029",
    "addr:street":"Calle De Pinos Alta",
    "iso:country":"ES",
    "sg:address":"Calle de Pinos Alta, 37",
    "sg:city":"Madrid",
    "sg:orig_category":"Caf\u00c9s, Bares, Cervecer\u00cdas",
    "sg:phone":"+34 913 15 86 93",
    "sg:postcode":"28029",
    "sg:province":"Madrid",
    "wof:name":"Caribe C.b.",
    "wof:placetype":"venue"
},
  "geometry": {"coordinates":[-3.6967830658,40.4667205811],"type":"Point"}
}