{
  "type": "Feature",
  "properties": {
    "addr:full":"Avda Reina Mercedes, 35 Sevilla Sevilla 41012",
    "addr:housenumber":"35",
    "addr:postcode":"41012",
    "addr:street":"Avda Reina Mercedes",
    "iso:country":"ES",
    "sg:address":"Avda Reina Mercedes, 35",
    "sg:city":"Sevilla",
    "sg:classifiers":[
        {
            "category":"Personal",
            "subcategory":"Barber",
            "type":"Services"
        }
    ],
    "sg:phone":"+34 954 62 64 05",
    "sg:postcode":"41012",
    "sg:province":"Sevilla",
    "sg:tags":[
        "caballeros",
        "de",
        "peluqueros"
    ],
    "wof:name":"Marquez Rodriguez Jose",
    "wof:placetype":"venue"
},
  "geometry": {"coordinates":[-5.9859681129,37.3590621948],"type":"Point"}
}