{
  "type": "Feature",
  "properties": {
    "iso:country":"ES",
    "sg:address":"Calle de Aguirre Maximo, 11",
    "sg:city":"Bilbao",
    "sg:orig_category":"Abogados",
    "sg:phone":"+34 946 00 49 26",
    "sg:postcode":"48011",
    "sg:province":"Vizcaya",
    "wof:name":"Camarero Lopez Federico",
    "wof:placetype":"venue"
},
  "geometry": {"coordinates":[-2.9376244545,43.2637939453],"type":"Point"}
}