{
  "type": "Feature",
  "properties": {
    "addr:full":"Ctra. Pamplona, Km. 0011,2 Tiebas Navarra 31398",
    "addr:postcode":"31398",
    "addr:street":"Ctra. Pamplona Km. 0011,2",
    "iso:country":"ES",
    "sg:address":"Ctra. Pamplona, Km. 0011,2",
    "sg:city":"Tiebas",
    "sg:orig_category":"Distribuci\u00d3n De Petr\u00d3leo Y Derivados",
    "sg:phone":"+34 948 36 05 51",
    "sg:postcode":"31398",
    "sg:province":"Navarra",
    "wof:name":"Cepsa Comercial Norte S.l.",
    "wof:placetype":"venue"
},
  "geometry": {"coordinates":[-1.6787090302,42.6921768188],"type":"Point"}
}