{
  "type": "Feature",
  "properties": {
    "iso:country":"ES",
    "sg:address":"Av. Pio Xii, 24",
    "sg:city":"Iru\u00f1a",
    "sg:orig_category":"Inmobiliaria (agencias)",
    "sg:phone":"+34 948 25 27 97",
    "sg:postcode":"31008",
    "sg:province":"Navarra",
    "sg:website":"www.donpiso.com",
    "wof:name":"Venitice S.l.",
    "wof:placetype":"venue"
},
  "geometry": {"coordinates":[-1.6602870226,42.8076629639],"type":"Point"}
}