{
  "type": "Feature",
  "properties": {
    "addr:full":"Carr Ventura Sabater, 3 Begur Girona 17255",
    "addr:housenumber":"3",
    "addr:postcode":"17255",
    "addr:street":"Carr Ventura Sabater",
    "iso:country":"ES",
    "sg:address":"Carr Ventura Sabater, 3",
    "sg:city":"Begur",
    "sg:orig_category":"Inmobiliaria (agencias)",
    "sg:phone":"+34 972 62 24 12",
    "sg:postcode":"17255",
    "sg:province":"Girona",
    "wof:name":"Villa May Lluis",
    "wof:placetype":"venue"
},
  "geometry": {"coordinates":[3.2071299553,41.9541053772],"type":"Point"}
}