{
  "type": "Feature",
  "properties": {
    "addr:full":"Carr Vicente Zaragoza, 17 Silla Valencia 46460",
    "addr:housenumber":"17",
    "addr:postcode":"46460",
    "addr:street":"Carr Vicente Zaragoza",
    "iso:country":"ES",
    "sg:address":"Carr Vicente Zaragoza, 17",
    "sg:city":"Silla",
    "sg:orig_category":"Droguer\u00cdas (al Por Menor)",
    "sg:phone":"+34 961 21 38 04",
    "sg:postcode":"46460",
    "sg:province":"Valencia",
    "wof:name":"Molero Ratia Maria Isabel",
    "wof:placetype":"venue"
},
  "geometry": {"coordinates":[-0.411601007,39.3568725586],"type":"Point"}
}