{
  "type": "Feature",
  "properties": {
    "addr:full":"Calle de Regueron, S/n Pobladura Pelayo Garcia Le\u00f3n 24249",
    "addr:housenumber":"s / n",
    "addr:postcode":"24249",
    "addr:street":"Calle De Regueron;Leo\u0301N",
    "iso:country":"ES",
    "sg:address":"Calle de Regueron, S/n",
    "sg:city":"Pobladura Pelayo Garcia",
    "sg:orig_category":"Alimentaci\u00d3n General (al Por Menor)",
    "sg:phone":"+34 987 38 40 22",
    "sg:postcode":"24249",
    "sg:province":"Le\u00f3n",
    "wof:name":"Lozano Fernandez Julian",
    "wof:placetype":"venue"
},
  "geometry": {"coordinates":[-5.6835098267,42.3096656799],"type":"Point"}
}