{
  "type": "Feature",
  "properties": {
    "addr:full":"Avda Lancia, 21 Le\u00f3n Le\u00f3n 24004",
    "addr:housenumber":"21",
    "addr:postcode":"24004",
    "addr:street":"Avda Lancia;Leo\u0301N",
    "iso:country":"ES",
    "sg:address":"Avda Lancia, 21",
    "sg:city":"Le\u00f3n",
    "sg:orig_category":"Peluqueros: De Se\u00d1oras",
    "sg:phone":"+34 987 25 03 06",
    "sg:postcode":"24004",
    "sg:province":"Le\u00f3n",
    "wof:name":"Rodriguez Moran S.l.",
    "wof:placetype":"venue"
},
  "geometry": {"coordinates":[-5.5750541687,42.593547821],"type":"Point"}
}