{
  "type": "Feature",
  "properties": {
    "iso:country":"ES",
    "sg:address":"Calle de Marcelo Usera, 65",
    "sg:city":"Madrid",
    "sg:orig_category":"Peluquer\u00cdas, Peluquer\u00cda Mixta",
    "sg:phone":"+34 914 76 80 84",
    "sg:postcode":"28026",
    "sg:province":"Madrid",
    "sg:website":"www.marcoaldany.com",
    "wof:name":"Lunas Peluqueros Y Estilistas",
    "wof:placetype":"venue"
},
  "geometry": {"coordinates":[-3.7050755024,40.3858337402],"type":"Point"}
}