{
  "type": "Feature",
  "properties": {
    "iso:country":"ES",
    "sg:address":"Avda Ramon Y Cajal, 13",
    "sg:city":"Ayamonte",
    "sg:orig_category":"Centros De Coordinaci\u00d3n",
    "sg:phone":"+34 959 47 00 57",
    "sg:postcode":"21400",
    "sg:province":"Huelva",
    "wof:name":"Carnasea Martin Gillermo Jose",
    "wof:placetype":"venue"
},
  "geometry": {"coordinates":[-7.402589798,37.212184906],"type":"Point"}
}