{
  "type": "Feature",
  "properties": {
    "iso:country":"ES",
    "sg:address":"Calle de Manuel Aza\u00d1a, 29",
    "sg:city":"Almeria",
    "sg:orig_category":"Electricidad: Instaladores",
    "sg:phone":"+34 950 22 77 58",
    "sg:postcode":"04006",
    "sg:province":"Almer\u00eda",
    "wof:name":"Iluminacion Y Montajes Electricos Almeria S.l.",
    "wof:placetype":"venue"
},
  "geometry": {"coordinates":[-2.4466269016,36.8434486389],"type":"Point"}
}