{
  "type": "Feature",
  "properties": {
    "iso:country":"ES",
    "sg:address":"Calle de Prim, 26",
    "sg:city":"Donostia-san Sebastian",
    "sg:orig_category":"Clases De M\u00dasica Y Canto",
    "sg:phone":"+34 943 45 89 92",
    "sg:postcode":"20006",
    "sg:province":"Guip\u00f9zcoa",
    "wof:name":"Espinosa I\u00f1iguez Alejandro",
    "wof:placetype":"venue"
},
  "geometry": {"coordinates":[-1.9801449776,43.3154678345],"type":"Point"}
}