{
  "type": "Feature",
  "properties": {
    "iso:country":"ES",
    "sg:address":"C/ Maria Garcia Ferrandez, 2",
    "sg:city":"Elche",
    "sg:orig_category":"Alimentaci\u00d3n General (al Por Menor)",
    "sg:phone":"+34 965 44 01 92",
    "sg:postcode":"03205",
    "sg:province":"Alicante",
    "wof:name":"Pollos Guerrero S.l.",
    "wof:placetype":"venue"
},
  "geometry": {"coordinates":[-0.713786006,38.274936676],"type":"Point"}
}