{
  "type": "Feature",
  "properties": {
    "iso:country":"ES",
    "sg:address":"Circunvalacion, 15",
    "sg:city":"Nava De Arevalo",
    "sg:orig_category":"Carpinteros",
    "sg:phone":"+34 920 31 49 00",
    "sg:postcode":"05216",
    "sg:province":"\u00c1vila",
    "wof:name":"Soto Gonzalez Ricardo",
    "wof:placetype":"venue"
},
  "geometry": {"coordinates":[-4.7785902023,40.9769172668],"type":"Point"}
}