{
  "type": "Feature",
  "properties": {
    "iso:country":"ES",
    "sg:address":"Carr Andreu Tuyet I Santamaria, 17",
    "sg:city":"Girona",
    "sg:orig_category":"Estancos",
    "sg:phone":"+34 972 20 92 33",
    "sg:postcode":"17003",
    "sg:province":"Girona",
    "wof:name":"Casas Soy Maria Teresa",
    "wof:placetype":"venue"
},
  "geometry": {"coordinates":[2.8267168999,41.9725418091],"type":"Point"}
}