{
  "type": "Feature",
  "properties": {
    "addr:full":"Calle de Brezo, 1 Ciudad Real Ciudad Real 13197",
    "addr:housenumber":"1",
    "addr:postcode":"13197",
    "addr:street":"Calle De Brezo",
    "iso:country":"ES",
    "sg:address":"Calle de Brezo, 1",
    "sg:city":"Ciudad Real",
    "sg:orig_category":"Agencias Y Agentes Comerciales, Representantes",
    "sg:phone":"+34 926 21 66 24",
    "sg:postcode":"13197",
    "sg:province":"Ciudad Real",
    "wof:name":"Rico Cruz Eugenio",
    "wof:placetype":"venue"
},
  "geometry": {"coordinates":[-3.9424054623,38.9739456177],"type":"Point"}
}