{
  "type": "Feature",
  "properties": {
    "addr:full":"Calle de Jose Ruiz Ruiz, 37 Caudete Albacete 02660",
    "addr:housenumber":"37",
    "addr:postcode":"02660",
    "addr:street":"Calle De Jose Ruiz Ruiz",
    "iso:country":"ES",
    "sg:address":"Calle de Jose Ruiz Ruiz, 37",
    "sg:city":"Caudete",
    "sg:orig_category":"Laboratorios Y Trabajos De Fotograf\u00cda, V\u00cddeo Y Cine",
    "sg:phone":"+34 965 82 69 21",
    "sg:postcode":"02660",
    "sg:province":"Albacete",
    "wof:name":"Algarra Albero Francisco",
    "wof:placetype":"venue"
},
  "geometry": {"coordinates":[-0.9860622883,38.7050895691],"type":"Point"}
}