{
  "type": "Feature",
  "properties": {
    "addr:full":"Carrer de Santa Agata, 34 Barcelona Barcelona 08012",
    "addr:housenumber":"34",
    "addr:postcode":"08012",
    "addr:street":"Carrer De Santa Agata",
    "iso:country":"ES",
    "sg:address":"Carrer de Santa Agata, 34",
    "sg:city":"Barcelona",
    "sg:orig_category":"Agencias Y Asesores De Publicidad",
    "sg:phone":"+34 932 37 57 53",
    "sg:postcode":"08012",
    "sg:province":"Barcelona",
    "wof:name":"Monros & Associats S.c.p.",
    "wof:placetype":"venue"
},
  "geometry": {"coordinates":[2.1536619663,41.4047470093],"type":"Point"}
}