{
  "type": "Feature",
  "properties": {
    "iso:country":"ES",
    "sg:address":"Calle de Quintanar, 8",
    "sg:city":"Villalgordo Jucar",
    "sg:orig_category":"Cajas Para Embalar",
    "sg:phone":"+34 967 45 52 01",
    "sg:postcode":"02636",
    "sg:province":"Albacete",
    "sg:website":"www.ruralvia.com",
    "wof:name":"Caja Rural De Albacete",
    "wof:placetype":"venue"
},
  "geometry": {"coordinates":[-2.0641539097,39.2965316772],"type":"Point"}
}