{
  "type": "Feature",
  "properties": {
    "addr:full":"Calle de Felix De La Cruz, 91 Villanueva Pardillo Madrid 28229",
    "addr:housenumber":"91",
    "addr:postcode":"28229",
    "addr:street":"Calle De Felix De La Cruz",
    "iso:country":"ES",
    "sg:address":"Calle de Felix De La Cruz, 91",
    "sg:city":"Villanueva Pardillo",
    "sg:orig_category":"Inmobiliaria (agencias)",
    "sg:phone":"+34 918 10 70 34",
    "sg:postcode":"28229",
    "sg:province":"Madrid",
    "wof:name":"San Jose Chamizo Justo",
    "wof:placetype":"venue"
},
  "geometry": {"coordinates":[-3.9628689289,40.4892883301],"type":"Point"}
}