{
  "type": "Feature",
  "properties": {
    "addr:full":"Carr Purissima, 26 Benissa Alicante 03720",
    "addr:housenumber":"26",
    "addr:postcode":"03720",
    "addr:street":"Carr Purissima",
    "iso:country":"ES",
    "sg:address":"Carr Purissima, 26",
    "sg:city":"Benissa",
    "sg:orig_category":"Arquitectos",
    "sg:phone":"+34 965 73 40 14",
    "sg:postcode":"03720",
    "sg:province":"Alicante",
    "wof:name":"Giner Ginestar Pascual",
    "wof:placetype":"venue"
},
  "geometry": {"coordinates":[0.0507009998,38.7156944275],"type":"Point"}
}