{
  "type": "Feature",
  "properties": {
    "addr:full":"A Porteli\u00f1a, 46 Porteli\u00d1a Pontevedra 36416",
    "addr:housenumber":"46",
    "addr:postcode":"36416",
    "addr:street":"Portelin\u0303A",
    "iso:country":"ES",
    "sg:address":"A Porteli\u00f1a, 46",
    "sg:city":"Porteli\u00d1a",
    "sg:orig_category":"Formaci\u00d3n Continuada (variada)",
    "sg:phone":"+34 986 33 05 46",
    "sg:postcode":"36416",
    "sg:province":"Pontevedra",
    "wof:name":"Rodriguez Lago Manuel",
    "wof:placetype":"venue"
},
  "geometry": {"coordinates":[-8.6372375488,42.1915473938],"type":"Point"}
}