{
  "type": "Feature",
  "properties": {
    "iso:country":"ES",
    "sg:address":"Calle de Madre Maria Dolores Segarra, 2",
    "sg:city":"Rozas De Madrid",
    "sg:orig_category":"El Hogar: Amueblado, Acondicionamiento, Decoraci\u00d3n Y Mantenimiento",
    "sg:phone":"+34 916 37 04 26",
    "sg:postcode":"28230",
    "sg:province":"Madrid",
    "wof:name":"Martin Munuera Sl",
    "wof:placetype":"venue"
},
  "geometry": {"coordinates":[-3.8610260487,40.4857330322],"type":"Point"}
}