{
  "type": "Feature",
  "properties": {
    "addr:full":"Cra. Nacional Ii, Km. 0515,0 Fonolleres Lleida 25218",
    "addr:postcode":"25218",
    "addr:street":"Km. 0515,0",
    "iso:country":"ES",
    "sg:address":"Cra. Nacional Ii, Km. 0515,0",
    "sg:city":"Fonolleres",
    "sg:orig_category":"Jardiner\u00cdas, Vegetales, Art\u00cdculos De Jardiner\u00cda (al Por Menor)",
    "sg:phone":"+34 973 53 12 21",
    "sg:postcode":"25218",
    "sg:province":"Lleida",
    "wof:name":"Calafell Pont Antonio",
    "wof:placetype":"venue"
},
  "geometry": {"coordinates":[1.2230299711,41.6490097046],"type":"Point"}
}