{
  "type": "Feature",
  "properties": {
    "iso:country":"ES",
    "sg:address":"Calle de Torrobales, S/n",
    "sg:city":"Rincon Soto",
    "sg:orig_category":"Muebles Y Accesorios Para Cocinas Y Cuartos De Ba\u00d1o (al Por Menor)",
    "sg:phone":"+34 941 14 17 26",
    "sg:postcode":"26550",
    "sg:province":"La Rioja",
    "wof:name":"Cocinas Esmeralda S.l.",
    "wof:placetype":"venue"
},
  "geometry": {"coordinates":[-1.8486180305,42.2304801941],"type":"Point"}
}