{
  "type": "Feature",
  "properties": {
    "iso:country":"ES",
    "sg:address":"Mestre Serrano, 10",
    "sg:city":"Sedavi",
    "sg:orig_category":"Tapiceros Y Tapiceros",
    "sg:phone":"+34 963 75 33 86",
    "sg:postcode":"46910",
    "sg:province":"Valencia",
    "wof:name":"Telles Gonzalez Miguel",
    "wof:placetype":"venue"
},
  "geometry": {"coordinates":[-0.3872300088,39.4275627136],"type":"Point"}
}