{
  "type": "Feature",
  "properties": {
    "addr:full":"Avda Olimpica, 9 Alcobendas Madrid 28108",
    "addr:housenumber":"9",
    "addr:postcode":"28108",
    "addr:street":"Avda Olimpica",
    "iso:country":"ES",
    "sg:address":"Avda Olimpica, 9",
    "sg:city":"Alcobendas",
    "sg:orig_category":"Asociaciones Y Clubs Deportivos",
    "sg:phone":"+34 916 57 45 35",
    "sg:postcode":"28108",
    "sg:province":"Madrid",
    "sg:website":"www.decimas.es",
    "wof:name":"Sport-street S. L.",
    "wof:placetype":"venue"
},
  "geometry": {"coordinates":[-3.6369590759,40.5351638794],"type":"Point"}
}