{
  "type": "Feature",
  "properties": {
    "iso:country":"ES",
    "sg:address":"Avda Lugo (de), 59",
    "sg:city":"Monterroso",
    "sg:orig_category":"Asociaciones Humanitarias, De Cooperaci\u00d3n, De Acci\u00d3n Social",
    "sg:phone":"+34 982 37 70 81",
    "sg:postcode":"27560",
    "sg:province":"Lugo",
    "wof:name":"Asociacion Fenilcetonurica De Galicia",
    "wof:placetype":"venue"
},
  "geometry": {"coordinates":[-7.8316340446,42.7931404114],"type":"Point"}
}