{
  "type": "Feature",
  "properties": {
    "iso:country":"ES",
    "sg:address":"Luga Playa De Oza, 25",
    "sg:city":"Casablanca",
    "sg:orig_category":"Distribuci\u00d3n De Petr\u00d3leo Y Derivados",
    "sg:phone":"+34 981 13 36 95",
    "sg:postcode":"15006",
    "sg:province":"La Coru\u00f1a",
    "wof:name":"Merson Ltd",
    "wof:placetype":"venue"
},
  "geometry": {"coordinates":[-8.3964595795,43.3701095581],"type":"Point"}
}