{
  "type": "Feature",
  "properties": {
    "iso:country":"ES",
    "sg:address":"Calle de Obispo Cobos, 57",
    "sg:city":"Ubeda",
    "sg:orig_category":"Productores Recolectores, Venta Directa De Vinos",
    "sg:phone":"+34 953 75 00 06",
    "sg:postcode":"23400",
    "sg:province":"Ja\u00e9n",
    "wof:name":"Baltasar Lara Y Compa\u00d1ia S.a.",
    "wof:placetype":"venue"
},
  "geometry": {"coordinates":[-3.3760390282,38.011390686],"type":"Point"}
}