{
  "type": "Feature",
  "properties": {
    "iso:country":"ES",
    "sg:address":"Ctra Seu D'urgell(la), 55",
    "sg:city":"Ponts",
    "sg:orig_category":"Fabricaci\u00d3n De Motores El\u00c9ctricos",
    "sg:phone":"+34 973 46 00 32",
    "sg:postcode":"25740",
    "sg:province":"Lleida",
    "wof:name":"Hidrodata S.a.",
    "wof:placetype":"venue"
},
  "geometry": {"coordinates":[1.1865830421,41.9171104431],"type":"Point"}
}