{
  "type": "Feature",
  "properties": {
    "addr:full":"Carr Urxella, 23 Puerto De Pollen\u00c7a Islas Baleares 07470",
    "addr:housenumber":"23",
    "addr:postcode":"07470",
    "addr:street":"Carr Urxella",
    "iso:country":"ES",
    "sg:address":"Carr Urxella, 23",
    "sg:city":"Puerto De Pollen\u00c7a",
    "sg:orig_category":"Agencias De Viajes",
    "sg:phone":"+34 971 86 63 91",
    "sg:postcode":"07470",
    "sg:province":"Islas Baleares",
    "wof:name":"Rentals Pollensa",
    "wof:placetype":"venue"
},
  "geometry": {"coordinates":[3.0821900368,39.9063034058],"type":"Point"}
}