{
  "type": "Feature",
  "properties": {
    "iso:country":"ES",
    "sg:address":"Calle de Estacion, 14",
    "sg:city":"Daimiel",
    "sg:orig_category":"Lanas (al Por Menor)",
    "sg:phone":"+34 926 85 06 66",
    "sg:postcode":"13250",
    "sg:province":"Ciudad Real",
    "wof:name":"Gonzalez Del Campo Belmonte Miguela",
    "wof:placetype":"venue"
},
  "geometry": {"coordinates":[-3.6105237007,39.0664138794],"type":"Point"}
}