{
  "type": "Feature",
  "properties": {
    "iso:country":"ES",
    "sg:address":"Avda Madrid, 118",
    "sg:city":"Zaragoza",
    "sg:orig_category":"Bisuter\u00cda, Joyer\u00cda, Relojer\u00cda (al Por Menor)",
    "sg:phone":"+34 976 33 58 57",
    "sg:postcode":"50010",
    "sg:province":"Zaragoza",
    "wof:name":"Dominguez Lopez Maria Elena",
    "wof:placetype":"venue"
},
  "geometry": {"coordinates":[-0.908774972,41.6525230408],"type":"Point"}
}