{
  "type": "Feature",
  "properties": {
    "addr:full":"Avda Adelfas (las)-campoamor, S/n Dehesa Campoamor Alicante 03189",
    "addr:housenumber":"s / n",
    "addr:postcode":"03189",
    "addr:street":"Avda Adelfas Las Campoamor",
    "iso:country":"ES",
    "sg:address":"Avda Adelfas (las)-campoamor, S/n",
    "sg:city":"Dehesa Campoamor",
    "sg:orig_category":"Promotores Constructores",
    "sg:phone":"+34 965 96 60 55",
    "sg:postcode":"03189",
    "sg:province":"Alicante",
    "sg:website":"www.urbazamora.com",
    "wof:name":"Urbanizadora Zamora S.l.",
    "wof:placetype":"venue"
},
  "geometry": {"coordinates":[-0.7677609921,37.9303321838],"type":"Point"}
}