{
  "type": "Feature",
  "properties": {
    "addr:full":"Calle de Vida, 8 Valladolid Valladolid 47009",
    "addr:housenumber":"8",
    "addr:postcode":"47009",
    "addr:street":"Calle De Vida",
    "iso:country":"ES",
    "sg:address":"Calle de Vida, 8",
    "sg:city":"Valladolid",
    "sg:orig_category":"Doctores En Medicina",
    "sg:phone":"+34 983 37 49 35",
    "sg:postcode":"47009",
    "sg:province":"Valladolid",
    "wof:name":"Sesma Gomez Jesus",
    "wof:placetype":"venue"
},
  "geometry": {"coordinates":[-4.7436461449,41.6567001343],"type":"Point"}
}