{
  "type": "Feature",
  "properties": {
    "iso:country":"ES",
    "sg:address":"Calle de Congreso (el), 23",
    "sg:city":"Frontera",
    "sg:orig_category":"Partidos Pol\u00cdticos",
    "sg:phone":"+34 922 55 97 28",
    "sg:postcode":"38911",
    "sg:province":"Santa Cruz De Tenerife",
    "wof:name":"Agrupacion Herre\u00f1a Independiente",
    "wof:placetype":"venue"
},
  "geometry": {"coordinates":[-18.0088424683,27.7531166077],"type":"Point"}
}