{
  "type": "Feature",
  "properties": {
    "addr:full":"Av. Carlos Iii El Noble, 14 Iru\u00f1a Navarra 31002",
    "addr:housenumber":"14",
    "addr:postcode":"31002",
    "addr:street":"Av. Carlos Iii El Noble",
    "iso:country":"ES",
    "sg:address":"Av. Carlos Iii El Noble, 14",
    "sg:city":"Iru\u00f1a",
    "sg:orig_category":"Ense\u00d1anza Variada",
    "sg:phone":"+34 948 22 28 79",
    "sg:postcode":"31002",
    "sg:province":"Navarra",
    "wof:name":"Mateo Salvatierra Angel",
    "wof:placetype":"venue"
},
  "geometry": {"coordinates":[-1.6404459476,42.8139038086],"type":"Point"}
}