{
  "type": "Feature",
  "properties": {
    "addr:full":"Calle de Caballeros, 124 Villavieja Yeltes Salamanca 37260",
    "addr:housenumber":"124",
    "addr:postcode":"37260",
    "addr:street":"Calle De Caballeros",
    "iso:country":"ES",
    "sg:address":"Calle de Caballeros, 124",
    "sg:city":"Villavieja Yeltes",
    "sg:orig_category":"Frutas, Legumbres Frescas Y Tempranas (al Por Menor)",
    "sg:phone":"+34 923 51 90 41",
    "sg:postcode":"37260",
    "sg:province":"Salamanca",
    "wof:name":"Muelas Acedo Juan Domingo",
    "wof:placetype":"venue"
},
  "geometry": {"coordinates":[-6.4650378227,40.8751907349],"type":"Point"}
}