{
  "type": "Feature",
  "properties": {
    "iso:country":"ES",
    "sg:address":"Avda Alt Rei En Jaume I (l'), 3",
    "sg:city":"Altea",
    "sg:orig_category":"Asesor\u00cda Sobre Comunicaci\u00d3n De Empresas",
    "sg:phone":"+34 965 84 01 05",
    "sg:postcode":"03590",
    "sg:province":"Alicante",
    "wof:name":"Perez Alvado Geronimo 000401033-p Sl.. N E",
    "wof:placetype":"venue"
},
  "geometry": {"coordinates":[-0.048847001,38.6005897522],"type":"Point"}
}