{
  "type": "Feature",
  "properties": {
    "addr:full":"Luga Castelo, 23 Castelo La Coru\u00f1a 15168",
    "addr:housenumber":"23",
    "addr:postcode":"15168",
    "addr:street":"Castelo;La Corun\u0303A",
    "iso:country":"ES",
    "sg:address":"Luga Castelo, 23",
    "sg:city":"Castelo",
    "sg:orig_category":"Molduras, Junquillos, Listones Y Molduras Perforadas",
    "sg:phone":"+34 981 61 07 56",
    "sg:postcode":"15168",
    "sg:province":"La Coru\u00f1a",
    "wof:name":"Castro Cancelada Rosa",
    "wof:placetype":"venue"
},
  "geometry": {"coordinates":[-8.2781639099,43.3678283691],"type":"Point"}
}