{
  "type": "Feature",
  "properties": {
    "iso:country":"ES",
    "sg:address":"Avda Doctor Fleming, 30",
    "sg:city":"Le\u00f3n",
    "sg:orig_category":"Molduras, Junquillos, Listones Y Molduras Perforadas",
    "sg:phone":"+34 987 20 99 54",
    "sg:postcode":"24009",
    "sg:province":"Le\u00f3n",
    "wof:name":"Perez Alvarez Candido",
    "wof:placetype":"venue"
},
  "geometry": {"coordinates":[-5.5855789185,42.5971603394],"type":"Point"}
}