{
  "type": "Feature",
  "properties": {
    "iso:country":"ES",
    "sg:address":"Av Pineda (de La), 44",
    "sg:city":"Canonja",
    "sg:orig_category":"Fabricaci\u00d3n De Taburetes, Sillas Y Sillones",
    "sg:phone":"+34 977 54 09 39",
    "sg:postcode":"43110",
    "sg:province":"Tarragona",
    "wof:name":"Donato Sofas S.l.",
    "wof:placetype":"venue"
},
  "geometry": {"coordinates":[1.1845730543,41.11536026],"type":"Point"}
}