{
  "type": "Feature",
  "properties": {
    "addr:full":"Calle de Juan De Juni, 60 Tafira Alta Las Palmas 35017",
    "addr:housenumber":"60",
    "addr:postcode":"35017",
    "addr:street":"Calle De Juan De Juni;Alta",
    "iso:country":"ES",
    "sg:address":"Calle de Juan De Juni, 60",
    "sg:city":"Tafira Alta",
    "sg:orig_category":"Fabricaci\u00d3n, Distribuci\u00d3n De Discos, V\u00cddeodiscos Y Musicassettes",
    "sg:phone":"+34 928 35 46 95",
    "sg:postcode":"35017",
    "sg:province":"Las Palmas",
    "sg:website":"www.ggmusicandsound.com",
    "wof:name":"Gg Music And Sound S.l.",
    "wof:placetype":"venue"
},
  "geometry": {"coordinates":[-15.4709568024,28.051525116],"type":"Point"}
}