{
  "type": "Feature",
  "properties": {
    "addr:full":"Calle de Marques De Vadillo, 3 Soria Soria 42002",
    "addr:housenumber":"3",
    "addr:postcode":"42002",
    "addr:street":"Calle De Marques De Vadillo",
    "iso:country":"ES",
    "sg:address":"Calle de Marques De Vadillo, 3",
    "sg:city":"Soria",
    "sg:orig_category":"Farmacias",
    "sg:phone":"+34 975 21 11 83",
    "sg:postcode":"42002",
    "sg:province":"Soria",
    "wof:name":"Martinez Beltran Maria Victoria Ascension",
    "wof:placetype":"venue"
},
  "geometry": {"coordinates":[-2.468059063,41.7641296387],"type":"Point"}
}