{
  "type": "Feature",
  "properties": {
    "addr:full":"Calle de Barranco Del Termino, S/n Cenes Vega Granada 18190",
    "addr:housenumber":"s / n",
    "addr:postcode":"18190",
    "addr:street":"Calle De Barranco Del Termino",
    "iso:country":"ES",
    "sg:address":"Calle de Barranco Del Termino, S/n",
    "sg:city":"Cenes Vega",
    "sg:orig_category":"Motores Diessel",
    "sg:phone":"+34 958 48 61 87",
    "sg:postcode":"18190",
    "sg:province":"Granada",
    "wof:name":"Auto Cenes S.a.l.",
    "wof:placetype":"venue"
},
  "geometry": {"coordinates":[-3.5481681824,37.1628494263],"type":"Point"}
}