{
  "type": "Feature",
  "properties": {
    "iso:country":"ES",
    "sg:address":"Urbanizacion Parque Sur, 4",
    "sg:city":"Viloria",
    "sg:orig_category":"Inmobiliaria (agencias)",
    "sg:phone":"+34 987 51 06 02",
    "sg:postcode":"24316",
    "sg:province":"Le\u00f3n",
    "wof:name":"Sorpresas Y Anexas S.a.",
    "wof:placetype":"venue"
},
  "geometry": {"coordinates":[-6.4102668762,42.5867042542],"type":"Point"}
}