{
  "type": "Feature",
  "properties": {
    "iso:country":"ES",
    "sg:address":"Pol Ind San Cristobal, S/n",
    "sg:city":"Mogente",
    "sg:orig_category":"Cester\u00cda (fabricaci\u00d3n)",
    "sg:phone":"+34 962 26 08 40",
    "sg:postcode":"46640",
    "sg:province":"Valencia",
    "wof:name":"Cesteria Joar S.c.",
    "wof:placetype":"venue"
},
  "geometry": {"coordinates":[-0.754324019,38.8792114258],"type":"Point"}
}