{
  "type": "Feature",
  "properties": {
    "addr:full":"Pl. Espa\u00f1a, 22 Santiago Alcantara C\u00e1ceres 10510",
    "addr:housenumber":"22",
    "addr:postcode":"10510",
    "addr:street":"Pl. Espan\u0303A;Alcantara Ca\u0301Ceres",
    "iso:country":"ES",
    "sg:address":"Pl. Espa\u00f1a, 22",
    "sg:city":"Santiago Alcantara",
    "sg:orig_category":"Iglesia Cat\u00d3lica",
    "sg:phone":"+34 927 59 20 46",
    "sg:postcode":"10510",
    "sg:province":"C\u00e1ceres",
    "wof:name":"Parroquia De La Consolacion",
    "wof:placetype":"venue"
},
  "geometry": {"coordinates":[-7.2416229248,39.607334137],"type":"Point"}
}