{
  "type": "Feature",
  "properties": {
    "addr:full":"Calle de Cristo De La Victoria, 108 Madrid Madrid 28026",
    "addr:housenumber":"108",
    "addr:postcode":"28026",
    "addr:street":"Calle De Cristo De La Victoria",
    "iso:country":"ES",
    "sg:address":"Calle de Cristo De La Victoria, 108",
    "sg:city":"Madrid",
    "sg:orig_category":"Reposter\u00cdas",
    "sg:phone":"+34 914 75 30 67",
    "sg:postcode":"28026",
    "sg:province":"Madrid",
    "wof:name":"Martin Rodriguez Maria Del Carmen",
    "wof:placetype":"venue"
},
  "geometry": {"coordinates":[-3.7047884464,40.3796577454],"type":"Point"}
}