{
  "type": "Feature",
  "properties": {
    "iso:country":"ES",
    "sg:address":"Kale Alborkoin, 2",
    "sg:city":"Alegria-dulantzi",
    "sg:orig_category":"Maquinaria Y Herramientas Para Madera, Pvc, Aluminio Y Aperos (fabricaci\u00d3n, Comercio)",
    "sg:phone":"+34 945 40 08 92",
    "sg:postcode":"01240",
    "sg:province":"\u00c1lava",
    "wof:name":"Dulantzi S.l.",
    "wof:placetype":"venue"
},
  "geometry": {"coordinates":[-2.5141289234,42.8400802612],"type":"Point"}
}