{
  "type": "Feature",
  "properties": {
    "addr:full":"Calle de San Vicente Martir, 160 Valencia Valencia 46007",
    "addr:housenumber":"160",
    "addr:postcode":"46007",
    "addr:street":"Calle De San Vicente Martir",
    "iso:country":"ES",
    "sg:address":"Calle de San Vicente Martir, 160",
    "sg:city":"Valencia",
    "sg:orig_category":"Importaci\u00d3n",
    "sg:phone":"+34 963 17 26 07",
    "sg:postcode":"46007",
    "sg:province":"Valencia",
    "wof:name":"Top Traders S.l.",
    "wof:placetype":"venue"
},
  "geometry": {"coordinates":[-0.3825309873,39.4618988037],"type":"Point"}
}