{
  "type": "Feature",
  "properties": {
    "addr:full":"Ctra. Majadahonda, Km. 0002,6 Pozuelo Madrid 28223",
    "addr:postcode":"28223",
    "addr:street":"Ctra. Majadahonda Km. 0002,6",
    "iso:country":"ES",
    "sg:address":"Ctra. Majadahonda, Km. 0002,6",
    "sg:city":"Pozuelo",
    "sg:orig_category":"Camiser\u00cda Y Ropa Interior Masculina (al Por Menor)",
    "sg:phone":"+34 913 52 54 31",
    "sg:postcode":"28223",
    "sg:province":"Madrid",
    "wof:name":"Cordero Alonso Luis",
    "wof:placetype":"venue"
},
  "geometry": {"coordinates":[-3.8179600239,40.4291191101],"type":"Point"}
}