{
  "type": "Feature",
  "properties": {
    "iso:country":"ES",
    "sg:address":"Carrer de Teodor Gonzalez (de), 36",
    "sg:city":"Tortosa",
    "sg:orig_category":"Electrodom\u00c9sticos (al Por Menor)",
    "sg:phone":"+34 977 44 47 37",
    "sg:postcode":"43500",
    "sg:province":"Tarragona",
    "wof:name":"Electrodomestics Dolors S.c.c.l.",
    "wof:placetype":"venue"
},
  "geometry": {"coordinates":[0.5225539804,40.8102226257],"type":"Point"}
}