{
  "type": "Feature",
  "properties": {
    "iso:country":"ES",
    "sg:address":"Calle de Avila, 6",
    "sg:city":"San Sebastian De Los Reyes",
    "sg:orig_category":"Ense\u00d1anza Variada",
    "sg:phone":"+34 916 59 14 20",
    "sg:postcode":"28700",
    "sg:province":"Madrid",
    "sg:website":"www.gebeter.com",
    "wof:name":"Proactiva Formacion S.l.",
    "wof:placetype":"venue"
},
  "geometry": {"coordinates":[-3.6366727352,40.5490646362],"type":"Point"}
}