{
  "type": "Feature",
  "properties": {
    "iso:country":"ES",
    "sg:address":"Q. De Llano, 28",
    "sg:city":"Torre Mar",
    "sg:orig_category":"Abogados",
    "sg:phone":"+34 952 54 08 93",
    "sg:postcode":"29740",
    "sg:province":"M\u00e1laga",
    "wof:name":"Garcia Cordoba Manuel",
    "wof:placetype":"venue"
},
  "geometry": {"coordinates":[-4.1049766541,36.7418327332],"type":"Point"}
}