{
  "type": "Feature",
  "properties": {
    "addr:full":"Calle de Rio Mi\u00d1o, 35 Mostoles Madrid 28935",
    "addr:housenumber":"35",
    "addr:postcode":"28935",
    "addr:street":"Calle De Rio Min\u0303O",
    "iso:country":"ES",
    "sg:address":"Calle de Rio Mi\u00d1o, 35",
    "sg:city":"Mostoles",
    "sg:orig_category":"Muebles, Minoristas",
    "sg:phone":"+34 916 45 75 26",
    "sg:postcode":"28935",
    "sg:province":"Madrid",
    "wof:name":"Riofrio Fuerte Julian",
    "wof:placetype":"venue"
},
  "geometry": {"coordinates":[-3.8810889721,40.3149108887],"type":"Point"}
}