{
  "type": "Feature",
  "properties": {
    "iso:country":"ES",
    "sg:address":"Via Laietana, 45",
    "sg:city":"Barcelona",
    "sg:orig_category":"Empresarios",
    "sg:phone":"+34 933 42 60 46",
    "sg:postcode":"08003",
    "sg:province":"Barcelona",
    "sg:website":"www.fundacioequilibri.org",
    "wof:name":"Fundacio Equilibri",
    "wof:placetype":"venue"
},
  "geometry": {"coordinates":[2.1749839783,41.386631012],"type":"Point"}
}