{
  "type": "Feature",
  "properties": {
    "iso:country":"ES",
    "sg:address":"Ctra. Pamplona, 27",
    "sg:city":"Campanas",
    "sg:orig_category":"Administraci\u00d3n En Agricultura",
    "sg:phone":"+34 948 36 03 68",
    "sg:postcode":"31397",
    "sg:province":"Navarra",
    "wof:name":"Oroz Biurun Jc Y Mangado Pinillos P S.cv.",
    "wof:placetype":"venue"
},
  "geometry": {"coordinates":[-1.6374239922,42.6963653564],"type":"Point"}
}