{
  "type": "Feature",
  "properties": {
    "addr:full":"Carr Cervantes, 63 Algemesi Valencia 46680",
    "addr:housenumber":"63",
    "addr:postcode":"46680",
    "addr:street":"Carr Cervantes",
    "iso:country":"ES",
    "sg:address":"Carr Cervantes, 63",
    "sg:city":"Algemesi",
    "sg:orig_category":"Reposter\u00cdas",
    "sg:phone":"+34 962 48 02 84",
    "sg:postcode":"46680",
    "sg:province":"Valencia",
    "wof:name":"Sansaloni Carrascosa Vicente",
    "wof:placetype":"venue"
},
  "geometry": {"coordinates":[-0.4391309917,39.1935348511],"type":"Point"}
}