{
  "type": "Feature",
  "properties": {
    "iso:country":"ES",
    "sg:address":"Via Augusta, 132",
    "sg:city":"Barcelona",
    "sg:orig_category":"Tapicer\u00cdas",
    "sg:phone":"+34 934 14 07 12",
    "sg:postcode":"08006",
    "sg:province":"Barcelona",
    "wof:name":"Villegas Ca\u00f1ellas Pedro",
    "wof:placetype":"venue"
},
  "geometry": {"coordinates":[2.1458389759,41.4006881714],"type":"Point"}
}