{
  "type": "Feature",
  "properties": {
    "iso:country":"ES",
    "sg:address":"Cristofol De Moura, 59",
    "sg:city":"S. Adria Besos",
    "sg:orig_category":"Zapatos (al Por Menor)",
    "sg:phone":"+34 934 62 29 34",
    "sg:postcode":"08930",
    "sg:province":"Barcelona",
    "wof:name":"Bata S.a.espa\u00f1ola S.u.",
    "wof:placetype":"venue"
},
  "geometry": {"coordinates":[2.2153689861,41.4305000305],"type":"Point"}
}