{
  "type": "Feature",
  "properties": {
    "iso:country":"ES",
    "sg:address":"Don Francisco Pe\u00f1alver, 1",
    "sg:city":"Redovan",
    "sg:orig_category":"Psic\u00d3logos",
    "sg:phone":"+34 966 75 55 71",
    "sg:postcode":"03370",
    "sg:province":"Alicante",
    "wof:name":"Bas Lorenzo Leticia",
    "wof:placetype":"venue"
},
  "geometry": {"coordinates":[-0.9054669738,38.1110725403],"type":"Point"}
}