{
  "type": "Feature",
  "properties": {
    "addr:full":"Carr Gran Bretanya, 9 Igualada Barcelona 08700",
    "addr:housenumber":"9",
    "addr:postcode":"08700",
    "addr:street":"Carr Gran Bretanya",
    "iso:country":"ES",
    "sg:address":"Carr Gran Bretanya, 9",
    "sg:city":"Igualada",
    "sg:orig_category":"Materias Pl\u00c1sticas: Productos De Consumo Masivo (fabricaci\u00d3n, Al Por Mayor)",
    "sg:phone":"+34 938 03 10 18",
    "sg:postcode":"08700",
    "sg:province":"Barcelona",
    "wof:name":"Moncunill Claramunt Miguel",
    "wof:placetype":"venue"
},
  "geometry": {"coordinates":[1.6252299547,41.5903739929],"type":"Point"}
}