{
  "type": "Feature",
  "properties": {
    "iso:country":"ES",
    "sg:address":"Cm\u00d1o Poio De Arriba, 22",
    "sg:city":"Poio De Arriba",
    "sg:orig_category":"Promotores Constructores",
    "sg:phone":"+34 986 87 40 71",
    "sg:postcode":"36163",
    "sg:province":"Pontevedra",
    "wof:name":"Odiga S.l.",
    "wof:placetype":"venue"
},
  "geometry": {"coordinates":[-8.6428003311,42.4304618835],"type":"Point"}
}