{
  "type": "Feature",
  "properties": {
    "iso:country":"ES",
    "sg:address":"Calle de Santa Ana, 1",
    "sg:city":"Villamayor Santiago",
    "sg:orig_category":"Centros Empresariales",
    "sg:phone":"+34 969 13 84 08",
    "sg:postcode":"16415",
    "sg:province":"Cuenca",
    "wof:name":"Autoservicio Villamayor Sl",
    "wof:placetype":"venue"
},
  "geometry": {"coordinates":[-2.9232459068,39.7292327881],"type":"Point"}
}