{
  "type": "Feature",
  "properties": {
    "iso:country":"ES",
    "sg:address":"Calle de Carlos Iii, 4",
    "sg:city":"Cartagena",
    "sg:orig_category":"Lencer\u00cda Femenina, Corseter\u00cda, Trajes De Ba\u00d1o (al Por Menor)",
    "sg:phone":"+34 968 12 50 64",
    "sg:postcode":"30201",
    "sg:province":"Murcia",
    "wof:name":"Rosalvi",
    "wof:placetype":"venue"
},
  "geometry": {"coordinates":[-0.9902377725,37.60546875],"type":"Point"}
}