{
  "type": "Feature",
  "properties": {
    "iso:country":"ES",
    "sg:address":"Calle de Amsterdam, 5",
    "sg:city":"Parla",
    "sg:orig_category":"Papel (al Por Mayor)",
    "sg:phone":"+34 916 05 00 79",
    "sg:postcode":"28980",
    "sg:province":"Madrid",
    "wof:name":"Prados Y Maqueda S.l.",
    "wof:placetype":"venue"
},
  "geometry": {"coordinates":[-3.7444341183,40.2397041321],"type":"Point"}
}