{
  "type": "Feature",
  "properties": {
    "iso:country":"ES",
    "sg:address":"Calle de Lope De Vega, 2",
    "sg:city":"Madrid",
    "sg:orig_category":"Audiovisuales (producci\u00d3n, Edici\u00d3n, Realizaci\u00d3n)",
    "sg:phone":"+34 914 29 18 12",
    "sg:postcode":"28014",
    "sg:province":"Madrid",
    "wof:name":"Gonzalez Balsa Jose Angel",
    "wof:placetype":"venue"
},
  "geometry": {"coordinates":[-3.698734045,40.4137992859],"type":"Point"}
}