{
  "type": "Feature",
  "properties": {
    "iso:country":"ES",
    "sg:address":"Via Julia, 53",
    "sg:city":"Barcelona",
    "sg:orig_category":"Ropa Para Se\u00d1oras Y Caballeros (al Por Menor)",
    "sg:phone":"+34 933 59 99 25",
    "sg:postcode":"08042",
    "sg:province":"Barcelona",
    "wof:name":"Hernandez Gonzalez Eleuterio",
    "wof:placetype":"venue"
},
  "geometry": {"coordinates":[2.1763119698,41.4406776428],"type":"Point"}
}