{
  "type": "Feature",
  "properties": {
    "addr:full":"Calle de Llerena, 43 Fuente Cantos Badajoz 06240",
    "addr:housenumber":"43",
    "addr:postcode":"06240",
    "addr:street":"Calle De Llerena",
    "iso:country":"ES",
    "sg:address":"Calle de Llerena, 43",
    "sg:city":"Fuente Cantos",
    "sg:orig_category":"Abogados",
    "sg:phone":"+34 924 58 00 24",
    "sg:postcode":"06240",
    "sg:province":"Badajoz",
    "wof:name":"Saban Gutierrez Carlos",
    "wof:placetype":"venue"
},
  "geometry": {"coordinates":[-6.3047919273,38.2472381592],"type":"Point"}
}