{
  "type": "Feature",
  "properties": {
    "addr:full":"Carrer de Artesa De Segre, 12 Barcelona Barcelona 08022",
    "addr:housenumber":"12",
    "addr:postcode":"08022",
    "addr:street":"Carrer De Artesa De Segre",
    "iso:country":"ES",
    "sg:address":"Carrer de Artesa De Segre, 12",
    "sg:city":"Barcelona",
    "sg:orig_category":"Costureras",
    "sg:phone":"+34 932 11 78 14",
    "sg:postcode":"08022",
    "sg:province":"Barcelona",
    "wof:name":"Forns Rovira Maria Rosa",
    "wof:placetype":"venue"
},
  "geometry": {"coordinates":[2.1350209713,41.4032592773],"type":"Point"}
}