{
  "type": "Feature",
  "properties": {
    "iso:country":"ES",
    "sg:address":"Calle de Reyes Catolicos, 8",
    "sg:city":"Fuenlabrada De Los Montes",
    "sg:classifiers":[
        {
            "category":"Taxi",
            "type":"Transportation"
        }
    ],
    "sg:phone":"+34 924 65 66 17",
    "sg:postcode":"06660",
    "sg:province":"Badajoz",
    "wof:name":"Solana Babiano Guillermo",
    "wof:placetype":"venue"
},
  "geometry": {"coordinates":[-4.9328680038,39.1328773499],"type":"Point"}
}