{
  "type": "Feature",
  "properties": {
    "addr:full":"Calle de Joaquin Costa, 3 Santander Cantabria 39005",
    "addr:housenumber":"3",
    "addr:postcode":"39005",
    "addr:street":"Calle De Joaquin Costa",
    "iso:country":"ES",
    "sg:address":"Calle de Joaquin Costa, 3",
    "sg:city":"Santander",
    "sg:orig_category":"Promotores Constructores",
    "sg:phone":"+34 942 27 34 64",
    "sg:postcode":"39005",
    "sg:province":"Cantabria",
    "wof:name":"Riore\u00f1a S.l.",
    "wof:placetype":"venue"
},
  "geometry": {"coordinates":[-3.7860291004,43.4676589966],"type":"Point"}
}