{
  "type": "Feature",
  "properties": {
    "iso:country":"ES",
    "sg:address":"Pl Roige I Badia, 3",
    "sg:city":"Prat Llobregat",
    "sg:orig_category":"Cooperativas Agr\u00cdcolas",
    "sg:phone":"+34 933 79 14 00",
    "sg:postcode":"08820",
    "sg:province":"Barcelona",
    "wof:name":"Cooperativa Obrera De Viviendas",
    "wof:placetype":"venue"
},
  "geometry": {"coordinates":[2.0986840725,41.329410553],"type":"Point"}
}