{
  "type": "Feature",
  "properties": {
    "addr:full":"La Torre, 1 Alquerias Ni\u00f1o Perdido Castell\u00f3n 12539",
    "addr:housenumber":"1",
    "addr:postcode":"12539",
    "addr:street":"La Torre;Castello\u0301N",
    "iso:country":"ES",
    "sg:address":"La Torre, 1",
    "sg:city":"Alquerias Ni\u00f1o Perdido",
    "sg:orig_category":"\u00d3ptica: Instrumentos (fabricaci\u00d3n)",
    "sg:phone":"+34 964 51 29 22",
    "sg:postcode":"12539",
    "sg:province":"Castell\u00f3n",
    "wof:name":"Gari Martin S.l.",
    "wof:placetype":"venue"
},
  "geometry": {"coordinates":[-0.1130329967,39.8973236084],"type":"Point"}
}