{
  "type": "Feature",
  "properties": {
    "addr:full":"Calle de Mayor, 60 Alcantarilla Murcia 30820",
    "addr:housenumber":"60",
    "addr:postcode":"30820",
    "addr:street":"Calle De Mayor",
    "iso:country":"ES",
    "sg:address":"Calle de Mayor, 60",
    "sg:city":"Alcantarilla",
    "sg:orig_category":"Asesor\u00cda Sobre Comunicaci\u00d3n De Empresas",
    "sg:phone":"+34 968 80 84 05",
    "sg:postcode":"30820",
    "sg:province":"Murcia",
    "wof:name":"Mendez Bartolome Alfonso",
    "wof:placetype":"venue"
},
  "geometry": {"coordinates":[-1.2112059593,37.9709510803],"type":"Point"}
}