{
  "type": "Feature",
  "properties": {
    "iso:country":"ES",
    "sg:address":"Calle de Mayor, 20",
    "sg:city":"Grijota",
    "sg:orig_category":"Farmacias",
    "sg:phone":"+34 979 76 71 28",
    "sg:postcode":"34192",
    "sg:province":"Palencia",
    "wof:name":"Garre Contreras Jesus",
    "wof:placetype":"venue"
},
  "geometry": {"coordinates":[-4.5821390152,42.0523681641],"type":"Point"}
}