{
  "type": "Feature",
  "properties": {
    "iso:country":"ES",
    "sg:address":"Calle de Ambrosio Ballesteros, 6",
    "sg:city":"Torrijos",
    "sg:orig_category":"Muebles, Minoristas",
    "sg:phone":"+34 925 76 02 13",
    "sg:postcode":"45500",
    "sg:province":"Toledo",
    "wof:name":"Muebles Carrasco Alonso S.l.",
    "wof:placetype":"venue"
},
  "geometry": {"coordinates":[-4.2825317383,39.982635498],"type":"Point"}
}