{
  "type": "Feature",
  "properties": {
    "iso:country":"ES",
    "sg:address":"Calle de Eugenio Gonzalez Gil, 22",
    "sg:city":"Villalba Alcor",
    "sg:orig_category":"Contenedores (mercanc\u00cdas)",
    "sg:phone":"+34 959 42 03 18",
    "sg:postcode":"21860",
    "sg:province":"Huelva",
    "wof:name":"Cruzado Lozano Manuel",
    "wof:placetype":"venue"
},
  "geometry": {"coordinates":[-6.4778661728,37.3964691162],"type":"Point"}
}