{
  "type": "Feature",
  "properties": {
    "addr:full":"Calle de Nueva Zelanda, 20 Salamanca Salamanca 37003",
    "addr:housenumber":"20",
    "addr:postcode":"37003",
    "addr:street":"Calle De Nueva Zelanda",
    "iso:country":"ES",
    "sg:address":"Calle de Nueva Zelanda, 20",
    "sg:city":"Salamanca",
    "sg:orig_category":"Droguer\u00cdas (al Por Menor)",
    "sg:phone":"+34 923 18 47 41",
    "sg:postcode":"37003",
    "sg:province":"Salamanca",
    "wof:name":"Viloria Calvo Maria Teresa",
    "wof:placetype":"venue"
},
  "geometry": {"coordinates":[-5.6428527832,40.9716796875],"type":"Point"}
}