{
  "type": "Feature",
  "properties": {
    "iso:country":"ES",
    "sg:address":"Pase Florida, 26",
    "sg:city":"Madrid",
    "sg:orig_category":"\u00d3ptica: Instrumentos (fabricaci\u00d3n)",
    "sg:phone":"+34 915 41 88 47",
    "sg:postcode":"28008",
    "sg:province":"Madrid",
    "wof:name":"Garcia Mution Ana Belen",
    "wof:placetype":"venue"
},
  "geometry": {"coordinates":[-3.7245500088,40.4243049622],"type":"Point"}
}