{
  "type": "Feature",
  "properties": {
    "iso:country":"ES",
    "sg:address":"Calle de Maria Cristina, 10",
    "sg:city":"Brihuega",
    "sg:orig_category":"Muebles Y Accesorios Para Cocinas Y Cuartos De Ba\u00d1o (al Por Menor)",
    "sg:phone":"+34 949 28 04 30",
    "sg:postcode":"19400",
    "sg:province":"Guadalajara",
    "wof:name":"Garcia Soria Mobiliario S.l.",
    "wof:placetype":"venue"
},
  "geometry": {"coordinates":[-2.8713190556,40.763961792],"type":"Point"}
}