{
  "type": "Feature",
  "properties": {
    "addr:full":"Calle de Perfeccion, 6 Valladolid Valladolid 47010",
    "addr:housenumber":"6",
    "addr:postcode":"47010",
    "addr:street":"Calle De Perfeccion",
    "iso:country":"ES",
    "sg:address":"Calle de Perfeccion, 6",
    "sg:city":"Valladolid",
    "sg:orig_category":"M\u00c1rmoles, Granitos Y Piedras Naturales",
    "sg:phone":"+34 983 26 57 73",
    "sg:postcode":"47010",
    "sg:province":"Valladolid",
    "wof:name":"Ordu\u00f1a Aguilar Luis",
    "wof:placetype":"venue"
},
  "geometry": {"coordinates":[-4.7241849899,41.6599655151],"type":"Point"}
}