{
  "type": "Feature",
  "properties": {
    "addr:full":"Calle de Carbonell Y Morand, 3 Cordoba C\u00f3rdoba 14001",
    "addr:housenumber":"3",
    "addr:postcode":"14001",
    "addr:street":"Calle De Carbonell Y Morand;Co\u0301Rdoba",
    "iso:country":"ES",
    "sg:address":"Calle de Carbonell Y Morand, 3",
    "sg:city":"Cordoba",
    "sg:orig_category":"Arquitectos",
    "sg:phone":"+34 957 47 37 28",
    "sg:postcode":"14001",
    "sg:province":"C\u00f3rdoba",
    "wof:name":"Rebollo Puig Gabriel",
    "wof:placetype":"venue"
},
  "geometry": {"coordinates":[-4.7768125534,37.8868408203],"type":"Point"}
}