{
  "type": "Feature",
  "properties": {
    "addr:full":"Ptge Prim, 26 Barcelona Barcelona 08019",
    "addr:housenumber":"26",
    "addr:postcode":"08019",
    "addr:street":"Ptge Prim",
    "iso:country":"ES",
    "sg:address":"Ptge Prim, 26",
    "sg:city":"Barcelona",
    "sg:orig_category":"Empresas De Carpinter\u00cda De Madera",
    "sg:phone":"+34 933 05 26 02",
    "sg:postcode":"08019",
    "sg:province":"Barcelona",
    "wof:name":"Tamargo Fonta Juan",
    "wof:placetype":"venue"
},
  "geometry": {"coordinates":[2.216119051,41.4141464233],"type":"Point"}
}