{
  "type": "Feature",
  "properties": {
    "addr:full":"Carrer de Torres (gracia), 12 Barcelona Barcelona 08012",
    "addr:housenumber":"12",
    "addr:postcode":"08012",
    "addr:street":"Carrer De Torres Gracia",
    "iso:country":"ES",
    "sg:address":"Carrer de Torres (gracia), 12",
    "sg:city":"Barcelona",
    "sg:orig_category":"Ebanister\u00cda",
    "sg:phone":"+34 934 57 13 88",
    "sg:postcode":"08012",
    "sg:province":"Barcelona",
    "wof:name":"Sociedad Cooperativa Limitada Artesanos Cooperativos Sucesores De J. Taltavull",
    "wof:placetype":"venue"
},
  "geometry": {"coordinates":[2.1614460945,41.4007148743],"type":"Point"}
}