{
  "type": "Feature",
  "properties": {
    "addr:full":"Calle de Lezama Legizamon, 11 Legizamon Vizcaya 48450",
    "addr:housenumber":"11",
    "addr:postcode":"48450",
    "addr:street":"Calle De Lezama Legizamon",
    "iso:country":"ES",
    "sg:address":"Calle de Lezama Legizamon, 11",
    "sg:city":"Legizamon",
    "sg:orig_category":"Bebidas",
    "sg:phone":"+34 944 49 11 42",
    "sg:postcode":"48450",
    "sg:province":"Vizcaya",
    "wof:name":"Larris M.g. S.l.",
    "wof:placetype":"venue"
},
  "geometry": {"coordinates":[-2.8930881023,43.2473907471],"type":"Point"}
}