{
  "type": "Feature",
  "properties": {
    "addr:full":"Calle de Matiko, 5 Bilbao Vizcaya 48007",
    "addr:housenumber":"5",
    "addr:postcode":"48007",
    "addr:street":"Calle De Matiko",
    "iso:country":"ES",
    "sg:address":"Calle de Matiko, 5",
    "sg:city":"Bilbao",
    "sg:orig_category":"Inversiones",
    "sg:phone":"+34 944 46 64 89",
    "sg:postcode":"48007",
    "sg:province":"Vizcaya",
    "wof:name":"Organizacion Y Programacion De Inveersiones S.a.",
    "wof:placetype":"venue"
},
  "geometry": {"coordinates":[-2.9242930412,43.268081665],"type":"Point"}
}