{
  "type": "Feature",
  "properties": {
    "addr:full":"Praj Carretera De Pinoso, Km. 0001,0 Campo Abajo Murcia 30510",
    "addr:postcode":"30510",
    "addr:street":"Carretera De Pinoso Km. 0001,0",
    "iso:country":"ES",
    "sg:address":"Praj Carretera De Pinoso, Km. 0001,0",
    "sg:city":"Campo Abajo",
    "sg:orig_category":"Fabricaci\u00d3n De Productos Textiles Sin Tejer",
    "sg:phone":"+34 968 75 33 70",
    "sg:postcode":"30510",
    "sg:province":"Murcia",
    "wof:name":"Jospumar S.l.",
    "wof:placetype":"venue"
},
  "geometry": {"coordinates":[-1.1149940491,38.6145591736],"type":"Point"}
}