{
  "type": "Feature",
  "properties": {
    "iso:country":"ES",
    "sg:address":"Calle de Emigrantes, 10",
    "sg:city":"Madrid",
    "sg:orig_category":"Distribuci\u00d3n De Petr\u00d3leo Y Derivados",
    "sg:phone":"+34 913 00 40 09",
    "sg:postcode":"28043",
    "sg:province":"Madrid",
    "wof:name":"Greemoil S.a.",
    "wof:placetype":"venue"
},
  "geometry": {"coordinates":[-3.636600256,40.4667625427],"type":"Point"}
}