{
  "type": "Feature",
  "properties": {
    "iso:country":"ES",
    "sg:address":"As Barreiras, 19",
    "sg:city":"Loureda",
    "sg:orig_category":"Centros Empresariales",
    "sg:phone":"+34 981 63 39 45",
    "sg:postcode":"15141",
    "sg:province":"La Coru\u00f1a",
    "wof:name":"Gelibra Arteixo Servicios De Mantenimiento S.l.",
    "wof:placetype":"venue"
},
  "geometry": {"coordinates":[-8.4798288345,43.3172454834],"type":"Point"}
}