{
  "type": "Feature",
  "properties": {
    "iso:country":"ES",
    "sg:address":"Carrer de Consell De Cent, 366",
    "sg:city":"Barcelona",
    "sg:orig_category":"Fotograf\u00cda Art\u00cdstica Y Retratos",
    "sg:phone":"+34 932 15 66 38",
    "sg:postcode":"08009",
    "sg:province":"Barcelona",
    "wof:name":"Par Gali Ignacio",
    "wof:placetype":"venue"
},
  "geometry": {"coordinates":[2.1704990864,41.3945274353],"type":"Point"}
}