{
  "type": "Feature",
  "properties": {
    "iso:country":"ES",
    "sg:address":"Avda Juan Grande De, S/n",
    "sg:city":"Malaga",
    "sg:orig_category":"Caf\u00c9s, Bares, Cervecer\u00cdas",
    "sg:phone":"+34 952 26 81 46",
    "sg:postcode":"29014",
    "sg:province":"M\u00e1laga",
    "wof:name":"Ruiz Montiel Francisca",
    "wof:placetype":"venue"
},
  "geometry": {"coordinates":[-4.4241552353,36.7566223145],"type":"Point"}
}