{
  "type": "Feature",
  "properties": {
    "iso:country":"ES",
    "sg:address":"Carrer de Convent, 50",
    "sg:city":"Sabadell",
    "sg:orig_category":"Fabricaci\u00d3n De Telas Y Sedas",
    "sg:phone":"+34 937 25 17 93",
    "sg:postcode":"08202",
    "sg:province":"Barcelona",
    "wof:name":"Vilarrubias Boy Carlos",
    "wof:placetype":"venue"
},
  "geometry": {"coordinates":[2.1086790562,41.5508308411],"type":"Point"}
}