{
  "type": "Feature",
  "properties": {
    "iso:country":"ES",
    "sg:address":"Pque Lamera, 1",
    "sg:city":"Bermeo",
    "sg:orig_category":"Cajas De Ahorro",
    "sg:phone":"+34 946 88 28 91",
    "sg:postcode":"48370",
    "sg:province":"Vizcaya",
    "wof:name":"Bilbao Bizkaia Kutxa",
    "wof:placetype":"venue"
},
  "geometry": {"coordinates":[-2.7212541103,43.4193115234],"type":"Point"}
}