{
  "type": "Feature",
  "properties": {
    "iso:country":"ES",
    "sg:address":"Av Pais Valenciano, 57",
    "sg:city":"Guardamar Segura",
    "sg:orig_category":"Inmobiliaria (agencias)",
    "sg:phone":"+34 965 72 99 68",
    "sg:postcode":"03140",
    "sg:province":"Alicante",
    "wof:name":"Guardamar Inmogestion S.l.",
    "wof:placetype":"venue"
},
  "geometry": {"coordinates":[-0.653832972,38.0869483948],"type":"Point"}
}