{
  "type": "Feature",
  "properties": {
    "addr:full":"Calle de General Vara De Rey, 9 Logro\u00f1o La Rioja 26002",
    "addr:housenumber":"9",
    "addr:postcode":"26002",
    "addr:street":"Calle De General Vara De Rey;Rioja",
    "iso:country":"ES",
    "sg:address":"Calle de General Vara De Rey, 9",
    "sg:city":"Logro\u00f1o",
    "sg:orig_category":"Cl\u00cdnicas M\u00c9dicas",
    "sg:phone":"+34 941 24 38 68",
    "sg:postcode":"26002",
    "sg:province":"La Rioja",
    "wof:name":"Clinica Ginesalud S.l.",
    "wof:placetype":"venue"
},
  "geometry": {"coordinates":[-2.4466691017,42.4585189819],"type":"Point"}
}