{
  "type": "Feature",
  "properties": {
    "iso:country":"ES",
    "sg:address":"Psaj Azahares (los), S/n",
    "sg:city":"Sevilla",
    "sg:orig_category":"Electrodom\u00c9sticos (al Por Menor)",
    "sg:phone":"+34 954 22 42 64",
    "sg:postcode":"41003",
    "sg:province":"Sevilla",
    "wof:name":"Navarro Garcia Mari Del Aguila",
    "wof:placetype":"venue"
},
  "geometry": {"coordinates":[-5.9933772087,37.3938102722],"type":"Point"}
}