{
  "type": "Feature",
  "properties": {
    "iso:country":"ES",
    "sg:address":"Ctra Pinos Puente, 3",
    "sg:city":"Atarfe",
    "sg:orig_category":"Piedra, Vidrio, Cer\u00c1mica Y Porcelana",
    "sg:phone":"+34 958 43 73 69",
    "sg:postcode":"18230",
    "sg:province":"Granada",
    "wof:name":"Ceramica Arabe Los Arrayanes S.l.",
    "wof:placetype":"venue"
},
  "geometry": {"coordinates":[-3.7151238918,37.2666282654],"type":"Point"}
}