{
  "type": "Feature",
  "properties": {
    "addr:full":"Calle de Balmes, S/n Salamanca Salamanca 37008",
    "addr:housenumber":"s / n",
    "addr:postcode":"37008",
    "addr:street":"Calle De Balmes",
    "iso:country":"ES",
    "sg:address":"Calle de Balmes, S/n",
    "sg:city":"Salamanca",
    "sg:orig_category":"Promotores Constructores",
    "sg:phone":"+34 923 21 05 11",
    "sg:postcode":"37008",
    "sg:province":"Salamanca",
    "wof:name":"Dragados S.a.",
    "wof:placetype":"venue"
},
  "geometry": {"coordinates":[-5.6694712639,40.961101532],"type":"Point"}
}