{
  "type": "Feature",
  "properties": {
    "iso:country":"ES",
    "sg:address":"Av Cala Petita, 10",
    "sg:city":"Porto Cristo",
    "sg:orig_category":"Mec\u00c1nico Del Autom\u00d3vil",
    "sg:phone":"+34 971 82 14 46",
    "sg:postcode":"07680",
    "sg:province":"Islas Baleares",
    "wof:name":"Sureda Llinas Melchor S.l.n.e.",
    "wof:placetype":"venue"
},
  "geometry": {"coordinates":[3.3412349224,39.5450820923],"type":"Point"}
}