{
  "type": "Feature",
  "properties": {
    "iso:country":"ES",
    "sg:address":"Mallabia, S/n",
    "sg:city":"Mallabia",
    "sg:orig_category":"Carnes De Carnicer\u00cda (al Por Mayor)",
    "sg:phone":"+34 943 17 53 54",
    "sg:postcode":"48269",
    "sg:province":"Vizcaya",
    "wof:name":"Ayerbe Iturburu Mikel",
    "wof:placetype":"venue"
},
  "geometry": {"coordinates":[-2.5167715549,43.1843032837],"type":"Point"}
}