{
  "type": "Feature",
  "properties": {
    "addr:full":"Calle de Marques De Larios, 4 Malaga M\u00e1laga 29005",
    "addr:housenumber":"4",
    "addr:postcode":"29005",
    "addr:street":"Calle De Marques De Larios;Ma\u0301Laga",
    "iso:country":"ES",
    "sg:address":"Calle de Marques De Larios, 4",
    "sg:city":"Malaga",
    "sg:orig_category":"Aud\u00cdfonos",
    "sg:phone":"+34 952 22 54 80",
    "sg:postcode":"29005",
    "sg:province":"M\u00e1laga",
    "wof:name":"Widex Audifonos S.a.",
    "wof:placetype":"venue"
},
  "geometry": {"coordinates":[-4.421661377,36.7201766968],"type":"Point"}
}