{
  "type": "Feature",
  "properties": {
    "addr:full":"Ctra Madrid-cadiz, S/n Jerez De La Frontera C\u00e1diz 11407",
    "addr:postcode":"11407",
    "addr:street":"Ctra Madrid-Cadiz S / N",
    "iso:country":"ES",
    "sg:address":"Ctra Madrid-cadiz, S/n",
    "sg:city":"Jerez De La Frontera",
    "sg:orig_category":"Empresarios Y Productoras De Espect\u00c1culos",
    "sg:phone":"+34 956 32 63 20",
    "sg:postcode":"11407",
    "sg:province":"C\u00e1diz",
    "sg:website":"www.sendajerez.com",
    "wof:name":"Senda S.l.",
    "wof:placetype":"venue"
},
  "geometry": {"coordinates":[-6.113779068,36.7087211609],"type":"Point"}
}