{
  "type": "Feature",
  "properties": {
    "addr:full":"Carrer de Castillejos, 11 S. Cugat Valles Barcelona 08172",
    "addr:housenumber":"11",
    "addr:postcode":"08172",
    "addr:street":"Carrer De Castillejos;S. Cugat Valles Barcelona",
    "iso:country":"ES",
    "sg:address":"Carrer de Castillejos, 11",
    "sg:city":"S. Cugat Valles",
    "sg:orig_category":"Peluqueros: De Se\u00d1oras",
    "sg:phone":"+34 935 89 42 25",
    "sg:postcode":"08172",
    "sg:province":"Barcelona",
    "wof:name":"Navarro Rosel Isabel",
    "wof:placetype":"venue"
},
  "geometry": {"coordinates":[2.0813250542,41.4734649658],"type":"Point"}
}