{
  "type": "Feature",
  "properties": {
    "iso:country":"ES",
    "sg:address":"Carr Sant Cristofol, 17",
    "sg:city":"Migjorn Gran",
    "sg:orig_category":"Electromec\u00c1nica",
    "sg:phone":"+34 971 37 06 05",
    "sg:postcode":"07749",
    "sg:province":"Islas Baleares",
    "wof:name":"Janer Pons Vicente",
    "wof:placetype":"venue"
},
  "geometry": {"coordinates":[4.0503702164,39.9455299377],"type":"Point"}
}