{
  "type": "Feature",
  "properties": {
    "addr:full":"Calle de La Felicidad, 12 San Vicente De Barakaldo Vizcaya 48901",
    "addr:housenumber":"12",
    "addr:postcode":"48901",
    "addr:street":"Calle De La Felicidad",
    "iso:country":"ES",
    "sg:address":"Calle de La Felicidad, 12",
    "sg:city":"San Vicente De Barakaldo",
    "sg:orig_category":"Peluqueros: De Se\u00d1oras",
    "sg:phone":"+34 944 38 82 64",
    "sg:postcode":"48901",
    "sg:province":"Vizcaya",
    "wof:name":"Calvo Codesal Aurelia",
    "wof:placetype":"venue"
},
  "geometry": {"coordinates":[-2.9902079105,43.2989578247],"type":"Point"}
}