{
  "type": "Feature",
  "properties": {
    "iso:country":"ES",
    "sg:address":"Calle de Nieves, 16",
    "sg:city":"Bola\u00e7os De Calatrava",
    "sg:orig_category":"Venta Al Preg\u00d3n",
    "sg:phone":"+34 926 87 03 75",
    "sg:postcode":"13260",
    "sg:province":"Ciudad Real",
    "wof:name":"Diaz Fernandez Aurelia",
    "wof:placetype":"venue"
},
  "geometry": {"coordinates":[-3.6663589478,38.906791687],"type":"Point"}
}