{
  "type": "Feature",
  "properties": {
    "addr:full":"Ptda Perleta, 151 Elche Alicante 03295",
    "addr:housenumber":"151",
    "addr:postcode":"03295",
    "addr:street":"Ptda Perleta",
    "iso:country":"ES",
    "sg:address":"Ptda Perleta, 151",
    "sg:city":"Elche",
    "sg:orig_category":"Semiller\u00cdas",
    "sg:phone":"+34 965 45 69 42",
    "sg:postcode":"03295",
    "sg:province":"Alicante",
    "sg:website":"www.viverosdemoy.com",
    "wof:name":"Viveros Demoy S.l.",
    "wof:placetype":"venue"
},
  "geometry": {"coordinates":[-0.6429250836,38.3055953979],"type":"Point"}
}