{
  "type": "Feature",
  "properties": {
    "iso:country":"ES",
    "sg:address":"Calle de Francisco Garcia De Sola, 3",
    "sg:city":"Cadiz",
    "sg:orig_category":"Alimentaci\u00d3n General (al Por Menor)",
    "sg:phone":"+34 956 27 19 19",
    "sg:postcode":"11008",
    "sg:province":"C\u00e1diz",
    "wof:name":"Cobo Gomez Cesareo",
    "wof:placetype":"venue"
},
  "geometry": {"coordinates":[-6.2819061279,36.5196876526],"type":"Point"}
}