{
  "type": "Feature",
  "properties": {
    "iso:country":"ES",
    "sg:address":"Avda Ciudad De Linares (de La), S/n",
    "sg:city":"Ubeda",
    "sg:orig_category":"Fabricaci\u00d3n, Importaci\u00d3n De L\u00c1mparas Y Bombillas",
    "sg:phone":"+34 953 75 41 81",
    "sg:postcode":"23400",
    "sg:province":"Ja\u00e9n",
    "wof:name":"Castroluz Andalucia S.l.l.",
    "wof:placetype":"venue"
},
  "geometry": {"coordinates":[-3.3772549629,38.013092041],"type":"Point"}
}