{
  "type": "Feature",
  "properties": {
    "iso:country":"ES",
    "sg:address":"Carrer de Claverol, 1",
    "sg:city":"Sant Vicen\u00c7 Dels Horts",
    "sg:orig_category":"Peluquer\u00cdas, Peluquer\u00cda Mixta",
    "sg:phone":"+34 936 56 07 48",
    "sg:postcode":"08620",
    "sg:province":"Barcelona",
    "wof:name":"Rodrigo Anton Maria Dolores",
    "wof:placetype":"venue"
},
  "geometry": {"coordinates":[2.0072250366,41.3887062073],"type":"Point"}
}