{
  "type": "Feature",
  "properties": {
    "addr:full":"Magdalena, S/n Santecilla Burgos 09585",
    "addr:postcode":"09585",
    "addr:street":"Magdalena S / N Santecilla",
    "iso:country":"ES",
    "sg:address":"Magdalena, S/n",
    "sg:city":"Santecilla",
    "sg:orig_category":"Art\u00cdculos De Madera (fabricaci\u00d3n Y Al Por Mayor)",
    "sg:phone":"+34 947 14 05 55",
    "sg:postcode":"09585",
    "sg:province":"Burgos",
    "wof:name":"Novo-holl Interiores Sl",
    "wof:placetype":"venue"
},
  "geometry": {"coordinates":[-3.2485289574,43.1226615906],"type":"Point"}
}