{
  "type": "Feature",
  "properties": {
    "addr:full":"Calle de Mateos, 38 Carmen Murcia 30002",
    "addr:postcode":"30002",
    "addr:street":"Calle De Mateos 38",
    "iso:country":"ES",
    "sg:address":"Calle de Mateos, 38",
    "sg:city":"Carmen",
    "sg:orig_category":"Inform\u00c1tica: Soportes De Informaci\u00d3n, Suministros & Accesorios",
    "sg:phone":"+34 968 35 00 80",
    "sg:postcode":"30002",
    "sg:province":"Murcia",
    "wof:name":"Reciclaje Ofimatico S.l.",
    "wof:placetype":"venue"
},
  "geometry": {"coordinates":[-1.1302499771,37.9829597473],"type":"Point"}
}