{
  "type": "Feature",
  "properties": {
    "iso:country":"ES",
    "sg:address":"C/ Alfonso Xii, 19",
    "sg:city":"Elche",
    "sg:orig_category":"Caf\u00c9s, Bares, Cervecer\u00cdas",
    "sg:phone":"+34 966 61 08 38",
    "sg:postcode":"03203",
    "sg:province":"Alicante",
    "wof:name":"Telemorgar S.l.",
    "wof:placetype":"venue"
},
  "geometry": {"coordinates":[-0.6989989877,38.2644271851],"type":"Point"}
}