{
  "type": "Feature",
  "properties": {
    "addr:full":"Carrer de Sant Julia, 10 Vilafranca Penedes Barcelona 08720",
    "addr:housenumber":"10",
    "addr:postcode":"08720",
    "addr:street":"Carrer De Sant Julia;Penedes Barcelona",
    "iso:country":"ES",
    "sg:address":"Carrer de Sant Julia, 10",
    "sg:city":"Vilafranca Penedes",
    "sg:orig_category":"Cajas De Ahorro",
    "sg:phone":"+34 938 90 40 10",
    "sg:postcode":"08720",
    "sg:province":"Barcelona",
    "wof:name":"Caixa D'estalvis Del Penedes",
    "wof:placetype":"venue"
},
  "geometry": {"coordinates":[1.6957570314,41.3454818726],"type":"Point"}
}