{
  "type": "Feature",
  "properties": {
    "addr:full":"Calle de Larga, 15 Jerez De La Frontera C\u00e1diz 11402",
    "addr:housenumber":"15",
    "addr:postcode":"11402",
    "addr:street":"Calle De Larga",
    "iso:country":"ES",
    "sg:address":"Calle de Larga, 15",
    "sg:city":"Jerez De La Frontera",
    "sg:orig_category":"Bisuter\u00cda, Joyer\u00cda, Relojer\u00cda (al Por Menor)",
    "sg:phone":"+34 956 34 30 17",
    "sg:postcode":"11402",
    "sg:province":"C\u00e1diz",
    "wof:name":"Sepulveda Zapata Miguel Angel",
    "wof:placetype":"venue"
},
  "geometry": {"coordinates":[-6.1362338066,36.6852302551],"type":"Point"}
}