{
  "type": "Feature",
  "properties": {
    "iso:country":"ES",
    "sg:address":"Avgd De Magallanes, S/n",
    "sg:city":"Benicarlo",
    "sg:orig_category":"Agentes, Concesionarios Y Sucursales De Camiones Y Veh\u00cdculos Industriales",
    "sg:phone":"+34 964 47 57 11",
    "sg:postcode":"12580",
    "sg:province":"Castell\u00f3n",
    "wof:name":"Perez Ugalde Maria Antonia",
    "wof:placetype":"venue"
},
  "geometry": {"coordinates":[0.4042100012,40.4457893372],"type":"Point"}
}