{
  "type": "Feature",
  "properties": {
    "addr:full":"Calle de Constitucion, 13 Alcora Castell\u00f3n 12110",
    "addr:housenumber":"13",
    "addr:postcode":"12110",
    "addr:street":"Calle De Constitucion;Castello\u0301N",
    "iso:country":"ES",
    "sg:address":"Calle de Constitucion, 13",
    "sg:city":"Alcora",
    "sg:orig_category":"Carnicer\u00cdas, Carnicer\u00cdas",
    "sg:phone":"+34 964 38 62 37",
    "sg:postcode":"12110",
    "sg:province":"Castell\u00f3n",
    "wof:name":"Fabra Andreu Aurelio",
    "wof:placetype":"venue"
},
  "geometry": {"coordinates":[-0.2138490975,40.0756874084],"type":"Point"}
}