{
  "type": "Feature",
  "properties": {
    "addr:full":"Calle de Mayor, 44 Molina Segura Murcia 30500",
    "addr:housenumber":"44",
    "addr:postcode":"30500",
    "addr:street":"Calle De Mayor",
    "iso:country":"ES",
    "sg:address":"Calle de Mayor, 44",
    "sg:city":"Molina Segura",
    "sg:orig_category":"Importaci\u00d3n",
    "sg:phone":"+34 968 61 50 16",
    "sg:postcode":"30500",
    "sg:province":"Murcia",
    "wof:name":"Garcia Nicolas Joaquin",
    "wof:placetype":"venue"
},
  "geometry": {"coordinates":[-1.2107989788,38.0514183044],"type":"Point"}
}