{
  "type": "Feature",
  "properties": {
    "iso:country":"ES",
    "sg:address":"Golf Del Sur, S/n",
    "sg:city":"Golf Sur",
    "sg:orig_category":"Alquiler De Veh\u00cdculos: Turismos Y Utilitarios",
    "sg:phone":"+34 922 73 88 39",
    "sg:postcode":"38639",
    "sg:province":"Santa Cruz De Tenerife",
    "wof:name":"Samson  Michael Brian",
    "wof:placetype":"venue"
},
  "geometry": {"coordinates":[-16.6115474701,28.0350246429],"type":"Point"}
}