{
  "type": "Feature",
  "properties": {
    "iso:country":"ES",
    "sg:address":"Calle de Sagasta, 24",
    "sg:city":"Sevilla",
    "sg:orig_category":"Complementos De Vestir (al Por Menor)",
    "sg:phone":"+34 954 22 80 08",
    "sg:postcode":"41004",
    "sg:province":"Sevilla",
    "wof:name":"Perez Santana Francisco",
    "wof:placetype":"venue"
},
  "geometry": {"coordinates":[-5.994122982,37.3901062012],"type":"Point"}
}