{
  "type": "Feature",
  "properties": {
    "addr:full":"Calle de Madrid, 8 Ibi Alicante 03440",
    "addr:housenumber":"8",
    "addr:postcode":"03440",
    "addr:street":"Calle De Madrid",
    "iso:country":"ES",
    "sg:address":"Calle de Madrid, 8",
    "sg:city":"Ibi",
    "sg:orig_category":"Fabricaci\u00d3n De Moldes Y Modelos",
    "sg:phone":"+34 965 55 42 88",
    "sg:postcode":"03440",
    "sg:province":"Alicante",
    "wof:name":"Taller Rocio S.l.",
    "wof:placetype":"venue"
},
  "geometry": {"coordinates":[-0.5927540064,38.6106567383],"type":"Point"}
}