{
  "type": "Feature",
  "properties": {
    "addr:full":"Carr Mar, 2 Port Selva Girona 17489",
    "addr:housenumber":"2",
    "addr:postcode":"17489",
    "addr:street":"Carr Mar",
    "iso:country":"ES",
    "sg:address":"Carr Mar, 2",
    "sg:city":"Port Selva",
    "sg:orig_category":"Pintura, Barniz, Productos Asimilables (fabricaci\u00d3n, Al Por Mayor)",
    "sg:phone":"+34 972 12 64 61",
    "sg:postcode":"17489",
    "sg:province":"Girona",
    "wof:name":"Pinturas Pittsburgh Iberica S.a.",
    "wof:placetype":"venue"
},
  "geometry": {"coordinates":[3.1865150928,42.3239517212],"type":"Point"}
}