{
  "type": "Feature",
  "properties": {
    "addr:full":"Barr Pol (el), S/n Hoznayo Cantabria 39716",
    "addr:postcode":"39716",
    "addr:street":"El S / N",
    "iso:country":"ES",
    "sg:address":"Barr Pol (el), S/n",
    "sg:city":"Hoznayo",
    "sg:orig_category":"Transporte En General",
    "sg:phone":"+34 942 52 40 48",
    "sg:postcode":"39716",
    "sg:province":"Cantabria",
    "wof:name":"Clyanor S.a.",
    "wof:placetype":"venue"
},
  "geometry": {"coordinates":[-3.6326639652,43.3630180359],"type":"Point"}
}