{
  "type": "Feature",
  "properties": {
    "addr:full":"Av La Paz, 15 Onil Alicante 03430",
    "addr:housenumber":"15",
    "addr:postcode":"03430",
    "addr:street":"Av La Paz",
    "iso:country":"ES",
    "sg:address":"Av La Paz, 15",
    "sg:city":"Onil",
    "sg:orig_category":"\u00d3ptica: Instrumentos (fabricaci\u00d3n)",
    "sg:phone":"+34 965 56 45 85",
    "sg:postcode":"03430",
    "sg:province":"Alicante",
    "wof:name":"Paybe S.l.u.",
    "wof:placetype":"venue"
},
  "geometry": {"coordinates":[-0.6772789955,38.6275863647],"type":"Point"}
}