{
  "type": "Feature",
  "properties": {
    "iso:country":"ES",
    "sg:address":"Cra Santa Coloma, 15",
    "sg:city":"Pladevall",
    "sg:orig_category":"Forjas Y Altos Hornos",
    "sg:phone":"+34 972 69 30 81",
    "sg:postcode":"17178",
    "sg:province":"Girona",
    "wof:name":"Tallers Brosa S.",
    "wof:placetype":"venue"
},
  "geometry": {"coordinates":[2.4583799839,42.1440010071],"type":"Point"}
}