{
  "type": "Feature",
  "properties": {
    "iso:country":"ES",
    "sg:address":"Avda Alcalde Alfonso De Rojas, 4",
    "sg:city":"Alacant",
    "sg:orig_category":"Art\u00cdculos De Regalo (al Por Menor)",
    "sg:phone":"+34 965 25 12 12",
    "sg:postcode":"03004",
    "sg:province":"Alicante",
    "wof:name":"Boreas-art S.l.l",
    "wof:placetype":"venue"
},
  "geometry": {"coordinates":[-0.4862599969,38.3524436951],"type":"Point"}
}