{
  "type": "Feature",
  "properties": {
    "addr:full":"Plaz Santo Domingo, 4 Le\u00f3n Le\u00f3n 24001",
    "addr:housenumber":"4",
    "addr:postcode":"24001",
    "addr:street":"Santo Domingo;Leo\u0301N",
    "iso:country":"ES",
    "sg:address":"Plaz Santo Domingo, 4",
    "sg:city":"Le\u00f3n",
    "sg:orig_category":"Asociaciones Humanitarias, De Cooperaci\u00d3n, De Acci\u00d3n Social",
    "sg:phone":"+34 987 27 20 05",
    "sg:postcode":"24001",
    "sg:province":"Le\u00f3n",
    "sg:website":"www.asc.es",
    "wof:name":"Asociacion Espa\u00d1ola Contra El Cancer",
    "wof:placetype":"venue"
},
  "geometry": {"coordinates":[-5.5761685371,42.5978317261],"type":"Point"}
}