{
  "type": "Feature",
  "properties": {
    "addr:full":"Carrer de Sant Magi, 68 Palma Islas Baleares 07013",
    "addr:housenumber":"68",
    "addr:postcode":"07013",
    "addr:street":"Carrer De Sant Magi",
    "iso:country":"ES",
    "sg:address":"Carrer de Sant Magi, 68",
    "sg:city":"Palma",
    "sg:orig_category":"Caf\u00c9s, Bares, Cervecer\u00cdas",
    "sg:phone":"+34 971 22 07 41",
    "sg:postcode":"07013",
    "sg:province":"Islas Baleares",
    "wof:name":"Ona Vegetariana C.b",
    "wof:placetype":"venue"
},
  "geometry": {"coordinates":[2.6363620758,39.5706748962],"type":"Point"}
}