{
  "type": "Feature",
  "properties": {
    "iso:country":"ES",
    "sg:address":"Afores, S/n",
    "sg:city":"Montagut",
    "sg:orig_category":"Zonas De Acampada, Aparcamiento Para Caravanas",
    "sg:phone":"+34 972 28 72 02",
    "sg:postcode":"17855",
    "sg:province":"Girona",
    "wof:name":"El Pont Del Llierca S.l.",
    "wof:placetype":"venue"
},
  "geometry": {"coordinates":[2.5958900452,42.2317695618],"type":"Point"}
}