{
  "type": "Feature",
  "properties": {
    "addr:full":"Olite-erriberri Kalea, 37 Iru\u00f1a Navarra 31004",
    "addr:housenumber":"37",
    "addr:postcode":"31004",
    "addr:street":"Olite-Erriberri Kalea",
    "iso:country":"ES",
    "sg:address":"Olite-erriberri Kalea, 37",
    "sg:city":"Iru\u00f1a",
    "sg:orig_category":"Grabados",
    "sg:phone":"+34 948 23 39 81",
    "sg:postcode":"31004",
    "sg:province":"Navarra",
    "sg:website":"www.gravograph-spain.com",
    "wof:name":"Martinez Estevez S. L.",
    "wof:placetype":"venue"
},
  "geometry": {"coordinates":[-1.6334710121,42.8107452393],"type":"Point"}
}