{
  "type": "Feature",
  "properties": {
    "addr:full":"Urb Costa Sancti Petri, 31 Barrosa C\u00e1diz 11130",
    "addr:housenumber":"31",
    "addr:postcode":"11130",
    "addr:street":"Urb Costa Sancti Petri;Ca\u0301Diz",
    "iso:country":"ES",
    "sg:address":"Urb Costa Sancti Petri, 31",
    "sg:city":"Barrosa",
    "sg:orig_category":"Abogados",
    "sg:phone":"+34 956 49 73 99",
    "sg:postcode":"11130",
    "sg:province":"C\u00e1diz",
    "wof:name":"Basallote De Alba Juan",
    "wof:placetype":"venue"
},
  "geometry": {"coordinates":[-6.1447038651,36.4212188721],"type":"Point"}
}