{
  "type": "Feature",
  "properties": {
    "addr:full":"Avda Segovia, 6 Valladolid Valladolid 47013",
    "addr:housenumber":"6",
    "addr:postcode":"47013",
    "addr:street":"Avda Segovia",
    "iso:country":"ES",
    "sg:address":"Avda Segovia, 6",
    "sg:city":"Valladolid",
    "sg:orig_category":"Ropa Para Se\u00d1oras (al Por Menor)",
    "sg:phone":"+34 983 47 75 69",
    "sg:postcode":"47013",
    "sg:province":"Valladolid",
    "wof:name":"Ruiz Rivero Maria Luisa",
    "wof:placetype":"venue"
},
  "geometry": {"coordinates":[-4.7205982208,41.6402168274],"type":"Point"}
}