{
  "type": "Feature",
  "properties": {
    "iso:country":"ES",
    "sg:address":"Afores, S/n",
    "sg:city":"Senet",
    "sg:orig_category":"Edici\u00d3n De Diarios, Revistas, Boletines",
    "sg:phone":"+34 973 69 81 93",
    "sg:postcode":"25553",
    "sg:province":"Lleida",
    "wof:name":"Associacio La Forja S.c.v.",
    "wof:placetype":"venue"
},
  "geometry": {"coordinates":[0.7522221804,42.5577774048],"type":"Point"}
}