{
  "type": "Feature",
  "properties": {
    "iso:country":"ES",
    "sg:address":"Carr Lopez I Puigcerver, 33",
    "sg:city":"Palamos",
    "sg:orig_category":"Alquiler De Apartamentos",
    "sg:phone":"+34 972 31 61 83",
    "sg:postcode":"17230",
    "sg:province":"Girona",
    "wof:name":"Mil Nou-cents Quinze S.l.",
    "wof:placetype":"venue"
},
  "geometry": {"coordinates":[3.1240000725,41.8488464355],"type":"Point"}
}