{
  "type": "Feature",
  "properties": {
    "iso:country":"ES",
    "sg:address":"Calle de Feria (de La), S/n",
    "sg:city":"Alcazares",
    "sg:orig_category":"Asesor\u00cda Sobre Comunicaci\u00d3n De Empresas",
    "sg:phone":"+34 968 57 50 31",
    "sg:postcode":"30710",
    "sg:province":"Murcia",
    "wof:name":"Garre Martinez Jose",
    "wof:placetype":"venue"
},
  "geometry": {"coordinates":[-0.8496490121,37.7407646179],"type":"Point"}
}