{
  "type": "Feature",
  "properties": {
    "iso:country":"ES",
    "sg:address":"Calle de Gonzalez Vicen, 12",
    "sg:city":"Santa Pola",
    "sg:orig_category":"Arquitectos",
    "sg:phone":"+34 965 41 68 80",
    "sg:postcode":"03130",
    "sg:province":"Alicante",
    "wof:name":"Urban Brotons Pascual",
    "wof:placetype":"venue"
},
  "geometry": {"coordinates":[-0.5519989729,38.1900215149],"type":"Point"}
}