{
  "type": "Feature",
  "properties": {
    "iso:country":"ES",
    "sg:address":"Calle de Relatores, 9",
    "sg:city":"Madrid",
    "sg:orig_category":"Ropa Y Accesorios",
    "sg:phone":"+34 913 69 33 75",
    "sg:postcode":"28012",
    "sg:province":"Madrid",
    "wof:name":"Confecciones New Caro Espa\u00d1ola S.l.",
    "wof:placetype":"venue"
},
  "geometry": {"coordinates":[-3.7029891014,40.4131813049],"type":"Point"}
}