{
  "type": "Feature",
  "properties": {
    "addr:full":"Avda Alfonso Xiii, S/n Boveda Lugo 27340",
    "addr:housenumber":"s / n",
    "addr:postcode":"27340",
    "addr:street":"Avda Alfonso Xiii",
    "iso:country":"ES",
    "sg:address":"Avda Alfonso Xiii, S/n",
    "sg:city":"Boveda",
    "sg:orig_category":"Fabricaci\u00d3n De Productos L\u00c1cteos Y Derivados",
    "sg:phone":"+34 982 42 60 13",
    "sg:postcode":"27340",
    "sg:province":"Lugo",
    "wof:name":"Lacteos Xabelo S. L.",
    "wof:placetype":"venue"
},
  "geometry": {"coordinates":[-7.4826569557,42.6255302429],"type":"Point"}
}