{
  "type": "Feature",
  "properties": {
    "iso:country":"ES",
    "sg:address":"Calle de Oca\u00d1a, 147",
    "sg:city":"Madrid",
    "sg:orig_category":"Edici\u00d3n De Diarios, Revistas, Boletines",
    "sg:phone":"+34 917 17 42 54",
    "sg:postcode":"28047",
    "sg:province":"Madrid",
    "wof:name":"Ediciones Distribuciones Fraile S. A.",
    "wof:placetype":"venue"
},
  "geometry": {"coordinates":[-3.7535281181,40.3860168457],"type":"Point"}
}