{
  "type": "Feature",
  "properties": {
    "iso:country":"ES",
    "sg:address":"Calle de Ordo\u00d1ez, 30",
    "sg:city":"Sagunt",
    "sg:orig_category":"Cl\u00cdnicas Dentales",
    "sg:phone":"+34 962 66 13 39",
    "sg:postcode":"46500",
    "sg:province":"Valencia",
    "wof:name":"Perez Peiro Manuel Luis",
    "wof:placetype":"venue"
},
  "geometry": {"coordinates":[-0.2747150064,39.6808052063],"type":"Point"}
}