{
  "type": "Feature",
  "properties": {
    "addr:full":"Trav Barranquet (el), 10 Barranquet Alicante 03690",
    "addr:housenumber":"10",
    "addr:postcode":"03690",
    "addr:street":"Trav Barranquet El;Alicante",
    "iso:country":"ES",
    "sg:address":"Trav Barranquet (el), 10",
    "sg:city":"Barranquet",
    "sg:orig_category":"Venta, Localizaci\u00d3n, Reparaci\u00d3n De Material E Instrumental M\u00c9dico",
    "sg:phone":"+34 965 66 51 88",
    "sg:postcode":"03690",
    "sg:province":"Alicante",
    "wof:name":"Lab Invest S.l.",
    "wof:placetype":"venue"
},
  "geometry": {"coordinates":[-0.5060960054,38.4158325195],"type":"Point"}
}