{
  "type": "Feature",
  "properties": {
    "addr:full":"Pda. Tosses, S/n Amposta Tarragona 43870",
    "addr:housenumber":"s / n",
    "addr:postcode":"43870",
    "iso:country":"ES",
    "sg:address":"Pda. Tosses, S/n",
    "sg:city":"Amposta",
    "sg:orig_category":"Electricidad: Instaladores",
    "sg:phone":"+34 977 70 33 19",
    "sg:postcode":"43870",
    "sg:province":"Tarragona",
    "wof:name":"Xarxes I Manteniments S.l.",
    "wof:placetype":"venue"
},
  "geometry": {"coordinates":[0.6298921704,40.683719635],"type":"Point"}
}