{
  "type": "Feature",
  "properties": {
    "iso:country":"ES",
    "sg:address":"Calle de Corredera, 44",
    "sg:city":"Almansa",
    "sg:classifiers":[
        {
            "category":"Autos & Motor Vehicles",
            "subcategory":"Automobile Sales",
            "type":"Retail Goods"
        }
    ],
    "sg:phone":"+34 967 34 00 75",
    "sg:postcode":"02640",
    "sg:province":"Albacete",
    "wof:name":"Autoescuela Tercero S.l.",
    "wof:placetype":"venue"
},
  "geometry": {"coordinates":[-1.0960445404,38.8675193787],"type":"Point"}
}