{
  "type": "Feature",
  "properties": {
    "iso:country":"ES",
    "sg:address":"C/ Clos, 7",
    "sg:city":"Cerdanyola Valles",
    "sg:orig_category":"Delineantes",
    "sg:phone":"+34 936 91 74 04",
    "sg:postcode":"08290",
    "sg:province":"Barcelona",
    "wof:name":"Inydel S.c.c.l.",
    "wof:placetype":"venue"
},
  "geometry": {"coordinates":[2.1477351189,41.4944839478],"type":"Point"}
}