{
  "type": "Feature",
  "properties": {
    "iso:country":"ES",
    "sg:address":"Carrer de Hospitalet, 17",
    "sg:city":"Sant Feliu Llobregat",
    "sg:orig_category":"Florister\u00cdas",
    "sg:phone":"+34 936 32 67 44",
    "sg:postcode":"08980",
    "sg:province":"Barcelona",
    "wof:name":"Armengol Andreu Nuria",
    "wof:placetype":"venue"
},
  "geometry": {"coordinates":[2.0424458981,41.3874206543],"type":"Point"}
}