{
  "type": "Feature",
  "properties": {
    "addr:full":"Carrer de Monterols, 25 Reus Tarragona 43201",
    "addr:housenumber":"25",
    "addr:postcode":"43201",
    "addr:street":"Carrer De Monterols",
    "iso:country":"ES",
    "sg:address":"Carrer de Monterols, 25",
    "sg:city":"Reus",
    "sg:orig_category":"Mercer\u00cda, Lencer\u00cda (al Por Menor)",
    "sg:phone":"+34 977 34 38 97",
    "sg:postcode":"43201",
    "sg:province":"Tarragona",
    "wof:name":"Sarda Margarit Pedro",
    "wof:placetype":"venue"
},
  "geometry": {"coordinates":[1.107839942,41.1557807922],"type":"Point"}
}