{
  "type": "Feature",
  "properties": {
    "addr:full":"Guipuzcoa, 38 Iru\u00f1a Navarra 31014",
    "addr:housenumber":"38",
    "addr:postcode":"31014",
    "addr:street":"Guipuzcoa",
    "iso:country":"ES",
    "sg:address":"Guipuzcoa, 38",
    "sg:city":"Iru\u00f1a",
    "sg:orig_category":"Asilos De Ancianos. Centros Privados",
    "sg:phone":"+34 948 14 43 00",
    "sg:postcode":"31014",
    "sg:province":"Navarra",
    "wof:name":"Hermanitas De Los Pobres",
    "wof:placetype":"venue"
},
  "geometry": {"coordinates":[-1.6630330086,42.8291053772],"type":"Point"}
}