{
  "type": "Feature",
  "properties": {
    "addr:full":"Calle de Fuente, 7 Moratalla Murcia 30440",
    "addr:housenumber":"7",
    "addr:postcode":"30440",
    "addr:street":"Calle De Fuente",
    "iso:country":"ES",
    "sg:address":"Calle de Fuente, 7",
    "sg:city":"Moratalla",
    "sg:orig_category":"Agencias Y Agentes Comerciales, Representantes",
    "sg:phone":"+34 968 73 04 10",
    "sg:postcode":"30440",
    "sg:province":"Murcia",
    "wof:name":"Martinez Garcia Alonso",
    "wof:placetype":"venue"
},
  "geometry": {"coordinates":[-1.894323945,38.1906318665],"type":"Point"}
}