{
  "type": "Feature",
  "properties": {
    "iso:country":"ES",
    "sg:address":"Calle de San Roque, 21",
    "sg:city":"Novelda",
    "sg:orig_category":"Ropa Para Caballeros (al Por Menor)",
    "sg:phone":"+34 965 60 41 58",
    "sg:postcode":"03660",
    "sg:province":"Alicante",
    "wof:name":"Serrano Lopez Luis Miguel",
    "wof:placetype":"venue"
},
  "geometry": {"coordinates":[-0.7693359852,38.3841094971],"type":"Point"}
}