{
  "type": "Feature",
  "properties": {
    "iso:country":"ES",
    "sg:address":"Carrer de Terra Alta, 55",
    "sg:city":"Poligono Industrial Can Carner",
    "sg:orig_category":"Impresiones Sobre Tela",
    "sg:phone":"+34 937 14 86 37",
    "sg:postcode":"08211",
    "sg:province":"Barcelona",
    "wof:name":"Estampats Montsan S.l.",
    "wof:placetype":"venue"
},
  "geometry": {"coordinates":[2.0857300758,41.6151885986],"type":"Point"}
}