{
  "type": "Feature",
  "properties": {
    "iso:country":"ES",
    "sg:address":"M. Ing. S. Lloveras, S/n",
    "sg:city":"Castello Plana",
    "sg:orig_category":"Centros Comerciales Y Grandes Tiendas",
    "sg:phone":"+34 964 73 71 10",
    "sg:postcode":"12100",
    "sg:province":"Castell\u00f3n",
    "wof:name":"Porto Grande Trading S.l",
    "wof:placetype":"venue"
},
  "geometry": {"coordinates":[0.0176999997,39.9888801575],"type":"Point"}
}