{
  "type": "Feature",
  "properties": {
    "iso:country":"ES",
    "sg:address":"Rua Evaristo Vaamonde (de), 3",
    "sg:city":"Carballi\u00f1o",
    "sg:orig_category":"Iglesia Cat\u00d3lica",
    "sg:phone":"+34 988 27 09 43",
    "sg:postcode":"32500",
    "sg:province":"Ourense",
    "wof:name":"Obispado De Orense",
    "wof:placetype":"venue"
},
  "geometry": {"coordinates":[-8.0733537674,42.4324684143],"type":"Point"}
}