{
  "type": "Feature",
  "properties": {
    "iso:country":"ES",
    "sg:address":"Calle de Corregidor Pedro Zapata, 16",
    "sg:city":"Malaga",
    "sg:orig_category":"Iglesia Cat\u00d3lica",
    "sg:phone":"+34 952 33 48 48",
    "sg:postcode":"29006",
    "sg:province":"M\u00e1laga",
    "wof:name":"Obispado De Malaga",
    "wof:placetype":"venue"
},
  "geometry": {"coordinates":[-4.4536356926,36.7105712891],"type":"Point"}
}