{
  "type": "Feature",
  "properties": {
    "addr:full":"Carrer de Comte Jofre, 23 Sabadell Barcelona 08205",
    "addr:housenumber":"23",
    "addr:postcode":"08205",
    "addr:street":"Carrer De Comte Jofre",
    "iso:country":"ES",
    "sg:address":"Carrer de Comte Jofre, 23",
    "sg:city":"Sabadell",
    "sg:orig_category":"Abogados",
    "sg:phone":"+34 937 27 07 99",
    "sg:postcode":"08205",
    "sg:province":"Barcelona",
    "wof:name":"Enrich Franco Jaume",
    "wof:placetype":"venue"
},
  "geometry": {"coordinates":[2.1012830734,41.5431442261],"type":"Point"}
}