{
  "type": "Feature",
  "properties": {
    "iso:country":"ES",
    "sg:address":"Carrer de Craywinckel, 15",
    "sg:city":"Barcelona",
    "sg:orig_category":"Frutas, Legumbres Frescas Y Tempranas (al Por Menor)",
    "sg:phone":"+34 934 17 75 91",
    "sg:postcode":"08022",
    "sg:province":"Barcelona",
    "wof:name":"Nugafruits Serveis De Distribucio S.a.",
    "wof:placetype":"venue"
},
  "geometry": {"coordinates":[2.1392168999,41.4117088318],"type":"Point"}
}