{
  "type": "Feature",
  "properties": {
    "iso:country":"ES",
    "sg:address":"Calle de Juan I De Portugal, 17",
    "sg:city":"Ceuta",
    "sg:orig_category":"Mec\u00c1nico Del Autom\u00d3vil",
    "sg:phone":"+34 956 51 19 62",
    "sg:postcode":"51001",
    "sg:province":"Ceuta",
    "wof:name":"Aparicio Perez Francisco Javier",
    "wof:placetype":"venue"
},
  "geometry": {"coordinates":[-5.3010482788,35.8918838501],"type":"Point"}
}