{
  "type": "Feature",
  "properties": {
    "iso:country":"ES",
    "sg:address":"Plaz Santiago, 1",
    "sg:city":"Orihuela",
    "sg:orig_category":"Promotores Constructores",
    "sg:phone":"+34 965 30 71 09",
    "sg:postcode":"03300",
    "sg:province":"Alicante",
    "wof:name":"Contemur",
    "wof:placetype":"venue"
},
  "geometry": {"coordinates":[-0.9503359795,38.0875091553],"type":"Point"}
}