{
  "type": "Feature",
  "properties": {
    "iso:country":"ES",
    "sg:address":"Calle de Aranibar, 5",
    "sg:city":"Irun",
    "sg:orig_category":"Vinos Y Licores (venta Al Por Menor)",
    "sg:phone":"+34 943 63 43 20",
    "sg:postcode":"20305",
    "sg:province":"Guip\u00f9zcoa",
    "wof:name":"Exclusivas Merlot S.l.",
    "wof:placetype":"venue"
},
  "geometry": {"coordinates":[-1.8226183653,43.3283157349],"type":"Point"}
}