{
  "type": "Feature",
  "properties": {
    "iso:country":"ES",
    "sg:address":"Calle de Compositor David Templado, S/n",
    "sg:city":"Abaran",
    "sg:orig_category":"Cooperativas Agr\u00cdcolas",
    "sg:phone":"+34 968 45 14 07",
    "sg:postcode":"30550",
    "sg:province":"Murcia",
    "wof:name":"Asociacion De Agricultores El Progreso",
    "wof:placetype":"venue"
},
  "geometry": {"coordinates":[-1.4002126455,38.20545578],"type":"Point"}
}