{
  "type": "Feature",
  "properties": {
    "iso:country":"ES",
    "sg:address":"Lantemil, S/n",
    "sg:city":"Illa",
    "sg:classifiers":[
        {
            "category":"Taxi",
            "type":"Transportation"
        }
    ],
    "sg:phone":"+34 988 43 38 30",
    "sg:postcode":"32869",
    "sg:province":"Ourense",
    "wof:name":"Rodriguez Gonzalez Manuel",
    "wof:placetype":"venue"
},
  "geometry": {"coordinates":[-8.2071142197,41.9112663269],"type":"Point"}
}