{
  "type": "Feature",
  "properties": {
    "iso:country":"ES",
    "sg:address":"Calle de Humilladero, 27",
    "sg:city":"Sig\u00fcenza",
    "sg:orig_category":"Carnicer\u00cdas, Carnicer\u00cdas",
    "sg:phone":"+34 949 39 01 39",
    "sg:postcode":"19250",
    "sg:province":"Guadalajara",
    "wof:name":"Riosalido Andres Juan",
    "wof:placetype":"venue"
},
  "geometry": {"coordinates":[-2.64407897,41.0689697266],"type":"Point"}
}