{
  "type": "Feature",
  "properties": {
    "addr:full":"C/ Hospital, 8 Elche Alicante 03203",
    "addr:housenumber":"8",
    "addr:postcode":"03203",
    "addr:street":"C / Hospital",
    "iso:country":"ES",
    "sg:address":"C/ Hospital, 8",
    "sg:city":"Elche",
    "sg:orig_category":"Agencias De Viajes",
    "sg:phone":"+34 965 42 76 88",
    "sg:postcode":"03203",
    "sg:province":"Alicante",
    "wof:name":"Viatges Calendura S.l.",
    "wof:placetype":"venue"
},
  "geometry": {"coordinates":[-0.6969720125,38.265411377],"type":"Point"}
}