{
  "type": "Feature",
  "properties": {
    "iso:country":"ES",
    "sg:address":"Calle de Gran Via, 25",
    "sg:city":"Elche Sierra",
    "sg:orig_category":"Cl\u00cdnicas Dentales",
    "sg:phone":"+34 967 41 10 31",
    "sg:postcode":"02430",
    "sg:province":"Albacete",
    "wof:name":"Clinica Dental Elche Sierra S.l.",
    "wof:placetype":"venue"
},
  "geometry": {"coordinates":[-2.0469911098,38.4502372742],"type":"Point"}
}