{
  "type": "Feature",
  "properties": {
    "addr:full":"Calle de Pe\u00d1as De Aya, 7 Irun Guip\u00f9zcoa 20301",
    "addr:housenumber":"7",
    "addr:postcode":"20301",
    "addr:street":"Calle De Pen\u0303As De Aya;Guipu\u0300Zcoa",
    "iso:country":"ES",
    "sg:address":"Calle de Pe\u00d1as De Aya, 7",
    "sg:city":"Irun",
    "sg:orig_category":"Peluquer\u00cdas, Peluquer\u00cda Mixta",
    "sg:phone":"+34 943 61 93 07",
    "sg:postcode":"20301",
    "sg:province":"Guip\u00f9zcoa",
    "wof:name":"Gil Del Sol Angela",
    "wof:placetype":"venue"
},
  "geometry": {"coordinates":[-1.8078739643,43.3421936035],"type":"Point"}
}