{
  "type": "Feature",
  "properties": {
    "iso:country":"ES",
    "sg:address":"Calle de Maquirriain, 14",
    "sg:city":"Tafalla",
    "sg:orig_category":"Empresas De Carpinter\u00cda De Madera",
    "sg:phone":"+34 948 70 22 64",
    "sg:postcode":"31300",
    "sg:province":"Navarra",
    "wof:name":"Caballero Zeligueta Oscar",
    "wof:placetype":"venue"
},
  "geometry": {"coordinates":[-1.6705089808,42.5304756165],"type":"Point"}
}