{
  "type": "Feature",
  "properties": {
    "addr:full":"Calle de Moncasi, 8 Zaragoza Zaragoza 50006",
    "addr:housenumber":"8",
    "addr:postcode":"50006",
    "addr:street":"Calle De Moncasi",
    "iso:country":"ES",
    "sg:address":"Calle de Moncasi, 8",
    "sg:city":"Zaragoza",
    "sg:orig_category":"Ingenier\u00cda, Centros De Estudios (diversos)",
    "sg:phone":"+34 976 37 06 30",
    "sg:postcode":"50006",
    "sg:province":"Zaragoza",
    "wof:name":"Consultora Aragonesa De Ingenieria S.a.",
    "wof:placetype":"venue"
},
  "geometry": {"coordinates":[-0.8869699836,41.6415061951],"type":"Point"}
}