{
  "type": "Feature",
  "properties": {
    "addr:full":"Calle de Roldana (la), S/n Luque C\u00f3rdoba 14880",
    "addr:postcode":"14880",
    "addr:street":"Calle De Roldana La S / N;Co\u0301Rdoba",
    "iso:country":"ES",
    "sg:address":"Calle de Roldana (la), S/n",
    "sg:city":"Luque",
    "sg:orig_category":"Negocio De Materiales De Construcci\u00d3n",
    "sg:phone":"+34 957 67 40 06",
    "sg:postcode":"14880",
    "sg:province":"C\u00f3rdoba",
    "wof:name":"Telesforo Servicios S.l.",
    "wof:placetype":"venue"
},
  "geometry": {"coordinates":[-4.2779221535,37.5622406006],"type":"Point"}
}