{
  "type": "Feature",
  "properties": {
    "iso:country":"ES",
    "sg:address":"Calle de Marques De La Valdavia (del), 54",
    "sg:city":"Alcobendas",
    "sg:orig_category":"Negocio De Materiales De Construcci\u00d3n",
    "sg:phone":"+34 916 54 13 70",
    "sg:postcode":"28100",
    "sg:province":"Madrid",
    "sg:website":"www.chimeneasinmacon.com",
    "wof:name":"Inmacon S.l.",
    "wof:placetype":"venue"
},
  "geometry": {"coordinates":[-3.6391830444,40.5430641174],"type":"Point"}
}