{
  "type": "Feature",
  "properties": {
    "iso:country":"ES",
    "sg:address":"Calle de Roque Morera, 2",
    "sg:city":"Palmas De Gran Canaria",
    "sg:orig_category":"Laboratorios Farmac\u00c9uticos",
    "sg:phone":"+34 928 33 13 81",
    "sg:postcode":"35001",
    "sg:province":"Las Palmas",
    "wof:name":"Janssen-cilag S.a.",
    "wof:placetype":"venue"
},
  "geometry": {"coordinates":[-15.4122695923,28.1012306213],"type":"Point"}
}