{
  "type": "Feature",
  "properties": {
    "addr:full":"Calle de Guadalquivir, 18 Fuenlabrada Madrid 28947",
    "addr:housenumber":"18",
    "addr:postcode":"28947",
    "addr:street":"Calle De Guadalquivir",
    "iso:country":"ES",
    "sg:address":"Calle de Guadalquivir, 18",
    "sg:city":"Fuenlabrada",
    "sg:orig_category":"Trabajos De Perforaciones, Sondeos, Construcci\u00d3n De Pozos",
    "sg:phone":"+34 916 42 25 96",
    "sg:postcode":"28947",
    "sg:province":"Madrid",
    "wof:name":"Talleres Royse S.l.",
    "wof:placetype":"venue"
},
  "geometry": {"coordinates":[-3.754774332,40.2639770508],"type":"Point"}
}