{
  "type": "Feature",
  "properties": {
    "iso:country":"ES",
    "sg:address":"Pl Pau Casals, 5",
    "sg:city":"Prat Llobregat",
    "sg:orig_category":"Molduras, Junquillos, Listones Y Molduras Perforadas",
    "sg:phone":"+34 933 79 15 11",
    "sg:postcode":"08820",
    "sg:province":"Barcelona",
    "wof:name":"Cabrera Garcia Sebastian",
    "wof:placetype":"venue"
},
  "geometry": {"coordinates":[2.0941329002,41.3258857727],"type":"Point"}
}