{
  "type": "Feature",
  "properties": {
    "addr:full":"Calle de Francisco Cantera, 9 Miranda Ebro Burgos 09200",
    "addr:housenumber":"9",
    "addr:postcode":"09200",
    "addr:street":"Calle De Francisco Cantera",
    "iso:country":"ES",
    "sg:address":"Calle de Francisco Cantera, 9",
    "sg:city":"Miranda Ebro",
    "sg:orig_category":"Ropa Para Ni\u00d1os (al Por Menor)",
    "sg:phone":"+34 947 31 07 97",
    "sg:postcode":"09200",
    "sg:province":"Burgos",
    "wof:name":"Zabala Olano Irene",
    "wof:placetype":"venue"
},
  "geometry": {"coordinates":[-2.9453821182,42.6859779358],"type":"Point"}
}