{
  "type": "Feature",
  "properties": {
    "iso:country":"ES",
    "sg:address":"Calle de Goya, 3",
    "sg:city":"Estepona",
    "sg:orig_category":"Bisuteros (fabricaci\u00d3n, Al Por Mayor)",
    "sg:phone":"+34 952 80 49 54",
    "sg:postcode":"29680",
    "sg:province":"M\u00e1laga",
    "wof:name":"Soto Chacon Miguel",
    "wof:placetype":"venue"
},
  "geometry": {"coordinates":[-5.1450390816,36.4289245605],"type":"Point"}
}