{
  "type": "Feature",
  "properties": {
    "addr:full":"Rua Nueva De Abajo, 32 Pontevedra Pontevedra 36002",
    "addr:housenumber":"32",
    "addr:postcode":"36002",
    "addr:street":"Rua Nueva De Abajo",
    "iso:country":"ES",
    "sg:address":"Rua Nueva De Abajo, 32",
    "sg:city":"Pontevedra",
    "sg:orig_category":"Promotores Constructores",
    "sg:phone":"+34 986 84 16 25",
    "sg:postcode":"36002",
    "sg:province":"Pontevedra",
    "wof:name":"Comunidad De Propietarios Nova Dabaixo 32",
    "wof:placetype":"venue"
},
  "geometry": {"coordinates":[-8.6511077881,42.4311676025],"type":"Point"}
}