{
  "type": "Feature",
  "properties": {
    "addr:full":"Plaz Valle Del Nalon (del), 6 Partija-santa Monica Madrid 28529",
    "addr:postcode":"28529",
    "iso:country":"ES",
    "sg:address":"Plaz Valle Del Nalon (del), 6",
    "sg:city":"Partija-santa Monica",
    "sg:orig_category":"Comercio, Reparaci\u00d3n De Bicicletas, De Motocicletas, De Accesorios",
    "sg:phone":"+34 916 66 77 00",
    "sg:postcode":"28529",
    "sg:province":"Madrid",
    "wof:name":"Parrado Sanchez Carlos",
    "wof:placetype":"venue"
},
  "geometry": {"coordinates":[-3.5102670193,40.314289093],"type":"Point"}
}