{
  "type": "Feature",
  "properties": {
    "addr:full":"Calle de Mercedes, 9 Valladolid Valladolid 47006",
    "addr:housenumber":"9",
    "addr:postcode":"47006",
    "addr:street":"Calle De Mercedes",
    "iso:country":"ES",
    "sg:address":"Calle de Mercedes, 9",
    "sg:city":"Valladolid",
    "sg:orig_category":"Peluqueros: De Se\u00d1oras",
    "sg:phone":"+34 983 27 82 42",
    "sg:postcode":"47006",
    "sg:province":"Valladolid",
    "wof:name":"Alonso Casta\u00f1eda Eutiquiano",
    "wof:placetype":"venue"
},
  "geometry": {"coordinates":[-4.7396841049,41.639919281],"type":"Point"}
}