{
  "type": "Feature",
  "properties": {
    "iso:country":"ES",
    "sg:address":"Avgd Verge Del Puig, 12",
    "sg:city":"Puig",
    "sg:orig_category":"Bisuter\u00cda, Joyer\u00cda, Relojer\u00cda (al Por Menor)",
    "sg:phone":"+34 961 47 23 44",
    "sg:postcode":"46540",
    "sg:province":"Valencia",
    "wof:name":"Romero Hernandez Vicente",
    "wof:placetype":"venue"
},
  "geometry": {"coordinates":[-0.3003259897,39.5874519348],"type":"Point"}
}