{
  "type": "Feature",
  "properties": {
    "iso:country":"ES",
    "sg:address":"Calle de Ferrocarril, 39",
    "sg:city":"S. Fernando",
    "sg:orig_category":"Fabricaci\u00d3n, Comercio De Muebles En Ca\u00d1a, Mimbre",
    "sg:phone":"+34 956 88 16 08",
    "sg:postcode":"11100",
    "sg:province":"C\u00e1diz",
    "wof:name":"La Casa De Ronda S.l.",
    "wof:placetype":"venue"
},
  "geometry": {"coordinates":[-6.2051558495,36.470905304],"type":"Point"}
}