{
  "type": "Feature",
  "properties": {
    "iso:country":"ES",
    "sg:address":"Pl. Obpo Irurita, 6",
    "sg:city":"Iru\u00f1a",
    "sg:orig_category":"Ense\u00d1anza: Idiomas",
    "sg:phone":"+34 948 26 65 60",
    "sg:postcode":"31011",
    "sg:province":"Navarra",
    "wof:name":"Azpilicueta Dome\u00f1o Maria Sagrario",
    "wof:placetype":"venue"
},
  "geometry": {"coordinates":[-1.6578519344,42.8164863586],"type":"Point"}
}