{
  "type": "Feature",
  "properties": {
    "iso:country":"ES",
    "sg:address":"Plazuela Doctor Jarrin, 1",
    "sg:city":"Ibahernando",
    "sg:orig_category":"Loter\u00cda Y T\u00d3mbola",
    "sg:phone":"+34 927 33 00 07",
    "sg:postcode":"10280",
    "sg:province":"C\u00e1ceres",
    "wof:name":"Redondo Moreno Juan",
    "wof:placetype":"venue"
},
  "geometry": {"coordinates":[-5.9188280106,39.325504303],"type":"Point"}
}