{
  "type": "Feature",
  "properties": {
    "iso:country":"ES",
    "sg:address":"Calvo Sotelo, 2",
    "sg:city":"Carnota",
    "sg:orig_category":"Fisioterapia",
    "sg:phone":"+34 981 85 74 65",
    "sg:postcode":"15293",
    "sg:province":"La Coru\u00f1a",
    "wof:name":"Lado Hermida Ines",
    "wof:placetype":"venue"
},
  "geometry": {"coordinates":[-9.0886993408,42.822769165],"type":"Point"}
}