{
  "type": "Feature",
  "properties": {
    "iso:country":"ES",
    "sg:address":"Calle de Tarancon, 20",
    "sg:city":"Burriana",
    "sg:orig_category":"Peleter\u00cdas",
    "sg:phone":"+34 964 57 09 96",
    "sg:postcode":"12530",
    "sg:province":"Castell\u00f3n",
    "wof:name":"Badenes Fontfria Sonia",
    "wof:placetype":"venue"
},
  "geometry": {"coordinates":[-0.0840568021,39.888130188],"type":"Point"}
}