{
  "type": "Feature",
  "properties": {
    "addr:full":"Pg Verdaguer, 169 Igualada Barcelona 08700",
    "addr:housenumber":"169",
    "addr:postcode":"08700",
    "addr:street":"Pg Verdaguer",
    "iso:country":"ES",
    "sg:address":"Pg Verdaguer, 169",
    "sg:city":"Igualada",
    "sg:orig_category":"Abogados",
    "sg:phone":"+34 938 03 14 70",
    "sg:postcode":"08700",
    "sg:province":"Barcelona",
    "wof:name":"Diez Garcia Marcelino",
    "wof:placetype":"venue"
},
  "geometry": {"coordinates":[1.6292439699,41.5785179138],"type":"Point"}
}