{
  "type": "Feature",
  "properties": {
    "addr:full":"Avda Julian Besteiro, 54 Olvera C\u00e1diz 11690",
    "addr:housenumber":"54",
    "addr:postcode":"11690",
    "addr:street":"Avda Julian Besteiro;Ca\u0301Diz",
    "iso:country":"ES",
    "sg:address":"Avda Julian Besteiro, 54",
    "sg:city":"Olvera",
    "sg:orig_category":"Aguas (distribuci\u00d3n, Servicios)",
    "sg:phone":"+34 956 13 09 21",
    "sg:postcode":"11690",
    "sg:province":"C\u00e1diz",
    "wof:name":"Aguas Sierra De Cadiz S.a.",
    "wof:placetype":"venue"
},
  "geometry": {"coordinates":[-5.2555317879,36.9343070984],"type":"Point"}
}