{
  "type": "Feature",
  "properties": {
    "addr:full":"Calle de Toledo, 75 Ciudad Real Ciudad Real 13003",
    "addr:housenumber":"75",
    "addr:postcode":"13003",
    "addr:street":"Calle De Toledo",
    "iso:country":"ES",
    "sg:address":"Calle de Toledo, 75",
    "sg:city":"Ciudad Real",
    "sg:orig_category":"Material Y Suministros Para Fotocopiadoras, Reprograf\u00cda",
    "sg:phone":"+34 926 25 44 08",
    "sg:postcode":"13003",
    "sg:province":"Ciudad Real",
    "wof:name":"Mu\u00f1oz Morcillo Pedro",
    "wof:placetype":"venue"
},
  "geometry": {"coordinates":[-3.9279520512,38.9940757751],"type":"Point"}
}