{
  "type": "Feature",
  "properties": {
    "iso:country":"ES",
    "sg:address":"Calle de Mayor, 13",
    "sg:city":"Espinardo",
    "sg:orig_category":"Bancos",
    "sg:phone":"+34 968 34 78 01",
    "sg:postcode":"30011",
    "sg:province":"Murcia",
    "sg:website":"www.bancodevalencia.es",
    "wof:name":"Banco De Valencia S.a.",
    "wof:placetype":"venue"
},
  "geometry": {"coordinates":[-1.1059099436,37.9790267944],"type":"Point"}
}