{
  "type": "Feature",
  "properties": {
    "addr:full":"Calle de Guen-kalea, 14 Markina-xemein Vizcaya 48270",
    "addr:housenumber":"14",
    "addr:postcode":"48270",
    "addr:street":"Calle De Guen-Kalea",
    "iso:country":"ES",
    "sg:address":"Calle de Guen-kalea, 14",
    "sg:city":"Markina-xemein",
    "sg:orig_category":"Puros, Cigarrillos Y Tabaco (al Por Menor)",
    "sg:phone":"+34 946 16 62 31",
    "sg:postcode":"48270",
    "sg:province":"Vizcaya",
    "wof:name":"Etxeberria Mazkiaran Maria Jesus",
    "wof:placetype":"venue"
},
  "geometry": {"coordinates":[-2.4973740578,43.2673377991],"type":"Point"}
}