{
  "type": "Feature",
  "properties": {
    "iso:country":"ES",
    "sg:address":"Calle de Molino, 19",
    "sg:city":"Picazo",
    "sg:orig_category":"Frutas, Legumbres Frescas Y Tempranas (al Por Menor)",
    "sg:phone":"+34 969 38 01 20",
    "sg:postcode":"16211",
    "sg:province":"Cuenca",
    "wof:name":"Poveda Meneses Pedro",
    "wof:placetype":"venue"
},
  "geometry": {"coordinates":[-2.088269949,39.4471435547],"type":"Point"}
}