{
  "type": "Feature",
  "properties": {
    "iso:country":"ES",
    "sg:address":"Calle de Ricardo Montes, 28",
    "sg:city":"Oviedo",
    "sg:orig_category":"Institutos De Belleza",
    "sg:phone":"+34 985 29 40 03",
    "sg:postcode":"33012",
    "sg:province":"Asturias",
    "wof:name":"Liz Gonzalez Adelaida",
    "wof:placetype":"venue"
},
  "geometry": {"coordinates":[-5.8544912338,43.3702659607],"type":"Point"}
}