{
  "type": "Feature",
  "properties": {
    "addr:full":"Calle de Virrey Poveda, 4 Petrer Alicante 03610",
    "addr:housenumber":"4",
    "addr:postcode":"03610",
    "addr:street":"Calle De Virrey Poveda",
    "iso:country":"ES",
    "sg:address":"Calle de Virrey Poveda, 4",
    "sg:city":"Petrer",
    "sg:orig_category":"Empresas De Limpieza",
    "sg:phone":"+34 966 95 03 28",
    "sg:postcode":"03610",
    "sg:province":"Alicante",
    "wof:name":"Brocamar S.l.",
    "wof:placetype":"venue"
},
  "geometry": {"coordinates":[-0.7767959833,38.4835891724],"type":"Point"}
}