{
  "type": "Feature",
  "properties": {
    "iso:country":"ES",
    "sg:address":"Calle de Alcala, 412",
    "sg:city":"Madrid",
    "sg:orig_category":"Cervezas, Bebidas (al Por Mayor)",
    "sg:phone":"+34 914 07 74 82",
    "sg:postcode":"28027",
    "sg:province":"Madrid",
    "wof:name":"Africa Garcia Cristina",
    "wof:placetype":"venue"
},
  "geometry": {"coordinates":[-3.6390171051,40.4374771118],"type":"Point"}
}