{
  "type": "Feature",
  "properties": {
    "iso:country":"ES",
    "sg:address":"Puerta Cerrada, 5",
    "sg:city":"Ecija",
    "sg:orig_category":"Quincaller\u00cda (al Por Menor)",
    "sg:phone":"+34 954 83 08 45",
    "sg:postcode":"41400",
    "sg:province":"Sevilla",
    "wof:name":"Rodriguez Baeza Rafael",
    "wof:placetype":"venue"
},
  "geometry": {"coordinates":[-5.0827579498,37.5399589539],"type":"Point"}
}