{
  "type": "Feature",
  "properties": {
    "iso:country":"ES",
    "sg:address":"Calle de Don Cristian, 10",
    "sg:city":"Malaga",
    "sg:orig_category":"Servicios De Higiene Y Peluquer\u00cda Para Perros Y Gatos",
    "sg:phone":"+34 952 27 31 13",
    "sg:postcode":"29007",
    "sg:province":"M\u00e1laga",
    "wof:name":"Galan Molina Pilar",
    "wof:placetype":"venue"
},
  "geometry": {"coordinates":[-4.429377079,36.7187652588],"type":"Point"}
}