{
  "type": "Feature",
  "properties": {
    "iso:country":"ES",
    "sg:address":"Avda Camilo Jose Cela (de), 5",
    "sg:city":"Alcobendas",
    "sg:orig_category":"Tintes (fabricaci\u00d3n, Al Por Mayor)",
    "sg:phone":"+34 916 62 67 85",
    "sg:postcode":"28100",
    "sg:province":"Madrid",
    "sg:website":"www.pressto.com",
    "wof:name":"Servicio De Tintoreria 2007 Rosa Markt S.l.",
    "wof:placetype":"venue"
},
  "geometry": {"coordinates":[-3.6568100452,40.5466384888],"type":"Point"}
}