{
  "type": "Feature",
  "properties": {
    "addr:full":"Calle de Alibarra, 46 Vitoria-gasteiz \u00c1lava 01010",
    "addr:housenumber":"46",
    "addr:postcode":"01010",
    "addr:street":"Calle De Alibarra",
    "iso:country":"ES",
    "sg:address":"Calle de Alibarra, 46",
    "sg:city":"Vitoria-gasteiz",
    "sg:orig_category":"Venta De Caravanas, Casas M\u00d3viles, Camping",
    "sg:phone":"+34 945 24 04 17",
    "sg:postcode":"01010",
    "sg:province":"\u00c1lava",
    "wof:name":"Centro Autocaravaning Orbea S.l.",
    "wof:placetype":"venue"
},
  "geometry": {"coordinates":[-2.7098133564,42.8655395508],"type":"Point"}
}