{
  "type": "Feature",
  "properties": {
    "addr:full":"Pl Santa Magdalena, 23 Esplugues Llobregat Barcelona 08950",
    "addr:housenumber":"23",
    "addr:postcode":"08950",
    "addr:street":"Pl Santa Magdalena",
    "iso:country":"ES",
    "sg:address":"Pl Santa Magdalena, 23",
    "sg:city":"Esplugues Llobregat",
    "sg:orig_category":"Librer\u00cdas",
    "sg:phone":"+34 933 71 61 13",
    "sg:postcode":"08950",
    "sg:province":"Barcelona",
    "wof:name":"Garcia Pons Albert",
    "wof:placetype":"venue"
},
  "geometry": {"coordinates":[2.0880198479,41.3775901794],"type":"Point"}
}