{
  "type": "Feature",
  "properties": {
    "iso:country":"ES",
    "sg:address":"Calle de La Jara, 1",
    "sg:city":"Trigueros",
    "sg:orig_category":"Ense\u00d1anza, Formaci\u00d3n Profesional: Aprendizaje",
    "sg:phone":"+34 959 30 50 75",
    "sg:postcode":"21620",
    "sg:province":"Huelva",
    "wof:name":"Ayuntamiento De Trigueros",
    "wof:placetype":"venue"
},
  "geometry": {"coordinates":[-6.8352308273,37.3832435608],"type":"Point"}
}