{
  "type": "Feature",
  "properties": {
    "addr:full":"La Fuentina, S/n Navatejera Le\u00f3n 24008",
    "addr:housenumber":"s",
    "addr:postcode":"24008",
    "addr:street":"/ N;Leo\u0301N",
    "iso:country":"ES",
    "sg:address":"La Fuentina, S/n",
    "sg:city":"Navatejera",
    "sg:orig_category":"Empresas De Carpinter\u00cda Met\u00c1lica",
    "sg:phone":"+34 987 28 52 24",
    "sg:postcode":"24008",
    "sg:province":"Le\u00f3n",
    "wof:name":"Suarez Garcia Luciano",
    "wof:placetype":"venue"
},
  "geometry": {"coordinates":[-5.5728387833,42.6237678528],"type":"Point"}
}