{
  "type": "Feature",
  "properties": {
    "addr:full":"Calle de Campo Marin, 1 Zafra Badajoz 06300",
    "addr:housenumber":"1",
    "addr:postcode":"06300",
    "addr:street":"Calle De Campo Marin",
    "iso:country":"ES",
    "sg:address":"Calle de Campo Marin, 1",
    "sg:city":"Zafra",
    "sg:orig_category":"Fabricaci\u00d3n De Equipos Y Piezas Para Veh\u00cdculos, Veh\u00cdculos Industriales",
    "sg:phone":"+34 924 55 03 20",
    "sg:postcode":"06300",
    "sg:province":"Badajoz",
    "wof:name":"Guerrero Y Mu\u00f1oz S. L.",
    "wof:placetype":"venue"
},
  "geometry": {"coordinates":[-6.4190740585,38.4230995178],"type":"Point"}
}