{
  "type": "Feature",
  "properties": {
    "iso:country":"ES",
    "sg:address":"Calle de Mayor, 35",
    "sg:city":"Madrid",
    "sg:orig_category":"Restaurantes",
    "sg:phone":"+34 913 66 46 64",
    "sg:postcode":"28013",
    "sg:province":"Madrid",
    "wof:name":"Cofrades Rodriguez Maria Luisa",
    "wof:placetype":"venue"
},
  "geometry": {"coordinates":[-3.7076640129,40.4161109924],"type":"Point"}
}