{
  "type": "Feature",
  "properties": {
    "addr:full":"Calle de Pablo Picasso, 8 Santa Cruz De Tenerife Santa Cruz De Tenerife 38007",
    "addr:housenumber":"8",
    "addr:postcode":"38007",
    "addr:street":"Calle De Pablo Picasso",
    "iso:country":"ES",
    "sg:address":"Calle de Pablo Picasso, 8",
    "sg:city":"Santa Cruz De Tenerife",
    "sg:orig_category":"\u00d3pticos Optometristas (al Por Menor)",
    "sg:phone":"+34 922 20 54 55",
    "sg:postcode":"38007",
    "sg:province":"Santa Cruz De Tenerife",
    "wof:name":"Centro Optico La Granja Picasso I S.l.",
    "wof:placetype":"venue"
},
  "geometry": {"coordinates":[-16.2645206451,28.4605770111],"type":"Point"}
}