{
  "type": "Feature",
  "properties": {
    "addr:full":"Calle de Blasco De Garay, 19 Madrid Madrid 28015",
    "addr:housenumber":"19",
    "addr:postcode":"madrid;28015",
    "addr:street":"Calle De Blasco De Garay",
    "iso:country":"ES",
    "sg:address":"Calle de Blasco De Garay, 19",
    "sg:city":"Madrid",
    "sg:orig_category":"Centros Empresariales",
    "sg:phone":"+34 915 49 22 07",
    "sg:postcode":"28015",
    "sg:province":"Madrid",
    "sg:website":"www.teycos.com",
    "wof:name":"Television Y Comunicacion Sanitaria S.l.",
    "wof:placetype":"venue"
},
  "geometry": {"coordinates":[-3.7118680477,40.4320526123],"type":"Point"}
}