{
  "type": "Feature",
  "properties": {
    "addr:full":"Calle de Alcalde Sainz De Baranda, 42 Madrid Madrid 28009",
    "addr:housenumber":"42",
    "addr:postcode":"madrid;28009",
    "addr:street":"Calle De Alcalde Sainz De Baranda",
    "iso:country":"ES",
    "sg:address":"Calle de Alcalde Sainz De Baranda, 42",
    "sg:city":"Madrid",
    "sg:orig_category":"Arreglo, Reparaci\u00d3n, Piezas Sueltas De Televisi\u00d3n, V\u00cddeo, Hi",
    "sg:phone":"+34 915 73 34 81",
    "sg:postcode":"28009",
    "sg:province":"Madrid",
    "wof:name":"Futursat S.l.",
    "wof:placetype":"venue"
},
  "geometry": {"coordinates":[-3.672842741,40.4166679382],"type":"Point"}
}