{
  "type": "Feature",
  "properties": {
    "iso:country":"ES",
    "sg:address":"Carrer de Sant Quinti, 31",
    "sg:city":"Barcelona",
    "sg:orig_category":"Empresarios",
    "sg:phone":"+34 934 33 12 25",
    "sg:postcode":"08026",
    "sg:province":"Barcelona",
    "wof:name":"Fundacion Internacional Jose Carreras",
    "wof:placetype":"venue"
},
  "geometry": {"coordinates":[2.178812027,41.4127388],"type":"Point"}
}