{
  "type": "Feature",
  "properties": {
    "iso:country":"ES",
    "sg:address":"Calle de Tortola, 15",
    "sg:city":"Fuenlabrada",
    "sg:orig_category":"Electricidad: Equipos Industriales, Componentes (fabricaci\u00d3n)",
    "sg:phone":"+34 916 42 28 25",
    "sg:postcode":"28946",
    "sg:province":"Madrid",
    "wof:name":"Repel S. L.",
    "wof:placetype":"venue"
},
  "geometry": {"coordinates":[-3.7612540722,40.2651634216],"type":"Point"}
}