{
  "type": "Feature",
  "properties": {
    "iso:country":"ES",
    "sg:address":"Calle de Claveles, 11",
    "sg:city":"Sangonera La Verde O Ermita Nueva",
    "sg:orig_category":"Promotores Constructores",
    "sg:phone":"+34 968 86 93 26",
    "sg:postcode":"30833",
    "sg:province":"Murcia",
    "wof:name":"Galian Perez Pedro",
    "wof:placetype":"venue"
},
  "geometry": {"coordinates":[-1.2072185278,37.9296531677],"type":"Point"}
}