{
  "type": "Feature",
  "properties": {
    "iso:country":"ES",
    "sg:address":"Avda San Jose, S/n",
    "sg:city":"Jumilla",
    "sg:orig_category":"Productores Recolectores, Venta Directa De Vinos",
    "sg:phone":"+34 968 78 07 61",
    "sg:postcode":"30520",
    "sg:province":"Murcia",
    "wof:name":"Finca Luzon S.l.",
    "wof:placetype":"venue"
},
  "geometry": {"coordinates":[-1.3199739456,38.4779891968],"type":"Point"}
}