{
  "type": "Feature",
  "properties": {
    "iso:country":"ES",
    "sg:address":"Calle de Caceres, 1",
    "sg:city":"Polan",
    "sg:orig_category":"Fabricaci\u00d3n De Muebles",
    "sg:phone":"+34 925 37 03 05",
    "sg:postcode":"45161",
    "sg:province":"Toledo",
    "wof:name":"Cariada Del S.l.",
    "wof:placetype":"venue"
},
  "geometry": {"coordinates":[-4.1756806374,39.7882080078],"type":"Point"}
}