{
  "type": "Feature",
  "properties": {
    "iso:country":"ES",
    "sg:address":"Calle de Ferrocarril, 29",
    "sg:city":"Madrid",
    "sg:orig_category":"Bisuter\u00cda, Joyer\u00cda, Relojer\u00cda (al Por Menor)",
    "sg:phone":"+34 915 39 59 30",
    "sg:postcode":"28045",
    "sg:province":"Madrid",
    "wof:name":"Hernanz Hernanz Pedro",
    "wof:placetype":"venue"
},
  "geometry": {"coordinates":[-3.6964566708,40.4008789062],"type":"Point"}
}