{
  "type": "Feature",
  "properties": {
    "iso:country":"ES",
    "sg:address":"Calle de Nueva, 15",
    "sg:city":"Villabona",
    "sg:orig_category":"Molduras, Junquillos, Listones Y Molduras Perforadas",
    "sg:phone":"+34 943 69 09 41",
    "sg:postcode":"20150",
    "sg:province":"Guip\u00f9zcoa",
    "wof:name":"Escudero Huici Gotzon",
    "wof:placetype":"venue"
},
  "geometry": {"coordinates":[-2.0523750782,43.1869430542],"type":"Point"}
}