{
  "type": "Feature",
  "properties": {
    "addr:full":"Trva Siervas De Jesus, 2 Haro La Rioja 26200",
    "addr:housenumber":"2",
    "addr:postcode":"26200",
    "addr:street":"Trva Siervas;Jesus",
    "iso:country":"ES",
    "sg:address":"Trva Siervas De Jesus, 2",
    "sg:city":"Haro",
    "sg:orig_category":"Sindicatos De Trabajadores",
    "sg:phone":"+34 941 31 25 95",
    "sg:postcode":"26200",
    "sg:province":"La Rioja",
    "wof:name":"Union General De Trabajadores De Rioja",
    "wof:placetype":"venue"
},
  "geometry": {"coordinates":[-2.8452138901,42.5770988464],"type":"Point"}
}