{
  "type": "Feature",
  "properties": {
    "addr:full":"Calle de Belmonte De Tajo, 72 Madrid Madrid 28019",
    "addr:housenumber":"72",
    "addr:postcode":"madrid;28019",
    "addr:street":"Calle De Belmonte De Tajo",
    "iso:country":"ES",
    "sg:address":"Calle de Belmonte De Tajo, 72",
    "sg:city":"Madrid",
    "sg:orig_category":"Cerrajer\u00cda, Ferrallista",
    "sg:phone":"+34 915 65 58 10",
    "sg:postcode":"28019",
    "sg:province":"Madrid",
    "wof:name":"Rio Crespo Manuela Del",
    "wof:placetype":"venue"
},
  "geometry": {"coordinates":[-3.720140934,40.3901481628],"type":"Point"}
}