{
  "type": "Feature",
  "properties": {
    "addr:full":"Calle de Alcala, 396 Madrid Madrid 28027",
    "addr:housenumber":"396",
    "addr:postcode":"28027",
    "addr:street":"Calle De Alcala",
    "iso:country":"ES",
    "sg:address":"Calle de Alcala, 396",
    "sg:city":"Madrid",
    "sg:orig_category":"Abogados",
    "sg:phone":"+34 914 07 76 24",
    "sg:postcode":"28027",
    "sg:province":"Madrid",
    "wof:name":"Bayo Herranz Jose",
    "wof:placetype":"venue"
},
  "geometry": {"coordinates":[-3.640568018,40.4367332458],"type":"Point"}
}