{
  "type": "Feature",
  "properties": {
    "iso:country":"ES",
    "sg:address":"Calle de Kareaga Goikoa, 55",
    "sg:city":"Arizgoiti",
    "sg:orig_category":"Muebles, Minoristas",
    "sg:phone":"+34 944 49 13 43",
    "sg:postcode":"48970",
    "sg:province":"Vizcaya",
    "sg:website":"www.muebleslarena.com",
    "wof:name":"Muebles S.larena S.l.",
    "wof:placetype":"venue"
},
  "geometry": {"coordinates":[-2.8961520195,43.2384529114],"type":"Point"}
}