{
  "type": "Feature",
  "properties": {
    "iso:country":"ES",
    "sg:address":"Carrer de Obispo, 39",
    "sg:city":"Santanyi",
    "sg:orig_category":"Loter\u00cda Y T\u00d3mbola",
    "sg:phone":"+34 971 65 41 68",
    "sg:postcode":"07650",
    "sg:province":"Islas Baleares",
    "wof:name":"Garcia Gonzalez Rafael",
    "wof:placetype":"venue"
},
  "geometry": {"coordinates":[3.1265099049,39.353263855],"type":"Point"}
}