{
  "type": "Feature",
  "properties": {
    "iso:country":"ES",
    "sg:address":"Calle de Marques De Comillas, 4",
    "sg:city":"Almeria",
    "sg:classifiers":[
        {
            "category":"Shopping",
            "subcategory":"Clothing, Apparel, & Fashions",
            "type":"Retail Goods"
        }
    ],
    "sg:phone":"+34 950 25 13 55",
    "sg:postcode":"04004",
    "sg:province":"Almer\u00eda",
    "sg:tags":[
        "boutique"
    ],
    "wof:name":"Rodriguez Campra Maria Del Carmen",
    "wof:placetype":"venue"
},
  "geometry": {"coordinates":[-2.4623699188,36.8376159668],"type":"Point"}
}