{
  "type": "Feature",
  "properties": {
    "iso:country":"ES",
    "sg:address":"Calle de Iglesia, S/n",
    "sg:city":"Morales Rey",
    "sg:orig_category":"Iglesia Cat\u00d3lica",
    "sg:phone":"+34 980 65 13 24",
    "sg:postcode":"49693",
    "sg:province":"Zamora",
    "wof:name":"Baladron Santos Angel",
    "wof:placetype":"venue"
},
  "geometry": {"coordinates":[-5.7855081558,42.0689620972],"type":"Point"}
}