{
  "type": "Feature",
  "properties": {
    "addr:full":"Calle de Lopez De Hoyos, 364 Madrid Madrid 28043",
    "addr:housenumber":"364",
    "addr:postcode":"28043",
    "addr:street":"Calle De Lopez De Hoyos",
    "iso:country":"ES",
    "sg:address":"Calle de Lopez De Hoyos, 364",
    "sg:city":"Madrid",
    "sg:orig_category":"Asesor\u00cda Sobre Comunicaci\u00d3n De Empresas",
    "sg:phone":"+34 914 13 15 64",
    "sg:postcode":"28043",
    "sg:province":"Madrid",
    "wof:name":"Federico Ruiz Y Asociados S.l.",
    "wof:placetype":"venue"
},
  "geometry": {"coordinates":[-3.6599578857,40.4584503174],"type":"Point"}
}