{
  "type": "Feature",
  "properties": {
    "addr:full":"Carr Creu (la), 2 Mollerussa Lleida 25230",
    "addr:housenumber":"2",
    "addr:postcode":"25230",
    "addr:street":"Carr Creu La",
    "iso:country":"ES",
    "sg:address":"Carr Creu (la), 2",
    "sg:city":"Mollerussa",
    "sg:classifiers":[
        {
            "category":"Autos & Motor Vehicles",
            "subcategory":"Automobile Sales",
            "type":"Retail Goods"
        }
    ],
    "sg:phone":"+34 973 60 12 42",
    "sg:postcode":"25230",
    "sg:province":"Lleida",
    "wof:name":"Ros Ausas Consuelo",
    "wof:placetype":"venue"
},
  "geometry": {"coordinates":[0.8936949968,41.6300392151],"type":"Point"}
}