{
  "type": "Feature",
  "properties": {
    "addr:full":"Calle de Iglesia Baja, S/n Villamayor Zaragoza 50162",
    "addr:housenumber":"s",
    "addr:postcode":"50162",
    "addr:street":"Calle De Iglesia Baja;/ N Villamayor",
    "iso:country":"ES",
    "sg:address":"Calle de Iglesia Baja, S/n",
    "sg:city":"Villamayor",
    "sg:orig_category":"Panader\u00cdas, Panader\u00cdas",
    "sg:phone":"+34 976 58 96 35",
    "sg:postcode":"50162",
    "sg:province":"Zaragoza",
    "wof:name":"Arribas Macipe Josefa",
    "wof:placetype":"venue"
},
  "geometry": {"coordinates":[-0.7734904289,41.6853294373],"type":"Point"}
}