{
  "type": "Feature",
  "properties": {
    "addr:full":"Calle de Pinar (el), 27 Santo Domingo De La Calzada La Rioja 26250",
    "addr:housenumber":"27",
    "addr:postcode":"26250",
    "addr:street":"Calle De Pinar El;Rioja",
    "iso:country":"ES",
    "sg:address":"Calle de Pinar (el), 27",
    "sg:city":"Santo Domingo De La Calzada",
    "sg:orig_category":"Juegos Y Juguetes (al Por Menor)",
    "sg:phone":"+34 941 34 28 53",
    "sg:postcode":"26250",
    "sg:province":"La Rioja",
    "wof:name":"Mendiola Ortega S.l.",
    "wof:placetype":"venue"
},
  "geometry": {"coordinates":[-2.9521620274,42.4396438599],"type":"Point"}
}