{
  "type": "Feature",
  "properties": {
    "addr:full":"Pg Manresa, 15 Sabadell Barcelona 08201",
    "addr:housenumber":"15",
    "addr:postcode":"08201",
    "addr:street":"Pg Manresa",
    "iso:country":"ES",
    "sg:address":"Pg Manresa, 15",
    "sg:city":"Sabadell",
    "sg:orig_category":"Restaurantes",
    "sg:phone":"+34 937 26 24 95",
    "sg:postcode":"08201",
    "sg:province":"Barcelona",
    "wof:name":"Bikate Valles S.l.",
    "wof:placetype":"venue"
},
  "geometry": {"coordinates":[2.1085979939,41.5473060608],"type":"Point"}
}