{
  "type": "Feature",
  "properties": {
    "addr:full":"Calle de Barquero (el), 8 Alcossebre Castell\u00f3n 12579",
    "addr:housenumber":"8",
    "addr:postcode":"12579",
    "addr:street":"Calle De Barquero El;Castello\u0301N",
    "iso:country":"ES",
    "sg:address":"Calle de Barquero (el), 8",
    "sg:city":"Alcossebre",
    "sg:orig_category":"Promotores Constructores",
    "sg:phone":"+34 964 41 44 12",
    "sg:postcode":"12579",
    "sg:province":"Castell\u00f3n",
    "wof:name":"Meson Ximo C.b.",
    "wof:placetype":"venue"
},
  "geometry": {"coordinates":[0.2755751908,40.2440490723],"type":"Point"}
}