{
  "type": "Feature",
  "properties": {
    "iso:country":"ES",
    "sg:address":"Ctra. Extremadura, Km. 0087,0",
    "sg:city":"Otero",
    "sg:orig_category":"Distribuci\u00d3n De Petr\u00d3leo Y Derivados",
    "sg:phone":"+34 925 86 15 85",
    "sg:postcode":"45543",
    "sg:province":"Toledo",
    "sg:website":"www.cepsa.es",
    "wof:name":"Esteban S.l.",
    "wof:placetype":"venue"
},
  "geometry": {"coordinates":[-4.5130162239,39.9997634888],"type":"Point"}
}