{
  "type": "Feature",
  "properties": {
    "addr:full":"Carrer de Cort (la), 30 Vilafranca Penedes Barcelona 08720",
    "addr:housenumber":"30",
    "addr:postcode":"08720",
    "addr:street":"Carrer De Cort La;Penedes Barcelona",
    "iso:country":"ES",
    "sg:address":"Carrer de Cort (la), 30",
    "sg:city":"Vilafranca Penedes",
    "sg:orig_category":"Bisuter\u00cda, Joyer\u00cda, Relojer\u00cda (al Por Menor)",
    "sg:phone":"+34 938 92 19 38",
    "sg:postcode":"08720",
    "sg:province":"Barcelona",
    "wof:name":"Nogues Mumbru Jose Antonio",
    "wof:placetype":"venue"
},
  "geometry": {"coordinates":[1.697527051,41.3458976746],"type":"Point"}
}