{
  "type": "Feature",
  "properties": {
    "addr:full":"Avda Galicia, 17 Pontes Garcia Rodriguez La Coru\u00f1a 15320",
    "addr:housenumber":"17",
    "addr:postcode":"15320",
    "addr:street":"Avda Galicia;Corun\u0303A",
    "iso:country":"ES",
    "sg:address":"Avda Galicia, 17",
    "sg:city":"Pontes Garcia Rodriguez",
    "sg:orig_category":"Caf\u00c9s, Bares, Cervecer\u00cdas",
    "sg:phone":"+34 981 45 06 87",
    "sg:postcode":"15320",
    "sg:province":"La Coru\u00f1a",
    "wof:name":"Lopez Lopez Maria Jose",
    "wof:placetype":"venue"
},
  "geometry": {"coordinates":[-7.8527188301,43.4470481873],"type":"Point"}
}