{
  "type": "Feature",
  "properties": {
    "addr:full":"Calle de Serpis, 52 Valencia Valencia 46022",
    "addr:housenumber":"52",
    "addr:postcode":"46022",
    "addr:street":"Calle De Serpis",
    "iso:country":"ES",
    "sg:address":"Calle de Serpis, 52",
    "sg:city":"Valencia",
    "sg:orig_category":"Peluquer\u00cdas, Peluquer\u00cda Mixta",
    "sg:phone":"+34 963 72 30 57",
    "sg:postcode":"46022",
    "sg:province":"Valencia",
    "wof:name":"Montesinos Mariano Josefina",
    "wof:placetype":"venue"
},
  "geometry": {"coordinates":[-0.3446860015,39.4747505188],"type":"Point"}
}