{
  "type": "Feature",
  "properties": {
    "addr:full":"Calle de Jerusalen, 5 Zaragoza Zaragoza 50009",
    "addr:housenumber":"5",
    "addr:postcode":"50009",
    "addr:street":"Calle De Jerusalen",
    "iso:country":"ES",
    "sg:address":"Calle de Jerusalen, 5",
    "sg:city":"Zaragoza",
    "sg:orig_category":"Industria Qu\u00cdmica",
    "sg:phone":"+34 976 56 78 92",
    "sg:postcode":"50009",
    "sg:province":"Zaragoza",
    "wof:name":"Merida Gil Joaquin",
    "wof:placetype":"venue"
},
  "geometry": {"coordinates":[-0.9031230211,41.6356811523],"type":"Point"}
}