{
  "type": "Feature",
  "properties": {
    "iso:country":"ES",
    "sg:address":"Carrer de Doctor Marti I Julia, S/n",
    "sg:city":"Hospitalet Llobregat",
    "sg:orig_category":"Confecci\u00d3n De Trajes Para Se\u00d1oras",
    "sg:phone":"+34 934 49 25 43",
    "sg:postcode":"08903",
    "sg:province":"Barcelona",
    "wof:name":"Balanza Colom Merce",
    "wof:placetype":"venue"
},
  "geometry": {"coordinates":[2.1232655048,41.3727912903],"type":"Point"}
}