{
  "type": "Feature",
  "properties": {
    "addr:full":"Calle de Calderon De La Barca, 21 Campo Criptana Ciudad Real 13610",
    "addr:housenumber":"21",
    "addr:postcode":"13610",
    "addr:street":"Calle De Calderon De La Barca;Criptana",
    "iso:country":"ES",
    "sg:address":"Calle de Calderon De La Barca, 21",
    "sg:city":"Campo Criptana",
    "sg:orig_category":"Agencias Y Agentes Comerciales, Representantes",
    "sg:phone":"+34 926 56 14 51",
    "sg:postcode":"13610",
    "sg:province":"Ciudad Real",
    "wof:name":"Rodriguez Lucas-torres Tomas",
    "wof:placetype":"venue"
},
  "geometry": {"coordinates":[-3.1307415962,39.4052391052],"type":"Point"}
}