{
  "type": "Feature",
  "properties": {
    "iso:country":"ES",
    "sg:address":"Rua Cardeal Paya (do), 12",
    "sg:city":"Santiago De Compostela",
    "sg:orig_category":"Lencer\u00cda Femenina, Corseter\u00cda, Trajes De Ba\u00d1o (al Por Menor)",
    "sg:phone":"+34 981 57 16 04",
    "sg:postcode":"15703",
    "sg:province":"A Coru\u00f1a",
    "wof:name":"Seijo Penido Concepcion",
    "wof:placetype":"venue"
},
  "geometry": {"coordinates":[-8.5428886414,42.8779067993],"type":"Point"}
}