{
  "type": "Feature",
  "properties": {
    "addr:full":"Avda Montecelo, 21 Mourente Pontevedra 36161",
    "addr:housenumber":"21",
    "addr:postcode":"36161",
    "addr:street":"Avda Montecelo",
    "iso:country":"ES",
    "sg:address":"Avda Montecelo, 21",
    "sg:city":"Mourente",
    "sg:orig_category":"Centros Empresariales",
    "sg:phone":"+34 986 86 68 89",
    "sg:postcode":"36161",
    "sg:province":"Pontevedra",
    "wof:name":"Pontevedra Luz S.l.",
    "wof:placetype":"venue"
},
  "geometry": {"coordinates":[-8.5811071396,42.4439888],"type":"Point"}
}