{
  "type": "Feature",
  "properties": {
    "iso:country":"ES",
    "sg:address":"Calle de Padre Tabernero, 20",
    "sg:city":"Guadalajara",
    "sg:orig_category":"Puertas Autom\u00c1ticas, Puertas De Garaje",
    "sg:phone":"+34 949 22 14 36",
    "sg:postcode":"19002",
    "sg:province":"Guadalajara",
    "wof:name":"Yela Diaz Pedro",
    "wof:placetype":"venue"
},
  "geometry": {"coordinates":[-3.1645920277,40.6272621155],"type":"Point"}
}