{
  "type": "Feature",
  "properties": {
    "addr:full":"Plaz Pablo Iglesias, S/n Algaba Sevilla 41980",
    "addr:postcode":"41980",
    "addr:street":"Pablo Iglesias S / N Algaba",
    "iso:country":"ES",
    "sg:address":"Plaz Pablo Iglesias, S/n",
    "sg:city":"Algaba",
    "sg:orig_category":"Importaci\u00d3n",
    "sg:phone":"+34 955 78 85 38",
    "sg:postcode":"41980",
    "sg:province":"Sevilla",
    "wof:name":"Molina Herrera Francisco",
    "wof:placetype":"venue"
},
  "geometry": {"coordinates":[-6.0098190308,37.4644851685],"type":"Point"}
}