{
  "type": "Feature",
  "properties": {
    "iso:country":"ES",
    "sg:address":"San Pedro Kalea, 19",
    "sg:city":"Bergara",
    "sg:orig_category":"Estancos",
    "sg:phone":"+34 943 76 20 13",
    "sg:postcode":"20570",
    "sg:province":"Guip\u00f9zcoa",
    "wof:name":"Azcarate Azcarate Rosa Maria",
    "wof:placetype":"venue"
},
  "geometry": {"coordinates":[-2.4136929512,43.1161766052],"type":"Point"}
}