{
  "type": "Feature",
  "properties": {
    "iso:country":"ES",
    "sg:address":"Plaz San Ignacio, 1",
    "sg:city":"Malaga",
    "sg:orig_category":"M\u00c9dicos: Psiquiatr\u00cda",
    "sg:phone":"+34 952 21 25 88",
    "sg:postcode":"29008",
    "sg:province":"M\u00e1laga",
    "wof:name":"Cotrina De Luna Esteban",
    "wof:placetype":"venue"
},
  "geometry": {"coordinates":[-4.4234938622,36.721408844],"type":"Point"}
}