{
  "type": "Feature",
  "properties": {
    "iso:country":"ES",
    "sg:address":"Calle de Jose Tallavi, 1",
    "sg:city":"Malaga",
    "sg:orig_category":"Loter\u00cda Y T\u00d3mbola",
    "sg:phone":"+34 952 26 05 95",
    "sg:postcode":"29014",
    "sg:province":"M\u00e1laga",
    "wof:name":"Valenzuela Gonzalez Isabel",
    "wof:placetype":"venue"
},
  "geometry": {"coordinates":[-4.4222640991,36.7409553528],"type":"Point"}
}