{
  "type": "Feature",
  "properties": {
    "addr:full":"Calle de Escoriaza Y Fabro, 103 Zaragoza Zaragoza 50010",
    "addr:housenumber":"103",
    "addr:postcode":"50010",
    "addr:street":"Calle De Escoriaza Y Fabro",
    "iso:country":"ES",
    "sg:address":"Calle de Escoriaza Y Fabro, 103",
    "sg:city":"Zaragoza",
    "sg:orig_category":"Institutos De Belleza",
    "sg:phone":"+34 976 32 73 99",
    "sg:postcode":"50010",
    "sg:province":"Zaragoza",
    "wof:name":"De La Hoya Benito Olga",
    "wof:placetype":"venue"
},
  "geometry": {"coordinates":[-0.8980590105,41.6541900635],"type":"Point"}
}