{
  "type": "Feature",
  "properties": {
    "addr:full":"Calle de San Juan, 1 Molina Guadalajara 19300",
    "addr:housenumber":"1",
    "addr:postcode":"19300",
    "addr:street":"Calle De San Juan",
    "iso:country":"ES",
    "sg:address":"Calle de San Juan, 1",
    "sg:city":"Molina",
    "sg:orig_category":"Bisuter\u00cda, Joyer\u00cda, Relojer\u00cda (al Por Menor)",
    "sg:phone":"+34 949 83 20 31",
    "sg:postcode":"19300",
    "sg:province":"Guadalajara",
    "wof:name":"Terybal Promiser S.l.",
    "wof:placetype":"venue"
},
  "geometry": {"coordinates":[-1.8850489855,40.8433685303],"type":"Point"}
}