{
  "type": "Feature",
  "properties": {
    "iso:country":"ES",
    "sg:address":"Calle de Barranco San Juan, 183",
    "sg:city":"Puerto De La Madera",
    "sg:orig_category":"Prot\u00c9sicos Dentales",
    "sg:phone":"+34 922 56 17 11",
    "sg:postcode":"38350",
    "sg:province":"Santa Cruz De Tenerife",
    "wof:name":"Keradent S.l.",
    "wof:placetype":"venue"
},
  "geometry": {"coordinates":[-16.3995780945,28.494550705],"type":"Point"}
}