{
  "type": "Feature",
  "properties": {
    "iso:country":"ES",
    "sg:address":"Ctra Logro\u00d1o, 42",
    "sg:city":"Oyon-oion",
    "sg:orig_category":"Reposter\u00cdas",
    "sg:phone":"+34 945 60 18 46",
    "sg:postcode":"01320",
    "sg:province":"\u00c1lava",
    "wof:name":"Panaderia Reposteria La Oka S.c.",
    "wof:placetype":"venue"
},
  "geometry": {"coordinates":[-2.4375290871,42.4983596802],"type":"Point"}
}