{
  "type": "Feature",
  "properties": {
    "addr:full":"Calle de Socorro, 38 Vinaros Castell\u00f3n 12500",
    "addr:housenumber":"38",
    "addr:postcode":"12500",
    "addr:street":"Calle De Socorro",
    "iso:country":"ES",
    "sg:address":"Calle de Socorro, 38",
    "sg:city":"Vinaros",
    "sg:orig_category":"Bancos",
    "sg:phone":"+34 964 40 72 30",
    "sg:postcode":"12500",
    "sg:province":"Castell\u00f3n",
    "sg:website":"www.bancopastor.es",
    "wof:name":"R Cable Y Telecomunicaciones Galicia S.a.",
    "wof:placetype":"venue"
},
  "geometry": {"coordinates":[0.4749450088,40.4711990356],"type":"Point"}
}