{
  "type": "Feature",
  "properties": {
    "iso:country":"ES",
    "sg:address":"Calle de Virgen Del Rosario, 3",
    "sg:city":"Torrent",
    "sg:orig_category":"Empresas De Pintura Y Revestimientos",
    "sg:phone":"+34 961 56 13 84",
    "sg:postcode":"46900",
    "sg:province":"Valencia",
    "wof:name":"Sanchez Martinez Julian",
    "wof:placetype":"venue"
},
  "geometry": {"coordinates":[-0.464598,39.4353675842],"type":"Point"}
}