{
  "type": "Feature",
  "properties": {
    "addr:full":"Calle de Puerta Nueva, 22 San Lorenzo Murcia 30008",
    "addr:housenumber":"22",
    "addr:postcode":"30008",
    "addr:street":"Calle De Puerta Nueva",
    "iso:country":"ES",
    "sg:address":"Calle de Puerta Nueva, 22",
    "sg:city":"San Lorenzo",
    "sg:orig_category":"Cajas De Ahorro",
    "sg:phone":"+34 968 24 18 63",
    "sg:postcode":"30008",
    "sg:province":"Murcia",
    "wof:name":"Caixa D'estalvis I Pensions De Barcelona",
    "wof:placetype":"venue"
},
  "geometry": {"coordinates":[-1.1280479431,37.9919090271],"type":"Point"}
}