{
  "type": "Feature",
  "properties": {
    "iso:country":"ES",
    "sg:address":"Calle de Fragua, 5",
    "sg:city":"Huermeces Cerro",
    "sg:orig_category":"Deportes Y Programas De Aventura",
    "sg:phone":"+34 949 39 77 21",
    "sg:postcode":"19295",
    "sg:province":"Guadalajara",
    "wof:name":"Ecoaventura S.l.",
    "wof:placetype":"venue"
},
  "geometry": {"coordinates":[-2.7959730625,41.0531768799],"type":"Point"}
}