{
  "type": "Feature",
  "properties": {
    "addr:full":"Carrer de Pallars, 141 Barcelona Barcelona 08018",
    "addr:housenumber":"141",
    "addr:postcode":"08018",
    "addr:street":"Carrer De Pallars",
    "iso:country":"ES",
    "sg:address":"Carrer de Pallars, 141",
    "sg:city":"Barcelona",
    "sg:orig_category":"Electricidad: Instaladores",
    "sg:phone":"+34 933 00 68 70",
    "sg:postcode":"08018",
    "sg:province":"Barcelona",
    "wof:name":"Promotec Instalaciones S.l.",
    "wof:placetype":"venue"
},
  "geometry": {"coordinates":[2.1936030388,41.3980979919],"type":"Point"}
}