{
  "type": "Feature",
  "properties": {
    "iso:country":"ES",
    "sg:address":"Calle de Anselmo Cuenca, 9",
    "sg:city":"Huete",
    "sg:orig_category":"Carnicer\u00cdas, Carnicer\u00cdas",
    "sg:phone":"+34 969 37 11 67",
    "sg:postcode":"16500",
    "sg:province":"Cuenca",
    "wof:name":"Carbone Lopez Isidro",
    "wof:placetype":"venue"
},
  "geometry": {"coordinates":[-2.6586401463,40.155796051],"type":"Point"}
}