{
  "type": "Feature",
  "properties": {
    "addr:full":"Calle de Miranda De Ebro, 2 Vitoria-gasteiz \u00c1lava 01003",
    "addr:housenumber":"2",
    "addr:postcode":"01003",
    "addr:street":"Calle De Miranda;Ebro",
    "iso:country":"ES",
    "sg:address":"Calle de Miranda De Ebro, 2",
    "sg:city":"Vitoria-gasteiz",
    "sg:orig_category":"Venta, Instalaci\u00d3n De Calefacci\u00d3n",
    "sg:phone":"+34 945 12 26 75",
    "sg:postcode":"01003",
    "sg:province":"\u00c1lava",
    "wof:name":"Giroa S.a.",
    "wof:placetype":"venue"
},
  "geometry": {"coordinates":[-2.6627209187,42.8472671509],"type":"Point"}
}