{
  "type": "Feature",
  "properties": {
    "iso:country":"ES",
    "sg:address":"Avda Mar (del), S/n",
    "sg:city":"Linea De La Concepcion",
    "sg:orig_category":"Pr\u00c1ctica De Vela, Navegaci\u00d3n Y Deportes N\u00c1uticos Y Acu\u00c1ticos",
    "sg:phone":"+34 956 17 10 17",
    "sg:postcode":"11300",
    "sg:province":"C\u00e1diz",
    "wof:name":"Real Club Nautico De La Linea",
    "wof:placetype":"venue"
},
  "geometry": {"coordinates":[-5.3525838852,36.1608390808],"type":"Point"}
}