{
  "type": "Feature",
  "properties": {
    "iso:country":"ES",
    "sg:address":"Calle de Quijote (don), 44",
    "sg:city":"Socuellamos",
    "sg:orig_category":"Relojer\u00cda (al Por Menor, Reparaci\u00d3n)",
    "sg:phone":"+34 926 53 08 10",
    "sg:postcode":"13630",
    "sg:province":"Ciudad Real",
    "wof:name":"Zalve Bustos Antonio",
    "wof:placetype":"venue"
},
  "geometry": {"coordinates":[-2.7896430492,39.2869987488],"type":"Point"}
}