{
  "type": "Feature",
  "properties": {
    "addr:full":"Pl Forum (del), S/n Tarragona Tarragona 43003",
    "addr:housenumber":"/ n",
    "addr:postcode":"43003",
    "addr:street":"Pl;Del S",
    "iso:country":"ES",
    "sg:address":"Pl Forum (del), S/n",
    "sg:city":"Tarragona",
    "sg:orig_category":"Pescader\u00cdas (al Por Menor)",
    "sg:phone":"+34 977 21 60 00",
    "sg:postcode":"43003",
    "sg:province":"Tarragona",
    "wof:name":"Espa\u00f1ol Franqueza Rosa Maria",
    "wof:placetype":"venue"
},
  "geometry": {"coordinates":[1.2587850094,41.1177940369],"type":"Point"}
}