{
  "type": "Feature",
  "properties": {
    "iso:country":"ES",
    "sg:address":"Pol Ind La Barrena, S/n",
    "sg:city":"Tudela",
    "sg:orig_category":"Material Y Herramientas Agr\u00cdcolas",
    "sg:phone":"+34 948 84 83 81",
    "sg:postcode":"31500",
    "sg:province":"Navarra",
    "wof:name":"Tavesa Y Servicios S. A.",
    "wof:placetype":"venue"
},
  "geometry": {"coordinates":[-1.60295403,42.0619239807],"type":"Point"}
}