{
  "type": "Feature",
  "properties": {
    "addr:full":"Pla\u00c7 Sant Roc, 27 Bellpuig Lleida 25250",
    "addr:housenumber":"27",
    "addr:postcode":"25250",
    "iso:country":"ES",
    "sg:address":"Pla\u00c7 Sant Roc, 27",
    "sg:city":"Bellpuig",
    "sg:orig_category":"Distribuci\u00d3n De Petr\u00d3leo Y Derivados",
    "sg:phone":"+34 973 32 03 92",
    "sg:postcode":"25250",
    "sg:province":"Lleida",
    "wof:name":"Tosca Mata S.c.p",
    "wof:placetype":"venue"
},
  "geometry": {"coordinates":[1.0088200569,41.6270713806],"type":"Point"}
}