{
  "type": "Feature",
  "properties": {
    "addr:full":"Calle de Gravina, 21 Palmas De Gran Canaria Las Palmas 35010",
    "addr:housenumber":"21",
    "addr:postcode":"35010",
    "addr:street":"Calle De Gravina",
    "iso:country":"ES",
    "sg:address":"Calle de Gravina, 21",
    "sg:city":"Palmas De Gran Canaria",
    "sg:orig_category":"Promotores Constructores",
    "sg:phone":"+34 928 22 56 43",
    "sg:postcode":"35010",
    "sg:province":"Las Palmas",
    "wof:name":"Gravinamar S.l.",
    "wof:placetype":"venue"
},
  "geometry": {"coordinates":[-15.4389486313,28.1346683502],"type":"Point"}
}