{
  "type": "Feature",
  "properties": {
    "iso:country":"ES",
    "sg:address":"Avgd Sud, (del), 2",
    "sg:city":"Carlet",
    "sg:orig_category":"Agencias De Viajes",
    "sg:phone":"+34 962 53 80 92",
    "sg:postcode":"46240",
    "sg:province":"Valencia",
    "sg:website":"www.giramondo.es",
    "wof:name":"Viatges Carlet S.l",
    "wof:placetype":"venue"
},
  "geometry": {"coordinates":[-0.5209739804,39.2250289917],"type":"Point"}
}