{
  "type": "Feature",
  "properties": {
    "iso:country":"ES",
    "sg:address":"Pl Constitucio (la), S/n",
    "sg:city":"Denia",
    "sg:orig_category":"Iglesia Cat\u00d3lica",
    "sg:phone":"+34 965 78 01 76",
    "sg:postcode":"03700",
    "sg:province":"Alicante",
    "wof:name":"Parroquia Nuestra Se\u00f1ora De La Asuncion",
    "wof:placetype":"venue"
},
  "geometry": {"coordinates":[0.1061500013,38.8407440186],"type":"Point"}
}