{
  "type": "Feature",
  "properties": {
    "iso:country":"ES",
    "sg:address":"Avda San Juan De La Salle, 37",
    "sg:city":"Sevilla",
    "sg:orig_category":"Frutas, Legumbres Frescas Y Tempranas (al Por Menor)",
    "sg:phone":"+34 954 06 15 23",
    "sg:postcode":"41008",
    "sg:province":"Sevilla",
    "wof:name":"Galera Colla Isabel",
    "wof:placetype":"venue"
},
  "geometry": {"coordinates":[-5.9730410576,37.4066619873],"type":"Point"}
}