{
  "type": "Feature",
  "properties": {
    "addr:full":"Avda Cuba, 13 Palencia Palencia 34003",
    "addr:housenumber":"13",
    "addr:postcode":"34003",
    "addr:street":"Avda Cuba",
    "iso:country":"ES",
    "sg:address":"Avda Cuba, 13",
    "sg:city":"Palencia",
    "sg:orig_category":"Seguridad Social",
    "sg:phone":"+34 979 75 05 31",
    "sg:postcode":"34003",
    "sg:province":"Palencia",
    "wof:name":"Mutua Monta\u00f1esa Mutua Patronal De Accidentes De Trabajo N 7",
    "wof:placetype":"venue"
},
  "geometry": {"coordinates":[-4.5221247673,42.0131950378],"type":"Point"}
}