{
  "type": "Feature",
  "properties": {
    "addr:full":"Calle de Aurora, 11 Puerto De Santa Maria C\u00e1diz 11500",
    "addr:housenumber":"11",
    "addr:postcode":"11500",
    "addr:street":"Calle De Aurora;Ca\u0301Diz",
    "iso:country":"ES",
    "sg:address":"Calle de Aurora, 11",
    "sg:city":"Puerto De Santa Maria",
    "sg:orig_category":"Abogados",
    "sg:phone":"+34 956 54 07 26",
    "sg:postcode":"11500",
    "sg:province":"C\u00e1diz",
    "wof:name":"Delgado Gomez Juan Pascual",
    "wof:placetype":"venue"
},
  "geometry": {"coordinates":[-6.2281470299,36.5933303833],"type":"Point"}
}