{
  "type": "Feature",
  "properties": {
    "iso:country":"ES",
    "sg:address":"Calle de Anton De Alaminos, 4",
    "sg:city":"Sevilla",
    "sg:orig_category":"Productos Fitosanitarios (negocio, Aplicaci\u00d3n)",
    "sg:phone":"+34 954 67 28 05",
    "sg:postcode":"41007",
    "sg:province":"Sevilla",
    "sg:website":"www.monsanto.com",
    "wof:name":"Monsanto Agricultura Espa\u00d1a S.l.",
    "wof:placetype":"venue"
},
  "geometry": {"coordinates":[-5.9498953819,37.3964576721],"type":"Point"}
}