{
  "type": "Feature",
  "properties": {
    "addr:full":"Calle de Duque De Sesto, 38 Madrid Madrid 28009",
    "addr:housenumber":"38",
    "addr:postcode":"madrid;28009",
    "addr:street":"Calle De Duque De Sesto",
    "iso:country":"ES",
    "sg:address":"Calle de Duque De Sesto, 38",
    "sg:city":"Madrid",
    "sg:orig_category":"Comercio, Reparaci\u00d3n De Motocicletas, Bicicletas Y Piezas Sueltas",
    "sg:phone":"+34 914 31 49 95",
    "sg:postcode":"28009",
    "sg:province":"Madrid",
    "wof:name":"Motorecambios Y Accesorios S.l.",
    "wof:placetype":"venue"
},
  "geometry": {"coordinates":[-3.6755273342,40.4224510193],"type":"Point"}
}