{
  "type": "Feature",
  "properties": {
    "addr:full":"Rua Doctor Fleming, 2 Ourense Ourense 32003",
    "addr:housenumber":"2",
    "addr:postcode":"32003",
    "addr:street":"Rua Doctor Fleming",
    "iso:country":"ES",
    "sg:address":"Rua Doctor Fleming, 2",
    "sg:city":"Ourense",
    "sg:orig_category":"Caf\u00c9s, Bares, Cervecer\u00cdas",
    "sg:phone":"+34 988 22 10 02",
    "sg:postcode":"32003",
    "sg:province":"Ourense",
    "wof:name":"Puga Cid Emilia",
    "wof:placetype":"venue"
},
  "geometry": {"coordinates":[-7.8671030998,42.3367843628],"type":"Point"}
}