{
  "type": "Feature",
  "properties": {
    "iso:country":"ES",
    "sg:address":"Carr Sant Grau, 11",
    "sg:city":"Girona",
    "sg:orig_category":"Cerrajer\u00cda, Ferrallista",
    "sg:phone":"+34 972 20 27 31",
    "sg:postcode":"17003",
    "sg:province":"Girona",
    "wof:name":"Manrique Jerez Primitivo",
    "wof:placetype":"venue"
},
  "geometry": {"coordinates":[2.8313260078,41.9726104736],"type":"Point"}
}