{
  "type": "Feature",
  "properties": {
    "addr:full":"Cmno Purchil (de), 66 Granada Granada 18...",
    "addr:housenumber":"66;18 ...",
    "addr:street":"Cmno Purchil De;Granada",
    "iso:country":"ES",
    "sg:address":"Cmno Purchil (de), 66",
    "sg:city":"Granada",
    "sg:orig_category":"Lecher\u00cdas",
    "sg:phone":"+34 958 24 01 00",
    "sg:postcode":"18...",
    "sg:province":"Granada",
    "wof:name":"Puleva Food S.l.",
    "wof:placetype":"venue"
},
  "geometry": {"coordinates":[-3.6054260731,37.1703987122],"type":"Point"}
}