{
  "type": "Feature",
  "properties": {
    "addr:full":"Calle de Victor Pradera, 6 Logro\u00f1o La Rioja 26001",
    "addr:housenumber":"6",
    "addr:postcode":"26001",
    "addr:street":"Calle De Victor Pradera;Rioja",
    "iso:country":"ES",
    "sg:address":"Calle de Victor Pradera, 6",
    "sg:city":"Logro\u00f1o",
    "sg:orig_category":"Arquitectos",
    "sg:phone":"+34 941 21 28 61",
    "sg:postcode":"26001",
    "sg:province":"La Rioja",
    "wof:name":"A Mas C Arquitectura Integral Y Consultoria S.l.",
    "wof:placetype":"venue"
},
  "geometry": {"coordinates":[-2.4478461742,42.4640159607],"type":"Point"}
}