{
  "type": "Feature",
  "properties": {
    "iso:country":"ES",
    "sg:address":"Calle de Seco Oloroso, 12",
    "sg:city":"Malaga",
    "sg:orig_category":"Promotores Constructores",
    "sg:phone":"+34 952 65 19 61",
    "sg:postcode":"29014",
    "sg:province":"M\u00e1laga",
    "wof:name":"Consymant S.l",
    "wof:placetype":"venue"
},
  "geometry": {"coordinates":[-4.4135398865,36.7446937561],"type":"Point"}
}