{
  "type": "Feature",
  "properties": {
    "addr:full":"Monasterio Usun, 2 Iru\u00f1a Navarra 31011",
    "addr:housenumber":"2",
    "addr:postcode":"31011",
    "addr:street":"Usun",
    "iso:country":"ES",
    "sg:address":"Monasterio Usun, 2",
    "sg:city":"Iru\u00f1a",
    "sg:orig_category":"Empresas De Pintura Y Revestimientos",
    "sg:phone":"+34 948 25 08 49",
    "sg:postcode":"31011",
    "sg:province":"Navarra",
    "wof:name":"Pinturas Araiz S.l.",
    "wof:placetype":"venue"
},
  "geometry": {"coordinates":[-1.6566669941,42.8141517639],"type":"Point"}
}