{
  "type": "Feature",
  "properties": {
    "iso:country":"ES",
    "sg:address":"Calle de Pintor Luis Alvarez, 18",
    "sg:city":"Cangas Narcea",
    "sg:orig_category":"M\u00c9dicos: Foniatr\u00cda Y Logopedia",
    "sg:phone":"+34 985 81 34 19",
    "sg:postcode":"33800",
    "sg:province":"Asturias",
    "wof:name":"Martinez Marcos Laura",
    "wof:placetype":"venue"
},
  "geometry": {"coordinates":[-6.5505580902,43.1801147461],"type":"Point"}
}