{
  "type": "Feature",
  "properties": {
    "addr:full":"Insua, 10 Caion La Coru\u00f1a 15105",
    "addr:housenumber":"10",
    "addr:postcode":"15105",
    "addr:street":"Insua;La Corun\u0303A",
    "iso:country":"ES",
    "sg:address":"Insua, 10",
    "sg:city":"Caion",
    "sg:orig_category":"Alimentaci\u00d3n General (al Por Menor)",
    "sg:phone":"+34 981 60 40 28",
    "sg:postcode":"15105",
    "sg:province":"La Coru\u00f1a",
    "wof:name":"Prieto Alvarez Cecilia",
    "wof:placetype":"venue"
},
  "geometry": {"coordinates":[-8.607008934,43.3210258484],"type":"Point"}
}