{
  "type": "Feature",
  "properties": {
    "addr:full":"Calle de Doctor Cantero Cuadrado, 1 Huelva Huelva 21004",
    "addr:housenumber":"1",
    "addr:postcode":"21004",
    "addr:street":"Calle De Doctor Cantero Cuadrado",
    "iso:country":"ES",
    "sg:address":"Calle de Doctor Cantero Cuadrado, 1",
    "sg:city":"Huelva",
    "sg:orig_category":"Alimentaci\u00d3n General (al Por Menor)",
    "sg:phone":"+34 959 28 42 47",
    "sg:postcode":"21004",
    "sg:province":"Huelva",
    "sg:website":"www.proartin.com",
    "wof:name":"Proartin S.l.",
    "wof:placetype":"venue"
},
  "geometry": {"coordinates":[-6.9425458908,37.2600097656],"type":"Point"}
}