{
  "type": "Feature",
  "properties": {
    "addr:full":"Calle de Carmen (del), 34 Cartagena Murcia 30201",
    "addr:postcode":"30201",
    "addr:street":"Calle De Carmen Del",
    "iso:country":"ES",
    "sg:address":"Calle de Carmen (del), 34",
    "sg:city":"Cartagena",
    "sg:orig_category":"Farmacias",
    "sg:phone":"+34 968 50 21 36",
    "sg:postcode":"30201",
    "sg:province":"Murcia",
    "wof:name":"Gonzalez Gonzalez Jose Juan",
    "wof:placetype":"venue"
},
  "geometry": {"coordinates":[-0.9906917214,37.6050987244],"type":"Point"}
}