{
  "type": "Feature",
  "properties": {
    "addr:full":"Calle de Pablo Rada, 23 Huelva Huelva 21004",
    "addr:housenumber":"23",
    "addr:postcode":"21004",
    "addr:street":"Calle De Pablo Rada",
    "iso:country":"ES",
    "sg:address":"Calle de Pablo Rada, 23",
    "sg:city":"Huelva",
    "sg:orig_category":"Cajas De Ahorro",
    "sg:phone":"+34 959 54 23 28",
    "sg:postcode":"21004",
    "sg:province":"Huelva",
    "sg:website":"www.unicaja.es",
    "wof:name":"Unicaja",
    "wof:placetype":"venue"
},
  "geometry": {"coordinates":[-6.948756218,37.2592887878],"type":"Point"}
}