{
  "type": "Feature",
  "properties": {
    "addr:full":"Rua Serafin Pazo, 50 Estrada Pontevedra 36680",
    "addr:housenumber":"50",
    "addr:postcode":"36680",
    "addr:street":"Rua Serafin Pazo;Estrada Pontevedra",
    "iso:country":"ES",
    "sg:address":"Rua Serafin Pazo, 50",
    "sg:city":"Estrada",
    "sg:classifiers":[
        {
            "category":"Taxi",
            "type":"Transportation"
        }
    ],
    "sg:phone":"+34 986 57 06 69",
    "sg:postcode":"36680",
    "sg:province":"Pontevedra",
    "wof:name":"Garcia Vidal Jose",
    "wof:placetype":"venue"
},
  "geometry": {"coordinates":[-8.4875974655,42.6858596802],"type":"Point"}
}