{
  "type": "Feature",
  "properties": {
    "addr:full":"Calle de Gravina, 9 Huelva Huelva 21001",
    "addr:housenumber":"9",
    "addr:postcode":"21001",
    "addr:street":"Calle De Gravina",
    "iso:country":"ES",
    "sg:address":"Calle de Gravina, 9",
    "sg:city":"Huelva",
    "sg:orig_category":"Muebles, Minoristas",
    "sg:phone":"+34 959 28 33 62",
    "sg:postcode":"21001",
    "sg:province":"Huelva",
    "wof:name":"Santos Mora Jose Maria",
    "wof:placetype":"venue"
},
  "geometry": {"coordinates":[-6.9554729462,37.2575912476],"type":"Point"}
}