{
  "type": "Feature",
  "properties": {
    "addr:full":"Calle de Sant Jaume, 83 Santa Eulalia Islas Baleares 07840",
    "addr:housenumber":"83",
    "addr:postcode":"07840",
    "addr:street":"Calle De Sant Jaume",
    "iso:country":"ES",
    "sg:address":"Calle de Sant Jaume, 83",
    "sg:city":"Santa Eulalia",
    "sg:orig_category":"Internados & Ense\u00d1anza Privada",
    "sg:phone":"+34 971 33 01 57",
    "sg:postcode":"07840",
    "sg:province":"Islas Baleares",
    "wof:name":"Religiosas Trinitarias",
    "wof:placetype":"venue"
},
  "geometry": {"coordinates":[1.53629601,38.9862518311],"type":"Point"}
}