{
  "type": "Feature",
  "properties": {
    "iso:country":"ES",
    "sg:address":"A Milicroca, 3",
    "sg:city":"Milicroca",
    "sg:orig_category":"Serrer\u00cdas De Madera",
    "sg:phone":"+34 982 55 85 05",
    "sg:postcode":"27776",
    "sg:province":"Lugo",
    "wof:name":"Rodriguez Freire Antonio",
    "wof:placetype":"venue"
},
  "geometry": {"coordinates":[-7.415585041,43.5507011414],"type":"Point"}
}