{
  "type": "Feature",
  "properties": {
    "addr:full":"Calle de Carcel, 1 Coin M\u00e1laga 29100",
    "addr:housenumber":"1",
    "addr:postcode":"29100",
    "addr:street":"Calle De Carcel;Ma\u0301Laga",
    "iso:country":"ES",
    "sg:address":"Calle de Carcel, 1",
    "sg:city":"Coin",
    "sg:orig_category":"Asociaciones Humanitarias, De Cooperaci\u00d3n, De Acci\u00d3n Social",
    "sg:phone":"+34 952 45 04 82",
    "sg:postcode":"29100",
    "sg:province":"M\u00e1laga",
    "wof:name":"Asociacion Espa\u00f1ola Contra El Cancer",
    "wof:placetype":"venue"
},
  "geometry": {"coordinates":[-4.7596530914,36.6600112915],"type":"Point"}
}