{
  "type": "Feature",
  "properties": {
    "addr:full":"Carrer de Segarra, 25 Premia Mar Barcelona 08330",
    "addr:housenumber":"25",
    "addr:postcode":"08330",
    "addr:street":"Carrer De Segarra",
    "iso:country":"ES",
    "sg:address":"Carrer de Segarra, 25",
    "sg:city":"Premia Mar",
    "sg:orig_category":"Molduras, Junquillos, Listones Y Molduras Perforadas",
    "sg:phone":"+34 937 51 18 30",
    "sg:postcode":"08330",
    "sg:province":"Barcelona",
    "wof:name":"Estevez Caracuel Eduardo",
    "wof:placetype":"venue"
},
  "geometry": {"coordinates":[2.3723061085,41.4943656921],"type":"Point"}
}