{
  "type": "Feature",
  "properties": {
    "iso:country":"ES",
    "sg:address":"Calle de Onesimo Redondo, 1",
    "sg:city":"Pedrajas S. Esteban",
    "sg:orig_category":"Cooperativas Agr\u00cdcolas",
    "sg:phone":"+34 983 60 54 16",
    "sg:postcode":"47430",
    "sg:province":"Valladolid",
    "wof:name":"Supermercados La Salve S.l.",
    "wof:placetype":"venue"
},
  "geometry": {"coordinates":[-4.5811591148,41.3406105042],"type":"Point"}
}