{
  "type": "Feature",
  "properties": {
    "iso:country":"ES",
    "sg:address":"Carrer de Oms, 49",
    "sg:city":"Palma",
    "sg:orig_category":"Ropa Para Caballeros (al Por Menor)",
    "sg:phone":"+34 971 71 29 74",
    "sg:postcode":"07003",
    "sg:province":"Islas Baleares",
    "wof:name":"Barrys S. L.",
    "wof:placetype":"venue"
},
  "geometry": {"coordinates":[2.6487369537,39.574886322],"type":"Point"}
}