{
  "type": "Feature",
  "properties": {
    "addr:full":"Calle de Francisco De Quevedo, 15 Santander Cantabria 39001",
    "addr:housenumber":"15",
    "addr:postcode":"39001",
    "addr:street":"Calle De Francisco De Quevedo",
    "iso:country":"ES",
    "sg:address":"Calle de Francisco De Quevedo, 15",
    "sg:city":"Santander",
    "sg:orig_category":"Zapatos (al Por Menor)",
    "sg:phone":"+34 942 21 92 66",
    "sg:postcode":"39001",
    "sg:province":"Cantabria",
    "wof:name":"Zap-in Shoes Company S.l.",
    "wof:placetype":"venue"
},
  "geometry": {"coordinates":[-3.8087100983,43.4635887146],"type":"Point"}
}