{
  "type": "Feature",
  "properties": {
    "iso:country":"ES",
    "sg:address":"Avda Costa Blanca, 22",
    "sg:city":"Alacant",
    "sg:orig_category":"Delegados, Agentes De Tr\u00c1nsito, Auxiliares De Transporte Internacional",
    "sg:phone":"+34 965 26 13 93",
    "sg:postcode":"03540",
    "sg:province":"Alicante",
    "wof:name":"Auto Escuela Maisonabe S.l",
    "wof:placetype":"venue"
},
  "geometry": {"coordinates":[-0.430660814,38.3577804565],"type":"Point"}
}