{
  "type": "Feature",
  "properties": {
    "addr:full":"Calle de Santiago De La Fuente, 22 Bargas Toledo 45593",
    "addr:housenumber":"22",
    "addr:postcode":"45593",
    "addr:street":"Calle De Santiago;La Fuente",
    "iso:country":"ES",
    "sg:address":"Calle de Santiago De La Fuente, 22",
    "sg:city":"Bargas",
    "sg:orig_category":"Estancos",
    "sg:phone":"+34 925 35 70 50",
    "sg:postcode":"45593",
    "sg:province":"Toledo",
    "wof:name":"Gutierrez Franco Lorena",
    "wof:placetype":"venue"
},
  "geometry": {"coordinates":[-4.0203080177,39.9396057129],"type":"Point"}
}