{
  "type": "Feature",
  "properties": {
    "addr:full":"Calle de Pintor Sorolla, 31 Banyeres Mariola Alicante 03450",
    "addr:housenumber":"31",
    "addr:postcode":"03450",
    "addr:street":"Calle De Pintor Sorolla",
    "iso:country":"ES",
    "sg:address":"Calle de Pintor Sorolla, 31",
    "sg:city":"Banyeres Mariola",
    "sg:orig_category":"Institutos De Belleza",
    "sg:phone":"+34 966 56 75 12",
    "sg:postcode":"03450",
    "sg:province":"Alicante",
    "wof:name":"Bodi Frances Maria Evora",
    "wof:placetype":"venue"
},
  "geometry": {"coordinates":[-0.6580740213,38.7120857239],"type":"Point"}
}