{
  "type": "Feature",
  "properties": {
    "iso:country":"ES",
    "sg:address":"Avda Infanta, 22",
    "sg:city":"Aldeatejada",
    "sg:orig_category":"Reposter\u00cdas",
    "sg:phone":"+34 923 34 11 39",
    "sg:postcode":"37187",
    "sg:province":"Salamanca",
    "wof:name":"Sillero Oliva Antonio",
    "wof:placetype":"venue"
},
  "geometry": {"coordinates":[-5.6912260056,40.9244041443],"type":"Point"}
}