{
  "type": "Feature",
  "properties": {
    "addr:full":"Carrer de Banys, 132 Garriga Barcelona 08530",
    "addr:housenumber":"132",
    "addr:postcode":"08530",
    "addr:street":"Carrer De Banys",
    "iso:country":"ES",
    "sg:address":"Carrer de Banys, 132",
    "sg:city":"Garriga",
    "sg:orig_category":"Librer\u00cdas",
    "sg:phone":"+34 938 71 91 10",
    "sg:postcode":"08530",
    "sg:province":"Barcelona",
    "wof:name":"Diaz Martinez Maria Jose",
    "wof:placetype":"venue"
},
  "geometry": {"coordinates":[2.2864871025,41.6793937683],"type":"Point"}
}