{
  "type": "Feature",
  "properties": {
    "addr:full":"Trva. Trece De Septiembre, 24 Porto Son La Coru\u00f1a 15970",
    "addr:postcode":"15970",
    "addr:street":"Trece;Septiembre 24 Porto Son La Corun\u0303A",
    "iso:country":"ES",
    "sg:address":"Trva. Trece De Septiembre, 24",
    "sg:city":"Porto Son",
    "sg:orig_category":"Alquiler De Veh\u00cdculos: Turismos Y Utilitarios",
    "sg:phone":"+34 981 85 31 38",
    "sg:postcode":"15970",
    "sg:province":"La Coru\u00f1a",
    "wof:name":"Fernandez Perez Antonio",
    "wof:placetype":"venue"
},
  "geometry": {"coordinates":[-9.0049142838,42.7234649658],"type":"Point"}
}