{
  "type": "Feature",
  "properties": {
    "iso:country":"ES",
    "sg:address":"Calle de Azafranal, 51",
    "sg:city":"Salamanca",
    "sg:orig_category":"Bazares, Art\u00cdculos De Limpieza Y De Cocina (al Por Menor)",
    "sg:phone":"+34 923 26 54 65",
    "sg:postcode":"37001",
    "sg:province":"Salamanca",
    "wof:name":"Los Cacharros De Pedro Y Teresa S.l.",
    "wof:placetype":"venue"
},
  "geometry": {"coordinates":[-5.6593203545,40.967880249],"type":"Point"}
}