{
  "type": "Feature",
  "properties": {
    "addr:full":"Calle de Obispo Cobos, 8 Ubeda Ja\u00e9n 23400",
    "addr:housenumber":"8",
    "addr:postcode":"23400",
    "addr:street":"Calle De Obispo Cobos;Jae\u0301N",
    "iso:country":"ES",
    "sg:address":"Calle de Obispo Cobos, 8",
    "sg:city":"Ubeda",
    "sg:orig_category":"Cl\u00cdnicas Dentales",
    "sg:phone":"+34 953 75 04 87",
    "sg:postcode":"23400",
    "sg:province":"Ja\u00e9n",
    "wof:name":"Molina Navarrete Miguel",
    "wof:placetype":"venue"
},
  "geometry": {"coordinates":[-3.3768260479,38.0116729736],"type":"Point"}
}