{
  "type": "Feature",
  "properties": {
    "addr:full":"Calle de Pe\u00d1uelas, 60 Madrid Madrid 28005",
    "addr:housenumber":"60",
    "addr:postcode":"madrid;28005",
    "addr:street":"Calle De Pen\u0303Uelas",
    "iso:country":"ES",
    "sg:address":"Calle de Pe\u00d1uelas, 60",
    "sg:city":"Madrid",
    "sg:orig_category":"Centros De Coordinaci\u00d3n",
    "sg:phone":"+34 914 73 46 53",
    "sg:postcode":"28005",
    "sg:province":"Madrid",
    "wof:name":"Navalon Tomas Miguel",
    "wof:placetype":"venue"
},
  "geometry": {"coordinates":[-3.7013370991,40.3991355896],"type":"Point"}
}