{
  "type": "Feature",
  "properties": {
    "addr:full":"C\u00f1o Pinicho-vilamean, 2 Nigran Pontevedra 36350",
    "addr:housenumber":"2",
    "addr:postcode":"36350",
    "addr:street":"Pinicho-Vilamean",
    "iso:country":"ES",
    "sg:address":"C\u00f1o Pinicho-vilamean, 2",
    "sg:city":"Nigran",
    "sg:orig_category":"Abogados",
    "sg:phone":"+34 986 38 00 10",
    "sg:postcode":"36350",
    "sg:province":"Pontevedra",
    "wof:name":"Estevez Dieguez Miguel Angel",
    "wof:placetype":"venue"
},
  "geometry": {"coordinates":[-8.8062238693,42.141494751],"type":"Point"}
}