{
  "type": "Feature",
  "properties": {
    "iso:country":"ES",
    "sg:address":"Via Augusta, 39",
    "sg:city":"Hospitalet Infant",
    "sg:orig_category":"Cl\u00cdnicas Dentales",
    "sg:phone":"+34 977 82 20 28",
    "sg:postcode":"43890",
    "sg:province":"Tarragona",
    "wof:name":"Anadon Sole Arturo",
    "wof:placetype":"venue"
},
  "geometry": {"coordinates":[0.9222111106,40.9910926819],"type":"Point"}
}