{
  "type": "Feature",
  "properties": {
    "addr:full":"Juaida Alta, S/n Ca\u00f1ada San Urbano Almer\u00eda 04120",
    "addr:housenumber":"s / n",
    "addr:postcode":"04120",
    "addr:street":"Almeri\u0301A",
    "iso:country":"ES",
    "sg:address":"Juaida Alta, S/n",
    "sg:city":"Ca\u00f1ada San Urbano",
    "sg:classifiers":[
        {
            "category":"Taxi",
            "type":"Transportation"
        }
    ],
    "sg:phone":"+34 950 29 00 03",
    "sg:postcode":"04120",
    "sg:province":"Almer\u00eda",
    "wof:name":"Asociacion Profesional De Unitaxi",
    "wof:placetype":"venue"
},
  "geometry": {"coordinates":[-2.4679217339,36.8401641846],"type":"Point"}
}