{
  "type": "Feature",
  "properties": {
    "addr:full":"C/ Major (m.), 14 Manacor Islas Baleares 07500",
    "addr:housenumber":"14",
    "addr:postcode":"07500",
    "addr:street":"C / Major M.",
    "iso:country":"ES",
    "sg:address":"C/ Major (m.), 14",
    "sg:city":"Manacor",
    "sg:orig_category":"Ropa Para Se\u00d1oras (al Por Menor)",
    "sg:phone":"+34 971 55 45 86",
    "sg:postcode":"07500",
    "sg:province":"Islas Baleares",
    "wof:name":"Mel I Sucre 2 C.b",
    "wof:placetype":"venue"
},
  "geometry": {"coordinates":[3.209072113,39.5694007874],"type":"Point"}
}