{
  "type": "Feature",
  "properties": {
    "iso:country":"ES",
    "sg:address":"Av Mare Deu De Montserrat, 33",
    "sg:city":"Barcelona",
    "sg:orig_category":"Ropa Para Se\u00d1oras (al Por Menor)",
    "sg:phone":"+34 932 84 49 66",
    "sg:postcode":"08024",
    "sg:province":"Barcelona",
    "wof:name":"Gestors De Telecomunicacions Del Maresme",
    "wof:placetype":"venue"
},
  "geometry": {"coordinates":[2.1624920368,41.4143028259],"type":"Point"}
}