{
  "type": "Feature",
  "properties": {
    "addr:full":"Calle de Padre Ignacio Ellacuria, 10 Laredo Cantabria 39770",
    "addr:housenumber":"10",
    "addr:postcode":"39770",
    "addr:street":"Calle De Padre Ignacio Ellacuria",
    "iso:country":"ES",
    "sg:address":"Calle de Padre Ignacio Ellacuria, 10",
    "sg:city":"Laredo",
    "sg:orig_category":"Agencias De Viajes",
    "sg:phone":"+34 942 60 81 65",
    "sg:postcode":"39770",
    "sg:province":"Cantabria",
    "sg:website":"www.viajeseroski.es",
    "wof:name":"Viajes Eroski S.a.",
    "wof:placetype":"venue"
},
  "geometry": {"coordinates":[-3.4164481163,43.410320282],"type":"Point"}
}