{
  "type": "Feature",
  "properties": {
    "addr:full":"Calle de Pilar (el), 20 Santa Cruz De Tenerife Santa Cruz De Tenerife 38002",
    "addr:housenumber":"20",
    "addr:postcode":"38002",
    "addr:street":"Calle De Pilar El",
    "iso:country":"ES",
    "sg:address":"Calle de Pilar (el), 20",
    "sg:city":"Santa Cruz De Tenerife",
    "sg:orig_category":"Abogados",
    "sg:phone":"+34 922 28 67 63",
    "sg:postcode":"38002",
    "sg:province":"Santa Cruz De Tenerife",
    "wof:name":"Diaz-llanos La Roche Miguel",
    "wof:placetype":"venue"
},
  "geometry": {"coordinates":[-16.2519226074,28.4692516327],"type":"Point"}
}