{
  "type": "Feature",
  "properties": {
    "addr:full":"Villatresmil, S/n Villatresmil Asturias 33879",
    "addr:postcode":"33879",
    "addr:street":"Villatresmil S / N Villatresmil Asturias",
    "iso:country":"ES",
    "sg:address":"Villatresmil, S/n",
    "sg:city":"Villatresmil",
    "sg:orig_category":"Serrer\u00cdas De Madera",
    "sg:phone":"+34 985 80 31 00",
    "sg:postcode":"33879",
    "sg:province":"Asturias",
    "wof:name":"Maderas Americano-villatresmil S.l.",
    "wof:placetype":"venue"
},
  "geometry": {"coordinates":[-6.4714770317,43.386844635],"type":"Point"}
}