{
  "type": "Feature",
  "properties": {
    "addr:full":"Avda Marina (de La), S/n S. Fernando C\u00e1diz 11100",
    "addr:postcode":"11100",
    "addr:street":"Avda Marina De La S / N S. Fernando Ca\u0301Diz",
    "iso:country":"ES",
    "sg:address":"Avda Marina (de La), S/n",
    "sg:city":"S. Fernando",
    "sg:orig_category":"Cajas De Ahorro",
    "sg:phone":"+34 956 59 27 74",
    "sg:postcode":"11100",
    "sg:province":"C\u00e1diz",
    "sg:website":"www.cajasanfernando.es",
    "wof:name":"Caja San Fernando De Sevilla Y Jerez",
    "wof:placetype":"venue"
},
  "geometry": {"coordinates":[-6.2026791573,36.4562759399],"type":"Point"}
}