{
  "type": "Feature",
  "properties": {
    "addr:full":"Plaz Constitucion (la), 1 Laredo Cantabria 39770",
    "addr:housenumber":"1",
    "addr:postcode":"39770",
    "addr:street":"Constitucion La",
    "iso:country":"ES",
    "sg:address":"Plaz Constitucion (la), 1",
    "sg:city":"Laredo",
    "sg:orig_category":"Administraciones Regionales, Departamentales Y Locales",
    "sg:phone":"+34 942 60 51 00",
    "sg:postcode":"39770",
    "sg:province":"Cantabria",
    "sg:website":"www.ayuntamientolaredo.com",
    "wof:name":"Ayuntamiento De Laredo",
    "wof:placetype":"venue"
},
  "geometry": {"coordinates":[-3.4127290249,43.411075592],"type":"Point"}
}