{
  "type": "Feature",
  "properties": {
    "addr:full":"Carr Guifre, 146 Badalona Barcelona 08912",
    "addr:housenumber":"146",
    "addr:postcode":"08912",
    "addr:street":"Carr Guifre",
    "iso:country":"ES",
    "sg:address":"Carr Guifre, 146",
    "sg:city":"Badalona",
    "sg:orig_category":"Chapa Y Pintura Veh\u00cdculos",
    "sg:phone":"+34 933 99 04 07",
    "sg:postcode":"08912",
    "sg:province":"Barcelona",
    "wof:name":"J.ribera Universo S.l.",
    "wof:placetype":"venue"
},
  "geometry": {"coordinates":[2.2430050373,41.4451332092],"type":"Point"}
}