{
  "type": "Feature",
  "properties": {
    "addr:full":"Pase Florida, S/n Madrid Madrid 28008",
    "addr:housenumber":"s / n",
    "addr:postcode":"28008",
    "iso:country":"ES",
    "sg:address":"Pase Florida, S/n",
    "sg:city":"Madrid",
    "sg:orig_category":"Retoques De Vestidos",
    "sg:phone":"+34 915 47 01 70",
    "sg:postcode":"28008",
    "sg:province":"Madrid",
    "sg:website":"www.retoucherie.com",
    "wof:name":"La Retoucherie De Manuela S.l.",
    "wof:placetype":"venue"
},
  "geometry": {"coordinates":[-3.7212738991,40.4230766296],"type":"Point"}
}