{
  "type": "Feature",
  "properties": {
    "iso:country":"ES",
    "sg:address":"Partida El Poce, S/n",
    "sg:city":"Valdealgorfa",
    "sg:orig_category":"Cr\u00cda De Cerdos",
    "sg:phone":"+34 978 76 90 37",
    "sg:postcode":"44594",
    "sg:province":"Teruel",
    "wof:name":"Sociedad Agraria De Transformacion El Pocet Numero 1238",
    "wof:placetype":"venue"
},
  "geometry": {"coordinates":[-0.0346239991,40.9885292053],"type":"Point"}
}