{
  "type": "Feature",
  "properties": {
    "iso:country":"ES",
    "sg:address":"Calle de Isidoro Macabich, 31",
    "sg:city":"Santa Eulalia",
    "sg:orig_category":"Deportes N\u00c1uticos, Acu\u00c1ticos Y Subacu\u00c1ticos: Art\u00cdculos Y Equipo (al Por Menor)",
    "sg:phone":"+34 971 33 20 67",
    "sg:postcode":"07840",
    "sg:province":"Islas Baleares",
    "wof:name":"Juan Escandell Antoni Vicent",
    "wof:placetype":"venue"
},
  "geometry": {"coordinates":[1.535877943,38.9851379395],"type":"Point"}
}