{
  "type": "Feature",
  "properties": {
    "addr:full":"Avda Miranda, 3 San Vicente De Barakaldo Vizcaya 48902",
    "addr:housenumber":"3",
    "addr:postcode":"48902",
    "addr:street":"Avda Miranda",
    "iso:country":"ES",
    "sg:address":"Avda Miranda, 3",
    "sg:city":"San Vicente De Barakaldo",
    "sg:orig_category":"Inform\u00c1tica (estudios, Servicios, Asesor\u00cda, Formaci\u00d3n)",
    "sg:phone":"+34 944 78 03 88",
    "sg:postcode":"48902",
    "sg:province":"Vizcaya",
    "sg:website":"www.meatze.es",
    "wof:name":"Centro De Informatica Y Gestion Meatze S.l.",
    "wof:placetype":"venue"
},
  "geometry": {"coordinates":[-2.9934709072,43.2985916138],"type":"Point"}
}