{
  "type": "Feature",
  "properties": {
    "addr:full":"Avda Constitucion, 173 Torrejon Ardoz Madrid 28850",
    "addr:housenumber":"173",
    "addr:postcode":"28850",
    "addr:street":"Avda Constitucion",
    "iso:country":"ES",
    "sg:address":"Avda Constitucion, 173",
    "sg:city":"Torrejon Ardoz",
    "sg:orig_category":"Organizaci\u00d3n De Actos, Seminarios Y Congresos",
    "sg:phone":"+34 916 77 65 53",
    "sg:postcode":"28850",
    "sg:province":"Madrid",
    "sg:website":"www.hostaltorrejon.com",
    "wof:name":"Hostal Torrejon S.l.",
    "wof:placetype":"venue"
},
  "geometry": {"coordinates":[-3.4634950161,40.4594154358],"type":"Point"}
}