{
  "type": "Feature",
  "properties": {
    "addr:full":"Carrer de Mig, 6 Castalla Alicante 03420",
    "addr:housenumber":"6",
    "addr:postcode":"03420",
    "addr:street":"Carrer De Mig",
    "iso:country":"ES",
    "sg:address":"Carrer de Mig, 6",
    "sg:city":"Castalla",
    "sg:orig_category":"Agencias Y Asesores De Publicidad",
    "sg:phone":"+34 965 56 09 28",
    "sg:postcode":"03420",
    "sg:province":"Alicante",
    "wof:name":"Bernabeu Perez Javier",
    "wof:placetype":"venue"
},
  "geometry": {"coordinates":[-0.6726559997,38.5944633484],"type":"Point"}
}