{
  "type": "Feature",
  "properties": {
    "iso:country":"ES",
    "sg:address":"Calle de Luz (de La), 2",
    "sg:city":"Santomera",
    "sg:orig_category":"Alimentaci\u00d3n General (al Por Menor)",
    "sg:phone":"+34 968 86 02 12",
    "sg:postcode":"30140",
    "sg:province":"Murcia",
    "wof:name":"Mayor Y Mayor S.c.",
    "wof:placetype":"venue"
},
  "geometry": {"coordinates":[-1.0509480238,38.0602416992],"type":"Point"}
}