{
  "type": "Feature",
  "properties": {
    "iso:country":"ES",
    "sg:address":"Carrer de Font Vella, 15",
    "sg:city":"Terrassa",
    "sg:orig_category":"Institutos De Belleza",
    "sg:phone":"+34 937 33 71 11",
    "sg:postcode":"08221",
    "sg:province":"Barcelona",
    "wof:name":"Estetibel S.l.",
    "wof:placetype":"venue"
},
  "geometry": {"coordinates":[2.0117630959,41.562625885],"type":"Point"}
}