{
  "type": "Feature",
  "properties": {
    "iso:country":"ES",
    "sg:address":"Calle de Bueso Pineda, 29",
    "sg:city":"Madrid",
    "sg:orig_category":"Cine (producci\u00d3n, Realizaci\u00d3n)",
    "sg:phone":"+34 917 44 02 14",
    "sg:postcode":"28043",
    "sg:province":"Madrid",
    "wof:name":"Fernando Trueba Producciones Cinematogramicas S.a.",
    "wof:placetype":"venue"
},
  "geometry": {"coordinates":[-3.6554510593,40.4540214539],"type":"Point"}
}