{
  "type": "Feature",
  "properties": {
    "addr:full":"Ctra Murcia-alicante, Km. 0049,5 Crevillent Alicante 03330",
    "addr:postcode":"03330",
    "addr:street":"Ctra Murcia-Alicante Km. 0049,5",
    "iso:country":"ES",
    "sg:address":"Ctra Murcia-alicante, Km. 0049,5",
    "sg:city":"Crevillent",
    "sg:orig_category":"Productos Qu\u00cdmicos (fabricaci\u00d3n, Al Por Mayor)",
    "sg:phone":"+34 966 68 03 41",
    "sg:postcode":"03330",
    "sg:province":"Alicante",
    "wof:name":"Quimicas Rodriguez S.l.",
    "wof:placetype":"venue"
},
  "geometry": {"coordinates":[-0.8139619827,38.2384681702],"type":"Point"}
}