{
  "type": "Feature",
  "properties": {
    "addr:full":"Calle de Nardo (del), 49 Alcobendas Madrid 28109",
    "addr:postcode":"28109",
    "addr:street":"Calle De Nardo Del;Alcobendas",
    "iso:country":"ES",
    "sg:address":"Calle de Nardo (del), 49",
    "sg:city":"Alcobendas",
    "sg:orig_category":"Promotores Constructores",
    "sg:phone":"+34 916 50 65 48",
    "sg:postcode":"28109",
    "sg:province":"Madrid",
    "wof:name":"Comunidad De Propietarios Corro De Santiago",
    "wof:placetype":"venue"
},
  "geometry": {"coordinates":[-3.637609005,40.5278511047],"type":"Point"}
}