{
  "type": "Feature",
  "properties": {
    "addr:full":"Calle de Txapillo, 1 Donostia-san Sebastian Guip\u00f9zcoa 20009",
    "addr:housenumber":"1",
    "addr:postcode":"20009",
    "addr:street":"Calle De Txapillo",
    "iso:country":"ES",
    "sg:address":"Calle de Txapillo, 1",
    "sg:city":"Donostia-san Sebastian",
    "sg:orig_category":"Molduras, Junquillos, Listones Y Molduras Perforadas",
    "sg:phone":"+34 943 31 66 47",
    "sg:postcode":"20009",
    "sg:province":"Guip\u00f9zcoa",
    "wof:name":"Aramburu Loitegi Amaia",
    "wof:placetype":"venue"
},
  "geometry": {"coordinates":[-1.9851355553,43.3005409241],"type":"Point"}
}