{
  "type": "Feature",
  "properties": {
    "addr:full":"Avda Constitucion, 7 Jerica Castell\u00f3n 12450",
    "addr:housenumber":"7",
    "addr:postcode":"12450",
    "addr:street":"Avda Constitucion;Castello\u0301N",
    "iso:country":"ES",
    "sg:address":"Avda Constitucion, 7",
    "sg:city":"Jerica",
    "sg:orig_category":"Cajas Para Embalar",
    "sg:phone":"+34 964 12 95 56",
    "sg:postcode":"12450",
    "sg:province":"Castell\u00f3n",
    "sg:website":"www.ruralcaja.es",
    "wof:name":"Caja Rural Del Mediterraneo Ruralcaja S Coop De Credito",
    "wof:placetype":"venue"
},
  "geometry": {"coordinates":[-0.5721560121,39.9130249023],"type":"Point"}
}