{
  "type": "Feature",
  "properties": {
    "iso:country":"ES",
    "sg:address":"Avda Blasco Iba\u00d1ez, 125",
    "sg:city":"Valencia",
    "sg:orig_category":"Fabricaci\u00d3n De Productos L\u00c1cteos Y Derivados",
    "sg:phone":"+34 963 71 71 13",
    "sg:postcode":"46022",
    "sg:province":"Valencia",
    "wof:name":"Leche Celta S.l.",
    "wof:placetype":"venue"
},
  "geometry": {"coordinates":[-0.3433780074,39.4731025696],"type":"Point"}
}