{
  "type": "Feature",
  "properties": {
    "addr:full":"Calle de Saavedra, 18 Gijon Asturias 33208",
    "addr:housenumber":"18",
    "addr:postcode":"33208",
    "addr:street":"Calle De Saavedra",
    "iso:country":"ES",
    "sg:address":"Calle de Saavedra, 18",
    "sg:city":"Gijon",
    "sg:orig_category":"Lubrificantes (fabricaci\u00d3n, Al Por Mayor)",
    "sg:phone":"+34 985 38 64 99",
    "sg:postcode":"33208",
    "sg:province":"Asturias",
    "sg:website":"www.proquimetal.es",
    "wof:name":"Espa\u00f1ola De Productos Quimicos Industriales S.a.",
    "wof:placetype":"venue"
},
  "geometry": {"coordinates":[-5.6640877724,43.5347366333],"type":"Point"}
}