{
  "type": "Feature",
  "properties": {
    "iso:country":"ES",
    "sg:address":"Calle de Mar Oceana, 7",
    "sg:city":"Rozas De Madrid",
    "sg:orig_category":"Cristaler\u00cdas",
    "sg:phone":"+34 916 36 00 14",
    "sg:postcode":"28230",
    "sg:province":"Madrid",
    "wof:name":"Cristalerias Carma S.l.",
    "wof:placetype":"venue"
},
  "geometry": {"coordinates":[-3.871213913,40.4929656982],"type":"Point"}
}