{
  "type": "Feature",
  "properties": {
    "iso:country":"ES",
    "sg:address":"Ctra Extremadura (zona Ind Santiponce), Km. 0472,0",
    "sg:city":"Santiponce",
    "sg:orig_category":"Seguridad En El Trabajo Y Prevenci\u00d3n De Riesgos Laborales",
    "sg:phone":"+34 955 99 63 84",
    "sg:postcode":"41970",
    "sg:province":"Sevilla",
    "wof:name":"Segurand De Mantenimiento S.l.",
    "wof:placetype":"venue"
},
  "geometry": {"coordinates":[-6.0385842323,37.434841156],"type":"Point"}
}