{
  "type": "Feature",
  "properties": {
    "iso:country":"ES",
    "sg:address":"Calle de Felipe Del Castillo, 18",
    "sg:city":"Tegueste Casco",
    "sg:orig_category":"Fisioterapia",
    "sg:phone":"+34 922 15 02 12",
    "sg:postcode":"38280",
    "sg:province":"Santa Cruz De Tenerife",
    "wof:name":"Batista Hernandez Maximo",
    "wof:placetype":"venue"
},
  "geometry": {"coordinates":[-16.3384284973,28.5251293182],"type":"Point"}
}