{
  "type": "Feature",
  "properties": {
    "addr:full":"Calle de Plus Ultra, 2 Estepona M\u00e1laga 29680",
    "addr:housenumber":"2",
    "addr:postcode":"29680",
    "addr:street":"Calle De Plus Ultra",
    "iso:country":"ES",
    "sg:address":"Calle de Plus Ultra, 2",
    "sg:city":"Estepona",
    "sg:orig_category":"Alquiler De Veh\u00cdculos: Turismos Y Utilitarios",
    "sg:phone":"+34 952 80 58 05",
    "sg:postcode":"29680",
    "sg:province":"M\u00e1laga",
    "wof:name":"Fernandez Guerrero Miguel",
    "wof:placetype":"venue"
},
  "geometry": {"coordinates":[-5.1499428749,36.4210777283],"type":"Point"}
}