{
  "type": "Feature",
  "properties": {
    "addr:full":"Carrer de Santander, 75 Barcelona Barcelona 08020",
    "addr:housenumber":"75",
    "addr:postcode":"08020",
    "addr:street":"Carrer De Santander",
    "iso:country":"ES",
    "sg:address":"Carrer de Santander, 75",
    "sg:city":"Barcelona",
    "sg:orig_category":"Servicio De Salud",
    "sg:phone":"+34 932 78 05 16",
    "sg:postcode":"08020",
    "sg:province":"Barcelona",
    "wof:name":"Tuysa S.a.",
    "wof:placetype":"venue"
},
  "geometry": {"coordinates":[2.2045519352,41.4307594299],"type":"Point"}
}