{
  "type": "Feature",
  "properties": {
    "iso:country":"ES",
    "sg:address":"Calle de Echegaray, 52",
    "sg:city":"Palmas De Gran Canaria",
    "sg:orig_category":"Internados & Ense\u00d1anza Privada",
    "sg:phone":"+34 928 25 28 87",
    "sg:postcode":"35011",
    "sg:province":"Las Palmas",
    "wof:name":"Cardenes Armas Encarnacion",
    "wof:placetype":"venue"
},
  "geometry": {"coordinates":[-15.4329633713,28.1159133911],"type":"Point"}
}