{
  "type": "Feature",
  "properties": {
    "addr:full":"Benjamin De Tudela, 34 Iru\u00f1a Navarra 31008",
    "addr:housenumber":"34",
    "addr:postcode":"31008",
    "iso:country":"ES",
    "sg:address":"Benjamin De Tudela, 34",
    "sg:city":"Iru\u00f1a",
    "sg:orig_category":"Supermercados Y Hipermercados",
    "sg:phone":"+34 948 17 08 99",
    "sg:postcode":"31008",
    "sg:province":"Navarra",
    "wof:name":"Caprabo S.a.",
    "wof:placetype":"venue"
},
  "geometry": {"coordinates":[-1.6743860245,42.8097915649],"type":"Point"}
}