{
  "type": "Feature",
  "properties": {
    "iso:country":"ES",
    "sg:address":"Calle de Ancha, 38",
    "sg:city":"Motril",
    "sg:orig_category":"Electricidad: Instaladores",
    "sg:phone":"+34 958 60 27 24",
    "sg:postcode":"18600",
    "sg:province":"Granada",
    "wof:name":"Electricidad Malpa Cb",
    "wof:placetype":"venue"
},
  "geometry": {"coordinates":[-3.5139565468,36.7520713806],"type":"Point"}
}