{
  "type": "Feature",
  "properties": {
    "iso:country":"ES",
    "sg:address":"Calle de Malaga, 1",
    "sg:city":"Valencia",
    "sg:orig_category":"Laboratorios Farmac\u00c9uticos",
    "sg:phone":"+34 963 47 84 58",
    "sg:postcode":"46009",
    "sg:province":"Valencia",
    "wof:name":"Laboratorios Normon S.a.",
    "wof:placetype":"venue"
},
  "geometry": {"coordinates":[-0.3788209856,39.4847831726],"type":"Point"}
}