{
  "type": "Feature",
  "properties": {
    "iso:country":"ES",
    "sg:address":"Calle de Estalajes, 89",
    "sg:city":"Azuaga",
    "sg:orig_category":"Institutos De Belleza",
    "sg:phone":"+34 924 89 01 89",
    "sg:postcode":"06920",
    "sg:province":"Badajoz",
    "wof:name":"Gomez Bustamante Josefa",
    "wof:placetype":"venue"
},
  "geometry": {"coordinates":[-5.680021286,38.2601547241],"type":"Point"}
}