{
  "type": "Feature",
  "properties": {
    "iso:country":"ES",
    "sg:address":"Calle de Olvera, 2",
    "sg:city":"Ubeda",
    "sg:orig_category":"M\u00c9dicos: Otorrinolaringolog\u00cda",
    "sg:phone":"+34 953 75 25 40",
    "sg:postcode":"23400",
    "sg:province":"Ja\u00e9n",
    "wof:name":"Martin Rodriguez Luis Carlos",
    "wof:placetype":"venue"
},
  "geometry": {"coordinates":[-3.3789579868,38.0182113647],"type":"Point"}
}