{
  "type": "Feature",
  "properties": {
    "addr:full":"Altzo-muino, 160 Altzo Guip\u00f9zcoa 20268",
    "addr:housenumber":"160",
    "addr:postcode":"20268",
    "addr:street":"Altzo-Muino;Guipu\u0300Zcoa",
    "iso:country":"ES",
    "sg:address":"Altzo-muino, 160",
    "sg:city":"Altzo",
    "sg:orig_category":"Centros De Educaci\u00d3n Especial",
    "sg:phone":"+34 943 65 57 32",
    "sg:postcode":"20268",
    "sg:province":"Guip\u00f9zcoa",
    "wof:name":"Gobierno Vasco-eusko Jaurlaritza",
    "wof:placetype":"venue"
},
  "geometry": {"coordinates":[-2.0837790966,43.0991401672],"type":"Point"}
}