{
  "type": "Feature",
  "properties": {
    "addr:full":"Calle de Carretera De Fontanar, 6 Guadalajara Guadalajara 19004",
    "addr:postcode":"19004",
    "addr:street":"Calle De Carretera De Fontanar 6",
    "iso:country":"ES",
    "sg:address":"Calle de Carretera De Fontanar, 6",
    "sg:city":"Guadalajara",
    "sg:orig_category":"Cr\u00cda De Animales",
    "sg:phone":"+34 949 22 19 51",
    "sg:postcode":"19004",
    "sg:province":"Guadalajara",
    "wof:name":"Zafonic S.a.",
    "wof:placetype":"venue"
},
  "geometry": {"coordinates":[-3.1641490459,40.6297950745],"type":"Point"}
}