{
  "type": "Feature",
  "properties": {
    "iso:country":"ES",
    "sg:address":"Calle de San Anton, 13",
    "sg:city":"Logro\u00f1o",
    "sg:orig_category":"Abogados",
    "sg:phone":"+34 941 24 64 11",
    "sg:postcode":"26002",
    "sg:province":"La Rioja",
    "wof:name":"Angulo Fontecha Luis Antonio",
    "wof:placetype":"venue"
},
  "geometry": {"coordinates":[-2.4466016293,42.4618453979],"type":"Point"}
}