{
  "type": "Feature",
  "properties": {
    "addr:full":"Barr Mendieta, 17 Mendieta Vizcaya 48330",
    "addr:housenumber":"17",
    "addr:postcode":"48330",
    "addr:street":"Mendieta",
    "iso:country":"ES",
    "sg:address":"Barr Mendieta, 17",
    "sg:city":"Mendieta",
    "sg:orig_category":"Material Y Herramientas Agr\u00cdcolas",
    "sg:phone":"+34 946 31 32 46",
    "sg:postcode":"48330",
    "sg:province":"Vizcaya",
    "wof:name":"Garcia Olaechea Jesus",
    "wof:placetype":"venue"
},
  "geometry": {"coordinates":[-2.6621451378,43.3101615906],"type":"Point"}
}