{
  "type": "Feature",
  "properties": {
    "iso:country":"ES",
    "sg:address":"Calle de Cami Reial, 110",
    "sg:city":"Torrent",
    "sg:orig_category":"Institutos De Belleza",
    "sg:phone":"+34 961 55 29 03",
    "sg:postcode":"46900",
    "sg:province":"Valencia",
    "wof:name":"Belle Mayte S.l.",
    "wof:placetype":"venue"
},
  "geometry": {"coordinates":[-0.4623290002,39.441619873],"type":"Point"}
}