{
  "type": "Feature",
  "properties": {
    "addr:full":"Calle de Teresa Gil, 12 Valladolid Valladolid 47002",
    "addr:housenumber":"12",
    "addr:postcode":"47002",
    "addr:street":"Calle De Teresa Gil",
    "iso:country":"ES",
    "sg:address":"Calle de Teresa Gil, 12",
    "sg:city":"Valladolid",
    "sg:orig_category":"Librer\u00cdas",
    "sg:phone":"+34 983 21 35 60",
    "sg:postcode":"47002",
    "sg:province":"Valladolid",
    "wof:name":"Librerias Oletum S.l.",
    "wof:placetype":"venue"
},
  "geometry": {"coordinates":[-4.726129055,41.6512565613],"type":"Point"}
}