{
  "type": "Feature",
  "properties": {
    "iso:country":"ES",
    "sg:address":"Av Sofia, 8",
    "sg:city":"Sitges",
    "sg:orig_category":"Cajas De Ahorro",
    "sg:phone":"+34 938 11 31 70",
    "sg:postcode":"08870",
    "sg:province":"Barcelona",
    "sg:website":"www.lacaixa.es",
    "wof:name":"Caixa D'estalvis I Pensions De Barcelona",
    "wof:placetype":"venue"
},
  "geometry": {"coordinates":[1.8039940596,41.2344398499],"type":"Point"}
}