{
  "type": "Feature",
  "properties": {
    "addr:full":"Calle de Carteya, 10 Linea De La Concepcion C\u00e1diz 11300",
    "addr:housenumber":"10",
    "addr:postcode":"11300",
    "addr:street":"Calle De Carteya;Ca\u0301Diz",
    "iso:country":"ES",
    "sg:address":"Calle de Carteya, 10",
    "sg:city":"Linea De La Concepcion",
    "sg:orig_category":"Albergues",
    "sg:phone":"+34 956 17 66 68",
    "sg:postcode":"11300",
    "sg:province":"C\u00e1diz",
    "wof:name":"Lopez Lopez Antonio",
    "wof:placetype":"venue"
},
  "geometry": {"coordinates":[-5.3509259224,36.1632766724],"type":"Point"}
}