{
  "type": "Feature",
  "properties": {
    "addr:full":"Alam Urquijo, 9 Bilbao Vizcaya 48008",
    "addr:housenumber":"9",
    "addr:postcode":"48008",
    "addr:street":"Alam Urquijo",
    "iso:country":"ES",
    "sg:address":"Alam Urquijo, 9",
    "sg:city":"Bilbao",
    "sg:orig_category":"Librer\u00cdas",
    "sg:phone":"+34 944 15 31 99",
    "sg:postcode":"48008",
    "sg:province":"Vizcaya",
    "sg:website":"www.casadellibro.com",
    "wof:name":"Espasa Calpe S.a.",
    "wof:placetype":"venue"
},
  "geometry": {"coordinates":[-2.9300251007,43.2609062195],"type":"Point"}
}