{
  "type": "Feature",
  "properties": {
    "addr:full":"Plaza De La Lama, 4 Espinosa Monteros Burgos 09560",
    "addr:housenumber":"4",
    "addr:postcode":"09560",
    "iso:country":"ES",
    "sg:address":"Plaza De La Lama, 4",
    "sg:city":"Espinosa Monteros",
    "sg:orig_category":"Supermercados Y Hipermercados",
    "sg:phone":"+34 947 12 00 84",
    "sg:postcode":"09560",
    "sg:province":"Burgos",
    "wof:name":"Zorrila Marcide Ricardo",
    "wof:placetype":"venue"
},
  "geometry": {"coordinates":[-3.552883625,43.0763092041],"type":"Point"}
}