{
  "type": "Feature",
  "properties": {
    "iso:country":"ES",
    "sg:address":"Francisco Quevedo, 6",
    "sg:city":"Pinoso",
    "sg:orig_category":"Material Y Herramientas Agr\u00cdcolas",
    "sg:phone":"+34 965 47 75 14",
    "sg:postcode":"03650",
    "sg:province":"Alicante",
    "wof:name":"Mu\u00f1oz Ferriz Francisco",
    "wof:placetype":"venue"
},
  "geometry": {"coordinates":[-1.0392570496,38.4026374817],"type":"Point"}
}