{
  "type": "Feature",
  "properties": {
    "addr:full":"C/ Conde De Torrellano, 83 Torrellano Alicante 03320",
    "addr:housenumber":"83",
    "addr:postcode":"03320",
    "addr:street":"C / Conde De Torrellano",
    "iso:country":"ES",
    "sg:address":"C/ Conde De Torrellano, 83",
    "sg:city":"Torrellano",
    "sg:orig_category":"Carnicer\u00cdas, Carnicer\u00cdas",
    "sg:phone":"+34 965 68 39 65",
    "sg:postcode":"03320",
    "sg:province":"Alicante",
    "wof:name":"Ruz Lucena Jose",
    "wof:placetype":"venue"
},
  "geometry": {"coordinates":[-0.5883839726,38.2929649353],"type":"Point"}
}