{
  "type": "Feature",
  "properties": {
    "addr:full":"Calle de Mayor, 20 Huercal-overa Almer\u00eda 04600",
    "addr:housenumber":"20",
    "addr:postcode":"04600",
    "addr:street":"Calle De Mayor;Almeri\u0301A",
    "iso:country":"ES",
    "sg:address":"Calle de Mayor, 20",
    "sg:city":"Huercal-overa",
    "sg:orig_category":"Electrodom\u00c9sticos (al Por Menor)",
    "sg:phone":"+34 950 13 48 04",
    "sg:postcode":"04600",
    "sg:province":"Almer\u00eda",
    "wof:name":"Oller Castellano Gines",
    "wof:placetype":"venue"
},
  "geometry": {"coordinates":[-1.9419310093,37.3887290955],"type":"Point"}
}