{
  "type": "Feature",
  "properties": {
    "addr:full":"Calle de Orense, 4 Tui Pontevedra 36700",
    "addr:housenumber":"4",
    "addr:postcode":"36700",
    "addr:street":"Calle De Orense",
    "iso:country":"ES",
    "sg:address":"Calle de Orense, 4",
    "sg:city":"Tui",
    "sg:orig_category":"Ropa Para Ni\u00d1os (al Por Menor)",
    "sg:phone":"+34 986 60 39 05",
    "sg:postcode":"36700",
    "sg:province":"Pontevedra",
    "wof:name":"Anaqui\u00f1os S.l.",
    "wof:placetype":"venue"
},
  "geometry": {"coordinates":[-8.6456432343,42.0503463745],"type":"Point"}
}