{
  "type": "Feature",
  "properties": {
    "iso:country":"ES",
    "sg:address":"Calle de Monfrague, 2",
    "sg:city":"Caceres",
    "sg:orig_category":"Institutos De Belleza (productos Y Aparatos)",
    "sg:phone":"+34 927 23 09 31",
    "sg:postcode":"10005",
    "sg:province":"C\u00e1ceres",
    "wof:name":"Marquez Salas Maria Jesus",
    "wof:placetype":"venue"
},
  "geometry": {"coordinates":[-6.3921642303,39.4702568054],"type":"Point"}
}