{
  "type": "Feature",
  "properties": {
    "addr:full":"Calle de Mejillon, 14 Sevilla Sevilla 41015",
    "addr:housenumber":"14",
    "addr:postcode":"41015",
    "addr:street":"Calle De Mejillon",
    "iso:country":"ES",
    "sg:address":"Calle de Mejillon, 14",
    "sg:city":"Sevilla",
    "sg:orig_category":"Panader\u00cdas, Panader\u00cdas",
    "sg:phone":"+34 954 37 10 56",
    "sg:postcode":"41015",
    "sg:province":"Sevilla",
    "wof:name":"Martin Espinosa Francisco Javier",
    "wof:placetype":"venue"
},
  "geometry": {"coordinates":[-5.9831080437,37.4263648987],"type":"Point"}
}