{
  "type": "Feature",
  "properties": {
    "addr:full":"Avda Tra\u00d1abarren, 9 Tra\u00e7a-matiena Vizcaya 48220",
    "addr:housenumber":"9",
    "addr:postcode":"48220",
    "addr:street":"Avda Tran\u0303Abarren",
    "iso:country":"ES",
    "sg:address":"Avda Tra\u00d1abarren, 9",
    "sg:city":"Tra\u00e7a-matiena",
    "sg:orig_category":"Caf\u00c9s, Bares, Cervecer\u00cdas",
    "sg:phone":"+34 946 81 73 68",
    "sg:postcode":"48220",
    "sg:province":"Vizcaya",
    "wof:name":"Rodriguez Cid Armando",
    "wof:placetype":"venue"
},
  "geometry": {"coordinates":[-2.6079039574,43.1692581177],"type":"Point"}
}