{
  "type": "Feature",
  "properties": {
    "iso:country":"ES",
    "sg:address":"Calle de Arguelles, 18",
    "sg:city":"Arriondas",
    "sg:orig_category":"Agencias De Viajes",
    "sg:phone":"+34 985 84 36 14",
    "sg:postcode":"33540",
    "sg:province":"Asturias",
    "wof:name":"Garcia Fernandez Natalia",
    "wof:placetype":"venue"
},
  "geometry": {"coordinates":[-5.1877074242,43.388053894],"type":"Point"}
}