{
  "type": "Feature",
  "properties": {
    "iso:country":"ES",
    "sg:address":"Alcalde Clemente Garcia(p I Oeste), S/n",
    "sg:city":"S. Gines",
    "sg:orig_category":"Bancos",
    "sg:phone":"+34 968 89 16 06",
    "sg:postcode":"30169",
    "sg:province":"Murcia",
    "wof:name":"Banco De Valencia S.a.",
    "wof:placetype":"venue"
},
  "geometry": {"coordinates":[-1.1928639412,37.9559898376],"type":"Point"}
}