{
  "type": "Feature",
  "properties": {
    "addr:full":"Calle de Escolta Real, 40 Donostia-san Sebastian Guip\u00f9zcoa 20008",
    "addr:housenumber":"40",
    "addr:postcode":"20008",
    "addr:street":"Calle De Escolta Real",
    "iso:country":"ES",
    "sg:address":"Calle de Escolta Real, 40",
    "sg:city":"Donostia-san Sebastian",
    "sg:orig_category":"Supermercados Y Hipermercados",
    "sg:phone":"+34 943 31 32 95",
    "sg:postcode":"20008",
    "sg:province":"Guip\u00f9zcoa",
    "wof:name":"Distribucion De Supermercados S.l.",
    "wof:placetype":"venue"
},
  "geometry": {"coordinates":[-2.000494957,43.3118209839],"type":"Point"}
}