{
  "type": "Feature",
  "properties": {
    "addr:full":"Carrer de Corunya, 31 Barcelona Barcelona 08026",
    "addr:housenumber":"31",
    "addr:postcode":"08026",
    "addr:street":"Carrer De Corunya",
    "iso:country":"ES",
    "sg:address":"Carrer de Corunya, 31",
    "sg:city":"Barcelona",
    "sg:orig_category":"Empresas De Limpieza",
    "sg:phone":"+34 934 54 84 89",
    "sg:postcode":"08026",
    "sg:province":"Barcelona",
    "wof:name":"Lim'pdec S.l.",
    "wof:placetype":"venue"
},
  "geometry": {"coordinates":[2.1849770546,41.4081916809],"type":"Point"}
}