{
  "type": "Feature",
  "properties": {
    "iso:country":"ES",
    "sg:address":"Carrer de Verge De Montserrat, 19",
    "sg:city":"Barriada Nova",
    "sg:orig_category":"Papeler\u00cdas, Librer\u00cdas",
    "sg:phone":"+34 938 40 32 57",
    "sg:postcode":"08420",
    "sg:province":"Barcelona",
    "wof:name":"Papeleria Universal",
    "wof:placetype":"venue"
},
  "geometry": {"coordinates":[2.2780098915,41.6220703125],"type":"Point"}
}