{
  "type": "Feature",
  "properties": {
    "addr:full":"Rbla Joaquim Ruyra, 65 Blanes Girona 17300",
    "addr:housenumber":"65",
    "addr:postcode":"17300",
    "addr:street":"Rbla Joaquim Ruyra",
    "iso:country":"ES",
    "sg:address":"Rbla Joaquim Ruyra, 65",
    "sg:city":"Blanes",
    "sg:orig_category":"Abogados",
    "sg:phone":"+34 972 33 12 59",
    "sg:postcode":"17300",
    "sg:province":"Girona",
    "wof:name":"Cotrina Biscos Francisca",
    "wof:placetype":"venue"
},
  "geometry": {"coordinates":[2.7902879715,41.6733627319],"type":"Point"}
}