{
  "type": "Feature",
  "properties": {
    "iso:country":"ES",
    "sg:address":"Carrer de Selva, 19",
    "sg:city":"Can Guitart Vell",
    "sg:classifiers":[
        {
            "category":"Communications",
            "type":"Services"
        }
    ],
    "sg:phone":"+34 936 84 12 92",
    "sg:postcode":"08758",
    "sg:province":"Barcelona",
    "sg:tags":[
        "televisiones",
        "y",
        "radio"
    ],
    "wof:name":"Schenker Sae",
    "wof:placetype":"venue"
},
  "geometry": {"coordinates":[1.9747309685,41.3918685913],"type":"Point"}
}