{
  "type": "Feature",
  "properties": {
    "iso:country":"ES",
    "sg:address":"Avda Hernan Cortes, 46",
    "sg:city":"Caceres",
    "sg:orig_category":"M\u00c9dicos: Medicina Interna",
    "sg:phone":"+34 927 24 35 40",
    "sg:postcode":"10004",
    "sg:province":"C\u00e1ceres",
    "wof:name":"Rufo Gonzalez Fernando",
    "wof:placetype":"venue"
},
  "geometry": {"coordinates":[-6.3793101311,39.4767227173],"type":"Point"}
}