{
  "type": "Feature",
  "properties": {
    "iso:country":"ES",
    "sg:address":"Av. Madrid, 18",
    "sg:city":"Sedavi",
    "sg:orig_category":"Abogados",
    "sg:phone":"+34 963 96 32 21",
    "sg:postcode":"46910",
    "sg:province":"Valencia",
    "wof:name":"Albiach Perez Maria Carmen",
    "wof:placetype":"venue"
},
  "geometry": {"coordinates":[-0.3833031952,39.4265556335],"type":"Point"}
}