{
  "type": "Feature",
  "properties": {
    "iso:country":"ES",
    "sg:address":"Calle de Pintor Clemente, 49",
    "sg:city":"Santiago Ribera",
    "sg:orig_category":"Arquitectos",
    "sg:phone":"+34 968 19 51 22",
    "sg:postcode":"30720",
    "sg:province":"Murcia",
    "wof:name":"Laym Arquitectos S.l-",
    "wof:placetype":"venue"
},
  "geometry": {"coordinates":[-0.8056989908,37.7975196838],"type":"Point"}
}