{
  "type": "Feature",
  "properties": {
    "addr:full":"Calle de Bao, 3 Valladolid Valladolid 47003",
    "addr:housenumber":"3",
    "addr:postcode":"47003",
    "addr:street":"Calle De Bao",
    "iso:country":"ES",
    "sg:address":"Calle de Bao, 3",
    "sg:city":"Valladolid",
    "sg:orig_category":"M\u00c9dicos: Estomatolog\u00cda",
    "sg:phone":"+34 983 25 14 19",
    "sg:postcode":"47003",
    "sg:province":"Valladolid",
    "wof:name":"Sarriugarte Aldecoa Esteban",
    "wof:placetype":"venue"
},
  "geometry": {"coordinates":[-4.7238402367,41.6553916931],"type":"Point"}
}