{
  "type": "Feature",
  "properties": {
    "iso:country":"ES",
    "sg:address":"Calle de Velazquez, 14",
    "sg:city":"Alcazar S. Juan",
    "sg:orig_category":"Delegados, Agentes De Tr\u00c1nsito, Auxiliares De Transporte Internacional",
    "sg:phone":"+34 926 54 01 30",
    "sg:postcode":"13600",
    "sg:province":"Ciudad Real",
    "wof:name":"Arias Paniagua Baudilio",
    "wof:placetype":"venue"
},
  "geometry": {"coordinates":[-3.2030968666,39.3927459717],"type":"Point"}
}