{
  "type": "Feature",
  "properties": {
    "addr:full":"Avda Santiago, 41 Negreira La Coru\u00f1a 15830",
    "addr:housenumber":"41",
    "addr:postcode":"15830",
    "addr:street":"Avda Santiago;La Corun\u0303A",
    "iso:country":"ES",
    "sg:address":"Avda Santiago, 41",
    "sg:city":"Negreira",
    "sg:orig_category":"Confecci\u00d3n De Trajes Para Se\u00d1oras",
    "sg:phone":"+34 981 88 16 98",
    "sg:postcode":"15830",
    "sg:province":"La Coru\u00f1a",
    "wof:name":"Confecciones Regueiro S.l.",
    "wof:placetype":"venue"
},
  "geometry": {"coordinates":[-8.7368841171,42.9089660645],"type":"Point"}
}