{
  "type": "Feature",
  "properties": {
    "iso:country":"ES",
    "sg:address":"Avda Pumarin De, 40",
    "sg:city":"Oviedo",
    "sg:orig_category":"Molduras, Junquillos, Listones Y Molduras Perforadas",
    "sg:phone":"+34 985 29 45 60",
    "sg:postcode":"33011",
    "sg:province":"Asturias",
    "wof:name":"Sanchez Garcia Maria Teresa",
    "wof:placetype":"venue"
},
  "geometry": {"coordinates":[-5.8436050415,43.3688964844],"type":"Point"}
}