{
  "type": "Feature",
  "properties": {
    "addr:full":"Ptge Pau, 6 Femades Barcelona 08940",
    "addr:housenumber":"6",
    "addr:postcode":"08940",
    "addr:street":"Ptge Pau;Barcelona",
    "iso:country":"ES",
    "sg:address":"Ptge Pau, 6",
    "sg:city":"Femades",
    "sg:orig_category":"Fabricaci\u00d3n, Importaci\u00d3n De L\u00c1mparas Y Bombillas",
    "sg:phone":"+34 934 75 02 13",
    "sg:postcode":"08940",
    "sg:province":"Barcelona",
    "wof:name":"Aimarc 2000 S.l.",
    "wof:placetype":"venue"
},
  "geometry": {"coordinates":[2.1004781723,41.3618736267],"type":"Point"}
}