{
  "type": "Feature",
  "properties": {
    "addr:full":"Carr Barcelona, 1 Eivissa Islas Baleares 07800",
    "addr:housenumber":"1",
    "addr:postcode":"07800",
    "addr:street":"Carr Barcelona",
    "iso:country":"ES",
    "sg:address":"Carr Barcelona, 1",
    "sg:city":"Eivissa",
    "sg:orig_category":"Molduras, Junquillos, Listones Y Molduras Perforadas",
    "sg:phone":"+34 971 31 62 71",
    "sg:postcode":"07800",
    "sg:province":"Islas Baleares",
    "wof:name":"Lollo Berceruelo Carlos Alberto",
    "wof:placetype":"venue"
},
  "geometry": {"coordinates":[1.437672019,38.9098739624],"type":"Point"}
}