{
  "type": "Feature",
  "properties": {
    "addr:full":"Avda Zumalakarregi, 40 \u00c1lava 01400",
    "addr:housenumber":"40",
    "addr:postcode":"01400",
    "addr:street":"Avda Zumalakarregi;A\u0301Lava",
    "iso:country":"ES",
    "sg:address":"Avda Zumalakarregi, 40",
    "sg:orig_category":"Fotocopias, Reprograf\u00cda",
    "sg:phone":"+34 946 08 42 27",
    "sg:postcode":"01400",
    "sg:province":"\u00c1lava",
    "wof:name":"Josu Gotzon Larrinaga Landazuri",
    "wof:placetype":"venue"
},
  "geometry": {"coordinates":[-2.9647090435,43.1417808533],"type":"Point"}
}