{
  "type": "Feature",
  "properties": {
    "iso:country":"ES",
    "sg:address":"Ctra. Jauja, S/n",
    "sg:city":"Lucena",
    "sg:orig_category":"Muebles, Minoristas",
    "sg:phone":"+34 957 51 16 30",
    "sg:postcode":"14900",
    "sg:province":"C\u00f3rdoba",
    "wof:name":"Muebles Leycor S.l.",
    "wof:placetype":"venue"
},
  "geometry": {"coordinates":[-4.5054841042,37.3916549683],"type":"Point"}
}