{
  "type": "Feature",
  "properties": {
    "iso:country":"ES",
    "sg:address":"Calle de Porlier, 91",
    "sg:city":"Santa Cruz De Tenerife",
    "sg:orig_category":"Desinfecci\u00d3n, Desinsectaci\u00d3n, Desratizaci\u00d3n",
    "sg:phone":"+34 922 28 35 04",
    "sg:postcode":"38006",
    "sg:province":"Santa Cruz De Tenerife",
    "wof:name":"Bola\u00f1os Suarez Juan Lucio",
    "wof:placetype":"venue"
},
  "geometry": {"coordinates":[-16.2652893066,28.4761505127],"type":"Point"}
}