{
  "type": "Feature",
  "properties": {
    "addr:full":"Rbla Rambla, 54 Sabadell Barcelona 08201",
    "addr:housenumber":"54",
    "addr:postcode":"08201",
    "addr:street":"Rambla",
    "iso:country":"ES",
    "sg:address":"Rbla Rambla, 54",
    "sg:city":"Sabadell",
    "sg:orig_category":"Fotograf\u00cda Y Cine: Aparatos, Pel\u00cdculas Y Accesorios (fabricaci\u00d3n, Al Por Mayor)",
    "sg:phone":"+34 937 25 88 20",
    "sg:postcode":"08201",
    "sg:province":"Barcelona",
    "wof:name":"Movifot S.l.",
    "wof:placetype":"venue"
},
  "geometry": {"coordinates":[2.1098101139,41.5446968079],"type":"Point"}
}