{
  "type": "Feature",
  "properties": {
    "addr:full":"Av. Roncesvalles, 11 Iru\u00f1a Navarra 31002",
    "addr:housenumber":"11",
    "addr:postcode":"31002",
    "addr:street":"Av. Roncesvalles",
    "iso:country":"ES",
    "sg:address":"Av. Roncesvalles, 11",
    "sg:city":"Iru\u00f1a",
    "sg:orig_category":"Compraventa De Antig\u00dcedades",
    "sg:phone":"+34 948 22 00 83",
    "sg:postcode":"31002",
    "sg:province":"Navarra",
    "wof:name":"Alcorta Miqueleiz Maria Pilar Y Maria Teresa S.cv.",
    "wof:placetype":"venue"
},
  "geometry": {"coordinates":[-1.6414014101,42.8147544861],"type":"Point"}
}