{
  "type": "Feature",
  "properties": {
    "addr:full":"Calle de Palma, 76 Madrid Madrid 28015",
    "addr:housenumber":"76",
    "addr:postcode":"madrid;28015",
    "addr:street":"Calle De Palma",
    "iso:country":"ES",
    "sg:address":"Calle de Palma, 76",
    "sg:city":"Madrid",
    "sg:orig_category":"Centros Empresariales",
    "sg:phone":"+34 915 23 47 74",
    "sg:postcode":"28015",
    "sg:province":"Madrid",
    "wof:name":"Leyva Sarmiento Teresa",
    "wof:placetype":"venue"
},
  "geometry": {"coordinates":[-3.7090029716,40.4269752502],"type":"Point"}
}