{
  "type": "Feature",
  "properties": {
    "iso:country":"ES",
    "sg:address":"Calle de Domingo Juliana, 16",
    "sg:city":"Gijon",
    "sg:orig_category":"Ortopedia General",
    "sg:phone":"+34 985 32 33 45",
    "sg:postcode":"33212",
    "sg:province":"Asturias",
    "wof:name":"Instituto Ortopedico Espa\u00f1ol S.l.",
    "wof:placetype":"venue"
},
  "geometry": {"coordinates":[-5.6958994865,43.5405883789],"type":"Point"}
}