{
  "type": "Feature",
  "properties": {
    "addr:full":"Calle de Centro Rural, 3 Almendricos Murcia 30893",
    "addr:housenumber":"3",
    "addr:postcode":"30893",
    "addr:street":"Calle De Centro Rural",
    "iso:country":"ES",
    "sg:address":"Calle de Centro Rural, 3",
    "sg:city":"Almendricos",
    "sg:orig_category":"Comercio, Reparaci\u00d3n De Motocicletas, Bicicletas Y Piezas Sueltas",
    "sg:phone":"+34 968 44 00 86",
    "sg:postcode":"30893",
    "sg:province":"Murcia",
    "wof:name":"Ortega Valverde Juan",
    "wof:placetype":"venue"
},
  "geometry": {"coordinates":[-1.7753709555,37.4740066528],"type":"Point"}
}