{
  "type": "Feature",
  "properties": {
    "addr:full":"Carrer de Industria, 5 Can Bondia Barcelona 08519",
    "addr:housenumber":"5",
    "addr:postcode":"08519",
    "addr:street":"Carrer De Industria",
    "iso:country":"ES",
    "sg:address":"Carrer de Industria, 5",
    "sg:city":"Can Bondia",
    "sg:orig_category":"Instalaci\u00d3n De Vestuarios",
    "sg:phone":"+34 938 50 25 73",
    "sg:postcode":"08519",
    "sg:province":"Barcelona",
    "wof:name":"Gircon S.l.",
    "wof:placetype":"venue"
},
  "geometry": {"coordinates":[2.3100700378,41.9359512329],"type":"Point"}
}