{
  "type": "Feature",
  "properties": {
    "iso:country":"ES",
    "sg:address":"Calle de Doctor Juan Sanchez Cozar, 1",
    "sg:city":"Granada",
    "sg:orig_category":"Laboratorios Y Trabajos De Fotograf\u00cda, V\u00cddeo Y Cine",
    "sg:phone":"+34 958 28 56 42",
    "sg:postcode":"18003",
    "sg:province":"Granada",
    "wof:name":"Bahon Martinez Andres",
    "wof:placetype":"venue"
},
  "geometry": {"coordinates":[-3.6112360954,37.1800346375],"type":"Point"}
}