{
  "type": "Feature",
  "properties": {
    "iso:country":"ES",
    "sg:address":"Avda Alfonso R. Castelao, 31",
    "sg:city":"Calle",
    "sg:orig_category":"Panader\u00cdas, Panader\u00cdas",
    "sg:phone":"+34 986 70 06 75",
    "sg:postcode":"36690",
    "sg:province":"Pontevedra",
    "wof:name":"Ibarrez Mu\u00f1iz Miguel",
    "wof:placetype":"venue"
},
  "geometry": {"coordinates":[-8.6109972,42.3424911499],"type":"Point"}
}