{
  "type": "Feature",
  "properties": {
    "addr:full":"Carrer de Montcada, 5 Granollers Barcelona 08402",
    "addr:housenumber":"5",
    "addr:postcode":"08402",
    "addr:street":"Carrer De Montcada",
    "iso:country":"ES",
    "sg:address":"Carrer de Montcada, 5",
    "sg:city":"Granollers",
    "sg:orig_category":"Peluqueros: De Se\u00d1oras",
    "sg:phone":"+34 938 49 63 85",
    "sg:postcode":"08402",
    "sg:province":"Barcelona",
    "wof:name":"Perez Rodriguez Antonia",
    "wof:placetype":"venue"
},
  "geometry": {"coordinates":[2.2932760715,41.6190834045],"type":"Point"}
}