{
  "type": "Feature",
  "properties": {
    "iso:country":"ES",
    "sg:address":"Calle de Principe De Vergara, 43",
    "sg:city":"Madrid",
    "sg:classifiers":[
        {
            "category":"Casinos & Gambling",
            "type":"Entertainment"
        }
    ],
    "sg:phone":"+34 915 78 40 96",
    "sg:postcode":"28001",
    "sg:province":"Madrid",
    "sg:tags":[
        "locale",
        "de",
        "juego"
    ],
    "wof:name":"Telefono Publico Del Sur S. L.",
    "wof:placetype":"venue"
},
  "geometry": {"coordinates":[-3.6799297333,40.429107666],"type":"Point"}
}