{
  "type": "Feature",
  "properties": {
    "addr:full":"Calle de Mayor, 25 San Jorge Castell\u00f3n 12320",
    "addr:housenumber":"25",
    "addr:postcode":"12320",
    "addr:street":"Calle De Mayor",
    "iso:country":"ES",
    "sg:address":"Calle de Mayor, 25",
    "sg:city":"San Jorge",
    "sg:orig_category":"Cajas De Ahorro",
    "sg:phone":"+34 964 49 91 37",
    "sg:postcode":"12320",
    "sg:province":"Castell\u00f3n",
    "wof:name":"Caja De Ahorros De Valencia Castellon Y Alicante",
    "wof:placetype":"venue"
},
  "geometry": {"coordinates":[0.3639900088,40.5369186401],"type":"Point"}
}