{
  "type": "Feature",
  "properties": {
    "addr:full":"Pase Maritimo Rey De Espa\u00d1a, 32 Fuengirola M\u00e1laga 29640",
    "addr:housenumber":"32",
    "addr:postcode":"29640",
    "addr:street":"Espan\u0303A;Ma\u0301Laga",
    "iso:country":"ES",
    "sg:address":"Pase Maritimo Rey De Espa\u00d1a, 32",
    "sg:city":"Fuengirola",
    "sg:orig_category":"Confecci\u00d3n De Trajes De Ba\u00d1o Y De Ropa De Playa",
    "sg:phone":"+34 952 47 14 39",
    "sg:postcode":"29640",
    "sg:province":"M\u00e1laga",
    "wof:name":"Seco Perez Aurora",
    "wof:placetype":"venue"
},
  "geometry": {"coordinates":[-4.6223402023,36.5367965698],"type":"Point"}
}