{
  "type": "Feature",
  "properties": {
    "addr:full":"Calle de Juan Xxiii, 2 Torrejon Ardoz Madrid 28850",
    "addr:housenumber":"2",
    "addr:postcode":"28850",
    "addr:street":"Calle De Juan Xxiii",
    "iso:country":"ES",
    "sg:address":"Calle de Juan Xxiii, 2",
    "sg:city":"Torrejon Ardoz",
    "sg:orig_category":"Frutas Y Legumbres Secas (al Por Mayor)",
    "sg:phone":"+34 916 75 11 14",
    "sg:postcode":"28850",
    "sg:province":"Madrid",
    "wof:name":"Casero Juara Demetrio",
    "wof:placetype":"venue"
},
  "geometry": {"coordinates":[-3.4803030491,40.4565086365],"type":"Point"}
}