{
  "type": "Feature",
  "properties": {
    "addr:full":"Carr Juan Izquierdo (de), 50 Lliria Valencia 46160",
    "addr:housenumber":"50",
    "addr:postcode":"46160",
    "addr:street":"Carr Juan Izquierdo De",
    "iso:country":"ES",
    "sg:address":"Carr Juan Izquierdo (de), 50",
    "sg:city":"Lliria",
    "sg:orig_category":"Promotores Constructores",
    "sg:phone":"+34 962 78 04 02",
    "sg:postcode":"46160",
    "sg:province":"Valencia",
    "wof:name":"Merino Montesinos S.l.",
    "wof:placetype":"venue"
},
  "geometry": {"coordinates":[-0.5928059816,39.6238021851],"type":"Point"}
}