{
  "type": "Feature",
  "properties": {
    "iso:country":"ES",
    "sg:address":"Avda Doctor Martinez Pardo - Teixeiro, 13",
    "sg:city":"Teijeiro",
    "sg:classifiers":[
        {
            "category":"Banks & Credit Unions",
            "subcategory":"Bureau De Change",
            "type":"Services"
        }
    ],
    "sg:phone":"+34 981 78 92 18",
    "sg:postcode":"15310",
    "sg:province":"A Coru\u00f1a",
    "sg:tags":[
        "organismos",
        "control"
    ],
    "wof:name":"S.a.t. San Cibre",
    "wof:placetype":"venue"
},
  "geometry": {"coordinates":[-8.1450586319,43.1260108948],"type":"Point"}
}