{
  "type": "Feature",
  "properties": {
    "iso:country":"ES",
    "sg:address":"Plaz Constitucion, S/n",
    "sg:city":"Cartaya",
    "sg:orig_category":"Empresas De Desmonte",
    "sg:phone":"+34 959 39 24 43",
    "sg:postcode":"21450",
    "sg:province":"Huelva",
    "wof:name":"Movimientos De Tierra Anpeva E Hijos",
    "wof:placetype":"venue"
},
  "geometry": {"coordinates":[-7.1586990356,37.2868652344],"type":"Point"}
}