{
  "type": "Feature",
  "properties": {
    "addr:full":"Afores, S/n Estamariu Lleida 25719",
    "addr:housenumber":"s / n",
    "addr:postcode":"25719",
    "addr:street":"Afores",
    "iso:country":"ES",
    "sg:address":"Afores, S/n",
    "sg:city":"Estamariu",
    "sg:orig_category":"Fabricaci\u00d3n De Bebidas No Alcoh\u00d3licas",
    "sg:phone":"+34 973 36 07 38",
    "sg:postcode":"25719",
    "sg:province":"Lleida",
    "wof:name":"Naturquell S.a.",
    "wof:placetype":"venue"
},
  "geometry": {"coordinates":[1.524230957,42.3747787476],"type":"Point"}
}