{
  "type": "Feature",
  "properties": {
    "addr:full":"L'albors, S/n Benicassim Castell\u00f3n 12560",
    "addr:postcode":"12560",
    "addr:street":"L'Albors S / N Benicassim Castello\u0301N",
    "iso:country":"ES",
    "sg:address":"L'albors, S/n",
    "sg:city":"Benicassim",
    "sg:orig_category":"Farmacias",
    "sg:phone":"+34 964 39 32 14",
    "sg:postcode":"12560",
    "sg:province":"Castell\u00f3n",
    "wof:name":"Bengochea Vallet Enrique Jose",
    "wof:placetype":"venue"
},
  "geometry": {"coordinates":[0.0467110015,40.0375747681],"type":"Point"}
}