{
  "type": "Feature",
  "properties": {
    "addr:full":"Carrer de Comte Borrell, 5 Barcelona Barcelona 08015",
    "addr:housenumber":"5",
    "addr:postcode":"08015",
    "addr:street":"Carrer De Comte Borrell",
    "iso:country":"ES",
    "sg:address":"Carrer de Comte Borrell, 5",
    "sg:city":"Barcelona",
    "sg:orig_category":"Molduras, Junquillos, Listones Y Molduras Perforadas",
    "sg:phone":"+34 934 42 30 42",
    "sg:postcode":"08015",
    "sg:province":"Barcelona",
    "wof:name":"Vazquez Barral Jose",
    "wof:placetype":"venue"
},
  "geometry": {"coordinates":[2.1648719311,41.3754653931],"type":"Point"}
}