{
  "type": "Feature",
  "properties": {
    "iso:country":"ES",
    "sg:address":"Calle de Sandro Pertini, 2",
    "sg:city":"Illescas",
    "sg:orig_category":"Cr\u00cda De Animales",
    "sg:phone":"+34 925 54 08 86",
    "sg:postcode":"45200",
    "sg:province":"Toledo",
    "wof:name":"Tercentro S.l.",
    "wof:placetype":"venue"
},
  "geometry": {"coordinates":[-3.8524699211,40.1221809387],"type":"Point"}
}