{
  "type": "Feature",
  "properties": {
    "addr:full":"Ctra Puebla De Soto, 12 Alcantarilla Murcia 30820",
    "addr:housenumber":"12",
    "addr:postcode":"30820",
    "addr:street":"Ctra Puebla De Soto",
    "iso:country":"ES",
    "sg:address":"Ctra Puebla De Soto, 12",
    "sg:city":"Alcantarilla",
    "sg:orig_category":"Mec\u00c1nico Del Autom\u00d3vil",
    "sg:phone":"+34 968 89 08 93",
    "sg:postcode":"30820",
    "sg:province":"Murcia",
    "wof:name":"Benedicto Jimenez Alberto",
    "wof:placetype":"venue"
},
  "geometry": {"coordinates":[-1.2049939632,37.9755897522],"type":"Point"}
}