{
  "type": "Feature",
  "properties": {
    "addr:full":"Prje Las Fuentes, S/n Villena Alicante 03400",
    "addr:housenumber":"s / n",
    "addr:postcode":"03400",
    "iso:country":"ES",
    "sg:address":"Prje Las Fuentes, S/n",
    "sg:city":"Villena",
    "sg:orig_category":"Asociaciones De Vecinos, Centros De Juventud",
    "sg:phone":"+34 965 34 80 26",
    "sg:postcode":"03400",
    "sg:province":"Alicante",
    "sg:website":"www.adav.org",
    "wof:name":"Asociacion Para El Desarrollo Del Alto Vinalopo",
    "wof:placetype":"venue"
},
  "geometry": {"coordinates":[-0.8865833879,38.6286621094],"type":"Point"}
}