{
  "type": "Feature",
  "properties": {
    "addr:full":"Calle de Durrio Francisco Escultor, 3 Bilbao Vizcaya 48015",
    "addr:housenumber":"3",
    "addr:postcode":"48015",
    "addr:street":"Calle De Durrio Francisco Escultor",
    "iso:country":"ES",
    "sg:address":"Calle de Durrio Francisco Escultor, 3",
    "sg:city":"Bilbao",
    "sg:orig_category":"Peluquer\u00cdas, Peluquer\u00cda Mixta",
    "sg:phone":"+34 944 47 13 78",
    "sg:postcode":"48015",
    "sg:province":"Vizcaya",
    "wof:name":"Arrate Zarate Santamaria -  Izaskun Zarate, C.b.",
    "wof:placetype":"venue"
},
  "geometry": {"coordinates":[-2.9500646591,43.2794685364],"type":"Point"}
}