{
  "type": "Feature",
  "properties": {
    "iso:country":"ES",
    "sg:address":"Calle de Canovas Del Castillo, 29",
    "sg:city":"Santa Eulalia",
    "sg:orig_category":"Deportes Diversos",
    "sg:phone":"+34 968 22 10 12",
    "sg:postcode":"30003",
    "sg:province":"Murcia",
    "wof:name":"Federacion Murciana De Pesca",
    "wof:placetype":"venue"
},
  "geometry": {"coordinates":[-1.1251878738,37.9846115112],"type":"Point"}
}