{
  "type": "Feature",
  "properties": {
    "iso:country":"ES",
    "sg:address":"Ctra Benavente, 7",
    "sg:city":"Valderas",
    "sg:orig_category":"Empresas De Carpinter\u00cda De Madera",
    "sg:phone":"+34 987 76 21 47",
    "sg:postcode":"24220",
    "sg:province":"Le\u00f3n",
    "wof:name":"Llanos Pastor Fernando",
    "wof:placetype":"venue"
},
  "geometry": {"coordinates":[-5.4420042038,42.076461792],"type":"Point"}
}