{
  "type": "Feature",
  "properties": {
    "iso:country":"ES",
    "sg:address":"Cmno Torres (las), 103",
    "sg:city":"Zaragoza",
    "sg:orig_category":"Agencias De Viajes",
    "sg:phone":"+34 976 37 22 23",
    "sg:postcode":"50007",
    "sg:province":"Zaragoza",
    "sg:website":"www.viajeseroski.es",
    "wof:name":"Viajes Eroski S.a.",
    "wof:placetype":"venue"
},
  "geometry": {"coordinates":[-0.8854140043,41.640083313],"type":"Point"}
}