{
  "type": "Feature",
  "properties": {
    "addr:full":"Av Francesc Macia, 55 Sabadell Barcelona 08206",
    "addr:housenumber":"55",
    "addr:postcode":"08206",
    "addr:street":"Av Francesc Macia",
    "iso:country":"ES",
    "sg:address":"Av Francesc Macia, 55",
    "sg:city":"Sabadell",
    "sg:orig_category":"Ropa Para Se\u00d1oras Y Caballeros (al Por Menor)",
    "sg:phone":"+34 937 23 55 40",
    "sg:postcode":"08206",
    "sg:province":"Barcelona",
    "wof:name":"Hernandez Navarro Franchesca",
    "wof:placetype":"venue"
},
  "geometry": {"coordinates":[2.0969510078,41.557849884],"type":"Point"}
}