{
  "type": "Feature",
  "properties": {
    "iso:country":"ES",
    "sg:address":"Cra. Ermita, S/n",
    "sg:city":"L'aldea",
    "sg:orig_category":"Zootecnia",
    "sg:phone":"+34 977 45 10 04",
    "sg:postcode":"43896",
    "sg:province":"Tarragona",
    "wof:name":"Promotora Bama S. A.",
    "wof:placetype":"venue"
},
  "geometry": {"coordinates":[0.6140480042,40.7452278137],"type":"Point"}
}