{
  "type": "Feature",
  "properties": {
    "iso:country":"ES",
    "sg:address":"Plaz Franchy Alfaro (1/2), 5",
    "sg:city":"Orotava",
    "sg:orig_category":"Asociaciones, Organismos Culturales Y Socioeducativos",
    "sg:phone":"+34 922 32 06 76",
    "sg:postcode":"38300",
    "sg:province":"Santa Cruz De Tenerife",
    "wof:name":"Fundacion Benefica Docente San Isidro",
    "wof:placetype":"venue"
},
  "geometry": {"coordinates":[-16.5221004486,28.3937988281],"type":"Point"}
}