{
  "type": "Feature",
  "properties": {
    "addr:full":"Carrer de Albert Llanas, 32 Barcelona Barcelona 08024",
    "addr:housenumber":"32",
    "addr:postcode":"08024",
    "addr:street":"Carrer De Albert Llanas",
    "iso:country":"ES",
    "sg:address":"Carrer de Albert Llanas, 32",
    "sg:city":"Barcelona",
    "sg:orig_category":"Productos Qu\u00cdmicos (fabricaci\u00d3n, Al Por Mayor)",
    "sg:phone":"+34 932 84 86 33",
    "sg:postcode":"08024",
    "sg:province":"Barcelona",
    "sg:website":"www.adiquimica.com",
    "wof:name":"Adiquimica S. A.",
    "wof:placetype":"venue"
},
  "geometry": {"coordinates":[2.1577022076,41.416934967],"type":"Point"}
}