{
  "type": "Feature",
  "properties": {
    "addr:full":"Calle de Hurtado De Amezaga, 4 Bilbao Vizcaya 48008",
    "addr:housenumber":"4",
    "addr:postcode":"48008",
    "addr:street":"Calle De Hurtado De Amezaga",
    "iso:country":"ES",
    "sg:address":"Calle de Hurtado De Amezaga, 4",
    "sg:city":"Bilbao",
    "sg:orig_category":"Caf\u00c9s, Bares, Cervecer\u00cdas",
    "sg:phone":"+34 944 24 85 32",
    "sg:postcode":"48008",
    "sg:province":"Vizcaya",
    "wof:name":"Guenechea Belaza Angel",
    "wof:placetype":"venue"
},
  "geometry": {"coordinates":[-2.9282610416,43.2607574463],"type":"Point"}
}