{
  "type": "Feature",
  "properties": {
    "addr:full":"Calle de San Pascual, 15 Jumilla Murcia 30520",
    "addr:housenumber":"15",
    "addr:postcode":"30520",
    "addr:street":"Calle De San Pascual",
    "iso:country":"ES",
    "sg:address":"Calle de San Pascual, 15",
    "sg:city":"Jumilla",
    "sg:orig_category":"Molduras, Junquillos, Listones Y Molduras Perforadas",
    "sg:phone":"+34 968 78 17 44",
    "sg:postcode":"30520",
    "sg:province":"Murcia",
    "wof:name":"Mondejar Alfaro Ana Maria",
    "wof:placetype":"venue"
},
  "geometry": {"coordinates":[-1.3189270496,38.4794311523],"type":"Point"}
}