{
  "type": "Feature",
  "properties": {
    "addr:full":"Calle de Olivar, 1 Pozuelo De Alarcon Madrid 28223",
    "addr:housenumber":"1",
    "addr:postcode":"28223",
    "addr:street":"Calle De Olivar",
    "iso:country":"ES",
    "sg:address":"Calle de Olivar, 1",
    "sg:city":"Pozuelo De Alarcon",
    "sg:orig_category":"Urbanistas",
    "sg:phone":"+34 913 52 92 28",
    "sg:postcode":"28223",
    "sg:province":"Madrid",
    "wof:name":"Adiego-vizmanos 3 S.a.",
    "wof:placetype":"venue"
},
  "geometry": {"coordinates":[-3.8153932095,40.4342765808],"type":"Point"}
}