{
  "type": "Feature",
  "properties": {
    "addr:full":"Ctr. Cuenca, Km. 0044,0 Quintanar Rey Cuenca 16220",
    "addr:postcode":"16220",
    "addr:street":"Cuenca Km. 0044,0 Quintanar Rey",
    "iso:country":"ES",
    "sg:address":"Ctr. Cuenca, Km. 0044,0",
    "sg:city":"Quintanar Rey",
    "sg:orig_category":"Producci\u00d3n De Champi\u00d1ones",
    "sg:phone":"+34 967 49 68 96",
    "sg:postcode":"16220",
    "sg:province":"Cuenca",
    "wof:name":"Alarcon Martinez Jeronimo",
    "wof:placetype":"venue"
},
  "geometry": {"coordinates":[-1.9307767153,39.3435173035],"type":"Point"}
}