{
  "type": "Feature",
  "properties": {
    "addr:full":"Pzta Convent, S/n Sueca Valencia 46410",
    "addr:housenumber":"s / n",
    "addr:postcode":"46410",
    "iso:country":"ES",
    "sg:address":"Pzta Convent, S/n",
    "sg:city":"Sueca",
    "sg:orig_category":"Centros P\u00dablicos De Formaci\u00d3n Profesional Y T\u00c9cnica",
    "sg:phone":"+34 961 70 33 81",
    "sg:postcode":"46410",
    "sg:province":"Valencia",
    "wof:name":"Colegio De Procuradores De Valencia",
    "wof:placetype":"venue"
},
  "geometry": {"coordinates":[-0.31585899,39.2022399902],"type":"Point"}
}