{
  "type": "Feature",
  "properties": {
    "addr:full":"Carrer de Sant Miquel, 12 Torello Barcelona 08570",
    "addr:housenumber":"12",
    "addr:postcode":"08570",
    "addr:street":"Carrer De Sant Miquel",
    "iso:country":"ES",
    "sg:address":"Carrer de Sant Miquel, 12",
    "sg:city":"Torello",
    "sg:orig_category":"Fabrica, Negocio De Vidrieras, Productos Vidriados Y Espejos",
    "sg:phone":"+34 938 59 51 43",
    "sg:postcode":"08570",
    "sg:province":"Barcelona",
    "wof:name":"Vidres Mora S.l.",
    "wof:placetype":"venue"
},
  "geometry": {"coordinates":[2.2642490864,42.0475311279],"type":"Point"}
}