{
  "type": "Feature",
  "properties": {
    "iso:country":"ES",
    "sg:address":"Carrer de Mar (la), 149",
    "sg:city":"Altea",
    "sg:orig_category":"Ingenier\u00cda, Centros De Estudios (diversos)",
    "sg:phone":"+34 965 84 04 97",
    "sg:postcode":"03590",
    "sg:province":"Alicante",
    "wof:name":"Benedicto Albi\u00f1ana Manuel Francisco",
    "wof:placetype":"venue"
},
  "geometry": {"coordinates":[-0.054051999,38.594078064],"type":"Point"}
}