{
  "type": "Feature",
  "properties": {
    "iso:country":"ES",
    "sg:address":"Calle de Juan De Juanes, 4",
    "sg:city":"Mislata",
    "sg:orig_category":"Fabricaci\u00d3n De Mobiliario Met\u00c1lico",
    "sg:phone":"+34 963 59 91 64",
    "sg:postcode":"46920",
    "sg:province":"Valencia",
    "wof:name":"Garcia Zapata Ramon",
    "wof:placetype":"venue"
},
  "geometry": {"coordinates":[-0.4156480134,39.4710922241],"type":"Point"}
}