{
  "type": "Feature",
  "properties": {
    "iso:country":"ES",
    "sg:address":"Carrer de Santa Teresa, 7",
    "sg:city":"Barcelona",
    "sg:orig_category":"Asesor\u00cda Sobre Comunicaci\u00d3n De Empresas",
    "sg:phone":"+34 933 68 05 10",
    "sg:postcode":"08012",
    "sg:province":"Barcelona",
    "wof:name":"Pedrosa & Asociados A.l.t. S.l.",
    "wof:placetype":"venue"
},
  "geometry": {"coordinates":[2.1600880623,41.3978309631],"type":"Point"}
}