{
  "type": "Feature",
  "properties": {
    "iso:country":"ES",
    "sg:address":"Calle de Jose Sinues, 10",
    "sg:city":"Ejea De Los Caballeros",
    "sg:orig_category":"Radiocomunicaciones, Telefon\u00cda M\u00d3vil, Radiomensajer\u00cda: Servicios, Comercializaci\u00d3n",
    "sg:phone":"+34 976 67 71 18",
    "sg:postcode":"50600",
    "sg:province":"Zaragoza",
    "wof:name":"Comunicaciones Exea, Sc",
    "wof:placetype":"venue"
},
  "geometry": {"coordinates":[-1.1382750273,42.1269798279],"type":"Point"}
}