{
  "type": "Feature",
  "properties": {
    "iso:country":"ES",
    "sg:address":"Calle de Salvador Martinez Lozano, 16",
    "sg:city":"Madrid",
    "sg:orig_category":"Asociaciones Y Clubs Deportivos",
    "sg:phone":"+34 915 52 70 43",
    "sg:postcode":"28053",
    "sg:province":"Madrid",
    "wof:name":"Body Work S.l.",
    "wof:placetype":"venue"
},
  "geometry": {"coordinates":[-3.6699500084,40.3951148987],"type":"Point"}
}