{
  "type": "Feature",
  "properties": {
    "iso:country":"ES",
    "sg:address":"Dema Entrevies, S/n",
    "sg:city":"Pinedes",
    "sg:classifiers":[
        {
            "category":"Manufacturing",
            "subcategory":"Building Materials",
            "type":"Manufacturing & Wholesale Goods"
        }
    ],
    "sg:phone":"+34 977 54 04 72",
    "sg:postcode":"43006",
    "sg:province":"Tarragona",
    "sg:tags":[
        "cemento",
        "y",
        "de",
        "fabricaci\u00d3n",
        "cal"
    ],
    "sg:website":"www.cementosesfera.com",
    "wof:name":"Cementos Esfera S.a.",
    "wof:placetype":"venue"
},
  "geometry": {"coordinates":[1.2209249735,41.1154441833],"type":"Point"}
}