{
  "type": "Feature",
  "properties": {
    "iso:country":"ES",
    "sg:address":"Calle de Claudio Coello, 66",
    "sg:city":"Madrid",
    "sg:orig_category":"Lencer\u00cda Femenina, Corseter\u00cda, Trajes De Ba\u00d1o (al Por Menor)",
    "sg:phone":"+34 915 76 41 32",
    "sg:postcode":"28001",
    "sg:province":"Madrid",
    "wof:name":"Proposicio 92 S.a.",
    "wof:placetype":"venue"
},
  "geometry": {"coordinates":[-3.6860389709,40.4288330078],"type":"Point"}
}