{
  "type": "Feature",
  "properties": {
    "iso:country":"ES",
    "sg:address":"Carrer de Sant Pau, 32",
    "sg:city":"Vilafranca Penedes",
    "sg:orig_category":"Inform\u00c1tica (estudios, Servicios, Asesor\u00cda, Formaci\u00d3n)",
    "sg:phone":"+34 938 90 21 88",
    "sg:postcode":"08720",
    "sg:province":"Barcelona",
    "wof:name":"Espai Data Serveis Informatics S.l.",
    "wof:placetype":"venue"
},
  "geometry": {"coordinates":[1.6963180304,41.3494415283],"type":"Point"}
}