{
  "type": "Feature",
  "properties": {
    "iso:country":"ES",
    "sg:address":"Calle de Prosperidad, 3",
    "sg:city":"Alcazar S. Juan",
    "sg:orig_category":"Producci\u00d3n De Abonos Y De Fertilizantes",
    "sg:phone":"+34 926 54 09 25",
    "sg:postcode":"13600",
    "sg:province":"Ciudad Real",
    "wof:name":"Abonos Y Semillas Eusebio S.l.",
    "wof:placetype":"venue"
},
  "geometry": {"coordinates":[-3.213217,39.391243],"type":"Point"}
}