{
  "type": "Feature",
  "properties": {
    "iso:country":"ES",
    "sg:address":"Calle de Pintor Zurbaran, 11",
    "sg:city":"Petrer",
    "sg:orig_category":"Delegados, Agentes De Tr\u00c1nsito, Auxiliares De Transporte Internacional",
    "sg:phone":"+34 965 37 26 17",
    "sg:postcode":"03610",
    "sg:province":"Alicante",
    "wof:name":"Garcia Sanchez Domingo",
    "wof:placetype":"venue"
},
  "geometry": {"coordinates":[-0.7805190086,38.4843254089],"type":"Point"}
}