{
  "type": "Feature",
  "properties": {
    "iso:country":"ES",
    "sg:address":"Calle de Silencio (el), 8",
    "sg:city":"Sevilla",
    "sg:orig_category":"Bisuter\u00cda, Joyer\u00cda, Relojer\u00cda (al Por Menor)",
    "sg:phone":"+34 954 50 25 39",
    "sg:postcode":"41001",
    "sg:province":"Sevilla",
    "wof:name":"Perez Martinez Micaela",
    "wof:placetype":"venue"
},
  "geometry": {"coordinates":[-5.996899128,37.3922386169],"type":"Point"}
}