{
  "type": "Feature",
  "properties": {
    "iso:country":"ES",
    "sg:address":"Calle de Santiago De Compostela, 100",
    "sg:city":"Madrid",
    "sg:orig_category":"Aceros Inoxidables",
    "sg:phone":"+34 913 98 51 00",
    "sg:postcode":"28...",
    "sg:province":"Madrid",
    "sg:website":"www.acerinox.es",
    "wof:name":"Acerinox S.a.",
    "wof:placetype":"venue"
},
  "geometry": {"coordinates":[-3.7203803062,40.4770278931],"type":"Point"}
}