{
  "type": "Feature",
  "properties": {
    "iso:country":"ES",
    "sg:address":"Calle de Astorga, 6",
    "sg:city":"Fuenlabrada",
    "sg:orig_category":"Alimentaci\u00d3n: Aditivos, Esencias Alimentarias, Levaduras (fabricaci\u00d3n, Al Por Mayor)",
    "sg:phone":"+34 916 42 05 80",
    "sg:postcode":"28947",
    "sg:province":"Madrid",
    "sg:website":"www.boaya.es",
    "wof:name":"Boaya S.l.",
    "wof:placetype":"venue"
},
  "geometry": {"coordinates":[-3.7465610504,40.2635765076],"type":"Point"}
}