{
  "type": "Feature",
  "properties": {
    "addr:full":"Calle de Principe De Vergara, 126 Madrid Madrid 28002",
    "addr:housenumber":"126",
    "addr:postcode":"28002",
    "addr:street":"Calle De Principe De Vergara",
    "iso:country":"ES",
    "sg:address":"Calle de Principe De Vergara, 126",
    "sg:city":"Madrid",
    "sg:orig_category":"Sociedades, Compa\u00d1\u00cdas Aseguradoras",
    "sg:phone":"+34 915 61 24 39",
    "sg:postcode":"28002",
    "sg:province":"Madrid",
    "wof:name":"Banco Vitalicio De Espa\u00f1a C.a.",
    "wof:placetype":"venue"
},
  "geometry": {"coordinates":[-3.678467989,40.4420013428],"type":"Point"}
}