{
  "type": "Feature",
  "properties": {
    "iso:country":"ES",
    "sg:address":"Carrer de Zurbaran, 3",
    "sg:city":"Ondara",
    "sg:orig_category":"Empresas De Carpinter\u00cda De Madera",
    "sg:phone":"+34 965 76 62 14",
    "sg:postcode":"03760",
    "sg:province":"Alicante",
    "wof:name":"Fusta Ondara S.c.p",
    "wof:placetype":"venue"
},
  "geometry": {"coordinates":[0.01516,38.8275604248],"type":"Point"}
}