{
  "type": "Feature",
  "properties": {
    "addr:full":"Av Primavera, 3 Cerdanyola Valles Barcelona 08290",
    "addr:housenumber":"3",
    "addr:postcode":"08290",
    "addr:street":"Av Primavera;Valles Barcelona",
    "iso:country":"ES",
    "sg:address":"Av Primavera, 3",
    "sg:city":"Cerdanyola Valles",
    "sg:orig_category":"M\u00c9dicos: Cirug\u00cda Pl\u00c1stica, Reconstructiva Y Est\u00c9tica",
    "sg:phone":"+34 935 80 48 48",
    "sg:postcode":"08290",
    "sg:province":"Barcelona",
    "wof:name":"Guillen Sanchez Mercedes",
    "wof:placetype":"venue"
},
  "geometry": {"coordinates":[2.1469800472,41.4922523499],"type":"Point"}
}