{
  "type": "Feature",
  "properties": {
    "iso:country":"ES",
    "sg:address":"Calle de Virgen De Los Dolores, 25",
    "sg:city":"Ronda",
    "sg:orig_category":"Procuradores",
    "sg:phone":"+34 952 87 60 17",
    "sg:postcode":"29400",
    "sg:province":"M\u00e1laga",
    "wof:name":"Canduela Tardio Yolanda",
    "wof:placetype":"venue"
},
  "geometry": {"coordinates":[-5.1624622345,36.7433357239],"type":"Point"}
}