{
  "type": "Feature",
  "properties": {
    "addr:full":"Calle de Beurko Viejo, 14 San Vicente De Barakaldo Vizcaya 48902",
    "addr:housenumber":"14",
    "addr:postcode":"48902",
    "addr:street":"Calle De Beurko Viejo",
    "iso:country":"ES",
    "sg:address":"Calle de Beurko Viejo, 14",
    "sg:city":"San Vicente De Barakaldo",
    "sg:orig_category":"Cl\u00cdnicas Dentales",
    "sg:phone":"+34 944 38 34 06",
    "sg:postcode":"48902",
    "sg:province":"Vizcaya",
    "wof:name":"Progressive Dental Supplies Spain S.l.",
    "wof:placetype":"venue"
},
  "geometry": {"coordinates":[-2.9950582981,43.2927894592],"type":"Point"}
}