{
  "type": "Feature",
  "properties": {
    "iso:country":"ES",
    "sg:address":"Carr Mar, 11",
    "sg:city":"Torroella Montgri",
    "sg:orig_category":"Carnicer\u00cdas, Carnicer\u00cdas",
    "sg:phone":"+34 972 75 81 77",
    "sg:postcode":"17257",
    "sg:province":"Girona",
    "wof:name":"Ramio Juanola Rosa",
    "wof:placetype":"venue"
},
  "geometry": {"coordinates":[3.1277420521,42.042766571],"type":"Point"}
}