{
  "type": "Feature",
  "properties": {
    "iso:country":"ES",
    "sg:address":"Carrer de Jacint Verdaguer, 5",
    "sg:city":"S. Feliu Guixols",
    "sg:orig_category":"Caf\u00c9s, Bares, Cervecer\u00cdas",
    "sg:phone":"+34 972 32 42 09",
    "sg:postcode":"17220",
    "sg:province":"Girona",
    "wof:name":"Martinez Souto Julian Carlos",
    "wof:placetype":"venue"
},
  "geometry": {"coordinates":[3.0293829441,41.7819404602],"type":"Point"}
}