{
  "type": "Feature",
  "properties": {
    "addr:full":"Calle de Bolarin, 33 Santiago Ribera Murcia 30720",
    "addr:housenumber":"33",
    "addr:postcode":"30720",
    "addr:street":"Calle De Bolarin",
    "iso:country":"ES",
    "sg:address":"Calle de Bolarin, 33",
    "sg:city":"Santiago Ribera",
    "sg:orig_category":"Caf\u00c9s, Bares, Cervecer\u00cdas",
    "sg:phone":"+34 968 57 01 87",
    "sg:postcode":"30720",
    "sg:province":"Murcia",
    "sg:website":"www.panaderiajoseantonio.com",
    "wof:name":"Patriher S.l.",
    "wof:placetype":"venue"
},
  "geometry": {"coordinates":[-0.805809617,37.7958450317],"type":"Point"}
}