{
  "type": "Feature",
  "properties": {
    "iso:country":"ES",
    "sg:address":"Carrer de Pare Llaurador, 88",
    "sg:city":"Terrassa",
    "sg:orig_category":"Electricidad: Instaladores",
    "sg:phone":"+34 937 80 64 47",
    "sg:postcode":"08224",
    "sg:province":"Barcelona",
    "sg:website":"www.barrinet.net/electicitatcein",
    "wof:name":"Robles Rodriguez Monserrat",
    "wof:placetype":"venue"
},
  "geometry": {"coordinates":[2.0047399998,41.5641593933],"type":"Point"}
}