{
  "type": "Feature",
  "properties": {
    "iso:country":"ES",
    "sg:address":"C/ Gines Macia Pascual, 3",
    "sg:city":"Elche",
    "sg:orig_category":"Promotores Constructores",
    "sg:phone":"+34 965 42 50 86",
    "sg:postcode":"03203",
    "sg:province":"Alicante",
    "wof:name":"Vidal Lerma Maria Elena",
    "wof:placetype":"venue"
},
  "geometry": {"coordinates":[-0.6803330183,38.2659072876],"type":"Point"}
}