{
  "type": "Feature",
  "properties": {
    "addr:full":"Calle de Etxegorri Kalea, 2 Erandio Vizcaya 48950",
    "addr:housenumber":"2",
    "addr:postcode":"48950",
    "addr:street":"Calle De Etxegorri Kalea",
    "iso:country":"ES",
    "sg:address":"Calle de Etxegorri Kalea, 2",
    "sg:city":"Erandio",
    "sg:orig_category":"Estancos",
    "sg:phone":"+34 944 67 18 32",
    "sg:postcode":"48950",
    "sg:province":"Vizcaya",
    "wof:name":"Beatriz Gonzalez Gonzalez,",
    "wof:placetype":"venue"
},
  "geometry": {"coordinates":[-2.9846920967,43.3154258728],"type":"Point"}
}