{
  "type": "Feature",
  "properties": {
    "iso:country":"ES",
    "sg:address":"Calle de Ramon Del Valle Ballina, 5",
    "sg:city":"Villaviciosa",
    "sg:orig_category":"Ingeniero",
    "sg:phone":"+34 985 89 09 38",
    "sg:postcode":"33300",
    "sg:province":"Asturias",
    "wof:name":"Anfer Topografia C.b.",
    "wof:placetype":"venue"
},
  "geometry": {"coordinates":[-5.4322371483,43.4833641052],"type":"Point"}
}