{
  "type": "Feature",
  "properties": {
    "iso:country":"ES",
    "sg:address":"Pl Vila, 3",
    "sg:city":"Badalona",
    "sg:orig_category":"Promotores Constructores",
    "sg:phone":"+34 933 89 01 69",
    "sg:postcode":"08911",
    "sg:province":"Barcelona",
    "wof:name":"Construcciones Gior S. A.",
    "wof:placetype":"venue"
},
  "geometry": {"coordinates":[2.247410059,41.4499740601],"type":"Point"}
}