{
  "type": "Feature",
  "properties": {
    "iso:country":"ES",
    "sg:address":"Calle de San Isidro (de), 1",
    "sg:city":"Talamanca De Jarama",
    "sg:orig_category":"Quincaller\u00cda (al Por Menor)",
    "sg:phone":"+34 918 41 70 84",
    "sg:postcode":"28160",
    "sg:province":"Madrid",
    "wof:name":"Mu\u00f1oz Maldonado Jose",
    "wof:placetype":"venue"
},
  "geometry": {"coordinates":[-3.5129621029,40.7448425293],"type":"Point"}
}