{
  "type": "Feature",
  "properties": {
    "addr:full":"Zona Barrio Nuevo De Ofra, 78 Cuesta Santa Cruz De Tenerife 38320",
    "addr:housenumber":"78",
    "addr:postcode":"38320",
    "addr:street":"Cuesta Santa Cruz De",
    "iso:country":"ES",
    "sg:address":"Zona Barrio Nuevo De Ofra, 78",
    "sg:city":"Cuesta",
    "sg:orig_category":"Centros Empresariales",
    "sg:phone":"+34 922 65 83 74",
    "sg:postcode":"38320",
    "sg:province":"Santa Cruz De Tenerife",
    "wof:name":"Sociedad Cooperativa Algecar Canarias",
    "wof:placetype":"venue"
},
  "geometry": {"coordinates":[-16.2880134583,28.468454361],"type":"Point"}
}