{
  "type": "Feature",
  "properties": {
    "iso:country":"ES",
    "sg:address":"Plaza Marina, 11",
    "sg:city":"Cari\u00f1o",
    "sg:orig_category":"Estancos",
    "sg:phone":"+34 981 40 51 89",
    "sg:postcode":"15360",
    "sg:province":"La Coru\u00f1a",
    "wof:name":"Pe\u00f1a Ramil Antonia",
    "wof:placetype":"venue"
},
  "geometry": {"coordinates":[-7.8683691025,43.7413787842],"type":"Point"}
}