{
  "type": "Feature",
  "properties": {
    "addr:full":"Pase Castellana, 133 Madrid Madrid 28046",
    "addr:housenumber":"133",
    "addr:postcode":"28046",
    "addr:street":"Castellana",
    "iso:country":"ES",
    "sg:address":"Pase Castellana, 133",
    "sg:city":"Madrid",
    "sg:orig_category":"Propiedad Industrial: Patentes De Inventos, Marcas, Modelos, Dise\u00d1os",
    "sg:phone":"+34 915 55 65 34",
    "sg:postcode":"28046",
    "sg:province":"Madrid",
    "wof:name":"Grupo Fomento Multimedia S.l.",
    "wof:placetype":"venue"
},
  "geometry": {"coordinates":[-3.6906349659,40.4582290649],"type":"Point"}
}