{
  "type": "Feature",
  "properties": {
    "addr:full":"Calle de Guadiana, 16 Villarrubia C\u00f3rdoba 14710",
    "addr:housenumber":"16",
    "addr:postcode":"14710",
    "addr:street":"Calle De Guadiana;Co\u0301Rdoba",
    "iso:country":"ES",
    "sg:address":"Calle de Guadiana, 16",
    "sg:city":"Villarrubia",
    "sg:orig_category":"Ayuda En Tareas Dom\u00c9sticas, Ayuda A Domicilio",
    "sg:phone":"+34 957 45 85 51",
    "sg:postcode":"14710",
    "sg:province":"C\u00f3rdoba",
    "wof:name":"Arteclinic S.l.",
    "wof:placetype":"venue"
},
  "geometry": {"coordinates":[-4.915345192,37.848526001],"type":"Point"}
}