{
  "type": "Feature",
  "properties": {
    "iso:country":"ES",
    "sg:address":"Calle de Berio Kalea, 4",
    "sg:city":"Irun",
    "sg:orig_category":"Tapicer\u00cdas",
    "sg:phone":"+34 943 62 15 14",
    "sg:postcode":"20303",
    "sg:province":"Guip\u00f9zcoa",
    "wof:name":"Diaz Rodriguez, Santiago",
    "wof:placetype":"venue"
},
  "geometry": {"coordinates":[-1.7900370359,43.3332366943],"type":"Point"}
}