{
  "type": "Feature",
  "properties": {
    "iso:country":"ES",
    "sg:address":"Carrer de La Palma, 60",
    "sg:city":"Sabadell",
    "sg:orig_category":"Alimentaci\u00d3n General (al Por Menor)",
    "sg:phone":"+34 937 26 55 45",
    "sg:postcode":"08205",
    "sg:province":"Barcelona",
    "wof:name":"Asador De La Vila Scp",
    "wof:placetype":"venue"
},
  "geometry": {"coordinates":[2.0877139568,41.5446434021],"type":"Point"}
}