{
  "type": "Feature",
  "properties": {
    "addr:full":"c/ Luchana 23, 4\u00aa Pl. Madrid 28010",
    "addr:housenumber":"23",
    "addr:postcode":"28010",
    "addr:street":"C / Luchana",
    "iso:country":"ES",
    "sg:address":"c/ Luchana 23, 4\u00aa Pl.",
    "sg:city":"Madrid",
    "sg:classifiers":[
        {
            "category":"Professional",
            "subcategory":"Computer Services",
            "type":"Services"
        }
    ],
    "sg:postcode":"28010",
    "sg:tags":[
        "twitter",
        "poewnce",
        "microbloguing"
    ],
    "sg:website":"http://www.mohook.com",
    "wof:name":"Mohook.com",
    "wof:placetype":"venue"
},
  "geometry": {"coordinates":[-3.6997749,40.4308366],"type":"Point"}
}