{
  "type": "Feature",
  "properties": {
    "addr:full":"Avgd Artesa, 66 Lleida Lleida 25001",
    "addr:housenumber":"66",
    "addr:postcode":"25001",
    "addr:street":"Artesa",
    "iso:country":"ES",
    "sg:address":"Avgd Artesa, 66",
    "sg:city":"Lleida",
    "sg:orig_category":"Venta, Instalaci\u00d3n De Calefacci\u00d3n",
    "sg:phone":"+34 973 20 62 82",
    "sg:postcode":"25001",
    "sg:province":"Lleida",
    "wof:name":"Velez-sanchez S.c.c.l.",
    "wof:placetype":"venue"
},
  "geometry": {"coordinates":[0.6434760094,41.5998764038],"type":"Point"}
}