{
  "type": "Feature",
  "properties": {
    "addr:full":"Avgd Garrigues, 58 Lleida Lleida 25001",
    "addr:housenumber":"58",
    "addr:postcode":"25001",
    "iso:country":"ES",
    "sg:address":"Avgd Garrigues, 58",
    "sg:city":"Lleida",
    "sg:orig_category":"Mec\u00c1nico Del Autom\u00d3vil",
    "sg:phone":"+34 973 21 10 24",
    "sg:postcode":"25001",
    "sg:province":"Lleida",
    "wof:name":"Dios Gari Antonio Carlos De",
    "wof:placetype":"venue"
},
  "geometry": {"coordinates":[0.6333960295,41.6099777222],"type":"Point"}
}