{
  "type": "Feature",
  "properties": {
    "addr:full":"Praz Exilio, S/n Porto De Santa Cruz La Coru\u00f1a 15179",
    "addr:housenumber":"s",
    "addr:postcode":"15179",
    "addr:street":"Praz Exilio;/ N;Corun\u0303A",
    "iso:country":"ES",
    "sg:address":"Praz Exilio, S/n",
    "sg:city":"Porto De Santa Cruz",
    "sg:orig_category":"Sociedades, Compa\u00d1\u00cdas Aseguradoras",
    "sg:phone":"+34 981 62 68 91",
    "sg:postcode":"15179",
    "sg:province":"La Coru\u00f1a",
    "wof:name":"Mapfre Servicios De Informatica",
    "wof:placetype":"venue"
},
  "geometry": {"coordinates":[-8.3444890976,43.3433189392],"type":"Point"}
}