{
  "type": "Feature",
  "properties": {
    "addr:full":"Calle de Ra Carretera, S/n Castillazuelo Huesca 22313",
    "addr:postcode":"22313",
    "addr:street":"Calle De Ra Carretera S / N Castillazuelo",
    "iso:country":"ES",
    "sg:address":"Calle de Ra Carretera, S/n",
    "sg:city":"Castillazuelo",
    "sg:orig_category":"Empresas De Carpinter\u00cda Met\u00c1lica",
    "sg:phone":"+34 974 30 22 60",
    "sg:postcode":"22313",
    "sg:province":"Huesca",
    "wof:name":"Broto Baron Antonio",
    "wof:placetype":"venue"
},
  "geometry": {"coordinates":[0.0657199994,42.0705718994],"type":"Point"}
}