{
  "type": "Feature",
  "properties": {
    "addr:full":"Calle de Alfarerias, S/n Huercal-overa Almer\u00eda 04600",
    "addr:housenumber":"s / n",
    "addr:postcode":"04600",
    "addr:street":"Calle De Alfarerias;Almeri\u0301A",
    "iso:country":"ES",
    "sg:address":"Calle de Alfarerias, S/n",
    "sg:city":"Huercal-overa",
    "sg:orig_category":"Promotores Constructores",
    "sg:phone":"+34 950 13 55 97",
    "sg:postcode":"04600",
    "sg:province":"Almer\u00eda",
    "wof:name":"Construcciones Amosur",
    "wof:placetype":"venue"
},
  "geometry": {"coordinates":[-1.9443919659,37.385799408],"type":"Point"}
}