{
  "type": "Feature",
  "properties": {
    "addr:full":"Carrer de Salvador Espriu, 38 Papiol Barcelona 08754",
    "addr:housenumber":"38",
    "addr:postcode":"08754",
    "addr:street":"Carrer De Salvador Espriu",
    "iso:country":"ES",
    "sg:address":"Carrer de Salvador Espriu, 38",
    "sg:city":"Papiol",
    "sg:orig_category":"Construcciones Met\u00c1licas",
    "sg:phone":"+34 936 73 05 68",
    "sg:postcode":"08754",
    "sg:province":"Barcelona",
    "wof:name":"Rodriguez Cespedes Hector",
    "wof:placetype":"venue"
},
  "geometry": {"coordinates":[2.0078630447,41.4300498962],"type":"Point"}
}