{
  "type": "Feature",
  "properties": {
    "addr:full":"Calle de Alcalde Andres Vilchez, 13 Malaga M\u00e1laga 29006",
    "addr:housenumber":"13",
    "addr:postcode":"29006",
    "addr:street":"Calle De Alcalde Andres Vilchez;Ma\u0301Laga",
    "iso:country":"ES",
    "sg:address":"Calle de Alcalde Andres Vilchez, 13",
    "sg:city":"Malaga",
    "sg:orig_category":"Vinos (agentes)",
    "sg:phone":"+34 902 15 74 03",
    "sg:postcode":"29006",
    "sg:province":"M\u00e1laga",
    "sg:website":"www.dng-disnagar.com",
    "wof:name":"Distribuciones Disnagar S.l.",
    "wof:placetype":"venue"
},
  "geometry": {"coordinates":[-4.4742217064,36.7091255188],"type":"Point"}
}