{
  "type": "Feature",
  "properties": {
    "addr:full":"Coronel Alfonso Beorlegui, 43 Iru\u00f1a Navarra 31015",
    "addr:housenumber":"43",
    "addr:postcode":"31015",
    "addr:street":"Coronel Alfonso Beorlegui",
    "iso:country":"ES",
    "sg:address":"Coronel Alfonso Beorlegui, 43",
    "sg:city":"Iru\u00f1a",
    "sg:orig_category":"Frutas, Legumbres Frescas Y Tempranas (al Por Menor)",
    "sg:phone":"+34 948 12 49 68",
    "sg:postcode":"31015",
    "sg:province":"Navarra",
    "wof:name":"Valero Lafoz S.l.",
    "wof:placetype":"venue"
},
  "geometry": {"coordinates":[-1.6437540054,42.81275177],"type":"Point"}
}