{
  "type": "Feature",
  "properties": {
    "addr:full":"Calle de Doctor Aquilino Hurle, 25 Gijon Asturias 33202",
    "addr:housenumber":"25",
    "addr:postcode":"33202",
    "addr:street":"Calle De Doctor Aquilino Hurle",
    "iso:country":"ES",
    "sg:address":"Calle de Doctor Aquilino Hurle, 25",
    "sg:city":"Gijon",
    "sg:orig_category":"Alumbrados",
    "sg:phone":"+34 985 37 40 28",
    "sg:postcode":"33202",
    "sg:province":"Asturias",
    "wof:name":"Diaz Quintanilla Jose Luis",
    "wof:placetype":"venue"
},
  "geometry": {"coordinates":[-5.648393631,43.5383071899],"type":"Point"}
}