{
  "type": "Feature",
  "properties": {
    "iso:country":"ES",
    "sg:address":"Calle de Eguren Enrique, 3",
    "sg:city":"Bilbao",
    "sg:orig_category":"Ropa Para Ni\u00d1os (al Por Menor)",
    "sg:phone":"+34 944 21 75 80",
    "sg:postcode":"48012",
    "sg:province":"Vizcaya",
    "wof:name":"Xinduo  Lin-lin",
    "wof:placetype":"venue"
},
  "geometry": {"coordinates":[-2.9382050037,43.2569961548],"type":"Point"}
}