{
  "type": "Feature",
  "properties": {
    "addr:full":"Plaz Merced, 24 Malaga M\u00e1laga 29012",
    "addr:housenumber":"24",
    "addr:postcode":"29012",
    "addr:street":"Plaz Merced;Ma\u0301Laga",
    "iso:country":"ES",
    "sg:address":"Plaz Merced, 24",
    "sg:city":"Malaga",
    "sg:orig_category":"Arquitectos",
    "sg:phone":"+34 952 21 89 64",
    "sg:postcode":"29012",
    "sg:province":"M\u00e1laga",
    "wof:name":"Riera Moreno Joaquin",
    "wof:placetype":"venue"
},
  "geometry": {"coordinates":[-4.4171710014,36.7229385376],"type":"Point"}
}