{
  "type": "Feature",
  "properties": {
    "addr:full":"Carr Alcota, L', 23 Quart Poblet Valencia 46930",
    "addr:housenumber":"23",
    "addr:postcode":"46930",
    "addr:street":"Carr Alcota L ';Poblet",
    "iso:country":"ES",
    "sg:address":"Carr Alcota, L', 23",
    "sg:city":"Quart Poblet",
    "sg:orig_category":"Renovaci\u00d3n Inmobiliaria",
    "sg:phone":"+34 961 54 18 96",
    "sg:postcode":"46930",
    "sg:province":"Valencia",
    "wof:name":"Loft Europa S.l",
    "wof:placetype":"venue"
},
  "geometry": {"coordinates":[-0.4446136057,39.4841575623],"type":"Point"}
}