{
  "type": "Feature",
  "properties": {
    "addr:full":"Calle de Norte, 22 Villarquemado Teruel 44380",
    "addr:housenumber":"22",
    "addr:postcode":"44380",
    "addr:street":"Calle De Norte",
    "iso:country":"ES",
    "sg:address":"Calle de Norte, 22",
    "sg:city":"Villarquemado",
    "sg:orig_category":"Adaptaciones, Acondicionamientos Especiales Para Veh\u00cdculos, Veh\u00cdculos Industriales",
    "sg:phone":"+34 978 86 73 49",
    "sg:postcode":"44380",
    "sg:province":"Teruel",
    "wof:name":"Guillen Lopez Angel",
    "wof:placetype":"venue"
},
  "geometry": {"coordinates":[-1.2652299404,40.5196418762],"type":"Point"}
}