{
  "type": "Feature",
  "properties": {
    "addr:full":"C/ Montcada, 77 Ripollet Barcelona 08291",
    "addr:housenumber":"77",
    "addr:postcode":"08291",
    "addr:street":"C / Montcada",
    "iso:country":"ES",
    "sg:address":"C/ Montcada, 77",
    "sg:city":"Ripollet",
    "sg:classifiers":[
        {
            "category":"Shopping",
            "subcategory":"Clothing, Apparel, & Fashions",
            "type":"Retail Goods"
        }
    ],
    "sg:phone":"+34 902 11 76 99",
    "sg:postcode":"08291",
    "sg:province":"Barcelona",
    "sg:tags":[
        "boutique"
    ],
    "wof:name":"Delta Packet Valles S.l.",
    "wof:placetype":"venue"
},
  "geometry": {"coordinates":[2.1623771191,41.4949035645],"type":"Point"}
}