{
  "type": "Feature",
  "properties": {
    "iso:country":"ES",
    "sg:address":"Av Alemanya, 15",
    "sg:city":"Palma",
    "sg:orig_category":"M\u00c9dicos: Estomatolog\u00cda",
    "sg:phone":"+34 971 72 68 14",
    "sg:postcode":"07003",
    "sg:province":"Islas Baleares",
    "wof:name":"Jaume Maimo Alejandro",
    "wof:placetype":"venue"
},
  "geometry": {"coordinates":[2.6471197605,39.5766868591],"type":"Point"}
}