{
  "type": "Feature",
  "properties": {
    "addr:full":"Plaz Salamero, 14 Zaragoza Zaragoza 50004",
    "addr:housenumber":"14",
    "addr:postcode":"50004",
    "addr:street":"Plaz Salamero",
    "iso:country":"ES",
    "sg:address":"Plaz Salamero, 14",
    "sg:city":"Zaragoza",
    "sg:orig_category":"Asesor\u00cda Sobre Comunicaci\u00d3n De Empresas",
    "sg:phone":"+34 976 23 73 00",
    "sg:postcode":"50004",
    "sg:province":"Zaragoza",
    "wof:name":"Servicio De Asistencia Empresarial S. L.",
    "wof:placetype":"venue"
},
  "geometry": {"coordinates":[-0.8840969801,41.6527633667],"type":"Point"}
}