{
  "type": "Feature",
  "properties": {
    "addr:full":"Calle de Alcalde Gomez Gomez, 75 Malaga M\u00e1laga 29006",
    "addr:housenumber":"75",
    "addr:postcode":"29006",
    "addr:street":"Calle De Alcalde Gomez Gomez;Ma\u0301Laga",
    "iso:country":"ES",
    "sg:address":"Calle de Alcalde Gomez Gomez, 75",
    "sg:city":"Malaga",
    "sg:orig_category":"Mec\u00c1nico Del Autom\u00d3vil",
    "sg:phone":"+34 952 31 64 15",
    "sg:postcode":"29006",
    "sg:province":"M\u00e1laga",
    "wof:name":"Talleres De Ambulancias Malague\u00f1as S.l.",
    "wof:placetype":"venue"
},
  "geometry": {"coordinates":[-4.4840512276,36.7105331421],"type":"Point"}
}