{
  "type": "Feature",
  "properties": {
    "iso:country":"ES",
    "sg:address":"Calle de Joaquin Jorge Alarcon, 49",
    "sg:city":"Madrid",
    "sg:orig_category":"Guarder\u00cdas",
    "sg:phone":"+34 913 16 31 40",
    "sg:postcode":"28035",
    "sg:province":"Madrid",
    "wof:name":"Ense\u00f1anza Infantil Garabatos S.l.",
    "wof:placetype":"venue"
},
  "geometry": {"coordinates":[-3.723056078,40.4770965576],"type":"Point"}
}