{
  "type": "Feature",
  "properties": {
    "iso:country":"ES",
    "sg:address":"Calle de Mesones, 10",
    "sg:city":"Priego Cordoba",
    "sg:orig_category":"M\u00c9dicos: Estomatolog\u00cda",
    "sg:phone":"+34 957 54 23 48",
    "sg:postcode":"14800",
    "sg:province":"C\u00f3rdoba",
    "wof:name":"Peix Santos Manuel",
    "wof:placetype":"venue"
},
  "geometry": {"coordinates":[-4.1933941841,37.4383811951],"type":"Point"}
}