{
  "type": "Feature",
  "properties": {
    "iso:country":"ES",
    "sg:address":"Av Montserrat, 49",
    "sg:city":"Lli\u00e7a Vall",
    "sg:orig_category":"Inmobiliaria (agencias)",
    "sg:phone":"+34 938 43 83 00",
    "sg:postcode":"08185",
    "sg:province":"Barcelona",
    "wof:name":"Intercasa Gestion Inmobiliaria S.l.",
    "wof:placetype":"venue"
},
  "geometry": {"coordinates":[2.2421369553,41.5886650085],"type":"Point"}
}