{
  "type": "Feature",
  "properties": {
    "iso:country":"ES",
    "sg:address":"Calle de Lago Enol, 4",
    "sg:city":"Rivas Vaciamadrid",
    "sg:orig_category":"Agencias Y Agentes Comerciales, Representantes",
    "sg:phone":"+34 916 70 39 00",
    "sg:postcode":"28529",
    "sg:province":"Madrid",
    "wof:name":"Gonzalez Fernandez Cristina",
    "wof:placetype":"venue"
},
  "geometry": {"coordinates":[-3.5075750351,40.3293762207],"type":"Point"}
}