{
  "type": "Feature",
  "properties": {
    "addr:full":"Calle de Daoiz, 24 Bollullos Par Condado Huelva 21710",
    "addr:housenumber":"24",
    "addr:postcode":"21710",
    "addr:street":"Calle De Daoiz",
    "iso:country":"ES",
    "sg:address":"Calle de Daoiz, 24",
    "sg:city":"Bollullos Par Condado",
    "sg:orig_category":"Fabricaci\u00d3n De Muebles",
    "sg:phone":"+34 959 40 80 08",
    "sg:postcode":"21710",
    "sg:province":"Huelva",
    "wof:name":"Fabrica De Muebles Santos S.l.",
    "wof:placetype":"venue"
},
  "geometry": {"coordinates":[-6.5387368202,37.3369560242],"type":"Point"}
}