{
  "type": "Feature",
  "properties": {
    "addr:full":"Bardanca(sisamo), 5 Bardanca La Coru\u00f1a 15106",
    "addr:housenumber":"5",
    "addr:postcode":"15106",
    "addr:street":"Sisamo;La Corun\u0303A",
    "iso:country":"ES",
    "sg:address":"Bardanca(sisamo), 5",
    "sg:city":"Bardanca",
    "sg:orig_category":"Promotores Constructores",
    "sg:phone":"+34 981 70 14 18",
    "sg:postcode":"15106",
    "sg:province":"La Coru\u00f1a",
    "wof:name":"Gomez Couto Jose",
    "wof:placetype":"venue"
},
  "geometry": {"coordinates":[-8.7134256363,43.2131004333],"type":"Point"}
}