{
  "type": "Feature",
  "properties": {
    "addr:full":"Cami Ral, 221 Mataro Barcelona 08301",
    "addr:housenumber":"221",
    "addr:postcode":"08301",
    "addr:street":"Ral",
    "iso:country":"ES",
    "sg:address":"Cami Ral, 221",
    "sg:city":"Mataro",
    "sg:orig_category":"Bordado, Marcado A Medida",
    "sg:phone":"+34 937 90 39 25",
    "sg:postcode":"08301",
    "sg:province":"Barcelona",
    "wof:name":"Berga Pla Jordi",
    "wof:placetype":"venue"
},
  "geometry": {"coordinates":[2.449764967,41.5392456055],"type":"Point"}
}