{
  "type": "Feature",
  "properties": {
    "addr:full":"Avda Independencia (de La), 36 S. Jose Valle C\u00e1diz 11580",
    "addr:housenumber":"36",
    "addr:postcode":"11580",
    "addr:street":"Avda Independencia De La;Ca\u0301Diz",
    "iso:country":"ES",
    "sg:address":"Avda Independencia (de La), 36",
    "sg:city":"S. Jose Valle",
    "sg:orig_category":"T\u00c9cnicos Veterinarios",
    "sg:phone":"+34 956 16 01 40",
    "sg:postcode":"11580",
    "sg:province":"C\u00e1diz",
    "wof:name":"Salinas Garrido Alvaro",
    "wof:placetype":"venue"
},
  "geometry": {"coordinates":[-5.7983422279,36.6039848328],"type":"Point"}
}