{
  "type": "Feature",
  "properties": {
    "addr:full":"Avda Virgen De Los Dolores, 9 Cordoba C\u00f3rdoba 14004",
    "addr:housenumber":"9",
    "addr:postcode":"14004",
    "addr:street":"Avda Virgen De Los Dolores;Co\u0301Rdoba",
    "iso:country":"ES",
    "sg:address":"Avda Virgen De Los Dolores, 9",
    "sg:city":"Cordoba",
    "sg:orig_category":"Peluqueros: De Se\u00d1oras",
    "sg:phone":"+34 957 23 02 72",
    "sg:postcode":"14004",
    "sg:province":"C\u00f3rdoba",
    "wof:name":"Nieto Moreno Maria Del Carmen",
    "wof:placetype":"venue"
},
  "geometry": {"coordinates":[-4.7957692146,37.8745536804],"type":"Point"}
}