{
  "type": "Feature",
  "properties": {
    "addr:full":"Calle de Francisco Franco, 4 Tapia Casariego Asturias 33740",
    "addr:housenumber":"4",
    "addr:postcode":"33740",
    "addr:street":"Calle De Francisco Franco;Casariego",
    "iso:country":"ES",
    "sg:address":"Calle de Francisco Franco, 4",
    "sg:city":"Tapia Casariego",
    "sg:orig_category":"Peluqueros: De Se\u00d1oras",
    "sg:phone":"+34 985 62 82 22",
    "sg:postcode":"33740",
    "sg:province":"Asturias",
    "wof:name":"Lopez Garcia Ana Maria",
    "wof:placetype":"venue"
},
  "geometry": {"coordinates":[-6.9456739426,43.5698280334],"type":"Point"}
}