{
  "type": "Feature",
  "properties": {
    "addr:full":"Calle de Ba\u00d1er De Salcedo, S/n Sevilla Sevilla 41014",
    "addr:housenumber":"s / n",
    "addr:postcode":"41014",
    "addr:street":"Calle De Ban\u0303Er De Salcedo",
    "iso:country":"ES",
    "sg:address":"Calle de Ba\u00d1er De Salcedo, S/n",
    "sg:city":"Sevilla",
    "sg:orig_category":"Cajas De Ahorro",
    "sg:phone":"+34 954 68 92 16",
    "sg:postcode":"41014",
    "sg:province":"Sevilla",
    "wof:name":"Unicaja",
    "wof:placetype":"venue"
},
  "geometry": {"coordinates":[-5.9689540863,37.3224945068],"type":"Point"}
}