{
  "type": "Feature",
  "properties": {
    "addr:full":"Grup Miramar, 1 Sestao Vizcaya 48910",
    "addr:housenumber":"1",
    "addr:postcode":"48910",
    "addr:street":"Miramar",
    "iso:country":"ES",
    "sg:address":"Grup Miramar, 1",
    "sg:city":"Sestao",
    "sg:orig_category":"Instalaci\u00d3n De Aspiraci\u00d3n De Gases Y Humos",
    "sg:phone":"+34 944 72 04 78",
    "sg:postcode":"48910",
    "sg:province":"Vizcaya",
    "sg:website":"www.tamesgas.es.vg",
    "wof:name":"Tamesgas Sl",
    "wof:placetype":"venue"
},
  "geometry": {"coordinates":[-3.0116350651,43.31275177],"type":"Point"}
}