{
  "type": "Feature",
  "properties": {
    "iso:country":"ES",
    "sg:address":"Avda Estella, 3",
    "sg:city":"Tafalla",
    "sg:orig_category":"Agencias Y Agentes Comerciales, Representantes",
    "sg:phone":"+34 948 70 44 02",
    "sg:postcode":"31300",
    "sg:province":"Navarra",
    "wof:name":"Esquiroz Esquiroz Jesus",
    "wof:placetype":"venue"
},
  "geometry": {"coordinates":[-1.6780869961,42.526348114],"type":"Point"}
}