{
  "type": "Feature",
  "properties": {
    "iso:country":"ES",
    "sg:address":"Psaj Playa De Las Alcaravaneras, 6",
    "sg:city":"Puertillo",
    "sg:orig_category":"Electricidad: Instaladores",
    "sg:phone":"+34 928 62 64 00",
    "sg:postcode":"35414",
    "sg:province":"Las Palmas",
    "wof:name":"Hernandez Rivero Luis",
    "wof:placetype":"venue"
},
  "geometry": {"coordinates":[-15.5317401886,28.146730423],"type":"Point"}
}