{
  "type": "Feature",
  "properties": {
    "iso:country":"ES",
    "sg:address":"Pase Francisco Mir Berlanga, Maritimo, S/n",
    "sg:city":"Melilla",
    "sg:orig_category":"Fabricaci\u00d3n De Enlosados, Soler\u00cdas",
    "sg:phone":"+34 952 69 61 74",
    "sg:postcode":"52006",
    "sg:province":"Melilla",
    "wof:name":"Melilla Ceramicas S.a.",
    "wof:placetype":"venue"
},
  "geometry": {"coordinates":[-2.9383699894,35.2764587402],"type":"Point"}
}