{
  "type": "Feature",
  "properties": {
    "addr:full":"Calle de Covachuelas, 16 Toledo Toledo 45003",
    "addr:housenumber":"16",
    "addr:postcode":"45003",
    "addr:street":"Calle De Covachuelas",
    "iso:country":"ES",
    "sg:address":"Calle de Covachuelas, 16",
    "sg:city":"Toledo",
    "sg:orig_category":"Asesor\u00cda Sobre Comunicaci\u00d3n De Empresas",
    "sg:phone":"+34 925 22 23 62",
    "sg:postcode":"45003",
    "sg:province":"Toledo",
    "sg:website":"www.infonegocio.com/ferdise",
    "wof:name":"Ferdise Asesores S.l.",
    "wof:placetype":"venue"
},
  "geometry": {"coordinates":[-4.0223350525,39.8641242981],"type":"Point"}
}