{
  "type": "Feature",
  "properties": {
    "iso:country":"ES",
    "sg:address":"Carr Ramon Muntaner, 73",
    "sg:city":"Eivissa",
    "sg:orig_category":"Regalos, Souvenires (fabricaci\u00d3n, Al Por Mayor)",
    "sg:phone":"+34 971 30 51 70",
    "sg:postcode":"07800",
    "sg:province":"Islas Baleares",
    "wof:name":"Tur Escandell Josefa",
    "wof:placetype":"venue"
},
  "geometry": {"coordinates":[1.4288929701,38.9045448303],"type":"Point"}
}