{
  "type": "Feature",
  "properties": {
    "iso:country":"ES",
    "sg:address":"Carr Sant Jordi, 11",
    "sg:city":"S. Hilari Sacalm",
    "sg:orig_category":"Tapicer\u00cdas",
    "sg:phone":"+34 972 86 83 33",
    "sg:postcode":"17403",
    "sg:province":"Girona",
    "wof:name":"Cuberta Rique Jorge",
    "wof:placetype":"venue"
},
  "geometry": {"coordinates":[2.5119540691,41.8778266907],"type":"Point"}
}