{
  "type": "Feature",
  "properties": {
    "addr:full":"Calle de Ruperto Andues, 13 Nerja M\u00e1laga 29780",
    "addr:housenumber":"13",
    "addr:postcode":"29780",
    "addr:street":"Calle De Ruperto Andues",
    "iso:country":"ES",
    "sg:address":"Calle de Ruperto Andues, 13",
    "sg:city":"Nerja",
    "sg:orig_category":"Mec\u00c1nico Del Autom\u00d3vil",
    "sg:phone":"+34 952 52 26 65",
    "sg:postcode":"29780",
    "sg:province":"M\u00e1laga",
    "wof:name":"Autojosoria S.l.",
    "wof:placetype":"venue"
},
  "geometry": {"coordinates":[-3.8746399879,36.7513465881],"type":"Point"}
}