{
  "type": "Feature",
  "properties": {
    "addr:full":"Avda Mar Mediterraneo, 12 Leganes Madrid 28913",
    "addr:housenumber":"12",
    "addr:postcode":"28913",
    "addr:street":"Avda Mar Mediterraneo",
    "iso:country":"ES",
    "sg:address":"Avda Mar Mediterraneo, 12",
    "sg:city":"Leganes",
    "sg:orig_category":"Bibliotecas, Mediatecas",
    "sg:phone":"+34 916 80 31 25",
    "sg:postcode":"28913",
    "sg:province":"Madrid",
    "wof:name":"Ayuntamiento De Leganes",
    "wof:placetype":"venue"
},
  "geometry": {"coordinates":[-3.7640779018,40.3360176086],"type":"Point"}
}