{
  "type": "Feature",
  "properties": {
    "iso:country":"ES",
    "sg:address":"Avda Ejercito Y Marina, 7",
    "sg:city":"Marin",
    "sg:orig_category":"Imprenta",
    "sg:phone":"+34 986 88 02 20",
    "sg:postcode":"36900",
    "sg:province":"Pontevedra",
    "wof:name":"Amoedo Rodriguez Rosendo",
    "wof:placetype":"venue"
},
  "geometry": {"coordinates":[-8.7050714493,42.3915939331],"type":"Point"}
}