{
  "type": "Feature",
  "properties": {
    "iso:country":"ES",
    "sg:address":"Carr Sant Iscle, 5",
    "sg:city":"Breda",
    "sg:orig_category":"Inmobiliaria (agencias)",
    "sg:phone":"+34 972 87 14 06",
    "sg:postcode":"17400",
    "sg:province":"Girona",
    "wof:name":"Pladevall Gracia Montserrat",
    "wof:placetype":"venue"
},
  "geometry": {"coordinates":[2.5570130348,41.7480163574],"type":"Point"}
}