{
  "type": "Feature",
  "properties": {
    "addr:full":"Carrer de Historiador Cardus, 125 Terrassa Barcelona 08226",
    "addr:housenumber":"125",
    "addr:postcode":"08226",
    "addr:street":"Carrer De Historiador Cardus",
    "iso:country":"ES",
    "sg:address":"Carrer de Historiador Cardus, 125",
    "sg:city":"Terrassa",
    "sg:orig_category":"Charcuter\u00cdas (al Por Mayor)",
    "sg:phone":"+34 937 83 35 06",
    "sg:postcode":"08226",
    "sg:province":"Barcelona",
    "wof:name":"Jamones Manolo S.l.",
    "wof:placetype":"venue"
},
  "geometry": {"coordinates":[2.0242860317,41.5752944946],"type":"Point"}
}