{
  "type": "Feature",
  "properties": {
    "addr:full":"Ctra Malilla, 80 Valencia Valencia 46026",
    "addr:housenumber":"80",
    "addr:postcode":"46026",
    "addr:street":"Ctra Malilla",
    "iso:country":"ES",
    "sg:address":"Ctra Malilla, 80",
    "sg:city":"Valencia",
    "sg:orig_category":"Asociaciones Y Clubs Deportivos",
    "sg:phone":"+34 963 73 03 71",
    "sg:postcode":"46026",
    "sg:province":"Valencia",
    "wof:name":"Garcia Fores Maria Vicenta",
    "wof:placetype":"venue"
},
  "geometry": {"coordinates":[-0.3796899915,39.4487190247],"type":"Point"}
}