{
  "type": "Feature",
  "properties": {
    "iso:country":"ES",
    "sg:address":"Herriko Etxea Plaza, 11",
    "sg:city":"Bera",
    "sg:orig_category":"Plomeros",
    "sg:phone":"+34 948 63 00 02",
    "sg:postcode":"31780",
    "sg:province":"Navarra",
    "wof:name":"Echeveste Beovide Eduardo",
    "wof:placetype":"venue"
},
  "geometry": {"coordinates":[-1.6813839674,43.2808914185],"type":"Point"}
}