{
  "type": "Feature",
  "properties": {
    "addr:full":"Ctra Andalucia, Km. 0036,0 Sese\u00e7a Nuevo Toledo 45224",
    "addr:postcode":"45224",
    "addr:street":"Ctra Andalucia Km. 0036,0 Sesec\u0327A",
    "iso:country":"ES",
    "sg:address":"Ctra Andalucia, Km. 0036,0",
    "sg:city":"Sese\u00e7a Nuevo",
    "sg:orig_category":"Transporte En General",
    "sg:phone":"+34 918 93 66 40",
    "sg:postcode":"45224",
    "sg:province":"Toledo",
    "sg:website":"www.glortiz.com",
    "wof:name":"Aldisbar S.l.",
    "wof:placetype":"venue"
},
  "geometry": {"coordinates":[-4.0244760513,39.8567771912],"type":"Point"}
}