{
  "type": "Feature",
  "properties": {
    "addr:full":"Pol Ind Urbayecla, S/n Yecla Murcia 30510",
    "addr:housenumber":"s / n",
    "addr:postcode":"30510",
    "iso:country":"ES",
    "sg:address":"Pol Ind Urbayecla, S/n",
    "sg:city":"Yecla",
    "sg:orig_category":"Art\u00cdculos De Madera (fabricaci\u00d3n Y Al Por Mayor)",
    "sg:phone":"+34 968 71 90 71",
    "sg:postcode":"30510",
    "sg:province":"Murcia",
    "sg:website":"www.nogalyecla.com",
    "wof:name":"Muebles Nogal Yecla S.l.",
    "wof:placetype":"venue"
},
  "geometry": {"coordinates":[-1.1149940491,38.6145591736],"type":"Point"}
}