{
  "type": "Feature",
  "properties": {
    "addr:full":"Calle de Resina, 3 Cuellar Segovia 40200",
    "addr:housenumber":"3",
    "addr:postcode":"40200",
    "addr:street":"Calle De Resina",
    "iso:country":"ES",
    "sg:address":"Calle de Resina, 3",
    "sg:city":"Cuellar",
    "sg:orig_category":"Quincaller\u00cda (al Por Menor)",
    "sg:phone":"+34 921 14 17 97",
    "sg:postcode":"40200",
    "sg:province":"Segovia",
    "wof:name":"Aguado Santos Tomas",
    "wof:placetype":"venue"
},
  "geometry": {"coordinates":[-4.3107352257,41.3990592957],"type":"Point"}
}