{
  "type": "Feature",
  "properties": {
    "iso:country":"ES",
    "sg:address":"Carrer de Bruixa, 30",
    "sg:city":"Barcelona",
    "sg:orig_category":"Organizaciones Profesionales",
    "sg:phone":"+34 934 09 33 87",
    "sg:postcode":"08014",
    "sg:province":"Barcelona",
    "wof:name":"Zamora Terres Juan",
    "wof:placetype":"venue"
},
  "geometry": {"coordinates":[2.1325352192,41.3840904236],"type":"Point"}
}