{
  "type": "Feature",
  "properties": {
    "iso:country":"ES",
    "sg:address":"Calle de Iglesia, 15",
    "sg:city":"Herrumblar",
    "sg:orig_category":"M\u00dasicos Int\u00c9rpretes",
    "sg:phone":"+34 962 31 30 28",
    "sg:postcode":"16290",
    "sg:province":"Cuenca",
    "wof:name":"Sanglada Guillamon Julia",
    "wof:placetype":"venue"
},
  "geometry": {"coordinates":[-1.6225379705,39.402015686],"type":"Point"}
}