{
  "type": "Feature",
  "properties": {
    "addr:full":"Calle de Sancho Arroyo, 9 Zaragoza Zaragoza 50002",
    "addr:housenumber":"9",
    "addr:postcode":"50002",
    "addr:street":"Calle De Sancho Arroyo",
    "iso:country":"ES",
    "sg:address":"Calle de Sancho Arroyo, 9",
    "sg:city":"Zaragoza",
    "sg:orig_category":"Fabricaci\u00d3n, Distribuci\u00d3n De Material Para La Climatizaci\u00d3n, Aireaci\u00d3n Y Ventilaci\u00d3n",
    "sg:phone":"+34 976 49 86 05",
    "sg:postcode":"50002",
    "sg:province":"Zaragoza",
    "wof:name":"Climatizacion J P S.l.",
    "wof:placetype":"venue"
},
  "geometry": {"coordinates":[-0.8662520051,41.6466789246],"type":"Point"}
}