{
  "type": "Feature",
  "properties": {
    "iso:country":"ES",
    "sg:address":"Cmno Peinada (de La), 34",
    "sg:city":"Huercal Almeria",
    "sg:orig_category":"Maquinaria Para Industrias Diversas",
    "sg:phone":"+34 950 60 07 18",
    "sg:postcode":"04230",
    "sg:province":"Almer\u00eda",
    "wof:name":"Maquidoce S.l.",
    "wof:placetype":"venue"
},
  "geometry": {"coordinates":[-2.4429118633,36.8872413635],"type":"Point"}
}