{
  "type": "Feature",
  "properties": {
    "iso:country":"ES",
    "sg:address":"Avda General Fanjul, 93",
    "sg:city":"Madrid",
    "sg:orig_category":"Administradores De Bienes Y Delegados De Comunidades De Propietarios",
    "sg:phone":"+34 915 09 44 62",
    "sg:postcode":"28044",
    "sg:province":"Madrid",
    "wof:name":"Administradores Y Asesores Juridicos Asociados Atb S.l.",
    "wof:placetype":"venue"
},
  "geometry": {"coordinates":[-3.7744846344,40.3821907043],"type":"Point"}
}