{
  "type": "Feature",
  "properties": {
    "iso:country":"ES",
    "sg:address":"Calle de Covadonga, 5",
    "sg:city":"Salamanca",
    "sg:orig_category":"Fabricaci\u00d3n De Acumuladores Y De Pilas El\u00c9ctricas",
    "sg:phone":"+34 923 18 26 56",
    "sg:postcode":"37003",
    "sg:province":"Salamanca",
    "wof:name":"Ova-lux S.l.",
    "wof:placetype":"venue"
},
  "geometry": {"coordinates":[-5.6522707939,40.9637870789],"type":"Point"}
}