{
  "type": "Feature",
  "properties": {
    "iso:country":"ES",
    "sg:address":"Calle de Nueva, 1",
    "sg:city":"Marbella",
    "sg:orig_category":"Ropa Para Caballeros (al Por Menor)",
    "sg:phone":"+34 952 82 74 67",
    "sg:postcode":"29600",
    "sg:province":"M\u00e1laga",
    "sg:website":"www.baileys.nl",
    "wof:name":"Verweij Retailo International Bv",
    "wof:placetype":"venue"
},
  "geometry": {"coordinates":[-4.8847498894,36.5100212097],"type":"Point"}
}