{
  "type": "Feature",
  "properties": {
    "iso:country":"ES",
    "sg:address":"Calle de Heroes Del Seis De Junio, 27",
    "sg:city":"Valdepe\u00f1as",
    "sg:orig_category":"Agentes Generales De Seguros",
    "sg:phone":"+34 926 31 10 93",
    "sg:postcode":"13300",
    "sg:province":"Ciudad Real",
    "wof:name":"Villegas Lerida Magdalena",
    "wof:placetype":"venue"
},
  "geometry": {"coordinates":[-3.3896319866,38.7691268921],"type":"Point"}
}