{
  "type": "Feature",
  "properties": {
    "addr:full":"Calle de Perpetuo Socorro, 7 Zaragoza Zaragoza 50006",
    "addr:housenumber":"7",
    "addr:postcode":"50006",
    "addr:street":"Calle De Perpetuo Socorro",
    "iso:country":"ES",
    "sg:address":"Calle de Perpetuo Socorro, 7",
    "sg:city":"Zaragoza",
    "sg:orig_category":"Fotograf\u00cda Y Cine: Aparatos, Pel\u00cdculas Y Accesorios (fabricaci\u00d3n, Al Por Mayor)",
    "sg:phone":"+34 976 25 40 11",
    "sg:postcode":"50006",
    "sg:province":"Zaragoza",
    "wof:name":"Arpiserra S.a.",
    "wof:placetype":"venue"
},
  "geometry": {"coordinates":[-0.887832284,41.6420936584],"type":"Point"}
}