{
  "type": "Feature",
  "properties": {
    "addr:full":"Calle de Concordia, 48 Torrevieja Alicante 03180",
    "addr:housenumber":"48",
    "addr:postcode":"03180",
    "addr:street":"Calle De Concordia",
    "iso:country":"ES",
    "sg:address":"Calle de Concordia, 48",
    "sg:city":"Torrevieja",
    "sg:orig_category":"Trabajos De Fotocomposici\u00d3n",
    "sg:phone":"+34 965 71 12 95",
    "sg:postcode":"03180",
    "sg:province":"Alicante",
    "wof:name":"Ferreteria Industrial Cano S.l.",
    "wof:placetype":"venue"
},
  "geometry": {"coordinates":[-0.6776980758,37.9785308838],"type":"Point"}
}