{
  "type": "Feature",
  "properties": {
    "iso:country":"ES",
    "sg:address":"Calle de Andalucia, 5",
    "sg:city":"Linea De La Concepcion",
    "sg:orig_category":"Loter\u00cda Y T\u00d3mbola",
    "sg:phone":"+34 956 17 43 33",
    "sg:postcode":"11300",
    "sg:province":"C\u00e1diz",
    "wof:name":"Sanchez Olondriz Antonio",
    "wof:placetype":"venue"
},
  "geometry": {"coordinates":[-5.356089592,36.1662063599],"type":"Point"}
}