{
  "type": "Feature",
  "properties": {
    "iso:country":"ES",
    "sg:address":"Calle de Juan De Dios, 9",
    "sg:city":"Angeles",
    "sg:orig_category":"Aceites Y Grasas Alimentarias (fabricaci\u00d3n, Al Por Mayor)",
    "sg:phone":"+34 956 64 01 85",
    "sg:postcode":"11330",
    "sg:province":"C\u00e1diz",
    "wof:name":"Aceites La Canastera S.l.",
    "wof:placetype":"venue"
},
  "geometry": {"coordinates":[-5.4346041679,36.4242172241],"type":"Point"}
}