{
  "type": "Feature",
  "properties": {
    "addr:full":"Calle de Palafox, 17 Burgo Osma Soria 42300",
    "addr:housenumber":"17",
    "addr:postcode":"42300",
    "addr:street":"Calle De Palafox",
    "iso:country":"ES",
    "sg:address":"Calle de Palafox, 17",
    "sg:city":"Burgo Osma",
    "sg:orig_category":"Fisioterapia",
    "sg:phone":"+34 975 34 02 94",
    "sg:postcode":"42300",
    "sg:province":"Soria",
    "wof:name":"Gomez Sanz Elena",
    "wof:placetype":"venue"
},
  "geometry": {"coordinates":[-3.0707058907,41.5849456787],"type":"Point"}
}