{
  "type": "Feature",
  "properties": {
    "addr:full":"Avda Fernando Calzadilla, 29 Badajoz Badajoz 06004",
    "addr:housenumber":"29",
    "addr:postcode":"06004",
    "addr:street":"Avda Fernando Calzadilla",
    "iso:country":"ES",
    "sg:address":"Avda Fernando Calzadilla, 29",
    "sg:city":"Badajoz",
    "sg:classifiers":[
        {
            "category":"Communications",
            "type":"Services"
        }
    ],
    "sg:phone":"+34 924 24 84 81",
    "sg:postcode":"06004",
    "sg:province":"Badajoz",
    "sg:tags":[
        "televisiones",
        "y",
        "radio"
    ],
    "wof:name":"Telebadajoz S.l.",
    "wof:placetype":"venue"
},
  "geometry": {"coordinates":[-6.972878933,38.869758606],"type":"Point"}
}