{
  "type": "Feature",
  "properties": {
    "addr:full":"Calle de Gran Via, 31 Madrid Madrid 28013",
    "addr:housenumber":"31",
    "addr:postcode":"madrid;28013",
    "addr:street":"Calle De Gran Via",
    "iso:country":"ES",
    "sg:address":"Calle de Gran Via, 31",
    "sg:city":"Madrid",
    "sg:orig_category":"Ense\u00d1anza Variada",
    "sg:phone":"+34 917 01 12 25",
    "sg:postcode":"28013",
    "sg:province":"Madrid",
    "wof:name":"Global Design Factory S.l",
    "wof:placetype":"venue"
},
  "geometry": {"coordinates":[-3.7036979198,40.4200210571],"type":"Point"}
}