{
  "type": "Feature",
  "properties": {
    "addr:full":"Carr Paer Casanovas, 25 Lleida Lleida 25004",
    "addr:housenumber":"25",
    "addr:postcode":"25004",
    "addr:street":"Carr Paer Casanovas",
    "iso:country":"ES",
    "sg:address":"Carr Paer Casanovas, 25",
    "sg:city":"Lleida",
    "sg:orig_category":"Cr\u00cda De Animales",
    "sg:phone":"+34 973 23 35 67",
    "sg:postcode":"25004",
    "sg:province":"Lleida",
    "wof:name":"Ganados Montanuy S.l.",
    "wof:placetype":"venue"
},
  "geometry": {"coordinates":[0.6250299811,41.6227912903],"type":"Point"}
}