{
  "type": "Feature",
  "properties": {
    "addr:full":"Avda Gipuzkoa, 6 Irun Guip\u00f9zcoa 20302",
    "addr:housenumber":"6",
    "addr:postcode":"20302",
    "addr:street":"Avda Gipuzkoa;Guipu\u0300Zcoa",
    "iso:country":"ES",
    "sg:address":"Avda Gipuzkoa, 6",
    "sg:city":"Irun",
    "sg:orig_category":"Ingeniero",
    "sg:phone":"+34 943 00 25 84",
    "sg:postcode":"20302",
    "sg:province":"Guip\u00f9zcoa",
    "wof:name":"Telbask S.l.",
    "wof:placetype":"venue"
},
  "geometry": {"coordinates":[-1.7947659492,43.3398704529],"type":"Point"}
}