{
  "type": "Feature",
  "properties": {
    "addr:full":"Calle de Andalucia, 3 Estacion Madrid 28400",
    "addr:housenumber":"3 estacion",
    "addr:postcode":"28400",
    "addr:street":"Calle De Andalucia",
    "iso:country":"ES",
    "sg:address":"Calle de Andalucia, 3",
    "sg:city":"Estacion",
    "sg:orig_category":"Telas (al Por Mayor)",
    "sg:phone":"+34 918 50 00 76",
    "sg:postcode":"28400",
    "sg:province":"Madrid",
    "wof:name":"Cortes Del Arco Julian",
    "wof:placetype":"venue"
},
  "geometry": {"coordinates":[-3.3898994923,38.9960403442],"type":"Point"}
}