{
  "type": "Feature",
  "properties": {
    "iso:country":"ES",
    "sg:address":"Calle de Pilar (del), 25",
    "sg:city":"Montalban De Cordoba",
    "sg:orig_category":"Frutas Y Legumbres Frescas (al Por Mayor)",
    "sg:phone":"+34 957 31 01 74",
    "sg:postcode":"14548",
    "sg:province":"C\u00f3rdoba",
    "sg:website":"www.elmesto.com",
    "wof:name":"Ruz Jimenez Alfonso",
    "wof:placetype":"venue"
},
  "geometry": {"coordinates":[-4.748442173,37.5851821899],"type":"Point"}
}