{
  "type": "Feature",
  "properties": {
    "iso:country":"ES",
    "sg:address":"Calle de Virgen De Las Angustias, 35",
    "sg:city":"Almeria",
    "sg:orig_category":"Chapister\u00cda",
    "sg:phone":"+34 950 24 07 22",
    "sg:postcode":"04009",
    "sg:province":"Almer\u00eda",
    "wof:name":"Garcia Lopez Juan Jose",
    "wof:placetype":"venue"
},
  "geometry": {"coordinates":[-2.4527540207,36.8554077148],"type":"Point"}
}