{
  "type": "Feature",
  "properties": {
    "addr:full":"Calle de Alfonso Morales, 2 Irun Guip\u00f9zcoa 20303",
    "addr:housenumber":"2",
    "addr:postcode":"20303",
    "addr:street":"Calle De Alfonso Morales;Guipu\u0300Zcoa",
    "iso:country":"ES",
    "sg:address":"Calle de Alfonso Morales, 2",
    "sg:city":"Irun",
    "sg:orig_category":"Asesor\u00cda Sobre Comunicaci\u00d3n De Empresas",
    "sg:phone":"+34 943 61 44 22",
    "sg:postcode":"20303",
    "sg:province":"Guip\u00f9zcoa",
    "wof:name":"Avila Bikandi Asesores S.l.",
    "wof:placetype":"venue"
},
  "geometry": {"coordinates":[-1.79537642,43.3386268616],"type":"Point"}
}