{
  "type": "Feature",
  "properties": {
    "addr:full":"Plaz Ferial, 36 Tamames Salamanca 37600",
    "addr:housenumber":"36",
    "addr:postcode":"37600",
    "iso:country":"ES",
    "sg:address":"Plaz Ferial, 36",
    "sg:city":"Tamames",
    "sg:orig_category":"Fabrica De Charcuter\u00cda",
    "sg:phone":"+34 923 44 90 06",
    "sg:postcode":"37600",
    "sg:province":"Salamanca",
    "wof:name":"Gomez Moro Francisco",
    "wof:placetype":"venue"
},
  "geometry": {"coordinates":[-6.1020750999,40.6556167603],"type":"Point"}
}