{
  "type": "Feature",
  "properties": {
    "addr:full":"Calle de Bruno Mauricio Zabala Kalea, 5 Durango Vizcaya 48200",
    "addr:housenumber":"5",
    "addr:postcode":"48200",
    "addr:street":"Calle De Bruno Mauricio Zabala Kalea",
    "iso:country":"ES",
    "sg:address":"Calle de Bruno Mauricio Zabala Kalea, 5",
    "sg:city":"Durango",
    "sg:orig_category":"Asociaciones Y Clubs Deportivos",
    "sg:phone":"+34 946 20 33 60",
    "sg:postcode":"48200",
    "sg:province":"Vizcaya",
    "wof:name":"Gimnasio Zirkin S.l.",
    "wof:placetype":"venue"
},
  "geometry": {"coordinates":[-2.6340425014,43.167339325],"type":"Point"}
}