{
  "type": "Feature",
  "properties": {
    "addr:full":"Calle de San Marcos, 40 Priego Cordoba C\u00f3rdoba 14800",
    "addr:housenumber":"40",
    "addr:postcode":"14800",
    "addr:street":"Calle De San Marcos;Cordoba Co\u0301Rdoba",
    "iso:country":"ES",
    "sg:address":"Calle de San Marcos, 40",
    "sg:city":"Priego Cordoba",
    "sg:classifiers":[
        {
            "category":"Taxi",
            "type":"Transportation"
        }
    ],
    "sg:phone":"+34 957 70 01 73",
    "sg:postcode":"14800",
    "sg:province":"C\u00f3rdoba",
    "wof:name":"Montes Pozo Francisco De Paula",
    "wof:placetype":"venue"
},
  "geometry": {"coordinates":[-4.2000350952,37.4378089905],"type":"Point"}
}