{
  "type": "Feature",
  "properties": {
    "iso:country":"ES",
    "sg:address":"Carrer de Montseny, 48",
    "sg:city":"Manlleu",
    "sg:orig_category":"Prendas Y Chalecos De Punto (al Por Menor)",
    "sg:phone":"+34 938 50 77 83",
    "sg:postcode":"08560",
    "sg:province":"Barcelona",
    "wof:name":"Laarbi Sayo Ahamar",
    "wof:placetype":"venue"
},
  "geometry": {"coordinates":[2.2832009792,42.0036010742],"type":"Point"}
}