{
  "type": "Feature",
  "properties": {
    "iso:country":"ES",
    "sg:address":"Calle de Perdomo, 11",
    "sg:city":"Palmas De Gran Canaria",
    "sg:orig_category":"Abogados",
    "sg:phone":"+34 928 38 04 51",
    "sg:postcode":"35002",
    "sg:province":"Las Palmas",
    "wof:name":"Grande Perdomo Horacio",
    "wof:placetype":"venue"
},
  "geometry": {"coordinates":[-15.4185523987,28.1059074402],"type":"Point"}
}