{
  "type": "Feature",
  "properties": {
    "iso:country":"ES",
    "sg:address":"Barr San Roman El Somo, 39",
    "sg:city":"San Roman",
    "sg:orig_category":"Cristaler\u00cdas",
    "sg:phone":"+34 942 33 06 15",
    "sg:postcode":"39012",
    "sg:province":"Cantabria",
    "wof:name":"Cristaleria Altamira S.al.",
    "wof:placetype":"venue"
},
  "geometry": {"coordinates":[-3.8412749767,43.4640846252],"type":"Point"}
}