{
  "type": "Feature",
  "properties": {
    "addr:full":"Calle de Salamanca, 6 Carbajosa Sagrada Salamanca 37188",
    "addr:housenumber":"6",
    "addr:postcode":"37188",
    "addr:street":"Calle De Salamanca",
    "iso:country":"ES",
    "sg:address":"Calle de Salamanca, 6",
    "sg:city":"Carbajosa Sagrada",
    "sg:orig_category":"Panader\u00cdas, Panader\u00cdas",
    "sg:phone":"+34 923 20 84 06",
    "sg:postcode":"37188",
    "sg:province":"Salamanca",
    "wof:name":"Barragan Hernandez Cristina",
    "wof:placetype":"venue"
},
  "geometry": {"coordinates":[-5.6513528824,40.9337654114],"type":"Point"}
}