{
  "type": "Feature",
  "properties": {
    "iso:country":"ES",
    "sg:address":"Carr Sor Flor Ricomana, 15",
    "sg:city":"Pollen\u00e7a",
    "sg:orig_category":"Forjas Y Altos Hornos",
    "sg:phone":"+34 971 53 00 72",
    "sg:postcode":"07460",
    "sg:province":"Islas Baleares",
    "wof:name":"Herreria Pollenca S.l.",
    "wof:placetype":"venue"
},
  "geometry": {"coordinates":[3.0200340748,39.878288269],"type":"Point"}
}