{
  "type": "Feature",
  "properties": {
    "iso:country":"ES",
    "sg:address":"Calle de Manuel Mas, 67",
    "sg:city":"Talayuela",
    "sg:orig_category":"Servicio De Salud",
    "sg:phone":"+34 927 57 85 85",
    "sg:postcode":"10310",
    "sg:province":"C\u00e1ceres",
    "wof:name":"Gonzalez Ca\u00f1adas Tamara",
    "wof:placetype":"venue"
},
  "geometry": {"coordinates":[-5.6098880768,39.9875679016],"type":"Point"}
}