{
  "type": "Feature",
  "properties": {
    "iso:country":"ES",
    "sg:address":"Valent\u00edn Huertas, S/n",
    "sg:city":"El Pedernoso",
    "sg:orig_category":"Fabricaci\u00d3n De Tapices Y Moquetas Para Suelos Y Paredes",
    "sg:phone":"+34 967 16 40 54",
    "sg:postcode":"16638",
    "sg:province":"Cuenca",
    "wof:name":"Casado Molina Joaquin",
    "wof:placetype":"venue"
},
  "geometry": {"coordinates":[-2.7425038815,39.4827728271],"type":"Point"}
}