{
  "type": "Feature",
  "properties": {
    "iso:country":"ES",
    "sg:address":"Calle de Manteria, 20",
    "sg:city":"Valladolid",
    "sg:orig_category":"Zapatos (al Por Menor)",
    "sg:phone":"+34 983 20 45 17",
    "sg:postcode":"47004",
    "sg:province":"Valladolid",
    "wof:name":"Gandara Cruz Jose Manuel",
    "wof:placetype":"venue"
},
  "geometry": {"coordinates":[-4.722743988,41.6484527588],"type":"Point"}
}