{
  "type": "Feature",
  "properties": {
    "iso:country":"ES",
    "sg:address":"Avda Mijas, 32",
    "sg:city":"Fuengirola",
    "sg:orig_category":"Abogados",
    "sg:phone":"+34 952 46 98 28",
    "sg:postcode":"29640",
    "sg:province":"M\u00e1laga",
    "wof:name":"Martin Merida Maria Gema",
    "wof:placetype":"venue"
},
  "geometry": {"coordinates":[-4.6292791367,36.5430297852],"type":"Point"}
}