{
  "type": "Feature",
  "properties": {
    "addr:full":"Avda Doctor Fleming, 39 Ecija Sevilla 41400",
    "addr:housenumber":"39",
    "addr:postcode":"41400",
    "addr:street":"Avda Doctor Fleming",
    "iso:country":"ES",
    "sg:address":"Avda Doctor Fleming, 39",
    "sg:city":"Ecija",
    "sg:orig_category":"Agentes, Concesionarios Y Sucursales De Veh\u00cdculos",
    "sg:phone":"+34 955 90 41 37",
    "sg:postcode":"41400",
    "sg:province":"Sevilla",
    "wof:name":"Astimovil S.a.",
    "wof:placetype":"venue"
},
  "geometry": {"coordinates":[-5.0731301308,37.5416297913],"type":"Point"}
}