{
  "type": "Feature",
  "properties": {
    "iso:country":"ES",
    "sg:address":"Pg Colom, 103",
    "sg:city":"Ca'n Picafort",
    "sg:orig_category":"Juegos Y Juguetes (al Por Menor)",
    "sg:phone":"+34 971 85 22 27",
    "sg:postcode":"07458",
    "sg:province":"Islas Baleares",
    "wof:name":"Super Palace S.l.",
    "wof:placetype":"venue"
},
  "geometry": {"coordinates":[2.9117100239,39.6136398315],"type":"Point"}
}