{
  "type": "Feature",
  "properties": {
    "iso:country":"ES",
    "sg:address":"Calle de Rosal, 28",
    "sg:city":"Monegrillo",
    "sg:orig_category":"M\u00c9dicos: Medicina Manual",
    "sg:phone":"+34 976 16 31 52",
    "sg:postcode":"50164",
    "sg:province":"Zaragoza",
    "wof:name":"Cortes Pelet Enrique",
    "wof:placetype":"venue"
},
  "geometry": {"coordinates":[-0.4163419902,41.6370697021],"type":"Point"}
}