{
  "type": "Feature",
  "properties": {
    "addr:full":"Calle de Virgen De Iciar, 15 Alcorcon Madrid 28921",
    "addr:housenumber":"15",
    "addr:postcode":"28921",
    "addr:street":"Calle De Virgen De Iciar",
    "iso:country":"ES",
    "sg:address":"Calle de Virgen De Iciar, 15",
    "sg:city":"Alcorcon",
    "sg:orig_category":"Ense\u00d1anza Variada",
    "sg:phone":"+34 916 43 22 22",
    "sg:postcode":"28921",
    "sg:province":"Madrid",
    "wof:name":"Perez Del Prado Javier",
    "wof:placetype":"venue"
},
  "geometry": {"coordinates":[-3.8301339149,40.3448486328],"type":"Point"}
}