{
  "type": "Feature",
  "properties": {
    "iso:country":"ES",
    "sg:address":"Pase Estacion, 8",
    "sg:city":"Torredonjimeno",
    "sg:orig_category":"Bares, Piano",
    "sg:phone":"+34 953 57 13 11",
    "sg:postcode":"23650",
    "sg:province":"Ja\u00e9n",
    "wof:name":"Villena Garrido Francisco",
    "wof:placetype":"venue"
},
  "geometry": {"coordinates":[-3.9492950439,37.7635307312],"type":"Point"}
}