{
  "type": "Feature",
  "properties": {
    "iso:country":"ES",
    "sg:address":"Calle de Perdomo, 25",
    "sg:city":"Palmas De Gran Canaria",
    "sg:orig_category":"Venta, Alquiler De Instrumentos Y Accesorios De M\u00dasica",
    "sg:phone":"+34 928 36 05 90",
    "sg:postcode":"35002",
    "sg:province":"Las Palmas",
    "wof:name":"Gil Herrera Maria Encarnacion",
    "wof:placetype":"venue"
},
  "geometry": {"coordinates":[-15.4181127548,28.1061058044],"type":"Point"}
}