{
  "type": "Feature",
  "properties": {
    "addr:full":"Pol Ind El Poligono, S/n Mancha Real Ja\u00e9n 23100",
    "addr:postcode":"23100",
    "addr:street":"Poligono S / N",
    "iso:country":"ES",
    "sg:address":"Pol Ind El Poligono, S/n",
    "sg:city":"Mancha Real",
    "sg:orig_category":"Colocaci\u00d3n, Mantenimiento De Canalizaciones",
    "sg:phone":"+34 953 35 43 30",
    "sg:postcode":"23100",
    "sg:province":"Ja\u00e9n",
    "wof:name":"Jose Montesinos Garzon Y Otro C.b.",
    "wof:placetype":"venue"
},
  "geometry": {"coordinates":[-3.609249115,37.7891464233],"type":"Point"}
}