{
  "type": "Feature",
  "properties": {
    "addr:full":"C\u00aa Salt Vilablareix, S/n Salt Girona 17190",
    "addr:housenumber":"s / n",
    "addr:postcode":"17190",
    "addr:street":"Vilablareix",
    "iso:country":"ES",
    "sg:address":"C\u00aa Salt Vilablareix, S/n",
    "sg:city":"Salt",
    "sg:orig_category":"Agentes, Concesionarios Y Sucursales De Veh\u00cdculos",
    "sg:phone":"+34 972 23 63 03",
    "sg:postcode":"17190",
    "sg:province":"Girona",
    "wof:name":"Girona Comercial D'automocio S. A.",
    "wof:placetype":"venue"
},
  "geometry": {"coordinates":[2.7779150009,41.9651832581],"type":"Point"}
}