{
  "type": "Feature",
  "properties": {
    "iso:country":"ES",
    "sg:address":"Carr Havana, L', 4",
    "sg:city":"Vilanova I La Geltru",
    "sg:orig_category":"Obras Y Organismos Sociales",
    "sg:phone":"+34 938 93 57 54",
    "sg:postcode":"08800",
    "sg:province":"Barcelona",
    "wof:name":"Cruz Roja Espa\u00f1ola",
    "wof:placetype":"venue"
},
  "geometry": {"coordinates":[1.724421978,41.2213134766],"type":"Point"}
}