{
  "type": "Feature",
  "properties": {
    "addr:full":"Calle de Juan Tur Tur, 13 Santa Eulalia Islas Baleares 07840",
    "addr:housenumber":"13",
    "addr:postcode":"07840",
    "addr:street":"Calle De Juan Tur Tur",
    "iso:country":"ES",
    "sg:address":"Calle de Juan Tur Tur, 13",
    "sg:city":"Santa Eulalia",
    "sg:orig_category":"Caf\u00c9s, Bares, Cervecer\u00cdas",
    "sg:phone":"+34 971 33 68 08",
    "sg:postcode":"07840",
    "sg:province":"Islas Baleares",
    "wof:name":"Kalisol Ibiza S.l.",
    "wof:placetype":"venue"
},
  "geometry": {"coordinates":[1.5314819813,38.9831733704],"type":"Point"}
}