{
  "type": "Feature",
  "properties": {
    "addr:full":"Calle de Uranzu, 22 Irun Guip\u00f9zcoa 20304",
    "addr:housenumber":"22",
    "addr:postcode":"20304",
    "addr:street":"Calle De Uranzu;Guipu\u0300Zcoa",
    "iso:country":"ES",
    "sg:address":"Calle de Uranzu, 22",
    "sg:city":"Irun",
    "sg:orig_category":"Carnicer\u00cdas, Carnicer\u00cdas",
    "sg:phone":"+34 943 62 11 71",
    "sg:postcode":"20304",
    "sg:province":"Guip\u00f9zcoa",
    "wof:name":"Borda Perurena Jose Luis",
    "wof:placetype":"venue"
},
  "geometry": {"coordinates":[-1.7835129499,43.3384552002],"type":"Point"}
}