{
  "type": "Feature",
  "properties": {
    "addr:full":"Calle de San Juan, 20 Sanlucar De Barrameda C\u00e1diz 11540",
    "addr:housenumber":"20",
    "addr:postcode":"11540",
    "addr:street":"Calle De San Juan;Ca\u0301Diz",
    "iso:country":"ES",
    "sg:address":"Calle de San Juan, 20",
    "sg:city":"Sanlucar De Barrameda",
    "sg:orig_category":"Agencias De Viajes",
    "sg:phone":"+34 956 36 25 40",
    "sg:postcode":"11540",
    "sg:province":"C\u00e1diz",
    "wof:name":"Viajes Do\u00f1ana S.l.",
    "wof:placetype":"venue"
},
  "geometry": {"coordinates":[-6.3546118736,36.778427124],"type":"Point"}
}