{
  "type": "Feature",
  "properties": {
    "addr:full":"Calle de Valle Inclan, 6 Cehegin Murcia 30430",
    "addr:housenumber":"6",
    "addr:postcode":"30430",
    "addr:street":"Calle De Valle Inclan",
    "iso:country":"ES",
    "sg:address":"Calle de Valle Inclan, 6",
    "sg:city":"Cehegin",
    "sg:orig_category":"Cristaler\u00cdas",
    "sg:phone":"+34 968 74 29 47",
    "sg:postcode":"30430",
    "sg:province":"Murcia",
    "wof:name":"Valera Nadal Francisco",
    "wof:placetype":"venue"
},
  "geometry": {"coordinates":[-1.7968169451,38.0915679932],"type":"Point"}
}