{
  "type": "Feature",
  "properties": {
    "iso:country":"ES",
    "sg:address":"Calle de Urquijo Julio, 14",
    "sg:city":"Bilbao",
    "sg:orig_category":"Telas Y Sedas (al Por Menor)",
    "sg:phone":"+34 944 76 15 00",
    "sg:postcode":"48014",
    "sg:province":"Vizcaya",
    "wof:name":"Bilbao Turuelo Maria Asuncion",
    "wof:placetype":"venue"
},
  "geometry": {"coordinates":[-2.9527258873,43.270778656],"type":"Point"}
}