{
  "type": "Feature",
  "properties": {
    "iso:country":"ES",
    "sg:address":"Calle de Honda, 3",
    "sg:city":"Cartagena",
    "sg:orig_category":"Alumbrados",
    "sg:phone":"+34 968 50 15 17",
    "sg:postcode":"30201",
    "sg:province":"Murcia",
    "wof:name":"Cervantes Hernandez Juan",
    "wof:placetype":"venue"
},
  "geometry": {"coordinates":[-0.9865289927,37.6017570496],"type":"Point"}
}