{
  "type": "Feature",
  "properties": {
    "iso:country":"ES",
    "sg:address":"Pase Constitucion (de La), 24",
    "sg:city":"Logro\u00f1o",
    "sg:orig_category":"Empresas De Limpieza",
    "sg:phone":"+34 941 25 20 00",
    "sg:postcode":"26004",
    "sg:province":"La Rioja",
    "wof:name":"Torres Jimenez Antonio",
    "wof:placetype":"venue"
},
  "geometry": {"coordinates":[-2.4461789131,42.4652786255],"type":"Point"}
}