{
  "type": "Feature",
  "properties": {
    "addr:full":"Av Estrasburg, 2 Platja D'aro Girona 17250",
    "addr:housenumber":"2",
    "addr:postcode":"17250",
    "addr:street":"Av Estrasburg",
    "iso:country":"ES",
    "sg:address":"Av Estrasburg, 2",
    "sg:city":"Platja D'aro",
    "sg:orig_category":"Centros Comerciales Y Grandes Tiendas",
    "sg:phone":"+34 972 81 63 61",
    "sg:postcode":"17250",
    "sg:province":"Girona",
    "sg:website":"vall@vall.com",
    "wof:name":"Magatzems Vall S.a.",
    "wof:placetype":"venue"
},
  "geometry": {"coordinates":[2.8225619793,41.9659194946],"type":"Point"}
}