{
  "type": "Feature",
  "properties": {
    "addr:full":"Calle de Arces (de Los), 28 Parque Coimbra Madrid 28935",
    "addr:postcode":"28935",
    "addr:street":"Calle De Arces De Los;Parque",
    "iso:country":"ES",
    "sg:address":"Calle de Arces (de Los), 28",
    "sg:city":"Parque Coimbra",
    "sg:orig_category":"M\u00c9dicos: Estomatolog\u00cda",
    "sg:phone":"+34 916 47 70 86",
    "sg:postcode":"28935",
    "sg:province":"Madrid",
    "wof:name":"Santos Garcia Rene",
    "wof:placetype":"venue"
},
  "geometry": {"coordinates":[-3.9379630089,40.3035240173],"type":"Point"}
}