{
  "type": "Feature",
  "properties": {
    "addr:full":"Calle de Mayor, 25 Alegria-dulantzi \u00c1lava 01240",
    "addr:housenumber":"25",
    "addr:postcode":"01240",
    "addr:street":"Calle De Mayor;A\u0301Lava",
    "iso:country":"ES",
    "sg:address":"Calle de Mayor, 25",
    "sg:city":"Alegria-dulantzi",
    "sg:orig_category":"Instalaci\u00d3n, Reparaci\u00d3n De Calefacci\u00d3n El\u00c9ctrica",
    "sg:phone":"+34 945 42 01 68",
    "sg:postcode":"01240",
    "sg:province":"\u00c1lava",
    "wof:name":"Perez Ruiz Jose",
    "wof:placetype":"venue"
},
  "geometry": {"coordinates":[-2.5115890503,42.8405685425],"type":"Point"}
}