{
  "type": "Feature",
  "properties": {
    "addr:full":"Ctra Aguilas (de), Km. 0001,0 Granja Murcia 30800",
    "addr:postcode":"30800",
    "addr:street":"Ctra Aguilas De Km. 0001,0",
    "iso:country":"ES",
    "sg:address":"Ctra Aguilas (de), Km. 0001,0",
    "sg:city":"Granja",
    "sg:orig_category":"Muebles, Minoristas",
    "sg:phone":"+34 968 46 74 87",
    "sg:postcode":"30800",
    "sg:province":"Murcia",
    "wof:name":"Las Vegas Euromobiliario S.l.",
    "wof:placetype":"venue"
},
  "geometry": {"coordinates":[-1.6905640364,37.680557251],"type":"Point"}
}