{
  "type": "Feature",
  "properties": {
    "addr:full":"Ctra Tf-324-la Perdoma, 85 Perdoma Santa Cruz De Tenerife 38315",
    "addr:housenumber":"85",
    "addr:postcode":"38315",
    "addr:street":"Ctra Tf-324-La Perdoma",
    "iso:country":"ES",
    "sg:address":"Ctra Tf-324-la Perdoma, 85",
    "sg:city":"Perdoma",
    "sg:orig_category":"Motocicletas (agentes, Concesionarios)",
    "sg:phone":"+34 922 30 89 33",
    "sg:postcode":"38315",
    "sg:province":"Santa Cruz De Tenerife",
    "wof:name":"Alonso Hernandez Juan Antonio",
    "wof:placetype":"venue"
},
  "geometry": {"coordinates":[-16.2548561096,28.4698104858],"type":"Point"}
}