{
  "type": "Feature",
  "properties": {
    "iso:country":"ES",
    "sg:address":"Las Tuneras, 26",
    "sg:city":"Garita",
    "sg:orig_category":"Guarder\u00cdas",
    "sg:phone":"+34 928 70 66 78",
    "sg:postcode":"35212",
    "sg:province":"Las Palmas",
    "wof:name":"Guarderia La Luna S.l.",
    "wof:placetype":"venue"
},
  "geometry": {"coordinates":[-15.3771390915,28.0030403137],"type":"Point"}
}