{
  "type": "Feature",
  "properties": {
    "addr:full":"Carrer de Pau Gargallo, 5 Barcelona Barcelona 08028",
    "addr:housenumber":"5",
    "addr:postcode":"08028",
    "addr:street":"Carrer De Pau Gargallo",
    "iso:country":"ES",
    "sg:address":"Carrer de Pau Gargallo, 5",
    "sg:city":"Barcelona",
    "sg:orig_category":"Molduras, Junquillos, Listones Y Molduras Perforadas",
    "sg:phone":"+34 933 34 61 86",
    "sg:postcode":"08028",
    "sg:province":"Barcelona",
    "wof:name":"Del Molino Roa S.l.",
    "wof:placetype":"venue"
},
  "geometry": {"coordinates":[2.1140379906,41.3830795288],"type":"Point"}
}