{
  "type": "Feature",
  "properties": {
    "iso:country":"ES",
    "sg:address":"Calle de Belen, 15",
    "sg:city":"Madrid",
    "sg:orig_category":"Art\u00cdculos De Decoraci\u00d3n",
    "sg:phone":"+34 913 19 67 69",
    "sg:postcode":"28004",
    "sg:province":"Madrid",
    "wof:name":"Inmuebles Mh Salesas Sl",
    "wof:placetype":"venue"
},
  "geometry": {"coordinates":[-3.6955485344,40.4245414734],"type":"Point"}
}