{
  "type": "Feature",
  "properties": {
    "addr:full":"Calle de Cordoba, 27 Castro Rio C\u00f3rdoba 14840",
    "addr:housenumber":"27",
    "addr:postcode":"14840",
    "addr:street":"Calle De Cordoba;Rio Co\u0301Rdoba",
    "iso:country":"ES",
    "sg:address":"Calle de Cordoba, 27",
    "sg:city":"Castro Rio",
    "sg:orig_category":"Supermercados Y Hipermercados",
    "sg:phone":"+34 957 37 04 63",
    "sg:postcode":"14840",
    "sg:province":"C\u00f3rdoba",
    "wof:name":"Miranda Medina Francisco",
    "wof:placetype":"venue"
},
  "geometry": {"coordinates":[-4.4845342636,37.6905174255],"type":"Point"}
}