{
  "type": "Feature",
  "properties": {
    "addr:full":"Carr Sant Antoni, 13 Sant Joan Les Fonts Girona 17857",
    "addr:housenumber":"13",
    "addr:postcode":"17857",
    "addr:street":"Carr Sant Antoni",
    "iso:country":"ES",
    "sg:address":"Carr Sant Antoni, 13",
    "sg:city":"Sant Joan Les Fonts",
    "sg:orig_category":"Panader\u00cdas, Panader\u00cdas",
    "sg:phone":"+34 972 29 07 53",
    "sg:postcode":"17857",
    "sg:province":"Girona",
    "wof:name":"Domenech Roquer Salvador",
    "wof:placetype":"venue"
},
  "geometry": {"coordinates":[2.5108819008,42.2128372192],"type":"Point"}
}