{
  "type": "Feature",
  "properties": {
    "addr:full":"Avda Espa\u00d1a, 3 Estepona M\u00e1laga 29680",
    "addr:housenumber":"3",
    "addr:postcode":"29680",
    "addr:street":"Avda Espan\u0303A",
    "iso:country":"ES",
    "sg:address":"Avda Espa\u00d1a, 3",
    "sg:city":"Estepona",
    "sg:orig_category":"M\u00c9dicos: Pediatr\u00cda. Enfermedades De Los Ni\u00d1os",
    "sg:phone":"+34 952 79 14 68",
    "sg:postcode":"29680",
    "sg:province":"M\u00e1laga",
    "wof:name":"Sanchez Aguilar Antonio",
    "wof:placetype":"venue"
},
  "geometry": {"coordinates":[-5.1431522369,36.4256019592],"type":"Point"}
}