{
  "type": "Feature",
  "properties": {
    "iso:country":"ES",
    "sg:address":"Carrer de Angel Guimera, 12",
    "sg:city":"Molins Rei",
    "sg:orig_category":"Grafistas",
    "sg:phone":"+34 936 80 42 86",
    "sg:postcode":"08750",
    "sg:province":"Barcelona",
    "wof:name":"Nocion Grafica S.l.",
    "wof:placetype":"venue"
},
  "geometry": {"coordinates":[2.0199689865,41.4106483459],"type":"Point"}
}