{
  "type": "Feature",
  "properties": {
    "iso:country":"ES",
    "sg:address":"Meson, 3",
    "sg:city":"Cerceda",
    "sg:orig_category":"Ingenier\u00cda, Centros De Estudios (diversos)",
    "sg:phone":"+34 981 68 61 47",
    "sg:postcode":"15185",
    "sg:province":"La Coru\u00f1a",
    "wof:name":"Itc Ingenieros S.l.",
    "wof:placetype":"venue"
},
  "geometry": {"coordinates":[-8.4736642838,43.1888847351],"type":"Point"}
}