{
  "type": "Feature",
  "properties": {
    "iso:country":"ES",
    "sg:address":"Avda Galicia, 74",
    "sg:city":"Cambados",
    "sg:orig_category":"Mercer\u00cda, Lencer\u00cda (al Por Menor)",
    "sg:phone":"+34 986 54 36 03",
    "sg:postcode":"36630",
    "sg:province":"Pontevedra",
    "wof:name":"Fari\u00f1a Oubi\u00f1a Maria De Los Dolores",
    "wof:placetype":"venue"
},
  "geometry": {"coordinates":[-8.8156642914,42.5111503601],"type":"Point"}
}