{
  "type": "Feature",
  "properties": {
    "addr:full":"Pl Jaume El Conqueridor, 4 Alcoi Alicante 03802",
    "addr:housenumber":"4",
    "addr:postcode":"03802",
    "addr:street":"Pl;El Conqueridor",
    "iso:country":"ES",
    "sg:address":"Pl Jaume El Conqueridor, 4",
    "sg:city":"Alcoi",
    "sg:orig_category":"Embalajes",
    "sg:phone":"+34 965 33 08 77",
    "sg:postcode":"03802",
    "sg:province":"Alicante",
    "wof:name":"Paya Bernabeu Manuel Jesus",
    "wof:placetype":"venue"
},
  "geometry": {"coordinates":[-0.4855929911,38.697517395],"type":"Point"}
}