{
  "type": "Feature",
  "properties": {
    "addr:full":"Calle de San Marcos, 14 S. Fernando C\u00e1diz 11100",
    "addr:housenumber":"14",
    "addr:postcode":"11100",
    "addr:street":"Calle De San Marcos;S. Fernando Ca\u0301Diz",
    "iso:country":"ES",
    "sg:address":"Calle de San Marcos, 14",
    "sg:city":"S. Fernando",
    "sg:orig_category":"Imprenta",
    "sg:phone":"+34 956 88 67 12",
    "sg:postcode":"11100",
    "sg:province":"C\u00e1diz",
    "wof:name":"Callealta Oneto Juan De Dios",
    "wof:placetype":"venue"
},
  "geometry": {"coordinates":[-6.1928520203,36.4661712646],"type":"Point"}
}