{
  "type": "Feature",
  "properties": {
    "iso:country":"ES",
    "sg:address":"Carrer de Diputacio, 163",
    "sg:city":"Barcelona",
    "sg:orig_category":"Ropa Para Caballeros (al Por Menor)",
    "sg:phone":"+34 934 51 75 03",
    "sg:postcode":"08011",
    "sg:province":"Barcelona",
    "wof:name":"Het Out S.c.p.",
    "wof:placetype":"venue"
},
  "geometry": {"coordinates":[2.1589028835,41.3844566345],"type":"Point"}
}