{
  "type": "Feature",
  "properties": {
    "iso:country":"ES",
    "sg:address":"Calle de Pintor Maella, 32",
    "sg:city":"Valencia",
    "sg:orig_category":"Aceites Y Grasas Alimentarias (fabricaci\u00d3n, Al Por Mayor)",
    "sg:phone":"+34 963 31 26 77",
    "sg:postcode":"46023",
    "sg:province":"Valencia",
    "wof:name":"Devis Devis Francisco",
    "wof:placetype":"venue"
},
  "geometry": {"coordinates":[-0.3480240107,39.4600334167],"type":"Point"}
}