{
  "type": "Feature",
  "properties": {
    "iso:country":"ES",
    "sg:address":"Barrio Almendral, 1",
    "sg:city":"Caniles",
    "sg:orig_category":"Empresas De Carpinter\u00cda De Madera",
    "sg:phone":"+34 958 71 07 92",
    "sg:postcode":"18810",
    "sg:province":"Granada",
    "wof:name":"Norbeisma S.c.a.",
    "wof:placetype":"venue"
},
  "geometry": {"coordinates":[-2.7245531082,37.4428367615],"type":"Point"}
}