{
  "type": "Feature",
  "properties": {
    "iso:country":"ES",
    "sg:address":"Avda Reina Sofia, 5",
    "sg:city":"Coin",
    "sg:orig_category":"Promotores Constructores",
    "sg:phone":"+34 952 45 52 95",
    "sg:postcode":"29100",
    "sg:province":"M\u00e1laga",
    "wof:name":"Construcciones V P R S.l.",
    "wof:placetype":"venue"
},
  "geometry": {"coordinates":[-4.756196022,36.6622543335],"type":"Point"}
}