{
  "type": "Feature",
  "properties": {
    "addr:full":"Ptda Torreta, S/n Alcora Castell\u00f3n 12110",
    "addr:housenumber":"s / n",
    "addr:postcode":"12110",
    "addr:street":"Ptda Torreta;Alcora Castello\u0301N",
    "iso:country":"ES",
    "sg:address":"Ptda Torreta, S/n",
    "sg:city":"Alcora",
    "sg:orig_category":"Plomeros",
    "sg:phone":"+34 964 36 03 76",
    "sg:postcode":"12110",
    "sg:province":"Castell\u00f3n",
    "wof:name":"Fontaneria Lazaro S.l.u",
    "wof:placetype":"venue"
},
  "geometry": {"coordinates":[-0.2178789973,40.0734786987],"type":"Point"}
}