{
  "type": "Feature",
  "properties": {
    "addr:full":"Carr Animes, 17 Palafrugell Girona 17200",
    "addr:housenumber":"17",
    "addr:postcode":"17200",
    "addr:street":"Carr Animes",
    "iso:country":"ES",
    "sg:address":"Carr Animes, 17",
    "sg:city":"Palafrugell",
    "sg:orig_category":"Arreglo, Reparaci\u00d3n, Piezas Sueltas De Televisi\u00d3n, V\u00cddeo, Hi",
    "sg:phone":"+34 972 61 19 52",
    "sg:postcode":"17200",
    "sg:province":"Girona",
    "wof:name":"Serrano Riquelme Manuel",
    "wof:placetype":"venue"
},
  "geometry": {"coordinates":[3.1652650833,41.9160003662],"type":"Point"}
}