{
  "type": "Feature",
  "properties": {
    "iso:country":"ES",
    "sg:address":"Calle de Joaquin Sorolla, 16",
    "sg:city":"Sevilla",
    "sg:orig_category":"Carnicer\u00cdas, Carnicer\u00cdas",
    "sg:phone":"+34 954 64 74 10",
    "sg:postcode":"41006",
    "sg:province":"Sevilla",
    "wof:name":"Diaz Gallego Antonio",
    "wof:placetype":"venue"
},
  "geometry": {"coordinates":[-5.950466156,37.3702735901],"type":"Point"}
}