{
  "type": "Feature",
  "properties": {
    "addr:full":"Avda Ordo\u00d1o Ii, 26 Le\u00f3n Le\u00f3n 24001",
    "addr:housenumber":"26",
    "addr:postcode":"24001",
    "addr:street":"Avda Ordon\u0303O Ii;Leo\u0301N",
    "iso:country":"ES",
    "sg:address":"Avda Ordo\u00d1o Ii, 26",
    "sg:city":"Le\u00f3n",
    "sg:orig_category":"Arquitectos",
    "sg:phone":"+34 987 26 04 46",
    "sg:postcode":"24001",
    "sg:province":"Le\u00f3n",
    "wof:name":"Diez Florez Fernando",
    "wof:placetype":"venue"
},
  "geometry": {"coordinates":[-5.5764780045,42.5968093872],"type":"Point"}
}