{
  "type": "Feature",
  "properties": {
    "addr:full":"Avda Limones, 20 Benidorm Alicante 03500",
    "addr:housenumber":"20",
    "addr:postcode":"03500",
    "addr:street":"Avda Limones",
    "iso:country":"ES",
    "sg:address":"Avda Limones, 20",
    "sg:city":"Benidorm",
    "sg:orig_category":"Cristaler\u00cdas",
    "sg:phone":"+34 965 86 79 73",
    "sg:postcode":"03500",
    "sg:province":"Alicante",
    "wof:name":"Perez Fuster Maria Del Sufragio",
    "wof:placetype":"venue"
},
  "geometry": {"coordinates":[-0.1333120018,38.5398979187],"type":"Point"}
}