{
  "type": "Feature",
  "properties": {
    "iso:country":"ES",
    "sg:address":"Carrer de Mercat, 4",
    "sg:city":"Benidorm",
    "sg:orig_category":"Bisuter\u00cda, Joyer\u00cda, Relojer\u00cda (al Por Menor)",
    "sg:phone":"+34 965 85 25 03",
    "sg:postcode":"03500",
    "sg:province":"Alicante",
    "wof:name":"Lopez Casta\u00f1eda Vicente",
    "wof:placetype":"venue"
},
  "geometry": {"coordinates":[-0.1314779967,38.5370635986],"type":"Point"}
}