{
  "type": "Feature",
  "properties": {
    "iso:country":"ES",
    "sg:address":"Pase Soto (el), 3",
    "sg:city":"Lerma",
    "sg:orig_category":"Laboratorios Y Cl\u00cdnicas Veterinarias",
    "sg:phone":"+34 947 17 07 07",
    "sg:postcode":"09340",
    "sg:province":"Burgos",
    "wof:name":"Clinica Residencia Arlanza",
    "wof:placetype":"venue"
},
  "geometry": {"coordinates":[-3.7584710121,42.0313110352],"type":"Point"}
}