{
  "type": "Feature",
  "properties": {
    "iso:country":"ES",
    "sg:address":"Carr Bisbe Miquel Moncadas, 30",
    "sg:city":"Muro",
    "sg:orig_category":"Mec\u00c1nico Del Autom\u00d3vil",
    "sg:phone":"+34 971 53 73 55",
    "sg:postcode":"07440",
    "sg:province":"Islas Baleares",
    "wof:name":"Joan Palleras I Boades S.l.",
    "wof:placetype":"venue"
},
  "geometry": {"coordinates":[3.0527799129,39.7414093018],"type":"Point"}
}