{
  "type": "Feature",
  "properties": {
    "addr:full":"Praz Lians, S/n Porto De Santa Cruz La Coru\u00f1a 15179",
    "addr:housenumber":"s / n",
    "addr:postcode":"15179",
    "addr:street":"Praz Lians;Corun\u0303A",
    "iso:country":"ES",
    "sg:address":"Praz Lians, S/n",
    "sg:city":"Porto De Santa Cruz",
    "sg:orig_category":"Electrodom\u00c9sticos (al Por Menor)",
    "sg:phone":"+34 981 61 52 27",
    "sg:postcode":"15179",
    "sg:province":"La Coru\u00f1a",
    "wof:name":"Mata Botana Concepcion",
    "wof:placetype":"venue"
},
  "geometry": {"coordinates":[-8.3444890976,43.3433189392],"type":"Point"}
}