{
  "type": "Feature",
  "properties": {
    "addr:full":"Calle de Quebrantahuesos, 8 Zamora Zamora 49004",
    "addr:housenumber":"8",
    "addr:postcode":"49004",
    "addr:street":"Calle De Quebrantahuesos",
    "iso:country":"ES",
    "sg:address":"Calle de Quebrantahuesos, 8",
    "sg:city":"Zamora",
    "sg:orig_category":"Cuchiller\u00cda (al Por Menor)",
    "sg:phone":"+34 980 53 31 28",
    "sg:postcode":"49004",
    "sg:province":"Zamora",
    "wof:name":"Perez Delgado Jose Manuel",
    "wof:placetype":"venue"
},
  "geometry": {"coordinates":[-5.7460889816,41.5040512085],"type":"Point"}
}