{
  "type": "Feature",
  "properties": {
    "iso:country":"ES",
    "sg:address":"Avda Federico Garcia Lorca, 117",
    "sg:city":"Almeria",
    "sg:orig_category":"Comunidades Religiosas",
    "sg:phone":"+34 950 23 12 73",
    "sg:postcode":"04004",
    "sg:province":"Almer\u00eda",
    "wof:name":"Comunidad Virgen Del Mar-hijas De Jesus",
    "wof:placetype":"venue"
},
  "geometry": {"coordinates":[-2.4581589699,36.8436889648],"type":"Point"}
}