{
  "type": "Feature",
  "properties": {
    "iso:country":"ES",
    "sg:address":"Calle de Alicante, 40",
    "sg:city":"Albal",
    "sg:orig_category":"Muebles, Minoristas",
    "sg:phone":"+34 961 26 00 03",
    "sg:postcode":"46470",
    "sg:province":"Valencia",
    "wof:name":"Grupo Naturane S.l.",
    "wof:placetype":"venue"
},
  "geometry": {"coordinates":[-0.4066621065,39.405582428],"type":"Point"}
}