{
  "type": "Feature",
  "properties": {
    "addr:full":"Pase Castilla, 9 Alcorcon Madrid 28921",
    "addr:housenumber":"9",
    "addr:postcode":"28921",
    "addr:street":"Castilla",
    "iso:country":"ES",
    "sg:address":"Pase Castilla, 9",
    "sg:city":"Alcorcon",
    "sg:orig_category":"Mec\u00c1nico Del Autom\u00d3vil",
    "sg:phone":"+34 916 12 28 87",
    "sg:postcode":"28921",
    "sg:province":"Madrid",
    "wof:name":"Ya\u00f1ez Lopez Joaquin",
    "wof:placetype":"venue"
},
  "geometry": {"coordinates":[-3.8294446468,40.3492279053],"type":"Point"}
}