{
  "type": "Feature",
  "properties": {
    "addr:full":"Calle de Cecilio Montes, 11 Icod De Los Vinos Santa Cruz De Tenerife 38430",
    "addr:housenumber":"11",
    "addr:postcode":"38430",
    "addr:street":"Calle De Cecilio Montes",
    "iso:country":"ES",
    "sg:address":"Calle de Cecilio Montes, 11",
    "sg:city":"Icod De Los Vinos",
    "sg:orig_category":"Mec\u00c1nico Del Autom\u00d3vil",
    "sg:phone":"+34 922 81 52 98",
    "sg:postcode":"38430",
    "sg:province":"Santa Cruz De Tenerife",
    "wof:name":"Afonso  Taller De Leon",
    "wof:placetype":"venue"
},
  "geometry": {"coordinates":[-16.7128486633,28.3711891174],"type":"Point"}
}