{
  "type": "Feature",
  "properties": {
    "addr:full":"Calle de Alfarerias Bajas, 14 Villarrobledo Albacete 02600",
    "addr:housenumber":"14",
    "addr:postcode":"02600",
    "addr:street":"Calle De Alfarerias Bajas",
    "iso:country":"ES",
    "sg:address":"Calle de Alfarerias Bajas, 14",
    "sg:city":"Villarrobledo",
    "sg:orig_category":"Laboratorios Y Trabajos De Fotograf\u00cda, V\u00cddeo Y Cine",
    "sg:phone":"+34 967 14 52 77",
    "sg:postcode":"02600",
    "sg:province":"Albacete",
    "sg:website":"www.fotoprix.com",
    "wof:name":"Pixelatum S.l.",
    "wof:placetype":"venue"
},
  "geometry": {"coordinates":[-2.6027898788,39.2678451538],"type":"Point"}
}