{
  "type": "Feature",
  "properties": {
    "addr:full":"Plaz Circular, 7 Valladolid Valladolid 47005",
    "addr:housenumber":"7",
    "addr:postcode":"47005",
    "addr:street":"Plaz Circular",
    "iso:country":"ES",
    "sg:address":"Plaz Circular, 7",
    "sg:city":"Valladolid",
    "sg:orig_category":"Muebles Y Accesorios Para Cocinas Y Cuartos De Ba\u00d1o (al Por Menor)",
    "sg:phone":"+34 983 39 45 54",
    "sg:postcode":"47005",
    "sg:province":"Valladolid",
    "wof:name":"Comercial Uyo S. A.",
    "wof:placetype":"venue"
},
  "geometry": {"coordinates":[-4.7163128853,41.6473579407],"type":"Point"}
}