{
  "type": "Feature",
  "properties": {
    "iso:country":"ES",
    "sg:address":"Calle de Carretera General, S/n",
    "sg:city":"Unquera",
    "sg:orig_category":"Molduras, Junquillos, Listones Y Molduras Perforadas",
    "sg:phone":"+34 942 71 70 74",
    "sg:postcode":"39560",
    "sg:province":"Cantabria",
    "wof:name":"Bar La Granja",
    "wof:placetype":"venue"
},
  "geometry": {"coordinates":[-4.5151238441,43.3745231628],"type":"Point"}
}