{
  "type": "Feature",
  "properties": {
    "addr:full":"Calle de Pista La, 2 Mieres Asturias 33600",
    "addr:housenumber":"2",
    "addr:postcode":"33600",
    "addr:street":"Calle De Pista La",
    "iso:country":"ES",
    "sg:address":"Calle de Pista La, 2",
    "sg:city":"Mieres",
    "sg:classifiers":[
        {
            "category":"Autos & Motor Vehicles",
            "subcategory":"Automobile Sales",
            "type":"Retail Goods"
        }
    ],
    "sg:phone":"+34 985 46 13 04",
    "sg:postcode":"33600",
    "sg:province":"Asturias",
    "wof:name":"Autoescuela Jose S.l.",
    "wof:placetype":"venue"
},
  "geometry": {"coordinates":[-5.774204731,43.2493362427],"type":"Point"}
}