{
  "type": "Feature",
  "properties": {
    "iso:country":"ES",
    "sg:address":"Calle de Mayor, 8",
    "sg:city":"Valladolises",
    "sg:orig_category":"Transportes Por V\u00cdas Navegables",
    "sg:phone":"+34 968 38 40 41",
    "sg:postcode":"30154",
    "sg:province":"Murcia",
    "wof:name":"Cereales Valladolises S.a.",
    "wof:placetype":"venue"
},
  "geometry": {"coordinates":[-1.1239919662,37.7767677307],"type":"Point"}
}