{
  "type": "Feature",
  "properties": {
    "iso:country":"ES",
    "sg:address":"Valls, S/n",
    "sg:city":"Vic",
    "sg:orig_category":"Muebles Y Accesorios Para Cocinas Y Cuartos De Ba\u00d1o (al Por Menor)",
    "sg:phone":"+34 938 89 10 33",
    "sg:postcode":"08500",
    "sg:province":"Barcelona",
    "wof:name":"Sanglas Baulenas S.l.",
    "wof:placetype":"venue"
},
  "geometry": {"coordinates":[2.2738220692,41.9507675171],"type":"Point"}
}