{
  "type": "Feature",
  "properties": {
    "iso:country":"ES",
    "sg:address":"Calle de Llana, 6",
    "sg:city":"Garganta La Olla",
    "sg:orig_category":"Art\u00cdculos De Regalo (al Por Menor)",
    "sg:phone":"+34 927 17 97 55",
    "sg:postcode":"10412",
    "sg:province":"C\u00e1ceres",
    "wof:name":"Casta\u00f1o Miranda Juan",
    "wof:placetype":"venue"
},
  "geometry": {"coordinates":[-5.7763199806,40.1117134094],"type":"Point"}
}