{
  "type": "Feature",
  "properties": {
    "addr:full":"Calle de General Sanz Pastor, 16 Burgos Burgos 09003",
    "addr:housenumber":"16",
    "addr:postcode":"09003",
    "addr:street":"Calle De General Sanz Pastor",
    "iso:country":"ES",
    "sg:address":"Calle de General Sanz Pastor, 16",
    "sg:city":"Burgos",
    "sg:orig_category":"Material Y Suministros Para Dentistas, Cirujanos",
    "sg:phone":"+34 947 27 38 25",
    "sg:postcode":"09003",
    "sg:province":"Burgos",
    "wof:name":"Cg 3 Laboratorio Dental S.l.",
    "wof:placetype":"venue"
},
  "geometry": {"coordinates":[-3.6996769905,42.3443527222],"type":"Point"}
}