{
  "type": "Feature",
  "properties": {
    "addr:full":"Avda Catalu\u00d1a, 22 Zaragoza Zaragoza 50014",
    "addr:housenumber":"22",
    "addr:postcode":"50014",
    "addr:street":"Avda Catalun\u0303A",
    "iso:country":"ES",
    "sg:address":"Avda Catalu\u00d1a, 22",
    "sg:city":"Zaragoza",
    "sg:orig_category":"Molduras, Junquillos, Listones Y Molduras Perforadas",
    "sg:phone":"+34 976 39 37 92",
    "sg:postcode":"50014",
    "sg:province":"Zaragoza",
    "wof:name":"Izquierdo Forcen Federico",
    "wof:placetype":"venue"
},
  "geometry": {"coordinates":[-0.8713030219,41.6591072083],"type":"Point"}
}