{
  "type": "Feature",
  "properties": {
    "iso:country":"ES",
    "sg:address":"Calle de Virgen De Lluc, 76",
    "sg:city":"Madrid",
    "sg:orig_category":"Confecci\u00d3n (fabricaci\u00d3n, Al Por Mayor)",
    "sg:phone":"+34 914 08 28 13",
    "sg:postcode":"28027",
    "sg:province":"Madrid",
    "wof:name":"Charmline S. L.",
    "wof:placetype":"venue"
},
  "geometry": {"coordinates":[-3.6471068859,40.436126709],"type":"Point"}
}