{
  "type": "Feature",
  "properties": {
    "iso:country":"ES",
    "sg:address":"C/ Marti Metge, 118",
    "sg:city":"Inca",
    "sg:orig_category":"Doctores En Medicina",
    "sg:phone":"+34 971 50 32 58",
    "sg:postcode":"07300",
    "sg:province":"Islas Baleares",
    "wof:name":"Comas Matheu Juan",
    "wof:placetype":"venue"
},
  "geometry": {"coordinates":[2.9112610817,39.723110199],"type":"Point"}
}