{
  "type": "Feature",
  "properties": {
    "addr:full":"Carr Malet, 8 Guils Cerdanya Girona 17528",
    "addr:housenumber":"8",
    "addr:postcode":"17528",
    "addr:street":"Carr Malet",
    "iso:country":"ES",
    "sg:address":"Carr Malet, 8",
    "sg:city":"Guils Cerdanya",
    "sg:orig_category":"Administraciones Regionales, Departamentales Y Locales",
    "sg:phone":"+34 972 88 00 16",
    "sg:postcode":"17528",
    "sg:province":"Girona",
    "wof:name":"Ajuntament De Guils De Cerdanya",
    "wof:placetype":"venue"
},
  "geometry": {"coordinates":[1.8807953596,42.447769165],"type":"Point"}
}