{
  "type": "Feature",
  "properties": {
    "iso:country":"ES",
    "sg:address":"Avda Ana De Viya, 14",
    "sg:city":"Cadiz",
    "sg:orig_category":"Loter\u00cda Y T\u00d3mbola",
    "sg:phone":"+34 956 25 13 55",
    "sg:postcode":"11008",
    "sg:province":"C\u00e1diz",
    "wof:name":"Perez Abascal Milagros",
    "wof:placetype":"venue"
},
  "geometry": {"coordinates":[-6.2806558609,36.512752533],"type":"Point"}
}