{
  "type": "Feature",
  "properties": {
    "addr:full":"Calle de Menendez Y Pelayo, 22 Entrego Asturias 33940",
    "addr:housenumber":"22",
    "addr:postcode":"33940",
    "addr:street":"Calle De Menendez Y Pelayo",
    "iso:country":"ES",
    "sg:address":"Calle de Menendez Y Pelayo, 22",
    "sg:city":"Entrego",
    "sg:orig_category":"Art\u00cdculos De Decoraci\u00d3n",
    "sg:phone":"+34 985 66 05 40",
    "sg:postcode":"33940",
    "sg:province":"Asturias",
    "wof:name":"Lopez Alvarez Tomas",
    "wof:placetype":"venue"
},
  "geometry": {"coordinates":[-5.6404290199,43.2870483398],"type":"Point"}
}