{
  "type": "Feature",
  "properties": {
    "addr:full":"Zaldo, S/n Santurde La Rioja 26260",
    "addr:postcode":"26260",
    "addr:street":"Zaldo S / N Santurde;Rioja",
    "iso:country":"ES",
    "sg:address":"Zaldo, S/n",
    "sg:city":"Santurde",
    "sg:orig_category":"Albergues",
    "sg:phone":"+34 941 42 66 96",
    "sg:postcode":"26260",
    "sg:province":"La Rioja",
    "wof:name":"Victor Guerra S.a.",
    "wof:placetype":"venue"
},
  "geometry": {"coordinates":[-2.978151083,42.3888778687],"type":"Point"}
}