{
  "type": "Feature",
  "properties": {
    "addr:full":"Autovia Logro\u00f1o Pol Ind Europa, Km. 0007,4 Zaragoza Zaragoza 50011",
    "addr:postcode":"50011",
    "addr:street":"Autovia Logron\u0303O Pol;Europa Km. 0007,4",
    "iso:country":"ES",
    "sg:address":"Autovia Logro\u00f1o Pol Ind Europa, Km. 0007,4",
    "sg:city":"Zaragoza",
    "sg:orig_category":"Productos Qu\u00cdmicos (fabricaci\u00d3n, Al Por Mayor)",
    "sg:phone":"+34 976 46 07 02",
    "sg:postcode":"50011",
    "sg:province":"Zaragoza",
    "wof:name":"Valero Analitica S.l.",
    "wof:placetype":"venue"
},
  "geometry": {"coordinates":[-0.9913589954,41.662853241],"type":"Point"}
}