{
  "type": "Feature",
  "properties": {
    "addr:full":"Pase Olivos, 90 Madrid Madrid 28011",
    "addr:housenumber":"90",
    "addr:postcode":"madrid;28011",
    "addr:street":"Olivos",
    "iso:country":"ES",
    "sg:address":"Pase Olivos, 90",
    "sg:city":"Madrid",
    "sg:orig_category":"Empresas De Portes Y Mensajer\u00cda",
    "sg:phone":"+34 914 70 21 66",
    "sg:postcode":"28011",
    "sg:province":"Madrid",
    "wof:name":"Hakim  Khettab",
    "wof:placetype":"venue"
},
  "geometry": {"coordinates":[-3.7393240929,40.40574646],"type":"Point"}
}