{
  "type": "Feature",
  "properties": {
    "iso:country":"ES",
    "sg:address":"Plaz Ecce Homo, S/n",
    "sg:city":"Guitiriz",
    "sg:orig_category":"Molduras, Junquillos, Listones Y Molduras Perforadas",
    "sg:phone":"+34 982 37 06 61",
    "sg:postcode":"27300",
    "sg:province":"Lugo",
    "wof:name":"Blanco Cupeiro Maria",
    "wof:placetype":"venue"
},
  "geometry": {"coordinates":[-7.8988189697,43.1811637878],"type":"Point"}
}