{
  "type": "Feature",
  "properties": {
    "addr:full":"Calle de Libertad, 135 Hellin Albacete 02400",
    "addr:housenumber":"135",
    "addr:postcode":"02400",
    "addr:street":"Calle De Libertad",
    "iso:country":"ES",
    "sg:address":"Calle de Libertad, 135",
    "sg:city":"Hellin",
    "sg:orig_category":"Chapister\u00cda",
    "sg:phone":"+34 967 30 09 62",
    "sg:postcode":"02400",
    "sg:province":"Albacete",
    "wof:name":"Tallares Hermanos Mu\u00f1oz De Hellin C.b.",
    "wof:placetype":"venue"
},
  "geometry": {"coordinates":[-1.7042899132,38.5203971863],"type":"Point"}
}