{
  "type": "Feature",
  "properties": {
    "addr:full":"Pl Catalunya, 1 Cambrils Tarragona 43850",
    "addr:housenumber":"1",
    "addr:postcode":"43850",
    "addr:street":"Pl Catalunya",
    "iso:country":"ES",
    "sg:address":"Pl Catalunya, 1",
    "sg:city":"Cambrils",
    "sg:orig_category":"Peluqueros: De Se\u00d1oras",
    "sg:phone":"+34 977 36 03 07",
    "sg:postcode":"43850",
    "sg:province":"Tarragona",
    "sg:website":"www.jeanninasanahuja.com",
    "wof:name":"Peluqueria Miramar Ii S.l.",
    "wof:placetype":"venue"
},
  "geometry": {"coordinates":[1.0593219995,41.0655555725],"type":"Point"}
}