{
  "type": "Feature",
  "properties": {
    "addr:full":"San J. Bosco, 3 Iru\u00f1a Navarra 31007",
    "addr:housenumber":"3",
    "addr:postcode":"31007",
    "addr:street":"Irun\u0303A Navarra",
    "iso:country":"ES",
    "sg:address":"San J. Bosco, 3",
    "sg:city":"Iru\u00f1a",
    "sg:orig_category":"Cajas De Ahorro",
    "sg:phone":"+34 948 27 14 73",
    "sg:postcode":"31007",
    "sg:province":"Navarra",
    "sg:website":"www.cajalaboral.es",
    "wof:name":"Caja Laboral Popular",
    "wof:placetype":"venue"
},
  "geometry": {"coordinates":[-1.6475059986,42.8062820435],"type":"Point"}
}