{
  "type": "Feature",
  "properties": {
    "iso:country":"ES",
    "sg:address":"Pase Estacion (la), 60",
    "sg:city":"Jaen",
    "sg:orig_category":"Promotores Constructores",
    "sg:phone":"+34 953 26 10 06",
    "sg:postcode":"23007",
    "sg:province":"Ja\u00e9n",
    "wof:name":"Noriega S. A.",
    "wof:placetype":"venue"
},
  "geometry": {"coordinates":[-3.7890949249,37.7773323059],"type":"Point"}
}