{
  "type": "Feature",
  "properties": {
    "iso:country":"ES",
    "sg:address":"Plaz Domingo Gascon, 3",
    "sg:city":"Teruel",
    "sg:orig_category":"Supermercados Y Hipermercados",
    "sg:phone":"+34 978 60 57 46",
    "sg:postcode":"44001",
    "sg:province":"Teruel",
    "wof:name":"Supermercados Mika S.l.",
    "wof:placetype":"venue"
},
  "geometry": {"coordinates":[-1.1045490503,40.3420944214],"type":"Point"}
}