{
  "type": "Feature",
  "properties": {
    "iso:country":"ES",
    "sg:address":"Rua Serafin Avenda\u00d1o, 5",
    "sg:city":"Vigo",
    "sg:orig_category":"Navegaci\u00d3n (equipos Fluviales)",
    "sg:phone":"+34 986 22 46 56",
    "sg:postcode":"36201",
    "sg:province":"Pontevedra",
    "sg:website":"www.suflenorsa.es",
    "wof:name":"Suflenor S.a.",
    "wof:placetype":"venue"
},
  "geometry": {"coordinates":[-8.7122812271,42.2381782532],"type":"Point"}
}