{
  "type": "Feature",
  "properties": {
    "addr:full":"Calle de Jose Ortega Y Gasset, 43 Madrid Madrid 28006",
    "addr:housenumber":"43",
    "addr:postcode":"madrid;28006",
    "addr:street":"Calle De Jose Ortega Y Gasset",
    "iso:country":"ES",
    "sg:address":"Calle de Jose Ortega Y Gasset, 43",
    "sg:city":"Madrid",
    "sg:orig_category":"M\u00c9dicos: Estomatolog\u00cda",
    "sg:phone":"+34 914 01 51 66",
    "sg:postcode":"28006",
    "sg:province":"Madrid",
    "wof:name":"Plaza Mayor Alfonso",
    "wof:placetype":"venue"
},
  "geometry": {"coordinates":[-3.6779689789,40.4301528931],"type":"Point"}
}