{
  "type": "Feature",
  "properties": {
    "addr:full":"Carrer de Viatjants, 22 Sabadell Barcelona 08204",
    "addr:housenumber":"22",
    "addr:postcode":"08204",
    "addr:street":"Carrer De Viatjants",
    "iso:country":"ES",
    "sg:address":"Carrer de Viatjants, 22",
    "sg:city":"Sabadell",
    "sg:orig_category":"Peluquer\u00cdas, Peluquer\u00cda Mixta",
    "sg:phone":"+34 937 12 37 94",
    "sg:postcode":"08204",
    "sg:province":"Barcelona",
    "wof:name":"Brea  Felipa",
    "wof:placetype":"venue"
},
  "geometry": {"coordinates":[2.1116919518,41.5281295776],"type":"Point"}
}