{
  "type": "Feature",
  "properties": {
    "addr:full":"Avda Antonio Y Miguel Navarro, 8 Montilla C\u00f3rdoba 14550",
    "addr:housenumber":"8",
    "addr:postcode":"14550",
    "addr:street":"Avda Antonio Y Miguel Navarro;Co\u0301Rdoba",
    "iso:country":"ES",
    "sg:address":"Avda Antonio Y Miguel Navarro, 8",
    "sg:city":"Montilla",
    "sg:orig_category":"Equitaci\u00d3n: Guarnicioner\u00cda, Equipo (al Por Menor)",
    "sg:phone":"+34 957 65 36 06",
    "sg:postcode":"14550",
    "sg:province":"C\u00f3rdoba",
    "wof:name":"Berral Garrido Joaquin",
    "wof:placetype":"venue"
},
  "geometry": {"coordinates":[-4.6460709572,37.5778007507],"type":"Point"}
}