{
  "type": "Feature",
  "properties": {
    "iso:country":"ES",
    "sg:address":"Plaz Rosario (el), 2",
    "sg:city":"Soria",
    "sg:orig_category":"Asesor\u00cda Sobre Comunicaci\u00d3n De Empresas",
    "sg:phone":"+34 975 24 01 65",
    "sg:postcode":"42001",
    "sg:province":"Soria",
    "wof:name":"Acg-key Asesores S.l.",
    "wof:placetype":"venue"
},
  "geometry": {"coordinates":[-2.467577219,41.7666893005],"type":"Point"}
}