{
  "type": "Feature",
  "properties": {
    "addr:full":"Avda Santa Cruz (de), 72 G\u00fcimar Santa Cruz De Tenerife 38500",
    "addr:housenumber":"72",
    "addr:postcode":"38500",
    "addr:street":"Avda Santa Cruz De",
    "iso:country":"ES",
    "sg:address":"Avda Santa Cruz (de), 72",
    "sg:city":"G\u00fcimar",
    "sg:orig_category":"Agentes, Concesionarios Y Sucursales De Veh\u00cdculos",
    "sg:phone":"+34 922 51 07 62",
    "sg:postcode":"38500",
    "sg:province":"Santa Cruz De Tenerife",
    "wof:name":"Toyoauto S.l.",
    "wof:placetype":"venue"
},
  "geometry": {"coordinates":[-16.4071502686,28.3194293976],"type":"Point"}
}