{
  "type": "Feature",
  "properties": {
    "iso:country":"ES",
    "sg:address":"Calle de Carnicerias, 2",
    "sg:city":"Burgos",
    "sg:orig_category":"Arquitectos",
    "sg:phone":"+34 947 27 93 52",
    "sg:postcode":"09003",
    "sg:province":"Burgos",
    "wof:name":"Gonzalez Bartolome Arquitectura Y Urbanismo S.l.",
    "wof:placetype":"venue"
},
  "geometry": {"coordinates":[-3.7008626461,42.3409805298],"type":"Point"}
}