{
  "type": "Feature",
  "properties": {
    "addr:full":"Avda Gamonal, 10 Arroyo De La Miel-benalmadena Costa M\u00e1laga 29631",
    "addr:housenumber":"10",
    "addr:postcode":"29631",
    "addr:street":"Avda Gamonal;Ma\u0301Laga",
    "iso:country":"ES",
    "sg:address":"Avda Gamonal, 10",
    "sg:city":"Arroyo De La Miel-benalmadena Costa",
    "sg:orig_category":"Fisioterapia",
    "sg:phone":"+34 952 96 45 99",
    "sg:postcode":"29631",
    "sg:province":"M\u00e1laga",
    "wof:name":"Fernandez Garcia Nuria",
    "wof:placetype":"venue"
},
  "geometry": {"coordinates":[-4.5482521057,36.6017608643],"type":"Point"}
}