{
  "type": "Feature",
  "properties": {
    "addr:full":"Calle de Alfareria, 4 Palma Rio C\u00f3rdoba 14700",
    "addr:housenumber":"4",
    "addr:postcode":"14700",
    "addr:street":"Calle De Alfareria;Rio Co\u0301Rdoba",
    "iso:country":"ES",
    "sg:address":"Calle de Alfareria, 4",
    "sg:city":"Palma Rio",
    "sg:orig_category":"Mec\u00c1nico Del Autom\u00d3vil",
    "sg:phone":"+34 957 64 45 20",
    "sg:postcode":"14700",
    "sg:province":"C\u00f3rdoba",
    "wof:name":"Automoviles Eugenio Olmo S.l.",
    "wof:placetype":"venue"
},
  "geometry": {"coordinates":[-5.2774000168,37.694683075],"type":"Point"}
}