{
  "type": "Feature",
  "properties": {
    "addr:full":"Estd Caranza, S/n Ferrol La Coru\u00f1a 15406",
    "addr:housenumber":"s / n",
    "addr:postcode":"15406",
    "addr:street":"Estd Caranza;La Corun\u0303A",
    "iso:country":"ES",
    "sg:address":"Estd Caranza, S/n",
    "sg:city":"Ferrol",
    "sg:orig_category":"Bares, Piano",
    "sg:phone":"+34 981 35 07 37",
    "sg:postcode":"15406",
    "sg:province":"La Coru\u00f1a",
    "wof:name":"Garcia Martinez Yolanda",
    "wof:placetype":"venue"
},
  "geometry": {"coordinates":[-8.2062616348,43.4831771851],"type":"Point"}
}