{
  "type": "Feature",
  "properties": {
    "addr:full":"Carrer de Merce Rodoreda, 9 Casco Urbano Barcelona 08450",
    "addr:housenumber":"9",
    "addr:postcode":"08450",
    "addr:street":"Carrer De Merce Rodoreda",
    "iso:country":"ES",
    "sg:address":"Carrer de Merce Rodoreda, 9",
    "sg:city":"Casco Urbano",
    "sg:orig_category":"Equitaci\u00d3n Y Centros De H\u00cdpica",
    "sg:phone":"+34 938 41 31 99",
    "sg:postcode":"08450",
    "sg:province":"Barcelona",
    "wof:name":"Piaffe Equestrian Design S.l",
    "wof:placetype":"venue"
},
  "geometry": {"coordinates":[2.3952701092,41.6382713318],"type":"Point"}
}