{
  "type": "Feature",
  "properties": {
    "addr:full":"Avda Luchon, 3 Benasque Huesca 22440",
    "addr:housenumber":"3",
    "addr:postcode":"22440",
    "addr:street":"Avda Luchon",
    "iso:country":"ES",
    "sg:address":"Avda Luchon, 3",
    "sg:city":"Benasque",
    "sg:orig_category":"Asociaciones Y Clubs Deportivos",
    "sg:phone":"+34 974 55 20 93",
    "sg:postcode":"22440",
    "sg:province":"Huesca",
    "sg:website":"www.koala-deportes.com",
    "wof:name":"Deportes Koala S.l.",
    "wof:placetype":"venue"
},
  "geometry": {"coordinates":[0.5245320201,42.605255127],"type":"Point"}
}