{
  "type": "Feature",
  "properties": {
    "iso:country":"ES",
    "sg:address":"Calle de Serrano, 212",
    "sg:city":"Madrid",
    "sg:orig_category":"Internados & Ense\u00d1anza Privada",
    "sg:phone":"+34 915 63 85 34",
    "sg:postcode":"28002",
    "sg:province":"Madrid",
    "wof:name":"Gonzalez Capdevila Pedro",
    "wof:placetype":"venue"
},
  "geometry": {"coordinates":[-3.6814630032,40.4513130188],"type":"Point"}
}