{
  "type": "Feature",
  "properties": {
    "iso:country":"ES",
    "sg:address":"Av Matadepera, 64",
    "sg:city":"Sabadell",
    "sg:orig_category":"Promotores Constructores",
    "sg:phone":"+34 937 24 07 09",
    "sg:postcode":"08207",
    "sg:province":"Barcelona",
    "wof:name":"Construcciones Avenida 2002 S.l.",
    "wof:placetype":"venue"
},
  "geometry": {"coordinates":[2.0897619724,41.5657463074],"type":"Point"}
}