{
  "type": "Feature",
  "properties": {
    "iso:country":"ES",
    "sg:address":"Calle de Pilar, 4",
    "sg:city":"Bujaraloz",
    "sg:orig_category":"Asesor\u00cda De Formaci\u00d3n Y Gesti\u00d3n De Personal",
    "sg:phone":"+34 976 17 34 27",
    "sg:postcode":"50177",
    "sg:province":"Zaragoza",
    "wof:name":"Barrachina Ferrer S.cv.",
    "wof:placetype":"venue"
},
  "geometry": {"coordinates":[-0.1524879932,41.4981918335],"type":"Point"}
}