{
  "type": "Feature",
  "properties": {
    "iso:country":"ES",
    "sg:address":"Barr Puente Pumar, S/n",
    "sg:city":"Puente Pumar",
    "sg:orig_category":"Centros De Educaci\u00d3n Especial",
    "sg:phone":"+34 942 72 90 64",
    "sg:postcode":"39556",
    "sg:province":"Cantabria",
    "wof:name":"Cp Valle De Polaciones",
    "wof:placetype":"venue"
},
  "geometry": {"coordinates":[-4.4046339989,43.1093139648],"type":"Point"}
}