{
  "type": "Feature",
  "properties": {
    "iso:country":"ES",
    "sg:address":"Calle de Polan, 2",
    "sg:city":"Madrid",
    "sg:orig_category":"Agencias Y Agentes Comerciales, Representantes",
    "sg:phone":"+34 917 46 39 07",
    "sg:postcode":"28025",
    "sg:province":"Madrid",
    "wof:name":"Granados Rodriguez Antonio",
    "wof:placetype":"venue"
},
  "geometry": {"coordinates":[-3.726238966,40.3742218018],"type":"Point"}
}