{
  "type": "Feature",
  "properties": {
    "addr:full":"Carrer de Villarroel, 78 Barcelona Barcelona 08011",
    "addr:housenumber":"78",
    "addr:postcode":"08011",
    "addr:street":"Carrer De Villarroel",
    "iso:country":"ES",
    "sg:address":"Carrer de Villarroel, 78",
    "sg:city":"Barcelona",
    "sg:orig_category":"Reposter\u00cdas",
    "sg:phone":"+34 934 53 70 15",
    "sg:postcode":"08011",
    "sg:province":"Barcelona",
    "wof:name":"Farras Melia Gregorio",
    "wof:placetype":"venue"
},
  "geometry": {"coordinates":[2.1582090855,41.384311676],"type":"Point"}
}