{
  "type": "Feature",
  "properties": {
    "iso:country":"ES",
    "sg:address":"Carrer de Santa Rita, 8",
    "sg:city":"S. Cugat Valles",
    "sg:orig_category":"Suministros Y Materiales Industriales",
    "sg:phone":"+34 935 89 63 73",
    "sg:postcode":"08173",
    "sg:province":"Barcelona",
    "wof:name":"Southoco Europe Ltd",
    "wof:placetype":"venue"
},
  "geometry": {"coordinates":[2.073925972,41.4711341858],"type":"Point"}
}