{
  "type": "Feature",
  "properties": {
    "iso:country":"ES",
    "sg:address":"Calle de San Fernando, 5",
    "sg:city":"Priego Cordoba",
    "sg:classifiers":[
        {
            "category":"Personal",
            "subcategory":"Barber",
            "type":"Services"
        }
    ],
    "sg:phone":"+34 957 70 14 72",
    "sg:postcode":"14800",
    "sg:province":"C\u00f3rdoba",
    "sg:tags":[
        "caballeros",
        "de",
        "peluqueros"
    ],
    "wof:name":"Valdivia Mu\u00f1oz Juan Miguel",
    "wof:placetype":"venue"
},
  "geometry": {"coordinates":[-4.2006998062,37.4391937256],"type":"Point"}
}