{
  "type": "Feature",
  "properties": {
    "iso:country":"ES",
    "sg:address":"Calle de Ramon Menendez Pidal, 6",
    "sg:city":"Pola De Laviana",
    "sg:orig_category":"Cristaler\u00cdas",
    "sg:phone":"+34 985 61 02 44",
    "sg:postcode":"33980",
    "sg:province":"Asturias",
    "wof:name":"Coto Bartolome German",
    "wof:placetype":"venue"
},
  "geometry": {"coordinates":[-5.5629677773,43.2462272644],"type":"Point"}
}