{
  "type": "Feature",
  "properties": {
    "iso:country":"ES",
    "sg:address":"Calle de Valserrano (de), 8",
    "sg:city":"Algete",
    "sg:orig_category":"Arreglo, Instalaci\u00d3n Y Acondicionamiento De Talleres",
    "sg:phone":"+34 916 28 91 78",
    "sg:postcode":"28110",
    "sg:province":"Madrid",
    "wof:name":"Ayuntamiento De Algete",
    "wof:placetype":"venue"
},
  "geometry": {"coordinates":[-3.5010390282,40.5923194885],"type":"Point"}
}