{
  "type": "Feature",
  "properties": {
    "iso:country":"ES",
    "sg:address":"Calle de Puerto De Tarna, 10",
    "sg:city":"Gijon",
    "sg:orig_category":"Lencer\u00cda Femenina, Corseter\u00cda, Trajes De Ba\u00d1o (al Por Menor)",
    "sg:phone":"+34 985 14 64 34",
    "sg:postcode":"33207",
    "sg:province":"Asturias",
    "wof:name":"Garcia Alonso Felicidad",
    "wof:placetype":"venue"
},
  "geometry": {"coordinates":[-5.672894001,43.5308265686],"type":"Point"}
}