{
  "type": "Feature",
  "properties": {
    "iso:country":"ES",
    "sg:address":"G.v. Corts Catalanes, 192",
    "sg:city":"Barcelona",
    "sg:orig_category":"Transportes Por Carretera: Lotes Completos, Mercanc\u00cdas Diversas",
    "sg:phone":"+34 933 31 51 66",
    "sg:postcode":"08004",
    "sg:province":"Barcelona",
    "wof:name":"Bon-preu S.a.",
    "wof:placetype":"venue"
},
  "geometry": {"coordinates":[2.1407790184,41.3684196472],"type":"Point"}
}