{
  "type": "Feature",
  "properties": {
    "iso:country":"ES",
    "sg:address":"Calle de Conde Luna, 28",
    "sg:city":"Benavides De Orbigo",
    "sg:orig_category":"Farmacias",
    "sg:phone":"+34 987 37 14 02",
    "sg:postcode":"24280",
    "sg:province":"Le\u00f3n",
    "wof:name":"Carrasco Fernandez Antonio",
    "wof:placetype":"venue"
},
  "geometry": {"coordinates":[-5.8939042091,42.5030059814],"type":"Point"}
}