{
  "type": "Feature",
  "properties": {
    "iso:country":"ES",
    "sg:address":"Calle de Toledo, 4",
    "sg:city":"Villaviciosa Cordoba",
    "sg:orig_category":"Electrodom\u00c9sticos (al Por Menor)",
    "sg:phone":"+34 957 36 05 32",
    "sg:postcode":"14300",
    "sg:province":"C\u00f3rdoba",
    "wof:name":"Alcalde Garcia Alfonso",
    "wof:placetype":"venue"
},
  "geometry": {"coordinates":[-5.014752388,38.0776824951],"type":"Point"}
}