{
  "type": "Feature",
  "properties": {
    "addr:full":"Calle de Canarias, S/n Madro\u00f1era C\u00e1ceres 10210",
    "addr:housenumber":"s / n",
    "addr:postcode":"10210",
    "addr:street":"Calle De Canarias;Ca\u0301Ceres",
    "iso:country":"ES",
    "sg:address":"Calle de Canarias, S/n",
    "sg:city":"Madro\u00f1era",
    "sg:orig_category":"Chapister\u00cda",
    "sg:phone":"+34 927 33 42 18",
    "sg:postcode":"10210",
    "sg:province":"C\u00e1ceres",
    "wof:name":"Solis Pablo Pablo",
    "wof:placetype":"venue"
},
  "geometry": {"coordinates":[-5.7595038414,39.4271812439],"type":"Point"}
}