{
  "type": "Feature",
  "properties": {
    "iso:country":"ES",
    "sg:address":"Ctra. Valencia, Km. 0009,0",
    "sg:city":"Cuarte Huerva",
    "sg:orig_category":"Veh\u00cdculos De Ocasi\u00d3n",
    "sg:phone":"+34 976 50 41 39",
    "sg:postcode":"50410",
    "sg:province":"Zaragoza",
    "sg:website":"www.autotrade-center.com",
    "wof:name":"Emotion Cars S.c.",
    "wof:placetype":"venue"
},
  "geometry": {"coordinates":[-0.9296389818,41.6074638367],"type":"Point"}
}