{
  "type": "Feature",
  "properties": {
    "addr:full":"Pg Sant Joan Bosco, 62 Barcelona Barcelona 08017",
    "addr:housenumber":"62",
    "addr:postcode":"08017",
    "addr:street":"Pg Sant Joan Bosco",
    "iso:country":"ES",
    "sg:address":"Pg Sant Joan Bosco, 62",
    "sg:city":"Barcelona",
    "sg:orig_category":"Edici\u00d3n De Diarios, Revistas, Boletines",
    "sg:phone":"+34 932 03 13 47",
    "sg:postcode":"08017",
    "sg:province":"Barcelona",
    "sg:website":"www.edebe.com",
    "wof:name":"Sociedad San Francisco De Sales. Editorial Edebe",
    "wof:placetype":"venue"
},
  "geometry": {"coordinates":[2.1270370483,41.3949966431],"type":"Point"}
}