{
  "type": "Feature",
  "properties": {
    "addr:full":"Calle de Balandro, 10 Varadero Granada 18600",
    "addr:housenumber":"10",
    "addr:postcode":"18600",
    "addr:street":"Calle De Balandro",
    "iso:country":"ES",
    "sg:address":"Calle de Balandro, 10",
    "sg:city":"Varadero",
    "sg:orig_category":"Ferreter\u00cda (diversos)",
    "sg:phone":"+34 958 83 32 69",
    "sg:postcode":"18600",
    "sg:province":"Granada",
    "wof:name":"Construvemo Motril S.l.",
    "wof:placetype":"venue"
},
  "geometry": {"coordinates":[-3.5324401855,36.7255935669],"type":"Point"}
}