{
  "type": "Feature",
  "properties": {
    "addr:full":"Calle de Breton De Los Herreros, 4 Valencia Valencia 46003",
    "addr:housenumber":"4",
    "addr:postcode":"46003",
    "addr:street":"Calle De Breton De Los Herreros",
    "iso:country":"ES",
    "sg:address":"Calle de Breton De Los Herreros, 4",
    "sg:city":"Valencia",
    "sg:orig_category":"Peluqueros: De Se\u00d1oras",
    "sg:phone":"+34 963 50 94 30",
    "sg:postcode":"46003",
    "sg:province":"Valencia",
    "wof:name":"Savigne Revilla Norges",
    "wof:placetype":"venue"
},
  "geometry": {"coordinates":[-0.3709329963,39.4734191895],"type":"Point"}
}