{
  "type": "Feature",
  "properties": {
    "iso:country":"ES",
    "sg:address":"Calle de Tulipan, S/n",
    "sg:city":"Torrijos",
    "sg:orig_category":"Metales (labores, Pulido)",
    "sg:phone":"+34 925 76 12 76",
    "sg:postcode":"45500",
    "sg:province":"Toledo",
    "wof:name":"Rafael Ruiz Rodriguez S.l.",
    "wof:placetype":"venue"
},
  "geometry": {"coordinates":[-4.2702889442,39.9800567627],"type":"Point"}
}