{
  "type": "Feature",
  "properties": {
    "iso:country":"ES",
    "sg:address":"Calle de Marcenado, 7",
    "sg:city":"Madrid",
    "sg:orig_category":"Electricidad: Equipos Industriales, Componentes (fabricaci\u00d3n)",
    "sg:phone":"+34 914 15 46 36",
    "sg:postcode":"28002",
    "sg:province":"Madrid",
    "wof:name":"Resistencias Electrisan S. L",
    "wof:placetype":"venue"
},
  "geometry": {"coordinates":[-3.6729550362,40.4455490112],"type":"Point"}
}