{
  "type": "Feature",
  "properties": {
    "addr:full":"Calle de Aller, 55 Mieres Asturias 33600",
    "addr:housenumber":"55",
    "addr:postcode":"33600",
    "addr:street":"Calle De Aller",
    "iso:country":"ES",
    "sg:address":"Calle de Aller, 55",
    "sg:city":"Mieres",
    "sg:orig_category":"Carnicer\u00cdas, Carnicer\u00cdas",
    "sg:phone":"+34 985 46 84 89",
    "sg:postcode":"33600",
    "sg:province":"Asturias",
    "wof:name":"Carniceria Eliseo",
    "wof:placetype":"venue"
},
  "geometry": {"coordinates":[-5.7770133018,43.2539672852],"type":"Point"}
}