{
  "type": "Feature",
  "properties": {
    "iso:country":"ES",
    "sg:address":"Iglesia De Arriba, S/n",
    "sg:city":"Vega",
    "sg:orig_category":"Sindicatos De Trabajadores",
    "sg:phone":"+34 985 13 61 62",
    "sg:postcode":"33391",
    "sg:province":"Asturias",
    "wof:name":"Corriente Sindical De Izquierda-mina La Camocha",
    "wof:placetype":"venue"
},
  "geometry": {"coordinates":[-5.6513209343,43.4914054871],"type":"Point"}
}