{
  "type": "Feature",
  "properties": {
    "iso:country":"ES",
    "sg:address":"Afores, S/n",
    "sg:city":"Mar\u00e7a",
    "sg:orig_category":"Poller\u00cda Y Caza (al Por Menor)",
    "sg:phone":"+34 977 17 81 97",
    "sg:postcode":"43775",
    "sg:province":"Tarragona",
    "wof:name":"Carrete Sabate Joaquin",
    "wof:placetype":"venue"
},
  "geometry": {"coordinates":[0.8010500073,41.1268997192],"type":"Point"}
}