{
  "type": "Feature",
  "properties": {
    "iso:country":"ES",
    "sg:address":"Avgd Antonio Almela, 71",
    "sg:city":"Alcudia",
    "sg:orig_category":"Electromec\u00c1nica",
    "sg:phone":"+34 962 54 03 40",
    "sg:postcode":"46250",
    "sg:province":"Valencia",
    "wof:name":"Electro Levante S.l.",
    "wof:placetype":"venue"
},
  "geometry": {"coordinates":[-0.5070289969,39.1940689087],"type":"Point"}
}