{
  "type": "Feature",
  "properties": {
    "addr:full":"Calle de Nuestra Se\u00d1ora De Monserrate, 4 Torrevieja Alicante 03180",
    "addr:housenumber":"4",
    "addr:postcode":"03180",
    "addr:street":"Calle De Nuestra Sen\u0303Ora De Monserrate",
    "iso:country":"ES",
    "sg:address":"Calle de Nuestra Se\u00d1ora De Monserrate, 4",
    "sg:city":"Torrevieja",
    "sg:orig_category":"Lavado, Limpieza De Veh\u00cdculos",
    "sg:phone":"+34 966 70 32 74",
    "sg:postcode":"03180",
    "sg:province":"Alicante",
    "wof:name":"Pesantes Casta\u00f1eda Martin",
    "wof:placetype":"venue"
},
  "geometry": {"coordinates":[-0.6536790133,38.0173606873],"type":"Point"}
}