{
  "type": "Feature",
  "properties": {
    "addr:full":"Calle de Utrillas, 4 Madrid Madrid 28043",
    "addr:housenumber":"4",
    "addr:postcode":"28043",
    "addr:street":"Calle De Utrillas",
    "iso:country":"ES",
    "sg:address":"Calle de Utrillas, 4",
    "sg:city":"Madrid",
    "sg:classifiers":[
        {
            "category":"Autos & Motor Vehicles",
            "subcategory":"Automobile Sales",
            "type":"Retail Goods"
        }
    ],
    "sg:phone":"+34 917 59 37 85",
    "sg:postcode":"28043",
    "sg:province":"Madrid",
    "wof:name":"Rueda De La Rosa Miguel",
    "wof:placetype":"venue"
},
  "geometry": {"coordinates":[-3.6452820301,40.4631118774],"type":"Point"}
}