{
  "type": "Feature",
  "properties": {
    "iso:country":"ES",
    "sg:address":"Calle de San Cristobal, 8",
    "sg:city":"Osuna",
    "sg:orig_category":"Asilos De Ancianos. Centros Privados",
    "sg:phone":"+34 955 82 04 58",
    "sg:postcode":"41640",
    "sg:province":"Sevilla",
    "wof:name":"Federacion De Organizaciones Andaluzas De Mayores",
    "wof:placetype":"venue"
},
  "geometry": {"coordinates":[-5.1005778313,37.2402801514],"type":"Point"}
}