{
  "type": "Feature",
  "properties": {
    "addr:full":"Carrer de Jacint Verdaguer, 99 Molins Rei Barcelona 08750",
    "addr:housenumber":"99",
    "addr:postcode":"08750",
    "addr:street":"Carrer De Jacint Verdaguer;Barcelona",
    "iso:country":"ES",
    "sg:address":"Carrer de Jacint Verdaguer, 99",
    "sg:city":"Molins Rei",
    "sg:orig_category":"Laboratorios Y Trabajos De Fotograf\u00cda, V\u00cddeo Y Cine",
    "sg:phone":"+34 936 80 01 39",
    "sg:postcode":"08750",
    "sg:province":"Barcelona",
    "wof:name":"Roc Bermudez Pilar",
    "wof:placetype":"venue"
},
  "geometry": {"coordinates":[2.0161969662,41.4144554138],"type":"Point"}
}