{
  "type": "Feature",
  "properties": {
    "iso:country":"ES",
    "sg:address":"Calle de Jorge Juan, 20",
    "sg:city":"Valencia",
    "sg:orig_category":"Cl\u00cdnicas Dentales",
    "sg:phone":"+34 963 52 93 91",
    "sg:postcode":"46004",
    "sg:province":"Valencia",
    "sg:website":"www.sonrie.com",
    "wof:name":"Clinica Dental Cuspide S.l.",
    "wof:placetype":"venue"
},
  "geometry": {"coordinates":[-0.369423002,39.4690628052],"type":"Point"}
}