{
  "type": "Feature",
  "properties": {
    "addr:full":"Calle de Langreo, 9 Pola De Laviana Asturias 33980",
    "addr:housenumber":"9",
    "addr:postcode":"33980",
    "addr:street":"Calle De Langreo;Pola",
    "iso:country":"ES",
    "sg:address":"Calle de Langreo, 9",
    "sg:city":"Pola De Laviana",
    "sg:orig_category":"Molduras, Junquillos, Listones Y Molduras Perforadas",
    "sg:phone":"+34 985 61 09 27",
    "sg:postcode":"33980",
    "sg:province":"Asturias",
    "wof:name":"Redon Perez Pablo",
    "wof:placetype":"venue"
},
  "geometry": {"coordinates":[-5.5640521049,43.2485809326],"type":"Point"}
}