{
  "type": "Feature",
  "properties": {
    "addr:full":"Calle de Segre, 1 Algeciras C\u00e1diz 11206",
    "addr:housenumber":"1;ca\u0301diz",
    "addr:postcode":"11206",
    "addr:street":"Calle De Segre",
    "iso:country":"ES",
    "sg:address":"Calle de Segre, 1",
    "sg:city":"Algeciras",
    "sg:orig_category":"Molduras, Junquillos, Listones Y Molduras Perforadas",
    "sg:phone":"+34 956 60 59 56",
    "sg:postcode":"11206",
    "sg:province":"C\u00e1diz",
    "wof:name":"Gutierrez Gutierrez Maria Del Mar",
    "wof:placetype":"venue"
},
  "geometry": {"coordinates":[-5.4507789612,36.123046875],"type":"Point"}
}