{
  "type": "Feature",
  "properties": {
    "addr:full":"Calle de Virgen De Los Milagros, 4 Puerto De Santa Maria C\u00e1diz 11500",
    "addr:housenumber":"4",
    "addr:postcode":"11500",
    "addr:street":"Calle De Virgen De Los Milagros;Ca\u0301Diz",
    "iso:country":"ES",
    "sg:address":"Calle de Virgen De Los Milagros, 4",
    "sg:city":"Puerto De Santa Maria",
    "sg:orig_category":"Arquitectos",
    "sg:phone":"+34 956 86 04 25",
    "sg:postcode":"11500",
    "sg:province":"C\u00e1diz",
    "wof:name":"Carrasco Arquitectos S.l.",
    "wof:placetype":"venue"
},
  "geometry": {"coordinates":[-6.2213749886,36.6040534973],"type":"Point"}
}