{
  "type": "Feature",
  "properties": {
    "addr:full":"Carrer de Holanda, 43 Hospitalet Llobregat Barcelona 08903",
    "addr:housenumber":"43",
    "addr:postcode":"08903",
    "addr:street":"Carrer De Holanda",
    "iso:country":"ES",
    "sg:address":"Carrer de Holanda, 43",
    "sg:city":"Hospitalet Llobregat",
    "sg:orig_category":"Ropa Para Se\u00d1oras Y Caballeros (al Por Menor)",
    "sg:phone":"+34 934 22 77 81",
    "sg:postcode":"08903",
    "sg:province":"Barcelona",
    "wof:name":"Gonzalez Lamas Juan Luis",
    "wof:placetype":"venue"
},
  "geometry": {"coordinates":[2.1262340546,41.3698234558],"type":"Point"}
}