{
  "type": "Feature",
  "properties": {
    "iso:country":"ES",
    "sg:address":"Av Sarria, 45",
    "sg:city":"Barcelona",
    "sg:classifiers":[
        {
            "category":"Casinos & Gambling",
            "type":"Entertainment"
        }
    ],
    "sg:phone":"+34 933 22 04 55",
    "sg:postcode":"08029",
    "sg:province":"Barcelona",
    "sg:tags":[
        "locale",
        "de",
        "juego"
    ],
    "wof:name":"Sertebi S.a.",
    "wof:placetype":"venue"
},
  "geometry": {"coordinates":[2.1432740688,41.3904495239],"type":"Point"}
}