{
  "type": "Feature",
  "properties": {
    "iso:country":"ES",
    "sg:address":"Ctra Porrera, Km. 0001,5",
    "sg:city":"Falset",
    "sg:orig_category":"Materias Pl\u00c1sticas: Productos De Consumo Masivo (fabricaci\u00d3n, Al Por Mayor)",
    "sg:phone":"+34 977 83 01 02",
    "sg:postcode":"43730",
    "sg:province":"Tarragona",
    "wof:name":"Roda Bielsa Carlos",
    "wof:placetype":"venue"
},
  "geometry": {"coordinates":[0.8204879761,41.1442565918],"type":"Point"}
}