{
  "type": "Feature",
  "properties": {
    "addr:full":"Calle de Ronda De Los Cuarteles, 54 Logro\u00f1o La Rioja 26005",
    "addr:housenumber":"54",
    "addr:postcode":"26005",
    "addr:street":"Calle De Ronda De Los Cuarteles;Rioja",
    "iso:country":"ES",
    "sg:address":"Calle de Ronda De Los Cuarteles, 54",
    "sg:city":"Logro\u00f1o",
    "sg:orig_category":"Agentes Y Bufetes De Negocio",
    "sg:phone":"+34 941 20 35 99",
    "sg:postcode":"26005",
    "sg:province":"La Rioja",
    "wof:name":"Centro De Negocios Ocon S.l",
    "wof:placetype":"venue"
},
  "geometry": {"coordinates":[-2.462927103,42.4689598083],"type":"Point"}
}