{
  "type": "Feature",
  "properties": {
    "iso:country":"ES",
    "sg:address":"Calle de Hermanos Pinzon, 54",
    "sg:city":"Almeria",
    "sg:orig_category":"Cajas Para Embalar",
    "sg:phone":"+34 950 62 27 15",
    "sg:postcode":"04005",
    "sg:province":"Almer\u00eda",
    "sg:website":"www.cajamar.es",
    "wof:name":"Cajamar",
    "wof:placetype":"venue"
},
  "geometry": {"coordinates":[-2.4550290108,36.8410110474],"type":"Point"}
}