{
  "type": "Feature",
  "properties": {
    "iso:country":"ES",
    "sg:address":"Psaj Pintor Ramirez, S/n",
    "sg:city":"Cordoba",
    "sg:orig_category":"Ropa Para Se\u00d1oras (al Por Menor)",
    "sg:phone":"+34 957 40 14 34",
    "sg:postcode":"14006",
    "sg:province":"C\u00f3rdoba",
    "wof:name":"Ortiz Alcala Violeta",
    "wof:placetype":"venue"
},
  "geometry": {"coordinates":[-4.7768988609,37.8963546753],"type":"Point"}
}