{
  "type": "Feature",
  "properties": {
    "iso:country":"ES",
    "sg:address":"Calle de Calvo Sotelo, 22",
    "sg:city":"Logro\u00f1o",
    "sg:orig_category":"Abogados",
    "sg:phone":"+34 941 26 38 89",
    "sg:postcode":"26003",
    "sg:province":"La Rioja",
    "wof:name":"Abogados Gomez Y Asensio S.c",
    "wof:placetype":"venue"
},
  "geometry": {"coordinates":[-2.441979,42.464073],"type":"Point"}
}