{
  "type": "Feature",
  "properties": {
    "iso:country":"ES",
    "sg:address":"Calle de Bruselas, 24",
    "sg:city":"Malaga",
    "sg:orig_category":"Trabajos De Soldaduras",
    "sg:phone":"+34 952 32 02 42",
    "sg:postcode":"29006",
    "sg:province":"M\u00e1laga",
    "wof:name":"Alticron Xxi S.l.",
    "wof:placetype":"venue"
},
  "geometry": {"coordinates":[-4.4724698067,36.6997032166],"type":"Point"}
}