{
  "type": "Feature",
  "properties": {
    "iso:country":"ES",
    "sg:address":"Calle de San Cristobal, 8",
    "sg:city":"Vinaros",
    "sg:orig_category":"Asesor\u00cda Fiscal Y Jur\u00cddica",
    "sg:phone":"+34 964 40 72 10",
    "sg:postcode":"12500",
    "sg:province":"Castell\u00f3n",
    "wof:name":"Emilio Arnau Vives S.l.",
    "wof:placetype":"venue"
},
  "geometry": {"coordinates":[0.4753920138,40.471496582],"type":"Point"}
}