{
  "type": "Feature",
  "properties": {
    "addr:full":"Calle de Pedro Hidalgo, 97 Palmas De Gran Canaria Las Palmas 35016",
    "addr:postcode":"35016",
    "addr:street":"Calle De Pedro Hidalgo 97",
    "iso:country":"ES",
    "sg:address":"Calle de Pedro Hidalgo, 97",
    "sg:city":"Palmas De Gran Canaria",
    "sg:orig_category":"Iglesias Cristianas Diversas",
    "sg:phone":"+34 928 31 14 69",
    "sg:postcode":"35016",
    "sg:province":"Las Palmas",
    "wof:name":"Testigos Cristianos De Jehova",
    "wof:placetype":"venue"
},
  "geometry": {"coordinates":[-15.4229393005,28.0714492798],"type":"Point"}
}