{
  "type": "Feature",
  "properties": {
    "addr:full":"Ptda Llano San Jose, 124 Elche Alicante 03293",
    "addr:housenumber":"124",
    "addr:postcode":"03293",
    "addr:street":"Ptda Llano San Jose",
    "iso:country":"ES",
    "sg:address":"Ptda Llano San Jose, 124",
    "sg:city":"Elche",
    "sg:orig_category":"Fabricaci\u00d3n De Muebles",
    "sg:phone":"+34 965 46 91 16",
    "sg:postcode":"03293",
    "sg:province":"Alicante",
    "wof:name":"Agullo Parre\u00f1o Manuel",
    "wof:placetype":"venue"
},
  "geometry": {"coordinates":[-0.7218046188,38.2306518555],"type":"Point"}
}