{
  "type": "Feature",
  "properties": {
    "iso:country":"ES",
    "sg:address":"Ctra. Huelva, S/n",
    "sg:city":"Gibraleon",
    "sg:orig_category":"Empresas De Carpinter\u00cda Met\u00c1lica",
    "sg:phone":"+34 959 50 01 69",
    "sg:postcode":"21500",
    "sg:province":"Huelva",
    "wof:name":"Aluminios Villase\u00f1or S.l.",
    "wof:placetype":"venue"
},
  "geometry": {"coordinates":[-6.9590587616,37.371547699],"type":"Point"}
}