{
  "type": "Feature",
  "properties": {
    "addr:full":"Calle de Sakanpea, 27 Ansoain Navarra 31013",
    "addr:housenumber":"27",
    "addr:postcode":"31013",
    "addr:street":"Calle De Sakanpea",
    "iso:country":"ES",
    "sg:address":"Calle de Sakanpea, 27",
    "sg:city":"Ansoain",
    "sg:orig_category":"Encuadernaci\u00d3n E Impresi\u00d3n De Folletos",
    "sg:phone":"+34 948 13 18 00",
    "sg:postcode":"31013",
    "sg:province":"Navarra",
    "wof:name":"Ciscar Escandell Ignacio",
    "wof:placetype":"venue"
},
  "geometry": {"coordinates":[-1.6428120136,42.832244873],"type":"Point"}
}