{
  "type": "Feature",
  "properties": {
    "addr:full":"Avda Antonio Machado, 84 Peal Becerro Ja\u00e9n 23460",
    "addr:housenumber":"84",
    "addr:postcode":"23460",
    "addr:street":"Avda Antonio Machado",
    "iso:country":"ES",
    "sg:address":"Avda Antonio Machado, 84",
    "sg:city":"Peal Becerro",
    "sg:orig_category":"Telas Y Sedas (al Por Menor)",
    "sg:phone":"+34 953 73 02 82",
    "sg:postcode":"23460",
    "sg:province":"Ja\u00e9n",
    "wof:name":"Aparicio Millan Francisco Antonio",
    "wof:placetype":"venue"
},
  "geometry": {"coordinates":[-3.1265518665,37.9135169983],"type":"Point"}
}