{
  "type": "Feature",
  "properties": {
    "addr:full":"Calle de Matias Fernandez Bayo, 13 Langreo Asturias 33930",
    "addr:housenumber":"13",
    "addr:postcode":"33930",
    "addr:street":"Calle De Matias Fernandez Bayo",
    "iso:country":"ES",
    "sg:address":"Calle de Matias Fernandez Bayo, 13",
    "sg:city":"Langreo",
    "sg:orig_category":"Empresarios",
    "sg:phone":"+34 985 68 11 11",
    "sg:postcode":"33930",
    "sg:province":"Asturias",
    "wof:name":"Construcciones Angel Suarez S.l.",
    "wof:placetype":"venue"
},
  "geometry": {"coordinates":[-5.6904978752,43.3066444397],"type":"Point"}
}