{
  "type": "Feature",
  "properties": {
    "addr:full":"Calle de Factoria Matagorda, 72 Pto Real C\u00e1diz 11510",
    "addr:housenumber":"72",
    "addr:postcode":"11510",
    "addr:street":"Calle De Factoria Matagorda;Ca\u0301Diz",
    "iso:country":"ES",
    "sg:address":"Calle de Factoria Matagorda, 72",
    "sg:city":"Pto Real",
    "sg:orig_category":"Veh\u00cdculos De Ocasi\u00d3n",
    "sg:phone":"+34 956 47 35 86",
    "sg:postcode":"11510",
    "sg:province":"C\u00e1diz",
    "wof:name":"Garcia Sanchez Francisco",
    "wof:placetype":"venue"
},
  "geometry": {"coordinates":[-6.1970090866,36.529548645],"type":"Point"}
}