{
  "type": "Feature",
  "properties": {
    "iso:country":"ES",
    "sg:address":"Cmno Huerta, 128",
    "sg:city":"Madrid",
    "sg:orig_category":"Inversiones",
    "sg:phone":"+34 916 25 53 29",
    "sg:postcode":"28050",
    "sg:province":"Madrid",
    "wof:name":"Iceberg Inversiones S.l.",
    "wof:placetype":"venue"
},
  "geometry": {"coordinates":[-3.6373319626,40.5077018738],"type":"Point"}
}