{
  "type": "Feature",
  "properties": {
    "addr:full":"Carrer de Sant Joan De Malta, 219 Barcelona Barcelona 08018",
    "addr:housenumber":"219",
    "addr:postcode":"08018",
    "addr:street":"Carrer De Sant Joan De Malta",
    "iso:country":"ES",
    "sg:address":"Carrer de Sant Joan De Malta, 219",
    "sg:city":"Barcelona",
    "sg:orig_category":"Fabricaci\u00d3n, Distribuci\u00d3n De Discos, V\u00cddeodiscos Y Musicassettes",
    "sg:phone":"+34 933 08 52 92",
    "sg:postcode":"08018",
    "sg:province":"Barcelona",
    "sg:website":"www.fonodisco.es",
    "wof:name":"Edifon Distribuciones S.l.",
    "wof:placetype":"venue"
},
  "geometry": {"coordinates":[2.1987810135,41.4043426514],"type":"Point"}
}