{
  "type": "Feature",
  "properties": {
    "addr:full":"C/ Ntra. Sra. Dels Angels, 12 Ripollet Barcelona 08291",
    "addr:housenumber":"12",
    "addr:postcode":"08291",
    "addr:street":"C / Ntra. Sra. Dels Angels",
    "iso:country":"ES",
    "sg:address":"C/ Ntra. Sra. Dels Angels, 12",
    "sg:city":"Ripollet",
    "sg:orig_category":"Prendas Y Chalecos De Punto (al Por Menor)",
    "sg:phone":"+34 935 80 93 75",
    "sg:postcode":"08291",
    "sg:province":"Barcelona",
    "wof:name":"Solsona Esteve S.cp.",
    "wof:placetype":"venue"
},
  "geometry": {"coordinates":[2.1581029892,41.4984054565],"type":"Point"}
}