{
  "type": "Feature",
  "properties": {
    "addr:full":"Calle de Javier De Miguel, 40 Madrid Madrid 28018",
    "addr:housenumber":"40",
    "addr:postcode":"madrid;28018",
    "addr:street":"Calle De Javier De Miguel",
    "iso:country":"ES",
    "sg:address":"Calle de Javier De Miguel, 40",
    "sg:city":"Madrid",
    "sg:orig_category":"Abogados",
    "sg:phone":"+34 915 07 79 04",
    "sg:postcode":"28018",
    "sg:province":"Madrid",
    "wof:name":"Bravo Valentin Pilar",
    "wof:placetype":"venue"
},
  "geometry": {"coordinates":[-3.660556078,40.3875617981],"type":"Point"}
}