{
  "type": "Feature",
  "properties": {
    "iso:country":"ES",
    "sg:address":"Av Rei En Jaume, 48",
    "sg:city":"Cardedeu",
    "sg:orig_category":"Ense\u00d1anza: Profesiones Art\u00cdsticas",
    "sg:phone":"+34 938 71 22 43",
    "sg:postcode":"08440",
    "sg:province":"Barcelona",
    "wof:name":"A Cop De Llum S.c.p.",
    "wof:placetype":"venue"
},
  "geometry": {"coordinates":[2.3585908413,41.6370277405],"type":"Point"}
}