{
  "type": "Feature",
  "properties": {
    "iso:country":"ES",
    "sg:address":"Calle de Moratin, 11",
    "sg:city":"Valencia",
    "sg:orig_category":"Abogados",
    "sg:phone":"+34 963 52 70 86",
    "sg:postcode":"46002",
    "sg:province":"Valencia",
    "wof:name":"Albelda Peralt Rafael Tomas",
    "wof:placetype":"venue"
},
  "geometry": {"coordinates":[-0.3758665025,39.4710731506],"type":"Point"}
}