{
  "type": "Feature",
  "properties": {
    "addr:full":"Calle de General Diaz Porlier, 25 Madrid Madrid 28001",
    "addr:housenumber":"25",
    "addr:postcode":"madrid;28001",
    "addr:street":"Calle De General Diaz Porlier",
    "iso:country":"ES",
    "sg:address":"Calle de General Diaz Porlier, 25",
    "sg:city":"Madrid",
    "sg:orig_category":"Comunidades Religiosas",
    "sg:phone":"+34 915 75 99 81",
    "sg:postcode":"28001",
    "sg:province":"Madrid",
    "wof:name":"Agustinas Misioneras-provincia San Agust",
    "wof:placetype":"venue"
},
  "geometry": {"coordinates":[-3.6770906448,40.4269676208],"type":"Point"}
}