{
  "type": "Feature",
  "properties": {
    "iso:country":"ES",
    "sg:address":"Calle de Balsas, 5",
    "sg:city":"Santa Eulalia",
    "sg:orig_category":"Asesor\u00cda De Formaci\u00d3n Y Gesti\u00d3n De Personal",
    "sg:phone":"+34 968 22 03 46",
    "sg:postcode":"30001",
    "sg:province":"Murcia",
    "wof:name":"Celestino Molina Y Asociados S.c.",
    "wof:placetype":"venue"
},
  "geometry": {"coordinates":[-1.5738861561,37.7936096191],"type":"Point"}
}