{
  "type": "Feature",
  "properties": {
    "addr:full":"Rond Buenavista, 24 Toledo Toledo 45005",
    "addr:housenumber":"24",
    "addr:postcode":"45005",
    "addr:street":"Buenavista",
    "iso:country":"ES",
    "sg:address":"Rond Buenavista, 24",
    "sg:city":"Toledo",
    "sg:orig_category":"Centros Empresariales",
    "sg:phone":"+34 925 28 36 65",
    "sg:postcode":"45005",
    "sg:province":"Toledo",
    "wof:name":"Innopole",
    "wof:placetype":"venue"
},
  "geometry": {"coordinates":[-4.0327429771,39.8775596619],"type":"Point"}
}