{
  "type": "Feature",
  "properties": {
    "iso:country":"ES",
    "sg:address":"Carrer de Vint, 37",
    "sg:city":"Bonavista",
    "sg:orig_category":"Electrodom\u00c9sticos (al Por Menor)",
    "sg:phone":"+34 977 54 99 85",
    "sg:postcode":"43100",
    "sg:province":"Tarragona",
    "wof:name":"Electro Cupe S.l.",
    "wof:placetype":"venue"
},
  "geometry": {"coordinates":[1.1944799423,41.1188468933],"type":"Point"}
}