{
  "type": "Feature",
  "properties": {
    "iso:country":"ES",
    "sg:address":"Cami Ral, 578",
    "sg:city":"Mataro",
    "sg:orig_category":"Abogados",
    "sg:phone":"+34 937 99 54 73",
    "sg:postcode":"08302",
    "sg:province":"Barcelona",
    "wof:name":"Doria Cabot Francesc Xavier De",
    "wof:placetype":"venue"
},
  "geometry": {"coordinates":[2.439510107,41.533618927],"type":"Point"}
}