{
  "type": "Feature",
  "properties": {
    "iso:country":"ES",
    "sg:address":"Ctra Lomo Blanco, 8",
    "sg:city":"Lomo Blanco",
    "sg:orig_category":"Peluquer\u00cdas, Peluquer\u00cda Mixta",
    "sg:phone":"+34 928 35 66 25",
    "sg:postcode":"35015",
    "sg:province":"Las Palmas",
    "wof:name":"Avenue Navaro S.l.",
    "wof:placetype":"venue"
},
  "geometry": {"coordinates":[-15.4232616425,28.095746994],"type":"Point"}
}