{
  "type": "Feature",
  "properties": {
    "addr:full":"Guadalupe, 2 Novelda Guadiana Badajoz 06183",
    "addr:housenumber":"2",
    "addr:postcode":"06183",
    "addr:street":"Guadalupe",
    "iso:country":"ES",
    "sg:address":"Guadalupe, 2",
    "sg:city":"Novelda Guadiana",
    "sg:orig_category":"Cajas Para Embalar",
    "sg:phone":"+34 924 47 52 22",
    "sg:postcode":"06183",
    "sg:province":"Badajoz",
    "sg:website":"www.cajarural.com/extremadura",
    "wof:name":"Caja Rural De Extremadura",
    "wof:placetype":"venue"
},
  "geometry": {"coordinates":[-6.6902599335,38.9282913208],"type":"Point"}
}