{
  "type": "Feature",
  "properties": {
    "addr:full":"Rua Canizo, 8 Seixalbo Ourense 32970",
    "addr:housenumber":"8",
    "addr:postcode":"32970",
    "addr:street":"Rua Canizo",
    "iso:country":"ES",
    "sg:address":"Rua Canizo, 8",
    "sg:city":"Seixalbo",
    "sg:orig_category":"Pompas F\u00danebres, Inhumaciones Y Cremaciones",
    "sg:phone":"+34 988 24 73 61",
    "sg:postcode":"32970",
    "sg:province":"Ourense",
    "wof:name":"Velatorios As Burgas S.l.",
    "wof:placetype":"venue"
},
  "geometry": {"coordinates":[-7.8508682251,42.3009872437],"type":"Point"}
}