{
  "type": "Feature",
  "properties": {
    "iso:country":"ES",
    "sg:address":"Calle de Pablo Picasso, 7",
    "sg:city":"Almoradi",
    "sg:orig_category":"Agencias De Viajes",
    "sg:phone":"+34 966 78 19 50",
    "sg:postcode":"03160",
    "sg:province":"Alicante",
    "wof:name":"Fernandez Ayala Juan Manuel",
    "wof:placetype":"venue"
},
  "geometry": {"coordinates":[-0.7921900153,38.1101913452],"type":"Point"}
}