{
  "type": "Feature",
  "properties": {
    "addr:full":"Luga Piosa, 28 Tasara\u00d1o La Coru\u00f1a 15122",
    "addr:housenumber":"28",
    "addr:postcode":"15122",
    "addr:street":"Piosa;La Corun\u0303A",
    "iso:country":"ES",
    "sg:address":"Luga Piosa, 28",
    "sg:city":"Tasara\u00d1o",
    "sg:orig_category":"Aparatos De Iluminaci\u00d3n (al Por Menor)",
    "sg:phone":"+34 981 73 01 15",
    "sg:postcode":"15122",
    "sg:province":"La Coru\u00f1a",
    "wof:name":"Insmontel Cutrin S.l.",
    "wof:placetype":"venue"
},
  "geometry": {"coordinates":[-8.3959693909,43.3714904785],"type":"Point"}
}