{
  "type": "Feature",
  "properties": {
    "addr:full":"Avda Mare Nostrum, S/n Almeria Almer\u00eda 04009",
    "addr:housenumber":"s / n",
    "addr:postcode":"04009",
    "addr:street":"Avda Mare Nostrum",
    "iso:country":"ES",
    "sg:address":"Avda Mare Nostrum, S/n",
    "sg:city":"Almeria",
    "sg:orig_category":"Promotores Constructores",
    "sg:phone":"+34 950 22 71 29",
    "sg:postcode":"04009",
    "sg:province":"Almer\u00eda",
    "wof:name":"Multiservicios Zahori S.l.",
    "wof:placetype":"venue"
},
  "geometry": {"coordinates":[-2.4320890903,36.8440132141],"type":"Point"}
}