{
  "type": "Feature",
  "properties": {
    "iso:country":"ES",
    "sg:address":"Plaz Espa\u00d1a, 1",
    "sg:city":"Alca\u00f1iz",
    "sg:orig_category":"Administraciones Regionales, Departamentales Y Locales",
    "sg:phone":"+34 978 87 05 65",
    "sg:postcode":"44600",
    "sg:province":"Teruel",
    "sg:website":"www.ayto-alcaniz.es",
    "wof:name":"Ayuntamiento De Alca\u00f1iz",
    "wof:placetype":"venue"
},
  "geometry": {"coordinates":[-0.1869643927,41.0795669556],"type":"Point"}
}