{
  "type": "Feature",
  "properties": {
    "iso:country":"ES",
    "sg:address":"Calle de Ramon Y Cajal, 12",
    "sg:city":"Espiel",
    "sg:orig_category":"Delegados, Agentes De Tr\u00c1nsito, Auxiliares De Transporte Internacional",
    "sg:phone":"+34 957 36 31 80",
    "sg:postcode":"14220",
    "sg:province":"C\u00f3rdoba",
    "wof:name":"Transportes Fernandez Lopez E Hijos S.l.",
    "wof:placetype":"venue"
},
  "geometry": {"coordinates":[-5.0210390091,38.1885986328],"type":"Point"}
}