{
  "type": "Feature",
  "properties": {
    "addr:full":"Calle de Alferez Oleza Gual, 26 Palma Islas Baleares 07010",
    "addr:housenumber":"26",
    "addr:postcode":"07010",
    "addr:street":"Calle De Alferez Oleza Gual",
    "iso:country":"ES",
    "sg:address":"Calle de Alferez Oleza Gual, 26",
    "sg:city":"Palma",
    "sg:orig_category":"Reparaciones Y Remolcado De Veh\u00cdculos",
    "sg:phone":"+34 971 20 70 20",
    "sg:postcode":"07010",
    "sg:province":"Islas Baleares",
    "wof:name":"Fernandez Rodriguez Maria Dolores",
    "wof:placetype":"venue"
},
  "geometry": {"coordinates":[2.6476948261,39.5837364197],"type":"Point"}
}