{
  "type": "Feature",
  "properties": {
    "iso:country":"ES",
    "sg:address":"Avda Lugo, 17",
    "sg:city":"Palas Rei",
    "sg:orig_category":"Centros Empresariales",
    "sg:phone":"+34 982 38 01 40",
    "sg:postcode":"27200",
    "sg:province":"Lugo",
    "wof:name":"A.s.i.p.a",
    "wof:placetype":"venue"
},
  "geometry": {"coordinates":[-7.8664073944,42.8755836487],"type":"Point"}
}