{
  "type": "Feature",
  "properties": {
    "addr:full":"Avda Schulz, 29 Gijon Asturias 33208",
    "addr:housenumber":"29",
    "addr:postcode":"33208",
    "addr:street":"Avda Schulz",
    "iso:country":"ES",
    "sg:address":"Avda Schulz, 29",
    "sg:city":"Gijon",
    "sg:orig_category":"Empresas De Carpinter\u00cda",
    "sg:phone":"+34 985 16 49 04",
    "sg:postcode":"33208",
    "sg:province":"Asturias",
    "wof:name":"Carpinteria De Aluminio Y Pvc Pi\u00f1era S.l.",
    "wof:placetype":"venue"
},
  "geometry": {"coordinates":[-5.6655502319,43.534324646],"type":"Point"}
}