{
  "type": "Feature",
  "properties": {
    "addr:full":"Serra Perenxisa, 29 Aldaia Valencia 46960",
    "addr:housenumber":"29",
    "addr:postcode":"46960",
    "addr:street":"Perenxisa",
    "iso:country":"ES",
    "sg:address":"Serra Perenxisa, 29",
    "sg:city":"Aldaia",
    "sg:orig_category":"Paneles De Madera: Contrachapados, Fibras, Particulados, Estratificados (fabricaci\u00d3n, Venta)",
    "sg:phone":"+34 961 50 01 44",
    "sg:postcode":"46960",
    "sg:province":"Valencia",
    "wof:name":"Tableros Curvados Canin S. L.",
    "wof:placetype":"venue"
},
  "geometry": {"coordinates":[-0.4662809968,39.4730567932],"type":"Point"}
}