{
  "type": "Feature",
  "properties": {
    "iso:country":"ES",
    "sg:address":"Calle de Dicenta, 5",
    "sg:city":"Calatayud",
    "sg:classifiers":[
        {
            "category":"Personal",
            "subcategory":"Barber",
            "type":"Services"
        }
    ],
    "sg:phone":"+34 976 88 67 05",
    "sg:postcode":"50300",
    "sg:province":"Zaragoza",
    "sg:tags":[
        "caballeros",
        "de",
        "peluqueros"
    ],
    "wof:name":"Esteras Maluenda Jose Maria",
    "wof:placetype":"venue"
},
  "geometry": {"coordinates":[-1.6435261965,41.352771759],"type":"Point"}
}