{
  "type": "Feature",
  "properties": {
    "addr:full":"Calle de Emilio Thuillier, 54 Malaga M\u00e1laga 29014",
    "addr:housenumber":"54",
    "addr:postcode":"29014",
    "addr:street":"Calle De Emilio Thuillier;Ma\u0301Laga",
    "iso:country":"ES",
    "sg:address":"Calle de Emilio Thuillier, 54",
    "sg:city":"Malaga",
    "sg:orig_category":"Alquiler De V\u00cddeo",
    "sg:phone":"+34 952 26 31 58",
    "sg:postcode":"29014",
    "sg:province":"M\u00e1laga",
    "wof:name":"Perez Palomo Antonio Miguel",
    "wof:placetype":"venue"
},
  "geometry": {"coordinates":[-4.3667907715,36.8204078674],"type":"Point"}
}