{
  "type": "Feature",
  "properties": {
    "iso:country":"ES",
    "sg:address":"Avda Andalucia, 47",
    "sg:city":"Coripe",
    "sg:orig_category":"Material Y Herramientas Agr\u00cdcolas",
    "sg:phone":"+34 955 85 86 24",
    "sg:postcode":"41780",
    "sg:province":"Sevilla",
    "wof:name":"Campos Vazquez Cristobal",
    "wof:placetype":"venue"
},
  "geometry": {"coordinates":[-5.4397988319,36.9778289795],"type":"Point"}
}