{
  "type": "Feature",
  "properties": {
    "iso:country":"ES",
    "sg:address":"Calle de Trafalgar, 15",
    "sg:city":"Mojonera",
    "sg:orig_category":"Promotores Constructores",
    "sg:phone":"+34 950 33 06 41",
    "sg:postcode":"04745",
    "sg:province":"Almer\u00eda",
    "wof:name":"Construcciones Melidar S.l.",
    "wof:placetype":"venue"
},
  "geometry": {"coordinates":[-2.6800589561,36.7492179871],"type":"Point"}
}