{
  "type": "Feature",
  "properties": {
    "iso:country":"ES",
    "sg:address":"Calle de Huesca, 6",
    "sg:city":"Getafe",
    "sg:orig_category":"Muebles, Minoristas",
    "sg:phone":"+34 916 95 70 47",
    "sg:postcode":"28903",
    "sg:province":"Madrid",
    "wof:name":"Y-mobel",
    "wof:placetype":"venue"
},
  "geometry": {"coordinates":[-3.7180519104,40.3111419678],"type":"Point"}
}