{
  "type": "Feature",
  "properties": {
    "addr:full":"Calle de San Felipe, 12 Sevilla Sevilla 41003",
    "addr:housenumber":"12",
    "addr:postcode":"41003",
    "addr:street":"Calle De San Felipe",
    "iso:country":"ES",
    "sg:address":"Calle de San Felipe, 12",
    "sg:city":"Sevilla",
    "sg:orig_category":"M\u00c9dicos: Cirug\u00cda General",
    "sg:phone":"+34 954 22 96 15",
    "sg:postcode":"41003",
    "sg:province":"Sevilla",
    "wof:name":"Garcia-donas Abril Antonio",
    "wof:placetype":"venue"
},
  "geometry": {"coordinates":[-5.9890341759,37.3931312561],"type":"Point"}
}