{
  "type": "Feature",
  "properties": {
    "iso:country":"ES",
    "sg:address":"Carrer de Alacant, 26",
    "sg:city":"Barcelona",
    "sg:orig_category":"Bisuter\u00cda, Joyer\u00cda, Relojer\u00cda (al Por Menor)",
    "sg:phone":"+34 932 11 02 45",
    "sg:postcode":"08022",
    "sg:province":"Barcelona",
    "wof:name":"Vives Rodriguez De Inojosa Anna Maria",
    "wof:placetype":"venue"
},
  "geometry": {"coordinates":[2.1348834038,41.4011306763],"type":"Point"}
}