{
  "type": "Feature",
  "properties": {
    "addr:full":"Calle de Juan De Dios, 9 Madrid Madrid 28015",
    "addr:housenumber":"9",
    "addr:postcode":"madrid;28015",
    "addr:street":"Calle De Juan De Dios",
    "iso:country":"ES",
    "sg:address":"Calle de Juan De Dios, 9",
    "sg:city":"Madrid",
    "sg:orig_category":"Alimentaci\u00d3n General (al Por Menor)",
    "sg:phone":"+34 915 42 47 62",
    "sg:postcode":"28015",
    "sg:province":"Madrid",
    "wof:name":"Eyenga Ngua Adela",
    "wof:placetype":"venue"
},
  "geometry": {"coordinates":[-3.7100360394,40.4257659912],"type":"Point"}
}