{
  "type": "Feature",
  "properties": {
    "addr:full":"Tv. Bayona, 2 Iru\u00f1a Navarra 31011",
    "addr:housenumber":"2",
    "addr:postcode":"31011",
    "addr:street":"Bayona",
    "iso:country":"ES",
    "sg:address":"Tv. Bayona, 2",
    "sg:city":"Iru\u00f1a",
    "sg:orig_category":"Molduras, Junquillos, Listones Y Molduras Perforadas",
    "sg:phone":"+34 948 25 50 45",
    "sg:postcode":"31011",
    "sg:province":"Navarra",
    "wof:name":"Onmase S.a.l.",
    "wof:placetype":"venue"
},
  "geometry": {"coordinates":[-1.6555149555,42.8152084351],"type":"Point"}
}