{
  "type": "Feature",
  "properties": {
    "addr:full":"Carrer de Valencia, 632 Barcelona Barcelona 08026",
    "addr:housenumber":"632",
    "addr:postcode":"08026",
    "addr:street":"Carrer De Valencia",
    "iso:country":"ES",
    "sg:address":"Carrer de Valencia, 632",
    "sg:city":"Barcelona",
    "sg:orig_category":"Alquiler De V\u00cddeo",
    "sg:phone":"+34 932 32 34 07",
    "sg:postcode":"08026",
    "sg:province":"Barcelona",
    "wof:name":"Oficina De Viatges & Assegurances S.l",
    "wof:placetype":"venue"
},
  "geometry": {"coordinates":[2.1880431175,41.4110946655],"type":"Point"}
}