{
  "type": "Feature",
  "properties": {
    "iso:country":"ES",
    "sg:address":"Carrer de Viladomat, 89",
    "sg:city":"Barcelona",
    "sg:orig_category":"M\u00c1quinas De Escribir, M\u00c1quinas Calculadoras, Maquinaria De Oficina (al Por Menor Y Alquiler)",
    "sg:phone":"+34 934 23 99 69",
    "sg:postcode":"08015",
    "sg:province":"Barcelona",
    "sg:website":"www.elcodata.com",
    "wof:name":"Electronica Y Control S. A.",
    "wof:placetype":"venue"
},
  "geometry": {"coordinates":[2.1580450535,41.3789405823],"type":"Point"}
}