{
  "type": "Feature",
  "properties": {
    "addr:full":"Cno. Son Morell, S/n Ciutadella Menorca Islas Baleares 07760",
    "addr:housenumber":"s / n",
    "addr:postcode":"07760",
    "addr:street":"Cno. Son Morell",
    "iso:country":"ES",
    "sg:address":"Cno. Son Morell, S/n",
    "sg:city":"Ciutadella Menorca",
    "sg:orig_category":"Art\u00cdculos Funerarios (al Por Menor)",
    "sg:phone":"+34 971 48 19 01",
    "sg:postcode":"07760",
    "sg:province":"Islas Baleares",
    "wof:name":"Funeraria Bonets.c.p.",
    "wof:placetype":"venue"
},
  "geometry": {"coordinates":[3.8416149616,40.0027542114],"type":"Point"}
}