{
  "type": "Feature",
  "properties": {
    "addr:full":"Pase Isaac Peral, 11 Aguilas Murcia 30880",
    "addr:housenumber":"11",
    "addr:postcode":"30880",
    "addr:street":"Isaac Peral",
    "iso:country":"ES",
    "sg:address":"Pase Isaac Peral, 11",
    "sg:city":"Aguilas",
    "sg:orig_category":"Cajas De Ahorro",
    "sg:phone":"+34 968 41 48 58",
    "sg:postcode":"30880",
    "sg:province":"Murcia",
    "wof:name":"Caja De Ahorros De Valencia Castellon Y Alicante",
    "wof:placetype":"venue"
},
  "geometry": {"coordinates":[-1.5803740025,37.4031562805],"type":"Point"}
}