{
  "type": "Feature",
  "properties": {
    "addr:full":"Calle de Alamos (los), 31 Sant Joan D'alacant Alicante 03550",
    "addr:housenumber":"31",
    "addr:postcode":"03550",
    "addr:street":"Calle De Alamos Los",
    "iso:country":"ES",
    "sg:address":"Calle de Alamos (los), 31",
    "sg:city":"Sant Joan D'alacant",
    "sg:orig_category":"Ingenier\u00cda, Centros De Estudios (diversos)",
    "sg:phone":"+34 965 65 13 44",
    "sg:postcode":"03550",
    "sg:province":"Alicante",
    "wof:name":"Bultectonics S.l.u.",
    "wof:placetype":"venue"
},
  "geometry": {"coordinates":[-0.434415102,38.4056129456],"type":"Point"}
}