{
  "type": "Feature",
  "properties": {
    "iso:country":"ES",
    "sg:address":"Infantas",
    "sg:city":"Alcorcon",
    "sg:orig_category":"Poller\u00cda Y Caza (al Por Menor)",
    "sg:phone":"+34 916 43 75 80",
    "sg:postcode":"28922",
    "sg:province":"Madrid",
    "wof:name":"Vico Castillo Manuel",
    "wof:placetype":"venue"
},
  "geometry": {"coordinates":[-3.8319690228,40.3465385437],"type":"Point"}
}