{
  "type": "Feature",
  "properties": {
    "iso:country":"ES",
    "sg:address":"Carr Pi I Margall, 3",
    "sg:city":"Torroella Montgri",
    "sg:classifiers":[
        {
            "category":"Personal",
            "subcategory":"Barber",
            "type":"Services"
        }
    ],
    "sg:phone":"+34 972 75 82 98",
    "sg:postcode":"17257",
    "sg:province":"Girona",
    "sg:tags":[
        "caballeros",
        "de",
        "peluqueros"
    ],
    "wof:name":"Ruiz Amer Enric",
    "wof:placetype":"venue"
},
  "geometry": {"coordinates":[3.1257050037,42.040271759],"type":"Point"}
}