{
  "type": "Feature",
  "properties": {
    "addr:full":"Calle de Rafael Alberti, 48 Caceres C\u00e1ceres 10005",
    "addr:housenumber":"48",
    "addr:postcode":"10005",
    "addr:street":"Calle De Rafael Alberti;Ca\u0301Ceres",
    "iso:country":"ES",
    "sg:address":"Calle de Rafael Alberti, 48",
    "sg:city":"Caceres",
    "sg:orig_category":"Arquitectos",
    "sg:phone":"+34 927 23 13 51",
    "sg:postcode":"10005",
    "sg:province":"C\u00e1ceres",
    "wof:name":"Manso Rapado Francisco Javier",
    "wof:placetype":"venue"
},
  "geometry": {"coordinates":[-6.3965291977,39.472869873],"type":"Point"}
}