{
  "type": "Feature",
  "properties": {
    "addr:full":"Carrer de Sant Vicent Ferrer, 12 Crevillent Alicante 03330",
    "addr:housenumber":"12",
    "addr:postcode":"03330",
    "addr:street":"Carrer De Sant Vicent Ferrer",
    "iso:country":"ES",
    "sg:address":"Carrer de Sant Vicent Ferrer, 12",
    "sg:city":"Crevillent",
    "sg:orig_category":"Ropa Para Beb\u00c9s Y Ni\u00d1os (confecci\u00d3n, Al Por Mayor)",
    "sg:phone":"+34 966 68 05 85",
    "sg:postcode":"03330",
    "sg:province":"Alicante",
    "sg:website":"www.boutique-naco.com",
    "wof:name":"Izerbb S.l.",
    "wof:placetype":"venue"
},
  "geometry": {"coordinates":[-0.8079010248,38.2455444336],"type":"Point"}
}