{
  "type": "Feature",
  "properties": {
    "iso:country":"ES",
    "sg:address":"Calle de Laguna, 12",
    "sg:city":"Madrid",
    "sg:orig_category":"Tintorer\u00cdas, Limpieza En Seco",
    "sg:phone":"+34 914 65 17 04",
    "sg:postcode":"28047",
    "sg:province":"Madrid",
    "wof:name":"Pajares Ria\u00f1o Victoriano",
    "wof:placetype":"venue"
},
  "geometry": {"coordinates":[-3.7423241138,40.3915290833],"type":"Point"}
}