{
  "type": "Feature",
  "properties": {
    "iso:country":"ES",
    "sg:address":"Avda Mediterraneo (del), S/n",
    "sg:city":"Almeria",
    "sg:orig_category":"Bisuter\u00cda, Joyer\u00cda, Relojer\u00cda (al Por Menor)",
    "sg:phone":"+34 950 62 43 25",
    "sg:postcode":"04007",
    "sg:province":"Almer\u00eda",
    "wof:name":"Joyeria Jose Luis S.l.",
    "wof:placetype":"venue"
},
  "geometry": {"coordinates":[-2.4460990429,36.8307914734],"type":"Point"}
}