{
  "type": "Feature",
  "properties": {
    "addr:full":"Ctra Vic, 256 Manresa Barcelona 08243",
    "addr:housenumber":"256",
    "addr:postcode":"08243",
    "addr:street":"Ctra Vic",
    "iso:country":"ES",
    "sg:address":"Ctra Vic, 256",
    "sg:city":"Manresa",
    "sg:orig_category":"Electricidad Veh\u00cdculo",
    "sg:phone":"+34 938 73 22 73",
    "sg:postcode":"08243",
    "sg:province":"Barcelona",
    "wof:name":"Arpa Barchino Ramon",
    "wof:placetype":"venue"
},
  "geometry": {"coordinates":[1.8425486088,41.7352638245],"type":"Point"}
}