{
  "type": "Feature",
  "properties": {
    "addr:full":"Calle de Etxebarria Tar Kresentzi, 21 Bermeo Vizcaya 48370",
    "addr:housenumber":"21",
    "addr:postcode":"48370",
    "addr:street":"Calle De Etxebarria Tar Kresentzi",
    "iso:country":"ES",
    "sg:address":"Calle de Etxebarria Tar Kresentzi, 21",
    "sg:city":"Bermeo",
    "sg:orig_category":"Lencer\u00cda Femenina, Corseter\u00cda, Trajes De Ba\u00d1o (al Por Menor)",
    "sg:phone":"+34 946 88 59 92",
    "sg:postcode":"48370",
    "sg:province":"Vizcaya",
    "wof:name":"Garcia Alonso Araceli",
    "wof:placetype":"venue"
},
  "geometry": {"coordinates":[-2.7481176853,43.4026641846],"type":"Point"}
}