{
  "type": "Feature",
  "properties": {
    "iso:country":"ES",
    "sg:address":"Pl. Consistorial, 1",
    "sg:city":"Iru\u00f1a",
    "sg:orig_category":"Ropa Para Se\u00d1oras Y Caballeros (al Por Menor)",
    "sg:phone":"+34 948 22 55 93",
    "sg:postcode":"31001",
    "sg:province":"Navarra",
    "wof:name":"Gutierrez Jimeno Martin",
    "wof:placetype":"venue"
},
  "geometry": {"coordinates":[-1.6437840462,42.8182106018],"type":"Point"}
}