{
  "type": "Feature",
  "properties": {
    "iso:country":"ES",
    "sg:address":"Calle de San Jacinto, 1",
    "sg:city":"Sevilla",
    "sg:orig_category":"Bancos",
    "sg:phone":"+34 954 33 33 96",
    "sg:postcode":"41010",
    "sg:province":"Sevilla",
    "wof:name":"Bt Espa\u00d1a Compa\u00d1ia De Servicios Globales De Telecomunicaciones S.a.u.",
    "wof:placetype":"venue"
},
  "geometry": {"coordinates":[-6.0033588409,37.3849945068],"type":"Point"}
}