{
  "type": "Feature",
  "properties": {
    "addr:full":"Calle de Urano, 12 Pozuelo De Alarcon Madrid 28224",
    "addr:housenumber":"12",
    "addr:postcode":"28224",
    "addr:street":"Calle De Urano",
    "iso:country":"ES",
    "sg:address":"Calle de Urano, 12",
    "sg:city":"Pozuelo De Alarcon",
    "sg:orig_category":"Agencias Y Asesores De Publicidad",
    "sg:phone":"+34 917 99 14 40",
    "sg:postcode":"28224",
    "sg:province":"Madrid",
    "wof:name":"Criterio De Publicidad Y Marketing S.l.",
    "wof:placetype":"venue"
},
  "geometry": {"coordinates":[-3.7930428982,40.4424514771],"type":"Point"}
}