{
  "type": "Feature",
  "properties": {
    "iso:country":"ES",
    "sg:address":"Calle de Sanz De Bremond, 18",
    "sg:city":"Castellon",
    "sg:orig_category":"\u00d3ptica: Instrumentos (fabricaci\u00d3n)",
    "sg:phone":"+34 964 23 21 57",
    "sg:postcode":"12004",
    "sg:province":"Castell\u00f3n",
    "wof:name":"Prats Monforte Consuelo",
    "wof:placetype":"venue"
},
  "geometry": {"coordinates":[-0.0328049995,39.9912414551],"type":"Point"}
}