{
  "type": "Feature",
  "properties": {
    "addr:full":"Cami Son Rapinya, 65 Vileta -son Rapinya Islas Baleares 07013",
    "addr:housenumber":"65",
    "addr:postcode":"07013",
    "addr:street":"Rapinya;Vileta Son;Islas",
    "iso:country":"ES",
    "sg:address":"Cami Son Rapinya, 65",
    "sg:city":"Vileta -son Rapinya",
    "sg:orig_category":"Farmacias",
    "sg:phone":"+34 971 79 33 37",
    "sg:postcode":"07013",
    "sg:province":"Islas Baleares",
    "wof:name":"Caldentey Vives Carmen",
    "wof:placetype":"venue"
},
  "geometry": {"coordinates":[2.6150588989,39.5871963501],"type":"Point"}
}