{
  "type": "Feature",
  "properties": {
    "iso:country":"ES",
    "sg:address":"Carrer de Circumval.lacio, 11",
    "sg:city":"Viladecans",
    "sg:orig_category":"Confecci\u00d3n De Trajes Para Se\u00d1oras",
    "sg:phone":"+34 936 58 32 58",
    "sg:postcode":"08840",
    "sg:province":"Barcelona",
    "wof:name":"Hernandez Benito Desiderio",
    "wof:placetype":"venue"
},
  "geometry": {"coordinates":[2.0078120232,41.3219146729],"type":"Point"}
}