{
  "type": "Feature",
  "properties": {
    "iso:country":"ES",
    "sg:address":"Carr Barcelona, 31",
    "sg:city":"Girona",
    "sg:orig_category":"Doctores En Medicina",
    "sg:phone":"+34 972 21 67 11",
    "sg:postcode":"17002",
    "sg:province":"Girona",
    "wof:name":"Jubert Gimbernat Jose",
    "wof:placetype":"venue"
},
  "geometry": {"coordinates":[2.8183670044,41.9794540405],"type":"Point"}
}