{
  "type": "Feature",
  "properties": {
    "addr:full":"Calle de Zamora, 17 Salamanca Salamanca 37002",
    "addr:housenumber":"17",
    "addr:postcode":"37002",
    "addr:street":"Calle De Zamora",
    "iso:country":"ES",
    "sg:address":"Calle de Zamora, 17",
    "sg:city":"Salamanca",
    "sg:orig_category":"Peluqueros: De Se\u00d1oras",
    "sg:phone":"+34 923 28 03 35",
    "sg:postcode":"37002",
    "sg:province":"Salamanca",
    "wof:name":"Paco-charo Peluqueros S.l.",
    "wof:placetype":"venue"
},
  "geometry": {"coordinates":[-5.6641840935,40.9661407471],"type":"Point"}
}