{
  "type": "Feature",
  "properties": {
    "addr:full":"Calle de Galdames, 2 Ayamonte Huelva 21400",
    "addr:housenumber":"2",
    "addr:postcode":"21400",
    "addr:street":"Calle De Galdames",
    "iso:country":"ES",
    "sg:address":"Calle de Galdames, 2",
    "sg:city":"Ayamonte",
    "sg:orig_category":"Restaurantes",
    "sg:phone":"+34 959 47 03 94",
    "sg:postcode":"21400",
    "sg:province":"Huelva",
    "wof:name":"Meson Los Caleros S.l.",
    "wof:placetype":"venue"
},
  "geometry": {"coordinates":[-7.407365799,37.2205314636],"type":"Point"}
}