{
  "type": "Feature",
  "properties": {
    "addr:full":"Calle de Jose Silva, 7 Madrid Madrid 28043",
    "addr:housenumber":"7",
    "addr:postcode":"madrid;28043",
    "addr:street":"Calle De Jose Silva",
    "iso:country":"ES",
    "sg:address":"Calle de Jose Silva, 7",
    "sg:city":"Madrid",
    "sg:orig_category":"M\u00c9dicos: Ginecolog\u00cda M\u00c9dica, Obstetricia",
    "sg:phone":"+34 917 44 41 00",
    "sg:postcode":"28043",
    "sg:province":"Madrid",
    "sg:website":"www.clinicabelen.es",
    "wof:name":"Clinica De Maternidad Nuestra Se\u00d1ora De Belen S.a.",
    "wof:placetype":"venue"
},
  "geometry": {"coordinates":[-3.6573019028,40.4552268982],"type":"Point"}
}