{
  "type": "Feature",
  "properties": {
    "iso:country":"ES",
    "sg:address":"Ctra Camposancos, 219",
    "sg:city":"Verdeal",
    "sg:orig_category":"Caf\u00c9s, Bares, Cervecer\u00cdas",
    "sg:phone":"+34 986 49 12 05",
    "sg:postcode":"36330",
    "sg:province":"Pontevedra",
    "wof:name":"Public Phone Noroeste S.l.",
    "wof:placetype":"venue"
},
  "geometry": {"coordinates":[-8.694773674,42.6678962708],"type":"Point"}
}