{
  "type": "Feature",
  "properties": {
    "addr:full":"Calle de Huerta De Casta\u00d1eda, 44 Madrid Madrid 28011",
    "addr:housenumber":"44",
    "addr:postcode":"madrid;28011",
    "addr:street":"Calle De Huerta De Castan\u0303Eda",
    "iso:country":"ES",
    "sg:address":"Calle de Huerta De Casta\u00d1eda, 44",
    "sg:city":"Madrid",
    "sg:orig_category":"Estilistas Y Estudios De Estilo De Corte Y Confecci\u00d3n",
    "sg:phone":"+34 914 64 50 98",
    "sg:postcode":"28011",
    "sg:province":"Madrid",
    "wof:name":"Roba Blaya Francisco",
    "wof:placetype":"venue"
},
  "geometry": {"coordinates":[-3.7422819138,40.4049491882],"type":"Point"}
}