{
  "type": "Feature",
  "properties": {
    "iso:country":"ES",
    "sg:address":"Emilio Arrieta, 16",
    "sg:city":"Iru\u00f1a",
    "sg:orig_category":"Abogados",
    "sg:phone":"+34 948 22 59 16",
    "sg:postcode":"31002",
    "sg:province":"Navarra",
    "wof:name":"Lecumberri De Castro Pilar Y Murillo Azcona Maria Isabel S.cv",
    "wof:placetype":"venue"
},
  "geometry": {"coordinates":[-1.6417528391,42.8135948181],"type":"Point"}
}