{
  "type": "Feature",
  "properties": {
    "iso:country":"ES",
    "sg:address":"Avda Ricardo Soriano, 12",
    "sg:city":"Marbella",
    "sg:orig_category":"M\u00c9dicos: Foniatr\u00cda Y Logopedia",
    "sg:phone":"+34 951 31 72 55",
    "sg:postcode":"29600",
    "sg:province":"M\u00e1laga",
    "wof:name":"Hinestrosa Silva Dolores",
    "wof:placetype":"venue"
},
  "geometry": {"coordinates":[-4.8877000809,36.5098266602],"type":"Point"}
}