{
  "type": "Feature",
  "properties": {
    "addr:full":"Calle de Antonio Reyes Huertas, 15 Caceres C\u00e1ceres 10002",
    "addr:housenumber":"15",
    "addr:postcode":"10002",
    "addr:street":"Calle De Antonio Reyes Huertas;Ca\u0301Ceres",
    "iso:country":"ES",
    "sg:address":"Calle de Antonio Reyes Huertas, 15",
    "sg:city":"Caceres",
    "sg:orig_category":"Empresas De Limpieza",
    "sg:phone":"+34 927 21 60 06",
    "sg:postcode":"10002",
    "sg:province":"C\u00e1ceres",
    "wof:name":"A.c.s. Limpiezas S.l.",
    "wof:placetype":"venue"
},
  "geometry": {"coordinates":[-6.3761773109,39.467628479],"type":"Point"}
}