{
  "type": "Feature",
  "properties": {
    "addr:full":"Calle de Huertas, 20 Pe\u00f1afiel Valladolid 47300",
    "addr:housenumber":"20",
    "addr:postcode":"47300",
    "addr:street":"Calle De Huertas",
    "iso:country":"ES",
    "sg:address":"Calle de Huertas, 20",
    "sg:city":"Pe\u00f1afiel",
    "sg:orig_category":"Construcci\u00d3n De Edificios Residenciales Y No Residenciales",
    "sg:phone":"+34 983 88 18 67",
    "sg:postcode":"47300",
    "sg:province":"Valladolid",
    "wof:name":"Garcia Minguez Javier",
    "wof:placetype":"venue"
},
  "geometry": {"coordinates":[-4.1243419647,41.5986022949],"type":"Point"}
}