{
  "type": "Feature",
  "properties": {
    "addr:full":"Ctra Ademuz, Km. 0033,0 Casinos Valencia 46171",
    "addr:postcode":"46171",
    "addr:street":"Ctra Ademuz Km. 0033,0",
    "iso:country":"ES",
    "sg:address":"Ctra Ademuz, Km. 0033,0",
    "sg:city":"Casinos",
    "sg:orig_category":"Arenas, Guijarros Y Granulados",
    "sg:phone":"+34 962 70 01 44",
    "sg:postcode":"46171",
    "sg:province":"Valencia",
    "wof:name":"Triturados Elcano S.l.",
    "wof:placetype":"venue"
},
  "geometry": {"coordinates":[-0.7101870179,39.6979827881],"type":"Point"}
}