{
  "type": "Feature",
  "properties": {
    "iso:country":"ES",
    "sg:address":"Calle de Gaztelu, 24",
    "sg:city":"Donostia-san Sebastian",
    "sg:orig_category":"Importaci\u00d3n",
    "sg:phone":"+34 943 29 74 25",
    "sg:postcode":"20013",
    "sg:province":"Guip\u00f9zcoa",
    "wof:name":"Manver Gizartea S.l.",
    "wof:placetype":"venue"
},
  "geometry": {"coordinates":[-1.9551559687,43.3183937073],"type":"Point"}
}