{
  "type": "Feature",
  "properties": {
    "iso:country":"ES",
    "sg:address":"Calle de Honduras, 31",
    "sg:city":"Coslada",
    "sg:orig_category":"Aparcamientos (infraestructuras, Accesorios)",
    "sg:phone":"+34 916 73 73 81",
    "sg:postcode":"28820",
    "sg:province":"Madrid",
    "wof:name":"Aparcamiemto Tramo-c Rambla Coslada S.l.",
    "wof:placetype":"venue"
},
  "geometry": {"coordinates":[-3.5498318672,40.4254989624],"type":"Point"}
}