{
  "type": "Feature",
  "properties": {
    "iso:country":"ES",
    "sg:address":"Calle de Moreno De Mora, 4",
    "sg:city":"Ubrique",
    "sg:orig_category":"Agentes Generales De Seguros",
    "sg:phone":"+34 956 46 40 14",
    "sg:postcode":"11600",
    "sg:province":"C\u00e1diz",
    "wof:name":"Casiano Lopez S.l.u.",
    "wof:placetype":"venue"
},
  "geometry": {"coordinates":[-5.4436187744,36.6765937805],"type":"Point"}
}