{
  "type": "Feature",
  "properties": {
    "addr:full":"Ll Domenech I Muntane, 6 El Vendrell Tarragona 43700",
    "addr:housenumber":"6",
    "addr:postcode":"43700",
    "addr:street":"Muntane",
    "iso:country":"ES",
    "sg:address":"Ll Domenech I Muntane, 6",
    "sg:city":"El Vendrell",
    "sg:orig_category":"Agencias Y Agentes Comerciales, Representantes",
    "sg:phone":"+34 977 66 11 91",
    "sg:postcode":"43700",
    "sg:province":"Tarragona",
    "wof:name":"Acif Ponent S.l.",
    "wof:placetype":"venue"
},
  "geometry": {"coordinates":[1.5111806393,41.2207603455],"type":"Point"}
}