{
  "type": "Feature",
  "properties": {
    "addr:full":"Pase Carmelitas, 57 Salamanca Salamanca 37002",
    "addr:housenumber":"57",
    "addr:postcode":"37002",
    "addr:street":"Carmelitas",
    "iso:country":"ES",
    "sg:address":"Pase Carmelitas, 57",
    "sg:city":"Salamanca",
    "sg:orig_category":"Inmobiliaria (agencias)",
    "sg:phone":"+34 923 21 69 66",
    "sg:postcode":"37002",
    "sg:province":"Salamanca",
    "wof:name":"Constructora Inmobiliaria Salmantina",
    "wof:placetype":"venue"
},
  "geometry": {"coordinates":[-5.6666841507,40.9685516357],"type":"Point"}
}