{
  "type": "Feature",
  "properties": {
    "iso:country":"ES",
    "sg:address":"Calle de Juan De Berrueta, 3",
    "sg:city":"Sang\u00fcesa",
    "sg:orig_category":"Plomeros",
    "sg:phone":"+34 948 43 05 08",
    "sg:postcode":"31400",
    "sg:province":"Navarra",
    "wof:name":"Fontaneria Leire S.l.",
    "wof:placetype":"venue"
},
  "geometry": {"coordinates":[-1.2851810455,42.5765953064],"type":"Point"}
}