{
  "type": "Feature",
  "properties": {
    "iso:country":"ES",
    "sg:address":"Calle de Zaida, 46",
    "sg:city":"Madrid",
    "sg:orig_category":"Molduras, Junquillos, Listones Y Molduras Perforadas",
    "sg:phone":"+34 914 66 42 29",
    "sg:postcode":"28019",
    "sg:province":"Madrid",
    "wof:name":"Martin Sanchez Teodoro",
    "wof:placetype":"venue"
},
  "geometry": {"coordinates":[-3.7357969284,40.3922348022],"type":"Point"}
}