{
  "type": "Feature",
  "properties": {
    "addr:full":"Carrer de Francoli, 25 Barcelona Barcelona 08006",
    "addr:housenumber":"25",
    "addr:postcode":"08006",
    "addr:street":"Carrer De Francoli",
    "iso:country":"ES",
    "sg:address":"Carrer de Francoli, 25",
    "sg:city":"Barcelona",
    "sg:orig_category":"Herboristas (al Por Menor)",
    "sg:phone":"+34 932 38 03 40",
    "sg:postcode":"08006",
    "sg:province":"Barcelona",
    "wof:name":"Bolos Marti Elvira",
    "wof:placetype":"venue"
},
  "geometry": {"coordinates":[2.1473639011,41.4041671753],"type":"Point"}
}