{
  "type": "Feature",
  "properties": {
    "iso:country":"ES",
    "sg:address":"La Constitucion, 4",
    "sg:city":"Valverde",
    "sg:orig_category":"Reposter\u00cdas",
    "sg:phone":"+34 922 55 18 99",
    "sg:postcode":"38910",
    "sg:province":"Santa Cruz De Tenerife",
    "wof:name":"C.b. Boutique Del Pan De La Villa",
    "wof:placetype":"venue"
},
  "geometry": {"coordinates":[-17.8970718384,27.8238143921],"type":"Point"}
}