{
  "type": "Feature",
  "properties": {
    "iso:country":"ES",
    "sg:address":"Calle de Padre Ruiz Candil, 16",
    "sg:city":"Jerez De La Frontera",
    "sg:orig_category":"M\u00c9dicos: Pediatr\u00cda. Enfermedades De Los Ni\u00d1os",
    "sg:phone":"+34 956 34 66 73",
    "sg:postcode":"11405",
    "sg:province":"C\u00e1diz",
    "wof:name":"Prieto Soler Francisco",
    "wof:placetype":"venue"
},
  "geometry": {"coordinates":[-6.129529953,36.6864852905],"type":"Point"}
}