{
  "type": "Feature",
  "properties": {
    "addr:full":"Calle de Arechaga, 14 Bilbao Vizcaya 48003",
    "addr:housenumber":"14",
    "addr:postcode":"48003",
    "addr:street":"Calle De Arechaga",
    "iso:country":"ES",
    "sg:address":"Calle de Arechaga, 14",
    "sg:city":"Bilbao",
    "sg:orig_category":"Alimentaci\u00d3n General (al Por Menor)",
    "sg:phone":"+34 944 16 56 78",
    "sg:postcode":"48003",
    "sg:province":"Vizcaya",
    "wof:name":"Linares Esquerra Angel",
    "wof:placetype":"venue"
},
  "geometry": {"coordinates":[-2.9264953136,43.2549247742],"type":"Point"}
}