{
  "type": "Feature",
  "properties": {
    "addr:full":"Cami Son Toells, 12 Sant Agusti Islas Baleares 07015",
    "addr:housenumber":"12",
    "addr:postcode":"07015",
    "addr:street":"Toells",
    "iso:country":"ES",
    "sg:address":"Cami Son Toells, 12",
    "sg:city":"Sant Agusti",
    "sg:orig_category":"Farmacias",
    "sg:phone":"+34 971 40 57 06",
    "sg:postcode":"07015",
    "sg:province":"Islas Baleares",
    "wof:name":"Sastre Daviu Maria Pilar",
    "wof:placetype":"venue"
},
  "geometry": {"coordinates":[2.5971109867,39.5515823364],"type":"Point"}
}