{
  "type": "Feature",
  "properties": {
    "addr:full":"Urb Colinas De Marbella (las), S/n Colinas De Marbella M\u00e1laga 29679",
    "addr:postcode":"29679",
    "addr:street":"Urb;Las S / N Colinas De Marbella Ma\u0301Laga",
    "iso:country":"ES",
    "sg:address":"Urb Colinas De Marbella (las), S/n",
    "sg:city":"Colinas De Marbella",
    "sg:orig_category":"Inmobiliaria (agencias)",
    "sg:phone":"+34 952 78 78 29",
    "sg:postcode":"29679",
    "sg:province":"M\u00e1laga",
    "wof:name":"Chasan Internacional Desarrollo S.l.",
    "wof:placetype":"venue"
},
  "geometry": {"coordinates":[-5.0462741852,36.5238952637],"type":"Point"}
}