{
  "type": "Feature",
  "properties": {
    "addr:full":"Plaz Santo Domingo, 21 Sang\u00fcesa Navarra 31400",
    "addr:housenumber":"21",
    "addr:postcode":"31400",
    "addr:street":"Santo Domingo",
    "iso:country":"ES",
    "sg:address":"Plaz Santo Domingo, 21",
    "sg:city":"Sang\u00fcesa",
    "sg:orig_category":"Empresas De Limpieza",
    "sg:phone":"+34 948 43 06 28",
    "sg:postcode":"31400",
    "sg:province":"Navarra",
    "sg:website":"www.ecojarlim.com",
    "wof:name":"Ecojarlim Sanguesa S.l.",
    "wof:placetype":"venue"
},
  "geometry": {"coordinates":[-1.2806440592,42.5711250305],"type":"Point"}
}