{
  "type": "Feature",
  "properties": {
    "iso:country":"ES",
    "sg:address":"Calle de Esteban Ramirez Martinez (de), 2",
    "sg:city":"Jaen",
    "sg:orig_category":"Asesor\u00cda Sobre Comunicaci\u00d3n De Empresas",
    "sg:phone":"+34 953 29 17 35",
    "sg:postcode":"23008",
    "sg:province":"Ja\u00e9n",
    "wof:name":"Gabinete Empresarial De Jaen S.l.",
    "wof:placetype":"venue"
},
  "geometry": {"coordinates":[-3.7890706062,37.7852325439],"type":"Point"}
}