{
  "type": "Feature",
  "properties": {
    "addr:full":"Calle de Islas Marquesas, 6 Madrid Madrid 28035",
    "addr:housenumber":"6",
    "addr:postcode":"28035",
    "addr:street":"Calle De Islas Marquesas",
    "iso:country":"ES",
    "sg:address":"Calle de Islas Marquesas, 6",
    "sg:city":"Madrid",
    "sg:orig_category":"Agentes Generales De Seguros",
    "sg:phone":"+34 913 86 99 56",
    "sg:postcode":"28035",
    "sg:province":"Madrid",
    "wof:name":"Galan Morales Jose Tomas",
    "wof:placetype":"venue"
},
  "geometry": {"coordinates":[-3.7259891033,40.4750976562],"type":"Point"}
}