{
  "type": "Feature",
  "properties": {
    "iso:country":"ES",
    "sg:address":"Txikierdi Auzoa, 7",
    "sg:city":"Txikierdi",
    "sg:orig_category":"Bisuter\u00cda, Joyer\u00cda, Relojer\u00cda (al Por Menor)",
    "sg:phone":"+34 943 36 70 04",
    "sg:postcode":"20170",
    "sg:province":"Guip\u00f9zcoa",
    "sg:website":"www.bijoubrigitte.com",
    "wof:name":"Bijou Brigitte Modische Accesoires S.l.",
    "wof:placetype":"venue"
},
  "geometry": {"coordinates":[-2.0539140701,43.2733459473],"type":"Point"}
}