{
  "type": "Feature",
  "properties": {
    "iso:country":"ES",
    "sg:address":"Carrer de Baixada De La Font, 14",
    "sg:city":"Mar\u00e7a",
    "sg:orig_category":"Centros De Educaci\u00d3n Especial",
    "sg:phone":"+34 977 17 82 16",
    "sg:postcode":"43775",
    "sg:province":"Tarragona",
    "wof:name":"Ceip Anicet Villar S.a.",
    "wof:placetype":"venue"
},
  "geometry": {"coordinates":[0.8010500073,41.1268997192],"type":"Point"}
}