{
  "type": "Feature",
  "properties": {
    "iso:country":"ES",
    "sg:address":"Avda Constitucion, 139",
    "sg:city":"Torredelcampo",
    "sg:orig_category":"Droguer\u00cdas (al Por Menor)",
    "sg:phone":"+34 953 41 03 22",
    "sg:postcode":"23640",
    "sg:province":"Ja\u00e9n",
    "wof:name":"Exposito Mu\u00f1oz Rosa",
    "wof:placetype":"venue"
},
  "geometry": {"coordinates":[-3.8963449001,37.7726402283],"type":"Point"}
}