{
  "type": "Feature",
  "properties": {
    "addr:full":"Calle de Maestra, 120 Mancha Real Ja\u00e9n 23100",
    "addr:housenumber":"120",
    "addr:postcode":"23100",
    "addr:street":"Calle De Maestra",
    "iso:country":"ES",
    "sg:address":"Calle de Maestra, 120",
    "sg:city":"Mancha Real",
    "sg:orig_category":"Loter\u00cda Y T\u00d3mbola",
    "sg:phone":"+34 953 35 27 05",
    "sg:postcode":"23100",
    "sg:province":"Ja\u00e9n",
    "wof:name":"Vargas Martinez Isabel",
    "wof:placetype":"venue"
},
  "geometry": {"coordinates":[-3.6096179485,37.7862091064],"type":"Point"}
}