{
  "type": "Feature",
  "properties": {
    "iso:country":"ES",
    "sg:address":"Calle de Pintor Velazquez, 12",
    "sg:city":"Granada",
    "sg:orig_category":"Doctores En Medicina",
    "sg:phone":"+34 958 27 32 19",
    "sg:postcode":"18002",
    "sg:province":"Granada",
    "wof:name":"Garcia Polo Ramon",
    "wof:placetype":"venue"
},
  "geometry": {"coordinates":[-3.6079769135,37.1772117615],"type":"Point"}
}