{
  "type": "Feature",
  "properties": {
    "iso:country":"ES",
    "sg:address":"Ctra Rosario (del), 132",
    "sg:city":"Santa Cruz De Tenerife",
    "sg:orig_category":"Asociaciones Y Clubs Deportivos",
    "sg:phone":"+34 922 64 27 87",
    "sg:postcode":"38009",
    "sg:province":"Santa Cruz De Tenerife",
    "wof:name":"Hernandez Cabrera Feliciano",
    "wof:placetype":"venue"
},
  "geometry": {"coordinates":[-17.7755756378,28.6416091919],"type":"Point"}
}