{
  "type": "Feature",
  "properties": {
    "addr:full":"Trss Sindicat, 8 Soses Lleida 25181",
    "addr:housenumber":"8",
    "addr:postcode":"25181",
    "addr:street":"Sindicat",
    "iso:country":"ES",
    "sg:address":"Trss Sindicat, 8",
    "sg:city":"Soses",
    "sg:orig_category":"Sanatorios M\u00c9dico",
    "sg:phone":"+34 973 79 75 04",
    "sg:postcode":"25181",
    "sg:province":"Lleida",
    "wof:name":"Ajuntament De Soses",
    "wof:placetype":"venue"
},
  "geometry": {"coordinates":[0.4596720934,41.5303535461],"type":"Point"}
}