{
  "type": "Feature",
  "properties": {
    "addr:full":"Carrer de Providencia, 119 Barcelona Barcelona 08024",
    "addr:housenumber":"119",
    "addr:postcode":"08024",
    "addr:street":"Carrer De Providencia",
    "iso:country":"ES",
    "sg:address":"Carrer de Providencia, 119",
    "sg:city":"Barcelona",
    "sg:orig_category":"Guarder\u00cdas",
    "sg:phone":"+34 932 19 69 41",
    "sg:postcode":"08024",
    "sg:province":"Barcelona",
    "wof:name":"Sellares Serra Susana",
    "wof:placetype":"venue"
},
  "geometry": {"coordinates":[2.1615860462,41.4094200134],"type":"Point"}
}