{
  "type": "Feature",
  "properties": {
    "addr:full":"Calle de Racholar De Matilda, 36 Racholar Castell\u00f3n 12200",
    "addr:housenumber":"36",
    "addr:postcode":"12200",
    "addr:street":"Calle De Racholar De Matilda;Castello\u0301N",
    "iso:country":"ES",
    "sg:address":"Calle de Racholar De Matilda, 36",
    "sg:city":"Racholar",
    "sg:orig_category":"Paletas",
    "sg:phone":"+34 964 60 13 78",
    "sg:postcode":"12200",
    "sg:province":"Castell\u00f3n",
    "wof:name":"Serreria Y Pallets Chiva S.l.",
    "wof:placetype":"venue"
},
  "geometry": {"coordinates":[-0.2620640099,39.9651794434],"type":"Point"}
}