{
  "type": "Feature",
  "properties": {
    "iso:country":"ES",
    "sg:address":"Calle de Asuncion, 35",
    "sg:city":"Sevilla",
    "sg:orig_category":"Zapatos (al Por Menor)",
    "sg:phone":"+34 954 27 85 18",
    "sg:postcode":"41011",
    "sg:province":"Sevilla",
    "wof:name":"Ortiz Blazquez Francisco",
    "wof:placetype":"venue"
},
  "geometry": {"coordinates":[-5.9976010323,37.3767089844],"type":"Point"}
}