{
  "type": "Feature",
  "properties": {
    "addr:full":"Plaz Mayor, 11 Valladolid Valladolid 47001",
    "addr:housenumber":"11",
    "addr:postcode":"47001",
    "addr:street":"Plaz Mayor",
    "iso:country":"ES",
    "sg:address":"Plaz Mayor, 11",
    "sg:city":"Valladolid",
    "sg:orig_category":"\u00d3ptica: Instrumentos (fabricaci\u00d3n)",
    "sg:phone":"+34 983 35 66 62",
    "sg:postcode":"47001",
    "sg:province":"Valladolid",
    "sg:website":"paginasamarillas.es",
    "wof:name":"Tremi\u00f1o S. A.",
    "wof:placetype":"venue"
},
  "geometry": {"coordinates":[-4.7283830643,41.6515312195],"type":"Point"}
}