{
  "type": "Feature",
  "properties": {
    "iso:country":"ES",
    "sg:address":"Av Joan Miro, 33",
    "sg:city":"Sol De Mallorca",
    "sg:orig_category":"Inmobiliaria (agencias)",
    "sg:phone":"+34 971 13 17 96",
    "sg:postcode":"07181",
    "sg:province":"Islas Baleares",
    "wof:name":"San Jacobo S.l.",
    "wof:placetype":"venue"
},
  "geometry": {"coordinates":[2.5279901028,39.4800224304],"type":"Point"}
}