{
  "type": "Feature",
  "properties": {
    "addr:full":"Carr Tuejar, Km. 0016,0 Eliana Valencia 46183",
    "addr:postcode":"46183",
    "addr:street":"Carr Tuejar Km. 0016,0",
    "iso:country":"ES",
    "sg:address":"Carr Tuejar, Km. 0016,0",
    "sg:city":"Eliana",
    "sg:orig_category":"Servicios De Telecomunicaciones",
    "sg:phone":"+34 961 65 66 55",
    "sg:postcode":"46183",
    "sg:province":"Valencia",
    "wof:name":"Ardite Ortu\u00f1o Vicente",
    "wof:placetype":"venue"
},
  "geometry": {"coordinates":[-0.5229440928,39.5755500793],"type":"Point"}
}