{
  "type": "Feature",
  "properties": {
    "iso:country":"ES",
    "sg:address":"Calle de Gallegos, 9",
    "sg:city":"Alcala Henares",
    "sg:orig_category":"Psic\u00d3logos",
    "sg:phone":"+34 918 80 80 01",
    "sg:postcode":"28807",
    "sg:province":"Madrid",
    "wof:name":"Cino Nu\u00f1ez Estela Del Mar",
    "wof:placetype":"venue"
},
  "geometry": {"coordinates":[-3.3660590649,40.4866752625],"type":"Point"}
}