{
  "type": "Feature",
  "properties": {
    "addr:full":"Av Europa, 3 Gava Barcelona 08850",
    "addr:housenumber":"3",
    "addr:postcode":"08850",
    "addr:street":"Av Europa",
    "iso:country":"ES",
    "sg:address":"Av Europa, 3",
    "sg:city":"Gava",
    "sg:orig_category":"Inmobiliaria (agencias)",
    "sg:phone":"+34 936 33 17 13",
    "sg:postcode":"08850",
    "sg:province":"Barcelona",
    "wof:name":"Novotei Plastic Sl",
    "wof:placetype":"venue"
},
  "geometry": {"coordinates":[2.040407896,41.2711372375],"type":"Point"}
}