{
  "type": "Feature",
  "properties": {
    "iso:country":"ES",
    "sg:address":"Calle de Pelayo, 29",
    "sg:city":"Aviles",
    "sg:orig_category":"Bricolaje, Herramientas (al Por Menor)",
    "sg:phone":"+34 985 54 51 25",
    "sg:postcode":"33402",
    "sg:province":"Asturias",
    "wof:name":"Lopez Garcia Maria Luz",
    "wof:placetype":"venue"
},
  "geometry": {"coordinates":[-5.9196181297,43.5473747253],"type":"Point"}
}