{
  "type": "Feature",
  "properties": {
    "iso:country":"ES",
    "sg:address":"Avda Guadalajara (de), 17",
    "sg:city":"Azuqueca Henares",
    "sg:orig_category":"Zapater\u00cdas",
    "sg:phone":"+34 949 26 78 46",
    "sg:postcode":"19200",
    "sg:province":"Guadalajara",
    "wof:name":"Montero Benito Jose Miguel",
    "wof:placetype":"venue"
},
  "geometry": {"coordinates":[-3.2652409077,40.563999176],"type":"Point"}
}