{
  "type": "Feature",
  "properties": {
    "addr:full":"Avgd Colon, 20 Alcasser Valencia 46290",
    "addr:housenumber":"20",
    "addr:postcode":"46290",
    "addr:street":"Colon",
    "iso:country":"ES",
    "sg:address":"Avgd Colon, 20",
    "sg:city":"Alcasser",
    "sg:orig_category":"Molduras, Junquillos, Listones Y Molduras Perforadas",
    "sg:phone":"+34 961 24 20 52",
    "sg:postcode":"46290",
    "sg:province":"Valencia",
    "wof:name":"Turegano Blanco Amparo",
    "wof:placetype":"venue"
},
  "geometry": {"coordinates":[-0.4446519911,39.3653755188],"type":"Point"}
}