{
  "type": "Feature",
  "properties": {
    "addr:full":"Carrer de Melio, 121 Vilafranca Penedes Barcelona 08720",
    "addr:housenumber":"121",
    "addr:postcode":"08720",
    "addr:street":"Carrer De Melio;Penedes Barcelona",
    "iso:country":"ES",
    "sg:address":"Carrer de Melio, 121",
    "sg:city":"Vilafranca Penedes",
    "sg:orig_category":"Reparaciones Y Remolcado De Veh\u00cdculos",
    "sg:phone":"+34 938 90 05 92",
    "sg:postcode":"08720",
    "sg:province":"Barcelona",
    "wof:name":"Tallers S. Romeu S.l.",
    "wof:placetype":"venue"
},
  "geometry": {"coordinates":[1.7078499794,41.3468589783],"type":"Point"}
}