{
  "type": "Feature",
  "properties": {
    "iso:country":"ES",
    "sg:address":"Calle de Cardenal Cisneros (del), 4",
    "sg:city":"Torrelaguna",
    "sg:orig_category":"Art\u00cdculos Funerarios (al Por Menor)",
    "sg:phone":"+34 918 43 07 98",
    "sg:postcode":"28180",
    "sg:province":"Madrid",
    "wof:name":"Gonzalo Fra Maria Teresa",
    "wof:placetype":"venue"
},
  "geometry": {"coordinates":[-3.537820816,40.8275337219],"type":"Point"}
}