{
  "type": "Feature",
  "properties": {
    "addr:full":"Calle de Francisco De Goya, 5 Pedrola Zaragoza 50690",
    "addr:housenumber":"5",
    "addr:postcode":"50690",
    "addr:street":"Calle De Francisco De Goya",
    "iso:country":"ES",
    "sg:address":"Calle de Francisco De Goya, 5",
    "sg:city":"Pedrola",
    "sg:orig_category":"Transportes Por V\u00cdas Navegables",
    "sg:phone":"+34 976 61 56 90",
    "sg:postcode":"50690",
    "sg:province":"Zaragoza",
    "wof:name":"Castro Furriel Jose Luis",
    "wof:placetype":"venue"
},
  "geometry": {"coordinates":[-1.2162189484,41.7854804993],"type":"Point"}
}