{
  "type": "Feature",
  "properties": {
    "addr:full":"Bard Tinte (el), S/n Utrera Sevilla 41710",
    "addr:postcode":"41710",
    "addr:street":"S / N",
    "iso:country":"ES",
    "sg:address":"Bard Tinte (el), S/n",
    "sg:city":"Utrera",
    "sg:orig_category":"Empresas De Desmonte",
    "sg:phone":"+34 954 86 41 65",
    "sg:postcode":"41710",
    "sg:province":"Sevilla",
    "wof:name":"Nivelaciones Fercon S.l",
    "wof:placetype":"venue"
},
  "geometry": {"coordinates":[-5.7885599136,37.1774864197],"type":"Point"}
}