{
  "type": "Feature",
  "properties": {
    "iso:country":"ES",
    "sg:address":"Calle de Mesa De Leon, 3",
    "sg:city":"Palmas De Gran Canaria",
    "sg:orig_category":"Molduras, Junquillos, Listones Y Molduras Perforadas",
    "sg:phone":"+34 928 31 33 30",
    "sg:postcode":"35001",
    "sg:province":"Las Palmas",
    "wof:name":"Rodriguez Angulo Jose",
    "wof:placetype":"venue"
},
  "geometry": {"coordinates":[-15.4155597687,28.1018333435],"type":"Point"}
}