{
  "type": "Feature",
  "properties": {
    "addr:full":"Pase Rosaleda (la), 1 Jerez De La Frontera C\u00e1diz 11405",
    "addr:postcode":"11405",
    "iso:country":"ES",
    "sg:address":"Pase Rosaleda (la), 1",
    "sg:city":"Jerez De La Frontera",
    "sg:orig_category":"Centros Comerciales Y Grandes Tiendas",
    "sg:phone":"+34 956 30 08 37",
    "sg:postcode":"11405",
    "sg:province":"C\u00e1diz",
    "wof:name":"Taller De Costura El Dedal",
    "wof:placetype":"venue"
},
  "geometry": {"coordinates":[-6.1005191803,36.7067260742],"type":"Point"}
}