{
  "type": "Feature",
  "properties": {
    "addr:full":"Calle de Avelino Gonzalez Mallada, 44 Gijon Asturias 33204",
    "addr:housenumber":"44",
    "addr:postcode":"33204",
    "addr:street":"Calle De Avelino Gonzalez Mallada",
    "iso:country":"ES",
    "sg:address":"Calle de Avelino Gonzalez Mallada, 44",
    "sg:city":"Gijon",
    "sg:orig_category":"Farmacias",
    "sg:phone":"+34 985 36 69 26",
    "sg:postcode":"33204",
    "sg:province":"Asturias",
    "wof:name":"Farmacia Pagin C.b.",
    "wof:placetype":"venue"
},
  "geometry": {"coordinates":[-5.6486873627,43.5326004028],"type":"Point"}
}