{
  "type": "Feature",
  "properties": {
    "addr:full":"Pl Esglesia (de L'), 3 Flix Tarragona 43750",
    "addr:housenumber":"3",
    "addr:postcode":"43750",
    "addr:street":"Pl Esglesia De L '",
    "iso:country":"ES",
    "sg:address":"Pl Esglesia (de L'), 3",
    "sg:city":"Flix",
    "sg:orig_category":"Cajas De Ahorro",
    "sg:phone":"+34 977 41 08 99",
    "sg:postcode":"43750",
    "sg:province":"Tarragona",
    "sg:website":"www.caixatarragona.es",
    "wof:name":"Caixa D'estalvis De Tarragona",
    "wof:placetype":"venue"
},
  "geometry": {"coordinates":[0.54993999,41.2310791016],"type":"Point"}
}