{
  "type": "Feature",
  "properties": {
    "addr:full":"Calle de Garcia Lorca, S/n Anna Valencia 46820",
    "addr:housenumber":"/ n",
    "addr:postcode":"46820",
    "addr:street":"Calle De Garcia Lorca S",
    "iso:country":"ES",
    "sg:address":"Calle de Garcia Lorca, S/n",
    "sg:city":"Anna",
    "sg:orig_category":"Confecci\u00d3n De Ropa Interior",
    "sg:phone":"+34 962 92 21 37",
    "sg:postcode":"46820",
    "sg:province":"Valencia",
    "wof:name":"Beneyto Monfort S.l.",
    "wof:placetype":"venue"
},
  "geometry": {"coordinates":[-0.6475340128,39.0191268921],"type":"Point"}
}