{
  "type": "Feature",
  "properties": {
    "addr:full":"Gil, 3 Mirambel Teruel 44141",
    "addr:housenumber":"3",
    "addr:postcode":"44141",
    "addr:street":"Gil",
    "iso:country":"ES",
    "sg:address":"Gil, 3",
    "sg:city":"Mirambel",
    "sg:orig_category":"Cr\u00cda De Animales",
    "sg:phone":"+34 964 17 82 76",
    "sg:postcode":"44141",
    "sg:province":"Teruel",
    "wof:name":"Dolmarporc S.l.",
    "wof:placetype":"venue"
},
  "geometry": {"coordinates":[-0.3982740045,40.6202468872],"type":"Point"}
}