{
  "type": "Feature",
  "properties": {
    "iso:country":"ES",
    "sg:address":"Calle de Sebastian Souviron, 22",
    "sg:city":"Malaga",
    "sg:orig_category":"Psic\u00d3logos",
    "sg:phone":"+34 952 22 12 47",
    "sg:postcode":"29005",
    "sg:province":"M\u00e1laga",
    "wof:name":"Perez-bryan Mu\u00f1oz Lourdes",
    "wof:placetype":"venue"
},
  "geometry": {"coordinates":[-4.4247422218,36.7191200256],"type":"Point"}
}