{
  "type": "Feature",
  "properties": {
    "iso:country":"ES",
    "sg:address":"Ctr. Nacional V, 2",
    "sg:city":"Oropesa",
    "sg:orig_category":"Suministros Para Hoteles",
    "sg:phone":"+34 925 43 10 12",
    "sg:postcode":"45560",
    "sg:province":"Toledo",
    "wof:name":"Santiper Night S.l.",
    "wof:placetype":"venue"
},
  "geometry": {"coordinates":[-5.1782941818,39.9192237854],"type":"Point"}
}