{
  "type": "Feature",
  "properties": {
    "addr:full":"Calle de Rio Marches, 15 Poligono Sta M. De Benquerencia Toledo 45007",
    "addr:housenumber":"15 poligono",
    "addr:postcode":"45007",
    "addr:street":"Calle De Rio Marches;Sta M. De Benquerencia",
    "iso:country":"ES",
    "sg:address":"Calle de Rio Marches, 15",
    "sg:city":"Poligono Sta M. De Benquerencia",
    "sg:orig_category":"Agentes, Concesionarios Y Sucursales De Veh\u00cdculos",
    "sg:phone":"+34 925 23 09 39",
    "sg:postcode":"45007",
    "sg:province":"Toledo",
    "sg:website":"www.automotorsl.com",
    "wof:name":"Automoviles Automotor S.l.",
    "wof:placetype":"venue"
},
  "geometry": {"coordinates":[-4.0244760513,39.8567771912],"type":"Point"}
}