{
  "type": "Feature",
  "properties": {
    "addr:full":"Carrer de Sant Marius, 20 Barcelona Barcelona 08022",
    "addr:housenumber":"20",
    "addr:postcode":"08022",
    "addr:street":"Carrer De Sant Marius",
    "iso:country":"ES",
    "sg:address":"Carrer de Sant Marius, 20",
    "sg:city":"Barcelona",
    "sg:orig_category":"Asesor\u00cda Fiscal Y Jur\u00cddica",
    "sg:phone":"+34 934 18 27 97",
    "sg:postcode":"08022",
    "sg:province":"Barcelona",
    "wof:name":"Advadgeapas S.cp.",
    "wof:placetype":"venue"
},
  "geometry": {"coordinates":[2.1375758648,41.4038887024],"type":"Point"}
}