{
  "type": "Feature",
  "properties": {
    "iso:country":"ES",
    "sg:address":"Calle de Embajadores, 63",
    "sg:city":"Madrid",
    "sg:orig_category":"Supermercados Y Hipermercados",
    "sg:phone":"+34 915 30 95 19",
    "sg:postcode":"28012",
    "sg:province":"Madrid",
    "wof:name":"Alvarez Peces Pablo",
    "wof:placetype":"venue"
},
  "geometry": {"coordinates":[-3.7016990185,40.4040641785],"type":"Point"}
}