{
  "type": "Feature",
  "properties": {
    "iso:country":"ES",
    "sg:address":"Plaz Marques De Salamanca, 11",
    "sg:city":"Madrid",
    "sg:orig_category":"Organismos De Investigaciones Cient\u00cdficas Y T\u00c9cnicas",
    "sg:phone":"+34 914 36 47 74",
    "sg:postcode":"28006",
    "sg:province":"Madrid",
    "wof:name":"Fundacion Cotec Para La Innovacion Tecnologica",
    "wof:placetype":"venue"
},
  "geometry": {"coordinates":[-3.6794910431,40.4296226501],"type":"Point"}
}