{
  "type": "Feature",
  "properties": {
    "iso:country":"ES",
    "sg:address":"Calle de Sangenis, 15",
    "sg:city":"Zaragoza",
    "sg:orig_category":"Bisuter\u00cda, Joyer\u00cda, Relojer\u00cda (al Por Menor)",
    "sg:phone":"+34 976 33 11 82",
    "sg:postcode":"50010",
    "sg:province":"Zaragoza",
    "wof:name":"Lezcano Ca\u00f1on Isabel",
    "wof:placetype":"venue"
},
  "geometry": {"coordinates":[-0.9042515159,41.6521339417],"type":"Point"}
}