{
  "type": "Feature",
  "properties": {
    "addr:full":"Carrer de Corominas, 37 Hospitalet Llobregat Barcelona 08902",
    "addr:housenumber":"37",
    "addr:postcode":"08902",
    "addr:street":"Carrer De Corominas",
    "iso:country":"ES",
    "sg:address":"Carrer de Corominas, 37",
    "sg:city":"Hospitalet Llobregat",
    "sg:orig_category":"Artes Gr\u00c1ficas, Artes Pl\u00c1sticas (curso)",
    "sg:phone":"+34 934 31 33 88",
    "sg:postcode":"08902",
    "sg:province":"Barcelona",
    "wof:name":"Graficas Moreno S.l.",
    "wof:placetype":"venue"
},
  "geometry": {"coordinates":[2.1205921173,41.3671646118],"type":"Point"}
}