{
  "type": "Feature",
  "properties": {
    "iso:country":"ES",
    "sg:address":"Muralla De Sant Llorenc, 24",
    "sg:city":"Mataro",
    "sg:orig_category":"M\u00c9dicos: Reumatolog\u00cda",
    "sg:phone":"+34 937 90 29 10",
    "sg:postcode":"08302",
    "sg:province":"Barcelona",
    "wof:name":"Ayet Vicent Enrique",
    "wof:placetype":"venue"
},
  "geometry": {"coordinates":[2.4440460205,41.538520813],"type":"Point"}
}