{
  "type": "Feature",
  "properties": {
    "addr:full":"Av Can Roses, S/n Rubi Barcelona 08191",
    "addr:housenumber":"/ n",
    "addr:postcode":"08191",
    "addr:street":"Av",
    "iso:country":"ES",
    "sg:address":"Av Can Roses, S/n",
    "sg:city":"Rubi",
    "sg:orig_category":"Montaje (empresas De)",
    "sg:phone":"+34 935 88 69 92",
    "sg:postcode":"08191",
    "sg:province":"Barcelona",
    "wof:name":"Tessag Iberica S.a.",
    "wof:placetype":"venue"
},
  "geometry": {"coordinates":[2.0436809063,41.5048446655],"type":"Point"}
}