{
  "type": "Feature",
  "properties": {
    "iso:country":"ES",
    "sg:address":"Calle de San Isidoro, 40",
    "sg:city":"Coru\u00d1a",
    "sg:orig_category":"Perfumer\u00cda, Art\u00cdculos De Ba\u00d1o (fabricaci\u00d3n, Al Por Mayor)",
    "sg:phone":"+34 981 15 04 07",
    "sg:postcode":"15007",
    "sg:province":"A Coru\u00f1a",
    "wof:name":"Soilan Gonzalez Invencion",
    "wof:placetype":"venue"
},
  "geometry": {"coordinates":[-8.4174203873,43.3590011597],"type":"Point"}
}