{
  "type": "Feature",
  "properties": {
    "iso:country":"ES",
    "sg:address":"Avda Valladolid, S/n",
    "sg:city":"Soria",
    "sg:orig_category":"Agentes, Concesionarios Y Sucursales De Camiones Y Veh\u00cdculos Industriales",
    "sg:phone":"+34 975 22 72 90",
    "sg:postcode":"42004",
    "sg:province":"Soria",
    "wof:name":"Motortrans S.a.",
    "wof:placetype":"venue"
},
  "geometry": {"coordinates":[-2.4828391075,41.7677268982],"type":"Point"}
}