{
  "type": "Feature",
  "properties": {
    "addr:full":"C/ Pont Dels Ortissos, 2 Elche Alicante 03202",
    "addr:housenumber":"2",
    "addr:postcode":"03202",
    "addr:street":"C / Pont Dels Ortissos",
    "iso:country":"ES",
    "sg:address":"C/ Pont Dels Ortissos, 2",
    "sg:city":"Elche",
    "sg:orig_category":"Asociaciones Y Clubs Deportivos",
    "sg:phone":"+34 965 42 37 25",
    "sg:postcode":"03202",
    "sg:province":"Alicante",
    "wof:name":"Atlanta Sport S.l.",
    "wof:placetype":"venue"
},
  "geometry": {"coordinates":[-0.6953892112,38.2661056519],"type":"Point"}
}