{
  "type": "Feature",
  "properties": {
    "iso:country":"ES",
    "sg:address":"Calle de Senda Galiana (de La), 6",
    "sg:city":"Coslada",
    "sg:orig_category":"Mec\u00c1nica Y Herramientas De Precisi\u00d3n",
    "sg:phone":"+34 916 72 32 11",
    "sg:postcode":"28820",
    "sg:province":"Madrid",
    "wof:name":"Frigo Electric San Marcial S. A.",
    "wof:placetype":"venue"
},
  "geometry": {"coordinates":[-3.536823988,40.4431037903],"type":"Point"}
}