{
  "type": "Feature",
  "properties": {
    "iso:country":"ES",
    "sg:address":"Calle de Collado (el), 31",
    "sg:city":"Soria",
    "sg:orig_category":"Quiropr\u00c1cticos",
    "sg:phone":"+34 975 22 47 43",
    "sg:postcode":"42002",
    "sg:province":"Soria",
    "wof:name":"Garcia Martinez Natividad",
    "wof:placetype":"venue"
},
  "geometry": {"coordinates":[-2.4663670063,41.764213562],"type":"Point"}
}