{
  "type": "Feature",
  "properties": {
    "addr:full":"Calle de Somosierra, 17 Logro\u00f1o La Rioja 26002",
    "addr:housenumber":"17",
    "addr:postcode":"26002",
    "addr:street":"Calle De Somosierra;Rioja",
    "iso:country":"ES",
    "sg:address":"Calle de Somosierra, 17",
    "sg:city":"Logro\u00f1o",
    "sg:orig_category":"Alquiler De V\u00cddeo",
    "sg:phone":"+34 941 25 77 29",
    "sg:postcode":"26002",
    "sg:province":"La Rioja",
    "wof:name":"Fuertes Sanchez Maria Isabel",
    "wof:placetype":"venue"
},
  "geometry": {"coordinates":[-2.4485220909,42.4599761963],"type":"Point"}
}