{
  "type": "Feature",
  "properties": {
    "addr:full":"Avda Corredera, 38 Hinojosa Del Duque C\u00f3rdoba 14270",
    "addr:housenumber":"38",
    "addr:postcode":"14270",
    "addr:street":"Avda Corredera;Co\u0301Rdoba",
    "iso:country":"ES",
    "sg:address":"Avda Corredera, 38",
    "sg:city":"Hinojosa Del Duque",
    "sg:orig_category":"Sociedades, Compa\u00d1\u00cdas Aseguradoras",
    "sg:phone":"+34 957 14 23 86",
    "sg:postcode":"14270",
    "sg:province":"C\u00f3rdoba",
    "wof:name":"Gomez Gonzalez Ricardo",
    "wof:placetype":"venue"
},
  "geometry": {"coordinates":[-5.1456818581,38.4987297058],"type":"Point"}
}