{
  "type": "Feature",
  "properties": {
    "addr:full":"Carrer de Major, 342 Centre Barcelona 08759",
    "addr:housenumber":"342",
    "addr:postcode":"08759",
    "addr:street":"Carrer De Major;Centre Barcelona",
    "iso:country":"ES",
    "sg:address":"Carrer de Major, 342",
    "sg:city":"Centre",
    "sg:orig_category":"Cajas De Ahorro",
    "sg:phone":"+34 936 83 12 26",
    "sg:postcode":"08759",
    "sg:province":"Barcelona",
    "wof:name":"Caixa D'estalvis Del Penedes",
    "wof:placetype":"venue"
},
  "geometry": {"coordinates":[1.9328349829,41.3889045715],"type":"Point"}
}