{
  "type": "Feature",
  "properties": {
    "addr:full":"Maldonado, 21 Plasencia C\u00e1ceres 10600",
    "addr:housenumber":"21",
    "addr:postcode":"10600",
    "addr:street":"Maldonado;Ca\u0301Ceres",
    "iso:country":"ES",
    "sg:address":"Maldonado, 21",
    "sg:city":"Plasencia",
    "sg:orig_category":"Fabricaci\u00d3n De Peines Y De Accesorios De Peluquer\u00cda",
    "sg:phone":"+34 927 42 19 84",
    "sg:postcode":"10600",
    "sg:province":"C\u00e1ceres",
    "wof:name":"Dionisio Hernandez Calatayud Y Otros Cdad",
    "wof:placetype":"venue"
},
  "geometry": {"coordinates":[-6.0898518562,40.0299453735],"type":"Point"}
}