{
  "type": "Feature",
  "properties": {
    "addr:full":"Rua Tapia, 2 Temple La Coru\u00f1a 15679",
    "addr:housenumber":"2",
    "addr:postcode":"15679",
    "addr:street":"Rua Tapia;La Corun\u0303A",
    "iso:country":"ES",
    "sg:address":"Rua Tapia, 2",
    "sg:city":"Temple",
    "sg:orig_category":"Colchones (fabricaci\u00d3n, Al Por Mayor, Al Por Menor)",
    "sg:phone":"+34 981 65 22 71",
    "sg:postcode":"15679",
    "sg:province":"La Coru\u00f1a",
    "wof:name":"Gundin Muebles S.l.",
    "wof:placetype":"venue"
},
  "geometry": {"coordinates":[-8.3564567566,43.3178977966],"type":"Point"}
}