{
  "type": "Feature",
  "properties": {
    "iso:country":"ES",
    "sg:address":"Calle de Villalar, 3",
    "sg:city":"Madrid",
    "sg:orig_category":"Inmobiliaria (agencias)",
    "sg:phone":"+34 915 77 88 34",
    "sg:postcode":"28001",
    "sg:province":"Madrid",
    "wof:name":"Burke  Kevin Jhon",
    "wof:placetype":"venue"
},
  "geometry": {"coordinates":[-3.6901900768,40.4209098816],"type":"Point"}
}