{
  "type": "Feature",
  "properties": {
    "iso:country":"ES",
    "sg:address":"C/ Fusters, Dels, S/n",
    "sg:city":"Manacor",
    "sg:orig_category":"Artes Gr\u00c1ficas, Artes Pl\u00c1sticas (curso)",
    "sg:phone":"+34 971 84 60 68",
    "sg:postcode":"07500",
    "sg:province":"Islas Baleares",
    "sg:website":"www.ravanetto.com",
    "wof:name":"Ravanetto S.l.",
    "wof:placetype":"venue"
},
  "geometry": {"coordinates":[3.1828780174,39.5712127686],"type":"Point"}
}