{
  "type": "Feature",
  "properties": {
    "addr:full":"Calle de Menendez Pelayo, 7 Marchena Sevilla 41620",
    "addr:housenumber":"7",
    "addr:postcode":"41620",
    "addr:street":"Calle De Menendez Pelayo",
    "iso:country":"ES",
    "sg:address":"Calle de Menendez Pelayo, 7",
    "sg:city":"Marchena",
    "sg:orig_category":"Asesor\u00cda Sobre Comunicaci\u00d3n De Empresas",
    "sg:phone":"+34 954 84 34 41",
    "sg:postcode":"41620",
    "sg:province":"Sevilla",
    "sg:website":"www.multigestionsur.com",
    "wof:name":"Multigestion Sur S.l.l.",
    "wof:placetype":"venue"
},
  "geometry": {"coordinates":[-5.4158740044,37.3278999329],"type":"Point"}
}