{
  "type": "Feature",
  "properties": {
    "addr:full":"Calle de Leguizamon Tristan De, 5 Bilbao Vizcaya 48007",
    "addr:housenumber":"5",
    "addr:postcode":"48007",
    "addr:street":"Calle De Leguizamon Tristan De",
    "iso:country":"ES",
    "sg:address":"Calle de Leguizamon Tristan De, 5",
    "sg:city":"Bilbao",
    "sg:orig_category":"M\u00c1rmoles, Granitos Y Piedras Naturales",
    "sg:phone":"+34 944 46 16 66",
    "sg:postcode":"48007",
    "sg:province":"Vizcaya",
    "wof:name":"Lopez Dacosta Ana",
    "wof:placetype":"venue"
},
  "geometry": {"coordinates":[-2.9293720722,43.2689056396],"type":"Point"}
}