{
  "type": "Feature",
  "properties": {
    "iso:country":"ES",
    "sg:address":"Vred Ajofrin, 5",
    "sg:city":"Sonseca",
    "sg:orig_category":"Art\u00cdculos De Madera (fabricaci\u00d3n Y Al Por Mayor)",
    "sg:phone":"+34 925 38 27 82",
    "sg:postcode":"45100",
    "sg:province":"Toledo",
    "wof:name":"Tecnologia Integral Del Mueble S.l.",
    "wof:placetype":"venue"
},
  "geometry": {"coordinates":[-3.9745690823,39.6818695068],"type":"Point"}
}