{
  "type": "Feature",
  "properties": {
    "iso:country":"ES",
    "sg:address":"Calle de Arrasate, 15",
    "sg:city":"Donostia-san Sebastian",
    "sg:orig_category":"Ropa Para Ni\u00d1os (al Por Menor)",
    "sg:phone":"+34 943 42 04 76",
    "sg:postcode":"20005",
    "sg:province":"Guip\u00f9zcoa",
    "wof:name":"Garin Tolosa Arancha",
    "wof:placetype":"venue"
},
  "geometry": {"coordinates":[-1.9811719656,43.3184127808],"type":"Point"}
}