{
  "type": "Feature",
  "properties": {
    "iso:country":"ES",
    "sg:address":"Av Onze De Setembre (de L'), 7",
    "sg:city":"Montornes Centre",
    "sg:orig_category":"Farmacias",
    "sg:phone":"+34 935 68 17 48",
    "sg:postcode":"08170",
    "sg:province":"Barcelona",
    "wof:name":"Trepat Pique Francisca",
    "wof:placetype":"venue"
},
  "geometry": {"coordinates":[2.2634260654,41.5424880981],"type":"Point"}
}