{
  "type": "Feature",
  "properties": {
    "iso:country":"ES",
    "sg:address":"C/ Sant Ramon, 119",
    "sg:city":"Cerdanyola Valles",
    "sg:orig_category":"Porcelanas, Azulejos (fabricaci\u00d3n, Al Por Mayor)",
    "sg:phone":"+34 935 80 54 00",
    "sg:postcode":"08290",
    "sg:province":"Barcelona",
    "wof:name":"Endeka Ceramics S.a.",
    "wof:placetype":"venue"
},
  "geometry": {"coordinates":[2.1364850998,41.4902877808],"type":"Point"}
}