{
  "type": "Feature",
  "properties": {
    "iso:country":"ES",
    "sg:address":"Ctra Vic, 9",
    "sg:city":"Manresa",
    "sg:orig_category":"Molduras, Junquillos, Listones Y Molduras Perforadas",
    "sg:phone":"+34 938 72 75 43",
    "sg:postcode":"08241",
    "sg:province":"Barcelona",
    "wof:name":"Cobaleda Marin Francisco",
    "wof:placetype":"venue"
},
  "geometry": {"coordinates":[1.8256980181,41.7256965637],"type":"Point"}
}