{
  "type": "Feature",
  "properties": {
    "addr:full":"Calle de Montesinos, S/n Badajoz Badajoz 06002",
    "addr:housenumber":"s / n",
    "addr:postcode":"06002",
    "addr:street":"Calle De Montesinos",
    "iso:country":"ES",
    "sg:address":"Calle de Montesinos, S/n",
    "sg:city":"Badajoz",
    "sg:orig_category":"Aparcamientos (infraestructuras, Accesorios)",
    "sg:phone":"+34 924 23 08 62",
    "sg:postcode":"06002",
    "sg:province":"Badajoz",
    "wof:name":"Servicios Integrales Extreme\u00f1os 2000",
    "wof:placetype":"venue"
},
  "geometry": {"coordinates":[-6.9692811966,38.8803787231],"type":"Point"}
}