{
  "type": "Feature",
  "properties": {
    "addr:full":"Carr Far D'emporda, S/n Figueres Girona 17600",
    "addr:housenumber":"s",
    "addr:postcode":"17600",
    "addr:street":"Carr Far D'Emporda;/ N",
    "iso:country":"ES",
    "sg:address":"Carr Far D'emporda, S/n",
    "sg:city":"Figueres",
    "sg:orig_category":"Distribuci\u00d3n De Petr\u00d3leo Y Derivados",
    "sg:phone":"+34 972 67 55 93",
    "sg:postcode":"17600",
    "sg:province":"Girona",
    "wof:name":"Tulsa Petroli S.l.",
    "wof:placetype":"venue"
},
  "geometry": {"coordinates":[2.9705770016,42.2653160095],"type":"Point"}
}