{
  "type": "Feature",
  "properties": {
    "addr:full":"Plaz Santo, 1 Salamanca Salamanca 37001",
    "addr:housenumber":"1",
    "addr:postcode":"37001",
    "addr:street":"Santo",
    "iso:country":"ES",
    "sg:address":"Plaz Santo, 1",
    "sg:city":"Salamanca",
    "sg:orig_category":"Promotores Constructores",
    "sg:phone":"+34 923 27 07 11",
    "sg:postcode":"37001",
    "sg:province":"Salamanca",
    "wof:name":"Leyfer S.l.",
    "wof:placetype":"venue"
},
  "geometry": {"coordinates":[-5.663848877,40.964225769],"type":"Point"}
}