{
  "type": "Feature",
  "properties": {
    "iso:country":"ES",
    "sg:address":"Ctra Lora Rio, S/n",
    "sg:city":"Cantillana",
    "sg:orig_category":"Maquinaria Para Industrias Diversas",
    "sg:phone":"+34 955 73 01 80",
    "sg:postcode":"41320",
    "sg:province":"Sevilla",
    "wof:name":"Maytu S.l.",
    "wof:placetype":"venue"
},
  "geometry": {"coordinates":[-5.8236131668,37.6098098755],"type":"Point"}
}