{
  "type": "Feature",
  "properties": {
    "iso:country":"ES",
    "sg:address":"Avda Carlos De Haya, 68",
    "sg:city":"Malaga",
    "sg:orig_category":"Cristaler\u00cdas",
    "sg:phone":"+34 952 61 15 59",
    "sg:postcode":"29010",
    "sg:province":"M\u00e1laga",
    "wof:name":"Marin Sanchez Isabel Maria",
    "wof:placetype":"venue"
},
  "geometry": {"coordinates":[-4.4467258453,36.7222175598],"type":"Point"}
}