{
  "type": "Feature",
  "properties": {
    "addr:full":"Calle de Santa Cruz, 22 Camas Sevilla 41900",
    "addr:housenumber":"22",
    "addr:postcode":"41900",
    "addr:street":"Calle De Santa Cruz",
    "iso:country":"ES",
    "sg:address":"Calle de Santa Cruz, 22",
    "sg:city":"Camas",
    "sg:orig_category":"Armarios Y Cuadros El\u00c9ctricos",
    "sg:phone":"+34 954 39 26 72",
    "sg:postcode":"41900",
    "sg:province":"Sevilla",
    "wof:name":"Ingemark Servicios Agrupados S. L.",
    "wof:placetype":"venue"
},
  "geometry": {"coordinates":[-6.0369791985,37.420009613],"type":"Point"}
}