{
  "type": "Feature",
  "properties": {
    "addr:full":"Calle de Infanta Mercedes, 107 Madrid Madrid 28020",
    "addr:housenumber":"107",
    "addr:postcode":"28020",
    "addr:street":"Calle De Infanta Mercedes",
    "iso:country":"ES",
    "sg:address":"Calle de Infanta Mercedes, 107",
    "sg:city":"Madrid",
    "sg:orig_category":"Arquitectos",
    "sg:phone":"+34 915 71 47 41",
    "sg:postcode":"28020",
    "sg:province":"Madrid",
    "wof:name":"Marquina Jimenez Eduardo",
    "wof:placetype":"venue"
},
  "geometry": {"coordinates":[-3.6934230328,40.4637107849],"type":"Point"}
}