{
  "type": "Feature",
  "properties": {
    "addr:full":"Plaz Cuestas (de Las), 3 Getafe Madrid 28901",
    "addr:housenumber":"3",
    "addr:postcode":"28901",
    "addr:street":"Plaz Cuestas De Las",
    "iso:country":"ES",
    "sg:address":"Plaz Cuestas (de Las), 3",
    "sg:city":"Getafe",
    "sg:orig_category":"Empresas De Portes Y Mensajer\u00cda",
    "sg:phone":"+34 916 81 31 70",
    "sg:postcode":"28901",
    "sg:province":"Madrid",
    "wof:name":"Universal Europa Cargo S.l.",
    "wof:placetype":"venue"
},
  "geometry": {"coordinates":[-3.7334220409,40.3058280945],"type":"Point"}
}