{
  "type": "Feature",
  "properties": {
    "iso:country":"ES",
    "sg:address":"Calle de Ministro Fernandez Ordo\u00d1ez, 3",
    "sg:city":"Alcorcon",
    "sg:orig_category":"Electricidad: Instaladores",
    "sg:phone":"+34 916 19 13 85",
    "sg:postcode":"28924",
    "sg:province":"Madrid",
    "wof:name":"Palacios Calle Serafin",
    "wof:placetype":"venue"
},
  "geometry": {"coordinates":[-3.8101570606,40.3492622375],"type":"Point"}
}