{
  "type": "Feature",
  "properties": {
    "iso:country":"ES",
    "sg:address":"Avda San Luis Gonzaga, 1",
    "sg:city":"Puerto De Santa Maria",
    "sg:orig_category":"Internados & Ense\u00d1anza Privada",
    "sg:phone":"+34 956 87 52 22",
    "sg:postcode":"11500",
    "sg:province":"C\u00e1diz",
    "wof:name":"Escuelas Profesionales Sagrada Familia",
    "wof:placetype":"venue"
},
  "geometry": {"coordinates":[-6.2351388931,36.5987205505],"type":"Point"}
}