{
  "type": "Feature",
  "properties": {
    "addr:full":"Calle de Doctor Zamenhof, 7 Valencia Valencia 46008",
    "addr:housenumber":"7",
    "addr:postcode":"46008",
    "addr:street":"Calle De Doctor Zamenhof",
    "iso:country":"ES",
    "sg:address":"Calle de Doctor Zamenhof, 7",
    "sg:city":"Valencia",
    "sg:orig_category":"Agencias Y Agentes Comerciales, Representantes",
    "sg:phone":"+34 963 82 33 66",
    "sg:postcode":"46008",
    "sg:province":"Valencia",
    "wof:name":"Representaciones Alfredo Anton S. L.",
    "wof:placetype":"venue"
},
  "geometry": {"coordinates":[-0.3905113935,39.4763374329],"type":"Point"}
}