{
  "type": "Feature",
  "properties": {
    "addr:full":"Carrer de Llastres, 2 Hospitalet De L'infant Tarragona 43890",
    "addr:housenumber":"2",
    "addr:postcode":"43890",
    "addr:street":"Carrer De Llastres",
    "iso:country":"ES",
    "sg:address":"Carrer de Llastres, 2",
    "sg:city":"Hospitalet De L'infant",
    "sg:orig_category":"Arquitectos",
    "sg:phone":"+34 977 82 00 57",
    "sg:postcode":"43890",
    "sg:province":"Tarragona",
    "wof:name":"Marques Bargallo Josep Ramon",
    "wof:placetype":"venue"
},
  "geometry": {"coordinates":[1.2570739985,41.1172904968],"type":"Point"}
}