{
  "type": "Feature",
  "properties": {
    "addr:full":"Calle de Clavel, 2 Chauchina Granada 18330",
    "addr:housenumber":"2",
    "addr:postcode":"18330",
    "addr:street":"Calle De Clavel",
    "iso:country":"ES",
    "sg:address":"Calle de Clavel, 2",
    "sg:city":"Chauchina",
    "sg:orig_category":"Carnicer\u00cdas, Carnicer\u00cdas",
    "sg:phone":"+34 958 44 71 96",
    "sg:postcode":"18330",
    "sg:province":"Granada",
    "wof:name":"Jamones Caberna",
    "wof:placetype":"venue"
},
  "geometry": {"coordinates":[-3.7732100487,37.2009162903],"type":"Point"}
}