{
  "type": "Feature",
  "properties": {
    "addr:full":"Calle de Jorge Guillen, 28 Vista Alegre Murcia 30007",
    "addr:housenumber":"28",
    "addr:postcode":"30007",
    "addr:street":"Calle De Jorge Guillen",
    "iso:country":"ES",
    "sg:address":"Calle de Jorge Guillen, 28",
    "sg:city":"Vista Alegre",
    "sg:orig_category":"Plomeros",
    "sg:phone":"+34 968 24 33 20",
    "sg:postcode":"30007",
    "sg:province":"Murcia",
    "wof:name":"Bayona Molina Jose Maria",
    "wof:placetype":"venue"
},
  "geometry": {"coordinates":[-1.1142389774,37.9970092773],"type":"Point"}
}