{
  "type": "Feature",
  "properties": {
    "addr:full":"Sect S, 26 Torre De La Higuera O Matalasca\u00e7as Huelva 21760",
    "addr:housenumber":"26",
    "addr:postcode":"21760",
    "addr:street":"Sect S",
    "iso:country":"ES",
    "sg:address":"Sect S, 26",
    "sg:city":"Torre De La Higuera O Matalasca\u00e7as",
    "sg:orig_category":"Alquiler De Apartamentos",
    "sg:phone":"+34 959 44 01 83",
    "sg:postcode":"21760",
    "sg:province":"Huelva",
    "wof:name":"Valladolid Romero Dolores",
    "wof:placetype":"venue"
},
  "geometry": {"coordinates":[-6.9495940208,37.256313324],"type":"Point"}
}