{
  "type": "Feature",
  "properties": {
    "iso:country":"ES",
    "sg:address":"Calle de Escultor Jamete, S/n",
    "sg:city":"Cuenca",
    "sg:orig_category":"Establecimientos De Cura, Prevenci\u00d3n Y Readaptaci\u00d3n",
    "sg:phone":"+34 969 24 06 47",
    "sg:postcode":"16003",
    "sg:province":"Cuenca",
    "sg:website":"www.epitelio.org/cuenca/luz",
    "wof:name":"Asociacion De Padres Contra La Droga Luz",
    "wof:placetype":"venue"
},
  "geometry": {"coordinates":[-2.1404666901,40.0678367615],"type":"Point"}
}