{
  "type": "Feature",
  "properties": {
    "iso:country":"ES",
    "sg:address":"Calle de Heros, 18",
    "sg:city":"Bilbao",
    "sg:orig_category":"Psic\u00d3logos",
    "sg:phone":"+34 944 24 82 13",
    "sg:postcode":"48009",
    "sg:province":"Vizcaya",
    "wof:name":"Corcuera Arejula Maria Dolores",
    "wof:placetype":"venue"
},
  "geometry": {"coordinates":[-2.9325680733,43.2653923035],"type":"Point"}
}