{
  "type": "Feature",
  "properties": {
    "iso:country":"ES",
    "sg:address":"Carr Arc, 2",
    "sg:city":"Sort",
    "sg:orig_category":"Abogados",
    "sg:phone":"+34 973 62 04 12",
    "sg:postcode":"25560",
    "sg:province":"Lleida",
    "wof:name":"Muxi Moner Ramon",
    "wof:placetype":"venue"
},
  "geometry": {"coordinates":[1.1303800344,42.4112358093],"type":"Point"}
}