{
  "type": "Feature",
  "properties": {
    "addr:full":"Calle de Marques De La Vega De Anzo, 3 Oviedo Asturias 33007",
    "addr:housenumber":"3",
    "addr:postcode":"33007",
    "addr:street":"Calle De Marques De La Vega De Anzo",
    "iso:country":"ES",
    "sg:address":"Calle de Marques De La Vega De Anzo, 3",
    "sg:city":"Oviedo",
    "sg:orig_category":"Asistencia Y Consejos",
    "sg:phone":"+34 985 27 17 71",
    "sg:postcode":"33007",
    "sg:province":"Asturias",
    "wof:name":"Fernandez-vigil Garcia Arturo",
    "wof:placetype":"venue"
},
  "geometry": {"coordinates":[-5.8483018875,43.3610877991],"type":"Point"}
}