{
  "type": "Feature",
  "properties": {
    "iso:country":"ES",
    "sg:address":"Condado De Trevi\u00f1o, 26",
    "sg:city":"Villalonquejar",
    "sg:orig_category":"Negocio De Madera",
    "sg:phone":"+34 947 29 70 50",
    "sg:postcode":"09001",
    "sg:province":"Burgos",
    "wof:name":"Carlemar S.l.",
    "wof:placetype":"venue"
},
  "geometry": {"coordinates":[-3.7355909348,42.375667572],"type":"Point"}
}