{
  "type": "Feature",
  "properties": {
    "addr:full":"Calle de Carrera De Darro, 23 Granada Granada 18010",
    "addr:housenumber":"23",
    "addr:postcode":"18010",
    "addr:street":"Calle De Carrera De Darro",
    "iso:country":"ES",
    "sg:address":"Calle de Carrera De Darro, 23",
    "sg:city":"Granada",
    "sg:orig_category":"Hoteles",
    "sg:phone":"+34 958 21 57 30",
    "sg:postcode":"18010",
    "sg:province":"Granada",
    "wof:name":"Inversiones Fernandez Mena S.l.",
    "wof:placetype":"venue"
},
  "geometry": {"coordinates":[-3.5934407711,37.1781387329],"type":"Point"}
}