{
  "type": "Feature",
  "properties": {
    "iso:country":"ES",
    "sg:address":"Calle de Pino Macareno, S/n",
    "sg:city":"Pe\u00f1afiel",
    "sg:orig_category":"Tratamiento De Aguas (productos)",
    "sg:phone":"+34 983 88 05 56",
    "sg:postcode":"47300",
    "sg:province":"Valladolid",
    "wof:name":"Ute Pe\u00f1afiel Edar",
    "wof:placetype":"venue"
},
  "geometry": {"coordinates":[-4.122235775,41.6019859314],"type":"Point"}
}