{
  "type": "Feature",
  "properties": {
    "addr:full":"Calle de Procesiones, 7 Bargas Toledo 45593",
    "addr:housenumber":"7",
    "addr:postcode":"45593",
    "addr:street":"Calle De Procesiones",
    "iso:country":"ES",
    "sg:address":"Calle de Procesiones, 7",
    "sg:city":"Bargas",
    "sg:orig_category":"Carnicer\u00cdas, Carnicer\u00cdas",
    "sg:phone":"+34 925 35 73 19",
    "sg:postcode":"45593",
    "sg:province":"Toledo",
    "wof:name":"Vianda Toledo S. L.",
    "wof:placetype":"venue"
},
  "geometry": {"coordinates":[-4.021982193,39.9394874573],"type":"Point"}
}