{
  "type": "Feature",
  "properties": {
    "iso:country":"ES",
    "sg:address":"Calle de Badajoz, 12",
    "sg:city":"San Fernando De Henares",
    "sg:orig_category":"Tiendas De Grano, Frutas Y Legumbres Secas (al Por Menor)",
    "sg:phone":"+34 916 73 49 50",
    "sg:postcode":"28830",
    "sg:province":"Madrid",
    "wof:name":"Liedo Aguado Angel Carlos",
    "wof:placetype":"venue"
},
  "geometry": {"coordinates":[-3.5356824398,40.4289474487],"type":"Point"}
}