{
  "type": "Feature",
  "properties": {
    "iso:country":"ES",
    "sg:address":"Plaz Santa Cruz, 2",
    "sg:city":"Sahagun",
    "sg:orig_category":"Art\u00cdculos Funerarios (al Por Menor)",
    "sg:phone":"+34 987 78 11 04",
    "sg:postcode":"24320",
    "sg:province":"Le\u00f3n",
    "sg:website":"www.paginasamarillas.es",
    "wof:name":"Ausibio Antolin S.l.",
    "wof:placetype":"venue"
},
  "geometry": {"coordinates":[-5.0078449249,42.3731536865],"type":"Point"}
}