{
  "type": "Feature",
  "properties": {
    "iso:country":"ES",
    "sg:address":"Calle de Prensa, 11",
    "sg:city":"Madrid",
    "sg:orig_category":"Inmobiliaria (agencias)",
    "sg:phone":"+34 917 66 84 44",
    "sg:postcode":"28033",
    "sg:province":"Madrid",
    "wof:name":"Mirape S.l.",
    "wof:placetype":"venue"
},
  "geometry": {"coordinates":[-3.6686189175,40.4704208374],"type":"Point"}
}