{
  "type": "Feature",
  "properties": {
    "iso:country":"ES",
    "sg:address":"Ctra Almatriche De, 83",
    "sg:city":"Almatriche Alto",
    "sg:orig_category":"Peluqueros: De Se\u00d1oras",
    "sg:phone":"+34 928 67 70 42",
    "sg:postcode":"35018",
    "sg:province":"Las Palmas",
    "wof:name":"Ramos Santana Carmen Nelia",
    "wof:placetype":"venue"
},
  "geometry": {"coordinates":[-15.4607486725,28.0851097107],"type":"Point"}
}