{
  "type": "Feature",
  "properties": {
    "addr:full":"Av Lloren\u00c7 Puig Tomas, 2 Viladecans Barcelona 08840",
    "addr:housenumber":"2",
    "addr:postcode":"08840",
    "addr:street":"Av Llorenc\u0327 Puig Tomas",
    "iso:country":"ES",
    "sg:address":"Av Lloren\u00c7 Puig Tomas, 2",
    "sg:city":"Viladecans",
    "sg:orig_category":"Cajas De Ahorro",
    "sg:phone":"+34 936 47 30 56",
    "sg:postcode":"08840",
    "sg:province":"Barcelona",
    "wof:name":"Caixa D'estalvis I Pensions De Barcelona",
    "wof:placetype":"venue"
},
  "geometry": {"coordinates":[2.0148069859,41.3248214722],"type":"Point"}
}