{
  "type": "Feature",
  "properties": {
    "addr:full":"Avda Ricardo Soriano, 36 Marbella M\u00e1laga 29600",
    "addr:housenumber":"36",
    "addr:postcode":"29600",
    "addr:street":"Avda Ricardo Soriano;Ma\u0301Laga",
    "iso:country":"ES",
    "sg:address":"Avda Ricardo Soriano, 36",
    "sg:city":"Marbella",
    "sg:orig_category":"Asesor\u00cda Fiscal Y Jur\u00cddica",
    "sg:phone":"+34 952 86 69 43",
    "sg:postcode":"29600",
    "sg:province":"M\u00e1laga",
    "wof:name":"Sundewall  Petra",
    "wof:placetype":"venue"
},
  "geometry": {"coordinates":[-4.8912148476,36.5105857849],"type":"Point"}
}