{
  "type": "Feature",
  "properties": {
    "addr:full":"Calle de Ebanisteria (la), 18 Alacant Alicante 03008",
    "addr:postcode":"03008",
    "addr:street":"Calle De Ebanisteria La",
    "iso:country":"ES",
    "sg:address":"Calle de Ebanisteria (la), 18",
    "sg:city":"Alacant",
    "sg:orig_category":"Chapister\u00cda",
    "sg:phone":"+34 965 28 45 39",
    "sg:postcode":"03008",
    "sg:province":"Alicante",
    "wof:name":"Chapa Autos 2000 S.l.",
    "wof:placetype":"venue"
},
  "geometry": {"coordinates":[-0.514514029,38.3343544006],"type":"Point"}
}