{
  "type": "Feature",
  "properties": {
    "addr:full":"Calle de Ayala, 22 Malaga M\u00e1laga 29002",
    "addr:housenumber":"22",
    "addr:postcode":"29002",
    "addr:street":"Calle De Ayala;Ma\u0301Laga",
    "iso:country":"ES",
    "sg:address":"Calle de Ayala, 22",
    "sg:city":"Malaga",
    "sg:orig_category":"Organizaciones Profesionales",
    "sg:phone":"+34 952 32 98 04",
    "sg:postcode":"29002",
    "sg:province":"M\u00e1laga",
    "wof:name":"Fermax Electronica S.a.e.",
    "wof:placetype":"venue"
},
  "geometry": {"coordinates":[-4.4321660995,36.7093353271],"type":"Point"}
}