{
  "type": "Feature",
  "properties": {
    "addr:full":"San Pedro (leixa), S/n Leixa La Coru\u00f1a 15405",
    "addr:postcode":"15405",
    "addr:street":"Leixa S / N Leixa La Corun\u0303A",
    "iso:country":"ES",
    "sg:address":"San Pedro (leixa), S/n",
    "sg:city":"Leixa",
    "sg:orig_category":"Molduras, Junquillos, Listones Y Molduras Perforadas",
    "sg:phone":"+34 981 32 60 27",
    "sg:postcode":"15405",
    "sg:province":"La Coru\u00f1a",
    "wof:name":"Sanchez Sanmartin Generosa Doradita",
    "wof:placetype":"venue"
},
  "geometry": {"coordinates":[-8.2437515259,43.5037994385],"type":"Point"}
}