{
  "type": "Feature",
  "properties": {
    "iso:country":"ES",
    "sg:address":"Calle de General Morales, 6",
    "sg:city":"Baena",
    "sg:orig_category":"Asesor\u00cda Sobre Comunicaci\u00d3n De Empresas",
    "sg:phone":"+34 957 67 11 40",
    "sg:postcode":"14850",
    "sg:province":"C\u00f3rdoba",
    "wof:name":"Baena 2001 S.l.",
    "wof:placetype":"venue"
},
  "geometry": {"coordinates":[-4.3224701881,37.6172714233],"type":"Point"}
}