{
  "type": "Feature",
  "properties": {
    "iso:country":"ES",
    "sg:address":"Calle de Caridad (la), 9",
    "sg:city":"Le\u00f3n",
    "sg:orig_category":"Modelistas",
    "sg:phone":"+34 987 22 97 78",
    "sg:postcode":"24007",
    "sg:province":"Le\u00f3n",
    "wof:name":"Garcia Lopez Luis",
    "wof:placetype":"venue"
},
  "geometry": {"coordinates":[-5.5635895729,42.6020355225],"type":"Point"}
}