{
  "type": "Feature",
  "properties": {
    "addr:full":"Av Bilbao, 70 Mira-sol Barcelona 08195",
    "addr:housenumber":"70",
    "addr:postcode":"08195",
    "addr:street":"Av Bilbao",
    "iso:country":"ES",
    "sg:address":"Av Bilbao, 70",
    "sg:city":"Mira-sol",
    "sg:orig_category":"Piscinas, Accesorios, Suministros (fabricaci\u00d3n, Al Por Mayor)",
    "sg:phone":"+34 935 89 27 75",
    "sg:postcode":"08195",
    "sg:province":"Barcelona",
    "wof:name":"Ferrer Robles Jose",
    "wof:placetype":"venue"
},
  "geometry": {"coordinates":[2.0627140999,41.4651985168],"type":"Point"}
}