{
  "type": "Feature",
  "properties": {
    "iso:country":"ES",
    "sg:address":"Plaz Conde Del Valle De Suchil, 19",
    "sg:city":"Madrid",
    "sg:orig_category":"M\u00c9dicos: An\u00c1lisis Cl\u00cdnicos",
    "sg:phone":"+34 914 46 23 43",
    "sg:postcode":"28015",
    "sg:province":"Madrid",
    "wof:name":"Alonso Munarriz Gloria",
    "wof:placetype":"venue"
},
  "geometry": {"coordinates":[-3.7105116844,40.4304542542],"type":"Point"}
}