{
  "type": "Feature",
  "properties": {
    "iso:country":"ES",
    "sg:address":"Zirkuitu Ibilbidea - Camino Del Circuito, 2",
    "sg:city":"Lasarte-oria",
    "sg:orig_category":"Electricidad, Electr\u00d3nica: Suministros (al Por Menor)",
    "sg:phone":"+34 943 36 23 19",
    "sg:postcode":"20160",
    "sg:province":"Guip\u00f9zcoa",
    "sg:website":"www.lanekin.com",
    "wof:name":"Lanekin, S.a.",
    "wof:placetype":"venue"
},
  "geometry": {"coordinates":[-2.0190370083,43.2557983398],"type":"Point"}
}