{
  "type": "Feature",
  "properties": {
    "iso:country":"ES",
    "sg:address":"Carrer de Sepulveda, 46",
    "sg:city":"Barcelona",
    "sg:orig_category":"Quincaller\u00cda (fabricaci\u00d3n)",
    "sg:phone":"+34 934 24 02 12",
    "sg:postcode":"08015",
    "sg:province":"Barcelona",
    "wof:name":"Alaball Miralles Maria",
    "wof:placetype":"venue"
},
  "geometry": {"coordinates":[2.1544778347,41.377117157],"type":"Point"}
}