{
  "type": "Feature",
  "properties": {
    "addr:full":"Calle de Filiberto Villalobos, 131 Guijuelo Salamanca 37770",
    "addr:housenumber":"131",
    "addr:postcode":"37770",
    "addr:street":"Calle De Filiberto Villalobos",
    "iso:country":"ES",
    "sg:address":"Calle de Filiberto Villalobos, 131",
    "sg:city":"Guijuelo",
    "sg:orig_category":"Institutos De Belleza",
    "sg:phone":"+34 923 58 01 26",
    "sg:postcode":"37770",
    "sg:province":"Salamanca",
    "wof:name":"Marti Jimenez Beatriz",
    "wof:placetype":"venue"
},
  "geometry": {"coordinates":[-5.6724090576,40.5599899292],"type":"Point"}
}