{
  "type": "Feature",
  "properties": {
    "iso:country":"ES",
    "sg:address":"Calle de Manuel Aza\u00d1a, 9",
    "sg:city":"Valladolid",
    "sg:orig_category":"Arquitectos",
    "sg:phone":"+34 983 33 59 93",
    "sg:postcode":"47014",
    "sg:province":"Valladolid",
    "wof:name":"Fernandez Tezanos Juan Jose",
    "wof:placetype":"venue"
},
  "geometry": {"coordinates":[-4.7678351402,41.6377716064],"type":"Point"}
}