{
  "type": "Feature",
  "properties": {
    "iso:country":"ES",
    "sg:address":"Avda Rafael Beca, 3",
    "sg:city":"Isla Mayor",
    "sg:orig_category":"Clubes Y Asociaciones Deportivas Y De Actividades Invernales Y De Monta\u00d1a",
    "sg:phone":"+34 954 77 72 16",
    "sg:postcode":"41140",
    "sg:province":"Sevilla",
    "wof:name":"Sociedad Deportiva De Caza Y Pesca",
    "wof:placetype":"venue"
},
  "geometry": {"coordinates":[-6.1640992165,37.1306800842],"type":"Point"}
}