{
  "type": "Feature",
  "properties": {
    "addr:full":"Calle de San Martin, 59 Donostia-san Sebastian Guip\u00f9zcoa 20007",
    "addr:housenumber":"59",
    "addr:postcode":"20007",
    "addr:street":"Calle De San Martin",
    "iso:country":"ES",
    "sg:address":"Calle de San Martin, 59",
    "sg:city":"Donostia-san Sebastian",
    "sg:orig_category":"M\u00c9dicos: Cirug\u00cda General",
    "sg:phone":"+34 943 46 53 90",
    "sg:postcode":"20007",
    "sg:province":"Guip\u00f9zcoa",
    "wof:name":"Irazusta Goena Martin",
    "wof:placetype":"venue"
},
  "geometry": {"coordinates":[-1.9872740507,43.3153419495],"type":"Point"}
}