{
  "type": "Feature",
  "properties": {
    "addr:full":"Calle de Valle De Aran, 3 Graus Huesca 22430",
    "addr:housenumber":"3",
    "addr:postcode":"22430",
    "addr:street":"Calle De Valle De Aran",
    "iso:country":"ES",
    "sg:address":"Calle de Valle De Aran, 3",
    "sg:city":"Graus",
    "sg:orig_category":"Frutas, Legumbres Frescas Y Tempranas (al Por Menor)",
    "sg:phone":"+34 974 54 07 74",
    "sg:postcode":"22430",
    "sg:province":"Huesca",
    "wof:name":"Noguero S.cv.",
    "wof:placetype":"venue"
},
  "geometry": {"coordinates":[0.3477500081,42.1910858154],"type":"Point"}
}