{
  "type": "Feature",
  "properties": {
    "addr:full":"Via Hispanidad, 30 Zaragoza Zaragoza 50009",
    "addr:housenumber":"30",
    "addr:postcode":"50009",
    "addr:street":"Via Hispanidad",
    "iso:country":"ES",
    "sg:address":"Via Hispanidad, 30",
    "sg:city":"Zaragoza",
    "sg:orig_category":"M\u00dasicos Int\u00c9rpretes",
    "sg:phone":"+34 976 75 00 30",
    "sg:postcode":"50009",
    "sg:province":"Zaragoza",
    "wof:name":"Al Ayre Espa\u00f1ol Clasicos S.l.",
    "wof:placetype":"venue"
},
  "geometry": {"coordinates":[-0.9132490158,41.6377487183],"type":"Point"}
}