{
  "type": "Feature",
  "properties": {
    "iso:country":"ES",
    "sg:address":"Calle de Baza, 324",
    "sg:city":"Albolote",
    "sg:orig_category":"Venta, Colocaci\u00d3n De Amortiguadores",
    "sg:phone":"+34 958 46 60 04",
    "sg:postcode":"18220",
    "sg:province":"Granada",
    "wof:name":"Bolcase Granada C. D.",
    "wof:placetype":"venue"
},
  "geometry": {"coordinates":[-3.6401340961,37.2252807617],"type":"Point"}
}