{
  "type": "Feature",
  "properties": {
    "iso:country":"ES",
    "sg:address":"Avda Santa Maria (de), 8",
    "sg:city":"Pontevedra",
    "sg:orig_category":"Agencias Y Agentes Comerciales, Representantes",
    "sg:phone":"+34 986 84 32 24",
    "sg:postcode":"36002",
    "sg:province":"Pontevedra",
    "wof:name":"Corbal Fernandez Manuel",
    "wof:placetype":"venue"
},
  "geometry": {"coordinates":[-8.6471939087,42.4323501587],"type":"Point"}
}