{
  "type": "Feature",
  "properties": {
    "iso:country":"ES",
    "sg:address":"Carr Ganganell, 23",
    "sg:city":"Besalu",
    "sg:orig_category":"Heladeros",
    "sg:phone":"+34 972 59 01 66",
    "sg:postcode":"17850",
    "sg:province":"Girona",
    "wof:name":"Millastra Planella Roser",
    "wof:placetype":"venue"
},
  "geometry": {"coordinates":[2.7091920376,42.2370147705],"type":"Point"}
}