{
  "type": "Feature",
  "properties": {
    "addr:full":"Carrer de Francesc Llunell, 34 Esplugues Llobregat Barcelona 08950",
    "addr:housenumber":"34",
    "addr:postcode":"08950",
    "addr:street":"Carrer De Francesc Llunell",
    "iso:country":"ES",
    "sg:address":"Carrer de Francesc Llunell, 34",
    "sg:city":"Esplugues Llobregat",
    "sg:orig_category":"Ropa Para Se\u00d1oras Y Caballeros (al Por Menor)",
    "sg:phone":"+34 933 72 61 09",
    "sg:postcode":"08950",
    "sg:province":"Barcelona",
    "wof:name":"Esplus-moda S.l.",
    "wof:placetype":"venue"
},
  "geometry": {"coordinates":[2.086220026,41.3735542297],"type":"Point"}
}