{
  "type": "Feature",
  "properties": {
    "addr:full":"Calle de Francisco Berenguer Mora, 4 Banyeres Mariola Alicante 03450",
    "addr:housenumber":"4",
    "addr:postcode":"03450",
    "addr:street":"Calle De Francisco Berenguer Mora",
    "iso:country":"ES",
    "sg:address":"Calle de Francisco Berenguer Mora, 4",
    "sg:city":"Banyeres Mariola",
    "sg:orig_category":"Asociaciones Humanitarias, De Cooperaci\u00d3n, De Acci\u00d3n Social",
    "sg:phone":"+34 965 56 71 87",
    "sg:postcode":"03450",
    "sg:province":"Alicante",
    "wof:name":"Associacio Alzheimer",
    "wof:placetype":"venue"
},
  "geometry": {"coordinates":[-0.658072412,38.7178421021],"type":"Point"}
}