{
  "type": "Feature",
  "properties": {
    "addr:full":"Calle de Federico Lopez, 31 Pozuelo De Alarcon Madrid 28224",
    "addr:housenumber":"31",
    "addr:postcode":"28224",
    "addr:street":"Calle De Federico Lopez",
    "iso:country":"ES",
    "sg:address":"Calle de Federico Lopez, 31",
    "sg:city":"Pozuelo De Alarcon",
    "sg:orig_category":"Minerales (al Por Mayor)",
    "sg:phone":"+34 913 51 52 74",
    "sg:postcode":"28224",
    "sg:province":"Madrid",
    "wof:name":"Minera Del Odiel S.l.",
    "wof:placetype":"venue"
},
  "geometry": {"coordinates":[-3.805038929,40.4581489563],"type":"Point"}
}