{
  "type": "Feature",
  "properties": {
    "iso:country":"ES",
    "sg:address":"Ctra Fuendejalon, 3",
    "sg:city":"Pozuelo De Aragon",
    "sg:orig_category":"Forjas Y Altos Hornos",
    "sg:phone":"+34 976 86 28 44",
    "sg:postcode":"50529",
    "sg:province":"Zaragoza",
    "wof:name":"Escolan Remon Yolanda",
    "wof:placetype":"venue"
},
  "geometry": {"coordinates":[-1.4735529423,41.759677887],"type":"Point"}
}