{
  "type": "Feature",
  "properties": {
    "iso:country":"ES",
    "sg:address":"Calle de Juan Ruiz De Alarcon, 21",
    "sg:city":"Ibi",
    "sg:orig_category":"Aparatos Y Equipo Para Tratamiento De Aguas",
    "sg:phone":"+34 965 55 14 84",
    "sg:postcode":"03440",
    "sg:province":"Alicante",
    "wof:name":"Sida S. A.",
    "wof:placetype":"venue"
},
  "geometry": {"coordinates":[-0.5757759809,38.6182327271],"type":"Point"}
}