{
  "type": "Feature",
  "properties": {
    "addr:full":"Calle de Plastico (el), 7 Azuqueca Henares Guadalajara 19200",
    "addr:housenumber":"7",
    "addr:postcode":"19200",
    "addr:street":"Calle De Plastico El",
    "iso:country":"ES",
    "sg:address":"Calle de Plastico (el), 7",
    "sg:city":"Azuqueca Henares",
    "sg:orig_category":"Empresas De Operaciones Portuarias Y Elevaci\u00d3n De Mercanc\u00cdas",
    "sg:phone":"+34 949 26 45 56",
    "sg:postcode":"19200",
    "sg:province":"Guadalajara",
    "wof:name":"Manipulados Y Retractilados Polo S.l.",
    "wof:placetype":"venue"
},
  "geometry": {"coordinates":[-3.2754080296,40.5512580872],"type":"Point"}
}