{
  "type": "Feature",
  "properties": {
    "addr:full":"Avda Giorgeta, 2 Valencia Valencia 46007",
    "addr:housenumber":"2",
    "addr:postcode":"46007",
    "addr:street":"Avda Giorgeta",
    "iso:country":"ES",
    "sg:address":"Avda Giorgeta, 2",
    "sg:city":"Valencia",
    "sg:orig_category":"Electricidad: Instaladores",
    "sg:phone":"+34 963 80 64 00",
    "sg:postcode":"46007",
    "sg:province":"Valencia",
    "wof:name":"Martinez Serrano Santiago",
    "wof:placetype":"venue"
},
  "geometry": {"coordinates":[-0.3866460025,39.4621162415],"type":"Point"}
}