{
  "type": "Feature",
  "properties": {
    "iso:country":"ES",
    "sg:address":"Calle de Bizkai, 77",
    "sg:city":"Galdakao",
    "sg:orig_category":"Peluquer\u00cdas, Peluquer\u00cda Mixta",
    "sg:phone":"+34 944 57 18 68",
    "sg:postcode":"48960",
    "sg:province":"Vizcaya",
    "wof:name":"Josune Parada Martinez",
    "wof:placetype":"venue"
},
  "geometry": {"coordinates":[-2.8479349613,43.2339897156],"type":"Point"}
}