{
  "type": "Feature",
  "properties": {
    "addr:full":"Disseminat, S/n Argentona Barcelona 08310",
    "addr:housenumber":"/ n",
    "addr:postcode":"08310",
    "addr:street":"Disseminat S",
    "iso:country":"ES",
    "sg:address":"Disseminat, S/n",
    "sg:city":"Argentona",
    "sg:orig_category":"Asociaciones Y Clubs Deportivos",
    "sg:phone":"+34 937 97 16 04",
    "sg:postcode":"08310",
    "sg:province":"Barcelona",
    "wof:name":"Tir Esportiu Mataro",
    "wof:placetype":"venue"
},
  "geometry": {"coordinates":[2.4036650658,41.5564155579],"type":"Point"}
}