{
  "type": "Feature",
  "properties": {
    "addr:full":"Carr Davant, 85 Alcarras Lleida 25180",
    "addr:housenumber":"85",
    "addr:postcode":"25180",
    "addr:street":"Carr Davant",
    "iso:country":"ES",
    "sg:address":"Carr Davant, 85",
    "sg:city":"Alcarras",
    "sg:orig_category":"Producci\u00d3n, Venta De Productos De Agricultura Biol\u00d3gica",
    "sg:phone":"+34 973 79 04 29",
    "sg:postcode":"25180",
    "sg:province":"Lleida",
    "wof:name":"Gilart Ribes Scp",
    "wof:placetype":"venue"
},
  "geometry": {"coordinates":[0.5282099843,41.5634155273],"type":"Point"}
}