{
  "type": "Feature",
  "properties": {
    "addr:full":"Carrer de Aribau, 74 Barcelona Barcelona 08036",
    "addr:housenumber":"74",
    "addr:postcode":"08036",
    "addr:street":"Carrer De Aribau",
    "iso:country":"ES",
    "sg:address":"Carrer de Aribau, 74",
    "sg:city":"Barcelona",
    "sg:orig_category":"Agencias De Viajes",
    "sg:phone":"+34 933 23 58 11",
    "sg:postcode":"08036",
    "sg:province":"Barcelona",
    "sg:website":"www.viajesiberia.com",
    "wof:name":"Viajes Iberia S.a.",
    "wof:placetype":"venue"
},
  "geometry": {"coordinates":[2.1583919525,41.3893356323],"type":"Point"}
}