{
  "type": "Feature",
  "properties": {
    "iso:country":"ES",
    "sg:address":"Calle de Octavio Vicent (escultor), 3",
    "sg:city":"Valencia",
    "sg:orig_category":"Ingenier\u00cda, Centros De Estudios (diversos)",
    "sg:phone":"+34 963 37 46 50",
    "sg:postcode":"46023",
    "sg:province":"Valencia",
    "sg:website":"www.codapa.com",
    "wof:name":"Codapa Ingenieria Y Gestion S.l.",
    "wof:placetype":"venue"
},
  "geometry": {"coordinates":[-0.3546510041,39.4617462158],"type":"Point"}
}