{
  "type": "Feature",
  "properties": {
    "iso:country":"ES",
    "sg:address":"Pantano, Km. 0002,0",
    "sg:city":"Lorca",
    "sg:orig_category":"Ferreter\u00cda (diversos)",
    "sg:phone":"+34 968 46 73 03",
    "sg:postcode":"30817",
    "sg:province":"Murcia",
    "wof:name":"Fernandez Mena Julio",
    "wof:placetype":"venue"
},
  "geometry": {"coordinates":[-1.7477288246,37.6872901917],"type":"Point"}
}