{
  "type": "Feature",
  "properties": {
    "iso:country":"ES",
    "sg:address":"Calle de Jose Canovas Ortiz, 3",
    "sg:city":"Beniajan",
    "sg:orig_category":"Alquiler De V\u00cddeo",
    "sg:phone":"+34 968 83 72 12",
    "sg:postcode":"30570",
    "sg:province":"Murcia",
    "wof:name":"Dvd. Estudios S.l.",
    "wof:placetype":"venue"
},
  "geometry": {"coordinates":[-1.0721189976,37.9789581299],"type":"Point"}
}