{
  "type": "Feature",
  "properties": {
    "iso:country":"ES",
    "sg:address":"Rbla San Julian (de), 12",
    "sg:city":"Teruel",
    "sg:orig_category":"Molduras, Junquillos, Listones Y Molduras Perforadas",
    "sg:phone":"+34 978 60 18 27",
    "sg:postcode":"44003",
    "sg:province":"Teruel",
    "wof:name":"Abril Dauden Juan",
    "wof:placetype":"venue"
},
  "geometry": {"coordinates":[-1.104184,40.339798],"type":"Point"}
}