{
  "type": "Feature",
  "properties": {
    "addr:full":"Avda Muelle (del), S/n Arguineguin Las Palmas 35120",
    "addr:postcode":"35120",
    "addr:street":"Avda Muelle Del S / N;Palmas",
    "iso:country":"ES",
    "sg:address":"Avda Muelle (del), S/n",
    "sg:city":"Arguineguin",
    "sg:orig_category":"Molduras, Junquillos, Listones Y Molduras Perforadas",
    "sg:phone":"+34 928 15 09 63",
    "sg:postcode":"35120",
    "sg:province":"Las Palmas",
    "wof:name":"Santana Ortega Manuel",
    "wof:placetype":"venue"
},
  "geometry": {"coordinates":[-15.6830463409,27.7618026733],"type":"Point"}
}