{
  "type": "Feature",
  "properties": {
    "addr:full":"Carr Bonavista, 42 Picassent Valencia 46220",
    "addr:housenumber":"42",
    "addr:postcode":"46220",
    "addr:street":"Carr Bonavista",
    "iso:country":"ES",
    "sg:address":"Carr Bonavista, 42",
    "sg:city":"Picassent",
    "sg:orig_category":"Panader\u00cdas, Panader\u00cdas",
    "sg:phone":"+34 961 24 28 72",
    "sg:postcode":"46220",
    "sg:province":"Valencia",
    "wof:name":"Forn Pastisseria L'abadia S.l.",
    "wof:placetype":"venue"
},
  "geometry": {"coordinates":[-0.4563469887,39.3655662537],"type":"Point"}
}