{
  "type": "Feature",
  "properties": {
    "addr:full":"Calle de Almeria, 39 Guillena Sevilla 41210",
    "addr:housenumber":"39",
    "addr:postcode":"41210",
    "addr:street":"Calle De Almeria",
    "iso:country":"ES",
    "sg:address":"Calle de Almeria, 39",
    "sg:city":"Guillena",
    "sg:orig_category":"Caf\u00c9s, Bares, Cervecer\u00cdas",
    "sg:phone":"+34 955 78 52 49",
    "sg:postcode":"41210",
    "sg:province":"Sevilla",
    "wof:name":"Santamaria Perez Manuel",
    "wof:placetype":"venue"
},
  "geometry": {"coordinates":[-6.0589170456,37.545337677],"type":"Point"}
}