{
  "type": "Feature",
  "properties": {
    "addr:full":"Carrer de Cortada, 24 Barcelona Barcelona 08035",
    "addr:housenumber":"24",
    "addr:postcode":"08035",
    "addr:street":"Carrer De Cortada",
    "iso:country":"ES",
    "sg:address":"Carrer de Cortada, 24",
    "sg:city":"Barcelona",
    "sg:orig_category":"Contenedores (mercanc\u00cdas)",
    "sg:phone":"+34 934 07 11 24",
    "sg:postcode":"08035",
    "sg:province":"Barcelona",
    "wof:name":"Izaplac Sl",
    "wof:placetype":"venue"
},
  "geometry": {"coordinates":[2.14686203,41.4238891602],"type":"Point"}
}