{
  "type": "Feature",
  "properties": {
    "iso:country":"ES",
    "sg:address":"Ctra. Calera, Km. 0005,7",
    "sg:city":"Talavera La Nueva",
    "sg:orig_category":"Empresas De Carpinter\u00cda De Madera",
    "sg:phone":"+34 925 59 91 81",
    "sg:postcode":"45694",
    "sg:province":"Toledo",
    "wof:name":"Euca Alberche S.l.",
    "wof:placetype":"venue"
},
  "geometry": {"coordinates":[-4.888379097,39.9339752197],"type":"Point"}
}