{
  "type": "Feature",
  "properties": {
    "addr:full":"Plaz Mayor, 23 Belorado Burgos 09250",
    "addr:housenumber":"23",
    "addr:postcode":"09250",
    "addr:street":"Plaz Mayor",
    "iso:country":"ES",
    "sg:address":"Plaz Mayor, 23",
    "sg:city":"Belorado",
    "sg:orig_category":"Loter\u00cda Y T\u00d3mbola",
    "sg:phone":"+34 947 58 12 37",
    "sg:postcode":"09250",
    "sg:province":"Burgos",
    "wof:name":"Delgado Camara Luis Alberto",
    "wof:placetype":"venue"
},
  "geometry": {"coordinates":[-3.9201889038,42.2467765808],"type":"Point"}
}