{
  "type": "Feature",
  "properties": {
    "addr:full":"Calle de La Rosa Del Azafran, 5 Madrid Madrid 28041",
    "addr:housenumber":"5",
    "addr:postcode":"28041",
    "addr:street":"Calle De La Rosa Del Azafran",
    "iso:country":"ES",
    "sg:address":"Calle de La Rosa Del Azafran, 5",
    "sg:city":"Madrid",
    "sg:orig_category":"Tiendas De Grano, Frutas Y Legumbres Secas (al Por Menor)",
    "sg:phone":"+34 917 95 17 85",
    "sg:postcode":"28041",
    "sg:province":"Madrid",
    "wof:name":"Alejo Mera Josefa",
    "wof:placetype":"venue"
},
  "geometry": {"coordinates":[-3.6951520443,40.3544921875],"type":"Point"}
}