{
  "type": "Feature",
  "properties": {
    "iso:country":"ES",
    "sg:address":"Avda Diputacion, S/n",
    "sg:city":"Calpe",
    "sg:orig_category":"Inmobiliaria (agencias)",
    "sg:phone":"+34 965 83 79 63",
    "sg:postcode":"03710",
    "sg:province":"Alicante",
    "wof:name":"Campillo Viejo Agapito",
    "wof:placetype":"venue"
},
  "geometry": {"coordinates":[0.0416899994,38.6459236145],"type":"Point"}
}