{
  "type": "Feature",
  "properties": {
    "addr:full":"Calle de Vega La, 3 Mieres Asturias 33600",
    "addr:housenumber":"3",
    "addr:postcode":"33600",
    "addr:street":"Calle De Vega La",
    "iso:country":"ES",
    "sg:address":"Calle de Vega La, 3",
    "sg:city":"Mieres",
    "sg:orig_category":"Plomeros",
    "sg:phone":"+34 985 45 26 30",
    "sg:postcode":"33600",
    "sg:province":"Asturias",
    "wof:name":"Pardo Lopez Julian",
    "wof:placetype":"venue"
},
  "geometry": {"coordinates":[-5.772977829,43.2498207092],"type":"Point"}
}