{
  "type": "Feature",
  "properties": {
    "iso:country":"ES",
    "sg:address":"Av Carrilet, 196",
    "sg:city":"Hospitalet Llobregat",
    "sg:orig_category":"Productores Recolectores, Venta Directa De Vinos",
    "sg:phone":"+34 933 38 06 22",
    "sg:postcode":"08901",
    "sg:province":"Barcelona",
    "wof:name":"Capel Vinos S.a.",
    "wof:placetype":"venue"
},
  "geometry": {"coordinates":[2.1126470566,41.3618240356],"type":"Point"}
}