{
  "type": "Feature",
  "properties": {
    "addr:full":"Carrer de Orient, 78 S. Cugat Valles Barcelona 08172",
    "addr:housenumber":"78",
    "addr:postcode":"08172",
    "addr:street":"Carrer De Orient;S. Cugat Valles Barcelona",
    "iso:country":"ES",
    "sg:address":"Carrer de Orient, 78",
    "sg:city":"S. Cugat Valles",
    "sg:orig_category":"Inmobiliaria (agencias)",
    "sg:phone":"+34 935 44 26 72",
    "sg:postcode":"08172",
    "sg:province":"Barcelona",
    "sg:website":"www.festaiserveis.com",
    "wof:name":"Mca Festa & Serveis S.l.",
    "wof:placetype":"venue"
},
  "geometry": {"coordinates":[2.091835022,41.4746932983],"type":"Point"}
}