{
  "type": "Feature",
  "properties": {
    "iso:country":"ES",
    "sg:address":"Avda Monforte, 100",
    "sg:city":"Chantada",
    "sg:orig_category":"Mec\u00c1nico Del Autom\u00d3vil",
    "sg:phone":"+34 982 44 11 87",
    "sg:postcode":"27500",
    "sg:province":"Lugo",
    "wof:name":"Talleres Diaz Y Ledo S.l.",
    "wof:placetype":"venue"
},
  "geometry": {"coordinates":[-7.766149044,42.6088485718],"type":"Point"}
}