{
  "type": "Feature",
  "properties": {
    "iso:country":"ES",
    "sg:address":"Ctra Calatorao-longares, 73",
    "sg:city":"Alfamen",
    "sg:orig_category":"Aparatos E Instalaci\u00d3n De Regad\u00cdos",
    "sg:phone":"+34 976 62 61 54",
    "sg:postcode":"50461",
    "sg:province":"Zaragoza",
    "sg:website":"www.riegosgperez.com",
    "wof:name":"Perez Valero Gregorio",
    "wof:placetype":"venue"
},
  "geometry": {"coordinates":[-1.2478239536,41.4400253296],"type":"Point"}
}