{
  "type": "Feature",
  "properties": {
    "iso:country":"ES",
    "sg:address":"Pase Guadalajara (de), 16",
    "sg:city":"San Sebastian De Los Reyes",
    "sg:orig_category":"Ense\u00d1anza Variada",
    "sg:phone":"+34 916 63 90 61",
    "sg:postcode":"28700",
    "sg:province":"Madrid",
    "sg:website":"www.alexna.com",
    "wof:name":"Alexna Formacion Social Limitada",
    "wof:placetype":"venue"
},
  "geometry": {"coordinates":[-3.6263942719,40.5475120544],"type":"Point"}
}