{
  "type": "Feature",
  "properties": {
    "addr:full":"Av Mistral, 69 Barcelona Barcelona 08015",
    "addr:housenumber":"69",
    "addr:postcode":"08015",
    "addr:street":"Av Mistral",
    "iso:country":"ES",
    "sg:address":"Av Mistral, 69",
    "sg:city":"Barcelona",
    "sg:orig_category":"Poller\u00cda Y Caza (al Por Menor)",
    "sg:phone":"+34 934 23 11 60",
    "sg:postcode":"08015",
    "sg:province":"Barcelona",
    "wof:name":"Justo Lozano Enriqueta",
    "wof:placetype":"venue"
},
  "geometry": {"coordinates":[2.1539101601,41.375793457],"type":"Point"}
}