{
  "type": "Feature",
  "properties": {
    "addr:full":"Calle de Ancha, 38 Ponferrada Le\u00f3n 24400",
    "addr:housenumber":"38",
    "addr:postcode":"24400",
    "addr:street":"Calle De Ancha",
    "iso:country":"ES",
    "sg:address":"Calle de Ancha, 38",
    "sg:city":"Ponferrada",
    "sg:orig_category":"Bancos",
    "sg:phone":"+34 987 42 84 82",
    "sg:postcode":"24400",
    "sg:province":"Le\u00f3n",
    "wof:name":"Banco Popular Espa\u00f1ol",
    "wof:placetype":"venue"
},
  "geometry": {"coordinates":[-6.5875940323,42.5471878052],"type":"Point"}
}