{
  "type": "Feature",
  "properties": {
    "iso:country":"ES",
    "sg:address":"Carrer de Senia (la), 2",
    "sg:city":"Muro Alcoy",
    "sg:orig_category":"Grafistas",
    "sg:phone":"+34 966 54 40 97",
    "sg:postcode":"03830",
    "sg:province":"Alicante",
    "sg:website":"www.artidiseny.com",
    "wof:name":"Climent Cortes Carmen",
    "wof:placetype":"venue"
},
  "geometry": {"coordinates":[-0.4395950139,38.7779045105],"type":"Point"}
}