{
  "type": "Feature",
  "properties": {
    "iso:country":"ES",
    "sg:address":"Av Can Cabanyes, 4",
    "sg:city":"Rubi",
    "sg:orig_category":"Peluquer\u00cdas, Peluquer\u00cda Mixta",
    "sg:phone":"+34 936 97 06 89",
    "sg:postcode":"08191",
    "sg:province":"Barcelona",
    "wof:name":"Quiroga Vazquez Susana",
    "wof:placetype":"venue"
},
  "geometry": {"coordinates":[2.031719923,41.4855957031],"type":"Point"}
}