{
  "type": "Feature",
  "properties": {
    "iso:country":"ES",
    "sg:address":"Calle de Jose Luis Perez Cepeda, 23",
    "sg:city":"Coru\u00d1a",
    "sg:orig_category":"Abogados",
    "sg:phone":"+34 981 14 39 55",
    "sg:postcode":"15004",
    "sg:province":"A Coru\u00f1a",
    "wof:name":"Varela Estevez Maria Esther",
    "wof:placetype":"venue"
},
  "geometry": {"coordinates":[-8.4135789871,43.3653526306],"type":"Point"}
}