{
  "type": "Feature",
  "properties": {
    "iso:country":"ES",
    "sg:address":"Carrer de Francesc Ferrer I Guardia, 29",
    "sg:city":"Mollet Valles",
    "sg:orig_category":"Comercio, Reparaci\u00d3n De Motocicletas, Bicicletas Y Piezas Sueltas",
    "sg:phone":"+34 935 70 04 56",
    "sg:postcode":"08100",
    "sg:province":"Barcelona",
    "wof:name":"Centro Holistic S.c.p.",
    "wof:placetype":"venue"
},
  "geometry": {"coordinates":[2.2057249546,41.5481529236],"type":"Point"}
}