{
  "type": "Feature",
  "properties": {
    "addr:full":"C/ Sant Bartomeu, 204 Inca Islas Baleares 07300",
    "addr:housenumber":"204",
    "addr:postcode":"07300",
    "addr:street":"C / Sant Bartomeu",
    "iso:country":"ES",
    "sg:address":"C/ Sant Bartomeu, 204",
    "sg:city":"Inca",
    "sg:orig_category":"Reposter\u00cdas",
    "sg:phone":"+34 971 50 10 28",
    "sg:postcode":"07300",
    "sg:province":"Islas Baleares",
    "wof:name":"Navarro Horrach Andres",
    "wof:placetype":"venue"
},
  "geometry": {"coordinates":[2.9077219963,39.7233276367],"type":"Point"}
}