{
  "type": "Feature",
  "properties": {
    "addr:full":"Avda Agua Marina, 25 Algeciras C\u00e1diz 11203",
    "addr:housenumber":"25;ca\u0301diz",
    "addr:postcode":"11203",
    "addr:street":"Avda Agua Marina",
    "iso:country":"ES",
    "sg:address":"Avda Agua Marina, 25",
    "sg:city":"Algeciras",
    "sg:orig_category":"Artes Gr\u00c1ficas, Artes Pl\u00c1sticas: Material Y Suministros (al Por Menor)",
    "sg:phone":"+34 956 66 30 71",
    "sg:postcode":"11203",
    "sg:province":"C\u00e1diz",
    "wof:name":"Respuestos Algesur S.l.",
    "wof:placetype":"venue"
},
  "geometry": {"coordinates":[-5.4601330757,36.1289024353],"type":"Point"}
}