{
  "type": "Feature",
  "properties": {
    "addr:full":"Calle de Fruta De La, 18 Aviles Asturias 33402",
    "addr:housenumber":"18",
    "addr:postcode":"33402",
    "addr:street":"Calle De Fruta De La",
    "iso:country":"ES",
    "sg:address":"Calle de Fruta De La, 18",
    "sg:city":"Aviles",
    "sg:orig_category":"Ropa Para Se\u00d1oras (al Por Menor)",
    "sg:phone":"+34 985 12 93 53",
    "sg:postcode":"33402",
    "sg:province":"Asturias",
    "sg:website":"www.benetton.com",
    "wof:name":"Meddle 72 S.l.",
    "wof:placetype":"venue"
},
  "geometry": {"coordinates":[-5.9220209122,43.5564498901],"type":"Point"}
}