{
  "type": "Feature",
  "properties": {
    "iso:country":"ES",
    "sg:address":"Carr Major, 18",
    "sg:city":"Almussafes",
    "sg:orig_category":"Abogados",
    "sg:phone":"+34 961 78 53 36",
    "sg:postcode":"46440",
    "sg:province":"Valencia",
    "wof:name":"Chaques Ramon Josep Domenec",
    "wof:placetype":"venue"
},
  "geometry": {"coordinates":[-0.4127599895,39.2909317017],"type":"Point"}
}