{
  "type": "Feature",
  "properties": {
    "addr:full":"Barr Ibarguren, S/n Amorebieta Vizcaya 48340",
    "addr:housenumber":"s / n",
    "addr:postcode":"48340",
    "iso:country":"ES",
    "sg:address":"Barr Ibarguren, S/n",
    "sg:city":"Amorebieta",
    "sg:orig_category":"Quincaller\u00cda (fabricaci\u00d3n)",
    "sg:phone":"+34 946 30 09 57",
    "sg:postcode":"48340",
    "sg:province":"Vizcaya",
    "wof:name":"Amilibia Y De La Iglesia S.a.",
    "wof:placetype":"venue"
},
  "geometry": {"coordinates":[-2.7282190323,43.2100524902],"type":"Point"}
}