{
  "type": "Feature",
  "properties": {
    "addr:full":"Carrer de Major, 3 Molins Rei Barcelona 08750",
    "addr:housenumber":"3",
    "addr:postcode":"08750",
    "addr:street":"Carrer De Major;Barcelona",
    "iso:country":"ES",
    "sg:address":"Carrer de Major, 3",
    "sg:city":"Molins Rei",
    "sg:orig_category":"Artes Gr\u00c1ficas, Artes Pl\u00c1sticas (curso)",
    "sg:phone":"+34 936 80 02 95",
    "sg:postcode":"08750",
    "sg:province":"Barcelona",
    "wof:name":"La Comercial S Coop. C. Ltda.",
    "wof:placetype":"venue"
},
  "geometry": {"coordinates":[2.0188190937,41.4111289978],"type":"Point"}
}