{
  "type": "Feature",
  "properties": {
    "addr:full":"Trva San Pelayo, 6 Ermua Vizcaya 48260",
    "addr:housenumber":"6",
    "addr:postcode":"48260",
    "addr:street":"Trva San Pelayo",
    "iso:country":"ES",
    "sg:address":"Trva San Pelayo, 6",
    "sg:city":"Ermua",
    "sg:orig_category":"Asesor\u00cda Sobre Comunicaci\u00d3n De Empresas",
    "sg:phone":"+34 943 17 14 04",
    "sg:postcode":"48260",
    "sg:province":"Vizcaya",
    "wof:name":"Pascual Marquina Ana",
    "wof:placetype":"venue"
},
  "geometry": {"coordinates":[-2.5052089691,43.1873512268],"type":"Point"}
}