{
  "type": "Feature",
  "properties": {
    "iso:country":"ES",
    "sg:address":"Bajera, S/n",
    "sg:city":"Poveda Soria",
    "sg:orig_category":"Promotores Constructores",
    "sg:phone":"+34 975 18 00 42",
    "sg:postcode":"42169",
    "sg:province":"Soria",
    "wof:name":"Tunel Piquera Ute",
    "wof:placetype":"venue"
},
  "geometry": {"coordinates":[-2.5031309128,42.0116462708],"type":"Point"}
}