{
  "type": "Feature",
  "properties": {
    "addr:full":"Carrer de Belchite, 9 Hospitalet Llobregat Barcelona 08906",
    "addr:housenumber":"9",
    "addr:postcode":"08906",
    "addr:street":"Carrer De Belchite",
    "iso:country":"ES",
    "sg:address":"Carrer de Belchite, 9",
    "sg:city":"Hospitalet Llobregat",
    "sg:orig_category":"Albergues",
    "sg:phone":"+34 934 37 04 58",
    "sg:postcode":"08906",
    "sg:province":"Barcelona",
    "wof:name":"Fundacion Salud Y Comunidad",
    "wof:placetype":"venue"
},
  "geometry": {"coordinates":[2.1032500267,41.3744392395],"type":"Point"}
}