{
  "type": "Feature",
  "properties": {
    "addr:full":"Urbanizacion Hacienda Las Chapas, 86 Elviria M\u00e1laga 29604",
    "addr:housenumber":"86",
    "addr:postcode":"29604",
    "addr:street":"Hacienda;Chapas;Ma\u0301Laga",
    "iso:country":"ES",
    "sg:address":"Urbanizacion Hacienda Las Chapas, 86",
    "sg:city":"Elviria",
    "sg:orig_category":"Promotores Constructores",
    "sg:phone":"+34 952 83 04 09",
    "sg:postcode":"29604",
    "sg:province":"M\u00e1laga",
    "wof:name":"J.m.a.ferguinot Marbella S.l.",
    "wof:placetype":"venue"
},
  "geometry": {"coordinates":[-4.7839570045,36.4972267151],"type":"Point"}
}