{
  "type": "Feature",
  "properties": {
    "addr:full":"Avda Zarauz (de), 35 San Fernando De Henares Madrid 28830",
    "addr:housenumber":"35",
    "addr:postcode":"28830",
    "addr:street":"Avda Zarauz De",
    "iso:country":"ES",
    "sg:address":"Avda Zarauz (de), 35",
    "sg:city":"San Fernando De Henares",
    "sg:orig_category":"Bazares, Art\u00cdculos De Limpieza Y De Cocina (al Por Menor)",
    "sg:phone":"+34 916 74 06 73",
    "sg:postcode":"28830",
    "sg:province":"Madrid",
    "wof:name":"Lopez Perez Maria Angeles",
    "wof:placetype":"venue"
},
  "geometry": {"coordinates":[-3.5264830589,40.4183235168],"type":"Point"}
}