{
  "type": "Feature",
  "properties": {
    "addr:full":"Calle de Mayor, 3 Tarazona Zaragoza 50500",
    "addr:housenumber":"3",
    "addr:postcode":"50500",
    "addr:street":"Calle De Mayor",
    "iso:country":"ES",
    "sg:address":"Calle de Mayor, 3",
    "sg:city":"Tarazona",
    "sg:orig_category":"Peluquer\u00cdas, Peluquer\u00cda Mixta",
    "sg:phone":"+34 976 64 07 74",
    "sg:postcode":"50500",
    "sg:province":"Zaragoza",
    "wof:name":"Murillo Calvo Elena",
    "wof:placetype":"venue"
},
  "geometry": {"coordinates":[-1.7329980135,41.9039382935],"type":"Point"}
}