{
  "type": "Feature",
  "properties": {
    "addr:full":"Carrer de Mandri, 44 Barcelona Barcelona 08022",
    "addr:housenumber":"44",
    "addr:postcode":"08022",
    "addr:street":"Carrer De Mandri",
    "iso:country":"ES",
    "sg:address":"Carrer de Mandri, 44",
    "sg:city":"Barcelona",
    "sg:orig_category":"Ropa Para Ni\u00d1os (al Por Menor)",
    "sg:phone":"+34 934 17 17 84",
    "sg:postcode":"08022",
    "sg:province":"Barcelona",
    "wof:name":"Imibcn S.l.",
    "wof:placetype":"venue"
},
  "geometry": {"coordinates":[2.1333060265,41.4039382935],"type":"Point"}
}