{
  "type": "Feature",
  "properties": {
    "iso:country":"ES",
    "sg:address":"Avda Atance (el), S/n",
    "sg:city":"Guadalajara",
    "sg:orig_category":"Distribuci\u00d3n De Petr\u00d3leo Y Derivados",
    "sg:phone":"+34 949 24 89 40",
    "sg:postcode":"19005",
    "sg:province":"Guadalajara",
    "wof:name":"Gasogu S.l.",
    "wof:placetype":"venue"
},
  "geometry": {"coordinates":[-3.155823946,40.6411361694],"type":"Point"}
}