{
  "type": "Feature",
  "properties": {
    "addr:full":"Barr Lombra\u00d1a, S/n Lombra\u00d1a Cantabria 39557",
    "addr:postcode":"39557",
    "addr:street":"Lombran\u0303A S / N",
    "iso:country":"ES",
    "sg:address":"Barr Lombra\u00d1a, S/n",
    "sg:city":"Lombra\u00d1a",
    "sg:orig_category":"Cajas De Ahorro",
    "sg:phone":"+34 942 72 90 67",
    "sg:postcode":"39557",
    "sg:province":"Cantabria",
    "sg:website":"www.cajacantabria.es",
    "wof:name":"Cableuropa",
    "wof:placetype":"venue"
},
  "geometry": {"coordinates":[-4.4142680168,43.1012878418],"type":"Point"}
}