{
  "type": "Feature",
  "properties": {
    "iso:country":"ES",
    "sg:address":"Av Pi I Margall, 7",
    "sg:city":"S. Adria Besos",
    "sg:orig_category":"Panader\u00cdas, Panader\u00cdas",
    "sg:phone":"+34 933 81 00 89",
    "sg:postcode":"08930",
    "sg:province":"Barcelona",
    "wof:name":"Casademont Folcra Maria",
    "wof:placetype":"venue"
},
  "geometry": {"coordinates":[2.2162799835,41.4328346252],"type":"Point"}
}