{
  "type": "Feature",
  "properties": {
    "addr:full":"Carr Bisbe Huix, Del, 16 Eivissa Islas Baleares 07800",
    "addr:housenumber":"16",
    "addr:postcode":"07800",
    "addr:street":"Carr Bisbe Huix Del",
    "iso:country":"ES",
    "sg:address":"Carr Bisbe Huix, Del, 16",
    "sg:city":"Eivissa",
    "sg:orig_category":"Mercer\u00cda, Lencer\u00cda (al Por Menor)",
    "sg:phone":"+34 971 30 79 07",
    "sg:postcode":"07800",
    "sg:province":"Islas Baleares",
    "wof:name":"Sanchez Gonzalez Antonio",
    "wof:placetype":"venue"
},
  "geometry": {"coordinates":[1.4294029474,38.9102745056],"type":"Point"}
}