{
  "type": "Feature",
  "properties": {
    "iso:country":"ES",
    "sg:address":"Calle de Nicomedes Pastor Diaz, 17",
    "sg:city":"Coru\u00d1a",
    "sg:orig_category":"Electrodom\u00c9sticos (al Por Menor)",
    "sg:phone":"+34 981 29 46 14",
    "sg:postcode":"15006",
    "sg:province":"La Coru\u00f1a",
    "wof:name":"Reborido Pose Alfredo",
    "wof:placetype":"venue"
},
  "geometry": {"coordinates":[-8.3995571136,43.3562736511],"type":"Point"}
}