{
  "type": "Feature",
  "properties": {
    "addr:full":"Calle de Carmen, 2 S. Clemente Cuenca 16600",
    "addr:housenumber":"2",
    "addr:postcode":"16600",
    "addr:street":"Calle De Carmen;S. Clemente Cuenca",
    "iso:country":"ES",
    "sg:address":"Calle de Carmen, 2",
    "sg:city":"S. Clemente",
    "sg:orig_category":"Pescader\u00cdas (al Por Menor)",
    "sg:phone":"+34 969 30 07 80",
    "sg:postcode":"16600",
    "sg:province":"Cuenca",
    "wof:name":"Esteso Saiz Maria Teresa",
    "wof:placetype":"venue"
},
  "geometry": {"coordinates":[-2.4256842136,39.4059028625],"type":"Point"}
}