{
  "type": "Feature",
  "properties": {
    "addr:full":"Calle de Virgen De Bego\u00d1a, 4 Sevilla Sevilla 41011",
    "addr:housenumber":"4",
    "addr:postcode":"41011",
    "addr:street":"Calle De Virgen De Begon\u0303A",
    "iso:country":"ES",
    "sg:address":"Calle de Virgen De Bego\u00d1a, 4",
    "sg:city":"Sevilla",
    "sg:orig_category":"Inform\u00c1tica, Ofim\u00c1tica (estudios, Asesor\u00cda, Ingenier\u00cda, Formaci\u00d3n)",
    "sg:phone":"+34 954 28 36 28",
    "sg:postcode":"41011",
    "sg:province":"Sevilla",
    "sg:website":"www.computerapia.com",
    "wof:name":"Mobiliario Iluminacion Y Obras S.l.",
    "wof:placetype":"venue"
},
  "geometry": {"coordinates":[-5.9995908737,37.3776359558],"type":"Point"}
}