{
  "type": "Feature",
  "properties": {
    "addr:full":"Carrer de Sant Jordi, 60 Vic Barcelona 08500",
    "addr:housenumber":"60",
    "addr:postcode":"08500",
    "addr:street":"Carrer De Sant Jordi",
    "iso:country":"ES",
    "sg:address":"Carrer de Sant Jordi, 60",
    "sg:city":"Vic",
    "sg:orig_category":"Cueros Y Pieles (al Por Mayor)",
    "sg:phone":"+34 938 86 22 09",
    "sg:postcode":"08500",
    "sg:province":"Barcelona",
    "wof:name":"Serra Rovira S.a.",
    "wof:placetype":"venue"
},
  "geometry": {"coordinates":[2.2641639709,41.9324035645],"type":"Point"}
}