{
  "type": "Feature",
  "properties": {
    "iso:country":"ES",
    "sg:address":"Avda Madrid, 21",
    "sg:city":"Sotillo Adrada",
    "sg:orig_category":"Zapater\u00cdas",
    "sg:phone":"+34 918 60 12 40",
    "sg:postcode":"05420",
    "sg:province":"\u00c1vila",
    "wof:name":"Moreno Y Plaza C.b.",
    "wof:placetype":"venue"
},
  "geometry": {"coordinates":[-4.5770921707,40.2944488525],"type":"Point"}
}