{
  "type": "Feature",
  "properties": {
    "iso:country":"ES",
    "sg:address":"Calle de Foxo, 14",
    "sg:city":"Tui",
    "sg:orig_category":"Institutos De Belleza",
    "sg:phone":"+34 986 60 07 72",
    "sg:postcode":"36700",
    "sg:province":"Pontevedra",
    "wof:name":"Alvarez Vilar Maria De Los Angeles",
    "wof:placetype":"venue"
},
  "geometry": {"coordinates":[-8.6451826096,42.0478668213],"type":"Point"}
}