{
  "type": "Feature",
  "properties": {
    "iso:country":"ES",
    "sg:address":"Avda Murcia (de), 2",
    "sg:city":"Cartagena",
    "sg:orig_category":"Cristaler\u00cdas",
    "sg:phone":"+34 968 12 35 14",
    "sg:postcode":"30203",
    "sg:province":"Murcia",
    "wof:name":"Galindo Segura Isidro",
    "wof:placetype":"venue"
},
  "geometry": {"coordinates":[-0.9847000241,37.6121864319],"type":"Point"}
}