{
  "type": "Feature",
  "properties": {
    "addr:full":"Avda Espa\u00d1a, 48 Plasencia C\u00e1ceres 10600",
    "addr:housenumber":"48",
    "addr:postcode":"10600",
    "addr:street":"Avda Espan\u0303A;Ca\u0301Ceres",
    "iso:country":"ES",
    "sg:address":"Avda Espa\u00d1a, 48",
    "sg:city":"Plasencia",
    "sg:orig_category":"Agentes, Concesionarios Y Sucursales De Camiones Y Veh\u00cdculos Industriales",
    "sg:phone":"+34 927 42 60 73",
    "sg:postcode":"10600",
    "sg:province":"C\u00e1ceres",
    "sg:website":"www.grupogerauto.com",
    "wof:name":"Extrecar S.l.",
    "wof:placetype":"venue"
},
  "geometry": {"coordinates":[-6.0983781815,40.0218467712],"type":"Point"}
}