{
  "type": "Feature",
  "properties": {
    "addr:full":"Ptda Algoros, 14 Elche Alicante 03293",
    "addr:housenumber":"14",
    "addr:postcode":"03293",
    "addr:street":"Ptda Algoros",
    "iso:country":"ES",
    "sg:address":"Ptda Algoros, 14",
    "sg:city":"Elche",
    "sg:orig_category":"Semiller\u00cdas",
    "sg:phone":"+34 966 63 10 51",
    "sg:postcode":"03293",
    "sg:province":"Alicante",
    "wof:name":"Ilicitana De Areas Rusticas S. L.",
    "wof:placetype":"venue"
},
  "geometry": {"coordinates":[-0.6995239854,38.2634811401],"type":"Point"}
}