{
  "type": "Feature",
  "properties": {
    "iso:country":"ES",
    "sg:address":"Plaz Andes (los), 1",
    "sg:city":"Sevilla",
    "sg:orig_category":"Molduras, Junquillos, Listones Y Molduras Perforadas",
    "sg:phone":"+34 954 23 97 37",
    "sg:postcode":"41012",
    "sg:province":"Sevilla",
    "wof:name":"Alvarez Alvarez Engracia",
    "wof:placetype":"venue"
},
  "geometry": {"coordinates":[-5.9734034538,37.4062309265],"type":"Point"}
}