{
  "type": "Feature",
  "properties": {
    "addr:full":"Calle de Fermin Palma, 5 Jaen Ja\u00e9n 23008",
    "addr:housenumber":"5;jae\u0301n",
    "addr:postcode":"23008",
    "addr:street":"Calle De Fermin Palma",
    "iso:country":"ES",
    "sg:address":"Calle de Fermin Palma, 5",
    "sg:city":"Jaen",
    "sg:orig_category":"Aparcamientos (infraestructuras, Accesorios)",
    "sg:phone":"+34 953 29 50 87",
    "sg:postcode":"23008",
    "sg:province":"Ja\u00e9n",
    "sg:website":"www.epassa.es",
    "wof:name":"Empresa Publica De Aparcamientos Y Servicios Municipales S.a.",
    "wof:placetype":"venue"
},
  "geometry": {"coordinates":[-3.7876288891,37.7749786377],"type":"Point"}
}