{
  "type": "Feature",
  "properties": {
    "addr:full":"Calle de Goya, S/n Beas Huelva 21630",
    "addr:housenumber":"s / n",
    "addr:postcode":"21630",
    "addr:street":"Calle De Goya",
    "iso:country":"ES",
    "sg:address":"Calle de Goya, S/n",
    "sg:city":"Beas",
    "sg:orig_category":"Chapister\u00cda",
    "sg:phone":"+34 959 30 84 47",
    "sg:postcode":"21630",
    "sg:province":"Huelva",
    "wof:name":"Marquez Pacheco Juan Manuel",
    "wof:placetype":"venue"
},
  "geometry": {"coordinates":[-6.7926921844,37.4220199585],"type":"Point"}
}