{
  "type": "Feature",
  "properties": {
    "addr:full":"Ctra. N. 340, Km. 0004,9 Sorbas Almer\u00eda 04270",
    "addr:postcode":"04270",
    "addr:street":"Ctra. N. 340 Km. 0004,9;Almeri\u0301A",
    "iso:country":"ES",
    "sg:address":"Ctra. N. 340, Km. 0004,9",
    "sg:city":"Sorbas",
    "sg:orig_category":"Albergues",
    "sg:phone":"+34 950 36 41 60",
    "sg:postcode":"04270",
    "sg:province":"Almer\u00eda",
    "wof:name":"Herrero Navarro Emilio",
    "wof:placetype":"venue"
},
  "geometry": {"coordinates":[-2.0861330032,37.086139679],"type":"Point"}
}