{
  "type": "Feature",
  "properties": {
    "iso:country":"ES",
    "sg:address":"Disset (urb Sta Maria De L'avall), 26",
    "sg:city":"Corbera Llobregat",
    "sg:orig_category":"Aceros Especiales",
    "sg:phone":"+34 936 88 18 50",
    "sg:postcode":"08757",
    "sg:province":"Barcelona",
    "wof:name":"Swissmetal S.l.",
    "wof:placetype":"venue"
},
  "geometry": {"coordinates":[1.9521909952,41.4241905212],"type":"Point"}
}