{
  "type": "Feature",
  "properties": {
    "addr:full":"Calle de Doctor Santos Olivera, 39 Hospital Orbigo Le\u00f3n 24286",
    "addr:housenumber":"39",
    "addr:postcode":"24286",
    "addr:street":"Calle De Doctor Santos Olivera;Leo\u0301N",
    "iso:country":"ES",
    "sg:address":"Calle de Doctor Santos Olivera, 39",
    "sg:city":"Hospital Orbigo",
    "sg:orig_category":"Caf\u00c9s, Bares, Cervecer\u00cdas",
    "sg:phone":"+34 987 36 11 99",
    "sg:postcode":"24286",
    "sg:province":"Le\u00f3n",
    "wof:name":"Fradejas Guerra Dionisio",
    "wof:placetype":"venue"
},
  "geometry": {"coordinates":[-5.881061554,42.4629592896],"type":"Point"}
}