{
  "type": "Feature",
  "properties": {
    "addr:full":"Avda Coria, 49 Palomares Rio Sevilla 41928",
    "addr:housenumber":"49",
    "addr:postcode":"41928",
    "addr:street":"Avda Coria;Rio Sevilla",
    "iso:country":"ES",
    "sg:address":"Avda Coria, 49",
    "sg:city":"Palomares Rio",
    "sg:orig_category":"Electricidad: Instaladores",
    "sg:phone":"+34 955 76 32 94",
    "sg:postcode":"41928",
    "sg:province":"Sevilla",
    "wof:name":"Coca Leflet Juan",
    "wof:placetype":"venue"
},
  "geometry": {"coordinates":[-6.0601887703,37.318939209],"type":"Point"}
}