{
  "type": "Feature",
  "properties": {
    "addr:full":"Calle de Pablo Ruiz Picasso, 1 Cordoba C\u00f3rdoba 14014",
    "addr:housenumber":"1",
    "addr:postcode":"14014",
    "addr:street":"Calle De Pablo Ruiz Picasso;Co\u0301Rdoba",
    "iso:country":"ES",
    "sg:address":"Calle de Pablo Ruiz Picasso, 1",
    "sg:city":"Cordoba",
    "sg:orig_category":"Molduras, Junquillos, Listones Y Molduras Perforadas",
    "sg:phone":"+34 957 44 19 55",
    "sg:postcode":"14014",
    "sg:province":"C\u00f3rdoba",
    "wof:name":"Fernandez Flores Rafael Manuel",
    "wof:placetype":"venue"
},
  "geometry": {"coordinates":[-4.7584700584,37.8902282715],"type":"Point"}
}