{
  "type": "Feature",
  "properties": {
    "addr:full":"Calle de Carrera, 10 Villanueva Arzobispo Ja\u00e9n 23330",
    "addr:postcode":"23330",
    "addr:street":"Calle De Carrera 10;Arzobispo Jae\u0301N",
    "iso:country":"ES",
    "sg:address":"Calle de Carrera, 10",
    "sg:city":"Villanueva Arzobispo",
    "sg:orig_category":"Panader\u00cdas, Panader\u00cdas",
    "sg:phone":"+34 953 45 09 46",
    "sg:postcode":"23330",
    "sg:province":"Ja\u00e9n",
    "wof:name":"Martines Perez David",
    "wof:placetype":"venue"
},
  "geometry": {"coordinates":[-3.0087752342,38.1696739197],"type":"Point"}
}