{
  "type": "Feature",
  "properties": {
    "iso:country":"ES",
    "sg:address":"Avda Tenor Fleta, 8",
    "sg:city":"Zaragoza",
    "sg:orig_category":"Arquitectos",
    "sg:phone":"+34 976 37 36 86",
    "sg:postcode":"50007",
    "sg:province":"Zaragoza",
    "wof:name":"Zar Arquitectos S.l.",
    "wof:placetype":"venue"
},
  "geometry": {"coordinates":[-0.8853139877,41.6417045593],"type":"Point"}
}