{
  "type": "Feature",
  "properties": {
    "addr:full":"Baltar, S/n Baltar La Coru\u00f1a 15541",
    "addr:housenumber":"s / n",
    "addr:postcode":"15541",
    "addr:street":"Baltar;La Corun\u0303A",
    "iso:country":"ES",
    "sg:address":"Baltar, S/n",
    "sg:city":"Baltar",
    "sg:orig_category":"Metales (labores, Pulido)",
    "sg:phone":"+34 981 36 33 50",
    "sg:postcode":"15541",
    "sg:province":"La Coru\u00f1a",
    "wof:name":"Cairo Metal S.l.",
    "wof:placetype":"venue"
},
  "geometry": {"coordinates":[-8.2099151611,43.5525283813],"type":"Point"}
}