{
  "type": "Feature",
  "properties": {
    "iso:country":"ES",
    "sg:address":"Av Mistral, 66",
    "sg:city":"Barcelona",
    "sg:orig_category":"Farmacias",
    "sg:phone":"+34 934 23 59 65",
    "sg:postcode":"08015",
    "sg:province":"Barcelona",
    "wof:name":"Frances Bosch Rosa",
    "wof:placetype":"venue"
},
  "geometry": {"coordinates":[2.1529760361,41.375869751],"type":"Point"}
}