{
  "type": "Feature",
  "properties": {
    "addr:full":"Avgd Mura, 20 Villarreal Castell\u00f3n 12540",
    "addr:housenumber":"20",
    "addr:postcode":"12540",
    "addr:street":"Mura",
    "iso:country":"ES",
    "sg:address":"Avgd Mura, 20",
    "sg:city":"Villarreal",
    "sg:orig_category":"Guarder\u00cdas",
    "sg:phone":"+34 964 53 76 05",
    "sg:postcode":"12540",
    "sg:province":"Castell\u00f3n",
    "wof:name":"Barrachina Reig Ana Belen",
    "wof:placetype":"venue"
},
  "geometry": {"coordinates":[-0.0952939987,39.9453048706],"type":"Point"}
}