{
  "type": "Feature",
  "properties": {
    "iso:country":"ES",
    "sg:address":"Calle de Cruz Blanca, 1",
    "sg:city":"Vitoria-gasteiz",
    "sg:orig_category":"Electrodom\u00c9sticos (al Por Menor)",
    "sg:phone":"+34 945 22 00 47",
    "sg:postcode":"01012",
    "sg:province":"\u00c1lava",
    "wof:name":"Ladritel Gasteiz S.l.",
    "wof:placetype":"venue"
},
  "geometry": {"coordinates":[-2.677451849,42.8521995544],"type":"Point"}
}