{
  "type": "Feature",
  "properties": {
    "addr:full":"Calle de Alfonso Xii, 2 Huelva Huelva 21003",
    "addr:housenumber":"2",
    "addr:postcode":"21003",
    "addr:street":"Calle De Alfonso Xii",
    "iso:country":"ES",
    "sg:address":"Calle de Alfonso Xii, 2",
    "sg:city":"Huelva",
    "sg:orig_category":"Ropa Para Se\u00d1oras (al Por Menor)",
    "sg:phone":"+34 959 25 36 06",
    "sg:postcode":"21003",
    "sg:province":"Huelva",
    "sg:website":"www.antonio-pernas.es",
    "wof:name":"Lourdes Y Maria Jose Sanchez S.l.",
    "wof:placetype":"venue"
},
  "geometry": {"coordinates":[-6.9498925209,37.2556037903],"type":"Point"}
}