{
  "type": "Feature",
  "properties": {
    "iso:country":"ES",
    "sg:address":"Carrer de Bruguera, 245",
    "sg:city":"Calella",
    "sg:orig_category":"Inform\u00c1tica (estudios, Servicios, Asesor\u00cda, Formaci\u00d3n)",
    "sg:phone":"+34 937 66 30 13",
    "sg:postcode":"08370",
    "sg:province":"Barcelona",
    "sg:website":"www.reset.es",
    "wof:name":"Recerca I Serveis Tecnologics S.l.",
    "wof:placetype":"venue"
},
  "geometry": {"coordinates":[2.665088892,41.6166038513],"type":"Point"}
}