{
  "type": "Feature",
  "properties": {
    "addr:full":"C/ Astronautas, 10 Torrellano Alicante 03320",
    "addr:housenumber":"10",
    "addr:postcode":"03320",
    "addr:street":"C / Astronautas",
    "iso:country":"ES",
    "sg:address":"C/ Astronautas, 10",
    "sg:city":"Torrellano",
    "sg:orig_category":"Empresarios",
    "sg:phone":"+34 965 68 11 21",
    "sg:postcode":"03320",
    "sg:province":"Alicante",
    "wof:name":"Los Tabiqueros S.l.",
    "wof:placetype":"venue"
},
  "geometry": {"coordinates":[-0.5852490067,38.2927131653],"type":"Point"}
}