{
  "type": "Feature",
  "properties": {
    "addr:full":"Ctra. Seo D'urgell, Km. 0184,2 Bolvir Girona 17539",
    "addr:postcode":"17539",
    "addr:street":"Ctra. Seo D'Urgell Km. 0184,2",
    "iso:country":"ES",
    "sg:address":"Ctra. Seo D'urgell, Km. 0184,2",
    "sg:city":"Bolvir",
    "sg:orig_category":"Perreras, Pensiones Para Perros, Gatos Y Otros Animales",
    "sg:phone":"+34 972 89 51 86",
    "sg:postcode":"17539",
    "sg:province":"Girona",
    "wof:name":"Gonzalez Colomina Nuria",
    "wof:placetype":"venue"
},
  "geometry": {"coordinates":[1.8799899817,42.4180793762],"type":"Point"}
}