{
  "type": "Feature",
  "properties": {
    "iso:country":"ES",
    "sg:address":"Avda Monelos, 103",
    "sg:city":"Coru\u00d1a",
    "sg:orig_category":"Ingenier\u00cda, Centros De Estudios (diversos)",
    "sg:phone":"+34 981 28 06 62",
    "sg:postcode":"15009",
    "sg:province":"La Coru\u00f1a",
    "wof:name":"Oyp S.l.",
    "wof:placetype":"venue"
},
  "geometry": {"coordinates":[-8.4014053345,43.3473472595],"type":"Point"}
}