{
  "type": "Feature",
  "properties": {
    "addr:full":"Avda Manuel De Falla, 13 Logro\u00f1o La Rioja 26006",
    "addr:housenumber":"13",
    "addr:postcode":"26006",
    "addr:street":"Avda Manuel De Falla;Rioja",
    "iso:country":"ES",
    "sg:address":"Avda Manuel De Falla, 13",
    "sg:city":"Logro\u00f1o",
    "sg:orig_category":"Arquitectos",
    "sg:phone":"+34 941 12 01 87",
    "sg:postcode":"26006",
    "sg:province":"La Rioja",
    "wof:name":"Almendariz Fernandez Juan Jose",
    "wof:placetype":"venue"
},
  "geometry": {"coordinates":[-2.4757456779,42.4566726685],"type":"Point"}
}