{
  "type": "Feature",
  "properties": {
    "addr:full":"Calle de Sol, 26 Montehermoso C\u00e1ceres 10810",
    "addr:housenumber":"26",
    "addr:postcode":"10810",
    "addr:street":"Calle De Sol;Ca\u0301Ceres",
    "iso:country":"ES",
    "sg:address":"Calle de Sol, 26",
    "sg:city":"Montehermoso",
    "sg:orig_category":"Cooperativas Agr\u00cdcolas",
    "sg:phone":"+34 927 43 02 31",
    "sg:postcode":"10810",
    "sg:province":"C\u00e1ceres",
    "wof:name":"Garrido Se\u00f1oran Benito",
    "wof:placetype":"venue"
},
  "geometry": {"coordinates":[-6.3496031761,40.0910186768],"type":"Point"}
}