{
  "type": "Feature",
  "properties": {
    "addr:full":"Calle de Rozabella, 6 Matas-pinar-monte Rozas Madrid 28290",
    "addr:housenumber":"6",
    "addr:postcode":"28290",
    "addr:street":"Calle De Rozabella",
    "iso:country":"ES",
    "sg:address":"Calle de Rozabella, 6",
    "sg:city":"Matas-pinar-monte Rozas",
    "sg:orig_category":"Asociaciones Y Clubs Deportivos",
    "sg:phone":"+34 916 40 10 22",
    "sg:postcode":"28290",
    "sg:province":"Madrid",
    "wof:name":"Gasset Fitness S.l. Unipersonal",
    "wof:placetype":"venue"
},
  "geometry": {"coordinates":[-3.8920469284,40.5388526917],"type":"Point"}
}