{
  "type": "Feature",
  "properties": {
    "addr:full":"Ctra Montcada, 230 Terrassa Barcelona 08223",
    "addr:housenumber":"230",
    "addr:postcode":"08223",
    "addr:street":"Ctra Montcada",
    "iso:country":"ES",
    "sg:address":"Ctra Montcada, 230",
    "sg:city":"Terrassa",
    "sg:orig_category":"Inmobiliaria (agencias)",
    "sg:phone":"+34 937 31 47 91",
    "sg:postcode":"08223",
    "sg:province":"Barcelona",
    "wof:name":"Inmobiliaria Manin-2 S.l.",
    "wof:placetype":"venue"
},
  "geometry": {"coordinates":[2.0151400566,41.5576324463],"type":"Point"}
}