{
  "type": "Feature",
  "properties": {
    "iso:country":"ES",
    "sg:address":"Calle de Cadiz, 2",
    "sg:city":"Padul",
    "sg:orig_category":"Empresas De Hormig\u00d3n, Hormig\u00d3n Armado Y Pretensado",
    "sg:phone":"+34 958 79 05 15",
    "sg:postcode":"18640",
    "sg:province":"Granada",
    "wof:name":"Extremera Moreno Ana",
    "wof:placetype":"venue"
},
  "geometry": {"coordinates":[-3.6363363266,37.0286064148],"type":"Point"}
}