{
  "type": "Feature",
  "properties": {
    "addr:full":"Gipuzkoa Etorbidea, 32 Arrasate Guip\u00f9zcoa 20500",
    "addr:housenumber":"32",
    "addr:postcode":"20500",
    "addr:street":"Gipuzkoa Etorbidea;Guipu\u0300Zcoa",
    "iso:country":"ES",
    "sg:address":"Gipuzkoa Etorbidea, 32",
    "sg:city":"Arrasate",
    "sg:orig_category":"Buzones De Correos",
    "sg:phone":"+34 943 79 15 58",
    "sg:postcode":"20500",
    "sg:province":"Guip\u00f9zcoa",
    "wof:name":"Jose Maria Gallastegui Y Cia S.a.",
    "wof:placetype":"venue"
},
  "geometry": {"coordinates":[-2.4786570072,43.0667304993],"type":"Point"}
}