{
  "type": "Feature",
  "properties": {
    "iso:country":"ES",
    "sg:address":"La Iglesia, 143",
    "sg:city":"Castillejo Robledo",
    "sg:orig_category":"Alquiler De Casas Y Habitaciones Amuebladas",
    "sg:phone":"+34 975 35 50 05",
    "sg:postcode":"42328",
    "sg:province":"Soria",
    "wof:name":"Casa Turismo Rural El Robledal Cb",
    "wof:placetype":"venue"
},
  "geometry": {"coordinates":[-3.4951789379,41.5592002869],"type":"Point"}
}