{
  "type": "Feature",
  "properties": {
    "addr:full":"Calle de Atarizar, 18 Donostia-san Sebastian Guip\u00f9zcoa 20013",
    "addr:housenumber":"18",
    "addr:postcode":"20013",
    "addr:street":"Calle De Atarizar",
    "iso:country":"ES",
    "sg:address":"Calle de Atarizar, 18",
    "sg:city":"Donostia-san Sebastian",
    "sg:orig_category":"Ense\u00d1anza: Idiomas",
    "sg:phone":"+34 943 28 72 32",
    "sg:postcode":"20013",
    "sg:province":"Guip\u00f9zcoa",
    "wof:name":"Zurriola Ikastola I.k.e.",
    "wof:placetype":"venue"
},
  "geometry": {"coordinates":[-1.9622219801,43.3212814331],"type":"Point"}
}