{
  "type": "Feature",
  "properties": {
    "addr:full":"Partida El Mascarat, 41 Altea Alicante 03590",
    "addr:housenumber":"41",
    "addr:postcode":"03590",
    "addr:street":"Partida El Mascarat",
    "iso:country":"ES",
    "sg:address":"Partida El Mascarat, 41",
    "sg:city":"Altea",
    "sg:orig_category":"Fabricaci\u00d3n De Cajas De Cart\u00d3n",
    "sg:phone":"+34 965 84 15 90",
    "sg:postcode":"03590",
    "sg:province":"Alicante",
    "wof:name":"Mora Delgado Vicente",
    "wof:placetype":"venue"
},
  "geometry": {"coordinates":[-0.0350769982,38.6129608154],"type":"Point"}
}