{
  "type": "Feature",
  "properties": {
    "addr:full":"Carrer de Ignasi Iglesias, 156 Prat Llobregat Barcelona 08820",
    "addr:housenumber":"156",
    "addr:postcode":"08820",
    "addr:street":"Carrer De Ignasi Iglesias;Llobregat",
    "iso:country":"ES",
    "sg:address":"Carrer de Ignasi Iglesias, 156",
    "sg:city":"Prat Llobregat",
    "sg:orig_category":"Fabricaci\u00d3n De Jabones, Detergentes Y Lej\u00cdas",
    "sg:phone":"+34 933 79 16 15",
    "sg:postcode":"08820",
    "sg:province":"Barcelona",
    "wof:name":"Maye Pujol Amparo",
    "wof:placetype":"venue"
},
  "geometry": {"coordinates":[2.0986170769,41.3318557739],"type":"Point"}
}