{
  "type": "Feature",
  "properties": {
    "addr:full":"Avda Aviacion Espa\u00d1ola, 11 San Javier Murcia 30730",
    "addr:housenumber":"11",
    "addr:postcode":"30730",
    "addr:street":"Avda Aviacion Espan\u0303Ola",
    "iso:country":"ES",
    "sg:address":"Avda Aviacion Espa\u00d1ola, 11",
    "sg:city":"San Javier",
    "sg:orig_category":"Farmacias",
    "sg:phone":"+34 968 19 11 38",
    "sg:postcode":"30730",
    "sg:province":"Murcia",
    "wof:name":"Fernandez Iba\u00f1ez Matilde",
    "wof:placetype":"venue"
},
  "geometry": {"coordinates":[-0.8311319947,37.8039054871],"type":"Point"}
}