{
  "type": "Feature",
  "properties": {
    "addr:full":"Arribes Del Duero, 12 Valladolid Valladolid 47012",
    "addr:housenumber":"12",
    "addr:postcode":"47012",
    "addr:street":"Del Duero",
    "iso:country":"ES",
    "sg:address":"Arribes Del Duero, 12",
    "sg:city":"Valladolid",
    "sg:orig_category":"Comercio De Piezas De Recambio Y De Accesorios De Veh\u00cdculos, Veh\u00cdculos Industriales",
    "sg:phone":"+34 983 29 17 67",
    "sg:postcode":"47012",
    "sg:province":"Valladolid",
    "wof:name":"Intercontinental De Automocion S.a.",
    "wof:placetype":"venue"
},
  "geometry": {"coordinates":[-4.7163348198,41.6241264343],"type":"Point"}
}