{
  "type": "Feature",
  "properties": {
    "iso:country":"ES",
    "sg:address":"Calle de Salamanca, Km. 0270,0",
    "sg:city":"Zamora",
    "sg:orig_category":"Bebidas",
    "sg:phone":"+34 980 53 00 96",
    "sg:postcode":"49028",
    "sg:province":"Zamora",
    "wof:name":"Casbega S.a.",
    "wof:placetype":"venue"
},
  "geometry": {"coordinates":[-5.7417287827,41.4942207336],"type":"Point"}
}