{
  "type": "Feature",
  "properties": {
    "addr:full":"Carr Dr Pujades, 52 Igualada Barcelona 08700",
    "addr:housenumber":"52",
    "addr:postcode":"08700",
    "addr:street":"Carr Dr Pujades",
    "iso:country":"ES",
    "sg:address":"Carr Dr Pujades, 52",
    "sg:city":"Igualada",
    "sg:orig_category":"Fabricaci\u00d3n De Su\u00c9ters Y Chalecos De Punto",
    "sg:phone":"+34 938 03 23 36",
    "sg:postcode":"08700",
    "sg:province":"Barcelona",
    "wof:name":"Sevilla Garsulla Merce",
    "wof:placetype":"venue"
},
  "geometry": {"coordinates":[1.6269429922,41.5818481445],"type":"Point"}
}