{
  "type": "Feature",
  "properties": {
    "addr:full":"Calle de Molino, 2 Bu\u00f1ol Valencia 46360",
    "addr:housenumber":"2",
    "addr:postcode":"46360",
    "addr:street":"Calle De Molino",
    "iso:country":"ES",
    "sg:address":"Calle de Molino, 2",
    "sg:city":"Bu\u00f1ol",
    "sg:orig_category":"Tubos De Cart\u00d3n Y Papel",
    "sg:phone":"+34 962 50 09 16",
    "sg:postcode":"46360",
    "sg:province":"Valencia",
    "wof:name":"La Papelera De Sant Jordi S.l.",
    "wof:placetype":"venue"
},
  "geometry": {"coordinates":[-0.7900890112,39.4177513123],"type":"Point"}
}