{
  "type": "Feature",
  "properties": {
    "addr:full":"Elizatxo Auzoa, 12 Hernani Guip\u00f9zcoa 20120",
    "addr:housenumber":"12",
    "addr:postcode":"20120",
    "addr:street":"Elizatxo Auzoa;Guipu\u0300Zcoa",
    "iso:country":"ES",
    "sg:address":"Elizatxo Auzoa, 12",
    "sg:city":"Hernani",
    "sg:orig_category":"Centros De Educaci\u00d3n Especial",
    "sg:phone":"+34 943 55 72 24",
    "sg:postcode":"20120",
    "sg:province":"Guip\u00f9zcoa",
    "sg:website":"www.elizatxoikastola.com",
    "wof:name":"Gobierno Vasco-eusko Jaurlaritza",
    "wof:placetype":"venue"
},
  "geometry": {"coordinates":[-1.9751670361,43.2638702393],"type":"Point"}
}