{
  "type": "Feature",
  "properties": {
    "addr:full":"San Bartolome Kalea, 13 Elgoibar Guip\u00f9zcoa 20870",
    "addr:housenumber":"13",
    "addr:postcode":"20870",
    "addr:street":"San Bartolome Kalea;Guipu\u0300Zcoa",
    "iso:country":"ES",
    "sg:address":"San Bartolome Kalea, 13",
    "sg:city":"Elgoibar",
    "sg:classifiers":[
        {
            "category":"Taxi",
            "type":"Transportation"
        }
    ],
    "sg:phone":"+34 943 74 11 11",
    "sg:postcode":"20870",
    "sg:province":"Guip\u00f9zcoa",
    "wof:name":"Moreno Chaves Fernando",
    "wof:placetype":"venue"
},
  "geometry": {"coordinates":[-2.4166080952,43.2144241333],"type":"Point"}
}