{
  "type": "Feature",
  "properties": {
    "addr:full":"Plaz Feria De La, 34 Palmas De Gran Canaria Las Palmas 35003",
    "addr:postcode":"35003",
    "iso:country":"ES",
    "sg:address":"Plaz Feria De La, 34",
    "sg:city":"Palmas De Gran Canaria",
    "sg:orig_category":"Abogados",
    "sg:phone":"+34 928 29 52 06",
    "sg:postcode":"35003",
    "sg:province":"Las Palmas",
    "wof:name":"Adarve Corporacion Juridica S.l.",
    "wof:placetype":"venue"
},
  "geometry": {"coordinates":[-15.4199867249,28.1103744507],"type":"Point"}
}