{
  "type": "Feature",
  "properties": {
    "addr:full":"Ctra. Nal. Madrid, 1 Caudete Fuentes Valencia 46315",
    "addr:housenumber":"1",
    "addr:postcode":"46315",
    "addr:street":"Ctra. Nal. Madrid",
    "iso:country":"ES",
    "sg:address":"Ctra. Nal. Madrid, 1",
    "sg:city":"Caudete Fuentes",
    "sg:orig_category":"Productores Recolectores, Venta Directa De Vinos",
    "sg:phone":"+34 962 31 91 28",
    "sg:postcode":"46315",
    "sg:province":"Valencia",
    "wof:name":"Cooperativa Agricola Y Caja Rural Nuestra Se\u00f1ora De Las Vi\u00f1as",
    "wof:placetype":"venue"
},
  "geometry": {"coordinates":[-1.2811390162,39.5577049255],"type":"Point"}
}