{
  "type": "Feature",
  "properties": {
    "addr:full":"Calle de Marques De Luca De Tena, 32 Sevilla Sevilla 41013",
    "addr:housenumber":"32",
    "addr:postcode":"41013",
    "addr:street":"Calle De Marques De Luca De Tena",
    "iso:country":"ES",
    "sg:address":"Calle de Marques De Luca De Tena, 32",
    "sg:city":"Sevilla",
    "sg:orig_category":"Bisuter\u00cda, Joyer\u00cda, Relojer\u00cda (al Por Menor)",
    "sg:phone":"+34 954 23 04 32",
    "sg:postcode":"41013",
    "sg:province":"Sevilla",
    "wof:name":"Mateo Cabrera Antonio",
    "wof:placetype":"venue"
},
  "geometry": {"coordinates":[-5.977025032,37.361831665],"type":"Point"}
}