{
  "type": "Feature",
  "properties": {
    "iso:country":"ES",
    "sg:address":"Calle de El Cerko, 3",
    "sg:city":"San Vicente De Barakaldo",
    "sg:orig_category":"Edici\u00d3n De Diarios, Revistas, Boletines",
    "sg:phone":"+34 944 99 92 48",
    "sg:postcode":"48903",
    "sg:province":"Vizcaya",
    "wof:name":"Hierro Santacoloma Jesus",
    "wof:placetype":"venue"
},
  "geometry": {"coordinates":[-2.9830539227,43.2847175598],"type":"Point"}
}