{
  "type": "Feature",
  "properties": {
    "iso:country":"ES",
    "sg:address":"Ctra Logro\u00d1o, S/n",
    "sg:city":"Oyon-oion",
    "sg:orig_category":"Empresas De Carpinter\u00cda",
    "sg:phone":"+34 945 62 23 32",
    "sg:postcode":"01320",
    "sg:province":"\u00c1lava",
    "wof:name":"Metalisterias Alumar S.l.",
    "wof:placetype":"venue"
},
  "geometry": {"coordinates":[-2.4376089573,42.4994850159],"type":"Point"}
}