{
  "type": "Feature",
  "properties": {
    "addr:full":"Ctra Valencia, 14 Pulgosa Albacete 02006",
    "addr:housenumber":"14",
    "addr:postcode":"02006",
    "addr:street":"Ctra Valencia",
    "iso:country":"ES",
    "sg:address":"Ctra Valencia, 14",
    "sg:city":"Pulgosa",
    "sg:orig_category":"Escayola Y Productos De Escayola (fabricaci\u00d3n, Al Por Mayor)",
    "sg:phone":"+34 967 24 46 75",
    "sg:postcode":"02006",
    "sg:province":"Albacete",
    "wof:name":"Escayolas Antonio S.l.",
    "wof:placetype":"venue"
},
  "geometry": {"coordinates":[-2.044303894,39.0605888367],"type":"Point"}
}