{
  "type": "Feature",
  "properties": {
    "addr:full":"Avda Alemania (de), S/n Playa Del Ingles Las Palmas 35100",
    "addr:housenumber":"/ n",
    "addr:postcode":"35100",
    "addr:street":"Avda Alemania De S",
    "iso:country":"ES",
    "sg:address":"Avda Alemania (de), S/n",
    "sg:city":"Playa Del Ingles",
    "sg:orig_category":"Ropa Para Ni\u00d1os (al Por Menor)",
    "sg:phone":"+34 928 76 56 18",
    "sg:postcode":"35100",
    "sg:province":"Las Palmas",
    "wof:name":"Canarias Amatista S.l.",
    "wof:placetype":"venue"
},
  "geometry": {"coordinates":[-15.5737190247,27.7490711212],"type":"Point"}
}