{
  "type": "Feature",
  "properties": {
    "iso:country":"ES",
    "sg:address":"Calle de Miguel Moya, 11",
    "sg:city":"Malaga",
    "sg:orig_category":"Muebles, Minoristas",
    "sg:phone":"+34 952 29 44 24",
    "sg:postcode":"29017",
    "sg:province":"M\u00e1laga",
    "wof:name":"Galvez Ruiz Jose",
    "wof:placetype":"venue"
},
  "geometry": {"coordinates":[-4.35983181,36.7202987671],"type":"Point"}
}