{
  "type": "Feature",
  "properties": {
    "addr:full":"Calle de Cristobal Colon, 6 Bailen Ja\u00e9n 23710",
    "addr:housenumber":"6",
    "addr:postcode":"23710",
    "addr:street":"Calle De Cristobal Colon;Jae\u0301N",
    "iso:country":"ES",
    "sg:address":"Calle de Cristobal Colon, 6",
    "sg:city":"Bailen",
    "sg:orig_category":"Florister\u00cdas",
    "sg:phone":"+34 953 67 13 08",
    "sg:postcode":"23710",
    "sg:province":"Ja\u00e9n",
    "wof:name":"Romero Cedron Roman",
    "wof:placetype":"venue"
},
  "geometry": {"coordinates":[-3.7768082619,38.0962524414],"type":"Point"}
}