{
  "type": "Feature",
  "properties": {
    "iso:country":"ES",
    "sg:address":"Calle de Dominicas, 17",
    "sg:city":"Almagro",
    "sg:orig_category":"Hoteles",
    "sg:phone":"+34 926 26 13 66",
    "sg:postcode":"13270",
    "sg:province":"Ciudad Real",
    "wof:name":"Hosteria De Almagro Valdeolivo Cr Sl",
    "wof:placetype":"venue"
},
  "geometry": {"coordinates":[-3.7079451084,38.8887634277],"type":"Point"}
}