{
  "type": "Feature",
  "properties": {
    "iso:country":"ES",
    "sg:address":"Pl Arago, 7",
    "sg:city":"Cambrils",
    "sg:orig_category":"Inmobiliaria (agencias)",
    "sg:phone":"+34 977 36 41 92",
    "sg:postcode":"43850",
    "sg:province":"Tarragona",
    "wof:name":"Comunidad De Propietarios De La Plaza Aragon",
    "wof:placetype":"venue"
},
  "geometry": {"coordinates":[1.0613000393,41.0672912598],"type":"Point"}
}