{
  "type": "Feature",
  "properties": {
    "addr:full":"Calle de Aladino, 9 Torremolinos M\u00e1laga 29620",
    "addr:housenumber":"9",
    "addr:postcode":"29620",
    "addr:street":"Calle De Aladino;Ma\u0301Laga",
    "iso:country":"ES",
    "sg:address":"Calle de Aladino, 9",
    "sg:city":"Torremolinos",
    "sg:orig_category":"Caf\u00c9s, Bares, Cervecer\u00cdas",
    "sg:phone":"+34 952 38 30 83",
    "sg:postcode":"29620",
    "sg:province":"M\u00e1laga",
    "wof:name":"Gnisci  Gladys",
    "wof:placetype":"venue"
},
  "geometry": {"coordinates":[-4.5050706863,36.6098861694],"type":"Point"}
}