{
  "type": "Feature",
  "properties": {
    "addr:full":"Avgd Caritg, 128 Badalona Barcelona 08917",
    "addr:housenumber":"128",
    "addr:postcode":"08917",
    "iso:country":"ES",
    "sg:address":"Avgd Caritg, 128",
    "sg:city":"Badalona",
    "sg:orig_category":"Molduras, Junquillos, Listones Y Molduras Perforadas",
    "sg:phone":"+34 933 99 97 42",
    "sg:postcode":"08917",
    "sg:province":"Barcelona",
    "wof:name":"Pedroche Macias Blasa",
    "wof:placetype":"venue"
},
  "geometry": {"coordinates":[2.2243900299,41.4483909607],"type":"Point"}
}