{
  "type": "Feature",
  "properties": {
    "iso:country":"ES",
    "sg:address":"Carrer de Toledo, 19",
    "sg:city":"Amposta",
    "sg:orig_category":"Colocaci\u00d3n, Mantenimiento, Vitrificaci\u00d3n De Parquets",
    "sg:phone":"+34 977 70 00 91",
    "sg:postcode":"43870",
    "sg:province":"Tarragona",
    "wof:name":"Costes Monllau Jordi",
    "wof:placetype":"venue"
},
  "geometry": {"coordinates":[0.5809839964,40.7088050842],"type":"Point"}
}