{
  "type": "Feature",
  "properties": {
    "iso:country":"ES",
    "sg:address":"Calle de Santa Cruz, 6",
    "sg:city":"Dos Hermanas",
    "sg:orig_category":"Fabricaci\u00d3n De Productos Textiles Sin Tejer",
    "sg:phone":"+34 955 67 60 21",
    "sg:postcode":"41700",
    "sg:province":"Sevilla",
    "wof:name":"Gonzalez Palma Juana",
    "wof:placetype":"venue"
},
  "geometry": {"coordinates":[-5.9249081612,37.2826652527],"type":"Point"}
}