{
  "type": "Feature",
  "properties": {
    "addr:full":"Calle de Serrano, 8 Algar Murcia 30366",
    "addr:housenumber":"8",
    "addr:postcode":"30366",
    "addr:street":"Calle De Serrano",
    "iso:country":"ES",
    "sg:address":"Calle de Serrano, 8",
    "sg:city":"Algar",
    "sg:orig_category":"Autob\u00das (explotaci\u00d3n Y Servicios De)",
    "sg:phone":"+34 968 50 60 82",
    "sg:postcode":"30366",
    "sg:province":"Murcia",
    "sg:website":"www.autocarespaterna.com",
    "wof:name":"Autocares Paterna S.l.",
    "wof:placetype":"venue"
},
  "geometry": {"coordinates":[-1.1298867464,37.9834747314],"type":"Point"}
}