{
  "type": "Feature",
  "properties": {
    "iso:country":"ES",
    "sg:address":"Cno. Villaca\u00f1as, S/n",
    "sg:city":"Tembleque",
    "sg:orig_category":"Mec\u00c1nico Del Autom\u00d3vil",
    "sg:phone":"+34 925 14 51 13",
    "sg:postcode":"45780",
    "sg:province":"Toledo",
    "wof:name":"Agromecanica Tembleque S.c.l.",
    "wof:placetype":"venue"
},
  "geometry": {"coordinates":[-3.54341,39.609165],"type":"Point"}
}