{
  "type": "Feature",
  "properties": {
    "iso:country":"ES",
    "sg:address":"Matxitxako Kalea, 4",
    "sg:city":"Zarautz",
    "sg:orig_category":"Asociaciones, Organismos Culturales Y Socioeducativos",
    "sg:phone":"+34 943 83 39 59",
    "sg:postcode":"20800",
    "sg:province":"Guip\u00f9zcoa",
    "wof:name":"Sociedad Cultural Galtza-gorri",
    "wof:placetype":"venue"
},
  "geometry": {"coordinates":[-2.1714220047,43.2865257263],"type":"Point"}
}