{
  "type": "Feature",
  "properties": {
    "addr:full":"Calle de Mayor, S/n Alcantarilla Murcia 30820",
    "addr:housenumber":"s",
    "addr:postcode":"30820",
    "addr:street":"Calle De Mayor;/ N",
    "iso:country":"ES",
    "sg:address":"Calle de Mayor, S/n",
    "sg:city":"Alcantarilla",
    "sg:orig_category":"Centros Comerciales Y Grandes Tiendas",
    "sg:phone":"+34 968 89 22 68",
    "sg:postcode":"30820",
    "sg:province":"Murcia",
    "wof:name":"Mu\u00f1oz Tomas Juan",
    "wof:placetype":"venue"
},
  "geometry": {"coordinates":[-1.2149790525,37.969203949],"type":"Point"}
}