{
  "type": "Feature",
  "properties": {
    "iso:country":"ES",
    "sg:address":"Rua Xeneral Pardi\u00d1as (do), 2",
    "sg:city":"Santiago De Compostela",
    "sg:orig_category":"Farmacias",
    "sg:phone":"+34 981 58 02 10",
    "sg:postcode":"15701",
    "sg:province":"La Coru\u00f1a",
    "wof:name":"De Donno  Alessadro",
    "wof:placetype":"venue"
},
  "geometry": {"coordinates":[-8.5465698242,42.8764724731],"type":"Point"}
}