{
  "type": "Feature",
  "properties": {
    "addr:full":"Lg Pi\u00f1eiro(buxan), S/n Buxan La Coru\u00f1a 15873",
    "addr:housenumber":"s",
    "addr:postcode":"15873",
    "addr:street":"/ N Buxan La Corun\u0303A",
    "iso:country":"ES",
    "sg:address":"Lg Pi\u00f1eiro(buxan), S/n",
    "sg:city":"Buxan",
    "sg:orig_category":"Art\u00cdculos De Madera (fabricaci\u00d3n Y Al Por Mayor)",
    "sg:phone":"+34 981 80 43 56",
    "sg:postcode":"15873",
    "sg:province":"La Coru\u00f1a",
    "wof:name":"Miguens Rois Eduardo",
    "wof:placetype":"venue"
},
  "geometry": {"coordinates":[-8.3964595795,43.3701095581],"type":"Point"}
}