{
  "type": "Feature",
  "properties": {
    "iso:country":"ES",
    "sg:address":"Carrer de Sor Lluisa Estivill, 10",
    "sg:city":"Reus",
    "sg:orig_category":"Lubrificantes (fabricaci\u00d3n, Al Por Mayor)",
    "sg:phone":"+34 977 31 12 91",
    "sg:postcode":"43202",
    "sg:province":"Tarragona",
    "wof:name":"Ferran Palleja Antoni",
    "wof:placetype":"venue"
},
  "geometry": {"coordinates":[1.1007709503,41.1506958008],"type":"Point"}
}