{
  "type": "Feature",
  "properties": {
    "iso:country":"ES",
    "sg:address":"Goya, 2",
    "sg:city":"Ainsa",
    "sg:orig_category":"Artesanado",
    "sg:phone":"+34 974 50 02 68",
    "sg:postcode":"22330",
    "sg:province":"Huesca",
    "wof:name":"Martinez Souto Manuel",
    "wof:placetype":"venue"
},
  "geometry": {"coordinates":[0.1332260072,42.4117507935],"type":"Point"}
}