{
  "type": "Feature",
  "properties": {
    "iso:country":"ES",
    "sg:address":"Carrer de Rocafort, 7",
    "sg:city":"Barcelona",
    "sg:orig_category":"Peleter\u00cdas",
    "sg:phone":"+34 933 25 75 92",
    "sg:postcode":"08015",
    "sg:province":"Barcelona",
    "wof:name":"Leony's Piel S. L.",
    "wof:placetype":"venue"
},
  "geometry": {"coordinates":[2.1580519676,41.3755187988],"type":"Point"}
}