{
  "type": "Feature",
  "properties": {
    "iso:country":"ES",
    "sg:address":"Calle de Maestria, 25",
    "sg:city":"Almeria",
    "sg:orig_category":"Molduras, Junquillos, Listones Y Molduras Perforadas",
    "sg:phone":"+34 950 26 41 16",
    "sg:postcode":"04008",
    "sg:province":"Almer\u00eda",
    "wof:name":"Pino Gonzalez Rosa Lorena",
    "wof:placetype":"venue"
},
  "geometry": {"coordinates":[-2.4568550587,36.8498649597],"type":"Point"}
}