{
  "type": "Feature",
  "properties": {
    "iso:country":"ES",
    "sg:address":"Praz Porto Pesqueiro-lonxa, S/n",
    "sg:city":"Vigo",
    "sg:orig_category":"Delegados, Agentes De Tr\u00c1nsito, Auxiliares De Transporte Internacional",
    "sg:phone":"+34 986 23 62 88",
    "sg:postcode":"36202",
    "sg:province":"Pontevedra",
    "wof:name":"Transportes C.novoa E Hijos",
    "wof:placetype":"venue"
},
  "geometry": {"coordinates":[-8.7320985794,42.2364654541],"type":"Point"}
}