{
  "type": "Feature",
  "properties": {
    "iso:country":"ES",
    "sg:address":"Calle de Calderon De La Barca, S/n",
    "sg:city":"Gijon",
    "sg:orig_category":"Supermercados Y Hipermercados",
    "sg:phone":"+34 985 19 55 15",
    "sg:postcode":"33204",
    "sg:province":"Asturias",
    "wof:name":"Trebol Center S. A.",
    "wof:placetype":"venue"
},
  "geometry": {"coordinates":[-5.651403904,43.5342483521],"type":"Point"}
}