{
  "type": "Feature",
  "properties": {
    "iso:country":"ES",
    "sg:address":"Plaz Constitucion (de La), 1",
    "sg:city":"Santa Cruz Del Valle",
    "sg:orig_category":"Oficinas De Turismo, Asociaciones De Iniciativa",
    "sg:phone":"+34 920 38 62 01",
    "sg:postcode":"05411",
    "sg:province":"\u00c1vila",
    "sg:website":"www.avilaturismo.com",
    "wof:name":"Ayuntamiento De Santa Cruz Del Valle",
    "wof:placetype":"venue"
},
  "geometry": {"coordinates":[-5.0023941994,40.2520599365],"type":"Point"}
}