{
  "type": "Feature",
  "properties": {
    "addr:full":"Poligono Industrial, 112 Astorga Le\u00f3n 24700",
    "addr:housenumber":"112",
    "addr:postcode":"24700",
    "addr:street":"Industrial;Leo\u0301N",
    "iso:country":"ES",
    "sg:address":"Poligono Industrial, 112",
    "sg:city":"Astorga",
    "sg:orig_category":"Escayola Y Productos De Escayola (fabricaci\u00d3n, Al Por Mayor)",
    "sg:phone":"+34 987 61 50 91",
    "sg:postcode":"24700",
    "sg:province":"Le\u00f3n",
    "wof:name":"Creaciones Pon Sl",
    "wof:placetype":"venue"
},
  "geometry": {"coordinates":[-6.0532841682,42.4577598572],"type":"Point"}
}