{
  "type": "Feature",
  "properties": {
    "iso:country":"ES",
    "sg:address":"Calle de Julio Ferrer, 6",
    "sg:city":"Pozuelo De Alarcon",
    "sg:orig_category":"Pod\u00d3logos: Pedicuros",
    "sg:phone":"+34 913 52 74 94",
    "sg:postcode":"28223",
    "sg:province":"Madrid",
    "wof:name":"Podoasistencia S.l.",
    "wof:placetype":"venue"
},
  "geometry": {"coordinates":[-3.8127400875,40.4358520508],"type":"Point"}
}