{
  "type": "Feature",
  "properties": {
    "addr:full":"Calle de Belostikale, 5 Bilbao Vizcaya 48005",
    "addr:housenumber":"5",
    "addr:postcode":"48005",
    "addr:street":"Calle De Belostikale",
    "iso:country":"ES",
    "sg:address":"Calle de Belostikale, 5",
    "sg:city":"Bilbao",
    "sg:orig_category":"Ropa Para Se\u00d1oras (al Por Menor)",
    "sg:phone":"+34 944 16 31 71",
    "sg:postcode":"48005",
    "sg:province":"Vizcaya",
    "wof:name":"Naveira Mosquera Obdulia",
    "wof:placetype":"venue"
},
  "geometry": {"coordinates":[-2.9244909286,43.2560844421],"type":"Point"}
}