{
  "type": "Feature",
  "properties": {
    "addr:full":"Urb Puerto Paraiso, S/n Estepona M\u00e1laga 29680",
    "addr:postcode":"29680",
    "addr:street":"Urb Puerto Paraiso S / N;Ma\u0301Laga",
    "iso:country":"ES",
    "sg:address":"Urb Puerto Paraiso, S/n",
    "sg:city":"Estepona",
    "sg:orig_category":"Manicuras",
    "sg:phone":"+34 951 31 82 90",
    "sg:postcode":"29680",
    "sg:province":"M\u00e1laga",
    "wof:name":"Parrilla Caceres Alejandra",
    "wof:placetype":"venue"
},
  "geometry": {"coordinates":[-5.1608190536,36.4156455994],"type":"Point"}
}