{
  "type": "Feature",
  "properties": {
    "addr:full":"Del Casino, 2 Dalias Almer\u00eda 04750",
    "addr:housenumber":"2",
    "addr:postcode":"04750",
    "addr:street":"Dalias Almeri\u0301A",
    "iso:country":"ES",
    "sg:address":"Del Casino, 2",
    "sg:city":"Dalias",
    "sg:orig_category":"Alimentaci\u00d3n General (al Por Menor)",
    "sg:phone":"+34 950 49 44 71",
    "sg:postcode":"04750",
    "sg:province":"Almer\u00eda",
    "wof:name":"Cara Martin David Salvador",
    "wof:placetype":"venue"
},
  "geometry": {"coordinates":[-2.8728890419,36.8234138489],"type":"Point"}
}