{
  "type": "Feature",
  "properties": {
    "addr:full":"Avda Gijon, 77 Valladolid Valladolid 47009",
    "addr:housenumber":"77",
    "addr:postcode":"47009",
    "addr:street":"Avda Gijon",
    "iso:country":"ES",
    "sg:address":"Avda Gijon, 77",
    "sg:city":"Valladolid",
    "sg:orig_category":"Agentes, Concesionarios Y Sucursales De Veh\u00cdculos",
    "sg:phone":"+34 983 36 29 77",
    "sg:postcode":"47009",
    "sg:province":"Valladolid",
    "wof:name":"Segauto 2000 S.l.",
    "wof:placetype":"venue"
},
  "geometry": {"coordinates":[-4.7572031021,41.6602478027],"type":"Point"}
}