{
  "type": "Feature",
  "properties": {
    "iso:country":"ES",
    "sg:address":"Calle de Canovas Del Castillo, 73",
    "sg:city":"Jumilla",
    "sg:orig_category":"Droguer\u00cdas (al Por Menor)",
    "sg:phone":"+34 968 78 02 62",
    "sg:postcode":"30520",
    "sg:province":"Murcia",
    "wof:name":"Ochando Requena Jose Manuel",
    "wof:placetype":"venue"
},
  "geometry": {"coordinates":[-1.3265861273,38.4749107361],"type":"Point"}
}