{
  "type": "Feature",
  "properties": {
    "iso:country":"ES",
    "sg:address":"Carrer de Leiva, 80",
    "sg:city":"Barcelona",
    "sg:orig_category":"Electricidad: Instaladores",
    "sg:phone":"+34 934 23 70 94",
    "sg:postcode":"08014",
    "sg:province":"Barcelona",
    "wof:name":"Instalaciones Mb42 S.l.",
    "wof:placetype":"venue"
},
  "geometry": {"coordinates":[2.1466519833,41.3742446899],"type":"Point"}
}