{
  "type": "Feature",
  "properties": {
    "addr:full":"Calle de Jesus Alferez, 32 Santa Maria Aguila Almer\u00eda 04710",
    "addr:housenumber":"32",
    "addr:postcode":"04710",
    "addr:street":"Calle De Jesus Alferez;Almeri\u0301A",
    "iso:country":"ES",
    "sg:address":"Calle de Jesus Alferez, 32",
    "sg:city":"Santa Maria Aguila",
    "sg:orig_category":"Quincaller\u00cda (al Por Menor)",
    "sg:phone":"+34 950 58 04 87",
    "sg:postcode":"04710",
    "sg:province":"Almer\u00eda",
    "wof:name":"Romero Sanchez Ana Maria",
    "wof:placetype":"venue"
},
  "geometry": {"coordinates":[-2.7761869431,36.7820968628],"type":"Point"}
}