{
  "type": "Feature",
  "properties": {
    "addr:full":"Calle de Baza, 6 Albolote Granada 18220",
    "addr:housenumber":"6",
    "addr:postcode":"18220",
    "addr:street":"Calle De Baza",
    "iso:country":"ES",
    "sg:address":"Calle de Baza, 6",
    "sg:city":"Albolote",
    "sg:orig_category":"Ingeniero De Sonido",
    "sg:phone":"+34 900 50 44 77",
    "sg:postcode":"18220",
    "sg:province":"Granada",
    "sg:website":"www.laboratorioscavendish.com",
    "wof:name":"Cavendish S.l.",
    "wof:placetype":"venue"
},
  "geometry": {"coordinates":[-3.6205580235,37.1914863586],"type":"Point"}
}