{
  "type": "Feature",
  "properties": {
    "iso:country":"ES",
    "sg:address":"Calle de Fe, 9",
    "sg:city":"Madrid",
    "sg:orig_category":"Herboristas (al Por Menor)",
    "sg:phone":"+34 915 27 28 33",
    "sg:postcode":"28012",
    "sg:province":"Madrid",
    "wof:name":"Herbolario El Druida De Lavapies S.l.",
    "wof:placetype":"venue"
},
  "geometry": {"coordinates":[-3.7002341747,40.4089889526],"type":"Point"}
}