{
  "type": "Feature",
  "properties": {
    "iso:country":"ES",
    "sg:address":"Plaz Iglesia, S/n",
    "sg:city":"Cabezo Torres",
    "sg:orig_category":"Centros De Educaci\u00d3n Especial",
    "sg:phone":"+34 968 83 23 51",
    "sg:postcode":"30110",
    "sg:province":"Murcia",
    "wof:name":"Colegio Nacional J. Rubio Gomariz",
    "wof:placetype":"venue"
},
  "geometry": {"coordinates":[-1.1360189915,38.0214653015],"type":"Point"}
}