{
  "type": "Feature",
  "properties": {
    "iso:country":"ES",
    "sg:address":"Ctra Nacional 340, Km. 1178,0",
    "sg:city":"Torredembarra",
    "sg:orig_category":"Albergues",
    "sg:phone":"+34 977 64 51 21",
    "sg:postcode":"43830",
    "sg:province":"Tarragona",
    "wof:name":"A Nosa Casa Galega S.l.",
    "wof:placetype":"venue"
},
  "geometry": {"coordinates":[1.3949923515,41.1409492493],"type":"Point"}
}