{
  "type": "Feature",
  "properties": {
    "iso:country":"ES",
    "sg:address":"Carrer de Pont, 4",
    "sg:city":"Denia",
    "sg:orig_category":"Inmobiliaria (agencias)",
    "sg:phone":"+34 966 42 45 61",
    "sg:postcode":"03700",
    "sg:province":"Alicante",
    "wof:name":"Tursing S.l.",
    "wof:placetype":"venue"
},
  "geometry": {"coordinates":[0.1092749983,38.8433532715],"type":"Point"}
}