{
  "type": "Feature",
  "properties": {
    "iso:country":"ES",
    "sg:address":"Cami Ca La Madrona (de), 28",
    "sg:city":"Mataro",
    "sg:orig_category":"Fabricaci\u00d3n De Su\u00c9ters Y Chalecos De Punto",
    "sg:phone":"+34 937 90 22 71",
    "sg:postcode":"08304",
    "sg:province":"Barcelona",
    "wof:name":"Logarpunt S.l.",
    "wof:placetype":"venue"
},
  "geometry": {"coordinates":[2.453979969,41.5543670654],"type":"Point"}
}