{
  "type": "Feature",
  "properties": {
    "addr:full":"Calle de Medina Azahara, S/n Arroyo De La Miel-benalmadena Costa M\u00e1laga 29631",
    "addr:housenumber":"s / n",
    "addr:postcode":"29631",
    "addr:street":"Calle De Medina Azahara;Ma\u0301Laga",
    "iso:country":"ES",
    "sg:address":"Calle de Medina Azahara, S/n",
    "sg:city":"Arroyo De La Miel-benalmadena Costa",
    "sg:orig_category":"Art\u00cdculos De Decoraci\u00d3n",
    "sg:phone":"+34 952 44 05 11",
    "sg:postcode":"29631",
    "sg:province":"M\u00e1laga",
    "wof:name":"Lindgren  Riitta",
    "wof:placetype":"venue"
},
  "geometry": {"coordinates":[-4.5289440155,36.6027412415],"type":"Point"}
}