{
  "type": "Feature",
  "properties": {
    "iso:country":"ES",
    "sg:address":"Calle de Doctor Alfredo Martinez, 3",
    "sg:city":"Oviedo",
    "sg:orig_category":"M\u00c9dicos: Alergolog\u00cda",
    "sg:phone":"+34 985 23 80 12",
    "sg:postcode":"33005",
    "sg:province":"Asturias",
    "wof:name":"Bayon Garcia Jose Manuel",
    "wof:placetype":"venue"
},
  "geometry": {"coordinates":[-5.8571929932,43.3597640991],"type":"Point"}
}