{
  "type": "Feature",
  "properties": {
    "addr:full":"Avda Vigo, 119 Laredo Pontevedra 36320",
    "addr:housenumber":"119",
    "addr:postcode":"36320",
    "addr:street":"Avda Vigo",
    "iso:country":"ES",
    "sg:address":"Avda Vigo, 119",
    "sg:city":"Laredo",
    "sg:orig_category":"Caf\u00c9s, Bares, Cervecer\u00cdas",
    "sg:phone":"+34 986 45 01 59",
    "sg:postcode":"36320",
    "sg:province":"Pontevedra",
    "wof:name":"Lopez Vazquez Jose",
    "wof:placetype":"venue"
},
  "geometry": {"coordinates":[-8.6428003311,42.4304618835],"type":"Point"}
}