{
  "type": "Feature",
  "properties": {
    "iso:country":"ES",
    "sg:address":"Carrer de Lledoner, 6",
    "sg:city":"Palma",
    "sg:orig_category":"Internados & Ense\u00d1anza Privada",
    "sg:phone":"+34 971 47 40 96",
    "sg:postcode":"07008",
    "sg:province":"Islas Baleares",
    "wof:name":"Fundacion Heura 1",
    "wof:placetype":"venue"
},
  "geometry": {"coordinates":[2.6760249138,39.586971283],"type":"Point"}
}