{
  "type": "Feature",
  "properties": {
    "addr:full":"Calle de Sepulcro, 26 Zaragoza Zaragoza 50001",
    "addr:housenumber":"26",
    "addr:postcode":"50001",
    "addr:street":"Calle De Sepulcro",
    "iso:country":"ES",
    "sg:address":"Calle de Sepulcro, 26",
    "sg:city":"Zaragoza",
    "sg:orig_category":"Molduras, Junquillos, Listones Y Molduras Perforadas",
    "sg:phone":"+34 976 39 99 07",
    "sg:postcode":"50001",
    "sg:province":"Zaragoza",
    "wof:name":"Bar Boteron",
    "wof:placetype":"venue"
},
  "geometry": {"coordinates":[-0.8735949993,41.6542854309],"type":"Point"}
}