{
  "type": "Feature",
  "properties": {
    "addr:full":"Ctra La Geria - San Bartolome, S/n Geria Las Palmas 35570",
    "addr:housenumber":"s / n",
    "addr:postcode":"35570",
    "addr:street":"Ctra La Geria San Bartolome",
    "iso:country":"ES",
    "sg:address":"Ctra La Geria - San Bartolome, S/n",
    "sg:city":"Geria",
    "sg:orig_category":"Bazares, Art\u00cdculos De Limpieza Y De Cocina (al Por Menor)",
    "sg:phone":"+34 928 17 31 38",
    "sg:postcode":"35570",
    "sg:province":"Las Palmas",
    "wof:name":"De Leon Exposito Dulcenombre Eugenia",
    "wof:placetype":"venue"
},
  "geometry": {"coordinates":[-13.7659454346,28.9523696899],"type":"Point"}
}