{
  "type": "Feature",
  "properties": {
    "iso:country":"ES",
    "sg:address":"Trav De Gracia, 147",
    "sg:city":"Barcelona",
    "sg:orig_category":"Ropa Para Se\u00d1oras (al Por Menor)",
    "sg:phone":"+34 932 17 32 89",
    "sg:postcode":"08012",
    "sg:province":"Barcelona",
    "wof:name":"Sanchez Cardozo Luis Agustin",
    "wof:placetype":"venue"
},
  "geometry": {"coordinates":[2.1568379402,41.4008712769],"type":"Point"}
}