{
  "type": "Feature",
  "properties": {
    "addr:full":"Carrer de Montseny, 15 Barcelona Barcelona 08012",
    "addr:housenumber":"15",
    "addr:postcode":"08012",
    "addr:street":"Carrer De Montseny",
    "iso:country":"ES",
    "sg:address":"Carrer de Montseny, 15",
    "sg:city":"Barcelona",
    "sg:orig_category":"Reparaci\u00d3n Y Restauraci\u00d3n De Objetos Diversos",
    "sg:phone":"+34 932 18 05 09",
    "sg:postcode":"08012",
    "sg:province":"Barcelona",
    "wof:name":"Mendez Revuelto Oscar",
    "wof:placetype":"venue"
},
  "geometry": {"coordinates":[2.1545660496,41.4019088745],"type":"Point"}
}