{
  "type": "Feature",
  "properties": {
    "addr:full":"Calle de Robledo, 23 Pola De Lena Asturias 33630",
    "addr:housenumber":"23",
    "addr:postcode":"33630",
    "addr:street":"Calle De Robledo",
    "iso:country":"ES",
    "sg:address":"Calle de Robledo, 23",
    "sg:city":"Pola De Lena",
    "sg:orig_category":"Venta, Instalaci\u00d3n De Cocinas",
    "sg:phone":"+34 985 49 39 14",
    "sg:postcode":"33630",
    "sg:province":"Asturias",
    "wof:name":"Kintaca\u00f1ada C.b.",
    "wof:placetype":"venue"
},
  "geometry": {"coordinates":[-5.8269290924,43.1535987854],"type":"Point"}
}