{
  "type": "Feature",
  "properties": {
    "addr:full":"S. Y Leche, S/n Campohermoso Almer\u00eda 04110",
    "addr:housenumber":"s",
    "addr:postcode":"04110",
    "addr:street":"/ N Campohermoso Almeri\u0301A",
    "iso:country":"ES",
    "sg:address":"S. Y Leche, S/n",
    "sg:city":"Campohermoso",
    "sg:orig_category":"Flores Y Plantas Naturales (al Por Mayor)",
    "sg:phone":"+34 950 16 52 21",
    "sg:postcode":"04110",
    "sg:province":"Almer\u00eda",
    "wof:name":"Agro Organics S.c.a.",
    "wof:placetype":"venue"
},
  "geometry": {"coordinates":[-2.132749,36.937721],"type":"Point"}
}