{
  "type": "Feature",
  "properties": {
    "addr:full":"Calle de Miguel Moreno Masson, 8 Malaga M\u00e1laga 29007",
    "addr:housenumber":"8",
    "addr:postcode":"29007",
    "addr:street":"Calle De Miguel Moreno Masson;Ma\u0301Laga",
    "iso:country":"ES",
    "sg:address":"Calle de Miguel Moreno Masson, 8",
    "sg:city":"Malaga",
    "sg:orig_category":"Arreglo, Reparaci\u00d3n, Piezas Sueltas De Televisi\u00d3n, V\u00cddeo, Hi",
    "sg:phone":"+34 952 32 81 80",
    "sg:postcode":"29007",
    "sg:province":"M\u00e1laga",
    "wof:name":"Gonzalez Sanchez Maria Isabel",
    "wof:placetype":"venue"
},
  "geometry": {"coordinates":[-4.4424438477,36.7155075073],"type":"Point"}
}