{
  "type": "Feature",
  "properties": {
    "addr:full":"Av Carrilet, 217 Hospitalet Llobregat Barcelona 08907",
    "addr:housenumber":"217",
    "addr:postcode":"08907",
    "addr:street":"Av Carrilet",
    "iso:country":"ES",
    "sg:address":"Av Carrilet, 217",
    "sg:city":"Hospitalet Llobregat",
    "sg:orig_category":"Cristaler\u00cda Art\u00cdstica, Vidrio Soplado (fabricaci\u00d3n, Al Por Mayor)",
    "sg:phone":"+34 932 60 28 28",
    "sg:postcode":"08907",
    "sg:province":"Barcelona",
    "wof:name":"Vidrios Navas S.l.",
    "wof:placetype":"venue"
},
  "geometry": {"coordinates":[2.1026198864,41.3577919006],"type":"Point"}
}