{
  "type": "Feature",
  "properties": {
    "addr:full":"Carrer de Gremi De Boneters, S/n Poligon Industrial De Son Castello Islas Baleares 07009",
    "addr:housenumber":"s / n",
    "addr:postcode":"07009",
    "addr:street":"Carrer De Gremi De Boneters;Islas",
    "iso:country":"ES",
    "sg:address":"Carrer de Gremi De Boneters, S/n",
    "sg:city":"Poligon Industrial De Son Castello",
    "sg:orig_category":"Galvanizaci\u00d3n, Esta\u00d1ado, Emplomado",
    "sg:phone":"+34 971 43 04 06",
    "sg:postcode":"07009",
    "sg:province":"Islas Baleares",
    "wof:name":"Galvanitzats Illes S.l.",
    "wof:placetype":"venue"
},
  "geometry": {"coordinates":[2.6776249409,39.6072845459],"type":"Point"}
}