{
  "type": "Feature",
  "properties": {
    "iso:country":"ES",
    "sg:address":"Calle de Corredera, 97",
    "sg:city":"Alia",
    "sg:orig_category":"Empresas De Carpinter\u00cda De Madera",
    "sg:phone":"+34 927 36 61 60",
    "sg:postcode":"10137",
    "sg:province":"C\u00e1ceres",
    "wof:name":"Carpinteria Hermanos Lopez C.b.",
    "wof:placetype":"venue"
},
  "geometry": {"coordinates":[-5.2185487747,39.4472694397],"type":"Point"}
}