{
  "type": "Feature",
  "properties": {
    "iso:country":"ES",
    "sg:address":"Calle de Sagitario, 8",
    "sg:city":"Zaragoza",
    "sg:orig_category":"Escayola Y Productos De Escayola (fabricaci\u00d3n, Al Por Mayor)",
    "sg:phone":"+34 976 75 82 67",
    "sg:postcode":"50012",
    "sg:province":"Zaragoza",
    "wof:name":"Soto Tallada Yolanda",
    "wof:placetype":"venue"
},
  "geometry": {"coordinates":[-0.9263918996,41.6355171204],"type":"Point"}
}