{
  "type": "Feature",
  "properties": {
    "iso:country":"ES",
    "sg:address":"Seminari, 18",
    "sg:city":"Ciutadella Menorca",
    "sg:orig_category":"Caf\u00c9s, Bares, Cervecer\u00cdas",
    "sg:phone":"+34 971 38 15 08",
    "sg:postcode":"07760",
    "sg:province":"Islas Baleares",
    "wof:name":"Cafeteria Es Rodol C.b.",
    "wof:placetype":"venue"
},
  "geometry": {"coordinates":[3.8386130333,40.001449585],"type":"Point"}
}