{
  "type": "Feature",
  "properties": {
    "addr:full":"Ctra. Tarragona-san Sebastian, Km. 0152,0 Barbastro Huesca 22300",
    "addr:postcode":"22300",
    "addr:street":"Ctra. Tarragona-San Sebastian Km. 0152,0",
    "iso:country":"ES",
    "sg:address":"Ctra. Tarragona-san Sebastian, Km. 0152,0",
    "sg:city":"Barbastro",
    "sg:orig_category":"Asesor\u00cda Para La Organizaci\u00d3n Y Gesti\u00d3n Del Transporte",
    "sg:phone":"+34 974 31 05 30",
    "sg:postcode":"22300",
    "sg:province":"Huesca",
    "wof:name":"Transportes Aragon S. A.",
    "wof:placetype":"venue"
},
  "geometry": {"coordinates":[0.1047969982,42.0337791443],"type":"Point"}
}