{
  "type": "Feature",
  "properties": {
    "iso:country":"ES",
    "sg:address":"Carr Caritat, 4",
    "sg:city":"Felanitx",
    "sg:orig_category":"Electrodom\u00c9sticos (al Por Menor)",
    "sg:phone":"+34 971 58 34 59",
    "sg:postcode":"07200",
    "sg:province":"Islas Baleares",
    "wof:name":"Ca'n Caveia S.l.",
    "wof:placetype":"venue"
},
  "geometry": {"coordinates":[3.1490340233,39.46849823],"type":"Point"}
}