{
  "type": "Feature",
  "properties": {
    "iso:country":"ES",
    "sg:address":"Rbla Principal, 28",
    "sg:city":"Vilanova I La Geltru",
    "sg:orig_category":"Perfumer\u00cda, Art\u00cdculos De Ba\u00d1o (fabricaci\u00d3n, Al Por Mayor)",
    "sg:phone":"+34 938 93 02 24",
    "sg:postcode":"08800",
    "sg:province":"Barcelona",
    "wof:name":"Lopez Robleda Emilio",
    "wof:placetype":"venue"
},
  "geometry": {"coordinates":[1.7243959904,41.2246284485],"type":"Point"}
}