{
  "type": "Feature",
  "properties": {
    "iso:country":"ES",
    "sg:address":"Calle de Regato Del Anis, 10",
    "sg:city":"Salamanca",
    "sg:orig_category":"Electricidad: Instaladores",
    "sg:phone":"+34 923 23 34 54",
    "sg:postcode":"37006",
    "sg:province":"Salamanca",
    "wof:name":"Electricidad Sanper S.l.",
    "wof:placetype":"venue"
},
  "geometry": {"coordinates":[-5.6683387756,40.9746932983],"type":"Point"}
}