{
  "type": "Feature",
  "properties": {
    "addr:full":"Calle de Mayor, 49 Salvatierra O Agurain \u00c1lava 01200",
    "addr:housenumber":"49",
    "addr:postcode":"01200",
    "addr:street":"Calle De Mayor;A\u0301Lava",
    "iso:country":"ES",
    "sg:address":"Calle de Mayor, 49",
    "sg:city":"Salvatierra O Agurain",
    "sg:orig_category":"Peluqueros: De Se\u00d1oras",
    "sg:phone":"+34 945 31 20 89",
    "sg:postcode":"01200",
    "sg:province":"\u00c1lava",
    "wof:name":"Lopez De Munain Erro Laura",
    "wof:placetype":"venue"
},
  "geometry": {"coordinates":[-2.39001894,42.8541908264],"type":"Point"}
}