{
  "type": "Feature",
  "properties": {
    "iso:country":"ES",
    "sg:address":"Calle de Mayor, 21",
    "sg:city":"Cari\u00f1ena",
    "sg:orig_category":"Alimentaci\u00d3n General (al Por Menor)",
    "sg:phone":"+34 976 62 03 35",
    "sg:postcode":"50400",
    "sg:province":"Zaragoza",
    "wof:name":"Gil Jimeno Mariano",
    "wof:placetype":"venue"
},
  "geometry": {"coordinates":[-1.2240959406,41.3362197876],"type":"Point"}
}