{
  "type": "Feature",
  "properties": {
    "iso:country":"ES",
    "sg:address":"Rond Llevant, 16",
    "sg:city":"Argentona",
    "sg:orig_category":"Empresas De Carpinter\u00cda",
    "sg:phone":"+34 937 56 12 42",
    "sg:postcode":"08310",
    "sg:province":"Barcelona",
    "wof:name":"Ruiz Maurin Jose",
    "wof:placetype":"venue"
},
  "geometry": {"coordinates":[2.4036650658,41.5564155579],"type":"Point"}
}