{
  "type": "Feature",
  "properties": {
    "iso:country":"ES",
    "sg:address":"Riells, 60",
    "sg:city":"Escala",
    "sg:orig_category":"Art\u00cdculos De Regalo (al Por Menor)",
    "sg:phone":"+34 972 77 34 03",
    "sg:postcode":"17130",
    "sg:province":"Girona",
    "wof:name":"Paulovic  Melanie",
    "wof:placetype":"venue"
},
  "geometry": {"coordinates":[3.1390259266,42.114906311],"type":"Point"}
}