{
  "type": "Feature",
  "properties": {
    "addr:full":"Avda Blas Infante, 25 Viso Del Alcor Sevilla 41520",
    "addr:housenumber":"25",
    "addr:postcode":"41520",
    "addr:street":"Avda Blas Infante",
    "iso:country":"ES",
    "sg:address":"Avda Blas Infante, 25",
    "sg:city":"Viso Del Alcor",
    "sg:orig_category":"Ense\u00d1anza Secundaria: Colegios Y Escuelas Privadas",
    "sg:phone":"+34 955 94 54 68",
    "sg:postcode":"41520",
    "sg:province":"Sevilla",
    "wof:name":"Junta De Andalucia",
    "wof:placetype":"venue"
},
  "geometry": {"coordinates":[-5.7260980606,37.3903121948],"type":"Point"}
}