{
  "type": "Feature",
  "properties": {
    "iso:country":"ES",
    "sg:address":"Calle de San Anton, 11",
    "sg:city":"Granada",
    "sg:orig_category":"Farmacias",
    "sg:phone":"+34 958 52 32 90",
    "sg:postcode":"18005",
    "sg:province":"Granada",
    "wof:name":"Rodriguez Pinto Mercedes",
    "wof:placetype":"venue"
},
  "geometry": {"coordinates":[-3.5999269485,37.1727371216],"type":"Point"}
}