{
  "type": "Feature",
  "properties": {
    "addr:full":"Carrer de Clos De Sant Francesc, 25 Barcelona Barcelona 08034",
    "addr:housenumber":"25",
    "addr:postcode":"08034",
    "addr:street":"Carrer De Clos De Sant Francesc",
    "iso:country":"ES",
    "sg:address":"Carrer de Clos De Sant Francesc, 25",
    "sg:city":"Barcelona",
    "sg:orig_category":"Productos Qu\u00cdmicos (fabricaci\u00d3n, Al Por Mayor)",
    "sg:phone":"+34 932 03 13 91",
    "sg:postcode":"08034",
    "sg:province":"Barcelona",
    "wof:name":"Laboratorios Espinos Y Bofill S. A.",
    "wof:placetype":"venue"
},
  "geometry": {"coordinates":[2.12114501,41.3985977173],"type":"Point"}
}