{
  "type": "Feature",
  "properties": {
    "addr:full":"Ctra Llerena-utrera, S/n Mairena Alcor Sevilla 41510",
    "addr:housenumber":"s / n",
    "addr:postcode":"41510",
    "addr:street":"Ctra Llerena-Utrera",
    "iso:country":"ES",
    "sg:address":"Ctra Llerena-utrera, S/n",
    "sg:city":"Mairena Alcor",
    "sg:orig_category":"Agentes, Concesionarios Y Sucursales De Camiones Y Veh\u00cdculos Industriales",
    "sg:phone":"+34 955 74 62 13",
    "sg:postcode":"41510",
    "sg:province":"Sevilla",
    "wof:name":"Ramon Vera E Hijos S.l.",
    "wof:placetype":"venue"
},
  "geometry": {"coordinates":[-5.7439141273,37.377117157],"type":"Point"}
}