{
  "type": "Feature",
  "properties": {
    "iso:country":"ES",
    "sg:address":"Carrer de Ventura Gassol, 6",
    "sg:city":"S. Boi Llobregat",
    "sg:orig_category":"\u00d3ptica: Instrumentos (fabricaci\u00d3n)",
    "sg:phone":"+34 936 30 04 14",
    "sg:postcode":"08830",
    "sg:province":"Barcelona",
    "wof:name":"Hispaoptik S.l.",
    "wof:placetype":"venue"
},
  "geometry": {"coordinates":[2.0314769745,41.3568344116],"type":"Point"}
}