{
  "type": "Feature",
  "properties": {
    "iso:country":"ES",
    "sg:address":"Avda Pais Valencia (del), 68",
    "sg:city":"Onda",
    "sg:orig_category":"Peluqueros: De Se\u00d1oras",
    "sg:phone":"+34 964 60 08 76",
    "sg:postcode":"12200",
    "sg:province":"Castell\u00f3n",
    "wof:name":"Aguilella Badenes Maria Dolores",
    "wof:placetype":"venue"
},
  "geometry": {"coordinates":[-0.2627610862,39.9651832581],"type":"Point"}
}