{
  "type": "Feature",
  "properties": {
    "iso:country":"ES",
    "sg:address":"Barr Txiriboketa, S/n",
    "sg:city":"Txiriboketa",
    "sg:orig_category":"Maquinaria Para Industrias Diversas",
    "sg:phone":"+34 946 31 40 02",
    "sg:postcode":"48330",
    "sg:province":"Vizcaya",
    "sg:website":"www.ipsing.com",
    "wof:name":"Ingenieria Poliuretano Flexible S.l.",
    "wof:placetype":"venue"
},
  "geometry": {"coordinates":[-2.7691090107,43.2078361511],"type":"Point"}
}