{
  "type": "Feature",
  "properties": {
    "addr:full":"Avda Republica De Nicaragua, 63 Viso Del Alcor Sevilla 41520",
    "addr:housenumber":"63",
    "addr:postcode":"41520",
    "addr:street":"Avda Republica De Nicaragua",
    "iso:country":"ES",
    "sg:address":"Avda Republica De Nicaragua, 63",
    "sg:city":"Viso Del Alcor",
    "sg:orig_category":"Producci\u00d3n De Abonos Y De Fertilizantes",
    "sg:phone":"+34 955 74 09 31",
    "sg:postcode":"41520",
    "sg:province":"Sevilla",
    "wof:name":"Gabriel Avila S.l.",
    "wof:placetype":"venue"
},
  "geometry": {"coordinates":[-5.7280621529,37.3824920654],"type":"Point"}
}