{
  "type": "Feature",
  "properties": {
    "addr:full":"Ctra Barcelona, 158 Barbera Valles Barcelona 08210",
    "addr:housenumber":"158",
    "addr:postcode":"08210",
    "addr:street":"Ctra Barcelona",
    "iso:country":"ES",
    "sg:address":"Ctra Barcelona, 158",
    "sg:city":"Barbera Valles",
    "sg:orig_category":"Garajes De Veh\u00cdculos",
    "sg:phone":"+34 937 18 89 11",
    "sg:postcode":"08210",
    "sg:province":"Barcelona",
    "wof:name":"Sanchez Pamplona Equipos Para Automocion S.l.",
    "wof:placetype":"venue"
},
  "geometry": {"coordinates":[2.1273679733,41.5154037476],"type":"Point"}
}