{
  "type": "Feature",
  "properties": {
    "iso:country":"ES",
    "sg:address":"Rua Joaquin Loriga, 11",
    "sg:city":"Lalin",
    "sg:orig_category":"Bancos",
    "sg:phone":"+34 986 78 00 78",
    "sg:postcode":"36500",
    "sg:province":"Pontevedra",
    "wof:name":"Banco Espa\u00f1ol De Credito S.a.",
    "wof:placetype":"venue"
},
  "geometry": {"coordinates":[-8.1124219894,42.660320282],"type":"Point"}
}