{
  "type": "Feature",
  "properties": {
    "addr:full":"Calle de Pepe Corzo, 2 Alcala Guadaira Sevilla 41500",
    "addr:housenumber":"2",
    "addr:postcode":"41500",
    "addr:street":"Calle De Pepe Corzo",
    "iso:country":"ES",
    "sg:address":"Calle de Pepe Corzo, 2",
    "sg:city":"Alcala Guadaira",
    "sg:orig_category":"Arquitectos",
    "sg:phone":"+34 955 68 56 40",
    "sg:postcode":"41500",
    "sg:province":"Sevilla",
    "wof:name":"Floridobono Arquitectos S.l. En Constitucion",
    "wof:placetype":"venue"
},
  "geometry": {"coordinates":[-5.8398590088,37.3383140564],"type":"Point"}
}