{
  "type": "Feature",
  "properties": {
    "addr:full":"Calle de Tudela, 27 Alfaro La Rioja 26540",
    "addr:housenumber":"27",
    "addr:postcode":"26540",
    "addr:street":"Calle De Tudela;Rioja",
    "iso:country":"ES",
    "sg:address":"Calle de Tudela, 27",
    "sg:city":"Alfaro",
    "sg:classifiers":[
        {
            "category":"Communications",
            "type":"Services"
        }
    ],
    "sg:phone":"+34 941 18 38 88",
    "sg:postcode":"26540",
    "sg:province":"La Rioja",
    "sg:tags":[
        "televisiones",
        "y",
        "radio"
    ],
    "wof:name":"Radio Rioja S.a.",
    "wof:placetype":"venue"
},
  "geometry": {"coordinates":[-1.7502100468,42.1751174927],"type":"Point"}
}