{
  "type": "Feature",
  "properties": {
    "iso:country":"ES",
    "sg:address":"Calle de Pozas (las), 29",
    "sg:city":"Alfaro",
    "sg:orig_category":"Ingenier\u00cda, Centros De Estudios (diversos)",
    "sg:phone":"+34 941 18 03 17",
    "sg:postcode":"26540",
    "sg:province":"La Rioja",
    "wof:name":"Martinez Balmaseda Fernando",
    "wof:placetype":"venue"
},
  "geometry": {"coordinates":[-1.7509109974,42.178981781],"type":"Point"}
}