{
  "type": "Feature",
  "properties": {
    "iso:country":"ES",
    "sg:address":"Poli Industrial Ibarria, S/n",
    "sg:city":"Alsasua",
    "sg:orig_category":"Comercio, Reparaci\u00d3n De Bicicletas, De Motocicletas, De Accesorios",
    "sg:phone":"+34 948 46 82 80",
    "sg:postcode":"31800",
    "sg:province":"Navarra",
    "wof:name":"Letona Juarez Juan Carlos",
    "wof:placetype":"venue"
},
  "geometry": {"coordinates":[-2.1696588993,42.8959083557],"type":"Point"}
}