{
  "type": "Feature",
  "properties": {
    "addr:full":"Avda Campoamor, 9 Salamanca Salamanca 37003",
    "addr:housenumber":"9",
    "addr:postcode":"37003",
    "addr:street":"Avda Campoamor",
    "iso:country":"ES",
    "sg:address":"Avda Campoamor, 9",
    "sg:city":"Salamanca",
    "sg:orig_category":"Transportes Por Carretera: Lotes Completos, Mercanc\u00cdas Diversas",
    "sg:phone":"+34 923 22 68 25",
    "sg:postcode":"37003",
    "sg:province":"Salamanca",
    "wof:name":"Diaz Sebastian Manuel",
    "wof:placetype":"venue"
},
  "geometry": {"coordinates":[-5.655629158,40.9661445618],"type":"Point"}
}