{
  "type": "Feature",
  "properties": {
    "iso:country":"ES",
    "sg:address":"Plaz Arguelles, 2",
    "sg:city":"Cadiz",
    "sg:orig_category":"Asociaciones, Organismos Culturales Y Socioeducativos",
    "sg:phone":"+34 956 22 06 28",
    "sg:postcode":"11004",
    "sg:province":"C\u00e1diz",
    "wof:name":"Ayuntamiento De Cadiz",
    "wof:placetype":"venue"
},
  "geometry": {"coordinates":[-6.2946996689,36.5338935852],"type":"Point"}
}