{
  "type": "Feature",
  "properties": {
    "addr:full":"Calle de Neptuno, 25 Pozuelo De Alarcon Madrid 28224",
    "addr:housenumber":"25",
    "addr:postcode":"28224",
    "addr:street":"Calle De Neptuno",
    "iso:country":"ES",
    "sg:address":"Calle de Neptuno, 25",
    "sg:city":"Pozuelo De Alarcon",
    "sg:orig_category":"Ense\u00d1anza, Formaci\u00d3n Profesional: Aprendizaje",
    "sg:phone":"+34 917 15 21 69",
    "sg:postcode":"28224",
    "sg:province":"Madrid",
    "wof:name":"Instituto Tecnologico Del Hogar S.l.",
    "wof:placetype":"venue"
},
  "geometry": {"coordinates":[-3.7930629253,40.4443321228],"type":"Point"}
}