{
  "type": "Feature",
  "properties": {
    "addr:full":"Calle de Leandro De Saralegui, 1 Valencia Valencia 46021",
    "addr:housenumber":"1",
    "addr:postcode":"46021",
    "addr:street":"Calle De Leandro De Saralegui",
    "iso:country":"ES",
    "sg:address":"Calle de Leandro De Saralegui, 1",
    "sg:city":"Valencia",
    "sg:orig_category":"Farmacias",
    "sg:phone":"+34 963 62 14 88",
    "sg:postcode":"46021",
    "sg:province":"Valencia",
    "wof:name":"Navarro Perez Maria Magdalena",
    "wof:placetype":"venue"
},
  "geometry": {"coordinates":[-0.3486109972,39.4754676819],"type":"Point"}
}