{
  "type": "Feature",
  "properties": {
    "addr:full":"Plaz Aguado, 2 Langreo Asturias 33900",
    "addr:housenumber":"2",
    "addr:postcode":"33900",
    "addr:street":"Plaz Aguado",
    "iso:country":"ES",
    "sg:address":"Plaz Aguado, 2",
    "sg:city":"Langreo",
    "sg:orig_category":"Quincaller\u00cda (al Por Menor)",
    "sg:phone":"+34 985 69 69 97",
    "sg:postcode":"33900",
    "sg:province":"Asturias",
    "wof:name":"Fernandez Ordo\u00f1ez Jose German",
    "wof:placetype":"venue"
},
  "geometry": {"coordinates":[-5.684191227,43.2963066101],"type":"Point"}
}