{
  "type": "Feature",
  "properties": {
    "iso:country":"ES",
    "sg:address":"Carrer de Pintor Pahissa, 8",
    "sg:city":"Barcelona",
    "sg:orig_category":"Arquitectos",
    "sg:phone":"+34 934 40 62 81",
    "sg:postcode":"08028",
    "sg:province":"Barcelona",
    "wof:name":"Barba Carbonell Josep Maria",
    "wof:placetype":"venue"
},
  "geometry": {"coordinates":[2.1232039928,41.378364563],"type":"Point"}
}