{
  "type": "Feature",
  "properties": {
    "iso:country":"ES",
    "sg:address":"C\u00d1ad De La Vizana, 90",
    "sg:city":"Benavente",
    "sg:orig_category":"Molduras, Junquillos, Listones Y Molduras Perforadas",
    "sg:phone":"+34 980 63 64 21",
    "sg:postcode":"49600",
    "sg:province":"Zamora",
    "wof:name":"Alfayete Alvarez Roberto",
    "wof:placetype":"venue"
},
  "geometry": {"coordinates":[-5.6773509979,42.0072517395],"type":"Point"}
}