{
  "type": "Feature",
  "properties": {
    "addr:full":"Calle de Rio Aranda, 11 Calatayud Zaragoza 50300",
    "addr:housenumber":"11",
    "addr:postcode":"50300",
    "addr:street":"Calle De Rio Aranda",
    "iso:country":"ES",
    "sg:address":"Calle de Rio Aranda, 11",
    "sg:city":"Calatayud",
    "sg:orig_category":"M\u00c9dicos: Ginecolog\u00cda Y Obstetricia",
    "sg:phone":"+34 976 88 07 87",
    "sg:postcode":"50300",
    "sg:province":"Zaragoza",
    "wof:name":"Alcober Perez Jose Luis",
    "wof:placetype":"venue"
},
  "geometry": {"coordinates":[-1.6360038519,41.355796814],"type":"Point"}
}