{
  "type": "Feature",
  "properties": {
    "iso:country":"ES",
    "sg:address":"Calle de Palo, 3",
    "sg:city":"Madridejos",
    "sg:orig_category":"Asociaciones Humanitarias, De Cooperaci\u00d3n, De Acci\u00d3n Social",
    "sg:phone":"+34 925 46 07 84",
    "sg:postcode":"45710",
    "sg:province":"Toledo",
    "wof:name":"Asoc.de Ayuda Y Prevencio De Drogodependecias",
    "wof:placetype":"venue"
},
  "geometry": {"coordinates":[-3.5344445705,39.4705467224],"type":"Point"}
}