{
  "type": "Feature",
  "properties": {
    "iso:country":"ES",
    "sg:address":"Calle de Isla De Alboran, 1",
    "sg:city":"Pozuelo De Alarcon",
    "sg:orig_category":"Promotores Constructores",
    "sg:phone":"+34 917 15 52 76",
    "sg:postcode":"28223",
    "sg:province":"Madrid",
    "wof:name":"Gallego Garcia Angel",
    "wof:placetype":"venue"
},
  "geometry": {"coordinates":[-3.8158249855,40.4436073303],"type":"Point"}
}