{
  "type": "Feature",
  "properties": {
    "addr:full":"Molino, 35 Lebrija Sevilla 41740",
    "addr:housenumber":"35",
    "addr:postcode":"41740",
    "addr:street":"Molino",
    "iso:country":"ES",
    "sg:address":"Molino, 35",
    "sg:city":"Lebrija",
    "sg:orig_category":"Electricidad: Instaladores",
    "sg:phone":"+34 955 97 04 58",
    "sg:postcode":"41740",
    "sg:province":"Sevilla",
    "wof:name":"Fernandez Garcia Antonio",
    "wof:placetype":"venue"
},
  "geometry": {"coordinates":[-6.0744361877,36.9211997986],"type":"Point"}
}