{
  "type": "Feature",
  "properties": {
    "addr:full":"Luga Horno (el), 28 Horno Las Palmas 35140",
    "addr:postcode":"35140",
    "iso:country":"ES",
    "sg:address":"Luga Horno (el), 28",
    "sg:city":"Horno",
    "sg:orig_category":"Alimentaci\u00d3n General (al Por Menor)",
    "sg:phone":"+34 928 15 91 73",
    "sg:postcode":"35140",
    "sg:province":"Las Palmas",
    "wof:name":"Baez Zerpa Isaac",
    "wof:placetype":"venue"
},
  "geometry": {"coordinates":[-15.7237386703,27.8846378326],"type":"Point"}
}