{
  "type": "Feature",
  "properties": {
    "addr:full":"Calle de Max Garcia Soriano, 33 Elda Alicante 03600",
    "addr:housenumber":"33",
    "addr:postcode":"03600",
    "addr:street":"Calle De Max Garcia Soriano",
    "iso:country":"ES",
    "sg:address":"Calle de Max Garcia Soriano, 33",
    "sg:city":"Elda",
    "sg:orig_category":"T\u00c9cnicos Veterinarios",
    "sg:phone":"+34 966 98 20 90",
    "sg:postcode":"03600",
    "sg:province":"Alicante",
    "wof:name":"Perez Ycardo Maricruz",
    "wof:placetype":"venue"
},
  "geometry": {"coordinates":[-0.7870150208,38.4749145508],"type":"Point"}
}