{
  "type": "Feature",
  "properties": {
    "iso:country":"ES",
    "sg:address":"Calle de Cuartel, 5",
    "sg:city":"Fuenlabrada",
    "sg:orig_category":"Centros Comerciales Y Grandes Tiendas",
    "sg:phone":"+34 916 15 64 61",
    "sg:postcode":"28944",
    "sg:province":"Madrid",
    "wof:name":"Jiang  Qingxin",
    "wof:placetype":"venue"
},
  "geometry": {"coordinates":[-3.7953178883,40.2837333679],"type":"Point"}
}