{
  "type": "Feature",
  "properties": {
    "iso:country":"ES",
    "sg:address":"Calle de Calvo Sotelo, 26",
    "sg:city":"Villatoro",
    "sg:orig_category":"Farmacias",
    "sg:phone":"+34 920 23 01 45",
    "sg:postcode":"05560",
    "sg:province":"\u00c1vila",
    "wof:name":"Fadrique Jimenez Silvia",
    "wof:placetype":"venue"
},
  "geometry": {"coordinates":[-5.112241745,40.5552482605],"type":"Point"}
}