{
  "type": "Feature",
  "properties": {
    "addr:full":"Avda America, 22 Estrada Pontevedra 36680",
    "addr:housenumber":"22",
    "addr:postcode":"36680",
    "addr:street":"Avda America;Estrada Pontevedra",
    "iso:country":"ES",
    "sg:address":"Avda America, 22",
    "sg:city":"Estrada",
    "sg:orig_category":"Muebles Y Accesorios Para Cocinas Y Cuartos De Ba\u00d1o (al Por Menor)",
    "sg:phone":"+34 986 57 27 01",
    "sg:postcode":"36680",
    "sg:province":"Pontevedra",
    "wof:name":"Prado Renda Fabrica De Muebles S.l.",
    "wof:placetype":"venue"
},
  "geometry": {"coordinates":[-8.4910736084,42.6887664795],"type":"Point"}
}