{
  "type": "Feature",
  "properties": {
    "iso:country":"ES",
    "sg:address":"Pl Karl Marx, 1",
    "sg:city":"Barcelona",
    "sg:orig_category":"Ense\u00d1anza, Formaci\u00d3n Profesional: Aprendizaje",
    "sg:phone":"+34 934 28 39 53",
    "sg:postcode":"08035",
    "sg:province":"Barcelona",
    "sg:website":"www.sabater-tobella.com",
    "wof:name":"Laboratorio Stauros S. L.",
    "wof:placetype":"venue"
},
  "geometry": {"coordinates":[2.1616001129,41.4404411316],"type":"Point"}
}