{
  "type": "Feature",
  "properties": {
    "iso:country":"ES",
    "sg:address":"Calle de Alfonso Xiii, 18",
    "sg:city":"S. Nicolas Tolentino",
    "sg:orig_category":"Molduras, Junquillos, Listones Y Molduras Perforadas",
    "sg:phone":"+34 928 89 06 74",
    "sg:postcode":"35470",
    "sg:province":"Las Palmas",
    "wof:name":"Diaz Diaz Francisco",
    "wof:placetype":"venue"
},
  "geometry": {"coordinates":[-15.7824430466,27.9859638214],"type":"Point"}
}