{
  "type": "Feature",
  "properties": {
    "iso:country":"ES",
    "sg:address":"Avda San Blas, 4",
    "sg:city":"Legutiano",
    "sg:orig_category":"Revisi\u00d3n, Reconstrucci\u00d3n De M\u00c1quinas Y Herramientas",
    "sg:phone":"+34 945 46 60 13",
    "sg:postcode":"01170",
    "sg:province":"\u00c1lava",
    "sg:website":"www.leanmachinery.com",
    "wof:name":"Lean Machinery S.l.",
    "wof:placetype":"venue"
},
  "geometry": {"coordinates":[-2.678935051,42.9762420654],"type":"Point"}
}