{
  "type": "Feature",
  "properties": {
    "addr:full":"Carrer de Cardenal Casa\u00d1as, 5 Barcelona Barcelona 08002",
    "addr:housenumber":"5",
    "addr:postcode":"08002",
    "addr:street":"Carrer De Cardenal Casan\u0303As",
    "iso:country":"ES",
    "sg:address":"Carrer de Cardenal Casa\u00d1as, 5",
    "sg:city":"Barcelona",
    "sg:orig_category":"Librer\u00cdas",
    "sg:phone":"+34 933 17 85 92",
    "sg:postcode":"08002",
    "sg:province":"Barcelona",
    "wof:name":"Marti Guadall Maria Montserrat",
    "wof:placetype":"venue"
},
  "geometry": {"coordinates":[2.1732170582,41.3816642761],"type":"Point"}
}