{
  "type": "Feature",
  "properties": {
    "addr:full":"Calle de Mesones, 30 Burgo M\u00e1laga 29420",
    "addr:housenumber":"30",
    "addr:postcode":"29420",
    "addr:street":"Calle De Mesones;Ma\u0301Laga",
    "iso:country":"ES",
    "sg:address":"Calle de Mesones, 30",
    "sg:city":"Burgo",
    "sg:orig_category":"Iglesia Cat\u00d3lica",
    "sg:phone":"+34 952 16 01 57",
    "sg:postcode":"29420",
    "sg:province":"M\u00e1laga",
    "wof:name":"Obispado De Malaga",
    "wof:placetype":"venue"
},
  "geometry": {"coordinates":[-4.9465742111,36.7892990112],"type":"Point"}
}