{
  "type": "Feature",
  "properties": {
    "addr:full":"Calle de Hermano Antonio, S/n Nava Rey Valladolid 47500",
    "addr:housenumber":"s / n",
    "addr:postcode":"47500",
    "addr:street":"Calle De Hermano Antonio",
    "iso:country":"ES",
    "sg:address":"Calle de Hermano Antonio, S/n",
    "sg:city":"Nava Rey",
    "sg:orig_category":"Bebidas",
    "sg:phone":"+34 983 85 07 95",
    "sg:postcode":"47500",
    "sg:province":"Valladolid",
    "wof:name":"Distribuciones Lasaosa C.b",
    "wof:placetype":"venue"
},
  "geometry": {"coordinates":[-5.0790138245,41.3352050781],"type":"Point"}
}