{
  "type": "Feature",
  "properties": {
    "addr:full":"Avda Gaspar Aguilar, 66 Valencia Valencia 46017",
    "addr:housenumber":"66",
    "addr:postcode":"46017",
    "addr:street":"Avda Gaspar Aguilar",
    "iso:country":"ES",
    "sg:address":"Avda Gaspar Aguilar, 66",
    "sg:city":"Valencia",
    "sg:orig_category":"Molduras, Junquillos, Listones Y Molduras Perforadas",
    "sg:phone":"+34 963 77 50 34",
    "sg:postcode":"46017",
    "sg:province":"Valencia",
    "wof:name":"Bermejo Vega Javier",
    "wof:placetype":"venue"
},
  "geometry": {"coordinates":[-0.3916890025,39.4546852112],"type":"Point"}
}