{
  "type": "Feature",
  "properties": {
    "addr:full":"Calle de Santa Adela, S/n Pedro-martinez Granada 18530",
    "addr:housenumber":"s",
    "addr:postcode":"18530",
    "addr:street":"Calle De Santa Adela;/ N Pedro-Martinez",
    "iso:country":"ES",
    "sg:address":"Calle de Santa Adela, S/n",
    "sg:city":"Pedro-martinez",
    "sg:orig_category":"Alimentaci\u00d3n General (al Por Mayor)",
    "sg:phone":"+34 958 68 70 06",
    "sg:postcode":"18530",
    "sg:province":"Granada",
    "wof:name":"Navarro Martinez Victoriano",
    "wof:placetype":"venue"
},
  "geometry": {"coordinates":[-3.2291340828,37.4996948242],"type":"Point"}
}