{
  "type": "Feature",
  "properties": {
    "iso:country":"ES",
    "sg:address":"Calle de Patron, 2",
    "sg:city":"Playa Honda",
    "sg:orig_category":"Importaci\u00d3n",
    "sg:phone":"+34 928 82 13 47",
    "sg:postcode":"35509",
    "sg:province":"Las Palmas",
    "wof:name":"Lanza Zulle S.l.",
    "wof:placetype":"venue"
},
  "geometry": {"coordinates":[-13.5852594376,28.955745697],"type":"Point"}
}