{
  "type": "Feature",
  "properties": {
    "addr:full":"Calle de Maldonado, 17 Barrios C\u00e1diz 11370",
    "addr:housenumber":"17",
    "addr:postcode":"11370",
    "addr:street":"Calle De Maldonado;Ca\u0301Diz",
    "iso:country":"ES",
    "sg:address":"Calle de Maldonado, 17",
    "sg:city":"Barrios",
    "sg:orig_category":"Contenedores (mercanc\u00cdas)",
    "sg:phone":"+34 956 62 00 74",
    "sg:postcode":"11370",
    "sg:province":"C\u00e1diz",
    "wof:name":"Martinez Santos Ana Maria",
    "wof:placetype":"venue"
},
  "geometry": {"coordinates":[-5.4914932251,36.1835441589],"type":"Point"}
}