{
  "type": "Feature",
  "properties": {
    "addr:full":"Afores, S/n Alfarras Lleida 25120",
    "addr:housenumber":"s / n",
    "addr:postcode":"25120",
    "addr:street":"Afores",
    "iso:country":"ES",
    "sg:address":"Afores, S/n",
    "sg:city":"Alfarras",
    "sg:orig_category":"Aguas (distribuci\u00d3n, Servicios)",
    "sg:phone":"+34 973 76 05 61",
    "sg:postcode":"25120",
    "sg:province":"Lleida",
    "wof:name":"Sociedad Regional De Abastecimientos De Aguas, S.a.",
    "wof:placetype":"venue"
},
  "geometry": {"coordinates":[0.5686320066,41.8303451538],"type":"Point"}
}