{
  "type": "Feature",
  "properties": {
    "addr:full":"Avgd Europa, 13 Villarreal Castell\u00f3n 12540",
    "addr:housenumber":"13",
    "addr:postcode":"12540",
    "addr:street":"Europa",
    "iso:country":"ES",
    "sg:address":"Avgd Europa, 13",
    "sg:city":"Villarreal",
    "sg:orig_category":"Cer\u00c1mica Art\u00cdstica Y Decorativa",
    "sg:phone":"+34 964 53 69 45",
    "sg:postcode":"12540",
    "sg:province":"Castell\u00f3n",
    "wof:name":"Listelos Ceramicos De Vila-real S.l.",
    "wof:placetype":"venue"
},
  "geometry": {"coordinates":[-0.0952939987,39.9453048706],"type":"Point"}
}