{
  "type": "Feature",
  "properties": {
    "addr:full":"Calle de Concepcion, 8 Villarrubia De Los Ojos Ciudad Real 13670",
    "addr:housenumber":"8",
    "addr:postcode":"13670",
    "addr:street":"Calle De Concepcion",
    "iso:country":"ES",
    "sg:address":"Calle de Concepcion, 8",
    "sg:city":"Villarrubia De Los Ojos",
    "sg:orig_category":"Muebles Y Accesorios Para Cocinas Y Cuartos De Ba\u00d1o (al Por Menor)",
    "sg:phone":"+34 926 89 72 59",
    "sg:postcode":"13670",
    "sg:province":"Ciudad Real",
    "wof:name":"Camacho Ramirez De Arellano Agustin",
    "wof:placetype":"venue"
},
  "geometry": {"coordinates":[-3.6064200401,39.2172889709],"type":"Point"}
}