{
  "type": "Feature",
  "properties": {
    "addr:full":"Carrer de Sant Vicen\u00c7 Ferrer, 10 Palma Islas Baleares 07008",
    "addr:housenumber":"10",
    "addr:postcode":"07008",
    "addr:street":"Carrer De Sant Vicenc\u0327 Ferrer",
    "iso:country":"ES",
    "sg:address":"Carrer de Sant Vicen\u00c7 Ferrer, 10",
    "sg:city":"Palma",
    "sg:orig_category":"Mec\u00c1nico Del Autom\u00d3vil",
    "sg:phone":"+34 971 27 48 39",
    "sg:postcode":"07008",
    "sg:province":"Islas Baleares",
    "wof:name":"Mesquida Marti Catalina",
    "wof:placetype":"venue"
},
  "geometry": {"coordinates":[2.6708168983,39.5750312805],"type":"Point"}
}