{
  "type": "Feature",
  "properties": {
    "addr:full":"Calle de Paz De La, 27 Aviles Asturias 33402",
    "addr:housenumber":"27",
    "addr:postcode":"33402",
    "addr:street":"Calle De Paz De La",
    "iso:country":"ES",
    "sg:address":"Calle de Paz De La, 27",
    "sg:city":"Aviles",
    "sg:orig_category":"Mercer\u00cda, Lencer\u00cda (al Por Menor)",
    "sg:phone":"+34 985 51 10 95",
    "sg:postcode":"33402",
    "sg:province":"Asturias",
    "wof:name":"Martin Martin Domingo",
    "wof:placetype":"venue"
},
  "geometry": {"coordinates":[-5.9263877869,43.534324646],"type":"Point"}
}