{
  "type": "Feature",
  "properties": {
    "iso:country":"ES",
    "sg:address":"Av Costa I Llobera, De, 34",
    "sg:city":"Arta",
    "sg:orig_category":"Plomeros",
    "sg:phone":"+34 971 83 67 10",
    "sg:postcode":"07570",
    "sg:province":"Islas Baleares",
    "wof:name":"Instalaciones Mascaro,s.l.",
    "wof:placetype":"venue"
},
  "geometry": {"coordinates":[3.3547599316,39.69140625],"type":"Point"}
}