{
  "type": "Feature",
  "properties": {
    "addr:full":"Avda Ollerias (de Las), 30 Cordoba C\u00f3rdoba 14001",
    "addr:housenumber":"30",
    "addr:postcode":"14001",
    "addr:street":"Avda Ollerias De Las;Co\u0301Rdoba",
    "iso:country":"ES",
    "sg:address":"Avda Ollerias (de Las), 30",
    "sg:city":"Cordoba",
    "sg:orig_category":"Carnicer\u00cdas, Carnicer\u00cdas",
    "sg:phone":"+34 957 48 01 27",
    "sg:postcode":"14001",
    "sg:province":"C\u00f3rdoba",
    "wof:name":"Cuevas Flores Jose Luis",
    "wof:placetype":"venue"
},
  "geometry": {"coordinates":[-4.7738409042,37.8917388916],"type":"Point"}
}