{
  "type": "Feature",
  "properties": {
    "addr:full":"Poli Poligono Industrial 5, 22 Collado Villalba Madrid 28400",
    "addr:housenumber":"5 22",
    "addr:postcode":"28400",
    "addr:street":"Poligono Industrial",
    "iso:country":"ES",
    "sg:address":"Poli Poligono Industrial 5, 22",
    "sg:city":"Collado Villalba",
    "sg:orig_category":"Mec\u00c1nico Del Autom\u00d3vil",
    "sg:phone":"+34 918 50 22 88",
    "sg:postcode":"28400",
    "sg:province":"Madrid",
    "wof:name":"Talleres Angel Morales S.l.",
    "wof:placetype":"venue"
},
  "geometry": {"coordinates":[-4.0048007965,40.6373901367],"type":"Point"}
}