{
  "type": "Feature",
  "properties": {
    "addr:full":"Calle de Huerta, 22 Sangonera La Verde O Ermita Nueva Murcia 30833",
    "addr:housenumber":"22",
    "addr:postcode":"30833",
    "addr:street":"Calle De Huerta",
    "iso:country":"ES",
    "sg:address":"Calle de Huerta, 22",
    "sg:city":"Sangonera La Verde O Ermita Nueva",
    "sg:orig_category":"Fabricaci\u00d3n, Instalaci\u00d3n Y Reparaci\u00d3n De Bombas",
    "sg:phone":"+34 968 86 95 14",
    "sg:postcode":"30833",
    "sg:province":"Murcia",
    "wof:name":"Pellicer Y Fuentes S.l.",
    "wof:placetype":"venue"
},
  "geometry": {"coordinates":[-1.2069989443,37.9333190918],"type":"Point"}
}