{
  "type": "Feature",
  "properties": {
    "addr:full":"Rbla Pau, 33 Vilanova I La Geltru Barcelona 08800",
    "addr:housenumber":"33",
    "addr:postcode":"08800",
    "addr:street":"Rbla Pau",
    "iso:country":"ES",
    "sg:address":"Rbla Pau, 33",
    "sg:city":"Vilanova I La Geltru",
    "sg:orig_category":"Cer\u00c1micas: Material Y Suministros",
    "sg:phone":"+34 938 15 87 43",
    "sg:postcode":"08800",
    "sg:province":"Barcelona",
    "wof:name":"Darebany S.l.",
    "wof:placetype":"venue"
},
  "geometry": {"coordinates":[1.7272599936,41.2202453613],"type":"Point"}
}