{
  "type": "Feature",
  "properties": {
    "addr:full":"Calle de Senda Del Infante, 14 Madrid Madrid 28035",
    "addr:housenumber":"14",
    "addr:postcode":"madrid;28035",
    "addr:street":"Calle De Senda Del Infante",
    "iso:country":"ES",
    "sg:address":"Calle de Senda Del Infante, 14",
    "sg:city":"Madrid",
    "sg:orig_category":"Caf\u00c9s, Bares, Cervecer\u00cdas",
    "sg:phone":"+34 913 76 30 02",
    "sg:postcode":"28035",
    "sg:province":"Madrid",
    "wof:name":"Pasiones Del Infante S.l.",
    "wof:placetype":"venue"
},
  "geometry": {"coordinates":[-3.722673893,40.4913406372],"type":"Point"}
}