{
  "type": "Feature",
  "properties": {
    "addr:full":"Calle de Alfonso De Cordoba, 8 Valencia Valencia 46010",
    "addr:housenumber":"8",
    "addr:postcode":"46010",
    "addr:street":"Calle De Alfonso De Cordoba",
    "iso:country":"ES",
    "sg:address":"Calle de Alfonso De Cordoba, 8",
    "sg:city":"Valencia",
    "sg:orig_category":"Arquitectos",
    "sg:phone":"+34 963 94 13 63",
    "sg:postcode":"46010",
    "sg:province":"Valencia",
    "wof:name":"Landar Paisaje Y Arquitectura S.l.",
    "wof:placetype":"venue"
},
  "geometry": {"coordinates":[-0.3592297137,39.4763526917],"type":"Point"}
}