{
  "type": "Feature",
  "properties": {
    "addr:full":"Calle de Gil De Santiva\u00d1es, 6 Madrid Madrid 28001",
    "addr:housenumber":"6",
    "addr:postcode":"28001",
    "addr:street":"Calle De Gil De Santivan\u0303Es",
    "iso:country":"ES",
    "sg:address":"Calle de Gil De Santiva\u00d1es, 6",
    "sg:city":"Madrid",
    "sg:orig_category":"\u00d3ptica: Instrumentos (fabricaci\u00d3n)",
    "sg:phone":"+34 915 76 76 34",
    "sg:postcode":"28001",
    "sg:province":"Madrid",
    "wof:name":"Jimenez-diaz Jorrin Ana Maria",
    "wof:placetype":"venue"
},
  "geometry": {"coordinates":[-3.689002037,40.4221763611],"type":"Point"}
}