{
  "type": "Feature",
  "properties": {
    "addr:full":"Rio, S/n Vegas Coria C\u00e1ceres 10623",
    "addr:housenumber":"/ n",
    "addr:postcode":"10623",
    "addr:street":"Rio S",
    "iso:country":"ES",
    "sg:address":"Rio, S/n",
    "sg:city":"Vegas Coria",
    "sg:orig_category":"Carnicer\u00cdas, Carnicer\u00cdas",
    "sg:phone":"+34 927 43 40 76",
    "sg:postcode":"10623",
    "sg:province":"C\u00e1ceres",
    "wof:name":"Hnos Dominguez C.b",
    "wof:placetype":"venue"
},
  "geometry": {"coordinates":[-6.165222168,40.3793907166],"type":"Point"}
}