{
  "type": "Feature",
  "properties": {
    "addr:full":"Carr Miguel De Cervantes, 35 Palamos Girona 17230",
    "addr:housenumber":"35",
    "addr:postcode":"17230",
    "addr:street":"Carr Miguel De Cervantes",
    "iso:country":"ES",
    "sg:address":"Carr Miguel De Cervantes, 35",
    "sg:city":"Palamos",
    "sg:orig_category":"Zapatos (al Por Menor)",
    "sg:phone":"+34 972 31 64 31",
    "sg:postcode":"17230",
    "sg:province":"Girona",
    "wof:name":"Coll Noguer Neus",
    "wof:placetype":"venue"
},
  "geometry": {"coordinates":[3.1293649673,41.8485832214],"type":"Point"}
}