{
  "type": "Feature",
  "properties": {
    "addr:full":"Calle de Ramon Y Cajal, 44 Archena Murcia 30600",
    "addr:housenumber":"44",
    "addr:postcode":"30600",
    "addr:street":"Calle De Ramon Y Cajal",
    "iso:country":"ES",
    "sg:address":"Calle de Ramon Y Cajal, 44",
    "sg:city":"Archena",
    "sg:orig_category":"Ropa Para Ni\u00d1os (al Por Menor)",
    "sg:phone":"+34 968 67 27 65",
    "sg:postcode":"30600",
    "sg:province":"Murcia",
    "wof:name":"Brox Moratalla Ines",
    "wof:placetype":"venue"
},
  "geometry": {"coordinates":[-1.29944098,38.1148643494],"type":"Point"}
}