{
  "type": "Feature",
  "properties": {
    "iso:country":"ES",
    "sg:address":"Calle de General Santiago (del), 4",
    "sg:city":"Segovia",
    "sg:orig_category":"Inmobiliaria (agencias)",
    "sg:phone":"+34 921 42 14 79",
    "sg:postcode":"40005",
    "sg:province":"Segovia",
    "wof:name":"Aprovechamientos Forestales S.l.",
    "wof:placetype":"venue"
},
  "geometry": {"coordinates":[-4.1131329536,40.9416465759],"type":"Point"}
}