{
  "type": "Feature",
  "properties": {
    "iso:country":"ES",
    "sg:address":"C/ Doctor Ferran, 41",
    "sg:city":"Salt",
    "sg:orig_category":"Farmacias",
    "sg:phone":"+34 972 23 01 03",
    "sg:postcode":"17190",
    "sg:province":"Girona",
    "wof:name":"Escatllar Sagrera Josefa",
    "wof:placetype":"venue"
},
  "geometry": {"coordinates":[2.7923600674,41.9727516174],"type":"Point"}
}