{
  "type": "Feature",
  "properties": {
    "addr:full":"Calle de Tomas Salvador, S/n Villada Palencia 34340",
    "addr:housenumber":"s / n",
    "addr:postcode":"34340",
    "addr:street":"Calle De Tomas Salvador",
    "iso:country":"ES",
    "sg:address":"Calle de Tomas Salvador, S/n",
    "sg:city":"Villada",
    "sg:orig_category":"Mec\u00c1nico Del Autom\u00d3vil",
    "sg:phone":"+34 979 84 70 53",
    "sg:postcode":"34340",
    "sg:province":"Palencia",
    "wof:name":"Calle Crespo Francisco Javier",
    "wof:placetype":"venue"
},
  "geometry": {"coordinates":[-4.9694070816,42.2526550293],"type":"Point"}
}