{
  "type": "Feature",
  "properties": {
    "addr:full":"Calle de Jacobo Rodriguez Pereira, 1 Badajoz Badajoz 06010",
    "addr:housenumber":"1",
    "addr:postcode":"06010",
    "addr:street":"Calle De Jacobo Rodriguez Pereira",
    "iso:country":"ES",
    "sg:address":"Calle de Jacobo Rodriguez Pereira, 1",
    "sg:city":"Badajoz",
    "sg:orig_category":"Bisuter\u00cda, Joyer\u00cda, Relojer\u00cda (al Por Menor)",
    "sg:phone":"+34 924 26 14 10",
    "sg:postcode":"06010",
    "sg:province":"Badajoz",
    "wof:name":"Pinilla Marcelo Vicente",
    "wof:placetype":"venue"
},
  "geometry": {"coordinates":[-6.9788947105,38.8694839478],"type":"Point"}
}