{
  "type": "Feature",
  "properties": {
    "addr:full":"Carrer de Velazquez, 86 Terrassa Barcelona 08224",
    "addr:housenumber":"86",
    "addr:postcode":"08224",
    "addr:street":"Carrer De Velazquez",
    "iso:country":"ES",
    "sg:address":"Carrer de Velazquez, 86",
    "sg:city":"Terrassa",
    "sg:orig_category":"Chapister\u00cda",
    "sg:phone":"+34 937 80 15 96",
    "sg:postcode":"08224",
    "sg:province":"Barcelona",
    "wof:name":"Nieto Luque Jordi",
    "wof:placetype":"venue"
},
  "geometry": {"coordinates":[1.9945299625,41.560131073],"type":"Point"}
}