{
  "type": "Feature",
  "properties": {
    "iso:country":"ES",
    "sg:address":"Calle de Azafran, S/n",
    "sg:city":"Carmona",
    "sg:orig_category":"Asociaciones Y Clubs Deportivos",
    "sg:phone":"+34 954 19 62 56",
    "sg:postcode":"41410",
    "sg:province":"Sevilla",
    "wof:name":"Inture Pazos Carmona U.t.e.",
    "wof:placetype":"venue"
},
  "geometry": {"coordinates":[-5.652305603,37.4745788574],"type":"Point"}
}