{
  "type": "Feature",
  "properties": {
    "iso:country":"ES",
    "sg:address":"Calle de San Juan De La Cruz, 2",
    "sg:city":"Zaragoza",
    "sg:orig_category":"Cervecer\u00cdas",
    "sg:phone":"+34 976 55 66 80",
    "sg:postcode":"50006",
    "sg:province":"Zaragoza",
    "wof:name":"Telefonos Publicos De Aragon S.l.",
    "wof:placetype":"venue"
},
  "geometry": {"coordinates":[-0.8937404752,41.6417770386],"type":"Point"}
}