{
  "type": "Feature",
  "properties": {
    "iso:country":"ES",
    "sg:address":"Avda Burjasot, 261",
    "sg:city":"Valencia",
    "sg:orig_category":"Chapister\u00cda",
    "sg:phone":"+34 963 40 39 65",
    "sg:postcode":"46015",
    "sg:province":"Valencia",
    "wof:name":"Delgado Jimenez Jose",
    "wof:placetype":"venue"
},
  "geometry": {"coordinates":[-0.3968549967,39.4956016541],"type":"Point"}
}