{
  "type": "Feature",
  "properties": {
    "addr:full":"Calle de Rio Alberche, 62 Poligono Sta M. De Benquerencia Toledo 45007",
    "addr:housenumber":"62 poligono",
    "addr:postcode":"45007",
    "addr:street":"Calle De Rio Alberche;Sta M. De Benquerencia",
    "iso:country":"ES",
    "sg:address":"Calle de Rio Alberche, 62",
    "sg:city":"Poligono Sta M. De Benquerencia",
    "sg:orig_category":"Abogados",
    "sg:phone":"+34 925 23 32 42",
    "sg:postcode":"45007",
    "sg:province":"Toledo",
    "wof:name":"Real Gayo Alberto",
    "wof:placetype":"venue"
},
  "geometry": {"coordinates":[-3.9432630539,39.8681640625],"type":"Point"}
}