{
  "type": "Feature",
  "properties": {
    "iso:country":"ES",
    "sg:address":"Avgd Ausias March, 45",
    "sg:city":"Burjassot",
    "sg:orig_category":"Muebles, Minoristas",
    "sg:phone":"+34 963 63 76 93",
    "sg:postcode":"46100",
    "sg:province":"Valencia",
    "sg:website":"www.andreuworld.com",
    "wof:name":"Nu\u00f1ez Collado Juan Jose",
    "wof:placetype":"venue"
},
  "geometry": {"coordinates":[-0.4109590054,39.5136184692],"type":"Point"}
}