{
  "type": "Feature",
  "properties": {
    "addr:full":"Rua Torrente (de), 92 Santiago De Compostela La Coru\u00f1a 15899",
    "addr:housenumber":"92",
    "addr:postcode":"15899",
    "addr:street":"Rua Torrente De;Corun\u0303A",
    "iso:country":"ES",
    "sg:address":"Rua Torrente (de), 92",
    "sg:city":"Santiago De Compostela",
    "sg:orig_category":"Chapister\u00cda",
    "sg:phone":"+34 981 52 12 53",
    "sg:postcode":"15899",
    "sg:province":"La Coru\u00f1a",
    "wof:name":"Castro Vazquez Constantino",
    "wof:placetype":"venue"
},
  "geometry": {"coordinates":[-8.5657291412,42.8607406616],"type":"Point"}
}