{
  "type": "Feature",
  "properties": {
    "iso:country":"ES",
    "sg:address":"Calle de Valle De Aran, 20",
    "sg:city":"Valladolid",
    "sg:orig_category":"Ebanister\u00cda",
    "sg:phone":"+34 983 25 07 17",
    "sg:postcode":"47010",
    "sg:province":"Valladolid",
    "wof:name":"Yenes Martinez Pedro",
    "wof:placetype":"venue"
},
  "geometry": {"coordinates":[-4.7158946991,41.6673431396],"type":"Point"}
}