{
  "type": "Feature",
  "properties": {
    "iso:country":"ES",
    "sg:address":"Carrer de Bonavista, 64",
    "sg:city":"S. Just Desvern",
    "sg:orig_category":"Asesor\u00cda Sobre Comunicaci\u00d3n De Empresas",
    "sg:phone":"+34 933 71 13 13",
    "sg:postcode":"08960",
    "sg:province":"Barcelona",
    "wof:name":"Asesoria Internacional Aluminio Sl",
    "wof:placetype":"venue"
},
  "geometry": {"coordinates":[2.0773043633,41.3832740784],"type":"Point"}
}