{
  "type": "Feature",
  "properties": {
    "addr:full":"Avda Mariana Pineda, S/n Guadix Granada 18500",
    "addr:housenumber":"s",
    "addr:postcode":"18500",
    "addr:street":"Avda Mariana Pineda;/ N",
    "iso:country":"ES",
    "sg:address":"Avda Mariana Pineda, S/n",
    "sg:city":"Guadix",
    "sg:orig_category":"Ambulancias",
    "sg:phone":"+34 958 66 47 44",
    "sg:postcode":"18500",
    "sg:province":"Granada",
    "wof:name":"Consocio De Transportes Sanitario De Granada Aie",
    "wof:placetype":"venue"
},
  "geometry": {"coordinates":[-3.1395690441,37.3033981323],"type":"Point"}
}