{
  "type": "Feature",
  "properties": {
    "addr:full":"Bard Unceta Parroco, 18 Bilbao Vizcaya 48004",
    "addr:housenumber":"18",
    "addr:postcode":"48004",
    "addr:street":"Unceta Parroco",
    "iso:country":"ES",
    "sg:address":"Bard Unceta Parroco, 18",
    "sg:city":"Bilbao",
    "sg:orig_category":"Electromec\u00c1nica",
    "sg:phone":"+34 944 05 84 51",
    "sg:postcode":"48004",
    "sg:province":"Vizcaya",
    "wof:name":"Electromecanica Etorki, C.b",
    "wof:placetype":"venue"
},
  "geometry": {"coordinates":[-2.9146258831,43.2506561279],"type":"Point"}
}