{
  "type": "Feature",
  "properties": {
    "iso:country":"ES",
    "sg:address":"Calle de Juntas Generales, 49",
    "sg:city":"Vitoria-gasteiz",
    "sg:classifiers":[
        {
            "category":"Personal",
            "subcategory":"Barber",
            "type":"Services"
        }
    ],
    "sg:phone":"+34 945 26 95 69",
    "sg:postcode":"01010",
    "sg:province":"\u00c1lava",
    "sg:tags":[
        "caballeros",
        "de",
        "peluqueros"
    ],
    "wof:name":"Pardo Flores Francisco",
    "wof:placetype":"venue"
},
  "geometry": {"coordinates":[-2.6789190769,42.8655700684],"type":"Point"}
}