{
  "type": "Feature",
  "properties": {
    "iso:country":"ES",
    "sg:address":"San Franzisko Kalea, 22",
    "sg:city":"Elgoibar",
    "sg:orig_category":"Asociaciones, Organismos Culturales Y Socioeducativos",
    "sg:phone":"+34 943 74 01 99",
    "sg:postcode":"20870",
    "sg:province":"Guip\u00f9zcoa",
    "wof:name":"Sociedad Atletica Egotoki",
    "wof:placetype":"venue"
},
  "geometry": {"coordinates":[-2.4140729904,43.2154312134],"type":"Point"}
}