{
  "type": "Feature",
  "properties": {
    "iso:country":"ES",
    "sg:address":"Carrer de Rossello (de), 20",
    "sg:city":"Tortosa",
    "sg:orig_category":"Telas Y Sedas (al Por Menor)",
    "sg:phone":"+34 977 44 93 75",
    "sg:postcode":"43500",
    "sg:province":"Tarragona",
    "wof:name":"Tejidos El Pilar S.a.",
    "wof:placetype":"venue"
},
  "geometry": {"coordinates":[0.5185559988,40.8066978455],"type":"Point"}
}