{
  "type": "Feature",
  "properties": {
    "addr:full":"Calle de Republica Checa, 8 Madrid Madrid 28032",
    "addr:housenumber":"8",
    "addr:postcode":"madrid;28032",
    "addr:street":"Calle De Republica Checa",
    "iso:country":"ES",
    "sg:address":"Calle de Republica Checa, 8",
    "sg:city":"Madrid",
    "sg:orig_category":"Inmobiliaria (agencias)",
    "sg:phone":"+34 913 13 52 04",
    "sg:postcode":"28032",
    "sg:province":"Madrid",
    "wof:name":"Zona Inmobiliaria Las Rosas S.l.",
    "wof:placetype":"venue"
},
  "geometry": {"coordinates":[-3.6159880161,40.4199867249],"type":"Point"}
}