{
  "type": "Feature",
  "properties": {
    "addr:full":"Plaz San Andres, 3 Berlanga Duero Soria 42360",
    "addr:housenumber":"3",
    "addr:postcode":"42360",
    "addr:street":"Plaz San Andres",
    "iso:country":"ES",
    "sg:address":"Plaz San Andres, 3",
    "sg:city":"Berlanga Duero",
    "sg:orig_category":"Molduras, Junquillos, Listones Y Molduras Perforadas",
    "sg:phone":"+34 975 34 30 27",
    "sg:postcode":"42360",
    "sg:province":"Soria",
    "wof:name":"Francisco Javier Rello Gamarra C.b.",
    "wof:placetype":"venue"
},
  "geometry": {"coordinates":[-2.8622839451,41.4676399231],"type":"Point"}
}