{
  "type": "Feature",
  "properties": {
    "addr:full":"Calle de Torres Quevedo, 10 Ponferrada Le\u00f3n 24400",
    "addr:housenumber":"10",
    "addr:postcode":"24400",
    "addr:street":"Calle De Torres Quevedo",
    "iso:country":"ES",
    "sg:address":"Calle de Torres Quevedo, 10",
    "sg:city":"Ponferrada",
    "sg:orig_category":"Arreglo, Reparaci\u00d3n, Piezas Sueltas De Televisi\u00d3n, V\u00cddeo, Hi",
    "sg:phone":"+34 987 41 46 23",
    "sg:postcode":"24400",
    "sg:province":"Le\u00f3n",
    "wof:name":"Marques Fernandez Adolfo",
    "wof:placetype":"venue"
},
  "geometry": {"coordinates":[-6.6014280319,42.5507545471],"type":"Point"}
}