{
  "type": "Feature",
  "properties": {
    "addr:full":"Calle de Calderon De La Barca, 3 Navatejera Le\u00f3n 24008",
    "addr:housenumber":"3",
    "addr:postcode":"24008",
    "addr:street":"Calle De Calderon De La Barca;Leo\u0301N",
    "iso:country":"ES",
    "sg:address":"Calle de Calderon De La Barca, 3",
    "sg:city":"Navatejera",
    "sg:orig_category":"Centros De Coordinaci\u00d3n",
    "sg:phone":"+34 987 28 66 75",
    "sg:postcode":"24008",
    "sg:province":"Le\u00f3n",
    "wof:name":"Garcia Velado Javier",
    "wof:placetype":"venue"
},
  "geometry": {"coordinates":[-5.5751976967,42.6106529236],"type":"Point"}
}