{
  "type": "Feature",
  "properties": {
    "addr:full":"Avda Alicante, 74 Villena Alicante 03400",
    "addr:housenumber":"74",
    "addr:postcode":"03400",
    "addr:street":"Avda Alicante",
    "iso:country":"ES",
    "sg:address":"Avda Alicante, 74",
    "sg:city":"Villena",
    "sg:orig_category":"Confecci\u00d3n De Zapatos",
    "sg:phone":"+34 965 80 43 51",
    "sg:postcode":"03400",
    "sg:province":"Alicante",
    "wof:name":"Gimenez Ruiz Pascual",
    "wof:placetype":"venue"
},
  "geometry": {"coordinates":[-0.8550390005,38.6288490295],"type":"Point"}
}