{
  "type": "Feature",
  "properties": {
    "iso:country":"ES",
    "sg:address":"Pla, 48",
    "sg:city":"Javea",
    "sg:orig_category":"Cr\u00cda De Animales",
    "sg:phone":"+34 965 77 02 21",
    "sg:postcode":"03730",
    "sg:province":"Alicante",
    "wof:name":"C.h. Merk C.b.",
    "wof:placetype":"venue"
},
  "geometry": {"coordinates":[0.172973007,38.7885856628],"type":"Point"}
}