{
  "type": "Feature",
  "properties": {
    "iso:country":"ES",
    "sg:address":"Calle de Lago Carucedo (del), S/n",
    "sg:city":"Fuenlabrada",
    "sg:orig_category":"Centros Empresariales",
    "sg:phone":"+34 916 21 45 81",
    "sg:postcode":"28947",
    "sg:province":"Madrid",
    "wof:name":"Recursos En El Punto De Venta S.l.",
    "wof:placetype":"venue"
},
  "geometry": {"coordinates":[-3.7407329082,40.2652893066],"type":"Point"}
}