{
  "type": "Feature",
  "properties": {
    "addr:full":"Fuente Del Perro, 38 Alhaurin Grande M\u00e1laga 29120",
    "addr:housenumber":"38",
    "addr:postcode":"29120",
    "addr:street":"Alhaurin",
    "iso:country":"ES",
    "sg:address":"Fuente Del Perro, 38",
    "sg:city":"Alhaurin Grande",
    "sg:orig_category":"Promotores Constructores",
    "sg:phone":"+34 952 49 16 64",
    "sg:postcode":"29120",
    "sg:province":"M\u00e1laga",
    "sg:website":"www.jycf.com",
    "wof:name":"Jose Y Carlos Fernandez S.l.l.",
    "wof:placetype":"venue"
},
  "geometry": {"coordinates":[-4.6911292076,36.6420783997],"type":"Point"}
}