{
  "type": "Feature",
  "properties": {
    "iso:country":"ES",
    "sg:address":"Antziola Auzoa, 5",
    "sg:city":"Hernani",
    "sg:orig_category":"Pescader\u00cdas (al Por Menor)",
    "sg:phone":"+34 943 33 03 65",
    "sg:postcode":"20120",
    "sg:province":"Guip\u00f9zcoa",
    "wof:name":"Aramburu Etxezarreta Maria Encarnacion",
    "wof:placetype":"venue"
},
  "geometry": {"coordinates":[-1.9752477407,43.2694206238],"type":"Point"}
}