{
  "type": "Feature",
  "properties": {
    "iso:country":"ES",
    "sg:address":"Calle de Manuel Casana, 15",
    "sg:city":"Sevilla",
    "sg:orig_category":"Abogados",
    "sg:phone":"+34 954 65 53 24",
    "sg:postcode":"41005",
    "sg:province":"Sevilla",
    "wof:name":"Lobo Cantos Maria Del Carmen",
    "wof:placetype":"venue"
},
  "geometry": {"coordinates":[-5.9701590538,37.3815994263],"type":"Point"}
}