{
  "type": "Feature",
  "properties": {
    "addr:full":"Avda Guadalajara, 35 Madrid Madrid 28032",
    "addr:housenumber":"35",
    "addr:postcode":"madrid;28032",
    "addr:street":"Avda Guadalajara",
    "iso:country":"ES",
    "sg:address":"Avda Guadalajara, 35",
    "sg:city":"Madrid",
    "sg:orig_category":"Electrodom\u00c9sticos (al Por Menor)",
    "sg:phone":"+34 913 06 72 16",
    "sg:postcode":"28032",
    "sg:province":"Madrid",
    "wof:name":"Electrodomesticos Las Rosas De San Blas S.l.",
    "wof:placetype":"venue"
},
  "geometry": {"coordinates":[-3.6202509403,40.4196014404],"type":"Point"}
}