{
  "type": "Feature",
  "properties": {
    "addr:full":"Carrer de Josep Guardiet, 3 Sabadell Barcelona 08204",
    "addr:housenumber":"3",
    "addr:postcode":"08204",
    "addr:street":"Carrer De Josep Guardiet",
    "iso:country":"ES",
    "sg:address":"Carrer de Josep Guardiet, 3",
    "sg:city":"Sabadell",
    "sg:orig_category":"Molduras, Junquillos, Listones Y Molduras Perforadas",
    "sg:phone":"+34 937 10 55 28",
    "sg:postcode":"08204",
    "sg:province":"Barcelona",
    "wof:name":"Fernandez Garcia Salvador",
    "wof:placetype":"venue"
},
  "geometry": {"coordinates":[2.108602047,41.5260047913],"type":"Point"}
}