{
  "type": "Feature",
  "properties": {
    "iso:country":"ES",
    "sg:address":"Carr Mestral, 30",
    "sg:city":"Carlet",
    "sg:orig_category":"Fabricaci\u00d3n De Muebles",
    "sg:phone":"+34 962 53 81 00",
    "sg:postcode":"46240",
    "sg:province":"Valencia",
    "sg:website":"www.alpuch.com",
    "wof:name":"Yns Mon Sociedad De Gestion Y Desarrollo S.l.",
    "wof:placetype":"venue"
},
  "geometry": {"coordinates":[-0.554148972,39.2258453369],"type":"Point"}
}