{
  "type": "Feature",
  "properties": {
    "addr:full":"Calle de Venezuela, 29 Valencia Valencia 46007",
    "addr:housenumber":"29",
    "addr:postcode":"46007",
    "addr:street":"Calle De Venezuela",
    "iso:country":"ES",
    "sg:address":"Calle de Venezuela, 29",
    "sg:city":"Valencia",
    "sg:orig_category":"Cajas De Ahorro",
    "sg:phone":"+34 963 77 24 81",
    "sg:postcode":"46007",
    "sg:province":"Valencia",
    "sg:website":"www.cam.es",
    "wof:name":"Caja De Ahorros Del Mediterraneo",
    "wof:placetype":"venue"
},
  "geometry": {"coordinates":[-0.38736099,39.4551582336],"type":"Point"}
}