{
  "type": "Feature",
  "properties": {
    "iso:country":"ES",
    "sg:address":"Sect Embarcaciones, S/n",
    "sg:city":"Tres Cantos",
    "sg:orig_category":"Centros De Educaci\u00d3n Especial",
    "sg:phone":"+34 918 03 29 57",
    "sg:postcode":"28760",
    "sg:province":"Madrid",
    "wof:name":"Colegio Publico Enrique Tierno Galvan De Tres Cantos Mec",
    "wof:placetype":"venue"
},
  "geometry": {"coordinates":[-3.7038691044,40.5983810425],"type":"Point"}
}