{
  "type": "Feature",
  "properties": {
    "addr:full":"Carrer de Iluro, 32 Mataro Barcelona 08302",
    "addr:housenumber":"32",
    "addr:postcode":"08302",
    "addr:street":"Carrer De Iluro",
    "iso:country":"ES",
    "sg:address":"Carrer de Iluro, 32",
    "sg:city":"Mataro",
    "sg:orig_category":"Fabricaci\u00d3n De Su\u00c9ters Y Chalecos De Punto",
    "sg:phone":"+34 937 57 30 09",
    "sg:postcode":"08302",
    "sg:province":"Barcelona",
    "wof:name":"Perafil S.a.",
    "wof:placetype":"venue"
},
  "geometry": {"coordinates":[2.439344883,41.5369720459],"type":"Point"}
}