{
  "type": "Feature",
  "properties": {
    "addr:full":"Calle de Goirialde, 6 Elexalde Vizcaya 48970",
    "addr:housenumber":"6",
    "addr:postcode":"48970",
    "addr:street":"Calle De Goirialde",
    "iso:country":"ES",
    "sg:address":"Calle de Goirialde, 6",
    "sg:city":"Elexalde",
    "sg:orig_category":"Promotores Constructores",
    "sg:phone":"+34 944 40 14 47",
    "sg:postcode":"48970",
    "sg:province":"Vizcaya",
    "wof:name":"Construcciones Antonio Rodriguez Quintela Sl",
    "wof:placetype":"venue"
},
  "geometry": {"coordinates":[-2.8870439529,43.2375488281],"type":"Point"}
}