{
  "type": "Feature",
  "properties": {
    "iso:country":"ES",
    "sg:address":"Ctra Navalpino, Km. 0003,4",
    "sg:city":"Toledo",
    "sg:orig_category":"Inmobiliaria (agencias)",
    "sg:phone":"+34 925 25 08 75",
    "sg:postcode":"45004",
    "sg:province":"Toledo",
    "wof:name":"Covelca S.a.",
    "wof:placetype":"venue"
},
  "geometry": {"coordinates":[-4.0412340164,39.8600196838],"type":"Point"}
}