{
  "type": "Feature",
  "properties": {
    "iso:country":"ES",
    "sg:address":"Pl. Cde Rodezno, 10",
    "sg:city":"Iru\u00f1a",
    "sg:orig_category":"Ropa Para Se\u00d1oras (al Por Menor)",
    "sg:phone":"+34 948 24 82 57",
    "sg:postcode":"31003",
    "sg:province":"Navarra",
    "wof:name":"Coello Gerediaga Luisa",
    "wof:placetype":"venue"
},
  "geometry": {"coordinates":[-1.6437540054,42.81275177],"type":"Point"}
}