{
  "type": "Feature",
  "properties": {
    "iso:country":"ES",
    "sg:address":"Calle de Conde De Montornes, 6",
    "sg:city":"Valencia",
    "sg:orig_category":"Tapicer\u00cdas",
    "sg:phone":"+34 963 92 30 35",
    "sg:postcode":"46003",
    "sg:province":"Valencia",
    "wof:name":"Tomas Jordan Tomas",
    "wof:placetype":"venue"
},
  "geometry": {"coordinates":[-0.3715629876,39.4738082886],"type":"Point"}
}