{
  "type": "Feature",
  "properties": {
    "addr:full":"Calle de Horno De Abad, 14 Granada Granada 18002",
    "addr:housenumber":"14",
    "addr:postcode":"18002",
    "addr:street":"Calle De Horno De Abad",
    "iso:country":"ES",
    "sg:address":"Calle de Horno De Abad, 14",
    "sg:city":"Granada",
    "sg:orig_category":"Electromedicina: Equipo",
    "sg:phone":"+34 958 28 22 09",
    "sg:postcode":"18002",
    "sg:province":"Granada",
    "wof:name":"Rios Martinez Francisco",
    "wof:placetype":"venue"
},
  "geometry": {"coordinates":[-3.603331089,37.1777229309],"type":"Point"}
}