{
  "type": "Feature",
  "properties": {
    "addr:full":"Plaz Espa\u00d1a (de), 1 Azuqueca Henares Guadalajara 19200",
    "addr:postcode":"19200",
    "addr:street":"Plaz",
    "iso:country":"ES",
    "sg:address":"Plaz Espa\u00d1a (de), 1",
    "sg:city":"Azuqueca Henares",
    "sg:orig_category":"Arquitectos",
    "sg:phone":"+34 949 26 44 11",
    "sg:postcode":"19200",
    "sg:province":"Guadalajara",
    "wof:name":"Gonzalez Quintas Julio",
    "wof:placetype":"venue"
},
  "geometry": {"coordinates":[-3.1664927006,40.6298179626],"type":"Point"}
}