{
  "type": "Feature",
  "properties": {
    "addr:full":"Avda Camilo Alonso Vega, 33 Santander Cantabria 39007",
    "addr:housenumber":"33",
    "addr:postcode":"39007",
    "addr:street":"Avda Camilo Alonso Vega",
    "iso:country":"ES",
    "sg:address":"Avda Camilo Alonso Vega, 33",
    "sg:city":"Santander",
    "sg:orig_category":"Asociaciones Y Clubs Deportivos",
    "sg:phone":"+34 942 33 41 41",
    "sg:postcode":"39007",
    "sg:province":"Cantabria",
    "wof:name":"Agrupacion Deportiva Lasalle",
    "wof:placetype":"venue"
},
  "geometry": {"coordinates":[-3.8240306377,43.4622154236],"type":"Point"}
}