{
  "type": "Feature",
  "properties": {
    "addr:full":"Calle de Pico El, 24 Ribadesella Asturias 33560",
    "addr:postcode":"33560",
    "addr:street":"Calle De Pico",
    "iso:country":"ES",
    "sg:address":"Calle de Pico El, 24",
    "sg:city":"Ribadesella",
    "sg:orig_category":"Restaurantes",
    "sg:phone":"+34 985 86 03 91",
    "sg:postcode":"33560",
    "sg:province":"Asturias",
    "wof:name":"Fernandez Martinez Jose Ramon",
    "wof:placetype":"venue"
},
  "geometry": {"coordinates":[-5.0604438782,43.4609565735],"type":"Point"}
}