{
  "type": "Feature",
  "properties": {
    "iso:country":"ES",
    "sg:address":"Tomas Garbizu Kalea, S/n",
    "sg:city":"Lezo",
    "sg:orig_category":"Ba\u00d1os Y Duchas P\u00dablicos",
    "sg:phone":"+34 943 52 82 44",
    "sg:postcode":"20100",
    "sg:province":"Guip\u00f9zcoa",
    "sg:website":"www.serviocio.es",
    "wof:name":"Serviocio Cultura Deporte Y Recreacion S",
    "wof:placetype":"venue"
},
  "geometry": {"coordinates":[-1.8998379707,43.3171310425],"type":"Point"}
}