{
  "type": "Feature",
  "properties": {
    "iso:country":"ES",
    "sg:address":"Carrer de Llull, 51",
    "sg:city":"Barcelona",
    "sg:orig_category":"Torrefactado De Caf\u00c9",
    "sg:phone":"+34 933 09 62 29",
    "sg:postcode":"08005",
    "sg:province":"Barcelona",
    "wof:name":"Torrelsa Sa",
    "wof:placetype":"venue"
},
  "geometry": {"coordinates":[2.1920471191,41.3937263489],"type":"Point"}
}