{
  "type": "Feature",
  "properties": {
    "iso:country":"ES",
    "sg:address":"Calle de Quinta Avenida, 85",
    "sg:city":"Almeria",
    "sg:orig_category":"Promotores Constructores",
    "sg:phone":"+34 950 14 19 68",
    "sg:postcode":"04008",
    "sg:province":"Almer\u00eda",
    "wof:name":"Freniche Torres;s.l.u.",
    "wof:placetype":"venue"
},
  "geometry": {"coordinates":[-2.4565939903,36.8503875732],"type":"Point"}
}