{
  "type": "Feature",
  "properties": {
    "iso:country":"ES",
    "sg:address":"Avda Andalucia, 19",
    "sg:city":"Lanjaron",
    "sg:orig_category":"Asesor\u00cda Fiscal Y Jur\u00cddica",
    "sg:phone":"+34 958 77 10 26",
    "sg:postcode":"18420",
    "sg:province":"Granada",
    "wof:name":"Cuellar Marcos Rafael",
    "wof:placetype":"venue"
},
  "geometry": {"coordinates":[-3.485033989,36.9184837341],"type":"Point"}
}