{
  "type": "Feature",
  "properties": {
    "addr:full":"Azkarruntz Auzoa, S/n Bergara Guip\u00f9zcoa 20570",
    "addr:housenumber":"s / n",
    "addr:postcode":"20570",
    "addr:street":"Azkarruntz Auzoa;Guipu\u0300Zcoa",
    "iso:country":"ES",
    "sg:address":"Azkarruntz Auzoa, S/n",
    "sg:city":"Bergara",
    "sg:orig_category":"Metalurgia",
    "sg:phone":"+34 943 76 26 43",
    "sg:postcode":"20570",
    "sg:province":"Guip\u00f9zcoa",
    "wof:name":"Trefinor S.l.",
    "wof:placetype":"venue"
},
  "geometry": {"coordinates":[-2.4243841171,43.1055450439],"type":"Point"}
}