{
  "type": "Feature",
  "properties": {
    "iso:country":"ES",
    "sg:address":"Pg Ajuntament, 5",
    "sg:city":"Sta. Oliva",
    "sg:orig_category":"Molduras, Junquillos, Listones Y Molduras Perforadas",
    "sg:phone":"+34 977 67 92 46",
    "sg:postcode":"43710",
    "sg:province":"Tarragona",
    "wof:name":"Las Tablas De Santa Oliva S.l.",
    "wof:placetype":"venue"
},
  "geometry": {"coordinates":[1.5493099689,41.2517204285],"type":"Point"}
}