{
  "type": "Feature",
  "properties": {
    "addr:full":"Calle de Barrio Nuevo, 12 Talavan C\u00e1ceres 10193",
    "addr:housenumber":"12",
    "addr:postcode":"10193",
    "addr:street":"Calle De Barrio Nuevo;Ca\u0301Ceres",
    "iso:country":"ES",
    "sg:address":"Calle de Barrio Nuevo, 12",
    "sg:city":"Talavan",
    "sg:orig_category":"Centros De Reservas Hoteleras",
    "sg:phone":"+34 927 28 53 93",
    "sg:postcode":"10193",
    "sg:province":"C\u00e1ceres",
    "wof:name":"Jimenez Bre\u00f1a Fulgencio",
    "wof:placetype":"venue"
},
  "geometry": {"coordinates":[-6.2810769081,39.7161369324],"type":"Point"}
}