{
  "type": "Feature",
  "properties": {
    "iso:country":"ES",
    "sg:address":"Luga Parque Tecnologico De Boecillo, S/n",
    "sg:city":"Parque Tecnologico De Boecillo",
    "sg:orig_category":"Ingeniero",
    "sg:phone":"+34 983 54 80 63",
    "sg:postcode":"47151",
    "sg:province":"Valladolid",
    "sg:website":"www.axpe.com",
    "wof:name":"Axpe Consulting S.a.",
    "wof:placetype":"venue"
},
  "geometry": {"coordinates":[-4.7162079811,41.5228118896],"type":"Point"}
}