{
  "type": "Feature",
  "properties": {
    "addr:full":"Rua Magallanes, 4 Vigo Pontevedra 36203",
    "addr:housenumber":"4",
    "addr:postcode":"36203",
    "addr:street":"Rua Magallanes",
    "iso:country":"ES",
    "sg:address":"Rua Magallanes, 4",
    "sg:city":"Vigo",
    "sg:orig_category":"Muebles, Minoristas",
    "sg:phone":"+34 986 22 45 97",
    "sg:postcode":"36203",
    "sg:province":"Pontevedra",
    "wof:name":"Comercial Del Mueble Amxo S.l.",
    "wof:placetype":"venue"
},
  "geometry": {"coordinates":[-8.7193584442,42.2349472046],"type":"Point"}
}