{
  "type": "Feature",
  "properties": {
    "iso:country":"ES",
    "sg:address":"Carrer de Aribau, 298",
    "sg:city":"Barcelona",
    "sg:orig_category":"Fisioterapia",
    "sg:phone":"+34 932 02 13 66",
    "sg:postcode":"08006",
    "sg:province":"Barcelona",
    "wof:name":"Centro De Rehabilitacion Y Medicina Fisica Sastre Roca S.l.",
    "wof:placetype":"venue"
},
  "geometry": {"coordinates":[2.1464469433,41.3987998962],"type":"Point"}
}