{
  "type": "Feature",
  "properties": {
    "iso:country":"ES",
    "sg:address":"Avda Arlanzon, 34",
    "sg:city":"Burgos",
    "sg:orig_category":"Locales Y Clases De Danza",
    "sg:phone":"+34 947 20 42 20",
    "sg:postcode":"09004",
    "sg:province":"Burgos",
    "wof:name":"Sainz Anuncibay Celestino",
    "wof:placetype":"venue"
},
  "geometry": {"coordinates":[-3.6896591187,42.3424873352],"type":"Point"}
}