{
  "type": "Feature",
  "properties": {
    "iso:country":"ES",
    "sg:address":"Pase Castellana, 117",
    "sg:city":"Madrid",
    "sg:orig_category":"Ingenier\u00cda, Centros De Estudios (diversos)",
    "sg:phone":"+34 915 98 09 30",
    "sg:postcode":"28046",
    "sg:province":"Madrid",
    "wof:name":"Politecnica De Ingenieria Y Arquitectura S.a.",
    "wof:placetype":"venue"
},
  "geometry": {"coordinates":[-3.6907989979,40.4571075439],"type":"Point"}
}