{
  "type": "Feature",
  "properties": {
    "addr:full":"Calle de General Davila, 11 Madrid Madrid 28003",
    "addr:housenumber":"11",
    "addr:postcode":"madrid;28003",
    "addr:street":"Calle De General Davila",
    "iso:country":"ES",
    "sg:address":"Calle de General Davila, 11",
    "sg:city":"Madrid",
    "sg:orig_category":"Florister\u00cdas",
    "sg:phone":"+34 915 54 81 68",
    "sg:postcode":"28003",
    "sg:province":"Madrid",
    "wof:name":"Mateu Vela Eusebio",
    "wof:placetype":"venue"
},
  "geometry": {"coordinates":[-3.7145750523,40.4436340332],"type":"Point"}
}