{
  "type": "Feature",
  "properties": {
    "addr:full":"Calle de Nueva, 43 Mairena Aljarafe Sevilla 41927",
    "addr:housenumber":"43",
    "addr:postcode":"41927",
    "addr:street":"Calle De Nueva",
    "iso:country":"ES",
    "sg:address":"Calle de Nueva, 43",
    "sg:city":"Mairena Aljarafe",
    "sg:orig_category":"M\u00c9dicos: Medicina Interna",
    "sg:phone":"+34 954 18 23 09",
    "sg:postcode":"41927",
    "sg:province":"Sevilla",
    "wof:name":"Pavon Colchero Andres",
    "wof:placetype":"venue"
},
  "geometry": {"coordinates":[-6.0642800331,37.3447761536],"type":"Point"}
}