{
  "type": "Feature",
  "properties": {
    "iso:country":"ES",
    "sg:address":"Carrer de Rafael Casanovas, 14",
    "sg:city":"Vilanova Cami",
    "sg:orig_category":"Venta, Instalaci\u00d3n, Mantenimiento De Chimeneas De Interior Y Accesorios",
    "sg:phone":"+34 938 03 49 55",
    "sg:postcode":"08788",
    "sg:province":"Barcelona",
    "wof:name":"Cristalleria J.iglesias S.l.",
    "wof:placetype":"venue"
},
  "geometry": {"coordinates":[1.6411030293,41.5720062256],"type":"Point"}
}