{
  "type": "Feature",
  "properties": {
    "iso:country":"ES",
    "sg:address":"Ctra Almoines (d'), 1",
    "sg:city":"Gandia",
    "sg:orig_category":"Promotores Constructores",
    "sg:phone":"+34 962 95 02 69",
    "sg:postcode":"46700",
    "sg:province":"Valencia",
    "wof:name":"Construcciones Salvador Mico S.l.u.",
    "wof:placetype":"venue"
},
  "geometry": {"coordinates":[-0.1770820022,38.9604873657],"type":"Point"}
}