{
  "type": "Feature",
  "properties": {
    "addr:full":"Pg S'abanell, 2 Blanes Girona 17300",
    "addr:housenumber":"2",
    "addr:postcode":"17300",
    "addr:street":"Pg S'Abanell",
    "iso:country":"ES",
    "sg:address":"Pg S'abanell, 2",
    "sg:city":"Blanes",
    "sg:orig_category":"Alquiler De Apartamentos",
    "sg:phone":"+34 972 33 08 06",
    "sg:postcode":"17300",
    "sg:province":"Girona",
    "wof:name":"Bordallo Baltrons Esteban",
    "wof:placetype":"venue"
},
  "geometry": {"coordinates":[2.7825069427,41.6597595215],"type":"Point"}
}