{
  "type": "Feature",
  "properties": {
    "iso:country":"ES",
    "sg:address":"Calle de Feria, 3",
    "sg:city":"Pozoblanco",
    "sg:orig_category":"Tiendas De Grano, Frutas Y Legumbres Secas (al Por Menor)",
    "sg:phone":"+34 957 13 13 67",
    "sg:postcode":"14400",
    "sg:province":"C\u00f3rdoba",
    "wof:name":"Mu\u00f1oz Fernandez Andres",
    "wof:placetype":"venue"
},
  "geometry": {"coordinates":[-4.8473801613,38.3770904541],"type":"Point"}
}