{
  "type": "Feature",
  "properties": {
    "iso:country":"ES",
    "sg:address":"Carrer de Pont Roma, 6",
    "sg:city":"Barqueres",
    "sg:orig_category":"Forjas Y Altos Hornos",
    "sg:phone":"+34 938 67 09 49",
    "sg:postcode":"08460",
    "sg:province":"Barcelona",
    "wof:name":"Puerto Murillo Jesus",
    "wof:placetype":"venue"
},
  "geometry": {"coordinates":[2.4345400333,41.6977996826],"type":"Point"}
}