{
  "type": "Feature",
  "properties": {
    "iso:country":"ES",
    "sg:address":"Carrer de Pelai, 48",
    "sg:city":"Barcelona",
    "sg:orig_category":"Empresarios Y Productoras De Espect\u00c1culos",
    "sg:phone":"+34 933 01 00 28",
    "sg:postcode":"08001",
    "sg:province":"Barcelona",
    "wof:name":"Huyeng  Ingeborg",
    "wof:placetype":"venue"
},
  "geometry": {"coordinates":[2.1685039997,41.3854751587],"type":"Point"}
}