{
  "type": "Feature",
  "properties": {
    "addr:full":"Calle de Pozo Nuevo, 5 Mairena Aljarafe Sevilla 41927",
    "addr:housenumber":"5",
    "addr:postcode":"41927",
    "addr:street":"Calle De Pozo Nuevo",
    "iso:country":"ES",
    "sg:address":"Calle de Pozo Nuevo, 5",
    "sg:city":"Mairena Aljarafe",
    "sg:orig_category":"Arreglo, Reparaci\u00d3n, Piezas Sueltas De Televisi\u00d3n, V\u00cddeo, Hi",
    "sg:phone":"+34 955 60 97 08",
    "sg:postcode":"41927",
    "sg:province":"Sevilla",
    "wof:name":"Television Y Tecnica S.l.",
    "wof:placetype":"venue"
},
  "geometry": {"coordinates":[-6.0660591125,37.3446884155],"type":"Point"}
}