{
  "type": "Feature",
  "properties": {
    "iso:country":"ES",
    "sg:address":"Plaz Mancha (la), 23",
    "sg:city":"Mahora",
    "sg:orig_category":"Cajas De Ahorro",
    "sg:phone":"+34 967 49 40 46",
    "sg:postcode":"02240",
    "sg:province":"Albacete",
    "wof:name":"Caja De Ahorros De Castilla La Mancha",
    "wof:placetype":"venue"
},
  "geometry": {"coordinates":[-1.7229089737,39.2092208862],"type":"Point"}
}