{
  "type": "Feature",
  "properties": {
    "iso:country":"ES",
    "sg:address":"Ctra. Nal. 332, 35",
    "sg:city":"Gandia",
    "sg:orig_category":"Colchones (fabricaci\u00d3n, Al Por Mayor, Al Por Menor)",
    "sg:phone":"+34 962 86 46 74",
    "sg:postcode":"46700",
    "sg:province":"Valencia",
    "wof:name":"Hermanos Pallares Cb",
    "wof:placetype":"venue"
},
  "geometry": {"coordinates":[-0.1913339943,38.960735321],"type":"Point"}
}