{
  "type": "Feature",
  "properties": {
    "iso:country":"ES",
    "sg:address":"Carr Pirotecnia Brunchu, 80",
    "sg:city":"Godella",
    "sg:orig_category":"Ferreter\u00cda (diversos)",
    "sg:phone":"+34 963 63 96 35",
    "sg:postcode":"46110",
    "sg:province":"Valencia",
    "wof:name":"Montoro Valero Manuel",
    "wof:placetype":"venue"
},
  "geometry": {"coordinates":[-0.4224489927,39.5221405029],"type":"Point"}
}