{
  "type": "Feature",
  "properties": {
    "addr:full":"La Coma, S/n La Coma Valencia 46220",
    "addr:housenumber":"s / n",
    "addr:postcode":"46220",
    "addr:street":"Coma",
    "iso:country":"ES",
    "sg:address":"La Coma, S/n",
    "sg:city":"La Coma",
    "sg:orig_category":"Poller\u00cda Y Caza (al Por Menor)",
    "sg:phone":"+34 961 24 04 69",
    "sg:postcode":"46220",
    "sg:province":"Valencia",
    "wof:name":"Explotaciones Avicolas La Granja S.l.",
    "wof:placetype":"venue"
},
  "geometry": {"coordinates":[-0.4503290057,39.3280639648],"type":"Point"}
}