{
  "type": "Feature",
  "properties": {
    "iso:country":"ES",
    "sg:address":"Calle de Jose Luis Morales Marin, 23",
    "sg:city":"Marbella",
    "sg:orig_category":"Promotores Constructores",
    "sg:phone":"+34 952 77 76 79",
    "sg:postcode":"29600",
    "sg:province":"M\u00e1laga",
    "wof:name":"Priemarsol S.l.",
    "wof:placetype":"venue"
},
  "geometry": {"coordinates":[-4.889318943,36.5152282715],"type":"Point"}
}