{
  "type": "Feature",
  "properties": {
    "iso:country":"ES",
    "sg:address":"Calle de Heraclio Diaz Mesa, 31",
    "sg:city":"Icod De Los Vinos",
    "sg:orig_category":"Electrodom\u00c9sticos (al Por Menor)",
    "sg:phone":"+34 922 81 46 84",
    "sg:postcode":"38430",
    "sg:province":"Santa Cruz De Tenerife",
    "wof:name":"Industrial Icod S.a.",
    "wof:placetype":"venue"
},
  "geometry": {"coordinates":[-16.7203159332,28.3706169128],"type":"Point"}
}