{
  "type": "Feature",
  "properties": {
    "iso:country":"ES",
    "sg:address":"Calle de Juan Rico, 21",
    "sg:city":"Lucena",
    "sg:orig_category":"Electricidad: Instaladores",
    "sg:phone":"+34 957 51 32 64",
    "sg:postcode":"14900",
    "sg:province":"C\u00f3rdoba",
    "wof:name":"Fuenaras S.l.",
    "wof:placetype":"venue"
},
  "geometry": {"coordinates":[-4.4823951721,37.4096031189],"type":"Point"}
}