{
  "type": "Feature",
  "properties": {
    "addr:full":"Carr Mossen Agusti Coy I Cotonat, 4 Sort Lleida 25560",
    "addr:housenumber":"4",
    "addr:postcode":"25560",
    "addr:street":"Carr Mossen Agusti Coy;Cotonat",
    "iso:country":"ES",
    "sg:address":"Carr Mossen Agusti Coy I Cotonat, 4",
    "sg:city":"Sort",
    "sg:orig_category":"Alimentaci\u00d3n General (al Por Menor)",
    "sg:phone":"+34 973 62 14 36",
    "sg:postcode":"25560",
    "sg:province":"Lleida",
    "wof:name":"Borda Tariou S.l.",
    "wof:placetype":"venue"
},
  "geometry": {"coordinates":[1.1311160326,42.4119415283],"type":"Point"}
}