{
  "type": "Feature",
  "properties": {
    "iso:country":"ES",
    "sg:address":"Avda Compostela, 31",
    "sg:city":"Serra De Outes",
    "sg:orig_category":"Mercer\u00cda, Lencer\u00cda (al Por Menor)",
    "sg:phone":"+34 981 85 02 67",
    "sg:postcode":"15230",
    "sg:province":"La Coru\u00f1a",
    "wof:name":"Leston Arcos Dolores Carmen",
    "wof:placetype":"venue"
},
  "geometry": {"coordinates":[-8.9048891068,42.8418807983],"type":"Point"}
}