{
  "type": "Feature",
  "properties": {
    "iso:country":"ES",
    "sg:address":"Pase Independencia, 1",
    "sg:city":"Huelva",
    "sg:orig_category":"Supermercados Y Hipermercados",
    "sg:phone":"+34 959 54 07 95",
    "sg:postcode":"21002",
    "sg:province":"Huelva",
    "wof:name":"Centro Comercial El Jamon S.l.",
    "wof:placetype":"venue"
},
  "geometry": {"coordinates":[-6.9531569481,37.261089325],"type":"Point"}
}