{
  "type": "Feature",
  "properties": {
    "addr:full":"Calle de Cerejana (la), S/n San Pablo De Buceite C\u00e1diz 11320",
    "addr:housenumber":"/ n",
    "addr:postcode":"11320",
    "addr:street":"Calle De Cerejana La S;Ca\u0301Diz",
    "iso:country":"ES",
    "sg:address":"Calle de Cerejana (la), S/n",
    "sg:city":"San Pablo De Buceite",
    "sg:orig_category":"Ense\u00d1anza Secundaria: Colegios Y Escuelas Privadas",
    "sg:phone":"+34 956 64 22 02",
    "sg:postcode":"11320",
    "sg:province":"C\u00e1diz",
    "wof:name":"Junta De Andalucia",
    "wof:placetype":"venue"
},
  "geometry": {"coordinates":[-5.4125638008,36.4681282043],"type":"Point"}
}