{
  "type": "Feature",
  "properties": {
    "iso:country":"ES",
    "sg:address":"Carr La Noguera, 10",
    "sg:city":"Lleida",
    "sg:orig_category":"Chapister\u00cda",
    "sg:phone":"+34 973 23 14 83",
    "sg:postcode":"25005",
    "sg:province":"Lleida",
    "wof:name":"Carmona Cruces Antonio Jose",
    "wof:placetype":"venue"
},
  "geometry": {"coordinates":[0.6264449954,41.6269950867],"type":"Point"}
}