{
  "type": "Feature",
  "properties": {
    "iso:country":"ES",
    "sg:address":"Calle de Andorra, 69",
    "sg:city":"Madrid",
    "sg:orig_category":"Agencias Y Asesores De Publicidad",
    "sg:phone":"+34 913 88 64 92",
    "sg:postcode":"28043",
    "sg:province":"Madrid",
    "wof:name":"Labayru Y Anciones S.l.",
    "wof:placetype":"venue"
},
  "geometry": {"coordinates":[-3.643579483,40.4593582153],"type":"Point"}
}