{
  "type": "Feature",
  "properties": {
    "addr:full":"Rond Universitat, 29 Barcelona Barcelona 08007",
    "addr:housenumber":"29",
    "addr:postcode":"08007",
    "iso:country":"ES",
    "sg:address":"Rond Universitat, 29",
    "sg:city":"Barcelona",
    "sg:orig_category":"M\u00c9dicos: Cirug\u00cda Urol\u00d3gica",
    "sg:phone":"+34 932 15 13 10",
    "sg:postcode":"08007",
    "sg:province":"Barcelona",
    "wof:name":"Mu\u00f1oz Segui Jose",
    "wof:placetype":"venue"
},
  "geometry": {"coordinates":[2.1676340103,41.3871955872],"type":"Point"}
}