{
  "type": "Feature",
  "properties": {
    "iso:country":"ES",
    "sg:address":"Avgd Mestre Montaner, Km. 0551,9",
    "sg:city":"Igualada",
    "sg:orig_category":"M\u00c1quinas De Coser Y De Hacer Punto (al Por Mayor)",
    "sg:phone":"+34 938 05 06 42",
    "sg:postcode":"08700",
    "sg:province":"Barcelona",
    "wof:name":"Oteman S.a.",
    "wof:placetype":"venue"
},
  "geometry": {"coordinates":[1.6096110344,41.5911560059],"type":"Point"}
}