{
  "type": "Feature",
  "properties": {
    "iso:country":"ES",
    "sg:address":"Pase Rosales, 34",
    "sg:city":"Merida",
    "sg:orig_category":"Guarder\u00cdas",
    "sg:phone":"+34 924 37 16 59",
    "sg:postcode":"06800",
    "sg:province":"Badajoz",
    "wof:name":"Arroyo Perez Rafael",
    "wof:placetype":"venue"
},
  "geometry": {"coordinates":[-6.3540682793,38.9074363708],"type":"Point"}
}