{
  "type": "Feature",
  "properties": {
    "iso:country":"ES",
    "sg:address":"Calle de Verdier, 4",
    "sg:city":"Atarfe",
    "sg:orig_category":"Delegados, Agentes De Tr\u00c1nsito, Auxiliares De Transporte Internacional",
    "sg:phone":"+34 958 43 71 74",
    "sg:postcode":"18230",
    "sg:province":"Granada",
    "wof:name":"Garzon Garcia Jose",
    "wof:placetype":"venue"
},
  "geometry": {"coordinates":[-3.6803030968,37.2278327942],"type":"Point"}
}