{
  "type": "Feature",
  "properties": {
    "iso:country":"ES",
    "sg:address":"Carrer de Sol, 46",
    "sg:city":"Mollet Valles",
    "sg:orig_category":"Animales (al Por Menor)",
    "sg:phone":"+34 935 70 82 61",
    "sg:postcode":"08100",
    "sg:province":"Barcelona",
    "wof:name":"Ortega Ceruelo Maria Pilar",
    "wof:placetype":"venue"
},
  "geometry": {"coordinates":[2.2173140049,41.5407485962],"type":"Point"}
}