{
  "type": "Feature",
  "properties": {
    "addr:full":"Calle de Creus, 18 Sevilla Sevilla 41016",
    "addr:housenumber":"18",
    "addr:postcode":"41016",
    "addr:street":"Calle De Creus",
    "iso:country":"ES",
    "sg:address":"Calle de Creus, 18",
    "sg:city":"Sevilla",
    "sg:orig_category":"Agencias Y Asesores De Publicidad",
    "sg:phone":"+34 954 52 14 31",
    "sg:postcode":"41016",
    "sg:province":"Sevilla",
    "sg:website":"www.publicidadlazaro.com",
    "wof:name":"Lazaro Martinez Emilio",
    "wof:placetype":"venue"
},
  "geometry": {"coordinates":[-5.9148025513,37.3844718933],"type":"Point"}
}