{
  "type": "Feature",
  "properties": {
    "addr:full":"Calle de Abadia (la), 4 Caudete Albacete 02660",
    "addr:housenumber":"4",
    "addr:postcode":"02660",
    "addr:street":"Calle De Abadia La",
    "iso:country":"ES",
    "sg:address":"Calle de Abadia (la), 4",
    "sg:city":"Caudete",
    "sg:orig_category":"Quincaller\u00cda (al Por Menor)",
    "sg:phone":"+34 965 82 53 18",
    "sg:postcode":"02660",
    "sg:province":"Albacete",
    "wof:name":"Requena Gimeno Elia",
    "wof:placetype":"venue"
},
  "geometry": {"coordinates":[-0.9893202782,38.7036170959],"type":"Point"}
}