{
  "type": "Feature",
  "properties": {
    "addr:full":"Calle de Osinagea, 5 Vitoria-gasteiz \u00c1lava 01013",
    "addr:housenumber":"5",
    "addr:postcode":"01013",
    "addr:street":"Calle De Osinagea",
    "iso:country":"ES",
    "sg:address":"Calle de Osinagea, 5",
    "sg:city":"Vitoria-gasteiz",
    "sg:orig_category":"Tubos Y Tuber\u00cdas De Goma Y Pl\u00c1stico (fabricaci\u00d3n, Al Por Mayor)",
    "sg:phone":"+34 945 26 34 88",
    "sg:postcode":"01013",
    "sg:province":"\u00c1lava",
    "wof:name":"Mugica Garcia De Acilu Jose Luis",
    "wof:placetype":"venue"
},
  "geometry": {"coordinates":[-2.6557409763,42.8698120117],"type":"Point"}
}