{
  "type": "Feature",
  "properties": {
    "iso:country":"ES",
    "sg:address":"Calle de Losas (las), 9",
    "sg:city":"Castro Rio",
    "sg:orig_category":"Fisioterapia",
    "sg:phone":"+34 957 37 03 05",
    "sg:postcode":"14840",
    "sg:province":"C\u00f3rdoba",
    "wof:name":"Gomez Criado Laura",
    "wof:placetype":"venue"
},
  "geometry": {"coordinates":[-4.4837698936,37.6888237],"type":"Point"}
}