{
  "type": "Feature",
  "properties": {
    "iso:country":"ES",
    "sg:address":"Carr Mossen Cinto Verdaguer, 1",
    "sg:city":"Alpicat",
    "sg:orig_category":"Lencer\u00cda Femenina, Corseter\u00cda, Trajes De Ba\u00d1o (al Por Menor)",
    "sg:phone":"+34 973 73 76 68",
    "sg:postcode":"25110",
    "sg:province":"Lleida",
    "wof:name":"Tot X Tu S.c.p.",
    "wof:placetype":"venue"
},
  "geometry": {"coordinates":[0.5561959743,41.6614875793],"type":"Point"}
}