{
  "type": "Feature",
  "properties": {
    "addr:full":"Calle de De Los Herreros, 14 Benavente Zamora 49600",
    "addr:housenumber":"14",
    "addr:postcode":"49600",
    "addr:street":"Calle De De Los Herreros",
    "iso:country":"ES",
    "sg:address":"Calle de De Los Herreros, 14",
    "sg:city":"Benavente",
    "sg:orig_category":"Librer\u00cdas",
    "sg:phone":"+34 980 63 12 73",
    "sg:postcode":"49600",
    "sg:province":"Zamora",
    "wof:name":"Cordero Herrero Victor",
    "wof:placetype":"venue"
},
  "geometry": {"coordinates":[-5.6791591644,42.0026092529],"type":"Point"}
}