{
  "type": "Feature",
  "properties": {
    "addr:full":"Calle de Juan Carlos I, 3 Puerto Del Carmen Las Palmas 35510",
    "addr:housenumber":"3",
    "addr:postcode":"35510",
    "addr:street":"Calle De Juan Carlos I",
    "iso:country":"ES",
    "sg:address":"Calle de Juan Carlos I, 3",
    "sg:city":"Puerto Del Carmen",
    "sg:orig_category":"Artesan\u00cda",
    "sg:phone":"+34 928 51 59 00",
    "sg:postcode":"35510",
    "sg:province":"Las Palmas",
    "wof:name":"Cadore  Bernard",
    "wof:placetype":"venue"
},
  "geometry": {"coordinates":[-13.6700820923,28.9217166901],"type":"Point"}
}