{
  "type": "Feature",
  "properties": {
    "addr:full":"Calle de Segovia, 13 Navas Riofrio Segovia 40420",
    "addr:housenumber":"13",
    "addr:postcode":"40420",
    "addr:street":"Calle De Segovia",
    "iso:country":"ES",
    "sg:address":"Calle de Segovia, 13",
    "sg:city":"Navas Riofrio",
    "sg:orig_category":"Ense\u00d1anza, Formaci\u00d3n Profesional: Aprendizaje",
    "sg:phone":"+34 921 48 00 82",
    "sg:postcode":"40420",
    "sg:province":"Segovia",
    "wof:name":"Ayuntamiento De Navas De Riofrio",
    "wof:placetype":"venue"
},
  "geometry": {"coordinates":[-4.1353268623,40.8473968506],"type":"Point"}
}