{
  "type": "Feature",
  "properties": {
    "iso:country":"ES",
    "sg:address":"Ctra Trigueros, 17",
    "sg:city":"Beas",
    "sg:orig_category":"Mec\u00c1nico Del Autom\u00d3vil",
    "sg:phone":"+34 959 30 80 86",
    "sg:postcode":"21630",
    "sg:province":"Huelva",
    "wof:name":"Fernandez Ramirez Francisco",
    "wof:placetype":"venue"
},
  "geometry": {"coordinates":[-6.7992668152,37.4230651855],"type":"Point"}
}