{
  "type": "Feature",
  "properties": {
    "addr:full":"Calle de Mayor, 14 Arenas -areeta Vizcaya 48930",
    "addr:housenumber":"14;areeta",
    "addr:postcode":"48930",
    "addr:street":"Calle De Mayor",
    "iso:country":"ES",
    "sg:address":"Calle de Mayor, 14",
    "sg:city":"Arenas -areeta",
    "sg:orig_category":"Tintorer\u00cdas, Limpieza En Seco",
    "sg:phone":"+34 944 64 72 18",
    "sg:postcode":"48930",
    "sg:province":"Vizcaya",
    "wof:name":"Irastorza Urbiztondo Maria Jesus",
    "wof:placetype":"venue"
},
  "geometry": {"coordinates":[-3.0129179955,43.3257102966],"type":"Point"}
}