{
  "type": "Feature",
  "properties": {
    "iso:country":"ES",
    "sg:address":"Bulandegi Bidea, 1",
    "sg:city":"Elbarrena",
    "sg:orig_category":"Carnicer\u00cdas, Carnicer\u00cdas",
    "sg:phone":"+34 943 69 62 42",
    "sg:postcode":"20159",
    "sg:province":"Guip\u00f9zcoa",
    "wof:name":"Aramburu Izaguirre Jose Antonio",
    "wof:placetype":"venue"
},
  "geometry": {"coordinates":[-2.056460619,43.1910209656],"type":"Point"}
}