{
  "type": "Feature",
  "properties": {
    "addr:full":"Calle de Solares, 1 Granada Granada 18009",
    "addr:housenumber":"1",
    "addr:postcode":"18009",
    "addr:street":"Calle De Solares",
    "iso:country":"ES",
    "sg:address":"Calle de Solares, 1",
    "sg:city":"Granada",
    "sg:orig_category":"Reposter\u00cdas",
    "sg:phone":"+34 958 22 71 72",
    "sg:postcode":"18009",
    "sg:province":"Granada",
    "wof:name":"Jimenez Leon Maria Dolores",
    "wof:placetype":"venue"
},
  "geometry": {"coordinates":[-3.5906739235,37.1702804565],"type":"Point"}
}