{
  "type": "Feature",
  "properties": {
    "addr:full":"Intxaurdia Cent Com Itaroa, 5 Huarte Navarra 31620",
    "addr:housenumber":"5",
    "addr:postcode":"31620",
    "addr:street":"Itaroa;Navarra",
    "iso:country":"ES",
    "sg:address":"Intxaurdia Cent Com Itaroa, 5",
    "sg:city":"Huarte",
    "sg:orig_category":"Venta, Alquiler De V\u00cddeo",
    "sg:phone":"+34 948 35 74 29",
    "sg:postcode":"31620",
    "sg:province":"Navarra",
    "sg:website":"www.centromail.es",
    "wof:name":"Engine Technology System S.l.",
    "wof:placetype":"venue"
},
  "geometry": {"coordinates":[-1.5902739763,42.83177948],"type":"Point"}
}