{
  "type": "Feature",
  "properties": {
    "addr:full":"Calle de Sor Alegria, 8 Melilla Melilla 52002",
    "addr:housenumber":"8",
    "addr:postcode":"52002",
    "addr:street":"Calle De Sor Alegria",
    "iso:country":"ES",
    "sg:address":"Calle de Sor Alegria, 8",
    "sg:city":"Melilla",
    "sg:orig_category":"Tintorer\u00cdas, Limpieza En Seco",
    "sg:phone":"+34 952 68 17 77",
    "sg:postcode":"52002",
    "sg:province":"Melilla",
    "wof:name":"Escalona Nache Juan",
    "wof:placetype":"venue"
},
  "geometry": {"coordinates":[-2.9435338974,35.2943534851],"type":"Point"}
}