{
  "type": "Feature",
  "properties": {
    "addr:full":"Calle de Elizondo, 2 Bilbao Vizcaya 48004",
    "addr:housenumber":"2",
    "addr:postcode":"48004",
    "addr:street":"Calle De Elizondo",
    "iso:country":"ES",
    "sg:address":"Calle de Elizondo, 2",
    "sg:city":"Bilbao",
    "sg:orig_category":"Loter\u00cda Y T\u00d3mbola",
    "sg:phone":"+34 944 11 20 19",
    "sg:postcode":"48004",
    "sg:province":"Vizcaya",
    "wof:name":"Mu\u00f1oz Urizar Maria Inmaculada Del Alcazar",
    "wof:placetype":"venue"
},
  "geometry": {"coordinates":[-2.9111089706,43.2534446716],"type":"Point"}
}