{
  "type": "Feature",
  "properties": {
    "addr:full":"Avgd Blasco Iba\u00d1ez, 18 Manises Valencia 46940",
    "addr:housenumber":"18",
    "addr:postcode":"46940",
    "addr:street":"Iban\u0303Ez",
    "iso:country":"ES",
    "sg:address":"Avgd Blasco Iba\u00d1ez, 18",
    "sg:city":"Manises",
    "sg:orig_category":"Peluquer\u00cdas, Peluquer\u00cda Mixta",
    "sg:phone":"+34 961 52 55 92",
    "sg:postcode":"46940",
    "sg:province":"Valencia",
    "wof:name":"Benlloch Alcalde Mercedes",
    "wof:placetype":"venue"
},
  "geometry": {"coordinates":[-0.4590190053,39.4916381836],"type":"Point"}
}