{
  "type": "Feature",
  "properties": {
    "iso:country":"ES",
    "sg:address":"Calle de San Francisco, 24",
    "sg:city":"Maella",
    "sg:orig_category":"Procuradores",
    "sg:phone":"+34 976 63 85 71",
    "sg:postcode":"50710",
    "sg:province":"Zaragoza",
    "wof:name":"Cortes Acero Inmaculada",
    "wof:placetype":"venue"
},
  "geometry": {"coordinates":[0.1377000064,41.1215515137],"type":"Point"}
}