{
  "type": "Feature",
  "properties": {
    "addr:full":"Pseo. Constitucion, 22 Almaraz C\u00e1ceres 10350",
    "addr:housenumber":"22",
    "addr:postcode":"10350",
    "addr:street":"Constitucion;Ca\u0301Ceres",
    "iso:country":"ES",
    "sg:address":"Pseo. Constitucion, 22",
    "sg:city":"Almaraz",
    "sg:orig_category":"Peluqueros: De Se\u00d1oras",
    "sg:phone":"+34 927 54 42 79",
    "sg:postcode":"10350",
    "sg:province":"C\u00e1ceres",
    "wof:name":"Fernandez Gonzalez Bego\u00f1a",
    "wof:placetype":"venue"
},
  "geometry": {"coordinates":[-5.6752381325,39.8143997192],"type":"Point"}
}