{
  "type": "Feature",
  "properties": {
    "iso:country":"ES",
    "sg:address":"Carr Bellavista, 24",
    "sg:city":"Lleida",
    "sg:orig_category":"Molduras, Junquillos, Listones Y Molduras Perforadas",
    "sg:phone":"+34 973 21 09 16",
    "sg:postcode":"25001",
    "sg:province":"Lleida",
    "wof:name":"Gaset Tarrat David",
    "wof:placetype":"venue"
},
  "geometry": {"coordinates":[0.6382510066,41.6052207947],"type":"Point"}
}