{
  "type": "Feature",
  "properties": {
    "iso:country":"ES",
    "sg:address":"Calle de San Lorenzo, 14",
    "sg:city":"Coru\u00d1a",
    "sg:orig_category":"Empresas De Limpieza",
    "sg:phone":"+34 981 20 01 85",
    "sg:postcode":"15002",
    "sg:province":"A Coru\u00f1a",
    "wof:name":"Vazquez Garcia Olga",
    "wof:placetype":"venue"
},
  "geometry": {"coordinates":[-8.3969640732,43.3756942749],"type":"Point"}
}