{
  "type": "Feature",
  "properties": {
    "iso:country":"ES",
    "sg:address":"Calle de Antonio Del Rey, 8",
    "sg:city":"Torrecampo",
    "sg:orig_category":"Iglesia Cat\u00d3lica",
    "sg:phone":"+34 957 15 53 35",
    "sg:postcode":"14410",
    "sg:province":"C\u00f3rdoba",
    "wof:name":"Parroquia De Torrecampo",
    "wof:placetype":"venue"
},
  "geometry": {"coordinates":[-4.679186821,38.4739723206],"type":"Point"}
}