{
  "type": "Feature",
  "properties": {
    "iso:country":"ES",
    "sg:address":"Calle de Economista G.bernacer, 5",
    "sg:city":"Alacant",
    "sg:orig_category":"Laboratorios Y Cl\u00cdnicas Veterinarias",
    "sg:phone":"+34 965 18 28 66",
    "sg:postcode":"03011",
    "sg:province":"Alicante",
    "wof:name":"Clinica Virgen Del Remedio S.l.",
    "wof:placetype":"venue"
},
  "geometry": {"coordinates":[-0.4903430939,38.3747596741],"type":"Point"}
}