{
  "type": "Feature",
  "properties": {
    "iso:country":"ES",
    "sg:address":"Carrer de Alexander Bell, 151",
    "sg:city":"Terrassa",
    "sg:orig_category":"Aparcamientos (infraestructuras, Accesorios)",
    "sg:phone":"+34 937 88 91 99",
    "sg:postcode":"08224",
    "sg:province":"Barcelona",
    "wof:name":"Marin Diezhandino Jose Maria",
    "wof:placetype":"venue"
},
  "geometry": {"coordinates":[1.9988650084,41.5662918091],"type":"Point"}
}