{
  "type": "Feature",
  "properties": {
    "iso:country":"ES",
    "sg:address":"Carrer de Ballestera, 14",
    "sg:city":"Prat Llobregat",
    "sg:orig_category":"Empresas De Pintura Y Revestimientos",
    "sg:phone":"+34 934 78 67 06",
    "sg:postcode":"08820",
    "sg:province":"Barcelona",
    "wof:name":"Risque Merino Victor",
    "wof:placetype":"venue"
},
  "geometry": {"coordinates":[2.0914349556,41.3197555542],"type":"Point"}
}