{
  "type": "Feature",
  "properties": {
    "addr:full":"Av Llibertat, 38 Prat Llobregat Barcelona 08820",
    "addr:housenumber":"38",
    "addr:postcode":"08820",
    "addr:street":"Av Llibertat;Llobregat",
    "iso:country":"ES",
    "sg:address":"Av Llibertat, 38",
    "sg:city":"Prat Llobregat",
    "sg:orig_category":"Molduras, Junquillos, Listones Y Molduras Perforadas",
    "sg:phone":"+34 934 78 62 03",
    "sg:postcode":"08820",
    "sg:province":"Barcelona",
    "wof:name":"Naranjo Paz Francisca",
    "wof:placetype":"venue"
},
  "geometry": {"coordinates":[2.1025300026,41.3250579834],"type":"Point"}
}