{
  "type": "Feature",
  "properties": {
    "addr:full":"Rua Hernan Cortes, 8 Vigo Pontevedra 36203",
    "addr:housenumber":"8",
    "addr:postcode":"36203",
    "addr:street":"Rua Hernan Cortes",
    "iso:country":"ES",
    "sg:address":"Rua Hernan Cortes, 8",
    "sg:city":"Vigo",
    "sg:orig_category":"Estancos",
    "sg:phone":"+34 986 43 61 30",
    "sg:postcode":"36203",
    "sg:province":"Pontevedra",
    "wof:name":"Alvarez Navarrete Aurea",
    "wof:placetype":"venue"
},
  "geometry": {"coordinates":[-8.7177124023,42.2343559265],"type":"Point"}
}