{
  "type": "Feature",
  "properties": {
    "addr:full":"Calle de Manuel Daza, 4 Gibraleon Huelva 21500",
    "addr:housenumber":"4",
    "addr:postcode":"21500",
    "addr:street":"Calle De Manuel Daza",
    "iso:country":"ES",
    "sg:address":"Calle de Manuel Daza, 4",
    "sg:city":"Gibraleon",
    "sg:orig_category":"Farmacias",
    "sg:phone":"+34 959 30 00 09",
    "sg:postcode":"21500",
    "sg:province":"Huelva",
    "wof:name":"Farmacia Rite Duque S.c.",
    "wof:placetype":"venue"
},
  "geometry": {"coordinates":[-6.9692578316,37.3755187988],"type":"Point"}
}