{
  "type": "Feature",
  "properties": {
    "addr:full":"Av Catalunya, 176 Palau-solita I Plegamans Barcelona 08184",
    "addr:housenumber":"176",
    "addr:postcode":"08184",
    "addr:street":"Av Catalunya",
    "iso:country":"ES",
    "sg:address":"Av Catalunya, 176",
    "sg:city":"Palau-solita I Plegamans",
    "sg:orig_category":"Comercio De Piezas De Recambio Y De Accesorios De Veh\u00cdculos, Veh\u00cdculos Industriales",
    "sg:phone":"+34 938 64 49 29",
    "sg:postcode":"08184",
    "sg:province":"Barcelona",
    "wof:name":"Recambios Palau S.l.",
    "wof:placetype":"venue"
},
  "geometry": {"coordinates":[2.1806209087,41.5841941833],"type":"Point"}
}