{
  "type": "Feature",
  "properties": {
    "addr:full":"Calle de Vegafria, 1 Madrid Madrid 28035",
    "addr:housenumber":"1",
    "addr:postcode":"28035",
    "addr:street":"Calle De Vegafria",
    "iso:country":"ES",
    "sg:address":"Calle de Vegafria, 1",
    "sg:city":"Madrid",
    "sg:orig_category":"Bisuteros (fabricaci\u00d3n, Al Por Mayor)",
    "sg:phone":"+34 913 16 97 84",
    "sg:postcode":"28035",
    "sg:province":"Madrid",
    "wof:name":"Teresa G. De Diego S.l.",
    "wof:placetype":"venue"
},
  "geometry": {"coordinates":[-3.7433080673,40.4747123718],"type":"Point"}
}