{
  "type": "Feature",
  "properties": {
    "iso:country":"ES",
    "sg:address":"Acevo, S/n",
    "sg:city":"Acebo",
    "sg:orig_category":"Administraciones Regionales, Departamentales Y Locales",
    "sg:phone":"+34 982 17 45 75",
    "sg:postcode":"27243",
    "sg:province":"Lugo",
    "wof:name":"Concello De Ribeira De Piquin",
    "wof:placetype":"venue"
},
  "geometry": {"coordinates":[-7.1901988983,43.2087898254],"type":"Point"}
}