{
  "type": "Feature",
  "properties": {
    "addr:full":"Calle de Goya, 1 Alberic Valencia 46260",
    "addr:housenumber":"1",
    "addr:postcode":"46260",
    "addr:street":"Calle De Goya",
    "iso:country":"ES",
    "sg:address":"Calle de Goya, 1",
    "sg:city":"Alberic",
    "sg:orig_category":"Organizaci\u00d3n De Actos, Seminarios Y Congresos",
    "sg:phone":"+34 962 44 09 50",
    "sg:postcode":"46260",
    "sg:province":"Valencia",
    "wof:name":"Atenea Hosteleria S.l.",
    "wof:placetype":"venue"
},
  "geometry": {"coordinates":[-0.5224124193,39.1164588928],"type":"Point"}
}