{
  "type": "Feature",
  "properties": {
    "iso:country":"ES",
    "sg:address":"Calle de Rodriguez Murias, 10",
    "sg:city":"Ribadeo",
    "sg:orig_category":"Agencias De Viajes",
    "sg:phone":"+34 982 13 08 90",
    "sg:postcode":"27700",
    "sg:province":"Lugo",
    "wof:name":"Viajes Terra Mar S.l.",
    "wof:placetype":"venue"
},
  "geometry": {"coordinates":[-7.0414991379,43.537021637],"type":"Point"}
}