{
  "type": "Feature",
  "properties": {
    "addr:full":"Av Isabel La Catolica, 98 Hospitalet Llobregat Barcelona 08905",
    "addr:housenumber":"98",
    "addr:postcode":"08905",
    "addr:street":"Av Isabel La Catolica",
    "iso:country":"ES",
    "sg:address":"Av Isabel La Catolica, 98",
    "sg:city":"Hospitalet Llobregat",
    "sg:orig_category":"Cl\u00cdnicas Dentales",
    "sg:phone":"+34 934 37 30 30",
    "sg:postcode":"08905",
    "sg:province":"Barcelona",
    "wof:name":"Dentaplus Hospitalet S.l.",
    "wof:placetype":"venue"
},
  "geometry": {"coordinates":[2.105107069,41.3715934753],"type":"Point"}
}