{
  "type": "Feature",
  "properties": {
    "addr:full":"Calle de Terronal (el), 48 Fuente El Saz De Jarama Madrid 28140",
    "addr:housenumber":"48",
    "addr:postcode":"28140",
    "addr:street":"Calle De Terronal El",
    "iso:country":"ES",
    "sg:address":"Calle de Terronal (el), 48",
    "sg:city":"Fuente El Saz De Jarama",
    "sg:orig_category":"Papel, Reciclaje",
    "sg:phone":"+34 916 22 41 04",
    "sg:postcode":"28140",
    "sg:province":"Madrid",
    "wof:name":"Recuperaciones Barajas S.l.",
    "wof:placetype":"venue"
},
  "geometry": {"coordinates":[-3.5142989159,40.6470870972],"type":"Point"}
}