{
  "type": "Feature",
  "properties": {
    "iso:country":"ES",
    "sg:address":"Carrer de Paris, 205",
    "sg:city":"Barcelona",
    "sg:orig_category":"M\u00c9dicos: Radioterapia (radioterapia Como Opci\u00d3n Oncol\u00d3gica)",
    "sg:phone":"+34 932 09 99 64",
    "sg:postcode":"08008",
    "sg:province":"Barcelona",
    "wof:name":"Garcia Espuche Antonio",
    "wof:placetype":"venue"
},
  "geometry": {"coordinates":[2.1536719799,41.3941612244],"type":"Point"}
}