{
  "type": "Feature",
  "properties": {
    "iso:country":"ES",
    "sg:address":"Calle de Andres Cegarra, 14",
    "sg:city":"Union",
    "sg:orig_category":"Aguas (distribuci\u00d3n, Servicios)",
    "sg:phone":"+34 968 54 20 17",
    "sg:postcode":"30360",
    "sg:province":"Murcia",
    "wof:name":"La Union Servicios Municipales S.a.",
    "wof:placetype":"venue"
},
  "geometry": {"coordinates":[-0.8783631921,37.6190681458],"type":"Point"}
}