{
  "type": "Feature",
  "properties": {
    "addr:full":"Plaz Ayuntamiento Del, 1 Isla Cristina Huelva 21410",
    "addr:postcode":"21410",
    "iso:country":"ES",
    "sg:address":"Plaz Ayuntamiento Del, 1",
    "sg:city":"Isla Cristina",
    "sg:orig_category":"Inmobiliaria (agencias)",
    "sg:phone":"+34 959 33 20 44",
    "sg:postcode":"21410",
    "sg:province":"Huelva",
    "wof:name":"Islanorte S. A.",
    "wof:placetype":"venue"
},
  "geometry": {"coordinates":[-7.3203940392,37.2019615173],"type":"Point"}
}