{
  "type": "Feature",
  "properties": {
    "iso:country":"ES",
    "sg:address":"Urb. Balitra, 18",
    "sg:city":"Palamos",
    "sg:orig_category":"Empresas De Vigilancia, Guardia Y Protecci\u00d3n",
    "sg:phone":"+34 972 31 21 20",
    "sg:postcode":"17230",
    "sg:province":"Girona",
    "wof:name":"Garcia Gavilan Ricardo Luis",
    "wof:placetype":"venue"
},
  "geometry": {"coordinates":[3.1328010559,41.8621673584],"type":"Point"}
}