{
  "type": "Feature",
  "properties": {
    "iso:country":"ES",
    "sg:address":"Ctra Seixi\u00d1os, 3",
    "sg:city":"Pena",
    "sg:orig_category":"Centros Empresariales",
    "sg:phone":"+34 986 41 18 69",
    "sg:postcode":"36312",
    "sg:province":"Pontevedra",
    "wof:name":"Herlayca S.l.",
    "wof:placetype":"venue"
},
  "geometry": {"coordinates":[-8.1588478088,42.6563339233],"type":"Point"}
}