{
  "type": "Feature",
  "properties": {
    "addr:full":"Carrer de Marina, 57 Barcelona Barcelona 08005",
    "addr:housenumber":"57",
    "addr:postcode":"08005",
    "addr:street":"Carrer De Marina",
    "iso:country":"ES",
    "sg:address":"Carrer de Marina, 57",
    "sg:city":"Barcelona",
    "sg:orig_category":"Dietistas",
    "sg:phone":"+34 932 21 21 94",
    "sg:postcode":"08005",
    "sg:province":"Barcelona",
    "wof:name":"Losche Cm S.l.",
    "wof:placetype":"venue"
},
  "geometry": {"coordinates":[2.1909160614,41.3915710449],"type":"Point"}
}