{
  "type": "Feature",
  "properties": {
    "iso:country":"ES",
    "sg:address":"Plaz Mayor, 7",
    "sg:city":"Macotera",
    "sg:orig_category":"Electrodom\u00c9sticos (al Por Menor)",
    "sg:phone":"+34 923 55 50 56",
    "sg:postcode":"37310",
    "sg:province":"Salamanca",
    "wof:name":"Carabias Martin Norberto",
    "wof:placetype":"venue"
},
  "geometry": {"coordinates":[-5.2855100632,40.8306350708],"type":"Point"}
}