{
  "type": "Feature",
  "properties": {
    "iso:country":"ES",
    "sg:address":"Carr El Penedes, 83",
    "sg:city":"Lleida",
    "sg:orig_category":"Empresas De Pintura Y Revestimientos",
    "sg:phone":"+34 973 22 10 58",
    "sg:postcode":"25005",
    "sg:province":"Lleida",
    "wof:name":"Alvarez Rodriguez Jesus",
    "wof:placetype":"venue"
},
  "geometry": {"coordinates":[0.6239411235,41.6287574768],"type":"Point"}
}