{
  "type": "Feature",
  "properties": {
    "iso:country":"ES",
    "sg:address":"Urbieta Kalea, 18",
    "sg:city":"Hernani",
    "sg:orig_category":"Seguridad En El Trabajo Y Prevenci\u00d3n De Riesgos Laborales",
    "sg:phone":"+34 943 33 11 59",
    "sg:postcode":"20120",
    "sg:province":"Guip\u00f9zcoa",
    "wof:name":"Collado Echeberria Jose Maria",
    "wof:placetype":"venue"
},
  "geometry": {"coordinates":[-1.9786100388,43.267906189],"type":"Point"}
}