{
  "type": "Feature",
  "properties": {
    "iso:country":"ES",
    "sg:address":"Carr Pintor Ribera, 14",
    "sg:city":"Benetusser",
    "sg:orig_category":"Asesor\u00cdas Y Estudios Financieros",
    "sg:phone":"+34 963 75 12 46",
    "sg:postcode":"46910",
    "sg:province":"Valencia",
    "wof:name":"Eco-alaiki S.l.",
    "wof:placetype":"venue"
},
  "geometry": {"coordinates":[-0.3940939903,39.4234352112],"type":"Point"}
}