{
  "type": "Feature",
  "properties": {
    "addr:full":"Calle de Andres Borrego, 6 Madrid Madrid 28004",
    "addr:housenumber":"6",
    "addr:postcode":"28004",
    "addr:street":"Calle De Andres Borrego",
    "iso:country":"ES",
    "sg:address":"Calle de Andres Borrego, 6",
    "sg:city":"Madrid",
    "sg:orig_category":"Bisuter\u00cda, Joyer\u00cda, Relojer\u00cda (al Por Menor)",
    "sg:phone":"+34 915 31 59 65",
    "sg:postcode":"28004",
    "sg:province":"Madrid",
    "wof:name":"Garrote Rumbado Fernando",
    "wof:placetype":"venue"
},
  "geometry": {"coordinates":[-3.7067360878,40.423160553],"type":"Point"}
}