{
  "type": "Feature",
  "properties": {
    "iso:country":"ES",
    "sg:address":"Ctra Entrena, Km. 0001,5",
    "sg:city":"Navarrete",
    "sg:orig_category":"Venta De Caravanas, Casas M\u00d3viles, Camping",
    "sg:phone":"+34 941 44 01 69",
    "sg:postcode":"26370",
    "sg:province":"La Rioja",
    "sg:website":"www.abisindustrial.com",
    "wof:name":"Trescamp S.a.",
    "wof:placetype":"venue"
},
  "geometry": {"coordinates":[-2.5627059937,42.4329109192],"type":"Point"}
}