{
  "type": "Feature",
  "properties": {
    "addr:full":"Calle de Corral De La Copera, 2 Zaratan Valladolid 47610",
    "addr:housenumber":"2",
    "addr:postcode":"47610",
    "addr:street":"Calle De Corral De La Copera",
    "iso:country":"ES",
    "sg:address":"Calle de Corral De La Copera, 2",
    "sg:city":"Zaratan",
    "sg:orig_category":"Promotores Constructores",
    "sg:phone":"+34 983 33 40 63",
    "sg:postcode":"47610",
    "sg:province":"Valladolid",
    "wof:name":"Construcciones Excuevas S.l",
    "wof:placetype":"venue"
},
  "geometry": {"coordinates":[-4.7834568024,41.6598320007],"type":"Point"}
}