{
  "type": "Feature",
  "properties": {
    "addr:full":"Calle de Valderribas, 32 Madrid Madrid 28007",
    "addr:housenumber":"32",
    "addr:postcode":"madrid;28007",
    "addr:street":"Calle De Valderribas",
    "iso:country":"ES",
    "sg:address":"Calle de Valderribas, 32",
    "sg:city":"Madrid",
    "sg:orig_category":"Herboristas (al Por Menor)",
    "sg:phone":"+34 915 01 96 72",
    "sg:postcode":"28007",
    "sg:province":"Madrid",
    "wof:name":"Campos Qui\u00f1ones Maria De Los Angeles",
    "wof:placetype":"venue"
},
  "geometry": {"coordinates":[-3.6753880978,40.4042015076],"type":"Point"}
}