{
  "type": "Feature",
  "properties": {
    "addr:full":"Calle de Bartolome Abelenda, S/n Coin M\u00e1laga 29100",
    "addr:housenumber":"s / n",
    "addr:postcode":"29100",
    "addr:street":"Calle De Bartolome Abelenda;Ma\u0301Laga",
    "iso:country":"ES",
    "sg:address":"Calle de Bartolome Abelenda, S/n",
    "sg:city":"Coin",
    "sg:orig_category":"Electrodom\u00c9sticos (al Por Menor)",
    "sg:phone":"+34 952 45 33 18",
    "sg:postcode":"29100",
    "sg:province":"M\u00e1laga",
    "wof:name":"Cortes Dominguez Miguel",
    "wof:placetype":"venue"
},
  "geometry": {"coordinates":[-4.7544941902,36.659450531],"type":"Point"}
}