{
  "type": "Feature",
  "properties": {
    "addr:full":"San Xusto, S/n Avion Ourense 32435",
    "addr:housenumber":"/ n",
    "addr:postcode":"32435",
    "addr:street":"Xusto S",
    "iso:country":"ES",
    "sg:address":"San Xusto, S/n",
    "sg:city":"Avion",
    "sg:orig_category":"Librer\u00cdas",
    "sg:phone":"+34 988 48 60 50",
    "sg:postcode":"32435",
    "sg:province":"Ourense",
    "wof:name":"Lamelas Gulias Elvira",
    "wof:placetype":"venue"
},
  "geometry": {"coordinates":[-8.2517595291,42.374420166],"type":"Point"}
}