{
  "type": "Feature",
  "properties": {
    "iso:country":"ES",
    "sg:address":"Cra Piera, Km. 0025,7",
    "sg:city":"Martorell",
    "sg:orig_category":"Acondicionamiento, Mantenimiento De Jardines Y Parques",
    "sg:phone":"+34 937 75 30 19",
    "sg:postcode":"08760",
    "sg:province":"Barcelona",
    "wof:name":"Centre De Jardineria Martorell S.l.",
    "wof:placetype":"venue"
},
  "geometry": {"coordinates":[1.9265979528,41.474105835],"type":"Point"}
}