{
  "type": "Feature",
  "properties": {
    "addr:full":"Carrer de Proven\u00c7a, 213 Barcelona Barcelona 08008",
    "addr:housenumber":"213",
    "addr:postcode":"08008",
    "addr:street":"Carrer De Provenc\u0327A",
    "iso:country":"ES",
    "sg:address":"Carrer de Proven\u00c7a, 213",
    "sg:city":"Barcelona",
    "sg:orig_category":"Librer\u00cdas",
    "sg:phone":"+34 932 15 71 21",
    "sg:postcode":"08008",
    "sg:province":"Barcelona",
    "wof:name":"Mas Sampietro Jose",
    "wof:placetype":"venue"
},
  "geometry": {"coordinates":[2.1584584713,41.3924827576],"type":"Point"}
}