{
  "type": "Feature",
  "properties": {
    "addr:full":"Carrer de Cardenal Vidal I Barraquer, S/n Sitges Barcelona 08870",
    "addr:housenumber":"s / n",
    "addr:postcode":"08870",
    "addr:street":"Carrer De Cardenal Vidal I Barraquer",
    "iso:country":"ES",
    "sg:address":"Carrer de Cardenal Vidal I Barraquer, S/n",
    "sg:city":"Sitges",
    "sg:orig_category":"Internados & Ense\u00d1anza Privada",
    "sg:phone":"+34 938 94 07 91",
    "sg:postcode":"08870",
    "sg:province":"Barcelona",
    "wof:name":"Misioneras De La Inmaculada Concepcion Provincia De Cataluna Curia Provincial",
    "wof:placetype":"venue"
},
  "geometry": {"coordinates":[1.8125050068,41.241355896],"type":"Point"}
}