{
  "type": "Feature",
  "properties": {
    "iso:country":"ES",
    "sg:address":"Avda Marina, 2",
    "sg:city":"Coru\u00d1a",
    "sg:orig_category":"Caf\u00c9s Teatro",
    "sg:phone":"+34 981 22 42 41",
    "sg:postcode":"15001",
    "sg:province":"La Coru\u00f1a",
    "wof:name":"Agra Vilari\u00f1o Jesus Manuel",
    "wof:placetype":"venue"
},
  "geometry": {"coordinates":[-8.4001083374,43.3694267273],"type":"Point"}
}