{
  "type": "Feature",
  "properties": {
    "iso:country":"ES",
    "sg:address":"Calle de Torreta De Miramar, 8",
    "sg:city":"Valencia",
    "sg:orig_category":"Agencias Y Agentes Comerciales, Representantes",
    "sg:phone":"+34 963 69 42 79",
    "sg:postcode":"46020",
    "sg:province":"Valencia",
    "wof:name":"Sanchez Garcia Patricia",
    "wof:placetype":"venue"
},
  "geometry": {"coordinates":[-0.3624419868,39.4877204895],"type":"Point"}
}