{
  "type": "Feature",
  "properties": {
    "iso:country":"ES",
    "sg:address":"Carr Manuel Gaya I Tomas, 18",
    "sg:city":"Lleida",
    "sg:orig_category":"Agencias Y Agentes Comerciales, Representantes",
    "sg:phone":"+34 973 21 29 03",
    "sg:postcode":"25001",
    "sg:province":"Lleida",
    "wof:name":"Vila Rubio Jose Ramon",
    "wof:placetype":"venue"
},
  "geometry": {"coordinates":[0.6376289725,41.610710144],"type":"Point"}
}