{
  "type": "Feature",
  "properties": {
    "addr:full":"Calle de Torrecilla, 16 Valladolid Valladolid 47003",
    "addr:housenumber":"16",
    "addr:postcode":"47003",
    "addr:street":"Calle De Torrecilla",
    "iso:country":"ES",
    "sg:address":"Calle de Torrecilla, 16",
    "sg:city":"Valladolid",
    "sg:orig_category":"Carnicer\u00cdas, Carnicer\u00cdas",
    "sg:phone":"+34 983 25 38 23",
    "sg:postcode":"47003",
    "sg:province":"Valladolid",
    "wof:name":"Garcia Bermejo Jose Maria",
    "wof:placetype":"venue"
},
  "geometry": {"coordinates":[-4.7228441238,41.6563262939],"type":"Point"}
}