{
  "type": "Feature",
  "properties": {
    "addr:full":"Calle de Ochoa Ondategui, 6 Segovia Segovia 40001",
    "addr:housenumber":"6",
    "addr:postcode":"40001",
    "addr:street":"Calle De Ochoa Ondategui",
    "iso:country":"ES",
    "sg:address":"Calle de Ochoa Ondategui, 6",
    "sg:city":"Segovia",
    "sg:orig_category":"Ense\u00d1anza Variada",
    "sg:phone":"+34 921 44 41 39",
    "sg:postcode":"40001",
    "sg:province":"Segovia",
    "wof:name":"Alvaro De Las Heras Nicolas De",
    "wof:placetype":"venue"
},
  "geometry": {"coordinates":[-4.1164755821,40.9475288391],"type":"Point"}
}