{
  "type": "Feature",
  "properties": {
    "iso:country":"ES",
    "sg:address":"Calle de Conde De Santa Barbara De Lugones, S/n",
    "sg:city":"Pola De Siero",
    "sg:orig_category":"Ropa Para Se\u00d1oras (al Por Menor)",
    "sg:phone":"+34 985 72 04 87",
    "sg:postcode":"33510",
    "sg:province":"Asturias",
    "wof:name":"Balsa Fernandez Dulce Maria",
    "wof:placetype":"venue"
},
  "geometry": {"coordinates":[-5.6611890793,43.3918952942],"type":"Point"}
}