{
  "type": "Feature",
  "properties": {
    "iso:country":"ES",
    "sg:address":"Calle de Villa Conesa, 14",
    "sg:city":"Fuente Alamo",
    "sg:orig_category":"Electromec\u00c1nica",
    "sg:phone":"+34 968 59 60 54",
    "sg:postcode":"30320",
    "sg:province":"Murcia",
    "wof:name":"Mu\u00f1oz Martinez Juan Antonio",
    "wof:placetype":"venue"
},
  "geometry": {"coordinates":[-1.1730489731,37.714099884],"type":"Point"}
}