{
  "type": "Feature",
  "properties": {
    "iso:country":"ES",
    "sg:address":"guzman el bueno, 133",
    "sg:city":"Madrid",
    "sg:classifiers":[
        {
            "category":"Professional",
            "subcategory":"Management & Consulting",
            "type":"Services"
        }
    ],
    "sg:postcode":"28003",
    "sg:tags":[
        "ibm-portal",
        "ibm-ecm",
        "ibm-rational"
    ],
    "sg:website":"http://www.sowre.es",
    "wof:name":"Sowre",
    "wof:placetype":"venue"
},
  "geometry": {"coordinates":[-3.7125615,40.4431637],"type":"Point"}
}