{
  "type": "Feature",
  "properties": {
    "addr:full":"Calle de Gonzalo Del Rio, S/n Santa Maria Del Tietar \u00c1vila 05429",
    "addr:postcode":"05429",
    "addr:street":"Calle De Gonzalo Del Rio S / N;A\u0301Vila",
    "iso:country":"ES",
    "sg:address":"Calle de Gonzalo Del Rio, S/n",
    "sg:city":"Santa Maria Del Tietar",
    "sg:orig_category":"Farmacias",
    "sg:phone":"+34 918 66 20 90",
    "sg:postcode":"05429",
    "sg:province":"\u00c1vila",
    "wof:name":"Gomez Hurtado Luis",
    "wof:placetype":"venue"
},
  "geometry": {"coordinates":[-97.78224945069999,45.7040786743],"type":"Point"}
}