{
  "type": "Feature",
  "properties": {
    "addr:full":"Rua Numancia, 52 Vigo Pontevedra 36206",
    "addr:housenumber":"52",
    "addr:postcode":"36206",
    "addr:street":"Rua Numancia",
    "iso:country":"ES",
    "sg:address":"Rua Numancia, 52",
    "sg:city":"Vigo",
    "sg:orig_category":"Guarder\u00cdas",
    "sg:phone":"+34 986 26 25 70",
    "sg:postcode":"36206",
    "sg:province":"Pontevedra",
    "wof:name":"Asociacion Educativa San Nicolas",
    "wof:placetype":"venue"
},
  "geometry": {"coordinates":[-8.7046365738,42.2339706421],"type":"Point"}
}