{
  "type": "Feature",
  "properties": {
    "iso:country":"ES",
    "sg:address":"Pla\u00c7 Benet Mercader, 1",
    "sg:city":"Bisbal D'emporda",
    "sg:orig_category":"Carnicer\u00cdas, Carnicer\u00cdas",
    "sg:phone":"+34 972 64 53 29",
    "sg:postcode":"17100",
    "sg:province":"Girona",
    "wof:name":"Mias Bonet Pedro",
    "wof:placetype":"venue"
},
  "geometry": {"coordinates":[3.0425977707,41.9439201355],"type":"Point"}
}