{
  "type": "Feature",
  "properties": {
    "iso:country":"ES",
    "sg:address":"C/ Ciutat De Barcelona, 46",
    "sg:city":"Paterna",
    "sg:orig_category":"Productos Qu\u00cdmicos (fabricaci\u00d3n, Al Por Mayor)",
    "sg:phone":"+34 961 32 14 62",
    "sg:postcode":"46988",
    "sg:province":"Valencia",
    "sg:website":"w.w.w.villaranquimica-sa.es",
    "wof:name":"Industrial Kern Espa\u00f1ola S.a.",
    "wof:placetype":"venue"
},
  "geometry": {"coordinates":[-0.4629589915,39.5087623596],"type":"Point"}
}