{
  "type": "Feature",
  "properties": {
    "addr:full":"Plaz Iglesia, S/n Cabezo Torres Murcia 30110",
    "addr:housenumber":"s / n",
    "addr:postcode":"30110",
    "addr:street":"Cabezo",
    "iso:country":"ES",
    "sg:address":"Plaz Iglesia, S/n",
    "sg:city":"Cabezo Torres",
    "sg:orig_category":"Iglesia Cat\u00d3lica",
    "sg:phone":"+34 968 83 10 09",
    "sg:postcode":"30110",
    "sg:province":"Murcia",
    "wof:name":"Parroquia Nuestra Se\u00f1ora De Las Lagrimas",
    "wof:placetype":"venue"
},
  "geometry": {"coordinates":[-1.1360189915,38.0214653015],"type":"Point"}
}