{
  "type": "Feature",
  "properties": {
    "addr:full":"Carrer de Amigo, 57 Barcelona Barcelona 08021",
    "addr:housenumber":"57",
    "addr:postcode":"08021",
    "addr:street":"Carrer De Amigo",
    "iso:country":"ES",
    "sg:address":"Carrer de Amigo, 57",
    "sg:city":"Barcelona",
    "sg:orig_category":"Producci\u00d3n, Distribuci\u00d3n De Electricidad",
    "sg:phone":"+34 932 00 43 23",
    "sg:postcode":"08021",
    "sg:province":"Barcelona",
    "wof:name":"Valls Rey Francesc",
    "wof:placetype":"venue"
},
  "geometry": {"coordinates":[2.143155098,41.396156311],"type":"Point"}
}