{
  "type": "Feature",
  "properties": {
    "addr:full":"Calle de Sancho Ramirez, 20 Huesca Huesca 22001",
    "addr:housenumber":"20",
    "addr:postcode":"22001",
    "addr:street":"Calle De Sancho Ramirez",
    "iso:country":"ES",
    "sg:address":"Calle de Sancho Ramirez, 20",
    "sg:city":"Huesca",
    "sg:orig_category":"Centros De Educaci\u00d3n Especial",
    "sg:phone":"+34 974 22 68 93",
    "sg:postcode":"22001",
    "sg:province":"Huesca",
    "wof:name":"Colegio Publico Sancho Ramirez Y Comedor",
    "wof:placetype":"venue"
},
  "geometry": {"coordinates":[-0.4050599933,42.1370239258],"type":"Point"}
}