{
  "type": "Feature",
  "properties": {
    "iso:country":"ES",
    "sg:address":"Carr Mig, 8",
    "sg:city":"Vilanova I La Geltru",
    "sg:orig_category":"Escultores, Estatuarios E Imagineros",
    "sg:phone":"+34 938 14 42 54",
    "sg:postcode":"08800",
    "sg:province":"Barcelona",
    "wof:name":"Porras Garcia Jose Luis",
    "wof:placetype":"venue"
},
  "geometry": {"coordinates":[1.7268999815,41.2211303711],"type":"Point"}
}