{
  "type": "Feature",
  "properties": {
    "addr:full":"Calle de Arcipreste De Hita, 18 Guadalajara Guadalajara 19001",
    "addr:housenumber":"18",
    "addr:postcode":"19001",
    "addr:street":"Calle De Arcipreste De Hita",
    "iso:country":"ES",
    "sg:address":"Calle de Arcipreste De Hita, 18",
    "sg:city":"Guadalajara",
    "sg:orig_category":"Plomeros",
    "sg:phone":"+34 949 23 24 06",
    "sg:postcode":"19001",
    "sg:province":"Guadalajara",
    "wof:name":"Jose Benito Barrasa Y Otro Cdad",
    "wof:placetype":"venue"
},
  "geometry": {"coordinates":[-3.1624851227,40.6322135925],"type":"Point"}
}