{
  "type": "Feature",
  "properties": {
    "addr:full":"B, 53 Santiago De Compostela La Coru\u00f1a 15890",
    "addr:housenumber":"53",
    "addr:postcode":"15890",
    "addr:street":"Corun\u0303A",
    "iso:country":"ES",
    "sg:address":"B, 53",
    "sg:city":"Santiago De Compostela",
    "sg:orig_category":"Electricidad: Equipos Industriales, Componentes (fabricaci\u00d3n)",
    "sg:phone":"+34 981 57 53 03",
    "sg:postcode":"15890",
    "sg:province":"La Coru\u00f1a",
    "wof:name":"Palmeiro S.l.",
    "wof:placetype":"venue"
},
  "geometry": {"coordinates":[-8.4769210815,42.8835983276],"type":"Point"}
}