{
  "type": "Feature",
  "properties": {
    "addr:full":"Calle de Cartagena, 39 Torre-pacheco Murcia 30700",
    "addr:housenumber":"39",
    "addr:postcode":"30700",
    "addr:street":"Calle De Cartagena",
    "iso:country":"ES",
    "sg:address":"Calle de Cartagena, 39",
    "sg:city":"Torre-pacheco",
    "sg:orig_category":"Carb\u00d3n, Carb\u00d3n De Madera (al Por Mayor)",
    "sg:phone":"+34 968 57 72 59",
    "sg:postcode":"30700",
    "sg:province":"Murcia",
    "wof:name":"Comercial Aljuvi S.l.",
    "wof:placetype":"venue"
},
  "geometry": {"coordinates":[-0.9532266259,37.7413101196],"type":"Point"}
}