{
  "type": "Feature",
  "properties": {
    "addr:full":"Sta. Marina Piedramuelle, S/n San Claudio Asturias 33191",
    "addr:housenumber":"s / n",
    "addr:postcode":"33191",
    "iso:country":"ES",
    "sg:address":"Sta. Marina Piedramuelle, S/n",
    "sg:city":"San Claudio",
    "sg:orig_category":"M\u00c9dicos: Ginecolog\u00cda Y Obstetricia",
    "sg:phone":"+34 985 78 12 57",
    "sg:postcode":"33191",
    "sg:province":"Asturias",
    "sg:website":"www.cefiva.com",
    "wof:name":"Fuente Ciruelas Pedro De La",
    "wof:placetype":"venue"
},
  "geometry": {"coordinates":[-5.9176192284,43.3596382141],"type":"Point"}
}