{
  "type": "Feature",
  "properties": {
    "iso:country":"ES",
    "sg:address":"Calle de Naranjo (el), 12",
    "sg:city":"Algeciras",
    "sg:orig_category":"Electrodom\u00c9sticos (al Por Menor)",
    "sg:phone":"+34 956 65 36 74",
    "sg:postcode":"11205",
    "sg:province":"C\u00e1diz",
    "wof:name":"Pe\u00f1a Vera Mario",
    "wof:placetype":"venue"
},
  "geometry": {"coordinates":[-5.4575791359,36.1516494751],"type":"Point"}
}