{
  "type": "Feature",
  "properties": {
    "iso:country":"ES",
    "sg:address":"Calle de Azcona, 16",
    "sg:city":"Madrid",
    "sg:orig_category":"Producci\u00d3n, Distribuci\u00d3n De Electricidad",
    "sg:phone":"+34 917 25 72 49",
    "sg:postcode":"28028",
    "sg:province":"Madrid",
    "wof:name":"Fernandez Almunia Jose Maria",
    "wof:placetype":"venue"
},
  "geometry": {"coordinates":[-3.6712436676,40.4333763123],"type":"Point"}
}