{
  "type": "Feature",
  "properties": {
    "iso:country":"ES",
    "sg:address":"Plaz Espa\u00d1a, 17",
    "sg:city":"Vezdemarban",
    "sg:orig_category":"Carnicer\u00cdas, Carnicer\u00cdas",
    "sg:phone":"+34 980 69 52 77",
    "sg:postcode":"49840",
    "sg:province":"Zamora",
    "wof:name":"Castro Fernandez Miguel De",
    "wof:placetype":"venue"
},
  "geometry": {"coordinates":[-5.3671221733,41.6539306641],"type":"Point"}
}