{
  "type": "Feature",
  "properties": {
    "addr:full":"Carrer de Constitucio, 108 Barcelona Barcelona 08014",
    "addr:housenumber":"108",
    "addr:postcode":"08014",
    "addr:street":"Carrer De Constitucio",
    "iso:country":"ES",
    "sg:address":"Carrer de Constitucio, 108",
    "sg:city":"Barcelona",
    "sg:orig_category":"Electricidad: Equipos Industriales, Componentes (fabricaci\u00d3n)",
    "sg:phone":"+34 933 32 49 41",
    "sg:postcode":"08014",
    "sg:province":"Barcelona",
    "wof:name":"Sanchez Monferrer Daniel",
    "wof:placetype":"venue"
},
  "geometry": {"coordinates":[2.1343948841,41.3696746826],"type":"Point"}
}