{
  "type": "Feature",
  "properties": {
    "addr:full":"Calle de Duero, 108 Bosque Madrid 28670",
    "addr:housenumber":"108",
    "addr:postcode":"28670",
    "addr:street":"Calle De Duero",
    "iso:country":"ES",
    "sg:address":"Calle de Duero, 108",
    "sg:city":"Bosque",
    "sg:orig_category":"Reparaciones Y Remolcado De Veh\u00cdculos",
    "sg:phone":"+34 916 16 84 94",
    "sg:postcode":"28670",
    "sg:province":"Madrid",
    "wof:name":"Gruas Barragan S.l.",
    "wof:placetype":"venue"
},
  "geometry": {"coordinates":[-3.9251554012,40.3996162415],"type":"Point"}
}