{
  "type": "Feature",
  "properties": {
    "iso:country":"ES",
    "sg:address":"Calle de Obispo Laplana, 2",
    "sg:city":"Zaragoza",
    "sg:orig_category":"M\u00c9dicos: Estomatolog\u00cda",
    "sg:phone":"+34 976 42 77 19",
    "sg:postcode":"50002",
    "sg:province":"Zaragoza",
    "wof:name":"Bescos Ferraz Mario",
    "wof:placetype":"venue"
},
  "geometry": {"coordinates":[-0.8629320264,41.645526886],"type":"Point"}
}