{
  "type": "Feature",
  "properties": {
    "addr:full":"Calle de Ca\u00d1adilla, 13 Nerva Huelva 21670",
    "addr:housenumber":"13",
    "addr:postcode":"21670",
    "addr:street":"Calle De Can\u0303Adilla",
    "iso:country":"ES",
    "sg:address":"Calle de Ca\u00d1adilla, 13",
    "sg:city":"Nerva",
    "sg:orig_category":"Agentes Generales De Seguros",
    "sg:phone":"+34 959 58 28 20",
    "sg:postcode":"21670",
    "sg:province":"Huelva",
    "wof:name":"Cirilo Fari\u00f1as Maria Del Rocio",
    "wof:placetype":"venue"
},
  "geometry": {"coordinates":[-6.5519652367,37.6958198547],"type":"Point"}
}