{
  "type": "Feature",
  "properties": {
    "addr:full":"Calle de Angel Guimera, 7 Valencia Valencia 46008",
    "addr:housenumber":"7",
    "addr:postcode":"46008",
    "addr:street":"Calle De Angel Guimera",
    "iso:country":"ES",
    "sg:address":"Calle de Angel Guimera, 7",
    "sg:city":"Valencia",
    "sg:orig_category":"Aparcamientos (infraestructuras, Accesorios)",
    "sg:phone":"+34 963 85 28 15",
    "sg:postcode":"46008",
    "sg:province":"Valencia",
    "wof:name":"Garaje Angel Guimera S.l.",
    "wof:placetype":"venue"
},
  "geometry": {"coordinates":[-0.3853183091,39.4703140259],"type":"Point"}
}