{
  "type": "Feature",
  "properties": {
    "iso:country":"ES",
    "sg:address":"Av Novelda, 69",
    "sg:city":"Elche",
    "sg:classifiers":[
        {
            "category":"Personal",
            "subcategory":"Barber",
            "type":"Services"
        }
    ],
    "sg:phone":"+34 965 46 34 72",
    "sg:postcode":"03205",
    "sg:province":"Alicante",
    "sg:tags":[
        "caballeros",
        "de",
        "peluqueros"
    ],
    "wof:name":"Martinez Toledo Manuel",
    "wof:placetype":"venue"
},
  "geometry": {"coordinates":[-0.7120410204,38.2734642029],"type":"Point"}
}