{
  "type": "Feature",
  "properties": {
    "addr:full":"Carrer de Francesc Macia, 156 Granollers Barcelona 08401",
    "addr:housenumber":"156",
    "addr:postcode":"08401",
    "addr:street":"Carrer De Francesc Macia",
    "iso:country":"ES",
    "sg:address":"Carrer de Francesc Macia, 156",
    "sg:city":"Granollers",
    "sg:orig_category":"Mec\u00c1nico Del Autom\u00d3vil",
    "sg:phone":"+34 938 79 23 17",
    "sg:postcode":"08401",
    "sg:province":"Barcelona",
    "wof:name":"Gestiones Prieto S.l.",
    "wof:placetype":"venue"
},
  "geometry": {"coordinates":[2.2867529392,41.5989494324],"type":"Point"}
}