{
  "type": "Feature",
  "properties": {
    "addr:full":"Avda Cedros, 40 Salamanca Salamanca 37004",
    "addr:housenumber":"40",
    "addr:postcode":"37004",
    "addr:street":"Avda Cedros",
    "iso:country":"ES",
    "sg:address":"Avda Cedros, 40",
    "sg:city":"Salamanca",
    "sg:orig_category":"Ropa Para Se\u00d1oras Y Caballeros (al Por Menor)",
    "sg:phone":"+34 923 25 66 53",
    "sg:postcode":"37004",
    "sg:province":"Salamanca",
    "wof:name":"Mayoral Berguio Maximiano",
    "wof:placetype":"venue"
},
  "geometry": {"coordinates":[-5.650454998,40.9743347168],"type":"Point"}
}