{
  "type": "Feature",
  "properties": {
    "iso:country":"ES",
    "sg:address":"Carrer de Negrevernis, 10",
    "sg:city":"Barcelona",
    "sg:orig_category":"Sales (al Por Mayor)",
    "sg:phone":"+34 932 80 01 54",
    "sg:postcode":"08034",
    "sg:province":"Barcelona",
    "wof:name":"Aliments Biologics S.l.",
    "wof:placetype":"venue"
},
  "geometry": {"coordinates":[2.1209936142,41.3991127014],"type":"Point"}
}