{
  "type": "Feature",
  "properties": {
    "addr:full":"Plaz Olmos (los), 2 Bara\u00f1ain Navarra 31010",
    "addr:postcode":"31010",
    "iso:country":"ES",
    "sg:address":"Plaz Olmos (los), 2",
    "sg:city":"Bara\u00f1ain",
    "sg:orig_category":"Manicuras",
    "sg:phone":"+34 948 26 00 62",
    "sg:postcode":"31010",
    "sg:province":"Navarra",
    "wof:name":"U\u00d1as Esculturadas Pili S.l.",
    "wof:placetype":"venue"
},
  "geometry": {"coordinates":[-97.78224945069999,45.7040786743],"type":"Point"}
}