{
  "type": "Feature",
  "properties": {
    "addr:full":"Gpo. Landazabal, 14 Atarrabia Navarra 31610",
    "addr:housenumber":"14",
    "addr:postcode":"31610",
    "addr:street":"Landazabal",
    "iso:country":"ES",
    "sg:address":"Gpo. Landazabal, 14",
    "sg:city":"Atarrabia",
    "sg:orig_category":"Agentes, Concesionarios Y Sucursales De Veh\u00cdculos",
    "sg:phone":"+34 948 14 40 70",
    "sg:postcode":"31610",
    "sg:province":"Navarra",
    "wof:name":"Tecnavarra S.a.",
    "wof:placetype":"venue"
},
  "geometry": {"coordinates":[-1.6155200005,42.8328285217],"type":"Point"}
}