{
  "type": "Feature",
  "properties": {
    "addr:full":"Carr Sant Vicent, 73 Benifaio Valencia 46450",
    "addr:housenumber":"73",
    "addr:postcode":"46450",
    "addr:street":"Carr Sant Vicent",
    "iso:country":"ES",
    "sg:address":"Carr Sant Vicent, 73",
    "sg:city":"Benifaio",
    "sg:orig_category":"Agencias Y Agentes Comerciales, Representantes",
    "sg:phone":"+34 961 79 46 15",
    "sg:postcode":"46450",
    "sg:province":"Valencia",
    "wof:name":"Duart Regal Concepcion",
    "wof:placetype":"venue"
},
  "geometry": {"coordinates":[-0.4275430143,39.2884635925],"type":"Point"}
}