{
  "type": "Feature",
  "properties": {
    "addr:full":"Rua Aduana (da), 6 San Cibrao Lugo 27890",
    "addr:postcode":"27890",
    "addr:street":"Rua Aduana Da 6 San Cibrao",
    "iso:country":"ES",
    "sg:address":"Rua Aduana (da), 6",
    "sg:city":"San Cibrao",
    "sg:orig_category":"Dibujantes (diversos)",
    "sg:phone":"+34 982 59 30 04",
    "sg:postcode":"27890",
    "sg:province":"Lugo",
    "wof:name":"Edyproga S.l.",
    "wof:placetype":"venue"
},
  "geometry": {"coordinates":[-7.4403162003,43.696395874],"type":"Point"}
}