{
  "type": "Feature",
  "properties": {
    "addr:full":"Calle de Apostol San Pedro, 7 Carpesa Valencia 46016",
    "addr:housenumber":"7",
    "addr:postcode":"46016",
    "addr:street":"Calle De Apostol San Pedro",
    "iso:country":"ES",
    "sg:address":"Calle de Apostol San Pedro, 7",
    "sg:city":"Carpesa",
    "sg:orig_category":"Reposter\u00cdas",
    "sg:phone":"+34 961 85 15 87",
    "sg:postcode":"46016",
    "sg:province":"Valencia",
    "wof:name":"Vicent Terrasa Maria Concepcion",
    "wof:placetype":"venue"
},
  "geometry": {"coordinates":[-0.378767997,39.5170860291],"type":"Point"}
}