{
  "type": "Feature",
  "properties": {
    "iso:country":"ES",
    "sg:address":"Calle de Rosa Bahamonde, 12",
    "sg:city":"Tui",
    "sg:orig_category":"Servicios De Telecomunicaciones",
    "sg:phone":"+34 986 60 31 79",
    "sg:postcode":"36700",
    "sg:province":"Pontevedra",
    "wof:name":"Comunicaciones Tuicom S.l.u.",
    "wof:placetype":"venue"
},
  "geometry": {"coordinates":[-8.6453351974,42.0481758118],"type":"Point"}
}