{
  "type": "Feature",
  "properties": {
    "addr:full":"Calle de Tenerias, 3 Villarrubia De Los Ojos Ciudad Real 13670",
    "addr:housenumber":"3",
    "addr:postcode":"13670",
    "addr:street":"Calle De Tenerias",
    "iso:country":"ES",
    "sg:address":"Calle de Tenerias, 3",
    "sg:city":"Villarrubia De Los Ojos",
    "sg:orig_category":"Ense\u00d1anza, Formaci\u00d3n Profesional: Aprendizaje",
    "sg:phone":"+34 926 89 65 62",
    "sg:postcode":"13670",
    "sg:province":"Ciudad Real",
    "wof:name":"Ayuntamiento De Villarrubia De Los Ojos.centro Social Polivalente",
    "wof:placetype":"venue"
},
  "geometry": {"coordinates":[-3.6082258224,39.2183494568],"type":"Point"}
}