{
  "type": "Feature",
  "properties": {
    "iso:country":"ES",
    "sg:address":"Calle de Gonzalez Garbin, 10",
    "sg:city":"Almeria",
    "sg:orig_category":"Inmobiliaria (agencias)",
    "sg:phone":"+34 950 24 58 08",
    "sg:postcode":"04001",
    "sg:province":"Almer\u00eda",
    "wof:name":"Frasagra S.l.",
    "wof:placetype":"venue"
},
  "geometry": {"coordinates":[-2.4623939991,36.8414916992],"type":"Point"}
}