{
  "type": "Feature",
  "properties": {
    "addr:full":"Calle de Reyes Magos, 10 Madrid Madrid 28009",
    "addr:housenumber":"10",
    "addr:postcode":"madrid;28009",
    "addr:street":"Calle De Reyes Magos",
    "iso:country":"ES",
    "sg:address":"Calle de Reyes Magos, 10",
    "sg:city":"Madrid",
    "sg:orig_category":"Asistencia Social",
    "sg:phone":"+34 915 04 09 98",
    "sg:postcode":"28009",
    "sg:province":"Madrid",
    "wof:name":"Asociacion Infantil Oncologica De La Comunidad De Madrid",
    "wof:placetype":"venue"
},
  "geometry": {"coordinates":[-3.6748971939,40.4112358093],"type":"Point"}
}