{
  "type": "Feature",
  "properties": {
    "addr:full":"Cno. Real, 294 Barranco De Las Lajas Santa Cruz De Tenerife 38355",
    "addr:housenumber":"294",
    "addr:postcode":"38355",
    "addr:street":"Cno. Real",
    "iso:country":"ES",
    "sg:address":"Cno. Real, 294",
    "sg:city":"Barranco De Las Lajas",
    "sg:orig_category":"Mec\u00c1nico Del Autom\u00d3vil",
    "sg:phone":"+34 922 56 73 47",
    "sg:postcode":"38355",
    "sg:province":"Santa Cruz De Tenerife",
    "sg:website":"www.mgson.net",
    "wof:name":"Delgado Darias Imma Yurena",
    "wof:placetype":"venue"
},
  "geometry": {"coordinates":[-16.4059047699,28.4648990631],"type":"Point"}
}