{
  "type": "Feature",
  "properties": {
    "iso:country":"ES",
    "sg:address":"Carrer de Huelva, 136",
    "sg:city":"Barcelona",
    "sg:orig_category":"T\u00c9cnicos Veterinarios",
    "sg:phone":"+34 933 13 61 08",
    "sg:postcode":"08020",
    "sg:province":"Barcelona",
    "wof:name":"Clinica Veterinaria La Verneda S.cv.",
    "wof:placetype":"venue"
},
  "geometry": {"coordinates":[2.2011198997,41.4209136963],"type":"Point"}
}