{
  "type": "Feature",
  "properties": {
    "iso:country":"ES",
    "sg:address":"Calle de Severo Ochoa, S/n",
    "sg:city":"Santomera",
    "sg:orig_category":"Droguer\u00cdas (al Por Menor)",
    "sg:phone":"+34 968 86 03 33",
    "sg:postcode":"30140",
    "sg:province":"Murcia",
    "wof:name":"Droguemur S.l.",
    "wof:placetype":"venue"
},
  "geometry": {"coordinates":[-1.0516840219,38.0632362366],"type":"Point"}
}