{
  "type": "Feature",
  "properties": {
    "iso:country":"ES",
    "sg:address":"Calle de Oca\u00d1a, 20",
    "sg:city":"Ejido",
    "sg:orig_category":"Contenedores (mercanc\u00cdas)",
    "sg:phone":"+34 950 48 05 02",
    "sg:postcode":"04700",
    "sg:province":"Almer\u00eda",
    "wof:name":"Lopez Martinez Francisco",
    "wof:placetype":"venue"
},
  "geometry": {"coordinates":[-2.8215100765,36.7662467957],"type":"Point"}
}