{
  "type": "Feature",
  "properties": {
    "iso:country":"ES",
    "sg:address":"Calle de Santa Teresa De Jesus, 70",
    "sg:city":"Talavera Reina",
    "sg:orig_category":"Contenedores (mercanc\u00cdas)",
    "sg:phone":"+34 925 82 53 03",
    "sg:postcode":"45600",
    "sg:province":"Toledo",
    "wof:name":"Oviedo Gomez Esteban",
    "wof:placetype":"venue"
},
  "geometry": {"coordinates":[-4.8273019791,39.9666290283],"type":"Point"}
}