{
  "type": "Feature",
  "properties": {
    "iso:country":"ES",
    "sg:address":"Calle de Rio Tormes, 15",
    "sg:city":"Mostoles",
    "sg:orig_category":"Empresas De Limpieza",
    "sg:phone":"+34 916 45 71 11",
    "sg:postcode":"28935",
    "sg:province":"Madrid",
    "wof:name":"Limpieza Tecnica Especializada S.l.",
    "wof:placetype":"venue"
},
  "geometry": {"coordinates":[-3.8774516582,40.316947937],"type":"Point"}
}