{
  "type": "Feature",
  "properties": {
    "iso:country":"ES",
    "sg:address":"C\u00f1da. Covatilla, S/n",
    "sg:city":"Arganda",
    "sg:orig_category":"Producci\u00d3n De Champi\u00d1ones",
    "sg:phone":"+34 918 71 90 18",
    "sg:postcode":"28500",
    "sg:province":"Madrid",
    "wof:name":"Pla Micelios S.a.t.",
    "wof:placetype":"venue"
},
  "geometry": {"coordinates":[-3.4406979084,40.2999954224],"type":"Point"}
}