{
  "type": "Feature",
  "properties": {
    "iso:country":"ES",
    "sg:address":"Carr Caritat, 83",
    "sg:city":"Igualada",
    "sg:orig_category":"Cueros Y Pieles (al Por Mayor)",
    "sg:phone":"+34 938 04 11 61",
    "sg:postcode":"08700",
    "sg:province":"Barcelona",
    "wof:name":"Dernova S.a.",
    "wof:placetype":"venue"
},
  "geometry": {"coordinates":[1.6232140064,41.5769042969],"type":"Point"}
}