{
  "type": "Feature",
  "properties": {
    "addr:full":"Carrer de Canonge Pibernat, 23 Barcelona Barcelona 08028",
    "addr:housenumber":"23",
    "addr:postcode":"08028",
    "addr:street":"Carrer De Canonge Pibernat",
    "iso:country":"ES",
    "sg:address":"Carrer de Canonge Pibernat, 23",
    "sg:city":"Barcelona",
    "sg:orig_category":"Promotores Constructores",
    "sg:phone":"+34 934 11 11 94",
    "sg:postcode":"08028",
    "sg:province":"Barcelona",
    "wof:name":"Rehabilitacions J S.c.p.",
    "wof:placetype":"venue"
},
  "geometry": {"coordinates":[2.1291790009,41.3764038086],"type":"Point"}
}