{
  "type": "Feature",
  "properties": {
    "iso:country":"ES",
    "sg:address":"Rua Emilia Pardo Bazan, 4",
    "sg:city":"Celanova",
    "sg:orig_category":"Caf\u00c9s, Bares, Cervecer\u00cdas",
    "sg:phone":"+34 988 45 11 92",
    "sg:postcode":"32800",
    "sg:province":"Ourense",
    "wof:name":"Cafe Londres C.b.",
    "wof:placetype":"venue"
},
  "geometry": {"coordinates":[-7.9575629234,42.1525421143],"type":"Point"}
}