{
  "type": "Feature",
  "properties": {
    "iso:country":"ES",
    "sg:address":"Carrer de Maracaibo, 13",
    "sg:city":"Barcelona",
    "sg:orig_category":"Tratamiento De Metales",
    "sg:phone":"+34 933 46 14 55",
    "sg:postcode":"08030",
    "sg:province":"Barcelona",
    "wof:name":"Argent 2000 S.l.",
    "wof:placetype":"venue"
},
  "geometry": {"coordinates":[2.2046432495,41.4421272278],"type":"Point"}
}