{
  "type": "Feature",
  "properties": {
    "iso:country":"ES",
    "sg:address":"Calle de Zaragoza, 13",
    "sg:city":"Pedrola",
    "sg:orig_category":"Asilos De Ancianos. Centros Privados",
    "sg:phone":"+34 976 61 91 92",
    "sg:postcode":"50690",
    "sg:province":"Zaragoza",
    "wof:name":"Asociacion De Jubilados Y Pensionistas Antonio Zenon Almau",
    "wof:placetype":"venue"
},
  "geometry": {"coordinates":[-1.2166856527,41.78698349],"type":"Point"}
}