{
  "type": "Feature",
  "properties": {
    "iso:country":"ES",
    "sg:address":"Ctra Alicante-valencia, 332",
    "sg:city":"Gata Gorgos",
    "sg:orig_category":"Papeler\u00cdas, Librer\u00cdas",
    "sg:phone":"+34 965 75 76 73",
    "sg:postcode":"03740",
    "sg:province":"Alicante",
    "wof:name":"Berndsen  Gunter Josef",
    "wof:placetype":"venue"
},
  "geometry": {"coordinates":[0.0839079991,38.7759056091],"type":"Point"}
}