{
  "type": "Feature",
  "properties": {
    "addr:full":"Plaz Constitucion (iriepal), S/n Iriepal Guadalajara 19150",
    "addr:postcode":"19150",
    "addr:street":"Iriepal S / N Iriepal",
    "iso:country":"ES",
    "sg:address":"Plaz Constitucion (iriepal), S/n",
    "sg:city":"Iriepal",
    "sg:orig_category":"Centros De Educaci\u00d3n Especial",
    "sg:phone":"+34 949 22 84 27",
    "sg:postcode":"19150",
    "sg:province":"Guadalajara",
    "wof:name":"Colegio Rural Agrupado De Iriepal",
    "wof:placetype":"venue"
},
  "geometry": {"coordinates":[-3.1216239929,40.6374359131],"type":"Point"}
}