{
  "type": "Feature",
  "properties": {
    "iso:country":"ES",
    "sg:address":"Pg Isabel Ii, 2",
    "sg:city":"Barcelona",
    "sg:orig_category":"Agencias Y Asesores De Publicidad",
    "sg:phone":"+34 933 10 62 00",
    "sg:postcode":"08003",
    "sg:province":"Barcelona",
    "wof:name":"Equip Reset Sociedad Limitada",
    "wof:placetype":"venue"
},
  "geometry": {"coordinates":[2.1825349331,41.3813056946],"type":"Point"}
}