{
  "type": "Feature",
  "properties": {
    "addr:full":"Calle de Mayor, 45 Bu\u00f1uel Navarra 31540",
    "addr:housenumber":"45",
    "addr:postcode":"31540",
    "addr:street":"Calle De Mayor",
    "iso:country":"ES",
    "sg:address":"Calle de Mayor, 45",
    "sg:city":"Bu\u00f1uel",
    "sg:orig_category":"Confiter\u00cdas, Chocolater\u00cdas (al Por Menor)",
    "sg:phone":"+34 948 83 33 00",
    "sg:postcode":"31540",
    "sg:province":"Navarra",
    "wof:name":"Miranda Garcia Maria Gracia",
    "wof:placetype":"venue"
},
  "geometry": {"coordinates":[-1.4451860189,41.9813766479],"type":"Point"}
}