{
  "type": "Feature",
  "properties": {
    "iso:country":"ES",
    "sg:address":"Carrer de Migdia, 12",
    "sg:city":"Llagostera",
    "sg:orig_category":"Peluqueros: De Se\u00d1oras",
    "sg:phone":"+34 972 83 00 79",
    "sg:postcode":"17240",
    "sg:province":"Girona",
    "wof:name":"Ciurana Comas Ana Maria",
    "wof:placetype":"venue"
},
  "geometry": {"coordinates":[2.8926079273,41.8270874023],"type":"Point"}
}