{
  "type": "Feature",
  "properties": {
    "addr:full":"Carrer de Comte D'urgell, 111 Barcelona Barcelona 08011",
    "addr:housenumber":"111",
    "addr:postcode":"08011",
    "addr:street":"Carrer De Comte D'Urgell",
    "iso:country":"ES",
    "sg:address":"Carrer de Comte D'urgell, 111",
    "sg:city":"Barcelona",
    "sg:orig_category":"Florister\u00cdas",
    "sg:phone":"+34 933 23 91 78",
    "sg:postcode":"08011",
    "sg:province":"Barcelona",
    "wof:name":"Marquez Ruiz Maria Concepcion",
    "wof:placetype":"venue"
},
  "geometry": {"coordinates":[2.155112505,41.3847389221],"type":"Point"}
}