{
  "type": "Feature",
  "properties": {
    "iso:country":"ES",
    "sg:address":"Estd A Portela, 11",
    "sg:city":"Redondela",
    "sg:orig_category":"Pescader\u00cdas (al Por Mayor)",
    "sg:phone":"+34 986 40 13 58",
    "sg:postcode":"36800",
    "sg:province":"Pontevedra",
    "wof:name":"Otero Reguera Raul",
    "wof:placetype":"venue"
},
  "geometry": {"coordinates":[-8.6090641022,42.2820243835],"type":"Point"}
}