{
  "type": "Feature",
  "properties": {
    "addr:full":"Pla\u00c7 Dolors, S/n Torroella Montgri Girona 17257",
    "addr:housenumber":"s / n",
    "addr:postcode":"17257",
    "iso:country":"ES",
    "sg:address":"Pla\u00c7 Dolors, S/n",
    "sg:city":"Torroella Montgri",
    "sg:orig_category":"Supermercados Y Hipermercados",
    "sg:phone":"+34 972 75 86 55",
    "sg:postcode":"17257",
    "sg:province":"Girona",
    "wof:name":"Miquel Alimentacio Grup S.a.",
    "wof:placetype":"venue"
},
  "geometry": {"coordinates":[3.1034500599,42.0303268433],"type":"Point"}
}