{
  "type": "Feature",
  "properties": {
    "addr:full":"Pl. Abastos, 4 Azuaga Badajoz 06920",
    "addr:housenumber":"4",
    "addr:postcode":"06920",
    "addr:street":"Abastos",
    "iso:country":"ES",
    "sg:address":"Pl. Abastos, 4",
    "sg:city":"Azuaga",
    "sg:orig_category":"Pescader\u00cdas (al Por Menor)",
    "sg:phone":"+34 924 89 11 92",
    "sg:postcode":"06920",
    "sg:province":"Badajoz",
    "wof:name":"Murillo Manchon Pedro",
    "wof:placetype":"venue"
},
  "geometry": {"coordinates":[-5.6808290482,38.2573204041],"type":"Point"}
}