{
  "type": "Feature",
  "properties": {
    "addr:full":"Rbla Jaume I, 58 Cambrils Tarragona 43850",
    "addr:housenumber":"58",
    "addr:postcode":"43850",
    "addr:street":"Rbla Jaume I",
    "iso:country":"ES",
    "sg:address":"Rbla Jaume I, 58",
    "sg:city":"Cambrils",
    "sg:orig_category":"Asesor\u00cda De Formaci\u00d3n Y Gesti\u00d3n De Personal",
    "sg:phone":"+34 977 36 42 91",
    "sg:postcode":"43850",
    "sg:province":"Tarragona",
    "wof:name":"Gabinet D'assesoria Cambrils S.l.",
    "wof:placetype":"venue"
},
  "geometry": {"coordinates":[1.0608290434,41.0672264099],"type":"Point"}
}