{
  "type": "Feature",
  "properties": {
    "addr:full":"Calle de Rey, 32 Plasencia C\u00e1ceres 10600",
    "addr:housenumber":"32",
    "addr:postcode":"10600",
    "addr:street":"Calle De Rey;Ca\u0301Ceres",
    "iso:country":"ES",
    "sg:address":"Calle de Rey, 32",
    "sg:city":"Plasencia",
    "sg:orig_category":"Peluqueros: De Se\u00d1oras",
    "sg:phone":"+34 927 41 36 82",
    "sg:postcode":"10600",
    "sg:province":"C\u00e1ceres",
    "wof:name":"Famagar Luis S.l.",
    "wof:placetype":"venue"
},
  "geometry": {"coordinates":[-6.0888500214,40.030834198],"type":"Point"}
}