{
  "type": "Feature",
  "properties": {
    "iso:country":"ES",
    "sg:address":"Juan Carlos Guerra Plaza, 2",
    "sg:city":"Arrasate",
    "sg:orig_category":"Lencer\u00cda Femenina, Corseter\u00cda, Trajes De Ba\u00d1o (al Por Menor)",
    "sg:phone":"+34 943 79 87 95",
    "sg:postcode":"20500",
    "sg:province":"Guip\u00f9zcoa",
    "wof:name":"Alonso Casado Angel",
    "wof:placetype":"venue"
},
  "geometry": {"coordinates":[-2.489582777,43.0666923523],"type":"Point"}
}