{
  "type": "Feature",
  "properties": {
    "addr:full":"Calle de Rios Rosas, 55 Madrid Madrid 28003",
    "addr:housenumber":"55",
    "addr:postcode":"madrid;28003",
    "addr:street":"Calle De Rios Rosas",
    "iso:country":"ES",
    "sg:address":"Calle de Rios Rosas, 55",
    "sg:city":"Madrid",
    "sg:orig_category":"Prendas De Cuero Y De Piel (al Por Menor)",
    "sg:phone":"+34 915 36 35 71",
    "sg:postcode":"28003",
    "sg:province":"Madrid",
    "wof:name":"Raquel Esclar S.l.",
    "wof:placetype":"venue"
},
  "geometry": {"coordinates":[-3.6962270737,40.4418830872],"type":"Point"}
}