{
  "type": "Feature",
  "properties": {
    "iso:country":"ES",
    "sg:address":"Avda Maragatos, 41",
    "sg:city":"Benavente",
    "sg:orig_category":"Venta, Montaje De Neum\u00c1ticos",
    "sg:phone":"+34 980 63 44 97",
    "sg:postcode":"49600",
    "sg:province":"Zamora",
    "wof:name":"Boyano Nistal Rogelio Jose",
    "wof:placetype":"venue"
},
  "geometry": {"coordinates":[-5.6763868332,42.0090713501],"type":"Point"}
}