{
  "type": "Feature",
  "properties": {
    "addr:full":"Calle de Ramon Franco, 28 Calvario Pontevedra 36770",
    "addr:housenumber":"28",
    "addr:postcode":"36770",
    "addr:street":"Calle De Ramon Franco",
    "iso:country":"ES",
    "sg:address":"Calle de Ramon Franco, 28",
    "sg:city":"Calvario",
    "sg:orig_category":"Librer\u00cdas",
    "sg:phone":"+34 986 62 60 48",
    "sg:postcode":"36770",
    "sg:province":"Pontevedra",
    "wof:name":"Papeleria Colores O Rosal C.b",
    "wof:placetype":"venue"
},
  "geometry": {"coordinates":[-8.8362493515,41.9370346069],"type":"Point"}
}