{
  "type": "Feature",
  "properties": {
    "iso:country":"ES",
    "sg:address":"Calle de Dos De Mayo, 5",
    "sg:city":"Miranda Ebro",
    "sg:orig_category":"Arquitectos",
    "sg:phone":"+34 947 31 42 04",
    "sg:postcode":"09200",
    "sg:province":"Burgos",
    "wof:name":"Gonzalez Rebollo Felix",
    "wof:placetype":"venue"
},
  "geometry": {"coordinates":[-2.9529466629,42.686580658],"type":"Point"}
}