{
  "type": "Feature",
  "properties": {
    "addr:full":"Calle de Repulles Y Vargas, 3 Madrid Madrid 28011",
    "addr:housenumber":"3",
    "addr:postcode":"28011",
    "addr:street":"Calle De Repulles Y Vargas",
    "iso:country":"ES",
    "sg:address":"Calle de Repulles Y Vargas, 3",
    "sg:city":"Madrid",
    "sg:orig_category":"Peluquer\u00cdas, Peluquer\u00cda Mixta",
    "sg:phone":"+34 914 63 26 80",
    "sg:postcode":"28011",
    "sg:province":"Madrid",
    "wof:name":"Naranjo Marmol Manuel",
    "wof:placetype":"venue"
},
  "geometry": {"coordinates":[-3.7346110344,40.4107971191],"type":"Point"}
}