{
  "type": "Feature",
  "properties": {
    "iso:country":"ES",
    "sg:address":"Ctra. Nal. 340, Km. 0203,0",
    "sg:city":"Alberic",
    "sg:orig_category":"Molduras, Junquillos, Listones Y Molduras Perforadas",
    "sg:phone":"+34 962 44 36 93",
    "sg:postcode":"46260",
    "sg:province":"Valencia",
    "wof:name":"Pla Climent Dolores",
    "wof:placetype":"venue"
},
  "geometry": {"coordinates":[-0.520138979,39.11901474],"type":"Point"}
}