{
  "type": "Feature",
  "properties": {
    "iso:country":"ES",
    "sg:address":"Poli Elvi\u00d1a 2 Fase Alcalde Molina Edificio, S/n",
    "sg:city":"Coru\u00d1a",
    "sg:orig_category":"Asociaciones Y Clubs Deportivos",
    "sg:phone":"+34 981 13 23 62",
    "sg:postcode":"15008",
    "sg:province":"La Coru\u00f1a",
    "wof:name":"Asociacion De Futbol De Veteranos",
    "wof:placetype":"venue"
},
  "geometry": {"coordinates":[-8.4129400253,43.3328208923],"type":"Point"}
}