{
  "type": "Feature",
  "properties": {
    "addr:full":"Carrer de Dos De Maig, 207 Barcelona Barcelona 08013",
    "addr:housenumber":"207",
    "addr:postcode":"08013",
    "addr:street":"Carrer De Dos De Maig",
    "iso:country":"ES",
    "sg:address":"Carrer de Dos De Maig, 207",
    "sg:city":"Barcelona",
    "sg:orig_category":"Compraventa De Antig\u00dcedades",
    "sg:phone":"+34 932 65 50 55",
    "sg:postcode":"08013",
    "sg:province":"Barcelona",
    "wof:name":"Pujades Sarries Jordi",
    "wof:placetype":"venue"
},
  "geometry": {"coordinates":[2.1839060783,41.4054679871],"type":"Point"}
}