{
  "type": "Feature",
  "properties": {
    "addr:full":"Av Catalunya, S/n Mont-roig Camp Tarragona 43300",
    "addr:housenumber":"s / n",
    "addr:postcode":"43300",
    "addr:street":"Av Catalunya;Mont-Roig",
    "iso:country":"ES",
    "sg:address":"Av Catalunya, S/n",
    "sg:city":"Mont-roig Camp",
    "sg:orig_category":"Mec\u00c1nico Del Autom\u00d3vil",
    "sg:phone":"+34 977 83 71 42",
    "sg:postcode":"43300",
    "sg:province":"Tarragona",
    "wof:name":"Duch Llorens Jose Maria",
    "wof:placetype":"venue"
},
  "geometry": {"coordinates":[0.9615100026,41.0856895447],"type":"Point"}
}