{
  "type": "Feature",
  "properties": {
    "addr:full":"Av Josep Tarradellas I Joan, 168 Hospitalet Llobregat Barcelona 08901",
    "addr:housenumber":"168",
    "addr:postcode":"08901",
    "addr:street":"Av Josep Tarradellas I Joan",
    "iso:country":"ES",
    "sg:address":"Av Josep Tarradellas I Joan, 168",
    "sg:city":"Hospitalet Llobregat",
    "sg:orig_category":"Pescader\u00cdas (al Por Menor)",
    "sg:phone":"+34 933 37 73 60",
    "sg:postcode":"08901",
    "sg:province":"Barcelona",
    "wof:name":"Vituri Martin Marcos",
    "wof:placetype":"venue"
},
  "geometry": {"coordinates":[2.1062684059,41.3639030457],"type":"Point"}
}