{
  "type": "Feature",
  "properties": {
    "iso:country":"ES",
    "sg:address":"Calle de Martires, 14",
    "sg:city":"Torrelavega",
    "sg:orig_category":"M\u00c9dicos: An\u00c1lisis Cl\u00cdnicos",
    "sg:phone":"+34 942 80 09 01",
    "sg:postcode":"39300",
    "sg:province":"Cantabria",
    "wof:name":"Diaz Rodriguez Carlos",
    "wof:placetype":"venue"
},
  "geometry": {"coordinates":[-4.0480918884,43.3523101807],"type":"Point"}
}