{
  "type": "Feature",
  "properties": {
    "iso:country":"ES",
    "sg:address":"Av Madrid, 150",
    "sg:city":"Barcelona",
    "sg:orig_category":"Muebles, Minoristas",
    "sg:phone":"+34 933 39 40 04",
    "sg:postcode":"08028",
    "sg:province":"Barcelona",
    "wof:name":"Carrasco Padilla Juan Jose",
    "wof:placetype":"venue"
},
  "geometry": {"coordinates":[2.1305549145,41.3799476624],"type":"Point"}
}