{
  "type": "Feature",
  "properties": {
    "addr:full":"Calle de Gallegos, 14 Pedrajas S. Esteban Valladolid 47430",
    "addr:housenumber":"14",
    "addr:postcode":"47430",
    "addr:street":"Calle De Gallegos;Pedrajas S. Esteban Valladolid",
    "iso:country":"ES",
    "sg:address":"Calle de Gallegos, 14",
    "sg:city":"Pedrajas S. Esteban",
    "sg:orig_category":"Ropa Para Se\u00d1oras (al Por Menor)",
    "sg:phone":"+34 983 62 57 21",
    "sg:postcode":"47430",
    "sg:province":"Valladolid",
    "wof:name":"Fernandez Soria Jaime",
    "wof:placetype":"venue"
},
  "geometry": {"coordinates":[-4.5834755898,41.3438796997],"type":"Point"}
}