{
  "type": "Feature",
  "properties": {
    "iso:country":"ES",
    "sg:address":"Av Sant Miquel Del Pui, 18",
    "sg:city":"Pobla Segur",
    "sg:orig_category":"Molduras, Junquillos, Listones Y Molduras Perforadas",
    "sg:phone":"+34 973 66 01 44",
    "sg:postcode":"25500",
    "sg:province":"Lleida",
    "wof:name":"Espinosa Burgos Maria Soledad",
    "wof:placetype":"venue"
},
  "geometry": {"coordinates":[0.9670670033,42.2481002808],"type":"Point"}
}