{
  "type": "Feature",
  "properties": {
    "addr:full":"Calle de Italia, 33 Alacant Alicante 03003",
    "addr:housenumber":"33",
    "addr:postcode":"03003",
    "addr:street":"Calle De Italia",
    "iso:country":"ES",
    "sg:address":"Calle de Italia, 33",
    "sg:city":"Alacant",
    "sg:orig_category":"Alquiler De V\u00cddeo",
    "sg:phone":"+34 965 12 67 94",
    "sg:postcode":"03003",
    "sg:province":"Alicante",
    "wof:name":"Gestion Del Video 10 S.l.",
    "wof:placetype":"venue"
},
  "geometry": {"coordinates":[-0.4915330112,38.3401451111],"type":"Point"}
}