{
  "type": "Feature",
  "properties": {
    "addr:full":"Calle de Aries, 41 Caceres C\u00e1ceres 10001",
    "addr:housenumber":"41",
    "addr:postcode":"10001",
    "addr:street":"Calle De Aries;Ca\u0301Ceres",
    "iso:country":"ES",
    "sg:address":"Calle de Aries, 41",
    "sg:city":"Caceres",
    "sg:orig_category":"Transportes Por V\u00cdas Navegables",
    "sg:phone":"+34 927 23 10 01",
    "sg:postcode":"10001",
    "sg:province":"C\u00e1ceres",
    "wof:name":"Guzman Torre\u00f1o Felipe",
    "wof:placetype":"venue"
},
  "geometry": {"coordinates":[-6.3946728706,39.4771537781],"type":"Point"}
}