{
  "type": "Feature",
  "properties": {
    "addr:full":"Calle de Pablo Iglesias, 25 Elda Alicante 03600",
    "addr:housenumber":"25",
    "addr:postcode":"03600",
    "addr:street":"Calle De Pablo Iglesias",
    "iso:country":"ES",
    "sg:address":"Calle de Pablo Iglesias, 25",
    "sg:city":"Elda",
    "sg:orig_category":"Agencias Y Agentes Comerciales, Representantes",
    "sg:phone":"+34 965 39 54 03",
    "sg:postcode":"03600",
    "sg:province":"Alicante",
    "wof:name":"Marina Marco S.l.",
    "wof:placetype":"venue"
},
  "geometry": {"coordinates":[-0.7867940068,38.4764442444],"type":"Point"}
}