{
  "type": "Feature",
  "properties": {
    "iso:country":"ES",
    "sg:address":"Calle de Nuestra Se\u00d1ora De La Oliva, 19",
    "sg:city":"Vejer De La Frontera",
    "sg:orig_category":"Inmobiliaria (agencias)",
    "sg:phone":"+34 956 45 10 82",
    "sg:postcode":"11150",
    "sg:province":"C\u00e1diz",
    "sg:website":"www.lasegur.com",
    "wof:name":"Miralles Romero Juan Carlos",
    "wof:placetype":"venue"
},
  "geometry": {"coordinates":[-5.9647288322,36.2539215088],"type":"Point"}
}