{
  "type": "Feature",
  "properties": {
    "iso:country":"ES",
    "sg:address":"Ctra Tomelloso, Km. 0004,2",
    "sg:city":"Villarrobledo",
    "sg:orig_category":"Armer\u00cdas",
    "sg:phone":"+34 967 57 30 58",
    "sg:postcode":"02600",
    "sg:province":"Albacete",
    "wof:name":"Frevo S.a.l.",
    "wof:placetype":"venue"
},
  "geometry": {"coordinates":[-0.6567689776,38.0584983826],"type":"Point"}
}