{
  "type": "Feature",
  "properties": {
    "iso:country":"ES",
    "sg:address":"Av Juan Gil - Albert, 3",
    "sg:city":"Alcoi",
    "sg:orig_category":"Alquiler De V\u00cddeo",
    "sg:phone":"+34 965 52 59 07",
    "sg:postcode":"03804",
    "sg:province":"Alicante",
    "sg:website":"www.galaxia-video.com",
    "wof:name":"Alsu Vision S.l.",
    "wof:placetype":"venue"
},
  "geometry": {"coordinates":[-0.4737715125,38.7050819397],"type":"Point"}
}