{
  "type": "Feature",
  "properties": {
    "iso:country":"ES",
    "sg:address":"Calle de Rosario Creixach, 20",
    "sg:city":"Vall D'uixo",
    "sg:orig_category":"Asesor\u00cda Fiscal Y Jur\u00cddica",
    "sg:phone":"+34 964 66 41 82",
    "sg:postcode":"12600",
    "sg:province":"Castell\u00f3n",
    "wof:name":"Ager Asesores S.l.",
    "wof:placetype":"venue"
},
  "geometry": {"coordinates":[-0.2338730991,39.8219032288],"type":"Point"}
}