{
  "type": "Feature",
  "properties": {
    "addr:full":"Calle de Maestro Giner, 53 Vall D'uixo Castell\u00f3n 12600",
    "addr:housenumber":"53",
    "addr:postcode":"12600",
    "addr:street":"Calle De Maestro Giner",
    "iso:country":"ES",
    "sg:address":"Calle de Maestro Giner, 53",
    "sg:city":"Vall D'uixo",
    "sg:orig_category":"Plomeros",
    "sg:phone":"+34 964 66 15 34",
    "sg:postcode":"12600",
    "sg:province":"Castell\u00f3n",
    "wof:name":"Leger Rubio,maria Remedios",
    "wof:placetype":"venue"
},
  "geometry": {"coordinates":[-0.0453969985,39.9904518127],"type":"Point"}
}