{
  "type": "Feature",
  "properties": {
    "iso:country":"ES",
    "sg:address":"Calle de Telefonica, 10",
    "sg:city":"Olivos-la Postura",
    "sg:orig_category":"Asesor\u00cda De Formaci\u00d3n Y Gesti\u00d3n De Personal",
    "sg:phone":"+34 922 71 06 50",
    "sg:postcode":"38670",
    "sg:province":"Santa Cruz De Tenerife",
    "wof:name":"Rodriguez Alvarez Francisco",
    "wof:placetype":"venue"
},
  "geometry": {"coordinates":[-16.7319164276,28.1201953888],"type":"Point"}
}