{
  "type": "Feature",
  "properties": {
    "addr:full":"S. Del Corral, 31 Huetor-tajar Granada 18360",
    "addr:housenumber":"31",
    "addr:postcode":"18360",
    "addr:street":"S. Del Corral",
    "iso:country":"ES",
    "sg:address":"S. Del Corral, 31",
    "sg:city":"Huetor-tajar",
    "sg:orig_category":"Centros Empresariales",
    "sg:phone":"+34 958 33 36 66",
    "sg:postcode":"18360",
    "sg:province":"Granada",
    "wof:name":"Laredo Romero Rosa Ana",
    "wof:placetype":"venue"
},
  "geometry": {"coordinates":[-4.046749115,37.1978111267],"type":"Point"}
}