{
  "type": "Feature",
  "properties": {
    "addr:full":"Calle de Hermanos Granda, 10 Pola De Lena Asturias 33630",
    "addr:housenumber":"10",
    "addr:postcode":"33630",
    "addr:street":"Calle De Hermanos Granda",
    "iso:country":"ES",
    "sg:address":"Calle de Hermanos Granda, 10",
    "sg:city":"Pola De Lena",
    "sg:orig_category":"Comunidades Religiosas",
    "sg:phone":"+34 985 49 01 91",
    "sg:postcode":"33630",
    "sg:province":"Asturias",
    "wof:name":"Compa\u00f1ia De Maria",
    "wof:placetype":"venue"
},
  "geometry": {"coordinates":[-5.829624176,43.165813446],"type":"Point"}
}