{
  "type": "Feature",
  "properties": {
    "iso:country":"ES",
    "sg:address":"Calle de Fray Luis De Leon, 4",
    "sg:city":"Palma",
    "sg:orig_category":"Peluqueros: De Se\u00d1oras",
    "sg:phone":"+34 971 45 78 02",
    "sg:postcode":"07011",
    "sg:province":"Islas Baleares",
    "wof:name":"Abraham Sampol Miguel",
    "wof:placetype":"venue"
},
  "geometry": {"coordinates":[2.641156,39.573605],"type":"Point"}
}