{
  "type": "Feature",
  "properties": {
    "iso:country":"ES",
    "sg:address":"Calle de Santa Engracia, 105",
    "sg:city":"Madrid",
    "sg:orig_category":"Moda",
    "sg:phone":"+34 914 46 27 93",
    "sg:postcode":"28010",
    "sg:province":"Madrid",
    "sg:website":"www.srchque.com",
    "wof:name":"Se\u00f1or Chaque S.l.",
    "wof:placetype":"venue"
},
  "geometry": {"coordinates":[-3.6997919083,40.4369621277],"type":"Point"}
}