{
  "type": "Feature",
  "properties": {
    "iso:country":"ES",
    "sg:address":"Calle de Isla La, 4",
    "sg:city":"Pola De Siero",
    "sg:orig_category":"Caf\u00c9s, Bares, Cervecer\u00cdas",
    "sg:phone":"+34 985 72 53 25",
    "sg:postcode":"33510",
    "sg:province":"Asturias",
    "wof:name":"Ruiz Diaz Yolanda",
    "wof:placetype":"venue"
},
  "geometry": {"coordinates":[-5.664604187,43.3888816833],"type":"Point"}
}