{
  "type": "Feature",
  "properties": {
    "addr:full":"Calle de Ponzano, 80 Madrid Madrid 28003",
    "addr:housenumber":"80",
    "addr:postcode":"madrid;28003",
    "addr:street":"Calle De Ponzano",
    "iso:country":"ES",
    "sg:address":"Calle de Ponzano, 80",
    "sg:city":"Madrid",
    "sg:orig_category":"Librer\u00cdas",
    "sg:phone":"+34 915 35 83 76",
    "sg:postcode":"28003",
    "sg:province":"Madrid",
    "wof:name":"Zambhala C.b",
    "wof:placetype":"venue"
},
  "geometry": {"coordinates":[-3.6988236904,40.4445533752],"type":"Point"}
}