{
  "type": "Feature",
  "properties": {
    "iso:country":"ES",
    "sg:address":"Rua Francisco Castello, 24",
    "sg:city":"Carballi\u00f1o",
    "sg:orig_category":"Electricidad: Instaladores",
    "sg:phone":"+34 988 27 16 92",
    "sg:postcode":"32500",
    "sg:province":"Ourense",
    "wof:name":"Diaz Gonzalez Ramon",
    "wof:placetype":"venue"
},
  "geometry": {"coordinates":[-8.075419426,42.4338302612],"type":"Point"}
}