{
  "type": "Feature",
  "properties": {
    "addr:full":"Calle de General Ricardos, 28 Barbastro Huesca 22300",
    "addr:housenumber":"28",
    "addr:postcode":"22300",
    "addr:street":"Calle De General Ricardos",
    "iso:country":"ES",
    "sg:address":"Calle de General Ricardos, 28",
    "sg:city":"Barbastro",
    "sg:orig_category":"Organizaciones Internacionales",
    "sg:phone":"+34 974 31 56 14",
    "sg:postcode":"22300",
    "sg:province":"Huesca",
    "sg:website":"www.manosunidas.org",
    "wof:name":"Manos Unidas Campa\u00f1a Contra El Hambre",
    "wof:placetype":"venue"
},
  "geometry": {"coordinates":[0.1242370009,42.0354156494],"type":"Point"}
}