{
  "type": "Feature",
  "properties": {
    "iso:country":"ES",
    "sg:address":"Calle de Medico Ramon Tarazona, 3",
    "sg:city":"Valencia",
    "sg:orig_category":"Reposter\u00cdas",
    "sg:phone":"+34 963 47 49 26",
    "sg:postcode":"46015",
    "sg:province":"Valencia",
    "wof:name":"Diez Badenes Carmen",
    "wof:placetype":"venue"
},
  "geometry": {"coordinates":[-0.4004989862,39.4844818115],"type":"Point"}
}