{
  "type": "Feature",
  "properties": {
    "iso:country":"ES",
    "sg:address":"Calle de Doctor Cornago, 16",
    "sg:city":"Pozuelo De Alarcon",
    "sg:orig_category":"Molduras, Junquillos, Listones Y Molduras Perforadas",
    "sg:phone":"+34 917 15 31 49",
    "sg:postcode":"28223",
    "sg:province":"Madrid",
    "wof:name":"Garcia Cercas Rita",
    "wof:placetype":"venue"
},
  "geometry": {"coordinates":[-3.8136463165,40.4366531372],"type":"Point"}
}