{
  "type": "Feature",
  "properties": {
    "addr:full":"Calle de Rey, 10 Antequera M\u00e1laga 29200",
    "addr:housenumber":"10",
    "addr:postcode":"29200",
    "addr:street":"Calle De Rey",
    "iso:country":"ES",
    "sg:address":"Calle de Rey, 10",
    "sg:city":"Antequera",
    "sg:orig_category":"Inform\u00c1tica Equipo Y Programas (al Por Mayor)",
    "sg:phone":"+34 952 70 42 69",
    "sg:postcode":"29200",
    "sg:province":"M\u00e1laga",
    "sg:website":"www.gt3soluciones.com",
    "wof:name":"Gt3 Soluciones S.l.",
    "wof:placetype":"venue"
},
  "geometry": {"coordinates":[-4.5592479706,37.0173301697],"type":"Point"}
}