{
  "type": "Feature",
  "properties": {
    "iso:country":"ES",
    "sg:address":"Rua Xeneral Gutierrez Mellado, 2",
    "sg:city":"Pontevedra",
    "sg:orig_category":"Ense\u00d1ante, Direcci\u00d3n",
    "sg:phone":"+34 986 85 66 86",
    "sg:postcode":"36001",
    "sg:province":"Pontevedra",
    "wof:name":"Moreira Carrascal Jose Alberto",
    "wof:placetype":"venue"
},
  "geometry": {"coordinates":[-8.6458559036,42.4311637878],"type":"Point"}
}