{
  "type": "Feature",
  "properties": {
    "addr:full":"Calle de Doctor Castelo, 10 Madrid Madrid 28009",
    "addr:housenumber":"10",
    "addr:postcode":"madrid;28009",
    "addr:street":"Calle De Doctor Castelo",
    "iso:country":"ES",
    "sg:address":"Calle de Doctor Castelo, 10",
    "sg:city":"Madrid",
    "sg:orig_category":"Confecci\u00d3n De Sombreros Y Tocados",
    "sg:phone":"+34 915 73 78 00",
    "sg:postcode":"28009",
    "sg:province":"Madrid",
    "wof:name":"Alcaraz Lopez Juan Antonio",
    "wof:placetype":"venue"
},
  "geometry": {"coordinates":[-3.678122282,40.4204444885],"type":"Point"}
}