{
  "type": "Feature",
  "properties": {
    "iso:country":"ES",
    "sg:address":"Calle de San Juan Txurru, 8",
    "sg:city":"Ondarroa",
    "sg:orig_category":"Empresas De Carpinter\u00cda De Madera",
    "sg:phone":"+34 946 83 27 25",
    "sg:postcode":"48700",
    "sg:province":"Vizcaya",
    "wof:name":"Ituarte Irueta Cruz",
    "wof:placetype":"venue"
},
  "geometry": {"coordinates":[-2.4223361015,43.3185157776],"type":"Point"}
}