{
  "type": "Feature",
  "properties": {
    "addr:full":"Cno San Vicente, S/n Tarazona Zaragoza 50500",
    "addr:housenumber":"s / n",
    "addr:postcode":"50500",
    "addr:street":"Cno San Vicente",
    "iso:country":"ES",
    "sg:address":"Cno San Vicente, S/n",
    "sg:city":"Tarazona",
    "sg:orig_category":"Sindicatos De Trabajadores",
    "sg:phone":"+34 976 64 09 27",
    "sg:postcode":"50500",
    "sg:province":"Zaragoza",
    "wof:name":"Union General De Trabajadores",
    "wof:placetype":"venue"
},
  "geometry": {"coordinates":[-1.7188789845,41.9095497131],"type":"Point"}
}