{
  "type": "Feature",
  "properties": {
    "addr:full":"Avda Zumalacarregui, 35 Cedeira La Coru\u00f1a 15350",
    "addr:housenumber":"35",
    "addr:postcode":"15350",
    "addr:street":"Avda Zumalacarregui;La Corun\u0303A",
    "iso:country":"ES",
    "sg:address":"Avda Zumalacarregui, 35",
    "sg:city":"Cedeira",
    "sg:orig_category":"Inmobiliaria (agencias)",
    "sg:phone":"+34 981 48 21 00",
    "sg:postcode":"15350",
    "sg:province":"La Coru\u00f1a",
    "wof:name":"Garcia Forestal S.l.",
    "wof:placetype":"venue"
},
  "geometry": {"coordinates":[-8.0498695374,43.6641616821],"type":"Point"}
}