{
  "type": "Feature",
  "properties": {
    "iso:country":"ES",
    "sg:address":"Calle de Cauce, 12",
    "sg:city":"Torremolinos",
    "sg:orig_category":"Bisuter\u00cda, Joyer\u00cda, Relojer\u00cda (al Por Menor)",
    "sg:phone":"+34 952 37 59 54",
    "sg:postcode":"29620",
    "sg:province":"M\u00e1laga",
    "wof:name":"Bailly Milenium S.l.",
    "wof:placetype":"venue"
},
  "geometry": {"coordinates":[-4.4994831085,36.6236495972],"type":"Point"}
}