{
  "type": "Feature",
  "properties": {
    "iso:country":"ES",
    "sg:address":"Calle de Pintor Mariano More, 22",
    "sg:city":"Gijon",
    "sg:orig_category":"Sindicatos De Trabajadores",
    "sg:phone":"+34 985 35 24 19",
    "sg:postcode":"33206",
    "sg:province":"Asturias",
    "wof:name":"Mca-ugt",
    "wof:placetype":"venue"
},
  "geometry": {"coordinates":[-5.6713171005,43.5404624939],"type":"Point"}
}