{
  "type": "Feature",
  "properties": {
    "addr:full":"Avda Isabel De Moctezuma, 31 Caceres C\u00e1ceres 10005",
    "addr:housenumber":"31",
    "addr:postcode":"10005",
    "addr:street":"Avda Isabel De Moctezuma;Ca\u0301Ceres",
    "iso:country":"ES",
    "sg:address":"Avda Isabel De Moctezuma, 31",
    "sg:city":"Caceres",
    "sg:orig_category":"Quincaller\u00cda (al Por Menor)",
    "sg:phone":"+34 927 21 60 05",
    "sg:postcode":"10005",
    "sg:province":"C\u00e1ceres",
    "wof:name":"Verdejo Guerra Maria Victoria",
    "wof:placetype":"venue"
},
  "geometry": {"coordinates":[-6.379128933,39.4619178772],"type":"Point"}
}