{
  "type": "Feature",
  "properties": {
    "iso:country":"ES",
    "sg:address":"Carr Ramon Muntaner, 3",
    "sg:city":"Girona",
    "sg:orig_category":"Peluqueros: De Se\u00d1oras",
    "sg:phone":"+34 972 23 48 40",
    "sg:postcode":"17005",
    "sg:province":"Girona",
    "wof:name":"Escura Pou Maria Angels",
    "wof:placetype":"venue"
},
  "geometry": {"coordinates":[2.8134119511,41.9776725769],"type":"Point"}
}