{
  "type": "Feature",
  "properties": {
    "addr:full":"Calle de Tetuan, 49 Lebrija Sevilla 41740",
    "addr:housenumber":"49",
    "addr:postcode":"41740",
    "addr:street":"Calle De Tetuan",
    "iso:country":"ES",
    "sg:address":"Calle de Tetuan, 49",
    "sg:city":"Lebrija",
    "sg:orig_category":"Inform\u00c1tica: Material Y Suministros",
    "sg:phone":"+34 955 97 50 91",
    "sg:postcode":"41740",
    "sg:province":"Sevilla",
    "wof:name":"Offysum Lebrija S.l.",
    "wof:placetype":"venue"
},
  "geometry": {"coordinates":[-6.0816516876,36.9167900085],"type":"Point"}
}