{
  "type": "Feature",
  "properties": {
    "addr:full":"Calle de Ramal (el), 6 Orotava Santa Cruz De Tenerife 38300",
    "addr:housenumber":"6",
    "addr:postcode":"38300",
    "addr:street":"Calle De Ramal El",
    "iso:country":"ES",
    "sg:address":"Calle de Ramal (el), 6",
    "sg:city":"Orotava",
    "sg:orig_category":"Lavado, Limpieza De Veh\u00cdculos",
    "sg:phone":"+34 922 33 08 75",
    "sg:postcode":"38300",
    "sg:province":"Santa Cruz De Tenerife",
    "wof:name":"Autolavados El Torreon S.l.",
    "wof:placetype":"venue"
},
  "geometry": {"coordinates":[-16.521232605,28.397731781],"type":"Point"}
}