{
  "type": "Feature",
  "properties": {
    "addr:full":"Gesalibar Auzoa, 29 Gesalibar Guip\u00f9zcoa 20509",
    "addr:housenumber":"29",
    "addr:postcode":"20509",
    "addr:street":"Gesalibar Auzoa;Guipu\u0300Zcoa",
    "iso:country":"ES",
    "sg:address":"Gesalibar Auzoa, 29",
    "sg:city":"Gesalibar",
    "sg:orig_category":"Proveedores De Acceso A Internet",
    "sg:phone":"+34 943 79 57 05",
    "sg:postcode":"20509",
    "sg:province":"Guip\u00f9zcoa",
    "wof:name":"Kelnara Banda Zabala S.l.",
    "wof:placetype":"venue"
},
  "geometry": {"coordinates":[-2.520637989,43.0691261292],"type":"Point"}
}