{
  "type": "Feature",
  "properties": {
    "iso:country":"ES",
    "sg:address":"Carrer de Lluis Millet, 102",
    "sg:city":"Masnou",
    "sg:orig_category":"Alimentaci\u00d3n General (al Por Menor)",
    "sg:phone":"+34 935 55 28 45",
    "sg:postcode":"08320",
    "sg:province":"Barcelona",
    "wof:name":"Fontanella Torras Rosa Maria",
    "wof:placetype":"venue"
},
  "geometry": {"coordinates":[2.3135399818,41.4788665771],"type":"Point"}
}