{
  "type": "Feature",
  "properties": {
    "addr:full":"Avda Carmelo Fortes Perez, 28 S. Silvestre Guzman Huelva 21591",
    "addr:housenumber":"28",
    "addr:postcode":"21591",
    "addr:street":"Avda Carmelo Fortes Perez;S. Silvestre Guzman Huelva",
    "iso:country":"ES",
    "sg:address":"Avda Carmelo Fortes Perez, 28",
    "sg:city":"S. Silvestre Guzman",
    "sg:orig_category":"Restaurantes",
    "sg:phone":"+34 959 34 07 42",
    "sg:postcode":"21591",
    "sg:province":"Huelva",
    "wof:name":"Hostal San Silvestre Sociedad Cooperativa Andaluza",
    "wof:placetype":"venue"
},
  "geometry": {"coordinates":[-7.3480992317,37.3880081177],"type":"Point"}
}