{
  "type": "Feature",
  "properties": {
    "iso:country":"ES",
    "sg:address":"Calle de Gran Capitan, 8",
    "sg:city":"Huelva",
    "sg:orig_category":"Inform\u00c1tica: Material Y Suministros",
    "sg:phone":"+34 959 26 13 00",
    "sg:postcode":"21002",
    "sg:province":"Huelva",
    "wof:name":"Fernandez Cotta Jimenez Rafael A",
    "wof:placetype":"venue"
},
  "geometry": {"coordinates":[-6.9542961121,37.2607536316],"type":"Point"}
}