{
  "type": "Feature",
  "properties": {
    "addr:full":"Calle de Genoveses, 4 Almeria Almer\u00eda 04008",
    "addr:housenumber":"4",
    "addr:postcode":"04008",
    "addr:street":"Calle De Genoveses",
    "iso:country":"ES",
    "sg:address":"Calle de Genoveses, 4",
    "sg:city":"Almeria",
    "sg:orig_category":"Molduras, Junquillos, Listones Y Molduras Perforadas",
    "sg:phone":"+34 950 25 16 79",
    "sg:postcode":"04008",
    "sg:province":"Almer\u00eda",
    "wof:name":"Martinez Portillo Joaquin",
    "wof:placetype":"venue"
},
  "geometry": {"coordinates":[-2.4680490494,36.8464012146],"type":"Point"}
}