{
  "type": "Feature",
  "properties": {
    "addr:full":"Del Rio, 1 Escalona Toledo 45910",
    "addr:housenumber":"1",
    "addr:postcode":"45910",
    "addr:street":"Del Rio",
    "iso:country":"ES",
    "sg:address":"Del Rio, 1",
    "sg:city":"Escalona",
    "sg:orig_category":"Asesor\u00cda Fiscal Y Jur\u00cddica",
    "sg:phone":"+34 925 78 01 71",
    "sg:postcode":"45910",
    "sg:province":"Toledo",
    "wof:name":"Jimeno Galan Ramon",
    "wof:placetype":"venue"
},
  "geometry": {"coordinates":[-4.4034180641,40.1653404236],"type":"Point"}
}