{
  "type": "Feature",
  "properties": {
    "addr:full":"Av Sant Jordi, 12 Ma\u00e7anet Selva Girona 17412",
    "addr:housenumber":"12",
    "addr:postcode":"17412",
    "addr:street":"Av Sant Jordi",
    "iso:country":"ES",
    "sg:address":"Av Sant Jordi, 12",
    "sg:city":"Ma\u00e7anet Selva",
    "sg:orig_category":"Torrefactado De Caf\u00c9",
    "sg:phone":"+34 972 16 50 30",
    "sg:postcode":"17412",
    "sg:province":"Girona",
    "wof:name":"Saula S. A.",
    "wof:placetype":"venue"
},
  "geometry": {"coordinates":[2.7316699028,41.7760887146],"type":"Point"}
}