{
  "type": "Feature",
  "properties": {
    "iso:country":"ES",
    "sg:address":"Calle de Monasterio Del Cuervo, S/n",
    "sg:city":"Benalup",
    "sg:classifiers":[
        {
            "category":"Autos & Motor Vehicles",
            "subcategory":"Automobile Sales",
            "type":"Retail Goods"
        }
    ],
    "sg:phone":"+34 956 41 76 23",
    "sg:postcode":"11190",
    "sg:province":"C\u00e1diz",
    "wof:name":"Crespo Mu\u00f1oz Juan Manuel",
    "wof:placetype":"venue"
},
  "geometry": {"coordinates":[-5.8151140213,36.3434791565],"type":"Point"}
}