{
  "type": "Feature",
  "properties": {
    "iso:country":"ES",
    "sg:address":"Calle de Valentin Calderon, 8",
    "sg:city":"Palencia",
    "sg:orig_category":"M\u00c9dicos: Estomatolog\u00cda",
    "sg:phone":"+34 979 74 19 39",
    "sg:postcode":"34001",
    "sg:province":"Palencia",
    "wof:name":"Pastor Casas Javier",
    "wof:placetype":"venue"
},
  "geometry": {"coordinates":[-4.5327811241,42.0118713379],"type":"Point"}
}