{
  "type": "Feature",
  "properties": {
    "addr:full":"Pl Joan Manent, S/n Santa Coloma De Gramenet Barcelona 08921",
    "addr:housenumber":"s / n",
    "addr:postcode":"08921",
    "addr:street":"Pl Joan Manent",
    "iso:country":"ES",
    "sg:address":"Pl Joan Manent, S/n",
    "sg:city":"Santa Coloma De Gramenet",
    "sg:orig_category":"Peluquer\u00cdas, Peluquer\u00cda Mixta",
    "sg:phone":"+34 933 85 74 45",
    "sg:postcode":"08921",
    "sg:province":"Barcelona",
    "wof:name":"Pe\u00f1a Mestres Josefa De La",
    "wof:placetype":"venue"
},
  "geometry": {"coordinates":[2.2066249847,41.4538345337],"type":"Point"}
}