{
  "type": "Feature",
  "properties": {
    "iso:country":"ES",
    "sg:address":"Carrer de Doctor Letamendi, 40",
    "sg:city":"Barcelona",
    "sg:orig_category":"Fabricaci\u00d3n De Enlosados, Soler\u00cdas",
    "sg:phone":"+34 934 27 44 67",
    "sg:postcode":"08031",
    "sg:province":"Barcelona",
    "wof:name":"Puigfel S. A.",
    "wof:placetype":"venue"
},
  "geometry": {"coordinates":[2.1604449749,41.4357070923],"type":"Point"}
}