{
  "type": "Feature",
  "properties": {
    "iso:country":"ES",
    "sg:address":"Trva Irmans Martinez, 5",
    "sg:city":"Bande",
    "sg:orig_category":"Molduras, Junquillos, Listones Y Molduras Perforadas",
    "sg:phone":"+34 988 44 31 83",
    "sg:postcode":"32840",
    "sg:province":"Ourense",
    "wof:name":"Lopez Feijoo Benita",
    "wof:placetype":"venue"
},
  "geometry": {"coordinates":[-7.9692811966,42.0345993042],"type":"Point"}
}