{
  "type": "Feature",
  "properties": {
    "iso:country":"ES",
    "sg:address":"Plaz Cruz Verde, 6",
    "sg:city":"Valladolid",
    "sg:orig_category":"Promotores Constructores",
    "sg:phone":"+34 983 29 44 25",
    "sg:postcode":"47002",
    "sg:province":"Valladolid",
    "wof:name":"Construcciones Y Promociones Manuel Brizuela S.l.",
    "wof:placetype":"venue"
},
  "geometry": {"coordinates":[-4.7202801704,41.6480751038],"type":"Point"}
}