{
  "type": "Feature",
  "properties": {
    "iso:country":"ES",
    "sg:address":"Carrer de Joiers, 5",
    "sg:city":"Poligon Industrial Riera De Caldes",
    "sg:orig_category":"Trabajos De Soldaduras",
    "sg:phone":"+34 938 63 96 76",
    "sg:postcode":"08184",
    "sg:province":"Barcelona",
    "sg:website":"www.nicrotec.com",
    "wof:name":"Soldaduras Nicrotec S. A.",
    "wof:placetype":"venue"
},
  "geometry": {"coordinates":[2.1748530865,41.5814743042],"type":"Point"}
}