{
  "type": "Feature",
  "properties": {
    "addr:full":"Calle de Islas Cies, 1 Madrid Madrid 28035",
    "addr:housenumber":"1",
    "addr:postcode":"28035",
    "addr:street":"Calle De Islas Cies",
    "iso:country":"ES",
    "sg:address":"Calle de Islas Cies, 1",
    "sg:city":"Madrid",
    "sg:orig_category":"Fisioterapia",
    "sg:phone":"+34 917 30 92 05",
    "sg:postcode":"28035",
    "sg:province":"Madrid",
    "wof:name":"Fisioterapia Betanzos S.l.",
    "wof:placetype":"venue"
},
  "geometry": {"coordinates":[-3.7173779011,40.4811248779],"type":"Point"}
}