{
  "type": "Feature",
  "properties": {
    "iso:country":"ES",
    "sg:address":"Calle de Friela, 6",
    "sg:city":"Maside",
    "sg:orig_category":"Carnicer\u00cdas, Carnicer\u00cdas",
    "sg:phone":"+34 988 28 84 59",
    "sg:postcode":"32570",
    "sg:province":"Ourense",
    "wof:name":"Gonzalez Mosquera Manuel",
    "wof:placetype":"venue"
},
  "geometry": {"coordinates":[-8.0267791748,42.4151000977],"type":"Point"}
}