{
  "type": "Feature",
  "properties": {
    "addr:full":"Calle de Hernan Cortes, 85 Villanueva Serena Badajoz 06700",
    "addr:housenumber":"85",
    "addr:postcode":"06700",
    "addr:street":"Calle De Hernan Cortes",
    "iso:country":"ES",
    "sg:address":"Calle de Hernan Cortes, 85",
    "sg:city":"Villanueva Serena",
    "sg:orig_category":"Laboratorios Y Trabajos De Fotograf\u00cda, V\u00cddeo Y Cine",
    "sg:phone":"+34 924 84 00 79",
    "sg:postcode":"06700",
    "sg:province":"Badajoz",
    "wof:name":"Rayego Gutierrez Luis",
    "wof:placetype":"venue"
},
  "geometry": {"coordinates":[-5.7927408218,38.9731750488],"type":"Point"}
}