{
  "type": "Feature",
  "properties": {
    "addr:full":"Avda Gran Via, 15 Caravaca Cruz Murcia 30400",
    "addr:housenumber":"15",
    "addr:postcode":"30400",
    "addr:street":"Avda Gran Via",
    "iso:country":"ES",
    "sg:address":"Avda Gran Via, 15",
    "sg:city":"Caravaca Cruz",
    "sg:orig_category":"Inmobiliaria (agencias)",
    "sg:phone":"+34 968 70 02 10",
    "sg:postcode":"30400",
    "sg:province":"Murcia",
    "wof:name":"Istomur Murcia Corporacion Inmobiliaria S.l.",
    "wof:placetype":"venue"
},
  "geometry": {"coordinates":[-1.8621220589,38.1020584106],"type":"Point"}
}