{
  "type": "Feature",
  "properties": {
    "addr:full":"Calle de Ramon Y Cajal, 17 Priego Cordoba C\u00f3rdoba 14800",
    "addr:housenumber":"17",
    "addr:postcode":"14800",
    "addr:street":"Calle De Ramon Y Cajal;Cordoba Co\u0301Rdoba",
    "iso:country":"ES",
    "sg:address":"Calle de Ramon Y Cajal, 17",
    "sg:city":"Priego Cordoba",
    "sg:orig_category":"Panader\u00cdas, Panader\u00cdas",
    "sg:phone":"+34 957 70 12 77",
    "sg:postcode":"14800",
    "sg:province":"C\u00f3rdoba",
    "wof:name":"Lopez Bermudez Juan",
    "wof:placetype":"venue"
},
  "geometry": {"coordinates":[-4.2015480995,37.4386024475],"type":"Point"}
}