{
  "type": "Feature",
  "properties": {
    "iso:country":"ES",
    "sg:address":"Calle de Canonigo Mu\u00d1oz, 23",
    "sg:city":"Utiel",
    "sg:orig_category":"Agencias De Viajes",
    "sg:phone":"+34 962 16 81 95",
    "sg:postcode":"46300",
    "sg:province":"Valencia",
    "wof:name":"La Maleta C.b.",
    "wof:placetype":"venue"
},
  "geometry": {"coordinates":[-1.2034947872,39.5669708252],"type":"Point"}
}