{
  "type": "Feature",
  "properties": {
    "addr:full":"Calle de Infante Don Juan Manuel, 10 Cordoba C\u00f3rdoba 14009",
    "addr:housenumber":"10",
    "addr:postcode":"14009",
    "addr:street":"Calle De Infante Don Juan Manuel;Co\u0301Rdoba",
    "iso:country":"ES",
    "sg:address":"Calle de Infante Don Juan Manuel, 10",
    "sg:city":"Cordoba",
    "sg:orig_category":"Ense\u00d1anza Variada",
    "sg:phone":"+34 957 29 28 01",
    "sg:postcode":"14009",
    "sg:province":"C\u00f3rdoba",
    "wof:name":"Jimenez Prats Francisca",
    "wof:placetype":"venue"
},
  "geometry": {"coordinates":[-4.7748260498,37.8741912842],"type":"Point"}
}