{
  "type": "Feature",
  "properties": {
    "iso:country":"ES",
    "sg:address":"Calle de Maqueda, 132",
    "sg:city":"Madrid",
    "sg:orig_category":"Centros Empresariales",
    "sg:phone":"+34 917 17 43 61",
    "sg:postcode":"28024",
    "sg:province":"Madrid",
    "wof:name":"Uchechukwu Eke Christ",
    "wof:placetype":"venue"
},
  "geometry": {"coordinates":[-3.7622029781,40.3881645203],"type":"Point"}
}