{
  "type": "Feature",
  "properties": {
    "iso:country":"ES",
    "sg:address":"Calle de Uruguay, 24",
    "sg:city":"Toscal",
    "sg:orig_category":"Bazares, Art\u00cdculos De Limpieza Y De Cocina (al Por Menor)",
    "sg:phone":"+34 922 36 27 13",
    "sg:postcode":"38418",
    "sg:province":"Santa Cruz De Tenerife",
    "wof:name":"Calarco  Francesco",
    "wof:placetype":"venue"
},
  "geometry": {"coordinates":[-16.5708503723,28.4004707336],"type":"Point"}
}