{
  "type": "Feature",
  "properties": {
    "iso:country":"ES",
    "sg:address":"Matadero, S/n",
    "sg:city":"Beniparrell",
    "sg:orig_category":"Limpieza Con Chorro De Arena Y Con Granalla, Pulido",
    "sg:phone":"+34 961 21 60 23",
    "sg:postcode":"46469",
    "sg:province":"Valencia",
    "wof:name":"Decoracion Orpal S.l.",
    "wof:placetype":"venue"
},
  "geometry": {"coordinates":[-0.4040139914,39.3805236816],"type":"Point"}
}