{
  "type": "Feature",
  "properties": {
    "iso:country":"ES",
    "sg:address":"Crt. La Roda, Km. 0005,0",
    "sg:city":"Tarazona Mancha",
    "sg:orig_category":"Hormigonados",
    "sg:phone":"+34 967 58 90 00",
    "sg:postcode":"02100",
    "sg:province":"Albacete",
    "wof:name":"Hormigones Campollano S.a.",
    "wof:placetype":"venue"
},
  "geometry": {"coordinates":[-1.9125390053,39.2651023865],"type":"Point"}
}