{
  "type": "Feature",
  "properties": {
    "addr:full":"Calle de Antonio Gaudi (de), 25 Fuenlabrada Madrid 28946",
    "addr:housenumber":"25",
    "addr:postcode":"28946",
    "addr:street":"Calle De Antonio Gaudi De",
    "iso:country":"ES",
    "sg:address":"Calle de Antonio Gaudi (de), 25",
    "sg:city":"Fuenlabrada",
    "sg:orig_category":"Cristaler\u00cdas",
    "sg:phone":"+34 916 06 22 45",
    "sg:postcode":"28946",
    "sg:province":"Madrid",
    "wof:name":"Cristalerias Magan S.a.",
    "wof:placetype":"venue"
},
  "geometry": {"coordinates":[-3.776696682,40.2806434631],"type":"Point"}
}