{
  "type": "Feature",
  "properties": {
    "iso:country":"ES",
    "sg:address":"Major, 36",
    "sg:city":"Malpartit",
    "sg:orig_category":"Agricultores, Agricultores",
    "sg:phone":"+34 973 73 63 89",
    "sg:postcode":"25110",
    "sg:province":"Lleida",
    "wof:name":"Agropecuaria Santa Eulalia S.c.p.",
    "wof:placetype":"venue"
},
  "geometry": {"coordinates":[0.5551552176,41.6670875549],"type":"Point"}
}