{
  "type": "Feature",
  "properties": {
    "iso:country":"ES",
    "sg:address":"Calle de Nava (la), S/n",
    "sg:city":"Ablitas",
    "sg:orig_category":"Art\u00cdculos Funerarios (al Por Menor)",
    "sg:phone":"+34 948 81 38 21",
    "sg:postcode":"31523",
    "sg:province":"Navarra",
    "wof:name":"Saturnino Pe\u00f1a Bueno Y Javier Jimenez Garcia",
    "wof:placetype":"venue"
},
  "geometry": {"coordinates":[-1.6356489658,41.9752349854],"type":"Point"}
}