{
  "type": "Feature",
  "properties": {
    "addr:full":"Pase Yeserias, 43 Madrid Madrid 28005",
    "addr:housenumber":"43",
    "addr:postcode":"madrid;28005",
    "addr:street":"Yeserias",
    "iso:country":"ES",
    "sg:address":"Pase Yeserias, 43",
    "sg:city":"Madrid",
    "sg:orig_category":"Peluquer\u00cdas, Peluquer\u00cda Mixta",
    "sg:phone":"+34 914 74 49 85",
    "sg:postcode":"28005",
    "sg:province":"Madrid",
    "wof:name":"Amaro Cuenca Maria Pilar",
    "wof:placetype":"venue"
},
  "geometry": {"coordinates":[-3.7068729401,40.3975219727],"type":"Point"}
}