{
  "type": "Feature",
  "properties": {
    "addr:full":"Calle de Atalaya, 38 Palmas De Gran Canaria Las Palmas 35010",
    "addr:housenumber":"38",
    "addr:postcode":"35010",
    "addr:street":"Calle De Atalaya",
    "iso:country":"ES",
    "sg:address":"Calle de Atalaya, 38",
    "sg:city":"Palmas De Gran Canaria",
    "sg:orig_category":"Chapister\u00cda",
    "sg:phone":"+34 928 48 52 25",
    "sg:postcode":"35010",
    "sg:province":"Las Palmas",
    "wof:name":"Santana Travieso Vicente",
    "wof:placetype":"venue"
},
  "geometry": {"coordinates":[-15.4545679092,28.1053237915],"type":"Point"}
}