{
  "type": "Feature",
  "properties": {
    "addr:full":"Calle de Mijo, 7 Madrid Madrid 28026",
    "addr:housenumber":"7",
    "addr:postcode":"madrid;28026",
    "addr:street":"Calle De Mijo",
    "iso:country":"ES",
    "sg:address":"Calle de Mijo, 7",
    "sg:city":"Madrid",
    "sg:orig_category":"Electricidad, Electr\u00d3nica: Material Y Suministros (al Por Mayor)",
    "sg:phone":"+34 914 60 17 93",
    "sg:postcode":"28026",
    "sg:province":"Madrid",
    "sg:website":"www.selenico@selenico03.com",
    "wof:name":"Seleniko 03 S.l.",
    "wof:placetype":"venue"
},
  "geometry": {"coordinates":[-3.7175130844,40.3772201538],"type":"Point"}
}