{
  "type": "Feature",
  "properties": {
    "iso:country":"ES",
    "sg:address":"Calle de Silos, S/n",
    "sg:city":"Alcala Guadaira",
    "sg:orig_category":"Farmacias",
    "sg:phone":"+34 955 61 40 39",
    "sg:postcode":"41500",
    "sg:province":"Sevilla",
    "wof:name":"Romero Leon Maria Dolores",
    "wof:placetype":"venue"
},
  "geometry": {"coordinates":[-5.8456888199,37.3450737],"type":"Point"}
}