{
  "type": "Feature",
  "properties": {
    "addr:full":"Calle de Malaga, 30 Binefar Huesca 22500",
    "addr:housenumber":"30",
    "addr:postcode":"22500",
    "addr:street":"Calle De Malaga",
    "iso:country":"ES",
    "sg:address":"Calle de Malaga, 30",
    "sg:city":"Binefar",
    "sg:orig_category":"Material Y Herramientas Agr\u00cdcolas",
    "sg:phone":"+34 974 42 82 39",
    "sg:postcode":"22500",
    "sg:province":"Huesca",
    "wof:name":"Macar S.c.",
    "wof:placetype":"venue"
},
  "geometry": {"coordinates":[0.3003410101,41.8432312012],"type":"Point"}
}