{
  "type": "Feature",
  "properties": {
    "addr:full":"Carrer de Sant Andreu, 9 Manresa Barcelona 08241",
    "addr:housenumber":"9",
    "addr:postcode":"08241",
    "addr:street":"Carrer De Sant Andreu",
    "iso:country":"ES",
    "sg:address":"Carrer de Sant Andreu, 9",
    "sg:city":"Manresa",
    "sg:orig_category":"Molduras, Junquillos, Listones Y Molduras Perforadas",
    "sg:phone":"+34 938 72 45 59",
    "sg:postcode":"08241",
    "sg:province":"Barcelona",
    "wof:name":"Berges Sensarich Gavina",
    "wof:placetype":"venue"
},
  "geometry": {"coordinates":[1.8283179998,41.7251968384],"type":"Point"}
}