{
  "type": "Feature",
  "properties": {
    "addr:full":"Pol Ind Semolilla, S/n Abanilla Murcia 30640",
    "addr:housenumber":"s / n",
    "addr:postcode":"30640",
    "iso:country":"ES",
    "sg:address":"Pol Ind Semolilla, S/n",
    "sg:city":"Abanilla",
    "sg:orig_category":"Importaci\u00d3n",
    "sg:phone":"+34 968 68 00 30",
    "sg:postcode":"30640",
    "sg:province":"Murcia",
    "wof:name":"Kettle Produce Espa\u00d1a S.l.",
    "wof:placetype":"venue"
},
  "geometry": {"coordinates":[-1.0497989655,38.1779708862],"type":"Point"}
}