{
  "type": "Feature",
  "properties": {
    "addr:full":"Ctra Cogullada Mercazaragoza, 65 Zaragoza Zaragoza 50014",
    "addr:housenumber":"65",
    "addr:postcode":"50014",
    "addr:street":"Ctra Cogullada Mercazaragoza",
    "iso:country":"ES",
    "sg:address":"Ctra Cogullada Mercazaragoza, 65",
    "sg:city":"Zaragoza",
    "sg:orig_category":"Supermercados Y Hipermercados",
    "sg:phone":"+34 976 47 20 46",
    "sg:postcode":"50014",
    "sg:province":"Zaragoza",
    "wof:name":"Supermercados Sabeco S.a.",
    "wof:placetype":"venue"
},
  "geometry": {"coordinates":[-0.8813189864,41.6517295837],"type":"Point"}
}