{
  "type": "Feature",
  "properties": {
    "iso:country":"ES",
    "sg:address":"Calle de Zumardia, 7",
    "sg:city":"Algorta",
    "sg:orig_category":"Inmobiliaria (agencias)",
    "sg:phone":"+34 944 60 79 82",
    "sg:postcode":"48992",
    "sg:province":"Vizcaya",
    "wof:name":"Telosa S.a.",
    "wof:placetype":"venue"
},
  "geometry": {"coordinates":[-3.0054860115,43.3360137939],"type":"Point"}
}