{
  "type": "Feature",
  "properties": {
    "iso:country":"ES",
    "sg:address":"Calle de Chile, 15",
    "sg:city":"Ejido",
    "sg:orig_category":"Publicidad (soportes Y Gesti\u00d3n)",
    "sg:phone":"+34 950 57 31 62",
    "sg:postcode":"04700",
    "sg:province":"Almer\u00eda",
    "wof:name":"Perspectiva Neusky S.l.",
    "wof:placetype":"venue"
},
  "geometry": {"coordinates":[-2.8179914951,36.7707633972],"type":"Point"}
}