{
  "type": "Feature",
  "properties": {
    "addr:full":"Avda Luxemburgo, 18 Eurovillas-las Villas Madrid 28514",
    "addr:housenumber":"18",
    "addr:postcode":"28514",
    "addr:street":"Avda Luxemburgo",
    "iso:country":"ES",
    "sg:address":"Avda Luxemburgo, 18",
    "sg:city":"Eurovillas-las Villas",
    "sg:orig_category":"Fotograf\u00cda Y Cine: Aparatos, Pel\u00cdculas Y Accesorios (fabricaci\u00d3n, Al Por Mayor)",
    "sg:phone":"+34 918 73 43 62",
    "sg:postcode":"28514",
    "sg:province":"Madrid",
    "wof:name":"Bailarin Moreno Jaime",
    "wof:placetype":"venue"
},
  "geometry": {"coordinates":[-3.2641530037,40.354385376],"type":"Point"}
}