{
  "type": "Feature",
  "properties": {
    "addr:full":"C/ President Francesc Macia, 56 Salt Girona 17190",
    "addr:housenumber":"56",
    "addr:postcode":"17190",
    "addr:street":"C / President Francesc Macia",
    "iso:country":"ES",
    "sg:address":"C/ President Francesc Macia, 56",
    "sg:city":"Salt",
    "sg:orig_category":"Asociaciones Y Clubs Deportivos",
    "sg:phone":"+34 972 24 53 74",
    "sg:postcode":"17190",
    "sg:province":"Girona",
    "wof:name":"Esports Parra S.l.",
    "wof:placetype":"venue"
},
  "geometry": {"coordinates":[2.7922270298,41.9711074829],"type":"Point"}
}