{
  "type": "Feature",
  "properties": {
    "addr:full":"Plaz Brasil (del), S/n Alcorcon Madrid 28921",
    "addr:postcode":"28921",
    "addr:street":"Plaz;Del S / N Alcorcon",
    "iso:country":"ES",
    "sg:address":"Plaz Brasil (del), S/n",
    "sg:city":"Alcorcon",
    "sg:orig_category":"Caf\u00c9s, Bares, Cervecer\u00cdas",
    "sg:phone":"+34 916 12 71 49",
    "sg:postcode":"28921",
    "sg:province":"Madrid",
    "wof:name":"Luna Platero Pedro",
    "wof:placetype":"venue"
},
  "geometry": {"coordinates":[-3.8242239952,40.3513946533],"type":"Point"}
}