{
  "type": "Feature",
  "properties": {
    "iso:country":"ES",
    "sg:address":"Montesalgueiro, S/n",
    "sg:city":"Montesalgueiro",
    "sg:orig_category":"Puertas Y Portales",
    "sg:phone":"+34 981 78 92 27",
    "sg:postcode":"15317",
    "sg:province":"A Coru\u00f1a",
    "wof:name":"Vales Coru\u00d1a S.l.u",
    "wof:placetype":"venue"
},
  "geometry": {"coordinates":[-8.0159168243,43.2337150574],"type":"Point"}
}