{
  "type": "Feature",
  "properties": {
    "iso:country":"ES",
    "sg:address":"Calle de Santo Domingo, 20",
    "sg:city":"Sanlucar De Barrameda",
    "sg:orig_category":"Farmacias",
    "sg:phone":"+34 956 36 07 78",
    "sg:postcode":"11540",
    "sg:province":"C\u00e1diz",
    "wof:name":"Barbadillo Vidaurreta Belen",
    "wof:placetype":"venue"
},
  "geometry": {"coordinates":[-6.3475441933,36.7833976746],"type":"Point"}
}