{
  "type": "Feature",
  "properties": {
    "addr:full":"Calle de Pico Lin De Cubel, 2 Pravia Asturias 33120",
    "addr:housenumber":"2",
    "addr:postcode":"33120",
    "addr:street":"Calle De Pico Lin De Cubel",
    "iso:country":"ES",
    "sg:address":"Calle de Pico Lin De Cubel, 2",
    "sg:city":"Pravia",
    "sg:orig_category":"Carnicer\u00cdas, Carnicer\u00cdas",
    "sg:phone":"+34 985 82 05 82",
    "sg:postcode":"33120",
    "sg:province":"Asturias",
    "wof:name":"Menendez Arias Jacinto",
    "wof:placetype":"venue"
},
  "geometry": {"coordinates":[-6.111096859,43.4873542786],"type":"Point"}
}