{
  "type": "Feature",
  "properties": {
    "addr:full":"Avda Tren De Los Panaderos, S/n Alcala Guadaira Sevilla 41500",
    "addr:housenumber":"s",
    "addr:postcode":"41500",
    "addr:street":"Avda Tren De Los Panaderos;/ N",
    "iso:country":"ES",
    "sg:address":"Avda Tren De Los Panaderos, S/n",
    "sg:city":"Alcala Guadaira",
    "sg:orig_category":"Inmobiliaria (agencias)",
    "sg:phone":"+34 955 68 77 51",
    "sg:postcode":"41500",
    "sg:province":"Sevilla",
    "wof:name":"C & B Larrea Y Qui\u00f1ones Asociados S.l.",
    "wof:placetype":"venue"
},
  "geometry": {"coordinates":[-5.8373389244,37.3306083679],"type":"Point"}
}