{
  "type": "Feature",
  "properties": {
    "iso:country":"ES",
    "sg:address":"Calle de Republica Argentina, 61",
    "sg:city":"Carrizal",
    "sg:orig_category":"Zapatos (al Por Menor)",
    "sg:phone":"+34 928 78 26 70",
    "sg:postcode":"35240",
    "sg:province":"Las Palmas",
    "wof:name":"Suarez Afonso Maria Del Mar",
    "wof:placetype":"venue"
},
  "geometry": {"coordinates":[-15.4094209671,27.9121551514],"type":"Point"}
}