{
  "type": "Feature",
  "properties": {
    "iso:country":"ES",
    "sg:address":"Calle de Jai Alai, S/n",
    "sg:city":"Fuentes",
    "sg:orig_category":"Inmobiliaria (agencias)",
    "sg:phone":"+34 964 41 47 75",
    "sg:postcode":"12579",
    "sg:province":"Castell\u00f3n",
    "wof:name":"Teissier  Eric",
    "wof:placetype":"venue"
},
  "geometry": {"coordinates":[0.2712750137,40.2442741394],"type":"Point"}
}