{
  "type": "Feature",
  "properties": {
    "addr:full":"Calle de Cea Bermudez, 51 Madrid Madrid 28003",
    "addr:housenumber":"51",
    "addr:postcode":"madrid;28003",
    "addr:street":"Calle De Cea Bermudez",
    "iso:country":"ES",
    "sg:address":"Calle de Cea Bermudez, 51",
    "sg:city":"Madrid",
    "sg:orig_category":"M\u00c9dicos: Estomatolog\u00cda",
    "sg:phone":"+34 915 43 41 48",
    "sg:postcode":"28003",
    "sg:province":"Madrid",
    "wof:name":"Martin Gutierrez Juan Luis",
    "wof:placetype":"venue"
},
  "geometry": {"coordinates":[-3.7143464088,40.4390068054],"type":"Point"}
}