{
  "type": "Feature",
  "properties": {
    "iso:country":"ES",
    "sg:address":"Calle de Rosario Pino, 14",
    "sg:city":"Madrid",
    "sg:orig_category":"Aguas (distribuci\u00d3n, Servicios)",
    "sg:phone":"+34 915 71 28 00",
    "sg:postcode":"28...",
    "sg:province":"Madrid",
    "wof:name":"Gestagua S.a.",
    "wof:placetype":"venue"
},
  "geometry": {"coordinates":[-3.6925530434,40.4622879028],"type":"Point"}
}