{
  "type": "Feature",
  "properties": {
    "addr:full":"Calle de Lanzarote, 10 San Sebastian De Los Reyes Madrid 28700",
    "addr:housenumber":"10",
    "addr:postcode":"28700",
    "addr:street":"Calle De Lanzarote",
    "iso:country":"ES",
    "sg:address":"Calle de Lanzarote, 10",
    "sg:city":"San Sebastian De Los Reyes",
    "sg:orig_category":"Promotores Constructores",
    "sg:phone":"+34 916 23 81 29",
    "sg:postcode":"28700",
    "sg:province":"Madrid",
    "wof:name":"R Y G Construcciones 97 S.l.",
    "wof:placetype":"venue"
},
  "geometry": {"coordinates":[-3.6216089725,40.5572166443],"type":"Point"}
}