{
  "type": "Feature",
  "properties": {
    "iso:country":"ES",
    "sg:address":"Cano La Ca\u00f1ada, S/n",
    "sg:city":"Tias",
    "sg:orig_category":"Aguas (distribuci\u00d3n, Servicios)",
    "sg:phone":"+34 928 51 15 36",
    "sg:postcode":"35572",
    "sg:province":"Las Palmas",
    "wof:name":"Insular De Aguas De Lanzarote S.a.",
    "wof:placetype":"venue"
},
  "geometry": {"coordinates":[-13.6521291733,28.9543895721],"type":"Point"}
}