{
  "type": "Feature",
  "properties": {
    "iso:country":"ES",
    "sg:address":"Carrer de Consellers, 26",
    "sg:city":"Llagostera",
    "sg:orig_category":"Florister\u00cdas",
    "sg:phone":"+34 972 83 05 24",
    "sg:postcode":"17240",
    "sg:province":"Girona",
    "wof:name":"Oliveras Falgueras Jose",
    "wof:placetype":"venue"
},
  "geometry": {"coordinates":[2.8934240341,41.8265533447],"type":"Point"}
}