{
  "type": "Feature",
  "properties": {
    "iso:country":"ES",
    "sg:address":"Calle de Rualasal, 21",
    "sg:city":"Santander",
    "sg:orig_category":"Perfumer\u00cda (al Por Menor)",
    "sg:phone":"+34 942 22 82 47",
    "sg:postcode":"39001",
    "sg:province":"Cantabria",
    "wof:name":"Charlon Y Martinez S.c.",
    "wof:placetype":"venue"
},
  "geometry": {"coordinates":[-3.8057999611,43.4629364014],"type":"Point"}
}