{
  "type": "Feature",
  "properties": {
    "iso:country":"ES",
    "sg:address":"Calle de Pergolas, 6",
    "sg:city":"Marmolejo",
    "sg:orig_category":"Alimentaci\u00d3n General (al Por Menor)",
    "sg:phone":"+34 953 51 74 34",
    "sg:postcode":"23770",
    "sg:province":"Ja\u00e9n",
    "wof:name":"Tienda Heris S.l.",
    "wof:placetype":"venue"
},
  "geometry": {"coordinates":[-4.1709132195,38.043636322],"type":"Point"}
}