{
  "type": "Feature",
  "properties": {
    "addr:full":"Ctra Almarcha, 36 S. Clemente Cuenca 16600",
    "addr:housenumber":"36",
    "addr:postcode":"16600",
    "addr:street":"Ctra Almarcha;S. Clemente Cuenca",
    "iso:country":"ES",
    "sg:address":"Ctra Almarcha, 36",
    "sg:city":"S. Clemente",
    "sg:orig_category":"Talleres El\u00c9ctricos Para Veh\u00cdculos",
    "sg:phone":"+34 969 30 22 24",
    "sg:postcode":"16600",
    "sg:province":"Cuenca",
    "wof:name":"Talleres Orsaiz S.l.",
    "wof:placetype":"venue"
},
  "geometry": {"coordinates":[-2.4215929508,39.4065208435],"type":"Point"}
}