{
  "type": "Feature",
  "properties": {
    "iso:country":"ES",
    "sg:address":"Avda Juan Xxiii, 9",
    "sg:city":"Logro\u00f1o",
    "sg:orig_category":"Institutos De Belleza",
    "sg:phone":"+34 941 25 67 11",
    "sg:postcode":"26003",
    "sg:province":"La Rioja",
    "wof:name":"Clinica Dermatologica Santiago Aparicio Fernandez S.l",
    "wof:placetype":"venue"
},
  "geometry": {"coordinates":[-2.4420690536,42.4639892578],"type":"Point"}
}