{
  "type": "Feature",
  "properties": {
    "iso:country":"ES",
    "sg:address":"Rbla Iberia, 139",
    "sg:city":"Sabadell",
    "sg:orig_category":"Tubos Met\u00c1licos",
    "sg:phone":"+34 937 27 51 37",
    "sg:postcode":"08205",
    "sg:province":"Barcelona",
    "wof:name":"Sistemas De Ventilacion Nova S. A.",
    "wof:placetype":"venue"
},
  "geometry": {"coordinates":[2.0975100994,41.5392570496],"type":"Point"}
}