{
  "type": "Feature",
  "properties": {
    "addr:full":"Calle de Ador, 47 Castellar-oliveral Valencia 46026",
    "addr:housenumber":"47",
    "addr:postcode":"46026",
    "addr:street":"Calle De Ador",
    "iso:country":"ES",
    "sg:address":"Calle de Ador, 47",
    "sg:city":"Castellar-oliveral",
    "sg:orig_category":"Alimentaci\u00d3n General (al Por Menor)",
    "sg:phone":"+34 963 96 13 23",
    "sg:postcode":"46026",
    "sg:province":"Valencia",
    "wof:name":"Rodrigo Dasi Natividad",
    "wof:placetype":"venue"
},
  "geometry": {"coordinates":[-0.3622053862,39.4297981262],"type":"Point"}
}