{
  "type": "Feature",
  "properties": {
    "addr:full":"Carr Nou Del Convent, 40 Algemesi Valencia 46680",
    "addr:housenumber":"40",
    "addr:postcode":"46680",
    "addr:street":"Carr Nou Del Convent",
    "iso:country":"ES",
    "sg:address":"Carr Nou Del Convent, 40",
    "sg:city":"Algemesi",
    "sg:orig_category":"Agencias Y Agentes Comerciales, Representantes",
    "sg:phone":"+34 962 42 15 67",
    "sg:postcode":"46680",
    "sg:province":"Valencia",
    "wof:name":"Ribes Tortajada Enrique",
    "wof:placetype":"venue"
},
  "geometry": {"coordinates":[-0.438906014,39.1901741028],"type":"Point"}
}