{
  "type": "Feature",
  "properties": {
    "addr:full":"Calle de Monte Esquinza, 30 Madrid Madrid 28010",
    "addr:housenumber":"30",
    "addr:postcode":"madrid;28010",
    "addr:street":"Calle De Monte Esquinza",
    "iso:country":"ES",
    "sg:address":"Calle de Monte Esquinza, 30",
    "sg:city":"Madrid",
    "sg:orig_category":"Importaci\u00d3n",
    "sg:phone":"+34 915 75 77 13",
    "sg:postcode":"28010",
    "sg:province":"Madrid",
    "wof:name":"Fundacion Entorno, Empresa Y Desarrollo Sostenible",
    "wof:placetype":"venue"
},
  "geometry": {"coordinates":[-3.6918039322,40.4293251038],"type":"Point"}
}