{
  "type": "Feature",
  "properties": {
    "iso:country":"ES",
    "sg:address":"Calle de Eucalipto (del), S/n",
    "sg:city":"Parque Coimbra",
    "sg:orig_category":"Venta, Instalaci\u00d3n De Calefacci\u00d3n",
    "sg:phone":"+34 916 47 67 73",
    "sg:postcode":"28935",
    "sg:province":"Madrid",
    "wof:name":"Instalaciones Coimbra C.b.",
    "wof:placetype":"venue"
},
  "geometry": {"coordinates":[-3.9252781868,40.3130722046],"type":"Point"}
}