{
  "type": "Feature",
  "properties": {
    "addr:full":"Avda Olivares (los), S/n Vilches Ja\u00e9n 23220",
    "addr:postcode":"23220",
    "addr:street":"Avda Olivares Los S / N;Jae\u0301N",
    "iso:country":"ES",
    "sg:address":"Avda Olivares (los), S/n",
    "sg:city":"Vilches",
    "sg:orig_category":"Triper\u00cdas",
    "sg:phone":"+34 953 63 01 13",
    "sg:postcode":"23220",
    "sg:province":"Ja\u00e9n",
    "wof:name":"Comunidad De Bienes Jose Luis Vazque Rodriguez Y Otro",
    "wof:placetype":"venue"
},
  "geometry": {"coordinates":[-3.5133690834,38.2094993591],"type":"Point"}
}