{
  "type": "Feature",
  "properties": {
    "addr:full":"Calle de Poeta Miguel Hernandez, 4 Puente Tocinos Murcia 30006",
    "addr:housenumber":"4",
    "addr:postcode":"30006",
    "addr:street":"Calle De Poeta Miguel Hernandez",
    "iso:country":"ES",
    "sg:address":"Calle de Poeta Miguel Hernandez, 4",
    "sg:city":"Puente Tocinos",
    "sg:orig_category":"Farmacias",
    "sg:phone":"+34 968 30 14 76",
    "sg:postcode":"30006",
    "sg:province":"Murcia",
    "wof:name":"Murfarma S.l.",
    "wof:placetype":"venue"
},
  "geometry": {"coordinates":[-1.1011680365,37.9942703247],"type":"Point"}
}