{
  "type": "Feature",
  "properties": {
    "addr:full":"Carrer de Sant Miquel, 70 Palma Islas Baleares 07002",
    "addr:housenumber":"70",
    "addr:postcode":"07002",
    "addr:street":"Carrer De Sant Miquel",
    "iso:country":"ES",
    "sg:address":"Carrer de Sant Miquel, 70",
    "sg:city":"Palma",
    "sg:orig_category":"Refiner\u00cdas De Petr\u00d3leo",
    "sg:phone":"+34 971 72 05 39",
    "sg:postcode":"07002",
    "sg:province":"Islas Baleares",
    "wof:name":"Sans Bili Maria",
    "wof:placetype":"venue"
},
  "geometry": {"coordinates":[2.6525249481,39.5771713257],"type":"Point"}
}