{
  "type": "Feature",
  "properties": {
    "addr:full":"Plaz Mayor, 1 S. Esteban Gormaz Soria 42330",
    "addr:housenumber":"1",
    "addr:postcode":"42330",
    "addr:street":"Plaz Mayor;S. Esteban Gormaz",
    "iso:country":"ES",
    "sg:address":"Plaz Mayor, 1",
    "sg:city":"S. Esteban Gormaz",
    "sg:orig_category":"Asociaciones Y Clubs Deportivos",
    "sg:phone":"+34 975 35 03 78",
    "sg:postcode":"42330",
    "sg:province":"Soria",
    "wof:name":"Aguilera Manzanares Natividad",
    "wof:placetype":"venue"
},
  "geometry": {"coordinates":[-3.2020728588,41.5730895996],"type":"Point"}
}