{
  "type": "Feature",
  "properties": {
    "addr:full":"Calle de Ezequiel Lopez, 30 Cedeira La Coru\u00f1a 15350",
    "addr:housenumber":"30",
    "addr:postcode":"15350",
    "addr:street":"Calle De Ezequiel Lopez;La Corun\u0303A",
    "iso:country":"ES",
    "sg:address":"Calle de Ezequiel Lopez, 30",
    "sg:city":"Cedeira",
    "sg:orig_category":"Ropa Para Se\u00d1oras (al Por Menor)",
    "sg:phone":"+34 981 48 09 31",
    "sg:postcode":"15350",
    "sg:province":"La Coru\u00f1a",
    "wof:name":"Fernandez Riestra Dulce Nombre De Maria",
    "wof:placetype":"venue"
},
  "geometry": {"coordinates":[-8.0562152863,43.6603164673],"type":"Point"}
}