{
  "type": "Feature",
  "properties": {
    "iso:country":"ES",
    "sg:address":"Avda La Rioja, 27",
    "sg:city":"Haro",
    "sg:orig_category":"Vinos Y Licores (venta Al Por Menor)",
    "sg:phone":"+34 941 30 33 60",
    "sg:postcode":"26200",
    "sg:province":"La Rioja",
    "wof:name":"Vinicola Jarrera S.l.",
    "wof:placetype":"venue"
},
  "geometry": {"coordinates":[-2.8522949219,42.574382782],"type":"Point"}
}