{
  "type": "Feature",
  "properties": {
    "iso:country":"ES",
    "sg:address":"Trva Garbera, 1",
    "sg:city":"Donostia-san Sebastian",
    "sg:orig_category":"Ropa Para Se\u00d1oras Y Caballeros (al Por Menor)",
    "sg:phone":"+34 943 39 35 22",
    "sg:postcode":"20017",
    "sg:province":"Guip\u00f9zcoa",
    "wof:name":"Miner Urdampilleta Jose Luis",
    "wof:placetype":"venue"
},
  "geometry": {"coordinates":[-1.9393490553,43.3108291626],"type":"Point"}
}