{
  "type": "Feature",
  "properties": {
    "addr:full":"Carrer de Boria, 19 Barcelona Barcelona 08003",
    "addr:housenumber":"19",
    "addr:postcode":"08003",
    "addr:street":"Carrer De Boria",
    "iso:country":"ES",
    "sg:address":"Carrer de Boria, 19",
    "sg:city":"Barcelona",
    "sg:orig_category":"Molduras, Junquillos, Listones Y Molduras Perforadas",
    "sg:phone":"+34 932 68 16 73",
    "sg:postcode":"08003",
    "sg:province":"Barcelona",
    "wof:name":"Lopez Martinez Priscila",
    "wof:placetype":"venue"
},
  "geometry": {"coordinates":[2.1788370609,41.3846130371],"type":"Point"}
}