{
  "type": "Feature",
  "properties": {
    "addr:full":"Calle de Castelao, 52 Malaga M\u00e1laga 29004",
    "addr:housenumber":"52",
    "addr:postcode":"29004",
    "addr:street":"Calle De Castelao;Ma\u0301Laga",
    "iso:country":"ES",
    "sg:address":"Calle de Castelao, 52",
    "sg:city":"Malaga",
    "sg:orig_category":"Hormig\u00d3n (m\u00c1quinas E Instalaci\u00d3n)",
    "sg:phone":"+34 952 24 60 17",
    "sg:postcode":"29004",
    "sg:province":"M\u00e1laga",
    "wof:name":"Bombeos Malaga S.l.",
    "wof:placetype":"venue"
},
  "geometry": {"coordinates":[-4.4836130142,36.6958389282],"type":"Point"}
}