{
  "type": "Feature",
  "properties": {
    "addr:full":"Avda Republica Argentina, 32 Le\u00f3n Le\u00f3n 24004",
    "addr:housenumber":"32",
    "addr:postcode":"24004",
    "addr:street":"Avda Republica Argentina;Leo\u0301N",
    "iso:country":"ES",
    "sg:address":"Avda Republica Argentina, 32",
    "sg:city":"Le\u00f3n",
    "sg:orig_category":"Organismos De Turismo",
    "sg:phone":"+34 987 25 01 51",
    "sg:postcode":"24004",
    "sg:province":"Le\u00f3n",
    "wof:name":"Asociacion Provincial De Empresarios De Hosteleria Y Turismo De Leon",
    "wof:placetype":"venue"
},
  "geometry": {"coordinates":[-5.5764870644,42.5959281921],"type":"Point"}
}