{
  "type": "Feature",
  "properties": {
    "addr:full":"Calle de Americas (de Las), 8 Coslada Madrid 28820",
    "addr:housenumber":"8",
    "addr:postcode":"28820",
    "addr:street":"Calle De Americas De Las",
    "iso:country":"ES",
    "sg:address":"Calle de Americas (de Las), 8",
    "sg:city":"Coslada",
    "sg:orig_category":"Centros Empresariales",
    "sg:phone":"+34 916 69 53 15",
    "sg:postcode":"28820",
    "sg:province":"Madrid",
    "wof:name":"Grt Asociacion De Transportistas",
    "wof:placetype":"venue"
},
  "geometry": {"coordinates":[-3.5292677879,40.4338226318],"type":"Point"}
}