{
  "type": "Feature",
  "properties": {
    "addr:full":"Calle de Real, 3 Horcajo De Los Montes Ciudad Real 13110",
    "addr:housenumber":"3",
    "addr:postcode":"13110",
    "addr:street":"Calle De Real",
    "iso:country":"ES",
    "sg:address":"Calle de Real, 3",
    "sg:city":"Horcajo De Los Montes",
    "sg:orig_category":"Hoteles",
    "sg:phone":"+34 926 77 54 77",
    "sg:postcode":"13110",
    "sg:province":"Ciudad Real",
    "wof:name":"Horcatur S.l.",
    "wof:placetype":"venue"
},
  "geometry": {"coordinates":[-4.6505970955,39.3248825073],"type":"Point"}
}