{
  "type": "Feature",
  "properties": {
    "addr:full":"Calle de Francisco De Huerta Y Vega, 3 Alcala Henares Madrid 28805",
    "addr:housenumber":"3",
    "addr:postcode":"28805",
    "addr:street":"Calle De Francisco De Huerta Y Vega",
    "iso:country":"ES",
    "sg:address":"Calle de Francisco De Huerta Y Vega, 3",
    "sg:city":"Alcala Henares",
    "sg:orig_category":"Carnicer\u00cdas, Carnicer\u00cdas",
    "sg:phone":"+34 918 83 23 38",
    "sg:postcode":"28805",
    "sg:province":"Madrid",
    "wof:name":"Diaz Dominguez Fernando",
    "wof:placetype":"venue"
},
  "geometry": {"coordinates":[-3.3583099842,40.4907608032],"type":"Point"}
}