{
  "type": "Feature",
  "properties": {
    "iso:country":"ES",
    "sg:address":"Avgd Colon, 74",
    "sg:city":"Alcasser",
    "sg:orig_category":"Material Ferroviario",
    "sg:phone":"+34 961 24 17 04",
    "sg:postcode":"46290",
    "sg:province":"Valencia",
    "wof:name":"Ute Ave Picassent",
    "wof:placetype":"venue"
},
  "geometry": {"coordinates":[-0.4422290027,39.3660469055],"type":"Point"}
}