{
  "type": "Feature",
  "properties": {
    "iso:country":"ES",
    "sg:address":"Trav Dalt, 6",
    "sg:city":"Barcelona",
    "sg:orig_category":"Estancos",
    "sg:phone":"+34 932 17 30 61",
    "sg:postcode":"08024",
    "sg:province":"Barcelona",
    "wof:name":"Argenti Creus Eugenia",
    "wof:placetype":"venue"
},
  "geometry": {"coordinates":[2.1628940105,41.4073600769],"type":"Point"}
}