{
  "type": "Feature",
  "properties": {
    "iso:country":"ES",
    "sg:address":"Calle de Alegria, 5",
    "sg:city":"Valencia",
    "sg:orig_category":"Guarder\u00cdas",
    "sg:phone":"+34 963 67 43 79",
    "sg:postcode":"46011",
    "sg:province":"Valencia",
    "wof:name":"Serrano Rosado Beatriz",
    "wof:placetype":"venue"
},
  "geometry": {"coordinates":[-0.3322510123,39.4653549194],"type":"Point"}
}