{
  "type": "Feature",
  "properties": {
    "addr:full":"Calle de Espiritu Santo, 5 Medina-sidonia C\u00e1diz 11170",
    "addr:housenumber":"5",
    "addr:postcode":"11170",
    "addr:street":"Calle De Espiritu Santo;Ca\u0301Diz",
    "iso:country":"ES",
    "sg:address":"Calle de Espiritu Santo, 5",
    "sg:city":"Medina-sidonia",
    "sg:orig_category":"Iglesia Cat\u00d3lica",
    "sg:phone":"+34 956 41 00 49",
    "sg:postcode":"11170",
    "sg:province":"C\u00e1diz",
    "wof:name":"Parroquia Santa Maria Casa Rectoral",
    "wof:placetype":"venue"
},
  "geometry": {"coordinates":[-5.9293937683,36.4597396851],"type":"Point"}
}