{
  "type": "Feature",
  "properties": {
    "iso:country":"ES",
    "sg:address":"Calle de Formigal, S/n",
    "sg:city":"Utebo",
    "sg:orig_category":"Molduras, Junquillos, Listones Y Molduras Perforadas",
    "sg:phone":"+34 976 78 61 35",
    "sg:postcode":"50180",
    "sg:province":"Zaragoza",
    "wof:name":"Marco Riesgo Angel",
    "wof:placetype":"venue"
},
  "geometry": {"coordinates":[-1.0251790285,41.716003418],"type":"Point"}
}