{
  "type": "Feature",
  "properties": {
    "addr:full":"Calle de Baltasar Gracian, 4 Zaragoza Zaragoza 50005",
    "addr:housenumber":"4",
    "addr:postcode":"50005",
    "addr:street":"Calle De Baltasar Gracian",
    "iso:country":"ES",
    "sg:address":"Calle de Baltasar Gracian, 4",
    "sg:city":"Zaragoza",
    "sg:orig_category":"Asesor\u00cda Fiscal Y Jur\u00cddica",
    "sg:phone":"+34 976 56 66 59",
    "sg:postcode":"50005",
    "sg:province":"Zaragoza",
    "wof:name":"Arnauda Alvarez Luis Carlos",
    "wof:placetype":"venue"
},
  "geometry": {"coordinates":[-0.8930237293,41.6441917419],"type":"Point"}
}