{
  "type": "Feature",
  "properties": {
    "iso:country":"ES",
    "sg:address":"Calle de Doctor Ma\u00d1as Bernabeu, 13",
    "sg:city":"Malaga",
    "sg:orig_category":"Agencias Y Agentes Comerciales, Representantes",
    "sg:phone":"+34 952 34 67 27",
    "sg:postcode":"29006",
    "sg:province":"M\u00e1laga",
    "wof:name":"Casco Manzanares Maria Angeles",
    "wof:placetype":"venue"
},
  "geometry": {"coordinates":[-4.444671154,36.7104301453],"type":"Point"}
}