{
  "type": "Feature",
  "properties": {
    "iso:country":"ES",
    "sg:address":"Pase Estacion (la), 58",
    "sg:city":"Jaen",
    "sg:orig_category":"Mutuas De Seguros",
    "sg:phone":"+34 953 29 41 61",
    "sg:postcode":"23007",
    "sg:province":"Ja\u00e9n",
    "wof:name":"Mutua Reddis Matt Mutua De Accidentes De Trabajo Y Enfermedades Profesionales De La Seguridad Social",
    "wof:placetype":"venue"
},
  "geometry": {"coordinates":[-3.7890949249,37.7773323059],"type":"Point"}
}