{
  "type": "Feature",
  "properties": {
    "addr:full":"Calle de Luis Velez De Guevara, 8 Madrid Madrid 28012",
    "addr:housenumber":"8",
    "addr:postcode":"madrid;28012",
    "addr:street":"Calle De Luis Velez De Guevara",
    "iso:country":"ES",
    "sg:address":"Calle de Luis Velez De Guevara, 8",
    "sg:city":"Madrid",
    "sg:orig_category":"Tapiceros Y Tapiceros",
    "sg:phone":"+34 913 69 08 14",
    "sg:postcode":"28012",
    "sg:province":"Madrid",
    "wof:name":"Rodriguez Martinez Luis Carlos",
    "wof:placetype":"venue"
},
  "geometry": {"coordinates":[-3.7025399208,40.4132537842],"type":"Point"}
}