{
  "type": "Feature",
  "properties": {
    "iso:country":"ES",
    "sg:address":"Calle de Alcala, 90",
    "sg:city":"Madrid",
    "sg:orig_category":"Perfumer\u00cda (al Por Menor)",
    "sg:phone":"+34 914 31 03 24",
    "sg:postcode":"28009",
    "sg:province":"Madrid",
    "wof:name":"Algalia Perfumes S.l.u.",
    "wof:placetype":"venue"
},
  "geometry": {"coordinates":[-3.6785581112,40.4235572815],"type":"Point"}
}