{
  "type": "Feature",
  "properties": {
    "addr:full":"Avda Infante Juan Manuel, 7 Infante Juan Manuel Murcia 30011",
    "addr:housenumber":"7",
    "addr:postcode":"30011",
    "addr:street":"Avda Infante Juan Manuel",
    "iso:country":"ES",
    "sg:address":"Avda Infante Juan Manuel, 7",
    "sg:city":"Infante Juan Manuel",
    "sg:orig_category":"Bisuteros (fabricaci\u00d3n, Al Por Mayor)",
    "sg:phone":"+34 868 94 54 63",
    "sg:postcode":"30011",
    "sg:province":"Murcia",
    "wof:name":"Lajarin Gonzalez Enrique",
    "wof:placetype":"venue"
},
  "geometry": {"coordinates":[-1.1203730106,37.9814414978],"type":"Point"}
}