{
  "type": "Feature",
  "properties": {
    "addr:full":"Calle de Abedul, 6 Poligono Industrial De Arinaga Las Palmas 35118",
    "addr:housenumber":"6",
    "addr:postcode":"35118",
    "addr:street":"Calle De Abedul;Poligono Industrial De Arinaga Las",
    "iso:country":"ES",
    "sg:address":"Calle de Abedul, 6",
    "sg:city":"Poligono Industrial De Arinaga",
    "sg:orig_category":"Supermercados Y Hipermercados",
    "sg:phone":"+34 928 79 57 69",
    "sg:postcode":"35118",
    "sg:province":"Las Palmas",
    "wof:name":"Comercial Jesuman S.a.",
    "wof:placetype":"venue"
},
  "geometry": {"coordinates":[-15.3927698135,27.8557987213],"type":"Point"}
}