{
  "type": "Feature",
  "properties": {
    "addr:full":"Carrer de Cardenal Rossell, S/n Coll De'n Rabassa Islas Baleares 07007",
    "addr:housenumber":"s / n",
    "addr:postcode":"07007",
    "addr:street":"Carrer De Cardenal Rossell",
    "iso:country":"ES",
    "sg:address":"Carrer de Cardenal Rossell, S/n",
    "sg:city":"Coll De'n Rabassa",
    "sg:orig_category":"Dietistas",
    "sg:phone":"+34 971 74 57 33",
    "sg:postcode":"07007",
    "sg:province":"Islas Baleares",
    "wof:name":"Winoky's S.l.",
    "wof:placetype":"venue"
},
  "geometry": {"coordinates":[2.7029440403,39.5536270142],"type":"Point"}
}