{
  "type": "Feature",
  "properties": {
    "iso:country":"ES",
    "sg:address":"Calle de Sucre, 7",
    "sg:city":"Palmas De Gran Canaria",
    "sg:orig_category":"Importaci\u00d3n",
    "sg:phone":"+34 928 46 80 03",
    "sg:postcode":"35008",
    "sg:province":"Las Palmas",
    "wof:name":"Antonio Sanchez Romero S.a.",
    "wof:placetype":"venue"
},
  "geometry": {"coordinates":[-15.4126653671,28.1696929932],"type":"Point"}
}