{
  "type": "Feature",
  "properties": {
    "iso:country":"ES",
    "sg:address":"Varadero, S/n",
    "sg:city":"Maspalomas",
    "sg:orig_category":"Suministros Y Materiales Industriales",
    "sg:phone":"+34 928 14 37 51",
    "sg:postcode":"35100",
    "sg:province":"Las Palmas",
    "wof:name":"Sumiguel S.l.",
    "wof:placetype":"venue"
},
  "geometry": {"coordinates":[-15.5830888748,27.7700748444],"type":"Point"}
}