{
  "type": "Feature",
  "properties": {
    "addr:full":"Tenor Fleta, 2 Maria Huerva Zaragoza 50430",
    "addr:housenumber":"2",
    "addr:postcode":"50430",
    "addr:street":"Tenor Fleta;Huerva",
    "iso:country":"ES",
    "sg:address":"Tenor Fleta, 2",
    "sg:city":"Maria Huerva",
    "sg:orig_category":"Promotores Constructores",
    "sg:phone":"+34 976 12 39 24",
    "sg:postcode":"50430",
    "sg:province":"Zaragoza",
    "wof:name":"Arnisal S.xxi",
    "wof:placetype":"venue"
},
  "geometry": {"coordinates":[-0.9941346049,41.5415916443],"type":"Point"}
}