{
  "type": "Feature",
  "properties": {
    "iso:country":"ES",
    "sg:address":"Carrer de Jovara, 50",
    "sg:city":"Calella",
    "sg:orig_category":"Librer\u00cdas",
    "sg:phone":"+34 937 69 17 81",
    "sg:postcode":"08370",
    "sg:province":"Barcelona",
    "wof:name":"Turon Puigvert Amparo",
    "wof:placetype":"venue"
},
  "geometry": {"coordinates":[2.6571259499,41.6120834351],"type":"Point"}
}