{
  "type": "Feature",
  "properties": {
    "addr:full":"Ctra Alcazares(hoyamorena), 36 Torre-pacheco Murcia 30700",
    "addr:housenumber":"36",
    "addr:postcode":"30700",
    "addr:street":"Ctra Alcazares Hoyamorena",
    "iso:country":"ES",
    "sg:address":"Ctra Alcazares(hoyamorena), 36",
    "sg:city":"Torre-pacheco",
    "sg:orig_category":"Chapister\u00cda",
    "sg:phone":"+34 968 57 97 84",
    "sg:postcode":"30700",
    "sg:province":"Murcia",
    "wof:name":"Talleres Carrillo Sl",
    "wof:placetype":"venue"
},
  "geometry": {"coordinates":[-1.1302490234,37.9829597473],"type":"Point"}
}