{
  "type": "Feature",
  "properties": {
    "addr:full":"Jesus Artesano, S/n Navas Del Rey Madrid 28695",
    "addr:housenumber":"s / n",
    "addr:postcode":"28695",
    "iso:country":"ES",
    "sg:address":"Jesus Artesano, S/n",
    "sg:city":"Navas Del Rey",
    "sg:orig_category":"Fabricaci\u00d3n De Material Y Sistemas De Se\u00d1alizaci\u00d3n De Carreteras, Urbanos Y De Obras",
    "sg:phone":"+34 918 65 00 14",
    "sg:postcode":"28695",
    "sg:province":"Madrid",
    "wof:name":"Grupisa Infraestructuras S.a.",
    "wof:placetype":"venue"
},
  "geometry": {"coordinates":[-4.2438092232,40.385219574],"type":"Point"}
}