{
  "type": "Feature",
  "properties": {
    "iso:country":"ES",
    "sg:address":"Calle de Virgen De Las Aguas, 5",
    "sg:city":"Sevilla",
    "sg:orig_category":"Fachadas",
    "sg:phone":"+34 954 67 11 30",
    "sg:postcode":"41016",
    "sg:province":"Sevilla",
    "wof:name":"Conlipress Sl",
    "wof:placetype":"venue"
},
  "geometry": {"coordinates":[-5.9126400948,37.3836326599],"type":"Point"}
}