{
  "type": "Feature",
  "properties": {
    "iso:country":"ES",
    "sg:address":"Prj Aceicaos, S/n",
    "sg:city":"Casas De Garcimolina",
    "sg:orig_category":"Alimentaci\u00d3n General (al Por Menor)",
    "sg:phone":"+34 969 36 54 45",
    "sg:postcode":"16338",
    "sg:province":"Cuenca",
    "wof:name":"Producciones Agropecuarias Garcimolina S.l.",
    "wof:placetype":"venue"
},
  "geometry": {"coordinates":[-1.3641159534,39.9503631592],"type":"Point"}
}