{
  "type": "Feature",
  "properties": {
    "addr:full":"Rua Norias (das), 15 Lugo Lugo 27001",
    "addr:housenumber":"15",
    "addr:postcode":"27001",
    "addr:street":"Rua Norias Das",
    "iso:country":"ES",
    "sg:address":"Rua Norias (das), 15",
    "sg:city":"Lugo",
    "sg:orig_category":"Abogados",
    "sg:phone":"+34 982 25 52 58",
    "sg:postcode":"27001",
    "sg:province":"Lugo",
    "wof:name":"Arias Regueira Maria Jose",
    "wof:placetype":"venue"
},
  "geometry": {"coordinates":[-7.5544452667,43.0109138489],"type":"Point"}
}