{
  "type": "Feature",
  "properties": {
    "addr:full":"Luga Poligono Industrial, 1 Camponaraya Le\u00f3n 24410",
    "addr:housenumber":"1",
    "addr:postcode":"24410",
    "addr:street":"Poligono Industrial",
    "iso:country":"ES",
    "sg:address":"Luga Poligono Industrial, 1",
    "sg:city":"Camponaraya",
    "sg:orig_category":"Transporte En General",
    "sg:phone":"+34 987 46 40 42",
    "sg:postcode":"24410",
    "sg:province":"Le\u00f3n",
    "wof:name":"Bimbo-martinez Comercial S.l.u.",
    "wof:placetype":"venue"
},
  "geometry": {"coordinates":[-6.6785559654,42.6148796082],"type":"Point"}
}