{
  "type": "Feature",
  "properties": {
    "iso:country":"ES",
    "sg:address":"Calle de Casas Bajas, 22",
    "sg:city":"Calicasas",
    "sg:orig_category":"\u00c1rboles Frutales",
    "sg:phone":"+34 958 40 96 49",
    "sg:postcode":"18290",
    "sg:province":"Granada",
    "wof:name":"Pravel, Sociedad Cooperativa Andaluza",
    "wof:placetype":"venue"
},
  "geometry": {"coordinates":[-3.6164503098,37.2730979919],"type":"Point"}
}