{
  "type": "Feature",
  "properties": {
    "addr:full":"Calle de Dos De Mayo, 2 Guadalajara Guadalajara 19004",
    "addr:postcode":"19004",
    "addr:street":"Calle De Dos De Mayo 2",
    "iso:country":"ES",
    "sg:address":"Calle de Dos De Mayo, 2",
    "sg:city":"Guadalajara",
    "sg:orig_category":"Autob\u00das (explotaci\u00d3n Y Servicios De)",
    "sg:phone":"+34 949 21 83 68",
    "sg:postcode":"19004",
    "sg:province":"Guadalajara",
    "wof:name":"Autocares Serrano Campos S.l.",
    "wof:placetype":"venue"
},
  "geometry": {"coordinates":[-3.1721732616,40.6354980469],"type":"Point"}
}