{
  "type": "Feature",
  "properties": {
    "addr:full":"Calle de Alonso De Ojeda, 17 Gijon Asturias 33208",
    "addr:housenumber":"17",
    "addr:postcode":"33208",
    "addr:street":"Calle De Alonso De Ojeda",
    "iso:country":"ES",
    "sg:address":"Calle de Alonso De Ojeda, 17",
    "sg:city":"Gijon",
    "sg:orig_category":"Contenedores (mercanc\u00cdas)",
    "sg:phone":"+34 985 38 83 11",
    "sg:postcode":"33208",
    "sg:province":"Asturias",
    "wof:name":"Blazquez Madrid Manuel",
    "wof:placetype":"venue"
},
  "geometry": {"coordinates":[-5.6684041023,43.5307846069],"type":"Point"}
}