{
  "type": "Feature",
  "properties": {
    "addr:full":"Pol Ind Capitana, 3 Lebrija Sevilla 41740",
    "addr:housenumber":"3",
    "addr:postcode":"41740",
    "addr:street":"Capitana",
    "iso:country":"ES",
    "sg:address":"Pol Ind Capitana, 3",
    "sg:city":"Lebrija",
    "sg:orig_category":"Molduras, Junquillos, Listones Y Molduras Perforadas",
    "sg:phone":"+34 955 97 55 04",
    "sg:postcode":"41740",
    "sg:province":"Sevilla",
    "wof:name":"Ruiz Fernandez Benito",
    "wof:placetype":"venue"
},
  "geometry": {"coordinates":[-6.0658698082,36.9205932617],"type":"Point"}
}