{
  "type": "Feature",
  "properties": {
    "addr:full":"Carrer de Antoni Asens, 17 Mora D'ebre Tarragona 43740",
    "addr:housenumber":"17",
    "addr:postcode":"43740",
    "addr:street":"Carrer De Antoni Asens;D'Ebre",
    "iso:country":"ES",
    "sg:address":"Carrer de Antoni Asens, 17",
    "sg:city":"Mora D'ebre",
    "sg:orig_category":"Fotocopias, Reprograf\u00cda",
    "sg:phone":"+34 977 40 22 29",
    "sg:postcode":"43740",
    "sg:province":"Tarragona",
    "wof:name":"Casals Su\u00f1e Maria Teresa",
    "wof:placetype":"venue"
},
  "geometry": {"coordinates":[1.2530610561,41.1208877563],"type":"Point"}
}