{
  "type": "Feature",
  "properties": {
    "addr:full":"Plaz Constitucion (la), 8 Albacete Albacete 02002",
    "addr:housenumber":"8",
    "addr:postcode":"02002",
    "addr:street":"Constitucion La",
    "iso:country":"ES",
    "sg:address":"Plaz Constitucion (la), 8",
    "sg:city":"Albacete",
    "sg:orig_category":"Abogados",
    "sg:phone":"+34 967 52 11 20",
    "sg:postcode":"02002",
    "sg:province":"Albacete",
    "wof:name":"Alfer Abogados S.l.",
    "wof:placetype":"venue"
},
  "geometry": {"coordinates":[-1.8559308052,38.9948654175],"type":"Point"}
}