{
  "type": "Feature",
  "properties": {
    "addr:full":"Calle de San Anton, 5 Madotz Navarra 31879",
    "addr:housenumber":"5",
    "addr:postcode":"31879",
    "addr:street":"Calle De San Anton",
    "iso:country":"ES",
    "sg:address":"Calle de San Anton, 5",
    "sg:city":"Madotz",
    "sg:orig_category":"Fabricaci\u00d3n De Quesos",
    "sg:phone":"+34 948 50 40 88",
    "sg:postcode":"31879",
    "sg:province":"Navarra",
    "wof:name":"Huarte Oscoz Victorino",
    "wof:placetype":"venue"
},
  "geometry": {"coordinates":[-1.895596981,42.9910316467],"type":"Point"}
}