{
  "type": "Feature",
  "properties": {
    "iso:country":"ES",
    "sg:address":"Calle de Estatuto De Galicia, 45",
    "sg:city":"Boiro",
    "sg:orig_category":"Ropa Para Se\u00d1oras Y Caballeros (al Por Menor)",
    "sg:phone":"+34 981 84 86 18",
    "sg:postcode":"15930",
    "sg:province":"La Coru\u00f1a",
    "wof:name":"Okepasa S.l.",
    "wof:placetype":"venue"
},
  "geometry": {"coordinates":[-8.8798904419,42.6483535767],"type":"Point"}
}