{
  "type": "Feature",
  "properties": {
    "iso:country":"ES",
    "sg:address":"Calle de Cristobal Bordiu, 44",
    "sg:city":"Madrid",
    "sg:orig_category":"Asesor\u00cda Sobre Comunicaci\u00d3n De Empresas",
    "sg:phone":"+34 915 33 61 93",
    "sg:postcode":"28003",
    "sg:province":"Madrid",
    "wof:name":"Sabinacum S.l.",
    "wof:placetype":"venue"
},
  "geometry": {"coordinates":[-3.6970329285,40.4427986145],"type":"Point"}
}