{
  "type": "Feature",
  "properties": {
    "iso:country":"ES",
    "sg:address":"Calle de Emilia Pardo Bazan, 12",
    "sg:city":"Coru\u00d1a",
    "sg:orig_category":"Tintorer\u00cdas, Limpieza En Seco",
    "sg:phone":"+34 981 12 00 05",
    "sg:postcode":"15005",
    "sg:province":"La Coru\u00f1a",
    "wof:name":"Pedreira Perez Ana",
    "wof:placetype":"venue"
},
  "geometry": {"coordinates":[-8.4071130753,43.3633041382],"type":"Point"}
}