{
  "type": "Feature",
  "properties": {
    "iso:country":"ES",
    "sg:address":"Calle de Silva, 2",
    "sg:city":"Estepona",
    "sg:orig_category":"Doctores En Medicina",
    "sg:phone":"+34 952 80 16 97",
    "sg:postcode":"29680",
    "sg:province":"M\u00e1laga",
    "wof:name":"Flores Simon Antonio",
    "wof:placetype":"venue"
},
  "geometry": {"coordinates":[-5.1454920769,36.4275054932],"type":"Point"}
}