{
  "type": "Feature",
  "properties": {
    "addr:full":"Pase Pintor Rosales, 14 Madrid Madrid 28008",
    "addr:housenumber":"14",
    "addr:postcode":"madrid;28008",
    "addr:street":"Pintor Rosales",
    "iso:country":"ES",
    "sg:address":"Pase Pintor Rosales, 14",
    "sg:city":"Madrid",
    "sg:orig_category":"Abogados",
    "sg:phone":"+34 915 48 17 77",
    "sg:postcode":"28008",
    "sg:province":"Madrid",
    "wof:name":"De Aragon Balboa-sandoval Carlos",
    "wof:placetype":"venue"
},
  "geometry": {"coordinates":[-3.718503952,40.4257621765],"type":"Point"}
}