{
  "type": "Feature",
  "properties": {
    "iso:country":"ES",
    "sg:address":"Avda Padre Monta\u00d1a, S/n",
    "sg:city":"Caridad",
    "sg:orig_category":"Florister\u00cdas",
    "sg:phone":"+34 985 47 80 31",
    "sg:postcode":"33750",
    "sg:province":"Asturias",
    "wof:name":"Lopez Gonzalez Ramon",
    "wof:placetype":"venue"
},
  "geometry": {"coordinates":[-6.8267917633,43.5491752625],"type":"Point"}
}