{
  "type": "Feature",
  "properties": {
    "addr:full":"Calle de Maria Auxiliadora, 27 Salamanca Salamanca 37004",
    "addr:housenumber":"27",
    "addr:postcode":"37004",
    "addr:street":"Calle De Maria Auxiliadora",
    "iso:country":"ES",
    "sg:address":"Calle de Maria Auxiliadora, 27",
    "sg:city":"Salamanca",
    "sg:orig_category":"Freidur\u00cdas: Equipos Y Suministros",
    "sg:phone":"+34 923 22 43 44",
    "sg:postcode":"37004",
    "sg:province":"Salamanca",
    "wof:name":"Canete Sillero Federico",
    "wof:placetype":"venue"
},
  "geometry": {"coordinates":[-5.6589012146,40.9702835083],"type":"Point"}
}