{
  "type": "Feature",
  "properties": {
    "iso:country":"ES",
    "sg:address":"Carrer de Dos De Maig, 225",
    "sg:city":"Barcelona",
    "sg:orig_category":"M\u00c9dicos: Fisioterapia Y Rehabilitaci\u00d3n",
    "sg:phone":"+34 932 31 64 04",
    "sg:postcode":"08013",
    "sg:province":"Barcelona",
    "sg:website":"www.clinicaandresbosch.com",
    "wof:name":"Andres Ortu\u00f1o Josep Gabriel",
    "wof:placetype":"venue"
},
  "geometry": {"coordinates":[2.1828064919,41.406463623],"type":"Point"}
}