{
  "type": "Feature",
  "properties": {
    "iso:country":"ES",
    "sg:address":"Calle de Felipe Valls, 24",
    "sg:city":"Benimamet-beniferri",
    "sg:orig_category":"Reposter\u00cdas",
    "sg:phone":"+34 963 40 17 37",
    "sg:postcode":"46035",
    "sg:province":"Valencia",
    "wof:name":"Polo Herreros Jose Luis",
    "wof:placetype":"venue"
},
  "geometry": {"coordinates":[-0.4184660017,39.5000953674],"type":"Point"}
}