{
  "type": "Feature",
  "properties": {
    "addr:full":"Grup Solivent, 51 Grup Solivent Girona 17170",
    "addr:housenumber":"51",
    "addr:postcode":"17170",
    "addr:street":"Solivent",
    "iso:country":"ES",
    "sg:address":"Grup Solivent, 51",
    "sg:city":"Grup Solivent",
    "sg:orig_category":"Agentes Generales De Seguros",
    "sg:phone":"+34 972 43 07 78",
    "sg:postcode":"17170",
    "sg:province":"Girona",
    "wof:name":"Domenech Domenech Antonio",
    "wof:placetype":"venue"
},
  "geometry": {"coordinates":[2.6044440269,42.0092544556],"type":"Point"}
}