{
  "type": "Feature",
  "properties": {
    "addr:full":"Calle de Montes Tirado, Teniente, 10 Melilla Melilla 52002",
    "addr:housenumber":"10",
    "addr:postcode":"52002",
    "addr:street":"Calle De Montes Tirado Teniente",
    "iso:country":"ES",
    "sg:address":"Calle de Montes Tirado, Teniente, 10",
    "sg:city":"Melilla",
    "sg:orig_category":"Alimentaci\u00d3n General (al Por Menor)",
    "sg:phone":"+34 952 68 29 48",
    "sg:postcode":"52002",
    "sg:province":"Melilla",
    "wof:name":"Halifa Mohamed Nadir",
    "wof:placetype":"venue"
},
  "geometry": {"coordinates":[-2.9458100796,35.2976875305],"type":"Point"}
}