{
  "type": "Feature",
  "properties": {
    "addr:full":"Calle de Santa Ana, 17 Miguel Esteban Toledo 45830",
    "addr:housenumber":"17",
    "addr:postcode":"45830",
    "addr:street":"Calle De Santa Ana;Miguel Esteban",
    "iso:country":"ES",
    "sg:address":"Calle de Santa Ana, 17",
    "sg:city":"Miguel Esteban",
    "sg:orig_category":"Trabajos De Soldaduras",
    "sg:phone":"+34 925 17 28 17",
    "sg:postcode":"45830",
    "sg:province":"Toledo",
    "wof:name":"Solados Y Alicatados Carreras S.l.",
    "wof:placetype":"venue"
},
  "geometry": {"coordinates":[-3.0753777027,39.5250205994],"type":"Point"}
}