{
  "type": "Feature",
  "properties": {
    "iso:country":"ES",
    "sg:address":"Calle de Teatro, S/n",
    "sg:city":"Luanco",
    "sg:orig_category":"Inmobiliaria (agencias)",
    "sg:phone":"+34 985 88 25 35",
    "sg:postcode":"33440",
    "sg:province":"Asturias",
    "wof:name":"Vetusta Gestion Inmobiliaria S.l.",
    "wof:placetype":"venue"
},
  "geometry": {"coordinates":[-5.7917981148,43.615562439],"type":"Point"}
}