{
  "type": "Feature",
  "properties": {
    "iso:country":"ES",
    "sg:address":"C/ Sant Lluis, De, 5",
    "sg:city":"Porto Cristo",
    "sg:orig_category":"Peluqueros: De Se\u00d1oras",
    "sg:phone":"+34 971 82 10 73",
    "sg:postcode":"07680",
    "sg:province":"Islas Baleares",
    "wof:name":"Riera Duran Maria Isabel",
    "wof:placetype":"venue"
},
  "geometry": {"coordinates":[3.3334379196,39.5397911072],"type":"Point"}
}