{
  "type": "Feature",
  "properties": {
    "addr:full":"Pg Paisos Catalans, 60 Salt Girona 17190",
    "addr:housenumber":"60",
    "addr:postcode":"17190",
    "addr:street":"Pg Paisos Catalans",
    "iso:country":"ES",
    "sg:address":"Pg Paisos Catalans, 60",
    "sg:city":"Salt",
    "sg:orig_category":"Promotores Constructores",
    "sg:phone":"+34 972 24 47 91",
    "sg:postcode":"17190",
    "sg:province":"Girona",
    "wof:name":"Ger-fer Consgirona S.l.",
    "wof:placetype":"venue"
},
  "geometry": {"coordinates":[2.7894990444,41.9720840454],"type":"Point"}
}