{
  "type": "Feature",
  "properties": {
    "iso:country":"ES",
    "sg:address":"Calle de Rodeo, 7",
    "sg:city":"Fregenal Sierra",
    "sg:orig_category":"Sociedades, Compa\u00d1\u00cdas Aseguradoras",
    "sg:phone":"+34 924 70 04 77",
    "sg:postcode":"06340",
    "sg:province":"Badajoz",
    "wof:name":"David Alfonso Agencia De Seguros S.l.",
    "wof:placetype":"venue"
},
  "geometry": {"coordinates":[-6.6518068314,38.1678276062],"type":"Point"}
}