{
  "type": "Feature",
  "properties": {
    "iso:country":"ES",
    "sg:address":"Avda Camilo Alonso Vega, 18",
    "sg:city":"Santander",
    "sg:orig_category":"Zapatos (al Por Menor)",
    "sg:phone":"+34 942 37 24 68",
    "sg:postcode":"39007",
    "sg:province":"Cantabria",
    "wof:name":"Martinez Rubira Enrique",
    "wof:placetype":"venue"
},
  "geometry": {"coordinates":[-3.8256840706,43.4600982666],"type":"Point"}
}