{
  "type": "Feature",
  "properties": {
    "iso:country":"ES",
    "sg:address":"Calle de Magallanes, 4",
    "sg:city":"Pobla Llarga",
    "sg:orig_category":"Electricidad (montaje, Ensamblaje De Componentes)",
    "sg:phone":"+34 962 59 10 25",
    "sg:postcode":"46670",
    "sg:province":"Valencia",
    "wof:name":"Talleres Hermanos Sanz Vaya S.l.",
    "wof:placetype":"venue"
},
  "geometry": {"coordinates":[-0.4787180126,39.0842514038],"type":"Point"}
}