{
  "type": "Feature",
  "properties": {
    "iso:country":"ES",
    "sg:address":"Av Icaria, 141",
    "sg:city":"Barcelona",
    "sg:orig_category":"Abogados",
    "sg:phone":"+34 932 25 47 12",
    "sg:postcode":"08005",
    "sg:province":"Barcelona",
    "wof:name":"Del Rio Arce Jose Joaquin",
    "wof:placetype":"venue"
},
  "geometry": {"coordinates":[2.2008039951,41.3948326111],"type":"Point"}
}