{
  "type": "Feature",
  "properties": {
    "iso:country":"ES",
    "sg:address":"Carrer de Igualada, 1",
    "sg:city":"Vilafranca Penedes",
    "sg:orig_category":"Electricidad: Instaladores",
    "sg:phone":"+34 938 18 23 33",
    "sg:postcode":"08720",
    "sg:province":"Barcelona",
    "wof:name":"Instalacions Parera S.l.",
    "wof:placetype":"venue"
},
  "geometry": {"coordinates":[1.7025170326,41.3477973938],"type":"Point"}
}