{
  "type": "Feature",
  "properties": {
    "addr:full":"Calle de San Jaime, 26 Majadahonda Madrid 28220",
    "addr:housenumber":"26",
    "addr:postcode":"28220",
    "addr:street":"Calle De San Jaime",
    "iso:country":"ES",
    "sg:address":"Calle de San Jaime, 26",
    "sg:city":"Majadahonda",
    "sg:orig_category":"Fabricaci\u00d3n, Importaci\u00d3n De Material Y Sistemas De Telecomunicaciones",
    "sg:phone":"+34 916 34 53 25",
    "sg:postcode":"28220",
    "sg:province":"Madrid",
    "wof:name":"Jimenez Marti Ramon",
    "wof:placetype":"venue"
},
  "geometry": {"coordinates":[-3.8800458908,40.4699935913],"type":"Point"}
}