{
  "type": "Feature",
  "properties": {
    "iso:country":"ES",
    "sg:address":"Av Catalunya, 23",
    "sg:city":"Sant Joan De Palamos",
    "sg:orig_category":"Sociedades, Compa\u00d1\u00cdas Aseguradoras",
    "sg:phone":"+34 972 31 83 43",
    "sg:postcode":"17230",
    "sg:province":"Girona",
    "wof:name":"Antoni Vega S.l.",
    "wof:placetype":"venue"
},
  "geometry": {"coordinates":[3.1384882927,41.871887207],"type":"Point"}
}