{
  "type": "Feature",
  "properties": {
    "iso:country":"ES",
    "sg:address":"Calle de Fernan Velazquez, 18",
    "sg:city":"Lebrija",
    "sg:orig_category":"Cl\u00cdnicas Dentales",
    "sg:phone":"+34 955 97 14 31",
    "sg:postcode":"41740",
    "sg:province":"Sevilla",
    "wof:name":"Caro Castro Carmelo",
    "wof:placetype":"venue"
},
  "geometry": {"coordinates":[-6.0778870583,36.9182624817],"type":"Point"}
}