{
  "type": "Feature",
  "properties": {
    "addr:full":"Crta Azucarera-intelhorce (pi Gudalhorc), 20 Malaga M\u00e1laga 29004",
    "addr:housenumber":"20",
    "addr:postcode":"29004",
    "addr:street":"Crta Azucarera-Intelhorce Pi Gudalhorc;Ma\u0301Laga",
    "iso:country":"ES",
    "sg:address":"Crta Azucarera-intelhorce (pi Gudalhorc), 20",
    "sg:city":"Malaga",
    "sg:orig_category":"Distribuci\u00d3n De Petr\u00d3leo Y Derivados",
    "sg:phone":"+34 952 23 74 99",
    "sg:postcode":"29004",
    "sg:province":"M\u00e1laga",
    "wof:name":"Congelados Lopemar S.l.",
    "wof:placetype":"venue"
},
  "geometry": {"coordinates":[-4.4788208008,36.6886405945],"type":"Point"}
}