{
  "type": "Feature",
  "properties": {
    "iso:country":"ES",
    "sg:address":"Costa Llimpa, S/n",
    "sg:city":"Alaior",
    "sg:orig_category":"Promotores Constructores",
    "sg:phone":"+34 971 37 81 40",
    "sg:postcode":"07730",
    "sg:province":"Islas Baleares",
    "sg:website":"www.compromisosurbanos.com",
    "wof:name":"Compromisos Urbanos S.l.",
    "wof:placetype":"venue"
},
  "geometry": {"coordinates":[4.1487078667,39.9349632263],"type":"Point"}
}