{
  "type": "Feature",
  "properties": {
    "iso:country":"ES",
    "sg:address":"Calle de Campo, 3",
    "sg:city":"Soria",
    "sg:orig_category":"Fisioterapia",
    "sg:phone":"+34 975 22 55 75",
    "sg:postcode":"42001",
    "sg:province":"Soria",
    "wof:name":"Delgado Ordax Miriam",
    "wof:placetype":"venue"
},
  "geometry": {"coordinates":[-2.4705612659,41.7683944702],"type":"Point"}
}