{
  "type": "Feature",
  "properties": {
    "addr:full":"Carrer de L'artesania, 5 Barcelona Barcelona 08016",
    "addr:housenumber":"5",
    "addr:postcode":"08016",
    "addr:street":"Carrer De L'Artesania",
    "iso:country":"ES",
    "sg:address":"Carrer de L'artesania, 5",
    "sg:city":"Barcelona",
    "sg:orig_category":"Promotores Constructores",
    "sg:phone":"+34 932 76 83 33",
    "sg:postcode":"08016",
    "sg:province":"Barcelona",
    "wof:name":"Armen-cat Construcciones Y Edificaciones S.l",
    "wof:placetype":"venue"
},
  "geometry": {"coordinates":[2.1759343147,41.4387664795],"type":"Point"}
}