{
  "type": "Feature",
  "properties": {
    "addr:full":"Carrer de Major, 25 Arbo\u00e7 Tarragona 43720",
    "addr:housenumber":"25",
    "addr:postcode":"43720",
    "addr:street":"Carrer De Major",
    "iso:country":"ES",
    "sg:address":"Carrer de Major, 25",
    "sg:city":"Arbo\u00e7",
    "sg:orig_category":"Molduras, Junquillos, Listones Y Molduras Perforadas",
    "sg:phone":"+34 977 67 02 30",
    "sg:postcode":"43720",
    "sg:province":"Tarragona",
    "wof:name":"Victoria L'arbo\u00e7 S.l.l.",
    "wof:placetype":"venue"
},
  "geometry": {"coordinates":[1.6038049459,41.2678565979],"type":"Point"}
}