{
  "type": "Feature",
  "properties": {
    "addr:full":"Carrer de Doctor Letamendi, 18 Barcelona Barcelona 08031",
    "addr:housenumber":"18",
    "addr:postcode":"08031",
    "addr:street":"Carrer De Doctor Letamendi",
    "iso:country":"ES",
    "sg:address":"Carrer de Doctor Letamendi, 18",
    "sg:city":"Barcelona",
    "sg:orig_category":"Molduras, Junquillos, Listones Y Molduras Perforadas",
    "sg:phone":"+34 934 27 87 47",
    "sg:postcode":"08031",
    "sg:province":"Barcelona",
    "wof:name":"Galvez Caro Miguel",
    "wof:placetype":"venue"
},
  "geometry": {"coordinates":[2.1595020294,41.4348716736],"type":"Point"}
}