{
  "type": "Feature",
  "properties": {
    "iso:country":"ES",
    "sg:address":"Calle de Santa Teresa De Jesus, 14",
    "sg:city":"Gijon",
    "sg:orig_category":"Ingeniero",
    "sg:phone":"+34 985 38 62 70",
    "sg:postcode":"33208",
    "sg:province":"Asturias",
    "wof:name":"Martinez Perez Ignacio",
    "wof:placetype":"venue"
},
  "geometry": {"coordinates":[-5.6665449142,43.5352706909],"type":"Point"}
}