{
  "type": "Feature",
  "properties": {
    "iso:country":"ES",
    "sg:address":"Calle de Lamuza, 33",
    "sg:city":"Llodio",
    "sg:orig_category":"Asociaciones Humanitarias, De Cooperaci\u00d3n, De Acci\u00d3n Social",
    "sg:phone":"+34 946 72 50 61",
    "sg:postcode":"01400",
    "sg:province":"\u00c1lava",
    "wof:name":"Asociacion Prodeficientes Mentales De Alava",
    "wof:placetype":"venue"
},
  "geometry": {"coordinates":[-2.9656398296,43.1456604004],"type":"Point"}
}