{
  "type": "Feature",
  "properties": {
    "iso:country":"ES",
    "sg:address":"Carrer de Marti Costa, 11",
    "sg:city":"Santa Perpetua De Mogoda",
    "sg:orig_category":"Tintorer\u00cdas, Limpieza En Seco",
    "sg:phone":"+34 935 60 70 06",
    "sg:postcode":"08130",
    "sg:province":"Barcelona",
    "wof:name":"Ruiz Jimenez Carmen",
    "wof:placetype":"venue"
},
  "geometry": {"coordinates":[2.1803619862,41.53540802],"type":"Point"}
}