{
  "type": "Feature",
  "properties": {
    "iso:country":"ES",
    "sg:address":"Calle de San Romualdo, 26",
    "sg:city":"Madrid",
    "sg:orig_category":"Arquitectos",
    "sg:phone":"+34 917 54 55 96",
    "sg:postcode":"28037",
    "sg:province":"Madrid",
    "wof:name":"C.d.e. Arquitectura C.b",
    "wof:placetype":"venue"
},
  "geometry": {"coordinates":[-3.6216089725,40.4380226135],"type":"Point"}
}