{
  "type": "Feature",
  "properties": {
    "addr:full":"Calle de Lusitania, 26 Ayamonte Huelva 21400",
    "addr:housenumber":"26",
    "addr:postcode":"21400",
    "addr:street":"Calle De Lusitania",
    "iso:country":"ES",
    "sg:address":"Calle de Lusitania, 26",
    "sg:city":"Ayamonte",
    "sg:orig_category":"Cajas Para Embalar",
    "sg:phone":"+34 959 32 10 42",
    "sg:postcode":"21400",
    "sg:province":"Huelva",
    "sg:website":"www.ruralvia.com",
    "wof:name":"Caja Rural Del Sur Sociedad Cooperativa",
    "wof:placetype":"venue"
},
  "geometry": {"coordinates":[-7.4090209007,37.2130584717],"type":"Point"}
}