{
  "type": "Feature",
  "properties": {
    "addr:full":"Calle de Maestro Guerrero, S/n Fuensalida Toledo 45510",
    "addr:postcode":"45510",
    "addr:street":"Calle De Maestro Guerrero S / N",
    "iso:country":"ES",
    "sg:address":"Calle de Maestro Guerrero, S/n",
    "sg:city":"Fuensalida",
    "sg:orig_category":"Confecci\u00d3n De Zapatos",
    "sg:phone":"+34 925 78 42 78",
    "sg:postcode":"45510",
    "sg:province":"Toledo",
    "wof:name":"Artesano Conejo S.a.",
    "wof:placetype":"venue"
},
  "geometry": {"coordinates":[-4.2151069641,40.0533752441],"type":"Point"}
}