{
  "type": "Feature",
  "properties": {
    "addr:full":"Praj Carretera De Caudete, S/n Campo Abajo Murcia 30510",
    "addr:housenumber":"s / n",
    "addr:postcode":"30510",
    "addr:street":"Carretera De Caudete",
    "iso:country":"ES",
    "sg:address":"Praj Carretera De Caudete, S/n",
    "sg:city":"Campo Abajo",
    "sg:orig_category":"Fabricaci\u00d3n De Taburetes, Sillas Y Sillones",
    "sg:phone":"+34 968 75 06 43",
    "sg:postcode":"30510",
    "sg:province":"Murcia",
    "wof:name":"Silleria Soriano Y Lopez S.l.",
    "wof:placetype":"venue"
},
  "geometry": {"coordinates":[-1.1149940491,38.6145591736],"type":"Point"}
}