{
  "type": "Feature",
  "properties": {
    "addr:full":"Pl. San Sebastian, 3 Toro Zamora 49800",
    "addr:housenumber":"3",
    "addr:postcode":"49800",
    "addr:street":"Pl. San Sebastian",
    "iso:country":"ES",
    "sg:address":"Pl. San Sebastian, 3",
    "sg:city":"Toro",
    "sg:orig_category":"Autob\u00das (explotaci\u00d3n Y Servicios De)",
    "sg:phone":"+34 980 69 10 05",
    "sg:postcode":"49800",
    "sg:province":"Zamora",
    "wof:name":"Rico Gonzalez Lucia",
    "wof:placetype":"venue"
},
  "geometry": {"coordinates":[-5.3906588554,41.525844574],"type":"Point"}
}