{
  "type": "Feature",
  "properties": {
    "iso:country":"ES",
    "sg:address":"Carr Marisc, 6",
    "sg:city":"Port D'alcudia",
    "sg:orig_category":"Servicios De Telecomunicaciones",
    "sg:phone":"+34 971 54 95 31",
    "sg:postcode":"07410",
    "sg:province":"Islas Baleares",
    "sg:website":"www.bts.es",
    "wof:name":"Business Telecom Systems S.l.",
    "wof:placetype":"venue"
},
  "geometry": {"coordinates":[3.1316530704,39.8428344727],"type":"Point"}
}