{
  "type": "Feature",
  "properties": {
    "iso:country":"ES",
    "sg:address":"Ctra Carretera Carrion (poligono Industrial), Km. 0003,5",
    "sg:city":"Ciudad Real",
    "sg:orig_category":"M\u00c1rmoles, Granitos Y Piedras Naturales",
    "sg:phone":"+34 926 27 49 50",
    "sg:postcode":"13005",
    "sg:province":"Ciudad Real",
    "wof:name":"Fergo C.b.",
    "wof:placetype":"venue"
},
  "geometry": {"coordinates":[-3.9525969028,38.9611473083],"type":"Point"}
}