{
  "type": "Feature",
  "properties": {
    "addr:full":"Calle de San Vicente, S/n Oviedo Asturias 33003",
    "addr:housenumber":"s / n",
    "addr:postcode":"33003",
    "addr:street":"Calle De San Vicente",
    "iso:country":"ES",
    "sg:address":"Calle de San Vicente, S/n",
    "sg:city":"Oviedo",
    "sg:orig_category":"Promotores Constructores",
    "sg:phone":"+34 985 21 34 56",
    "sg:postcode":"33003",
    "sg:province":"Asturias",
    "wof:name":"Construcciones Alfredo Rodriguez Sl Y Tecnicas Arqut Monumental Sa",
    "wof:placetype":"venue"
},
  "geometry": {"coordinates":[-5.8421640396,43.3623809814],"type":"Point"}
}