{
  "type": "Feature",
  "properties": {
    "addr:full":"Calle de Siervas De Jesus, 15 Burriana Castell\u00f3n 12530",
    "addr:housenumber":"15",
    "addr:postcode":"12530",
    "addr:street":"Calle De Siervas;Jesus",
    "iso:country":"ES",
    "sg:address":"Calle de Siervas De Jesus, 15",
    "sg:city":"Burriana",
    "sg:classifiers":[
        {
            "category":"Autos & Motor Vehicles",
            "subcategory":"Automobile Sales",
            "type":"Retail Goods"
        }
    ],
    "sg:phone":"+34 964 51 13 98",
    "sg:postcode":"12530",
    "sg:province":"Castell\u00f3n",
    "wof:name":"Autoescuela Vergara S.c.",
    "wof:placetype":"venue"
},
  "geometry": {"coordinates":[-0.0852660015,39.8894195557],"type":"Point"}
}