{
  "type": "Feature",
  "properties": {
    "iso:country":"ES",
    "sg:address":"Avda Constitucion, 73",
    "sg:city":"Mansilla Mulas",
    "sg:orig_category":"Negocio De Materiales De Construcci\u00d3n",
    "sg:phone":"+34 987 31 12 31",
    "sg:postcode":"24210",
    "sg:province":"Le\u00f3n",
    "wof:name":"Juventino Alvarez S.l.",
    "wof:placetype":"venue"
},
  "geometry": {"coordinates":[-5.4169688225,42.4984016418],"type":"Point"}
}