{
  "type": "Feature",
  "properties": {
    "addr:full":"Carr Migdia, 16 Figueres Girona 17600",
    "addr:housenumber":"16",
    "addr:postcode":"17600",
    "addr:street":"Carr Migdia",
    "iso:country":"ES",
    "sg:address":"Carr Migdia, 16",
    "sg:city":"Figueres",
    "sg:orig_category":"Molduras, Junquillos, Listones Y Molduras Perforadas",
    "sg:phone":"+34 972 50 86 72",
    "sg:postcode":"17600",
    "sg:province":"Girona",
    "wof:name":"Moreno Megias Enrique",
    "wof:placetype":"venue"
},
  "geometry": {"coordinates":[2.9674179554,42.263053894],"type":"Point"}
}