{
  "type": "Feature",
  "properties": {
    "addr:full":"Calle de Alfonso Xii, 6 Madrid Madrid 28014",
    "addr:housenumber":"6",
    "addr:postcode":"28014",
    "addr:street":"Calle De Alfonso Xii",
    "iso:country":"ES",
    "sg:address":"Calle de Alfonso Xii, 6",
    "sg:city":"Madrid",
    "sg:classifiers":[
        {
            "category":"Arts & Performance",
            "subcategory":"Art Gallery",
            "type":"Entertainment"
        }
    ],
    "sg:phone":"+34 915 21 07 16",
    "sg:postcode":"28014",
    "sg:province":"Madrid",
    "sg:tags":[
        "arte",
        "de",
        "galer\u00cdas"
    ],
    "wof:name":"Agueira S.a.",
    "wof:placetype":"venue"
},
  "geometry": {"coordinates":[-3.6889207363,40.4187011719],"type":"Point"}
}