{
  "type": "Feature",
  "properties": {
    "iso:country":"ES",
    "sg:address":"Calle de Andre Gide, 38",
    "sg:city":"Malaga",
    "sg:orig_category":"Ropa Y Accesorios",
    "sg:phone":"+34 952 17 33 97",
    "sg:postcode":"29004",
    "sg:province":"M\u00e1laga",
    "wof:name":"Dise\u00d1o Zus S.l.",
    "wof:placetype":"venue"
},
  "geometry": {"coordinates":[-4.4749836922,36.6909408569],"type":"Point"}
}