{
  "type": "Feature",
  "properties": {
    "addr:full":"Barr San Juan, 22 San Juan De Muskiz Vizcaya 48550",
    "addr:housenumber":"22",
    "addr:postcode":"48550",
    "addr:street":"San Juan",
    "iso:country":"ES",
    "sg:address":"Barr San Juan, 22",
    "sg:city":"San Juan De Muskiz",
    "sg:orig_category":"Asociaciones, Organismos Culturales Y Socioeducativos",
    "sg:phone":"+34 946 70 75 77",
    "sg:postcode":"48550",
    "sg:province":"Vizcaya",
    "wof:name":"Eusko Alkartasuna De Muskiz",
    "wof:placetype":"venue"
},
  "geometry": {"coordinates":[-3.1229119301,43.3212242126],"type":"Point"}
}