{
  "type": "Feature",
  "properties": {
    "iso:country":"ES",
    "sg:address":"Avda Reyes Catolicos, 1",
    "sg:city":"Alcala Henares",
    "sg:orig_category":"Asesor\u00cda Fiscal Y Jur\u00cddica",
    "sg:phone":"+34 918 80 38 77",
    "sg:postcode":"28802",
    "sg:province":"Madrid",
    "wof:name":"Tecnica Contable Informatizada S. L.",
    "wof:placetype":"venue"
},
  "geometry": {"coordinates":[-3.3725960255,40.4781913757],"type":"Point"}
}