{
  "type": "Feature",
  "properties": {
    "addr:full":"Carr Colada D'arago, 1 Pai I Capellans Valencia 46930",
    "addr:housenumber":"1",
    "addr:postcode":"46930",
    "addr:street":"Carr Colada D'Arago",
    "iso:country":"ES",
    "sg:address":"Carr Colada D'arago, 1",
    "sg:city":"Pai I Capellans",
    "sg:orig_category":"Materiales De Construcci\u00d3n, Herramientas",
    "sg:phone":"+34 961 92 11 11",
    "sg:postcode":"46930",
    "sg:province":"Valencia",
    "wof:name":"Accesorios Y Maquinaria Logarcan S.l.",
    "wof:placetype":"venue"
},
  "geometry": {"coordinates":[-0.3768048882,39.4702377319],"type":"Point"}
}