{
  "type": "Feature",
  "properties": {
    "iso:country":"ES",
    "sg:address":"Calle de Montesa, 32",
    "sg:city":"Madrid",
    "sg:orig_category":"Comerciantes Al Por Mayor De Vinos, Licores Y Alcoholes",
    "sg:phone":"+34 914 01 32 22",
    "sg:postcode":"28006",
    "sg:province":"Madrid",
    "wof:name":"Vera Ecija Rafael",
    "wof:placetype":"venue"
},
  "geometry": {"coordinates":[-3.67197299,40.430103302],"type":"Point"}
}