{
  "type": "Feature",
  "properties": {
    "addr:full":"C/ Casa Blanca, 5 Alcoi Alicante 03801",
    "addr:housenumber":"5",
    "addr:postcode":"03801",
    "addr:street":"C / Casa Blanca",
    "iso:country":"ES",
    "sg:address":"C/ Casa Blanca, 5",
    "sg:city":"Alcoi",
    "sg:orig_category":"Albergues",
    "sg:phone":"+34 965 54 72 72",
    "sg:postcode":"03801",
    "sg:province":"Alicante",
    "wof:name":"Hostal Savoy S.l.",
    "wof:placetype":"venue"
},
  "geometry": {"coordinates":[-0.4718799889,38.6974754333],"type":"Point"}
}