{
  "type": "Feature",
  "properties": {
    "iso:country":"ES",
    "sg:address":"Calle de Arcpte Navarro Nogueroles, 6",
    "sg:city":"Torrent",
    "sg:orig_category":"Inversiones",
    "sg:phone":"+34 961 55 39 10",
    "sg:postcode":"46900",
    "sg:province":"Valencia",
    "wof:name":"Sogevasa Inversiones S.l.",
    "wof:placetype":"venue"
},
  "geometry": {"coordinates":[-0.5352355838,39.4127235413],"type":"Point"}
}