{
  "type": "Feature",
  "properties": {
    "addr:full":"Avda Quevedo, 33 Le\u00f3n Le\u00f3n 24009",
    "addr:housenumber":"33",
    "addr:postcode":"24009",
    "addr:street":"Avda Quevedo;Leo\u0301N",
    "iso:country":"ES",
    "sg:address":"Avda Quevedo, 33",
    "sg:city":"Le\u00f3n",
    "sg:orig_category":"Confecci\u00d3n (fabricaci\u00d3n, Al Por Mayor)",
    "sg:phone":"+34 987 27 06 48",
    "sg:postcode":"24009",
    "sg:province":"Le\u00f3n",
    "wof:name":"Modas Queen S.l.",
    "wof:placetype":"venue"
},
  "geometry": {"coordinates":[-5.5872993469,42.5996246338],"type":"Point"}
}