{
  "type": "Feature",
  "properties": {
    "iso:country":"ES",
    "sg:address":"Carrer de Torres Jordi, 9",
    "sg:city":"Espluga Francoli",
    "sg:orig_category":"Fabricaci\u00d3n De Productos Textiles Sin Tejer",
    "sg:phone":"+34 977 87 00 11",
    "sg:postcode":"43440",
    "sg:province":"Tarragona",
    "wof:name":"Cuadrat Palau Francisco",
    "wof:placetype":"venue"
},
  "geometry": {"coordinates":[1.1036549807,41.3964309692],"type":"Point"}
}