{
  "type": "Feature",
  "properties": {
    "iso:country":"ES",
    "sg:address":"Avda Francia (de), 5",
    "sg:city":"Playa Del Ingles",
    "sg:orig_category":"Inmobiliaria (agencias)",
    "sg:phone":"+34 928 76 01 55",
    "sg:postcode":"35100",
    "sg:province":"Las Palmas",
    "wof:name":"Copucen S.l.",
    "wof:placetype":"venue"
},
  "geometry": {"coordinates":[-15.5761032104,27.7511062622],"type":"Point"}
}