{
  "type": "Feature",
  "properties": {
    "iso:country":"ES",
    "sg:address":"Carrer de Puig-agut, 16",
    "sg:city":"Manlleu",
    "sg:orig_category":"Fabricaci\u00d3n De Juguetes Autom\u00c1ticos",
    "sg:phone":"+34 938 50 61 57",
    "sg:postcode":"08560",
    "sg:province":"Barcelona",
    "wof:name":"Rose S.l.",
    "wof:placetype":"venue"
},
  "geometry": {"coordinates":[2.2817640305,42.0046234131],"type":"Point"}
}