{
  "type": "Feature",
  "properties": {
    "addr:full":"Calle de Corredera, 4 Ponferrada Le\u00f3n 24400",
    "addr:housenumber":"4",
    "addr:postcode":"24400",
    "addr:street":"Calle De Corredera",
    "iso:country":"ES",
    "sg:address":"Calle de Corredera, 4",
    "sg:city":"Ponferrada",
    "sg:orig_category":"Carnicer\u00cdas, Carnicer\u00cdas",
    "sg:phone":"+34 987 41 18 07",
    "sg:postcode":"24400",
    "sg:province":"Le\u00f3n",
    "wof:name":"Rodriguez Vidal Luis",
    "wof:placetype":"venue"
},
  "geometry": {"coordinates":[-6.4994387627,42.5581703186],"type":"Point"}
}