{
  "type": "Feature",
  "properties": {
    "addr:full":"Carr Oliva, 95 Figueres Girona 17600",
    "addr:housenumber":"95",
    "addr:postcode":"17600",
    "addr:street":"Carr Oliva",
    "iso:country":"ES",
    "sg:address":"Carr Oliva, 95",
    "sg:city":"Figueres",
    "sg:orig_category":"Asesor\u00cda Sobre Comunicaci\u00d3n De Empresas",
    "sg:phone":"+34 972 67 27 46",
    "sg:postcode":"17600",
    "sg:province":"Girona",
    "wof:name":"Orri Assessors Assessoria D'empreses S.l",
    "wof:placetype":"venue"
},
  "geometry": {"coordinates":[2.9654290676,42.258102417],"type":"Point"}
}