{
  "type": "Feature",
  "properties": {
    "iso:country":"ES",
    "sg:address":"Calle de La Florida, 50",
    "sg:city":"Vitoria-gasteiz",
    "sg:orig_category":"Art\u00cdculos De Decoraci\u00d3n",
    "sg:phone":"+34 945 25 76 33",
    "sg:postcode":"01005",
    "sg:province":"\u00c1lava",
    "wof:name":"El Baul Decoracion S.c",
    "wof:placetype":"venue"
},
  "geometry": {"coordinates":[-2.6701390743,42.8428001404],"type":"Point"}
}