{
  "type": "Feature",
  "properties": {
    "iso:country":"ES",
    "sg:address":"Rua Progreso (do), 32",
    "sg:city":"Lugo",
    "sg:orig_category":"Ropa Para Se\u00d1oras Y Caballeros (al Por Menor)",
    "sg:phone":"+34 982 22 65 96",
    "sg:postcode":"27001",
    "sg:province":"Lugo",
    "wof:name":"Ramil Rivera Amadeo",
    "wof:placetype":"venue"
},
  "geometry": {"coordinates":[-7.5550780296,43.0116882324],"type":"Point"}
}