{
  "type": "Feature",
  "properties": {
    "iso:country":"ES",
    "sg:address":"Cno. Emborras, S/n",
    "sg:city":"Vinaros",
    "sg:orig_category":"Empresas De Carpinter\u00cda De Madera",
    "sg:phone":"+34 964 40 00 94",
    "sg:postcode":"12500",
    "sg:province":"Castell\u00f3n",
    "wof:name":"Carpinteria Miranda S.l.",
    "wof:placetype":"venue"
},
  "geometry": {"coordinates":[0.4749450088,40.4711990356],"type":"Point"}
}