{
  "type": "Feature",
  "properties": {
    "addr:full":"Calle de Palomares (de Los), 21 Algete Madrid 28110",
    "addr:postcode":"28110",
    "addr:street":"Calle De Palomares De",
    "iso:country":"ES",
    "sg:address":"Calle de Palomares (de Los), 21",
    "sg:city":"Algete",
    "sg:orig_category":"Cl\u00cdnicas Dentales",
    "sg:phone":"+34 916 28 20 75",
    "sg:postcode":"28110",
    "sg:province":"Madrid",
    "wof:name":"Clinica Hernadent S.l.",
    "wof:placetype":"venue"
},
  "geometry": {"coordinates":[-3.5024130344,40.5968475342],"type":"Point"}
}