{
  "type": "Feature",
  "properties": {
    "addr:full":"Carrer de Matilde Diez, 9 Barcelona Barcelona 08006",
    "addr:housenumber":"9",
    "addr:postcode":"08006",
    "addr:street":"Carrer De Matilde Diez",
    "iso:country":"ES",
    "sg:address":"Carrer de Matilde Diez, 9",
    "sg:city":"Barcelona",
    "sg:orig_category":"Arquitectos",
    "sg:phone":"+34 932 17 47 23",
    "sg:postcode":"08006",
    "sg:province":"Barcelona",
    "wof:name":"Vidal Rebull German",
    "wof:placetype":"venue"
},
  "geometry": {"coordinates":[2.1487100124,41.4018287659],"type":"Point"}
}