{
  "type": "Feature",
  "properties": {
    "addr:full":"Afores, S/n Salou Tarragona 43840",
    "addr:housenumber":"s / n",
    "addr:postcode":"43840",
    "addr:street":"Afores",
    "iso:country":"ES",
    "sg:address":"Afores, S/n",
    "sg:city":"Salou",
    "sg:orig_category":"Pompas F\u00danebres, Inhumaciones Y Cremaciones",
    "sg:phone":"+34 977 38 82 02",
    "sg:postcode":"43840",
    "sg:province":"Tarragona",
    "wof:name":"Funeraria De La Torre-giralto S.l.",
    "wof:placetype":"venue"
},
  "geometry": {"coordinates":[1.136950016,41.0749702454],"type":"Point"}
}