{
  "type": "Feature",
  "properties": {
    "addr:full":"Poli Ciudad Del Transporte, 5 San Juan De Mozarrifar Zaragoza 50820",
    "addr:housenumber":"5",
    "addr:postcode":"50820",
    "addr:street":"Transporte;Juan De Mozarrifar",
    "iso:country":"ES",
    "sg:address":"Poli Ciudad Del Transporte, 5",
    "sg:city":"San Juan De Mozarrifar",
    "sg:orig_category":"Transporte En General",
    "sg:phone":"+34 976 58 74 26",
    "sg:postcode":"50820",
    "sg:province":"Zaragoza",
    "wof:name":"Exel Iberia Grupo S.l.spain S.l.u.",
    "wof:placetype":"venue"
},
  "geometry": {"coordinates":[-0.8416489959,41.7171096802],"type":"Point"}
}