{
  "type": "Feature",
  "properties": {
    "addr:full":"Pase San Gregorio, 65 Puertollano Ciudad Real 13500",
    "addr:housenumber":"65",
    "addr:postcode":"13500",
    "addr:street":"San Gregorio",
    "iso:country":"ES",
    "sg:address":"Pase San Gregorio, 65",
    "sg:city":"Puertollano",
    "sg:orig_category":"Doctores En Medicina",
    "sg:phone":"+34 926 42 58 71",
    "sg:postcode":"13500",
    "sg:province":"Ciudad Real",
    "wof:name":"Moro Avila Jose Antonio",
    "wof:placetype":"venue"
},
  "geometry": {"coordinates":[-4.1029372215,38.6894989014],"type":"Point"}
}