{
  "type": "Feature",
  "properties": {
    "iso:country":"ES",
    "sg:address":"Calle de Jose Macias, 13",
    "sg:city":"Madrid",
    "sg:orig_category":"Elementos Para Suelos Prefabricados",
    "sg:phone":"+34 914 65 28 49",
    "sg:postcode":"28047",
    "sg:province":"Madrid",
    "wof:name":"Acoparq Sociedad Cooperativa Limitada",
    "wof:placetype":"venue"
},
  "geometry": {"coordinates":[-3.746358633,40.3871154785],"type":"Point"}
}