{
  "type": "Feature",
  "properties": {
    "iso:country":"ES",
    "sg:address":"Avda San Telmo, 29",
    "sg:city":"Palencia",
    "sg:orig_category":"Carnicer\u00cdas, Carnicer\u00cdas",
    "sg:phone":"+34 979 16 01 08",
    "sg:postcode":"34004",
    "sg:province":"Palencia",
    "wof:name":"Sanmartin Rebollar David",
    "wof:placetype":"venue"
},
  "geometry": {"coordinates":[-4.5114197731,41.9916267395],"type":"Point"}
}