{
  "type": "Feature",
  "properties": {
    "iso:country":"ES",
    "sg:address":"Calle de Pastor Poeta, 10",
    "sg:city":"Oca\u00f1a",
    "sg:orig_category":"Promotores Constructores",
    "sg:phone":"+34 925 12 12 35",
    "sg:postcode":"45300",
    "sg:province":"Toledo",
    "wof:name":"Construcciones Arquero Poeta S.l",
    "wof:placetype":"venue"
},
  "geometry": {"coordinates":[-3.501240015,39.9608001709],"type":"Point"}
}