{
  "type": "Feature",
  "properties": {
    "iso:country":"ES",
    "sg:address":"Avda Generalisimo, 25",
    "sg:city":"Feira Do Monte",
    "sg:orig_category":"Caf\u00c9s, Bares, Cervecer\u00cdas",
    "sg:phone":"+34 982 50 30 98",
    "sg:postcode":"27377",
    "sg:province":"Lugo",
    "wof:name":"Vazquez Val Josefa Jovita",
    "wof:placetype":"venue"
},
  "geometry": {"coordinates":[-7.553896904,43.2366027832],"type":"Point"}
}