{
  "type": "Feature",
  "properties": {
    "iso:country":"ES",
    "sg:address":"Carrer de Rec Del Moli, 36",
    "sg:city":"S. Fost Campsentelles",
    "sg:orig_category":"Confecci\u00d3n, Alquiler Y Venta De Maniqu\u00cdes De Escaparate",
    "sg:phone":"+34 935 93 68 03",
    "sg:postcode":"08105",
    "sg:province":"Barcelona",
    "wof:name":"Duran Y Miguel S.l.",
    "wof:placetype":"venue"
},
  "geometry": {"coordinates":[2.2225570679,41.5284767151],"type":"Point"}
}