{
  "type": "Feature",
  "properties": {
    "addr:full":"Rua Joaquin Loriga, 10 Lalin Pontevedra 36500",
    "addr:housenumber":"10",
    "addr:postcode":"36500",
    "addr:street":"Rua Joaquin Loriga",
    "iso:country":"ES",
    "sg:address":"Rua Joaquin Loriga, 10",
    "sg:city":"Lalin",
    "sg:orig_category":"Marroquiner\u00cda (confecci\u00d3n)",
    "sg:phone":"+34 986 78 00 13",
    "sg:postcode":"36500",
    "sg:province":"Pontevedra",
    "wof:name":"Balado Rozas Manuel",
    "wof:placetype":"venue"
},
  "geometry": {"coordinates":[-8.112370491,42.6609992981],"type":"Point"}
}