{
  "type": "Feature",
  "properties": {
    "addr:full":"Ctra Ermitas (de Las), Km. 0000,1 Cordoba C\u00f3rdoba 14012",
    "addr:postcode":"14012",
    "addr:street":"Ctra Ermitas De Las Km. 0000,1;Co\u0301Rdoba",
    "iso:country":"ES",
    "sg:address":"Ctra Ermitas (de Las), Km. 0000,1",
    "sg:city":"Cordoba",
    "sg:orig_category":"Tratamientos De Conversi\u00d3n Qu\u00cdmica O Electrol\u00cdtica De Metales",
    "sg:phone":"+34 957 27 12 51",
    "sg:postcode":"14012",
    "sg:province":"C\u00f3rdoba",
    "wof:name":"Montajes Electricos Hermanos Castro S.l.",
    "wof:placetype":"venue"
},
  "geometry": {"coordinates":[-4.7997469902,37.9072036743],"type":"Point"}
}