{
  "type": "Feature",
  "properties": {
    "iso:country":"ES",
    "sg:address":"Calle de Martires De Paracuellos, 9",
    "sg:city":"Madrid",
    "sg:orig_category":"Inversiones",
    "sg:phone":"+34 915 71 07 72",
    "sg:postcode":"28020",
    "sg:province":"Madrid",
    "wof:name":"Partbrook Inversiones S. L.",
    "wof:placetype":"venue"
},
  "geometry": {"coordinates":[-3.6966609955,40.4534988403],"type":"Point"}
}