{
  "type": "Feature",
  "properties": {
    "iso:country":"ES",
    "sg:address":"Carrer de Sindicat, 16",
    "sg:city":"Palma",
    "sg:orig_category":"Zapatos (al Por Menor)",
    "sg:phone":"+34 971 72 12 80",
    "sg:postcode":"07002",
    "sg:province":"Islas Baleares",
    "wof:name":"Orangelia S.l.",
    "wof:placetype":"venue"
},
  "geometry": {"coordinates":[2.6524839401,39.570930481],"type":"Point"}
}