{
  "type": "Feature",
  "properties": {
    "iso:country":"ES",
    "sg:address":"Calle de Casasimarro, 22",
    "sg:city":"Quintanar Rey",
    "sg:orig_category":"Bares, Piano",
    "sg:phone":"+34 967 49 68 80",
    "sg:postcode":"16220",
    "sg:province":"Cuenca",
    "wof:name":"Mu\u00f1oz Marcilla Arcadio",
    "wof:placetype":"venue"
},
  "geometry": {"coordinates":[-1.9334042072,39.3451004028],"type":"Point"}
}