{
  "type": "Feature",
  "properties": {
    "iso:country":"ES",
    "sg:address":"Avda Sotolargo, 124",
    "sg:city":"Sotolargo",
    "sg:orig_category":"Edici\u00d3n De Diarios, Revistas, Boletines",
    "sg:phone":"+34 949 33 93 01",
    "sg:postcode":"19176",
    "sg:province":"Guadalajara",
    "wof:name":"Ediciones Facsimiles S.l.",
    "wof:placetype":"venue"
},
  "geometry": {"coordinates":[-3.304500103,40.6413993835],"type":"Point"}
}