{
  "type": "Feature",
  "properties": {
    "addr:full":"Calle de Antonio Ayala Garre, 7 Torre-pacheco Murcia 30700",
    "addr:housenumber":"7",
    "addr:postcode":"30700",
    "addr:street":"Calle De Antonio Ayala Garre",
    "iso:country":"ES",
    "sg:address":"Calle de Antonio Ayala Garre, 7",
    "sg:city":"Torre-pacheco",
    "sg:orig_category":"Peluquer\u00cdas, Peluquer\u00cda Mixta",
    "sg:phone":"+34 968 33 63 17",
    "sg:postcode":"30700",
    "sg:province":"Murcia",
    "wof:name":"Hernandez Pedre\u00f1o Ana Maria",
    "wof:placetype":"venue"
},
  "geometry": {"coordinates":[-0.9569218755,37.7464408875],"type":"Point"}
}