{
  "type": "Feature",
  "properties": {
    "addr:full":"Calle de Kaleberri, 7 Berriozar Navarra 31013",
    "addr:housenumber":"7",
    "addr:postcode":"31013",
    "addr:street":"Calle De Kaleberri",
    "iso:country":"ES",
    "sg:address":"Calle de Kaleberri, 7",
    "sg:city":"Berriozar",
    "sg:orig_category":"Sanatorios M\u00c9dico",
    "sg:phone":"+34 948 30 94 04",
    "sg:postcode":"31013",
    "sg:province":"Navarra",
    "wof:name":"Opnatel",
    "wof:placetype":"venue"
},
  "geometry": {"coordinates":[-1.6739710569,42.8363189697],"type":"Point"}
}