{
  "type": "Feature",
  "properties": {
    "addr:full":"Avda Isaac Peral, 3 Malaga M\u00e1laga 29004",
    "addr:housenumber":"3",
    "addr:postcode":"29004",
    "addr:street":"Avda Isaac Peral;Ma\u0301Laga",
    "iso:country":"ES",
    "sg:address":"Avda Isaac Peral, 3",
    "sg:city":"Malaga",
    "sg:orig_category":"Inmobiliaria (agencias)",
    "sg:phone":"+34 952 23 55 65",
    "sg:postcode":"29004",
    "sg:province":"M\u00e1laga",
    "wof:name":"Inmobiliaria Romero La Luz S.l.",
    "wof:placetype":"venue"
},
  "geometry": {"coordinates":[-4.4556097984,36.6977043152],"type":"Point"}
}