{
  "type": "Feature",
  "properties": {
    "addr:full":"Calle de San Modesto, 34 Madrid Madrid 28034",
    "addr:housenumber":"34",
    "addr:postcode":"madrid;28034",
    "addr:street":"Calle De San Modesto",
    "iso:country":"ES",
    "sg:address":"Calle de San Modesto, 34",
    "sg:city":"Madrid",
    "sg:orig_category":"Arquitectos",
    "sg:phone":"+34 913 58 53 78",
    "sg:postcode":"28034",
    "sg:province":"Madrid",
    "wof:name":"Olivares Alcala Jose",
    "wof:placetype":"venue"
},
  "geometry": {"coordinates":[-3.6962099075,40.4877700806],"type":"Point"}
}