{
  "type": "Feature",
  "properties": {
    "addr:full":"Cami Can Valls, S/n Gelida Barcelona 08790",
    "addr:housenumber":"s / n",
    "addr:postcode":"08790",
    "iso:country":"ES",
    "sg:address":"Cami Can Valls, S/n",
    "sg:city":"Gelida",
    "sg:orig_category":"Fabricaci\u00d3n De Tapices Y Moquetas Para Suelos Y Paredes",
    "sg:phone":"+34 937 79 20 71",
    "sg:postcode":"08790",
    "sg:province":"Barcelona",
    "wof:name":"Valero Ruf Francisco Jose",
    "wof:placetype":"venue"
},
  "geometry": {"coordinates":[1.8676400185,41.4464111328],"type":"Point"}
}