{
  "type": "Feature",
  "properties": {
    "addr:full":"Bolivia, 1 Huetor-tajar Granada 18360",
    "addr:housenumber":"1",
    "addr:postcode":"18360",
    "addr:street":"Bolivia",
    "iso:country":"ES",
    "sg:address":"Bolivia, 1",
    "sg:city":"Huetor-tajar",
    "sg:orig_category":"Ropa Y Accesorios",
    "sg:phone":"+34 958 33 21 60",
    "sg:postcode":"18360",
    "sg:province":"Granada",
    "sg:website":"www.cardenas-jeans@wanadoo.es",
    "wof:name":"Confecciones Cardenas E Hijas S.l.",
    "wof:placetype":"venue"
},
  "geometry": {"coordinates":[-4.0706038475,37.2185134888],"type":"Point"}
}