{
  "type": "Feature",
  "properties": {
    "iso:country":"ES",
    "sg:address":"Ctra Collblanc, 11",
    "sg:city":"Hospitalet Llobregat",
    "sg:orig_category":"Cester\u00cda (fabricaci\u00d3n)",
    "sg:phone":"+34 934 40 67 32",
    "sg:postcode":"08903",
    "sg:province":"Barcelona",
    "wof:name":"Salom Olle Jose",
    "wof:placetype":"venue"
},
  "geometry": {"coordinates":[2.121062994,41.3755760193],"type":"Point"}
}