{
  "type": "Feature",
  "properties": {
    "iso:country":"ES",
    "sg:address":"Rua Galiano, 22",
    "sg:city":"Ferrol",
    "sg:orig_category":"Loter\u00cda Y T\u00d3mbola",
    "sg:phone":"+34 981 32 16 26",
    "sg:postcode":"15402",
    "sg:province":"La Coru\u00f1a",
    "wof:name":"Garaboa Eiris Javier",
    "wof:placetype":"venue"
},
  "geometry": {"coordinates":[-8.2301483154,43.4857406616],"type":"Point"}
}