{
  "type": "Feature",
  "properties": {
    "iso:country":"ES",
    "sg:address":"Hondo, S/n",
    "sg:city":"Barinas",
    "sg:orig_category":"Discotecas Y Salas De Baile",
    "sg:phone":"+34 968 68 91 12",
    "sg:postcode":"30648",
    "sg:province":"Murcia",
    "wof:name":"Murcia Diversion S.l.",
    "wof:placetype":"venue"
},
  "geometry": {"coordinates":[-1.058109045,38.2696266174],"type":"Point"}
}