{
  "type": "Feature",
  "properties": {
    "iso:country":"ES",
    "sg:address":"Avda Giorgeta, 12",
    "sg:city":"Valencia",
    "sg:orig_category":"Agencias Y Agentes Comerciales, Representantes",
    "sg:phone":"+34 963 42 03 33",
    "sg:postcode":"46007",
    "sg:province":"Valencia",
    "wof:name":"Sulumber S.l.",
    "wof:placetype":"venue"
},
  "geometry": {"coordinates":[-0.3862510026,39.4613800049],"type":"Point"}
}