{
  "type": "Feature",
  "properties": {
    "iso:country":"ES",
    "sg:address":"Avda Langraiz, 36",
    "sg:city":"Nanclares De La Oca",
    "sg:orig_category":"Molduras, Junquillos, Listones Y Molduras Perforadas",
    "sg:phone":"+34 945 36 17 01",
    "sg:postcode":"01230",
    "sg:province":"\u00c1lava",
    "wof:name":"Salgado Aguayo Asier",
    "wof:placetype":"venue"
},
  "geometry": {"coordinates":[-2.8150889874,42.8163604736],"type":"Point"}
}