{
  "type": "Feature",
  "properties": {
    "iso:country":"ES",
    "sg:address":"Calle de Monta\u00d1a Clara, S/n",
    "sg:city":"Fa\u00d1abe",
    "sg:orig_category":"Cl\u00cdnicas Dentales",
    "sg:phone":"+34 922 72 44 70",
    "sg:postcode":"38670",
    "sg:province":"Santa Cruz De Tenerife",
    "wof:name":"Luzcarlos E Hijos S.l.",
    "wof:placetype":"venue"
},
  "geometry": {"coordinates":[-16.724899292,28.1215400696],"type":"Point"}
}