{
  "type": "Feature",
  "properties": {
    "addr:full":"Calle de Cerrolaza, 9 Pozuelo De Alarcon Madrid 28224",
    "addr:housenumber":"9",
    "addr:postcode":"28224",
    "addr:street":"Calle De Cerrolaza",
    "iso:country":"ES",
    "sg:address":"Calle de Cerrolaza, 9",
    "sg:city":"Pozuelo De Alarcon",
    "sg:orig_category":"Expertos Contables, Revisores De Cuentas",
    "sg:phone":"+34 913 52 25 32",
    "sg:postcode":"28224",
    "sg:province":"Madrid",
    "wof:name":"Reguera Bueno Jose Luis Alfredo",
    "wof:placetype":"venue"
},
  "geometry": {"coordinates":[-3.8042285442,40.4469413757],"type":"Point"}
}