{
  "type": "Feature",
  "properties": {
    "addr:full":"Avda Primero De Mayo, 23 Palmas De Gran Canaria Las Palmas 35002",
    "addr:postcode":"35002",
    "addr:street":"Avda Primero De Mayo 23",
    "iso:country":"ES",
    "sg:address":"Avda Primero De Mayo, 23",
    "sg:city":"Palmas De Gran Canaria",
    "sg:orig_category":"Inmobiliaria (agencias)",
    "sg:phone":"+34 928 36 29 98",
    "sg:postcode":"35002",
    "sg:province":"Las Palmas",
    "wof:name":"Masufe S.l.",
    "wof:placetype":"venue"
},
  "geometry": {"coordinates":[-15.4194087982,28.1047992706],"type":"Point"}
}