{
  "type": "Feature",
  "properties": {
    "iso:country":"ES",
    "sg:address":"Trav. Madres, 12",
    "sg:city":"Avila",
    "sg:orig_category":"Fotocopias, Reprograf\u00cda",
    "sg:phone":"+34 920 25 44 76",
    "sg:postcode":"05001",
    "sg:province":"\u00c1vila",
    "wof:name":"Copias Paris S.l.",
    "wof:placetype":"venue"
},
  "geometry": {"coordinates":[-4.692317009,40.6547241211],"type":"Point"}
}