{
  "type": "Feature",
  "properties": {
    "iso:country":"ES",
    "sg:address":"Calle de Pozo, S/n",
    "sg:city":"Friera Valverde",
    "sg:orig_category":"Molduras, Junquillos, Listones Y Molduras Perforadas",
    "sg:phone":"+34 980 65 45 19",
    "sg:postcode":"49698",
    "sg:province":"Zamora",
    "wof:name":"Fidalgo Gutierrez Oliva",
    "wof:placetype":"venue"
},
  "geometry": {"coordinates":[-5.841878891,41.9124908447],"type":"Point"}
}