{
  "type": "Feature",
  "properties": {
    "iso:country":"ES",
    "sg:address":"Calle de Parroco Penzol, S/n",
    "sg:city":"Puerto De Vega",
    "sg:orig_category":"Imprenta",
    "sg:phone":"+34 985 64 84 41",
    "sg:postcode":"33790",
    "sg:province":"Asturias",
    "wof:name":"Diaz Mendez Luis",
    "wof:placetype":"venue"
},
  "geometry": {"coordinates":[-6.649066925,43.5639877319],"type":"Point"}
}