{
  "type": "Feature",
  "properties": {
    "addr:full":"Barr Larzabal, 5 Errenteria Guip\u00f9zcoa 20100",
    "addr:housenumber":"5",
    "addr:postcode":"20100",
    "addr:street":"Barr Larzabal;Guipu\u0300Zcoa",
    "iso:country":"ES",
    "sg:address":"Barr Larzabal, 5",
    "sg:city":"Errenteria",
    "sg:orig_category":"Promotores Constructores",
    "sg:phone":"+34 943 34 10 90",
    "sg:postcode":"20100",
    "sg:province":"Guip\u00f9zcoa",
    "wof:name":"Barbazan Obras S.l.",
    "wof:placetype":"venue"
},
  "geometry": {"coordinates":[-1.8838490248,43.3099708557],"type":"Point"}
}