{
  "type": "Feature",
  "properties": {
    "iso:country":"ES",
    "sg:address":"Calle de Libertad, S/n",
    "sg:city":"Carrizosa",
    "sg:orig_category":"Empresas De Carpinter\u00cda De Madera",
    "sg:phone":"+34 926 36 92 07",
    "sg:postcode":"13329",
    "sg:province":"Ciudad Real",
    "wof:name":"Dominguez Monje Antonio",
    "wof:placetype":"venue"
},
  "geometry": {"coordinates":[-2.9935441017,38.8394889832],"type":"Point"}
}