{
  "type": "Feature",
  "properties": {
    "addr:full":"Rond Constitucio, 24 Monovar Alicante 03640",
    "addr:housenumber":"24",
    "addr:postcode":"03640",
    "addr:street":"Rond Constitucio;Alicante",
    "iso:country":"ES",
    "sg:address":"Rond Constitucio, 24",
    "sg:city":"Monovar",
    "sg:orig_category":"Peleter\u00cdas",
    "sg:phone":"+34 965 47 24 46",
    "sg:postcode":"03640",
    "sg:province":"Alicante",
    "wof:name":"Hidalgo Do\u00f1ate Francisco",
    "wof:placetype":"venue"
},
  "geometry": {"coordinates":[-0.8425480127,38.4362030029],"type":"Point"}
}