{
  "type": "Feature",
  "properties": {
    "addr:full":"Calle de Olaguibel, 46 Vitoria-gasteiz \u00c1lava 01003",
    "addr:housenumber":"46",
    "addr:postcode":"01003",
    "addr:street":"Calle De Olaguibel",
    "iso:country":"ES",
    "sg:address":"Calle de Olaguibel, 46",
    "sg:city":"Vitoria-gasteiz",
    "sg:orig_category":"Torrefactado De Caf\u00c9",
    "sg:phone":"+34 945 26 79 95",
    "sg:postcode":"01003",
    "sg:province":"\u00c1lava",
    "wof:name":"Cafes La Brasile\u00f1a S.a.",
    "wof:placetype":"venue"
},
  "geometry": {"coordinates":[-2.6650900841,42.8456382751],"type":"Point"}
}