{
  "type": "Feature",
  "properties": {
    "addr:full":"Pase Constitucion (la), 19 Zaragoza Zaragoza 50001",
    "addr:housenumber":"19",
    "addr:postcode":"50001",
    "addr:street":"Constitucion La",
    "iso:country":"ES",
    "sg:address":"Pase Constitucion (la), 19",
    "sg:city":"Zaragoza",
    "sg:orig_category":"Peluquer\u00cdas, Peluquer\u00cda Mixta",
    "sg:phone":"+34 976 21 31 71",
    "sg:postcode":"50001",
    "sg:province":"Zaragoza",
    "wof:name":"Cimatulay S.l.",
    "wof:placetype":"venue"
},
  "geometry": {"coordinates":[-0.8829860091,41.6483917236],"type":"Point"}
}