{
  "type": "Feature",
  "properties": {
    "addr:full":"Pg Valldaura, 195 Barcelona Barcelona 08016",
    "addr:housenumber":"195",
    "addr:postcode":"08016",
    "addr:street":"Pg Valldaura",
    "iso:country":"ES",
    "sg:address":"Pg Valldaura, 195",
    "sg:city":"Barcelona",
    "sg:orig_category":"Dorados, Plater\u00cda (orfebrer\u00cda)",
    "sg:phone":"+34 932 76 42 02",
    "sg:postcode":"08016",
    "sg:province":"Barcelona",
    "wof:name":"Martinez Martinez Asuncion",
    "wof:placetype":"venue"
},
  "geometry": {"coordinates":[2.1762690544,41.4386634827],"type":"Point"}
}