{
  "type": "Feature",
  "properties": {
    "addr:full":"Av Bendinat, 19 Portals Nous Islas Baleares 07181",
    "addr:housenumber":"19",
    "addr:postcode":"07181",
    "addr:street":"Av Bendinat",
    "iso:country":"ES",
    "sg:address":"Av Bendinat, 19",
    "sg:city":"Portals Nous",
    "sg:orig_category":"Inmobiliaria (agencias)",
    "sg:phone":"+34 971 67 57 29",
    "sg:postcode":"07181",
    "sg:province":"Islas Baleares",
    "wof:name":"Inversiones Grudisan S.l.",
    "wof:placetype":"venue"
},
  "geometry": {"coordinates":[2.5791079998,39.5340652466],"type":"Point"}
}