{
  "type": "Feature",
  "properties": {
    "iso:country":"ES",
    "sg:address":"Calle de Cueva De Menga, 3",
    "sg:city":"Sevilla",
    "sg:orig_category":"\u00d3ptica: Instrumentos (fabricaci\u00d3n)",
    "sg:phone":"+34 954 25 95 04",
    "sg:postcode":"41020",
    "sg:province":"Sevilla",
    "wof:name":"Reales Arroyo Maria Isabel",
    "wof:placetype":"venue"
},
  "geometry": {"coordinates":[-5.9422106743,37.3986053467],"type":"Point"}
}