{
  "type": "Feature",
  "properties": {
    "addr:full":"Calle de Zamora, 30 Salamanca Salamanca 37002",
    "addr:housenumber":"30",
    "addr:postcode":"37002",
    "addr:street":"Calle De Zamora",
    "iso:country":"ES",
    "sg:address":"Calle de Zamora, 30",
    "sg:city":"Salamanca",
    "sg:orig_category":"Zapater\u00cdas",
    "sg:phone":"+34 923 21 65 17",
    "sg:postcode":"37002",
    "sg:province":"Salamanca",
    "wof:name":"Sanchez Frontela Jose Antonio",
    "wof:placetype":"venue"
},
  "geometry": {"coordinates":[-5.6640048027,40.9667434692],"type":"Point"}
}