{
  "type": "Feature",
  "properties": {
    "addr:full":"Avda Portugal, 52 Chantada Lugo 27500",
    "addr:housenumber":"52",
    "addr:postcode":"27500",
    "addr:street":"Avda Portugal",
    "iso:country":"ES",
    "sg:address":"Avda Portugal, 52",
    "sg:city":"Chantada",
    "sg:orig_category":"Venta, Montaje De Neum\u00c1ticos",
    "sg:phone":"+34 982 46 20 03",
    "sg:postcode":"27500",
    "sg:province":"Lugo",
    "wof:name":"Mazaira Iriarte Olga Teresa",
    "wof:placetype":"venue"
},
  "geometry": {"coordinates":[-7.7762641907,42.6085166931],"type":"Point"}
}