{
  "type": "Feature",
  "properties": {
    "iso:country":"ES",
    "sg:address":"Calle de Virgen Del Val, 24",
    "sg:city":"Madrid",
    "sg:orig_category":"Molduras, Junquillos, Listones Y Molduras Perforadas",
    "sg:phone":"+34 914 04 90 09",
    "sg:postcode":"28027",
    "sg:province":"Madrid",
    "wof:name":"Soldental 2000 S.l.",
    "wof:placetype":"venue"
},
  "geometry": {"coordinates":[-3.653449297,40.4382362366],"type":"Point"}
}