{
  "type": "Feature",
  "properties": {
    "iso:country":"ES",
    "sg:address":"Ctra Villacastin, S/n",
    "sg:city":"Tabara",
    "sg:orig_category":"Talleres El\u00c9ctricos Para Veh\u00cdculos",
    "sg:phone":"+34 980 59 01 26",
    "sg:postcode":"49140",
    "sg:province":"Zamora",
    "wof:name":"Talleres Lozano Y Beato S.l.",
    "wof:placetype":"venue"
},
  "geometry": {"coordinates":[-5.9588150978,41.8262939453],"type":"Point"}
}