{
  "type": "Feature",
  "properties": {
    "addr:full":"Ctra Barrio Peral, 42 Barrio De Peral Murcia 30300",
    "addr:housenumber":"42",
    "addr:postcode":"30300",
    "addr:street":"Ctra Barrio Peral",
    "iso:country":"ES",
    "sg:address":"Ctra Barrio Peral, 42",
    "sg:city":"Barrio De Peral",
    "sg:orig_category":"Caf\u00c9s, Bares, Cervecer\u00cdas",
    "sg:phone":"+34 968 31 30 70",
    "sg:postcode":"30300",
    "sg:province":"Murcia",
    "wof:name":"Eurotel Sur S.l.",
    "wof:placetype":"venue"
},
  "geometry": {"coordinates":[-1.1302499771,37.9829597473],"type":"Point"}
}