{
  "type": "Feature",
  "properties": {
    "addr:full":"Calle de Pintor Juan Guillermo, 5 Palmas De Gran Canaria Las Palmas 35011",
    "addr:housenumber":"5",
    "addr:postcode":"35011",
    "addr:street":"Calle De Pintor Juan Guillermo",
    "iso:country":"ES",
    "sg:address":"Calle de Pintor Juan Guillermo, 5",
    "sg:city":"Palmas De Gran Canaria",
    "sg:orig_category":"Fabricaci\u00d3n, Reparaci\u00d3n Y Mantenimiento De Construcciones Navales Y Fluviales",
    "sg:phone":"+34 928 29 92 94",
    "sg:postcode":"35011",
    "sg:province":"Las Palmas",
    "sg:website":"www.pressto.com",
    "wof:name":"Pazo Ben Carlos Del",
    "wof:placetype":"venue"
},
  "geometry": {"coordinates":[-15.437582016,28.1280097961],"type":"Point"}
}