{
  "type": "Feature",
  "properties": {
    "addr:full":"Carrer de Canvis Vells, 13 Barcelona Barcelona 08003",
    "addr:housenumber":"13",
    "addr:postcode":"08003",
    "addr:street":"Carrer De Canvis Vells",
    "iso:country":"ES",
    "sg:address":"Carrer de Canvis Vells, 13",
    "sg:city":"Barcelona",
    "sg:orig_category":"Sociedades, Compa\u00d1\u00cdas Aseguradoras",
    "sg:phone":"+34 933 10 69 22",
    "sg:postcode":"08003",
    "sg:province":"Barcelona",
    "wof:name":"Carde\u00f1es Roger Juan",
    "wof:placetype":"venue"
},
  "geometry": {"coordinates":[2.1823060513,41.3829116821],"type":"Point"}
}