{
  "type": "Feature",
  "properties": {
    "addr:full":"Ctra. Navahermosa, 4 Menasalbas Toledo 45128",
    "addr:housenumber":"4",
    "addr:postcode":"45128",
    "addr:street":"Ctra. Navahermosa",
    "iso:country":"ES",
    "sg:address":"Ctra. Navahermosa, 4",
    "sg:city":"Menasalbas",
    "sg:orig_category":"Cr\u00cda De Animales",
    "sg:phone":"+34 925 40 70 58",
    "sg:postcode":"45128",
    "sg:province":"Toledo",
    "wof:name":"Vaquero Garcia Juan",
    "wof:placetype":"venue"
},
  "geometry": {"coordinates":[-4.2943539619,39.6386604309],"type":"Point"}
}