{
  "type": "Feature",
  "properties": {
    "addr:full":"Carrer de Pi I Margall, 12 Molins Rei Barcelona 08750",
    "addr:housenumber":"12",
    "addr:postcode":"08750",
    "addr:street":"Carrer De Pi I Margall;Barcelona",
    "iso:country":"ES",
    "sg:address":"Carrer de Pi I Margall, 12",
    "sg:city":"Molins Rei",
    "sg:orig_category":"Frutas, Legumbres Frescas Y Tempranas (al Por Menor)",
    "sg:phone":"+34 936 68 17 68",
    "sg:postcode":"08750",
    "sg:province":"Barcelona",
    "wof:name":"Caliz Ayora Jesus",
    "wof:placetype":"venue"
},
  "geometry": {"coordinates":[2.0191791058,41.4104003906],"type":"Point"}
}