{
  "type": "Feature",
  "properties": {
    "iso:country":"ES",
    "sg:address":"Calle de Marti, 14",
    "sg:city":"Valencia",
    "sg:orig_category":"Aguas (distribuci\u00d3n, Servicios)",
    "sg:phone":"+34 963 95 81 40",
    "sg:postcode":"46005",
    "sg:province":"Valencia",
    "wof:name":"Empresa Mixta Valenciana De Aguas S.a.",
    "wof:placetype":"venue"
},
  "geometry": {"coordinates":[-0.3704900146,39.4648208618],"type":"Point"}
}