{
  "type": "Feature",
  "properties": {
    "addr:full":"Calle de Alfonso Xii, 13 Santa Pola Alicante 03130",
    "addr:housenumber":"13",
    "addr:postcode":"03130",
    "addr:street":"Calle De Alfonso Xii",
    "iso:country":"ES",
    "sg:address":"Calle de Alfonso Xii, 13",
    "sg:city":"Santa Pola",
    "sg:orig_category":"Agencias Y Agentes Comerciales, Representantes",
    "sg:phone":"+34 966 69 20 43",
    "sg:postcode":"03130",
    "sg:province":"Alicante",
    "wof:name":"Promociones Las Gaviotas S. A.",
    "wof:placetype":"venue"
},
  "geometry": {"coordinates":[-0.554148972,38.2203483582],"type":"Point"}
}