{
  "type": "Feature",
  "properties": {
    "addr:full":"Calle de Federico Garcia Lorca, 15 Burgos Burgos 09007",
    "addr:housenumber":"15",
    "addr:postcode":"09007",
    "addr:street":"Calle De Federico Garcia Lorca",
    "iso:country":"ES",
    "sg:address":"Calle de Federico Garcia Lorca, 15",
    "sg:city":"Burgos",
    "sg:orig_category":"Molduras, Junquillos, Listones Y Molduras Perforadas",
    "sg:phone":"+34 947 48 96 75",
    "sg:postcode":"09007",
    "sg:province":"Burgos",
    "wof:name":"Bueno Diez Soluciones S. L.",
    "wof:placetype":"venue"
},
  "geometry": {"coordinates":[-3.6643071175,42.3502922058],"type":"Point"}
}