{
  "type": "Feature",
  "properties": {
    "iso:country":"ES",
    "sg:address":"Rua Santiago Apostol, 1",
    "sg:city":"Verin",
    "sg:orig_category":"Plomeros",
    "sg:phone":"+34 988 41 08 80",
    "sg:postcode":"32600",
    "sg:province":"Ourense",
    "wof:name":"Soto Cid Ricardo",
    "wof:placetype":"venue"
},
  "geometry": {"coordinates":[-7.4278731346,41.9424629211],"type":"Point"}
}