{
  "type": "Feature",
  "properties": {
    "iso:country":"ES",
    "sg:address":"Calle de Perez Dolz, 11",
    "sg:city":"Castellon",
    "sg:orig_category":"Mec\u00c1nico Del Autom\u00d3vil",
    "sg:phone":"+34 964 22 09 71",
    "sg:postcode":"12003",
    "sg:province":"Castell\u00f3n",
    "wof:name":"Abril Botia Cristobal",
    "wof:placetype":"venue"
},
  "geometry": {"coordinates":[-0.030947,39.981575],"type":"Point"}
}