{
  "type": "Feature",
  "properties": {
    "addr:full":"Plgn Ind Sepes, S/n Puertollano Ciudad Real 13500",
    "addr:housenumber":"/ n",
    "addr:postcode":"13500",
    "addr:street":"Sepes S",
    "iso:country":"ES",
    "sg:address":"Plgn Ind Sepes, S/n",
    "sg:city":"Puertollano",
    "sg:orig_category":"Tubos Met\u00c1licos",
    "sg:phone":"+34 926 41 29 42",
    "sg:postcode":"13500",
    "sg:province":"Ciudad Real",
    "wof:name":"Tubacero S.a.",
    "wof:placetype":"venue"
},
  "geometry": {"coordinates":[-4.1123538017,38.6858253479],"type":"Point"}
}