{
  "type": "Feature",
  "properties": {
    "addr:full":"Carrer de Goya, 50 S. Vicen\u00e7 Castellet Barcelona 08295",
    "addr:housenumber":"50",
    "addr:postcode":"08295",
    "addr:street":"Carrer De Goya;S. Vicenc\u0327;Barcelona",
    "iso:country":"ES",
    "sg:address":"Carrer de Goya, 50",
    "sg:city":"S. Vicen\u00e7 Castellet",
    "sg:orig_category":"Ense\u00d1anza Secundaria: Colegios Y Escuelas Privadas",
    "sg:phone":"+34 938 33 07 51",
    "sg:postcode":"08295",
    "sg:province":"Barcelona",
    "wof:name":"Centre De Telecomunicaciones De Catalunya",
    "wof:placetype":"venue"
},
  "geometry": {"coordinates":[1.8631449938,41.6706848145],"type":"Point"}
}