{
  "type": "Feature",
  "properties": {
    "iso:country":"ES",
    "sg:address":"Carrer de Candela, 19",
    "sg:city":"Valls",
    "sg:orig_category":"Cajas Y Embalajes De Cart\u00d3n Y Papel",
    "sg:phone":"+34 977 60 80 29",
    "sg:postcode":"43800",
    "sg:province":"Tarragona",
    "wof:name":"Melero Arroyo Manuel",
    "wof:placetype":"venue"
},
  "geometry": {"coordinates":[1.246006012,41.283416748],"type":"Point"}
}