{
  "type": "Feature",
  "properties": {
    "iso:country":"ES",
    "sg:address":"Carrer de Llanera, 51",
    "sg:city":"Sabadell",
    "sg:orig_category":"Obras Y Organismos Sociales",
    "sg:phone":"+34 937 23 45 64",
    "sg:postcode":"08207",
    "sg:province":"Barcelona",
    "wof:name":"Bracos Obert D'assistencia Social",
    "wof:placetype":"venue"
},
  "geometry": {"coordinates":[2.0903151035,41.5686187744],"type":"Point"}
}