{
  "type": "Feature",
  "properties": {
    "addr:full":"Carrer de Alcalde Rafael Carreras, 43 Mataro Barcelona 08304",
    "addr:housenumber":"43",
    "addr:postcode":"08304",
    "addr:street":"Carrer De Alcalde Rafael Carreras",
    "iso:country":"ES",
    "sg:address":"Carrer de Alcalde Rafael Carreras, 43",
    "sg:city":"Mataro",
    "sg:orig_category":"Mec\u00c1nico Del Autom\u00d3vil",
    "sg:phone":"+34 937 96 40 07",
    "sg:postcode":"08304",
    "sg:province":"Barcelona",
    "wof:name":"Gonzalez Gonzalez Gines",
    "wof:placetype":"venue"
},
  "geometry": {"coordinates":[2.4535000324,41.5474090576],"type":"Point"}
}