{
  "type": "Feature",
  "properties": {
    "addr:full":"Avda Blasco Iba\u00d1ez, 71 Valencia Valencia 46021",
    "addr:housenumber":"71",
    "addr:postcode":"46021",
    "addr:street":"Avda Blasco Iban\u0303Ez",
    "iso:country":"ES",
    "sg:address":"Avda Blasco Iba\u00d1ez, 71",
    "sg:city":"Valencia",
    "sg:orig_category":"Inmobiliaria (agencias)",
    "sg:phone":"+34 963 62 11 00",
    "sg:postcode":"46021",
    "sg:province":"Valencia",
    "wof:name":"Lagos S. L.",
    "wof:placetype":"venue"
},
  "geometry": {"coordinates":[-0.3489859998,39.4748573303],"type":"Point"}
}