{
  "type": "Feature",
  "properties": {
    "addr:full":"Cra Rio, 311 Pinedo Valencia 46012",
    "addr:housenumber":"311",
    "addr:postcode":"46012",
    "addr:street":"Pinedo",
    "iso:country":"ES",
    "sg:address":"Cra Rio, 311",
    "sg:city":"Pinedo",
    "sg:orig_category":"Cajas De Ahorro",
    "sg:phone":"+34 963 24 82 55",
    "sg:postcode":"46012",
    "sg:province":"Valencia",
    "sg:website":"www.bancaja.es",
    "wof:name":"Caja De Ahorros De Valencia Castellon Y Alicante",
    "wof:placetype":"venue"
},
  "geometry": {"coordinates":[-0.3400790095,39.4209518433],"type":"Point"}
}