{
  "type": "Feature",
  "properties": {
    "iso:country":"ES",
    "sg:address":"Carrer de Sant Joan, 1",
    "sg:city":"Rodonya",
    "sg:orig_category":"Farmacias",
    "sg:phone":"+34 977 62 83 85",
    "sg:postcode":"43812",
    "sg:province":"Tarragona",
    "wof:name":"Folch Gil Vicenta",
    "wof:placetype":"venue"
},
  "geometry": {"coordinates":[1.3987540007,41.2800750732],"type":"Point"}
}