{
  "type": "Feature",
  "properties": {
    "addr:full":"Calle de Fernandez Vallin, 5 Gijon Asturias 33205",
    "addr:housenumber":"5",
    "addr:postcode":"33205",
    "addr:street":"Calle De Fernandez Vallin",
    "iso:country":"ES",
    "sg:address":"Calle de Fernandez Vallin, 5",
    "sg:city":"Gijon",
    "sg:orig_category":"Hoteles",
    "sg:phone":"+34 985 34 60 00",
    "sg:postcode":"33205",
    "sg:province":"Asturias",
    "wof:name":"Hotel Hernan Cortes S. A.",
    "wof:placetype":"venue"
},
  "geometry": {"coordinates":[-5.6621508598,43.5395851135],"type":"Point"}
}