{
  "type": "Feature",
  "properties": {
    "iso:country":"ES",
    "sg:address":"Calle de Hermanos Ortiz Echague, 5",
    "sg:city":"Cadiz",
    "sg:orig_category":"M\u00c9dicos: Estomatolog\u00cda",
    "sg:phone":"+34 956 20 00 38",
    "sg:postcode":"11011",
    "sg:province":"C\u00e1diz",
    "wof:name":"Guerrero Gavira Maria Teresa",
    "wof:placetype":"venue"
},
  "geometry": {"coordinates":[-6.2711567879,36.5046043396],"type":"Point"}
}