{
  "type": "Feature",
  "properties": {
    "addr:full":"Av Roma (de), 20 Tarragona Tarragona 43005",
    "addr:housenumber":"20",
    "addr:postcode":"43005",
    "addr:street":"Av Roma De",
    "iso:country":"ES",
    "sg:address":"Av Roma (de), 20",
    "sg:city":"Tarragona",
    "sg:orig_category":"Promotores Constructores",
    "sg:phone":"+34 977 24 07 96",
    "sg:postcode":"43005",
    "sg:province":"Tarragona",
    "wof:name":"Promociones Inmobiliarias Clegui S.l",
    "wof:placetype":"venue"
},
  "geometry": {"coordinates":[1.2409009933,41.1180534363],"type":"Point"}
}