{
  "type": "Feature",
  "properties": {
    "iso:country":"ES",
    "sg:address":"Carrer de Miguel De Cervantes (de), 2",
    "sg:city":"Tortosa",
    "sg:orig_category":"Confiter\u00cdas, Chocolater\u00cdas (al Por Menor)",
    "sg:phone":"+34 977 51 04 62",
    "sg:postcode":"43500",
    "sg:province":"Tarragona",
    "wof:name":"Morant Ramos Jose Luis",
    "wof:placetype":"venue"
},
  "geometry": {"coordinates":[0.5219249725,40.810333252],"type":"Point"}
}