{
  "type": "Feature",
  "properties": {
    "iso:country":"ES",
    "sg:address":"Av Mediterrani, 5",
    "sg:city":"Reus",
    "sg:orig_category":"Reposter\u00cdas",
    "sg:phone":"+34 977 77 47 13",
    "sg:postcode":"43205",
    "sg:province":"Tarragona",
    "wof:name":"Forn De Pa Monica S.l.",
    "wof:placetype":"venue"
},
  "geometry": {"coordinates":[1.1155689955,41.1406669617],"type":"Point"}
}