{
  "type": "Feature",
  "properties": {
    "iso:country":"ES",
    "sg:address":"Avda Lugo, 16",
    "sg:city":"Pontevedra",
    "sg:orig_category":"Agentes, Concesionarios Y Sucursales De Camiones Y Veh\u00cdculos Industriales",
    "sg:phone":"+34 986 86 25 46",
    "sg:postcode":"36004",
    "sg:province":"Pontevedra",
    "wof:name":"Ramos Morell Francisco Javier",
    "wof:placetype":"venue"
},
  "geometry": {"coordinates":[-8.6214952469,42.4359664917],"type":"Point"}
}