{
  "type": "Feature",
  "properties": {
    "addr:full":"Las Huertas, 2 Quintanadue\u00f1as Burgos 09197",
    "addr:housenumber":"2",
    "addr:postcode":"09197",
    "addr:street":"Las Huertas",
    "iso:country":"ES",
    "sg:address":"Las Huertas, 2",
    "sg:city":"Quintanadue\u00f1as",
    "sg:orig_category":"Ingeniero",
    "sg:phone":"+34 947 29 25 85",
    "sg:postcode":"09197",
    "sg:province":"Burgos",
    "wof:name":"Rodriguez Agreda Jose Luis",
    "wof:placetype":"venue"
},
  "geometry": {"coordinates":[-3.7351219654,42.3831176758],"type":"Point"}
}