{
  "type": "Feature",
  "properties": {
    "iso:country":"ES",
    "sg:address":"Cami Ral, 385",
    "sg:city":"Mataro",
    "sg:orig_category":"Cajas De Ahorro",
    "sg:phone":"+34 937 55 50 67",
    "sg:postcode":"08301",
    "sg:province":"Barcelona",
    "wof:name":"Caja De Ahorros Del Mediterraneo",
    "wof:placetype":"venue"
},
  "geometry": {"coordinates":[2.444382906,41.5370025635],"type":"Point"}
}