{
  "type": "Feature",
  "properties": {
    "iso:country":"ES",
    "sg:address":"Carrer de Sant Ramon, 16",
    "sg:city":"Santa Coloma De Gramenet",
    "sg:orig_category":"Restaurantes",
    "sg:phone":"+34 933 86 30 81",
    "sg:postcode":"08922",
    "sg:province":"Barcelona",
    "wof:name":"Xurreria Granja Victoria S.l.",
    "wof:placetype":"venue"
},
  "geometry": {"coordinates":[2.2117686272,41.4499015808],"type":"Point"}
}