{
  "type": "Feature",
  "properties": {
    "addr:full":"Calle de Ayala, 27 Madrid Madrid 28001",
    "addr:housenumber":"27",
    "addr:postcode":"madrid;28001",
    "addr:street":"Calle De Ayala",
    "iso:country":"ES",
    "sg:address":"Calle de Ayala, 27",
    "sg:city":"Madrid",
    "sg:orig_category":"Inmobiliaria (agencias)",
    "sg:phone":"+34 915 75 05 54",
    "sg:postcode":"28001",
    "sg:province":"Madrid",
    "wof:name":"Compa\u00f1ia De Transportes E Inversiones S.a.",
    "wof:placetype":"venue"
},
  "geometry": {"coordinates":[-3.6845047474,40.4277496338],"type":"Point"}
}