{
  "type": "Feature",
  "properties": {
    "addr:full":"C/ Cala Romaguera, S/n Cales Mallorca Islas Baleares 07689",
    "addr:housenumber":"s",
    "addr:postcode":"07689",
    "addr:street":"C / Cala Romaguera;/ N Cales",
    "iso:country":"ES",
    "sg:address":"C/ Cala Romaguera, S/n",
    "sg:city":"Cales Mallorca",
    "sg:orig_category":"Alquiler De Veh\u00cdculos: Turismos Y Utilitarios",
    "sg:phone":"+34 971 82 80 18",
    "sg:postcode":"07689",
    "sg:province":"Islas Baleares",
    "wof:name":"Autos Ve\u00f1y S.a.",
    "wof:placetype":"venue"
},
  "geometry": {"coordinates":[3.2794799805,39.4620285034],"type":"Point"}
}