{
  "type": "Feature",
  "properties": {
    "addr:full":"Avda Sinforiano Madro\u00d1ero, 33 Badajoz Badajoz 06011",
    "addr:housenumber":"33",
    "addr:postcode":"06011",
    "addr:street":"Avda Sinforiano Madron\u0303Ero",
    "iso:country":"ES",
    "sg:address":"Avda Sinforiano Madro\u00d1ero, 33",
    "sg:city":"Badajoz",
    "sg:orig_category":"Fabricaci\u00d3n De Distribuidores Autom\u00c1ticos",
    "sg:phone":"+34 924 24 32 02",
    "sg:postcode":"06011",
    "sg:province":"Badajoz",
    "sg:website":"www.cavareal.com",
    "wof:name":"Conejo Blazquez Jeronimo",
    "wof:placetype":"venue"
},
  "geometry": {"coordinates":[-6.9871587753,38.8681488037],"type":"Point"}
}