{
  "type": "Feature",
  "properties": {
    "addr:full":"Calle de Ardigales, 15 Castro Urdiales Cantabria 39700",
    "addr:housenumber":"15",
    "addr:postcode":"39700",
    "addr:street":"Calle De Ardigales",
    "iso:country":"ES",
    "sg:address":"Calle de Ardigales, 15",
    "sg:city":"Castro Urdiales",
    "sg:orig_category":"Perfumer\u00cda (al Por Menor)",
    "sg:phone":"+34 942 86 90 42",
    "sg:postcode":"39700",
    "sg:province":"Cantabria",
    "wof:name":"Espliego Color S. L.",
    "wof:placetype":"venue"
},
  "geometry": {"coordinates":[-3.218862772,43.3821220398],"type":"Point"}
}