{
  "type": "Feature",
  "properties": {
    "iso:country":"ES",
    "sg:address":"Carrer de Victor Balaguer, 26",
    "sg:city":"S. Boi Llobregat",
    "sg:orig_category":"Librer\u00cdas",
    "sg:phone":"+34 936 30 91 77",
    "sg:postcode":"08830",
    "sg:province":"Barcelona",
    "wof:name":"Gonzalez Martinez Florentina",
    "wof:placetype":"venue"
},
  "geometry": {"coordinates":[2.0370540619,41.3458099365],"type":"Point"}
}