{
  "type": "Feature",
  "properties": {
    "iso:country":"ES",
    "sg:address":"Calle de Maestro Calles, 4",
    "sg:city":"Santurtzi",
    "sg:orig_category":"Comercio De Piezas De Recambio Y De Accesorios De Veh\u00cdculos, Veh\u00cdculos Industriales",
    "sg:phone":"+34 944 62 06 54",
    "sg:postcode":"48980",
    "sg:province":"Vizcaya",
    "wof:name":"Ayuela Merino Valentin",
    "wof:placetype":"venue"
},
  "geometry": {"coordinates":[-3.0333390236,43.3302230835],"type":"Point"}
}