{
  "type": "Feature",
  "properties": {
    "iso:country":"ES",
    "sg:address":"Carrer de Carme, 4",
    "sg:city":"Palma",
    "sg:orig_category":"Deportes Y Programas De Aventura",
    "sg:phone":"+34 971 22 78 88",
    "sg:postcode":"07003",
    "sg:province":"Islas Baleares",
    "wof:name":"Massanella Activitates S.l.",
    "wof:placetype":"venue"
},
  "geometry": {"coordinates":[2.6508080959,39.5744743347],"type":"Point"}
}