{
  "type": "Feature",
  "properties": {
    "addr:full":"Calle de Miro, 14 Adra Almer\u00eda 04770",
    "addr:housenumber":"14",
    "addr:postcode":"04770",
    "addr:street":"Calle De Miro;Almeri\u0301A",
    "iso:country":"ES",
    "sg:address":"Calle de Miro, 14",
    "sg:city":"Adra",
    "sg:orig_category":"Servicios Diversos",
    "sg:phone":"+34 950 40 33 86",
    "sg:postcode":"04770",
    "sg:province":"Almer\u00eda",
    "wof:name":"Ecologistas En Accion-almeria",
    "wof:placetype":"venue"
},
  "geometry": {"coordinates":[-3.0143539906,36.7469711304],"type":"Point"}
}