{
  "type": "Feature",
  "properties": {
    "iso:country":"ES",
    "sg:address":"Avda Pablo Vi, 9",
    "sg:city":"Pozuelo De Alarcon",
    "sg:orig_category":"Administradores De Bienes Y Delegados De Comunidades De Propietarios",
    "sg:phone":"+34 913 51 44 80",
    "sg:postcode":"28224",
    "sg:province":"Madrid",
    "sg:website":"www.kirsa.es",
    "wof:name":"Kirsa S.l.",
    "wof:placetype":"venue"
},
  "geometry": {"coordinates":[-3.8108370304,40.4301948547],"type":"Point"}
}