{
  "type": "Feature",
  "properties": {
    "iso:country":"ES",
    "sg:address":"Calle de Mesones, 3",
    "sg:city":"Ubeda",
    "sg:orig_category":"Mercer\u00cda, Lencer\u00cda (al Por Menor)",
    "sg:phone":"+34 953 75 45 77",
    "sg:postcode":"23400",
    "sg:province":"Ja\u00e9n",
    "wof:name":"Due\u00f1as Jimenez Juan Eduardo",
    "wof:placetype":"venue"
},
  "geometry": {"coordinates":[-3.373488903,38.011264801],"type":"Point"}
}