{
  "type": "Feature",
  "properties": {
    "iso:country":"ES",
    "sg:address":"Calle de Garcilaso De La Vega, 2",
    "sg:city":"Gijon",
    "sg:orig_category":"Cl\u00cdnicas M\u00c9dicas",
    "sg:phone":"+34 985 33 15 53",
    "sg:postcode":"33202",
    "sg:province":"Asturias",
    "sg:website":"www.institutoiris.com",
    "wof:name":"Pantiga Menendez Maria De Los Angeles",
    "wof:placetype":"venue"
},
  "geometry": {"coordinates":[-5.6552882195,43.5387039185],"type":"Point"}
}