{
  "type": "Feature",
  "properties": {
    "iso:country":"ES",
    "sg:address":"Avda Ordo\u00d1o Ii, 33",
    "sg:city":"Le\u00f3n",
    "sg:orig_category":"Asesor\u00cda Fiscal Y Jur\u00cddica",
    "sg:phone":"+34 987 21 51 50",
    "sg:postcode":"24001",
    "sg:province":"Le\u00f3n",
    "sg:website":"www.consultiber.com",
    "wof:name":"Ccv Zona 5 Consultores S.l.",
    "wof:placetype":"venue"
},
  "geometry": {"coordinates":[-5.5763092041,42.5966377258],"type":"Point"}
}