{
  "type": "Feature",
  "properties": {
    "iso:country":"ES",
    "sg:address":"C/ Doctor Ferran, 10",
    "sg:city":"Salt",
    "sg:classifiers":[
        {
            "category":"Autos & Motor Vehicles",
            "subcategory":"Automobile Sales",
            "type":"Retail Goods"
        }
    ],
    "sg:phone":"+34 972 23 84 03",
    "sg:postcode":"17190",
    "sg:province":"Girona",
    "wof:name":"Guevara Martin Antonio",
    "wof:placetype":"venue"
},
  "geometry": {"coordinates":[2.7885038853,41.9740257263],"type":"Point"}
}