{
  "type": "Feature",
  "properties": {
    "addr:full":"Ctra. Malaga-almeria, S/n Torrox-costa M\u00e1laga 29793",
    "addr:housenumber":"s",
    "addr:postcode":"29793",
    "addr:street":"Ctra. Malaga-Almeria;/ N Torrox-Costa Ma\u0301Laga",
    "iso:country":"ES",
    "sg:address":"Ctra. Malaga-almeria, S/n",
    "sg:city":"Torrox-costa",
    "sg:orig_category":"Tubos Y Tuber\u00cdas De Goma Y Pl\u00c1stico (fabricaci\u00d3n, Al Por Mayor)",
    "sg:phone":"+34 952 53 02 27",
    "sg:postcode":"29793",
    "sg:province":"M\u00e1laga",
    "wof:name":"Pastor Gonzalez Sebastian",
    "wof:placetype":"venue"
},
  "geometry": {"coordinates":[-3.9598391056,36.7302436829],"type":"Point"}
}