{
  "type": "Feature",
  "properties": {
    "iso:country":"ES",
    "sg:address":"Calle de Antonio Machin, 2",
    "sg:city":"Sevilla",
    "sg:orig_category":"Artesan\u00cda",
    "sg:phone":"+34 954 35 05 61",
    "sg:postcode":"41009",
    "sg:province":"Sevilla",
    "wof:name":"Artesania Carvajal S.c.",
    "wof:placetype":"venue"
},
  "geometry": {"coordinates":[-5.9811849594,37.4031677246],"type":"Point"}
}