{
  "type": "Feature",
  "properties": {
    "iso:country":"ES",
    "sg:address":"Calle de Fuencarral, 48",
    "sg:city":"Madrid",
    "sg:orig_category":"Ropa Para Se\u00d1oras Y Caballeros (al Por Menor)",
    "sg:phone":"+34 915 32 73 00",
    "sg:postcode":"28004",
    "sg:province":"Madrid",
    "wof:name":"Orellana-1 S.l.",
    "wof:placetype":"venue"
},
  "geometry": {"coordinates":[-3.7004868984,40.4233398438],"type":"Point"}
}