{
  "type": "Feature",
  "properties": {
    "iso:country":"ES",
    "sg:address":"Calle de Braulio Foz, 5",
    "sg:city":"Borja",
    "sg:orig_category":"Telas Y Sedas (al Por Menor)",
    "sg:phone":"+34 976 85 27 32",
    "sg:postcode":"50540",
    "sg:province":"Zaragoza",
    "wof:name":"Aznar Zueco Pascual",
    "wof:placetype":"venue"
},
  "geometry": {"coordinates":[-1.5325059891,41.832447052],"type":"Point"}
}