{
  "type": "Feature",
  "properties": {
    "addr:full":"Carrer de Reding (de), 46 Tarragona Tarragona 43001",
    "addr:housenumber":"46",
    "addr:postcode":"43001",
    "addr:street":"Carrer De Reding De",
    "iso:country":"ES",
    "sg:address":"Carrer de Reding (de), 46",
    "sg:city":"Tarragona",
    "sg:orig_category":"Cl\u00cdnicas Dentales",
    "sg:phone":"+34 977 23 56 55",
    "sg:postcode":"43001",
    "sg:province":"Tarragona",
    "wof:name":"Martinez Fargas Victor",
    "wof:placetype":"venue"
},
  "geometry": {"coordinates":[1.2477589846,41.1163406372],"type":"Point"}
}