{
  "type": "Feature",
  "properties": {
    "addr:full":"Rua Azalea, 2 Lugo Lugo 27004",
    "addr:housenumber":"2",
    "addr:postcode":"27004",
    "addr:street":"Rua Azalea",
    "iso:country":"ES",
    "sg:address":"Rua Azalea, 2",
    "sg:city":"Lugo",
    "sg:orig_category":"Asociaciones Y Clubs Deportivos",
    "sg:phone":"+34 982 20 01 21",
    "sg:postcode":"27004",
    "sg:province":"Lugo",
    "wof:name":"Alonso Castro Maria Jose",
    "wof:placetype":"venue"
},
  "geometry": {"coordinates":[-7.5671281815,43.0127067566],"type":"Point"}
}