{
  "type": "Feature",
  "properties": {
    "iso:country":"ES",
    "sg:address":"Calle de Jerico, 8",
    "sg:city":"Sevilla",
    "sg:orig_category":"Peluquer\u00cdas, Peluquer\u00cda Mixta",
    "sg:phone":"+34 954 51 26 70",
    "sg:postcode":"41007",
    "sg:province":"Sevilla",
    "wof:name":"Pablo Velazque Peluquero S.l.",
    "wof:placetype":"venue"
},
  "geometry": {"coordinates":[-5.9591870308,37.3935279846],"type":"Point"}
}