{
  "type": "Feature",
  "properties": {
    "iso:country":"ES",
    "sg:address":"Calle de Valladolid, 22",
    "sg:city":"Parla",
    "sg:orig_category":"Inmobiliaria (agencias)",
    "sg:phone":"+34 916 99 61 91",
    "sg:postcode":"28980",
    "sg:province":"Madrid",
    "wof:name":"Coinsur, S.l.",
    "wof:placetype":"venue"
},
  "geometry": {"coordinates":[-3.7631189823,40.2418403625],"type":"Point"}
}