{
  "type": "Feature",
  "properties": {
    "iso:country":"ES",
    "sg:address":"Calle de Santiago De Compostela, S/n",
    "sg:city":"Madrid",
    "sg:classifiers":[
        {
            "category":"Cinema",
            "subcategory":"Movie Theater",
            "type":"Entertainment"
        }
    ],
    "sg:phone":"+34 917 30 06 22",
    "sg:postcode":"28029",
    "sg:province":"Madrid",
    "sg:tags":[
        "salas",
        "de",
        "cine"
    ],
    "sg:website":"www.guiadelocio.com",
    "wof:name":"Sociedad Cinematografica De Centros Comerciales S. A.",
    "wof:placetype":"venue"
},
  "geometry": {"coordinates":[-3.7070300579,40.4818534851],"type":"Point"}
}