{
  "type": "Feature",
  "properties": {
    "addr:full":"Plaz Polka (la), 1 Gracia Santa Cruz De Tenerife 38295",
    "addr:housenumber":"1",
    "addr:postcode":"38295",
    "addr:street":"Gracia",
    "iso:country":"ES",
    "sg:address":"Plaz Polka (la), 1",
    "sg:city":"Gracia",
    "sg:orig_category":"Traductores",
    "sg:phone":"+34 922 31 55 93",
    "sg:postcode":"38295",
    "sg:province":"Santa Cruz De Tenerife",
    "wof:name":"Hernandez Lima Valentin",
    "wof:placetype":"venue"
},
  "geometry": {"coordinates":[-16.3025226593,28.4732723236],"type":"Point"}
}