{
  "type": "Feature",
  "properties": {
    "addr:full":"Calle de Pino (del), 17 Yuncos Toledo 45210",
    "addr:housenumber":"17",
    "addr:postcode":"45210",
    "addr:street":"Calle De Pino Del",
    "iso:country":"ES",
    "sg:address":"Calle de Pino (del), 17",
    "sg:city":"Yuncos",
    "sg:orig_category":"Lacadores",
    "sg:phone":"+34 925 53 60 92",
    "sg:postcode":"45210",
    "sg:province":"Toledo",
    "sg:website":"www.lacadosmg.com",
    "wof:name":"Lacados M.g.s.l",
    "wof:placetype":"venue"
},
  "geometry": {"coordinates":[-3.8866889477,40.0756912231],"type":"Point"}
}