{
  "type": "Feature",
  "properties": {
    "addr:full":"Trva Ciudad Jardin, 3 Bilbao Vizcaya 48007",
    "addr:housenumber":"3",
    "addr:postcode":"48007",
    "addr:street":"Trva Ciudad Jardin",
    "iso:country":"ES",
    "sg:address":"Trva Ciudad Jardin, 3",
    "sg:city":"Bilbao",
    "sg:orig_category":"Asesor\u00cda Fiscal Y Jur\u00cddica",
    "sg:phone":"+34 944 45 42 11",
    "sg:postcode":"48007",
    "sg:province":"Vizcaya",
    "wof:name":"Seoane Varela Pilar",
    "wof:placetype":"venue"
},
  "geometry": {"coordinates":[-2.9222590923,43.268699646],"type":"Point"}
}