{
  "type": "Feature",
  "properties": {
    "addr:full":"Barcelones (pol Ind La Borda), 14 Caldes Montbui Barcelona 08140",
    "addr:housenumber":"14",
    "addr:postcode":"08140",
    "addr:street":"Borda;Montbui Barcelona",
    "iso:country":"ES",
    "sg:address":"Barcelones (pol Ind La Borda), 14",
    "sg:city":"Caldes Montbui",
    "sg:orig_category":"Electricidad: Equipos Industriales, Componentes (fabricaci\u00d3n)",
    "sg:phone":"+34 938 62 68 36",
    "sg:postcode":"08140",
    "sg:province":"Barcelona",
    "wof:name":"Sanper Caldes S.l.",
    "wof:placetype":"venue"
},
  "geometry": {"coordinates":[2.1618270874,41.6338577271],"type":"Point"}
}