{
  "type": "Feature",
  "properties": {
    "addr:full":"Baserritar Etorbidea, 11 Akartegi Guip\u00f9zcoa 20280",
    "addr:housenumber":"11",
    "addr:postcode":"20280",
    "addr:street":"Baserritar Etorbidea;Guipu\u0300Zcoa",
    "iso:country":"ES",
    "sg:address":"Baserritar Etorbidea, 11",
    "sg:city":"Akartegi",
    "sg:orig_category":"Transportes Por V\u00cdas Navegables",
    "sg:phone":"+34 943 64 39 18",
    "sg:postcode":"20280",
    "sg:province":"Guip\u00f9zcoa",
    "wof:name":"Zabalo Echegaray Martin",
    "wof:placetype":"venue"
},
  "geometry": {"coordinates":[-1.7963260412,43.3678588867],"type":"Point"}
}