{
  "type": "Feature",
  "properties": {
    "addr:full":"Avda Pinoso (de), 12 Torrevieja Alicante 03180",
    "addr:housenumber":"12",
    "addr:postcode":"03180",
    "addr:street":"Avda Pinoso De",
    "iso:country":"ES",
    "sg:address":"Avda Pinoso (de), 12",
    "sg:city":"Torrevieja",
    "sg:orig_category":"Administradores De Bienes Y Delegados De Comunidades De Propietarios",
    "sg:phone":"+34 965 71 42 21",
    "sg:postcode":"03180",
    "sg:province":"Alicante",
    "wof:name":"Fernandez Garcia Jose Angel",
    "wof:placetype":"venue"
},
  "geometry": {"coordinates":[-0.6536790133,38.0173606873],"type":"Point"}
}