{
  "type": "Feature",
  "properties": {
    "addr:full":"Carrer de Rosa Ribas I Parellada, 52 Prat Llobregat Barcelona 08820",
    "addr:housenumber":"52",
    "addr:postcode":"08820",
    "addr:street":"Carrer De Rosa Ribas;Parellada;Llobregat",
    "iso:country":"ES",
    "sg:address":"Carrer de Rosa Ribas I Parellada, 52",
    "sg:city":"Prat Llobregat",
    "sg:orig_category":"Ropa Para Se\u00d1oras (al Por Menor)",
    "sg:phone":"+34 933 79 44 03",
    "sg:postcode":"08820",
    "sg:province":"Barcelona",
    "wof:name":"Nieto Garcia Alejandro",
    "wof:placetype":"venue"
},
  "geometry": {"coordinates":[2.0896298885,41.3231506348],"type":"Point"}
}