{
  "type": "Feature",
  "properties": {
    "iso:country":"ES",
    "sg:address":"Avda Constitucion, 37",
    "sg:city":"Tauste",
    "sg:orig_category":"Molduras, Junquillos, Listones Y Molduras Perforadas",
    "sg:phone":"+34 976 85 94 99",
    "sg:postcode":"50660",
    "sg:province":"Zaragoza",
    "wof:name":"Arriazu Perez Blas",
    "wof:placetype":"venue"
},
  "geometry": {"coordinates":[-1.2580370903,41.9210853577],"type":"Point"}
}