{
  "type": "Feature",
  "properties": {
    "iso:country":"ES",
    "sg:address":"Polig Izarilla, 6",
    "sg:city":"Matamorosa",
    "sg:orig_category":"Empresas De Pintura Y Revestimientos",
    "sg:phone":"+34 942 75 42 82",
    "sg:postcode":"39200",
    "sg:province":"Cantabria",
    "wof:name":"Pinturas Campoo Sociedad Cooperativa",
    "wof:placetype":"venue"
},
  "geometry": {"coordinates":[-4.1391940117,43.0004043579],"type":"Point"}
}