{
  "type": "Feature",
  "properties": {
    "addr:full":"Ctra Villena, Km. 0025,5 Bocairent Valencia 46880",
    "addr:postcode":"46880",
    "addr:street":"Ctra Villena Km. 0025,5",
    "iso:country":"ES",
    "sg:address":"Ctra Villena, Km. 0025,5",
    "sg:city":"Bocairent",
    "sg:orig_category":"Cueros Y Pieles (al Por Mayor)",
    "sg:phone":"+34 962 35 05 16",
    "sg:postcode":"46880",
    "sg:province":"Valencia",
    "wof:name":"Euronapa S. A.",
    "wof:placetype":"venue"
},
  "geometry": {"coordinates":[-0.6109189987,38.7625846863],"type":"Point"}
}