{
  "type": "Feature",
  "properties": {
    "addr:full":"Ctra Madrid (p I Espartales), Km. 0531,0 Rinconada Sevilla 41309",
    "addr:postcode":"41309",
    "addr:street":"Ctra Madrid P;Espartales Km. 0531,0",
    "iso:country":"ES",
    "sg:address":"Ctra Madrid (p I Espartales), Km. 0531,0",
    "sg:city":"Rinconada",
    "sg:orig_category":"Construcciones Navales Y Fluviales",
    "sg:phone":"+34 954 99 91 05",
    "sg:postcode":"41309",
    "sg:province":"Sevilla",
    "wof:name":"Sociedad Andaluza De Componentes Especia",
    "wof:placetype":"venue"
},
  "geometry": {"coordinates":[-5.9782538414,37.492855072],"type":"Point"}
}