{
  "type": "Feature",
  "properties": {
    "addr:full":"Rua Jose Arcos Moldes, 4 Rianxo La Coru\u00f1a 15920",
    "addr:housenumber":"4",
    "addr:postcode":"15920",
    "addr:street":"Rua Jose Arcos Moldes;La Corun\u0303A",
    "iso:country":"ES",
    "sg:address":"Rua Jose Arcos Moldes, 4",
    "sg:city":"Rianxo",
    "sg:orig_category":"Urbanistas",
    "sg:phone":"+34 981 84 37 90",
    "sg:postcode":"15920",
    "sg:province":"La Coru\u00f1a",
    "wof:name":"Arqo Arquitectura E Urbanismo S.l.",
    "wof:placetype":"venue"
},
  "geometry": {"coordinates":[-8.8145370483,42.652557373],"type":"Point"}
}