{
  "type": "Feature",
  "properties": {
    "addr:full":"Carrer de Narcis Monturiol, 35 Sabadell Barcelona 08203",
    "addr:housenumber":"35",
    "addr:postcode":"08203",
    "addr:street":"Carrer De Narcis Monturiol",
    "iso:country":"ES",
    "sg:address":"Carrer de Narcis Monturiol, 35",
    "sg:city":"Sabadell",
    "sg:orig_category":"Fabricaci\u00d3n De Distribuidores Autom\u00c1ticos",
    "sg:phone":"+34 937 10 63 15",
    "sg:postcode":"08203",
    "sg:province":"Barcelona",
    "wof:name":"R.d.v. S.l.",
    "wof:placetype":"venue"
},
  "geometry": {"coordinates":[2.1085209846,41.5355796814],"type":"Point"}
}