{
  "type": "Feature",
  "properties": {
    "iso:country":"ES",
    "sg:address":"Carrer de Francesc Macia (de), 1",
    "sg:city":"Mora D'ebre",
    "sg:orig_category":"Centros Empresariales",
    "sg:phone":"+34 977 40 25 54",
    "sg:postcode":"43740",
    "sg:province":"Tarragona",
    "wof:name":"Giros Durich S.l.",
    "wof:placetype":"venue"
},
  "geometry": {"coordinates":[1.2427539825,41.1158790588],"type":"Point"}
}