{
  "type": "Feature",
  "properties": {
    "addr:full":"Calle de San Martin, 3 Haro La Rioja 26200",
    "addr:housenumber":"3",
    "addr:postcode":"26200",
    "addr:street":"Calle De San Martin",
    "iso:country":"ES",
    "sg:address":"Calle de San Martin, 3",
    "sg:city":"Haro",
    "sg:orig_category":"Ingeniero",
    "sg:phone":"+34 941 30 56 11",
    "sg:postcode":"26200",
    "sg:province":"La Rioja",
    "wof:name":"Fernandez De Las Heras Gomez Valvanera",
    "wof:placetype":"venue"
},
  "geometry": {"coordinates":[-2.8463580608,42.5777206421],"type":"Point"}
}