{
  "type": "Feature",
  "properties": {
    "addr:full":"Carr Academia, 46 Lleida Lleida 25002",
    "addr:housenumber":"46",
    "addr:postcode":"25002",
    "addr:street":"Carr Academia",
    "iso:country":"ES",
    "sg:address":"Carr Academia, 46",
    "sg:city":"Lleida",
    "sg:orig_category":"Universidades",
    "sg:phone":"+34 973 28 98 00",
    "sg:postcode":"25002",
    "sg:province":"Lleida",
    "wof:name":"V.blanch Gabinet D'assessors S.l.",
    "wof:placetype":"venue"
},
  "geometry": {"coordinates":[0.61699301,41.6095962524],"type":"Point"}
}