{
  "type": "Feature",
  "properties": {
    "addr:full":"Calle de Luna, 17 Santiago El Mayor Murcia 30012",
    "addr:housenumber":"17",
    "addr:postcode":"30012",
    "addr:street":"Calle De Luna",
    "iso:country":"ES",
    "sg:address":"Calle de Luna, 17",
    "sg:city":"Santiago El Mayor",
    "sg:orig_category":"Instalaci\u00d3n De Aspiraci\u00d3n De Gases Y Humos",
    "sg:phone":"+34 968 34 49 31",
    "sg:postcode":"30012",
    "sg:province":"Murcia",
    "wof:name":"Rodriguez Saura Francisco",
    "wof:placetype":"venue"
},
  "geometry": {"coordinates":[-1.1216490269,37.9715652466],"type":"Point"}
}