{
  "type": "Feature",
  "properties": {
    "iso:country":"ES",
    "sg:address":"Calle de Bellas Artes, 4",
    "sg:city":"Zaragoza",
    "sg:orig_category":"Ingeniero",
    "sg:phone":"+34 976 75 82 94",
    "sg:postcode":"50012",
    "sg:province":"Zaragoza",
    "wof:name":"Llosa Serna Francisco Leandro",
    "wof:placetype":"venue"
},
  "geometry": {"coordinates":[-0.9275354147,41.6302108765],"type":"Point"}
}