{
  "type": "Feature",
  "properties": {
    "addr:full":"Calle de Poeta Salvador Rueda, 38 Fuengirola M\u00e1laga 29640",
    "addr:housenumber":"38",
    "addr:postcode":"29640",
    "addr:street":"Calle De Poeta Salvador Rueda;Ma\u0301Laga",
    "iso:country":"ES",
    "sg:address":"Calle de Poeta Salvador Rueda, 38",
    "sg:city":"Fuengirola",
    "sg:orig_category":"Controles De Edificaci\u00d3n (construcci\u00d3n, Seguridad)",
    "sg:phone":"+34 952 66 72 96",
    "sg:postcode":"29640",
    "sg:province":"M\u00e1laga",
    "wof:name":"Septemba S.l.",
    "wof:placetype":"venue"
},
  "geometry": {"coordinates":[-4.6134710312,36.553188324],"type":"Point"}
}