{
  "type": "Feature",
  "properties": {
    "iso:country":"ES",
    "sg:address":"Barr Fuente (la), S/n",
    "sg:city":"Selores",
    "sg:orig_category":"Muebles, Minoristas",
    "sg:phone":"+34 942 70 63 08",
    "sg:postcode":"39511",
    "sg:province":"Cantabria",
    "wof:name":"Calderon Quintero Irma",
    "wof:placetype":"venue"
},
  "geometry": {"coordinates":[-4.259595871,43.1898956299],"type":"Point"}
}