{
  "type": "Feature",
  "properties": {
    "iso:country":"ES",
    "sg:address":"Ctra Massalfassar, S/n",
    "sg:city":"Museros",
    "sg:orig_category":"Supermercados Y Hipermercados",
    "sg:phone":"+34 961 45 24 20",
    "sg:postcode":"46136",
    "sg:province":"Valencia",
    "wof:name":"Supermercados Sabeco S.a.",
    "wof:placetype":"venue"
},
  "geometry": {"coordinates":[-0.3326840103,39.5605201721],"type":"Point"}
}