{
  "type": "Feature",
  "properties": {
    "addr:full":"Pg Sant Joan, 31 Barcelona Barcelona 08010",
    "addr:housenumber":"31",
    "addr:postcode":"08010",
    "addr:street":"Pg Sant Joan",
    "iso:country":"ES",
    "sg:address":"Pg Sant Joan, 31",
    "sg:city":"Barcelona",
    "sg:orig_category":"Molduras, Junquillos, Listones Y Molduras Perforadas",
    "sg:phone":"+34 932 31 59 28",
    "sg:postcode":"08010",
    "sg:province":"Barcelona",
    "wof:name":"Sol Codina Jordi",
    "wof:placetype":"venue"
},
  "geometry": {"coordinates":[2.1772389412,41.3934135437],"type":"Point"}
}