{
  "type": "Feature",
  "properties": {
    "addr:full":"Calle de Magisterio, 2 Logro\u00f1o La Rioja 26004",
    "addr:housenumber":"2",
    "addr:postcode":"26004",
    "addr:street":"Calle De Magisterio;Rioja",
    "iso:country":"ES",
    "sg:address":"Calle de Magisterio, 2",
    "sg:city":"Logro\u00f1o",
    "sg:orig_category":"Iglesia Cat\u00d3lica",
    "sg:phone":"+34 941 23 25 14",
    "sg:postcode":"26004",
    "sg:province":"La Rioja",
    "wof:name":"Parroquia De San Jose Obrero",
    "wof:placetype":"venue"
},
  "geometry": {"coordinates":[-2.4275660515,42.4656677246],"type":"Point"}
}