{
  "type": "Feature",
  "properties": {
    "addr:full":"Trva Circo (el), 5 Monteagudo De Las Vicarias Soria 42220",
    "addr:housenumber":"5",
    "addr:postcode":"42220",
    "addr:street":"Trva Circo El",
    "iso:country":"ES",
    "sg:address":"Trva Circo (el), 5",
    "sg:city":"Monteagudo De Las Vicarias",
    "sg:orig_category":"Iglesia Cat\u00d3lica",
    "sg:phone":"+34 975 32 50 51",
    "sg:postcode":"42220",
    "sg:province":"Soria",
    "wof:name":"Parroquia Nuestra Se\u00f1ora De La Muela",
    "wof:placetype":"venue"
},
  "geometry": {"coordinates":[-2.1628670692,41.4551353455],"type":"Point"}
}