{
  "type": "Feature",
  "properties": {
    "iso:country":"ES",
    "sg:address":"Avda Constitucion (la), S/n",
    "sg:city":"Olivos-la Postura",
    "sg:orig_category":"Sindicatos De Trabajadores",
    "sg:phone":"+34 922 77 52 00",
    "sg:postcode":"38670",
    "sg:province":"Santa Cruz De Tenerife",
    "wof:name":"Fundacion Formacion Y Empleo",
    "wof:placetype":"venue"
},
  "geometry": {"coordinates":[-16.2548561096,28.4698104858],"type":"Point"}
}