{
  "type": "Feature",
  "properties": {
    "iso:country":"ES",
    "sg:address":"Calle de Feria, 140",
    "sg:city":"Sevilla",
    "sg:orig_category":"Complementos De Vestir (al Por Menor)",
    "sg:phone":"+34 954 38 08 65",
    "sg:postcode":"41002",
    "sg:province":"Sevilla",
    "wof:name":"Reina Fernandez Maria Jesus",
    "wof:placetype":"venue"
},
  "geometry": {"coordinates":[-5.9916319847,37.4014625549],"type":"Point"}
}