{
  "type": "Feature",
  "properties": {
    "addr:full":"Calle de Maria Diaz De Haro, 18 Portugalete Vizcaya 48920",
    "addr:housenumber":"18",
    "addr:postcode":"48920",
    "addr:street":"Calle De Maria Diaz De Haro",
    "iso:country":"ES",
    "sg:address":"Calle de Maria Diaz De Haro, 18",
    "sg:city":"Portugalete",
    "sg:orig_category":"Agencias De Viajes",
    "sg:phone":"+34 944 72 20 56",
    "sg:postcode":"48920",
    "sg:province":"Vizcaya",
    "wof:name":"B. T. Bel Tour S. L.",
    "wof:placetype":"venue"
},
  "geometry": {"coordinates":[-3.0183160305,43.3228569031],"type":"Point"}
}