{
  "type": "Feature",
  "properties": {
    "iso:country":"ES",
    "sg:address":"Calle de Lanzarote, 12",
    "sg:city":"San Sebastian De Los Reyes",
    "sg:orig_category":"Laboratorios Farmac\u00c9uticos",
    "sg:phone":"+34 916 52 12 28",
    "sg:postcode":"28700",
    "sg:province":"Madrid",
    "wof:name":"B.braun Medical S A",
    "wof:placetype":"venue"
},
  "geometry": {"coordinates":[-3.6206109524,40.5577354431],"type":"Point"}
}