{
  "type": "Feature",
  "properties": {
    "addr:full":"Avda Vega Baja, 13 Rojales Alicante 03170",
    "addr:housenumber":"13",
    "addr:postcode":"03170",
    "addr:street":"Avda Vega Baja",
    "iso:country":"ES",
    "sg:address":"Avda Vega Baja, 13",
    "sg:city":"Rojales",
    "sg:orig_category":"Ropa Para Ni\u00d1os (al Por Menor)",
    "sg:phone":"+34 966 71 56 09",
    "sg:postcode":"03170",
    "sg:province":"Alicante",
    "wof:name":"Garcia Hernandez Maria Angeles",
    "wof:placetype":"venue"
},
  "geometry": {"coordinates":[-0.7247689962,38.0882415771],"type":"Point"}
}