{
  "type": "Feature",
  "properties": {
    "iso:country":"ES",
    "sg:address":"Carrer de Pont, 43",
    "sg:city":"Manlleu",
    "sg:orig_category":"Pod\u00d3logos: Pedicuros",
    "sg:phone":"+34 938 51 07 90",
    "sg:postcode":"08560",
    "sg:province":"Barcelona",
    "wof:name":"Rifa Crespi Josefa",
    "wof:placetype":"venue"
},
  "geometry": {"coordinates":[2.2852339745,41.9990081787],"type":"Point"}
}