{
  "type": "Feature",
  "properties": {
    "iso:country":"ES",
    "sg:address":"Avda Conde De Lumiares, 12",
    "sg:city":"Alacant",
    "sg:orig_category":"Agencias Y Agentes Comerciales, Representantes",
    "sg:phone":"+34 965 24 41 90",
    "sg:postcode":"03010",
    "sg:province":"Alicante",
    "wof:name":"Vaquero Quijada Maria Del Carmen",
    "wof:placetype":"venue"
},
  "geometry": {"coordinates":[-0.4899510145,38.3594665527],"type":"Point"}
}