{
  "type": "Feature",
  "properties": {
    "addr:full":"Carr Mossen Baldiri Reixac, 14 Girona Girona 17003",
    "addr:housenumber":"14",
    "addr:postcode":"17003",
    "addr:street":"Carr Mossen Baldiri Reixac",
    "iso:country":"ES",
    "sg:address":"Carr Mossen Baldiri Reixac, 14",
    "sg:city":"Girona",
    "sg:orig_category":"Ense\u00d1anza Variada",
    "sg:phone":"+34 972 20 27 84",
    "sg:postcode":"17003",
    "sg:province":"Girona",
    "wof:name":"Escola De Dansa Cont-class",
    "wof:placetype":"venue"
},
  "geometry": {"coordinates":[2.8230121136,41.9732894897],"type":"Point"}
}