{
  "type": "Feature",
  "properties": {
    "iso:country":"ES",
    "sg:address":"Calle de Sierra De La Atalaya, 1",
    "sg:city":"Viator",
    "sg:orig_category":"Estudios, Instalaci\u00d3n De Climatizaci\u00d3n",
    "sg:phone":"+34 950 30 52 03",
    "sg:postcode":"04240",
    "sg:province":"Almer\u00eda",
    "wof:name":"Airzone S.l.",
    "wof:placetype":"venue"
},
  "geometry": {"coordinates":[-2.4222350121,36.8789215088],"type":"Point"}
}