{
  "type": "Feature",
  "properties": {
    "iso:country":"ES",
    "sg:address":"Plaz Rey Chindasvinto, 9",
    "sg:city":"Covarrubias",
    "sg:orig_category":"Cajas Para Embalar",
    "sg:phone":"+34 947 40 65 75",
    "sg:postcode":"09346",
    "sg:province":"Burgos",
    "wof:name":"Caja Rural De Burgos",
    "wof:placetype":"venue"
},
  "geometry": {"coordinates":[-3.5195400715,42.0582504272],"type":"Point"}
}