{
  "type": "Feature",
  "properties": {
    "addr:full":"Calle de Naval La, 4 Palmas De Gran Canaria Las Palmas 35008",
    "addr:postcode":"35008",
    "addr:street":"Calle De Naval La 4",
    "iso:country":"ES",
    "sg:address":"Calle de Naval La, 4",
    "sg:city":"Palmas De Gran Canaria",
    "sg:orig_category":"Ingenier\u00cda, Centros De Estudios (industria)",
    "sg:phone":"+34 928 47 02 55",
    "sg:postcode":"35008",
    "sg:province":"Las Palmas",
    "wof:name":"Gomez Hernandez Emilio",
    "wof:placetype":"venue"
},
  "geometry": {"coordinates":[-15.4307718277,28.1485023499],"type":"Point"}
}