{
  "type": "Feature",
  "properties": {
    "addr:full":"Avda Ayuntamiento, 49 Agolada Pontevedra 36520",
    "addr:housenumber":"49",
    "addr:postcode":"36520",
    "addr:street":"Avda Ayuntamiento",
    "iso:country":"ES",
    "sg:address":"Avda Ayuntamiento, 49",
    "sg:city":"Agolada",
    "sg:orig_category":"Art\u00cdculos Funerarios (al Por Menor)",
    "sg:phone":"+34 986 78 80 48",
    "sg:postcode":"36520",
    "sg:province":"Pontevedra",
    "wof:name":"Sanchez Otero Jose Antonio",
    "wof:placetype":"venue"
},
  "geometry": {"coordinates":[-8.0172491074,42.7643013],"type":"Point"}
}