{
  "type": "Feature",
  "properties": {
    "iso:country":"ES",
    "sg:address":"Calle de Pozo, 6",
    "sg:city":"Ventilla",
    "sg:orig_category":"Farmacias",
    "sg:phone":"+34 957 63 87 82",
    "sg:postcode":"14112",
    "sg:province":"C\u00f3rdoba",
    "wof:name":"La Casa Becerril Jesus",
    "wof:placetype":"venue"
},
  "geometry": {"coordinates":[-5.070813179,37.7126312256],"type":"Point"}
}