{
  "type": "Feature",
  "properties": {
    "iso:country":"ES",
    "sg:address":"San Nikolas Kalea, 6",
    "sg:city":"Hondarribia",
    "sg:orig_category":"Alimentaci\u00d3n General (al Por Menor)",
    "sg:phone":"+34 943 64 52 58",
    "sg:postcode":"20280",
    "sg:province":"Guip\u00f9zcoa",
    "wof:name":"Paz Alvarez Blanca",
    "wof:placetype":"venue"
},
  "geometry": {"coordinates":[-1.7921439409,43.3635520935],"type":"Point"}
}