{
  "type": "Feature",
  "properties": {
    "iso:country":"ES",
    "sg:address":"Avda Blasco Iba\u00d1ez, 124",
    "sg:city":"Valencia",
    "sg:orig_category":"Carnicer\u00cdas, Carnicer\u00cdas",
    "sg:phone":"+34 963 55 34 52",
    "sg:postcode":"46022",
    "sg:province":"Valencia",
    "wof:name":"Perez Lahoz Teodoro",
    "wof:placetype":"venue"
},
  "geometry": {"coordinates":[-0.3464260101,39.473110199],"type":"Point"}
}