{
  "type": "Feature",
  "properties": {
    "addr:full":"Calle de Carretera, S/n Tolva Huesca 22585",
    "addr:postcode":"22585",
    "addr:street":"Calle De Carretera S / N Tolva",
    "iso:country":"ES",
    "sg:address":"Calle de Carretera, S/n",
    "sg:city":"Tolva",
    "sg:orig_category":"Cr\u00cda De Cerdos",
    "sg:phone":"+34 974 54 35 94",
    "sg:postcode":"22585",
    "sg:province":"Huesca",
    "wof:name":"Pubill De Tolva S.l.",
    "wof:placetype":"venue"
},
  "geometry": {"coordinates":[0.5620827079,42.1145973206],"type":"Point"}
}