{
  "type": "Feature",
  "properties": {
    "addr:full":"Luga Vega (la), 1 Pedro Valiente C\u00e1diz 11380",
    "addr:postcode":"11380",
    "addr:street":"La 1 Pedro Valiente Ca\u0301Diz",
    "iso:country":"ES",
    "sg:address":"Luga Vega (la), 1",
    "sg:city":"Pedro Valiente",
    "sg:orig_category":"Empresas De Carpinter\u00cda Met\u00c1lica",
    "sg:phone":"+34 956 68 22 78",
    "sg:postcode":"11380",
    "sg:province":"C\u00e1diz",
    "wof:name":"Alucristal Tarifa 2004 S.l.",
    "wof:placetype":"venue"
},
  "geometry": {"coordinates":[-5.6250824928,36.0428543091],"type":"Point"}
}