{
  "type": "Feature",
  "properties": {
    "addr:full":"Avda Manantiales De Los, 21 Torremolinos M\u00e1laga 29620",
    "addr:postcode":"29620",
    "addr:street":"Avda Manantiales De Los;Ma\u0301Laga",
    "iso:country":"ES",
    "sg:address":"Avda Manantiales De Los, 21",
    "sg:city":"Torremolinos",
    "sg:orig_category":"Pintura Y Barniz (al Por Menor)",
    "sg:phone":"+34 952 37 15 86",
    "sg:postcode":"29620",
    "sg:province":"M\u00e1laga",
    "wof:name":"Almacen De Pinturas Andalucia S.a.",
    "wof:placetype":"venue"
},
  "geometry": {"coordinates":[-4.5022087097,36.6265678406],"type":"Point"}
}