{
  "type": "Feature",
  "properties": {
    "addr:full":"Gustey, S/n Gustei Ourense 32100",
    "addr:postcode":"32100",
    "addr:street":"Gustey S / N",
    "iso:country":"ES",
    "sg:address":"Gustey, S/n",
    "sg:city":"Gustei",
    "sg:orig_category":"M\u00c1rmoles, Granitos Y Piedras Naturales",
    "sg:phone":"+34 988 20 40 49",
    "sg:postcode":"32100",
    "sg:province":"Ourense",
    "wof:name":"Marmoles Failde S.l.",
    "wof:placetype":"venue"
},
  "geometry": {"coordinates":[-7.852959156,42.3917961121],"type":"Point"}
}