{
  "type": "Feature",
  "properties": {
    "addr:full":"Calle de Benquerencia, 12 Monterrubio Serena Badajoz 06427",
    "addr:housenumber":"12",
    "addr:postcode":"06427",
    "addr:street":"Calle De Benquerencia",
    "iso:country":"ES",
    "sg:address":"Calle de Benquerencia, 12",
    "sg:city":"Monterrubio Serena",
    "sg:orig_category":"Farmacias",
    "sg:phone":"+34 924 61 03 59",
    "sg:postcode":"06427",
    "sg:province":"Badajoz",
    "wof:name":"Jimenez Benitez-cano Agustin",
    "wof:placetype":"venue"
},
  "geometry": {"coordinates":[-5.4464364052,38.5892715454],"type":"Point"}
}