{
  "type": "Feature",
  "properties": {
    "addr:full":"Carrer de Cuartel Del Sur, 24 Almoster Tarragona 43393",
    "addr:housenumber":"24",
    "addr:postcode":"43393",
    "addr:street":"Carrer De Cuartel Del;Almoster",
    "iso:country":"ES",
    "sg:address":"Carrer de Cuartel Del Sur, 24",
    "sg:city":"Almoster",
    "sg:orig_category":"Ingeniero",
    "sg:phone":"+34 977 85 51 67",
    "sg:postcode":"43393",
    "sg:province":"Tarragona",
    "wof:name":"Llevat Grau Jose Maria",
    "wof:placetype":"venue"
},
  "geometry": {"coordinates":[1.1149460077,41.1972198486],"type":"Point"}
}