{
  "type": "Feature",
  "properties": {
    "addr:full":"Calle de Santa Maria Bajera, 42 Briviesca Burgos 09240",
    "addr:housenumber":"42",
    "addr:postcode":"09240",
    "addr:street":"Calle De Santa;Bajera",
    "iso:country":"ES",
    "sg:address":"Calle de Santa Maria Bajera, 42",
    "sg:city":"Briviesca",
    "sg:orig_category":"Empresas De Desmonte",
    "sg:phone":"+34 947 59 03 52",
    "sg:postcode":"09240",
    "sg:province":"Burgos",
    "wof:name":"Rua Prieto Manuel Y Otros S.c.",
    "wof:placetype":"venue"
},
  "geometry": {"coordinates":[-3.3234388828,42.5518035889],"type":"Point"}
}