{
  "type": "Feature",
  "properties": {
    "addr:full":"Rua San Lazaro, 25 Monforte De Lemos Lugo 27400",
    "addr:housenumber":"25",
    "addr:postcode":"27400",
    "addr:street":"Rua San Lazaro",
    "iso:country":"ES",
    "sg:address":"Rua San Lazaro, 25",
    "sg:city":"Monforte De Lemos",
    "sg:orig_category":"Molduras, Junquillos, Listones Y Molduras Perforadas",
    "sg:phone":"+34 982 40 30 01",
    "sg:postcode":"27400",
    "sg:province":"Lugo",
    "wof:name":"Martinez Suarez Pablo",
    "wof:placetype":"venue"
},
  "geometry": {"coordinates":[-7.5217971802,42.5139465332],"type":"Point"}
}