{
  "type": "Feature",
  "properties": {
    "iso:country":"ES",
    "sg:address":"C/ Sant Nicolau, 37",
    "sg:city":"Alcoi",
    "sg:classifiers":[
        {
            "category":"Personal",
            "subcategory":"Barber",
            "type":"Services"
        }
    ],
    "sg:phone":"+34 965 54 24 29",
    "sg:postcode":"03801",
    "sg:province":"Alicante",
    "sg:tags":[
        "caballeros",
        "de",
        "peluqueros"
    ],
    "wof:name":"Mora Masia Pedro Luis",
    "wof:placetype":"venue"
},
  "geometry": {"coordinates":[-0.4729830027,38.6962127686],"type":"Point"}
}