{
  "type": "Feature",
  "properties": {
    "addr:full":"Irlanda (pol Industrial), S/n Constanti Tarragona 43120",
    "addr:housenumber":"/ n",
    "addr:postcode":"43120",
    "addr:street":"Industrial",
    "iso:country":"ES",
    "sg:address":"Irlanda (pol Industrial), S/n",
    "sg:city":"Constanti",
    "sg:orig_category":"Hormigonados",
    "sg:phone":"+34 977 29 63 82",
    "sg:postcode":"43120",
    "sg:province":"Tarragona",
    "wof:name":"Promotora Mediterranea 2 S.a.",
    "wof:placetype":"venue"
},
  "geometry": {"coordinates":[1.1769750118,41.1675987244],"type":"Point"}
}