{
  "type": "Feature",
  "properties": {
    "iso:country":"ES",
    "sg:address":"Calle de Tegucigalpa, S/n",
    "sg:city":"Motril",
    "sg:orig_category":"Agencias Y Agentes Comerciales, Representantes",
    "sg:phone":"+34 958 82 22 87",
    "sg:postcode":"18600",
    "sg:province":"Granada",
    "wof:name":"Javier Carrion S.l.u.",
    "wof:placetype":"venue"
},
  "geometry": {"coordinates":[-3.5123870373,36.7385215759],"type":"Point"}
}