{
  "type": "Feature",
  "properties": {
    "addr:full":"Carrer de Rosa De Alejandria, 46 Hospitalet Llobregat Barcelona 08906",
    "addr:housenumber":"46",
    "addr:postcode":"08906",
    "addr:street":"Carrer De Rosa De Alejandria",
    "iso:country":"ES",
    "sg:address":"Carrer de Rosa De Alejandria, 46",
    "sg:city":"Hospitalet Llobregat",
    "sg:orig_category":"Carnicer\u00cdas, Carnicer\u00cdas",
    "sg:phone":"+34 934 37 11 21",
    "sg:postcode":"08906",
    "sg:province":"Barcelona",
    "wof:name":"Porredon Sole Jordi-ramon",
    "wof:placetype":"venue"
},
  "geometry": {"coordinates":[12.4903001785,51.6163101196],"type":"Point"}
}