{
  "type": "Feature",
  "properties": {
    "iso:country":"ES",
    "sg:address":"Avda Juan Andres, 15",
    "sg:city":"Madrid",
    "sg:orig_category":"Inversiones",
    "sg:phone":"+34 913 73 87 63",
    "sg:postcode":"28035",
    "sg:province":"Madrid",
    "wof:name":"Confecciones Y Distribuciones Picos,s.l.",
    "wof:placetype":"venue"
},
  "geometry": {"coordinates":[-3.723058939,40.4678153992],"type":"Point"}
}