{
  "type": "Feature",
  "properties": {
    "iso:country":"ES",
    "sg:address":"Calle de Infantes, 18",
    "sg:city":"Ronda",
    "sg:orig_category":"Promotores Constructores",
    "sg:phone":"+34 952 87 71 33",
    "sg:postcode":"29400",
    "sg:province":"M\u00e1laga",
    "wof:name":"Inprosur Inversiones S.l.",
    "wof:placetype":"venue"
},
  "geometry": {"coordinates":[-5.1640868187,36.7447738647],"type":"Point"}
}