{
  "type": "Feature",
  "properties": {
    "iso:country":"ES",
    "sg:address":"Calle de San Juan De Dios, 1",
    "sg:city":"Cadiz",
    "sg:orig_category":"Hospitales",
    "sg:phone":"+34 956 28 73 51",
    "sg:postcode":"11005",
    "sg:province":"C\u00e1diz",
    "wof:name":"Hospital De La Misericordia Y San Juan De Dios",
    "wof:placetype":"venue"
},
  "geometry": {"coordinates":[-6.2923350334,36.5303268433],"type":"Point"}
}