{
  "type": "Feature",
  "properties": {
    "iso:country":"ES",
    "sg:address":"Calle de San Fernando, 113",
    "sg:city":"Najera",
    "sg:orig_category":"Molduras, Junquillos, Listones Y Molduras Perforadas",
    "sg:phone":"+34 941 36 00 69",
    "sg:postcode":"26300",
    "sg:province":"La Rioja",
    "wof:name":"Cambero Uru\u00f1uela Fausto",
    "wof:placetype":"venue"
},
  "geometry": {"coordinates":[-2.7240419388,42.4181098938],"type":"Point"}
}