{
  "type": "Feature",
  "properties": {
    "iso:country":"ES",
    "sg:address":"Pg Fabra I Puig, 394",
    "sg:city":"Barcelona",
    "sg:orig_category":"Psic\u00d3logos",
    "sg:phone":"+34 934 20 99 14",
    "sg:postcode":"08031",
    "sg:province":"Barcelona",
    "wof:name":"Garcia Delgado Francesc",
    "wof:placetype":"venue"
},
  "geometry": {"coordinates":[2.1631879807,41.4329071045],"type":"Point"}
}