{
  "type": "Feature",
  "properties": {
    "addr:full":"La Amarguilla, S/n Alameda M\u00e1laga 29530",
    "addr:housenumber":"/ n",
    "addr:postcode":"29530",
    "addr:street":"Amarguilla S;Alameda Ma\u0301Laga",
    "iso:country":"ES",
    "sg:address":"La Amarguilla, S/n",
    "sg:city":"Alameda",
    "sg:orig_category":"Muebles",
    "sg:phone":"+34 952 71 11 55",
    "sg:postcode":"29530",
    "sg:province":"M\u00e1laga",
    "wof:name":"Granados Fuentes S.l.",
    "wof:placetype":"venue"
},
  "geometry": {"coordinates":[-4.6518378258,37.2117919922],"type":"Point"}
}