{
  "type": "Feature",
  "properties": {
    "addr:full":"Pase Pio Baroja De, 4 Donostia-san Sebastian Guip\u00f9zcoa 20008",
    "addr:housenumber":"4",
    "addr:postcode":"20008",
    "addr:street":"Pio Baroja De",
    "iso:country":"ES",
    "sg:address":"Pase Pio Baroja De, 4",
    "sg:city":"Donostia-san Sebastian",
    "sg:orig_category":"M\u00c9dicos: Cardiolog\u00cda Y Afecciones Cardiovasculares",
    "sg:phone":"+34 943 45 33 65",
    "sg:postcode":"20008",
    "sg:province":"Guip\u00f9zcoa",
    "wof:name":"Arrue Imaz Ricardo",
    "wof:placetype":"venue"
},
  "geometry": {"coordinates":[-1.995388031,43.3103942871],"type":"Point"}
}