{
  "type": "Feature",
  "properties": {
    "addr:full":"Calle de Santos Justo Y Pastor, 140 Valencia Valencia 46022",
    "addr:housenumber":"140",
    "addr:postcode":"46022",
    "addr:street":"Calle De Santos Justo Y Pastor",
    "iso:country":"ES",
    "sg:address":"Calle de Santos Justo Y Pastor, 140",
    "sg:city":"Valencia",
    "sg:orig_category":"Cl\u00cdnicas Dentales",
    "sg:phone":"+34 963 55 96 00",
    "sg:postcode":"46022",
    "sg:province":"Valencia",
    "wof:name":"Clinicas Farmalent S.l.",
    "wof:placetype":"venue"
},
  "geometry": {"coordinates":[-0.3373709917,39.4665489197],"type":"Point"}
}