{
  "type": "Feature",
  "properties": {
    "addr:full":"Avda Antonio Machado, 20 Ubeda Ja\u00e9n 23400",
    "addr:housenumber":"20",
    "addr:postcode":"23400",
    "addr:street":"Avda Antonio Machado;Jae\u0301N",
    "iso:country":"ES",
    "sg:address":"Avda Antonio Machado, 20",
    "sg:city":"Ubeda",
    "sg:orig_category":"Iglesias Evang\u00c9licas",
    "sg:phone":"+34 953 75 31 75",
    "sg:postcode":"23400",
    "sg:province":"Ja\u00e9n",
    "wof:name":"Iglesia Cristiana Evangelica De Ubeda",
    "wof:placetype":"venue"
},
  "geometry": {"coordinates":[-3.3674418926,38.013633728],"type":"Point"}
}