{
  "type": "Feature",
  "properties": {
    "iso:country":"ES",
    "sg:address":"Calle de Olid, 4",
    "sg:city":"Madrid",
    "sg:orig_category":"Teatro, Ballet, Danza (agrupaciones, Compa\u00d1\u00cdas)",
    "sg:phone":"+34 915 94 41 52",
    "sg:postcode":"28010",
    "sg:province":"Madrid",
    "wof:name":"Haro Y Triana Asociados S.l.",
    "wof:placetype":"venue"
},
  "geometry": {"coordinates":[-3.7028579712,40.4315643311],"type":"Point"}
}