{
  "type": "Feature",
  "properties": {
    "addr:full":"Ctra Oca\u00d1a, Km. 0034,5 Alameda Sagra Toledo 45240",
    "addr:postcode":"45240",
    "addr:street":"Ctra Ocan\u0303A Km. 0034,5;Sagra",
    "iso:country":"ES",
    "sg:address":"Ctra Oca\u00d1a, Km. 0034,5",
    "sg:city":"Alameda Sagra",
    "sg:orig_category":"Material Y Herramientas Agr\u00cdcolas",
    "sg:phone":"+34 925 50 02 18",
    "sg:postcode":"45240",
    "sg:province":"Toledo",
    "wof:name":"Agrosagra S.l.",
    "wof:placetype":"venue"
},
  "geometry": {"coordinates":[-3.7944357395,40.0096588135],"type":"Point"}
}