{
  "type": "Feature",
  "properties": {
    "addr:full":"Calle de Belgica, 54 San Fernando Santa Cruz De Tenerife 38400",
    "addr:housenumber":"54",
    "addr:postcode":"38400",
    "addr:street":"Calle De Belgica",
    "iso:country":"ES",
    "sg:address":"Calle de Belgica, 54",
    "sg:city":"San Fernando",
    "sg:orig_category":"Ropa Para Se\u00d1oras (al Por Menor)",
    "sg:phone":"+34 922 38 47 38",
    "sg:postcode":"38400",
    "sg:province":"Santa Cruz De Tenerife",
    "wof:name":"Bornak  Azadeh",
    "wof:placetype":"venue"
},
  "geometry": {"coordinates":[-16.2548561096,28.4698104858],"type":"Point"}
}