{
  "type": "Feature",
  "properties": {
    "iso:country":"ES",
    "sg:address":"Calle de Luis Cabrera, 43",
    "sg:city":"Madrid",
    "sg:orig_category":"Dorados, Plater\u00cda (orfebrer\u00cda)",
    "sg:phone":"+34 915 63 89 31",
    "sg:postcode":"28002",
    "sg:province":"Madrid",
    "wof:name":"Orfebreria Pascual S.a.",
    "wof:placetype":"venue"
},
  "geometry": {"coordinates":[-3.674202919,40.4434242249],"type":"Point"}
}