{
  "type": "Feature",
  "properties": {
    "addr:full":"Calle de Vereda De Los Barros, 11 Ventorro Del Cano Madrid 28925",
    "addr:housenumber":"11",
    "addr:postcode":"28925",
    "addr:street":"Calle De Vereda De Los Barros",
    "iso:country":"ES",
    "sg:address":"Calle de Vereda De Los Barros, 11",
    "sg:city":"Ventorro Del Cano",
    "sg:orig_category":"Fabricaci\u00d3n De Cervezas",
    "sg:phone":"+34 916 33 16 98",
    "sg:postcode":"28925",
    "sg:province":"Madrid",
    "wof:name":"Delgado De Madrid, S.l.",
    "wof:placetype":"venue"
},
  "geometry": {"coordinates":[-3.832005024,40.3908424377],"type":"Point"}
}