{
  "type": "Feature",
  "properties": {
    "iso:country":"ES",
    "sg:address":"Avda Tenerife (de), 14",
    "sg:city":"San Sebastian De Los Reyes",
    "sg:orig_category":"Distribuci\u00d3n De Petr\u00d3leo Y Derivados",
    "sg:phone":"+34 916 53 45 92",
    "sg:postcode":"28700",
    "sg:province":"Madrid",
    "wof:name":"Los Olivos Estacion De Servicio S.a.",
    "wof:placetype":"venue"
},
  "geometry": {"coordinates":[-3.6213591099,40.5597915649],"type":"Point"}
}