{
  "type": "Feature",
  "properties": {
    "iso:country":"ES",
    "sg:address":"Cust San Vicente, 2",
    "sg:city":"Vitoria-gasteiz",
    "sg:orig_category":"Ropa Y Accesorios",
    "sg:phone":"+34 945 28 03 26",
    "sg:postcode":"01001",
    "sg:province":"\u00c1lava",
    "wof:name":"Higueras Paulete Jose Luis",
    "wof:placetype":"venue"
},
  "geometry": {"coordinates":[-2.6722991467,42.8485374451],"type":"Point"}
}