{
  "type": "Feature",
  "properties": {
    "addr:full":"Avda Bravo Murillo, 3 Santa Cruz De Tenerife Santa Cruz De Tenerife 38003",
    "addr:housenumber":"3",
    "addr:postcode":"38003",
    "addr:street":"Avda Bravo Murillo",
    "iso:country":"ES",
    "sg:address":"Avda Bravo Murillo, 3",
    "sg:city":"Santa Cruz De Tenerife",
    "sg:orig_category":"Refiner\u00cdas De Petr\u00d3leo",
    "sg:phone":"+34 922 53 43 80",
    "sg:postcode":"38003",
    "sg:province":"Santa Cruz De Tenerife",
    "sg:website":"www.petrogas.es",
    "wof:name":"Distribuidora Maritima Petrogas S.l.",
    "wof:placetype":"venue"
},
  "geometry": {"coordinates":[-16.3326644897,28.4846744537],"type":"Point"}
}