{
  "type": "Feature",
  "properties": {
    "iso:country":"ES",
    "sg:address":"Calle de Apolo, 2",
    "sg:city":"Mairena Aljarafe",
    "sg:orig_category":"Centros De Educaci\u00d3n Especial",
    "sg:phone":"+34 954 18 69 69",
    "sg:postcode":"41927",
    "sg:province":"Sevilla",
    "wof:name":"Colegio La Casita De Chocolate S.l.",
    "wof:placetype":"venue"
},
  "geometry": {"coordinates":[-6.0510787964,37.3555984497],"type":"Point"}
}