{
  "type": "Feature",
  "properties": {
    "iso:country":"ES",
    "sg:address":"Avda Seis De Diciembre, 1",
    "sg:city":"Sant Joan D'alacant",
    "sg:classifiers":[
        {
            "category":"Professional",
            "subcategory":"Management & Consulting",
            "type":"Services"
        }
    ],
    "sg:phone":"+34 965 65 28 56",
    "sg:postcode":"03550",
    "sg:province":"Alicante",
    "sg:tags":[
        "asesor\u00cda",
        "en",
        "marketing"
    ],
    "wof:name":"Aula Empresarial S.l.",
    "wof:placetype":"venue"
},
  "geometry": {"coordinates":[-0.4804700017,38.3440818787],"type":"Point"}
}