{
  "type": "Feature",
  "properties": {
    "iso:country":"ES",
    "sg:address":"Calle de Olavide, 60",
    "sg:city":"Carolina",
    "sg:orig_category":"Servicios Diversos",
    "sg:phone":"+34 953 66 11 55",
    "sg:postcode":"23200",
    "sg:province":"Ja\u00e9n",
    "wof:name":"Sistemas De Informacion Y Verificacion S.l.",
    "wof:placetype":"venue"
},
  "geometry": {"coordinates":[-3.6198420525,38.2727584839],"type":"Point"}
}