{
  "type": "Feature",
  "properties": {
    "addr:full":"Calle de Ezcurdia, 98 Gijon Asturias 33202",
    "addr:housenumber":"98",
    "addr:postcode":"33202",
    "addr:street":"Calle De Ezcurdia",
    "iso:country":"ES",
    "sg:address":"Calle de Ezcurdia, 98",
    "sg:city":"Gijon",
    "sg:orig_category":"Estancos",
    "sg:phone":"+34 985 33 08 54",
    "sg:postcode":"33202",
    "sg:province":"Asturias",
    "wof:name":"Mu\u00f1iz Rodriguez Maria Victoria",
    "wof:placetype":"venue"
},
  "geometry": {"coordinates":[-5.6509990692,43.5385551453],"type":"Point"}
}