{
  "type": "Feature",
  "properties": {
    "addr:full":"Calle de San Ildefonso, 32 Villarrobledo Albacete 02600",
    "addr:housenumber":"32",
    "addr:postcode":"02600",
    "addr:street":"Calle De San Ildefonso",
    "iso:country":"ES",
    "sg:address":"Calle de San Ildefonso, 32",
    "sg:city":"Villarrobledo",
    "sg:orig_category":"Chapister\u00cda",
    "sg:phone":"+34 967 14 05 25",
    "sg:postcode":"02600",
    "sg:province":"Albacete",
    "wof:name":"Montoya Lopez Juan",
    "wof:placetype":"venue"
},
  "geometry": {"coordinates":[-2.6026189327,39.2637481689],"type":"Point"}
}