{
  "type": "Feature",
  "properties": {
    "iso:country":"ES",
    "sg:address":"Av Josep Tarradellas, 31",
    "sg:city":"Barcelona",
    "sg:orig_category":"\u00d3ptica: Instrumentos (fabricaci\u00d3n)",
    "sg:phone":"+34 933 22 45 22",
    "sg:postcode":"08029",
    "sg:province":"Barcelona",
    "wof:name":"Optica Segura S.c.p.",
    "wof:placetype":"venue"
},
  "geometry": {"coordinates":[2.1420960426,41.3828735352],"type":"Point"}
}