{
  "type": "Feature",
  "properties": {
    "iso:country":"ES",
    "sg:address":"Calle de Mayor, 6",
    "sg:city":"Cartagena",
    "sg:orig_category":"Organizaciones Profesionales",
    "sg:phone":"+34 968 52 87 51",
    "sg:postcode":"30201",
    "sg:province":"Murcia",
    "wof:name":"Daniel Gomez Gomez S.a.",
    "wof:placetype":"venue"
},
  "geometry": {"coordinates":[-0.9156429768,37.600566864],"type":"Point"}
}