{
  "type": "Feature",
  "properties": {
    "addr:full":"Carr Sant Tomas, 8 Benicasim Castell\u00f3n 12560",
    "addr:housenumber":"8",
    "addr:postcode":"12560",
    "addr:street":"Carr Sant Tomas",
    "iso:country":"ES",
    "sg:address":"Carr Sant Tomas, 8",
    "sg:city":"Benicasim",
    "sg:orig_category":"Estancos",
    "sg:phone":"+34 964 30 49 97",
    "sg:postcode":"12560",
    "sg:province":"Castell\u00f3n",
    "wof:name":"Ventura Abego Francisco Angel",
    "wof:placetype":"venue"
},
  "geometry": {"coordinates":[0.0457400009,40.0510292053],"type":"Point"}
}