{
  "type": "Feature",
  "properties": {
    "iso:country":"ES",
    "sg:address":"Pla\u00c7 Serra Del Cadi, 1",
    "sg:city":"Tuixent",
    "sg:orig_category":"Museos",
    "sg:phone":"+34 973 37 00 30",
    "sg:postcode":"25717",
    "sg:province":"Lleida",
    "wof:name":"Recursos I Iniciatives Tuixent S.a.",
    "wof:placetype":"venue"
},
  "geometry": {"coordinates":[1.5666669607,42.2310714722],"type":"Point"}
}