{
  "type": "Feature",
  "properties": {
    "iso:country":"ES",
    "sg:address":"Ctra Almeria, Km. 0286,0",
    "sg:city":"Llanos",
    "sg:orig_category":"Frutas Y Legumbres Frescas (al Por Mayor)",
    "sg:phone":"+34 952 53 10 26",
    "sg:postcode":"29793",
    "sg:province":"M\u00e1laga",
    "wof:name":"Gonzalez Gonzalez Manuel",
    "wof:placetype":"venue"
},
  "geometry": {"coordinates":[-3.9633140564,36.7310066223],"type":"Point"}
}