{
  "type": "Feature",
  "properties": {
    "addr:full":"Calle de Doctor Iranzo, 44 Zaragoza Zaragoza 50002",
    "addr:housenumber":"44",
    "addr:postcode":"50002",
    "addr:street":"Calle De Doctor Iranzo",
    "iso:country":"ES",
    "sg:address":"Calle de Doctor Iranzo, 44",
    "sg:city":"Zaragoza",
    "sg:orig_category":"Quincaller\u00cda (al Por Menor)",
    "sg:phone":"+34 976 42 85 88",
    "sg:postcode":"50002",
    "sg:province":"Zaragoza",
    "wof:name":"Pinturas Y Ferreteria Candelas S.l.",
    "wof:placetype":"venue"
},
  "geometry": {"coordinates":[-0.8643869162,41.6449050903],"type":"Point"}
}