{
  "type": "Feature",
  "properties": {
    "iso:country":"ES",
    "sg:address":"Calle de Poeta Llorente, 28",
    "sg:city":"Pobla Vallbona",
    "sg:orig_category":"Bancos",
    "sg:phone":"+34 962 76 12 11",
    "sg:postcode":"46185",
    "sg:province":"Valencia",
    "wof:name":"Banco Popular Espa\u00f1ol",
    "wof:placetype":"venue"
},
  "geometry": {"coordinates":[-0.5529469848,39.5924224854],"type":"Point"}
}