{
  "type": "Feature",
  "properties": {
    "iso:country":"ES",
    "sg:address":"Avda Marques De Figueroa, 1",
    "sg:city":"Ameneiral",
    "sg:orig_category":"Inmobiliaria (agencias)",
    "sg:phone":"+34 981 34 01 60",
    "sg:postcode":"15500",
    "sg:province":"La Coru\u00f1a",
    "wof:name":"Perez Soto Pablo Manuel",
    "wof:placetype":"venue"
},
  "geometry": {"coordinates":[-8.1644191742,43.4750747681],"type":"Point"}
}