{
  "type": "Feature",
  "properties": {
    "iso:country":"ES",
    "sg:address":"Avda Pio Xii, 15",
    "sg:city":"Logro\u00f1o",
    "sg:orig_category":"Centros De Salud",
    "sg:phone":"+34 941 25 67 80",
    "sg:postcode":"26003",
    "sg:province":"La Rioja",
    "wof:name":"Lafuente Castells Juan Miguel",
    "wof:placetype":"venue"
},
  "geometry": {"coordinates":[-2.4435589314,42.4603996277],"type":"Point"}
}