{
  "type": "Feature",
  "properties": {
    "iso:country":"ES",
    "sg:address":"Calle de Camino Viejo De Leganes, 10",
    "sg:city":"Madrid",
    "sg:orig_category":"M\u00c9dicos: Estomatolog\u00cda",
    "sg:phone":"+34 914 72 23 29",
    "sg:postcode":"28019",
    "sg:province":"Madrid",
    "wof:name":"Barale Villosio Rodolfo Ramon",
    "wof:placetype":"venue"
},
  "geometry": {"coordinates":[-3.7238690853,40.3926315308],"type":"Point"}
}