{
  "type": "Feature",
  "properties": {
    "iso:country":"ES",
    "sg:address":"Calle de Isabel Ii, 8",
    "sg:city":"Santander",
    "sg:orig_category":"Bisuter\u00cda, Joyer\u00cda, Relojer\u00cda (al Por Menor)",
    "sg:phone":"+34 942 36 03 79",
    "sg:postcode":"39002",
    "sg:province":"Cantabria",
    "wof:name":"Gomez Fernandez Jesus Maria",
    "wof:placetype":"venue"
},
  "geometry": {"coordinates":[-3.8095920086,43.4610786438],"type":"Point"}
}