{
  "type": "Feature",
  "properties": {
    "addr:full":"Carr Galerias Albatros, 76 Platja D'aro Girona 17250",
    "addr:housenumber":"76",
    "addr:postcode":"17250",
    "addr:street":"Carr Galerias Albatros",
    "iso:country":"ES",
    "sg:address":"Carr Galerias Albatros, 76",
    "sg:city":"Platja D'aro",
    "sg:orig_category":"Ropa Para Ni\u00d1os (al Por Menor)",
    "sg:phone":"+34 972 82 54 52",
    "sg:postcode":"17250",
    "sg:province":"Girona",
    "wof:name":"Van Winsen S.l.",
    "wof:placetype":"venue"
},
  "geometry": {"coordinates":[2.8163490295,41.9701499939],"type":"Point"}
}