{
  "type": "Feature",
  "properties": {
    "addr:full":"Calle de Aldebaran, 3 Alacant Alicante 03006",
    "addr:housenumber":"3",
    "addr:postcode":"03006",
    "addr:street":"Calle De Aldebaran",
    "iso:country":"ES",
    "sg:address":"Calle de Aldebaran, 3",
    "sg:city":"Alacant",
    "sg:orig_category":"Pintura Y Barniz (al Por Menor)",
    "sg:phone":"+34 965 11 05 30",
    "sg:postcode":"03006",
    "sg:province":"Alicante",
    "wof:name":"Marpas Color S.c.",
    "wof:placetype":"venue"
},
  "geometry": {"coordinates":[-0.5109544992,38.3449783325],"type":"Point"}
}