{
  "type": "Feature",
  "properties": {
    "addr:full":"Calle de San Roque, 9 Pinseque Zaragoza 50298",
    "addr:housenumber":"9",
    "addr:postcode":"50298",
    "addr:street":"Calle De San Roque",
    "iso:country":"ES",
    "sg:address":"Calle de San Roque, 9",
    "sg:city":"Pinseque",
    "sg:orig_category":"Asilos De Ancianos. Centros Privados",
    "sg:phone":"+34 976 65 67 48",
    "sg:postcode":"50298",
    "sg:province":"Zaragoza",
    "wof:name":"Operadores Telefonicos De Aragon S.l.",
    "wof:placetype":"venue"
},
  "geometry": {"coordinates":[-1.0995980501,41.7370872498],"type":"Point"}
}