{
  "type": "Feature",
  "properties": {
    "addr:full":"Calle de Duque De Frias, 10 Burgos Burgos 09006",
    "addr:housenumber":"10",
    "addr:postcode":"09006",
    "addr:street":"Calle De Duque De Frias",
    "iso:country":"ES",
    "sg:address":"Calle de Duque De Frias, 10",
    "sg:city":"Burgos",
    "sg:orig_category":"Perfumer\u00cda (al Por Menor)",
    "sg:phone":"+34 947 22 96 94",
    "sg:postcode":"09006",
    "sg:province":"Burgos",
    "wof:name":"Perfumeria Tinuca S.l.",
    "wof:placetype":"venue"
},
  "geometry": {"coordinates":[-3.6776063442,42.3598098755],"type":"Point"}
}