{
  "type": "Feature",
  "properties": {
    "iso:country":"ES",
    "sg:address":"Calle de Pe\u00d1on (el), 1",
    "sg:city":"Puerto Cruz",
    "sg:orig_category":"M\u00c9dicos: Oftalmolog\u00cda",
    "sg:phone":"+34 922 37 01 20",
    "sg:postcode":"38400",
    "sg:province":"Santa Cruz De Tenerife",
    "wof:name":"Mantolan Sarmiento Maria Cristina",
    "wof:placetype":"venue"
},
  "geometry": {"coordinates":[-16.5525894165,28.4156570435],"type":"Point"}
}