{
  "type": "Feature",
  "properties": {
    "iso:country":"ES",
    "sg:address":"Poligono Industrial De Valls, S/n",
    "sg:city":"Valls",
    "sg:orig_category":"Electricidad: Equipos Industriales, Componentes (fabricaci\u00d3n)",
    "sg:phone":"+34 977 61 70 00",
    "sg:postcode":"43800",
    "sg:province":"Tarragona",
    "sg:website":"www.tycoelectronics.com",
    "wof:name":"Tyco Electronics Amp Espa\u00d1a S.a.",
    "wof:placetype":"venue"
},
  "geometry": {"coordinates":[1.2525299788,41.2871513367],"type":"Point"}
}