{
  "type": "Feature",
  "properties": {
    "addr:full":"Calle de Puente, 34 Roquetas Mar Almer\u00eda 04740",
    "addr:housenumber":"34",
    "addr:postcode":"04740",
    "addr:street":"Calle De Puente;Mar Almeri\u0301A",
    "iso:country":"ES",
    "sg:address":"Calle de Puente, 34",
    "sg:city":"Roquetas Mar",
    "sg:orig_category":"Servicios Gsm",
    "sg:phone":"+34 950 32 88 61",
    "sg:postcode":"04740",
    "sg:province":"Almer\u00eda",
    "wof:name":"Tandi Representacion S.l.l.",
    "wof:placetype":"venue"
},
  "geometry": {"coordinates":[-2.6150739193,36.7632713318],"type":"Point"}
}