{
  "type": "Feature",
  "properties": {
    "iso:country":"ES",
    "sg:address":"Pol Ind Pilas Sur, 31",
    "sg:city":"Pilas",
    "sg:orig_category":"Muebles",
    "sg:phone":"+34 954 75 03 64",
    "sg:postcode":"41840",
    "sg:province":"Sevilla",
    "wof:name":"Ofisofa Andalucia S.l.",
    "wof:placetype":"venue"
},
  "geometry": {"coordinates":[-6.3043088913,37.3053894043],"type":"Point"}
}