{
  "type": "Feature",
  "properties": {
    "addr:full":"Calle de Hercules, 16 Linea De La Concepcion C\u00e1diz 11300",
    "addr:housenumber":"16",
    "addr:postcode":"11300",
    "addr:street":"Calle De Hercules;Ca\u0301Diz",
    "iso:country":"ES",
    "sg:address":"Calle de Hercules, 16",
    "sg:city":"Linea De La Concepcion",
    "sg:orig_category":"Empresarios",
    "sg:phone":"+34 956 69 02 89",
    "sg:postcode":"11300",
    "sg:province":"C\u00e1diz",
    "wof:name":"Fundacion Secretariado Gitano",
    "wof:placetype":"venue"
},
  "geometry": {"coordinates":[-5.3495488167,36.1614608765],"type":"Point"}
}