{
  "type": "Feature",
  "properties": {
    "iso:country":"ES",
    "sg:address":"Avda Francia, 34",
    "sg:city":"Laredo",
    "sg:orig_category":"Aguas (distribuci\u00d3n, Servicios)",
    "sg:phone":"+34 942 61 07 33",
    "sg:postcode":"39770",
    "sg:province":"Cantabria",
    "wof:name":"Hidrodena S.l.",
    "wof:placetype":"venue"
},
  "geometry": {"coordinates":[-3.4352788925,43.4124908447],"type":"Point"}
}