{
  "type": "Feature",
  "properties": {
    "iso:country":"ES",
    "sg:address":"Carrer de Ramon I Cajal, 8",
    "sg:city":"Ametlla Mar",
    "sg:orig_category":"Agentes Generales De Seguros",
    "sg:phone":"+34 977 45 63 13",
    "sg:postcode":"43860",
    "sg:province":"Tarragona",
    "wof:name":"Segurboyer S.l.",
    "wof:placetype":"venue"
},
  "geometry": {"coordinates":[0.8023849726,40.8869400024],"type":"Point"}
}