{
  "type": "Feature",
  "properties": {
    "iso:country":"ES",
    "sg:address":"Barro Gorosibai, 5",
    "sg:city":"Galdakao",
    "sg:orig_category":"Fabricaci\u00d3n, Venta, Instalaci\u00d3n De R\u00d3tulos, De R\u00d3tulos Luminosos",
    "sg:phone":"+34 944 56 88 99",
    "sg:postcode":"48960",
    "sg:province":"Vizcaya",
    "sg:website":"www.cintrolsl.com",
    "wof:name":"Cintrol, S.l.",
    "wof:placetype":"venue"
},
  "geometry": {"coordinates":[-2.8138599396,43.2192001343],"type":"Point"}
}