{
  "type": "Feature",
  "properties": {
    "iso:country":"ES",
    "sg:address":"Calle de Obispo Zumarraga, 37",
    "sg:city":"Sevilla",
    "sg:orig_category":"Agencias Y Agentes Comerciales, Representantes",
    "sg:phone":"+34 954 52 89 61",
    "sg:postcode":"41007",
    "sg:province":"Sevilla",
    "wof:name":"Leon Palacios Pedro",
    "wof:placetype":"venue"
},
  "geometry": {"coordinates":[-5.9544610977,37.4005012512],"type":"Point"}
}