{
  "type": "Feature",
  "properties": {
    "addr:full":"Calle de Santo, 2 Villafranca De Los Caballeros Toledo 45730",
    "addr:housenumber":"2",
    "addr:postcode":"45730",
    "addr:street":"Calle De Santo",
    "iso:country":"ES",
    "sg:address":"Calle de Santo, 2",
    "sg:city":"Villafranca De Los Caballeros",
    "sg:orig_category":"Caf\u00c9s, Bares, Cervecer\u00cdas",
    "sg:phone":"+34 926 55 86 31",
    "sg:postcode":"45730",
    "sg:province":"Toledo",
    "wof:name":"Marchante Aviles Felipe",
    "wof:placetype":"venue"
},
  "geometry": {"coordinates":[-3.3635010719,39.4275894165],"type":"Point"}
}