{
  "type": "Feature",
  "properties": {
    "iso:country":"ES",
    "sg:address":"Carr Paborde Marti, 30",
    "sg:city":"Ciutadella Menorca",
    "sg:orig_category":"Asociaciones Y Clubs Deportivos",
    "sg:phone":"+34 971 38 57 98",
    "sg:postcode":"07760",
    "sg:province":"Islas Baleares",
    "wof:name":"Art Gim S.l.",
    "wof:placetype":"venue"
},
  "geometry": {"coordinates":[3.8427782059,40.0010490417],"type":"Point"}
}