{
  "type": "Feature",
  "properties": {
    "iso:country":"ES",
    "sg:address":"Calle de Pedreguer, 30",
    "sg:city":"Alacant",
    "sg:orig_category":"Inmobiliaria (agencias)",
    "sg:phone":"+34 965 28 65 06",
    "sg:postcode":"03008",
    "sg:province":"Alicante",
    "wof:name":"Gigant Vra Neumatic S.l.",
    "wof:placetype":"venue"
},
  "geometry": {"coordinates":[-0.5131620169,38.3268928528],"type":"Point"}
}