{
  "type": "Feature",
  "properties": {
    "addr:full":"Calle de Atocha, 121 Madrid Madrid 28012",
    "addr:housenumber":"121",
    "addr:postcode":"28012",
    "addr:street":"Calle De Atocha",
    "iso:country":"ES",
    "sg:address":"Calle de Atocha, 121",
    "sg:city":"Madrid",
    "sg:orig_category":"Parques De Atracciones Y Centros De Esparcimiento",
    "sg:phone":"+34 913 69 00 21",
    "sg:postcode":"28012",
    "sg:province":"Madrid",
    "wof:name":"Alvarez Cano-caballero Antonio",
    "wof:placetype":"venue"
},
  "geometry": {"coordinates":[-3.6941084862,40.4099388123],"type":"Point"}
}