{
  "type": "Feature",
  "properties": {
    "addr:full":"Calle de Triana, 6 Pilar Horadada Alicante 03190",
    "addr:housenumber":"6",
    "addr:postcode":"03190",
    "addr:street":"Calle De Triana",
    "iso:country":"ES",
    "sg:address":"Calle de Triana, 6",
    "sg:city":"Pilar Horadada",
    "sg:classifiers":[
        {
            "category":"Autos & Motor Vehicles",
            "subcategory":"Automobile Sales",
            "type":"Retail Goods"
        }
    ],
    "sg:phone":"+34 965 35 19 40",
    "sg:postcode":"03190",
    "sg:province":"Alicante",
    "wof:name":"Sansano Sanchez Manuel",
    "wof:placetype":"venue"
},
  "geometry": {"coordinates":[-0.7915179729,37.8644981384],"type":"Point"}
}