{
  "type": "Feature",
  "properties": {
    "iso:country":"ES",
    "sg:address":"Calle de Ayala, 134",
    "sg:city":"Madrid",
    "sg:orig_category":"M\u00c9dicos: Estomatolog\u00cda",
    "sg:phone":"+34 914 35 03 06",
    "sg:postcode":"28006",
    "sg:province":"Madrid",
    "wof:name":"Dengates, S.r.l.",
    "wof:placetype":"venue"
},
  "geometry": {"coordinates":[-3.6726830006,40.4271621704],"type":"Point"}
}