{
  "type": "Feature",
  "properties": {
    "addr:full":"Carrer de Mare De Deu De Loreto, 70 Palleja Barcelona 08780",
    "addr:housenumber":"70",
    "addr:postcode":"08780",
    "addr:street":"Carrer De Mare De Deu De Loreto",
    "iso:country":"ES",
    "sg:address":"Carrer de Mare De Deu De Loreto, 70",
    "sg:city":"Palleja",
    "sg:orig_category":"Molduras, Junquillos, Listones Y Molduras Perforadas",
    "sg:phone":"+34 936 63 00 95",
    "sg:postcode":"08780",
    "sg:province":"Barcelona",
    "wof:name":"Maldonado Carrasco Antonio",
    "wof:placetype":"venue"
},
  "geometry": {"coordinates":[1.9972980022,41.4253883362],"type":"Point"}
}