{
  "type": "Feature",
  "properties": {
    "addr:full":"Pl Goya, 16 Cerdanyola Valles Barcelona 08290",
    "addr:housenumber":"16",
    "addr:postcode":"08290",
    "addr:street":"Pl Goya;Valles Barcelona",
    "iso:country":"ES",
    "sg:address":"Pl Goya, 16",
    "sg:city":"Cerdanyola Valles",
    "sg:orig_category":"Alquiler De V\u00cddeo",
    "sg:phone":"+34 936 92 01 14",
    "sg:postcode":"08290",
    "sg:province":"Barcelona",
    "wof:name":"Rodriguez Camacho Estefania",
    "wof:placetype":"venue"
},
  "geometry": {"coordinates":[2.1483399868,41.489944458],"type":"Point"}
}