{
  "type": "Feature",
  "properties": {
    "iso:country":"ES",
    "sg:address":"Calle de Alcalde Reig, 6",
    "sg:city":"Valencia",
    "sg:orig_category":"Abogados",
    "sg:phone":"+34 963 95 31 02",
    "sg:postcode":"46006",
    "sg:province":"Valencia",
    "wof:name":"Higuera Lujan Luis Miguel",
    "wof:placetype":"venue"
},
  "geometry": {"coordinates":[-0.3603388965,39.4616241455],"type":"Point"}
}