{
  "type": "Feature",
  "properties": {
    "addr:full":"Avda Isabel De Moctezuma, 15 Caceres C\u00e1ceres 10005",
    "addr:housenumber":"15",
    "addr:postcode":"10005",
    "addr:street":"Avda Isabel De Moctezuma;Ca\u0301Ceres",
    "iso:country":"ES",
    "sg:address":"Avda Isabel De Moctezuma, 15",
    "sg:city":"Caceres",
    "sg:orig_category":"Frutas Y Legumbres Secas (al Por Mayor)",
    "sg:phone":"+34 927 21 54 88",
    "sg:postcode":"10005",
    "sg:province":"C\u00e1ceres",
    "wof:name":"Deseos Caceres S.l.",
    "wof:placetype":"venue"
},
  "geometry": {"coordinates":[-6.3791389465,39.4636993408],"type":"Point"}
}