{
  "type": "Feature",
  "properties": {
    "iso:country":"ES",
    "sg:address":"Bard San Vicente, 20",
    "sg:city":"Alquian",
    "sg:orig_category":"Papeler\u00cdas, Librer\u00cdas",
    "sg:phone":"+34 950 29 73 19",
    "sg:postcode":"04130",
    "sg:province":"Almer\u00eda",
    "wof:name":"Castillo Fernandez Matilde",
    "wof:placetype":"venue"
},
  "geometry": {"coordinates":[-2.3529150486,36.8523406982],"type":"Point"}
}