{
  "type": "Feature",
  "properties": {
    "iso:country":"ES",
    "sg:address":"Plaz Esteve, 2",
    "sg:city":"Jerez De La Frontera",
    "sg:orig_category":"Zapatos (al Por Menor)",
    "sg:phone":"+34 956 34 90 75",
    "sg:postcode":"11402",
    "sg:province":"C\u00e1diz",
    "wof:name":"Herrero Alonso Rosario",
    "wof:placetype":"venue"
},
  "geometry": {"coordinates":[-6.135468483,36.6873931885],"type":"Point"}
}