{
  "type": "Feature",
  "properties": {
    "addr:full":"Pla\u00c7 Pilar, 4 Igualada Barcelona 08700",
    "addr:postcode":"08700",
    "iso:country":"ES",
    "sg:address":"Pla\u00c7 Pilar, 4",
    "sg:city":"Igualada",
    "sg:orig_category":"Bisuter\u00cda, Joyer\u00cda, Relojer\u00cda (al Por Menor)",
    "sg:phone":"+34 938 03 20 10",
    "sg:postcode":"08700",
    "sg:province":"Barcelona",
    "wof:name":"Tribo Sendra Carmina",
    "wof:placetype":"venue"
},
  "geometry": {"coordinates":[1.6183480024,41.5790672302],"type":"Point"}
}