{
  "type": "Feature",
  "properties": {
    "iso:country":"ES",
    "sg:address":"Calle de Lepanto, 1",
    "sg:city":"Bollullos Mitacion",
    "sg:orig_category":"Centros De Educaci\u00d3n Especial",
    "sg:phone":"+34 955 76 55 41",
    "sg:postcode":"41110",
    "sg:province":"Sevilla",
    "wof:name":"Junta De Andalucia",
    "wof:placetype":"venue"
},
  "geometry": {"coordinates":[-6.1340680122,37.3373069763],"type":"Point"}
}