{
  "type": "Feature",
  "properties": {
    "addr:full":"C/ Benlliure, 1 Cerdanyola Valles Barcelona 08290",
    "addr:housenumber":"1",
    "addr:postcode":"08290",
    "addr:street":"C / Benlliure;Valles Barcelona",
    "iso:country":"ES",
    "sg:address":"C/ Benlliure, 1",
    "sg:city":"Cerdanyola Valles",
    "sg:orig_category":"Camiser\u00cda Y Ropa Interior Masculina (al Por Menor)",
    "sg:phone":"+34 935 80 60 35",
    "sg:postcode":"08290",
    "sg:province":"Barcelona",
    "wof:name":"Collado Lizama Antonio Juan",
    "wof:placetype":"venue"
},
  "geometry": {"coordinates":[2.1447980404,41.4894142151],"type":"Point"}
}