{
  "type": "Feature",
  "properties": {
    "iso:country":"ES",
    "sg:address":"Calle de Alberto Aguilera, 27",
    "sg:city":"Madrid",
    "sg:orig_category":"Administradores De Bienes Y Delegados De Comunidades De Propietarios",
    "sg:phone":"+34 915 41 01 08",
    "sg:postcode":"28015",
    "sg:province":"Madrid",
    "wof:name":"Solaf Xxi",
    "wof:placetype":"venue"
},
  "geometry": {"coordinates":[-3.712395668,40.4301681519],"type":"Point"}
}