{
  "type": "Feature",
  "properties": {
    "addr:full":"Calle de Evaristo Valle, 5 Lugones Asturias 33420",
    "addr:housenumber":"5",
    "addr:postcode":"33420",
    "addr:street":"Calle De Evaristo Valle",
    "iso:country":"ES",
    "sg:address":"Calle de Evaristo Valle, 5",
    "sg:city":"Lugones",
    "sg:orig_category":"Partidos Pol\u00cdticos",
    "sg:phone":"+34 985 26 57 02",
    "sg:postcode":"33420",
    "sg:province":"Asturias",
    "wof:name":"Partido Socialista Obrero Espa\u00f1ol",
    "wof:placetype":"venue"
},
  "geometry": {"coordinates":[-5.8066353798,43.3996315002],"type":"Point"}
}