{
  "type": "Feature",
  "properties": {
    "addr:full":"Carrer de Major, 49 Roca Valles Barcelona 08430",
    "addr:housenumber":"49",
    "addr:postcode":"08430",
    "addr:street":"Carrer De Major;Barcelona",
    "iso:country":"ES",
    "sg:address":"Carrer de Major, 49",
    "sg:city":"Roca Valles",
    "sg:orig_category":"Empresas De Carpinter\u00cda Met\u00c1lica",
    "sg:phone":"+34 938 42 20 05",
    "sg:postcode":"08430",
    "sg:province":"Barcelona",
    "wof:name":"Euro-sistemes I Rehabilitacio S.l.",
    "wof:placetype":"venue"
},
  "geometry": {"coordinates":[2.3256509304,41.5887832642],"type":"Point"}
}