{
  "type": "Feature",
  "properties": {
    "addr:full":"Rua Pepe Castro, 64 Barreiro Pontevedra 36214",
    "addr:housenumber":"64",
    "addr:postcode":"36214",
    "addr:street":"Castro",
    "iso:country":"ES",
    "sg:address":"Rua Pepe Castro, 64",
    "sg:city":"Barreiro",
    "sg:orig_category":"Molduras, Junquillos, Listones Y Molduras Perforadas",
    "sg:phone":"+34 986 27 10 47",
    "sg:postcode":"36214",
    "sg:province":"Pontevedra",
    "wof:name":"Gonzalez Roman Fuensanta",
    "wof:placetype":"venue"
},
  "geometry": {"coordinates":[-8.7059106827,42.2124443054],"type":"Point"}
}