{
  "type": "Feature",
  "properties": {
    "addr:full":"Carrer de Doctor Pi I Molist, 39 Barcelona Barcelona 08031",
    "addr:housenumber":"39",
    "addr:postcode":"08031",
    "addr:street":"Carrer De Doctor Pi I Molist",
    "iso:country":"ES",
    "sg:address":"Carrer de Doctor Pi I Molist, 39",
    "sg:city":"Barcelona",
    "sg:orig_category":"Cajas De Ahorro",
    "sg:phone":"+34 933 40 65 62",
    "sg:postcode":"08031",
    "sg:province":"Barcelona",
    "sg:website":"www.lacaixa.es",
    "wof:name":"Caixa D'estalvis I Pensions De Barcelona",
    "wof:placetype":"venue"
},
  "geometry": {"coordinates":[2.1733179092,41.4327468872],"type":"Point"}
}