{
  "type": "Feature",
  "properties": {
    "addr:full":"Calle de Brindis, 2 Granada Granada 18014",
    "addr:housenumber":"2",
    "addr:postcode":"18014",
    "addr:street":"Calle De Brindis",
    "iso:country":"ES",
    "sg:address":"Calle de Brindis, 2",
    "sg:city":"Granada",
    "sg:orig_category":"Art\u00cdculos De Regalo (al Por Menor)",
    "sg:phone":"+34 958 15 62 36",
    "sg:postcode":"18014",
    "sg:province":"Granada",
    "wof:name":"Sanchez Castro Amelia Josefa",
    "wof:placetype":"venue"
},
  "geometry": {"coordinates":[-3.6192471981,37.1966323853],"type":"Point"}
}