{
  "type": "Feature",
  "properties": {
    "iso:country":"ES",
    "sg:address":"Pg Gran Passeig Ronda, 70",
    "sg:city":"Lleida",
    "sg:orig_category":"Bisuter\u00cda, Joyer\u00cda, Relojer\u00cda (al Por Menor)",
    "sg:phone":"+34 973 26 61 76",
    "sg:postcode":"25006",
    "sg:province":"Lleida",
    "wof:name":"Campanera Oronich Fermin Jorge",
    "wof:placetype":"venue"
},
  "geometry": {"coordinates":[0.6136530042,41.6170768738],"type":"Point"}
}