{
  "type": "Feature",
  "properties": {
    "iso:country":"ES",
    "sg:address":"Avda Andres Segovia, 32",
    "sg:city":"Linares",
    "sg:orig_category":"Alimentaci\u00d3n General (al Por Menor)",
    "sg:phone":"+34 953 69 49 02",
    "sg:postcode":"23700",
    "sg:province":"Ja\u00e9n",
    "wof:name":"Alimentacion Checa S.l.",
    "wof:placetype":"venue"
},
  "geometry": {"coordinates":[-3.6386671066,38.0973358154],"type":"Point"}
}