{
  "type": "Feature",
  "properties": {
    "iso:country":"ES",
    "sg:address":"Calle de Artesanos, 9",
    "sg:city":"Ecija",
    "sg:orig_category":"Venta, Colocaci\u00d3n, Reparaci\u00d3n De Parabrisas, Techos Descapotables",
    "sg:phone":"+34 954 83 08 94",
    "sg:postcode":"41400",
    "sg:province":"Sevilla",
    "wof:name":"Gaitan Garrido Francisco Javier",
    "wof:placetype":"venue"
},
  "geometry": {"coordinates":[-5.1015224457,37.4861946106],"type":"Point"}
}