{
  "type": "Feature",
  "properties": {
    "addr:full":"Carr Riu Millars (del), S/n Manises Valencia 46940",
    "addr:housenumber":"/ n",
    "addr:postcode":"46940",
    "addr:street":"Carr Riu Millars Del S",
    "iso:country":"ES",
    "sg:address":"Carr Riu Millars (del), S/n",
    "sg:city":"Manises",
    "sg:orig_category":"Asociaciones Humanitarias, De Cooperaci\u00d3n, De Acci\u00d3n Social",
    "sg:phone":"+34 961 53 31 37",
    "sg:postcode":"46940",
    "sg:province":"Valencia",
    "wof:name":"Asociaciones Para La Lucha Contra Las En",
    "wof:placetype":"venue"
},
  "geometry": {"coordinates":[-0.4503997862,39.4902229309],"type":"Point"}
}