{
  "type": "Feature",
  "properties": {
    "iso:country":"ES",
    "sg:address":"Pla\u00c7 Sant Joan, 18",
    "sg:city":"Lleida",
    "sg:orig_category":"Centros Empresariales",
    "sg:phone":"+34 973 22 49 21",
    "sg:postcode":"25007",
    "sg:province":"Lleida",
    "wof:name":"Femac",
    "wof:placetype":"venue"
},
  "geometry": {"coordinates":[0.6282659769,41.6168136597],"type":"Point"}
}