{
  "type": "Feature",
  "properties": {
    "addr:full":"Pl Espanya (d'), 1 Caseres Tarragona 43787",
    "addr:postcode":"43787",
    "addr:street":"Pl",
    "iso:country":"ES",
    "sg:address":"Pl Espanya (d'), 1",
    "sg:city":"Caseres",
    "sg:orig_category":"Iglesia Cat\u00d3lica",
    "sg:phone":"+34 977 43 19 11",
    "sg:postcode":"43787",
    "sg:province":"Tarragona",
    "wof:name":"Bisbat De Tortosa",
    "wof:placetype":"venue"
},
  "geometry": {"coordinates":[0.2506250143,41.0385894775],"type":"Point"}
}