{
  "type": "Feature",
  "properties": {
    "addr:full":"Carrer de Galceran De Pinos, 26 Sabadell Barcelona 08203",
    "addr:housenumber":"26",
    "addr:postcode":"08203",
    "addr:street":"Carrer De Galceran De Pinos",
    "iso:country":"ES",
    "sg:address":"Carrer de Galceran De Pinos, 26",
    "sg:city":"Sabadell",
    "sg:orig_category":"Agencias Y Asesores De Publicidad",
    "sg:phone":"+34 937 27 16 14",
    "sg:postcode":"08203",
    "sg:province":"Barcelona",
    "sg:website":"www.enfasicmsasi.com",
    "wof:name":"Enfasi Comunicacio Digital",
    "wof:placetype":"venue"
},
  "geometry": {"coordinates":[2.1185340881,41.542804718],"type":"Point"}
}