{
  "type": "Feature",
  "properties": {
    "addr:full":"Avda Alfonso Pe\u00d1a, 55 Santo Domingo De La Calzada La Rioja 26250",
    "addr:housenumber":"55",
    "addr:postcode":"26250",
    "addr:street":"Avda Alfonso Pen\u0303A;Rioja",
    "iso:country":"ES",
    "sg:address":"Avda Alfonso Pe\u00d1a, 55",
    "sg:city":"Santo Domingo De La Calzada",
    "sg:orig_category":"Sindicatos De Trabajadores",
    "sg:phone":"+34 941 34 30 58",
    "sg:postcode":"26250",
    "sg:province":"La Rioja",
    "wof:name":"Union General De Trabajadores De Rioja",
    "wof:placetype":"venue"
},
  "geometry": {"coordinates":[-2.9537820816,42.4343261719],"type":"Point"}
}