{
  "type": "Feature",
  "properties": {
    "iso:country":"ES",
    "sg:address":"Barr San Martin Del Pino, 16",
    "sg:city":"Pe\u00d1acastillo",
    "sg:orig_category":"Farmacias",
    "sg:phone":"+34 942 34 15 05",
    "sg:postcode":"39011",
    "sg:province":"Cantabria",
    "wof:name":"Martinez-vaquero Lopez Bernardo",
    "wof:placetype":"venue"
},
  "geometry": {"coordinates":[-3.8739891052,43.4491386414],"type":"Point"}
}