{
  "type": "Feature",
  "properties": {
    "addr:full":"Barr Hoya (la), 12 Argo\u00f1os Cantabria 39197",
    "addr:postcode":"39197",
    "iso:country":"ES",
    "sg:address":"Barr Hoya (la), 12",
    "sg:city":"Argo\u00f1os",
    "sg:orig_category":"Empresas De Carpinter\u00cda Met\u00c1lica",
    "sg:phone":"+34 942 62 62 93",
    "sg:postcode":"39197",
    "sg:province":"Cantabria",
    "sg:website":"www.parquempresarial.com/dei",
    "wof:name":"Talleres Metalicos Dei S.l.",
    "wof:placetype":"venue"
},
  "geometry": {"coordinates":[-3.4864890575,43.4572067261],"type":"Point"}
}