{
  "type": "Feature",
  "properties": {
    "iso:country":"ES",
    "sg:address":"Plaz Cesar Manrique, 2",
    "sg:city":"Olivos-la Postura",
    "sg:orig_category":"Servicios De Telecomunicaciones",
    "sg:phone":"+34 922 71 15 79",
    "sg:postcode":"38670",
    "sg:province":"Santa Cruz De Tenerife",
    "wof:name":"Teleagua Tenerife S.l.",
    "wof:placetype":"venue"
},
  "geometry": {"coordinates":[-16.724899292,28.1215400696],"type":"Point"}
}