{
  "type": "Feature",
  "properties": {
    "addr:full":"Av Mare De Deu De Bellvitge, 40 Hospitalet Llobregat Barcelona 08907",
    "addr:housenumber":"40",
    "addr:postcode":"08907",
    "addr:street":"Av Mare De Deu De Bellvitge",
    "iso:country":"ES",
    "sg:address":"Av Mare De Deu De Bellvitge, 40",
    "sg:city":"Hospitalet Llobregat",
    "sg:classifiers":[
        {
            "category":"Autos & Motor Vehicles",
            "subcategory":"Automobile Sales",
            "type":"Retail Goods"
        }
    ],
    "sg:phone":"+34 933 35 03 88",
    "sg:postcode":"08907",
    "sg:province":"Barcelona",
    "wof:name":"Su\u00f1e Juan Pedro",
    "wof:placetype":"venue"
},
  "geometry": {"coordinates":[2.1077399254,41.3482208252],"type":"Point"}
}