{
  "type": "Feature",
  "properties": {
    "iso:country":"ES",
    "sg:address":"Carrer de Cardona, 55",
    "sg:city":"Sabadell",
    "sg:orig_category":"Maquinaria Y Herramientas Para Madera, Pvc, Aluminio Y Aperos (fabricaci\u00d3n, Comercio)",
    "sg:phone":"+34 937 27 40 57",
    "sg:postcode":"08203",
    "sg:province":"Barcelona",
    "sg:website":"www.lombartegroup.com",
    "wof:name":"Lombarte Machinery S.l.",
    "wof:placetype":"venue"
},
  "geometry": {"coordinates":[2.1203200817,41.5444946289],"type":"Point"}
}