{
  "type": "Feature",
  "properties": {
    "addr:full":"Calle de Fernandez De Oviedo, S/n Malaga M\u00e1laga 29006",
    "addr:housenumber":"s / n",
    "addr:postcode":"29006",
    "addr:street":"Calle De Fernandez De Oviedo;Ma\u0301Laga",
    "iso:country":"ES",
    "sg:address":"Calle de Fernandez De Oviedo, S/n",
    "sg:city":"Malaga",
    "sg:orig_category":"Transportes Por Carretera: Lotes Completos, Mercanc\u00cdas Diversas",
    "sg:phone":"+34 952 36 32 94",
    "sg:postcode":"29006",
    "sg:province":"M\u00e1laga",
    "wof:name":"Los Ku\u00f1ados E Hijos S.l.",
    "wof:placetype":"venue"
},
  "geometry": {"coordinates":[-4.4687180519,36.7018470764],"type":"Point"}
}