{
  "type": "Feature",
  "properties": {
    "iso:country":"ES",
    "sg:address":"C/ Ramon Cosp, 12",
    "sg:city":"Puigcerda",
    "sg:orig_category":"Bisuter\u00cda, Joyer\u00cda, Relojer\u00cda (al Por Menor)",
    "sg:phone":"+34 972 88 02 68",
    "sg:postcode":"17520",
    "sg:province":"Girona",
    "wof:name":"Santana Vega Andres",
    "wof:placetype":"venue"
},
  "geometry": {"coordinates":[1.9276920557,42.4319534302],"type":"Point"}
}