{
  "type": "Feature",
  "properties": {
    "addr:full":"Calle de Ajustadores, 5 Chiclana De La Frontera C\u00e1diz 11130",
    "addr:housenumber":"5",
    "addr:postcode":"11130",
    "addr:street":"Calle De Ajustadores",
    "iso:country":"ES",
    "sg:address":"Calle de Ajustadores, 5",
    "sg:city":"Chiclana De La Frontera",
    "sg:orig_category":"Electricidad: Instaladores",
    "sg:phone":"+34 956 53 57 68",
    "sg:postcode":"11130",
    "sg:province":"C\u00e1diz",
    "wof:name":"Electrificaciones Bahia S.%.",
    "wof:placetype":"venue"
},
  "geometry": {"coordinates":[-6.1507158279,36.4260635376],"type":"Point"}
}