{
  "type": "Feature",
  "properties": {
    "addr:full":"Carrer de Armanya, 4 Tarragona Tarragona 43004",
    "addr:housenumber":"4",
    "addr:postcode":"43004",
    "addr:street":"Carrer De Armanya",
    "iso:country":"ES",
    "sg:address":"Carrer de Armanya, 4",
    "sg:city":"Tarragona",
    "sg:orig_category":"Agencias De Viajes",
    "sg:phone":"+34 977 24 02 20",
    "sg:postcode":"43004",
    "sg:province":"Tarragona",
    "sg:website":"www.viajeseroski.es",
    "wof:name":"Viajes Eroski S.a.",
    "wof:placetype":"venue"
},
  "geometry": {"coordinates":[1.2521539927,41.1146202087],"type":"Point"}
}