{
  "type": "Feature",
  "properties": {
    "iso:country":"ES",
    "sg:address":"Calle de Coimbra, 1",
    "sg:city":"Zaragoza",
    "sg:orig_category":"Ense\u00d1anza, Formaci\u00d3n Profesional: Aprendizaje",
    "sg:phone":"+34 976 59 71 83",
    "sg:postcode":"50008",
    "sg:province":"Zaragoza",
    "wof:name":"Delegacion Especial De Economia Y Hacienda De Zaragoza",
    "wof:placetype":"venue"
},
  "geometry": {"coordinates":[-0.8757759929,41.6484069824],"type":"Point"}
}