{
  "type": "Feature",
  "properties": {
    "addr:full":"Avda Torre Minguez, S/n Santiago Ribera Murcia 30720",
    "addr:housenumber":"s / n",
    "addr:postcode":"30720",
    "addr:street":"Avda Torre Minguez",
    "iso:country":"ES",
    "sg:address":"Avda Torre Minguez, S/n",
    "sg:city":"Santiago Ribera",
    "sg:orig_category":"Supermercados Y Hipermercados",
    "sg:phone":"+34 968 33 65 09",
    "sg:postcode":"30720",
    "sg:province":"Murcia",
    "wof:name":"Supermercados Pardo S.l.",
    "wof:placetype":"venue"
},
  "geometry": {"coordinates":[-0.8069189787,37.8014183044],"type":"Point"}
}