{
  "type": "Feature",
  "properties": {
    "iso:country":"ES",
    "sg:address":"Calle de Camaron De La Isla, 15",
    "sg:city":"Algeciras",
    "sg:orig_category":"Molduras, Junquillos, Listones Y Molduras Perforadas",
    "sg:phone":"+34 956 60 46 67",
    "sg:postcode":"11207",
    "sg:province":"C\u00e1diz",
    "wof:name":"Godoy Jara Manuel",
    "wof:placetype":"venue"
},
  "geometry": {"coordinates":[-5.4472699165,36.1139183044],"type":"Point"}
}