{
  "type": "Feature",
  "properties": {
    "addr:full":"Av Catalunya, 33 Sant Valeria Barcelona 08185",
    "addr:housenumber":"33",
    "addr:postcode":"08185",
    "addr:street":"Av Catalunya",
    "iso:country":"ES",
    "sg:address":"Av Catalunya, 33",
    "sg:city":"Sant Valeria",
    "sg:orig_category":"Platos Preparados Refrigerados (fabricaci\u00d3n, Al Por Mayor)",
    "sg:phone":"+34 938 43 76 00",
    "sg:postcode":"08185",
    "sg:province":"Barcelona",
    "wof:name":"Agundez Andres Jesus Pedro",
    "wof:placetype":"venue"
},
  "geometry": {"coordinates":[2.1699187756,41.3879165649],"type":"Point"}
}