{
  "type": "Feature",
  "properties": {
    "addr:full":"Calle de Mayor, 63 Torreaguera Murcia 30579",
    "addr:housenumber":"63",
    "addr:postcode":"30579",
    "addr:street":"Calle De Mayor",
    "iso:country":"ES",
    "sg:address":"Calle de Mayor, 63",
    "sg:city":"Torreaguera",
    "sg:orig_category":"Promotores Constructores",
    "sg:phone":"+34 968 87 36 76",
    "sg:postcode":"30579",
    "sg:province":"Murcia",
    "wof:name":"Promociones Torreaguera S.l.",
    "wof:placetype":"venue"
},
  "geometry": {"coordinates":[-1.0518740416,37.9835624695],"type":"Point"}
}