{
  "type": "Feature",
  "properties": {
    "addr:full":"Calle de Avila, 2 San Fernando De Henares Madrid 28830",
    "addr:housenumber":"2",
    "addr:postcode":"28830",
    "addr:street":"Calle De Avila",
    "iso:country":"ES",
    "sg:address":"Calle de Avila, 2",
    "sg:city":"San Fernando De Henares",
    "sg:orig_category":"Promotores Constructores",
    "sg:phone":"+34 917 65 27 61",
    "sg:postcode":"28830",
    "sg:province":"Madrid",
    "wof:name":"Cervantes Martinez S.l.",
    "wof:placetype":"venue"
},
  "geometry": {"coordinates":[-3.5297875404,40.4306259155],"type":"Point"}
}