{
  "type": "Feature",
  "properties": {
    "iso:country":"ES",
    "sg:address":"Avda Castilla, 32",
    "sg:city":"Aranda Duero",
    "sg:orig_category":"Electrodom\u00c9sticos (al Por Menor)",
    "sg:phone":"+34 947 50 64 06",
    "sg:postcode":"09400",
    "sg:province":"Burgos",
    "wof:name":"Camarero Benito Juan Francisco",
    "wof:placetype":"venue"
},
  "geometry": {"coordinates":[-3.6911759377,41.6671295166],"type":"Point"}
}