{
  "type": "Feature",
  "properties": {
    "addr:full":"Avda Santa Eugenia, 14 Madrid Madrid 28031",
    "addr:housenumber":"14",
    "addr:postcode":"madrid;28031",
    "addr:street":"Avda Santa Eugenia",
    "iso:country":"ES",
    "sg:address":"Avda Santa Eugenia, 14",
    "sg:city":"Madrid",
    "sg:orig_category":"Cristaler\u00cdas",
    "sg:phone":"+34 913 31 84 30",
    "sg:postcode":"28031",
    "sg:province":"Madrid",
    "wof:name":"Cristalerias Meneses S.l.",
    "wof:placetype":"venue"
},
  "geometry": {"coordinates":[-3.6121110916,40.3847732544],"type":"Point"}
}