{
  "type": "Feature",
  "properties": {
    "addr:full":"Carrer de Andorra, 15 Hospitalet Llobregat Barcelona 08906",
    "addr:housenumber":"15",
    "addr:postcode":"08906",
    "addr:street":"Carrer De Andorra",
    "iso:country":"ES",
    "sg:address":"Carrer de Andorra, 15",
    "sg:city":"Hospitalet Llobregat",
    "sg:orig_category":"Peluquer\u00cdas, Peluquer\u00cda Mixta",
    "sg:phone":"+34 934 38 79 84",
    "sg:postcode":"08906",
    "sg:province":"Barcelona",
    "wof:name":"Rozas Marco Montserrat",
    "wof:placetype":"venue"
},
  "geometry": {"coordinates":[2.1001050472,41.3694381714],"type":"Point"}
}