{
  "type": "Feature",
  "properties": {
    "iso:country":"ES",
    "sg:address":"Avda El Ferial, 17",
    "sg:city":"Benavente",
    "sg:orig_category":"Albergues",
    "sg:phone":"+34 980 63 10 31",
    "sg:postcode":"49600",
    "sg:province":"Zamora",
    "wof:name":"Hostal Avenida",
    "wof:placetype":"venue"
},
  "geometry": {"coordinates":[-5.6743550301,42.0017814636],"type":"Point"}
}