{
  "type": "Feature",
  "properties": {
    "addr:full":"Av M. Celayeta, 62 Iru\u00f1a Navarra 31014",
    "addr:housenumber":"62",
    "addr:postcode":"31014",
    "addr:street":"Av M. Celayeta",
    "iso:country":"ES",
    "sg:address":"Av M. Celayeta, 62",
    "sg:city":"Iru\u00f1a",
    "sg:orig_category":"Muebles, Minoristas",
    "sg:phone":"+34 948 12 57 75",
    "sg:postcode":"31014",
    "sg:province":"Navarra",
    "wof:name":"Muebles Don Marcelo",
    "wof:placetype":"venue"
},
  "geometry": {"coordinates":[-1.6437540054,42.81275177],"type":"Point"}
}