{
  "type": "Feature",
  "properties": {
    "addr:full":"Avda Joaquin Costa, 26 Alcampell Huesca 22560",
    "addr:housenumber":"26",
    "addr:postcode":"22560",
    "addr:street":"Avda Joaquin Costa",
    "iso:country":"ES",
    "sg:address":"Avda Joaquin Costa, 26",
    "sg:city":"Alcampell",
    "sg:orig_category":"Carnicer\u00cdas, Carnicer\u00cdas",
    "sg:phone":"+34 974 42 09 58",
    "sg:postcode":"22560",
    "sg:province":"Huesca",
    "wof:name":"Casa Ramonet De Sidro S.l.",
    "wof:placetype":"venue"
},
  "geometry": {"coordinates":[0.4362609982,41.9064903259],"type":"Point"}
}