{
  "type": "Feature",
  "properties": {
    "addr:full":"Calle de Eduardo Garcia De Enterria, 16 Potes Cantabria 39570",
    "addr:housenumber":"16",
    "addr:postcode":"39570",
    "addr:street":"Calle De Eduardo Garcia De Enterria",
    "iso:country":"ES",
    "sg:address":"Calle de Eduardo Garcia De Enterria, 16",
    "sg:city":"Potes",
    "sg:orig_category":"Panader\u00cdas, Panader\u00cdas",
    "sg:phone":"+34 942 73 03 73",
    "sg:postcode":"39570",
    "sg:province":"Cantabria",
    "wof:name":"Lede\u00f1a De La Torre Carmen",
    "wof:placetype":"venue"
},
  "geometry": {"coordinates":[-4.626625061,43.1546287537],"type":"Point"}
}