{
  "type": "Feature",
  "properties": {
    "addr:full":"Calle de Escuelas (las), S/n Quintanilla Agua Burgos 09347",
    "addr:postcode":"09347",
    "addr:street":"Calle De Escuelas Las S / N Quintanilla",
    "iso:country":"ES",
    "sg:address":"Calle de Escuelas (las), S/n",
    "sg:city":"Quintanilla Agua",
    "sg:orig_category":"Farmacias",
    "sg:phone":"+34 947 17 45 31",
    "sg:postcode":"09347",
    "sg:province":"Burgos",
    "wof:name":"Marijuan Masa Rosario",
    "wof:placetype":"venue"
},
  "geometry": {"coordinates":[-3.6049189568,42.029460907],"type":"Point"}
}