{
  "type": "Feature",
  "properties": {
    "iso:country":"ES",
    "sg:address":"Calle de Angel Bruna, 18",
    "sg:city":"Cartagena",
    "sg:orig_category":"M\u00c9dicos: Anatom\u00cda Patol\u00d3gica Y Citolog\u00cda",
    "sg:phone":"+34 968 50 04 77",
    "sg:postcode":"30203",
    "sg:province":"Murcia",
    "wof:name":"Blasco Mu\u00f1oz Pedro Damian",
    "wof:placetype":"venue"
},
  "geometry": {"coordinates":[-0.9847490191,37.6075592041],"type":"Point"}
}