{
  "type": "Feature",
  "properties": {
    "addr:full":"Calle de Villa (la), 12 Agoncillo La Rioja 26509",
    "addr:housenumber":"12",
    "addr:postcode":"26509",
    "addr:street":"Calle De Villa La;Rioja",
    "iso:country":"ES",
    "sg:address":"Calle de Villa (la), 12",
    "sg:city":"Agoncillo",
    "sg:orig_category":"Asociaciones, Organismos Culturales Y Socioeducativos",
    "sg:phone":"+34 941 43 72 82",
    "sg:postcode":"26509",
    "sg:province":"La Rioja",
    "wof:name":"Asociacion De La Tercera Edad Jubilados Y Pensionista De Agoncillo",
    "wof:placetype":"venue"
},
  "geometry": {"coordinates":[-2.2902181149,42.4460411072],"type":"Point"}
}