{
  "type": "Feature",
  "properties": {
    "addr:full":"Calle de Imagen, 2 Sevilla Sevilla 41003",
    "addr:housenumber":"2",
    "addr:postcode":"41003",
    "addr:street":"Calle De Imagen",
    "iso:country":"ES",
    "sg:address":"Calle de Imagen, 2",
    "sg:city":"Sevilla",
    "sg:orig_category":"Cajas De Ahorro",
    "sg:phone":"+34 954 21 48 65",
    "sg:postcode":"41003",
    "sg:province":"Sevilla",
    "wof:name":"Caja San Fernando De Sevilla Y Jerez",
    "wof:placetype":"venue"
},
  "geometry": {"coordinates":[-5.9900012016,37.3926086426],"type":"Point"}
}