{
  "type": "Feature",
  "properties": {
    "addr:full":"Rua Vilar (do), 7 Santiago De Compostela La Coru\u00f1a 15705",
    "addr:housenumber":"7",
    "addr:postcode":"15705",
    "addr:street":"Rua Vilar Do;Corun\u0303A",
    "iso:country":"ES",
    "sg:address":"Rua Vilar (do), 7",
    "sg:city":"Santiago De Compostela",
    "sg:orig_category":"Empresarios",
    "sg:phone":"+34 981 55 23 04",
    "sg:postcode":"15705",
    "sg:province":"La Coru\u00f1a",
    "wof:name":"Fundacion Gonzalo Torrente Ballester",
    "wof:placetype":"venue"
},
  "geometry": {"coordinates":[-8.5441093445,42.8794975281],"type":"Point"}
}