{
  "type": "Feature",
  "properties": {
    "iso:country":"ES",
    "sg:address":"Calle de Arroyo Belincoso, S/n",
    "sg:city":"Madrid",
    "sg:orig_category":"Empresas De Limpieza",
    "sg:phone":"+34 914 30 98 04",
    "sg:postcode":"28030",
    "sg:province":"Madrid",
    "wof:name":"Sufi S.a.",
    "wof:placetype":"venue"
},
  "geometry": {"coordinates":[-3.6524658203,40.4103088379],"type":"Point"}
}