{
  "type": "Feature",
  "properties": {
    "addr:full":"Ugaldeguren Kalea, 1 Derio Vizcaya 48160",
    "addr:housenumber":"1",
    "addr:postcode":"48160",
    "addr:street":"Ugaldeguren Kalea",
    "iso:country":"ES",
    "sg:address":"Ugaldeguren Kalea, 1",
    "sg:city":"Derio",
    "sg:orig_category":"Fabricaci\u00d3n De Motores El\u00c9ctricos",
    "sg:phone":"+34 944 54 41 78",
    "sg:postcode":"48160",
    "sg:province":"Vizcaya",
    "wof:name":"Comercial Del Motor S. A.",
    "wof:placetype":"venue"
},
  "geometry": {"coordinates":[-2.8869380951,43.2908973694],"type":"Point"}
}