{
  "type": "Feature",
  "properties": {
    "iso:country":"ES",
    "sg:address":"Carrer de Major De Sarria, 154",
    "sg:city":"Barcelona",
    "sg:orig_category":"Doctores En Medicina",
    "sg:phone":"+34 932 04 41 93",
    "sg:postcode":"08017",
    "sg:province":"Barcelona",
    "wof:name":"Udaeta Valentin Francisco Javier De",
    "wof:placetype":"venue"
},
  "geometry": {"coordinates":[2.1205229759,41.4009933472],"type":"Point"}
}