{
  "type": "Feature",
  "properties": {
    "addr:full":"Avda Manolete, 19 Cordoba C\u00f3rdoba 14005",
    "addr:housenumber":"19",
    "addr:postcode":"14005",
    "addr:street":"Avda Manolete;Co\u0301Rdoba",
    "iso:country":"ES",
    "sg:address":"Avda Manolete, 19",
    "sg:city":"Cordoba",
    "sg:orig_category":"Cajas Para Embalar",
    "sg:phone":"+34 957 23 23 00",
    "sg:postcode":"14005",
    "sg:province":"C\u00f3rdoba",
    "wof:name":"Caja Rural De Cordoba",
    "wof:placetype":"venue"
},
  "geometry": {"coordinates":[-4.7980999947,37.8788375854],"type":"Point"}
}