{
  "type": "Feature",
  "properties": {
    "addr:full":"Carr Major, 67 Sant Joan Islas Baleares 07240",
    "addr:housenumber":"67",
    "addr:postcode":"07240",
    "addr:street":"Carr Major",
    "iso:country":"ES",
    "sg:address":"Carr Major, 67",
    "sg:city":"Sant Joan",
    "sg:orig_category":"Carnes De Carnicer\u00cda (al Por Mayor)",
    "sg:phone":"+34 971 52 63 31",
    "sg:postcode":"07240",
    "sg:province":"Islas Baleares",
    "wof:name":"Dalmau Nigorra Antonia",
    "wof:placetype":"venue"
},
  "geometry": {"coordinates":[3.0390019417,39.5964813232],"type":"Point"}
}