{
  "type": "Feature",
  "properties": {
    "addr:full":"Carr Orient, 10 Palamos Girona 17230",
    "addr:housenumber":"10",
    "addr:postcode":"17230",
    "addr:street":"Carr Orient",
    "iso:country":"ES",
    "sg:address":"Carr Orient, 10",
    "sg:city":"Palamos",
    "sg:orig_category":"Supermercados Y Hipermercados",
    "sg:phone":"+34 972 31 53 22",
    "sg:postcode":"17230",
    "sg:province":"Girona",
    "wof:name":"Sabat Gracia Eleuterio",
    "wof:placetype":"venue"
},
  "geometry": {"coordinates":[3.1277410984,41.8481140137],"type":"Point"}
}