{
  "type": "Feature",
  "properties": {
    "addr:full":"Calle de Colon, 40 Denia Alicante 03700",
    "addr:housenumber":"40",
    "addr:postcode":"03700",
    "addr:street":"Calle De Colon",
    "iso:country":"ES",
    "sg:address":"Calle de Colon, 40",
    "sg:city":"Denia",
    "sg:orig_category":"Edici\u00d3n De Diarios, Revistas, Boletines",
    "sg:phone":"+34 966 42 73 36",
    "sg:postcode":"03700",
    "sg:province":"Alicante",
    "wof:name":"Editorial Prensa Iberica S.a.",
    "wof:placetype":"venue"
},
  "geometry": {"coordinates":[0.1080294028,38.8395042419],"type":"Point"}
}