{
  "type": "Feature",
  "properties": {
    "iso:country":"ES",
    "sg:address":"Avda Juveria, 50",
    "sg:city":"Gijon",
    "sg:orig_category":"Artes Gr\u00c1ficas, Artes Pl\u00c1sticas (curso)",
    "sg:phone":"+34 985 30 05 87",
    "sg:postcode":"33211",
    "sg:province":"Asturias",
    "wof:name":"De La Fuente Martinez Enrique",
    "wof:placetype":"venue"
},
  "geometry": {"coordinates":[-5.7175040245,43.5337524414],"type":"Point"}
}