{
  "type": "Feature",
  "properties": {
    "addr:full":"Calle de Constitucion, 1 Valladolid Valladolid 47001",
    "addr:housenumber":"1",
    "addr:postcode":"47001",
    "addr:street":"Calle De Constitucion",
    "iso:country":"ES",
    "sg:address":"Calle de Constitucion, 1",
    "sg:city":"Valladolid",
    "sg:orig_category":"Moquetas, Alfombras (al Por Menor)",
    "sg:phone":"+34 983 35 61 82",
    "sg:postcode":"47001",
    "sg:province":"Valladolid",
    "wof:name":"Carmelo Diaz Y Compa\u00f1ia S. L.",
    "wof:placetype":"venue"
},
  "geometry": {"coordinates":[-4.7283706665,41.6509666443],"type":"Point"}
}