{
  "type": "Feature",
  "properties": {
    "iso:country":"ES",
    "sg:address":"Calle de Pedro Bustos (don), 40",
    "sg:city":"Socuellamos",
    "sg:orig_category":"Asociaciones Y Clubs Deportivos",
    "sg:phone":"+34 926 53 11 67",
    "sg:postcode":"13630",
    "sg:province":"Ciudad Real",
    "wof:name":"Alarcon Medina Casiano",
    "wof:placetype":"venue"
},
  "geometry": {"coordinates":[-2.7908153534,39.289276123],"type":"Point"}
}