{
  "type": "Feature",
  "properties": {
    "addr:full":"Carrer de Vall, 5 Terrassa Barcelona 08221",
    "addr:housenumber":"5",
    "addr:postcode":"08221",
    "addr:street":"Carrer De Vall",
    "iso:country":"ES",
    "sg:address":"Carrer de Vall, 5",
    "sg:city":"Terrassa",
    "sg:orig_category":"Arquitectos",
    "sg:phone":"+34 937 88 39 71",
    "sg:postcode":"08221",
    "sg:province":"Barcelona",
    "wof:name":"Satorras Marti Lluis",
    "wof:placetype":"venue"
},
  "geometry": {"coordinates":[2.011578083,41.5610542297],"type":"Point"}
}