{
  "type": "Feature",
  "properties": {
    "addr:full":"Calle de Francisco Pizarro, 14 Badajoz Badajoz 06001",
    "addr:housenumber":"14",
    "addr:postcode":"06001",
    "addr:street":"Calle De Francisco Pizarro",
    "iso:country":"ES",
    "sg:address":"Calle de Francisco Pizarro, 14",
    "sg:city":"Badajoz",
    "sg:orig_category":"Loter\u00cda Y T\u00d3mbola",
    "sg:phone":"+34 924 22 00 55",
    "sg:postcode":"06001",
    "sg:province":"Badajoz",
    "wof:name":"Guerrero Ramos Alberto",
    "wof:placetype":"venue"
},
  "geometry": {"coordinates":[-6.9714803696,38.879901886],"type":"Point"}
}