{
  "type": "Feature",
  "properties": {
    "iso:country":"ES",
    "sg:address":"Sancho Ramirez, 31",
    "sg:city":"Iru\u00f1a",
    "sg:orig_category":"Edici\u00d3n De Diarios, Revistas, Boletines",
    "sg:phone":"+34 948 27 96 59",
    "sg:postcode":"31008",
    "sg:province":"Navarra",
    "sg:website":"www.edebe.com",
    "wof:name":"Sociedad Salesiana San Francisco De Sales. Ediciones Edebe",
    "wof:placetype":"venue"
},
  "geometry": {"coordinates":[-1.66624403,42.8082962036],"type":"Point"}
}