{
  "type": "Feature",
  "properties": {
    "iso:country":"ES",
    "sg:address":"Calle de Aquiles, S/n",
    "sg:city":"Torrejon Ardoz",
    "sg:orig_category":"Asociaciones, Organismos Culturales Y Socioeducativos",
    "sg:phone":"+34 916 77 68 15",
    "sg:postcode":"28850",
    "sg:province":"Madrid",
    "wof:name":"Casa Andalucia",
    "wof:placetype":"venue"
},
  "geometry": {"coordinates":[-3.4744269848,40.4500999451],"type":"Point"}
}