{
  "type": "Feature",
  "properties": {
    "addr:full":"Carr Castellar, 42 Casc Urba Girona 17490",
    "addr:housenumber":"42;urba",
    "addr:postcode":"17490",
    "addr:street":"Carr Castellar",
    "iso:country":"ES",
    "sg:address":"Carr Castellar, 42",
    "sg:city":"Casc Urba",
    "sg:orig_category":"Inmobiliaria (agencias)",
    "sg:phone":"+34 972 38 00 80",
    "sg:postcode":"17490",
    "sg:province":"Girona",
    "sg:website":"www.fabrega-goertzen.com",
    "wof:name":"Fabrega-goertzen S.l.",
    "wof:placetype":"venue"
},
  "geometry": {"coordinates":[3.1481759548,42.3640785217],"type":"Point"}
}