{
  "type": "Feature",
  "properties": {
    "iso:country":"ES",
    "sg:address":"L Poligono, S/n",
    "sg:city":"Soria",
    "sg:orig_category":"Maquinaria Para Industrias Diversas",
    "sg:phone":"+34 975 22 09 32",
    "sg:postcode":"42005",
    "sg:province":"Soria",
    "wof:name":"Garcia Gonzalo Clemente",
    "wof:placetype":"venue"
},
  "geometry": {"coordinates":[-2.4691669941,41.7646598816],"type":"Point"}
}