{
  "type": "Feature",
  "properties": {
    "iso:country":"ES",
    "sg:address":"Calle de B(campollano), 4",
    "sg:city":"Albacete",
    "sg:orig_category":"Oficinas: Suministros Para (fabricaci\u00d3n, Al Por Mayor)",
    "sg:phone":"+34 967 21 64 00",
    "sg:postcode":"02...",
    "sg:province":"Albacete",
    "sg:website":"www.adimpo.es",
    "wof:name":"Adimpo S.a.",
    "wof:placetype":"venue"
},
  "geometry": {"coordinates":[-1.8600701094,38.9976501465],"type":"Point"}
}