{
  "type": "Feature",
  "properties": {
    "iso:country":"ES",
    "sg:address":"Calle de Linares, 1",
    "sg:city":"Velez-malaga",
    "sg:orig_category":"Quincaller\u00cda (al Por Menor)",
    "sg:phone":"+34 952 55 87 30",
    "sg:postcode":"29700",
    "sg:province":"M\u00e1laga",
    "wof:name":"Gonzalez Roa Maria Isabel De Africa",
    "wof:placetype":"venue"
},
  "geometry": {"coordinates":[-4.0993590355,36.7732429504],"type":"Point"}
}