{
  "type": "Feature",
  "properties": {
    "iso:country":"ES",
    "sg:address":"Calle de General Garcia Escamez, 230",
    "sg:city":"Arrecife",
    "sg:orig_category":"Bazares, Art\u00cdculos De Limpieza Y De Cocina (al Por Menor)",
    "sg:phone":"+34 928 80 54 17",
    "sg:postcode":"35500",
    "sg:province":"Las Palmas",
    "wof:name":"Tiendas Especializadas De Canarias S.l.",
    "wof:placetype":"venue"
},
  "geometry": {"coordinates":[-13.5569601059,28.965637207],"type":"Point"}
}