{
  "type": "Feature",
  "properties": {
    "addr:full":"Calle de Navalcarnero, 8 Alcorcon Madrid 28921",
    "addr:housenumber":"8",
    "addr:postcode":"28921",
    "addr:street":"Calle De Navalcarnero",
    "iso:country":"ES",
    "sg:address":"Calle de Navalcarnero, 8",
    "sg:city":"Alcorcon",
    "sg:orig_category":"Farmacias",
    "sg:phone":"+34 916 10 10 32",
    "sg:postcode":"28921",
    "sg:province":"Madrid",
    "wof:name":"Villar Fernandez Francisca",
    "wof:placetype":"venue"
},
  "geometry": {"coordinates":[-3.830673933,40.3500289917],"type":"Point"}
}