{
  "type": "Feature",
  "properties": {
    "addr:full":"Calle de Libertad, 14 Bejar Salamanca 37700",
    "addr:housenumber":"14",
    "addr:postcode":"37700",
    "addr:street":"Calle De Libertad",
    "iso:country":"ES",
    "sg:address":"Calle de Libertad, 14",
    "sg:city":"Bejar",
    "sg:orig_category":"Asesor\u00cda Fiscal Y Jur\u00cddica",
    "sg:phone":"+34 923 40 11 93",
    "sg:postcode":"37700",
    "sg:province":"Salamanca",
    "wof:name":"Brito Gonzalez Felipe",
    "wof:placetype":"venue"
},
  "geometry": {"coordinates":[-5.763133049,40.3860168457],"type":"Point"}
}