{
  "type": "Feature",
  "properties": {
    "addr:full":"Calle de San Roque, 2 Burgos Burgos 09006",
    "addr:housenumber":"2",
    "addr:postcode":"09006",
    "addr:street":"Calle De San Roque",
    "iso:country":"ES",
    "sg:address":"Calle de San Roque, 2",
    "sg:city":"Burgos",
    "sg:orig_category":"M\u00c1quinas De Jardiner\u00cda",
    "sg:phone":"+34 947 22 41 51",
    "sg:postcode":"09006",
    "sg:province":"Burgos",
    "wof:name":"Eurocampo Verde S.l.",
    "wof:placetype":"venue"
},
  "geometry": {"coordinates":[-3.6804978848,42.3483543396],"type":"Point"}
}