{
  "type": "Feature",
  "properties": {
    "addr:full":"Avgd Pais Valencia, 57 Algemesi Valencia 46680",
    "addr:housenumber":"57",
    "addr:postcode":"46680",
    "addr:street":"Valencia",
    "iso:country":"ES",
    "sg:address":"Avgd Pais Valencia, 57",
    "sg:city":"Algemesi",
    "sg:orig_category":"Reparaciones Y Remolcado De Veh\u00cdculos",
    "sg:phone":"+34 962 48 34 90",
    "sg:postcode":"46680",
    "sg:province":"Valencia",
    "wof:name":"Colomer Lasheras Carlos",
    "wof:placetype":"venue"
},
  "geometry": {"coordinates":[-0.4353710115,39.1940155029],"type":"Point"}
}