{
  "type": "Feature",
  "properties": {
    "addr:full":"Calle de Real, 10 Rozas De Madrid Madrid 28230",
    "addr:housenumber":"10",
    "addr:postcode":"28230",
    "addr:street":"Calle De Real",
    "iso:country":"ES",
    "sg:address":"Calle de Real, 10",
    "sg:city":"Rozas De Madrid",
    "sg:orig_category":"Empresas De Desmonte",
    "sg:phone":"+34 917 10 43 93",
    "sg:postcode":"28230",
    "sg:province":"Madrid",
    "wof:name":"Excavaciones Y Hormigones Esm S.l.",
    "wof:placetype":"venue"
},
  "geometry": {"coordinates":[-3.8735918999,40.4922065735],"type":"Point"}
}