{
  "type": "Feature",
  "properties": {
    "addr:full":"Rua Amizade, 3 Torre Pontevedra 36613",
    "addr:housenumber":"3",
    "addr:postcode":"36613",
    "addr:street":"Rua Amizade",
    "iso:country":"ES",
    "sg:address":"Rua Amizade, 3",
    "sg:city":"Torre",
    "sg:orig_category":"Ense\u00d1anza, Formaci\u00d3n Profesional: Aprendizaje",
    "sg:phone":"+34 986 50 43 31",
    "sg:postcode":"36613",
    "sg:province":"Pontevedra",
    "wof:name":"Concello De Vilagarcia De Arousa",
    "wof:placetype":"venue"
},
  "geometry": {"coordinates":[-8.7695436478,42.6105308533],"type":"Point"}
}