{
  "type": "Feature",
  "properties": {
    "iso:country":"ES",
    "sg:address":"Av Corts Catalanes, 3",
    "sg:city":"S. Adria Besos",
    "sg:orig_category":"Centros De Coordinaci\u00d3n",
    "sg:phone":"+34 933 81 15 66",
    "sg:postcode":"08930",
    "sg:province":"Barcelona",
    "wof:name":"Asociacion Catalana De Conductores Minusvalidos",
    "wof:placetype":"venue"
},
  "geometry": {"coordinates":[2.212600708,41.423034668],"type":"Point"}
}