{
  "type": "Feature",
  "properties": {
    "iso:country":"ES",
    "sg:address":"Avda Victoria, 80",
    "sg:city":"Madrid",
    "sg:orig_category":"Inform\u00c1tica Equipo Y Programas (al Por Mayor)",
    "sg:phone":"+34 917 08 07 63",
    "sg:postcode":"28023",
    "sg:province":"Madrid",
    "sg:website":"www.unitio.com",
    "wof:name":"Unitio Plus S.l.",
    "wof:placetype":"venue"
},
  "geometry": {"coordinates":[-3.827354908,40.4716529846],"type":"Point"}
}