{
  "type": "Feature",
  "properties": {
    "iso:country":"ES",
    "sg:address":"Urb. Palmeras, 2",
    "sg:city":"Villanueva Vera",
    "sg:orig_category":"Quincaller\u00cda (al Por Menor)",
    "sg:phone":"+34 927 56 70 72",
    "sg:postcode":"10470",
    "sg:province":"C\u00e1ceres",
    "wof:name":"Tornero Jimenez Felipe",
    "wof:placetype":"venue"
},
  "geometry": {"coordinates":[-5.4627428055,40.1311225891],"type":"Point"}
}