{
  "type": "Feature",
  "properties": {
    "iso:country":"ES",
    "sg:address":"Zarugalde Kalea, 25",
    "sg:city":"Arrasate",
    "sg:orig_category":"Muebles, Minoristas",
    "sg:phone":"+34 943 77 18 35",
    "sg:postcode":"20500",
    "sg:province":"Guip\u00f9zcoa",
    "wof:name":"Valor Valor Ana Jose",
    "wof:placetype":"venue"
},
  "geometry": {"coordinates":[-2.493999958,43.0653152466],"type":"Point"}
}