{
  "type": "Feature",
  "properties": {
    "iso:country":"ES",
    "sg:address":"Calle de San Juan, 9",
    "sg:city":"Puerto Cruz",
    "sg:orig_category":"Geolog\u00cda Y Geof\u00cdsica",
    "sg:phone":"+34 922 36 83 03",
    "sg:postcode":"38400",
    "sg:province":"Santa Cruz De Tenerife",
    "wof:name":"Bravo Bethercourt Lourdes",
    "wof:placetype":"venue"
},
  "geometry": {"coordinates":[-16.5498924255,28.4167613983],"type":"Point"}
}