{
  "type": "Feature",
  "properties": {
    "addr:full":"Calle de Espino (del), 13 Camarma Esteruelas Madrid 28816",
    "addr:housenumber":"13",
    "addr:postcode":"esteruelas;28816",
    "addr:street":"Calle De Espino Del",
    "iso:country":"ES",
    "sg:address":"Calle de Espino (del), 13",
    "sg:city":"Camarma Esteruelas",
    "sg:orig_category":"Servicios, Asesor\u00cda, Formaci\u00d3n En Ofim\u00c1tica",
    "sg:phone":"+34 918 86 52 25",
    "sg:postcode":"28816",
    "sg:province":"Madrid",
    "wof:name":"Saepap S.c.",
    "wof:placetype":"venue"
},
  "geometry": {"coordinates":[-3.3813281059,40.5540504456],"type":"Point"}
}