{
  "type": "Feature",
  "properties": {
    "addr:full":"Calle de San Jose, 89 San Jose Rinconada Sevilla 41300",
    "addr:postcode":"41300",
    "addr:street":"Calle De San;89",
    "iso:country":"ES",
    "sg:address":"Calle de San Jose, 89",
    "sg:city":"San Jose Rinconada",
    "sg:orig_category":"Cajas De Ahorro",
    "sg:phone":"+34 954 79 56 06",
    "sg:postcode":"41300",
    "sg:province":"Sevilla",
    "sg:website":"www.unicaja.es",
    "wof:name":"Unicaja",
    "wof:placetype":"venue"
},
  "geometry": {"coordinates":[-5.9447460175,37.481880188],"type":"Point"}
}