{
  "type": "Feature",
  "properties": {
    "iso:country":"ES",
    "sg:address":"Calle de Estudios, 12",
    "sg:city":"Soria",
    "sg:orig_category":"Abogados",
    "sg:phone":"+34 975 23 11 27",
    "sg:postcode":"42002",
    "sg:province":"Soria",
    "wof:name":"Gaspar Alcubilla Jesus",
    "wof:placetype":"venue"
},
  "geometry": {"coordinates":[-2.4662585258,41.7657089233],"type":"Point"}
}