{
  "type": "Feature",
  "properties": {
    "iso:country":"ES",
    "sg:address":"Calle de Doctor Galvez Ginachero, S/n",
    "sg:city":"Fuengirola",
    "sg:orig_category":"Abogados",
    "sg:phone":"+34 952 47 34 62",
    "sg:postcode":"29640",
    "sg:province":"M\u00e1laga",
    "wof:name":"Castro Sanchez Juan",
    "wof:placetype":"venue"
},
  "geometry": {"coordinates":[-4.6285090446,36.5324134827],"type":"Point"}
}