{
  "type": "Feature",
  "properties": {
    "iso:country":"ES",
    "sg:address":"Calle de Carretas, 19",
    "sg:city":"Santa Cristina De La Polvorosa",
    "sg:orig_category":"Farmacias",
    "sg:phone":"+34 980 63 07 08",
    "sg:postcode":"49620",
    "sg:province":"Zamora",
    "wof:name":"Vega Otero Maria Cristina De",
    "wof:placetype":"venue"
},
  "geometry": {"coordinates":[-5.7117085457,42.00025177],"type":"Point"}
}