{
  "type": "Feature",
  "properties": {
    "addr:full":"Av Alzira, 1 Corbera Valencia 46612",
    "addr:housenumber":"1",
    "addr:postcode":"46612",
    "addr:street":"Av Alzira",
    "iso:country":"ES",
    "sg:address":"Av Alzira, 1",
    "sg:city":"Corbera",
    "sg:orig_category":"Hielo Artificial (fabricaci\u00d3n, Distribuci\u00d3n)",
    "sg:phone":"+34 962 56 02 14",
    "sg:postcode":"46612",
    "sg:province":"Valencia",
    "wof:name":"Gomez Gil Benito",
    "wof:placetype":"venue"
},
  "geometry": {"coordinates":[-0.3556360006,39.1604042053],"type":"Point"}
}