{
  "type": "Feature",
  "properties": {
    "addr:full":"Calle de Molino De Viento (del), S/n Colmenar Viejo Madrid 28770",
    "addr:housenumber":"/ n",
    "addr:postcode":"28770",
    "addr:street":"Calle De Molino De Viento Del S",
    "iso:country":"ES",
    "sg:address":"Calle de Molino De Viento (del), S/n",
    "sg:city":"Colmenar Viejo",
    "sg:orig_category":"Tintes (fabricaci\u00d3n, Al Por Mayor)",
    "sg:phone":"+34 918 45 22 74",
    "sg:postcode":"28770",
    "sg:province":"Madrid",
    "wof:name":"Olalla Y Crespo S.c",
    "wof:placetype":"venue"
},
  "geometry": {"coordinates":[-3.7731199265,40.6647148132],"type":"Point"}
}