{
  "type": "Feature",
  "properties": {
    "iso:country":"ES",
    "sg:address":"Calle de Do\u00d1a Blasa, S/n",
    "sg:city":"Villarramiel",
    "sg:orig_category":"Asilos De Ancianos. Centros Privados",
    "sg:phone":"+34 979 83 71 87",
    "sg:postcode":"34140",
    "sg:province":"Palencia",
    "wof:name":"Asociacion Edad Dorada Mensajeros De La Paz Castilla Y Leon",
    "wof:placetype":"venue"
},
  "geometry": {"coordinates":[-4.9112725258,42.0433349609],"type":"Point"}
}