{
  "type": "Feature",
  "properties": {
    "iso:country":"ES",
    "sg:address":"Avda Toreros (de Los), 4",
    "sg:city":"Puerto De Santa Maria",
    "sg:orig_category":"Cerrajer\u00cda, Ferrallista",
    "sg:phone":"+34 956 85 09 56",
    "sg:postcode":"11500",
    "sg:province":"C\u00e1diz",
    "wof:name":"Lara Neto Jose Antonio",
    "wof:placetype":"venue"
},
  "geometry": {"coordinates":[-6.2361288071,36.5972557068],"type":"Point"}
}