{
  "type": "Feature",
  "properties": {
    "iso:country":"ES",
    "sg:address":"Carrer de Bruniquer, 14",
    "sg:city":"Barcelona",
    "sg:orig_category":"Molduras, Junquillos, Listones Y Molduras Perforadas",
    "sg:phone":"+34 932 13 10 64",
    "sg:postcode":"08012",
    "sg:province":"Barcelona",
    "wof:name":"Fontan Iturre S.l.",
    "wof:placetype":"venue"
},
  "geometry": {"coordinates":[2.1603109837,41.4043121338],"type":"Point"}
}