{
  "type": "Feature",
  "properties": {
    "addr:full":"Pque Nicolas Salmeron (de), 11 Almeria Almer\u00eda 04002",
    "addr:postcode":"04002",
    "addr:street":"Salmeron;Almeri\u0301A",
    "iso:country":"ES",
    "sg:address":"Pque Nicolas Salmeron (de), 11",
    "sg:city":"Almeria",
    "sg:orig_category":"Centros Comerciales Y Grandes Tiendas",
    "sg:phone":"+34 950 28 08 93",
    "sg:postcode":"04002",
    "sg:province":"Almer\u00eda",
    "wof:name":"Carretero Sierra Silvia",
    "wof:placetype":"venue"
},
  "geometry": {"coordinates":[-2.465321064,36.8353157043],"type":"Point"}
}