{
  "type": "Feature",
  "properties": {
    "iso:country":"ES",
    "sg:address":"Av Doctor Severo Ochoa, S/n",
    "sg:city":"Benidorm",
    "sg:orig_category":"Zonas De Acampada, Aparcamiento Para Caravanas",
    "sg:phone":"+34 965 86 85 52",
    "sg:postcode":"03500",
    "sg:province":"Alicante",
    "wof:name":"Benitelmo S.l.",
    "wof:placetype":"venue"
},
  "geometry": {"coordinates":[-0.1040249988,38.5408935547],"type":"Point"}
}