{
  "type": "Feature",
  "properties": {
    "addr:full":"Calle de Albeniz, 19 Pedro Mu\u00e7oz Ciudad Real 13620",
    "addr:housenumber":"19",
    "addr:postcode":"13620",
    "addr:street":"Calle De Albeniz;Pedro Muc\u0327Oz",
    "iso:country":"ES",
    "sg:address":"Calle de Albeniz, 19",
    "sg:city":"Pedro Mu\u00e7oz",
    "sg:orig_category":"Reposter\u00cdas",
    "sg:phone":"+34 926 56 86 49",
    "sg:postcode":"13620",
    "sg:province":"Ciudad Real",
    "wof:name":"Agrupacion Panadera San Cristobal S.l.",
    "wof:placetype":"venue"
},
  "geometry": {"coordinates":[-3.9272627831,38.9860954285],"type":"Point"}
}