{
  "type": "Feature",
  "properties": {
    "iso:country":"ES",
    "sg:address":"Calle de D. Luis Oliveros, 4",
    "sg:city":"Barrachina",
    "sg:orig_category":"Plomeros",
    "sg:phone":"+34 978 73 28 41",
    "sg:postcode":"44220",
    "sg:province":"Teruel",
    "wof:name":"Corbaton Beltran Manuel",
    "wof:placetype":"venue"
},
  "geometry": {"coordinates":[-1.1395314932,40.8980255127],"type":"Point"}
}