{
  "type": "Feature",
  "properties": {
    "iso:country":"ES",
    "sg:address":"Calle de Doctor Gregorio Mara\u00d1on, 43",
    "sg:city":"Almeria",
    "sg:orig_category":"Sindicatos De Trabajadores",
    "sg:phone":"+34 950 22 12 56",
    "sg:postcode":"04005",
    "sg:province":"Almer\u00eda",
    "wof:name":"Anpe Sindicato Independiente",
    "wof:placetype":"venue"
},
  "geometry": {"coordinates":[-2.4558649063,36.837474823],"type":"Point"}
}