{
  "type": "Feature",
  "properties": {
    "addr:full":"Carr De Pius Xii, 10 Ontinyent Valencia 46870",
    "addr:housenumber":"10",
    "addr:postcode":"46870",
    "addr:street":"Carr De Pius Xii",
    "iso:country":"ES",
    "sg:address":"Carr De Pius Xii, 10",
    "sg:city":"Ontinyent",
    "sg:orig_category":"Aparatos E Instalaci\u00d3n De Regad\u00cdos",
    "sg:phone":"+34 962 91 27 71",
    "sg:postcode":"46870",
    "sg:province":"Valencia",
    "wof:name":"Aguas Molto S.l.",
    "wof:placetype":"venue"
},
  "geometry": {"coordinates":[-0.6012338996,38.8243141174],"type":"Point"}
}