{
  "type": "Feature",
  "properties": {
    "addr:full":"Carrer de Francisco Rover, 1 Palma Islas Baleares 07003",
    "addr:housenumber":"1",
    "addr:postcode":"07003",
    "addr:street":"Carrer De Francisco Rover",
    "iso:country":"ES",
    "sg:address":"Carrer de Francisco Rover, 1",
    "sg:city":"Palma",
    "sg:orig_category":"Abogados",
    "sg:phone":"+34 971 20 62 50",
    "sg:postcode":"07003",
    "sg:province":"Islas Baleares",
    "wof:name":"Despatx Missers Capella Associats S.l.",
    "wof:placetype":"venue"
},
  "geometry": {"coordinates":[2.6473009586,39.57995224],"type":"Point"}
}