{
  "type": "Feature",
  "properties": {
    "iso:country":"ES",
    "sg:address":"Calle de Olmo, 1",
    "sg:city":"Vera",
    "sg:orig_category":"Telas Y Sedas (al Por Menor)",
    "sg:phone":"+34 950 39 00 80",
    "sg:postcode":"04620",
    "sg:province":"Almer\u00eda",
    "wof:name":"Rodriguez Albarracin Bartolome",
    "wof:placetype":"venue"
},
  "geometry": {"coordinates":[-1.8580629826,37.2454833984],"type":"Point"}
}