{
  "type": "Feature",
  "properties": {
    "iso:country":"ES",
    "sg:address":"Avda Valdefierro, 30",
    "sg:city":"Zaragoza",
    "sg:orig_category":"Molduras, Junquillos, Listones Y Molduras Perforadas",
    "sg:phone":"+34 976 31 19 81",
    "sg:postcode":"50012",
    "sg:province":"Zaragoza",
    "wof:name":"Ramirez Alcantara Silvia",
    "wof:placetype":"venue"
},
  "geometry": {"coordinates":[-0.9294019938,41.6402740479],"type":"Point"}
}