{
  "type": "Feature",
  "properties": {
    "addr:full":"Calle de Natividad, 1 Alcala Henares Madrid 28805",
    "addr:housenumber":"1",
    "addr:postcode":"28805",
    "addr:street":"Calle De Natividad",
    "iso:country":"ES",
    "sg:address":"Calle de Natividad, 1",
    "sg:city":"Alcala Henares",
    "sg:orig_category":"Inmobiliaria (agencias)",
    "sg:phone":"+34 918 83 44 24",
    "sg:postcode":"28805",
    "sg:province":"Madrid",
    "wof:name":"O\u00d1oro Gestion Inmobiliaria Y Servicios S.l.",
    "wof:placetype":"venue"
},
  "geometry": {"coordinates":[-3.3613541126,40.4859199524],"type":"Point"}
}