{
  "type": "Feature",
  "properties": {
    "iso:country":"ES",
    "sg:address":"Los Remedios, 2",
    "sg:city":"San Miguel De Meruelo",
    "sg:orig_category":"Invernaderos Y Semilleros",
    "sg:phone":"+34 942 67 48 51",
    "sg:postcode":"39192",
    "sg:province":"Cantabria",
    "wof:name":"Alvarez Castillo Felipe",
    "wof:placetype":"venue"
},
  "geometry": {"coordinates":[-3.5785262585,43.4593086243],"type":"Point"}
}