{
  "type": "Feature",
  "properties": {
    "iso:country":"ES",
    "sg:address":"Avda Federico Silva Mu\u00d1oz, S/n",
    "sg:city":"Isla Cristina",
    "sg:orig_category":"Ense\u00d1anza, Formaci\u00d3n Profesional: Aprendizaje",
    "sg:phone":"+34 959 34 42 63",
    "sg:postcode":"21410",
    "sg:province":"Huelva",
    "wof:name":"Direccion Provincial Del Instituto Social De La Marina De Huelva",
    "wof:placetype":"venue"
},
  "geometry": {"coordinates":[-7.3247790337,37.1958465576],"type":"Point"}
}