{
  "type": "Feature",
  "properties": {
    "addr:full":"Calle de Miguel Yuste, 22 Madrid Madrid 28037",
    "addr:housenumber":"22",
    "addr:postcode":"madrid;28037",
    "addr:street":"Calle De Miguel Yuste",
    "iso:country":"ES",
    "sg:address":"Calle de Miguel Yuste, 22",
    "sg:city":"Madrid",
    "sg:orig_category":"Fabricaci\u00d3n, Venta, Instalaci\u00d3n De R\u00d3tulos, De R\u00d3tulos Luminosos",
    "sg:phone":"+34 917 54 11 13",
    "sg:postcode":"28037",
    "sg:province":"Madrid",
    "wof:name":"Grafismos Decorativos S.l.",
    "wof:placetype":"venue"
},
  "geometry": {"coordinates":[-3.6248428822,40.4390792847],"type":"Point"}
}