{
  "type": "Feature",
  "properties": {
    "addr:full":"Carr Tramuntana, 19 Puerto De Pollen\u00c7a Islas Baleares 07470",
    "addr:housenumber":"19",
    "addr:postcode":"07470",
    "addr:street":"Carr Tramuntana",
    "iso:country":"ES",
    "sg:address":"Carr Tramuntana, 19",
    "sg:city":"Puerto De Pollen\u00c7a",
    "sg:orig_category":"Restaurantes",
    "sg:phone":"+34 971 86 74 25",
    "sg:postcode":"07470",
    "sg:province":"Islas Baleares",
    "wof:name":"Laval C.d",
    "wof:placetype":"venue"
},
  "geometry": {"coordinates":[3.0821900368,39.9063034058],"type":"Point"}
}