{
  "type": "Feature",
  "properties": {
    "addr:full":"Avda Torrelobaton, 27 Tordesillas Valladolid 47100",
    "addr:housenumber":"27",
    "addr:postcode":"47100",
    "addr:street":"Avda Torrelobaton",
    "iso:country":"ES",
    "sg:address":"Avda Torrelobaton, 27",
    "sg:city":"Tordesillas",
    "sg:orig_category":"Contenedores (mercanc\u00cdas)",
    "sg:phone":"+34 983 77 00 18",
    "sg:postcode":"47100",
    "sg:province":"Valladolid",
    "wof:name":"Puertas Labajos Juan Antonio",
    "wof:placetype":"venue"
},
  "geometry": {"coordinates":[-4.9976592064,41.5077362061],"type":"Point"}
}