{
  "type": "Feature",
  "properties": {
    "iso:country":"ES",
    "sg:address":"Calle de Santisima Trinidad, 3",
    "sg:city":"Madrid",
    "sg:orig_category":"Sindicatos Y Colegios Profesionales",
    "sg:phone":"+34 915 93 12 66",
    "sg:postcode":"28010",
    "sg:province":"Madrid",
    "wof:name":"Asociacion Espanola De Desguace Y Reciclaje",
    "wof:placetype":"venue"
},
  "geometry": {"coordinates":[-3.7003691196,40.4349403381],"type":"Point"}
}