{
  "type": "Feature",
  "properties": {
    "addr:full":"Calle de General Ceballos, 8 Torrelavega Cantabria 39300",
    "addr:housenumber":"8",
    "addr:postcode":"39300",
    "addr:street":"Calle De General Ceballos",
    "iso:country":"ES",
    "sg:address":"Calle de General Ceballos, 8",
    "sg:city":"Torrelavega",
    "sg:orig_category":"Empresas De Portes Y Mensajer\u00cda",
    "sg:phone":"+34 942 88 88 88",
    "sg:postcode":"39300",
    "sg:province":"Cantabria",
    "wof:name":"Radio Servicios 88 S.l.",
    "wof:placetype":"venue"
},
  "geometry": {"coordinates":[-4.0475301743,43.3523101807],"type":"Point"}
}