{
  "type": "Feature",
  "properties": {
    "addr:full":"Calle de Virgen Del Camino, 3 Potes Cantabria 39570",
    "addr:housenumber":"3",
    "addr:postcode":"39570",
    "addr:street":"Calle De Virgen Del Camino",
    "iso:country":"ES",
    "sg:address":"Calle de Virgen Del Camino, 3",
    "sg:city":"Potes",
    "sg:orig_category":"Mayoristas E Intermediarios En Alcoholes",
    "sg:phone":"+34 942 73 21 03",
    "sg:postcode":"39570",
    "sg:province":"Cantabria",
    "wof:name":"Distribuciones El Canchal Cantabria S.l.",
    "wof:placetype":"venue"
},
  "geometry": {"coordinates":[-4.6274437904,43.1538505554],"type":"Point"}
}