{
  "type": "Feature",
  "properties": {
    "addr:full":"Calle de Juan Francisco, 20 Madrid Madrid 28025",
    "addr:housenumber":"20",
    "addr:postcode":"madrid;28025",
    "addr:street":"Calle De Juan Francisco",
    "iso:country":"ES",
    "sg:address":"Calle de Juan Francisco, 20",
    "sg:city":"Madrid",
    "sg:orig_category":"Material Did\u00c1ctico",
    "sg:phone":"+34 914 66 72 56",
    "sg:postcode":"28025",
    "sg:province":"Madrid",
    "wof:name":"Educamat",
    "wof:placetype":"venue"
},
  "geometry": {"coordinates":[-3.7334198952,40.3865470886],"type":"Point"}
}