{
  "type": "Feature",
  "properties": {
    "iso:country":"ES",
    "sg:address":"Avda Garcia Barbon, 122",
    "sg:city":"Vigo",
    "sg:orig_category":"Traductores",
    "sg:phone":"+34 986 22 01 62",
    "sg:postcode":"36201",
    "sg:province":"Pontevedra",
    "wof:name":"Garcia Montero Carmen Maria",
    "wof:placetype":"venue"
},
  "geometry": {"coordinates":[-8.7114305496,42.2375068665],"type":"Point"}
}