{
  "type": "Feature",
  "properties": {
    "iso:country":"ES",
    "sg:address":"Carrer de Garcilaso, 1",
    "sg:city":"Sabadell",
    "sg:orig_category":"Cl\u00cdnicas Dentales",
    "sg:phone":"+34 937 27 81 71",
    "sg:postcode":"08201",
    "sg:province":"Barcelona",
    "wof:name":"Herrero Mu\u00f1oz Alberto",
    "wof:placetype":"venue"
},
  "geometry": {"coordinates":[2.1070730686,41.5507011414],"type":"Point"}
}