{
  "type": "Feature",
  "properties": {
    "iso:country":"ES",
    "sg:address":"Calle de Poza Licenciado, 62",
    "sg:city":"Bilbao",
    "sg:orig_category":"Copas, Insignias, Trofeos",
    "sg:phone":"+34 944 39 33 30",
    "sg:postcode":"48013",
    "sg:province":"Vizcaya",
    "wof:name":"Trofeos Madariaga S.l.",
    "wof:placetype":"venue"
},
  "geometry": {"coordinates":[-2.9464271069,43.2634277344],"type":"Point"}
}