{
  "type": "Feature",
  "properties": {
    "addr:full":"Calle de Postigo De San Martin, 5 Madrid Madrid 28013",
    "addr:housenumber":"5",
    "addr:postcode":"28013",
    "addr:street":"Calle De Postigo De San Martin",
    "iso:country":"ES",
    "sg:address":"Calle de Postigo De San Martin, 5",
    "sg:city":"Madrid",
    "sg:orig_category":"Molduras, Junquillos, Listones Y Molduras Perforadas",
    "sg:phone":"+34 915 21 59 00",
    "sg:postcode":"28013",
    "sg:province":"Madrid",
    "wof:name":"Blazquez Vallejo Victorina",
    "wof:placetype":"venue"
},
  "geometry": {"coordinates":[-3.7064070702,40.4190597534],"type":"Point"}
}