{
  "type": "Feature",
  "properties": {
    "addr:full":"Calle de Federico Garcia Lorca, S/n Jerez De La Frontera C\u00e1diz 11407",
    "addr:postcode":"11407",
    "addr:street":"Calle De Federico Garcia Lorca S / N",
    "iso:country":"ES",
    "sg:address":"Calle de Federico Garcia Lorca, S/n",
    "sg:city":"Jerez De La Frontera",
    "sg:orig_category":"Farmacias",
    "sg:phone":"+34 956 30 06 76",
    "sg:postcode":"11407",
    "sg:province":"C\u00e1diz",
    "wof:name":"Sanchez Martinez Maria Paz",
    "wof:placetype":"venue"
},
  "geometry": {"coordinates":[-6.1353192329,36.700214386],"type":"Point"}
}