{
  "type": "Feature",
  "properties": {
    "addr:full":"Avda Sevilla (de), S/n Rota C\u00e1diz 11520",
    "addr:housenumber":"/ n",
    "addr:postcode":"11520",
    "addr:street":"Avda Sevilla De S;Ca\u0301Diz",
    "iso:country":"ES",
    "sg:address":"Avda Sevilla (de), S/n",
    "sg:city":"Rota",
    "sg:orig_category":"Negocio De Materiales De Construcci\u00d3n",
    "sg:phone":"+34 956 81 03 40",
    "sg:postcode":"11520",
    "sg:province":"C\u00e1diz",
    "wof:name":"Representaciones Portilla S.c.",
    "wof:placetype":"venue"
},
  "geometry": {"coordinates":[-6.3641138077,36.620929718],"type":"Point"}
}