{
  "type": "Feature",
  "properties": {
    "addr:full":"Cra. De Gualba, S/n Gualba Barcelona 08474",
    "addr:housenumber":"s / n",
    "addr:postcode":"08474",
    "iso:country":"ES",
    "sg:address":"Cra. De Gualba, S/n",
    "sg:city":"Gualba",
    "sg:orig_category":"Fabricaci\u00d3n De Moldes Y Modelos",
    "sg:phone":"+34 938 47 07 47",
    "sg:postcode":"08474",
    "sg:province":"Barcelona",
    "wof:name":"Plastics Ide S.a.",
    "wof:placetype":"venue"
},
  "geometry": {"coordinates":[2.5258259773,41.7097396851],"type":"Point"}
}