{
  "type": "Feature",
  "properties": {
    "addr:full":"Av Drassanes, 29 Barcelona Barcelona 08001",
    "addr:housenumber":"29",
    "addr:postcode":"08001",
    "addr:street":"Av Drassanes",
    "iso:country":"ES",
    "sg:address":"Av Drassanes, 29",
    "sg:city":"Barcelona",
    "sg:orig_category":"Cajas De Ahorro",
    "sg:phone":"+34 933 29 22 54",
    "sg:postcode":"08001",
    "sg:province":"Barcelona",
    "wof:name":"Caixa D'estalvis I Pensions De Barcelona",
    "wof:placetype":"venue"
},
  "geometry": {"coordinates":[2.172162056,41.3767700195],"type":"Point"}
}