{
  "type": "Feature",
  "properties": {
    "addr:full":"Plaz Espa\u00d1a, 37 Gibraleon Huelva 21500",
    "addr:housenumber":"37",
    "addr:postcode":"21500",
    "addr:street":"Plaz Espan\u0303A",
    "iso:country":"ES",
    "sg:address":"Plaz Espa\u00d1a, 37",
    "sg:city":"Gibraleon",
    "sg:orig_category":"Servicios Gsm",
    "sg:phone":"+34 959 30 12 72",
    "sg:postcode":"21500",
    "sg:province":"Huelva",
    "wof:name":"Prieto Macias Vicente Jesus",
    "wof:placetype":"venue"
},
  "geometry": {"coordinates":[-6.9744291306,37.3773460388],"type":"Point"}
}