{
  "type": "Feature",
  "properties": {
    "iso:country":"ES",
    "sg:address":"Pla\u00c7 Font, S/n",
    "sg:city":"Vilamalla",
    "sg:classifiers":[
        {
            "category":"Communications",
            "type":"Services"
        }
    ],
    "sg:phone":"+34 972 52 58 94",
    "sg:postcode":"17469",
    "sg:province":"Girona",
    "sg:tags":[
        "televisiones",
        "y",
        "radio"
    ],
    "sg:website":"www.radiovilamalla.com",
    "wof:name":"Messina  Salvatore",
    "wof:placetype":"venue"
},
  "geometry": {"coordinates":[3.0403180122,42.2426719666],"type":"Point"}
}