{
  "type": "Feature",
  "properties": {
    "iso:country":"ES",
    "sg:address":"Calle de Leon Y Escosura, 8",
    "sg:city":"Oviedo",
    "sg:orig_category":"Aparcamientos (infraestructuras, Accesorios)",
    "sg:phone":"+34 985 24 16 22",
    "sg:postcode":"33013",
    "sg:province":"Asturias",
    "wof:name":"Garaje Principado S. A.",
    "wof:placetype":"venue"
},
  "geometry": {"coordinates":[-5.8612117767,43.3622398376],"type":"Point"}
}