{
  "type": "Feature",
  "properties": {
    "addr:full":"Calle de Isidoro Melero, 15 Alsasua Navarra 31800",
    "addr:housenumber":"15",
    "addr:postcode":"31800",
    "addr:street":"Calle De Isidoro Melero",
    "iso:country":"ES",
    "sg:address":"Calle de Isidoro Melero, 15",
    "sg:city":"Alsasua",
    "sg:orig_category":"Agencias De Viajes",
    "sg:phone":"+34 948 56 24 12",
    "sg:postcode":"31800",
    "sg:province":"Navarra",
    "sg:website":"www.halconviajes.com",
    "wof:name":"Viajes Halcon S.a.",
    "wof:placetype":"venue"
},
  "geometry": {"coordinates":[-2.1706559658,42.8966674805],"type":"Point"}
}