{
  "type": "Feature",
  "properties": {
    "addr:full":"Calle de Cebada (de La), 3 Sese\u00f1a Toledo 45223",
    "addr:housenumber":"3",
    "addr:postcode":"45223",
    "addr:street":"Calle De Cebada De La",
    "iso:country":"ES",
    "sg:address":"Calle de Cebada (de La), 3",
    "sg:city":"Sese\u00f1a",
    "sg:orig_category":"Negocio De Materiales De Construcci\u00d3n",
    "sg:phone":"+34 918 08 81 17",
    "sg:postcode":"45223",
    "sg:province":"Toledo",
    "wof:name":"Distribuciones El Pinar 2000 S.l.",
    "wof:placetype":"venue"
},
  "geometry": {"coordinates":[-3.6784238815,40.1063499451],"type":"Point"}
}