{
  "type": "Feature",
  "properties": {
    "iso:country":"ES",
    "sg:address":"Calle de Diego De Leon, 21",
    "sg:city":"Madrid",
    "sg:orig_category":"M\u00c9dicos: Oftalmolog\u00cda",
    "sg:phone":"+34 914 11 08 37",
    "sg:postcode":"28006",
    "sg:province":"Madrid",
    "wof:name":"Thomas Vi\u00f1as Silvia",
    "wof:placetype":"venue"
},
  "geometry": {"coordinates":[-3.6826813221,40.4349403381],"type":"Point"}
}