{
  "type": "Feature",
  "properties": {
    "iso:country":"ES",
    "sg:address":"Avda San Javier, 1",
    "sg:city":"Churriana",
    "sg:orig_category":"Servicios Gsm",
    "sg:phone":"+34 952 43 55 51",
    "sg:postcode":"29140",
    "sg:province":"M\u00e1laga",
    "wof:name":"Villanueva Lopez Francisca",
    "wof:placetype":"venue"
},
  "geometry": {"coordinates":[-4.5037641525,36.6657714844],"type":"Point"}
}