{
  "type": "Feature",
  "properties": {
    "addr:full":"Ctra Palma Del Rio (bda. Occidente), 1 Cordoba C\u00f3rdoba 14005",
    "addr:housenumber":"1",
    "addr:postcode":"14005",
    "addr:street":"Ctra Palma Del Rio Bda. Occidente;Co\u0301Rdoba",
    "iso:country":"ES",
    "sg:address":"Ctra Palma Del Rio (bda. Occidente), 1",
    "sg:city":"Cordoba",
    "sg:orig_category":"Chapister\u00cda",
    "sg:phone":"+34 957 46 43 73",
    "sg:postcode":"14005",
    "sg:province":"C\u00f3rdoba",
    "wof:name":"Sanchez Fuentes S.l.",
    "wof:placetype":"venue"
},
  "geometry": {"coordinates":[-4.7997479439,37.8853874207],"type":"Point"}
}