{
  "type": "Feature",
  "properties": {
    "iso:country":"ES",
    "sg:address":"Calle de Covadonga, 17",
    "sg:city":"Valladolid",
    "sg:orig_category":"Peluquer\u00cdas, Peluquer\u00cda Mixta",
    "sg:phone":"+34 983 29 48 14",
    "sg:postcode":"47005",
    "sg:province":"Valladolid",
    "wof:name":"Lopez Gonzalez Maria Jesus",
    "wof:placetype":"venue"
},
  "geometry": {"coordinates":[-4.7131814957,41.6558227539],"type":"Point"}
}