{
  "type": "Feature",
  "properties": {
    "iso:country":"ES",
    "sg:address":"Calle de Abu Zeyan, 10",
    "sg:city":"Denia",
    "sg:orig_category":"Empresas De Limpieza",
    "sg:phone":"+34 965 78 80 40",
    "sg:postcode":"03700",
    "sg:province":"Alicante",
    "sg:website":"www.msu.cc",
    "wof:name":"M.s.u. Higiene Industrial S.l",
    "wof:placetype":"venue"
},
  "geometry": {"coordinates":[0.0840215012,38.8309745789],"type":"Point"}
}