{
  "type": "Feature",
  "properties": {
    "addr:full":"Calle de Mequinez, 112 Puerto Cruz Santa Cruz De Tenerife 38400",
    "addr:housenumber":"112",
    "addr:postcode":"38400",
    "addr:street":"Calle De Mequinez;Cruz",
    "iso:country":"ES",
    "sg:address":"Calle de Mequinez, 112",
    "sg:city":"Puerto Cruz",
    "sg:orig_category":"Peluquer\u00cdas, Peluquer\u00cda Mixta",
    "sg:phone":"+34 922 37 42 23",
    "sg:postcode":"38400",
    "sg:province":"Santa Cruz De Tenerife",
    "wof:name":"Marrero Gonzalez Maria De Los Angeles",
    "wof:placetype":"venue"
},
  "geometry": {"coordinates":[-16.5552368164,28.4164848328],"type":"Point"}
}