{
  "type": "Feature",
  "properties": {
    "addr:full":"Avda Canarias, 336 Vecindario Las Palmas 35110",
    "addr:housenumber":"336",
    "addr:postcode":"35110",
    "addr:street":"Avda Canarias;Las Palmas",
    "iso:country":"ES",
    "sg:address":"Avda Canarias, 336",
    "sg:city":"Vecindario",
    "sg:orig_category":"Panader\u00cdas, Panader\u00cdas",
    "sg:phone":"+34 928 79 13 19",
    "sg:postcode":"35110",
    "sg:province":"Las Palmas",
    "wof:name":"Perez Santana Teresa Elsa",
    "wof:placetype":"venue"
},
  "geometry": {"coordinates":[-15.4450893402,27.844789505],"type":"Point"}
}