{
  "type": "Feature",
  "properties": {
    "addr:full":"Carrer de Panta, 90 Terrassa Barcelona 08221",
    "addr:housenumber":"90",
    "addr:postcode":"08221",
    "addr:street":"Carrer De Panta",
    "iso:country":"ES",
    "sg:address":"Carrer de Panta, 90",
    "sg:city":"Terrassa",
    "sg:orig_category":"Arquitectos",
    "sg:phone":"+34 937 88 77 49",
    "sg:postcode":"08221",
    "sg:province":"Barcelona",
    "wof:name":"Rambla Amat Luis",
    "wof:placetype":"venue"
},
  "geometry": {"coordinates":[2.0102789402,41.5668945312],"type":"Point"}
}