{
  "type": "Feature",
  "properties": {
    "iso:country":"ES",
    "sg:address":"Avda Arretxinaga, 22",
    "sg:city":"Markina-xemein",
    "sg:orig_category":"Formaci\u00d3n Continuada (variada)",
    "sg:phone":"+34 946 16 89 15",
    "sg:postcode":"48270",
    "sg:province":"Vizcaya",
    "wof:name":"Ilunza Hezgarri Kolektiboa",
    "wof:placetype":"venue"
},
  "geometry": {"coordinates":[-2.4939088821,43.2742881775],"type":"Point"}
}