{
  "type": "Feature",
  "properties": {
    "iso:country":"ES",
    "sg:address":"Calle de Manuel Noya, 29",
    "sg:city":"Madrid",
    "sg:orig_category":"Zapatos (al Por Menor)",
    "sg:phone":"+34 914 60 52 76",
    "sg:postcode":"28026",
    "sg:province":"Madrid",
    "wof:name":"Del Arco Almazan Maria Del Rosario",
    "wof:placetype":"venue"
},
  "geometry": {"coordinates":[-3.7117989063,40.3853721619],"type":"Point"}
}