{
  "type": "Feature",
  "properties": {
    "addr:full":"Carr Guardia Civil, 11 Cullera Valencia 46400",
    "addr:housenumber":"11",
    "addr:postcode":"46400",
    "addr:street":"Carr Guardia Civil",
    "iso:country":"ES",
    "sg:address":"Carr Guardia Civil, 11",
    "sg:city":"Cullera",
    "sg:orig_category":"Organizaciones Profesionales",
    "sg:phone":"+34 961 72 16 34",
    "sg:postcode":"46400",
    "sg:province":"Valencia",
    "wof:name":"Puig Olmo Jose Antonio",
    "wof:placetype":"venue"
},
  "geometry": {"coordinates":[-0.2592290044,39.1644096375],"type":"Point"}
}