{
  "type": "Feature",
  "properties": {
    "addr:full":"Estd Castela, 25 Ferrol La Coru\u00f1a 15403",
    "addr:housenumber":"25",
    "addr:postcode":"15403",
    "addr:street":"Castela;La Corun\u0303A",
    "iso:country":"ES",
    "sg:address":"Estd Castela, 25",
    "sg:city":"Ferrol",
    "sg:orig_category":"Reposter\u00cdas",
    "sg:phone":"+34 981 37 20 75",
    "sg:postcode":"15403",
    "sg:province":"La Coru\u00f1a",
    "wof:name":"Garrote Montero Jose",
    "wof:placetype":"venue"
},
  "geometry": {"coordinates":[-8.2258491516,43.4874992371],"type":"Point"}
}