{
  "type": "Feature",
  "properties": {
    "addr:full":"Calle de Virgen De Fatima, 8 Sevilla Sevilla 41010",
    "addr:housenumber":"8",
    "addr:postcode":"41010",
    "addr:street":"Calle De Virgen De Fatima",
    "iso:country":"ES",
    "sg:address":"Calle de Virgen De Fatima, 8",
    "sg:city":"Sevilla",
    "sg:orig_category":"Iglesia Cat\u00d3lica",
    "sg:phone":"+34 954 45 73 84",
    "sg:postcode":"41010",
    "sg:province":"Sevilla",
    "wof:name":"Parroquia Nuestra Se\u00f1ora Del Buen Aire",
    "wof:placetype":"venue"
},
  "geometry": {"coordinates":[-6.0040221214,37.3778114319],"type":"Point"}
}