{
  "type": "Feature",
  "properties": {
    "iso:country":"ES",
    "sg:address":"Calle de Santa Maria De Gracia, 25",
    "sg:city":"Camas",
    "sg:orig_category":"Pintura Y Barniz (al Por Menor)",
    "sg:phone":"+34 955 98 00 92",
    "sg:postcode":"41900",
    "sg:province":"Sevilla",
    "wof:name":"Pinturas Mohedano S.l.",
    "wof:placetype":"venue"
},
  "geometry": {"coordinates":[-6.0351729393,37.4028320312],"type":"Point"}
}