{
  "type": "Feature",
  "properties": {
    "addr:full":"Avda Reina Victoria Eugenia, 1 Cartagena Murcia 30205",
    "addr:housenumber":"1",
    "addr:postcode":"30205",
    "addr:street":"Avda Reina Victoria Eugenia",
    "iso:country":"ES",
    "sg:address":"Avda Reina Victoria Eugenia, 1",
    "sg:city":"Cartagena",
    "sg:orig_category":"Sociedades, Compa\u00d1\u00cdas Aseguradoras",
    "sg:phone":"+34 968 12 00 03",
    "sg:postcode":"30205",
    "sg:province":"Murcia",
    "sg:website":"www.santalucia.es",
    "wof:name":"Santa Lucia S.a.",
    "wof:placetype":"venue"
},
  "geometry": {"coordinates":[-0.9920989871,37.6093254089],"type":"Point"}
}