{
  "type": "Feature",
  "properties": {
    "addr:full":"Plaz Mercado Del, 3 Zamora Zamora 49003",
    "addr:postcode":"49003",
    "iso:country":"ES",
    "sg:address":"Plaz Mercado Del, 3",
    "sg:city":"Zamora",
    "sg:orig_category":"Platos Preparados Refrigerados (fabricaci\u00d3n, Al Por Mayor)",
    "sg:phone":"+34 980 53 65 94",
    "sg:postcode":"49003",
    "sg:province":"Zamora",
    "wof:name":"Prieto Beneitez Juan Jose",
    "wof:placetype":"venue"
},
  "geometry": {"coordinates":[-5.7457342148,41.5033302307],"type":"Point"}
}