{
  "type": "Feature",
  "properties": {
    "iso:country":"ES",
    "sg:address":"Carrer de Carrio, 3",
    "sg:city":"Manresa",
    "sg:orig_category":"Abogados",
    "sg:phone":"+34 938 75 11 49",
    "sg:postcode":"08242",
    "sg:province":"Barcelona",
    "wof:name":"Guix Brunet Jose",
    "wof:placetype":"venue"
},
  "geometry": {"coordinates":[1.8222279549,41.7276153564],"type":"Point"}
}