{
  "type": "Feature",
  "properties": {
    "addr:full":"Carr Dr Fleming, 35 Balaguer Lleida 25600",
    "addr:housenumber":"35",
    "addr:postcode":"25600",
    "addr:street":"Carr Dr Fleming",
    "iso:country":"ES",
    "sg:address":"Carr Dr Fleming, 35",
    "sg:city":"Balaguer",
    "sg:orig_category":"Frutas, Legumbres Frescas Y Tempranas (al Por Menor)",
    "sg:phone":"+34 973 45 08 17",
    "sg:postcode":"25600",
    "sg:province":"Lleida",
    "wof:name":"Mestres 1993 S.l.",
    "wof:placetype":"venue"
},
  "geometry": {"coordinates":[0.8099160194,41.7898139954],"type":"Point"}
}