{
  "type": "Feature",
  "properties": {
    "addr:full":"Don Jose Fdez., 6 Ca\u00f1amero C\u00e1ceres 10136",
    "addr:housenumber":"6",
    "addr:postcode":"10136",
    "addr:street":"Fdez.;Ca\u0301Ceres",
    "iso:country":"ES",
    "sg:address":"Don Jose Fdez., 6",
    "sg:city":"Ca\u00f1amero",
    "sg:orig_category":"Inform\u00c1tica (estudios, Servicios, Asesor\u00cda, Formaci\u00d3n)",
    "sg:phone":"+34 927 36 92 26",
    "sg:postcode":"10136",
    "sg:province":"C\u00e1ceres",
    "wof:name":"Cidex Centro De Informacion Y Desarrollo De Extremadura S.l.l",
    "wof:placetype":"venue"
},
  "geometry": {"coordinates":[-5.388174057,39.3798522949],"type":"Point"}
}