{
  "type": "Feature",
  "properties": {
    "iso:country":"ES",
    "sg:address":"Calle de Bravo Murillo, 194",
    "sg:city":"Madrid",
    "sg:orig_category":"Art\u00cdculos De Decoraci\u00d3n",
    "sg:phone":"+34 915 70 98 51",
    "sg:postcode":"28020",
    "sg:province":"Madrid",
    "sg:website":"www.tiendas-asi.com",
    "wof:name":"Asivil S.l.",
    "wof:placetype":"venue"
},
  "geometry": {"coordinates":[-3.7026219368,40.4552268982],"type":"Point"}
}