{
  "type": "Feature",
  "properties": {
    "addr:full":"Calle de Manuel Llaneza, 68 Mieres Asturias 33600",
    "addr:housenumber":"68",
    "addr:postcode":"33600",
    "addr:street":"Calle De Manuel Llaneza",
    "iso:country":"ES",
    "sg:address":"Calle de Manuel Llaneza, 68",
    "sg:city":"Mieres",
    "sg:orig_category":"Peluqueros: De Se\u00d1oras",
    "sg:phone":"+34 985 45 21 15",
    "sg:postcode":"33600",
    "sg:province":"Asturias",
    "wof:name":"Espina Barbado Nuria",
    "wof:placetype":"venue"
},
  "geometry": {"coordinates":[-5.778758049,43.2505989075],"type":"Point"}
}