{
  "type": "Feature",
  "properties": {
    "addr:full":"Pl. Espa\u00f1a Leganes Madrid 28911",
    "addr:postcode":"28911",
    "addr:street":"Pl. Espan\u0303A",
    "iso:country":"ES",
    "sg:address":"Pl. Espa\u00f1a",
    "sg:city":"Leganes",
    "sg:orig_category":"Art\u00cdculos De Regalo (al Por Menor)",
    "sg:phone":"+34 916 93 67 05",
    "sg:postcode":"28911",
    "sg:province":"Madrid",
    "wof:name":"Mundiboda 2000 S.l.",
    "wof:placetype":"venue"
},
  "geometry": {"coordinates":[-3.7654390335,40.3283462524],"type":"Point"}
}