{
  "type": "Feature",
  "properties": {
    "iso:country":"ES",
    "sg:address":"Calle de Esteban Domingo, 1",
    "sg:city":"Avila",
    "sg:orig_category":"Cristaler\u00cdas",
    "sg:phone":"+34 920 21 28 94",
    "sg:postcode":"05001",
    "sg:province":"\u00c1vila",
    "wof:name":"Rodriguez Leiva Jose Antonio",
    "wof:placetype":"venue"
},
  "geometry": {"coordinates":[-4.6993789673,40.6569786072],"type":"Point"}
}