{
  "type": "Feature",
  "properties": {
    "iso:country":"ES",
    "sg:address":"Rua Mui\u00d1o, 50",
    "sg:city":"Carballo",
    "sg:orig_category":"M\u00c1rmoles, Granitos Y Piedras Naturales",
    "sg:phone":"+34 981 75 72 20",
    "sg:postcode":"15100",
    "sg:province":"La Coru\u00f1a",
    "wof:name":"Marmoles Lisema S.l.",
    "wof:placetype":"venue"
},
  "geometry": {"coordinates":[-8.6893186569,43.2181816101],"type":"Point"}
}