{
  "type": "Feature",
  "properties": {
    "addr:full":"Avgd Prat De La Riba, 77 Lleida Lleida 25004",
    "addr:housenumber":"77",
    "addr:postcode":"25004",
    "addr:street":"La Riba",
    "iso:country":"ES",
    "sg:address":"Avgd Prat De La Riba, 77",
    "sg:city":"Lleida",
    "sg:orig_category":"Aceites Y Grasas Alimentarias (fabricaci\u00d3n, Al Por Mayor)",
    "sg:phone":"+34 973 24 54 51",
    "sg:postcode":"25004",
    "sg:province":"Lleida",
    "wof:name":"Anglada Martinez Maria Dolors",
    "wof:placetype":"venue"
},
  "geometry": {"coordinates":[0.6264765263,41.6221466064],"type":"Point"}
}