{
  "type": "Feature",
  "properties": {
    "iso:country":"ES",
    "sg:address":"Avda Castilla La Mancha, 14",
    "sg:city":"Illescas",
    "sg:orig_category":"Muebles, Minoristas",
    "sg:phone":"+34 925 54 09 29",
    "sg:postcode":"45200",
    "sg:province":"Toledo",
    "wof:name":"Villa Gutierrez Miriam",
    "wof:placetype":"venue"
},
  "geometry": {"coordinates":[-3.8505890369,40.1212997437],"type":"Point"}
}