{
  "type": "Feature",
  "properties": {
    "iso:country":"ES",
    "sg:address":"Carrer de Unio, 7",
    "sg:city":"Porrera",
    "sg:orig_category":"Cooperativas Agr\u00cdcolas",
    "sg:phone":"+34 977 82 80 01",
    "sg:postcode":"43739",
    "sg:province":"Tarragona",
    "wof:name":"Agricola De Porrera S.c.c.l.",
    "wof:placetype":"venue"
},
  "geometry": {"coordinates":[0.8571689725,41.1885261536],"type":"Point"}
}