{
  "type": "Feature",
  "properties": {
    "addr:full":"Calle de Santa Agueda, 3 Cocentaina Alicante 03820",
    "addr:housenumber":"3",
    "addr:postcode":"03820",
    "addr:street":"Calle De Santa Agueda",
    "iso:country":"ES",
    "sg:address":"Calle de Santa Agueda, 3",
    "sg:city":"Cocentaina",
    "sg:orig_category":"Reposter\u00cdas",
    "sg:phone":"+34 965 59 05 27",
    "sg:postcode":"03820",
    "sg:province":"Alicante",
    "wof:name":"San Salvador Vicedo Miguel",
    "wof:placetype":"venue"
},
  "geometry": {"coordinates":[-0.4389959872,38.7440948486],"type":"Point"}
}