{
  "type": "Feature",
  "properties": {
    "iso:country":"ES",
    "sg:address":"Calle de Ramon Y Cajal, 57",
    "sg:city":"Fuensalida",
    "sg:orig_category":"Asociaciones Y Clubs Deportivos",
    "sg:phone":"+34 925 78 51 78",
    "sg:postcode":"45510",
    "sg:province":"Toledo",
    "wof:name":"Serrano Ortiz Victor",
    "wof:placetype":"venue"
},
  "geometry": {"coordinates":[-4.2097592354,40.0518608093],"type":"Point"}
}