{
  "type": "Feature",
  "properties": {
    "iso:country":"ES",
    "sg:address":"Rua Loureiro, 32",
    "sg:city":"Redondela",
    "sg:orig_category":"Estancos",
    "sg:phone":"+34 986 40 15 01",
    "sg:postcode":"36800",
    "sg:province":"Pontevedra",
    "wof:name":"Lago Moreira Ana Belen",
    "wof:placetype":"venue"
},
  "geometry": {"coordinates":[-8.6079187393,42.2861709595],"type":"Point"}
}