{
  "type": "Feature",
  "properties": {
    "addr:full":"Avda Constitucion (de La), 20 Granada Granada 18012",
    "addr:housenumber":"20",
    "addr:postcode":"18012",
    "addr:street":"Avda Constitucion De La",
    "iso:country":"ES",
    "sg:address":"Avda Constitucion (de La), 20",
    "sg:city":"Granada",
    "sg:orig_category":"Aparatos, Material Y Suministros Para Laboratorios",
    "sg:phone":"+34 958 29 09 45",
    "sg:postcode":"18012",
    "sg:province":"Granada",
    "wof:name":"Vitro S.a.",
    "wof:placetype":"venue"
},
  "geometry": {"coordinates":[-3.6061449051,37.1851768494],"type":"Point"}
}