{
  "type": "Feature",
  "properties": {
    "iso:country":"ES",
    "sg:address":"Calle de Toca, 13",
    "sg:city":"Fuenlabrada",
    "sg:orig_category":"Centros Empresariales",
    "sg:phone":"+34 917 77 77 89",
    "sg:postcode":"28947",
    "sg:province":"Madrid",
    "wof:name":"Repliman S.l.",
    "wof:placetype":"venue"
},
  "geometry": {"coordinates":[-3.754308939,40.2660217285],"type":"Point"}
}