{
  "type": "Feature",
  "properties": {
    "addr:full":"Calle de Ondategi, 1 Arenas -areeta Vizcaya 48930",
    "addr:housenumber":"1;areeta",
    "addr:postcode":"48930",
    "addr:street":"Calle De Ondategi",
    "iso:country":"ES",
    "sg:address":"Calle de Ondategi, 1",
    "sg:city":"Arenas -areeta",
    "sg:orig_category":"Arquitectos",
    "sg:phone":"+34 944 64 91 12",
    "sg:postcode":"48930",
    "sg:province":"Vizcaya",
    "wof:name":"De Pedro Perez-salado Rafael",
    "wof:placetype":"venue"
},
  "geometry": {"coordinates":[-3.0103440285,43.3332672119],"type":"Point"}
}