{
  "type": "Feature",
  "properties": {
    "addr:full":"Rua Diputacion, 2 Verin Ourense 32600",
    "addr:housenumber":"2",
    "addr:postcode":"32600",
    "addr:street":"Rua Diputacion",
    "iso:country":"ES",
    "sg:address":"Rua Diputacion, 2",
    "sg:city":"Verin",
    "sg:orig_category":"Zapatos (al Por Menor)",
    "sg:phone":"+34 988 41 20 81",
    "sg:postcode":"32600",
    "sg:province":"Ourense",
    "wof:name":"Fernandez Araujo Elisa",
    "wof:placetype":"venue"
},
  "geometry": {"coordinates":[-7.435324192,41.937335968],"type":"Point"}
}