{
  "type": "Feature",
  "properties": {
    "addr:full":"Carrer de Sant Pere Martir, 41 Barcelona Barcelona 08012",
    "addr:housenumber":"41",
    "addr:postcode":"08012",
    "addr:street":"Carrer De Sant;Martir",
    "iso:country":"ES",
    "sg:address":"Carrer de Sant Pere Martir, 41",
    "sg:city":"Barcelona",
    "sg:classifiers":[
        {
            "category":"Professional",
            "subcategory":"Management & Consulting",
            "type":"Services"
        }
    ],
    "sg:phone":"+34 934 15 22 55",
    "sg:postcode":"08012",
    "sg:province":"Barcelona",
    "sg:tags":[
        "asesor\u00cda",
        "en",
        "marketing"
    ],
    "wof:name":"Delgado Gualino Anna",
    "wof:placetype":"venue"
},
  "geometry": {"coordinates":[2.1567471027,41.3999061584],"type":"Point"}
}