{
  "type": "Feature",
  "properties": {
    "iso:country":"ES",
    "sg:address":"Pol Ind La Rosa, 40",
    "sg:city":"Chauchina",
    "sg:orig_category":"Artes Gr\u00c1ficas, Artes Pl\u00c1sticas (curso)",
    "sg:phone":"+34 958 44 61 73",
    "sg:postcode":"18330",
    "sg:province":"Granada",
    "wof:name":"Aereopirnt Producciones S.l.",
    "wof:placetype":"venue"
},
  "geometry": {"coordinates":[-3.7725400925,37.2014160156],"type":"Point"}
}