{
  "type": "Feature",
  "properties": {
    "addr:full":"Calle de Severo Ochoa, S/n San Jose Rinconada Sevilla 41300",
    "addr:housenumber":"s / n",
    "addr:postcode":"41300",
    "addr:street":"Calle De Severo Ochoa",
    "iso:country":"ES",
    "sg:address":"Calle de Severo Ochoa, S/n",
    "sg:city":"San Jose Rinconada",
    "sg:orig_category":"Transportes Por Carretera: Lotes Completos, Mercanc\u00cdas Diversas",
    "sg:phone":"+34 954 79 31 96",
    "sg:postcode":"41300",
    "sg:province":"Sevilla",
    "wof:name":"Distribuidora Internacional De Alimentacion S.a.",
    "wof:placetype":"venue"
},
  "geometry": {"coordinates":[-5.9531440735,37.4778213501],"type":"Point"}
}