{
  "type": "Feature",
  "properties": {
    "addr:full":"Carrer de Montserrat, 23 Mataro Barcelona 08302",
    "addr:housenumber":"23",
    "addr:postcode":"08302",
    "addr:street":"Carrer De Montserrat",
    "iso:country":"ES",
    "sg:address":"Carrer de Montserrat, 23",
    "sg:city":"Mataro",
    "sg:orig_category":"Doctores En Medicina",
    "sg:phone":"+34 937 90 40 78",
    "sg:postcode":"08302",
    "sg:province":"Barcelona",
    "wof:name":"Barbosa Colomer Jorge",
    "wof:placetype":"venue"
},
  "geometry": {"coordinates":[2.4426651001,41.5375862122],"type":"Point"}
}