{
  "type": "Feature",
  "properties": {
    "addr:full":"Calle de Inocencio Fernandez, 77 Madrid Madrid 28035",
    "addr:housenumber":"77",
    "addr:postcode":"madrid;28035",
    "addr:street":"Calle De Inocencio Fernandez",
    "iso:country":"ES",
    "sg:address":"Calle de Inocencio Fernandez, 77",
    "sg:city":"Madrid",
    "sg:orig_category":"Cine (producci\u00d3n, Realizaci\u00d3n)",
    "sg:phone":"+34 913 73 52 87",
    "sg:postcode":"28035",
    "sg:province":"Madrid",
    "wof:name":"G M Producciones Cine T.v. Video S.a.",
    "wof:placetype":"venue"
},
  "geometry": {"coordinates":[-3.7312378883,40.4774093628],"type":"Point"}
}