{
  "type": "Feature",
  "properties": {
    "addr:full":"Calle de Cava, 38 Fuente Maestre Badajoz 06360",
    "addr:housenumber":"38",
    "addr:postcode":"06360",
    "addr:street":"Calle De Cava",
    "iso:country":"ES",
    "sg:address":"Calle de Cava, 38",
    "sg:city":"Fuente Maestre",
    "sg:orig_category":"Estancos",
    "sg:phone":"+34 924 53 13 81",
    "sg:postcode":"06360",
    "sg:province":"Badajoz",
    "wof:name":"Garcia Chaves Concepcion",
    "wof:placetype":"venue"
},
  "geometry": {"coordinates":[-6.447453022,38.5263633728],"type":"Point"}
}