{
  "type": "Feature",
  "properties": {
    "iso:country":"ES",
    "sg:address":"Ctra. Granada, Km. 0053,0",
    "sg:city":"Puebla Don Fadrique",
    "sg:orig_category":"Negocio De Materiales De Construcci\u00d3n",
    "sg:phone":"+34 958 72 10 21",
    "sg:postcode":"18820",
    "sg:province":"Granada",
    "wof:name":"Garcia Sanchez Victor",
    "wof:placetype":"venue"
},
  "geometry": {"coordinates":[-2.4338490963,37.9588508606],"type":"Point"}
}