{
  "type": "Feature",
  "properties": {
    "addr:full":"Cami Nou De Son Banya, S/n Turo Islas Baleares 07198",
    "addr:housenumber":"s / n",
    "addr:postcode":"07198",
    "addr:street":"Nou De Son Banya",
    "iso:country":"ES",
    "sg:address":"Cami Nou De Son Banya, S/n",
    "sg:city":"Turo",
    "sg:orig_category":"Aeropuertos Y Servicios Aeroportuarios",
    "sg:phone":"+34 971 42 88 46",
    "sg:postcode":"07198",
    "sg:province":"Islas Baleares",
    "wof:name":"Aireuropa Lineas Aereas S.a.",
    "wof:placetype":"venue"
},
  "geometry": {"coordinates":[2.8577105999,39.5341796875],"type":"Point"}
}