{
  "type": "Feature",
  "properties": {
    "addr:full":"Calle de Primitivo Aguado, 7 Iscar Valladolid 47420",
    "addr:housenumber":"7",
    "addr:postcode":"47420",
    "addr:street":"Calle De Primitivo Aguado",
    "iso:country":"ES",
    "sg:address":"Calle de Primitivo Aguado, 7",
    "sg:city":"Iscar",
    "sg:orig_category":"Fabrica, Negocio De Vidrieras, Productos Vidriados Y Espejos",
    "sg:phone":"+34 983 62 03 71",
    "sg:postcode":"47420",
    "sg:province":"Valladolid",
    "wof:name":"Perez Merlo Rufino",
    "wof:placetype":"venue"
},
  "geometry": {"coordinates":[-4.5317440033,41.3594932556],"type":"Point"}
}