{
  "type": "Feature",
  "properties": {
    "iso:country":"ES",
    "sg:address":"Calle de Licenciado Jose Mu\u00d1oz, 17",
    "sg:city":"Lagartera",
    "sg:orig_category":"Carnicer\u00cdas, Carnicer\u00cdas",
    "sg:phone":"+34 925 43 06 12",
    "sg:postcode":"45567",
    "sg:province":"Toledo",
    "wof:name":"Carnicas Igual Suela S.l.",
    "wof:placetype":"venue"
},
  "geometry": {"coordinates":[-5.2007389069,39.9058418274],"type":"Point"}
}