{
  "type": "Feature",
  "properties": {
    "iso:country":"ES",
    "sg:address":"Carrer de Arenys, 108",
    "sg:city":"Barcelona",
    "sg:orig_category":"Farmacias",
    "sg:phone":"+34 934 29 57 14",
    "sg:postcode":"08035",
    "sg:province":"Barcelona",
    "wof:name":"Gardella Roca Neus",
    "wof:placetype":"venue"
},
  "geometry": {"coordinates":[2.1470201015,41.423084259],"type":"Point"}
}