{
  "type": "Feature",
  "properties": {
    "addr:full":"Calle de Amor Hermoso, 51 Madrid Madrid 28026",
    "addr:housenumber":"51",
    "addr:postcode":"madrid;28026",
    "addr:street":"Calle De Amor Hermoso",
    "iso:country":"ES",
    "sg:address":"Calle de Amor Hermoso, 51",
    "sg:city":"Madrid",
    "sg:orig_category":"Quincaller\u00cda (al Por Menor)",
    "sg:phone":"+34 915 00 21 08",
    "sg:postcode":"28026",
    "sg:province":"Madrid",
    "sg:website":"www.desafix.com",
    "wof:name":"Desarrollos Especiales De Sistemas De Anclaje S.a.",
    "wof:placetype":"venue"
},
  "geometry": {"coordinates":[-3.7036979198,40.3843574524],"type":"Point"}
}