{
  "type": "Feature",
  "properties": {
    "addr:full":"Calle de Mariano Barbasan, 11 Zaragoza Zaragoza 50006",
    "addr:housenumber":"11",
    "addr:postcode":"50006",
    "addr:street":"Calle De Mariano Barbasan",
    "iso:country":"ES",
    "sg:address":"Calle de Mariano Barbasan, 11",
    "sg:city":"Zaragoza",
    "sg:orig_category":"Imprenta",
    "sg:phone":"+34 976 55 13 05",
    "sg:postcode":"50006",
    "sg:province":"Zaragoza",
    "wof:name":"Alfonso De Campos Desde 1965 S.l.l.",
    "wof:placetype":"venue"
},
  "geometry": {"coordinates":[-0.8907465935,41.6414146423],"type":"Point"}
}