{
  "type": "Feature",
  "properties": {
    "addr:full":"Avda Mariano Vicen, 6 Soria Soria 42003",
    "addr:housenumber":"6",
    "addr:postcode":"42003",
    "addr:street":"Avda Mariano Vicen",
    "iso:country":"ES",
    "sg:address":"Avda Mariano Vicen, 6",
    "sg:city":"Soria",
    "sg:orig_category":"Pescader\u00cdas (al Por Menor)",
    "sg:phone":"+34 975 23 28 94",
    "sg:postcode":"42003",
    "sg:province":"Soria",
    "wof:name":"El Norte Pescados Y Mariscos",
    "wof:placetype":"venue"
},
  "geometry": {"coordinates":[-2.4700729847,41.7609367371],"type":"Point"}
}