{
  "type": "Feature",
  "properties": {
    "addr:full":"Calle de Jerusalen, 3 Caceres C\u00e1ceres 10005",
    "addr:housenumber":"3",
    "addr:postcode":"10005",
    "addr:street":"Calle De Jerusalen;Ca\u0301Ceres",
    "iso:country":"ES",
    "sg:address":"Calle de Jerusalen, 3",
    "sg:city":"Caceres",
    "sg:orig_category":"Ense\u00d1anza Variada",
    "sg:phone":"+34 927 23 38 41",
    "sg:postcode":"10005",
    "sg:province":"C\u00e1ceres",
    "wof:name":"Castro Jimenez Sonia",
    "wof:placetype":"venue"
},
  "geometry": {"coordinates":[-6.5341739655,39.4675254822],"type":"Point"}
}