{
  "type": "Feature",
  "properties": {
    "iso:country":"ES",
    "sg:address":"Ptge Egara, S/n",
    "sg:city":"Rubi",
    "sg:orig_category":"Goma: Productos De Uso Industrial (fabricaci\u00d3n, Al Por Mayor)",
    "sg:phone":"+34 935 88 56 04",
    "sg:postcode":"08191",
    "sg:province":"Barcelona",
    "wof:name":"Textil Pumarola S.l.",
    "wof:placetype":"venue"
},
  "geometry": {"coordinates":[2.0326499939,41.5011291504],"type":"Point"}
}