{
  "type": "Feature",
  "properties": {
    "iso:country":"ES",
    "sg:address":"Carr Sant Agusti, 50",
    "sg:city":"Felanitx",
    "sg:orig_category":"Fabrica De Cer\u00c1micas",
    "sg:phone":"+34 971 58 02 01",
    "sg:postcode":"07200",
    "sg:province":"Islas Baleares",
    "sg:website":"www.ceramicasmallorca.com",
    "wof:name":"Ceramicas Mallorca S.l",
    "wof:placetype":"venue"
},
  "geometry": {"coordinates":[3.1454389095,39.4753837585],"type":"Point"}
}