{
  "type": "Feature",
  "properties": {
    "addr:full":"Calle de Manuel Maroto, 15 Madrid Madrid 28053",
    "addr:housenumber":"15",
    "addr:postcode":"madrid;28053",
    "addr:street":"Calle De Manuel Maroto",
    "iso:country":"ES",
    "sg:address":"Calle de Manuel Maroto, 15",
    "sg:city":"Madrid",
    "sg:orig_category":"Molduras, Junquillos, Listones Y Molduras Perforadas",
    "sg:phone":"+34 914 77 79 55",
    "sg:postcode":"28053",
    "sg:province":"Madrid",
    "wof:name":"Silva Sosa Olga",
    "wof:placetype":"venue"
},
  "geometry": {"coordinates":[-3.6685678959,40.3885421753],"type":"Point"}
}