{
  "type": "Feature",
  "properties": {
    "iso:country":"ES",
    "sg:address":"Calle de Real, 2",
    "sg:city":"Rus",
    "sg:orig_category":"Bares, Piano",
    "sg:phone":"+34 953 77 03 83",
    "sg:postcode":"23430",
    "sg:province":"Ja\u00e9n",
    "wof:name":"Lopez Perez Miguel",
    "wof:placetype":"venue"
},
  "geometry": {"coordinates":[-3.4621050358,38.04845047],"type":"Point"}
}