{
  "type": "Feature",
  "properties": {
    "iso:country":"ES",
    "sg:address":"Calle de Nueva Zelanda, 67",
    "sg:city":"Madrid",
    "sg:orig_category":"M\u00c9dicos: Radiolog\u00cda (radiodiagn\u00d3stico E Im\u00c1genes En Medicina)",
    "sg:phone":"+34 913 16 58 78",
    "sg:postcode":"28035",
    "sg:province":"Madrid",
    "wof:name":"Ramos Gonzalez Luis",
    "wof:placetype":"venue"
},
  "geometry": {"coordinates":[-3.7285590172,40.4730911255],"type":"Point"}
}