{
  "type": "Feature",
  "properties": {
    "iso:country":"ES",
    "sg:address":"Calle de Progreso, 26",
    "sg:city":"Mazarron",
    "sg:orig_category":"Tintorer\u00cdas, Limpieza En Seco",
    "sg:phone":"+34 968 59 14 71",
    "sg:postcode":"30870",
    "sg:province":"Murcia",
    "wof:name":"Aznar Lopez Francisco",
    "wof:placetype":"venue"
},
  "geometry": {"coordinates":[-1.3126490116,37.5997581482],"type":"Point"}
}