{
  "type": "Feature",
  "properties": {
    "addr:full":"Carrer de Sant Pere, 19 Prat Llobregat Barcelona 08820",
    "addr:housenumber":"19",
    "addr:postcode":"08820",
    "addr:street":"Carrer De Sant Pere;Llobregat",
    "iso:country":"ES",
    "sg:address":"Carrer de Sant Pere, 19",
    "sg:city":"Prat Llobregat",
    "sg:orig_category":"Ferreter\u00cda (diversos)",
    "sg:phone":"+34 933 70 49 02",
    "sg:postcode":"08820",
    "sg:province":"Barcelona",
    "wof:name":"Comercial Del Tirador S.l.",
    "wof:placetype":"venue"
},
  "geometry": {"coordinates":[2.0965890884,41.3269691467],"type":"Point"}
}