{
  "type": "Feature",
  "properties": {
    "addr:full":"Calle de Mayor, 77 Daroca Zaragoza 50360",
    "addr:housenumber":"77",
    "addr:postcode":"50360",
    "addr:street":"Calle De Mayor",
    "iso:country":"ES",
    "sg:address":"Calle de Mayor, 77",
    "sg:city":"Daroca",
    "sg:orig_category":"Peluqueros: De Se\u00d1oras",
    "sg:phone":"+34 976 80 07 10",
    "sg:postcode":"50360",
    "sg:province":"Zaragoza",
    "wof:name":"Lazaro Asensio Elena",
    "wof:placetype":"venue"
},
  "geometry": {"coordinates":[-1.4137370586,41.1140365601],"type":"Point"}
}