{
  "type": "Feature",
  "properties": {
    "addr:full":"Ctra Turis, 4 Chiva Valencia 46370",
    "addr:housenumber":"4",
    "addr:postcode":"46370",
    "addr:street":"Ctra Turis",
    "iso:country":"ES",
    "sg:address":"Ctra Turis, 4",
    "sg:city":"Chiva",
    "sg:orig_category":"Cer\u00c1mica Art\u00cdstica Y Decorativa",
    "sg:phone":"+34 962 52 20 65",
    "sg:postcode":"46370",
    "sg:province":"Valencia",
    "wof:name":"Home & Garden S.l.",
    "wof:placetype":"venue"
},
  "geometry": {"coordinates":[-0.7179690003,39.4728012085],"type":"Point"}
}