{
  "type": "Feature",
  "properties": {
    "iso:country":"ES",
    "sg:address":"Rua Calvo Sotelo, 60",
    "sg:city":"Sarria",
    "sg:orig_category":"Supermercados Y Hipermercados",
    "sg:phone":"+34 982 53 21 54",
    "sg:postcode":"27600",
    "sg:province":"Lugo",
    "wof:name":"Maboareza S.l.",
    "wof:placetype":"venue"
},
  "geometry": {"coordinates":[-7.4147801399,42.7811927795],"type":"Point"}
}