{
  "type": "Feature",
  "properties": {
    "addr:full":"Calle de Camilo Jose Cela, 1 Laguna Duero Valladolid 47140",
    "addr:housenumber":"1",
    "addr:postcode":"47140",
    "addr:street":"Calle De Camilo Jose Cela",
    "iso:country":"ES",
    "sg:address":"Calle de Camilo Jose Cela, 1",
    "sg:city":"Laguna Duero",
    "sg:orig_category":"Arreglo, Reparaci\u00d3n, Piezas Sueltas De Televisi\u00d3n, V\u00cddeo, Hi",
    "sg:phone":"+34 983 54 39 65",
    "sg:postcode":"47140",
    "sg:province":"Valladolid",
    "wof:name":"Seguridad Electronica Digital S.l.",
    "wof:placetype":"venue"
},
  "geometry": {"coordinates":[-4.7235541344,41.5803718567],"type":"Point"}
}