{
  "type": "Feature",
  "properties": {
    "addr:full":"Reboredo, 26 Noalla Ourense 32901",
    "addr:housenumber":"26",
    "addr:postcode":"32901",
    "addr:street":"Reboredo",
    "iso:country":"ES",
    "sg:address":"Reboredo, 26",
    "sg:city":"Noalla",
    "sg:orig_category":"Estancos",
    "sg:phone":"+34 988 23 75 94",
    "sg:postcode":"32901",
    "sg:province":"Ourense",
    "wof:name":"Losada Novoa Carmen",
    "wof:placetype":"venue"
},
  "geometry": {"coordinates":[-7.8334488869,42.2905006409],"type":"Point"}
}