{
  "type": "Feature",
  "properties": {
    "addr:full":"Carrer de Carme, 93 Malgrat Mar Barcelona 08380",
    "addr:housenumber":"93",
    "addr:postcode":"08380",
    "addr:street":"Carrer De Carme",
    "iso:country":"ES",
    "sg:address":"Carrer de Carme, 93",
    "sg:city":"Malgrat Mar",
    "sg:orig_category":"Confecci\u00d3n De Zapatos",
    "sg:phone":"+34 937 65 39 93",
    "sg:postcode":"08380",
    "sg:province":"Barcelona",
    "wof:name":"Xarol S. A.",
    "wof:placetype":"venue"
},
  "geometry": {"coordinates":[2.740434885,41.6454353333],"type":"Point"}
}