{
  "type": "Feature",
  "properties": {
    "addr:full":"Carr Major, 158 Lliria Valencia 46160",
    "addr:housenumber":"158",
    "addr:postcode":"46160",
    "addr:street":"Carr Major",
    "iso:country":"ES",
    "sg:address":"Carr Major, 158",
    "sg:city":"Lliria",
    "sg:orig_category":"Reposter\u00cdas",
    "sg:phone":"+34 962 78 06 53",
    "sg:postcode":"46160",
    "sg:province":"Valencia",
    "wof:name":"Santos Baidal Jose Ramon",
    "wof:placetype":"venue"
},
  "geometry": {"coordinates":[-0.6002209783,39.6277198792],"type":"Point"}
}