{
  "type": "Feature",
  "properties": {
    "addr:full":"Avda Barcelona (de), 10 Cordoba C\u00f3rdoba 14010",
    "addr:housenumber":"10",
    "addr:postcode":"14010",
    "addr:street":"Avda Barcelona De;Co\u0301Rdoba",
    "iso:country":"ES",
    "sg:address":"Avda Barcelona (de), 10",
    "sg:city":"Cordoba",
    "sg:orig_category":"Fabricaci\u00d3n De Telas Y Sedas",
    "sg:phone":"+34 957 26 44 94",
    "sg:postcode":"14010",
    "sg:province":"C\u00f3rdoba",
    "wof:name":"Tejidos Bossi S.l.",
    "wof:placetype":"venue"
},
  "geometry": {"coordinates":[-4.764632225,37.8891639709],"type":"Point"}
}