{
  "type": "Feature",
  "properties": {
    "iso:country":"ES",
    "sg:address":"Rua Alameda (da), 2",
    "sg:city":"Verin",
    "sg:orig_category":"Carnicer\u00cdas, Carnicer\u00cdas",
    "sg:phone":"+34 988 41 10 73",
    "sg:postcode":"32600",
    "sg:province":"Ourense",
    "wof:name":"Payo Boo Rafael",
    "wof:placetype":"venue"
},
  "geometry": {"coordinates":[-7.4407792091,41.9405937195],"type":"Point"}
}