{
  "type": "Feature",
  "properties": {
    "iso:country":"ES",
    "sg:address":"Cra Espinel, 48",
    "sg:city":"Ronda",
    "sg:orig_category":"Confecci\u00d3n De Zapatos",
    "sg:phone":"+34 952 87 19 95",
    "sg:postcode":"29400",
    "sg:province":"M\u00e1laga",
    "wof:name":"Carrillo Garcia Enrique",
    "wof:placetype":"venue"
},
  "geometry": {"coordinates":[-5.1639618874,36.7433013916],"type":"Point"}
}