{
  "type": "Feature",
  "properties": {
    "addr:full":"Calle de Mayor, 3 Cartagena Murcia 30201",
    "addr:housenumber":"3",
    "addr:postcode":"30201",
    "addr:street":"Calle De Mayor",
    "iso:country":"ES",
    "sg:address":"Calle de Mayor, 3",
    "sg:city":"Cartagena",
    "sg:orig_category":"Inmobiliaria (agencias)",
    "sg:phone":"+34 968 12 38 00",
    "sg:postcode":"30201",
    "sg:province":"Murcia",
    "wof:name":"Villanueva 15 S.l.",
    "wof:placetype":"venue"
},
  "geometry": {"coordinates":[-0.9156429768,37.600566864],"type":"Point"}
}