{
  "type": "Feature",
  "properties": {
    "addr:full":"Calle de Canonigo Torres, 16 Torrevieja Alicante 03180",
    "addr:housenumber":"16",
    "addr:postcode":"03180",
    "addr:street":"Calle De Canonigo Torres",
    "iso:country":"ES",
    "sg:address":"Calle de Canonigo Torres, 16",
    "sg:city":"Torrevieja",
    "sg:orig_category":"Abogados",
    "sg:phone":"+34 966 70 71 88",
    "sg:postcode":"03180",
    "sg:province":"Alicante",
    "wof:name":"Club Financiero E Inmobiliario De La Region De Murcia S.l.",
    "wof:placetype":"venue"
},
  "geometry": {"coordinates":[-0.6824898124,37.9762077332],"type":"Point"}
}