{
  "type": "Feature",
  "properties": {
    "iso:country":"ES",
    "sg:address":"Carr Capita Muntaner, 1",
    "sg:city":"Igualada",
    "sg:orig_category":"Agencias Y Agentes Comerciales, Representantes",
    "sg:phone":"+34 938 05 25 57",
    "sg:postcode":"08700",
    "sg:province":"Barcelona",
    "wof:name":"Serrano Marinez Francisco Javier",
    "wof:placetype":"venue"
},
  "geometry": {"coordinates":[1.6238299608,41.5921363831],"type":"Point"}
}