{
  "type": "Feature",
  "properties": {
    "addr:full":"Pl. Santiago, 2 Estella Navarra 31200",
    "addr:housenumber":"2",
    "addr:postcode":"31200",
    "addr:street":"Pl. Santiago",
    "iso:country":"ES",
    "sg:address":"Pl. Santiago, 2",
    "sg:city":"Estella",
    "sg:orig_category":"Art\u00cdculos De Regalo (al Por Menor)",
    "sg:phone":"+34 948 55 33 09",
    "sg:postcode":"31200",
    "sg:province":"Navarra",
    "wof:name":"Juan Lage Elizalde Y Maite Sotes Muguerza S.cv.",
    "wof:placetype":"venue"
},
  "geometry": {"coordinates":[-2.0341150761,42.6723937988],"type":"Point"}
}