{
  "type": "Feature",
  "properties": {
    "addr:full":"Plaz Espa\u00d1a, S/n Pedrola Zaragoza 50690",
    "addr:housenumber":"s / n",
    "addr:postcode":"50690",
    "addr:street":"Plaz Espan\u0303A",
    "iso:country":"ES",
    "sg:address":"Plaz Espa\u00d1a, S/n",
    "sg:city":"Pedrola",
    "sg:orig_category":"Administraciones Regionales, Departamentales Y Locales",
    "sg:phone":"+34 976 61 56 01",
    "sg:postcode":"50690",
    "sg:province":"Zaragoza",
    "wof:name":"Ayuntamiento De Pedrola",
    "wof:placetype":"venue"
},
  "geometry": {"coordinates":[-1.2138190269,41.7904052734],"type":"Point"}
}