{
  "type": "Feature",
  "properties": {
    "addr:full":"Kale Nagusia, 15 Etxarri-aranatz Navarra 31820",
    "addr:housenumber":"15",
    "addr:postcode":"31820",
    "addr:street":"Kale Nagusia",
    "iso:country":"ES",
    "sg:address":"Kale Nagusia, 15",
    "sg:city":"Etxarri-aranatz",
    "sg:orig_category":"Dietistas",
    "sg:phone":"+34 948 46 09 93",
    "sg:postcode":"31820",
    "sg:province":"Navarra",
    "wof:name":"Huarte Lacunza Ana Carmen",
    "wof:placetype":"venue"
},
  "geometry": {"coordinates":[-2.0638840199,42.9061965942],"type":"Point"}
}