{
  "type": "Feature",
  "properties": {
    "iso:country":"ES",
    "sg:address":"Calle de Menendez Pidal, 7",
    "sg:city":"Palencia",
    "sg:orig_category":"Peluquer\u00cdas, Peluquer\u00cda Mixta",
    "sg:phone":"+34 979 72 97 99",
    "sg:postcode":"34004",
    "sg:province":"Palencia",
    "wof:name":"Obispo Atienza Jesus",
    "wof:placetype":"venue"
},
  "geometry": {"coordinates":[-4.5215940475,41.9962463379],"type":"Point"}
}