{
  "type": "Feature",
  "properties": {
    "iso:country":"ES",
    "sg:address":"Carrer de Reina Cristina, 12",
    "sg:city":"Barcelona",
    "sg:orig_category":"Bazares, Art\u00cdculos De Limpieza Y De Cocina (al Por Menor)",
    "sg:phone":"+34 933 19 34 71",
    "sg:postcode":"08003",
    "sg:province":"Barcelona",
    "wof:name":"Moner Llovet Mercedes",
    "wof:placetype":"venue"
},
  "geometry": {"coordinates":[2.1838669777,41.3819541931],"type":"Point"}
}