{
  "type": "Feature",
  "properties": {
    "iso:country":"ES",
    "sg:address":"Calle de San Pedro, S/n",
    "sg:city":"Calasparra",
    "sg:orig_category":"Centros De Educaci\u00d3n Especial",
    "sg:phone":"+34 968 72 07 71",
    "sg:postcode":"30420",
    "sg:province":"Murcia",
    "wof:name":"Colegio Publico Los Molinos",
    "wof:placetype":"venue"
},
  "geometry": {"coordinates":[-1.6939109564,38.2309608459],"type":"Point"}
}