{
  "type": "Feature",
  "properties": {
    "iso:country":"ES",
    "sg:address":"Carrer de Punta Del Cavall (de La), 15",
    "sg:city":"Cap De Salou-nostra Senyora De Nuria",
    "sg:orig_category":"Supermercados Y Hipermercados",
    "sg:phone":"+34 977 37 33 37",
    "sg:postcode":"43840",
    "sg:province":"Tarragona",
    "wof:name":"Creus Belles Jose Manuel",
    "wof:placetype":"venue"
},
  "geometry": {"coordinates":[1.1644699574,41.0600814819],"type":"Point"}
}