{
  "type": "Feature",
  "properties": {
    "addr:full":"Calle de Isabel La Catolica, 1 Aguilas Murcia 30880",
    "addr:housenumber":"1",
    "addr:postcode":"30880",
    "addr:street":"Calle De Isabel La Catolica",
    "iso:country":"ES",
    "sg:address":"Calle de Isabel La Catolica, 1",
    "sg:city":"Aguilas",
    "sg:orig_category":"Institutos De Belleza",
    "sg:phone":"+34 968 41 12 21",
    "sg:postcode":"30880",
    "sg:province":"Murcia",
    "wof:name":"Gilabert Qui\u00f1onero Ana",
    "wof:placetype":"venue"
},
  "geometry": {"coordinates":[-1.5819280148,37.4033737183],"type":"Point"}
}