{
  "type": "Feature",
  "properties": {
    "addr:full":"Calle de Pastor Y Landero, 41 Sevilla Sevilla 41001",
    "addr:housenumber":"41",
    "addr:postcode":"41001",
    "addr:street":"Calle De Pastor Y Landero",
    "iso:country":"ES",
    "sg:address":"Calle de Pastor Y Landero, 41",
    "sg:city":"Sevilla",
    "sg:orig_category":"Asesor\u00cda Fiscal Y Jur\u00cddica",
    "sg:phone":"+34 954 56 34 32",
    "sg:postcode":"41001",
    "sg:province":"Sevilla",
    "wof:name":"Gomez Romero Manuel",
    "wof:placetype":"venue"
},
  "geometry": {"coordinates":[-5.9990987778,37.3874092102],"type":"Point"}
}