{
  "type": "Feature",
  "properties": {
    "addr:full":"Calle de Martinez Vigil, 2 Oviedo Asturias 33010",
    "addr:housenumber":"2",
    "addr:postcode":"33010",
    "addr:street":"Calle De Martinez Vigil",
    "iso:country":"ES",
    "sg:address":"Calle de Martinez Vigil, 2",
    "sg:city":"Oviedo",
    "sg:orig_category":"Administradores De Bienes Y Delegados De Comunidades De Propietarios",
    "sg:phone":"+34 985 21 28 51",
    "sg:postcode":"33010",
    "sg:province":"Asturias",
    "wof:name":"Sanchez Asegurado Bernardino Javier",
    "wof:placetype":"venue"
},
  "geometry": {"coordinates":[-5.8421177864,43.3636207581],"type":"Point"}
}