{
  "type": "Feature",
  "properties": {
    "iso:country":"ES",
    "sg:address":"Calle de Berna (de), 17",
    "sg:city":"Mejorada Campo",
    "sg:orig_category":"Agencias Y Asesores De Publicidad",
    "sg:phone":"+34 916 79 45 12",
    "sg:postcode":"28840",
    "sg:province":"Madrid",
    "wof:name":"Reparmadrid S.l.",
    "wof:placetype":"venue"
},
  "geometry": {"coordinates":[-3.4804973602,40.4000549316],"type":"Point"}
}