{
  "type": "Feature",
  "properties": {
    "addr:full":"Calle de Gremio De Los Caldereros (del), S/n Hontoria Segovia 40195",
    "addr:housenumber":"/ n",
    "addr:postcode":"40195",
    "addr:street":"Calle De Gremio De Los Caldereros Del S",
    "iso:country":"ES",
    "sg:address":"Calle de Gremio De Los Caldereros (del), S/n",
    "sg:city":"Hontoria",
    "sg:orig_category":"Cajas Registradoras, Terminales De Puntos De Venta",
    "sg:phone":"+34 921 43 19 74",
    "sg:postcode":"40195",
    "sg:province":"Segovia",
    "wof:name":"Alberto Gonzalez Maseda S.l.",
    "wof:placetype":"venue"
},
  "geometry": {"coordinates":[-4.108215332,40.9125480652],"type":"Point"}
}