{
  "type": "Feature",
  "properties": {
    "iso:country":"ES",
    "sg:address":"Avda Doctor Meca, 28",
    "sg:city":"Puerto Mazarron",
    "sg:orig_category":"M\u00c9dicos: Estomatolog\u00cda",
    "sg:phone":"+34 968 59 50 16",
    "sg:postcode":"30860",
    "sg:province":"Murcia",
    "wof:name":"Cordero Frias Sunilda Antonia",
    "wof:placetype":"venue"
},
  "geometry": {"coordinates":[-1.2608629465,37.5671958923],"type":"Point"}
}