{
  "type": "Feature",
  "properties": {
    "addr:full":"Poligono Industrial, S/n Mengibar Ja\u00e9n 23620",
    "addr:housenumber":"/ n",
    "addr:postcode":"23620",
    "addr:street":"Industrial S;Mengibar Jae\u0301N",
    "iso:country":"ES",
    "sg:address":"Poligono Industrial, S/n",
    "sg:city":"Mengibar",
    "sg:orig_category":"Armarios Y Cuadros El\u00c9ctricos",
    "sg:phone":"+34 953 37 40 10",
    "sg:postcode":"23620",
    "sg:province":"Ja\u00e9n",
    "wof:name":"Espinola Perez Pedro",
    "wof:placetype":"venue"
},
  "geometry": {"coordinates":[-3.8055789471,37.97265625],"type":"Point"}
}