{
  "type": "Feature",
  "properties": {
    "addr:full":"C/ Reconquesta, 21 Alcoi Alicante 03803",
    "addr:housenumber":"21",
    "addr:postcode":"03803",
    "addr:street":"C / Reconquesta",
    "iso:country":"ES",
    "sg:address":"C/ Reconquesta, 21",
    "sg:city":"Alcoi",
    "sg:orig_category":"Hilaturas, Hilos Y Actividades Relacionadas",
    "sg:phone":"+34 965 33 47 76",
    "sg:postcode":"03803",
    "sg:province":"Alicante",
    "wof:name":"Barrachina Esteve Francisco",
    "wof:placetype":"venue"
},
  "geometry": {"coordinates":[-0.4838120043,38.7015991211],"type":"Point"}
}