{
  "type": "Feature",
  "properties": {
    "iso:country":"ES",
    "sg:address":"Plaz Constitucion, S/n",
    "sg:city":"Cabezas Alambre",
    "sg:orig_category":"Molduras, Junquillos, Listones Y Molduras Perforadas",
    "sg:phone":"+34 920 31 61 23",
    "sg:postcode":"05217",
    "sg:province":"\u00c1vila",
    "wof:name":"Jimenez Lopez Antonio",
    "wof:placetype":"venue"
},
  "geometry": {"coordinates":[-4.8409237862,40.9429206848],"type":"Point"}
}