{
  "type": "Feature",
  "properties": {
    "addr:full":"Luga Ca\u00d1ada Ancha, S/n Ca\u00e7ada Ancha C\u00e1diz 11150",
    "addr:housenumber":"s / n",
    "addr:postcode":"11150",
    "addr:street":"Ancha;Cac\u0327Ada Ancha Ca\u0301Diz",
    "iso:country":"ES",
    "sg:address":"Luga Ca\u00d1ada Ancha, S/n",
    "sg:city":"Ca\u00e7ada Ancha",
    "sg:orig_category":"Muebles, Minoristas",
    "sg:phone":"+34 956 45 11 50",
    "sg:postcode":"11150",
    "sg:province":"C\u00e1diz",
    "wof:name":"Carpinteria Aluminio De Vejer",
    "wof:placetype":"venue"
},
  "geometry": {"coordinates":[-5.9644298553,36.2545776367],"type":"Point"}
}