{
  "type": "Feature",
  "properties": {
    "iso:country":"ES",
    "sg:address":"Calle de Juan Calzada Kalea, 85",
    "sg:city":"Gernika-lumo",
    "sg:orig_category":"Maquinaria Para Industrias Diversas",
    "sg:phone":"+34 946 25 53 76",
    "sg:postcode":"48300",
    "sg:province":"Vizcaya",
    "wof:name":"Jesus Uskola Gabiola",
    "wof:placetype":"venue"
},
  "geometry": {"coordinates":[-2.680314064,43.3078536987],"type":"Point"}
}