{
  "type": "Feature",
  "properties": {
    "iso:country":"ES",
    "sg:address":"Carrer de Trinitat, 22",
    "sg:city":"Sitges",
    "sg:orig_category":"Ense\u00d1anza Variada",
    "sg:phone":"+34 938 94 92 23",
    "sg:postcode":"08870",
    "sg:province":"Barcelona",
    "wof:name":"Boisot  Max Henri Marcel",
    "wof:placetype":"venue"
},
  "geometry": {"coordinates":[1.7948729992,41.2342910767],"type":"Point"}
}