{
  "type": "Feature",
  "properties": {
    "addr:full":"Calle de Castillo, 16 Alconchel De La Estrella Cuenca 16433",
    "addr:housenumber":"16",
    "addr:postcode":"16433",
    "addr:street":"Calle De Castillo",
    "iso:country":"ES",
    "sg:address":"Calle de Castillo, 16",
    "sg:city":"Alconchel De La Estrella",
    "sg:classifiers":[
        {
            "category":"Autos & Motor Vehicles",
            "subcategory":"Automobile Sales",
            "type":"Retail Goods"
        }
    ],
    "sg:phone":"+34 969 19 80 12",
    "sg:postcode":"16433",
    "sg:province":"Cuenca",
    "wof:name":"Autoescuela Zancara S.l",
    "wof:placetype":"venue"
},
  "geometry": {"coordinates":[-2.5751543045,39.7191848755],"type":"Point"}
}