{
  "type": "Feature",
  "properties": {
    "addr:full":"Calle de Lepanto, 11 Guadix Granada 18500",
    "addr:housenumber":"11",
    "addr:postcode":"18500",
    "addr:street":"Calle De Lepanto",
    "iso:country":"ES",
    "sg:address":"Calle de Lepanto, 11",
    "sg:city":"Guadix",
    "sg:orig_category":"Frutas Y Legumbres Secas (al Por Mayor)",
    "sg:phone":"+34 958 66 18 03",
    "sg:postcode":"18500",
    "sg:province":"Granada",
    "wof:name":"Cascales Ehijos S.l.",
    "wof:placetype":"venue"
},
  "geometry": {"coordinates":[-3.1308410168,37.3011703491],"type":"Point"}
}