{
  "type": "Feature",
  "properties": {
    "addr:full":"Plaza Corro, 8 Melgar Fernamental Burgos 09100",
    "addr:housenumber":"8",
    "addr:postcode":"09100",
    "addr:street":"Corro;Fernamental",
    "iso:country":"ES",
    "sg:address":"Plaza Corro, 8",
    "sg:city":"Melgar Fernamental",
    "sg:orig_category":"Perfumer\u00cda (al Por Menor)",
    "sg:phone":"+34 947 37 20 95",
    "sg:postcode":"09100",
    "sg:province":"Burgos",
    "wof:name":"Lozano Esteban Jose Luis",
    "wof:placetype":"venue"
},
  "geometry": {"coordinates":[-4.2460489273,42.4037094116],"type":"Point"}
}