{
  "type": "Feature",
  "properties": {
    "iso:country":"ES",
    "sg:address":"Calle de Sabadell, S/n",
    "sg:city":"Pinto",
    "sg:orig_category":"Molduras, Junquillos, Listones Y Molduras Perforadas",
    "sg:phone":"+34 916 92 19 58",
    "sg:postcode":"28320",
    "sg:province":"Madrid",
    "wof:name":"Bravo Medina Esteban",
    "wof:placetype":"venue"
},
  "geometry": {"coordinates":[-3.7059938908,40.2452468872],"type":"Point"}
}