{
  "type": "Feature",
  "properties": {
    "iso:country":"ES",
    "sg:address":"Carr 25 D'abril, 76",
    "sg:city":"Cullera",
    "sg:orig_category":"Farmacias",
    "sg:phone":"+34 961 72 14 30",
    "sg:postcode":"46400",
    "sg:province":"Valencia",
    "wof:name":"Peiro Alfonso C.b.",
    "wof:placetype":"venue"
},
  "geometry": {"coordinates":[-0.2480420023,39.1633262634],"type":"Point"}
}