{
  "type": "Feature",
  "properties": {
    "iso:country":"ES",
    "sg:address":"Calle de Salud (la), S/n",
    "sg:city":"Selaya",
    "sg:orig_category":"Plomeros",
    "sg:phone":"+34 942 59 03 44",
    "sg:postcode":"39696",
    "sg:province":"Cantabria",
    "wof:name":"Gomez Perez Tomas",
    "wof:placetype":"venue"
},
  "geometry": {"coordinates":[-3.8079121113,43.2155227661],"type":"Point"}
}