{
  "type": "Feature",
  "properties": {
    "addr:full":"Av Estatut, 21 Rubi Barcelona 08191",
    "addr:housenumber":"21",
    "addr:postcode":"08191",
    "addr:street":"Av Estatut",
    "iso:country":"ES",
    "sg:address":"Av Estatut, 21",
    "sg:city":"Rubi",
    "sg:orig_category":"Venta, Colocaci\u00d3n, Reparaci\u00d3n De Parabrisas, Techos Descapotables",
    "sg:phone":"+34 936 99 23 16",
    "sg:postcode":"08191",
    "sg:province":"Barcelona",
    "wof:name":"Alboar S. A.",
    "wof:placetype":"venue"
},
  "geometry": {"coordinates":[2.0399982929,41.4873771667],"type":"Point"}
}