{
  "type": "Feature",
  "properties": {
    "addr:full":"Calle de Censo, 6 Madrid Madrid 28041",
    "addr:housenumber":"6",
    "addr:postcode":"28041",
    "addr:street":"Calle De Censo",
    "iso:country":"ES",
    "sg:address":"Calle de Censo, 6",
    "sg:city":"Madrid",
    "sg:orig_category":"Organizaciones Internacionales",
    "sg:phone":"+34 913 41 56 04",
    "sg:postcode":"28041",
    "sg:province":"Madrid",
    "wof:name":"Asociacion Colectivo La Calle",
    "wof:placetype":"venue"
},
  "geometry": {"coordinates":[-3.7052598,40.3679924011],"type":"Point"}
}