{
  "type": "Feature",
  "properties": {
    "iso:country":"ES",
    "sg:address":"Calle de Artibai, 5",
    "sg:city":"Markina-xemein",
    "sg:orig_category":"Alquiler De V\u00cddeo",
    "sg:phone":"+34 946 16 94 11",
    "sg:postcode":"48270",
    "sg:province":"Vizcaya",
    "wof:name":"Agirregomezkorta Zabala Itsaso",
    "wof:placetype":"venue"
},
  "geometry": {"coordinates":[-2.4974033833,43.2690620422],"type":"Point"}
}