{
  "type": "Feature",
  "properties": {
    "iso:country":"ES",
    "sg:address":"Calle de Juan Puertes, 17",
    "sg:city":"Alfafar",
    "sg:orig_category":"Agencias Y Agentes Comerciales, Representantes",
    "sg:phone":"+34 963 75 94 72",
    "sg:postcode":"46910",
    "sg:province":"Valencia",
    "wof:name":"Tarazona Folch Antonio",
    "wof:placetype":"venue"
},
  "geometry": {"coordinates":[-0.3883770108,39.4232406616],"type":"Point"}
}