{
  "type": "Feature",
  "properties": {
    "iso:country":"ES",
    "sg:address":"Carrer de Jacint Verdaguer, 17",
    "sg:city":"Vic",
    "sg:orig_category":"Confecci\u00d3n De Trajes Para Se\u00d1oras",
    "sg:phone":"+34 938 85 44 04",
    "sg:postcode":"08500",
    "sg:province":"Barcelona",
    "wof:name":"M.-pretty S.l.",
    "wof:placetype":"venue"
},
  "geometry": {"coordinates":[2.2517220974,41.9304885864],"type":"Point"}
}