{
  "type": "Feature",
  "properties": {
    "addr:full":"Calle de Hoya (la), 43 Puerto Cruz Santa Cruz De Tenerife 38400",
    "addr:housenumber":"43",
    "addr:postcode":"38400",
    "addr:street":"Calle De Hoya La;Puerto Cruz",
    "iso:country":"ES",
    "sg:address":"Calle de Hoya (la), 43",
    "sg:city":"Puerto Cruz",
    "sg:orig_category":"Complementos De Vestir (al Por Menor)",
    "sg:phone":"+34 922 38 25 06",
    "sg:postcode":"38400",
    "sg:province":"Santa Cruz De Tenerife",
    "wof:name":"Mohamed  Aanan",
    "wof:placetype":"venue"
},
  "geometry": {"coordinates":[9.0760097504,52.7750091553],"type":"Point"}
}