{
  "type": "Feature",
  "properties": {
    "iso:country":"ES",
    "sg:address":"Calle de Colombia, 25",
    "sg:city":"Madrid",
    "sg:orig_category":"Inform\u00c1tica, Ofim\u00c1tica (estudios, Asesor\u00cda, Ingenier\u00cda, Formaci\u00d3n)",
    "sg:phone":"+34 913 45 52 11",
    "sg:postcode":"28016",
    "sg:province":"Madrid",
    "wof:name":"Oliva De Miguel Via\u00f1a Y Maria Cristina Altozano Gonzalez Cb",
    "wof:placetype":"venue"
},
  "geometry": {"coordinates":[-3.6738820076,40.4570388794],"type":"Point"}
}