{
  "type": "Feature",
  "properties": {
    "iso:country":"ES",
    "sg:address":"Tierras De San Pedro, S/n",
    "sg:city":"Sorriba",
    "sg:orig_category":"Hormigonados",
    "sg:phone":"+34 987 70 06 25",
    "sg:postcode":"24815",
    "sg:province":"Le\u00f3n",
    "wof:name":"Hormigones Robles S.l.",
    "wof:placetype":"venue"
},
  "geometry": {"coordinates":[-5.1262340546,42.7875862122],"type":"Point"}
}