{
  "type": "Feature",
  "properties": {
    "addr:full":"Ptda Madrigueres Sud (les), 64 Denia Alicante 03700",
    "addr:housenumber":"64",
    "addr:postcode":"03700",
    "addr:street":"Ptda Madrigueres Sud Les",
    "iso:country":"ES",
    "sg:address":"Ptda Madrigueres Sud (les), 64",
    "sg:city":"Denia",
    "sg:orig_category":"Asesor\u00cda Para La Organizaci\u00d3n Y Gesti\u00d3n Del Transporte",
    "sg:phone":"+34 966 42 61 83",
    "sg:postcode":"03700",
    "sg:province":"Alicante",
    "sg:website":"www.nacex.es",
    "wof:name":"Barreno  Edwin Geovanny",
    "wof:placetype":"venue"
},
  "geometry": {"coordinates":[0.0857219994,38.8364982605],"type":"Point"}
}