{
  "type": "Feature",
  "properties": {
    "iso:country":"ES",
    "sg:address":"Calle de Gravina, 9",
    "sg:city":"Huelva",
    "sg:orig_category":"M\u00c9dicos: Cardiolog\u00cda Y Afecciones Cardiovasculares",
    "sg:phone":"+34 959 24 65 98",
    "sg:postcode":"21001",
    "sg:province":"Huelva",
    "wof:name":"Motero Carrasco Juan",
    "wof:placetype":"venue"
},
  "geometry": {"coordinates":[-6.9554729462,37.2575912476],"type":"Point"}
}