{
  "type": "Feature",
  "properties": {
    "iso:country":"ES",
    "sg:address":"Calle de Palmeral (el), 25",
    "sg:city":"Mas Dels Frares",
    "sg:orig_category":"Promotores Constructores",
    "sg:phone":"+34 964 39 51 72",
    "sg:postcode":"12560",
    "sg:province":"Castell\u00f3n",
    "wof:name":"Enlucidos M.m. S.l.",
    "wof:placetype":"venue"
},
  "geometry": {"coordinates":[0.0590550005,40.0523414612],"type":"Point"}
}