{
  "type": "Feature",
  "properties": {
    "addr:full":"Calle de Tomillar, S/n Valquigoso Madrid 28694",
    "addr:housenumber":"s / n",
    "addr:postcode":"28694",
    "addr:street":"Calle De Tomillar",
    "iso:country":"ES",
    "sg:address":"Calle de Tomillar, S/n",
    "sg:city":"Valquigoso",
    "sg:orig_category":"Cerrajer\u00cda, Ferrallista",
    "sg:phone":"+34 918 65 26 24",
    "sg:postcode":"28694",
    "sg:province":"Madrid",
    "wof:name":"Cerrajeria Dosas S.l.l",
    "wof:placetype":"venue"
},
  "geometry": {"coordinates":[-4.1978168488,40.3967475891],"type":"Point"}
}