{
  "type": "Feature",
  "properties": {
    "addr:full":"Calle de Constitucion (de La), 60 Fuenlabrada Madrid 28946",
    "addr:housenumber":"60",
    "addr:postcode":"28946",
    "addr:street":"Calle De Constitucion De La",
    "iso:country":"ES",
    "sg:address":"Calle de Constitucion (de La), 60",
    "sg:city":"Fuenlabrada",
    "sg:orig_category":"Reparaciones Y Remolcado De Veh\u00cdculos",
    "sg:phone":"+34 916 09 89 14",
    "sg:postcode":"28946",
    "sg:province":"Madrid",
    "wof:name":"Gruas Amador S.l.",
    "wof:placetype":"venue"
},
  "geometry": {"coordinates":[-3.7862446308,40.281124115],"type":"Point"}
}