{
  "type": "Feature",
  "properties": {
    "iso:country":"ES",
    "sg:address":"Calle de Antonio Millon, 10",
    "sg:city":"Nerja",
    "sg:orig_category":"Inmobiliaria (agencias)",
    "sg:phone":"+34 952 52 72 01",
    "sg:postcode":"29780",
    "sg:province":"M\u00e1laga",
    "sg:website":"www.villasolrealestate.com",
    "wof:name":"Villasol Real Estate S.l.",
    "wof:placetype":"venue"
},
  "geometry": {"coordinates":[-3.8814809322,36.7450370789],"type":"Point"}
}