{
  "type": "Feature",
  "properties": {
    "addr:full":"Carr Prat De La Riba, 18 Bellver Cerdanya Lleida 25720",
    "addr:housenumber":"18",
    "addr:postcode":"25720",
    "addr:street":"Carr Prat De La Riba",
    "iso:country":"ES",
    "sg:address":"Carr Prat De La Riba, 18",
    "sg:city":"Bellver Cerdanya",
    "sg:orig_category":"Asilos De Ancianos. Centros Privados",
    "sg:phone":"+34 973 51 07 39",
    "sg:postcode":"25720",
    "sg:province":"Lleida",
    "wof:name":"Fundacion Publica De Servicios San Roc",
    "wof:placetype":"venue"
},
  "geometry": {"coordinates":[1.7763129473,42.371257782],"type":"Point"}
}