{
  "type": "Feature",
  "properties": {
    "addr:full":"Av Jaume I, 315 Terrassa Barcelona 08226",
    "addr:housenumber":"315",
    "addr:postcode":"08226",
    "addr:street":"Av Jaume I",
    "iso:country":"ES",
    "sg:address":"Av Jaume I, 315",
    "sg:city":"Terrassa",
    "sg:orig_category":"Molduras, Junquillos, Listones Y Molduras Perforadas",
    "sg:phone":"+34 937 34 23 85",
    "sg:postcode":"08226",
    "sg:province":"Barcelona",
    "wof:name":"Mantenimiento Y Servicios Bernal S.l.",
    "wof:placetype":"venue"
},
  "geometry": {"coordinates":[2.018862009,41.5738716125],"type":"Point"}
}