{
  "type": "Feature",
  "properties": {
    "addr:full":"Calle de Juan Bautista De La Concepcion, 10 Alcazar S. Juan Ciudad Real 13600",
    "addr:housenumber":"10",
    "addr:postcode":"13600",
    "addr:street":"Calle De Juan Bautista De La Concepcion;Alcazar S. Juan Ciudad Real",
    "iso:country":"ES",
    "sg:address":"Calle de Juan Bautista De La Concepcion, 10",
    "sg:city":"Alcazar S. Juan",
    "sg:orig_category":"Peluquer\u00cdas, Peluquer\u00cda Mixta",
    "sg:phone":"+34 926 54 38 96",
    "sg:postcode":"13600",
    "sg:province":"Ciudad Real",
    "wof:name":"Reflejos C.b.",
    "wof:placetype":"venue"
},
  "geometry": {"coordinates":[-3.2177290916,39.3949890137],"type":"Point"}
}