{
  "type": "Feature",
  "properties": {
    "iso:country":"ES",
    "sg:address":"Calle de Don Quijote, 1",
    "sg:city":"Alcorcon",
    "sg:orig_category":"Molduras, Junquillos, Listones Y Molduras Perforadas",
    "sg:phone":"+34 916 44 01 94",
    "sg:postcode":"28922",
    "sg:province":"Madrid",
    "wof:name":"Videojuegos Recreativos 2000 S.l.",
    "wof:placetype":"venue"
},
  "geometry": {"coordinates":[-3.8287370205,40.3404846191],"type":"Point"}
}