{
  "type": "Feature",
  "properties": {
    "iso:country":"ES",
    "sg:address":"Avda Pero Mingo (de), 32",
    "sg:city":"Sevilla",
    "sg:orig_category":"Ropa Para Se\u00d1oras (al Por Menor)",
    "sg:phone":"+34 954 25 12 15",
    "sg:postcode":"41016",
    "sg:province":"Sevilla",
    "wof:name":"Santiago Toro Maria Del Pilar",
    "wof:placetype":"venue"
},
  "geometry": {"coordinates":[-5.9107217789,37.3858375549],"type":"Point"}
}