{
  "type": "Feature",
  "properties": {
    "addr:full":"Pol Ind Cruz De Piedra, 44 Arjona Ja\u00e9n 23760",
    "addr:housenumber":"44",
    "addr:postcode":"23760",
    "addr:street":"Piedra;Jae\u0301N",
    "iso:country":"ES",
    "sg:address":"Pol Ind Cruz De Piedra, 44",
    "sg:city":"Arjona",
    "sg:orig_category":"Fabricaci\u00d3n De Muebles",
    "sg:phone":"+34 953 51 86 41",
    "sg:postcode":"23760",
    "sg:province":"Ja\u00e9n",
    "wof:name":"Framar Muebles S.l.",
    "wof:placetype":"venue"
},
  "geometry": {"coordinates":[-4.0609068871,37.9375991821],"type":"Point"}
}