{
  "type": "Feature",
  "properties": {
    "addr:full":"Avda Madrid (de), 32 Coslada Madrid 28820",
    "addr:housenumber":"32",
    "addr:postcode":"28820",
    "addr:street":"Avda Madrid De",
    "iso:country":"ES",
    "sg:address":"Avda Madrid (de), 32",
    "sg:city":"Coslada",
    "sg:orig_category":"Centros Comerciales Y Grandes Tiendas",
    "sg:phone":"+34 916 72 51 01",
    "sg:postcode":"28820",
    "sg:province":"Madrid",
    "wof:name":"Ren  Xuxan",
    "wof:placetype":"venue"
},
  "geometry": {"coordinates":[-3.5420811176,40.419128418],"type":"Point"}
}