{
  "type": "Feature",
  "properties": {
    "addr:full":"Fragua(p I Tres Hermanas), 22 Aspe Alicante 03680",
    "addr:housenumber":"22",
    "addr:postcode":"03680",
    "addr:street":"P;Tres Hermanas",
    "iso:country":"ES",
    "sg:address":"Fragua(p I Tres Hermanas), 22",
    "sg:city":"Aspe",
    "sg:orig_category":"Zapater\u00cdas",
    "sg:phone":"+34 965 49 50 37",
    "sg:postcode":"03680",
    "sg:province":"Alicante",
    "wof:name":"Stylo Tacon S.l.",
    "wof:placetype":"venue"
},
  "geometry": {"coordinates":[-0.7675589919,38.3242416382],"type":"Point"}
}