{
  "type": "Feature",
  "properties": {
    "addr:full":"Avda Serrana (la), 5 Jerez De La Frontera C\u00e1diz 11404",
    "addr:housenumber":"5",
    "addr:postcode":"11404",
    "addr:street":"Avda Serrana La",
    "iso:country":"ES",
    "sg:address":"Avda Serrana (la), 5",
    "sg:city":"Jerez De La Frontera",
    "sg:orig_category":"Institutos De Belleza",
    "sg:phone":"+34 956 18 51 53",
    "sg:postcode":"11404",
    "sg:province":"C\u00e1diz",
    "wof:name":"Burgos Herrero Pilar",
    "wof:placetype":"venue"
},
  "geometry": {"coordinates":[-6.1439290047,36.695098877],"type":"Point"}
}