{
  "type": "Feature",
  "properties": {
    "iso:country":"ES",
    "sg:address":"C/ Federico Garcia Lorca, 129",
    "sg:city":"Elche",
    "sg:orig_category":"Veh\u00cdculos De Ocasi\u00d3n",
    "sg:phone":"+34 966 63 30 33",
    "sg:postcode":"03204",
    "sg:province":"Alicante",
    "wof:name":"Navas Medina Manuel",
    "wof:placetype":"venue"
},
  "geometry": {"coordinates":[-0.7033039927,38.2543067932],"type":"Point"}
}