{
  "type": "Feature",
  "properties": {
    "iso:country":"ES",
    "sg:address":"Afueras, S/n",
    "sg:city":"Navaconcejo",
    "sg:orig_category":"Sales (al Por Mayor)",
    "sg:phone":"+34 927 17 31 07",
    "sg:postcode":"10613",
    "sg:province":"C\u00e1ceres",
    "wof:name":"Marcos Barbero S.l",
    "wof:placetype":"venue"
},
  "geometry": {"coordinates":[-5.8300590515,40.1774253845],"type":"Point"}
}