{
  "type": "Feature",
  "properties": {
    "addr:full":"Calle de Capuchinos, 7 Carmen Murcia 30002",
    "addr:housenumber":"7",
    "addr:postcode":"30002",
    "addr:street":"Calle De Capuchinos",
    "iso:country":"ES",
    "sg:address":"Calle de Capuchinos, 7",
    "sg:city":"Carmen",
    "sg:orig_category":"Quincaller\u00cda (fabricaci\u00d3n)",
    "sg:phone":"+34 968 25 27 49",
    "sg:postcode":"30002",
    "sg:province":"Murcia",
    "wof:name":"Ingenieria Contra Incendios Y Extintores S.l.",
    "wof:placetype":"venue"
},
  "geometry": {"coordinates":[-1.1298867464,37.9834747314],"type":"Point"}
}