{
  "type": "Feature",
  "properties": {
    "iso:country":"ES",
    "sg:address":"Av Barbera, 209",
    "sg:city":"Sabadell",
    "sg:orig_category":"Inmobiliaria (agencias)",
    "sg:phone":"+34 937 20 55 10",
    "sg:postcode":"08203",
    "sg:province":"Barcelona",
    "wof:name":"Fincas Corral Vetton S.l.",
    "wof:placetype":"venue"
},
  "geometry": {"coordinates":[2.115170002,41.5340385437],"type":"Point"}
}