{
  "type": "Feature",
  "properties": {
    "iso:country":"ES",
    "sg:address":"Elduain Sakabanatua, S/n",
    "sg:city":"Elduain",
    "sg:orig_category":"Empresas De Electricidad En General",
    "sg:phone":"+34 943 58 08 70",
    "sg:postcode":"20493",
    "sg:province":"Guip\u00f9zcoa",
    "wof:name":"Elektra Olloqui S.a.",
    "wof:placetype":"venue"
},
  "geometry": {"coordinates":[-2.0266590118,43.1455039978],"type":"Point"}
}