{
  "type": "Feature",
  "properties": {
    "addr:full":"Carrer de Secretari Coloma, 129 Barcelona Barcelona 08024",
    "addr:housenumber":"129",
    "addr:postcode":"08024",
    "addr:street":"Carrer De Secretari Coloma",
    "iso:country":"ES",
    "sg:address":"Carrer de Secretari Coloma, 129",
    "sg:city":"Barcelona",
    "sg:orig_category":"Industria Qu\u00cdmica",
    "sg:phone":"+34 932 84 19 15",
    "sg:postcode":"08024",
    "sg:province":"Barcelona",
    "wof:name":"Gaillard Serra Antonio",
    "wof:placetype":"venue"
},
  "geometry": {"coordinates":[2.1602780819,41.4118499756],"type":"Point"}
}