{
  "type": "Feature",
  "properties": {
    "iso:country":"ES",
    "sg:address":"Calle de Pedro Duro, 16",
    "sg:city":"Gijon",
    "sg:orig_category":"Abogados",
    "sg:phone":"+34 985 34 26 37",
    "sg:postcode":"33206",
    "sg:province":"Asturias",
    "wof:name":"Menendez Nu\u00f1ez Y Pe\u00f1a C.b",
    "wof:placetype":"venue"
},
  "geometry": {"coordinates":[-5.6664514542,43.5411376953],"type":"Point"}
}