{
  "type": "Feature",
  "properties": {
    "iso:country":"ES",
    "sg:address":"Avenida De La Fuente, 20",
    "sg:city":"Zafra",
    "sg:orig_category":"Audiovisuales (producci\u00d3n, Edici\u00d3n, Realizaci\u00d3n)",
    "sg:phone":"+34 924 56 30 48",
    "sg:postcode":"06300",
    "sg:province":"Badajoz",
    "wof:name":"Zafra Producciones Audiovisuales S.l.",
    "wof:placetype":"venue"
},
  "geometry": {"coordinates":[-6.4195818901,38.4280281067],"type":"Point"}
}