{
  "type": "Feature",
  "properties": {
    "addr:full":"Ctra Alcala-dos Hermanas, Km. 0006,0 Alcala Guadaira Sevilla 41500",
    "addr:postcode":"41500",
    "addr:street":"Ctra Alcala-Dos Hermanas Km. 0006,0",
    "iso:country":"ES",
    "sg:address":"Ctra Alcala-dos Hermanas, Km. 0006,0",
    "sg:city":"Alcala Guadaira",
    "sg:orig_category":"Promotores Constructores",
    "sg:phone":"+34 955 66 19 53",
    "sg:postcode":"41500",
    "sg:province":"Sevilla",
    "wof:name":"Fcc Construccion S.a.",
    "wof:placetype":"venue"
},
  "geometry": {"coordinates":[-5.8398590088,37.3383140564],"type":"Point"}
}