{
  "type": "Feature",
  "properties": {
    "addr:full":"Calle de Doctor Gost, 5 Valverde Santa Cruz De Tenerife 38910",
    "addr:housenumber":"5",
    "addr:postcode":"38910",
    "addr:street":"Calle De Doctor Gost",
    "iso:country":"ES",
    "sg:address":"Calle de Doctor Gost, 5",
    "sg:city":"Valverde",
    "sg:orig_category":"Agencias De Viajes",
    "sg:phone":"+34 922 55 04 84",
    "sg:postcode":"38910",
    "sg:province":"Santa Cruz De Tenerife",
    "wof:name":"Viajes El Hierro Islas S.l.l.",
    "wof:placetype":"venue"
},
  "geometry": {"coordinates":[-17.8970718384,27.8238143921],"type":"Point"}
}