{
  "type": "Feature",
  "properties": {
    "addr:full":"Plaz Sardoy, 6 San Lorenzo Murcia 30003",
    "addr:housenumber":"6",
    "addr:postcode":"30003",
    "addr:street":"Plaz Sardoy",
    "iso:country":"ES",
    "sg:address":"Plaz Sardoy, 6",
    "sg:city":"San Lorenzo",
    "sg:orig_category":"Comercio De Mobiliario De Oficina",
    "sg:phone":"+34 968 23 96 02",
    "sg:postcode":"30003",
    "sg:province":"Murcia",
    "wof:name":"Cotecna",
    "wof:placetype":"venue"
},
  "geometry": {"coordinates":[-1.1260540485,37.9870758057],"type":"Point"}
}