{
  "type": "Feature",
  "properties": {
    "addr:full":"Calle de California, 6 Palmas De Gran Canaria Las Palmas 35010",
    "addr:postcode":"35010",
    "addr:street":"Calle De California",
    "iso:country":"ES",
    "sg:address":"Calle de California, 6",
    "sg:city":"Palmas De Gran Canaria",
    "sg:orig_category":"Bazares, Art\u00cdculos De Limpieza Y De Cocina (al Por Menor)",
    "sg:phone":"+34 928 22 38 22",
    "sg:postcode":"35010",
    "sg:province":"Las Palmas",
    "wof:name":"Barrera Romera Luisa",
    "wof:placetype":"venue"
},
  "geometry": {"coordinates":[-15.4433479309,28.1322860718],"type":"Point"}
}