{
  "type": "Feature",
  "properties": {
    "addr:full":"Calle de Arriba, 25 Tejina Santa Cruz De Tenerife 38260",
    "addr:housenumber":"25",
    "addr:postcode":"38260",
    "addr:street":"Calle De Arriba",
    "iso:country":"ES",
    "sg:address":"Calle de Arriba, 25",
    "sg:city":"Tejina",
    "sg:orig_category":"Ropa Para Se\u00d1oras Y Caballeros (al Por Menor)",
    "sg:phone":"+34 922 54 04 87",
    "sg:postcode":"38260",
    "sg:province":"Santa Cruz De Tenerife",
    "wof:name":"Agrotejina S.l.",
    "wof:placetype":"venue"
},
  "geometry": {"coordinates":[-16.3600559235,28.5334510803],"type":"Point"}
}