{
  "type": "Feature",
  "properties": {
    "iso:country":"ES",
    "sg:address":"Calle de Verdu Diana, 24",
    "sg:city":"Requena",
    "sg:orig_category":"Obras Y Organismos Sociales",
    "sg:phone":"+34 962 30 11 33",
    "sg:postcode":"46340",
    "sg:province":"Valencia",
    "wof:name":"Hogar De Ancianos En Requena Hermanitas Ancianos Desamparados Provincia Sagrado Corazon",
    "wof:placetype":"venue"
},
  "geometry": {"coordinates":[-1.0971280336,39.4861412048],"type":"Point"}
}