{
  "type": "Feature",
  "properties": {
    "addr:full":"Major, 13 Vandellos Tarragona 43891",
    "addr:housenumber":"13",
    "addr:postcode":"43891",
    "addr:street":"Major",
    "iso:country":"ES",
    "sg:address":"Major, 13",
    "sg:city":"Vandellos",
    "sg:orig_category":"Iglesia Cat\u00d3lica",
    "sg:phone":"+34 977 82 40 18",
    "sg:postcode":"43891",
    "sg:province":"Tarragona",
    "wof:name":"Bisbat De Tortosa",
    "wof:placetype":"venue"
},
  "geometry": {"coordinates":[0.8311949968,41.0200386047],"type":"Point"}
}