{
  "type": "Feature",
  "properties": {
    "iso:country":"ES",
    "sg:address":"Rua San Sebastian, S/n",
    "sg:city":"Porri\u00f1o",
    "sg:orig_category":"Agentes Generales De Seguros",
    "sg:phone":"+34 986 33 04 10",
    "sg:postcode":"36400",
    "sg:province":"Pontevedra",
    "wof:name":"Santa Lucia S.a. Compa\u00d1ia De Seguros",
    "wof:placetype":"venue"
},
  "geometry": {"coordinates":[-8.6207494736,42.1552085876],"type":"Point"}
}