{
  "type": "Feature",
  "properties": {
    "iso:country":"ES",
    "sg:address":"Calle de San Francisco, 58",
    "sg:city":"Teruel",
    "sg:orig_category":"Asesor\u00cda Sobre Comunicaci\u00d3n De Empresas",
    "sg:phone":"+34 978 61 78 71",
    "sg:postcode":"44001",
    "sg:province":"Teruel",
    "wof:name":"Viesga S.a.l.",
    "wof:placetype":"venue"
},
  "geometry": {"coordinates":[-1.1104749441,40.3434715271],"type":"Point"}
}