{
  "type": "Feature",
  "properties": {
    "addr:full":"Calle de Andres Gaos, 29 Coru\u00d1a La Coru\u00f1a 15010",
    "addr:housenumber":"29",
    "addr:postcode":"15010",
    "addr:street":"Calle De Andres Gaos;Corun\u0303A",
    "iso:country":"ES",
    "sg:address":"Calle de Andres Gaos, 29",
    "sg:city":"Coru\u00d1a",
    "sg:orig_category":"Muebles, Minoristas",
    "sg:phone":"+34 981 26 37 81",
    "sg:postcode":"15010",
    "sg:province":"La Coru\u00f1a",
    "wof:name":"Perez Fernandez Jose",
    "wof:placetype":"venue"
},
  "geometry": {"coordinates":[-8.419046402,43.360118866],"type":"Point"}
}