{
  "type": "Feature",
  "properties": {
    "iso:country":"ES",
    "sg:address":"Ctra. Poza Sal, 79",
    "sg:city":"Burgos",
    "sg:orig_category":"Carnicer\u00cdas, Carnicer\u00cdas",
    "sg:phone":"+34 947 47 19 14",
    "sg:postcode":"09007",
    "sg:province":"Burgos",
    "wof:name":"Avila Hermanos S. A.",
    "wof:placetype":"venue"
},
  "geometry": {"coordinates":[-3.5867347717,42.4212799072],"type":"Point"}
}