{
  "type": "Feature",
  "properties": {
    "iso:country":"ES",
    "sg:address":"Carr Sant Joan Baptista La Salle, 28",
    "sg:city":"Girona",
    "sg:orig_category":"Peluqueros: De Se\u00d1oras",
    "sg:phone":"+34 972 20 24 12",
    "sg:postcode":"17002",
    "sg:province":"Girona",
    "wof:name":"Fortia Cana Yolanda",
    "wof:placetype":"venue"
},
  "geometry": {"coordinates":[2.8194069862,41.9779167175],"type":"Point"}
}