{
  "type": "Feature",
  "properties": {
    "iso:country":"ES",
    "sg:address":"Calle de Gomez Becerra, 14",
    "sg:city":"Caceres",
    "sg:orig_category":"Bazares, Art\u00cdculos De Limpieza Y De Cocina (al Por Menor)",
    "sg:phone":"+34 927 22 31 18",
    "sg:postcode":"10001",
    "sg:province":"C\u00e1ceres",
    "sg:website":"paginasamarillas.es",
    "wof:name":"Lazaro Galan Isabel Maria",
    "wof:placetype":"venue"
},
  "geometry": {"coordinates":[-6.3803834915,39.4693870544],"type":"Point"}
}