{
  "type": "Feature",
  "properties": {
    "addr:full":"Avda Almogavares (de), 43 Cordoba C\u00f3rdoba 14006",
    "addr:housenumber":"43",
    "addr:postcode":"14006",
    "addr:street":"Avda Almogavares De;Co\u0301Rdoba",
    "iso:country":"ES",
    "sg:address":"Avda Almogavares (de), 43",
    "sg:city":"Cordoba",
    "sg:orig_category":"Peluquer\u00cdas, Peluquer\u00cda Mixta",
    "sg:phone":"+34 957 28 04 27",
    "sg:postcode":"14006",
    "sg:province":"C\u00f3rdoba",
    "sg:website":"www.spejos.es",
    "wof:name":"Hernanz Color S.l.",
    "wof:placetype":"venue"
},
  "geometry": {"coordinates":[-4.7795639038,37.8982429504],"type":"Point"}
}