{
  "type": "Feature",
  "properties": {
    "iso:country":"ES",
    "sg:address":"Calle de Marcos Pe\u00d1a Royo, 27",
    "sg:city":"Oviedo",
    "sg:orig_category":"Animales (al Por Menor)",
    "sg:phone":"+34 985 25 38 38",
    "sg:postcode":"33013",
    "sg:province":"Asturias",
    "wof:name":"Martinez Fernandez Candido",
    "wof:placetype":"venue"
},
  "geometry": {"coordinates":[-5.8653302193,43.3625640869],"type":"Point"}
}