{
  "type": "Feature",
  "properties": {
    "addr:full":"Calle de Buensuceso, 1 Granada Granada 18002",
    "addr:housenumber":"1",
    "addr:postcode":"18002",
    "addr:street":"Calle De Buensuceso",
    "iso:country":"ES",
    "sg:address":"Calle de Buensuceso, 1",
    "sg:city":"Granada",
    "sg:orig_category":"Asesor\u00cda Fiscal Y Jur\u00cddica",
    "sg:phone":"+34 958 25 62 59",
    "sg:postcode":"18002",
    "sg:province":"Granada",
    "wof:name":"Crg Consultores Tributarios Financieros Y Mercantiles S.l.",
    "wof:placetype":"venue"
},
  "geometry": {"coordinates":[-3.6019220352,37.175655365],"type":"Point"}
}