{
  "type": "Feature",
  "properties": {
    "addr:full":"Carrer de Sant Joan, 7 Vilafranca Penedes Barcelona 08720",
    "addr:housenumber":"7",
    "addr:postcode":"08720",
    "addr:street":"Carrer De Sant Joan;Penedes Barcelona",
    "iso:country":"ES",
    "sg:address":"Carrer de Sant Joan, 7",
    "sg:city":"Vilafranca Penedes",
    "sg:orig_category":"Abogados",
    "sg:phone":"+34 938 92 53 53",
    "sg:postcode":"08720",
    "sg:province":"Barcelona",
    "wof:name":"Gual Poch Silvia",
    "wof:placetype":"venue"
},
  "geometry": {"coordinates":[1.6994329691,41.3457527161],"type":"Point"}
}