{
  "type": "Feature",
  "properties": {
    "iso:country":"ES",
    "sg:address":"Calle de Valgrande (de), 22",
    "sg:city":"Alcobendas",
    "sg:orig_category":"Rectificaci\u00d3n, Mecanizado, Fresado",
    "sg:phone":"+34 916 62 41 47",
    "sg:postcode":"28108",
    "sg:province":"Madrid",
    "wof:name":"Csd Mecanizados S.l.",
    "wof:placetype":"venue"
},
  "geometry": {"coordinates":[-3.6517100334,40.5381851196],"type":"Point"}
}