{
  "type": "Feature",
  "properties": {
    "iso:country":"ES",
    "sg:address":"Carrer de Olimpica, S/n",
    "sg:city":"S. Adria Besos",
    "sg:orig_category":"Ense\u00d1anza, Formaci\u00d3n Profesional: Aprendizaje",
    "sg:phone":"+34 934 62 24 69",
    "sg:postcode":"08930",
    "sg:province":"Barcelona",
    "wof:name":"Centre De Telecomunicaciones De Catalunya",
    "wof:placetype":"venue"
},
  "geometry": {"coordinates":[2.2249600887,41.4247398376],"type":"Point"}
}