{
  "type": "Feature",
  "properties": {
    "iso:country":"ES",
    "sg:address":"Avda Extremadura, 14",
    "sg:city":"Arroyo S Servan",
    "sg:orig_category":"Muebles, Minoristas",
    "sg:phone":"+34 924 34 30 28",
    "sg:postcode":"06850",
    "sg:province":"Badajoz",
    "wof:name":"Fasamo S L",
    "wof:placetype":"venue"
},
  "geometry": {"coordinates":[-6.4548311234,38.8549995422],"type":"Point"}
}