{
  "type": "Feature",
  "properties": {
    "addr:full":"Calle de Andalucia, 84 Paterna Campo Huelva 21880",
    "addr:housenumber":"84",
    "addr:postcode":"21880",
    "addr:street":"Calle De Andalucia",
    "iso:country":"ES",
    "sg:address":"Calle de Andalucia, 84",
    "sg:city":"Paterna Campo",
    "sg:orig_category":"Molduras, Junquillos, Listones Y Molduras Perforadas",
    "sg:phone":"+34 959 42 82 05",
    "sg:postcode":"21880",
    "sg:province":"Huelva",
    "wof:name":"Pascual Garrido Carmelo",
    "wof:placetype":"venue"
},
  "geometry": {"coordinates":[-6.4009871483,37.4173469543],"type":"Point"}
}