{
  "type": "Feature",
  "properties": {
    "iso:country":"ES",
    "sg:address":"Calle de Montoyos, 42",
    "sg:city":"San Vicente Del Raspeig-sant Vicent Del Raspeig",
    "sg:orig_category":"Contenedores (mercanc\u00cdas)",
    "sg:phone":"+34 965 66 08 32",
    "sg:postcode":"03690",
    "sg:province":"Alicante",
    "wof:name":"Navarro Sanchez Leonardo",
    "wof:placetype":"venue"
},
  "geometry": {"coordinates":[-0.5272269845,38.3937606812],"type":"Point"}
}