{
  "type": "Feature",
  "properties": {
    "iso:country":"ES",
    "sg:address":"Calle de Isla De La Alegranza, 6",
    "sg:city":"San Sebastian De Los Reyes",
    "sg:orig_category":"Ropa Para Ni\u00d1os (al Por Menor)",
    "sg:phone":"+34 916 51 40 67",
    "sg:postcode":"28700",
    "sg:province":"Madrid",
    "sg:website":"www.gugutata.net",
    "wof:name":"Azul Y Rosa Equipamiento Infantil S.l.",
    "wof:placetype":"venue"
},
  "geometry": {"coordinates":[-3.6204769611,40.5589866638],"type":"Point"}
}