{
  "type": "Feature",
  "properties": {
    "iso:country":"ES",
    "sg:address":"Carrer de Sant Antoni Maria Claret, 25",
    "sg:city":"Tarragona",
    "sg:orig_category":"Molduras, Junquillos, Listones Y Molduras Perforadas",
    "sg:phone":"+34 977 21 58 87",
    "sg:postcode":"43002",
    "sg:province":"Tarragona",
    "wof:name":"Gibert Saco Jose Maria",
    "wof:placetype":"venue"
},
  "geometry": {"coordinates":[1.2460809946,41.1214981079],"type":"Point"}
}