{
  "type": "Feature",
  "properties": {
    "addr:full":"Pino, 7 Mijas Costa M\u00e1laga 29649",
    "addr:housenumber":"7",
    "addr:postcode":"29649",
    "addr:street":"Pino",
    "iso:country":"ES",
    "sg:address":"Pino, 7",
    "sg:city":"Mijas Costa",
    "sg:orig_category":"Empresas De Carpinter\u00cda De Madera",
    "sg:phone":"+34 952 46 28 49",
    "sg:postcode":"29649",
    "sg:province":"M\u00e1laga",
    "wof:name":"Cortes Perez Antonio",
    "wof:placetype":"venue"
},
  "geometry": {"coordinates":[-4.6735768318,36.5086898804],"type":"Point"}
}