{
  "type": "Feature",
  "properties": {
    "addr:full":"Avda Pe\u00d1aflor, S/n Pe\u00f1aflor Zaragoza 50193",
    "addr:housenumber":"s",
    "addr:postcode":"50193",
    "addr:street":"Avda Pen\u0303Aflor;/ N Pen\u0303Aflor",
    "iso:country":"ES",
    "sg:address":"Avda Pe\u00d1aflor, S/n",
    "sg:city":"Pe\u00f1aflor",
    "sg:orig_category":"Perreras, Pensiones Para Perros, Gatos Y Otros Animales",
    "sg:phone":"+34 976 13 16 24",
    "sg:postcode":"50193",
    "sg:province":"Zaragoza",
    "wof:name":"Pozuelo Cadenas Maria Pilar",
    "wof:placetype":"venue"
},
  "geometry": {"coordinates":[-0.7956889868,41.7603912354],"type":"Point"}
}