{
  "type": "Feature",
  "properties": {
    "addr:full":"Calle de Canarias, 5 Badajoz Badajoz 06007",
    "addr:housenumber":"5",
    "addr:postcode":"06007",
    "addr:street":"Calle De Canarias",
    "iso:country":"ES",
    "sg:address":"Calle de Canarias, 5",
    "sg:city":"Badajoz",
    "sg:orig_category":"Iglesia Cat\u00d3lica",
    "sg:phone":"+34 924 27 01 13",
    "sg:postcode":"06007",
    "sg:province":"Badajoz",
    "wof:name":"Parroquia San Fernando Y Santa Isabel",
    "wof:placetype":"venue"
},
  "geometry": {"coordinates":[-6.980738163,38.887928009],"type":"Point"}
}