{
  "type": "Feature",
  "properties": {
    "addr:full":"Avda Luis Espada, 57 Verin Ourense 32600",
    "addr:housenumber":"57",
    "addr:postcode":"32600",
    "addr:street":"Avda Luis Espada",
    "iso:country":"ES",
    "sg:address":"Avda Luis Espada, 57",
    "sg:city":"Verin",
    "sg:orig_category":"M\u00c9dicos: Estomatolog\u00cda",
    "sg:phone":"+34 988 41 00 65",
    "sg:postcode":"32600",
    "sg:province":"Ourense",
    "wof:name":"Arias Baladron Sixto",
    "wof:placetype":"venue"
},
  "geometry": {"coordinates":[-7.4357500076,41.9401855469],"type":"Point"}
}