{
  "type": "Feature",
  "properties": {
    "iso:country":"ES",
    "sg:address":"Calle de Arrayan, 9",
    "sg:city":"Carmona",
    "sg:orig_category":"Carnicer\u00cdas, Carnicer\u00cdas",
    "sg:phone":"+34 954 14 23 24",
    "sg:postcode":"41410",
    "sg:province":"Sevilla",
    "wof:name":"Gonzalez Gomez Antonio",
    "wof:placetype":"venue"
},
  "geometry": {"coordinates":[-5.6516833305,37.473236084],"type":"Point"}
}