{
  "type": "Feature",
  "properties": {
    "addr:full":"Plaz Santa Maria Del Camino, 3 Le\u00f3n Le\u00f3n 24003",
    "addr:housenumber":"3",
    "addr:postcode":"24003",
    "addr:street":"Camino;Leo\u0301N",
    "iso:country":"ES",
    "sg:address":"Plaz Santa Maria Del Camino, 3",
    "sg:city":"Le\u00f3n",
    "sg:orig_category":"Internados & Ense\u00d1anza Privada",
    "sg:phone":"+34 987 25 28 66",
    "sg:postcode":"24003",
    "sg:province":"Le\u00f3n",
    "wof:name":"Benedictinas Carbajalas",
    "wof:placetype":"venue"
},
  "geometry": {"coordinates":[-5.568734169,42.5953216553],"type":"Point"}
}