{
  "type": "Feature",
  "properties": {
    "addr:full":"Calle de San Sebastian, 15 Puertollano Ciudad Real 13500",
    "addr:housenumber":"15",
    "addr:postcode":"13500",
    "addr:street":"Calle De San Sebastian",
    "iso:country":"ES",
    "sg:address":"Calle de San Sebastian, 15",
    "sg:city":"Puertollano",
    "sg:orig_category":"Negocio De Materiales De Construcci\u00d3n",
    "sg:phone":"+34 926 42 46 97",
    "sg:postcode":"13500",
    "sg:province":"Ciudad Real",
    "wof:name":"Rivilla Ruiz Antonio",
    "wof:placetype":"venue"
},
  "geometry": {"coordinates":[-4.1136507988,38.688583374],"type":"Point"}
}