{
  "type": "Feature",
  "properties": {
    "iso:country":"ES",
    "sg:address":"Calle de San Roque, S/n",
    "sg:city":"Riezu",
    "sg:orig_category":"Panader\u00cdas, Pasteler\u00cdas, Boller\u00cda Industriale (fabricaci\u00d3n, Al Por Mayor)",
    "sg:phone":"+34 948 54 22 47",
    "sg:postcode":"31176",
    "sg:province":"Navarra",
    "wof:name":"Jimenez Echarri Pedro Jose",
    "wof:placetype":"venue"
},
  "geometry": {"coordinates":[-1.9506458044,42.7616462708],"type":"Point"}
}