{
  "type": "Feature",
  "properties": {
    "addr:full":"Calle de General Sueiro, 8 Zaragoza Zaragoza 50008",
    "addr:housenumber":"8",
    "addr:postcode":"50008",
    "addr:street":"Calle De General Sueiro",
    "iso:country":"ES",
    "sg:address":"Calle de General Sueiro, 8",
    "sg:city":"Zaragoza",
    "sg:orig_category":"Abogados",
    "sg:phone":"+34 976 23 51 55",
    "sg:postcode":"50008",
    "sg:province":"Zaragoza",
    "wof:name":"Gascon San Martin Jose Maria",
    "wof:placetype":"venue"
},
  "geometry": {"coordinates":[-0.8831419945,41.6461639404],"type":"Point"}
}