{
  "type": "Feature",
  "properties": {
    "iso:country":"ES",
    "sg:address":"Ctra Vic, 242",
    "sg:city":"Manresa",
    "sg:orig_category":"Molduras, Junquillos, Listones Y Molduras Perforadas",
    "sg:phone":"+34 938 73 79 64",
    "sg:postcode":"08243",
    "sg:province":"Barcelona",
    "wof:name":"Diez Garcia Jesus",
    "wof:placetype":"venue"
},
  "geometry": {"coordinates":[1.8410160542,41.7342834473],"type":"Point"}
}