{
  "type": "Feature",
  "properties": {
    "addr:full":"Avda Santa Marina, 9 Badajoz Badajoz 06005",
    "addr:housenumber":"9",
    "addr:postcode":"06005",
    "addr:street":"Avda Santa Marina",
    "iso:country":"ES",
    "sg:address":"Avda Santa Marina, 9",
    "sg:city":"Badajoz",
    "sg:orig_category":"Centros P\u00dablicos De Formaci\u00d3n Profesional Y T\u00c9cnica",
    "sg:phone":"+34 924 23 07 39",
    "sg:postcode":"06005",
    "sg:province":"Badajoz",
    "wof:name":"Colegio Oficial De Veterinarios De Badajoz",
    "wof:placetype":"venue"
},
  "geometry": {"coordinates":[-6.9763832092,38.8737335205],"type":"Point"}
}