{
  "type": "Feature",
  "properties": {
    "iso:country":"ES",
    "sg:address":"Calle de Castuera, 19",
    "sg:city":"Madrid",
    "sg:orig_category":"Ebanister\u00cda",
    "sg:phone":"+34 914 63 52 12",
    "sg:postcode":"28047",
    "sg:province":"Madrid",
    "wof:name":"Aguilar Romero Jose Manuel",
    "wof:placetype":"venue"
},
  "geometry": {"coordinates":[-3.7479972839,40.401096344],"type":"Point"}
}