{
  "type": "Feature",
  "properties": {
    "addr:full":"Crta General, Km. 0180,0 Gama Cantabria 39790",
    "addr:postcode":"39790",
    "addr:street":"Crta General Km. 0180,0",
    "iso:country":"ES",
    "sg:address":"Crta General, Km. 0180,0",
    "sg:city":"Gama",
    "sg:orig_category":"Asilos De Ancianos. Centros Privados",
    "sg:phone":"+34 942 64 29 11",
    "sg:postcode":"39790",
    "sg:province":"Cantabria",
    "wof:name":"Residencias Marismas De Gama S.l.",
    "wof:placetype":"venue"
},
  "geometry": {"coordinates":[-3.5058469772,43.4200515747],"type":"Point"}
}