{
  "type": "Feature",
  "properties": {
    "addr:full":"Calle de Alzania, 6 Alsasua Navarra 31800",
    "addr:housenumber":"6",
    "addr:postcode":"31800",
    "addr:street":"Calle De Alzania",
    "iso:country":"ES",
    "sg:address":"Calle de Alzania, 6",
    "sg:city":"Alsasua",
    "sg:orig_category":"Carnicer\u00cdas, Carnicer\u00cdas",
    "sg:phone":"+34 948 46 72 24",
    "sg:postcode":"31800",
    "sg:province":"Navarra",
    "wof:name":"Pablo Leon Jesus",
    "wof:placetype":"venue"
},
  "geometry": {"coordinates":[-2.1717698574,42.8951873779],"type":"Point"}
}