{
  "type": "Feature",
  "properties": {
    "addr:full":"Calle de Mar, 15 Valencia Valencia 46003",
    "addr:housenumber":"15",
    "addr:postcode":"46003",
    "addr:street":"Calle De Mar",
    "iso:country":"ES",
    "sg:address":"Calle de Mar, 15",
    "sg:city":"Valencia",
    "sg:orig_category":"Confecci\u00d3n De Trajes Para Se\u00d1oras",
    "sg:phone":"+34 963 91 21 41",
    "sg:postcode":"46003",
    "sg:province":"Valencia",
    "wof:name":"Benedito Miralles Amparo",
    "wof:placetype":"venue"
},
  "geometry": {"coordinates":[-0.3743900061,39.4739952087],"type":"Point"}
}