{
  "type": "Feature",
  "properties": {
    "addr:full":"Carrer de Bruc, 30 Berga-ciudad Barcelona 08600",
    "addr:housenumber":"30",
    "addr:postcode":"08600",
    "addr:street":"Carrer De Bruc;Barcelona",
    "iso:country":"ES",
    "sg:address":"Carrer de Bruc, 30",
    "sg:city":"Berga-ciudad",
    "sg:orig_category":"Mercer\u00cda, Lencer\u00cda (al Por Menor)",
    "sg:phone":"+34 938 21 07 77",
    "sg:postcode":"08600",
    "sg:province":"Barcelona",
    "wof:name":"Benavides Moreno Juan",
    "wof:placetype":"venue"
},
  "geometry": {"coordinates":[1.8382029533,42.0960426331],"type":"Point"}
}