{
  "type": "Feature",
  "properties": {
    "addr:full":"Calle de Los Madrazo, 16 Madrid Madrid 28014",
    "addr:housenumber":"16",
    "addr:postcode":"madrid;28014",
    "addr:street":"Calle De Los Madrazo",
    "iso:country":"ES",
    "sg:address":"Calle de Los Madrazo, 16",
    "sg:city":"Madrid",
    "sg:orig_category":"Abogados",
    "sg:phone":"+34 914 20 38 91",
    "sg:postcode":"28014",
    "sg:province":"Madrid",
    "wof:name":"Arroyo Masero Maria Dolores",
    "wof:placetype":"venue"
},
  "geometry": {"coordinates":[-3.6972770691,40.4175796509],"type":"Point"}
}