{
  "type": "Feature",
  "properties": {
    "addr:full":"Pg Marina, 226 Castelldefels Barcelona 08860",
    "addr:housenumber":"226",
    "addr:postcode":"08860",
    "addr:street":"Pg Marina",
    "iso:country":"ES",
    "sg:address":"Pg Marina, 226",
    "sg:city":"Castelldefels",
    "sg:orig_category":"Molduras, Junquillos, Listones Y Molduras Perforadas",
    "sg:phone":"+34 936 65 66 45",
    "sg:postcode":"08860",
    "sg:province":"Barcelona",
    "wof:name":"Masip Amoros Juan",
    "wof:placetype":"venue"
},
  "geometry": {"coordinates":[1.9651639462,41.2672653198],"type":"Point"}
}