{
  "type": "Feature",
  "properties": {
    "addr:full":"Calle de General Ricardos, 11 Madrid Madrid 28019",
    "addr:housenumber":"11",
    "addr:postcode":"madrid;28019",
    "addr:street":"Calle De General Ricardos",
    "iso:country":"ES",
    "sg:address":"Calle de General Ricardos, 11",
    "sg:city":"Madrid",
    "sg:orig_category":"Iglesia Cat\u00d3lica",
    "sg:phone":"+34 914 72 77 16",
    "sg:postcode":"28019",
    "sg:province":"Madrid",
    "wof:name":"Parroquia De San Miguel Arcangel",
    "wof:placetype":"venue"
},
  "geometry": {"coordinates":[-3.7169950008,40.3969955444],"type":"Point"}
}