{
  "type": "Feature",
  "properties": {
    "iso:country":"ES",
    "sg:address":"Avda Hispanidad, 6",
    "sg:city":"Puerto",
    "sg:orig_category":"Transportes Internacionales",
    "sg:phone":"+34 962 68 33 94",
    "sg:postcode":"46520",
    "sg:province":"Valencia",
    "wof:name":"Hernandez Martinez Victoriano",
    "wof:placetype":"venue"
},
  "geometry": {"coordinates":[-0.2294200063,39.6653366089],"type":"Point"}
}