{
  "type": "Feature",
  "properties": {
    "addr:full":"Poligono Industrial, S/n Agoitz Navarra 31430",
    "addr:postcode":"31430",
    "addr:street":"Industrial S / N",
    "iso:country":"ES",
    "sg:address":"Poligono Industrial, S/n",
    "sg:city":"Agoitz",
    "sg:orig_category":"Pintura, Barniz, Productos Asimilables (fabricaci\u00d3n, Al Por Mayor)",
    "sg:phone":"+34 948 33 40 73",
    "sg:postcode":"31430",
    "sg:province":"Navarra",
    "wof:name":"Pinturas Lakabe S.l.",
    "wof:placetype":"venue"
},
  "geometry": {"coordinates":[-1.3753689528,42.7824897766],"type":"Point"}
}