{
  "type": "Feature",
  "properties": {
    "addr:full":"Pl. Sancho Vi Sabio, 2 Atarrabia Navarra 31610",
    "addr:housenumber":"2",
    "addr:postcode":"31610",
    "addr:street":"Pl.;Sabio",
    "iso:country":"ES",
    "sg:address":"Pl. Sancho Vi Sabio, 2",
    "sg:city":"Atarrabia",
    "sg:orig_category":"Confiter\u00cdas, Chocolater\u00cdas (al Por Menor)",
    "sg:phone":"+34 948 14 68 63",
    "sg:postcode":"31610",
    "sg:province":"Navarra",
    "wof:name":"Calleja Alcalde Felisa",
    "wof:placetype":"venue"
},
  "geometry": {"coordinates":[-1.6098489761,42.8311386108],"type":"Point"}
}