{
  "type": "Feature",
  "properties": {
    "iso:country":"ES",
    "sg:address":"Carr Prat De La Riba, 4",
    "sg:city":"Castello D'empuries",
    "sg:orig_category":"Reposter\u00cdas",
    "sg:phone":"+34 972 25 00 18",
    "sg:postcode":"17486",
    "sg:province":"Girona",
    "wof:name":"La Fleca De Castello S.a.",
    "wof:placetype":"venue"
},
  "geometry": {"coordinates":[2.8266990185,41.9800949097],"type":"Point"}
}