{
  "type": "Feature",
  "properties": {
    "iso:country":"ES",
    "sg:address":"Calle de Don Gonzalo, 11",
    "sg:city":"Montilla",
    "sg:orig_category":"Agentes Generales De Seguros",
    "sg:phone":"+34 957 65 32 95",
    "sg:postcode":"14550",
    "sg:province":"C\u00f3rdoba",
    "wof:name":"Agencia Montilla Hidalgo S.l.",
    "wof:placetype":"venue"
},
  "geometry": {"coordinates":[-4.6393446922,37.5895957947],"type":"Point"}
}