{
  "type": "Feature",
  "properties": {
    "addr:full":"Calle de Platanos, 45 Valencia Valencia 46025",
    "addr:housenumber":"45",
    "addr:postcode":"46025",
    "addr:street":"Calle De Platanos",
    "iso:country":"ES",
    "sg:address":"Calle de Platanos, 45",
    "sg:city":"Valencia",
    "sg:orig_category":"Asesor\u00cda Fiscal Y Jur\u00cddica",
    "sg:phone":"+34 963 48 57 21",
    "sg:postcode":"46025",
    "sg:province":"Valencia",
    "wof:name":"Montesinos Alfonso Jose Ramon",
    "wof:placetype":"venue"
},
  "geometry": {"coordinates":[-0.3883379996,39.4926452637],"type":"Point"}
}