{
  "type": "Feature",
  "properties": {
    "iso:country":"ES",
    "sg:address":"Subida La Fuensanta, 33",
    "sg:city":"Algezares",
    "sg:orig_category":"Asociaciones Y Clubs Deportivos",
    "sg:phone":"+34 968 84 19 22",
    "sg:postcode":"30157",
    "sg:province":"Murcia",
    "wof:name":"Tenis Club Algezares",
    "wof:placetype":"venue"
},
  "geometry": {"coordinates":[-1.1159290075,37.9399986267],"type":"Point"}
}