{
  "type": "Feature",
  "properties": {
    "addr:full":"Pg Pere Iii, 56 Manresa Barcelona 08242",
    "addr:housenumber":"56",
    "addr:postcode":"08242",
    "addr:street":"Pg Pere Iii",
    "iso:country":"ES",
    "sg:address":"Pg Pere Iii, 56",
    "sg:city":"Manresa",
    "sg:orig_category":"Abogados",
    "sg:phone":"+34 938 73 81 54",
    "sg:postcode":"08242",
    "sg:province":"Barcelona",
    "wof:name":"Berenguer Canet Enric",
    "wof:placetype":"venue"
},
  "geometry": {"coordinates":[1.8251949549,41.7295761108],"type":"Point"}
}