{
  "type": "Feature",
  "properties": {
    "addr:full":"Carrer de Sant Jaume, 3 Palma Islas Baleares 07012",
    "addr:housenumber":"3",
    "addr:postcode":"07012",
    "addr:street":"Carrer De Sant Jaume",
    "iso:country":"ES",
    "sg:address":"Carrer de Sant Jaume, 3",
    "sg:city":"Palma",
    "sg:orig_category":"Ense\u00d1anza: Profesiones Art\u00cdsticas",
    "sg:phone":"+34 971 72 69 14",
    "sg:postcode":"07012",
    "sg:province":"Islas Baleares",
    "wof:name":"Ramon Gorlero Gabriel",
    "wof:placetype":"venue"
},
  "geometry": {"coordinates":[2.6471049786,39.5719909668],"type":"Point"}
}