{
  "type": "Feature",
  "properties": {
    "addr:full":"Avda Bilbao, 5 Medina Pomar Burgos 09500",
    "addr:housenumber":"5",
    "addr:postcode":"09500",
    "addr:street":"Avda Bilbao",
    "iso:country":"ES",
    "sg:address":"Avda Bilbao, 5",
    "sg:city":"Medina Pomar",
    "sg:orig_category":"Fisioterapia",
    "sg:phone":"+34 947 19 19 22",
    "sg:postcode":"09500",
    "sg:province":"Burgos",
    "wof:name":"Benito Portugal David",
    "wof:placetype":"venue"
},
  "geometry": {"coordinates":[-3.4861359596,42.9326133728],"type":"Point"}
}