{
  "type": "Feature",
  "properties": {
    "addr:full":"Garagartza Auzoa, 21 Garagartza Guip\u00f9zcoa 20509",
    "addr:housenumber":"21",
    "addr:postcode":"20509",
    "addr:street":"Garagartza Auzoa;Guipu\u0300Zcoa",
    "iso:country":"ES",
    "sg:address":"Garagartza Auzoa, 21",
    "sg:city":"Garagartza",
    "sg:orig_category":"Asociaciones, Organismos Culturales Y Socioeducativos",
    "sg:phone":"+34 943 79 22 14",
    "sg:postcode":"20509",
    "sg:province":"Guip\u00f9zcoa",
    "wof:name":"Sociedad Recreativo Cultural Leze-txiki",
    "wof:placetype":"venue"
},
  "geometry": {"coordinates":[-2.520637989,43.0691261292],"type":"Point"}
}