{
  "type": "Feature",
  "properties": {
    "iso:country":"ES",
    "sg:address":"Urb Puerto De Mogan, S/n",
    "sg:city":"Playa De Mogan",
    "sg:orig_category":"Deportes N\u00c1uticos, Acu\u00c1ticos Y Subacu\u00c1ticos: Art\u00cdculos Y Equipo (al Por Menor)",
    "sg:phone":"+34 928 56 54 63",
    "sg:postcode":"35138",
    "sg:province":"Las Palmas",
    "wof:name":"Puerto De Mogan S. A.",
    "wof:placetype":"venue"
},
  "geometry": {"coordinates":[-13.8894538879,28.6940307617],"type":"Point"}
}