{
  "type": "Feature",
  "properties": {
    "addr:full":"Carrer de Travau, 27 Barcelona Barcelona 08031",
    "addr:housenumber":"27",
    "addr:postcode":"08031",
    "addr:street":"Carrer De Travau",
    "iso:country":"ES",
    "sg:address":"Carrer de Travau, 27",
    "sg:city":"Barcelona",
    "sg:orig_category":"Peleter\u00cdas",
    "sg:phone":"+34 933 58 24 55",
    "sg:postcode":"08031",
    "sg:province":"Barcelona",
    "wof:name":"Gomez Y Varela S.c",
    "wof:placetype":"venue"
},
  "geometry": {"coordinates":[2.1693708897,41.4328575134],"type":"Point"}
}