{
  "type": "Feature",
  "properties": {
    "iso:country":"ES",
    "sg:address":"Avda Cardenal Herrera Oria, 165",
    "sg:city":"Madrid",
    "sg:orig_category":"Diarios, Prensa, Revistas (al Por Menor)",
    "sg:phone":"+34 913 78 12 83",
    "sg:postcode":"28034",
    "sg:province":"Madrid",
    "wof:name":"Prensa Escorial S.l.",
    "wof:placetype":"venue"
},
  "geometry": {"coordinates":[-3.6957409382,40.4902687073],"type":"Point"}
}