{
  "type": "Feature",
  "properties": {
    "iso:country":"ES",
    "sg:address":"Calle de Moradas, 17",
    "sg:city":"Valladolid",
    "sg:orig_category":"Frutas, Legumbres Frescas Y Tempranas (al Por Menor)",
    "sg:phone":"+34 983 25 96 47",
    "sg:postcode":"47010",
    "sg:province":"Valladolid",
    "wof:name":"Sanchez Sanchez Maria",
    "wof:placetype":"venue"
},
  "geometry": {"coordinates":[-4.7224822044,41.6607208252],"type":"Point"}
}