{
  "type": "Feature",
  "properties": {
    "addr:full":"Calle de Arenal, 1 Valencina Concepcion Sevilla 41907",
    "addr:housenumber":"1",
    "addr:postcode":"41907",
    "addr:street":"Calle De Arenal",
    "iso:country":"ES",
    "sg:address":"Calle de Arenal, 1",
    "sg:city":"Valencina Concepcion",
    "sg:orig_category":"Agencias Y Agentes Comerciales, Representantes",
    "sg:phone":"+34 955 72 71 52",
    "sg:postcode":"41907",
    "sg:province":"Sevilla",
    "wof:name":"Relojufer S.l.",
    "wof:placetype":"venue"
},
  "geometry": {"coordinates":[-6.081032753,37.402179718],"type":"Point"}
}