{
  "type": "Feature",
  "properties": {
    "iso:country":"ES",
    "sg:address":"Carrer de Muntaner, 448",
    "sg:city":"Barcelona",
    "sg:orig_category":"Ingenier\u00cda, Centros De Estudios (diversos)",
    "sg:phone":"+34 934 14 25 84",
    "sg:postcode":"08006",
    "sg:province":"Barcelona",
    "wof:name":"Laborda Cotarelo Jaime",
    "wof:placetype":"venue"
},
  "geometry": {"coordinates":[2.1398360729,41.4015312195],"type":"Point"}
}