{
  "type": "Feature",
  "properties": {
    "iso:country":"ES",
    "sg:address":"Calle de De Los Carros, 47",
    "sg:city":"Benavente",
    "sg:orig_category":"Materiales De Construcci\u00d3n, Herramientas",
    "sg:phone":"+34 980 63 72 58",
    "sg:postcode":"49600",
    "sg:province":"Zamora",
    "wof:name":"Construcciones Perez Del Amo S.a.",
    "wof:placetype":"venue"
},
  "geometry": {"coordinates":[-5.6022672653,41.9902305603],"type":"Point"}
}