{
  "type": "Feature",
  "properties": {
    "iso:country":"ES",
    "sg:address":"Calle de Fragata, 1",
    "sg:city":"Palmones",
    "sg:orig_category":"Agencias De Viajes",
    "sg:phone":"+34 956 67 56 53",
    "sg:postcode":"11379",
    "sg:province":"C\u00e1diz",
    "wof:name":"Viajes Normandi S.l",
    "wof:placetype":"venue"
},
  "geometry": {"coordinates":[-5.4427189827,36.1786231995],"type":"Point"}
}