{
  "type": "Feature",
  "properties": {
    "addr:full":"El Puerto, 4 Alcala Real Ja\u00e9n 23680",
    "addr:postcode":"23680",
    "addr:street":"Jae\u0301N",
    "iso:country":"ES",
    "sg:address":"El Puerto, 4",
    "sg:city":"Alcala Real",
    "sg:orig_category":"Contenedores (mercanc\u00cdas)",
    "sg:phone":"+34 953 58 03 36",
    "sg:postcode":"23680",
    "sg:province":"Ja\u00e9n",
    "wof:name":"Ca\u00f1adas Garcia Francisco",
    "wof:placetype":"venue"
},
  "geometry": {"coordinates":[-3.9257619381,37.4603385925],"type":"Point"}
}