{
  "type": "Feature",
  "properties": {
    "iso:country":"ES",
    "sg:address":"Carrer de Venecia, 36",
    "sg:city":"Lloret Mar",
    "sg:orig_category":"Ropa Para Se\u00d1oras (al Por Menor)",
    "sg:phone":"+34 972 36 64 13",
    "sg:postcode":"17310",
    "sg:province":"Girona",
    "wof:name":"Marquez Ventura Juan",
    "wof:placetype":"venue"
},
  "geometry": {"coordinates":[2.8516800404,41.7001838684],"type":"Point"}
}