{
  "type": "Feature",
  "properties": {
    "addr:full":"Calle de Playa Del Puig, 3 Matas-pinar-monte Rozas Madrid 28290",
    "addr:housenumber":"3",
    "addr:postcode":"28290",
    "addr:street":"Calle De Playa Del Puig",
    "iso:country":"ES",
    "sg:address":"Calle de Playa Del Puig, 3",
    "sg:city":"Matas-pinar-monte Rozas",
    "sg:orig_category":"Gu\u00cdas Y Gu\u00cdas",
    "sg:phone":"+34 916 30 27 29",
    "sg:postcode":"28290",
    "sg:province":"Madrid",
    "wof:name":"Madrid Albarran Javier",
    "wof:placetype":"venue"
},
  "geometry": {"coordinates":[-3.9005339146,40.5397148132],"type":"Point"}
}