{
  "type": "Feature",
  "properties": {
    "addr:full":"Calle de Maria Auxiliadora, S/n Marbella M\u00e1laga 29600",
    "addr:housenumber":"s / n",
    "addr:postcode":"29600",
    "addr:street":"Calle De Maria Auxiliadora;Ma\u0301Laga",
    "iso:country":"ES",
    "sg:address":"Calle de Maria Auxiliadora, S/n",
    "sg:city":"Marbella",
    "sg:orig_category":"Asesor\u00cda Fiscal Y Jur\u00cddica",
    "sg:phone":"+34 952 76 66 54",
    "sg:postcode":"29600",
    "sg:province":"M\u00e1laga",
    "wof:name":"Gonzalez Arias Manuel",
    "wof:placetype":"venue"
},
  "geometry": {"coordinates":[-4.8872451782,36.5088348389],"type":"Point"}
}