{
  "type": "Feature",
  "properties": {
    "iso:country":"ES",
    "sg:address":"Calle de Goya, 3",
    "sg:city":"Gijon",
    "sg:orig_category":"Venta, Instalaci\u00d3n De Calefacci\u00d3n",
    "sg:phone":"+34 985 14 57 92",
    "sg:postcode":"33210",
    "sg:province":"Asturias",
    "wof:name":"Diaz Fernandez Jose Manuel",
    "wof:placetype":"venue"
},
  "geometry": {"coordinates":[-5.6680288315,43.5232582092],"type":"Point"}
}