{
  "type": "Feature",
  "properties": {
    "iso:country":"ES",
    "sg:address":"Calle de Valle Inclan, 16",
    "sg:city":"Roquetas Mar",
    "sg:orig_category":"Muebles",
    "sg:phone":"+34 950 32 76 95",
    "sg:postcode":"04740",
    "sg:province":"Almer\u00eda",
    "wof:name":"Garimar Suministros Y Servicios De Hosteleria S.l.",
    "wof:placetype":"venue"
},
  "geometry": {"coordinates":[-2.6131289005,36.7644615173],"type":"Point"}
}