{
  "type": "Feature",
  "properties": {
    "iso:country":"ES",
    "sg:address":"Carr Magdalena, 34",
    "sg:city":"Lleida",
    "sg:orig_category":"Confecci\u00d3n De Alpargatas",
    "sg:phone":"+34 973 23 22 10",
    "sg:postcode":"25007",
    "sg:province":"Lleida",
    "wof:name":"Giro Bigorda Celestina",
    "wof:placetype":"venue"
},
  "geometry": {"coordinates":[0.6292629838,41.6191673279],"type":"Point"}
}