{
  "type": "Feature",
  "properties": {
    "iso:country":"ES",
    "sg:address":"Plaz Errekalde, 4",
    "sg:city":"Bilbao",
    "sg:orig_category":"Caf\u00c9s, Bares, Cervecer\u00cdas",
    "sg:phone":"+34 944 22 11 38",
    "sg:postcode":"48002",
    "sg:province":"Vizcaya",
    "wof:name":"Fernandez De La Fuente Victorina",
    "wof:placetype":"venue"
},
  "geometry": {"coordinates":[-2.9470729828,43.2521896362],"type":"Point"}
}