{
  "type": "Feature",
  "properties": {
    "addr:full":"Carrer de Rossello, 423 Barcelona Barcelona 08025",
    "addr:housenumber":"423",
    "addr:postcode":"08025",
    "addr:street":"Carrer De Rossello",
    "iso:country":"ES",
    "sg:address":"Carrer de Rossello, 423",
    "sg:city":"Barcelona",
    "sg:orig_category":"Veh\u00cdculos De Ocasi\u00d3n",
    "sg:phone":"+34 934 35 85 89",
    "sg:postcode":"08025",
    "sg:province":"Barcelona",
    "wof:name":"Babot Picas Esteban-babot Llopart Jaime-babot Llopart Esteban S. Cv.",
    "wof:placetype":"venue"
},
  "geometry": {"coordinates":[2.1724340916,41.4048500061],"type":"Point"}
}