{
  "type": "Feature",
  "properties": {
    "iso:country":"ES",
    "sg:address":"Cno Polio, S/n",
    "sg:city":"Beniparrell",
    "sg:orig_category":"Pompas F\u00danebres, Inhumaciones Y Cremaciones",
    "sg:phone":"+34 961 21 23 22",
    "sg:postcode":"46469",
    "sg:province":"Valencia",
    "wof:name":"Valenciana De Arcas S.c.v.",
    "wof:placetype":"venue"
},
  "geometry": {"coordinates":[-0.4188640118,39.3784294128],"type":"Point"}
}