{
  "type": "Feature",
  "properties": {
    "addr:full":"Calle de San Jose, 44 Santa Amalia Badajoz 06410",
    "addr:housenumber":"44",
    "addr:postcode":"06410",
    "addr:street":"Calle De San;Santa",
    "iso:country":"ES",
    "sg:address":"Calle de San Jose, 44",
    "sg:city":"Santa Amalia",
    "sg:orig_category":"Chapister\u00cda",
    "sg:phone":"+34 924 83 02 76",
    "sg:postcode":"06410",
    "sg:province":"Badajoz",
    "wof:name":"Talleres Pajuelo Parejo S.l.",
    "wof:placetype":"venue"
},
  "geometry": {"coordinates":[-6.0150790215,39.0115318298],"type":"Point"}
}