{
  "type": "Feature",
  "properties": {
    "iso:country":"ES",
    "sg:address":"Carrer de Gran Vista, 87",
    "sg:city":"Barcelona",
    "sg:classifiers":[
        {
            "category":"Personal",
            "subcategory":"Barber",
            "type":"Services"
        }
    ],
    "sg:phone":"+34 934 29 38 77",
    "sg:postcode":"08032",
    "sg:province":"Barcelona",
    "sg:tags":[
        "caballeros",
        "de",
        "peluqueros"
    ],
    "wof:name":"Prieto Piedehierro Manuel",
    "wof:placetype":"venue"
},
  "geometry": {"coordinates":[2.1597700119,41.4197120667],"type":"Point"}
}