{
  "type": "Feature",
  "properties": {
    "iso:country":"ES",
    "sg:address":"Calle de Oca, 97",
    "sg:city":"Madrid",
    "sg:orig_category":"Cl\u00cdnicas Dentales",
    "sg:phone":"+34 914 61 73 66",
    "sg:postcode":"28025",
    "sg:province":"Madrid",
    "sg:website":"www",
    "wof:name":"Carluan Dental S.l.",
    "wof:placetype":"venue"
},
  "geometry": {"coordinates":[-3.7434740067,40.3880271912],"type":"Point"}
}