{
  "type": "Feature",
  "properties": {
    "addr:full":"Moli De La Sal, 19 Canovelles Barcelona 08420",
    "addr:housenumber":"19",
    "addr:postcode":"08420",
    "addr:street":"Moli De La Sal",
    "iso:country":"ES",
    "sg:address":"Moli De La Sal, 19",
    "sg:city":"Canovelles",
    "sg:orig_category":"Lubrificantes (fabricaci\u00d3n, Al Por Mayor)",
    "sg:phone":"+34 938 61 51 00",
    "sg:postcode":"08420",
    "sg:province":"Barcelona",
    "wof:name":"Welding Oil Iberica S.l.",
    "wof:placetype":"venue"
},
  "geometry": {"coordinates":[2.2780108452,41.6159515381],"type":"Point"}
}