{
  "type": "Feature",
  "properties": {
    "addr:full":"Carrer de Granada, 19 S. Andreu Barca Barcelona 08740",
    "addr:housenumber":"19",
    "addr:postcode":"08740",
    "addr:street":"Carrer De Granada;S. Andreu;Barcelona",
    "iso:country":"ES",
    "sg:address":"Carrer de Granada, 19",
    "sg:city":"S. Andreu Barca",
    "sg:orig_category":"Confiter\u00cda, Galletas Y Pastas, Chocolater\u00cda (al Por Mayor)",
    "sg:phone":"+34 936 53 22 11",
    "sg:postcode":"08740",
    "sg:province":"Barcelona",
    "sg:website":"www.feria.vilbonet.com/stenger",
    "wof:name":"Stenger S.a.",
    "wof:placetype":"venue"
},
  "geometry": {"coordinates":[1.9716449976,41.45545578],"type":"Point"}
}