{
  "type": "Feature",
  "properties": {
    "iso:country":"ES",
    "sg:address":"Rua Manuel Lemos, 63",
    "sg:city":"Ramallosa",
    "sg:orig_category":"Alimentaci\u00d3n General (al Por Menor)",
    "sg:phone":"+34 986 35 08 53",
    "sg:postcode":"36379",
    "sg:province":"Pontevedra",
    "wof:name":"Rigueira Lopez Jesus Antonio",
    "wof:placetype":"venue"
},
  "geometry": {"coordinates":[-8.8116369247,42.1211090088],"type":"Point"}
}