{
  "type": "Feature",
  "properties": {
    "iso:country":"ES",
    "sg:address":"Calle de Isaac Peral, 2",
    "sg:city":"Baza",
    "sg:orig_category":"Ense\u00d1anza Secundaria: Colegios Y Escuelas Privadas",
    "sg:phone":"+34 958 70 08 56",
    "sg:postcode":"18800",
    "sg:province":"Granada",
    "wof:name":"Junta De Andalucia",
    "wof:placetype":"venue"
},
  "geometry": {"coordinates":[-2.7663390636,37.4855308533],"type":"Point"}
}