{
  "type": "Feature",
  "properties": {
    "addr:full":"Avda Espa\u00f1a-calahonda, S/n Mijas Costa M\u00e1laga 29649",
    "addr:housenumber":"s / n",
    "addr:postcode":"29649",
    "addr:street":"Avda Espan\u0303A-Calahonda",
    "iso:country":"ES",
    "sg:address":"Avda Espa\u00f1a-calahonda, S/n",
    "sg:city":"Mijas Costa",
    "sg:orig_category":"Cajas De Ahorro",
    "sg:phone":"+34 952 93 98 20",
    "sg:postcode":"29649",
    "sg:province":"M\u00e1laga",
    "wof:name":"Cajamar",
    "wof:placetype":"venue"
},
  "geometry": {"coordinates":[-4.7157039642,36.4931945801],"type":"Point"}
}