{
  "type": "Feature",
  "properties": {
    "addr:full":"Plaz Santo, 1 Malagon Ciudad Real 13420",
    "addr:housenumber":"1",
    "addr:postcode":"13420",
    "addr:street":"Santo",
    "iso:country":"ES",
    "sg:address":"Plaz Santo, 1",
    "sg:city":"Malagon",
    "sg:orig_category":"\u00d3ptica: Instrumentos (fabricaci\u00d3n)",
    "sg:phone":"+34 926 80 03 25",
    "sg:postcode":"13420",
    "sg:province":"Ciudad Real",
    "wof:name":"Navarrete Opticos S.l.",
    "wof:placetype":"venue"
},
  "geometry": {"coordinates":[-3.8537249565,39.1670913696],"type":"Point"}
}