{
  "type": "Feature",
  "properties": {
    "iso:country":"ES",
    "sg:address":"Calle de San Marcos, 4",
    "sg:city":"Ubeda",
    "sg:orig_category":"Transportes Por Carretera: Lotes Completos, Mercanc\u00cdas Diversas",
    "sg:phone":"+34 953 79 01 89",
    "sg:postcode":"23400",
    "sg:province":"Ja\u00e9n",
    "wof:name":"Carrero Martinez Maria Juana",
    "wof:placetype":"venue"
},
  "geometry": {"coordinates":[-3.3765289783,38.0092315674],"type":"Point"}
}