{
  "type": "Feature",
  "properties": {
    "addr:full":"Avda Fuente (de La), 1 Peligros Granada 18210",
    "addr:housenumber":"1",
    "addr:postcode":"18210",
    "addr:street":"Avda Fuente De La",
    "iso:country":"ES",
    "sg:address":"Avda Fuente (de La), 1",
    "sg:city":"Peligros",
    "sg:orig_category":"Caf\u00c9s, Bares, Cervecer\u00cdas",
    "sg:phone":"+34 958 40 20 68",
    "sg:postcode":"18210",
    "sg:province":"Granada",
    "wof:name":"A. Y G. Inmobiliaria Pacolo S.l.",
    "wof:placetype":"venue"
},
  "geometry": {"coordinates":[-3.6292908192,37.2309951782],"type":"Point"}
}