{
  "type": "Feature",
  "properties": {
    "iso:country":"ES",
    "sg:address":"C/ Nou, 50",
    "sg:city":"Ripollet",
    "sg:orig_category":"Bazares, Art\u00cdculos De Limpieza Y De Cocina (al Por Menor)",
    "sg:phone":"+34 935 86 47 60",
    "sg:postcode":"08291",
    "sg:province":"Barcelona",
    "wof:name":"Quesada Ferrer Mercedes",
    "wof:placetype":"venue"
},
  "geometry": {"coordinates":[2.1575191021,41.4981689453],"type":"Point"}
}