{
  "type": "Feature",
  "properties": {
    "addr:full":"Avda Principe Felipe, 35 Martos Ja\u00e9n 23600",
    "addr:housenumber":"35",
    "addr:postcode":"23600",
    "addr:street":"Avda Principe Felipe;Jae\u0301N",
    "iso:country":"ES",
    "sg:address":"Avda Principe Felipe, 35",
    "sg:city":"Martos",
    "sg:orig_category":"Centros De Educaci\u00d3n Especial",
    "sg:phone":"+34 953 55 20 84",
    "sg:postcode":"23600",
    "sg:province":"Ja\u00e9n",
    "wof:name":"Junta De Andalucia",
    "wof:placetype":"venue"
},
  "geometry": {"coordinates":[-3.9693980217,37.7177963257],"type":"Point"}
}