{
  "type": "Feature",
  "properties": {
    "iso:country":"ES",
    "sg:address":"Calle de Maestro Guridi, 7",
    "sg:city":"Torrejon Ardoz",
    "sg:orig_category":"Molduras, Junquillos, Listones Y Molduras Perforadas",
    "sg:phone":"+34 916 77 21 67",
    "sg:postcode":"28850",
    "sg:province":"Madrid",
    "wof:name":"Sempertegui Valdez Tomas Antonio",
    "wof:placetype":"venue"
},
  "geometry": {"coordinates":[-3.4884619713,40.459148407],"type":"Point"}
}