{
  "type": "Feature",
  "properties": {
    "addr:full":"Calle de Juan Montes, 28 Coru\u00d1a La Coru\u00f1a 15006",
    "addr:housenumber":"28",
    "addr:postcode":"15006",
    "addr:street":"Calle De Juan Montes;La Corun\u0303A",
    "iso:country":"ES",
    "sg:address":"Calle de Juan Montes, 28",
    "sg:city":"Coru\u00d1a",
    "sg:orig_category":"Asesor\u00cda De Formaci\u00d3n Y Gesti\u00d3n De Personal",
    "sg:phone":"+34 981 28 78 47",
    "sg:postcode":"15006",
    "sg:province":"La Coru\u00f1a",
    "wof:name":"Rodriguez Gomez Montserrat",
    "wof:placetype":"venue"
},
  "geometry": {"coordinates":[-8.3963184357,43.3532905579],"type":"Point"}
}