{
  "type": "Feature",
  "properties": {
    "addr:full":"Calle de Santa Cruz, 8 Villarramiel Palencia 34140",
    "addr:housenumber":"8",
    "addr:postcode":"34140",
    "addr:street":"Calle De Santa Cruz",
    "iso:country":"ES",
    "sg:address":"Calle de Santa Cruz, 8",
    "sg:city":"Villarramiel",
    "sg:orig_category":"Alimentaci\u00d3n General (al Por Menor)",
    "sg:phone":"+34 979 83 75 11",
    "sg:postcode":"34140",
    "sg:province":"Palencia",
    "wof:name":"Ultramarinos Anfer S.l.",
    "wof:placetype":"venue"
},
  "geometry": {"coordinates":[-4.91294384,42.0432510376],"type":"Point"}
}