{
  "type": "Feature",
  "properties": {
    "iso:country":"ES",
    "sg:address":"Arado, 8",
    "sg:city":"Ingenio",
    "sg:orig_category":"Arquitectos",
    "sg:phone":"+34 928 78 44 39",
    "sg:postcode":"35250",
    "sg:province":"Las Palmas",
    "wof:name":"Acosta Morales Francisco",
    "wof:placetype":"venue"
},
  "geometry": {"coordinates":[-15.444442749,27.9186496735],"type":"Point"}
}