{
  "type": "Feature",
  "properties": {
    "iso:country":"ES",
    "sg:address":"Calle de Terbio, 23",
    "sg:city":"Sevilla",
    "sg:orig_category":"Edici\u00d3n De Diarios, Revistas, Boletines",
    "sg:phone":"+34 954 35 71 53",
    "sg:postcode":"41007",
    "sg:province":"Sevilla",
    "wof:name":"Editorial Magisterio Espa\u00f1ol S.a.",
    "wof:placetype":"venue"
},
  "geometry": {"coordinates":[-5.9572992325,37.4075737],"type":"Point"}
}