{
  "type": "Feature",
  "properties": {
    "addr:full":"Trille Cadiz C\u00e1diz 11009",
    "addr:postcode":"11009",
    "addr:street":"Trille;Ca\u0301Diz",
    "iso:country":"ES",
    "sg:address":"Trille",
    "sg:city":"Cadiz",
    "sg:orig_category":"Ropa Para Se\u00d1oras (al Por Menor)",
    "sg:phone":"+34 956 25 40 87",
    "sg:postcode":"11009",
    "sg:province":"C\u00e1diz",
    "wof:name":"Mayo S.c.",
    "wof:placetype":"venue"
},
  "geometry": {"coordinates":[-6.2762942314,36.5119247437],"type":"Point"}
}