{
  "type": "Feature",
  "properties": {
    "iso:country":"ES",
    "sg:address":"Vallehermoso, 104",
    "sg:city":"Madrid",
    "sg:orig_category":"Inmobiliaria (agencias)",
    "sg:phone":"+34 915 54 12 43",
    "sg:postcode":"28003",
    "sg:province":"Madrid",
    "wof:name":"Socomiber S.a.",
    "wof:placetype":"venue"
},
  "geometry": {"coordinates":[-3.7080130577,40.4398078918],"type":"Point"}
}