{
  "type": "Feature",
  "properties": {
    "iso:country":"ES",
    "sg:address":"Comp. Sta. Ana, S/n",
    "sg:city":"Atarfe",
    "sg:orig_category":"Barnizadores",
    "sg:phone":"+34 958 43 46 07",
    "sg:postcode":"18230",
    "sg:province":"Granada",
    "wof:name":"Martinez Garcia Maria Antonia",
    "wof:placetype":"venue"
},
  "geometry": {"coordinates":[-3.6903159618,37.2228775024],"type":"Point"}
}