{
  "type": "Feature",
  "properties": {
    "iso:country":"ES",
    "sg:address":"Carrer de Caracas, 15",
    "sg:city":"Barcelona",
    "sg:orig_category":"Empresas De Carpinter\u00cda De Madera",
    "sg:phone":"+34 933 11 82 01",
    "sg:postcode":"08030",
    "sg:province":"Barcelona",
    "wof:name":"Ona Ona Barcelona S.l.",
    "wof:placetype":"venue"
},
  "geometry": {"coordinates":[2.2030079365,41.4418373108],"type":"Point"}
}