{
  "type": "Feature",
  "properties": {
    "iso:country":"ES",
    "sg:address":"Luga Vegueta (la), 73",
    "sg:city":"Vegueta",
    "sg:orig_category":"Productores Recolectores, Venta Directa De Vinos",
    "sg:phone":"+34 928 84 08 49",
    "sg:postcode":"35560",
    "sg:province":"Las Palmas",
    "sg:website":"www.tinache.net",
    "wof:name":"Pio Carvajal Maria Josefa",
    "wof:placetype":"venue"
},
  "geometry": {"coordinates":[-13.676823616,29.0662899017],"type":"Point"}
}