{
  "type": "Feature",
  "properties": {
    "iso:country":"ES",
    "sg:address":"Calle de Calderon De La Barca (de), 3",
    "sg:city":"Alcobendas",
    "sg:orig_category":"Empresarios",
    "sg:phone":"+34 916 51 12 71",
    "sg:postcode":"28100",
    "sg:province":"Madrid",
    "wof:name":"Navarro Moral Francisco",
    "wof:placetype":"venue"
},
  "geometry": {"coordinates":[-3.6488480568,40.5474853516],"type":"Point"}
}