{
  "type": "Feature",
  "properties": {
    "iso:country":"ES",
    "sg:address":"Avda Juan Carlos I, 58",
    "sg:city":"Fernan Nu\u00e7ez",
    "sg:orig_category":"Electricidad (montaje, Ensamblaje De Componentes)",
    "sg:phone":"+34 957 38 03 57",
    "sg:postcode":"14520",
    "sg:province":"C\u00f3rdoba",
    "wof:name":"Miranda Criado Baldomero",
    "wof:placetype":"venue"
},
  "geometry": {"coordinates":[-4.7143359184,37.6636161804],"type":"Point"}
}