{
  "type": "Feature",
  "properties": {
    "addr:full":"Carrer de Francesc Macia, 17 Suredes D'en Mairo-grecs-muntanyeta Girona 17480",
    "addr:housenumber":"17",
    "addr:postcode":"17480",
    "addr:street":"Carrer De Francesc Macia",
    "iso:country":"ES",
    "sg:address":"Carrer de Francesc Macia, 17",
    "sg:city":"Suredes D'en Mairo-grecs-muntanyeta",
    "sg:orig_category":"Restaurantes",
    "sg:phone":"+34 972 25 73 37",
    "sg:postcode":"17480",
    "sg:province":"Girona",
    "wof:name":"La Mesa De Roses S.l.",
    "wof:placetype":"venue"
},
  "geometry": {"coordinates":[2.8303520679,41.9971847534],"type":"Point"}
}