{
  "type": "Feature",
  "properties": {
    "addr:full":"Calle de Gorbea, 18 Vitoria-gasteiz \u00c1lava 01012",
    "addr:housenumber":"18",
    "addr:postcode":"01012",
    "addr:street":"Calle De Gorbea",
    "iso:country":"ES",
    "sg:address":"Calle de Gorbea, 18",
    "sg:city":"Vitoria-gasteiz",
    "sg:orig_category":"Art\u00cdculos De Regalo (al Por Menor)",
    "sg:phone":"+34 945 22 28 15",
    "sg:postcode":"01012",
    "sg:province":"\u00c1lava",
    "wof:name":"Nieto Ramirez Roberto",
    "wof:placetype":"venue"
},
  "geometry": {"coordinates":[-2.6796240807,42.850189209],"type":"Point"}
}