{
  "type": "Feature",
  "properties": {
    "iso:country":"ES",
    "sg:address":"Pati Esglesia Nova, 3",
    "sg:city":"Alcover",
    "sg:orig_category":"Pescader\u00cdas (al Por Menor)",
    "sg:phone":"+34 977 76 01 92",
    "sg:postcode":"43460",
    "sg:province":"Tarragona",
    "wof:name":"Elias Figueras Sonia",
    "wof:placetype":"venue"
},
  "geometry": {"coordinates":[1.1689039469,41.2629203796],"type":"Point"}
}