{
  "type": "Feature",
  "properties": {
    "iso:country":"ES",
    "sg:address":"Calle de Almorox, 6",
    "sg:city":"Madrid",
    "sg:orig_category":"Contenedores (mercanc\u00cdas)",
    "sg:phone":"+34 914 59 55 53",
    "sg:postcode":"28039",
    "sg:province":"Madrid",
    "wof:name":"Villamor Ruiz Emeterio",
    "wof:placetype":"venue"
},
  "geometry": {"coordinates":[-3.7116229534,40.4635047913],"type":"Point"}
}