{
  "type": "Feature",
  "properties": {
    "addr:full":"Calle de Real, 12 Boecillo Valladolid 47151",
    "addr:housenumber":"12",
    "addr:postcode":"47151",
    "addr:street":"Calle De Real",
    "iso:country":"ES",
    "sg:address":"Calle de Real, 12",
    "sg:city":"Boecillo",
    "sg:orig_category":"Agencias Y Agentes Comerciales, Representantes",
    "sg:phone":"+34 983 55 27 45",
    "sg:postcode":"47151",
    "sg:province":"Valladolid",
    "sg:website":"www.diccionariosdemedicina.com",
    "wof:name":"Zirtabe S.a.",
    "wof:placetype":"venue"
},
  "geometry": {"coordinates":[-4.6985201836,41.5482292175],"type":"Point"}
}