{
  "type": "Feature",
  "properties": {
    "addr:full":"Calle de Severo Ochoa, 1 Gabia Grande Granada 18110",
    "addr:housenumber":"1",
    "addr:postcode":"18110",
    "addr:street":"Calle De Severo Ochoa",
    "iso:country":"ES",
    "sg:address":"Calle de Severo Ochoa, 1",
    "sg:city":"Gabia Grande",
    "sg:orig_category":"Muebles, Minoristas",
    "sg:phone":"+34 958 58 02 56",
    "sg:postcode":"18110",
    "sg:province":"Granada",
    "wof:name":"Muebles Lujan S.l.",
    "wof:placetype":"venue"
},
  "geometry": {"coordinates":[-3.6663579941,37.1362724304],"type":"Point"}
}