{
  "type": "Feature",
  "properties": {
    "addr:full":"Carrer de Pau Claris, 29 Sabadell Barcelona 08205",
    "addr:housenumber":"29",
    "addr:postcode":"08205",
    "addr:street":"Carrer De Pau Claris",
    "iso:country":"ES",
    "sg:address":"Carrer de Pau Claris, 29",
    "sg:city":"Sabadell",
    "sg:orig_category":"Ingeniero",
    "sg:phone":"+34 937 15 58 09",
    "sg:postcode":"08205",
    "sg:province":"Barcelona",
    "wof:name":"Ingebox Iberica Sl",
    "wof:placetype":"venue"
},
  "geometry": {"coordinates":[2.1037449837,41.5411491394],"type":"Point"}
}