{
  "type": "Feature",
  "properties": {
    "addr:full":"Pase Zorrilla, 46 Valladolid Valladolid 47006",
    "addr:housenumber":"46",
    "addr:postcode":"47006",
    "addr:street":"Zorrilla",
    "iso:country":"ES",
    "sg:address":"Pase Zorrilla, 46",
    "sg:city":"Valladolid",
    "sg:orig_category":"Ense\u00d1anza: Idiomas",
    "sg:phone":"+34 983 35 86 97",
    "sg:postcode":"47006",
    "sg:province":"Valladolid",
    "wof:name":"Fonolingua S.l",
    "wof:placetype":"venue"
},
  "geometry": {"coordinates":[-4.7347579002,41.6445236206],"type":"Point"}
}