{
  "type": "Feature",
  "properties": {
    "iso:country":"ES",
    "sg:address":"Calle de Guadiana, 16",
    "sg:city":"Ciudad Real",
    "sg:classifiers":[
        {
            "category":"Personal",
            "subcategory":"Barber",
            "type":"Services"
        }
    ],
    "sg:phone":"+34 926 21 11 32",
    "sg:postcode":"13002",
    "sg:province":"Ciudad Real",
    "sg:tags":[
        "caballeros",
        "de",
        "peluqueros"
    ],
    "wof:name":"Alcaide Barba Jesus",
    "wof:placetype":"venue"
},
  "geometry": {"coordinates":[-3.9344542027,38.9859771729],"type":"Point"}
}