{
  "type": "Feature",
  "properties": {
    "iso:country":"ES",
    "sg:address":"Cno Santa Anna, 8",
    "sg:city":"Xativa",
    "sg:orig_category":"Electromec\u00c1nica",
    "sg:phone":"+34 962 27 21 66",
    "sg:postcode":"46800",
    "sg:province":"Valencia",
    "wof:name":"Bataller Martinez Juan Vicente",
    "wof:placetype":"venue"
},
  "geometry": {"coordinates":[-0.5200830102,38.9934272766],"type":"Point"}
}