{
  "type": "Feature",
  "properties": {
    "iso:country":"ES",
    "sg:address":"Ctra Vilches, 4",
    "sg:city":"Ubeda",
    "sg:orig_category":"Agentes, Concesionarios Y Sucursales De Veh\u00cdculos",
    "sg:phone":"+34 953 79 60 68",
    "sg:postcode":"23400",
    "sg:province":"Ja\u00e9n",
    "wof:name":"Automoviles Siro S.l.",
    "wof:placetype":"venue"
},
  "geometry": {"coordinates":[-3.3709290028,38.0223999023],"type":"Point"}
}