{
  "type": "Feature",
  "properties": {
    "iso:country":"ES",
    "sg:address":"Carrer de Concili De Trento, 90",
    "sg:city":"Barcelona",
    "sg:orig_category":"Institutos De Belleza",
    "sg:phone":"+34 933 03 32 03",
    "sg:postcode":"08018",
    "sg:province":"Barcelona",
    "wof:name":"Centre D'estetic Estima't S.c.p.",
    "wof:placetype":"venue"
},
  "geometry": {"coordinates":[2.1954159737,41.4132194519],"type":"Point"}
}