{
  "type": "Feature",
  "properties": {
    "addr:full":"Calle de Alcalde Antonio Martinez, 13 Albatera Alicante 03340",
    "addr:housenumber":"13",
    "addr:postcode":"03340",
    "addr:street":"Calle De Alcalde Antonio Martinez",
    "iso:country":"ES",
    "sg:address":"Calle de Alcalde Antonio Martinez, 13",
    "sg:city":"Albatera",
    "sg:orig_category":"Ropa Para Ni\u00d1os (al Por Menor)",
    "sg:phone":"+34 965 48 75 17",
    "sg:postcode":"03340",
    "sg:province":"Alicante",
    "wof:name":"Confecciones Bugui Sociedad Limitada",
    "wof:placetype":"venue"
},
  "geometry": {"coordinates":[-0.8700401187,38.1834716797],"type":"Point"}
}