{
  "type": "Feature",
  "properties": {
    "addr:full":"Calle de Brasil, 20 Gijon Asturias 33213",
    "addr:housenumber":"20",
    "addr:postcode":"33213",
    "addr:street":"Calle De Brasil",
    "iso:country":"ES",
    "sg:address":"Calle de Brasil, 20",
    "sg:city":"Gijon",
    "sg:orig_category":"Supermercados Y Hipermercados",
    "sg:phone":"+34 985 30 14 04",
    "sg:postcode":"33213",
    "sg:province":"Asturias",
    "wof:name":"Hijos De Luis Rodriguez S.a.",
    "wof:placetype":"venue"
},
  "geometry": {"coordinates":[-5.6997709274,43.540397644],"type":"Point"}
}