{
  "type": "Feature",
  "properties": {
    "addr:full":"Carrer de Pablo Iglesias, 53 Palma Islas Baleares 07004",
    "addr:housenumber":"53",
    "addr:postcode":"07004",
    "addr:street":"Carrer De Pablo Iglesias",
    "iso:country":"ES",
    "sg:address":"Carrer de Pablo Iglesias, 53",
    "sg:city":"Palma",
    "sg:orig_category":"Equipo De Refrigeraci\u00d3n Industrial",
    "sg:phone":"+34 971 29 29 59",
    "sg:postcode":"07004",
    "sg:province":"Islas Baleares",
    "wof:name":"Perello Capella Antonio",
    "wof:placetype":"venue"
},
  "geometry": {"coordinates":[2.6550569534,39.583065033],"type":"Point"}
}