{
  "type": "Feature",
  "properties": {
    "iso:country":"ES",
    "sg:address":"Av Mossen Josep Guiteras, 7",
    "sg:city":"Vic",
    "sg:orig_category":"Molduras, Junquillos, Listones Y Molduras Perforadas",
    "sg:phone":"+34 938 89 50 52",
    "sg:postcode":"08500",
    "sg:province":"Barcelona",
    "wof:name":"Mesa Salguero Francisco",
    "wof:placetype":"venue"
},
  "geometry": {"coordinates":[2.2566859722,41.9125595093],"type":"Point"}
}