{
  "type": "Feature",
  "properties": {
    "addr:full":"Carrer de Arago, 517 Barcelona Barcelona 08013",
    "addr:housenumber":"517",
    "addr:postcode":"08013",
    "addr:street":"Carrer De Arago",
    "iso:country":"ES",
    "sg:address":"Carrer de Arago, 517",
    "sg:city":"Barcelona",
    "sg:orig_category":"Confecci\u00d3n De Trajes Para Se\u00d1oras",
    "sg:phone":"+34 932 45 05 02",
    "sg:postcode":"08013",
    "sg:province":"Barcelona",
    "wof:name":"Pino Juarez Concepcion Del",
    "wof:placetype":"venue"
},
  "geometry": {"coordinates":[2.1822500229,41.4053382874],"type":"Point"}
}