{
  "type": "Feature",
  "properties": {
    "addr:full":"Pase General Davila, 84 Santander Cantabria 39006",
    "addr:housenumber":"84",
    "addr:postcode":"39006",
    "addr:street":"Davila",
    "iso:country":"ES",
    "sg:address":"Pase General Davila, 84",
    "sg:city":"Santander",
    "sg:orig_category":"Papel Pintado (al Por Menor)",
    "sg:phone":"+34 942 21 81 50",
    "sg:postcode":"39006",
    "sg:province":"Cantabria",
    "wof:name":"Andreu Cimiano Santiago",
    "wof:placetype":"venue"
},
  "geometry": {"coordinates":[-3.8019378185,43.4676055908],"type":"Point"}
}