{
  "type": "Feature",
  "properties": {
    "addr:full":"Rua Zaragoza, 62 Vigo Pontevedra 36211",
    "addr:housenumber":"62",
    "addr:postcode":"36211",
    "addr:street":"Rua Zaragoza",
    "iso:country":"ES",
    "sg:address":"Rua Zaragoza, 62",
    "sg:city":"Vigo",
    "sg:orig_category":"Pescader\u00cdas (al Por Menor)",
    "sg:phone":"+34 986 47 15 58",
    "sg:postcode":"36211",
    "sg:province":"Pontevedra",
    "wof:name":"Pescaderias El Anzuelo S.l",
    "wof:placetype":"venue"
},
  "geometry": {"coordinates":[-8.7285928726,42.2235374451],"type":"Point"}
}