{
  "type": "Feature",
  "properties": {
    "iso:country":"ES",
    "sg:address":"C/ Jose Bernad Amoros, 8",
    "sg:city":"Elche",
    "sg:orig_category":"Aparcamientos (infraestructuras, Accesorios)",
    "sg:phone":"+34 965 46 84 08",
    "sg:postcode":"03205",
    "sg:province":"Alicante",
    "wof:name":"Vera Huerta Joaquina",
    "wof:placetype":"venue"
},
  "geometry": {"coordinates":[-0.7086420059,38.2697372437],"type":"Point"}
}