{
  "type": "Feature",
  "properties": {
    "addr:full":"Calle de Ermita, 15 Huetor-vega Granada 18198",
    "addr:housenumber":"15",
    "addr:postcode":"18198",
    "addr:street":"Calle De Ermita",
    "iso:country":"ES",
    "sg:address":"Calle de Ermita, 15",
    "sg:city":"Huetor-vega",
    "sg:orig_category":"Bancos",
    "sg:phone":"+34 958 50 23 66",
    "sg:postcode":"18198",
    "sg:province":"Granada",
    "wof:name":"Caja Rural De Granada",
    "wof:placetype":"venue"
},
  "geometry": {"coordinates":[-3.5702719688,37.1453437805],"type":"Point"}
}