{
  "type": "Feature",
  "properties": {
    "addr:full":"Carr Tuejar, S/n Eliana Valencia 46183",
    "addr:housenumber":"s / n",
    "addr:postcode":"46183",
    "addr:street":"Carr Tuejar",
    "iso:country":"ES",
    "sg:address":"Carr Tuejar, S/n",
    "sg:city":"Eliana",
    "sg:orig_category":"Agencias De Viajes",
    "sg:phone":"+34 962 74 21 04",
    "sg:postcode":"46183",
    "sg:province":"Valencia",
    "wof:name":"Arecibo El Osito S.l.",
    "wof:placetype":"venue"
},
  "geometry": {"coordinates":[-0.5228300095,39.5754737854],"type":"Point"}
}