{
  "type": "Feature",
  "properties": {
    "iso:country":"ES",
    "sg:address":"Calle de Gabriela Mistral, 12",
    "sg:city":"Loranca",
    "sg:classifiers":[
        {
            "category":"Autos & Motor Vehicles",
            "subcategory":"Automobile Sales",
            "type":"Retail Goods"
        }
    ],
    "sg:phone":"+34 914 86 45 70",
    "sg:postcode":"28942",
    "sg:province":"Madrid",
    "wof:name":"Auto Escuelas Nazaret S.l.",
    "wof:placetype":"venue"
},
  "geometry": {"coordinates":[-3.8328850269,40.295665741],"type":"Point"}
}