{
  "type": "Feature",
  "properties": {
    "addr:full":"Avda Filipinas, 40 Madrid Madrid 28003",
    "addr:housenumber":"40",
    "addr:postcode":"madrid;28003",
    "addr:street":"Avda Filipinas",
    "iso:country":"ES",
    "sg:address":"Avda Filipinas, 40",
    "sg:city":"Madrid",
    "sg:orig_category":"Inmobiliaria (agencias)",
    "sg:phone":"+34 915 53 47 52",
    "sg:postcode":"28003",
    "sg:province":"Madrid",
    "wof:name":"Ceciller S.l.",
    "wof:placetype":"venue"
},
  "geometry": {"coordinates":[-3.7072050571,40.4409866333],"type":"Point"}
}