{
  "type": "Feature",
  "properties": {
    "addr:full":"Psaj Caudal, 5 Malaga M\u00e1laga 29006",
    "addr:housenumber":"5",
    "addr:postcode":"29006",
    "addr:street":"Caudal;Ma\u0301Laga",
    "iso:country":"ES",
    "sg:address":"Psaj Caudal, 5",
    "sg:city":"Malaga",
    "sg:orig_category":"Electromec\u00c1nica",
    "sg:phone":"+34 952 02 32 36",
    "sg:postcode":"29006",
    "sg:province":"M\u00e1laga",
    "wof:name":"Padilla Escalona Jose Antonio",
    "wof:placetype":"venue"
},
  "geometry": {"coordinates":[-4.4813170433,36.7122840881],"type":"Point"}
}