{
  "type": "Feature",
  "properties": {
    "addr:full":"C/ Nord, 33 Ripollet Barcelona 08291",
    "addr:housenumber":"33",
    "addr:postcode":"08291",
    "addr:street":"C / Nord",
    "iso:country":"ES",
    "sg:address":"C/ Nord, 33",
    "sg:city":"Ripollet",
    "sg:orig_category":"Agencias De Viajes",
    "sg:phone":"+34 935 86 35 80",
    "sg:postcode":"08291",
    "sg:province":"Barcelona",
    "wof:name":"World Business Travel S.l.",
    "wof:placetype":"venue"
},
  "geometry": {"coordinates":[2.1448764801,41.4934234619],"type":"Point"}
}