{
  "type": "Feature",
  "properties": {
    "iso:country":"ES",
    "sg:address":"Avda Giorgeta, 37",
    "sg:city":"Valencia",
    "sg:orig_category":"M\u00c9dicos: Pediatr\u00cda. Enfermedades De Los Ni\u00d1os",
    "sg:phone":"+34 963 41 17 90",
    "sg:postcode":"46007",
    "sg:province":"Valencia",
    "wof:name":"Duran Garcia Enrique",
    "wof:placetype":"venue"
},
  "geometry": {"coordinates":[-0.3844400048,39.4593086243],"type":"Point"}
}