{
  "type": "Feature",
  "properties": {
    "iso:country":"ES",
    "sg:address":"Calle de Teide, 6",
    "sg:city":"Montijo",
    "sg:classifiers":[
        {
            "category":"Personal",
            "subcategory":"Barber",
            "type":"Services"
        }
    ],
    "sg:phone":"+34 924 45 27 62",
    "sg:postcode":"06480",
    "sg:province":"Badajoz",
    "sg:tags":[
        "caballeros",
        "de",
        "peluqueros"
    ],
    "wof:name":"Merino Peluqueros S.c.",
    "wof:placetype":"venue"
},
  "geometry": {"coordinates":[-6.6170592308,38.9090118408],"type":"Point"}
}