{
  "type": "Feature",
  "properties": {
    "iso:country":"ES",
    "sg:address":"Calle de Virgen De La Paz, 9",
    "sg:city":"Madrid",
    "sg:orig_category":"Asesor\u00cda Sobre Comunicaci\u00d3n De Empresas",
    "sg:phone":"+34 914 05 01 62",
    "sg:postcode":"28027",
    "sg:province":"Madrid",
    "sg:website":"www.agconsultores.com",
    "wof:name":"Alcala Grupo Consultores S.l.",
    "wof:placetype":"venue"
},
  "geometry": {"coordinates":[-3.6598875523,40.4327926636],"type":"Point"}
}