{
  "type": "Feature",
  "properties": {
    "addr:full":"Calle de Conde De La Ca\u00d1ada, 7 Ciudad Real Ciudad Real 13004",
    "addr:housenumber":"7",
    "addr:postcode":"13004",
    "addr:street":"Calle De Conde De La Can\u0303Ada",
    "iso:country":"ES",
    "sg:address":"Calle de Conde De La Ca\u00d1ada, 7",
    "sg:city":"Ciudad Real",
    "sg:orig_category":"Peluquer\u00cdas, Peluquer\u00cda Mixta",
    "sg:phone":"+34 926 25 67 97",
    "sg:postcode":"13004",
    "sg:province":"Ciudad Real",
    "wof:name":"Garcia Gonzalez Raquel",
    "wof:placetype":"venue"
},
  "geometry": {"coordinates":[-3.9255878925,38.9861755371],"type":"Point"}
}