{
  "type": "Feature",
  "properties": {
    "iso:country":"ES",
    "sg:address":"Carr Bellprat, 16",
    "sg:city":"Igualada",
    "sg:orig_category":"Peluqueros: De Se\u00d1oras",
    "sg:phone":"+34 938 03 69 71",
    "sg:postcode":"08700",
    "sg:province":"Barcelona",
    "wof:name":"Romero Camacho Purificacion",
    "wof:placetype":"venue"
},
  "geometry": {"coordinates":[1.616353035,41.5875091553],"type":"Point"}
}