{
  "type": "Feature",
  "properties": {
    "addr:full":"Calle de Francisco Bele\u00d1a, 19 Pozuelo De Alarcon Madrid 28224",
    "addr:housenumber":"19",
    "addr:postcode":"28224",
    "addr:street":"Calle De Francisco Belen\u0303A",
    "iso:country":"ES",
    "sg:address":"Calle de Francisco Bele\u00d1a, 19",
    "sg:city":"Pozuelo De Alarcon",
    "sg:orig_category":"Centros Empresariales",
    "sg:phone":"+34 917 15 66 08",
    "sg:postcode":"28224",
    "sg:province":"Madrid",
    "wof:name":"Befac 2200 S.l.",
    "wof:placetype":"venue"
},
  "geometry": {"coordinates":[-3.795511961,40.44348526],"type":"Point"}
}