{
  "type": "Feature",
  "properties": {
    "iso:country":"ES",
    "sg:address":"Calle de Arco, 40",
    "sg:city":"Palmas De Gran Canaria",
    "sg:orig_category":"Electricidad: Instaladores",
    "sg:phone":"+34 928 23 15 24",
    "sg:postcode":"35004",
    "sg:province":"Las Palmas",
    "wof:name":"Lumican S.a.",
    "wof:placetype":"venue"
},
  "geometry": {"coordinates":[-15.4269227982,28.1148929596],"type":"Point"}
}