{
  "type": "Feature",
  "properties": {
    "iso:country":"ES",
    "sg:address":"Calle de Portalada (la), S/n",
    "sg:city":"Logro\u00f1o",
    "sg:orig_category":"Maquinaria Para Industrias Diversas",
    "sg:phone":"+34 941 23 83 47",
    "sg:postcode":"26006",
    "sg:province":"La Rioja",
    "wof:name":"Fernandez Berceo Maximo",
    "wof:placetype":"venue"
},
  "geometry": {"coordinates":[-2.409774065,42.4581260681],"type":"Point"}
}