{
  "type": "Feature",
  "properties": {
    "iso:country":"ES",
    "sg:address":"Calle de Principal, 24",
    "sg:city":"Maside",
    "sg:orig_category":"Molinos",
    "sg:phone":"+34 988 28 83 51",
    "sg:postcode":"32570",
    "sg:province":"Ourense",
    "wof:name":"Gonzalez Prieto Francisco",
    "wof:placetype":"venue"
},
  "geometry": {"coordinates":[-8.0243244171,42.4137878418],"type":"Point"}
}