{
  "type": "Feature",
  "properties": {
    "addr:full":"Pase San Vicente, 54 Salamanca Salamanca 37007",
    "addr:housenumber":"54",
    "addr:postcode":"37007",
    "addr:street":"San Vicente",
    "iso:country":"ES",
    "sg:address":"Pase San Vicente, 54",
    "sg:city":"Salamanca",
    "sg:orig_category":"\u00d3ptica: Instrumentos (fabricaci\u00d3n)",
    "sg:phone":"+34 923 28 14 73",
    "sg:postcode":"37007",
    "sg:province":"Salamanca",
    "wof:name":"Hoshi Alfayate Cruz",
    "wof:placetype":"venue"
},
  "geometry": {"coordinates":[-5.6729669571,40.9643173218],"type":"Point"}
}