{
  "type": "Feature",
  "properties": {
    "iso:country":"ES",
    "sg:address":"Pl Catalunya, 3",
    "sg:city":"Sant Vicen\u00c7 Dels Horts",
    "sg:orig_category":"Loter\u00cda Y T\u00d3mbola",
    "sg:phone":"+34 936 56 49 69",
    "sg:postcode":"08620",
    "sg:province":"Barcelona",
    "wof:name":"Homar Ferrer De Sant Jordi Maria Magdalena",
    "wof:placetype":"venue"
},
  "geometry": {"coordinates":[2.010876894,41.3927574158],"type":"Point"}
}