{
  "type": "Feature",
  "properties": {
    "iso:country":"ES",
    "sg:address":"Calle de Cid (el), 18",
    "sg:city":"Roda",
    "sg:orig_category":"Ambulancias",
    "sg:phone":"+34 967 44 03 98",
    "sg:postcode":"02630",
    "sg:province":"Albacete",
    "wof:name":"Ambulancias Julian De Toro E Hijos S.coop.",
    "wof:placetype":"venue"
},
  "geometry": {"coordinates":[-2.1625974178,39.2055091858],"type":"Point"}
}