{
  "type": "Feature",
  "properties": {
    "iso:country":"ES",
    "sg:address":"Carretera Mutilva Baja, 33",
    "sg:city":"Mutiloabeiti",
    "sg:orig_category":"Servicio De Salud",
    "sg:phone":"+34 948 24 97 17",
    "sg:postcode":"31192",
    "sg:province":"Navarra",
    "wof:name":"Europea De Servicios E Higiene S.a.",
    "wof:placetype":"venue"
},
  "geometry": {"coordinates":[-1.6271239519,42.7843284607],"type":"Point"}
}