{
  "type": "Feature",
  "properties": {
    "iso:country":"ES",
    "sg:address":"Calle de Puebla De Sanabria, 1",
    "sg:city":"Huelva",
    "sg:orig_category":"Inmobiliaria (agencias)",
    "sg:phone":"+34 959 54 35 66",
    "sg:postcode":"21007",
    "sg:province":"Huelva",
    "sg:website":"www.inmohuelva.es",
    "wof:name":"Gestion Inmobiliaria De Huelva S.l.",
    "wof:placetype":"venue"
},
  "geometry": {"coordinates":[-6.9324250221,37.2593994141],"type":"Point"}
}