{
  "type": "Feature",
  "properties": {
    "iso:country":"ES",
    "sg:address":"Via Edison (de), 29",
    "sg:city":"Boisaca",
    "sg:orig_category":"Electricidad (montaje, Ensamblaje De Componentes)",
    "sg:phone":"+34 981 58 80 39",
    "sg:postcode":"15890",
    "sg:province":"A Coru\u00f1a",
    "wof:name":"Talleres Electricos Lorenzo S.l.",
    "wof:placetype":"venue"
},
  "geometry": {"coordinates":[-8.4769210815,42.8835983276],"type":"Point"}
}