{
  "type": "Feature",
  "properties": {
    "addr:full":"Calle de Sagitario, S/n Frailes C\u00e1diz 11500",
    "addr:housenumber":"s",
    "addr:postcode":"11500",
    "addr:street":"Calle De Sagitario;/ N",
    "iso:country":"ES",
    "sg:address":"Calle de Sagitario, S/n",
    "sg:city":"Frailes",
    "sg:orig_category":"Supermercados Y Hipermercados",
    "sg:phone":"+34 956 85 21 53",
    "sg:postcode":"11500",
    "sg:province":"C\u00e1diz",
    "sg:website":"www.mercadona.es",
    "wof:name":"Mercadona S.a.",
    "wof:placetype":"venue"
},
  "geometry": {"coordinates":[-6.2197542191,36.6056632996],"type":"Point"}
}