{
  "type": "Feature",
  "properties": {
    "iso:country":"ES",
    "sg:address":"Calle de Eustaquio Lecue, 1",
    "sg:city":"Langreo",
    "sg:orig_category":"Institutos De Belleza",
    "sg:phone":"+34 985 68 25 56",
    "sg:postcode":"33930",
    "sg:province":"Asturias",
    "wof:name":"Nu\u00f1o Cuetos Maria Julia",
    "wof:placetype":"venue"
},
  "geometry": {"coordinates":[-5.6921958923,43.3061637878],"type":"Point"}
}