{
  "type": "Feature",
  "properties": {
    "addr:full":"Calle de Anselmo Cifuentes, 16 Gijon Asturias 33205",
    "addr:housenumber":"16",
    "addr:postcode":"33205",
    "addr:street":"Calle De Anselmo Cifuentes",
    "iso:country":"ES",
    "sg:address":"Calle de Anselmo Cifuentes, 16",
    "sg:city":"Gijon",
    "sg:orig_category":"Venta, Instalaci\u00d3n De Cocinas",
    "sg:phone":"+34 985 34 02 38",
    "sg:postcode":"33205",
    "sg:province":"Asturias",
    "wof:name":"Prieto Menendez Maria Luisa",
    "wof:placetype":"venue"
},
  "geometry": {"coordinates":[-5.6626324654,43.5381202698],"type":"Point"}
}