{
  "type": "Feature",
  "properties": {
    "addr:full":"Pl. San Martin, S/n Zamora Zamora 49001",
    "addr:housenumber":"s / n",
    "addr:postcode":"49001",
    "addr:street":"Pl. San Martin",
    "iso:country":"ES",
    "sg:address":"Pl. San Martin, S/n",
    "sg:city":"Zamora",
    "sg:orig_category":"Aparcamientos (infraestructuras, Accesorios)",
    "sg:phone":"+34 980 53 02 10",
    "sg:postcode":"49001",
    "sg:province":"Zamora",
    "wof:name":"Planta Aparcamientos Zamora",
    "wof:placetype":"venue"
},
  "geometry": {"coordinates":[-5.7514791489,41.502494812],"type":"Point"}
}