{
  "type": "Feature",
  "properties": {
    "iso:country":"ES",
    "sg:address":"Calle de Mayor, 45",
    "sg:city":"Mues",
    "sg:orig_category":"Autob\u00das (explotaci\u00d3n Y Servicios De)",
    "sg:phone":"+34 948 64 02 79",
    "sg:postcode":"31219",
    "sg:province":"Navarra",
    "wof:name":"Gaston Arrastio Felix",
    "wof:placetype":"venue"
},
  "geometry": {"coordinates":[-2.2262818813,42.6059417725],"type":"Point"}
}