{
  "type": "Feature",
  "properties": {
    "iso:country":"ES",
    "sg:address":"Calle de Aranjuez, 16",
    "sg:city":"Parla",
    "sg:orig_category":"Empresas De Carpinter\u00cda",
    "sg:phone":"+34 916 05 68 07",
    "sg:postcode":"28980",
    "sg:province":"Madrid",
    "wof:name":"Martinez Fernandez-pacheco David",
    "wof:placetype":"venue"
},
  "geometry": {"coordinates":[-3.7753477097,40.2430458069],"type":"Point"}
}