{
  "type": "Feature",
  "properties": {
    "addr:full":"Avda Espa\u00d1a, 221 Isla Cristina Huelva 21410",
    "addr:housenumber":"221",
    "addr:postcode":"21410",
    "addr:street":"Avda Espan\u0303A",
    "iso:country":"ES",
    "sg:address":"Avda Espa\u00d1a, 221",
    "sg:city":"Isla Cristina",
    "sg:orig_category":"Ropa Para Se\u00d1oras Y Caballeros (al Por Menor)",
    "sg:phone":"+34 959 34 43 39",
    "sg:postcode":"21410",
    "sg:province":"Huelva",
    "wof:name":"Romero Millan Manuel Alejandro",
    "wof:placetype":"venue"
},
  "geometry": {"coordinates":[-7.3170819283,37.1988067627],"type":"Point"}
}