{
  "type": "Feature",
  "properties": {
    "iso:country":"ES",
    "sg:address":"Avda Iryda, 9",
    "sg:city":"Tobarra",
    "sg:orig_category":"Transporte En General",
    "sg:phone":"+34 967 32 84 90",
    "sg:postcode":"02500",
    "sg:province":"Albacete",
    "wof:name":"Coloniales Ortega Sanchez S.l.",
    "wof:placetype":"venue"
},
  "geometry": {"coordinates":[-1.6859140396,38.5923347473],"type":"Point"}
}