{
  "type": "Feature",
  "properties": {
    "iso:country":"ES",
    "sg:address":"Avda Zaragoza, S/n",
    "sg:city":"Pina De Ebro",
    "sg:orig_category":"Cerrajer\u00cda, Ferrallista",
    "sg:phone":"+34 976 16 51 32",
    "sg:postcode":"50750",
    "sg:province":"Zaragoza",
    "wof:name":"Cuen Vidal Vicente",
    "wof:placetype":"venue"
},
  "geometry": {"coordinates":[-0.530238986,41.4925460815],"type":"Point"}
}