{
  "type": "Feature",
  "properties": {
    "iso:country":"ES",
    "sg:address":"Plaz Doctor Lopez Saiz, 2",
    "sg:city":"Burgos",
    "sg:orig_category":"Reposter\u00cdas",
    "sg:phone":"+34 947 20 93 31",
    "sg:postcode":"09001",
    "sg:province":"Burgos",
    "wof:name":"Sanchez Ramos Felix",
    "wof:placetype":"venue"
},
  "geometry": {"coordinates":[-3.7011189461,42.3324317932],"type":"Point"}
}