{
  "type": "Feature",
  "properties": {
    "iso:country":"ES",
    "sg:address":"Avda Frontera De Haro, 2",
    "sg:city":"Venta De Ba\u00e7os",
    "sg:orig_category":"Alquiler De V\u00cddeo",
    "sg:phone":"+34 979 77 07 71",
    "sg:postcode":"34200",
    "sg:province":"Palencia",
    "wof:name":"Perez Poza Bernardino",
    "wof:placetype":"venue"
},
  "geometry": {"coordinates":[-4.4889559746,41.9210777283],"type":"Point"}
}