{
  "type": "Feature",
  "properties": {
    "addr:full":"Calle de Carretera De Carcar, 19 Lodosa Navarra 31580",
    "addr:housenumber":"19",
    "addr:postcode":"31580",
    "addr:street":"Calle De Carretera De Carcar",
    "iso:country":"ES",
    "sg:address":"Calle de Carretera De Carcar, 19",
    "sg:city":"Lodosa",
    "sg:orig_category":"Contenedores (mercanc\u00cdas)",
    "sg:phone":"+34 948 69 32 68",
    "sg:postcode":"31580",
    "sg:province":"Navarra",
    "wof:name":"Ataun Munarriz Enrique",
    "wof:placetype":"venue"
},
  "geometry": {"coordinates":[-2.0747699738,42.4227561951],"type":"Point"}
}