{
  "type": "Feature",
  "properties": {
    "addr:full":"Calle de Senda De Los Huertos, 17 Jaen Ja\u00e9n 23002",
    "addr:housenumber":"17;jae\u0301n",
    "addr:postcode":"23002",
    "addr:street":"Calle De Senda De Los Huertos",
    "iso:country":"ES",
    "sg:address":"Calle de Senda De Los Huertos, 17",
    "sg:city":"Jaen",
    "sg:classifiers":[
        {
            "category":"Autos & Motor Vehicles",
            "subcategory":"Automobile Sales",
            "type":"Retail Goods"
        }
    ],
    "sg:phone":"+34 953 23 71 72",
    "sg:postcode":"23002",
    "sg:province":"Ja\u00e9n",
    "wof:name":"Centro De Formacion Vial Novel S.l.",
    "wof:placetype":"venue"
},
  "geometry": {"coordinates":[-3.7912590504,37.7621612549],"type":"Point"}
}