{
  "type": "Feature",
  "properties": {
    "iso:country":"ES",
    "sg:address":"Calle de Villa Benavente, 21",
    "sg:city":"Le\u00f3n",
    "sg:orig_category":"Zapater\u00cdas",
    "sg:phone":"+34 987 25 26 64",
    "sg:postcode":"24004",
    "sg:province":"Le\u00f3n",
    "wof:name":"Almacenes Altogar S. L.",
    "wof:placetype":"venue"
},
  "geometry": {"coordinates":[-5.573841095,42.5943107605],"type":"Point"}
}