{
  "type": "Feature",
  "properties": {
    "addr:full":"Carr Isabel Ii, D', 128 Soller Islas Baleares 07100",
    "addr:housenumber":"128",
    "addr:postcode":"07100",
    "addr:street":"Carr Isabel Ii D '",
    "iso:country":"ES",
    "sg:address":"Carr Isabel Ii, D', 128",
    "sg:city":"Soller",
    "sg:orig_category":"Delegados, Agentes De Tr\u00c1nsito, Auxiliares De Transporte Internacional",
    "sg:phone":"+34 971 63 51 05",
    "sg:postcode":"07100",
    "sg:province":"Islas Baleares",
    "wof:name":"Arbona Lopez Javier",
    "wof:placetype":"venue"
},
  "geometry": {"coordinates":[2.7112934589,39.7620277405],"type":"Point"}
}