{
  "type": "Feature",
  "properties": {
    "addr:full":"Calle de Mediodia, 1 Leganes Madrid 28911",
    "addr:housenumber":"1",
    "addr:postcode":"28911",
    "addr:street":"Calle De Mediodia",
    "iso:country":"ES",
    "sg:address":"Calle de Mediodia, 1",
    "sg:city":"Leganes",
    "sg:orig_category":"Asesor\u00cda Fiscal Y Jur\u00cddica",
    "sg:phone":"+34 917 76 01 15",
    "sg:postcode":"28911",
    "sg:province":"Madrid",
    "wof:name":"Bergaz Alonso Paulino",
    "wof:placetype":"venue"
},
  "geometry": {"coordinates":[-3.7664909363,40.3289337158],"type":"Point"}
}