{
  "type": "Feature",
  "properties": {
    "iso:country":"ES",
    "sg:address":"Cuadros, S/n",
    "sg:city":"La Robla",
    "sg:orig_category":"Ense\u00d1anza, Formaci\u00d3n Profesional: Aprendizaje",
    "sg:phone":"+34 987 57 24 07",
    "sg:postcode":"24640",
    "sg:province":"Le\u00f3n",
    "wof:name":"Parque Regional De Artilleria",
    "wof:placetype":"venue"
},
  "geometry": {"coordinates":[-5.6283431053,42.7975349426],"type":"Point"}
}