{
  "type": "Feature",
  "properties": {
    "addr:full":"Calle de Dr Fleming, 11 Guadalajara Guadalajara 19003",
    "addr:housenumber":"11",
    "addr:postcode":"19003",
    "addr:street":"Calle De Dr Fleming",
    "iso:country":"ES",
    "sg:address":"Calle de Dr Fleming, 11",
    "sg:city":"Guadalajara",
    "sg:orig_category":"Cl\u00cdnicas Dentales",
    "sg:phone":"+34 949 25 36 45",
    "sg:postcode":"19003",
    "sg:province":"Guadalajara",
    "wof:name":"Sarnyol C.b.",
    "wof:placetype":"venue"
},
  "geometry": {"coordinates":[-3.164593935,40.6283226013],"type":"Point"}
}