{
  "type": "Feature",
  "properties": {
    "addr:full":"Pase Canalejas, 13 Santander Cantabria 39004",
    "addr:housenumber":"13",
    "addr:postcode":"39004",
    "addr:street":"Canalejas",
    "iso:country":"ES",
    "sg:address":"Pase Canalejas, 13",
    "sg:city":"Santander",
    "sg:orig_category":"Inmobiliaria (agencias)",
    "sg:phone":"+34 942 22 56 82",
    "sg:postcode":"39004",
    "sg:province":"Cantabria",
    "wof:name":"Martinez Perez Ignacio Maria",
    "wof:placetype":"venue"
},
  "geometry": {"coordinates":[-3.7882339954,43.4643936157],"type":"Point"}
}