{
  "type": "Feature",
  "properties": {
    "iso:country":"ES",
    "sg:address":"Calle de Martinez De Medina, 3",
    "sg:city":"Sevilla",
    "sg:orig_category":"Inmobiliaria (agencias)",
    "sg:phone":"+34 954 53 04 92",
    "sg:postcode":"41018",
    "sg:province":"Sevilla",
    "wof:name":"Faneva S.l.",
    "wof:placetype":"venue"
},
  "geometry": {"coordinates":[-5.972946167,37.3851585388],"type":"Point"}
}