{
  "type": "Feature",
  "properties": {
    "iso:country":"ES",
    "sg:address":"Carrer de Freixa, 38",
    "sg:city":"Barcelona",
    "sg:orig_category":"M\u00c9dicos: Naturistas",
    "sg:phone":"+34 932 09 93 00",
    "sg:postcode":"08021",
    "sg:province":"Barcelona",
    "wof:name":"Garcia Macia Ramona",
    "wof:placetype":"venue"
},
  "geometry": {"coordinates":[2.1382749081,41.3991012573],"type":"Point"}
}