{
  "type": "Feature",
  "properties": {
    "addr:full":"Avda Reyes Catolicos, 58 Cuenca Cuenca 16003",
    "addr:housenumber":"58",
    "addr:postcode":"16003",
    "addr:street":"Avda Reyes Catolicos",
    "iso:country":"ES",
    "sg:address":"Avda Reyes Catolicos, 58",
    "sg:city":"Cuenca",
    "sg:orig_category":"Carnicer\u00cdas, Carnicer\u00cdas",
    "sg:phone":"+34 969 22 17 02",
    "sg:postcode":"16003",
    "sg:province":"Cuenca",
    "wof:name":"Jimenez Collado Angel",
    "wof:placetype":"venue"
},
  "geometry": {"coordinates":[-2.1383531094,40.0602302551],"type":"Point"}
}