{
  "type": "Feature",
  "properties": {
    "addr:full":"Av Saler, 13 Silla Valencia 46460",
    "addr:housenumber":"13",
    "addr:postcode":"46460",
    "addr:street":"Av Saler",
    "iso:country":"ES",
    "sg:address":"Av Saler, 13",
    "sg:city":"Silla",
    "sg:orig_category":"Congelados: Productos Alimentarios (fabricaci\u00d3n, Al Por Mayor)",
    "sg:phone":"+34 963 67 01 31",
    "sg:postcode":"46460",
    "sg:province":"Valencia",
    "wof:name":"Mar Products Trading S.a.",
    "wof:placetype":"venue"
},
  "geometry": {"coordinates":[-0.4069319963,39.3762168884],"type":"Point"}
}