{
  "type": "Feature",
  "properties": {
    "addr:full":"Ptda Algibe, S/n Guardamar Segura Alicante 03140",
    "addr:housenumber":"s",
    "addr:postcode":"03140",
    "addr:street":"Ptda Algibe;/ N",
    "iso:country":"ES",
    "sg:address":"Ptda Algibe, S/n",
    "sg:city":"Guardamar Segura",
    "sg:orig_category":"Distribuci\u00d3n De Petr\u00d3leo Y Derivados",
    "sg:phone":"+34 966 72 68 78",
    "sg:postcode":"03140",
    "sg:province":"Alicante",
    "wof:name":"Estacion De Servicio El Moncayo",
    "wof:placetype":"venue"
},
  "geometry": {"coordinates":[-0.6540290117,38.086681366],"type":"Point"}
}