{
  "type": "Feature",
  "properties": {
    "addr:full":"Avda Ramon Ortega, 5 Denia Alicante 03700",
    "addr:housenumber":"5",
    "addr:postcode":"03700",
    "addr:street":"Avda Ramon Ortega",
    "iso:country":"ES",
    "sg:address":"Avda Ramon Ortega, 5",
    "sg:city":"Denia",
    "sg:orig_category":"Procuradores",
    "sg:phone":"+34 966 42 50 68",
    "sg:postcode":"03700",
    "sg:province":"Alicante",
    "wof:name":"Marcilla Gallego Francisca",
    "wof:placetype":"venue"
},
  "geometry": {"coordinates":[0.1016929969,38.8371391296],"type":"Point"}
}