{
  "type": "Feature",
  "properties": {
    "iso:country":"ES",
    "sg:address":"Barr Aldape, 12",
    "sg:city":"Berrio-aldape",
    "sg:orig_category":"Alquiler De V\u00cddeo",
    "sg:phone":"+34 946 23 19 31",
    "sg:postcode":"48230",
    "sg:province":"Vizcaya",
    "wof:name":"Aldapeco Etxegileak S.l.",
    "wof:placetype":"venue"
},
  "geometry": {"coordinates":[-2.524212122,43.1335678101],"type":"Point"}
}