{
  "type": "Feature",
  "properties": {
    "iso:country":"ES",
    "sg:address":"Plaz Colon (de), 11",
    "sg:city":"Cordoba",
    "sg:orig_category":"M\u00c9dicos: Ginecolog\u00cda Y Obstetricia",
    "sg:phone":"+34 957 47 35 21",
    "sg:postcode":"14001",
    "sg:province":"C\u00f3rdoba",
    "wof:name":"Lopez-quecuty Puig Manuel",
    "wof:placetype":"venue"
},
  "geometry": {"coordinates":[-4.7769255638,37.8897323608],"type":"Point"}
}