{
  "type": "Feature",
  "properties": {
    "addr:full":"Calle de Araba, 9 Portugalete Vizcaya 48920",
    "addr:housenumber":"9",
    "addr:postcode":"48920",
    "addr:street":"Calle De Araba",
    "iso:country":"ES",
    "sg:address":"Calle de Araba, 9",
    "sg:city":"Portugalete",
    "sg:orig_category":"Zapatos (al Por Menor)",
    "sg:phone":"+34 944 61 10 33",
    "sg:postcode":"48920",
    "sg:province":"Vizcaya",
    "wof:name":"Baroja Ruiz De Azua Alfredo",
    "wof:placetype":"venue"
},
  "geometry": {"coordinates":[-3.0217208862,43.3191719055],"type":"Point"}
}