{
  "type": "Feature",
  "properties": {
    "addr:full":"Av M. Celayeta, 44 Iru\u00f1a Navarra 31014",
    "addr:housenumber":"44",
    "addr:postcode":"31014",
    "addr:street":"Av M. Celayeta",
    "iso:country":"ES",
    "sg:address":"Av M. Celayeta, 44",
    "sg:city":"Iru\u00f1a",
    "sg:orig_category":"Alimentaci\u00d3n General (al Por Menor)",
    "sg:phone":"+34 948 13 28 71",
    "sg:postcode":"31014",
    "sg:province":"Navarra",
    "wof:name":"Xu  Lingyan",
    "wof:placetype":"venue"
},
  "geometry": {"coordinates":[-1.6516283751,42.8269805908],"type":"Point"}
}