{
  "type": "Feature",
  "properties": {
    "addr:full":"Pg Bonanova, 34 Barcelona Barcelona 08022",
    "addr:housenumber":"34",
    "addr:postcode":"08022",
    "addr:street":"Pg Bonanova",
    "iso:country":"ES",
    "sg:address":"Pg Bonanova, 34",
    "sg:city":"Barcelona",
    "sg:orig_category":"Farmacias",
    "sg:phone":"+34 934 17 34 52",
    "sg:postcode":"08022",
    "sg:province":"Barcelona",
    "wof:name":"Melguizo Corzo Raquel",
    "wof:placetype":"venue"
},
  "geometry": {"coordinates":[2.1300919056,41.4049339294],"type":"Point"}
}