{
  "type": "Feature",
  "properties": {
    "addr:full":"Calle de Maria De Molina, 41 Madrid Madrid 28006",
    "addr:housenumber":"41",
    "addr:postcode":"madrid;28006",
    "addr:street":"Calle De Maria De Molina",
    "iso:country":"ES",
    "sg:address":"Calle de Maria De Molina, 41",
    "sg:city":"Madrid",
    "sg:orig_category":"Agentes, Concesionarios Y Sucursales De Veh\u00cdculos",
    "sg:phone":"+34 917 45 14 11",
    "sg:postcode":"28006",
    "sg:province":"Madrid",
    "sg:website":"www.quickmotor.es",
    "wof:name":"Quickmotor Madrid S.l.",
    "wof:placetype":"venue"
},
  "geometry": {"coordinates":[-3.6784510612,40.4375495911],"type":"Point"}
}