{
  "type": "Feature",
  "properties": {
    "iso:country":"ES",
    "sg:address":"Ibai-ondo Kalea, 28",
    "sg:city":"Azkoitia",
    "sg:orig_category":"\u00d3ptica: Instrumentos (fabricaci\u00d3n)",
    "sg:phone":"+34 943 02 50 80",
    "sg:postcode":"20720",
    "sg:province":"Guip\u00f9zcoa",
    "wof:name":"Ostadar, C.b.",
    "wof:placetype":"venue"
},
  "geometry": {"coordinates":[-2.3094289303,43.1783103943],"type":"Point"}
}