{
  "type": "Feature",
  "properties": {
    "iso:country":"ES",
    "sg:address":"Carrer de Antoni Rovira I Virgili (d'), 5",
    "sg:city":"Tarragona",
    "sg:orig_category":"M\u00c9dicos: Cardiolog\u00cda Y Afecciones Cardiovasculares",
    "sg:phone":"+34 977 23 35 16",
    "sg:postcode":"43002",
    "sg:province":"Tarragona",
    "wof:name":"Esque Ruiz Francisco",
    "wof:placetype":"venue"
},
  "geometry": {"coordinates":[1.2498799562,41.1176681519],"type":"Point"}
}