{
  "type": "Feature",
  "properties": {
    "addr:full":"Crt Toledo-cuenca, Km. 0057,4 Noblejas Toledo 45350",
    "addr:postcode":"45350",
    "addr:street":"Toledo-Cuenca Km. 0057,4",
    "iso:country":"ES",
    "sg:address":"Crt Toledo-cuenca, Km. 0057,4",
    "sg:city":"Noblejas",
    "sg:orig_category":"Escayola Y Productos De Escayola (fabricaci\u00d3n, Al Por Mayor)",
    "sg:phone":"+34 925 14 09 68",
    "sg:postcode":"45350",
    "sg:province":"Toledo",
    "wof:name":"Yesos Torrique S.a.",
    "wof:placetype":"venue"
},
  "geometry": {"coordinates":[-3.439738512,39.9919242859],"type":"Point"}
}