{
  "type": "Feature",
  "properties": {
    "iso:country":"ES",
    "sg:address":"Avda Mediterraneo, S/n",
    "sg:city":"Benidorm",
    "sg:orig_category":"Farmacias",
    "sg:phone":"+34 965 85 23 14",
    "sg:postcode":"03500",
    "sg:province":"Alicante",
    "wof:name":"Muriel Lopez Livio",
    "wof:placetype":"venue"
},
  "geometry": {"coordinates":[-0.1239840016,38.5371551514],"type":"Point"}
}