{
  "type": "Feature",
  "properties": {
    "iso:country":"ES",
    "sg:address":"Calle de Astillero, 8",
    "sg:city":"Bilbao",
    "sg:orig_category":"Librer\u00cdas",
    "sg:phone":"+34 944 42 02 60",
    "sg:postcode":"48013",
    "sg:province":"Vizcaya",
    "wof:name":"Castelo Lopez Antonio",
    "wof:placetype":"venue"
},
  "geometry": {"coordinates":[-3.0972034931,43.3288841248],"type":"Point"}
}