{
  "type": "Feature",
  "properties": {
    "addr:full":"Calle de La Fabrica, 24 Alcora Castell\u00f3n 12110",
    "addr:housenumber":"24",
    "addr:postcode":"12110",
    "addr:street":"Calle De La Fabrica;Castello\u0301N",
    "iso:country":"ES",
    "sg:address":"Calle de La Fabrica, 24",
    "sg:city":"Alcora",
    "sg:orig_category":"Alquiler De V\u00cddeo",
    "sg:phone":"+34 964 36 37 18",
    "sg:postcode":"12110",
    "sg:province":"Castell\u00f3n",
    "wof:name":"Collado Soriano Isabel",
    "wof:placetype":"venue"
},
  "geometry": {"coordinates":[-0.2127320021,40.0726776123],"type":"Point"}
}