{
  "type": "Feature",
  "properties": {
    "addr:full":"Calle de Fuente Del Berro, 13 Madrid Madrid 28009",
    "addr:housenumber":"13",
    "addr:postcode":"madrid;28009",
    "addr:street":"Calle De Fuente Del Berro",
    "iso:country":"ES",
    "sg:address":"Calle de Fuente Del Berro, 13",
    "sg:city":"Madrid",
    "sg:orig_category":"Encuadernaci\u00d3n E Impresi\u00d3n De Folletos",
    "sg:phone":"+34 914 01 96 34",
    "sg:postcode":"28009",
    "sg:province":"Madrid",
    "wof:name":"Povedano Hernando Julian",
    "wof:placetype":"venue"
},
  "geometry": {"coordinates":[-3.6706318855,40.4261550903],"type":"Point"}
}