{
  "type": "Feature",
  "properties": {
    "addr:full":"Rua Saavedra Meneses, 52 Betanzos La Coru\u00f1a 15300",
    "addr:housenumber":"52",
    "addr:postcode":"15300",
    "addr:street":"Rua Saavedra Meneses;La",
    "iso:country":"ES",
    "sg:address":"Rua Saavedra Meneses, 52",
    "sg:city":"Betanzos",
    "sg:orig_category":"Electricidad: Instaladores",
    "sg:phone":"+34 981 77 17 54",
    "sg:postcode":"15300",
    "sg:province":"La Coru\u00f1a",
    "wof:name":"Exergia Electicidad Y Climatizacion S.l.",
    "wof:placetype":"venue"
},
  "geometry": {"coordinates":[-8.2080984116,43.281829834],"type":"Point"}
}