{
  "type": "Feature",
  "properties": {
    "addr:full":"Calle de Iru\u00d1a, 1 Mungia Vizcaya 48100",
    "addr:housenumber":"1",
    "addr:postcode":"48100",
    "addr:street":"Calle De Irun\u0303A",
    "iso:country":"ES",
    "sg:address":"Calle de Iru\u00d1a, 1",
    "sg:city":"Mungia",
    "sg:orig_category":"Electricidad: Instaladores",
    "sg:phone":"+34 946 15 60 27",
    "sg:postcode":"48100",
    "sg:province":"Vizcaya",
    "wof:name":"Jose Luis Elorduy Gurtubai",
    "wof:placetype":"venue"
},
  "geometry": {"coordinates":[-2.8405170441,43.3527641296],"type":"Point"}
}