{
  "type": "Feature",
  "properties": {
    "addr:full":"Calle de Mejico, 25 S. Fernando C\u00e1diz 11100",
    "addr:housenumber":"25",
    "addr:postcode":"11100",
    "addr:street":"Calle De Mejico;S. Fernando Ca\u0301Diz",
    "iso:country":"ES",
    "sg:address":"Calle de Mejico, 25",
    "sg:city":"S. Fernando",
    "sg:orig_category":"Abogados",
    "sg:phone":"+34 956 48 62 47",
    "sg:postcode":"11100",
    "sg:province":"C\u00e1diz",
    "wof:name":"Fernandez Cosme Miguel Angel",
    "wof:placetype":"venue"
},
  "geometry": {"coordinates":[-6.2172040939,36.4505653381],"type":"Point"}
}