{
  "type": "Feature",
  "properties": {
    "iso:country":"ES",
    "sg:address":"Calle de Islas Marquesas, 19",
    "sg:city":"Madrid",
    "sg:orig_category":"Ingenier\u00cda, Centros De Estudios (diversos)",
    "sg:phone":"+34 913 73 27 76",
    "sg:postcode":"28035",
    "sg:province":"Madrid",
    "wof:name":"Barrasa Fernandez Gabriel",
    "wof:placetype":"venue"
},
  "geometry": {"coordinates":[-3.7262840271,40.4757766724],"type":"Point"}
}