{
  "type": "Feature",
  "properties": {
    "addr:full":"Calle de Iturribide, 41 Bilbao Vizcaya 48006",
    "addr:housenumber":"41",
    "addr:postcode":"48006",
    "addr:street":"Calle De Iturribide",
    "iso:country":"ES",
    "sg:address":"Calle de Iturribide, 41",
    "sg:city":"Bilbao",
    "sg:orig_category":"Molduras, Junquillos, Listones Y Molduras Perforadas",
    "sg:phone":"+34 944 02 99 24",
    "sg:postcode":"48006",
    "sg:province":"Vizcaya",
    "wof:name":"Feux Teixeira Marin",
    "wof:placetype":"venue"
},
  "geometry": {"coordinates":[-2.9179139137,43.2575645447],"type":"Point"}
}