{
  "type": "Feature",
  "properties": {
    "addr:full":"Loureis, 1 Portonovo Pontevedra 36970",
    "addr:housenumber":"1",
    "addr:postcode":"36970",
    "addr:street":"Loureis",
    "iso:country":"ES",
    "sg:address":"Loureis, 1",
    "sg:city":"Portonovo",
    "sg:orig_category":"Ingenier\u00cda, Centros De Estudios (diversos)",
    "sg:phone":"+34 986 69 07 80",
    "sg:postcode":"36970",
    "sg:province":"Pontevedra",
    "wof:name":"Lores Uhia Pablo",
    "wof:placetype":"venue"
},
  "geometry": {"coordinates":[-8.8260879517,42.3942642212],"type":"Point"}
}