{
  "type": "Feature",
  "properties": {
    "addr:full":"Subida Al Faro, 61 Cabo Palos Murcia 30370",
    "addr:housenumber":"61",
    "addr:postcode":"30370",
    "addr:street":"Subida Al Faro",
    "iso:country":"ES",
    "sg:address":"Subida Al Faro, 61",
    "sg:city":"Cabo Palos",
    "sg:orig_category":"Artes Gr\u00c1ficas, Artes Pl\u00c1sticas: Material Y Suministros (al Por Menor)",
    "sg:phone":"+34 968 33 72 66",
    "sg:postcode":"30370",
    "sg:province":"Murcia",
    "wof:name":"Pescado Cabomar S.l.",
    "wof:placetype":"venue"
},
  "geometry": {"coordinates":[-0.7274389863,37.6292953491],"type":"Point"}
}