{
  "type": "Feature",
  "properties": {
    "addr:full":"Rua Bolivia, 6 Vigo Pontevedra 36203",
    "addr:housenumber":"6",
    "addr:postcode":"36203",
    "addr:street":"Rua Bolivia",
    "iso:country":"ES",
    "sg:address":"Rua Bolivia, 6",
    "sg:city":"Vigo",
    "sg:orig_category":"Gases Industriales",
    "sg:phone":"+34 986 49 34 69",
    "sg:postcode":"36203",
    "sg:province":"Pontevedra",
    "wof:name":"Jocar Vigo Instalaciones S.l.",
    "wof:placetype":"venue"
},
  "geometry": {"coordinates":[-8.7201251984,42.231754303],"type":"Point"}
}