{
  "type": "Feature",
  "properties": {
    "iso:country":"ES",
    "sg:address":"Calle de Pe\u00d1alara (de), 5",
    "sg:city":"Pozuelo De Alarcon",
    "sg:orig_category":"Importaci\u00d3n",
    "sg:phone":"+34 913 51 96 31",
    "sg:postcode":"28224",
    "sg:province":"Madrid",
    "wof:name":"Zilevex S.l.",
    "wof:placetype":"venue"
},
  "geometry": {"coordinates":[-3.8004274368,40.4593200684],"type":"Point"}
}