{
  "type": "Feature",
  "properties": {
    "addr:full":"Carrer de Pujades, 93 Barcelona Barcelona 08005",
    "addr:housenumber":"93",
    "addr:postcode":"08005",
    "addr:street":"Carrer De Pujades",
    "iso:country":"ES",
    "sg:address":"Carrer de Pujades, 93",
    "sg:city":"Barcelona",
    "sg:orig_category":"Molduras, Junquillos, Listones Y Molduras Perforadas",
    "sg:phone":"+34 933 09 17 77",
    "sg:postcode":"08005",
    "sg:province":"Barcelona",
    "wof:name":"Wu  Minhua",
    "wof:placetype":"venue"
},
  "geometry": {"coordinates":[2.1954870224,41.39793396],"type":"Point"}
}