{
  "type": "Feature",
  "properties": {
    "addr:full":"Pol Ind Dehesa Boyal, S/n Pozoblanco C\u00f3rdoba 14400",
    "addr:housenumber":"s / n",
    "addr:postcode":"14400",
    "iso:country":"ES",
    "sg:address":"Pol Ind Dehesa Boyal, S/n",
    "sg:city":"Pozoblanco",
    "sg:orig_category":"Carnicer\u00cdas, Carnicer\u00cdas",
    "sg:phone":"+34 957 77 28 92",
    "sg:postcode":"14400",
    "sg:province":"C\u00f3rdoba",
    "wof:name":"Jamones Y Embutidos Ibericos Sanchez Romero S.l.",
    "wof:placetype":"venue"
},
  "geometry": {"coordinates":[-4.7484517097,38.2839393616],"type":"Point"}
}