{
  "type": "Feature",
  "properties": {
    "addr:full":"Calle de Hacendita (la), 22 Dos Hermanas Sevilla 41700",
    "addr:housenumber":"22",
    "addr:postcode":"41700",
    "addr:street":"Calle De Hacendita La",
    "iso:country":"ES",
    "sg:address":"Calle de Hacendita (la), 22",
    "sg:city":"Dos Hermanas",
    "sg:orig_category":"Ense\u00d1anza Variada",
    "sg:phone":"+34 954 72 52 55",
    "sg:postcode":"41700",
    "sg:province":"Sevilla",
    "wof:name":"Academia Audio Tacto Visual S.l.",
    "wof:placetype":"venue"
},
  "geometry": {"coordinates":[-5.92795,37.28397],"type":"Point"}
}