{
  "type": "Feature",
  "properties": {
    "addr:full":"Avda. Benito Far\u00f1as, 13 A Ramallosa Pontevedra 36393",
    "addr:housenumber":"13 a",
    "addr:postcode":"36393",
    "addr:street":"Avda. Benito Farn\u0303As",
    "iso:country":"ES",
    "sg:address":"Avda. Benito Far\u00f1as, 13",
    "sg:city":"A Ramallosa",
    "sg:orig_category":"Centros De Educaci\u00d3n Especial",
    "sg:phone":"+34 986 35 45 95",
    "sg:postcode":"36393",
    "sg:province":"Pontevedra",
    "wof:name":"Colexio Publico Sabaris",
    "wof:placetype":"venue"
},
  "geometry": {"coordinates":[-8.8274269104,42.1040344238],"type":"Point"}
}