{
  "type": "Feature",
  "properties": {
    "iso:country":"ES",
    "sg:address":"Calle de Santo, 23",
    "sg:city":"Carrion Calatrava",
    "sg:orig_category":"Panader\u00cdas, Pasteler\u00cdas, Boller\u00cda Industriale (fabricaci\u00d3n, Al Por Mayor)",
    "sg:phone":"+34 926 81 40 61",
    "sg:postcode":"13150",
    "sg:province":"Ciudad Real",
    "wof:name":"Mero De Haro Mariano",
    "wof:placetype":"venue"
},
  "geometry": {"coordinates":[-3.8206169605,39.0172042847],"type":"Point"}
}