{
  "type": "Feature",
  "properties": {
    "iso:country":"ES",
    "sg:address":"Pase Pereda, 22",
    "sg:city":"Santander",
    "sg:orig_category":"Abogados",
    "sg:phone":"+34 942 31 27 47",
    "sg:postcode":"39004",
    "sg:province":"Cantabria",
    "wof:name":"Serrano Goyria Juan Pablo",
    "wof:placetype":"venue"
},
  "geometry": {"coordinates":[-3.8008520603,43.4621696472],"type":"Point"}
}