{
  "type": "Feature",
  "properties": {
    "addr:full":"Calle de Esterlines, 15 Donostia-san Sebastian Guip\u00f9zcoa 20003",
    "addr:housenumber":"15",
    "addr:postcode":"20003",
    "addr:street":"Calle De Esterlines",
    "iso:country":"ES",
    "sg:address":"Calle de Esterlines, 15",
    "sg:city":"Donostia-san Sebastian",
    "sg:orig_category":"Lencer\u00cda Femenina, Corseter\u00cda, Trajes De Ba\u00d1o (al Por Menor)",
    "sg:phone":"+34 943 42 76 93",
    "sg:postcode":"20003",
    "sg:province":"Guip\u00f9zcoa",
    "wof:name":"Luis Diaz Angela",
    "wof:placetype":"venue"
},
  "geometry": {"coordinates":[-1.9849973917,43.3227958679],"type":"Point"}
}