{
  "type": "Feature",
  "properties": {
    "addr:full":"Cami Porrassa, 10 Magaluf Islas Baleares 07181",
    "addr:housenumber":"10",
    "addr:postcode":"07181",
    "addr:street":"Porrassa",
    "iso:country":"ES",
    "sg:address":"Cami Porrassa, 10",
    "sg:city":"Magaluf",
    "sg:orig_category":"Iglesia Cat\u00d3lica",
    "sg:phone":"+34 971 13 03 23",
    "sg:postcode":"07181",
    "sg:province":"Islas Baleares",
    "wof:name":"Obispado De Mallorca",
    "wof:placetype":"venue"
},
  "geometry": {"coordinates":[2.5277099609,39.5041885376],"type":"Point"}
}