{
  "type": "Feature",
  "properties": {
    "iso:country":"ES",
    "sg:address":"Calle de Santa Vicenta, 4",
    "sg:city":"Coria",
    "sg:classifiers":[
        {
            "category":"Communications",
            "type":"Services"
        }
    ],
    "sg:phone":"+34 927 50 14 25",
    "sg:postcode":"10800",
    "sg:province":"C\u00e1ceres",
    "sg:tags":[
        "televisiones",
        "y",
        "radio"
    ],
    "wof:name":"Sociedad Espa\u00f1ola De Radiodifusion S.a.",
    "wof:placetype":"venue"
},
  "geometry": {"coordinates":[-6.5333662033,39.9856109619],"type":"Point"}
}