{
  "type": "Feature",
  "properties": {
    "addr:full":"Avgd Horchata, 18 Alboraya Valencia 46120",
    "addr:housenumber":"18",
    "addr:postcode":"46120",
    "addr:street":"Horchata",
    "iso:country":"ES",
    "sg:address":"Avgd Horchata, 18",
    "sg:city":"Alboraya",
    "sg:orig_category":"\u00d3ptica: Instrumentos (fabricaci\u00d3n)",
    "sg:phone":"+34 961 86 25 26",
    "sg:postcode":"46120",
    "sg:province":"Valencia",
    "wof:name":"Leira Opticos C.d.",
    "wof:placetype":"venue"
},
  "geometry": {"coordinates":[-0.3405140042,39.4990692139],"type":"Point"}
}