{
  "type": "Feature",
  "properties": {
    "addr:full":"Landeta Hiribidea, 40 Azpeitia Guip\u00f9zcoa 20730",
    "addr:housenumber":"40",
    "addr:postcode":"20730",
    "addr:street":"Landeta Hiribidea;Guipu\u0300Zcoa",
    "iso:country":"ES",
    "sg:address":"Landeta Hiribidea, 40",
    "sg:city":"Azpeitia",
    "sg:orig_category":"Rectificaci\u00d3n, Mecanizado, Fresado",
    "sg:phone":"+34 943 15 08 87",
    "sg:postcode":"20730",
    "sg:province":"Guip\u00f9zcoa",
    "wof:name":"Juan Garmendia Bastida Y Otro Cdad",
    "wof:placetype":"venue"
},
  "geometry": {"coordinates":[-2.2546570301,43.1761665344],"type":"Point"}
}