{
  "type": "Feature",
  "properties": {
    "addr:full":"Calle de Zaragoza, 21 Tauste Zaragoza 50660",
    "addr:housenumber":"21",
    "addr:postcode":"50660",
    "addr:street":"Calle De Zaragoza",
    "iso:country":"ES",
    "sg:address":"Calle de Zaragoza, 21",
    "sg:city":"Tauste",
    "sg:orig_category":"Farmacias",
    "sg:phone":"+34 976 85 47 41",
    "sg:postcode":"50660",
    "sg:province":"Zaragoza",
    "wof:name":"Usan Conde Concepcion",
    "wof:placetype":"venue"
},
  "geometry": {"coordinates":[-1.2539379597,41.9192123413],"type":"Point"}
}