{
  "type": "Feature",
  "properties": {
    "addr:full":"Calle de Obispo Rey Redondo, 6 San Cristobal De La Laguna Santa Cruz De Tenerife 38201",
    "addr:housenumber":"6",
    "addr:postcode":"38201",
    "addr:street":"Calle De Obispo Rey Redondo",
    "iso:country":"ES",
    "sg:address":"Calle de Obispo Rey Redondo, 6",
    "sg:city":"San Cristobal De La Laguna",
    "sg:orig_category":"Zapatos (al Por Menor)",
    "sg:phone":"+34 922 25 16 38",
    "sg:postcode":"38201",
    "sg:province":"Santa Cruz De Tenerife",
    "wof:name":"Teleropa S.l.",
    "wof:placetype":"venue"
},
  "geometry": {"coordinates":[-16.3151111603,28.4879646301],"type":"Point"}
}