{
  "type": "Feature",
  "properties": {
    "addr:full":"Ptge. Joan Miro, 16 S. Joan Despi Barcelona 08970",
    "addr:housenumber":"16",
    "addr:postcode":"08970",
    "addr:street":"Joan Miro;S. Joan Despi",
    "iso:country":"ES",
    "sg:address":"Ptge. Joan Miro, 16",
    "sg:city":"S. Joan Despi",
    "sg:orig_category":"Confecci\u00d3n (fabricaci\u00d3n, Al Por Mayor)",
    "sg:phone":"+34 934 77 01 78",
    "sg:postcode":"08970",
    "sg:province":"Barcelona",
    "wof:name":"Escuse-mi S.l.",
    "wof:placetype":"venue"
},
  "geometry": {"coordinates":[2.05747509,41.376449585],"type":"Point"}
}