{
  "type": "Feature",
  "properties": {
    "iso:country":"ES",
    "sg:address":"O Coto(brabio), 109",
    "sg:city":"Coto",
    "sg:orig_category":"Obras Y Organismos Sociales",
    "sg:phone":"+34 981 77 03 25",
    "sg:postcode":"15319",
    "sg:province":"La Coru\u00f1a",
    "wof:name":"Residencia Garcia Hermanos En Betanzos Hermanitas De Ancianos Desamparados Prov Galicia",
    "wof:placetype":"venue"
},
  "geometry": {"coordinates":[-8.0784473419,43.3035011292],"type":"Point"}
}