{
  "type": "Feature",
  "properties": {
    "iso:country":"ES",
    "sg:address":"Avda Carlos I De, 28",
    "sg:city":"Donostia-san Sebastian",
    "sg:orig_category":"Abogados",
    "sg:phone":"+34 943 46 06 38",
    "sg:postcode":"20011",
    "sg:province":"Guip\u00f9zcoa",
    "wof:name":"Alvarez Antolin Gerardo",
    "wof:placetype":"venue"
},
  "geometry": {"coordinates":[-1.9789128304,43.3032073975],"type":"Point"}
}