{
  "type": "Feature",
  "properties": {
    "iso:country":"ES",
    "sg:address":"Calle de Carretera Callosa, 21",
    "sg:city":"Altea Vella",
    "sg:orig_category":"Fisioterapia",
    "sg:phone":"+34 965 84 69 99",
    "sg:postcode":"03599",
    "sg:province":"Alicante",
    "wof:name":"Olivares Ripoll Alejandro",
    "wof:placetype":"venue"
},
  "geometry": {"coordinates":[-0.0442065001,38.6300354004],"type":"Point"}
}