{
  "type": "Feature",
  "properties": {
    "addr:full":"Carr Francesc Lairet, 14 Balaguer Lleida 25600",
    "addr:housenumber":"14",
    "addr:postcode":"25600",
    "addr:street":"Carr Francesc Lairet",
    "iso:country":"ES",
    "sg:address":"Carr Francesc Lairet, 14",
    "sg:city":"Balaguer",
    "sg:orig_category":"Comercio, Reparaci\u00d3n De Motocicletas, Bicicletas Y Piezas Sueltas",
    "sg:phone":"+34 973 44 65 23",
    "sg:postcode":"25600",
    "sg:province":"Lleida",
    "wof:name":"Casals Collado Jose Maria",
    "wof:placetype":"venue"
},
  "geometry": {"coordinates":[0.8007109761,41.7846717834],"type":"Point"}
}