{
  "type": "Feature",
  "properties": {
    "iso:country":"ES",
    "sg:address":"Carr Carlos Sarthou, 9",
    "sg:city":"Xativa",
    "sg:orig_category":"Ropa Para Se\u00d1oras (al Por Menor)",
    "sg:phone":"+34 962 28 36 16",
    "sg:postcode":"46800",
    "sg:province":"Valencia",
    "wof:name":"Martinez Zaragoza Jose Luis",
    "wof:placetype":"venue"
},
  "geometry": {"coordinates":[-0.5221030116,38.9916305542],"type":"Point"}
}