{
  "type": "Feature",
  "properties": {
    "iso:country":"ES",
    "sg:address":"Carrer de Huelva, 138",
    "sg:city":"Barcelona",
    "sg:orig_category":"Empresas De Limpieza",
    "sg:phone":"+34 933 05 32 63",
    "sg:postcode":"08020",
    "sg:province":"Barcelona",
    "wof:name":"Nausinet S.l.",
    "wof:placetype":"venue"
},
  "geometry": {"coordinates":[2.2013099194,41.4210357666],"type":"Point"}
}