{
  "type": "Feature",
  "properties": {
    "iso:country":"ES",
    "sg:address":"Calle de Mendoza, 11",
    "sg:city":"Palmas De Gran Canaria",
    "sg:orig_category":"Mec\u00c1nico Del Autom\u00d3vil",
    "sg:phone":"+34 928 46 60 20",
    "sg:postcode":"35008",
    "sg:province":"Las Palmas",
    "wof:name":"Talleres Rumari S.r.l.",
    "wof:placetype":"venue"
},
  "geometry": {"coordinates":[-15.4203186035,28.1537303925],"type":"Point"}
}