{
  "type": "Feature",
  "properties": {
    "iso:country":"ES",
    "sg:address":"Calle de Artajona, 31",
    "sg:city":"Madrid",
    "sg:classifiers":[
        {
            "category":"Personal",
            "subcategory":"Barber",
            "type":"Services"
        }
    ],
    "sg:phone":"+34 914 59 76 45",
    "sg:postcode":"28039",
    "sg:province":"Madrid",
    "sg:tags":[
        "caballeros",
        "de",
        "peluqueros"
    ],
    "wof:name":"Lopez Fernandez Luis",
    "wof:placetype":"venue"
},
  "geometry": {"coordinates":[-3.717730999,40.4644699097],"type":"Point"}
}