{
  "type": "Feature",
  "properties": {
    "addr:full":"Calle de Inzakardi, 2 Doneztebe Navarra 31740",
    "addr:housenumber":"2",
    "addr:postcode":"31740",
    "addr:street":"Calle De Inzakardi;Navarra",
    "iso:country":"ES",
    "sg:address":"Calle de Inzakardi, 2",
    "sg:city":"Doneztebe",
    "sg:orig_category":"\u00d3ptica: Instrumentos (fabricaci\u00d3n)",
    "sg:phone":"+34 948 45 03 45",
    "sg:postcode":"31740",
    "sg:province":"Navarra",
    "wof:name":"Optica Baztan S.l.",
    "wof:placetype":"venue"
},
  "geometry": {"coordinates":[-1.6680599451,43.1320114136],"type":"Point"}
}