{
  "type": "Feature",
  "properties": {
    "addr:full":"Avda Nueve De Octubre, 5 Puerto Valencia 46520",
    "addr:housenumber":"5",
    "addr:postcode":"46520",
    "addr:street":"Avda Nueve De Octubre",
    "iso:country":"ES",
    "sg:address":"Avda Nueve De Octubre, 5",
    "sg:city":"Puerto",
    "sg:classifiers":[
        {
            "category":"Casinos & Gambling",
            "type":"Entertainment"
        }
    ],
    "sg:phone":"+34 962 67 98 24",
    "sg:postcode":"46520",
    "sg:province":"Valencia",
    "sg:tags":[
        "locale",
        "de",
        "juego"
    ],
    "wof:name":"Comercial Igove 94 S.l.",
    "wof:placetype":"venue"
},
  "geometry": {"coordinates":[-0.2230550051,39.6596984863],"type":"Point"}
}