{
  "type": "Feature",
  "properties": {
    "addr:full":"Calle de Espa\u00d1a, 49 Almoradi Alicante 03160",
    "addr:housenumber":"49",
    "addr:postcode":"03160",
    "addr:street":"Calle De Espan\u0303A",
    "iso:country":"ES",
    "sg:address":"Calle de Espa\u00d1a, 49",
    "sg:city":"Almoradi",
    "sg:orig_category":"Pe\u00d1as Y Asociaciones Varias",
    "sg:phone":"+34 965 70 04 04",
    "sg:postcode":"03160",
    "sg:province":"Alicante",
    "wof:name":"Asociacion De La Tercera Edad",
    "wof:placetype":"venue"
},
  "geometry": {"coordinates":[-0.7881358862,38.1075172424],"type":"Point"}
}