{
  "type": "Feature",
  "properties": {
    "addr:full":"Calle de Santa Clara, 20 Zamora Zamora 49014",
    "addr:housenumber":"20",
    "addr:postcode":"49014",
    "addr:street":"Calle De Santa Clara",
    "iso:country":"ES",
    "sg:address":"Calle de Santa Clara, 20",
    "sg:city":"Zamora",
    "sg:orig_category":"Perfumer\u00cda (al Por Menor)",
    "sg:phone":"+34 980 53 25 02",
    "sg:postcode":"49014",
    "sg:province":"Zamora",
    "wof:name":"Cepeda Morales Encarnacion",
    "wof:placetype":"venue"
},
  "geometry": {"coordinates":[-5.7424612045,41.5060386658],"type":"Point"}
}