{
  "type": "Feature",
  "properties": {
    "iso:country":"ES",
    "sg:address":"Carrer de Sant Antoni, 49",
    "sg:city":"Sentmenat",
    "sg:orig_category":"Empresas De Pintura Y Revestimientos",
    "sg:phone":"+34 937 15 02 26",
    "sg:postcode":"08181",
    "sg:province":"Barcelona",
    "wof:name":"Curtiellas Cruells Jose",
    "wof:placetype":"venue"
},
  "geometry": {"coordinates":[2.1375510693,41.6097450256],"type":"Point"}
}