{
  "type": "Feature",
  "properties": {
    "addr:full":"Avda Estacion (de La), 6 Almeria Almer\u00eda 04005",
    "addr:housenumber":"6",
    "addr:postcode":"04005",
    "addr:street":"Avda Estacion De La",
    "iso:country":"ES",
    "sg:address":"Avda Estacion (de La), 6",
    "sg:city":"Almeria",
    "sg:orig_category":"Ingenier\u00cda, Centros De Estudios (diversos)",
    "sg:phone":"+34 950 27 74 11",
    "sg:postcode":"04005",
    "sg:province":"Almer\u00eda",
    "wof:name":"I.p.control S.l.",
    "wof:placetype":"venue"
},
  "geometry": {"coordinates":[-2.4596629143,36.8378715515],"type":"Point"}
}