{
  "type": "Feature",
  "properties": {
    "addr:full":"Carr Major, 91 S. Ramon Lleida 25215",
    "addr:housenumber":"91",
    "addr:postcode":"25215",
    "addr:street":"Carr Major;S. Ramon Lleida",
    "iso:country":"ES",
    "sg:address":"Carr Major, 91",
    "sg:city":"S. Ramon",
    "sg:orig_category":"Autob\u00das (explotaci\u00d3n Y Servicios De)",
    "sg:phone":"+34 973 52 40 07",
    "sg:postcode":"25215",
    "sg:province":"Lleida",
    "wof:name":"Munt  Jose",
    "wof:placetype":"venue"
},
  "geometry": {"coordinates":[1.3630199432,41.725894928],"type":"Point"}
}