{
  "type": "Feature",
  "properties": {
    "addr:full":"Ctra Almadraba, 4 Principe Felipe Ceuta 51002",
    "addr:housenumber":"4",
    "addr:postcode":"51002",
    "addr:street":"Ctra Almadraba",
    "iso:country":"ES",
    "sg:address":"Ctra Almadraba, 4",
    "sg:city":"Principe Felipe",
    "sg:orig_category":"Alimentaci\u00d3n General (al Por Menor)",
    "sg:phone":"+34 956 50 55 81",
    "sg:postcode":"51002",
    "sg:province":"Ceuta",
    "wof:name":"Berrocal Carretero Juan",
    "wof:placetype":"venue"
},
  "geometry": {"coordinates":[-5.3157300949,35.8891601562],"type":"Point"}
}