{
  "type": "Feature",
  "properties": {
    "iso:country":"ES",
    "sg:address":"Av De El Romeral (p I Antequera), S/n",
    "sg:city":"Antequera",
    "sg:orig_category":"Ense\u00d1anza Variada",
    "sg:phone":"+34 952 84 18 59",
    "sg:postcode":"29200",
    "sg:province":"M\u00e1laga",
    "wof:name":"Jose Antonio Sanchez Cozar S.l.",
    "wof:placetype":"venue"
},
  "geometry": {"coordinates":[-4.536049366,37.2492408752],"type":"Point"}
}