{
  "type": "Feature",
  "properties": {
    "iso:country":"ES",
    "sg:address":"Plaz Mayor, 7",
    "sg:city":"Madrid",
    "sg:orig_category":"Caf\u00c9s, Bares, Cervecer\u00cdas",
    "sg:phone":"+34 913 65 40 79",
    "sg:postcode":"28012",
    "sg:province":"Madrid",
    "wof:name":"Hernandez Martinez Maria Cristina",
    "wof:placetype":"venue"
},
  "geometry": {"coordinates":[-3.7065720558,40.4151039124],"type":"Point"}
}