{
  "type": "Feature",
  "properties": {
    "addr:full":"Monasterio Iranzu, 2 Iru\u00f1a Navarra 31011",
    "addr:housenumber":"2",
    "addr:postcode":"31011",
    "addr:street":"Iranzu",
    "iso:country":"ES",
    "sg:address":"Monasterio Iranzu, 2",
    "sg:city":"Iru\u00f1a",
    "sg:orig_category":"Venta, Instalaci\u00d3n De Calefacci\u00d3n",
    "sg:phone":"+34 948 17 51 23",
    "sg:postcode":"31011",
    "sg:province":"Navarra",
    "wof:name":"Cooperativa Calor Eguaras",
    "wof:placetype":"venue"
},
  "geometry": {"coordinates":[-1.6600760221,42.816318512],"type":"Point"}
}