{
  "type": "Feature",
  "properties": {
    "iso:country":"ES",
    "sg:address":"Calle de Maiatzaren Bata Kalea, 6",
    "sg:city":"Leioa",
    "sg:orig_category":"Mec\u00c1nico Del Autom\u00d3vil",
    "sg:phone":"+34 944 31 60 79",
    "sg:postcode":"48940",
    "sg:province":"Vizcaya",
    "wof:name":"Juan Balboa Rico",
    "wof:placetype":"venue"
},
  "geometry": {"coordinates":[-3.0055940151,43.3263816833],"type":"Point"}
}