{
  "type": "Feature",
  "properties": {
    "addr:full":"Cadernera, 1 S. Antonio Benageber Valencia 46184",
    "addr:housenumber":"1",
    "addr:postcode":"46184",
    "addr:street":"Cadernera;S. Antonio Benageber",
    "iso:country":"ES",
    "sg:address":"Cadernera, 1",
    "sg:city":"S. Antonio Benageber",
    "sg:orig_category":"Ingeniero",
    "sg:phone":"+34 961 35 14 41",
    "sg:postcode":"46184",
    "sg:province":"Valencia",
    "wof:name":"Lozano Morato Ignacio Jose",
    "wof:placetype":"venue"
},
  "geometry": {"coordinates":[-0.4961099923,39.5529289246],"type":"Point"}
}