{
  "type": "Feature",
  "properties": {
    "addr:full":"Ptge Joan Xxiii (parti), 4 Palma Islas Baleares 07002",
    "addr:housenumber":"4",
    "addr:postcode":"07002",
    "addr:street":"Ptge Joan Xxiii Parti",
    "iso:country":"ES",
    "sg:address":"Ptge Joan Xxiii (parti), 4",
    "sg:city":"Palma",
    "sg:orig_category":"Electrodom\u00c9sticos (al Por Menor)",
    "sg:phone":"+34 971 72 64 16",
    "sg:postcode":"07002",
    "sg:province":"Islas Baleares",
    "wof:name":"Cano Quesada Andres",
    "wof:placetype":"venue"
},
  "geometry": {"coordinates":[2.6527910233,39.5746955872],"type":"Point"}
}