{
  "type": "Feature",
  "properties": {
    "iso:country":"ES",
    "sg:address":"Calle de Maestros, 18",
    "sg:city":"Merida",
    "sg:orig_category":"Expertos Contables",
    "sg:phone":"+34 924 30 46 04",
    "sg:postcode":"06800",
    "sg:province":"Badajoz",
    "wof:name":"J.naharro Consultores S.r.l.l.",
    "wof:placetype":"venue"
},
  "geometry": {"coordinates":[-6.3437929153,38.9150772095],"type":"Point"}
}