{
  "type": "Feature",
  "properties": {
    "iso:country":"ES",
    "sg:address":"Carrer de Galera, 13",
    "sg:city":"Reus",
    "sg:orig_category":"Audiovisuales (producci\u00d3n, Edici\u00d3n, Realizaci\u00d3n)",
    "sg:phone":"+34 977 12 79 07",
    "sg:postcode":"43201",
    "sg:province":"Tarragona",
    "sg:website":"www.mabstv.com",
    "wof:name":"Videoproduccions Mab's S.l.",
    "wof:placetype":"venue"
},
  "geometry": {"coordinates":[1.1078619957,41.1548347473],"type":"Point"}
}