{
  "type": "Feature",
  "properties": {
    "iso:country":"ES",
    "sg:address":"Urb Playa Getares, S/n",
    "sg:city":"Algeciras",
    "sg:orig_category":"Farmacias",
    "sg:phone":"+34 956 60 53 16",
    "sg:postcode":"11207",
    "sg:province":"C\u00e1diz",
    "wof:name":"Perez Mateo Rosario",
    "wof:placetype":"venue"
},
  "geometry": {"coordinates":[-5.4444608688,36.0982589722],"type":"Point"}
}