{
  "type": "Feature",
  "properties": {
    "iso:country":"ES",
    "sg:address":"Calle de Juan Manuel Garcia Flores, 9",
    "sg:city":"Torre Esteban Hambran",
    "sg:orig_category":"Iglesia Cat\u00d3lica",
    "sg:phone":"+34 925 79 51 78",
    "sg:postcode":"45920",
    "sg:province":"Toledo",
    "wof:name":"Parroquia Santa Maria Magdalena",
    "wof:placetype":"venue"
},
  "geometry": {"coordinates":[-4.025138855,39.8618774414],"type":"Point"}
}