{
  "type": "Feature",
  "properties": {
    "addr:full":"Calle de Mayor, 14 Villamayor Santiago Cuenca 16415",
    "addr:housenumber":"14",
    "addr:postcode":"16415",
    "addr:street":"Calle De Mayor",
    "iso:country":"ES",
    "sg:address":"Calle de Mayor, 14",
    "sg:city":"Villamayor Santiago",
    "sg:orig_category":"Telas Y Sedas (al Por Menor)",
    "sg:phone":"+34 969 13 90 30",
    "sg:postcode":"16415",
    "sg:province":"Cuenca",
    "wof:name":"Tycanlop S. A.",
    "wof:placetype":"venue"
},
  "geometry": {"coordinates":[-2.9265239239,39.7297058105],"type":"Point"}
}