{
  "type": "Feature",
  "properties": {
    "iso:country":"ES",
    "sg:address":"Calle de Lirios, 26",
    "sg:city":"Isla Cristina",
    "sg:orig_category":"Agentes, Concesionarios Y Sucursales De Camiones Y Veh\u00cdculos Industriales",
    "sg:phone":"+34 959 33 21 40",
    "sg:postcode":"21410",
    "sg:province":"Huelva",
    "wof:name":"Madero Ojeda Juan Antonio",
    "wof:placetype":"venue"
},
  "geometry": {"coordinates":[-7.3204088211,37.2019309998],"type":"Point"}
}