{
  "type": "Feature",
  "properties": {
    "addr:full":"Carrer de Bailen, 145 Barcelona Barcelona 08037",
    "addr:housenumber":"145",
    "addr:postcode":"08037",
    "addr:street":"Carrer De Bailen",
    "iso:country":"ES",
    "sg:address":"Carrer de Bailen, 145",
    "sg:city":"Barcelona",
    "sg:orig_category":"Electrodom\u00c9sticos (al Por Menor)",
    "sg:phone":"+34 932 07 02 61",
    "sg:postcode":"08037",
    "sg:province":"Barcelona",
    "wof:name":"Sanchez Salgado Narciso",
    "wof:placetype":"venue"
},
  "geometry": {"coordinates":[2.1667981148,41.3996086121],"type":"Point"}
}