{
  "type": "Feature",
  "properties": {
    "addr:full":"Juan Martinez Meseguer, 1 Alquerias Murcia 30580",
    "addr:housenumber":"1",
    "addr:postcode":"30580",
    "addr:street":"Juan Martinez Meseguer",
    "iso:country":"ES",
    "sg:address":"Juan Martinez Meseguer, 1",
    "sg:city":"Alquerias",
    "sg:orig_category":"Abogados",
    "sg:phone":"+34 968 37 91 43",
    "sg:postcode":"30580",
    "sg:province":"Murcia",
    "wof:name":"Martinez Rolan Ana",
    "wof:placetype":"venue"
},
  "geometry": {"coordinates":[-1.0352619886,38.0136566162],"type":"Point"}
}