{
  "type": "Feature",
  "properties": {
    "iso:country":"ES",
    "sg:address":"Iturrama, 14",
    "sg:city":"Iru\u00f1a",
    "sg:orig_category":"Ropa Para Ni\u00d1os (al Por Menor)",
    "sg:phone":"+34 948 25 89 66",
    "sg:postcode":"31007",
    "sg:province":"Navarra",
    "wof:name":"Sucesores De Carlos Moreno S.l.",
    "wof:placetype":"venue"
},
  "geometry": {"coordinates":[-1.6523009539,42.8048095703],"type":"Point"}
}