{
  "type": "Feature",
  "properties": {
    "addr:full":"Lugar De Botica, S/n Botica La Coru\u00f1a 15145",
    "addr:housenumber":"/ n",
    "addr:postcode":"15145",
    "addr:street":"Lugar;S;Botica La Corun\u0303A",
    "iso:country":"ES",
    "sg:address":"Lugar De Botica, S/n",
    "sg:city":"Botica",
    "sg:orig_category":"Productos Fitosanitarios (negocio, Aplicaci\u00d3n)",
    "sg:phone":"+34 981 60 58 15",
    "sg:postcode":"15145",
    "sg:province":"La Coru\u00f1a",
    "wof:name":"Manuel Cotelo S.l.",
    "wof:placetype":"venue"
},
  "geometry": {"coordinates":[-8.5813436508,43.2482681274],"type":"Point"}
}