{
  "type": "Feature",
  "properties": {
    "iso:country":"ES",
    "sg:address":"Calle de Puerto Rico, S/n",
    "sg:city":"Alcantarilla",
    "sg:orig_category":"Delegados, Agentes De Tr\u00c1nsito, Auxiliares De Transporte Internacional",
    "sg:phone":"+34 968 89 56 81",
    "sg:postcode":"30820",
    "sg:province":"Murcia",
    "wof:name":"Tg Plus Transcamergomez S.a.u.",
    "wof:placetype":"venue"
},
  "geometry": {"coordinates":[-1.22103405,37.9716682434],"type":"Point"}
}