{
  "type": "Feature",
  "properties": {
    "iso:country":"ES",
    "sg:address":"Cm\u00d1o Laxe, 68",
    "sg:city":"Laxe",
    "sg:orig_category":"Farmacias",
    "sg:phone":"+34 986 47 26 31",
    "sg:postcode":"36214",
    "sg:province":"Pontevedra",
    "wof:name":"Priegue Fernandez Marina",
    "wof:placetype":"venue"
},
  "geometry": {"coordinates":[-8.7059106827,42.2124443054],"type":"Point"}
}