{
  "type": "Feature",
  "properties": {
    "iso:country":"ES",
    "sg:address":"Calle de Angustias, 17",
    "sg:city":"Valladolid",
    "sg:orig_category":"Arquitectos",
    "sg:phone":"+34 983 26 66 08",
    "sg:postcode":"47003",
    "sg:province":"Valladolid",
    "wof:name":"Grupo Arquitectos Asociados S.l.",
    "wof:placetype":"venue"
},
  "geometry": {"coordinates":[-4.7241134644,41.6559143066],"type":"Point"}
}