{
  "type": "Feature",
  "properties": {
    "iso:country":"ES",
    "sg:address":"Carrer de Isaac Albeniz, 6",
    "sg:city":"Peguera",
    "sg:orig_category":"Asociaciones Y Clubs Deportivos",
    "sg:phone":"+34 971 68 57 04",
    "sg:postcode":"07160",
    "sg:province":"Islas Baleares",
    "wof:name":"Martin Fernandez Maria Del Carmen",
    "wof:placetype":"venue"
},
  "geometry": {"coordinates":[2.4597249031,39.535068512],"type":"Point"}
}