{
  "type": "Feature",
  "properties": {
    "iso:country":"ES",
    "sg:address":"Carrer de Illa De Cuba, 14",
    "sg:city":"Sitges",
    "sg:orig_category":"Vinos Y Licores (venta Al Por Menor)",
    "sg:phone":"+34 938 11 20 75",
    "sg:postcode":"08870",
    "sg:province":"Barcelona",
    "wof:name":"Seleccio De Vins S L",
    "wof:placetype":"venue"
},
  "geometry": {"coordinates":[1.8100199699,41.237651825],"type":"Point"}
}