{
  "type": "Feature",
  "properties": {
    "addr:full":"Calle de Alcala, 98 Madrid Madrid 28009",
    "addr:housenumber":"98",
    "addr:postcode":"madrid;28009",
    "addr:street":"Calle De Alcala",
    "iso:country":"ES",
    "sg:address":"Calle de Alcala, 98",
    "sg:city":"Madrid",
    "sg:orig_category":"Abogados",
    "sg:phone":"+34 915 75 36 47",
    "sg:postcode":"28009",
    "sg:province":"Madrid",
    "wof:name":"Valladares Diez-canseco Adela",
    "wof:placetype":"venue"
},
  "geometry": {"coordinates":[-3.6748709679,40.4250297546],"type":"Point"}
}