{
  "type": "Feature",
  "properties": {
    "addr:full":"Avda Antonio Chacon, 4 Zafra Badajoz 06300",
    "addr:housenumber":"4",
    "addr:postcode":"06300",
    "addr:street":"Avda Antonio Chacon",
    "iso:country":"ES",
    "sg:address":"Avda Antonio Chacon, 4",
    "sg:city":"Zafra",
    "sg:orig_category":"Panader\u00cdas, Panader\u00cdas",
    "sg:phone":"+34 924 55 05 98",
    "sg:postcode":"06300",
    "sg:province":"Badajoz",
    "wof:name":"Lopez Burrero Francisco Jose",
    "wof:placetype":"venue"
},
  "geometry": {"coordinates":[-6.4121069908,38.4245681763],"type":"Point"}
}