{
  "type": "Feature",
  "properties": {
    "addr:full":"Avda Cameros, 11 Villamediana Iregua La Rioja 26142",
    "addr:housenumber":"11",
    "addr:postcode":"26142",
    "addr:street":"Avda Cameros;Rioja",
    "iso:country":"ES",
    "sg:address":"Avda Cameros, 11",
    "sg:city":"Villamediana Iregua",
    "sg:orig_category":"Inform\u00c1tica: Material Y Suministros",
    "sg:phone":"+34 941 43 50 24",
    "sg:postcode":"26142",
    "sg:province":"La Rioja",
    "wof:name":"Webmatica,sl",
    "wof:placetype":"venue"
},
  "geometry": {"coordinates":[-2.4165656567,42.4243354797],"type":"Point"}
}