{
  "type": "Feature",
  "properties": {
    "addr:full":"Calle de Ba\u00d1os, 51 Bailen Ja\u00e9n 23710",
    "addr:housenumber":"51",
    "addr:postcode":"23710",
    "addr:street":"Calle De Ban\u0303Os;Jae\u0301N",
    "iso:country":"ES",
    "sg:address":"Calle de Ba\u00d1os, 51",
    "sg:city":"Bailen",
    "sg:orig_category":"Cooperativas Agr\u00cdcolas",
    "sg:phone":"+34 953 67 67 56",
    "sg:postcode":"23710",
    "sg:province":"Ja\u00e9n",
    "wof:name":"Cooperativa Agricola De Bailen",
    "wof:placetype":"venue"
},
  "geometry": {"coordinates":[-3.7724940777,38.0997390747],"type":"Point"}
}