{
  "type": "Feature",
  "properties": {
    "addr:full":"Carrer de Merce, 13 Premia Mar Barcelona 08330",
    "addr:housenumber":"13",
    "addr:postcode":"08330",
    "addr:street":"Carrer De Merce",
    "iso:country":"ES",
    "sg:address":"Carrer de Merce, 13",
    "sg:city":"Premia Mar",
    "sg:orig_category":"Tapiceros Y Tapiceros",
    "sg:phone":"+34 937 52 30 92",
    "sg:postcode":"08330",
    "sg:province":"Barcelona",
    "wof:name":"Andreu Segura Antonia",
    "wof:placetype":"venue"
},
  "geometry": {"coordinates":[2.3537547588,41.4945144653],"type":"Point"}
}