{
  "type": "Feature",
  "properties": {
    "iso:country":"ES",
    "sg:address":"Binixica, 125",
    "sg:city":"Binixiquer",
    "sg:orig_category":"Bibliotecas, Mediatecas",
    "sg:phone":"+34 971 15 35 03",
    "sg:postcode":"07712",
    "sg:province":"Islas Baleares",
    "wof:name":"Chevallier  Berangere",
    "wof:placetype":"venue"
},
  "geometry": {"coordinates":[4.1795349121,39.8723258972],"type":"Point"}
}