{
  "type": "Feature",
  "properties": {
    "addr:full":"Plaz De Las Marismas, 1 Lepe Huelva 21440",
    "addr:housenumber":"1",
    "addr:postcode":"21440",
    "addr:street":"Plaz;Las Marismas",
    "iso:country":"ES",
    "sg:address":"Plaz De Las Marismas, 1",
    "sg:city":"Lepe",
    "sg:orig_category":"Agentes Generales De Seguros",
    "sg:phone":"+34 959 38 03 22",
    "sg:postcode":"21440",
    "sg:province":"Huelva",
    "wof:name":"Bilbao Compa\u00f1ia Anonima De Seguros",
    "wof:placetype":"venue"
},
  "geometry": {"coordinates":[-7.2029190063,37.255241394],"type":"Point"}
}