{
  "type": "Feature",
  "properties": {
    "addr:full":"Calle de San Juan, 41 San Cristobal De La Laguna Santa Cruz De Tenerife 38203",
    "addr:housenumber":"41",
    "addr:postcode":"38203",
    "addr:street":"Calle De San Juan",
    "iso:country":"ES",
    "sg:address":"Calle de San Juan, 41",
    "sg:city":"San Cristobal De La Laguna",
    "sg:orig_category":"Instalaci\u00d3n De Sanitarios",
    "sg:phone":"+34 922 25 72 10",
    "sg:postcode":"38203",
    "sg:province":"Santa Cruz De Tenerife",
    "sg:website":"www.ozonoterapiatenerife.com",
    "wof:name":"Romero Valdes Alesie De Jesus",
    "wof:placetype":"venue"
},
  "geometry": {"coordinates":[-16.3227043152,28.4883937836],"type":"Point"}
}