{
  "type": "Feature",
  "properties": {
    "addr:full":"Carrer de Major, 2 Bot Tarragona 43785",
    "addr:housenumber":"2",
    "addr:postcode":"43785",
    "addr:street":"Carrer De Major",
    "iso:country":"ES",
    "sg:address":"Carrer de Major, 2",
    "sg:city":"Bot",
    "sg:orig_category":"Asesor\u00cda Fiscal Y Jur\u00cddica",
    "sg:phone":"+34 977 42 82 61",
    "sg:postcode":"43785",
    "sg:province":"Tarragona",
    "wof:name":"Bos-men Assesors S.l.",
    "wof:placetype":"venue"
},
  "geometry": {"coordinates":[0.3852019906,41.0090408325],"type":"Point"}
}