{
  "type": "Feature",
  "properties": {
    "iso:country":"ES",
    "sg:address":"Afueras, 52",
    "sg:city":"Portinatx",
    "sg:orig_category":"Promotores Constructores",
    "sg:phone":"+34 971 32 07 64",
    "sg:postcode":"07810",
    "sg:province":"Islas Baleares",
    "wof:name":"Construcciones Cardona Mari S.l.",
    "wof:placetype":"venue"
},
  "geometry": {"coordinates":[1.5125099421,39.0776100159],"type":"Point"}
}