{
  "type": "Feature",
  "properties": {
    "iso:country":"ES",
    "sg:address":"Calle de Mendaro, 3",
    "sg:city":"Chiclana De La Frontera",
    "sg:orig_category":"Asesor\u00cda Sobre Comunicaci\u00d3n De Empresas",
    "sg:phone":"+34 956 53 76 59",
    "sg:postcode":"11130",
    "sg:province":"C\u00e1diz",
    "wof:name":"Tocino Caucin Jesus Maria",
    "wof:placetype":"venue"
},
  "geometry": {"coordinates":[-6.1521711349,36.4190216064],"type":"Point"}
}