{
  "type": "Feature",
  "properties": {
    "iso:country":"ES",
    "sg:address":"Calle de Tutor, 43",
    "sg:city":"Madrid",
    "sg:orig_category":"Artes Gr\u00c1ficas, Artes Pl\u00c1sticas (curso)",
    "sg:phone":"+34 915 47 32 86",
    "sg:postcode":"28008",
    "sg:province":"Madrid",
    "wof:name":"Marin Martinez Yolanda",
    "wof:placetype":"venue"
},
  "geometry": {"coordinates":[-3.7173728943,40.429977417],"type":"Point"}
}