{
  "type": "Feature",
  "properties": {
    "iso:country":"ES",
    "sg:address":"Calle de Pinos, 1",
    "sg:city":"Salamanca",
    "sg:orig_category":"Mec\u00c1nico Del Autom\u00d3vil",
    "sg:phone":"+34 923 22 35 27",
    "sg:postcode":"37005",
    "sg:province":"Salamanca",
    "wof:name":"Garaje Silvia S.l.",
    "wof:placetype":"venue"
},
  "geometry": {"coordinates":[-5.6546912193,40.9766654968],"type":"Point"}
}