{
  "type": "Feature",
  "properties": {
    "addr:full":"Ctra. Manacor, 246 Son Ferriol Islas Baleares 07198",
    "addr:housenumber":"246",
    "addr:postcode":"07198",
    "addr:street":"Ctra. Manacor",
    "iso:country":"ES",
    "sg:address":"Ctra. Manacor, 246",
    "sg:city":"Son Ferriol",
    "sg:orig_category":"Contenedores (mercanc\u00cdas)",
    "sg:phone":"+34 971 42 87 13",
    "sg:postcode":"07198",
    "sg:province":"Islas Baleares",
    "wof:name":"Aroca Garcia Juan",
    "wof:placetype":"venue"
},
  "geometry": {"coordinates":[2.7328736782,39.5712089539],"type":"Point"}
}