{
  "type": "Feature",
  "properties": {
    "iso:country":"ES",
    "sg:address":"Calle de Colombia, 19",
    "sg:city":"Toledo",
    "sg:orig_category":"Arquitectos",
    "sg:phone":"+34 925 21 37 61",
    "sg:postcode":"45004",
    "sg:province":"Toledo",
    "wof:name":"Heine Zubiaurre Carlos Emilio",
    "wof:placetype":"venue"
},
  "geometry": {"coordinates":[-4.0316953659,39.8680610657],"type":"Point"}
}