{
  "type": "Feature",
  "properties": {
    "iso:country":"ES",
    "sg:address":"Calle de Reyes Catolicos, 59",
    "sg:city":"Castalla",
    "sg:orig_category":"Ropa Para Ni\u00d1os (al Por Menor)",
    "sg:phone":"+34 966 56 00 10",
    "sg:postcode":"03420",
    "sg:province":"Alicante",
    "wof:name":"Confecciones Bergis S.l.",
    "wof:placetype":"venue"
},
  "geometry": {"coordinates":[-0.6692069769,38.5919113159],"type":"Point"}
}