{
  "type": "Feature",
  "properties": {
    "iso:country":"ES",
    "sg:address":"Avda Viella, 53",
    "sg:city":"Lugones",
    "sg:orig_category":"Alquiler De V\u00cddeo",
    "sg:phone":"+34 985 26 48 62",
    "sg:postcode":"33420",
    "sg:province":"Asturias",
    "wof:name":"Videoclub Flas Back C.b.",
    "wof:placetype":"venue"
},
  "geometry": {"coordinates":[-5.8106489182,43.4009132385],"type":"Point"}
}