{
  "type": "Feature",
  "properties": {
    "addr:full":"Avda Villalba, 29 Muimenta Lugo 27377",
    "addr:housenumber":"29",
    "addr:postcode":"27377",
    "addr:street":"Avda Villalba",
    "iso:country":"ES",
    "sg:address":"Avda Villalba, 29",
    "sg:city":"Muimenta",
    "sg:orig_category":"Caf\u00c9s, Bares, Cervecer\u00cdas",
    "sg:phone":"+34 982 52 81 08",
    "sg:postcode":"27377",
    "sg:province":"Lugo",
    "wof:name":"Fernandez Darriba Mercedes",
    "wof:placetype":"venue"
},
  "geometry": {"coordinates":[-7.4306840897,43.2528953552],"type":"Point"}
}