{
  "type": "Feature",
  "properties": {
    "iso:country":"ES",
    "sg:address":"Plaz Mayor, 16",
    "sg:city":"Bujalance",
    "sg:orig_category":"Molduras, Junquillos, Listones Y Molduras Perforadas",
    "sg:phone":"+34 957 17 05 62",
    "sg:postcode":"14650",
    "sg:province":"C\u00f3rdoba",
    "wof:name":"Ruiz Leon Antonio Enrique",
    "wof:placetype":"venue"
},
  "geometry": {"coordinates":[-4.380753994,37.895160675],"type":"Point"}
}