{
  "type": "Feature",
  "properties": {
    "iso:country":"ES",
    "sg:address":"Calle de Ayala, 2",
    "sg:city":"Don Benito",
    "sg:orig_category":"Ropa Para Se\u00d1oras (al Por Menor)",
    "sg:phone":"+34 924 80 25 82",
    "sg:postcode":"06400",
    "sg:province":"Badajoz",
    "wof:name":"Cesbea 2000 Networks S.l.",
    "wof:placetype":"venue"
},
  "geometry": {"coordinates":[-5.8615980148,38.9615898132],"type":"Point"}
}