{
  "type": "Feature",
  "properties": {
    "addr:full":"Calle de Santa Engracia, 77 Madrid Madrid 28010",
    "addr:housenumber":"77",
    "addr:postcode":"madrid;28010",
    "addr:street":"Calle De Santa Engracia",
    "iso:country":"ES",
    "sg:address":"Calle de Santa Engracia, 77",
    "sg:city":"Madrid",
    "sg:orig_category":"Papeler\u00cdas, Librer\u00cdas",
    "sg:phone":"+34 914 46 35 41",
    "sg:postcode":"28010",
    "sg:province":"Madrid",
    "wof:name":"Rosas Sanchez Andreina",
    "wof:placetype":"venue"
},
  "geometry": {"coordinates":[-3.6991269588,40.4354171753],"type":"Point"}
}