{
  "type": "Feature",
  "properties": {
    "iso:country":"ES",
    "sg:address":"Plaz Espa\u00d1a (de), 9",
    "sg:city":"Miraflores De La Sierra",
    "sg:orig_category":"Oficinas Y Gesti\u00d3n De Inmuebles",
    "sg:phone":"+34 918 44 44 44",
    "sg:postcode":"28792",
    "sg:province":"Madrid",
    "wof:name":"Miraflores Gestion De Inmuebles S.l.",
    "wof:placetype":"venue"
},
  "geometry": {"coordinates":[-3.7650659084,40.8086738586],"type":"Point"}
}