{
  "type": "Feature",
  "properties": {
    "addr:full":"Carrer de Doctor Pi I Molist, 3 Barcelona Barcelona 08031",
    "addr:housenumber":"3",
    "addr:postcode":"08031",
    "addr:street":"Carrer De Doctor Pi I Molist",
    "iso:country":"ES",
    "sg:address":"Carrer de Doctor Pi I Molist, 3",
    "sg:city":"Barcelona",
    "sg:orig_category":"Bisuter\u00cda, Joyer\u00cda, Relojer\u00cda (al Por Menor)",
    "sg:phone":"+34 934 08 31 77",
    "sg:postcode":"08031",
    "sg:province":"Barcelona",
    "wof:name":"Yebenes Joyeres S.l.",
    "wof:placetype":"venue"
},
  "geometry": {"coordinates":[2.1745331287,41.4305343628],"type":"Point"}
}