{
  "type": "Feature",
  "properties": {
    "iso:country":"ES",
    "sg:address":"Carr Bastiments, 12",
    "sg:city":"Girona",
    "sg:orig_category":"Confecci\u00d3n De Ropa Interior",
    "sg:phone":"+34 972 23 62 39",
    "sg:postcode":"17006",
    "sg:province":"Girona",
    "wof:name":"Lenceria Del Fenix",
    "wof:placetype":"venue"
},
  "geometry": {"coordinates":[2.8074634075,41.9741477966],"type":"Point"}
}