{
  "type": "Feature",
  "properties": {
    "iso:country":"ES",
    "sg:address":"Pl Oli (de L'), 10",
    "sg:city":"Valls",
    "sg:orig_category":"Carnicer\u00cdas, Carnicer\u00cdas",
    "sg:phone":"+34 977 60 10 93",
    "sg:postcode":"43800",
    "sg:province":"Tarragona",
    "wof:name":"Montala Lopez Emilio",
    "wof:placetype":"venue"
},
  "geometry": {"coordinates":[1.2490160465,41.283870697],"type":"Point"}
}