{
  "type": "Feature",
  "properties": {
    "addr:full":"C/ Santiago Ramon Y Cajal, 22 Salt Girona 17190",
    "addr:housenumber":"22",
    "addr:postcode":"17190",
    "addr:street":"C / Santiago Ramon Y Cajal",
    "iso:country":"ES",
    "sg:address":"C/ Santiago Ramon Y Cajal, 22",
    "sg:city":"Salt",
    "sg:orig_category":"Asesor\u00cda Fiscal Y Jur\u00cddica",
    "sg:phone":"+34 972 24 28 71",
    "sg:postcode":"17190",
    "sg:province":"Girona",
    "wof:name":"Assessorament I Gestio Salt S.l.",
    "wof:placetype":"venue"
},
  "geometry": {"coordinates":[2.7942237854,41.9717636108],"type":"Point"}
}