{
  "type": "Feature",
  "properties": {
    "addr:full":"Rua Nueva De Arriba, 43 Pontevedra Pontevedra 36002",
    "addr:housenumber":"43",
    "addr:postcode":"36002",
    "addr:street":"Rua Nueva De Arriba",
    "iso:country":"ES",
    "sg:address":"Rua Nueva De Arriba, 43",
    "sg:city":"Pontevedra",
    "sg:orig_category":"Bebidas",
    "sg:phone":"+34 986 86 39 01",
    "sg:postcode":"36002",
    "sg:province":"Pontevedra",
    "wof:name":"Gonzalez Martinez Luis Antonio",
    "wof:placetype":"venue"
},
  "geometry": {"coordinates":[-8.6517887115,42.4318199158],"type":"Point"}
}