{
  "type": "Feature",
  "properties": {
    "addr:full":"Avda Castilla La Mancha, 6 Toboso Toledo 45820",
    "addr:housenumber":"6",
    "addr:postcode":"45820",
    "addr:street":"Avda Castilla La Mancha",
    "iso:country":"ES",
    "sg:address":"Avda Castilla La Mancha, 6",
    "sg:city":"Toboso",
    "sg:orig_category":"Productores Recolectores, Venta Directa De Vinos",
    "sg:phone":"+34 925 19 70 43",
    "sg:postcode":"45820",
    "sg:province":"Toledo",
    "wof:name":"Cooperativa Agricola La Humildad",
    "wof:placetype":"venue"
},
  "geometry": {"coordinates":[-2.9910130501,39.5106315613],"type":"Point"}
}