{
  "type": "Feature",
  "properties": {
    "addr:full":"Calle de Voluntarios Catalanes, 21 Madrid Madrid 28039",
    "addr:housenumber":"21",
    "addr:postcode":"madrid;28039",
    "addr:street":"Calle De Voluntarios Catalanes",
    "iso:country":"ES",
    "sg:address":"Calle de Voluntarios Catalanes, 21",
    "sg:city":"Madrid",
    "sg:orig_category":"Fabricaci\u00d3n De Sobres, Bolsas Y Fundas",
    "sg:phone":"+34 915 79 34 46",
    "sg:postcode":"28039",
    "sg:province":"Madrid",
    "wof:name":"Perez Enguidanos Herminio",
    "wof:placetype":"venue"
},
  "geometry": {"coordinates":[-3.7002160549,40.465007782],"type":"Point"}
}