{
  "type": "Feature",
  "properties": {
    "addr:full":"Calle de Salvador Manrique De Lara, 3 Palmas De Gran Canaria Las Palmas 35010",
    "addr:postcode":"35010",
    "addr:street":"Calle De Salvador Manrique De Lara 3",
    "iso:country":"ES",
    "sg:address":"Calle de Salvador Manrique De Lara, 3",
    "sg:city":"Palmas De Gran Canaria",
    "sg:orig_category":"Agencias Y Asesores De Publicidad",
    "sg:phone":"+34 928 27 55 32",
    "sg:postcode":"35010",
    "sg:province":"Las Palmas",
    "sg:website":"www.tempoestudio.com",
    "wof:name":"Tempo Dise\u00f1o Y Nuevas Tecnologias S.l.",
    "wof:placetype":"venue"
},
  "geometry": {"coordinates":[-15.4353227615,28.1308269501],"type":"Point"}
}