{
  "type": "Feature",
  "properties": {
    "iso:country":"ES",
    "sg:address":"Padre Jesus Nazareno, 14",
    "sg:city":"Huelva",
    "sg:orig_category":"M\u00c9dicos: An\u00c1lisis Cl\u00cdnicos",
    "sg:phone":"+34 959 24 77 08",
    "sg:postcode":"21001",
    "sg:province":"Huelva",
    "wof:name":"Laboratorios Vazquez Pizarro S.l.",
    "wof:placetype":"venue"
},
  "geometry": {"coordinates":[-6.9547119141,37.2571372986],"type":"Point"}
}