{
  "type": "Feature",
  "properties": {
    "iso:country":"ES",
    "sg:address":"As Fontes, 6",
    "sg:city":"Bai\u00f1a",
    "sg:orig_category":"Audiovisuales (producci\u00d3n, Edici\u00d3n, Realizaci\u00d3n)",
    "sg:phone":"+34 986 35 55 98",
    "sg:postcode":"36308",
    "sg:province":"Pontevedra",
    "wof:name":"Ringo",
    "wof:placetype":"venue"
},
  "geometry": {"coordinates":[-8.8506288528,42.1063613892],"type":"Point"}
}