{
  "type": "Feature",
  "properties": {
    "iso:country":"ES",
    "sg:address":"Calle de Fuente, 49",
    "sg:city":"Quintanar Sierra",
    "sg:orig_category":"Supermercados Y Hipermercados",
    "sg:phone":"+34 947 39 54 75",
    "sg:postcode":"09670",
    "sg:province":"Burgos",
    "wof:name":"Marayus S.l.",
    "wof:placetype":"venue"
},
  "geometry": {"coordinates":[-3.0323390961,41.9873580933],"type":"Point"}
}