{
  "type": "Feature",
  "properties": {
    "iso:country":"ES",
    "sg:address":"Calle de Francisco Silvela, 92",
    "sg:city":"Madrid",
    "sg:orig_category":"Alimentaci\u00d3n General (al Por Menor)",
    "sg:phone":"+34 915 61 26 88",
    "sg:postcode":"28002",
    "sg:province":"Madrid",
    "wof:name":"Xu  Mengxun",
    "wof:placetype":"venue"
},
  "geometry": {"coordinates":[-3.678071022,40.4383392334],"type":"Point"}
}