{
  "type": "Feature",
  "properties": {
    "iso:country":"ES",
    "sg:address":"Luga Santo Medero, 49",
    "sg:city":"Santo Medero",
    "sg:orig_category":"Molduras, Junquillos, Listones Y Molduras Perforadas",
    "sg:phone":"+34 985 24 52 12",
    "sg:postcode":"33193",
    "sg:province":"Asturias",
    "wof:name":"Rivaya Iglesias Jose Alberto",
    "wof:placetype":"venue"
},
  "geometry": {"coordinates":[-5.894742012,43.3435211182],"type":"Point"}
}