{
  "type": "Feature",
  "properties": {
    "addr:full":"Calle de General Vives, 60 Ponferrada Le\u00f3n 24400",
    "addr:housenumber":"60",
    "addr:postcode":"24400",
    "addr:street":"Calle De General Vives",
    "iso:country":"ES",
    "sg:address":"Calle de General Vives, 60",
    "sg:city":"Ponferrada",
    "sg:orig_category":"Agencias Y Agentes Comerciales, Representantes",
    "sg:phone":"+34 987 41 29 37",
    "sg:postcode":"24400",
    "sg:province":"Le\u00f3n",
    "wof:name":"Vazquez Fernandez Emilio",
    "wof:placetype":"venue"
},
  "geometry": {"coordinates":[-6.5838499069,42.5493431091],"type":"Point"}
}