{
  "type": "Feature",
  "properties": {
    "addr:full":"Cmno Borja, 17 Alacant Alicante 03006",
    "addr:housenumber":"17",
    "addr:postcode":"03006",
    "addr:street":"Cmno Borja",
    "iso:country":"ES",
    "sg:address":"Cmno Borja, 17",
    "sg:city":"Alacant",
    "sg:orig_category":"Negocio De Materiales De Construcci\u00d3n",
    "sg:phone":"+34 965 10 65 79",
    "sg:postcode":"03006",
    "sg:province":"Alicante",
    "sg:website":"www.laconstructoraillicitana.com",
    "wof:name":"Constructora Ilicitana S.l",
    "wof:placetype":"venue"
},
  "geometry": {"coordinates":[-0.4804739952,38.3440856934],"type":"Point"}
}