{
  "type": "Feature",
  "properties": {
    "addr:full":"Calle de Joaquin Gaztambide, 7 Malaga M\u00e1laga 29011",
    "addr:housenumber":"7",
    "addr:postcode":"29011",
    "addr:street":"Calle De Joaquin Gaztambide;Ma\u0301Laga",
    "iso:country":"ES",
    "sg:address":"Calle de Joaquin Gaztambide, 7",
    "sg:city":"Malaga",
    "sg:orig_category":"Promotores Constructores",
    "sg:phone":"+34 952 61 56 14",
    "sg:postcode":"29011",
    "sg:province":"M\u00e1laga",
    "wof:name":"Comunidad De Propietarios Jardin Botanico 3 Y 4",
    "wof:placetype":"venue"
},
  "geometry": {"coordinates":[-4.4217538834,36.7456817627],"type":"Point"}
}