{
  "type": "Feature",
  "properties": {
    "addr:full":"Avda Beire, 15 Olite Navarra 31390",
    "addr:housenumber":"15",
    "addr:postcode":"31390",
    "addr:street":"Avda Beire",
    "iso:country":"ES",
    "sg:address":"Avda Beire, 15",
    "sg:city":"Olite",
    "sg:orig_category":"Aguas (distribuci\u00d3n, Servicios)",
    "sg:phone":"+34 948 71 24 67",
    "sg:postcode":"31390",
    "sg:province":"Navarra",
    "wof:name":"Infilco Espa\u00d1ola S.a.",
    "wof:placetype":"venue"
},
  "geometry": {"coordinates":[-1.6482173204,42.4773139954],"type":"Point"}
}