{
  "type": "Feature",
  "properties": {
    "iso:country":"ES",
    "sg:address":"Ctra Pliego (de), 6",
    "sg:city":"Mula",
    "sg:orig_category":"Mec\u00c1nico Del Autom\u00d3vil",
    "sg:phone":"+34 968 66 08 90",
    "sg:postcode":"30170",
    "sg:province":"Murcia",
    "wof:name":"Martinez Diaz Antonio",
    "wof:placetype":"venue"
},
  "geometry": {"coordinates":[-1.4940969944,38.0392417908],"type":"Point"}
}