{
  "type": "Feature",
  "properties": {
    "addr:full":"Calle de Eucaliptus, 8 Dos Hermanas Sevilla 41700",
    "addr:postcode":"41700",
    "addr:street":"Calle De Eucaliptus 8 Dos;Sevilla",
    "iso:country":"ES",
    "sg:address":"Calle de Eucaliptus, 8",
    "sg:city":"Dos Hermanas",
    "sg:orig_category":"Panader\u00cdas, Panader\u00cdas",
    "sg:phone":"+34 955 67 42 37",
    "sg:postcode":"41700",
    "sg:province":"Sevilla",
    "wof:name":"Panificadora Oliva S.l.",
    "wof:placetype":"venue"
},
  "geometry": {"coordinates":[-5.9094700813,37.275478363],"type":"Point"}
}