{
  "type": "Feature",
  "properties": {
    "addr:full":"Calle de Juan Perez Zu\u00d1iga, 27 Madrid Madrid 28027",
    "addr:housenumber":"27",
    "addr:postcode":"madrid;28027",
    "addr:street":"Calle De Juan;Zun\u0303Iga",
    "iso:country":"ES",
    "sg:address":"Calle de Juan Perez Zu\u00d1iga, 27",
    "sg:city":"Madrid",
    "sg:orig_category":"Molduras, Junquillos, Listones Y Molduras Perforadas",
    "sg:phone":"+34 914 07 10 85",
    "sg:postcode":"28027",
    "sg:province":"Madrid",
    "wof:name":"Hermoso Valles S.l.",
    "wof:placetype":"venue"
},
  "geometry": {"coordinates":[-3.6486279964,40.4425506592],"type":"Point"}
}