{
  "type": "Feature",
  "properties": {
    "addr:full":"Calle de Francisco Grandmontagne, 19 Burgos Burgos 09007",
    "addr:housenumber":"19",
    "addr:postcode":"09007",
    "addr:street":"Calle De Francisco Grandmontagne",
    "iso:country":"ES",
    "sg:address":"Calle de Francisco Grandmontagne, 19",
    "sg:city":"Burgos",
    "sg:orig_category":"Peluquer\u00cdas, Peluquer\u00cda Mixta",
    "sg:phone":"+34 947 23 56 02",
    "sg:postcode":"09007",
    "sg:province":"Burgos",
    "wof:name":"Peluqueria Prissma",
    "wof:placetype":"venue"
},
  "geometry": {"coordinates":[-3.6699130535,42.3503341675],"type":"Point"}
}