{
  "type": "Feature",
  "properties": {
    "addr:full":"Calle de Obispo Nieto, 21 Zamora Zamora 49005",
    "addr:housenumber":"21",
    "addr:postcode":"49005",
    "addr:street":"Calle De Obispo Nieto",
    "iso:country":"ES",
    "sg:address":"Calle de Obispo Nieto, 21",
    "sg:city":"Zamora",
    "sg:orig_category":"Mec\u00c1nico Del Autom\u00d3vil",
    "sg:phone":"+34 980 52 77 38",
    "sg:postcode":"49005",
    "sg:province":"Zamora",
    "wof:name":"Rodriguez Sansegundo Gregorio",
    "wof:placetype":"venue"
},
  "geometry": {"coordinates":[-5.7515969276,41.5051689148],"type":"Point"}
}