{
  "type": "Feature",
  "properties": {
    "iso:country":"ES",
    "sg:address":"Ctra Montcada, 591",
    "sg:city":"Terrassa",
    "sg:orig_category":"Alquiler De Veh\u00cdculos: Turismos Y Utilitarios",
    "sg:phone":"+34 937 31 54 12",
    "sg:postcode":"08227",
    "sg:province":"Barcelona",
    "wof:name":"Sepauto Movil S. A.",
    "wof:placetype":"venue"
},
  "geometry": {"coordinates":[2.0378410816,41.557434082],"type":"Point"}
}