{
  "type": "Feature",
  "properties": {
    "addr:full":"Calle de San Francisco, 17 Tarifa C\u00e1diz 11380",
    "addr:housenumber":"17",
    "addr:postcode":"11380",
    "addr:street":"Calle De San Francisco;Ca\u0301Diz",
    "iso:country":"ES",
    "sg:address":"Calle de San Francisco, 17",
    "sg:city":"Tarifa",
    "sg:orig_category":"Florister\u00cdas",
    "sg:phone":"+34 956 68 43 30",
    "sg:postcode":"11380",
    "sg:province":"C\u00e1diz",
    "wof:name":"Flores Donda Mariluz",
    "wof:placetype":"venue"
},
  "geometry": {"coordinates":[-5.603741169,36.0125846863],"type":"Point"}
}