{
  "type": "Feature",
  "properties": {
    "iso:country":"ES",
    "sg:address":"Calle de Hilanderas, 9",
    "sg:city":"Irun",
    "sg:orig_category":"Limpieza Con Chorro De Arena Y Con Granalla, Pulido",
    "sg:phone":"+34 943 63 28 03",
    "sg:postcode":"20303",
    "sg:province":"Guip\u00f9zcoa",
    "wof:name":"Pulimentos Metalicos Txingudi S.l.",
    "wof:placetype":"venue"
},
  "geometry": {"coordinates":[-1.8058079481,43.3341789246],"type":"Point"}
}