{
  "type": "Feature",
  "properties": {
    "addr:full":"Bo. Rans, 109 Mos Pontevedra 36416",
    "addr:housenumber":"109",
    "addr:postcode":"36416",
    "addr:street":"Rans",
    "iso:country":"ES",
    "sg:address":"Bo. Rans, 109",
    "sg:city":"Mos",
    "sg:orig_category":"Carnicer\u00cdas, Carnicer\u00cdas",
    "sg:phone":"+34 986 33 61 41",
    "sg:postcode":"36416",
    "sg:province":"Pontevedra",
    "wof:name":"Lorenzo Castro Eugenio",
    "wof:placetype":"venue"
},
  "geometry": {"coordinates":[-8.6403799057,42.1906967163],"type":"Point"}
}