{
  "type": "Feature",
  "properties": {
    "iso:country":"ES",
    "sg:address":"Carrer de Ciutat De Balaguer, 52",
    "sg:city":"Barcelona",
    "sg:orig_category":"Peluquer\u00cdas, Peluquer\u00cda Mixta",
    "sg:phone":"+34 934 17 91 73",
    "sg:postcode":"08022",
    "sg:province":"Barcelona",
    "wof:name":"Carrillo  Nansi Bibiana",
    "wof:placetype":"venue"
},
  "geometry": {"coordinates":[2.1347770691,41.4040908813],"type":"Point"}
}