{
  "type": "Feature",
  "properties": {
    "addr:full":"Calle de Doctor Moliner, 2 Valencia Valencia 46010",
    "addr:housenumber":"2",
    "addr:postcode":"46010",
    "addr:street":"Calle De Doctor Moliner",
    "iso:country":"ES",
    "sg:address":"Calle de Doctor Moliner, 2",
    "sg:city":"Valencia",
    "sg:orig_category":"Asesor\u00cda Sobre Comunicaci\u00d3n De Empresas",
    "sg:phone":"+34 963 62 09 11",
    "sg:postcode":"46010",
    "sg:province":"Valencia",
    "wof:name":"Pardo Y Pinazo Asesores S. L.",
    "wof:placetype":"venue"
},
  "geometry": {"coordinates":[-0.3630822897,39.4757080078],"type":"Point"}
}