{
  "type": "Feature",
  "properties": {
    "addr:full":"Calle de Pianista Amparo Iturbi, 61 Valencia Valencia 46006",
    "addr:housenumber":"61",
    "addr:postcode":"46006",
    "addr:street":"Calle De Pianista Amparo Iturbi",
    "iso:country":"ES",
    "sg:address":"Calle de Pianista Amparo Iturbi, 61",
    "sg:city":"Valencia",
    "sg:orig_category":"Mec\u00c1nico Del Autom\u00d3vil",
    "sg:phone":"+34 963 33 41 70",
    "sg:postcode":"46006",
    "sg:province":"Valencia",
    "wof:name":"Octavio Talleres C.b.",
    "wof:placetype":"venue"
},
  "geometry": {"coordinates":[-0.3769220114,39.4544754028],"type":"Point"}
}