{
  "type": "Feature",
  "properties": {
    "iso:country":"ES",
    "sg:address":"Ctra. Cadiz, Km. 0216,5",
    "sg:city":"Benalmadena",
    "sg:orig_category":"Postigos, Persianas Y Celos\u00cdas",
    "sg:phone":"+34 952 56 84 86",
    "sg:postcode":"29639",
    "sg:province":"M\u00e1laga",
    "wof:name":"Carbonell Blazquez Nicolas",
    "wof:placetype":"venue"
},
  "geometry": {"coordinates":[-4.5734581947,36.5951728821],"type":"Point"}
}