{
  "type": "Feature",
  "properties": {
    "iso:country":"ES",
    "sg:address":"Carrer de Major, 78",
    "sg:city":"Castellbisbal",
    "sg:classifiers":[
        {
            "category":"Home & Garden",
            "subcategory":"Household Appliances",
            "type":"Retail Goods"
        }
    ],
    "sg:phone":"+34 937 72 09 00",
    "sg:postcode":"08755",
    "sg:province":"Barcelona",
    "sg:tags":[
        "bodega",
        "de",
        "vino",
        "acondicionamiento"
    ],
    "sg:website":"www.joansarda.com",
    "wof:name":"Joan Sarda S. A.",
    "wof:placetype":"venue"
},
  "geometry": {"coordinates":[1.9802290201,41.4772834778],"type":"Point"}
}