{
  "type": "Feature",
  "properties": {
    "iso:country":"ES",
    "sg:address":"Carrer de Arago, 102",
    "sg:city":"Barcelona",
    "sg:orig_category":"Comercio De Piezas De Recambio Y De Accesorios De Veh\u00cdculos, Veh\u00cdculos Industriales",
    "sg:phone":"+34 934 54 48 66",
    "sg:postcode":"08015",
    "sg:province":"Barcelona",
    "wof:name":"Torrents Fargues Gabriel",
    "wof:placetype":"venue"
},
  "geometry": {"coordinates":[2.1537899971,41.3836364746],"type":"Point"}
}