{
  "type": "Feature",
  "properties": {
    "addr:full":"Carrer de Rector Salvador Ferrandiz, 24 Pedreguer Alicante 03750",
    "addr:housenumber":"24",
    "addr:postcode":"03750",
    "addr:street":"Carrer De Rector Salvador Ferrandiz",
    "iso:country":"ES",
    "sg:address":"Carrer de Rector Salvador Ferrandiz, 24",
    "sg:city":"Pedreguer",
    "sg:orig_category":"Comercio, Reparaci\u00d3n De Motocicletas, Bicicletas Y Piezas Sueltas",
    "sg:phone":"+34 965 76 08 70",
    "sg:postcode":"03750",
    "sg:province":"Alicante",
    "wof:name":"Miralles Ribes Jaime",
    "wof:placetype":"venue"
},
  "geometry": {"coordinates":[0.0319430009,38.7956733704],"type":"Point"}
}