{
  "type": "Feature",
  "properties": {
    "iso:country":"ES",
    "sg:address":"Calle de German Perez Carrasco, 2",
    "sg:city":"Madrid",
    "sg:orig_category":"Bisuter\u00cda, Joyer\u00cda, Relojer\u00cda (al Por Menor)",
    "sg:phone":"+34 913 67 97 40",
    "sg:postcode":"28027",
    "sg:province":"Madrid",
    "wof:name":"Perez Santamaria Jaime",
    "wof:placetype":"venue"
},
  "geometry": {"coordinates":[-3.6474540234,40.4342498779],"type":"Point"}
}