{
  "type": "Feature",
  "properties": {
    "iso:country":"ES",
    "sg:address":"Calle de Bosque El, 4",
    "sg:city":"Ronda",
    "sg:orig_category":"Ingeniero",
    "sg:phone":"+34 952 87 42 41",
    "sg:postcode":"29400",
    "sg:province":"M\u00e1laga",
    "wof:name":"Gonzalez Garcia Salvador",
    "wof:placetype":"venue"
},
  "geometry": {"coordinates":[-5.1527881622,36.752368927],"type":"Point"}
}