{
  "type": "Feature",
  "properties": {
    "addr:full":"Calle de Baltasar Pardal, 4 Coru\u00d1a A Coru\u00f1a 15001",
    "addr:housenumber":"4",
    "addr:postcode":"15001",
    "addr:street":"Calle De Baltasar Pardal;Corun\u0303A",
    "iso:country":"ES",
    "sg:address":"Calle de Baltasar Pardal, 4",
    "sg:city":"Coru\u00d1a",
    "sg:orig_category":"Peluqueros: De Se\u00d1oras",
    "sg:phone":"+34 981 20 32 96",
    "sg:postcode":"15001",
    "sg:province":"A Coru\u00f1a",
    "wof:name":"Silvosa Garcia Maria Sol",
    "wof:placetype":"venue"
},
  "geometry": {"coordinates":[-8.3195390701,43.1524581909],"type":"Point"}
}