{
  "type": "Feature",
  "properties": {
    "iso:country":"ES",
    "sg:address":"Avda Colon, 53",
    "sg:city":"Logro\u00f1o",
    "sg:orig_category":"Asesor\u00cdas Y Estudios Financieros",
    "sg:phone":"+34 941 24 90 88",
    "sg:postcode":"26003",
    "sg:province":"La Rioja",
    "wof:name":"Bazan I\u00f1iguez Rocio",
    "wof:placetype":"venue"
},
  "geometry": {"coordinates":[-2.4404079914,42.461265564],"type":"Point"}
}