{
  "type": "Feature",
  "properties": {
    "addr:full":"Rua Nosa Sra. Da Sainza, 20 Ourense Ourense 32005",
    "addr:housenumber":"20",
    "addr:postcode":"32005",
    "addr:street":"Rua Nosa Sra. Da Sainza",
    "iso:country":"ES",
    "sg:address":"Rua Nosa Sra. Da Sainza, 20",
    "sg:city":"Ourense",
    "sg:orig_category":"Comercio De Piezas De Recambio Y De Accesorios De Veh\u00cdculos, Veh\u00cdculos Industriales",
    "sg:phone":"+34 988 23 66 48",
    "sg:postcode":"32005",
    "sg:province":"Ourense",
    "sg:website":"www.guardianexpress.es",
    "wof:name":"Guardian Glass Express S. L.",
    "wof:placetype":"venue"
},
  "geometry": {"coordinates":[-7.8621068001,42.3285484314],"type":"Point"}
}