{
  "type": "Feature",
  "properties": {
    "addr:full":"Calle de Romeral, 6 Rozas De Madrid Madrid 28230",
    "addr:housenumber":"6",
    "addr:postcode":"28230",
    "addr:street":"Calle De Romeral",
    "iso:country":"ES",
    "sg:address":"Calle de Romeral, 6",
    "sg:city":"Rozas De Madrid",
    "sg:orig_category":"Cine: Pel\u00cdculas Educativas, Industriales Y Publicitarias (producci\u00d3n)",
    "sg:phone":"+34 916 37 80 81",
    "sg:postcode":"28230",
    "sg:province":"Madrid",
    "wof:name":"Celdran Y Gonzalez Comunicaciones S.l.",
    "wof:placetype":"venue"
},
  "geometry": {"coordinates":[-3.8732590675,40.4927558899],"type":"Point"}
}