{
  "type": "Feature",
  "properties": {
    "iso:country":"ES",
    "sg:address":"Calle de Padre Ferris, 34",
    "sg:city":"Valencia",
    "sg:orig_category":"Ingeniero",
    "sg:phone":"+34 963 40 49 66",
    "sg:postcode":"46009",
    "sg:province":"Valencia",
    "wof:name":"Talens Talens Jose",
    "wof:placetype":"venue"
},
  "geometry": {"coordinates":[-0.3863475025,39.4851379395],"type":"Point"}
}