{
  "type": "Feature",
  "properties": {
    "iso:country":"ES",
    "sg:address":"Calle de Vallterra, 2",
    "sg:city":"Benasal",
    "sg:orig_category":"T\u00c9cnicos Veterinarios",
    "sg:phone":"+34 964 44 40 33",
    "sg:postcode":"12160",
    "sg:province":"Castell\u00f3n",
    "wof:name":"Fabregat Ferrer Juan Tomas",
    "wof:placetype":"venue"
},
  "geometry": {"coordinates":[-0.1405189931,40.3801345825],"type":"Point"}
}