{
  "type": "Feature",
  "properties": {
    "addr:full":"Calle de Etxaide, 8 Donostia-san Sebastian Guip\u00f9zcoa 20005",
    "addr:housenumber":"8",
    "addr:postcode":"20005",
    "addr:street":"Calle De Etxaide",
    "iso:country":"ES",
    "sg:address":"Calle de Etxaide, 8",
    "sg:city":"Donostia-san Sebastian",
    "sg:orig_category":"Peluquer\u00cdas, Peluquer\u00cda Mixta",
    "sg:phone":"+34 943 42 07 40",
    "sg:postcode":"20005",
    "sg:province":"Guip\u00f9zcoa",
    "wof:name":"Esther Vivar Gonzalez",
    "wof:placetype":"venue"
},
  "geometry": {"coordinates":[-1.9797090292,43.3194770813],"type":"Point"}
}