{
  "type": "Feature",
  "properties": {
    "addr:full":"Calle de Bolivar Simon, 22 Bilbao Vizcaya 48013",
    "addr:housenumber":"22",
    "addr:postcode":"48013",
    "addr:street":"Calle De Bolivar Simon",
    "iso:country":"ES",
    "sg:address":"Calle de Bolivar Simon, 22",
    "sg:city":"Bilbao",
    "sg:orig_category":"Electricidad Veh\u00cdculo",
    "sg:phone":"+34 944 02 09 20",
    "sg:postcode":"48013",
    "sg:province":"Vizcaya",
    "wof:name":"Autos May Lasa, S.l",
    "wof:placetype":"venue"
},
  "geometry": {"coordinates":[-2.9453659058,43.2609443665],"type":"Point"}
}