{
  "type": "Feature",
  "properties": {
    "addr:full":"Ctra. Puerto Naos, 69 Los Llanos Aridane Santa Cruz De Tenerife 38760",
    "addr:housenumber":"69",
    "addr:postcode":"38760",
    "addr:street":"Ctra. Puerto Naos",
    "iso:country":"ES",
    "sg:address":"Ctra. Puerto Naos, 69",
    "sg:city":"Los Llanos Aridane",
    "sg:orig_category":"Quincaller\u00cda (al Por Menor)",
    "sg:phone":"+34 922 46 44 84",
    "sg:postcode":"38760",
    "sg:province":"Santa Cruz De Tenerife",
    "wof:name":"C.b. Comercial Isla Bonita",
    "wof:placetype":"venue"
},
  "geometry": {"coordinates":[-17.9085597992,28.6563796997],"type":"Point"}
}