{
  "type": "Feature",
  "properties": {
    "addr:full":"Barr Goitondo, 2 Berano Nagusi Vizcaya 48269",
    "addr:housenumber":"2",
    "addr:postcode":"48269",
    "addr:street":"Goitondo;Nagusi Vizcaya",
    "iso:country":"ES",
    "sg:address":"Barr Goitondo, 2",
    "sg:city":"Berano Nagusi",
    "sg:orig_category":"Escotaduras, Torneados",
    "sg:phone":"+34 943 17 34 70",
    "sg:postcode":"48269",
    "sg:province":"Vizcaya",
    "wof:name":"Cnc Lan S.a.",
    "wof:placetype":"venue"
},
  "geometry": {"coordinates":[-2.5300109386,43.1897888184],"type":"Point"}
}