{
  "type": "Feature",
  "properties": {
    "iso:country":"ES",
    "sg:address":"Calle de Ligustro, 18",
    "sg:city":"Sevilla",
    "sg:orig_category":"Aparatos, Material Y Suministros Para Laboratorios",
    "sg:phone":"+34 954 25 10 38",
    "sg:postcode":"41020",
    "sg:province":"Sevilla",
    "wof:name":"Comercial Sevillana De Laboratorios S.l.",
    "wof:placetype":"venue"
},
  "geometry": {"coordinates":[-5.9430689812,37.4079704285],"type":"Point"}
}