{
  "type": "Feature",
  "properties": {
    "addr:full":"Calle de Jose Carreras, S/n Dos Hermanas Sevilla 41700",
    "addr:housenumber":"s / n",
    "addr:postcode":"41700",
    "addr:street":"Calle De Jose Carreras",
    "iso:country":"ES",
    "sg:address":"Calle de Jose Carreras, S/n",
    "sg:city":"Dos Hermanas",
    "sg:orig_category":"Arreglo, Reparaci\u00d3n, Piezas Sueltas De Televisi\u00d3n, V\u00cddeo, Hi",
    "sg:phone":"+34 954 72 24 97",
    "sg:postcode":"41700",
    "sg:province":"Sevilla",
    "wof:name":"Tymedos S.l.",
    "wof:placetype":"venue"
},
  "geometry": {"coordinates":[-5.9167590141,37.2816696167],"type":"Point"}
}