{
  "type": "Feature",
  "properties": {
    "addr:full":"Calle de Cean Bermudez, 16 Gijon Asturias 33208",
    "addr:housenumber":"16",
    "addr:postcode":"33208",
    "addr:street":"Calle De Cean Bermudez",
    "iso:country":"ES",
    "sg:address":"Calle de Cean Bermudez, 16",
    "sg:city":"Gijon",
    "sg:orig_category":"Abogados",
    "sg:phone":"+34 985 38 31 94",
    "sg:postcode":"33208",
    "sg:province":"Asturias",
    "wof:name":"Gonzalez Gonzalez Juan Manuel",
    "wof:placetype":"venue"
},
  "geometry": {"coordinates":[-5.6681456566,43.5320625305],"type":"Point"}
}