{
  "type": "Feature",
  "properties": {
    "iso:country":"ES",
    "sg:address":"Calle de Marques De Molins, 22",
    "sg:city":"Alacant",
    "sg:orig_category":"Plomeros",
    "sg:phone":"+34 965 21 69 05",
    "sg:postcode":"03004",
    "sg:province":"Alicante",
    "wof:name":"Gras Tornero Miguel",
    "wof:placetype":"venue"
},
  "geometry": {"coordinates":[-0.4895769954,38.350440979],"type":"Point"}
}