{
  "type": "Feature",
  "properties": {
    "iso:country":"ES",
    "sg:address":"Calle de Panaderas, 52",
    "sg:city":"Coru\u00d1a",
    "sg:orig_category":"Perfumer\u00cda (al Por Menor)",
    "sg:phone":"+34 981 20 61 09",
    "sg:postcode":"15001",
    "sg:province":"La Coru\u00f1a",
    "wof:name":"Gonzalez Vilar Maria Roberina",
    "wof:placetype":"venue"
},
  "geometry": {"coordinates":[-8.3944396973,43.3710708618],"type":"Point"}
}