{
  "type": "Feature",
  "properties": {
    "addr:full":"Carrer de Font (de La), 11 Vila-seca Tarragona 43480",
    "addr:housenumber":"11",
    "addr:postcode":"43480",
    "addr:street":"Carrer De Font De La",
    "iso:country":"ES",
    "sg:address":"Carrer de Font (de La), 11",
    "sg:city":"Vila-seca",
    "sg:orig_category":"Bisuter\u00cda, Joyer\u00cda, Relojer\u00cda (al Por Menor)",
    "sg:phone":"+34 977 39 37 04",
    "sg:postcode":"43480",
    "sg:province":"Tarragona",
    "wof:name":"Morales Casado Natividad",
    "wof:placetype":"venue"
},
  "geometry": {"coordinates":[1.1439650059,41.1102027893],"type":"Point"}
}