{
  "type": "Feature",
  "properties": {
    "addr:full":"Calle de Eras (de Las), 12 Avila \u00c1vila 05002",
    "addr:housenumber":"12",
    "addr:postcode":"05002",
    "addr:street":"Calle De Eras De Las;A\u0301Vila",
    "iso:country":"ES",
    "sg:address":"Calle de Eras (de Las), 12",
    "sg:city":"Avila",
    "sg:orig_category":"Agencias De Viajes",
    "sg:phone":"+34 920 25 03 11",
    "sg:postcode":"05002",
    "sg:province":"\u00c1vila",
    "wof:name":"Sanz Perez Juan Carlos",
    "wof:placetype":"venue"
},
  "geometry": {"coordinates":[-4.7000432014,40.6486587524],"type":"Point"}
}