{
  "type": "Feature",
  "properties": {
    "addr:full":"Avda Pontevedra, 2 Estrada Pontevedra 36680",
    "addr:housenumber":"2",
    "addr:postcode":"36680",
    "addr:street":"Avda Pontevedra;Estrada Pontevedra",
    "iso:country":"ES",
    "sg:address":"Avda Pontevedra, 2",
    "sg:city":"Estrada",
    "sg:orig_category":"Muebles, Minoristas",
    "sg:phone":"+34 986 57 01 44",
    "sg:postcode":"36680",
    "sg:province":"Pontevedra",
    "wof:name":"Muebles Emilio Goldar S.l.",
    "wof:placetype":"venue"
},
  "geometry": {"coordinates":[-8.5009889603,42.6866493225],"type":"Point"}
}