{
  "type": "Feature",
  "properties": {
    "iso:country":"ES",
    "sg:address":"Calle de Tierra De Barros, S/n",
    "sg:city":"Villanueva Serena",
    "sg:orig_category":"Papeler\u00cdas, Librer\u00cdas",
    "sg:phone":"+34 924 84 40 51",
    "sg:postcode":"06700",
    "sg:province":"Badajoz",
    "wof:name":"Garcia Perez Angela",
    "wof:placetype":"venue"
},
  "geometry": {"coordinates":[-5.8066940308,38.9718360901],"type":"Point"}
}