{
  "type": "Feature",
  "properties": {
    "iso:country":"ES",
    "sg:address":"Calle de Bodegas, 15",
    "sg:city":"Laguna Duero",
    "sg:orig_category":"Venta, Instalaci\u00d3n De Calefacci\u00d3n",
    "sg:phone":"+34 983 54 04 17",
    "sg:postcode":"47140",
    "sg:province":"Valladolid",
    "wof:name":"Sanz Parra Jose Javier",
    "wof:placetype":"venue"
},
  "geometry": {"coordinates":[-4.7114701271,41.5824012756],"type":"Point"}
}