{
  "type": "Feature",
  "properties": {
    "iso:country":"ES",
    "sg:address":"Calle de Cuevas Del Becerro, 17",
    "sg:city":"Malaga",
    "sg:orig_category":"Autob\u00das (explotaci\u00d3n Y Servicios De)",
    "sg:phone":"+34 952 32 16 80",
    "sg:postcode":"29006",
    "sg:province":"M\u00e1laga",
    "wof:name":"Automoviles Torres S.l.",
    "wof:placetype":"venue"
},
  "geometry": {"coordinates":[-4.4647402763,36.7019004822],"type":"Point"}
}