{
  "type": "Feature",
  "properties": {
    "iso:country":"ES",
    "sg:address":"Avda Benito Perez Galdos, 29",
    "sg:city":"Alacant",
    "sg:orig_category":"Promotores Constructores",
    "sg:phone":"+34 965 14 56 88",
    "sg:postcode":"03004",
    "sg:province":"Alicante",
    "wof:name":"Obras Y Construcciones Costa De Alicante S.l.",
    "wof:placetype":"venue"
},
  "geometry": {"coordinates":[-0.4910289943,38.3481254578],"type":"Point"}
}