{
  "type": "Feature",
  "properties": {
    "addr:full":"V. Real, S/n S. Antonio Benageber Valencia 46184",
    "addr:housenumber":"s",
    "addr:postcode":"46184",
    "addr:street":"Real;/ N S. Antonio Benageber",
    "iso:country":"ES",
    "sg:address":"V. Real, S/n",
    "sg:city":"S. Antonio Benageber",
    "sg:orig_category":"Internados & Ense\u00d1anza Privada",
    "sg:phone":"+34 961 35 05 28",
    "sg:postcode":"46184",
    "sg:province":"Valencia",
    "wof:name":"Colegio Imperial De Ni\u00d1os Huerfanos De San Vicente Ferrer",
    "wof:placetype":"venue"
},
  "geometry": {"coordinates":[-0.5012540221,39.5620651245],"type":"Point"}
}