{
  "type": "Feature",
  "properties": {
    "addr:full":"Pg Saladar, 57 Denia Alicante 03700",
    "addr:housenumber":"57",
    "addr:postcode":"03700",
    "addr:street":"Pg Saladar",
    "iso:country":"ES",
    "sg:address":"Pg Saladar, 57",
    "sg:city":"Denia",
    "sg:orig_category":"Ropa Para Se\u00d1oras (al Por Menor)",
    "sg:phone":"+34 966 42 13 95",
    "sg:postcode":"03700",
    "sg:province":"Alicante",
    "wof:name":"Confecciones Trotto S.l.",
    "wof:placetype":"venue"
},
  "geometry": {"coordinates":[0.1088119969,38.8385009766],"type":"Point"}
}