{
  "type": "Feature",
  "properties": {
    "addr:full":"Basabe Poligonoa, 20 Aretxabaleta Guip\u00f9zcoa 20550",
    "addr:housenumber":"20",
    "addr:postcode":"20550",
    "addr:street":"Basabe Poligonoa;Guipu\u0300Zcoa",
    "iso:country":"ES",
    "sg:address":"Basabe Poligonoa, 20",
    "sg:city":"Aretxabaleta",
    "sg:orig_category":"Empresas De Carpinter\u00cda De Madera",
    "sg:phone":"+34 943 79 34 84",
    "sg:postcode":"20550",
    "sg:province":"Guip\u00f9zcoa",
    "wof:name":"Romero Sanchez Antonio",
    "wof:placetype":"venue"
},
  "geometry": {"coordinates":[-2.5058889389,43.0299415588],"type":"Point"}
}