{
  "type": "Feature",
  "properties": {
    "addr:full":"Cmno Parras (las), 152 Villafranqueza - Palamo Alicante 03112",
    "addr:housenumber":"152",
    "addr:postcode":"03112",
    "addr:street":"Cmno Parras Las",
    "iso:country":"ES",
    "sg:address":"Cmno Parras (las), 152",
    "sg:city":"Villafranqueza - Palamo",
    "sg:orig_category":"Alquiler De Gr\u00daas",
    "sg:phone":"+34 965 18 35 03",
    "sg:postcode":"03112",
    "sg:province":"Alicante",
    "wof:name":"Gruas Dyna S.l.",
    "wof:placetype":"venue"
},
  "geometry": {"coordinates":[-0.4810059965,38.3452033997],"type":"Point"}
}