{
  "type": "Feature",
  "properties": {
    "iso:country":"ES",
    "sg:address":"Calle de Juan Pablo Ii, 12",
    "sg:city":"Zaragoza",
    "sg:orig_category":"Carnicer\u00cdas, Carnicer\u00cdas",
    "sg:phone":"+34 976 75 07 65",
    "sg:postcode":"50009",
    "sg:province":"Zaragoza",
    "wof:name":"Use Solans Jesus Enrique",
    "wof:placetype":"venue"
},
  "geometry": {"coordinates":[-0.9126039743,41.6433143616],"type":"Point"}
}