{
  "type": "Feature",
  "properties": {
    "iso:country":"ES",
    "sg:address":"Avda Alemania (de), 4",
    "sg:city":"Caceres",
    "sg:orig_category":"Ropa Para Ni\u00d1os (al Por Menor)",
    "sg:phone":"+34 927 24 35 03",
    "sg:postcode":"10001",
    "sg:province":"C\u00e1ceres",
    "wof:name":"Moreno Sanchez Cipriano",
    "wof:placetype":"venue"
},
  "geometry": {"coordinates":[-6.3797988892,39.4677124023],"type":"Point"}
}