{
  "type": "Feature",
  "properties": {
    "iso:country":"ES",
    "sg:address":"Calle de Escritor Antonio Quintero Y Ramirez, 3",
    "sg:city":"Jerez De La Frontera",
    "sg:orig_category":"Ropa Y Accesorios",
    "sg:phone":"+34 956 14 17 47",
    "sg:postcode":"11408",
    "sg:province":"C\u00e1diz",
    "wof:name":"Ruda Y Fernandez S.l.",
    "wof:placetype":"venue"
},
  "geometry": {"coordinates":[-6.1484937668,36.6730155945],"type":"Point"}
}