{
  "type": "Feature",
  "properties": {
    "iso:country":"ES",
    "sg:address":"Calle de Don Tello, 22",
    "sg:city":"Gernika-lumo",
    "sg:orig_category":"Florister\u00cdas",
    "sg:phone":"+34 946 25 31 48",
    "sg:postcode":"48300",
    "sg:province":"Vizcaya",
    "wof:name":"Comercial Uriarte",
    "wof:placetype":"venue"
},
  "geometry": {"coordinates":[-2.6758244038,43.3161773682],"type":"Point"}
}