{
  "type": "Feature",
  "properties": {
    "iso:country":"ES",
    "sg:address":"Avda Toledo, Km. 0028,0",
    "sg:city":"Torrijos",
    "sg:orig_category":"Frutas Y Legumbres Frescas (al Por Mayor)",
    "sg:phone":"+34 925 76 18 53",
    "sg:postcode":"45500",
    "sg:province":"Toledo",
    "wof:name":"Frutas Bolado S.l.",
    "wof:placetype":"venue"
},
  "geometry": {"coordinates":[-4.2692389488,39.9786872864],"type":"Point"}
}