{
  "type": "Feature",
  "properties": {
    "iso:country":"ES",
    "sg:address":"Calle de Mu\u00d1oz Olive, 8",
    "sg:city":"Sevilla",
    "sg:orig_category":"Caf\u00c9s, Bares, Cervecer\u00cdas",
    "sg:phone":"+34 954 21 06 92",
    "sg:postcode":"41001",
    "sg:province":"Sevilla",
    "wof:name":"Madian S.l.",
    "wof:placetype":"venue"
},
  "geometry": {"coordinates":[-5.9967589378,37.3903083801],"type":"Point"}
}