{
  "type": "Feature",
  "properties": {
    "addr:full":"Calle de Motilla Del Palancar, 15 Valencia Valencia 46019",
    "addr:housenumber":"15",
    "addr:postcode":"46019",
    "addr:street":"Calle De Motilla Del Palancar",
    "iso:country":"ES",
    "sg:address":"Calle de Motilla Del Palancar, 15",
    "sg:city":"Valencia",
    "sg:orig_category":"Mensajer\u00cda Express, Portes Internacionales",
    "sg:phone":"+34 902 10 16 22",
    "sg:postcode":"46019",
    "sg:province":"Valencia",
    "sg:website":"www.medur.es",
    "wof:name":"Mensajeros De Levante S.l.",
    "wof:placetype":"venue"
},
  "geometry": {"coordinates":[-0.3687529862,39.490650177],"type":"Point"}
}