{
  "type": "Feature",
  "properties": {
    "addr:full":"Rbla Sant Esteve (de), 14 Ripollet Barcelona 08291",
    "addr:housenumber":"14",
    "addr:postcode":"08291",
    "addr:street":"Rbla Sant Esteve De",
    "iso:country":"ES",
    "sg:address":"Rbla Sant Esteve (de), 14",
    "sg:city":"Ripollet",
    "sg:orig_category":"Electrodom\u00c9sticos (al Por Menor)",
    "sg:phone":"+34 935 80 77 86",
    "sg:postcode":"08291",
    "sg:province":"Barcelona",
    "wof:name":"Standel-3 S.l.",
    "wof:placetype":"venue"
},
  "geometry": {"coordinates":[2.1573090553,41.4993553162],"type":"Point"}
}