{
  "type": "Feature",
  "properties": {
    "iso:country":"ES",
    "sg:address":"Carr Guasch, 83",
    "sg:city":"Badalona",
    "sg:orig_category":"Electricidad (montaje, Ensamblaje De Componentes)",
    "sg:phone":"+34 933 98 36 42",
    "sg:postcode":"08913",
    "sg:province":"Barcelona",
    "wof:name":"Cano Lopez Antonio",
    "wof:placetype":"venue"
},
  "geometry": {"coordinates":[2.2178208828,41.4350738525],"type":"Point"}
}