{
  "type": "Feature",
  "properties": {
    "addr:full":"Plaz Nueva De San Anton, 7 San Anton Murcia 30009",
    "addr:housenumber":"7",
    "addr:postcode":"30009",
    "addr:street":"Plaz Nueva De San Anton",
    "iso:country":"ES",
    "sg:address":"Plaz Nueva De San Anton, 7",
    "sg:city":"San Anton",
    "sg:orig_category":"Asesor\u00cda Sobre Comunicaci\u00d3n De Empresas",
    "sg:phone":"+34 968 27 45 60",
    "sg:postcode":"30009",
    "sg:province":"Murcia",
    "wof:name":"Nofer Asesores S.l.",
    "wof:placetype":"venue"
},
  "geometry": {"coordinates":[-1.1410030127,37.990814209],"type":"Point"}
}