{
  "type": "Feature",
  "properties": {
    "iso:country":"ES",
    "sg:address":"Calle de Mikeldi Kalea, 6",
    "sg:city":"Durango",
    "sg:orig_category":"Art\u00cdculos De Decoraci\u00d3n (fabricaci\u00d3n Y Al Por Mayor)",
    "sg:phone":"+34 944 66 86 19",
    "sg:postcode":"48200",
    "sg:province":"Vizcaya",
    "wof:name":"Alki Decoracion,s.l.",
    "wof:placetype":"venue"
},
  "geometry": {"coordinates":[-2.6342000961,43.1724205017],"type":"Point"}
}