{
  "type": "Feature",
  "properties": {
    "iso:country":"ES",
    "sg:address":"Carr Bassa, S/n",
    "sg:city":"Alguaire",
    "sg:orig_category":"Centros De Educaci\u00d3n Especial",
    "sg:phone":"+34 973 75 63 46",
    "sg:postcode":"25125",
    "sg:province":"Lleida",
    "wof:name":"C.e.i.p. Teresa Bergada",
    "wof:placetype":"venue"
},
  "geometry": {"coordinates":[0.5827929974,41.7364616394],"type":"Point"}
}