{
  "type": "Feature",
  "properties": {
    "iso:country":"ES",
    "sg:address":"Calle de Alcalde Aparicio Y Marin, 8",
    "sg:city":"Cordoba",
    "sg:orig_category":"Asociaciones Humanitarias, De Cooperaci\u00d3n, De Acci\u00d3n Social",
    "sg:phone":"+34 957 23 77 99",
    "sg:postcode":"14005",
    "sg:province":"C\u00f3rdoba",
    "wof:name":"Federacion Andaluza De Asociaciones Prod",
    "wof:placetype":"venue"
},
  "geometry": {"coordinates":[-4.7902579308,37.8847503662],"type":"Point"}
}