{
  "type": "Feature",
  "properties": {
    "iso:country":"ES",
    "sg:address":"Calle de Reyes Catolicos, 25",
    "sg:city":"Alacant",
    "sg:orig_category":"Calzados Ortop\u00c9dicos",
    "sg:phone":"+34 965 92 27 67",
    "sg:postcode":"03003",
    "sg:province":"Alicante",
    "wof:name":"Aparells Ortopedics Curto S.l.",
    "wof:placetype":"venue"
},
  "geometry": {"coordinates":[-0.4905908108,38.3422889709],"type":"Point"}
}