{
  "type": "Feature",
  "properties": {
    "iso:country":"ES",
    "sg:address":"Avda Espa\u00d1a, S/n",
    "sg:city":"Estepona",
    "sg:orig_category":"Museos",
    "sg:phone":"+34 952 80 71 48",
    "sg:postcode":"29680",
    "sg:province":"M\u00e1laga",
    "wof:name":"Ayuntamiento De Estepona",
    "wof:placetype":"venue"
},
  "geometry": {"coordinates":[-5.1565451622,36.417552948],"type":"Point"}
}