{
  "type": "Feature",
  "properties": {
    "iso:country":"ES",
    "sg:address":"Rua Colon, 17",
    "sg:city":"Vigo",
    "sg:orig_category":"Seguridad Social",
    "sg:phone":"+34 986 22 33 87",
    "sg:postcode":"36201",
    "sg:province":"Pontevedra",
    "wof:name":"Vicente Cerqueira Miguel Angel",
    "wof:placetype":"venue"
},
  "geometry": {"coordinates":[-8.7200651169,42.2374763489],"type":"Point"}
}