{
  "type": "Feature",
  "properties": {
    "addr:full":"Calle de Portalada (la), 24 Logro\u00f1o La Rioja 26006",
    "addr:housenumber":"24",
    "addr:postcode":"26006",
    "addr:street":"Calle De Portalada La;Rioja",
    "iso:country":"ES",
    "sg:address":"Calle de Portalada (la), 24",
    "sg:city":"Logro\u00f1o",
    "sg:orig_category":"Empresarios",
    "sg:phone":"+34 941 25 08 76",
    "sg:postcode":"26006",
    "sg:province":"La Rioja",
    "wof:name":"Geser Rioja S.l.",
    "wof:placetype":"venue"
},
  "geometry": {"coordinates":[-2.4110970497,42.4577140808],"type":"Point"}
}