{
  "type": "Feature",
  "properties": {
    "addr:full":"Calle de Honduras, 12 Madrid Madrid 28016",
    "addr:housenumber":"12",
    "addr:postcode":"madrid;28016",
    "addr:street":"Calle De Honduras",
    "iso:country":"ES",
    "sg:address":"Calle de Honduras, 12",
    "sg:city":"Madrid",
    "sg:orig_category":"Inmobiliaria (agencias)",
    "sg:phone":"+34 913 45 14 54",
    "sg:postcode":"28016",
    "sg:province":"Madrid",
    "wof:name":"Promolar S.xxi S.l./,",
    "wof:placetype":"venue"
},
  "geometry": {"coordinates":[-3.6793370247,40.4597320557],"type":"Point"}
}