{
  "type": "Feature",
  "properties": {
    "addr:full":"Av Josep Molins, 29 Hospitalet Llobregat Barcelona 08906",
    "addr:housenumber":"29",
    "addr:postcode":"08906",
    "addr:street":"Av Josep Molins",
    "iso:country":"ES",
    "sg:address":"Av Josep Molins, 29",
    "sg:city":"Hospitalet Llobregat",
    "sg:orig_category":"Productos Qu\u00cdmicos (fabricaci\u00d3n, Al Por Mayor)",
    "sg:phone":"+34 934 48 17 26",
    "sg:postcode":"08906",
    "sg:province":"Barcelona",
    "wof:name":"Dade Behring S.a.",
    "wof:placetype":"venue"
},
  "geometry": {"coordinates":[2.1066219807,41.3743515015],"type":"Point"}
}