{
  "type": "Feature",
  "properties": {
    "iso:country":"ES",
    "sg:address":"Calle de Arco De La Villa, 13",
    "sg:city":"Baena",
    "sg:orig_category":"Arquitectos",
    "sg:phone":"+34 957 67 16 76",
    "sg:postcode":"14850",
    "sg:province":"C\u00f3rdoba",
    "wof:name":"Ca\u00f1ete Perez Manuel",
    "wof:placetype":"venue"
},
  "geometry": {"coordinates":[-4.3291640282,37.6134757996],"type":"Point"}
}