{
  "type": "Feature",
  "properties": {
    "addr:full":"Calle de General Alava, 28 Vitoria-gasteiz \u00c1lava 01005",
    "addr:housenumber":"28",
    "addr:postcode":"01005",
    "addr:street":"Calle De General Alava",
    "iso:country":"ES",
    "sg:address":"Calle de General Alava, 28",
    "sg:city":"Vitoria-gasteiz",
    "sg:orig_category":"M\u00c9dicos: Medicina Interna",
    "sg:phone":"+34 945 23 30 68",
    "sg:postcode":"01005",
    "sg:province":"\u00c1lava",
    "wof:name":"Mendivil Ozamiz Antonio",
    "wof:placetype":"venue"
},
  "geometry": {"coordinates":[-2.6704599857,42.8446846008],"type":"Point"}
}