{
  "type": "Feature",
  "properties": {
    "addr:full":"Plaz Coca De La Pi\u00d1era, 2 Jaen Ja\u00e9n 23001",
    "addr:housenumber":"2;jae\u0301n",
    "addr:postcode":"23001",
    "addr:street":"Pin\u0303Era",
    "iso:country":"ES",
    "sg:address":"Plaz Coca De La Pi\u00d1era, 2",
    "sg:city":"Jaen",
    "sg:orig_category":"Radiocomunicaciones, Telefon\u00cda M\u00d3vil, Radiomensajer\u00cda: Servicios, Comercializaci\u00d3n",
    "sg:phone":"+34 953 27 01 12",
    "sg:postcode":"23001",
    "sg:province":"Ja\u00e9n",
    "sg:website":"www.telyco.es",
    "wof:name":"Teleinformatica Y Comunicaciones S.a.",
    "wof:placetype":"venue"
},
  "geometry": {"coordinates":[-3.7873001099,37.7709007263],"type":"Point"}
}