{
  "type": "Feature",
  "properties": {
    "iso:country":"ES",
    "sg:address":"Carrer de Castella, 5054",
    "sg:city":"Prat Llobregat",
    "sg:orig_category":"Asociaciones Y Clubs Deportivos",
    "sg:phone":"+34 933 70 58 52",
    "sg:postcode":"08820",
    "sg:province":"Barcelona",
    "wof:name":"Rilo Salas Justo",
    "wof:placetype":"venue"
},
  "geometry": {"coordinates":[2.0964579582,41.3242454529],"type":"Point"}
}