{
  "type": "Feature",
  "properties": {
    "iso:country":"ES",
    "sg:address":"Avda Castilla, S/n",
    "sg:city":"Antilla",
    "sg:orig_category":"Molduras, Junquillos, Listones Y Molduras Perforadas",
    "sg:phone":"+34 959 48 07 03",
    "sg:postcode":"21449",
    "sg:province":"Huelva",
    "wof:name":"Santana Real Francisca",
    "wof:placetype":"venue"
},
  "geometry": {"coordinates":[-7.2067580223,37.2075386047],"type":"Point"}
}