{
  "type": "Feature",
  "properties": {
    "addr:full":"Calle de Fuencarral, 106 Madrid Madrid 28004",
    "addr:housenumber":"106",
    "addr:postcode":"28004",
    "addr:street":"Calle De Fuencarral",
    "iso:country":"ES",
    "sg:address":"Calle de Fuencarral, 106",
    "sg:city":"Madrid",
    "sg:orig_category":"Animales (al Por Menor)",
    "sg:phone":"+34 915 24 09 36",
    "sg:postcode":"28004",
    "sg:province":"Madrid",
    "sg:website":"www.elhogardelperro.com",
    "wof:name":"Prol Conde Maria Del Pilar",
    "wof:placetype":"venue"
},
  "geometry": {"coordinates":[-3.7018918991,40.4282569885],"type":"Point"}
}