{
  "type": "Feature",
  "properties": {
    "iso:country":"ES",
    "sg:address":"Calle de Ca\u00d1ete, 23",
    "sg:city":"Cuenca",
    "sg:orig_category":"Alimentaci\u00d3n General (al Por Menor)",
    "sg:phone":"+34 969 22 08 90",
    "sg:postcode":"16004",
    "sg:province":"Cuenca",
    "wof:name":"Mora Valero Juan",
    "wof:placetype":"venue"
},
  "geometry": {"coordinates":[-2.1343669891,40.0692939758],"type":"Point"}
}