{
  "type": "Feature",
  "properties": {
    "iso:country":"ES",
    "sg:address":"Pase Parque, 33",
    "sg:city":"Albanchez Magina",
    "sg:orig_category":"Discotecas Y Salas De Baile",
    "sg:phone":"+34 953 35 83 20",
    "sg:postcode":"23538",
    "sg:province":"Ja\u00e9n",
    "wof:name":"Navarrete Ruiz Gabriel",
    "wof:placetype":"venue"
},
  "geometry": {"coordinates":[-3.4678039551,37.792339325],"type":"Point"}
}