{
  "type": "Feature",
  "properties": {
    "iso:country":"ES",
    "sg:address":"Av President Companys, 13",
    "sg:city":"Mataro",
    "sg:orig_category":"Molduras, Junquillos, Listones Y Molduras Perforadas",
    "sg:phone":"+34 937 99 06 05",
    "sg:postcode":"08302",
    "sg:province":"Barcelona",
    "wof:name":"Esparza Sanchez Jose",
    "wof:placetype":"venue"
},
  "geometry": {"coordinates":[2.4317519665,41.5355911255],"type":"Point"}
}