{
  "type": "Feature",
  "properties": {
    "iso:country":"ES",
    "sg:address":"Pl. Dachs, 8",
    "sg:city":"La Garriga",
    "sg:orig_category":"Lencer\u00cda Femenina, Corseter\u00cda, Trajes De Ba\u00d1o (al Por Menor)",
    "sg:phone":"+34 938 71 71 67",
    "sg:postcode":"08530",
    "sg:province":"Barcelona",
    "wof:name":"Coll Busquets Maria Eugenia",
    "wof:placetype":"venue"
},
  "geometry": {"coordinates":[2.2859749794,41.6846961975],"type":"Point"}
}