{
  "type": "Feature",
  "properties": {
    "addr:full":"Calle de Casto Plasencia, S/n San Esteban Asturias 33130",
    "addr:housenumber":"s / n",
    "addr:postcode":"33130",
    "addr:street":"Calle De Casto",
    "iso:country":"ES",
    "sg:address":"Calle de Casto Plasencia, S/n",
    "sg:city":"San Esteban",
    "sg:orig_category":"Transportes Ferroviarios",
    "sg:phone":"+34 985 58 00 39",
    "sg:postcode":"33130",
    "sg:province":"Asturias",
    "wof:name":"Ferrocarriles De Via Estrecha",
    "wof:placetype":"venue"
},
  "geometry": {"coordinates":[-6.8376889229,43.3146896362],"type":"Point"}
}