{
  "type": "Feature",
  "properties": {
    "addr:full":"Calle de Fuente Del Sol, 32 Alcala Henares Madrid 28803",
    "addr:housenumber":"32",
    "addr:postcode":"28803",
    "addr:street":"Calle De Fuente Del Sol",
    "iso:country":"ES",
    "sg:address":"Calle de Fuente Del Sol, 32",
    "sg:city":"Alcala Henares",
    "sg:orig_category":"Transporte En General",
    "sg:phone":"+34 918 80 67 66",
    "sg:postcode":"28803",
    "sg:province":"Madrid",
    "wof:name":"Gonzalez Jimenez Saturnino",
    "wof:placetype":"venue"
},
  "geometry": {"coordinates":[-3.3671479225,40.4706497192],"type":"Point"}
}