{
  "type": "Feature",
  "properties": {
    "addr:full":"Plaza Irailaren 23a, 4 Erandio Vizcaya 48950",
    "addr:housenumber":"23a 4",
    "addr:postcode":"48950",
    "addr:street":"Irailaren",
    "iso:country":"ES",
    "sg:address":"Plaza Irailaren 23a, 4",
    "sg:city":"Erandio",
    "sg:orig_category":"Ropa Para Ni\u00d1os (al Por Menor)",
    "sg:phone":"+34 944 67 36 86",
    "sg:postcode":"48950",
    "sg:province":"Vizcaya",
    "wof:name":"Ibarrondo Rebolledo Unaine",
    "wof:placetype":"venue"
},
  "geometry": {"coordinates":[-2.9758810997,43.30286026],"type":"Point"}
}