{
  "type": "Feature",
  "properties": {
    "addr:full":"Calle de Gabriel Lobo, 18 Madrid Madrid 28002",
    "addr:housenumber":"18",
    "addr:postcode":"madrid;28002",
    "addr:street":"Calle De Gabriel Lobo",
    "iso:country":"ES",
    "sg:address":"Calle de Gabriel Lobo, 18",
    "sg:city":"Madrid",
    "sg:orig_category":"\u00d3pticos Optometristas (al Por Menor)",
    "sg:phone":"+34 915 61 86 47",
    "sg:postcode":"28002",
    "sg:province":"Madrid",
    "wof:name":"Suarez Gonzalez Jesus",
    "wof:placetype":"venue"
},
  "geometry": {"coordinates":[-3.6801688671,40.4433135986],"type":"Point"}
}