{
  "type": "Feature",
  "properties": {
    "iso:country":"ES",
    "sg:address":"Carrer de Riera De Vallvidrera, S/n",
    "sg:city":"Molins Rei",
    "sg:orig_category":"Artes Gr\u00c1ficas, Artes Pl\u00c1sticas: Material Y Suministros (al Por Menor)",
    "sg:phone":"+34 936 80 11 25",
    "sg:postcode":"08750",
    "sg:province":"Barcelona",
    "wof:name":"Serveis Comercials Peremont S.l.",
    "wof:placetype":"venue"
},
  "geometry": {"coordinates":[2.0148820877,41.4205093384],"type":"Point"}
}