{
  "type": "Feature",
  "properties": {
    "iso:country":"ES",
    "sg:address":"Calle de Serena La, 7",
    "sg:city":"Gijon",
    "sg:orig_category":"Farmacias",
    "sg:phone":"+34 985 38 64 31",
    "sg:postcode":"33208",
    "sg:province":"Asturias",
    "wof:name":"Alvarez-sala De Faes Maria Silvina",
    "wof:placetype":"venue"
},
  "geometry": {"coordinates":[-5.665186882,43.5300979614],"type":"Point"}
}