{
  "type": "Feature",
  "properties": {
    "iso:country":"ES",
    "sg:address":"Avda Heroes De Baler, 23",
    "sg:city":"Caceres",
    "sg:orig_category":"Frutas, Legumbres Frescas Y Tempranas (al Por Menor)",
    "sg:phone":"+34 927 21 74 78",
    "sg:postcode":"10004",
    "sg:province":"C\u00e1ceres",
    "wof:name":"Amaya Mendo Juan Antonio",
    "wof:placetype":"venue"
},
  "geometry": {"coordinates":[-6.3653249741,39.483631134],"type":"Point"}
}