{
  "type": "Feature",
  "properties": {
    "addr:full":"Calle de Postas, 1 San Ildefonso O La Granja Segovia 40100",
    "addr:housenumber":"1",
    "addr:postcode":"40100",
    "addr:street":"Calle De Postas;O",
    "iso:country":"ES",
    "sg:address":"Calle de Postas, 1",
    "sg:city":"San Ildefonso O La Granja",
    "sg:orig_category":"Florister\u00cdas",
    "sg:phone":"+34 921 47 11 75",
    "sg:postcode":"40100",
    "sg:province":"Segovia",
    "wof:name":"Herrero Alberola Raul",
    "wof:placetype":"venue"
},
  "geometry": {"coordinates":[-4.0065932274,40.9022903442],"type":"Point"}
}