{
  "type": "Feature",
  "properties": {
    "addr:full":"I. Peral (z. Ind Cami Ral), S/n Gava Barcelona 08850",
    "addr:housenumber":"s / n",
    "addr:postcode":"08850",
    "addr:street":"I.;Cami Ral",
    "iso:country":"ES",
    "sg:address":"I. Peral (z. Ind Cami Ral), S/n",
    "sg:city":"Gava",
    "sg:orig_category":"Art\u00cdculos Funerarios (al Por Menor)",
    "sg:phone":"+34 936 62 79 68",
    "sg:postcode":"08850",
    "sg:province":"Barcelona",
    "wof:name":"Rodenas Sans Rafael",
    "wof:placetype":"venue"
},
  "geometry": {"coordinates":[1.9947919846,41.2888259888],"type":"Point"}
}