{
  "type": "Feature",
  "properties": {
    "addr:full":"Rua Catedral (da), 21 Lugo Lugo 27001",
    "addr:housenumber":"21",
    "addr:postcode":"27001",
    "addr:street":"Rua Catedral Da",
    "iso:country":"ES",
    "sg:address":"Rua Catedral (da), 21",
    "sg:city":"Lugo",
    "sg:orig_category":"Frutas, Legumbres Frescas Y Tempranas (al Por Menor)",
    "sg:phone":"+34 982 25 09 85",
    "sg:postcode":"27001",
    "sg:province":"Lugo",
    "wof:name":"Sanchez Lopez Maria Jesus",
    "wof:placetype":"venue"
},
  "geometry": {"coordinates":[-7.5589308739,43.0094718933],"type":"Point"}
}