{
  "type": "Feature",
  "properties": {
    "addr:full":"Calle de Maruja Garrido, 10 Caravaca Cruz Murcia 30400",
    "addr:housenumber":"10",
    "addr:postcode":"30400",
    "addr:street":"Calle De Maruja Garrido",
    "iso:country":"ES",
    "sg:address":"Calle de Maruja Garrido, 10",
    "sg:city":"Caravaca Cruz",
    "sg:orig_category":"Loter\u00cda Y T\u00d3mbola",
    "sg:phone":"+34 968 70 55 51",
    "sg:postcode":"30400",
    "sg:province":"Murcia",
    "wof:name":"Flores Molina Juan",
    "wof:placetype":"venue"
},
  "geometry": {"coordinates":[-1.8628330231,38.1046943665],"type":"Point"}
}