{
  "type": "Feature",
  "properties": {
    "iso:country":"ES",
    "sg:address":"Carrer de Avila, 35",
    "sg:city":"Amposta",
    "sg:orig_category":"Alimentaci\u00d3n General (al Por Menor)",
    "sg:phone":"+34 977 70 03 16",
    "sg:postcode":"43870",
    "sg:province":"Tarragona",
    "wof:name":"Maigi Cid Lourdes Alicia",
    "wof:placetype":"venue"
},
  "geometry": {"coordinates":[0.5823140144,40.7031326294],"type":"Point"}
}