{
  "type": "Feature",
  "properties": {
    "addr:full":"Avgd Mestre Montaner, 29 Igualada Barcelona 08700",
    "addr:housenumber":"29",
    "addr:postcode":"08700",
    "addr:street":"Mestre Montaner",
    "iso:country":"ES",
    "sg:address":"Avgd Mestre Montaner, 29",
    "sg:city":"Igualada",
    "sg:orig_category":"Arquitectos",
    "sg:phone":"+34 938 04 60 04",
    "sg:postcode":"08700",
    "sg:province":"Barcelona",
    "wof:name":"Arquitectura Anoia S.c.p.",
    "wof:placetype":"venue"
},
  "geometry": {"coordinates":[1.5906194448,41.6003875732],"type":"Point"}
}