{
  "type": "Feature",
  "properties": {
    "iso:country":"ES",
    "sg:address":"Calle de Lusitania, 2",
    "sg:city":"Ayamonte",
    "sg:orig_category":"Molduras, Junquillos, Listones Y Molduras Perforadas",
    "sg:phone":"+34 959 32 10 25",
    "sg:postcode":"21400",
    "sg:province":"Huelva",
    "wof:name":"Rodriguez Rodriguez Manuel",
    "wof:placetype":"venue"
},
  "geometry": {"coordinates":[-7.407324791,37.2132034302],"type":"Point"}
}