{
  "type": "Feature",
  "properties": {
    "iso:country":"ES",
    "sg:address":"Calle de Mayor, 24",
    "sg:city":"Lerma",
    "sg:orig_category":"Asesor\u00cda Fiscal Y Jur\u00cddica",
    "sg:phone":"+34 947 17 00 40",
    "sg:postcode":"09340",
    "sg:province":"Burgos",
    "wof:name":"Garcia Del Pozo Luis Daniel",
    "wof:placetype":"venue"
},
  "geometry": {"coordinates":[-3.7572829723,42.0259513855],"type":"Point"}
}