{
  "type": "Feature",
  "properties": {
    "addr:full":"Pl Ll San Agustin, 1 Lucena C\u00f3rdoba 14900",
    "addr:housenumber":"1",
    "addr:postcode":"14900",
    "addr:street":"Pl Ll San Agustin",
    "iso:country":"ES",
    "sg:address":"Pl Ll San Agustin, 1",
    "sg:city":"Lucena",
    "sg:orig_category":"Ingeniero",
    "sg:phone":"+34 957 50 39 86",
    "sg:postcode":"14900",
    "sg:province":"C\u00f3rdoba",
    "wof:name":"Agrotec Ingenieros Consultores Asociados S.c.",
    "wof:placetype":"venue"
},
  "geometry": {"coordinates":[-4.5418143272,37.3598442078],"type":"Point"}
}