{
  "type": "Feature",
  "properties": {
    "iso:country":"ES",
    "sg:address":"Urb Monte Mar, S/n",
    "sg:city":"Gran Alacant",
    "sg:orig_category":"Promotores Constructores",
    "sg:phone":"+34 966 69 80 48",
    "sg:postcode":"03130",
    "sg:province":"Alicante",
    "wof:name":"Monte Y Mar De Santa Pola S.l.",
    "wof:placetype":"venue"
},
  "geometry": {"coordinates":[-0.5578309894,38.2048950195],"type":"Point"}
}