{
  "type": "Feature",
  "properties": {
    "iso:country":"ES",
    "sg:address":"C/ Carme, 11",
    "sg:city":"Tarrega",
    "sg:orig_category":"Sociedades, Compa\u00d1\u00cdas Aseguradoras",
    "sg:phone":"+34 973 31 06 08",
    "sg:postcode":"25300",
    "sg:province":"Lleida",
    "wof:name":"Gine-escola Correduria De Seguros S.a.",
    "wof:placetype":"venue"
},
  "geometry": {"coordinates":[1.1396369934,41.6474075317],"type":"Point"}
}