{
  "type": "Feature",
  "properties": {
    "iso:country":"ES",
    "sg:address":"Calle de San Miguel, 18",
    "sg:city":"Albalate Cinca",
    "sg:orig_category":"Asesor\u00cda Sobre Comunicaci\u00d3n De Empresas",
    "sg:phone":"+34 974 46 93 06",
    "sg:postcode":"22534",
    "sg:province":"Huesca",
    "wof:name":"De Dios Cabrera Gonzalo",
    "wof:placetype":"venue"
},
  "geometry": {"coordinates":[0.1478749961,41.7240715027],"type":"Point"}
}