{
  "type": "Feature",
  "properties": {
    "iso:country":"ES",
    "sg:address":"Carrer de Pizarro, 5",
    "sg:city":"Barcelona",
    "sg:orig_category":"Empresarios",
    "sg:phone":"+34 933 19 30 55",
    "sg:postcode":"08003",
    "sg:province":"Barcelona",
    "wof:name":"Hernandez Ruiz Jose Antonio",
    "wof:placetype":"venue"
},
  "geometry": {"coordinates":[2.1883840561,41.3819923401],"type":"Point"}
}