{
  "type": "Feature",
  "properties": {
    "addr:full":"Calle de San Gines, 4 Santa Olalla Toledo 45530",
    "addr:housenumber":"4",
    "addr:postcode":"45530",
    "addr:street":"Calle De San Gines",
    "iso:country":"ES",
    "sg:address":"Calle de San Gines, 4",
    "sg:city":"Santa Olalla",
    "sg:orig_category":"Supermercados Y Hipermercados",
    "sg:phone":"+34 925 79 75 91",
    "sg:postcode":"45530",
    "sg:province":"Toledo",
    "wof:name":"Garcia Y Bermudez Alimentacion S.l.",
    "wof:placetype":"venue"
},
  "geometry": {"coordinates":[-4.4273929596,40.0246543884],"type":"Point"}
}