{
  "type": "Feature",
  "properties": {
    "addr:full":"Av Valles, 59 Cardedeu Barcelona 08440",
    "addr:housenumber":"59",
    "addr:postcode":"08440",
    "addr:street":"Av Valles",
    "iso:country":"ES",
    "sg:address":"Av Valles, 59",
    "sg:city":"Cardedeu",
    "sg:orig_category":"Artes Gr\u00c1ficas, Artes Pl\u00c1sticas: Material Y Suministros (al Por Menor)",
    "sg:phone":"+34 938 44 47 10",
    "sg:postcode":"08440",
    "sg:province":"Barcelona",
    "wof:name":"Sefar Maissa S.a.",
    "wof:placetype":"venue"
},
  "geometry": {"coordinates":[2.3595221043,41.6231803894],"type":"Point"}
}