{
  "type": "Feature",
  "properties": {
    "addr:full":"Calle de Conde Del Valle De San Juan, 7 San Pedro Murcia 30004",
    "addr:housenumber":"7",
    "addr:postcode":"30004",
    "addr:street":"Calle De Conde Del;San Juan",
    "iso:country":"ES",
    "sg:address":"Calle de Conde Del Valle De San Juan, 7",
    "sg:city":"San Pedro",
    "sg:orig_category":"Abogados",
    "sg:phone":"+34 968 22 52 75",
    "sg:postcode":"30004",
    "sg:province":"Murcia",
    "wof:name":"Vidal Perez Maria Fernanda",
    "wof:placetype":"venue"
},
  "geometry": {"coordinates":[-1.1316889524,37.9838790894],"type":"Point"}
}