{
  "type": "Feature",
  "properties": {
    "iso:country":"ES",
    "sg:address":"Avda Carlos De Haya, 156",
    "sg:city":"Malaga",
    "sg:orig_category":"M\u00c9dicos: Foniatr\u00cda Y Logopedia",
    "sg:phone":"+34 952 30 38 87",
    "sg:postcode":"29010",
    "sg:province":"M\u00e1laga",
    "wof:name":"Colegio Oficial De Logopedas De Andalucia",
    "wof:placetype":"venue"
},
  "geometry": {"coordinates":[-4.4545059204,36.7238540649],"type":"Point"}
}