{
  "type": "Feature",
  "properties": {
    "addr:full":"Carrer de Vallespir, 117 Barcelona Barcelona 08014",
    "addr:housenumber":"117",
    "addr:postcode":"08014",
    "addr:street":"Carrer De Vallespir",
    "iso:country":"ES",
    "sg:address":"Carrer de Vallespir, 117",
    "sg:city":"Barcelona",
    "sg:orig_category":"Quincaller\u00cda (al Por Menor)",
    "sg:phone":"+34 934 90 20 46",
    "sg:postcode":"08014",
    "sg:province":"Barcelona",
    "wof:name":"Puigoril Valls Victor",
    "wof:placetype":"venue"
},
  "geometry": {"coordinates":[2.1351959705,41.3820724487],"type":"Point"}
}