{
  "type": "Feature",
  "properties": {
    "addr:full":"Ctra Provincial, 71 Santa Ursula Santa Cruz De Tenerife 38390",
    "addr:postcode":"38390",
    "addr:street":"Ctra Provincial 71",
    "iso:country":"ES",
    "sg:address":"Ctra Provincial, 71",
    "sg:city":"Santa Ursula",
    "sg:orig_category":"Imprenta",
    "sg:phone":"+34 922 30 06 14",
    "sg:postcode":"38390",
    "sg:province":"Santa Cruz De Tenerife",
    "wof:name":"Gonzalez Hernandez Miguel Angel",
    "wof:placetype":"venue"
},
  "geometry": {"coordinates":[-16.4970397949,28.4235095978],"type":"Point"}
}