{
  "type": "Feature",
  "properties": {
    "addr:full":"Ctra Nal Iii, S/n Utiel Valencia 46300",
    "addr:housenumber":"s / n",
    "addr:postcode":"46300",
    "addr:street":"Ctra Nal Iii",
    "iso:country":"ES",
    "sg:address":"Ctra Nal Iii, S/n",
    "sg:city":"Utiel",
    "sg:orig_category":"Molduras, Junquillos, Listones Y Molduras Perforadas",
    "sg:phone":"+34 962 17 19 63",
    "sg:postcode":"46300",
    "sg:province":"Valencia",
    "wof:name":"Molero Garrido Francisco",
    "wof:placetype":"venue"
},
  "geometry": {"coordinates":[-1.2064390182,39.5707588196],"type":"Point"}
}