{
  "type": "Feature",
  "properties": {
    "iso:country":"ES",
    "sg:address":"Plaz Moreria, 4",
    "sg:city":"Madrid",
    "sg:orig_category":"Mec\u00c1nico Del Autom\u00d3vil",
    "sg:phone":"+34 913 66 28 74",
    "sg:postcode":"28005",
    "sg:province":"Madrid",
    "wof:name":"Corbacho Trinidad Domingo",
    "wof:placetype":"venue"
},
  "geometry": {"coordinates":[-3.713064909,40.413143158],"type":"Point"}
}