{
  "type": "Feature",
  "properties": {
    "addr:full":"Cno. Obispo, 25 Mostoles Madrid 28935",
    "addr:housenumber":"25",
    "addr:postcode":"28935",
    "addr:street":"Cno. Obispo",
    "iso:country":"ES",
    "sg:address":"Cno. Obispo, 25",
    "sg:city":"Mostoles",
    "sg:orig_category":"Postigos, Persianas Y Celos\u00cdas",
    "sg:phone":"+34 916 16 61 02",
    "sg:postcode":"28935",
    "sg:province":"Madrid",
    "wof:name":"Alcaide Garcia Encarnacion",
    "wof:placetype":"venue"
},
  "geometry": {"coordinates":[-3.8946096897,40.3354949951],"type":"Point"}
}