{
  "type": "Feature",
  "properties": {
    "iso:country":"ES",
    "sg:address":"Calle de Real, 94",
    "sg:city":"Estepona",
    "sg:orig_category":"Florister\u00cdas",
    "sg:phone":"+34 952 80 13 89",
    "sg:postcode":"29680",
    "sg:province":"M\u00e1laga",
    "wof:name":"Dominguez Casado Maria Emilia",
    "wof:placetype":"venue"
},
  "geometry": {"coordinates":[-5.1448788643,36.4250411987],"type":"Point"}
}