{
  "type": "Feature",
  "properties": {
    "iso:country":"ES",
    "sg:address":"Calle de San Blas, 20",
    "sg:city":"Almendralejo",
    "sg:orig_category":"Molduras, Junquillos, Listones Y Molduras Perforadas",
    "sg:phone":"+34 924 66 71 55",
    "sg:postcode":"06200",
    "sg:province":"Badajoz",
    "wof:name":"Huerta-mar Cb",
    "wof:placetype":"venue"
},
  "geometry": {"coordinates":[-6.4132990837,38.6879653931],"type":"Point"}
}