{
  "type": "Feature",
  "properties": {
    "iso:country":"ES",
    "sg:address":"Calle de Santiago, 13",
    "sg:city":"Olivenza",
    "sg:orig_category":"Tapicer\u00cdas",
    "sg:phone":"+34 924 49 13 20",
    "sg:postcode":"06100",
    "sg:province":"Badajoz",
    "wof:name":"Martinez Correa Maria Dolores",
    "wof:placetype":"venue"
},
  "geometry": {"coordinates":[-7.1015238762,38.6864852905],"type":"Point"}
}