{
  "type": "Feature",
  "properties": {
    "addr:full":"Avda Hispanidade, 33 Vigo Pontevedra 36203",
    "addr:housenumber":"33",
    "addr:postcode":"36203",
    "addr:street":"Avda Hispanidade",
    "iso:country":"ES",
    "sg:address":"Avda Hispanidade, 33",
    "sg:city":"Vigo",
    "sg:orig_category":"Internados & Ense\u00d1anza Privada",
    "sg:phone":"+34 986 42 36 23",
    "sg:postcode":"36203",
    "sg:province":"Pontevedra",
    "wof:name":"Centro De Estudios Bancarios Economicos Y Mercantiles S.l.",
    "wof:placetype":"venue"
},
  "geometry": {"coordinates":[-8.728386879,42.2318229675],"type":"Point"}
}