{
  "type": "Feature",
  "properties": {
    "addr:full":"Rua Vista Alegre (de), 91 Santiago De Compostela La Coru\u00f1a 15705",
    "addr:housenumber":"91",
    "addr:postcode":"15705",
    "addr:street":"Rua Vista Alegre De;Corun\u0303A",
    "iso:country":"ES",
    "sg:address":"Rua Vista Alegre (de), 91",
    "sg:city":"Santiago De Compostela",
    "sg:orig_category":"Molduras, Junquillos, Listones Y Molduras Perforadas",
    "sg:phone":"+34 981 57 17 45",
    "sg:postcode":"15705",
    "sg:province":"La Coru\u00f1a",
    "wof:name":"Rial Nieto Antonio",
    "wof:placetype":"venue"
},
  "geometry": {"coordinates":[-8.5472412109,42.8900794983],"type":"Point"}
}