{
  "type": "Feature",
  "properties": {
    "addr:full":"Iglesia, 1 Santa Fe Granada 18320",
    "addr:housenumber":"1",
    "addr:postcode":"18320",
    "addr:street":"Iglesia;Fe",
    "iso:country":"ES",
    "sg:address":"Iglesia, 1",
    "sg:city":"Santa Fe",
    "sg:orig_category":"Asociaciones, Organismos Culturales Y Socioeducativos",
    "sg:phone":"+34 958 44 00 38",
    "sg:postcode":"18320",
    "sg:province":"Granada",
    "wof:name":"Circulo De La Union",
    "wof:placetype":"venue"
},
  "geometry": {"coordinates":[-3.7192680836,37.1897354126],"type":"Point"}
}