{
  "type": "Feature",
  "properties": {
    "iso:country":"ES",
    "sg:address":"Calle de Diego De Vergara, 49",
    "sg:city":"Malaga",
    "sg:orig_category":"Tapicer\u00cdas",
    "sg:phone":"+34 952 27 08 27",
    "sg:postcode":"29009",
    "sg:province":"M\u00e1laga",
    "wof:name":"Jimenez Pe\u00f1a Rafael",
    "wof:placetype":"venue"
},
  "geometry": {"coordinates":[-4.4343733788,36.7237434387],"type":"Point"}
}