{
  "type": "Feature",
  "properties": {
    "addr:full":"Estda. De Vigo, 41 Ourense Ourense 32001",
    "addr:housenumber":"41",
    "addr:postcode":"32001",
    "addr:street":"Vigo",
    "iso:country":"ES",
    "sg:address":"Estda. De Vigo, 41",
    "sg:city":"Ourense",
    "sg:orig_category":"Chapister\u00cda",
    "sg:phone":"+34 988 21 70 42",
    "sg:postcode":"32001",
    "sg:province":"Ourense",
    "wof:name":"Suministros J.a.novoa S.l.",
    "wof:placetype":"venue"
},
  "geometry": {"coordinates":[-7.8814702034,42.3738327026],"type":"Point"}
}