{
  "type": "Feature",
  "properties": {
    "addr:full":"Pol Ind Dehesa Boyal, S/n Pozoblanco C\u00f3rdoba 14400",
    "addr:housenumber":"s / n",
    "addr:postcode":"14400",
    "iso:country":"ES",
    "sg:address":"Pol Ind Dehesa Boyal, S/n",
    "sg:city":"Pozoblanco",
    "sg:orig_category":"Autob\u00das (explotaci\u00d3n Y Servicios De)",
    "sg:phone":"+34 957 77 14 04",
    "sg:postcode":"14400",
    "sg:province":"C\u00f3rdoba",
    "wof:name":"Autobuses Tirado S.l.",
    "wof:placetype":"venue"
},
  "geometry": {"coordinates":[-4.8492288589,38.3810462952],"type":"Point"}
}