{
  "type": "Feature",
  "properties": {
    "addr:full":"Avda Bellas Vistas, 7 Alcorcon Madrid 28925",
    "addr:housenumber":"7",
    "addr:postcode":"28925",
    "addr:street":"Avda Bellas Vistas",
    "iso:country":"ES",
    "sg:address":"Avda Bellas Vistas, 7",
    "sg:city":"Alcorcon",
    "sg:orig_category":"Inform\u00c1tica (estudios, Servicios, Asesor\u00cda, Formaci\u00d3n)",
    "sg:phone":"+34 916 10 60 30",
    "sg:postcode":"28925",
    "sg:province":"Madrid",
    "wof:name":"Hipercubbo S.l.",
    "wof:placetype":"venue"
},
  "geometry": {"coordinates":[-3.8179008961,40.3564605713],"type":"Point"}
}