{
  "type": "Feature",
  "properties": {
    "addr:full":"Calle de Doctor Miguel Rios Sarmiento, 1 Sevilla Sevilla 41020",
    "addr:housenumber":"1",
    "addr:postcode":"41020",
    "addr:street":"Calle De Doctor Miguel Rios Sarmiento",
    "iso:country":"ES",
    "sg:address":"Calle de Doctor Miguel Rios Sarmiento, 1",
    "sg:city":"Sevilla",
    "sg:orig_category":"Molduras, Junquillos, Listones Y Molduras Perforadas",
    "sg:phone":"+34 954 40 10 28",
    "sg:postcode":"41020",
    "sg:province":"Sevilla",
    "wof:name":"Solier Bellido Juan Luis",
    "wof:placetype":"venue"
},
  "geometry": {"coordinates":[-5.9295787811,37.396522522],"type":"Point"}
}