{
  "type": "Feature",
  "properties": {
    "addr:full":"Calle de Picadores, 50 Sevilla Sevilla 41007",
    "addr:housenumber":"50",
    "addr:postcode":"41007",
    "addr:street":"Calle De Picadores",
    "iso:country":"ES",
    "sg:address":"Calle de Picadores, 50",
    "sg:city":"Sevilla",
    "sg:orig_category":"Carnicer\u00cdas, Carnicer\u00cdas",
    "sg:phone":"+34 954 25 30 93",
    "sg:postcode":"41007",
    "sg:province":"Sevilla",
    "wof:name":"Arispon Baeza Antonio",
    "wof:placetype":"venue"
},
  "geometry": {"coordinates":[-5.9593896866,37.3986053467],"type":"Point"}
}