{
  "type": "Feature",
  "properties": {
    "addr:full":"Calle de San Jose De Calasanz, 4 Albacete Albacete 02002",
    "addr:housenumber":"4",
    "addr:postcode":"02002",
    "addr:street":"Calle De San;De Calasanz",
    "iso:country":"ES",
    "sg:address":"Calle de San Jose De Calasanz, 4",
    "sg:city":"Albacete",
    "sg:orig_category":"Ropa Para Se\u00d1oras (al Por Menor)",
    "sg:phone":"+34 967 50 96 42",
    "sg:postcode":"02002",
    "sg:province":"Albacete",
    "wof:name":"Manuela Atienzar Gonzalez S.l.",
    "wof:placetype":"venue"
},
  "geometry": {"coordinates":[-1.8559089899,38.9901351929],"type":"Point"}
}