{
  "type": "Feature",
  "properties": {
    "addr:full":"Carrer de Petritxol, 11 Barcelona Barcelona 08002",
    "addr:housenumber":"11",
    "addr:postcode":"08002",
    "addr:street":"Carrer De Petritxol",
    "iso:country":"ES",
    "sg:address":"Carrer de Petritxol, 11",
    "sg:city":"Barcelona",
    "sg:orig_category":"Panader\u00cdas, Panader\u00cdas",
    "sg:phone":"+34 933 01 11 97",
    "sg:postcode":"08002",
    "sg:province":"Barcelona",
    "wof:name":"Escursell S.l.",
    "wof:placetype":"venue"
},
  "geometry": {"coordinates":[2.1726820469,41.3828201294],"type":"Point"}
}