{
  "type": "Feature",
  "properties": {
    "addr:full":"Calle de Checa, 5 Zaragoza Zaragoza 50007",
    "addr:housenumber":"5",
    "addr:postcode":"50007",
    "addr:street":"Calle De Checa",
    "iso:country":"ES",
    "sg:address":"Calle de Checa, 5",
    "sg:city":"Zaragoza",
    "sg:orig_category":"Inmobiliaria (agencias)",
    "sg:phone":"+34 976 45 34 53",
    "sg:postcode":"50007",
    "sg:province":"Zaragoza",
    "wof:name":"Gesticom Fincas S.l.",
    "wof:placetype":"venue"
},
  "geometry": {"coordinates":[-0.8863077164,41.6320991516],"type":"Point"}
}