{
  "type": "Feature",
  "properties": {
    "iso:country":"ES",
    "sg:address":"Avda Paz (de La), 24",
    "sg:city":"Burgos",
    "sg:classifiers":[
        {
            "category":"Banks & Credit Unions",
            "subcategory":"Bureau De Change",
            "type":"Services"
        }
    ],
    "sg:phone":"+34 947 20 78 20",
    "sg:postcode":"09004",
    "sg:province":"Burgos",
    "sg:tags":[
        "organismos",
        "control"
    ],
    "wof:name":"Applus Norcontrol S.l.u.",
    "wof:placetype":"venue"
},
  "geometry": {"coordinates":[-3.6919496059,42.3451118469],"type":"Point"}
}