{
  "type": "Feature",
  "properties": {
    "addr:full":"Disseminats, S/n Fogars De La Selva Barcelona 08915",
    "addr:housenumber":"/ n",
    "addr:postcode":"08915",
    "addr:street":"Disseminats S",
    "iso:country":"ES",
    "sg:address":"Disseminats, S/n",
    "sg:city":"Fogars De La Selva",
    "sg:orig_category":"Bazares, Art\u00cdculos De Limpieza Y De Cocina (al Por Menor)",
    "sg:phone":"+34 972 86 41 83",
    "sg:postcode":"08915",
    "sg:province":"Barcelona",
    "wof:name":"Navarro Berenguer Emili",
    "wof:placetype":"venue"
},
  "geometry": {"coordinates":[2.2469730377,41.4632911682],"type":"Point"}
}