{
  "type": "Feature",
  "properties": {
    "iso:country":"ES",
    "sg:address":"Calle de Basotxiki, 7",
    "sg:city":"Donostia-san Sebastian",
    "sg:orig_category":"Peluqueros: De Se\u00d1oras",
    "sg:phone":"+34 943 29 22 16",
    "sg:postcode":"20015",
    "sg:province":"Guip\u00f9zcoa",
    "wof:name":"Kokomotz C.b.",
    "wof:placetype":"venue"
},
  "geometry": {"coordinates":[-1.9534392357,43.3155860901],"type":"Point"}
}