{
  "type": "Feature",
  "properties": {
    "iso:country":"ES",
    "sg:address":"Calle de Jose De Zarate Y Penichet, 11",
    "sg:city":"Santa Cruz De Tenerife",
    "sg:orig_category":"Inform\u00c1tica (estudios, Servicios, Asesor\u00cda, Formaci\u00d3n)",
    "sg:phone":"+34 922 29 67 38",
    "sg:postcode":"38001",
    "sg:province":"Santa Cruz De Tenerife",
    "wof:name":"X-info Servicios Integrados S.l",
    "wof:placetype":"venue"
},
  "geometry": {"coordinates":[-16.2434005737,28.47996521],"type":"Point"}
}