{
  "type": "Feature",
  "properties": {
    "iso:country":"ES",
    "sg:address":"Calle de Navas De Tolosa, 2",
    "sg:city":"Jaen",
    "sg:orig_category":"Centros De Coordinaci\u00d3n",
    "sg:phone":"+34 953 25 40 14",
    "sg:postcode":"23001",
    "sg:province":"Ja\u00e9n",
    "wof:name":"Marchal Escalona Maria Del Carmen",
    "wof:placetype":"venue"
},
  "geometry": {"coordinates":[-3.7871599197,37.7691001892],"type":"Point"}
}