{
  "type": "Feature",
  "properties": {
    "iso:country":"ES",
    "sg:address":"Kale Nagusia, 16",
    "sg:city":"Idiazabal",
    "sg:orig_category":"Pescader\u00cdas (al Por Menor)",
    "sg:phone":"+34 943 18 71 13",
    "sg:postcode":"20213",
    "sg:province":"Guip\u00f9zcoa",
    "wof:name":"Imaz Urrestarazu Pedro",
    "wof:placetype":"venue"
},
  "geometry": {"coordinates":[-2.2322790623,43.0144882202],"type":"Point"}
}