{
  "type": "Feature",
  "properties": {
    "addr:full":"Avda Alcalde Federico Molina, 52 Huelva Huelva 21006",
    "addr:housenumber":"52",
    "addr:postcode":"21006",
    "addr:street":"Avda Alcalde Federico Molina",
    "iso:country":"ES",
    "sg:address":"Avda Alcalde Federico Molina, 52",
    "sg:city":"Huelva",
    "sg:orig_category":"Mudanzas",
    "sg:phone":"+34 959 22 68 30",
    "sg:postcode":"21006",
    "sg:province":"Huelva",
    "wof:name":"Mora Carretero Ignacio",
    "wof:placetype":"venue"
},
  "geometry": {"coordinates":[-6.9329838753,37.2590179443],"type":"Point"}
}