{
  "type": "Feature",
  "properties": {
    "addr:full":"Calle de Fuenclara, 30 Villanueva Arzobispo Ja\u00e9n 23330",
    "addr:housenumber":"30",
    "addr:postcode":"23330",
    "addr:street":"Calle De Fuenclara",
    "iso:country":"ES",
    "sg:address":"Calle de Fuenclara, 30",
    "sg:city":"Villanueva Arzobispo",
    "sg:orig_category":"Institutos De Belleza",
    "sg:phone":"+34 953 45 17 78",
    "sg:postcode":"23330",
    "sg:province":"Ja\u00e9n",
    "wof:name":"Maigler Unguetti Irene",
    "wof:placetype":"venue"
},
  "geometry": {"coordinates":[-3.0081779957,38.166885376],"type":"Point"}
}