{
  "type": "Feature",
  "properties": {
    "iso:country":"ES",
    "sg:address":"Avda Republica Argentina, 12",
    "sg:city":"Miranda Ebro",
    "sg:orig_category":"Caf\u00c9s, Bares, Cervecer\u00cdas",
    "sg:phone":"+34 947 33 52 16",
    "sg:postcode":"09200",
    "sg:province":"Burgos",
    "wof:name":"Martinez Carballo Jose",
    "wof:placetype":"venue"
},
  "geometry": {"coordinates":[-2.9426939487,42.6842651367],"type":"Point"}
}