{
  "type": "Feature",
  "properties": {
    "addr:full":"Avda Estacion (de La), 23 Puente-genil C\u00f3rdoba 14500",
    "addr:housenumber":"23",
    "addr:postcode":"14500",
    "addr:street":"Avda Estacion De La;Co\u0301Rdoba",
    "iso:country":"ES",
    "sg:address":"Avda Estacion (de La), 23",
    "sg:city":"Puente-genil",
    "sg:orig_category":"Relojer\u00cda (al Por Menor, Reparaci\u00d3n)",
    "sg:phone":"+34 957 60 67 01",
    "sg:postcode":"14500",
    "sg:province":"C\u00f3rdoba",
    "wof:name":"Garcia Humanes Jose Antonio",
    "wof:placetype":"venue"
},
  "geometry": {"coordinates":[-4.7624788284,37.3934669495],"type":"Point"}
}