{
  "type": "Feature",
  "properties": {
    "iso:country":"ES",
    "sg:address":"Calle de Olivares, 35",
    "sg:city":"Zarza",
    "sg:orig_category":"Venta, Montaje De Neum\u00c1ticos",
    "sg:phone":"+34 924 36 61 17",
    "sg:postcode":"06830",
    "sg:province":"Badajoz",
    "wof:name":"Cerrato Ramos Domingo",
    "wof:placetype":"venue"
},
  "geometry": {"coordinates":[-6.2194190025,38.821018219],"type":"Point"}
}