{
  "type": "Feature",
  "properties": {
    "iso:country":"ES",
    "sg:address":"Ctra Huesca, Km. 0024,0",
    "sg:city":"Estacion Portazgo",
    "sg:orig_category":"Mec\u00c1nico Del Autom\u00d3vil",
    "sg:phone":"+34 976 68 11 25",
    "sg:postcode":"50800",
    "sg:province":"Zaragoza",
    "sg:website":"www.talleressanlicer.con",
    "wof:name":"Blasco Ligorred Antonio",
    "wof:placetype":"venue"
},
  "geometry": {"coordinates":[-0.7865840197,41.867225647],"type":"Point"}
}