{
  "type": "Feature",
  "properties": {
    "iso:country":"ES",
    "sg:address":"Calle de Joaquin Rodrigo, 3",
    "sg:city":"Barriada San Cristobal",
    "sg:orig_category":"Farmacias",
    "sg:phone":"+34 968 51 52 51",
    "sg:postcode":"30310",
    "sg:province":"Murcia",
    "wof:name":"Baraza Laliga Juan Carlos",
    "wof:placetype":"venue"
},
  "geometry": {"coordinates":[-1.0045729876,37.6469078064],"type":"Point"}
}