{
  "type": "Feature",
  "properties": {
    "addr:full":"Plaz Chirinos (de), 4 Cordoba C\u00f3rdoba 14001",
    "addr:postcode":"14001",
    "addr:street":"Plaz;Co\u0301Rdoba",
    "iso:country":"ES",
    "sg:address":"Plaz Chirinos (de), 4",
    "sg:city":"Cordoba",
    "sg:orig_category":"Abogados",
    "sg:phone":"+34 957 48 11 26",
    "sg:postcode":"14001",
    "sg:province":"C\u00f3rdoba",
    "wof:name":"Ruiz Alcaide Carlos Luis",
    "wof:placetype":"venue"
},
  "geometry": {"coordinates":[-4.7796669006,37.8870887756],"type":"Point"}
}