{
  "type": "Feature",
  "properties": {
    "iso:country":"ES",
    "sg:address":"Avda Ricardo Soriano, 1",
    "sg:city":"Marbella",
    "sg:orig_category":"Psic\u00d3logos",
    "sg:phone":"+34 952 77 70 94",
    "sg:postcode":"29600",
    "sg:province":"M\u00e1laga",
    "wof:name":"Lorenzo Segovia Francisco Jesus",
    "wof:placetype":"venue"
},
  "geometry": {"coordinates":[-4.8867440224,36.5092163086],"type":"Point"}
}