{
  "type": "Feature",
  "properties": {
    "addr:full":"Calle de Ca\u00d1averal, 72 Madrid Madrid 28029",
    "addr:housenumber":"72",
    "addr:postcode":"madrid;28029",
    "addr:street":"Calle De Can\u0303Averal",
    "iso:country":"ES",
    "sg:address":"Calle de Ca\u00d1averal, 72",
    "sg:city":"Madrid",
    "sg:orig_category":"Empresas De Carpinter\u00cda",
    "sg:phone":"+34 913 15 07 09",
    "sg:postcode":"28029",
    "sg:province":"Madrid",
    "wof:name":"Fernandez Martin Dario",
    "wof:placetype":"venue"
},
  "geometry": {"coordinates":[-3.6931037903,40.4692649841],"type":"Point"}
}