{
  "type": "Feature",
  "properties": {
    "addr:full":"Calle de Busto De Abajo, 3 Marin Pontevedra 36900",
    "addr:housenumber":"3",
    "addr:postcode":"36900",
    "addr:street":"Calle De Busto De Abajo",
    "iso:country":"ES",
    "sg:address":"Calle de Busto De Abajo, 3",
    "sg:city":"Marin",
    "sg:orig_category":"Peluquer\u00cdas, Peluquer\u00cda Mixta",
    "sg:phone":"+34 986 88 38 04",
    "sg:postcode":"36900",
    "sg:province":"Pontevedra",
    "wof:name":"Caama\u00f1o Agulla Ana Belen",
    "wof:placetype":"venue"
},
  "geometry": {"coordinates":[-8.7023887634,42.3905105591],"type":"Point"}
}