{
  "type": "Feature",
  "properties": {
    "iso:country":"ES",
    "sg:address":"Calle de Anzofe, 67",
    "sg:city":"Cruce De Arinaga",
    "sg:orig_category":"Mec\u00c1nico Del Autom\u00d3vil",
    "sg:phone":"+34 928 18 03 73",
    "sg:postcode":"35118",
    "sg:province":"Las Palmas",
    "wof:name":"Taller Mecanico Lorenzo S.l.",
    "wof:placetype":"venue"
},
  "geometry": {"coordinates":[-15.4256877899,27.8787155151],"type":"Point"}
}