{
  "type": "Feature",
  "properties": {
    "iso:country":"ES",
    "sg:address":"Rond Cortes De Aragon, S/n",
    "sg:city":"Almunia De Do\u00e7a Godina",
    "sg:orig_category":"Polideportivos",
    "sg:phone":"+34 976 60 06 61",
    "sg:postcode":"50100",
    "sg:province":"Zaragoza",
    "wof:name":"Patronato Municipal De Deportes Pabellon Polideportivo",
    "wof:placetype":"venue"
},
  "geometry": {"coordinates":[-1.376899004,41.4743843079],"type":"Point"}
}