{
  "type": "Feature",
  "properties": {
    "iso:country":"ES",
    "sg:address":"Calle de Alameda Del Cura, 1",
    "sg:city":"Ubrique",
    "sg:orig_category":"Asilos De Ancianos. Centros Privados",
    "sg:phone":"+34 956 46 17 78",
    "sg:postcode":"11600",
    "sg:province":"C\u00e1diz",
    "wof:name":"Asilo Nuestra Se\u00d1ora De Los Remedios",
    "wof:placetype":"venue"
},
  "geometry": {"coordinates":[-5.4484777451,36.6805458069],"type":"Point"}
}