{
  "type": "Feature",
  "properties": {
    "addr:full":"Carrer de Jurats, 8 Reus Tarragona 43205",
    "addr:housenumber":"8",
    "addr:postcode":"43205",
    "addr:street":"Carrer De Jurats",
    "iso:country":"ES",
    "sg:address":"Carrer de Jurats, 8",
    "sg:city":"Reus",
    "sg:orig_category":"Muebles, Minoristas",
    "sg:phone":"+34 977 31 05 35",
    "sg:postcode":"43205",
    "sg:province":"Tarragona",
    "wof:name":"Trillas Moragas Josefa",
    "wof:placetype":"venue"
},
  "geometry": {"coordinates":[1.1057130098,41.1524505615],"type":"Point"}
}