{
  "type": "Feature",
  "properties": {
    "iso:country":"ES",
    "sg:address":"Calle de San Marcos, 31",
    "sg:city":"Zarza",
    "sg:orig_category":"Material Y Herramientas Agr\u00cdcolas",
    "sg:phone":"+34 924 36 70 60",
    "sg:postcode":"06830",
    "sg:province":"Badajoz",
    "wof:name":"Domerida Asociados S.l.",
    "wof:placetype":"venue"
},
  "geometry": {"coordinates":[-6.2141609192,38.8212966919],"type":"Point"}
}