{
  "type": "Feature",
  "properties": {
    "addr:full":"Calle de Pintor Mendoza, 47 Valdepe\u00f1as Ciudad Real 13300",
    "addr:housenumber":"47",
    "addr:postcode":"13300",
    "addr:street":"Calle De Pintor Mendoza",
    "iso:country":"ES",
    "sg:address":"Calle de Pintor Mendoza, 47",
    "sg:city":"Valdepe\u00f1as",
    "sg:orig_category":"Edici\u00d3n De Diarios, Revistas, Boletines",
    "sg:phone":"+34 926 32 17 27",
    "sg:postcode":"13300",
    "sg:province":"Ciudad Real",
    "wof:name":"Entidad Publica Empresarial Diario Lanza",
    "wof:placetype":"venue"
},
  "geometry": {"coordinates":[-3.383548975,38.7614593506],"type":"Point"}
}