{
  "type": "Feature",
  "properties": {
    "iso:country":"ES",
    "sg:address":"Calle de Montevideo, 12",
    "sg:city":"Huelva",
    "sg:orig_category":"Estudios, Instalaci\u00d3n De Climatizaci\u00d3n",
    "sg:phone":"+34 959 15 11 44",
    "sg:postcode":"21005",
    "sg:province":"Huelva",
    "wof:name":"Instalaciones Suero Sl",
    "wof:placetype":"venue"
},
  "geometry": {"coordinates":[-6.9442691803,37.2835426331],"type":"Point"}
}