{
  "type": "Feature",
  "properties": {
    "addr:full":"Calle de Cristobal Colon, 40 Torredonjimeno Ja\u00e9n 23650",
    "addr:housenumber":"40",
    "addr:postcode":"23650",
    "addr:street":"Calle De Cristobal Colon",
    "iso:country":"ES",
    "sg:address":"Calle de Cristobal Colon, 40",
    "sg:city":"Torredonjimeno",
    "sg:orig_category":"Electricidad (montaje, Ensamblaje De Componentes)",
    "sg:phone":"+34 953 57 12 77",
    "sg:postcode":"23650",
    "sg:province":"Ja\u00e9n",
    "wof:name":"Parraga Valenzuela Antonio",
    "wof:placetype":"venue"
},
  "geometry": {"coordinates":[-3.9584434032,37.769077301],"type":"Point"}
}