{
  "type": "Feature",
  "properties": {
    "iso:country":"ES",
    "sg:address":"Calle de Pico Veleta, 34",
    "sg:city":"Elda",
    "sg:orig_category":"Zapatos: Material, Suministros, Accesorios (fabricaci\u00d3n, Al Por Mayor)",
    "sg:phone":"+34 965 39 35 73",
    "sg:postcode":"03600",
    "sg:province":"Alicante",
    "wof:name":"Comercial Hijos De Jose Luis Martinez S.l.",
    "wof:placetype":"venue"
},
  "geometry": {"coordinates":[-0.8007979989,38.4918479919],"type":"Point"}
}