{
  "type": "Feature",
  "properties": {
    "iso:country":"ES",
    "sg:address":"Calle de San Sebastian, 36",
    "sg:city":"Santa Cruz De Mudela",
    "sg:orig_category":"Asesor\u00cda Sobre Comunicaci\u00d3n De Empresas",
    "sg:phone":"+34 926 33 12 41",
    "sg:postcode":"13730",
    "sg:province":"Ciudad Real",
    "wof:name":"O.c.p.e. & Hampston S.l.",
    "wof:placetype":"venue"
},
  "geometry": {"coordinates":[-3.4628090858,38.642250061],"type":"Point"}
}