{
  "type": "Feature",
  "properties": {
    "iso:country":"ES",
    "sg:address":"Calle de Arechavaleta, 4",
    "sg:city":"Madrid",
    "sg:orig_category":"Prendas Y Chalecos De Punto (al Por Menor)",
    "sg:phone":"+34 917 95 18 05",
    "sg:postcode":"28041",
    "sg:province":"Madrid",
    "wof:name":"Sanchez Gonzalez Fernando",
    "wof:placetype":"venue"
},
  "geometry": {"coordinates":[-3.696539402,40.3510971069],"type":"Point"}
}