{
  "type": "Feature",
  "properties": {
    "addr:full":"Pase Miraconcha De, 16 Donostia-san Sebastian Guip\u00f9zcoa 20007",
    "addr:housenumber":"16",
    "addr:postcode":"20007",
    "iso:country":"ES",
    "sg:address":"Pase Miraconcha De, 16",
    "sg:city":"Donostia-san Sebastian",
    "sg:orig_category":"Supermercados Y Hipermercados",
    "sg:phone":"+34 943 47 12 34",
    "sg:postcode":"20007",
    "sg:province":"Guip\u00f9zcoa",
    "wof:name":"Aurole S.l.",
    "wof:placetype":"venue"
},
  "geometry": {"coordinates":[-2.0346250534,43.2695808411],"type":"Point"}
}