{
  "type": "Feature",
  "properties": {
    "addr:full":"Calle de Infantes, 12 Torre Mar M\u00e1laga 29740",
    "addr:housenumber":"12",
    "addr:postcode":"29740",
    "addr:street":"Calle De Infantes;Ma\u0301Laga",
    "iso:country":"ES",
    "sg:address":"Calle de Infantes, 12",
    "sg:city":"Torre Mar",
    "sg:orig_category":"Perfumer\u00cda (al Por Menor)",
    "sg:phone":"+34 952 54 35 42",
    "sg:postcode":"29740",
    "sg:province":"M\u00e1laga",
    "wof:name":"Ortega Lopez Jose",
    "wof:placetype":"venue"
},
  "geometry": {"coordinates":[-4.437048912,36.7014884949],"type":"Point"}
}