{
  "type": "Feature",
  "properties": {
    "addr:full":"Carr Bajoli, 20 Poima Islas Baleares 07714",
    "addr:housenumber":"20",
    "addr:postcode":"07714",
    "addr:street":"Carr Bajoli;Islas",
    "iso:country":"ES",
    "sg:address":"Carr Bajoli, 20",
    "sg:city":"Poima",
    "sg:orig_category":"Mensajer\u00cda Express, Portes Internacionales",
    "sg:phone":"+34 971 35 43 00",
    "sg:postcode":"07714",
    "sg:province":"Islas Baleares",
    "sg:website":"www.ochoa.es",
    "wof:name":"Transportes Ochoa S.a.",
    "wof:placetype":"venue"
},
  "geometry": {"coordinates":[2.9117100239,39.6136398315],"type":"Point"}
}