{
  "type": "Feature",
  "properties": {
    "iso:country":"ES",
    "sg:address":"Calle de Madrid, 11",
    "sg:city":"Torrejon Ardoz",
    "sg:orig_category":"Sales (al Por Mayor)",
    "sg:phone":"+34 916 76 04 18",
    "sg:postcode":"28850",
    "sg:province":"Madrid",
    "wof:name":"Sevillano Miguel Teodoro",
    "wof:placetype":"venue"
},
  "geometry": {"coordinates":[-3.4767858982,40.463092804],"type":"Point"}
}