{
  "type": "Feature",
  "properties": {
    "iso:country":"ES",
    "sg:address":"Calle de Jose Maria Iglesia, 11",
    "sg:city":"Arahal",
    "sg:orig_category":"Ingeniero",
    "sg:phone":"+34 955 84 21 83",
    "sg:postcode":"41600",
    "sg:province":"Sevilla",
    "wof:name":"Jimenez Bohorquez Rafael",
    "wof:placetype":"venue"
},
  "geometry": {"coordinates":[-5.5453448296,37.2601394653],"type":"Point"}
}