{
  "type": "Feature",
  "properties": {
    "addr:full":"Rond Iberica, 77 Vilanova I La Geltru Barcelona 08800",
    "addr:housenumber":"77",
    "addr:postcode":"08800",
    "addr:street":"Iberica",
    "iso:country":"ES",
    "sg:address":"Rond Iberica, 77",
    "sg:city":"Vilanova I La Geltru",
    "sg:orig_category":"Centros De Coordinaci\u00d3n",
    "sg:phone":"+34 938 11 51 36",
    "sg:postcode":"08800",
    "sg:province":"Barcelona",
    "wof:name":"Gestoria Matifoll S.l.u.",
    "wof:placetype":"venue"
},
  "geometry": {"coordinates":[1.7285159826,41.2303466797],"type":"Point"}
}