{
  "type": "Feature",
  "properties": {
    "addr:full":"Calle de Castilla, 31 Madrid Madrid 28039",
    "addr:housenumber":"31",
    "addr:postcode":"madrid;28039",
    "addr:street":"Calle De Castilla",
    "iso:country":"ES",
    "sg:address":"Calle de Castilla, 31",
    "sg:city":"Madrid",
    "sg:orig_category":"Empresarios",
    "sg:phone":"+34 913 11 75 95",
    "sg:postcode":"28039",
    "sg:province":"Madrid",
    "wof:name":"Fabiszewski Ochoa E Hijos S.l.",
    "wof:placetype":"venue"
},
  "geometry": {"coordinates":[-3.7066953182,40.4531784058],"type":"Point"}
}