{
  "type": "Feature",
  "properties": {
    "iso:country":"ES",
    "sg:address":"Calle de Princesa, 4",
    "sg:city":"Torre Mar",
    "sg:orig_category":"Hielo Artificial (fabricaci\u00d3n, Distribuci\u00d3n)",
    "sg:phone":"+34 952 54 09 62",
    "sg:postcode":"29740",
    "sg:province":"M\u00e1laga",
    "wof:name":"Diaz Pardo Adela",
    "wof:placetype":"venue"
},
  "geometry": {"coordinates":[-4.4362831116,36.7005691528],"type":"Point"}
}