{
  "type": "Feature",
  "properties": {
    "addr:full":"Calle de Bajada De San Jeronimo, 10 Sig\u00fcenza Guadalajara 19250",
    "addr:housenumber":"10",
    "addr:postcode":"19250",
    "addr:street":"Calle De Bajada De San Jeronimo",
    "iso:country":"ES",
    "sg:address":"Calle de Bajada De San Jeronimo, 10",
    "sg:city":"Sig\u00fcenza",
    "sg:orig_category":"Empresas De Carpinter\u00cda Met\u00c1lica",
    "sg:phone":"+34 949 39 30 08",
    "sg:postcode":"19250",
    "sg:province":"Guadalajara",
    "wof:name":"Azabal Sanz Juan Antonio",
    "wof:placetype":"venue"
},
  "geometry": {"coordinates":[-2.6441707611,41.0653419495],"type":"Point"}
}