{
  "type": "Feature",
  "properties": {
    "addr:full":"Calle de Marina, 30 Campamento C\u00e1diz 11314",
    "addr:housenumber":"30",
    "addr:postcode":"11314",
    "addr:street":"Calle De Marina;Ca\u0301Diz",
    "iso:country":"ES",
    "sg:address":"Calle de Marina, 30",
    "sg:city":"Campamento",
    "sg:orig_category":"Promotores Constructores",
    "sg:phone":"+34 956 69 82 88",
    "sg:postcode":"11314",
    "sg:province":"C\u00e1diz",
    "wof:name":"Consurle S. L.",
    "wof:placetype":"venue"
},
  "geometry": {"coordinates":[-5.3784689903,36.1770591736],"type":"Point"}
}