{
  "type": "Feature",
  "properties": {
    "iso:country":"ES",
    "sg:address":"Calle de Agirrelanda, 9",
    "sg:city":"Vitoria-gasteiz",
    "sg:orig_category":"Empresarios",
    "sg:phone":"+34 945 26 50 02",
    "sg:postcode":"01013",
    "sg:province":"\u00c1lava",
    "wof:name":"Saez De Lafuente Gochicoa Jose Ignacio",
    "wof:placetype":"venue"
},
  "geometry": {"coordinates":[-2.6753897667,42.8647041321],"type":"Point"}
}