{
  "type": "Feature",
  "properties": {
    "addr:full":"Carrer de Anselm Clave, 3 Mollet Valles Barcelona 08100",
    "addr:housenumber":"3",
    "addr:postcode":"08100",
    "addr:street":"Carrer De Anselm Clave",
    "iso:country":"ES",
    "sg:address":"Carrer de Anselm Clave, 3",
    "sg:city":"Mollet Valles",
    "sg:classifiers":[
        {
            "category":"Professional",
            "subcategory":"Management & Consulting",
            "type":"Services"
        }
    ],
    "sg:phone":"+34 935 93 33 98",
    "sg:postcode":"08100",
    "sg:province":"Barcelona",
    "sg:tags":[
        "asesor\u00cda",
        "en",
        "marketing"
    ],
    "wof:name":"Casale Marin Rosa Maria",
    "wof:placetype":"venue"
},
  "geometry": {"coordinates":[2.2138199806,41.5380249023],"type":"Point"}
}