{
  "type": "Feature",
  "properties": {
    "iso:country":"ES",
    "sg:address":"Calle de Mendez Nu\u00d1ez, 12",
    "sg:city":"Almeria",
    "sg:orig_category":"Ropa Para Ni\u00d1os (al Por Menor)",
    "sg:phone":"+34 950 23 77 75",
    "sg:postcode":"04001",
    "sg:province":"Almer\u00eda",
    "wof:name":"Gil Perez Carmen",
    "wof:placetype":"venue"
},
  "geometry": {"coordinates":[-2.4623789787,36.8386306763],"type":"Point"}
}