{
  "type": "Feature",
  "properties": {
    "iso:country":"ES",
    "sg:address":"Carrer de Santa Magdalena, 183",
    "sg:city":"S. Feliu Guixols",
    "sg:orig_category":"Carnicer\u00cdas, Carnicer\u00cdas",
    "sg:phone":"+34 972 32 00 68",
    "sg:postcode":"17220",
    "sg:province":"Girona",
    "wof:name":"Ayguaviva Y Mascu\u00f1an S.l.",
    "wof:placetype":"venue"
},
  "geometry": {"coordinates":[3.0259099007,41.7845916748],"type":"Point"}
}