{
  "type": "Feature",
  "properties": {
    "iso:country":"ES",
    "sg:address":"Calle de Trujillo, 6",
    "sg:city":"Burgos",
    "sg:orig_category":"Molduras, Junquillos, Listones Y Molduras Perforadas",
    "sg:phone":"+34 947 48 38 56",
    "sg:postcode":"09007",
    "sg:province":"Burgos",
    "wof:name":"Castrillo Saiz Ismael",
    "wof:placetype":"venue"
},
  "geometry": {"coordinates":[-3.6555190086,42.3627471924],"type":"Point"}
}