{
  "type": "Feature",
  "properties": {
    "addr:full":"Calle de Iliada, 21 Madrid Madrid 28022",
    "addr:housenumber":"21",
    "addr:postcode":"madrid;28022",
    "addr:street":"Calle De Iliada",
    "iso:country":"ES",
    "sg:address":"Calle de Iliada, 21",
    "sg:city":"Madrid",
    "sg:orig_category":"Reposter\u00cdas",
    "sg:phone":"+34 917 41 54 74",
    "sg:postcode":"28022",
    "sg:province":"Madrid",
    "wof:name":"Mu\u00f1oz Pavon Jose",
    "wof:placetype":"venue"
},
  "geometry": {"coordinates":[-3.6095120907,40.4354324341],"type":"Point"}
}