{
  "type": "Feature",
  "properties": {
    "iso:country":"ES",
    "sg:address":"Carrer de Major (sant Celoni), 97",
    "sg:city":"S. Celoni",
    "sg:orig_category":"Cajas De Ahorro",
    "sg:phone":"+34 938 67 47 72",
    "sg:postcode":"08470",
    "sg:province":"Barcelona",
    "sg:website":"www.caixapenedes.es",
    "wof:name":"Caixa D'estalvis Del Penedes",
    "wof:placetype":"venue"
},
  "geometry": {"coordinates":[2.4908330441,41.6897125244],"type":"Point"}
}