{
  "type": "Feature",
  "properties": {
    "iso:country":"ES",
    "sg:address":"Calle de Jose Mara\u00d1on, 7",
    "sg:city":"Madrid",
    "sg:orig_category":"Mec\u00c1nico Del Autom\u00d3vil",
    "sg:phone":"+34 915 93 48 37",
    "sg:postcode":"28010",
    "sg:province":"Madrid",
    "wof:name":"Duran Garcia Antonio",
    "wof:placetype":"venue"
},
  "geometry": {"coordinates":[-3.6978960037,40.4291877747],"type":"Point"}
}