{
  "type": "Feature",
  "properties": {
    "iso:country":"ES",
    "sg:address":"Av Francesc Cambo, 15",
    "sg:city":"Barcelona",
    "sg:orig_category":"Ropa Para Beb\u00c9s Y Ni\u00d1os (confecci\u00d3n, Al Por Mayor)",
    "sg:phone":"+34 933 19 55 09",
    "sg:postcode":"08003",
    "sg:province":"Barcelona",
    "wof:name":"Pascual Abad Luis",
    "wof:placetype":"venue"
},
  "geometry": {"coordinates":[2.1772360802,41.3860588074],"type":"Point"}
}