{
  "type": "Feature",
  "properties": {
    "iso:country":"ES",
    "sg:address":"Pg Fabra I Puig, 100",
    "sg:city":"Barcelona",
    "sg:orig_category":"Perfumer\u00cda (al Por Menor)",
    "sg:phone":"+34 933 12 09 08",
    "sg:postcode":"08030",
    "sg:province":"Barcelona",
    "wof:name":"Carpio Pedrosa Salud",
    "wof:placetype":"venue"
},
  "geometry": {"coordinates":[2.1844449043,41.4302864075],"type":"Point"}
}