{
  "type": "Feature",
  "properties": {
    "addr:full":"Calle de Perpetuo Socorro (del), 7 San Sebastian De Los Reyes Madrid 28700",
    "addr:housenumber":"7",
    "addr:postcode":"28700",
    "addr:street":"Calle De Perpetuo Socorro Del",
    "iso:country":"ES",
    "sg:address":"Calle de Perpetuo Socorro (del), 7",
    "sg:city":"San Sebastian De Los Reyes",
    "sg:orig_category":"Farmacias",
    "sg:phone":"+34 916 52 51 30",
    "sg:postcode":"28700",
    "sg:province":"Madrid",
    "wof:name":"Marcos Alcaide Antonio",
    "wof:placetype":"venue"
},
  "geometry": {"coordinates":[-3.6301860809,40.5466308594],"type":"Point"}
}