{
  "type": "Feature",
  "properties": {
    "addr:full":"Carr Regencia D'urgell, 11 Seu D'urgell Lleida 25700",
    "addr:housenumber":"11",
    "addr:postcode":"25700",
    "addr:street":"Carr Regencia D'Urgell",
    "iso:country":"ES",
    "sg:address":"Carr Regencia D'urgell, 11",
    "sg:city":"Seu D'urgell",
    "sg:orig_category":"Tapicer\u00cdas",
    "sg:phone":"+34 973 35 25 28",
    "sg:postcode":"25700",
    "sg:province":"Lleida",
    "wof:name":"Gomez Burgos Cristobal",
    "wof:placetype":"venue"
},
  "geometry": {"coordinates":[0.6457189918,41.6027946472],"type":"Point"}
}