{
  "type": "Feature",
  "properties": {
    "addr:full":"Carrer de Feder Garcia Lorca, 19 Palma Islas Baleares 07014",
    "addr:housenumber":"19",
    "addr:postcode":"07014",
    "addr:street":"Carrer De Feder Garcia Lorca",
    "iso:country":"ES",
    "sg:address":"Carrer de Feder Garcia Lorca, 19",
    "sg:city":"Palma",
    "sg:orig_category":"Ense\u00d1anza Variada",
    "sg:phone":"+34 971 45 36 37",
    "sg:postcode":"07014",
    "sg:province":"Islas Baleares",
    "wof:name":"Informacio I Orientacio D'estudi Cap A La Professio S.l.",
    "wof:placetype":"venue"
},
  "geometry": {"coordinates":[2.6278970242,39.5655899048],"type":"Point"}
}