{
  "type": "Feature",
  "properties": {
    "iso:country":"ES",
    "sg:address":"Carrer de Sau, 53",
    "sg:city":"Torre-romeu",
    "sg:orig_category":"Reposter\u00cdas",
    "sg:phone":"+34 937 27 07 51",
    "sg:postcode":"08202",
    "sg:province":"Barcelona",
    "wof:name":"Panificadora Valero S.a.",
    "wof:placetype":"venue"
},
  "geometry": {"coordinates":[2.1687450409,41.3855895996],"type":"Point"}
}