{
  "type": "Feature",
  "properties": {
    "iso:country":"ES",
    "sg:address":"Carrer de Manyans, 1",
    "sg:city":"Pedreguer",
    "sg:orig_category":"Ense\u00d1anza: Profesiones Art\u00cdsticas",
    "sg:phone":"+34 965 76 04 91",
    "sg:postcode":"03750",
    "sg:province":"Alicante",
    "wof:name":"Sivera Marti Serafin",
    "wof:placetype":"venue"
},
  "geometry": {"coordinates":[0.0336819999,38.7925376892],"type":"Point"}
}