{
  "type": "Feature",
  "properties": {
    "iso:country":"ES",
    "sg:address":"Carrer de Santa Margarida I Monjos, 4",
    "sg:city":"Vilafranca Penedes",
    "sg:orig_category":"Fabricaci\u00d3n De Distribuidores Autom\u00c1ticos",
    "sg:phone":"+34 938 17 04 34",
    "sg:postcode":"08720",
    "sg:province":"Barcelona",
    "wof:name":"Lacambra Latorre Jesus Alejandro",
    "wof:placetype":"venue"
},
  "geometry": {"coordinates":[1.6935030222,41.3425140381],"type":"Point"}
}