{
  "type": "Feature",
  "properties": {
    "iso:country":"ES",
    "sg:address":"Calle de Ciencias (de Las), 12",
    "sg:city":"Jerez De La Frontera",
    "sg:orig_category":"Andamiajes Y Escaleras De Mano (fabricaci\u00d3n, Al Por Mayor)",
    "sg:phone":"+34 956 31 77 77",
    "sg:postcode":"11407",
    "sg:province":"C\u00e1diz",
    "wof:name":"Oliva Alquileres S.l.",
    "wof:placetype":"venue"
},
  "geometry": {"coordinates":[-6.122844696,36.7068519592],"type":"Point"}
}