{
  "type": "Feature",
  "properties": {
    "iso:country":"ES",
    "sg:address":"Calle de San Pedro, 14",
    "sg:city":"Motilla Palancar",
    "sg:orig_category":"Peluqueros: De Se\u00d1oras",
    "sg:phone":"+34 969 33 11 19",
    "sg:postcode":"16200",
    "sg:province":"Cuenca",
    "wof:name":"Navalon Carretero Encarnacion",
    "wof:placetype":"venue"
},
  "geometry": {"coordinates":[-1.9128220081,39.5616188049],"type":"Point"}
}