{
  "type": "Feature",
  "properties": {
    "addr:full":"Calle de Pianista Amparo Iturbi, 49 Valencia Valencia 46006",
    "addr:housenumber":"49",
    "addr:postcode":"46006",
    "addr:street":"Calle De Pianista Amparo Iturbi",
    "iso:country":"ES",
    "sg:address":"Calle de Pianista Amparo Iturbi, 49",
    "sg:city":"Valencia",
    "sg:orig_category":"Ropa Para Se\u00d1oras (al Por Menor)",
    "sg:phone":"+34 963 73 02 84",
    "sg:postcode":"46006",
    "sg:province":"Valencia",
    "wof:name":"Perez Angel Rosario",
    "wof:placetype":"venue"
},
  "geometry": {"coordinates":[-0.3780190051,39.454158783],"type":"Point"}
}