{
  "type": "Feature",
  "properties": {
    "addr:full":"Avda. Andalucia, 4 Mengibar Ja\u00e9n 23620",
    "addr:housenumber":"4",
    "addr:postcode":"23620",
    "addr:street":"Avda. Andalucia;Jae\u0301N",
    "iso:country":"ES",
    "sg:address":"Avda. Andalucia, 4",
    "sg:city":"Mengibar",
    "sg:orig_category":"Alquiler De V\u00cddeo",
    "sg:phone":"+34 953 37 14 47",
    "sg:postcode":"23620",
    "sg:province":"Ja\u00e9n",
    "wof:name":"Grupo Hostelero Hollywood S.l",
    "wof:placetype":"venue"
},
  "geometry": {"coordinates":[-3.8140022755,37.969581604],"type":"Point"}
}