{
  "type": "Feature",
  "properties": {
    "iso:country":"ES",
    "sg:address":"Rond Guinardo, 200",
    "sg:city":"Barcelona",
    "sg:orig_category":"Molduras, Junquillos, Listones Y Molduras Perforadas",
    "sg:phone":"+34 934 55 61 03",
    "sg:postcode":"08041",
    "sg:province":"Barcelona",
    "wof:name":"Noverques Bono Vicente",
    "wof:placetype":"venue"
},
  "geometry": {"coordinates":[2.1773169041,41.4216384888],"type":"Point"}
}