{
  "type": "Feature",
  "properties": {
    "addr:full":"Calle de Tamaran, 2 Cruce De Arinaga Las Palmas 35118",
    "addr:housenumber":"2",
    "addr:postcode":"35118",
    "addr:street":"Calle De Tamaran",
    "iso:country":"ES",
    "sg:address":"Calle de Tamaran, 2",
    "sg:city":"Cruce De Arinaga",
    "sg:orig_category":"Molduras, Junquillos, Listones Y Molduras Perforadas",
    "sg:phone":"+34 928 18 16 34",
    "sg:postcode":"35118",
    "sg:province":"Las Palmas",
    "wof:name":"Ferora S.l.",
    "wof:placetype":"venue"
},
  "geometry": {"coordinates":[-15.4238557816,27.8813896179],"type":"Point"}
}