{
  "type": "Feature",
  "properties": {
    "addr:full":"Pla\u00c7 La Sardana (de), 7 Balaguer Lleida 25600",
    "addr:postcode":"25600",
    "iso:country":"ES",
    "sg:address":"Pla\u00c7 La Sardana (de), 7",
    "sg:city":"Balaguer",
    "sg:orig_category":"Electrodom\u00c9sticos (al Por Menor)",
    "sg:phone":"+34 973 44 57 16",
    "sg:postcode":"25600",
    "sg:province":"Lleida",
    "wof:name":"Solsona Ortiz Delfin",
    "wof:placetype":"venue"
},
  "geometry": {"coordinates":[0.8071600199,41.7896003723],"type":"Point"}
}