{
  "type": "Feature",
  "properties": {
    "addr:full":"Calle de Matas (las), 30 Galapagar Madrid 28260",
    "addr:housenumber":"30",
    "addr:postcode":"28260",
    "addr:street":"Calle De Matas Las",
    "iso:country":"ES",
    "sg:address":"Calle de Matas (las), 30",
    "sg:city":"Galapagar",
    "sg:orig_category":"Centros Empresariales",
    "sg:phone":"+34 918 56 93 94",
    "sg:postcode":"28260",
    "sg:province":"Madrid",
    "wof:name":"Vicerco S.l.",
    "wof:placetype":"venue"
},
  "geometry": {"coordinates":[-4.0019888878,40.5774116516],"type":"Point"}
}