{
  "type": "Feature",
  "properties": {
    "iso:country":"ES",
    "sg:address":"Carrer de Fontcoberta, 10",
    "sg:city":"Barcelona",
    "sg:orig_category":"Agricultores, Agricultores",
    "sg:phone":"+34 932 03 06 55",
    "sg:postcode":"08034",
    "sg:province":"Barcelona",
    "wof:name":"Riera Figueras Jose",
    "wof:placetype":"venue"
},
  "geometry": {"coordinates":[2.1224310398,41.396736145],"type":"Point"}
}