{
  "type": "Feature",
  "properties": {
    "addr:full":"Carrer de Barcelona, 7 S. Adria Besos Barcelona 08930",
    "addr:housenumber":"7",
    "addr:postcode":"08930",
    "addr:street":"Carrer De Barcelona;Barcelona",
    "iso:country":"ES",
    "sg:address":"Carrer de Barcelona, 7",
    "sg:city":"S. Adria Besos",
    "sg:orig_category":"Mec\u00c1nico Del Autom\u00d3vil",
    "sg:phone":"+34 933 81 49 04",
    "sg:postcode":"08930",
    "sg:province":"Barcelona",
    "wof:name":"Gonzalez Cuartielles Jorge",
    "wof:placetype":"venue"
},
  "geometry": {"coordinates":[2.2273340225,41.4261245728],"type":"Point"}
}