{
  "type": "Feature",
  "properties": {
    "iso:country":"ES",
    "sg:address":"Calle de Villafranqueza, 45",
    "sg:city":"San Vicente Del Raspeig-sant Vicent Del Raspeig",
    "sg:orig_category":"Comercio De Cuadros, L\u00c1minas Y Reproducciones De Obras De Arte",
    "sg:phone":"+34 965 66 71 82",
    "sg:postcode":"03690",
    "sg:province":"Alicante",
    "wof:name":"Corcoles Tierraseca Angel",
    "wof:placetype":"venue"
},
  "geometry": {"coordinates":[-0.515812993,38.3944854736],"type":"Point"}
}