{
  "type": "Feature",
  "properties": {
    "addr:full":"Calle de Capua, 29 Gijon Asturias 33202",
    "addr:housenumber":"29",
    "addr:postcode":"33202",
    "addr:street":"Calle De Capua",
    "iso:country":"ES",
    "sg:address":"Calle de Capua, 29",
    "sg:city":"Gijon",
    "sg:orig_category":"Grafistas",
    "sg:phone":"+34 985 14 38 92",
    "sg:postcode":"33202",
    "sg:province":"Asturias",
    "sg:website":"www.emedigital.com",
    "wof:name":"Eme Digital Sl",
    "wof:placetype":"venue"
},
  "geometry": {"coordinates":[-5.6580615044,43.5400733948],"type":"Point"}
}