{
  "type": "Feature",
  "properties": {
    "iso:country":"ES",
    "sg:address":"Calle de Molino, 17",
    "sg:city":"Utrera",
    "sg:orig_category":"Material Y Equipo Para Panader\u00cdas Y Pasteler\u00cdas",
    "sg:phone":"+34 954 86 47 51",
    "sg:postcode":"41710",
    "sg:province":"Sevilla",
    "wof:name":"Blanco Bruque Manuel",
    "wof:placetype":"venue"
},
  "geometry": {"coordinates":[-5.7769980431,37.1844749451],"type":"Point"}
}