{
  "type": "Feature",
  "properties": {
    "iso:country":"ES",
    "sg:address":"Carrer de Dalt, 3",
    "sg:city":"Parcent",
    "sg:orig_category":"Ense\u00d1anza, Formaci\u00d3n Profesional: Aprendizaje",
    "sg:phone":"+34 966 40 53 72",
    "sg:postcode":"03792",
    "sg:province":"Alicante",
    "wof:name":"Comunidad De Regantes Y Usuarios Vall Del Pop",
    "wof:placetype":"venue"
},
  "geometry": {"coordinates":[-0.0649989992,38.7453117371],"type":"Point"}
}