{
  "type": "Feature",
  "properties": {
    "iso:country":"ES",
    "sg:address":"Calle de Vicente Regueral, 44",
    "sg:city":"Pola De Lena",
    "sg:orig_category":"Alimentaci\u00d3n General (al Por Menor)",
    "sg:phone":"+34 985 49 28 48",
    "sg:postcode":"33630",
    "sg:province":"Asturias",
    "wof:name":"Zapico Lada Rebeca",
    "wof:placetype":"venue"
},
  "geometry": {"coordinates":[-5.8279461861,43.163684845],"type":"Point"}
}