{
  "type": "Feature",
  "properties": {
    "addr:full":"Pase Zorrilla, 94 Valladolid Valladolid 47006",
    "addr:housenumber":"94",
    "addr:postcode":"47006",
    "addr:street":"Zorrilla",
    "iso:country":"ES",
    "sg:address":"Pase Zorrilla, 94",
    "sg:city":"Valladolid",
    "sg:orig_category":"M\u00c9dicos: Foniatr\u00cda Y Logopedia",
    "sg:phone":"+34 983 23 65 84",
    "sg:postcode":"47006",
    "sg:province":"Valladolid",
    "wof:name":"Alvarez Alfageme Isabel",
    "wof:placetype":"venue"
},
  "geometry": {"coordinates":[-4.7382087708,41.6399421692],"type":"Point"}
}