{
  "type": "Feature",
  "properties": {
    "iso:country":"ES",
    "sg:address":"C/ Barcelona, 13",
    "sg:city":"Torre",
    "sg:orig_category":"Agencias Y Agentes Comerciales, Representantes",
    "sg:phone":"+34 971 42 93 67",
    "sg:postcode":"07609",
    "sg:province":"Islas Baleares",
    "wof:name":"Puigros Llull Jaime",
    "wof:placetype":"venue"
},
  "geometry": {"coordinates":[2.9117100239,39.6136398315],"type":"Point"}
}