{
  "type": "Feature",
  "properties": {
    "addr:full":"La Amistad, 15 Colonia Les Penyes Valencia 46185",
    "addr:housenumber":"15",
    "addr:postcode":"46185",
    "addr:street":"Amistad;Les",
    "iso:country":"ES",
    "sg:address":"La Amistad, 15",
    "sg:city":"Colonia Les Penyes",
    "sg:orig_category":"Inmobiliaria (agencias)",
    "sg:phone":"+34 962 76 18 29",
    "sg:postcode":"46185",
    "sg:province":"Valencia",
    "wof:name":"Roasego S.l.",
    "wof:placetype":"venue"
},
  "geometry": {"coordinates":[-0.5190089941,39.5869903564],"type":"Point"}
}