{
  "type": "Feature",
  "properties": {
    "iso:country":"ES",
    "sg:address":"Av Peguera, 49",
    "sg:city":"Peguera",
    "sg:orig_category":"Zapatos (al Por Menor)",
    "sg:phone":"+34 971 68 58 46",
    "sg:postcode":"07160",
    "sg:province":"Islas Baleares",
    "wof:name":"Martinez Egea Esther",
    "wof:placetype":"venue"
},
  "geometry": {"coordinates":[2.4521520138,39.5380058289],"type":"Point"}
}