{
  "type": "Feature",
  "properties": {
    "addr:full":"Calle de Maria Nicolasa, 11 Jerez De La Frontera C\u00e1diz 11401",
    "addr:housenumber":"11",
    "addr:postcode":"11401",
    "addr:street":"Calle De Maria Nicolasa",
    "iso:country":"ES",
    "sg:address":"Calle de Maria Nicolasa, 11",
    "sg:city":"Jerez De La Frontera",
    "sg:orig_category":"Alimentaci\u00d3n General (al Por Menor)",
    "sg:phone":"+34 956 14 06 78",
    "sg:postcode":"11401",
    "sg:province":"C\u00e1diz",
    "wof:name":"Moreno Alba Isabel Maria",
    "wof:placetype":"venue"
},
  "geometry": {"coordinates":[-6.1403617859,36.6778297424],"type":"Point"}
}