{
  "type": "Feature",
  "properties": {
    "iso:country":"ES",
    "sg:address":"Avda Vigo, 316",
    "sg:city":"Laredo",
    "sg:orig_category":"Alimentaci\u00d3n General (al Por Menor)",
    "sg:phone":"+34 986 45 05 58",
    "sg:postcode":"36320",
    "sg:province":"Pontevedra",
    "wof:name":"Perez Alvarez Jose Luis",
    "wof:placetype":"venue"
},
  "geometry": {"coordinates":[-8.6428003311,42.4304618835],"type":"Point"}
}