{
  "type": "Feature",
  "properties": {
    "addr:full":"Avda Faro (del), 4 Morro Jable Las Palmas 35625",
    "addr:housenumber":"4",
    "addr:postcode":"35625",
    "addr:street":"Avda Faro Del",
    "iso:country":"ES",
    "sg:address":"Avda Faro (del), 4",
    "sg:city":"Morro Jable",
    "sg:orig_category":"Alquiler De Apartamentos",
    "sg:phone":"+34 928 54 51 27",
    "sg:postcode":"35625",
    "sg:province":"Las Palmas",
    "wof:name":"Apartamentos Alberto S.l.",
    "wof:placetype":"venue"
},
  "geometry": {"coordinates":[-14.3536272049,28.0517253876],"type":"Point"}
}