{
  "type": "Feature",
  "properties": {
    "addr:full":"Calle de Santo Costado, 2 Jumilla Murcia 30520",
    "addr:housenumber":"2",
    "addr:postcode":"30520",
    "addr:street":"Calle De Santo Costado",
    "iso:country":"ES",
    "sg:address":"Calle de Santo Costado, 2",
    "sg:city":"Jumilla",
    "sg:orig_category":"Arquitectos",
    "sg:phone":"+34 968 78 00 08",
    "sg:postcode":"30520",
    "sg:province":"Murcia",
    "sg:website":"www.coamu.es/taj",
    "wof:name":"Taller De Arquitectura De Jumilla S.l.",
    "wof:placetype":"venue"
},
  "geometry": {"coordinates":[-1.3275910616,38.4721755981],"type":"Point"}
}