{
  "type": "Feature",
  "properties": {
    "iso:country":"ES",
    "sg:address":"Fila Berimerines(pol Ind), 7",
    "sg:city":"Alcoi",
    "sg:orig_category":"Fabricaci\u00d3n De Telas Y Sedas",
    "sg:phone":"+34 965 33 31 58",
    "sg:postcode":"03800",
    "sg:province":"Alicante",
    "wof:name":"Cotton Color Drap S.l.",
    "wof:placetype":"venue"
},
  "geometry": {"coordinates":[-0.4732739925,38.6984100342],"type":"Point"}
}