{
  "type": "Feature",
  "properties": {
    "addr:full":"Calle de Real, 71 Arganda Madrid 28500",
    "addr:housenumber":"71",
    "addr:postcode":"28500",
    "addr:street":"Calle De Real",
    "iso:country":"ES",
    "sg:address":"Calle de Real, 71",
    "sg:city":"Arganda",
    "sg:orig_category":"Papeler\u00cdas, Librer\u00cdas",
    "sg:phone":"+34 918 71 58 02",
    "sg:postcode":"28500",
    "sg:province":"Madrid",
    "wof:name":"Aguilar Garcia Maria Jose",
    "wof:placetype":"venue"
},
  "geometry": {"coordinates":[-3.434381485,40.2993927002],"type":"Point"}
}