{
  "type": "Feature",
  "properties": {
    "addr:full":"Calle de Manuel Machado, 25 Palacios Y Villafranca Sevilla 41720",
    "addr:housenumber":"25",
    "addr:postcode":"41720",
    "addr:street":"Calle De Manuel Machado",
    "iso:country":"ES",
    "sg:address":"Calle de Manuel Machado, 25",
    "sg:city":"Palacios Y Villafranca",
    "sg:orig_category":"Caf\u00c9s, Bares, Cervecer\u00cdas",
    "sg:phone":"+34 955 81 58 03",
    "sg:postcode":"41720",
    "sg:province":"Sevilla",
    "wof:name":"Garcia Lainez Joaquin",
    "wof:placetype":"venue"
},
  "geometry": {"coordinates":[-5.915749073,37.1614379883],"type":"Point"}
}