{
  "type": "Feature",
  "properties": {
    "addr:full":"Calle de Virgen Del Portillo, 29 Madrid Madrid 28027",
    "addr:housenumber":"29",
    "addr:postcode":"madrid;28027",
    "addr:street":"Calle De Virgen Del Portillo",
    "iso:country":"ES",
    "sg:address":"Calle de Virgen Del Portillo, 29",
    "sg:city":"Madrid",
    "sg:orig_category":"Confecci\u00d3n De Trajes Para Se\u00d1oras",
    "sg:phone":"+34 914 04 09 00",
    "sg:postcode":"28027",
    "sg:province":"Madrid",
    "wof:name":"Navazo Aguilera Herminio",
    "wof:placetype":"venue"
},
  "geometry": {"coordinates":[-3.6498599052,40.4381790161],"type":"Point"}
}