{
  "type": "Feature",
  "properties": {
    "addr:full":"Calle de Vizcaya, S/n Palencia Palencia 34003",
    "addr:housenumber":"s / n",
    "addr:postcode":"34003",
    "addr:street":"Calle De Vizcaya",
    "iso:country":"ES",
    "sg:address":"Calle de Vizcaya, S/n",
    "sg:city":"Palencia",
    "sg:orig_category":"Comercio De Piezas De Recambio Y De Accesorios De Veh\u00cdculos, Veh\u00cdculos Industriales",
    "sg:phone":"+34 979 72 17 85",
    "sg:postcode":"34003",
    "sg:province":"Palencia",
    "wof:name":"Rebolledo Calvo Valentin",
    "wof:placetype":"venue"
},
  "geometry": {"coordinates":[-4.5160989761,42.0025482178],"type":"Point"}
}