{
  "type": "Feature",
  "properties": {
    "iso:country":"ES",
    "sg:address":"Calle de Pio Xii, 26",
    "sg:city":"Santiago El Mayor",
    "sg:orig_category":"Bisuter\u00cda, Joyer\u00cda, Relojer\u00cda (al Por Menor)",
    "sg:phone":"+34 968 34 39 40",
    "sg:postcode":"30012",
    "sg:province":"Murcia",
    "wof:name":"Sanchez Canovas Jose Luis",
    "wof:placetype":"venue"
},
  "geometry": {"coordinates":[-1.1228029728,37.9725875854],"type":"Point"}
}