{
  "type": "Feature",
  "properties": {
    "addr:full":"Calle de Modesto Lafuente, 46 Madrid Madrid 28003",
    "addr:housenumber":"46",
    "addr:postcode":"madrid;28003",
    "addr:street":"Calle De Modesto Lafuente",
    "iso:country":"ES",
    "sg:address":"Calle de Modesto Lafuente, 46",
    "sg:city":"Madrid",
    "sg:orig_category":"M\u00c9dicos: Cirug\u00cda Pl\u00c1stica, Reconstructiva Y Est\u00c9tica",
    "sg:phone":"+34 915 53 34 63",
    "sg:postcode":"28003",
    "sg:province":"Madrid",
    "sg:website":"www.salus-center.com",
    "wof:name":"Salus Center Europa S.l.",
    "wof:placetype":"venue"
},
  "geometry": {"coordinates":[-3.6958780289,40.4411392212],"type":"Point"}
}