{
  "type": "Feature",
  "properties": {
    "addr:full":"Calle de Andalucia, 2 Kukullaga Vizcaya 48450",
    "addr:housenumber":"2",
    "addr:postcode":"48450",
    "addr:street":"Calle De Andalucia",
    "iso:country":"ES",
    "sg:address":"Calle de Andalucia, 2",
    "sg:city":"Kukullaga",
    "sg:classifiers":[
        {
            "category":"Personal",
            "subcategory":"Barber",
            "type":"Services"
        }
    ],
    "sg:phone":"+34 944 26 94 94",
    "sg:postcode":"48450",
    "sg:province":"Vizcaya",
    "sg:tags":[
        "caballeros",
        "de",
        "peluqueros"
    ],
    "wof:name":"Laguna Baca Vanesa",
    "wof:placetype":"venue"
},
  "geometry": {"coordinates":[-2.8839957714,43.2521095276],"type":"Point"}
}