{
  "type": "Feature",
  "properties": {
    "addr:full":"Calle de Salvador Allende, 5 Vall D'uixo Castell\u00f3n 12600",
    "addr:housenumber":"5",
    "addr:postcode":"12600",
    "addr:street":"Calle De Salvador Allende",
    "iso:country":"ES",
    "sg:address":"Calle de Salvador Allende, 5",
    "sg:city":"Vall D'uixo",
    "sg:orig_category":"Reposter\u00cdas",
    "sg:phone":"+34 964 66 53 93",
    "sg:postcode":"12600",
    "sg:province":"Castell\u00f3n",
    "wof:name":"Sanz Sancho Enrique",
    "wof:placetype":"venue"
},
  "geometry": {"coordinates":[-0.0482099988,39.992477417],"type":"Point"}
}