{
  "type": "Feature",
  "properties": {
    "addr:full":"Calle de Segura, 4 Carmona Sevilla 41410",
    "addr:housenumber":"4",
    "addr:postcode":"41410",
    "addr:street":"Calle De Segura",
    "iso:country":"ES",
    "sg:address":"Calle de Segura, 4",
    "sg:city":"Carmona",
    "sg:orig_category":"Carnicer\u00cdas, Carnicer\u00cdas",
    "sg:phone":"+34 954 14 19 64",
    "sg:postcode":"41410",
    "sg:province":"Sevilla",
    "wof:name":"Narvaez Garrido Francisco",
    "wof:placetype":"venue"
},
  "geometry": {"coordinates":[-5.6484303474,37.4746208191],"type":"Point"}
}