{
  "type": "Feature",
  "properties": {
    "iso:country":"ES",
    "sg:address":"Calle de Macarena (de La), 31",
    "sg:city":"Parla",
    "sg:orig_category":"Agentes De Seguros",
    "sg:phone":"+34 916 98 04 02",
    "sg:postcode":"28980",
    "sg:province":"Madrid",
    "wof:name":"Piqueras-matey Correduria De Seguros",
    "wof:placetype":"venue"
},
  "geometry": {"coordinates":[-3.7652258873,40.2368431091],"type":"Point"}
}