{
  "type": "Feature",
  "properties": {
    "addr:full":"Carrer de Gaspar Fabregas, 23 Esplugues Llobregat Barcelona 08950",
    "addr:housenumber":"23",
    "addr:postcode":"08950",
    "addr:street":"Carrer De Gaspar Fabregas",
    "iso:country":"ES",
    "sg:address":"Carrer de Gaspar Fabregas, 23",
    "sg:city":"Esplugues Llobregat",
    "sg:orig_category":"Empresas De Carpinter\u00cda De Madera",
    "sg:phone":"+34 933 71 95 19",
    "sg:postcode":"08950",
    "sg:province":"Barcelona",
    "wof:name":"Mayor Calvo Jose",
    "wof:placetype":"venue"
},
  "geometry": {"coordinates":[2.0816888809,41.3751106262],"type":"Point"}
}