{
  "type": "Feature",
  "properties": {
    "addr:full":"Ctra Taiala, 50 Girona Girona 17007",
    "addr:housenumber":"50",
    "addr:postcode":"17007",
    "addr:street":"Ctra Taiala",
    "iso:country":"ES",
    "sg:address":"Ctra Taiala, 50",
    "sg:city":"Girona",
    "sg:orig_category":"Confiter\u00cdas, Chocolater\u00cdas (al Por Menor)",
    "sg:phone":"+34 972 22 49 04",
    "sg:postcode":"17007",
    "sg:province":"Girona",
    "wof:name":"Espa\u00f1a Ortega Encarna",
    "wof:placetype":"venue"
},
  "geometry": {"coordinates":[2.8055810928,41.9943847656],"type":"Point"}
}