{
  "type": "Feature",
  "properties": {
    "iso:country":"ES",
    "sg:address":"Calle de San Elias, 52",
    "sg:city":"Onda",
    "sg:orig_category":"Agentes Generales De Seguros",
    "sg:phone":"+34 964 60 46 28",
    "sg:postcode":"12200",
    "sg:province":"Castell\u00f3n",
    "wof:name":"Carrasco Lozano Juan Jose",
    "wof:placetype":"venue"
},
  "geometry": {"coordinates":[-0.2668350041,39.961265564],"type":"Point"}
}