{
  "type": "Feature",
  "properties": {
    "addr:full":"Av Josep Tarradellas I Joan, 205 Hospitalet Llobregat Barcelona 08901",
    "addr:housenumber":"205",
    "addr:postcode":"08901",
    "addr:street":"Av Josep Tarradellas I Joan",
    "iso:country":"ES",
    "sg:address":"Av Josep Tarradellas I Joan, 205",
    "sg:city":"Hospitalet Llobregat",
    "sg:orig_category":"Guarder\u00cdas",
    "sg:phone":"+34 933 38 60 60",
    "sg:postcode":"08901",
    "sg:province":"Barcelona",
    "wof:name":"Academia Alpes S.l.",
    "wof:placetype":"venue"
},
  "geometry": {"coordinates":[2.098847,41.363422],"type":"Point"}
}