{
  "type": "Feature",
  "properties": {
    "addr:full":"Carr Doctor Subiros, 24 Limits Girona 17709",
    "addr:housenumber":"24",
    "addr:postcode":"17709",
    "addr:street":"Carr Doctor Subiros",
    "iso:country":"ES",
    "sg:address":"Carr Doctor Subiros, 24",
    "sg:city":"Limits",
    "sg:orig_category":"Confecci\u00d3n (fabricaci\u00d3n, Al Por Mayor)",
    "sg:phone":"+34 972 55 56 87",
    "sg:postcode":"17709",
    "sg:province":"Girona",
    "wof:name":"Jordi 24 S.l.",
    "wof:placetype":"venue"
},
  "geometry": {"coordinates":[2.8643319607,42.4608459473],"type":"Point"}
}