{
  "type": "Feature",
  "properties": {
    "iso:country":"ES",
    "sg:address":"Calle de Capitan Vigueras, 1",
    "sg:city":"Sevilla",
    "sg:orig_category":"Asociaciones, Organismos Culturales Y Socioeducativos",
    "sg:phone":"+34 954 53 31 94",
    "sg:postcode":"41004",
    "sg:province":"Sevilla",
    "wof:name":"Fundacion Formacion Y Empleo De Andalucia",
    "wof:placetype":"venue"
},
  "geometry": {"coordinates":[-5.9867224693,37.3828392029],"type":"Point"}
}