{
  "type": "Feature",
  "properties": {
    "iso:country":"ES",
    "sg:address":"Via Hispanidad, 37",
    "sg:city":"Zaragoza",
    "sg:orig_category":"Centros De Coordinaci\u00d3n",
    "sg:phone":"+34 976 75 81 29",
    "sg:postcode":"50012",
    "sg:province":"Zaragoza",
    "wof:name":"Trafic Consulting S.l.",
    "wof:placetype":"venue"
},
  "geometry": {"coordinates":[-0.918325007,41.6480789185],"type":"Point"}
}