{
  "type": "Feature",
  "properties": {
    "iso:country":"ES",
    "sg:address":"Marnela-pant\u00edn, S/n",
    "sg:city":"Atios",
    "sg:orig_category":"Arquitectos",
    "sg:phone":"+34 981 48 62 60",
    "sg:postcode":"15552",
    "sg:province":"La Coru\u00f1a",
    "wof:name":"Ramos Fraga Maria Jose",
    "wof:placetype":"venue"
},
  "geometry": {"coordinates":[-8.1421136856,43.6080055237],"type":"Point"}
}