{
  "type": "Feature",
  "properties": {
    "iso:country":"ES",
    "sg:address":"Calle de Olmo, 3",
    "sg:city":"Puebla Alfinden",
    "sg:orig_category":"Empresas De Carpinter\u00cda De Madera",
    "sg:phone":"+34 976 10 73 03",
    "sg:postcode":"50171",
    "sg:province":"Zaragoza",
    "sg:website":"www.joserutia.com",
    "wof:name":"Carpinteria Jose Rutia S.l.",
    "wof:placetype":"venue"
},
  "geometry": {"coordinates":[-0.7660539746,41.6409492493],"type":"Point"}
}