{
  "type": "Feature",
  "properties": {
    "iso:country":"ES",
    "sg:address":"Carrer de Sant Benilde, 1",
    "sg:city":"Zona Eixample",
    "sg:orig_category":"Institutos De Belleza",
    "sg:phone":"+34 977 54 92 00",
    "sg:postcode":"43006",
    "sg:province":"Tarragona",
    "wof:name":"Gonzalez Martinez Maria Jose",
    "wof:placetype":"venue"
},
  "geometry": {"coordinates":[1.215921998,41.1208534241],"type":"Point"}
}