{
  "type": "Feature",
  "properties": {
    "iso:country":"ES",
    "sg:address":"Mercado Sansomendi, S/n",
    "sg:city":"Vitoria-gasteiz",
    "sg:orig_category":"Frutas, Legumbres Frescas Y Tempranas (al Por Menor)",
    "sg:phone":"+34 945 22 84 88",
    "sg:postcode":"01010",
    "sg:province":"\u00c1lava",
    "wof:name":"Alonso Garcia Maria Del Pilar",
    "wof:placetype":"venue"
},
  "geometry": {"coordinates":[-2.7033574581,42.8563346863],"type":"Point"}
}