{
  "type": "Feature",
  "properties": {
    "iso:country":"ES",
    "sg:address":"Calle de Hileras, 1",
    "sg:city":"Carmena",
    "sg:orig_category":"Asilos De Ancianos. Centros Privados",
    "sg:phone":"+34 925 74 20 59",
    "sg:postcode":"45531",
    "sg:province":"Toledo",
    "wof:name":"Asociacion Hogar De Pensionistas Y Jubilados La Paz",
    "wof:placetype":"venue"
},
  "geometry": {"coordinates":[-4.4019346237,39.9578018188],"type":"Point"}
}