{
  "type": "Feature",
  "properties": {
    "addr:full":"Calle de Manuel Blasco, 4 Soria Soria 42004",
    "addr:housenumber":"4",
    "addr:postcode":"42004",
    "addr:street":"Calle De Manuel Blasco",
    "iso:country":"ES",
    "sg:address":"Calle de Manuel Blasco, 4",
    "sg:city":"Soria",
    "sg:classifiers":[
        {
            "category":"Taxi",
            "type":"Transportation"
        }
    ],
    "sg:phone":"+34 975 22 47 80",
    "sg:postcode":"42004",
    "sg:province":"Soria",
    "wof:name":"Jimenez Stoduto Francisco",
    "wof:placetype":"venue"
},
  "geometry": {"coordinates":[-2.4728910923,41.7605857849],"type":"Point"}
}