{
  "type": "Feature",
  "properties": {
    "addr:full":"Avda Profesor Peraza De Ayala, 8 Santa Cruz De Tenerife Santa Cruz De Tenerife 38001",
    "addr:housenumber":"8",
    "addr:postcode":"38001",
    "addr:street":"Avda Profesor Peraza De Ayala",
    "iso:country":"ES",
    "sg:address":"Avda Profesor Peraza De Ayala, 8",
    "sg:city":"Santa Cruz De Tenerife",
    "sg:orig_category":"Arquitectos",
    "sg:phone":"+34 922 29 19 59",
    "sg:postcode":"38001",
    "sg:province":"Santa Cruz De Tenerife",
    "wof:name":"Gonzalez De Chaves Calamita Francisco Jose",
    "wof:placetype":"venue"
},
  "geometry": {"coordinates":[-16.2538375854,28.4946174622],"type":"Point"}
}