{
  "type": "Feature",
  "properties": {
    "addr:full":"Calle de Gallegos, 25 Tarazona Mancha Albacete 02100",
    "addr:housenumber":"25",
    "addr:postcode":"02100",
    "addr:street":"Calle De Gallegos",
    "iso:country":"ES",
    "sg:address":"Calle de Gallegos, 25",
    "sg:city":"Tarazona Mancha",
    "sg:orig_category":"Iglesia Cat\u00d3lica",
    "sg:phone":"+34 967 48 00 46",
    "sg:postcode":"02100",
    "sg:province":"Albacete",
    "wof:name":"Parroquia De San Bartolome Apostol",
    "wof:placetype":"venue"
},
  "geometry": {"coordinates":[-1.9117590189,39.2636909485],"type":"Point"}
}