{
  "type": "Feature",
  "properties": {
    "iso:country":"ES",
    "sg:address":"Carrer de Arago, 335",
    "sg:city":"Barcelona",
    "sg:orig_category":"Asesor\u00cda Fiscal Y Jur\u00cddica",
    "sg:phone":"+34 934 59 20 89",
    "sg:postcode":"08009",
    "sg:province":"Barcelona",
    "wof:name":"S.j.gestio I Administracio",
    "wof:placetype":"venue"
},
  "geometry": {"coordinates":[2.1704831123,41.3965682983],"type":"Point"}
}