{
  "type": "Feature",
  "properties": {
    "iso:country":"ES",
    "sg:address":"Avda Santiago, S/n",
    "sg:city":"Negreira",
    "sg:orig_category":"Venta, Montaje De Neum\u00c1ticos",
    "sg:phone":"+34 981 88 54 01",
    "sg:postcode":"15830",
    "sg:province":"La Coru\u00f1a",
    "wof:name":"Neumaticos Negreira Sc",
    "wof:placetype":"venue"
},
  "geometry": {"coordinates":[-8.724609375,42.9113388062],"type":"Point"}
}