{
  "type": "Feature",
  "properties": {
    "addr:full":"Calle de Doctor Mu\u00d1oz, S/n Cazorla Ja\u00e9n 23470",
    "addr:housenumber":"s / n",
    "addr:postcode":"23470",
    "addr:street":"Calle De Doctor Mun\u0303Oz",
    "iso:country":"ES",
    "sg:address":"Calle de Doctor Mu\u00d1oz, S/n",
    "sg:city":"Cazorla",
    "sg:orig_category":"Hoteles",
    "sg:phone":"+34 953 71 05 29",
    "sg:postcode":"23470",
    "sg:province":"Ja\u00e9n",
    "wof:name":"Eurotel-sur S.l.",
    "wof:placetype":"venue"
},
  "geometry": {"coordinates":[-3.0027930737,37.9118499756],"type":"Point"}
}