{
  "type": "Feature",
  "properties": {
    "addr:full":"Carrer de Anselm Clave, 6 S. Celoni Barcelona 08470",
    "addr:housenumber":"6",
    "addr:postcode":"08470",
    "addr:street":"Carrer De Anselm Clave",
    "iso:country":"ES",
    "sg:address":"Carrer de Anselm Clave, 6",
    "sg:city":"S. Celoni",
    "sg:orig_category":"Bisuter\u00cda, Joyer\u00cda, Relojer\u00cda (al Por Menor)",
    "sg:phone":"+34 938 67 46 75",
    "sg:postcode":"08470",
    "sg:province":"Barcelona",
    "wof:name":"Ramos Aguila Maria",
    "wof:placetype":"venue"
},
  "geometry": {"coordinates":[2.4920840263,41.6905899048],"type":"Point"}
}