{
  "type": "Feature",
  "properties": {
    "addr:full":"El Islote, 88 S. Bartolome Las Palmas 35550",
    "addr:housenumber":"88",
    "addr:postcode":"35550",
    "addr:street":"El Islote;S. Bartolome Las",
    "iso:country":"ES",
    "sg:address":"El Islote, 88",
    "sg:city":"S. Bartolome",
    "sg:orig_category":"Agricultores, Agricultores",
    "sg:phone":"+34 928 52 21 16",
    "sg:postcode":"35550",
    "sg:province":"Las Palmas",
    "wof:name":"Martel Lopez Antonio Lorenzo",
    "wof:placetype":"venue"
},
  "geometry": {"coordinates":[-13.6098937988,29.0045204163],"type":"Point"}
}