{
  "type": "Feature",
  "properties": {
    "iso:country":"ES",
    "sg:address":"Carrer de Sofre (del), S/n",
    "sg:city":"Floresta",
    "sg:orig_category":"Diarios, Revistas Y Boletines (suscripciones)",
    "sg:phone":"+34 977 55 25 75",
    "sg:postcode":"43006",
    "sg:province":"Tarragona",
    "wof:name":"Distribuciones Tarraconenses De Publicaciones S.l.",
    "wof:placetype":"venue"
},
  "geometry": {"coordinates":[1.2209249735,41.1154441833],"type":"Point"}
}