{
  "type": "Feature",
  "properties": {
    "addr:full":"Carrer de Liuva, 67 Barcelona Barcelona 08030",
    "addr:housenumber":"67",
    "addr:postcode":"08030",
    "addr:street":"Carrer De Liuva",
    "iso:country":"ES",
    "sg:address":"Carrer de Liuva, 67",
    "sg:city":"Barcelona",
    "sg:orig_category":"Ropa Para Beb\u00c9s Y Ni\u00d1os (confecci\u00d3n, Al Por Mayor)",
    "sg:phone":"+34 933 46 83 53",
    "sg:postcode":"08030",
    "sg:province":"Barcelona",
    "wof:name":"Piscis Confecciones S.l.",
    "wof:placetype":"venue"
},
  "geometry": {"coordinates":[2.1940720081,41.4314842224],"type":"Point"}
}