{
  "type": "Feature",
  "properties": {
    "addr:full":"Carrer de Diputacio, 280 Barcelona Barcelona 08009",
    "addr:housenumber":"280",
    "addr:postcode":"08009",
    "addr:street":"Carrer De Diputacio",
    "iso:country":"ES",
    "sg:address":"Carrer de Diputacio, 280",
    "sg:city":"Barcelona",
    "sg:orig_category":"Agencias Y Asesores De Publicidad",
    "sg:phone":"+34 932 01 20 77",
    "sg:postcode":"08009",
    "sg:province":"Barcelona",
    "wof:name":"Circulo De Comunicacion S. A.",
    "wof:placetype":"venue"
},
  "geometry": {"coordinates":[2.1694409847,41.3920173645],"type":"Point"}
}