{
  "type": "Feature",
  "properties": {
    "iso:country":"ES",
    "sg:address":"Avda Constitucion, 9",
    "sg:city":"Alcazar S. Juan",
    "sg:orig_category":"Farmacias",
    "sg:phone":"+34 926 54 65 37",
    "sg:postcode":"13600",
    "sg:province":"Ciudad Real",
    "wof:name":"Perucho Lizcano Mercedes",
    "wof:placetype":"venue"
},
  "geometry": {"coordinates":[-3.2190089226,39.392906189],"type":"Point"}
}