{
  "type": "Feature",
  "properties": {
    "addr:full":"Avda San Rogelio, 22 Illora Granada 18260",
    "addr:housenumber":"22",
    "addr:postcode":"18260",
    "addr:street":"Avda San Rogelio",
    "iso:country":"ES",
    "sg:address":"Avda San Rogelio, 22",
    "sg:city":"Illora",
    "sg:orig_category":"Aguas (distribuci\u00d3n, Servicios)",
    "sg:phone":"+34 958 43 39 13",
    "sg:postcode":"18260",
    "sg:province":"Granada",
    "wof:name":"Gestion Y Tecnicas Del Agua S.a.",
    "wof:placetype":"venue"
},
  "geometry": {"coordinates":[-3.8776841164,37.2880020142],"type":"Point"}
}