{
  "type": "Feature",
  "properties": {
    "iso:country":"ES",
    "sg:address":"Avgd Pais Valencia, 21",
    "sg:city":"Paterna",
    "sg:orig_category":"Notarios",
    "sg:phone":"+34 961 38 57 11",
    "sg:postcode":"46980",
    "sg:province":"Valencia",
    "wof:name":"Guardo Santamaria Angel",
    "wof:placetype":"venue"
},
  "geometry": {"coordinates":[-0.4368756115,39.4998245239],"type":"Point"}
}