{
  "type": "Feature",
  "properties": {
    "iso:country":"ES",
    "sg:address":"Calle de Mendez Cabezola, 15",
    "sg:city":"Santa Cruz Palma",
    "sg:orig_category":"Contables",
    "sg:phone":"+34 922 41 50 15",
    "sg:postcode":"38700",
    "sg:province":"Santa Cruz De Tenerife",
    "wof:name":"Garcia Perez Jose Antonio",
    "wof:placetype":"venue"
},
  "geometry": {"coordinates":[-17.7610569,28.6865692139],"type":"Point"}
}