{
  "type": "Feature",
  "properties": {
    "addr:full":"Calle de Burniola Kalea, 7 Irun Guip\u00f9zcoa 20303",
    "addr:housenumber":"7",
    "addr:postcode":"20303",
    "addr:street":"Calle De Burniola Kalea;Guipu\u0300Zcoa",
    "iso:country":"ES",
    "sg:address":"Calle de Burniola Kalea, 7",
    "sg:city":"Irun",
    "sg:orig_category":"Promotores Constructores",
    "sg:phone":"+34 943 61 48 55",
    "sg:postcode":"20303",
    "sg:province":"Guip\u00f9zcoa",
    "wof:name":"Construcciones Roser S.a.l.",
    "wof:placetype":"venue"
},
  "geometry": {"coordinates":[-1.7902339697,43.3395233154],"type":"Point"}
}