{
  "type": "Feature",
  "properties": {
    "addr:full":"Pase Constitucion (de La), 12 Logro\u00f1o La Rioja 26004",
    "addr:postcode":"26004",
    "addr:street":"Rioja",
    "iso:country":"ES",
    "sg:address":"Pase Constitucion (de La), 12",
    "sg:city":"Logro\u00f1o",
    "sg:orig_category":"Asociaciones, Organismos Culturales Y Socioeducativos",
    "sg:phone":"+34 941 23 17 18",
    "sg:postcode":"26004",
    "sg:province":"La Rioja",
    "wof:name":"Asociacion De Promocion Gitana De La Rioja",
    "wof:placetype":"venue"
},
  "geometry": {"coordinates":[-2.4332249165,42.4688072205],"type":"Point"}
}