{
  "type": "Feature",
  "properties": {
    "addr:full":"Ctra Estella-vitoria, 37 Murieta Navarra 31280",
    "addr:housenumber":"37",
    "addr:postcode":"31280",
    "addr:street":"Ctra Estella-Vitoria;Navarra",
    "iso:country":"ES",
    "sg:address":"Ctra Estella-vitoria, 37",
    "sg:city":"Murieta",
    "sg:orig_category":"Albergues",
    "sg:phone":"+34 948 53 40 39",
    "sg:postcode":"31280",
    "sg:province":"Navarra",
    "wof:name":"Gutierrez Rodriguez J. Y Rubio Redondo P. C.b.",
    "wof:placetype":"venue"
},
  "geometry": {"coordinates":[-2.1435830593,42.6476287842],"type":"Point"}
}