{
  "type": "Feature",
  "properties": {
    "addr:full":"Poli Pol.indust. El Segre, 9 Lleida Lleida 25191",
    "addr:housenumber":"9",
    "addr:postcode":"25191",
    "addr:street":"El Segre",
    "iso:country":"ES",
    "sg:address":"Poli Pol.indust. El Segre, 9",
    "sg:city":"Lleida",
    "sg:orig_category":"Venta, Montaje De Neum\u00c1ticos",
    "sg:phone":"+34 973 20 29 22",
    "sg:postcode":"25191",
    "sg:province":"Lleida",
    "wof:name":"Vulcanizados Diaz-subias S. A.",
    "wof:placetype":"venue"
},
  "geometry": {"coordinates":[0.6630749702,41.6341972351],"type":"Point"}
}