{
  "type": "Feature",
  "properties": {
    "iso:country":"ES",
    "sg:address":"Plaz Constitucion (de La), S/n",
    "sg:city":"Totana",
    "sg:classifiers":[
        {
            "category":"Taxi",
            "type":"Transportation"
        }
    ],
    "sg:phone":"+34 968 42 02 44",
    "sg:postcode":"30850",
    "sg:province":"Murcia",
    "wof:name":"Romero Izquierdo Eliseo",
    "wof:placetype":"venue"
},
  "geometry": {"coordinates":[-1.5025440454,37.7696418762],"type":"Point"}
}