{
  "type": "Feature",
  "properties": {
    "iso:country":"ES",
    "sg:address":"Pl Reis Catolics, 11",
    "sg:city":"Elche",
    "sg:orig_category":"Asociaciones, Organismos Culturales Y Socioeducativos",
    "sg:phone":"+34 965 43 29 89",
    "sg:postcode":"03201",
    "sg:province":"Alicante",
    "wof:name":"Asociacion De Bellas Artes De Elche",
    "wof:placetype":"venue"
},
  "geometry": {"coordinates":[-0.7012363076,38.2608413696],"type":"Point"}
}