{
  "type": "Feature",
  "properties": {
    "addr:full":"Calle de Leon, 47 Astorga Le\u00f3n 24700",
    "addr:housenumber":"47",
    "addr:postcode":"24700",
    "addr:street":"Calle De Leon;Leo\u0301N",
    "iso:country":"ES",
    "sg:address":"Calle de Leon, 47",
    "sg:city":"Astorga",
    "sg:orig_category":"Electricidad (montaje, Ensamblaje De Componentes)",
    "sg:phone":"+34 987 61 60 18",
    "sg:postcode":"24700",
    "sg:province":"Le\u00f3n",
    "wof:name":"Alonso Luengo Jose Antonio",
    "wof:placetype":"venue"
},
  "geometry": {"coordinates":[-6.0614423752,42.4587898254],"type":"Point"}
}