{
  "type": "Feature",
  "properties": {
    "addr:full":"Carrer de Vilanova, 55 Copons Barcelona 08281",
    "addr:housenumber":"55",
    "addr:postcode":"08281",
    "addr:street":"Carrer De Vilanova",
    "iso:country":"ES",
    "sg:address":"Carrer de Vilanova, 55",
    "sg:city":"Copons",
    "sg:orig_category":"Mataderos Y Talleres De Despiezado",
    "sg:phone":"+34 938 09 00 36",
    "sg:postcode":"08281",
    "sg:province":"Barcelona",
    "wof:name":"Closa I Fills S.l.",
    "wof:placetype":"venue"
},
  "geometry": {"coordinates":[1.518682003,41.6346931458],"type":"Point"}
}