{
  "type": "Feature",
  "properties": {
    "addr:full":"Calle de Conjunto Avenida (del), S/n Alcobendas Madrid 28100",
    "addr:postcode":"28100",
    "addr:street":"Calle De;Avenida Del S / N",
    "iso:country":"ES",
    "sg:address":"Calle de Conjunto Avenida (del), S/n",
    "sg:city":"Alcobendas",
    "sg:orig_category":"Supermercados Y Hipermercados",
    "sg:phone":"+34 916 51 45 66",
    "sg:postcode":"28100",
    "sg:province":"Madrid",
    "wof:name":"Comercial Superma S.a.",
    "wof:placetype":"venue"
},
  "geometry": {"coordinates":[-3.646586895,40.5473365784],"type":"Point"}
}