{
  "type": "Feature",
  "properties": {
    "iso:country":"ES",
    "sg:address":"Pase Lugaritz, 23",
    "sg:city":"Donostia-san Sebastian",
    "sg:orig_category":"Caf\u00c9s, Bares, Cervecer\u00cdas",
    "sg:phone":"+34 943 31 04 30",
    "sg:postcode":"20018",
    "sg:province":"Guip\u00f9zcoa",
    "wof:name":"Arretxe Kafetegia S.l.l.",
    "wof:placetype":"venue"
},
  "geometry": {"coordinates":[-2.0029520988,43.2836837769],"type":"Point"}
}