{
  "type": "Feature",
  "properties": {
    "iso:country":"ES",
    "sg:address":"Play San Marcos, 3",
    "sg:city":"San Marcos",
    "sg:orig_category":"Arquitectos",
    "sg:phone":"+34 922 81 14 06",
    "sg:postcode":"38430",
    "sg:province":"Santa Cruz De Tenerife",
    "wof:name":"Guanche Luis-ravelo Pedro Manuel",
    "wof:placetype":"venue"
},
  "geometry": {"coordinates":[-16.7204761505,28.3677654266],"type":"Point"}
}