{
  "type": "Feature",
  "properties": {
    "iso:country":"ES",
    "sg:address":"Carrer de Aries, 19",
    "sg:city":"Terrassa",
    "sg:orig_category":"Electrolisis, Depurado Del Aluminio Y De Aleaciones",
    "sg:phone":"+34 937 86 92 35",
    "sg:postcode":"08228",
    "sg:province":"Barcelona",
    "wof:name":"Tecanal S.a.",
    "wof:placetype":"venue"
},
  "geometry": {"coordinates":[2.033509016,41.5452232361],"type":"Point"}
}