{
  "type": "Feature",
  "properties": {
    "addr:full":"Calle de Camino Viejo De Leganes, 141 Madrid Madrid 28025",
    "addr:housenumber":"141",
    "addr:postcode":"28025",
    "addr:street":"Calle De Camino Viejo De Leganes",
    "iso:country":"ES",
    "sg:address":"Calle de Camino Viejo De Leganes, 141",
    "sg:city":"Madrid",
    "sg:orig_category":"Ropa Para Ni\u00d1os (al Por Menor)",
    "sg:phone":"+34 915 25 54 77",
    "sg:postcode":"28025",
    "sg:province":"Madrid",
    "wof:name":"Gestion De Fincas Camino Viejo Viejo Sl",
    "wof:placetype":"venue"
},
  "geometry": {"coordinates":[-3.7290658951,40.3838500977],"type":"Point"}
}