{
  "type": "Feature",
  "properties": {
    "addr:full":"Rava Robuster, 41 Reus Tarragona 43204",
    "addr:housenumber":"41",
    "addr:postcode":"43204",
    "addr:street":"Robuster",
    "iso:country":"ES",
    "sg:address":"Rava Robuster, 41",
    "sg:city":"Reus",
    "sg:orig_category":"Peluquer\u00cdas, Peluquer\u00cda Mixta",
    "sg:phone":"+34 977 34 09 03",
    "sg:postcode":"43204",
    "sg:province":"Tarragona",
    "wof:name":"Miras Quiciof Maria",
    "wof:placetype":"venue"
},
  "geometry": {"coordinates":[1.1091680527,41.1530570984],"type":"Point"}
}