{
  "type": "Feature",
  "properties": {
    "addr:full":"Ctra Vella (sant Celoni), 32 S. Celoni Barcelona 08470",
    "addr:housenumber":"32",
    "addr:postcode":"08470",
    "addr:street":"Ctra Vella Sant Celoni;S. Celoni Barcelona",
    "iso:country":"ES",
    "sg:address":"Ctra Vella (sant Celoni), 32",
    "sg:city":"S. Celoni",
    "sg:orig_category":"Panader\u00cdas, Panader\u00cdas",
    "sg:phone":"+34 938 67 27 93",
    "sg:postcode":"08470",
    "sg:province":"Barcelona",
    "wof:name":"Egea Prat Alfons",
    "wof:placetype":"venue"
},
  "geometry": {"coordinates":[2.48959589,41.6870117188],"type":"Point"}
}