{
  "type": "Feature",
  "properties": {
    "iso:country":"ES",
    "sg:address":"Calle de Antioco, 5",
    "sg:city":"Ceuta",
    "sg:orig_category":"Bazares, Art\u00cdculos De Limpieza Y De Cocina (al Por Menor)",
    "sg:phone":"+34 956 51 66 34",
    "sg:postcode":"51001",
    "sg:province":"Ceuta",
    "wof:name":"Rios Mata Francisco",
    "wof:placetype":"venue"
},
  "geometry": {"coordinates":[-5.3104262352,35.8879585266],"type":"Point"}
}