{
  "type": "Feature",
  "properties": {
    "iso:country":"ES",
    "sg:address":"Carrer de Lleida, 31",
    "sg:city":"Barcelona",
    "sg:orig_category":"Institutos De Belleza",
    "sg:phone":"+34 934 26 11 36",
    "sg:postcode":"08004",
    "sg:province":"Barcelona",
    "wof:name":"Garin Diaz Cristina",
    "wof:placetype":"venue"
},
  "geometry": {"coordinates":[2.1555149555,41.3726234436],"type":"Point"}
}