{
  "type": "Feature",
  "properties": {
    "addr:full":"Avda Andalucia, Km. 0010,3 Madrid Madrid 28021",
    "addr:postcode":"28021",
    "addr:street":"Avda Andalucia Km. 0010,3",
    "iso:country":"ES",
    "sg:address":"Avda Andalucia, Km. 0010,3",
    "sg:city":"Madrid",
    "sg:orig_category":"Empresas De Estuco",
    "sg:phone":"+34 917 10 97 07",
    "sg:postcode":"28021",
    "sg:province":"Madrid",
    "wof:name":"Sello Grafico S.l.",
    "wof:placetype":"venue"
},
  "geometry": {"coordinates":[-3.6932249069,40.3462486267],"type":"Point"}
}