{
  "type": "Feature",
  "properties": {
    "iso:country":"ES",
    "sg:address":"Urb Poligono Juncaril, 252",
    "sg:city":"Albolote",
    "sg:orig_category":"Construcciones Met\u00c1licas",
    "sg:phone":"+34 958 46 51 07",
    "sg:postcode":"18220",
    "sg:province":"Granada",
    "wof:name":"Talleres Metalurgicos Poyatos Juncaril S.l.",
    "wof:placetype":"venue"
},
  "geometry": {"coordinates":[-3.6585440636,37.2332839966],"type":"Point"}
}