{
  "type": "Feature",
  "properties": {
    "addr:full":"Avda Nuestra Se\u00d1ora De Fatima, 27 Madrid Madrid 28047",
    "addr:housenumber":"27",
    "addr:postcode":"madrid;28047",
    "addr:street":"Avda Nuestra Sen\u0303Ora De Fatima",
    "iso:country":"ES",
    "sg:address":"Avda Nuestra Se\u00d1ora De Fatima, 27",
    "sg:city":"Madrid",
    "sg:orig_category":"Fabricaci\u00d3n De Sobres, Bolsas Y Fundas",
    "sg:phone":"+34 915 25 45 70",
    "sg:postcode":"28047",
    "sg:province":"Madrid",
    "wof:name":"Merino Simon Pompeyo",
    "wof:placetype":"venue"
},
  "geometry": {"coordinates":[-3.7452409267,40.3853263855],"type":"Point"}
}