{
  "type": "Feature",
  "properties": {
    "addr:full":"Zuaznabar Kalea, 100 Ugaldetxo Guip\u00f9zcoa 20180",
    "addr:housenumber":"100",
    "addr:postcode":"20180",
    "addr:street":"Zuaznabar Kalea;Guipu\u0300Zcoa",
    "iso:country":"ES",
    "sg:address":"Zuaznabar Kalea, 100",
    "sg:city":"Ugaldetxo",
    "sg:orig_category":"Extinci\u00d3n De Incendios: Material Y Suministros (fabricaci\u00d3n, Al Por Mayor)",
    "sg:phone":"+34 943 49 04 88",
    "sg:postcode":"20180",
    "sg:province":"Guip\u00f9zcoa",
    "wof:name":"Markosa S.l.l",
    "wof:placetype":"venue"
},
  "geometry": {"coordinates":[-1.8843630552,43.293006897],"type":"Point"}
}