{
  "type": "Feature",
  "properties": {
    "addr:full":"Carrer de Sant Benet, 61 Mataro Barcelona 08302",
    "addr:housenumber":"61",
    "addr:postcode":"08302",
    "addr:street":"Carrer De Sant Benet",
    "iso:country":"ES",
    "sg:address":"Carrer de Sant Benet, 61",
    "sg:city":"Mataro",
    "sg:orig_category":"Molduras, Junquillos, Listones Y Molduras Perforadas",
    "sg:phone":"+34 937 99 04 33",
    "sg:postcode":"08302",
    "sg:province":"Barcelona",
    "wof:name":"Nieto Jimenez Josefa",
    "wof:placetype":"venue"
},
  "geometry": {"coordinates":[2.4391989708,41.5379371643],"type":"Point"}
}