{
  "type": "Feature",
  "properties": {
    "iso:country":"ES",
    "sg:address":"Carrer de Tamarit, 118",
    "sg:city":"Barcelona",
    "sg:orig_category":"Zapatos (al Por Menor)",
    "sg:phone":"+34 934 24 73 41",
    "sg:postcode":"08015",
    "sg:province":"Barcelona",
    "wof:name":"Paytubi Barbe Antonio",
    "wof:placetype":"venue"
},
  "geometry": {"coordinates":[2.1589579582,41.3769607544],"type":"Point"}
}