{
  "type": "Feature",
  "properties": {
    "addr:full":"Carrer de Doctor Barrera, 8 Rocafort Queralt Tarragona 43426",
    "addr:housenumber":"8",
    "addr:postcode":"43426",
    "addr:street":"Carrer De Doctor Barrera;Queralt",
    "iso:country":"ES",
    "sg:address":"Carrer de Doctor Barrera, 8",
    "sg:city":"Rocafort Queralt",
    "sg:orig_category":"Condimentos, Especias, Vinagres, Salsas Preparadas (fabricaci\u00d3n, Al Por Mayor)",
    "sg:phone":"+34 977 89 80 93",
    "sg:postcode":"43426",
    "sg:province":"Tarragona",
    "wof:name":"Corbella C.b.",
    "wof:placetype":"venue"
},
  "geometry": {"coordinates":[1.2819650173,41.4773406982],"type":"Point"}
}