{
  "type": "Feature",
  "properties": {
    "iso:country":"ES",
    "sg:address":"Rua Constitucion (da), 12",
    "sg:city":"Xinzo De Limia",
    "sg:orig_category":"Molduras, Junquillos, Listones Y Molduras Perforadas",
    "sg:phone":"+34 988 46 12 35",
    "sg:postcode":"32630",
    "sg:province":"Ourense",
    "wof:name":"Cuquejo Arias Herminio",
    "wof:placetype":"venue"
},
  "geometry": {"coordinates":[-7.727145195,42.063117981],"type":"Point"}
}