{
  "type": "Feature",
  "properties": {
    "addr:full":"Rbla Guipuscoa, 23 Barcelona Barcelona 08018",
    "addr:housenumber":"23",
    "addr:postcode":"08018",
    "addr:street":"Rbla Guipuscoa",
    "iso:country":"ES",
    "sg:address":"Rbla Guipuscoa, 23",
    "sg:city":"Barcelona",
    "sg:orig_category":"Deportes Diversos",
    "sg:phone":"+34 933 03 01 60",
    "sg:postcode":"08018",
    "sg:province":"Barcelona",
    "wof:name":"Federacio Catalana D'hipica",
    "wof:placetype":"venue"
},
  "geometry": {"coordinates":[2.1939959526,41.414352417],"type":"Point"}
}