{
  "type": "Feature",
  "properties": {
    "addr:full":"Calle de Germanies, 98 Torrent Valencia 46900",
    "addr:housenumber":"98",
    "addr:postcode":"46900",
    "addr:street":"Calle De Germanies;Valencia",
    "iso:country":"ES",
    "sg:address":"Calle de Germanies, 98",
    "sg:city":"Torrent",
    "sg:orig_category":"Peluqueros: De Se\u00d1oras",
    "sg:phone":"+34 961 57 44 50",
    "sg:postcode":"46900",
    "sg:province":"Valencia",
    "wof:name":"Olivares Bueno Angeles Isabel",
    "wof:placetype":"venue"
},
  "geometry": {"coordinates":[-0.4766739905,39.4305419922],"type":"Point"}
}