{
  "type": "Feature",
  "properties": {
    "iso:country":"ES",
    "sg:address":"Calle de Villamanin, 29",
    "sg:city":"Madrid",
    "sg:orig_category":"Guarder\u00cdas",
    "sg:phone":"+34 914 64 98 39",
    "sg:postcode":"28011",
    "sg:province":"Madrid",
    "wof:name":"Hidalgo Castro Maria Isabel",
    "wof:placetype":"venue"
},
  "geometry": {"coordinates":[-3.7523629665,40.4072914124],"type":"Point"}
}