{
  "type": "Feature",
  "properties": {
    "iso:country":"ES",
    "sg:address":"Calle de Angel Nieto, 29",
    "sg:city":"Priego Cordoba",
    "sg:orig_category":"Agencias Y Agentes Comerciales, Representantes",
    "sg:phone":"+34 957 54 08 81",
    "sg:postcode":"14800",
    "sg:province":"C\u00f3rdoba",
    "wof:name":"Jurado Lopez Antonio",
    "wof:placetype":"venue"
},
  "geometry": {"coordinates":[-4.2072620392,37.4419822693],"type":"Point"}
}