{
  "type": "Feature",
  "properties": {
    "iso:country":"ES",
    "sg:address":"Calle de Mayor, 150",
    "sg:city":"Murchante",
    "sg:orig_category":"Ferreter\u00cda (diversos)",
    "sg:phone":"+34 948 81 86 79",
    "sg:postcode":"31521",
    "sg:province":"Navarra",
    "wof:name":"Inacero S.l.",
    "wof:placetype":"venue"
},
  "geometry": {"coordinates":[-1.6494859457,42.0336341858],"type":"Point"}
}