{
  "type": "Feature",
  "properties": {
    "addr:full":"Barr Camarreal, 9 Pe\u00d1acastillo Cantabria 39011",
    "addr:housenumber":"9",
    "addr:postcode":"39011",
    "addr:street":"Barr Camarreal",
    "iso:country":"ES",
    "sg:address":"Barr Camarreal, 9",
    "sg:city":"Pe\u00d1acastillo",
    "sg:orig_category":"Electrodom\u00c9sticos (al Por Menor)",
    "sg:phone":"+34 942 34 37 39",
    "sg:postcode":"39011",
    "sg:province":"Cantabria",
    "wof:name":"Merino Valdor S. L.",
    "wof:placetype":"venue"
},
  "geometry": {"coordinates":[-3.8643889427,43.4480743408],"type":"Point"}
}