{
  "type": "Feature",
  "properties": {
    "addr:full":"Rua Pombal, 52 Cambados Pontevedra 36630",
    "addr:housenumber":"52",
    "addr:postcode":"36630",
    "addr:street":"Rua Pombal",
    "iso:country":"ES",
    "sg:address":"Rua Pombal, 52",
    "sg:city":"Cambados",
    "sg:orig_category":"Electricidad: Instaladores",
    "sg:phone":"+34 986 52 00 20",
    "sg:postcode":"36630",
    "sg:province":"Pontevedra",
    "sg:website":"www.salvadorcores.com",
    "wof:name":"Electricidade Salvador Cores S.l.",
    "wof:placetype":"venue"
},
  "geometry": {"coordinates":[-8.8134393692,42.5220375061],"type":"Point"}
}