{
  "type": "Feature",
  "properties": {
    "addr:full":"Calle de Islas Marquesas, 1 Madrid Madrid 28035",
    "addr:housenumber":"1",
    "addr:postcode":"28035",
    "addr:street":"Calle De Islas Marquesas",
    "iso:country":"ES",
    "sg:address":"Calle de Islas Marquesas, 1",
    "sg:city":"Madrid",
    "sg:orig_category":"Mec\u00c1nico Del Autom\u00d3vil",
    "sg:phone":"+34 913 16 00 78",
    "sg:postcode":"28035",
    "sg:province":"Madrid",
    "wof:name":"Talleres Agustin S.l",
    "wof:placetype":"venue"
},
  "geometry": {"coordinates":[-3.7262370586,40.4744606018],"type":"Point"}
}