{
  "type": "Feature",
  "properties": {
    "addr:full":"Carrer de Sant Blai (de), 24 Tortosa Tarragona 43500",
    "addr:housenumber":"24",
    "addr:postcode":"43500",
    "addr:street":"Carrer De Sant Blai De",
    "iso:country":"ES",
    "sg:address":"Carrer de Sant Blai (de), 24",
    "sg:city":"Tortosa",
    "sg:orig_category":"Abogados",
    "sg:phone":"+34 977 44 28 64",
    "sg:postcode":"43500",
    "sg:province":"Tarragona",
    "wof:name":"Roca Sala Inmaculada",
    "wof:placetype":"venue"
},
  "geometry": {"coordinates":[0.5216640234,40.8110733032],"type":"Point"}
}