{
  "type": "Feature",
  "properties": {
    "iso:country":"ES",
    "sg:address":"Pg Paisos Catalans, 30",
    "sg:city":"Salt",
    "sg:orig_category":"Inmobiliaria (agencias)",
    "sg:phone":"+34 972 40 50 81",
    "sg:postcode":"17190",
    "sg:province":"Girona",
    "wof:name":"Gestion Inmobiliaria F.i.m.e. S.l.",
    "wof:placetype":"venue"
},
  "geometry": {"coordinates":[2.7886989117,41.9719619751],"type":"Point"}
}