{
  "type": "Feature",
  "properties": {
    "addr:full":"Cami Serra, 1 Castell Bendinat Islas Baleares 07181",
    "addr:housenumber":"1",
    "addr:postcode":"07181",
    "addr:street":"Serra;Islas",
    "iso:country":"ES",
    "sg:address":"Cami Serra, 1",
    "sg:city":"Castell Bendinat",
    "sg:orig_category":"Inmobiliaria (agencias)",
    "sg:phone":"+34 971 70 26 70",
    "sg:postcode":"07181",
    "sg:province":"Islas Baleares",
    "wof:name":"Anobra S.a.",
    "wof:placetype":"venue"
},
  "geometry": {"coordinates":[2.8577105999,39.5341796875],"type":"Point"}
}