{
  "type": "Feature",
  "properties": {
    "iso:country":"ES",
    "sg:address":"Carrer de Costa Brava, 3",
    "sg:city":"Cornella Llobregat",
    "sg:orig_category":"Animales (al Por Menor)",
    "sg:phone":"+34 933 77 89 49",
    "sg:postcode":"08940",
    "sg:province":"Barcelona",
    "wof:name":"Serrano Tirado Juan Antonio",
    "wof:placetype":"venue"
},
  "geometry": {"coordinates":[2.0724380016,41.3595619202],"type":"Point"}
}