{
  "type": "Feature",
  "properties": {
    "iso:country":"ES",
    "sg:address":"Carr Forn Nou, 14",
    "sg:city":"Figueres",
    "sg:orig_category":"Comadronas",
    "sg:phone":"+34 972 51 13 12",
    "sg:postcode":"17600",
    "sg:province":"Girona",
    "wof:name":"Compte Corominas Maria Del Carmen",
    "wof:placetype":"venue"
},
  "geometry": {"coordinates":[2.9614698887,42.26612854],"type":"Point"}
}