{
  "type": "Feature",
  "properties": {
    "addr:full":"Ctra. Sagunto-burgos, S/n Monreal Campo Teruel 44300",
    "addr:housenumber":"s",
    "addr:postcode":"44300",
    "addr:street":"Ctra. Sagunto-Burgos;/ N",
    "iso:country":"ES",
    "sg:address":"Ctra. Sagunto-burgos, S/n",
    "sg:city":"Monreal Campo",
    "sg:orig_category":"Mec\u00c1nico Del Autom\u00d3vil",
    "sg:phone":"+34 978 86 30 47",
    "sg:postcode":"44300",
    "sg:province":"Teruel",
    "wof:name":"Lucia Martin Francisco",
    "wof:placetype":"venue"
},
  "geometry": {"coordinates":[-1.3579939604,40.7872505188],"type":"Point"}
}