{
  "type": "Feature",
  "properties": {
    "addr:full":"Calle de Quintanar, 4 Villanueva Alcardete Toledo 45810",
    "addr:housenumber":"4",
    "addr:postcode":"45810",
    "addr:street":"Calle De Quintanar",
    "iso:country":"ES",
    "sg:address":"Calle de Quintanar, 4",
    "sg:city":"Villanueva Alcardete",
    "sg:orig_category":"Bosques (trabajos, Asesor\u00cda, Gesti\u00d3n)",
    "sg:phone":"+34 925 16 79 63",
    "sg:postcode":"45810",
    "sg:province":"Toledo",
    "wof:name":"Renta Y Negocios Tim S.l.",
    "wof:placetype":"venue"
},
  "geometry": {"coordinates":[-3.0146689415,39.6690635681],"type":"Point"}
}