{
  "type": "Feature",
  "properties": {
    "addr:full":"Avda Constitucion, S/n Medina Campo Valladolid 47400",
    "addr:housenumber":"/ n",
    "addr:postcode":"47400",
    "addr:street":"Avda Constitucion S",
    "iso:country":"ES",
    "sg:address":"Avda Constitucion, S/n",
    "sg:city":"Medina Campo",
    "sg:orig_category":"Venta, Montaje De Neum\u00c1ticos",
    "sg:phone":"+34 983 80 06 91",
    "sg:postcode":"47400",
    "sg:province":"Valladolid",
    "wof:name":"Euronet Spain S.a.",
    "wof:placetype":"venue"
},
  "geometry": {"coordinates":[-4.9192790985,41.3202781677],"type":"Point"}
}