{
  "type": "Feature",
  "properties": {
    "iso:country":"ES",
    "sg:address":"Ctra. Etxauri, 9",
    "sg:city":"Orkoien",
    "sg:orig_category":"Rectificaci\u00d3n, Mecanizado, Fresado",
    "sg:phone":"+34 948 32 14 04",
    "sg:postcode":"31160",
    "sg:province":"Navarra",
    "sg:website":"www.gruporeside.com",
    "wof:name":"Componentes De Direccion Recylan S.l.",
    "wof:placetype":"venue"
},
  "geometry": {"coordinates":[-1.7060990334,42.8219032288],"type":"Point"}
}