{
  "type": "Feature",
  "properties": {
    "iso:country":"ES",
    "sg:address":"Eusko Gudarien Kalea, 23",
    "sg:city":"Orio",
    "sg:orig_category":"Estancos",
    "sg:phone":"+34 943 83 12 12",
    "sg:postcode":"20810",
    "sg:province":"Guip\u00f9zcoa",
    "wof:name":"Lerchundi Murguiondo Maria Jesus",
    "wof:placetype":"venue"
},
  "geometry": {"coordinates":[-2.1274859905,43.2783050537],"type":"Point"}
}