{
  "type": "Feature",
  "properties": {
    "iso:country":"ES",
    "sg:address":"Rua Beato Sebastian De Aparicio, S/n",
    "sg:city":"Gudi\u00f1a",
    "sg:orig_category":"Florister\u00cdas",
    "sg:phone":"+34 988 42 10 32",
    "sg:postcode":"32540",
    "sg:province":"Ourense",
    "wof:name":"Barros Martinez Jesus",
    "wof:placetype":"venue"
},
  "geometry": {"coordinates":[-7.1380591393,42.0612564087],"type":"Point"}
}