{
  "type": "Feature",
  "properties": {
    "iso:country":"ES",
    "sg:address":"Calle de Dos De Mayo, 10",
    "sg:city":"Ponferrada",
    "sg:orig_category":"Contenedores (mercanc\u00cdas)",
    "sg:phone":"+34 987 41 27 57",
    "sg:postcode":"24400",
    "sg:province":"Le\u00f3n",
    "wof:name":"Transportes Siryelo S.l.",
    "wof:placetype":"venue"
},
  "geometry": {"coordinates":[-6.5983390808,42.5483360291],"type":"Point"}
}