{
  "type": "Feature",
  "properties": {
    "iso:country":"ES",
    "sg:address":"Calle de Leon Felipe, 22",
    "sg:city":"Zaragoza",
    "sg:orig_category":"Centros De Coordinaci\u00d3n",
    "sg:phone":"+34 976 73 06 62",
    "sg:postcode":"50015",
    "sg:province":"Zaragoza",
    "wof:name":"Dein Tecnologia S.l.",
    "wof:placetype":"venue"
},
  "geometry": {"coordinates":[-0.8829380274,41.6672210693],"type":"Point"}
}