{
  "type": "Feature",
  "properties": {
    "addr:full":"Calle de Tiendas (las), S/n Molina Guadalajara 19300",
    "addr:postcode":"19300",
    "addr:street":"Calle De Tiendas Las S / N Molina",
    "iso:country":"ES",
    "sg:address":"Calle de Tiendas (las), S/n",
    "sg:city":"Molina",
    "sg:orig_category":"Molduras, Junquillos, Listones Y Molduras Perforadas",
    "sg:phone":"+34 949 83 03 23",
    "sg:postcode":"19300",
    "sg:province":"Guadalajara",
    "wof:name":"Carrasco Sanchez C.b.",
    "wof:placetype":"venue"
},
  "geometry": {"coordinates":[-1.8877439499,40.8436813354],"type":"Point"}
}