{
  "type": "Feature",
  "properties": {
    "addr:full":"Avda Jesus Santos Rein, 140 Fuengirola M\u00e1laga 29640",
    "addr:housenumber":"140",
    "addr:postcode":"29640",
    "addr:street":"Avda Jesus Santos Rein;Ma\u0301Laga",
    "iso:country":"ES",
    "sg:address":"Avda Jesus Santos Rein, 140",
    "sg:city":"Fuengirola",
    "sg:orig_category":"Plomeros",
    "sg:phone":"+34 952 47 25 43",
    "sg:postcode":"29640",
    "sg:province":"M\u00e1laga",
    "wof:name":"Pastora Moreno Antonio",
    "wof:placetype":"venue"
},
  "geometry": {"coordinates":[-4.6208791733,36.5460395813],"type":"Point"}
}