{
  "type": "Feature",
  "properties": {
    "addr:full":"Avda Cervantes, S/n Alora M\u00e1laga 29500",
    "addr:housenumber":"s / n",
    "addr:postcode":"29500",
    "addr:street":"Avda Cervantes;Alora Ma\u0301Laga",
    "iso:country":"ES",
    "sg:address":"Avda Cervantes, S/n",
    "sg:city":"Alora",
    "sg:orig_category":"Ropa Para Se\u00d1oras Y Caballeros (al Por Menor)",
    "sg:phone":"+34 952 49 88 89",
    "sg:postcode":"29500",
    "sg:province":"M\u00e1laga",
    "wof:name":"Morales Martinez Juan",
    "wof:placetype":"venue"
},
  "geometry": {"coordinates":[-4.7046990395,36.8277244568],"type":"Point"}
}