{
  "type": "Feature",
  "properties": {
    "iso:country":"ES",
    "sg:address":"Pl. Mayor, 1",
    "sg:city":"Galve Sorbe",
    "sg:orig_category":"Iglesia Cat\u00d3lica",
    "sg:phone":"+34 949 30 32 56",
    "sg:postcode":"19275",
    "sg:province":"Guadalajara",
    "wof:name":"Obispado De Siguenza-guadalajara",
    "wof:placetype":"venue"
},
  "geometry": {"coordinates":[-3.246295929,41.2345085144],"type":"Point"}
}