{
  "type": "Feature",
  "properties": {
    "addr:full":"Guitoi, 3 Guitoi La Coru\u00f1a 15108",
    "addr:housenumber":"3",
    "addr:postcode":"15108",
    "addr:street":"Guitoi;La Corun\u0303A",
    "iso:country":"ES",
    "sg:address":"Guitoi, 3",
    "sg:city":"Guitoi",
    "sg:orig_category":"Empresas De Pintura Y Revestimientos",
    "sg:phone":"+34 981 75 32 46",
    "sg:postcode":"15108",
    "sg:province":"La Coru\u00f1a",
    "wof:name":"Ponte Enjamio Jose Manuel",
    "wof:placetype":"venue"
},
  "geometry": {"coordinates":[-8.6454324722,43.2194480896],"type":"Point"}
}