{
  "type": "Feature",
  "properties": {
    "addr:full":"Lug. Fca. Corbamures, S/n Calvarrasa Abajo Salamanca 37181",
    "addr:housenumber":"s",
    "addr:postcode":"37181",
    "addr:street":"/ N",
    "iso:country":"ES",
    "sg:address":"Lug. Fca. Corbamures, S/n",
    "sg:city":"Calvarrasa Abajo",
    "sg:orig_category":"Agricultores, Agricultores",
    "sg:phone":"+34 923 30 63 87",
    "sg:postcode":"37181",
    "sg:province":"Salamanca",
    "wof:name":"Rodriguez Gomez Juan",
    "wof:placetype":"venue"
},
  "geometry": {"coordinates":[-5.5539340973,40.9458961487],"type":"Point"}
}