{
  "type": "Feature",
  "properties": {
    "addr:full":"Plaz Luis De Zu\u00d1iga, 27 Plasencia C\u00e1ceres 10600",
    "addr:housenumber":"27",
    "addr:postcode":"10600",
    "addr:street":"Plaz Luis De Zun\u0303Iga;Ca\u0301Ceres",
    "iso:country":"ES",
    "sg:address":"Plaz Luis De Zu\u00d1iga, 27",
    "sg:city":"Plasencia",
    "sg:orig_category":"Estancos",
    "sg:phone":"+34 927 41 46 05",
    "sg:postcode":"10600",
    "sg:province":"C\u00e1ceres",
    "wof:name":"Blasco Calle Ascension",
    "wof:placetype":"venue"
},
  "geometry": {"coordinates":[-6.0828690529,40.0327110291],"type":"Point"}
}