{
  "type": "Feature",
  "properties": {
    "addr:full":"Calle de Jose Maria Fernandez Lanseros, 11 Madrid Madrid 28017",
    "addr:housenumber":"11",
    "addr:postcode":"madrid;28017",
    "addr:street":"Calle De Jose Maria Fernandez Lanseros",
    "iso:country":"ES",
    "sg:address":"Calle de Jose Maria Fernandez Lanseros, 11",
    "sg:city":"Madrid",
    "sg:orig_category":"Alimentaci\u00d3n General (al Por Menor)",
    "sg:phone":"+34 913 61 32 20",
    "sg:postcode":"28017",
    "sg:province":"Madrid",
    "wof:name":"Jin  Ai Ying",
    "wof:placetype":"venue"
},
  "geometry": {"coordinates":[-3.6572830677,40.4311256409],"type":"Point"}
}