{
  "type": "Feature",
  "properties": {
    "addr:full":"Calle de Lepanto, 1 Albatera Alicante 03340",
    "addr:housenumber":"1",
    "addr:postcode":"03340",
    "addr:street":"Calle De Lepanto",
    "iso:country":"ES",
    "sg:address":"Calle de Lepanto, 1",
    "sg:city":"Albatera",
    "sg:orig_category":"Ropa Para Ni\u00d1os (al Por Menor)",
    "sg:phone":"+34 965 48 82 63",
    "sg:postcode":"03340",
    "sg:province":"Alicante",
    "wof:name":"Quesads Navarro Juan Antonio",
    "wof:placetype":"venue"
},
  "geometry": {"coordinates":[-0.8758320212,38.17710495],"type":"Point"}
}