{
  "type": "Feature",
  "properties": {
    "iso:country":"ES",
    "sg:address":"Real, 51",
    "sg:city":"Orgiva",
    "sg:orig_category":"Loter\u00cda Y T\u00d3mbola",
    "sg:phone":"+34 958 78 55 61",
    "sg:postcode":"18400",
    "sg:province":"Granada",
    "wof:name":"Medina Martin Encarnacion",
    "wof:placetype":"venue"
},
  "geometry": {"coordinates":[-3.4232020378,36.900894165],"type":"Point"}
}