{
  "type": "Feature",
  "properties": {
    "addr:full":"Calle de Fco. Martinez Morella, 11 Alacant Alicante 03011",
    "addr:housenumber":"11",
    "addr:postcode":"03011",
    "addr:street":"Calle De Fco. Martinez Morella",
    "iso:country":"ES",
    "sg:address":"Calle de Fco. Martinez Morella, 11",
    "sg:city":"Alacant",
    "sg:orig_category":"Iglesia Cat\u00d3lica",
    "sg:phone":"+34 965 17 30 02",
    "sg:postcode":"03011",
    "sg:province":"Alicante",
    "wof:name":"Parroquia De La Redencion",
    "wof:placetype":"venue"
},
  "geometry": {"coordinates":[-0.4952999949,38.3741073608],"type":"Point"}
}