{
  "type": "Feature",
  "properties": {
    "addr:full":"Pg Sant Joan, 33 Barcelona Barcelona 08010",
    "addr:housenumber":"33",
    "addr:postcode":"08010",
    "addr:street":"Pg Sant Joan",
    "iso:country":"ES",
    "sg:address":"Pg Sant Joan, 33",
    "sg:city":"Barcelona",
    "sg:orig_category":"Mec\u00c1nico Del Autom\u00d3vil",
    "sg:phone":"+34 932 65 17 36",
    "sg:postcode":"08010",
    "sg:province":"Barcelona",
    "wof:name":"Servicio Mantenimiento Del Automovil S.l.",
    "wof:placetype":"venue"
},
  "geometry": {"coordinates":[2.1771099567,41.3935089111],"type":"Point"}
}