{
  "type": "Feature",
  "properties": {
    "addr:full":"Calle de Postdam, 1 Madrid Madrid 28032",
    "addr:housenumber":"1",
    "addr:postcode":"28032",
    "addr:street":"Calle De Postdam",
    "iso:country":"ES",
    "sg:address":"Calle de Postdam, 1",
    "sg:city":"Madrid",
    "sg:orig_category":"Promotores Constructores",
    "sg:phone":"+34 913 06 16 11",
    "sg:postcode":"28032",
    "sg:province":"Madrid",
    "sg:website":"www.iberianpromove.com",
    "wof:name":"Iberian Promove",
    "wof:placetype":"venue"
},
  "geometry": {"coordinates":[-3.624874115,40.4144973755],"type":"Point"}
}