{
  "type": "Feature",
  "properties": {
    "iso:country":"ES",
    "sg:address":"Calle de Boticas, 7",
    "sg:city":"Aranda Duero",
    "sg:orig_category":"Estilistas Y Estudios De Estilo De Corte Y Confecci\u00d3n",
    "sg:phone":"+34 947 50 00 72",
    "sg:postcode":"09400",
    "sg:province":"Burgos",
    "wof:name":"Rodriguez Gomez Ignacio",
    "wof:placetype":"venue"
},
  "geometry": {"coordinates":[-3.6885330677,41.6712188721],"type":"Point"}
}