{
  "type": "Feature",
  "properties": {
    "addr:full":"Cra. Caldes, S/n Barruera Lleida 25527",
    "addr:housenumber":"s",
    "addr:postcode":"25527",
    "addr:street":"/ N Barruera",
    "iso:country":"ES",
    "sg:address":"Cra. Caldes, S/n",
    "sg:city":"Barruera",
    "sg:orig_category":"Fabricaci\u00d3n De Bebidas No Alcoh\u00d3licas",
    "sg:phone":"+34 973 69 60 83",
    "sg:postcode":"25527",
    "sg:province":"Lleida",
    "wof:name":"Aguas Minerales De Caldas De Bohi S. A.",
    "wof:placetype":"venue"
},
  "geometry": {"coordinates":[0.8009269238,42.5051765442],"type":"Point"}
}