{
  "type": "Feature",
  "properties": {
    "addr:full":"Avda Nuevo Mundo (del), 5 Boadilla Del Monte Madrid 28660",
    "addr:housenumber":"5",
    "addr:postcode":"28660",
    "addr:street":"Avda Nuevo Mundo Del",
    "iso:country":"ES",
    "sg:address":"Avda Nuevo Mundo (del), 5",
    "sg:city":"Boadilla Del Monte",
    "sg:orig_category":"Doctores En Medicina",
    "sg:phone":"+34 916 32 67 61",
    "sg:postcode":"28660",
    "sg:province":"Madrid",
    "wof:name":"Mantenimientos Activa S.l.",
    "wof:placetype":"venue"
},
  "geometry": {"coordinates":[-3.8856990337,40.4057807922],"type":"Point"}
}