{
  "type": "Feature",
  "properties": {
    "addr:full":"Plaz Itxas Aurre, 4 Ondarroa Vizcaya 48700",
    "addr:housenumber":"4",
    "addr:postcode":"48700",
    "iso:country":"ES",
    "sg:address":"Plaz Itxas Aurre, 4",
    "sg:city":"Ondarroa",
    "sg:orig_category":"Molduras, Junquillos, Listones Y Molduras Perforadas",
    "sg:phone":"+34 946 83 04 50",
    "sg:postcode":"48700",
    "sg:province":"Vizcaya",
    "wof:name":"Urresti Badiola Pedro",
    "wof:placetype":"venue"
},
  "geometry": {"coordinates":[-2.4225530624,43.3236732483],"type":"Point"}
}