{
  "type": "Feature",
  "properties": {
    "addr:full":"Calle de Empedrada, 12 Villena Alicante 03400",
    "addr:housenumber":"12",
    "addr:postcode":"03400",
    "addr:street":"Calle De Empedrada",
    "iso:country":"ES",
    "sg:address":"Calle de Empedrada, 12",
    "sg:city":"Villena",
    "sg:orig_category":"Peluquer\u00cdas, Peluquer\u00cda Mixta",
    "sg:phone":"+34 965 81 53 00",
    "sg:postcode":"03400",
    "sg:province":"Alicante",
    "wof:name":"Alamo Contreras Maria Jose",
    "wof:placetype":"venue"
},
  "geometry": {"coordinates":[-0.8631262183,38.6321907043],"type":"Point"}
}