{
  "type": "Feature",
  "properties": {
    "iso:country":"ES",
    "sg:address":"Cmno Pago Barranco, S/n",
    "sg:city":"Archena",
    "sg:orig_category":"Centros Empresariales",
    "sg:phone":"+34 968 43 21 22",
    "sg:postcode":"30600",
    "sg:province":"Murcia",
    "wof:name":"Comunidad De Regantes Del Motor Nuestra Se\u00f1ora De La Esperanz",
    "wof:placetype":"venue"
},
  "geometry": {"coordinates":[-1.2977989912,38.1132583618],"type":"Point"}
}