{
  "type": "Feature",
  "properties": {
    "addr:full":"Pol. Indust. Emporda, S/n Vilamalla Girona 17469",
    "addr:housenumber":"s / n",
    "addr:postcode":"17469",
    "addr:street":"Pol.",
    "iso:country":"ES",
    "sg:address":"Pol. Indust. Emporda, S/n",
    "sg:city":"Vilamalla",
    "sg:orig_category":"Material Y Suministros Para Dentistas, Cirujanos",
    "sg:phone":"+34 972 52 61 69",
    "sg:postcode":"17469",
    "sg:province":"Girona",
    "wof:name":"Famadent S. L.",
    "wof:placetype":"venue"
},
  "geometry": {"coordinates":[2.9704549313,42.2177505493],"type":"Point"}
}