{
  "type": "Feature",
  "properties": {
    "addr:full":"Carrer de Cuba, 9 Sabadell Barcelona 08205",
    "addr:housenumber":"9",
    "addr:postcode":"08205",
    "addr:street":"Carrer De Cuba",
    "iso:country":"ES",
    "sg:address":"Carrer de Cuba, 9",
    "sg:city":"Sabadell",
    "sg:orig_category":"Cooperativas Agr\u00cdcolas",
    "sg:phone":"+34 937 27 00 70",
    "sg:postcode":"08205",
    "sg:province":"Barcelona",
    "wof:name":"Cooperativa Agraria Sabadell",
    "wof:placetype":"venue"
},
  "geometry": {"coordinates":[2.0931699276,41.5450782776],"type":"Point"}
}