{
  "type": "Feature",
  "properties": {
    "addr:full":"Avda Aragon, 10 Sang\u00fcesa Navarra 31400",
    "addr:housenumber":"10",
    "addr:postcode":"31400",
    "addr:street":"Avda Aragon",
    "iso:country":"ES",
    "sg:address":"Avda Aragon, 10",
    "sg:city":"Sang\u00fcesa",
    "sg:orig_category":"Productos Fitosanitarios (negocio, Aplicaci\u00d3n)",
    "sg:phone":"+34 948 87 07 35",
    "sg:postcode":"31400",
    "sg:province":"Navarra",
    "wof:name":"Baigorri San Gorrin Antonio",
    "wof:placetype":"venue"
},
  "geometry": {"coordinates":[-1.2807879448,42.5737457275],"type":"Point"}
}