{
  "type": "Feature",
  "properties": {
    "iso:country":"ES",
    "sg:address":"Calle de Julio Hauzeur, 6",
    "sg:city":"Torrelavega",
    "sg:orig_category":"Electrodom\u00c9sticos (al Por Menor)",
    "sg:phone":"+34 942 88 41 07",
    "sg:postcode":"39300",
    "sg:province":"Cantabria",
    "wof:name":"Arpapem S. L.",
    "wof:placetype":"venue"
},
  "geometry": {"coordinates":[-4.0582799911,43.3513221741],"type":"Point"}
}