{
  "type": "Feature",
  "properties": {
    "iso:country":"ES",
    "sg:address":"Urb Puig-val, S/n",
    "sg:city":"Playa Puig",
    "sg:orig_category":"Alimentaci\u00d3n General (al Por Menor)",
    "sg:phone":"+34 961 46 18 27",
    "sg:postcode":"46540",
    "sg:province":"Valencia",
    "wof:name":"Forner Gimeno Vicente",
    "wof:placetype":"venue"
},
  "geometry": {"coordinates":[-0.3003390133,39.5875854492],"type":"Point"}
}