{
  "type": "Feature",
  "properties": {
    "addr:full":"Pla\u00c7 Rei En Jaume I (del), 4 Gandia Valencia 46700",
    "addr:postcode":"46700",
    "iso:country":"ES",
    "sg:address":"Pla\u00c7 Rei En Jaume I (del), 4",
    "sg:city":"Gandia",
    "sg:orig_category":"Ropa Para Caballeros (al Por Menor)",
    "sg:phone":"+34 962 87 84 52",
    "sg:postcode":"46700",
    "sg:province":"Valencia",
    "wof:name":"Torini S.l.",
    "wof:placetype":"venue"
},
  "geometry": {"coordinates":[-0.1913339943,38.960735321],"type":"Point"}
}