{
  "type": "Feature",
  "properties": {
    "addr:full":"Pl Urquinaona, 6 Barcelona Barcelona 08010",
    "addr:housenumber":"6",
    "addr:postcode":"08010",
    "addr:street":"Pl Urquinaona",
    "iso:country":"ES",
    "sg:address":"Pl Urquinaona, 6",
    "sg:city":"Barcelona",
    "sg:orig_category":"Perfumer\u00cda Y Cosm\u00c9tica (fabricaci\u00d3n, Al Por Mayor)",
    "sg:phone":"+34 933 18 29 34",
    "sg:postcode":"08010",
    "sg:province":"Barcelona",
    "sg:website":"www.marcel-cluny.es",
    "wof:name":"Marcel Cluny S.a.",
    "wof:placetype":"venue"
},
  "geometry": {"coordinates":[2.1731050014,41.389629364],"type":"Point"}
}