{
  "type": "Feature",
  "properties": {
    "addr:full":"Carr Duc De Lliria (del), 99 Lliria Valencia 46160",
    "addr:housenumber":"99",
    "addr:postcode":"46160",
    "addr:street":"Carr Duc De Lliria Del",
    "iso:country":"ES",
    "sg:address":"Carr Duc De Lliria (del), 99",
    "sg:city":"Lliria",
    "sg:orig_category":"Venta, Montaje De Neum\u00c1ticos",
    "sg:phone":"+34 962 78 29 32",
    "sg:postcode":"46160",
    "sg:province":"Valencia",
    "wof:name":"Cuni Tellez Francisco",
    "wof:placetype":"venue"
},
  "geometry": {"coordinates":[-0.6022490263,39.6297988892],"type":"Point"}
}