{
  "type": "Feature",
  "properties": {
    "addr:full":"Calle de Jose Segura Torres, S/n Corralejo Las Palmas 35660",
    "addr:postcode":"35660",
    "addr:street":"Calle De Jose Segura Torres S / N",
    "iso:country":"ES",
    "sg:address":"Calle de Jose Segura Torres, S/n",
    "sg:city":"Corralejo",
    "sg:orig_category":"Camiser\u00cda Y Ropa Interior Masculina (al Por Menor)",
    "sg:phone":"+34 928 53 57 20",
    "sg:postcode":"35660",
    "sg:province":"Las Palmas",
    "wof:name":"Molotov S.l.",
    "wof:placetype":"venue"
},
  "geometry": {"coordinates":[-13.8679990768,28.7394142151],"type":"Point"}
}