{
  "type": "Feature",
  "properties": {
    "addr:full":"Avda Juan Alfonso Batista, S/n Cristianos Santa Cruz De Tenerife 38650",
    "addr:housenumber":"s / n",
    "addr:postcode":"38650",
    "addr:street":"Avda Juan Alfonso Batista",
    "iso:country":"ES",
    "sg:address":"Avda Juan Alfonso Batista, S/n",
    "sg:city":"Cristianos",
    "sg:orig_category":"Bazares, Art\u00cdculos De Limpieza Y De Cocina (al Por Menor)",
    "sg:phone":"+34 922 75 25 24",
    "sg:postcode":"38650",
    "sg:province":"Santa Cruz De Tenerife",
    "wof:name":"Mirchandani  Raju Kishin",
    "wof:placetype":"venue"
},
  "geometry": {"coordinates":[-16.7178783417,28.0508804321],"type":"Point"}
}