{
  "type": "Feature",
  "properties": {
    "addr:full":"Carrer de Cartagena, 317 Barcelona Barcelona 08025",
    "addr:housenumber":"317",
    "addr:postcode":"08025",
    "addr:street":"Carrer De Cartagena",
    "iso:country":"ES",
    "sg:address":"Carrer de Cartagena, 317",
    "sg:city":"Barcelona",
    "sg:orig_category":"Comerciantes Al Por Mayor De Vinos, Licores Y Alcoholes",
    "sg:phone":"+34 934 55 70 44",
    "sg:postcode":"08025",
    "sg:province":"Barcelona",
    "wof:name":"Hualcas Jimenez Sonia Soledad",
    "wof:placetype":"venue"
},
  "geometry": {"coordinates":[2.1744558811,41.4109306335],"type":"Point"}
}