{
  "type": "Feature",
  "properties": {
    "addr:full":"Plaz Constitucion (la), 3 Maracena Granada 18200",
    "addr:housenumber":"3",
    "addr:postcode":"18200",
    "addr:street":"Constitucion La",
    "iso:country":"ES",
    "sg:address":"Plaz Constitucion (la), 3",
    "sg:city":"Maracena",
    "sg:orig_category":"Empresarios",
    "sg:phone":"+34 958 42 07 56",
    "sg:postcode":"18200",
    "sg:province":"Granada",
    "wof:name":"Fundacion Benefica Rojas",
    "wof:placetype":"venue"
},
  "geometry": {"coordinates":[-3.6347329617,37.2074241638],"type":"Point"}
}