{
  "type": "Feature",
  "properties": {
    "iso:country":"ES",
    "sg:address":"Bloc Sant Jordi, S/n",
    "sg:city":"Sant Pere I Sant Pau",
    "sg:orig_category":"Ropa Para Ni\u00d1os (al Por Menor)",
    "sg:phone":"+34 977 20 00 68",
    "sg:postcode":"43007",
    "sg:province":"Tarragona",
    "wof:name":"Sanchez-mariscal Guerra Isabel",
    "wof:placetype":"venue"
},
  "geometry": {"coordinates":[1.2959779501,41.1377334595],"type":"Point"}
}