{
  "type": "Feature",
  "properties": {
    "addr:full":"Cmno Cruz Campillo, 12 Campillo Murcia 30813",
    "addr:housenumber":"12",
    "addr:postcode":"30813",
    "addr:street":"Cmno Cruz Campillo",
    "iso:country":"ES",
    "sg:address":"Cmno Cruz Campillo, 12",
    "sg:city":"Campillo",
    "sg:orig_category":"Iglesia Cat\u00d3lica",
    "sg:phone":"+34 968 46 90 79",
    "sg:postcode":"30813",
    "sg:province":"Murcia",
    "wof:name":"Obispado De Cartagena",
    "wof:placetype":"venue"
},
  "geometry": {"coordinates":[-1.7215889692,37.491394043],"type":"Point"}
}