{
  "type": "Feature",
  "properties": {
    "iso:country":"ES",
    "sg:address":"Avda Juan Carlos I, 36",
    "sg:city":"Monforte Cid",
    "sg:orig_category":"Promotores Constructores",
    "sg:phone":"+34 965 62 15 27",
    "sg:postcode":"03670",
    "sg:province":"Alicante",
    "wof:name":"Agromaster S.l.",
    "wof:placetype":"venue"
},
  "geometry": {"coordinates":[-0.729647,38.3778],"type":"Point"}
}