{
  "type": "Feature",
  "properties": {
    "addr:full":"Calle de Miracruz, 16 Donostia-san Sebastian Guip\u00f9zcoa 20001",
    "addr:housenumber":"16",
    "addr:postcode":"20001",
    "addr:street":"Calle De Miracruz",
    "iso:country":"ES",
    "sg:address":"Calle de Miracruz, 16",
    "sg:city":"Donostia-san Sebastian",
    "sg:orig_category":"Inmobiliaria (agencias)",
    "sg:phone":"+34 943 29 08 00",
    "sg:postcode":"20001",
    "sg:province":"Guip\u00f9zcoa",
    "wof:name":"Sese Espadas Francisco Javier",
    "wof:placetype":"venue"
},
  "geometry": {"coordinates":[-1.9747619629,43.3218803406],"type":"Point"}
}