{
  "type": "Feature",
  "properties": {
    "addr:full":"Carrer de Gremi Selleters, 10 Poligon Industrial De Son Castello Islas Baleares 07009",
    "addr:housenumber":"10",
    "addr:postcode":"07009",
    "addr:street":"Carrer De Gremi Selleters;Industrial;Islas",
    "iso:country":"ES",
    "sg:address":"Carrer de Gremi Selleters, 10",
    "sg:city":"Poligon Industrial De Son Castello",
    "sg:orig_category":"Fabricaci\u00d3n De Jabones, Detergentes Y Lej\u00cdas",
    "sg:phone":"+34 971 43 03 48",
    "sg:postcode":"07009",
    "sg:province":"Islas Baleares",
    "wof:name":"Pedrosa Veny Pedro Jose",
    "wof:placetype":"venue"
},
  "geometry": {"coordinates":[2.6741399765,39.6011390686],"type":"Point"}
}