{
  "type": "Feature",
  "properties": {
    "addr:full":"Calle de Deportes, 1 Pantoja Toledo 45290",
    "addr:housenumber":"1",
    "addr:postcode":"45290",
    "addr:street":"Calle De Deportes",
    "iso:country":"ES",
    "sg:address":"Calle de Deportes, 1",
    "sg:city":"Pantoja",
    "sg:orig_category":"Ense\u00d1anza: Profesiones Art\u00cdsticas",
    "sg:phone":"+34 925 55 40 52",
    "sg:postcode":"45290",
    "sg:province":"Toledo",
    "wof:name":"Hernandez Sanchez Fidel",
    "wof:placetype":"venue"
},
  "geometry": {"coordinates":[-3.8361740112,40.0475273132],"type":"Point"}
}