{
  "type": "Feature",
  "properties": {
    "addr:full":"Pase Rollo, 17 Salamanca Salamanca 37003",
    "addr:housenumber":"17",
    "addr:postcode":"37003",
    "addr:street":"Rollo",
    "iso:country":"ES",
    "sg:address":"Pase Rollo, 17",
    "sg:city":"Salamanca",
    "sg:orig_category":"Bancos",
    "sg:phone":"+34 923 12 00 20",
    "sg:postcode":"37003",
    "sg:province":"Salamanca",
    "wof:name":"Banco De Castilla",
    "wof:placetype":"venue"
},
  "geometry": {"coordinates":[-5.6528282166,40.9655151367],"type":"Point"}
}