{
  "type": "Feature",
  "properties": {
    "iso:country":"ES",
    "sg:address":"C/ Trencadors, 28",
    "sg:city":"Arenal",
    "sg:orig_category":"Mercer\u00cda, Lencer\u00cda (al Por Menor)",
    "sg:phone":"+34 971 44 32 87",
    "sg:postcode":"07600",
    "sg:province":"Islas Baleares",
    "wof:name":"Llinas Mateu Margarita",
    "wof:placetype":"venue"
},
  "geometry": {"coordinates":[2.752327919,39.5086097717],"type":"Point"}
}