{
  "type": "Feature",
  "properties": {
    "iso:country":"ES",
    "sg:address":"Calle de Pozuelo, S/n",
    "sg:city":"Marmolejo",
    "sg:orig_category":"Aceites Y Grasas Alimentarias (fabricaci\u00d3n, Al Por Mayor)",
    "sg:phone":"+34 953 51 71 25",
    "sg:postcode":"23770",
    "sg:province":"Ja\u00e9n",
    "wof:name":"Aceites Uticoliva S.a",
    "wof:placetype":"venue"
},
  "geometry": {"coordinates":[-4.1692862511,38.048740387],"type":"Point"}
}