{
  "type": "Feature",
  "properties": {
    "addr:full":"Ctra Armilla (de), S/n Granada Granada 18006",
    "addr:housenumber":"/ n",
    "addr:postcode":"18006",
    "addr:street":"Ctra Armilla De S",
    "iso:country":"ES",
    "sg:address":"Ctra Armilla (de), S/n",
    "sg:city":"Granada",
    "sg:orig_category":"Negocio De Materiales De Construcci\u00d3n",
    "sg:phone":"+34 958 13 38 88",
    "sg:postcode":"18006",
    "sg:province":"Granada",
    "wof:name":"Rafael Ceballos S.a.",
    "wof:placetype":"venue"
},
  "geometry": {"coordinates":[-3.6087090969,37.1570549011],"type":"Point"}
}