{
  "type": "Feature",
  "properties": {
    "iso:country":"ES",
    "sg:address":"Carrer de Calvet, 56",
    "sg:city":"Barcelona",
    "sg:orig_category":"Material Y Herramientas Agr\u00cdcolas",
    "sg:phone":"+34 932 00 17 28",
    "sg:postcode":"08021",
    "sg:province":"Barcelona",
    "wof:name":"Busquets Thomas Joan",
    "wof:placetype":"venue"
},
  "geometry": {"coordinates":[2.1423909664,41.3958091736],"type":"Point"}
}