{
  "type": "Feature",
  "properties": {
    "addr:full":"Calle de Mayor, 47 Madrid Madrid 28013",
    "addr:housenumber":"47",
    "addr:postcode":"madrid;28013",
    "addr:street":"Calle De Mayor",
    "iso:country":"ES",
    "sg:address":"Calle de Mayor, 47",
    "sg:city":"Madrid",
    "sg:orig_category":"Serigraf\u00cda (material Y Suministros)",
    "sg:phone":"+34 915 48 90 25",
    "sg:postcode":"28013",
    "sg:province":"Madrid",
    "sg:website":"www.kukuxumusu.com",
    "wof:name":"Lagarto D.v.cdad.",
    "wof:placetype":"venue"
},
  "geometry": {"coordinates":[-3.7085707188,40.4159698486],"type":"Point"}
}