{
  "type": "Feature",
  "properties": {
    "addr:full":"Poligono Jessica, 20 Gerindote Toledo 45518",
    "addr:housenumber":"20",
    "addr:postcode":"45518",
    "addr:street":"Poligono Jessica",
    "iso:country":"ES",
    "sg:address":"Poligono Jessica, 20",
    "sg:city":"Gerindote",
    "sg:orig_category":"Cerrajer\u00cda, Ferrallista",
    "sg:phone":"+34 925 76 19 88",
    "sg:postcode":"45518",
    "sg:province":"Toledo",
    "wof:name":"Cristaleria Trenado S.l.",
    "wof:placetype":"venue"
},
  "geometry": {"coordinates":[-4.3021659851,39.9683151245],"type":"Point"}
}