{
  "type": "Feature",
  "properties": {
    "iso:country":"ES",
    "sg:address":"Calle de Puerta Aduana, S/n",
    "sg:city":"Villafranca Cordoba",
    "sg:orig_category":"Supermercados Y Hipermercados",
    "sg:phone":"+34 957 19 02 96",
    "sg:postcode":"14420",
    "sg:province":"C\u00f3rdoba",
    "wof:name":"Molina Romero Antonio",
    "wof:placetype":"venue"
},
  "geometry": {"coordinates":[-4.5471448898,37.959526062],"type":"Point"}
}