{
  "type": "Feature",
  "properties": {
    "iso:country":"ES",
    "sg:address":"Covadonga, 13",
    "sg:city":"Infiesto",
    "sg:orig_category":"Relojer\u00cda (al Por Menor, Reparaci\u00d3n)",
    "sg:phone":"+34 985 71 02 82",
    "sg:postcode":"33530",
    "sg:province":"Asturias",
    "wof:name":"Fernandez Artidiello Eriberto",
    "wof:placetype":"venue"
},
  "geometry": {"coordinates":[-5.3620138168,43.3459243774],"type":"Point"}
}