{
  "type": "Feature",
  "properties": {
    "iso:country":"ES",
    "sg:address":"Carrer de Abat Oliba, 20",
    "sg:city":"Manresa",
    "sg:orig_category":"Mec\u00c1nico Del Autom\u00d3vil",
    "sg:phone":"+34 938 77 32 45",
    "sg:postcode":"08242",
    "sg:province":"Barcelona",
    "wof:name":"Subirana Safont Lluis",
    "wof:placetype":"venue"
},
  "geometry": {"coordinates":[1.8288969994,41.7329673767],"type":"Point"}
}