{
  "type": "Feature",
  "properties": {
    "addr:full":"Avda Naranjos (los), 7 Utrera Sevilla 41710",
    "addr:postcode":"41710",
    "addr:street":"Avda Naranjos Los",
    "iso:country":"ES",
    "sg:address":"Avda Naranjos (los), 7",
    "sg:city":"Utrera",
    "sg:orig_category":"Caf\u00c9s, Bares, Cervecer\u00cdas",
    "sg:phone":"+34 955 86 24 80",
    "sg:postcode":"41710",
    "sg:province":"Sevilla",
    "wof:name":"Sistelcom-telemensaje S.a.",
    "wof:placetype":"venue"
},
  "geometry": {"coordinates":[-5.7767691612,37.1858482361],"type":"Point"}
}