{
  "type": "Feature",
  "properties": {
    "addr:full":"Barr Ambasaguas, 77 Ambasaguas Vizcaya 48891",
    "addr:housenumber":"77",
    "addr:postcode":"48891",
    "addr:street":"Ambasaguas",
    "iso:country":"ES",
    "sg:address":"Barr Ambasaguas, 77",
    "sg:city":"Ambasaguas",
    "sg:orig_category":"Tractores Agr\u00cdcolas Y Remolques",
    "sg:phone":"+34 946 80 65 12",
    "sg:postcode":"48891",
    "sg:province":"Vizcaya",
    "wof:name":"Maquinaria Agricola Matienzo S.l.",
    "wof:placetype":"venue"
},
  "geometry": {"coordinates":[-3.3572590351,43.2212486267],"type":"Point"}
}