{
  "type": "Feature",
  "properties": {
    "addr:full":"Pque Salvador Castell, 81 Algemesi Valencia 46680",
    "addr:housenumber":"81",
    "addr:postcode":"46680",
    "iso:country":"ES",
    "sg:address":"Pque Salvador Castell, 81",
    "sg:city":"Algemesi",
    "sg:orig_category":"Plomeros",
    "sg:phone":"+34 962 42 12 94",
    "sg:postcode":"46680",
    "sg:province":"Valencia",
    "wof:name":"Estrela Roca Jose Enrique",
    "wof:placetype":"venue"
},
  "geometry": {"coordinates":[-0.4365890026,39.1850318909],"type":"Point"}
}