{
  "type": "Feature",
  "properties": {
    "iso:country":"ES",
    "sg:address":"Calle de Altozano, 2",
    "sg:city":"Hinojos",
    "sg:orig_category":"Alquiler De V\u00cddeo",
    "sg:phone":"+34 959 45 98 98",
    "sg:postcode":"21740",
    "sg:province":"Huelva",
    "wof:name":"Pascual Del Valle Luisa",
    "wof:placetype":"venue"
},
  "geometry": {"coordinates":[-6.378862381,37.2913169861],"type":"Point"}
}