{
  "type": "Feature",
  "properties": {
    "iso:country":"ES",
    "sg:address":"Plaz Zaharra, 1",
    "sg:city":"Lesaka",
    "sg:orig_category":"Ense\u00d1anza, Formaci\u00d3n Profesional: Aprendizaje",
    "sg:phone":"+34 948 63 70 05",
    "sg:postcode":"31770",
    "sg:province":"Navarra",
    "wof:name":"Ayuntamiento De Lesaka",
    "wof:placetype":"venue"
},
  "geometry": {"coordinates":[-1.7040748596,43.2468566895],"type":"Point"}
}