{
  "type": "Feature",
  "properties": {
    "iso:country":"ES",
    "sg:address":"Carrer de Font, 34",
    "sg:city":"Hospitalet Llobregat",
    "sg:orig_category":"Herboristas (al Por Menor)",
    "sg:phone":"+34 934 48 44 31",
    "sg:postcode":"08905",
    "sg:province":"Barcelona",
    "wof:name":"Nu\u00f1ez Perez Orisia",
    "wof:placetype":"venue"
},
  "geometry": {"coordinates":[2.1118919849,41.3718109131],"type":"Point"}
}