{
  "type": "Feature",
  "properties": {
    "iso:country":"ES",
    "sg:address":"Ctra Brillante (del), 50",
    "sg:city":"Hospital Los Morales",
    "sg:orig_category":"Zonas De Acampada, Aparcamiento Para Caravanas",
    "sg:phone":"+34 957 40 38 36",
    "sg:postcode":"14012",
    "sg:province":"C\u00f3rdoba",
    "wof:name":"Promociones Turisticas De Cordoba S.l.",
    "wof:placetype":"venue"
},
  "geometry": {"coordinates":[-4.7873067856,37.9001235962],"type":"Point"}
}