{
  "type": "Feature",
  "properties": {
    "addr:full":"Carrer de Carles Altes, 4 Viladecans Barcelona 08840",
    "addr:housenumber":"4",
    "addr:postcode":"08840",
    "addr:street":"Carrer De Carles Altes",
    "iso:country":"ES",
    "sg:address":"Carrer de Carles Altes, 4",
    "sg:city":"Viladecans",
    "sg:orig_category":"Promotores Constructores",
    "sg:phone":"+34 936 58 37 14",
    "sg:postcode":"08840",
    "sg:province":"Barcelona",
    "wof:name":"Vila-burca Construcciones S.l.",
    "wof:placetype":"venue"
},
  "geometry": {"coordinates":[2.0123150349,41.3216705322],"type":"Point"}
}