{
  "type": "Feature",
  "properties": {
    "addr:full":"Calle de Pedro Herrero, 11 Candas Asturias 33430",
    "addr:housenumber":"11",
    "addr:postcode":"33430",
    "addr:street":"Calle De Pedro Herrero",
    "iso:country":"ES",
    "sg:address":"Calle de Pedro Herrero, 11",
    "sg:city":"Candas",
    "sg:orig_category":"Peluquer\u00cdas, Peluquer\u00cda Mixta",
    "sg:phone":"+34 985 88 48 09",
    "sg:postcode":"33430",
    "sg:province":"Asturias",
    "wof:name":"Nogueira Lopez Maria Dolores",
    "wof:placetype":"venue"
},
  "geometry": {"coordinates":[-5.7635807991,43.5894622803],"type":"Point"}
}