{
  "type": "Feature",
  "properties": {
    "iso:country":"ES",
    "sg:address":"Ctra. Burgos-portugal, Km. 0327,0",
    "sg:city":"Ciudad Rodrigo",
    "sg:orig_category":"Centros Y Asociaciones De Gesti\u00d3n Homologados",
    "sg:phone":"+34 923 46 21 42",
    "sg:postcode":"37500",
    "sg:province":"Salamanca",
    "wof:name":"Blanco H-r S.l.",
    "wof:placetype":"venue"
},
  "geometry": {"coordinates":[-6.5304489136,40.598865509],"type":"Point"}
}