{
  "type": "Feature",
  "properties": {
    "iso:country":"ES",
    "sg:address":"Carr Pintor Sorolla, 9",
    "sg:city":"Burjassot",
    "sg:orig_category":"Chapister\u00cda",
    "sg:phone":"+34 963 64 08 04",
    "sg:postcode":"46100",
    "sg:province":"Valencia",
    "wof:name":"Talleres Mu\u00f1oz Blasco E Hijos S.l.",
    "wof:placetype":"venue"
},
  "geometry": {"coordinates":[-0.4170770049,39.511390686],"type":"Point"}
}