{
  "type": "Feature",
  "properties": {
    "iso:country":"ES",
    "sg:address":"Calle de Camarena, 149",
    "sg:city":"Madrid",
    "sg:orig_category":"Iglesia Cat\u00d3lica",
    "sg:phone":"+34 917 17 87 80",
    "sg:postcode":"28047",
    "sg:province":"Madrid",
    "wof:name":"Parroquia Nuestra Se\u00f1ora De Aluche",
    "wof:placetype":"venue"
},
  "geometry": {"coordinates":[-3.7556419373,40.3899345398],"type":"Point"}
}