{
  "type": "Feature",
  "properties": {
    "addr:full":"Calle de Alcalde Ruy Lopez, S/n Villanueva Cordoba C\u00f3rdoba 14440",
    "addr:housenumber":"s",
    "addr:postcode":"14440",
    "addr:street":"Calle De Alcalde Ruy Lopez;/ N;Cordoba Co\u0301Rdoba",
    "iso:country":"ES",
    "sg:address":"Calle de Alcalde Ruy Lopez, S/n",
    "sg:city":"Villanueva Cordoba",
    "sg:orig_category":"Negocio De Materiales De Construcci\u00d3n",
    "sg:phone":"+34 957 12 21 83",
    "sg:postcode":"14440",
    "sg:province":"C\u00f3rdoba",
    "wof:name":"Hermanos Illescas Rubio S.l.",
    "wof:placetype":"venue"
},
  "geometry": {"coordinates":[-4.630004406,38.3158302307],"type":"Point"}
}