{
  "type": "Feature",
  "properties": {
    "addr:full":"Carr Mercaders, 14 Girona Girona 17004",
    "addr:housenumber":"14",
    "addr:postcode":"17004",
    "addr:street":"Carr Mercaders",
    "iso:country":"ES",
    "sg:address":"Carr Mercaders, 14",
    "sg:city":"Girona",
    "sg:orig_category":"Mercer\u00cda, Lencer\u00cda (al Por Menor)",
    "sg:phone":"+34 972 20 41 72",
    "sg:postcode":"17004",
    "sg:province":"Girona",
    "wof:name":"Hernando Jimeno Matilde",
    "wof:placetype":"venue"
},
  "geometry": {"coordinates":[2.8247709274,41.9839744568],"type":"Point"}
}