{
  "type": "Feature",
  "properties": {
    "iso:country":"ES",
    "sg:address":"Alboreda, S/n",
    "sg:city":"Yecla",
    "sg:orig_category":"Expositores",
    "sg:phone":"+34 968 43 51 85",
    "sg:postcode":"30510",
    "sg:province":"Murcia",
    "wof:name":"Termo Marcos S.l.",
    "wof:placetype":"venue"
},
  "geometry": {"coordinates":[-1.1263689995,38.6143493652],"type":"Point"}
}