{
  "type": "Feature",
  "properties": {
    "addr:full":"Rua Vicedo (de), 32 Marzan Lugo 27780",
    "addr:housenumber":"32",
    "addr:postcode":"27780",
    "addr:street":"Rua Vicedo De",
    "iso:country":"ES",
    "sg:address":"Rua Vicedo (de), 32",
    "sg:city":"Marzan",
    "sg:orig_category":"Contenedores (mercanc\u00cdas)",
    "sg:phone":"+34 982 14 00 30",
    "sg:postcode":"27780",
    "sg:province":"Lugo",
    "wof:name":"Rubi\u00d1os S L",
    "wof:placetype":"venue"
},
  "geometry": {"coordinates":[-7.2613739967,43.5743751526],"type":"Point"}
}