{
  "type": "Feature",
  "properties": {
    "iso:country":"ES",
    "sg:address":"Calle de Perez Oliva, 30",
    "sg:city":"Yebenes",
    "sg:orig_category":"Supermercados Y Hipermercados",
    "sg:phone":"+34 925 32 10 34",
    "sg:postcode":"45470",
    "sg:province":"Toledo",
    "wof:name":"Perez Maroto Emiliano",
    "wof:placetype":"venue"
},
  "geometry": {"coordinates":[-3.8638939857,39.5827713013],"type":"Point"}
}