{
  "type": "Feature",
  "properties": {
    "iso:country":"ES",
    "sg:address":"Carrer de Doctor Salarich, 36",
    "sg:city":"Vic",
    "sg:orig_category":"Asociaciones Y Clubs Deportivos",
    "sg:phone":"+34 938 85 00 28",
    "sg:postcode":"08500",
    "sg:province":"Barcelona",
    "wof:name":"Agrupacion De Pescadores Deportivos De Vich",
    "wof:placetype":"venue"
},
  "geometry": {"coordinates":[2.2571783066,41.9232330322],"type":"Point"}
}