{
  "type": "Feature",
  "properties": {
    "addr:full":"Avda Yeseros (de Los), 97 Valmor-rompecubas Madrid 28340",
    "addr:housenumber":"97",
    "addr:postcode":"28340",
    "addr:street":"Avda Yeseros De Los",
    "iso:country":"ES",
    "sg:address":"Avda Yeseros (de Los), 97",
    "sg:city":"Valmor-rompecubas",
    "sg:orig_category":"Cerrajer\u00cda, Ferrallista",
    "sg:phone":"+34 918 95 65 45",
    "sg:postcode":"28340",
    "sg:province":"Madrid",
    "wof:name":"Dubamar S.l.",
    "wof:placetype":"venue"
},
  "geometry": {"coordinates":[-3.6677899361,40.1646308899],"type":"Point"}
}