{
  "type": "Feature",
  "properties": {
    "iso:country":"ES",
    "sg:address":"Calle de Barcelona, 6",
    "sg:city":"Puerto",
    "sg:orig_category":"Venta, Localizaci\u00d3n, Reparaci\u00d3n De Material E Instrumental M\u00c9dico",
    "sg:phone":"+34 962 69 90 87",
    "sg:postcode":"46520",
    "sg:province":"Valencia",
    "wof:name":"Dental Torres Puerto Sagunto S.l.",
    "wof:placetype":"venue"
},
  "geometry": {"coordinates":[-0.2252462059,39.663898468],"type":"Point"}
}