{
  "type": "Feature",
  "properties": {
    "addr:full":"Carrer de Galileu, 229 Barcelona Barcelona 08028",
    "addr:housenumber":"229",
    "addr:postcode":"08028",
    "addr:street":"Carrer De Galileu",
    "iso:country":"ES",
    "sg:address":"Carrer de Galileu, 229",
    "sg:city":"Barcelona",
    "sg:orig_category":"Comercio De Piezas De Recambio Y De Accesorios De Veh\u00cdculos, Veh\u00cdculos Industriales",
    "sg:phone":"+34 933 30 80 19",
    "sg:postcode":"08028",
    "sg:province":"Barcelona",
    "wof:name":"Oliva Gomez Manuel",
    "wof:placetype":"venue"
},
  "geometry": {"coordinates":[2.1330490112,41.3819923401],"type":"Point"}
}