{
  "type": "Feature",
  "properties": {
    "iso:country":"ES",
    "sg:address":"Calle de Segorbe, 16",
    "sg:city":"Castellon",
    "sg:orig_category":"Carnicer\u00cdas, Carnicer\u00cdas",
    "sg:phone":"+34 964 21 19 59",
    "sg:postcode":"12004",
    "sg:province":"Castell\u00f3n",
    "wof:name":"Hermanos Cervera-99 S.l.",
    "wof:placetype":"venue"
},
  "geometry": {"coordinates":[-0.0402709991,39.9923057556],"type":"Point"}
}