{
  "type": "Feature",
  "properties": {
    "iso:country":"ES",
    "sg:address":"Calle de Mayor, 4",
    "sg:city":"Pozoblanco",
    "sg:orig_category":"Papeler\u00cdas, Librer\u00cdas",
    "sg:phone":"+34 957 77 03 21",
    "sg:postcode":"14400",
    "sg:province":"C\u00f3rdoba",
    "wof:name":"Papeleria Libreria Angel Lopez S.l.",
    "wof:placetype":"venue"
},
  "geometry": {"coordinates":[-4.848072052,38.3780479431],"type":"Point"}
}