{
  "type": "Feature",
  "properties": {
    "addr:full":"Calle de Marques De Cerralbo, 7 Soria Soria 42004",
    "addr:housenumber":"7",
    "addr:postcode":"42004",
    "addr:street":"Calle De Marques De Cerralbo",
    "iso:country":"ES",
    "sg:address":"Calle de Marques De Cerralbo, 7",
    "sg:city":"Soria",
    "sg:orig_category":"Promotores Constructores",
    "sg:phone":"+34 975 22 48 00",
    "sg:postcode":"42004",
    "sg:province":"Soria",
    "wof:name":"Llogary Construcciones S.l.l.",
    "wof:placetype":"venue"
},
  "geometry": {"coordinates":[-2.4778687954,41.7621994019],"type":"Point"}
}