{
  "type": "Feature",
  "properties": {
    "addr:full":"Calle de Nuestra Sra De Nuria, 9 Pozuelo De Alarcon Madrid 28224",
    "addr:housenumber":"9",
    "addr:postcode":"28224",
    "addr:street":"Calle De Nuestra Sra De Nuria",
    "iso:country":"ES",
    "sg:address":"Calle de Nuestra Sra De Nuria, 9",
    "sg:city":"Pozuelo De Alarcon",
    "sg:orig_category":"M\u00c9dicos: Estomatolog\u00cda",
    "sg:phone":"+34 917 15 01 69",
    "sg:postcode":"28224",
    "sg:province":"Madrid",
    "wof:name":"Cervera Pelaez Luis",
    "wof:placetype":"venue"
},
  "geometry": {"coordinates":[-3.7992889881,40.4414520264],"type":"Point"}
}