{
  "type": "Feature",
  "properties": {
    "addr:full":"C/ Alfons I, 18 Puigcerda Girona 17520",
    "addr:housenumber":"18",
    "addr:postcode":"17520",
    "addr:street":"C / Alfons I",
    "iso:country":"ES",
    "sg:address":"C/ Alfons I, 18",
    "sg:city":"Puigcerda",
    "sg:orig_category":"Deportes Y Programas De Aventura",
    "sg:phone":"+34 972 88 11 83",
    "sg:postcode":"17520",
    "sg:province":"Girona",
    "wof:name":"Couloir Extreme S.l.l.",
    "wof:placetype":"venue"
},
  "geometry": {"coordinates":[1.9283289909,42.431930542],"type":"Point"}
}