{
  "type": "Feature",
  "properties": {
    "iso:country":"ES",
    "sg:address":"Calle de Alicante, 5",
    "sg:city":"Getafe",
    "sg:orig_category":"Carnicer\u00cdas, Carnicer\u00cdas",
    "sg:phone":"+34 916 81 54 28",
    "sg:postcode":"28903",
    "sg:province":"Madrid",
    "wof:name":"Hernandez Calvo Tomas",
    "wof:placetype":"venue"
},
  "geometry": {"coordinates":[-3.7204473019,40.312084198],"type":"Point"}
}