{
  "type": "Feature",
  "properties": {
    "addr:full":"Mayor, 9 Atarrabia Navarra 31610",
    "addr:housenumber":"9",
    "addr:postcode":"31610",
    "addr:street":"Mayor",
    "iso:country":"ES",
    "sg:address":"Mayor, 9",
    "sg:city":"Atarrabia",
    "sg:orig_category":"Farmacias",
    "sg:phone":"+34 948 14 86 48",
    "sg:postcode":"31610",
    "sg:province":"Navarra",
    "wof:name":"Erro Azcarate Maria Aranzazu",
    "wof:placetype":"venue"
},
  "geometry": {"coordinates":[-1.6085489988,42.8313407898],"type":"Point"}
}