{
  "type": "Feature",
  "properties": {
    "iso:country":"ES",
    "sg:address":"Crrtra De Huescar, Km. 0001,0",
    "sg:city":"Cullar",
    "sg:orig_category":"Electricidad (montaje, Ensamblaje De Componentes)",
    "sg:phone":"+34 958 73 25 50",
    "sg:postcode":"18850",
    "sg:province":"Granada",
    "wof:name":"Masegosa Martinez Fadrique",
    "wof:placetype":"venue"
},
  "geometry": {"coordinates":[-2.5776090622,37.5830955505],"type":"Point"}
}