{
  "type": "Feature",
  "properties": {
    "iso:country":"ES",
    "sg:address":"Calle de Feria, 29",
    "sg:city":"Albacete",
    "sg:orig_category":"Agencias Y Agentes Comerciales, Representantes",
    "sg:phone":"+34 967 22 02 29",
    "sg:postcode":"02005",
    "sg:province":"Albacete",
    "wof:name":"Carrasco Garces Antolin",
    "wof:placetype":"venue"
},
  "geometry": {"coordinates":[-1.8603659868,38.9958305359],"type":"Point"}
}