{
  "type": "Feature",
  "properties": {
    "addr:full":"Avda Hontanilla, 12 Espinar Segovia 40400",
    "addr:housenumber":"12",
    "addr:postcode":"40400",
    "addr:street":"Avda Hontanilla",
    "iso:country":"ES",
    "sg:address":"Avda Hontanilla, 12",
    "sg:city":"Espinar",
    "sg:orig_category":"Molduras, Junquillos, Listones Y Molduras Perforadas",
    "sg:phone":"+34 921 18 10 25",
    "sg:postcode":"40400",
    "sg:province":"Segovia",
    "wof:name":"Iglesias Martin Jose Maria",
    "wof:placetype":"venue"
},
  "geometry": {"coordinates":[-4.2470521927,40.7178230286],"type":"Point"}
}