{
  "type": "Feature",
  "properties": {
    "iso:country":"ES",
    "sg:address":"Calle de Labastida, 17",
    "sg:city":"Madrid",
    "sg:orig_category":"Artes Gr\u00c1ficas, Artes Pl\u00c1sticas: Material Y Suministros (al Por Menor)",
    "sg:phone":"+34 917 29 42 83",
    "sg:postcode":"28034",
    "sg:province":"Madrid",
    "wof:name":"Pe\u00f1a Aylagas Julian",
    "wof:placetype":"venue"
},
  "geometry": {"coordinates":[-3.6870360374,40.4908981323],"type":"Point"}
}