{
  "type": "Feature",
  "properties": {
    "iso:country":"ES",
    "sg:address":"Cimanes, Km. 0100,0",
    "sg:city":"Villanueva Carrizo",
    "sg:orig_category":"Distribuci\u00d3n De Petr\u00d3leo Y Derivados",
    "sg:phone":"+34 987 35 70 10",
    "sg:postcode":"24270",
    "sg:province":"Le\u00f3n",
    "wof:name":"Calvucrial S.l.",
    "wof:placetype":"venue"
},
  "geometry": {"coordinates":[-5.8275270462,42.584312439],"type":"Point"}
}