{
  "type": "Feature",
  "properties": {
    "addr:full":"Calle de Pelayo, 18 Daimiel Ciudad Real 13250",
    "addr:housenumber":"18",
    "addr:postcode":"13250",
    "addr:street":"Calle De Pelayo",
    "iso:country":"ES",
    "sg:address":"Calle de Pelayo, 18",
    "sg:city":"Daimiel",
    "sg:orig_category":"Empresas De Carpinter\u00cda Met\u00c1lica",
    "sg:phone":"+34 926 85 38 19",
    "sg:postcode":"13250",
    "sg:province":"Ciudad Real",
    "wof:name":"Carpinteria Metalica Gonzalez S.l.",
    "wof:placetype":"venue"
},
  "geometry": {"coordinates":[-3.6179389954,39.0699615479],"type":"Point"}
}