{
  "type": "Feature",
  "properties": {
    "addr:full":"G.v. Marques Del Turia, 59 Valencia Valencia 46005",
    "addr:housenumber":"59",
    "addr:postcode":"46005",
    "addr:street":"Turia",
    "iso:country":"ES",
    "sg:address":"G.v. Marques Del Turia, 59",
    "sg:city":"Valencia",
    "sg:orig_category":"Abogados",
    "sg:phone":"+34 963 52 16 06",
    "sg:postcode":"46005",
    "sg:province":"Valencia",
    "wof:name":"Escriva Garcia Salvador",
    "wof:placetype":"venue"
},
  "geometry": {"coordinates":[-0.3676240146,39.4678268433],"type":"Point"}
}