{
  "type": "Feature",
  "properties": {
    "addr:full":"Carrer de Mila I Fontanals, 11 Sabadell Barcelona 08205",
    "addr:housenumber":"11",
    "addr:postcode":"08205",
    "addr:street":"Carrer De Mila I Fontanals",
    "iso:country":"ES",
    "sg:address":"Carrer de Mila I Fontanals, 11",
    "sg:city":"Sabadell",
    "sg:orig_category":"Transportes Por V\u00cdas Navegables",
    "sg:phone":"+34 937 20 50 65",
    "sg:postcode":"08205",
    "sg:province":"Barcelona",
    "wof:name":"Distribucion De Valijas Disval S.c.c.l.",
    "wof:placetype":"venue"
},
  "geometry": {"coordinates":[2.1039390564,41.5359420776],"type":"Point"}
}