{
  "type": "Feature",
  "properties": {
    "addr:full":"Cami General, S/n S. Antoni Portmany Islas Baleares 07820",
    "addr:postcode":"07820",
    "addr:street":"General S / N S. Antoni Portmany",
    "iso:country":"ES",
    "sg:address":"Cami General, S/n",
    "sg:city":"S. Antoni Portmany",
    "sg:orig_category":"Productores Recolectores, Venta Directa De Vinos",
    "sg:phone":"+34 971 80 33 77",
    "sg:postcode":"07820",
    "sg:province":"Islas Baleares",
    "wof:name":"Can Rich Dei Vuscastell S.l.",
    "wof:placetype":"venue"
},
  "geometry": {"coordinates":[1.3050999641,38.9828414917],"type":"Point"}
}