{
  "type": "Feature",
  "properties": {
    "addr:full":"Calle de Isla Cristina, 4 Paz Murcia 30007",
    "addr:housenumber":"4",
    "addr:postcode":"30007",
    "addr:street":"Calle De Isla",
    "iso:country":"ES",
    "sg:address":"Calle de Isla Cristina, 4",
    "sg:city":"Paz",
    "sg:orig_category":"Discotecas Y Salas De Baile",
    "sg:phone":"+34 968 24 88 93",
    "sg:postcode":"30007",
    "sg:province":"Murcia",
    "wof:name":"Remurocio S.l.",
    "wof:placetype":"venue"
},
  "geometry": {"coordinates":[-1.1142389774,37.9970092773],"type":"Point"}
}