{
  "type": "Feature",
  "properties": {
    "addr:full":"Plaz Palacio, 4 Argamasilla Calatrava Ciudad Real 13440",
    "addr:housenumber":"4",
    "addr:postcode":"13440",
    "addr:street":"Plaz Palacio",
    "iso:country":"ES",
    "sg:address":"Plaz Palacio, 4",
    "sg:city":"Argamasilla Calatrava",
    "sg:orig_category":"Mec\u00c1nico Del Autom\u00d3vil",
    "sg:phone":"+34 926 47 78 77",
    "sg:postcode":"13440",
    "sg:province":"Ciudad Real",
    "wof:name":"Garcia Letrado Romualdo",
    "wof:placetype":"venue"
},
  "geometry": {"coordinates":[-4.0790791512,38.7305603027],"type":"Point"}
}