{
  "type": "Feature",
  "properties": {
    "iso:country":"ES",
    "sg:address":"Carrer de Ciencia, 25",
    "sg:city":"Gava",
    "sg:orig_category":"Fabricaci\u00d3n, Comercio De Flores Y Plantas Artificiales",
    "sg:phone":"+34 936 62 29 25",
    "sg:postcode":"08850",
    "sg:province":"Barcelona",
    "sg:website":"www.liderflor.com",
    "wof:name":"Liderflor S.l.",
    "wof:placetype":"venue"
},
  "geometry": {"coordinates":[2.0163350105,41.3005142212],"type":"Point"}
}