{
  "type": "Feature",
  "properties": {
    "iso:country":"ES",
    "sg:address":"Calle de Doctor Fernando Primo De Rivera, 1",
    "sg:city":"Madrid",
    "sg:orig_category":"Bancos",
    "sg:phone":"+34 914 77 05 50",
    "sg:postcode":"28053",
    "sg:province":"Madrid",
    "wof:name":"Bankinter S.a.",
    "wof:placetype":"venue"
},
  "geometry": {"coordinates":[-3.6653060913,40.39610672],"type":"Point"}
}