{
  "type": "Feature",
  "properties": {
    "iso:country":"ES",
    "sg:address":"Mare Deu Consolacio, 3",
    "sg:city":"Cala D'or",
    "sg:orig_category":"Asesor\u00cda Fiscal Y Jur\u00cddica",
    "sg:phone":"+34 971 64 81 79",
    "sg:postcode":"07660",
    "sg:province":"Islas Baleares",
    "wof:name":"Assesoria Cala D Or C. B.",
    "wof:placetype":"venue"
},
  "geometry": {"coordinates":[3.2307112217,39.3770217896],"type":"Point"}
}