{
  "type": "Feature",
  "properties": {
    "addr:full":"Pl. Abastos, 8 Arjonilla Ja\u00e9n 23750",
    "addr:housenumber":"8",
    "addr:postcode":"23750",
    "addr:street":"Abastos",
    "iso:country":"ES",
    "sg:address":"Pl. Abastos, 8",
    "sg:city":"Arjonilla",
    "sg:orig_category":"Pescader\u00cdas (al Por Menor)",
    "sg:phone":"+34 953 52 01 31",
    "sg:postcode":"23750",
    "sg:province":"Ja\u00e9n",
    "wof:name":"Castillo Alvarez Manuel Del",
    "wof:placetype":"venue"
},
  "geometry": {"coordinates":[-4.1027722359,37.9744949341],"type":"Point"}
}