{
  "type": "Feature",
  "properties": {
    "addr:full":"Avda Mariano Andres, 123 Le\u00f3n Le\u00f3n 24008",
    "addr:housenumber":"123",
    "addr:postcode":"24008",
    "addr:street":"Avda Mariano Andres",
    "iso:country":"ES",
    "sg:address":"Avda Mariano Andres, 123",
    "sg:city":"Le\u00f3n",
    "sg:orig_category":"Carnicer\u00cdas, Carnicer\u00cdas",
    "sg:phone":"+34 987 22 10 56",
    "sg:postcode":"24008",
    "sg:province":"Le\u00f3n",
    "wof:name":"El Negrillon 2002 S.l.",
    "wof:placetype":"venue"
},
  "geometry": {"coordinates":[-5.5693778992,42.6139526367],"type":"Point"}
}