{
  "type": "Feature",
  "properties": {
    "iso:country":"ES",
    "sg:address":"Carrer de Angel Guimera, 5",
    "sg:city":"S. Adria Besos",
    "sg:orig_category":"Imprenta",
    "sg:phone":"+34 934 62 25 40",
    "sg:postcode":"08930",
    "sg:province":"Barcelona",
    "wof:name":"Mastrodi Andre Alfonso",
    "wof:placetype":"venue"
},
  "geometry": {"coordinates":[2.2226190567,41.4290657043],"type":"Point"}
}