{
  "type": "Feature",
  "properties": {
    "addr:full":"Avda Paz (de La), 6 Huesca Huesca 22003",
    "addr:housenumber":"6",
    "addr:postcode":"22003",
    "addr:street":"Avda Paz De La",
    "iso:country":"ES",
    "sg:address":"Avda Paz (de La), 6",
    "sg:city":"Huesca",
    "sg:orig_category":"Prendas Y Chalecos De Punto (al Por Menor)",
    "sg:phone":"+34 974 22 16 88",
    "sg:postcode":"22003",
    "sg:province":"Huesca",
    "wof:name":"Aquilue Valero Jose Carlos",
    "wof:placetype":"venue"
},
  "geometry": {"coordinates":[-0.4158858061,42.1394920349],"type":"Point"}
}