{
  "type": "Feature",
  "properties": {
    "addr:full":"Avda Gran Via, 3 Vigo Pontevedra 36204",
    "addr:housenumber":"3",
    "addr:postcode":"36204",
    "addr:street":"Avda Gran Via",
    "iso:country":"ES",
    "sg:address":"Avda Gran Via, 3",
    "sg:city":"Vigo",
    "sg:orig_category":"Electrodom\u00c9sticos (al Por Menor)",
    "sg:phone":"+34 986 41 63 98",
    "sg:postcode":"36204",
    "sg:province":"Pontevedra",
    "wof:name":"Blanco Cardelle Manuel",
    "wof:placetype":"venue"
},
  "geometry": {"coordinates":[-8.716293335,42.2341308594],"type":"Point"}
}