{
  "type": "Feature",
  "properties": {
    "addr:full":"Calle de Cordoba, 60 Pozoblanco C\u00f3rdoba 14400",
    "addr:housenumber":"60",
    "addr:postcode":"14400",
    "addr:street":"Calle De Cordoba",
    "iso:country":"ES",
    "sg:address":"Calle de Cordoba, 60",
    "sg:city":"Pozoblanco",
    "sg:orig_category":"Pr\u00c9stamos Personales E Hipotecarios",
    "sg:phone":"+34 957 77 06 97",
    "sg:postcode":"14400",
    "sg:province":"C\u00f3rdoba",
    "wof:name":"Hava Garcia Almudena Del Carmen",
    "wof:placetype":"venue"
},
  "geometry": {"coordinates":[-4.8545055389,38.3774833679],"type":"Point"}
}