{
  "type": "Feature",
  "properties": {
    "iso:country":"ES",
    "sg:address":"Av Espanya, 52",
    "sg:city":"Eivissa",
    "sg:orig_category":"Bisuter\u00cda, Joyer\u00cda, Relojer\u00cda (al Por Menor)",
    "sg:phone":"+34 971 39 08 38",
    "sg:postcode":"07800",
    "sg:province":"Islas Baleares",
    "wof:name":"Joyeria Y Relojeria Pitiusa C.b.",
    "wof:placetype":"venue"
},
  "geometry": {"coordinates":[1.4269069433,38.9078903198],"type":"Point"}
}