{
  "type": "Feature",
  "properties": {
    "addr:full":"Carr Circuit Del Llac, S/n Platja De Muro Islas Baleares 07440",
    "addr:housenumber":"s / n",
    "addr:postcode":"07440",
    "addr:street":"Carr Circuit Del Llac",
    "iso:country":"ES",
    "sg:address":"Carr Circuit Del Llac, S/n",
    "sg:city":"Platja De Muro",
    "sg:orig_category":"Productos Qu\u00cdmicos (fabricaci\u00d3n, Al Por Mayor)",
    "sg:phone":"+34 971 89 11 70",
    "sg:postcode":"07440",
    "sg:province":"Islas Baleares",
    "wof:name":"Cedabi S.l.",
    "wof:placetype":"venue"
},
  "geometry": {"coordinates":[3.1117429733,39.8129005432],"type":"Point"}
}