{
  "type": "Feature",
  "properties": {
    "iso:country":"ES",
    "sg:address":"Avda Teresa Pascual, 3",
    "sg:city":"Benasal",
    "sg:orig_category":"Empresas De Desmonte",
    "sg:phone":"+34 964 43 11 02",
    "sg:postcode":"12160",
    "sg:province":"Castell\u00f3n",
    "wof:name":"Hermanos Barreda Tena S.l.",
    "wof:placetype":"venue"
},
  "geometry": {"coordinates":[-0.138112694,40.3784980774],"type":"Point"}
}