{
  "type": "Feature",
  "properties": {
    "addr:full":"Calle de Segorbe, 3 Valencia Valencia 46004",
    "addr:housenumber":"3",
    "addr:postcode":"46004",
    "addr:street":"Calle De Segorbe",
    "iso:country":"ES",
    "sg:address":"Calle de Segorbe, 3",
    "sg:city":"Valencia",
    "sg:orig_category":"Bazares, Art\u00cdculos De Limpieza Y De Cocina (al Por Menor)",
    "sg:phone":"+34 963 41 59 08",
    "sg:postcode":"46004",
    "sg:province":"Valencia",
    "wof:name":"Toure  Mor",
    "wof:placetype":"venue"
},
  "geometry": {"coordinates":[-0.376372993,39.4650993347],"type":"Point"}
}