{
  "type": "Feature",
  "properties": {
    "addr:full":"Pase Gabierrota, 2 Errenteria Guip\u00f9zcoa 20100",
    "addr:housenumber":"2",
    "addr:postcode":"20100",
    "addr:street":"Gabierrota;Guipu\u0300Zcoa",
    "iso:country":"ES",
    "sg:address":"Pase Gabierrota, 2",
    "sg:city":"Errenteria",
    "sg:orig_category":"Masajistas Kinesiterapeutas",
    "sg:phone":"+34 943 52 90 61",
    "sg:postcode":"20100",
    "sg:province":"Guip\u00f9zcoa",
    "wof:name":"Igoa Mari\u00f1elarena Eusebio",
    "wof:placetype":"venue"
},
  "geometry": {"coordinates":[-1.8917740583,43.3100852966],"type":"Point"}
}