{
  "type": "Feature",
  "properties": {
    "iso:country":"ES",
    "sg:address":"Calle de Veracruz, 1",
    "sg:city":"Alora",
    "sg:orig_category":"Quincaller\u00cda (al Por Menor)",
    "sg:phone":"+34 952 49 61 24",
    "sg:postcode":"29500",
    "sg:province":"M\u00e1laga",
    "wof:name":"Hermanas Sanchez-el Pintor S.l.",
    "wof:placetype":"venue"
},
  "geometry": {"coordinates":[-4.7058849335,36.8241271973],"type":"Point"}
}