{
  "type": "Feature",
  "properties": {
    "addr:full":"Calle de Murga, 61 Palmas De Gran Canaria Las Palmas 35003",
    "addr:housenumber":"61",
    "addr:postcode":"35003",
    "addr:street":"Calle De Murga",
    "iso:country":"ES",
    "sg:address":"Calle de Murga, 61",
    "sg:city":"Palmas De Gran Canaria",
    "sg:orig_category":"Cine (producci\u00d3n, Realizaci\u00d3n)",
    "sg:phone":"+34 928 37 35 82",
    "sg:postcode":"35003",
    "sg:province":"Las Palmas",
    "wof:name":"Herrera Perez Francisco Jose",
    "wof:placetype":"venue"
},
  "geometry": {"coordinates":[-15.422334671,28.1099815369],"type":"Point"}
}