{
  "type": "Feature",
  "properties": {
    "addr:full":"Calle de Iglesia, 9 Majadahonda Madrid 28220",
    "addr:housenumber":"9",
    "addr:postcode":"28220",
    "addr:street":"Calle De Iglesia",
    "iso:country":"ES",
    "sg:address":"Calle de Iglesia, 9",
    "sg:city":"Majadahonda",
    "sg:orig_category":"Ense\u00d1anza Variada",
    "sg:phone":"+34 916 39 08 97",
    "sg:postcode":"28220",
    "sg:province":"Madrid",
    "wof:name":"C.estudios Rodesa S.l.",
    "wof:placetype":"venue"
},
  "geometry": {"coordinates":[-3.8734760284,40.4735145569],"type":"Point"}
}