{
  "type": "Feature",
  "properties": {
    "iso:country":"ES",
    "sg:address":"Avda Concordia (de La), 13",
    "sg:city":"Pozo Ca\u00e7ada",
    "sg:orig_category":"Mec\u00c1nico Del Autom\u00d3vil",
    "sg:phone":"+34 967 25 00 18",
    "sg:postcode":"02510",
    "sg:province":"Albacete",
    "wof:name":"Lopez Navarro Juan",
    "wof:placetype":"venue"
},
  "geometry": {"coordinates":[-1.7321920395,38.8035125732],"type":"Point"}
}