{
  "type": "Feature",
  "properties": {
    "addr:full":"Calle de Isabel La Catolica, 2 Valencia Valencia 46004",
    "addr:housenumber":"2",
    "addr:postcode":"46004",
    "addr:street":"Calle De Isabel La Catolica",
    "iso:country":"ES",
    "sg:address":"Calle de Isabel La Catolica, 2",
    "sg:city":"Valencia",
    "sg:orig_category":"Papeler\u00cdas, Librer\u00cdas",
    "sg:phone":"+34 963 51 59 69",
    "sg:postcode":"46004",
    "sg:province":"Valencia",
    "wof:name":"Simo Aguilar Inmaculada",
    "wof:placetype":"venue"
},
  "geometry": {"coordinates":[-0.371100992,39.4694061279],"type":"Point"}
}