{
  "type": "Feature",
  "properties": {
    "iso:country":"ES",
    "sg:address":"Calle de Chicos (los), 11",
    "sg:city":"Ajalvir",
    "sg:orig_category":"Maquinaria Para Industrias Diversas",
    "sg:phone":"+34 918 84 48 48",
    "sg:postcode":"28864",
    "sg:province":"Madrid",
    "wof:name":"Integracion De Servicios En Pintura S.l.",
    "wof:placetype":"venue"
},
  "geometry": {"coordinates":[-3.4784481525,40.5086555481],"type":"Point"}
}