{
  "type": "Feature",
  "properties": {
    "addr:full":"Calle de Constitucion (de La), 3 Alcobendas Madrid 28100",
    "addr:postcode":"28100",
    "addr:street":"Calle De Constitucion De La 3",
    "iso:country":"ES",
    "sg:address":"Calle de Constitucion (de La), 3",
    "sg:city":"Alcobendas",
    "sg:orig_category":"Psic\u00d3logos",
    "sg:phone":"+34 916 51 55 25",
    "sg:postcode":"28100",
    "sg:province":"Madrid",
    "sg:website":"www.areapsicologia.com",
    "wof:name":"Avileo Gutierrez Mercedes",
    "wof:placetype":"venue"
},
  "geometry": {"coordinates":[-3.634147644,40.541305542],"type":"Point"}
}