{
  "type": "Feature",
  "properties": {
    "addr:full":"Ctra. Majadahonda, Km. 0002,6 Pozuelo Madrid 28223",
    "addr:postcode":"28223",
    "addr:street":"Ctra. Majadahonda Km. 0002,6",
    "iso:country":"ES",
    "sg:address":"Ctra. Majadahonda, Km. 0002,6",
    "sg:city":"Pozuelo",
    "sg:orig_category":"Laboratorios Y Cl\u00cdnicas Veterinarias",
    "sg:phone":"+34 913 52 72 56",
    "sg:postcode":"28223",
    "sg:province":"Madrid",
    "wof:name":"Alcoba Hernandez Maria Del Carmen",
    "wof:placetype":"venue"
},
  "geometry": {"coordinates":[-3.8230142593,40.43334198],"type":"Point"}
}