{
  "type": "Feature",
  "properties": {
    "addr:full":"Carrer de Pare Roca, 10 Olot Girona 17800",
    "addr:housenumber":"10",
    "addr:postcode":"17800",
    "addr:street":"Carrer De Pare Roca",
    "iso:country":"ES",
    "sg:address":"Carrer de Pare Roca, 10",
    "sg:city":"Olot",
    "sg:orig_category":"Carnicer\u00cdas, Carnicer\u00cdas",
    "sg:phone":"+34 972 26 59 09",
    "sg:postcode":"17800",
    "sg:province":"Girona",
    "wof:name":"Ventola Ferres Jaime",
    "wof:placetype":"venue"
},
  "geometry": {"coordinates":[2.4834730625,42.1819381714],"type":"Point"}
}