{
  "type": "Feature",
  "properties": {
    "iso:country":"ES",
    "sg:address":"Barr San Bartolome, 11",
    "sg:city":"Axpe-san Bartolome",
    "sg:orig_category":"Centro De Estudios",
    "sg:phone":"+34 946 18 72 66",
    "sg:postcode":"48350",
    "sg:province":"Vizcaya",
    "wof:name":"Ba\u00f1os Vicente Roberto",
    "wof:placetype":"venue"
},
  "geometry": {"coordinates":[-2.7021501064,43.3697471619],"type":"Point"}
}