{
  "type": "Feature",
  "properties": {
    "addr:full":"Calle de Mayor, 44 Madrid Madrid 28013",
    "addr:housenumber":"44",
    "addr:postcode":"madrid;28013",
    "addr:street":"Calle De Mayor",
    "iso:country":"ES",
    "sg:address":"Calle de Mayor, 44",
    "sg:city":"Madrid",
    "sg:orig_category":"Molduras, Junquillos, Listones Y Molduras Perforadas",
    "sg:phone":"+34 915 48 13 31",
    "sg:postcode":"28013",
    "sg:province":"Madrid",
    "wof:name":"Mendez Fernandez Gregoria",
    "wof:placetype":"venue"
},
  "geometry": {"coordinates":[-3.7088360786,40.4160232544],"type":"Point"}
}