{
  "type": "Feature",
  "properties": {
    "iso:country":"ES",
    "sg:address":"Calle de Torredonjimeno, S/n",
    "sg:city":"Arjona",
    "sg:orig_category":"Material Y Herramientas Agr\u00cdcolas",
    "sg:phone":"+34 953 51 87 76",
    "sg:postcode":"23760",
    "sg:province":"Ja\u00e9n",
    "wof:name":"Metaldinamica Agricola E Industrial S.l.l.",
    "wof:placetype":"venue"
},
  "geometry": {"coordinates":[-4.0648889542,37.9366569519],"type":"Point"}
}