{
  "type": "Feature",
  "properties": {
    "iso:country":"ES",
    "sg:address":"Calle de Francia, S/n",
    "sg:city":"Vitoria-gasteiz",
    "sg:orig_category":"Supermercados Y Hipermercados",
    "sg:phone":"+34 945 12 48 71",
    "sg:postcode":"01002",
    "sg:province":"\u00c1lava",
    "wof:name":"Hiper Costa S.l.",
    "wof:placetype":"venue"
},
  "geometry": {"coordinates":[-2.6678938866,42.8474998474],"type":"Point"}
}