{
  "type": "Feature",
  "properties": {
    "iso:country":"ES",
    "sg:address":"Avda Albufera, 32",
    "sg:city":"Madrid",
    "sg:orig_category":"Ropa Para Se\u00d1oras (al Por Menor)",
    "sg:phone":"+34 915 01 45 95",
    "sg:postcode":"28038",
    "sg:province":"Madrid",
    "wof:name":"Nadisar Moda S.l.",
    "wof:placetype":"venue"
},
  "geometry": {"coordinates":[-3.666852951,40.3969841003],"type":"Point"}
}