{
  "type": "Feature",
  "properties": {
    "iso:country":"ES",
    "sg:address":"Ctra Gandia De, 23",
    "sg:city":"Oliva",
    "sg:orig_category":"Molduras, Junquillos, Listones Y Molduras Perforadas",
    "sg:phone":"+34 962 85 17 55",
    "sg:postcode":"46780",
    "sg:province":"Valencia",
    "wof:name":"Vidal Mu\u00f1oz Jose",
    "wof:placetype":"venue"
},
  "geometry": {"coordinates":[-0.1235449985,38.9220848083],"type":"Point"}
}