{
  "type": "Feature",
  "properties": {
    "addr:full":"Avda Benigno Rivera, S/n Lugo Lugo 27003",
    "addr:housenumber":"s / n",
    "addr:postcode":"27003",
    "addr:street":"Avda Benigno Rivera",
    "iso:country":"ES",
    "sg:address":"Avda Benigno Rivera, S/n",
    "sg:city":"Lugo",
    "sg:orig_category":"Bancos",
    "sg:phone":"+34 982 20 71 64",
    "sg:postcode":"27003",
    "sg:province":"Lugo",
    "sg:website":"www.bancogalicia.es",
    "wof:name":"Banco De Galicia",
    "wof:placetype":"venue"
},
  "geometry": {"coordinates":[-7.5751237869,43.036113739],"type":"Point"}
}