{
  "type": "Feature",
  "properties": {
    "iso:country":"ES",
    "sg:address":"Carrer de Vinyar, 56",
    "sg:city":"Barcelona",
    "sg:orig_category":"Carnicer\u00cdas, Carnicer\u00cdas",
    "sg:phone":"+34 933 50 51 02",
    "sg:postcode":"08016",
    "sg:province":"Barcelona",
    "wof:name":"El Romero De Salamanca S.l.",
    "wof:placetype":"venue"
},
  "geometry": {"coordinates":[2.184180975,41.4437561035],"type":"Point"}
}