{
  "type": "Feature",
  "properties": {
    "iso:country":"ES",
    "sg:address":"C/ Antonio Machado, 40",
    "sg:city":"Elche",
    "sg:orig_category":"Confecci\u00d3n De Zapatos",
    "sg:phone":"+34 965 44 98 00",
    "sg:postcode":"03201",
    "sg:province":"Alicante",
    "wof:name":"Rumbo S.a.",
    "wof:placetype":"venue"
},
  "geometry": {"coordinates":[-0.7073349953,38.2623825073],"type":"Point"}
}