{
  "type": "Feature",
  "properties": {
    "addr:full":"Calle de Gomez De Barreda, 16 Ubeda Ja\u00e9n 23400",
    "addr:housenumber":"16",
    "addr:postcode":"23400",
    "addr:street":"Calle De Gomez De Barreda;Jae\u0301N",
    "iso:country":"ES",
    "sg:address":"Calle de Gomez De Barreda, 16",
    "sg:city":"Ubeda",
    "sg:orig_category":"Agricultores, Agricultores",
    "sg:phone":"+34 953 79 38 43",
    "sg:postcode":"23400",
    "sg:province":"Ja\u00e9n",
    "wof:name":"Martinez Granero Antonio",
    "wof:placetype":"venue"
},
  "geometry": {"coordinates":[-3.3764760494,38.0084533691],"type":"Point"}
}