{
  "type": "Feature",
  "properties": {
    "addr:full":"Carrer de Treball, S/n S. Just Desvern Barcelona 08960",
    "addr:housenumber":"s",
    "addr:postcode":"08960",
    "addr:street":"Carrer De Treball;/ N",
    "iso:country":"ES",
    "sg:address":"Carrer de Treball, S/n",
    "sg:city":"S. Just Desvern",
    "sg:orig_category":"Productos Qu\u00cdmicos (fabricaci\u00d3n, Al Por Mayor)",
    "sg:phone":"+34 933 71 82 71",
    "sg:postcode":"08960",
    "sg:province":"Barcelona",
    "sg:website":"www.ashland.com",
    "wof:name":"Iberia Ashland Chemical S.a.",
    "wof:placetype":"venue"
},
  "geometry": {"coordinates":[2.066660881,41.3788337708],"type":"Point"}
}