{
  "type": "Feature",
  "properties": {
    "addr:full":"Pg Maragall, 261 Barcelona Barcelona 08032",
    "addr:housenumber":"261",
    "addr:postcode":"08032",
    "addr:street":"Pg Maragall",
    "iso:country":"ES",
    "sg:address":"Pg Maragall, 261",
    "sg:city":"Barcelona",
    "sg:orig_category":"Abogados",
    "sg:phone":"+34 934 56 51 96",
    "sg:postcode":"08032",
    "sg:province":"Barcelona",
    "wof:name":"Ferreiro Mari\u00f1o Juan Carlos",
    "wof:placetype":"venue"
},
  "geometry": {"coordinates":[2.1736021042,41.4261169434],"type":"Point"}
}