{
  "type": "Feature",
  "properties": {
    "iso:country":"ES",
    "sg:address":"Piscis(bda Villalba), 3",
    "sg:city":"Cartagena",
    "sg:orig_category":"Inmobiliaria (agencias)",
    "sg:phone":"+34 968 50 93 24",
    "sg:postcode":"30205",
    "sg:province":"Murcia",
    "wof:name":"Pellicer Nicolas Juan Antonio",
    "wof:placetype":"venue"
},
  "geometry": {"coordinates":[-1.0042209625,37.608795166],"type":"Point"}
}