{
  "type": "Feature",
  "properties": {
    "addr:full":"Carrer de Santalo, 53 Barcelona Barcelona 08021",
    "addr:housenumber":"53",
    "addr:postcode":"08021",
    "addr:street":"Carrer De Santalo",
    "iso:country":"ES",
    "sg:address":"Carrer de Santalo, 53",
    "sg:city":"Barcelona",
    "sg:orig_category":"Herboristas (al Por Menor)",
    "sg:phone":"+34 934 14 49 33",
    "sg:postcode":"08021",
    "sg:province":"Barcelona",
    "wof:name":"Herbocat S.l.",
    "wof:placetype":"venue"
},
  "geometry": {"coordinates":[2.1444220543,41.3966140747],"type":"Point"}
}