{
  "type": "Feature",
  "properties": {
    "iso:country":"ES",
    "sg:address":"Pl Mossen Jacint Verdaguer, 6",
    "sg:city":"Terrassa",
    "sg:orig_category":"Serigraf\u00cda (material Y Suministros)",
    "sg:phone":"+34 937 84 05 20",
    "sg:postcode":"08221",
    "sg:province":"Barcelona",
    "wof:name":"Fabres Cardona Valentin",
    "wof:placetype":"venue"
},
  "geometry": {"coordinates":[2.0133960247,41.5662117004],"type":"Point"}
}