{
  "type": "Feature",
  "properties": {
    "addr:full":"Avda Hispanidad, 15 Valderrobres Teruel 44580",
    "addr:housenumber":"15",
    "addr:postcode":"44580",
    "addr:street":"Avda Hispanidad",
    "iso:country":"ES",
    "sg:address":"Avda Hispanidad, 15",
    "sg:city":"Valderrobres",
    "sg:orig_category":"Fabricaci\u00d3n De Art\u00cdculos Para Papeler\u00cdas",
    "sg:phone":"+34 978 89 00 77",
    "sg:postcode":"44580",
    "sg:province":"Teruel",
    "wof:name":"Serret Guardia Octavio",
    "wof:placetype":"venue"
},
  "geometry": {"coordinates":[0.1544550061,40.8699455261],"type":"Point"}
}