{
  "type": "Feature",
  "properties": {
    "iso:country":"ES",
    "sg:address":"Calle de Ca\u00d1uelo, 7",
    "sg:city":"Villanueva Cordoba",
    "sg:orig_category":"Farmacias",
    "sg:phone":"+34 957 12 01 56",
    "sg:postcode":"14440",
    "sg:province":"C\u00f3rdoba",
    "wof:name":"Rico Otero Maria Jose",
    "wof:placetype":"venue"
},
  "geometry": {"coordinates":[-4.6266598701,38.3226165771],"type":"Point"}
}