{
  "type": "Feature",
  "properties": {
    "addr:full":"Carr Gracia, 16 Mao Islas Baleares 07702",
    "addr:housenumber":"16",
    "addr:postcode":"07702",
    "addr:street":"Carr Gracia",
    "iso:country":"ES",
    "sg:address":"Carr Gracia, 16",
    "sg:city":"Mao",
    "sg:orig_category":"Teatros Y Salas De Espect\u00c1culos",
    "sg:phone":"+34 971 36 13 62",
    "sg:postcode":"07702",
    "sg:province":"Islas Baleares",
    "wof:name":"Lorenzo Alvarez Francisco",
    "wof:placetype":"venue"
},
  "geometry": {"coordinates":[4.2619109154,39.8876495361],"type":"Point"}
}