{
  "type": "Feature",
  "properties": {
    "addr:full":"Calle de Valle Guadalix (del), 2 San Sebastian De Los Reyes Madrid 28700",
    "addr:housenumber":"2",
    "addr:postcode":"28700",
    "addr:street":"Calle De Valle Guadalix Del",
    "iso:country":"ES",
    "sg:address":"Calle de Valle Guadalix (del), 2",
    "sg:city":"San Sebastian De Los Reyes",
    "sg:orig_category":"Mec\u00c1nico Del Autom\u00d3vil",
    "sg:phone":"+34 916 53 61 63",
    "sg:postcode":"28700",
    "sg:province":"Madrid",
    "wof:name":"Leal Garrido David",
    "wof:placetype":"venue"
},
  "geometry": {"coordinates":[-3.625442028,40.5550079346],"type":"Point"}
}