{
  "type": "Feature",
  "properties": {
    "addr:full":"Calle de Betanzos, 3 Tui Pontevedra 36700",
    "addr:housenumber":"3",
    "addr:postcode":"36700",
    "addr:street":"Calle De Betanzos",
    "iso:country":"ES",
    "sg:address":"Calle de Betanzos, 3",
    "sg:city":"Tui",
    "sg:orig_category":"Peluqueros: De Se\u00d1oras",
    "sg:phone":"+34 986 60 10 68",
    "sg:postcode":"36700",
    "sg:province":"Pontevedra",
    "wof:name":"Peluqueria Sencar C B",
    "wof:placetype":"venue"
},
  "geometry": {"coordinates":[-8.644118309,42.0496177673],"type":"Point"}
}