{
  "type": "Feature",
  "properties": {
    "addr:full":"Ctra Alcantarilla, Km. 0003,0 Nonduermas Murcia 30166",
    "addr:postcode":"30166",
    "addr:street":"Ctra Alcantarilla Km. 0003,0",
    "iso:country":"ES",
    "sg:address":"Ctra Alcantarilla, Km. 0003,0",
    "sg:city":"Nonduermas",
    "sg:orig_category":"Delegados, Agentes De Tr\u00c1nsito, Auxiliares De Transporte Internacional",
    "sg:phone":"+34 968 34 75 73",
    "sg:postcode":"30166",
    "sg:province":"Murcia",
    "wof:name":"Autocares Iberocar S. A.",
    "wof:placetype":"venue"
},
  "geometry": {"coordinates":[-1.1557910442,37.9739494324],"type":"Point"}
}