{
  "type": "Feature",
  "properties": {
    "iso:country":"ES",
    "sg:address":"Calle de Virgen De Los Desamparados, 6",
    "sg:city":"Dos Hermanas",
    "sg:orig_category":"Instalaci\u00d3n De Aspiraci\u00d3n De Gases Y Humos",
    "sg:phone":"+34 955 67 58 85",
    "sg:postcode":"41700",
    "sg:province":"Sevilla",
    "wof:name":"Coantel Telecom S.a.",
    "wof:placetype":"venue"
},
  "geometry": {"coordinates":[-5.9316120148,37.2771530151],"type":"Point"}
}