{
  "type": "Feature",
  "properties": {
    "addr:full":"Plaz San Miguel, 9 Montoro C\u00f3rdoba 14600",
    "addr:housenumber":"9",
    "addr:postcode":"14600",
    "addr:street":"Plaz San Miguel;Co\u0301Rdoba",
    "iso:country":"ES",
    "sg:address":"Plaz San Miguel, 9",
    "sg:city":"Montoro",
    "sg:orig_category":"Molduras, Junquillos, Listones Y Molduras Perforadas",
    "sg:phone":"+34 957 16 09 12",
    "sg:postcode":"14600",
    "sg:province":"C\u00f3rdoba",
    "wof:name":"Moreno Camino Juan Antonio",
    "wof:placetype":"venue"
},
  "geometry": {"coordinates":[-4.3815989494,38.0260391235],"type":"Point"}
}