{
  "type": "Feature",
  "properties": {
    "addr:full":"Calle de Fuster, 63 Alcazares Murcia 30710",
    "addr:housenumber":"63",
    "addr:postcode":"30710",
    "addr:street":"Calle De Fuster",
    "iso:country":"ES",
    "sg:address":"Calle de Fuster, 63",
    "sg:city":"Alcazares",
    "sg:orig_category":"Organismos De Turismo",
    "sg:phone":"+34 968 57 49 94",
    "sg:postcode":"30710",
    "sg:province":"Murcia",
    "sg:website":"www.enmarmenor.net",
    "wof:name":"Asociacion Consorcio Estacion Nautica Mar Menor",
    "wof:placetype":"venue"
},
  "geometry": {"coordinates":[-0.8519775867,37.7384109497],"type":"Point"}
}