{
  "type": "Feature",
  "properties": {
    "addr:full":"Calle de Merced, 2 Cadiz C\u00e1diz 11005",
    "addr:housenumber":"2",
    "addr:postcode":"11005",
    "addr:street":"Calle De Merced",
    "iso:country":"ES",
    "sg:address":"Calle de Merced, 2",
    "sg:city":"Cadiz",
    "sg:orig_category":"Supermercados Y Hipermercados",
    "sg:phone":"+34 956 25 34 62",
    "sg:postcode":"11005",
    "sg:province":"C\u00e1diz",
    "wof:name":"Super Gades S.a.",
    "wof:placetype":"venue"
},
  "geometry": {"coordinates":[-6.2918128967,36.5290756226],"type":"Point"}
}