{
  "type": "Feature",
  "properties": {
    "addr:full":"Errebal Kalea, 24 Eibar Guip\u00f9zcoa 20600",
    "addr:housenumber":"24",
    "addr:postcode":"20600",
    "addr:street":"Errebal Kalea;Guipu\u0300Zcoa",
    "iso:country":"ES",
    "sg:address":"Errebal Kalea, 24",
    "sg:city":"Eibar",
    "sg:orig_category":"M\u00c9dicos: Cardiolog\u00cda Y Afecciones Cardiovasculares",
    "sg:phone":"+34 943 20 33 60",
    "sg:postcode":"20600",
    "sg:province":"Guip\u00f9zcoa",
    "wof:name":"Arrillaga Ibarlucea Manuel",
    "wof:placetype":"venue"
},
  "geometry": {"coordinates":[-2.4683556557,43.1858100891],"type":"Point"}
}