{
  "type": "Feature",
  "properties": {
    "iso:country":"ES",
    "sg:address":"Calle de Eras, S/n",
    "sg:city":"Villafafila",
    "sg:orig_category":"Producci\u00d3n, Venta De Productos De Agricultura Biol\u00d3gica",
    "sg:phone":"+34 980 59 18 18",
    "sg:postcode":"49136",
    "sg:province":"Zamora",
    "wof:name":"Montero Gomez S.a.c.o.o.p.",
    "wof:placetype":"venue"
},
  "geometry": {"coordinates":[-5.6139922142,41.8442878723],"type":"Point"}
}