{
  "type": "Feature",
  "properties": {
    "addr:full":"Pg Garbi, 152 Castelldefels Barcelona 08860",
    "addr:housenumber":"152",
    "addr:postcode":"08860",
    "addr:street":"Pg Garbi",
    "iso:country":"ES",
    "sg:address":"Pg Garbi, 152",
    "sg:city":"Castelldefels",
    "sg:orig_category":"Asilos De Ancianos. Centros Privados",
    "sg:phone":"+34 936 64 39 77",
    "sg:postcode":"08860",
    "sg:province":"Barcelona",
    "wof:name":"Castro Pie S.l.",
    "wof:placetype":"venue"
},
  "geometry": {"coordinates":[1.9733560085,41.2668571472],"type":"Point"}
}