{
  "type": "Feature",
  "properties": {
    "iso:country":"ES",
    "sg:address":"Calle de Toledo, 11",
    "sg:city":"Manzanares",
    "sg:orig_category":"Asociaciones Y Clubs Deportivos",
    "sg:phone":"+34 926 61 00 93",
    "sg:postcode":"13200",
    "sg:province":"Ciudad Real",
    "wof:name":"Carranza Espinosa Pablo",
    "wof:placetype":"venue"
},
  "geometry": {"coordinates":[-3.3696689606,39.0010681152],"type":"Point"}
}