{
  "type": "Feature",
  "properties": {
    "addr:full":"C/ Sant Vicent Ferrer, 56 Alcoi Alicante 03801",
    "addr:housenumber":"56",
    "addr:postcode":"03801",
    "addr:street":"C / Sant Vicent Ferrer",
    "iso:country":"ES",
    "sg:address":"C/ Sant Vicent Ferrer, 56",
    "sg:city":"Alcoi",
    "sg:orig_category":"Bares, Piano",
    "sg:phone":"+34 965 54 65 82",
    "sg:postcode":"03801",
    "sg:province":"Alicante",
    "wof:name":"Abad Martinez Federico",
    "wof:placetype":"venue"
},
  "geometry": {"coordinates":[-0.472621,38.689724],"type":"Point"}
}