{
  "type": "Feature",
  "properties": {
    "iso:country":"ES",
    "sg:address":"Calle de Ibarrekolanda, 17",
    "sg:city":"Bilbao",
    "sg:orig_category":"Cl\u00cdnicas Dentales",
    "sg:phone":"+34 944 76 21 18",
    "sg:postcode":"48015",
    "sg:province":"Vizcaya",
    "wof:name":"Jesus Guerra Azpitarte",
    "wof:placetype":"venue"
},
  "geometry": {"coordinates":[-2.9563724995,43.2744674683],"type":"Point"}
}