{
  "type": "Feature",
  "properties": {
    "addr:full":"Calle de Azorin, 34 Javea Alicante 03730",
    "addr:housenumber":"34",
    "addr:postcode":"03730",
    "addr:street":"Calle De Azorin",
    "iso:country":"ES",
    "sg:address":"Calle de Azorin, 34",
    "sg:city":"Javea",
    "sg:orig_category":"Frutas Y Legumbres Frescas (al Por Mayor)",
    "sg:phone":"+34 966 46 18 06",
    "sg:postcode":"03730",
    "sg:province":"Alicante",
    "wof:name":"Recio Villalba Francisco Jose",
    "wof:placetype":"venue"
},
  "geometry": {"coordinates":[0.1649618,38.7847824097],"type":"Point"}
}