{
  "type": "Feature",
  "properties": {
    "iso:country":"ES",
    "sg:address":"Calle de Ronda Mijares, 54",
    "sg:city":"Castellon",
    "sg:orig_category":"Loter\u00cda Y T\u00d3mbola",
    "sg:phone":"+34 964 20 30 38",
    "sg:postcode":"12002",
    "sg:province":"Castell\u00f3n",
    "wof:name":"Neila Macarro Carmen",
    "wof:placetype":"venue"
},
  "geometry": {"coordinates":[-0.0417400002,39.9835395813],"type":"Point"}
}