{
  "type": "Feature",
  "properties": {
    "addr:full":"Autovia(p Campollano), 65 Albacete Albacete 02006",
    "addr:housenumber":"65",
    "addr:postcode":"02006",
    "addr:street":"Autovia P Campollano",
    "iso:country":"ES",
    "sg:address":"Autovia(p Campollano), 65",
    "sg:city":"Albacete",
    "sg:orig_category":"Agencias Y Agentes Comerciales, Representantes",
    "sg:phone":"+34 967 19 32 75",
    "sg:postcode":"02006",
    "sg:province":"Albacete",
    "wof:name":"Disgavi S.l.",
    "wof:placetype":"venue"
},
  "geometry": {"coordinates":[-2.044303894,39.0605888367],"type":"Point"}
}