{
  "type": "Feature",
  "properties": {
    "addr:full":"Calle de Cruz (la), 28 Nerja M\u00e1laga 29780",
    "addr:housenumber":"28",
    "addr:postcode":"29780",
    "addr:street":"Calle De Cruz La",
    "iso:country":"ES",
    "sg:address":"Calle de Cruz (la), 28",
    "sg:city":"Nerja",
    "sg:orig_category":"Muebles Y Accesorios Para Cocinas Y Cuartos De Ba\u00d1o (al Por Menor)",
    "sg:phone":"+34 952 52 64 60",
    "sg:postcode":"29780",
    "sg:province":"M\u00e1laga",
    "wof:name":"Franco Fernandez Jose",
    "wof:placetype":"venue"
},
  "geometry": {"coordinates":[-3.8776061535,36.7475471497],"type":"Point"}
}