{
  "type": "Feature",
  "properties": {
    "iso:country":"ES",
    "sg:address":"Calle de San Juan, 13",
    "sg:city":"San Vicente De Barakaldo",
    "sg:orig_category":"Establecimientos De Cura, Prevenci\u00d3n Y Readaptaci\u00d3n",
    "sg:phone":"+34 944 78 07 90",
    "sg:postcode":"48901",
    "sg:province":"Vizcaya",
    "wof:name":"Ayuntamiento De Baracaldo",
    "wof:placetype":"venue"
},
  "geometry": {"coordinates":[-2.9864358902,43.2977294922],"type":"Point"}
}