{
  "type": "Feature",
  "properties": {
    "addr:full":"Avda Matias Saenz De Tejada, 3 Fuengirola M\u00e1laga 29640",
    "addr:postcode":"29640",
    "addr:street":"Avda Matias Saenz De Tejada 3;Ma\u0301Laga",
    "iso:country":"ES",
    "sg:address":"Avda Matias Saenz De Tejada, 3",
    "sg:city":"Fuengirola",
    "sg:orig_category":"Abogados",
    "sg:phone":"+34 952 46 43 36",
    "sg:postcode":"29640",
    "sg:province":"M\u00e1laga",
    "wof:name":"Garcia Prado Alfonso",
    "wof:placetype":"venue"
},
  "geometry": {"coordinates":[-4.6228260994,36.5411071777],"type":"Point"}
}