{
  "type": "Feature",
  "properties": {
    "addr:full":"Avda Lancia, 5 Le\u00f3n Le\u00f3n 24004",
    "addr:housenumber":"5",
    "addr:postcode":"24004",
    "addr:street":"Avda Lancia;Leo\u0301N",
    "iso:country":"ES",
    "sg:address":"Avda Lancia, 5",
    "sg:city":"Le\u00f3n",
    "sg:orig_category":"Arquitectos",
    "sg:phone":"+34 987 25 14 07",
    "sg:postcode":"24004",
    "sg:province":"Le\u00f3n",
    "wof:name":"Caballero Guerra Adolfo",
    "wof:placetype":"venue"
},
  "geometry": {"coordinates":[-5.5728650093,42.5936203003],"type":"Point"}
}