{
  "type": "Feature",
  "properties": {
    "addr:full":"Pg Sant Joan Bosco, 57 Barcelona Barcelona 08017",
    "addr:housenumber":"57",
    "addr:postcode":"08017",
    "addr:street":"Pg Sant Joan Bosco",
    "iso:country":"ES",
    "sg:address":"Pg Sant Joan Bosco, 57",
    "sg:city":"Barcelona",
    "sg:orig_category":"Farmacias",
    "sg:phone":"+34 932 03 21 19",
    "sg:postcode":"08017",
    "sg:province":"Barcelona",
    "wof:name":"Cebrian Anaut Maria Jesus",
    "wof:placetype":"venue"
},
  "geometry": {"coordinates":[2.1264019012,41.3951072693],"type":"Point"}
}