{
  "type": "Feature",
  "properties": {
    "iso:country":"ES",
    "sg:address":"Calle de San Clemente, 24",
    "sg:city":"Santa Cruz De Tenerife",
    "sg:orig_category":"Asesor\u00cda De Formaci\u00d3n Y Gesti\u00d3n De Personal",
    "sg:phone":"+34 922 28 74 56",
    "sg:postcode":"38003",
    "sg:province":"Santa Cruz De Tenerife",
    "wof:name":"Asesoria Laboral Gabino Ramos Bethencourt S.l.",
    "wof:placetype":"venue"
},
  "geometry": {"coordinates":[-16.2518596649,28.4696559906],"type":"Point"}
}