{
  "type": "Feature",
  "properties": {
    "iso:country":"ES",
    "sg:address":"Carrer de Sant Lloren\u00c7 De Brindisi, 5",
    "sg:city":"Manresa",
    "sg:orig_category":"Ropa Para Se\u00d1oras (al Por Menor)",
    "sg:phone":"+34 938 74 61 58",
    "sg:postcode":"08241",
    "sg:province":"Barcelona",
    "wof:name":"Suarez Benavides Nati",
    "wof:placetype":"venue"
},
  "geometry": {"coordinates":[1.8341189623,41.7230110168],"type":"Point"}
}