{
  "type": "Feature",
  "properties": {
    "iso:country":"ES",
    "sg:address":"Cividanes, S/n",
    "sg:city":"Serantes",
    "sg:orig_category":"Hoteles",
    "sg:phone":"+34 981 62 85 51",
    "sg:postcode":"15177",
    "sg:province":"La Coru\u00f1a",
    "wof:name":"Albaneve S.l.",
    "wof:placetype":"venue"
},
  "geometry": {"coordinates":[-8.2227516174,43.488319397],"type":"Point"}
}