{
  "type": "Feature",
  "properties": {
    "addr:full":"Las Eras, 9 Campara\u00f1on Soria 42290",
    "addr:housenumber":"9",
    "addr:postcode":"42290",
    "addr:street":"Las Eras",
    "iso:country":"ES",
    "sg:address":"Las Eras, 9",
    "sg:city":"Campara\u00f1on",
    "sg:orig_category":"Maquinaria Para Industrias Diversas",
    "sg:phone":"+34 975 18 05 15",
    "sg:postcode":"42290",
    "sg:province":"Soria",
    "wof:name":"Sanz Gonzalez Ramiro",
    "wof:placetype":"venue"
},
  "geometry": {"coordinates":[-2.5800459385,41.7056808472],"type":"Point"}
}