{
  "type": "Feature",
  "properties": {
    "iso:country":"ES",
    "sg:address":"Pase Reina Cristina, 11",
    "sg:city":"Madrid",
    "sg:orig_category":"Psic\u00d3logos",
    "sg:phone":"+34 915 52 00 06",
    "sg:postcode":"28014",
    "sg:province":"Madrid",
    "wof:name":"Delgado Gil Maria Victoria",
    "wof:placetype":"venue"
},
  "geometry": {"coordinates":[-3.682612896,40.4070091248],"type":"Point"}
}