{
  "type": "Feature",
  "properties": {
    "iso:country":"ES",
    "sg:address":"Calle de Principe De Asturias, 20",
    "sg:city":"Yuncos",
    "sg:orig_category":"Peluqueros: De Se\u00d1oras",
    "sg:phone":"+34 925 53 76 26",
    "sg:postcode":"45210",
    "sg:province":"Toledo",
    "wof:name":"Garcia Sanchez Concepcion",
    "wof:placetype":"venue"
},
  "geometry": {"coordinates":[-3.8764190674,40.0890197754],"type":"Point"}
}