{
  "type": "Feature",
  "properties": {
    "addr:full":"Calle de Coso, 16 Zaragoza Zaragoza 50004",
    "addr:housenumber":"16",
    "addr:postcode":"50004",
    "addr:street":"Calle De Coso",
    "iso:country":"ES",
    "sg:address":"Calle de Coso, 16",
    "sg:city":"Zaragoza",
    "sg:orig_category":"Centros Empresariales",
    "sg:phone":"+34 976 23 24 51",
    "sg:postcode":"50004",
    "sg:province":"Zaragoza",
    "wof:name":"Consultores De Planeamiento Y Gestion Urbanistica S.cv.",
    "wof:placetype":"venue"
},
  "geometry": {"coordinates":[-0.8837326169,41.6538772583],"type":"Point"}
}