{
  "type": "Feature",
  "properties": {
    "addr:full":"Calle de Oslo, 21 Toledo Toledo 45005",
    "addr:housenumber":"21",
    "addr:postcode":"45005",
    "addr:street":"Calle De Oslo",
    "iso:country":"ES",
    "sg:address":"Calle de Oslo, 21",
    "sg:city":"Toledo",
    "sg:orig_category":"M\u00c9dicos: Estomatolog\u00cda",
    "sg:phone":"+34 925 21 06 47",
    "sg:postcode":"45005",
    "sg:province":"Toledo",
    "sg:website":"www.paginasamarillas.es",
    "wof:name":"Porras Colmenares Nora Eugenia",
    "wof:placetype":"venue"
},
  "geometry": {"coordinates":[-4.0248031616,39.8733825684],"type":"Point"}
}