{
  "type": "Feature",
  "properties": {
    "iso:country":"ES",
    "sg:address":"Avenida De La Vera, 102",
    "sg:city":"Villanueva Vera",
    "sg:orig_category":"Bancos",
    "sg:phone":"+34 927 56 61 15",
    "sg:postcode":"10470",
    "sg:province":"C\u00e1ceres",
    "wof:name":"Banco Caixa Geral S.a.",
    "wof:placetype":"venue"
},
  "geometry": {"coordinates":[-5.4650230408,40.1292266846],"type":"Point"}
}