{
  "type": "Feature",
  "properties": {
    "addr:full":"Martixe De Abaixo, 15 Martixe Pontevedra 36546",
    "addr:housenumber":"15",
    "addr:postcode":"36546",
    "addr:street":"Abaixo",
    "iso:country":"ES",
    "sg:address":"Martixe De Abaixo, 15",
    "sg:city":"Martixe",
    "sg:orig_category":"Maquinaria Para Industrias Diversas",
    "sg:phone":"+34 986 58 56 51",
    "sg:postcode":"36546",
    "sg:province":"Pontevedra",
    "wof:name":"Excavaciones Benito S.l.",
    "wof:placetype":"venue"
},
  "geometry": {"coordinates":[-8.278670311,42.7603225708],"type":"Point"}
}