{
  "type": "Feature",
  "properties": {
    "iso:country":"ES",
    "sg:address":"Avda Tomas Roca Bosch, S/n",
    "sg:city":"Puerto Rico",
    "sg:orig_category":"Restaurantes",
    "sg:phone":"+34 928 56 07 83",
    "sg:postcode":"35130",
    "sg:province":"Las Palmas",
    "wof:name":"Amadeus Trading S.l.",
    "wof:placetype":"venue"
},
  "geometry": {"coordinates":[-15.7079524994,27.7907733917],"type":"Point"}
}