{
  "type": "Feature",
  "properties": {
    "addr:full":"Avda J. Solis Ruiz, 49 Cabra C\u00f3rdoba 14940",
    "addr:housenumber":"49",
    "addr:postcode":"14940",
    "addr:street":"Avda J. Solis Ruiz;Co\u0301Rdoba",
    "iso:country":"ES",
    "sg:address":"Avda J. Solis Ruiz, 49",
    "sg:city":"Cabra",
    "sg:orig_category":"Cajas De Ahorro",
    "sg:phone":"+34 957 52 25 12",
    "sg:postcode":"14940",
    "sg:province":"C\u00f3rdoba",
    "sg:website":"www.lacaixa.es",
    "wof:name":"Caixa D'estalvis I Pensions De Barcelona",
    "wof:placetype":"venue"
},
  "geometry": {"coordinates":[-4.4433588982,37.4731063843],"type":"Point"}
}