{
  "type": "Feature",
  "properties": {
    "addr:full":"Calle de Bailen, 28 Albacete Albacete 02006",
    "addr:housenumber":"28",
    "addr:postcode":"02006",
    "addr:street":"Calle De Bailen",
    "iso:country":"ES",
    "sg:address":"Calle de Bailen, 28",
    "sg:city":"Albacete",
    "sg:orig_category":"Promotores Constructores",
    "sg:phone":"+34 967 50 02 30",
    "sg:postcode":"02006",
    "sg:province":"Albacete",
    "wof:name":"Estructuras Al Basit S.l.",
    "wof:placetype":"venue"
},
  "geometry": {"coordinates":[-1.8738472462,38.9976005554],"type":"Point"}
}