{
  "type": "Feature",
  "properties": {
    "iso:country":"ES",
    "sg:address":"Pase Castellana, 178",
    "sg:city":"Madrid",
    "sg:orig_category":"Inmobiliaria (agencias)",
    "sg:phone":"+34 913 50 42 00",
    "sg:postcode":"28046",
    "sg:province":"Madrid",
    "wof:name":"Zonagest S.l.",
    "wof:placetype":"venue"
},
  "geometry": {"coordinates":[-3.6892876625,40.460975647],"type":"Point"}
}