{
  "type": "Feature",
  "properties": {
    "iso:country":"ES",
    "sg:address":"Calle de Illescas, 69",
    "sg:city":"Madrid",
    "sg:orig_category":"Artes Gr\u00c1ficas, Artes Pl\u00c1sticas (curso)",
    "sg:phone":"+34 915 18 65 83",
    "sg:postcode":"28024",
    "sg:province":"Madrid",
    "wof:name":"Calvo Sanchez Jose",
    "wof:placetype":"venue"
},
  "geometry": {"coordinates":[-3.7632288933,40.3949317932],"type":"Point"}
}