{
  "type": "Feature",
  "properties": {
    "addr:full":"Calle de Plana, 4 Murchante Navarra 31521",
    "addr:housenumber":"4",
    "addr:postcode":"31521",
    "addr:street":"Calle De Plana",
    "iso:country":"ES",
    "sg:address":"Calle de Plana, 4",
    "sg:city":"Murchante",
    "sg:orig_category":"Producci\u00d3n, Distribuci\u00d3n De Electricidad",
    "sg:phone":"+34 948 83 84 96",
    "sg:postcode":"31521",
    "sg:province":"Navarra",
    "wof:name":"Simon Jarauta Jose",
    "wof:placetype":"venue"
},
  "geometry": {"coordinates":[-1.6562520266,42.0308761597],"type":"Point"}
}