{
  "type": "Feature",
  "properties": {
    "iso:country":"ES",
    "sg:address":"Calle de Andres Torrejon, 17",
    "sg:city":"Madrid",
    "sg:orig_category":"Mec\u00c1nico Del Autom\u00d3vil",
    "sg:phone":"+34 915 51 86 84",
    "sg:postcode":"28014",
    "sg:province":"Madrid",
    "wof:name":"Talleres Alpi S.a.",
    "wof:placetype":"venue"
},
  "geometry": {"coordinates":[-3.6824450493,40.4078102112],"type":"Point"}
}