{
  "type": "Feature",
  "properties": {
    "iso:country":"ES",
    "sg:address":"Calle de Santo Domingo, 62",
    "sg:city":"Sanlucar De Barrameda",
    "sg:orig_category":"Complementos De Vestir (al Por Menor)",
    "sg:phone":"+34 956 96 03 41",
    "sg:postcode":"11540",
    "sg:province":"C\u00e1diz",
    "wof:name":"Ortega",
    "wof:placetype":"venue"
},
  "geometry": {"coordinates":[-6.3498449326,36.7805862427],"type":"Point"}
}