{
  "type": "Feature",
  "properties": {
    "addr:full":"Calle de Conde De Robledo, 4 Cordoba C\u00f3rdoba 14008",
    "addr:housenumber":"4",
    "addr:postcode":"14008",
    "addr:street":"Calle De Conde De Robledo;Co\u0301Rdoba",
    "iso:country":"ES",
    "sg:address":"Calle de Conde De Robledo, 4",
    "sg:city":"Cordoba",
    "sg:orig_category":"Cajas De Ahorro",
    "sg:phone":"+34 957 49 25 29",
    "sg:postcode":"14008",
    "sg:province":"C\u00f3rdoba",
    "sg:website":"www.cajabadajoz.es",
    "wof:name":"Caja De Badajoz",
    "wof:placetype":"venue"
},
  "geometry": {"coordinates":[-4.7817177773,37.886390686],"type":"Point"}
}