{
  "type": "Feature",
  "properties": {
    "addr:full":"Calle de Zacatin, 11 Pinos-puente Granada 18240",
    "addr:housenumber":"11",
    "addr:postcode":"18240",
    "addr:street":"Calle De Zacatin",
    "iso:country":"ES",
    "sg:address":"Calle de Zacatin, 11",
    "sg:city":"Pinos-puente",
    "sg:classifiers":[
        {
            "category":"Autos & Motor Vehicles",
            "subcategory":"Automobile Sales",
            "type":"Retail Goods"
        }
    ],
    "sg:phone":"+34 958 45 20 89",
    "sg:postcode":"18240",
    "sg:province":"Granada",
    "wof:name":"Autoescuela Jimenez Molina S.l.",
    "wof:placetype":"venue"
},
  "geometry": {"coordinates":[-3.7491168976,37.2503967285],"type":"Point"}
}