{
  "type": "Feature",
  "properties": {
    "iso:country":"ES",
    "sg:address":"Avda Espa\u00d1a, 157",
    "sg:city":"Segorbe",
    "sg:orig_category":"Negocio De Materiales De Construcci\u00d3n",
    "sg:phone":"+34 964 13 20 04",
    "sg:postcode":"12400",
    "sg:province":"Castell\u00f3n",
    "wof:name":"Chavarria Materiales De Construccion S.l.",
    "wof:placetype":"venue"
},
  "geometry": {"coordinates":[-0.4934689999,39.8479385376],"type":"Point"}
}