{
  "type": "Feature",
  "properties": {
    "iso:country":"ES",
    "sg:address":"Calle de Gabriel Celaya, 1",
    "sg:city":"Zaragoza",
    "sg:orig_category":"Peluqueros: De Se\u00d1oras",
    "sg:phone":"+34 976 52 71 39",
    "sg:postcode":"50015",
    "sg:province":"Zaragoza",
    "wof:name":"Mariano Insa Peluquero S.l.",
    "wof:placetype":"venue"
},
  "geometry": {"coordinates":[-0.8862919807,41.6703948975],"type":"Point"}
}