{
  "type": "Feature",
  "properties": {
    "iso:country":"ES",
    "sg:address":"Calle de Compa\u00d1ia, 1",
    "sg:city":"Salamanca",
    "sg:orig_category":"Art\u00cdculos De Regalo (al Por Menor)",
    "sg:phone":"+34 923 21 82 49",
    "sg:postcode":"37002",
    "sg:province":"Salamanca",
    "wof:name":"Calama Criado Maria Carmen",
    "wof:placetype":"venue"
},
  "geometry": {"coordinates":[-5.6664628983,40.9634475708],"type":"Point"}
}