{
  "type": "Feature",
  "properties": {
    "iso:country":"ES",
    "sg:address":"Calle de Hoya Del Molino, 6",
    "sg:city":"Lucena",
    "sg:orig_category":"Mensajer\u00cda Express, Portes Internacionales",
    "sg:phone":"+34 957 59 13 71",
    "sg:postcode":"14900",
    "sg:province":"C\u00f3rdoba",
    "wof:name":"Merval Mensajeros S.l.",
    "wof:placetype":"venue"
},
  "geometry": {"coordinates":[-4.4893488884,37.4063987732],"type":"Point"}
}