{
  "type": "Feature",
  "properties": {
    "iso:country":"ES",
    "sg:address":"Calle de Alicante, 10",
    "sg:city":"Riba-roja Turia",
    "sg:orig_category":"Promotores Constructores",
    "sg:phone":"+34 961 65 34 47",
    "sg:postcode":"46190",
    "sg:province":"Valencia",
    "wof:name":"Construcciones Ribatur S.l.",
    "wof:placetype":"venue"
},
  "geometry": {"coordinates":[-0.5809473991,39.5510292053],"type":"Point"}
}