{
  "type": "Feature",
  "properties": {
    "addr:full":"Calle de Jorge Juan, 15 Cartagena Murcia 30204",
    "addr:housenumber":"15",
    "addr:postcode":"30204",
    "addr:street":"Calle De Jorge Juan",
    "iso:country":"ES",
    "sg:address":"Calle de Jorge Juan, 15",
    "sg:city":"Cartagena",
    "sg:orig_category":"Caf\u00c9s, Bares, Cervecer\u00cdas",
    "sg:phone":"+34 968 31 54 00",
    "sg:postcode":"30204",
    "sg:province":"Murcia",
    "wof:name":"Pi\u00f1ero Martinez Pedro",
    "wof:placetype":"venue"
},
  "geometry": {"coordinates":[-0.9948340058,37.6142501831],"type":"Point"}
}