{
  "type": "Feature",
  "properties": {
    "addr:full":"Via Sant Ignasi, 67 Manresa Barcelona 08241",
    "addr:housenumber":"67",
    "addr:postcode":"08241",
    "addr:street":"Via Sant Ignasi",
    "iso:country":"ES",
    "sg:address":"Via Sant Ignasi, 67",
    "sg:city":"Manresa",
    "sg:orig_category":"Mec\u00c1nico Del Autom\u00d3vil",
    "sg:phone":"+34 938 73 32 95",
    "sg:postcode":"08241",
    "sg:province":"Barcelona",
    "wof:name":"Ca\u00f1izares Olmos Tomas",
    "wof:placetype":"venue"
},
  "geometry": {"coordinates":[1.830728054,41.7255363464],"type":"Point"}
}