{
  "type": "Feature",
  "properties": {
    "addr:full":"Pase Oriamendi De, 64 A\u00d1orga Guip\u00f9zcoa 20009",
    "addr:housenumber":"an\u0303orga",
    "addr:postcode":"20009",
    "addr:street":"Oriamendi;Guipu\u0300Zcoa",
    "iso:country":"ES",
    "sg:address":"Pase Oriamendi De, 64",
    "sg:city":"A\u00d1orga",
    "sg:orig_category":"Mec\u00c1nico Del Autom\u00d3vil",
    "sg:phone":"+34 943 30 83 60",
    "sg:postcode":"20009",
    "sg:province":"Guip\u00f9zcoa",
    "wof:name":"Lizarazu Egia Xabier",
    "wof:placetype":"venue"
},
  "geometry": {"coordinates":[-1.9803700447,43.2960700989],"type":"Point"}
}