{
  "type": "Feature",
  "properties": {
    "iso:country":"ES",
    "sg:address":"C/ Gabriel Miro, 23",
    "sg:city":"Elche",
    "sg:orig_category":"Asesor\u00cda Sobre Comunicaci\u00d3n De Empresas",
    "sg:phone":"+34 966 67 29 31",
    "sg:postcode":"03201",
    "sg:province":"Alicante",
    "wof:name":"Crisol Arjona Eva Maria",
    "wof:placetype":"venue"
},
  "geometry": {"coordinates":[-0.7025129795,38.2640953064],"type":"Point"}
}