{
  "type": "Feature",
  "properties": {
    "addr:full":"Pase San Francisco De Sales, 29 Madrid Madrid 28003",
    "addr:housenumber":"29",
    "addr:postcode":"madrid;28003",
    "addr:street":"Francisco De Sales",
    "iso:country":"ES",
    "sg:address":"Pase San Francisco De Sales, 29",
    "sg:city":"Madrid",
    "sg:orig_category":"Cl\u00cdnicas Dentales",
    "sg:phone":"+34 915 44 83 38",
    "sg:postcode":"28003",
    "sg:province":"Madrid",
    "wof:name":"Centro De Implantologia Estetica Y Periodoncia S.l.",
    "wof:placetype":"venue"
},
  "geometry": {"coordinates":[-3.7138259411,40.4419441223],"type":"Point"}
}