{
  "type": "Feature",
  "properties": {
    "addr:full":"Rbla Celler, 25 S. Cugat Valles Barcelona 08172",
    "addr:housenumber":"25",
    "addr:postcode":"08172",
    "addr:street":"Rbla Celler;S. Cugat Valles Barcelona",
    "iso:country":"ES",
    "sg:address":"Rbla Celler, 25",
    "sg:city":"S. Cugat Valles",
    "sg:orig_category":"Droguer\u00cdas (al Por Menor)",
    "sg:phone":"+34 936 75 30 52",
    "sg:postcode":"08172",
    "sg:province":"Barcelona",
    "wof:name":"Rodriguez Pordoy Jesus Angel",
    "wof:placetype":"venue"
},
  "geometry": {"coordinates":[2.0848019123,41.4712982178],"type":"Point"}
}