{
  "type": "Feature",
  "properties": {
    "addr:full":"Calle de Principe De Vergara, 112 Madrid Madrid 28002",
    "addr:housenumber":"112",
    "addr:postcode":"28002",
    "addr:street":"Calle De Principe De Vergara",
    "iso:country":"ES",
    "sg:address":"Calle de Principe De Vergara, 112",
    "sg:city":"Madrid",
    "sg:orig_category":"Inform\u00c1tica: Material Y Suministros",
    "sg:phone":"+34 915 61 31 75",
    "sg:postcode":"28002",
    "sg:province":"Madrid",
    "wof:name":"Itway Iberica S.l.",
    "wof:placetype":"venue"
},
  "geometry": {"coordinates":[-3.67867589,40.4391746521],"type":"Point"}
}