{
  "type": "Feature",
  "properties": {
    "addr:full":"Calle de Vicente Andres Estelles, 2 Alaquas Valencia 46970",
    "addr:housenumber":"2",
    "addr:postcode":"46970",
    "addr:street":"Calle De Vicente Andres Estelles",
    "iso:country":"ES",
    "sg:address":"Calle de Vicente Andres Estelles, 2",
    "sg:city":"Alaquas",
    "sg:orig_category":"Lencer\u00cda Femenina, Corseter\u00cda, Trajes De Ba\u00d1o (al Por Menor)",
    "sg:phone":"+34 961 50 01 93",
    "sg:postcode":"46970",
    "sg:province":"Valencia",
    "wof:name":"Castellanos Jimenez Maria Del Carmen",
    "wof:placetype":"venue"
},
  "geometry": {"coordinates":[-0.4536739886,39.4553184509],"type":"Point"}
}