{
  "type": "Feature",
  "properties": {
    "iso:country":"ES",
    "sg:address":"Avda Islas Canarias, 14",
    "sg:city":"Costa Teguise",
    "sg:orig_category":"Alquiler De Veh\u00cdculos: Turismos Y Utilitarios",
    "sg:phone":"+34 928 59 12 94",
    "sg:postcode":"35509",
    "sg:province":"Las Palmas",
    "sg:website":"www.autospluscar.com",
    "wof:name":"Anibal Y German S.l.",
    "wof:placetype":"venue"
},
  "geometry": {"coordinates":[-13.4868221283,29.0012302399],"type":"Point"}
}