{
  "type": "Feature",
  "properties": {
    "iso:country":"ES",
    "sg:address":"Carretera, Km. 0026,0",
    "sg:city":"Salinas",
    "sg:orig_category":"Hoteles",
    "sg:phone":"+34 974 50 40 01",
    "sg:postcode":"22365",
    "sg:province":"Huesca",
    "wof:name":"Meson De Salinas S.l",
    "wof:placetype":"venue"
},
  "geometry": {"coordinates":[0.1910520047,42.6644706726],"type":"Point"}
}