{
  "type": "Feature",
  "properties": {
    "iso:country":"ES",
    "sg:address":"Partida Senijola, 2",
    "sg:city":"Benissa",
    "sg:orig_category":"Equitaci\u00d3n Y Centros De H\u00cdpica",
    "sg:phone":"+34 965 73 18 32",
    "sg:postcode":"03720",
    "sg:province":"Alicante",
    "sg:website":"www.cts.es/users/hipica",
    "wof:name":"Club Hipico Benissa",
    "wof:placetype":"venue"
},
  "geometry": {"coordinates":[0.050774999,38.7144584656],"type":"Point"}
}