{
  "type": "Feature",
  "properties": {
    "iso:country":"ES",
    "sg:address":"Aritz-bidea, 18",
    "sg:city":"Mungia",
    "sg:orig_category":"Laboratorios Y Cl\u00cdnicas Veterinarias",
    "sg:phone":"+34 946 74 42 51",
    "sg:postcode":"48100",
    "sg:province":"Vizcaya",
    "wof:name":"Analitica Veterinaria Mungivet S.l.",
    "wof:placetype":"venue"
},
  "geometry": {"coordinates":[-2.8394706249,43.3530883789],"type":"Point"}
}