{
  "type": "Feature",
  "properties": {
    "addr:full":"Avda Ferral, 11 Villabalter Le\u00f3n 24010",
    "addr:housenumber":"11",
    "addr:postcode":"24010",
    "addr:street":"Avda Ferral;Leo\u0301N",
    "iso:country":"ES",
    "sg:address":"Avda Ferral, 11",
    "sg:city":"Villabalter",
    "sg:orig_category":"Doctores En Medicina",
    "sg:phone":"+34 987 84 63 55",
    "sg:postcode":"24010",
    "sg:province":"Le\u00f3n",
    "wof:name":"Instanbouli Instanbouli Abdul Kader",
    "wof:placetype":"venue"
},
  "geometry": {"coordinates":[-5.6204690933,42.6200141907],"type":"Point"}
}