{
  "type": "Feature",
  "properties": {
    "iso:country":"ES",
    "sg:address":"Pg Fabra I Puig, 441",
    "sg:city":"Barcelona",
    "sg:orig_category":"Peluqueros: De Se\u00d1oras",
    "sg:phone":"+34 934 27 87 45",
    "sg:postcode":"08042",
    "sg:province":"Barcelona",
    "wof:name":"Romero Gomez Maria Del Carmen",
    "wof:placetype":"venue"
},
  "geometry": {"coordinates":[2.1655960083,41.4386329651],"type":"Point"}
}