{
  "type": "Feature",
  "properties": {
    "addr:full":"Rua San Francisco (de), 17 Ourense Ourense 32005",
    "addr:housenumber":"17",
    "addr:postcode":"32005",
    "addr:street":"Rua San Francisco De",
    "iso:country":"ES",
    "sg:address":"Rua San Francisco (de), 17",
    "sg:city":"Ourense",
    "sg:orig_category":"Aguas (distribuci\u00d3n, Servicios)",
    "sg:phone":"+34 988 22 02 37",
    "sg:postcode":"32005",
    "sg:province":"Ourense",
    "wof:name":"Aquagest S.a.",
    "wof:placetype":"venue"
},
  "geometry": {"coordinates":[-7.861123085,42.3376922607],"type":"Point"}
}