{
  "type": "Feature",
  "properties": {
    "iso:country":"ES",
    "sg:address":"Rua A. Xan Carballeira, 16",
    "sg:city":"Bueu",
    "sg:orig_category":"Peluqueros: De Se\u00d1oras",
    "sg:phone":"+34 986 32 09 86",
    "sg:postcode":"36930",
    "sg:province":"Pontevedra",
    "wof:name":"Estevez Martinez Jose",
    "wof:placetype":"venue"
},
  "geometry": {"coordinates":[-8.7835788727,42.3259315491],"type":"Point"}
}