{
  "type": "Feature",
  "properties": {
    "iso:country":"ES",
    "sg:address":"Calle de Ca\u00d1adilla, 6",
    "sg:city":"Rozas De Madrid",
    "sg:orig_category":"Fabricaci\u00d3n, Importaci\u00d3n De Material Y Sistemas De Telecomunicaciones",
    "sg:phone":"+34 916 40 61 65",
    "sg:postcode":"28230",
    "sg:province":"Madrid",
    "wof:name":"V Y D Con S.l.",
    "wof:placetype":"venue"
},
  "geometry": {"coordinates":[-3.8707897663,40.4894676208],"type":"Point"}
}