{
  "type": "Feature",
  "properties": {
    "iso:country":"ES",
    "sg:address":"Pol Ind, 5",
    "sg:city":"Puerto Lumbreras",
    "sg:orig_category":"Mec\u00c1nico Del Autom\u00d3vil",
    "sg:phone":"+34 968 40 13 57",
    "sg:postcode":"30890",
    "sg:province":"Murcia",
    "wof:name":"Beycris S.l.l.",
    "wof:placetype":"venue"
},
  "geometry": {"coordinates":[-1.9274189472,37.6259460449],"type":"Point"}
}