{
  "type": "Feature",
  "properties": {
    "addr:full":"Carrer de Puigcerda, 245 Barcelona Barcelona 08020",
    "addr:housenumber":"245",
    "addr:postcode":"08020",
    "addr:street":"Carrer De Puigcerda",
    "iso:country":"ES",
    "sg:address":"Carrer de Puigcerda, 245",
    "sg:city":"Barcelona",
    "sg:orig_category":"Persianas Interiores, Exteriores",
    "sg:phone":"+34 933 14 50 24",
    "sg:postcode":"08020",
    "sg:province":"Barcelona",
    "wof:name":"Lopez Pascual Enrique",
    "wof:placetype":"venue"
},
  "geometry": {"coordinates":[2.203263998,41.419883728],"type":"Point"}
}