{
  "type": "Feature",
  "properties": {
    "iso:country":"ES",
    "sg:address":"Calle de Larga, 1",
    "sg:city":"Cabaco",
    "sg:orig_category":"Estancos",
    "sg:phone":"+34 923 45 40 50",
    "sg:postcode":"37620",
    "sg:province":"Salamanca",
    "wof:name":"Flechl Scherz Wilelm",
    "wof:placetype":"venue"
},
  "geometry": {"coordinates":[-6.1272110939,40.5653610229],"type":"Point"}
}