{
  "type": "Feature",
  "properties": {
    "iso:country":"ES",
    "sg:address":"Calle de Vigo, 4",
    "sg:city":"Armilla",
    "sg:classifiers":[
        {
            "category":"Taxi",
            "type":"Transportation"
        }
    ],
    "sg:phone":"+34 958 57 03 81",
    "sg:postcode":"18100",
    "sg:province":"Granada",
    "wof:name":"Soto Ruiz Antonio",
    "wof:placetype":"venue"
},
  "geometry": {"coordinates":[-3.6300308704,37.1401138306],"type":"Point"}
}