{
  "type": "Feature",
  "properties": {
    "addr:full":"Calle de Luis Jimenez, 2 Talavera Reina Toledo 45600",
    "addr:housenumber":"2",
    "addr:postcode":"45600",
    "addr:street":"Calle De Luis Jimenez",
    "iso:country":"ES",
    "sg:address":"Calle de Luis Jimenez, 2",
    "sg:city":"Talavera Reina",
    "sg:orig_category":"Peluqueros: De Se\u00d1oras",
    "sg:phone":"+34 925 82 39 37",
    "sg:postcode":"45600",
    "sg:province":"Toledo",
    "wof:name":"Moran Segovia Maria Soledad",
    "wof:placetype":"venue"
},
  "geometry": {"coordinates":[-4.8346180916,39.9599266052],"type":"Point"}
}