{
  "type": "Feature",
  "properties": {
    "iso:country":"ES",
    "sg:address":"Carrer de Arquebisbe Alemany, 33",
    "sg:city":"Vic",
    "sg:orig_category":"Muebles, Minoristas",
    "sg:phone":"+34 938 85 37 07",
    "sg:postcode":"08500",
    "sg:province":"Barcelona",
    "wof:name":"Ausona Mobles S.l.",
    "wof:placetype":"venue"
},
  "geometry": {"coordinates":[2.2500910759,41.9316635132],"type":"Point"}
}