{
  "type": "Feature",
  "properties": {
    "addr:full":"Far De Creus, S/n Cadaques Girona 17488",
    "addr:housenumber":"s / n",
    "addr:postcode":"17488",
    "iso:country":"ES",
    "sg:address":"Far De Creus, S/n",
    "sg:city":"Cadaques",
    "sg:orig_category":"Ense\u00d1anza, Formaci\u00d3n Profesional: Aprendizaje",
    "sg:phone":"+34 972 19 90 25",
    "sg:postcode":"17488",
    "sg:province":"Girona",
    "wof:name":"Autoritat Portuaria De Barcelona",
    "wof:placetype":"venue"
},
  "geometry": {"coordinates":[3.2796268463,42.2902069092],"type":"Point"}
}