{
  "type": "Feature",
  "properties": {
    "iso:country":"ES",
    "sg:address":"Calle de Camino De Puntallana, S/n",
    "sg:city":"S. Sebastian Gomera",
    "sg:orig_category":"Alimentaci\u00d3n Animal (fabricaci\u00d3n, Al Por Mayor)",
    "sg:phone":"+34 922 87 03 60",
    "sg:postcode":"38800",
    "sg:province":"Santa Cruz De Tenerife",
    "wof:name":"Sociedad Cooperativa Agricola Agricultores De La Gomera",
    "wof:placetype":"venue"
},
  "geometry": {"coordinates":[-17.1105136871,28.0907344818],"type":"Point"}
}