{
  "type": "Feature",
  "properties": {
    "iso:country":"ES",
    "sg:address":"Calle de Pintor Jose Arrue, 6",
    "sg:city":"Llodio",
    "sg:orig_category":"M\u00c9dicos: Estomatolog\u00cda",
    "sg:phone":"+34 946 72 31 65",
    "sg:postcode":"01400",
    "sg:province":"\u00c1lava",
    "wof:name":"Salmon Anton Alberto",
    "wof:placetype":"venue"
},
  "geometry": {"coordinates":[-2.9594979286,43.1457633972],"type":"Point"}
}