{
  "type": "Feature",
  "properties": {
    "addr:full":"Calle de Luis Bejar, 1 Pozuelo De Alarcon Madrid 28223",
    "addr:housenumber":"1",
    "addr:postcode":"28223",
    "addr:street":"Calle De Luis Bejar",
    "iso:country":"ES",
    "sg:address":"Calle de Luis Bejar, 1",
    "sg:city":"Pozuelo De Alarcon",
    "sg:orig_category":"Art\u00cdculos De Decoraci\u00d3n",
    "sg:phone":"+34 913 51 07 29",
    "sg:postcode":"28223",
    "sg:province":"Madrid",
    "wof:name":"Dekolor S.l.",
    "wof:placetype":"venue"
},
  "geometry": {"coordinates":[-3.814718008,40.4356307983],"type":"Point"}
}