{
  "type": "Feature",
  "properties": {
    "iso:country":"ES",
    "sg:address":"Calle de Alcalde Diaz Penedela, 1",
    "sg:city":"Cangas Narcea",
    "sg:orig_category":"Caf\u00c9s, Bares, Cervecer\u00cdas",
    "sg:phone":"+34 985 81 00 64",
    "sg:postcode":"33800",
    "sg:province":"Asturias",
    "wof:name":"Valle Patallo Maria Del Rosario",
    "wof:placetype":"venue"
},
  "geometry": {"coordinates":[-6.5504379272,43.1779098511],"type":"Point"}
}