{
  "type": "Feature",
  "properties": {
    "addr:full":"Pl Joan Alsina, 11 Cardedeu Barcelona 08440",
    "addr:housenumber":"11",
    "addr:postcode":"08440",
    "addr:street":"Pl Joan Alsina",
    "iso:country":"ES",
    "sg:address":"Pl Joan Alsina, 11",
    "sg:city":"Cardedeu",
    "sg:orig_category":"Zapatos (al Por Menor)",
    "sg:phone":"+34 938 71 30 19",
    "sg:postcode":"08440",
    "sg:province":"Barcelona",
    "wof:name":"Suelves Sauri Maria Luisa",
    "wof:placetype":"venue"
},
  "geometry": {"coordinates":[2.3612360954,41.6422538757],"type":"Point"}
}