{
  "type": "Feature",
  "properties": {
    "iso:country":"ES",
    "sg:address":"Calle de Tordesillas, 6",
    "sg:city":"Alcorcon",
    "sg:orig_category":"Mec\u00c1nico Del Autom\u00d3vil",
    "sg:phone":"+34 916 10 21 60",
    "sg:postcode":"28924",
    "sg:province":"Madrid",
    "wof:name":"Urrea Lopez Trinitario",
    "wof:placetype":"venue"
},
  "geometry": {"coordinates":[-3.824215889,40.3523330688],"type":"Point"}
}