{
  "type": "Feature",
  "properties": {
    "addr:full":"Calle de Juan Xxiii, 10 Torrelavega Cantabria 39300",
    "addr:housenumber":"10",
    "addr:postcode":"39300",
    "addr:street":"Calle De Juan Xxiii",
    "iso:country":"ES",
    "sg:address":"Calle de Juan Xxiii, 10",
    "sg:city":"Torrelavega",
    "sg:orig_category":"Mercer\u00cda, Lencer\u00cda (al Por Menor)",
    "sg:phone":"+34 942 89 42 23",
    "sg:postcode":"39300",
    "sg:province":"Cantabria",
    "wof:name":"Calderon Diego Esperanza",
    "wof:placetype":"venue"
},
  "geometry": {"coordinates":[-4.0464630127,43.3520278931],"type":"Point"}
}