{
  "type": "Feature",
  "properties": {
    "iso:country":"ES",
    "sg:address":"C/ Biniamar, 14",
    "sg:city":"Inca",
    "sg:orig_category":"Mercer\u00cda, Lencer\u00cda (al Por Menor)",
    "sg:phone":"+34 971 50 09 93",
    "sg:postcode":"07300",
    "sg:province":"Islas Baleares",
    "wof:name":"Fills Dep Barcelo C.b.",
    "wof:placetype":"venue"
},
  "geometry": {"coordinates":[2.9072599411,39.7215003967],"type":"Point"}
}