{
  "type": "Feature",
  "properties": {
    "iso:country":"ES",
    "sg:address":"Calle de Cielos, 71",
    "sg:city":"Puerto De Santa Maria",
    "sg:orig_category":"Art\u00cdculos Funerarios (al Por Menor)",
    "sg:phone":"+34 956 87 21 56",
    "sg:postcode":"11500",
    "sg:province":"C\u00e1diz",
    "wof:name":"Peinado Campos Milagros",
    "wof:placetype":"venue"
},
  "geometry": {"coordinates":[-6.2252197266,36.6014671326],"type":"Point"}
}