{
  "type": "Feature",
  "properties": {
    "iso:country":"ES",
    "sg:address":"Calle de Sierra Gorda, 25",
    "sg:city":"Madrid",
    "sg:orig_category":"Cervecer\u00cdas",
    "sg:phone":"+34 913 32 77 87",
    "sg:postcode":"28031",
    "sg:province":"Madrid",
    "wof:name":"Franganillo Simon Ramiro",
    "wof:placetype":"venue"
},
  "geometry": {"coordinates":[-3.6176979542,40.3813362122],"type":"Point"}
}