{
  "type": "Feature",
  "properties": {
    "iso:country":"ES",
    "sg:address":"Calle de Historiador Jaen Morente, 18",
    "sg:city":"Cordoba",
    "sg:orig_category":"Muebles, Minoristas",
    "sg:phone":"+34 957 25 77 57",
    "sg:postcode":"14014",
    "sg:province":"C\u00f3rdoba",
    "wof:name":"Baron Chaparro Rafael",
    "wof:placetype":"venue"
},
  "geometry": {"coordinates":[-4.7551989555,37.8985519409],"type":"Point"}
}