{
  "type": "Feature",
  "properties": {
    "addr:full":"Calle de General Diaz Porlier, 55 Madrid Madrid 28006",
    "addr:housenumber":"55",
    "addr:postcode":"madrid;28006",
    "addr:street":"Calle De General Diaz Porlier",
    "iso:country":"ES",
    "sg:address":"Calle de General Diaz Porlier, 55",
    "sg:city":"Madrid",
    "sg:orig_category":"Confecci\u00d3n De Trajes Para Se\u00d1oras",
    "sg:phone":"+34 914 02 52 43",
    "sg:postcode":"28006",
    "sg:province":"Madrid",
    "wof:name":"Rolania Moreton Maria Jose",
    "wof:placetype":"venue"
},
  "geometry": {"coordinates":[-3.676956892,40.4301719666],"type":"Point"}
}