{
  "type": "Feature",
  "properties": {
    "addr:full":"Carrer de Massenet, 9 Santa Coloma De Gramenet Barcelona 08922",
    "addr:housenumber":"9",
    "addr:postcode":"08922",
    "addr:street":"Carrer De Massenet",
    "iso:country":"ES",
    "sg:address":"Carrer de Massenet, 9",
    "sg:city":"Santa Coloma De Gramenet",
    "sg:orig_category":"Bisuter\u00cda, Joyer\u00cda, Relojer\u00cda (al Por Menor)",
    "sg:phone":"+34 934 68 20 00",
    "sg:postcode":"08922",
    "sg:province":"Barcelona",
    "wof:name":"Vila Roch Jaime",
    "wof:placetype":"venue"
},
  "geometry": {"coordinates":[2.2186150551,41.4504089355],"type":"Point"}
}