{
  "type": "Feature",
  "properties": {
    "addr:full":"Av. Maritima, S/n Los Cristianos Santa Cruz De Tenerife 38650",
    "addr:housenumber":"s / n",
    "addr:postcode":"38650",
    "addr:street":"Av. Maritima",
    "iso:country":"ES",
    "sg:address":"Av. Maritima, S/n",
    "sg:city":"Los Cristianos",
    "sg:orig_category":"Supermercados Y Hipermercados",
    "sg:phone":"+34 922 78 85 27",
    "sg:postcode":"38650",
    "sg:province":"Santa Cruz De Tenerife",
    "wof:name":"Chelsea/,noelle Jean",
    "wof:placetype":"venue"
},
  "geometry": {"coordinates":[-16.7313289642,28.0631198883],"type":"Point"}
}