{
  "type": "Feature",
  "properties": {
    "addr:full":"Calle de Marquesa De Canillejas, 43 Pola De Siero Asturias 33510",
    "addr:housenumber":"43",
    "addr:postcode":"33510",
    "addr:street":"Calle De Marquesa De Canillejas",
    "iso:country":"ES",
    "sg:address":"Calle de Marquesa De Canillejas, 43",
    "sg:city":"Pola De Siero",
    "sg:classifiers":[
        {
            "category":"Autos & Motor Vehicles",
            "subcategory":"Automobile Sales",
            "type":"Retail Goods"
        }
    ],
    "sg:phone":"+34 985 72 50 29",
    "sg:postcode":"33510",
    "sg:province":"Asturias",
    "wof:name":"Autoescuela Veli S.l.",
    "wof:placetype":"venue"
},
  "geometry": {"coordinates":[-5.662706852,43.3892097473],"type":"Point"}
}