{
  "type": "Feature",
  "properties": {
    "iso:country":"ES",
    "sg:address":"Ziara Kalea, 82",
    "sg:city":"Oiartzun",
    "sg:orig_category":"Fabricaci\u00d3n De Moldes Y Modelos",
    "sg:phone":"+34 943 26 03 87",
    "sg:postcode":"20180",
    "sg:province":"Guip\u00f9zcoa",
    "wof:name":"Talleres Zapirain, S.l",
    "wof:placetype":"venue"
},
  "geometry": {"coordinates":[-1.8629590273,43.2992401123],"type":"Point"}
}