{
  "type": "Feature",
  "properties": {
    "addr:full":"Psaj Villalbilla, 1 Madrid Madrid 28030",
    "addr:housenumber":"1",
    "addr:postcode":"28030",
    "addr:street":"Villalbilla",
    "iso:country":"ES",
    "sg:address":"Psaj Villalbilla, 1",
    "sg:city":"Madrid",
    "sg:orig_category":"Agencias De Viajes",
    "sg:phone":"+34 917 51 28 98",
    "sg:postcode":"28030",
    "sg:province":"Madrid",
    "wof:name":"Learning English-franch Experience S.l.",
    "wof:placetype":"venue"
},
  "geometry": {"coordinates":[-3.6340301037,40.4055328369],"type":"Point"}
}