{
  "type": "Feature",
  "properties": {
    "addr:full":"Calle de Pelayo, 6 Madrid Madrid 28004",
    "addr:housenumber":"6",
    "addr:postcode":"28004",
    "addr:street":"Calle De Pelayo",
    "iso:country":"ES",
    "sg:address":"Calle de Pelayo, 6",
    "sg:city":"Madrid",
    "sg:orig_category":"Peluquer\u00cdas, Peluquer\u00cda Mixta",
    "sg:phone":"+34 915 32 54 78",
    "sg:postcode":"28004",
    "sg:province":"Madrid",
    "wof:name":"Lopez Ayuso Mari Cruz",
    "wof:placetype":"venue"
},
  "geometry": {"coordinates":[-3.6989109516,40.4218978882],"type":"Point"}
}