{
  "type": "Feature",
  "properties": {
    "addr:full":"Avda Ranillas, 16 Zaragoza Zaragoza 50015",
    "addr:housenumber":"16",
    "addr:postcode":"50015",
    "addr:street":"Avda Ranillas",
    "iso:country":"ES",
    "sg:address":"Avda Ranillas, 16",
    "sg:city":"Zaragoza",
    "sg:orig_category":"Centros Empresariales",
    "sg:phone":"+34 976 52 42 07",
    "sg:postcode":"50015",
    "sg:province":"Zaragoza",
    "wof:name":"Federacion Empresas Quimicas Y Plasticos De Aragon",
    "wof:placetype":"venue"
},
  "geometry": {"coordinates":[-0.8629540205,41.6912841797],"type":"Point"}
}