{
  "type": "Feature",
  "properties": {
    "iso:country":"ES",
    "sg:address":"Carr Santa Maria, 109",
    "sg:city":"Badalona",
    "sg:orig_category":"Maquinaria Para Industrias Diversas",
    "sg:phone":"+34 933 84 31 20",
    "sg:postcode":"08911",
    "sg:province":"Barcelona",
    "wof:name":"Servicio Tecnico Maquinaria Automocion",
    "wof:placetype":"venue"
},
  "geometry": {"coordinates":[2.2554650307,41.4526367188],"type":"Point"}
}