{
  "type": "Feature",
  "properties": {
    "addr:full":"Calle de Francisc.y Jose Martin Granizo, 1 Pozuelo De Alarcon Madrid 28224",
    "addr:housenumber":"1",
    "addr:postcode":"28224",
    "addr:street":"Calle De Francisc.Y Jose Martin Granizo",
    "iso:country":"ES",
    "sg:address":"Calle de Francisc.y Jose Martin Granizo, 1",
    "sg:city":"Pozuelo De Alarcon",
    "sg:orig_category":"T\u00c9cnicos Veterinarios",
    "sg:phone":"+34 913 52 02 87",
    "sg:postcode":"28224",
    "sg:province":"Madrid",
    "wof:name":"Loraque De La Hoz Rafael",
    "wof:placetype":"venue"
},
  "geometry": {"coordinates":[-3.7931580544,40.448059082],"type":"Point"}
}