{
  "type": "Feature",
  "properties": {
    "iso:country":"ES",
    "sg:address":"Calle de Algodonales, 7",
    "sg:city":"Ubrique",
    "sg:orig_category":"Marroquiner\u00cda (confecci\u00d3n)",
    "sg:phone":"+34 956 46 01 10",
    "sg:postcode":"11600",
    "sg:province":"C\u00e1diz",
    "wof:name":"Lamela Parra Antonio",
    "wof:placetype":"venue"
},
  "geometry": {"coordinates":[-5.4504032135,36.677936554],"type":"Point"}
}