{
  "type": "Feature",
  "properties": {
    "addr:full":"Calle de Estonia, 20 Malaga M\u00e1laga 29196",
    "addr:housenumber":"20",
    "addr:postcode":"29196",
    "addr:street":"Calle De Estonia;Ma\u0301Laga",
    "iso:country":"ES",
    "sg:address":"Calle de Estonia, 20",
    "sg:city":"Malaga",
    "sg:orig_category":"Lencer\u00cda Femenina, Corseter\u00cda, Trajes De Ba\u00d1o (al Por Menor)",
    "sg:phone":"+34 952 96 06 52",
    "sg:postcode":"29196",
    "sg:province":"M\u00e1laga",
    "wof:name":"Queban Textil S.l.",
    "wof:placetype":"venue"
},
  "geometry": {"coordinates":[-4.4951457977,36.6948280334],"type":"Point"}
}