{
  "type": "Feature",
  "properties": {
    "iso:country":"ES",
    "sg:address":"Carrer de Sinia, 21",
    "sg:city":"Zona Costera",
    "sg:orig_category":"Asociaciones Y Clubs Deportivos",
    "sg:phone":"+34 977 80 13 74",
    "sg:postcode":"43883",
    "sg:province":"Tarragona",
    "wof:name":"Club Deportivo Las Piscinas",
    "wof:placetype":"venue"
},
  "geometry": {"coordinates":[1.4860930443,41.1724205017],"type":"Point"}
}