{
  "type": "Feature",
  "properties": {
    "iso:country":"ES",
    "sg:address":"Cmno Veredon De Los Frailes, S/n",
    "sg:city":"Veredon Frailes",
    "sg:orig_category":"Centros De Educaci\u00d3n Especial",
    "sg:phone":"+34 957 32 75 90",
    "sg:postcode":"14710",
    "sg:province":"C\u00f3rdoba",
    "wof:name":"Junta De Andalucia-colegio Publico La Paz",
    "wof:placetype":"venue"
},
  "geometry": {"coordinates":[-4.9146289825,37.8490753174],"type":"Point"}
}