{
  "type": "Feature",
  "properties": {
    "addr:full":"Avda Italia (de), 2 Granada Granada 18007",
    "addr:housenumber":"2",
    "addr:postcode":"18007",
    "addr:street":"Avda Italia De",
    "iso:country":"ES",
    "sg:address":"Avda Italia (de), 2",
    "sg:city":"Granada",
    "sg:orig_category":"Panader\u00cdas, Panader\u00cdas",
    "sg:phone":"+34 958 81 23 45",
    "sg:postcode":"18007",
    "sg:province":"Granada",
    "wof:name":"Garcia Sanchez Antonio",
    "wof:placetype":"venue"
},
  "geometry": {"coordinates":[-3.5970430374,37.1606636047],"type":"Point"}
}