{
  "type": "Feature",
  "properties": {
    "iso:country":"ES",
    "sg:address":"Carrer de Sant Antoni Maria Claret, 3",
    "sg:city":"S. Just Desvern",
    "sg:orig_category":"Negocio De Materiales De Construcci\u00d3n",
    "sg:phone":"+34 933 71 13 21",
    "sg:postcode":"08960",
    "sg:province":"Barcelona",
    "wof:name":"Serra Sanroma Jorge",
    "wof:placetype":"venue"
},
  "geometry": {"coordinates":[2.080231905,41.3826217651],"type":"Point"}
}