{
  "type": "Feature",
  "properties": {
    "addr:full":"Pg Esglesia, 10 Sentmenat Barcelona 08181",
    "addr:housenumber":"10",
    "addr:postcode":"08181",
    "addr:street":"Pg Esglesia",
    "iso:country":"ES",
    "sg:address":"Pg Esglesia, 10",
    "sg:city":"Sentmenat",
    "sg:orig_category":"Iglesia Cat\u00d3lica",
    "sg:phone":"+34 937 15 00 32",
    "sg:postcode":"08181",
    "sg:province":"Barcelona",
    "wof:name":"Parroquia De Sentmenat",
    "wof:placetype":"venue"
},
  "geometry": {"coordinates":[2.1364600658,41.6059112549],"type":"Point"}
}