{
  "type": "Feature",
  "properties": {
    "iso:country":"ES",
    "sg:address":"Ctra Sevilla-huelva, 406",
    "sg:city":"Umbrete",
    "sg:orig_category":"Pirotecnia (espect\u00c1culos)",
    "sg:phone":"+34 955 71 60 15",
    "sg:postcode":"41806",
    "sg:province":"Sevilla",
    "wof:name":"Campos Calero Francisco",
    "wof:placetype":"venue"
},
  "geometry": {"coordinates":[-6.1562099457,37.3696289062],"type":"Point"}
}