{
  "type": "Feature",
  "properties": {
    "addr:full":"Carrer de Antoni Gaudi, 91 S. Boi Llobregat Barcelona 08830",
    "addr:housenumber":"91",
    "addr:postcode":"08830",
    "addr:street":"Carrer De Antoni Gaudi",
    "iso:country":"ES",
    "sg:address":"Carrer de Antoni Gaudi, 91",
    "sg:city":"S. Boi Llobregat",
    "sg:orig_category":"Venta, Localizaci\u00d3n, Reparaci\u00d3n De Material E Instrumental M\u00c9dico",
    "sg:phone":"+34 936 30 43 45",
    "sg:postcode":"08830",
    "sg:province":"Barcelona",
    "sg:website":"www.eurogine.com",
    "wof:name":"Eurogine S.l.",
    "wof:placetype":"venue"
},
  "geometry": {"coordinates":[2.0261199474,41.3481788635],"type":"Point"}
}