{
  "type": "Feature",
  "properties": {
    "addr:full":"Calle de Nuestra Se\u00d1ora De Aiala, 21 Alegria-dulantzi \u00c1lava 01240",
    "addr:housenumber":"21",
    "addr:postcode":"01240",
    "addr:street":"Calle De Nuestra Sen\u0303Ora;Aiala;A\u0301Lava",
    "iso:country":"ES",
    "sg:address":"Calle de Nuestra Se\u00d1ora De Aiala, 21",
    "sg:city":"Alegria-dulantzi",
    "sg:orig_category":"Maquinaria Y Herramientas Para Madera, Pvc, Aluminio Y Aperos (fabricaci\u00d3n, Comercio)",
    "sg:phone":"+34 945 40 06 74",
    "sg:postcode":"01240",
    "sg:province":"\u00c1lava",
    "wof:name":"Dulantzi Metals S.a.",
    "wof:placetype":"venue"
},
  "geometry": {"coordinates":[-2.5135939121,42.8456497192],"type":"Point"}
}