{
  "type": "Feature",
  "properties": {
    "addr:full":"Pla\u00c7 Espanya, S/n Girona Girona 17002",
    "addr:housenumber":"s / n",
    "addr:postcode":"17002",
    "iso:country":"ES",
    "sg:address":"Pla\u00c7 Espanya, S/n",
    "sg:city":"Girona",
    "sg:orig_category":"Servicios Gsm",
    "sg:phone":"+34 972 22 84 67",
    "sg:postcode":"17002",
    "sg:province":"Girona",
    "wof:name":"Inter-mobils 33 S.l.",
    "wof:placetype":"venue"
},
  "geometry": {"coordinates":[2.8171200752,41.9789161682],"type":"Point"}
}