{
  "type": "Feature",
  "properties": {
    "addr:full":"C/ Doctor Bergos, 64 Ripollet Barcelona 08291",
    "addr:housenumber":"64",
    "addr:postcode":"08291",
    "addr:street":"C / Doctor Bergos",
    "iso:country":"ES",
    "sg:address":"C/ Doctor Bergos, 64",
    "sg:city":"Ripollet",
    "sg:orig_category":"Ropa Para Se\u00d1oras Y Caballeros (al Por Menor)",
    "sg:phone":"+34 936 92 76 24",
    "sg:postcode":"08291",
    "sg:province":"Barcelona",
    "wof:name":"Aguilar Chicano Antonia",
    "wof:placetype":"venue"
},
  "geometry": {"coordinates":[2.1644587517,41.4969673157],"type":"Point"}
}