{
  "type": "Feature",
  "properties": {
    "iso:country":"ES",
    "sg:address":"Calle de Segovia, 24",
    "sg:city":"Madrid",
    "sg:orig_category":"Asociaciones, Organismos Culturales Y Socioeducativos",
    "sg:phone":"+34 915 59 25 58",
    "sg:postcode":"28005",
    "sg:province":"Madrid",
    "sg:website":"www.arte-heraldica.com",
    "wof:name":"Cordero Ruiz Jaime",
    "wof:placetype":"venue"
},
  "geometry": {"coordinates":[-3.7116661072,40.4138565063],"type":"Point"}
}