{
  "type": "Feature",
  "properties": {
    "addr:full":"Ctra S Jose De La Vega, 20 Murcia Murcia 30011",
    "addr:housenumber":"20",
    "addr:postcode":"30011",
    "addr:street":"Ctra S Jose De La Vega",
    "iso:country":"ES",
    "sg:address":"Ctra S Jose De La Vega, 20",
    "sg:city":"Murcia",
    "sg:orig_category":"Molduras, Junquillos, Listones Y Molduras Perforadas",
    "sg:phone":"+34 968 34 43 63",
    "sg:postcode":"30011",
    "sg:province":"Murcia",
    "wof:name":"Mu\u00f1oz Mu\u00f1oz Francisco Javier",
    "wof:placetype":"venue"
},
  "geometry": {"coordinates":[-1.1055790186,37.9783668518],"type":"Point"}
}