{
  "type": "Feature",
  "properties": {
    "addr:full":"Calle de San Ignacio, 6 Sevilla Sevilla 41018",
    "addr:housenumber":"6",
    "addr:postcode":"41018",
    "addr:street":"Calle De San Ignacio",
    "iso:country":"ES",
    "sg:address":"Calle de San Ignacio, 6",
    "sg:city":"Sevilla",
    "sg:orig_category":"Molduras, Junquillos, Listones Y Molduras Perforadas",
    "sg:phone":"+34 954 57 45 43",
    "sg:postcode":"41018",
    "sg:province":"Sevilla",
    "wof:name":"Aserplus S.l.",
    "wof:placetype":"venue"
},
  "geometry": {"coordinates":[-5.9763493538,37.3865585327],"type":"Point"}
}