{
  "type": "Feature",
  "properties": {
    "addr:full":"Calle de Marques De Teverga, 2 Oviedo Asturias 33005",
    "addr:housenumber":"2",
    "addr:postcode":"33005",
    "addr:street":"Calle De Marques De Teverga",
    "iso:country":"ES",
    "sg:address":"Calle de Marques De Teverga, 2",
    "sg:city":"Oviedo",
    "sg:orig_category":"Ropa Para Se\u00d1oras (al Por Menor)",
    "sg:phone":"+34 985 24 52 09",
    "sg:postcode":"33005",
    "sg:province":"Asturias",
    "wof:name":"Marivi Fashion S.l.",
    "wof:placetype":"venue"
},
  "geometry": {"coordinates":[-5.8565311432,43.3613128662],"type":"Point"}
}