{
  "type": "Feature",
  "properties": {
    "iso:country":"ES",
    "sg:address":"Plaz Margarita Valldaura, 1",
    "sg:city":"Valencia",
    "sg:orig_category":"Dibujantes (diversos)",
    "sg:phone":"+34 963 52 20 26",
    "sg:postcode":"46003",
    "sg:province":"Valencia",
    "wof:name":"Alvaro Gaya Jose Maria",
    "wof:placetype":"venue"
},
  "geometry": {"coordinates":[-0.3749324083,39.4732933044],"type":"Point"}
}