{
  "type": "Feature",
  "properties": {
    "iso:country":"ES",
    "sg:address":"Pol. Ind. La Basala, S/n",
    "sg:city":"Castello Plana",
    "sg:orig_category":"Negocio De Enlosados, Soler\u00cdas",
    "sg:phone":"+34 964 34 02 53",
    "sg:postcode":"12006",
    "sg:province":"Castell\u00f3n",
    "wof:name":"Bubbles Systems S.l.",
    "wof:placetype":"venue"
},
  "geometry": {"coordinates":[-0.1292939931,40.0168533325],"type":"Point"}
}