{
  "type": "Feature",
  "properties": {
    "iso:country":"ES",
    "sg:address":"Pol Ind Llanos Jarata, 78",
    "sg:city":"Montilla",
    "sg:orig_category":"Centros Empresariales",
    "sg:phone":"+34 957 65 07 21",
    "sg:postcode":"14550",
    "sg:province":"C\u00f3rdoba",
    "wof:name":"Recambios Marcasur S.l.",
    "wof:placetype":"venue"
},
  "geometry": {"coordinates":[-4.6404590607,37.58177948],"type":"Point"}
}