{
  "type": "Feature",
  "properties": {
    "addr:full":"Calle de Fernando Casariego, 16 Langreo Asturias 33930",
    "addr:housenumber":"16",
    "addr:postcode":"33930",
    "addr:street":"Calle De Fernando Casariego",
    "iso:country":"ES",
    "sg:address":"Calle de Fernando Casariego, 16",
    "sg:city":"Langreo",
    "sg:orig_category":"Cajas Para Embalar",
    "sg:phone":"+34 985 67 83 33",
    "sg:postcode":"33930",
    "sg:province":"Asturias",
    "sg:website":"www.ruralvia.es",
    "wof:name":"Caja Rural De Asturias",
    "wof:placetype":"venue"
},
  "geometry": {"coordinates":[-5.6966438293,43.3077964783],"type":"Point"}
}