{
  "type": "Feature",
  "properties": {
    "addr:full":"Calle de Manuel Laguna, 32 Madrid Madrid 28018",
    "addr:housenumber":"32",
    "addr:postcode":"madrid;28018",
    "addr:street":"Calle De Manuel Laguna",
    "iso:country":"ES",
    "sg:address":"Calle de Manuel Laguna, 32",
    "sg:city":"Madrid",
    "sg:orig_category":"Mec\u00c1nico Del Autom\u00d3vil",
    "sg:phone":"+34 917 85 98 88",
    "sg:postcode":"28018",
    "sg:province":"Madrid",
    "wof:name":"Quero Quero Antonio",
    "wof:placetype":"venue"
},
  "geometry": {"coordinates":[-3.664550066,40.3825683594],"type":"Point"}
}