{
  "type": "Feature",
  "properties": {
    "iso:country":"ES",
    "sg:address":"Pg Pere Iii, 88",
    "sg:city":"Manresa",
    "sg:orig_category":"Hilaturas, Hilos Y Actividades Relacionadas",
    "sg:phone":"+34 938 73 27 88",
    "sg:postcode":"08242",
    "sg:province":"Barcelona",
    "wof:name":"Martinez Escardo Antonio",
    "wof:placetype":"venue"
},
  "geometry": {"coordinates":[1.8301719427,41.7296943665],"type":"Point"}
}