{
  "type": "Feature",
  "properties": {
    "iso:country":"ES",
    "sg:address":"Marjals, 24",
    "sg:city":"Ondara",
    "sg:orig_category":"Fotograf\u00cda Art\u00cdstica Y Retratos",
    "sg:phone":"+34 965 76 76 21",
    "sg:postcode":"03760",
    "sg:province":"Alicante",
    "wof:name":"Foto Estudi Sl",
    "wof:placetype":"venue"
},
  "geometry": {"coordinates":[0.0192140006,38.8233184814],"type":"Point"}
}