{
  "type": "Feature",
  "properties": {
    "iso:country":"ES",
    "sg:address":"Carrer de Paris, 206",
    "sg:city":"Barcelona",
    "sg:orig_category":"Inmobiliaria (agencias)",
    "sg:phone":"+34 933 21 10 80",
    "sg:postcode":"08008",
    "sg:province":"Barcelona",
    "wof:name":"Antoli Mendez Carlos",
    "wof:placetype":"venue"
},
  "geometry": {"coordinates":[2.1547403336,41.3947677612],"type":"Point"}
}