{
  "type": "Feature",
  "properties": {
    "iso:country":"ES",
    "sg:address":"Pase San Francisco De Sales, 16",
    "sg:city":"Madrid",
    "sg:orig_category":"Ingenier\u00cda, Centros De Estudios (diversos)",
    "sg:phone":"+34 914 41 52 91",
    "sg:postcode":"28003",
    "sg:province":"Madrid",
    "wof:name":"Hernandez Gomez Pedro",
    "wof:placetype":"venue"
},
  "geometry": {"coordinates":[-3.7150421143,40.4407691956],"type":"Point"}
}