{
  "type": "Feature",
  "properties": {
    "addr:full":"Calle de Galileo, 7 Benicasim Castell\u00f3n 12560",
    "addr:housenumber":"7",
    "addr:postcode":"12560",
    "addr:street":"Calle De Galileo",
    "iso:country":"ES",
    "sg:address":"Calle de Galileo, 7",
    "sg:city":"Benicasim",
    "sg:orig_category":"Empresas De Carpinter\u00cda De Madera",
    "sg:phone":"+34 964 30 21 61",
    "sg:postcode":"12560",
    "sg:province":"Castell\u00f3n",
    "wof:name":"Carpinteria Lubeco S.l.u.",
    "wof:placetype":"venue"
},
  "geometry": {"coordinates":[0.0457400009,40.0510292053],"type":"Point"}
}