{
  "type": "Feature",
  "properties": {
    "addr:full":"Calle de Cuartel De Simancas, 2 Madrid Madrid 28053",
    "addr:housenumber":"2",
    "addr:postcode":"28053",
    "addr:street":"Calle De Cuartel;Simancas",
    "iso:country":"ES",
    "sg:address":"Calle de Cuartel De Simancas, 2",
    "sg:city":"Madrid",
    "sg:orig_category":"Fisioterapia",
    "sg:phone":"+34 914 77 78 03",
    "sg:postcode":"28053",
    "sg:province":"Madrid",
    "wof:name":"Centro Terapeutico Aura C.b.",
    "wof:placetype":"venue"
},
  "geometry": {"coordinates":[-3.662006855,40.3943977356],"type":"Point"}
}