{
  "type": "Feature",
  "properties": {
    "iso:country":"ES",
    "sg:address":"Carrer de Sant Miquel, 2",
    "sg:city":"Argentona",
    "sg:orig_category":"Fisioterapia",
    "sg:phone":"+34 937 56 05 15",
    "sg:postcode":"08310",
    "sg:province":"Barcelona",
    "wof:name":"Babiloni Coll Gabriela",
    "wof:placetype":"venue"
},
  "geometry": {"coordinates":[2.4018769264,41.5546379089],"type":"Point"}
}