{
  "type": "Feature",
  "properties": {
    "iso:country":"ES",
    "sg:address":"Avda Cruz De Juarez, 4",
    "sg:city":"Cordoba",
    "sg:orig_category":"Arquitectos",
    "sg:phone":"+34 957 40 12 84",
    "sg:postcode":"14006",
    "sg:province":"C\u00f3rdoba",
    "wof:name":"Giraldez Mateos Luis",
    "wof:placetype":"venue"
},
  "geometry": {"coordinates":[-4.780559063,37.8971633911],"type":"Point"}
}