{
  "type": "Feature",
  "properties": {
    "addr:full":"Calle de Ferrocarril (del), 13 Coslada Madrid 28820",
    "addr:housenumber":"13",
    "addr:postcode":"28820",
    "addr:street":"Calle De Ferrocarril Del",
    "iso:country":"ES",
    "sg:address":"Calle de Ferrocarril (del), 13",
    "sg:city":"Coslada",
    "sg:orig_category":"Electricidad (montaje, Ensamblaje De Componentes)",
    "sg:phone":"+34 916 69 69 55",
    "sg:postcode":"28820",
    "sg:province":"Madrid",
    "wof:name":"Belcrilux S.l.",
    "wof:placetype":"venue"
},
  "geometry": {"coordinates":[-3.5369169712,40.442691803],"type":"Point"}
}