{
  "type": "Feature",
  "properties": {
    "iso:country":"ES",
    "sg:address":"Av Mediterrani, 30",
    "sg:city":"Poblenou",
    "sg:orig_category":"Negocio De Enlosados, Soler\u00cdas",
    "sg:phone":"+34 937 69 73 38",
    "sg:postcode":"08397",
    "sg:province":"Barcelona",
    "wof:name":"Acebes Prada Pilar",
    "wof:placetype":"venue"
},
  "geometry": {"coordinates":[2.6734507084,41.6180305481],"type":"Point"}
}