{
  "type": "Feature",
  "properties": {
    "addr:full":"Afores, S/n Castellfollit Riubregos Barcelona 08281",
    "addr:housenumber":"s / n",
    "addr:postcode":"08281",
    "addr:street":"Afores",
    "iso:country":"ES",
    "sg:address":"Afores, S/n",
    "sg:city":"Castellfollit Riubregos",
    "sg:orig_category":"Cr\u00cda De Cerdos",
    "sg:phone":"+34 938 69 30 23",
    "sg:postcode":"08281",
    "sg:province":"Barcelona",
    "wof:name":"Castilla I Dorado S.c.p.",
    "wof:placetype":"venue"
},
  "geometry": {"coordinates":[1.539180994,41.7054977417],"type":"Point"}
}