{
  "type": "Feature",
  "properties": {
    "iso:country":"ES",
    "sg:address":"Avenida Del Monte Caxado, 11",
    "sg:city":"Pontes Garcia Rodriguez",
    "sg:orig_category":"Promotores Constructores",
    "sg:phone":"+34 981 45 06 53",
    "sg:postcode":"15320",
    "sg:province":"La Coru\u00f1a",
    "wof:name":"Cruz Diaz Dario Jesus",
    "wof:placetype":"venue"
},
  "geometry": {"coordinates":[-7.8519802094,43.4437828064],"type":"Point"}
}