{
  "type": "Feature",
  "properties": {
    "addr:full":"Carrer de Bruc, 76 Barcelona Barcelona 08009",
    "addr:housenumber":"76",
    "addr:postcode":"08009",
    "addr:street":"Carrer De Bruc",
    "iso:country":"ES",
    "sg:address":"Carrer de Bruc, 76",
    "sg:city":"Barcelona",
    "sg:orig_category":"Inmobiliaria (agencias)",
    "sg:phone":"+34 934 88 35 89",
    "sg:postcode":"08009",
    "sg:province":"Barcelona",
    "wof:name":"Lan S.a.",
    "wof:placetype":"venue"
},
  "geometry": {"coordinates":[2.1703588963,41.3938941956],"type":"Point"}
}