{
  "type": "Feature",
  "properties": {
    "iso:country":"ES",
    "sg:address":"Avda Pe\u00d1a Prieta, 27",
    "sg:city":"Madrid",
    "sg:orig_category":"Molduras, Junquillos, Listones Y Molduras Perforadas",
    "sg:phone":"+34 914 33 96 05",
    "sg:postcode":"28038",
    "sg:province":"Madrid",
    "wof:name":"Domingues  Dinis Afonso",
    "wof:placetype":"venue"
},
  "geometry": {"coordinates":[-3.666052103,40.4009017944],"type":"Point"}
}