{
  "type": "Feature",
  "properties": {
    "addr:full":"Ptge Prudencia, S/n Terrassa Barcelona 08222",
    "addr:housenumber":"s / n",
    "addr:postcode":"08222",
    "addr:street":"Ptge Prudencia",
    "iso:country":"ES",
    "sg:address":"Ptge Prudencia, S/n",
    "sg:city":"Terrassa",
    "sg:orig_category":"Carnicer\u00cdas, Carnicer\u00cdas",
    "sg:phone":"+34 937 85 04 48",
    "sg:postcode":"08222",
    "sg:province":"Barcelona",
    "wof:name":"Restoy Guerrero Ana",
    "wof:placetype":"venue"
},
  "geometry": {"coordinates":[2.0300600529,41.5668792725],"type":"Point"}
}