{
  "type": "Feature",
  "properties": {
    "iso:country":"ES",
    "sg:address":"Carrer de Murtra, 1",
    "sg:city":"Viladecans",
    "sg:orig_category":"Centros Empresariales",
    "sg:phone":"+34 936 58 06 67",
    "sg:postcode":"08840",
    "sg:province":"Barcelona",
    "wof:name":"Sistemes I Fluids De Vendrell S.l.",
    "wof:placetype":"venue"
},
  "geometry": {"coordinates":[2.0333449841,41.2924156189],"type":"Point"}
}