{
  "type": "Feature",
  "properties": {
    "addr:full":"Av. Libertad, 35 Alcorcon Madrid 28925",
    "addr:housenumber":"35",
    "addr:postcode":"28925",
    "addr:street":"Av. Libertad",
    "iso:country":"ES",
    "sg:address":"Av. Libertad, 35",
    "sg:city":"Alcorcon",
    "sg:orig_category":"Agencias De Viajes",
    "sg:phone":"+34 916 19 52 77",
    "sg:postcode":"28925",
    "sg:province":"Madrid",
    "sg:website":"www.viajescrisol.com",
    "wof:name":"Viajes Crisol S A",
    "wof:placetype":"venue"
},
  "geometry": {"coordinates":[-3.8043038845,40.352771759],"type":"Point"}
}