{
  "type": "Feature",
  "properties": {
    "addr:full":"Calle de Ibarra, 3 San Vicente De Barakaldo Vizcaya 48901",
    "addr:housenumber":"3",
    "addr:postcode":"48901",
    "addr:street":"Calle De Ibarra",
    "iso:country":"ES",
    "sg:address":"Calle de Ibarra, 3",
    "sg:city":"San Vicente De Barakaldo",
    "sg:orig_category":"Fotocopias, Reprograf\u00cda",
    "sg:phone":"+34 944 37 61 67",
    "sg:postcode":"48901",
    "sg:province":"Vizcaya",
    "wof:name":"Arana Arranz Josu",
    "wof:placetype":"venue"
},
  "geometry": {"coordinates":[-2.984818697,43.2983016968],"type":"Point"}
}