{
  "type": "Feature",
  "properties": {
    "iso:country":"ES",
    "sg:address":"A Igrexa, S/n",
    "sg:city":"Iglesia",
    "sg:orig_category":"Iglesia Cat\u00d3lica",
    "sg:phone":"+34 986 66 85 28",
    "sg:postcode":"36873",
    "sg:province":"Pontevedra",
    "wof:name":"Obispado De Tui-vigo-parroquia De Maria",
    "wof:placetype":"venue"
},
  "geometry": {"coordinates":[-8.3466157913,42.2657089233],"type":"Point"}
}