{
  "type": "Feature",
  "properties": {
    "addr:full":"Rond Canigo, 6 Esplugues Llobregat Barcelona 08950",
    "addr:housenumber":"6",
    "addr:postcode":"08950",
    "addr:street":"Canigo",
    "iso:country":"ES",
    "sg:address":"Rond Canigo, 6",
    "sg:city":"Esplugues Llobregat",
    "sg:orig_category":"Electromec\u00c1nica",
    "sg:phone":"+34 933 72 48 98",
    "sg:postcode":"08950",
    "sg:province":"Barcelona",
    "wof:name":"Casals Mila Jose Maria",
    "wof:placetype":"venue"
},
  "geometry": {"coordinates":[2.0842609406,41.3737335205],"type":"Point"}
}