{
  "type": "Feature",
  "properties": {
    "iso:country":"ES",
    "sg:address":"A Devesa, S/n",
    "sg:city":"Devesa",
    "sg:orig_category":"Agricultura: Abastecimiento Y Cosechado (negocio)",
    "sg:phone":"+34 986 55 65 51",
    "sg:postcode":"36647",
    "sg:province":"Pontevedra",
    "wof:name":"Campa\u00f1o Casal Jesus",
    "wof:placetype":"venue"
},
  "geometry": {"coordinates":[-8.6949396133,42.6937942505],"type":"Point"}
}