{
  "type": "Feature",
  "properties": {
    "addr:full":"Calle de Robinson Crusoe, 3 Malaga M\u00e1laga 29006",
    "addr:housenumber":"3",
    "addr:postcode":"29006",
    "addr:street":"Calle De Robinson Crusoe;Ma\u0301Laga",
    "iso:country":"ES",
    "sg:address":"Calle de Robinson Crusoe, 3",
    "sg:city":"Malaga",
    "sg:orig_category":"Calefacci\u00d3n Central: Material (fabricaci\u00d3n, Al Por Mayor)",
    "sg:phone":"+34 952 32 86 43",
    "sg:postcode":"29006",
    "sg:province":"M\u00e1laga",
    "wof:name":"Representaciones Marfil Y Aran A.l.",
    "wof:placetype":"venue"
},
  "geometry": {"coordinates":[-4.4638018608,36.7090415955],"type":"Point"}
}