{
  "type": "Feature",
  "properties": {
    "addr:full":"Plaz Legion Espa\u00d1ola, 12 Valencia Valencia 46010",
    "addr:housenumber":"12",
    "addr:postcode":"46010",
    "addr:street":"Valencia",
    "iso:country":"ES",
    "sg:address":"Plaz Legion Espa\u00d1ola, 12",
    "sg:city":"Valencia",
    "sg:orig_category":"Tintes (fabricaci\u00d3n, Al Por Mayor)",
    "sg:phone":"+34 963 62 15 91",
    "sg:postcode":"46010",
    "sg:province":"Valencia",
    "wof:name":"Diaz Montes Angel",
    "wof:placetype":"venue"
},
  "geometry": {"coordinates":[-0.3663989902,39.4783859253],"type":"Point"}
}