{
  "type": "Feature",
  "properties": {
    "iso:country":"ES",
    "sg:address":"Calle de Emilio Borrajo, 1",
    "sg:city":"Talavera Reina",
    "sg:orig_category":"Electricidad: Instaladores",
    "sg:phone":"+34 925 81 76 71",
    "sg:postcode":"45600",
    "sg:province":"Toledo",
    "wof:name":"Comunicaciones Talavera Mediterraneo S.l.",
    "wof:placetype":"venue"
},
  "geometry": {"coordinates":[-4.8139190674,39.9662017822],"type":"Point"}
}