{
  "type": "Feature",
  "properties": {
    "addr:full":"Pg Germanies (de Les), 82 Gandia Valencia 46700",
    "addr:housenumber":"82",
    "addr:postcode":"46700",
    "addr:street":"Pg Germanies De Les;Valencia",
    "iso:country":"ES",
    "sg:address":"Pg Germanies (de Les), 82",
    "sg:city":"Gandia",
    "sg:orig_category":"Cajas De Ahorro",
    "sg:phone":"+34 962 86 57 03",
    "sg:postcode":"46700",
    "sg:province":"Valencia",
    "wof:name":"Caja De Ahorros De Valencia Castellon Y Alicante",
    "wof:placetype":"venue"
},
  "geometry": {"coordinates":[-0.1896030009,38.9667663574],"type":"Point"}
}