{
  "type": "Feature",
  "properties": {
    "iso:country":"ES",
    "sg:address":"Xopada, 2",
    "sg:city":"Alqueria Asnar",
    "sg:orig_category":"Electricidad: Equipos Industriales, Componentes (fabricaci\u00d3n)",
    "sg:phone":"+34 966 51 71 50",
    "sg:postcode":"03829",
    "sg:province":"Alicante",
    "wof:name":"I.j.r. Electronics S.l.",
    "wof:placetype":"venue"
},
  "geometry": {"coordinates":[-0.4268589914,38.7745857239],"type":"Point"}
}