{
  "type": "Feature",
  "properties": {
    "iso:country":"ES",
    "sg:address":"Calle de Astorga, 61",
    "sg:city":"Ba\u00d1eza",
    "sg:orig_category":"Escayola Y Productos De Escayola (fabricaci\u00d3n, Al Por Mayor)",
    "sg:phone":"+34 987 64 17 45",
    "sg:postcode":"24750",
    "sg:province":"Le\u00f3n",
    "wof:name":"Amigo Gonzalez Francisco",
    "wof:placetype":"venue"
},
  "geometry": {"coordinates":[-5.9002776146,42.3023643494],"type":"Point"}
}