{
  "type": "Feature",
  "properties": {
    "iso:country":"ES",
    "sg:address":"Pase Delicias, 23",
    "sg:city":"Madrid",
    "sg:orig_category":"Inform\u00c1tica: Material Y Suministros",
    "sg:phone":"+34 915 27 92 78",
    "sg:postcode":"28045",
    "sg:province":"Madrid",
    "wof:name":"Cuerda Martin Nieto Maria Pilar",
    "wof:placetype":"venue"
},
  "geometry": {"coordinates":[-3.6926190853,40.4041900635],"type":"Point"}
}