{
  "type": "Feature",
  "properties": {
    "addr:full":"Avda Granada, 9 Jaen Ja\u00e9n 23001",
    "addr:housenumber":"9;jae\u0301n",
    "addr:postcode":"23001",
    "addr:street":"Avda Granada",
    "iso:country":"ES",
    "sg:address":"Avda Granada, 9",
    "sg:city":"Jaen",
    "sg:orig_category":"Comit\u00c9s De Organizaci\u00d3n De Exposiciones, Ferias, Salones",
    "sg:phone":"+34 953 24 18 98",
    "sg:postcode":"23001",
    "sg:province":"Ja\u00e9n",
    "wof:name":"Crespi Azafatas Promociones Y Congresos S.l.",
    "wof:placetype":"venue"
},
  "geometry": {"coordinates":[-3.7854990959,37.7691268921],"type":"Point"}
}