{
  "type": "Feature",
  "properties": {
    "iso:country":"ES",
    "sg:address":"Mercado Santa Barbara, S/n",
    "sg:city":"Vitoria-gasteiz",
    "sg:orig_category":"Sales (al Por Mayor)",
    "sg:phone":"+34 945 25 93 67",
    "sg:postcode":"01004",
    "sg:province":"\u00c1lava",
    "wof:name":"Alonso Lopez-leon Mariano",
    "wof:placetype":"venue"
},
  "geometry": {"coordinates":[-2.6667108536,42.8444061279],"type":"Point"}
}