{
  "type": "Feature",
  "properties": {
    "iso:country":"ES",
    "sg:address":"Avgd Valencia, 18",
    "sg:city":"Algimia De Alfara",
    "sg:orig_category":"Cooperativas Agr\u00cdcolas",
    "sg:phone":"+34 962 62 63 75",
    "sg:postcode":"46148",
    "sg:province":"Valencia",
    "wof:name":"Cooperativa Agricola El Porvenir",
    "wof:placetype":"venue"
},
  "geometry": {"coordinates":[-0.3646489978,39.7502441406],"type":"Point"}
}