{
  "type": "Feature",
  "properties": {
    "addr:full":"Carrer de Marina, 82 Barcelona Barcelona 08018",
    "addr:housenumber":"82",
    "addr:postcode":"08018",
    "addr:street":"Carrer De Marina",
    "iso:country":"ES",
    "sg:address":"Carrer de Marina, 82",
    "sg:city":"Barcelona",
    "sg:orig_category":"Agentes, Concesionarios Y Sucursales De Veh\u00cdculos",
    "sg:phone":"+34 933 00 26 50",
    "sg:postcode":"08018",
    "sg:province":"Barcelona",
    "wof:name":"Euronet Spain S.a.",
    "wof:placetype":"venue"
},
  "geometry": {"coordinates":[2.1891050339,41.3933181763],"type":"Point"}
}