{
  "type": "Feature",
  "properties": {
    "iso:country":"ES",
    "sg:address":"Calle de Amparo Usera, 40",
    "sg:city":"Madrid",
    "sg:orig_category":"Ortopedia General",
    "sg:phone":"+34 915 00 25 18",
    "sg:postcode":"28026",
    "sg:province":"Madrid",
    "wof:name":"Quiropedistas Berkiemann S.l.",
    "wof:placetype":"venue"
},
  "geometry": {"coordinates":[-3.7043600082,40.3872528076],"type":"Point"}
}