{
  "type": "Feature",
  "properties": {
    "addr:full":"Avgd Villalba De Lugo, 3 Quart Poblet Valencia 46930",
    "addr:housenumber":"3",
    "addr:postcode":"46930",
    "addr:street":"Lugo;Poblet",
    "iso:country":"ES",
    "sg:address":"Avgd Villalba De Lugo, 3",
    "sg:city":"Quart Poblet",
    "sg:orig_category":"Alimentaci\u00d3n General (al Por Menor)",
    "sg:phone":"+34 961 52 44 17",
    "sg:postcode":"46930",
    "sg:province":"Valencia",
    "wof:name":"Bort Millan Amparo",
    "wof:placetype":"venue"
},
  "geometry": {"coordinates":[-0.4419890046,39.482711792],"type":"Point"}
}