{
  "type": "Feature",
  "properties": {
    "iso:country":"ES",
    "sg:address":"Calle de Fuente (la), 79",
    "sg:city":"Alacant",
    "sg:orig_category":"Carnicer\u00cdas, Carnicer\u00cdas",
    "sg:phone":"+34 965 18 53 88",
    "sg:postcode":"03009",
    "sg:province":"Alicante",
    "wof:name":"Salazones Quintana S.l.",
    "wof:placetype":"venue"
},
  "geometry": {"coordinates":[-0.4973370135,38.3643112183],"type":"Point"}
}