{
  "type": "Feature",
  "properties": {
    "addr:full":"Bjad San Martin, 8 Zamora Zamora 49004",
    "addr:housenumber":"8",
    "addr:postcode":"49004",
    "addr:street":"San Martin",
    "iso:country":"ES",
    "sg:address":"Bjad San Martin, 8",
    "sg:city":"Zamora",
    "sg:orig_category":"Empresas De Carpinter\u00cda Met\u00c1lica",
    "sg:phone":"+34 980 53 05 83",
    "sg:postcode":"49004",
    "sg:province":"Zamora",
    "wof:name":"Carretero Pelayo Claudio",
    "wof:placetype":"venue"
},
  "geometry": {"coordinates":[-5.7457342148,41.5033302307],"type":"Point"}
}