{
  "type": "Feature",
  "properties": {
    "iso:country":"ES",
    "sg:address":"Calle de Mayor, 35",
    "sg:city":"Huete",
    "sg:orig_category":"Estancos",
    "sg:phone":"+34 969 37 10 38",
    "sg:postcode":"16500",
    "sg:province":"Cuenca",
    "wof:name":"Lopez Rubio Maria Jesus",
    "wof:placetype":"venue"
},
  "geometry": {"coordinates":[-2.6891388893,40.1436576843],"type":"Point"}
}