{
  "type": "Feature",
  "properties": {
    "iso:country":"ES",
    "sg:address":"Ctra Alovera (de), 24",
    "sg:city":"Azuqueca Henares",
    "sg:orig_category":"Alquiler De V\u00cddeo",
    "sg:phone":"+34 949 26 65 64",
    "sg:postcode":"19200",
    "sg:province":"Guadalajara",
    "wof:name":"Tavira Cuadrado Jose Antonio",
    "wof:placetype":"venue"
},
  "geometry": {"coordinates":[-3.2625069618,40.5713577271],"type":"Point"}
}