{
  "type": "Feature",
  "properties": {
    "addr:full":"Calle de Villaleal, 4 Catedral Murcia 30001",
    "addr:housenumber":"4",
    "addr:postcode":"30001",
    "addr:street":"Calle De Villaleal",
    "iso:country":"ES",
    "sg:address":"Calle de Villaleal, 4",
    "sg:city":"Catedral",
    "sg:orig_category":"Imprenta",
    "sg:phone":"+34 968 21 42 04",
    "sg:postcode":"30001",
    "sg:province":"Murcia",
    "wof:name":"Lopez Izquierdo Francisco",
    "wof:placetype":"venue"
},
  "geometry": {"coordinates":[-1.1299129725,37.9854888916],"type":"Point"}
}