{
  "type": "Feature",
  "properties": {
    "addr:full":"Carrer de Salvador Dali, 38 Palma Islas Baleares 07011",
    "addr:housenumber":"38",
    "addr:postcode":"07011",
    "addr:street":"Carrer De Salvador Dali",
    "iso:country":"ES",
    "sg:address":"Carrer de Salvador Dali, 38",
    "sg:city":"Palma",
    "sg:orig_category":"Mec\u00c1nico Del Autom\u00d3vil",
    "sg:phone":"+34 971 45 00 97",
    "sg:postcode":"07011",
    "sg:province":"Islas Baleares",
    "wof:name":"Joyma S.l.",
    "wof:placetype":"venue"
},
  "geometry": {"coordinates":[2.6337659359,39.5839195251],"type":"Point"}
}