{
  "type": "Feature",
  "properties": {
    "iso:country":"ES",
    "sg:address":"Av Sant Ildefons, 6",
    "sg:city":"Cornella Llobregat",
    "sg:orig_category":"Caf\u00c9s, Bares, Cervecer\u00cdas",
    "sg:phone":"+34 933 75 55 05",
    "sg:postcode":"08940",
    "sg:province":"Barcelona",
    "wof:name":"Sistelcom-telemensaje S.a.",
    "wof:placetype":"venue"
},
  "geometry": {"coordinates":[2.0828509331,41.3654212952],"type":"Point"}
}