{
  "type": "Feature",
  "properties": {
    "iso:country":"ES",
    "sg:address":"Calle de Lomas (de Las), 3",
    "sg:city":"Cordoba",
    "sg:orig_category":"Supermercados Y Hipermercados",
    "sg:phone":"+34 957 46 13 59",
    "sg:postcode":"14005",
    "sg:province":"C\u00f3rdoba",
    "wof:name":"Perez Siles Antonio",
    "wof:placetype":"venue"
},
  "geometry": {"coordinates":[-4.8141717911,37.8806915283],"type":"Point"}
}