{
  "type": "Feature",
  "properties": {
    "addr:full":"Plaza Nagusia, 4 Ordizia Guip\u00f9zcoa 20240",
    "addr:housenumber":"4",
    "addr:postcode":"20240",
    "addr:street":"Nagusia;Guipu\u0300Zcoa",
    "iso:country":"ES",
    "sg:address":"Plaza Nagusia, 4",
    "sg:city":"Ordizia",
    "sg:orig_category":"Parques De Atracciones Y Centros De Esparcimiento",
    "sg:phone":"+34 943 88 20 52",
    "sg:postcode":"20240",
    "sg:province":"Guip\u00f9zcoa",
    "wof:name":"Arregui Imaz Francisco",
    "wof:placetype":"venue"
},
  "geometry": {"coordinates":[-2.1802563667,43.053478241],"type":"Point"}
}