{
  "type": "Feature",
  "properties": {
    "iso:country":"ES",
    "sg:address":"Av Carmen Amaya, 30",
    "sg:city":"Hospitalet Llobregat",
    "sg:orig_category":"Molduras, Junquillos, Listones Y Molduras Perforadas",
    "sg:phone":"+34 932 63 19 61",
    "sg:postcode":"08902",
    "sg:province":"Barcelona",
    "wof:name":"Sepulveda Valencia Fatima",
    "wof:placetype":"venue"
},
  "geometry": {"coordinates":[2.1179709435,41.3551597595],"type":"Point"}
}