{
  "type": "Feature",
  "properties": {
    "iso:country":"ES",
    "sg:address":"Estacion, S/n",
    "sg:city":"Cehegin",
    "sg:orig_category":"Fabricaci\u00d3n, Importaci\u00d3n De L\u00c1mparas Y Bombillas",
    "sg:phone":"+34 968 74 06 39",
    "sg:postcode":"30430",
    "sg:province":"Murcia",
    "wof:name":"Gonzalez Morales Pedro",
    "wof:placetype":"venue"
},
  "geometry": {"coordinates":[-1.7919274569,38.0875396729],"type":"Point"}
}