{
  "type": "Feature",
  "properties": {
    "iso:country":"ES",
    "sg:address":"Calle de El Jabero, S/n",
    "sg:city":"Zaratan",
    "sg:orig_category":"Inmobiliaria (agencias)",
    "sg:phone":"+34 983 37 90 54",
    "sg:postcode":"47610",
    "sg:province":"Valladolid",
    "wof:name":"Progres 99 S.l.",
    "wof:placetype":"venue"
},
  "geometry": {"coordinates":[-4.7820091248,41.6547203064],"type":"Point"}
}