{
  "type": "Feature",
  "properties": {
    "iso:country":"ES",
    "sg:address":"B, 2",
    "sg:city":"Alcoi",
    "sg:orig_category":"Inform\u00c1tica, Ofim\u00c1tica (estudios, Asesor\u00cda, Ingenier\u00cda, Formaci\u00d3n)",
    "sg:phone":"+34 965 33 58 16",
    "sg:postcode":"03800",
    "sg:province":"Alicante",
    "wof:name":"A B M Informatica S.l.",
    "wof:placetype":"venue"
},
  "geometry": {"coordinates":[-0.462406,38.710079],"type":"Point"}
}