{
  "type": "Feature",
  "properties": {
    "iso:country":"ES",
    "sg:address":"Carrer de Radas, 13",
    "sg:city":"Barcelona",
    "sg:orig_category":"Bibliotecas, Mediatecas",
    "sg:phone":"+34 933 24 85 57",
    "sg:postcode":"08004",
    "sg:province":"Barcelona",
    "wof:name":"Entrega Rapit 2002 S.c.p.",
    "wof:placetype":"venue"
},
  "geometry": {"coordinates":[2.1612069607,41.3741188049],"type":"Point"}
}