{
  "type": "Feature",
  "properties": {
    "iso:country":"ES",
    "sg:address":"Carr Monestir De Lavaix (del), 6",
    "sg:city":"Pont Suert",
    "sg:orig_category":"Asesor\u00cda Fiscal Y Jur\u00cddica",
    "sg:phone":"+34 973 69 01 86",
    "sg:postcode":"25520",
    "sg:province":"Lleida",
    "wof:name":"Grup 90 Pont De Suert S.l.",
    "wof:placetype":"venue"
},
  "geometry": {"coordinates":[0.7411800027,42.4085388184],"type":"Point"}
}