{
  "type": "Feature",
  "properties": {
    "iso:country":"ES",
    "sg:address":"Calle de Cuarteles (de Los), 126",
    "sg:city":"Aranjuez",
    "sg:orig_category":"Material Y Suministros Para Relojer\u00cda",
    "sg:phone":"+34 918 92 17 82",
    "sg:postcode":"28300",
    "sg:province":"Madrid",
    "wof:name":"Martin Rodriguez Evaristo",
    "wof:placetype":"venue"
},
  "geometry": {"coordinates":[-3.5910518169,40.032409668],"type":"Point"}
}