{
  "type": "Feature",
  "properties": {
    "iso:country":"ES",
    "sg:address":"Calle de Fermin Caballero, 20",
    "sg:city":"Cuenca",
    "sg:orig_category":"Transporte En General",
    "sg:phone":"+34 969 22 04 96",
    "sg:postcode":"16004",
    "sg:province":"Cuenca",
    "wof:name":"Autobuses Alsina S.l.",
    "wof:placetype":"venue"
},
  "geometry": {"coordinates":[-2.1350080967,40.0667037964],"type":"Point"}
}