{
  "type": "Feature",
  "properties": {
    "iso:country":"ES",
    "sg:address":"Avda Real De Madrid, 79",
    "sg:city":"Valencia",
    "sg:orig_category":"Agentes, Concesionarios Y Sucursales De Camiones Y Veh\u00cdculos Industriales",
    "sg:phone":"+34 963 75 05 43",
    "sg:postcode":"46017",
    "sg:province":"Valencia",
    "wof:name":"Automocion Casanova S.a.",
    "wof:placetype":"venue"
},
  "geometry": {"coordinates":[-0.3920229971,39.43126297],"type":"Point"}
}