{
  "type": "Feature",
  "properties": {
    "iso:country":"ES",
    "sg:address":"Calle de Gustavo Adolfo Becquer, 8",
    "sg:city":"Puertollano",
    "sg:orig_category":"Empresas De Limpieza",
    "sg:phone":"+34 926 41 30 31",
    "sg:postcode":"13500",
    "sg:province":"Ciudad Real",
    "wof:name":"Manzanares Baeza Julia",
    "wof:placetype":"venue"
},
  "geometry": {"coordinates":[-4.1123538017,38.6858253479],"type":"Point"}
}