{
  "type": "Feature",
  "properties": {
    "addr:full":"Calle de Corregidor Juan Francisco De Lujan, 17 Madrid Madrid 28030",
    "addr:housenumber":"17",
    "addr:postcode":"madrid;28030",
    "addr:street":"Calle De Corregidor Juan Francisco De Lujan",
    "iso:country":"ES",
    "sg:address":"Calle de Corregidor Juan Francisco De Lujan, 17",
    "sg:city":"Madrid",
    "sg:orig_category":"Inform\u00c1tica (estudios, Servicios, Asesor\u00cda, Formaci\u00d3n)",
    "sg:phone":"+34 914 37 79 73",
    "sg:postcode":"28030",
    "sg:province":"Madrid",
    "sg:website":"www.apliclik.com",
    "wof:name":"Aplinet Click.s.l.",
    "wof:placetype":"venue"
},
  "geometry": {"coordinates":[-3.6492569447,40.4030609131],"type":"Point"}
}