{
  "type": "Feature",
  "properties": {
    "iso:country":"ES",
    "sg:address":"Txatxamendi Kalea, 3",
    "sg:city":"Lezo",
    "sg:orig_category":"Resinas Sint\u00c9ticas (fabricaci\u00d3n, Al Por Mayor)",
    "sg:phone":"+34 943 52 11 44",
    "sg:postcode":"20100",
    "sg:province":"Guip\u00f9zcoa",
    "wof:name":"Indarplas S.l.",
    "wof:placetype":"venue"
},
  "geometry": {"coordinates":[-1.8722610474,43.3248062134],"type":"Point"}
}