{
  "type": "Feature",
  "properties": {
    "addr:full":"Plaz Soledad Arias Moreno, 4 Robledo Del Mazo Toledo 45674",
    "addr:housenumber":"4",
    "addr:postcode":"45674",
    "addr:street":"Plaz Soledad Arias Moreno",
    "iso:country":"ES",
    "sg:address":"Plaz Soledad Arias Moreno, 4",
    "sg:city":"Robledo Del Mazo",
    "sg:orig_category":"Supermercados Y Hipermercados",
    "sg:phone":"+34 925 45 66 25",
    "sg:postcode":"45674",
    "sg:province":"Toledo",
    "wof:name":"Elez Fernandez Alfredo",
    "wof:placetype":"venue"
},
  "geometry": {"coordinates":[-4.9048628807,39.6097297668],"type":"Point"}
}