{
  "type": "Feature",
  "properties": {
    "iso:country":"ES",
    "sg:address":"Calle de Diego Gomez Salido, S/n",
    "sg:city":"Jerez De La Frontera",
    "sg:orig_category":"Seguridad En El Trabajo Y Prevenci\u00d3n De Riesgos Laborales",
    "sg:phone":"+34 956 32 68 37",
    "sg:postcode":"11401",
    "sg:province":"C\u00e1diz",
    "sg:website":"www.preving.com",
    "wof:name":"Preving Consultores S.l.",
    "wof:placetype":"venue"
},
  "geometry": {"coordinates":[-6.1296062469,36.6823043823],"type":"Point"}
}