{
  "type": "Feature",
  "properties": {
    "addr:full":"Calle de Nueva, 144 Benalua Guadix Granada 18510",
    "addr:housenumber":"144",
    "addr:postcode":"18510",
    "addr:street":"Calle De Nueva",
    "iso:country":"ES",
    "sg:address":"Calle de Nueva, 144",
    "sg:city":"Benalua Guadix",
    "sg:orig_category":"Inform\u00c1tica Equipo Y Programas (al Por Mayor)",
    "sg:phone":"+34 958 68 44 11",
    "sg:postcode":"18510",
    "sg:province":"Granada",
    "wof:name":"Mikrobit Cb",
    "wof:placetype":"venue"
},
  "geometry": {"coordinates":[-3.1670091152,37.3523483276],"type":"Point"}
}