{
  "type": "Feature",
  "properties": {
    "addr:full":"Calle de Don Quijote, 10 Elda Alicante 03600",
    "addr:housenumber":"10",
    "addr:postcode":"03600",
    "addr:street":"Calle De Don Quijote",
    "iso:country":"ES",
    "sg:address":"Calle de Don Quijote, 10",
    "sg:city":"Elda",
    "sg:orig_category":"Cl\u00cdnicas M\u00c9dicas",
    "sg:phone":"+34 965 38 01 36",
    "sg:postcode":"03600",
    "sg:province":"Alicante",
    "wof:name":"Policlinica Elda S.l.",
    "wof:placetype":"venue"
},
  "geometry": {"coordinates":[-0.7910869718,38.476726532],"type":"Point"}
}