{
  "type": "Feature",
  "properties": {
    "iso:country":"ES",
    "sg:address":"Diseminados, 45",
    "sg:city":"Urretxu",
    "sg:orig_category":"Empresas De Carpinter\u00cda Met\u00c1lica",
    "sg:phone":"+34 943 72 39 25",
    "sg:postcode":"20700",
    "sg:province":"Guip\u00f9zcoa",
    "wof:name":"Eutsi Montajes Y Servicios S.coop.",
    "wof:placetype":"venue"
},
  "geometry": {"coordinates":[-2.3134770393,43.086730957],"type":"Point"}
}