{
  "type": "Feature",
  "properties": {
    "iso:country":"ES",
    "sg:address":"Carrer de Cinca, 44",
    "sg:city":"Barcelona",
    "sg:orig_category":"Promotores Constructores",
    "sg:phone":"+34 933 45 05 66",
    "sg:postcode":"08030",
    "sg:province":"Barcelona",
    "wof:name":"Carrasco Murillo Feliciano",
    "wof:placetype":"venue"
},
  "geometry": {"coordinates":[2.1924331188,41.4375114441],"type":"Point"}
}