{
  "type": "Feature",
  "properties": {
    "iso:country":"ES",
    "sg:address":"Avgd Marti Pujol, 22",
    "sg:city":"Badalona",
    "sg:orig_category":"Abogados",
    "sg:phone":"+34 933 89 38 45",
    "sg:postcode":"08911",
    "sg:province":"Barcelona",
    "wof:name":"Lligo\u00f1a Domenech Jose Maria",
    "wof:placetype":"venue"
},
  "geometry": {"coordinates":[2.2483270168,41.4467773438],"type":"Point"}
}