{
  "type": "Feature",
  "properties": {
    "iso:country":"ES",
    "sg:address":"Carrer de Gran, 10",
    "sg:city":"S. Vicen\u00e7 Castellet",
    "sg:orig_category":"Cajas De Ahorro",
    "sg:phone":"+34 938 33 08 70",
    "sg:postcode":"08295",
    "sg:province":"Barcelona",
    "sg:website":"www.lacaixa.es",
    "wof:name":"Caixa D'estalvis I Pensions De Barcelona",
    "wof:placetype":"venue"
},
  "geometry": {"coordinates":[1.8629529476,41.6670417786],"type":"Point"}
}