{
  "type": "Feature",
  "properties": {
    "addr:full":"Calle de Embajador Vich, 3 Valencia Valencia 46002",
    "addr:housenumber":"3",
    "addr:postcode":"46002",
    "addr:street":"Calle De Embajador Vich",
    "iso:country":"ES",
    "sg:address":"Calle de Embajador Vich, 3",
    "sg:city":"Valencia",
    "sg:orig_category":"Edici\u00d3n De Diarios, Revistas, Boletines",
    "sg:phone":"+34 963 94 37 17",
    "sg:postcode":"46002",
    "sg:province":"Valencia",
    "sg:website":"www.edijardin.com",
    "wof:name":"Ediciones Jardin S.l.",
    "wof:placetype":"venue"
},
  "geometry": {"coordinates":[-0.3753600121,39.4726104736],"type":"Point"}
}