{
  "type": "Feature",
  "properties": {
    "iso:country":"ES",
    "sg:address":"Calle de Camilo Jose Cela, 20",
    "sg:city":"Villanueva Gallego",
    "sg:orig_category":"Arquitectos",
    "sg:phone":"+34 976 45 10 79",
    "sg:postcode":"50830",
    "sg:province":"Zaragoza",
    "wof:name":"Paris Izaga Jose Luis",
    "wof:placetype":"venue"
},
  "geometry": {"coordinates":[-0.8216747046,41.7753181458],"type":"Point"}
}