{
  "type": "Feature",
  "properties": {
    "iso:country":"ES",
    "sg:address":"Carrer de Can Peric, 18",
    "sg:city":"Sentmenat",
    "sg:orig_category":"Estudios, Instalaci\u00d3n De Climatizaci\u00d3n",
    "sg:phone":"+34 937 15 47 03",
    "sg:postcode":"08181",
    "sg:province":"Barcelona",
    "sg:website":"www.compact-cool.comm",
    "wof:name":"Prat Yllueca Ramon",
    "wof:placetype":"venue"
},
  "geometry": {"coordinates":[2.144012928,41.6091194153],"type":"Point"}
}