{
  "type": "Feature",
  "properties": {
    "addr:full":"Plaz Mercado, S/n Valencia Valencia 46001",
    "addr:housenumber":"/ n",
    "addr:postcode":"46001",
    "addr:street":"S",
    "iso:country":"ES",
    "sg:address":"Plaz Mercado, S/n",
    "sg:city":"Valencia",
    "sg:orig_category":"Turismo",
    "sg:phone":"+34 963 91 73 95",
    "sg:postcode":"46001",
    "sg:province":"Valencia",
    "wof:name":"Consulado De La Lonja",
    "wof:placetype":"venue"
},
  "geometry": {"coordinates":[-0.3788340092,39.4743080139],"type":"Point"}
}