{
  "type": "Feature",
  "properties": {
    "iso:country":"ES",
    "sg:address":"Calle de Valeria, 7",
    "sg:city":"Madrid",
    "sg:orig_category":"Chapister\u00cda",
    "sg:phone":"+34 915 52 46 37",
    "sg:postcode":"28007",
    "sg:province":"Madrid",
    "wof:name":"Talleres Belincar S.l.l.",
    "wof:placetype":"venue"
},
  "geometry": {"coordinates":[-3.669523716,40.4017066956],"type":"Point"}
}