{
  "type": "Feature",
  "properties": {
    "addr:full":"Calle de Poceros (los), 20 Pto. Rosario Las Palmas 35600",
    "addr:postcode":"35600",
    "addr:street":"Calle De Poceros Los;Pto.",
    "iso:country":"ES",
    "sg:address":"Calle de Poceros (los), 20",
    "sg:city":"Pto. Rosario",
    "sg:orig_category":"Audiovisuales (producci\u00d3n, Edici\u00d3n, Realizaci\u00d3n)",
    "sg:phone":"+34 928 85 93 94",
    "sg:postcode":"35600",
    "sg:province":"Las Palmas",
    "wof:name":"Masmusica S.l.",
    "wof:placetype":"venue"
},
  "geometry": {"coordinates":[-13.8600683212,28.5103816986],"type":"Point"}
}