{
  "type": "Feature",
  "properties": {
    "iso:country":"ES",
    "sg:address":"Calle de Isaac Peral, 2",
    "sg:city":"Matas-pinar-monte Rozas",
    "sg:orig_category":"Papeler\u00cdas, Librer\u00cdas",
    "sg:phone":"+34 916 30 39 92",
    "sg:postcode":"28290",
    "sg:province":"Madrid",
    "wof:name":"Matera Ciaccio Massimo",
    "wof:placetype":"venue"
},
  "geometry": {"coordinates":[-3.8964540958,40.5534515381],"type":"Point"}
}