{
  "type": "Feature",
  "properties": {
    "iso:country":"ES",
    "sg:address":"Rua Doutor Teixeiro (do), 5",
    "sg:city":"Santiago De Compostela",
    "sg:orig_category":"Procuradores",
    "sg:phone":"+34 981 58 18 28",
    "sg:postcode":"15701",
    "sg:province":"La Coru\u00f1a",
    "wof:name":"Gomez Martin Santiago",
    "wof:placetype":"venue"
},
  "geometry": {"coordinates":[-8.5447349548,42.8756408691],"type":"Point"}
}