{
  "type": "Feature",
  "properties": {
    "addr:full":"Calle de Estrella Polar, 26 Madrid Madrid 28007",
    "addr:housenumber":"26",
    "addr:postcode":"madrid;28007",
    "addr:street":"Calle De Estrella Polar",
    "iso:country":"ES",
    "sg:address":"Calle de Estrella Polar, 26",
    "sg:city":"Madrid",
    "sg:orig_category":"Molduras, Junquillos, Listones Y Molduras Perforadas",
    "sg:phone":"+34 914 09 28 60",
    "sg:postcode":"28007",
    "sg:province":"Madrid",
    "wof:name":"Onta\u00f1on Carrera Manuel",
    "wof:placetype":"venue"
},
  "geometry": {"coordinates":[-3.6661159992,40.4110298157],"type":"Point"}
}