{
  "type": "Feature",
  "properties": {
    "iso:country":"ES",
    "sg:address":"Carrer de Enric Prat De La Riba, 241",
    "sg:city":"Hospitalet Llobregat",
    "sg:orig_category":"Fabricaci\u00d3n Y Comercio De M\u00c1quinas",
    "sg:phone":"+34 933 37 22 61",
    "sg:postcode":"08901",
    "sg:province":"Barcelona",
    "wof:name":"Gomez Paez Julia",
    "wof:placetype":"venue"
},
  "geometry": {"coordinates":[2.1055579185,41.3606834412],"type":"Point"}
}