{
  "type": "Feature",
  "properties": {
    "iso:country":"ES",
    "sg:address":"Avda Puerto De Santamaria, 10",
    "sg:city":"Calpe",
    "sg:orig_category":"Productores Recolectores, Venta Directa De Vinos",
    "sg:phone":"+34 965 83 92 96",
    "sg:postcode":"03710",
    "sg:province":"Alicante",
    "wof:name":"Pineda Fluixa Maria Iluminada",
    "wof:placetype":"venue"
},
  "geometry": {"coordinates":[0.0535200015,38.6515808105],"type":"Point"}
}