{
  "type": "Feature",
  "properties": {
    "addr:full":"Calle de Tarifa, 40 Tomares Sevilla 41940",
    "addr:housenumber":"40",
    "addr:postcode":"41940",
    "addr:street":"Calle De Tarifa",
    "iso:country":"ES",
    "sg:address":"Calle de Tarifa, 40",
    "sg:city":"Tomares",
    "sg:orig_category":"Chapister\u00cda",
    "sg:phone":"+34 954 15 15 21",
    "sg:postcode":"41940",
    "sg:province":"Sevilla",
    "wof:name":"Ochoa Florido Gaspar",
    "wof:placetype":"venue"
},
  "geometry": {"coordinates":[-6.0297794342,37.376247406],"type":"Point"}
}