{
  "type": "Feature",
  "properties": {
    "iso:country":"ES",
    "sg:address":"Avda America (de), 46",
    "sg:city":"Granada",
    "sg:orig_category":"Agencias De Viajes",
    "sg:phone":"+34 958 18 30 86",
    "sg:postcode":"18008",
    "sg:province":"Granada",
    "wof:name":"Ruiz Morel Jose Miguel",
    "wof:placetype":"venue"
},
  "geometry": {"coordinates":[-3.5934290886,37.160358429],"type":"Point"}
}