{
  "type": "Feature",
  "properties": {
    "addr:full":"Calle de Tiradores Bajos B, 7 Cuenca Cuenca 16001",
    "addr:housenumber":"7",
    "addr:postcode":"16001",
    "addr:street":"Calle De Tiradores",
    "iso:country":"ES",
    "sg:address":"Calle de Tiradores Bajos B, 7",
    "sg:city":"Cuenca",
    "sg:orig_category":"Iglesia Cat\u00d3lica",
    "sg:phone":"+34 969 23 26 72",
    "sg:postcode":"16001",
    "sg:province":"Cuenca",
    "wof:name":"Parroquia Del Santisimo Cristo Del Amparo",
    "wof:placetype":"venue"
},
  "geometry": {"coordinates":[-2.1313164234,40.0738716125],"type":"Point"}
}