{
  "type": "Feature",
  "properties": {
    "addr:full":"P I San Cristobal, S/n Espinardo Murcia 30100",
    "addr:postcode":"30100",
    "addr:street":"P I San Cristobal S / N",
    "iso:country":"ES",
    "sg:address":"P I San Cristobal, S/n",
    "sg:city":"Espinardo",
    "sg:orig_category":"Cerrajer\u00cda, Ferrallista",
    "sg:phone":"+34 968 83 04 40",
    "sg:postcode":"30100",
    "sg:province":"Murcia",
    "wof:name":"Campoy De La Concepcion Manuel",
    "wof:placetype":"venue"
},
  "geometry": {"coordinates":[-1.155418992,38.0091514587],"type":"Point"}
}