{
  "type": "Feature",
  "properties": {
    "iso:country":"ES",
    "sg:address":"Calle de Zezilia Gallartzagoitia, 9",
    "sg:city":"Amorebieta",
    "sg:orig_category":"Moda",
    "sg:phone":"+34 946 73 11 50",
    "sg:postcode":"48340",
    "sg:province":"Vizcaya",
    "wof:name":"Umeak S.l",
    "wof:placetype":"venue"
},
  "geometry": {"coordinates":[-2.7333989143,43.2196388245],"type":"Point"}
}