{
  "type": "Feature",
  "properties": {
    "addr:full":"Ctra Madrid, S/n Jaen Ja\u00e9n 23009",
    "addr:housenumber":"s / n;jae\u0301n",
    "addr:postcode":"23009",
    "addr:street":"Ctra Madrid",
    "iso:country":"ES",
    "sg:address":"Ctra Madrid, S/n",
    "sg:city":"Jaen",
    "sg:orig_category":"Agricultores, Agricultores",
    "sg:phone":"+34 953 28 07 34",
    "sg:postcode":"23009",
    "sg:province":"Ja\u00e9n",
    "wof:name":"Rafael Y Pedro Antonio Toledano Colmenero Cdad",
    "wof:placetype":"venue"
},
  "geometry": {"coordinates":[-3.7803349495,37.7929763794],"type":"Point"}
}