{
  "type": "Feature",
  "properties": {
    "addr:full":"El Cementerio, S/n Benavides Le\u00f3n 24280",
    "addr:housenumber":"s / n",
    "addr:postcode":"24280",
    "addr:street":"El;Leo\u0301N",
    "iso:country":"ES",
    "sg:address":"El Cementerio, S/n",
    "sg:city":"Benavides",
    "sg:orig_category":"Fabrica De Cer\u00c1micas",
    "sg:phone":"+34 987 37 01 03",
    "sg:postcode":"24280",
    "sg:province":"Le\u00f3n",
    "wof:name":"Maderas Y Materiales De Construccion Arry C.b.",
    "wof:placetype":"venue"
},
  "geometry": {"coordinates":[-5.8994832039,42.4986763],"type":"Point"}
}