{
  "type": "Feature",
  "properties": {
    "iso:country":"ES",
    "sg:address":"Carr Constitucio, 17",
    "sg:city":"Vila Joiosa",
    "sg:orig_category":"Peluqueros: De Se\u00d1oras",
    "sg:phone":"+34 965 89 48 47",
    "sg:postcode":"03570",
    "sg:province":"Alicante",
    "wof:name":"Vicent Igual Maria Carmen",
    "wof:placetype":"venue"
},
  "geometry": {"coordinates":[-0.2327190042,38.505821228],"type":"Point"}
}