{
  "type": "Feature",
  "properties": {
    "iso:country":"ES",
    "sg:address":"Calle de Cubo (el), 2",
    "sg:city":"Autol",
    "sg:orig_category":"Contenedores (mercanc\u00cdas)",
    "sg:phone":"+34 941 39 06 49",
    "sg:postcode":"26560",
    "sg:province":"La Rioja",
    "wof:name":"Cristobal Tomas Jose Antonio",
    "wof:placetype":"venue"
},
  "geometry": {"coordinates":[-2.0061047077,42.2182159424],"type":"Point"}
}