{
  "type": "Feature",
  "properties": {
    "iso:country":"ES",
    "sg:address":"Carrer de Mallorca, 3",
    "sg:city":"Zona Costera",
    "sg:orig_category":"Inmobiliaria (agencias)",
    "sg:phone":"+34 977 80 12 95",
    "sg:postcode":"43883",
    "sg:province":"Tarragona",
    "wof:name":"Esplugas Lafarga Marina",
    "wof:placetype":"venue"
},
  "geometry": {"coordinates":[1.4600640535,41.1879272461],"type":"Point"}
}