{
  "type": "Feature",
  "properties": {
    "iso:country":"ES",
    "sg:address":"Barr Mazas (las), 11",
    "sg:city":"Liencres",
    "sg:orig_category":"Chapister\u00cda",
    "sg:phone":"+34 942 57 86 32",
    "sg:postcode":"39120",
    "sg:province":"Cantabria",
    "wof:name":"Escalante Caso Alfredo",
    "wof:placetype":"venue"
},
  "geometry": {"coordinates":[-3.9269039631,43.4604797363],"type":"Point"}
}