{
  "type": "Feature",
  "properties": {
    "addr:full":"Calle de Altamira, 30 Almeria Almer\u00eda 04005",
    "addr:housenumber":"30",
    "addr:postcode":"04005",
    "addr:street":"Calle De Altamira",
    "iso:country":"ES",
    "sg:address":"Calle de Altamira, 30",
    "sg:city":"Almeria",
    "sg:orig_category":"Bisuter\u00cda, Joyer\u00cda, Relojer\u00cda (al Por Menor)",
    "sg:phone":"+34 950 22 59 74",
    "sg:postcode":"04005",
    "sg:province":"Almer\u00eda",
    "wof:name":"Besemat S.l.",
    "wof:placetype":"venue"
},
  "geometry": {"coordinates":[-2.4575493336,36.8395042419],"type":"Point"}
}