{
  "type": "Feature",
  "properties": {
    "addr:full":"Calle de Francisco A\u00d1on, 38 Coru\u00d1a La Coru\u00f1a 15010",
    "addr:housenumber":"38",
    "addr:postcode":"15010",
    "addr:street":"Calle De Francisco An\u0303On;Corun\u0303A",
    "iso:country":"ES",
    "sg:address":"Calle de Francisco A\u00d1on, 38",
    "sg:city":"Coru\u00d1a",
    "sg:classifiers":[
        {
            "category":"Personal",
            "subcategory":"Barber",
            "type":"Services"
        }
    ],
    "sg:phone":"+34 981 25 08 22",
    "sg:postcode":"15010",
    "sg:province":"La Coru\u00f1a",
    "sg:tags":[
        "caballeros",
        "de",
        "peluqueros"
    ],
    "wof:name":"Iglesias Calvi\u00f1o Manuel",
    "wof:placetype":"venue"
},
  "geometry": {"coordinates":[-8.4189996719,43.3643112183],"type":"Point"}
}