{
  "type": "Feature",
  "properties": {
    "addr:full":"Plaz Mayor, 13 Burgos Burgos 09003",
    "addr:housenumber":"13",
    "addr:postcode":"09003",
    "addr:street":"Plaz Mayor",
    "iso:country":"ES",
    "sg:address":"Plaz Mayor, 13",
    "sg:city":"Burgos",
    "sg:orig_category":"Ropa Para Se\u00d1oras (al Por Menor)",
    "sg:phone":"+34 947 20 79 92",
    "sg:postcode":"09003",
    "sg:province":"Burgos",
    "wof:name":"Carrera Rabago Angel Manuel",
    "wof:placetype":"venue"
},
  "geometry": {"coordinates":[-3.7016890049,42.3413772583],"type":"Point"}
}