{
  "type": "Feature",
  "properties": {
    "addr:full":"Plaz Parque De Capuchinos, 5 Jerez De La Frontera C\u00e1diz 11405",
    "addr:postcode":"11405",
    "iso:country":"ES",
    "sg:address":"Plaz Parque De Capuchinos, 5",
    "sg:city":"Jerez De La Frontera",
    "sg:orig_category":"Ense\u00d1anza, Formaci\u00d3n Profesional: Aprendizaje",
    "sg:phone":"+34 956 18 01 86",
    "sg:postcode":"11405",
    "sg:province":"C\u00e1diz",
    "wof:name":"Servicio Andaluz De Empleo",
    "wof:placetype":"venue"
},
  "geometry": {"coordinates":[-6.1310372353,36.6931838989],"type":"Point"}
}