{
  "type": "Feature",
  "properties": {
    "addr:full":"Calle de Hospicio, 4 Calasparra Murcia 30420",
    "addr:housenumber":"4",
    "addr:postcode":"30420",
    "addr:street":"Calle De Hospicio",
    "iso:country":"ES",
    "sg:address":"Calle de Hospicio, 4",
    "sg:city":"Calasparra",
    "sg:orig_category":"Parafarmacias",
    "sg:phone":"+34 968 72 03 71",
    "sg:postcode":"30420",
    "sg:province":"Murcia",
    "wof:name":"Moya Sanchez Maria Dolores",
    "wof:placetype":"venue"
},
  "geometry": {"coordinates":[-1.6969130039,38.2302093506],"type":"Point"}
}