{
  "type": "Feature",
  "properties": {
    "addr:full":"Carr Juan Xxiii, 22 Quart Poblet Valencia 46930",
    "addr:housenumber":"22",
    "addr:postcode":"46930",
    "addr:street":"Carr Juan Xxiii;Poblet",
    "iso:country":"ES",
    "sg:address":"Carr Juan Xxiii, 22",
    "sg:city":"Quart Poblet",
    "sg:orig_category":"Artesan\u00cda",
    "sg:phone":"+34 961 52 45 94",
    "sg:postcode":"46930",
    "sg:province":"Valencia",
    "wof:name":"Valls Alca\u00f1iz Julian Salvador",
    "wof:placetype":"venue"
},
  "geometry": {"coordinates":[-0.4411270022,39.4815330505],"type":"Point"}
}