{
  "type": "Feature",
  "properties": {
    "iso:country":"ES",
    "sg:address":"Avda Diputacion, 61",
    "sg:city":"Palma Rio",
    "sg:orig_category":"Electrodom\u00c9sticos (al Por Menor)",
    "sg:phone":"+34 957 64 66 33",
    "sg:postcode":"14700",
    "sg:province":"C\u00f3rdoba",
    "wof:name":"Cano Navarro Avenida S.l.",
    "wof:placetype":"venue"
},
  "geometry": {"coordinates":[-5.2795991898,37.7004241943],"type":"Point"}
}