{
  "type": "Feature",
  "properties": {
    "iso:country":"ES",
    "sg:address":"Rua Rosalia De Castro, 36",
    "sg:city":"Pontevedra",
    "sg:orig_category":"Arquitectos",
    "sg:phone":"+34 986 85 01 94",
    "sg:postcode":"36001",
    "sg:province":"Pontevedra",
    "wof:name":"Eyo Valladares Pelayo Celso",
    "wof:placetype":"venue"
},
  "geometry": {"coordinates":[-8.6480302811,42.4279785156],"type":"Point"}
}