{
  "type": "Feature",
  "properties": {
    "iso:country":"ES",
    "sg:address":"Plaz San Francisco, 12",
    "sg:city":"Zaragoza",
    "sg:orig_category":"M\u00c9dicos: Naturistas",
    "sg:phone":"+34 976 35 94 77",
    "sg:postcode":"50006",
    "sg:province":"Zaragoza",
    "wof:name":"Jimeno Recarte Maria Luisa",
    "wof:placetype":"venue"
},
  "geometry": {"coordinates":[-0.8955039978,41.6409797668],"type":"Point"}
}