{
  "type": "Feature",
  "properties": {
    "iso:country":"ES",
    "sg:address":"Pase Marques De Corvera, 34",
    "sg:city":"Carmen",
    "sg:orig_category":"Zapatos (al Por Menor)",
    "sg:phone":"+34 968 26 30 10",
    "sg:postcode":"30002",
    "sg:province":"Murcia",
    "wof:name":"Robles Navarro Antonio",
    "wof:placetype":"venue"
},
  "geometry": {"coordinates":[-1.1302499771,37.9829597473],"type":"Point"}
}