{
  "type": "Feature",
  "properties": {
    "addr:full":"Ctra. Megeces, S/n Mojados Valladolid 47250",
    "addr:housenumber":"s / n",
    "addr:postcode":"47250",
    "addr:street":"Ctra. Megeces",
    "iso:country":"ES",
    "sg:address":"Ctra. Megeces, S/n",
    "sg:city":"Mojados",
    "sg:orig_category":"Fabricaci\u00d3n De Quesos",
    "sg:phone":"+34 983 60 71 31",
    "sg:postcode":"47250",
    "sg:province":"Valladolid",
    "wof:name":"Quesos Mu\u00f1iz S.a.",
    "wof:placetype":"venue"
},
  "geometry": {"coordinates":[-4.6654090881,41.4321861267],"type":"Point"}
}