{
  "type": "Feature",
  "properties": {
    "iso:country":"ES",
    "sg:address":"Calle de San Martin, 27",
    "sg:city":"Donostia-san Sebastian",
    "sg:orig_category":"Trajes Y Adornos De Boda (confecci\u00d3n, Al Por Menor)",
    "sg:phone":"+34 943 42 07 34",
    "sg:postcode":"20005",
    "sg:province":"Guip\u00f9zcoa",
    "wof:name":"Financiera Pronovias S.a.",
    "wof:placetype":"venue"
},
  "geometry": {"coordinates":[-1.9831490517,43.3168258667],"type":"Point"}
}