{
  "type": "Feature",
  "properties": {
    "addr:full":"Carrer de Can Terres, 115 Garriga Barcelona 08530",
    "addr:housenumber":"115",
    "addr:postcode":"08530",
    "addr:street":"Carrer De Can Terres",
    "iso:country":"ES",
    "sg:address":"Carrer de Can Terres, 115",
    "sg:city":"Garriga",
    "sg:orig_category":"Asesor\u00cda Fiscal Y Jur\u00cddica",
    "sg:phone":"+34 938 71 53 21",
    "sg:postcode":"08530",
    "sg:province":"Barcelona",
    "wof:name":"Doys Roura Joaquim",
    "wof:placetype":"venue"
},
  "geometry": {"coordinates":[2.2860848904,41.6744003296],"type":"Point"}
}