{
  "type": "Feature",
  "properties": {
    "addr:full":"Avda Victoria, 2 Ronda M\u00e1laga 29400",
    "addr:housenumber":"2",
    "addr:postcode":"29400",
    "addr:street":"Avda Victoria;Ronda Ma\u0301Laga",
    "iso:country":"ES",
    "sg:address":"Avda Victoria, 2",
    "sg:city":"Ronda",
    "sg:orig_category":"Agentes Generales De Seguros",
    "sg:phone":"+34 952 87 63 04",
    "sg:postcode":"29400",
    "sg:province":"M\u00e1laga",
    "wof:name":"Sociedad Agencia De Seguros Toro Truncer S.l.",
    "wof:placetype":"venue"
},
  "geometry": {"coordinates":[-5.1685490608,36.7470779419],"type":"Point"}
}