{
  "type": "Feature",
  "properties": {
    "iso:country":"ES",
    "sg:address":"Carr Pintor Calbo, 5",
    "sg:city":"Mao",
    "sg:orig_category":"Alimentaci\u00d3n General (al Por Menor)",
    "sg:phone":"+34 971 36 73 55",
    "sg:postcode":"07703",
    "sg:province":"Islas Baleares",
    "wof:name":"Taltavull Sintes Jaime",
    "wof:placetype":"venue"
},
  "geometry": {"coordinates":[4.2585849762,39.885597229],"type":"Point"}
}