{
  "type": "Feature",
  "properties": {
    "iso:country":"ES",
    "sg:address":"Rua Isaac Peral, 12",
    "sg:city":"Vigo",
    "sg:orig_category":"Alumbrados",
    "sg:phone":"+34 986 22 55 36",
    "sg:postcode":"36201",
    "sg:province":"Pontevedra",
    "wof:name":"Vascogali S.l.",
    "wof:placetype":"venue"
},
  "geometry": {"coordinates":[-8.7082767487,42.2386360168],"type":"Point"}
}