{
  "type": "Feature",
  "properties": {
    "iso:country":"ES",
    "sg:address":"Calle de San Francisco, 13",
    "sg:city":"Oviedo",
    "sg:orig_category":"Construcciones Met\u00c1licas",
    "sg:phone":"+34 985 21 92 58",
    "sg:postcode":"33003",
    "sg:province":"Asturias",
    "wof:name":"Indemesa S.l.",
    "wof:placetype":"venue"
},
  "geometry": {"coordinates":[-5.8479290009,43.3617897034],"type":"Point"}
}