{
  "type": "Feature",
  "properties": {
    "iso:country":"ES",
    "sg:address":"Calle de Lorenzo Pardo, 24",
    "sg:city":"Zaragoza",
    "sg:orig_category":"Comidas Por Encargo, Organizaci\u00d3n De Recepciones",
    "sg:phone":"+34 976 49 62 97",
    "sg:postcode":"50008",
    "sg:province":"Zaragoza",
    "wof:name":"Abad Duato Antonio",
    "wof:placetype":"venue"
},
  "geometry": {"coordinates":[-0.875495,41.643837],"type":"Point"}
}