{
  "type": "Feature",
  "properties": {
    "iso:country":"ES",
    "sg:address":"Carrer de Santiago Rusi\u00d1ol, 36",
    "sg:city":"Sitges",
    "sg:orig_category":"Alquiler De V\u00cddeo",
    "sg:phone":"+34 938 94 42 12",
    "sg:postcode":"08870",
    "sg:province":"Barcelona",
    "wof:name":"Mora Aragon Angel",
    "wof:placetype":"venue"
},
  "geometry": {"coordinates":[1.8114819527,41.2376403809],"type":"Point"}
}