{
  "type": "Feature",
  "properties": {
    "iso:country":"ES",
    "sg:address":"Avda Parque, S/n",
    "sg:city":"Isla Cristina",
    "sg:orig_category":"Ropa Para Se\u00d1oras Y Caballeros (al Por Menor)",
    "sg:phone":"+34 959 33 24 82",
    "sg:postcode":"21410",
    "sg:province":"Huelva",
    "wof:name":"Somolinos Perez Israel",
    "wof:placetype":"venue"
},
  "geometry": {"coordinates":[-7.3163437843,37.1966667175],"type":"Point"}
}