{
  "type": "Feature",
  "properties": {
    "addr:full":"Avda Andalucia, 196 Dos Hermanas Sevilla 41700",
    "addr:housenumber":"196",
    "addr:postcode":"41700",
    "addr:street":"Avda Andalucia;Sevilla",
    "iso:country":"ES",
    "sg:address":"Avda Andalucia, 196",
    "sg:city":"Dos Hermanas",
    "sg:orig_category":"Muebles, Minoristas",
    "sg:phone":"+34 954 72 19 74",
    "sg:postcode":"41700",
    "sg:province":"Sevilla",
    "wof:name":"2h Borbon S.l.",
    "wof:placetype":"venue"
},
  "geometry": {"coordinates":[-5.920746,37.279263],"type":"Point"}
}