{
  "type": "Feature",
  "properties": {
    "addr:full":"Calle de Martin Ramos, 49 Puerto Santa Cruz C\u00e1ceres 10261",
    "addr:housenumber":"49",
    "addr:postcode":"10261",
    "addr:street":"Calle De Martin Ramos;Santa Cruz Ca\u0301Ceres",
    "iso:country":"ES",
    "sg:address":"Calle de Martin Ramos, 49",
    "sg:city":"Puerto Santa Cruz",
    "sg:orig_category":"Arquitectos",
    "sg:phone":"+34 927 34 20 67",
    "sg:postcode":"10261",
    "sg:province":"C\u00e1ceres",
    "wof:name":"Solis Merino Oscar",
    "wof:placetype":"venue"
},
  "geometry": {"coordinates":[-5.8580589294,39.3144416809],"type":"Point"}
}