{
  "type": "Feature",
  "properties": {
    "iso:country":"ES",
    "sg:address":"C/ Peru, 38",
    "sg:city":"Alcoi",
    "sg:orig_category":"Asociaciones Y Clubs Deportivos",
    "sg:phone":"+34 965 33 99 89",
    "sg:postcode":"03803",
    "sg:province":"Alicante",
    "wof:name":"Club Deportivo G. Y R.",
    "wof:placetype":"venue"
},
  "geometry": {"coordinates":[-0.4815460145,38.7014694214],"type":"Point"}
}