{
  "type": "Feature",
  "properties": {
    "addr:full":"Calle de Navarro Villoslada, 10 Vitoria-gasteiz \u00c1lava 01012",
    "addr:housenumber":"10",
    "addr:postcode":"01012",
    "addr:street":"Calle De Navarro Villoslada",
    "iso:country":"ES",
    "sg:address":"Calle de Navarro Villoslada, 10",
    "sg:city":"Vitoria-gasteiz",
    "sg:orig_category":"Ropa Para Se\u00d1oras (al Por Menor)",
    "sg:phone":"+34 945 22 47 85",
    "sg:postcode":"01012",
    "sg:province":"\u00c1lava",
    "wof:name":"Aguirre Villamor Maria Concepcion",
    "wof:placetype":"venue"
},
  "geometry": {"coordinates":[-2.6790418625,42.8535995483],"type":"Point"}
}