{
  "type": "Feature",
  "properties": {
    "addr:full":"Abelendo, 1 Abelendo Pontevedra 36954",
    "addr:housenumber":"1",
    "addr:postcode":"36954",
    "addr:street":"Abelendo",
    "iso:country":"ES",
    "sg:address":"Abelendo, 1",
    "sg:city":"Abelendo",
    "sg:orig_category":"Distribuci\u00d3n De Petr\u00d3leo Y Derivados",
    "sg:phone":"+34 986 39 31 13",
    "sg:postcode":"36954",
    "sg:province":"Pontevedra",
    "wof:name":"Gasoleo De Morrazo Sanchilan S.l.",
    "wof:placetype":"venue"
},
  "geometry": {"coordinates":[-8.6480531693,42.4336204529],"type":"Point"}
}