{
  "type": "Feature",
  "properties": {
    "addr:full":"Avda Florez Estrada, 37 Nore\u00f1a Asturias 33180",
    "addr:housenumber":"37",
    "addr:postcode":"33180",
    "addr:street":"Avda Florez Estrada",
    "iso:country":"ES",
    "sg:address":"Avda Florez Estrada, 37",
    "sg:city":"Nore\u00f1a",
    "sg:orig_category":"Peluquer\u00cdas, Peluquer\u00cda Mixta",
    "sg:phone":"+34 985 74 30 88",
    "sg:postcode":"33180",
    "sg:province":"Asturias",
    "wof:name":"Rio Martinez Maria Isabel Del",
    "wof:placetype":"venue"
},
  "geometry": {"coordinates":[-5.7053990364,43.3933410645],"type":"Point"}
}