{
  "type": "Feature",
  "properties": {
    "iso:country":"ES",
    "sg:address":"Calle de Bolivar, 26",
    "sg:city":"Madrid",
    "sg:orig_category":"Servicio De Salud",
    "sg:phone":"+34 914 68 04 77",
    "sg:postcode":"28045",
    "sg:province":"Madrid",
    "wof:name":"Romero Esteso Julia",
    "wof:placetype":"venue"
},
  "geometry": {"coordinates":[-3.6902484894,40.3926506042],"type":"Point"}
}