{
  "type": "Feature",
  "properties": {
    "iso:country":"ES",
    "sg:address":"Calle de Zaragoza, 4",
    "sg:city":"Sevilla",
    "sg:orig_category":"Venta, Alquiler De Instrumentos Y Accesorios De M\u00dasica",
    "sg:phone":"+34 954 22 45 57",
    "sg:postcode":"41001",
    "sg:province":"Sevilla",
    "wof:name":"Cayela Cayela Juan Luis",
    "wof:placetype":"venue"
},
  "geometry": {"coordinates":[-5.9992389679,37.3892097473],"type":"Point"}
}