{
  "type": "Feature",
  "properties": {
    "addr:full":"Calle de Jose Zorrilla, 105 Segovia Segovia 40002",
    "addr:housenumber":"105",
    "addr:postcode":"40002",
    "addr:street":"Calle De Jose Zorrilla",
    "iso:country":"ES",
    "sg:address":"Calle de Jose Zorrilla, 105",
    "sg:city":"Segovia",
    "sg:orig_category":"Tintes (fabricaci\u00d3n, Al Por Mayor)",
    "sg:phone":"+34 921 43 71 38",
    "sg:postcode":"40002",
    "sg:province":"Segovia",
    "wof:name":"Laguna Martin Cdad.",
    "wof:placetype":"venue"
},
  "geometry": {"coordinates":[-4.1140937805,40.9387435913],"type":"Point"}
}