{
  "type": "Feature",
  "properties": {
    "iso:country":"ES",
    "sg:address":"Ntra Sra Perpetuo Socorro, 3",
    "sg:city":"Almoradi",
    "sg:orig_category":"Institutos De Belleza",
    "sg:phone":"+34 966 78 13 65",
    "sg:postcode":"03160",
    "sg:province":"Alicante",
    "wof:name":"Parres Filiu Carmen Inmaculada",
    "wof:placetype":"venue"
},
  "geometry": {"coordinates":[-0.7926859856,38.1107788086],"type":"Point"}
}