{
  "type": "Feature",
  "properties": {
    "iso:country":"ES",
    "sg:address":"C/ Candalix, 6",
    "sg:city":"Elche",
    "sg:orig_category":"Inmobiliaria (agencias)",
    "sg:phone":"+34 965 42 46 69",
    "sg:postcode":"03202",
    "sg:province":"Alicante",
    "wof:name":"Fernando Valero Y Asociados S.l.",
    "wof:placetype":"venue"
},
  "geometry": {"coordinates":[-0.6956359744,38.2706871033],"type":"Point"}
}