{
  "type": "Feature",
  "properties": {
    "addr:full":"Calle de San Pio V, 9 Valencia Valencia 46010",
    "addr:housenumber":"9",
    "addr:postcode":"46010",
    "addr:street":"Calle De San;V",
    "iso:country":"ES",
    "sg:address":"Calle de San Pio V, 9",
    "sg:city":"Valencia",
    "sg:orig_category":"Ense\u00d1anza: Profesiones Art\u00cdsticas",
    "sg:phone":"+34 963 69 03 38",
    "sg:postcode":"46010",
    "sg:province":"Valencia",
    "wof:name":"Real Academia De Bellas Artes De San Carlos De Valencia",
    "wof:placetype":"venue"
},
  "geometry": {"coordinates":[-0.3675990105,39.4771614075],"type":"Point"}
}