{
  "type": "Feature",
  "properties": {
    "addr:full":"Pl Cos, D'es, 5 Manacor Islas Baleares 07500",
    "addr:housenumber":"5",
    "addr:postcode":"07500",
    "addr:street":"Pl Cos D'Es",
    "iso:country":"ES",
    "sg:address":"Pl Cos, D'es, 5",
    "sg:city":"Manacor",
    "sg:orig_category":"Agencias De Viajes",
    "sg:phone":"+34 971 84 51 93",
    "sg:postcode":"07500",
    "sg:province":"Islas Baleares",
    "sg:website":"www.halconviajes.com",
    "wof:name":"Viajes Halcon S.a.",
    "wof:placetype":"venue"
},
  "geometry": {"coordinates":[3.2113089561,39.5681877136],"type":"Point"}
}