{
  "type": "Feature",
  "properties": {
    "addr:full":"Calle de Gayano Lluch, 16 Valencia Valencia 46025",
    "addr:housenumber":"16",
    "addr:postcode":"46025",
    "addr:street":"Calle De Gayano Lluch",
    "iso:country":"ES",
    "sg:address":"Calle de Gayano Lluch, 16",
    "sg:city":"Valencia",
    "sg:orig_category":"Peluquer\u00cdas, Peluquer\u00cda Mixta",
    "sg:phone":"+34 963 47 37 64",
    "sg:postcode":"46025",
    "sg:province":"Valencia",
    "wof:name":"Rissos 21 S.l.",
    "wof:placetype":"venue"
},
  "geometry": {"coordinates":[-0.3805890083,39.4916267395],"type":"Point"}
}