{
  "type": "Feature",
  "properties": {
    "iso:country":"ES",
    "sg:address":"Calle de Estacion, 58",
    "sg:city":"Mendavia",
    "sg:orig_category":"Empresas De Carpinter\u00cda Met\u00c1lica",
    "sg:phone":"+34 948 69 50 01",
    "sg:postcode":"31587",
    "sg:province":"Navarra",
    "wof:name":"Jesus Angel Romero Cordovin Y Otros Cdad",
    "wof:placetype":"venue"
},
  "geometry": {"coordinates":[-2.2006690502,42.4419708252],"type":"Point"}
}