{
  "type": "Feature",
  "properties": {
    "iso:country":"ES",
    "sg:address":"Av. Fisterra, S/n",
    "sg:city":"Laracha",
    "sg:orig_category":"Florister\u00cdas",
    "sg:phone":"+34 981 60 60 40",
    "sg:postcode":"15145",
    "sg:province":"La Coru\u00f1a",
    "wof:name":"Cotelo Vilari\u00f1o Josefa",
    "wof:placetype":"venue"
},
  "geometry": {"coordinates":[-8.5791826248,43.2475547791],"type":"Point"}
}