{
  "type": "Feature",
  "properties": {
    "iso:country":"ES",
    "sg:address":"Reboredo, 20",
    "sg:city":"Merza",
    "sg:orig_category":"Madera (al Por Menor)",
    "sg:phone":"+34 986 58 35 72",
    "sg:postcode":"36580",
    "sg:province":"Pontevedra",
    "wof:name":"Guzman Pereira Natalia",
    "wof:placetype":"venue"
},
  "geometry": {"coordinates":[-8.2612113953,42.7677345276],"type":"Point"}
}