{
  "type": "Feature",
  "properties": {
    "iso:country":"ES",
    "sg:address":"Carrer de Esglesia, 228",
    "sg:city":"Calella",
    "sg:orig_category":"Zapatos (al Por Menor)",
    "sg:phone":"+34 937 69 74 65",
    "sg:postcode":"08370",
    "sg:province":"Barcelona",
    "wof:name":"Sabateria Infantil Ferlau S.l.",
    "wof:placetype":"venue"
},
  "geometry": {"coordinates":[2.6651170254,41.6156272888],"type":"Point"}
}