{
  "type": "Feature",
  "properties": {
    "addr:full":"Ptge Patriarca, 99997 Barcelona Barcelona 08002",
    "addr:postcode":"99997;08002",
    "addr:street":"Ptge Patriarca",
    "iso:country":"ES",
    "sg:address":"Ptge Patriarca, 99997",
    "sg:city":"Barcelona",
    "sg:orig_category":"Fotograf\u00cda Art\u00cdstica Y Retratos",
    "sg:phone":"+34 931 84 08 77",
    "sg:postcode":"08002",
    "sg:province":"Barcelona",
    "wof:name":"Joan Cabaces  S.l.",
    "wof:placetype":"venue"
},
  "geometry": {"coordinates":[2.1733698845,41.3862915039],"type":"Point"}
}