{
  "type": "Feature",
  "properties": {
    "addr:full":"Carrer de Beat Oriol, S/n Mas Rampinyo Barcelona 08110",
    "addr:housenumber":"s / n",
    "addr:postcode":"08110",
    "addr:street":"Carrer De;Oriol",
    "iso:country":"ES",
    "sg:address":"Carrer de Beat Oriol, S/n",
    "sg:city":"Mas Rampinyo",
    "sg:orig_category":"Muebles, Minoristas",
    "sg:phone":"+34 935 75 23 43",
    "sg:postcode":"08110",
    "sg:province":"Barcelona",
    "wof:name":"Muebles Chip S.cv.",
    "wof:placetype":"venue"
},
  "geometry": {"coordinates":[2.1815750599,41.4910697937],"type":"Point"}
}