{
  "type": "Feature",
  "properties": {
    "addr:full":"Calle de Cristobal De Franchy, 2 Orotava Santa Cruz De Tenerife 38300",
    "addr:housenumber":"2",
    "addr:postcode":"38300",
    "addr:street":"Calle De Cristobal De Franchy",
    "iso:country":"ES",
    "sg:address":"Calle de Cristobal De Franchy, 2",
    "sg:city":"Orotava",
    "sg:orig_category":"Pescader\u00cdas (al Por Menor)",
    "sg:phone":"+34 922 32 28 15",
    "sg:postcode":"38300",
    "sg:province":"Santa Cruz De Tenerife",
    "wof:name":"Torres Del Pino Eulalio Cristobal",
    "wof:placetype":"venue"
},
  "geometry": {"coordinates":[-16.5282268524,28.3936004639],"type":"Point"}
}