{
  "type": "Feature",
  "properties": {
    "addr:full":"Crta. St. Feliu, S/n Quart Girona 17242",
    "addr:housenumber":"s / n",
    "addr:postcode":"17242",
    "addr:street":"Crta. St. Feliu",
    "iso:country":"ES",
    "sg:address":"Crta. St. Feliu, S/n",
    "sg:city":"Quart",
    "sg:orig_category":"Distribuci\u00d3n De Petr\u00d3leo Y Derivados",
    "sg:phone":"+34 972 46 92 14",
    "sg:postcode":"17242",
    "sg:province":"Girona",
    "wof:name":"Estacio Servei Quart S.l.",
    "wof:placetype":"venue"
},
  "geometry": {"coordinates":[2.8431999683,41.9333381653],"type":"Point"}
}