{
  "type": "Feature",
  "properties": {
    "addr:full":"Rua Bailen, 11 Vigo Pontevedra 36206",
    "addr:housenumber":"11",
    "addr:postcode":"36206",
    "addr:street":"Rua Bailen",
    "iso:country":"ES",
    "sg:address":"Rua Bailen, 11",
    "sg:city":"Vigo",
    "sg:orig_category":"Cervecer\u00cdas",
    "sg:phone":"+34 986 28 15 92",
    "sg:postcode":"36206",
    "sg:province":"Pontevedra",
    "wof:name":"Monserrat C.b.",
    "wof:placetype":"venue"
},
  "geometry": {"coordinates":[-8.7001848221,42.2420501709],"type":"Point"}
}