{
  "type": "Feature",
  "properties": {
    "addr:full":"Calle de Los Isunza, 13 Vitoria-gasteiz \u00c1lava 01002",
    "addr:housenumber":"13",
    "addr:postcode":"01002",
    "addr:street":"Calle De Los Isunza",
    "iso:country":"ES",
    "sg:address":"Calle de Los Isunza, 13",
    "sg:city":"Vitoria-gasteiz",
    "sg:orig_category":"Contenedores (mercanc\u00cdas)",
    "sg:phone":"+34 945 26 97 15",
    "sg:postcode":"01002",
    "sg:province":"\u00c1lava",
    "wof:name":"Aragolaza Gonzalez Abel",
    "wof:placetype":"venue"
},
  "geometry": {"coordinates":[-2.6641094685,42.8552474976],"type":"Point"}
}