{
  "type": "Feature",
  "properties": {
    "iso:country":"ES",
    "sg:address":"Calle de Marcos Del Torniello, 1",
    "sg:city":"Aviles",
    "sg:orig_category":"Confecci\u00d3n De Trajes Para Se\u00d1oras",
    "sg:phone":"+34 985 56 93 83",
    "sg:postcode":"33401",
    "sg:province":"Asturias",
    "wof:name":"Mieres Alvarez Jose Maria",
    "wof:placetype":"venue"
},
  "geometry": {"coordinates":[-5.9242320061,43.559173584],"type":"Point"}
}