{
  "type": "Feature",
  "properties": {
    "iso:country":"ES",
    "sg:address":"Federico Garcia Lorca, S/n",
    "sg:city":"Caniles",
    "sg:orig_category":"Molduras, Junquillos, Listones Y Molduras Perforadas",
    "sg:phone":"+34 958 71 07 25",
    "sg:postcode":"18810",
    "sg:province":"Granada",
    "wof:name":"Corral Rubio Juan Santiago",
    "wof:placetype":"venue"
},
  "geometry": {"coordinates":[-2.7215490341,37.4435958862],"type":"Point"}
}