{
  "type": "Feature",
  "properties": {
    "addr:full":"Carr Cronista Muntaner, 24 Lleida Lleida 25001",
    "addr:housenumber":"24",
    "addr:postcode":"25001",
    "addr:street":"Carr Cronista Muntaner",
    "iso:country":"ES",
    "sg:address":"Carr Cronista Muntaner, 24",
    "sg:city":"Lleida",
    "sg:orig_category":"Electricidad: Instaladores",
    "sg:phone":"+34 973 20 30 42",
    "sg:postcode":"25001",
    "sg:province":"Lleida",
    "wof:name":"Pi\u00f1ol Prenafeta Jose Antonio",
    "wof:placetype":"venue"
},
  "geometry": {"coordinates":[0.6346369982,41.6103439331],"type":"Point"}
}