{
  "type": "Feature",
  "properties": {
    "iso:country":"ES",
    "sg:address":"Rua Eduardo Pondal, 32",
    "sg:city":"Foz",
    "sg:orig_category":"Molduras, Junquillos, Listones Y Molduras Perforadas",
    "sg:phone":"+34 982 13 35 11",
    "sg:postcode":"27780",
    "sg:province":"Lugo",
    "wof:name":"Morroncho S.l.",
    "wof:placetype":"venue"
},
  "geometry": {"coordinates":[-7.2549619675,43.5681686401],"type":"Point"}
}