{
  "type": "Feature",
  "properties": {
    "addr:full":"Calle de Orden (la), 2 Yeste Albacete 02480",
    "addr:housenumber":"2",
    "addr:postcode":"02480",
    "addr:street":"Calle De Orden La",
    "iso:country":"ES",
    "sg:address":"Calle de Orden (la), 2",
    "sg:city":"Yeste",
    "sg:orig_category":"Charcuter\u00cdas (al Por Mayor)",
    "sg:phone":"+34 967 43 10 32",
    "sg:postcode":"02480",
    "sg:province":"Albacete",
    "wof:name":"Carnicas Marfer S.l.",
    "wof:placetype":"venue"
},
  "geometry": {"coordinates":[-2.3180770874,38.3685264587],"type":"Point"}
}