{
  "type": "Feature",
  "properties": {
    "addr:full":"Calle de San Isidro, 2 Yecla Murcia 30510",
    "addr:housenumber":"2",
    "addr:postcode":"30510",
    "addr:street":"Calle De San Isidro",
    "iso:country":"ES",
    "sg:address":"Calle de San Isidro, 2",
    "sg:city":"Yecla",
    "sg:orig_category":"Complementos De Vestir (al Por Menor)",
    "sg:phone":"+34 968 75 25 90",
    "sg:postcode":"30510",
    "sg:province":"Murcia",
    "wof:name":"Puig Camarasa Belen",
    "wof:placetype":"venue"
},
  "geometry": {"coordinates":[-1.1117470264,38.6112709045],"type":"Point"}
}