{
  "type": "Feature",
  "properties": {
    "addr:full":"Carretera De Soria-zaragoza, S/n Matalebreras Soria 42113",
    "addr:housenumber":"s",
    "addr:postcode":"42113",
    "addr:street":"Carretera De Soria-Zaragoza;/ N",
    "iso:country":"ES",
    "sg:address":"Carretera De Soria-zaragoza, S/n",
    "sg:city":"Matalebreras",
    "sg:orig_category":"Restaurantes",
    "sg:phone":"+34 975 38 31 67",
    "sg:postcode":"42113",
    "sg:province":"Soria",
    "wof:name":"Jimenez Martinez M.a. Y Otro",
    "wof:placetype":"venue"
},
  "geometry": {"coordinates":[-2.0627989769,41.8756866455],"type":"Point"}
}