{
  "type": "Feature",
  "properties": {
    "addr:full":"Av Vint De Juny De 1808, 7 Girona Girona 17001",
    "addr:housenumber":"7",
    "addr:postcode":"17001",
    "addr:street":"Av Vint;1808",
    "iso:country":"ES",
    "sg:address":"Av Vint De Juny De 1808, 7",
    "sg:city":"Girona",
    "sg:orig_category":"Abogados",
    "sg:phone":"+34 972 21 42 36",
    "sg:postcode":"17001",
    "sg:province":"Girona",
    "wof:name":"Turon Roura Ramon",
    "wof:placetype":"venue"
},
  "geometry": {"coordinates":[2.819106102,41.9838829041],"type":"Point"}
}