{
  "type": "Feature",
  "properties": {
    "iso:country":"ES",
    "sg:address":"Calle de Bidebarrieta, 14",
    "sg:city":"Bilbao",
    "sg:orig_category":"Grabados",
    "sg:phone":"+34 944 16 32 37",
    "sg:postcode":"48005",
    "sg:province":"Vizcaya",
    "wof:name":"Rojo Murguia Rosario",
    "wof:placetype":"venue"
},
  "geometry": {"coordinates":[-2.9243092537,43.2579574585],"type":"Point"}
}