{
  "type": "Feature",
  "properties": {
    "iso:country":"ES",
    "sg:address":"Carretera Pinillos, 12",
    "sg:city":"Cantimpalos",
    "sg:orig_category":"Electricidad: Instaladores",
    "sg:phone":"+34 921 49 62 13",
    "sg:postcode":"40360",
    "sg:province":"Segovia",
    "wof:name":"Movement S.a.",
    "wof:placetype":"venue"
},
  "geometry": {"coordinates":[-4.1494789124,41.0765800476],"type":"Point"}
}