{
  "type": "Feature",
  "properties": {
    "addr:full":"Calle de Beato Juan De Avila, 6 Fuensalida Toledo 45510",
    "addr:housenumber":"6",
    "addr:postcode":"45510",
    "addr:street":"Calle De Beato Juan De Avila",
    "iso:country":"ES",
    "sg:address":"Calle de Beato Juan De Avila, 6",
    "sg:city":"Fuensalida",
    "sg:orig_category":"M\u00c9dicos: Estomatolog\u00cda",
    "sg:phone":"+34 925 73 13 14",
    "sg:postcode":"45510",
    "sg:province":"Toledo",
    "wof:name":"Kea Dental S.l.",
    "wof:placetype":"venue"
},
  "geometry": {"coordinates":[-4.2135925293,40.0488853455],"type":"Point"}
}