{
  "type": "Feature",
  "properties": {
    "addr:full":"Calle de Santa Barbara, 9 Madrid Madrid 28004",
    "addr:housenumber":"9",
    "addr:postcode":"madrid;28004",
    "addr:street":"Calle De Santa Barbara",
    "iso:country":"ES",
    "sg:address":"Calle de Santa Barbara, 9",
    "sg:city":"Madrid",
    "sg:orig_category":"Ropa Para Se\u00d1oras (al Por Menor)",
    "sg:phone":"+34 915 23 11 91",
    "sg:postcode":"28004",
    "sg:province":"Madrid",
    "sg:website":"www.terra.es/personal4/helenavaltierra",
    "wof:name":"Guzaman Encina Sara",
    "wof:placetype":"venue"
},
  "geometry": {"coordinates":[-3.701515913,40.4241371155],"type":"Point"}
}