{
  "type": "Feature",
  "properties": {
    "addr:full":"Calle de Patio Del Casta\u00d1o, 2 Palencia Palencia 34001",
    "addr:housenumber":"2",
    "addr:postcode":"34001",
    "addr:street":"Calle De",
    "iso:country":"ES",
    "sg:address":"Calle de Patio Del Casta\u00d1o, 2",
    "sg:city":"Palencia",
    "sg:orig_category":"Asesor\u00cda Fiscal Y Jur\u00cddica",
    "sg:phone":"+34 979 70 03 01",
    "sg:postcode":"34001",
    "sg:province":"Palencia",
    "wof:name":"Diez Escribano Maria Covadonga",
    "wof:placetype":"venue"
},
  "geometry": {"coordinates":[-4.5334677696,42.0108146667],"type":"Point"}
}