{
  "type": "Feature",
  "properties": {
    "addr:full":"Luga Olivares, 35 Oviedo Asturias 33013",
    "addr:housenumber":"35",
    "addr:postcode":"33013",
    "addr:street":"Olivares",
    "iso:country":"ES",
    "sg:address":"Luga Olivares, 35",
    "sg:city":"Oviedo",
    "sg:orig_category":"Inform\u00c1tica (estudios, Servicios, Asesor\u00cda, Formaci\u00d3n)",
    "sg:phone":"+34 985 20 09 70",
    "sg:postcode":"33013",
    "sg:province":"Asturias",
    "wof:name":"Grupo Gonvarp Sl",
    "wof:placetype":"venue"
},
  "geometry": {"coordinates":[-5.876139164,43.3637809753],"type":"Point"}
}