{
  "type": "Feature",
  "properties": {
    "addr:full":"Carrer de Palmes (les), S/n Canet Mar Barcelona 08360",
    "addr:housenumber":"s / n",
    "addr:postcode":"08360",
    "addr:street":"Carrer De Palmes Les",
    "iso:country":"ES",
    "sg:address":"Carrer de Palmes (les), S/n",
    "sg:city":"Canet Mar",
    "sg:orig_category":"Teatro, Ballet, Danza (agrupaciones, Compa\u00d1\u00cdas)",
    "sg:phone":"+34 937 95 48 59",
    "sg:postcode":"08360",
    "sg:province":"Barcelona",
    "wof:name":"Comediants S. A.",
    "wof:placetype":"venue"
},
  "geometry": {"coordinates":[2.57385993,41.5880241394],"type":"Point"}
}