{
  "type": "Feature",
  "properties": {
    "iso:country":"ES",
    "sg:address":"Carrer de Roger De Flor, 100",
    "sg:city":"Barcelona",
    "sg:orig_category":"Deportes Y Ocio: Art\u00cdculos Y Equipos (al Por Mayor)",
    "sg:phone":"+34 932 31 21 89",
    "sg:postcode":"08013",
    "sg:province":"Barcelona",
    "sg:website":"www.jorcani.com",
    "wof:name":"Jorcani S.l.",
    "wof:placetype":"venue"
},
  "geometry": {"coordinates":[2.1786470413,41.3944740295],"type":"Point"}
}