{
  "type": "Feature",
  "properties": {
    "iso:country":"ES",
    "sg:address":"Calle de Medina, 45",
    "sg:city":"Jerez De La Frontera",
    "sg:orig_category":"Juegos Y Juguetes (al Por Menor)",
    "sg:phone":"+34 956 33 58 56",
    "sg:postcode":"11406",
    "sg:province":"C\u00e1diz",
    "sg:website":"www.logohobby.es",
    "wof:name":"Logistica Del Hobby S.a.",
    "wof:placetype":"venue"
},
  "geometry": {"coordinates":[-6.1324939728,36.6820030212],"type":"Point"}
}