{
  "type": "Feature",
  "properties": {
    "addr:full":"Rua Magdalena, 224 Ferrol La Coru\u00f1a 15402",
    "addr:housenumber":"224",
    "addr:postcode":"15402",
    "addr:street":"Rua Magdalena;La Corun\u0303A",
    "iso:country":"ES",
    "sg:address":"Rua Magdalena, 224",
    "sg:city":"Ferrol",
    "sg:orig_category":"Abogados",
    "sg:phone":"+34 981 36 41 41",
    "sg:postcode":"15402",
    "sg:province":"La Coru\u00f1a",
    "wof:name":"Perille Arribe Maria De Los Angeles",
    "wof:placetype":"venue"
},
  "geometry": {"coordinates":[-8.2377691269,43.4815292358],"type":"Point"}
}