{
  "type": "Feature",
  "properties": {
    "iso:country":"ES",
    "sg:address":"Pg Gracia, 50",
    "sg:city":"Barcelona",
    "sg:orig_category":"Notarios",
    "sg:phone":"+34 934 67 21 27",
    "sg:postcode":"08007",
    "sg:province":"Barcelona",
    "wof:name":"Casanovas-permanyer Casas Ignacio",
    "wof:placetype":"venue"
},
  "geometry": {"coordinates":[2.1656079292,41.3919906616],"type":"Point"}
}