{
  "type": "Feature",
  "properties": {
    "iso:country":"ES",
    "sg:address":"Avda Veintiocho De Febrero, S/n",
    "sg:city":"Bollullos Par Condado",
    "sg:orig_category":"Asociaciones Humanitarias, De Cooperaci\u00d3n, De Acci\u00d3n Social",
    "sg:phone":"+34 959 41 14 50",
    "sg:postcode":"21710",
    "sg:province":"Huelva",
    "wof:name":"Federacion Provicial De Huelva De Asociaciones Solidarias Con El Sahara",
    "wof:placetype":"venue"
},
  "geometry": {"coordinates":[-6.5395088196,37.3449249268],"type":"Point"}
}