{
  "type": "Feature",
  "properties": {
    "iso:country":"ES",
    "sg:address":"Ctra Madrid (de), Km. 0377,0",
    "sg:city":"Molina Segura",
    "sg:orig_category":"Muebles, Minoristas",
    "sg:phone":"+34 968 61 12 45",
    "sg:postcode":"30500",
    "sg:province":"Murcia",
    "wof:name":"Capel Sanchez Juan",
    "wof:placetype":"venue"
},
  "geometry": {"coordinates":[-1.2119740248,38.0535736084],"type":"Point"}
}