{
  "type": "Feature",
  "properties": {
    "iso:country":"ES",
    "sg:address":"Calle de Alejandro Ferrant, 9",
    "sg:city":"Madrid",
    "sg:orig_category":"Asesor\u00cda Fiscal Y Jur\u00cddica",
    "sg:phone":"+34 914 67 70 75",
    "sg:postcode":"28045",
    "sg:province":"Madrid",
    "wof:name":"De La Cruz Alonso Alicia Paloma",
    "wof:placetype":"venue"
},
  "geometry": {"coordinates":[-3.6932756901,40.3950233459],"type":"Point"}
}