{
  "type": "Feature",
  "properties": {
    "addr:full":"Pl Melies, S/n Pineda Mar Barcelona 08397",
    "addr:housenumber":"s / n",
    "addr:postcode":"08397",
    "addr:street":"Pl Melies;Barcelona",
    "iso:country":"ES",
    "sg:address":"Pl Melies, S/n",
    "sg:city":"Pineda Mar",
    "sg:orig_category":"Bibliotecas, Mediatecas",
    "sg:phone":"+34 937 62 37 96",
    "sg:postcode":"08397",
    "sg:province":"Barcelona",
    "wof:name":"Ajuntament De Pineda De Mar",
    "wof:placetype":"venue"
},
  "geometry": {"coordinates":[2.6891815662,41.6263580322],"type":"Point"}
}