{
  "type": "Feature",
  "properties": {
    "addr:full":"Calle de Lanuza, 3 Madrid Madrid 28028",
    "addr:housenumber":"3",
    "addr:postcode":"28028",
    "addr:street":"Calle De Lanuza",
    "iso:country":"ES",
    "sg:address":"Calle de Lanuza, 3",
    "sg:city":"Madrid",
    "sg:orig_category":"Sat\u00c9lite",
    "sg:phone":"+34 913 56 37 94",
    "sg:postcode":"28028",
    "sg:province":"Madrid",
    "wof:name":"Cristalerias Crisurge S.l.",
    "wof:placetype":"venue"
},
  "geometry": {"coordinates":[-3.665389061,40.4258766174],"type":"Point"}
}