{
  "type": "Feature",
  "properties": {
    "addr:full":"Calle de Madre De Dios, 14 Malaga M\u00e1laga 29012",
    "addr:housenumber":"14",
    "addr:postcode":"29012",
    "addr:street":"Calle De Madre;Dios;Ma\u0301Laga",
    "iso:country":"ES",
    "sg:address":"Calle de Madre De Dios, 14",
    "sg:city":"Malaga",
    "sg:orig_category":"Asociaciones Humanitarias, De Cooperaci\u00d3n, De Acci\u00d3n Social",
    "sg:phone":"+34 952 21 45 89",
    "sg:postcode":"29012",
    "sg:province":"M\u00e1laga",
    "wof:name":"Asociacion Nacional De Invalidos Civiles",
    "wof:placetype":"venue"
},
  "geometry": {"coordinates":[-4.4186081886,36.7238311768],"type":"Point"}
}