{
  "type": "Feature",
  "properties": {
    "iso:country":"ES",
    "sg:address":"Calle de Gijones, 23",
    "sg:city":"Villarrubia De Los Ojos",
    "sg:orig_category":"Farmacias",
    "sg:phone":"+34 926 89 69 17",
    "sg:postcode":"13670",
    "sg:province":"Ciudad Real",
    "wof:name":"Calcerrada Mu\u00f1oz Enrique",
    "wof:placetype":"venue"
},
  "geometry": {"coordinates":[-3.6060390472,39.2185287476],"type":"Point"}
}