{
  "type": "Feature",
  "properties": {
    "addr:full":"Carrer de Concha Espina, 2 Vileta -son Rapinya Islas Baleares 07011",
    "addr:housenumber":"2",
    "addr:postcode":"07011",
    "addr:street":"Carrer De Concha Espina;Vileta Son;Islas",
    "iso:country":"ES",
    "sg:address":"Carrer de Concha Espina, 2",
    "sg:city":"Vileta -son Rapinya",
    "sg:orig_category":"Estancos",
    "sg:phone":"+34 971 79 06 35",
    "sg:postcode":"07011",
    "sg:province":"Islas Baleares",
    "wof:name":"Acu\u00f1a Bennasar Julian",
    "wof:placetype":"venue"
},
  "geometry": {"coordinates":[2.6151881218,39.5942840576],"type":"Point"}
}