{
  "type": "Feature",
  "properties": {
    "addr:full":"Calle de Egetiaga Uribarri, 7 Doneztebe Vizcaya 48450",
    "addr:housenumber":"7",
    "addr:postcode":"48450",
    "addr:street":"Calle De Egetiaga Uribarri",
    "iso:country":"ES",
    "sg:address":"Calle de Egetiaga Uribarri, 7",
    "sg:city":"Doneztebe",
    "sg:orig_category":"Farmacias",
    "sg:phone":"+34 944 49 26 96",
    "sg:postcode":"48450",
    "sg:province":"Vizcaya",
    "wof:name":"Gonzalez Calvo Maria Aurora",
    "wof:placetype":"venue"
},
  "geometry": {"coordinates":[-2.8926033974,43.2457389832],"type":"Point"}
}