{
  "type": "Feature",
  "properties": {
    "addr:full":"Avda Padre Tacoronte, 2 Badajoz Badajoz 06007",
    "addr:housenumber":"2",
    "addr:postcode":"06007",
    "addr:street":"Avda Padre Tacoronte",
    "iso:country":"ES",
    "sg:address":"Avda Padre Tacoronte, 2",
    "sg:city":"Badajoz",
    "sg:orig_category":"Panader\u00cdas, Panader\u00cdas",
    "sg:phone":"+34 924 27 02 54",
    "sg:postcode":"06007",
    "sg:province":"Badajoz",
    "wof:name":"Suarez De Figueroa Maria Nieves",
    "wof:placetype":"venue"
},
  "geometry": {"coordinates":[-6.9776000977,38.8910827637],"type":"Point"}
}