{
  "type": "Feature",
  "properties": {
    "iso:country":"ES",
    "sg:address":"Carr Cavallers, 24",
    "sg:city":"Algaida",
    "sg:orig_category":"Asilos De Ancianos. Centros Privados",
    "sg:phone":"+34 971 12 50 64",
    "sg:postcode":"07210",
    "sg:province":"Islas Baleares",
    "wof:name":"Associacio De Persones Majors",
    "wof:placetype":"venue"
},
  "geometry": {"coordinates":[2.8988728523,39.5580940247],"type":"Point"}
}