{
  "type": "Feature",
  "properties": {
    "addr:full":"Trva Ezquerro, 39 Autol La Rioja 26560",
    "addr:housenumber":"39",
    "addr:postcode":"26560",
    "addr:street":"Trva Ezquerro;Rioja",
    "iso:country":"ES",
    "sg:address":"Trva Ezquerro, 39",
    "sg:city":"Autol",
    "sg:orig_category":"Partidos Pol\u00cdticos",
    "sg:phone":"+34 941 39 03 51",
    "sg:postcode":"26560",
    "sg:province":"La Rioja",
    "wof:name":"Partido Socialista Obrero Espa\u00d1ol",
    "wof:placetype":"venue"
},
  "geometry": {"coordinates":[-2.0053830147,42.215473175],"type":"Point"}
}