{
  "type": "Feature",
  "properties": {
    "iso:country":"ES",
    "sg:address":"Calle de San Nicolas, 14",
    "sg:city":"Alacant",
    "sg:orig_category":"Molduras, Junquillos, Listones Y Molduras Perforadas",
    "sg:phone":"+34 965 20 06 59",
    "sg:postcode":"03002",
    "sg:province":"Alicante",
    "wof:name":"Quinta De Hosteleria S.l",
    "wof:placetype":"venue"
},
  "geometry": {"coordinates":[-0.4819859862,38.3458442688],"type":"Point"}
}