{
  "type": "Feature",
  "properties": {
    "addr:full":"Calle de Bravo Murillo, 205 Madrid Madrid 28020",
    "addr:housenumber":"205",
    "addr:postcode":"28020",
    "addr:street":"Calle De Bravo Murillo",
    "iso:country":"ES",
    "sg:address":"Calle de Bravo Murillo, 205",
    "sg:city":"Madrid",
    "sg:orig_category":"Puericultora",
    "sg:phone":"+34 914 50 21 22",
    "sg:postcode":"28020",
    "sg:province":"Madrid",
    "wof:name":"Ramirez Garcia Javier",
    "wof:placetype":"venue"
},
  "geometry": {"coordinates":[-3.7026352882,40.4553184509],"type":"Point"}
}