{
  "type": "Feature",
  "properties": {
    "addr:full":"Calle de Doctor Perez Camacho, S/n Santa Cruz De Tenerife Santa Cruz De Tenerife 38006",
    "addr:postcode":"38006",
    "addr:street":"Calle De Doctor Perez Camacho S / N",
    "iso:country":"ES",
    "sg:address":"Calle de Doctor Perez Camacho, S/n",
    "sg:city":"Santa Cruz De Tenerife",
    "sg:orig_category":"M\u00c9dicos: Neumolog\u00cda",
    "sg:phone":"+34 922 28 74 55",
    "sg:postcode":"38006",
    "sg:province":"Santa Cruz De Tenerife",
    "wof:name":"Zerolo Saez Ignacio",
    "wof:placetype":"venue"
},
  "geometry": {"coordinates":[-16.2607650757,28.4733657837],"type":"Point"}
}