{
  "type": "Feature",
  "properties": {
    "addr:full":"Calle de Salamanca, 50 Valencia Valencia 46005",
    "addr:housenumber":"50",
    "addr:postcode":"46005",
    "addr:street":"Calle De Salamanca",
    "iso:country":"ES",
    "sg:address":"Calle de Salamanca, 50",
    "sg:city":"Valencia",
    "sg:orig_category":"Inform\u00c1tica (estudios, Servicios, Asesor\u00cda, Formaci\u00d3n)",
    "sg:phone":"+34 963 16 34 00",
    "sg:postcode":"46005",
    "sg:province":"Valencia",
    "sg:website":"www.iver.es",
    "wof:name":"Iver Tecnologias De La Informacion S.a.",
    "wof:placetype":"venue"
},
  "geometry": {"coordinates":[-0.3630880117,39.4642715454],"type":"Point"}
}