{
  "type": "Feature",
  "properties": {
    "iso:country":"ES",
    "sg:address":"Carrer de Sant Josep, 29",
    "sg:city":"Sitges",
    "sg:orig_category":"Comercio, Reparaci\u00d3n De Motocicletas, Bicicletas Y Piezas Sueltas",
    "sg:phone":"+34 938 94 13 09",
    "sg:postcode":"08870",
    "sg:province":"Barcelona",
    "wof:name":"Moto Centre S.c.p.",
    "wof:placetype":"venue"
},
  "geometry": {"coordinates":[1.8069369793,41.2372512817],"type":"Point"}
}