{
  "type": "Feature",
  "properties": {
    "iso:country":"ES",
    "sg:address":"Calle de Beraqueta, 15",
    "sg:city":"Irun",
    "sg:orig_category":"Psic\u00d3logos",
    "sg:phone":"+34 943 62 68 13",
    "sg:postcode":"20302",
    "sg:province":"Guip\u00f9zcoa",
    "wof:name":"Garbizu Sanchez Guadalupe",
    "wof:placetype":"venue"
},
  "geometry": {"coordinates":[-1.7900110483,43.3400726318],"type":"Point"}
}