{
  "type": "Feature",
  "properties": {
    "iso:country":"ES",
    "sg:address":"Calle de Estatuto, 19",
    "sg:city":"Castellon",
    "sg:orig_category":"Comercio, Reparaci\u00d3n De Bicicletas, De Motocicletas, De Accesorios",
    "sg:phone":"+34 964 23 68 67",
    "sg:postcode":"12004",
    "sg:province":"Castell\u00f3n",
    "wof:name":"Cicles A.b.castello S.l.l.",
    "wof:placetype":"venue"
},
  "geometry": {"coordinates":[-0.034008,39.993221283],"type":"Point"}
}