{
  "type": "Feature",
  "properties": {
    "iso:country":"ES",
    "sg:address":"Calle de Villa De Negreira, 62",
    "sg:city":"Coru\u00d1a",
    "sg:orig_category":"Confecci\u00d3n (fabricaci\u00d3n, Al Por Mayor)",
    "sg:phone":"+34 981 26 25 84",
    "sg:postcode":"15011",
    "sg:province":"A Coru\u00f1a",
    "wof:name":"Vazquez Sanchez Jose Antonio",
    "wof:placetype":"venue"
},
  "geometry": {"coordinates":[-8.4229574203,43.363483429],"type":"Point"}
}