{
  "type": "Feature",
  "properties": {
    "addr:full":"Calle de Mayor, 43 Garrucha Almer\u00eda 04630",
    "addr:housenumber":"43",
    "addr:postcode":"04630",
    "addr:street":"Calle De Mayor;Almeri\u0301A",
    "iso:country":"ES",
    "sg:address":"Calle de Mayor, 43",
    "sg:city":"Garrucha",
    "sg:orig_category":"Asociaciones Y Clubs Deportivos",
    "sg:phone":"+34 950 46 08 31",
    "sg:postcode":"04630",
    "sg:province":"Almer\u00eda",
    "wof:name":"Flores Hernandez Carmen",
    "wof:placetype":"venue"
},
  "geometry": {"coordinates":[-1.8217339516,37.1810340881],"type":"Point"}
}