{
  "type": "Feature",
  "properties": {
    "addr:full":"Carrer de La Sarga, 1 Xixona Alicante 03100",
    "addr:housenumber":"1",
    "addr:postcode":"03100",
    "addr:street":"Carrer De La Sarga",
    "iso:country":"ES",
    "sg:address":"Carrer de La Sarga, 1",
    "sg:city":"Xixona",
    "sg:orig_category":"Electricidad: Instaladores",
    "sg:phone":"+34 965 61 03 18",
    "sg:postcode":"03100",
    "sg:province":"Alicante",
    "wof:name":"Montajes Electricos Miralles Mira S.l.",
    "wof:placetype":"venue"
},
  "geometry": {"coordinates":[-0.4641070068,38.6400489807],"type":"Point"}
}