{
  "type": "Feature",
  "properties": {
    "iso:country":"ES",
    "sg:address":"Calle de Consuelo, 18",
    "sg:city":"Valencia",
    "sg:orig_category":"Estudios, Instalaci\u00d3n De Climatizaci\u00d3n",
    "sg:phone":"+34 963 67 02 69",
    "sg:postcode":"46011",
    "sg:province":"Valencia",
    "wof:name":"France Telecom Espa\u00d1a S.a.",
    "wof:placetype":"venue"
},
  "geometry": {"coordinates":[-0.3365418017,39.462688446],"type":"Point"}
}