{
  "type": "Feature",
  "properties": {
    "addr:full":"Calle de Donantes De Sangre, S/n Campillos M\u00e1laga 29320",
    "addr:housenumber":"s / n",
    "addr:postcode":"29320",
    "addr:street":"Calle De Donantes De Sangre",
    "iso:country":"ES",
    "sg:address":"Calle de Donantes De Sangre, S/n",
    "sg:city":"Campillos",
    "sg:orig_category":"Molduras, Junquillos, Listones Y Molduras Perforadas",
    "sg:phone":"+34 952 72 35 81",
    "sg:postcode":"29320",
    "sg:province":"M\u00e1laga",
    "wof:name":"Morillo Mora Jose",
    "wof:placetype":"venue"
},
  "geometry": {"coordinates":[-4.8624134064,37.0457725525],"type":"Point"}
}