{
  "type": "Feature",
  "properties": {
    "addr:full":"Avda Virgen De La Candelaria, 1 Rincon Victoria M\u00e1laga 29730",
    "addr:housenumber":"1",
    "addr:postcode":"29730",
    "addr:street":"Avda Virgen De La Candelaria;Ma\u0301Laga",
    "iso:country":"ES",
    "sg:address":"Avda Virgen De La Candelaria, 1",
    "sg:city":"Rincon Victoria",
    "sg:orig_category":"Cajas De Ahorro",
    "sg:phone":"+34 952 97 05 17",
    "sg:postcode":"29730",
    "sg:province":"M\u00e1laga",
    "sg:website":"www.lacaixa.es",
    "wof:name":"Caixa D'estalvis I Pensions De Barcelona",
    "wof:placetype":"venue"
},
  "geometry": {"coordinates":[-4.2807641029,36.714641571],"type":"Point"}
}