{
  "type": "Feature",
  "properties": {
    "addr:full":"Calle de Bruno Solano, 1 Zaragoza Zaragoza 50006",
    "addr:housenumber":"1",
    "addr:postcode":"50006",
    "addr:street":"Calle De Bruno Solano",
    "iso:country":"ES",
    "sg:address":"Calle de Bruno Solano, 1",
    "sg:city":"Zaragoza",
    "sg:orig_category":"Venta, Instalaci\u00d3n De Calefacci\u00d3n",
    "sg:phone":"+34 976 55 22 97",
    "sg:postcode":"50006",
    "sg:province":"Zaragoza",
    "wof:name":"Enfedaque Villuendas Jose Joaquin",
    "wof:placetype":"venue"
},
  "geometry": {"coordinates":[-0.8953782916,41.6398010254],"type":"Point"}
}