{
  "type": "Feature",
  "properties": {
    "addr:full":"Calle de Telleria, 14 Bilbao Vizcaya 48004",
    "addr:housenumber":"14",
    "addr:postcode":"48004",
    "addr:street":"Calle De Telleria",
    "iso:country":"ES",
    "sg:address":"Calle de Telleria, 14",
    "sg:city":"Bilbao",
    "sg:orig_category":"Sales (al Por Mayor)",
    "sg:phone":"+34 944 11 40 23",
    "sg:postcode":"48004",
    "sg:province":"Vizcaya",
    "wof:name":"Almacen De Aceitunas Martin Martin Sa",
    "wof:placetype":"venue"
},
  "geometry": {"coordinates":[-2.9012510777,43.2492713928],"type":"Point"}
}