{
  "type": "Feature",
  "properties": {
    "iso:country":"ES",
    "sg:address":"Calle de Sevilla, 5",
    "sg:city":"Ronda",
    "sg:orig_category":"Asesor\u00cdas Y Estudios Financieros",
    "sg:phone":"+34 952 87 77 60",
    "sg:postcode":"29400",
    "sg:province":"M\u00e1laga",
    "wof:name":"Servian Mu\u00f1oz Fernando",
    "wof:placetype":"venue"
},
  "geometry": {"coordinates":[-5.1647648811,36.7433280945],"type":"Point"}
}