{
  "type": "Feature",
  "properties": {
    "addr:full":"Carrer de Sant Iscle, 10 Barcelona Barcelona 08031",
    "addr:housenumber":"10",
    "addr:postcode":"08031",
    "addr:street":"Carrer De Sant Iscle",
    "iso:country":"ES",
    "sg:address":"Carrer de Sant Iscle, 10",
    "sg:city":"Barcelona",
    "sg:orig_category":"Ropa Para Se\u00d1oras (al Por Menor)",
    "sg:phone":"+34 932 43 00 58",
    "sg:postcode":"08031",
    "sg:province":"Barcelona",
    "sg:website":"www.kirowa.es",
    "wof:name":"Kirowa Fashion S.l.",
    "wof:placetype":"venue"
},
  "geometry": {"coordinates":[2.1739850044,41.4308280945],"type":"Point"}
}