{
  "type": "Feature",
  "properties": {
    "addr:full":"Calle de Ramon Y Cajal, 8 Berbegal Huesca 22131",
    "addr:housenumber":"8",
    "addr:postcode":"22131",
    "addr:street":"Calle De Ramon Y Cajal",
    "iso:country":"ES",
    "sg:address":"Calle de Ramon Y Cajal, 8",
    "sg:city":"Berbegal",
    "sg:orig_category":"Carnicer\u00cdas, Carnicer\u00cdas",
    "sg:phone":"+34 974 30 15 00",
    "sg:postcode":"22131",
    "sg:province":"Huesca",
    "wof:name":"Capablo Lacambra Joaquin",
    "wof:placetype":"venue"
},
  "geometry": {"coordinates":[-0.002106,41.9614067078],"type":"Point"}
}