{
  "type": "Feature",
  "properties": {
    "addr:full":"Carrer de Neptu, 36 Barcelona Barcelona 08006",
    "addr:housenumber":"36",
    "addr:postcode":"08006",
    "addr:street":"Carrer De Neptu",
    "iso:country":"ES",
    "sg:address":"Carrer de Neptu, 36",
    "sg:city":"Barcelona",
    "sg:orig_category":"Agencias Y Asesores De Publicidad",
    "sg:phone":"+34 934 15 19 66",
    "sg:postcode":"08006",
    "sg:province":"Barcelona",
    "wof:name":"Ba\u00f1os Xatart Leopoldo",
    "wof:placetype":"venue"
},
  "geometry": {"coordinates":[2.1539490223,41.3986206055],"type":"Point"}
}