{
  "type": "Feature",
  "properties": {
    "addr:full":"Plaz Viudas, 18 Cadiz C\u00e1diz 11003",
    "addr:housenumber":"18",
    "addr:postcode":"11003",
    "addr:street":"Viudas",
    "iso:country":"ES",
    "sg:address":"Plaz Viudas, 18",
    "sg:city":"Cadiz",
    "sg:orig_category":"M\u00c9dicos: Cirug\u00cda General",
    "sg:phone":"+34 956 22 30 18",
    "sg:postcode":"11003",
    "sg:province":"C\u00e1diz",
    "wof:name":"Mu\u00f1oz De La Pascua Fernando",
    "wof:placetype":"venue"
},
  "geometry": {"coordinates":[-6.3004050255,36.5341110229],"type":"Point"}
}