{
  "type": "Feature",
  "properties": {
    "iso:country":"ES",
    "sg:address":"Calle de Rio Deva, 5",
    "sg:city":"Santander",
    "sg:orig_category":"Centros Empresariales",
    "sg:phone":"+34 942 34 35 62",
    "sg:postcode":"39011",
    "sg:province":"Cantabria",
    "wof:name":"Promoservicios S. A.",
    "wof:placetype":"venue"
},
  "geometry": {"coordinates":[-3.8322529793,43.4476280212],"type":"Point"}
}