{
  "type": "Feature",
  "properties": {
    "iso:country":"ES",
    "sg:address":"Calle de Lope De Haro, 5",
    "sg:city":"Madrid",
    "sg:orig_category":"Electricidad: Instaladores",
    "sg:phone":"+34 915 79 06 91",
    "sg:postcode":"28039",
    "sg:province":"Madrid",
    "wof:name":"Sanchez Simon Francisco",
    "wof:placetype":"venue"
},
  "geometry": {"coordinates":[-3.7023260593,40.4571304321],"type":"Point"}
}