{
  "type": "Feature",
  "properties": {
    "addr:full":"Calle de Dario Aparicio, S/n Madrid Madrid 28023",
    "addr:housenumber":"s / n",
    "addr:postcode":"28023",
    "addr:street":"Calle De Dario Aparicio",
    "iso:country":"ES",
    "sg:address":"Calle de Dario Aparicio, S/n",
    "sg:city":"Madrid",
    "sg:orig_category":"Internados & Ense\u00d1anza Privada",
    "sg:phone":"+34 913 07 96 60",
    "sg:postcode":"28023",
    "sg:province":"Madrid",
    "wof:name":"Restal S.l.",
    "wof:placetype":"venue"
},
  "geometry": {"coordinates":[-3.7673170567,40.4688301086],"type":"Point"}
}