{
  "type": "Feature",
  "properties": {
    "addr:full":"Carrer de Hermenegild Clascar, 14 Vilafranca Penedes Barcelona 08720",
    "addr:housenumber":"14",
    "addr:postcode":"08720",
    "addr:street":"Carrer De Hermenegild Clascar;Penedes Barcelona",
    "iso:country":"ES",
    "sg:address":"Carrer de Hermenegild Clascar, 14",
    "sg:city":"Vilafranca Penedes",
    "sg:orig_category":"Peluqueros: De Se\u00d1oras",
    "sg:phone":"+34 938 90 19 81",
    "sg:postcode":"08720",
    "sg:province":"Barcelona",
    "wof:name":"Saumell Fortuny Maria Teresa",
    "wof:placetype":"venue"
},
  "geometry": {"coordinates":[1.6992199421,41.3447799683],"type":"Point"}
}