{
  "type": "Feature",
  "properties": {
    "iso:country":"ES",
    "sg:address":"Calle de Perdida, 57",
    "sg:city":"Bonillo",
    "sg:orig_category":"Carnicer\u00cdas, Carnicer\u00cdas",
    "sg:phone":"+34 967 37 06 60",
    "sg:postcode":"02610",
    "sg:province":"Albacete",
    "wof:name":"Calero Ca\u00f1averas Jesus",
    "wof:placetype":"venue"
},
  "geometry": {"coordinates":[-2.534979105,38.9509391785],"type":"Point"}
}