{
  "type": "Feature",
  "properties": {
    "addr:full":"Avda General Aviles, 7 Valencia Valencia 46015",
    "addr:housenumber":"7",
    "addr:postcode":"46015",
    "addr:street":"Avda General Aviles",
    "iso:country":"ES",
    "sg:address":"Avda General Aviles, 7",
    "sg:city":"Valencia",
    "sg:orig_category":"Ingenier\u00cda, Centros De Estudios (diversos)",
    "sg:phone":"+34 963 49 79 55",
    "sg:postcode":"46015",
    "sg:province":"Valencia",
    "sg:website":"www.nkelectronica.com",
    "wof:name":"N. K. Electronica S. L.",
    "wof:placetype":"venue"
},
  "geometry": {"coordinates":[-0.3910740018,39.4877586365],"type":"Point"}
}