{
  "type": "Feature",
  "properties": {
    "addr:full":"Calle de Doctor Esquerdo, 71 Madrid Madrid 28007",
    "addr:housenumber":"71",
    "addr:postcode":"madrid;28007",
    "addr:street":"Calle De Doctor Esquerdo",
    "iso:country":"ES",
    "sg:address":"Calle de Doctor Esquerdo, 71",
    "sg:city":"Madrid",
    "sg:orig_category":"Herboristas (al Por Menor)",
    "sg:phone":"+34 915 04 26 78",
    "sg:postcode":"28007",
    "sg:province":"Madrid",
    "wof:name":"Cannabiogen S.l.",
    "wof:placetype":"venue"
},
  "geometry": {"coordinates":[-3.6690468788,40.4191131592],"type":"Point"}
}