{
  "type": "Feature",
  "properties": {
    "addr:full":"Plaz Lanchas, S/n Santos Salamanca 37768",
    "addr:housenumber":"s / n",
    "addr:postcode":"37768",
    "addr:street":"Plaz Lanchas",
    "iso:country":"ES",
    "sg:address":"Plaz Lanchas, S/n",
    "sg:city":"Santos",
    "sg:orig_category":"Electrodom\u00c9sticos (al Por Menor)",
    "sg:phone":"+34 923 59 21 00",
    "sg:postcode":"37768",
    "sg:province":"Salamanca",
    "wof:name":"Merino Miguel Agustin",
    "wof:placetype":"venue"
},
  "geometry": {"coordinates":[-5.7337388992,40.5642967224],"type":"Point"}
}