{
  "type": "Feature",
  "properties": {
    "addr:full":"Calle de Martin Belda, 19 Cabra C\u00f3rdoba 14940",
    "addr:housenumber":"19",
    "addr:postcode":"14940",
    "addr:street":"Calle De Martin Belda;Co\u0301Rdoba",
    "iso:country":"ES",
    "sg:address":"Calle de Martin Belda, 19",
    "sg:city":"Cabra",
    "sg:orig_category":"M\u00c9dicos: An\u00c1lisis Cl\u00cdnicos",
    "sg:phone":"+34 957 52 16 65",
    "sg:postcode":"14940",
    "sg:province":"C\u00f3rdoba",
    "wof:name":"Pe\u00f1a Blanco Jose",
    "wof:placetype":"venue"
},
  "geometry": {"coordinates":[-4.4430727959,37.471950531],"type":"Point"}
}