{
  "type": "Feature",
  "properties": {
    "addr:full":"Carrer de Italia, S/n Terrassa Barcelona 08228",
    "addr:housenumber":"s / n",
    "addr:postcode":"08228",
    "addr:street":"Carrer De Italia",
    "iso:country":"ES",
    "sg:address":"Carrer de Italia, S/n",
    "sg:city":"Terrassa",
    "sg:orig_category":"M\u00c9dicos: Estomatolog\u00cda",
    "sg:phone":"+34 937 86 37 36",
    "sg:postcode":"08228",
    "sg:province":"Barcelona",
    "wof:name":"Sabate Armengoll Jorge",
    "wof:placetype":"venue"
},
  "geometry": {"coordinates":[2.0469899178,41.5365333557],"type":"Point"}
}