{
  "type": "Feature",
  "properties": {
    "iso:country":"ES",
    "sg:address":"Cra Nacional Ii, Km. 0006,4",
    "sg:city":"Mataro",
    "sg:orig_category":"Ropa Y Accesorios",
    "sg:phone":"+34 937 41 67 60",
    "sg:postcode":"08301",
    "sg:province":"Barcelona",
    "wof:name":"Textil Impex S.l.",
    "wof:placetype":"venue"
},
  "geometry": {"coordinates":[2.4479300976,41.5427207947],"type":"Point"}
}