{
  "type": "Feature",
  "properties": {
    "addr:full":"Ctra. Matillas, S/n Mandayona Guadalajara 19294",
    "addr:housenumber":"s",
    "addr:postcode":"19294",
    "addr:street":"Ctra. Matillas;/ N Mandayona",
    "iso:country":"ES",
    "sg:address":"Ctra. Matillas, S/n",
    "sg:city":"Mandayona",
    "sg:orig_category":"Centros De Salud",
    "sg:phone":"+34 949 30 57 15",
    "sg:postcode":"19294",
    "sg:province":"Guadalajara",
    "wof:name":"Asociacion El Alba",
    "wof:placetype":"venue"
},
  "geometry": {"coordinates":[-2.7509732246,40.95652771],"type":"Point"}
}