{
  "type": "Feature",
  "properties": {
    "addr:full":"Calle de Hervideros (los), S/n Costa Teguise Las Palmas 35509",
    "addr:postcode":"35509",
    "addr:street":"Calle De Hervideros Los S / N",
    "iso:country":"ES",
    "sg:address":"Calle de Hervideros (los), S/n",
    "sg:city":"Costa Teguise",
    "sg:orig_category":"Bazares, Art\u00cdculos De Limpieza Y De Cocina (al Por Menor)",
    "sg:phone":"+34 928 59 02 08",
    "sg:postcode":"35509",
    "sg:province":"Las Palmas",
    "wof:name":"Gutierrez Arrocha Diego Sergio",
    "wof:placetype":"venue"
},
  "geometry": {"coordinates":[-13.5916891098,28.955160141],"type":"Point"}
}