{
  "type": "Feature",
  "properties": {
    "iso:country":"ES",
    "sg:address":"Calle de Juan De Aragon, 3",
    "sg:city":"Alfaro",
    "sg:orig_category":"Abogados",
    "sg:phone":"+34 941 18 08 69",
    "sg:postcode":"26540",
    "sg:province":"La Rioja",
    "wof:name":"Casas Ugarte Jose Antonio",
    "wof:placetype":"venue"
},
  "geometry": {"coordinates":[-1.7509679794,42.1786460876],"type":"Point"}
}