{
  "type": "Feature",
  "properties": {
    "addr:full":"Plaz Mision Rescate, 4 Ubrique C\u00e1diz 11600",
    "addr:housenumber":"4",
    "addr:postcode":"11600",
    "addr:street":"Mision Rescate;Ca\u0301Diz",
    "iso:country":"ES",
    "sg:address":"Plaz Mision Rescate, 4",
    "sg:city":"Ubrique",
    "sg:orig_category":"Estancos",
    "sg:phone":"+34 956 46 07 11",
    "sg:postcode":"11600",
    "sg:province":"C\u00e1diz",
    "wof:name":"Moreno Morales Juan Miguel",
    "wof:placetype":"venue"
},
  "geometry": {"coordinates":[-5.4475698471,36.6776618958],"type":"Point"}
}