{
  "type": "Feature",
  "properties": {
    "addr:full":"Calle de Mimosas Las, S/n Poligono Industrial De Arinaga Las Palmas 35118",
    "addr:postcode":"35118",
    "addr:street":"Calle De Mimosas Las S / N Poligono Industrial De Arinaga Las",
    "iso:country":"ES",
    "sg:address":"Calle de Mimosas Las, S/n",
    "sg:city":"Poligono Industrial De Arinaga",
    "sg:orig_category":"Mec\u00c1nico Del Autom\u00d3vil",
    "sg:phone":"+34 928 18 02 95",
    "sg:postcode":"35118",
    "sg:province":"Las Palmas",
    "wof:name":"Pe\u00f1a Torres Benjamin",
    "wof:placetype":"venue"
},
  "geometry": {"coordinates":[-15.4319887161,27.8808555603],"type":"Point"}
}