{
  "type": "Feature",
  "properties": {
    "addr:full":"Calle de Nieves, 22 S. Clemente Cuenca 16600",
    "addr:housenumber":"22",
    "addr:postcode":"16600",
    "addr:street":"Calle De Nieves;S. Clemente Cuenca",
    "iso:country":"ES",
    "sg:address":"Calle de Nieves, 22",
    "sg:city":"S. Clemente",
    "sg:orig_category":"Autob\u00das (explotaci\u00d3n Y Servicios De)",
    "sg:phone":"+34 969 30 04 57",
    "sg:postcode":"16600",
    "sg:province":"Cuenca",
    "wof:name":"Jimenez Martinez Jose",
    "wof:placetype":"venue"
},
  "geometry": {"coordinates":[-2.4267594814,39.4078636169],"type":"Point"}
}