{
  "type": "Feature",
  "properties": {
    "iso:country":"ES",
    "sg:address":"Calle de San Pedro, 20",
    "sg:city":"Alquerias Del Ni\u00e7o Perdido",
    "sg:orig_category":"Transportes Por Carretera: Lotes Completos, Mercanc\u00cdas Diversas",
    "sg:phone":"+34 964 57 11 96",
    "sg:postcode":"12539",
    "sg:province":"Castell\u00f3n",
    "wof:name":"Pascual Garcia Rafael Jose",
    "wof:placetype":"venue"
},
  "geometry": {"coordinates":[-0.1214139983,39.8971862793],"type":"Point"}
}