{
  "type": "Feature",
  "properties": {
    "iso:country":"ES",
    "sg:address":"Calle de Serrano, 61",
    "sg:city":"Madrid",
    "sg:orig_category":"Ropa Para Se\u00d1oras (al Por Menor)",
    "sg:phone":"+34 915 76 87 50",
    "sg:postcode":"28006",
    "sg:province":"Madrid",
    "wof:name":"Kanap Fusion S.l.",
    "wof:placetype":"venue"
},
  "geometry": {"coordinates":[-3.6868038177,40.4321937561],"type":"Point"}
}