{
  "type": "Feature",
  "properties": {
    "iso:country":"ES",
    "sg:address":"Av Cardenal Tarancon, 49",
    "sg:city":"Solsona",
    "sg:orig_category":"Internados & Ense\u00d1anza Privada",
    "sg:phone":"+34 973 48 26 07",
    "sg:postcode":"25280",
    "sg:province":"Lleida",
    "wof:name":"Fundacio Privada Escolar Mare De Deu Del Claustre",
    "wof:placetype":"venue"
},
  "geometry": {"coordinates":[1.5582829714,41.9756584167],"type":"Point"}
}