{
  "type": "Feature",
  "properties": {
    "iso:country":"ES",
    "sg:address":"Calle de Atis Tirma, 25",
    "sg:city":"Gran Tarajal",
    "sg:orig_category":"Bazares, Art\u00cdculos De Limpieza Y De Cocina (al Por Menor)",
    "sg:phone":"+34 928 16 52 21",
    "sg:postcode":"35620",
    "sg:province":"Las Palmas",
    "wof:name":"Camejo Herrera Luz Elena",
    "wof:placetype":"venue"
},
  "geometry": {"coordinates":[-14.0202198029,28.2122707367],"type":"Point"}
}