{
  "type": "Feature",
  "properties": {
    "addr:full":"Avda Baleares, 137 Caba\u00d1uelas Almer\u00eda 04738",
    "addr:housenumber":"137",
    "addr:postcode":"04738",
    "addr:street":"Avda Baleares;Almeri\u0301A",
    "iso:country":"ES",
    "sg:address":"Avda Baleares, 137",
    "sg:city":"Caba\u00d1uelas",
    "sg:orig_category":"Bancos",
    "sg:phone":"+34 950 55 53 66",
    "sg:postcode":"04738",
    "sg:province":"Almer\u00eda",
    "sg:website":"www.bancoandalucia.es",
    "wof:name":"Banco De Andalucia",
    "wof:placetype":"venue"
},
  "geometry": {"coordinates":[-2.6302781105,36.8037414551],"type":"Point"}
}