{
  "type": "Feature",
  "properties": {
    "iso:country":"ES",
    "sg:address":"Ezkiaga Etorbidea, 3",
    "sg:city":"Beasain",
    "sg:orig_category":"Seguridad En El Trabajo Y Prevenci\u00d3n De Riesgos Laborales",
    "sg:phone":"+34 943 80 50 23",
    "sg:postcode":"20200",
    "sg:province":"Guip\u00f9zcoa",
    "wof:name":"Prevenalia",
    "wof:placetype":"venue"
},
  "geometry": {"coordinates":[-2.1898419857,43.0526161194],"type":"Point"}
}