{
  "type": "Feature",
  "properties": {
    "iso:country":"ES",
    "sg:address":"Calle de Bailen, 2",
    "sg:city":"Gijon",
    "sg:orig_category":"Aparcamientos (infraestructuras, Accesorios)",
    "sg:phone":"+34 985 31 44 53",
    "sg:postcode":"33212",
    "sg:province":"Asturias",
    "wof:name":"Perez Pato Manuel",
    "wof:placetype":"venue"
},
  "geometry": {"coordinates":[-5.6843752861,43.5392150879],"type":"Point"}
}