{
  "type": "Feature",
  "properties": {
    "iso:country":"ES",
    "sg:address":"Avda Fred Olsen, 6",
    "sg:city":"Arrecife",
    "sg:orig_category":"Sociedades, Compa\u00d1\u00cdas Aseguradoras",
    "sg:phone":"+34 928 81 60 96",
    "sg:postcode":"35500",
    "sg:province":"Las Palmas",
    "wof:name":"I.c.broker Correduria De Seguros S.l.",
    "wof:placetype":"venue"
},
  "geometry": {"coordinates":[-13.5574169159,28.9587154388],"type":"Point"}
}