{
  "type": "Feature",
  "properties": {
    "addr:full":"Calle de Elkano, 6 Donostia-san Sebastian Guip\u00f9zcoa 20004",
    "addr:housenumber":"6",
    "addr:postcode":"20004",
    "addr:street":"Calle De Elkano",
    "iso:country":"ES",
    "sg:address":"Calle de Elkano, 6",
    "sg:city":"Donostia-san Sebastian",
    "sg:orig_category":"Peluquer\u00cdas, Peluquer\u00cda Mixta",
    "sg:phone":"+34 943 42 68 26",
    "sg:postcode":"20004",
    "sg:province":"Guip\u00f9zcoa",
    "wof:name":"Perez Garay Maria Teresa",
    "wof:placetype":"venue"
},
  "geometry": {"coordinates":[-1.9833179712,43.3217048645],"type":"Point"}
}