{
  "type": "Feature",
  "properties": {
    "addr:full":"Carrer de Doctor Pi I Molist, 83 Barcelona Barcelona 08031",
    "addr:housenumber":"83",
    "addr:postcode":"08031",
    "addr:street":"Carrer De Doctor Pi I Molist",
    "iso:country":"ES",
    "sg:address":"Carrer de Doctor Pi I Molist, 83",
    "sg:city":"Barcelona",
    "sg:orig_category":"Ropa Para Caballeros (al Por Menor)",
    "sg:phone":"+34 933 59 82 45",
    "sg:postcode":"08031",
    "sg:province":"Barcelona",
    "wof:name":"Vallejo Escolano Jose Carlos",
    "wof:placetype":"venue"
},
  "geometry": {"coordinates":[2.1726400852,41.4340858459],"type":"Point"}
}