{
  "type": "Feature",
  "properties": {
    "iso:country":"ES",
    "sg:address":"Calle de Arenal, Km. 0004,9",
    "sg:city":"Fuentes De Andalucia",
    "sg:orig_category":"Explotaci\u00d3n De Canteras",
    "sg:phone":"+34 955 95 52 81",
    "sg:postcode":"41420",
    "sg:province":"Sevilla",
    "wof:name":"Silices De Fuentes S.l.",
    "wof:placetype":"venue"
},
  "geometry": {"coordinates":[-5.3513541222,37.4667015076],"type":"Point"}
}