{
  "type": "Feature",
  "properties": {
    "iso:country":"ES",
    "sg:address":"Carrer de Josep Anselm Clave, 6",
    "sg:city":"Palma",
    "sg:orig_category":"Abogados",
    "sg:phone":"+34 971 71 53 23",
    "sg:postcode":"07002",
    "sg:province":"Islas Baleares",
    "wof:name":"Teulada Yachts S.l.",
    "wof:placetype":"venue"
},
  "geometry": {"coordinates":[2.6548240185,39.5735206604],"type":"Point"}
}