{
  "type": "Feature",
  "properties": {
    "iso:country":"ES",
    "sg:address":"Carrer de Ermita De Bellvitge, 29",
    "sg:city":"Hospitalet Llobregat",
    "sg:orig_category":"Molduras, Junquillos, Listones Y Molduras Perforadas",
    "sg:phone":"+34 932 63 47 11",
    "sg:postcode":"08907",
    "sg:province":"Barcelona",
    "wof:name":"Javed  Mamjid",
    "wof:placetype":"venue"
},
  "geometry": {"coordinates":[2.1086790562,41.3494529724],"type":"Point"}
}