{
  "type": "Feature",
  "properties": {
    "iso:country":"ES",
    "sg:address":"Carrer de Xavier Nogues, 19",
    "sg:city":"Barcelona",
    "sg:orig_category":"Papeler\u00cdas, Librer\u00cdas",
    "sg:phone":"+34 933 05 56 52",
    "sg:postcode":"08019",
    "sg:province":"Barcelona",
    "wof:name":"Perarnau Mayol Maria Dolors",
    "wof:placetype":"venue"
},
  "geometry": {"coordinates":[2.2156300545,41.4147796631],"type":"Point"}
}