{
  "type": "Feature",
  "properties": {
    "iso:country":"ES",
    "sg:address":"Calle de Etxatxu Kalea, 6",
    "sg:city":"Trobika",
    "sg:orig_category":"Promotores Constructores",
    "sg:phone":"+34 946 74 50 60",
    "sg:postcode":"48100",
    "sg:province":"Vizcaya",
    "wof:name":"Sociedad Anonima De Mantenimiento De Obr",
    "wof:placetype":"venue"
},
  "geometry": {"coordinates":[-2.8507039547,43.3569412231],"type":"Point"}
}