{
  "type": "Feature",
  "properties": {
    "iso:country":"ES",
    "sg:address":"Carrer de Dues Aigues (de Les), S/n",
    "sg:city":"Torredembarra",
    "sg:orig_category":"Centros Empresariales",
    "sg:phone":"+34 977 64 08 02",
    "sg:postcode":"43830",
    "sg:province":"Tarragona",
    "wof:name":"Nipro S.l.",
    "wof:placetype":"venue"
},
  "geometry": {"coordinates":[1.395424962,41.1436691284],"type":"Point"}
}