{
  "type": "Feature",
  "properties": {
    "addr:full":"Calle de Salitre, 11 Malaga M\u00e1laga 29002",
    "addr:housenumber":"11",
    "addr:postcode":"29002",
    "addr:street":"Calle De Salitre;Ma\u0301Laga",
    "iso:country":"ES",
    "sg:address":"Calle de Salitre, 11",
    "sg:city":"Malaga",
    "sg:orig_category":"Abogados",
    "sg:phone":"+34 952 31 16 14",
    "sg:postcode":"29002",
    "sg:province":"M\u00e1laga",
    "wof:name":"Moreno Verdugo Maria Jose",
    "wof:placetype":"venue"
},
  "geometry": {"coordinates":[-4.4268941879,36.713760376],"type":"Point"}
}