{
  "type": "Feature",
  "properties": {
    "addr:full":"Carr Carme, 51 Bisbal D'emporda Girona 17100",
    "addr:housenumber":"51",
    "addr:postcode":"17100",
    "addr:street":"Carr Carme",
    "iso:country":"ES",
    "sg:address":"Carr Carme, 51",
    "sg:city":"Bisbal D'emporda",
    "sg:orig_category":"Instalaci\u00d3n De Aspiraci\u00d3n De Gases Y Humos",
    "sg:phone":"+34 972 64 06 10",
    "sg:postcode":"17100",
    "sg:province":"Girona",
    "wof:name":"Lampisteria Sabria S.l.",
    "wof:placetype":"venue"
},
  "geometry": {"coordinates":[2.8246738911,41.9791946411],"type":"Point"}
}