{
  "type": "Feature",
  "properties": {
    "iso:country":"ES",
    "sg:address":"Carrer de Sants, 35",
    "sg:city":"Barcelona",
    "sg:classifiers":[
        {
            "category":"Autos & Motor Vehicles",
            "subcategory":"Automobile Sales",
            "type":"Retail Goods"
        }
    ],
    "sg:phone":"+34 934 21 21 56",
    "sg:postcode":"08014",
    "sg:province":"Barcelona",
    "wof:name":"Autoescoles Garrido S.l.",
    "wof:placetype":"venue"
},
  "geometry": {"coordinates":[2.1387929916,41.3752212524],"type":"Point"}
}