{
  "type": "Feature",
  "properties": {
    "addr:full":"Ctra Tocina, Km. 0000,8 Viso Del Alcor Sevilla 41520",
    "addr:postcode":"41520",
    "addr:street":"Ctra Tocina Km. 0000,8",
    "iso:country":"ES",
    "sg:address":"Ctra Tocina, Km. 0000,8",
    "sg:city":"Viso Del Alcor",
    "sg:orig_category":"Negocio De Materiales De Construcci\u00d3n",
    "sg:phone":"+34 955 74 07 59",
    "sg:postcode":"41520",
    "sg:province":"Sevilla",
    "wof:name":"Hermanos Pineda Vergara S.l.",
    "wof:placetype":"venue"
},
  "geometry": {"coordinates":[-5.7224740982,37.3872108459],"type":"Point"}
}