{
  "type": "Feature",
  "properties": {
    "iso:country":"ES",
    "sg:address":"Calle de Escorrata (la), 4",
    "sg:city":"Redovan",
    "sg:orig_category":"Molduras, Junquillos, Listones Y Molduras Perforadas",
    "sg:phone":"+34 966 75 46 75",
    "sg:postcode":"03370",
    "sg:province":"Alicante",
    "wof:name":"Cerda Portugues Pedro",
    "wof:placetype":"venue"
},
  "geometry": {"coordinates":[-0.9086390138,38.1130714417],"type":"Point"}
}