{
  "type": "Feature",
  "properties": {
    "addr:full":"Plza La Constitucion, S/n Biescas Huesca 22630",
    "addr:housenumber":"s / n",
    "addr:postcode":"22630",
    "iso:country":"ES",
    "sg:address":"Plza La Constitucion, S/n",
    "sg:city":"Biescas",
    "sg:orig_category":"Hospitales",
    "sg:phone":"+34 974 49 54 01",
    "sg:postcode":"22630",
    "sg:province":"Huesca",
    "wof:name":"Hospital Comarcal De Jaca",
    "wof:placetype":"venue"
},
  "geometry": {"coordinates":[-0.3262380064,42.6301383972],"type":"Point"}
}