{
  "type": "Feature",
  "properties": {
    "addr:full":"Carrer de Baionetes, 6 Palma Islas Baleares 07014",
    "addr:housenumber":"6",
    "addr:postcode":"07014",
    "addr:street":"Carrer De Baionetes",
    "iso:country":"ES",
    "sg:address":"Carrer de Baionetes, 6",
    "sg:city":"Palma",
    "sg:orig_category":"Comercio, Reparaci\u00d3n De Motocicletas, Bicicletas Y Piezas Sueltas",
    "sg:phone":"+34 971 28 53 05",
    "sg:postcode":"07014",
    "sg:province":"Islas Baleares",
    "wof:name":"Cladera Motos S.l.",
    "wof:placetype":"venue"
},
  "geometry": {"coordinates":[2.6257588863,39.5645256042],"type":"Point"}
}