{
  "type": "Feature",
  "properties": {
    "addr:full":"Carr Rafael Estela, 3 Vila Girona 17490",
    "addr:housenumber":"3",
    "addr:postcode":"17490",
    "addr:street":"Carr Rafael Estela",
    "iso:country":"ES",
    "sg:address":"Carr Rafael Estela, 3",
    "sg:city":"Vila",
    "sg:classifiers":[
        {
            "category":"Taxi",
            "type":"Transportation"
        }
    ],
    "sg:phone":"+34 972 38 01 92",
    "sg:postcode":"17490",
    "sg:province":"Girona",
    "wof:name":"Turro Vilanova Narciso",
    "wof:placetype":"venue"
},
  "geometry": {"coordinates":[3.1481759548,42.3640785217],"type":"Point"}
}