{
  "type": "Feature",
  "properties": {
    "iso:country":"ES",
    "sg:address":"Ptda Almafra Alta, 28",
    "sg:city":"Almafra",
    "sg:orig_category":"Zapatos: Material, Suministros, Accesorios (fabricaci\u00d3n, Al Por Mayor)",
    "sg:phone":"+34 966 95 30 12",
    "sg:postcode":"03610",
    "sg:province":"Alicante",
    "wof:name":"Escamez Murcia Angel",
    "wof:placetype":"venue"
},
  "geometry": {"coordinates":[-0.7731289864,38.4793281555],"type":"Point"}
}