{
  "type": "Feature",
  "properties": {
    "addr:full":"Avda Mar, Del, S/n Castellon Castell\u00f3n 12100",
    "addr:housenumber":"/ n",
    "addr:postcode":"12100",
    "addr:street":"Avda Mar Del S",
    "iso:country":"ES",
    "sg:address":"Avda Mar, Del, S/n",
    "sg:city":"Castellon",
    "sg:orig_category":"Animales (al Por Menor)",
    "sg:phone":"+34 964 26 90 75",
    "sg:postcode":"12100",
    "sg:province":"Castell\u00f3n",
    "wof:name":"Navarro Garcia Fernando",
    "wof:placetype":"venue"
},
  "geometry": {"coordinates":[0.0175199993,39.9810714722],"type":"Point"}
}