{
  "type": "Feature",
  "properties": {
    "iso:country":"ES",
    "sg:address":"Pso. Parque, S/n",
    "sg:city":"Alcaudete",
    "sg:orig_category":"Asociaciones, Organismos Culturales Y Socioeducativos",
    "sg:phone":"+34 953 56 07 61",
    "sg:postcode":"23660",
    "sg:province":"Ja\u00e9n",
    "wof:name":"Ayuntamiento De Alcaudete",
    "wof:placetype":"venue"
},
  "geometry": {"coordinates":[-4.0774087906,37.5880699158],"type":"Point"}
}