{
  "type": "Feature",
  "properties": {
    "iso:country":"ES",
    "sg:address":"Calle de Puerta Del Mar, 6",
    "sg:city":"Malaga",
    "sg:orig_category":"Electrodom\u00c9sticos (al Por Menor)",
    "sg:phone":"+34 952 22 13 12",
    "sg:postcode":"29005",
    "sg:province":"M\u00e1laga",
    "wof:name":"Ortega Carrasco Jose",
    "wof:placetype":"venue"
},
  "geometry": {"coordinates":[-4.4230809212,36.7188453674],"type":"Point"}
}