{
  "type": "Feature",
  "properties": {
    "iso:country":"ES",
    "sg:address":"Calle de Santas Patronas, 28",
    "sg:city":"Sevilla",
    "sg:orig_category":"Asesor\u00cda Fiscal Y Jur\u00cddica",
    "sg:phone":"+34 954 21 39 69",
    "sg:postcode":"41001",
    "sg:province":"Sevilla",
    "wof:name":"Manuel Fernandez Calero S.l.l.",
    "wof:placetype":"venue"
},
  "geometry": {"coordinates":[-5.9986181259,37.3879089355],"type":"Point"}
}