{
  "type": "Feature",
  "properties": {
    "iso:country":"ES",
    "sg:address":"Carrer de Selva Del Camp (la), 5",
    "sg:city":"Reus",
    "sg:orig_category":"Tatuajes",
    "sg:phone":"+34 977 34 35 21",
    "sg:postcode":"43201",
    "sg:province":"Tarragona",
    "wof:name":"Lopez Casal Jordi",
    "wof:placetype":"venue"
},
  "geometry": {"coordinates":[1.1086479425,41.1570014954],"type":"Point"}
}