{
  "type": "Feature",
  "properties": {
    "iso:country":"ES",
    "sg:address":"Calle de De Los Aguadores, S/n",
    "sg:city":"Benavente",
    "sg:orig_category":"Agentes Generales De Seguros",
    "sg:phone":"+34 980 63 10 17",
    "sg:postcode":"49600",
    "sg:province":"Zamora",
    "wof:name":"Mansilla Diez S.l.",
    "wof:placetype":"venue"
},
  "geometry": {"coordinates":[-5.6814141273,42.0017089844],"type":"Point"}
}