{
  "type": "Feature",
  "properties": {
    "iso:country":"ES",
    "sg:address":"Carrer de Autovia De Castelldefels, S/n",
    "sg:city":"Gava",
    "sg:orig_category":"Asistencia Y Seguros De Automovilistas Y Turistas",
    "sg:phone":"+34 902 35 17 35",
    "sg:postcode":"08850",
    "sg:province":"Barcelona",
    "wof:name":"Gruas Castelldefels S.l.",
    "wof:placetype":"venue"
},
  "geometry": {"coordinates":[2.0502977371,41.2936592102],"type":"Point"}
}