{
  "type": "Feature",
  "properties": {
    "addr:full":"Carrer de Gremi De Ferrers, 6 Poligon Industrial De Son Castello Islas Baleares 07009",
    "addr:housenumber":"6",
    "addr:postcode":"07009",
    "addr:street":"Carrer De Gremi De Ferrers;Islas",
    "iso:country":"ES",
    "sg:address":"Carrer de Gremi De Ferrers, 6",
    "sg:city":"Poligon Industrial De Son Castello",
    "sg:orig_category":"Electricidad: Equipos Industriales, Componentes (fabricaci\u00d3n)",
    "sg:phone":"+34 971 43 65 17",
    "sg:postcode":"07009",
    "sg:province":"Islas Baleares",
    "wof:name":"Maipret Suministros Industriales S.a.",
    "wof:placetype":"venue"
},
  "geometry": {"coordinates":[2.6776249409,39.6072845459],"type":"Point"}
}