{
  "type": "Feature",
  "properties": {
    "addr:full":"Plaz Ezkabazabal, 3 Burlada Navarra 31600",
    "addr:housenumber":"3",
    "addr:postcode":"31600",
    "addr:street":"Plaz Ezkabazabal",
    "iso:country":"ES",
    "sg:address":"Plaz Ezkabazabal, 3",
    "sg:city":"Burlada",
    "sg:orig_category":"Peluquer\u00cdas, Peluquer\u00cda Mixta",
    "sg:phone":"+34 948 14 86 58",
    "sg:postcode":"31600",
    "sg:province":"Navarra",
    "wof:name":"Gamboa Barandiaran Ma Gonzalez Mediavilla Ai Y Urrizola Zazpe Ai",
    "wof:placetype":"venue"
},
  "geometry": {"coordinates":[-1.6152689457,42.8264541626],"type":"Point"}
}