{
  "type": "Feature",
  "properties": {
    "addr:full":"Calle de Goya, S/n Malaga M\u00e1laga 29002",
    "addr:housenumber":"s",
    "addr:postcode":"29002",
    "addr:street":"Calle De Goya;/ N;Ma\u0301Laga",
    "iso:country":"ES",
    "sg:address":"Calle de Goya, S/n",
    "sg:city":"Malaga",
    "sg:orig_category":"Frutas, Legumbres Frescas Y Tempranas (al Por Menor)",
    "sg:phone":"+34 952 32 11 94",
    "sg:postcode":"29002",
    "sg:province":"M\u00e1laga",
    "wof:name":"Leal Torres Maria Isabel",
    "wof:placetype":"venue"
},
  "geometry": {"coordinates":[-4.4376540184,36.7058296204],"type":"Point"}
}