{
  "type": "Feature",
  "properties": {
    "addr:full":"Polig. Pocomaco, 21 A Coru\u00f1a La Coru\u00f1a 15190",
    "addr:housenumber":"21 a",
    "addr:postcode":"15190",
    "addr:street":"Polig. Pocomaco;Corun\u0303A La Corun\u0303A",
    "iso:country":"ES",
    "sg:address":"Polig. Pocomaco, 21",
    "sg:city":"A Coru\u00f1a",
    "sg:orig_category":"Confecci\u00d3n De Trajes Para Se\u00d1oras",
    "sg:phone":"+34 981 13 82 59",
    "sg:postcode":"15190",
    "sg:province":"La Coru\u00f1a",
    "wof:name":"Confecciones Ferbal S.l.",
    "wof:placetype":"venue"
},
  "geometry": {"coordinates":[-8.4312744141,43.3228416443],"type":"Point"}
}