{
  "type": "Feature",
  "properties": {
    "addr:full":"San Anton, 56 Iru\u00f1a Navarra 31001",
    "addr:housenumber":"56",
    "addr:postcode":"31001",
    "addr:street":"San Anton",
    "iso:country":"ES",
    "sg:address":"San Anton, 56",
    "sg:city":"Iru\u00f1a",
    "sg:orig_category":"Fabricaci\u00d3n, Venta De Cuadros, Accesorios Para Enmarcar",
    "sg:phone":"+34 948 20 41 42",
    "sg:postcode":"31001",
    "sg:province":"Navarra",
    "wof:name":"Amecan S.l.",
    "wof:placetype":"venue"
},
  "geometry": {"coordinates":[-1.6471087933,42.8158760071],"type":"Point"}
}