{
  "type": "Feature",
  "properties": {
    "addr:full":"Calle de Lapurbide, 5 Ansoain Navarra 31013",
    "addr:housenumber":"5",
    "addr:postcode":"31013",
    "addr:street":"Calle De Lapurbide",
    "iso:country":"ES",
    "sg:address":"Calle de Lapurbide, 5",
    "sg:city":"Ansoain",
    "sg:orig_category":"Cajas De Ahorro",
    "sg:phone":"+34 948 12 46 89",
    "sg:postcode":"31013",
    "sg:province":"Navarra",
    "sg:website":"www.cajalaboralpopular.com",
    "wof:name":"Caja Laboral Popular",
    "wof:placetype":"venue"
},
  "geometry": {"coordinates":[-1.6384199858,42.8329429626],"type":"Point"}
}