{
  "type": "Feature",
  "properties": {
    "addr:full":"Carrer de Saltadora, 17 Ulldemolins Tarragona 43363",
    "addr:housenumber":"17",
    "addr:postcode":"43363",
    "addr:street":"Carrer De Saltadora",
    "iso:country":"ES",
    "sg:address":"Carrer de Saltadora, 17",
    "sg:city":"Ulldemolins",
    "sg:orig_category":"Cooperativas Agr\u00cdcolas",
    "sg:phone":"+34 977 56 16 13",
    "sg:postcode":"43363",
    "sg:province":"Tarragona",
    "wof:name":"Agricola D'ulldemolins Santa Jaume Sccl",
    "wof:placetype":"venue"
},
  "geometry": {"coordinates":[0.8765195012,41.3217201233],"type":"Point"}
}