{
  "type": "Feature",
  "properties": {
    "addr:full":"Plaz Alfalfa (la), 9 Sevilla Sevilla 41004",
    "addr:housenumber":"9",
    "addr:postcode":"41004",
    "addr:street":"La",
    "iso:country":"ES",
    "sg:address":"Plaz Alfalfa (la), 9",
    "sg:city":"Sevilla",
    "sg:orig_category":"\u00d3ptica: Instrumentos (fabricaci\u00d3n)",
    "sg:phone":"+34 954 21 31 59",
    "sg:postcode":"41004",
    "sg:province":"Sevilla",
    "wof:name":"Delgado Lopez Jose Maria",
    "wof:placetype":"venue"
},
  "geometry": {"coordinates":[-5.9899020195,37.3901329041],"type":"Point"}
}