{
  "type": "Feature",
  "properties": {
    "iso:country":"ES",
    "sg:address":"Ctra. Ciudad Rodrigo, Km. 0242,0",
    "sg:city":"Carrascal Barregas",
    "sg:orig_category":"Promotores Constructores",
    "sg:phone":"+34 923 33 01 61",
    "sg:postcode":"37129",
    "sg:province":"Salamanca",
    "wof:name":"Recauchutados Y Construcciones Manuel S. A.",
    "wof:placetype":"venue"
},
  "geometry": {"coordinates":[-5.761329174,40.9782981873],"type":"Point"}
}