{
  "type": "Feature",
  "properties": {
    "addr:full":"F Salazar Alonso, S/n Las Galletas Santa Cruz De Tenerife 38631",
    "addr:housenumber":"s / n",
    "addr:postcode":"38631",
    "addr:street":"Alonso",
    "iso:country":"ES",
    "sg:address":"F Salazar Alonso, S/n",
    "sg:city":"Las Galletas",
    "sg:orig_category":"Perfumer\u00cda (al Por Menor)",
    "sg:phone":"+34 922 73 27 37",
    "sg:postcode":"38631",
    "sg:province":"Santa Cruz De Tenerife",
    "wof:name":"Gomez Gonzalez Ana Maria",
    "wof:placetype":"venue"
},
  "geometry": {"coordinates":[-16.670463562,28.0141906738],"type":"Point"}
}