{
  "type": "Feature",
  "properties": {
    "iso:country":"ES",
    "sg:address":"Calle de Marques De Lema, 25",
    "sg:city":"Alcorisa",
    "sg:orig_category":"Carnicer\u00cdas, Carnicer\u00cdas",
    "sg:phone":"+34 978 84 03 18",
    "sg:postcode":"44550",
    "sg:province":"Teruel",
    "wof:name":"Espallargas Andreu Miguel",
    "wof:placetype":"venue"
},
  "geometry": {"coordinates":[-0.3830080032,40.891204834],"type":"Point"}
}