{
  "type": "Feature",
  "properties": {
    "addr:full":"Avda Concordia, S/n Tui Pontevedra 36700",
    "addr:housenumber":"s / n",
    "addr:postcode":"36700",
    "addr:street":"Avda Concordia",
    "iso:country":"ES",
    "sg:address":"Avda Concordia, S/n",
    "sg:city":"Tui",
    "sg:classifiers":[
        {
            "category":"Taxi",
            "type":"Transportation"
        }
    ],
    "sg:phone":"+34 986 60 01 60",
    "sg:postcode":"36700",
    "sg:province":"Pontevedra",
    "wof:name":"Agrupacion Taxis Guillarei",
    "wof:placetype":"venue"
},
  "geometry": {"coordinates":[-8.6426553726,42.0541381836],"type":"Point"}
}