{
  "type": "Feature",
  "properties": {
    "iso:country":"ES",
    "sg:address":"Calle de Venus, S/n",
    "sg:city":"Benidorm",
    "sg:orig_category":"Art\u00cdculos De Decoraci\u00d3n",
    "sg:phone":"+34 965 85 23 86",
    "sg:postcode":"03500",
    "sg:province":"Alicante",
    "wof:name":"Decobric Santafe S.a.",
    "wof:placetype":"venue"
},
  "geometry": {"coordinates":[-0.1315640062,38.5409965515],"type":"Point"}
}