{
  "type": "Feature",
  "properties": {
    "addr:full":"Avda Badajoz, 5 Madrid Madrid 28027",
    "addr:housenumber":"5",
    "addr:postcode":"28027",
    "addr:street":"Avda Badajoz",
    "iso:country":"ES",
    "sg:address":"Avda Badajoz, 5",
    "sg:city":"Madrid",
    "sg:orig_category":"Laboratorios Y Cl\u00cdnicas Veterinarias",
    "sg:phone":"+34 914 03 99 55",
    "sg:postcode":"28027",
    "sg:province":"Madrid",
    "wof:name":"Garcia Pedrosa Maria Del Mar",
    "wof:placetype":"venue"
},
  "geometry": {"coordinates":[-3.6553928852,40.4415168762],"type":"Point"}
}