{
  "type": "Feature",
  "properties": {
    "addr:full":"Carrer de Vene\u00c7uela, S/n Granollers Barcelona 08402",
    "addr:housenumber":"s",
    "addr:postcode":"08402",
    "addr:street":"Carrer De Venec\u0327Uela;/ N",
    "iso:country":"ES",
    "sg:address":"Carrer de Vene\u00c7uela, S/n",
    "sg:city":"Granollers",
    "sg:classifiers":[
        {
            "category":"Communications",
            "type":"Services"
        }
    ],
    "sg:phone":"+34 938 46 83 13",
    "sg:postcode":"08402",
    "sg:province":"Barcelona",
    "sg:tags":[
        "televisiones",
        "y",
        "radio"
    ],
    "wof:name":"Ajuntament Granollers",
    "wof:placetype":"venue"
},
  "geometry": {"coordinates":[2.2901277542,41.595916748],"type":"Point"}
}