{
  "type": "Feature",
  "properties": {
    "addr:full":"Calle de Ascao, 47 Madrid Madrid 28017",
    "addr:housenumber":"47",
    "addr:postcode":"madrid;28017",
    "addr:street":"Calle De Ascao",
    "iso:country":"ES",
    "sg:address":"Calle de Ascao, 47",
    "sg:city":"Madrid",
    "sg:orig_category":"Farmacias",
    "sg:phone":"+34 913 67 52 42",
    "sg:postcode":"28017",
    "sg:province":"Madrid",
    "wof:name":"Martin Perez Jose Miguel",
    "wof:placetype":"venue"
},
  "geometry": {"coordinates":[-3.6387162209,40.4311408997],"type":"Point"}
}