{
  "type": "Feature",
  "properties": {
    "iso:country":"ES",
    "sg:address":"Carrer de Casals I Cubero, 256",
    "sg:city":"Barcelona",
    "sg:orig_category":"Tintorer\u00cdas, Limpieza En Seco",
    "sg:phone":"+34 933 50 69 53",
    "sg:postcode":"08042",
    "sg:province":"Barcelona",
    "wof:name":"Sancho Aparicio Leonor",
    "wof:placetype":"venue"
},
  "geometry": {"coordinates":[2.176678896,41.4423103333],"type":"Point"}
}