{
  "type": "Feature",
  "properties": {
    "addr:full":"Carr Riu Freser, 39 Girona Girona 17003",
    "addr:housenumber":"39",
    "addr:postcode":"17003",
    "addr:street":"Carr Riu Freser",
    "iso:country":"ES",
    "sg:address":"Carr Riu Freser, 39",
    "sg:city":"Girona",
    "sg:orig_category":"Calefacci\u00d3n Central: Material (fabricaci\u00d3n, Al Por Mayor)",
    "sg:phone":"+34 972 22 17 91",
    "sg:postcode":"17003",
    "sg:province":"Girona",
    "wof:name":"Termibarna S. A.",
    "wof:placetype":"venue"
},
  "geometry": {"coordinates":[2.8145709038,41.9668273926],"type":"Point"}
}