{
  "type": "Feature",
  "properties": {
    "addr:full":"Carrer de Indalecio Prieto, 11 Palma Islas Baleares 07008",
    "addr:housenumber":"11",
    "addr:postcode":"07008",
    "addr:street":"Carrer De Indalecio Prieto",
    "iso:country":"ES",
    "sg:address":"Carrer de Indalecio Prieto, 11",
    "sg:city":"Palma",
    "sg:orig_category":"Zapatos (al Por Menor)",
    "sg:phone":"+34 971 27 16 87",
    "sg:postcode":"07008",
    "sg:province":"Islas Baleares",
    "wof:name":"Inmobulding Group S.l.",
    "wof:placetype":"venue"
},
  "geometry": {"coordinates":[2.6698079109,39.5773162842],"type":"Point"}
}