{
  "type": "Feature",
  "properties": {
    "iso:country":"ES",
    "sg:address":"Calle de Pintor Puig Roda, 33",
    "sg:city":"Vinaros",
    "sg:orig_category":"Electricidad: Instaladores",
    "sg:phone":"+34 964 45 03 63",
    "sg:postcode":"12500",
    "sg:province":"Castell\u00f3n",
    "wof:name":"Ayza Buch Roman",
    "wof:placetype":"venue"
},
  "geometry": {"coordinates":[0.4689485133,40.472454071],"type":"Point"}
}