{
  "type": "Feature",
  "properties": {
    "iso:country":"ES",
    "sg:address":"Avda Paz, 16",
    "sg:city":"Martos",
    "sg:orig_category":"Inmobiliaria (agencias)",
    "sg:phone":"+34 953 70 41 21",
    "sg:postcode":"23600",
    "sg:province":"Ja\u00e9n",
    "wof:name":"Moral Millan S.l.",
    "wof:placetype":"venue"
},
  "geometry": {"coordinates":[-3.9744689465,37.7198600769],"type":"Point"}
}