{
  "type": "Feature",
  "properties": {
    "addr:full":"Carr Joan Maso I Valenti, 24 Girona Girona 17005",
    "addr:housenumber":"24",
    "addr:postcode":"17005",
    "addr:street":"Carr Joan Maso I Valenti",
    "iso:country":"ES",
    "sg:address":"Carr Joan Maso I Valenti, 24",
    "sg:city":"Girona",
    "sg:orig_category":"Inmobiliaria (agencias)",
    "sg:phone":"+34 972 24 21 49",
    "sg:postcode":"17005",
    "sg:province":"Girona",
    "wof:name":"Comunidad De Propietarios Joan Maso I Valenti 4 Esc D",
    "wof:placetype":"venue"
},
  "geometry": {"coordinates":[2.814884901,41.976688385],"type":"Point"}
}