{
  "type": "Feature",
  "properties": {
    "addr:full":"Calvo Sotelo, 5 Pobra Carami\u00f1al La Coru\u00f1a 15940",
    "addr:housenumber":"5",
    "addr:postcode":"15940",
    "addr:street":"Calvo Sotelo;Corun\u0303A",
    "iso:country":"ES",
    "sg:address":"Calvo Sotelo, 5",
    "sg:city":"Pobra Carami\u00f1al",
    "sg:orig_category":"Peluqueros: De Se\u00d1oras",
    "sg:phone":"+34 981 83 25 22",
    "sg:postcode":"15940",
    "sg:province":"La Coru\u00f1a",
    "wof:name":"Outeiral Matis Dolores",
    "wof:placetype":"venue"
},
  "geometry": {"coordinates":[-8.9388437271,42.6042404175],"type":"Point"}
}