{
  "type": "Feature",
  "properties": {
    "iso:country":"ES",
    "sg:address":"Calle de Graham Bell, 5",
    "sg:city":"Sevilla",
    "sg:orig_category":"Promotores Constructores",
    "sg:phone":"+34 954 23 70 52",
    "sg:postcode":"41010",
    "sg:province":"Sevilla",
    "wof:name":"Rafael Morales S. A.",
    "wof:placetype":"venue"
},
  "geometry": {"coordinates":[-6.0092940331,37.3758773804],"type":"Point"}
}