{
  "type": "Feature",
  "properties": {
    "iso:country":"ES",
    "sg:address":"Calle de Carmen, 42",
    "sg:city":"Pe\u00e7aranda De Bracamonte",
    "sg:orig_category":"Muebles Y Accesorios Para Cocinas Y Cuartos De Ba\u00d1o (al Por Menor)",
    "sg:phone":"+34 923 54 11 30",
    "sg:postcode":"37300",
    "sg:province":"Salamanca",
    "wof:name":"Mu\u00f1oz Salgado Generoso",
    "wof:placetype":"venue"
},
  "geometry": {"coordinates":[-5.6630473137,40.9649734497],"type":"Point"}
}