{
  "type": "Feature",
  "properties": {
    "iso:country":"ES",
    "sg:address":"Calle de Calzada (la), 18",
    "sg:city":"Lucena",
    "sg:orig_category":"Reposter\u00cdas",
    "sg:phone":"+34 957 50 01 01",
    "sg:postcode":"14900",
    "sg:province":"C\u00f3rdoba",
    "wof:name":"Panaderia Confiteria Nuestra Se\u00f1ora De Araceli S.l",
    "wof:placetype":"venue"
},
  "geometry": {"coordinates":[-4.4870476723,37.4052238464],"type":"Point"}
}