{
  "type": "Feature",
  "properties": {
    "addr:full":"Barr Urioste, 60 Urioste Vizcaya 48530",
    "addr:housenumber":"60",
    "addr:postcode":"48530",
    "addr:street":"Urioste",
    "iso:country":"ES",
    "sg:address":"Barr Urioste, 60",
    "sg:city":"Urioste",
    "sg:orig_category":"Fabricaci\u00d3n, Reparaci\u00d3n Y Mantenimiento De Construcciones Navales Y Fluviales",
    "sg:phone":"+34 946 64 19 53",
    "sg:postcode":"48530",
    "sg:province":"Vizcaya",
    "sg:website":"www.mycasal.com",
    "wof:name":"Mecanica Y Caldereria Asociada S.a.l.",
    "wof:placetype":"venue"
},
  "geometry": {"coordinates":[-3.0566248894,43.3107376099],"type":"Point"}
}