{
  "type": "Feature",
  "properties": {
    "iso:country":"ES",
    "sg:address":"Rua Porta Da Pena (da), 2",
    "sg:city":"Santiago De Compostela",
    "sg:orig_category":"Asociaciones, Organismos Culturales Y Socioeducativos",
    "sg:phone":"+34 981 58 46 51",
    "sg:postcode":"15704",
    "sg:province":"La Coru\u00f1a",
    "wof:name":"Asociacion Cultural Sempre Cine",
    "wof:placetype":"venue"
},
  "geometry": {"coordinates":[-8.5433692932,42.8827209473],"type":"Point"}
}