{
  "type": "Feature",
  "properties": {
    "addr:full":"Calle de Venegas, 2 Palmas De Gran Canaria Las Palmas 35003",
    "addr:housenumber":"2",
    "addr:postcode":"35003",
    "addr:street":"Calle De Venegas",
    "iso:country":"ES",
    "sg:address":"Calle de Venegas, 2",
    "sg:city":"Palmas De Gran Canaria",
    "sg:orig_category":"Mobiliario M\u00c9dico Y Quir\u00dargico",
    "sg:phone":"+34 928 43 27 55",
    "sg:postcode":"35003",
    "sg:province":"Las Palmas",
    "wof:name":"Sirona Equipos Dentales Iberica S.a.",
    "wof:placetype":"venue"
},
  "geometry": {"coordinates":[-15.4178524017,28.1109867096],"type":"Point"}
}