{
  "type": "Feature",
  "properties": {
    "addr:full":"Carrer de Romania, 3 Terrassa Barcelona 08228",
    "addr:housenumber":"3",
    "addr:postcode":"08228",
    "addr:street":"Carrer De Romania",
    "iso:country":"ES",
    "sg:address":"Carrer de Romania, 3",
    "sg:city":"Terrassa",
    "sg:orig_category":"Agencias Y Agentes Comerciales, Representantes",
    "sg:phone":"+34 937 31 64 70",
    "sg:postcode":"08228",
    "sg:province":"Barcelona",
    "wof:name":"Lopez Moreno Antonio",
    "wof:placetype":"venue"
},
  "geometry": {"coordinates":[2.0403029919,41.5367240906],"type":"Point"}
}