{
  "type": "Feature",
  "properties": {
    "iso:country":"ES",
    "sg:address":"Pl Palmeres, 2",
    "sg:city":"Cerdanyola Valles",
    "sg:orig_category":"Institutos De Belleza",
    "sg:phone":"+34 935 92 02 30",
    "sg:postcode":"08290",
    "sg:province":"Barcelona",
    "wof:name":"Puga Lluch Ana",
    "wof:placetype":"venue"
},
  "geometry": {"coordinates":[2.1329228878,41.4951438904],"type":"Point"}
}