{
  "type": "Feature",
  "properties": {
    "iso:country":"ES",
    "sg:address":"Elbarrena Kalea (pol Lanbarren), 3",
    "sg:city":"Oiartzun",
    "sg:orig_category":"Trabajos De Soldaduras",
    "sg:phone":"+34 943 49 06 98",
    "sg:postcode":"20180",
    "sg:province":"Guip\u00f9zcoa",
    "wof:name":"Ubare Soldadura S.l.",
    "wof:placetype":"venue"
},
  "geometry": {"coordinates":[-1.8697190285,43.3174095154],"type":"Point"}
}