{
  "type": "Feature",
  "properties": {
    "iso:country":"ES",
    "sg:address":"Calle de Alfonso Viii, 4",
    "sg:city":"Carolina",
    "sg:orig_category":"Confiter\u00cdas, Chocolater\u00cdas (al Por Menor)",
    "sg:phone":"+34 953 68 19 31",
    "sg:postcode":"23200",
    "sg:province":"Ja\u00e9n",
    "wof:name":"Carre\u00f1o Martinez Antonia",
    "wof:placetype":"venue"
},
  "geometry": {"coordinates":[-3.5870280266,38.2852516174],"type":"Point"}
}