{
  "type": "Feature",
  "properties": {
    "iso:country":"ES",
    "sg:address":"Pase Mediterraneo (del), 263",
    "sg:city":"Ventanicas-el Cantal",
    "sg:orig_category":"Inmobiliaria (agencias)",
    "sg:phone":"+34 950 47 24 10",
    "sg:postcode":"04638",
    "sg:province":"Almer\u00eda",
    "wof:name":"Tobin  Declan",
    "wof:placetype":"venue"
},
  "geometry": {"coordinates":[-1.8406590223,37.122089386],"type":"Point"}
}