{
  "type": "Feature",
  "properties": {
    "iso:country":"ES",
    "sg:address":"Calle de Sdo Isern Comas, 27",
    "sg:city":"Palma",
    "sg:orig_category":"Chapister\u00cda",
    "sg:phone":"+34 971 75 64 35",
    "sg:postcode":"07010",
    "sg:province":"Islas Baleares",
    "wof:name":"Sanso Ginard Jose",
    "wof:placetype":"venue"
},
  "geometry": {"coordinates":[2.6481490135,39.5867080688],"type":"Point"}
}