{
  "type": "Feature",
  "properties": {
    "iso:country":"ES",
    "sg:address":"Plaz Salamanca, 17",
    "sg:city":"Villanueva Serena",
    "sg:orig_category":"Librer\u00cdas",
    "sg:phone":"+34 924 84 55 82",
    "sg:postcode":"06700",
    "sg:province":"Badajoz",
    "wof:name":"Benitez Leon Joaquina",
    "wof:placetype":"venue"
},
  "geometry": {"coordinates":[-5.7927408218,38.9731750488],"type":"Point"}
}