{
  "type": "Feature",
  "properties": {
    "addr:full":"Calle de Alcoy, 30 Onil Alicante 03430",
    "addr:housenumber":"30",
    "addr:postcode":"03430",
    "addr:street":"Calle De Alcoy",
    "iso:country":"ES",
    "sg:address":"Calle de Alcoy, 30",
    "sg:city":"Onil",
    "sg:orig_category":"Disfraces",
    "sg:phone":"+34 965 56 47 71",
    "sg:postcode":"03430",
    "sg:province":"Alicante",
    "wof:name":"Limit Sport S.l.",
    "wof:placetype":"venue"
},
  "geometry": {"coordinates":[-0.6705511808,38.6286659241],"type":"Point"}
}