{
  "type": "Feature",
  "properties": {
    "addr:full":"Carrer de Ferralla, S/n Poligon Industrial Sant Vicen\u00c7 Barcelona 08755",
    "addr:housenumber":"s / n",
    "addr:postcode":"08755",
    "addr:street":"Carrer De Ferralla",
    "iso:country":"ES",
    "sg:address":"Carrer de Ferralla, S/n",
    "sg:city":"Poligon Industrial Sant Vicen\u00c7",
    "sg:orig_category":"Ferreter\u00cda (diversos)",
    "sg:phone":"+34 937 72 00 57",
    "sg:postcode":"08755",
    "sg:province":"Barcelona",
    "wof:name":"Viuda De Lauro Clariana S.l.",
    "wof:placetype":"venue"
},
  "geometry": {"coordinates":[1.9902952909,41.4415168762],"type":"Point"}
}