{
  "type": "Feature",
  "properties": {
    "iso:country":"ES",
    "sg:address":"Calle de Mirador (el), 2",
    "sg:city":"San Isidro",
    "sg:orig_category":"M\u00c9dicos: An\u00c1lisis Cl\u00cdnicos",
    "sg:phone":"+34 922 39 09 49",
    "sg:postcode":"38611",
    "sg:province":"Santa Cruz De Tenerife",
    "wof:name":"Hernandez Fumero Maria Hildelina",
    "wof:placetype":"venue"
},
  "geometry": {"coordinates":[-16.5598697662,28.0736293793],"type":"Point"}
}