{
  "type": "Feature",
  "properties": {
    "iso:country":"ES",
    "sg:address":"Ctra Molins De Rei, Km. 0013,0",
    "sg:city":"Rubi",
    "sg:orig_category":"Fabricaci\u00d3n De Su\u00c9ters Y Chalecos De Punto",
    "sg:phone":"+34 936 99 97 63",
    "sg:postcode":"08191",
    "sg:province":"Barcelona",
    "wof:name":"Jorsa S.l",
    "wof:placetype":"venue"
},
  "geometry": {"coordinates":[2.0307109356,41.4825019836],"type":"Point"}
}