{
  "type": "Feature",
  "properties": {
    "addr:full":"Avda Olivo, 3 Mora Toledo 45400",
    "addr:housenumber":"3",
    "addr:postcode":"45400",
    "addr:street":"Avda Olivo",
    "iso:country":"ES",
    "sg:address":"Avda Olivo, 3",
    "sg:city":"Mora",
    "sg:orig_category":"Empresas De Carpinter\u00cda De Madera",
    "sg:phone":"+34 925 34 18 33",
    "sg:postcode":"45400",
    "sg:province":"Toledo",
    "wof:name":"Carpinteria Hermanos Montoya S.l.",
    "wof:placetype":"venue"
},
  "geometry": {"coordinates":[-3.7735650539,39.6867980957],"type":"Point"}
}