{
  "type": "Feature",
  "properties": {
    "addr:full":"Calle de Ramon Y Cajal, 23 Calanda Teruel 44570",
    "addr:housenumber":"23",
    "addr:postcode":"44570",
    "addr:street":"Calle De Ramon Y Cajal",
    "iso:country":"ES",
    "sg:address":"Calle de Ramon Y Cajal, 23",
    "sg:city":"Calanda",
    "sg:orig_category":"Cr\u00cda De Cerdos",
    "sg:phone":"+34 978 84 71 14",
    "sg:postcode":"44570",
    "sg:province":"Teruel",
    "wof:name":"Medina Balaguer S.cv.",
    "wof:placetype":"venue"
},
  "geometry": {"coordinates":[-0.2338099927,40.9401512146],"type":"Point"}
}