{
  "type": "Feature",
  "properties": {
    "iso:country":"ES",
    "sg:address":"Calle de Fundacion, S/n",
    "sg:city":"Jumilla",
    "sg:orig_category":"Pescader\u00cdas (al Por Menor)",
    "sg:phone":"+34 968 75 63 13",
    "sg:postcode":"30520",
    "sg:province":"Murcia",
    "wof:name":"Gilar Herrero Pedro Jose",
    "wof:placetype":"venue"
},
  "geometry": {"coordinates":[-1.3180290461,38.4763755798],"type":"Point"}
}