{
  "type": "Feature",
  "properties": {
    "addr:full":"Av. Galicia, 20 Iru\u00f1a Navarra 31003",
    "addr:housenumber":"20",
    "addr:postcode":"31003",
    "addr:street":"Av. Galicia",
    "iso:country":"ES",
    "sg:address":"Av. Galicia, 20",
    "sg:city":"Iru\u00f1a",
    "sg:orig_category":"Organizaciones Internacionales",
    "sg:phone":"+34 948 15 19 58",
    "sg:postcode":"31003",
    "sg:province":"Navarra",
    "wof:name":"Maristas Ong Sed",
    "wof:placetype":"venue"
},
  "geometry": {"coordinates":[-1.6386150122,42.8094596863],"type":"Point"}
}