{
  "type": "Feature",
  "properties": {
    "addr:full":"Calle de Lepanto, 108 Castellon Castell\u00f3n 12006",
    "addr:housenumber":"108",
    "addr:postcode":"12006",
    "addr:street":"Calle De Lepanto",
    "iso:country":"ES",
    "sg:address":"Calle de Lepanto, 108",
    "sg:city":"Castellon",
    "sg:orig_category":"Material Y Suministros Para Fotocopiadoras, Reprograf\u00cda",
    "sg:phone":"+34 964 24 00 13",
    "sg:postcode":"12006",
    "sg:province":"Castell\u00f3n",
    "wof:name":"Copidos S.l.",
    "wof:placetype":"venue"
},
  "geometry": {"coordinates":[-0.1292939931,40.0168533325],"type":"Point"}
}