{
  "type": "Feature",
  "properties": {
    "iso:country":"ES",
    "sg:address":"Calle de Reyes Leoneses, 38",
    "sg:city":"Le\u00f3n",
    "sg:orig_category":"Tintorer\u00cdas, Limpieza En Seco",
    "sg:phone":"+34 987 80 80 30",
    "sg:postcode":"24008",
    "sg:province":"Le\u00f3n",
    "sg:website":"www.paginasamarillas.es",
    "wof:name":"Lamacane S.l.",
    "wof:placetype":"venue"
},
  "geometry": {"coordinates":[-5.5893340111,42.6134605408],"type":"Point"}
}