{
  "type": "Feature",
  "properties": {
    "iso:country":"ES",
    "sg:address":"Ptda Verdala, 15",
    "sg:city":"Pego",
    "sg:orig_category":"Fabricaci\u00d3n Y Distribuci\u00d3n De Colas, Masillas Y Encoladoras",
    "sg:phone":"+34 965 57 05 40",
    "sg:postcode":"03780",
    "sg:province":"Alicante",
    "wof:name":"Xavier Y Reich S.l",
    "wof:placetype":"venue"
},
  "geometry": {"coordinates":[-0.1027180031,38.8518714905],"type":"Point"}
}