{
  "type": "Feature",
  "properties": {
    "addr:full":"Avda Portugal, 2 Alcorcon Madrid 28921",
    "addr:housenumber":"2",
    "addr:postcode":"28921",
    "addr:street":"Avda Portugal",
    "iso:country":"ES",
    "sg:address":"Avda Portugal, 2",
    "sg:city":"Alcorcon",
    "sg:orig_category":"Administradores De Bienes Y Delegados De Comunidades De Propietarios",
    "sg:phone":"+34 916 42 54 90",
    "sg:postcode":"28921",
    "sg:province":"Madrid",
    "wof:name":"Jesus Navarro Consultores Y Asesores S.a.",
    "wof:placetype":"venue"
},
  "geometry": {"coordinates":[-3.8292989731,40.3490905762],"type":"Point"}
}