{
  "type": "Feature",
  "properties": {
    "addr:full":"Calle de Carmen De Icaza, 26 Granada Granada 18007",
    "addr:housenumber":"26",
    "addr:postcode":"18007",
    "addr:street":"Calle De Carmen De Icaza",
    "iso:country":"ES",
    "sg:address":"Calle de Carmen De Icaza, 26",
    "sg:city":"Granada",
    "sg:orig_category":"Cajas Y Embalajes Met\u00c1licos",
    "sg:phone":"+34 958 12 83 53",
    "sg:postcode":"18007",
    "sg:province":"Granada",
    "wof:name":"Fedinsa Envases S.a.",
    "wof:placetype":"venue"
},
  "geometry": {"coordinates":[-3.6033320427,37.1557121277],"type":"Point"}
}