{
  "type": "Feature",
  "properties": {
    "addr:full":"Avda Yecla (de), S/n Jumilla Murcia 30520",
    "addr:housenumber":"/ n",
    "addr:postcode":"30520",
    "addr:street":"Avda Yecla De S",
    "iso:country":"ES",
    "sg:address":"Avda Yecla (de), S/n",
    "sg:city":"Jumilla",
    "sg:orig_category":"Fabricaci\u00d3n De Quesos",
    "sg:phone":"+34 968 78 13 69",
    "sg:postcode":"30520",
    "sg:province":"Murcia",
    "wof:name":"Queseria El Romeral S.l.",
    "wof:placetype":"venue"
},
  "geometry": {"coordinates":[-1.3222140074,38.4765434265],"type":"Point"}
}