{
  "type": "Feature",
  "properties": {
    "addr:full":"Calle de Santa Teresa Del Ni\u00d1o Jesus, 3 Sanlucar Mayor Sevilla 41800",
    "addr:housenumber":"3",
    "addr:postcode":"41800",
    "addr:street":"Calle De Santa;Jesus",
    "iso:country":"ES",
    "sg:address":"Calle de Santa Teresa Del Ni\u00d1o Jesus, 3",
    "sg:city":"Sanlucar Mayor",
    "sg:orig_category":"Librer\u00cdas",
    "sg:phone":"+34 955 70 26 48",
    "sg:postcode":"41800",
    "sg:province":"Sevilla",
    "wof:name":"Gutierrez Gallego Maria Teresa",
    "wof:placetype":"venue"
},
  "geometry": {"coordinates":[-6.2012529373,37.385433197],"type":"Point"}
}