{
  "type": "Feature",
  "properties": {
    "addr:full":"Carrer de Andalusia, 38 Barcelona Barcelona 08014",
    "addr:housenumber":"38",
    "addr:postcode":"08014",
    "addr:street":"Carrer De Andalusia",
    "iso:country":"ES",
    "sg:address":"Carrer de Andalusia, 38",
    "sg:city":"Barcelona",
    "sg:orig_category":"Peluquer\u00cdas, Peluquer\u00cda Mixta",
    "sg:phone":"+34 934 22 96 44",
    "sg:postcode":"08014",
    "sg:province":"Barcelona",
    "wof:name":"Ferreres Gil Antonia",
    "wof:placetype":"venue"
},
  "geometry": {"coordinates":[2.1333611012,41.3711776733],"type":"Point"}
}