{
  "type": "Feature",
  "properties": {
    "addr:full":"Belgica (pol Ind Pla Llerona), S/n Llerona Barcelona 08520",
    "addr:housenumber":"s",
    "addr:postcode":"08520",
    "addr:street":"Belgica Pol Ind Pla Llerona;/ N",
    "iso:country":"ES",
    "sg:address":"Belgica (pol Ind Pla Llerona), S/n",
    "sg:city":"Llerona",
    "sg:orig_category":"Productos Qu\u00cdmicos (fabricaci\u00d3n, Al Por Mayor)",
    "sg:phone":"+34 938 49 34 55",
    "sg:postcode":"08520",
    "sg:province":"Barcelona",
    "wof:name":"Cygyc S.a.",
    "wof:placetype":"venue"
},
  "geometry": {"coordinates":[2.2953050137,41.6295814514],"type":"Point"}
}