{
  "type": "Feature",
  "properties": {
    "addr:full":"Av Catalunya, 2 Mollerussa Lleida 25230",
    "addr:housenumber":"2",
    "addr:postcode":"25230",
    "addr:street":"Av Catalunya",
    "iso:country":"ES",
    "sg:address":"Av Catalunya, 2",
    "sg:city":"Mollerussa",
    "sg:orig_category":"Agencias Y Agentes Comerciales, Representantes",
    "sg:phone":"+34 973 60 02 43",
    "sg:postcode":"25230",
    "sg:province":"Lleida",
    "wof:name":"Minguell Amoros Francesc Xavier",
    "wof:placetype":"venue"
},
  "geometry": {"coordinates":[0.8974230289,41.6283073425],"type":"Point"}
}