{
  "type": "Feature",
  "properties": {
    "addr:full":"Avda Luz, S/n Malaga M\u00e1laga 29004",
    "addr:housenumber":"s / n",
    "addr:postcode":"29004",
    "addr:street":"Avda Luz;Ma\u0301Laga",
    "iso:country":"ES",
    "sg:address":"Avda Luz, S/n",
    "sg:city":"Malaga",
    "sg:orig_category":"Congelados: Productos Alimentarios (al Por Menor)",
    "sg:phone":"+34 952 17 37 81",
    "sg:postcode":"29004",
    "sg:province":"M\u00e1laga",
    "wof:name":"Montoya Ortigosa Mari Carmen",
    "wof:placetype":"venue"
},
  "geometry": {"coordinates":[-4.4555840492,36.6973152161],"type":"Point"}
}