{
  "type": "Feature",
  "properties": {
    "addr:full":"Plaza Mercado De Abastos, S/n Ponferrada Le\u00f3n 24400",
    "addr:housenumber":"s / n",
    "addr:postcode":"24400",
    "iso:country":"ES",
    "sg:address":"Plaza Mercado De Abastos, S/n",
    "sg:city":"Ponferrada",
    "sg:orig_category":"Casquer\u00cda (al Por Menor)",
    "sg:phone":"+34 987 42 45 82",
    "sg:postcode":"24400",
    "sg:province":"Le\u00f3n",
    "wof:name":"Soto Fernandez Isidro",
    "wof:placetype":"venue"
},
  "geometry": {"coordinates":[-6.5983390808,42.5483360291],"type":"Point"}
}