{
  "type": "Feature",
  "properties": {
    "addr:full":"Calle de Humera (de), 18 Fuenlabrada Madrid 28945",
    "addr:housenumber":"18",
    "addr:postcode":"28945",
    "addr:street":"Calle De Humera De",
    "iso:country":"ES",
    "sg:address":"Calle de Humera (de), 18",
    "sg:city":"Fuenlabrada",
    "sg:orig_category":"Ropa Para Caballeros (al Por Menor)",
    "sg:phone":"+34 916 06 14 89",
    "sg:postcode":"28945",
    "sg:province":"Madrid",
    "wof:name":"Collado Cuenca C.b.",
    "wof:placetype":"venue"
},
  "geometry": {"coordinates":[-3.7953701019,40.2872924805],"type":"Point"}
}