{
  "type": "Feature",
  "properties": {
    "addr:full":"Carrer de Major, 76 Hospitalet Llobregat Barcelona 08901",
    "addr:housenumber":"76",
    "addr:postcode":"08901",
    "addr:street":"Carrer De Major",
    "iso:country":"ES",
    "sg:address":"Carrer de Major, 76",
    "sg:city":"Hospitalet Llobregat",
    "sg:orig_category":"Comercio De Piezas De Recambio Y De Accesorios De Veh\u00cdculos, Veh\u00cdculos Industriales",
    "sg:phone":"+34 933 37 99 99",
    "sg:postcode":"08901",
    "sg:province":"Barcelona",
    "wof:name":"Clave Marcet Jose",
    "wof:placetype":"venue"
},
  "geometry": {"coordinates":[2.0968260765,41.3594970703],"type":"Point"}
}