{
  "type": "Feature",
  "properties": {
    "iso:country":"ES",
    "sg:address":"Rua Nosa Sra. Do Viso, 13",
    "sg:city":"Ourense",
    "sg:orig_category":"Carnicer\u00cdas, Carnicer\u00cdas",
    "sg:phone":"+34 988 23 31 02",
    "sg:postcode":"32005",
    "sg:province":"Ourense",
    "wof:name":"Sierra Sierra Rosa",
    "wof:placetype":"venue"
},
  "geometry": {"coordinates":[-7.8643908501,42.3288459778],"type":"Point"}
}