{
  "type": "Feature",
  "properties": {
    "iso:country":"ES",
    "sg:address":"Roquedo, S/n",
    "sg:city":"Caraquiz",
    "sg:orig_category":"Bancos",
    "sg:phone":"+34 949 85 97 06",
    "sg:postcode":"19185",
    "sg:province":"Guadalajara",
    "wof:name":"Auna Telecomunicaciones S.a.u.",
    "wof:placetype":"venue"
},
  "geometry": {"coordinates":[-3.4832873344,40.7928886414],"type":"Point"}
}