{
  "type": "Feature",
  "properties": {
    "addr:full":"Calle de Panaderos, 7 Talavera Reina Toledo 45600",
    "addr:housenumber":"7",
    "addr:postcode":"45600",
    "addr:street":"Calle De Panaderos",
    "iso:country":"ES",
    "sg:address":"Calle de Panaderos, 7",
    "sg:city":"Talavera Reina",
    "sg:orig_category":"Chapister\u00cda",
    "sg:phone":"+34 925 81 17 18",
    "sg:postcode":"45600",
    "sg:province":"Toledo",
    "wof:name":"Talleres Julian Moran S.l.",
    "wof:placetype":"venue"
},
  "geometry": {"coordinates":[-4.8461899757,39.9549598694],"type":"Point"}
}