{
  "type": "Feature",
  "properties": {
    "iso:country":"ES",
    "sg:address":"Calle de Vereda De Santa Ana, S/n",
    "sg:city":"Caudete",
    "sg:orig_category":"Fabricaci\u00d3n De Telas Y Sedas",
    "sg:phone":"+34 965 82 71 70",
    "sg:postcode":"02660",
    "sg:province":"Albacete",
    "wof:name":"Textil Caudete Cdad",
    "wof:placetype":"venue"
},
  "geometry": {"coordinates":[-0.9946839809,38.704750061],"type":"Point"}
}