{
  "type": "Feature",
  "properties": {
    "addr:full":"Carr Angel Planells, 9 Blanes Girona 17300",
    "addr:housenumber":"9",
    "addr:postcode":"17300",
    "addr:street":"Carr Angel Planells",
    "iso:country":"ES",
    "sg:address":"Carr Angel Planells, 9",
    "sg:city":"Blanes",
    "sg:orig_category":"Peluquer\u00cdas, Peluquer\u00cda Mixta",
    "sg:phone":"+34 972 35 73 97",
    "sg:postcode":"17300",
    "sg:province":"Girona",
    "wof:name":"Zulema Peluqueria Unisex",
    "wof:placetype":"venue"
},
  "geometry": {"coordinates":[2.7853763103,41.675151825],"type":"Point"}
}