{
  "type": "Feature",
  "properties": {
    "iso:country":"ES",
    "sg:address":"Calle de Don Cristian, 48",
    "sg:city":"Malaga",
    "sg:orig_category":"Asesor\u00cda Fiscal Y Jur\u00cddica",
    "sg:phone":"+34 952 28 18 96",
    "sg:postcode":"29007",
    "sg:province":"M\u00e1laga",
    "wof:name":"Mendoza Alcain Jose Carlos",
    "wof:placetype":"venue"
},
  "geometry": {"coordinates":[-4.430970192,36.7202377319],"type":"Point"}
}