{
  "type": "Feature",
  "properties": {
    "addr:full":"Avda Francisco Javier A\u00d1on Baigorri, 54 Tudela Navarra 31500",
    "addr:housenumber":"54",
    "addr:postcode":"31500",
    "addr:street":"Avda Francisco Javier An\u0303On Baigorri",
    "iso:country":"ES",
    "sg:address":"Avda Francisco Javier A\u00d1on Baigorri, 54",
    "sg:city":"Tudela",
    "sg:orig_category":"M\u00c1quinas De Jardiner\u00cda",
    "sg:phone":"+34 948 41 20 12",
    "sg:postcode":"31500",
    "sg:province":"Navarra",
    "wof:name":"Jardin De La Rosa Tudela S.l",
    "wof:placetype":"venue"
},
  "geometry": {"coordinates":[-1.598533988,42.0545501709],"type":"Point"}
}