{
  "type": "Feature",
  "properties": {
    "iso:country":"ES",
    "sg:address":"Carrer de Arago, 78",
    "sg:city":"Barcelona",
    "sg:orig_category":"Aparcamientos (infraestructuras, Accesorios)",
    "sg:phone":"+34 934 24 49 25",
    "sg:postcode":"08015",
    "sg:province":"Barcelona",
    "wof:name":"Garaje Provenza 205 S.l.",
    "wof:placetype":"venue"
},
  "geometry": {"coordinates":[2.1524000168,41.3825874329],"type":"Point"}
}