{
  "type": "Feature",
  "properties": {
    "addr:full":"Calle de Canalejas, 25 Rute C\u00f3rdoba 14960",
    "addr:housenumber":"25",
    "addr:postcode":"14960",
    "addr:street":"Calle De Canalejas;Co\u0301Rdoba",
    "iso:country":"ES",
    "sg:address":"Calle de Canalejas, 25",
    "sg:city":"Rute",
    "sg:orig_category":"Guarder\u00cdas",
    "sg:phone":"+34 957 53 84 74",
    "sg:postcode":"14960",
    "sg:province":"C\u00f3rdoba",
    "wof:name":"Arapades",
    "wof:placetype":"venue"
},
  "geometry": {"coordinates":[-4.3684158325,37.3237838745],"type":"Point"}
}