{
  "type": "Feature",
  "properties": {
    "iso:country":"ES",
    "sg:address":"Calle de Camino Real, 3",
    "sg:city":"Yecla",
    "sg:orig_category":"Asesor\u00cda Fiscal Y Jur\u00cddica",
    "sg:phone":"+34 968 75 00 47",
    "sg:postcode":"30510",
    "sg:province":"Murcia",
    "wof:name":"Diaz Soriano Maria",
    "wof:placetype":"venue"
},
  "geometry": {"coordinates":[-1.113773942,38.6152305603],"type":"Point"}
}