{
  "type": "Feature",
  "properties": {
    "addr:full":"Del Medio, 111 S. Sebastian Gomera Santa Cruz De Tenerife 38800",
    "addr:housenumber":"111",
    "addr:postcode":"38800",
    "addr:street":"Del Medio;S. Sebastian Gomera",
    "iso:country":"ES",
    "sg:address":"Del Medio, 111",
    "sg:city":"S. Sebastian Gomera",
    "sg:orig_category":"Ropa Para Ni\u00d1os (al Por Menor)",
    "sg:phone":"+34 922 87 12 17",
    "sg:postcode":"38800",
    "sg:province":"Santa Cruz De Tenerife",
    "wof:name":"Antonia",
    "wof:placetype":"venue"
},
  "geometry": {"coordinates":[-17.1949615479,28.1544494629],"type":"Point"}
}