{
  "type": "Feature",
  "properties": {
    "addr:full":"Calle de Mayor, 26 Pozoblanco C\u00f3rdoba 14400",
    "addr:housenumber":"26",
    "addr:postcode":"14400",
    "addr:street":"Calle De Mayor",
    "iso:country":"ES",
    "sg:address":"Calle de Mayor, 26",
    "sg:city":"Pozoblanco",
    "sg:orig_category":"Telas Y Sedas (al Por Menor)",
    "sg:phone":"+34 957 77 15 79",
    "sg:postcode":"14400",
    "sg:province":"C\u00f3rdoba",
    "wof:name":"Due\u00f1as Cabrera Maria Del Carmen",
    "wof:placetype":"venue"
},
  "geometry": {"coordinates":[-4.8488769531,38.3789215088],"type":"Point"}
}