{
  "type": "Feature",
  "properties": {
    "addr:full":"Calle de Fernan Gonzalez, 65 Madrid Madrid 28009",
    "addr:housenumber":"65",
    "addr:postcode":"madrid;28009",
    "addr:street":"Calle De Fernan Gonzalez",
    "iso:country":"ES",
    "sg:address":"Calle de Fernan Gonzalez, 65",
    "sg:city":"Madrid",
    "sg:orig_category":"Aparcamientos (infraestructuras, Accesorios)",
    "sg:phone":"+34 914 09 09 25",
    "sg:postcode":"28009",
    "sg:province":"Madrid",
    "wof:name":"Gil Coca Mariano",
    "wof:placetype":"venue"
},
  "geometry": {"coordinates":[-3.6746520996,40.4177207947],"type":"Point"}
}