{
  "type": "Feature",
  "properties": {
    "iso:country":"ES",
    "sg:address":"Carrer de Pla, 47",
    "sg:city":"Molins Rei",
    "sg:orig_category":"Alumbrados",
    "sg:phone":"+34 936 80 11 10",
    "sg:postcode":"08750",
    "sg:province":"Barcelona",
    "wof:name":"Erco Iluminacion S.a.",
    "wof:placetype":"venue"
},
  "geometry": {"coordinates":[2.0243580341,41.4006843567],"type":"Point"}
}