{
  "type": "Feature",
  "properties": {
    "iso:country":"ES",
    "sg:address":"Cami Alcanada, S/n",
    "sg:city":"Port D'alcudia",
    "sg:orig_category":"Restaurantes",
    "sg:phone":"+34 971 54 56 11",
    "sg:postcode":"07410",
    "sg:province":"Islas Baleares",
    "wof:name":"Casa Gallega Alcudia S.l.",
    "wof:placetype":"venue"
},
  "geometry": {"coordinates":[2.9117100239,39.6136398315],"type":"Point"}
}