{
  "type": "Feature",
  "properties": {
    "iso:country":"ES",
    "sg:address":"Calle de Cisne, 9",
    "sg:city":"Granada",
    "sg:orig_category":"Pescader\u00cdas (al Por Menor)",
    "sg:phone":"+34 958 20 27 31",
    "sg:postcode":"18014",
    "sg:province":"Granada",
    "wof:name":"Moron Martinez Carmen",
    "wof:placetype":"venue"
},
  "geometry": {"coordinates":[-3.6103191376,37.1856384277],"type":"Point"}
}