{
  "type": "Feature",
  "properties": {
    "iso:country":"ES",
    "sg:address":"Plaz Mayor, 11",
    "sg:city":"Valladolid",
    "sg:orig_category":"Fotograf\u00cda Y Cine: Aparatos, Pel\u00cdculas Y Accesorios (al Por Menor)",
    "sg:phone":"+34 983 35 83 43",
    "sg:postcode":"47001",
    "sg:province":"Valladolid",
    "wof:name":"Vara Hernanz Ana Maria",
    "wof:placetype":"venue"
},
  "geometry": {"coordinates":[-4.7283830643,41.6515312195],"type":"Point"}
}