{
  "type": "Feature",
  "properties": {
    "iso:country":"ES",
    "sg:address":"Carrer de Cristofor Colom, 21",
    "sg:city":"S. Boi Llobregat",
    "sg:orig_category":"Inform\u00c1tica: Material Y Suministros",
    "sg:phone":"+34 936 30 86 16",
    "sg:postcode":"08830",
    "sg:province":"Barcelona",
    "wof:name":"Rodriguez Pulgarin Jose",
    "wof:placetype":"venue"
},
  "geometry": {"coordinates":[2.0447490215,41.3357429504],"type":"Point"}
}