{
  "type": "Feature",
  "properties": {
    "iso:country":"ES",
    "sg:address":"Calle de Padre Flores, 1",
    "sg:city":"Alcala Henares",
    "sg:orig_category":"Laboratorios Farmac\u00c9uticos",
    "sg:phone":"+34 918 88 56 80",
    "sg:postcode":"28805",
    "sg:province":"Madrid",
    "wof:name":"Compa\u00f1ia Farmaceutica Madrile\u00f1a S. A.",
    "wof:placetype":"venue"
},
  "geometry": {"coordinates":[-3.3588249683,40.490070343],"type":"Point"}
}