{
  "type": "Feature",
  "properties": {
    "iso:country":"ES",
    "sg:address":"Avda Pumarin De, 18",
    "sg:city":"Oviedo",
    "sg:orig_category":"Venta, Colocaci\u00d3n, Reparaci\u00d3n De Radiadores Para Veh\u00cdculos",
    "sg:phone":"+34 985 28 18 03",
    "sg:postcode":"33001",
    "sg:province":"Asturias",
    "wof:name":"Berrocal Santervas Jose Luis",
    "wof:placetype":"venue"
},
  "geometry": {"coordinates":[-5.8445191383,43.3678817749],"type":"Point"}
}