{
  "type": "Feature",
  "properties": {
    "addr:full":"Avda Puerto, 85 Valencia Valencia 46021",
    "addr:housenumber":"85",
    "addr:postcode":"46021",
    "addr:street":"Avda Puerto",
    "iso:country":"ES",
    "sg:address":"Avda Puerto, 85",
    "sg:city":"Valencia",
    "sg:orig_category":"Cajas De Ahorro",
    "sg:phone":"+34 963 61 76 11",
    "sg:postcode":"46021",
    "sg:province":"Valencia",
    "wof:name":"Caja De Ahorros De Murcia",
    "wof:placetype":"venue"
},
  "geometry": {"coordinates":[-0.3769130111,39.4687919617],"type":"Point"}
}