{
  "type": "Feature",
  "properties": {
    "addr:full":"Rua Benito Corbal, 14 Pontevedra Pontevedra 36001",
    "addr:housenumber":"14",
    "addr:postcode":"36001",
    "addr:street":"Rua Benito Corbal",
    "iso:country":"ES",
    "sg:address":"Rua Benito Corbal, 14",
    "sg:city":"Pontevedra",
    "sg:orig_category":"Peluqueros: De Se\u00d1oras",
    "sg:phone":"+34 986 84 77 39",
    "sg:postcode":"36001",
    "sg:province":"Pontevedra",
    "wof:name":"Luchy Peluquerias Cb",
    "wof:placetype":"venue"
},
  "geometry": {"coordinates":[-8.6420192719,42.4304275513],"type":"Point"}
}