{
  "type": "Feature",
  "properties": {
    "iso:country":"ES",
    "sg:address":"Falces, S/n",
    "sg:city":"Orrios",
    "sg:orig_category":"Forjas Y Altos Hornos",
    "sg:phone":"+34 978 77 01 68",
    "sg:postcode":"44161",
    "sg:province":"Teruel",
    "wof:name":"Talleres Ramirez Hernandez S.l.",
    "wof:placetype":"venue"
},
  "geometry": {"coordinates":[-0.9878849983,40.5880241394],"type":"Point"}
}