{
  "type": "Feature",
  "properties": {
    "iso:country":"ES",
    "sg:address":"Calle de Roll Del Colomer, S/n",
    "sg:city":"Rafelbunyol",
    "sg:orig_category":"Cables Y Hilos El\u00c9ctricos (fabricaci\u00d3n, Al Por Mayor)",
    "sg:phone":"+34 961 41 14 56",
    "sg:postcode":"46138",
    "sg:province":"Valencia",
    "wof:name":"Jose Casa\u00f1 Colomar S. A.",
    "wof:placetype":"venue"
},
  "geometry": {"coordinates":[-0.3314439952,39.5867614746],"type":"Point"}
}