{
  "type": "Feature",
  "properties": {
    "addr:full":"Tramuntana, 13 Viladamat Girona 17137",
    "addr:housenumber":"13",
    "addr:postcode":"17137",
    "addr:street":"Tramuntana",
    "iso:country":"ES",
    "sg:address":"Tramuntana, 13",
    "sg:city":"Viladamat",
    "sg:orig_category":"Dise\u00d1o Industrial",
    "sg:phone":"+34 972 78 81 17",
    "sg:postcode":"17137",
    "sg:province":"Girona",
    "wof:name":"Garcia Tarifa Miguel Angel",
    "wof:placetype":"venue"
},
  "geometry": {"coordinates":[3.0778961182,42.1339874268],"type":"Point"}
}