{
  "type": "Feature",
  "properties": {
    "iso:country":"ES",
    "sg:address":"Ctra Almeria, 5",
    "sg:city":"Viator",
    "sg:orig_category":"Promotores Constructores",
    "sg:phone":"+34 950 30 46 28",
    "sg:postcode":"04240",
    "sg:province":"Almer\u00eda",
    "wof:name":"Residencial Lajuaida C.b.",
    "wof:placetype":"venue"
},
  "geometry": {"coordinates":[-2.4270989895,36.8871383667],"type":"Point"}
}