{
  "type": "Feature",
  "properties": {
    "iso:country":"ES",
    "sg:address":"Ctra Andalucia (de), Km. 0043,5",
    "sg:city":"Aranjuez",
    "sg:orig_category":"Veh\u00cdculos De Ocasi\u00d3n",
    "sg:phone":"+34 918 91 23 31",
    "sg:postcode":"28300",
    "sg:province":"Madrid",
    "wof:name":"Galmasa S. A.",
    "wof:placetype":"venue"
},
  "geometry": {"coordinates":[-3.6052339077,40.0332527161],"type":"Point"}
}