{
  "type": "Feature",
  "properties": {
    "iso:country":"ES",
    "sg:address":"Plaz Rio Albentosa, 2",
    "sg:city":"Castellon",
    "sg:orig_category":"Electricidad: Instaladores",
    "sg:phone":"+34 964 23 40 21",
    "sg:postcode":"12006",
    "sg:province":"Castell\u00f3n",
    "wof:name":"Global Satel-lit Comunicacions S.l.",
    "wof:placetype":"venue"
},
  "geometry": {"coordinates":[-0.1073935032,39.9965820312],"type":"Point"}
}