{
  "type": "Feature",
  "properties": {
    "iso:country":"ES",
    "sg:address":"Calle de Marques De Mendigorria, 14",
    "sg:city":"Toledo",
    "sg:orig_category":"Abogados",
    "sg:phone":"+34 925 25 48 18",
    "sg:postcode":"45003",
    "sg:province":"Toledo",
    "wof:name":"Moraleda Nieto Juan Carlos",
    "wof:placetype":"venue"
},
  "geometry": {"coordinates":[-4.0222988129,39.8671836853],"type":"Point"}
}