{
  "type": "Feature",
  "properties": {
    "addr:full":"Luga Bastidas (los), S/n Mero\u00d1os Murcia 30700",
    "addr:postcode":"30700",
    "addr:street":"Los S / N",
    "iso:country":"ES",
    "sg:address":"Luga Bastidas (los), S/n",
    "sg:city":"Mero\u00d1os",
    "sg:classifiers":[
        {
            "category":"Food & Beverages",
            "subcategory":"Candy",
            "type":"Retail Goods"
        }
    ],
    "sg:phone":"+34 968 57 96 90",
    "sg:postcode":"30700",
    "sg:province":"Murcia",
    "sg:tags":[
        "confiter\u00cdas",
        "y",
        "de",
        "fabricaci\u00d3n",
        "chocolate"
    ],
    "wof:name":"Caramelos Cerdan S.l.",
    "wof:placetype":"venue"
},
  "geometry": {"coordinates":[-0.9535620213,37.7442855835],"type":"Point"}
}