{
  "type": "Feature",
  "properties": {
    "addr:full":"C/ Cami (el), 74 Alcoi Alicante 03801",
    "addr:postcode":"03801",
    "addr:street":"C /;El",
    "iso:country":"ES",
    "sg:address":"C/ Cami (el), 74",
    "sg:city":"Alcoi",
    "sg:orig_category":"\u00d3ptica: Instrumentos (fabricaci\u00d3n)",
    "sg:phone":"+34 965 54 05 75",
    "sg:postcode":"03801",
    "sg:province":"Alicante",
    "wof:name":"Candela Reig Maria Del Carmen",
    "wof:placetype":"venue"
},
  "geometry": {"coordinates":[-0.4755739868,38.6908683777],"type":"Point"}
}