{
  "type": "Feature",
  "properties": {
    "iso:country":"ES",
    "sg:address":"Calle de Jardines, 1",
    "sg:city":"Salas De Los Infantes",
    "sg:orig_category":"Cl\u00cdnicas Dentales",
    "sg:phone":"+34 947 38 21 91",
    "sg:postcode":"09600",
    "sg:province":"Burgos",
    "wof:name":"Hoyuelos Bartolome Concepcion",
    "wof:placetype":"venue"
},
  "geometry": {"coordinates":[-3.2864089012,42.0221328735],"type":"Point"}
}