{
  "type": "Feature",
  "properties": {
    "iso:country":"ES",
    "sg:address":"Lazarraga Kalea, 1",
    "sg:city":"O\u00f1ati",
    "sg:orig_category":"Cristaler\u00cdas",
    "sg:phone":"+34 943 78 24 06",
    "sg:postcode":"20560",
    "sg:province":"Guip\u00f9zcoa",
    "wof:name":"Cristaleria Elkoro, C.b.",
    "wof:placetype":"venue"
},
  "geometry": {"coordinates":[-2.409512043,43.0315818787],"type":"Point"}
}