{
  "type": "Feature",
  "properties": {
    "addr:full":"Vander Hofstadt, 2 S. Juan Alicante Alicante 03550",
    "addr:housenumber":"2",
    "addr:postcode":"03550",
    "addr:street":"Hofstadt;S. Juan",
    "iso:country":"ES",
    "sg:address":"Vander Hofstadt, 2",
    "sg:city":"S. Juan Alicante",
    "sg:orig_category":"Asesor\u00cda Sobre Comunicaci\u00d3n De Empresas",
    "sg:phone":"+34 965 65 93 79",
    "sg:postcode":"03550",
    "sg:province":"Alicante",
    "wof:name":"Institud Mediterrani De La Cal S.l",
    "wof:placetype":"venue"
},
  "geometry": {"coordinates":[-0.4289290011,38.400390625],"type":"Point"}
}