{
  "type": "Feature",
  "properties": {
    "addr:full":"Calle de Cervantes, 10 Linares Ja\u00e9n 23700",
    "addr:housenumber":"10",
    "addr:postcode":"23700",
    "addr:street":"Calle De Cervantes;Jae\u0301N",
    "iso:country":"ES",
    "sg:address":"Calle de Cervantes, 10",
    "sg:city":"Linares",
    "sg:orig_category":"Abogados",
    "sg:phone":"+34 953 60 70 12",
    "sg:postcode":"23700",
    "sg:province":"Ja\u00e9n",
    "wof:name":"Salas Molina Jose Ramon",
    "wof:placetype":"venue"
},
  "geometry": {"coordinates":[-3.6323974133,38.0963554382],"type":"Point"}
}