{
  "type": "Feature",
  "properties": {
    "iso:country":"ES",
    "sg:address":"Pase Pintor Martinez Vazquez, 16",
    "sg:city":"Arenas San Pedro",
    "sg:orig_category":"Mec\u00c1nico Del Autom\u00d3vil",
    "sg:phone":"+34 920 37 05 70",
    "sg:postcode":"05400",
    "sg:province":"\u00c1vila",
    "wof:name":"R. Fraile,s.l.",
    "wof:placetype":"venue"
},
  "geometry": {"coordinates":[-5.0851020813,40.211479187],"type":"Point"}
}