{
  "type": "Feature",
  "properties": {
    "iso:country":"ES",
    "sg:address":"Calle de Francisco Aritio, 68",
    "sg:city":"Guadalajara",
    "sg:orig_category":"Bares, Piano",
    "sg:phone":"+34 949 21 54 74",
    "sg:postcode":"19004",
    "sg:province":"Guadalajara",
    "wof:name":"Comunidad De Bienes Bar Restaurante Las Galeras",
    "wof:placetype":"venue"
},
  "geometry": {"coordinates":[-3.1866540909,40.6388816833],"type":"Point"}
}