{
  "type": "Feature",
  "properties": {
    "iso:country":"ES",
    "sg:address":"Calle de Inglaterra, 9",
    "sg:city":"San Fernando",
    "sg:orig_category":"Arquitectos",
    "sg:phone":"+34 922 37 38 18",
    "sg:postcode":"38400",
    "sg:province":"Santa Cruz De Tenerife",
    "wof:name":"Neira Rios Carlos",
    "wof:placetype":"venue"
},
  "geometry": {"coordinates":[-16.5459346771,28.4096279144],"type":"Point"}
}