{
  "type": "Feature",
  "properties": {
    "addr:full":"Plaz Constitucion (de La), 11 Socuellamos Ciudad Real 13630",
    "addr:postcode":"13630",
    "iso:country":"ES",
    "sg:address":"Plaz Constitucion (de La), 11",
    "sg:city":"Socuellamos",
    "sg:orig_category":"Fabricaci\u00d3n, Venta De Productos Base Farmac\u00c9uticos",
    "sg:phone":"+34 926 53 03 13",
    "sg:postcode":"13630",
    "sg:province":"Ciudad Real",
    "wof:name":"Barba Escudero Isabel",
    "wof:placetype":"venue"
},
  "geometry": {"coordinates":[-2.7948589325,39.2849845886],"type":"Point"}
}