{
  "type": "Feature",
  "properties": {
    "addr:full":"Avda Leopoldo Alas, 3 Aviles Asturias 33402",
    "addr:housenumber":"3",
    "addr:postcode":"33402",
    "addr:street":"Avda Leopoldo Alas",
    "iso:country":"ES",
    "sg:address":"Avda Leopoldo Alas, 3",
    "sg:city":"Aviles",
    "sg:orig_category":"Guarder\u00cdas",
    "sg:phone":"+34 985 51 22 65",
    "sg:postcode":"33402",
    "sg:province":"Asturias",
    "wof:name":"Ayuntamiento De Aviles",
    "wof:placetype":"venue"
},
  "geometry": {"coordinates":[-5.9256820679,43.5475578308],"type":"Point"}
}