{
  "type": "Feature",
  "properties": {
    "addr:full":"Poligono Industrial, S/n Guadix Granada 18500",
    "addr:postcode":"18500",
    "addr:street":"Industrial S / N",
    "iso:country":"ES",
    "sg:address":"Poligono Industrial, S/n",
    "sg:city":"Guadix",
    "sg:orig_category":"Asesor\u00cda Sobre Comunicaci\u00d3n De Empresas",
    "sg:phone":"+34 958 66 10 92",
    "sg:postcode":"18500",
    "sg:province":"Granada",
    "wof:name":"Proyectos Asesoria Y Servicios S.a.",
    "wof:placetype":"venue"
},
  "geometry": {"coordinates":[-3.1343688965,37.303894043],"type":"Point"}
}