{
  "type": "Feature",
  "properties": {
    "iso:country":"ES",
    "sg:address":"Calle de Almibar (del), 100",
    "sg:city":"Aranjuez",
    "sg:orig_category":"Tapiceros Y Tapiceros",
    "sg:phone":"+34 918 91 34 82",
    "sg:postcode":"28300",
    "sg:province":"Madrid",
    "wof:name":"Puerta Varon Miguel Angel",
    "wof:placetype":"venue"
},
  "geometry": {"coordinates":[-3.6030306816,40.0309028625],"type":"Point"}
}