{
  "type": "Feature",
  "properties": {
    "iso:country":"ES",
    "sg:address":"Calle de Matias Perello, 50",
    "sg:city":"Valencia",
    "sg:orig_category":"Bisuter\u00cda, Joyer\u00cda, Relojer\u00cda (al Por Menor)",
    "sg:phone":"+34 963 34 11 17",
    "sg:postcode":"46005",
    "sg:province":"Valencia",
    "wof:name":"Garcia Pilan Alfonso",
    "wof:placetype":"venue"
},
  "geometry": {"coordinates":[-0.365624994,39.4622421265],"type":"Point"}
}