{
  "type": "Feature",
  "properties": {
    "iso:country":"ES",
    "sg:address":"Calle de Padre Manjon, 54",
    "sg:city":"Valladolid",
    "sg:orig_category":"Televisi\u00d3n, V\u00cddeo: Aparatos Y Accesorios (venta)",
    "sg:phone":"+34 983 22 42 31",
    "sg:postcode":"47013",
    "sg:province":"Valladolid",
    "wof:name":"Cortijo Saenz Juan Jesus",
    "wof:placetype":"venue"
},
  "geometry": {"coordinates":[-4.7197117805,41.6385726929],"type":"Point"}
}