{
  "type": "Feature",
  "properties": {
    "addr:full":"Calle de Manuel Llaneza, 25 Langreo Asturias 33900",
    "addr:housenumber":"25",
    "addr:postcode":"33900",
    "addr:street":"Calle De Manuel Llaneza",
    "iso:country":"ES",
    "sg:address":"Calle de Manuel Llaneza, 25",
    "sg:city":"Langreo",
    "sg:orig_category":"Droguer\u00cdas (al Por Menor)",
    "sg:phone":"+34 985 69 61 06",
    "sg:postcode":"33900",
    "sg:province":"Asturias",
    "wof:name":"Drofel S.l.",
    "wof:placetype":"venue"
},
  "geometry": {"coordinates":[-5.67796278,43.292263031],"type":"Point"}
}