{
  "type": "Feature",
  "properties": {
    "addr:full":"Calle de Ruiz De Salazar, 16 Le\u00f3n Le\u00f3n 24002",
    "addr:housenumber":"16",
    "addr:postcode":"24002",
    "addr:street":"Calle De Ruiz De Salazar;Leo\u0301N",
    "iso:country":"ES",
    "sg:address":"Calle de Ruiz De Salazar, 16",
    "sg:city":"Le\u00f3n",
    "sg:orig_category":"Librer\u00cdas",
    "sg:phone":"+34 987 87 62 22",
    "sg:postcode":"24002",
    "sg:province":"Le\u00f3n",
    "sg:website":"www.latrastiendalibros.com",
    "wof:name":"Nadal Rego Marta",
    "wof:placetype":"venue"
},
  "geometry": {"coordinates":[-5.5709252357,42.5991706848],"type":"Point"}
}