{
  "type": "Feature",
  "properties": {
    "addr:full":"Calle de Roncesvalles, 19 Andosilla Navarra 31261",
    "addr:housenumber":"19",
    "addr:postcode":"31261",
    "addr:street":"Calle De Roncesvalles",
    "iso:country":"ES",
    "sg:address":"Calle de Roncesvalles, 19",
    "sg:city":"Andosilla",
    "sg:orig_category":"Empresas De Carpinter\u00cda De Madera",
    "sg:phone":"+34 948 67 41 15",
    "sg:postcode":"31261",
    "sg:province":"Navarra",
    "wof:name":"Carpinteria Arrontes S.l.",
    "wof:placetype":"venue"
},
  "geometry": {"coordinates":[-1.9448180199,42.3778572083],"type":"Point"}
}