{
  "type": "Feature",
  "properties": {
    "iso:country":"ES",
    "sg:address":"Calle de Sao Paulo, 53",
    "sg:city":"Palmas De Gran Canaria",
    "sg:classifiers":[
        {
            "category":"Communications",
            "type":"Services"
        }
    ],
    "sg:phone":"+34 928 47 13 29",
    "sg:postcode":"35008",
    "sg:province":"Las Palmas",
    "sg:tags":[
        "televisiones",
        "y",
        "radio"
    ],
    "wof:name":"Ciberinterbit S.l.",
    "wof:placetype":"venue"
},
  "geometry": {"coordinates":[-15.419380188,28.1532001495],"type":"Point"}
}