{
  "type": "Feature",
  "properties": {
    "iso:country":"ES",
    "sg:address":"Carrer de Ramon Turro, 68",
    "sg:city":"Malgrat Mar",
    "sg:orig_category":"Agentes Generales De Seguros",
    "sg:phone":"+34 937 61 29 53",
    "sg:postcode":"08380",
    "sg:province":"Barcelona",
    "wof:name":"Mapfre Servicios De Informatica",
    "wof:placetype":"venue"
},
  "geometry": {"coordinates":[2.7395188808,41.643535614],"type":"Point"}
}