{
  "type": "Feature",
  "properties": {
    "addr:full":"Calle de Alonso Castrillo, 1 Madrid Madrid 28020",
    "addr:housenumber":"1",
    "addr:postcode":"28020",
    "addr:street":"Calle De Alonso Castrillo",
    "iso:country":"ES",
    "sg:address":"Calle de Alonso Castrillo, 1",
    "sg:city":"Madrid",
    "sg:orig_category":"Radiocomunicaciones, Telefon\u00cda M\u00d3vil, Radiomensajer\u00cda: Servicios, Comercializaci\u00d3n",
    "sg:phone":"+34 915 79 32 97",
    "sg:postcode":"28020",
    "sg:province":"Madrid",
    "wof:name":"Rodmog Multiservicios S.l.",
    "wof:placetype":"venue"
},
  "geometry": {"coordinates":[-3.6994297504,40.4593811035],"type":"Point"}
}