{
  "type": "Feature",
  "properties": {
    "iso:country":"ES",
    "sg:address":"Avda Jerez, 2",
    "sg:city":"Sevilla",
    "sg:orig_category":"Restaurantes",
    "sg:phone":"+34 954 69 06 60",
    "sg:postcode":"41012",
    "sg:province":"Sevilla",
    "wof:name":"R.v.a. Catering S.l.",
    "wof:placetype":"venue"
},
  "geometry": {"coordinates":[-5.9799289703,37.3555526733],"type":"Point"}
}