{
  "type": "Feature",
  "properties": {
    "addr:full":"Pla\u00c7 Mercat, S/n Almenar Lleida 25126",
    "addr:housenumber":"s / n",
    "addr:postcode":"25126",
    "iso:country":"ES",
    "sg:address":"Pla\u00c7 Mercat, S/n",
    "sg:city":"Almenar",
    "sg:orig_category":"Electrodom\u00c9sticos (al Por Menor)",
    "sg:phone":"+34 973 77 00 57",
    "sg:postcode":"25126",
    "sg:province":"Lleida",
    "wof:name":"Puig Lafita Jose",
    "wof:placetype":"venue"
},
  "geometry": {"coordinates":[0.5682600141,41.7968521118],"type":"Point"}
}