{
  "type": "Feature",
  "properties": {
    "addr:full":"Calle de Rivero Del, 10 Aviles Asturias 33402",
    "addr:housenumber":"10",
    "addr:postcode":"33402",
    "addr:street":"Calle De Rivero Del",
    "iso:country":"ES",
    "sg:address":"Calle de Rivero Del, 10",
    "sg:city":"Aviles",
    "sg:orig_category":"Farmacias",
    "sg:phone":"+34 985 54 01 10",
    "sg:postcode":"33402",
    "sg:province":"Asturias",
    "wof:name":"Laviana Lada Marcos Aurelio",
    "wof:placetype":"venue"
},
  "geometry": {"coordinates":[-5.9214258194,43.5548858643],"type":"Point"}
}