{
  "type": "Feature",
  "properties": {
    "iso:country":"ES",
    "sg:address":"Calle de Ubi\u00d1as Las, 2",
    "sg:city":"Pola De Lena",
    "sg:classifiers":[
        {
            "category":"Personal",
            "subcategory":"Barber",
            "type":"Services"
        }
    ],
    "sg:phone":"+34 985 49 23 52",
    "sg:postcode":"33630",
    "sg:province":"Asturias",
    "sg:tags":[
        "caballeros",
        "de",
        "peluqueros"
    ],
    "wof:name":"Prieto Lopez Jose",
    "wof:placetype":"venue"
},
  "geometry": {"coordinates":[-5.8283619881,43.1649513245],"type":"Point"}
}