{
  "type": "Feature",
  "properties": {
    "addr:full":"Calle de Nobel, 5 Mairena Aljarafe Sevilla 41927",
    "addr:housenumber":"5",
    "addr:postcode":"41927",
    "addr:street":"Calle De Nobel",
    "iso:country":"ES",
    "sg:address":"Calle de Nobel, 5",
    "sg:city":"Mairena Aljarafe",
    "sg:orig_category":"Electrodom\u00c9sticos (fabricaci\u00d3n, Al Por Mayor)",
    "sg:phone":"+34 955 98 27 00",
    "sg:postcode":"41927",
    "sg:province":"Sevilla",
    "sg:website":"www.frigicoll.es",
    "wof:name":"Frigicoll S.a.",
    "wof:placetype":"venue"
},
  "geometry": {"coordinates":[-6.0517511368,37.3579177856],"type":"Point"}
}