{
  "type": "Feature",
  "properties": {
    "addr:full":"Avda Independencia, 4 Illueca Zaragoza 50250",
    "addr:housenumber":"4",
    "addr:postcode":"50250",
    "addr:street":"Avda Independencia",
    "iso:country":"ES",
    "sg:address":"Avda Independencia, 4",
    "sg:city":"Illueca",
    "sg:orig_category":"Sociedades, Compa\u00d1\u00cdas Aseguradoras",
    "sg:phone":"+34 976 82 25 32",
    "sg:postcode":"50250",
    "sg:province":"Zaragoza",
    "wof:name":"Mateo Gascon Francisco",
    "wof:placetype":"venue"
},
  "geometry": {"coordinates":[-1.6245789528,41.537109375],"type":"Point"}
}