{
  "type": "Feature",
  "properties": {
    "iso:country":"ES",
    "sg:address":"Calle de Santa Teresa, 60",
    "sg:city":"Villarrin De Campos",
    "sg:orig_category":"Ense\u00d1anza, Formaci\u00d3n Profesional: Aprendizaje",
    "sg:phone":"+34 980 58 00 37",
    "sg:postcode":"49137",
    "sg:province":"Zamora",
    "wof:name":"Gerencia De Atencion Primaria De Zamora",
    "wof:placetype":"venue"
},
  "geometry": {"coordinates":[-5.6356368065,41.794670105],"type":"Point"}
}