{
  "type": "Feature",
  "properties": {
    "addr:full":"Carr Sant Pere, S/n Almacelles Lleida 25100",
    "addr:housenumber":"s / n",
    "addr:postcode":"25100",
    "addr:street":"Carr Sant Pere",
    "iso:country":"ES",
    "sg:address":"Carr Sant Pere, S/n",
    "sg:city":"Almacelles",
    "sg:orig_category":"Cooperativas Agr\u00cdcolas",
    "sg:phone":"+34 973 74 00 71",
    "sg:postcode":"25100",
    "sg:province":"Lleida",
    "wof:name":"Cooperativa De Fruticultores De Almacellas Y Comarca",
    "wof:placetype":"venue"
},
  "geometry": {"coordinates":[0.4362100065,41.7334213257],"type":"Point"}
}