{
  "type": "Feature",
  "properties": {
    "iso:country":"ES",
    "sg:address":"Rbla Rambla Nova, 16",
    "sg:city":"Tarragona",
    "sg:orig_category":"Desinfecci\u00d3n, Desinsectaci\u00d3n, Desratizaci\u00d3n",
    "sg:phone":"+34 977 23 45 29",
    "sg:postcode":"43004",
    "sg:province":"Tarragona",
    "wof:name":"Sendra Vellve Josep Joaquim",
    "wof:placetype":"venue"
},
  "geometry": {"coordinates":[1.2541049719,41.1169281006],"type":"Point"}
}