{
  "type": "Feature",
  "properties": {
    "iso:country":"ES",
    "sg:address":"Calle de Rodrigo Vivas Miras, 55",
    "sg:city":"Almeria",
    "sg:orig_category":"Molduras, Junquillos, Listones Y Molduras Perforadas",
    "sg:phone":"+34 950 25 88 30",
    "sg:postcode":"04007",
    "sg:province":"Almer\u00eda",
    "wof:name":"Hermanos Berenguer Padilla S.l",
    "wof:placetype":"venue"
},
  "geometry": {"coordinates":[-2.4468688965,36.8265838623],"type":"Point"}
}