{
  "type": "Feature",
  "properties": {
    "iso:country":"ES",
    "sg:address":"C/ Ausias March, 8",
    "sg:city":"Moncofa",
    "sg:orig_category":"Bares, Piano",
    "sg:phone":"+34 964 58 05 06",
    "sg:postcode":"12593",
    "sg:province":"Castell\u00f3n",
    "wof:name":"Guart Silvestre Ricardo",
    "wof:placetype":"venue"
},
  "geometry": {"coordinates":[-0.1510975063,39.8076934814],"type":"Point"}
}