{
  "type": "Feature",
  "properties": {
    "iso:country":"ES",
    "sg:address":"Rua Balsa, 28",
    "sg:city":"Pontes Garcia Rodriguez",
    "sg:orig_category":"Florister\u00cdas",
    "sg:phone":"+34 981 45 01 04",
    "sg:postcode":"15320",
    "sg:province":"A Coru\u00f1a",
    "wof:name":"Servicios San Roqui\u00f1o S.l.",
    "wof:placetype":"venue"
},
  "geometry": {"coordinates":[-7.8519802094,43.4437828064],"type":"Point"}
}