{
  "type": "Feature",
  "properties": {
    "addr:full":"Rua Juan Montes, 18 Monforte De Lemos Lugo 27400",
    "addr:housenumber":"18",
    "addr:postcode":"27400",
    "addr:street":"Rua Juan Montes",
    "iso:country":"ES",
    "sg:address":"Rua Juan Montes, 18",
    "sg:city":"Monforte De Lemos",
    "sg:orig_category":"Agencias Y Agentes Comerciales, Representantes",
    "sg:phone":"+34 982 40 43 52",
    "sg:postcode":"27400",
    "sg:province":"Lugo",
    "wof:name":"Sanchez Valdes Jose Luis",
    "wof:placetype":"venue"
},
  "geometry": {"coordinates":[-7.5029478073,42.5354995728],"type":"Point"}
}