{
  "type": "Feature",
  "properties": {
    "addr:full":"Calle de Camino Estacion, 20 Villarreal De Huerva Zaragoza 50490",
    "addr:housenumber":"20",
    "addr:postcode":"50490",
    "addr:street":"Calle De Camino Estacion",
    "iso:country":"ES",
    "sg:address":"Calle de Camino Estacion, 20",
    "sg:city":"Villarreal De Huerva",
    "sg:orig_category":"Ingenier\u00cda, Centros De Estudios (diversos)",
    "sg:phone":"+34 976 80 70 62",
    "sg:postcode":"50490",
    "sg:province":"Zaragoza",
    "sg:website":"www.idom.es",
    "wof:name":"Idom Zaragoza S.a.",
    "wof:placetype":"venue"
},
  "geometry": {"coordinates":[-1.2872816324,41.1909294128],"type":"Point"}
}