{
  "type": "Feature",
  "properties": {
    "addr:full":"Calle de Fermin Caballero, 6 Madrid Madrid 28034",
    "addr:housenumber":"6",
    "addr:postcode":"28034",
    "addr:street":"Calle De Fermin Caballero",
    "iso:country":"ES",
    "sg:address":"Calle de Fermin Caballero, 6",
    "sg:city":"Madrid",
    "sg:orig_category":"Florister\u00cdas",
    "sg:phone":"+34 917 30 86 09",
    "sg:postcode":"28034",
    "sg:province":"Madrid",
    "wof:name":"Cano Rubio Manuel Antonio",
    "wof:placetype":"venue"
},
  "geometry": {"coordinates":[-3.6991291046,40.4873008728],"type":"Point"}
}