{
  "type": "Feature",
  "properties": {
    "addr:full":"Calle de Santo Domingo, 1 Jerez De La Frontera C\u00e1diz 11402",
    "addr:housenumber":"1",
    "addr:postcode":"11402",
    "addr:street":"Calle De Santo Domingo",
    "iso:country":"ES",
    "sg:address":"Calle de Santo Domingo, 1",
    "sg:city":"Jerez De La Frontera",
    "sg:orig_category":"Promotores Constructores",
    "sg:phone":"+34 956 32 60 89",
    "sg:postcode":"11402",
    "sg:province":"C\u00e1diz",
    "wof:name":"Rodigest S.l.",
    "wof:placetype":"venue"
},
  "geometry": {"coordinates":[-6.1356091499,36.6882019043],"type":"Point"}
}