{
  "type": "Feature",
  "properties": {
    "iso:country":"ES",
    "sg:address":"Avda Oporto, 41",
    "sg:city":"Madrid",
    "sg:orig_category":"Molduras, Junquillos, Listones Y Molduras Perforadas",
    "sg:phone":"+34 915 60 49 12",
    "sg:postcode":"28019",
    "sg:province":"Madrid",
    "wof:name":"Garcia Usum Elisabet",
    "wof:placetype":"venue"
},
  "geometry": {"coordinates":[-3.7252659798,40.3855400085],"type":"Point"}
}