{
  "type": "Feature",
  "properties": {
    "addr:full":"Barreiro(vilaza), 3 Barreiro Pontevedra 36380",
    "addr:housenumber":"3",
    "addr:postcode":"36380",
    "addr:street":"Vilaza",
    "iso:country":"ES",
    "sg:address":"Barreiro(vilaza), 3",
    "sg:city":"Barreiro",
    "sg:orig_category":"Alimentaci\u00d3n General (al Por Menor)",
    "sg:phone":"+34 986 36 07 32",
    "sg:postcode":"36380",
    "sg:province":"Pontevedra",
    "wof:name":"Ferreiro Martinez Basilisa",
    "wof:placetype":"venue"
},
  "geometry": {"coordinates":[-8.7611093521,42.1116867065],"type":"Point"}
}