{
  "type": "Feature",
  "properties": {
    "iso:country":"ES",
    "sg:address":"Calle de Carrera De Las Mercedes, 41",
    "sg:city":"Alcala Real",
    "sg:orig_category":"Electrodom\u00c9sticos (al Por Menor)",
    "sg:phone":"+34 953 58 04 97",
    "sg:postcode":"23680",
    "sg:province":"Ja\u00e9n",
    "wof:name":"Atienza Romero Antonio",
    "wof:placetype":"venue"
},
  "geometry": {"coordinates":[-3.9227724075,37.4627456665],"type":"Point"}
}