{
  "type": "Feature",
  "properties": {
    "addr:full":"Grauer E. Aunos, S/n Bossost Lleida 25550",
    "addr:housenumber":"s",
    "addr:postcode":"25550",
    "addr:street":"Grauer;/ N Bossost",
    "iso:country":"ES",
    "sg:address":"Grauer E. Aunos, S/n",
    "sg:city":"Bossost",
    "sg:orig_category":"Oficinas De Turismo, Asociaciones De Iniciativa",
    "sg:phone":"+34 973 64 72 79",
    "sg:postcode":"25550",
    "sg:province":"Lleida",
    "wof:name":"Ajuntament De Bossost",
    "wof:placetype":"venue"
},
  "geometry": {"coordinates":[0.6915392876,42.7787971497],"type":"Point"}
}