{
  "type": "Feature",
  "properties": {
    "iso:country":"ES",
    "sg:address":"Plaz Larramendi, 4",
    "sg:city":"Valle Trapaga",
    "sg:orig_category":"Confecci\u00d3n (fabricaci\u00d3n, Al Por Mayor)",
    "sg:phone":"+34 944 92 04 54",
    "sg:postcode":"48510",
    "sg:province":"Vizcaya",
    "wof:name":"Zubizarreta Alonso Maria Angeles",
    "wof:placetype":"venue"
},
  "geometry": {"coordinates":[-3.0360119343,43.3041496277],"type":"Point"}
}