{
  "type": "Feature",
  "properties": {
    "addr:full":"Calle de Navarra, 1 Arroyo De La Miel-benalmadena Costa M\u00e1laga 29631",
    "addr:housenumber":"1",
    "addr:postcode":"29631",
    "addr:street":"Calle De Navarra;Arroyo De La Miel-Benalmadena Costa Ma\u0301Laga",
    "iso:country":"ES",
    "sg:address":"Calle de Navarra, 1",
    "sg:city":"Arroyo De La Miel-benalmadena Costa",
    "sg:orig_category":"Agentes Generales De Seguros",
    "sg:phone":"+34 952 56 69 29",
    "sg:postcode":"29631",
    "sg:province":"M\u00e1laga",
    "wof:name":"Banco Vitalicio De Espa\u00d1a C A",
    "wof:placetype":"venue"
},
  "geometry": {"coordinates":[-4.5482521057,36.6017608643],"type":"Point"}
}