{
  "type": "Feature",
  "properties": {
    "iso:country":"ES",
    "sg:address":"Carrer de Antoni Gaudi, 31",
    "sg:city":"Gava",
    "sg:orig_category":"Cl\u00cdnicas Dentales",
    "sg:phone":"+34 936 38 42 98",
    "sg:postcode":"08850",
    "sg:province":"Barcelona",
    "wof:name":"Gavadent S.l.",
    "wof:placetype":"venue"
},
  "geometry": {"coordinates":[1.9996210337,41.2960395813],"type":"Point"}
}