{
  "type": "Feature",
  "properties": {
    "iso:country":"ES",
    "sg:address":"Calle de Periana, 1",
    "sg:city":"Fuengirola",
    "sg:orig_category":"Bazares, Art\u00cdculos De Limpieza Y De Cocina (al Por Menor)",
    "sg:phone":"+34 952 58 68 45",
    "sg:postcode":"29640",
    "sg:province":"M\u00e1laga",
    "wof:name":"Trujillo Pe\u00f1a Jose",
    "wof:placetype":"venue"
},
  "geometry": {"coordinates":[-4.6283798218,36.5390815735],"type":"Point"}
}