{
  "type": "Feature",
  "properties": {
    "iso:country":"ES",
    "sg:address":"Calle de General Sanjurjo, 61",
    "sg:city":"Santa Cruz De Tenerife",
    "sg:orig_category":"Tintes (fabricaci\u00d3n, Al Por Mayor)",
    "sg:phone":"+34 922 27 38 21",
    "sg:postcode":"38006",
    "sg:province":"Santa Cruz De Tenerife",
    "wof:name":"Krawietz Thomalla Francisco",
    "wof:placetype":"venue"
},
  "geometry": {"coordinates":[-16.2624225616,28.4699459076],"type":"Point"}
}