{
  "type": "Feature",
  "properties": {
    "addr:full":"Calle de Vereda De Castro, S/n Lucena C\u00f3rdoba 14900",
    "addr:housenumber":"s",
    "addr:postcode":"14900",
    "addr:street":"Calle De Vereda De Castro;/ N",
    "iso:country":"ES",
    "sg:address":"Calle de Vereda De Castro, S/n",
    "sg:city":"Lucena",
    "sg:orig_category":"Metalurgia",
    "sg:phone":"+34 957 51 31 43",
    "sg:postcode":"14900",
    "sg:province":"C\u00f3rdoba",
    "wof:name":"Parra Torralbo Juan Pedro",
    "wof:placetype":"venue"
},
  "geometry": {"coordinates":[-4.4981241226,37.404209137],"type":"Point"}
}