{
  "type": "Feature",
  "properties": {
    "addr:full":"Rbla Fiveller, 5 Mollet Valles Barcelona 08100",
    "addr:housenumber":"5",
    "addr:postcode":"08100",
    "addr:street":"Rbla Fiveller",
    "iso:country":"ES",
    "sg:address":"Rbla Fiveller, 5",
    "sg:city":"Mollet Valles",
    "sg:orig_category":"Cajas De Ahorro",
    "sg:phone":"+34 935 70 69 48",
    "sg:postcode":"08100",
    "sg:province":"Barcelona",
    "wof:name":"Caixa D'estalvis I Pensions De Barcelona",
    "wof:placetype":"venue"
},
  "geometry": {"coordinates":[2.2121949196,41.5381202698],"type":"Point"}
}