{
  "type": "Feature",
  "properties": {
    "iso:country":"ES",
    "sg:address":"Calle de Camarena, 86",
    "sg:city":"Madrid",
    "sg:orig_category":"Molduras, Junquillos, Listones Y Molduras Perforadas",
    "sg:phone":"+34 917 17 20 20",
    "sg:postcode":"28047",
    "sg:province":"Madrid",
    "wof:name":"Diaz Martin Domingo",
    "wof:placetype":"venue"
},
  "geometry": {"coordinates":[-3.757080555,40.3939208984],"type":"Point"}
}