{
  "type": "Feature",
  "properties": {
    "iso:country":"ES",
    "sg:address":"Avda Constitucion (de La), 28",
    "sg:city":"Moraleja",
    "sg:orig_category":"Doctores En Medicina",
    "sg:phone":"+34 927 51 56 39",
    "sg:postcode":"10840",
    "sg:province":"C\u00e1ceres",
    "wof:name":"Semedo Morales Jose Carlos",
    "wof:placetype":"venue"
},
  "geometry": {"coordinates":[-6.6586871147,40.0691223145],"type":"Point"}
}