{
  "type": "Feature",
  "properties": {
    "addr:full":"Calle de Ramon Bautista Claveria, 24 Langreo Asturias 33930",
    "addr:housenumber":"24",
    "addr:postcode":"33930",
    "addr:street":"Calle De Ramon Bautista Claveria",
    "iso:country":"ES",
    "sg:address":"Calle de Ramon Bautista Claveria, 24",
    "sg:city":"Langreo",
    "sg:orig_category":"Psic\u00d3logos",
    "sg:phone":"+34 985 68 08 86",
    "sg:postcode":"33930",
    "sg:province":"Asturias",
    "wof:name":"Tamargo Llana Margarita",
    "wof:placetype":"venue"
},
  "geometry": {"coordinates":[-5.6936821938,43.3083648682],"type":"Point"}
}