{
  "type": "Feature",
  "properties": {
    "addr:full":"Av Capdella, S/n Calvia Islas Baleares 07184",
    "addr:housenumber":"s",
    "addr:postcode":"07184",
    "addr:street":"Av Capdella;/ N",
    "iso:country":"ES",
    "sg:address":"Av Capdella, S/n",
    "sg:city":"Calvia",
    "sg:orig_category":"Asociaciones Y Clubs Deportivos",
    "sg:phone":"+34 971 67 03 37",
    "sg:postcode":"07184",
    "sg:province":"Islas Baleares",
    "wof:name":"Club Deportivo Calvia",
    "wof:placetype":"venue"
},
  "geometry": {"coordinates":[2.5024049282,39.5655059814],"type":"Point"}
}