{
  "type": "Feature",
  "properties": {
    "iso:country":"ES",
    "sg:address":"Carr Fusters, 6",
    "sg:city":"Godella",
    "sg:orig_category":"Estudios, Instalaci\u00d3n De Climatizaci\u00d3n",
    "sg:phone":"+34 961 52 48 66",
    "sg:postcode":"46110",
    "sg:province":"Valencia",
    "wof:name":"Termigo S.l.",
    "wof:placetype":"venue"
},
  "geometry": {"coordinates":[-0.4154840112,39.5255889893],"type":"Point"}
}