{
  "type": "Feature",
  "properties": {
    "iso:country":"ES",
    "sg:address":"Calle de Iturribide, 6",
    "sg:city":"Andra Mari",
    "sg:orig_category":"Mec\u00c1nica Y Herramientas De Precisi\u00d3n",
    "sg:phone":"+34 944 30 75 06",
    "sg:postcode":"48993",
    "sg:province":"Vizcaya",
    "sg:website":"www.topcon.es",
    "wof:name":"Topcon Espa\u00d1a S. A.",
    "wof:placetype":"venue"
},
  "geometry": {"coordinates":[-2.7541499138,43.2982711792],"type":"Point"}
}