{
  "type": "Feature",
  "properties": {
    "iso:country":"ES",
    "sg:address":"Calle de General Vara De Rey, 17",
    "sg:city":"Logro\u00f1o",
    "sg:orig_category":"Florister\u00cdas",
    "sg:phone":"+34 941 24 57 11",
    "sg:postcode":"26002",
    "sg:province":"La Rioja",
    "wof:name":"Medrano Hernandez Jose Maria",
    "wof:placetype":"venue"
},
  "geometry": {"coordinates":[-2.4466691017,42.4585189819],"type":"Point"}
}