{
  "type": "Feature",
  "properties": {
    "iso:country":"ES",
    "sg:address":"Poli Rubira Sola, S/n",
    "sg:city":"Macael",
    "sg:orig_category":"Plomeros",
    "sg:phone":"+34 950 44 56 03",
    "sg:postcode":"04867",
    "sg:province":"Almer\u00eda",
    "wof:name":"Fontaneria Nuestra Se\u00f1ora Del Rosario S.l.",
    "wof:placetype":"venue"
},
  "geometry": {"coordinates":[-2.3048915863,37.3322906494],"type":"Point"}
}