{
  "type": "Feature",
  "properties": {
    "iso:country":"ES",
    "sg:address":"Rio Urederra, 8",
    "sg:city":"Iru\u00f1a",
    "sg:orig_category":"Mec\u00c1nico Del Autom\u00d3vil",
    "sg:phone":"+34 948 23 56 31",
    "sg:postcode":"31005",
    "sg:province":"Navarra",
    "wof:name":"Jimenez Celigrera Pedro Jose",
    "wof:placetype":"venue"
},
  "geometry": {"coordinates":[-1.6435650587,42.8037986755],"type":"Point"}
}