{
  "type": "Feature",
  "properties": {
    "addr:full":"Rua Lisa, 5 Verin Ourense 32600",
    "addr:housenumber":"5",
    "addr:postcode":"32600",
    "addr:street":"Rua Lisa",
    "iso:country":"ES",
    "sg:address":"Rua Lisa, 5",
    "sg:city":"Verin",
    "sg:orig_category":"Panader\u00cdas, Panader\u00cdas",
    "sg:phone":"+34 988 41 07 11",
    "sg:postcode":"32600",
    "sg:province":"Ourense",
    "wof:name":"Castro Iglesias Francisca",
    "wof:placetype":"venue"
},
  "geometry": {"coordinates":[-7.4378771782,41.9408683777],"type":"Point"}
}