{
  "type": "Feature",
  "properties": {
    "addr:full":"Calle de Jose Maria De Castro, 8 Madrid Madrid 28020",
    "addr:housenumber":"8",
    "addr:postcode":"madrid;28020",
    "addr:street":"Calle De Jose Maria De Castro",
    "iso:country":"ES",
    "sg:address":"Calle de Jose Maria De Castro, 8",
    "sg:city":"Madrid",
    "sg:orig_category":"Zapatos (al Por Menor)",
    "sg:phone":"+34 915 72 22 10",
    "sg:postcode":"28020",
    "sg:province":"Madrid",
    "wof:name":"Galindo Garcia Marcelino",
    "wof:placetype":"venue"
},
  "geometry": {"coordinates":[-3.699878931,40.4525375366],"type":"Point"}
}