{
  "type": "Feature",
  "properties": {
    "iso:country":"ES",
    "sg:address":"Calle de Palencia, 18",
    "sg:city":"Vitoria-gasteiz",
    "sg:orig_category":"Puertas Y Portales",
    "sg:phone":"+34 945 27 85 75",
    "sg:postcode":"01002",
    "sg:province":"\u00c1lava",
    "wof:name":"Luis Retuerto Gonzalez",
    "wof:placetype":"venue"
},
  "geometry": {"coordinates":[-2.6638050079,42.8502502441],"type":"Point"}
}