{
  "type": "Feature",
  "properties": {
    "iso:country":"ES",
    "sg:address":"Don Leandro Kalea, 3",
    "sg:city":"Zarautz",
    "sg:orig_category":"Promotores Constructores",
    "sg:phone":"+34 943 83 05 94",
    "sg:postcode":"20800",
    "sg:province":"Guip\u00f9zcoa",
    "wof:name":"Aguirre Elustondo Jose Miguel",
    "wof:placetype":"venue"
},
  "geometry": {"coordinates":[-2.1660590172,43.2862014771],"type":"Point"}
}