{
  "type": "Feature",
  "properties": {
    "iso:country":"ES",
    "sg:address":"Calle de Jesus Del Calvario, 29",
    "sg:city":"Cordoba",
    "sg:orig_category":"Alimentaci\u00d3n General (al Por Menor)",
    "sg:phone":"+34 957 48 41 86",
    "sg:postcode":"14001",
    "sg:province":"C\u00f3rdoba",
    "wof:name":"Ortiz Echevarria Antonio",
    "wof:placetype":"venue"
},
  "geometry": {"coordinates":[-4.7687802315,37.8892822266],"type":"Point"}
}