{
  "type": "Feature",
  "properties": {
    "addr:full":"Carr Camprodon, 72 Arbucies Girona 17401",
    "addr:housenumber":"72",
    "addr:postcode":"17401",
    "addr:street":"Carr Camprodon",
    "iso:country":"ES",
    "sg:address":"Carr Camprodon, 72",
    "sg:city":"Arbucies",
    "sg:orig_category":"M\u00c9dicos: Estomatolog\u00cda",
    "sg:phone":"+34 972 86 07 32",
    "sg:postcode":"17401",
    "sg:province":"Girona",
    "wof:name":"Alcocer Porras Ismael",
    "wof:placetype":"venue"
},
  "geometry": {"coordinates":[2.5181624889,41.8145256042],"type":"Point"}
}