{
  "type": "Feature",
  "properties": {
    "iso:country":"ES",
    "sg:address":"Trullas, S/n",
    "sg:city":"Alginet",
    "sg:orig_category":"Cooperativas Agr\u00cdcolas",
    "sg:phone":"+34 961 75 03 21",
    "sg:postcode":"46230",
    "sg:province":"Valencia",
    "wof:name":"Agricola Alginet Sociedad Cooperativa Valenciana",
    "wof:placetype":"venue"
},
  "geometry": {"coordinates":[-0.4672681987,39.2622871399],"type":"Point"}
}