{
  "type": "Feature",
  "properties": {
    "iso:country":"ES",
    "sg:address":"Carrer de Salvador Espriu, S/n",
    "sg:city":"Pla Del Remei",
    "sg:orig_category":"M\u00c9dicos: Anestesiolog\u00cda Y Reanimaci\u00d3n Quir\u00dargica",
    "sg:phone":"+34 938 48 27 57",
    "sg:postcode":"08460",
    "sg:province":"Barcelona",
    "wof:name":"Pessas Cusso Joan Pere",
    "wof:placetype":"venue"
},
  "geometry": {"coordinates":[2.4345400333,41.6977996826],"type":"Point"}
}