{
  "type": "Feature",
  "properties": {
    "addr:full":"Avda Guadalajara, 35 Madrid Madrid 28032",
    "addr:housenumber":"35",
    "addr:postcode":"madrid;28032",
    "addr:street":"Avda Guadalajara",
    "iso:country":"ES",
    "sg:address":"Avda Guadalajara, 35",
    "sg:city":"Madrid",
    "sg:orig_category":"Cerrajer\u00cda, Ferrallista",
    "sg:phone":"+34 913 24 03 59",
    "sg:postcode":"28032",
    "sg:province":"Madrid",
    "wof:name":"Amo Garcia Miguel Angel",
    "wof:placetype":"venue"
},
  "geometry": {"coordinates":[-3.6201729774,40.4194717407],"type":"Point"}
}