{
  "type": "Feature",
  "properties": {
    "addr:full":"Calle de Ba\u00d1eza (la), 16 Le\u00f3n Le\u00f3n 24007",
    "addr:housenumber":"16",
    "addr:postcode":"24007",
    "addr:street":"Calle De Ban\u0303Eza La;Leo\u0301N",
    "iso:country":"ES",
    "sg:address":"Calle de Ba\u00d1eza (la), 16",
    "sg:city":"Le\u00f3n",
    "sg:orig_category":"Panader\u00cdas, Panader\u00cdas",
    "sg:phone":"+34 987 22 34 13",
    "sg:postcode":"24007",
    "sg:province":"Le\u00f3n",
    "wof:name":"Alvarez Rodriguez Justina",
    "wof:placetype":"venue"
},
  "geometry": {"coordinates":[-5.5699391365,42.6074028015],"type":"Point"}
}