{
  "type": "Feature",
  "properties": {
    "addr:full":"Prado San Pedro, 15 Sig\u00fcenza Guadalajara 19250",
    "addr:housenumber":"15",
    "addr:postcode":"19250",
    "addr:street":"San Pedro",
    "iso:country":"ES",
    "sg:address":"Prado San Pedro, 15",
    "sg:city":"Sig\u00fcenza",
    "sg:orig_category":"Arenas, Guijarros Y Granulados",
    "sg:phone":"+34 949 39 11 85",
    "sg:postcode":"19250",
    "sg:province":"Guadalajara",
    "wof:name":"Sardina Mazario Modesto",
    "wof:placetype":"venue"
},
  "geometry": {"coordinates":[-2.6444160938,41.0686836243],"type":"Point"}
}