{
  "type": "Feature",
  "properties": {
    "iso:country":"ES",
    "sg:address":"Calle de Nuestra Se\u00d1ora De Sonsoles, 91",
    "sg:city":"Avila",
    "sg:orig_category":"M\u00c9dicos: Cirug\u00cda Urol\u00d3gica",
    "sg:phone":"+34 920 22 91 53",
    "sg:postcode":"05002",
    "sg:province":"\u00c1vila",
    "wof:name":"Aguila Malato Luis Del",
    "wof:placetype":"venue"
},
  "geometry": {"coordinates":[-4.6981859207,40.6470794678],"type":"Point"}
}