{
  "type": "Feature",
  "properties": {
    "addr:full":"Calle de Virgen De Las Nieves, 4 Malaga M\u00e1laga 29007",
    "addr:housenumber":"4",
    "addr:postcode":"29007",
    "addr:street":"Calle De Virgen De Las Nieves;Ma\u0301Laga",
    "iso:country":"ES",
    "sg:address":"Calle de Virgen De Las Nieves, 4",
    "sg:city":"Malaga",
    "sg:orig_category":"Iglesia Cat\u00d3lica",
    "sg:phone":"+34 952 30 69 43",
    "sg:postcode":"29007",
    "sg:province":"M\u00e1laga",
    "wof:name":"Obispado De Malaga",
    "wof:placetype":"venue"
},
  "geometry": {"coordinates":[-4.4441790581,36.717414856],"type":"Point"}
}