{
  "type": "Feature",
  "properties": {
    "addr:full":"Calle de Sol, 2 Algaba Sevilla 41980",
    "addr:housenumber":"2",
    "addr:postcode":"41980",
    "addr:street":"Calle De Sol",
    "iso:country":"ES",
    "sg:address":"Calle de Sol, 2",
    "sg:city":"Algaba",
    "sg:orig_category":"Art\u00cdculos Funerarios (al Por Menor)",
    "sg:phone":"+34 955 78 92 04",
    "sg:postcode":"41980",
    "sg:province":"Sevilla",
    "wof:name":"Servicios Especiales S. A.",
    "wof:placetype":"venue"
},
  "geometry": {"coordinates":[-6.0110230446,37.4637260437],"type":"Point"}
}