{
  "type": "Feature",
  "properties": {
    "addr:full":"Barrio San Roque, 1 Roa Burgos 09300",
    "addr:housenumber":"1",
    "addr:postcode":"09300",
    "addr:street":"Barrio San Roque",
    "iso:country":"ES",
    "sg:address":"Barrio San Roque, 1",
    "sg:city":"Roa",
    "sg:orig_category":"Bebidas",
    "sg:phone":"+34 947 54 00 11",
    "sg:postcode":"09300",
    "sg:province":"Burgos",
    "wof:name":"Julio Guijarro S.l.",
    "wof:placetype":"venue"
},
  "geometry": {"coordinates":[-3.9295990467,41.6983032227],"type":"Point"}
}