{
  "type": "Feature",
  "properties": {
    "iso:country":"ES",
    "sg:address":"Carrer de Verge De La Paloma, 21",
    "sg:city":"Esplugues Llobregat",
    "sg:orig_category":"M\u00c1quinas De Escribir, M\u00c1quinas De Oficina (al Por Menor, Reparaci\u00d3n)",
    "sg:phone":"+34 933 22 70 62",
    "sg:postcode":"08950",
    "sg:province":"Barcelona",
    "wof:name":"Martinez Guinot Mercedes",
    "wof:placetype":"venue"
},
  "geometry": {"coordinates":[2.0834159851,41.3671760559],"type":"Point"}
}