{
  "type": "Feature",
  "properties": {
    "iso:country":"ES",
    "sg:address":"Pl Reina, 1",
    "sg:city":"Palma",
    "sg:orig_category":"Perfumer\u00cda (al Por Menor)",
    "sg:phone":"+34 971 42 54 54",
    "sg:postcode":"07012",
    "sg:province":"Islas Baleares",
    "wof:name":"Tintin S. A.",
    "wof:placetype":"venue"
},
  "geometry": {"coordinates":[2.6469399929,39.5714836121],"type":"Point"}
}