{
  "type": "Feature",
  "properties": {
    "addr:full":"Carrer de Banys, 93 Garriga Barcelona 08530",
    "addr:housenumber":"93",
    "addr:postcode":"08530",
    "addr:street":"Carrer De Banys",
    "iso:country":"ES",
    "sg:address":"Carrer de Banys, 93",
    "sg:city":"Garriga",
    "sg:orig_category":"Peluqueros: De Se\u00d1oras",
    "sg:phone":"+34 938 71 73 80",
    "sg:postcode":"08530",
    "sg:province":"Barcelona",
    "wof:name":"Alexandre Perruquers Unisex S.c.p.",
    "wof:placetype":"venue"
},
  "geometry": {"coordinates":[2.2864117622,41.679473877],"type":"Point"}
}