{
  "type": "Feature",
  "properties": {
    "iso:country":"ES",
    "sg:address":"Rua Xeneral Gutierrez Mellado, 11",
    "sg:city":"Pontevedra",
    "sg:orig_category":"Procuradores",
    "sg:phone":"+34 986 84 46 41",
    "sg:postcode":"36001",
    "sg:province":"Pontevedra",
    "wof:name":"Santa Cecilia Escudero Ana Isabel",
    "wof:placetype":"venue"
},
  "geometry": {"coordinates":[-8.6459665298,42.4305114746],"type":"Point"}
}