{
  "type": "Feature",
  "properties": {
    "iso:country":"ES",
    "sg:address":"Calle de Vitoria, 226",
    "sg:city":"Burgos",
    "sg:orig_category":"Loter\u00cda Y T\u00d3mbola",
    "sg:phone":"+34 947 48 73 18",
    "sg:postcode":"09007",
    "sg:province":"Burgos",
    "wof:name":"Gil Tobar Victoria",
    "wof:placetype":"venue"
},
  "geometry": {"coordinates":[-3.6639280319,42.3546981812],"type":"Point"}
}