{
  "type": "Feature",
  "properties": {
    "addr:full":"Martoko Kalea, 1 Bergara Guip\u00f9zcoa 20570",
    "addr:housenumber":"1",
    "addr:postcode":"20570",
    "addr:street":"Martoko Kalea;Guipu\u0300Zcoa",
    "iso:country":"ES",
    "sg:address":"Martoko Kalea, 1",
    "sg:city":"Bergara",
    "sg:orig_category":"Cristaler\u00cdas",
    "sg:phone":"+34 943 76 54 68",
    "sg:postcode":"20570",
    "sg:province":"Guip\u00f9zcoa",
    "wof:name":"Felix Urrezola Oria",
    "wof:placetype":"venue"
},
  "geometry": {"coordinates":[-2.4153079987,43.1098709106],"type":"Point"}
}