{
  "type": "Feature",
  "properties": {
    "addr:full":"Rbla Francesc Macia, 14 Terrassa Barcelona 08226",
    "addr:housenumber":"14",
    "addr:postcode":"08226",
    "addr:street":"Rbla Francesc Macia",
    "iso:country":"ES",
    "sg:address":"Rbla Francesc Macia, 14",
    "sg:city":"Terrassa",
    "sg:orig_category":"Inmobiliaria (agencias)",
    "sg:phone":"+34 937 34 93 32",
    "sg:postcode":"08226",
    "sg:province":"Barcelona",
    "wof:name":"A.s Santa Coloma 2002 S.l",
    "wof:placetype":"venue"
},
  "geometry": {"coordinates":[2.0191836357,41.5762176514],"type":"Point"}
}