{
  "type": "Feature",
  "properties": {
    "iso:country":"ES",
    "sg:address":"Carrer de Mestre Perez Moya, 11",
    "sg:city":"Sant Vicen\u00c7 Dels Horts",
    "sg:orig_category":"Alimentaci\u00d3n General (al Por Menor)",
    "sg:phone":"+34 936 76 93 14",
    "sg:postcode":"08620",
    "sg:province":"Barcelona",
    "wof:name":"Blasco Giner Jose",
    "wof:placetype":"venue"
},
  "geometry": {"coordinates":[2.0100400448,41.3932189941],"type":"Point"}
}