{
  "type": "Feature",
  "properties": {
    "iso:country":"ES",
    "sg:address":"Calle de Leon Y Castillo, 7",
    "sg:city":"Arrecife",
    "sg:orig_category":"Cajas De Ahorro",
    "sg:phone":"+34 928 81 60 50",
    "sg:postcode":"35500",
    "sg:province":"Las Palmas",
    "sg:website":"www.cajacanarias.es",
    "wof:name":"Caja General De Ahorros De Canarias",
    "wof:placetype":"venue"
},
  "geometry": {"coordinates":[-13.5485973358,28.9589614868],"type":"Point"}
}