{
  "type": "Feature",
  "properties": {
    "iso:country":"ES",
    "sg:address":"Poli Industrial Alces, 11",
    "sg:city":"Alcazar S. Juan",
    "sg:orig_category":"Agentes, Concesionarios Y Sucursales De Veh\u00cdculos",
    "sg:phone":"+34 926 54 00 37",
    "sg:postcode":"13600",
    "sg:province":"Ciudad Real",
    "wof:name":"Auto Comercial Toledana S.a.",
    "wof:placetype":"venue"
},
  "geometry": {"coordinates":[-3.9272627831,38.9860954285],"type":"Point"}
}