{
  "type": "Feature",
  "properties": {
    "iso:country":"ES",
    "sg:address":"Calle de Maestro Barbieri, 2",
    "sg:city":"Alacant",
    "sg:orig_category":"Materias Pl\u00c1sticas: Productos De Consumo Masivo (fabricaci\u00d3n, Al Por Mayor)",
    "sg:phone":"+34 965 20 74 96",
    "sg:postcode":"03004",
    "sg:province":"Alicante",
    "wof:name":"Asociacion Provincial De Plasticos De Alicante",
    "wof:placetype":"venue"
},
  "geometry": {"coordinates":[-0.4900816977,38.3487358093],"type":"Point"}
}