{
  "type": "Feature",
  "properties": {
    "addr:full":"Avda I(p Campollano), 74 Albacete Albacete 02006",
    "addr:housenumber":"74",
    "addr:postcode":"02006",
    "addr:street":"Avda I P Campollano",
    "iso:country":"ES",
    "sg:address":"Avda I(p Campollano), 74",
    "sg:city":"Albacete",
    "sg:orig_category":"Venta, Montaje De Neum\u00c1ticos",
    "sg:phone":"+34 967 52 41 06",
    "sg:postcode":"02006",
    "sg:province":"Albacete",
    "wof:name":"Albaneuman S.l.",
    "wof:placetype":"venue"
},
  "geometry": {"coordinates":[-1.9490209818,39.013168335],"type":"Point"}
}