{
  "type": "Feature",
  "properties": {
    "iso:country":"ES",
    "sg:address":"Calle de Teniente Luengo, S/n",
    "sg:city":"Bermillo Sayago",
    "sg:orig_category":"Cerrajer\u00cda, Ferrallista",
    "sg:phone":"+34 980 61 02 28",
    "sg:postcode":"49200",
    "sg:province":"Zamora",
    "wof:name":"Bartolome Fermoselle Valeriano",
    "wof:placetype":"venue"
},
  "geometry": {"coordinates":[-6.1089668274,41.3664703369],"type":"Point"}
}