{
  "type": "Feature",
  "properties": {
    "iso:country":"ES",
    "sg:address":"Calle de Duques De Najera, 45",
    "sg:city":"Logro\u00f1o",
    "sg:orig_category":"Inform\u00c1tica: Material Y Suministros",
    "sg:phone":"+34 941 22 27 28",
    "sg:postcode":"26005",
    "sg:province":"La Rioja",
    "wof:name":"Informatica Soft Rioja S.l.u.",
    "wof:placetype":"venue"
},
  "geometry": {"coordinates":[-2.4570710659,42.4598960876],"type":"Point"}
}