{
  "type": "Feature",
  "properties": {
    "addr:full":"Carrer de Sant Joan, 74 Manresa Barcelona 08243",
    "addr:housenumber":"74",
    "addr:postcode":"08243",
    "addr:street":"Carrer De Sant Joan",
    "iso:country":"ES",
    "sg:address":"Carrer de Sant Joan, 74",
    "sg:city":"Manresa",
    "sg:orig_category":"Cooperativas Agr\u00cdcolas",
    "sg:phone":"+34 938 74 25 20",
    "sg:postcode":"08243",
    "sg:province":"Barcelona",
    "wof:name":"Corporacion Alimentaria Guissona S.a.",
    "wof:placetype":"venue"
},
  "geometry": {"coordinates":[1.8438600302,41.7327194214],"type":"Point"}
}