{
  "type": "Feature",
  "properties": {
    "iso:country":"ES",
    "sg:address":"Ptge Mercader, 15",
    "sg:city":"Barcelona",
    "sg:orig_category":"Internados & Ense\u00d1anza Privada",
    "sg:phone":"+34 934 88 03 83",
    "sg:postcode":"08008",
    "sg:province":"Barcelona",
    "wof:name":"Institucion Teresiana Asociacion Civil",
    "wof:placetype":"venue"
},
  "geometry": {"coordinates":[2.1603150368,41.3924026489],"type":"Point"}
}