{
  "type": "Feature",
  "properties": {
    "iso:country":"ES",
    "sg:address":"Calle de Rio Manzanares, 3",
    "sg:city":"Brunete",
    "sg:orig_category":"Hielo Artificial (fabricaci\u00d3n, Distribuci\u00d3n)",
    "sg:phone":"+34 918 16 45 30",
    "sg:postcode":"28690",
    "sg:province":"Madrid",
    "wof:name":"Discub S.l.",
    "wof:placetype":"venue"
},
  "geometry": {"coordinates":[-3.9943809509,40.3973808289],"type":"Point"}
}