{
  "type": "Feature",
  "properties": {
    "iso:country":"ES",
    "sg:address":"Calle de Loza, 4",
    "sg:city":"Ecija",
    "sg:orig_category":"Empresas De Carpinter\u00cda De Madera",
    "sg:phone":"+34 954 83 16 19",
    "sg:postcode":"41400",
    "sg:province":"Sevilla",
    "wof:name":"Joyfemar S.l.",
    "wof:placetype":"venue"
},
  "geometry": {"coordinates":[-5.0856351852,37.5439949036],"type":"Point"}
}