{
  "type": "Feature",
  "properties": {
    "iso:country":"ES",
    "sg:address":"Calle de Burgos, 13",
    "sg:city":"Urdu\u00e7a-ordu\u00e7a",
    "sg:orig_category":"Fotograf\u00cda Y Cine: Aparatos, Pel\u00cdculas Y Accesorios (al Por Menor)",
    "sg:phone":"+34 945 38 39 00",
    "sg:postcode":"48460",
    "sg:province":"Vizcaya",
    "wof:name":"Torres Mauleon Marta",
    "wof:placetype":"venue"
},
  "geometry": {"coordinates":[-3.0069389343,42.9948730469],"type":"Point"}
}