{
  "type": "Feature",
  "properties": {
    "addr:full":"Ctra. Jerez-cartagena, S/n Antequera M\u00e1laga 29200",
    "addr:housenumber":"s",
    "addr:postcode":"29200",
    "addr:street":"Ctra. Jerez-Cartagena;/ N;Ma\u0301Laga",
    "iso:country":"ES",
    "sg:address":"Ctra. Jerez-cartagena, S/n",
    "sg:city":"Antequera",
    "sg:orig_category":"Comisarios",
    "sg:phone":"+34 952 84 40 59",
    "sg:postcode":"29200",
    "sg:province":"M\u00e1laga",
    "wof:name":"Antiguedades Las Tinajas",
    "wof:placetype":"venue"
},
  "geometry": {"coordinates":[-4.6945333481,37.0607872009],"type":"Point"}
}