{
  "type": "Feature",
  "properties": {
    "iso:country":"ES",
    "sg:address":"Ctra Estella, 6",
    "sg:city":"Larraga",
    "sg:orig_category":"Farmacias",
    "sg:phone":"+34 948 71 10 64",
    "sg:postcode":"31251",
    "sg:province":"Navarra",
    "wof:name":"Osaba Arellano Maria Pilar",
    "wof:placetype":"venue"
},
  "geometry": {"coordinates":[-1.8514839411,42.5628585815],"type":"Point"}
}