{
  "type": "Feature",
  "properties": {
    "iso:country":"ES",
    "sg:address":"Calle de Vicente Camaron, 6",
    "sg:city":"Madrid",
    "sg:orig_category":"Farmacias",
    "sg:phone":"+34 914 63 49 94",
    "sg:postcode":"28011",
    "sg:province":"Madrid",
    "wof:name":"Rios Duran Ana Maria",
    "wof:placetype":"venue"
},
  "geometry": {"coordinates":[-3.7379050255,40.4061775208],"type":"Point"}
}