{
  "type": "Feature",
  "properties": {
    "iso:country":"ES",
    "sg:address":"Avda Antonio Ramos Carratala, S/n",
    "sg:city":"Alacant",
    "sg:orig_category":"Alimentaci\u00d3n General (al Por Menor)",
    "sg:phone":"+34 965 26 40 66",
    "sg:postcode":"03015",
    "sg:province":"Alicante",
    "wof:name":"Luz Garden S.l.",
    "wof:placetype":"venue"
},
  "geometry": {"coordinates":[-0.4619489908,38.369178772],"type":"Point"}
}