{
  "type": "Feature",
  "properties": {
    "iso:country":"ES",
    "sg:address":"S. Antoni, 9",
    "sg:city":"Bossost",
    "sg:orig_category":"Empresas De Pintura Y Revestimientos",
    "sg:phone":"+34 973 64 83 67",
    "sg:postcode":"25550",
    "sg:province":"Lleida",
    "wof:name":"Pintures Nasarre S.c.p.",
    "wof:placetype":"venue"
},
  "geometry": {"coordinates":[0.6910129786,42.7821159363],"type":"Point"}
}