{
  "type": "Feature",
  "properties": {
    "addr:full":"Calle de Ermita (la), 5 Azuqueca Henares Guadalajara 19200",
    "addr:housenumber":"5",
    "addr:postcode":"19200",
    "addr:street":"Calle De Ermita La",
    "iso:country":"ES",
    "sg:address":"Calle de Ermita (la), 5",
    "sg:city":"Azuqueca Henares",
    "sg:orig_category":"Papeler\u00cdas, Librer\u00cdas",
    "sg:phone":"+34 949 26 00 13",
    "sg:postcode":"19200",
    "sg:province":"Guadalajara",
    "wof:name":"Lopez Garcia Ana Margarita",
    "wof:placetype":"venue"
},
  "geometry": {"coordinates":[-3.2629988194,40.5700798035],"type":"Point"}
}