{
  "type": "Feature",
  "properties": {
    "iso:country":"ES",
    "sg:address":"Calle de San Martin, 39",
    "sg:city":"Donostia-san Sebastian",
    "sg:orig_category":"Fisioterapia",
    "sg:phone":"+34 943 42 07 56",
    "sg:postcode":"20005",
    "sg:province":"Guip\u00f9zcoa",
    "wof:name":"Lana Romero Maria Carmen",
    "wof:placetype":"venue"
},
  "geometry": {"coordinates":[-1.9840619564,43.3178329468],"type":"Point"}
}