{
  "type": "Feature",
  "properties": {
    "iso:country":"ES",
    "sg:address":"Plaz Tetuan, 9",
    "sg:city":"Castellon",
    "sg:orig_category":"Deportes Diversos",
    "sg:phone":"+34 964 20 11 54",
    "sg:postcode":"12001",
    "sg:province":"Castell\u00f3n",
    "wof:name":"Federacion Provincial De Caza",
    "wof:placetype":"venue"
},
  "geometry": {"coordinates":[-0.0390199982,39.9866409302],"type":"Point"}
}