{
  "type": "Feature",
  "properties": {
    "addr:full":"Pase Sancha, 22 Malaga M\u00e1laga 29016",
    "addr:housenumber":"22",
    "addr:postcode":"29016",
    "addr:street":"Sancha;Ma\u0301Laga",
    "iso:country":"ES",
    "sg:address":"Pase Sancha, 22",
    "sg:city":"Malaga",
    "sg:orig_category":"Alquiler De Veh\u00cdculos: Turismos Y Utilitarios",
    "sg:phone":"+34 952 22 48 89",
    "sg:postcode":"29016",
    "sg:province":"M\u00e1laga",
    "sg:website":"www.goldenteamlasvegas.com",
    "wof:name":"Vegas Malaga S.a.",
    "wof:placetype":"venue"
},
  "geometry": {"coordinates":[-4.4028520584,36.721370697],"type":"Point"}
}