{
  "type": "Feature",
  "properties": {
    "iso:country":"ES",
    "sg:address":"Carr Torrent, 1",
    "sg:city":"Port D'alcudia",
    "sg:orig_category":"Electricidad: Instaladores",
    "sg:phone":"+34 971 54 64 22",
    "sg:postcode":"07410",
    "sg:province":"Islas Baleares",
    "wof:name":"Vadell Rocamir Francisco",
    "wof:placetype":"venue"
},
  "geometry": {"coordinates":[3.1342539787,39.8427238464],"type":"Point"}
}