{
  "type": "Feature",
  "properties": {
    "addr:full":"Pl Jordi Caldentey, 1 Manacor Islas Baleares 07500",
    "addr:housenumber":"1",
    "addr:postcode":"07500",
    "addr:street":"Pl;Caldentey",
    "iso:country":"ES",
    "sg:address":"Pl Jordi Caldentey, 1",
    "sg:city":"Manacor",
    "sg:orig_category":"Fabricaci\u00d3n De Sobres, Bolsas Y Fundas",
    "sg:phone":"+34 971 55 90 80",
    "sg:postcode":"07500",
    "sg:province":"Islas Baleares",
    "wof:name":"Buades Garau Gabriel",
    "wof:placetype":"venue"
},
  "geometry": {"coordinates":[3.2114539146,39.5712547302],"type":"Point"}
}