{
  "type": "Feature",
  "properties": {
    "iso:country":"ES",
    "sg:address":"Carrer de Mataro, S/n",
    "sg:city":"Sant Feliu Llobregat",
    "sg:orig_category":"Ferreter\u00cda (diversos)",
    "sg:phone":"+34 936 66 59 07",
    "sg:postcode":"08980",
    "sg:province":"Barcelona",
    "wof:name":"Perez Garcia Jose Antonio",
    "wof:placetype":"venue"
},
  "geometry": {"coordinates":[2.0419061184,41.3907241821],"type":"Point"}
}