{
  "type": "Feature",
  "properties": {
    "addr:full":"Calle de Plata (pol. Ind. ), 33 Marbella M\u00e1laga 29600",
    "addr:housenumber":"33",
    "addr:postcode":"29600",
    "addr:street":"Calle De Plata Pol. Ind.;Ma\u0301Laga",
    "iso:country":"ES",
    "sg:address":"Calle de Plata (pol. Ind. ), 33",
    "sg:city":"Marbella",
    "sg:orig_category":"Promotores Constructores",
    "sg:phone":"+34 952 82 97 76",
    "sg:postcode":"29600",
    "sg:province":"M\u00e1laga",
    "wof:name":"Mu\u00f1oz Moreno Francisco",
    "wof:placetype":"venue"
},
  "geometry": {"coordinates":[-4.8666582108,36.5111656189],"type":"Point"}
}