{
  "type": "Feature",
  "properties": {
    "addr:full":"Bidekurutzeta Kalea, 17 Bergara Guip\u00f9zcoa 20570",
    "addr:housenumber":"17",
    "addr:postcode":"20570",
    "addr:street":"Bidekurutzeta Kalea;Guipu\u0300Zcoa",
    "iso:country":"ES",
    "sg:address":"Bidekurutzeta Kalea, 17",
    "sg:city":"Bergara",
    "sg:orig_category":"Abogados",
    "sg:phone":"+34 943 76 72 50",
    "sg:postcode":"20570",
    "sg:province":"Guip\u00f9zcoa",
    "wof:name":"Altuna Gabilondo Ainoa",
    "wof:placetype":"venue"
},
  "geometry": {"coordinates":[-2.4137382507,43.1159591675],"type":"Point"}
}