{
  "type": "Feature",
  "properties": {
    "addr:full":"Carrer de Call, 20 Barcelona Barcelona 08002",
    "addr:housenumber":"20",
    "addr:postcode":"08002",
    "addr:street":"Carrer De Call",
    "iso:country":"ES",
    "sg:address":"Carrer de Call, 20",
    "sg:city":"Barcelona",
    "sg:orig_category":"Fabricaci\u00d3n De Ropa De Deportes",
    "sg:phone":"+34 933 17 56 92",
    "sg:postcode":"08002",
    "sg:province":"Barcelona",
    "wof:name":"Flotats Fransitorra Ramon",
    "wof:placetype":"venue"
},
  "geometry": {"coordinates":[2.1762399673,41.3821907043],"type":"Point"}
}