{
  "type": "Feature",
  "properties": {
    "addr:full":"Carrer de Sant Cristofol, 46 Piera Barcelona 08784",
    "addr:housenumber":"46",
    "addr:postcode":"08784",
    "addr:street":"Carrer De Sant Cristofol",
    "iso:country":"ES",
    "sg:address":"Carrer de Sant Cristofol, 46",
    "sg:city":"Piera",
    "sg:orig_category":"Fabricaci\u00d3n De Mobiliario De Oficina",
    "sg:phone":"+34 937 76 10 02",
    "sg:postcode":"08784",
    "sg:province":"Barcelona",
    "wof:name":"Sengros Pujol Jose Miguel",
    "wof:placetype":"venue"
},
  "geometry": {"coordinates":[1.7509419918,41.5221252441],"type":"Point"}
}