{
  "type": "Feature",
  "properties": {
    "iso:country":"ES",
    "sg:address":"Calle de Fuente (la), 8",
    "sg:city":"Losa Del Obispo",
    "sg:orig_category":"Ingenier\u00cda, Centros De Estudios (diversos)",
    "sg:phone":"+34 962 70 60 35",
    "sg:postcode":"46168",
    "sg:province":"Valencia",
    "wof:name":"Torres Cervera S.l.",
    "wof:placetype":"venue"
},
  "geometry": {"coordinates":[-0.8707572222,39.6957359314],"type":"Point"}
}