{
  "type": "Feature",
  "properties": {
    "addr:full":"Calle de Puerto De Las Pedrizas, S/n Sevilla Sevilla 41006",
    "addr:housenumber":"s / n",
    "addr:postcode":"41006",
    "addr:street":"Calle De Puerto De Las Pedrizas",
    "iso:country":"ES",
    "sg:address":"Calle de Puerto De Las Pedrizas, S/n",
    "sg:city":"Sevilla",
    "sg:orig_category":"Centros De Educaci\u00d3n Especial",
    "sg:phone":"+34 954 63 52 04",
    "sg:postcode":"41006",
    "sg:province":"Sevilla",
    "wof:name":"Junta De Andalucia",
    "wof:placetype":"venue"
},
  "geometry": {"coordinates":[-5.954914093,37.3728904724],"type":"Point"}
}