{
  "type": "Feature",
  "properties": {
    "addr:full":"Idotorbe (san Pedro) Bailara, 21 San Pedro Guip\u00f9zcoa 20870",
    "addr:housenumber":"21",
    "addr:postcode":"20870",
    "addr:street":"Idotorbe San Pedro Bailara",
    "iso:country":"ES",
    "sg:address":"Idotorbe (san Pedro) Bailara, 21",
    "sg:city":"San Pedro",
    "sg:orig_category":"Ense\u00d1anza: Idiomas",
    "sg:phone":"+34 943 74 43 40",
    "sg:postcode":"20870",
    "sg:province":"Guip\u00f9zcoa",
    "wof:name":"Gobierno Vasco-delegacion Territorial De Educacion",
    "wof:placetype":"venue"
},
  "geometry": {"coordinates":[-2.4138290882,43.2163581848],"type":"Point"}
}