{
  "type": "Feature",
  "properties": {
    "iso:country":"ES",
    "sg:address":"Calle de Mariana Pineda, 18",
    "sg:city":"Zaragoza",
    "sg:orig_category":"Carnicer\u00cdas, Carnicer\u00cdas",
    "sg:phone":"+34 976 51 60 62",
    "sg:postcode":"50015",
    "sg:province":"Zaragoza",
    "wof:name":"Lazaro Blasco Juan Simon",
    "wof:placetype":"venue"
},
  "geometry": {"coordinates":[-0.8895810246,41.6651268005],"type":"Point"}
}