{
  "type": "Feature",
  "properties": {
    "iso:country":"ES",
    "sg:address":"Calle de Jose Maria Bayarri, 1",
    "sg:city":"Valencia",
    "sg:orig_category":"Farmacias",
    "sg:phone":"+34 963 83 56 55",
    "sg:postcode":"46014",
    "sg:province":"Valencia",
    "wof:name":"Iborra Lopez Isabel",
    "wof:placetype":"venue"
},
  "geometry": {"coordinates":[-0.4115790129,39.4686012268],"type":"Point"}
}