{
  "type": "Feature",
  "properties": {
    "addr:full":"Calle de Clinica (de La), 4 San Sebastian De Los Reyes Madrid 28700",
    "addr:postcode":"28700",
    "addr:street":"Calle De Clinica De La 4",
    "iso:country":"ES",
    "sg:address":"Calle de Clinica (de La), 4",
    "sg:city":"San Sebastian De Los Reyes",
    "sg:orig_category":"Peluqueros: De Se\u00d1oras",
    "sg:phone":"+34 916 63 87 68",
    "sg:postcode":"28700",
    "sg:province":"Madrid",
    "wof:name":"Chicote Lopez Laura",
    "wof:placetype":"venue"
},
  "geometry": {"coordinates":[-3.6268584728,40.5466651917],"type":"Point"}
}