{
  "type": "Feature",
  "properties": {
    "iso:country":"ES",
    "sg:address":"Carr Moll, De's, 2",
    "sg:city":"Cala Ratjada",
    "sg:orig_category":"Art\u00cdculos De Regalo (al Por Menor)",
    "sg:phone":"+34 971 56 37 56",
    "sg:postcode":"07590",
    "sg:province":"Islas Baleares",
    "wof:name":"Estarellas Ramon Mateo",
    "wof:placetype":"venue"
},
  "geometry": {"coordinates":[3.4632320404,39.7139549255],"type":"Point"}
}