{
  "type": "Feature",
  "properties": {
    "addr:full":"Carretera Almazan-burgo De Osma, S/n Hortezuela Soria 42366",
    "addr:housenumber":"s",
    "addr:postcode":"42366",
    "addr:street":"Carretera Almazan-Burgo De Osma;/ N",
    "iso:country":"ES",
    "sg:address":"Carretera Almazan-burgo De Osma, S/n",
    "sg:city":"Hortezuela",
    "sg:orig_category":"Agricultores, Agricultores",
    "sg:phone":"+34 975 34 35 22",
    "sg:postcode":"42366",
    "sg:province":"Soria",
    "wof:name":"Medina Blanco Antonio",
    "wof:placetype":"venue"
},
  "geometry": {"coordinates":[-2.896394968,41.5271759033],"type":"Point"}
}