{
  "type": "Feature",
  "properties": {
    "iso:country":"ES",
    "sg:address":"Rua Tarrio, S/n",
    "sg:city":"Tarrio",
    "sg:orig_category":"Asociaciones Y Clubs Deportivos",
    "sg:phone":"+34 981 67 71 55",
    "sg:postcode":"15189",
    "sg:province":"La Coru\u00f1a",
    "wof:name":"Club De Campo As Mari\u00f1as S.a.",
    "wof:placetype":"venue"
},
  "geometry": {"coordinates":[-8.3897981644,43.2883262634],"type":"Point"}
}