{
  "type": "Feature",
  "properties": {
    "iso:country":"ES",
    "sg:address":"Valle De Las Cenizas, S/n",
    "sg:city":"Escucha",
    "sg:orig_category":"Producci\u00d3n De Abonos Y De Fertilizantes",
    "sg:phone":"+34 978 72 70 20",
    "sg:postcode":"44770",
    "sg:province":"Teruel",
    "wof:name":"Agrimartin Fertilizantes S.l.",
    "wof:placetype":"venue"
},
  "geometry": {"coordinates":[-0.8151170015,40.7788581848],"type":"Point"}
}