{
  "type": "Feature",
  "properties": {
    "iso:country":"ES",
    "sg:address":"Av. Sagrera (la Sagrera), 51",
    "sg:city":"Corro D'avall",
    "sg:orig_category":"Equipo De Refrigeraci\u00d3n Industrial",
    "sg:phone":"+34 938 46 72 71",
    "sg:postcode":"08520",
    "sg:province":"Barcelona",
    "wof:name":"Pueyo Agudo Jose Benito",
    "wof:placetype":"venue"
},
  "geometry": {"coordinates":[2.2962567806,41.6326560974],"type":"Point"}
}