{
  "type": "Feature",
  "properties": {
    "addr:full":"Calle de Castelar, 6 Linares Ja\u00e9n 23700",
    "addr:housenumber":"6",
    "addr:postcode":"23700",
    "addr:street":"Calle De Castelar;Jae\u0301N",
    "iso:country":"ES",
    "sg:address":"Calle de Castelar, 6",
    "sg:city":"Linares",
    "sg:orig_category":"Peluqueros: De Se\u00d1oras",
    "sg:phone":"+34 953 60 11 33",
    "sg:postcode":"23700",
    "sg:province":"Ja\u00e9n",
    "wof:name":"Garcia Lebrancon Francisco",
    "wof:placetype":"venue"
},
  "geometry": {"coordinates":[-3.6379971504,38.0957832336],"type":"Point"}
}