{
  "type": "Feature",
  "properties": {
    "iso:country":"ES",
    "sg:address":"Calle de Trasmonjas, 1",
    "sg:city":"Priego Cordoba",
    "sg:orig_category":"Abogados",
    "sg:phone":"+34 957 54 72 64",
    "sg:postcode":"14800",
    "sg:province":"C\u00f3rdoba",
    "wof:name":"Garcia Luque Francisco Manuel",
    "wof:placetype":"venue"
},
  "geometry": {"coordinates":[-4.195250988,37.4391708374],"type":"Point"}
}