{
  "type": "Feature",
  "properties": {
    "addr:full":"Avda Juan Carlos I, 26 Pilas Sevilla 41840",
    "addr:housenumber":"26",
    "addr:postcode":"41840",
    "addr:street":"Avda Juan Carlos I",
    "iso:country":"ES",
    "sg:address":"Avda Juan Carlos I, 26",
    "sg:city":"Pilas",
    "sg:orig_category":"Producci\u00d3n, Comercio De Cereales",
    "sg:phone":"+34 954 75 01 31",
    "sg:postcode":"41840",
    "sg:province":"Sevilla",
    "wof:name":"Ferquicer S.l.",
    "wof:placetype":"venue"
},
  "geometry": {"coordinates":[-6.3043460846,37.304599762],"type":"Point"}
}