{
  "type": "Feature",
  "properties": {
    "iso:country":"ES",
    "sg:address":"Avda Gasteiz, 73",
    "sg:city":"Vitoria-gasteiz",
    "sg:orig_category":"Alimentaci\u00d3n General (al Por Menor)",
    "sg:phone":"+34 945 22 41 41",
    "sg:postcode":"01009",
    "sg:province":"\u00c1lava",
    "wof:name":"Gonzalez Prieto Guillermo",
    "wof:placetype":"venue"
},
  "geometry": {"coordinates":[-2.6811261177,42.8504180908],"type":"Point"}
}