{
  "type": "Feature",
  "properties": {
    "iso:country":"ES",
    "sg:address":"Calle de General Franco, 32",
    "sg:city":"Padron",
    "sg:orig_category":"Quincaller\u00cda (al Por Menor)",
    "sg:phone":"+34 981 81 08 11",
    "sg:postcode":"15900",
    "sg:province":"A Coru\u00f1a",
    "wof:name":"Titanio Ferreteria S.l.",
    "wof:placetype":"venue"
},
  "geometry": {"coordinates":[-8.6604585648,42.7376899719],"type":"Point"}
}