{
  "type": "Feature",
  "properties": {
    "addr:full":"Calle de San Marcos, 19 Fernan Nu\u00e7ez C\u00f3rdoba 14520",
    "addr:housenumber":"19",
    "addr:postcode":"14520",
    "addr:street":"Calle De San Marcos;Co\u0301Rdoba",
    "iso:country":"ES",
    "sg:address":"Calle de San Marcos, 19",
    "sg:city":"Fernan Nu\u00e7ez",
    "sg:orig_category":"Cajas Para Embalar",
    "sg:phone":"+34 957 38 03 33",
    "sg:postcode":"14520",
    "sg:province":"C\u00f3rdoba",
    "wof:name":"Caja Rural De Cordoba",
    "wof:placetype":"venue"
},
  "geometry": {"coordinates":[-4.7264637947,37.6709442139],"type":"Point"}
}