{
  "type": "Feature",
  "properties": {
    "addr:full":"Calle de San Sebastian, 6 Puente-genil C\u00f3rdoba 14500",
    "addr:housenumber":"6",
    "addr:postcode":"14500",
    "addr:street":"Calle De San Sebastian;Co\u0301Rdoba",
    "iso:country":"ES",
    "sg:address":"Calle de San Sebastian, 6",
    "sg:city":"Puente-genil",
    "sg:orig_category":"Ingeniero",
    "sg:phone":"+34 957 60 78 88",
    "sg:postcode":"14500",
    "sg:province":"C\u00f3rdoba",
    "wof:name":"Alcantara Arrabal Jose",
    "wof:placetype":"venue"
},
  "geometry": {"coordinates":[-4.7781510353,37.3909301758],"type":"Point"}
}