{
  "type": "Feature",
  "properties": {
    "addr:full":"Avda Segovia, 105 Valladolid Valladolid 47013",
    "addr:housenumber":"105",
    "addr:postcode":"47013",
    "addr:street":"Avda Segovia",
    "iso:country":"ES",
    "sg:address":"Avda Segovia, 105",
    "sg:city":"Valladolid",
    "sg:orig_category":"Bisuter\u00cda, Joyer\u00cda, Relojer\u00cda (al Por Menor)",
    "sg:phone":"+34 983 22 44 48",
    "sg:postcode":"47013",
    "sg:province":"Valladolid",
    "wof:name":"Lesmes Martin Jesus",
    "wof:placetype":"venue"
},
  "geometry": {"coordinates":[-4.7209730148,41.6388969421],"type":"Point"}
}