{
  "type": "Feature",
  "properties": {
    "iso:country":"ES",
    "sg:address":"Carr Doctor Gomez Ulla, 52",
    "sg:city":"Capdepera",
    "sg:orig_category":"Mec\u00c1nico Del Autom\u00d3vil",
    "sg:phone":"+34 971 56 33 40",
    "sg:postcode":"07580",
    "sg:province":"Islas Baleares",
    "wof:name":"Tallers Ca'n Riutort S.l.",
    "wof:placetype":"venue"
},
  "geometry": {"coordinates":[3.4337749481,39.7023048401],"type":"Point"}
}