{
  "type": "Feature",
  "properties": {
    "addr:full":"Calle de San Gregorio, 3 Montealegre Castillo Albacete 02650",
    "addr:housenumber":"3",
    "addr:postcode":"02650",
    "addr:street":"Calle De San Gregorio",
    "iso:country":"ES",
    "sg:address":"Calle de San Gregorio, 3",
    "sg:city":"Montealegre Castillo",
    "sg:orig_category":"Reposter\u00cdas",
    "sg:phone":"+34 967 33 60 60",
    "sg:postcode":"02650",
    "sg:province":"Albacete",
    "wof:name":"Ruiz Riaza Luisa",
    "wof:placetype":"venue"
},
  "geometry": {"coordinates":[-1.3270030022,38.7869758606],"type":"Point"}
}