{
  "type": "Feature",
  "properties": {
    "addr:full":"Calle de Bravo Murillo, 21 Madrid Madrid 28015",
    "addr:housenumber":"21",
    "addr:postcode":"madrid;28015",
    "addr:street":"Calle De Bravo Murillo",
    "iso:country":"ES",
    "sg:address":"Calle de Bravo Murillo, 21",
    "sg:city":"Madrid",
    "sg:orig_category":"Artesan\u00cda",
    "sg:phone":"+34 915 91 41 35",
    "sg:postcode":"28015",
    "sg:province":"Madrid",
    "wof:name":"Tarasov Zenin Alexei",
    "wof:placetype":"venue"
},
  "geometry": {"coordinates":[-3.704472065,40.4355125427],"type":"Point"}
}