{
  "type": "Feature",
  "properties": {
    "iso:country":"ES",
    "sg:address":"Part. B. Alta, 137",
    "sg:city":"Las Bayas",
    "sg:orig_category":"Semiller\u00cdas",
    "sg:phone":"+34 965 45 48 23",
    "sg:postcode":"03292",
    "sg:province":"Alicante",
    "wof:name":"Vivers La Baya S.l.",
    "wof:placetype":"venue"
},
  "geometry": {"coordinates":[-0.6436975002,38.2197151184],"type":"Point"}
}