{
  "type": "Feature",
  "properties": {
    "addr:full":"Carrer de Severo Ochoa, S/n Granollers Barcelona 08403",
    "addr:housenumber":"s / n",
    "addr:postcode":"08403",
    "addr:street":"Carrer De Severo Ochoa",
    "iso:country":"ES",
    "sg:address":"Carrer de Severo Ochoa, S/n",
    "sg:city":"Granollers",
    "sg:orig_category":"Bebidas",
    "sg:phone":"+34 938 40 22 29",
    "sg:postcode":"08403",
    "sg:province":"Barcelona",
    "wof:name":"Covaca S.a.",
    "wof:placetype":"venue"
},
  "geometry": {"coordinates":[2.2663869858,41.5966796875],"type":"Point"}
}