{
  "type": "Feature",
  "properties": {
    "iso:country":"ES",
    "sg:address":"Carr Carmen\u00c7o, 1",
    "sg:city":"Empuriabrava",
    "sg:orig_category":"Inmobiliaria (agencias)",
    "sg:phone":"+34 972 45 43 40",
    "sg:postcode":"17487",
    "sg:province":"Girona",
    "wof:name":"Magnolia 2001 Sl",
    "wof:placetype":"venue"
},
  "geometry": {"coordinates":[3.1190633774,42.2478713989],"type":"Point"}
}