{
  "type": "Feature",
  "properties": {
    "iso:country":"ES",
    "sg:address":"Calle de San Sebastian, 31",
    "sg:city":"Espiel",
    "sg:orig_category":"Asesor\u00cda Fiscal Y Jur\u00cddica",
    "sg:phone":"+34 957 36 40 47",
    "sg:postcode":"14220",
    "sg:province":"C\u00f3rdoba",
    "wof:name":"Cavar Asesores S.l.",
    "wof:placetype":"venue"
},
  "geometry": {"coordinates":[-5.020362854,38.1884346008],"type":"Point"}
}