{
  "type": "Feature",
  "properties": {
    "addr:full":"Avda. Generalisimo, 1 Siles Ja\u00e9n 23380",
    "addr:housenumber":"1",
    "addr:postcode":"23380",
    "addr:street":"Avda. Generalisimo",
    "iso:country":"ES",
    "sg:address":"Avda. Generalisimo, 1",
    "sg:city":"Siles",
    "sg:orig_category":"Ingeniero",
    "sg:phone":"+34 953 49 01 78",
    "sg:postcode":"23380",
    "sg:province":"Ja\u00e9n",
    "wof:name":"Vigueras Gonzalez Juan Antonio",
    "wof:placetype":"venue"
},
  "geometry": {"coordinates":[-2.5846040249,38.389289856],"type":"Point"}
}