{
  "type": "Feature",
  "properties": {
    "addr:full":"Av Llibertat, 2 Mollet Valles Barcelona 08100",
    "addr:housenumber":"2",
    "addr:postcode":"08100",
    "addr:street":"Av Llibertat",
    "iso:country":"ES",
    "sg:address":"Av Llibertat, 2",
    "sg:city":"Mollet Valles",
    "sg:orig_category":"Cl\u00cdnicas Dentales",
    "sg:phone":"+34 935 70 59 12",
    "sg:postcode":"08100",
    "sg:province":"Barcelona",
    "wof:name":"Valero Plaza Juan",
    "wof:placetype":"venue"
},
  "geometry": {"coordinates":[2.2127709389,41.5376472473],"type":"Point"}
}