{
  "type": "Feature",
  "properties": {
    "iso:country":"ES",
    "sg:address":"Calle de Espiritu Santo, S/n",
    "sg:city":"Puerto De Santa Maria",
    "sg:orig_category":"Agencias Y Agentes Comerciales, Representantes",
    "sg:phone":"+34 956 86 03 05",
    "sg:postcode":"11500",
    "sg:province":"C\u00e1diz",
    "wof:name":"Inversiones Diversificadas S.a.",
    "wof:placetype":"venue"
},
  "geometry": {"coordinates":[-6.2213540077,36.6029853821],"type":"Point"}
}