{
  "type": "Feature",
  "properties": {
    "iso:country":"ES",
    "sg:address":"Calle de Orense, 20",
    "sg:city":"Madrid",
    "sg:orig_category":"Centros Empresariales",
    "sg:phone":"+34 915 55 44 43",
    "sg:postcode":"28020",
    "sg:province":"Madrid",
    "sg:website":"www.anced.es",
    "wof:name":"Asociacion Nacional De Centros De Ense\u00f1anza A Distancia",
    "wof:placetype":"venue"
},
  "geometry": {"coordinates":[-3.6951467991,40.450630188],"type":"Point"}
}