{
  "type": "Feature",
  "properties": {
    "addr:full":"Avda Jose Mesa Y Lopez, 15 Palmas De Gran Canaria Las Palmas 35006",
    "addr:postcode":"35006",
    "addr:street":"Avda Jose Mesa Y Lopez 15",
    "iso:country":"ES",
    "sg:address":"Avda Jose Mesa Y Lopez, 15",
    "sg:city":"Palmas De Gran Canaria",
    "sg:orig_category":"Servicios De Telecomunicaciones",
    "sg:phone":"+34 928 24 11 97",
    "sg:postcode":"35006",
    "sg:province":"Las Palmas",
    "wof:name":"Telecor S.a.",
    "wof:placetype":"venue"
},
  "geometry": {"coordinates":[-15.4320087433,28.1345024109],"type":"Point"}
}