{
  "type": "Feature",
  "properties": {
    "addr:full":"Avda Laguardia (de), S/n Logro\u00f1o La Rioja 26006",
    "addr:postcode":"26006",
    "addr:street":"Avda Laguardia De S / N Logron\u0303O;Rioja",
    "iso:country":"ES",
    "sg:address":"Avda Laguardia (de), S/n",
    "sg:city":"Logro\u00f1o",
    "sg:orig_category":"Materias Pl\u00c1sticas: Productos De Consumo Masivo (fabricaci\u00d3n, Al Por Mayor)",
    "sg:phone":"+34 941 23 16 33",
    "sg:postcode":"26006",
    "sg:province":"La Rioja",
    "wof:name":"Plast Papel La Rioja S.c.",
    "wof:placetype":"venue"
},
  "geometry": {"coordinates":[-2.4761888981,42.4873657227],"type":"Point"}
}