{
  "type": "Feature",
  "properties": {
    "addr:full":"Recuerdo, S/n San Javier Murcia 30730",
    "addr:housenumber":"s / n",
    "addr:postcode":"30730",
    "iso:country":"ES",
    "sg:address":"Recuerdo, S/n",
    "sg:city":"San Javier",
    "sg:orig_category":"Centros De Educaci\u00d3n Especial",
    "sg:phone":"+34 968 19 19 20",
    "sg:postcode":"30730",
    "sg:province":"Murcia",
    "wof:name":"Colegio La Paz De San Javier",
    "wof:placetype":"venue"
},
  "geometry": {"coordinates":[-0.8283489943,37.8018417358],"type":"Point"}
}