{
  "type": "Feature",
  "properties": {
    "iso:country":"ES",
    "sg:address":"Calle de Vicente Dura\u00d1ona, 3",
    "sg:city":"Portugalete",
    "sg:orig_category":"Asociaciones Y Clubs Deportivos",
    "sg:phone":"+34 944 83 91 92",
    "sg:postcode":"48920",
    "sg:province":"Vizcaya",
    "wof:name":"Sociedad Ciclista Iru Herri",
    "wof:placetype":"venue"
},
  "geometry": {"coordinates":[-3.0199079514,43.3159065247],"type":"Point"}
}