{
  "type": "Feature",
  "properties": {
    "addr:full":"Pol Ind Ca\u00f1ada De La Fuente, S/n Martos Ja\u00e9n 23600",
    "addr:housenumber":"s / n",
    "addr:postcode":"23600",
    "addr:street":"Fuente;Jae\u0301N",
    "iso:country":"ES",
    "sg:address":"Pol Ind Ca\u00f1ada De La Fuente, S/n",
    "sg:city":"Martos",
    "sg:orig_category":"Materias Pl\u00c1sticas: Productos De Consumo Masivo (fabricaci\u00d3n, Al Por Mayor)",
    "sg:phone":"+34 953 70 47 65",
    "sg:postcode":"23600",
    "sg:province":"Ja\u00e9n",
    "wof:name":"Industrias Auxiliares Marte\u00f1as S.a.",
    "wof:placetype":"venue"
},
  "geometry": {"coordinates":[-3.9491291046,37.601436615],"type":"Point"}
}