{
  "type": "Feature",
  "properties": {
    "addr:full":"Calle de Mayor, 28 Villama\u00f1an Le\u00f3n 24234",
    "addr:housenumber":"28",
    "addr:postcode":"24234",
    "addr:street":"Calle De Mayor;Leo\u0301N",
    "iso:country":"ES",
    "sg:address":"Calle de Mayor, 28",
    "sg:city":"Villama\u00f1an",
    "sg:orig_category":"Carnicer\u00cdas, Carnicer\u00cdas",
    "sg:phone":"+34 987 76 70 14",
    "sg:postcode":"24234",
    "sg:province":"Le\u00f3n",
    "wof:name":"Herrero Cadenas Filomena",
    "wof:placetype":"venue"
},
  "geometry": {"coordinates":[-5.5823187828,42.3222618103],"type":"Point"}
}