{
  "type": "Feature",
  "properties": {
    "iso:country":"ES",
    "sg:address":"Avda Logro\u00d1o, 40",
    "sg:city":"Arnedo",
    "sg:orig_category":"Muebles, Minoristas",
    "sg:phone":"+34 941 38 56 70",
    "sg:postcode":"26580",
    "sg:province":"La Rioja",
    "wof:name":"Muebles Domo Perez S.l.",
    "wof:placetype":"venue"
},
  "geometry": {"coordinates":[-2.0944299698,42.2295227051],"type":"Point"}
}