{
  "type": "Feature",
  "properties": {
    "addr:full":"Calle de Calixto Iii, 29 Valencia Valencia 46008",
    "addr:housenumber":"29",
    "addr:postcode":"46008",
    "addr:street":"Calle De Calixto Iii",
    "iso:country":"ES",
    "sg:address":"Calle de Calixto Iii, 29",
    "sg:city":"Valencia",
    "sg:orig_category":"Restaurantes",
    "sg:phone":"+34 963 84 80 97",
    "sg:postcode":"46008",
    "sg:province":"Valencia",
    "wof:name":"Taberna Kalixto Sl",
    "wof:placetype":"venue"
},
  "geometry": {"coordinates":[-0.3892480135,39.4710044861],"type":"Point"}
}