{
  "type": "Feature",
  "properties": {
    "addr:full":"Po. Ugarte, 6 Moiordin-barrondo Vizcaya 48480",
    "addr:housenumber":"6",
    "addr:postcode":"48480",
    "addr:street":"Po. Ugarte",
    "iso:country":"ES",
    "sg:address":"Po. Ugarte, 6",
    "sg:city":"Moiordin-barrondo",
    "sg:orig_category":"Materias Pl\u00c1sticas: Productos De Consumo Masivo (fabricaci\u00d3n, Al Por Mayor)",
    "sg:phone":"+34 946 71 31 70",
    "sg:postcode":"48480",
    "sg:province":"Vizcaya",
    "wof:name":"Gonzalez Vidal Sergio",
    "wof:placetype":"venue"
},
  "geometry": {"coordinates":[-2.6983869076,43.2204284668],"type":"Point"}
}