{
  "type": "Feature",
  "properties": {
    "addr:full":"Calle de Cristo De La Epidemia, 89 Malaga M\u00e1laga 29013",
    "addr:housenumber":"89",
    "addr:postcode":"29013",
    "addr:street":"Calle De Cristo De La Epidemia;Ma\u0301Laga",
    "iso:country":"ES",
    "sg:address":"Calle de Cristo De La Epidemia, 89",
    "sg:city":"Malaga",
    "sg:orig_category":"Agencias Y Agentes Comerciales, Representantes",
    "sg:phone":"+34 952 25 37 77",
    "sg:postcode":"29013",
    "sg:province":"M\u00e1laga",
    "wof:name":"Santiago Casares Francisco",
    "wof:placetype":"venue"
},
  "geometry": {"coordinates":[-4.4155669212,36.7321662903],"type":"Point"}
}