{
  "type": "Feature",
  "properties": {
    "addr:full":"Calle de Divino Maestro, 2 Logro\u00f1o La Rioja 26002",
    "addr:housenumber":"2",
    "addr:postcode":"26002",
    "addr:street":"Calle De Divino Maestro;Rioja",
    "iso:country":"ES",
    "sg:address":"Calle de Divino Maestro, 2",
    "sg:city":"Logro\u00f1o",
    "sg:orig_category":"Ense\u00d1anza, Formaci\u00d3n Profesional: Aprendizaje",
    "sg:phone":"+34 941 21 45 54",
    "sg:postcode":"26002",
    "sg:province":"La Rioja",
    "wof:name":"Comunidad Autonoma De La Rioja",
    "wof:placetype":"venue"
},
  "geometry": {"coordinates":[-2.4529130459,42.4573822021],"type":"Point"}
}