{
  "type": "Feature",
  "properties": {
    "addr:full":"C/ Sureda, D'en, 25 Porto Cristo Islas Baleares 07680",
    "addr:housenumber":"25",
    "addr:postcode":"07680",
    "addr:street":"C / Sureda D'En;Islas Baleares",
    "iso:country":"ES",
    "sg:address":"C/ Sureda, D'en, 25",
    "sg:city":"Porto Cristo",
    "sg:orig_category":"Pescader\u00cdas (al Por Menor)",
    "sg:phone":"+34 971 82 10 93",
    "sg:postcode":"07680",
    "sg:province":"Islas Baleares",
    "wof:name":"Barcelo Juan Damian",
    "wof:placetype":"venue"
},
  "geometry": {"coordinates":[3.3348650932,39.5417861938],"type":"Point"}
}