{
  "type": "Feature",
  "properties": {
    "addr:full":"Calle de Uribea, 2 Durana \u00c1lava 01520",
    "addr:housenumber":"2",
    "addr:postcode":"01520",
    "addr:street":"Calle De Uribea;A\u0301Lava",
    "iso:country":"ES",
    "sg:address":"Calle de Uribea, 2",
    "sg:city":"Durana",
    "sg:orig_category":"Venta, Instalaci\u00d3n De Calefacci\u00d3n",
    "sg:phone":"+34 945 29 95 41",
    "sg:postcode":"01520",
    "sg:province":"\u00c1lava",
    "wof:name":"Reparaciones Y Mantenimientos Jodra S.l.",
    "wof:placetype":"venue"
},
  "geometry": {"coordinates":[-2.639703989,42.8898353577],"type":"Point"}
}