{
  "type": "Feature",
  "properties": {
    "addr:full":"Arrabal Inferior, 17 Palafrugell Girona 17200",
    "addr:housenumber":"17",
    "addr:postcode":"17200",
    "addr:street":"Inferior",
    "iso:country":"ES",
    "sg:address":"Arrabal Inferior, 17",
    "sg:city":"Palafrugell",
    "sg:orig_category":"Fabricaci\u00d3n De Mobiliario Met\u00c1lico",
    "sg:phone":"+34 972 30 70 60",
    "sg:postcode":"17200",
    "sg:province":"Girona",
    "wof:name":"Palafrugell Interior Arts S.l.",
    "wof:placetype":"venue"
},
  "geometry": {"coordinates":[3.1635940075,41.9163398743],"type":"Point"}
}