{
  "type": "Feature",
  "properties": {
    "iso:country":"ES",
    "sg:address":"Urb C.r. Novo Sancti-petri, S/n",
    "sg:city":"Barrosa",
    "sg:orig_category":"Asilos De Ancianos. Centros Privados",
    "sg:phone":"+34 956 49 23 77",
    "sg:postcode":"11130",
    "sg:province":"C\u00e1diz",
    "sg:website":"www.satesl.com",
    "wof:name":"Servicios Avanzados De La 3 Edad S.l.",
    "wof:placetype":"venue"
},
  "geometry": {"coordinates":[-6.1447038651,36.4212188721],"type":"Point"}
}