{
  "type": "Feature",
  "properties": {
    "addr:full":"Calle de Cuestas (las), 32 S. Vicente Sonsierra La Rioja 26338",
    "addr:housenumber":"32",
    "addr:postcode":"26338",
    "addr:street":"Calle De Cuestas Las;S. Vicente Sonsierra;Rioja",
    "iso:country":"ES",
    "sg:address":"Calle de Cuestas (las), 32",
    "sg:city":"S. Vicente Sonsierra",
    "sg:orig_category":"Bebidas",
    "sg:phone":"+34 941 33 44 50",
    "sg:postcode":"26338",
    "sg:province":"La Rioja",
    "wof:name":"Vinos De Bejamin Romeo S.l",
    "wof:placetype":"venue"
},
  "geometry": {"coordinates":[-2.7608299255,42.5630073547],"type":"Point"}
}