{
  "type": "Feature",
  "properties": {
    "iso:country":"ES",
    "sg:address":"Carrer de Marina (de La), S/n",
    "sg:city":"Ca L'artigues",
    "sg:orig_category":"Reparaciones Y Remolcado De Veh\u00cdculos",
    "sg:phone":"+34 938 41 64 51",
    "sg:postcode":"08186",
    "sg:province":"Barcelona",
    "wof:name":"Carrillo Pajares Jose",
    "wof:placetype":"venue"
},
  "geometry": {"coordinates":[2.1718220711,41.5917434692],"type":"Point"}
}