{
  "type": "Feature",
  "properties": {
    "addr:full":"C/ Formentor, S/n Cales Mallorca Islas Baleares 07689",
    "addr:housenumber":"s",
    "addr:postcode":"07689",
    "addr:street":"C / Formentor;/ N Cales",
    "iso:country":"ES",
    "sg:address":"C/ Formentor, S/n",
    "sg:city":"Cales Mallorca",
    "sg:orig_category":"Centros Empresariales",
    "sg:phone":"+34 971 83 33 64",
    "sg:postcode":"07689",
    "sg:province":"Islas Baleares",
    "wof:name":"Pascual Bennasar Isabel Maria",
    "wof:placetype":"venue"
},
  "geometry": {"coordinates":[3.2789549828,39.4605445862],"type":"Point"}
}