{
  "type": "Feature",
  "properties": {
    "addr:full":"Rua Mosteiro De Sobrado, 2 Acea De Ama A Coru\u00f1a 15670",
    "addr:housenumber":"2",
    "addr:postcode":"15670",
    "addr:street":"Rua Mosteiro De Sobrado;Corun\u0303A",
    "iso:country":"ES",
    "sg:address":"Rua Mosteiro De Sobrado, 2",
    "sg:city":"Acea De Ama",
    "sg:orig_category":"Alquiler De V\u00cddeo",
    "sg:phone":"+34 981 65 00 90",
    "sg:postcode":"15670",
    "sg:province":"A Coru\u00f1a",
    "wof:name":"Videoclub El Burgo",
    "wof:placetype":"venue"
},
  "geometry": {"coordinates":[-8.3809137344,43.32447052],"type":"Point"}
}