{
  "type": "Feature",
  "properties": {
    "addr:full":"Bard San Isidro, S/n Barrios C\u00e1diz 11370",
    "addr:housenumber":"s",
    "addr:postcode":"11370",
    "addr:street":"San Isidro;/ N Barrios Ca\u0301Diz",
    "iso:country":"ES",
    "sg:address":"Bard San Isidro, S/n",
    "sg:city":"Barrios",
    "sg:orig_category":"Droguer\u00cdas (al Por Menor)",
    "sg:phone":"+34 956 62 01 54",
    "sg:postcode":"11370",
    "sg:province":"C\u00e1diz",
    "wof:name":"Correro Corbacho Antonio",
    "wof:placetype":"venue"
},
  "geometry": {"coordinates":[-5.4946498871,36.1863174438],"type":"Point"}
}