{
  "type": "Feature",
  "properties": {
    "iso:country":"ES",
    "sg:address":"Calle de Maestro Palau, 4",
    "sg:city":"Valencia",
    "sg:orig_category":"Farmacias",
    "sg:phone":"+34 963 91 56 04",
    "sg:postcode":"46008",
    "sg:province":"Valencia",
    "wof:name":"Buj Herrero Rosario",
    "wof:placetype":"venue"
},
  "geometry": {"coordinates":[-0.3844119906,39.4716300964],"type":"Point"}
}