{
  "type": "Feature",
  "properties": {
    "iso:country":"ES",
    "sg:address":"Calle de Julio Del Campo, 4",
    "sg:city":"Le\u00f3n",
    "sg:orig_category":"Propiedad Industrial: Patentes De Inventos, Marcas, Modelos, Dise\u00d1os",
    "sg:phone":"+34 987 22 87 78",
    "sg:postcode":"24002",
    "sg:province":"Le\u00f3n",
    "wof:name":"Caballero & Cidon S.l.",
    "wof:placetype":"venue"
},
  "geometry": {"coordinates":[-5.5738358498,42.600227356],"type":"Point"}
}