{
  "type": "Feature",
  "properties": {
    "addr:full":"Calle de Marmoles, 37 Malaga M\u00e1laga 29007",
    "addr:housenumber":"37",
    "addr:postcode":"29007",
    "addr:street":"Calle De Marmoles;Ma\u0301Laga",
    "iso:country":"ES",
    "sg:address":"Calle de Marmoles, 37",
    "sg:city":"Malaga",
    "sg:orig_category":"Cajas De Ahorro",
    "sg:phone":"+34 952 28 33 12",
    "sg:postcode":"29007",
    "sg:province":"M\u00e1laga",
    "sg:website":"www.unicaja.es",
    "wof:name":"Unicaja",
    "wof:placetype":"venue"
},
  "geometry": {"coordinates":[-4.4297318459,36.7214546204],"type":"Point"}
}