{
  "type": "Feature",
  "properties": {
    "addr:full":"Av Generalitat (de La), 74 Tortosa Tarragona 43500",
    "addr:housenumber":"74",
    "addr:postcode":"43500",
    "addr:street":"Av Generalitat De La",
    "iso:country":"ES",
    "sg:address":"Av Generalitat (de La), 74",
    "sg:city":"Tortosa",
    "sg:orig_category":"Agentes, Concesionarios Y Sucursales De Veh\u00cdculos",
    "sg:phone":"+34 977 44 34 95",
    "sg:postcode":"43500",
    "sg:province":"Tarragona",
    "wof:name":"Garage Rosellon S.l.",
    "wof:placetype":"venue"
},
  "geometry": {"coordinates":[0.5202460289,40.8065109253],"type":"Point"}
}