{
  "type": "Feature",
  "properties": {
    "addr:full":"Avda Colmenar Viejo (de), 3 San Sebastian De Los Reyes Madrid 28700",
    "addr:postcode":"28700",
    "addr:street":"Avda Colmenar",
    "iso:country":"ES",
    "sg:address":"Avda Colmenar Viejo (de), 3",
    "sg:city":"San Sebastian De Los Reyes",
    "sg:orig_category":"Ropa Para Se\u00d1oras Y Caballeros (al Por Menor)",
    "sg:phone":"+34 916 53 25 33",
    "sg:postcode":"28700",
    "sg:province":"Madrid",
    "wof:name":"Cabero Garcia Antonio",
    "wof:placetype":"venue"
},
  "geometry": {"coordinates":[-3.6285851002,40.5450820923],"type":"Point"}
}