{
  "type": "Feature",
  "properties": {
    "addr:full":"Centro Comercial Bonaire, S/n Aldaia Valencia 46960",
    "addr:housenumber":"s / n",
    "addr:postcode":"46960",
    "iso:country":"ES",
    "sg:address":"Centro Comercial Bonaire, S/n",
    "sg:city":"Aldaia",
    "sg:orig_category":"Muebles",
    "sg:phone":"+34 961 92 05 54",
    "sg:postcode":"46960",
    "sg:province":"Valencia",
    "sg:website":"www.natuzzi.es",
    "wof:name":"Natuzzi Iberica S. A.",
    "wof:placetype":"venue"
},
  "geometry": {"coordinates":[-0.4853590131,39.4696578979],"type":"Point"}
}