{
  "type": "Feature",
  "properties": {
    "addr:full":"Calle de Becquer, 1 Guardo Palencia 34880",
    "addr:housenumber":"1",
    "addr:postcode":"34880",
    "addr:street":"Calle De Becquer",
    "iso:country":"ES",
    "sg:address":"Calle de Becquer, 1",
    "sg:city":"Guardo",
    "sg:orig_category":"Electrodom\u00c9sticos (al Por Menor)",
    "sg:phone":"+34 979 85 04 88",
    "sg:postcode":"34880",
    "sg:province":"Palencia",
    "wof:name":"Liebana Villarroel Francisco Javier",
    "wof:placetype":"venue"
},
  "geometry": {"coordinates":[-4.8454341888,42.7880134583],"type":"Point"}
}