{
  "type": "Feature",
  "properties": {
    "addr:full":"Calle de Joaquin Arnau, 2 Teruel Teruel 44001",
    "addr:housenumber":"2",
    "addr:postcode":"44001",
    "addr:street":"Calle De Joaquin Arnau",
    "iso:country":"ES",
    "sg:address":"Calle de Joaquin Arnau, 2",
    "sg:city":"Teruel",
    "sg:orig_category":"Centros P\u00dablicos De Formaci\u00d3n Profesional Y T\u00c9cnica",
    "sg:phone":"+34 978 61 72 10",
    "sg:postcode":"44001",
    "sg:province":"Teruel",
    "wof:name":"Colegio Oficial De Medicos De Teruel",
    "wof:placetype":"venue"
},
  "geometry": {"coordinates":[-1.1076899767,40.3416557312],"type":"Point"}
}