{
  "type": "Feature",
  "properties": {
    "iso:country":"ES",
    "sg:address":"Carrer de Francesc Pi I Margall, 77",
    "sg:city":"S. Boi Llobregat",
    "sg:orig_category":"Ropa Y Art\u00cdculos Pre",
    "sg:phone":"+34 936 40 20 93",
    "sg:postcode":"08830",
    "sg:province":"Barcelona",
    "wof:name":"Rodriguez Maga\u00f1a Juan Antonio",
    "wof:placetype":"venue"
},
  "geometry": {"coordinates":[2.03697896,41.3470993042],"type":"Point"}
}