{
  "type": "Feature",
  "properties": {
    "addr:full":"Carrer de Roger De Lluria, 86 Barcelona Barcelona 08009",
    "addr:housenumber":"86",
    "addr:postcode":"08009",
    "addr:street":"Carrer De Roger De Lluria",
    "iso:country":"ES",
    "sg:address":"Carrer de Roger De Lluria, 86",
    "sg:city":"Barcelona",
    "sg:orig_category":"Abogados",
    "sg:phone":"+34 934 57 22 97",
    "sg:postcode":"08009",
    "sg:province":"Barcelona",
    "wof:name":"Marfil Nu\u00f1ez Carolina",
    "wof:placetype":"venue"
},
  "geometry": {"coordinates":[2.166162014,41.395362854],"type":"Point"}
}