{
  "type": "Feature",
  "properties": {
    "iso:country":"ES",
    "sg:address":"Av Castiero, 7",
    "sg:city":"Vielha",
    "sg:orig_category":"Laboratorios Y Trabajos De Fotograf\u00cda, V\u00cddeo Y Cine",
    "sg:phone":"+34 973 64 01 37",
    "sg:postcode":"25530",
    "sg:province":"Lleida",
    "wof:name":"Caseny Durro Alfonso",
    "wof:placetype":"venue"
},
  "geometry": {"coordinates":[0.7947720289,42.7023925781],"type":"Point"}
}