{
  "type": "Feature",
  "properties": {
    "iso:country":"ES",
    "sg:address":"Calle de Rambla De Capuchinos, 22",
    "sg:city":"Motril",
    "sg:orig_category":"Confecci\u00d3n De Trajes Para Se\u00d1oras",
    "sg:phone":"+34 958 60 29 18",
    "sg:postcode":"18600",
    "sg:province":"Granada",
    "wof:name":"Saez Delgado Costa Tropical S.l.",
    "wof:placetype":"venue"
},
  "geometry": {"coordinates":[-3.5179190636,36.7481384277],"type":"Point"}
}