{
  "type": "Feature",
  "properties": {
    "addr:full":"Ctra. Quintanaopio, S/n Cantabrana Burgos 09593",
    "addr:housenumber":"s / n",
    "addr:postcode":"09593",
    "addr:street":"Ctra. Quintanaopio",
    "iso:country":"ES",
    "sg:address":"Ctra. Quintanaopio, S/n",
    "sg:city":"Cantabrana",
    "sg:orig_category":"Ense\u00d1anza, Formaci\u00d3n Profesional: Aprendizaje",
    "sg:phone":"+34 947 30 00 51",
    "sg:postcode":"09593",
    "sg:province":"Burgos",
    "wof:name":"Ayuntamiento-centro Rural De Higiene",
    "wof:placetype":"venue"
},
  "geometry": {"coordinates":[-3.4740223885,42.7350311279],"type":"Point"}
}