{
  "type": "Feature",
  "properties": {
    "iso:country":"ES",
    "sg:address":"Carrer de Bruc, 84",
    "sg:city":"Barcelona",
    "sg:orig_category":"Aud\u00cdfonos",
    "sg:phone":"+34 932 15 26 06",
    "sg:postcode":"08009",
    "sg:province":"Barcelona",
    "wof:name":"Eva Factory S.l.",
    "wof:placetype":"venue"
},
  "geometry": {"coordinates":[2.1697220802,41.3943748474],"type":"Point"}
}