{
  "type": "Feature",
  "properties": {
    "addr:full":"Luga Arco Del Populo, S/n Cadiz C\u00e1diz 11005",
    "addr:housenumber":"s / n",
    "addr:postcode":"11005",
    "iso:country":"ES",
    "sg:address":"Luga Arco Del Populo, S/n",
    "sg:city":"Cadiz",
    "sg:orig_category":"Comunidades Religiosas",
    "sg:phone":"+34 956 26 43 85",
    "sg:postcode":"11005",
    "sg:province":"C\u00e1diz",
    "wof:name":"Secretariado Diocesano De Hermandades Y Cofradias De Cadiz",
    "wof:placetype":"venue"
},
  "geometry": {"coordinates":[-6.2902388573,36.5298614502],"type":"Point"}
}