{
  "type": "Feature",
  "properties": {
    "iso:country":"ES",
    "sg:address":"Carr Pins, 6",
    "sg:city":"Port D'alcudia",
    "sg:orig_category":"Agencias De Viajes",
    "sg:phone":"+34 971 54 54 78",
    "sg:postcode":"07410",
    "sg:province":"Islas Baleares",
    "wof:name":"Viajes Alcudia Tours S.l.",
    "wof:placetype":"venue"
},
  "geometry": {"coordinates":[3.1233201027,39.8516082764],"type":"Point"}
}