{
  "type": "Feature",
  "properties": {
    "addr:full":"Ctra. Stgo-a Estrada, S/n Cacheiras La Coru\u00f1a 15883",
    "addr:housenumber":"s",
    "addr:postcode":"15883",
    "addr:street":"Ctra. Stgo-A Estrada;/ N;La Corun\u0303A",
    "iso:country":"ES",
    "sg:address":"Ctra. Stgo-a Estrada, S/n",
    "sg:city":"Cacheiras",
    "sg:orig_category":"\u00d3ptica: Instrumentos (fabricaci\u00d3n)",
    "sg:phone":"+34 981 80 71 43",
    "sg:postcode":"15883",
    "sg:province":"La Coru\u00f1a",
    "wof:name":"Garcia Rego Manuel",
    "wof:placetype":"venue"
},
  "geometry": {"coordinates":[-8.5463113785,42.8224372864],"type":"Point"}
}