{
  "type": "Feature",
  "properties": {
    "iso:country":"ES",
    "sg:address":"Carr Mestre Chapi, 14",
    "sg:city":"Alcasser",
    "sg:orig_category":"M\u00c9dicos: Estomatolog\u00cda",
    "sg:phone":"+34 961 23 54 60",
    "sg:postcode":"46290",
    "sg:province":"Valencia",
    "wof:name":"Guerrero Guerola Joaquin",
    "wof:placetype":"venue"
},
  "geometry": {"coordinates":[-0.4470080137,39.3701133728],"type":"Point"}
}