{
  "type": "Feature",
  "properties": {
    "addr:full":"Avda Primo De Rivera, 4 Coru\u00d1a A Coru\u00f1a 15006",
    "addr:housenumber":"4",
    "addr:postcode":"15006",
    "addr:street":"Avda Primo De Rivera;Corun\u0303A",
    "iso:country":"ES",
    "sg:address":"Avda Primo De Rivera, 4",
    "sg:city":"Coru\u00d1a",
    "sg:orig_category":"Ense\u00d1anza: Profesiones Art\u00cdsticas",
    "sg:phone":"+34 981 16 81 40",
    "sg:postcode":"15006",
    "sg:province":"A Coru\u00f1a",
    "wof:name":"Xulio Correa Asociados S.l.",
    "wof:placetype":"venue"
},
  "geometry": {"coordinates":[-8.4040670395,43.3601646423],"type":"Point"}
}