{
  "type": "Feature",
  "properties": {
    "addr:full":"Carrer de Paisos Catalans, 7 Calldetenes Barcelona 08519",
    "addr:housenumber":"7",
    "addr:postcode":"08519",
    "addr:street":"Carrer De Paisos Catalans",
    "iso:country":"ES",
    "sg:address":"Carrer de Paisos Catalans, 7",
    "sg:city":"Calldetenes",
    "sg:orig_category":"Trabajos De Perforaciones, Sondeos, Construcci\u00d3n De Pozos",
    "sg:phone":"+34 938 89 08 58",
    "sg:postcode":"08519",
    "sg:province":"Barcelona",
    "wof:name":"Perforacions Josep Casany S.l",
    "wof:placetype":"venue"
},
  "geometry": {"coordinates":[-97.78224945069999,45.7040786743],"type":"Point"}
}