{
  "type": "Feature",
  "properties": {
    "iso:country":"ES",
    "sg:address":"Ptda. Arriba, 11",
    "sg:city":"Valencia",
    "sg:orig_category":"Contenedores Para Transporte De Mercanc\u00cdas",
    "sg:phone":"+34 963 48 15 15",
    "sg:postcode":"46015",
    "sg:province":"Valencia",
    "wof:name":"Contenedores Fabado S.l.",
    "wof:placetype":"venue"
},
  "geometry": {"coordinates":[-0.4112049937,39.4840507507],"type":"Point"}
}