{
  "type": "Feature",
  "properties": {
    "addr:full":"Calle de Iturribide, 8 Getxo Vizcaya 48990",
    "addr:housenumber":"8",
    "addr:postcode":"48990",
    "addr:street":"Calle De Iturribide",
    "iso:country":"ES",
    "sg:address":"Calle de Iturribide, 8",
    "sg:city":"Getxo",
    "sg:orig_category":"Peluquer\u00cdas, Peluquer\u00cda Mixta",
    "sg:phone":"+34 944 30 08 91",
    "sg:postcode":"48990",
    "sg:province":"Vizcaya",
    "wof:name":"Peluqueria Aloa",
    "wof:placetype":"venue"
},
  "geometry": {"coordinates":[-3.0096554756,43.3587417603],"type":"Point"}
}