{
  "type": "Feature",
  "properties": {
    "iso:country":"ES",
    "sg:address":"Plaz Molviedro, S/n",
    "sg:city":"Sevilla",
    "sg:orig_category":"Asociaciones, Organismos Culturales Y Socioeducativos",
    "sg:phone":"+34 954 22 05 18",
    "sg:postcode":"41001",
    "sg:province":"Sevilla",
    "wof:name":"Hermandad De Nuestro Padre Jesus Despojado",
    "wof:placetype":"venue"
},
  "geometry": {"coordinates":[-5.997824192,37.3877639771],"type":"Point"}
}