{
  "type": "Feature",
  "properties": {
    "addr:full":"Calle de Fuente Nueva, 19 Algeciras C\u00e1diz 11203",
    "addr:housenumber":"19;ca\u0301diz",
    "addr:postcode":"11203",
    "addr:street":"Calle De Fuente Nueva",
    "iso:country":"ES",
    "sg:address":"Calle de Fuente Nueva, 19",
    "sg:city":"Algeciras",
    "sg:orig_category":"Peluquer\u00cdas, Peluquer\u00cda Mixta",
    "sg:phone":"+34 956 66 28 07",
    "sg:postcode":"11203",
    "sg:province":"C\u00e1diz",
    "wof:name":"Melendez Gaona Jose",
    "wof:placetype":"venue"
},
  "geometry": {"coordinates":[-5.4533390999,36.1320610046],"type":"Point"}
}