{
  "type": "Feature",
  "properties": {
    "addr:full":"Calle de Jose Soto Mico, 25 Valencia Valencia 46017",
    "addr:housenumber":"25",
    "addr:postcode":"46017",
    "addr:street":"Calle De Jose Soto Mico",
    "iso:country":"ES",
    "sg:address":"Calle de Jose Soto Mico, 25",
    "sg:city":"Valencia",
    "sg:orig_category":"Mec\u00c1nico Del Autom\u00d3vil",
    "sg:phone":"+34 963 57 71 86",
    "sg:postcode":"46017",
    "sg:province":"Valencia",
    "wof:name":"Bautista Roman Isidro",
    "wof:placetype":"venue"
},
  "geometry": {"coordinates":[-0.3883019984,39.4409370422],"type":"Point"}
}