{
  "type": "Feature",
  "properties": {
    "addr:full":"Pla\u00c7 Sant Roc, 4 Puig Valencia 46540",
    "addr:postcode":"46540",
    "iso:country":"ES",
    "sg:address":"Pla\u00c7 Sant Roc, 4",
    "sg:city":"Puig",
    "sg:orig_category":"Arquitectos",
    "sg:phone":"+34 961 47 00 88",
    "sg:postcode":"46540",
    "sg:province":"Valencia",
    "wof:name":"Oriola Arnal Daniel",
    "wof:placetype":"venue"
},
  "geometry": {"coordinates":[-0.3003390133,39.5875854492],"type":"Point"}
}