{
  "type": "Feature",
  "properties": {
    "addr:full":"Carrer de Sant Ramon, 22 Santa Coloma De Gramenet Barcelona 08922",
    "addr:housenumber":"22",
    "addr:postcode":"08922",
    "addr:street":"Carrer De Sant Ramon",
    "iso:country":"ES",
    "sg:address":"Carrer de Sant Ramon, 22",
    "sg:city":"Santa Coloma De Gramenet",
    "sg:orig_category":"Bordado, Marcado A Medida",
    "sg:phone":"+34 933 86 60 44",
    "sg:postcode":"08922",
    "sg:province":"Barcelona",
    "wof:name":"Ramos Nicolas Angel",
    "wof:placetype":"venue"
},
  "geometry": {"coordinates":[2.2125930786,41.4496650696],"type":"Point"}
}