{
  "type": "Feature",
  "properties": {
    "iso:country":"ES",
    "sg:address":"A Barca, 10",
    "sg:city":"Barca",
    "sg:orig_category":"Transportes Por Carretera: Lotes Completos, Mercanc\u00cdas Diversas",
    "sg:phone":"+34 986 54 28 21",
    "sg:postcode":"36639",
    "sg:province":"Pontevedra",
    "wof:name":"Gomez Sanmartin Faustino",
    "wof:placetype":"venue"
},
  "geometry": {"coordinates":[-8.8220100403,42.4838981628],"type":"Point"}
}