{
  "type": "Feature",
  "properties": {
    "iso:country":"ES",
    "sg:address":"Calle de Santa Teresa De Jesus (de), 18",
    "sg:city":"San Sebastian De Los Reyes",
    "sg:orig_category":"Diet\u00c9tica: Productos Biol\u00d3gicos, Naturales Y Diet\u00c9ticos (fabricaci\u00d3n, Al Por Mayor)",
    "sg:phone":"+34 916 63 85 95",
    "sg:postcode":"28700",
    "sg:province":"Madrid",
    "wof:name":"Trujillo Martin Luis Fernando",
    "wof:placetype":"venue"
},
  "geometry": {"coordinates":[-3.6318984032,40.5458717346],"type":"Point"}
}