{
  "type": "Feature",
  "properties": {
    "addr:full":"Ctra Cortijo, Km. 0003,0 Logro\u00f1o La Rioja 26006",
    "addr:postcode":"26006",
    "addr:street":"Ctra Cortijo Km. 0003,0 Logron\u0303O;Rioja",
    "iso:country":"ES",
    "sg:address":"Ctra Cortijo, Km. 0003,0",
    "sg:city":"Logro\u00f1o",
    "sg:orig_category":"Muebles Y Accesorios Para Cocinas Y Cuartos De Ba\u00d1o (al Por Menor)",
    "sg:phone":"+34 941 20 10 41",
    "sg:postcode":"26006",
    "sg:province":"La Rioja",
    "sg:website":"www.indukit.com",
    "wof:name":"Indukit S.a.",
    "wof:placetype":"venue"
},
  "geometry": {"coordinates":[-2.4845588207,42.4849243164],"type":"Point"}
}