{
  "type": "Feature",
  "properties": {
    "iso:country":"ES",
    "sg:address":"Calle de Mayor, 1",
    "sg:city":"Puntal",
    "sg:orig_category":"Bibliotecas, Mediatecas",
    "sg:phone":"+34 968 30 69 70",
    "sg:postcode":"30100",
    "sg:province":"Murcia",
    "wof:name":"Ayuntamiento De Murcia",
    "wof:placetype":"venue"
},
  "geometry": {"coordinates":[-1.1537233591,38.0133018494],"type":"Point"}
}