{
  "type": "Feature",
  "properties": {
    "addr:full":"Carr Fray Antonio Juan, 4 Sueca Valencia 46410",
    "addr:housenumber":"4",
    "addr:postcode":"46410",
    "addr:street":"Carr Fray Antonio Juan",
    "iso:country":"ES",
    "sg:address":"Carr Fray Antonio Juan, 4",
    "sg:city":"Sueca",
    "sg:orig_category":"Zapatos (al Por Menor)",
    "sg:phone":"+34 961 70 39 14",
    "sg:postcode":"46410",
    "sg:province":"Valencia",
    "wof:name":"Escriva Meseguer Silvia",
    "wof:placetype":"venue"
},
  "geometry": {"coordinates":[-0.3108490109,39.2024421692],"type":"Point"}
}