{
  "type": "Feature",
  "properties": {
    "addr:full":"Calle de Principe De Vergara, 72 Madrid Madrid 28006",
    "addr:housenumber":"72",
    "addr:postcode":"madrid;28006",
    "addr:street":"Calle De Principe De Vergara",
    "iso:country":"ES",
    "sg:address":"Calle de Principe De Vergara, 72",
    "sg:city":"Madrid",
    "sg:orig_category":"Ense\u00d1anza, Formaci\u00d3n Profesional: Aprendizaje",
    "sg:phone":"+34 914 11 34 55",
    "sg:postcode":"28006",
    "sg:province":"Madrid",
    "wof:name":"Comision Vigilancia Seguimiento C.c. De Registradores Ppadad.",
    "wof:placetype":"venue"
},
  "geometry": {"coordinates":[-3.6791899204,40.4344215393],"type":"Point"}
}