{
  "type": "Feature",
  "properties": {
    "addr:full":"Calle de Ramon Perez De Ayala, 40 Madrid Madrid 28038",
    "addr:housenumber":"40",
    "addr:postcode":"madrid;28038",
    "addr:street":"Calle De Ramon Perez De Ayala",
    "iso:country":"ES",
    "sg:address":"Calle de Ramon Perez De Ayala, 40",
    "sg:city":"Madrid",
    "sg:orig_category":"Supermercados Y Hipermercados",
    "sg:phone":"+34 913 28 34 30",
    "sg:postcode":"28038",
    "sg:province":"Madrid",
    "wof:name":"Autoservicios De La Vega S.l.",
    "wof:placetype":"venue"
},
  "geometry": {"coordinates":[-3.6540162563,40.3991279602],"type":"Point"}
}