{
  "type": "Feature",
  "properties": {
    "addr:full":"Mcdo Ctral Abastos, S/n Elda Alicante 03600",
    "addr:housenumber":"s / n",
    "addr:postcode":"03600",
    "iso:country":"ES",
    "sg:address":"Mcdo Ctral Abastos, S/n",
    "sg:city":"Elda",
    "sg:orig_category":"Fabricaci\u00d3n De Productos L\u00c1cteos Y Derivados",
    "sg:phone":"+34 966 98 18 94",
    "sg:postcode":"03600",
    "sg:province":"Alicante",
    "wof:name":"Maestre Domenech Evaristo",
    "wof:placetype":"venue"
},
  "geometry": {"coordinates":[-0.7966089845,38.4770317078],"type":"Point"}
}