{
  "type": "Feature",
  "properties": {
    "iso:country":"ES",
    "sg:address":"Pase Cauce, 69",
    "sg:city":"Valladolid",
    "sg:orig_category":"Asilos De Ancianos. Centros Privados",
    "sg:phone":"+34 983 39 77 44",
    "sg:postcode":"47005",
    "sg:province":"Valladolid",
    "wof:name":"Asociacion Castellano Leonesa De Servicios Sociales",
    "wof:placetype":"venue"
},
  "geometry": {"coordinates":[-4.7112522125,41.654384613],"type":"Point"}
}