{
  "type": "Feature",
  "properties": {
    "iso:country":"ES",
    "sg:address":"Calle de Talega, 8",
    "sg:city":"Albarracin",
    "sg:orig_category":"Artesan\u00cda Y Trabajos Manuales: Suministros (al Por Menor)",
    "sg:phone":"+34 978 71 01 10",
    "sg:postcode":"44100",
    "sg:province":"Teruel",
    "wof:name":"Vila Valero Esther",
    "wof:placetype":"venue"
},
  "geometry": {"coordinates":[-1.4442290068,40.4073143005],"type":"Point"}
}