{
  "type": "Feature",
  "properties": {
    "addr:full":"Calle de Cervantes, 58 Argamasilla Calatrava Ciudad Real 13440",
    "addr:housenumber":"58",
    "addr:postcode":"calatrava;13440",
    "addr:street":"Calle De Cervantes",
    "iso:country":"ES",
    "sg:address":"Calle de Cervantes, 58",
    "sg:city":"Argamasilla Calatrava",
    "sg:orig_category":"Mec\u00c1nico Del Autom\u00d3vil",
    "sg:phone":"+34 926 47 77 00",
    "sg:postcode":"13440",
    "sg:province":"Ciudad Real",
    "wof:name":"Talleres San Juan Lozano Garcia S.l.",
    "wof:placetype":"venue"
},
  "geometry": {"coordinates":[-4.0796370506,38.7278785706],"type":"Point"}
}