{
  "type": "Feature",
  "properties": {
    "iso:country":"ES",
    "sg:address":"Calle de Arrabal, S/n",
    "sg:city":"Pantoja",
    "sg:orig_category":"Peluqueros: De Se\u00d1oras",
    "sg:phone":"+34 925 55 45 45",
    "sg:postcode":"45290",
    "sg:province":"Toledo",
    "wof:name":"Nombela Perales Isabel",
    "wof:placetype":"venue"
},
  "geometry": {"coordinates":[-3.8376743793,40.0476570129],"type":"Point"}
}