{
  "type": "Feature",
  "properties": {
    "addr:full":"Calle de Pascual Y Genis, 14 Valencia Valencia 46002",
    "addr:housenumber":"14",
    "addr:postcode":"46002",
    "addr:street":"Calle De Pascual Y Genis",
    "iso:country":"ES",
    "sg:address":"Calle de Pascual Y Genis, 14",
    "sg:city":"Valencia",
    "sg:orig_category":"Camiser\u00cda Y Ropa Interior Masculina (al Por Menor)",
    "sg:phone":"+34 963 94 23 06",
    "sg:postcode":"46002",
    "sg:province":"Valencia",
    "wof:name":"Jimenez Galan Jose Luis",
    "wof:placetype":"venue"
},
  "geometry": {"coordinates":[-0.3739950061,39.4690361023],"type":"Point"}
}