{
  "type": "Feature",
  "properties": {
    "addr:full":"Cra Capuchinos, 73 Malaga M\u00e1laga 29013",
    "addr:housenumber":"73",
    "addr:postcode":"29013",
    "addr:street":"Capuchinos;Ma\u0301Laga",
    "iso:country":"ES",
    "sg:address":"Cra Capuchinos, 73",
    "sg:city":"Malaga",
    "sg:orig_category":"Peluqueros: De Se\u00d1oras",
    "sg:phone":"+34 952 65 20 57",
    "sg:postcode":"29013",
    "sg:province":"M\u00e1laga",
    "wof:name":"Alvarez Barranco Carmen",
    "wof:placetype":"venue"
},
  "geometry": {"coordinates":[-4.4117789268,36.7367668152],"type":"Point"}
}