{
  "type": "Feature",
  "properties": {
    "addr:full":"Calle de Mompeon Motos, 1 Zaragoza Zaragoza 50017",
    "addr:housenumber":"1",
    "addr:postcode":"50017",
    "addr:street":"Calle De",
    "iso:country":"ES",
    "sg:address":"Calle de Mompeon Motos, 1",
    "sg:city":"Zaragoza",
    "sg:orig_category":"Cajas Para Embalar",
    "sg:phone":"+34 976 30 00 13",
    "sg:postcode":"50017",
    "sg:province":"Zaragoza",
    "sg:website":"www.cajalon.es",
    "wof:name":"Caja Rural De Aragon S.coop Credito",
    "wof:placetype":"venue"
},
  "geometry": {"coordinates":[-0.9122059941,41.6512145996],"type":"Point"}
}