{
  "type": "Feature",
  "properties": {
    "addr:full":"Calle de Milanos, 8 Pinto Madrid 28320",
    "addr:housenumber":"8",
    "addr:postcode":"28320",
    "addr:street":"Calle De Milanos;Pinto",
    "iso:country":"ES",
    "sg:address":"Calle de Milanos, 8",
    "sg:city":"Pinto",
    "sg:orig_category":"Muebles, Minoristas",
    "sg:phone":"+34 916 92 41 62",
    "sg:postcode":"28320",
    "sg:province":"Madrid",
    "wof:name":"Sanchez Perez Oscar",
    "wof:placetype":"venue"
},
  "geometry": {"coordinates":[-3.7054920197,40.2492256165],"type":"Point"}
}