{
  "type": "Feature",
  "properties": {
    "addr:full":"Calle de San Jose, 41 Huelva Huelva 21002",
    "addr:housenumber":"41",
    "addr:postcode":"21002",
    "addr:street":"Calle De San",
    "iso:country":"ES",
    "sg:address":"Calle de San Jose, 41",
    "sg:city":"Huelva",
    "sg:orig_category":"Zapatos (al Por Menor)",
    "sg:phone":"+34 959 24 74 19",
    "sg:postcode":"21002",
    "sg:province":"Huelva",
    "wof:name":"Saavedra Suarez Josefa",
    "wof:placetype":"venue"
},
  "geometry": {"coordinates":[-6.9533572197,37.260307312],"type":"Point"}
}