{
  "type": "Feature",
  "properties": {
    "iso:country":"ES",
    "sg:address":"Barr Can Guasch, S/n",
    "sg:city":"Can Guasch",
    "sg:orig_category":"Deportes N\u00c1uticos, Acu\u00c1ticos Y Subacu\u00c1ticos: Art\u00cdculos Y Equipo (al Por Menor)",
    "sg:phone":"+34 971 80 70 33",
    "sg:postcode":"07840",
    "sg:province":"Islas Baleares",
    "wof:name":"Ibiza Painter S.l.",
    "wof:placetype":"venue"
},
  "geometry": {"coordinates":[1.5267180204,38.9829177856],"type":"Point"}
}