{
  "type": "Feature",
  "properties": {
    "addr:full":"Avda Cardenal Benlloch, 106 Valencia Valencia 46021",
    "addr:housenumber":"106",
    "addr:postcode":"46021",
    "addr:street":"Avda Cardenal Benlloch",
    "iso:country":"ES",
    "sg:address":"Avda Cardenal Benlloch, 106",
    "sg:city":"Valencia",
    "sg:orig_category":"M\u00c9dicos: Psiquiatr\u00cda",
    "sg:phone":"+34 963 61 21 64",
    "sg:postcode":"46021",
    "sg:province":"Valencia",
    "wof:name":"Soriano Perez Maria Jesus",
    "wof:placetype":"venue"
},
  "geometry": {"coordinates":[-0.3527640104,39.4743804932],"type":"Point"}
}