{
  "type": "Feature",
  "properties": {
    "iso:country":"ES",
    "sg:address":"Plaz Cristo De La Salud, S/n",
    "sg:city":"Arona",
    "sg:orig_category":"Administraciones Regionales, Departamentales Y Locales",
    "sg:phone":"+34 922 76 16 00",
    "sg:postcode":"38640",
    "sg:province":"Santa Cruz De Tenerife",
    "sg:website":"www.arona.org",
    "wof:name":"Ayuntamiento De Arona",
    "wof:placetype":"venue"
},
  "geometry": {"coordinates":[-16.6821880341,28.0520858765],"type":"Point"}
}