{
  "type": "Feature",
  "properties": {
    "addr:full":"Plaz Alhondiga (la), 19 Alagon Zaragoza 50630",
    "addr:postcode":"50630",
    "addr:street":"Plaz;La;Alagon",
    "iso:country":"ES",
    "sg:address":"Plaz Alhondiga (la), 19",
    "sg:city":"Alagon",
    "sg:orig_category":"Reposter\u00cdas",
    "sg:phone":"+34 976 61 04 87",
    "sg:postcode":"50630",
    "sg:province":"Zaragoza",
    "wof:name":"Barrios Lahera Anunciacion",
    "wof:placetype":"venue"
},
  "geometry": {"coordinates":[-1.1267240047,41.768196106],"type":"Point"}
}