{
  "type": "Feature",
  "properties": {
    "addr:full":"Calle de Alfonso Morales, 5 Irun Guip\u00f9zcoa 20303",
    "addr:housenumber":"5",
    "addr:postcode":"20303",
    "addr:street":"Calle De Alfonso Morales;Guipu\u0300Zcoa",
    "iso:country":"ES",
    "sg:address":"Calle de Alfonso Morales, 5",
    "sg:city":"Irun",
    "sg:orig_category":"Molduras, Junquillos, Listones Y Molduras Perforadas",
    "sg:phone":"+34 943 61 94 05",
    "sg:postcode":"20303",
    "sg:province":"Guip\u00f9zcoa",
    "wof:name":"Call Phone S.l.",
    "wof:placetype":"venue"
},
  "geometry": {"coordinates":[-1.7958846092,43.3386993408],"type":"Point"}
}