{
  "type": "Feature",
  "properties": {
    "addr:full":"Via Dos Castillas (de Las), 33 Pozuelo De Alarcon Madrid 28224",
    "addr:housenumber":"33",
    "addr:postcode":"28224",
    "addr:street":"Via Dos Castillas De Las",
    "iso:country":"ES",
    "sg:address":"Via Dos Castillas (de Las), 33",
    "sg:city":"Pozuelo De Alarcon",
    "sg:orig_category":"Asociaciones Humanitarias, De Cooperaci\u00d3n, De Acci\u00d3n Social",
    "sg:phone":"+34 917 15 93 82",
    "sg:postcode":"28224",
    "sg:province":"Madrid",
    "sg:website":"www.aesleme.es",
    "wof:name":"Asociacion Para El Estudio De La Lesion Medular Espinal",
    "wof:placetype":"venue"
},
  "geometry": {"coordinates":[-3.7855107784,40.4401626587],"type":"Point"}
}