{
  "type": "Feature",
  "properties": {
    "iso:country":"ES",
    "sg:address":"Calle de Juan Duque, 27",
    "sg:city":"Madrid",
    "sg:orig_category":"Ingenier\u00cda, Centros De Estudios (diversos)",
    "sg:phone":"+34 913 54 09 40",
    "sg:postcode":"28005",
    "sg:province":"Madrid",
    "wof:name":"Penagos Proyectos S.l.",
    "wof:placetype":"venue"
},
  "geometry": {"coordinates":[-3.7193629742,40.4105644226],"type":"Point"}
}