{
  "type": "Feature",
  "properties": {
    "iso:country":"ES",
    "sg:address":"Calle de Jeronimo Ibran, 19",
    "sg:city":"Mieres",
    "sg:orig_category":"Centros Empresariales",
    "sg:phone":"+34 985 46 11 04",
    "sg:postcode":"33600",
    "sg:province":"Asturias",
    "wof:name":"Asproden Servicios S. Coop.",
    "wof:placetype":"venue"
},
  "geometry": {"coordinates":[-5.773088932,43.2513694763],"type":"Point"}
}