{
  "type": "Feature",
  "properties": {
    "addr:full":"Calle de Escultor Marin Higuero, 12 Malaga M\u00e1laga 29017",
    "addr:housenumber":"12",
    "addr:postcode":"29017",
    "addr:street":"Calle De Escultor Marin Higuero;Ma\u0301Laga",
    "iso:country":"ES",
    "sg:address":"Calle de Escultor Marin Higuero, 12",
    "sg:city":"Malaga",
    "sg:orig_category":"Cr\u00cda De Animales",
    "sg:phone":"+34 952 20 12 49",
    "sg:postcode":"29017",
    "sg:province":"M\u00e1laga",
    "wof:name":"Alcala-zamora Sanchez Luis Julio",
    "wof:placetype":"venue"
},
  "geometry": {"coordinates":[-4.3646006584,36.7199554443],"type":"Point"}
}