{
  "type": "Feature",
  "properties": {
    "addr:full":"Avda Reyes Catolicos, 142 Villarrobledo Albacete 02600",
    "addr:housenumber":"142",
    "addr:postcode":"02600",
    "addr:street":"Avda Reyes Catolicos",
    "iso:country":"ES",
    "sg:address":"Avda Reyes Catolicos, 142",
    "sg:city":"Villarrobledo",
    "sg:orig_category":"Alquiler De Gr\u00daas",
    "sg:phone":"+34 967 14 21 50",
    "sg:postcode":"02600",
    "sg:province":"Albacete",
    "sg:website":"www.laguiatalleresygruas.com",
    "wof:name":"La Guia Gutierrez Joaquin",
    "wof:placetype":"venue"
},
  "geometry": {"coordinates":[-2.5916728973,39.2760658264],"type":"Point"}
}