{
  "type": "Feature",
  "properties": {
    "iso:country":"ES",
    "sg:address":"Pg Ferrocarrils Catalans, 231",
    "sg:city":"Cornella Llobregat",
    "sg:orig_category":"Restaurantes",
    "sg:phone":"+34 933 77 26 02",
    "sg:postcode":"08940",
    "sg:province":"Barcelona",
    "wof:name":"Restaurant Famadas S.l.",
    "wof:placetype":"venue"
},
  "geometry": {"coordinates":[2.0848701,41.3533782959],"type":"Point"}
}