{
  "type": "Feature",
  "properties": {
    "addr:full":"Av Castell D'aro, 114 Platja D'aro Girona 17250",
    "addr:housenumber":"114",
    "addr:postcode":"17250",
    "addr:street":"Av Castell D'Aro",
    "iso:country":"ES",
    "sg:address":"Av Castell D'aro, 114",
    "sg:city":"Platja D'aro",
    "sg:orig_category":"Fabricaci\u00d3n, Reparaci\u00d3n Y Mantenimiento De Construcciones Navales Y Fluviales",
    "sg:phone":"+34 972 81 76 12",
    "sg:postcode":"17250",
    "sg:province":"Girona",
    "wof:name":"Nautica Casas S.a.",
    "wof:placetype":"venue"
},
  "geometry": {"coordinates":[2.8271551132,41.988822937],"type":"Point"}
}