{
  "type": "Feature",
  "properties": {
    "iso:country":"ES",
    "sg:address":"Calle de Villanueva, 31",
    "sg:city":"Madrid",
    "sg:orig_category":"Inmobiliaria (agencias)",
    "sg:phone":"+34 917 81 40 52",
    "sg:postcode":"28001",
    "sg:province":"Madrid",
    "wof:name":"Rojas Silva Mario",
    "wof:placetype":"venue"
},
  "geometry": {"coordinates":[-3.6831810474,40.4222755432],"type":"Point"}
}