{
  "type": "Feature",
  "properties": {
    "iso:country":"ES",
    "sg:address":"Vilafria, 15",
    "sg:city":"Vilafria",
    "sg:orig_category":"Electrodom\u00c9sticos (al Por Menor)",
    "sg:phone":"+34 986 33 64 28",
    "sg:postcode":"36418",
    "sg:province":"Pontevedra",
    "wof:name":"Martinez Giraldez Manuel",
    "wof:placetype":"venue"
},
  "geometry": {"coordinates":[-8.617515564,42.1448669434],"type":"Point"}
}