{
  "type": "Feature",
  "properties": {
    "addr:full":"Carrer de Canyelles (de), 3 Tarragona Tarragona 43001",
    "addr:postcode":"43001",
    "addr:street":"Carrer De Canyelles De 3",
    "iso:country":"ES",
    "sg:address":"Carrer de Canyelles (de), 3",
    "sg:city":"Tarragona",
    "sg:orig_category":"Peluqueros: De Se\u00d1oras",
    "sg:phone":"+34 977 23 78 25",
    "sg:postcode":"43001",
    "sg:province":"Tarragona",
    "wof:name":"Aranega Garcia Ana Maria",
    "wof:placetype":"venue"
},
  "geometry": {"coordinates":[1.2502012253,41.116104126],"type":"Point"}
}