{
  "type": "Feature",
  "properties": {
    "addr:full":"La Vega, 79 Armellada Le\u00f3n 24284",
    "addr:housenumber":"79",
    "addr:postcode":"24284",
    "addr:street":"La Vega;Leo\u0301N",
    "iso:country":"ES",
    "sg:address":"La Vega, 79",
    "sg:city":"Armellada",
    "sg:orig_category":"Carnicer\u00cdas, Carnicer\u00cdas",
    "sg:phone":"+34 987 36 35 40",
    "sg:postcode":"24284",
    "sg:province":"Le\u00f3n",
    "wof:name":"Martinez Alvarez Manuel",
    "wof:placetype":"venue"
},
  "geometry": {"coordinates":[-5.8642177582,42.5517501831],"type":"Point"}
}