{
  "type": "Feature",
  "properties": {
    "iso:country":"ES",
    "sg:address":"Calle de San Bartolome, 5",
    "sg:city":"Moclinejo",
    "sg:orig_category":"Comerciantes Al Por Mayor De Vinos, Licores Y Alcoholes",
    "sg:phone":"+34 952 40 05 60",
    "sg:postcode":"29738",
    "sg:province":"M\u00e1laga",
    "wof:name":"Distribuidora Moclinejense De Bebidas S.l.",
    "wof:placetype":"venue"
},
  "geometry": {"coordinates":[-4.2541618347,36.7715835571],"type":"Point"}
}