{
  "type": "Feature",
  "properties": {
    "iso:country":"ES",
    "sg:address":"Pol Ind La Vega, S/n",
    "sg:city":"Priego Cordoba",
    "sg:orig_category":"Filtros Y Elementos Filtradores",
    "sg:phone":"+34 957 70 05 54",
    "sg:postcode":"14800",
    "sg:province":"C\u00f3rdoba",
    "sg:website":"www.mafair.com",
    "wof:name":"Mafair S.a.",
    "wof:placetype":"venue"
},
  "geometry": {"coordinates":[-4.1962990761,37.4413757324],"type":"Point"}
}