{
  "type": "Feature",
  "properties": {
    "iso:country":"ES",
    "sg:address":"Altzutzate, S/n",
    "sg:city":"Huarte",
    "sg:orig_category":"Automatizaci\u00d3n De Procesos Industriales Y De Edificaci\u00d3n (estudios, Instalaci\u00d3n)",
    "sg:phone":"+34 948 33 35 39",
    "sg:postcode":"31620",
    "sg:province":"Navarra",
    "wof:name":"Master Navarra Automatismos S.l.",
    "wof:placetype":"venue"
},
  "geometry": {"coordinates":[-1.6038600206,42.8225440979],"type":"Point"}
}