{
  "type": "Feature",
  "properties": {
    "addr:full":"Carrer de Santa Catalina, 51 Barcelona Barcelona 08014",
    "addr:housenumber":"51",
    "addr:postcode":"08014",
    "addr:street":"Carrer De Santa Catalina",
    "iso:country":"ES",
    "sg:address":"Carrer de Santa Catalina, 51",
    "sg:city":"Barcelona",
    "sg:orig_category":"Molduras, Junquillos, Listones Y Molduras Perforadas",
    "sg:phone":"+34 934 90 03 08",
    "sg:postcode":"08014",
    "sg:province":"Barcelona",
    "wof:name":"Vazquez Hervella Cecilia",
    "wof:placetype":"venue"
},
  "geometry": {"coordinates":[2.135696888,41.3796577454],"type":"Point"}
}