{
  "type": "Feature",
  "properties": {
    "iso:country":"ES",
    "sg:address":"Avda Encartaciones, S/n",
    "sg:city":"Balmaseda",
    "sg:orig_category":"Aguas (distribuci\u00d3n, Servicios)",
    "sg:phone":"+34 946 10 30 04",
    "sg:postcode":"48800",
    "sg:province":"Vizcaya",
    "wof:name":"Consorcio De Aguas Bilbao Bizkaia",
    "wof:placetype":"venue"
},
  "geometry": {"coordinates":[-3.1979160309,43.192024231],"type":"Point"}
}