{
  "type": "Feature",
  "properties": {
    "iso:country":"ES",
    "sg:address":"Calle de Arganda, 27",
    "sg:city":"Madrid",
    "sg:orig_category":"Aparatos, Sistemas De Tele",
    "sg:phone":"+34 915 17 08 10",
    "sg:postcode":"28005",
    "sg:province":"Madrid",
    "wof:name":"Ekintza Seguridad S.l.",
    "wof:placetype":"venue"
},
  "geometry": {"coordinates":[-3.7049541473,40.3984031677],"type":"Point"}
}