{
  "type": "Feature",
  "properties": {
    "iso:country":"ES",
    "sg:address":"Carrer de Escoles Pies, 62",
    "sg:city":"Barcelona",
    "sg:orig_category":"Reposter\u00cdas",
    "sg:phone":"+34 932 11 37 01",
    "sg:postcode":"08017",
    "sg:province":"Barcelona",
    "wof:name":"Oliveros Traveset Neus",
    "wof:placetype":"venue"
},
  "geometry": {"coordinates":[2.1313869953,41.4001426697],"type":"Point"}
}