{
  "type": "Feature",
  "properties": {
    "addr:full":"Calle de Francisco Gourie, 101 Palmas De Gran Canaria Las Palmas 35002",
    "addr:housenumber":"101",
    "addr:postcode":"35002",
    "addr:street":"Calle De Francisco Gourie",
    "iso:country":"ES",
    "sg:address":"Calle de Francisco Gourie, 101",
    "sg:city":"Palmas De Gran Canaria",
    "sg:orig_category":"Bazares, Art\u00cdculos De Limpieza Y De Cocina (al Por Menor)",
    "sg:phone":"+34 928 36 38 00",
    "sg:postcode":"35002",
    "sg:province":"Las Palmas",
    "wof:name":"Viyao S.l.",
    "wof:placetype":"venue"
},
  "geometry": {"coordinates":[-15.4155921936,28.1058616638],"type":"Point"}
}