{
  "type": "Feature",
  "properties": {
    "addr:full":"Figueroles, 1 Manises Valencia 46940",
    "addr:housenumber":"1",
    "addr:postcode":"46940",
    "addr:street":"Figueroles",
    "iso:country":"ES",
    "sg:address":"Figueroles, 1",
    "sg:city":"Manises",
    "sg:orig_category":"Controles De Edificaci\u00d3n (construcci\u00d3n, Seguridad)",
    "sg:phone":"+34 961 52 01 09",
    "sg:postcode":"46940",
    "sg:province":"Valencia",
    "wof:name":"Obra Civil Canoper S.l.",
    "wof:placetype":"venue"
},
  "geometry": {"coordinates":[-0.4730559886,39.4983711243],"type":"Point"}
}