{
  "type": "Feature",
  "properties": {
    "addr:full":"Pl. Neda, 2 Algeciras C\u00e1diz 11201",
    "addr:housenumber":"2;ca\u0301diz",
    "addr:postcode":"11201",
    "addr:street":"Neda",
    "iso:country":"ES",
    "sg:address":"Pl. Neda, 2",
    "sg:city":"Algeciras",
    "sg:orig_category":"Molduras, Junquillos, Listones Y Molduras Perforadas",
    "sg:phone":"+34 956 63 34 05",
    "sg:postcode":"11201",
    "sg:province":"C\u00e1diz",
    "wof:name":"Sistelcom-telemensaje S.a.",
    "wof:placetype":"venue"
},
  "geometry": {"coordinates":[-5.4495739937,36.1325683594],"type":"Point"}
}