{
  "type": "Feature",
  "properties": {
    "addr:full":"Calle de Virgen Del Pilar, 1 Palmas De Gran Canaria Las Palmas 35012",
    "addr:housenumber":"1",
    "addr:postcode":"35012",
    "addr:street":"Calle De Virgen Del Pilar",
    "iso:country":"ES",
    "sg:address":"Calle de Virgen Del Pilar, 1",
    "sg:city":"Palmas De Gran Canaria",
    "sg:orig_category":"Quiropr\u00c1cticos",
    "sg:phone":"+34 928 42 09 67",
    "sg:postcode":"35012",
    "sg:province":"Las Palmas",
    "wof:name":"Belfir Grupo Peluqueros; S.l.",
    "wof:placetype":"venue"
},
  "geometry": {"coordinates":[-15.4444255829,28.1167316437],"type":"Point"}
}