{
  "type": "Feature",
  "properties": {
    "iso:country":"ES",
    "sg:address":"Calle de Higueras, 37",
    "sg:city":"Madrid",
    "sg:orig_category":"Carnicer\u00cdas, Carnicer\u00cdas",
    "sg:phone":"+34 914 79 41 71",
    "sg:postcode":"28011",
    "sg:province":"Madrid",
    "wof:name":"Gomez Aleman Jose",
    "wof:placetype":"venue"
},
  "geometry": {"coordinates":[-3.7448840141,40.4061927795],"type":"Point"}
}