{
  "type": "Feature",
  "properties": {
    "iso:country":"ES",
    "sg:address":"Calle de Fuenclara, 41",
    "sg:city":"Villanueva Arzobispo",
    "sg:orig_category":"Cajas Y Embalajes De Madera",
    "sg:phone":"+34 953 45 07 98",
    "sg:postcode":"23330",
    "sg:province":"Ja\u00e9n",
    "wof:name":"Sanchez Secaduras Manuel Y Otros C.b.",
    "wof:placetype":"venue"
},
  "geometry": {"coordinates":[-3.0072090626,38.1666641235],"type":"Point"}
}