{
  "type": "Feature",
  "properties": {
    "addr:full":"Plaz Pavona, 1 Villacastin Segovia 40150",
    "addr:housenumber":"1",
    "addr:postcode":"40150",
    "addr:street":"Plaz Pavona",
    "iso:country":"ES",
    "sg:address":"Plaz Pavona, 1",
    "sg:city":"Villacastin",
    "sg:orig_category":"Parques De Atracciones Y Centros De Esparcimiento",
    "sg:phone":"+34 921 19 70 01",
    "sg:postcode":"40150",
    "sg:province":"Segovia",
    "wof:name":"Gonzalez Maria Maria Gloria",
    "wof:placetype":"venue"
},
  "geometry": {"coordinates":[-4.4138379097,40.7807350159],"type":"Point"}
}