{
  "type": "Feature",
  "properties": {
    "addr:full":"Calle de Postigos, S/n Santiago Espada Ja\u00e9n 23290",
    "addr:housenumber":"s / n",
    "addr:postcode":"23290",
    "addr:street":"Calle De Postigos;Jae\u0301N",
    "iso:country":"ES",
    "sg:address":"Calle de Postigos, S/n",
    "sg:city":"Santiago Espada",
    "sg:orig_category":"Centros De Educaci\u00d3n Especial",
    "sg:phone":"+34 953 43 82 83",
    "sg:postcode":"23290",
    "sg:province":"Ja\u00e9n",
    "wof:name":"Delegacion Provincial De La Consejeria De Educacion De La Junta De Andalucia",
    "wof:placetype":"venue"
},
  "geometry": {"coordinates":[-2.5501170158,38.1117782593],"type":"Point"}
}