{
  "type": "Feature",
  "properties": {
    "iso:country":"ES",
    "sg:address":"Calle de Foglietti, 1",
    "sg:city":"Alacant",
    "sg:orig_category":"Panader\u00cdas, Panader\u00cdas",
    "sg:phone":"+34 965 13 00 92",
    "sg:postcode":"03007",
    "sg:province":"Alicante",
    "wof:name":"Confiterias La Murciana S.l.",
    "wof:placetype":"venue"
},
  "geometry": {"coordinates":[-0.4942739904,38.3408737183],"type":"Point"}
}