{
  "type": "Feature",
  "properties": {
    "iso:country":"ES",
    "sg:address":"Calle de Juan De Mata Carriazo, S/n",
    "sg:city":"Sevilla",
    "sg:orig_category":"Frutas, Legumbres Frescas Y Tempranas (al Por Menor)",
    "sg:phone":"+34 954 53 66 25",
    "sg:postcode":"41018",
    "sg:province":"Sevilla",
    "wof:name":"Perez Martinez Joaquin Angel",
    "wof:placetype":"venue"
},
  "geometry": {"coordinates":[-5.983754158,37.3825263977],"type":"Point"}
}