{
  "type": "Feature",
  "properties": {
    "addr:full":"Doc L Pi\u00f1ero-t Ferrandis, 9 Altura Castell\u00f3n 12410",
    "addr:housenumber":"9",
    "addr:postcode":"12410",
    "addr:street":"Doc L Pin\u0303Ero-T Ferrandis",
    "iso:country":"ES",
    "sg:address":"Doc L Pi\u00f1ero-t Ferrandis, 9",
    "sg:city":"Altura",
    "sg:orig_category":"Escayola Y Productos De Escayola (fabricaci\u00d3n, Al Por Mayor)",
    "sg:phone":"+34 964 14 60 10",
    "sg:postcode":"12410",
    "sg:province":"Castell\u00f3n",
    "wof:name":"Rovira Zarzoso Antonio",
    "wof:placetype":"venue"
},
  "geometry": {"coordinates":[-0.5144039989,39.8478736877],"type":"Point"}
}