{
  "type": "Feature",
  "properties": {
    "iso:country":"ES",
    "sg:address":"Alam Colon, 34",
    "sg:city":"Malaga",
    "sg:orig_category":"Asilos De Ancianos. Centros Privados",
    "sg:phone":"+34 952 21 39 94",
    "sg:postcode":"29001",
    "sg:province":"M\u00e1laga",
    "wof:name":"Carrera Merino Juan Carlos",
    "wof:placetype":"venue"
},
  "geometry": {"coordinates":[-4.42395401,36.7134666443],"type":"Point"}
}