{
  "type": "Feature",
  "properties": {
    "addr:full":"Calle de Goya, 52 Cordoba C\u00f3rdoba 14011",
    "addr:housenumber":"52",
    "addr:postcode":"14011",
    "addr:street":"Calle De Goya;Co\u0301Rdoba",
    "iso:country":"ES",
    "sg:address":"Calle de Goya, 52",
    "sg:city":"Cordoba",
    "sg:orig_category":"Fotograf\u00cda Art\u00cdstica Y Retratos",
    "sg:phone":"+34 957 28 11 56",
    "sg:postcode":"14011",
    "sg:province":"C\u00f3rdoba",
    "wof:name":"Torres Morillo Juan Antonio",
    "wof:placetype":"venue"
},
  "geometry": {"coordinates":[-4.7881789207,37.8928146362],"type":"Point"}
}