{
  "type": "Feature",
  "properties": {
    "iso:country":"ES",
    "sg:address":"Calle de Donantes De Sangre, 14",
    "sg:city":"Haro",
    "sg:orig_category":"Peluqueros: De Se\u00d1oras",
    "sg:phone":"+34 941 30 34 00",
    "sg:postcode":"26200",
    "sg:province":"La Rioja",
    "wof:name":"Mu\u00f1oz Saenz Encarnacion",
    "wof:placetype":"venue"
},
  "geometry": {"coordinates":[-2.8484592438,42.5731163025],"type":"Point"}
}