{
  "type": "Feature",
  "properties": {
    "iso:country":"ES",
    "sg:address":"Calle de Santo Tomas, 1",
    "sg:city":"Segovia",
    "sg:orig_category":"M\u00c9dicos: An\u00c1lisis Cl\u00cdnicos",
    "sg:phone":"+34 921 43 76 27",
    "sg:postcode":"40002",
    "sg:province":"Segovia",
    "wof:name":"Sanchez-valverde Gil Pablo",
    "wof:placetype":"venue"
},
  "geometry": {"coordinates":[-4.1186990738,40.9439620972],"type":"Point"}
}