{
  "type": "Feature",
  "properties": {
    "addr:full":"Avda Santa Marina, 11 Badajoz Badajoz 06005",
    "addr:housenumber":"11",
    "addr:postcode":"06005",
    "addr:street":"Avda Santa Marina",
    "iso:country":"ES",
    "sg:address":"Avda Santa Marina, 11",
    "sg:city":"Badajoz",
    "sg:orig_category":"Asesor\u00cda Sobre Comunicaci\u00d3n De Empresas",
    "sg:phone":"+34 924 23 27 36",
    "sg:postcode":"06005",
    "sg:province":"Badajoz",
    "sg:website":"www.amadormata.com",
    "wof:name":"Asesorias Amador Mata S.l.",
    "wof:placetype":"venue"
},
  "geometry": {"coordinates":[-6.9765915871,38.8738975525],"type":"Point"}
}