{
  "type": "Feature",
  "properties": {
    "addr:full":"Carrer de Sant Francesc, 42 Sarral Tarragona 43424",
    "addr:housenumber":"42",
    "addr:postcode":"43424",
    "addr:street":"Carrer De Sant Francesc",
    "iso:country":"ES",
    "sg:address":"Carrer de Sant Francesc, 42",
    "sg:city":"Sarral",
    "sg:orig_category":"Arquitectos",
    "sg:phone":"+34 977 89 01 10",
    "sg:postcode":"43424",
    "sg:province":"Tarragona",
    "wof:name":"Puig Torne Jose",
    "wof:placetype":"venue"
},
  "geometry": {"coordinates":[1.2474069595,41.4443778992],"type":"Point"}
}