{
  "type": "Feature",
  "properties": {
    "addr:full":"Plaz Goleta, De La, 1 Melilla Melilla 52006",
    "addr:housenumber":"1",
    "addr:postcode":"52006",
    "addr:street":"Plaz;De La",
    "iso:country":"ES",
    "sg:address":"Plaz Goleta, De La, 1",
    "sg:city":"Melilla",
    "sg:orig_category":"Agentes Generales De Seguros",
    "sg:phone":"+34 952 67 77 76",
    "sg:postcode":"52006",
    "sg:province":"Melilla",
    "wof:name":"Arrieta Uroz Mariano",
    "wof:placetype":"venue"
},
  "geometry": {"coordinates":[-2.9395914078,35.279800415],"type":"Point"}
}