{
  "type": "Feature",
  "properties": {
    "iso:country":"ES",
    "sg:address":"La Maquinista (ciutat Asuncion), 53",
    "sg:city":"Barcelona",
    "sg:orig_category":"Comercio De Piezas De Recambio Y De Accesorios De Veh\u00cdculos, Veh\u00cdculos Industriales",
    "sg:phone":"+34 933 60 89 90",
    "sg:postcode":"08030",
    "sg:province":"Barcelona",
    "sg:website":"www.lamaquinista.es",
    "wof:name":"Autocenter Racing S.l.",
    "wof:placetype":"venue"
},
  "geometry": {"coordinates":[2.1966180801,41.4378700256],"type":"Point"}
}