{
  "type": "Feature",
  "properties": {
    "iso:country":"ES",
    "sg:address":"Calle de Fuenterrabia, 17",
    "sg:city":"Donostia-san Sebastian",
    "sg:orig_category":"Confecci\u00d3n De Trajes Para Se\u00d1oras",
    "sg:phone":"+34 943 42 71 74",
    "sg:postcode":"20005",
    "sg:province":"Guip\u00f9zcoa",
    "wof:name":"Mansoa Alkorta Elena",
    "wof:placetype":"venue"
},
  "geometry": {"coordinates":[-1.9812819958,43.3178215027],"type":"Point"}
}