{
  "type": "Feature",
  "properties": {
    "addr:full":"Carrer de Faraday, 160 Terrassa Barcelona 08224",
    "addr:housenumber":"160",
    "addr:postcode":"08224",
    "addr:street":"Carrer De Faraday",
    "iso:country":"ES",
    "sg:address":"Carrer de Faraday, 160",
    "sg:city":"Terrassa",
    "sg:orig_category":"Peluquer\u00cdas, Peluquer\u00cda Mixta",
    "sg:phone":"+34 937 88 42 23",
    "sg:postcode":"08224",
    "sg:province":"Barcelona",
    "wof:name":"Ribera Riera Cristina",
    "wof:placetype":"venue"
},
  "geometry": {"coordinates":[2.0025269985,41.5615158081],"type":"Point"}
}