{
  "type": "Feature",
  "properties": {
    "iso:country":"ES",
    "sg:address":"Calle de Casimiro Sainz, 42",
    "sg:city":"Matamorosa",
    "sg:orig_category":"Molduras, Junquillos, Listones Y Molduras Perforadas",
    "sg:phone":"+34 942 75 24 16",
    "sg:postcode":"39200",
    "sg:province":"Cantabria",
    "wof:name":"Perez Sanchez Maria Luisa",
    "wof:placetype":"venue"
},
  "geometry": {"coordinates":[-4.1473112106,42.9850006104],"type":"Point"}
}