{
  "type": "Feature",
  "properties": {
    "addr:full":"Calle de Kasune, 56 Algorta Vizcaya 48991",
    "addr:housenumber":"56",
    "addr:postcode":"48991",
    "addr:street":"Calle De Kasune",
    "iso:country":"ES",
    "sg:address":"Calle de Kasune, 56",
    "sg:city":"Algorta",
    "sg:orig_category":"Molduras, Junquillos, Listones Y Molduras Perforadas",
    "sg:phone":"+34 944 30 00 50",
    "sg:postcode":"48991",
    "sg:province":"Vizcaya",
    "wof:name":"Serrano Chamorro Miguel",
    "wof:placetype":"venue"
},
  "geometry": {"coordinates":[-3.0082640648,43.3550300598],"type":"Point"}
}