{
  "type": "Feature",
  "properties": {
    "iso:country":"ES",
    "sg:address":"Ptge Boada Vell, 45",
    "sg:city":"Poligon Industrial Riera De Caldes",
    "sg:orig_category":"Fabricaci\u00d3n De Telas Y Sedas",
    "sg:phone":"+34 938 64 52 22",
    "sg:postcode":"08184",
    "sg:province":"Barcelona",
    "wof:name":"Ravial S. A.",
    "wof:placetype":"venue"
},
  "geometry": {"coordinates":[2.181032896,41.5802307129],"type":"Point"}
}