{
  "type": "Feature",
  "properties": {
    "addr:full":"Calle de Martinez Izquierdo, 45 Madrid Madrid 28028",
    "addr:housenumber":"45",
    "addr:postcode":"madrid;28028",
    "addr:street":"Calle De Martinez Izquierdo",
    "iso:country":"ES",
    "sg:address":"Calle de Martinez Izquierdo, 45",
    "sg:city":"Madrid",
    "sg:orig_category":"Peluqueros: De Se\u00d1oras",
    "sg:phone":"+34 913 55 51 49",
    "sg:postcode":"28028",
    "sg:province":"Madrid",
    "wof:name":"Sanchez Blanco Maria Victoria",
    "wof:placetype":"venue"
},
  "geometry": {"coordinates":[-3.6666600704,40.4350967407],"type":"Point"}
}