{
  "type": "Feature",
  "properties": {
    "addr:full":"Canar, S/n Sta. Eularia Riu Islas Baleares 07840",
    "addr:housenumber":"/ n",
    "addr:postcode":"07840",
    "addr:street":"Canar S;Islas Baleares",
    "iso:country":"ES",
    "sg:address":"Canar, S/n",
    "sg:city":"Sta. Eularia Riu",
    "sg:orig_category":"Doctores En Medicina",
    "sg:phone":"+34 971 33 88 18",
    "sg:postcode":"07840",
    "sg:province":"Islas Baleares",
    "wof:name":"Ciria Uriarte Alberto",
    "wof:placetype":"venue"
},
  "geometry": {"coordinates":[1.547279954,38.9919815063],"type":"Point"}
}