{
  "type": "Feature",
  "properties": {
    "addr:full":"Calle de Rodrigo De Triana, 2 Madrid Madrid 28017",
    "addr:housenumber":"2",
    "addr:postcode":"28017",
    "addr:street":"Calle De Rodrigo De Triana",
    "iso:country":"ES",
    "sg:address":"Calle de Rodrigo De Triana, 2",
    "sg:city":"Madrid",
    "sg:orig_category":"Importaci\u00d3n",
    "sg:phone":"+34 913 27 11 15",
    "sg:postcode":"28017",
    "sg:province":"Madrid",
    "wof:name":"Janeiro Blazquez Rodrigo",
    "wof:placetype":"venue"
},
  "geometry": {"coordinates":[-3.6315619946,40.4205474854],"type":"Point"}
}