{
  "type": "Feature",
  "properties": {
    "addr:full":"Carrer de Joaquim Rubio I Ors, 20 S. Boi Llobregat Barcelona 08830",
    "addr:housenumber":"20",
    "addr:postcode":"08830",
    "addr:street":"Carrer De Joaquim Rubio;Ors",
    "iso:country":"ES",
    "sg:address":"Carrer de Joaquim Rubio I Ors, 20",
    "sg:city":"S. Boi Llobregat",
    "sg:orig_category":"Pescader\u00cdas (al Por Menor)",
    "sg:phone":"+34 936 30 62 34",
    "sg:postcode":"08830",
    "sg:province":"Barcelona",
    "wof:name":"Jimenez Mancha Manuel",
    "wof:placetype":"venue"
},
  "geometry": {"coordinates":[2.0290720463,41.3484153748],"type":"Point"}
}