{
  "type": "Feature",
  "properties": {
    "iso:country":"ES",
    "sg:address":"Calle de Miguel Hernandez, 12",
    "sg:city":"Villaobispo De Las Regueras",
    "sg:orig_category":"Centros Empresariales",
    "sg:phone":"+34 987 30 75 39",
    "sg:postcode":"24007",
    "sg:province":"Le\u00f3n",
    "sg:website":"www.paginasamarillas.es",
    "wof:name":"Atekal Mantenimiento S.l.l.",
    "wof:placetype":"venue"
},
  "geometry": {"coordinates":[-5.55200243,42.6143684387],"type":"Point"}
}