{
  "type": "Feature",
  "properties": {
    "iso:country":"ES",
    "sg:address":"Ptda Cotes Baixes, S/n",
    "sg:city":"Alcoi",
    "sg:classifiers":[
        {
            "category":"Banks & Credit Unions",
            "subcategory":"Bureau De Change",
            "type":"Services"
        }
    ],
    "sg:phone":"+34 965 33 69 82",
    "sg:postcode":"03804",
    "sg:province":"Alicante",
    "sg:tags":[
        "organismos",
        "control"
    ],
    "wof:name":"Consejo Regulador De Licores Tradicionales De Alicante",
    "wof:placetype":"venue"
},
  "geometry": {"coordinates":[-0.4650489986,38.712688446],"type":"Point"}
}