{
  "type": "Feature",
  "properties": {
    "addr:full":"Calle de Gonzalez Silva, 15 Cisterniga Valladolid 47193",
    "addr:housenumber":"15",
    "addr:postcode":"47193",
    "addr:street":"Calle De Gonzalez Silva",
    "iso:country":"ES",
    "sg:address":"Calle de Gonzalez Silva, 15",
    "sg:city":"Cisterniga",
    "sg:orig_category":"Ense\u00d1anza Variada",
    "sg:phone":"+34 983 40 25 80",
    "sg:postcode":"47193",
    "sg:province":"Valladolid",
    "wof:name":"Santos Velasco Ana Isabel",
    "wof:placetype":"venue"
},
  "geometry": {"coordinates":[-4.6858711243,41.6110801697],"type":"Point"}
}