{
  "type": "Feature",
  "properties": {
    "iso:country":"ES",
    "sg:address":"Calle de Concejal Garcia Feo, 30",
    "sg:city":"Palmas De Gran Canaria",
    "sg:orig_category":"Agencias Y Agentes Comerciales, Representantes",
    "sg:phone":"+34 928 22 00 72",
    "sg:postcode":"35011",
    "sg:province":"Las Palmas",
    "wof:name":"Absolute Marketing And Events",
    "wof:placetype":"venue"
},
  "geometry": {"coordinates":[-15.438874,28.121981],"type":"Point"}
}