{
  "type": "Feature",
  "properties": {
    "addr:full":"Carr Poeta Querol, 10 Oliva Valencia 46780",
    "addr:housenumber":"10",
    "addr:postcode":"46780",
    "addr:street":"Carr Poeta Querol",
    "iso:country":"ES",
    "sg:address":"Carr Poeta Querol, 10",
    "sg:city":"Oliva",
    "sg:orig_category":"Bisuter\u00cda, Joyer\u00cda, Relojer\u00cda (al Por Menor)",
    "sg:phone":"+34 962 85 03 41",
    "sg:postcode":"46780",
    "sg:province":"Valencia",
    "wof:name":"Moncho Fenollar Vicente",
    "wof:placetype":"venue"
},
  "geometry": {"coordinates":[-0.1178290024,38.9200210571],"type":"Point"}
}