{
  "type": "Feature",
  "properties": {
    "iso:country":"ES",
    "sg:address":"Calle de Doctor Lozano, 16",
    "sg:city":"Madrid",
    "sg:orig_category":"Alimentaci\u00d3n General (al Por Menor)",
    "sg:phone":"+34 915 51 10 84",
    "sg:postcode":"28038",
    "sg:province":"Madrid",
    "wof:name":"Sanchez Torremocha Ildefonso",
    "wof:placetype":"venue"
},
  "geometry": {"coordinates":[-3.6600430012,40.4031257629],"type":"Point"}
}