{
  "type": "Feature",
  "properties": {
    "addr:full":"Calle de Gomez Arias, 21 Salamanca Salamanca 37006",
    "addr:housenumber":"21",
    "addr:postcode":"37006",
    "addr:street":"Calle De Gomez Arias",
    "iso:country":"ES",
    "sg:address":"Calle de Gomez Arias, 21",
    "sg:city":"Salamanca",
    "sg:orig_category":"Pescader\u00cdas (al Por Menor)",
    "sg:phone":"+34 923 24 36 51",
    "sg:postcode":"37006",
    "sg:province":"Salamanca",
    "wof:name":"Simon Enrique Josefa",
    "wof:placetype":"venue"
},
  "geometry": {"coordinates":[-5.6640181541,40.9750022888],"type":"Point"}
}