{
  "type": "Feature",
  "properties": {
    "addr:full":"Calle de Sierra De Guadarrama, 10 Arganda Madrid 28500",
    "addr:housenumber":"10",
    "addr:postcode":"28500",
    "addr:street":"Calle De Sierra De Guadarrama",
    "iso:country":"ES",
    "sg:address":"Calle de Sierra De Guadarrama, 10",
    "sg:city":"Arganda",
    "sg:orig_category":"Transformaci\u00d3n De Materias Pl\u00c1sticas",
    "sg:phone":"+34 918 71 95 69",
    "sg:postcode":"28500",
    "sg:province":"Madrid",
    "wof:name":"Semiplast S.l.",
    "wof:placetype":"venue"
},
  "geometry": {"coordinates":[-3.4763998985,40.307308197],"type":"Point"}
}