{
  "type": "Feature",
  "properties": {
    "iso:country":"ES",
    "sg:address":"Calle de Caballeros, 16",
    "sg:city":"Avila",
    "sg:orig_category":"Psic\u00d3logos",
    "sg:phone":"+34 920 25 68 19",
    "sg:postcode":"05001",
    "sg:province":"\u00c1vila",
    "wof:name":"Mu\u00f1oz Garcia Benjamin",
    "wof:placetype":"venue"
},
  "geometry": {"coordinates":[-4.7004513741,40.6552314758],"type":"Point"}
}