{
  "type": "Feature",
  "properties": {
    "addr:full":"Pg Ramon Berenguer Iii, 75 Mataro Barcelona 08303",
    "addr:housenumber":"75",
    "addr:postcode":"08303",
    "addr:street":"Mataro Barcelona",
    "iso:country":"ES",
    "sg:address":"Pg Ramon Berenguer Iii, 75",
    "sg:city":"Mataro",
    "sg:orig_category":"Farmacias",
    "sg:phone":"+34 937 57 90 93",
    "sg:postcode":"08303",
    "sg:province":"Barcelona",
    "wof:name":"Corona Pol Maria Rosa",
    "wof:placetype":"venue"
},
  "geometry": {"coordinates":[2.4246799946,41.537071228],"type":"Point"}
}