{
  "type": "Feature",
  "properties": {
    "iso:country":"ES",
    "sg:address":"Pol Ind La Espartera, S/n",
    "sg:city":"Benalua Guadix",
    "sg:orig_category":"Fabricaci\u00d3n De Muebles De Cocina",
    "sg:phone":"+34 958 69 61 35",
    "sg:postcode":"18510",
    "sg:province":"Granada",
    "wof:name":"Cocinas Benalua S.l.",
    "wof:placetype":"venue"
},
  "geometry": {"coordinates":[-3.1669239998,37.3522415161],"type":"Point"}
}