{
  "type": "Feature",
  "properties": {
    "addr:full":"Plaza Alta Y Baja, 38 Lucena C\u00f3rdoba 14900",
    "addr:housenumber":"38",
    "addr:postcode":"14900",
    "addr:street":"Baja",
    "iso:country":"ES",
    "sg:address":"Plaza Alta Y Baja, 38",
    "sg:city":"Lucena",
    "sg:orig_category":"Producci\u00d3n, Distribuci\u00d3n De Gas Butano Y Propano",
    "sg:phone":"+34 957 51 31 23",
    "sg:postcode":"14900",
    "sg:province":"C\u00f3rdoba",
    "wof:name":"Hermanos Longo Gomez S.l.",
    "wof:placetype":"venue"
},
  "geometry": {"coordinates":[-4.4833889008,37.4090995789],"type":"Point"}
}