{
  "type": "Feature",
  "properties": {
    "iso:country":"ES",
    "sg:address":"Av Ntra. Sra. De L'assumpcio, 64",
    "sg:city":"Deltebre",
    "sg:orig_category":"Peluqueros: De Se\u00d1oras",
    "sg:phone":"+34 977 48 95 76",
    "sg:postcode":"43580",
    "sg:province":"Tarragona",
    "wof:name":"Pi\u00f1ol Llao Jose",
    "wof:placetype":"venue"
},
  "geometry": {"coordinates":[0.7052810192,40.7193603516],"type":"Point"}
}