{
  "type": "Feature",
  "properties": {
    "iso:country":"ES",
    "sg:address":"Pl Carles Iii (de), 14",
    "sg:city":"S. Carles Rapita",
    "sg:orig_category":"Cajas De Ahorro",
    "sg:phone":"+34 977 74 34 60",
    "sg:postcode":"43540",
    "sg:province":"Tarragona",
    "wof:name":"Caja De Ahorros De Valencia Castellon Y Alicante",
    "wof:placetype":"venue"
},
  "geometry": {"coordinates":[0.5927090049,40.6198883057],"type":"Point"}
}