{
  "type": "Feature",
  "properties": {
    "addr:full":"Calle de Marques De Quintanar, 16 Baiona Pontevedra 36300",
    "addr:housenumber":"16",
    "addr:postcode":"36300",
    "addr:street":"Calle De Marques De Quintanar",
    "iso:country":"ES",
    "sg:address":"Calle de Marques De Quintanar, 16",
    "sg:city":"Baiona",
    "sg:classifiers":[
        {
            "category":"Personal",
            "subcategory":"Barber",
            "type":"Services"
        }
    ],
    "sg:phone":"+34 986 35 82 34",
    "sg:postcode":"36300",
    "sg:province":"Pontevedra",
    "sg:tags":[
        "caballeros",
        "de",
        "peluqueros"
    ],
    "wof:name":"Peluqueria Baiona S.b",
    "wof:placetype":"venue"
},
  "geometry": {"coordinates":[-8.8521270752,42.1195411682],"type":"Point"}
}