{
  "type": "Feature",
  "properties": {
    "addr:full":"Calle de Doctor Casas, 12 Zaragoza Zaragoza 50008",
    "addr:housenumber":"12",
    "addr:postcode":"50008",
    "addr:street":"Calle De Doctor Casas",
    "iso:country":"ES",
    "sg:address":"Calle de Doctor Casas, 12",
    "sg:city":"Zaragoza",
    "sg:orig_category":"Peluqueros: De Se\u00d1oras",
    "sg:phone":"+34 976 15 85 52",
    "sg:postcode":"50008",
    "sg:province":"Zaragoza",
    "wof:name":"Gil Anson Raquel",
    "wof:placetype":"venue"
},
  "geometry": {"coordinates":[-0.8835909963,41.6434631348],"type":"Point"}
}