{
  "type": "Feature",
  "properties": {
    "iso:country":"ES",
    "sg:address":"Cami Albelda, 3",
    "sg:city":"Rossello",
    "sg:orig_category":"Pintores",
    "sg:phone":"+34 973 73 27 92",
    "sg:postcode":"25124",
    "sg:province":"Lleida",
    "wof:name":"Poliedric Forms S.l.",
    "wof:placetype":"venue"
},
  "geometry": {"coordinates":[0.5939149857,41.697429657],"type":"Point"}
}