{
  "type": "Feature",
  "properties": {
    "iso:country":"ES",
    "sg:address":"Calle de Huesca De, 15",
    "sg:city":"Fraga",
    "sg:orig_category":"Confecci\u00d3n (fabricaci\u00d3n, Al Por Mayor)",
    "sg:phone":"+34 974 47 11 21",
    "sg:postcode":"22520",
    "sg:province":"Huesca",
    "wof:name":"Modas Cambalache S.l.",
    "wof:placetype":"venue"
},
  "geometry": {"coordinates":[0.335123986,41.5215148926],"type":"Point"}
}