{
  "type": "Feature",
  "properties": {
    "addr:full":"Calle de Cruz, 9 Ciudad Real Ciudad Real 13001",
    "addr:housenumber":"9",
    "addr:postcode":"13001",
    "addr:street":"Calle De Cruz",
    "iso:country":"ES",
    "sg:address":"Calle de Cruz, 9",
    "sg:city":"Ciudad Real",
    "sg:orig_category":"Ropa Para Se\u00d1oras (al Por Menor)",
    "sg:phone":"+34 926 22 41 44",
    "sg:postcode":"13001",
    "sg:province":"Ciudad Real",
    "wof:name":"Fernandez Caba\u00f1as Marisol",
    "wof:placetype":"venue"
},
  "geometry": {"coordinates":[-3.9279108047,38.9860420227],"type":"Point"}
}