{
  "type": "Feature",
  "properties": {
    "iso:country":"ES",
    "sg:address":"Calle de Alameda, 42",
    "sg:city":"Coru\u00d1a",
    "sg:orig_category":"Caf\u00c9s, Bares, Cervecer\u00cdas",
    "sg:phone":"+34 981 22 84 88",
    "sg:postcode":"15003",
    "sg:province":"A Coru\u00f1a",
    "wof:name":"Silva Gomez Isolina",
    "wof:placetype":"venue"
},
  "geometry": {"coordinates":[-8.4057445526,43.3678894043],"type":"Point"}
}