{
  "type": "Feature",
  "properties": {
    "addr:full":"Calle de Rosales (los), 52 Rosales Las Palmas 35430",
    "addr:housenumber":"52",
    "addr:postcode":"35430",
    "addr:street":"Calle De Rosales Los",
    "iso:country":"ES",
    "sg:address":"Calle de Rosales (los), 52",
    "sg:city":"Rosales",
    "sg:orig_category":"Alimentaci\u00d3n General (al Por Menor)",
    "sg:phone":"+34 928 62 50 69",
    "sg:postcode":"35430",
    "sg:province":"Las Palmas",
    "wof:name":"Aleman Marrero Roque",
    "wof:placetype":"venue"
},
  "geometry": {"coordinates":[-15.5539751053,28.1131362915],"type":"Point"}
}