{
  "type": "Feature",
  "properties": {
    "addr:full":"Calle de Doctor Don Manuel Sanchez Saugar, S/n Sotillo Adrada \u00c1vila 05420",
    "addr:housenumber":"s",
    "addr:postcode":"05420",
    "addr:street":"Calle De Doctor Don Manuel Sanchez Saugar;/ N Sotillo;A\u0301Vila",
    "iso:country":"ES",
    "sg:address":"Calle de Doctor Don Manuel Sanchez Saugar, S/n",
    "sg:city":"Sotillo Adrada",
    "sg:orig_category":"Cajas De Ahorro",
    "sg:phone":"+34 918 66 10 06",
    "sg:postcode":"05420",
    "sg:province":"\u00c1vila",
    "wof:name":"Caja De Avila",
    "wof:placetype":"venue"
},
  "geometry": {"coordinates":[-4.5898241997,40.2908287048],"type":"Point"}
}