{
  "type": "Feature",
  "properties": {
    "addr:full":"Poli Puntido (el), S/n Oyon-oion \u00c1lava 01320",
    "addr:postcode":"01320",
    "addr:street":"El S / N Oyon-Oion A\u0301Lava",
    "iso:country":"ES",
    "sg:address":"Poli Puntido (el), S/n",
    "sg:city":"Oyon-oion",
    "sg:orig_category":"Deportes Y Programas De Aventura",
    "sg:phone":"+34 945 62 21 58",
    "sg:postcode":"01320",
    "sg:province":"\u00c1lava",
    "wof:name":"Grupo Empresarial Criteria S.l.",
    "wof:placetype":"venue"
},
  "geometry": {"coordinates":[-2.4307539463,42.5546722412],"type":"Point"}
}