{
  "type": "Feature",
  "properties": {
    "addr:full":"Calle de Alcala, 125 Madrid Madrid 28009",
    "addr:housenumber":"125",
    "addr:postcode":"28009",
    "addr:street":"Calle De Alcala",
    "iso:country":"ES",
    "sg:address":"Calle de Alcala, 125",
    "sg:city":"Madrid",
    "sg:orig_category":"Fabricaci\u00d3n De Bebidas No Alcoh\u00d3licas",
    "sg:phone":"+34 915 76 58 17",
    "sg:postcode":"28009",
    "sg:province":"Madrid",
    "sg:website":"www.horchaterialboraya.com",
    "wof:name":"Monros Mari Jose Luis",
    "wof:placetype":"venue"
},
  "geometry": {"coordinates":[-3.6798734665,40.4229507446],"type":"Point"}
}