{
  "type": "Feature",
  "properties": {
    "addr:full":"C/ Sant Maurici, 14 Vilafant Girona 17740",
    "addr:housenumber":"14",
    "addr:postcode":"17740",
    "addr:street":"C / Sant Maurici",
    "iso:country":"ES",
    "sg:address":"C/ Sant Maurici, 14",
    "sg:city":"Vilafant",
    "sg:orig_category":"Inform\u00c1tica: Soportes De Informaci\u00d3n, Suministros & Accesorios",
    "sg:phone":"+34 972 54 66 50",
    "sg:postcode":"17740",
    "sg:province":"Girona",
    "wof:name":"Essaige S.l.",
    "wof:placetype":"venue"
},
  "geometry": {"coordinates":[2.9426651001,42.2532806396],"type":"Point"}
}