{
  "type": "Feature",
  "properties": {
    "iso:country":"ES",
    "sg:address":"Pl Creu (de La), 1",
    "sg:city":"Valls",
    "sg:orig_category":"Internados & Ense\u00d1anza Privada",
    "sg:phone":"+34 977 60 04 21",
    "sg:postcode":"43800",
    "sg:province":"Tarragona",
    "wof:name":"Col-legi Claret-misioneros Hijos Del Inmaculado Corazon De Maria",
    "wof:placetype":"venue"
},
  "geometry": {"coordinates":[1.2535059452,41.2895126343],"type":"Point"}
}