{
  "type": "Feature",
  "properties": {
    "iso:country":"ES",
    "sg:address":"Ptda Pla Roig, 2",
    "sg:city":"Calpe",
    "sg:orig_category":"Empresas De Limpieza",
    "sg:phone":"+34 965 83 49 69",
    "sg:postcode":"03710",
    "sg:province":"Alicante",
    "wof:name":"Perles Morato Rosa",
    "wof:placetype":"venue"
},
  "geometry": {"coordinates":[0.0478550009,38.6447563171],"type":"Point"}
}