{
  "type": "Feature",
  "properties": {
    "iso:country":"ES",
    "sg:address":"Calle de Ramiro I, 15",
    "sg:city":"Piedras Blancas",
    "sg:orig_category":"Ropa Para Se\u00d1oras Y Caballeros (al Por Menor)",
    "sg:phone":"+34 985 53 03 03",
    "sg:postcode":"33450",
    "sg:province":"Asturias",
    "wof:name":"Moreno Bueno Francisco",
    "wof:placetype":"venue"
},
  "geometry": {"coordinates":[-5.9758720398,43.5609397888],"type":"Point"}
}