{
  "type": "Feature",
  "properties": {
    "iso:country":"ES",
    "sg:address":"Avda Blas Infante, 74",
    "sg:city":"Lepe",
    "sg:orig_category":"Muebles",
    "sg:phone":"+34 959 64 51 71",
    "sg:postcode":"21440",
    "sg:province":"Huelva",
    "wof:name":"Tapizados Gomars S.l.",
    "wof:placetype":"venue"
},
  "geometry": {"coordinates":[-7.203168869,37.2505264282],"type":"Point"}
}