{
  "type": "Feature",
  "properties": {
    "addr:full":"Carrer de Sureda, 55 Palma Islas Baleares 07007",
    "addr:housenumber":"55",
    "addr:postcode":"07007",
    "addr:street":"Carrer De Sureda",
    "iso:country":"ES",
    "sg:address":"Carrer de Sureda, 55",
    "sg:city":"Palma",
    "sg:orig_category":"Automatizaci\u00d3n De Procesos Industriales Y De Edificaci\u00d3n (estudios, Instalaci\u00d3n)",
    "sg:phone":"+34 971 27 65 64",
    "sg:postcode":"07007",
    "sg:province":"Islas Baleares",
    "wof:name":"Little Nice S.l.",
    "wof:placetype":"venue"
},
  "geometry": {"coordinates":[2.6754961014,39.5718383789],"type":"Point"}
}