{
  "type": "Feature",
  "properties": {
    "addr:full":"Cmno Hornera (la), 82 Gracia Santa Cruz De Tenerife 38295",
    "addr:housenumber":"82",
    "addr:postcode":"38295",
    "addr:street":"Cmno Hornera La",
    "iso:country":"ES",
    "sg:address":"Cmno Hornera (la), 82",
    "sg:city":"Gracia",
    "sg:orig_category":"Librer\u00cdas",
    "sg:phone":"+34 922 25 54 27",
    "sg:postcode":"38295",
    "sg:province":"Santa Cruz De Tenerife",
    "wof:name":"Perez Reyes Esteban",
    "wof:placetype":"venue"
},
  "geometry": {"coordinates":[-16.3025226593,28.4732723236],"type":"Point"}
}