{
  "type": "Feature",
  "properties": {
    "iso:country":"ES",
    "sg:address":"Calle de Acera De Guerrita, 2",
    "sg:city":"Cordoba",
    "sg:orig_category":"Asesor\u00cda Fiscal Y Jur\u00cddica",
    "sg:phone":"+34 957 49 66 67",
    "sg:postcode":"14001",
    "sg:province":"C\u00f3rdoba",
    "wof:name":"Naficon Asesores S.l.",
    "wof:placetype":"venue"
},
  "geometry": {"coordinates":[-4.7798714638,37.891002655],"type":"Point"}
}