{
  "type": "Feature",
  "properties": {
    "addr:full":"Rond Europa, 468 Sabadell Barcelona 08207",
    "addr:housenumber":"468",
    "addr:postcode":"08207",
    "addr:street":"Europa",
    "iso:country":"ES",
    "sg:address":"Rond Europa, 468",
    "sg:city":"Sabadell",
    "sg:orig_category":"Peluquer\u00cdas, Peluquer\u00cda Mixta",
    "sg:phone":"+34 937 46 01 62",
    "sg:postcode":"08207",
    "sg:province":"Barcelona",
    "wof:name":"Simon Garcia Rosa Maria",
    "wof:placetype":"venue"
},
  "geometry": {"coordinates":[2.0826098919,41.5643882751],"type":"Point"}
}