{
  "type": "Feature",
  "properties": {
    "iso:country":"ES",
    "sg:address":"Mercado Municipal, S/n",
    "sg:city":"Javea",
    "sg:orig_category":"Carnicer\u00cdas, Carnicer\u00cdas",
    "sg:phone":"+34 966 46 06 63",
    "sg:postcode":"03730",
    "sg:province":"Alicante",
    "wof:name":"Catala Crua\u00f1as Jose",
    "wof:placetype":"venue"
},
  "geometry": {"coordinates":[0.1668650061,38.7890739441],"type":"Point"}
}