{
  "type": "Feature",
  "properties": {
    "iso:country":"ES",
    "sg:address":"Calle de Pedro Vitoria, 13",
    "sg:city":"Motril",
    "sg:orig_category":"Clubes, Asociaciones De Ocio",
    "sg:phone":"+34 958 60 74 05",
    "sg:postcode":"18600",
    "sg:province":"Granada",
    "wof:name":"Gutierrez Lopez Francisco",
    "wof:placetype":"venue"
},
  "geometry": {"coordinates":[-3.5155689716,36.7442016602],"type":"Point"}
}