{
  "type": "Feature",
  "properties": {
    "addr:full":"Calle de Cruz De San Sebastian, 3 Alcala Henares Madrid 28803",
    "addr:housenumber":"3",
    "addr:postcode":"28803",
    "addr:street":"Calle De Cruz De San Sebastian",
    "iso:country":"ES",
    "sg:address":"Calle de Cruz De San Sebastian, 3",
    "sg:city":"Alcala Henares",
    "sg:orig_category":"Farmacias",
    "sg:phone":"+34 918 88 27 11",
    "sg:postcode":"28803",
    "sg:province":"Madrid",
    "wof:name":"Palacios Bujalance Andres",
    "wof:placetype":"venue"
},
  "geometry": {"coordinates":[-3.3697497845,40.476184845],"type":"Point"}
}