{
  "type": "Feature",
  "properties": {
    "addr:full":"Carrer de Pla\u00c7a, 93 Premia Mar Barcelona 08330",
    "addr:housenumber":"93",
    "addr:postcode":"08330",
    "addr:street":"Carrer De Plac\u0327A",
    "iso:country":"ES",
    "sg:address":"Carrer de Pla\u00c7a, 93",
    "sg:city":"Premia Mar",
    "sg:orig_category":"Sanatorios M\u00c9dico",
    "sg:phone":"+34 937 54 77 10",
    "sg:postcode":"08330",
    "sg:province":"Barcelona",
    "wof:name":"Centre De Telecomunicaciones De Catalunya",
    "wof:placetype":"venue"
},
  "geometry": {"coordinates":[2.3536279202,41.4943695068],"type":"Point"}
}