{
  "type": "Feature",
  "properties": {
    "addr:full":"Ctra. Casas Iba\u00f1ez, 2 Albacete Albacete 02006",
    "addr:housenumber":"2",
    "addr:postcode":"02006",
    "addr:street":"Ctra. Casas Iban\u0303Ez",
    "iso:country":"ES",
    "sg:address":"Ctra. Casas Iba\u00f1ez, 2",
    "sg:city":"Albacete",
    "sg:orig_category":"Agencias Y Asesores De Publicidad",
    "sg:phone":"+34 902 19 32 55",
    "sg:postcode":"02006",
    "sg:province":"Albacete",
    "wof:name":"Imprimadrid Publicitarios S.l.",
    "wof:placetype":"venue"
},
  "geometry": {"coordinates":[-1.8665416241,39.0125617981],"type":"Point"}
}