{
  "type": "Feature",
  "properties": {
    "iso:country":"ES",
    "sg:address":"Carrer de Barcelona, 41",
    "sg:city":"Hospitalet Llobregat",
    "sg:orig_category":"Fotocopias, Reprograf\u00cda",
    "sg:phone":"+34 932 61 12 06",
    "sg:postcode":"08901",
    "sg:province":"Barcelona",
    "wof:name":"J.beltran Y Otro S.c.p.",
    "wof:placetype":"venue"
},
  "geometry": {"coordinates":[2.1038858891,41.3611946106],"type":"Point"}
}