{
  "type": "Feature",
  "properties": {
    "iso:country":"ES",
    "sg:address":"Calle de Ensenada, 5",
    "sg:city":"Salafranca",
    "sg:orig_category":"Inmobiliaria (agencias)",
    "sg:phone":"+34 965 94 40 23",
    "sg:postcode":"03550",
    "sg:province":"Alicante",
    "wof:name":"Cava Cava Isabel",
    "wof:placetype":"venue"
},
  "geometry": {"coordinates":[-0.4451659918,38.4037666321],"type":"Point"}
}