{
  "type": "Feature",
  "properties": {
    "addr:full":"Pl. Los Fueros, 1 Estella Navarra 31200",
    "addr:housenumber":"1",
    "addr:postcode":"31200",
    "addr:street":"Los Fueros",
    "iso:country":"ES",
    "sg:address":"Pl. Los Fueros, 1",
    "sg:city":"Estella",
    "sg:orig_category":"El Hogar: Amueblado, Acondicionamiento, Decoraci\u00d3n Y Mantenimiento",
    "sg:phone":"+34 948 55 18 44",
    "sg:postcode":"31200",
    "sg:province":"Navarra",
    "wof:name":"Contreras Moreno S.l.",
    "wof:placetype":"venue"
},
  "geometry": {"coordinates":[-2.0317890644,42.6719856262],"type":"Point"}
}