{
  "type": "Feature",
  "properties": {
    "addr:full":"Avda Ca\u00d1a (la), 59 Algeciras C\u00e1diz 11203",
    "addr:housenumber":"59;ca\u0301diz",
    "addr:postcode":"11203",
    "addr:street":"Avda Can\u0303A La",
    "iso:country":"ES",
    "sg:address":"Avda Ca\u00d1a (la), 59",
    "sg:city":"Algeciras",
    "sg:orig_category":"Cajas De Ahorro",
    "sg:phone":"+34 956 65 58 04",
    "sg:postcode":"11203",
    "sg:province":"C\u00e1diz",
    "sg:website":"www.unicaja.es",
    "wof:name":"Unicaja",
    "wof:placetype":"venue"
},
  "geometry": {"coordinates":[-5.4568920135,36.1313781738],"type":"Point"}
}