{
  "type": "Feature",
  "properties": {
    "iso:country":"ES",
    "sg:address":"Calle de Pio Xii, 14",
    "sg:city":"Vitoria-gasteiz",
    "sg:orig_category":"Restaurantes",
    "sg:phone":"+34 945 25 77 02",
    "sg:postcode":"01004",
    "sg:province":"\u00c1lava",
    "wof:name":"Garcia Gil Jose Luis",
    "wof:placetype":"venue"
},
  "geometry": {"coordinates":[-2.6657109261,42.8435974121],"type":"Point"}
}