{
  "type": "Feature",
  "properties": {
    "iso:country":"ES",
    "sg:address":"Calle de Juan Pantoja, 12",
    "sg:city":"Madrid",
    "sg:orig_category":"Molduras, Junquillos, Listones Y Molduras Perforadas",
    "sg:phone":"+34 915 54 47 38",
    "sg:postcode":"28039",
    "sg:province":"Madrid",
    "wof:name":"Sampedro Martinez Florentino",
    "wof:placetype":"venue"
},
  "geometry": {"coordinates":[-3.7044329643,40.4501838684],"type":"Point"}
}