{
  "type": "Feature",
  "properties": {
    "addr:full":"Calle de Torralba, 11 Chucena Huelva 21891",
    "addr:housenumber":"11",
    "addr:postcode":"21891",
    "addr:street":"Calle De Torralba",
    "iso:country":"ES",
    "sg:address":"Calle de Torralba, 11",
    "sg:city":"Chucena",
    "sg:orig_category":"Supermercados Y Hipermercados",
    "sg:phone":"+34 959 42 41 78",
    "sg:postcode":"21891",
    "sg:province":"Huelva",
    "wof:name":"C. Do\u00f1ana S.l.l.",
    "wof:placetype":"venue"
},
  "geometry": {"coordinates":[-6.3932518959,37.3619232178],"type":"Point"}
}