{
  "type": "Feature",
  "properties": {
    "addr:full":"Plaz Eras, 1 Zaragoza Zaragoza 50002",
    "addr:housenumber":"1",
    "addr:postcode":"50002",
    "addr:street":"Plaz Eras",
    "iso:country":"ES",
    "sg:address":"Plaz Eras, 1",
    "sg:city":"Zaragoza",
    "sg:orig_category":"Agencias Y Agentes Comerciales, Representantes",
    "sg:phone":"+34 976 29 89 21",
    "sg:postcode":"50002",
    "sg:province":"Zaragoza",
    "wof:name":"Arag\u00fces Algas Mariano",
    "wof:placetype":"venue"
},
  "geometry": {"coordinates":[-0.8718069792,41.6499404907],"type":"Point"}
}