{
  "type": "Feature",
  "properties": {
    "iso:country":"ES",
    "sg:address":"Calle de Ceramistas, 15",
    "sg:city":"Madrid",
    "sg:orig_category":"Plomeros",
    "sg:phone":"+34 913 06 06 23",
    "sg:postcode":"28037",
    "sg:province":"Madrid",
    "wof:name":"Araque Araque Lorenzo",
    "wof:placetype":"venue"
},
  "geometry": {"coordinates":[-3.6141200066,40.4263267517],"type":"Point"}
}