{
  "type": "Feature",
  "properties": {
    "addr:full":"Avda Rosaleda (de La), 26 Archena Murcia 30600",
    "addr:housenumber":"26",
    "addr:postcode":"30600",
    "addr:street":"Avda Rosaleda De La",
    "iso:country":"ES",
    "sg:address":"Avda Rosaleda (de La), 26",
    "sg:city":"Archena",
    "sg:orig_category":"Pintura Y Barniz (al Por Menor)",
    "sg:phone":"+34 968 68 82 03",
    "sg:postcode":"30600",
    "sg:province":"Murcia",
    "wof:name":"Marin Quesada Amparo",
    "wof:placetype":"venue"
},
  "geometry": {"coordinates":[-1.3079930544,38.1160202026],"type":"Point"}
}