{
  "type": "Feature",
  "properties": {
    "addr:full":"Avda Ris, 59 Noja Cantabria 39180",
    "addr:housenumber":"59",
    "addr:postcode":"39180",
    "addr:street":"Avda Ris",
    "iso:country":"ES",
    "sg:address":"Avda Ris, 59",
    "sg:city":"Noja",
    "sg:orig_category":"Molduras, Junquillos, Listones Y Molduras Perforadas",
    "sg:phone":"+34 942 63 07 42",
    "sg:postcode":"39180",
    "sg:province":"Cantabria",
    "wof:name":"Hermanos Quintana Torre S.l.",
    "wof:placetype":"venue"
},
  "geometry": {"coordinates":[-3.529807806,43.4867362976],"type":"Point"}
}