{
  "type": "Feature",
  "properties": {
    "iso:country":"ES",
    "sg:address":"Carrer de Amunt (d'), 27",
    "sg:city":"Botarell",
    "sg:orig_category":"Productos Fitosanitarios (negocio, Aplicaci\u00d3n)",
    "sg:phone":"+34 977 82 63 31",
    "sg:postcode":"43772",
    "sg:province":"Tarragona",
    "wof:name":"Agroquimics Roige S.l.",
    "wof:placetype":"venue"
},
  "geometry": {"coordinates":[0.9878479838,41.1361122131],"type":"Point"}
}