{
  "type": "Feature",
  "properties": {
    "addr:full":"Calle de Sargento Provisional, 5 Valladolid Valladolid 47013",
    "addr:housenumber":"5",
    "addr:postcode":"47013",
    "addr:street":"Calle De Sargento Provisional",
    "iso:country":"ES",
    "sg:address":"Calle de Sargento Provisional, 5",
    "sg:city":"Valladolid",
    "sg:orig_category":"Caf\u00c9s, Bares, Cervecer\u00cdas",
    "sg:phone":"+34 983 22 13 47",
    "sg:postcode":"47013",
    "sg:province":"Valladolid",
    "wof:name":"Blanco Vega Elicio",
    "wof:placetype":"venue"
},
  "geometry": {"coordinates":[-4.7242817879,41.6314849854],"type":"Point"}
}