{
  "type": "Feature",
  "properties": {
    "iso:country":"ES",
    "sg:address":"Carr Doctor Combelles, 49",
    "sg:city":"Lleida",
    "sg:classifiers":[
        {
            "category":"Personal",
            "subcategory":"Barber",
            "type":"Services"
        }
    ],
    "sg:phone":"+34 973 26 70 54",
    "sg:postcode":"25003",
    "sg:province":"Lleida",
    "sg:tags":[
        "caballeros",
        "de",
        "peluqueros"
    ],
    "wof:name":"Mu\u00f1oz Pauls Buenaventura",
    "wof:placetype":"venue"
},
  "geometry": {"coordinates":[0.616764009,41.6140098572],"type":"Point"}
}