{
  "type": "Feature",
  "properties": {
    "addr:full":"Calle de Hermanos Quintero, 2 Castellon Castell\u00f3n 12006",
    "addr:housenumber":"2",
    "addr:postcode":"12006",
    "addr:street":"Calle De Hermanos Quintero;Castello\u0301N",
    "iso:country":"ES",
    "sg:address":"Calle de Hermanos Quintero, 2",
    "sg:city":"Castellon",
    "sg:orig_category":"Fabricaci\u00d3n, Importaci\u00d3n De Material Y Sistemas De Telecomunicaciones",
    "sg:phone":"+34 964 25 61 31",
    "sg:postcode":"12006",
    "sg:province":"Castell\u00f3n",
    "sg:website":"www.msmcomunicacion.com",
    "wof:name":"Selvi Millan Manuel",
    "wof:placetype":"venue"
},
  "geometry": {"coordinates":[-0.1292939931,40.0168533325],"type":"Point"}
}