{
  "type": "Feature",
  "properties": {
    "iso:country":"ES",
    "sg:address":"Ctra. Nacional 340, Km. 0098,2",
    "sg:city":"Torreblanca",
    "sg:orig_category":"Restaurantes",
    "sg:phone":"+34 964 42 10 86",
    "sg:postcode":"12596",
    "sg:province":"Castell\u00f3n",
    "wof:name":"Camioneros Serra S.l.",
    "wof:placetype":"venue"
},
  "geometry": {"coordinates":[0.1960400045,40.2205581665],"type":"Point"}
}