{
  "type": "Feature",
  "properties": {
    "iso:country":"ES",
    "sg:address":"Calle de Corral, 5",
    "sg:city":"Aljorra",
    "sg:orig_category":"Fabricaci\u00d3n De Ventanas",
    "sg:phone":"+34 968 16 42 17",
    "sg:postcode":"30390",
    "sg:province":"Murcia",
    "wof:name":"Puertas Y Cerrajerias Martinez S.l.",
    "wof:placetype":"venue"
},
  "geometry": {"coordinates":[-1.0634709597,37.6884765625],"type":"Point"}
}