{
  "type": "Feature",
  "properties": {
    "iso:country":"ES",
    "sg:address":"Calle de Zamora, 4",
    "sg:city":"Roquetas Mar",
    "sg:orig_category":"Promotores Constructores",
    "sg:phone":"+34 950 32 91 99",
    "sg:postcode":"04740",
    "sg:province":"Almer\u00eda",
    "sg:website":"www.promotaria.com",
    "wof:name":"Moreno Zamora Miguel",
    "wof:placetype":"venue"
},
  "geometry": {"coordinates":[-2.6161038876,36.7644882202],"type":"Point"}
}