{
  "type": "Feature",
  "properties": {
    "addr:full":"Calle de Malena (la), 1 Banyeres Mariola Alicante 03450",
    "addr:housenumber":"1",
    "addr:postcode":"03450",
    "addr:street":"Calle De Malena La",
    "iso:country":"ES",
    "sg:address":"Calle de Malena (la), 1",
    "sg:city":"Banyeres Mariola",
    "sg:orig_category":"Agentes Generales De Seguros",
    "sg:phone":"+34 966 56 70 77",
    "sg:postcode":"03450",
    "sg:province":"Alicante",
    "wof:name":"Blanes Verdu Jose Antonio",
    "wof:placetype":"venue"
},
  "geometry": {"coordinates":[-0.6567389965,38.7162780762],"type":"Point"}
}