{
  "type": "Feature",
  "properties": {
    "iso:country":"ES",
    "sg:address":"Calle de Melilla, 55",
    "sg:city":"Madrid",
    "sg:orig_category":"Escuelas Primarias P\u00dablicas",
    "sg:phone":"+34 915 17 80 91",
    "sg:postcode":"28005",
    "sg:province":"Madrid",
    "sg:website":"www.acadomia.es",
    "wof:name":"Magar Estudios S.l.",
    "wof:placetype":"venue"
},
  "geometry": {"coordinates":[-3.7097990513,40.4012718201],"type":"Point"}
}