{
  "type": "Feature",
  "properties": {
    "addr:full":"Carrer de Corsega, 610 Barcelona Barcelona 08025",
    "addr:housenumber":"610",
    "addr:postcode":"08025",
    "addr:street":"Carrer De Corsega",
    "iso:country":"ES",
    "sg:address":"Carrer de Corsega, 610",
    "sg:city":"Barcelona",
    "sg:orig_category":"Molduras, Junquillos, Listones Y Molduras Perforadas",
    "sg:phone":"+34 934 56 04 50",
    "sg:postcode":"08025",
    "sg:province":"Barcelona",
    "wof:name":"Gonzalez Pe\u00f1uelo Evelio",
    "wof:placetype":"venue"
},
  "geometry": {"coordinates":[2.1764509678,41.4091911316],"type":"Point"}
}