{
  "type": "Feature",
  "properties": {
    "addr:full":"Avda Los Huetos, 50 Vitoria-gasteiz \u00c1lava 01010",
    "addr:housenumber":"50",
    "addr:postcode":"01010",
    "addr:street":"Avda Los Huetos",
    "iso:country":"ES",
    "sg:address":"Avda Los Huetos, 50",
    "sg:city":"Vitoria-gasteiz",
    "sg:orig_category":"Promotores Constructores",
    "sg:phone":"+34 945 21 40 11",
    "sg:postcode":"01010",
    "sg:province":"\u00c1lava",
    "wof:name":"Construcciones Lujaraba S.l.",
    "wof:placetype":"venue"
},
  "geometry": {"coordinates":[-2.7113409042,42.8562355042],"type":"Point"}
}