{
  "type": "Feature",
  "properties": {
    "addr:full":"Luga Rabales, 17 Balsapintada Murcia 30332",
    "addr:housenumber":"17",
    "addr:postcode":"30332",
    "addr:street":"Rabales",
    "iso:country":"ES",
    "sg:address":"Luga Rabales, 17",
    "sg:city":"Balsapintada",
    "sg:orig_category":"M\u00c1rmoles, Granitos Y Piedras Naturales",
    "sg:phone":"+34 968 15 97 87",
    "sg:postcode":"30332",
    "sg:province":"Murcia",
    "wof:name":"Balmarmol C.b.",
    "wof:placetype":"venue"
},
  "geometry": {"coordinates":[-1.1106909513,37.732383728],"type":"Point"}
}