{
  "type": "Feature",
  "properties": {
    "iso:country":"ES",
    "sg:address":"Pase Carlos Era\u00d1a, 37",
    "sg:city":"Ciudad Real",
    "sg:orig_category":"Construcciones Met\u00c1licas",
    "sg:phone":"+34 926 27 43 47",
    "sg:postcode":"13004",
    "sg:province":"Ciudad Real",
    "wof:name":"Aldaba Estructuras S.l.",
    "wof:placetype":"venue"
},
  "geometry": {"coordinates":[-3.9228279591,38.9805908203],"type":"Point"}
}