{
  "type": "Feature",
  "properties": {
    "iso:country":"ES",
    "sg:address":"Calle de Rigoberta Menchu, 4",
    "sg:city":"Cordoba",
    "sg:orig_category":"Aparatos De Iluminaci\u00d3n (al Por Menor)",
    "sg:phone":"+34 957 40 11 21",
    "sg:postcode":"14011",
    "sg:province":"C\u00f3rdoba",
    "wof:name":"Ingenieria Y Electromontajes Cordobeses S.l.",
    "wof:placetype":"venue"
},
  "geometry": {"coordinates":[-4.7979240417,37.8976783752],"type":"Point"}
}