{
  "type": "Feature",
  "properties": {
    "iso:country":"ES",
    "sg:address":"Calle de Argenta, 14",
    "sg:city":"Madrid",
    "sg:orig_category":"Peluqueros: De Se\u00d1oras",
    "sg:phone":"+34 917 75 53 77",
    "sg:postcode":"28037",
    "sg:province":"Madrid",
    "wof:name":"Diaz Rodriguez Elisa Maria",
    "wof:placetype":"venue"
},
  "geometry": {"coordinates":[-3.6150708199,40.4232940674],"type":"Point"}
}