{
  "type": "Feature",
  "properties": {
    "iso:country":"ES",
    "sg:address":"Plaz Espa\u00d1a, 10",
    "sg:city":"Rozas De Madrid",
    "sg:orig_category":"Ingeniero",
    "sg:phone":"+34 916 40 74 16",
    "sg:postcode":"28230",
    "sg:province":"Madrid",
    "wof:name":"Equistica Y Urbanismo S.l.",
    "wof:placetype":"venue"
},
  "geometry": {"coordinates":[-3.8913800716,40.5247497559],"type":"Point"}
}