{
  "type": "Feature",
  "properties": {
    "iso:country":"ES",
    "sg:address":"Avda Villafranca, 30",
    "sg:city":"Bembibre",
    "sg:orig_category":"Asesor\u00cda Sobre Comunicaci\u00d3n De Empresas",
    "sg:phone":"+34 987 51 16 46",
    "sg:postcode":"24300",
    "sg:province":"Le\u00f3n",
    "wof:name":"Centro De Gestion Informatizada Abaco S.l.",
    "wof:placetype":"venue"
},
  "geometry": {"coordinates":[-6.4179491997,42.6159896851],"type":"Point"}
}