{
  "type": "Feature",
  "properties": {
    "addr:full":"Carrer de Pablo Iglesias, 102 Barcelona Barcelona 08016",
    "addr:housenumber":"102",
    "addr:postcode":"08016",
    "addr:street":"Carrer De Pablo Iglesias",
    "iso:country":"ES",
    "sg:address":"Carrer de Pablo Iglesias, 102",
    "sg:city":"Barcelona",
    "sg:orig_category":"Empresarios",
    "sg:phone":"+34 933 59 91 68",
    "sg:postcode":"08016",
    "sg:province":"Barcelona",
    "wof:name":"Fundacio Viure I Conviure",
    "wof:placetype":"venue"
},
  "geometry": {"coordinates":[2.1831660271,41.4452362061],"type":"Point"}
}