{
  "type": "Feature",
  "properties": {
    "addr:full":"Calle de Fueros, 22 Salvatierra O Agurain \u00c1lava 01200",
    "addr:housenumber":"22",
    "addr:postcode":"01200",
    "addr:street":"Calle De Fueros;A\u0301Lava",
    "iso:country":"ES",
    "sg:address":"Calle de Fueros, 22",
    "sg:city":"Salvatierra O Agurain",
    "sg:orig_category":"Agentes Generales De Seguros",
    "sg:phone":"+34 945 30 10 27",
    "sg:postcode":"01200",
    "sg:province":"\u00c1lava",
    "wof:name":"Mapfre Servicios De Informatica S.a.",
    "wof:placetype":"venue"
},
  "geometry": {"coordinates":[-2.3855280876,42.8499412537],"type":"Point"}
}