{
  "type": "Feature",
  "properties": {
    "addr:full":"Calle de Mequinenza (cha), 11 Madrid Madrid 28004",
    "addr:housenumber":"11",
    "addr:postcode":"madrid;28004",
    "addr:street":"Calle De Mequinenza Cha",
    "iso:country":"ES",
    "sg:address":"Calle de Mequinenza (cha), 11",
    "sg:city":"Madrid",
    "sg:orig_category":"Discotecas Y Salas De Baile",
    "sg:phone":"+34 914 47 73 54",
    "sg:postcode":"28004",
    "sg:province":"Madrid",
    "wof:name":"Eventos Y Comunicacion 2003 S.l.",
    "wof:placetype":"venue"
},
  "geometry": {"coordinates":[-3.605987072,40.4469223022],"type":"Point"}
}