{
  "type": "Feature",
  "properties": {
    "addr:full":"Calle de Pigmalio, S/n Benaguasil Valencia 46180",
    "addr:housenumber":"s",
    "addr:postcode":"46180",
    "addr:street":"Calle De Pigmalio;/ N",
    "iso:country":"ES",
    "sg:address":"Calle de Pigmalio, S/n",
    "sg:city":"Benaguasil",
    "sg:orig_category":"Mataderos Y Talleres De Despiezado",
    "sg:phone":"+34 962 73 72 17",
    "sg:postcode":"46180",
    "sg:province":"Valencia",
    "wof:name":"Gimeno Bolea S.l.",
    "wof:placetype":"venue"
},
  "geometry": {"coordinates":[-0.5875390172,39.5956382751],"type":"Point"}
}