{
  "type": "Feature",
  "properties": {
    "iso:country":"ES",
    "sg:address":"Pl Nolla, S/n",
    "sg:city":"Meliana",
    "sg:orig_category":"Mercer\u00cda, Lencer\u00cda (al Por Menor)",
    "sg:phone":"+34 961 49 06 93",
    "sg:postcode":"46133",
    "sg:province":"Valencia",
    "wof:name":"Bueno Ruiz Carmen",
    "wof:placetype":"venue"
},
  "geometry": {"coordinates":[-0.3468990028,39.5215835571],"type":"Point"}
}