{
  "type": "Feature",
  "properties": {
    "iso:country":"ES",
    "sg:address":"Calle de Calvario, 4",
    "sg:city":"Pozuelo De Alarcon",
    "sg:orig_category":"Carnicer\u00cdas, Carnicer\u00cdas",
    "sg:phone":"+34 913 52 81 63",
    "sg:postcode":"28223",
    "sg:province":"Madrid",
    "wof:name":"Carrillo Rioja Ivan",
    "wof:placetype":"venue"
},
  "geometry": {"coordinates":[-3.8127179146,40.4347038269],"type":"Point"}
}