{
  "type": "Feature",
  "properties": {
    "iso:country":"ES",
    "sg:address":"Avgd Valencia, 43",
    "sg:city":"Lleida",
    "sg:orig_category":"Alimentaci\u00d3n General (al Por Menor)",
    "sg:phone":"+34 973 20 09 25",
    "sg:postcode":"25001",
    "sg:province":"Lleida",
    "wof:name":"Campos Chacon Juana",
    "wof:placetype":"venue"
},
  "geometry": {"coordinates":[0.6270179749,41.6099700928],"type":"Point"}
}