{
  "type": "Feature",
  "properties": {
    "iso:country":"ES",
    "sg:address":"Ctra Albacete, Km. 0002,5",
    "sg:city":"Ayora",
    "sg:orig_category":"Asociaciones Y Clubs Deportivos",
    "sg:phone":"+34 961 89 04 65",
    "sg:postcode":"46620",
    "sg:province":"Valencia",
    "wof:name":"Club De Tenis Ayora S.cv.",
    "wof:placetype":"venue"
},
  "geometry": {"coordinates":[-1.0537240505,39.0609741211],"type":"Point"}
}