{
  "type": "Feature",
  "properties": {
    "iso:country":"ES",
    "sg:address":"Calle de Torrene, 4",
    "sg:city":"Algorta",
    "sg:orig_category":"Pescader\u00cdas (al Por Menor)",
    "sg:phone":"+34 944 91 18 20",
    "sg:postcode":"48991",
    "sg:province":"Vizcaya",
    "wof:name":"Molano Moreno Julio",
    "wof:placetype":"venue"
},
  "geometry": {"coordinates":[-3.0109050274,43.3499679565],"type":"Point"}
}