{
  "type": "Feature",
  "properties": {
    "addr:full":"Calle de Alcala Galiano, 26 Playa De Arinaga Las Palmas 35118",
    "addr:housenumber":"26",
    "addr:postcode":"35118",
    "addr:street":"Calle De Alcala Galiano",
    "iso:country":"ES",
    "sg:address":"Calle de Alcala Galiano, 26",
    "sg:city":"Playa De Arinaga",
    "sg:orig_category":"Servicios De Telecomunicaciones",
    "sg:phone":"+34 928 18 84 47",
    "sg:postcode":"35118",
    "sg:province":"Las Palmas",
    "wof:name":"Artiles Caballero Antonio",
    "wof:placetype":"venue"
},
  "geometry": {"coordinates":[-15.3927698135,27.8557987213],"type":"Point"}
}