{
  "type": "Feature",
  "properties": {
    "addr:full":"Carrer de Hurtado, 27 Barcelona Barcelona 08022",
    "addr:housenumber":"27",
    "addr:postcode":"08022",
    "addr:street":"Carrer De Hurtado",
    "iso:country":"ES",
    "sg:address":"Carrer de Hurtado, 27",
    "sg:city":"Barcelona",
    "sg:orig_category":"Doctores En Medicina",
    "sg:phone":"+34 934 34 25 50",
    "sg:postcode":"08022",
    "sg:province":"Barcelona",
    "wof:name":"Centros Sanitarios General S.a.",
    "wof:placetype":"venue"
},
  "geometry": {"coordinates":[2.1399199963,41.4112548828],"type":"Point"}
}