{
  "type": "Feature",
  "properties": {
    "iso:country":"ES",
    "sg:address":"Carrer de Jocs Olimpics, S/n",
    "sg:city":"Terrassa",
    "sg:orig_category":"Asociaciones Y Clubs Deportivos",
    "sg:phone":"+34 937 35 19 38",
    "sg:postcode":"08225",
    "sg:province":"Barcelona",
    "sg:website":"www.terrassafcsad.com",
    "wof:name":"Terrassa Futbol Club S.a.d.",
    "wof:placetype":"venue"
},
  "geometry": {"coordinates":[2.0098600388,41.5793914795],"type":"Point"}
}