{
  "type": "Feature",
  "properties": {
    "addr:full":"Ctra. Madrid-coru\u00f1a, Km. 0111,0 Adanero \u00c1vila 05296",
    "addr:postcode":"05296",
    "addr:street":"Ctra. Madrid-Corun\u0303A Km. 0111,0;A\u0301Vila",
    "iso:country":"ES",
    "sg:address":"Ctra. Madrid-coru\u00f1a, Km. 0111,0",
    "sg:city":"Adanero",
    "sg:orig_category":"Distribuci\u00d3n De Petr\u00d3leo Y Derivados",
    "sg:phone":"+34 920 30 70 54",
    "sg:postcode":"05296",
    "sg:province":"\u00c1vila",
    "sg:website":"www.cepsa.es",
    "wof:name":"Grajma S.l.",
    "wof:placetype":"venue"
},
  "geometry": {"coordinates":[-4.6066594124,40.9459114075],"type":"Point"}
}