{
  "type": "Feature",
  "properties": {
    "addr:full":"Calle de Maldonado, 60 Madrid Madrid 28006",
    "addr:housenumber":"60",
    "addr:postcode":"madrid;28006",
    "addr:street":"Calle De Maldonado",
    "iso:country":"ES",
    "sg:address":"Calle de Maldonado, 60",
    "sg:city":"Madrid",
    "sg:orig_category":"Empresarios Y Productoras De Espect\u00c1culos",
    "sg:phone":"+34 914 02 60 58",
    "sg:postcode":"28006",
    "sg:province":"Madrid",
    "wof:name":"Seoane Calvo Juan Jose",
    "wof:placetype":"venue"
},
  "geometry": {"coordinates":[-3.6742749214,40.433303833],"type":"Point"}
}