{
  "type": "Feature",
  "properties": {
    "addr:full":"Calle de Mostoles (de), S/n Fuenlabrada Madrid 28942",
    "addr:postcode":"28942",
    "addr:street":"Calle De Mostoles De S / N",
    "iso:country":"ES",
    "sg:address":"Calle de Mostoles (de), S/n",
    "sg:city":"Fuenlabrada",
    "sg:orig_category":"Supermercados Y Hipermercados",
    "sg:phone":"+34 914 92 07 07",
    "sg:postcode":"28942",
    "sg:province":"Madrid",
    "wof:name":"Supermercados De Alimentacion De Madrid S.l.",
    "wof:placetype":"venue"
},
  "geometry": {"coordinates":[-3.8165140152,40.2968292236],"type":"Point"}
}