{
  "type": "Feature",
  "properties": {
    "addr:full":"Calle de Calvario, 21 Monforte Cid Alicante 03670",
    "addr:housenumber":"21",
    "addr:postcode":"03670",
    "addr:street":"Calle De Calvario",
    "iso:country":"ES",
    "sg:address":"Calle de Calvario, 21",
    "sg:city":"Monforte Cid",
    "sg:orig_category":"Comerciantes Al Por Mayor De Vinos, Licores Y Alcoholes",
    "sg:phone":"+34 965 62 01 34",
    "sg:postcode":"03670",
    "sg:province":"Alicante",
    "wof:name":"Boyer Carrrasco Francisca",
    "wof:placetype":"venue"
},
  "geometry": {"coordinates":[-0.7274619937,38.3800773621],"type":"Point"}
}