{
  "type": "Feature",
  "properties": {
    "iso:country":"ES",
    "sg:address":"Carr Calvari, 52",
    "sg:city":"Castellnou Seana",
    "sg:orig_category":"Ropa De Trabajo Y Profesionales (al Por Menor)",
    "sg:phone":"+34 973 32 07 43",
    "sg:postcode":"25265",
    "sg:province":"Lleida",
    "wof:name":"Duran Llanes Jose",
    "wof:placetype":"venue"
},
  "geometry": {"coordinates":[0.9706739783,41.6483421326],"type":"Point"}
}