{
  "type": "Feature",
  "properties": {
    "iso:country":"ES",
    "sg:address":"Rua Galicia, 16",
    "sg:city":"Guarda",
    "sg:orig_category":"Librer\u00cdas",
    "sg:phone":"+34 986 61 38 39",
    "sg:postcode":"36780",
    "sg:province":"Pontevedra",
    "wof:name":"Alonso Alpuin Maria Montserrat",
    "wof:placetype":"venue"
},
  "geometry": {"coordinates":[-8.876698494,41.9104537964],"type":"Point"}
}