{
  "type": "Feature",
  "properties": {
    "addr:full":"Av Catalunya, 16 Alcover Tarragona 43460",
    "addr:housenumber":"16",
    "addr:postcode":"43460",
    "addr:street":"Av Catalunya",
    "iso:country":"ES",
    "sg:address":"Av Catalunya, 16",
    "sg:city":"Alcover",
    "sg:orig_category":"Promotores Constructores",
    "sg:phone":"+34 977 76 03 16",
    "sg:postcode":"43460",
    "sg:province":"Tarragona",
    "wof:name":"Construccions Josep Arenas S.l.",
    "wof:placetype":"venue"
},
  "geometry": {"coordinates":[1.1727999449,41.2623405457],"type":"Point"}
}