{
  "type": "Feature",
  "properties": {
    "addr:full":"Joan Cast. Guasch, 70 Pujols Islas Baleares 07871",
    "addr:housenumber":"70",
    "addr:postcode":"07871",
    "addr:street":"Guasch",
    "iso:country":"ES",
    "sg:address":"Joan Cast. Guasch, 70",
    "sg:city":"Pujols",
    "sg:orig_category":"Radiocomunicaciones, Telefon\u00cda M\u00d3vil, Radiomensajer\u00cda: Servicios, Comercializaci\u00d3n",
    "sg:phone":"+34 971 32 87 63",
    "sg:postcode":"07871",
    "sg:province":"Islas Baleares",
    "sg:website":"www.formentera.net",
    "wof:name":"Es Freus S.l.",
    "wof:placetype":"venue"
},
  "geometry": {"coordinates":[1.4565550089,38.7221031189],"type":"Point"}
}