{
  "type": "Feature",
  "properties": {
    "addr:full":"Carr Est, De L', 13 Campos Islas Baleares 07630",
    "addr:postcode":"07630",
    "addr:street":"Carr",
    "iso:country":"ES",
    "sg:address":"Carr Est, De L', 13",
    "sg:city":"Campos",
    "sg:orig_category":"Empresas De Desmonte",
    "sg:phone":"+34 971 65 15 09",
    "sg:postcode":"07630",
    "sg:province":"Islas Baleares",
    "wof:name":"Hermanos Gost Simo S.a.",
    "wof:placetype":"venue"
},
  "geometry": {"coordinates":[3.0234570503,39.4303703308],"type":"Point"}
}