{
  "type": "Feature",
  "properties": {
    "addr:full":"Bendoiro, 1 Bendoiro Pontevedra 36500",
    "addr:housenumber":"1",
    "addr:postcode":"36500",
    "addr:street":"Bendoiro",
    "iso:country":"ES",
    "sg:address":"Bendoiro, 1",
    "sg:city":"Bendoiro",
    "sg:orig_category":"Prendas Y Chalecos De Punto (al Por Menor)",
    "sg:phone":"+34 986 79 40 17",
    "sg:postcode":"36500",
    "sg:province":"Pontevedra",
    "wof:name":"Generos De Punto Ivan S.l.",
    "wof:placetype":"venue"
},
  "geometry": {"coordinates":[-8.1106138229,42.6577606201],"type":"Point"}
}