{
  "type": "Feature",
  "properties": {
    "addr:full":"Calle de Mayor, 6 Arenas -areeta Vizcaya 48930",
    "addr:housenumber":"6;areeta",
    "addr:postcode":"48930",
    "addr:street":"Calle De Mayor",
    "iso:country":"ES",
    "sg:address":"Calle de Mayor, 6",
    "sg:city":"Arenas -areeta",
    "sg:classifiers":[
        {
            "category":"Taxi",
            "type":"Transportation"
        }
    ],
    "sg:phone":"+34 944 63 54 64",
    "sg:postcode":"48930",
    "sg:province":"Vizcaya",
    "wof:name":"Ayuntamiento De Guecho",
    "wof:placetype":"venue"
},
  "geometry": {"coordinates":[-2.6983869076,43.2204284668],"type":"Point"}
}