{
  "type": "Feature",
  "properties": {
    "addr:full":"Calle de Lagasca, S/n San Pedro Alcantara M\u00e1laga 29670",
    "addr:housenumber":"s / n",
    "addr:postcode":"29670",
    "addr:street":"Calle De Lagasca",
    "iso:country":"ES",
    "sg:address":"Calle de Lagasca, S/n",
    "sg:city":"San Pedro Alcantara",
    "sg:orig_category":"Molduras, Junquillos, Listones Y Molduras Perforadas",
    "sg:phone":"+34 952 78 89 52",
    "sg:postcode":"29670",
    "sg:province":"M\u00e1laga",
    "wof:name":"Fernandez Gonzalez Juan",
    "wof:placetype":"venue"
},
  "geometry": {"coordinates":[-4.9899687767,36.4859237671],"type":"Point"}
}