{
  "type": "Feature",
  "properties": {
    "iso:country":"ES",
    "sg:address":"Calle de Villablino, 47",
    "sg:city":"Fuenlabrada",
    "sg:orig_category":"Albergues",
    "sg:phone":"+34 916 42 02 35",
    "sg:postcode":"28947",
    "sg:province":"Madrid",
    "wof:name":"Fu Shi Yon Shun",
    "wof:placetype":"venue"
},
  "geometry": {"coordinates":[-3.7448210716,40.2596473694],"type":"Point"}
}