{
  "type": "Feature",
  "properties": {
    "iso:country":"ES",
    "sg:address":"Carrer de Ausias Marc, 12",
    "sg:city":"Barcelona",
    "sg:orig_category":"M\u00c9dicos: Medicina General Orientada A La Homeopat\u00cda",
    "sg:phone":"+34 933 01 82 25",
    "sg:postcode":"08010",
    "sg:province":"Barcelona",
    "wof:name":"Vila Alcalde Jorge",
    "wof:placetype":"venue"
},
  "geometry": {"coordinates":[2.1744689941,41.3903045654],"type":"Point"}
}