{
  "type": "Feature",
  "properties": {
    "iso:country":"ES",
    "sg:address":"Carrer de Proven\u00c7a, 156",
    "sg:city":"Barcelona",
    "sg:orig_category":"M\u00c9dicos: Cirug\u00cda Ortop\u00c9dica Y Traumatolog\u00cda",
    "sg:phone":"+34 934 54 30 53",
    "sg:postcode":"08036",
    "sg:province":"Barcelona",
    "wof:name":"Majo Buigas Juan",
    "wof:placetype":"venue"
},
  "geometry": {"coordinates":[2.1526060104,41.3878669739],"type":"Point"}
}