{
  "type": "Feature",
  "properties": {
    "addr:full":"Carr Gran Bretanya, 66 Badalona Barcelona 08917",
    "addr:housenumber":"66",
    "addr:postcode":"08917",
    "addr:street":"Carr Gran Bretanya",
    "iso:country":"ES",
    "sg:address":"Carr Gran Bretanya, 66",
    "sg:city":"Badalona",
    "sg:orig_category":"Ropa De Casa (fabricaci\u00d3n, Al Por Mayor)",
    "sg:phone":"+34 933 95 66 80",
    "sg:postcode":"08917",
    "sg:province":"Barcelona",
    "wof:name":"Pronto Moda Nivel 30 S.l.",
    "wof:placetype":"venue"
},
  "geometry": {"coordinates":[2.2231600285,41.4609107971],"type":"Point"}
}