{
  "type": "Feature",
  "properties": {
    "iso:country":"ES",
    "sg:address":"Calle de Isaac Peral, 12",
    "sg:city":"Madrid",
    "sg:orig_category":"Librer\u00cdas",
    "sg:phone":"+34 915 43 09 46",
    "sg:postcode":"28015",
    "sg:province":"Madrid",
    "wof:name":"Fotocopias Marta S.l.",
    "wof:placetype":"venue"
},
  "geometry": {"coordinates":[-3.7179999352,40.4360198975],"type":"Point"}
}