{
  "type": "Feature",
  "properties": {
    "addr:full":"Ctra Crevillente, S/n Torretas Alicante 03180",
    "addr:housenumber":"s",
    "addr:postcode":"03180",
    "addr:street":"Ctra Crevillente;/ N Torretas",
    "iso:country":"ES",
    "sg:address":"Ctra Crevillente, S/n",
    "sg:city":"Torretas",
    "sg:orig_category":"Caf\u00c9s, Bares, Cervecer\u00cdas",
    "sg:phone":"+34 966 92 78 52",
    "sg:postcode":"03180",
    "sg:province":"Alicante",
    "wof:name":"Espuma De Levante S.l.",
    "wof:placetype":"venue"
},
  "geometry": {"coordinates":[-0.6536790133,38.0173606873],"type":"Point"}
}