{
  "type": "Feature",
  "properties": {
    "addr:full":"Carrer de Boulevard D'or, S/n Cala D'or Islas Baleares 07660",
    "addr:housenumber":"s",
    "addr:postcode":"07660",
    "addr:street":"Carrer De Boulevard D'Or;/ N",
    "iso:country":"ES",
    "sg:address":"Carrer de Boulevard D'or, S/n",
    "sg:city":"Cala D'or",
    "sg:orig_category":"Molduras, Junquillos, Listones Y Molduras Perforadas",
    "sg:phone":"+34 971 65 92 39",
    "sg:postcode":"07660",
    "sg:province":"Islas Baleares",
    "wof:name":"Igewski S.l.",
    "wof:placetype":"venue"
},
  "geometry": {"coordinates":[2.9117100239,39.6136398315],"type":"Point"}
}