{
  "type": "Feature",
  "properties": {
    "iso:country":"ES",
    "sg:address":"Vega De Los Caseros, S/n",
    "sg:city":"Villanueva",
    "sg:orig_category":"T\u00c9cnicos Veterinarios",
    "sg:phone":"+34 985 84 86 44",
    "sg:postcode":"33559",
    "sg:province":"Asturias",
    "wof:name":"Cifuentes Llorente Cesar",
    "wof:placetype":"venue"
},
  "geometry": {"coordinates":[-5.1673641205,43.3433876038],"type":"Point"}
}