{
  "type": "Feature",
  "properties": {
    "iso:country":"ES",
    "sg:address":"Carrer de Badajoz, 48",
    "sg:city":"Barcelona",
    "sg:orig_category":"Panader\u00cdas, Panader\u00cdas",
    "sg:phone":"+34 932 21 27 10",
    "sg:postcode":"08005",
    "sg:province":"Barcelona",
    "wof:name":"Sabor Borras S.l.",
    "wof:placetype":"venue"
},
  "geometry": {"coordinates":[2.1985030174,41.3964271545],"type":"Point"}
}