{
  "type": "Feature",
  "properties": {
    "iso:country":"ES",
    "sg:address":"Calle de Miguel Servet, 7",
    "sg:city":"Zaragoza",
    "sg:orig_category":"Cristaler\u00cda: Suministros",
    "sg:phone":"+34 976 49 00 90",
    "sg:postcode":"50002",
    "sg:province":"Zaragoza",
    "wof:name":"Carro Almazan Eladio",
    "wof:placetype":"venue"
},
  "geometry": {"coordinates":[-0.8744969964,41.6478500366],"type":"Point"}
}