{
  "type": "Feature",
  "properties": {
    "iso:country":"ES",
    "sg:address":"Calle de San Juan De Mata, 4",
    "sg:city":"Madrid",
    "sg:orig_category":"Farmacias",
    "sg:phone":"+34 914 64 04 71",
    "sg:postcode":"28011",
    "sg:province":"Madrid",
    "wof:name":"Paredes Carrasco Julia Concepcion",
    "wof:placetype":"venue"
},
  "geometry": {"coordinates":[-3.7563529015,40.4039115906],"type":"Point"}
}