{
  "type": "Feature",
  "properties": {
    "iso:country":"ES",
    "sg:address":"Urb Canuta Ifach, 2",
    "sg:city":"Calpe",
    "sg:orig_category":"Inmobiliaria (agencias)",
    "sg:phone":"+34 965 83 77 59",
    "sg:postcode":"03710",
    "sg:province":"Alicante",
    "wof:name":"Zodiak Villas S.l.",
    "wof:placetype":"venue"
},
  "geometry": {"coordinates":[0.0419876985,38.647731781],"type":"Point"}
}