{
  "type": "Feature",
  "properties": {
    "addr:full":"Calle de Cervantes, 16 Alginet Valencia 46230",
    "addr:housenumber":"16",
    "addr:postcode":"46230",
    "addr:street":"Calle De Cervantes",
    "iso:country":"ES",
    "sg:address":"Calle de Cervantes, 16",
    "sg:city":"Alginet",
    "sg:orig_category":"Promotores Constructores",
    "sg:phone":"+34 961 75 06 80",
    "sg:postcode":"46230",
    "sg:province":"Valencia",
    "wof:name":"Construcciones Alginet S. L.",
    "wof:placetype":"venue"
},
  "geometry": {"coordinates":[-0.4677264094,39.2617645264],"type":"Point"}
}