{
  "type": "Feature",
  "properties": {
    "iso:country":"ES",
    "sg:address":"Calle de Rey, 3",
    "sg:city":"Medina Campo",
    "sg:orig_category":"Seguridad Social",
    "sg:phone":"+34 983 81 23 60",
    "sg:postcode":"47400",
    "sg:province":"Valladolid",
    "wof:name":"Tesoreria General De La Seguridad Social-direccion Provincial De Valladolid",
    "wof:placetype":"venue"
},
  "geometry": {"coordinates":[-4.9174661636,41.3083610535],"type":"Point"}
}