{
  "type": "Feature",
  "properties": {
    "iso:country":"ES",
    "sg:address":"Calle de San Gabriel, 11",
    "sg:city":"Tamaraceite",
    "sg:orig_category":"Ense\u00d1anza, Formaci\u00d3n Profesional: Aprendizaje",
    "sg:phone":"+34 928 67 61 29",
    "sg:postcode":"35018",
    "sg:province":"Las Palmas",
    "wof:name":"Instituto Municipal De Deportes De Las P",
    "wof:placetype":"venue"
},
  "geometry": {"coordinates":[-15.4770822525,28.100402832],"type":"Point"}
}