{
  "type": "Feature",
  "properties": {
    "iso:country":"ES",
    "sg:address":"Calle de Juan De Lanuza, 4",
    "sg:city":"Barbastro",
    "sg:orig_category":"Organizaciones Internacionales",
    "sg:phone":"+34 974 31 00 31",
    "sg:postcode":"22300",
    "sg:province":"Huesca",
    "wof:name":"Caritas Diocesana Barbastro Monzon",
    "wof:placetype":"venue"
},
  "geometry": {"coordinates":[0.1313380003,42.03490448],"type":"Point"}
}