{
  "type": "Feature",
  "properties": {
    "iso:country":"ES",
    "sg:address":"Carrer de Paco Mutllo, 48",
    "sg:city":"Sabadell",
    "sg:orig_category":"Empresas De Limpieza",
    "sg:phone":"+34 937 23 02 42",
    "sg:postcode":"08208",
    "sg:province":"Barcelona",
    "wof:name":"Neteges Creu Alta S.l.",
    "wof:placetype":"venue"
},
  "geometry": {"coordinates":[2.1053700447,41.5560379028],"type":"Point"}
}