{
  "type": "Feature",
  "properties": {
    "addr:full":"Calle de Arbolancha, 4 Tudela Navarra 31500",
    "addr:housenumber":"4",
    "addr:postcode":"31500",
    "addr:street":"Calle De Arbolancha",
    "iso:country":"ES",
    "sg:address":"Calle de Arbolancha, 4",
    "sg:city":"Tudela",
    "sg:orig_category":"Partidos Pol\u00cdticos",
    "sg:phone":"+34 948 41 11 69",
    "sg:postcode":"31500",
    "sg:province":"Navarra",
    "wof:name":"Convergencia De Democratas Navarros",
    "wof:placetype":"venue"
},
  "geometry": {"coordinates":[-1.6059341431,42.0621643066],"type":"Point"}
}