{
  "type": "Feature",
  "properties": {
    "iso:country":"ES",
    "sg:address":"Carrer de Fra Luis De Leon, 152",
    "sg:city":"Sabadell",
    "sg:orig_category":"Centros De Educaci\u00d3n Especial",
    "sg:phone":"+34 937 10 56 43",
    "sg:postcode":"08203",
    "sg:province":"Barcelona",
    "wof:name":"Colegio Publico Amadeo Vives",
    "wof:placetype":"venue"
},
  "geometry": {"coordinates":[2.1161780357,41.5346641541],"type":"Point"}
}