{
  "type": "Feature",
  "properties": {
    "addr:full":"Avda Ramon Y Cajal, 68 Almaden Ciudad Real 13400",
    "addr:housenumber":"68",
    "addr:postcode":"13400",
    "addr:street":"Avda Ramon Y Cajal;Real",
    "iso:country":"ES",
    "sg:address":"Avda Ramon Y Cajal, 68",
    "sg:city":"Almaden",
    "sg:orig_category":"Molduras, Junquillos, Listones Y Molduras Perforadas",
    "sg:phone":"+34 926 71 30 12",
    "sg:postcode":"13400",
    "sg:province":"Ciudad Real",
    "wof:name":"Mata Casasola Eduardo",
    "wof:placetype":"venue"
},
  "geometry": {"coordinates":[-4.8295559883,38.7821083069],"type":"Point"}
}