{
  "type": "Feature",
  "properties": {
    "addr:full":"Pase Doctor Vallejo Nagera, 36 Madrid Madrid 28005",
    "addr:housenumber":"36",
    "addr:postcode":"madrid;28005",
    "addr:street":"Nagera",
    "iso:country":"ES",
    "sg:address":"Pase Doctor Vallejo Nagera, 36",
    "sg:city":"Madrid",
    "sg:orig_category":"Panader\u00cdas, Panader\u00cdas",
    "sg:phone":"+34 914 67 63 10",
    "sg:postcode":"28005",
    "sg:province":"Madrid",
    "wof:name":"Arroyo Claro S.a.",
    "wof:placetype":"venue"
},
  "geometry": {"coordinates":[-3.7100017071,40.4024772644],"type":"Point"}
}