{
  "type": "Feature",
  "properties": {
    "addr:full":"Calle de Alcala, 54 Madrid Madrid 28014",
    "addr:housenumber":"54",
    "addr:postcode":"madrid;28014",
    "addr:street":"Calle De Alcala",
    "iso:country":"ES",
    "sg:address":"Calle de Alcala, 54",
    "sg:city":"Madrid",
    "sg:orig_category":"Cajas De Ahorro",
    "sg:phone":"+34 915 21 11 30",
    "sg:postcode":"28014",
    "sg:province":"Madrid",
    "sg:website":"www.cajasegovia.es",
    "wof:name":"Caja De Ahorros Y Monte De Piedad De Segovia",
    "wof:placetype":"venue"
},
  "geometry": {"coordinates":[-3.6907587051,40.4195785522],"type":"Point"}
}