{
  "type": "Feature",
  "properties": {
    "addr:full":"Carr Sant Gregori, 130 Girona Girona 17007",
    "addr:housenumber":"130",
    "addr:postcode":"17007",
    "addr:street":"Carr Sant Gregori",
    "iso:country":"ES",
    "sg:address":"Carr Sant Gregori, 130",
    "sg:city":"Girona",
    "sg:orig_category":"Restaurantes",
    "sg:phone":"+34 972 21 36 73",
    "sg:postcode":"17007",
    "sg:province":"Girona",
    "wof:name":"Restaurant Casa Dalmau S.l.",
    "wof:placetype":"venue"
},
  "geometry": {"coordinates":[2.8057210445,41.9924049377],"type":"Point"}
}