{
  "type": "Feature",
  "properties": {
    "iso:country":"ES",
    "sg:address":"Calle de Cardenal Belluga, 5",
    "sg:city":"Madrid",
    "sg:orig_category":"Promotores Constructores",
    "sg:phone":"+34 913 56 07 49",
    "sg:postcode":"28028",
    "sg:province":"Madrid",
    "wof:name":"Analisis Social De Gestion S.l.u.",
    "wof:placetype":"venue"
},
  "geometry": {"coordinates":[-3.6652209759,40.4304084778],"type":"Point"}
}