{
  "type": "Feature",
  "properties": {
    "addr:full":"Avda Derechos Humanos (de Los), 4 Palencia Palencia 34003",
    "addr:postcode":"34003",
    "addr:street":"Avda Derechos Humanos De Los",
    "iso:country":"ES",
    "sg:address":"Avda Derechos Humanos (de Los), 4",
    "sg:city":"Palencia",
    "sg:orig_category":"M\u00c9dicos: Medicina General Orientada A La Acupuntura",
    "sg:phone":"+34 979 74 00 07",
    "sg:postcode":"34003",
    "sg:province":"Palencia",
    "wof:name":"Kim  Kwang Ii",
    "wof:placetype":"venue"
},
  "geometry": {"coordinates":[-4.5287661552,42.0189476013],"type":"Point"}
}