{
  "type": "Feature",
  "properties": {
    "iso:country":"ES",
    "sg:address":"Calle de Hondon De Los Frailes, 2",
    "sg:city":"Alacant",
    "sg:orig_category":"Escuelas De Maternidad P\u00dablicas",
    "sg:phone":"+34 965 25 62 45",
    "sg:postcode":"03005",
    "sg:province":"Alicante",
    "wof:name":"Montessori Escuela Infantil S. L.",
    "wof:placetype":"venue"
},
  "geometry": {"coordinates":[-0.4964100122,38.3547477722],"type":"Point"}
}