{
  "type": "Feature",
  "properties": {
    "addr:full":"Avda Libertad, 7 San Miguel Murcia 30009",
    "addr:housenumber":"7",
    "addr:postcode":"30009",
    "addr:street":"Avda Libertad",
    "iso:country":"ES",
    "sg:address":"Avda Libertad, 7",
    "sg:city":"San Miguel",
    "sg:orig_category":"Bancos",
    "sg:phone":"+34 968 27 42 02",
    "sg:postcode":"30009",
    "sg:province":"Murcia",
    "sg:website":"www.bancopastor.es",
    "wof:name":"R Cable Y Telecomunicaciones Galicia S.a.",
    "wof:placetype":"venue"
},
  "geometry": {"coordinates":[-1.1325889826,37.9893684387],"type":"Point"}
}