{
  "type": "Feature",
  "properties": {
    "iso:country":"ES",
    "sg:address":"Calle de Ciscar, 59",
    "sg:city":"Valencia",
    "sg:orig_category":"Farmacias",
    "sg:phone":"+34 963 74 36 23",
    "sg:postcode":"46005",
    "sg:province":"Valencia",
    "wof:name":"Ruiz-garces C.b.",
    "wof:placetype":"venue"
},
  "geometry": {"coordinates":[-0.3638168871,39.4634170532],"type":"Point"}
}