{
  "type": "Feature",
  "properties": {
    "iso:country":"ES",
    "sg:address":"Calle de Isaac Peral, 18",
    "sg:city":"Linares",
    "sg:orig_category":"M\u00c9dicos: Estomatolog\u00cda",
    "sg:phone":"+34 953 65 10 08",
    "sg:postcode":"23700",
    "sg:province":"Ja\u00e9n",
    "wof:name":"Marin Garcia De Alca\u00f1iz Diego",
    "wof:placetype":"venue"
},
  "geometry": {"coordinates":[-3.6330919266,38.0955886841],"type":"Point"}
}