{
  "type": "Feature",
  "properties": {
    "iso:country":"ES",
    "sg:address":"Carrer de Tetuan, 1",
    "sg:city":"Reus",
    "sg:orig_category":"Fabricaci\u00d3n, Distribuci\u00d3n De Material Para La Climatizaci\u00d3n, Aireaci\u00d3n Y Ventilaci\u00d3n",
    "sg:phone":"+34 977 75 46 44",
    "sg:postcode":"43205",
    "sg:province":"Tarragona",
    "wof:name":"Instalaciones Frigorificas Anguera S.l.",
    "wof:placetype":"venue"
},
  "geometry": {"coordinates":[1.1092410088,41.1504173279],"type":"Point"}
}