{
  "type": "Feature",
  "properties": {
    "addr:full":"Calle de Transportes (los), 17 Alacant Alicante 03008",
    "addr:postcode":"03008",
    "addr:street":"Calle De Transportes Los",
    "iso:country":"ES",
    "sg:address":"Calle de Transportes (los), 17",
    "sg:city":"Alacant",
    "sg:orig_category":"Venta, Instalaci\u00d3n De Sistemas De Alarmas Y Vigilancia",
    "sg:phone":"+34 965 11 17 10",
    "sg:postcode":"03008",
    "sg:province":"Alicante",
    "sg:website":"www.securitas.es",
    "wof:name":"Securitas Tratamiento Integral De Valores S.a.",
    "wof:placetype":"venue"
},
  "geometry": {"coordinates":[-0.5158309937,38.3366508484],"type":"Point"}
}