{
  "type": "Feature",
  "properties": {
    "addr:full":"Calle de Palomera, S/n Le\u00f3n Le\u00f3n 24007",
    "addr:postcode":"24007",
    "addr:street":"Calle De Palomera S / N Leo\u0301N Leo\u0301N",
    "iso:country":"ES",
    "sg:address":"Calle de Palomera, S/n",
    "sg:city":"Le\u00f3n",
    "sg:orig_category":"Ense\u00d1anza Secundaria: Colegios Y Escuelas Privadas",
    "sg:phone":"+34 987 22 32 00",
    "sg:postcode":"24007",
    "sg:province":"Le\u00f3n",
    "wof:name":"Instituto Nacional De Bachillerato Ordo\u00d1o Ii",
    "wof:placetype":"venue"
},
  "geometry": {"coordinates":[-5.5666069984,42.6020088196],"type":"Point"}
}