{
  "type": "Feature",
  "properties": {
    "addr:full":"Pg Pont, S/n Cerdanyola Valles Barcelona 08290",
    "addr:housenumber":"s / n",
    "addr:postcode":"08290",
    "addr:street":"Pg Pont;Valles Barcelona",
    "iso:country":"ES",
    "sg:address":"Pg Pont, S/n",
    "sg:city":"Cerdanyola Valles",
    "sg:orig_category":"Restaurantes",
    "sg:phone":"+34 935 97 04 79",
    "sg:postcode":"08290",
    "sg:province":"Barcelona",
    "wof:name":"Romero Mu\u00f1oz Francisco",
    "wof:placetype":"venue"
},
  "geometry": {"coordinates":[2.1471889019,41.4915351868],"type":"Point"}
}