{
  "type": "Feature",
  "properties": {
    "iso:country":"ES",
    "sg:address":"El Peligro, 1",
    "sg:city":"Retuerta Bullaque",
    "sg:orig_category":"Farmacias",
    "sg:phone":"+34 925 42 17 50",
    "sg:postcode":"13194",
    "sg:province":"Ciudad Real",
    "wof:name":"Rodriguez Vazquez Del Rey Pablo Bernardo",
    "wof:placetype":"venue"
},
  "geometry": {"coordinates":[-4.4095778465,39.4610328674],"type":"Point"}
}