{
  "type": "Feature",
  "properties": {
    "addr:full":"Pase Damas (las), 44 Zaragoza Zaragoza 50008",
    "addr:housenumber":"44",
    "addr:postcode":"50008",
    "addr:street":"Las",
    "iso:country":"ES",
    "sg:address":"Pase Damas (las), 44",
    "sg:city":"Zaragoza",
    "sg:orig_category":"Agencias De Viajes",
    "sg:phone":"+34 976 23 06 12",
    "sg:postcode":"50008",
    "sg:province":"Zaragoza",
    "sg:website":"www.viajesiberia.com",
    "wof:name":"Viajes Iberia S.a.",
    "wof:placetype":"venue"
},
  "geometry": {"coordinates":[-0.8825510144,41.6430053711],"type":"Point"}
}