{
  "type": "Feature",
  "properties": {
    "iso:country":"ES",
    "sg:address":"Sta Lucia (p I Arroyo Miel), 3",
    "sg:city":"Arroyo Miel",
    "sg:orig_category":"Asociaciones Y Clubs Deportivos",
    "sg:phone":"+34 952 44 97 08",
    "sg:postcode":"29631",
    "sg:province":"M\u00e1laga",
    "wof:name":"Servi-fitness S.l.",
    "wof:placetype":"venue"
},
  "geometry": {"coordinates":[-4.5303959846,36.6042938232],"type":"Point"}
}