{
  "type": "Feature",
  "properties": {
    "iso:country":"ES",
    "sg:address":"Pg Nit De L'alba, 1",
    "sg:city":"Elche",
    "sg:orig_category":"Ropa Para Ni\u00d1os (al Por Menor)",
    "sg:phone":"+34 965 46 48 08",
    "sg:postcode":"03206",
    "sg:province":"Alicante",
    "wof:name":"Brufal Fernandez Jose Luis",
    "wof:placetype":"venue"
},
  "geometry": {"coordinates":[-0.7072250247,38.2692756653],"type":"Point"}
}