{
  "type": "Feature",
  "properties": {
    "addr:full":"Calle de San Antonio, 9 Pravia Asturias 33120",
    "addr:housenumber":"9",
    "addr:postcode":"33120",
    "addr:street":"Calle De San Antonio",
    "iso:country":"ES",
    "sg:address":"Calle de San Antonio, 9",
    "sg:city":"Pravia",
    "sg:orig_category":"Farmacias",
    "sg:phone":"+34 985 82 09 20",
    "sg:postcode":"33120",
    "sg:province":"Asturias",
    "wof:name":"Mateo Rodriguez Joaquin Daniel",
    "wof:placetype":"venue"
},
  "geometry": {"coordinates":[-6.1116271019,43.4900779724],"type":"Point"}
}