{
  "type": "Feature",
  "properties": {
    "addr:full":"Avda Federico Anaya, 12 Salamanca Salamanca 37004",
    "addr:housenumber":"12",
    "addr:postcode":"37004",
    "addr:street":"Avda Federico Anaya",
    "iso:country":"ES",
    "sg:address":"Avda Federico Anaya, 12",
    "sg:city":"Salamanca",
    "sg:orig_category":"Suministros Y Materiales Industriales",
    "sg:phone":"+34 923 12 19 33",
    "sg:postcode":"37004",
    "sg:province":"Salamanca",
    "wof:name":"Benito Sanchez Manuela",
    "wof:placetype":"venue"
},
  "geometry": {"coordinates":[-5.6574010849,40.9721298218],"type":"Point"}
}