{
  "type": "Feature",
  "properties": {
    "iso:country":"ES",
    "sg:address":"Calle de Cid, 6",
    "sg:city":"Miranda Ebro",
    "sg:orig_category":"Cl\u00cdnicas Dentales",
    "sg:phone":"+34 947 33 16 70",
    "sg:postcode":"09200",
    "sg:province":"Burgos",
    "wof:name":"Morandeira Saavedra Manuel",
    "wof:placetype":"venue"
},
  "geometry": {"coordinates":[-2.9447746277,42.686630249],"type":"Point"}
}