{
  "type": "Feature",
  "properties": {
    "addr:full":"Carrer de Roger, 15 Barcelona Barcelona 08028",
    "addr:housenumber":"15",
    "addr:postcode":"08028",
    "addr:street":"Carrer De Roger",
    "iso:country":"ES",
    "sg:address":"Carrer de Roger, 15",
    "sg:city":"Barcelona",
    "sg:orig_category":"Inmobiliaria (agencias)",
    "sg:phone":"+34 934 91 40 24",
    "sg:postcode":"08028",
    "sg:province":"Barcelona",
    "wof:name":"Comunidad De Propietarios Roger 15",
    "wof:placetype":"venue"
},
  "geometry": {"coordinates":[2.1265149117,41.3767776489],"type":"Point"}
}