{
  "type": "Feature",
  "properties": {
    "addr:full":"Calle de Concepcion Arenal, 20 Granada Granada 18013",
    "addr:housenumber":"20",
    "addr:postcode":"18013",
    "addr:street":"Calle De Concepcion Arenal",
    "iso:country":"ES",
    "sg:address":"Calle de Concepcion Arenal, 20",
    "sg:city":"Granada",
    "sg:orig_category":"Internados & Ense\u00d1anza Privada",
    "sg:phone":"+34 958 16 26 28",
    "sg:postcode":"18013",
    "sg:province":"Granada",
    "wof:name":"Fundacion Patronato Avemariano De Granada",
    "wof:placetype":"venue"
},
  "geometry": {"coordinates":[-3.6045873165,37.1918334961],"type":"Point"}
}