{
  "type": "Feature",
  "properties": {
    "iso:country":"ES",
    "sg:address":"Calle de Suecia, 6",
    "sg:city":"Badajoz",
    "sg:orig_category":"Supermercados Y Hipermercados",
    "sg:phone":"+34 924 24 04 00",
    "sg:postcode":"06003",
    "sg:province":"Badajoz",
    "wof:name":"Sacusa S.l.",
    "wof:placetype":"venue"
},
  "geometry": {"coordinates":[-6.9610037804,38.8644256592],"type":"Point"}
}