{
  "type": "Feature",
  "properties": {
    "iso:country":"ES",
    "sg:address":"Estd Xoane, 170",
    "sg:city":"Ferrol",
    "sg:orig_category":"Internados & Ense\u00d1anza Privada",
    "sg:phone":"+34 981 33 01 40",
    "sg:postcode":"15405",
    "sg:province":"La Coru\u00f1a",
    "wof:name":"Colegio Valle Inclan 1 S.l.",
    "wof:placetype":"venue"
},
  "geometry": {"coordinates":[-8.2437515259,43.5037994385],"type":"Point"}
}