{
  "type": "Feature",
  "properties": {
    "addr:full":"Crri Baeza, S/n Secano Murcia 30006",
    "addr:housenumber":"s / n",
    "addr:postcode":"30006",
    "iso:country":"ES",
    "sg:address":"Crri Baeza, S/n",
    "sg:city":"Secano",
    "sg:orig_category":"Confecci\u00d3n (fabricaci\u00d3n, Al Por Mayor)",
    "sg:phone":"+34 968 23 38 02",
    "sg:postcode":"30006",
    "sg:province":"Murcia",
    "wof:name":"Confecciones Liwe S.a.e.",
    "wof:placetype":"venue"
},
  "geometry": {"coordinates":[-1.1008939743,37.9940185547],"type":"Point"}
}