{
  "type": "Feature",
  "properties": {
    "iso:country":"ES",
    "sg:address":"Calle de Carrera, 22",
    "sg:city":"Archidona",
    "sg:orig_category":"Droguer\u00cdas (al Por Menor)",
    "sg:phone":"+34 952 71 63 75",
    "sg:postcode":"29300",
    "sg:province":"M\u00e1laga",
    "wof:name":"Drosolu S.l.",
    "wof:placetype":"venue"
},
  "geometry": {"coordinates":[-4.3884711266,37.0955963135],"type":"Point"}
}