{
  "type": "Feature",
  "properties": {
    "iso:country":"ES",
    "sg:address":"Calle de Fernando Vela, 1",
    "sg:city":"Oviedo",
    "sg:orig_category":"Asesor\u00cda Sobre Comunicaci\u00d3n De Empresas",
    "sg:phone":"+34 985 11 34 47",
    "sg:postcode":"33001",
    "sg:province":"Asturias",
    "wof:name":"Astursayme S.l.",
    "wof:placetype":"venue"
},
  "geometry": {"coordinates":[-5.845097065,43.3674087524],"type":"Point"}
}