{
  "type": "Feature",
  "properties": {
    "addr:full":"Bista-eder Kalea, 10 Eibar Guip\u00f9zcoa 20600",
    "addr:housenumber":"10",
    "addr:postcode":"20600",
    "addr:street":"Bista-Eder Kalea;Guipu\u0300Zcoa",
    "iso:country":"ES",
    "sg:address":"Bista-eder Kalea, 10",
    "sg:city":"Eibar",
    "sg:orig_category":"Molduras, Junquillos, Listones Y Molduras Perforadas",
    "sg:phone":"+34 943 20 68 68",
    "sg:postcode":"20600",
    "sg:province":"Guip\u00f9zcoa",
    "wof:name":"I\u00f1aki Sanchez Horcajada Y Otro C.b.",
    "wof:placetype":"venue"
},
  "geometry": {"coordinates":[-2.4697179794,43.1844711304],"type":"Point"}
}