{
  "type": "Feature",
  "properties": {
    "addr:full":"Crta Vinaroz-vitoria, Km. 0061,5 Morella Castell\u00f3n 12300",
    "addr:postcode":"12300",
    "addr:street":"Crta Vinaroz-Vitoria Km. 0061,5 Morella Castello\u0301N",
    "iso:country":"ES",
    "sg:address":"Crta Vinaroz-vitoria, Km. 0061,5",
    "sg:city":"Morella",
    "sg:orig_category":"Electricidad: Instalaciones Industriales",
    "sg:phone":"+34 964 17 32 12",
    "sg:postcode":"12300",
    "sg:province":"Castell\u00f3n",
    "wof:name":"Electra Del Maestrazgo S.a.",
    "wof:placetype":"venue"
},
  "geometry": {"coordinates":[-0.0977939963,40.6189155579],"type":"Point"}
}