{
  "type": "Feature",
  "properties": {
    "iso:country":"ES",
    "sg:address":"Plaz Espa\u00d1a, 4",
    "sg:city":"Binaced",
    "sg:orig_category":"Bancos",
    "sg:phone":"+34 974 42 74 51",
    "sg:postcode":"22510",
    "sg:province":"Huesca",
    "wof:name":"Ballarin Alaman Angeles",
    "wof:placetype":"venue"
},
  "geometry": {"coordinates":[0.200443998,41.8266868591],"type":"Point"}
}