{
  "type": "Feature",
  "properties": {
    "iso:country":"ES",
    "sg:address":"Calle de San Benito, 2",
    "sg:city":"Ecija",
    "sg:orig_category":"Empresarios Y Productoras De Espect\u00c1culos",
    "sg:phone":"+34 954 83 02 43",
    "sg:postcode":"41400",
    "sg:province":"Sevilla",
    "wof:name":"Ca\u00f1as Diaz Jose",
    "wof:placetype":"venue"
},
  "geometry": {"coordinates":[-5.0838627815,37.532661438],"type":"Point"}
}