{
  "type": "Feature",
  "properties": {
    "iso:country":"ES",
    "sg:address":"Calle de Lerida, 3",
    "sg:city":"Madrid",
    "sg:orig_category":"Venta, Instalaci\u00d3n, Mantenimiento De Chimeneas De Interior Y Accesorios",
    "sg:phone":"+34 915 71 55 37",
    "sg:postcode":"28020",
    "sg:province":"Madrid",
    "wof:name":"Airfex Ingenieria S.l.",
    "wof:placetype":"venue"
},
  "geometry": {"coordinates":[-3.7014067173,40.4520339966],"type":"Point"}
}