{
  "type": "Feature",
  "properties": {
    "addr:full":"Carr Dalt, 9 Masos De Pals Girona 17256",
    "addr:housenumber":"9",
    "addr:postcode":"17256",
    "addr:street":"Carr Dalt",
    "iso:country":"ES",
    "sg:address":"Carr Dalt, 9",
    "sg:city":"Masos De Pals",
    "sg:orig_category":"Fabricaci\u00d3n, Importaci\u00d3n De L\u00c1mparas Y Bombillas",
    "sg:phone":"+34 972 63 68 97",
    "sg:postcode":"17256",
    "sg:province":"Girona",
    "wof:name":"Riembau Rue Pedro",
    "wof:placetype":"venue"
},
  "geometry": {"coordinates":[3.1482629776,41.9678573608],"type":"Point"}
}