{
  "type": "Feature",
  "properties": {
    "addr:full":"Rua Profesor Eloy Mira, 5 Barco Ourense 32300",
    "addr:housenumber":"5",
    "addr:postcode":"32300",
    "addr:street":"Rua Profesor Eloy Mira",
    "iso:country":"ES",
    "sg:address":"Rua Profesor Eloy Mira, 5",
    "sg:city":"Barco",
    "sg:orig_category":"M\u00c9dicos: Estomatolog\u00cda",
    "sg:phone":"+34 988 32 74 75",
    "sg:postcode":"32300",
    "sg:province":"Ourense",
    "wof:name":"Mendez Diaz Francisco",
    "wof:placetype":"venue"
},
  "geometry": {"coordinates":[-6.9811491966,42.4160003662],"type":"Point"}
}