{
  "type": "Feature",
  "properties": {
    "iso:country":"ES",
    "sg:address":"Calle de Fernandez Ardavin, 3",
    "sg:city":"Calatayud",
    "sg:orig_category":"Museos",
    "sg:phone":"+34 976 88 16 73",
    "sg:postcode":"50300",
    "sg:province":"Zaragoza",
    "wof:name":"Ayuntamiento De Calatayud",
    "wof:placetype":"venue"
},
  "geometry": {"coordinates":[-1.6465907097,41.3517417908],"type":"Point"}
}