{
  "type": "Feature",
  "properties": {
    "iso:country":"ES",
    "sg:address":"Ctra San Andres, 26",
    "sg:city":"Ba\u00f1aderos-san Andres",
    "sg:orig_category":"Fabricaci\u00d3n, Venta De Cuadros, Accesorios Para Enmarcar",
    "sg:phone":"+34 928 62 63 82",
    "sg:postcode":"35414",
    "sg:province":"Las Palmas",
    "wof:name":"Aleman Gonzalez Manuel",
    "wof:placetype":"venue"
},
  "geometry": {"coordinates":[-15.5541639328,28.1453914642],"type":"Point"}
}