{
  "type": "Feature",
  "properties": {
    "addr:full":"Alcoy, 19 Banyeres Mariola Alicante 03450",
    "addr:housenumber":"19",
    "addr:postcode":"03450",
    "addr:street":"Alcoy",
    "iso:country":"ES",
    "sg:address":"Alcoy, 19",
    "sg:city":"Banyeres Mariola",
    "sg:orig_category":"Mec\u00c1nico Del Autom\u00d3vil",
    "sg:phone":"+34 965 56 71 25",
    "sg:postcode":"03450",
    "sg:province":"Alicante",
    "wof:name":"Talleres Motor Start S.l.",
    "wof:placetype":"venue"
},
  "geometry": {"coordinates":[-0.657400012,38.7120323181],"type":"Point"}
}