{
  "type": "Feature",
  "properties": {
    "addr:full":"Calle de Federico Garcia Lorca, 94 Gibraleon Huelva 21500",
    "addr:housenumber":"94",
    "addr:postcode":"21500",
    "addr:street":"Calle De Federico Garcia Lorca",
    "iso:country":"ES",
    "sg:address":"Calle de Federico Garcia Lorca, 94",
    "sg:city":"Gibraleon",
    "sg:orig_category":"Carnicer\u00cdas, Carnicer\u00cdas",
    "sg:phone":"+34 959 30 14 80",
    "sg:postcode":"21500",
    "sg:province":"Huelva",
    "wof:name":"Garcia Fernandez Jose",
    "wof:placetype":"venue"
},
  "geometry": {"coordinates":[-6.9689598083,37.3732147217],"type":"Point"}
}