{
  "type": "Feature",
  "properties": {
    "addr:full":"Pol. Ind. De Somonte, S/n Cenero Asturias 33393",
    "addr:housenumber":"s / n",
    "addr:postcode":"33393",
    "iso:country":"ES",
    "sg:address":"Pol. Ind. De Somonte, S/n",
    "sg:city":"Cenero",
    "sg:orig_category":"Papel (al Por Mayor)",
    "sg:phone":"+34 985 30 13 00",
    "sg:postcode":"33393",
    "sg:province":"Asturias",
    "wof:name":"Ceferino Alvarez S.l.",
    "wof:placetype":"venue"
},
  "geometry": {"coordinates":[-5.7263522148,43.507850647],"type":"Point"}
}