{
  "type": "Feature",
  "properties": {
    "addr:full":"Calle de Bronce, S/n Leganes Madrid 28914",
    "addr:housenumber":"s / n",
    "addr:postcode":"28914",
    "addr:street":"Calle De Bronce",
    "iso:country":"ES",
    "sg:address":"Calle de Bronce, S/n",
    "sg:city":"Leganes",
    "sg:orig_category":"Agencias Y Asesores De Publicidad",
    "sg:phone":"+34 916 93 98 88",
    "sg:postcode":"28914",
    "sg:province":"Madrid",
    "wof:name":"Unimail S.a.",
    "wof:placetype":"venue"
},
  "geometry": {"coordinates":[-3.7769827843,40.3276481628],"type":"Point"}
}