{
  "type": "Feature",
  "properties": {
    "iso:country":"ES",
    "sg:address":"Calle de San Miguel De Atxa, 23",
    "sg:city":"Vitoria-gasteiz",
    "sg:orig_category":"Metales (labores, Pulido)",
    "sg:phone":"+34 945 24 31 66",
    "sg:postcode":"01010",
    "sg:province":"\u00c1lava",
    "wof:name":"Estampaciones Puma S.a.",
    "wof:placetype":"venue"
},
  "geometry": {"coordinates":[-2.7080938816,42.8644752502],"type":"Point"}
}