{
  "type": "Feature",
  "properties": {
    "addr:full":"Rond Alfons Xii, 87 Mataro Barcelona 08302",
    "addr:postcode":"08302",
    "iso:country":"ES",
    "sg:address":"Rond Alfons Xii, 87",
    "sg:city":"Mataro",
    "sg:orig_category":"Centros De Educaci\u00d3n Especial",
    "sg:phone":"+34 937 98 29 93",
    "sg:postcode":"08302",
    "sg:province":"Barcelona",
    "wof:name":"Fundacio El Maresme",
    "wof:placetype":"venue"
},
  "geometry": {"coordinates":[2.4377861023,41.5361595154],"type":"Point"}
}