{
  "type": "Feature",
  "properties": {
    "iso:country":"ES",
    "sg:address":"Calle de Solana, 19",
    "sg:city":"Alsasua",
    "sg:orig_category":"Porcelanas, Azulejos (fabricaci\u00d3n, Al Por Mayor)",
    "sg:phone":"+34 948 46 72 32",
    "sg:postcode":"31800",
    "sg:province":"Navarra",
    "wof:name":"Aratz Proyect S.l.",
    "wof:placetype":"venue"
},
  "geometry": {"coordinates":[-2.1675333977,42.893787384],"type":"Point"}
}