{
  "type": "Feature",
  "properties": {
    "iso:country":"ES",
    "sg:address":"Av Cornella, 63",
    "sg:city":"Esplugues Llobregat",
    "sg:orig_category":"Mercer\u00cda, Lencer\u00cda (al Por Menor)",
    "sg:phone":"+34 934 99 01 32",
    "sg:postcode":"08950",
    "sg:province":"Barcelona",
    "wof:name":"Sans Banal Carmen",
    "wof:placetype":"venue"
},
  "geometry": {"coordinates":[2.0856399536,41.3741874695],"type":"Point"}
}