{
  "type": "Feature",
  "properties": {
    "iso:country":"ES",
    "sg:address":"Ctra. Lluc, 321",
    "sg:city":"Inca",
    "sg:orig_category":"Zapatos (al Por Menor)",
    "sg:phone":"+34 971 50 28 86",
    "sg:postcode":"07300",
    "sg:province":"Islas Baleares",
    "wof:name":"Ramis Martinez Juan",
    "wof:placetype":"venue"
},
  "geometry": {"coordinates":[2.9111759663,39.7279968262],"type":"Point"}
}