{
  "type": "Feature",
  "properties": {
    "addr:full":"Calle de Natividad, 21 Guadamur Toledo 45160",
    "addr:housenumber":"21",
    "addr:postcode":"45160",
    "addr:street":"Calle De Natividad",
    "iso:country":"ES",
    "sg:address":"Calle de Natividad, 21",
    "sg:city":"Guadamur",
    "sg:orig_category":"Peluquer\u00cdas, Peluquer\u00cda Mixta",
    "sg:phone":"+34 925 29 13 42",
    "sg:postcode":"45160",
    "sg:province":"Toledo",
    "wof:name":"Peluqueria Dorita C.b.",
    "wof:placetype":"venue"
},
  "geometry": {"coordinates":[-4.1476521492,39.810874939],"type":"Point"}
}