{
  "type": "Feature",
  "properties": {
    "iso:country":"ES",
    "sg:address":"Ctra Madrid-irun(oeste), 2",
    "sg:city":"Aranda Duero",
    "sg:orig_category":"Transporte En General",
    "sg:phone":"+34 947 51 30 18",
    "sg:postcode":"09400",
    "sg:province":"Burgos",
    "wof:name":"P.s.h. Velasco S.l.",
    "wof:placetype":"venue"
},
  "geometry": {"coordinates":[-3.685338974,41.6884841919],"type":"Point"}
}