{
  "type": "Feature",
  "properties": {
    "addr:full":"Plaz Castellini, 12 Cartagena Murcia 30201",
    "addr:housenumber":"12",
    "addr:postcode":"30201",
    "addr:street":"Plaz Castellini",
    "iso:country":"ES",
    "sg:address":"Plaz Castellini, 12",
    "sg:city":"Cartagena",
    "sg:orig_category":"Empresas De Limpieza",
    "sg:phone":"+34 968 52 90 32",
    "sg:postcode":"30201",
    "sg:province":"Murcia",
    "wof:name":"Bayo Garcia Paz",
    "wof:placetype":"venue"
},
  "geometry": {"coordinates":[-0.9875789881,37.6026611328],"type":"Point"}
}