{
  "type": "Feature",
  "properties": {
    "iso:country":"ES",
    "sg:address":"Carrer de Baix, 46",
    "sg:city":"Esparreguera",
    "sg:orig_category":"Locales Y Clases De Danza",
    "sg:phone":"+34 937 77 55 63",
    "sg:postcode":"08292",
    "sg:province":"Barcelona",
    "wof:name":"Monfort Agramunt Gemma",
    "wof:placetype":"venue"
},
  "geometry": {"coordinates":[1.8698949814,41.5376739502],"type":"Point"}
}