{
  "type": "Feature",
  "properties": {
    "iso:country":"ES",
    "sg:address":"Luga Pantano Roto, S/n",
    "sg:city":"Salto Del Agua",
    "sg:orig_category":"Centros Empresariales",
    "sg:phone":"+34 952 78 21 18",
    "sg:postcode":"29670",
    "sg:province":"M\u00e1laga",
    "wof:name":"Captains Wear House S.l",
    "wof:placetype":"venue"
},
  "geometry": {"coordinates":[-4.9902391434,36.4866333008],"type":"Point"}
}