{
  "type": "Feature",
  "properties": {
    "addr:full":"Calle de San Lucas, 13 Aljorra Murcia 30390",
    "addr:housenumber":"13",
    "addr:postcode":"30390",
    "addr:street":"Calle De San Lucas",
    "iso:country":"ES",
    "sg:address":"Calle de San Lucas, 13",
    "sg:city":"Aljorra",
    "sg:orig_category":"Bazares, Art\u00cdculos De Limpieza Y De Cocina (al Por Menor)",
    "sg:phone":"+34 968 55 82 75",
    "sg:postcode":"30390",
    "sg:province":"Murcia",
    "wof:name":"Electrosabi Scp",
    "wof:placetype":"venue"
},
  "geometry": {"coordinates":[-1.0664969683,37.689655304],"type":"Point"}
}