{
  "type": "Feature",
  "properties": {
    "addr:full":"Pl Major, 5 Flix Tarragona 43750",
    "addr:housenumber":"5",
    "addr:postcode":"43750",
    "addr:street":"Pl Major",
    "iso:country":"ES",
    "sg:address":"Pl Major, 5",
    "sg:city":"Flix",
    "sg:orig_category":"Venta, Instalaci\u00d3n De Cocinas",
    "sg:phone":"+34 977 41 13 11",
    "sg:postcode":"43750",
    "sg:province":"Tarragona",
    "wof:name":"Castro Terre Rafael",
    "wof:placetype":"venue"
},
  "geometry": {"coordinates":[0.5501670241,41.2315788269],"type":"Point"}
}