{
  "type": "Feature",
  "properties": {
    "addr:full":"Pase Cidacos, 13 Autol La Rioja 26560",
    "addr:housenumber":"13",
    "addr:postcode":"26560",
    "addr:street":"Cidacos;Rioja",
    "iso:country":"ES",
    "sg:address":"Pase Cidacos, 13",
    "sg:city":"Autol",
    "sg:orig_category":"Peluqueros: De Se\u00d1oras",
    "sg:phone":"+34 941 40 14 26",
    "sg:postcode":"26560",
    "sg:province":"La Rioja",
    "wof:name":"Cristobal Jimenez Nuria",
    "wof:placetype":"venue"
},
  "geometry": {"coordinates":[-2.0035309792,42.2143287659],"type":"Point"}
}