{
  "type": "Feature",
  "properties": {
    "iso:country":"ES",
    "sg:address":"Carr Pobla (la), 53",
    "sg:city":"Granadella",
    "sg:orig_category":"Farmacias",
    "sg:phone":"+34 973 13 32 95",
    "sg:postcode":"25177",
    "sg:province":"Lleida",
    "wof:name":"Pena Arnaiz Jose Luis",
    "wof:placetype":"venue"
},
  "geometry": {"coordinates":[0.6685199738,41.3533248901],"type":"Point"}
}