{
  "type": "Feature",
  "properties": {
    "iso:country":"ES",
    "sg:address":"Calle de Autindana, 45",
    "sg:city":"Cruce De Arinaga",
    "sg:orig_category":"Quincaller\u00cda (al Por Menor)",
    "sg:phone":"+34 928 18 01 47",
    "sg:postcode":"35118",
    "sg:province":"Las Palmas",
    "wof:name":"Antonio Guedes Lopez S.l.",
    "wof:placetype":"venue"
},
  "geometry": {"coordinates":[-15.4270515442,27.8806095123],"type":"Point"}
}