{
  "type": "Feature",
  "properties": {
    "addr:full":"Avda Montecillo, S/n Aranda Duero Burgos 09400",
    "addr:housenumber":"s / n",
    "addr:postcode":"09400",
    "addr:street":"Avda Montecillo",
    "iso:country":"ES",
    "sg:address":"Avda Montecillo, S/n",
    "sg:city":"Aranda Duero",
    "sg:orig_category":"Acondicionamiento De Terrenos Para Deporte Y Juegos",
    "sg:phone":"+34 947 50 14 21",
    "sg:postcode":"09400",
    "sg:province":"Burgos",
    "wof:name":"Ayuntamiento De Aranda De Duero",
    "wof:placetype":"venue"
},
  "geometry": {"coordinates":[-3.7064871788,41.6718711853],"type":"Point"}
}