{
  "type": "Feature",
  "properties": {
    "iso:country":"ES",
    "sg:address":"Carrer de Moli, 4",
    "sg:city":"Esplugues Llobregat",
    "sg:orig_category":"Par\u00cds",
    "sg:phone":"+34 934 73 18 18",
    "sg:postcode":"08950",
    "sg:province":"Barcelona",
    "wof:name":"Ortiz Buiza Juan Jose",
    "wof:placetype":"venue"
},
  "geometry": {"coordinates":[2.0985639095,41.3703956604],"type":"Point"}
}