{
  "type": "Feature",
  "properties": {
    "iso:country":"ES",
    "sg:address":"Carretera Galera, 16",
    "sg:city":"Sta. Barbara",
    "sg:orig_category":"Institutos De Belleza",
    "sg:phone":"+34 977 71 83 54",
    "sg:postcode":"43570",
    "sg:province":"Tarragona",
    "wof:name":"Fava Bel Maria Luisa",
    "wof:placetype":"venue"
},
  "geometry": {"coordinates":[0.4884600043,40.7129096985],"type":"Point"}
}