{
  "type": "Feature",
  "properties": {
    "addr:full":"Ctra Balsareny, 113 Suria Barcelona 08260",
    "addr:housenumber":"113",
    "addr:postcode":"08260",
    "addr:street":"Ctra Balsareny",
    "iso:country":"ES",
    "sg:address":"Ctra Balsareny, 113",
    "sg:city":"Suria",
    "sg:orig_category":"Agencias De Viajes",
    "sg:phone":"+34 938 69 50 25",
    "sg:postcode":"08260",
    "sg:province":"Barcelona",
    "sg:website":"www.fspromotur.com",
    "wof:name":"E F S Promotur 2000 S.l.",
    "wof:placetype":"venue"
},
  "geometry": {"coordinates":[1.762493968,41.8345146179],"type":"Point"}
}