{
  "type": "Feature",
  "properties": {
    "addr:full":"Calle de Buenavista, 16 Madrid Madrid 28012",
    "addr:housenumber":"16",
    "addr:postcode":"madrid;28012",
    "addr:street":"Calle De Buenavista",
    "iso:country":"ES",
    "sg:address":"Calle de Buenavista, 16",
    "sg:city":"Madrid",
    "sg:orig_category":"Cueros Y Pieles (al Por Mayor)",
    "sg:phone":"+34 914 68 41 27",
    "sg:postcode":"28012",
    "sg:province":"Madrid",
    "wof:name":"Menendez Garcia Gerardo",
    "wof:placetype":"venue"
},
  "geometry": {"coordinates":[-3.6988694668,40.4101448059],"type":"Point"}
}