{
  "type": "Feature",
  "properties": {
    "addr:full":"Plaz Virgen Del Romero, 4 Madrid Madrid 28027",
    "addr:housenumber":"4",
    "addr:postcode":"28027",
    "addr:street":"Plaz Virgen Del Romero",
    "iso:country":"ES",
    "sg:address":"Plaz Virgen Del Romero, 4",
    "sg:city":"Madrid",
    "sg:orig_category":"Centros Empresariales",
    "sg:phone":"+34 914 04 76 61",
    "sg:postcode":"28027",
    "sg:province":"Madrid",
    "wof:name":"Consultores Pesqueros S.l.",
    "wof:placetype":"venue"
},
  "geometry": {"coordinates":[-3.6586899757,40.4336433411],"type":"Point"}
}