{
  "type": "Feature",
  "properties": {
    "iso:country":"ES",
    "sg:address":"Calle de Vendeja, 30",
    "sg:city":"Malaga",
    "sg:orig_category":"Bazares, Art\u00cdculos De Limpieza Y De Cocina (al Por Menor)",
    "sg:phone":"+34 952 21 16 44",
    "sg:postcode":"29001",
    "sg:province":"M\u00e1laga",
    "wof:name":"Comercial Mate C.b.",
    "wof:placetype":"venue"
},
  "geometry": {"coordinates":[-4.4236288071,36.7164421082],"type":"Point"}
}