{
  "type": "Feature",
  "properties": {
    "addr:full":"Calle de Ave Maria, 25 Ponferrada Le\u00f3n 24400",
    "addr:housenumber":"25",
    "addr:postcode":"24400",
    "addr:street":"Calle De Ave Maria",
    "iso:country":"ES",
    "sg:address":"Calle de Ave Maria, 25",
    "sg:city":"Ponferrada",
    "sg:orig_category":"Restaurantes",
    "sg:phone":"+34 987 42 58 14",
    "sg:postcode":"24400",
    "sg:province":"Le\u00f3n",
    "wof:name":"Lopez Lopez Luis",
    "wof:placetype":"venue"
},
  "geometry": {"coordinates":[-6.6023397446,42.5477905273],"type":"Point"}
}