{
  "type": "Feature",
  "properties": {
    "iso:country":"ES",
    "sg:address":"Calle de Fortuny, 3",
    "sg:city":"Madrid",
    "sg:orig_category":"Fabricaci\u00d3n, Venta, Instalaci\u00d3n De R\u00d3tulos, De R\u00d3tulos Luminosos",
    "sg:phone":"+34 913 10 29 22",
    "sg:postcode":"28010",
    "sg:province":"Madrid",
    "wof:name":"Aplicca Identity Solutions S.l.",
    "wof:placetype":"venue"
},
  "geometry": {"coordinates":[-3.6911017895,40.4283676147],"type":"Point"}
}