{
  "type": "Feature",
  "properties": {
    "iso:country":"ES",
    "sg:address":"Carretera Centro, 19",
    "sg:city":"Guijo Santa Barbara",
    "sg:orig_category":"C\u00c1maras De Comercio E Industria, Oficios, Agricultura",
    "sg:phone":"+34 927 56 02 66",
    "sg:postcode":"10459",
    "sg:province":"C\u00e1ceres",
    "wof:name":"Sociedad Cooperativa Agroganadera Nuestra Se\u00f1ora De Las Nieves",
    "wof:placetype":"venue"
},
  "geometry": {"coordinates":[-5.655064106,40.1535835266],"type":"Point"}
}