{
  "type": "Feature",
  "properties": {
    "iso:country":"ES",
    "sg:address":"Calle de Virgen De Las Virtudes, 6",
    "sg:city":"Alacant",
    "sg:orig_category":"Material Y Suministros Para Peluquer\u00cda",
    "sg:phone":"+34 965 17 38 09",
    "sg:postcode":"03009",
    "sg:province":"Alicante",
    "wof:name":"Carcases Selles Vanessa",
    "wof:placetype":"venue"
},
  "geometry": {"coordinates":[-0.4976109862,38.3683013916],"type":"Point"}
}