{
  "type": "Feature",
  "properties": {
    "iso:country":"ES",
    "sg:address":"Calle de Acera Fleming, 7",
    "sg:city":"Cabra",
    "sg:orig_category":"Reposter\u00cdas",
    "sg:phone":"+34 957 52 52 12",
    "sg:postcode":"14940",
    "sg:province":"C\u00f3rdoba",
    "wof:name":"Panaderia Ariza Jurado S.l.",
    "wof:placetype":"venue"
},
  "geometry": {"coordinates":[-4.4288678169,37.4760246277],"type":"Point"}
}