{
  "type": "Feature",
  "properties": {
    "addr:full":"Marmoleja, 11 Almonte Huelva 21730",
    "addr:housenumber":"11",
    "addr:postcode":"21730",
    "addr:street":"Marmoleja",
    "iso:country":"ES",
    "sg:address":"Marmoleja, 11",
    "sg:city":"Almonte",
    "sg:orig_category":"Centros De Coordinaci\u00d3n",
    "sg:phone":"+34 959 45 16 42",
    "sg:postcode":"21730",
    "sg:province":"Huelva",
    "wof:name":"Iglesias Garcia Maria Alfonsa",
    "wof:placetype":"venue"
},
  "geometry": {"coordinates":[-6.5150170326,37.2575836182],"type":"Point"}
}