{
  "type": "Feature",
  "properties": {
    "iso:country":"ES",
    "sg:address":"Pase Ronda, S/n",
    "sg:city":"Melilla",
    "sg:orig_category":"Centros De Educaci\u00d3n Especial",
    "sg:phone":"+34 952 67 42 53",
    "sg:postcode":"52005",
    "sg:province":"Melilla",
    "wof:name":"Centro De Educacion De Personas Adultas",
    "wof:placetype":"venue"
},
  "geometry": {"coordinates":[-2.9556701183,35.2835693359],"type":"Point"}
}