{
  "type": "Feature",
  "properties": {
    "iso:country":"ES",
    "sg:address":"Cno Vistabella (miralbueno), 209",
    "sg:city":"Zaragoza",
    "sg:orig_category":"Asilos De Ancianos. Centros Privados",
    "sg:phone":"+34 976 78 30 80",
    "sg:postcode":"50011",
    "sg:province":"Zaragoza",
    "wof:name":"Congregacion Hermanas Angelicas",
    "wof:placetype":"venue"
},
  "geometry": {"coordinates":[-0.9419389963,41.6605682373],"type":"Point"}
}