{
  "type": "Feature",
  "properties": {
    "iso:country":"ES",
    "sg:address":"Calle de San Basilio, 3",
    "sg:city":"Cartagena",
    "sg:orig_category":"Reposter\u00cdas",
    "sg:phone":"+34 968 52 43 01",
    "sg:postcode":"30205",
    "sg:province":"Murcia",
    "wof:name":"Nieto Perez Juana",
    "wof:placetype":"venue"
},
  "geometry": {"coordinates":[-0.9606140256,37.594997406],"type":"Point"}
}