{
  "type": "Feature",
  "properties": {
    "addr:full":"Calle de Herrador, 8 Puerto Santiago Santa Cruz De Tenerife 38683",
    "addr:housenumber":"8",
    "addr:postcode":"38683",
    "addr:street":"Calle De Herrador",
    "iso:country":"ES",
    "sg:address":"Calle de Herrador, 8",
    "sg:city":"Puerto Santiago",
    "sg:orig_category":"Centros De Coordinaci\u00d3n",
    "sg:phone":"+34 922 86 01 07",
    "sg:postcode":"38683",
    "sg:province":"Santa Cruz De Tenerife",
    "wof:name":"Gonzalez Oliver Reinaldo",
    "wof:placetype":"venue"
},
  "geometry": {"coordinates":[-16.8412456512,28.2312526703],"type":"Point"}
}