{
  "type": "Feature",
  "properties": {
    "addr:full":"Avda Montecillo, 14 Aranda Duero Burgos 09400",
    "addr:housenumber":"14",
    "addr:postcode":"09400",
    "addr:street":"Avda Montecillo",
    "iso:country":"ES",
    "sg:address":"Avda Montecillo, 14",
    "sg:city":"Aranda Duero",
    "sg:orig_category":"Autob\u00das (explotaci\u00d3n Y Servicios De)",
    "sg:phone":"+34 947 51 13 21",
    "sg:postcode":"09400",
    "sg:province":"Burgos",
    "wof:name":"Autocares Victor Bayo S.l",
    "wof:placetype":"venue"
},
  "geometry": {"coordinates":[-3.7064871788,41.6718711853],"type":"Point"}
}