{
  "type": "Feature",
  "properties": {
    "addr:full":"Avda Pablo Picasso, 79 Roquetas Mar Almer\u00eda 04740",
    "addr:housenumber":"79",
    "addr:postcode":"04740",
    "addr:street":"Avda Pablo Picasso;Mar Almeri\u0301A",
    "iso:country":"ES",
    "sg:address":"Avda Pablo Picasso, 79",
    "sg:city":"Roquetas Mar",
    "sg:orig_category":"Frutas Y Legumbres Frescas (al Por Mayor)",
    "sg:phone":"+34 950 32 06 55",
    "sg:postcode":"04740",
    "sg:province":"Almer\u00eda",
    "wof:name":"Antonio Moreno Y Rafael Sanchez Cdad",
    "wof:placetype":"venue"
},
  "geometry": {"coordinates":[-2.6228797436,36.762840271],"type":"Point"}
}