{
  "type": "Feature",
  "properties": {
    "iso:country":"ES",
    "sg:address":"Carr Bisbe Ruano, 13",
    "sg:city":"Lleida",
    "sg:orig_category":"Arquitectos",
    "sg:phone":"+34 973 27 94 92",
    "sg:postcode":"25006",
    "sg:province":"Lleida",
    "wof:name":"Planning Planificacio Seguiment I Control S.l.",
    "wof:placetype":"venue"
},
  "geometry": {"coordinates":[0.6178380251,41.6171798706],"type":"Point"}
}