{
  "type": "Feature",
  "properties": {
    "iso:country":"ES",
    "sg:address":"Trva Fuentecilla, 3",
    "sg:city":"Villaviciosa Odon",
    "sg:orig_category":"Cl\u00cdnicas M\u00c9dicas",
    "sg:phone":"+34 916 16 56 56",
    "sg:postcode":"28670",
    "sg:province":"Madrid",
    "wof:name":"Centro Medico Summer S.a.",
    "wof:placetype":"venue"
},
  "geometry": {"coordinates":[-3.9060781002,40.3566017151],"type":"Point"}
}