{
  "type": "Feature",
  "properties": {
    "addr:full":"Calle de Florida (la), S/n Florida Murcia 30565",
    "addr:postcode":"30565",
    "addr:street":"Calle De Florida La S / N",
    "iso:country":"ES",
    "sg:address":"Calle de Florida (la), S/n",
    "sg:city":"Florida",
    "sg:orig_category":"Comercio, Reparaci\u00d3n De Motocicletas, Bicicletas Y Piezas Sueltas",
    "sg:phone":"+34 968 62 74 60",
    "sg:postcode":"30565",
    "sg:province":"Murcia",
    "wof:name":"Ciclos Sarabia S.l.",
    "wof:placetype":"venue"
},
  "geometry": {"coordinates":[-1.2445640564,38.0440254211],"type":"Point"}
}