{
  "type": "Feature",
  "properties": {
    "iso:country":"ES",
    "sg:address":"Crta Viver-pto Burriana, Km. 0006,0",
    "sg:city":"Vila-real",
    "sg:orig_category":"Cer\u00c1mica Art\u00cdstica Y Decorativa",
    "sg:phone":"+34 964 62 60 33",
    "sg:postcode":"12540",
    "sg:province":"Castell\u00f3n",
    "wof:name":"Ceramica Evana S.l.",
    "wof:placetype":"venue"
},
  "geometry": {"coordinates":[-0.0952899978,39.9453010559],"type":"Point"}
}