{
  "type": "Feature",
  "properties": {
    "iso:country":"ES",
    "sg:address":"Calle de Paseo Chico, 14",
    "sg:city":"Fontiveros",
    "sg:orig_category":"Arquitectos",
    "sg:phone":"+34 920 24 50 79",
    "sg:postcode":"05310",
    "sg:province":"\u00c1vila",
    "wof:name":"Diaz Delgado Jose Antonio",
    "wof:placetype":"venue"
},
  "geometry": {"coordinates":[-4.9613490105,40.9290504456],"type":"Point"}
}