{
  "type": "Feature",
  "properties": {
    "iso:country":"ES",
    "sg:address":"Carrer de Jesus I Maria, 4",
    "sg:city":"Barcelona",
    "sg:orig_category":"Centros De Educaci\u00d3n Especial",
    "sg:phone":"+34 934 17 52 71",
    "sg:postcode":"08022",
    "sg:province":"Barcelona",
    "wof:name":"Fundacio Privada Escola Decroly De Barcelona",
    "wof:placetype":"venue"
},
  "geometry": {"coordinates":[2.1338100433,41.4093360901],"type":"Point"}
}