{
  "type": "Feature",
  "properties": {
    "iso:country":"ES",
    "sg:address":"Calle de Santa Aurora, 2",
    "sg:city":"Tomelloso",
    "sg:orig_category":"Fabricaci\u00d3n, Importaci\u00d3n De Material Y Sistemas De Telecomunicaciones",
    "sg:phone":"+34 926 50 10 15",
    "sg:postcode":"13700",
    "sg:province":"Ciudad Real",
    "sg:website":"www.decomtel.com",
    "wof:name":"Decomtel La Mancha S.l.",
    "wof:placetype":"venue"
},
  "geometry": {"coordinates":[-3.0246090889,39.1513442993],"type":"Point"}
}