{
  "type": "Feature",
  "properties": {
    "iso:country":"ES",
    "sg:address":"Pg Valldaura, 192",
    "sg:city":"Barcelona",
    "sg:orig_category":"Peluqueros: De Se\u00d1oras",
    "sg:phone":"+34 933 54 17 83",
    "sg:postcode":"08042",
    "sg:province":"Barcelona",
    "wof:name":"Fernandez Felipe Antonio",
    "wof:placetype":"venue"
},
  "geometry": {"coordinates":[2.1726820469,41.4384689331],"type":"Point"}
}