{
  "type": "Feature",
  "properties": {
    "iso:country":"ES",
    "sg:address":"Carrer de Sant Joan, 3",
    "sg:city":"Mataro",
    "sg:orig_category":"Pintura Industrial (trabajos De)",
    "sg:phone":"+34 937 55 60 59",
    "sg:postcode":"08301",
    "sg:province":"Barcelona",
    "sg:website":"www.aida-sl.com",
    "wof:name":"Aida S.l.",
    "wof:placetype":"venue"
},
  "geometry": {"coordinates":[2.447742939,41.5383872986],"type":"Point"}
}