{
  "type": "Feature",
  "properties": {
    "addr:full":"Urbanizacion Albardinal, S/n Mojacar Almer\u00eda 04638",
    "addr:housenumber":"s",
    "addr:postcode":"04638",
    "addr:street":"/ N;Almeri\u0301A",
    "iso:country":"ES",
    "sg:address":"Urbanizacion Albardinal, S/n",
    "sg:city":"Mojacar",
    "sg:orig_category":"Restaurantes",
    "sg:phone":"+34 950 47 57 74",
    "sg:postcode":"04638",
    "sg:province":"Almer\u00eda",
    "wof:name":"Modus Hispanica S.l.",
    "wof:placetype":"venue"
},
  "geometry": {"coordinates":[-1.8295990229,37.1382598877],"type":"Point"}
}