{
  "type": "Feature",
  "properties": {
    "iso:country":"ES",
    "sg:address":"Calle de Arrabaleria, 61",
    "sg:city":"Algodonales",
    "sg:orig_category":"Alquiler De Casas Y Habitaciones Amuebladas",
    "sg:phone":"+34 956 13 78 82",
    "sg:postcode":"11680",
    "sg:province":"C\u00e1diz",
    "wof:name":"Al-qutun Agroturismo S.l.l.",
    "wof:placetype":"venue"
},
  "geometry": {"coordinates":[-5.4110479355,36.8775024414],"type":"Point"}
}