{
  "type": "Feature",
  "properties": {
    "addr:full":"Rua Andalucia, 6 Vigo Pontevedra 36205",
    "addr:housenumber":"6",
    "addr:postcode":"36205",
    "addr:street":"Rua Andalucia",
    "iso:country":"ES",
    "sg:address":"Rua Andalucia, 6",
    "sg:city":"Vigo",
    "sg:orig_category":"Molduras, Junquillos, Listones Y Molduras Perforadas",
    "sg:phone":"+34 986 25 30 28",
    "sg:postcode":"36205",
    "sg:province":"Pontevedra",
    "wof:name":"Meira Lago Maria Luisa",
    "wof:placetype":"venue"
},
  "geometry": {"coordinates":[-8.7049026489,42.230556488],"type":"Point"}
}