{
  "type": "Feature",
  "properties": {
    "iso:country":"ES",
    "sg:address":"Carr Monestir De Vallbona, 21",
    "sg:city":"Lleida",
    "sg:orig_category":"Asesores De Gesti\u00d3n Del Patrimonio",
    "sg:phone":"+34 973 23 95 43",
    "sg:postcode":"25199",
    "sg:province":"Lleida",
    "wof:name":"Primigrup S.l.",
    "wof:placetype":"venue"
},
  "geometry": {"coordinates":[0.6014419794,41.6290512085],"type":"Point"}
}