{
  "type": "Feature",
  "properties": {
    "addr:full":"Arry Colmenas (de Las), S/n Ceuta Ceuta 51002",
    "addr:postcode":"51002",
    "addr:street":"S / N",
    "iso:country":"ES",
    "sg:address":"Arry Colmenas (de Las), S/n",
    "sg:city":"Ceuta",
    "sg:orig_category":"Transporte En General",
    "sg:phone":"+34 956 52 13 04",
    "sg:postcode":"51002",
    "sg:province":"Ceuta",
    "wof:name":"Hamed Mohamed Mohamed",
    "wof:placetype":"venue"
},
  "geometry": {"coordinates":[-5.3299298286,35.8878097534],"type":"Point"}
}