{
  "type": "Feature",
  "properties": {
    "addr:full":"Carrer de Sant Pere, 44 Altea Alicante 03590",
    "addr:housenumber":"44",
    "addr:postcode":"03590",
    "addr:street":"Carrer De Sant Pere",
    "iso:country":"ES",
    "sg:address":"Carrer de Sant Pere, 44",
    "sg:city":"Altea",
    "sg:orig_category":"Restaurantes",
    "sg:phone":"+34 965 84 26 18",
    "sg:postcode":"03590",
    "sg:province":"Alicante",
    "wof:name":"Sanchez Lopez Maria Pilar",
    "wof:placetype":"venue"
},
  "geometry": {"coordinates":[-0.0544830002,38.5929603577],"type":"Point"}
}