{
  "type": "Feature",
  "properties": {
    "iso:country":"ES",
    "sg:address":"Carrer de Major (sant Celoni), 84",
    "sg:city":"S. Celoni",
    "sg:orig_category":"Librer\u00cdas",
    "sg:phone":"+34 938 67 07 91",
    "sg:postcode":"08470",
    "sg:province":"Barcelona",
    "wof:name":"Dou Costa Josep",
    "wof:placetype":"venue"
},
  "geometry": {"coordinates":[2.489470005,41.6888542175],"type":"Point"}
}