{
  "type": "Feature",
  "properties": {
    "iso:country":"ES",
    "sg:address":"Rua Damas Apostolicas, 8",
    "sg:city":"Ramallosa",
    "sg:orig_category":"Arquitectos",
    "sg:phone":"+34 986 38 61 21",
    "sg:postcode":"36379",
    "sg:province":"Pontevedra",
    "wof:name":"Artecub A+g S.l.",
    "wof:placetype":"venue"
},
  "geometry": {"coordinates":[-8.8113260269,42.1172943115],"type":"Point"}
}