{
  "type": "Feature",
  "properties": {
    "addr:full":"Carrer de Argentina (de L'), 11 Tortosa Tarragona 43500",
    "addr:housenumber":"11",
    "addr:postcode":"43500",
    "addr:street":"Carrer De Argentina De L '",
    "iso:country":"ES",
    "sg:address":"Carrer de Argentina (de L'), 11",
    "sg:city":"Tortosa",
    "sg:orig_category":"Peluqueros: De Se\u00d1oras",
    "sg:phone":"+34 977 44 10 79",
    "sg:postcode":"43500",
    "sg:province":"Tarragona",
    "wof:name":"Ferrando Marti Maria Cinta",
    "wof:placetype":"venue"
},
  "geometry": {"coordinates":[0.5202130079,40.8098258972],"type":"Point"}
}