{
  "type": "Feature",
  "properties": {
    "addr:full":"Calle de Mina (la), 15 Dos Hermanas Sevilla 41700",
    "addr:housenumber":"15",
    "addr:postcode":"41700",
    "addr:street":"Calle De Mina La",
    "iso:country":"ES",
    "sg:address":"Calle de Mina (la), 15",
    "sg:city":"Dos Hermanas",
    "sg:orig_category":"Agencias De Trabajo Temporal",
    "sg:phone":"+34 955 67 51 52",
    "sg:postcode":"41700",
    "sg:province":"Sevilla",
    "sg:website":"www.adecco.es",
    "wof:name":"Adecco E.t.t. S.a.",
    "wof:placetype":"venue"
},
  "geometry": {"coordinates":[-5.9211821556,37.2822532654],"type":"Point"}
}