{
  "type": "Feature",
  "properties": {
    "addr:full":"Avda Alemania (de), 27 Caceres C\u00e1ceres 10001",
    "addr:housenumber":"27",
    "addr:postcode":"10001",
    "addr:street":"Avda Alemania De;Ca\u0301Ceres",
    "iso:country":"ES",
    "sg:address":"Avda Alemania (de), 27",
    "sg:city":"Caceres",
    "sg:classifiers":[
        {
            "category":"Utilities",
            "subcategory":"Natural Gas",
            "type":"Services"
        }
    ],
    "sg:phone":"+34 927 23 85 37",
    "sg:postcode":"10001",
    "sg:province":"C\u00e1ceres",
    "wof:name":"Distribucion Y Comercializacion De Gas Extremadura S.a",
    "wof:placetype":"venue"
},
  "geometry": {"coordinates":[-6.3801188469,39.4669303894],"type":"Point"}
}