{
  "type": "Feature",
  "properties": {
    "addr:full":"Calle de La Rua, 17 Villalon Campos Valladolid 47600",
    "addr:postcode":"47600",
    "addr:street":"Calle De La Rua 17 Villalon Campos",
    "iso:country":"ES",
    "sg:address":"Calle de La Rua, 17",
    "sg:city":"Villalon Campos",
    "sg:orig_category":"Zapatos (al Por Menor)",
    "sg:phone":"+34 983 74 02 13",
    "sg:postcode":"47600",
    "sg:province":"Valladolid",
    "wof:name":"Calzados Vibot S.l.",
    "wof:placetype":"venue"
},
  "geometry": {"coordinates":[-5.0348992348,42.0987815857],"type":"Point"}
}