{
  "type": "Feature",
  "properties": {
    "addr:full":"Cmno Cartagena, 34 San Cristobal Murcia 30815",
    "addr:housenumber":"34",
    "addr:postcode":"30815",
    "addr:street":"Cmno Cartagena",
    "iso:country":"ES",
    "sg:address":"Cmno Cartagena, 34",
    "sg:city":"San Cristobal",
    "sg:orig_category":"Frutas Y Legumbres Frescas (al Por Mayor)",
    "sg:phone":"+34 968 44 35 42",
    "sg:postcode":"30815",
    "sg:province":"Murcia",
    "wof:name":"Mayper Grupo Alimentario S.r.l.",
    "wof:placetype":"venue"
},
  "geometry": {"coordinates":[-1.5774840117,37.5886192322],"type":"Point"}
}