{
  "type": "Feature",
  "properties": {
    "iso:country":"ES",
    "sg:address":"Calle de Juan De La Cierva, 5",
    "sg:city":"Mazarron",
    "sg:orig_category":"Inmobiliaria (agencias)",
    "sg:phone":"+34 968 59 26 79",
    "sg:postcode":"30870",
    "sg:province":"Murcia",
    "wof:name":"Another World Properties S.l.",
    "wof:placetype":"venue"
},
  "geometry": {"coordinates":[-1.3143273592,37.5997543335],"type":"Point"}
}