{
  "type": "Feature",
  "properties": {
    "iso:country":"ES",
    "sg:address":"Plaz Maestro Teofilo Azabal, 1",
    "sg:city":"Jerez De La Frontera",
    "sg:orig_category":"Carnicer\u00cdas, Carnicer\u00cdas",
    "sg:phone":"+34 956 14 26 32",
    "sg:postcode":"11408",
    "sg:province":"C\u00e1diz",
    "wof:name":"Marin Garcia Victor",
    "wof:placetype":"venue"
},
  "geometry": {"coordinates":[-6.1290249825,36.670425415],"type":"Point"}
}