{
  "type": "Feature",
  "properties": {
    "iso:country":"ES",
    "sg:address":"Calle de Igualdegi Kalea, 3",
    "sg:city":"Lekeitio",
    "sg:orig_category":"Restaurantes",
    "sg:phone":"+34 946 84 02 55",
    "sg:postcode":"48280",
    "sg:province":"Vizcaya",
    "wof:name":"Zapirain Arribalzaga Francisco Jeronimo",
    "wof:placetype":"venue"
},
  "geometry": {"coordinates":[-2.504404068,43.363899231],"type":"Point"}
}