{
  "type": "Feature",
  "properties": {
    "iso:country":"ES",
    "sg:address":"Calle de Santa Cecilia, 10",
    "sg:city":"Mislata",
    "sg:orig_category":"Fabricaci\u00d3n De Muebles",
    "sg:phone":"+34 963 70 03 52",
    "sg:postcode":"46920",
    "sg:province":"Valencia",
    "wof:name":"Guerrero Ma\u00f1ogil Carmen Maria",
    "wof:placetype":"venue"
},
  "geometry": {"coordinates":[-0.4207549989,39.4718399048],"type":"Point"}
}