{
  "type": "Feature",
  "properties": {
    "addr:full":"Rond Olivares (de Los), 7 Jaen Ja\u00e9n 23009",
    "addr:postcode":"23009",
    "addr:street":"Olivares;Jae\u0301N",
    "iso:country":"ES",
    "sg:address":"Rond Olivares (de Los), 7",
    "sg:city":"Jaen",
    "sg:orig_category":"Aluminio Y Aleaciones (producci\u00d3n, Transformaci\u00d3n, Negocio)",
    "sg:phone":"+34 953 28 04 01",
    "sg:postcode":"23009",
    "sg:province":"Ja\u00e9n",
    "wof:name":"Aluminios De Jaen S. A.",
    "wof:placetype":"venue"
},
  "geometry": {"coordinates":[-3.7232005596,37.8562049866],"type":"Point"}
}