{
  "type": "Feature",
  "properties": {
    "addr:full":"Avda Reino De Leon, S/n Santa Maria Del Paramo Le\u00f3n 24240",
    "addr:postcode":"24240",
    "addr:street":"Avda Reino De Leon S / N",
    "iso:country":"ES",
    "sg:address":"Avda Reino De Leon, S/n",
    "sg:city":"Santa Maria Del Paramo",
    "sg:orig_category":"Producci\u00d3n, Comercio De Cereales",
    "sg:phone":"+34 987 36 01 81",
    "sg:postcode":"24240",
    "sg:province":"Le\u00f3n",
    "wof:name":"Antonio Gonzalez Mendoza S.a.",
    "wof:placetype":"venue"
},
  "geometry": {"coordinates":[-5.745513916,42.3582611084],"type":"Point"}
}