{
  "type": "Feature",
  "properties": {
    "addr:full":"Carrer de Jose M Usandizaga, 4 Palma Islas Baleares 07009",
    "addr:housenumber":"4",
    "addr:postcode":"07009",
    "addr:street":"Carrer De Jose M Usandizaga",
    "iso:country":"ES",
    "sg:address":"Carrer de Jose M Usandizaga, 4",
    "sg:city":"Palma",
    "sg:orig_category":"Carnicer\u00cdas, Carnicer\u00cdas",
    "sg:phone":"+34 971 29 00 20",
    "sg:postcode":"07009",
    "sg:province":"Islas Baleares",
    "wof:name":"Arias Perez Tomas",
    "wof:placetype":"venue"
},
  "geometry": {"coordinates":[2.6625831127,39.5880279541],"type":"Point"}
}