{
  "type": "Feature",
  "properties": {
    "addr:full":"Calle de Rio Guadalquivir, 5 Torrejon Ardoz Madrid 28850",
    "addr:housenumber":"5",
    "addr:postcode":"28850",
    "addr:street":"Calle De Rio Guadalquivir",
    "iso:country":"ES",
    "sg:address":"Calle de Rio Guadalquivir, 5",
    "sg:city":"Torrejon Ardoz",
    "sg:orig_category":"Armarios Y Cuadros El\u00c9ctricos",
    "sg:phone":"+34 916 75 30 46",
    "sg:postcode":"28850",
    "sg:province":"Madrid",
    "wof:name":"Norma Componentes S. L.",
    "wof:placetype":"venue"
},
  "geometry": {"coordinates":[-3.4649000168,40.4601554871],"type":"Point"}
}