{
  "type": "Feature",
  "properties": {
    "addr:full":"Calle de Lealtad, 4 Sevilla Sevilla 41010",
    "addr:housenumber":"4",
    "addr:postcode":"41010",
    "addr:street":"Calle De Lealtad",
    "iso:country":"ES",
    "sg:address":"Calle de Lealtad, 4",
    "sg:city":"Sevilla",
    "sg:orig_category":"Cerrajer\u00cda, Ferrallista",
    "sg:phone":"+34 954 27 13 25",
    "sg:postcode":"41010",
    "sg:province":"Sevilla",
    "wof:name":"Jimenez Mariano Roberto",
    "wof:placetype":"venue"
},
  "geometry": {"coordinates":[-6.0058159828,37.3799819946],"type":"Point"}
}