{
  "type": "Feature",
  "properties": {
    "iso:country":"ES",
    "sg:address":"Calle de Galicia, 24",
    "sg:city":"Madrid",
    "sg:orig_category":"Alimentaci\u00d3n General (al Por Menor)",
    "sg:phone":"+34 917 11 81 09",
    "sg:postcode":"28024",
    "sg:province":"Madrid",
    "wof:name":"Pulido De La Casa Eufemio",
    "wof:placetype":"venue"
},
  "geometry": {"coordinates":[-3.771873951,40.3981437683],"type":"Point"}
}