{
  "type": "Feature",
  "properties": {
    "addr:full":"La Huertona-ardines, S/n Ucio Asturias 33569",
    "addr:housenumber":"s",
    "addr:postcode":"33569",
    "addr:street":"/ N Ucio Asturias",
    "iso:country":"ES",
    "sg:address":"La Huertona-ardines, S/n",
    "sg:city":"Ucio",
    "sg:orig_category":"Maquinaria Para Industrias Diversas",
    "sg:phone":"+34 985 86 12 64",
    "sg:postcode":"33569",
    "sg:province":"Asturias",
    "sg:website":"www.grupoaliser.com",
    "wof:name":"Grupo Aliser S.a.",
    "wof:placetype":"venue"
},
  "geometry": {"coordinates":[-5.9832577705,43.2504386902],"type":"Point"}
}