{
  "type": "Feature",
  "properties": {
    "addr:full":"Rond San Torcuato, 13 Zamora Zamora 49006",
    "addr:housenumber":"13",
    "addr:postcode":"49006",
    "addr:street":"San Torcuato",
    "iso:country":"ES",
    "sg:address":"Rond San Torcuato, 13",
    "sg:city":"Zamora",
    "sg:orig_category":"Negocio De Materiales De Construcci\u00d3n",
    "sg:phone":"+34 980 50 80 95",
    "sg:postcode":"49006",
    "sg:province":"Zamora",
    "sg:website":"www.portalinmobank.com",
    "wof:name":"Ceramicas Y Construcciones La Corona De Los Villares S.l.",
    "wof:placetype":"venue"
},
  "geometry": {"coordinates":[-5.7457342148,41.5033302307],"type":"Point"}
}