{
  "type": "Feature",
  "properties": {
    "addr:full":"Calle de Real, 76 San Sebastian De Los Reyes Madrid 28700",
    "addr:housenumber":"76",
    "addr:postcode":"28700",
    "addr:street":"Calle De Real",
    "iso:country":"ES",
    "sg:address":"Calle de Real, 76",
    "sg:city":"San Sebastian De Los Reyes",
    "sg:orig_category":"Bancos",
    "sg:phone":"+34 916 63 93 93",
    "sg:postcode":"28700",
    "sg:province":"Madrid",
    "sg:website":"www.sch.es",
    "wof:name":"Bt Espa\u00d1a Compa\u00d1ia De Servicios Globales De Telecomunicaciones S.a.u.",
    "wof:placetype":"venue"
},
  "geometry": {"coordinates":[-3.6219420433,40.550567627],"type":"Point"}
}