{
  "type": "Feature",
  "properties": {
    "addr:full":"Carr Josep Maria Vila, 5 Platja D'aro Girona 17250",
    "addr:housenumber":"5",
    "addr:postcode":"17250",
    "addr:street":"Carr Josep Maria Vila",
    "iso:country":"ES",
    "sg:address":"Carr Josep Maria Vila, 5",
    "sg:city":"Platja D'aro",
    "sg:orig_category":"Bebidas",
    "sg:phone":"+34 972 81 90 53",
    "sg:postcode":"17250",
    "sg:province":"Girona",
    "wof:name":"Coll Bernat S.l.",
    "wof:placetype":"venue"
},
  "geometry": {"coordinates":[2.8187398911,41.9808616638],"type":"Point"}
}