{
  "type": "Feature",
  "properties": {
    "addr:full":"Calle de Julio Hauzeur, 40 Torrelavega Cantabria 39300",
    "addr:housenumber":"40",
    "addr:postcode":"39300",
    "addr:street":"Calle De Julio Hauzeur",
    "iso:country":"ES",
    "sg:address":"Calle de Julio Hauzeur, 40",
    "sg:city":"Torrelavega",
    "sg:orig_category":"Ense\u00d1anza, Formaci\u00d3n Profesional: Aprendizaje",
    "sg:phone":"+34 942 88 37 20",
    "sg:postcode":"39300",
    "sg:province":"Cantabria",
    "wof:name":"Ayuntamiento De Torrelavega",
    "wof:placetype":"venue"
},
  "geometry": {"coordinates":[-4.0588912964,43.3515396118],"type":"Point"}
}