{
  "type": "Feature",
  "properties": {
    "iso:country":"ES",
    "sg:address":"Carrer de Industria, 3",
    "sg:city":"Santa Perpetua De Mogoda",
    "sg:orig_category":"Escotaduras, Torneados",
    "sg:phone":"+34 935 44 94 93",
    "sg:postcode":"08130",
    "sg:province":"Barcelona",
    "wof:name":"Industrias Mestres S. A.",
    "wof:placetype":"venue"
},
  "geometry": {"coordinates":[2.1807971001,41.5380592346],"type":"Point"}
}