{
  "type": "Feature",
  "properties": {
    "iso:country":"ES",
    "sg:address":"Pg Gran Passeig Ronda, 51",
    "sg:city":"Lleida",
    "sg:orig_category":"Venta, Instalaci\u00d3n, Reparaci\u00d3n De Antenas Para Televisi\u00d3n",
    "sg:phone":"+34 973 28 10 63",
    "sg:postcode":"25006",
    "sg:province":"Lleida",
    "wof:name":"Plana Fabrega Seguretat S.l.",
    "wof:placetype":"venue"
},
  "geometry": {"coordinates":[0.6132599711,41.6166000366],"type":"Point"}
}