{
  "type": "Feature",
  "properties": {
    "iso:country":"ES",
    "sg:address":"Calle de Roberto Cano, 4",
    "sg:city":"Melilla",
    "sg:orig_category":"Obras Y Organismos Sociales",
    "sg:phone":"+34 952 68 42 00",
    "sg:postcode":"52001",
    "sg:province":"Melilla",
    "wof:name":"Caritas Interparroquial Melilla",
    "wof:placetype":"venue"
},
  "geometry": {"coordinates":[-2.9398870468,35.2942466736],"type":"Point"}
}