{
  "type": "Feature",
  "properties": {
    "iso:country":"ES",
    "sg:address":"Carr Pere Gerones, 2",
    "sg:city":"Santa Cristina D'aro",
    "sg:orig_category":"Cerrajer\u00cda, Ferrallista",
    "sg:phone":"+34 972 83 70 63",
    "sg:postcode":"17246",
    "sg:province":"Girona",
    "wof:name":"Camps Marco Joan",
    "wof:placetype":"venue"
},
  "geometry": {"coordinates":[2.8040521145,41.9643173218],"type":"Point"}
}