{
  "type": "Feature",
  "properties": {
    "addr:full":"Calle de Fuentes (las), 6 Villagonzalo-pedernales Burgos 09195",
    "addr:housenumber":"6",
    "addr:postcode":"09195",
    "addr:street":"Calle De Fuentes Las",
    "iso:country":"ES",
    "sg:address":"Calle de Fuentes (las), 6",
    "sg:city":"Villagonzalo-pedernales",
    "sg:orig_category":"Inform\u00c1tica: Consultores",
    "sg:phone":"+34 947 29 49 03",
    "sg:postcode":"09195",
    "sg:province":"Burgos",
    "wof:name":"Lombillo Garcia Oscar",
    "wof:placetype":"venue"
},
  "geometry": {"coordinates":[-3.7549920082,42.2654838562],"type":"Point"}
}