{
  "type": "Feature",
  "properties": {
    "addr:full":"Ctra Alicante-valencia, Km. 0167,3 Pedreguer Alicante 03750",
    "addr:postcode":"03750",
    "addr:street":"Ctra Alicante-Valencia Km. 0167,3",
    "iso:country":"ES",
    "sg:address":"Ctra Alicante-valencia, Km. 0167,3",
    "sg:city":"Pedreguer",
    "sg:orig_category":"Transporte En General",
    "sg:phone":"+34 965 76 07 58",
    "sg:postcode":"03750",
    "sg:province":"Alicante",
    "wof:name":"Dialsur S.a.",
    "wof:placetype":"venue"
},
  "geometry": {"coordinates":[0.0347849987,38.7958145142],"type":"Point"}
}