{
  "type": "Feature",
  "properties": {
    "addr:full":"Ctra San Roque, 11 Tineo Asturias 33870",
    "addr:housenumber":"11",
    "addr:postcode":"33870",
    "addr:street":"Ctra San Roque",
    "iso:country":"ES",
    "sg:address":"Ctra San Roque, 11",
    "sg:city":"Tineo",
    "sg:orig_category":"Aguas (distribuci\u00d3n, Servicios)",
    "sg:phone":"+34 985 80 08 87",
    "sg:postcode":"33870",
    "sg:province":"Asturias",
    "wof:name":"Asturagua S. A.",
    "wof:placetype":"venue"
},
  "geometry": {"coordinates":[-6.4130454063,43.3356170654],"type":"Point"}
}