{
  "type": "Feature",
  "properties": {
    "iso:country":"ES",
    "sg:address":"Carrer de Marinel.lo Bosch, 113",
    "sg:city":"Terrassa",
    "sg:orig_category":"Bisuter\u00cda, Joyer\u00cda, Relojer\u00cda (al Por Menor)",
    "sg:phone":"+34 937 85 08 53",
    "sg:postcode":"08222",
    "sg:province":"Barcelona",
    "wof:name":"Lentijo Heras Maria Josefa",
    "wof:placetype":"venue"
},
  "geometry": {"coordinates":[2.0263819695,41.5602035522],"type":"Point"}
}