{
  "type": "Feature",
  "properties": {
    "addr:full":"Avda Juan Carlos I, 1 Costa Ballena C\u00e1diz 11520",
    "addr:housenumber":"1",
    "addr:postcode":"11520",
    "addr:street":"Avda Juan Carlos I;Ca\u0301Diz",
    "iso:country":"ES",
    "sg:address":"Avda Juan Carlos I, 1",
    "sg:city":"Costa Ballena",
    "sg:orig_category":"Ropa Para Se\u00d1oras (al Por Menor)",
    "sg:phone":"+34 956 84 74 99",
    "sg:postcode":"11520",
    "sg:province":"C\u00e1diz",
    "wof:name":"Ayuso Martin Marcos",
    "wof:placetype":"venue"
},
  "geometry": {"coordinates":[-6.413643837,36.6910705566],"type":"Point"}
}