{
  "type": "Feature",
  "properties": {
    "iso:country":"ES",
    "sg:address":"Calle de Concepcion Ximenez, 8",
    "sg:city":"Cascante",
    "sg:orig_category":"Abogados",
    "sg:phone":"+34 948 85 15 09",
    "sg:postcode":"31520",
    "sg:province":"Navarra",
    "wof:name":"Rueda Pascual Santiago",
    "wof:placetype":"venue"
},
  "geometry": {"coordinates":[-1.6783978939,41.9998283386],"type":"Point"}
}