{
  "type": "Feature",
  "properties": {
    "addr:full":"Avda Madrid (de), 76 Xinzo De Limia Ourense 32630",
    "addr:housenumber":"76",
    "addr:postcode":"32630",
    "addr:street":"Avda Madrid De",
    "iso:country":"ES",
    "sg:address":"Avda Madrid (de), 76",
    "sg:city":"Xinzo De Limia",
    "sg:orig_category":"Financiaci\u00d3n Y Cr\u00c9ditos",
    "sg:phone":"+34 988 46 15 66",
    "sg:postcode":"32630",
    "sg:province":"Ourense",
    "wof:name":"Rural Consulting,s.l",
    "wof:placetype":"venue"
},
  "geometry": {"coordinates":[-7.7233037949,42.0619850159],"type":"Point"}
}