{
  "type": "Feature",
  "properties": {
    "addr:full":"Calle de Micer Masco, 24 Valencia Valencia 46010",
    "addr:housenumber":"24",
    "addr:postcode":"46010",
    "addr:street":"Calle De Micer Masco",
    "iso:country":"ES",
    "sg:address":"Calle de Micer Masco, 24",
    "sg:city":"Valencia",
    "sg:orig_category":"\u00d3ptica: Instrumentos (fabricaci\u00d3n)",
    "sg:phone":"+34 963 93 42 31",
    "sg:postcode":"46010",
    "sg:province":"Valencia",
    "wof:name":"Optica Reyes S.l.",
    "wof:placetype":"venue"
},
  "geometry": {"coordinates":[-0.3629019856,39.4754142761],"type":"Point"}
}