{
  "type": "Feature",
  "properties": {
    "iso:country":"ES",
    "sg:address":"Pl Dins (de), 4",
    "sg:city":"Alcoi",
    "sg:orig_category":"Agencias De Viajes",
    "sg:phone":"+34 965 54 27 94",
    "sg:postcode":"03801",
    "sg:province":"Alicante",
    "wof:name":"Viajes Alcoy S. L.",
    "wof:placetype":"venue"
},
  "geometry": {"coordinates":[-0.4737589955,38.697769165],"type":"Point"}
}