{
  "type": "Feature",
  "properties": {
    "iso:country":"ES",
    "sg:address":"Carr Agudes, 49",
    "sg:city":"Girona",
    "sg:orig_category":"Plomeros",
    "sg:phone":"+34 972 23 67 38",
    "sg:postcode":"17006",
    "sg:province":"Girona",
    "wof:name":"Suministros Gac S.l.",
    "wof:placetype":"venue"
},
  "geometry": {"coordinates":[2.8034110069,41.9736328125],"type":"Point"}
}