{
  "type": "Feature",
  "properties": {
    "iso:country":"ES",
    "sg:address":"Avda Sevilla, 35",
    "sg:city":"Palacios Y Villafranca",
    "sg:orig_category":"M\u00c9dicos: Oftalmolog\u00cda",
    "sg:phone":"+34 955 81 58 85",
    "sg:postcode":"41720",
    "sg:province":"Sevilla",
    "wof:name":"Roldan Jimenez Antonio Isidoro",
    "wof:placetype":"venue"
},
  "geometry": {"coordinates":[-5.9242258072,37.1625480652],"type":"Point"}
}