{
  "type": "Feature",
  "properties": {
    "iso:country":"ES",
    "sg:address":"Avda Antibioticos, S/n",
    "sg:city":"Armunia",
    "sg:orig_category":"Lavado, Limpieza De Veh\u00cdculos",
    "sg:phone":"+34 987 21 86 52",
    "sg:postcode":"24009",
    "sg:province":"Le\u00f3n",
    "wof:name":"Lavado Hiproleon",
    "wof:placetype":"venue"
},
  "geometry": {"coordinates":[-5.5833239555,42.576789856],"type":"Point"}
}