{
  "type": "Feature",
  "properties": {
    "addr:full":"Calle de Jose Perseguer, 11 Petrer Alicante 03610",
    "addr:housenumber":"11",
    "addr:postcode":"03610",
    "addr:street":"Calle De Jose Perseguer",
    "iso:country":"ES",
    "sg:address":"Calle de Jose Perseguer, 11",
    "sg:city":"Petrer",
    "sg:orig_category":"Agencias De Viajes",
    "sg:phone":"+34 965 37 14 58",
    "sg:postcode":"03610",
    "sg:province":"Alicante",
    "wof:name":"Viajes Valle S. A.",
    "wof:placetype":"venue"
},
  "geometry": {"coordinates":[-0.7714819908,38.4835205078],"type":"Point"}
}