{
  "type": "Feature",
  "properties": {
    "addr:full":"Calle de Corredera, 6 Moron Frontera Sevilla 41530",
    "addr:housenumber":"6",
    "addr:postcode":"41530",
    "addr:street":"Calle De Corredera",
    "iso:country":"ES",
    "sg:address":"Calle de Corredera, 6",
    "sg:city":"Moron Frontera",
    "sg:orig_category":"Relojer\u00cda (al Por Menor, Reparaci\u00d3n)",
    "sg:phone":"+34 954 85 27 43",
    "sg:postcode":"41530",
    "sg:province":"Sevilla",
    "wof:name":"Santos Puerta Jose",
    "wof:placetype":"venue"
},
  "geometry": {"coordinates":[-5.45210886,37.1225585938],"type":"Point"}
}