{
  "type": "Feature",
  "properties": {
    "addr:full":"Calle de Ayala, 77 Madrid Madrid 28006",
    "addr:housenumber":"77",
    "addr:postcode":"madrid;28006",
    "addr:street":"Calle De Ayala",
    "iso:country":"ES",
    "sg:address":"Calle de Ayala, 77",
    "sg:city":"Madrid",
    "sg:orig_category":"Laboratorios Y Cl\u00cdnicas Veterinarias",
    "sg:phone":"+34 914 01 02 71",
    "sg:postcode":"28006",
    "sg:province":"Madrid",
    "wof:name":"Ros Bascu\u00f1ana Fernando",
    "wof:placetype":"venue"
},
  "geometry": {"coordinates":[-3.6751205921,40.4272994995],"type":"Point"}
}