{
  "type": "Feature",
  "properties": {
    "addr:full":"Calle de Loiola, 4 Donostia-san Sebastian Guip\u00f9zcoa 20005",
    "addr:housenumber":"4",
    "addr:postcode":"20005",
    "addr:street":"Calle De Loiola",
    "iso:country":"ES",
    "sg:address":"Calle de Loiola, 4",
    "sg:city":"Donostia-san Sebastian",
    "sg:orig_category":"Abogados",
    "sg:phone":"+34 943 43 09 60",
    "sg:postcode":"20005",
    "sg:province":"Guip\u00f9zcoa",
    "wof:name":"Salvador Asenjo Y Asociados S.l.",
    "wof:placetype":"venue"
},
  "geometry": {"coordinates":[-1.9832539558,43.3187789917],"type":"Point"}
}