{
  "type": "Feature",
  "properties": {
    "iso:country":"ES",
    "sg:address":"Carrer de Portaferrissa, 24",
    "sg:city":"Barcelona",
    "sg:orig_category":"Bisuter\u00cda, Joyer\u00cda, Relojer\u00cda (al Por Menor)",
    "sg:phone":"+34 933 02 48 80",
    "sg:postcode":"08002",
    "sg:province":"Barcelona",
    "wof:name":"Contreras Perez Joaquin",
    "wof:placetype":"venue"
},
  "geometry": {"coordinates":[2.1732189655,41.3834877014],"type":"Point"}
}