{
  "type": "Feature",
  "properties": {
    "addr:full":"Carrer de Proven\u00c7a, 215 Barcelona Barcelona 08008",
    "addr:housenumber":"215",
    "addr:postcode":"08008",
    "addr:street":"Carrer De Provenc\u0327A",
    "iso:country":"ES",
    "sg:address":"Carrer de Proven\u00c7a, 215",
    "sg:city":"Barcelona",
    "sg:orig_category":"Zapatos (al Por Menor)",
    "sg:phone":"+34 932 15 08 47",
    "sg:postcode":"08008",
    "sg:province":"Barcelona",
    "wof:name":"Sancho Garcia Joaquin",
    "wof:placetype":"venue"
},
  "geometry": {"coordinates":[2.1585290432,41.3926773071],"type":"Point"}
}