{
  "type": "Feature",
  "properties": {
    "iso:country":"ES",
    "sg:address":"Ctra Palmar (el), S/n",
    "sg:city":"Buenavista Norte",
    "sg:orig_category":"Doctores En Medicina",
    "sg:phone":"+34 922 12 77 66",
    "sg:postcode":"38480",
    "sg:province":"Santa Cruz De Tenerife",
    "wof:name":"Yanes Palenzuela Maria Del Carmen",
    "wof:placetype":"venue"
},
  "geometry": {"coordinates":[-16.8462409973,28.3568630219],"type":"Point"}
}