{
  "type": "Feature",
  "properties": {
    "addr:full":"Avda Astorga, 9 Ponferrada Le\u00f3n 24400",
    "addr:housenumber":"9",
    "addr:postcode":"24400",
    "addr:street":"Avda Astorga",
    "iso:country":"ES",
    "sg:address":"Avda Astorga, 9",
    "sg:city":"Ponferrada",
    "sg:orig_category":"Molduras, Junquillos, Listones Y Molduras Perforadas",
    "sg:phone":"+34 987 42 49 76",
    "sg:postcode":"24400",
    "sg:province":"Le\u00f3n",
    "wof:name":"Burbisil Sl",
    "wof:placetype":"venue"
},
  "geometry": {"coordinates":[-6.5821609497,42.5498390198],"type":"Point"}
}