{
  "type": "Feature",
  "properties": {
    "addr:full":"Pase Revellin (del), 10 Ceuta Ceuta 51001",
    "addr:postcode":"51001",
    "iso:country":"ES",
    "sg:address":"Pase Revellin (del), 10",
    "sg:city":"Ceuta",
    "sg:orig_category":"M\u00c9dicos: Otorrinolaringolog\u00cda",
    "sg:phone":"+34 956 51 86 77",
    "sg:postcode":"51001",
    "sg:province":"Ceuta",
    "wof:name":"Rial Morilla Francisco Jose",
    "wof:placetype":"venue"
},
  "geometry": {"coordinates":[-5.3302302361,35.8947601318],"type":"Point"}
}