{
  "type": "Feature",
  "properties": {
    "iso:country":"ES",
    "sg:address":"Plaz Ametzola, 1",
    "sg:city":"Bilbao",
    "sg:orig_category":"Tubos Y Tuber\u00cdas De Goma Y Pl\u00c1stico (fabricaci\u00d3n, Al Por Mayor)",
    "sg:phone":"+34 944 22 00 94",
    "sg:postcode":"48012",
    "sg:province":"Vizcaya",
    "wof:name":"Vulcanizados Luis S.a.",
    "wof:placetype":"venue"
},
  "geometry": {"coordinates":[-2.9387390614,43.2560348511],"type":"Point"}
}