{
  "type": "Feature",
  "properties": {
    "iso:country":"ES",
    "sg:address":"Calle de Portal De Legutiano, 1",
    "sg:city":"Vitoria-gasteiz",
    "sg:orig_category":"Frutas Y Legumbres Frescas (al Por Mayor)",
    "sg:phone":"+34 945 26 01 03",
    "sg:postcode":"01002",
    "sg:province":"\u00c1lava",
    "wof:name":"Teofilo Jaras Gomez",
    "wof:placetype":"venue"
},
  "geometry": {"coordinates":[-2.668804884,42.8532943726],"type":"Point"}
}