{
  "type": "Feature",
  "properties": {
    "addr:full":"Calle de Molino, 32 Ronda M\u00e1laga 29400",
    "addr:housenumber":"32",
    "addr:postcode":"29400",
    "addr:street":"Calle De Molino;Ronda Ma\u0301Laga",
    "iso:country":"ES",
    "sg:address":"Calle de Molino, 32",
    "sg:city":"Ronda",
    "sg:orig_category":"Arquitectos",
    "sg:phone":"+34 952 87 76 32",
    "sg:postcode":"29400",
    "sg:province":"M\u00e1laga",
    "wof:name":"Lara Pastora Salvador",
    "wof:placetype":"venue"
},
  "geometry": {"coordinates":[-5.1668148041,36.7452545166],"type":"Point"}
}