{
  "type": "Feature",
  "properties": {
    "iso:country":"ES",
    "sg:address":"Calle de Principe De Viana, 4",
    "sg:city":"Caparroso",
    "sg:orig_category":"Equipo Y Material Deportivo Y De Actividades Invernales Y De Monta\u00d1a",
    "sg:phone":"+34 948 73 01 99",
    "sg:postcode":"31380",
    "sg:province":"Navarra",
    "wof:name":"Serdepor S.l.",
    "wof:placetype":"venue"
},
  "geometry": {"coordinates":[-1.6509050131,42.3409690857],"type":"Point"}
}