{
  "type": "Feature",
  "properties": {
    "addr:full":"Calle de Lauaxeta Olerkari, 14 Mungia Vizcaya 48100",
    "addr:housenumber":"14",
    "addr:postcode":"48100",
    "addr:street":"Calle De Lauaxeta Olerkari",
    "iso:country":"ES",
    "sg:address":"Calle de Lauaxeta Olerkari, 14",
    "sg:city":"Mungia",
    "sg:orig_category":"Caf\u00c9s, Bares, Cervecer\u00cdas",
    "sg:phone":"+34 946 74 53 48",
    "sg:postcode":"48100",
    "sg:province":"Vizcaya",
    "wof:name":"Pedro De Los Bueis Santamaria",
    "wof:placetype":"venue"
},
  "geometry": {"coordinates":[-2.8488550186,43.355884552],"type":"Point"}
}