{
  "type": "Feature",
  "properties": {
    "addr:full":"Calle de Mayor, 7 Traiguera Castell\u00f3n 12330",
    "addr:housenumber":"7",
    "addr:postcode":"12330",
    "addr:street":"Calle De Mayor;Castello\u0301N",
    "iso:country":"ES",
    "sg:address":"Calle de Mayor, 7",
    "sg:city":"Traiguera",
    "sg:orig_category":"Centros De Coordinaci\u00d3n",
    "sg:phone":"+34 964 49 55 07",
    "sg:postcode":"12330",
    "sg:province":"Castell\u00f3n",
    "wof:name":"Gestoria Mampel S.l.",
    "wof:placetype":"venue"
},
  "geometry": {"coordinates":[0.2892799973,40.5237693787],"type":"Point"}
}