{
  "type": "Feature",
  "properties": {
    "addr:full":"Calle de Antares, 64 Alacant Alicante 03006",
    "addr:housenumber":"64",
    "addr:postcode":"03006",
    "addr:street":"Calle De Antares",
    "iso:country":"ES",
    "sg:address":"Calle de Antares, 64",
    "sg:city":"Alacant",
    "sg:orig_category":"Moquetas, Alfombras (al Por Menor)",
    "sg:phone":"+34 965 10 76 06",
    "sg:postcode":"03006",
    "sg:province":"Alicante",
    "wof:name":"Persicort Grupo Distribuidora S.l.",
    "wof:placetype":"venue"
},
  "geometry": {"coordinates":[-0.5108876824,38.3481254578],"type":"Point"}
}