{
  "type": "Feature",
  "properties": {
    "addr:full":"Avda Constitucion, 4 Alacant Alicante 03002",
    "addr:housenumber":"4",
    "addr:postcode":"03002",
    "addr:street":"Avda Constitucion",
    "iso:country":"ES",
    "sg:address":"Avda Constitucion, 4",
    "sg:city":"Alacant",
    "sg:orig_category":"M\u00c9dicos: Dermatolog\u00cda Y Venereolog\u00cda",
    "sg:phone":"+34 965 14 41 81",
    "sg:postcode":"03002",
    "sg:province":"Alicante",
    "wof:name":"Dermo Tratamientos Por Laser S.l.",
    "wof:placetype":"venue"
},
  "geometry": {"coordinates":[-0.4848650098,38.3464698792],"type":"Point"}
}