{
  "type": "Feature",
  "properties": {
    "addr:full":"Carrer de Cultura, 5 Santa Coloma De Gramenet Barcelona 08922",
    "addr:housenumber":"5",
    "addr:postcode":"08922",
    "addr:street":"Carrer De Cultura",
    "iso:country":"ES",
    "sg:address":"Carrer de Cultura, 5",
    "sg:city":"Santa Coloma De Gramenet",
    "sg:orig_category":"Electrodom\u00c9sticos (al Por Menor)",
    "sg:phone":"+34 934 66 39 82",
    "sg:postcode":"08922",
    "sg:province":"Barcelona",
    "wof:name":"Expert Badalona S.a.",
    "wof:placetype":"venue"
},
  "geometry": {"coordinates":[2.2097671032,41.4477310181],"type":"Point"}
}