{
  "type": "Feature",
  "properties": {
    "addr:full":"Calle de Fuente (la), 5 Sotillo Adrada \u00c1vila 05420",
    "addr:housenumber":"5",
    "addr:postcode":"05420",
    "addr:street":"Calle De Fuente La",
    "iso:country":"ES",
    "sg:address":"Calle de Fuente (la), 5",
    "sg:city":"Sotillo Adrada",
    "sg:orig_category":"Reposter\u00cdas",
    "sg:phone":"+34 918 66 00 51",
    "sg:postcode":"05420",
    "sg:province":"\u00c1vila",
    "wof:name":"Hermanos Gonzalez Los Grillos S.l.",
    "wof:placetype":"venue"
},
  "geometry": {"coordinates":[-4.5834989548,40.2928466797],"type":"Point"}
}