{
  "type": "Feature",
  "properties": {
    "iso:country":"ES",
    "sg:address":"Pol Ind Ctra Albalat, 3",
    "sg:city":"Alzira",
    "sg:orig_category":"Almacenes Frigor\u00cdficos",
    "sg:phone":"+34 962 40 03 95",
    "sg:postcode":"46600",
    "sg:province":"Valencia",
    "wof:name":"Nadalfret S. L.",
    "wof:placetype":"venue"
},
  "geometry": {"coordinates":[-0.4378489852,39.1517295837],"type":"Point"}
}