{
  "type": "Feature",
  "properties": {
    "iso:country":"ES",
    "sg:address":"Avda Doctor Federico Rubio Y Gali, 50",
    "sg:city":"Madrid",
    "sg:orig_category":"Supermercados Y Hipermercados",
    "sg:phone":"+34 914 50 89 62",
    "sg:postcode":"28039",
    "sg:province":"Madrid",
    "wof:name":"Superfresh S. A",
    "wof:placetype":"venue"
},
  "geometry": {"coordinates":[-3.7095210552,40.4522514343],"type":"Point"}
}