{
  "type": "Feature",
  "properties": {
    "iso:country":"ES",
    "sg:address":"Aitzkorri Kalea, 7",
    "sg:city":"Legazpi",
    "sg:classifiers":[
        {
            "category":"Autos & Motor Vehicles",
            "subcategory":"Automobile Sales",
            "type":"Retail Goods"
        }
    ],
    "sg:phone":"+34 943 73 10 96",
    "sg:postcode":"20230",
    "sg:province":"Guip\u00f9zcoa",
    "wof:name":"Arantza Odriozola (autoescuela Legazpi)",
    "wof:placetype":"venue"
},
  "geometry": {"coordinates":[-2.3350579739,43.0489349365],"type":"Point"}
}