{
  "type": "Feature",
  "properties": {
    "addr:full":"Calle de O'donnell, General, 9 Melilla Melilla 52001",
    "addr:housenumber":"9",
    "addr:postcode":"52001",
    "addr:street":"Calle De O'Donnell General",
    "iso:country":"ES",
    "sg:address":"Calle de O'donnell, General, 9",
    "sg:city":"Melilla",
    "sg:orig_category":"M\u00c9dicos: Estomatolog\u00cda",
    "sg:phone":"+34 952 68 38 91",
    "sg:postcode":"52001",
    "sg:province":"Melilla",
    "wof:name":"Linares Valera Rosa Mercedes",
    "wof:placetype":"venue"
},
  "geometry": {"coordinates":[-2.9434149265,35.2970504761],"type":"Point"}
}