{
  "type": "Feature",
  "properties": {
    "iso:country":"ES",
    "sg:address":"Calle de Capitana, 4",
    "sg:city":"Bu\u00f1ol",
    "sg:orig_category":"Asociaciones Y Clubs Deportivos",
    "sg:phone":"+34 962 50 37 75",
    "sg:postcode":"46360",
    "sg:province":"Valencia",
    "wof:name":"Gim Ortiz Carrascosa S.l",
    "wof:placetype":"venue"
},
  "geometry": {"coordinates":[-0.7908831239,39.4170417786],"type":"Point"}
}