{
  "type": "Feature",
  "properties": {
    "addr:full":"Calle de Esteban Palacios, 17 Madrid Madrid 28043",
    "addr:housenumber":"17",
    "addr:postcode":"madrid;28043",
    "addr:street":"Calle De Esteban Palacios",
    "iso:country":"ES",
    "sg:address":"Calle de Esteban Palacios, 17",
    "sg:city":"Madrid",
    "sg:orig_category":"Traductores",
    "sg:phone":"+34 913 00 28 66",
    "sg:postcode":"28043",
    "sg:province":"Madrid",
    "wof:name":"Imtec Traducciones S.l.",
    "wof:placetype":"venue"
},
  "geometry": {"coordinates":[-3.6229391098,40.4583435059],"type":"Point"}
}