{
  "type": "Feature",
  "properties": {
    "iso:country":"ES",
    "sg:address":"Calle de Constitucion, 2",
    "sg:city":"Marchamalo",
    "sg:classifiers":[
        {
            "category":"Banks & Credit Unions",
            "subcategory":"Bureau De Change",
            "type":"Services"
        }
    ],
    "sg:phone":"+34 902 21 22 21",
    "sg:postcode":"19180",
    "sg:province":"Guadalajara",
    "sg:tags":[
        "organismos",
        "control"
    ],
    "wof:name":"Servicio Integral De Consultoria Medioambiental S.l.",
    "wof:placetype":"venue"
},
  "geometry": {"coordinates":[-3.2047948837,40.6671295166],"type":"Point"}
}