{
  "type": "Feature",
  "properties": {
    "iso:country":"ES",
    "sg:address":"Calle de Peru, 64",
    "sg:city":"Palmas De Gran Canaria",
    "sg:orig_category":"Mec\u00c1nico Del Autom\u00d3vil",
    "sg:phone":"+34 928 26 03 14",
    "sg:postcode":"35010",
    "sg:province":"Las Palmas",
    "wof:name":"Talleres Socorro Y Ramirez S. R. C.",
    "wof:placetype":"venue"
},
  "geometry": {"coordinates":[-15.4421787262,28.1301288605],"type":"Point"}
}