{
  "type": "Feature",
  "properties": {
    "addr:full":"Ctra. Palma-alcudia, S/n Inca Islas Baleares 07300",
    "addr:housenumber":"s / n",
    "addr:postcode":"07300",
    "addr:street":"Ctra. Palma-Alcudia",
    "iso:country":"ES",
    "sg:address":"Ctra. Palma-alcudia, S/n",
    "sg:city":"Inca",
    "sg:orig_category":"Venta, Montaje De Neum\u00c1ticos",
    "sg:phone":"+34 971 50 12 67",
    "sg:postcode":"07300",
    "sg:province":"Islas Baleares",
    "wof:name":"Abastecedora Balear S. A.",
    "wof:placetype":"venue"
},
  "geometry": {"coordinates":[2.922447,39.72646],"type":"Point"}
}