{
  "type": "Feature",
  "properties": {
    "addr:full":"Calle de Pizarro, 42 Salamanca Salamanca 37005",
    "addr:housenumber":"42",
    "addr:postcode":"37005",
    "addr:street":"Calle De Pizarro",
    "iso:country":"ES",
    "sg:address":"Calle de Pizarro, 42",
    "sg:city":"Salamanca",
    "sg:orig_category":"Asilos De Ancianos. Centros Privados",
    "sg:phone":"+34 923 25 11 11",
    "sg:postcode":"37005",
    "sg:province":"Salamanca",
    "wof:name":"Hernandez Martin Julian",
    "wof:placetype":"venue"
},
  "geometry": {"coordinates":[-5.6600270271,40.9736289978],"type":"Point"}
}