{
  "type": "Feature",
  "properties": {
    "iso:country":"ES",
    "sg:address":"Carrer de Montserrat, 88",
    "sg:city":"Esparreguera",
    "sg:orig_category":"Empresarios",
    "sg:phone":"+34 937 77 11 48",
    "sg:postcode":"08292",
    "sg:province":"Barcelona",
    "wof:name":"Torres Ulles S.l.",
    "wof:placetype":"venue"
},
  "geometry": {"coordinates":[1.8670150042,41.5418968201],"type":"Point"}
}