{
  "type": "Feature",
  "properties": {
    "addr:full":"Del Castillo, 2 Duruelo Sierra Soria 42158",
    "addr:housenumber":"2",
    "addr:postcode":"42158",
    "addr:street":"Del Castillo",
    "iso:country":"ES",
    "sg:address":"Del Castillo, 2",
    "sg:city":"Duruelo Sierra",
    "sg:orig_category":"Bancos",
    "sg:phone":"+34 975 37 10 63",
    "sg:postcode":"42158",
    "sg:province":"Soria",
    "sg:website":"www.bancocastilla.es",
    "wof:name":"Banco De Castilla",
    "wof:placetype":"venue"
},
  "geometry": {"coordinates":[-2.9291338921,41.9528656006],"type":"Point"}
}