{
  "type": "Feature",
  "properties": {
    "addr:full":"Calle de Coso, 33 Zaragoza Zaragoza 50003",
    "addr:housenumber":"33",
    "addr:postcode":"50003",
    "addr:street":"Calle De Coso",
    "iso:country":"ES",
    "sg:address":"Calle de Coso, 33",
    "sg:city":"Zaragoza",
    "sg:orig_category":"Colchones (fabricaci\u00d3n, Al Por Mayor, Al Por Menor)",
    "sg:phone":"+34 976 20 07 74",
    "sg:postcode":"50003",
    "sg:province":"Zaragoza",
    "wof:name":"Colchones Aznar S.l.",
    "wof:placetype":"venue"
},
  "geometry": {"coordinates":[-0.8810554743,41.652469635],"type":"Point"}
}