{
  "type": "Feature",
  "properties": {
    "addr:full":"Calle de Lealtad, 13 Santander Cantabria 39002",
    "addr:housenumber":"13",
    "addr:postcode":"39002",
    "addr:street":"Calle De Lealtad",
    "iso:country":"ES",
    "sg:address":"Calle de Lealtad, 13",
    "sg:city":"Santander",
    "sg:orig_category":"Arquitectos",
    "sg:phone":"+34 942 22 47 40",
    "sg:postcode":"39002",
    "sg:province":"Cantabria",
    "wof:name":"Norte\u00f1a Roor S.l.",
    "wof:placetype":"venue"
},
  "geometry": {"coordinates":[-3.8082239628,43.4608802795],"type":"Point"}
}