{
  "type": "Feature",
  "properties": {
    "addr:full":"Carr Guifre, 132 Badalona Barcelona 08912",
    "addr:housenumber":"132",
    "addr:postcode":"08912",
    "addr:street":"Carr Guifre",
    "iso:country":"ES",
    "sg:address":"Carr Guifre, 132",
    "sg:city":"Badalona",
    "sg:orig_category":"Ropa Para Ni\u00d1os (al Por Menor)",
    "sg:phone":"+34 934 60 19 45",
    "sg:postcode":"08912",
    "sg:province":"Barcelona",
    "wof:name":"Esclusas Matosas S.c.p.",
    "wof:placetype":"venue"
},
  "geometry": {"coordinates":[2.2432351112,41.4453277588],"type":"Point"}
}