{
  "type": "Feature",
  "properties": {
    "iso:country":"ES",
    "sg:address":"Calle de Secundino Esnaola, 21",
    "sg:city":"Donostia-san Sebastian",
    "sg:orig_category":"Ropa Para Ni\u00d1os (al Por Menor)",
    "sg:phone":"+34 943 27 98 50",
    "sg:postcode":"20001",
    "sg:province":"Guip\u00f9zcoa",
    "wof:name":"Martinez Arraiza Maria Isabel",
    "wof:placetype":"venue"
},
  "geometry": {"coordinates":[-1.9734209776,43.3235054016],"type":"Point"}
}