{
  "type": "Feature",
  "properties": {
    "addr:full":"Calle de Tejares, 82 Albacete Albacete 02002",
    "addr:housenumber":"82",
    "addr:postcode":"02002",
    "addr:street":"Calle De Tejares",
    "iso:country":"ES",
    "sg:address":"Calle de Tejares, 82",
    "sg:city":"Albacete",
    "sg:orig_category":"Reposter\u00cdas",
    "sg:phone":"+34 967 23 67 41",
    "sg:postcode":"02002",
    "sg:province":"Albacete",
    "wof:name":"Esparcia Matias Juan",
    "wof:placetype":"venue"
},
  "geometry": {"coordinates":[-1.8537579775,38.9875831604],"type":"Point"}
}