{
  "type": "Feature",
  "properties": {
    "addr:full":"Cra Espinel, 87 Ronda M\u00e1laga 29400",
    "addr:postcode":"29400",
    "addr:street":"Ronda Ma\u0301Laga",
    "iso:country":"ES",
    "sg:address":"Cra Espinel, 87",
    "sg:city":"Ronda",
    "sg:orig_category":"Abogados",
    "sg:phone":"+34 952 87 18 99",
    "sg:postcode":"29400",
    "sg:province":"M\u00e1laga",
    "wof:name":"Rivero Calderon Diego",
    "wof:placetype":"venue"
},
  "geometry": {"coordinates":[-5.1615958214,36.7449798584],"type":"Point"}
}