{
  "type": "Feature",
  "properties": {
    "addr:full":"Calle de Real De Arganda, 11 Madrid Madrid 28031",
    "addr:housenumber":"11",
    "addr:postcode":"madrid;28031",
    "addr:street":"Calle De Real De Arganda",
    "iso:country":"ES",
    "sg:address":"Calle de Real De Arganda, 11",
    "sg:city":"Madrid",
    "sg:orig_category":"\u00d3ptica: Instrumentos (fabricaci\u00d3n)",
    "sg:phone":"+34 913 32 76 44",
    "sg:postcode":"28031",
    "sg:province":"Madrid",
    "wof:name":"Centro Optico Abascal S.l.",
    "wof:placetype":"venue"
},
  "geometry": {"coordinates":[-3.6201300621,40.3797073364],"type":"Point"}
}