{
  "type": "Feature",
  "properties": {
    "iso:country":"ES",
    "sg:address":"Avda Espinela, 2",
    "sg:city":"Madrid",
    "sg:orig_category":"Zapatos (al Por Menor)",
    "sg:phone":"+34 917 97 12 05",
    "sg:postcode":"28021",
    "sg:province":"Madrid",
    "wof:name":"Arquepaz S.a.",
    "wof:placetype":"venue"
},
  "geometry": {"coordinates":[-3.7090034485,40.3462333679],"type":"Point"}
}