{
  "type": "Feature",
  "properties": {
    "addr:full":"Calle de Ardemans, 8 Madrid Madrid 28028",
    "addr:housenumber":"8",
    "addr:postcode":"madrid;28028",
    "addr:street":"Calle De Ardemans",
    "iso:country":"ES",
    "sg:address":"Calle de Ardemans, 8",
    "sg:city":"Madrid",
    "sg:orig_category":"Fisioterapia",
    "sg:phone":"+34 917 13 01 26",
    "sg:postcode":"28028",
    "sg:province":"Madrid",
    "wof:name":"Care Fisioterapia S.l.",
    "wof:placetype":"venue"
},
  "geometry": {"coordinates":[-3.6711080074,40.4331092834],"type":"Point"}
}