{
  "type": "Feature",
  "properties": {
    "iso:country":"ES",
    "sg:address":"Calle de Alfonso X El Sabio, 1",
    "sg:city":"Burgos",
    "sg:orig_category":"Frutas, Legumbres Frescas Y Tempranas (al Por Menor)",
    "sg:phone":"+34 947 22 14 22",
    "sg:postcode":"09005",
    "sg:province":"Burgos",
    "wof:name":"Gonzalez Alegre Carmelo",
    "wof:placetype":"venue"
},
  "geometry": {"coordinates":[-3.6957755089,42.3477096558],"type":"Point"}
}