{
  "type": "Feature",
  "properties": {
    "iso:country":"ES",
    "sg:address":"Calle de Gabriel Y Zamora, 9",
    "sg:city":"Andujar",
    "sg:orig_category":"Doctores En Medicina",
    "sg:phone":"+34 953 51 01 66",
    "sg:postcode":"23740",
    "sg:province":"Ja\u00e9n",
    "wof:name":"Perea Serrano Lorenzo",
    "wof:placetype":"venue"
},
  "geometry": {"coordinates":[-4.0546884537,38.0409622192],"type":"Point"}
}