{
  "type": "Feature",
  "properties": {
    "iso:country":"ES",
    "sg:address":"Calle de Pio Gullon, 22",
    "sg:city":"Astorga",
    "sg:orig_category":"Electricidad: Instaladores",
    "sg:phone":"+34 987 61 82 02",
    "sg:postcode":"24700",
    "sg:province":"Le\u00f3n",
    "wof:name":"Vi\u00f1ambres Panizo Alberto",
    "wof:placetype":"venue"
},
  "geometry": {"coordinates":[-6.053984642,42.4557113647],"type":"Point"}
}