{
  "type": "Feature",
  "properties": {
    "addr:full":"Calle de Puerto De Ordu\u00d1a, 1 Andra Mari Vizcaya 48993",
    "addr:housenumber":"1",
    "addr:postcode":"48993",
    "addr:street":"Calle De Puerto De Ordun\u0303A",
    "iso:country":"ES",
    "sg:address":"Calle de Puerto De Ordu\u00d1a, 1",
    "sg:city":"Andra Mari",
    "sg:orig_category":"Cooperativas Agr\u00cdcolas",
    "sg:phone":"+34 944 30 22 10",
    "sg:postcode":"48993",
    "sg:province":"Vizcaya",
    "wof:name":"Eroski Sociedad Cooperativa",
    "wof:placetype":"venue"
},
  "geometry": {"coordinates":[-2.7541499138,43.2982711792],"type":"Point"}
}