{
  "type": "Feature",
  "properties": {
    "iso:country":"ES",
    "sg:address":"Fcn Pu\u00f1o En Rostro, S/n",
    "sg:city":"Albacete",
    "sg:orig_category":"Producci\u00d3n, Venta De Productos De Agricultura Biol\u00d3gica",
    "sg:phone":"+34 967 58 04 29",
    "sg:postcode":"02006",
    "sg:province":"Albacete",
    "wof:name":"Enco Albacete S.a.",
    "wof:placetype":"venue"
},
  "geometry": {"coordinates":[-1.878393054,39.0851097107],"type":"Point"}
}