{
  "type": "Feature",
  "properties": {
    "addr:full":"Calle de Goienkalea, 2 Durango Vizcaya 48200",
    "addr:housenumber":"2",
    "addr:postcode":"48200",
    "addr:street":"Calle De Goienkalea",
    "iso:country":"ES",
    "sg:address":"Calle de Goienkalea, 2",
    "sg:city":"Durango",
    "sg:orig_category":"Molduras, Junquillos, Listones Y Molduras Perforadas",
    "sg:phone":"+34 946 81 18 02",
    "sg:postcode":"48200",
    "sg:province":"Vizcaya",
    "wof:name":"Phone Euskadi S. L.",
    "wof:placetype":"venue"
},
  "geometry": {"coordinates":[-2.6310191154,43.1667976379],"type":"Point"}
}