{
  "type": "Feature",
  "properties": {
    "iso:country":"ES",
    "sg:address":"Autovia(p Campollano), 14",
    "sg:city":"Albacete",
    "sg:orig_category":"Transportes Internacionales",
    "sg:phone":"+34 967 21 35 68",
    "sg:postcode":"02006",
    "sg:province":"Albacete",
    "wof:name":"Pedro Galiano S.l.",
    "wof:placetype":"venue"
},
  "geometry": {"coordinates":[-1.9050639868,38.9838294983],"type":"Point"}
}