{
  "type": "Feature",
  "properties": {
    "addr:full":"Rbla Just Oliveras, 66 Hospitalet Llobregat Barcelona 08901",
    "addr:housenumber":"66",
    "addr:postcode":"08901",
    "addr:street":"Rbla Just Oliveras",
    "iso:country":"ES",
    "sg:address":"Rbla Just Oliveras, 66",
    "sg:city":"Hospitalet Llobregat",
    "sg:orig_category":"Caf\u00c9s, Bares, Cervecer\u00cdas",
    "sg:phone":"+34 933 38 31 63",
    "sg:postcode":"08901",
    "sg:province":"Barcelona",
    "wof:name":"Supertrol S.l.",
    "wof:placetype":"venue"
},
  "geometry": {"coordinates":[2.105494976,41.3626899719],"type":"Point"}
}