{
  "type": "Feature",
  "properties": {
    "iso:country":"ES",
    "sg:address":"Calle de Llama (la), 4",
    "sg:city":"Torrelavega",
    "sg:orig_category":"Distribuci\u00d3n De Petr\u00d3leo Y Derivados",
    "sg:phone":"+34 942 89 31 10",
    "sg:postcode":"39300",
    "sg:province":"Cantabria",
    "wof:name":"Manupinturas S.l.",
    "wof:placetype":"venue"
},
  "geometry": {"coordinates":[-4.0443549156,43.3476142883],"type":"Point"}
}