{
  "type": "Feature",
  "properties": {
    "addr:full":"Pg Gran Passeig Ronda, 31 Lleida Lleida 25003",
    "addr:housenumber":"31",
    "addr:postcode":"25003",
    "addr:street":"Pg Gran Passeig Ronda",
    "iso:country":"ES",
    "sg:address":"Pg Gran Passeig Ronda, 31",
    "sg:city":"Lleida",
    "sg:orig_category":"Asistencia Social",
    "sg:phone":"+34 973 27 11 85",
    "sg:postcode":"25003",
    "sg:province":"Lleida",
    "wof:name":"Remar Espa\u00f1a",
    "wof:placetype":"venue"
},
  "geometry": {"coordinates":[0.6135339737,41.6129341125],"type":"Point"}
}