{
  "type": "Feature",
  "properties": {
    "addr:full":"Rua Illas Canarias, 2 Lugo Lugo 27003",
    "addr:housenumber":"2",
    "addr:postcode":"27003",
    "addr:street":"Rua Illas Canarias",
    "iso:country":"ES",
    "sg:address":"Rua Illas Canarias, 2",
    "sg:city":"Lugo",
    "sg:orig_category":"Reposter\u00cdas",
    "sg:phone":"+34 982 21 70 51",
    "sg:postcode":"27003",
    "sg:province":"Lugo",
    "wof:name":"Pan Y Panaderia De Ousa S.l.",
    "wof:placetype":"venue"
},
  "geometry": {"coordinates":[-7.5647192001,43.0225105286],"type":"Point"}
}