{
  "type": "Feature",
  "properties": {
    "addr:full":"Av Lluis Companys, 24 S. Cugat Valles Barcelona 08172",
    "addr:housenumber":"24",
    "addr:postcode":"08172",
    "addr:street":"Av Lluis Companys;S. Cugat Valles Barcelona",
    "iso:country":"ES",
    "sg:address":"Av Lluis Companys, 24",
    "sg:city":"S. Cugat Valles",
    "sg:classifiers":[
        {
            "category":"Personal",
            "subcategory":"Barber",
            "type":"Services"
        }
    ],
    "sg:phone":"+34 936 74 00 77",
    "sg:postcode":"08172",
    "sg:province":"Barcelona",
    "sg:tags":[
        "caballeros",
        "de",
        "peluqueros"
    ],
    "wof:name":"Garcia Alemany Fernando",
    "wof:placetype":"venue"
},
  "geometry": {"coordinates":[2.0788419247,41.4704437256],"type":"Point"}
}