{
  "type": "Feature",
  "properties": {
    "iso:country":"ES",
    "sg:address":"Avda Barcelona, 11",
    "sg:city":"Jaen",
    "sg:orig_category":"Peluqueros: De Se\u00d1oras",
    "sg:phone":"+34 953 26 79 12",
    "sg:postcode":"23006",
    "sg:province":"Ja\u00e9n",
    "wof:name":"Barajas Guzman Maria Josefa",
    "wof:placetype":"venue"
},
  "geometry": {"coordinates":[-3.798032999,37.7802772522],"type":"Point"}
}