{
  "type": "Feature",
  "properties": {
    "iso:country":"ES",
    "sg:address":"Calle de Avda. Diputacion, 17",
    "sg:city":"Ribaforada",
    "sg:orig_category":"Asesor\u00cda Sobre Comunicaci\u00d3n De Empresas",
    "sg:phone":"+34 948 81 94 77",
    "sg:postcode":"31550",
    "sg:province":"Navarra",
    "wof:name":"Iber Asesores Mga S.l.",
    "wof:placetype":"venue"
},
  "geometry": {"coordinates":[-1.5133136511,41.9981040955],"type":"Point"}
}