{
  "type": "Feature",
  "properties": {
    "addr:full":"Calle de Gregorio Aurre, 37 Langreo Asturias 33930",
    "addr:housenumber":"37",
    "addr:postcode":"33930",
    "addr:street":"Calle De Gregorio Aurre",
    "iso:country":"ES",
    "sg:address":"Calle de Gregorio Aurre, 37",
    "sg:city":"Langreo",
    "sg:orig_category":"Zapatos (al Por Menor)",
    "sg:phone":"+34 985 67 59 34",
    "sg:postcode":"33930",
    "sg:province":"Asturias",
    "wof:name":"Llamas Garcia Placi",
    "wof:placetype":"venue"
},
  "geometry": {"coordinates":[-5.69120121,43.3093566895],"type":"Point"}
}