{
  "type": "Feature",
  "properties": {
    "iso:country":"ES",
    "sg:address":"Avda Extremadura, 69",
    "sg:city":"Navaconcejo",
    "sg:orig_category":"Aparatos E Instalaci\u00d3n De Regad\u00cdos",
    "sg:phone":"+34 927 17 35 21",
    "sg:postcode":"10613",
    "sg:province":"C\u00e1ceres",
    "wof:name":"Riegos Del Norte Extreme\u00f1o S.l.",
    "wof:placetype":"venue"
},
  "geometry": {"coordinates":[-5.8289971352,40.1785354614],"type":"Point"}
}