{
  "type": "Feature",
  "properties": {
    "iso:country":"ES",
    "sg:address":"Carrer de Joan Coll, 6",
    "sg:city":"Granollers",
    "sg:orig_category":"Aparcamientos (infraestructuras, Accesorios)",
    "sg:phone":"+34 938 46 36 39",
    "sg:postcode":"08401",
    "sg:province":"Barcelona",
    "wof:name":"Estacionamientos Y Servicios S.a.",
    "wof:placetype":"venue"
},
  "geometry": {"coordinates":[2.2879359722,41.6107139587],"type":"Point"}
}