{
  "type": "Feature",
  "properties": {
    "addr:full":"Carrer de Barcelona (de), 25 Salou Tarragona 43840",
    "addr:housenumber":"25",
    "addr:postcode":"43840",
    "addr:street":"Carrer De Barcelona De",
    "iso:country":"ES",
    "sg:address":"Carrer de Barcelona (de), 25",
    "sg:city":"Salou",
    "sg:orig_category":"Perfumer\u00cda (al Por Menor)",
    "sg:phone":"+34 977 35 08 73",
    "sg:postcode":"43840",
    "sg:province":"Tarragona",
    "wof:name":"Fernan's S.a.",
    "wof:placetype":"venue"
},
  "geometry": {"coordinates":[1.1313949823,41.0775527954],"type":"Point"}
}