{
  "type": "Feature",
  "properties": {
    "iso:country":"ES",
    "sg:address":"Ferro, 7",
    "sg:city":"Pol. Ind. Can Pelegri",
    "sg:orig_category":"Productos Qu\u00cdmicos (fabricaci\u00d3n, Al Por Mayor)",
    "sg:phone":"+34 936 53 50 22",
    "sg:postcode":"08755",
    "sg:province":"Barcelona",
    "sg:website":"www.texsa.com",
    "wof:name":"Texsa S.a.",
    "wof:placetype":"venue"
},
  "geometry": {"coordinates":[1.9751399755,41.4769897461],"type":"Point"}
}