{
  "type": "Feature",
  "properties": {
    "addr:full":"Calle de Elduayen, 15 Baiona Pontevedra 36300",
    "addr:housenumber":"15",
    "addr:postcode":"36300",
    "addr:street":"Calle De Elduayen",
    "iso:country":"ES",
    "sg:address":"Calle de Elduayen, 15",
    "sg:city":"Baiona",
    "sg:orig_category":"Cajas De Ahorro",
    "sg:phone":"+34 986 35 80 89",
    "sg:postcode":"36300",
    "sg:province":"Pontevedra",
    "wof:name":"Caixa D'estalvis I Pensions De Barcelona",
    "wof:placetype":"venue"
},
  "geometry": {"coordinates":[-97.78224945069999,45.7040786743],"type":"Point"}
}