{
  "type": "Feature",
  "properties": {
    "iso:country":"ES",
    "sg:address":"Calle de Huertas, 9",
    "sg:city":"Cabra Del Santo Cristo",
    "sg:orig_category":"Empresas De Carpinter\u00cda De Madera",
    "sg:phone":"+34 953 39 70 16",
    "sg:postcode":"23550",
    "sg:province":"Ja\u00e9n",
    "wof:name":"Perea Fernandez Antonio",
    "wof:placetype":"venue"
},
  "geometry": {"coordinates":[-3.2883250713,37.7031822205],"type":"Point"}
}