{
  "type": "Feature",
  "properties": {
    "addr:full":"Monte, 51 Mos Pontevedra 36418",
    "addr:housenumber":"51",
    "addr:postcode":"36418",
    "addr:street":"Monte",
    "iso:country":"ES",
    "sg:address":"Monte, 51",
    "sg:city":"Mos",
    "sg:orig_category":"Caf\u00c9s, Bares, Cervecer\u00cdas",
    "sg:phone":"+34 986 33 00 30",
    "sg:postcode":"36418",
    "sg:province":"Pontevedra",
    "wof:name":"Don Cafe C.b.",
    "wof:placetype":"venue"
},
  "geometry": {"coordinates":[-8.6304483414,42.1770477295],"type":"Point"}
}