{
  "type": "Feature",
  "properties": {
    "addr:full":"Calle de Timoteo Padros, 13 San Lorenzo De El Escorial Madrid 28200",
    "addr:housenumber":"13",
    "addr:postcode":"28200",
    "addr:street":"Calle De Timoteo Padros",
    "iso:country":"ES",
    "sg:address":"Calle de Timoteo Padros, 13",
    "sg:city":"San Lorenzo De El Escorial",
    "sg:orig_category":"Centros Empresariales",
    "sg:phone":"+34 918 90 59 08",
    "sg:postcode":"28200",
    "sg:province":"Madrid",
    "wof:name":"Einsteinnet S.l.",
    "wof:placetype":"venue"
},
  "geometry": {"coordinates":[-4.1539940834,40.5892486572],"type":"Point"}
}