{
  "type": "Feature",
  "properties": {
    "addr:full":"Calle de Carreterica Posete, 31 Cieza Murcia 30530",
    "addr:housenumber":"31",
    "addr:postcode":"30530",
    "addr:street":"Calle De Carreterica Posete",
    "iso:country":"ES",
    "sg:address":"Calle de Carreterica Posete, 31",
    "sg:city":"Cieza",
    "sg:orig_category":"Promotores Constructores",
    "sg:phone":"+34 968 45 65 87",
    "sg:postcode":"30530",
    "sg:province":"Murcia",
    "wof:name":"Hermanos Lopez Lucas S.a.",
    "wof:placetype":"venue"
},
  "geometry": {"coordinates":[-1.4198486805,38.2382926941],"type":"Point"}
}