{
  "type": "Feature",
  "properties": {
    "iso:country":"ES",
    "sg:address":"Mercat Collblanc, 125",
    "sg:city":"Hospitalet Llobregat",
    "sg:orig_category":"Pescader\u00cdas (al Por Menor)",
    "sg:phone":"+34 933 34 66 55",
    "sg:postcode":"08903",
    "sg:province":"Barcelona",
    "wof:name":"Llado Ayala Sergio",
    "wof:placetype":"venue"
},
  "geometry": {"coordinates":[2.1196498871,41.3757705688],"type":"Point"}
}