{
  "type": "Feature",
  "properties": {
    "addr:full":"Calle de Francos, 19 Jerez De La Frontera C\u00e1diz 11403",
    "addr:housenumber":"19",
    "addr:postcode":"11403",
    "addr:street":"Calle De Francos",
    "iso:country":"ES",
    "sg:address":"Calle de Francos, 19",
    "sg:city":"Jerez De La Frontera",
    "sg:orig_category":"Electrodom\u00c9sticos (al Por Menor)",
    "sg:phone":"+34 956 34 03 46",
    "sg:postcode":"11403",
    "sg:province":"C\u00e1diz",
    "wof:name":"Suministros Industriales Vega S. L.",
    "wof:placetype":"venue"
},
  "geometry": {"coordinates":[-6.138985157,36.6843757629],"type":"Point"}
}