{
  "type": "Feature",
  "properties": {
    "iso:country":"ES",
    "sg:address":"Ctra. De Alhama, 5",
    "sg:city":"Ventas Zafarraya",
    "sg:orig_category":"Quincaller\u00cda (al Por Menor)",
    "sg:phone":"+34 958 36 21 83",
    "sg:postcode":"18128",
    "sg:province":"Granada",
    "wof:name":"Moreno Perez Maria Isabel",
    "wof:placetype":"venue"
},
  "geometry": {"coordinates":[-4.1186099052,36.9584274292],"type":"Point"}
}