{
  "type": "Feature",
  "properties": {
    "iso:country":"ES",
    "sg:address":"Ctra Benasque, S/n",
    "sg:city":"Campo",
    "sg:orig_category":"Centros Empresariales",
    "sg:phone":"+34 974 55 02 34",
    "sg:postcode":"22450",
    "sg:province":"Huesca",
    "wof:name":"Hermanos Gasquet-larramona",
    "wof:placetype":"venue"
},
  "geometry": {"coordinates":[0.3431740105,42.4554100037],"type":"Point"}
}