{
  "type": "Feature",
  "properties": {
    "addr:full":"Carrer de Llevant, 82 Hospitalet Llobregat Barcelona 08905",
    "addr:housenumber":"82",
    "addr:postcode":"08905",
    "addr:street":"Carrer De Llevant",
    "iso:country":"ES",
    "sg:address":"Carrer de Llevant, 82",
    "sg:city":"Hospitalet Llobregat",
    "sg:orig_category":"Tatuajes",
    "sg:phone":"+34 933 33 32 29",
    "sg:postcode":"08905",
    "sg:province":"Barcelona",
    "wof:name":"Olivan Arnau Maria Angeles",
    "wof:placetype":"venue"
},
  "geometry": {"coordinates":[2.1080930233,41.3723907471],"type":"Point"}
}