{
  "type": "Feature",
  "properties": {
    "iso:country":"ES",
    "sg:address":"Carrer de Josep Pla, 184",
    "sg:city":"Barcelona",
    "sg:orig_category":"Telas Y Sedas (al Por Menor)",
    "sg:phone":"+34 932 78 13 75",
    "sg:postcode":"08020",
    "sg:province":"Barcelona",
    "wof:name":"Berges Ibarz Carmen",
    "wof:placetype":"venue"
},
  "geometry": {"coordinates":[2.2060229778,41.4164733887],"type":"Point"}
}