{
  "type": "Feature",
  "properties": {
    "addr:full":"Calle de Fonte, 15 Arzua La Coru\u00f1a 15810",
    "addr:housenumber":"15",
    "addr:postcode":"15810",
    "addr:street":"Calle De Fonte;La Corun\u0303A",
    "iso:country":"ES",
    "sg:address":"Calle de Fonte, 15",
    "sg:city":"Arzua",
    "sg:orig_category":"Electrodom\u00c9sticos (al Por Menor)",
    "sg:phone":"+34 981 50 08 54",
    "sg:postcode":"15810",
    "sg:province":"La Coru\u00f1a",
    "wof:name":"Pampin Quinteiro Antonio",
    "wof:placetype":"venue"
},
  "geometry": {"coordinates":[-8.1644201279,42.9291992188],"type":"Point"}
}