{
  "type": "Feature",
  "properties": {
    "addr:full":"Calle de Chile, 21 Ponferrada Le\u00f3n 24400",
    "addr:housenumber":"21",
    "addr:postcode":"24400",
    "addr:street":"Calle De Chile",
    "iso:country":"ES",
    "sg:address":"Calle de Chile, 21",
    "sg:city":"Ponferrada",
    "sg:orig_category":"Molduras, Junquillos, Listones Y Molduras Perforadas",
    "sg:phone":"+34 987 40 54 80",
    "sg:postcode":"24400",
    "sg:province":"Le\u00f3n",
    "wof:name":"Teldespa\u00d1a S.l.",
    "wof:placetype":"venue"
},
  "geometry": {"coordinates":[-6.587143898,42.5500030518],"type":"Point"}
}