{
  "type": "Feature",
  "properties": {
    "addr:full":"Avda Carolina (la), 17 Vilches Ja\u00e9n 23220",
    "addr:housenumber":"17",
    "addr:postcode":"23220",
    "addr:street":"Avda Carolina La;Jae\u0301N",
    "iso:country":"ES",
    "sg:address":"Avda Carolina (la), 17",
    "sg:city":"Vilches",
    "sg:orig_category":"Aparatos E Instalaci\u00d3n De Regad\u00cdos",
    "sg:phone":"+34 953 63 23 70",
    "sg:postcode":"23220",
    "sg:province":"Ja\u00e9n",
    "wof:name":"Navarro Carretero Rogelio",
    "wof:placetype":"venue"
},
  "geometry": {"coordinates":[-3.5159599781,38.2160835266],"type":"Point"}
}