{
  "type": "Feature",
  "properties": {
    "iso:country":"ES",
    "sg:address":"Calle de Cebrian, 7",
    "sg:city":"Palmas De Gran Canaria",
    "sg:orig_category":"Centros De Coordinaci\u00d3n",
    "sg:phone":"+34 928 37 29 14",
    "sg:postcode":"35003",
    "sg:province":"Las Palmas",
    "wof:name":"Gestocredit",
    "wof:placetype":"venue"
},
  "geometry": {"coordinates":[-15.4174699783,28.1106014252],"type":"Point"}
}