{
  "type": "Feature",
  "properties": {
    "addr:full":"Calle de Galeon, 5 S. Fernando C\u00e1diz 11100",
    "addr:housenumber":"5",
    "addr:postcode":"11100",
    "addr:street":"Calle De Galeon;S. Fernando Ca\u0301Diz",
    "iso:country":"ES",
    "sg:address":"Calle de Galeon, 5",
    "sg:city":"S. Fernando",
    "sg:orig_category":"Artesan\u00cda",
    "sg:phone":"+34 956 59 11 48",
    "sg:postcode":"11100",
    "sg:province":"C\u00e1diz",
    "sg:website":"www.rotulosbahia.com",
    "wof:name":"Rotlulos Bahia S.l.",
    "wof:placetype":"venue"
},
  "geometry": {"coordinates":[-6.2068839073,36.4545211792],"type":"Point"}
}