{
  "type": "Feature",
  "properties": {
    "addr:full":"Calle de Patxi Arrazola, S/n Leitza Navarra 31880",
    "addr:housenumber":"s / n",
    "addr:postcode":"31880",
    "addr:street":"Calle De Patxi Arrazola",
    "iso:country":"ES",
    "sg:address":"Calle de Patxi Arrazola, S/n",
    "sg:city":"Leitza",
    "sg:orig_category":"Suministros Para Carrocer\u00cdas",
    "sg:phone":"+34 948 51 04 60",
    "sg:postcode":"31880",
    "sg:province":"Navarra",
    "wof:name":"Loitegui Yaben Ignacio",
    "wof:placetype":"venue"
},
  "geometry": {"coordinates":[-1.9177122116,43.0861778259],"type":"Point"}
}