{
  "type": "Feature",
  "properties": {
    "iso:country":"ES",
    "sg:address":"Carrer de Sardenya, 375",
    "sg:city":"Barcelona",
    "sg:orig_category":"Electrodom\u00c9sticos (al Por Menor)",
    "sg:phone":"+34 932 07 63 99",
    "sg:postcode":"08025",
    "sg:province":"Barcelona",
    "wof:name":"Sukhminder  Singh",
    "wof:placetype":"venue"
},
  "geometry": {"coordinates":[2.1692860126,41.4062843323],"type":"Point"}
}