{
  "type": "Feature",
  "properties": {
    "iso:country":"ES",
    "sg:address":"Trav De Gracia, 347",
    "sg:city":"Barcelona",
    "sg:orig_category":"M\u00c9dicos: Estomatolog\u00cda",
    "sg:phone":"+34 932 07 39 96",
    "sg:postcode":"08025",
    "sg:province":"Barcelona",
    "wof:name":"Andres Gil Maria Isabel",
    "wof:placetype":"venue"
},
  "geometry": {"coordinates":[2.1599330902,41.3959159851],"type":"Point"}
}