{
  "type": "Feature",
  "properties": {
    "addr:full":"Calle de Los Herran, 30 Vitoria-gasteiz \u00c1lava 01004",
    "addr:housenumber":"30",
    "addr:postcode":"01004",
    "addr:street":"Calle De Los Herran",
    "iso:country":"ES",
    "sg:address":"Calle de Los Herran, 30",
    "sg:city":"Vitoria-gasteiz",
    "sg:orig_category":"Porcelanas, Azulejos (fabricaci\u00d3n, Al Por Mayor)",
    "sg:phone":"+34 945 25 96 68",
    "sg:postcode":"01004",
    "sg:province":"\u00c1lava",
    "sg:website":"www.jorgefernandezceramicas.com",
    "wof:name":"Jorge Fernandez Ceramicas S. A.",
    "wof:placetype":"venue"
},
  "geometry": {"coordinates":[-2.6647489071,42.8447113037],"type":"Point"}
}