{
  "type": "Feature",
  "properties": {
    "addr:full":"Pase General Davila, 272 Santander Cantabria 39006",
    "addr:housenumber":"272",
    "addr:postcode":"39006",
    "iso:country":"ES",
    "sg:address":"Pase General Davila, 272",
    "sg:city":"Santander",
    "sg:orig_category":"Plomeros",
    "sg:phone":"+34 942 34 46 84",
    "sg:postcode":"39006",
    "sg:province":"Cantabria",
    "wof:name":"Santoyo Carriegos Francisco Miguel",
    "wof:placetype":"venue"
},
  "geometry": {"coordinates":[-3.8203589916,43.4641914368],"type":"Point"}
}