{
  "type": "Feature",
  "properties": {
    "addr:full":"Avda Madrid, 42 Zaragoza Zaragoza 50010",
    "addr:housenumber":"42",
    "addr:postcode":"50010",
    "addr:street":"Avda Madrid",
    "iso:country":"ES",
    "sg:address":"Avda Madrid, 42",
    "sg:city":"Zaragoza",
    "sg:orig_category":"\u00d3pticos Optometristas (al Por Menor)",
    "sg:phone":"+34 976 34 04 91",
    "sg:postcode":"50010",
    "sg:province":"Zaragoza",
    "wof:name":"Anadisa S.l.",
    "wof:placetype":"venue"
},
  "geometry": {"coordinates":[-0.9050599933,41.6533164978],"type":"Point"}
}