{
  "type": "Feature",
  "properties": {
    "addr:full":"Avda Monforte De Lemos, 131 Madrid Madrid 28029",
    "addr:housenumber":"131",
    "addr:postcode":"28029",
    "addr:street":"Avda Monforte De Lemos",
    "iso:country":"ES",
    "sg:address":"Avda Monforte De Lemos, 131",
    "sg:city":"Madrid",
    "sg:orig_category":"Tintorer\u00cdas, Limpieza En Seco",
    "sg:phone":"+34 917 30 89 22",
    "sg:postcode":"28029",
    "sg:province":"Madrid",
    "wof:name":"Caceres Castro Jose",
    "wof:placetype":"venue"
},
  "geometry": {"coordinates":[-3.7114470005,40.4776878357],"type":"Point"}
}