{
  "type": "Feature",
  "properties": {
    "addr:full":"D. Juana, 2 Huetor-vega Granada 18198",
    "addr:postcode":"18198",
    "addr:street":"Juana 2 Huetor-Vega",
    "iso:country":"ES",
    "sg:address":"D. Juana, 2",
    "sg:city":"Huetor-vega",
    "sg:orig_category":"Empresas De Carpinter\u00cda Met\u00c1lica",
    "sg:phone":"+34 958 30 13 36",
    "sg:postcode":"18198",
    "sg:province":"Granada",
    "wof:name":"Toldos Y Metalisteria Hv S.l.",
    "wof:placetype":"venue"
},
  "geometry": {"coordinates":[-3.5746409893,37.1468925476],"type":"Point"}
}