{
  "type": "Feature",
  "properties": {
    "addr:full":"Avda Juan Garcia Navia Castrillon, 15 Viveiro Lugo 27850",
    "addr:housenumber":"15",
    "addr:postcode":"27850",
    "addr:street":"Avda Juan Garcia;Castrillon",
    "iso:country":"ES",
    "sg:address":"Avda Juan Garcia Navia Castrillon, 15",
    "sg:city":"Viveiro",
    "sg:orig_category":"M\u00c9dicos: Cirug\u00cda Ortop\u00c9dica Y Traumatolog\u00cda",
    "sg:phone":"+34 982 56 18 08",
    "sg:postcode":"27850",
    "sg:province":"Lugo",
    "wof:name":"Montero Rodriguez Romulo",
    "wof:placetype":"venue"
},
  "geometry": {"coordinates":[-7.5969400406,43.6587028503],"type":"Point"}
}