{
  "type": "Feature",
  "properties": {
    "addr:full":"Avda Garcia Barbon, 28 Vigo Pontevedra 36201",
    "addr:housenumber":"28",
    "addr:postcode":"36201",
    "addr:street":"Avda Garcia Barbon",
    "iso:country":"ES",
    "sg:address":"Avda Garcia Barbon, 28",
    "sg:city":"Vigo",
    "sg:classifiers":[
        {
            "category":"Communications",
            "type":"Services"
        }
    ],
    "sg:phone":"+34 986 44 11 81",
    "sg:postcode":"36201",
    "sg:province":"Pontevedra",
    "sg:tags":[
        "televisiones",
        "y",
        "radio"
    ],
    "sg:website":"www.ondacero.es",
    "wof:name":"Uniprex-onda Cero",
    "wof:placetype":"venue"
},
  "geometry": {"coordinates":[-8.7164077759,42.2367553711],"type":"Point"}
}