{
  "type": "Feature",
  "properties": {
    "iso:country":"ES",
    "sg:address":"Calle de Amatos, 2",
    "sg:city":"Salamanca",
    "sg:orig_category":"Molduras, Junquillos, Listones Y Molduras Perforadas",
    "sg:phone":"+34 923 19 27 84",
    "sg:postcode":"37008",
    "sg:province":"Salamanca",
    "wof:name":"Sanchez Hernandez Nicanor",
    "wof:placetype":"venue"
},
  "geometry": {"coordinates":[-5.6714959145,40.9453811646],"type":"Point"}
}