{
  "type": "Feature",
  "properties": {
    "addr:full":"Cust Carrajete (del), 8 Teruel Teruel 44003",
    "addr:postcode":"44003",
    "iso:country":"ES",
    "sg:address":"Cust Carrajete (del), 8",
    "sg:city":"Teruel",
    "sg:orig_category":"Construcciones Met\u00c1licas",
    "sg:phone":"+34 978 60 39 62",
    "sg:postcode":"44003",
    "sg:province":"Teruel",
    "wof:name":"Acciona Infraestructuras S.a.",
    "wof:placetype":"venue"
},
  "geometry": {"coordinates":[-1.0988419056,40.3351669312],"type":"Point"}
}