{
  "type": "Feature",
  "properties": {
    "addr:full":"Calle de Jose Oto, 24 Zaragoza Zaragoza 50014",
    "addr:housenumber":"24",
    "addr:postcode":"50014",
    "addr:street":"Calle De Jose Oto",
    "iso:country":"ES",
    "sg:address":"Calle de Jose Oto, 24",
    "sg:city":"Zaragoza",
    "sg:orig_category":"Teatros Y Salas De Espect\u00c1culos",
    "sg:phone":"+34 976 47 42 80",
    "sg:postcode":"50014",
    "sg:province":"Zaragoza",
    "wof:name":"Teatro Lirico De Zaragoza",
    "wof:placetype":"venue"
},
  "geometry": {"coordinates":[-0.8627399802,41.6623039246],"type":"Point"}
}