{
  "type": "Feature",
  "properties": {
    "addr:full":"Calle de Ni\u00d1o Jesus, 6 Fuensalida Toledo 45510",
    "addr:housenumber":"6",
    "addr:postcode":"45510",
    "addr:street":"Calle De Nin\u0303O Jesus",
    "iso:country":"ES",
    "sg:address":"Calle de Ni\u00d1o Jesus, 6",
    "sg:city":"Fuensalida",
    "sg:orig_category":"Material Y Suministros Para Perforaciones, Sondeos",
    "sg:phone":"+34 925 78 43 54",
    "sg:postcode":"45510",
    "sg:province":"Toledo",
    "wof:name":"Martin Garcia Constancio",
    "wof:placetype":"venue"
},
  "geometry": {"coordinates":[-4.2117190361,40.0508651733],"type":"Point"}
}