{
  "type": "Feature",
  "properties": {
    "addr:full":"Calle de Cabo San Vicente, 4 Alcorcon Madrid 28924",
    "addr:housenumber":"4",
    "addr:postcode":"28924",
    "addr:street":"Calle De Cabo San Vicente",
    "iso:country":"ES",
    "sg:address":"Calle de Cabo San Vicente, 4",
    "sg:city":"Alcorcon",
    "sg:orig_category":"Bisuter\u00cda, Joyer\u00cda, Relojer\u00cda (al Por Menor)",
    "sg:phone":"+34 916 10 18 76",
    "sg:postcode":"28924",
    "sg:province":"Madrid",
    "wof:name":"Palma Blanco Antonio",
    "wof:placetype":"venue"
},
  "geometry": {"coordinates":[-3.8171451092,40.3535461426],"type":"Point"}
}