{
  "type": "Feature",
  "properties": {
    "iso:country":"ES",
    "sg:address":"Avda Zaragoza (de), 12",
    "sg:city":"Alagon",
    "sg:orig_category":"Muebles, Minoristas",
    "sg:phone":"+34 976 61 11 21",
    "sg:postcode":"50630",
    "sg:province":"Zaragoza",
    "wof:name":"Mayor Perez Pilar",
    "wof:placetype":"venue"
},
  "geometry": {"coordinates":[-1.1180009842,41.7684745789],"type":"Point"}
}