{
  "type": "Feature",
  "properties": {
    "iso:country":"ES",
    "sg:address":"Pl Constitucio, 2",
    "sg:city":"Rubi",
    "sg:orig_category":"Asociaciones Y Clubs Deportivos",
    "sg:phone":"+34 935 87 20 03",
    "sg:postcode":"08191",
    "sg:province":"Barcelona",
    "sg:website":"www.horitzo.org",
    "wof:name":"Club Minusvalids Horitzo",
    "wof:placetype":"venue"
},
  "geometry": {"coordinates":[2.031140089,41.4843635559],"type":"Point"}
}