{
  "type": "Feature",
  "properties": {
    "iso:country":"ES",
    "sg:address":"Carr Jaume Ii, 37",
    "sg:city":"Gandia",
    "sg:orig_category":"Importaci\u00d3n",
    "sg:phone":"+34 962 86 50 05",
    "sg:postcode":"46700",
    "sg:province":"Valencia",
    "wof:name":"Mascarell Cloquell Montse",
    "wof:placetype":"venue"
},
  "geometry": {"coordinates":[-0.1807920039,38.9750366211],"type":"Point"}
}