{
  "type": "Feature",
  "properties": {
    "iso:country":"ES",
    "sg:address":"Calle de Carretas, 2",
    "sg:city":"Nerja",
    "sg:orig_category":"Platos Preparados Refrigerados (fabricaci\u00d3n, Al Por Mayor)",
    "sg:phone":"+34 952 52 57 96",
    "sg:postcode":"29780",
    "sg:province":"M\u00e1laga",
    "wof:name":"Palacio Del Pollo Asado-avpad Sl",
    "wof:placetype":"venue"
},
  "geometry": {"coordinates":[-3.8763906956,36.7489280701],"type":"Point"}
}