{
  "type": "Feature",
  "properties": {
    "iso:country":"ES",
    "sg:address":"Calle de Casas Iba\u00d1ez, S/n",
    "sg:city":"Villamalea",
    "sg:orig_category":"Mec\u00c1nico Del Autom\u00d3vil",
    "sg:phone":"+34 967 48 34 11",
    "sg:postcode":"02270",
    "sg:province":"Albacete",
    "wof:name":"Descalzo Caballero Cb",
    "wof:placetype":"venue"
},
  "geometry": {"coordinates":[-1.5969090462,39.364200592],"type":"Point"}
}