{
  "type": "Feature",
  "properties": {
    "addr:full":"Calle de San Severo, 18 Madrid Madrid 28042",
    "addr:housenumber":"18",
    "addr:postcode":"madrid;28042",
    "addr:street":"Calle De San Severo",
    "iso:country":"ES",
    "sg:address":"Calle de San Severo, 18",
    "sg:city":"Madrid",
    "sg:orig_category":"Asesor\u00cda Sobre Comunicaci\u00d3n De Empresas",
    "sg:phone":"+34 913 29 14 53",
    "sg:postcode":"28042",
    "sg:province":"Madrid",
    "wof:name":"Elsamex S.a.",
    "wof:placetype":"venue"
},
  "geometry": {"coordinates":[-3.5815320015,40.4626235962],"type":"Point"}
}