{
  "type": "Feature",
  "properties": {
    "iso:country":"ES",
    "sg:address":"Calle de Cadiz, 8",
    "sg:city":"Palmones",
    "sg:orig_category":"Molduras, Junquillos, Listones Y Molduras Perforadas",
    "sg:phone":"+34 956 67 52 50",
    "sg:postcode":"11379",
    "sg:province":"C\u00e1diz",
    "wof:name":"Plaza Romero Angel",
    "wof:placetype":"venue"
},
  "geometry": {"coordinates":[-5.3958101273,36.2083320618],"type":"Point"}
}