{
  "type": "Feature",
  "properties": {
    "iso:country":"ES",
    "sg:address":"Calle de Ajofrin, 14",
    "sg:city":"Madrid",
    "sg:orig_category":"Peluquer\u00cdas, Peluquer\u00cda Mixta",
    "sg:phone":"+34 913 06 44 43",
    "sg:postcode":"28037",
    "sg:province":"Madrid",
    "wof:name":"Martin Sanchez Alvaro",
    "wof:placetype":"venue"
},
  "geometry": {"coordinates":[-3.6245605946,40.4248123169],"type":"Point"}
}