{
  "type": "Feature",
  "properties": {
    "iso:country":"ES",
    "sg:address":"Calle de Catalans, 4",
    "sg:city":"Valencia",
    "sg:orig_category":"Imprenta",
    "sg:phone":"+34 963 91 31 09",
    "sg:postcode":"46001",
    "sg:province":"Valencia",
    "wof:name":"Puertes Martinez Jose Francisco",
    "wof:placetype":"venue"
},
  "geometry": {"coordinates":[-0.377440989,39.4754638672],"type":"Point"}
}