{
  "type": "Feature",
  "properties": {
    "iso:country":"ES",
    "sg:address":"Calle de Foguerer, 15",
    "sg:city":"Alacant",
    "sg:orig_category":"Inmobiliaria (agencias)",
    "sg:phone":"+34 965 24 81 57",
    "sg:postcode":"03012",
    "sg:province":"Alicante",
    "wof:name":"Casa Alicante 93 S.l.",
    "wof:placetype":"venue"
},
  "geometry": {"coordinates":[-0.479027003,38.3602523804],"type":"Point"}
}