{
  "type": "Feature",
  "properties": {
    "addr:full":"Calle de San Vicente Martir, 274 Valencia Valencia 46017",
    "addr:housenumber":"274",
    "addr:postcode":"46017",
    "addr:street":"Calle De San Vicente Martir",
    "iso:country":"ES",
    "sg:address":"Calle de San Vicente Martir, 274",
    "sg:city":"Valencia",
    "sg:orig_category":"Alquiler De Veh\u00cdculos: Turismos Y Utilitarios",
    "sg:phone":"+34 963 57 97 79",
    "sg:postcode":"46017",
    "sg:province":"Valencia",
    "wof:name":"Lider Rent S.l.",
    "wof:placetype":"venue"
},
  "geometry": {"coordinates":[-0.3846839964,39.4529724121],"type":"Point"}
}