{
  "type": "Feature",
  "properties": {
    "iso:country":"ES",
    "sg:address":"Carr Rutlla, 19",
    "sg:city":"Figueres",
    "sg:orig_category":"Cl\u00cdnicas M\u00c9dicas",
    "sg:phone":"+34 972 50 39 84",
    "sg:postcode":"17600",
    "sg:province":"Girona",
    "wof:name":"Bonany Pages Maria Antonia",
    "wof:placetype":"venue"
},
  "geometry": {"coordinates":[2.9640910625,42.266456604],"type":"Point"}
}