{
  "type": "Feature",
  "properties": {
    "iso:country":"ES",
    "sg:address":"Carrer de Cabanyes, 1",
    "sg:city":"Argentona",
    "sg:orig_category":"Explotaci\u00d3n De Bosques",
    "sg:phone":"+34 937 97 07 50",
    "sg:postcode":"08310",
    "sg:province":"Barcelona",
    "wof:name":"Famadas Guell Joaquin",
    "wof:placetype":"venue"
},
  "geometry": {"coordinates":[2.4020800591,41.5564117432],"type":"Point"}
}