{
  "type": "Feature",
  "properties": {
    "iso:country":"ES",
    "sg:address":"Calle de Daoiz Y Velarde, 6",
    "sg:city":"Villafranca De Los Barros",
    "sg:orig_category":"Cooperativas Agr\u00cdcolas",
    "sg:phone":"+34 924 52 58 24",
    "sg:postcode":"06220",
    "sg:province":"Badajoz",
    "wof:name":"Jovenes Agricultores Agri-pyme",
    "wof:placetype":"venue"
},
  "geometry": {"coordinates":[-6.3368763924,38.5623588562],"type":"Point"}
}