{
  "type": "Feature",
  "properties": {
    "addr:full":"Plaz Xuquer, 14 Valencia Valencia 46021",
    "addr:housenumber":"14",
    "addr:postcode":"46021",
    "addr:street":"Plaz Xuquer",
    "iso:country":"ES",
    "sg:address":"Plaz Xuquer, 14",
    "sg:city":"Valencia",
    "sg:orig_category":"Centros De Coordinaci\u00d3n",
    "sg:phone":"+34 963 60 12 97",
    "sg:postcode":"46021",
    "sg:province":"Valencia",
    "wof:name":"Benito Fortea Maria Elvira",
    "wof:placetype":"venue"
},
  "geometry": {"coordinates":[-0.3501589894,39.4759788513],"type":"Point"}
}