{
  "type": "Feature",
  "properties": {
    "iso:country":"ES",
    "sg:address":"Calle de Mesones, 23",
    "sg:city":"Constantina",
    "sg:orig_category":"Electrodom\u00c9sticos (al Por Menor)",
    "sg:phone":"+34 955 88 17 39",
    "sg:postcode":"41450",
    "sg:province":"Sevilla",
    "wof:name":"Antonio Rodriguez Guijarro E Hijos S.l.",
    "wof:placetype":"venue"
},
  "geometry": {"coordinates":[-5.6201658249,37.8740348816],"type":"Point"}
}