{
  "type": "Feature",
  "properties": {
    "addr:full":"Carrer de Cardenal Tedeschini, 4 Barcelona Barcelona 08027",
    "addr:housenumber":"4",
    "addr:postcode":"08027",
    "addr:street":"Carrer De Cardenal Tedeschini",
    "iso:country":"ES",
    "sg:address":"Carrer de Cardenal Tedeschini, 4",
    "sg:city":"Barcelona",
    "sg:orig_category":"Inmobiliaria (agencias)",
    "sg:phone":"+34 932 43 02 53",
    "sg:postcode":"08027",
    "sg:province":"Barcelona",
    "wof:name":"Fincas Jadraque S.l.",
    "wof:placetype":"venue"
},
  "geometry": {"coordinates":[2.1857430935,41.4256286621],"type":"Point"}
}