{
  "type": "Feature",
  "properties": {
    "iso:country":"ES",
    "sg:address":"Afueras, S/n",
    "sg:city":"Madrigalejo",
    "sg:orig_category":"Arenas, Guijarros Y Granulados",
    "sg:phone":"+34 927 49 20 24",
    "sg:postcode":"10110",
    "sg:province":"C\u00e1ceres",
    "wof:name":"Aritec Obra Civil S.l",
    "wof:placetype":"venue"
},
  "geometry": {"coordinates":[-5.6352801323,39.1327629089],"type":"Point"}
}