{
  "type": "Feature",
  "properties": {
    "addr:full":"Calle de Torreiro, 11 Coru\u00d1a La Coru\u00f1a 15003",
    "addr:housenumber":"11",
    "addr:postcode":"15003",
    "addr:street":"Calle De Torreiro;La Corun\u0303A",
    "iso:country":"ES",
    "sg:address":"Calle de Torreiro, 11",
    "sg:city":"Coru\u00d1a",
    "sg:orig_category":"Caf\u00c9s, Bares, Cervecer\u00cdas",
    "sg:phone":"+34 981 22 70 57",
    "sg:postcode":"15003",
    "sg:province":"La Coru\u00f1a",
    "wof:name":"Nieto Albar Manuel",
    "wof:placetype":"venue"
},
  "geometry": {"coordinates":[-8.4038801193,43.369720459],"type":"Point"}
}