{
  "type": "Feature",
  "properties": {
    "addr:full":"Avda San Carlos De Chile, 65 Baena C\u00f3rdoba 14850",
    "addr:housenumber":"65",
    "addr:postcode":"14850",
    "addr:street":"Avda San Carlos De Chile",
    "iso:country":"ES",
    "sg:address":"Avda San Carlos De Chile, 65",
    "sg:city":"Baena",
    "sg:orig_category":"Producci\u00d3n, Comercio De Cereales",
    "sg:phone":"+34 957 69 14 07",
    "sg:postcode":"14850",
    "sg:province":"C\u00f3rdoba",
    "wof:name":"Parraga Vargas Rafael",
    "wof:placetype":"venue"
},
  "geometry": {"coordinates":[-4.3228731155,37.62317276],"type":"Point"}
}