{
  "type": "Feature",
  "properties": {
    "iso:country":"ES",
    "sg:address":"Calle de San Bernardo, 109",
    "sg:city":"Madrid",
    "sg:orig_category":"Cl\u00cdnicas M\u00c9dicas",
    "sg:phone":"+34 914 47 11 44",
    "sg:postcode":"28015",
    "sg:province":"Madrid",
    "wof:name":"Fernandez Leiva I\u00f1igo",
    "wof:placetype":"venue"
},
  "geometry": {"coordinates":[-3.711648941,40.4257011414],"type":"Point"}
}