{
  "type": "Feature",
  "properties": {
    "addr:full":"Ruel Brion (de), 9 Santiago De Compostela La Coru\u00f1a 15702",
    "addr:postcode":"15702",
    "addr:street":"Corun\u0303A",
    "iso:country":"ES",
    "sg:address":"Ruel Brion (de), 9",
    "sg:city":"Santiago De Compostela",
    "sg:orig_category":"Arquitectos",
    "sg:phone":"+34 981 59 29 65",
    "sg:postcode":"15702",
    "sg:province":"La Coru\u00f1a",
    "wof:name":"Sabucedo Costa Antonio",
    "wof:placetype":"venue"
},
  "geometry": {"coordinates":[-8.5457162857,42.8682937622],"type":"Point"}
}