{
  "type": "Feature",
  "properties": {
    "addr:full":"Calle de Boggiero, 157 Zaragoza Zaragoza 50...",
    "addr:housenumber":"157;50 ...",
    "addr:street":"Calle De Boggiero;Zaragoza",
    "iso:country":"ES",
    "sg:address":"Calle de Boggiero, 157",
    "sg:city":"Zaragoza",
    "sg:orig_category":"Ingeniero",
    "sg:phone":"+34 976 76 61 30",
    "sg:postcode":"50...",
    "sg:province":"Zaragoza",
    "wof:name":"Comunitel Global S.a.",
    "wof:placetype":"venue"
},
  "geometry": {"coordinates":[-0.8865715265,41.6553611755],"type":"Point"}
}