{
  "type": "Feature",
  "properties": {
    "addr:full":"Rua Costa Do Pincho, 179 Carral La Coru\u00f1a 15175",
    "addr:housenumber":"179",
    "addr:postcode":"15175",
    "addr:street":"Rua Costa Do Pincho;La Corun\u0303A",
    "iso:country":"ES",
    "sg:address":"Rua Costa Do Pincho, 179",
    "sg:city":"Carral",
    "sg:orig_category":"Negocio De Materiales De Construcci\u00d3n",
    "sg:phone":"+34 981 67 03 53",
    "sg:postcode":"15175",
    "sg:province":"La Coru\u00f1a",
    "wof:name":"Gonzalez Bello Jesus",
    "wof:placetype":"venue"
},
  "geometry": {"coordinates":[-8.3558893204,43.2278442383],"type":"Point"}
}