{
  "type": "Feature",
  "properties": {
    "iso:country":"ES",
    "sg:address":"Calle de General Asensio, 6",
    "sg:city":"Fuensalida",
    "sg:orig_category":"Florister\u00cdas",
    "sg:phone":"+34 925 73 20 19",
    "sg:postcode":"45510",
    "sg:province":"Toledo",
    "wof:name":"Fernandez Gomez-escamilla Jesus",
    "wof:placetype":"venue"
},
  "geometry": {"coordinates":[-4.2100520134,40.0568313599],"type":"Point"}
}