{
  "type": "Feature",
  "properties": {
    "iso:country":"ES",
    "sg:address":"Calle de Fernando El Catolico, 77",
    "sg:city":"Madrid",
    "sg:orig_category":"Ense\u00d1anza: Profesiones Art\u00cdsticas",
    "sg:phone":"+34 915 49 83 44",
    "sg:postcode":"28015",
    "sg:province":"Madrid",
    "wof:name":"Shao  Xiao Yu",
    "wof:placetype":"venue"
},
  "geometry": {"coordinates":[-3.7168850899,40.4343070984],"type":"Point"}
}