{
  "type": "Feature",
  "properties": {
    "addr:full":"La Industria, 30 Utiel Valencia 46300",
    "addr:housenumber":"30",
    "addr:postcode":"46300",
    "addr:street":"Industria",
    "iso:country":"ES",
    "sg:address":"La Industria, 30",
    "sg:city":"Utiel",
    "sg:orig_category":"Empresas De Carpinter\u00cda De Madera",
    "sg:phone":"+34 962 17 09 10",
    "sg:postcode":"46300",
    "sg:province":"Valencia",
    "wof:name":"Eugenio Tebar S.l.",
    "wof:placetype":"venue"
},
  "geometry": {"coordinates":[-1.2083319426,39.5780944824],"type":"Point"}
}