{
  "type": "Feature",
  "properties": {
    "iso:country":"ES",
    "sg:address":"Calle de Miguel De Cervantes (de), 19",
    "sg:city":"Algete",
    "sg:orig_category":"Empresarios",
    "sg:phone":"+34 916 28 22 13",
    "sg:postcode":"28110",
    "sg:province":"Madrid",
    "wof:name":"Aguila Perez Antonio",
    "wof:placetype":"venue"
},
  "geometry": {"coordinates":[-3.506534338,40.5995178223],"type":"Point"}
}