{
  "type": "Feature",
  "properties": {
    "iso:country":"ES",
    "sg:address":"Carrer de Campoamor, 57",
    "sg:city":"Sabadell",
    "sg:orig_category":"Artes Gr\u00c1ficas, Artes Pl\u00c1sticas (curso)",
    "sg:phone":"+34 937 10 98 56",
    "sg:postcode":"08204",
    "sg:province":"Barcelona",
    "wof:name":"Martos Encuadernaciones Y Manipulados S.l.",
    "wof:placetype":"venue"
},
  "geometry": {"coordinates":[2.1094369888,41.5284843445],"type":"Point"}
}