{
  "type": "Feature",
  "properties": {
    "addr:full":"Calle de Balcones Los, 8 Palmas De Gran Canaria Las Palmas 35001",
    "addr:postcode":"35001",
    "addr:street":"Calle De;Los",
    "iso:country":"ES",
    "sg:address":"Calle de Balcones Los, 8",
    "sg:city":"Palmas De Gran Canaria",
    "sg:orig_category":"M\u00c9dicos: Foniatr\u00cda Y Logopedia",
    "sg:phone":"+34 928 33 47 02",
    "sg:postcode":"35001",
    "sg:province":"Las Palmas",
    "wof:name":"Casasnovas Susanna Luz",
    "wof:placetype":"venue"
},
  "geometry": {"coordinates":[-15.4131412506,28.1011161804],"type":"Point"}
}