{
  "type": "Feature",
  "properties": {
    "iso:country":"ES",
    "sg:address":"Ctra Madrid-cadiz(bellavista), 133",
    "sg:city":"Sevilla",
    "sg:orig_category":"Molduras, Junquillos, Listones Y Molduras Perforadas",
    "sg:phone":"+34 954 69 00 23",
    "sg:postcode":"41014",
    "sg:province":"Sevilla",
    "wof:name":"Lobato Amadeo Antonio",
    "wof:placetype":"venue"
},
  "geometry": {"coordinates":[-5.9596791267,37.3278617859],"type":"Point"}
}