{
  "type": "Feature",
  "properties": {
    "addr:full":"Calle de Colmenarejo, 48 Galapagar Madrid 28260",
    "addr:housenumber":"48",
    "addr:postcode":"28260",
    "addr:street":"Calle De Colmenarejo",
    "iso:country":"ES",
    "sg:address":"Calle de Colmenarejo, 48",
    "sg:city":"Galapagar",
    "sg:orig_category":"Muebles, Minoristas",
    "sg:phone":"+34 918 58 36 29",
    "sg:postcode":"28260",
    "sg:province":"Madrid",
    "sg:website":"www.casaoriente.com",
    "wof:name":"Hong Tong Comercio Internacional S.l.",
    "wof:placetype":"venue"
},
  "geometry": {"coordinates":[-4.0067501068,40.5741539001],"type":"Point"}
}