{
  "type": "Feature",
  "properties": {
    "addr:full":"Ovi\u00f1ana, S/n Ovi\u00f1ana Asturias 33156",
    "addr:postcode":"33156",
    "addr:street":"Ovin\u0303Ana S / N Ovin\u0303Ana Asturias",
    "iso:country":"ES",
    "sg:address":"Ovi\u00f1ana, S/n",
    "sg:city":"Ovi\u00f1ana",
    "sg:orig_category":"Delegados, Agentes De Tr\u00c1nsito, Auxiliares De Transporte Internacional",
    "sg:phone":"+34 985 59 60 78",
    "sg:postcode":"33156",
    "sg:province":"Asturias",
    "wof:name":"Pelaez Gutierrez Angel",
    "wof:placetype":"venue"
},
  "geometry": {"coordinates":[-6.2376999855,43.5530014038],"type":"Point"}
}