{
  "type": "Feature",
  "properties": {
    "iso:country":"ES",
    "sg:address":"Plaz San Antonio, S/n",
    "sg:city":"Santo\u00f1a",
    "sg:orig_category":"Restaurantes",
    "sg:phone":"+34 942 66 16 45",
    "sg:postcode":"39740",
    "sg:province":"Cantabria",
    "wof:name":"San Emeterio Lavin Constantino",
    "wof:placetype":"venue"
},
  "geometry": {"coordinates":[-3.4561240673,43.4431610107],"type":"Point"}
}