{
  "type": "Feature",
  "properties": {
    "iso:country":"ES",
    "sg:address":"Calle de San Esteban, 56",
    "sg:city":"Hortig\u00fcela",
    "sg:orig_category":"Apicultura",
    "sg:phone":"+34 947 38 40 46",
    "sg:postcode":"09640",
    "sg:province":"Burgos",
    "wof:name":"Blanco De Domingo Agustin",
    "wof:placetype":"venue"
},
  "geometry": {"coordinates":[-3.4268989563,42.0694007874],"type":"Point"}
}