{
  "type": "Feature",
  "properties": {
    "addr:full":"Calle de Doctor Mara\u00d1on, S/n Palmas De Gran Canaria Las Palmas 35013",
    "addr:housenumber":"s",
    "addr:postcode":"35013",
    "addr:street":"Calle De Doctor Maran\u0303On;/ N",
    "iso:country":"ES",
    "sg:address":"Calle de Doctor Mara\u00d1on, S/n",
    "sg:city":"Palmas De Gran Canaria",
    "sg:orig_category":"Distribuci\u00d3n De Petr\u00d3leo Y Derivados",
    "sg:phone":"+34 928 41 88 25",
    "sg:postcode":"35013",
    "sg:province":"Las Palmas",
    "wof:name":"Repsol Ypf S.a.",
    "wof:placetype":"venue"
},
  "geometry": {"coordinates":[-15.4398422241,28.1029815674],"type":"Point"}
}