{
  "type": "Feature",
  "properties": {
    "addr:full":"Calle de San Cayetano, 2 Jerez De La Frontera C\u00e1diz 11402",
    "addr:housenumber":"2",
    "addr:postcode":"11402",
    "addr:street":"Calle De San Cayetano",
    "iso:country":"ES",
    "sg:address":"Calle de San Cayetano, 2",
    "sg:city":"Jerez De La Frontera",
    "sg:orig_category":"Asociaciones Humanitarias, De Cooperaci\u00d3n, De Acci\u00d3n Social",
    "sg:phone":"+34 956 32 30 77",
    "sg:postcode":"11402",
    "sg:province":"C\u00e1diz",
    "wof:name":"Asociacion Padres Ni\u00f1os Sindrome De Down Aspanido",
    "wof:placetype":"venue"
},
  "geometry": {"coordinates":[-6.1357088089,36.688129425],"type":"Point"}
}