{
  "type": "Feature",
  "properties": {
    "iso:country":"ES",
    "sg:address":"Plaz San Pedro Nolasco, 1",
    "sg:city":"Zaragoza",
    "sg:orig_category":"Formaci\u00d3n Continuada (variada)",
    "sg:phone":"+34 976 39 24 21",
    "sg:postcode":"50001",
    "sg:province":"Zaragoza",
    "wof:name":"Lopez Lanuza Tomas",
    "wof:placetype":"venue"
},
  "geometry": {"coordinates":[-0.8772540092,41.652923584],"type":"Point"}
}