{
  "type": "Feature",
  "properties": {
    "addr:full":"Gta Jimenez Barberi, S/n Ayamonte Huelva 21400",
    "addr:postcode":"21400",
    "addr:street":"Gta;Barberi S / N",
    "iso:country":"ES",
    "sg:address":"Gta Jimenez Barberi, S/n",
    "sg:city":"Ayamonte",
    "sg:orig_category":"Molduras, Junquillos, Listones Y Molduras Perforadas",
    "sg:phone":"+34 959 47 15 77",
    "sg:postcode":"21400",
    "sg:province":"Huelva",
    "wof:name":"Garcia Landero Antonio",
    "wof:placetype":"venue"
},
  "geometry": {"coordinates":[-7.4002938271,37.2149963379],"type":"Point"}
}