{
  "type": "Feature",
  "properties": {
    "addr:full":"Avda Andalucia (de), 3 Alcala Real Ja\u00e9n 23680",
    "addr:postcode":"23680",
    "addr:street":"Avda Andalucia De 3 Alcala;Jae\u0301N",
    "iso:country":"ES",
    "sg:address":"Avda Andalucia (de), 3",
    "sg:city":"Alcala Real",
    "sg:orig_category":"Centros M\u00c9dicos Y Sociales, Dispensarios",
    "sg:phone":"+34 953 58 37 11",
    "sg:postcode":"23680",
    "sg:province":"Ja\u00e9n",
    "wof:name":"Mu\u00f1oz Gutierrez Marcelo",
    "wof:placetype":"venue"
},
  "geometry": {"coordinates":[-3.9228060246,37.4601516724],"type":"Point"}
}