{
  "type": "Feature",
  "properties": {
    "addr:full":"Plaz Mayor, 12 Ca\u00f1ada \u00c1vila 05294",
    "addr:housenumber":"12",
    "addr:postcode":"05294",
    "addr:street":"Plaz Mayor;A\u0301Vila",
    "iso:country":"ES",
    "sg:address":"Plaz Mayor, 12",
    "sg:city":"Ca\u00f1ada",
    "sg:orig_category":"Molduras, Junquillos, Listones Y Molduras Perforadas",
    "sg:phone":"+34 920 27 21 11",
    "sg:postcode":"05294",
    "sg:province":"\u00c1vila",
    "wof:name":"Alvarez Quiros Francisco",
    "wof:placetype":"venue"
},
  "geometry": {"coordinates":[-4.700322628,40.6564216614],"type":"Point"}
}