{
  "type": "Feature",
  "properties": {
    "addr:full":"Carr Sol, 4 S. Climent Sescebes Girona 17751",
    "addr:housenumber":"4",
    "addr:postcode":"17751",
    "addr:street":"Carr Sol",
    "iso:country":"ES",
    "sg:address":"Carr Sol, 4",
    "sg:city":"S. Climent Sescebes",
    "sg:orig_category":"Cooperativas Agr\u00cdcolas",
    "sg:phone":"+34 972 56 33 70",
    "sg:postcode":"17751",
    "sg:province":"Girona",
    "wof:name":"Cooperativa Agricola De San Clemente Sasebas",
    "wof:placetype":"venue"
},
  "geometry": {"coordinates":[2.973058939,42.3635139465],"type":"Point"}
}