{
  "type": "Feature",
  "properties": {
    "iso:country":"ES",
    "sg:address":"Avda Reina Victoria, 127",
    "sg:city":"Santander",
    "sg:orig_category":"Inversiones",
    "sg:phone":"+34 942 27 40 00",
    "sg:postcode":"39005",
    "sg:province":"Cantabria",
    "wof:name":"Inversiones Tres Mares 98 S.l.",
    "wof:placetype":"venue"
},
  "geometry": {"coordinates":[-3.7783288956,43.4708023071],"type":"Point"}
}