{
  "type": "Feature",
  "properties": {
    "addr:full":"Calle de Hospital, 2 Cartaya Huelva 21450",
    "addr:housenumber":"2",
    "addr:postcode":"21450",
    "addr:street":"Calle De Hospital",
    "iso:country":"ES",
    "sg:address":"Calle de Hospital, 2",
    "sg:city":"Cartaya",
    "sg:orig_category":"M\u00c9dicos: Estomatolog\u00cda",
    "sg:phone":"+34 959 39 01 97",
    "sg:postcode":"21450",
    "sg:province":"Huelva",
    "wof:name":"Sanchez Conejo-mir Jose Ignacio",
    "wof:placetype":"venue"
},
  "geometry": {"coordinates":[-7.1551527977,37.2831459045],"type":"Point"}
}