{
  "type": "Feature",
  "properties": {
    "addr:full":"Uno De Mayo, 8 Quart Poblet Valencia 46930",
    "addr:housenumber":"8",
    "addr:postcode":"46930",
    "addr:street":"Mayo;Poblet",
    "iso:country":"ES",
    "sg:address":"Uno De Mayo, 8",
    "sg:city":"Quart Poblet",
    "sg:orig_category":"Art\u00cdculos De Regalo (al Por Menor)",
    "sg:phone":"+34 961 54 48 73",
    "sg:postcode":"46930",
    "sg:province":"Valencia",
    "wof:name":"Sobrino Fernandez Francisca",
    "wof:placetype":"venue"
},
  "geometry": {"coordinates":[-0.4419890046,39.482711792],"type":"Point"}
}