{
  "type": "Feature",
  "properties": {
    "iso:country":"ES",
    "sg:address":"Calle de Palacio Valdes, 1",
    "sg:city":"Oviedo",
    "sg:orig_category":"Sindicatos De Trabajadores",
    "sg:phone":"+34 985 22 19 59",
    "sg:postcode":"33002",
    "sg:province":"Asturias",
    "wof:name":"U.g.t.federacion De Industrias Afines",
    "wof:placetype":"venue"
},
  "geometry": {"coordinates":[-5.8491950035,43.3635635376],"type":"Point"}
}