{
  "type": "Feature",
  "properties": {
    "addr:full":"Pla\u00c7 S Joan, 8 Igualada Barcelona 08700",
    "addr:housenumber":"8",
    "addr:postcode":"08700",
    "addr:street":"Plac\u0327;Joan",
    "iso:country":"ES",
    "sg:address":"Pla\u00c7 S Joan, 8",
    "sg:city":"Igualada",
    "sg:orig_category":"Carnicer\u00cdas, Carnicer\u00cdas",
    "sg:phone":"+34 938 03 13 85",
    "sg:postcode":"08700",
    "sg:province":"Barcelona",
    "wof:name":"Gual Angrill S.l.",
    "wof:placetype":"venue"
},
  "geometry": {"coordinates":[1.6129490137,41.5849189758],"type":"Point"}
}