{
  "type": "Feature",
  "properties": {
    "addr:full":"Calle de Pablo Penaguilas, 115 Palmas De Gran Canaria Las Palmas 35012",
    "addr:housenumber":"115",
    "addr:postcode":"35012",
    "addr:street":"Calle De Pablo Penaguilas",
    "iso:country":"ES",
    "sg:address":"Calle de Pablo Penaguilas, 115",
    "sg:city":"Palmas De Gran Canaria",
    "sg:orig_category":"Prot\u00c9sicos Dentales",
    "sg:phone":"+34 928 28 06 55",
    "sg:postcode":"35012",
    "sg:province":"Las Palmas",
    "wof:name":"Gonzalez Suarez Francisco Javier",
    "wof:placetype":"venue"
},
  "geometry": {"coordinates":[-15.4360265732,28.1095676422],"type":"Point"}
}