{
  "type": "Feature",
  "properties": {
    "addr:full":"Ctra Beniajan(la Azacaya), 105 Murcia Murcia 30011",
    "addr:housenumber":"105",
    "addr:postcode":"30011",
    "addr:street":"Ctra Beniajan La Azacaya",
    "iso:country":"ES",
    "sg:address":"Ctra Beniajan(la Azacaya), 105",
    "sg:city":"Murcia",
    "sg:orig_category":"Importaci\u00d3n",
    "sg:phone":"+34 968 34 76 22",
    "sg:postcode":"30011",
    "sg:province":"Murcia",
    "wof:name":"Importadora De Bisuteria Y Complementos J A N S. L.",
    "wof:placetype":"venue"
},
  "geometry": {"coordinates":[-1.1055790186,37.9783668518],"type":"Point"}
}