{
  "type": "Feature",
  "properties": {
    "iso:country":"ES",
    "sg:address":"Plaz Rendicion De Breda, 6",
    "sg:city":"Madrid",
    "sg:orig_category":"Molduras, Junquillos, Listones Y Molduras Perforadas",
    "sg:phone":"+34 914 69 35 06",
    "sg:postcode":"28025",
    "sg:province":"Madrid",
    "wof:name":"Gonzalez Fernandez Maria Teresa",
    "wof:placetype":"venue"
},
  "geometry": {"coordinates":[-3.7313089371,40.3765983582],"type":"Point"}
}