{
  "type": "Feature",
  "properties": {
    "addr:full":"Estd Castela, 372 Ponto La Coru\u00f1a 15570",
    "addr:housenumber":"372",
    "addr:postcode":"15570",
    "addr:street":"Castela;Corun\u0303A",
    "iso:country":"ES",
    "sg:address":"Estd Castela, 372",
    "sg:city":"Ponto",
    "sg:orig_category":"Transportes Por Carretera: Lotes Completos, Mercanc\u00cdas Diversas",
    "sg:phone":"+34 981 38 12 22",
    "sg:postcode":"15570",
    "sg:province":"La Coru\u00f1a",
    "wof:name":"Distribuciones Froiz S.a.",
    "wof:placetype":"venue"
},
  "geometry": {"coordinates":[-8.1647539139,43.5165405273],"type":"Point"}
}