{
  "type": "Feature",
  "properties": {
    "addr:full":"Calle de Loiolako Inazio Kalea, 3 Kurtzea Vizcaya 48960",
    "addr:housenumber":"3",
    "addr:postcode":"48960",
    "addr:street":"Calle De Loiolako Inazio Kalea",
    "iso:country":"ES",
    "sg:address":"Calle de Loiolako Inazio Kalea, 3",
    "sg:city":"Kurtzea",
    "sg:orig_category":"Frutas, Legumbres Frescas Y Tempranas (al Por Menor)",
    "sg:phone":"+34 944 56 40 13",
    "sg:postcode":"48960",
    "sg:province":"Vizcaya",
    "wof:name":"Miranda Gonzalez Gregorio",
    "wof:placetype":"venue"
},
  "geometry": {"coordinates":[-2.8470389843,43.2298049927],"type":"Point"}
}