{
  "type": "Feature",
  "properties": {
    "addr:full":"Av Sant Esteve, 98 Granollers Barcelona 08402",
    "addr:housenumber":"98",
    "addr:postcode":"08402",
    "addr:street":"Av Sant Esteve",
    "iso:country":"ES",
    "sg:address":"Av Sant Esteve, 98",
    "sg:city":"Granollers",
    "sg:orig_category":"Cajas De Ahorro",
    "sg:phone":"+34 938 70 66 35",
    "sg:postcode":"08402",
    "sg:province":"Barcelona",
    "sg:website":"www.caixasabadell.es",
    "wof:name":"Caixa D'estalvis Sabadell",
    "wof:placetype":"venue"
},
  "geometry": {"coordinates":[2.2902600765,41.6006698608],"type":"Point"}
}