{
  "type": "Feature",
  "properties": {
    "iso:country":"ES",
    "sg:address":"Poli Poliviso, S/n",
    "sg:city":"Viso Del Alcor",
    "sg:orig_category":"Suministros Y Materiales Industriales",
    "sg:phone":"+34 955 74 12 47",
    "sg:postcode":"41520",
    "sg:province":"Sevilla",
    "sg:website":"www.grupoalbatros.com",
    "wof:name":"Albatros Promotora Empresarial S.a.",
    "wof:placetype":"venue"
},
  "geometry": {"coordinates":[-5.7141880989,37.3890113831],"type":"Point"}
}