{
  "type": "Feature",
  "properties": {
    "iso:country":"ES",
    "sg:address":"Calle de Carmen Bruguera, 26",
    "sg:city":"Madrid",
    "sg:orig_category":"Doctores En Medicina",
    "sg:phone":"+34 915 00 40 26",
    "sg:postcode":"28026",
    "sg:province":"Madrid",
    "wof:name":"Gramatovich Chichek Sofia",
    "wof:placetype":"venue"
},
  "geometry": {"coordinates":[-3.7037165165,40.3880271912],"type":"Point"}
}