{
  "type": "Feature",
  "properties": {
    "iso:country":"ES",
    "sg:address":"Calle de Conde De Romanones, S/n",
    "sg:city":"Torres Cotillas",
    "sg:orig_category":"Mec\u00c1nico Del Autom\u00d3vil",
    "sg:phone":"+34 968 62 65 97",
    "sg:postcode":"30565",
    "sg:province":"Murcia",
    "wof:name":"Mariano Lopez Martinez S.l.",
    "wof:placetype":"venue"
},
  "geometry": {"coordinates":[-1.2465275526,38.0340919495],"type":"Point"}
}