{
  "type": "Feature",
  "properties": {
    "iso:country":"ES",
    "sg:address":"Avda Espa\u00d1a, 20",
    "sg:city":"Rozas De Madrid",
    "sg:orig_category":"Asesor\u00cda Fiscal Y Jur\u00cddica",
    "sg:phone":"+34 916 37 49 78",
    "sg:postcode":"28231",
    "sg:province":"Madrid",
    "wof:name":"Puente Jimenez Jose Emilio De",
    "wof:placetype":"venue"
},
  "geometry": {"coordinates":[-3.8732800484,40.4876365662],"type":"Point"}
}