{
  "type": "Feature",
  "properties": {
    "iso:country":"ES",
    "sg:address":"Calle de Polvoranca, 75",
    "sg:city":"Alcorcon",
    "sg:orig_category":"Empresas De Carpinter\u00cda Met\u00c1lica",
    "sg:phone":"+34 916 44 45 46",
    "sg:postcode":"28923",
    "sg:province":"Madrid",
    "wof:name":"Doracer S.l.l.",
    "wof:placetype":"venue"
},
  "geometry": {"coordinates":[-3.8108680248,40.3361663818],"type":"Point"}
}