{
  "type": "Feature",
  "properties": {
    "iso:country":"ES",
    "sg:address":"Bo. Seoane, 11",
    "sg:city":"Villaronte",
    "sg:orig_category":"Plomeros",
    "sg:phone":"+34 982 13 71 95",
    "sg:postcode":"27788",
    "sg:province":"Lugo",
    "wof:name":"Lopez Garcia Jesus Maria Maximino",
    "wof:placetype":"venue"
},
  "geometry": {"coordinates":[-7.2581348419,43.5699157715],"type":"Point"}
}