{
  "type": "Feature",
  "properties": {
    "addr:full":"Calle de Cabriana, S/n Miranda Ebro Burgos 09200",
    "addr:housenumber":"s / n",
    "addr:postcode":"09200",
    "addr:street":"Calle De Cabriana",
    "iso:country":"ES",
    "sg:address":"Calle de Cabriana, S/n",
    "sg:city":"Miranda Ebro",
    "sg:orig_category":"Material Y Suministros Para Horticultura, Arboricultura",
    "sg:phone":"+34 947 31 17 08",
    "sg:postcode":"09200",
    "sg:province":"Burgos",
    "wof:name":"Hernandez Contreras Gregorio",
    "wof:placetype":"venue"
},
  "geometry": {"coordinates":[-2.9675571918,42.6790657043],"type":"Point"}
}