{
  "type": "Feature",
  "properties": {
    "addr:full":"Plaz San Pedro, 6 Huesca Huesca 22001",
    "addr:housenumber":"6",
    "addr:postcode":"22001",
    "addr:street":"Plaz San Pedro",
    "iso:country":"ES",
    "sg:address":"Plaz San Pedro, 6",
    "sg:city":"Huesca",
    "sg:orig_category":"Tapiceros Y Tapiceros",
    "sg:phone":"+34 974 23 90 49",
    "sg:postcode":"22001",
    "sg:province":"Huesca",
    "wof:name":"Domec Becana Luis Mariano",
    "wof:placetype":"venue"
},
  "geometry": {"coordinates":[-0.4075680077,42.1386146545],"type":"Point"}
}