{
  "type": "Feature",
  "properties": {
    "addr:full":"Carr Jeroni Pujades, 2 Lleida Lleida 25005",
    "addr:housenumber":"2",
    "addr:postcode":"25005",
    "addr:street":"Carr Jeroni Pujades",
    "iso:country":"ES",
    "sg:address":"Carr Jeroni Pujades, 2",
    "sg:city":"Lleida",
    "sg:orig_category":"Agencias Y Agentes Comerciales, Representantes",
    "sg:phone":"+34 973 23 53 69",
    "sg:postcode":"25005",
    "sg:province":"Lleida",
    "wof:name":"Taules Valcarcel Salvador",
    "wof:placetype":"venue"
},
  "geometry": {"coordinates":[0.6346939802,41.6209945679],"type":"Point"}
}