{
  "type": "Feature",
  "properties": {
    "iso:country":"ES",
    "sg:address":"Carrer de Proven\u00c7a, 1",
    "sg:city":"Montcada Centre",
    "sg:orig_category":"Molduras, Junquillos, Listones Y Molduras Perforadas",
    "sg:phone":"+34 935 75 06 40",
    "sg:postcode":"08110",
    "sg:province":"Barcelona",
    "wof:name":"Rivas Diaz Manuel",
    "wof:placetype":"venue"
},
  "geometry": {"coordinates":[2.1883940697,41.4803237915],"type":"Point"}
}