{
  "type": "Feature",
  "properties": {
    "addr:full":"Plaz Generalisimo, 17 Villafranca Bierzo Le\u00f3n 24500",
    "addr:housenumber":"17",
    "addr:postcode":"24500",
    "addr:street":"Plaz Generalisimo",
    "iso:country":"ES",
    "sg:address":"Plaz Generalisimo, 17",
    "sg:city":"Villafranca Bierzo",
    "sg:orig_category":"Bancos",
    "sg:phone":"+34 987 54 05 50",
    "sg:postcode":"24500",
    "sg:province":"Le\u00f3n",
    "wof:name":"Banco Pastor",
    "wof:placetype":"venue"
},
  "geometry": {"coordinates":[-6.8084750175,42.6093559265],"type":"Point"}
}