{
  "type": "Feature",
  "properties": {
    "iso:country":"ES",
    "sg:address":"C/ Sant Francesc, 3",
    "sg:city":"Ripollet",
    "sg:orig_category":"Maquinaria Para Industrias Diversas",
    "sg:phone":"+34 935 92 18 57",
    "sg:postcode":"08291",
    "sg:province":"Barcelona",
    "wof:name":"Pressbindery S.l.",
    "wof:placetype":"venue"
},
  "geometry": {"coordinates":[2.145567894,41.4967651367],"type":"Point"}
}