{
  "type": "Feature",
  "properties": {
    "iso:country":"ES",
    "sg:address":"Carrer de Ruben Dario, 50",
    "sg:city":"Barcelona",
    "sg:orig_category":"Ferreter\u00cda (diversos)",
    "sg:phone":"+34 933 45 08 34",
    "sg:postcode":"08030",
    "sg:province":"Barcelona",
    "wof:name":"Giralt Costa Jose",
    "wof:placetype":"venue"
},
  "geometry": {"coordinates":[2.1874248981,41.4344406128],"type":"Point"}
}