{
  "type": "Feature",
  "properties": {
    "addr:full":"C/ Doctor Sapena, 64 Elche Alicante 03201",
    "addr:housenumber":"64",
    "addr:postcode":"03201",
    "addr:street":"C / Doctor Sapena",
    "iso:country":"ES",
    "sg:address":"C/ Doctor Sapena, 64",
    "sg:city":"Elche",
    "sg:orig_category":"Venta, Montaje De Neum\u00c1ticos",
    "sg:phone":"+34 966 66 05 13",
    "sg:postcode":"03201",
    "sg:province":"Alicante",
    "wof:name":"Gutierrez Perez Antonio",
    "wof:placetype":"venue"
},
  "geometry": {"coordinates":[-0.7099109888,38.2623748779],"type":"Point"}
}