{
  "type": "Feature",
  "properties": {
    "addr:full":"Carrer de Sant Josep De Calassan\u00c7, 17 Granollers Barcelona 08402",
    "addr:housenumber":"17",
    "addr:postcode":"08402",
    "addr:street":"Carrer De Sant Josep De Calassanc\u0327",
    "iso:country":"ES",
    "sg:address":"Carrer de Sant Josep De Calassan\u00c7, 17",
    "sg:city":"Granollers",
    "sg:orig_category":"Institutos De Belleza",
    "sg:phone":"+34 938 70 86 15",
    "sg:postcode":"08402",
    "sg:province":"Barcelona",
    "wof:name":"Egea Torres Maria",
    "wof:placetype":"venue"
},
  "geometry": {"coordinates":[2.2897338867,41.6038780212],"type":"Point"}
}