{
  "type": "Feature",
  "properties": {
    "addr:full":"Calle de Francisco Romero, 15 Madrid Madrid 28025",
    "addr:housenumber":"15",
    "addr:postcode":"madrid;28025",
    "addr:street":"Calle De Francisco Romero",
    "iso:country":"ES",
    "sg:address":"Calle de Francisco Romero, 15",
    "sg:city":"Madrid",
    "sg:orig_category":"Asesor\u00cda Sobre Comunicaci\u00d3n De Empresas",
    "sg:phone":"+34 915 25 14 55",
    "sg:postcode":"28025",
    "sg:province":"Madrid",
    "wof:name":"Administracion Y Gestion De Comunidades Empresas Navarro S.l.",
    "wof:placetype":"venue"
},
  "geometry": {"coordinates":[-3.7411375046,40.3831596375],"type":"Point"}
}