{
  "type": "Feature",
  "properties": {
    "addr:full":"Calle de Jose Miguel Galvan Bello, 7 Galletas Santa Cruz De Tenerife 38631",
    "addr:housenumber":"7",
    "addr:postcode":"38631",
    "addr:street":"Calle De Jose Miguel Galvan Bello",
    "iso:country":"ES",
    "sg:address":"Calle de Jose Miguel Galvan Bello, 7",
    "sg:city":"Galletas",
    "sg:orig_category":"Esoterismo",
    "sg:phone":"+34 922 78 44 86",
    "sg:postcode":"38631",
    "sg:province":"Santa Cruz De Tenerife",
    "wof:name":"Dinero Express Servicios Globales",
    "wof:placetype":"venue"
},
  "geometry": {"coordinates":[-16.670463562,28.0141906738],"type":"Point"}
}