{
  "type": "Feature",
  "properties": {
    "addr:full":"Calle de Ciudad Real, 3 Torrejon Ardoz Madrid 28850",
    "addr:housenumber":"3",
    "addr:postcode":"28850",
    "addr:street":"Calle De Ciudad Real",
    "iso:country":"ES",
    "sg:address":"Calle de Ciudad Real, 3",
    "sg:city":"Torrejon Ardoz",
    "sg:orig_category":"Retoques De Vestidos",
    "sg:phone":"+34 916 56 01 12",
    "sg:postcode":"28850",
    "sg:province":"Madrid",
    "wof:name":"Sanz Moya Nieves",
    "wof:placetype":"venue"
},
  "geometry": {"coordinates":[-3.4765589237,40.4615631104],"type":"Point"}
}