{
  "type": "Feature",
  "properties": {
    "iso:country":"ES",
    "sg:address":"Calle de Francisco Cuesta, 5",
    "sg:city":"Guadalajara",
    "sg:orig_category":"Peluquer\u00cdas, Peluquer\u00cda Mixta",
    "sg:phone":"+34 949 25 44 44",
    "sg:postcode":"19001",
    "sg:province":"Guadalajara",
    "wof:name":"Duran Salgado Jose",
    "wof:placetype":"venue"
},
  "geometry": {"coordinates":[-3.1673710346,40.6358757019],"type":"Point"}
}