{
  "type": "Feature",
  "properties": {
    "iso:country":"ES",
    "sg:address":"Calle de Azagador De Las Monjas, 4",
    "sg:city":"Valencia",
    "sg:orig_category":"Agencias Y Asesores De Publicidad",
    "sg:phone":"+34 963 34 23 88",
    "sg:postcode":"46018",
    "sg:province":"Valencia",
    "wof:name":"Sotanitas S.l.",
    "wof:placetype":"venue"
},
  "geometry": {"coordinates":[-0.3920356929,39.4607810974],"type":"Point"}
}