{
  "type": "Feature",
  "properties": {
    "addr:full":"Av Rivoli, 22 Mollet Valles Barcelona 08100",
    "addr:housenumber":"22",
    "addr:postcode":"08100",
    "addr:street":"Av Rivoli",
    "iso:country":"ES",
    "sg:address":"Av Rivoli, 22",
    "sg:city":"Mollet Valles",
    "sg:orig_category":"Sociedades, Compa\u00d1\u00cdas Aseguradoras",
    "sg:phone":"+34 935 70 57 82",
    "sg:postcode":"08100",
    "sg:province":"Barcelona",
    "wof:name":"Mapfre Servicios De Informatica",
    "wof:placetype":"venue"
},
  "geometry": {"coordinates":[2.2091259956,41.5466423035],"type":"Point"}
}