{
  "type": "Feature",
  "properties": {
    "iso:country":"ES",
    "sg:address":"Carrer de Tarragona, 14",
    "sg:city":"Barbera Valles",
    "sg:orig_category":"Cl\u00cdnicas Dentales",
    "sg:phone":"+34 937 18 71 05",
    "sg:postcode":"08210",
    "sg:province":"Barcelona",
    "wof:name":"Clinica Dental Tibidabo Scp.",
    "wof:placetype":"venue"
},
  "geometry": {"coordinates":[2.1228840351,41.5067100525],"type":"Point"}
}