{
  "type": "Feature",
  "properties": {
    "iso:country":"ES",
    "sg:address":"Calle de Luis Montoto, 46",
    "sg:city":"Sevilla",
    "sg:orig_category":"Caf\u00c9s, Bares, Cervecer\u00cdas",
    "sg:phone":"+34 954 53 36 20",
    "sg:postcode":"41018",
    "sg:province":"Sevilla",
    "wof:name":"Miguez Majon Francisco",
    "wof:placetype":"venue"
},
  "geometry": {"coordinates":[-5.9798951149,37.3874702454],"type":"Point"}
}