{
  "type": "Feature",
  "properties": {
    "iso:country":"ES",
    "sg:address":"Barro Lapatza, 4",
    "sg:city":"Basauri",
    "sg:orig_category":"Promotores Constructores",
    "sg:phone":"+34 944 05 45 38",
    "sg:postcode":"48970",
    "sg:province":"Vizcaya",
    "wof:name":"Emsama 2000 S.l",
    "wof:placetype":"venue"
},
  "geometry": {"coordinates":[-2.882848978,43.2195968628],"type":"Point"}
}