{
  "type": "Feature",
  "properties": {
    "iso:country":"ES",
    "sg:address":"Calle de Angustias, 3",
    "sg:city":"Ayamonte",
    "sg:orig_category":"Loter\u00cda Y T\u00d3mbola",
    "sg:phone":"+34 959 32 14 04",
    "sg:postcode":"21400",
    "sg:province":"Huelva",
    "wof:name":"Castellano Lorenzo Jose",
    "wof:placetype":"venue"
},
  "geometry": {"coordinates":[-7.4088835716,37.2134971619],"type":"Point"}
}