{
  "type": "Feature",
  "properties": {
    "iso:country":"ES",
    "sg:address":"Avda Italia, 8",
    "sg:city":"Salamanca",
    "sg:orig_category":"Asesor\u00cda Sobre Comunicaci\u00d3n De Empresas",
    "sg:phone":"+34 923 25 85 61",
    "sg:postcode":"37006",
    "sg:province":"Salamanca",
    "wof:name":"Jesus Cruz Martin C.b.",
    "wof:placetype":"venue"
},
  "geometry": {"coordinates":[-5.6643252373,40.9706993103],"type":"Point"}
}