{
  "type": "Feature",
  "properties": {
    "addr:full":"Plza Lagos Azules, 10 Zaragoza Zaragoza 50011",
    "addr:housenumber":"10",
    "addr:postcode":"50011",
    "addr:street":"Lagos Azules",
    "iso:country":"ES",
    "sg:address":"Plza Lagos Azules, 10",
    "sg:city":"Zaragoza",
    "sg:orig_category":"Promotores Constructores",
    "sg:phone":"+34 976 53 00 28",
    "sg:postcode":"50011",
    "sg:province":"Zaragoza",
    "wof:name":"Construcciones Tabuenca S.a.",
    "wof:placetype":"venue"
},
  "geometry": {"coordinates":[-0.9913589954,41.662853241],"type":"Point"}
}