{
  "type": "Feature",
  "properties": {
    "iso:country":"ES",
    "sg:address":"Ctra. Setenil-alcala Valle, Km. 0001,0",
    "sg:city":"Setenil",
    "sg:orig_category":"Distribuci\u00d3n De Petr\u00d3leo Y Derivados",
    "sg:phone":"+34 956 13 44 26",
    "sg:postcode":"11692",
    "sg:province":"C\u00e1diz",
    "wof:name":"Benitez Moreno Jose",
    "wof:placetype":"venue"
},
  "geometry": {"coordinates":[-5.1759090424,36.8626174927],"type":"Point"}
}