{
  "type": "Feature",
  "properties": {
    "addr:full":"Calle de Campito, 43 Aracena Huelva 21200",
    "addr:housenumber":"43",
    "addr:postcode":"21200",
    "addr:street":"Calle De Campito",
    "iso:country":"ES",
    "sg:address":"Calle de Campito, 43",
    "sg:city":"Aracena",
    "sg:orig_category":"Material Y Herramientas Agr\u00cdcolas",
    "sg:phone":"+34 959 12 72 85",
    "sg:postcode":"21200",
    "sg:province":"Huelva",
    "wof:name":"Diaz Dominguez Manuel",
    "wof:placetype":"venue"
},
  "geometry": {"coordinates":[-6.5614700317,37.8948554993],"type":"Point"}
}