{
  "type": "Feature",
  "properties": {
    "iso:country":"ES",
    "sg:address":"Calle de Federico Garcia Lorca, 60",
    "sg:city":"Alovera",
    "sg:orig_category":"Centros Empresariales",
    "sg:phone":"+34 949 27 45 22",
    "sg:postcode":"19208",
    "sg:province":"Guadalajara",
    "wof:name":"La Piramide Espectaculos S.l.",
    "wof:placetype":"venue"
},
  "geometry": {"coordinates":[-3.2573809624,40.5806922913],"type":"Point"}
}