{
  "type": "Feature",
  "properties": {
    "iso:country":"ES",
    "sg:address":"Ctra Valencia-ademuz, Km. 0023,6",
    "sg:city":"Lliria",
    "sg:orig_category":"Remolques, Carretillas De Mano Para Operaciones Portuarias",
    "sg:phone":"+34 962 78 09 15",
    "sg:postcode":"46160",
    "sg:province":"Valencia",
    "wof:name":"Sociedad Cooperativa Valenciana Limitada Volquetes Lliria",
    "wof:placetype":"venue"
},
  "geometry": {"coordinates":[-0.6295570135,39.6478462219],"type":"Point"}
}