{
  "type": "Feature",
  "properties": {
    "addr:full":"Calle de Metales (de Los), 24 Humanes De Madrid Madrid 28970",
    "addr:housenumber":"24",
    "addr:postcode":"28970",
    "addr:street":"Calle De Metales De Los",
    "iso:country":"ES",
    "sg:address":"Calle de Metales (de Los), 24",
    "sg:city":"Humanes De Madrid",
    "sg:orig_category":"Ebanister\u00cda",
    "sg:phone":"+34 916 97 77 65",
    "sg:postcode":"28970",
    "sg:province":"Madrid",
    "wof:name":"Monper 5 S.c.o.o.p.",
    "wof:placetype":"venue"
},
  "geometry": {"coordinates":[-3.8231580257,40.2674942017],"type":"Point"}
}