{
  "type": "Feature",
  "properties": {
    "addr:full":"Avda Camelias, 123 Vigo Pontevedra 36211",
    "addr:housenumber":"123",
    "addr:postcode":"36211",
    "addr:street":"Avda Camelias",
    "iso:country":"ES",
    "sg:address":"Avda Camelias, 123",
    "sg:city":"Vigo",
    "sg:orig_category":"Empresas De Limpieza",
    "sg:phone":"+34 986 42 55 61",
    "sg:postcode":"36211",
    "sg:province":"Pontevedra",
    "wof:name":"Limpiezas Limia S.l.",
    "wof:placetype":"venue"
},
  "geometry": {"coordinates":[-8.7296829224,42.2240333557],"type":"Point"}
}