{
  "type": "Feature",
  "properties": {
    "addr:full":"Plaz Txurruka, S/n Mutriku Guip\u00f9zcoa 20830",
    "addr:housenumber":"s / n",
    "addr:postcode":"20830",
    "addr:street":"Plaz Txurruka;Guipu\u0300Zcoa",
    "iso:country":"ES",
    "sg:address":"Plaz Txurruka, S/n",
    "sg:city":"Mutriku",
    "sg:orig_category":"Iglesia Cat\u00d3lica",
    "sg:phone":"+34 943 60 39 87",
    "sg:postcode":"20830",
    "sg:province":"Guip\u00f9zcoa",
    "wof:name":"Parroquia De Motrico",
    "wof:placetype":"venue"
},
  "geometry": {"coordinates":[-2.3858931065,43.3064956665],"type":"Point"}
}