{
  "type": "Feature",
  "properties": {
    "addr:full":"Calle de Charco, S/n Villa Don Fadrique Toledo 45850",
    "addr:housenumber":"s / n",
    "addr:postcode":"45850",
    "addr:street":"Calle De Charco",
    "iso:country":"ES",
    "sg:address":"Calle de Charco, S/n",
    "sg:city":"Villa Don Fadrique",
    "sg:orig_category":"Cajas Para Embalar",
    "sg:phone":"+34 925 19 52 31",
    "sg:postcode":"45850",
    "sg:province":"Toledo",
    "sg:website":"www.cajaruraldetoledo.es",
    "wof:name":"Caja Rural Provincial De Toledo",
    "wof:placetype":"venue"
},
  "geometry": {"coordinates":[-3.2192139626,39.6164093018],"type":"Point"}
}