{
  "type": "Feature",
  "properties": {
    "iso:country":"ES",
    "sg:address":"Calle de Corregidores, 10",
    "sg:city":"Arcos Frontera",
    "sg:orig_category":"Alimentaci\u00d3n General (al Por Menor)",
    "sg:phone":"+34 956 70 33 88",
    "sg:postcode":"11630",
    "sg:province":"C\u00e1diz",
    "wof:name":"Supercarmela S.l.",
    "wof:placetype":"venue"
},
  "geometry": {"coordinates":[-5.8167009354,36.7500953674],"type":"Point"}
}