{
  "type": "Feature",
  "properties": {
    "iso:country":"ES",
    "sg:address":"Carrer de Napols, 178",
    "sg:city":"Barcelona",
    "sg:orig_category":"Electricidad, Electr\u00d3nica: Material Y Suministros (al Por Mayor)",
    "sg:phone":"+34 932 46 90 27",
    "sg:postcode":"08013",
    "sg:province":"Barcelona",
    "wof:name":"Abc Napols S.l",
    "wof:placetype":"venue"
},
  "geometry": {"coordinates":[2.17558,41.398312],"type":"Point"}
}