{
  "type": "Feature",
  "properties": {
    "iso:country":"ES",
    "sg:address":"Ll. Companys I Jover, 3",
    "sg:city":"Riudoms",
    "sg:orig_category":"Fabricaci\u00d3n De Muebles",
    "sg:phone":"+34 977 85 15 61",
    "sg:postcode":"43330",
    "sg:province":"Tarragona",
    "wof:name":"Carinde 2002 S.l.u.",
    "wof:placetype":"venue"
},
  "geometry": {"coordinates":[1.0623420477,41.1342544556],"type":"Point"}
}