{
  "type": "Feature",
  "properties": {
    "addr:full":"Avda Granada, 30 Huescar Granada 18830",
    "addr:housenumber":"30",
    "addr:postcode":"18830",
    "addr:street":"Avda Granada",
    "iso:country":"ES",
    "sg:address":"Avda Granada, 30",
    "sg:city":"Huescar",
    "sg:orig_category":"Transportes Por Carretera: Lotes Completos, Mercanc\u00cdas Diversas",
    "sg:phone":"+34 958 74 03 40",
    "sg:postcode":"18830",
    "sg:province":"Granada",
    "wof:name":"Garcia De La Serrana Martinez Jose Manuel",
    "wof:placetype":"venue"
},
  "geometry": {"coordinates":[-2.5428309441,37.8058776855],"type":"Point"}
}