{
  "type": "Feature",
  "properties": {
    "iso:country":"ES",
    "sg:address":"Calle de Bolivia, 14",
    "sg:city":"Madrid",
    "sg:orig_category":"M\u00c9dicos: Medicina General Orientada A La Acupuntura",
    "sg:phone":"+34 914 57 44 03",
    "sg:postcode":"28016",
    "sg:province":"Madrid",
    "wof:name":"Pi\u00f1an Gonzalez Gema",
    "wof:placetype":"venue"
},
  "geometry": {"coordinates":[-3.6779797077,40.4567947388],"type":"Point"}
}