{
  "type": "Feature",
  "properties": {
    "addr:full":"Calle de Juan Xxiii, 17 Santurtzi Vizcaya 48980",
    "addr:housenumber":"17",
    "addr:postcode":"48980",
    "addr:street":"Calle De Juan Xxiii",
    "iso:country":"ES",
    "sg:address":"Calle de Juan Xxiii, 17",
    "sg:city":"Santurtzi",
    "sg:orig_category":"Panader\u00cdas, Panader\u00cdas",
    "sg:phone":"+34 944 83 61 61",
    "sg:postcode":"48980",
    "sg:province":"Vizcaya",
    "wof:name":"Pastelerias Izarra S.l.",
    "wof:placetype":"venue"
},
  "geometry": {"coordinates":[-3.03470397,43.3312950134],"type":"Point"}
}