{
  "type": "Feature",
  "properties": {
    "addr:full":"Avda Calvo Sotelo, 75 Beniel Murcia 30130",
    "addr:housenumber":"75",
    "addr:postcode":"30130",
    "addr:street":"Avda Calvo Sotelo",
    "iso:country":"ES",
    "sg:address":"Avda Calvo Sotelo, 75",
    "sg:city":"Beniel",
    "sg:orig_category":"Supermercados Y Hipermercados",
    "sg:phone":"+34 968 60 03 52",
    "sg:postcode":"30130",
    "sg:province":"Murcia",
    "wof:name":"Garcia Sanchez Gloria",
    "wof:placetype":"venue"
},
  "geometry": {"coordinates":[-1.0063350201,38.0423622131],"type":"Point"}
}