{
  "type": "Feature",
  "properties": {
    "iso:country":"ES",
    "sg:address":"Calle de Pozo Nuevo, S/n",
    "sg:city":"Sanlucar De Barrameda",
    "sg:orig_category":"Panader\u00cdas, Panader\u00cdas",
    "sg:phone":"+34 956 36 16 80",
    "sg:postcode":"11540",
    "sg:province":"C\u00e1diz",
    "sg:website":"www.larondena.com",
    "wof:name":"Dulces La Ronde\u00f1a S.l.",
    "wof:placetype":"venue"
},
  "geometry": {"coordinates":[-6.34562397,36.7716636658],"type":"Point"}
}