{
  "type": "Feature",
  "properties": {
    "addr:full":"Calle de Crisanta (do\u00d1a), 2 Tomelloso Ciudad Real 13700",
    "addr:housenumber":"2",
    "addr:postcode":"13700",
    "addr:street":"Calle De Crisanta Don\u0303A",
    "iso:country":"ES",
    "sg:address":"Calle de Crisanta (do\u00d1a), 2",
    "sg:city":"Tomelloso",
    "sg:orig_category":"Farmacias",
    "sg:phone":"+34 926 51 12 39",
    "sg:postcode":"13700",
    "sg:province":"Ciudad Real",
    "wof:name":"Mi\u00f1ano Falcon Amparo",
    "wof:placetype":"venue"
},
  "geometry": {"coordinates":[-3.0208315849,39.1581459045],"type":"Point"}
}