{
  "type": "Feature",
  "properties": {
    "addr:full":"Calle de Zaida, 79 Madrid Madrid 28019",
    "addr:housenumber":"79",
    "addr:postcode":"madrid;28019",
    "addr:street":"Calle De Zaida",
    "iso:country":"ES",
    "sg:address":"Calle de Zaida, 79",
    "sg:city":"Madrid",
    "sg:orig_category":"Ropa Para Se\u00d1oras Y Caballeros (al Por Menor)",
    "sg:phone":"+34 914 71 95 85",
    "sg:postcode":"28019",
    "sg:province":"Madrid",
    "wof:name":"Exclusivas Danilo S.a.",
    "wof:placetype":"venue"
},
  "geometry": {"coordinates":[-3.7356750965,40.3927536011],"type":"Point"}
}