{
  "type": "Feature",
  "properties": {
    "iso:country":"ES",
    "sg:address":"Rua Subride, 25",
    "sg:city":"Fonte Escura",
    "sg:orig_category":"Supermercados Y Hipermercados",
    "sg:phone":"+34 986 37 44 44",
    "sg:postcode":"36215",
    "sg:province":"Pontevedra",
    "wof:name":"Distribuciones Froiz S.a.",
    "wof:placetype":"venue"
},
  "geometry": {"coordinates":[-8.663274765,42.2263412476],"type":"Point"}
}