{
  "type": "Feature",
  "properties": {
    "addr:full":"Calle de Velazquez, 18 Madrid Madrid 28001",
    "addr:housenumber":"18",
    "addr:postcode":"madrid;28001",
    "addr:street":"Calle De Velazquez",
    "iso:country":"ES",
    "sg:address":"Calle de Velazquez, 18",
    "sg:city":"Madrid",
    "sg:orig_category":"Asesor\u00cdas En Comunicaci\u00d3n",
    "sg:phone":"+34 914 35 55 86",
    "sg:postcode":"28001",
    "sg:province":"Madrid",
    "sg:website":"www.cic-mediorp.com",
    "wof:name":"Cic Imagen Y Comunicacion Corporativa S.a.",
    "wof:placetype":"venue"
},
  "geometry": {"coordinates":[-3.6840970516,40.4234237671],"type":"Point"}
}