{
  "type": "Feature",
  "properties": {
    "addr:full":"Calle de Rafael Maria De Labra, 15 Oviedo Asturias 33010",
    "addr:housenumber":"15",
    "addr:postcode":"33010",
    "addr:street":"Calle De Rafael Maria De Labra",
    "iso:country":"ES",
    "sg:address":"Calle de Rafael Maria De Labra, 15",
    "sg:city":"Oviedo",
    "sg:orig_category":"Cajas De Ahorro",
    "sg:phone":"+34 985 20 81 87",
    "sg:postcode":"33010",
    "sg:province":"Asturias",
    "sg:website":"www.cajastur.es",
    "wof:name":"Caja De Ahorros De Asturias",
    "wof:placetype":"venue"
},
  "geometry": {"coordinates":[-5.8370862007,43.3629302979],"type":"Point"}
}