{
  "type": "Feature",
  "properties": {
    "addr:full":"Calle de San Vicente, 62 Castellon Castell\u00f3n 12002",
    "addr:housenumber":"62",
    "addr:postcode":"12002",
    "addr:street":"Calle De San Vicente",
    "iso:country":"ES",
    "sg:address":"Calle de San Vicente, 62",
    "sg:city":"Castellon",
    "sg:orig_category":"M\u00c9dicos: Estomatolog\u00cda",
    "sg:phone":"+34 964 25 25 79",
    "sg:postcode":"12002",
    "sg:province":"Castell\u00f3n",
    "wof:name":"Andres Beltran Cristobal",
    "wof:placetype":"venue"
},
  "geometry": {"coordinates":[-0.0431142002,39.9858398438],"type":"Point"}
}