{
  "type": "Feature",
  "properties": {
    "iso:country":"ES",
    "sg:address":"Calle de Ramon Y Cajal, 70",
    "sg:city":"Beas",
    "sg:orig_category":"Molduras, Junquillos, Listones Y Molduras Perforadas",
    "sg:phone":"+34 959 30 84 52",
    "sg:postcode":"21630",
    "sg:province":"Huelva",
    "wof:name":"Diaz Romero Bartolome",
    "wof:placetype":"venue"
},
  "geometry": {"coordinates":[-6.7964191437,37.4240188599],"type":"Point"}
}