{
  "type": "Feature",
  "properties": {
    "iso:country":"ES",
    "sg:address":"Calle de Herreria, 15",
    "sg:city":"Calatorao",
    "sg:orig_category":"Cajas Para Embalar",
    "sg:phone":"+34 976 60 76 54",
    "sg:postcode":"50280",
    "sg:province":"Zaragoza",
    "wof:name":"Caja Rural De Aragon S.coop Credito",
    "wof:placetype":"venue"
},
  "geometry": {"coordinates":[-1.3467489481,41.5231895447],"type":"Point"}
}