{
  "type": "Feature",
  "properties": {
    "iso:country":"ES",
    "sg:address":"Avda Salis, 4",
    "sg:city":"Irun",
    "sg:orig_category":"Peluquer\u00cdas, Peluquer\u00cda Mixta",
    "sg:phone":"+34 943 62 16 49",
    "sg:postcode":"20304",
    "sg:province":"Guip\u00f9zcoa",
    "wof:name":"Peluqueria Hazen C.b",
    "wof:placetype":"venue"
},
  "geometry": {"coordinates":[-1.7879159451,43.3423042297],"type":"Point"}
}