{
  "type": "Feature",
  "properties": {
    "iso:country":"ES",
    "sg:address":"Calle de Escritor Carrillo Lasso, 4",
    "sg:city":"Cordoba",
    "sg:orig_category":"Plomeros",
    "sg:phone":"+34 957 43 99 43",
    "sg:postcode":"14007",
    "sg:province":"C\u00f3rdoba",
    "wof:name":"Moreno Prieto Francisco",
    "wof:placetype":"venue"
},
  "geometry": {"coordinates":[-4.7547869682,37.8951339722],"type":"Point"}
}