{
  "type": "Feature",
  "properties": {
    "iso:country":"ES",
    "sg:address":"Calle de Pachin De Melas, 32",
    "sg:city":"Gijon",
    "sg:orig_category":"Deportes Diversos",
    "sg:phone":"+34 985 32 70 18",
    "sg:postcode":"33212",
    "sg:province":"Asturias",
    "sg:website":"www.www",
    "wof:name":"Federacion Asturiana De Natacion",
    "wof:placetype":"venue"
},
  "geometry": {"coordinates":[-5.6913118362,43.5421829224],"type":"Point"}
}