{
  "type": "Feature",
  "properties": {
    "addr:full":"Avda Jorge Vigon, 9 Logro\u00f1o La Rioja 26003",
    "addr:housenumber":"9",
    "addr:postcode":"26003",
    "addr:street":"Avda Jorge Vigon;Rioja",
    "iso:country":"ES",
    "sg:address":"Avda Jorge Vigon, 9",
    "sg:city":"Logro\u00f1o",
    "sg:orig_category":"Importaci\u00d3n, Negocio De Caf\u00c9, Cacao",
    "sg:phone":"+34 941 24 83 77",
    "sg:postcode":"26003",
    "sg:province":"La Rioja",
    "wof:name":"La Casa Del Cafe S. A.",
    "wof:placetype":"venue"
},
  "geometry": {"coordinates":[-2.4437730312,42.4626426697],"type":"Point"}
}