{
  "type": "Feature",
  "properties": {
    "iso:country":"ES",
    "sg:address":"Rua Cruz Gallastegui, 3",
    "sg:city":"Pontevedra",
    "sg:orig_category":"Psic\u00d3logos",
    "sg:phone":"+34 986 85 34 73",
    "sg:postcode":"36001",
    "sg:province":"Pontevedra",
    "wof:name":"Rodrigo Dapena Maria",
    "wof:placetype":"venue"
},
  "geometry": {"coordinates":[-8.640912056,42.4294395447],"type":"Point"}
}