{
  "type": "Feature",
  "properties": {
    "addr:full":"Cra. Balaguer, S/n Menarguens Lleida 25139",
    "addr:housenumber":"s",
    "addr:postcode":"25139",
    "addr:street":"Cra. Balaguer;/ N Menarguens",
    "iso:country":"ES",
    "sg:address":"Cra. Balaguer, S/n",
    "sg:city":"Menarguens",
    "sg:orig_category":"Cooperativas Agr\u00cdcolas",
    "sg:phone":"+34 973 18 03 61",
    "sg:postcode":"25139",
    "sg:province":"Lleida",
    "wof:name":"Serviman S.c.p.",
    "wof:placetype":"venue"
},
  "geometry": {"coordinates":[0.7507770061,41.7378196716],"type":"Point"}
}