{
  "type": "Feature",
  "properties": {
    "iso:country":"ES",
    "sg:address":"Carr Santanyi, De, 57",
    "sg:city":"Campos",
    "sg:orig_category":"Zapatos (al Por Menor)",
    "sg:phone":"+34 971 65 27 97",
    "sg:postcode":"07630",
    "sg:province":"Islas Baleares",
    "wof:name":"Mas Llado Apolonia",
    "wof:placetype":"venue"
},
  "geometry": {"coordinates":[3.0197050571,39.430480957],"type":"Point"}
}