{
  "type": "Feature",
  "properties": {
    "addr:full":"Calle de Mayor, 46 Cangas Narcea Asturias 33800",
    "addr:housenumber":"46",
    "addr:postcode":"33800",
    "addr:street":"Calle De Mayor",
    "iso:country":"ES",
    "sg:address":"Calle de Mayor, 46",
    "sg:city":"Cangas Narcea",
    "sg:orig_category":"Ropa Para Se\u00d1oras Y Caballeros (al Por Menor)",
    "sg:phone":"+34 985 81 25 49",
    "sg:postcode":"33800",
    "sg:province":"Asturias",
    "wof:name":"Alvarez Blanco Blanca",
    "wof:placetype":"venue"
},
  "geometry": {"coordinates":[-6.5510892868,43.178478241],"type":"Point"}
}