{
  "type": "Feature",
  "properties": {
    "addr:full":"Calle de Valladolid, 9 Alacant Alicante 03015",
    "addr:housenumber":"9",
    "addr:postcode":"03015",
    "addr:street":"Calle De Valladolid",
    "iso:country":"ES",
    "sg:address":"Calle de Valladolid, 9",
    "sg:city":"Alacant",
    "sg:orig_category":"Cervecer\u00cdas",
    "sg:phone":"+34 965 24 16 61",
    "sg:postcode":"03015",
    "sg:province":"Alicante",
    "wof:name":"Parra Avellan Dolores Gracia",
    "wof:placetype":"venue"
},
  "geometry": {"coordinates":[-0.4743869901,38.3635292053],"type":"Point"}
}