{
  "type": "Feature",
  "properties": {
    "addr:full":"Carrer de Gremi De Fusters, 43 Poligon Industrial De Son Castello Islas Baleares 07...",
    "addr:housenumber":"43;07 ...",
    "addr:street":"Carrer De Gremi De Fusters;Islas Baleares",
    "iso:country":"ES",
    "sg:address":"Carrer de Gremi De Fusters, 43",
    "sg:city":"Poligon Industrial De Son Castello",
    "sg:orig_category":"Electrodom\u00c9sticos (al Por Menor)",
    "sg:phone":"+34 971 43 04 86",
    "sg:postcode":"07...",
    "sg:province":"Islas Baleares",
    "sg:website":"www.dielectrobalear.com",
    "wof:name":"Dielectro Balear S.a.",
    "wof:placetype":"venue"
},
  "geometry": {"coordinates":[2.9117100239,39.6136398315],"type":"Point"}
}