{
  "type": "Feature",
  "properties": {
    "addr:full":"Carrer de Mare Deu Pilar (casc Antic), 7 Barcelona Barcelona 08003",
    "addr:housenumber":"7",
    "addr:postcode":"08003",
    "addr:street":"Carrer De Mare;Antic",
    "iso:country":"ES",
    "sg:address":"Carrer de Mare Deu Pilar (casc Antic), 7",
    "sg:city":"Barcelona",
    "sg:orig_category":"Peluquer\u00cdas, Peluquer\u00cda Mixta",
    "sg:phone":"+34 933 19 13 11",
    "sg:postcode":"08003",
    "sg:province":"Barcelona",
    "wof:name":"Godino Mota Maria",
    "wof:placetype":"venue"
},
  "geometry": {"coordinates":[2.1767239571,41.3869857788],"type":"Point"}
}