{
  "type": "Feature",
  "properties": {
    "iso:country":"ES",
    "sg:address":"Calle de Enmedio, 40",
    "sg:city":"Castellon",
    "sg:orig_category":"Confecci\u00d3n (fabricaci\u00d3n, Al Por Mayor)",
    "sg:phone":"+34 964 22 91 55",
    "sg:postcode":"12001",
    "sg:province":"Castell\u00f3n",
    "wof:name":"Oysho Espa\u00f1a S.a.",
    "wof:placetype":"venue"
},
  "geometry": {"coordinates":[-0.0388629995,39.9857177734],"type":"Point"}
}