{
  "type": "Feature",
  "properties": {
    "addr:full":"Calle de Sarrikobaso, 22 Algorta Vizcaya 48991",
    "addr:housenumber":"22",
    "addr:postcode":"48991",
    "addr:street":"Calle De Sarrikobaso",
    "iso:country":"ES",
    "sg:address":"Calle de Sarrikobaso, 22",
    "sg:city":"Algorta",
    "sg:orig_category":"Abogados",
    "sg:phone":"+34 944 30 43 29",
    "sg:postcode":"48991",
    "sg:province":"Vizcaya",
    "sg:website":"www.abokatuak.com",
    "wof:name":"Del Horno Santos Aitor",
    "wof:placetype":"venue"
},
  "geometry": {"coordinates":[-3.0093319416,43.3539962769],"type":"Point"}
}