{
  "type": "Feature",
  "properties": {
    "iso:country":"ES",
    "sg:address":"Calle de San Isidoro, 8",
    "sg:city":"Granada",
    "sg:orig_category":"Estancos",
    "sg:phone":"+34 958 29 14 89",
    "sg:postcode":"18003",
    "sg:province":"Granada",
    "wof:name":"Perez Espigares Octavio Luis",
    "wof:placetype":"venue"
},
  "geometry": {"coordinates":[-3.6108100414,37.1763000488],"type":"Point"}
}