{
  "type": "Feature",
  "properties": {
    "addr:full":"Carr Enrajolat, 33 Palamos Girona 17230",
    "addr:housenumber":"33",
    "addr:postcode":"17230",
    "addr:street":"Carr Enrajolat",
    "iso:country":"ES",
    "sg:address":"Carr Enrajolat, 33",
    "sg:city":"Palamos",
    "sg:orig_category":"Bazares, Art\u00cdculos De Limpieza Y De Cocina (al Por Menor)",
    "sg:phone":"+34 972 31 40 53",
    "sg:postcode":"17230",
    "sg:province":"Girona",
    "wof:name":"Maria Rosa Dalmau S.l.",
    "wof:placetype":"venue"
},
  "geometry": {"coordinates":[3.1279499531,41.8473548889],"type":"Point"}
}