{
  "type": "Feature",
  "properties": {
    "iso:country":"ES",
    "sg:address":"Calle de Juan De Padilla, 13",
    "sg:city":"Burgos",
    "sg:orig_category":"Cajas De Ahorro",
    "sg:phone":"+34 947 23 28 11",
    "sg:postcode":"09006",
    "sg:province":"Burgos",
    "sg:website":"www.cajacirculo.es",
    "wof:name":"Caja De Ahorros Del Circulo Catolico Obrero De Burgos",
    "wof:placetype":"venue"
},
  "geometry": {"coordinates":[-3.6849079132,42.3490524292],"type":"Point"}
}