{
  "type": "Feature",
  "properties": {
    "iso:country":"ES",
    "sg:address":"Estafeta, 71",
    "sg:city":"Iru\u00f1a",
    "sg:orig_category":"Caf\u00c9s, Bares, Cervecer\u00cdas",
    "sg:phone":"+34 948 22 83 53",
    "sg:postcode":"31001",
    "sg:province":"Navarra",
    "wof:name":"Argi-bici S.l.",
    "wof:placetype":"venue"
},
  "geometry": {"coordinates":[-1.6415318251,42.8165969849],"type":"Point"}
}