{
  "type": "Feature",
  "properties": {
    "iso:country":"ES",
    "sg:address":"Rua Fernando Iii O Santo (de), 39",
    "sg:city":"Santiago De Compostela",
    "sg:orig_category":"Librer\u00cdas",
    "sg:phone":"+34 981 59 98 60",
    "sg:postcode":"15701",
    "sg:province":"La Coru\u00f1a",
    "wof:name":"Lamas Iglesias Carlos Modesto",
    "wof:placetype":"venue"
},
  "geometry": {"coordinates":[-8.547545433,42.8705406189],"type":"Point"}
}