{
  "type": "Feature",
  "properties": {
    "iso:country":"ES",
    "sg:address":"Calle de Marina, 11",
    "sg:city":"Ronda",
    "sg:orig_category":"Edici\u00d3n De Diarios, Revistas, Boletines",
    "sg:phone":"+34 952 19 01 64",
    "sg:postcode":"29400",
    "sg:province":"M\u00e1laga",
    "wof:name":"Producciones Locales De Tv S.l.",
    "wof:placetype":"venue"
},
  "geometry": {"coordinates":[-5.1665468216,36.7435913086],"type":"Point"}
}