{
  "type": "Feature",
  "properties": {
    "iso:country":"ES",
    "sg:address":"Calle de Santo Domingo, 65",
    "sg:city":"Badajoz",
    "sg:orig_category":"Cl\u00cdnicas Dentales",
    "sg:phone":"+34 924 26 18 13",
    "sg:postcode":"06001",
    "sg:province":"Badajoz",
    "wof:name":"Holcer Tabalinsky Marcelo Alejandro",
    "wof:placetype":"venue"
},
  "geometry": {"coordinates":[-6.9747681618,38.8775177002],"type":"Point"}
}