{
  "type": "Feature",
  "properties": {
    "addr:full":"Calle de Simancas, 74 Palmas De Gran Canaria Las Palmas 35010",
    "addr:housenumber":"74",
    "addr:postcode":"35010",
    "addr:street":"Calle De Simancas",
    "iso:country":"ES",
    "sg:address":"Calle de Simancas, 74",
    "sg:city":"Palmas De Gran Canaria",
    "sg:orig_category":"Farmacias",
    "sg:phone":"+34 928 26 45 74",
    "sg:postcode":"35010",
    "sg:province":"Las Palmas",
    "wof:name":"Bitar Sayfan Maha",
    "wof:placetype":"venue"
},
  "geometry": {"coordinates":[-15.4437246323,28.1299514771],"type":"Point"}
}