{
  "type": "Feature",
  "properties": {
    "iso:country":"ES",
    "sg:address":"Plaz Sol (del), 2",
    "sg:city":"Vera",
    "sg:orig_category":"Cajas De Ahorro",
    "sg:phone":"+34 950 39 32 34",
    "sg:postcode":"04620",
    "sg:province":"Almer\u00eda",
    "wof:name":"Caja De Ahorros De Valencia Castellon Y Alicante",
    "wof:placetype":"venue"
},
  "geometry": {"coordinates":[-1.84869802,37.2382888794],"type":"Point"}
}