{
  "type": "Feature",
  "properties": {
    "addr:full":"Calle de Pozo Herrera, 1 Barrio La Herrera Le\u00f3n 24812",
    "addr:housenumber":"1",
    "addr:postcode":"24812",
    "addr:street":"Calle De Pozo Herrera;Barrio La Herrera Leo\u0301N",
    "iso:country":"ES",
    "sg:address":"Calle de Pozo Herrera, 1",
    "sg:city":"Barrio La Herrera",
    "sg:orig_category":"Panader\u00cdas, Panader\u00cdas",
    "sg:phone":"+34 987 70 30 04",
    "sg:postcode":"24812",
    "sg:province":"Le\u00f3n",
    "wof:name":"Pastelerias Esla C.b.",
    "wof:placetype":"venue"
},
  "geometry": {"coordinates":[-5.1618041992,42.8350753784],"type":"Point"}
}