{
  "type": "Feature",
  "properties": {
    "iso:country":"ES",
    "sg:address":"Carrer de Vinyals, 14",
    "sg:city":"Terrassa",
    "sg:orig_category":"Inform\u00c1tica, Ofim\u00c1tica (estudios, Asesor\u00cda, Ingenier\u00cda, Formaci\u00d3n)",
    "sg:phone":"+34 937 89 46 18",
    "sg:postcode":"08221",
    "sg:province":"Barcelona",
    "sg:website":"www.ds.datasystem.com",
    "wof:name":"Inforgest Informatica S.l.",
    "wof:placetype":"venue"
},
  "geometry": {"coordinates":[2.0080969334,41.5601234436],"type":"Point"}
}