{
  "type": "Feature",
  "properties": {
    "iso:country":"ES",
    "sg:address":"Avgd Dalias, De Las, 27",
    "sg:city":"Palmanyola",
    "sg:orig_category":"Laboratorios Y Trabajos De Fotograf\u00cda, V\u00cddeo Y Cine",
    "sg:phone":"+34 971 61 79 47",
    "sg:postcode":"07193",
    "sg:province":"Islas Baleares",
    "wof:name":"Mallorquina De Fotografia S.l.",
    "wof:placetype":"venue"
},
  "geometry": {"coordinates":[2.6715600491,39.6624183655],"type":"Point"}
}