{
  "type": "Feature",
  "properties": {
    "iso:country":"ES",
    "sg:address":"Av Principal, S/n",
    "sg:city":"Sentmenat",
    "sg:orig_category":"Charcuter\u00cdas (al Por Mayor)",
    "sg:phone":"+34 937 15 14 48",
    "sg:postcode":"08181",
    "sg:province":"Barcelona",
    "wof:name":"J. Bruy S. L.",
    "wof:placetype":"venue"
},
  "geometry": {"coordinates":[2.1387250423,41.6144294739],"type":"Point"}
}