{
  "type": "Feature",
  "properties": {
    "addr:full":"Barr La Trinidad, 23 Carreras Vizcaya 48540",
    "addr:housenumber":"23",
    "addr:postcode":"48540",
    "addr:street":"La Trinidad",
    "iso:country":"ES",
    "sg:address":"Barr La Trinidad, 23",
    "sg:city":"Carreras",
    "sg:orig_category":"Chapa Y Pintura Veh\u00cdculos",
    "sg:phone":"+34 946 36 83 27",
    "sg:postcode":"48540",
    "sg:province":"Vizcaya",
    "wof:name":"Citores San Pedro Pedro",
    "wof:placetype":"venue"
},
  "geometry": {"coordinates":[-3.1058120728,43.3131942749],"type":"Point"}
}