{
  "type": "Feature",
  "properties": {
    "iso:country":"ES",
    "sg:address":"Carrer de Fra Juniper Serra, 8",
    "sg:city":"Palma",
    "sg:orig_category":"Papeler\u00cdas, Librer\u00cdas",
    "sg:phone":"+34 971 28 23 73",
    "sg:postcode":"07014",
    "sg:province":"Islas Baleares",
    "wof:name":"Juan Canals Maria Pilar",
    "wof:placetype":"venue"
},
  "geometry": {"coordinates":[2.6295640469,39.5691108704],"type":"Point"}
}