{
  "type": "Feature",
  "properties": {
    "addr:full":"Carrer de Florida, 25 Barcelona Barcelona 08016",
    "addr:housenumber":"25",
    "addr:postcode":"08016",
    "addr:street":"Carrer De Florida",
    "iso:country":"ES",
    "sg:address":"Carrer de Florida, 25",
    "sg:city":"Barcelona",
    "sg:orig_category":"Reparaci\u00d3n Y Restauraci\u00d3n De Objetos Diversos",
    "sg:phone":"+34 933 54 02 17",
    "sg:postcode":"08016",
    "sg:province":"Barcelona",
    "wof:name":"Roman Gil Fernando",
    "wof:placetype":"venue"
},
  "geometry": {"coordinates":[2.1851320267,41.443649292],"type":"Point"}
}