{
  "type": "Feature",
  "properties": {
    "addr:full":"Calle de Pintor Lorenzo Casanova, 64 Alacant Alicante 03003",
    "addr:housenumber":"64",
    "addr:postcode":"03003",
    "addr:street":"Calle De Pintor Lorenzo Casanova",
    "iso:country":"ES",
    "sg:address":"Calle de Pintor Lorenzo Casanova, 64",
    "sg:city":"Alacant",
    "sg:orig_category":"Agencias Y Agentes Comerciales, Representantes",
    "sg:phone":"+34 965 92 47 41",
    "sg:postcode":"03003",
    "sg:province":"Alicante",
    "wof:name":"Promotora De Monovar S.l.",
    "wof:placetype":"venue"
},
  "geometry": {"coordinates":[-0.4932880104,38.3406410217],"type":"Point"}
}