{
  "type": "Feature",
  "properties": {
    "addr:full":"Rua Castelao, 25 Grove Pontevedra 36980",
    "addr:housenumber":"25",
    "addr:postcode":"36980",
    "addr:street":"Rua Castelao;Grove Pontevedra",
    "iso:country":"ES",
    "sg:address":"Rua Castelao, 25",
    "sg:city":"Grove",
    "sg:orig_category":"Ropa Para Ni\u00d1os (al Por Menor)",
    "sg:phone":"+34 986 73 28 01",
    "sg:postcode":"36980",
    "sg:province":"Pontevedra",
    "wof:name":"Maria Lina Escalante S.l.",
    "wof:placetype":"venue"
},
  "geometry": {"coordinates":[-8.8604784012,42.4922332764],"type":"Point"}
}