{
  "type": "Feature",
  "properties": {
    "iso:country":"ES",
    "sg:address":"Av Gava, 21",
    "sg:city":"Viladecans",
    "sg:orig_category":"Comercio De Piezas De Recambio Y De Accesorios De Veh\u00cdculos, Veh\u00cdculos Industriales",
    "sg:phone":"+34 936 58 28 30",
    "sg:postcode":"08840",
    "sg:province":"Barcelona",
    "wof:name":"Bermudez Torre\u00f1o Miguel",
    "wof:placetype":"venue"
},
  "geometry": {"coordinates":[2.0162189007,41.3126487732],"type":"Point"}
}