{
  "type": "Feature",
  "properties": {
    "addr:full":"Ing Pablo Esteban, 13 Pizarra M\u00e1laga 29560",
    "addr:housenumber":"13",
    "addr:postcode":"29560",
    "addr:street":"Ing Pablo Esteban",
    "iso:country":"ES",
    "sg:address":"Ing Pablo Esteban, 13",
    "sg:city":"Pizarra",
    "sg:orig_category":"Talleres De Corte Y Confecci\u00d3n",
    "sg:phone":"+34 952 48 31 90",
    "sg:postcode":"29560",
    "sg:province":"M\u00e1laga",
    "wof:name":"Confecciones Textiles Maro S.l.",
    "wof:placetype":"venue"
},
  "geometry": {"coordinates":[-4.707526207,36.7672538757],"type":"Point"}
}