{
  "type": "Feature",
  "properties": {
    "iso:country":"ES",
    "sg:address":"Avda Prensa (la), 81",
    "sg:city":"Sevilla",
    "sg:orig_category":"Autob\u00das (explotaci\u00d3n Y Servicios De)",
    "sg:phone":"+34 954 51 47 77",
    "sg:postcode":"41007",
    "sg:province":"Sevilla",
    "sg:website":"www.linesur.com",
    "wof:name":"R Diaz S.a.",
    "wof:placetype":"venue"
},
  "geometry": {"coordinates":[-5.956264019,37.3898506165],"type":"Point"}
}