{
  "type": "Feature",
  "properties": {
    "iso:country":"ES",
    "sg:address":"Carrer de Riu Llobregat, 56",
    "sg:city":"Prat Llobregat",
    "sg:orig_category":"Florister\u00cdas",
    "sg:phone":"+34 934 78 67 40",
    "sg:postcode":"08820",
    "sg:province":"Barcelona",
    "wof:name":"Gonzalez Serrato Francisco",
    "wof:placetype":"venue"
},
  "geometry": {"coordinates":[2.0855610371,41.3168296814],"type":"Point"}
}