{
  "type": "Feature",
  "properties": {
    "iso:country":"ES",
    "sg:address":"Calle de Santa Ana, 17",
    "sg:city":"Onil",
    "sg:orig_category":"Lavado, Limpieza De Veh\u00cdculos",
    "sg:phone":"+34 965 56 50 86",
    "sg:postcode":"03430",
    "sg:province":"Alicante",
    "wof:name":"Hermanos Arroyo S.l.",
    "wof:placetype":"venue"
},
  "geometry": {"coordinates":[-0.6663140059,38.6297302246],"type":"Point"}
}