{
  "type": "Feature",
  "properties": {
    "addr:full":"Calle de Carlos Iv, 6 Madrid Madrid 28037",
    "addr:housenumber":"6",
    "addr:postcode":"28037",
    "addr:street":"Calle De Carlos Iv",
    "iso:country":"ES",
    "sg:address":"Calle de Carlos Iv, 6",
    "sg:city":"Madrid",
    "sg:orig_category":"Sociedades, Compa\u00d1\u00cdas Aseguradoras",
    "sg:phone":"+34 913 88 04 92",
    "sg:postcode":"28037",
    "sg:province":"Madrid",
    "wof:name":"Eurovet S.l.",
    "wof:placetype":"venue"
},
  "geometry": {"coordinates":[-3.6181592941,40.4349441528],"type":"Point"}
}