{
  "type": "Feature",
  "properties": {
    "addr:full":"Miguel De Cervantes, 39 Zaragoza Zaragoza 50006",
    "addr:housenumber":"39",
    "addr:postcode":"50006",
    "addr:street":"Miguel;Cervantes",
    "iso:country":"ES",
    "sg:address":"Miguel De Cervantes, 39",
    "sg:city":"Zaragoza",
    "sg:orig_category":"Psic\u00d3logos",
    "sg:phone":"+34 976 22 97 28",
    "sg:postcode":"50006",
    "sg:province":"Zaragoza",
    "wof:name":"Cuadra Perez Jesus Luis",
    "wof:placetype":"venue"
},
  "geometry": {"coordinates":[-0.8893100023,41.6440849304],"type":"Point"}
}