{
  "type": "Feature",
  "properties": {
    "iso:country":"ES",
    "sg:address":"Calle de Cruz Y Castillo, 4",
    "sg:city":"Palencia",
    "sg:orig_category":"Estancos",
    "sg:phone":"+34 979 73 04 58",
    "sg:postcode":"34004",
    "sg:province":"Palencia",
    "wof:name":"Perez Gutierrez Mary Luz",
    "wof:placetype":"venue"
},
  "geometry": {"coordinates":[-4.5225868225,41.9981193542],"type":"Point"}
}