{
  "type": "Feature",
  "properties": {
    "addr:full":"Calle de Katuarri, S/n Ansoain Navarra 31013",
    "addr:housenumber":"s",
    "addr:postcode":"31013",
    "addr:street":"Calle De Katuarri;/ N Ansoain Navarra",
    "iso:country":"ES",
    "sg:address":"Calle de Katuarri, S/n",
    "sg:city":"Ansoain",
    "sg:orig_category":"Limpieza Industrial",
    "sg:phone":"+34 948 12 44 77",
    "sg:postcode":"31013",
    "sg:province":"Navarra",
    "wof:name":"Compains Torrea Gregorio",
    "wof:placetype":"venue"
},
  "geometry": {"coordinates":[-1.6457489729,42.832988739],"type":"Point"}
}