{
  "type": "Feature",
  "properties": {
    "iso:country":"ES",
    "sg:address":"Calle de Fray Luis Urbano, 27",
    "sg:city":"Zaragoza",
    "sg:orig_category":"Fabricaci\u00d3n De Distribuidores Autom\u00c1ticos",
    "sg:phone":"+34 976 49 83 41",
    "sg:postcode":"50002",
    "sg:province":"Zaragoza",
    "wof:name":"Miguel Mort S.l.",
    "wof:placetype":"venue"
},
  "geometry": {"coordinates":[-0.858479023,41.648979187],"type":"Point"}
}