{
  "type": "Feature",
  "properties": {
    "addr:full":"Pol. Indust., 6 Bargas Toledo 45593",
    "addr:housenumber":"6",
    "addr:postcode":"45593",
    "addr:street":"Pol. Indust.",
    "iso:country":"ES",
    "sg:address":"Pol. Indust., 6",
    "sg:city":"Bargas",
    "sg:orig_category":"Cajas Y Embalajes De Cart\u00d3n Y Papel",
    "sg:phone":"+34 925 39 50 73",
    "sg:postcode":"45593",
    "sg:province":"Toledo",
    "wof:name":"Mail Servicios Toledo S.l.",
    "wof:placetype":"venue"
},
  "geometry": {"coordinates":[-4.0194129944,39.9406776428],"type":"Point"}
}