{
  "type": "Feature",
  "properties": {
    "addr:full":"Calle de Pretil De Santisteban, 1 Madrid Madrid 28005",
    "addr:housenumber":"1",
    "addr:postcode":"28005",
    "addr:street":"Calle De Pretil;Santisteban",
    "iso:country":"ES",
    "sg:address":"Calle de Pretil De Santisteban, 1",
    "sg:city":"Madrid",
    "sg:orig_category":"Psic\u00d3logos",
    "sg:phone":"+34 913 66 62 05",
    "sg:postcode":"28005",
    "sg:province":"Madrid",
    "wof:name":"Alonso Ortiz Pilar",
    "wof:placetype":"venue"
},
  "geometry": {"coordinates":[-3.7101414204,40.4129905701],"type":"Point"}
}