{
  "type": "Feature",
  "properties": {
    "addr:full":"Carr Doctor Casals, 79 Santa Cristina D'aro Girona 17246",
    "addr:housenumber":"79",
    "addr:postcode":"17246",
    "addr:street":"Carr Doctor Casals",
    "iso:country":"ES",
    "sg:address":"Carr Doctor Casals, 79",
    "sg:city":"Santa Cristina D'aro",
    "sg:orig_category":"Bisuter\u00cda, Joyer\u00cda, Relojer\u00cda (al Por Menor)",
    "sg:phone":"+34 972 83 78 96",
    "sg:postcode":"17246",
    "sg:province":"Girona",
    "wof:name":"Tesler Schuarzberg Laura",
    "wof:placetype":"venue"
},
  "geometry": {"coordinates":[2.8163490295,41.9701499939],"type":"Point"}
}