{
  "type": "Feature",
  "properties": {
    "iso:country":"ES",
    "sg:address":"Calle de San Agustin, 3",
    "sg:city":"Chiclana De La Frontera",
    "sg:orig_category":"Ense\u00d1anza: Profesiones Art\u00cdsticas",
    "sg:phone":"+34 956 53 52 21",
    "sg:postcode":"11130",
    "sg:province":"C\u00e1diz",
    "wof:name":"Leal Aragon Pedro",
    "wof:placetype":"venue"
},
  "geometry": {"coordinates":[-6.1470088959,36.4222488403],"type":"Point"}
}