{
  "type": "Feature",
  "properties": {
    "iso:country":"ES",
    "sg:address":"Fco Bergamin, 2",
    "sg:city":"Iru\u00f1a",
    "sg:orig_category":"Complementos De Vestir (al Por Menor)",
    "sg:phone":"+34 948 22 57 54",
    "sg:postcode":"31002",
    "sg:province":"Navarra",
    "wof:name":"San Martin Pla Mari Carmen",
    "wof:placetype":"venue"
},
  "geometry": {"coordinates":[-1.6425759792,42.8134918213],"type":"Point"}
}