{
  "type": "Feature",
  "properties": {
    "iso:country":"ES",
    "sg:address":"Avda Matapi\u00d1onera, 2",
    "sg:city":"San Sebastian De Los Reyes",
    "sg:orig_category":"Electromedicina: Equipo",
    "sg:phone":"+34 916 53 81 98",
    "sg:postcode":"28700",
    "sg:province":"Madrid",
    "wof:name":"Viasys Healthcare Spain S.a.u.",
    "wof:placetype":"venue"
},
  "geometry": {"coordinates":[-3.6199541092,40.5485076904],"type":"Point"}
}