{
  "type": "Feature",
  "properties": {
    "iso:country":"ES",
    "sg:address":"Calle de Juan Pages, 10",
    "sg:city":"Andratx",
    "sg:orig_category":"Electricidad: Instaladores",
    "sg:phone":"+34 971 13 66 58",
    "sg:postcode":"07150",
    "sg:province":"Islas Baleares",
    "wof:name":"Instalaciones Ponent C.b.",
    "wof:placetype":"venue"
},
  "geometry": {"coordinates":[2.4200589657,39.5733261108],"type":"Point"}
}