{
  "type": "Feature",
  "properties": {
    "iso:country":"ES",
    "sg:address":"Pase Maritimo, 69",
    "sg:city":"Torremolinos",
    "sg:orig_category":"Supermercados Y Hipermercados",
    "sg:phone":"+34 952 38 83 18",
    "sg:postcode":"29620",
    "sg:province":"M\u00e1laga",
    "wof:name":"Torres Gonzalez Jose",
    "wof:placetype":"venue"
},
  "geometry": {"coordinates":[-4.4870209694,36.6337203979],"type":"Point"}
}