{
  "type": "Feature",
  "properties": {
    "addr:full":"Calle de Cervantes, 16 Palacios Y Villafranca Sevilla 41720",
    "addr:housenumber":"16",
    "addr:postcode":"41720",
    "addr:street":"Calle De Cervantes",
    "iso:country":"ES",
    "sg:address":"Calle de Cervantes, 16",
    "sg:city":"Palacios Y Villafranca",
    "sg:orig_category":"Asociaciones Y Clubs Deportivos",
    "sg:phone":"+34 955 81 04 87",
    "sg:postcode":"41720",
    "sg:province":"Sevilla",
    "wof:name":"Garcia Jimenez Fausto",
    "wof:placetype":"venue"
},
  "geometry": {"coordinates":[-5.9270148277,37.1605415344],"type":"Point"}
}