{
  "type": "Feature",
  "properties": {
    "iso:country":"ES",
    "sg:address":"Errota Poligonoa, 3",
    "sg:city":"Anoeta",
    "sg:orig_category":"Construcciones Met\u00c1licas",
    "sg:phone":"+34 943 65 24 40",
    "sg:postcode":"20270",
    "sg:province":"Guip\u00f9zcoa",
    "wof:name":"Caldereria Y Construccion S. A.",
    "wof:placetype":"venue"
},
  "geometry": {"coordinates":[-2.069963932,43.1619186401],"type":"Point"}
}