{
  "type": "Feature",
  "properties": {
    "addr:full":"Calle de Valdes Salas, 4 Aviles Asturias 33402",
    "addr:housenumber":"4",
    "addr:postcode":"33402",
    "addr:street":"Calle De Valdes Salas",
    "iso:country":"ES",
    "sg:address":"Calle de Valdes Salas, 4",
    "sg:city":"Aviles",
    "sg:orig_category":"Cl\u00cdnicas Psiqui\u00c1tricas",
    "sg:phone":"+34 985 54 92 19",
    "sg:postcode":"33402",
    "sg:province":"Asturias",
    "wof:name":"Servicio De Salud Del Principado De Asturias",
    "wof:placetype":"venue"
},
  "geometry": {"coordinates":[-5.9232420921,43.5489082336],"type":"Point"}
}