{
  "type": "Feature",
  "properties": {
    "addr:full":"Av Herois De 1808 (dels), 9 Arbo\u00e7 Tarragona 43720",
    "addr:housenumber":"9",
    "addr:postcode":"43720",
    "addr:street":"Av Herois De 1808 Dels",
    "iso:country":"ES",
    "sg:address":"Av Herois De 1808 (dels), 9",
    "sg:city":"Arbo\u00e7",
    "sg:orig_category":"Electricidad: Instaladores",
    "sg:phone":"+34 977 67 11 28",
    "sg:postcode":"43720",
    "sg:province":"Tarragona",
    "wof:name":"Nodriments L'arbo\u00e7 S.l.",
    "wof:placetype":"venue"
},
  "geometry": {"coordinates":[1.6015809774,41.2644615173],"type":"Point"}
}