{
  "type": "Feature",
  "properties": {
    "addr:full":"Carrer de Arago, 95 Barcelona Barcelona 08015",
    "addr:housenumber":"95",
    "addr:postcode":"08015",
    "addr:street":"Carrer De Arago",
    "iso:country":"ES",
    "sg:address":"Carrer de Arago, 95",
    "sg:city":"Barcelona",
    "sg:orig_category":"Restaurantes",
    "sg:phone":"+34 932 26 06 67",
    "sg:postcode":"08015",
    "sg:province":"Barcelona",
    "wof:name":"Bejar S.l",
    "wof:placetype":"venue"
},
  "geometry": {"coordinates":[2.15122509,41.3820838928],"type":"Point"}
}