{
  "type": "Feature",
  "properties": {
    "addr:full":"Calle de Sol, 2 Villaviciosa Asturias 33300",
    "addr:housenumber":"2",
    "addr:postcode":"33300",
    "addr:street":"Calle De Sol",
    "iso:country":"ES",
    "sg:address":"Calle de Sol, 2",
    "sg:city":"Villaviciosa",
    "sg:orig_category":"Quincaller\u00cda (al Por Menor)",
    "sg:phone":"+34 985 89 01 33",
    "sg:postcode":"33300",
    "sg:province":"Asturias",
    "wof:name":"Prida Solares Jaime",
    "wof:placetype":"venue"
},
  "geometry": {"coordinates":[-5.4355421066,43.4797554016],"type":"Point"}
}