{
  "type": "Feature",
  "properties": {
    "iso:country":"ES",
    "sg:address":"Rua Evaristo Correa Calderon, 77",
    "sg:city":"Baralla",
    "sg:orig_category":"Molduras, Junquillos, Listones Y Molduras Perforadas",
    "sg:phone":"+34 982 36 36 97",
    "sg:postcode":"27680",
    "sg:province":"Lugo",
    "wof:name":"Martinez Pombo Manuel",
    "wof:placetype":"venue"
},
  "geometry": {"coordinates":[-7.2502379417,42.8938331604],"type":"Point"}
}