{
  "type": "Feature",
  "properties": {
    "iso:country":"ES",
    "sg:address":"Avda Vega (de La), 1",
    "sg:city":"Alcobendas",
    "sg:orig_category":"Centros Empresariales",
    "sg:phone":"+34 916 62 90 66",
    "sg:postcode":"28108",
    "sg:province":"Madrid",
    "wof:name":"Confivendis S.l.",
    "wof:placetype":"venue"
},
  "geometry": {"coordinates":[-3.6309390068,40.5346374512],"type":"Point"}
}