{
  "type": "Feature",
  "properties": {
    "iso:country":"ES",
    "sg:address":"Rua Via, 5",
    "sg:city":"Penis",
    "sg:orig_category":"Molduras, Junquillos, Listones Y Molduras Perforadas",
    "sg:phone":"+34 986 27 51 12",
    "sg:postcode":"36215",
    "sg:province":"Pontevedra",
    "wof:name":"Mari\u00f1o Novoa Ramon",
    "wof:placetype":"venue"
},
  "geometry": {"coordinates":[-8.663274765,42.2263412476],"type":"Point"}
}