{
  "type": "Feature",
  "properties": {
    "addr:full":"Calle de Canovas Del Castillo, 5 Algeciras C\u00e1diz 11201",
    "addr:housenumber":"5;ca\u0301diz",
    "addr:postcode":"11201",
    "addr:street":"Calle De Canovas Del Castillo",
    "iso:country":"ES",
    "sg:address":"Calle de Canovas Del Castillo, 5",
    "sg:city":"Algeciras",
    "sg:orig_category":"Arquitectos",
    "sg:phone":"+34 956 66 44 46",
    "sg:postcode":"11201",
    "sg:province":"C\u00e1diz",
    "sg:website":"www.gcervera.com",
    "wof:name":"Cervera Cottrell Gonzalo Pascual",
    "wof:placetype":"venue"
},
  "geometry": {"coordinates":[-5.4461188316,36.1301651001],"type":"Point"}
}