{
  "type": "Feature",
  "properties": {
    "addr:full":"Calle de Juan De La Cierva, 5 Manzanares Ciudad Real 13200",
    "addr:housenumber":"5",
    "addr:postcode":"13200",
    "addr:street":"Calle De Juan De La Cierva",
    "iso:country":"ES",
    "sg:address":"Calle de Juan De La Cierva, 5",
    "sg:city":"Manzanares",
    "sg:orig_category":"Reposter\u00cdas",
    "sg:phone":"+34 926 61 43 78",
    "sg:postcode":"13200",
    "sg:province":"Ciudad Real",
    "wof:name":"Paton Panaderia Bolleria S.l.",
    "wof:placetype":"venue"
},
  "geometry": {"coordinates":[-3.3662390709,38.9970817566],"type":"Point"}
}