{
  "type": "Feature",
  "properties": {
    "iso:country":"ES",
    "sg:address":"Calle de Seco, 3",
    "sg:city":"Madrid",
    "sg:orig_category":"Droguer\u00cdas (al Por Menor)",
    "sg:phone":"+34 915 52 61 00",
    "sg:postcode":"28007",
    "sg:province":"Madrid",
    "wof:name":"Aldao Gil Ricardo",
    "wof:placetype":"venue"
},
  "geometry": {"coordinates":[-3.6720221043,40.3989830017],"type":"Point"}
}