{
  "type": "Feature",
  "properties": {
    "iso:country":"ES",
    "sg:address":"Calle de Villegas Marmolejo, 7",
    "sg:city":"Sevilla",
    "sg:orig_category":"Ingeniero",
    "sg:phone":"+34 954 64 39 48",
    "sg:postcode":"41005",
    "sg:province":"Sevilla",
    "wof:name":"Pareja Marcano Luis Carlos",
    "wof:placetype":"venue"
},
  "geometry": {"coordinates":[-5.9692950249,37.3788032532],"type":"Point"}
}