{
  "type": "Feature",
  "properties": {
    "iso:country":"ES",
    "sg:address":"Calle de Andalucia, 78",
    "sg:city":"Espera",
    "sg:orig_category":"Partidos Pol\u00cdticos",
    "sg:phone":"+34 956 72 10 04",
    "sg:postcode":"11648",
    "sg:province":"C\u00e1diz",
    "wof:name":"Izquierda Unida Convocatoria Por Andalucia",
    "wof:placetype":"venue"
},
  "geometry": {"coordinates":[-5.8056898117,36.8736419678],"type":"Point"}
}