{
  "type": "Feature",
  "properties": {
    "addr:full":"Calle de Marcelo Usera, 91 Madrid Madrid 28026",
    "addr:housenumber":"91",
    "addr:postcode":"madrid;28026",
    "addr:street":"Calle De Marcelo Usera",
    "iso:country":"ES",
    "sg:address":"Calle de Marcelo Usera, 91",
    "sg:city":"Madrid",
    "sg:orig_category":"Caf\u00c9s, Bares, Cervecer\u00cdas",
    "sg:phone":"+34 914 75 74 40",
    "sg:postcode":"28026",
    "sg:province":"Madrid",
    "wof:name":"Anton Cristobal Angel",
    "wof:placetype":"venue"
},
  "geometry": {"coordinates":[-3.7068812847,40.3856315613],"type":"Point"}
}