{
  "type": "Feature",
  "properties": {
    "addr:full":"Calle de Cardenal Herrera Oria, 4 Almeria Almer\u00eda 04005",
    "addr:housenumber":"4",
    "addr:postcode":"04005",
    "addr:street":"Calle De Cardenal Herrera Oria",
    "iso:country":"ES",
    "sg:address":"Calle de Cardenal Herrera Oria, 4",
    "sg:city":"Almeria",
    "sg:orig_category":"M\u00c1quinas Textiles, Accesorios Y Suministros (fabricaci\u00d3n)",
    "sg:phone":"+34 950 26 76 50",
    "sg:postcode":"04005",
    "sg:province":"Almer\u00eda",
    "wof:name":"Segura Gonzalvez Angeles",
    "wof:placetype":"venue"
},
  "geometry": {"coordinates":[-2.4562449455,36.840927124],"type":"Point"}
}