{
  "type": "Feature",
  "properties": {
    "iso:country":"ES",
    "sg:address":"Carr Marti Torrents, 3",
    "sg:city":"Vilanova I La Geltru",
    "sg:orig_category":"Carburadores",
    "sg:phone":"+34 938 15 38 27",
    "sg:postcode":"08800",
    "sg:province":"Barcelona",
    "wof:name":"Fortuny Casals Santiago",
    "wof:placetype":"venue"
},
  "geometry": {"coordinates":[1.7350059748,41.2175712585],"type":"Point"}
}