{
  "type": "Feature",
  "properties": {
    "iso:country":"ES",
    "sg:address":"Calle de General Fresneda, 25",
    "sg:city":"Jodar",
    "sg:orig_category":"Farmacias",
    "sg:phone":"+34 953 78 50 34",
    "sg:postcode":"23500",
    "sg:province":"Ja\u00e9n",
    "wof:name":"Fernandez Valades Antonio",
    "wof:placetype":"venue"
},
  "geometry": {"coordinates":[-3.3543539047,37.8440971375],"type":"Point"}
}