{
  "type": "Feature",
  "properties": {
    "addr:full":"O Vilar De Calo, S/n Vilar De Calo A Coru\u00f1a 15895",
    "addr:housenumber":"s / n",
    "addr:postcode":"15895",
    "addr:street":"O Vilar De Calo;Corun\u0303A",
    "iso:country":"ES",
    "sg:address":"O Vilar De Calo, S/n",
    "sg:city":"Vilar De Calo",
    "sg:orig_category":"Alimentaci\u00d3n Animal (fabricaci\u00d3n, Al Por Mayor)",
    "sg:phone":"+34 981 53 00 34",
    "sg:postcode":"15895",
    "sg:province":"A Coru\u00f1a",
    "wof:name":"Souto Cela Jose",
    "wof:placetype":"venue"
},
  "geometry": {"coordinates":[-8.5794343948,42.8416137695],"type":"Point"}
}