{
  "type": "Feature",
  "properties": {
    "iso:country":"ES",
    "sg:address":"Calle de Condor, 44",
    "sg:city":"Villares",
    "sg:orig_category":"Agencias Y Agentes Comerciales, Representantes",
    "sg:phone":"+34 918 74 76 47",
    "sg:postcode":"28500",
    "sg:province":"Madrid",
    "wof:name":"Crisdaes, S.a",
    "wof:placetype":"venue"
},
  "geometry": {"coordinates":[-3.4524669647,40.3133049011],"type":"Point"}
}