{
  "type": "Feature",
  "properties": {
    "addr:full":"Cami Ral, 391 Mataro Barcelona 08301",
    "addr:housenumber":"391",
    "addr:postcode":"08301",
    "addr:street":"Ral",
    "iso:country":"ES",
    "sg:address":"Cami Ral, 391",
    "sg:city":"Mataro",
    "sg:orig_category":"Inmobiliaria (agencias)",
    "sg:phone":"+34 937 55 40 50",
    "sg:postcode":"08301",
    "sg:province":"Barcelona",
    "wof:name":"Consultoria Inmobiliaria Gesimar S.l.",
    "wof:placetype":"venue"
},
  "geometry": {"coordinates":[2.4442451,41.5369377136],"type":"Point"}
}