{
  "type": "Feature",
  "properties": {
    "iso:country":"ES",
    "sg:address":"Calle de Villarroya, 26",
    "sg:city":"Vilamarxant",
    "sg:orig_category":"Ropa Para Se\u00d1oras Y Caballeros (al Por Menor)",
    "sg:phone":"+34 962 71 03 81",
    "sg:postcode":"46191",
    "sg:province":"Valencia",
    "wof:name":"Faus Jorge Ricardo",
    "wof:placetype":"venue"
},
  "geometry": {"coordinates":[-0.6228259802,39.5692977905],"type":"Point"}
}