{
  "type": "Feature",
  "properties": {
    "iso:country":"ES",
    "sg:address":"Calle de Gardenia, 10",
    "sg:city":"Alcala Henares",
    "sg:orig_category":"Electricidad: Instaladores",
    "sg:phone":"+34 918 82 39 34",
    "sg:postcode":"28803",
    "sg:province":"Madrid",
    "wof:name":"Mebil S.l.",
    "wof:placetype":"venue"
},
  "geometry": {"coordinates":[-3.3742001057,40.4756965637],"type":"Point"}
}