{
  "type": "Feature",
  "properties": {
    "iso:country":"ES",
    "sg:address":"Carrer de Eudald Pedrola I Millan, 25",
    "sg:city":"Ampolla",
    "sg:orig_category":"Arquitectos",
    "sg:phone":"+34 977 46 02 70",
    "sg:postcode":"43895",
    "sg:province":"Tarragona",
    "wof:name":"Vidal Roses Maria Teresa",
    "wof:placetype":"venue"
},
  "geometry": {"coordinates":[0.7060639858,40.8103904724],"type":"Point"}
}