{
  "type": "Feature",
  "properties": {
    "iso:country":"ES",
    "sg:address":"Carrer de Mallorca, 307",
    "sg:city":"Barcelona",
    "sg:orig_category":"Aparcamientos (infraestructuras, Accesorios)",
    "sg:phone":"+34 934 57 88 45",
    "sg:postcode":"08037",
    "sg:province":"Barcelona",
    "wof:name":"Arimar Activa S.l.",
    "wof:placetype":"venue"
},
  "geometry": {"coordinates":[2.1667916775,41.3970565796],"type":"Point"}
}