{
  "type": "Feature",
  "properties": {
    "iso:country":"ES",
    "sg:address":"Calle de Talavera De La Reina, 4",
    "sg:city":"Toledo",
    "sg:orig_category":"Servicios Diversos",
    "sg:phone":"+34 925 22 32 15",
    "sg:postcode":"45004",
    "sg:province":"Toledo",
    "wof:name":"Valenzuela Doussinague Luis",
    "wof:placetype":"venue"
},
  "geometry": {"coordinates":[-4.0270962715,39.8642463684],"type":"Point"}
}