{
  "type": "Feature",
  "properties": {
    "addr:full":"Calle de Estacion, 9 Valladolid Valladolid 47004",
    "addr:housenumber":"9",
    "addr:postcode":"47004",
    "addr:street":"Calle De Estacion",
    "iso:country":"ES",
    "sg:address":"Calle de Estacion, 9",
    "sg:city":"Valladolid",
    "sg:orig_category":"Estancos",
    "sg:phone":"+34 983 30 74 73",
    "sg:postcode":"47004",
    "sg:province":"Valladolid",
    "wof:name":"Rabanal Calvo Margarita",
    "wof:placetype":"venue"
},
  "geometry": {"coordinates":[-4.7251272202,41.6442947388],"type":"Point"}
}