{
  "type": "Feature",
  "properties": {
    "iso:country":"ES",
    "sg:address":"Avda Espa\u00d1a, 66",
    "sg:city":"Cedeira",
    "sg:orig_category":"Empresarios",
    "sg:phone":"+34 981 48 02 73",
    "sg:postcode":"15350",
    "sg:province":"La Coru\u00f1a",
    "wof:name":"Perez Fernandez Victorino",
    "wof:placetype":"venue"
},
  "geometry": {"coordinates":[-8.0507287979,43.6596298218],"type":"Point"}
}