{
  "type": "Feature",
  "properties": {
    "iso:country":"ES",
    "sg:address":"Carrer de Iluro, 72",
    "sg:city":"Mataro",
    "sg:orig_category":"Fabricaci\u00d3n, Venta De Cuadros, Accesorios Para Enmarcar",
    "sg:phone":"+34 937 57 52 58",
    "sg:postcode":"08302",
    "sg:province":"Barcelona",
    "wof:name":"Pacheco Martin Francisco",
    "wof:placetype":"venue"
},
  "geometry": {"coordinates":[2.4402029514,41.5360488892],"type":"Point"}
}