{
  "type": "Feature",
  "properties": {
    "iso:country":"ES",
    "sg:address":"San Marcos, 9",
    "sg:city":"Sillobre",
    "sg:orig_category":"Alimentaci\u00d3n General (al Por Mayor)",
    "sg:phone":"+34 981 34 07 92",
    "sg:postcode":"15509",
    "sg:province":"La Coru\u00f1a",
    "wof:name":"Piensos San Marcos S.a.",
    "wof:placetype":"venue"
},
  "geometry": {"coordinates":[-8.1570587158,43.4528083801],"type":"Point"}
}