{
  "type": "Feature",
  "properties": {
    "addr:full":"Calle de Libreros, 14 Madrid Madrid 28004",
    "addr:housenumber":"14",
    "addr:postcode":"madrid;28004",
    "addr:street":"Calle De Libreros",
    "iso:country":"ES",
    "sg:address":"Calle de Libreros, 14",
    "sg:city":"Madrid",
    "sg:orig_category":"Librer\u00cdas",
    "sg:phone":"+34 915 22 23 98",
    "sg:postcode":"28004",
    "sg:province":"Madrid",
    "sg:website":"www.libreriasalamanca.com",
    "wof:name":"Moreno De Salinas-medinilla Fernando",
    "wof:placetype":"venue"
},
  "geometry": {"coordinates":[-3.7062959671,40.421787262],"type":"Point"}
}