{
  "type": "Feature",
  "properties": {
    "iso:country":"ES",
    "sg:address":"Calle de Santa Cruz De Marcenado, 30",
    "sg:city":"Madrid",
    "sg:orig_category":"Farmacias",
    "sg:phone":"+34 915 59 78 57",
    "sg:postcode":"28015",
    "sg:province":"Madrid",
    "wof:name":"Masi Cantos Marta",
    "wof:placetype":"venue"
},
  "geometry": {"coordinates":[-3.7133004665,40.4297218323],"type":"Point"}
}