{
  "type": "Feature",
  "properties": {
    "iso:country":"ES",
    "sg:address":"Carr Miramar, 3",
    "sg:city":"Platja D'aro",
    "sg:orig_category":"Molduras, Junquillos, Listones Y Molduras Perforadas",
    "sg:phone":"+34 972 81 61 88",
    "sg:postcode":"17250",
    "sg:province":"Girona",
    "wof:name":"Giner Cortes Eugeni",
    "wof:placetype":"venue"
},
  "geometry": {"coordinates":[3.0675120354,41.8155860901],"type":"Point"}
}