{
  "type": "Feature",
  "properties": {
    "addr:full":"Calle de Granados, 23 Torrejon Ardoz Madrid 28850",
    "addr:housenumber":"23",
    "addr:postcode":"28850",
    "addr:street":"Calle De Granados",
    "iso:country":"ES",
    "sg:address":"Calle de Granados, 23",
    "sg:city":"Torrejon Ardoz",
    "sg:orig_category":"Fabricaci\u00d3n De Bombas De Calor",
    "sg:phone":"+34 916 77 79 58",
    "sg:postcode":"28850",
    "sg:province":"Madrid",
    "wof:name":"Frio Industrial Torrejon S.l.",
    "wof:placetype":"venue"
},
  "geometry": {"coordinates":[-3.4781322479,40.4601211548],"type":"Point"}
}