{
  "type": "Feature",
  "properties": {
    "addr:full":"Calle de Bueso Pineda, 62 Madrid Madrid 28043",
    "addr:housenumber":"62",
    "addr:postcode":"madrid;28043",
    "addr:street":"Calle De Bueso Pineda",
    "iso:country":"ES",
    "sg:address":"Calle de Bueso Pineda, 62",
    "sg:city":"Madrid",
    "sg:orig_category":"Inform\u00c1tica (estudios, Servicios, Asesor\u00cda, Formaci\u00d3n)",
    "sg:phone":"+34 913 00 17 07",
    "sg:postcode":"28043",
    "sg:province":"Madrid",
    "wof:name":"Diasa Informatica S. A.",
    "wof:placetype":"venue"
},
  "geometry": {"coordinates":[-3.6519069672,40.4559249878],"type":"Point"}
}