{
  "type": "Feature",
  "properties": {
    "iso:country":"ES",
    "sg:address":"Residencial Atlantico, 9",
    "sg:city":"Longuera-toscal",
    "sg:orig_category":"Inmobiliaria (agencias)",
    "sg:phone":"+34 922 36 28 62",
    "sg:postcode":"38418",
    "sg:province":"Santa Cruz De Tenerife",
    "wof:name":"Inmobiliaria Bobi\u00f1o Canarias S.l.",
    "wof:placetype":"venue"
},
  "geometry": {"coordinates":[-16.5757541656,28.3986797333],"type":"Point"}
}