{
  "type": "Feature",
  "properties": {
    "addr:full":"Carrer de Sant Baldiri, 15 Lloret Mar Girona 17310",
    "addr:housenumber":"15",
    "addr:postcode":"17310",
    "addr:street":"Carrer De Sant Baldiri",
    "iso:country":"ES",
    "sg:address":"Carrer de Sant Baldiri, 15",
    "sg:city":"Lloret Mar",
    "sg:orig_category":"Bazares, Art\u00cdculos De Limpieza Y De Cocina (al Por Menor)",
    "sg:phone":"+34 972 37 33 36",
    "sg:postcode":"17310",
    "sg:province":"Girona",
    "wof:name":"Gimenez Estaba Maria Del Carmen",
    "wof:placetype":"venue"
},
  "geometry": {"coordinates":[2.846834898,41.6981697083],"type":"Point"}
}