{
  "type": "Feature",
  "properties": {
    "addr:full":"Doktor Huizi Kalea, 21 Andoain Guip\u00f9zcoa 20140",
    "addr:housenumber":"21",
    "addr:postcode":"20140",
    "addr:street":"Doktor Huizi Kalea;Guipu\u0300Zcoa",
    "iso:country":"ES",
    "sg:address":"Doktor Huizi Kalea, 21",
    "sg:city":"Andoain",
    "sg:orig_category":"Molduras, Junquillos, Listones Y Molduras Perforadas",
    "sg:phone":"+34 943 59 37 01",
    "sg:postcode":"20140",
    "sg:province":"Guip\u00f9zcoa",
    "wof:name":"Sistelcom-telemensaje S.a.",
    "wof:placetype":"venue"
},
  "geometry": {"coordinates":[-2.0240290165,43.2218360901],"type":"Point"}
}