{
  "type": "Feature",
  "properties": {
    "addr:full":"Calle de Modelo, 15 Hoyo De Pinares \u00c1vila 05250",
    "addr:housenumber":"15",
    "addr:postcode":"05250",
    "addr:street":"Calle De Modelo;A\u0301Vila",
    "iso:country":"ES",
    "sg:address":"Calle de Modelo, 15",
    "sg:city":"Hoyo De Pinares",
    "sg:orig_category":"Abogados",
    "sg:phone":"+34 918 63 82 51",
    "sg:postcode":"05250",
    "sg:province":"\u00c1vila",
    "wof:name":"Alberche Consultores S.l.",
    "wof:placetype":"venue"
},
  "geometry": {"coordinates":[-4.4240441322,40.5019378662],"type":"Point"}
}