{
  "type": "Feature",
  "properties": {
    "addr:full":"Avda Galicia De, 11 Oviedo Asturias 33005",
    "addr:housenumber":"11",
    "addr:postcode":"33005",
    "addr:street":"Avda Galicia De",
    "iso:country":"ES",
    "sg:address":"Avda Galicia De, 11",
    "sg:city":"Oviedo",
    "sg:orig_category":"Lencer\u00cda Femenina, Corseter\u00cda, Trajes De Ba\u00d1o (al Por Menor)",
    "sg:phone":"+34 985 27 05 26",
    "sg:postcode":"33005",
    "sg:province":"Asturias",
    "wof:name":"Fernandez Riestra Maria Del Pilar",
    "wof:placetype":"venue"
},
  "geometry": {"coordinates":[-5.8553619385,43.3610801697],"type":"Point"}
}