{
  "type": "Feature",
  "properties": {
    "iso:country":"ES",
    "sg:address":"Plaz Conde Cheste (del), 7",
    "sg:city":"Segovia",
    "sg:orig_category":"Abogados",
    "sg:phone":"+34 921 46 32 70",
    "sg:postcode":"40001",
    "sg:province":"Segovia",
    "wof:name":"Fraile Casado Cesar",
    "wof:placetype":"venue"
},
  "geometry": {"coordinates":[-4.1171951294,40.9495811462],"type":"Point"}
}