{
  "type": "Feature",
  "properties": {
    "addr:full":"Ptda El Regadiu, S/n Bocairent Valencia 46880",
    "addr:housenumber":"s / n",
    "addr:postcode":"46880",
    "addr:street":"Ptda El Regadiu",
    "iso:country":"ES",
    "sg:address":"Ptda El Regadiu, S/n",
    "sg:city":"Bocairent",
    "sg:orig_category":"Fabricaci\u00d3n De Ventanas",
    "sg:phone":"+34 962 35 50 00",
    "sg:postcode":"46880",
    "sg:province":"Valencia",
    "wof:name":"Hoco Ventanas S.a.",
    "wof:placetype":"venue"
},
  "geometry": {"coordinates":[-0.6146739721,38.7609786987],"type":"Point"}
}