{
  "type": "Feature",
  "properties": {
    "addr:full":"Calle de Marcelo Usera, 113 Madrid Madrid 28026",
    "addr:housenumber":"113",
    "addr:postcode":"28026",
    "addr:street":"Calle De Marcelo Usera",
    "iso:country":"ES",
    "sg:address":"Calle de Marcelo Usera, 113",
    "sg:city":"Madrid",
    "sg:orig_category":"Perfumer\u00cda (al Por Menor)",
    "sg:phone":"+34 914 76 81 01",
    "sg:postcode":"28026",
    "sg:province":"Madrid",
    "sg:website":"www.juteco.es",
    "wof:name":"Blanju S.l.",
    "wof:placetype":"venue"
},
  "geometry": {"coordinates":[-3.7086520195,40.3854293823],"type":"Point"}
}