{
  "type": "Feature",
  "properties": {
    "iso:country":"ES",
    "sg:address":"Ctra Alfonso Xiii, 22",
    "sg:city":"Melilla",
    "sg:orig_category":"Peluquer\u00cdas, Peluquer\u00cda Mixta",
    "sg:phone":"+34 952 67 17 72",
    "sg:postcode":"52005",
    "sg:province":"Melilla",
    "wof:name":"Bouamama Abdellah Fattouch",
    "wof:placetype":"venue"
},
  "geometry": {"coordinates":[-2.9533600807,35.2899169922],"type":"Point"}
}