{
  "type": "Feature",
  "properties": {
    "iso:country":"ES",
    "sg:address":"Carrer de Mallorca, 41",
    "sg:city":"Barcelona",
    "sg:orig_category":"Aeropuertos Y Servicios Aeroportuarios",
    "sg:phone":"+34 934 30 58 80",
    "sg:postcode":"08029",
    "sg:province":"Barcelona",
    "sg:website":"www.aeroflot.ru",
    "wof:name":"Aeroflot Lineas Aereas Rusas",
    "wof:placetype":"venue"
},
  "geometry": {"coordinates":[2.1483356953,41.3831558228],"type":"Point"}
}