{
  "type": "Feature",
  "properties": {
    "addr:full":"Avda Constantino Gancedo, 47 Villablino Le\u00f3n 24100",
    "addr:housenumber":"47",
    "addr:postcode":"24100",
    "addr:street":"Avda Constantino Gancedo",
    "iso:country":"ES",
    "sg:address":"Avda Constantino Gancedo, 47",
    "sg:city":"Villablino",
    "sg:orig_category":"Molduras, Junquillos, Listones Y Molduras Perforadas",
    "sg:phone":"+34 987 47 03 13",
    "sg:postcode":"24100",
    "sg:province":"Le\u00f3n",
    "wof:name":"Cortizo Rey Adoracion",
    "wof:placetype":"venue"
},
  "geometry": {"coordinates":[-6.3215789795,42.9371757507],"type":"Point"}
}