{
  "type": "Feature",
  "properties": {
    "iso:country":"ES",
    "sg:address":"Calle de Antonio Garrigues, 52",
    "sg:city":"Totana",
    "sg:orig_category":"Reposter\u00cdas",
    "sg:phone":"+34 968 42 13 04",
    "sg:postcode":"30850",
    "sg:province":"Murcia",
    "wof:name":"Martinez Martinez Maria",
    "wof:placetype":"venue"
},
  "geometry": {"coordinates":[-1.5003963709,37.7701759338],"type":"Point"}
}