{
  "type": "Feature",
  "properties": {
    "addr:full":"Ctra Valbuena, S/n Pesquera Duero Valladolid 47315",
    "addr:housenumber":"s",
    "addr:postcode":"47315",
    "addr:street":"Ctra Valbuena;/ N",
    "iso:country":"ES",
    "sg:address":"Ctra Valbuena, S/n",
    "sg:city":"Pesquera Duero",
    "sg:orig_category":"Centros De Educaci\u00d3n Especial",
    "sg:phone":"+34 983 87 00 94",
    "sg:postcode":"47315",
    "sg:province":"Valladolid",
    "wof:name":"Colegio Rural Agrupado La Villa",
    "wof:placetype":"venue"
},
  "geometry": {"coordinates":[-4.1554298401,41.6420936584],"type":"Point"}
}