{
  "type": "Feature",
  "properties": {
    "addr:full":"Galicia, 20 Ribeira-santa Uxia La Coru\u00f1a 15960",
    "addr:housenumber":"20",
    "addr:postcode":"15960",
    "addr:street":"Galicia;Uxia;Corun\u0303A",
    "iso:country":"ES",
    "sg:address":"Galicia, 20",
    "sg:city":"Ribeira-santa Uxia",
    "sg:orig_category":"Sociedades, Compa\u00d1\u00cdas Aseguradoras",
    "sg:phone":"+34 981 87 32 54",
    "sg:postcode":"15960",
    "sg:province":"La Coru\u00f1a",
    "wof:name":"Ocaso S.a. Compa\u00d1ia De Seguros Y Reaseguros",
    "wof:placetype":"venue"
},
  "geometry": {"coordinates":[-8.989982605,42.5537452698],"type":"Point"}
}