{
  "type": "Feature",
  "properties": {
    "iso:country":"ES",
    "sg:address":"Calle de Silicio, 9",
    "sg:city":"Torrejon Ardoz",
    "sg:orig_category":"Empresas De Limpieza",
    "sg:phone":"+34 916 75 51 66",
    "sg:postcode":"28850",
    "sg:province":"Madrid",
    "wof:name":"Padimay 95 S.l.",
    "wof:placetype":"venue"
},
  "geometry": {"coordinates":[-3.4640390873,40.4457397461],"type":"Point"}
}