{
  "type": "Feature",
  "properties": {
    "addr:full":"Carr Enric-claudi Girbal I Nadal, 20 Girona Girona 17003",
    "addr:housenumber":"20",
    "addr:postcode":"17003",
    "addr:street":"Carr Enric-Claudi;Nadal",
    "iso:country":"ES",
    "sg:address":"Carr Enric-claudi Girbal I Nadal, 20",
    "sg:city":"Girona",
    "sg:orig_category":"Transporte En General",
    "sg:phone":"+34 972 20 73 13",
    "sg:postcode":"17003",
    "sg:province":"Girona",
    "wof:name":"Grup Supeco Maxor S L",
    "wof:placetype":"venue"
},
  "geometry": {"coordinates":[2.8227140903,41.9723205566],"type":"Point"}
}