{
  "type": "Feature",
  "properties": {
    "addr:full":"Calle de Floridablanca, 15 Carmen Murcia 30002",
    "addr:housenumber":"15",
    "addr:postcode":"30002",
    "addr:street":"Calle De Floridablanca",
    "iso:country":"ES",
    "sg:address":"Calle de Floridablanca, 15",
    "sg:city":"Carmen",
    "sg:orig_category":"Zapatos (al Por Menor)",
    "sg:phone":"+34 968 35 01 43",
    "sg:postcode":"30002",
    "sg:province":"Murcia",
    "wof:name":"Rumbo S. A.",
    "wof:placetype":"venue"
},
  "geometry": {"coordinates":[-1.1311370134,37.9786338806],"type":"Point"}
}