{
  "type": "Feature",
  "properties": {
    "addr:full":"Avda Fernandez Murube, 10 Sevilla Sevilla 41007",
    "addr:housenumber":"10",
    "addr:postcode":"41007",
    "addr:street":"Avda Fernandez Murube",
    "iso:country":"ES",
    "sg:address":"Avda Fernandez Murube, 10",
    "sg:city":"Sevilla",
    "sg:orig_category":"Agentes, Concesionarios Y Sucursales De Veh\u00cdculos",
    "sg:phone":"+34 954 25 24 77",
    "sg:postcode":"41007",
    "sg:province":"Sevilla",
    "wof:name":"Fiol Roca S.a.",
    "wof:placetype":"venue"
},
  "geometry": {"coordinates":[-5.9439849854,37.3935813904],"type":"Point"}
}