{
  "type": "Feature",
  "properties": {
    "addr:full":"Calle de General Mola, 1 Badajoz Badajoz 06008",
    "addr:housenumber":"1",
    "addr:postcode":"06008",
    "addr:street":"Calle De General Mola",
    "iso:country":"ES",
    "sg:address":"Calle de General Mola, 1",
    "sg:city":"Badajoz",
    "sg:orig_category":"M\u00c9dicos: Estomatolog\u00cda",
    "sg:phone":"+34 924 22 42 36",
    "sg:postcode":"06008",
    "sg:province":"Badajoz",
    "wof:name":"Crespo Madera Gladys Evelyn",
    "wof:placetype":"venue"
},
  "geometry": {"coordinates":[-6.9430441856,38.8723373413],"type":"Point"}
}