{
  "type": "Feature",
  "properties": {
    "iso:country":"ES",
    "sg:address":"Avda Andres De Cerezo, 55",
    "sg:city":"Cerezo De Rio Tiron",
    "sg:orig_category":"Agencias Y Agentes Comerciales, Representantes",
    "sg:phone":"+34 947 58 30 89",
    "sg:postcode":"09270",
    "sg:province":"Burgos",
    "wof:name":"Gordo Marotta Esteban",
    "wof:placetype":"venue"
},
  "geometry": {"coordinates":[-3.1371591091,42.4920005798],"type":"Point"}
}