{
  "type": "Feature",
  "properties": {
    "iso:country":"ES",
    "sg:address":"Av Burgos, 21",
    "sg:city":"Mollet Valles",
    "sg:orig_category":"Inmobiliaria (agencias)",
    "sg:phone":"+34 935 70 41 61",
    "sg:postcode":"08100",
    "sg:province":"Barcelona",
    "wof:name":"Cesar Paz I Associats S.l.",
    "wof:placetype":"venue"
},
  "geometry": {"coordinates":[2.2103059292,41.5365104675],"type":"Point"}
}