{
  "type": "Feature",
  "properties": {
    "iso:country":"ES",
    "sg:address":"Carrer de Burriac, 63",
    "sg:city":"Mataro",
    "sg:orig_category":"Peluquer\u00cdas, Peluquer\u00cda Mixta",
    "sg:phone":"+34 937 58 88 81",
    "sg:postcode":"08303",
    "sg:province":"Barcelona",
    "wof:name":"Serrano Portillo Maria Dolores",
    "wof:placetype":"venue"
},
  "geometry": {"coordinates":[2.4218969345,41.5413246155],"type":"Point"}
}