{
  "type": "Feature",
  "properties": {
    "iso:country":"ES",
    "sg:address":"Calle de Mayor, 50",
    "sg:city":"Alginet",
    "sg:orig_category":"Farmacias",
    "sg:phone":"+34 961 75 35 94",
    "sg:postcode":"46230",
    "sg:province":"Valencia",
    "wof:name":"Farmacia Mi\u00f1ana Serrano C.b.",
    "wof:placetype":"venue"
},
  "geometry": {"coordinates":[-0.4708130062,39.2599716187],"type":"Point"}
}