{
  "type": "Feature",
  "properties": {
    "iso:country":"ES",
    "sg:address":"Avda Patrimonio De La Humanidad, 6",
    "sg:city":"Avila",
    "sg:orig_category":"Inmobiliaria (agencias)",
    "sg:phone":"+34 920 21 98 42",
    "sg:postcode":"05006",
    "sg:province":"\u00c1vila",
    "wof:name":"Comunidad De Propietarios Residencial Las Encinas",
    "wof:placetype":"venue"
},
  "geometry": {"coordinates":[-4.662583828,40.6696128845],"type":"Point"}
}