{
  "type": "Feature",
  "properties": {
    "iso:country":"ES",
    "sg:address":"Doctor Ba\u00d1ez Kalea, 12",
    "sg:city":"Arrasate",
    "sg:orig_category":"Reposter\u00cdas",
    "sg:phone":"+34 943 79 22 57",
    "sg:postcode":"20500",
    "sg:province":"Guip\u00f9zcoa",
    "wof:name":"Panaderia Bolintxo S. A.",
    "wof:placetype":"venue"
},
  "geometry": {"coordinates":[-2.4931468964,43.0618972778],"type":"Point"}
}