{
  "type": "Feature",
  "properties": {
    "addr:full":"Calle de Correos, 13 Portugalete Vizcaya 48920",
    "addr:housenumber":"13",
    "addr:postcode":"48920",
    "addr:street":"Calle De Correos",
    "iso:country":"ES",
    "sg:address":"Calle de Correos, 13",
    "sg:city":"Portugalete",
    "sg:orig_category":"Pescader\u00cdas (al Por Menor)",
    "sg:phone":"+34 944 96 29 76",
    "sg:postcode":"48920",
    "sg:province":"Vizcaya",
    "wof:name":"Hermosilla Del Campo Domingo",
    "wof:placetype":"venue"
},
  "geometry": {"coordinates":[-3.0202372074,43.3200569153],"type":"Point"}
}