{
  "type": "Feature",
  "properties": {
    "iso:country":"ES",
    "sg:address":"Carrer de Muntaner, 494",
    "sg:city":"Barcelona",
    "sg:orig_category":"Centros Empresariales",
    "sg:phone":"+34 932 12 04 06",
    "sg:postcode":"08022",
    "sg:province":"Barcelona",
    "wof:name":"R S P 51 Sa",
    "wof:placetype":"venue"
},
  "geometry": {"coordinates":[2.1375520229,41.4033432007],"type":"Point"}
}