{
  "type": "Feature",
  "properties": {
    "iso:country":"ES",
    "sg:address":"Plaz Doce Martires, 8",
    "sg:city":"Le\u00f3n",
    "sg:orig_category":"Electrodom\u00c9sticos (al Por Menor)",
    "sg:phone":"+34 987 20 54 78",
    "sg:postcode":"24004",
    "sg:province":"Le\u00f3n",
    "wof:name":"Fernandez Casta\u00f1eda Maria Ester",
    "wof:placetype":"venue"
},
  "geometry": {"coordinates":[-5.5731801987,42.5913963318],"type":"Point"}
}