{
  "type": "Feature",
  "properties": {
    "addr:full":"Avda Corazon De Jesus, 125 Vall D'uixo Castell\u00f3n 12600",
    "addr:housenumber":"125",
    "addr:postcode":"12600",
    "addr:street":"Avda Corazon De Jesus",
    "iso:country":"ES",
    "sg:address":"Avda Corazon De Jesus, 125",
    "sg:city":"Vall D'uixo",
    "sg:orig_category":"Arqueolog\u00cda Y Patrimonio Cultural",
    "sg:phone":"+34 964 66 35 83",
    "sg:postcode":"12600",
    "sg:province":"Castell\u00f3n",
    "wof:name":"Arqueolegs C.b.",
    "wof:placetype":"venue"
},
  "geometry": {"coordinates":[-0.2230509073,39.8228416443],"type":"Point"}
}