{
  "type": "Feature",
  "properties": {
    "iso:country":"ES",
    "sg:address":"Avda Buenos Aires, 5",
    "sg:city":"Lalin",
    "sg:orig_category":"Bancos",
    "sg:phone":"+34 986 78 04 75",
    "sg:postcode":"36500",
    "sg:province":"Pontevedra",
    "sg:website":"www.gruposantander.es",
    "wof:name":"Bt Espa\u00d1a Compa\u00d1ia De Servicios Globales De Telecomunicaciones S.a.u.",
    "wof:placetype":"venue"
},
  "geometry": {"coordinates":[-8.1121387482,42.6544914246],"type":"Point"}
}