{
  "type": "Feature",
  "properties": {
    "iso:country":"ES",
    "sg:address":"Cno. Del Salobral, Km. 0001,5",
    "sg:city":"Bola\u00f1os Calatrava",
    "sg:orig_category":"Centros Comerciales Y Grandes Tiendas",
    "sg:phone":"+34 926 69 31 44",
    "sg:postcode":"13260",
    "sg:province":"Ciudad Real",
    "wof:name":"El Sabito Productos Agricolas S.l.",
    "wof:placetype":"venue"
},
  "geometry": {"coordinates":[-3.6656041145,38.9035949707],"type":"Point"}
}