{
  "type": "Feature",
  "properties": {
    "addr:full":"Av. Onze De Setembre, 271 Prat Llobregat Barcelona 08820",
    "addr:housenumber":"271",
    "addr:postcode":"08820",
    "addr:street":"Av. Onze De Setembre;Llobregat",
    "iso:country":"ES",
    "sg:address":"Av. Onze De Setembre, 271",
    "sg:city":"Prat Llobregat",
    "sg:orig_category":"Droguer\u00cdas (al Por Menor)",
    "sg:phone":"+34 933 70 50 67",
    "sg:postcode":"08820",
    "sg:province":"Barcelona",
    "sg:website":"www.schlecker.com",
    "wof:name":"Schlecker S.a.",
    "wof:placetype":"venue"
},
  "geometry": {"coordinates":[2.1045920849,41.3227806091],"type":"Point"}
}