{
  "type": "Feature",
  "properties": {
    "iso:country":"ES",
    "sg:address":"Ctra. Cantiveros, 3",
    "sg:city":"Bernuy-zapardiel",
    "sg:orig_category":"Promotores Constructores",
    "sg:phone":"+34 920 32 42 61",
    "sg:postcode":"05212",
    "sg:province":"\u00c1vila",
    "wof:name":"Alvarez Fernandez Enrique",
    "wof:placetype":"venue"
},
  "geometry": {"coordinates":[-4.9452462196,40.9739532471],"type":"Point"}
}