{
  "type": "Feature",
  "properties": {
    "addr:full":"La Caridad, 2 Tacoronte Santa Cruz De Tenerife 38350",
    "addr:housenumber":"2",
    "addr:postcode":"38350",
    "addr:street":"La Caridad",
    "iso:country":"ES",
    "sg:address":"La Caridad, 2",
    "sg:city":"Tacoronte",
    "sg:orig_category":"Flores Y Plantas Naturales (al Por Mayor)",
    "sg:phone":"+34 922 56 35 55",
    "sg:postcode":"38350",
    "sg:province":"Santa Cruz De Tenerife",
    "sg:website":"www.saboflor.com",
    "wof:name":"Saboflor S. A.",
    "wof:placetype":"venue"
},
  "geometry": {"coordinates":[-16.4174289703,28.4756546021],"type":"Point"}
}