{
  "type": "Feature",
  "properties": {
    "addr:full":"Avda Andalucia (de), 32 Montilla C\u00f3rdoba 14550",
    "addr:housenumber":"32",
    "addr:postcode":"14550",
    "addr:street":"Avda Andalucia De;Co\u0301Rdoba",
    "iso:country":"ES",
    "sg:address":"Avda Andalucia (de), 32",
    "sg:city":"Montilla",
    "sg:orig_category":"Fabricaci\u00d3n De Juegos Y Juguetes",
    "sg:phone":"+34 957 65 65 91",
    "sg:postcode":"14550",
    "sg:province":"C\u00f3rdoba",
    "wof:name":"Comercial Lucena S.l.",
    "wof:placetype":"venue"
},
  "geometry": {"coordinates":[-4.6439971924,37.5824394226],"type":"Point"}
}