{
  "type": "Feature",
  "properties": {
    "addr:full":"Calle de Mozart, 32 Pto. Rosario Las Palmas 35600",
    "addr:housenumber":"32",
    "addr:postcode":"35600",
    "addr:street":"Calle De Mozart;Pto. Rosario Las",
    "iso:country":"ES",
    "sg:address":"Calle de Mozart, 32",
    "sg:city":"Pto. Rosario",
    "sg:orig_category":"Abogados",
    "sg:phone":"+34 928 85 83 73",
    "sg:postcode":"35600",
    "sg:province":"Las Palmas",
    "wof:name":"Lopez Bautista Gonzalo",
    "wof:placetype":"venue"
},
  "geometry": {"coordinates":[-13.8770217896,28.5070152283],"type":"Point"}
}