{
  "type": "Feature",
  "properties": {
    "iso:country":"ES",
    "sg:address":"Calle de San Antonio, 27",
    "sg:city":"Dolores",
    "sg:orig_category":"Cristaler\u00cdas",
    "sg:phone":"+34 965 72 62 80",
    "sg:postcode":"03150",
    "sg:province":"Alicante",
    "wof:name":"Ca\u00f1izares Clemente Salvador",
    "wof:placetype":"venue"
},
  "geometry": {"coordinates":[-0.7666199803,38.1394615173],"type":"Point"}
}