{
  "type": "Feature",
  "properties": {
    "addr:full":"Calle de Menendez Valdes, 3 Gijon Asturias 33201",
    "addr:housenumber":"3",
    "addr:postcode":"33201",
    "addr:street":"Calle De Menendez Valdes",
    "iso:country":"ES",
    "sg:address":"Calle de Menendez Valdes, 3",
    "sg:city":"Gijon",
    "sg:orig_category":"Cl\u00cdnicas Dentales",
    "sg:phone":"+34 985 34 20 69",
    "sg:postcode":"33201",
    "sg:province":"Asturias",
    "wof:name":"Poblete Merino Gonzalo Andres",
    "wof:placetype":"venue"
},
  "geometry": {"coordinates":[-5.6608028412,43.5410919189],"type":"Point"}
}