{
  "type": "Feature",
  "properties": {
    "addr:full":"Ctra. Nal. 340, Km. 0200,6 Alberic Valencia 46260",
    "addr:postcode":"46260",
    "addr:street":"Ctra. Nal. 340 Km. 0200,6",
    "iso:country":"ES",
    "sg:address":"Ctra. Nal. 340, Km. 0200,6",
    "sg:city":"Alberic",
    "sg:orig_category":"Fabricaci\u00d3n De Muebles",
    "sg:phone":"+34 962 44 31 96",
    "sg:postcode":"46260",
    "sg:province":"Valencia",
    "sg:website":"www.mavilop.es",
    "wof:name":"Mavilop S.l.",
    "wof:placetype":"venue"
},
  "geometry": {"coordinates":[-0.520138979,39.11901474],"type":"Point"}
}