{
  "type": "Feature",
  "properties": {
    "addr:full":"Avda Aeroporto, 98 Vigo Pontevedra 36206",
    "addr:housenumber":"98",
    "addr:postcode":"36206",
    "addr:street":"Avda Aeroporto",
    "iso:country":"ES",
    "sg:address":"Avda Aeroporto, 98",
    "sg:city":"Vigo",
    "sg:orig_category":"Alimentaci\u00d3n General (al Por Menor)",
    "sg:phone":"+34 986 27 45 62",
    "sg:postcode":"36206",
    "sg:province":"Pontevedra",
    "wof:name":"Veloso Busto Carmen",
    "wof:placetype":"venue"
},
  "geometry": {"coordinates":[-8.6952781677,42.2343101501],"type":"Point"}
}