{
  "type": "Feature",
  "properties": {
    "addr:full":"Calle de Rio Fresnedoso, 41 Poligono Sta M. De Benquerencia Toledo 45007",
    "addr:housenumber":"41 poligono",
    "addr:postcode":"45007",
    "addr:street":"Calle De Rio Fresnedoso;Sta M. De Benquerencia",
    "iso:country":"ES",
    "sg:address":"Calle de Rio Fresnedoso, 41",
    "sg:city":"Poligono Sta M. De Benquerencia",
    "sg:orig_category":"Int\u00c9rpretes",
    "sg:phone":"+34 925 23 14 09",
    "sg:postcode":"45007",
    "sg:province":"Toledo",
    "sg:website":"www.babeliatraducciones.com",
    "wof:name":"Babelia Traducciones C.b.",
    "wof:placetype":"venue"
},
  "geometry": {"coordinates":[-3.94520998,39.8632125854],"type":"Point"}
}