{
  "type": "Feature",
  "properties": {
    "iso:country":"ES",
    "sg:address":"Ctra Barcelona, 644",
    "sg:city":"Sabadell",
    "sg:orig_category":"Persianas Interiores, Exteriores",
    "sg:phone":"+34 937 12 25 87",
    "sg:postcode":"08204",
    "sg:province":"Barcelona",
    "wof:name":"Moreno Gama Pedro",
    "wof:placetype":"venue"
},
  "geometry": {"coordinates":[2.1165380478,41.5315666199],"type":"Point"}
}