{
  "type": "Feature",
  "properties": {
    "iso:country":"ES",
    "sg:address":"Los Barrios, S/n",
    "sg:city":"Pto Real",
    "sg:orig_category":"Centros Comerciales Y Grandes Tiendas",
    "sg:phone":"+34 956 47 37 36",
    "sg:postcode":"11510",
    "sg:province":"C\u00e1diz",
    "wof:name":"Pinturas La Gioconda S.l.",
    "wof:placetype":"venue"
},
  "geometry": {"coordinates":[-6.1849589348,36.5267295837],"type":"Point"}
}