{
  "type": "Feature",
  "properties": {
    "iso:country":"ES",
    "sg:address":"Urb Benahadux, Km. 0340,0",
    "sg:city":"Benahadux",
    "sg:orig_category":"Art\u00cdculos De Decoraci\u00d3n (fabricaci\u00d3n Y Al Por Mayor)",
    "sg:phone":"+34 950 31 01 29",
    "sg:postcode":"04410",
    "sg:province":"Almer\u00eda",
    "wof:name":"Antonio Martinez Vergel E Hijos S.l.",
    "wof:placetype":"venue"
},
  "geometry": {"coordinates":[-2.4703056812,36.9177742004],"type":"Point"}
}