{
  "type": "Feature",
  "properties": {
    "addr:full":"Carrer de Jacint Verdaguer, 10 Reus Tarragona 43202",
    "addr:housenumber":"10",
    "addr:postcode":"43202",
    "addr:street":"Carrer De Jacint Verdaguer",
    "iso:country":"ES",
    "sg:address":"Carrer de Jacint Verdaguer, 10",
    "sg:city":"Reus",
    "sg:orig_category":"Talleres El\u00c9ctricos Para Veh\u00cdculos",
    "sg:phone":"+34 977 31 33 10",
    "sg:postcode":"43202",
    "sg:province":"Tarragona",
    "wof:name":"Auto Taller Vicar S.l.",
    "wof:placetype":"venue"
},
  "geometry": {"coordinates":[1.0988730192,41.1577110291],"type":"Point"}
}