{
  "type": "Feature",
  "properties": {
    "iso:country":"ES",
    "sg:address":"Calle de Caverina, 35",
    "sg:city":"Calasparra",
    "sg:orig_category":"Agencias Y Agentes Comerciales, Representantes",
    "sg:phone":"+34 968 74 53 81",
    "sg:postcode":"30420",
    "sg:province":"Murcia",
    "wof:name":"Vidal Martinez Jose",
    "wof:placetype":"venue"
},
  "geometry": {"coordinates":[-1.7033749819,38.2326774597],"type":"Point"}
}