{
  "type": "Feature",
  "properties": {
    "iso:country":"ES",
    "sg:address":"Calle de Veracruz, 16",
    "sg:city":"Galapagar",
    "sg:orig_category":"Lencer\u00cda Femenina, Corseter\u00cda, Trajes De Ba\u00d1o (al Por Menor)",
    "sg:phone":"+34 918 58 28 10",
    "sg:postcode":"28260",
    "sg:province":"Madrid",
    "wof:name":"Sanchez Solana Francisca",
    "wof:placetype":"venue"
},
  "geometry": {"coordinates":[-4.0026531219,40.5748405457],"type":"Point"}
}