{
  "type": "Feature",
  "properties": {
    "addr:full":"Ctra Terrassa, 126 Rubi Barcelona 08191",
    "addr:housenumber":"126",
    "addr:postcode":"08191",
    "addr:street":"Ctra Terrassa",
    "iso:country":"ES",
    "sg:address":"Ctra Terrassa, 126",
    "sg:city":"Rubi",
    "sg:orig_category":"Lavado, Limpieza De Veh\u00cdculos",
    "sg:phone":"+34 936 97 87 82",
    "sg:postcode":"08191",
    "sg:province":"Barcelona",
    "wof:name":"Omedics S.l.",
    "wof:placetype":"venue"
},
  "geometry": {"coordinates":[2.034817934,41.5037574768],"type":"Point"}
}