{
  "type": "Feature",
  "properties": {
    "addr:full":"Calle de Pio Xii, 23 Oropesa Castell\u00f3n 12594",
    "addr:housenumber":"23",
    "addr:postcode":"12594",
    "addr:street":"Calle De Pio Xii",
    "iso:country":"ES",
    "sg:address":"Calle de Pio Xii, 23",
    "sg:city":"Oropesa",
    "sg:orig_category":"Ropa Para Se\u00d1oras Y Caballeros (al Por Menor)",
    "sg:phone":"+34 964 31 35 01",
    "sg:postcode":"12594",
    "sg:province":"Castell\u00f3n",
    "wof:name":"Fernandez Caballero Petra",
    "wof:placetype":"venue"
},
  "geometry": {"coordinates":[0.1382060051,40.0921134949],"type":"Point"}
}