{
  "type": "Feature",
  "properties": {
    "iso:country":"ES",
    "sg:address":"Cra Granada, 3",
    "sg:city":"Berja",
    "sg:orig_category":"Procuradores",
    "sg:phone":"+34 950 49 02 59",
    "sg:postcode":"04760",
    "sg:province":"Almer\u00eda",
    "wof:name":"Alcoba Enriquez Jose",
    "wof:placetype":"venue"
},
  "geometry": {"coordinates":[-2.9575607777,36.80991745],"type":"Point"}
}