{
  "type": "Feature",
  "properties": {
    "addr:full":"Calle de Emilio Vargas, 17 Madrid Madrid 28043",
    "addr:housenumber":"17",
    "addr:postcode":"madrid;28043",
    "addr:street":"Calle De Emilio Vargas",
    "iso:country":"ES",
    "sg:address":"Calle de Emilio Vargas, 17",
    "sg:city":"Madrid",
    "sg:orig_category":"Inform\u00c1tica Equipo Y Programas (al Por Mayor)",
    "sg:phone":"+34 914 15 00 52",
    "sg:postcode":"28043",
    "sg:province":"Madrid",
    "wof:name":"Sleeve Import S.l.",
    "wof:placetype":"venue"
},
  "geometry": {"coordinates":[-3.6521189213,40.4490394592],"type":"Point"}
}