{
  "type": "Feature",
  "properties": {
    "iso:country":"ES",
    "sg:address":"Calle de Panama, 3",
    "sg:city":"Coru\u00d1a",
    "sg:orig_category":"Estancos",
    "sg:phone":"+34 981 27 22 15",
    "sg:postcode":"15010",
    "sg:province":"La Coru\u00f1a",
    "wof:name":"Iglesias Gonzalez Luisa",
    "wof:placetype":"venue"
},
  "geometry": {"coordinates":[-8.4205226898,43.3595237732],"type":"Point"}
}