{
  "type": "Feature",
  "properties": {
    "iso:country":"ES",
    "sg:address":"Carrer de Petrarca, 13",
    "sg:city":"Sabadell",
    "sg:orig_category":"Mec\u00c1nico Del Autom\u00d3vil",
    "sg:phone":"+34 937 16 56 48",
    "sg:postcode":"08206",
    "sg:province":"Barcelona",
    "wof:name":"Fernandez Iba\u00f1ez Jose",
    "wof:placetype":"venue"
},
  "geometry": {"coordinates":[2.086728096,41.5556793213],"type":"Point"}
}