{
  "type": "Feature",
  "properties": {
    "iso:country":"ES",
    "sg:address":"Cami Pla De Son Llarg, 10",
    "sg:city":"Port D'andratx",
    "sg:orig_category":"Inmobiliaria (agencias)",
    "sg:phone":"+34 971 67 49 02",
    "sg:postcode":"07157",
    "sg:province":"Islas Baleares",
    "wof:name":"Villa Fortuna Investments S.l.",
    "wof:placetype":"venue"
},
  "geometry": {"coordinates":[2.3879649639,39.5518455505],"type":"Point"}
}