{
  "type": "Feature",
  "properties": {
    "addr:full":"Calle de Thiviers, 1 Javea Alicante 03730",
    "addr:housenumber":"1",
    "addr:postcode":"03730",
    "addr:street":"Calle De Thiviers",
    "iso:country":"ES",
    "sg:address":"Calle de Thiviers, 1",
    "sg:city":"Javea",
    "sg:orig_category":"Alquiler De Veh\u00cdculos: Turismos Y Utilitarios",
    "sg:phone":"+34 965 79 00 10",
    "sg:postcode":"03730",
    "sg:province":"Alicante",
    "sg:website":"www.rentanewcar.com",
    "wof:name":"Black & White Cars S.l.",
    "wof:placetype":"venue"
},
  "geometry": {"coordinates":[0.1680250019,38.7913818359],"type":"Point"}
}