{
  "type": "Feature",
  "properties": {
    "iso:country":"ES",
    "sg:address":"Calle de Alferez Garcia Mateo, 1",
    "sg:city":"Villarrasa",
    "sg:orig_category":"Equitaci\u00d3n: Guarnicioner\u00cda, Equipo (al Por Menor)",
    "sg:phone":"+34 959 41 92 70",
    "sg:postcode":"21850",
    "sg:province":"Huelva",
    "wof:name":"Rodriguez Teba Fernando",
    "wof:placetype":"venue"
},
  "geometry": {"coordinates":[-6.6026678085,37.3880958557],"type":"Point"}
}