{
  "type": "Feature",
  "properties": {
    "addr:full":"Avda Asturias Regimiento Almansa, S/n Le\u00f3n Le\u00f3n 24008",
    "addr:housenumber":"s",
    "addr:postcode":"24008",
    "addr:street":"Avda Asturias Regimiento Almansa;/ N Leo\u0301N Leo\u0301N",
    "iso:country":"ES",
    "sg:address":"Avda Asturias Regimiento Almansa, S/n",
    "sg:city":"Le\u00f3n",
    "sg:orig_category":"Hospitales",
    "sg:phone":"+34 987 22 53 67",
    "sg:postcode":"24008",
    "sg:province":"Le\u00f3n",
    "wof:name":"Longinos Y Gloria S.l.",
    "wof:placetype":"venue"
},
  "geometry": {"coordinates":[-5.5774812698,42.6160774231],"type":"Point"}
}