{
  "type": "Feature",
  "properties": {
    "iso:country":"ES",
    "sg:address":"Sepes Poligono, S/n",
    "sg:city":"Huesca",
    "sg:orig_category":"Empresas De Carpinter\u00cda",
    "sg:phone":"+34 974 22 11 51",
    "sg:postcode":"22099",
    "sg:province":"Huesca",
    "wof:name":"Talleres Usieto S. A.",
    "wof:placetype":"venue"
},
  "geometry": {"coordinates":[-0.4083139896,42.1365661621],"type":"Point"}
}