{
  "type": "Feature",
  "properties": {
    "iso:country":"ES",
    "sg:address":"Calle de Tinte, 8",
    "sg:city":"Alcala Henares",
    "sg:orig_category":"Ropa Para Se\u00d1oras (al Por Menor)",
    "sg:phone":"+34 918 81 57 57",
    "sg:postcode":"28801",
    "sg:province":"Madrid",
    "wof:name":"Flores Olaya Maria Dolores",
    "wof:placetype":"venue"
},
  "geometry": {"coordinates":[-3.3643829823,40.4844284058],"type":"Point"}
}