{
  "type": "Feature",
  "properties": {
    "addr:full":"Calle de Jazmin, 9 Madrid Madrid 28033",
    "addr:housenumber":"9",
    "addr:postcode":"madrid;28033",
    "addr:street":"Calle De Jazmin",
    "iso:country":"ES",
    "sg:address":"Calle de Jazmin, 9",
    "sg:city":"Madrid",
    "sg:orig_category":"Peluquer\u00cdas, Peluquer\u00cda Mixta",
    "sg:phone":"+34 917 66 90 23",
    "sg:postcode":"28033",
    "sg:province":"Madrid",
    "wof:name":"Alberto Martinez De Aguilaz Calvo Y Otro Cdad",
    "wof:placetype":"venue"
},
  "geometry": {"coordinates":[-3.6666936874,40.4790496826],"type":"Point"}
}