{
  "type": "Feature",
  "properties": {
    "addr:full":"Calle de Egido, 46 Villanueva Cordoba C\u00f3rdoba 14440",
    "addr:housenumber":"46;cordoba co\u0301rdoba",
    "addr:postcode":"14440",
    "addr:street":"Calle De Egido",
    "iso:country":"ES",
    "sg:address":"Calle de Egido, 46",
    "sg:city":"Villanueva Cordoba",
    "sg:orig_category":"Contenedores (mercanc\u00cdas)",
    "sg:phone":"+34 957 12 17 69",
    "sg:postcode":"14440",
    "sg:province":"C\u00f3rdoba",
    "wof:name":"Cano Rubio Antonio",
    "wof:placetype":"venue"
},
  "geometry": {"coordinates":[-4.6307601929,38.3260002136],"type":"Point"}
}