{
  "type": "Feature",
  "properties": {
    "iso:country":"ES",
    "sg:address":"Calle de Carril De Cuenca, 6",
    "sg:city":"Adra",
    "sg:orig_category":"Agentes Generales De Seguros",
    "sg:phone":"+34 950 40 17 90",
    "sg:postcode":"04770",
    "sg:province":"Almer\u00eda",
    "wof:name":"Roldan Escobar Antonio",
    "wof:placetype":"venue"
},
  "geometry": {"coordinates":[-3.0181384087,36.7478599548],"type":"Point"}
}