{
  "type": "Feature",
  "properties": {
    "iso:country":"ES",
    "sg:address":"Calle de Mendoza, 8",
    "sg:city":"Ceuta",
    "sg:orig_category":"Comercio, Reparaci\u00d3n De Bicicletas, De Motocicletas, De Accesorios",
    "sg:phone":"+34 956 51 80 97",
    "sg:postcode":"51001",
    "sg:province":"Ceuta",
    "wof:name":"Bicicarrasco S.l.",
    "wof:placetype":"venue"
},
  "geometry": {"coordinates":[-5.3054938316,35.8890342712],"type":"Point"}
}