{
  "type": "Feature",
  "properties": {
    "addr:full":"Calle de Alcala, 339 Madrid Madrid 28027",
    "addr:housenumber":"339",
    "addr:postcode":"28027",
    "addr:street":"Calle De Alcala",
    "iso:country":"ES",
    "sg:address":"Calle de Alcala, 339",
    "sg:city":"Madrid",
    "sg:orig_category":"Ense\u00d1anza, Formaci\u00d3n Profesional: Aprendizaje",
    "sg:phone":"+34 914 08 73 11",
    "sg:postcode":"28027",
    "sg:province":"Madrid",
    "wof:name":"Colegio Teide S. A.",
    "wof:placetype":"venue"
},
  "geometry": {"coordinates":[-3.6479380131,40.433216095],"type":"Point"}
}