{
  "type": "Feature",
  "properties": {
    "addr:full":"Av Generalitat (de La), 57 Tortosa Tarragona 43500",
    "addr:housenumber":"57",
    "addr:postcode":"43500",
    "addr:street":"Av Generalitat De La",
    "iso:country":"ES",
    "sg:address":"Av Generalitat (de La), 57",
    "sg:city":"Tortosa",
    "sg:orig_category":"Fabricaci\u00d3n De Sobres, Bolsas Y Fundas",
    "sg:phone":"+34 977 44 30 83",
    "sg:postcode":"43500",
    "sg:province":"Tarragona",
    "wof:name":"Cugat Costa Trinidad",
    "wof:placetype":"venue"
},
  "geometry": {"coordinates":[0.5201209784,40.8104324341],"type":"Point"}
}