{
  "type": "Feature",
  "properties": {
    "iso:country":"ES",
    "sg:address":"Calle de San Roque, 10",
    "sg:city":"Estepona",
    "sg:orig_category":"Promotores Constructores",
    "sg:phone":"+34 952 80 87 43",
    "sg:postcode":"29680",
    "sg:province":"M\u00e1laga",
    "wof:name":"Vi\u00d1a Mendez S.l.",
    "wof:placetype":"venue"
},
  "geometry": {"coordinates":[-5.1489901543,36.4224891663],"type":"Point"}
}