{
  "type": "Feature",
  "properties": {
    "addr:full":"Ctra Pozoantiguo, Km. 0001,4 Toro Zamora 49800",
    "addr:postcode":"49800",
    "addr:street":"Ctra Pozoantiguo Km. 0001,4",
    "iso:country":"ES",
    "sg:address":"Ctra Pozoantiguo, Km. 0001,4",
    "sg:city":"Toro",
    "sg:orig_category":"Promotores Constructores",
    "sg:phone":"+34 980 69 29 92",
    "sg:postcode":"49800",
    "sg:province":"Zamora",
    "wof:name":"Edar Toro Ute",
    "wof:placetype":"venue"
},
  "geometry": {"coordinates":[-5.3985891342,41.5275497437],"type":"Point"}
}