{
  "type": "Feature",
  "properties": {
    "iso:country":"ES",
    "sg:address":"Ctra. B-motril, Km. 0297,0",
    "sg:city":"Bailen",
    "sg:orig_category":"Cer\u00c1mica Art\u00cdstica Y Decorativa",
    "sg:phone":"+34 953 67 34 88",
    "sg:postcode":"23710",
    "sg:province":"Ja\u00e9n",
    "wof:name":"Durillo Andres Antonio",
    "wof:placetype":"venue"
},
  "geometry": {"coordinates":[-3.7710540295,38.0965309143],"type":"Point"}
}