{
  "type": "Feature",
  "properties": {
    "addr:full":"Avda Republica Argentina, 15 Castalla Alicante 03420",
    "addr:housenumber":"15",
    "addr:postcode":"03420",
    "addr:street":"Avda Republica Argentina",
    "iso:country":"ES",
    "sg:address":"Avda Republica Argentina, 15",
    "sg:city":"Castalla",
    "sg:orig_category":"Supermercados Y Hipermercados",
    "sg:phone":"+34 965 56 02 61",
    "sg:postcode":"03420",
    "sg:province":"Alicante",
    "wof:name":"Fuster Torregrosa Francisco Javier",
    "wof:placetype":"venue"
},
  "geometry": {"coordinates":[-0.6711530089,38.5940055847],"type":"Point"}
}