{
  "type": "Feature",
  "properties": {
    "addr:full":"Carrer de Esglesia, 79 Castelldefels Barcelona 08860",
    "addr:housenumber":"79",
    "addr:postcode":"08860",
    "addr:street":"Carrer De Esglesia",
    "iso:country":"ES",
    "sg:address":"Carrer de Esglesia, 79",
    "sg:city":"Castelldefels",
    "sg:orig_category":"Art\u00cdculos De Regalo (al Por Menor)",
    "sg:phone":"+34 936 65 85 88",
    "sg:postcode":"08860",
    "sg:province":"Barcelona",
    "wof:name":"Chen  Jianwei",
    "wof:placetype":"venue"
},
  "geometry": {"coordinates":[1.9824969769,41.2851219177],"type":"Point"}
}