{
  "type": "Feature",
  "properties": {
    "addr:full":"Cami Fondo, 13 Burriana Castell\u00f3n 12530",
    "addr:housenumber":"13",
    "addr:postcode":"12530",
    "addr:street":"Fondo",
    "iso:country":"ES",
    "sg:address":"Cami Fondo, 13",
    "sg:city":"Burriana",
    "sg:orig_category":"Panader\u00cdas, Panader\u00cdas",
    "sg:phone":"+34 964 51 42 92",
    "sg:postcode":"12530",
    "sg:province":"Castell\u00f3n",
    "wof:name":"Tardul S.l.",
    "wof:placetype":"venue"
},
  "geometry": {"coordinates":[-0.0802489966,39.8801307678],"type":"Point"}
}