{
  "type": "Feature",
  "properties": {
    "iso:country":"ES",
    "sg:address":"Calle de Beneficencia, 3",
    "sg:city":"Logro\u00f1o",
    "sg:orig_category":"Muebles Y Accesorios Para Cocinas Y Cuartos De Ba\u00d1o (al Por Menor)",
    "sg:phone":"+34 941 22 78 70",
    "sg:postcode":"26005",
    "sg:province":"La Rioja",
    "wof:name":"Mendoza Ca\u00f1as Marcos",
    "wof:placetype":"venue"
},
  "geometry": {"coordinates":[-2.4617869854,42.463760376],"type":"Point"}
}