{
  "type": "Feature",
  "properties": {
    "iso:country":"ES",
    "sg:address":"Calle de Federico Sanchez Bedoya, 7",
    "sg:city":"Sevilla",
    "sg:orig_category":"Notarios",
    "sg:phone":"+34 954 21 91 16",
    "sg:postcode":"41001",
    "sg:province":"Sevilla",
    "wof:name":"Sanchez-osorio Sanchez Juan",
    "wof:placetype":"venue"
},
  "geometry": {"coordinates":[-5.9948310852,37.3859863281],"type":"Point"}
}