{
  "type": "Feature",
  "properties": {
    "iso:country":"ES",
    "sg:address":"Calle de Gonzalez De La Vega, 4",
    "sg:city":"Ceuta",
    "sg:orig_category":"Abogados",
    "sg:phone":"+34 956 51 24 42",
    "sg:postcode":"51001",
    "sg:province":"Ceuta",
    "wof:name":"Becerra Pe\u00f1afiel Emilio",
    "wof:placetype":"venue"
},
  "geometry": {"coordinates":[-5.3095011711,35.8870429993],"type":"Point"}
}