{
  "type": "Feature",
  "properties": {
    "iso:country":"ES",
    "sg:address":"Plaz Arturo Piera, 2",
    "sg:city":"Valencia",
    "sg:orig_category":"Electricidad Veh\u00cdculo",
    "sg:phone":"+34 963 84 99 95",
    "sg:postcode":"46018",
    "sg:province":"Valencia",
    "wof:name":"Alberotecnic,s.l.u.",
    "wof:placetype":"venue"
},
  "geometry": {"coordinates":[-0.3945826888,39.4700965881],"type":"Point"}
}