{
  "type": "Feature",
  "properties": {
    "iso:country":"ES",
    "sg:address":"Calle de Cte Alorda Bujosa, 8",
    "sg:city":"Palma",
    "sg:orig_category":"Empresas De Carpinter\u00cda De Madera",
    "sg:phone":"+34 971 75 17 19",
    "sg:postcode":"07004",
    "sg:province":"Islas Baleares",
    "wof:name":"Llull Marti Antonio",
    "wof:placetype":"venue"
},
  "geometry": {"coordinates":[2.6611232758,39.5878982544],"type":"Point"}
}