{
  "type": "Feature",
  "properties": {
    "addr:full":"Carrer de Industria, S/n Papiol Barcelona 08754",
    "addr:housenumber":"/ n",
    "addr:postcode":"08754",
    "addr:street":"Carrer De Industria S",
    "iso:country":"ES",
    "sg:address":"Carrer de Industria, S/n",
    "sg:city":"Papiol",
    "sg:orig_category":"Cerrajer\u00cda, Ferrallista",
    "sg:phone":"+34 936 73 05 97",
    "sg:postcode":"08754",
    "sg:province":"Barcelona",
    "wof:name":"Jose Peraire S. A.",
    "wof:placetype":"venue"
},
  "geometry": {"coordinates":[2.0108549595,41.4297981262],"type":"Point"}
}