{
  "type": "Feature",
  "properties": {
    "iso:country":"ES",
    "sg:address":"Calle de Real, S/n",
    "sg:city":"Rabanal Del Camino",
    "sg:orig_category":"Albergues",
    "sg:phone":"+34 987 69 12 74",
    "sg:postcode":"24722",
    "sg:province":"Le\u00f3n",
    "wof:name":"Perez Perez Antonio",
    "wof:placetype":"venue"
},
  "geometry": {"coordinates":[-6.2857818604,42.4824447632],"type":"Point"}
}