{
  "type": "Feature",
  "properties": {
    "iso:country":"ES",
    "sg:address":"Calle de Ildefonso Sanchez Del Rio, 8",
    "sg:city":"Oviedo",
    "sg:orig_category":"Electricidad, Electr\u00d3nica: Suministros (al Por Menor)",
    "sg:phone":"+34 985 11 34 35",
    "sg:postcode":"33011",
    "sg:province":"Asturias",
    "sg:website":"www.xerox.es",
    "wof:name":"Electronic Data System Espa\u00d1a S.a.",
    "wof:placetype":"venue"
},
  "geometry": {"coordinates":[-5.8410987854,43.3670005798],"type":"Point"}
}