{
  "type": "Feature",
  "properties": {
    "addr:full":"Carrer de Cervantes, 7 Barcelona Barcelona 08002",
    "addr:housenumber":"7",
    "addr:postcode":"08002",
    "addr:street":"Carrer De Cervantes",
    "iso:country":"ES",
    "sg:address":"Carrer de Cervantes, 7",
    "sg:city":"Barcelona",
    "sg:orig_category":"Muebles, Minoristas",
    "sg:phone":"+34 934 12 46 47",
    "sg:postcode":"08002",
    "sg:province":"Barcelona",
    "wof:name":"Nogues Aramburu Jose Maria",
    "wof:placetype":"venue"
},
  "geometry": {"coordinates":[2.1774280071,41.3813591003],"type":"Point"}
}