{
  "type": "Feature",
  "properties": {
    "iso:country":"ES",
    "sg:address":"Carrer de Angel Vidal, 12",
    "sg:city":"Sitges",
    "sg:orig_category":"Explotaci\u00d3n De Minas",
    "sg:phone":"+34 938 94 24 64",
    "sg:postcode":"08870",
    "sg:province":"Barcelona",
    "wof:name":"Minerales De Monterrey S.l.",
    "wof:placetype":"venue"
},
  "geometry": {"coordinates":[1.8102509975,41.2364349365],"type":"Point"}
}