{
  "type": "Feature",
  "properties": {
    "iso:country":"ES",
    "sg:address":"Av America, 6",
    "sg:city":"Mataro",
    "sg:orig_category":"Panader\u00cdas, Panader\u00cdas",
    "sg:phone":"+34 937 96 10 81",
    "sg:postcode":"08304",
    "sg:province":"Barcelona",
    "wof:name":"Pastinur S.l.",
    "wof:placetype":"venue"
},
  "geometry": {"coordinates":[2.4454579353,41.5473861694],"type":"Point"}
}