{
  "type": "Feature",
  "properties": {
    "iso:country":"ES",
    "sg:address":"Iguarte, 12",
    "sg:city":"Usurbil",
    "sg:orig_category":"Empresarios",
    "sg:phone":"+34 943 32 22 96",
    "sg:postcode":"20170",
    "sg:province":"Guip\u00f9zcoa",
    "wof:name":"Fundacion Euskomedia De Eusko Ikaskuntza",
    "wof:placetype":"venue"
},
  "geometry": {"coordinates":[-2.0539140701,43.2733459473],"type":"Point"}
}