{
  "type": "Feature",
  "properties": {
    "iso:country":"ES",
    "sg:address":"Carrer de Creu Coberta, 119",
    "sg:city":"Barcelona",
    "sg:orig_category":"Bisuter\u00cda, Joyer\u00cda, Relojer\u00cda (al Por Menor)",
    "sg:phone":"+34 933 31 44 00",
    "sg:postcode":"08014",
    "sg:province":"Barcelona",
    "wof:name":"Corporacion Catalana De Metales Preciosos Y Joyeria Selecta S.a.",
    "wof:placetype":"venue"
},
  "geometry": {"coordinates":[2.1420850754,41.3752212524],"type":"Point"}
}