{
  "type": "Feature",
  "properties": {
    "iso:country":"ES",
    "sg:address":"Calle de Escritor Herrera Santaolalla, 8",
    "sg:city":"Churriana",
    "sg:orig_category":"Chapister\u00cda",
    "sg:phone":"+34 952 43 70 65",
    "sg:postcode":"29140",
    "sg:province":"M\u00e1laga",
    "wof:name":"Repair Malaga S.l.l.",
    "wof:placetype":"venue"
},
  "geometry": {"coordinates":[-4.4949607849,36.6608276367],"type":"Point"}
}