{
  "type": "Feature",
  "properties": {
    "iso:country":"ES",
    "sg:address":"Calle de Villaamil, 7",
    "sg:city":"Madrid",
    "sg:orig_category":"Muebles",
    "sg:phone":"+34 913 11 37 95",
    "sg:postcode":"28039",
    "sg:province":"Madrid",
    "wof:name":"Atrio Cerezo Javier Valero",
    "wof:placetype":"venue"
},
  "geometry": {"coordinates":[-3.7055280209,40.4570274353],"type":"Point"}
}