{
  "type": "Feature",
  "properties": {
    "iso:country":"ES",
    "sg:address":"Calle de Antonio Pereira, 1",
    "sg:city":"Coru\u00d1a",
    "sg:orig_category":"Bibliotecas, Mediatecas",
    "sg:phone":"+34 981 15 02 27",
    "sg:postcode":"15007",
    "sg:province":"La Coru\u00f1a",
    "wof:name":"Ayuntamiento De La Coru\u00d1a",
    "wof:placetype":"venue"
},
  "geometry": {"coordinates":[-8.4174613953,43.3575134277],"type":"Point"}
}