{
  "type": "Feature",
  "properties": {
    "addr:full":"Carrer de Balmes, 215 Barcelona Barcelona 08006",
    "addr:housenumber":"215",
    "addr:postcode":"08006",
    "addr:street":"Carrer De Balmes",
    "iso:country":"ES",
    "sg:address":"Carrer de Balmes, 215",
    "sg:city":"Barcelona",
    "sg:orig_category":"Agencias Y Agentes Comerciales, Representantes",
    "sg:phone":"+34 932 18 15 56",
    "sg:postcode":"08006",
    "sg:province":"Barcelona",
    "wof:name":"Ruiz Torremocha Germinal",
    "wof:placetype":"venue"
},
  "geometry": {"coordinates":[2.1510848999,41.3983421326],"type":"Point"}
}