{
  "type": "Feature",
  "properties": {
    "iso:country":"ES",
    "sg:address":"Calle de Trasmonjas, 16",
    "sg:city":"Priego Cordoba",
    "sg:orig_category":"Promotores Constructores",
    "sg:phone":"+34 957 54 01 50",
    "sg:postcode":"14800",
    "sg:province":"C\u00f3rdoba",
    "wof:name":"Pricon S.a. De Construcciones",
    "wof:placetype":"venue"
},
  "geometry": {"coordinates":[-4.1952447891,37.4390068054],"type":"Point"}
}