{
  "type": "Feature",
  "properties": {
    "iso:country":"ES",
    "sg:address":"Calle de Corredera La, 3",
    "sg:city":"Coria",
    "sg:orig_category":"Sociedades, Compa\u00d1\u00cdas Aseguradoras",
    "sg:phone":"+34 927 50 19 56",
    "sg:postcode":"10800",
    "sg:province":"C\u00e1ceres",
    "wof:name":"Asesoria General Extreme\u00f1a S.l.",
    "wof:placetype":"venue"
},
  "geometry": {"coordinates":[-6.5350990295,39.9839897156],"type":"Point"}
}