{
  "type": "Feature",
  "properties": {
    "addr:full":"Pla\u00c7 Catalunya, 8 Banyoles Girona 17820",
    "addr:housenumber":"8",
    "addr:postcode":"17820",
    "iso:country":"ES",
    "sg:address":"Pla\u00c7 Catalunya, 8",
    "sg:city":"Banyoles",
    "sg:orig_category":"Asesor\u00cda Fiscal Y Jur\u00cddica",
    "sg:phone":"+34 972 57 42 12",
    "sg:postcode":"17820",
    "sg:province":"Girona",
    "wof:name":"Assesoria Miquel Pino S.l.l.",
    "wof:placetype":"venue"
},
  "geometry": {"coordinates":[2.7730026245,42.1189346313],"type":"Point"}
}