{
  "type": "Feature",
  "properties": {
    "addr:full":"Av Llibertat, 63 Mollet Valles Barcelona 08100",
    "addr:housenumber":"63",
    "addr:postcode":"08100",
    "addr:street":"Av Llibertat",
    "iso:country":"ES",
    "sg:address":"Av Llibertat, 63",
    "sg:city":"Mollet Valles",
    "sg:orig_category":"Abogados",
    "sg:phone":"+34 935 70 81 80",
    "sg:postcode":"08100",
    "sg:province":"Barcelona",
    "wof:name":"Borrego Rodriguez Jose",
    "wof:placetype":"venue"
},
  "geometry": {"coordinates":[2.2108631134,41.5345001221],"type":"Point"}
}