{
  "type": "Feature",
  "properties": {
    "addr:full":"Calle de Picasso, 1 Brunete Madrid 28690",
    "addr:housenumber":"1",
    "addr:postcode":"28690",
    "addr:street":"Calle De Picasso",
    "iso:country":"ES",
    "sg:address":"Calle de Picasso, 1",
    "sg:city":"Brunete",
    "sg:orig_category":"Televisi\u00d3n, V\u00cddeo: Aparatos Y Accesorios (venta)",
    "sg:phone":"+34 918 16 33 80",
    "sg:postcode":"28690",
    "sg:province":"Madrid",
    "sg:website":"www.antnetdigital.com",
    "wof:name":"Antnet Digital S.l.",
    "wof:placetype":"venue"
},
  "geometry": {"coordinates":[-3.9956200123,40.4069900513],"type":"Point"}
}