{
  "type": "Feature",
  "properties": {
    "iso:country":"ES",
    "sg:address":"Avda Galicia De, 12",
    "sg:city":"Luarca",
    "sg:orig_category":"Tintes (fabricaci\u00d3n, Al Por Mayor)",
    "sg:phone":"+34 985 64 22 06",
    "sg:postcode":"33700",
    "sg:province":"Asturias",
    "wof:name":"Citi Sec Tintorerias Gutierrez E Instillarte S.l.",
    "wof:placetype":"venue"
},
  "geometry": {"coordinates":[-6.5405840874,43.5432167053],"type":"Point"}
}