{
  "type": "Feature",
  "properties": {
    "addr:full":"Cami Carretera, 42 Villarreal Castell\u00f3n 12540",
    "addr:housenumber":"42",
    "addr:postcode":"12540",
    "addr:street":"Carretera",
    "iso:country":"ES",
    "sg:address":"Cami Carretera, 42",
    "sg:city":"Villarreal",
    "sg:orig_category":"Cer\u00c1mica Art\u00cdstica Y Decorativa",
    "sg:phone":"+34 964 53 36 37",
    "sg:postcode":"12540",
    "sg:province":"Castell\u00f3n",
    "wof:name":"Ceradecor S.l",
    "wof:placetype":"venue"
},
  "geometry": {"coordinates":[-0.1119690016,39.9314689636],"type":"Point"}
}