{
  "type": "Feature",
  "properties": {
    "iso:country":"ES",
    "sg:address":"Calle de Sevilla, 7",
    "sg:city":"Almu\u00f1ecar",
    "sg:orig_category":"Empresas De Carpinter\u00cda De Madera",
    "sg:phone":"+34 958 63 08 83",
    "sg:postcode":"18690",
    "sg:province":"Granada",
    "wof:name":"Herrera Rodrigo Francisco",
    "wof:placetype":"venue"
},
  "geometry": {"coordinates":[-3.6894938946,36.7344017029],"type":"Point"}
}