{
  "type": "Feature",
  "properties": {
    "addr:full":"Avda Burjasot, 271 Valencia Valencia 46015",
    "addr:housenumber":"271",
    "addr:postcode":"46015",
    "addr:street":"Avda Burjasot",
    "iso:country":"ES",
    "sg:address":"Avda Burjasot, 271",
    "sg:city":"Valencia",
    "sg:orig_category":"Tapicer\u00cdas",
    "sg:phone":"+34 963 48 56 34",
    "sg:postcode":"46015",
    "sg:province":"Valencia",
    "wof:name":"Saez Saez Josefa",
    "wof:placetype":"venue"
},
  "geometry": {"coordinates":[-0.3974399865,39.4961624146],"type":"Point"}
}