{
  "type": "Feature",
  "properties": {
    "addr:full":"Calle de Plus Ultra, 32 Valencia Valencia 46006",
    "addr:housenumber":"32",
    "addr:postcode":"46006",
    "addr:street":"Calle De Plus Ultra",
    "iso:country":"ES",
    "sg:address":"Calle de Plus Ultra, 32",
    "sg:city":"Valencia",
    "sg:orig_category":"Arreglo, Reparaci\u00d3n, Piezas Sueltas De Televisi\u00d3n, V\u00cddeo, Hi",
    "sg:phone":"+34 963 33 58 58",
    "sg:postcode":"46006",
    "sg:province":"Valencia",
    "wof:name":"Alabau Castrillo Vicente",
    "wof:placetype":"venue"
},
  "geometry": {"coordinates":[-0.3734566867,39.4551124573],"type":"Point"}
}