{
  "type": "Feature",
  "properties": {
    "iso:country":"ES",
    "sg:address":"Calle de Navas De Tolosa, 14",
    "sg:city":"Zaragoza",
    "sg:orig_category":"Bares, Piano",
    "sg:phone":"+34 976 53 19 86",
    "sg:postcode":"50010",
    "sg:province":"Zaragoza",
    "wof:name":"Ananavarro, S.l",
    "wof:placetype":"venue"
},
  "geometry": {"coordinates":[-0.9004964828,41.6539077759],"type":"Point"}
}