{
  "type": "Feature",
  "properties": {
    "iso:country":"ES",
    "sg:address":"Pje Matagallar, S/n",
    "sg:city":"Villanueva Algaidas",
    "sg:orig_category":"Ingenier\u00cda, Centros De Estudios (diversos)",
    "sg:phone":"+34 952 74 50 00",
    "sg:postcode":"29310",
    "sg:province":"M\u00e1laga",
    "wof:name":"Extragol S.l.",
    "wof:placetype":"venue"
},
  "geometry": {"coordinates":[-4.4497289658,37.1840057373],"type":"Point"}
}