{
  "type": "Feature",
  "properties": {
    "addr:full":"Plaz Manos Unidas, 15 Roquetas Mar Almer\u00eda 04740",
    "addr:housenumber":"15",
    "addr:postcode":"04740",
    "addr:street":"Manos Unidas",
    "iso:country":"ES",
    "sg:address":"Plaz Manos Unidas, 15",
    "sg:city":"Roquetas Mar",
    "sg:orig_category":"Escultores, Estatuarios E Imagineros",
    "sg:phone":"+34 950 32 62 10",
    "sg:postcode":"04740",
    "sg:province":"Almer\u00eda",
    "wof:name":"Proyectos Artisticos Lloren Y Lopez S.l.",
    "wof:placetype":"venue"
},
  "geometry": {"coordinates":[-2.6124989986,36.7638435364],"type":"Point"}
}