{
  "type": "Feature",
  "properties": {
    "addr:full":"Ptge Alio, 10 Barcelona Barcelona 08037",
    "addr:housenumber":"10",
    "addr:postcode":"08037",
    "addr:street":"Ptge Alio",
    "iso:country":"ES",
    "sg:address":"Ptge Alio, 10",
    "sg:city":"Barcelona",
    "sg:orig_category":"Electrodom\u00c9sticos (al Por Menor)",
    "sg:phone":"+34 934 59 11 55",
    "sg:postcode":"08037",
    "sg:province":"Barcelona",
    "wof:name":"Mantysat S.l.",
    "wof:placetype":"venue"
},
  "geometry": {"coordinates":[2.1666350365,41.4026985168],"type":"Point"}
}