{
  "type": "Feature",
  "properties": {
    "addr:full":"Calle de Copernico, 16 Coslada Madrid 28820",
    "addr:housenumber":"16",
    "addr:postcode":"28820",
    "addr:street":"Calle De Copernico",
    "iso:country":"ES",
    "sg:address":"Calle de Copernico, 16",
    "sg:city":"Coslada",
    "sg:orig_category":"Maquinaria Para Industrias Diversas",
    "sg:phone":"+34 916 60 10 65",
    "sg:postcode":"28820",
    "sg:province":"Madrid",
    "wof:name":"Ufs-tecnicas De Tratamiento De Superficies S.l.",
    "wof:placetype":"venue"
},
  "geometry": {"coordinates":[-3.5360820293,40.439666748],"type":"Point"}
}