{
  "type": "Feature",
  "properties": {
    "iso:country":"ES",
    "sg:address":"Calle de Santa Maria Bajera, 15",
    "sg:city":"Briviesca",
    "sg:orig_category":"Librer\u00cdas",
    "sg:phone":"+34 947 59 09 89",
    "sg:postcode":"09240",
    "sg:province":"Burgos",
    "wof:name":"Alonso Sagredo Natividad",
    "wof:placetype":"venue"
},
  "geometry": {"coordinates":[-3.3230588436,42.5514945984],"type":"Point"}
}