{
  "type": "Feature",
  "properties": {
    "iso:country":"ES",
    "sg:address":"Calle de Do\u00d1a Blanca, 3",
    "sg:city":"Jerez De La Frontera",
    "sg:orig_category":"Zapatos (al Por Menor)",
    "sg:phone":"+34 956 32 44 02",
    "sg:postcode":"11402",
    "sg:province":"C\u00e1diz",
    "wof:name":"Herrero Gracia Jesus",
    "wof:placetype":"venue"
},
  "geometry": {"coordinates":[-6.1361169815,36.682258606],"type":"Point"}
}