{
  "type": "Feature",
  "properties": {
    "iso:country":"ES",
    "sg:address":"Calle de Juan Picornell, 20",
    "sg:city":"Salamanca",
    "sg:orig_category":"Peluquer\u00cdas, Peluquer\u00cda Mixta",
    "sg:phone":"+34 923 22 93 50",
    "sg:postcode":"37006",
    "sg:province":"Salamanca",
    "wof:name":"Gonzalez Garcia Ines Maria",
    "wof:placetype":"venue"
},
  "geometry": {"coordinates":[-5.6649589539,40.9720802307],"type":"Point"}
}