{
  "type": "Feature",
  "properties": {
    "addr:full":"Calle de Compositor Lehmberg Ruiz, 5 Malaga M\u00e1laga 29007",
    "addr:housenumber":"5",
    "addr:postcode":"29007",
    "addr:street":"Calle De Compositor Lehmberg Ruiz;Ma\u0301Laga",
    "iso:country":"ES",
    "sg:address":"Calle de Compositor Lehmberg Ruiz, 5",
    "sg:city":"Malaga",
    "sg:orig_category":"Agencias Y Agentes Comerciales, Representantes",
    "sg:phone":"+34 952 30 74 94",
    "sg:postcode":"29007",
    "sg:province":"M\u00e1laga",
    "wof:name":"Barcenas Puertas Leovigildo",
    "wof:placetype":"venue"
},
  "geometry": {"coordinates":[-4.4319601059,36.717628479],"type":"Point"}
}