{
  "type": "Feature",
  "properties": {
    "iso:country":"ES",
    "sg:address":"Av Menorca, 7",
    "sg:city":"Mao",
    "sg:orig_category":"Prot\u00c9sicos Dentales",
    "sg:phone":"+34 971 36 96 75",
    "sg:postcode":"07703",
    "sg:province":"Islas Baleares",
    "wof:name":"Menorca Dent S.l.",
    "wof:placetype":"venue"
},
  "geometry": {"coordinates":[4.2580051422,39.8859138489],"type":"Point"}
}