{
  "type": "Feature",
  "properties": {
    "iso:country":"ES",
    "sg:address":"Mayor, 71",
    "sg:city":"Estella",
    "sg:orig_category":"Pescader\u00cdas (al Por Menor)",
    "sg:phone":"+34 948 55 05 34",
    "sg:postcode":"31200",
    "sg:province":"Navarra",
    "wof:name":"Lopez Navarro Gloria",
    "wof:placetype":"venue"
},
  "geometry": {"coordinates":[-2.0304489136,42.6710205078],"type":"Point"}
}