{
  "type": "Feature",
  "properties": {
    "iso:country":"ES",
    "sg:address":"Av Abat Marcet, 321",
    "sg:city":"Terrassa",
    "sg:orig_category":"Tintes (fabricaci\u00d3n, Al Por Mayor)",
    "sg:phone":"+34 937 89 12 90",
    "sg:postcode":"08225",
    "sg:province":"Barcelona",
    "wof:name":"Tintoreria Terrassa S.l.",
    "wof:placetype":"venue"
},
  "geometry": {"coordinates":[2.0051329136,41.5742416382],"type":"Point"}
}