{
  "type": "Feature",
  "properties": {
    "iso:country":"ES",
    "sg:address":"Ctra Alcazares, S/n",
    "sg:city":"Torre-pacheco",
    "sg:orig_category":"Flores Y Plantas Naturales (al Por Mayor)",
    "sg:phone":"+34 968 58 55 28",
    "sg:postcode":"30700",
    "sg:province":"Murcia",
    "wof:name":"Semilleros San Cayetano S.l.",
    "wof:placetype":"venue"
},
  "geometry": {"coordinates":[-0.9498599768,37.8160095215],"type":"Point"}
}