{
  "type": "Feature",
  "properties": {
    "addr:full":"Calle de Goya, 5 Borja Zaragoza 50540",
    "addr:housenumber":"5",
    "addr:postcode":"50540",
    "addr:street":"Calle De Goya",
    "iso:country":"ES",
    "sg:address":"Calle de Goya, 5",
    "sg:city":"Borja",
    "sg:orig_category":"Cajas De Ahorro",
    "sg:phone":"+34 976 86 80 44",
    "sg:postcode":"50540",
    "sg:province":"Zaragoza",
    "wof:name":"Caja Rural Aragonesa Y De Los Pirineos",
    "wof:placetype":"venue"
},
  "geometry": {"coordinates":[-1.5322380066,41.8344497681],"type":"Point"}
}