{
  "type": "Feature",
  "properties": {
    "iso:country":"ES",
    "sg:address":"Ctra Madrigalejo, S/n",
    "sg:city":"Zorita",
    "sg:orig_category":"Empresas De Carpinter\u00cda Met\u00c1lica",
    "sg:phone":"+34 927 34 07 25",
    "sg:postcode":"10130",
    "sg:province":"C\u00e1ceres",
    "wof:name":"Sojo Chamorro Agustin",
    "wof:placetype":"venue"
},
  "geometry": {"coordinates":[-5.6982688904,39.2826538086],"type":"Point"}
}