{
  "type": "Feature",
  "properties": {
    "iso:country":"ES",
    "sg:address":"Ctra Antiga A Sabadell, 9",
    "sg:city":"Can Cuias",
    "sg:orig_category":"Molduras, Junquillos, Listones Y Molduras Perforadas",
    "sg:phone":"+34 935 75 31 03",
    "sg:postcode":"08110",
    "sg:province":"Barcelona",
    "wof:name":"Restaurante Can Cuyas S.l.unipersonal",
    "wof:placetype":"venue"
},
  "geometry": {"coordinates":[2.1817660332,41.4890899658],"type":"Point"}
}