{
  "type": "Feature",
  "properties": {
    "addr:full":"Calle de Fraile Leku, 1 Bermeo Vizcaya 48370",
    "addr:housenumber":"1",
    "addr:postcode":"48370",
    "addr:street":"Calle De Fraile Leku",
    "iso:country":"ES",
    "sg:address":"Calle de Fraile Leku, 1",
    "sg:city":"Bermeo",
    "sg:orig_category":"Ense\u00d1anza, Formaci\u00d3n Profesional: Aprendizaje",
    "sg:phone":"+34 946 88 39 16",
    "sg:postcode":"48370",
    "sg:province":"Vizcaya",
    "wof:name":"Cofradia De Pescadores San Pedro De Bermeo",
    "wof:placetype":"venue"
},
  "geometry": {"coordinates":[-2.7207980156,43.4189033508],"type":"Point"}
}