{
  "type": "Feature",
  "properties": {
    "iso:country":"ES",
    "sg:address":"Carrer de Lope De Vega, 68",
    "sg:city":"Sabadell",
    "sg:orig_category":"Carnicer\u00cdas, Carnicer\u00cdas",
    "sg:phone":"+34 937 11 99 10",
    "sg:postcode":"08204",
    "sg:province":"Barcelona",
    "sg:website":"www.morenoantolinos.com",
    "wof:name":"Moreno-antolinos Cansaladers S.l.",
    "wof:placetype":"venue"
},
  "geometry": {"coordinates":[2.1175100803,41.5315361023],"type":"Point"}
}