{
  "type": "Feature",
  "properties": {
    "addr:full":"Avda Letxumborro, 92 Irun Guip\u00f9zcoa 20303",
    "addr:housenumber":"92",
    "addr:postcode":"20303",
    "addr:street":"Avda Letxumborro;Guipu\u0300Zcoa",
    "iso:country":"ES",
    "sg:address":"Avda Letxumborro, 92",
    "sg:city":"Irun",
    "sg:orig_category":"Delegados, Agentes De Tr\u00c1nsito, Auxiliares De Transporte Internacional",
    "sg:phone":"+34 943 63 44 17",
    "sg:postcode":"20303",
    "sg:province":"Guip\u00f9zcoa",
    "sg:website":"www.htgexpress.com",
    "wof:name":"Hirutrans Garraioak S.l.",
    "wof:placetype":"venue"
},
  "geometry": {"coordinates":[-1.7902339697,43.3395233154],"type":"Point"}
}