{
  "type": "Feature",
  "properties": {
    "addr:full":"Calle de San Ildefonso, 4 Madrid Madrid 28012",
    "addr:housenumber":"4",
    "addr:postcode":"28012",
    "addr:street":"Calle De San Ildefonso",
    "iso:country":"ES",
    "sg:address":"Calle de San Ildefonso, 4",
    "sg:city":"Madrid",
    "sg:orig_category":"Asesor\u00cdas En Comunicaci\u00d3n",
    "sg:phone":"+34 914 67 38 76",
    "sg:postcode":"28012",
    "sg:province":"Madrid",
    "wof:name":"Chaves Lopez Lara",
    "wof:placetype":"venue"
},
  "geometry": {"coordinates":[-3.6973280907,40.4108161926],"type":"Point"}
}