{
  "type": "Feature",
  "properties": {
    "iso:country":"ES",
    "sg:address":"Carr Barcelona, 3",
    "sg:city":"Girona",
    "sg:orig_category":"Notarios",
    "sg:phone":"+34 972 20 97 00",
    "sg:postcode":"17002",
    "sg:province":"Girona",
    "wof:name":"Brancos Nu\u00f1ez Enrique",
    "wof:placetype":"venue"
},
  "geometry": {"coordinates":[2.819133997,41.9813423157],"type":"Point"}
}