{
  "type": "Feature",
  "properties": {
    "addr:full":"Calle de San Fernando, 5 Valladolid Valladolid 47010",
    "addr:housenumber":"5",
    "addr:postcode":"47010",
    "addr:street":"Calle De San Fernando",
    "iso:country":"ES",
    "sg:address":"Calle de San Fernando, 5",
    "sg:city":"Valladolid",
    "sg:orig_category":"Plomeros",
    "sg:phone":"+34 983 32 00 68",
    "sg:postcode":"47010",
    "sg:province":"Valladolid",
    "wof:name":"Ma\u00d1anes Ips S.a.",
    "wof:placetype":"venue"
},
  "geometry": {"coordinates":[-4.7173271179,41.661693573],"type":"Point"}
}