{
  "type": "Feature",
  "properties": {
    "iso:country":"ES",
    "sg:address":"Carrer de Ramon Rocafull, 36",
    "sg:city":"Barcelona",
    "sg:orig_category":"Empresas De Carpinter\u00cda De Madera",
    "sg:phone":"+34 933 58 80 00",
    "sg:postcode":"08032",
    "sg:province":"Barcelona",
    "wof:name":"Suarez Ruiz Mateo",
    "wof:placetype":"venue"
},
  "geometry": {"coordinates":[2.1527578831,41.4237442017],"type":"Point"}
}