{
  "type": "Feature",
  "properties": {
    "addr:full":"Calle de Navasecas, 2 Madrid Madrid 28023",
    "addr:housenumber":"2",
    "addr:postcode":"28023",
    "addr:street":"Calle De Navasecas",
    "iso:country":"ES",
    "sg:address":"Calle de Navasecas, 2",
    "sg:city":"Madrid",
    "sg:orig_category":"Alquiler De V\u00cddeo",
    "sg:phone":"+34 913 72 96 93",
    "sg:postcode":"28023",
    "sg:province":"Madrid",
    "wof:name":"Intabo S.l.",
    "wof:placetype":"venue"
},
  "geometry": {"coordinates":[-3.8365390301,40.4764595032],"type":"Point"}
}