{
  "type": "Feature",
  "properties": {
    "iso:country":"ES",
    "sg:address":"Golondrina, 2",
    "sg:city":"Mijas Costa",
    "sg:orig_category":"Empresas De Carpinter\u00cda De Madera",
    "sg:phone":"+34 952 58 03 98",
    "sg:postcode":"29649",
    "sg:province":"M\u00e1laga",
    "wof:name":"Hermanos Carrion Cortes S.l.",
    "wof:placetype":"venue"
},
  "geometry": {"coordinates":[-4.7157039642,36.4931945801],"type":"Point"}
}