{
  "type": "Feature",
  "properties": {
    "iso:country":"ES",
    "sg:address":"Calle de Padre Pulido, 50",
    "sg:city":"Castelseras",
    "sg:orig_category":"Promotores Constructores",
    "sg:phone":"+34 978 87 71 17",
    "sg:postcode":"44630",
    "sg:province":"Teruel",
    "wof:name":"Construcciones Ceperuelo S.l.",
    "wof:placetype":"venue"
},
  "geometry": {"coordinates":[-0.1458590031,40.9798316956],"type":"Point"}
}