{
  "type": "Feature",
  "properties": {
    "addr:full":"Calle de Corredera, 63 Viso Del Alcor Sevilla 41520",
    "addr:housenumber":"63",
    "addr:postcode":"41520",
    "addr:street":"Calle De Corredera",
    "iso:country":"ES",
    "sg:address":"Calle de Corredera, 63",
    "sg:city":"Viso Del Alcor",
    "sg:orig_category":"Mercer\u00cda, Lencer\u00cda (al Por Menor)",
    "sg:phone":"+34 955 94 53 16",
    "sg:postcode":"41520",
    "sg:province":"Sevilla",
    "wof:name":"Vergara Escribano Lucia",
    "wof:placetype":"venue"
},
  "geometry": {"coordinates":[-5.7226705551,37.3868179321],"type":"Point"}
}