{
  "type": "Feature",
  "properties": {
    "iso:country":"ES",
    "sg:address":"Calle de Templarios, 18",
    "sg:city":"Jerez De Los Caballeros",
    "sg:orig_category":"Abogados",
    "sg:phone":"+34 924 73 00 72",
    "sg:postcode":"06380",
    "sg:province":"Badajoz",
    "wof:name":"Bravo Bravo Jose",
    "wof:placetype":"venue"
},
  "geometry": {"coordinates":[-6.7693300247,38.3212471008],"type":"Point"}
}