{
  "type": "Feature",
  "properties": {
    "addr:full":"Carr Cavallers, 50 Palafrugell Girona 17200",
    "addr:housenumber":"50",
    "addr:postcode":"17200",
    "addr:street":"Carr Cavallers",
    "iso:country":"ES",
    "sg:address":"Carr Cavallers, 50",
    "sg:city":"Palafrugell",
    "sg:orig_category":"Zapatos (al Por Menor)",
    "sg:phone":"+34 972 30 02 38",
    "sg:postcode":"17200",
    "sg:province":"Girona",
    "wof:name":"Alsina Suri\u00f1ach Josefa",
    "wof:placetype":"venue"
},
  "geometry": {"coordinates":[3.1639101505,41.9165649414],"type":"Point"}
}