{
  "type": "Feature",
  "properties": {
    "iso:country":"ES",
    "sg:address":"Ctra Aznalcollar, S/n",
    "sg:city":"Escacena Campo",
    "sg:orig_category":"Agricultores, Agricultores",
    "sg:phone":"+34 959 50 60 29",
    "sg:postcode":"21870",
    "sg:province":"Huelva",
    "wof:name":"Santa Maria Del Rio S.a.",
    "wof:placetype":"venue"
},
  "geometry": {"coordinates":[-6.3860478401,37.4094390869],"type":"Point"}
}