{
  "type": "Feature",
  "properties": {
    "iso:country":"ES",
    "sg:address":"Calle de Cabo Nicolas Mur, 16",
    "sg:city":"Madrid",
    "sg:orig_category":"Plomeros",
    "sg:phone":"+34 914 71 10 82",
    "sg:postcode":"28019",
    "sg:province":"Madrid",
    "wof:name":"Mencias Rivera Luis",
    "wof:placetype":"venue"
},
  "geometry": {"coordinates":[-3.7330684662,40.3945884705],"type":"Point"}
}