{
  "type": "Feature",
  "properties": {
    "iso:country":"ES",
    "sg:address":"Carrer de Ramon Llull, 141",
    "sg:city":"Terrassa",
    "sg:orig_category":"Organizaciones Profesionales",
    "sg:phone":"+34 937 88 35 28",
    "sg:postcode":"08224",
    "sg:province":"Barcelona",
    "wof:name":"Soler Bonavida Francisca",
    "wof:placetype":"venue"
},
  "geometry": {"coordinates":[2.0012090206,41.5595245361],"type":"Point"}
}