{
  "type": "Feature",
  "properties": {
    "addr:full":"Calle de Estacion, 85 Valladolid Valladolid 47004",
    "addr:housenumber":"85",
    "addr:postcode":"47004",
    "addr:street":"Calle De Estacion",
    "iso:country":"ES",
    "sg:address":"Calle de Estacion, 85",
    "sg:city":"Valladolid",
    "sg:orig_category":"Fiesta: Art\u00cdculos De (al Por Menor)",
    "sg:phone":"+34 983 29 20 74",
    "sg:postcode":"47004",
    "sg:province":"Valladolid",
    "wof:name":"Graficas Hispania Valladolid S.l.",
    "wof:placetype":"venue"
},
  "geometry": {"coordinates":[-4.7177886963,41.6453361511],"type":"Point"}
}