{
  "type": "Feature",
  "properties": {
    "addr:full":"Calle de Castello, 6 Rafelbunyol Valencia 46138",
    "addr:housenumber":"6",
    "addr:postcode":"46138",
    "addr:street":"Calle De Castello",
    "iso:country":"ES",
    "sg:address":"Calle de Castello, 6",
    "sg:city":"Rafelbunyol",
    "sg:orig_category":"Empresarios",
    "sg:phone":"+34 961 41 02 16",
    "sg:postcode":"46138",
    "sg:province":"Valencia",
    "wof:name":"Magdaleno Blanquez Mariano",
    "wof:placetype":"venue"
},
  "geometry": {"coordinates":[-0.3008159101,39.5894546509],"type":"Point"}
}