{
  "type": "Feature",
  "properties": {
    "iso:country":"ES",
    "sg:address":"Calle de Trespaderne, 37",
    "sg:city":"Medina Pomar",
    "sg:orig_category":"Empresas De Limpieza",
    "sg:phone":"+34 947 14 76 39",
    "sg:postcode":"09500",
    "sg:province":"Burgos",
    "wof:name":"Castrillo Saldamando Luis Miguel",
    "wof:placetype":"venue"
},
  "geometry": {"coordinates":[-3.4865629673,42.9429168701],"type":"Point"}
}