{
  "type": "Feature",
  "properties": {
    "iso:country":"ES",
    "sg:address":"Calle de Enguera, 23",
    "sg:city":"Valencia",
    "sg:orig_category":"Promotores Constructores",
    "sg:phone":"+34 963 85 62 30",
    "sg:postcode":"46018",
    "sg:province":"Valencia",
    "wof:name":"Cooperativa Casas Baratas Dependencia Mercantil",
    "wof:placetype":"venue"
},
  "geometry": {"coordinates":[-0.3943989873,39.4653587341],"type":"Point"}
}