{
  "type": "Feature",
  "properties": {
    "addr:full":"Avda Benvinguts, Dels, S/n Cala D'or Islas Baleares 07660",
    "addr:postcode":"07660",
    "addr:street":"Avda Benvinguts Dels S / N",
    "iso:country":"ES",
    "sg:address":"Avda Benvinguts, Dels, S/n",
    "sg:city":"Cala D'or",
    "sg:orig_category":"Centros De Coordinaci\u00d3n",
    "sg:phone":"+34 971 65 79 50",
    "sg:postcode":"07660",
    "sg:province":"Islas Baleares",
    "wof:name":"Adrover Fullana Maria Lourdes",
    "wof:placetype":"venue"
},
  "geometry": {"coordinates":[3.2276799679,39.3775138855],"type":"Point"}
}