{
  "type": "Feature",
  "properties": {
    "iso:country":"ES",
    "sg:address":"Plaz Iglesia (de La), S/n",
    "sg:city":"Linea De La Concepcion",
    "sg:orig_category":"Iglesia Cat\u00d3lica",
    "sg:phone":"+34 956 76 02 58",
    "sg:postcode":"11300",
    "sg:province":"C\u00e1diz",
    "wof:name":"Parroquia De La Concepcion",
    "wof:placetype":"venue"
},
  "geometry": {"coordinates":[-5.351539135,36.1621055603],"type":"Point"}
}