{
  "type": "Feature",
  "properties": {
    "addr:full":"Calle de Eugenia De Montijo, 2 Palencia Palencia 34003",
    "addr:housenumber":"2",
    "addr:postcode":"34003",
    "addr:street":"Calle De Eugenia De Montijo",
    "iso:country":"ES",
    "sg:address":"Calle de Eugenia De Montijo, 2",
    "sg:city":"Palencia",
    "sg:orig_category":"Productos Alimentarios",
    "sg:phone":"+34 979 74 46 46",
    "sg:postcode":"34003",
    "sg:province":"Palencia",
    "wof:name":"Iba\u00f1ez Lopez Florentino",
    "wof:placetype":"venue"
},
  "geometry": {"coordinates":[-4.5273690224,42.0164604187],"type":"Point"}
}