{
  "type": "Feature",
  "properties": {
    "addr:full":"Avda Algorta, 20 Algorta Vizcaya 48992",
    "addr:housenumber":"20",
    "addr:postcode":"48992",
    "addr:street":"Avda Algorta",
    "iso:country":"ES",
    "sg:address":"Avda Algorta, 20",
    "sg:city":"Algorta",
    "sg:orig_category":"Organismos De Reclutamiento",
    "sg:phone":"+34 944 91 10 36",
    "sg:postcode":"48992",
    "sg:province":"Vizcaya",
    "wof:name":"Chapa Imaz Alvaro",
    "wof:placetype":"venue"
},
  "geometry": {"coordinates":[-3.0093688965,43.3417510986],"type":"Point"}
}