{
  "type": "Feature",
  "properties": {
    "iso:country":"ES",
    "sg:address":"Calle de Blas Infante, 9",
    "sg:city":"Palacios Y Villafranca",
    "sg:orig_category":"Telas Y Sedas (al Por Menor)",
    "sg:phone":"+34 955 81 08 82",
    "sg:postcode":"41720",
    "sg:province":"Sevilla",
    "wof:name":"Lozano Garcia Manuel",
    "wof:placetype":"venue"
},
  "geometry": {"coordinates":[-5.9253211021,37.1596183777],"type":"Point"}
}