{
  "type": "Feature",
  "properties": {
    "iso:country":"ES",
    "sg:address":"Calle de Lorenzo Llona, 4",
    "sg:city":"Sestao",
    "sg:orig_category":"Agentes Generales De Seguros",
    "sg:phone":"+34 944 96 77 80",
    "sg:postcode":"48910",
    "sg:province":"Vizcaya",
    "wof:name":"Zubiaga Zarraga Rafael",
    "wof:placetype":"venue"
},
  "geometry": {"coordinates":[-3.0056130886,43.3084487915],"type":"Point"}
}