{
  "type": "Feature",
  "properties": {
    "addr:full":"Calle de Urbasa, 18 Alsasua Navarra 31800",
    "addr:housenumber":"18",
    "addr:postcode":"31800",
    "addr:street":"Calle De Urbasa",
    "iso:country":"ES",
    "sg:address":"Calle de Urbasa, 18",
    "sg:city":"Alsasua",
    "sg:orig_category":"Carnicer\u00cdas, Carnicer\u00cdas",
    "sg:phone":"+34 948 56 29 37",
    "sg:postcode":"31800",
    "sg:province":"Navarra",
    "wof:name":"Aracama Imaz Juan",
    "wof:placetype":"venue"
},
  "geometry": {"coordinates":[-2.1733415127,42.8932151794],"type":"Point"}
}