{
  "type": "Feature",
  "properties": {
    "iso:country":"ES",
    "sg:address":"Calle de Manuel Iradier, 64",
    "sg:city":"Vitoria-gasteiz",
    "sg:orig_category":"Televisi\u00d3n, V\u00cddeo: Aparatos Y Accesorios (venta)",
    "sg:phone":"+34 945 27 58 19",
    "sg:postcode":"01005",
    "sg:province":"\u00c1lava",
    "wof:name":"Arce Imagen Y Sonido S.l.",
    "wof:placetype":"venue"
},
  "geometry": {"coordinates":[-2.6690142155,42.8418045044],"type":"Point"}
}