{
  "type": "Feature",
  "properties": {
    "addr:full":"C/ Veri, 2 Porto Cristo Islas Baleares 07680",
    "addr:housenumber":"2",
    "addr:postcode":"07680",
    "addr:street":"C / Veri;Islas Baleares",
    "iso:country":"ES",
    "sg:address":"C/ Veri, 2",
    "sg:city":"Porto Cristo",
    "sg:orig_category":"Restaurantes",
    "sg:phone":"+34 971 82 24 44",
    "sg:postcode":"07680",
    "sg:province":"Islas Baleares",
    "wof:name":"Bennassar Caldentey S.l.",
    "wof:placetype":"venue"
},
  "geometry": {"coordinates":[3.3359000683,39.5415039062],"type":"Point"}
}