{
  "type": "Feature",
  "properties": {
    "iso:country":"ES",
    "sg:address":"Bo. Palmeral, 31",
    "sg:city":"Callosa Segura",
    "sg:orig_category":"Molduras, Junquillos, Listones Y Molduras Perforadas",
    "sg:phone":"+34 966 75 66 24",
    "sg:postcode":"03360",
    "sg:province":"Alicante",
    "wof:name":"Ballester Soto Manuel Jesus",
    "wof:placetype":"venue"
},
  "geometry": {"coordinates":[-0.8776689768,38.1256752014],"type":"Point"}
}