{
  "type": "Feature",
  "properties": {
    "iso:country":"ES",
    "sg:address":"Ptda Boqueres-a, 17",
    "sg:city":"Boqueres",
    "sg:orig_category":"Muebles",
    "sg:phone":"+34 965 66 33 10",
    "sg:postcode":"03690",
    "sg:province":"Alicante",
    "wof:name":"Bardisa Gimenez Manuel",
    "wof:placetype":"venue"
},
  "geometry": {"coordinates":[-0.5247189999,38.405040741],"type":"Point"}
}