{
  "type": "Feature",
  "properties": {
    "iso:country":"ES",
    "sg:address":"Carrer de Pintor Borrassa, 151",
    "sg:city":"Terrassa",
    "sg:orig_category":"Electricidad: Instaladores",
    "sg:phone":"+34 937 35 83 64",
    "sg:postcode":"08226",
    "sg:province":"Barcelona",
    "wof:name":"Instalaciones Electricas Terrassa 95 S.l.",
    "wof:placetype":"venue"
},
  "geometry": {"coordinates":[2.0228869915,41.5793647766],"type":"Point"}
}