{
  "type": "Feature",
  "properties": {
    "addr:full":"Murcia, 3 Puente Del Rio Almer\u00eda 04779",
    "addr:housenumber":"3",
    "addr:postcode":"04779",
    "addr:street":"Murcia;Del;Almeri\u0301A",
    "iso:country":"ES",
    "sg:address":"Murcia, 3",
    "sg:city":"Puente Del Rio",
    "sg:orig_category":"Supermercados Y Hipermercados",
    "sg:phone":"+34 950 56 81 77",
    "sg:postcode":"04779",
    "sg:province":"Almer\u00eda",
    "wof:name":"Supermercado Espin S.a.",
    "wof:placetype":"venue"
},
  "geometry": {"coordinates":[-2.972438097,36.7591819763],"type":"Point"}
}