{
  "type": "Feature",
  "properties": {
    "iso:country":"ES",
    "sg:address":"Quimica, 4",
    "sg:city":"Alcazar S. Juan",
    "sg:orig_category":"Electricidad: Instaladores",
    "sg:phone":"+34 926 55 10 11",
    "sg:postcode":"13600",
    "sg:province":"Ciudad Real",
    "wof:name":"Sanchez-mateos Castellanos Bernardo",
    "wof:placetype":"venue"
},
  "geometry": {"coordinates":[-3.210203886,39.3900718689],"type":"Point"}
}