{
  "type": "Feature",
  "properties": {
    "addr:full":"Calle de Duque De Rivas, 9 Gijon Asturias 33204",
    "addr:housenumber":"9",
    "addr:postcode":"33204",
    "addr:street":"Calle De Duque De Rivas",
    "iso:country":"ES",
    "sg:address":"Calle de Duque De Rivas, 9",
    "sg:city":"Gijon",
    "sg:orig_category":"Alquiler De Gr\u00daas",
    "sg:phone":"+34 985 13 47 51",
    "sg:postcode":"33204",
    "sg:province":"Asturias",
    "wof:name":"Gruas Costales S.l.",
    "wof:placetype":"venue"
},
  "geometry": {"coordinates":[-5.6527638435,43.5299263],"type":"Point"}
}