{
  "type": "Feature",
  "properties": {
    "iso:country":"ES",
    "sg:address":"Calle de Duque De Salas, 49",
    "sg:city":"Merida",
    "sg:orig_category":"Ingeniero",
    "sg:phone":"+34 924 31 83 54",
    "sg:postcode":"06800",
    "sg:province":"Badajoz",
    "wof:name":"Gabinete De Ingenieria Tecnica C.b.",
    "wof:placetype":"venue"
},
  "geometry": {"coordinates":[-6.3523154259,38.921459198],"type":"Point"}
}