{
  "type": "Feature",
  "properties": {
    "addr:full":"Avda Doctor Artero Guirao, 96 S. Pedro Pinatar Murcia 30740",
    "addr:housenumber":"96",
    "addr:postcode":"30740",
    "addr:street":"Avda Doctor Artero Guirao",
    "iso:country":"ES",
    "sg:address":"Avda Doctor Artero Guirao, 96",
    "sg:city":"S. Pedro Pinatar",
    "sg:orig_category":"Agentes Generales De Seguros",
    "sg:phone":"+34 968 18 56 16",
    "sg:postcode":"30740",
    "sg:province":"Murcia",
    "wof:name":"Samper Arenas S.l.",
    "wof:placetype":"venue"
},
  "geometry": {"coordinates":[-0.7908679843,37.8366165161],"type":"Point"}
}