{
  "type": "Feature",
  "properties": {
    "addr:full":"Calle de Bilibio, 1 Haro La Rioja 26200",
    "addr:housenumber":"1",
    "addr:postcode":"26200",
    "addr:street":"Calle De Bilibio",
    "iso:country":"ES",
    "sg:address":"Calle de Bilibio, 1",
    "sg:city":"Haro",
    "sg:orig_category":"Molduras, Junquillos, Listones Y Molduras Perforadas",
    "sg:phone":"+34 941 31 02 67",
    "sg:postcode":"26200",
    "sg:province":"La Rioja",
    "wof:name":"Rios Bustillo Francisco Javier",
    "wof:placetype":"venue"
},
  "geometry": {"coordinates":[-2.8465662003,42.5773696899],"type":"Point"}
}