{
  "type": "Feature",
  "properties": {
    "iso:country":"ES",
    "sg:address":"Ctra Campillo, 1",
    "sg:city":"Guijuelo",
    "sg:orig_category":"Asociaciones Y Clubs Deportivos",
    "sg:phone":"+34 923 58 14 00",
    "sg:postcode":"37770",
    "sg:province":"Salamanca",
    "wof:name":"Castro Jaen Maria Isabel",
    "wof:placetype":"venue"
},
  "geometry": {"coordinates":[-5.6728668213,40.5594177246],"type":"Point"}
}