{
  "type": "Feature",
  "properties": {
    "iso:country":"ES",
    "sg:address":"Calle de Capitan Quesada, 35",
    "sg:city":"Galdar",
    "sg:orig_category":"Bazares, Art\u00cdculos De Limpieza Y De Cocina (al Por Menor)",
    "sg:phone":"+34 928 88 34 18",
    "sg:postcode":"35460",
    "sg:province":"Las Palmas",
    "wof:name":"Cardenes Miranda Miguel Angel",
    "wof:placetype":"venue"
},
  "geometry": {"coordinates":[-15.6527891159,28.1454391479],"type":"Point"}
}