{
  "type": "Feature",
  "properties": {
    "iso:country":"ES",
    "sg:address":"Calle de Pozo, 33",
    "sg:city":"Moraleja Vino",
    "sg:orig_category":"Pescader\u00cdas (al Por Menor)",
    "sg:phone":"+34 980 57 11 88",
    "sg:postcode":"49150",
    "sg:province":"Zamora",
    "wof:name":"Freire Rodriguez Guillermo",
    "wof:placetype":"venue"
},
  "geometry": {"coordinates":[-5.65812397,41.4647712708],"type":"Point"}
}