{
  "type": "Feature",
  "properties": {
    "addr:full":"Calle de Ribadesella, 5 Gijon Asturias 33207",
    "addr:housenumber":"5",
    "addr:postcode":"33207",
    "addr:street":"Calle De Ribadesella",
    "iso:country":"ES",
    "sg:address":"Calle de Ribadesella, 5",
    "sg:city":"Gijon",
    "sg:orig_category":"Autob\u00das (explotaci\u00d3n Y Servicios De)",
    "sg:phone":"+34 985 34 52 08",
    "sg:postcode":"33207",
    "sg:province":"Asturias",
    "wof:name":"Servicios Del Principado S.a.",
    "wof:placetype":"venue"
},
  "geometry": {"coordinates":[-5.6676249504,43.5385894775],"type":"Point"}
}