{
  "type": "Feature",
  "properties": {
    "iso:country":"ES",
    "sg:address":"Calle de Almedina, 9",
    "sg:city":"Torrox",
    "sg:orig_category":"Centros De Coordinaci\u00d3n",
    "sg:phone":"+34 952 53 54 44",
    "sg:postcode":"29770",
    "sg:province":"M\u00e1laga",
    "wof:name":"Segura Chacon Maria Teresa",
    "wof:placetype":"venue"
},
  "geometry": {"coordinates":[-3.9509739876,36.7582702637],"type":"Point"}
}