{
  "type": "Feature",
  "properties": {
    "addr:full":"Calle de Palomar, 6 Caspe Zaragoza 50700",
    "addr:housenumber":"6",
    "addr:postcode":"50700",
    "addr:street":"Calle De Palomar",
    "iso:country":"ES",
    "sg:address":"Calle de Palomar, 6",
    "sg:city":"Caspe",
    "sg:orig_category":"Empresas De Carpinter\u00cda De Madera",
    "sg:phone":"+34 976 63 10 12",
    "sg:postcode":"50700",
    "sg:province":"Zaragoza",
    "wof:name":"Rafales Francin Domingo Miguel",
    "wof:placetype":"venue"
},
  "geometry": {"coordinates":[-0.0384549983,41.2328109741],"type":"Point"}
}