{
  "type": "Feature",
  "properties": {
    "iso:country":"ES",
    "sg:address":"Vilaguillulfe, 3",
    "sg:city":"Vilaguillulfe",
    "sg:orig_category":"Cr\u00cda De Animales",
    "sg:phone":"+34 982 46 62 31",
    "sg:postcode":"27527",
    "sg:province":"Lugo",
    "wof:name":"Tratante Sc",
    "wof:placetype":"venue"
},
  "geometry": {"coordinates":[-7.8528928757,42.5718955994],"type":"Point"}
}