{
  "type": "Feature",
  "properties": {
    "iso:country":"ES",
    "sg:address":"Carrer de Cinca, 92",
    "sg:city":"Barcelona",
    "sg:orig_category":"Farmacias",
    "sg:phone":"+34 933 45 40 08",
    "sg:postcode":"08030",
    "sg:province":"Barcelona",
    "wof:name":"Pulido Navarro Margarita",
    "wof:placetype":"venue"
},
  "geometry": {"coordinates":[2.1922039986,41.4400901794],"type":"Point"}
}