{
  "type": "Feature",
  "properties": {
    "iso:country":"ES",
    "sg:address":"Ctra Aguilar, 10",
    "sg:city":"Cervera Pisuerga",
    "sg:orig_category":"Laboratorios Y Cl\u00cdnicas Veterinarias",
    "sg:phone":"+34 979 87 06 26",
    "sg:postcode":"34840",
    "sg:province":"Palencia",
    "wof:name":"Comercial Norte Tecnipec S.l.",
    "wof:placetype":"venue"
},
  "geometry": {"coordinates":[-4.4180278778,42.8575897217],"type":"Point"}
}