{
  "type": "Feature",
  "properties": {
    "addr:full":"Ctra. Andratx, 43 Portals Nous Islas Baleares 07181",
    "addr:housenumber":"43",
    "addr:postcode":"07181",
    "addr:street":"Ctra. Andratx",
    "iso:country":"ES",
    "sg:address":"Ctra. Andratx, 43",
    "sg:city":"Portals Nous",
    "sg:orig_category":"Institutos De Belleza (productos Y Aparatos)",
    "sg:phone":"+34 971 67 71 36",
    "sg:postcode":"07181",
    "sg:province":"Islas Baleares",
    "wof:name":"Malmestron  Denise",
    "wof:placetype":"venue"
},
  "geometry": {"coordinates":[2.5714480877,39.5352134705],"type":"Point"}
}