{
  "type": "Feature",
  "properties": {
    "addr:full":"Calle de Federico Moreno Torroba, 9 Madrid Madrid 28007",
    "addr:housenumber":"9",
    "addr:postcode":"madrid;28007",
    "addr:street":"Calle De Federico Moreno Torroba",
    "iso:country":"ES",
    "sg:address":"Calle de Federico Moreno Torroba, 9",
    "sg:city":"Madrid",
    "sg:orig_category":"Asesor\u00cda Fiscal Y Jur\u00cddica",
    "sg:phone":"+34 915 01 01 91",
    "sg:postcode":"28007",
    "sg:province":"Madrid",
    "wof:name":"Asesoria Integral De Negocios S.l.",
    "wof:placetype":"venue"
},
  "geometry": {"coordinates":[-3.667222023,40.4053268433],"type":"Point"}
}