{
  "type": "Feature",
  "properties": {
    "iso:country":"ES",
    "sg:address":"Calle de Calvario, 26",
    "sg:city":"Jumilla",
    "sg:orig_category":"Zapatos (al Por Menor)",
    "sg:phone":"+34 968 78 02 20",
    "sg:postcode":"30520",
    "sg:province":"Murcia",
    "wof:name":"Esteve Garcia Jose",
    "wof:placetype":"venue"
},
  "geometry": {"coordinates":[-1.3307837248,38.4766769409],"type":"Point"}
}