{
  "type": "Feature",
  "properties": {
    "iso:country":"ES",
    "sg:address":"C/ Picapedrers, S/n",
    "sg:city":"Manacor",
    "sg:orig_category":"Servicio De Salud",
    "sg:phone":"+34 971 84 38 52",
    "sg:postcode":"07500",
    "sg:province":"Islas Baleares",
    "sg:website":"www.coinsaguel com",
    "wof:name":"Coinsa",
    "wof:placetype":"venue"
},
  "geometry": {"coordinates":[3.185847044,39.5719146729],"type":"Point"}
}