{
  "type": "Feature",
  "properties": {
    "addr:full":"Calle de Manuel Vargas, 5 Malaga M\u00e1laga 29004",
    "addr:housenumber":"5",
    "addr:postcode":"29004",
    "addr:street":"Calle De Manuel Vargas;Ma\u0301Laga",
    "iso:country":"ES",
    "sg:address":"Calle de Manuel Vargas, 5",
    "sg:city":"Malaga",
    "sg:orig_category":"Peluquer\u00cdas, Peluquer\u00cda Mixta",
    "sg:phone":"+34 952 34 33 94",
    "sg:postcode":"29004",
    "sg:province":"M\u00e1laga",
    "wof:name":"Eden Sonfil S.c.",
    "wof:placetype":"venue"
},
  "geometry": {"coordinates":[-4.4474611282,36.7004737854],"type":"Point"}
}