{
  "type": "Feature",
  "properties": {
    "iso:country":"ES",
    "sg:address":"Ctra La Concepcion, S/n",
    "sg:city":"Almu\u00f1ecar",
    "sg:orig_category":"Pintura, Barniz, Productos Asimilables (fabricaci\u00d3n, Al Por Mayor)",
    "sg:phone":"+34 958 88 07 25",
    "sg:postcode":"18690",
    "sg:province":"Granada",
    "wof:name":"Pinturas Menape S.l.",
    "wof:placetype":"venue"
},
  "geometry": {"coordinates":[-3.6882688999,36.736743927],"type":"Point"}
}