{
  "type": "Feature",
  "properties": {
    "iso:country":"ES",
    "sg:address":"Avda Jose Manuel Valles, 35",
    "sg:city":"Marbella",
    "sg:orig_category":"Farmacias",
    "sg:phone":"+34 952 82 91 93",
    "sg:postcode":"29600",
    "sg:province":"M\u00e1laga",
    "wof:name":"Sanchez Garcia Fernando",
    "wof:placetype":"venue"
},
  "geometry": {"coordinates":[-4.8722290993,36.5092163086],"type":"Point"}
}