{
  "type": "Feature",
  "properties": {
    "addr:full":"C/ Pou Florit, 3 Porreres Islas Baleares 07260",
    "addr:housenumber":"3",
    "addr:postcode":"07260",
    "addr:street":"C / Pou Florit",
    "iso:country":"ES",
    "sg:address":"C/ Pou Florit, 3",
    "sg:city":"Porreres",
    "sg:orig_category":"Quincaller\u00cda (al Por Menor)",
    "sg:phone":"+34 971 64 72 44",
    "sg:postcode":"07260",
    "sg:province":"Islas Baleares",
    "wof:name":"Mora Salom Mateo",
    "wof:placetype":"venue"
},
  "geometry": {"coordinates":[3.0229899883,39.516582489],"type":"Point"}
}