{
  "type": "Feature",
  "properties": {
    "iso:country":"ES",
    "sg:address":"Calle de Doctor Nacher, 54",
    "sg:city":"Chiva",
    "sg:orig_category":"Bisuter\u00cda, Joyer\u00cda, Relojer\u00cda (al Por Menor)",
    "sg:phone":"+34 962 52 28 50",
    "sg:postcode":"46370",
    "sg:province":"Valencia",
    "wof:name":"Bellver Atienza Jose Luis",
    "wof:placetype":"venue"
},
  "geometry": {"coordinates":[-0.7168859839,39.4713020325],"type":"Point"}
}