{
  "type": "Feature",
  "properties": {
    "addr:full":"Carrer de Sant Jaume, 16 Alcover Tarragona 43460",
    "addr:housenumber":"16",
    "addr:postcode":"43460",
    "addr:street":"Carrer De Sant Jaume",
    "iso:country":"ES",
    "sg:address":"Carrer de Sant Jaume, 16",
    "sg:city":"Alcover",
    "sg:orig_category":"Fabricaci\u00d3n De Peines Y De Accesorios De Peluquer\u00cda",
    "sg:phone":"+34 977 84 64 44",
    "sg:postcode":"43460",
    "sg:province":"Tarragona",
    "wof:name":"Catalana De Peluqueria Y Complementos S.l",
    "wof:placetype":"venue"
},
  "geometry": {"coordinates":[1.1708170176,41.2627906799],"type":"Point"}
}