{
  "type": "Feature",
  "properties": {
    "iso:country":"ES",
    "sg:address":"Calle de Casta\u00d1os, 32",
    "sg:city":"Alacant",
    "sg:orig_category":"Abogados",
    "sg:phone":"+34 965 20 76 42",
    "sg:postcode":"03001",
    "sg:province":"Alicante",
    "wof:name":"Alameda Giner Maria Dolores",
    "wof:placetype":"venue"
},
  "geometry": {"coordinates":[-0.4856694043,38.345905304],"type":"Point"}
}