{
  "type": "Feature",
  "properties": {
    "iso:country":"ES",
    "sg:address":"Calle de Mecanicos (los), S/n",
    "sg:city":"Chiclana De La Frontera",
    "sg:orig_category":"Molduras, Junquillos, Listones Y Molduras Perforadas",
    "sg:phone":"+34 956 53 59 20",
    "sg:postcode":"11130",
    "sg:province":"C\u00e1diz",
    "wof:name":"Gonzalez Avecilla Juana Maria",
    "wof:placetype":"venue"
},
  "geometry": {"coordinates":[-6.1400589943,36.4108657837],"type":"Point"}
}