{
  "type": "Feature",
  "properties": {
    "iso:country":"ES",
    "sg:address":"Ctra. B-motril, Km. 0000,0",
    "sg:city":"Bailen",
    "sg:orig_category":"Quincaller\u00cda (al Por Menor)",
    "sg:phone":"+34 953 67 09 54",
    "sg:postcode":"23710",
    "sg:province":"Ja\u00e9n",
    "wof:name":"Almacenes De Ferreteria Veracruz S.l.",
    "wof:placetype":"venue"
},
  "geometry": {"coordinates":[-3.763825655,38.1087646484],"type":"Point"}
}