{
  "type": "Feature",
  "properties": {
    "iso:country":"ES",
    "sg:address":"Ctra Agramunt, 14",
    "sg:city":"Artesa Segre",
    "sg:orig_category":"Estancos",
    "sg:phone":"+34 973 40 00 82",
    "sg:postcode":"25730",
    "sg:province":"Lleida",
    "wof:name":"Masana Rodriguez Miguel",
    "wof:placetype":"venue"
},
  "geometry": {"coordinates":[1.0475059748,41.895236969],"type":"Point"}
}