{
  "type": "Feature",
  "properties": {
    "addr:full":"Calle de Cazalilla, S/n Jaen Ja\u00e9n 23009",
    "addr:housenumber":"s / n;jae\u0301n",
    "addr:postcode":"23009",
    "addr:street":"Calle De Cazalilla",
    "iso:country":"ES",
    "sg:address":"Calle de Cazalilla, S/n",
    "sg:city":"Jaen",
    "sg:orig_category":"Aceros Inoxidables",
    "sg:phone":"+34 953 28 40 56",
    "sg:postcode":"23009",
    "sg:province":"Ja\u00e9n",
    "sg:website":"www.gruposopena.com",
    "wof:name":"Hierros Jativa S. L.",
    "wof:placetype":"venue"
},
  "geometry": {"coordinates":[-3.7885160446,37.7965965271],"type":"Point"}
}