{
  "type": "Feature",
  "properties": {
    "iso:country":"ES",
    "sg:address":"Calle de San Jose De Calasanz, 29",
    "sg:city":"Zaragoza",
    "sg:orig_category":"Promotores Constructores",
    "sg:phone":"+34 976 41 04 22",
    "sg:postcode":"50008",
    "sg:province":"Zaragoza",
    "wof:name":"Construcciones Artecho S.l.",
    "wof:placetype":"venue"
},
  "geometry": {"coordinates":[-0.8749909997,41.6370658875],"type":"Point"}
}