{
  "type": "Feature",
  "properties": {
    "addr:full":"Carr Guell, 2 Girona Girona 17005",
    "addr:housenumber":"2",
    "addr:postcode":"17005",
    "addr:street":"Carr Guell",
    "iso:country":"ES",
    "sg:address":"Carr Guell, 2",
    "sg:city":"Girona",
    "sg:orig_category":"Discotecas Y Salas De Baile",
    "sg:phone":"+34 972 20 14 39",
    "sg:postcode":"17005",
    "sg:province":"Girona",
    "wof:name":"Complex D'oci S.l.",
    "wof:placetype":"venue"
},
  "geometry": {"coordinates":[2.8153469563,41.9833602905],"type":"Point"}
}