{
  "type": "Feature",
  "properties": {
    "addr:full":"Calle de Ronda Del Ferrocarril, 26 Miranda Ebro Burgos 09200",
    "addr:housenumber":"26",
    "addr:postcode":"09200",
    "addr:street":"Calle De Ronda Del Ferrocarril",
    "iso:country":"ES",
    "sg:address":"Calle de Ronda Del Ferrocarril, 26",
    "sg:city":"Miranda Ebro",
    "sg:orig_category":"Ense\u00d1anza: Idiomas",
    "sg:phone":"+34 947 33 22 93",
    "sg:postcode":"09200",
    "sg:province":"Burgos",
    "wof:name":"Alfonso Tojeiro Jose Vicente",
    "wof:placetype":"venue"
},
  "geometry": {"coordinates":[-2.945826292,42.6884346008],"type":"Point"}
}