{
  "type": "Feature",
  "properties": {
    "iso:country":"ES",
    "sg:address":"Camino Del Rodon, S/n",
    "sg:city":"Campohermoso",
    "sg:orig_category":"Escotaduras, Torneados",
    "sg:phone":"+34 950 38 58 52",
    "sg:postcode":"04110",
    "sg:province":"Almer\u00eda",
    "wof:name":"Gruas Y Talleres Capel S.l.",
    "wof:placetype":"venue"
},
  "geometry": {"coordinates":[-2.1327490807,36.9377212524],"type":"Point"}
}