{
  "type": "Feature",
  "properties": {
    "iso:country":"ES",
    "sg:address":"Calle de Virgen De Los Reyes, 47",
    "sg:city":"Carmona",
    "sg:orig_category":"Institutos De Belleza",
    "sg:phone":"+34 954 19 03 89",
    "sg:postcode":"41410",
    "sg:province":"Sevilla",
    "wof:name":"Barrera Cabello Ana Belen",
    "wof:placetype":"venue"
},
  "geometry": {"coordinates":[-5.6469287872,37.4658203125],"type":"Point"}
}