{
  "type": "Feature",
  "properties": {
    "iso:country":"ES",
    "sg:address":"Ctra Nacional Ii, 6",
    "sg:city":"Jonquera",
    "sg:orig_category":"Reparaciones Y Remolcado De Veh\u00cdculos",
    "sg:phone":"+34 972 55 42 97",
    "sg:postcode":"17700",
    "sg:province":"Girona",
    "wof:name":"Grupo Auto Gruas Nadal S. L.",
    "wof:placetype":"venue"
},
  "geometry": {"coordinates":[2.8718750477,42.4159698486],"type":"Point"}
}