{
  "type": "Feature",
  "properties": {
    "addr:full":"Avda Atlantida, 8 Palafolls Barcelona 08389",
    "addr:housenumber":"8",
    "addr:postcode":"08389",
    "addr:street":"Avda Atlantida",
    "iso:country":"ES",
    "sg:address":"Avda Atlantida, 8",
    "sg:city":"Palafolls",
    "sg:orig_category":"Tiendas De Grano, Frutas Y Legumbres Secas (al Por Menor)",
    "sg:phone":"+34 937 65 22 34",
    "sg:postcode":"08389",
    "sg:province":"Barcelona",
    "wof:name":"Frit-ravich S.l.",
    "wof:placetype":"venue"
},
  "geometry": {"coordinates":[2.7503809929,41.6594619751],"type":"Point"}
}