{
  "type": "Feature",
  "properties": {
    "addr:full":"Ctra Tirig, Km. 0001,0 Sant Mateu Castell\u00f3n 12170",
    "addr:postcode":"12170",
    "addr:street":"Ctra Tirig Km. 0001,0;Castello\u0301N",
    "iso:country":"ES",
    "sg:address":"Ctra Tirig, Km. 0001,0",
    "sg:city":"Sant Mateu",
    "sg:orig_category":"Mec\u00c1nico Del Autom\u00d3vil",
    "sg:phone":"+34 964 41 64 93",
    "sg:postcode":"12170",
    "sg:province":"Castell\u00f3n",
    "wof:name":"Reparauto David S.l.",
    "wof:placetype":"venue"
},
  "geometry": {"coordinates":[0.1785899997,40.4668502808],"type":"Point"}
}