{
  "type": "Feature",
  "properties": {
    "iso:country":"ES",
    "sg:address":"Calle de Usandizaga, 18",
    "sg:city":"Donostia-san Sebastian",
    "sg:orig_category":"Deportes Y Programas De Aventura",
    "sg:phone":"+34 943 29 35 20",
    "sg:postcode":"20002",
    "sg:province":"Guip\u00f9zcoa",
    "wof:name":"Izadi Artean S.l.",
    "wof:placetype":"venue"
},
  "geometry": {"coordinates":[-1.9768509865,43.3236465454],"type":"Point"}
}