{
  "type": "Feature",
  "properties": {
    "iso:country":"ES",
    "sg:address":"Calle de Arturo Soria, 243",
    "sg:city":"Madrid",
    "sg:orig_category":"Fabricaci\u00d3n, Instalaci\u00d3n De Escaleras",
    "sg:phone":"+34 913 59 22 26",
    "sg:postcode":"28033",
    "sg:province":"Madrid",
    "wof:name":"Proteccion Barandillasy Redes S.l.",
    "wof:placetype":"venue"
},
  "geometry": {"coordinates":[-3.6656177044,40.464805603],"type":"Point"}
}