{
  "type": "Feature",
  "properties": {
    "addr:full":"Calle de Francisco Pacheco, 17 Malaga M\u00e1laga 29004",
    "addr:housenumber":"17",
    "addr:postcode":"29004",
    "addr:street":"Calle De Francisco Pacheco;Ma\u0301Laga",
    "iso:country":"ES",
    "sg:address":"Calle de Francisco Pacheco, 17",
    "sg:city":"Malaga",
    "sg:classifiers":[
        {
            "category":"Professional",
            "subcategory":"Management & Consulting",
            "type":"Services"
        }
    ],
    "sg:phone":"+34 952 23 92 04",
    "sg:postcode":"29004",
    "sg:province":"M\u00e1laga",
    "sg:tags":[
        "asesor\u00cda",
        "en",
        "marketing"
    ],
    "wof:name":"Rodriguez Cabrera Alberto",
    "wof:placetype":"venue"
},
  "geometry": {"coordinates":[-4.4484109879,36.6917724609],"type":"Point"}
}