{
  "type": "Feature",
  "properties": {
    "iso:country":"ES",
    "sg:address":"Calle de Mayor, 177",
    "sg:city":"Alcantarilla",
    "sg:orig_category":"Comercio De Piezas De Recambio Y De Accesorios De Veh\u00cdculos, Veh\u00cdculos Industriales",
    "sg:phone":"+34 968 80 17 93",
    "sg:postcode":"30820",
    "sg:province":"Murcia",
    "wof:name":"Jimenez Hita Jose Antonio",
    "wof:placetype":"venue"
},
  "geometry": {"coordinates":[-1.218203187,37.967010498],"type":"Point"}
}