{
  "type": "Feature",
  "properties": {
    "addr:full":"Tellerigaina Kalea, 18 Larrekoetxe Guip\u00f9zcoa 20160",
    "addr:housenumber":"18",
    "addr:postcode":"20160",
    "addr:street":"Tellerigaina Kalea;Guipu\u0300Zcoa",
    "iso:country":"ES",
    "sg:address":"Tellerigaina Kalea, 18",
    "sg:city":"Larrekoetxe",
    "sg:orig_category":"Electricidad: Instaladores",
    "sg:phone":"+34 943 37 21 84",
    "sg:postcode":"20160",
    "sg:province":"Guip\u00f9zcoa",
    "wof:name":"Vazquez Lopez Jose Antonio",
    "wof:placetype":"venue"
},
  "geometry": {"coordinates":[-2.020414114,43.2698173523],"type":"Point"}
}