{
  "type": "Feature",
  "properties": {
    "iso:country":"ES",
    "sg:address":"Avda Asturias, 17",
    "sg:city":"Villablino",
    "sg:orig_category":"Bazares, Art\u00cdculos De Limpieza Y De Cocina (al Por Menor)",
    "sg:phone":"+34 987 47 13 11",
    "sg:postcode":"24100",
    "sg:province":"Le\u00f3n",
    "wof:name":"Garcia Menendez Santiago",
    "wof:placetype":"venue"
},
  "geometry": {"coordinates":[-6.319314003,42.9403419495],"type":"Point"}
}