{
  "type": "Feature",
  "properties": {
    "iso:country":"ES",
    "sg:address":"Calle de Fernan Gonzalez, 31",
    "sg:city":"Madrid",
    "sg:orig_category":"Animales (al Por Menor)",
    "sg:phone":"+34 915 04 65 73",
    "sg:postcode":"28009",
    "sg:province":"Madrid",
    "wof:name":"Carre\u00f1o Arnal Jose Ricardo",
    "wof:placetype":"venue"
},
  "geometry": {"coordinates":[-3.6741979122,40.4219284058],"type":"Point"}
}