{
  "type": "Feature",
  "properties": {
    "addr:full":"Avda Denia, 47 Alacant Alicante 03013",
    "addr:housenumber":"47",
    "addr:postcode":"03013",
    "addr:street":"Avda Denia",
    "iso:country":"ES",
    "sg:address":"Avda Denia, 47",
    "sg:city":"Alacant",
    "sg:orig_category":"Ambulancias",
    "sg:phone":"+34 965 15 33 33",
    "sg:postcode":"03013",
    "sg:province":"Alicante",
    "wof:name":"Ambumed S.l.",
    "wof:placetype":"venue"
},
  "geometry": {"coordinates":[-0.4702349007,38.3574066162],"type":"Point"}
}