{
  "type": "Feature",
  "properties": {
    "iso:country":"ES",
    "sg:address":"Calle de Cristobal Bordiu, 10",
    "sg:city":"Madrid",
    "sg:orig_category":"Supermercados Y Hipermercados",
    "sg:phone":"+34 914 42 93 99",
    "sg:postcode":"28003",
    "sg:province":"Madrid",
    "wof:name":"Comercial Superma S. A",
    "wof:placetype":"venue"
},
  "geometry": {"coordinates":[-3.702958107,40.4432106018],"type":"Point"}
}