{
  "type": "Feature",
  "properties": {
    "addr:full":"Calle de Rabida, 3 Alcala Guadaira Sevilla 41500",
    "addr:housenumber":"3",
    "addr:postcode":"41500",
    "addr:street":"Calle De Rabida",
    "iso:country":"ES",
    "sg:address":"Calle de Rabida, 3",
    "sg:city":"Alcala Guadaira",
    "sg:orig_category":"Artes Gr\u00c1ficas, Artes Pl\u00c1sticas: Material Y Suministros (al Por Menor)",
    "sg:phone":"+34 955 69 96 47",
    "sg:postcode":"41500",
    "sg:province":"Sevilla",
    "wof:name":"Bellon Rodriguez Juan",
    "wof:placetype":"venue"
},
  "geometry": {"coordinates":[-5.8562641144,37.3282051086],"type":"Point"}
}