{
  "type": "Feature",
  "properties": {
    "addr:full":"Calle de Jose Maluquer, S/n Sevilla Sevilla 41008",
    "addr:housenumber":"s / n",
    "addr:postcode":"41008",
    "addr:street":"Calle De Jose Maluquer",
    "iso:country":"ES",
    "sg:address":"Calle de Jose Maluquer, S/n",
    "sg:city":"Sevilla",
    "sg:orig_category":"Ense\u00d1anza Variada",
    "sg:phone":"+34 954 35 31 11",
    "sg:postcode":"41008",
    "sg:province":"Sevilla",
    "wof:name":"Sistemas Y Fomentos Tecnologicos S.a.",
    "wof:placetype":"venue"
},
  "geometry": {"coordinates":[-5.9802489281,37.4038085938],"type":"Point"}
}