{
  "type": "Feature",
  "properties": {
    "iso:country":"ES",
    "sg:address":"Pase Virgen Del Puerto, 7",
    "sg:city":"Madrid",
    "sg:orig_category":"Arquitectos",
    "sg:phone":"+34 913 66 20 32",
    "sg:postcode":"28005",
    "sg:province":"Madrid",
    "wof:name":"Fernandez Gonzalez Ramon",
    "wof:placetype":"venue"
},
  "geometry": {"coordinates":[-3.7208929062,40.4133758545],"type":"Point"}
}