{
  "type": "Feature",
  "properties": {
    "addr:full":"Psaj Dulcinea Del Toboso, 1 Ciudad Real Ciudad Real 13001",
    "addr:postcode":"13001",
    "iso:country":"ES",
    "sg:address":"Psaj Dulcinea Del Toboso, 1",
    "sg:city":"Ciudad Real",
    "sg:orig_category":"Molduras, Junquillos, Listones Y Molduras Perforadas",
    "sg:phone":"+34 926 25 07 95",
    "sg:postcode":"13001",
    "sg:province":"Ciudad Real",
    "wof:name":"Reina Sobrino Lucio",
    "wof:placetype":"venue"
},
  "geometry": {"coordinates":[-3.9275290966,38.9832458496],"type":"Point"}
}