{
  "type": "Feature",
  "properties": {
    "addr:full":"Celsa, 17 Garrapinillos Zaragoza 50197",
    "addr:housenumber":"17",
    "addr:postcode":"50197",
    "addr:street":"Celsa",
    "iso:country":"ES",
    "sg:address":"Celsa, 17",
    "sg:city":"Garrapinillos",
    "sg:orig_category":"Aparatos, Material Y Suministros Para Laboratorios",
    "sg:phone":"+34 976 53 67 00",
    "sg:postcode":"50197",
    "sg:province":"Zaragoza",
    "wof:name":"Sistemas Tecnologicos Avanzados S.a.",
    "wof:placetype":"venue"
},
  "geometry": {"coordinates":[-1.0269140005,41.6842803955],"type":"Point"}
}