{
  "type": "Feature",
  "properties": {
    "iso:country":"ES",
    "sg:address":"Avda Luis Bu\u00d1uel, 36",
    "sg:city":"Roquetas Mar",
    "sg:orig_category":"Empresarios",
    "sg:phone":"+34 950 32 03 32",
    "sg:postcode":"04740",
    "sg:province":"Almer\u00eda",
    "wof:name":"Iba\u00f1ez Lopez Diego",
    "wof:placetype":"venue"
},
  "geometry": {"coordinates":[-2.6173191071,36.7658004761],"type":"Point"}
}