{
  "type": "Feature",
  "properties": {
    "iso:country":"ES",
    "sg:address":"Carr Nostra Sra Del Carme, 1",
    "sg:city":"Lleida",
    "sg:orig_category":"Empresas De Pintura Y Revestimientos",
    "sg:phone":"+34 973 20 27 64",
    "sg:postcode":"25001",
    "sg:province":"Lleida",
    "wof:name":"Palacios Agustin Delfin",
    "wof:placetype":"venue"
},
  "geometry": {"coordinates":[0.6419090033,41.60364151],"type":"Point"}
}