{
  "type": "Feature",
  "properties": {
    "iso:country":"ES",
    "sg:address":"Calle de Republica De Costa Rica, 3",
    "sg:city":"Campo Criptana",
    "sg:orig_category":"Peluquer\u00cdas, Peluquer\u00cda Mixta",
    "sg:phone":"+34 926 56 14 81",
    "sg:postcode":"13610",
    "sg:province":"Ciudad Real",
    "wof:name":"Gonzalez Monje Maria Isabel",
    "wof:placetype":"venue"
},
  "geometry": {"coordinates":[-3.127163887,39.3970870972],"type":"Point"}
}