{
  "type": "Feature",
  "properties": {
    "addr:full":"Calle de Akilino Arriola, 6 Sopelana Vizcaya 48600",
    "addr:housenumber":"6",
    "addr:postcode":"48600",
    "addr:street":"Calle De Akilino Arriola",
    "iso:country":"ES",
    "sg:address":"Calle de Akilino Arriola, 6",
    "sg:city":"Sopelana",
    "sg:orig_category":"Bisuter\u00cda, Joyer\u00cda, Relojer\u00cda (al Por Menor)",
    "sg:phone":"+34 946 76 18 59",
    "sg:postcode":"48600",
    "sg:province":"Vizcaya",
    "wof:name":"Jesus Maria Casado Baroja",
    "wof:placetype":"venue"
},
  "geometry": {"coordinates":[-2.982408762,43.3805656433],"type":"Point"}
}