{
  "type": "Feature",
  "properties": {
    "iso:country":"ES",
    "sg:address":"Avda Doctor Gadea, 23",
    "sg:city":"Alacant",
    "sg:orig_category":"M\u00c1quinas De Coser Y De Hacer Punto (al Por Mayor)",
    "sg:phone":"+34 965 12 67 17",
    "sg:postcode":"03003",
    "sg:province":"Alicante",
    "sg:website":"www.valentinsachez.com",
    "wof:name":"Valentin Sanchez Descans S.l.",
    "wof:placetype":"venue"
},
  "geometry": {"coordinates":[-0.4885689914,38.3427886963],"type":"Point"}
}