{
  "type": "Feature",
  "properties": {
    "iso:country":"ES",
    "sg:address":"Calle de Jardines, 26",
    "sg:city":"Chiclana De La Frontera",
    "sg:orig_category":"Empresas De Vigilancia, Guardia Y Protecci\u00d3n",
    "sg:phone":"+34 956 53 83 45",
    "sg:postcode":"11130",
    "sg:province":"C\u00e1diz",
    "wof:name":"Comunidad De Propietarios Ed. Santa Oria",
    "wof:placetype":"venue"
},
  "geometry": {"coordinates":[-6.1421279907,36.4194221497],"type":"Point"}
}