{
  "type": "Feature",
  "properties": {
    "addr:full":"Calle de Viacampo, 5 Calahorra La Rioja 26500",
    "addr:housenumber":"5",
    "addr:postcode":"26500",
    "addr:street":"Calle De Viacampo",
    "iso:country":"ES",
    "sg:address":"Calle de Viacampo, 5",
    "sg:city":"Calahorra",
    "sg:orig_category":"Mec\u00c1nico Del Autom\u00d3vil",
    "sg:phone":"+34 941 13 29 53",
    "sg:postcode":"26500",
    "sg:province":"La Rioja",
    "wof:name":"Cruz Mayor Jesus",
    "wof:placetype":"venue"
},
  "geometry": {"coordinates":[-1.9584399462,42.3094024658],"type":"Point"}
}