{
  "type": "Feature",
  "properties": {
    "iso:country":"ES",
    "sg:address":"Ctra Cami D'albalat, S/n",
    "sg:city":"Alzira",
    "sg:orig_category":"Ropa Para Se\u00d1oras Y Caballeros (al Por Menor)",
    "sg:phone":"+34 962 41 49 02",
    "sg:postcode":"46600",
    "sg:province":"Valencia",
    "wof:name":"New Orkan S.l.",
    "wof:placetype":"venue"
},
  "geometry": {"coordinates":[-0.4193289876,39.1732788086],"type":"Point"}
}