{
  "type": "Feature",
  "properties": {
    "iso:country":"ES",
    "sg:address":"Cno Vell D'oliva, S/n",
    "sg:city":"Gandia",
    "sg:orig_category":"Panader\u00cdas, Panader\u00cdas",
    "sg:phone":"+34 962 87 56 32",
    "sg:postcode":"46700",
    "sg:province":"Valencia",
    "wof:name":"Dulcesa S.a.",
    "wof:placetype":"venue"
},
  "geometry": {"coordinates":[-0.176109001,38.9623908997],"type":"Point"}
}