{
  "type": "Feature",
  "properties": {
    "addr:full":"Calle de Comercio, 52 Sevilla Sevilla 41007",
    "addr:housenumber":"52",
    "addr:postcode":"41007",
    "addr:street":"Calle De Comercio",
    "iso:country":"ES",
    "sg:address":"Calle de Comercio, 52",
    "sg:city":"Sevilla",
    "sg:orig_category":"Bater\u00cdas",
    "sg:phone":"+34 954 67 25 94",
    "sg:postcode":"41007",
    "sg:province":"Sevilla",
    "wof:name":"Sociedad Espa\u00f1ola Del Acumulador Tudor S. A.",
    "wof:placetype":"venue"
},
  "geometry": {"coordinates":[-5.9495191574,37.3927955627],"type":"Point"}
}