{
  "type": "Feature",
  "properties": {
    "addr:full":"Pase Herrera De, 10 Donostia-san Sebastian Guip\u00f9zcoa 20017",
    "addr:housenumber":"10",
    "addr:postcode":"20017",
    "iso:country":"ES",
    "sg:address":"Pase Herrera De, 10",
    "sg:city":"Donostia-san Sebastian",
    "sg:orig_category":"Soldadura Y Recortado Con Soplete",
    "sg:phone":"+34 943 39 16 29",
    "sg:postcode":"20017",
    "sg:province":"Guip\u00f9zcoa",
    "wof:name":"Oxigraf S. A.",
    "wof:placetype":"venue"
},
  "geometry": {"coordinates":[-1.9374910593,43.3188514709],"type":"Point"}
}