{
  "type": "Feature",
  "properties": {
    "addr:full":"Avda Jose Antonio, 42 Miraflores De La Sierra Madrid 28792",
    "addr:housenumber":"42",
    "addr:postcode":"28792",
    "addr:street":"Avda Jose Antonio",
    "iso:country":"ES",
    "sg:address":"Avda Jose Antonio, 42",
    "sg:city":"Miraflores De La Sierra",
    "sg:orig_category":"Cr\u00cda De Bovinos",
    "sg:phone":"+34 918 44 50 88",
    "sg:postcode":"28792",
    "sg:province":"Madrid",
    "wof:name":"Navalhoyo Ganadera S.l.",
    "wof:placetype":"venue"
},
  "geometry": {"coordinates":[-3.7733290195,40.8115959167],"type":"Point"}
}