{
  "type": "Feature",
  "properties": {
    "addr:full":"Avda Belgica, 57 Leganes Madrid 28916",
    "addr:housenumber":"57",
    "addr:postcode":"28916",
    "addr:street":"Avda Belgica",
    "iso:country":"ES",
    "sg:address":"Avda Belgica, 57",
    "sg:city":"Leganes",
    "sg:orig_category":"Ense\u00d1ante, Direcci\u00d3n",
    "sg:phone":"+34 916 80 02 30",
    "sg:postcode":"28916",
    "sg:province":"Madrid",
    "wof:name":"Olmos Berrocoso Jose Manuel",
    "wof:placetype":"venue"
},
  "geometry": {"coordinates":[-3.7396030426,40.3370437622],"type":"Point"}
}