{
  "type": "Feature",
  "properties": {
    "iso:country":"ES",
    "sg:address":"Calle de Berzocana, 16",
    "sg:city":"Merida",
    "sg:orig_category":"Ense\u00d1anza: Profesiones Art\u00cdsticas",
    "sg:phone":"+34 924 31 05 94",
    "sg:postcode":"06800",
    "sg:province":"Badajoz",
    "wof:name":"Molinero Villase\u00f1or Maria Luisa",
    "wof:placetype":"venue"
},
  "geometry": {"coordinates":[-6.3436331749,38.9171142578],"type":"Point"}
}