{
  "type": "Feature",
  "properties": {
    "addr:full":"Calle de Solana Blanca, 1 Rozas De Madrid Madrid 28230",
    "addr:housenumber":"1",
    "addr:postcode":"28230",
    "addr:street":"Calle De Solana Blanca",
    "iso:country":"ES",
    "sg:address":"Calle de Solana Blanca, 1",
    "sg:city":"Rozas De Madrid",
    "sg:orig_category":"Inmobiliaria (agencias)",
    "sg:phone":"+34 917 10 33 57",
    "sg:postcode":"28230",
    "sg:province":"Madrid",
    "wof:name":"Bravo San Juan S.l.",
    "wof:placetype":"venue"
},
  "geometry": {"coordinates":[-3.8730649948,40.4924697876],"type":"Point"}
}