{
  "type": "Feature",
  "properties": {
    "addr:full":"Calle de Carril San Diego, 37 Sanlucar De Barrameda C\u00e1diz 11540",
    "addr:housenumber":"37",
    "addr:postcode":"11540",
    "addr:street":"Calle De Carril;Diego;Ca\u0301Diz",
    "iso:country":"ES",
    "sg:address":"Calle de Carril San Diego, 37",
    "sg:city":"Sanlucar De Barrameda",
    "sg:orig_category":"Papeler\u00cdas, Librer\u00cdas",
    "sg:phone":"+34 956 36 91 31",
    "sg:postcode":"11540",
    "sg:province":"C\u00e1diz",
    "wof:name":"Alcon Atienza Juan",
    "wof:placetype":"venue"
},
  "geometry": {"coordinates":[-6.3511605263,36.779586792],"type":"Point"}
}