{
  "type": "Feature",
  "properties": {
    "addr:full":"Calle de Alvaro Caballero, 19 Madrid Madrid 28023",
    "addr:housenumber":"19",
    "addr:postcode":"madrid;28023",
    "addr:street":"Calle De Alvaro Caballero",
    "iso:country":"ES",
    "sg:address":"Calle de Alvaro Caballero, 19",
    "sg:city":"Madrid",
    "sg:orig_category":"Agencias Y Asesores De Publicidad",
    "sg:phone":"+34 913 07 73 09",
    "sg:postcode":"28023",
    "sg:province":"Madrid",
    "wof:name":"Victor Steinberg Y Asociados S.l.",
    "wof:placetype":"venue"
},
  "geometry": {"coordinates":[-3.8340198994,40.4729957581],"type":"Point"}
}