{
  "type": "Feature",
  "properties": {
    "addr:full":"Carrer de Pedraforca, 2 Hospitalet Llobregat Barcelona 08905",
    "addr:housenumber":"2",
    "addr:postcode":"08905",
    "addr:street":"Carrer De Pedraforca",
    "iso:country":"ES",
    "sg:address":"Carrer de Pedraforca, 2",
    "sg:city":"Hospitalet Llobregat",
    "sg:orig_category":"Guarder\u00cdas",
    "sg:phone":"+34 933 33 74 96",
    "sg:postcode":"08905",
    "sg:province":"Barcelona",
    "wof:name":"Blanco Lapesa Maria Gloria",
    "wof:placetype":"venue"
},
  "geometry": {"coordinates":[2.1117920876,41.3739242554],"type":"Point"}
}