{
  "type": "Feature",
  "properties": {
    "addr:full":"Rua Benito Corbal, 32 Pontevedra Pontevedra 36001",
    "addr:housenumber":"32",
    "addr:postcode":"36001",
    "addr:street":"Rua Benito Corbal",
    "iso:country":"ES",
    "sg:address":"Rua Benito Corbal, 32",
    "sg:city":"Pontevedra",
    "sg:orig_category":"Caf\u00c9s, Bares, Cervecer\u00cdas",
    "sg:phone":"+34 986 86 18 65",
    "sg:postcode":"36001",
    "sg:province":"Pontevedra",
    "wof:name":"Restauracion Rias Bajas S.l.",
    "wof:placetype":"venue"
},
  "geometry": {"coordinates":[-8.640253067,42.4302101135],"type":"Point"}
}