{
  "type": "Feature",
  "properties": {
    "iso:country":"ES",
    "sg:address":"Ctra Sagunto-burgos, Km. 0022,0",
    "sg:city":"Sot De Ferrer",
    "sg:orig_category":"Droguer\u00cdas (al Por Mayor)",
    "sg:phone":"+34 964 13 50 40",
    "sg:postcode":"12489",
    "sg:province":"Castell\u00f3n",
    "wof:name":"Comercial Aparacio Bada S.l.",
    "wof:placetype":"venue"
},
  "geometry": {"coordinates":[-0.4018499851,39.7978515625],"type":"Point"}
}