{
  "type": "Feature",
  "properties": {
    "iso:country":"ES",
    "sg:address":"Rond Migjorn, 64",
    "sg:city":"Llucmajor",
    "sg:orig_category":"Inmobiliaria (agencias)",
    "sg:phone":"+34 971 66 03 78",
    "sg:postcode":"07620",
    "sg:province":"Islas Baleares",
    "wof:name":"Mallorca Habitat Immobilien S.l.",
    "wof:placetype":"venue"
},
  "geometry": {"coordinates":[2.8869431019,39.4866523743],"type":"Point"}
}