{
  "type": "Feature",
  "properties": {
    "iso:country":"ES",
    "sg:address":"Carr Son Moner, S/n",
    "sg:city":"Andratx",
    "sg:orig_category":"Internados & Ense\u00d1anza Privada",
    "sg:phone":"+34 971 23 64 35",
    "sg:postcode":"07150",
    "sg:province":"Islas Baleares",
    "wof:name":"Casa Ramon Lull Andratx Agustinas Hermanas Del Amparo",
    "wof:placetype":"venue"
},
  "geometry": {"coordinates":[2.4224550724,39.5749893188],"type":"Point"}
}