{
  "type": "Feature",
  "properties": {
    "addr:full":"Carrer de Diputacio, 162 Barcelona Barcelona 08011",
    "addr:housenumber":"162",
    "addr:postcode":"08011",
    "addr:street":"Carrer De Diputacio",
    "iso:country":"ES",
    "sg:address":"Carrer de Diputacio, 162",
    "sg:city":"Barcelona",
    "sg:orig_category":"Bricolaje, Herramientas (al Por Menor)",
    "sg:phone":"+34 934 54 90 44",
    "sg:postcode":"08011",
    "sg:province":"Barcelona",
    "wof:name":"Fustes Fuste Sociedad Anonima",
    "wof:placetype":"venue"
},
  "geometry": {"coordinates":[2.1582219601,41.3835639954],"type":"Point"}
}