{
  "type": "Feature",
  "properties": {
    "addr:full":"Calle de Alfaz Del Pi, 6 Altea Alicante 03590",
    "addr:housenumber":"6",
    "addr:postcode":"03590",
    "addr:street":"Calle De Alfaz Del Pi",
    "iso:country":"ES",
    "sg:address":"Calle de Alfaz Del Pi, 6",
    "sg:city":"Altea",
    "sg:orig_category":"Molduras, Junquillos, Listones Y Molduras Perforadas",
    "sg:phone":"+34 966 88 53 49",
    "sg:postcode":"03590",
    "sg:province":"Alicante",
    "wof:name":"Company S.c.",
    "wof:placetype":"venue"
},
  "geometry": {"coordinates":[-0.0545388013,38.6007652283],"type":"Point"}
}