{
  "type": "Feature",
  "properties": {
    "addr:full":"Avda America, 1 Zaragoza Zaragoza 50007",
    "addr:housenumber":"1",
    "addr:postcode":"50007",
    "addr:street":"Avda America",
    "iso:country":"ES",
    "sg:address":"Avda America, 1",
    "sg:city":"Zaragoza",
    "sg:orig_category":"Asociaciones Ecologistas",
    "sg:phone":"+34 976 25 95 20",
    "sg:postcode":"50007",
    "sg:province":"Zaragoza",
    "wof:name":"Federacion De Comunidades De Regantes De La Cuenca Del Ebro",
    "wof:placetype":"venue"
},
  "geometry": {"coordinates":[-0.8849269748,41.6327438354],"type":"Point"}
}