{
  "type": "Feature",
  "properties": {
    "iso:country":"ES",
    "sg:address":"Ptge Santa Catalina Sen, 2",
    "sg:city":"Palma",
    "sg:orig_category":"Centros Empresariales",
    "sg:phone":"+34 971 71 93 73",
    "sg:postcode":"07002",
    "sg:province":"Islas Baleares",
    "wof:name":"Selec Balear",
    "wof:placetype":"venue"
},
  "geometry": {"coordinates":[2.6528949738,39.5747909546],"type":"Point"}
}