{
  "type": "Feature",
  "properties": {
    "iso:country":"ES",
    "sg:address":"Carrer de Barcelona, 6",
    "sg:city":"Prat Llobregat",
    "sg:orig_category":"Importaci\u00d3n",
    "sg:phone":"+34 934 78 36 93",
    "sg:postcode":"08820",
    "sg:province":"Barcelona",
    "wof:name":"Idea Internacional S. L.",
    "wof:placetype":"venue"
},
  "geometry": {"coordinates":[2.0935080051,41.3234176636],"type":"Point"}
}