{
  "type": "Feature",
  "properties": {
    "addr:full":"Calle de Pedralba, 11 Vilamarxant Valencia 46191",
    "addr:housenumber":"11",
    "addr:postcode":"46191",
    "addr:street":"Calle De Pedralba",
    "iso:country":"ES",
    "sg:address":"Calle de Pedralba, 11",
    "sg:city":"Vilamarxant",
    "sg:orig_category":"Venta, Instalaci\u00d3n, Reparaci\u00d3n De Antenas Para Televisi\u00d3n",
    "sg:phone":"+34 961 65 04 28",
    "sg:postcode":"46191",
    "sg:province":"Valencia",
    "wof:name":"Navarro Perez Jose Francisco",
    "wof:placetype":"venue"
},
  "geometry": {"coordinates":[-0.6232029796,39.5676193237],"type":"Point"}
}