{
  "type": "Feature",
  "properties": {
    "iso:country":"ES",
    "sg:address":"Calle de Santa Ana, 5",
    "sg:city":"Sanlucar De Barrameda",
    "sg:orig_category":"Institutos De Belleza",
    "sg:phone":"+34 956 38 16 93",
    "sg:postcode":"11540",
    "sg:province":"C\u00e1diz",
    "wof:name":"Sanchez Diaz Natividad",
    "wof:placetype":"venue"
},
  "geometry": {"coordinates":[-6.3511500359,36.7793502808],"type":"Point"}
}