{
  "type": "Feature",
  "properties": {
    "iso:country":"ES",
    "sg:address":"Carrer de Xucla, 16",
    "sg:city":"Barcelona",
    "sg:orig_category":"Arquitectos",
    "sg:phone":"+34 933 17 20 22",
    "sg:postcode":"08001",
    "sg:province":"Barcelona",
    "wof:name":"Selgas Caceres Mercedes",
    "wof:placetype":"venue"
},
  "geometry": {"coordinates":[2.1696250439,41.3838043213],"type":"Point"}
}