{
  "type": "Feature",
  "properties": {
    "addr:full":"Avda Guillermo Santana Rivero, S/n Palmas De Gran Canaria Las Palmas 35012",
    "addr:housenumber":"s",
    "addr:postcode":"35012",
    "addr:street":"Avda Guillermo Santana Rivero;/ N",
    "iso:country":"ES",
    "sg:address":"Avda Guillermo Santana Rivero, S/n",
    "sg:city":"Palmas De Gran Canaria",
    "sg:orig_category":"Empresas De Carpinter\u00cda",
    "sg:phone":"+34 928 41 45 66",
    "sg:postcode":"35012",
    "sg:province":"Las Palmas",
    "wof:name":"Aluminios Almeida S.l",
    "wof:placetype":"venue"
},
  "geometry": {"coordinates":[-15.4440383911,28.1093235016],"type":"Point"}
}