{
  "type": "Feature",
  "properties": {
    "iso:country":"ES",
    "sg:address":"Avda Castilla (de), 137",
    "sg:city":"Verin",
    "sg:orig_category":"Agentes, Concesionarios Y Sucursales De Veh\u00cdculos",
    "sg:phone":"+34 988 41 44 18",
    "sg:postcode":"32600",
    "sg:province":"Ourense",
    "wof:name":"Montes Cuevas Y Compa\u00f1ia S.a.",
    "wof:placetype":"venue"
},
  "geometry": {"coordinates":[-7.4205818176,41.9449501038],"type":"Point"}
}