{
  "type": "Feature",
  "properties": {
    "iso:country":"ES",
    "sg:address":"Pase San Francisco, 22",
    "sg:city":"Alcaraz",
    "sg:orig_category":"Empresas De Pintura Y Revestimientos",
    "sg:phone":"+34 967 38 07 74",
    "sg:postcode":"02300",
    "sg:province":"Albacete",
    "wof:name":"Palacios Moreno Francisco",
    "wof:placetype":"venue"
},
  "geometry": {"coordinates":[-2.491396904,38.6694869995],"type":"Point"}
}