{
  "type": "Feature",
  "properties": {
    "iso:country":"ES",
    "sg:address":"Carr Major, 61",
    "sg:city":"Almussafes",
    "sg:orig_category":"Aparatos E Instalaci\u00d3n De Regad\u00cdos",
    "sg:phone":"+34 961 79 51 26",
    "sg:postcode":"46440",
    "sg:province":"Valencia",
    "wof:name":"Acequia Real Del Jucar Junta Local De Almussafes",
    "wof:placetype":"venue"
},
  "geometry": {"coordinates":[-0.4121426046,39.2930908203],"type":"Point"}
}