{
  "type": "Feature",
  "properties": {
    "addr:full":"Via Laietana, 57 Barcelona Barcelona 08003",
    "addr:housenumber":"57",
    "addr:postcode":"08003",
    "addr:street":"Via Laietana",
    "iso:country":"ES",
    "sg:address":"Via Laietana, 57",
    "sg:city":"Barcelona",
    "sg:orig_category":"Asilos De Ancianos. Centros Privados",
    "sg:phone":"+34 933 01 06 77",
    "sg:postcode":"08003",
    "sg:province":"Barcelona",
    "wof:name":"Tejedor Saez Maria Rosa",
    "wof:placetype":"venue"
},
  "geometry": {"coordinates":[2.1737349033,41.3875617981],"type":"Point"}
}