{
  "type": "Feature",
  "properties": {
    "addr:full":"Avda Virgen De Los Dolores, 7 Cordoba C\u00f3rdoba 14004",
    "addr:housenumber":"7",
    "addr:postcode":"14004",
    "addr:street":"Avda Virgen De Los Dolores;Co\u0301Rdoba",
    "iso:country":"ES",
    "sg:address":"Avda Virgen De Los Dolores, 7",
    "sg:city":"Cordoba",
    "sg:orig_category":"Librer\u00cdas",
    "sg:phone":"+34 957 41 05 25",
    "sg:postcode":"14004",
    "sg:province":"C\u00f3rdoba",
    "wof:name":"Elvira De Pablo Maria Jesus",
    "wof:placetype":"venue"
},
  "geometry": {"coordinates":[-4.7959308624,37.8746070862],"type":"Point"}
}