{
  "type": "Feature",
  "properties": {
    "iso:country":"ES",
    "sg:address":"Carrer de Santalo, 34",
    "sg:city":"Barcelona",
    "sg:orig_category":"Molduras, Junquillos, Listones Y Molduras Perforadas",
    "sg:phone":"+34 932 00 39 42",
    "sg:postcode":"08021",
    "sg:province":"Barcelona",
    "wof:name":"Ruiz Huguet Valentin",
    "wof:placetype":"venue"
},
  "geometry": {"coordinates":[2.1459639072,41.3957176208],"type":"Point"}
}