{
  "type": "Feature",
  "properties": {
    "addr:full":"Toldao, S/n Toldao Lugo 27555",
    "addr:postcode":"27555",
    "addr:street":"S / N",
    "iso:country":"ES",
    "sg:address":"Toldao, S/n",
    "sg:city":"Toldao",
    "sg:orig_category":"Carpinteros",
    "sg:phone":"+34 982 46 50 02",
    "sg:postcode":"27555",
    "sg:province":"Lugo",
    "wof:name":"Taboada Coego Angel",
    "wof:placetype":"venue"
},
  "geometry": {"coordinates":[-7.8707251549,42.6946182251],"type":"Point"}
}