{
  "type": "Feature",
  "properties": {
    "addr:full":"Cmno Mosquetera (de La), 56 Zaragoza Zaragoza 50010",
    "addr:housenumber":"56",
    "addr:postcode":"50010",
    "addr:street":"Cmno Mosquetera De La",
    "iso:country":"ES",
    "sg:address":"Cmno Mosquetera (de La), 56",
    "sg:city":"Zaragoza",
    "sg:orig_category":"Inform\u00c1tica (estudios, Servicios, Asesor\u00cda, Formaci\u00d3n)",
    "sg:phone":"+34 976 53 64 85",
    "sg:postcode":"50010",
    "sg:province":"Zaragoza",
    "wof:name":"Janun S.c.",
    "wof:placetype":"venue"
},
  "geometry": {"coordinates":[-0.900267005,41.6505050659],"type":"Point"}
}