{
  "type": "Feature",
  "properties": {
    "iso:country":"ES",
    "sg:address":"Calle de Real, 266",
    "sg:city":"Calzada Calatrava",
    "sg:orig_category":"Mec\u00c1nico Del Autom\u00d3vil",
    "sg:phone":"+34 926 87 57 00",
    "sg:postcode":"13370",
    "sg:province":"Ciudad Real",
    "wof:name":"Rodriguez Castillo Francisco",
    "wof:placetype":"venue"
},
  "geometry": {"coordinates":[-3.7792489529,38.7065315247],"type":"Point"}
}