{
  "type": "Feature",
  "properties": {
    "iso:country":"ES",
    "sg:address":"Calle de Santuario, 28",
    "sg:city":"Montijo",
    "sg:orig_category":"Empresas De Carpinter\u00cda Met\u00c1lica",
    "sg:phone":"+34 924 45 08 09",
    "sg:postcode":"06480",
    "sg:province":"Badajoz",
    "wof:name":"Garcia Caballero Jose Maria",
    "wof:placetype":"venue"
},
  "geometry": {"coordinates":[-6.6066589355,38.9050788879],"type":"Point"}
}