{
  "type": "Feature",
  "properties": {
    "iso:country":"ES",
    "sg:address":"Calle de Pablo Picasso, 22",
    "sg:city":"Madrigueras",
    "sg:orig_category":"Fabricaci\u00d3n Y Venta De Volquetes Y Remolques",
    "sg:phone":"+34 967 48 53 09",
    "sg:postcode":"02230",
    "sg:province":"Albacete",
    "wof:name":"Ballesteros Villar Antonio",
    "wof:placetype":"venue"
},
  "geometry": {"coordinates":[-1.7991169691,39.2381515503],"type":"Point"}
}