{
  "type": "Feature",
  "properties": {
    "iso:country":"ES",
    "sg:address":"Calle de Padre Feijoo, 21",
    "sg:city":"Torrent",
    "sg:orig_category":"Agencias Y Agentes Comerciales, Representantes",
    "sg:phone":"+34 961 56 68 72",
    "sg:postcode":"46900",
    "sg:province":"Valencia",
    "wof:name":"Gallego Aguacil Antonio",
    "wof:placetype":"venue"
},
  "geometry": {"coordinates":[-0.4590820074,39.4408187866],"type":"Point"}
}