{
  "type": "Feature",
  "properties": {
    "addr:full":"Carrer de Riera, 46 Calella Barcelona 08370",
    "addr:housenumber":"46",
    "addr:postcode":"08370",
    "addr:street":"Carrer De Riera",
    "iso:country":"ES",
    "sg:address":"Carrer de Riera, 46",
    "sg:city":"Calella",
    "sg:orig_category":"Agencias De Viajes",
    "sg:phone":"+34 937 69 00 66",
    "sg:postcode":"08370",
    "sg:province":"Barcelona",
    "wof:name":"Menghnani  Hemlata",
    "wof:placetype":"venue"
},
  "geometry": {"coordinates":[2.6553049088,41.6129226685],"type":"Point"}
}