{
  "type": "Feature",
  "properties": {
    "iso:country":"ES",
    "sg:address":"Carrer de Vistalegre, 15",
    "sg:city":"Cornella Llobregat",
    "sg:orig_category":"Confecci\u00d3n De Trajes Para Se\u00d1oras",
    "sg:phone":"+34 933 76 25 67",
    "sg:postcode":"08940",
    "sg:province":"Barcelona",
    "wof:name":"Ponce Sanchez Clara",
    "wof:placetype":"venue"
},
  "geometry": {"coordinates":[2.0742380619,41.3613853455],"type":"Point"}
}