{
  "type": "Feature",
  "properties": {
    "addr:full":"C/ Vila De Madrid, 8 Paterna Valencia 46988",
    "addr:housenumber":"8",
    "addr:postcode":"46988",
    "addr:street":"C / Vila De Madrid",
    "iso:country":"ES",
    "sg:address":"C/ Vila De Madrid, 8",
    "sg:city":"Paterna",
    "sg:orig_category":"Material Did\u00c1ctico",
    "sg:phone":"+34 961 34 00 28",
    "sg:postcode":"46988",
    "sg:province":"Valencia",
    "wof:name":"Montichelvo Industrial S.a.",
    "wof:placetype":"venue"
},
  "geometry": {"coordinates":[-0.4687919915,39.5216217041],"type":"Point"}
}