{
  "type": "Feature",
  "properties": {
    "addr:full":"Calle de Orfila, 3 Sevilla Sevilla 41003",
    "addr:housenumber":"3",
    "addr:postcode":"41003",
    "addr:street":"Calle De Orfila",
    "iso:country":"ES",
    "sg:address":"Calle de Orfila, 3",
    "sg:city":"Sevilla",
    "sg:orig_category":"Caf\u00c9s, Bares, Cervecer\u00cdas",
    "sg:phone":"+34 954 21 30 73",
    "sg:postcode":"41003",
    "sg:province":"Sevilla",
    "wof:name":"Gil Y Brachi S. L.",
    "wof:placetype":"venue"
},
  "geometry": {"coordinates":[-5.9935779572,37.3935279846],"type":"Point"}
}