{
  "type": "Feature",
  "properties": {
    "addr:full":"Pr. Maior, 5 Verin Ourense 32600",
    "addr:housenumber":"5",
    "addr:postcode":"32600",
    "addr:street":"Verin Ourense",
    "iso:country":"ES",
    "sg:address":"Pr. Maior, 5",
    "sg:city":"Verin",
    "sg:orig_category":"Artesan\u00cda Y Trabajos Manuales: Suministros (al Por Menor)",
    "sg:phone":"+34 988 41 20 40",
    "sg:postcode":"32600",
    "sg:province":"Ourense",
    "wof:name":"Aqua Verin S.l.",
    "wof:placetype":"venue"
},
  "geometry": {"coordinates":[-7.4273195267,41.867805481],"type":"Point"}
}