{
  "type": "Feature",
  "properties": {
    "iso:country":"ES",
    "sg:address":"Calle de Doctor Plaza, 20",
    "sg:city":"Carrascosa Del Campo",
    "sg:orig_category":"Reposter\u00cdas",
    "sg:phone":"+34 969 12 40 23",
    "sg:postcode":"16830",
    "sg:province":"Cuenca",
    "wof:name":"Valenciano Martinez Juan Pablo",
    "wof:placetype":"venue"
},
  "geometry": {"coordinates":[-2.7381699085,40.0376281738],"type":"Point"}
}