{
  "type": "Feature",
  "properties": {
    "addr:full":"Cuesta-taco, 15 La Cuesta Santa Cruz De Tenerife 38320",
    "addr:housenumber":"15",
    "addr:postcode":"38320",
    "addr:street":"Cuesta-Taco",
    "iso:country":"ES",
    "sg:address":"Cuesta-taco, 15",
    "sg:city":"La Cuesta",
    "sg:orig_category":"Administradores De Bienes Y Delegados De Comunidades De Propietarios",
    "sg:phone":"+34 922 64 32 88",
    "sg:postcode":"38320",
    "sg:province":"Santa Cruz De Tenerife",
    "wof:name":"Barrios Llarena Gonzalo",
    "wof:placetype":"venue"
},
  "geometry": {"coordinates":[-16.2880134583,28.468454361],"type":"Point"}
}