{
  "type": "Feature",
  "properties": {
    "iso:country":"ES",
    "sg:address":"A\u00f1oreta Golf, 27",
    "sg:city":"Torre Benagalbon",
    "sg:orig_category":"Tratamientos De Conversi\u00d3n Qu\u00cdmica O Electrol\u00cdtica De Metales",
    "sg:phone":"+34 952 40 10 25",
    "sg:postcode":"29738",
    "sg:province":"M\u00e1laga",
    "wof:name":"Horna Arguedas Maria Jesus",
    "wof:placetype":"venue"
},
  "geometry": {"coordinates":[-4.2562980652,36.7710762024],"type":"Point"}
}