{
  "type": "Feature",
  "properties": {
    "addr:full":"Ptda La Contienda, 11 Buenavista Valencia 46900",
    "addr:housenumber":"11",
    "addr:postcode":"46900",
    "addr:street":"Ptda La Contienda",
    "iso:country":"ES",
    "sg:address":"Ptda La Contienda, 11",
    "sg:city":"Buenavista",
    "sg:orig_category":"Agricultores, Agricultores",
    "sg:phone":"+34 961 57 13 85",
    "sg:postcode":"46900",
    "sg:province":"Valencia",
    "wof:name":"Barona Conejero Manuel",
    "wof:placetype":"venue"
},
  "geometry": {"coordinates":[-0.4623290002,39.441619873],"type":"Point"}
}