{
  "type": "Feature",
  "properties": {
    "iso:country":"ES",
    "sg:address":"Carrer de Numero 40 De La Zona Franca, 14",
    "sg:city":"Barcelona",
    "sg:orig_category":"Productos Qu\u00cdmicos (fabricaci\u00d3n, Al Por Mayor)",
    "sg:phone":"+34 932 64 39 20",
    "sg:postcode":"08040",
    "sg:province":"Barcelona",
    "sg:website":"www.sidasa.com",
    "wof:name":"Sida S.a.",
    "wof:placetype":"venue"
},
  "geometry": {"coordinates":[2.1078538895,41.3331184387],"type":"Point"}
}