{
  "type": "Feature",
  "properties": {
    "iso:country":"ES",
    "sg:address":"Calle de Felipe Ii, 13",
    "sg:city":"Cordoba",
    "sg:orig_category":"Alimentaci\u00d3n General (al Por Menor)",
    "sg:phone":"+34 957 23 43 70",
    "sg:postcode":"14005",
    "sg:province":"C\u00f3rdoba",
    "wof:name":"Cardenas Soriano Juana",
    "wof:placetype":"venue"
},
  "geometry": {"coordinates":[-4.7909770012,37.8828582764],"type":"Point"}
}