{
  "type": "Feature",
  "properties": {
    "addr:full":"Carrer de Pere Dezcallar Net, 11 Palma Islas Baleares 07003",
    "addr:housenumber":"11",
    "addr:postcode":"07003",
    "addr:street":"Carrer De Pere Dezcallar Net",
    "iso:country":"ES",
    "sg:address":"Carrer de Pere Dezcallar Net, 11",
    "sg:city":"Palma",
    "sg:orig_category":"Arquitectos",
    "sg:phone":"+34 971 72 83 79",
    "sg:postcode":"07003",
    "sg:province":"Islas Baleares",
    "wof:name":"Reig Prosper Alberto",
    "wof:placetype":"venue"
},
  "geometry": {"coordinates":[2.6490700245,39.5776329041],"type":"Point"}
}