{
  "type": "Feature",
  "properties": {
    "iso:country":"ES",
    "sg:address":"Avda Paz, 210",
    "sg:city":"Yecla",
    "sg:orig_category":"Mec\u00c1nico Del Autom\u00d3vil",
    "sg:phone":"+34 968 75 06 31",
    "sg:postcode":"30510",
    "sg:province":"Murcia",
    "wof:name":"Automecanica Ruiz S.l.",
    "wof:placetype":"venue"
},
  "geometry": {"coordinates":[-1.1369630098,38.6118469238],"type":"Point"}
}