{
  "type": "Feature",
  "properties": {
    "addr:full":"Pase Constitucion (de La), 109 Ejea De Los Caballeros Zaragoza 50600",
    "addr:housenumber":"109",
    "addr:postcode":"50600",
    "iso:country":"ES",
    "sg:address":"Pase Constitucion (de La), 109",
    "sg:city":"Ejea De Los Caballeros",
    "sg:orig_category":"Grafistas",
    "sg:phone":"+34 976 67 78 54",
    "sg:postcode":"50600",
    "sg:province":"Zaragoza",
    "wof:name":"Copycasti Reproducciones Graficas, S.c",
    "wof:placetype":"venue"
},
  "geometry": {"coordinates":[-1.1382750273,42.1269798279],"type":"Point"}
}