{
  "type": "Feature",
  "properties": {
    "addr:full":"Carrer de Platja, S/n S. Adria Besos Barcelona 08930",
    "addr:housenumber":"s",
    "addr:postcode":"08930",
    "addr:street":"Carrer De Platja;/ N S.;Barcelona",
    "iso:country":"ES",
    "sg:address":"Carrer de Platja, S/n",
    "sg:city":"S. Adria Besos",
    "sg:orig_category":"Fabricaci\u00d3n, Importaci\u00d3n, Venta De Material De Telefon\u00cda, Peritelefon\u00cda",
    "sg:phone":"+34 934 62 60 07",
    "sg:postcode":"08930",
    "sg:province":"Barcelona",
    "wof:name":"Linea 92 Olimpic Barna S.l.",
    "wof:placetype":"venue"
},
  "geometry": {"coordinates":[2.2245550156,41.4277381897],"type":"Point"}
}