{
  "type": "Feature",
  "properties": {
    "iso:country":"ES",
    "sg:address":"Urb Urb Valdeolletas, 8",
    "sg:city":"Marbella",
    "sg:orig_category":"Psic\u00d3logos",
    "sg:phone":"+34 952 82 07 49",
    "sg:postcode":"29600",
    "sg:province":"M\u00e1laga",
    "wof:name":"Lares Garcia Jose",
    "wof:placetype":"venue"
},
  "geometry": {"coordinates":[-4.8833007812,36.5079956055],"type":"Point"}
}