{
  "type": "Feature",
  "properties": {
    "addr:full":"Carrer de Fronto, 16 Terrassa Barcelona 08221",
    "addr:housenumber":"16",
    "addr:postcode":"08221",
    "addr:street":"Carrer De Fronto",
    "iso:country":"ES",
    "sg:address":"Carrer de Fronto, 16",
    "sg:city":"Terrassa",
    "sg:orig_category":"M\u00c9dicos: Cirug\u00cda Pl\u00c1stica, Reconstructiva Y Est\u00c9tica",
    "sg:phone":"+34 937 84 09 77",
    "sg:postcode":"08221",
    "sg:province":"Barcelona",
    "wof:name":"Pujol Gali Jorge",
    "wof:placetype":"venue"
},
  "geometry": {"coordinates":[2.015763998,41.5690116882],"type":"Point"}
}