{
  "type": "Feature",
  "properties": {
    "addr:full":"Carrer de Sant Isidre (de), 9 S. Carles Rapita Tarragona 43540",
    "addr:postcode":"43540",
    "addr:street":"Carrer De Sant Isidre De 9 S. Carles Rapita",
    "iso:country":"ES",
    "sg:address":"Carrer de Sant Isidre (de), 9",
    "sg:city":"S. Carles Rapita",
    "sg:orig_category":"Peluquer\u00cdas, Peluquer\u00cda Mixta",
    "sg:phone":"+34 977 74 47 61",
    "sg:postcode":"43540",
    "sg:province":"Tarragona",
    "wof:name":"Redo Ferrer Maria De Les Neus",
    "wof:placetype":"venue"
},
  "geometry": {"coordinates":[0.5910859704,40.6198501587],"type":"Point"}
}