{
  "type": "Feature",
  "properties": {
    "addr:full":"Calle de Escorial (el), S/n Alcala Henares Madrid 28805",
    "addr:postcode":"28805",
    "addr:street":"Calle De Escorial El S / N",
    "iso:country":"ES",
    "sg:address":"Calle de Escorial (el), S/n",
    "sg:city":"Alcala Henares",
    "sg:orig_category":"Frutas Y Legumbres Frescas (al Por Mayor)",
    "sg:phone":"+34 918 82 34 13",
    "sg:postcode":"28805",
    "sg:province":"Madrid",
    "wof:name":"Frutas Y Hortalizas Tomas S.l.",
    "wof:placetype":"venue"
},
  "geometry": {"coordinates":[-3.3503851891,40.4945220947],"type":"Point"}
}