{
  "type": "Feature",
  "properties": {
    "iso:country":"ES",
    "sg:address":"Mossen Manya, 12",
    "sg:city":"Sta. Barbara",
    "sg:orig_category":"Empresas De Carpinter\u00cda Met\u00c1lica",
    "sg:phone":"+34 977 71 85 02",
    "sg:postcode":"43570",
    "sg:province":"Tarragona",
    "wof:name":"Aluminios Garcia Domenech Sl",
    "wof:placetype":"venue"
},
  "geometry": {"coordinates":[0.4908188879,40.7170791626],"type":"Point"}
}