{
  "type": "Feature",
  "properties": {
    "iso:country":"ES",
    "sg:address":"Calle de Joaquin Blume, 9",
    "sg:city":"San Vicente Del Raspeig-sant Vicent Del Raspeig",
    "sg:orig_category":"Mec\u00c1nico Del Autom\u00d3vil",
    "sg:phone":"+34 965 66 99 57",
    "sg:postcode":"03690",
    "sg:province":"Alicante",
    "wof:name":"Talleres Blume S.l.",
    "wof:placetype":"venue"
},
  "geometry": {"coordinates":[-0.52412498,38.4010276794],"type":"Point"}
}