{
  "type": "Feature",
  "properties": {
    "iso:country":"ES",
    "sg:address":"Rbla Principal, 5",
    "sg:city":"Vilanova I La Geltru",
    "sg:orig_category":"Muebles, Minoristas",
    "sg:phone":"+34 938 93 03 09",
    "sg:postcode":"08800",
    "sg:province":"Barcelona",
    "wof:name":"Rosich Cuatrecases Rosa",
    "wof:placetype":"venue"
},
  "geometry": {"coordinates":[1.7241690159,41.2255439758],"type":"Point"}
}