{
  "type": "Feature",
  "properties": {
    "iso:country":"ES",
    "sg:address":"Ctra. Picanya, 39",
    "sg:city":"Torrent",
    "sg:orig_category":"Bombas De Agua",
    "sg:phone":"+34 961 58 09 81",
    "sg:postcode":"46900",
    "sg:province":"Valencia",
    "wof:name":"Depuradores Mora S.l.",
    "wof:placetype":"venue"
},
  "geometry": {"coordinates":[-0.4590530097,39.4415130615],"type":"Point"}
}