{
  "type": "Feature",
  "properties": {
    "iso:country":"ES",
    "sg:address":"Plaz Foramontanos, 3",
    "sg:city":"Burgos",
    "sg:orig_category":"Comerciantes Al Por Mayor De Vinos, Licores Y Alcoholes",
    "sg:phone":"+34 947 21 01 14",
    "sg:postcode":"09007",
    "sg:province":"Burgos",
    "wof:name":"Gonzalez Lopez Jaime",
    "wof:placetype":"venue"
},
  "geometry": {"coordinates":[-3.6495990753,42.344959259],"type":"Point"}
}