{
  "type": "Feature",
  "properties": {
    "addr:full":"Calle de Menendez Pelayo, 3 Marchena Sevilla 41620",
    "addr:housenumber":"3",
    "addr:postcode":"41620",
    "addr:street":"Calle De Menendez Pelayo",
    "iso:country":"ES",
    "sg:address":"Calle de Menendez Pelayo, 3",
    "sg:city":"Marchena",
    "sg:orig_category":"Farmacias",
    "sg:phone":"+34 954 84 30 36",
    "sg:postcode":"41620",
    "sg:province":"Sevilla",
    "wof:name":"Farmacia Coronado C.b.",
    "wof:placetype":"venue"
},
  "geometry": {"coordinates":[-5.4155778885,37.3279533386],"type":"Point"}
}