{
  "type": "Feature",
  "properties": {
    "addr:full":"Avda Adelfas (de Las), S/n Castellar Frontera C\u00e1diz 11350",
    "addr:postcode":"11350",
    "addr:street":"Avda Adelfas De Las S / N",
    "iso:country":"ES",
    "sg:address":"Avda Adelfas (de Las), S/n",
    "sg:city":"Castellar Frontera",
    "sg:orig_category":"Ense\u00d1anza Secundaria: Colegios Y Escuelas Privadas",
    "sg:phone":"+34 956 64 70 19",
    "sg:postcode":"11350",
    "sg:province":"C\u00e1diz",
    "wof:name":"Junta De Andalucia",
    "wof:placetype":"venue"
},
  "geometry": {"coordinates":[-5.4138112068,36.2863044739],"type":"Point"}
}