{
  "type": "Feature",
  "properties": {
    "iso:country":"ES",
    "sg:address":"C/ Alcoi, 6",
    "sg:city":"Elche",
    "sg:orig_category":"Zapatos: Material, Suministros, Accesorios (fabricaci\u00d3n, Al Por Mayor)",
    "sg:phone":"+34 966 63 60 01",
    "sg:postcode":"03203",
    "sg:province":"Alicante",
    "wof:name":"Torres Hermanos S.l.",
    "wof:placetype":"venue"
},
  "geometry": {"coordinates":[-0.6715959907,38.2707290649],"type":"Point"}
}