{
  "type": "Feature",
  "properties": {
    "addr:full":"Calle de Galileo, 55 Madrid Madrid 28015",
    "addr:housenumber":"55",
    "addr:postcode":"madrid;28015",
    "addr:street":"Calle De Galileo",
    "iso:country":"ES",
    "sg:address":"Calle de Galileo, 55",
    "sg:city":"Madrid",
    "sg:orig_category":"Quincaller\u00cda (al Por Menor)",
    "sg:phone":"+34 915 49 64 20",
    "sg:postcode":"28015",
    "sg:province":"Madrid",
    "wof:name":"Perez Alvarez Francisco Javier",
    "wof:placetype":"venue"
},
  "geometry": {"coordinates":[-3.7103478909,40.4355583191],"type":"Point"}
}