{
  "type": "Feature",
  "properties": {
    "iso:country":"ES",
    "sg:address":"Avda San Jose, 198",
    "sg:city":"Zaragoza",
    "sg:orig_category":"Radiocomunicaciones, Telefon\u00cda M\u00d3vil, Radiomensajer\u00cda: Servicios, Comercializaci\u00d3n",
    "sg:phone":"+34 976 25 15 42",
    "sg:postcode":"50007",
    "sg:province":"Zaragoza",
    "wof:name":"Servicio Integral De Comunicaciones Movi",
    "wof:placetype":"venue"
},
  "geometry": {"coordinates":[-0.8793100119,41.6358261108],"type":"Point"}
}