{
  "type": "Feature",
  "properties": {
    "iso:country":"ES",
    "sg:address":"Calle de Montemar, 6",
    "sg:city":"Guadalajara",
    "sg:orig_category":"Ropa Para Se\u00d1oras Y Caballeros (al Por Menor)",
    "sg:phone":"+34 949 22 60 67",
    "sg:postcode":"19001",
    "sg:province":"Guadalajara",
    "wof:name":"May-jover S. A.",
    "wof:placetype":"venue"
},
  "geometry": {"coordinates":[-3.1654200554,40.6316184998],"type":"Point"}
}