{
  "type": "Feature",
  "properties": {
    "addr:full":"Calle de Muelle, 2 Puertollano Ciudad Real 13500",
    "addr:housenumber":"2",
    "addr:postcode":"13500",
    "addr:street":"Calle De Muelle",
    "iso:country":"ES",
    "sg:address":"Calle de Muelle, 2",
    "sg:city":"Puertollano",
    "sg:orig_category":"Molduras, Junquillos, Listones Y Molduras Perforadas",
    "sg:phone":"+34 926 41 39 28",
    "sg:postcode":"13500",
    "sg:province":"Ciudad Real",
    "wof:name":"Casales Martinez Juan Jose",
    "wof:placetype":"venue"
},
  "geometry": {"coordinates":[-4.1097240448,38.6912155151],"type":"Point"}
}