{
  "type": "Feature",
  "properties": {
    "addr:full":"Calle de Alfonso Xiii, S/n Albolote Granada 18220",
    "addr:housenumber":"s / n",
    "addr:postcode":"18220",
    "addr:street":"Calle De Alfonso Xiii",
    "iso:country":"ES",
    "sg:address":"Calle de Alfonso Xiii, S/n",
    "sg:city":"Albolote",
    "sg:orig_category":"Sanatorios M\u00c9dico",
    "sg:phone":"+34 958 46 72 09",
    "sg:postcode":"18220",
    "sg:province":"Granada",
    "wof:name":"Servicio Andaluz De Salud",
    "wof:placetype":"venue"
},
  "geometry": {"coordinates":[-3.6530940533,37.2270736694],"type":"Point"}
}