{
  "type": "Feature",
  "properties": {
    "addr:full":"Calle de Goienkalea, 18 Durango Vizcaya 48200",
    "addr:housenumber":"18",
    "addr:postcode":"48200",
    "addr:street":"Calle De Goienkalea",
    "iso:country":"ES",
    "sg:address":"Calle de Goienkalea, 18",
    "sg:city":"Durango",
    "sg:orig_category":"Asociaciones Y Clubs Deportivos",
    "sg:phone":"+34 946 20 00 07",
    "sg:postcode":"48200",
    "sg:province":"Vizcaya",
    "wof:name":"Durango Rugby Taldea",
    "wof:placetype":"venue"
},
  "geometry": {"coordinates":[-2.6312310696,43.1662216187],"type":"Point"}
}