{
  "type": "Feature",
  "properties": {
    "addr:full":"Carrer de Francesc Cambo, 33 Lloret Mar Girona 17310",
    "addr:housenumber":"33",
    "addr:postcode":"17310",
    "addr:street":"Carrer De Francesc Cambo",
    "iso:country":"ES",
    "sg:address":"Carrer de Francesc Cambo, 33",
    "sg:city":"Lloret Mar",
    "sg:orig_category":"Promotores Constructores",
    "sg:phone":"+34 972 34 93 10",
    "sg:postcode":"17310",
    "sg:province":"Girona",
    "sg:website":"www.dosolvi.com",
    "wof:name":"Construccions Soler K-litat S.l.",
    "wof:placetype":"venue"
},
  "geometry": {"coordinates":[2.8360340595,41.7001724243],"type":"Point"}
}