{
  "type": "Feature",
  "properties": {
    "iso:country":"ES",
    "sg:address":"Calle de Carretera De Carmona, 70",
    "sg:city":"Sevilla",
    "sg:orig_category":"Forjas Y Altos Hornos",
    "sg:phone":"+34 954 41 05 55",
    "sg:postcode":"41008",
    "sg:province":"Sevilla",
    "wof:name":"Romero Moreno Pedro",
    "wof:placetype":"venue"
},
  "geometry": {"coordinates":[-5.8550591469,37.4141998291],"type":"Point"}
}