{
  "type": "Feature",
  "properties": {
    "addr:full":"Calle de Macarena, 29 Madrid Madrid 28016",
    "addr:housenumber":"29",
    "addr:postcode":"madrid;28016",
    "addr:street":"Calle De Macarena",
    "iso:country":"ES",
    "sg:address":"Calle de Macarena, 29",
    "sg:city":"Madrid",
    "sg:orig_category":"Arquitectos",
    "sg:phone":"+34 913 45 32 81",
    "sg:postcode":"28016",
    "sg:province":"Madrid",
    "wof:name":"Manuel Vega Arquitectos S.l.",
    "wof:placetype":"venue"
},
  "geometry": {"coordinates":[-3.6776781082,40.4618263245],"type":"Point"}
}