{
  "type": "Feature",
  "properties": {
    "addr:full":"Calle de Solana (de La), 1 Collado Mediano Madrid 28450",
    "addr:housenumber":"1",
    "addr:postcode":"28450",
    "addr:street":"Calle De Solana De La",
    "iso:country":"ES",
    "sg:address":"Calle de Solana (de La), 1",
    "sg:city":"Collado Mediano",
    "sg:orig_category":"Colocaci\u00d3n, Mantenimiento De Canalizaciones",
    "sg:phone":"+34 918 55 85 02",
    "sg:postcode":"28450",
    "sg:province":"Madrid",
    "wof:name":"Olmedo Hijos Canalizaciones Y Tendidos S.l.",
    "wof:placetype":"venue"
},
  "geometry": {"coordinates":[-4.022646904,40.6948661804],"type":"Point"}
}