{
  "type": "Feature",
  "properties": {
    "addr:full":"Ctra Prat, 45 Viladecans Barcelona 08840",
    "addr:housenumber":"45",
    "addr:postcode":"08840",
    "addr:street":"Ctra Prat",
    "iso:country":"ES",
    "sg:address":"Ctra Prat, 45",
    "sg:city":"Viladecans",
    "sg:orig_category":"Molduras, Junquillos, Listones Y Molduras Perforadas",
    "sg:phone":"+34 936 37 07 32",
    "sg:postcode":"08840",
    "sg:province":"Barcelona",
    "wof:name":"Perez Limon Jose",
    "wof:placetype":"venue"
},
  "geometry": {"coordinates":[2.027299881,41.3167304993],"type":"Point"}
}