{
  "type": "Feature",
  "properties": {
    "iso:country":"ES",
    "sg:address":"Alemanya (pol Ind), S/n",
    "sg:city":"Constanti",
    "sg:orig_category":"Distribuci\u00d3n De Petr\u00d3leo Y Derivados",
    "sg:phone":"+34 977 52 48 67",
    "sg:postcode":"43120",
    "sg:province":"Tarragona",
    "wof:name":"Luvirr S.a.",
    "wof:placetype":"venue"
},
  "geometry": {"coordinates":[1.1651550531,41.1597290039],"type":"Point"}
}