{
  "type": "Feature",
  "properties": {
    "addr:full":"Calle de Cristobal Perez Pastor, 10 Albacete Albacete 02004",
    "addr:housenumber":"10",
    "addr:postcode":"02004",
    "addr:street":"Calle De Cristobal Perez Pastor",
    "iso:country":"ES",
    "sg:address":"Calle de Cristobal Perez Pastor, 10",
    "sg:city":"Albacete",
    "sg:orig_category":"Electrodom\u00c9sticos (al Por Menor)",
    "sg:phone":"+34 967 22 13 00",
    "sg:postcode":"02004",
    "sg:province":"Albacete",
    "wof:name":"Diaz Marquez Dativo",
    "wof:placetype":"venue"
},
  "geometry": {"coordinates":[-1.8608515263,38.9950675964],"type":"Point"}
}