{
  "type": "Feature",
  "properties": {
    "addr:full":"Calle de Manuel Vela, 23 Lepe Huelva 21440",
    "addr:housenumber":"23",
    "addr:postcode":"21440",
    "addr:street":"Calle De Manuel Vela",
    "iso:country":"ES",
    "sg:address":"Calle de Manuel Vela, 23",
    "sg:city":"Lepe",
    "sg:orig_category":"M\u00c9dicos: Pediatr\u00cda. Enfermedades De Los Ni\u00d1os",
    "sg:phone":"+34 959 38 03 44",
    "sg:postcode":"21440",
    "sg:province":"Huelva",
    "wof:name":"Ales Perez De Leon Ricardo",
    "wof:placetype":"venue"
},
  "geometry": {"coordinates":[-7.232925415,37.279296875],"type":"Point"}
}