{
  "type": "Feature",
  "properties": {
    "addr:full":"Calle de Manzanedo, 12 Santo\u00f1a Cantabria 39740",
    "addr:housenumber":"12",
    "addr:postcode":"39740",
    "addr:street":"Calle De Manzanedo",
    "iso:country":"ES",
    "sg:address":"Calle de Manzanedo, 12",
    "sg:city":"Santo\u00f1a",
    "sg:orig_category":"Comercio De Minerales, F\u00d3siles Y Conchas",
    "sg:phone":"+34 942 66 12 36",
    "sg:postcode":"39740",
    "sg:province":"Cantabria",
    "wof:name":"Lopez Pablos Urbano",
    "wof:placetype":"venue"
},
  "geometry": {"coordinates":[-3.4559340477,43.4442062378],"type":"Point"}
}