{
  "type": "Feature",
  "properties": {
    "iso:country":"ES",
    "sg:address":"Rua Real, 63",
    "sg:city":"Quiroga",
    "sg:orig_category":"Florister\u00cdas",
    "sg:phone":"+34 982 42 80 29",
    "sg:postcode":"27320",
    "sg:province":"Lugo",
    "wof:name":"Garrido Vilari\u00f1o Maria Elena",
    "wof:placetype":"venue"
},
  "geometry": {"coordinates":[-7.2711400986,42.4757995605],"type":"Point"}
}