{
  "type": "Feature",
  "properties": {
    "iso:country":"ES",
    "sg:address":"Calle de San Lorenzo, 2",
    "sg:city":"Alqueria D'asnar",
    "sg:orig_category":"Hilaturas, Hilos Y Actividades Relacionadas",
    "sg:phone":"+34 966 51 72 00",
    "sg:postcode":"03829",
    "sg:province":"Alicante",
    "wof:name":"Mundi Urdidos S.l.",
    "wof:placetype":"venue"
},
  "geometry": {"coordinates":[-0.5121359825,38.3418731689],"type":"Point"}
}