{
  "type": "Feature",
  "properties": {
    "iso:country":"ES",
    "sg:address":"Av. Terres De L'ebre, S/n",
    "sg:city":"Xerta",
    "sg:orig_category":"Producci\u00d3n, Venta De Productos De Agricultura Biol\u00d3gica",
    "sg:phone":"+34 977 47 31 30",
    "sg:postcode":"43592",
    "sg:province":"Tarragona",
    "wof:name":"Segarra Ventura Joaquin",
    "wof:placetype":"venue"
},
  "geometry": {"coordinates":[0.4894729853,40.9085388184],"type":"Point"}
}