{
  "type": "Feature",
  "properties": {
    "iso:country":"ES",
    "sg:address":"Calle de Manuel Rojas Marcos, 19",
    "sg:city":"Marchena",
    "sg:orig_category":"Muebles, Minoristas",
    "sg:phone":"+34 954 84 46 72",
    "sg:postcode":"41620",
    "sg:province":"Sevilla",
    "wof:name":"Francisco Olias S.l.",
    "wof:placetype":"venue"
},
  "geometry": {"coordinates":[-5.4167990685,37.3300209045],"type":"Point"}
}