{
  "type": "Feature",
  "properties": {
    "iso:country":"ES",
    "sg:address":"Avda Espa\u00d1a, 41",
    "sg:city":"Albacete",
    "sg:orig_category":"Ingenier\u00cda, Centros De Estudios (diversos)",
    "sg:phone":"+34 967 22 89 48",
    "sg:postcode":"02002",
    "sg:province":"Albacete",
    "wof:name":"Candel Gonzalez Viriato",
    "wof:placetype":"venue"
},
  "geometry": {"coordinates":[-1.8537000418,38.9852218628],"type":"Point"}
}