{
  "type": "Feature",
  "properties": {
    "addr:full":"Calle de Kareaga, 83 San Vicente De Barakaldo Vizcaya 48903",
    "addr:housenumber":"83",
    "addr:postcode":"48903",
    "addr:street":"Calle De Kareaga",
    "iso:country":"ES",
    "sg:address":"Calle de Kareaga, 83",
    "sg:city":"San Vicente De Barakaldo",
    "sg:orig_category":"Goma: Materias Primas (producci\u00d3n, Distribuci\u00d3n)",
    "sg:phone":"+34 944 97 00 18",
    "sg:postcode":"48903",
    "sg:province":"Vizcaya",
    "wof:name":"Indelcaucho Laboral S. L.",
    "wof:placetype":"venue"
},
  "geometry": {"coordinates":[-3.0094959736,43.28673172],"type":"Point"}
}