{
  "type": "Feature",
  "properties": {
    "addr:full":"Calle de Joaquin Costa, 30 Barbastro Huesca 22300",
    "addr:housenumber":"30",
    "addr:postcode":"22300",
    "addr:street":"Calle De Joaquin Costa",
    "iso:country":"ES",
    "sg:address":"Calle de Joaquin Costa, 30",
    "sg:city":"Barbastro",
    "sg:orig_category":"Carnicer\u00cdas, Carnicer\u00cdas",
    "sg:phone":"+34 974 31 34 53",
    "sg:postcode":"22300",
    "sg:province":"Huesca",
    "wof:name":"Bernad Sallan Antonio",
    "wof:placetype":"venue"
},
  "geometry": {"coordinates":[0.1272400022,42.0346260071],"type":"Point"}
}