{
  "type": "Feature",
  "properties": {
    "iso:country":"ES",
    "sg:address":"Carr Icaria, 17",
    "sg:city":"S. Climent Sescebes",
    "sg:orig_category":"Centros De Educaci\u00d3n Especial",
    "sg:phone":"+34 972 56 34 32",
    "sg:postcode":"17751",
    "sg:province":"Girona",
    "wof:name":"Co%egi Public De Sant Climent Sescebes",
    "wof:placetype":"venue"
},
  "geometry": {"coordinates":[2.973058939,42.3635139465],"type":"Point"}
}