{
  "type": "Feature",
  "properties": {
    "addr:full":"Carrer de Permanyer, 302 Sabadell Barcelona 08205",
    "addr:housenumber":"302",
    "addr:postcode":"08205",
    "addr:street":"Carrer De Permanyer",
    "iso:country":"ES",
    "sg:address":"Carrer de Permanyer, 302",
    "sg:city":"Sabadell",
    "sg:orig_category":"Empresas De Carpinter\u00cda De Madera",
    "sg:phone":"+34 937 10 33 48",
    "sg:postcode":"08205",
    "sg:province":"Barcelona",
    "wof:name":"Puig Carreras Jaume",
    "wof:placetype":"venue"
},
  "geometry": {"coordinates":[2.1021149158,41.5350265503],"type":"Point"}
}