{
  "type": "Feature",
  "properties": {
    "addr:full":"Calle de Leon Y Castillo, 179 Pto. Rosario Las Palmas 35600",
    "addr:housenumber":"179",
    "addr:postcode":"35600",
    "addr:street":"Calle De Leon Y Castillo;Pto. Rosario Las",
    "iso:country":"ES",
    "sg:address":"Calle de Leon Y Castillo, 179",
    "sg:city":"Pto. Rosario",
    "sg:orig_category":"Florister\u00cdas",
    "sg:phone":"+34 928 85 94 76",
    "sg:postcode":"35600",
    "sg:province":"Las Palmas",
    "wof:name":"Pozorio Guerrero Estebana",
    "wof:placetype":"venue"
},
  "geometry": {"coordinates":[-13.8733291626,28.5027694702],"type":"Point"}
}