{
  "type": "Feature",
  "properties": {
    "addr:full":"Calle de Eduardo Dato, 29 Vitoria-gasteiz \u00c1lava 01005",
    "addr:housenumber":"29",
    "addr:postcode":"01005",
    "addr:street":"Calle De Eduardo Dato",
    "iso:country":"ES",
    "sg:address":"Calle de Eduardo Dato, 29",
    "sg:city":"Vitoria-gasteiz",
    "sg:orig_category":"Abogados",
    "sg:phone":"+34 945 14 45 49",
    "sg:postcode":"01005",
    "sg:province":"\u00c1lava",
    "wof:name":"Santander Martinez Mario",
    "wof:placetype":"venue"
},
  "geometry": {"coordinates":[-2.6722979546,42.8434143066],"type":"Point"}
}