{
  "type": "Feature",
  "properties": {
    "addr:full":"Rond General Mitre, 199 Barcelona Barcelona 08023",
    "addr:housenumber":"199",
    "addr:postcode":"08023",
    "addr:street":"Mitre",
    "iso:country":"ES",
    "sg:address":"Rond General Mitre, 199",
    "sg:city":"Barcelona",
    "sg:orig_category":"Caf\u00c9s, Bares, Cervecer\u00cdas",
    "sg:phone":"+34 932 12 08 73",
    "sg:postcode":"08023",
    "sg:province":"Barcelona",
    "wof:name":"Wu  Yonghao",
    "wof:placetype":"venue"
},
  "geometry": {"coordinates":[2.1423966885,41.405292511],"type":"Point"}
}