{
  "type": "Feature",
  "properties": {
    "iso:country":"ES",
    "sg:address":"Calle de Pacheco, 12",
    "sg:city":"Solana",
    "sg:orig_category":"Zapatos (al Por Menor)",
    "sg:phone":"+34 926 63 39 44",
    "sg:postcode":"13240",
    "sg:province":"Ciudad Real",
    "wof:name":"Calzados Salcedo Mateos S.l",
    "wof:placetype":"venue"
},
  "geometry": {"coordinates":[-3.2368090153,38.94272995],"type":"Point"}
}