{
  "type": "Feature",
  "properties": {
    "addr:full":"Calle de Empedrada, 9 Manzanares Ciudad Real 13200",
    "addr:housenumber":"9",
    "addr:postcode":"13200",
    "addr:street":"Calle De Empedrada",
    "iso:country":"ES",
    "sg:address":"Calle de Empedrada, 9",
    "sg:city":"Manzanares",
    "sg:orig_category":"Bisuter\u00cda, Joyer\u00cda, Relojer\u00cda (al Por Menor)",
    "sg:phone":"+34 926 61 22 03",
    "sg:postcode":"13200",
    "sg:province":"Ciudad Real",
    "wof:name":"Simarro Matamoros Jacoba",
    "wof:placetype":"venue"
},
  "geometry": {"coordinates":[-3.3720190525,38.9964790344],"type":"Point"}
}