{
  "type": "Feature",
  "properties": {
    "iso:country":"ES",
    "sg:address":"Ctra General, S/n",
    "sg:city":"Sevares",
    "sg:orig_category":"Suministros Para Carrocer\u00cdas",
    "sg:phone":"+34 985 70 61 30",
    "sg:postcode":"33584",
    "sg:province":"Asturias",
    "wof:name":"Automoviles Tolivia S.l.",
    "wof:placetype":"venue"
},
  "geometry": {"coordinates":[-5.2607164383,43.3631134033],"type":"Point"}
}