{
  "type": "Feature",
  "properties": {
    "iso:country":"ES",
    "sg:address":"Calle de Beata Mariana, 7",
    "sg:city":"Burriana",
    "sg:orig_category":"Reposter\u00cdas",
    "sg:phone":"+34 964 51 27 99",
    "sg:postcode":"12530",
    "sg:province":"Castell\u00f3n",
    "wof:name":"Masip Garcia Jose",
    "wof:placetype":"venue"
},
  "geometry": {"coordinates":[-0.0808344036,39.8889160156],"type":"Point"}
}