{
  "type": "Feature",
  "properties": {
    "addr:full":"Larra\u00f1aga Area, 4 Urrestilla Guip\u00f9zcoa 20738",
    "addr:postcode":"20738",
    "addr:street":"Guipu\u0300Zcoa",
    "iso:country":"ES",
    "sg:address":"Larra\u00f1aga Area, 4",
    "sg:city":"Urrestilla",
    "sg:orig_category":"Pintura, Barniz, Productos Asimilables (fabricaci\u00d3n, Al Por Mayor)",
    "sg:phone":"+34 943 15 09 23",
    "sg:postcode":"20738",
    "sg:province":"Guip\u00f9zcoa",
    "wof:name":"Productos Solrac S.a.",
    "wof:placetype":"venue"
},
  "geometry": {"coordinates":[-2.2421760559,43.107749939],"type":"Point"}
}