{
  "type": "Feature",
  "properties": {
    "addr:full":"Fase Tres (p I La Luz), S/n Huelva Huelva 21007",
    "addr:housenumber":"s / n",
    "addr:postcode":"21007",
    "addr:street":"Luz",
    "iso:country":"ES",
    "sg:address":"Fase Tres (p I La Luz), S/n",
    "sg:city":"Huelva",
    "sg:orig_category":"Empresas De Limpieza",
    "sg:phone":"+34 959 23 26 89",
    "sg:postcode":"21007",
    "sg:province":"Huelva",
    "wof:name":"Eulen S.a.",
    "wof:placetype":"venue"
},
  "geometry": {"coordinates":[-6.9495940208,37.256313324],"type":"Point"}
}