{
  "type": "Feature",
  "properties": {
    "addr:full":"Carrer de Francesc Macia, 94 S. Boi Llobregat Barcelona 08830",
    "addr:housenumber":"94",
    "addr:postcode":"08830",
    "addr:street":"Carrer De Francesc Macia",
    "iso:country":"ES",
    "sg:address":"Carrer de Francesc Macia, 94",
    "sg:city":"S. Boi Llobregat",
    "sg:orig_category":"Librer\u00cdas",
    "sg:phone":"+34 936 61 40 97",
    "sg:postcode":"08830",
    "sg:province":"Barcelona",
    "wof:name":"Tirado Colet Jose",
    "wof:placetype":"venue"
},
  "geometry": {"coordinates":[2.0444378853,41.3387413025],"type":"Point"}
}