{
  "type": "Feature",
  "properties": {
    "addr:full":"Avda Blas Infante, 60 Posadas C\u00f3rdoba 14730",
    "addr:housenumber":"60;co\u0301rdoba",
    "addr:postcode":"14730",
    "addr:street":"Avda Blas Infante",
    "iso:country":"ES",
    "sg:address":"Avda Blas Infante, 60",
    "sg:city":"Posadas",
    "sg:orig_category":"Empresarios",
    "sg:phone":"+34 957 63 10 31",
    "sg:postcode":"14730",
    "sg:province":"C\u00f3rdoba",
    "wof:name":"Fundacion Francisco Martinez Benavides",
    "wof:placetype":"venue"
},
  "geometry": {"coordinates":[-97.78224945069999,45.7040786743],"type":"Point"}
}