{
  "type": "Feature",
  "properties": {
    "iso:country":"ES",
    "sg:address":"Rafael R, 2",
    "sg:city":"Selva Del Camp",
    "sg:orig_category":"Notarios",
    "sg:phone":"+34 977 84 48 49",
    "sg:postcode":"43470",
    "sg:province":"Tarragona",
    "wof:name":"Linage Hernanz Eva Alejandra",
    "wof:placetype":"venue"
},
  "geometry": {"coordinates":[1.1409749985,41.2144813538],"type":"Point"}
}