{
  "type": "Feature",
  "properties": {
    "addr:full":"Trva Montserrat (de), 10 San Fernando De Henares Madrid 28830",
    "addr:housenumber":"10",
    "addr:postcode":"28830",
    "addr:street":"Trva Montserrat De",
    "iso:country":"ES",
    "sg:address":"Trva Montserrat (de), 10",
    "sg:city":"San Fernando De Henares",
    "sg:orig_category":"Asesor\u00cda Sobre Comunicaci\u00d3n De Empresas",
    "sg:phone":"+34 916 73 84 98",
    "sg:postcode":"28830",
    "sg:province":"Madrid",
    "wof:name":"Asecon Gestion Empresarial S.l.",
    "wof:placetype":"venue"
},
  "geometry": {"coordinates":[-3.510453701,40.4290542603],"type":"Point"}
}