{
  "type": "Feature",
  "properties": {
    "addr:full":"Calle de Antonio Ordo\u00d1ez, 1 Batan C\u00e1ceres 10692",
    "addr:housenumber":"1",
    "addr:postcode":"10692",
    "addr:street":"Calle De Antonio Ordon\u0303Ez;Ca\u0301Ceres",
    "iso:country":"ES",
    "sg:address":"Calle de Antonio Ordo\u00d1ez, 1",
    "sg:city":"Batan",
    "sg:orig_category":"Hospitales",
    "sg:phone":"+34 927 67 29 13",
    "sg:postcode":"10692",
    "sg:province":"C\u00e1ceres",
    "wof:name":"Caja De Ahorros Y Monte De Piedad De Extremadura",
    "wof:placetype":"venue"
},
  "geometry": {"coordinates":[-6.378223896,39.9713592529],"type":"Point"}
}