{
  "type": "Feature",
  "properties": {
    "iso:country":"ES",
    "sg:address":"Calle de Cervantes, 18",
    "sg:city":"Rozas De Madrid",
    "sg:orig_category":"Laboratorios Farmac\u00c9uticos",
    "sg:phone":"+34 916 37 07 89",
    "sg:postcode":"28230",
    "sg:province":"Madrid",
    "wof:name":"Ortiz Garcia Pilar",
    "wof:placetype":"venue"
},
  "geometry": {"coordinates":[-4.4931716919,40.3089523315],"type":"Point"}
}