{
  "type": "Feature",
  "properties": {
    "iso:country":"ES",
    "sg:address":"Calle de Castilla La Nueva (de), 19",
    "sg:city":"Fuenlabrada",
    "sg:orig_category":"Centros De Coordinaci\u00d3n",
    "sg:phone":"+34 916 15 41 61",
    "sg:postcode":"28941",
    "sg:province":"Madrid",
    "wof:name":"Iglesias Heras Daniel",
    "wof:placetype":"venue"
},
  "geometry": {"coordinates":[-3.7973825932,40.2935028076],"type":"Point"}
}