{
  "type": "Feature",
  "properties": {
    "addr:full":"Pol. Industrial, 30 Jodar Ja\u00e9n 23500",
    "addr:housenumber":"30",
    "addr:postcode":"23500",
    "addr:street":"Pol. Industrial;Jae\u0301N",
    "iso:country":"ES",
    "sg:address":"Pol. Industrial, 30",
    "sg:city":"Jodar",
    "sg:orig_category":"Frutas Y Legumbres Frescas (al Por Mayor)",
    "sg:phone":"+34 953 78 90 92",
    "sg:postcode":"23500",
    "sg:province":"Ja\u00e9n",
    "wof:name":"Villaflores Hortofruticola S.c.a.",
    "wof:placetype":"venue"
},
  "geometry": {"coordinates":[-3.3526489735,37.8448600769],"type":"Point"}
}