{
  "type": "Feature",
  "properties": {
    "iso:country":"ES",
    "sg:address":"Calle de Santa Maria De Nieva, 1",
    "sg:city":"Segovia",
    "sg:orig_category":"Droguer\u00cdas (al Por Menor)",
    "sg:phone":"+34 921 43 66 27",
    "sg:postcode":"40003",
    "sg:province":"Segovia",
    "wof:name":"Lopez De Frutos Pablo",
    "wof:placetype":"venue"
},
  "geometry": {"coordinates":[-4.1162567139,40.9497451782],"type":"Point"}
}