{
  "type": "Feature",
  "properties": {
    "iso:country":"ES",
    "sg:address":"Calle de Enmedio, 97",
    "sg:city":"Castellon",
    "sg:orig_category":"Lencer\u00cda Femenina, Corseter\u00cda, Trajes De Ba\u00d1o (al Por Menor)",
    "sg:phone":"+34 964 24 77 97",
    "sg:postcode":"12001",
    "sg:province":"Castell\u00f3n",
    "wof:name":"Lopez Centelles Maria Eugenia",
    "wof:placetype":"venue"
},
  "geometry": {"coordinates":[-0.0378820002,39.9877548218],"type":"Point"}
}