{
  "type": "Feature",
  "properties": {
    "addr:full":"Emma Abadessa, 17 La Garriga Barcelona 08530",
    "addr:housenumber":"17",
    "addr:postcode":"08530",
    "iso:country":"ES",
    "sg:address":"Emma Abadessa, 17",
    "sg:city":"La Garriga",
    "sg:orig_category":"Caf\u00c9s, Bares, Cervecer\u00cdas",
    "sg:phone":"+34 938 71 80 35",
    "sg:postcode":"08530",
    "sg:province":"Barcelona",
    "wof:name":"Fleca Degustacio Ca N Illa",
    "wof:placetype":"venue"
},
  "geometry": {"coordinates":[2.2863399982,41.6740608215],"type":"Point"}
}