{
  "type": "Feature",
  "properties": {
    "iso:country":"ES",
    "sg:address":"El Pla, S/n",
    "sg:city":"Pol. Ind. Pla",
    "sg:orig_category":"Comercio De Piezas De Recambio Y De Accesorios De Veh\u00cdculos, Veh\u00cdculos Industriales",
    "sg:phone":"+34 961 22 13 80",
    "sg:postcode":"46290",
    "sg:province":"Valencia",
    "wof:name":"Insonorizantes Pelzer S.a.",
    "wof:placetype":"venue"
},
  "geometry": {"coordinates":[-0.4453490078,39.3651695251],"type":"Point"}
}