{
  "type": "Feature",
  "properties": {
    "addr:full":"Calle de Paraguay, 19 Alcantarilla Murcia 30820",
    "addr:housenumber":"19",
    "addr:postcode":"30820",
    "addr:street":"Calle De Paraguay",
    "iso:country":"ES",
    "sg:address":"Calle de Paraguay, 19",
    "sg:city":"Alcantarilla",
    "sg:orig_category":"Promotores Constructores",
    "sg:phone":"+34 968 83 60 88",
    "sg:postcode":"30820",
    "sg:province":"Murcia",
    "wof:name":"Jesan S.l.",
    "wof:placetype":"venue"
},
  "geometry": {"coordinates":[-1.2003959417,37.9537010193],"type":"Point"}
}