{
  "type": "Feature",
  "properties": {
    "addr:full":"Calle de Barrionuevo, 41 Mora Toledo 45400",
    "addr:housenumber":"41",
    "addr:postcode":"45400",
    "addr:street":"Calle De Barrionuevo",
    "iso:country":"ES",
    "sg:address":"Calle de Barrionuevo, 41",
    "sg:city":"Mora",
    "sg:orig_category":"Carnicer\u00cdas, Carnicer\u00cdas",
    "sg:phone":"+34 925 30 10 80",
    "sg:postcode":"45400",
    "sg:province":"Toledo",
    "wof:name":"Sanchez-cano De La Cruz Jose Luis",
    "wof:placetype":"venue"
},
  "geometry": {"coordinates":[-3.7711112499,39.6817550659],"type":"Point"}
}