{
  "type": "Feature",
  "properties": {
    "addr:full":"Ctra Funes, S/n Marcilla Navarra 31340",
    "addr:housenumber":"s / n",
    "addr:postcode":"31340",
    "addr:street":"Ctra Funes;Navarra",
    "iso:country":"ES",
    "sg:address":"Ctra Funes, S/n",
    "sg:city":"Marcilla",
    "sg:orig_category":"Agencias Y Agentes Comerciales, Representantes",
    "sg:phone":"+34 948 71 37 36",
    "sg:postcode":"31340",
    "sg:province":"Navarra",
    "wof:name":"Carlos Catalan S.l.",
    "wof:placetype":"venue"
},
  "geometry": {"coordinates":[-1.7424490452,42.327255249],"type":"Point"}
}