{
  "type": "Feature",
  "properties": {
    "iso:country":"ES",
    "sg:address":"Calle de Reyes Catolicos, 7",
    "sg:city":"Palos Frontera",
    "sg:orig_category":"Ense\u00d1anza: Comercio, Gesti\u00d3n, Inform\u00c1tica",
    "sg:phone":"+34 959 35 03 63",
    "sg:postcode":"21810",
    "sg:province":"Huelva",
    "sg:website":"www.worldwidecentre.com",
    "wof:name":"W.w.c. Palos Computer English Centre S.l.",
    "wof:placetype":"venue"
},
  "geometry": {"coordinates":[-6.8940877914,37.2287216187],"type":"Point"}
}