{
  "type": "Feature",
  "properties": {
    "addr:full":"Calle de Lope De Vega, 1 Granada Granada 18002",
    "addr:housenumber":"1",
    "addr:postcode":"18002",
    "addr:street":"Calle De Lope De Vega",
    "iso:country":"ES",
    "sg:address":"Calle de Lope De Vega, 1",
    "sg:city":"Granada",
    "sg:orig_category":"Granos Y Semillas (producci\u00d3n, Al Por Mayor)",
    "sg:phone":"+34 958 53 65 25",
    "sg:postcode":"18002",
    "sg:province":"Granada",
    "wof:name":"Hernandez Garcia Antonio Jesus",
    "wof:placetype":"venue"
},
  "geometry": {"coordinates":[-3.6050150394,37.1716346741],"type":"Point"}
}