{
  "type": "Feature",
  "properties": {
    "iso:country":"ES",
    "sg:address":"Calle de Santa Engracia, 30",
    "sg:city":"Madrid",
    "sg:orig_category":"Arquitectos",
    "sg:phone":"+34 914 48 04 57",
    "sg:postcode":"28010",
    "sg:province":"Madrid",
    "wof:name":"Planchuelo Martinez De Haro Alvaro",
    "wof:placetype":"venue"
},
  "geometry": {"coordinates":[-3.6970369816,40.4315071106],"type":"Point"}
}