{
  "type": "Feature",
  "properties": {
    "iso:country":"ES",
    "sg:address":"Calle de Gremio De Los Caldereros (del), 4",
    "sg:city":"Hontoria",
    "sg:orig_category":"Venta, Localizaci\u00d3n, Reparaci\u00d3n De Material E Instrumental M\u00c9dico",
    "sg:phone":"+34 921 41 29 43",
    "sg:postcode":"40195",
    "sg:province":"Segovia",
    "sg:website":"www.biolinesupply.com",
    "wof:name":"Bioline Supply S.l.l.",
    "wof:placetype":"venue"
},
  "geometry": {"coordinates":[-4.1077542305,40.9125099182],"type":"Point"}
}