{
  "type": "Feature",
  "properties": {
    "iso:country":"ES",
    "sg:address":"Avda Alamos (los), S/n",
    "sg:city":"Elda",
    "sg:orig_category":"Internados & Ense\u00d1anza Privada",
    "sg:phone":"+34 965 38 34 33",
    "sg:postcode":"03600",
    "sg:province":"Alicante",
    "wof:name":"Colegio Santa Maria Del Carmen",
    "wof:placetype":"venue"
},
  "geometry": {"coordinates":[-0.7883239985,38.4724731445],"type":"Point"}
}