{
  "type": "Feature",
  "properties": {
    "addr:full":"Zaramaga Carrer de Carrer de Boulevard De Vitoria, 1 Vitoria-gasteiz \u00c1lava 01013",
    "addr:housenumber":"1",
    "addr:postcode":"01013",
    "addr:street":"Carrer De Carrer De Boulevard De Vitoria",
    "iso:country":"ES",
    "sg:address":"Zaramaga Carrer de Carrer de Boulevard De Vitoria, 1",
    "sg:city":"Vitoria-gasteiz",
    "sg:orig_category":"Reposter\u00cdas",
    "sg:phone":"+34 945 06 55 55",
    "sg:postcode":"01013",
    "sg:province":"\u00c1lava",
    "sg:website":"www.artepan.com",
    "wof:name":"Artepan, S.a.",
    "wof:placetype":"venue"
},
  "geometry": {"coordinates":[-2.6844079494,42.839717865],"type":"Point"}
}