{
  "type": "Feature",
  "properties": {
    "addr:full":"Carrer de Valencia, 252 Barcelona Barcelona 08007",
    "addr:housenumber":"252",
    "addr:postcode":"08007",
    "addr:street":"Carrer De Valencia",
    "iso:country":"ES",
    "sg:address":"Carrer de Valencia, 252",
    "sg:city":"Barcelona",
    "sg:orig_category":"Administradores De Bienes Y Delegados De Comunidades De Propietarios",
    "sg:phone":"+34 934 87 14 61",
    "sg:postcode":"08007",
    "sg:province":"Barcelona",
    "wof:name":"De La Pe\u00f1a Puig Pilar",
    "wof:placetype":"venue"
},
  "geometry": {"coordinates":[2.1617619991,41.3913421631],"type":"Point"}
}