{
  "type": "Feature",
  "properties": {
    "iso:country":"ES",
    "sg:address":"Rua Benito Corbal, 10",
    "sg:city":"Pontevedra",
    "sg:orig_category":"M\u00c9dicos: Ginecolog\u00cda Y Obstetricia",
    "sg:phone":"+34 986 84 15 16",
    "sg:postcode":"36001",
    "sg:province":"Pontevedra",
    "wof:name":"Alonso San Martin Francisco Javier",
    "wof:placetype":"venue"
},
  "geometry": {"coordinates":[-8.6422281265,42.4305915833],"type":"Point"}
}