{
  "type": "Feature",
  "properties": {
    "iso:country":"ES",
    "sg:address":"Cmno Ronda (de), 127",
    "sg:city":"Granada",
    "sg:orig_category":"Pe\u00d1as Y Asociaciones Varias",
    "sg:phone":"+34 958 28 33 13",
    "sg:postcode":"18003",
    "sg:province":"Granada",
    "wof:name":"Asociacion Profesional De Representantes De Comercio",
    "wof:placetype":"venue"
},
  "geometry": {"coordinates":[-3.6111280918,37.1787185669],"type":"Point"}
}