{
  "type": "Feature",
  "properties": {
    "iso:country":"ES",
    "sg:address":"Calle de Melquiades Alvarez, 5",
    "sg:city":"Oviedo",
    "sg:orig_category":"Perfumer\u00cda (al Por Menor)",
    "sg:phone":"+34 985 21 97 94",
    "sg:postcode":"33002",
    "sg:province":"Asturias",
    "wof:name":"Drogueria E Industrias Reunidas S. A.",
    "wof:placetype":"venue"
},
  "geometry": {"coordinates":[-5.8504328728,43.3645057678],"type":"Point"}
}