{
  "type": "Feature",
  "properties": {
    "addr:full":"Calle de Pintores (los), 6 Alcorcon Madrid 28925",
    "addr:housenumber":"6",
    "addr:postcode":"28925",
    "addr:street":"Calle De Pintores Los",
    "iso:country":"ES",
    "sg:address":"Calle de Pintores (los), 6",
    "sg:city":"Alcorcon",
    "sg:orig_category":"Empresas De Desmonte",
    "sg:phone":"+34 916 41 67 10",
    "sg:postcode":"28925",
    "sg:province":"Madrid",
    "wof:name":"Chajamen S.l.",
    "wof:placetype":"venue"
},
  "geometry": {"coordinates":[-3.8086390495,40.3402404785],"type":"Point"}
}