{
  "type": "Feature",
  "properties": {
    "addr:full":"Avda Alcalde Gregorio Espino, 35 Vigo Pontevedra 36205",
    "addr:housenumber":"35",
    "addr:postcode":"36205",
    "addr:street":"Avda Alcalde Gregorio Espino",
    "iso:country":"ES",
    "sg:address":"Avda Alcalde Gregorio Espino, 35",
    "sg:city":"Vigo",
    "sg:orig_category":"Delegados, Agentes De Tr\u00c1nsito, Auxiliares De Transporte Internacional",
    "sg:phone":"+34 986 27 67 29",
    "sg:postcode":"36205",
    "sg:province":"Pontevedra",
    "wof:name":"Filgueira Abeijon Ignacio",
    "wof:placetype":"venue"
},
  "geometry": {"coordinates":[-8.7068481445,42.2298049927],"type":"Point"}
}