{
  "type": "Feature",
  "properties": {
    "addr:full":"Calle de General Aguilera, 58 Argamasilla Alba Ciudad Real 13710",
    "addr:housenumber":"58",
    "addr:postcode":"alba;13710",
    "addr:street":"Calle De General Aguilera",
    "iso:country":"ES",
    "sg:address":"Calle de General Aguilera, 58",
    "sg:city":"Argamasilla Alba",
    "sg:orig_category":"Escayola Y Productos De Escayola (fabricaci\u00d3n, Al Por Mayor)",
    "sg:phone":"+34 926 52 34 98",
    "sg:postcode":"13710",
    "sg:province":"Ciudad Real",
    "wof:name":"Escayolas Y Yesos Villena S.l.",
    "wof:placetype":"venue"
},
  "geometry": {"coordinates":[-3.0933599472,39.1312980652],"type":"Point"}
}