{
  "type": "Feature",
  "properties": {
    "addr:full":"Calle de Fontana, 8 Jerez De La Frontera C\u00e1diz 11402",
    "addr:housenumber":"8",
    "addr:postcode":"11402",
    "addr:street":"Calle De Fontana",
    "iso:country":"ES",
    "sg:address":"Calle de Fontana, 8",
    "sg:city":"Jerez De La Frontera",
    "sg:orig_category":"Ense\u00d1anza Variada",
    "sg:phone":"+34 956 32 03 18",
    "sg:postcode":"11402",
    "sg:province":"C\u00e1diz",
    "wof:name":"Zejegym C.b.",
    "wof:placetype":"venue"
},
  "geometry": {"coordinates":[-6.133934021,36.6832962036],"type":"Point"}
}