{
  "type": "Feature",
  "properties": {
    "addr:full":"Praz Constitucion 1812, 7 Redondela Pontevedra 36800",
    "addr:housenumber":"7",
    "addr:postcode":"36800",
    "addr:street":"1812",
    "iso:country":"ES",
    "sg:address":"Praz Constitucion 1812, 7",
    "sg:city":"Redondela",
    "sg:orig_category":"Ropa Para Ni\u00d1os (al Por Menor)",
    "sg:phone":"+34 986 40 10 90",
    "sg:postcode":"36800",
    "sg:province":"Pontevedra",
    "wof:name":"Rivas Araujo Fernando",
    "wof:placetype":"venue"
},
  "geometry": {"coordinates":[-8.608669281,42.2839317322],"type":"Point"}
}