{
  "type": "Feature",
  "properties": {
    "iso:country":"ES",
    "sg:address":"Carrer de Pelai, 12",
    "sg:city":"Barcelona",
    "sg:orig_category":"Promotores Constructores",
    "sg:phone":"+34 933 42 58 31",
    "sg:postcode":"08001",
    "sg:province":"Barcelona",
    "wof:name":"Misal 2004 S.l.",
    "wof:placetype":"venue"
},
  "geometry": {"coordinates":[2.1656289101,41.3857383728],"type":"Point"}
}