{
  "type": "Feature",
  "properties": {
    "iso:country":"ES",
    "sg:address":"C/ Nuestra Se\u00d1ora De La Cabeza, 21",
    "sg:city":"Elche",
    "sg:orig_category":"Fabricaci\u00d3n De Harinas, S\u00c9molas, Productos De Elaboraci\u00d3n Del Grano",
    "sg:phone":"+34 965 42 30 60",
    "sg:postcode":"03202",
    "sg:province":"Alicante",
    "wof:name":"Andres Serrano S.a.",
    "wof:placetype":"venue"
},
  "geometry": {"coordinates":[-0.6947439909,38.2706298828],"type":"Point"}
}