{
  "type": "Feature",
  "properties": {
    "addr:full":"Av Pau, De La, S/n Eivissa Islas Baleares 07800",
    "addr:postcode":"07800",
    "addr:street":"Av Pau De La S / N",
    "iso:country":"ES",
    "sg:address":"Av Pau, De La, S/n",
    "sg:city":"Eivissa",
    "sg:orig_category":"Ense\u00d1anza, Formaci\u00d3n Profesional: Aprendizaje",
    "sg:phone":"+34 971 30 67 18",
    "sg:postcode":"07800",
    "sg:province":"Islas Baleares",
    "sg:website":"www.mir.es}}",
    "wof:name":"Direccion General De La Policia",
    "wof:placetype":"venue"
},
  "geometry": {"coordinates":[1.4188899994,38.9061164856],"type":"Point"}
}