{
  "type": "Feature",
  "properties": {
    "addr:full":"Calle de San Vicente De Paul, 3 Vitoria-gasteiz \u00c1lava 01001",
    "addr:housenumber":"3",
    "addr:postcode":"01001",
    "addr:street":"Calle De San Vicente De Paul",
    "iso:country":"ES",
    "sg:address":"Calle de San Vicente De Paul, 3",
    "sg:city":"Vitoria-gasteiz",
    "sg:orig_category":"Funcionario",
    "sg:phone":"+34 945 25 02 09",
    "sg:postcode":"01001",
    "sg:province":"\u00c1lava",
    "wof:name":"Colegio Vasco De Economistas",
    "wof:placetype":"venue"
},
  "geometry": {"coordinates":[-2.6701579094,42.8492088318],"type":"Point"}
}