{
  "type": "Feature",
  "properties": {
    "iso:country":"ES",
    "sg:address":"Avgd Valencia, 24",
    "sg:city":"Muro Alcoy",
    "sg:orig_category":"Inmobiliaria (agencias)",
    "sg:phone":"+34 966 54 41 16",
    "sg:postcode":"03830",
    "sg:province":"Alicante",
    "wof:name":"Solana Inmobiliaria 2003 S.l.",
    "wof:placetype":"venue"
},
  "geometry": {"coordinates":[-0.4414289892,38.7812538147],"type":"Point"}
}