{
  "type": "Feature",
  "properties": {
    "addr:full":"Avda Pio Baroja, 14 Malaga M\u00e1laga 29017",
    "addr:housenumber":"14",
    "addr:postcode":"29017",
    "addr:street":"Avda Pio Baroja;Ma\u0301Laga",
    "iso:country":"ES",
    "sg:address":"Avda Pio Baroja, 14",
    "sg:city":"Malaga",
    "sg:orig_category":"Herboristas (al Por Menor)",
    "sg:phone":"+34 952 29 26 41",
    "sg:postcode":"29017",
    "sg:province":"M\u00e1laga",
    "wof:name":"Ortega Sanchez Jose",
    "wof:placetype":"venue"
},
  "geometry": {"coordinates":[-4.3632087708,36.7201576233],"type":"Point"}
}