{
  "type": "Feature",
  "properties": {
    "addr:full":"Avda Escaleritas, 30 Palmas De Gran Canaria Las Palmas 35011",
    "addr:housenumber":"30",
    "addr:postcode":"35011",
    "addr:street":"Avda Escaleritas",
    "iso:country":"ES",
    "sg:address":"Avda Escaleritas, 30",
    "sg:city":"Palmas De Gran Canaria",
    "sg:orig_category":"Empresas De Limpieza",
    "sg:phone":"+34 928 26 70 87",
    "sg:postcode":"35011",
    "sg:province":"Las Palmas",
    "wof:name":"Clecer S.a.",
    "wof:placetype":"venue"
},
  "geometry": {"coordinates":[-15.4359912872,28.1226882935],"type":"Point"}
}