{
  "type": "Feature",
  "properties": {
    "iso:country":"ES",
    "sg:address":"Poli Industrial Francoli, S/n",
    "sg:city":"Campsa",
    "sg:orig_category":"Alquiler De Gr\u00daas",
    "sg:phone":"+34 977 55 15 88",
    "sg:postcode":"43006",
    "sg:province":"Tarragona",
    "wof:name":"De La Rosa Garcia Joaquin",
    "wof:placetype":"venue"
},
  "geometry": {"coordinates":[1.2209249735,41.1154441833],"type":"Point"}
}