{
  "type": "Feature",
  "properties": {
    "iso:country":"ES",
    "sg:address":"Av Republica Argentina, 270",
    "sg:city":"Barcelona",
    "sg:orig_category":"Aparcamientos (infraestructuras, Accesorios)",
    "sg:phone":"+34 934 18 00 88",
    "sg:postcode":"08023",
    "sg:province":"Barcelona",
    "wof:name":"Format S.a.",
    "wof:placetype":"venue"
},
  "geometry": {"coordinates":[2.1386198997,41.4136619568],"type":"Point"}
}