{
  "type": "Feature",
  "properties": {
    "iso:country":"ES",
    "sg:address":"Plaz Baco, 1",
    "sg:city":"Selaya",
    "sg:orig_category":"Contenedores (mercanc\u00cdas)",
    "sg:phone":"+34 942 59 04 98",
    "sg:postcode":"39696",
    "sg:province":"Cantabria",
    "wof:name":"Abascal Diego Ramon",
    "wof:placetype":"venue"
},
  "geometry": {"coordinates":[-3.753666,43.200417],"type":"Point"}
}