{
  "type": "Feature",
  "properties": {
    "iso:country":"ES",
    "sg:address":"Avgd Balmes, 36",
    "sg:city":"Lleida",
    "sg:classifiers":[
        {
            "category":"Autos & Motor Vehicles",
            "subcategory":"Automobile Sales",
            "type":"Retail Goods"
        }
    ],
    "sg:phone":"+34 973 24 42 47",
    "sg:postcode":"25006",
    "sg:province":"Lleida",
    "wof:name":"Autoescola J.vila S.c.p.",
    "wof:placetype":"venue"
},
  "geometry": {"coordinates":[0.6196799874,41.6186447144],"type":"Point"}
}