{
  "type": "Feature",
  "properties": {
    "addr:full":"Calle de Gorbea, 38 Vitoria-gasteiz \u00c1lava 01012",
    "addr:housenumber":"38",
    "addr:postcode":"01012",
    "addr:street":"Calle De Gorbea",
    "iso:country":"ES",
    "sg:address":"Calle de Gorbea, 38",
    "sg:city":"Vitoria-gasteiz",
    "sg:orig_category":"Poller\u00cda Y Caza (al Por Menor)",
    "sg:phone":"+34 945 22 48 57",
    "sg:postcode":"01012",
    "sg:province":"\u00c1lava",
    "wof:name":"Derivados De Aves Y Conejos S.l.",
    "wof:placetype":"venue"
},
  "geometry": {"coordinates":[-2.6793079376,42.851890564],"type":"Point"}
}