{
  "type": "Feature",
  "properties": {
    "iso:country":"ES",
    "sg:address":"Calle de Bronce, 13",
    "sg:city":"Moraleja Enmedio",
    "sg:orig_category":"Afilado",
    "sg:phone":"+34 916 09 44 96",
    "sg:postcode":"28950",
    "sg:province":"Madrid",
    "wof:name":"Herramientas Especiales Del Metal S.l.",
    "wof:placetype":"venue"
},
  "geometry": {"coordinates":[-3.8496496677,40.2635803223],"type":"Point"}
}