{
  "type": "Feature",
  "properties": {
    "addr:full":"Calle de Mexico, 94 Arrecife Las Palmas 35500",
    "addr:housenumber":"94",
    "addr:postcode":"35500",
    "addr:street":"Calle De Mexico",
    "iso:country":"ES",
    "sg:address":"Calle de Mexico, 94",
    "sg:city":"Arrecife",
    "sg:orig_category":"Chapister\u00cda",
    "sg:phone":"+34 928 81 30 38",
    "sg:postcode":"35500",
    "sg:province":"Las Palmas",
    "wof:name":"Lois Fernandez Eduardo",
    "wof:placetype":"venue"
},
  "geometry": {"coordinates":[-13.5580530167,28.9639568329],"type":"Point"}
}