{
  "type": "Feature",
  "properties": {
    "iso:country":"ES",
    "sg:address":"Plaz San Juan Bautista La Salle, S/n",
    "sg:city":"Santa Cruz De Tenerife",
    "sg:orig_category":"Arquitectos",
    "sg:phone":"+34 922 21 71 90",
    "sg:postcode":"38005",
    "sg:province":"Santa Cruz De Tenerife",
    "wof:name":"Llopis Areny Pedro",
    "wof:placetype":"venue"
},
  "geometry": {"coordinates":[-16.2595691681,28.4578227997],"type":"Point"}
}