{
  "type": "Feature",
  "properties": {
    "addr:full":"Calle de Redentor, 11 Madrid Madrid 28044",
    "addr:housenumber":"11",
    "addr:postcode":"madrid;28044",
    "addr:street":"Calle De Redentor",
    "iso:country":"ES",
    "sg:address":"Calle de Redentor, 11",
    "sg:city":"Madrid",
    "sg:orig_category":"Peluqueros: De Se\u00d1oras",
    "sg:phone":"+34 915 08 10 63",
    "sg:postcode":"28044",
    "sg:province":"Madrid",
    "wof:name":"Mena Buendia Purificacion",
    "wof:placetype":"venue"
},
  "geometry": {"coordinates":[-3.7545759678,40.3724899292],"type":"Point"}
}