{
  "type": "Feature",
  "properties": {
    "iso:country":"ES",
    "sg:address":"Calle de Doctor Fco. Vazquez Limon, 16",
    "sg:city":"Huelva",
    "sg:orig_category":"Estancos",
    "sg:phone":"+34 959 25 58 49",
    "sg:postcode":"21002",
    "sg:province":"Huelva",
    "wof:name":"Arreciado Borrero Ana",
    "wof:placetype":"venue"
},
  "geometry": {"coordinates":[-6.9504380226,37.2722816467],"type":"Point"}
}