{
  "type": "Feature",
  "properties": {
    "addr:full":"Poli Poligono Uai-4, S/n Arriandi Vizcaya 48215",
    "addr:housenumber":"s",
    "addr:postcode":"48215",
    "addr:street":"Poligono Uai-4;/ N",
    "iso:country":"ES",
    "sg:address":"Poli Poligono Uai-4, S/n",
    "sg:city":"Arriandi",
    "sg:orig_category":"Centros Empresariales",
    "sg:phone":"+34 946 20 39 69",
    "sg:postcode":"48215",
    "sg:province":"Vizcaya",
    "wof:name":"Arcarazo Eguia Luis Alberto",
    "wof:placetype":"venue"
},
  "geometry": {"coordinates":[-2.6607964039,43.1831130981],"type":"Point"}
}