{
  "type": "Feature",
  "properties": {
    "addr:full":"C/ Sant Bartomeu, 72 Inca Islas Baleares 07300",
    "addr:housenumber":"72",
    "addr:postcode":"07300",
    "addr:street":"C / Sant Bartomeu",
    "iso:country":"ES",
    "sg:address":"C/ Sant Bartomeu, 72",
    "sg:city":"Inca",
    "sg:orig_category":"Fabricaci\u00d3n De Sobres, Bolsas Y Fundas",
    "sg:phone":"+34 971 50 01 99",
    "sg:postcode":"07300",
    "sg:province":"Islas Baleares",
    "wof:name":"Bonnin Forteza Gaspar",
    "wof:placetype":"venue"
},
  "geometry": {"coordinates":[2.9088160992,39.7223358154],"type":"Point"}
}