{
  "type": "Feature",
  "properties": {
    "addr:full":"Calle de Carrera, 25 Toledo Toledo 45003",
    "addr:housenumber":"25",
    "addr:postcode":"45003",
    "addr:street":"Calle De Carrera",
    "iso:country":"ES",
    "sg:address":"Calle de Carrera, 25",
    "sg:city":"Toledo",
    "sg:orig_category":"Formaci\u00d3n Continuada (variada)",
    "sg:phone":"+34 925 24 12 11",
    "sg:postcode":"45003",
    "sg:province":"Toledo",
    "wof:name":"Fundacion Formacion Y Empleo Castilla La Mancha",
    "wof:placetype":"venue"
},
  "geometry": {"coordinates":[-4.0219521523,39.8636550903],"type":"Point"}
}