{
  "type": "Feature",
  "properties": {
    "addr:full":"Calle de Murcia, 4 Angeles Madrid 28223",
    "addr:housenumber":"4",
    "addr:postcode":"28223",
    "addr:street":"Calle De Murcia",
    "iso:country":"ES",
    "sg:address":"Calle de Murcia, 4",
    "sg:city":"Angeles",
    "sg:orig_category":"Inform\u00c1tica (estudios, Servicios, Asesor\u00cda, Formaci\u00d3n)",
    "sg:phone":"+34 915 18 77 26",
    "sg:postcode":"28223",
    "sg:province":"Madrid",
    "wof:name":"Martin Rebollo Jose",
    "wof:placetype":"venue"
},
  "geometry": {"coordinates":[-3.7787160873,40.4044837952],"type":"Point"}
}