{
  "type": "Feature",
  "properties": {
    "iso:country":"ES",
    "sg:address":"Calle de Chueca, 8",
    "sg:city":"Granada",
    "sg:orig_category":"Tintes (fabricaci\u00d3n, Al Por Mayor)",
    "sg:phone":"+34 958 25 60 27",
    "sg:postcode":"18004",
    "sg:province":"Granada",
    "wof:name":"Padilla Solano Lorenzo",
    "wof:placetype":"venue"
},
  "geometry": {"coordinates":[-3.6028189659,37.1676483154],"type":"Point"}
}