{
  "type": "Feature",
  "properties": {
    "addr:full":"Can Boira, 32 La Florida Barcelona 08130",
    "addr:housenumber":"32",
    "addr:postcode":"08130",
    "iso:country":"ES",
    "sg:address":"Can Boira, 32",
    "sg:city":"La Florida",
    "sg:classifiers":[
        {
            "category":"Taxi",
            "type":"Transportation"
        }
    ],
    "sg:phone":"+34 935 60 18 44",
    "sg:postcode":"08130",
    "sg:province":"Barcelona",
    "wof:name":"Gonzalez Pla Esteban",
    "wof:placetype":"venue"
},
  "geometry": {"coordinates":[2.1847810745,41.5225906372],"type":"Point"}
}