{
  "type": "Feature",
  "properties": {
    "iso:country":"ES",
    "sg:address":"Av Constitucio, 124",
    "sg:city":"Castelldefels",
    "sg:orig_category":"Peluquer\u00cdas, Peluquer\u00cda Mixta",
    "sg:phone":"+34 936 36 55 97",
    "sg:postcode":"08860",
    "sg:province":"Barcelona",
    "sg:website":"www.deltrens.com",
    "wof:name":"Peluqueria Raffel Pages",
    "wof:placetype":"venue"
},
  "geometry": {"coordinates":[1.9787310362,41.279800415],"type":"Point"}
}