{
  "type": "Feature",
  "properties": {
    "addr:full":"Carr Lluis Companys, 4 Palafrugell Girona 17200",
    "addr:housenumber":"4",
    "addr:postcode":"17200",
    "addr:street":"Carr Lluis Companys",
    "iso:country":"ES",
    "sg:address":"Carr Lluis Companys, 4",
    "sg:city":"Palafrugell",
    "sg:classifiers":[
        {
            "category":"Taxi",
            "type":"Transportation"
        }
    ],
    "sg:phone":"+34 972 61 22 22",
    "sg:postcode":"17200",
    "sg:province":"Girona",
    "wof:name":"Taxis Costa Brava Sl",
    "wof:placetype":"venue"
},
  "geometry": {"coordinates":[3.1579051018,41.9161949158],"type":"Point"}
}