{
  "type": "Feature",
  "properties": {
    "iso:country":"ES",
    "sg:address":"Ctra Logro\u00d1o A Zaragoza, 11",
    "sg:city":"Ausejo",
    "sg:orig_category":"Material Y Herramientas Agr\u00cdcolas",
    "sg:phone":"+34 941 43 02 94",
    "sg:postcode":"26513",
    "sg:province":"La Rioja",
    "wof:name":"Perez San Juan Jesus",
    "wof:placetype":"venue"
},
  "geometry": {"coordinates":[-2.1675701141,42.3410720825],"type":"Point"}
}