{
  "type": "Feature",
  "properties": {
    "addr:full":"Avgd Marques De Sant Mori, 151 Badalona Barcelona 08914",
    "addr:housenumber":"151",
    "addr:postcode":"08914",
    "addr:street":"Mori",
    "iso:country":"ES",
    "sg:address":"Avgd Marques De Sant Mori, 151",
    "sg:city":"Badalona",
    "sg:orig_category":"Limpieza Con Chorro De Arena Y Con Granalla, Pulido",
    "sg:phone":"+34 933 97 11 21",
    "sg:postcode":"08914",
    "sg:province":"Barcelona",
    "wof:name":"Romero Valverde Francisco Javier",
    "wof:placetype":"venue"
},
  "geometry": {"coordinates":[2.2237100601,41.4420204163],"type":"Point"}
}