{
  "type": "Feature",
  "properties": {
    "iso:country":"ES",
    "sg:address":"Plaz Espa\u00d1a, 5",
    "sg:city":"Miguelturra",
    "sg:orig_category":"Hilaturas, Hilos Y Actividades Relacionadas",
    "sg:phone":"+34 926 24 19 96",
    "sg:postcode":"13170",
    "sg:province":"Ciudad Real",
    "wof:name":"Molina Calero Rita",
    "wof:placetype":"venue"
},
  "geometry": {"coordinates":[-3.8970448971,38.968372345],"type":"Point"}
}