{
  "type": "Feature",
  "properties": {
    "addr:full":"Calle de San Fernando, 44 Santander Cantabria 39010",
    "addr:housenumber":"44",
    "addr:postcode":"39010",
    "addr:street":"Calle De San Fernando",
    "iso:country":"ES",
    "sg:address":"Calle de San Fernando, 44",
    "sg:city":"Santander",
    "sg:orig_category":"Ingenier\u00cda, Centros De Estudios (diversos)",
    "sg:phone":"+34 942 37 33 12",
    "sg:postcode":"39010",
    "sg:province":"Cantabria",
    "wof:name":"Teficar S. A.",
    "wof:placetype":"venue"
},
  "geometry": {"coordinates":[-3.8226890564,43.459728241],"type":"Point"}
}