{
  "type": "Feature",
  "properties": {
    "iso:country":"ES",
    "sg:address":"Carrer de Bolivar, 43",
    "sg:city":"Barcelona",
    "sg:orig_category":"Agentes, Concesionarios Y Sucursales De Veh\u00cdculos",
    "sg:phone":"+34 932 19 81 79",
    "sg:postcode":"08023",
    "sg:province":"Barcelona",
    "wof:name":"Carre\u00f1o Morelli Sergio",
    "wof:placetype":"venue"
},
  "geometry": {"coordinates":[2.146075964,41.4103240967],"type":"Point"}
}