{
  "type": "Feature",
  "properties": {
    "addr:full":"Calle de Gibraltar Espa\u00d1ol, 53 Almeria Almer\u00eda 04007",
    "addr:housenumber":"53",
    "addr:postcode":"04007",
    "addr:street":"Calle De Gibraltar Espan\u0303Ol",
    "iso:country":"ES",
    "sg:address":"Calle de Gibraltar Espa\u00d1ol, 53",
    "sg:city":"Almeria",
    "sg:orig_category":"Arquitectos",
    "sg:phone":"+34 950 23 24 66",
    "sg:postcode":"04007",
    "sg:province":"Almer\u00eda",
    "wof:name":"Aguila Toro Leonardo",
    "wof:placetype":"venue"
},
  "geometry": {"coordinates":[-2.4527945518,36.8293685913],"type":"Point"}
}