{
  "type": "Feature",
  "properties": {
    "iso:country":"ES",
    "sg:address":"Calle de Vea Murguia, 22",
    "sg:city":"Cadiz",
    "sg:orig_category":"Tapiceros Y Tapiceros",
    "sg:phone":"+34 956 22 40 55",
    "sg:postcode":"11003",
    "sg:province":"C\u00e1diz",
    "wof:name":"Comesa\u00f1a Perez Rafael",
    "wof:placetype":"venue"
},
  "geometry": {"coordinates":[-6.2995419502,36.536113739],"type":"Point"}
}