{
  "type": "Feature",
  "properties": {
    "iso:country":"ES",
    "sg:address":"Avda Santa Cruz, 85",
    "sg:city":"San Isidro",
    "sg:orig_category":"Reposter\u00cdas",
    "sg:phone":"+34 922 39 13 08",
    "sg:postcode":"38611",
    "sg:province":"Santa Cruz De Tenerife",
    "wof:name":"Gonzalez Goya Marcos",
    "wof:placetype":"venue"
},
  "geometry": {"coordinates":[-16.558172226,28.0795383453],"type":"Point"}
}