{
  "type": "Feature",
  "properties": {
    "addr:full":"Urb Hawai V, 13 Manga Mar Menor Murcia 30380",
    "addr:housenumber":"13",
    "addr:postcode":"30380",
    "addr:street":"Urb Hawai V",
    "iso:country":"ES",
    "sg:address":"Urb Hawai V, 13",
    "sg:city":"Manga Mar Menor",
    "sg:orig_category":"Abogados",
    "sg:phone":"+34 968 14 36 25",
    "sg:postcode":"30380",
    "sg:province":"Murcia",
    "wof:name":"Sanchez Regueiro I\u00f1aki",
    "wof:placetype":"venue"
},
  "geometry": {"coordinates":[-0.7281540036,37.6686553955],"type":"Point"}
}