{
  "type": "Feature",
  "properties": {
    "addr:full":"Avda Alfonso Xiii, 41 Elda Alicante 03600",
    "addr:housenumber":"41",
    "addr:postcode":"03600",
    "addr:street":"Avda Alfonso Xiii",
    "iso:country":"ES",
    "sg:address":"Avda Alfonso Xiii, 41",
    "sg:city":"Elda",
    "sg:orig_category":"Tapicer\u00cdas",
    "sg:phone":"+34 965 39 13 00",
    "sg:postcode":"03600",
    "sg:province":"Alicante",
    "sg:website":"www.joanvi1981.galeon.com",
    "wof:name":"Gomez De Mora Jose Luis",
    "wof:placetype":"venue"
},
  "geometry": {"coordinates":[-0.7972080112,38.4724884033],"type":"Point"}
}