{
  "type": "Feature",
  "properties": {
    "addr:full":"Ctra Menarguens (de), S/n Balaguer Lleida 25600",
    "addr:postcode":"25600",
    "addr:street":"Ctra Menarguens De S / N",
    "iso:country":"ES",
    "sg:address":"Ctra Menarguens (de), S/n",
    "sg:city":"Balaguer",
    "sg:orig_category":"Fabrica De Cer\u00c1micas",
    "sg:phone":"+34 973 44 51 04",
    "sg:postcode":"25600",
    "sg:province":"Lleida",
    "wof:name":"Ceramica La Coma S. A.",
    "wof:placetype":"venue"
},
  "geometry": {"coordinates":[0.8020899892,41.7799301147],"type":"Point"}
}