{
  "type": "Feature",
  "properties": {
    "addr:full":"Calle de Martin Cortes, 12 Zaragoza Zaragoza 50005",
    "addr:housenumber":"12",
    "addr:postcode":"50005",
    "addr:street":"Calle De Martin Cortes",
    "iso:country":"ES",
    "sg:address":"Calle de Martin Cortes, 12",
    "sg:city":"Zaragoza",
    "sg:orig_category":"Molduras, Junquillos, Listones Y Molduras Perforadas",
    "sg:phone":"+34 976 35 23 10",
    "sg:postcode":"50005",
    "sg:province":"Zaragoza",
    "wof:name":"Morejon Sanz Nicolas",
    "wof:placetype":"venue"
},
  "geometry": {"coordinates":[-0.9003667235,41.6480751038],"type":"Point"}
}