{
  "type": "Feature",
  "properties": {
    "addr:full":"Carr Rossello, 33 Girona Girona 17005",
    "addr:housenumber":"33",
    "addr:postcode":"17005",
    "addr:street":"Carr Rossello",
    "iso:country":"ES",
    "sg:address":"Carr Rossello, 33",
    "sg:city":"Girona",
    "sg:orig_category":"Caf\u00c9s, Bares, Cervecer\u00cdas",
    "sg:phone":"+34 972 40 09 45",
    "sg:postcode":"17005",
    "sg:province":"Girona",
    "wof:name":"Mu\u00f1oz Lozano Maria Carmen",
    "wof:placetype":"venue"
},
  "geometry": {"coordinates":[2.809415102,41.9697265625],"type":"Point"}
}