{
  "type": "Feature",
  "properties": {
    "addr:full":"Carrer de Amargura, 57 Reus Tarragona 43201",
    "addr:housenumber":"57",
    "addr:postcode":"43201",
    "addr:street":"Carrer De Amargura",
    "iso:country":"ES",
    "sg:address":"Carrer de Amargura, 57",
    "sg:city":"Reus",
    "sg:orig_category":"Art\u00cdculos De Regalo (al Por Menor)",
    "sg:phone":"+34 977 34 50 89",
    "sg:postcode":"43201",
    "sg:province":"Tarragona",
    "wof:name":"La Cuca Igualames S.l.",
    "wof:placetype":"venue"
},
  "geometry": {"coordinates":[1.1061769724,41.1575622559],"type":"Point"}
}