{
  "type": "Feature",
  "properties": {
    "iso:country":"ES",
    "sg:address":"Calle de Joaquin Jose Landazuri, 7",
    "sg:city":"Vitoria-gasteiz",
    "sg:orig_category":"Perfumer\u00cda (al Por Menor)",
    "sg:phone":"+34 945 13 15 89",
    "sg:postcode":"01008",
    "sg:province":"\u00c1lava",
    "wof:name":"Gomez De Segura Yarza Eva Maria",
    "wof:placetype":"venue"
},
  "geometry": {"coordinates":[-2.6770789623,42.8475341797],"type":"Point"}
}