{
  "type": "Feature",
  "properties": {
    "addr:full":"Cabanella, S/n Villanueva Asturias 33719",
    "addr:postcode":"33719",
    "addr:street":"Cabanella S / N",
    "iso:country":"ES",
    "sg:address":"Cabanella, S/n",
    "sg:city":"Villanueva",
    "sg:orig_category":"Bebidas",
    "sg:phone":"+34 985 63 19 89",
    "sg:postcode":"33719",
    "sg:province":"Asturias",
    "wof:name":"Gonzalez Cerdeira Francisco",
    "wof:placetype":"venue"
},
  "geometry": {"coordinates":[-6.9859690666,43.3115539551],"type":"Point"}
}