{
  "type": "Feature",
  "properties": {
    "iso:country":"ES",
    "sg:address":"Av Mas De L'oli, 59",
    "sg:city":"P. I. La Cova",
    "sg:orig_category":"Porcelanas, Azulejos (fabricaci\u00d3n, Al Por Mayor)",
    "sg:phone":"+34 961 52 14 54",
    "sg:postcode":"46940",
    "sg:province":"Valencia",
    "wof:name":"Arte Salas S.l.",
    "wof:placetype":"venue"
},
  "geometry": {"coordinates":[-0.4961504936,39.5027885437],"type":"Point"}
}