{
  "type": "Feature",
  "properties": {
    "addr:full":"Avda Alvar Nu\u00d1ez, 9 Sevilla Sevilla 41010",
    "addr:housenumber":"9",
    "addr:postcode":"41010",
    "addr:street":"Avda Alvar Nun\u0303Ez",
    "iso:country":"ES",
    "sg:address":"Avda Alvar Nu\u00d1ez, 9",
    "sg:city":"Sevilla",
    "sg:orig_category":"Droguer\u00cdas (al Por Menor)",
    "sg:phone":"+34 954 33 03 36",
    "sg:postcode":"41010",
    "sg:province":"Sevilla",
    "wof:name":"Nu\u00f1ez Garcia Miguel",
    "wof:placetype":"venue"
},
  "geometry": {"coordinates":[-6.0098829269,37.379699707],"type":"Point"}
}