{
  "type": "Feature",
  "properties": {
    "addr:full":"Carrer de Jaume Balmes, 4 Crevillent Alicante 03330",
    "addr:housenumber":"4",
    "addr:postcode":"03330",
    "addr:street":"Carrer De Jaume Balmes",
    "iso:country":"ES",
    "sg:address":"Carrer de Jaume Balmes, 4",
    "sg:city":"Crevillent",
    "sg:orig_category":"Platos Preparados Refrigerados (fabricaci\u00d3n, Al Por Mayor)",
    "sg:phone":"+34 965 40 25 94",
    "sg:postcode":"03330",
    "sg:province":"Alicante",
    "wof:name":"Perez Valero Antonio Jose",
    "wof:placetype":"venue"
},
  "geometry": {"coordinates":[-0.8096569777,38.2456970215],"type":"Point"}
}