{
  "type": "Feature",
  "properties": {
    "iso:country":"ES",
    "sg:address":"Polig. Pocomaco, S/n",
    "sg:city":"A Coru\u00f1a",
    "sg:orig_category":"Congelados: Productos Alimentarios (fabricaci\u00d3n, Al Por Mayor)",
    "sg:phone":"+34 981 13 31 04",
    "sg:postcode":"15190",
    "sg:province":"La Coru\u00f1a",
    "wof:name":"Alimentacion Salgado S.l.",
    "wof:placetype":"venue"
},
  "geometry": {"coordinates":[-8.4335021973,43.3301010132],"type":"Point"}
}