{
  "type": "Feature",
  "properties": {
    "addr:full":"Calle de Rio, 13 Pe\u00f1iscola Castell\u00f3n 12598",
    "addr:housenumber":"13",
    "addr:postcode":"12598",
    "addr:street":"Calle De Rio;Castello\u0301N",
    "iso:country":"ES",
    "sg:address":"Calle de Rio, 13",
    "sg:city":"Pe\u00f1iscola",
    "sg:orig_category":"Promotores Constructores",
    "sg:phone":"+34 964 48 92 45",
    "sg:postcode":"12598",
    "sg:province":"Castell\u00f3n",
    "wof:name":"Forner Simo Romualdo",
    "wof:placetype":"venue"
},
  "geometry": {"coordinates":[0.4019010067,40.3608131409],"type":"Point"}
}