{
  "type": "Feature",
  "properties": {
    "iso:country":"ES",
    "sg:address":"Avda. Pamplona, 15",
    "sg:city":"Iru\u00f1a",
    "sg:orig_category":"Farmacias",
    "sg:phone":"+34 948 18 55 24",
    "sg:postcode":"31009",
    "sg:province":"Navarra",
    "wof:name":"Farmacia Palma Sagues Sociedad Comanditaria",
    "wof:placetype":"venue"
},
  "geometry": {"coordinates":[-1.6732770205,42.805141449],"type":"Point"}
}