{
  "type": "Feature",
  "properties": {
    "addr:full":"Calle de Mendez Alvaro, 63 Madrid Madrid 28045",
    "addr:housenumber":"63",
    "addr:postcode":"madrid;28045",
    "addr:street":"Calle De Mendez Alvaro",
    "iso:country":"ES",
    "sg:address":"Calle de Mendez Alvaro, 63",
    "sg:city":"Madrid",
    "sg:orig_category":"Inform\u00c1tica: Material Y Suministros",
    "sg:phone":"+34 915 39 84 31",
    "sg:postcode":"28045",
    "sg:province":"Madrid",
    "wof:name":"Soportes Sistemas Software Servicios Y Suministros Informaticos S.l.",
    "wof:placetype":"venue"
},
  "geometry": {"coordinates":[-3.6821742058,40.3974227905],"type":"Point"}
}