{
  "type": "Feature",
  "properties": {
    "addr:full":"Carr Magi Morera, 36 Lleida Lleida 25006",
    "addr:housenumber":"36",
    "addr:postcode":"25006",
    "addr:street":"Carr Magi Morera",
    "iso:country":"ES",
    "sg:address":"Carr Magi Morera, 36",
    "sg:city":"Lleida",
    "sg:orig_category":"Peluquer\u00cdas, Peluquer\u00cda Mixta",
    "sg:phone":"+34 973 23 30 37",
    "sg:postcode":"25006",
    "sg:province":"Lleida",
    "wof:name":"Nu\u00f1ez Florencia Ruth",
    "wof:placetype":"venue"
},
  "geometry": {"coordinates":[0.6173229814,41.6193237305],"type":"Point"}
}