{
  "type": "Feature",
  "properties": {
    "iso:country":"ES",
    "sg:address":"Rond Doctor Ferran, 80",
    "sg:city":"Mataro",
    "sg:orig_category":"Mudanzas",
    "sg:phone":"+34 937 99 17 79",
    "sg:postcode":"08304",
    "sg:province":"Barcelona",
    "sg:website":"www.mudanzasnieto.com",
    "wof:name":"Garrido Nieto Manuel",
    "wof:placetype":"venue"
},
  "geometry": {"coordinates":[2.4347805977,41.546875],"type":"Point"}
}