{
  "type": "Feature",
  "properties": {
    "iso:country":"ES",
    "sg:address":"Carr Monturull, 13",
    "sg:city":"Seu D'urgell",
    "sg:classifiers":[
        {
            "category":"Casinos & Gambling",
            "type":"Entertainment"
        }
    ],
    "sg:phone":"+34 973 36 09 31",
    "sg:postcode":"25700",
    "sg:province":"Lleida",
    "sg:tags":[
        "locale",
        "de",
        "juego"
    ],
    "wof:name":"Nau Trim Tram S.l.",
    "wof:placetype":"venue"
},
  "geometry": {"coordinates":[0.6286280155,41.6175880432],"type":"Point"}
}