{
  "type": "Feature",
  "properties": {
    "addr:full":"Avda Reino (del), 23 Beniel Murcia 30130",
    "addr:housenumber":"23",
    "addr:postcode":"30130",
    "addr:street":"Avda Reino Del",
    "iso:country":"ES",
    "sg:address":"Avda Reino (del), 23",
    "sg:city":"Beniel",
    "sg:orig_category":"Zapatos (al Por Menor)",
    "sg:phone":"+34 968 60 21 18",
    "sg:postcode":"30130",
    "sg:province":"Murcia",
    "wof:name":"Equipo De Moda Y Dise\u00f1o S.l.",
    "wof:placetype":"venue"
},
  "geometry": {"coordinates":[-0.9977149963,38.0484352112],"type":"Point"}
}