{
  "type": "Feature",
  "properties": {
    "addr:full":"Ctra Aranda, 16 Illueca Zaragoza 50250",
    "addr:housenumber":"16",
    "addr:postcode":"50250",
    "addr:street":"Ctra Aranda",
    "iso:country":"ES",
    "sg:address":"Ctra Aranda, 16",
    "sg:city":"Illueca",
    "sg:orig_category":"M\u00c9dicos: Estomatolog\u00cda",
    "sg:phone":"+34 976 82 25 23",
    "sg:postcode":"50250",
    "sg:province":"Zaragoza",
    "wof:name":"Landa Schneider Maria Carmen",
    "wof:placetype":"venue"
},
  "geometry": {"coordinates":[-1.6350140572,41.5382957458],"type":"Point"}
}