{
  "type": "Feature",
  "properties": {
    "addr:full":"Pase Extremadura, 46 Madrid Madrid 28011",
    "addr:housenumber":"46",
    "addr:postcode":"madrid;28011",
    "addr:street":"Extremadura",
    "iso:country":"ES",
    "sg:address":"Pase Extremadura, 46",
    "sg:city":"Madrid",
    "sg:orig_category":"Inmobiliaria (agencias)",
    "sg:phone":"+34 914 64 17 15",
    "sg:postcode":"28011",
    "sg:province":"Madrid",
    "wof:name":"Promociones Y Construcciones Jugarpe S.l.",
    "wof:placetype":"venue"
},
  "geometry": {"coordinates":[-3.7296431065,40.4133720398],"type":"Point"}
}