{
  "type": "Feature",
  "properties": {
    "iso:country":"ES",
    "sg:address":"Casa Astun, S/n",
    "sg:city":"Astun",
    "sg:orig_category":"Quincaller\u00cda (al Por Menor)",
    "sg:phone":"+34 974 37 23 60",
    "sg:postcode":"22889",
    "sg:province":"Huesca",
    "wof:name":"Ferreteria Irigaray S.l.",
    "wof:placetype":"venue"
},
  "geometry": {"coordinates":[-0.5231779814,42.7850799561],"type":"Point"}
}