{
  "type": "Feature",
  "properties": {
    "iso:country":"ES",
    "sg:address":"Carrer de Lleida, 138",
    "sg:city":"Prat Llobregat",
    "sg:orig_category":"Molduras, Junquillos, Listones Y Molduras Perforadas",
    "sg:phone":"+34 934 78 45 43",
    "sg:postcode":"08820",
    "sg:province":"Barcelona",
    "wof:name":"Fernandez Hernandez Jose",
    "wof:placetype":"venue"
},
  "geometry": {"coordinates":[2.1004700661,41.3241920471],"type":"Point"}
}