{
  "type": "Feature",
  "properties": {
    "addr:full":"Avda Aguirre Lehendakari, 155 Bilbao Vizcaya 48015",
    "addr:housenumber":"155",
    "addr:postcode":"48015",
    "addr:street":"Avda Aguirre Lehendakari",
    "iso:country":"ES",
    "sg:address":"Avda Aguirre Lehendakari, 155",
    "sg:city":"Bilbao",
    "sg:orig_category":"Zapatos (al Por Menor)",
    "sg:phone":"+34 944 47 29 35",
    "sg:postcode":"48015",
    "sg:province":"Vizcaya",
    "wof:name":"Otalora Perez Jose Antoio",
    "wof:placetype":"venue"
},
  "geometry": {"coordinates":[-2.9613211155,43.2784767151],"type":"Point"}
}