{
  "type": "Feature",
  "properties": {
    "addr:full":"Avda Osa Mayor, 42 Madrid Madrid 28023",
    "addr:housenumber":"42",
    "addr:postcode":"madrid;28023",
    "addr:street":"Avda Osa Mayor",
    "iso:country":"ES",
    "sg:address":"Avda Osa Mayor, 42",
    "sg:city":"Madrid",
    "sg:orig_category":"Florister\u00cdas",
    "sg:phone":"+34 913 57 35 60",
    "sg:postcode":"28023",
    "sg:province":"Madrid",
    "sg:website":"www.floresdocrys.com",
    "wof:name":"Asensio Garcia Maria Cristina",
    "wof:placetype":"venue"
},
  "geometry": {"coordinates":[-3.7807908058,40.4592323303],"type":"Point"}
}