{
  "type": "Feature",
  "properties": {
    "iso:country":"ES",
    "sg:address":"Pg Canal, 13",
    "sg:city":"S. Joan Despi",
    "sg:orig_category":"Promotores Constructores",
    "sg:phone":"+34 934 77 43 18",
    "sg:postcode":"08970",
    "sg:province":"Barcelona",
    "wof:name":"Instalaciones Cotes S.l.",
    "wof:placetype":"venue"
},
  "geometry": {"coordinates":[2.0590729713,41.3677368164],"type":"Point"}
}