{
  "type": "Feature",
  "properties": {
    "addr:full":"Calle de San Sebastian, 10 Icod De Los Vinos Santa Cruz De Tenerife 38430",
    "addr:housenumber":"10",
    "addr:postcode":"38430",
    "addr:street":"Calle De San Sebastian",
    "iso:country":"ES",
    "sg:address":"Calle de San Sebastian, 10",
    "sg:city":"Icod De Los Vinos",
    "sg:orig_category":"Lencer\u00cda Femenina, Corseter\u00cda, Trajes De Ba\u00d1o (al Por Menor)",
    "sg:phone":"+34 922 81 47 60",
    "sg:postcode":"38430",
    "sg:province":"Santa Cruz De Tenerife",
    "wof:name":"Tornillo S.l.",
    "wof:placetype":"venue"
},
  "geometry": {"coordinates":[-16.7203788757,28.3669910431],"type":"Point"}
}