{
  "type": "Feature",
  "properties": {
    "iso:country":"ES",
    "sg:address":"Calle de Marques De Larios, 1",
    "sg:city":"Malaga",
    "sg:orig_category":"Loter\u00cda Y T\u00d3mbola",
    "sg:phone":"+34 952 21 70 97",
    "sg:postcode":"29015",
    "sg:province":"M\u00e1laga",
    "wof:name":"Bueno Morales Fernando",
    "wof:placetype":"venue"
},
  "geometry": {"coordinates":[-4.4215388298,36.7206039429],"type":"Point"}
}