{
  "type": "Feature",
  "properties": {
    "addr:full":"Avda Costa, 86 Gijon Asturias 33201",
    "addr:housenumber":"86",
    "addr:postcode":"33201",
    "addr:street":"Avda Costa",
    "iso:country":"ES",
    "sg:address":"Avda Costa, 86",
    "sg:city":"Gijon",
    "sg:orig_category":"Molduras, Junquillos, Listones Y Molduras Perforadas",
    "sg:phone":"+34 985 33 70 58",
    "sg:postcode":"33201",
    "sg:province":"Asturias",
    "wof:name":"Fernandez Rodriguez Belen",
    "wof:placetype":"venue"
},
  "geometry": {"coordinates":[-5.6570620537,43.5375061035],"type":"Point"}
}