{
  "type": "Feature",
  "properties": {
    "iso:country":"ES",
    "sg:address":"Avda Jose Mesa Y Lopez, 41",
    "sg:city":"Palmas De Gran Canaria",
    "sg:orig_category":"Loter\u00cda Y T\u00d3mbola",
    "sg:phone":"+34 928 26 12 70",
    "sg:postcode":"35010",
    "sg:province":"Las Palmas",
    "wof:name":"Garcia Perez Jose Amado",
    "wof:placetype":"venue"
},
  "geometry": {"coordinates":[-15.4365959167,28.1332130432],"type":"Point"}
}