{
  "type": "Feature",
  "properties": {
    "addr:full":"Calle de Madre Soledad Torres Acosta, 10 Jaen Ja\u00e9n 23001",
    "addr:housenumber":"10;jae\u0301n",
    "addr:postcode":"23001",
    "addr:street":"Calle De Madre Soledad Torres Acosta",
    "iso:country":"ES",
    "sg:address":"Calle de Madre Soledad Torres Acosta, 10",
    "sg:city":"Jaen",
    "sg:orig_category":"M\u00c9dicos: Pediatr\u00cda. Enfermedades De Los Ni\u00d1os",
    "sg:phone":"+34 953 22 40 56",
    "sg:postcode":"23001",
    "sg:province":"Ja\u00e9n",
    "wof:name":"Alcantara Rubio Braulio",
    "wof:placetype":"venue"
},
  "geometry": {"coordinates":[-3.7895202637,37.7691078186],"type":"Point"}
}