{
  "type": "Feature",
  "properties": {
    "iso:country":"ES",
    "sg:address":"Avda Almazora, S/n",
    "sg:city":"Castellon",
    "sg:orig_category":"Pintura Y Barniz (al Por Menor)",
    "sg:phone":"+34 964 25 17 10",
    "sg:postcode":"12005",
    "sg:province":"Castell\u00f3n",
    "wof:name":"Industrias Titan S.a.",
    "wof:placetype":"venue"
},
  "geometry": {"coordinates":[-0.0297400001,39.9624290466],"type":"Point"}
}