{
  "type": "Feature",
  "properties": {
    "iso:country":"ES",
    "sg:address":"Calle de Viar, 4",
    "sg:city":"Cantillana",
    "sg:orig_category":"Molduras, Junquillos, Listones Y Molduras Perforadas",
    "sg:phone":"+34 955 73 06 43",
    "sg:postcode":"41320",
    "sg:province":"Sevilla",
    "wof:name":"Pino De La Hera Jose",
    "wof:placetype":"venue"
},
  "geometry": {"coordinates":[-5.82665205,37.6094055176],"type":"Point"}
}