{
  "type": "Feature",
  "properties": {
    "addr:full":"San Roque, 72 Coristanco A Coru\u00f1a 15147",
    "addr:housenumber":"72",
    "addr:postcode":"15147",
    "addr:street":"San Roque;Corun\u0303A",
    "iso:country":"ES",
    "sg:address":"San Roque, 72",
    "sg:city":"Coristanco",
    "sg:orig_category":"Librer\u00cdas",
    "sg:phone":"+34 981 73 34 03",
    "sg:postcode":"15147",
    "sg:province":"A Coru\u00f1a",
    "wof:name":"Veci\u00f1o Velo Elida",
    "wof:placetype":"venue"
},
  "geometry": {"coordinates":[-8.7346086502,43.1884384155],"type":"Point"}
}