{
  "type": "Feature",
  "properties": {
    "iso:country":"ES",
    "sg:address":"Calle de Reino Unido, 8",
    "sg:city":"Toledo",
    "sg:orig_category":"Promotores Constructores",
    "sg:phone":"+34 925 25 70 66",
    "sg:postcode":"45005",
    "sg:province":"Toledo",
    "wof:name":"Rallago Construcciones Y Servicios S.l.l.",
    "wof:placetype":"venue"
},
  "geometry": {"coordinates":[-4.0333991051,39.8825187683],"type":"Point"}
}