{
  "type": "Feature",
  "properties": {
    "iso:country":"ES",
    "sg:address":"Carrer de Maria Cubi, 66",
    "sg:city":"Barcelona",
    "sg:orig_category":"Arquitectos",
    "sg:phone":"+34 932 00 88 90",
    "sg:postcode":"08006",
    "sg:province":"Barcelona",
    "wof:name":"Iba\u00f1ez Anechina Tomas Jesus",
    "wof:placetype":"venue"
},
  "geometry": {"coordinates":[2.149107933,41.398059845],"type":"Point"}
}