{
  "type": "Feature",
  "properties": {
    "iso:country":"ES",
    "sg:address":"Avda Valladolid, 35",
    "sg:city":"Tordesillas",
    "sg:orig_category":"Empresas De Carpinter\u00cda De Madera",
    "sg:phone":"+34 983 77 12 78",
    "sg:postcode":"47100",
    "sg:province":"Valladolid",
    "wof:name":"Barragan De La Cruz Cesareo",
    "wof:placetype":"venue"
},
  "geometry": {"coordinates":[-4.9884839058,41.5042915344],"type":"Point"}
}