{
  "type": "Feature",
  "properties": {
    "addr:full":"Avda Andalucia, 1 Orcera Ja\u00e9n 23370",
    "addr:housenumber":"1",
    "addr:postcode":"23370",
    "addr:street":"Avda Andalucia;Jae\u0301N",
    "iso:country":"ES",
    "sg:address":"Avda Andalucia, 1",
    "sg:city":"Orcera",
    "sg:orig_category":"Cajas De Ahorro",
    "sg:phone":"+34 953 48 00 04",
    "sg:postcode":"23370",
    "sg:province":"Ja\u00e9n",
    "sg:website":"www.unicaja.es",
    "wof:name":"Unicaja",
    "wof:placetype":"venue"
},
  "geometry": {"coordinates":[-2.6610219479,38.3176231384],"type":"Point"}
}