{
  "type": "Feature",
  "properties": {
    "addr:full":"Calle de Rodrigo Rebolledo, 15 Zaragoza Zaragoza 50002",
    "addr:housenumber":"15",
    "addr:postcode":"50002",
    "addr:street":"Calle De Rodrigo Rebolledo",
    "iso:country":"ES",
    "sg:address":"Calle de Rodrigo Rebolledo, 15",
    "sg:city":"Zaragoza",
    "sg:orig_category":"Empresas De Carpinter\u00cda De Madera",
    "sg:phone":"+34 976 42 77 42",
    "sg:postcode":"50002",
    "sg:province":"Zaragoza",
    "wof:name":"Sucesores Casa Martinez S.c.l.",
    "wof:placetype":"venue"
},
  "geometry": {"coordinates":[-0.864256382,41.6461601257],"type":"Point"}
}