{
  "type": "Feature",
  "properties": {
    "addr:full":"Fonte Da Pedra, 2 Salceda Caselas Pontevedra 36470",
    "addr:housenumber":"2",
    "addr:postcode":"36470",
    "addr:street":"Da Pedra",
    "iso:country":"ES",
    "sg:address":"Fonte Da Pedra, 2",
    "sg:city":"Salceda Caselas",
    "sg:orig_category":"Alimentaci\u00d3n General (al Por Menor)",
    "sg:phone":"+34 986 34 90 63",
    "sg:postcode":"36470",
    "sg:province":"Pontevedra",
    "wof:name":"Alvarez Gonzalez Milagros",
    "wof:placetype":"venue"
},
  "geometry": {"coordinates":[-8.5567016602,42.1020431519],"type":"Point"}
}