{
  "type": "Feature",
  "properties": {
    "iso:country":"ES",
    "sg:address":"Avda Hercules, 79",
    "sg:city":"Coru\u00d1a",
    "sg:orig_category":"Alimentaci\u00d3n General (al Por Menor)",
    "sg:phone":"+34 981 20 91 17",
    "sg:postcode":"15002",
    "sg:province":"La Coru\u00f1a",
    "wof:name":"Figueiroa Mira Valentina",
    "wof:placetype":"venue"
},
  "geometry": {"coordinates":[-8.4042625427,43.3787384033],"type":"Point"}
}