{
  "type": "Feature",
  "properties": {
    "iso:country":"ES",
    "sg:address":"Carrer de Doctor Reig, 75",
    "sg:city":"Viladecans",
    "sg:orig_category":"Lencer\u00cda Femenina, Corseter\u00cda, Trajes De Ba\u00d1o (al Por Menor)",
    "sg:phone":"+34 936 59 02 07",
    "sg:postcode":"08840",
    "sg:province":"Barcelona",
    "wof:name":"Marinetto Lopez Josefina",
    "wof:placetype":"venue"
},
  "geometry": {"coordinates":[2.0120809078,41.3201065063],"type":"Point"}
}