{
  "type": "Feature",
  "properties": {
    "iso:country":"ES",
    "sg:address":"Pl Santa Elisabet, 5",
    "sg:city":"Palma",
    "sg:orig_category":"Agencias Y Asesores De Publicidad",
    "sg:phone":"+34 971 24 80 27",
    "sg:postcode":"07005",
    "sg:province":"Islas Baleares",
    "wof:name":"Carballal Escalante Carmen",
    "wof:placetype":"venue"
},
  "geometry": {"coordinates":[2.6614940166,39.5802078247],"type":"Point"}
}