{
  "type": "Feature",
  "properties": {
    "iso:country":"ES",
    "sg:address":"Calle de Manuel Garcia Matos, 1",
    "sg:city":"Plasencia",
    "sg:orig_category":"Iglesia Cat\u00d3lica",
    "sg:phone":"+34 927 41 75 40",
    "sg:postcode":"10600",
    "sg:province":"C\u00e1ceres",
    "wof:name":"Parroquia De Santa Maria De La Esperanza",
    "wof:placetype":"venue"
},
  "geometry": {"coordinates":[-6.0798888206,40.0417518616],"type":"Point"}
}