{
  "type": "Feature",
  "properties": {
    "addr:full":"Crri Cipres, 16 Malaga M\u00e1laga 29010",
    "addr:housenumber":"16",
    "addr:postcode":"29010",
    "addr:street":"Cipres;Ma\u0301Laga",
    "iso:country":"ES",
    "sg:address":"Crri Cipres, 16",
    "sg:city":"Malaga",
    "sg:orig_category":"Molduras, Junquillos, Listones Y Molduras Perforadas",
    "sg:phone":"+34 952 28 28 29",
    "sg:postcode":"29010",
    "sg:province":"M\u00e1laga",
    "wof:name":"Castillo Valenzuela Jose Maria",
    "wof:placetype":"venue"
},
  "geometry": {"coordinates":[-4.4481039047,36.7242431641],"type":"Point"}
}