{
  "type": "Feature",
  "properties": {
    "addr:full":"Pl Ntra Sra Carmen, 5 Pasai S. Pedro Guip\u00f9zcoa 20110",
    "addr:housenumber":"5",
    "addr:postcode":"20110",
    "addr:street":"Pl Ntra Sra Carmen;Guipu\u0300Zcoa",
    "iso:country":"ES",
    "sg:address":"Pl Ntra Sra Carmen, 5",
    "sg:city":"Pasai S. Pedro",
    "sg:orig_category":"Centros De Educaci\u00d3n Especial",
    "sg:phone":"+34 943 39 03 71",
    "sg:postcode":"20110",
    "sg:province":"Guip\u00f9zcoa",
    "wof:name":"Gobierno Vasco-eusko Jaurlaritza",
    "wof:placetype":"venue"
},
  "geometry": {"coordinates":[-1.9217879772,43.3260040283],"type":"Point"}
}