{
  "type": "Feature",
  "properties": {
    "iso:country":"ES",
    "sg:address":"Calle de Europa, 11",
    "sg:city":"Coru\u00d1a",
    "sg:orig_category":"Asesor\u00cda Sobre Comunicaci\u00d3n De Empresas",
    "sg:phone":"+34 981 16 91 25",
    "sg:postcode":"15007",
    "sg:province":"A Coru\u00f1a",
    "wof:name":"Suarez Mira Victorino",
    "wof:placetype":"venue"
},
  "geometry": {"coordinates":[-8.4129943848,43.3528785706],"type":"Point"}
}