{
  "type": "Feature",
  "properties": {
    "addr:full":"Avda Aldea Del Obispo, 18 Nuevo Poblado Salamanca 37480",
    "addr:housenumber":"18",
    "addr:postcode":"37480",
    "addr:street":"Avda Aldea Del Obispo;Poblado",
    "iso:country":"ES",
    "sg:address":"Avda Aldea Del Obispo, 18",
    "sg:city":"Nuevo Poblado",
    "sg:orig_category":"Empresas De Portes Y Mensajer\u00cda",
    "sg:phone":"+34 923 47 31 51",
    "sg:postcode":"37480",
    "sg:province":"Salamanca",
    "sg:website":"www.mrw.es",
    "wof:name":"Ramaje Courrier S.l.",
    "wof:placetype":"venue"
},
  "geometry": {"coordinates":[-6.8109388351,40.5948791504],"type":"Point"}
}