{
  "type": "Feature",
  "properties": {
    "addr:full":"Calle de Granada De Pinos Puente, 1 Pinos-puente Granada 18240",
    "addr:housenumber":"1",
    "addr:postcode":"18240",
    "addr:street":"Calle De Granada De Pinos Puente",
    "iso:country":"ES",
    "sg:address":"Calle de Granada De Pinos Puente, 1",
    "sg:city":"Pinos-puente",
    "sg:orig_category":"Droguer\u00cdas (al Por Menor)",
    "sg:phone":"+34 958 45 01 85",
    "sg:postcode":"18240",
    "sg:province":"Granada",
    "wof:name":"Lucena Martin Carlos Javier",
    "wof:placetype":"venue"
},
  "geometry": {"coordinates":[-3.7521839142,37.2517814636],"type":"Point"}
}