{
  "type": "Feature",
  "properties": {
    "addr:full":"Carrer de Comte D'urgell, 249 Barcelona Barcelona 08036",
    "addr:housenumber":"249",
    "addr:postcode":"08036",
    "addr:street":"Carrer De Comte D'Urgell",
    "iso:country":"ES",
    "sg:address":"Carrer de Comte D'urgell, 249",
    "sg:city":"Barcelona",
    "sg:orig_category":"Juegos Y Juguetes (al Por Menor)",
    "sg:phone":"+34 933 22 92 08",
    "sg:postcode":"08036",
    "sg:province":"Barcelona",
    "wof:name":"Vi\u00f1as Florensa Jose Maria",
    "wof:placetype":"venue"
},
  "geometry": {"coordinates":[2.1461834908,41.3914527893],"type":"Point"}
}