{
  "type": "Feature",
  "properties": {
    "addr:full":"Calle de Jose Barros, 2 Muriedas Cantabria 39600",
    "addr:housenumber":"2",
    "addr:postcode":"39600",
    "addr:street":"Calle De Jose Barros",
    "iso:country":"ES",
    "sg:address":"Calle de Jose Barros, 2",
    "sg:city":"Muriedas",
    "sg:orig_category":"Arreglo E Instalaci\u00d3n De Caf\u00c9s, Hoteles Y Restaurantes",
    "sg:phone":"+34 942 25 16 95",
    "sg:postcode":"39600",
    "sg:province":"Cantabria",
    "wof:name":"Martinez Rodriguez Jose",
    "wof:placetype":"venue"
},
  "geometry": {"coordinates":[-3.8458189964,43.4184341431],"type":"Point"}
}