{
  "type": "Feature",
  "properties": {
    "iso:country":"ES",
    "sg:address":"Calle de Vicente Aleixandre, 16",
    "sg:city":"Barrios",
    "sg:orig_category":"Molduras, Junquillos, Listones Y Molduras Perforadas",
    "sg:phone":"+34 956 62 19 99",
    "sg:postcode":"11370",
    "sg:province":"C\u00e1diz",
    "wof:name":"Gil Salas Prudencio",
    "wof:placetype":"venue"
},
  "geometry": {"coordinates":[-5.4945001602,36.1878890991],"type":"Point"}
}