{
  "type": "Feature",
  "properties": {
    "addr:full":"Las Higueras, 8 Tacoronte Santa Cruz De Tenerife 38350",
    "addr:housenumber":"8",
    "addr:postcode":"38350",
    "addr:street":"Las Higueras",
    "iso:country":"ES",
    "sg:address":"Las Higueras, 8",
    "sg:city":"Tacoronte",
    "sg:orig_category":"Abogados",
    "sg:phone":"+34 922 57 12 00",
    "sg:postcode":"38350",
    "sg:province":"Santa Cruz De Tenerife",
    "wof:name":"Arvelo Diaz Salvador",
    "wof:placetype":"venue"
},
  "geometry": {"coordinates":[-16.4143314362,28.4768333435],"type":"Point"}
}