{
  "type": "Feature",
  "properties": {
    "addr:full":"Ctra Canicosa, S/n Navaleno Soria 42149",
    "addr:housenumber":"s / n",
    "addr:postcode":"42149",
    "addr:street":"Ctra Canicosa",
    "iso:country":"ES",
    "sg:address":"Ctra Canicosa, S/n",
    "sg:city":"Navaleno",
    "sg:orig_category":"Negocio De Materiales De Construcci\u00d3n",
    "sg:phone":"+34 975 37 42 26",
    "sg:postcode":"42149",
    "sg:province":"Soria",
    "wof:name":"Orte Garicochea Jesus",
    "wof:placetype":"venue"
},
  "geometry": {"coordinates":[-3.0017540455,41.8406715393],"type":"Point"}
}