{
  "type": "Feature",
  "properties": {
    "addr:full":"Carr Pi I Margall, 20 Lleida Lleida 25004",
    "addr:housenumber":"20",
    "addr:postcode":"25004",
    "addr:street":"Carr Pi I Margall",
    "iso:country":"ES",
    "sg:address":"Carr Pi I Margall, 20",
    "sg:city":"Lleida",
    "sg:orig_category":"Confecci\u00d3n De Trajes Para Se\u00d1oras",
    "sg:phone":"+34 973 24 62 21",
    "sg:postcode":"25004",
    "sg:province":"Lleida",
    "wof:name":"Mestre Olivart Ana",
    "wof:placetype":"venue"
},
  "geometry": {"coordinates":[0.6284769773,41.6203651428],"type":"Point"}
}