{
  "type": "Feature",
  "properties": {
    "iso:country":"ES",
    "sg:address":"Ctra. Cordoba, 5",
    "sg:city":"Jaen",
    "sg:orig_category":"Fabricaci\u00d3n De Juguetes Autom\u00c1ticos",
    "sg:phone":"+34 953 24 02 11",
    "sg:postcode":"23005",
    "sg:province":"Ja\u00e9n",
    "sg:website":"www.valisa.es",
    "wof:name":"Valisa Internacional S.l.",
    "wof:placetype":"venue"
},
  "geometry": {"coordinates":[-3.7962241173,37.7735900879],"type":"Point"}
}