{
  "type": "Feature",
  "properties": {
    "addr:full":"Calle de Henares, 8 Baena C\u00f3rdoba 14850",
    "addr:housenumber":"8",
    "addr:postcode":"14850",
    "addr:street":"Calle De Henares",
    "iso:country":"ES",
    "sg:address":"Calle de Henares, 8",
    "sg:city":"Baena",
    "sg:orig_category":"Estancos",
    "sg:phone":"+34 957 69 17 07",
    "sg:postcode":"14850",
    "sg:province":"C\u00f3rdoba",
    "wof:name":"Murillo Conejero Rafael",
    "wof:placetype":"venue"
},
  "geometry": {"coordinates":[-4.3239879608,37.6164054871],"type":"Point"}
}