{
  "type": "Feature",
  "properties": {
    "addr:full":"Calle de Juan Carlos I, 35 Valmojado Toledo 45940",
    "addr:housenumber":"35",
    "addr:postcode":"45940",
    "addr:street":"Calle De Juan Carlos I",
    "iso:country":"ES",
    "sg:address":"Calle de Juan Carlos I, 35",
    "sg:city":"Valmojado",
    "sg:orig_category":"Electricidad: Instaladores",
    "sg:phone":"+34 918 17 08 46",
    "sg:postcode":"45940",
    "sg:province":"Toledo",
    "wof:name":"Lopes Bonafi Pascal",
    "wof:placetype":"venue"
},
  "geometry": {"coordinates":[-4.0909991264,40.2044487],"type":"Point"}
}