{
  "type": "Feature",
  "properties": {
    "addr:full":"Calle de Bizkarreta, 2 Ribabellosa \u00c1lava 01213",
    "addr:housenumber":"2",
    "addr:postcode":"01213",
    "addr:street":"Calle De Bizkarreta;A\u0301Lava",
    "iso:country":"ES",
    "sg:address":"Calle de Bizkarreta, 2",
    "sg:city":"Ribabellosa",
    "sg:orig_category":"Lavado, Limpieza De Veh\u00cdculos",
    "sg:phone":"+34 945 35 50 27",
    "sg:postcode":"01213",
    "sg:province":"\u00c1lava",
    "wof:name":"Lavamiranda S.l.",
    "wof:placetype":"venue"
},
  "geometry": {"coordinates":[-2.9169149399,42.7129211426],"type":"Point"}
}