{
  "type": "Feature",
  "properties": {
    "addr:full":"Carrer de Barcelona, 47 Castellar Valles Barcelona 08211",
    "addr:housenumber":"47",
    "addr:postcode":"08211",
    "addr:street":"Carrer De Barcelona",
    "iso:country":"ES",
    "sg:address":"Carrer de Barcelona, 47",
    "sg:city":"Castellar Valles",
    "sg:orig_category":"Alimentaci\u00d3n General (al Por Menor)",
    "sg:phone":"+34 937 47 24 51",
    "sg:postcode":"08211",
    "sg:province":"Barcelona",
    "wof:name":"Lopez Corbalan Angel",
    "wof:placetype":"venue"
},
  "geometry": {"coordinates":[2.0874860287,41.6098136902],"type":"Point"}
}