{
  "type": "Feature",
  "properties": {
    "iso:country":"ES",
    "sg:address":"Calle de Korreo Kalea, 27",
    "sg:city":"Tolosa",
    "sg:orig_category":"Muebles, Minoristas",
    "sg:phone":"+34 943 11 70 39",
    "sg:postcode":"20400",
    "sg:province":"Guip\u00f9zcoa",
    "wof:name":"Jose Miguel Irui\u00f1 Belaunzaran",
    "wof:placetype":"venue"
},
  "geometry": {"coordinates":[-2.0727069378,43.1381721497],"type":"Point"}
}