{
  "type": "Feature",
  "properties": {
    "addr:full":"Calle de Fataga, 12 Cruce I Las Palmas 35110",
    "addr:housenumber":"12",
    "addr:postcode":"35110",
    "addr:street":"Calle De Fataga;I Las",
    "iso:country":"ES",
    "sg:address":"Calle de Fataga, 12",
    "sg:city":"Cruce I",
    "sg:orig_category":"Promotores Constructores",
    "sg:phone":"+34 928 75 86 31",
    "sg:postcode":"35110",
    "sg:province":"Las Palmas",
    "wof:name":"Sistemas Integrales Constructivos S.l.",
    "wof:placetype":"venue"
},
  "geometry": {"coordinates":[-15.441868782,27.8550205231],"type":"Point"}
}