{
  "type": "Feature",
  "properties": {
    "addr:full":"Ctra Constantina, Km. 0027,0 Puebla Infantes Sevilla 41479",
    "addr:postcode":"41479",
    "addr:street":"Ctra Constantina Km. 0027,0;Infantes",
    "iso:country":"ES",
    "sg:address":"Ctra Constantina, Km. 0027,0",
    "sg:city":"Puebla Infantes",
    "sg:orig_category":"Aceites Y Grasas Alimentarias (fabricaci\u00d3n, Al Por Mayor)",
    "sg:phone":"+34 954 80 80 56",
    "sg:postcode":"41479",
    "sg:province":"Sevilla",
    "wof:name":"Virgen De Las Huertas S.c.a.",
    "wof:placetype":"venue"
},
  "geometry": {"coordinates":[-5.388958931,37.7803497314],"type":"Point"}
}