{
  "type": "Feature",
  "properties": {
    "addr:full":"Calle de Fomento, 13 Madrid Madrid 28013",
    "addr:housenumber":"13",
    "addr:postcode":"madrid;28013",
    "addr:street":"Calle De Fomento",
    "iso:country":"ES",
    "sg:address":"Calle de Fomento, 13",
    "sg:city":"Madrid",
    "sg:orig_category":"Organizaciones Internacionales",
    "sg:phone":"+34 915 48 13 63",
    "sg:postcode":"28013",
    "sg:province":"Madrid",
    "wof:name":"Confraternidad Carcelaria De Espa\u00f1a",
    "wof:placetype":"venue"
},
  "geometry": {"coordinates":[-3.7105569839,40.4209518433],"type":"Point"}
}