{
  "type": "Feature",
  "properties": {
    "iso:country":"ES",
    "sg:address":"Pg. Fluvial, S/n",
    "sg:city":"Granollers",
    "sg:orig_category":"Paletas",
    "sg:phone":"+34 938 79 59 53",
    "sg:postcode":"08400",
    "sg:province":"Barcelona",
    "wof:name":"Virta Gardu\u00f1o Francisco",
    "wof:placetype":"venue"
},
  "geometry": {"coordinates":[2.2767219543,41.581073761],"type":"Point"}
}