{
  "type": "Feature",
  "properties": {
    "iso:country":"ES",
    "sg:address":"Calle de Juan Ochoa, 9",
    "sg:city":"Aviles",
    "sg:orig_category":"Restaurantes",
    "sg:phone":"+34 985 52 13 57",
    "sg:postcode":"33401",
    "sg:province":"Asturias",
    "wof:name":"Vilar Lopez Juan Carlos",
    "wof:placetype":"venue"
},
  "geometry": {"coordinates":[-5.9308300018,43.5565834045],"type":"Point"}
}