{
  "type": "Feature",
  "properties": {
    "addr:full":"Llosar, S/n Tibi Alicante 03109",
    "addr:housenumber":"/ n",
    "addr:postcode":"03109",
    "addr:street":"Llosar S",
    "iso:country":"ES",
    "sg:address":"Llosar, S/n",
    "sg:city":"Tibi",
    "sg:orig_category":"Fabricaci\u00d3n De Moldes Y Modelos",
    "sg:phone":"+34 965 61 70 43",
    "sg:postcode":"03109",
    "sg:province":"Alicante",
    "wof:name":"Bersil S.l.",
    "wof:placetype":"venue"
},
  "geometry": {"coordinates":[-0.5847989917,38.5295906067],"type":"Point"}
}