{
  "type": "Feature",
  "properties": {
    "addr:full":"Carr Regino Mas, 12 Benifaio Valencia 46450",
    "addr:housenumber":"12",
    "addr:postcode":"46450",
    "addr:street":"Carr Regino Mas",
    "iso:country":"ES",
    "sg:address":"Carr Regino Mas, 12",
    "sg:city":"Benifaio",
    "sg:orig_category":"Negocio De Materiales De Construcci\u00d3n",
    "sg:phone":"+34 961 78 08 81",
    "sg:postcode":"46450",
    "sg:province":"Valencia",
    "wof:name":"A\u00f1edul S.l.",
    "wof:placetype":"venue"
},
  "geometry": {"coordinates":[-0.4256109893,39.2878417969],"type":"Point"}
}