{
  "type": "Feature",
  "properties": {
    "iso:country":"ES",
    "sg:address":"Pl Barco, 16",
    "sg:city":"Pedreguer",
    "sg:orig_category":"Molduras, Junquillos, Listones Y Molduras Perforadas",
    "sg:phone":"+34 965 76 06 49",
    "sg:postcode":"03750",
    "sg:province":"Alicante",
    "wof:name":"Morell Ribes Jose",
    "wof:placetype":"venue"
},
  "geometry": {"coordinates":[0.0347849987,38.7958145142],"type":"Point"}
}