{
  "type": "Feature",
  "properties": {
    "addr:full":"Calle de Via Carpetana, 55 Madrid Madrid 28047",
    "addr:housenumber":"55",
    "addr:postcode":"madrid;28047",
    "addr:street":"Calle De Via Carpetana",
    "iso:country":"ES",
    "sg:address":"Calle de Via Carpetana, 55",
    "sg:city":"Madrid",
    "sg:orig_category":"Cerrajer\u00cda, Ferrallista",
    "sg:phone":"+34 914 71 05 50",
    "sg:postcode":"28047",
    "sg:province":"Madrid",
    "wof:name":"Ranera Yela Timoteo",
    "wof:placetype":"venue"
},
  "geometry": {"coordinates":[-3.7350370884,40.3981590271],"type":"Point"}
}