{
  "type": "Feature",
  "properties": {
    "addr:full":"Calle de Antonio Garely, 20 Isla Cristina Huelva 21410",
    "addr:housenumber":"20",
    "addr:postcode":"21410",
    "addr:street":"Calle De Antonio Garely",
    "iso:country":"ES",
    "sg:address":"Calle de Antonio Garely, 20",
    "sg:city":"Isla Cristina",
    "sg:orig_category":"Mec\u00c1nico Del Autom\u00d3vil",
    "sg:phone":"+34 959 33 11 40",
    "sg:postcode":"21410",
    "sg:province":"Huelva",
    "wof:name":"Simoes Luis Alfredo",
    "wof:placetype":"venue"
},
  "geometry": {"coordinates":[-7.3277311325,37.2009887695],"type":"Point"}
}