{
  "type": "Feature",
  "properties": {
    "iso:country":"ES",
    "sg:address":"C/ Mossen Vicent Albors, 5",
    "sg:city":"Alcoi",
    "sg:orig_category":"M\u00c9dicos: Cirug\u00cda Urol\u00d3gica",
    "sg:phone":"+34 965 33 95 53",
    "sg:postcode":"03804",
    "sg:province":"Alicante",
    "wof:name":"Garcia Zamora Jose Antonio",
    "wof:placetype":"venue"
},
  "geometry": {"coordinates":[-0.4738149047,38.7063865662],"type":"Point"}
}