{
  "type": "Feature",
  "properties": {
    "iso:country":"ES",
    "sg:address":"Carrer de Font D'en Canyelles, 85",
    "sg:city":"Barcelona",
    "sg:orig_category":"Droguer\u00cdas (al Por Menor)",
    "sg:phone":"+34 933 54 04 39",
    "sg:postcode":"08042",
    "sg:province":"Barcelona",
    "wof:name":"Gomez Ruiz Manuel",
    "wof:placetype":"venue"
},
  "geometry": {"coordinates":[2.1750643253,41.4407272339],"type":"Point"}
}