{
  "type": "Feature",
  "properties": {
    "iso:country":"ES",
    "sg:address":"C/ Picapedrers, 67",
    "sg:city":"Manacor",
    "sg:orig_category":"Molduras, Junquillos, Listones Y Molduras Perforadas",
    "sg:phone":"+34 971 84 52 25",
    "sg:postcode":"07500",
    "sg:province":"Islas Baleares",
    "sg:website":"www.levant.com",
    "wof:name":"Balaustradas Llevant S.l.",
    "wof:placetype":"venue"
},
  "geometry": {"coordinates":[3.2279529572,39.564037323],"type":"Point"}
}