{
  "type": "Feature",
  "properties": {
    "iso:country":"ES",
    "sg:address":"Calle de Carlos Cano, 24",
    "sg:city":"Vera",
    "sg:orig_category":"Ropa Para Se\u00d1oras Y Caballeros (al Por Menor)",
    "sg:phone":"+34 950 39 15 31",
    "sg:postcode":"04620",
    "sg:province":"Almer\u00eda",
    "wof:name":"Alcasama S.l.l",
    "wof:placetype":"venue"
},
  "geometry": {"coordinates":[-1.8657838106,37.2486343384],"type":"Point"}
}