{
  "type": "Feature",
  "properties": {
    "iso:country":"ES",
    "sg:address":"Calle de Padre Arrupe, 89",
    "sg:city":"Madrid",
    "sg:orig_category":"Inmobiliaria (agencias)",
    "sg:phone":"+34 916 50 63 37",
    "sg:postcode":"28050",
    "sg:province":"Madrid",
    "wof:name":"Alsose Inversiones S.l.",
    "wof:placetype":"venue"
},
  "geometry": {"coordinates":[-3.6374974251,40.5053634644],"type":"Point"}
}