{
  "type": "Feature",
  "properties": {
    "addr:full":"Calle de Abilio Calderon, 41 Alar Del Rey Palencia 34480",
    "addr:housenumber":"41",
    "addr:postcode":"34480",
    "addr:street":"Calle De Abilio Calderon",
    "iso:country":"ES",
    "sg:address":"Calle de Abilio Calderon, 41",
    "sg:city":"Alar Del Rey",
    "sg:orig_category":"Albergues",
    "sg:phone":"+34 979 13 30 37",
    "sg:postcode":"34480",
    "sg:province":"Palencia",
    "wof:name":"Gonzalez Gomez Luis Maria",
    "wof:placetype":"venue"
},
  "geometry": {"coordinates":[-4.3108716011,42.6610641479],"type":"Point"}
}