{
  "type": "Feature",
  "properties": {
    "addr:full":"Calle de Plocia, 27 Cadiz C\u00e1diz 11006",
    "addr:housenumber":"27",
    "addr:postcode":"11006",
    "addr:street":"Calle De Plocia",
    "iso:country":"ES",
    "sg:address":"Calle de Plocia, 27",
    "sg:city":"Cadiz",
    "sg:orig_category":"Centros M\u00c9dicos Y Sociales, Dispensarios",
    "sg:phone":"+34 956 80 80 81",
    "sg:postcode":"11006",
    "sg:province":"C\u00e1diz",
    "wof:name":"Centro Medico Bahia De Cadiz S.l.",
    "wof:placetype":"venue"
},
  "geometry": {"coordinates":[-6.2902741432,36.5290298462],"type":"Point"}
}