{
  "type": "Feature",
  "properties": {
    "addr:full":"Calle de Libertad (de La), 56 Navalcarnero Madrid 28600",
    "addr:housenumber":"56",
    "addr:postcode":"28600",
    "addr:street":"Calle De Libertad De La",
    "iso:country":"ES",
    "sg:address":"Calle de Libertad (de La), 56",
    "sg:city":"Navalcarnero",
    "sg:orig_category":"Inmobiliaria (agencias)",
    "sg:phone":"+34 918 11 40 49",
    "sg:postcode":"28600",
    "sg:province":"Madrid",
    "wof:name":"Navalcarnero Gestion S.l.",
    "wof:placetype":"venue"
},
  "geometry": {"coordinates":[-4.0130019188,40.2901268005],"type":"Point"}
}