{
  "type": "Feature",
  "properties": {
    "iso:country":"ES",
    "sg:address":"Calle de Artes Graficas, 8",
    "sg:city":"Alacant",
    "sg:orig_category":"Bebidas",
    "sg:phone":"+34 965 10 33 33",
    "sg:postcode":"03008",
    "sg:province":"Alicante",
    "wof:name":"Distribuciones Guillen S. L.",
    "wof:placetype":"venue"
},
  "geometry": {"coordinates":[-0.5150375962,38.335559845],"type":"Point"}
}