{
  "type": "Feature",
  "properties": {
    "iso:country":"ES",
    "sg:address":"Calle de Rio Nalon, 7",
    "sg:city":"Oviedo",
    "sg:orig_category":"Molduras, Junquillos, Listones Y Molduras Perforadas",
    "sg:phone":"+34 985 20 00 47",
    "sg:postcode":"33010",
    "sg:province":"Asturias",
    "wof:name":"Iglesias Alonso Angel",
    "wof:placetype":"venue"
},
  "geometry": {"coordinates":[-5.8281788826,43.3674316406],"type":"Point"}
}