{
  "type": "Feature",
  "properties": {
    "addr:full":"Plaz Remonta, 15 Madrid Madrid 28039",
    "addr:housenumber":"15",
    "addr:postcode":"madrid;28039",
    "addr:street":"Plaz Remonta",
    "iso:country":"ES",
    "sg:address":"Plaz Remonta, 15",
    "sg:city":"Madrid",
    "sg:orig_category":"Estilistas, Estudios De Dise\u00d1o De Telas",
    "sg:phone":"+34 915 71 51 69",
    "sg:postcode":"28039",
    "sg:province":"Madrid",
    "wof:name":"Titanio Network S.l",
    "wof:placetype":"venue"
},
  "geometry": {"coordinates":[-3.6984529495,40.4637260437],"type":"Point"}
}