{
  "type": "Feature",
  "properties": {
    "iso:country":"ES",
    "sg:address":"Plaz Santiago, 2",
    "sg:city":"Burgos",
    "sg:orig_category":"Inmobiliaria (agencias)",
    "sg:phone":"+34 947 21 22 54",
    "sg:postcode":"09007",
    "sg:province":"Burgos",
    "wof:name":"Gestion Inmobiliaria Casabur S.l.",
    "wof:placetype":"venue"
},
  "geometry": {"coordinates":[-3.6684761047,42.3495674133],"type":"Point"}
}