{
  "type": "Feature",
  "properties": {
    "iso:country":"ES",
    "sg:address":"Calle de Don Antonio Cuadros, 19",
    "sg:city":"Jodar",
    "sg:orig_category":"Loter\u00cda Y T\u00d3mbola",
    "sg:phone":"+34 953 78 65 06",
    "sg:postcode":"23500",
    "sg:province":"Ja\u00e9n",
    "wof:name":"Plaza Ruiz Lorenzo",
    "wof:placetype":"venue"
},
  "geometry": {"coordinates":[-3.3187470436,37.8258590698],"type":"Point"}
}