{
  "type": "Feature",
  "properties": {
    "iso:country":"ES",
    "sg:address":"Ctra Montblanc De, 3",
    "sg:city":"Valls",
    "sg:orig_category":"Carnicer\u00cdas, Carnicer\u00cdas",
    "sg:phone":"+34 977 60 13 01",
    "sg:postcode":"43800",
    "sg:province":"Tarragona",
    "wof:name":"Figuerola Bonastre Santiago",
    "wof:placetype":"venue"
},
  "geometry": {"coordinates":[1.2452499866,41.2931785583],"type":"Point"}
}