{
  "type": "Feature",
  "properties": {
    "iso:country":"ES",
    "sg:address":"Rond Alarcos, 25",
    "sg:city":"Ciudad Real",
    "sg:orig_category":"Distribuci\u00d3n De Petr\u00d3leo Y Derivados",
    "sg:phone":"+34 926 21 12 36",
    "sg:postcode":"13002",
    "sg:province":"Ciudad Real",
    "wof:name":"El Encuentro Sociedad Anonima",
    "wof:placetype":"venue"
},
  "geometry": {"coordinates":[-3.9321489334,38.9822311401],"type":"Point"}
}