{
  "type": "Feature",
  "properties": {
    "iso:country":"ES",
    "sg:address":"Carrer de Despuig, 63",
    "sg:city":"Palma",
    "sg:orig_category":"Empresarios",
    "sg:phone":"+34 971 73 23 18",
    "sg:postcode":"07013",
    "sg:province":"Islas Baleares",
    "wof:name":"Guife S.l.",
    "wof:placetype":"venue"
},
  "geometry": {"coordinates":[2.6350669861,39.5713577271],"type":"Point"}
}