{
  "type": "Feature",
  "properties": {
    "iso:country":"ES",
    "sg:address":"San Justo, S/n",
    "sg:city":"San Justo",
    "sg:orig_category":"Molduras, Junquillos, Listones Y Molduras Perforadas",
    "sg:phone":"+34 985 89 95 01",
    "sg:postcode":"33314",
    "sg:province":"Asturias",
    "wof:name":"Alonso Garcia Miguel",
    "wof:placetype":"venue"
},
  "geometry": {"coordinates":[-6.5527462959,43.5434417725],"type":"Point"}
}