{
  "type": "Feature",
  "properties": {
    "addr:full":"Carrer de Canet, 38 Barcelona Barcelona 08017",
    "addr:housenumber":"38",
    "addr:postcode":"08017",
    "addr:street":"Carrer De Canet",
    "iso:country":"ES",
    "sg:address":"Carrer de Canet, 38",
    "sg:city":"Barcelona",
    "sg:orig_category":"Contenedores (mercanc\u00cdas)",
    "sg:phone":"+34 932 05 58 20",
    "sg:postcode":"08017",
    "sg:province":"Barcelona",
    "wof:name":"Soluciones Del Aire S.l.",
    "wof:placetype":"venue"
},
  "geometry": {"coordinates":[2.1235759258,41.3986206055],"type":"Point"}
}