{
  "type": "Feature",
  "properties": {
    "addr:full":"Calle de Doctor Iranzo, 90 Zaragoza Zaragoza 50002",
    "addr:housenumber":"90",
    "addr:postcode":"50002",
    "addr:street":"Calle De Doctor Iranzo",
    "iso:country":"ES",
    "sg:address":"Calle de Doctor Iranzo, 90",
    "sg:city":"Zaragoza",
    "sg:orig_category":"Empresas De Limpieza",
    "sg:phone":"+34 976 39 34 72",
    "sg:postcode":"50002",
    "sg:province":"Zaragoza",
    "wof:name":"Rodriguez Del Viejo Rosa Maria",
    "wof:placetype":"venue"
},
  "geometry": {"coordinates":[-0.8633419275,41.6501731873],"type":"Point"}
}