{
  "type": "Feature",
  "properties": {
    "iso:country":"ES",
    "sg:address":"Rua San Pedro (de), 111",
    "sg:city":"Santiago De Compostela",
    "sg:orig_category":"Panader\u00cdas, Panader\u00cdas",
    "sg:phone":"+34 981 56 42 78",
    "sg:postcode":"15703",
    "sg:province":"La Coru\u00f1a",
    "wof:name":"Iglesias Garcia Manuel",
    "wof:placetype":"venue"
},
  "geometry": {"coordinates":[-8.5357398987,42.8818435669],"type":"Point"}
}