{
  "type": "Feature",
  "properties": {
    "addr:full":"Carrer de Vila, 22 Mora D'ebre Tarragona 43740",
    "addr:housenumber":"22",
    "addr:postcode":"43740",
    "addr:street":"Carrer De Vila;D'Ebre",
    "iso:country":"ES",
    "sg:address":"Carrer de Vila, 22",
    "sg:city":"Mora D'ebre",
    "sg:orig_category":"Iglesia Cat\u00d3lica",
    "sg:phone":"+34 977 40 00 66",
    "sg:postcode":"43740",
    "sg:province":"Tarragona",
    "wof:name":"Bisbat De Tortosa",
    "wof:placetype":"venue"
},
  "geometry": {"coordinates":[1.2458280325,41.1134223938],"type":"Point"}
}