{
  "type": "Feature",
  "properties": {
    "addr:full":"Calle de Gran Via, 71 Blanca Murcia 30540",
    "addr:housenumber":"71",
    "addr:postcode":"30540",
    "addr:street":"Calle De Gran Via",
    "iso:country":"ES",
    "sg:address":"Calle de Gran Via, 71",
    "sg:city":"Blanca",
    "sg:orig_category":"Electricidad Veh\u00cdculo",
    "sg:phone":"+34 968 77 85 04",
    "sg:postcode":"30540",
    "sg:province":"Murcia",
    "wof:name":"Lopez Ramos David",
    "wof:placetype":"venue"
},
  "geometry": {"coordinates":[-1.3706489801,38.1795387268],"type":"Point"}
}