{
  "type": "Feature",
  "properties": {
    "iso:country":"ES",
    "sg:address":"Calle de Doctor Fleming, 6",
    "sg:city":"Xirivella",
    "sg:orig_category":"Lencer\u00cda Femenina, Corseter\u00cda, Trajes De Ba\u00d1o (al Por Menor)",
    "sg:phone":"+34 963 59 57 02",
    "sg:postcode":"46950",
    "sg:province":"Valencia",
    "wof:name":"Robles Bueno Maria Carmen",
    "wof:placetype":"venue"
},
  "geometry": {"coordinates":[-0.4257467091,39.4678344727],"type":"Point"}
}