{
  "type": "Feature",
  "properties": {
    "iso:country":"ES",
    "sg:address":"Calle de Maestro Mariani, 21",
    "sg:city":"Sevilla",
    "sg:orig_category":"Molduras, Junquillos, Listones Y Molduras Perforadas",
    "sg:phone":"+34 954 92 52 91",
    "sg:postcode":"41006",
    "sg:province":"Sevilla",
    "wof:name":"Gamero Ramirez Jacinto",
    "wof:placetype":"venue"
},
  "geometry": {"coordinates":[-5.9463891983,37.3706512451],"type":"Point"}
}