{
  "type": "Feature",
  "properties": {
    "iso:country":"ES",
    "sg:address":"Calle de Villaamil, S/n",
    "sg:city":"Mostoles",
    "sg:orig_category":"Carnicer\u00cdas, Carnicer\u00cdas",
    "sg:phone":"+34 916 14 50 95",
    "sg:postcode":"28934",
    "sg:province":"Madrid",
    "wof:name":"Blanco Otero Pedro Vicente",
    "wof:placetype":"venue"
},
  "geometry": {"coordinates":[-3.8739740849,40.3200416565],"type":"Point"}
}