{
  "type": "Feature",
  "properties": {
    "iso:country":"ES",
    "sg:address":"Calle de Halcon, 18",
    "sg:city":"Madrid",
    "sg:orig_category":"Bares, Piano",
    "sg:phone":"+34 914 61 09 99",
    "sg:postcode":"28025",
    "sg:province":"Madrid",
    "wof:name":"Becerra Gonzalez Blanca Adiela",
    "wof:placetype":"venue"
},
  "geometry": {"coordinates":[-3.7428150177,40.3887901306],"type":"Point"}
}