{
  "type": "Feature",
  "properties": {
    "addr:full":"Calle de Zurita, 3 Zaragoza Zaragoza 50001",
    "addr:housenumber":"3",
    "addr:postcode":"50001",
    "addr:street":"Calle De Zurita",
    "iso:country":"ES",
    "sg:address":"Calle de Zurita, 3",
    "sg:city":"Zaragoza",
    "sg:orig_category":"Electricidad: Instaladores",
    "sg:phone":"+34 976 22 71 32",
    "sg:postcode":"50001",
    "sg:province":"Zaragoza",
    "wof:name":"Badenas Moreno Eusebio",
    "wof:placetype":"venue"
},
  "geometry": {"coordinates":[-0.8814690113,41.650352478],"type":"Point"}
}