{
  "type": "Feature",
  "properties": {
    "iso:country":"ES",
    "sg:address":"Calle de Norias (las), 5",
    "sg:city":"San Anton",
    "sg:orig_category":"Quincaller\u00cda (al Por Menor)",
    "sg:phone":"+34 968 29 15 53",
    "sg:postcode":"30009",
    "sg:province":"Murcia",
    "wof:name":"Herrajes Serrano S.l.",
    "wof:placetype":"venue"
},
  "geometry": {"coordinates":[-1.1405459642,37.9903831482],"type":"Point"}
}