{
  "type": "Feature",
  "properties": {
    "addr:full":"Calle de Omega, 14 Madrid Madrid 28032",
    "addr:housenumber":"14",
    "addr:postcode":"madrid;28032",
    "addr:street":"Calle De Omega",
    "iso:country":"ES",
    "sg:address":"Calle de Omega, 14",
    "sg:city":"Madrid",
    "sg:orig_category":"Material Y Suministros Para Fotocopiadoras, Reprograf\u00cda",
    "sg:phone":"+34 917 75 34 84",
    "sg:postcode":"28032",
    "sg:province":"Madrid",
    "wof:name":"Bermejo Moran Jose Manuel",
    "wof:placetype":"venue"
},
  "geometry": {"coordinates":[-3.6055669785,40.4003143311],"type":"Point"}
}