{
  "type": "Feature",
  "properties": {
    "iso:country":"ES",
    "sg:address":"Av Carles Buigas (de), 20",
    "sg:city":"Salou",
    "sg:orig_category":"Deportes Y Programas De Aventura",
    "sg:phone":"+34 977 35 17 55",
    "sg:postcode":"43840",
    "sg:province":"Tarragona",
    "wof:name":"New Fast Time Company S.l.",
    "wof:placetype":"venue"
},
  "geometry": {"coordinates":[1.148015976,41.0724601746],"type":"Point"}
}