{
  "type": "Feature",
  "properties": {
    "iso:country":"ES",
    "sg:address":"Calle de Puerto Rico, 44",
    "sg:city":"Ejido",
    "sg:orig_category":"Transporte En General",
    "sg:phone":"+34 950 48 80 11",
    "sg:postcode":"04700",
    "sg:province":"Almer\u00eda",
    "wof:name":"Ejido Logistica S.l.u.",
    "wof:placetype":"venue"
},
  "geometry": {"coordinates":[-2.8037919998,36.7683982849],"type":"Point"}
}