{
  "type": "Feature",
  "properties": {
    "addr:full":"Rua Alberto Vilanova (de), 11 Carballi\u00f1o Ourense 32500",
    "addr:postcode":"32500",
    "addr:street":"Rua Alberto",
    "iso:country":"ES",
    "sg:address":"Rua Alberto Vilanova (de), 11",
    "sg:city":"Carballi\u00f1o",
    "sg:orig_category":"Promotores Constructores",
    "sg:phone":"+34 988 27 46 05",
    "sg:postcode":"32500",
    "sg:province":"Ourense",
    "wof:name":"Itelga S.l.",
    "wof:placetype":"venue"
},
  "geometry": {"coordinates":[-8.0723085403,42.4294700623],"type":"Point"}
}