{
  "type": "Feature",
  "properties": {
    "addr:full":"Carrer de Felip Pedrell, 83 Sabadell Barcelona 08208",
    "addr:housenumber":"83",
    "addr:postcode":"08208",
    "addr:street":"Carrer De Felip Pedrell",
    "iso:country":"ES",
    "sg:address":"Carrer de Felip Pedrell, 83",
    "sg:city":"Sabadell",
    "sg:orig_category":"Asesor\u00cda Sobre Comunicaci\u00d3n De Empresas",
    "sg:phone":"+34 937 23 38 86",
    "sg:postcode":"08208",
    "sg:province":"Barcelona",
    "wof:name":"Asesoramiento Mercantil Y Servic Admon S.a.",
    "wof:placetype":"venue"
},
  "geometry": {"coordinates":[2.0983667374,41.5595779419],"type":"Point"}
}