{
  "type": "Feature",
  "properties": {
    "iso:country":"ES",
    "sg:address":"Urbanizacion El Bosque, 341",
    "sg:city":"El Bosque",
    "sg:orig_category":"M\u00c9dicos: Cirug\u00cda Pl\u00c1stica, Reconstructiva Y Est\u00c9tica",
    "sg:phone":"+34 961 80 41 09",
    "sg:postcode":"46370",
    "sg:province":"Valencia",
    "wof:name":"Microcirugia Reconstructiva S.l.",
    "wof:placetype":"venue"
},
  "geometry": {"coordinates":[-0.7179690003,39.4728012085],"type":"Point"}
}