{
  "type": "Feature",
  "properties": {
    "iso:country":"ES",
    "sg:address":"Calle de Villegas Marmolejo, 5",
    "sg:city":"Sevilla",
    "sg:orig_category":"Farmacias",
    "sg:phone":"+34 954 63 26 30",
    "sg:postcode":"41005",
    "sg:province":"Sevilla",
    "wof:name":"Rider Perez Antonio",
    "wof:placetype":"venue"
},
  "geometry": {"coordinates":[-5.9692950249,37.3788032532],"type":"Point"}
}