{
  "type": "Feature",
  "properties": {
    "addr:full":"Carrer de Cultura, 2 Hospitalet Llobregat Barcelona 08902",
    "addr:housenumber":"2",
    "addr:postcode":"08902",
    "addr:street":"Carrer De Cultura",
    "iso:country":"ES",
    "sg:address":"Carrer de Cultura, 2",
    "sg:city":"Hospitalet Llobregat",
    "sg:orig_category":"Limpieza Con Chorro De Arena Y Con Granalla, Pulido",
    "sg:phone":"+34 933 31 55 82",
    "sg:postcode":"08902",
    "sg:province":"Barcelona",
    "wof:name":"Diaz Lopez Antonio",
    "wof:placetype":"venue"
},
  "geometry": {"coordinates":[2.1201210022,41.3658638],"type":"Point"}
}