{
  "type": "Feature",
  "properties": {
    "iso:country":"ES",
    "sg:address":"Av Creu Roja, 1",
    "sg:city":"Cerdanyola Valles",
    "sg:orig_category":"Inversiones",
    "sg:phone":"+34 935 80 29 86",
    "sg:postcode":"08290",
    "sg:province":"Barcelona",
    "wof:name":"Lixting Inversiones S.l.",
    "wof:placetype":"venue"
},
  "geometry": {"coordinates":[2.1486101151,41.4935913086],"type":"Point"}
}