{
  "type": "Feature",
  "properties": {
    "iso:country":"ES",
    "sg:address":"Carrer de Puerto Rico, 37",
    "sg:city":"Masnou",
    "sg:orig_category":"Papeler\u00cdas, Librer\u00cdas",
    "sg:phone":"+34 935 40 11 01",
    "sg:postcode":"08320",
    "sg:province":"Barcelona",
    "wof:name":"Castella Vilas Josefa",
    "wof:placetype":"venue"
},
  "geometry": {"coordinates":[2.3280949593,41.4816818237],"type":"Point"}
}