{
  "type": "Feature",
  "properties": {
    "addr:full":"Calle de Don Ricardo, 2 Malaga M\u00e1laga 29007",
    "addr:housenumber":"2",
    "addr:postcode":"29007",
    "addr:street":"Calle De Don Ricardo;Ma\u0301Laga",
    "iso:country":"ES",
    "sg:address":"Calle de Don Ricardo, 2",
    "sg:city":"Malaga",
    "sg:orig_category":"Psic\u00d3logos",
    "sg:phone":"+34 952 61 49 14",
    "sg:postcode":"29007",
    "sg:province":"M\u00e1laga",
    "wof:name":"Jimenez Pascual Teresa",
    "wof:placetype":"venue"
},
  "geometry": {"coordinates":[-4.4301557541,36.7193222046],"type":"Point"}
}