{
  "type": "Feature",
  "properties": {
    "iso:country":"ES",
    "sg:address":"Carrer de Major, S/n",
    "sg:city":"Centre",
    "sg:orig_category":"Estaciones De Servicio",
    "sg:phone":"+34 936 83 15 42",
    "sg:postcode":"08759",
    "sg:province":"Barcelona",
    "wof:name":"Repsol Ypf S.a.",
    "wof:placetype":"venue"
},
  "geometry": {"coordinates":[1.9203499556,41.380191803],"type":"Point"}
}