{
  "type": "Feature",
  "properties": {
    "addr:full":"Carrer de Major, S/n Centre Barcelona 08759",
    "addr:housenumber":"s / n",
    "addr:postcode":"08759",
    "addr:street":"Carrer De Major",
    "iso:country":"ES",
    "sg:address":"Carrer de Major, S/n",
    "sg:city":"Centre",
    "sg:orig_category":"Estaciones De Servicio",
    "sg:phone":"+34 936 83 15 42",
    "sg:postcode":"08759",
    "sg:province":"Barcelona",
    "wof:name":"Repsol Ypf S.a.",
    "wof:placetype":"venue"
},
  "geometry": {"coordinates":[1.9203499556,41.380191803],"type":"Point"}
}