{
  "type": "Feature",
  "properties": {
    "addr:full":"Plaz Candelaria (de La), 13 Gran Tarajal Las Palmas 35620",
    "addr:postcode":"35620",
    "addr:street":"Palmas",
    "iso:country":"ES",
    "sg:address":"Plaz Candelaria (de La), 13",
    "sg:city":"Gran Tarajal",
    "sg:orig_category":"Alimentaci\u00d3n General (al Por Menor)",
    "sg:phone":"+34 928 87 00 44",
    "sg:postcode":"35620",
    "sg:province":"Las Palmas",
    "wof:name":"Hernandez Cabrera Juan",
    "wof:placetype":"venue"
},
  "geometry": {"coordinates":[-14.0201587677,28.2145900726],"type":"Point"}
}