{
  "type": "Feature",
  "properties": {
    "iso:country":"ES",
    "sg:address":"Calle de Virgen De La Pe\u00d1a, 48",
    "sg:city":"Pto. Rosario",
    "sg:orig_category":"Ropa Para Se\u00d1oras Y Caballeros (al Por Menor)",
    "sg:phone":"+34 928 34 46 36",
    "sg:postcode":"35600",
    "sg:province":"Las Palmas",
    "wof:name":"Lopez Cruz Inmaculada",
    "wof:placetype":"venue"
},
  "geometry": {"coordinates":[-13.868396759,28.5010108948],"type":"Point"}
}