{
  "type": "Feature",
  "properties": {
    "iso:country":"ES",
    "sg:address":"O Covelo, 29",
    "sg:city":"Covelo",
    "sg:orig_category":"Material Y Herramientas Agr\u00cdcolas",
    "sg:phone":"+34 986 55 36 11",
    "sg:postcode":"36660",
    "sg:province":"Pontevedra",
    "wof:name":"Agricola Mora\u00f1esa S.l.",
    "wof:placetype":"venue"
},
  "geometry": {"coordinates":[-8.6038713455,42.5896911621],"type":"Point"}
}