{
  "type": "Feature",
  "properties": {
    "addr:full":"Calle de Juan De Olias, 26 Madrid Madrid 28020",
    "addr:housenumber":"26",
    "addr:postcode":"madrid;28020",
    "addr:street":"Calle De Juan De Olias",
    "iso:country":"ES",
    "sg:address":"Calle de Juan De Olias, 26",
    "sg:city":"Madrid",
    "sg:orig_category":"M\u00c1quinas De Escribir, M\u00c1quinas De Oficina (al Por Menor, Reparaci\u00d3n)",
    "sg:phone":"+34 915 71 87 76",
    "sg:postcode":"28020",
    "sg:province":"Madrid",
    "sg:website":"www.cymosl.com",
    "wof:name":"Copiadoras Y Medios De Oficina S.l.",
    "wof:placetype":"venue"
},
  "geometry": {"coordinates":[-3.7002389431,40.4531898499],"type":"Point"}
}