{
  "type": "Feature",
  "properties": {
    "iso:country":"ES",
    "sg:address":"Calle de Peru, 12",
    "sg:city":"Mostoles",
    "sg:orig_category":"Calefacci\u00d3n Central: Material (fabricaci\u00d3n, Al Por Mayor)",
    "sg:phone":"+34 916 45 37 64",
    "sg:postcode":"28936",
    "sg:province":"Madrid",
    "wof:name":"Vazquez Rodriguez Francisco",
    "wof:placetype":"venue"
},
  "geometry": {"coordinates":[-3.8557567596,40.3166618347],"type":"Point"}
}