{
  "type": "Feature",
  "properties": {
    "addr:full":"Calle de Tornavacas, 9 Plasencia C\u00e1ceres 10600",
    "addr:housenumber":"9",
    "addr:postcode":"10600",
    "addr:street":"Calle De Tornavacas;Ca\u0301Ceres",
    "iso:country":"ES",
    "sg:address":"Calle de Tornavacas, 9",
    "sg:city":"Plasencia",
    "sg:orig_category":"Arreglo, Reparaci\u00d3n, Piezas Sueltas De Televisi\u00d3n, V\u00cddeo, Hi",
    "sg:phone":"+34 927 41 11 21",
    "sg:postcode":"10600",
    "sg:province":"C\u00e1ceres",
    "wof:name":"Sanchez Quijada Arsenio",
    "wof:placetype":"venue"
},
  "geometry": {"coordinates":[-6.0898518562,40.0299453735],"type":"Point"}
}