{
  "type": "Feature",
  "properties": {
    "iso:country":"ES",
    "sg:address":"Calle de Santa Elena, 30",
    "sg:city":"Plasencia",
    "sg:orig_category":"Instalaci\u00d3n, Reparaci\u00d3n De Calefacci\u00d3n El\u00c9ctrica",
    "sg:phone":"+34 927 41 84 01",
    "sg:postcode":"10600",
    "sg:province":"C\u00e1ceres",
    "wof:name":"F Paramio S.l.",
    "wof:placetype":"venue"
},
  "geometry": {"coordinates":[-6.0834012032,40.0313491821],"type":"Point"}
}