{
  "type": "Feature",
  "properties": {
    "iso:country":"ES",
    "sg:address":"Calle de Milanos, 6",
    "sg:city":"Pinto",
    "sg:orig_category":"Producci\u00d3n De Huevos",
    "sg:phone":"+34 916 92 67 98",
    "sg:postcode":"28320",
    "sg:province":"Madrid",
    "wof:name":"Dismoraleda S.l.",
    "wof:placetype":"venue"
},
  "geometry": {"coordinates":[-3.7054750919,40.248626709],"type":"Point"}
}