{
  "type": "Feature",
  "properties": {
    "addr:full":"Carrer de Fisas, 7 Barcelona Barcelona 08028",
    "addr:housenumber":"7",
    "addr:postcode":"08028",
    "addr:street":"Carrer De Fisas",
    "iso:country":"ES",
    "sg:address":"Carrer de Fisas, 7",
    "sg:city":"Barcelona",
    "sg:orig_category":"M\u00c1rmoles, Granitos Y Piedras Naturales",
    "sg:phone":"+34 934 90 23 17",
    "sg:postcode":"08028",
    "sg:province":"Barcelona",
    "sg:website":"www.marmolesfernandez.es",
    "wof:name":"Fernandez Meca Maria",
    "wof:placetype":"venue"
},
  "geometry": {"coordinates":[2.1275200844,41.3767127991],"type":"Point"}
}