{
  "type": "Feature",
  "properties": {
    "addr:full":"Pg Maragall, 269 Barcelona Barcelona 08032",
    "addr:housenumber":"269",
    "addr:postcode":"08032",
    "addr:street":"Pg Maragall",
    "iso:country":"ES",
    "sg:address":"Pg Maragall, 269",
    "sg:city":"Barcelona",
    "sg:orig_category":"Panader\u00cdas, Panader\u00cdas",
    "sg:phone":"+34 934 35 48 73",
    "sg:postcode":"08032",
    "sg:province":"Barcelona",
    "wof:name":"Mas Clave Juan",
    "wof:placetype":"venue"
},
  "geometry": {"coordinates":[2.172825098,41.4263000488],"type":"Point"}
}