{
  "type": "Feature",
  "properties": {
    "iso:country":"ES",
    "sg:address":"Carrer de Albinyana, 82",
    "sg:city":"Terrassa",
    "sg:orig_category":"Materias Pl\u00c1sticas: Productos De Consumo Masivo (fabricaci\u00d3n, Al Por Mayor)",
    "sg:phone":"+34 937 85 45 35",
    "sg:postcode":"08223",
    "sg:province":"Barcelona",
    "wof:name":"Jordan Catambert Alberto",
    "wof:placetype":"venue"
},
  "geometry": {"coordinates":[2.0244479179,41.5563468933],"type":"Point"}
}