{
  "type": "Feature",
  "properties": {
    "addr:full":"Calle de Gabriel Paya, 40 Petrer Alicante 03610",
    "addr:housenumber":"40",
    "addr:postcode":"03610",
    "addr:street":"Calle De Gabriel Paya",
    "iso:country":"ES",
    "sg:address":"Calle de Gabriel Paya, 40",
    "sg:city":"Petrer",
    "sg:orig_category":"Electrodom\u00c9sticos (al Por Menor)",
    "sg:phone":"+34 965 37 07 74",
    "sg:postcode":"03610",
    "sg:province":"Alicante",
    "wof:name":"Electrodomesticos Boreal S.l.",
    "wof:placetype":"venue"
},
  "geometry": {"coordinates":[-0.7729489803,38.4847221375],"type":"Point"}
}