{
  "type": "Feature",
  "properties": {
    "iso:country":"ES",
    "sg:address":"Carrer de Roger De Lluria, 126",
    "sg:city":"Barcelona",
    "sg:orig_category":"Tapiceros Y Tapiceros",
    "sg:phone":"+34 932 07 21 25",
    "sg:postcode":"08037",
    "sg:province":"Barcelona",
    "wof:name":"Estudio Decoracion Lopez Landa S. L.",
    "wof:placetype":"venue"
},
  "geometry": {"coordinates":[2.1627750397,41.3979148865],"type":"Point"}
}