{
  "type": "Feature",
  "properties": {
    "addr:full":"C/ Maestro Albeniz, S/n Elche Alicante 03202",
    "addr:housenumber":"s / n",
    "addr:postcode":"03202",
    "addr:street":"C / Maestro Albeniz",
    "iso:country":"ES",
    "sg:address":"C/ Maestro Albeniz, S/n",
    "sg:city":"Elche",
    "sg:orig_category":"Ingenier\u00cda, Centros De Estudios (diversos)",
    "sg:phone":"+34 965 45 90 77",
    "sg:postcode":"03202",
    "sg:province":"Alicante",
    "wof:name":"Montenegro Casta\u00f1o Manuel",
    "wof:placetype":"venue"
},
  "geometry": {"coordinates":[-0.6950539947,38.2684440613],"type":"Point"}
}