{
  "type": "Feature",
  "properties": {
    "iso:country":"ES",
    "sg:address":"Calle de Santa Rosa, S/n",
    "sg:city":"Tapia Casariego",
    "sg:orig_category":"Ropa Para Se\u00d1oras (al Por Menor)",
    "sg:phone":"+34 985 47 28 85",
    "sg:postcode":"33740",
    "sg:province":"Asturias",
    "wof:name":"Cotarelo Fernandez Maria Isabel",
    "wof:placetype":"venue"
},
  "geometry": {"coordinates":[-6.9429087639,43.5710716248],"type":"Point"}
}