{
  "type": "Feature",
  "properties": {
    "iso:country":"ES",
    "sg:address":"Avda Generalisimo, S/n",
    "sg:city":"Barbate",
    "sg:orig_category":"Almacenes Frigor\u00cdficos",
    "sg:phone":"+34 956 43 00 04",
    "sg:postcode":"11160",
    "sg:province":"C\u00e1diz",
    "wof:name":"Conservas El Rey De Oros S.l.",
    "wof:placetype":"venue"
},
  "geometry": {"coordinates":[-5.9205489159,36.1911468506],"type":"Point"}
}