{
  "type": "Feature",
  "properties": {
    "addr:full":"Altea(jardin Jaravilla), 8 Pobla Vallbona Valencia 46185",
    "addr:housenumber":"8",
    "addr:postcode":"46185",
    "iso:country":"ES",
    "sg:address":"Altea(jardin Jaravilla), 8",
    "sg:city":"Pobla Vallbona",
    "sg:orig_category":"Inmobiliaria (agencias)",
    "sg:phone":"+34 962 76 40 06",
    "sg:postcode":"46185",
    "sg:province":"Valencia",
    "wof:name":"Martinez Cuadros Jose Luis",
    "wof:placetype":"venue"
},
  "geometry": {"coordinates":[-0.5194839835,39.5827102661],"type":"Point"}
}