{
  "type": "Feature",
  "properties": {
    "iso:country":"ES",
    "sg:address":"Calle de Artes Graficas, 24",
    "sg:city":"Valencia",
    "sg:orig_category":"Arquitectos",
    "sg:phone":"+34 963 61 85 66",
    "sg:postcode":"46010",
    "sg:province":"Valencia",
    "wof:name":"Gonzalo Aznar Ignacio",
    "wof:placetype":"venue"
},
  "geometry": {"coordinates":[-0.3610425889,39.4762916565],"type":"Point"}
}