{
  "type": "Feature",
  "properties": {
    "iso:country":"ES",
    "sg:address":"Calle de Jose M. Salaberria, 16",
    "sg:city":"Donostia-san Sebastian",
    "sg:orig_category":"Bisuter\u00cda, Joyer\u00cda, Relojer\u00cda (al Por Menor)",
    "sg:phone":"+34 943 47 38 82",
    "sg:postcode":"20010",
    "sg:province":"Guip\u00f9zcoa",
    "sg:website":"www.ambar.com",
    "wof:name":"Egido Ochoa Maria Carmen",
    "wof:placetype":"venue"
},
  "geometry": {"coordinates":[-1.9804120064,43.3033866882],"type":"Point"}
}