{
  "type": "Feature",
  "properties": {
    "iso:country":"ES",
    "sg:address":"Calle de Palacio, 11",
    "sg:city":"Bola\u00e7os De Campos",
    "sg:orig_category":"Cajas Para Embalar",
    "sg:phone":"+34 983 75 73 52",
    "sg:postcode":"47675",
    "sg:province":"Valladolid",
    "wof:name":"Caja Rural Del Duero",
    "wof:placetype":"venue"
},
  "geometry": {"coordinates":[-5.2857289314,42.0067214966],"type":"Point"}
}