{
  "type": "Feature",
  "properties": {
    "addr:full":"Calle de Nueva, 21 Malaga M\u00e1laga 29005",
    "addr:housenumber":"21",
    "addr:postcode":"29005",
    "addr:street":"Calle De Nueva;Ma\u0301Laga",
    "iso:country":"ES",
    "sg:address":"Calle de Nueva, 21",
    "sg:city":"Malaga",
    "sg:orig_category":"Complementos De Vestir (al Por Menor)",
    "sg:phone":"+34 952 12 24 50",
    "sg:postcode":"29005",
    "sg:province":"M\u00e1laga",
    "wof:name":"Francisco Pavon Fajardo S.l.",
    "wof:placetype":"venue"
},
  "geometry": {"coordinates":[-4.4227972031,36.7195167542],"type":"Point"}
}