{
  "type": "Feature",
  "properties": {
    "iso:country":"ES",
    "sg:address":"Calle de Jose Maria Doblas, 33",
    "sg:city":"Rincon Victoria",
    "sg:orig_category":"Artes Gr\u00c1ficas, Artes Pl\u00c1sticas: Material Y Suministros (al Por Menor)",
    "sg:phone":"+34 952 40 39 02",
    "sg:postcode":"29730",
    "sg:province":"M\u00e1laga",
    "wof:name":"Multiservicios Lupion Y Baez S.c",
    "wof:placetype":"venue"
},
  "geometry": {"coordinates":[-4.2863640785,36.7167282104],"type":"Point"}
}