{
  "type": "Feature",
  "properties": {
    "addr:full":"Boni Laskurain Pasealekua, 21 Bergara Guip\u00f9zcoa 20570",
    "addr:housenumber":"21",
    "addr:postcode":"20570",
    "addr:street":"Boni Laskurain Pasealekua;Guipu\u0300Zcoa",
    "iso:country":"ES",
    "sg:address":"Boni Laskurain Pasealekua, 21",
    "sg:city":"Bergara",
    "sg:orig_category":"Asociaciones Y Clubs Deportivos",
    "sg:phone":"+34 943 76 02 37",
    "sg:postcode":"20570",
    "sg:province":"Guip\u00f9zcoa",
    "wof:name":"Club Deportivo Bergara",
    "wof:placetype":"venue"
},
  "geometry": {"coordinates":[-2.4247009754,43.1205711365],"type":"Point"}
}