{
  "type": "Feature",
  "properties": {
    "iso:country":"ES",
    "sg:address":"Av Alfinach, 16",
    "sg:city":"Pu\u00e7ol",
    "sg:orig_category":"Sociedades, Compa\u00d1\u00cdas Aseguradoras",
    "sg:phone":"+34 961 46 52 18",
    "sg:postcode":"46530",
    "sg:province":"Valencia",
    "wof:name":"Esteve Bosch Mercedes Elisa",
    "wof:placetype":"venue"
},
  "geometry": {"coordinates":[-0.3008790016,39.6156044006],"type":"Point"}
}