{
  "type": "Feature",
  "properties": {
    "addr:full":"La Rambla, 6 Puente-genil C\u00f3rdoba 14500",
    "addr:housenumber":"6",
    "addr:postcode":"14500",
    "addr:street":"La Rambla;Co\u0301Rdoba",
    "iso:country":"ES",
    "sg:address":"La Rambla, 6",
    "sg:city":"Puente-genil",
    "sg:orig_category":"Veh\u00cdculos De Ocasi\u00d3n",
    "sg:phone":"+34 957 60 27 52",
    "sg:postcode":"14500",
    "sg:province":"C\u00f3rdoba",
    "wof:name":"Ure\u00f1a Molinas Francisco",
    "wof:placetype":"venue"
},
  "geometry": {"coordinates":[-4.765267849,37.394744873],"type":"Point"}
}