{
  "type": "Feature",
  "properties": {
    "addr:full":"Calle de Amatista, 2 Urbanizacion Mediterraneo Murcia 30310",
    "addr:housenumber":"2",
    "addr:postcode":"30310",
    "addr:street":"Calle De Amatista",
    "iso:country":"ES",
    "sg:address":"Calle de Amatista, 2",
    "sg:city":"Urbanizacion Mediterraneo",
    "sg:orig_category":"Tiendas De Grano, Frutas Y Legumbres Secas (al Por Menor)",
    "sg:phone":"+34 968 51 04 75",
    "sg:postcode":"30310",
    "sg:province":"Murcia",
    "wof:name":"Montoro Solano Francisco",
    "wof:placetype":"venue"
},
  "geometry": {"coordinates":[-1.1298867464,37.9834747314],"type":"Point"}
}