{
  "type": "Feature",
  "properties": {
    "iso:country":"ES",
    "sg:address":"Rua Ourense, 81",
    "sg:city":"Lugo",
    "sg:orig_category":"Agencias Y Agentes Comerciales, Representantes",
    "sg:phone":"+34 982 20 37 52",
    "sg:postcode":"27004",
    "sg:province":"Lugo",
    "wof:name":"Muralla Tramitaciones S.l.",
    "wof:placetype":"venue"
},
  "geometry": {"coordinates":[-7.565735817,43.0154914856],"type":"Point"}
}