{
  "type": "Feature",
  "properties": {
    "iso:country":"ES",
    "sg:address":"Carrer de Pica\u00d1ol, 72",
    "sg:city":"Sabadell",
    "sg:orig_category":"Peluqueros: De Se\u00d1oras",
    "sg:phone":"+34 937 17 43 51",
    "sg:postcode":"08208",
    "sg:province":"Barcelona",
    "wof:name":"Crous Sala Margarita",
    "wof:placetype":"venue"
},
  "geometry": {"coordinates":[2.1001999378,41.5522384644],"type":"Point"}
}