{
  "type": "Feature",
  "properties": {
    "iso:country":"ES",
    "sg:address":"Calle de Pintor Agustin Navarro, 15",
    "sg:city":"Mazarron",
    "sg:orig_category":"Droguer\u00cdas (al Por Menor)",
    "sg:phone":"+34 968 59 00 30",
    "sg:postcode":"30870",
    "sg:province":"Murcia",
    "wof:name":"Blaya Hernandez Bartolome",
    "wof:placetype":"venue"
},
  "geometry": {"coordinates":[-1.315950036,37.5989761353],"type":"Point"}
}