{
  "type": "Feature",
  "properties": {
    "iso:country":"ES",
    "sg:address":"Monte Senra, S/n",
    "sg:city":"Ortigueira",
    "sg:orig_category":"Barnizadores",
    "sg:phone":"+34 981 42 21 76",
    "sg:postcode":"15330",
    "sg:province":"La Coru\u00f1a",
    "wof:name":"Pinturas Y Decoraciones Bouces Sl",
    "wof:placetype":"venue"
},
  "geometry": {"coordinates":[-7.8530597687,43.6817398071],"type":"Point"}
}