{
  "type": "Feature",
  "properties": {
    "addr:full":"Calle de Maria La Talegona, 1 Cordoba C\u00f3rdoba 14005",
    "addr:housenumber":"1",
    "addr:postcode":"14005",
    "addr:street":"Calle De Maria La Talegona;Co\u0301Rdoba",
    "iso:country":"ES",
    "sg:address":"Calle de Maria La Talegona, 1",
    "sg:city":"Cordoba",
    "sg:orig_category":"Reposter\u00cdas",
    "sg:phone":"+34 957 46 31 51",
    "sg:postcode":"14005",
    "sg:province":"C\u00f3rdoba",
    "wof:name":"Comercial Seyco S.l.",
    "wof:placetype":"venue"
},
  "geometry": {"coordinates":[-4.8146648407,37.8848762512],"type":"Point"}
}