{
  "type": "Feature",
  "properties": {
    "addr:full":"Calle de Jucar, 7 Alagon C\u00e1ceres 10690",
    "addr:housenumber":"7",
    "addr:postcode":"10690",
    "addr:street":"Calle De Jucar;Ca\u0301Ceres",
    "iso:country":"ES",
    "sg:address":"Calle de Jucar, 7",
    "sg:city":"Alagon",
    "sg:orig_category":"Ingeniero",
    "sg:phone":"+34 927 45 42 46",
    "sg:postcode":"10690",
    "sg:province":"C\u00e1ceres",
    "wof:name":"Martin Sanchez Raul",
    "wof:placetype":"venue"
},
  "geometry": {"coordinates":[-6.3157300949,39.9715003967],"type":"Point"}
}