{
  "type": "Feature",
  "properties": {
    "addr:full":"Avda Constitucion, 15 Bollullos Par Condado Huelva 21710",
    "addr:housenumber":"15",
    "addr:postcode":"21710",
    "addr:street":"Avda Constitucion",
    "iso:country":"ES",
    "sg:address":"Avda Constitucion, 15",
    "sg:city":"Bollullos Par Condado",
    "sg:orig_category":"Ropa Para Se\u00d1oras Y Caballeros (al Por Menor)",
    "sg:phone":"+34 959 41 14 01",
    "sg:postcode":"21710",
    "sg:province":"Huelva",
    "wof:name":"Sarmiento Modas S.l.",
    "wof:placetype":"venue"
},
  "geometry": {"coordinates":[-6.5374717712,37.3395385742],"type":"Point"}
}