{
  "type": "Feature",
  "properties": {
    "addr:full":"Carrer de Monturiol, 75 Terrassa Barcelona 08225",
    "addr:housenumber":"75",
    "addr:postcode":"08225",
    "addr:street":"Carrer De Monturiol",
    "iso:country":"ES",
    "sg:address":"Carrer de Monturiol, 75",
    "sg:city":"Terrassa",
    "sg:orig_category":"Empresas De Carpinter\u00cda De Madera",
    "sg:phone":"+34 937 89 27 01",
    "sg:postcode":"08225",
    "sg:province":"Barcelona",
    "wof:name":"Garcia Aguayo Alejandro",
    "wof:placetype":"venue"
},
  "geometry": {"coordinates":[2.0061299801,41.5734672546],"type":"Point"}
}