{
  "type": "Feature",
  "properties": {
    "addr:full":"Av Vidal I Barraquer, 4 Cambrils Tarragona 43850",
    "addr:housenumber":"4",
    "addr:postcode":"43850",
    "addr:street":"Av Vidal I Barraquer",
    "iso:country":"ES",
    "sg:address":"Av Vidal I Barraquer, 4",
    "sg:city":"Cambrils",
    "sg:orig_category":"Parques De Atracciones Y Centros De Esparcimiento",
    "sg:phone":"+34 977 36 68 07",
    "sg:postcode":"43850",
    "sg:province":"Tarragona",
    "wof:name":"Escofet Elling Bernardet",
    "wof:placetype":"venue"
},
  "geometry": {"coordinates":[1.0522520542,41.0739173889],"type":"Point"}
}