{
  "type": "Feature",
  "properties": {
    "iso:country":"ES",
    "sg:address":"Avda Pulianas (de), 50",
    "sg:city":"Granada",
    "sg:orig_category":"Farmacias",
    "sg:phone":"+34 958 15 31 82",
    "sg:postcode":"18011",
    "sg:province":"Granada",
    "wof:name":"Tamayo Lopez Cristina",
    "wof:placetype":"venue"
},
  "geometry": {"coordinates":[-3.6078128815,37.2056007385],"type":"Point"}
}