{
  "type": "Feature",
  "properties": {
    "iso:country":"ES",
    "sg:address":"La Obra, S/n",
    "sg:city":"Obra",
    "sg:orig_category":"Chapister\u00cda",
    "sg:phone":"+34 985 89 94 90",
    "sg:postcode":"33314",
    "sg:province":"Asturias",
    "wof:name":"Carrocerias Emilio Miranda S.l.",
    "wof:placetype":"venue"
},
  "geometry": {"coordinates":[-5.5501618385,43.532699585],"type":"Point"}
}