{
  "type": "Feature",
  "properties": {
    "iso:country":"ES",
    "sg:address":"Carretera De Linares-orcera, Km. 0045,0",
    "sg:city":"Santisteban Puerto",
    "sg:orig_category":"Art\u00cdculos De Aluminio",
    "sg:phone":"+34 953 12 30 55",
    "sg:postcode":"23250",
    "sg:province":"Ja\u00e9n",
    "wof:name":"Navajas Sanchez Jose",
    "wof:placetype":"venue"
},
  "geometry": {"coordinates":[-3.2013289928,38.250743866],"type":"Point"}
}