{
  "type": "Feature",
  "properties": {
    "addr:full":"Zarugalde Kalea, 3 Arrasate Guip\u00f9zcoa 20500",
    "addr:housenumber":"3",
    "addr:postcode":"20500",
    "addr:street":"Zarugalde Kalea;Guipu\u0300Zcoa",
    "iso:country":"ES",
    "sg:address":"Zarugalde Kalea, 3",
    "sg:city":"Arrasate",
    "sg:orig_category":"Abogados",
    "sg:phone":"+34 943 71 10 16",
    "sg:postcode":"20500",
    "sg:province":"Guip\u00f9zcoa",
    "wof:name":"Asesoria Urrats C.b.",
    "wof:placetype":"venue"
},
  "geometry": {"coordinates":[-2.4920709133,43.0660629272],"type":"Point"}
}