{
  "type": "Feature",
  "properties": {
    "addr:full":"Calle de Camino De Los Vinateros, 38 Madrid Madrid 28030",
    "addr:housenumber":"38",
    "addr:postcode":"madrid;28030",
    "addr:street":"Calle De Camino De Los Vinateros",
    "iso:country":"ES",
    "sg:address":"Calle de Camino De Los Vinateros, 38",
    "sg:city":"Madrid",
    "sg:classifiers":[
        {
            "category":"Autos & Motor Vehicles",
            "subcategory":"Automobile Sales",
            "type":"Retail Goods"
        }
    ],
    "sg:phone":"+34 914 30 40 01",
    "sg:postcode":"28030",
    "sg:province":"Madrid",
    "wof:name":"Aviles Moran Paloma",
    "wof:placetype":"venue"
},
  "geometry": {"coordinates":[-3.6557328701,40.4105949402],"type":"Point"}
}