{
  "type": "Feature",
  "properties": {
    "addr:full":"Calle de Colegiata La, 4 Nava Asturias 33520",
    "addr:housenumber":"4",
    "addr:postcode":"33520",
    "addr:street":"Calle De Colegiata La",
    "iso:country":"ES",
    "sg:address":"Calle de Colegiata La, 4",
    "sg:city":"Nava",
    "sg:orig_category":"Muebles, Minoristas",
    "sg:phone":"+34 985 71 62 46",
    "sg:postcode":"33520",
    "sg:province":"Asturias",
    "wof:name":"Sanchez Collada Angel Luis",
    "wof:placetype":"venue"
},
  "geometry": {"coordinates":[-5.5098028183,43.3586387634],"type":"Point"}
}