{
  "type": "Feature",
  "properties": {
    "addr:full":"Av. Palencia, 120 Torrelavega Cantabria 39300",
    "addr:housenumber":"120",
    "addr:postcode":"39300",
    "addr:street":"Av. Palencia",
    "iso:country":"ES",
    "sg:address":"Av. Palencia, 120",
    "sg:city":"Torrelavega",
    "sg:orig_category":"Pintura Y Barniz (al Por Menor)",
    "sg:phone":"+34 942 89 37 50",
    "sg:postcode":"39300",
    "sg:province":"Cantabria",
    "sg:website":"www.ferroluz.com",
    "wof:name":"Pinturas Solpaint S.l.",
    "wof:placetype":"venue"
},
  "geometry": {"coordinates":[-4.0606408119,43.3388671875],"type":"Point"}
}