{
  "type": "Feature",
  "properties": {
    "addr:full":"Calle de Monte Albillo, 1 Algete Madrid 28110",
    "addr:housenumber":"1",
    "addr:postcode":"28110",
    "addr:street":"Calle De Monte Albillo",
    "iso:country":"ES",
    "sg:address":"Calle de Monte Albillo, 1",
    "sg:city":"Algete",
    "sg:orig_category":"Inmobiliaria (agencias)",
    "sg:phone":"+34 916 29 09 21",
    "sg:postcode":"28110",
    "sg:province":"Madrid",
    "wof:name":"Gestiones Inmobiliarias Archifera S.l",
    "wof:placetype":"venue"
},
  "geometry": {"coordinates":[-3.5046710968,40.5967407227],"type":"Point"}
}