{
  "type": "Feature",
  "properties": {
    "iso:country":"ES",
    "sg:address":"Avda Fernando Blanco, 59",
    "sg:city":"Cee",
    "sg:orig_category":"Parafarmacias",
    "sg:phone":"+34 981 74 76 13",
    "sg:postcode":"15270",
    "sg:province":"La Coru\u00f1a",
    "wof:name":"Construcciones Queirol S.l.",
    "wof:placetype":"venue"
},
  "geometry": {"coordinates":[-9.1849555969,42.9515113831],"type":"Point"}
}