{
  "type": "Feature",
  "properties": {
    "addr:full":"Calle de Navarrete El Mudo, 2 Logro\u00f1o La Rioja 26005",
    "addr:housenumber":"2",
    "addr:postcode":"26005",
    "addr:street":"Calle De Navarrete El Mudo;Rioja",
    "iso:country":"ES",
    "sg:address":"Calle de Navarrete El Mudo, 2",
    "sg:city":"Logro\u00f1o",
    "sg:orig_category":"Relojer\u00cda (al Por Menor, Reparaci\u00d3n)",
    "sg:phone":"+34 941 20 05 59",
    "sg:postcode":"26005",
    "sg:province":"La Rioja",
    "wof:name":"Vidal Oraa Carlos",
    "wof:placetype":"venue"
},
  "geometry": {"coordinates":[-2.4572629929,42.4638900757],"type":"Point"}
}