{
  "type": "Feature",
  "properties": {
    "addr:full":"Calle de San Lorenzo, 8 Donostia-san Sebastian Guip\u00f9zcoa 20003",
    "addr:housenumber":"8",
    "addr:postcode":"20003",
    "addr:street":"Calle De San Lorenzo",
    "iso:country":"ES",
    "sg:address":"Calle de San Lorenzo, 8",
    "sg:city":"Donostia-san Sebastian",
    "sg:orig_category":"Pescader\u00cdas (al Por Menor)",
    "sg:phone":"+34 943 42 06 34",
    "sg:postcode":"20003",
    "sg:province":"Guip\u00f9zcoa",
    "wof:name":"Pescados Fergar S.coop.",
    "wof:placetype":"venue"
},
  "geometry": {"coordinates":[-1.9836210012,43.3232154846],"type":"Point"}
}