{
  "type": "Feature",
  "properties": {
    "iso:country":"ES",
    "sg:address":"Avda Portugal (de), 51",
    "sg:city":"Ourense",
    "sg:orig_category":"Molduras, Junquillos, Listones Y Molduras Perforadas",
    "sg:phone":"+34 988 22 65 16",
    "sg:postcode":"32002",
    "sg:province":"Ourense",
    "wof:name":"Telefourense",
    "wof:placetype":"venue"
},
  "geometry": {"coordinates":[-7.8714947701,42.3374633789],"type":"Point"}
}