{
  "type": "Feature",
  "properties": {
    "addr:full":"Calle de General Diaz Porlier, 1 Madrid Madrid 28001",
    "addr:housenumber":"1",
    "addr:postcode":"28001",
    "addr:street":"Calle De General Diaz Porlier",
    "iso:country":"ES",
    "sg:address":"Calle de General Diaz Porlier, 1",
    "sg:city":"Madrid",
    "sg:orig_category":"Ense\u00d1anza: Idiomas",
    "sg:phone":"+34 914 35 42 38",
    "sg:postcode":"28001",
    "sg:province":"Madrid",
    "sg:website":"www.todosp.com",
    "wof:name":"Todo Espa\u00f1ol C.b.",
    "wof:placetype":"venue"
},
  "geometry": {"coordinates":[-3.6773240566,40.4241485596],"type":"Point"}
}