{
  "type": "Feature",
  "properties": {
    "addr:full":"Calle de Teniente Coronel Gautier, 37 Ceuta Ceuta 51002",
    "addr:housenumber":"37",
    "addr:postcode":"51002",
    "addr:street":"Calle De Teniente Coronel Gautier",
    "iso:country":"ES",
    "sg:address":"Calle de Teniente Coronel Gautier, 37",
    "sg:city":"Ceuta",
    "sg:orig_category":"Bazares, Art\u00cdculos De Limpieza Y De Cocina (al Por Menor)",
    "sg:phone":"+34 956 50 42 72",
    "sg:postcode":"51002",
    "sg:province":"Ceuta",
    "wof:name":"Granado Quintero Maria Luisa",
    "wof:placetype":"venue"
},
  "geometry": {"coordinates":[-5.3316898346,35.8851280212],"type":"Point"}
}