{
  "type": "Feature",
  "properties": {
    "addr:full":"Calle de Doctor Mara\u00d1on, 1 San Miguel Murcia 30008",
    "addr:housenumber":"1",
    "addr:postcode":"30008",
    "addr:street":"Calle De Doctor Maran\u0303On",
    "iso:country":"ES",
    "sg:address":"Calle de Doctor Mara\u00d1on, 1",
    "sg:city":"San Miguel",
    "sg:orig_category":"Supermercados Y Hipermercados",
    "sg:phone":"+34 968 23 81 93",
    "sg:postcode":"30008",
    "sg:province":"Murcia",
    "wof:name":"Murcia-andres Meseguer S. A.",
    "wof:placetype":"venue"
},
  "geometry": {"coordinates":[-1.1298867464,37.9834747314],"type":"Point"}
}