{
  "type": "Feature",
  "properties": {
    "addr:full":"Touron, S/n Touron Pontevedra 36828",
    "addr:housenumber":"s / n",
    "addr:postcode":"36828",
    "addr:street":"Touron",
    "iso:country":"ES",
    "sg:address":"Touron, S/n",
    "sg:city":"Touron",
    "sg:orig_category":"Art\u00cdculos De Madera (fabricaci\u00d3n Y Al Por Mayor)",
    "sg:phone":"+34 986 75 02 91",
    "sg:postcode":"36828",
    "sg:province":"Pontevedra",
    "wof:name":"Martinez Regueira Luis",
    "wof:placetype":"venue"
},
  "geometry": {"coordinates":[-8.5254440308,42.3846893311],"type":"Point"}
}