{
  "type": "Feature",
  "properties": {
    "iso:country":"ES",
    "sg:address":"Calle de Antonio Garcia Gascon, 13",
    "sg:city":"Pozuelo De Alarcon",
    "sg:orig_category":"Promotores Constructores",
    "sg:phone":"+34 917 15 58 49",
    "sg:postcode":"28224",
    "sg:province":"Madrid",
    "wof:name":"Arrufat 21 Promociones Y Serv. S.l.",
    "wof:placetype":"venue"
},
  "geometry": {"coordinates":[-3.8085370064,40.4495735168],"type":"Point"}
}