{
  "type": "Feature",
  "properties": {
    "addr:full":"Outeiro, 16 Monte Lugo 27143",
    "addr:housenumber":"16",
    "addr:postcode":"27143",
    "addr:street":"Outeiro",
    "iso:country":"ES",
    "sg:address":"Outeiro, 16",
    "sg:city":"Monte",
    "sg:orig_category":"Loter\u00cda Y T\u00d3mbola",
    "sg:phone":"+34 982 31 21 80",
    "sg:postcode":"27143",
    "sg:province":"Lugo",
    "wof:name":"Hernandez Sousa Jose Antonio",
    "wof:placetype":"venue"
},
  "geometry": {"coordinates":[-7.3253297806,42.9910087585],"type":"Point"}
}