{
  "type": "Feature",
  "properties": {
    "iso:country":"ES",
    "sg:address":"Cra Viladamat L'escala, Km. 0017,0",
    "sg:city":"Viladamat",
    "sg:orig_category":"Albergues",
    "sg:phone":"+34 972 78 80 86",
    "sg:postcode":"17137",
    "sg:province":"Girona",
    "wof:name":"Armengou Casas Maria Asuncion",
    "wof:placetype":"venue"
},
  "geometry": {"coordinates":[3.0754845142,42.1323127747],"type":"Point"}
}