{
  "type": "Feature",
  "properties": {
    "iso:country":"ES",
    "sg:address":"Pl Bous (dels), 3",
    "sg:city":"Mataro",
    "sg:orig_category":"Centros De Educaci\u00d3n Especial",
    "sg:phone":"+34 937 90 47 48",
    "sg:postcode":"08301",
    "sg:province":"Barcelona",
    "wof:name":"Fundacio El Maresme",
    "wof:placetype":"venue"
},
  "geometry": {"coordinates":[2.4445281029,41.5420608521],"type":"Point"}
}