{
  "type": "Feature",
  "properties": {
    "iso:country":"ES",
    "sg:address":"Calle de Salvador, 25",
    "sg:city":"Aldea Rey",
    "sg:orig_category":"Formaci\u00d3n Continuada (variada)",
    "sg:phone":"+34 926 86 52 02",
    "sg:postcode":"13380",
    "sg:province":"Ciudad Real",
    "wof:name":"Romero Rodriguez Rafael",
    "wof:placetype":"venue"
},
  "geometry": {"coordinates":[-3.8398690224,38.737651825],"type":"Point"}
}