{
  "type": "Feature",
  "properties": {
    "addr:full":"Pase Carmelitas, 11 Salamanca Salamanca 37002",
    "addr:housenumber":"11",
    "addr:postcode":"37002",
    "addr:street":"Carmelitas",
    "iso:country":"ES",
    "sg:address":"Pase Carmelitas, 11",
    "sg:city":"Salamanca",
    "sg:orig_category":"Tintes (fabricaci\u00d3n, Al Por Mayor)",
    "sg:phone":"+34 923 21 85 75",
    "sg:postcode":"37002",
    "sg:province":"Salamanca",
    "wof:name":"Satinsa C.b",
    "wof:placetype":"venue"
},
  "geometry": {"coordinates":[-5.6645989418,40.9698295593],"type":"Point"}
}