{
  "type": "Feature",
  "properties": {
    "addr:full":"Carrer de Nou, 49 Benigembla Alicante 03794",
    "addr:housenumber":"49",
    "addr:postcode":"03794",
    "addr:street":"Carrer De Nou",
    "iso:country":"ES",
    "sg:address":"Carrer de Nou, 49",
    "sg:city":"Benigembla",
    "sg:orig_category":"Aceites Y Grasas Alimentarias (fabricaci\u00d3n, Al Por Mayor)",
    "sg:phone":"+34 965 58 11 41",
    "sg:postcode":"03794",
    "sg:province":"Alicante",
    "wof:name":"Cooperativa Agricola La Protectora",
    "wof:placetype":"venue"
},
  "geometry": {"coordinates":[-0.1089880019,38.7535476685],"type":"Point"}
}