{
  "type": "Feature",
  "properties": {
    "iso:country":"ES",
    "sg:address":"Calle de Pe\u00d1uela, 3",
    "sg:city":"Fuensanta Martos",
    "sg:orig_category":"Alimentaci\u00d3n General (al Por Menor)",
    "sg:phone":"+34 953 56 54 95",
    "sg:postcode":"23610",
    "sg:province":"Ja\u00e9n",
    "wof:name":"Bonilla Moreno Juan Carlos",
    "wof:placetype":"venue"
},
  "geometry": {"coordinates":[-3.9085440636,37.6465873718],"type":"Point"}
}