{
  "type": "Feature",
  "properties": {
    "addr:full":"Calle de Carpio (el), S/n Montoro C\u00f3rdoba 14600",
    "addr:housenumber":"s / n",
    "addr:postcode":"14600",
    "addr:street":"Calle De Carpio El;Co\u0301Rdoba",
    "iso:country":"ES",
    "sg:address":"Calle de Carpio (el), S/n",
    "sg:city":"Montoro",
    "sg:orig_category":"Tapiceros Y Tapiceros",
    "sg:phone":"+34 957 16 00 00",
    "sg:postcode":"14600",
    "sg:province":"C\u00f3rdoba",
    "wof:name":"Tapizados San Bartolome S.l.",
    "wof:placetype":"venue"
},
  "geometry": {"coordinates":[-4.377199173,38.0110054016],"type":"Point"}
}