{
  "type": "Feature",
  "properties": {
    "iso:country":"ES",
    "sg:address":"Plaz Espa\u00d1a, 4",
    "sg:city":"Melgar Fernamental",
    "sg:orig_category":"Laboratorios Y Trabajos De Fotograf\u00cda, V\u00cddeo Y Cine",
    "sg:phone":"+34 947 37 26 51",
    "sg:postcode":"09100",
    "sg:province":"Burgos",
    "wof:name":"Blanco Garcia Antonio Maria",
    "wof:placetype":"venue"
},
  "geometry": {"coordinates":[-4.2453022003,42.4037704468],"type":"Point"}
}