{
  "type": "Feature",
  "properties": {
    "iso:country":"ES",
    "sg:address":"Carrer de Pau Casals, 16",
    "sg:city":"S. Cugat Valles",
    "sg:orig_category":"Promotores Constructores",
    "sg:phone":"+34 935 97 05 05",
    "sg:postcode":"08172",
    "sg:province":"Barcelona",
    "wof:name":"Inmobiliaria Imasa S. A.",
    "wof:placetype":"venue"
},
  "geometry": {"coordinates":[2.0916390419,41.4708709717],"type":"Point"}
}