{
  "type": "Feature",
  "properties": {
    "addr:full":"Carrer de Monturiol, 40 Barcelona Barcelona 08018",
    "addr:housenumber":"40",
    "addr:postcode":"08018",
    "addr:street":"Carrer De Monturiol",
    "iso:country":"ES",
    "sg:address":"Carrer de Monturiol, 40",
    "sg:city":"Barcelona",
    "sg:orig_category":"Reposter\u00cdas",
    "sg:phone":"+34 932 66 09 91",
    "sg:postcode":"08018",
    "sg:province":"Barcelona",
    "wof:name":"Vime Fonte Manuela",
    "wof:placetype":"venue"
},
  "geometry": {"coordinates":[2.191380024,41.4108314514],"type":"Point"}
}