{
  "type": "Feature",
  "properties": {
    "iso:country":"ES",
    "sg:address":"Calle de Rodriguez Arias, 23",
    "sg:city":"Bilbao",
    "sg:orig_category":"Agencias Y Agentes Comerciales, Representantes",
    "sg:phone":"+34 944 44 38 84",
    "sg:postcode":"48011",
    "sg:province":"Vizcaya",
    "wof:name":"De Urrutia Gomez Jose Ramon",
    "wof:placetype":"venue"
},
  "geometry": {"coordinates":[-2.9363050461,43.2619781494],"type":"Point"}
}