{
  "type": "Feature",
  "properties": {
    "iso:country":"ES",
    "sg:address":"Calle de Doctor Fidel Fernandez, 2",
    "sg:city":"Granada",
    "sg:orig_category":"Electricidad (montaje, Ensamblaje De Componentes)",
    "sg:phone":"+34 958 29 58 09",
    "sg:postcode":"18012",
    "sg:province":"Granada",
    "wof:name":"Eusebio Leiva Antonio",
    "wof:placetype":"venue"
},
  "geometry": {"coordinates":[-3.6085870266,37.1905860901],"type":"Point"}
}