{
  "type": "Feature",
  "properties": {
    "iso:country":"ES",
    "sg:address":"Carr Francesc De Blanes, 26",
    "sg:city":"Llafranc",
    "sg:orig_category":"Albergues",
    "sg:phone":"+34 972 30 01 15",
    "sg:postcode":"17211",
    "sg:province":"Girona",
    "wof:name":"Tarrago Daussa Maria Rosa",
    "wof:placetype":"venue"
},
  "geometry": {"coordinates":[3.1918048859,41.8932762146],"type":"Point"}
}