{
  "type": "Feature",
  "properties": {
    "addr:full":"Calle de Arroyada, 74 Sonseca Toledo 45100",
    "addr:housenumber":"74",
    "addr:postcode":"45100",
    "addr:street":"Calle De Arroyada",
    "iso:country":"ES",
    "sg:address":"Calle de Arroyada, 74",
    "sg:city":"Sonseca",
    "sg:orig_category":"Librer\u00cdas",
    "sg:phone":"+34 925 38 09 06",
    "sg:postcode":"45100",
    "sg:province":"Toledo",
    "wof:name":"Sonsecava S.l.",
    "wof:placetype":"venue"
},
  "geometry": {"coordinates":[-3.9731535912,39.6777420044],"type":"Point"}
}