{
  "type": "Feature",
  "properties": {
    "iso:country":"ES",
    "sg:address":"Pl Bonanova, 5",
    "sg:city":"Barcelona",
    "sg:orig_category":"Arquitectos",
    "sg:phone":"+34 932 11 69 24",
    "sg:postcode":"08022",
    "sg:province":"Barcelona",
    "wof:name":"Casanelles Massaguer Ramon",
    "wof:placetype":"venue"
},
  "geometry": {"coordinates":[2.1341600418,41.4067153931],"type":"Point"}
}