{
  "type": "Feature",
  "properties": {
    "iso:country":"ES",
    "sg:address":"Rua Luis Seoane, 29",
    "sg:city":"Grove",
    "sg:orig_category":"Fabricaci\u00d3n, Reparaci\u00d3n Y Mantenimiento De Construcciones Navales Y Fluviales",
    "sg:phone":"+34 986 73 03 57",
    "sg:postcode":"36980",
    "sg:province":"Pontevedra",
    "wof:name":"Lores Prol Adolfo Xose",
    "wof:placetype":"venue"
},
  "geometry": {"coordinates":[-8.8631429672,42.4939537048],"type":"Point"}
}