{
  "type": "Feature",
  "properties": {
    "addr:full":"Av Can Jofresa, 9 Terrassa Barcelona 08223",
    "addr:housenumber":"9",
    "addr:postcode":"08223",
    "addr:street":"Av Can Jofresa",
    "iso:country":"ES",
    "sg:address":"Av Can Jofresa, 9",
    "sg:city":"Terrassa",
    "sg:orig_category":"Ense\u00d1anza Secundaria: Colegios Y Escuelas Privadas",
    "sg:phone":"+34 937 85 07 25",
    "sg:postcode":"08223",
    "sg:province":"Barcelona",
    "wof:name":"Institut De Batxillerat Can Jofresa",
    "wof:placetype":"venue"
},
  "geometry": {"coordinates":[2.0228281021,41.5499382019],"type":"Point"}
}