{
  "type": "Feature",
  "properties": {
    "addr:full":"Ctra Madrid, Km. 0170,8 Pedraja Portillo Valladolid 47196",
    "addr:postcode":"47196",
    "addr:street":"Ctra Madrid Km. 0170,8",
    "iso:country":"ES",
    "sg:address":"Ctra Madrid, Km. 0170,8",
    "sg:city":"Pedraja Portillo",
    "sg:orig_category":"Negocio De Materiales De Construcci\u00d3n",
    "sg:phone":"+34 983 55 30 52",
    "sg:postcode":"47196",
    "sg:province":"Valladolid",
    "sg:website":"www.viguetasencinas.com",
    "wof:name":"Viguetas Encinas S.l.",
    "wof:placetype":"venue"
},
  "geometry": {"coordinates":[-4.6456189156,41.4737281799],"type":"Point"}
}