{
  "type": "Feature",
  "properties": {
    "iso:country":"ES",
    "sg:address":"Avda Borbolla (la), 13",
    "sg:city":"Sevilla",
    "sg:orig_category":"Abogados",
    "sg:phone":"+34 954 42 03 04",
    "sg:postcode":"41004",
    "sg:province":"Sevilla",
    "wof:name":"Baena Bocanegra Francisco Maria",
    "wof:placetype":"venue"
},
  "geometry": {"coordinates":[-5.9837026596,37.3781776428],"type":"Point"}
}