{
  "type": "Feature",
  "properties": {
    "iso:country":"ES",
    "sg:address":"Plaz Zarzuela, S/n",
    "sg:city":"Ecija",
    "sg:orig_category":"Alimentaci\u00d3n General (al Por Menor)",
    "sg:phone":"+34 955 90 22 79",
    "sg:postcode":"41400",
    "sg:province":"Sevilla",
    "wof:name":"Linamar S.c.",
    "wof:placetype":"venue"
},
  "geometry": {"coordinates":[-5.0782690048,37.5395584106],"type":"Point"}
}