{
  "type": "Feature",
  "properties": {
    "iso:country":"ES",
    "sg:address":"Calle de Recogidas, 2",
    "sg:city":"Granada",
    "sg:classifiers":[
        {
            "category":"Cinema",
            "subcategory":"Movie Theater",
            "type":"Entertainment"
        }
    ],
    "sg:phone":"+34 958 25 20 56",
    "sg:postcode":"18002",
    "sg:province":"Granada",
    "sg:tags":[
        "salas",
        "de",
        "cine"
    ],
    "wof:name":"T.i.c.e. S.a.",
    "wof:placetype":"venue"
},
  "geometry": {"coordinates":[-3.6005990505,37.1731491089],"type":"Point"}
}