{
  "type": "Feature",
  "properties": {
    "iso:country":"ES",
    "sg:address":"Calle de Baztan, 4",
    "sg:city":"Donostia-san Sebastian",
    "sg:orig_category":"Sociedades, Compa\u00d1\u00cdas Aseguradoras",
    "sg:phone":"+34 943 29 14 12",
    "sg:postcode":"20012",
    "sg:province":"Guip\u00f9zcoa",
    "wof:name":"Garcia De Eulate Ercille Luis Maria",
    "wof:placetype":"venue"
},
  "geometry": {"coordinates":[-1.9690506458,43.3182067871],"type":"Point"}
}