{
  "type": "Feature",
  "properties": {
    "iso:country":"ES",
    "sg:address":"Av Carles Buigas (de), 36",
    "sg:city":"Salou",
    "sg:orig_category":"Alimentaci\u00d3n General (al Por Menor)",
    "sg:phone":"+34 977 38 16 54",
    "sg:postcode":"43840",
    "sg:province":"Tarragona",
    "wof:name":"Ballabriga Garcia Josefina",
    "wof:placetype":"venue"
},
  "geometry": {"coordinates":[1.1489239931,41.0719184875],"type":"Point"}
}