{
  "type": "Feature",
  "properties": {
    "addr:full":"Carr Carrerada, 3 Borges Blanques Lleida 25400",
    "addr:housenumber":"3",
    "addr:postcode":"25400",
    "addr:street":"Carr Carrerada",
    "iso:country":"ES",
    "sg:address":"Carr Carrerada, 3",
    "sg:city":"Borges Blanques",
    "sg:orig_category":"Material Y Herramientas Agr\u00cdcolas",
    "sg:phone":"+34 973 14 35 41",
    "sg:postcode":"25400",
    "sg:province":"Lleida",
    "wof:name":"Gine Safont Andreu",
    "wof:placetype":"venue"
},
  "geometry": {"coordinates":[0.8739199042,41.5202445984],"type":"Point"}
}