{
  "type": "Feature",
  "properties": {
    "iso:country":"ES",
    "sg:address":"Ctra Matadepera, 133",
    "sg:city":"Terrassa",
    "sg:orig_category":"Frutas, Legumbres Frescas Y Tempranas (al Por Menor)",
    "sg:phone":"+34 937 35 74 18",
    "sg:postcode":"08225",
    "sg:province":"Barcelona",
    "wof:name":"Sanchez Martinez S.c.p.",
    "wof:placetype":"venue"
},
  "geometry": {"coordinates":[2.0175731182,41.5735435486],"type":"Point"}
}