{
  "type": "Feature",
  "properties": {
    "iso:country":"ES",
    "sg:address":"El Rio, 3",
    "sg:city":"Santillana",
    "sg:orig_category":"Alimentaci\u00d3n General (al Por Menor)",
    "sg:phone":"+34 942 81 82 80",
    "sg:postcode":"39330",
    "sg:province":"Cantabria",
    "wof:name":"Ansorena Herrero Eduardo",
    "wof:placetype":"venue"
},
  "geometry": {"coordinates":[-4.1066689491,43.3912582397],"type":"Point"}
}