{
  "type": "Feature",
  "properties": {
    "iso:country":"ES",
    "sg:address":"Calle de Virgen (la), 48",
    "sg:city":"San Bartolome Pinares",
    "sg:orig_category":"Supermercados Y Hipermercados",
    "sg:phone":"+34 920 27 03 69",
    "sg:postcode":"05267",
    "sg:province":"\u00c1vila",
    "wof:name":"Alimentacion Fausto Y Alejandro S.l.",
    "wof:placetype":"venue"
},
  "geometry": {"coordinates":[-4.5373754501,40.5431251526],"type":"Point"}
}