{
  "type": "Feature",
  "properties": {
    "iso:country":"ES",
    "sg:address":"Calle de Ascao, 58",
    "sg:city":"Madrid",
    "sg:orig_category":"Comerciantes Al Por Mayor De Vinos, Licores Y Alcoholes",
    "sg:phone":"+34 913 67 07 28",
    "sg:postcode":"28017",
    "sg:province":"Madrid",
    "wof:name":"Moreno Rodriguez-plaza Alipio Luis",
    "wof:placetype":"venue"
},
  "geometry": {"coordinates":[-3.6381142139,40.4313621521],"type":"Point"}
}