{
  "type": "Feature",
  "properties": {
    "iso:country":"ES",
    "sg:address":"Calle de Castelar, 17",
    "sg:city":"Madrid",
    "sg:orig_category":"Arquitectos",
    "sg:phone":"+34 913 55 74 95",
    "sg:postcode":"28028",
    "sg:province":"Madrid",
    "wof:name":"Pajares Ayuela Paloma",
    "wof:placetype":"venue"
},
  "geometry": {"coordinates":[-3.6662278175,40.4306335449],"type":"Point"}
}