{
  "type": "Feature",
  "properties": {
    "addr:full":"Calle de Federico Garcia Lorca, 15 Velez Benaudalla Granada 18670",
    "addr:housenumber":"15",
    "addr:postcode":"18670",
    "addr:street":"Calle De Federico Garcia Lorca;Benaudalla",
    "iso:country":"ES",
    "sg:address":"Calle de Federico Garcia Lorca, 15",
    "sg:city":"Velez Benaudalla",
    "sg:orig_category":"Panader\u00cdas, Panader\u00cdas",
    "sg:phone":"+34 958 65 84 48",
    "sg:postcode":"18670",
    "sg:province":"Granada",
    "wof:name":"Rodriguez Esteban Laura",
    "wof:placetype":"venue"
},
  "geometry": {"coordinates":[-3.515650034,36.8316078186],"type":"Point"}
}