{
  "type": "Feature",
  "properties": {
    "iso:country":"ES",
    "sg:address":"Avda I(p Campollano), 55",
    "sg:city":"Albacete",
    "sg:orig_category":"Cristaler\u00cdas",
    "sg:phone":"+34 967 24 02 11",
    "sg:postcode":"02006",
    "sg:province":"Albacete",
    "sg:website":"www.corbalan.com",
    "wof:name":"Biselados Albacete S. L.",
    "wof:placetype":"venue"
},
  "geometry": {"coordinates":[-1.8999890089,38.9776191711],"type":"Point"}
}