{
  "type": "Feature",
  "properties": {
    "addr:full":"Calle de Valdesangil, 55 Madrid Madrid 28039",
    "addr:housenumber":"55",
    "addr:postcode":"madrid;28039",
    "addr:street":"Calle De Valdesangil",
    "iso:country":"ES",
    "sg:address":"Calle de Valdesangil, 55",
    "sg:city":"Madrid",
    "sg:orig_category":"Material Did\u00c1ctico",
    "sg:phone":"+34 913 16 10 04",
    "sg:postcode":"28039",
    "sg:province":"Madrid",
    "wof:name":"Fermosel Sanchez Alberto",
    "wof:placetype":"venue"
},
  "geometry": {"coordinates":[-3.7157390118,40.4696311951],"type":"Point"}
}