{
  "type": "Feature",
  "properties": {
    "iso:country":"ES",
    "sg:address":"Calle de Federico Garcia Lorca, S/n",
    "sg:city":"Alcala Henares",
    "sg:orig_category":"Bancos",
    "sg:phone":"+34 918 77 04 57",
    "sg:postcode":"28806",
    "sg:province":"Madrid",
    "wof:name":"Auna Telecomunicaciones S.a.u.",
    "wof:placetype":"venue"
},
  "geometry": {"coordinates":[-3.3716826439,40.5039634705],"type":"Point"}
}