{
  "type": "Feature",
  "properties": {
    "addr:full":"Calle de Teide, 7 Montijo Badajoz 06480",
    "addr:housenumber":"7",
    "addr:postcode":"06480",
    "addr:street":"Calle De Teide",
    "iso:country":"ES",
    "sg:address":"Calle de Teide, 7",
    "sg:city":"Montijo",
    "sg:orig_category":"Cajas De Ahorro",
    "sg:phone":"+34 924 45 74 56",
    "sg:postcode":"06480",
    "sg:province":"Badajoz",
    "wof:name":"Caixa D'estalvis I Pensions De Barcelona",
    "wof:placetype":"venue"
},
  "geometry": {"coordinates":[-6.6169462204,38.9090652466],"type":"Point"}
}