{
  "type": "Feature",
  "properties": {
    "iso:country":"ES",
    "sg:address":"Calle de Francos, 32",
    "sg:city":"Jerez De La Frontera",
    "sg:orig_category":"Maquinaria Para Industrias Diversas",
    "sg:phone":"+34 956 33 37 61",
    "sg:postcode":"11403",
    "sg:province":"C\u00e1diz",
    "wof:name":"Verdugo Macias Antonio",
    "wof:placetype":"venue"
},
  "geometry": {"coordinates":[-6.1404018402,36.6858940125],"type":"Point"}
}