{
  "type": "Feature",
  "properties": {
    "addr:full":"Calle de Arroz, 19 Dos Hermanas Sevilla 41700",
    "addr:housenumber":"19",
    "addr:postcode":"41700",
    "addr:street":"Calle De Arroz",
    "iso:country":"ES",
    "sg:address":"Calle de Arroz, 19",
    "sg:city":"Dos Hermanas",
    "sg:orig_category":"Empresas De Pintura Y Revestimientos",
    "sg:phone":"+34 954 72 32 58",
    "sg:postcode":"41700",
    "sg:province":"Sevilla",
    "wof:name":"Alcantara Gomez Joaquin",
    "wof:placetype":"venue"
},
  "geometry": {"coordinates":[-5.9230542183,37.2764282227],"type":"Point"}
}