{
  "type": "Feature",
  "properties": {
    "iso:country":"ES",
    "sg:address":"Carr Humbert Torres, 14",
    "sg:city":"Lleida",
    "sg:orig_category":"Librer\u00cdas",
    "sg:phone":"+34 973 22 32 24",
    "sg:postcode":"25008",
    "sg:province":"Lleida",
    "wof:name":"Mu\u00f1oz Ruiz Carmen",
    "wof:placetype":"venue"
},
  "geometry": {"coordinates":[0.6211190224,41.6221618652],"type":"Point"}
}