{
  "type": "Feature",
  "properties": {
    "addr:full":"Calle de Poeta Artola, 13 Valencia Valencia 46021",
    "addr:housenumber":"13",
    "addr:postcode":"46021",
    "addr:street":"Calle De Poeta Artola",
    "iso:country":"ES",
    "sg:address":"Calle de Poeta Artola, 13",
    "sg:city":"Valencia",
    "sg:orig_category":"Ingenier\u00cda, Centros De Estudios (diversos)",
    "sg:phone":"+34 963 69 71 28",
    "sg:postcode":"46021",
    "sg:province":"Valencia",
    "wof:name":"Bertomeu Proyectos Tecnicos Industriales S.l.",
    "wof:placetype":"venue"
},
  "geometry": {"coordinates":[-0.3488489985,39.4759368896],"type":"Point"}
}