{
  "type": "Feature",
  "properties": {
    "iso:country":"ES",
    "sg:address":"Calle de Coso Bajo, 48",
    "sg:city":"Huesca",
    "sg:orig_category":"Carnicer\u00cdas, Carnicer\u00cdas",
    "sg:phone":"+34 974 22 41 41",
    "sg:postcode":"22001",
    "sg:province":"Huesca",
    "wof:name":"Andres Ferrer E Hijos S. A.",
    "wof:placetype":"venue"
},
  "geometry": {"coordinates":[-0.4057607949,42.1377563477],"type":"Point"}
}