{
  "type": "Feature",
  "properties": {
    "addr:full":"Avda Juan Carlos I, 14 Espinardo Murcia 30008",
    "addr:housenumber":"14",
    "addr:postcode":"30008",
    "addr:street":"Avda Juan Carlos I",
    "iso:country":"ES",
    "sg:address":"Avda Juan Carlos I, 14",
    "sg:city":"Espinardo",
    "sg:orig_category":"Agencias Y Agentes Comerciales, Representantes",
    "sg:phone":"+34 968 24 28 96",
    "sg:postcode":"30008",
    "sg:province":"Murcia",
    "wof:name":"Pacheco Bernabeu Agustin",
    "wof:placetype":"venue"
},
  "geometry": {"coordinates":[-1.133259058,37.9954223633],"type":"Point"}
}