{
  "type": "Feature",
  "properties": {
    "iso:country":"ES",
    "sg:address":"Cami Peiro, S/n",
    "sg:city":"Batea",
    "sg:orig_category":"Poller\u00cda Y Caza (al Por Menor)",
    "sg:phone":"+34 977 43 05 86",
    "sg:postcode":"43786",
    "sg:province":"Tarragona",
    "wof:name":"Bes Peig C.b",
    "wof:placetype":"venue"
},
  "geometry": {"coordinates":[0.3080770075,41.1008148193],"type":"Point"}
}