{
  "type": "Feature",
  "properties": {
    "addr:full":"Plaz Virgen, 2 Pozo Ca\u00e7ada Albacete 02510",
    "addr:housenumber":"2",
    "addr:postcode":"02510",
    "addr:street":"Plaz Virgen",
    "iso:country":"ES",
    "sg:address":"Plaz Virgen, 2",
    "sg:city":"Pozo Ca\u00e7ada",
    "sg:orig_category":"Iglesia Cat\u00d3lica",
    "sg:phone":"+34 967 25 00 02",
    "sg:postcode":"02510",
    "sg:province":"Albacete",
    "wof:name":"Obispado De Albacete",
    "wof:placetype":"venue"
},
  "geometry": {"coordinates":[-1.7307540178,38.8037147522],"type":"Point"}
}