{
  "type": "Feature",
  "properties": {
    "iso:country":"ES",
    "sg:address":"Pl Olivar, 4",
    "sg:city":"Palma",
    "sg:orig_category":"Abogados",
    "sg:phone":"+34 971 22 76 14",
    "sg:postcode":"07002",
    "sg:province":"Islas Baleares",
    "wof:name":"Moll Vidal Juan Carlos",
    "wof:placetype":"venue"
},
  "geometry": {"coordinates":[2.6529490948,39.5736541748],"type":"Point"}
}