{
  "type": "Feature",
  "properties": {
    "iso:country":"ES",
    "sg:address":"Carrer de Consell De Cent, 96",
    "sg:city":"Barcelona",
    "sg:orig_category":"Empresarios",
    "sg:phone":"+34 934 24 43 92",
    "sg:postcode":"08015",
    "sg:province":"Barcelona",
    "wof:name":"Gebo S.c.p.",
    "wof:placetype":"venue"
},
  "geometry": {"coordinates":[2.1513979435,41.3801383972],"type":"Point"}
}