{
  "type": "Feature",
  "properties": {
    "addr:full":"Avda Boliches De Los, 12 Fuengirola M\u00e1laga 29640",
    "addr:postcode":"29640",
    "addr:street":"Avda Boliches De Los;Ma\u0301Laga",
    "iso:country":"ES",
    "sg:address":"Avda Boliches De Los, 12",
    "sg:city":"Fuengirola",
    "sg:orig_category":"Ropa Para Se\u00d1oras (al Por Menor)",
    "sg:phone":"+34 952 47 09 46",
    "sg:postcode":"29640",
    "sg:province":"M\u00e1laga",
    "wof:name":"Arte Inversion 2000 S.l.",
    "wof:placetype":"venue"
},
  "geometry": {"coordinates":[-4.6160502434,36.5504493713],"type":"Point"}
}