{
  "type": "Feature",
  "properties": {
    "iso:country":"ES",
    "sg:address":"Calle de Verona, 13",
    "sg:city":"Torre-pacheco",
    "sg:orig_category":"Ense\u00d1anza: Peluquer\u00cda Est\u00c9tica",
    "sg:phone":"+34 968 58 53 99",
    "sg:postcode":"30700",
    "sg:province":"Murcia",
    "wof:name":"Fernandez Mero\u00f1o Maria",
    "wof:placetype":"venue"
},
  "geometry": {"coordinates":[-1.1302490234,37.9829597473],"type":"Point"}
}