{
  "type": "Feature",
  "properties": {
    "addr:full":"Carrer de Esglayers, 7 Olot Girona 17800",
    "addr:housenumber":"7",
    "addr:postcode":"17800",
    "addr:street":"Carrer De Esglayers",
    "iso:country":"ES",
    "sg:address":"Carrer de Esglayers, 7",
    "sg:city":"Olot",
    "sg:orig_category":"M\u00c9dicos: Estomatolog\u00cda",
    "sg:phone":"+34 972 26 95 06",
    "sg:postcode":"17800",
    "sg:province":"Girona",
    "wof:name":"Balcells Prat Josep",
    "wof:placetype":"venue"
},
  "geometry": {"coordinates":[2.4891219139,42.1832580566],"type":"Point"}
}