{
  "type": "Feature",
  "properties": {
    "iso:country":"ES",
    "sg:address":"Calle de Virgen Del Rosario, S/n",
    "sg:city":"Alacant",
    "sg:orig_category":"Mec\u00c1nico Del Autom\u00d3vil",
    "sg:phone":"+34 965 18 66 95",
    "sg:postcode":"03009",
    "sg:province":"Alicante",
    "wof:name":"Race Cars Alicante S.l.",
    "wof:placetype":"venue"
},
  "geometry": {"coordinates":[-0.5001620054,38.365852356],"type":"Point"}
}