{
  "type": "Feature",
  "properties": {
    "addr:full":"Calle de Espinar, 31 Madrid Madrid 28025",
    "addr:housenumber":"31",
    "addr:postcode":"madrid;28025",
    "addr:street":"Calle De Espinar",
    "iso:country":"ES",
    "sg:address":"Calle de Espinar, 31",
    "sg:city":"Madrid",
    "sg:orig_category":"Comercio, Reparaci\u00d3n De Bicicletas, De Motocicletas, De Accesorios",
    "sg:phone":"+34 915 25 01 94",
    "sg:postcode":"28025",
    "sg:province":"Madrid",
    "wof:name":"Calvo Herrera Angel",
    "wof:placetype":"venue"
},
  "geometry": {"coordinates":[-3.7433860302,40.3851394653],"type":"Point"}
}