{
  "type": "Feature",
  "properties": {
    "iso:country":"ES",
    "sg:address":"Ctra. Capdepera, Km. 0003,0",
    "sg:city":"Son Servera",
    "sg:classifiers":[
        {
            "category":"Sports & Exercise",
            "subcategory":"Golf",
            "type":"Entertainment"
        }
    ],
    "sg:phone":"+34 971 56 75 84",
    "sg:postcode":"07550",
    "sg:province":"Islas Baleares",
    "sg:tags":[
        "y",
        "de",
        "campos",
        "clases"
    ],
    "wof:name":"Sociedad Reial Pula Golf S.l.",
    "wof:placetype":"venue"
},
  "geometry": {"coordinates":[3.3548560143,39.6253509521],"type":"Point"}
}