{
  "type": "Feature",
  "properties": {
    "addr:full":"Calle de Goleta, 3 Carboneras Almer\u00eda 04140",
    "addr:housenumber":"3",
    "addr:postcode":"04140",
    "addr:street":"Calle De Goleta",
    "iso:country":"ES",
    "sg:address":"Calle de Goleta, 3",
    "sg:city":"Carboneras",
    "sg:orig_category":"Productos Fitosanitarios (negocio, Aplicaci\u00d3n)",
    "sg:phone":"+34 950 13 07 52",
    "sg:postcode":"04140",
    "sg:province":"Almer\u00eda",
    "wof:name":"Agricultura Moderna S.a.",
    "wof:placetype":"venue"
},
  "geometry": {"coordinates":[-1.8928662539,37.0015869141],"type":"Point"}
}