{
  "type": "Feature",
  "properties": {
    "iso:country":"ES",
    "sg:address":"Calle de Olmedo, 44",
    "sg:city":"Valladolid",
    "sg:classifiers":[
        {
            "category":"Home & Garden",
            "subcategory":"Household Appliances",
            "type":"Retail Goods"
        }
    ],
    "sg:phone":"+34 983 22 08 31",
    "sg:postcode":"47013",
    "sg:province":"Valladolid",
    "sg:tags":[
        "bodega",
        "de",
        "vino",
        "acondicionamiento"
    ],
    "wof:name":"Vinos Artesanales De Calidad S.l.",
    "wof:placetype":"venue"
},
  "geometry": {"coordinates":[-4.7179570198,41.6380233765],"type":"Point"}
}