{
  "type": "Feature",
  "properties": {
    "addr:full":"Ctra San Javier, Km. 0019,0 Balsicas Murcia 30591",
    "addr:postcode":"30591",
    "addr:street":"Ctra San Javier Km. 0019,0",
    "iso:country":"ES",
    "sg:address":"Ctra San Javier, Km. 0019,0",
    "sg:city":"Balsicas",
    "sg:orig_category":"Puertas Y Portales",
    "sg:phone":"+34 968 58 08 04",
    "sg:postcode":"30591",
    "sg:province":"Murcia",
    "wof:name":"Puertas Moratalla S.l.",
    "wof:placetype":"venue"
},
  "geometry": {"coordinates":[-0.9609609842,37.8191490173],"type":"Point"}
}