{
  "type": "Feature",
  "properties": {
    "addr:full":"C/ Escola (l'), 4 Alcoi Alicante 03801",
    "addr:housenumber":"4",
    "addr:postcode":"03801",
    "addr:street":"C / Escola L '",
    "iso:country":"ES",
    "sg:address":"C/ Escola (l'), 4",
    "sg:city":"Alcoi",
    "sg:orig_category":"Mercer\u00cda, Lencer\u00cda (al Por Menor)",
    "sg:phone":"+34 965 54 49 41",
    "sg:postcode":"03801",
    "sg:province":"Alicante",
    "wof:name":"Penades Pascual Maria De Los Angeles",
    "wof:placetype":"venue"
},
  "geometry": {"coordinates":[-0.473841995,38.6985359192],"type":"Point"}
}