{
  "type": "Feature",
  "properties": {
    "iso:country":"ES",
    "sg:address":"Calle de Aire (el), S/n",
    "sg:city":"Albentosa",
    "sg:orig_category":"Carnicer\u00cdas, Carnicer\u00cdas",
    "sg:phone":"+34 978 78 58 68",
    "sg:postcode":"44477",
    "sg:province":"Teruel",
    "wof:name":"Gargallo Perez Juan",
    "wof:placetype":"venue"
},
  "geometry": {"coordinates":[-0.7696387172,40.1031837463],"type":"Point"}
}