{
  "type": "Feature",
  "properties": {
    "addr:full":"C/ Mar, 42 Altet Alicante 03195",
    "addr:housenumber":"42",
    "addr:postcode":"03195",
    "addr:street":"C / Mar",
    "iso:country":"ES",
    "sg:address":"C/ Mar, 42",
    "sg:city":"Altet",
    "sg:orig_category":"Armarios Y Cuadros El\u00c9ctricos",
    "sg:phone":"+34 965 68 71 37",
    "sg:postcode":"03195",
    "sg:province":"Alicante",
    "wof:name":"Baeza Ripoll Antonio",
    "wof:placetype":"venue"
},
  "geometry": {"coordinates":[-0.5359933972,38.2726097107],"type":"Point"}
}