{
  "type": "Feature",
  "properties": {
    "addr:full":"Ctra Barcelona, 43 Viladecans Barcelona 08840",
    "addr:housenumber":"43",
    "addr:postcode":"08840",
    "addr:street":"Ctra Barcelona",
    "iso:country":"ES",
    "sg:address":"Ctra Barcelona, 43",
    "sg:city":"Viladecans",
    "sg:orig_category":"Agencias De Trabajo Temporal",
    "sg:phone":"+34 936 47 40 90",
    "sg:postcode":"08840",
    "sg:province":"Barcelona",
    "wof:name":"Barna Work S.l.",
    "wof:placetype":"venue"
},
  "geometry": {"coordinates":[2.0246379375,41.3192901611],"type":"Point"}
}