{
  "type": "Feature",
  "properties": {
    "iso:country":"ES",
    "sg:address":"Avda Cervera, 2",
    "sg:city":"Aguilar Campoo",
    "sg:orig_category":"Material Y Suministros Para Veterinarios",
    "sg:phone":"+34 979 12 51 04",
    "sg:postcode":"34800",
    "sg:province":"Palencia",
    "wof:name":"Comercial Norte Tecnipec S.l.",
    "wof:placetype":"venue"
},
  "geometry": {"coordinates":[-4.267621994,42.7954292297],"type":"Point"}
}