{
  "type": "Feature",
  "properties": {
    "addr:full":"Calle de Canalejas, 13 Marmolejo Ja\u00e9n 23770",
    "addr:housenumber":"13",
    "addr:postcode":"23770",
    "addr:street":"Calle De Canalejas;Jae\u0301N",
    "iso:country":"ES",
    "sg:address":"Calle de Canalejas, 13",
    "sg:city":"Marmolejo",
    "sg:orig_category":"Bebidas",
    "sg:phone":"+34 953 54 05 09",
    "sg:postcode":"23770",
    "sg:province":"Ja\u00e9n",
    "wof:name":"Rivillas Blanco Manuel",
    "wof:placetype":"venue"
},
  "geometry": {"coordinates":[-4.1724553108,38.0460319519],"type":"Point"}
}