{
  "type": "Feature",
  "properties": {
    "iso:country":"ES",
    "sg:address":"Carrer de Varsovia, 111",
    "sg:city":"Barcelona",
    "sg:orig_category":"Arreglo, Reparaci\u00d3n, Piezas Sueltas De Televisi\u00d3n, V\u00cddeo, Hi",
    "sg:phone":"+34 934 56 23 17",
    "sg:postcode":"08041",
    "sg:province":"Barcelona",
    "wof:name":"Cabanes Sarmiento Carles",
    "wof:placetype":"venue"
},
  "geometry": {"coordinates":[2.1733710766,41.4191474915],"type":"Point"}
}