{
  "type": "Feature",
  "properties": {
    "addr:full":"Calle de Angel Embil, 8 Pola De Siero Asturias 33510",
    "addr:housenumber":"8",
    "addr:postcode":"33510",
    "addr:street":"Calle De Angel Embil",
    "iso:country":"ES",
    "sg:address":"Calle de Angel Embil, 8",
    "sg:city":"Pola De Siero",
    "sg:orig_category":"Asociaciones Y Clubs Deportivos",
    "sg:phone":"+34 985 72 61 71",
    "sg:postcode":"33510",
    "sg:province":"Asturias",
    "wof:name":"Lopez Garcia Enrique Francisco",
    "wof:placetype":"venue"
},
  "geometry": {"coordinates":[-5.6552977562,43.3935203552],"type":"Point"}
}