{
  "type": "Feature",
  "properties": {
    "iso:country":"ES",
    "sg:address":"Avgd Paisos Catalans, S/n",
    "sg:city":"Igualada",
    "sg:orig_category":"Ropa Para Se\u00d1oras (al Por Menor)",
    "sg:phone":"+34 938 04 39 00",
    "sg:postcode":"08700",
    "sg:province":"Barcelona",
    "wof:name":"Guitart Castellvi Jose",
    "wof:placetype":"venue"
},
  "geometry": {"coordinates":[1.619500041,41.5911750793],"type":"Point"}
}