{
  "type": "Feature",
  "properties": {
    "iso:country":"ES",
    "sg:address":"Plaz Marques De Muros, 15",
    "sg:city":"Muros",
    "sg:orig_category":"Inmobiliaria (agencias)",
    "sg:phone":"+34 985 58 34 22",
    "sg:postcode":"33138",
    "sg:province":"Asturias",
    "wof:name":"Consejeros De Gestion Aviles 2000 S.l.",
    "wof:placetype":"venue"
},
  "geometry": {"coordinates":[-6.1034479141,43.5420303345],"type":"Point"}
}