{
  "type": "Feature",
  "properties": {
    "addr:full":"Av Iv (p Campollano), 2 Albacete Albacete 02006",
    "addr:housenumber":"2",
    "addr:postcode":"02006",
    "addr:street":"Av Iv P Campollano",
    "iso:country":"ES",
    "sg:address":"Av Iv (p Campollano), 2",
    "sg:city":"Albacete",
    "sg:orig_category":"M\u00c1quinas Y Material Para La Industria De La Alimentaci\u00d3n",
    "sg:phone":"+34 967 24 80 91",
    "sg:postcode":"02006",
    "sg:province":"Albacete",
    "wof:name":"Jose Bernad S. L.",
    "wof:placetype":"venue"
},
  "geometry": {"coordinates":[-1.9490209818,39.013168335],"type":"Point"}
}