{
  "type": "Feature",
  "properties": {
    "addr:full":"Calle de Malecon, 48 Mazarron Murcia 30870",
    "addr:housenumber":"48",
    "addr:postcode":"30870",
    "addr:street":"Calle De Malecon",
    "iso:country":"ES",
    "sg:address":"Calle de Malecon, 48",
    "sg:city":"Mazarron",
    "sg:orig_category":"Mec\u00c1nico Del Autom\u00d3vil",
    "sg:phone":"+34 968 59 10 15",
    "sg:postcode":"30870",
    "sg:province":"Murcia",
    "wof:name":"Carrillo Martinez Francisco",
    "wof:placetype":"venue"
},
  "geometry": {"coordinates":[-1.3128490448,37.5974998474],"type":"Point"}
}