{
  "type": "Feature",
  "properties": {
    "iso:country":"ES",
    "sg:address":"Calle de Ricardo Salas Redondo, 26",
    "sg:city":"Pozo-estrecho",
    "sg:orig_category":"Farmacias",
    "sg:phone":"+34 968 55 62 62",
    "sg:postcode":"30594",
    "sg:province":"Murcia",
    "wof:name":"Ballester Mero\u00f1o Alfonso",
    "wof:placetype":"venue"
},
  "geometry": {"coordinates":[-0.9950090051,37.7132110596],"type":"Point"}
}