{
  "type": "Feature",
  "properties": {
    "addr:full":"Pl Portalada (de La), 5 Altafulla Tarragona 43893",
    "addr:housenumber":"5",
    "addr:postcode":"43893",
    "addr:street":"Pl Portalada De La",
    "iso:country":"ES",
    "sg:address":"Pl Portalada (de La), 5",
    "sg:city":"Altafulla",
    "sg:orig_category":"Delegados, Agentes De Tr\u00c1nsito, Auxiliares De Transporte Internacional",
    "sg:phone":"+34 977 65 00 46",
    "sg:postcode":"43893",
    "sg:province":"Tarragona",
    "wof:name":"Gonzalez Mata Francisco",
    "wof:placetype":"venue"
},
  "geometry": {"coordinates":[1.3690550327,41.1410560608],"type":"Point"}
}