{
  "type": "Feature",
  "properties": {
    "iso:country":"ES",
    "sg:address":"Carr Canonge Baranera, 25",
    "sg:city":"Badalona",
    "sg:orig_category":"Ropa Para Ni\u00d1os (al Por Menor)",
    "sg:phone":"+34 934 64 45 33",
    "sg:postcode":"08911",
    "sg:province":"Barcelona",
    "wof:name":"Paun  Liliana Elena",
    "wof:placetype":"venue"
},
  "geometry": {"coordinates":[2.249202013,41.4490890503],"type":"Point"}
}