{
  "type": "Feature",
  "properties": {
    "addr:full":"Carrer de Jaume Balmes, 58 S. Boi Llobregat Barcelona 08830",
    "addr:housenumber":"58",
    "addr:postcode":"08830",
    "addr:street":"Carrer De Jaume Balmes",
    "iso:country":"ES",
    "sg:address":"Carrer de Jaume Balmes, 58",
    "sg:city":"S. Boi Llobregat",
    "sg:orig_category":"Aguas (distribuci\u00d3n, Servicios)",
    "sg:phone":"+34 936 30 73 16",
    "sg:postcode":"08830",
    "sg:province":"Barcelona",
    "wof:name":"Gjjetwater S.l.l.",
    "wof:placetype":"venue"
},
  "geometry": {"coordinates":[2.0441539288,41.3363685608],"type":"Point"}
}