{
  "type": "Feature",
  "properties": {
    "addr:full":"Avda Jaen, S/n Peligros Granada 18210",
    "addr:housenumber":"s / n",
    "addr:postcode":"18210",
    "addr:street":"Avda Jaen",
    "iso:country":"ES",
    "sg:address":"Avda Jaen, S/n",
    "sg:city":"Peligros",
    "sg:orig_category":"Molduras, Junquillos, Listones Y Molduras Perforadas",
    "sg:phone":"+34 958 40 28 13",
    "sg:postcode":"18210",
    "sg:province":"Granada",
    "wof:name":"Perez Rodriguez Jose Maria",
    "wof:placetype":"venue"
},
  "geometry": {"coordinates":[-3.6317739487,37.2302093506],"type":"Point"}
}