{
  "type": "Feature",
  "properties": {
    "addr:full":"Carrer de Gabriel Fuster, 16 Palma Islas Baleares 07004",
    "addr:housenumber":"16",
    "addr:postcode":"07004",
    "addr:street":"Carrer De Gabriel Fuster",
    "iso:country":"ES",
    "sg:address":"Carrer de Gabriel Fuster, 16",
    "sg:city":"Palma",
    "sg:orig_category":"Internados & Ense\u00d1anza Privada",
    "sg:phone":"+34 971 75 17 81",
    "sg:postcode":"07004",
    "sg:province":"Islas Baleares",
    "wof:name":"Congregacion Hermanas De Los S.s.c.c.",
    "wof:placetype":"venue"
},
  "geometry": {"coordinates":[2.6543679237,39.5862426758],"type":"Point"}
}