{
  "type": "Feature",
  "properties": {
    "addr:full":"Plaz Fuente De Las Damas, 5 Almonte Huelva 21730",
    "addr:housenumber":"5",
    "addr:postcode":"21730",
    "addr:street":"Plaz Fuente De Las Damas",
    "iso:country":"ES",
    "sg:address":"Plaz Fuente De Las Damas, 5",
    "sg:city":"Almonte",
    "sg:orig_category":"Asociaciones Y Clubs Deportivos",
    "sg:phone":"+34 959 40 71 03",
    "sg:postcode":"21730",
    "sg:province":"Huelva",
    "wof:name":"Pe\u00d1a Madridista Dominio Blanco",
    "wof:placetype":"venue"
},
  "geometry": {"coordinates":[-6.5216588974,37.2561607361],"type":"Point"}
}