{
  "type": "Feature",
  "properties": {
    "addr:full":"Calle de Plaza, S/n Granado Huelva 21594",
    "addr:housenumber":"s / n",
    "addr:postcode":"21594",
    "addr:street":"Calle De Plaza",
    "iso:country":"ES",
    "sg:address":"Calle de Plaza, S/n",
    "sg:city":"Granado",
    "sg:orig_category":"Administraciones Regionales, Departamentales Y Locales",
    "sg:phone":"+34 959 38 85 10",
    "sg:postcode":"21594",
    "sg:province":"Huelva",
    "wof:name":"Ayuntamiento Del Granado",
    "wof:placetype":"venue"
},
  "geometry": {"coordinates":[-7.4163799286,37.5214881897],"type":"Point"}
}