{
  "type": "Feature",
  "properties": {
    "iso:country":"ES",
    "sg:address":"Carrer de Sant Joan Bosco, 5",
    "sg:city":"S. Boi Llobregat",
    "sg:orig_category":"Art\u00cdculos De Regalo (al Por Menor)",
    "sg:phone":"+34 936 40 29 65",
    "sg:postcode":"08830",
    "sg:province":"Barcelona",
    "wof:name":"Mzs Comercial Import S.c.p.",
    "wof:placetype":"venue"
},
  "geometry": {"coordinates":[2.0436019897,41.3433418274],"type":"Point"}
}