{
  "type": "Feature",
  "properties": {
    "addr:full":"Carrer de Sant Joan, 94 Carrer De Baix -plana De Can Periquet Barcelona 08184",
    "addr:housenumber":"94",
    "addr:postcode":"08184",
    "addr:street":"Carrer De Sant Joan;Carrer De Baix Plana De Can Periquet",
    "iso:country":"ES",
    "sg:address":"Carrer de Sant Joan, 94",
    "sg:city":"Carrer De Baix -plana De Can Periquet",
    "sg:orig_category":"Reposter\u00cdas",
    "sg:phone":"+34 938 64 95 02",
    "sg:postcode":"08184",
    "sg:province":"Barcelona",
    "wof:name":"Miguel Y Jorge Corominas Pujol S.cv.",
    "wof:placetype":"venue"
},
  "geometry": {"coordinates":[2.1748530865,41.5814743042],"type":"Point"}
}