{
  "type": "Feature",
  "properties": {
    "addr:full":"Geltoki Kalea-calle Estacion, 25 Lasarte Guip\u00f9zcoa 20160",
    "addr:housenumber":"25",
    "addr:postcode":"20160",
    "addr:street":"Estacion;Guipu\u0300Zcoa",
    "iso:country":"ES",
    "sg:address":"Geltoki Kalea-calle Estacion, 25",
    "sg:city":"Lasarte",
    "sg:orig_category":"Zapatos (al Por Menor)",
    "sg:phone":"+34 943 36 17 99",
    "sg:postcode":"20160",
    "sg:province":"Guip\u00f9zcoa",
    "wof:name":"Lucena Etxebarria Ainhara",
    "wof:placetype":"venue"
},
  "geometry": {"coordinates":[-2.020414114,43.2698173523],"type":"Point"}
}