{
  "type": "Feature",
  "properties": {
    "addr:full":"Avda Gasteiz, 37 Vitoria-gasteiz \u00c1lava 01008",
    "addr:housenumber":"37",
    "addr:postcode":"01008",
    "addr:street":"Avda Gasteiz",
    "iso:country":"ES",
    "sg:address":"Avda Gasteiz, 37",
    "sg:city":"Vitoria-gasteiz",
    "sg:orig_category":"Caf\u00c9s, Bares, Cervecer\u00cdas",
    "sg:phone":"+34 945 24 33 05",
    "sg:postcode":"01008",
    "sg:province":"\u00c1lava",
    "wof:name":"Ramos De Las Heras Aureliano",
    "wof:placetype":"venue"
},
  "geometry": {"coordinates":[-2.6821529865,42.8466491699],"type":"Point"}
}