{
  "type": "Feature",
  "properties": {
    "iso:country":"ES",
    "sg:address":"Ptda El Palmar, S/n",
    "sg:city":"Pol Ind Fuente Jarro",
    "sg:orig_category":"Materias Pl\u00c1sticas: Productos Acabados Y Semiacabados (fabricaci\u00d3n)",
    "sg:phone":"+34 961 34 02 17",
    "sg:postcode":"46988",
    "sg:province":"Valencia",
    "wof:name":"Plasticos Viters S. A.",
    "wof:placetype":"venue"
},
  "geometry": {"coordinates":[-0.376819998,39.4691886902],"type":"Point"}
}