{
  "type": "Feature",
  "properties": {
    "iso:country":"ES",
    "sg:address":"Calle de Inocencia Rodriguez Rubio, 6",
    "sg:city":"Badajoz",
    "sg:classifiers":[
        {
            "category":"Personal",
            "subcategory":"Barber",
            "type":"Services"
        }
    ],
    "sg:phone":"+34 924 24 81 17",
    "sg:postcode":"06003",
    "sg:province":"Badajoz",
    "sg:tags":[
        "caballeros",
        "de",
        "peluqueros"
    ],
    "wof:name":"Rodriguez Garcia Matias",
    "wof:placetype":"venue"
},
  "geometry": {"coordinates":[-6.9692239761,38.8705749512],"type":"Point"}
}