{
  "type": "Feature",
  "properties": {
    "addr:full":"Calle de Lisboa, 3 Toledo Toledo 45005",
    "addr:housenumber":"3",
    "addr:postcode":"45005",
    "addr:street":"Calle De Lisboa",
    "iso:country":"ES",
    "sg:address":"Calle de Lisboa, 3",
    "sg:city":"Toledo",
    "sg:orig_category":"Caf\u00c9s, Bares, Cervecer\u00cdas",
    "sg:phone":"+34 925 22 13 83",
    "sg:postcode":"45005",
    "sg:province":"Toledo",
    "wof:name":"Ca\u00f1adas Contreras Victor",
    "wof:placetype":"venue"
},
  "geometry": {"coordinates":[-4.0350928307,39.8728141785],"type":"Point"}
}