{
  "type": "Feature",
  "properties": {
    "iso:country":"ES",
    "sg:address":"Calle de Cami Real, 24",
    "sg:city":"Sagunt",
    "sg:orig_category":"Arquitectos",
    "sg:phone":"+34 962 65 06 75",
    "sg:postcode":"46500",
    "sg:province":"Valencia",
    "wof:name":"Legarre Gil Francisco Javier",
    "wof:placetype":"venue"
},
  "geometry": {"coordinates":[-0.2772176862,39.6798210144],"type":"Point"}
}