{
  "type": "Feature",
  "properties": {
    "addr:full":"Calle de Luciano Pita, 23 Ortigueira La Coru\u00f1a 15330",
    "addr:housenumber":"23",
    "addr:postcode":"15330",
    "addr:street":"Calle De Luciano Pita;La Corun\u0303A",
    "iso:country":"ES",
    "sg:address":"Calle de Luciano Pita, 23",
    "sg:city":"Ortigueira",
    "sg:orig_category":"Ropa Para Ni\u00d1os (al Por Menor)",
    "sg:phone":"+34 981 40 02 93",
    "sg:postcode":"15330",
    "sg:province":"La Coru\u00f1a",
    "wof:name":"Rodriguez Martinez Maria Teresa",
    "wof:placetype":"venue"
},
  "geometry": {"coordinates":[-7.8537168503,43.6840629578],"type":"Point"}
}