{
  "type": "Feature",
  "properties": {
    "addr:full":"G.v. Corts Catalanes, 480 Barcelona Barcelona 08015",
    "addr:housenumber":"480",
    "addr:postcode":"08015",
    "addr:street":"Catalanes",
    "iso:country":"ES",
    "sg:address":"G.v. Corts Catalanes, 480",
    "sg:city":"Barcelona",
    "sg:orig_category":"Electrodom\u00c9sticos (al Por Menor)",
    "sg:phone":"+34 934 25 31 26",
    "sg:postcode":"08015",
    "sg:province":"Barcelona",
    "wof:name":"Quatre Vuitanta S.c.p.",
    "wof:placetype":"venue"
},
  "geometry": {"coordinates":[2.1561729908,41.379901886],"type":"Point"}
}