{
  "type": "Feature",
  "properties": {
    "iso:country":"ES",
    "sg:address":"Calle de Altos De La Condomina Sector 1, 6",
    "sg:city":"Villena",
    "sg:orig_category":"Material Y Herramientas Agr\u00cdcolas",
    "sg:phone":"+34 965 80 39 48",
    "sg:postcode":"03400",
    "sg:province":"Alicante",
    "wof:name":"Agromecanicas Condomina S.l.",
    "wof:placetype":"venue"
},
  "geometry": {"coordinates":[-0.870324,38.633213],"type":"Point"}
}