{
  "type": "Feature",
  "properties": {
    "iso:country":"ES",
    "sg:address":"Pque Hermanos Millares, 13",
    "sg:city":"Palmas De Gran Canaria",
    "sg:orig_category":"Panader\u00cdas, Panader\u00cdas",
    "sg:phone":"+34 928 25 26 07",
    "sg:postcode":"35011",
    "sg:province":"Las Palmas",
    "wof:name":"Quintana Acosta Luis",
    "wof:placetype":"venue"
},
  "geometry": {"coordinates":[-15.4375810623,28.1157207489],"type":"Point"}
}