{
  "type": "Feature",
  "properties": {
    "iso:country":"ES",
    "sg:address":"Carrer de Galileu, 164",
    "sg:city":"Terrassa",
    "sg:orig_category":"M\u00c9dicos: Dermatolog\u00cda Y Venereolog\u00cda",
    "sg:phone":"+34 937 80 71 63",
    "sg:postcode":"08224",
    "sg:province":"Barcelona",
    "wof:name":"Vives Vila Pere",
    "wof:placetype":"venue"
},
  "geometry": {"coordinates":[2.005512476,41.5625],"type":"Point"}
}