{
  "type": "Feature",
  "properties": {
    "addr:full":"Carrer de Josep Umbert, 58 Granollers Barcelona 08402",
    "addr:housenumber":"58",
    "addr:postcode":"08402",
    "addr:street":"Carrer De Josep Umbert",
    "iso:country":"ES",
    "sg:address":"Carrer de Josep Umbert, 58",
    "sg:city":"Granollers",
    "sg:orig_category":"Asociaciones Y Clubs Deportivos",
    "sg:phone":"+34 938 70 12 97",
    "sg:postcode":"08402",
    "sg:province":"Barcelona",
    "wof:name":"Reial Automobil Club De Catalunya",
    "wof:placetype":"venue"
},
  "geometry": {"coordinates":[2.2908489704,41.6056632996],"type":"Point"}
}