{
  "type": "Feature",
  "properties": {
    "addr:full":"Calle de Calderon De La Barca, 19 Nerva Huelva 21670",
    "addr:housenumber":"19",
    "addr:postcode":"21670",
    "addr:street":"Calle De Calderon De La Barca",
    "iso:country":"ES",
    "sg:address":"Calle de Calderon De La Barca, 19",
    "sg:city":"Nerva",
    "sg:orig_category":"Ense\u00d1anza, Formaci\u00d3n Profesional: Aprendizaje",
    "sg:phone":"+34 959 58 02 27",
    "sg:postcode":"21670",
    "sg:province":"Huelva",
    "wof:name":"Leon Garcia Manuel Jesus",
    "wof:placetype":"venue"
},
  "geometry": {"coordinates":[-6.5491080284,37.6976776123],"type":"Point"}
}