{
  "type": "Feature",
  "properties": {
    "addr:full":"Avda Pio Xii, 2 Valencia Valencia 46009",
    "addr:housenumber":"2",
    "addr:postcode":"46009",
    "addr:street":"Avda Pio Xii",
    "iso:country":"ES",
    "sg:address":"Avda Pio Xii, 2",
    "sg:city":"Valencia",
    "sg:orig_category":"Confecci\u00d3n De Zapatos",
    "sg:phone":"+34 963 49 68 53",
    "sg:postcode":"46009",
    "sg:province":"Valencia",
    "wof:name":"Yorga S. A.",
    "wof:placetype":"venue"
},
  "geometry": {"coordinates":[-0.3912586868,39.479598999],"type":"Point"}
}