{
  "type": "Feature",
  "properties": {
    "iso:country":"ES",
    "sg:address":"Calle de Canonigo Azofra Del Campo, 3",
    "sg:city":"Palmas De Gran Canaria",
    "sg:orig_category":"Supermercados Y Hipermercados",
    "sg:phone":"+34 928 20 94 20",
    "sg:postcode":"35011",
    "sg:province":"Las Palmas",
    "wof:name":"Deniz Santana Jose Juan",
    "wof:placetype":"venue"
},
  "geometry": {"coordinates":[-15.4375677109,28.1142463684],"type":"Point"}
}