{
  "type": "Feature",
  "properties": {
    "iso:country":"ES",
    "sg:address":"Avda Plana (la), 77",
    "sg:city":"Oropesa",
    "sg:orig_category":"Peluquer\u00cdas, Peluquer\u00cda Mixta",
    "sg:phone":"+34 964 31 02 78",
    "sg:postcode":"12594",
    "sg:province":"Castell\u00f3n",
    "wof:name":"Peluqueria Oropesa S.l.v.",
    "wof:placetype":"venue"
},
  "geometry": {"coordinates":[0.135886997,40.0910224915],"type":"Point"}
}