{
  "type": "Feature",
  "properties": {
    "iso:country":"ES",
    "sg:address":"Calle de Calderon De La Barca, 11",
    "sg:city":"Orihuela",
    "sg:classifiers":[
        {
            "category":"Communications",
            "type":"Services"
        }
    ],
    "sg:phone":"+34 965 30 23 80",
    "sg:postcode":"03300",
    "sg:province":"Alicante",
    "sg:tags":[
        "televisiones",
        "y",
        "radio"
    ],
    "wof:name":"Uniprex-onda Cero",
    "wof:placetype":"venue"
},
  "geometry": {"coordinates":[-0.9447839856,38.0841178894],"type":"Point"}
}