{
  "type": "Feature",
  "properties": {
    "iso:country":"ES",
    "sg:address":"Pg Maragall, 107",
    "sg:city":"Barcelona",
    "sg:orig_category":"Art\u00cdculos De Regalo (al Por Menor)",
    "sg:phone":"+34 934 36 67 41",
    "sg:postcode":"08041",
    "sg:province":"Barcelona",
    "wof:name":"Salvador Carayol Juan",
    "wof:placetype":"venue"
},
  "geometry": {"coordinates":[2.1804339886,41.4189605713],"type":"Point"}
}