{
  "type": "Feature",
  "properties": {
    "iso:country":"ES",
    "sg:address":"Calle de Mozarabes Los, 3",
    "sg:city":"Huelva",
    "sg:classifiers":[
        {
            "category":"Casinos & Gambling",
            "type":"Entertainment"
        }
    ],
    "sg:phone":"+34 959 25 22 02",
    "sg:postcode":"21001",
    "sg:province":"Huelva",
    "sg:tags":[
        "locale",
        "de",
        "juego"
    ],
    "wof:name":"Amonimares S.l.l.",
    "wof:placetype":"venue"
},
  "geometry": {"coordinates":[-6.9569749832,37.2597312927],"type":"Point"}
}