{
  "type": "Feature",
  "properties": {
    "iso:country":"ES",
    "sg:address":"Calle de Juan Manuel Duran Gonzalez, 43",
    "sg:city":"Palmas De Gran Canaria",
    "sg:orig_category":"Ropa Para Se\u00d1oras (al Por Menor)",
    "sg:phone":"+34 928 22 05 25",
    "sg:postcode":"35007",
    "sg:province":"Las Palmas",
    "wof:name":"Quesada Cerpa Eloisa Estrella",
    "wof:placetype":"venue"
},
  "geometry": {"coordinates":[-15.4343490601,28.1352901459],"type":"Point"}
}