{
  "type": "Feature",
  "properties": {
    "addr:full":"Trva Uruguay, 8 Toledo Toledo 45004",
    "addr:housenumber":"8",
    "addr:postcode":"45004",
    "addr:street":"Trva Uruguay",
    "iso:country":"ES",
    "sg:address":"Trva Uruguay, 8",
    "sg:city":"Toledo",
    "sg:orig_category":"Ropa De Hogar (al Por Menor)",
    "sg:phone":"+34 925 25 70 54",
    "sg:postcode":"45004",
    "sg:province":"Toledo",
    "wof:name":"Celestino Benito C.b.",
    "wof:placetype":"venue"
},
  "geometry": {"coordinates":[-4.033121109,39.8682327271],"type":"Point"}
}