{
  "type": "Feature",
  "properties": {
    "addr:full":"Av Doctor Francesc Massana, 14 Martorell Barcelona 08760",
    "addr:housenumber":"14",
    "addr:postcode":"08760",
    "addr:street":"Av Doctor Francesc Massana",
    "iso:country":"ES",
    "sg:address":"Av Doctor Francesc Massana, 14",
    "sg:city":"Martorell",
    "sg:orig_category":"Cajas De Ahorro",
    "sg:phone":"+34 937 75 52 20",
    "sg:postcode":"08760",
    "sg:province":"Barcelona",
    "sg:website":"www.lacaixa.es",
    "wof:name":"Caixa D'estalvis I Pensions De Barcelona",
    "wof:placetype":"venue"
},
  "geometry": {"coordinates":[1.9188090563,41.4790763855],"type":"Point"}
}