{
  "type": "Feature",
  "properties": {
    "addr:full":"Carr Cervantes, 38 Aldaia Valencia 46960",
    "addr:housenumber":"38",
    "addr:postcode":"46960",
    "addr:street":"Carr Cervantes",
    "iso:country":"ES",
    "sg:address":"Carr Cervantes, 38",
    "sg:city":"Aldaia",
    "sg:orig_category":"Fabricaci\u00d3n, Distribuci\u00d3n De Material Para La Climatizaci\u00d3n, Aireaci\u00d3n Y Ventilaci\u00d3n",
    "sg:phone":"+34 961 50 51 77",
    "sg:postcode":"46960",
    "sg:province":"Valencia",
    "wof:name":"Daniel Mateu S.l.",
    "wof:placetype":"venue"
},
  "geometry": {"coordinates":[-0.4601419866,39.4674987793],"type":"Point"}
}