{
  "type": "Feature",
  "properties": {
    "iso:country":"ES",
    "sg:address":"Calle de Ayala, 142",
    "sg:city":"Madrid",
    "sg:orig_category":"Tiendas De Grano, Frutas Y Legumbres Secas (al Por Menor)",
    "sg:phone":"+34 914 01 33 39",
    "sg:postcode":"28006",
    "sg:province":"Madrid",
    "wof:name":"Martin San Juan Agapito",
    "wof:placetype":"venue"
},
  "geometry": {"coordinates":[-3.6719682217,40.4271354675],"type":"Point"}
}