{
  "type": "Feature",
  "properties": {
    "addr:full":"Calle de Bizkargi, 17 Bilbao Vizcaya 48002",
    "addr:housenumber":"17",
    "addr:postcode":"48002",
    "addr:street":"Calle De Bizkargi",
    "iso:country":"ES",
    "sg:address":"Calle de Bizkargi, 17",
    "sg:city":"Bilbao",
    "sg:orig_category":"Suministros Y Materiales Industriales",
    "sg:phone":"+34 944 41 50 40",
    "sg:postcode":"48002",
    "sg:province":"Vizcaya",
    "wof:name":"Suminor Nervion S.l.",
    "wof:placetype":"venue"
},
  "geometry": {"coordinates":[-2.9455890656,43.2487411499],"type":"Point"}
}