{
  "type": "Feature",
  "properties": {
    "addr:full":"Plaz Constitucion, 2 Plasencia C\u00e1ceres 10600",
    "addr:postcode":"10600",
    "addr:street":"Constitucion;Ca\u0301Ceres",
    "iso:country":"ES",
    "sg:address":"Plaz Constitucion, 2",
    "sg:city":"Plasencia",
    "sg:orig_category":"Electricidad: Instaladores",
    "sg:phone":"+34 927 41 11 88",
    "sg:postcode":"10600",
    "sg:province":"C\u00e1ceres",
    "wof:name":"Fernandez Montero Agustin",
    "wof:placetype":"venue"
},
  "geometry": {"coordinates":[-6.0816130638,40.0343208313],"type":"Point"}
}