{
  "type": "Feature",
  "properties": {
    "addr:full":"Calle de Bolivia, 67 Zaragoza Zaragoza 50010",
    "addr:housenumber":"67",
    "addr:postcode":"50010",
    "addr:street":"Calle De Bolivia",
    "iso:country":"ES",
    "sg:address":"Calle de Bolivia, 67",
    "sg:city":"Zaragoza",
    "sg:orig_category":"Puertas Y Portales",
    "sg:phone":"+34 976 34 36 42",
    "sg:postcode":"50010",
    "sg:province":"Zaragoza",
    "wof:name":"Lozano Esteras Felix",
    "wof:placetype":"venue"
},
  "geometry": {"coordinates":[-0.9005268812,41.6512489319],"type":"Point"}
}