{
  "type": "Feature",
  "properties": {
    "iso:country":"ES",
    "sg:address":"Cmno Lomo La Bautista, S/n",
    "sg:city":"Santa Catalina",
    "sg:orig_category":"Cr\u00cda De Poller\u00cda Y De Conejos",
    "sg:phone":"+34 922 35 04 63",
    "sg:postcode":"38449",
    "sg:province":"Santa Cruz De Tenerife",
    "wof:name":"Rodriguez Felipe Maria Del Carmen",
    "wof:placetype":"venue"
},
  "geometry": {"coordinates":[-16.6644916534,28.3740024567],"type":"Point"}
}