{
  "type": "Feature",
  "properties": {
    "addr:full":"Calle de Juan Bautista Zabala, 12 Algorta Vizcaya 48991",
    "addr:housenumber":"12",
    "addr:postcode":"48991",
    "addr:street":"Calle De Juan Bautista Zabala",
    "iso:country":"ES",
    "sg:address":"Calle de Juan Bautista Zabala, 12",
    "sg:city":"Algorta",
    "sg:orig_category":"Tapiceros Y Tapiceros",
    "sg:phone":"+34 944 91 05 96",
    "sg:postcode":"48991",
    "sg:province":"Vizcaya",
    "wof:name":"Santiago Perez Monica",
    "wof:placetype":"venue"
},
  "geometry": {"coordinates":[-3.0100948811,43.3507347107],"type":"Point"}
}