{
  "type": "Feature",
  "properties": {
    "iso:country":"ES",
    "sg:address":"Carrer de Coll, 27",
    "sg:city":"Barcelona",
    "sg:orig_category":"Restaurantes",
    "sg:phone":"+34 933 49 50 00",
    "sg:postcode":"08027",
    "sg:province":"Barcelona",
    "wof:name":"Carmona Mercade Amanda",
    "wof:placetype":"venue"
},
  "geometry": {"coordinates":[2.1895139217,41.424495697],"type":"Point"}
}