{
  "type": "Feature",
  "properties": {
    "addr:full":"Calle de Miradores, 16 Valle Abdalajis M\u00e1laga 29240",
    "addr:housenumber":"16",
    "addr:postcode":"29240",
    "addr:street":"Calle De Miradores;Abdalajis Ma\u0301Laga",
    "iso:country":"ES",
    "sg:address":"Calle de Miradores, 16",
    "sg:city":"Valle Abdalajis",
    "sg:orig_category":"Delegados, Agentes De Tr\u00c1nsito, Auxiliares De Transporte Internacional",
    "sg:phone":"+34 952 48 80 28",
    "sg:postcode":"29240",
    "sg:province":"M\u00e1laga",
    "wof:name":"Ortiz Melero Fernando",
    "wof:placetype":"venue"
},
  "geometry": {"coordinates":[-4.6837239265,36.930141449],"type":"Point"}
}