{
  "type": "Feature",
  "properties": {
    "addr:full":"Calle de Gaspar Torrella, 11 Valencia Valencia 46017",
    "addr:housenumber":"11",
    "addr:postcode":"46017",
    "addr:street":"Calle De Gaspar Torrella",
    "iso:country":"ES",
    "sg:address":"Calle de Gaspar Torrella, 11",
    "sg:city":"Valencia",
    "sg:orig_category":"Mec\u00c1nico Del Autom\u00d3vil",
    "sg:phone":"+34 963 77 20 73",
    "sg:postcode":"46017",
    "sg:province":"Valencia",
    "wof:name":"Miguel Bonet C.b.",
    "wof:placetype":"venue"
},
  "geometry": {"coordinates":[-0.3930299878,39.4534797668],"type":"Point"}
}