{
  "type": "Feature",
  "properties": {
    "iso:country":"ES",
    "sg:address":"Calle de Palanquera, 18",
    "sg:city":"Larraga",
    "sg:orig_category":"Farmacias",
    "sg:phone":"+34 948 71 12 36",
    "sg:postcode":"31251",
    "sg:province":"Navarra",
    "wof:name":"Los Arcos Garcia Maria Jesus",
    "wof:placetype":"venue"
},
  "geometry": {"coordinates":[-1.8489730358,42.5577697754],"type":"Point"}
}