{
  "type": "Feature",
  "properties": {
    "addr:full":"Calle de Ruiz De Padron, 92 S. Sebastian Gomera Santa Cruz De Tenerife 38800",
    "addr:housenumber":"92",
    "addr:postcode":"38800",
    "addr:street":"Calle De Ruiz De Padron;S. Sebastian Gomera",
    "iso:country":"ES",
    "sg:address":"Calle de Ruiz De Padron, 92",
    "sg:city":"S. Sebastian Gomera",
    "sg:orig_category":"Servicios Diversos",
    "sg:phone":"+34 922 87 15 28",
    "sg:postcode":"38800",
    "sg:province":"Santa Cruz De Tenerife",
    "sg:website":"www.fotovideogomera.com",
    "wof:name":"Brito Gutierrez Carlos",
    "wof:placetype":"venue"
},
  "geometry": {"coordinates":[-17.1126708984,28.0934123993],"type":"Point"}
}