{
  "type": "Feature",
  "properties": {
    "iso:country":"ES",
    "sg:address":"Avda Plutarco, 20",
    "sg:city":"Malaga",
    "sg:orig_category":"Molduras, Junquillos, Listones Y Molduras Perforadas",
    "sg:phone":"+34 952 06 84 44",
    "sg:postcode":"29010",
    "sg:province":"M\u00e1laga",
    "wof:name":"Diaz Rueda Oscar",
    "wof:placetype":"venue"
},
  "geometry": {"coordinates":[-4.4771847725,36.7210388184],"type":"Point"}
}