{
  "type": "Feature",
  "properties": {
    "addr:full":"Calle de Jose Nogales, 2 Huelva Huelva 21001",
    "addr:housenumber":"2",
    "addr:postcode":"21001",
    "addr:street":"Calle De Jose Nogales",
    "iso:country":"ES",
    "sg:address":"Calle de Jose Nogales, 2",
    "sg:city":"Huelva",
    "sg:orig_category":"Abogados",
    "sg:phone":"+34 959 54 40 35",
    "sg:postcode":"21001",
    "sg:province":"Huelva",
    "wof:name":"Dominguez Salcedo Manuel",
    "wof:placetype":"venue"
},
  "geometry": {"coordinates":[-6.9543890953,37.2576408386],"type":"Point"}
}