{
  "type": "Feature",
  "properties": {
    "addr:full":"Calle de Meliton Corti\u00d1as, 4 Viveiro Lugo 27850",
    "addr:housenumber":"4",
    "addr:postcode":"27850",
    "addr:street":"Calle De Meliton Cortin\u0303As",
    "iso:country":"ES",
    "sg:address":"Calle de Meliton Corti\u00d1as, 4",
    "sg:city":"Viveiro",
    "sg:orig_category":"Ropa Para Caballeros (al Por Menor)",
    "sg:phone":"+34 982 56 16 56",
    "sg:postcode":"27850",
    "sg:province":"Lugo",
    "wof:name":"Lopez Castro Juan",
    "wof:placetype":"venue"
},
  "geometry": {"coordinates":[-7.5959348679,43.6629714966],"type":"Point"}
}