{
  "type": "Feature",
  "properties": {
    "addr:full":"Rua Garcia Olloqui, 6 Vigo Pontevedra 36201",
    "addr:housenumber":"6",
    "addr:postcode":"36201",
    "addr:street":"Rua Garcia Olloqui",
    "iso:country":"ES",
    "sg:address":"Rua Garcia Olloqui, 6",
    "sg:city":"Vigo",
    "sg:orig_category":"Deportes N\u00c1uticos, Acu\u00c1ticos Y Subacu\u00c1ticos: Art\u00cdculos Y Equipo (al Por Menor)",
    "sg:phone":"+34 986 43 44 72",
    "sg:postcode":"36201",
    "sg:province":"Pontevedra",
    "sg:website":"www.ronautica.com",
    "wof:name":"Ronautica S. A.",
    "wof:placetype":"venue"
},
  "geometry": {"coordinates":[-8.72397995,42.2397918701],"type":"Point"}
}