{
  "type": "Feature",
  "properties": {
    "addr:full":"Calle de Cardenal Cisneros, 12 Valladolid Valladolid 47010",
    "addr:housenumber":"12",
    "addr:postcode":"47010",
    "addr:street":"Calle De Cardenal Cisneros",
    "iso:country":"ES",
    "sg:address":"Calle de Cardenal Cisneros, 12",
    "sg:city":"Valladolid",
    "sg:orig_category":"Perfumer\u00cda (al Por Menor)",
    "sg:phone":"+34 983 25 08 92",
    "sg:postcode":"47010",
    "sg:province":"Valladolid",
    "sg:website":"www.marionnaud.es",
    "wof:name":"Marionnaud Perfumeries Iberica S.l.",
    "wof:placetype":"venue"
},
  "geometry": {"coordinates":[-4.7219977379,41.6613121033],"type":"Point"}
}