{
  "type": "Feature",
  "properties": {
    "addr:full":"A (pol Ind Moli Frares), 39 S. Vicen\u00e7 Horts Barcelona 08620",
    "addr:housenumber":"39",
    "addr:postcode":"08620",
    "addr:street":"Frares;S. Vicenc\u0327 Horts Barcelona",
    "iso:country":"ES",
    "sg:address":"A (pol Ind Moli Frares), 39",
    "sg:city":"S. Vicen\u00e7 Horts",
    "sg:orig_category":"Maquinaria Para Industrias Diversas",
    "sg:phone":"+34 936 56 80 70",
    "sg:postcode":"08620",
    "sg:province":"Barcelona",
    "sg:website":"www.spa-aquaservis.com",
    "wof:name":"Viva Aqua Service Spain S.a.",
    "wof:placetype":"venue"
},
  "geometry": {"coordinates":[2.1699187756,41.3879165649],"type":"Point"}
}