{
  "type": "Feature",
  "properties": {
    "iso:country":"ES",
    "sg:address":"Plaza Anteiglesia, 3",
    "sg:city":"Barakaldo",
    "sg:classifiers":[
        {
            "category":"Personal",
            "subcategory":"Barber",
            "type":"Services"
        }
    ],
    "sg:phone":"+34 944 38 06 52",
    "sg:postcode":"48902",
    "sg:province":"Vizcaya",
    "sg:tags":[
        "caballeros",
        "de",
        "peluqueros"
    ],
    "wof:name":"Peluqueria (jose Pe\u00f1a Maldonado)",
    "wof:placetype":"venue"
},
  "geometry": {"coordinates":[-2.997303009,43.2954711914],"type":"Point"}
}