{
  "type": "Feature",
  "properties": {
    "iso:country":"ES",
    "sg:address":"Calle de Bailen, 7",
    "sg:city":"Almendralejo",
    "sg:orig_category":"Electrodom\u00c9sticos (al Por Menor)",
    "sg:phone":"+34 924 66 29 16",
    "sg:postcode":"06200",
    "sg:province":"Badajoz",
    "wof:name":"Electronica Benjamin S.l.",
    "wof:placetype":"venue"
},
  "geometry": {"coordinates":[-6.4080648422,38.6821327209],"type":"Point"}
}