{
  "type": "Feature",
  "properties": {
    "addr:full":"Calle de Muelle, 3 Puertollano Ciudad Real 13500",
    "addr:housenumber":"3",
    "addr:postcode":"13500",
    "addr:street":"Calle De Muelle",
    "iso:country":"ES",
    "sg:address":"Calle de Muelle, 3",
    "sg:city":"Puertollano",
    "sg:orig_category":"Supermercados Y Hipermercados",
    "sg:phone":"+34 926 43 03 53",
    "sg:postcode":"13500",
    "sg:province":"Ciudad Real",
    "sg:website":"www.mercadona.es",
    "wof:name":"Mercadona S.a.",
    "wof:placetype":"venue"
},
  "geometry": {"coordinates":[-4.1097240448,38.6912155151],"type":"Point"}
}