{
  "type": "Feature",
  "properties": {
    "addr:full":"Carrer de Estadi (de L'), 41 Vila-seca Tarragona 43480",
    "addr:housenumber":"41",
    "addr:postcode":"43480",
    "addr:street":"Carrer De Estadi De L '",
    "iso:country":"ES",
    "sg:address":"Carrer de Estadi (de L'), 41",
    "sg:city":"Vila-seca",
    "sg:orig_category":"Ense\u00d1anza: Idiomas",
    "sg:phone":"+34 977 39 03 44",
    "sg:postcode":"43480",
    "sg:province":"Tarragona",
    "sg:website":"www.academiaspeakout.com",
    "wof:name":"Terrazas Gonzalez Maria",
    "wof:placetype":"venue"
},
  "geometry": {"coordinates":[1.1370999813,41.1125717163],"type":"Point"}
}