{
  "type": "Feature",
  "properties": {
    "addr:full":"Ctra Santpedor, 96 Manresa Barcelona 08243",
    "addr:housenumber":"96",
    "addr:postcode":"08243",
    "addr:street":"Ctra Santpedor",
    "iso:country":"ES",
    "sg:address":"Ctra Santpedor, 96",
    "sg:city":"Manresa",
    "sg:orig_category":"Reposter\u00cdas",
    "sg:phone":"+34 938 73 33 49",
    "sg:postcode":"08243",
    "sg:province":"Barcelona",
    "wof:name":"Llusa Pla Juan",
    "wof:placetype":"venue"
},
  "geometry": {"coordinates":[1.8320879936,41.7335281372],"type":"Point"}
}