{
  "type": "Feature",
  "properties": {
    "addr:full":"Calle de Rio Odiel, Km. 0016,5 Atalayuela Madrid 28906",
    "addr:postcode":"28906",
    "addr:street":"Calle De Rio Odiel Km. 0016,5",
    "iso:country":"ES",
    "sg:address":"Calle de Rio Odiel, Km. 0016,5",
    "sg:city":"Atalayuela",
    "sg:orig_category":"Fabricaci\u00d3n De Art\u00cdculos Y Equipos Deportivos Y De Ocio",
    "sg:phone":"+34 916 91 85 40",
    "sg:postcode":"28906",
    "sg:province":"Madrid",
    "sg:website":"www.decathlon.es",
    "wof:name":"Decathlon Espa\u00f1a S. A. U.",
    "wof:placetype":"venue"
},
  "geometry": {"coordinates":[-3.7057700157,40.42029953],"type":"Point"}
}