{
  "type": "Feature",
  "properties": {
    "iso:country":"ES",
    "sg:address":"Avda Libertad (de La), 91",
    "sg:city":"Alcazares",
    "sg:orig_category":"Plomeros",
    "sg:phone":"+34 968 57 54 46",
    "sg:postcode":"30710",
    "sg:province":"Murcia",
    "wof:name":"Olmos Martinez Miguel Angel",
    "wof:placetype":"venue"
},
  "geometry": {"coordinates":[-0.8523989916,37.7389907837],"type":"Point"}
}