{
  "type": "Feature",
  "properties": {
    "addr:full":"Rua Alcalde Domingo Sierra, 51 Conduzo La Coru\u00f1a 15174",
    "addr:housenumber":"51",
    "addr:postcode":"15174",
    "addr:street":"Rua Alcalde Domingo Sierra;La Corun\u0303A",
    "iso:country":"ES",
    "sg:address":"Rua Alcalde Domingo Sierra, 51",
    "sg:city":"Conduzo",
    "sg:orig_category":"Electricidad: Instaladores",
    "sg:phone":"+34 981 65 46 42",
    "sg:postcode":"15174",
    "sg:province":"La Coru\u00f1a",
    "wof:name":"Electricidad Y Proyectos De Galicia S.l.",
    "wof:placetype":"venue"
},
  "geometry": {"coordinates":[-8.3826389313,43.3110656738],"type":"Point"}
}