{
  "type": "Feature",
  "properties": {
    "addr:full":"Calle de Espinosa Y Carcel, 4 Sevilla Sevilla 41005",
    "addr:housenumber":"4",
    "addr:postcode":"41005",
    "addr:street":"Calle De Espinosa Y Carcel",
    "iso:country":"ES",
    "sg:address":"Calle de Espinosa Y Carcel, 4",
    "sg:city":"Sevilla",
    "sg:orig_category":"Papeler\u00cdas, Librer\u00cdas",
    "sg:phone":"+34 954 63 87 17",
    "sg:postcode":"41005",
    "sg:province":"Sevilla",
    "wof:name":"Ofinervion S.l.",
    "wof:placetype":"venue"
},
  "geometry": {"coordinates":[-5.9744510651,37.3777160645],"type":"Point"}
}