{
  "type": "Feature",
  "properties": {
    "iso:country":"ES",
    "sg:address":"Carrer de Jaume Isern, 58",
    "sg:city":"Mataro",
    "sg:orig_category":"Productos Qu\u00cdmicos (fabricaci\u00d3n, Al Por Mayor)",
    "sg:phone":"+34 937 41 41 45",
    "sg:postcode":"08302",
    "sg:province":"Barcelona",
    "wof:name":"Sun Siluet S.l.",
    "wof:placetype":"venue"
},
  "geometry": {"coordinates":[2.4382760525,41.5406265259],"type":"Point"}
}