{
  "type": "Feature",
  "properties": {
    "addr:full":"Calle de Zubiaurre, 8 Iurreta Vizcaya 48215",
    "addr:housenumber":"8",
    "addr:postcode":"48215",
    "addr:street":"Calle De Zubiaurre",
    "iso:country":"ES",
    "sg:address":"Calle de Zubiaurre, 8",
    "sg:city":"Iurreta",
    "sg:orig_category":"Plomeros",
    "sg:phone":"+34 946 20 27 68",
    "sg:postcode":"48215",
    "sg:province":"Vizcaya",
    "wof:name":"Aldecoa Totoricaguena Javier",
    "wof:placetype":"venue"
},
  "geometry": {"coordinates":[-2.6374783516,43.1737136841],"type":"Point"}
}