{
  "type": "Feature",
  "properties": {
    "iso:country":"ES",
    "sg:address":"Rua Numancia, 98",
    "sg:city":"Vigo",
    "sg:orig_category":"Ingeniero",
    "sg:phone":"+34 986 26 50 00",
    "sg:postcode":"36206",
    "sg:province":"Pontevedra",
    "wof:name":"Engel Axil S.l.",
    "wof:placetype":"venue"
},
  "geometry": {"coordinates":[-8.7046127319,42.2367286682],"type":"Point"}
}