{
  "type": "Feature",
  "properties": {
    "iso:country":"ES",
    "sg:address":"Carr Batllia, 31",
    "sg:city":"Bellver Cerdanya",
    "sg:orig_category":"Plomeros",
    "sg:phone":"+34 973 51 01 43",
    "sg:postcode":"25720",
    "sg:province":"Lleida",
    "wof:name":"Sarria Montane Fermin",
    "wof:placetype":"venue"
},
  "geometry": {"coordinates":[1.7763129473,42.371257782],"type":"Point"}
}