{
  "type": "Feature",
  "properties": {
    "addr:full":"Bo Casta\u00f1era, 537 Tanos Cantabria 39316",
    "addr:housenumber":"537",
    "addr:postcode":"39316",
    "addr:street":"Castan\u0303Era",
    "iso:country":"ES",
    "sg:address":"Bo Casta\u00f1era, 537",
    "sg:city":"Tanos",
    "sg:orig_category":"Agencias Y Agentes Comerciales, Representantes",
    "sg:phone":"+34 942 89 24 01",
    "sg:postcode":"39316",
    "sg:province":"Cantabria",
    "wof:name":"Escudero Ferreduela Carlos",
    "wof:placetype":"venue"
},
  "geometry": {"coordinates":[-4.044960022,43.3367385864],"type":"Point"}
}