{
  "type": "Feature",
  "properties": {
    "addr:full":"Calle de Cuna, 24 Sevilla Sevilla 41004",
    "addr:housenumber":"24",
    "addr:postcode":"41004",
    "addr:street":"Calle De Cuna",
    "iso:country":"ES",
    "sg:address":"Calle de Cuna, 24",
    "sg:city":"Sevilla",
    "sg:orig_category":"Ropa Para Ni\u00d1os (al Por Menor)",
    "sg:phone":"+34 954 21 30 38",
    "sg:postcode":"41004",
    "sg:province":"Sevilla",
    "wof:name":"Jorge Raposo Ana Rosa",
    "wof:placetype":"venue"
},
  "geometry": {"coordinates":[-5.9935050011,37.391494751],"type":"Point"}
}