{
  "type": "Feature",
  "properties": {
    "addr:full":"Barr Otelarre, S/n Villabona Guip\u00f9zcoa 20150",
    "addr:housenumber":"s / n",
    "addr:postcode":"20150",
    "addr:street":"Otelarre;Guipu\u0300Zcoa",
    "iso:country":"ES",
    "sg:address":"Barr Otelarre, S/n",
    "sg:city":"Villabona",
    "sg:classifiers":[
        {
            "category":"Autos & Motor Vehicles",
            "subcategory":"Automobile Sales",
            "type":"Retail Goods"
        }
    ],
    "sg:phone":"+34 943 69 40 86",
    "sg:postcode":"20150",
    "sg:province":"Guip\u00f9zcoa",
    "wof:name":"Autoescuela Bengoetxea S.l.",
    "wof:placetype":"venue"
},
  "geometry": {"coordinates":[-2.0502529144,43.1872177124],"type":"Point"}
}