{
  "type": "Feature",
  "properties": {
    "iso:country":"ES",
    "sg:address":"Calle de Bailen, S/n",
    "sg:city":"Malaga",
    "sg:orig_category":"Carnicer\u00cdas, Carnicer\u00cdas",
    "sg:phone":"+34 952 28 92 02",
    "sg:postcode":"29009",
    "sg:province":"M\u00e1laga",
    "wof:name":"Elena Perez Daniel",
    "wof:placetype":"venue"
},
  "geometry": {"coordinates":[-4.433784008,36.7246131897],"type":"Point"}
}