{
  "type": "Feature",
  "properties": {
    "iso:country":"ES",
    "sg:address":"Calle de Pidal, 27",
    "sg:city":"Llanes",
    "sg:orig_category":"Peluqueros: De Se\u00d1oras",
    "sg:phone":"+34 985 40 16 48",
    "sg:postcode":"33500",
    "sg:province":"Asturias",
    "wof:name":"Perez Perez Emilio",
    "wof:placetype":"venue"
},
  "geometry": {"coordinates":[-4.7549939156,43.4207191467],"type":"Point"}
}