{
  "type": "Feature",
  "properties": {
    "iso:country":"ES",
    "sg:address":"Calle de Lopez De Ayala, 16",
    "sg:city":"Almendralejo",
    "sg:orig_category":"Imprenta",
    "sg:phone":"+34 924 67 16 96",
    "sg:postcode":"06200",
    "sg:province":"Badajoz",
    "wof:name":"Inquietud De Juventud Sociedad Cooperativa",
    "wof:placetype":"venue"
},
  "geometry": {"coordinates":[-6.4130549431,38.6804275513],"type":"Point"}
}