{
  "type": "Feature",
  "properties": {
    "addr:full":"Avda Pablo Picasso, 30 Granada Granada 18008",
    "addr:housenumber":"30",
    "addr:postcode":"18008",
    "addr:street":"Avda Pablo Picasso",
    "iso:country":"ES",
    "sg:address":"Avda Pablo Picasso, 30",
    "sg:city":"Granada",
    "sg:orig_category":"Inmobiliaria (agencias)",
    "sg:phone":"+34 902 46 40 46",
    "sg:postcode":"18008",
    "sg:province":"Granada",
    "wof:name":"Chinar S.l.",
    "wof:placetype":"venue"
},
  "geometry": {"coordinates":[-3.5936479568,37.1651954651],"type":"Point"}
}