{
  "type": "Feature",
  "properties": {
    "addr:full":"Carr Belgica, 65 Badalona Barcelona 08917",
    "addr:housenumber":"65",
    "addr:postcode":"08917",
    "addr:street":"Carr Belgica",
    "iso:country":"ES",
    "sg:address":"Carr Belgica, 65",
    "sg:city":"Badalona",
    "sg:orig_category":"Ropa Y Accesorios",
    "sg:phone":"+34 933 95 25 65",
    "sg:postcode":"08917",
    "sg:province":"Barcelona",
    "wof:name":"Masas Sales Josefa",
    "wof:placetype":"venue"
},
  "geometry": {"coordinates":[2.2236700058,41.4585609436],"type":"Point"}
}