{
  "type": "Feature",
  "properties": {
    "addr:full":"Calle de Francisco Bejar, 24 Pozuelo De Alarcon Madrid 28223",
    "addr:housenumber":"24",
    "addr:postcode":"28223",
    "addr:street":"Calle De Francisco Bejar",
    "iso:country":"ES",
    "sg:address":"Calle de Francisco Bejar, 24",
    "sg:city":"Pozuelo De Alarcon",
    "sg:orig_category":"Financiaci\u00d3n Y Cr\u00c9ditos",
    "sg:phone":"+34 917 15 54 59",
    "sg:postcode":"28223",
    "sg:province":"Madrid",
    "wof:name":"Elfelama-2000 S.l.",
    "wof:placetype":"venue"
},
  "geometry": {"coordinates":[-3.8097970486,40.4399375916],"type":"Point"}
}