{
  "type": "Feature",
  "properties": {
    "iso:country":"ES",
    "sg:address":"Avda Central, 93",
    "sg:city":"Tias",
    "sg:orig_category":"Bisuter\u00cda, Joyer\u00cda, Relojer\u00cda (al Por Menor)",
    "sg:phone":"+34 928 83 43 92",
    "sg:postcode":"35572",
    "sg:province":"Las Palmas",
    "wof:name":"Joyeria Melvi S.l.",
    "wof:placetype":"venue"
},
  "geometry": {"coordinates":[-13.6558589935,28.9549694061],"type":"Point"}
}