{
  "type": "Feature",
  "properties": {
    "addr:full":"Carretera, S/n Cuevas Campo Granada 18813",
    "addr:postcode":"18813",
    "addr:street":"Carretera S / N",
    "iso:country":"ES",
    "sg:address":"Carretera, S/n",
    "sg:city":"Cuevas Campo",
    "sg:orig_category":"Negocio De Materiales De Construcci\u00d3n",
    "sg:phone":"+34 958 71 81 35",
    "sg:postcode":"18813",
    "sg:province":"Granada",
    "wof:name":"Lopez Mesas Marcelo",
    "wof:placetype":"venue"
},
  "geometry": {"coordinates":[-2.9325079918,37.6119651794],"type":"Point"}
}