{
  "type": "Feature",
  "properties": {
    "iso:country":"ES",
    "sg:address":"Calle de Oriental, 24",
    "sg:city":"Gijon",
    "sg:orig_category":"Mercer\u00cda, Lencer\u00cda (al Por Menor)",
    "sg:phone":"+34 985 32 75 73",
    "sg:postcode":"33213",
    "sg:province":"Asturias",
    "wof:name":"Delgado Rodriguez Patrocinio",
    "wof:placetype":"venue"
},
  "geometry": {"coordinates":[-5.6968002319,43.539352417],"type":"Point"}
}