{
  "type": "Feature",
  "properties": {
    "iso:country":"ES",
    "sg:address":"Ubeda, Km. 0047,0",
    "sg:city":"Cerro Molina",
    "sg:orig_category":"Cr\u00cda De Animales",
    "sg:phone":"+34 953 32 23 86",
    "sg:postcode":"23001",
    "sg:province":"Ja\u00e9n",
    "wof:name":"Piensos Jimenez S.l.",
    "wof:placetype":"venue"
},
  "geometry": {"coordinates":[-3.7906799316,37.7650909424],"type":"Point"}
}