{
  "type": "Feature",
  "properties": {
    "addr:full":"Carr Sant Jordi, S/n Bell-lloc D'urgell Lleida 25220",
    "addr:housenumber":"s / n",
    "addr:postcode":"25220",
    "addr:street":"Carr Sant Jordi",
    "iso:country":"ES",
    "sg:address":"Carr Sant Jordi, S/n",
    "sg:city":"Bell-lloc D'urgell",
    "sg:orig_category":"Venta, Instalaci\u00d3n De Cocinas",
    "sg:phone":"+34 973 56 06 08",
    "sg:postcode":"25220",
    "sg:province":"Lleida",
    "wof:name":"Amoros Simo Miguel",
    "wof:placetype":"venue"
},
  "geometry": {"coordinates":[0.7807369232,41.6340026855],"type":"Point"}
}