{
  "type": "Feature",
  "properties": {
    "addr:full":"Fuentes, 2 Cayarga Asturias 33586",
    "addr:housenumber":"2",
    "addr:postcode":"33586",
    "addr:street":"Fuentes;Asturias",
    "iso:country":"ES",
    "sg:address":"Fuentes, 2",
    "sg:city":"Cayarga",
    "sg:orig_category":"Silicatos Y Caol\u00cdn",
    "sg:phone":"+34 985 84 11 91",
    "sg:postcode":"33586",
    "sg:province":"Asturias",
    "wof:name":"A.f.de Micelli S.l.",
    "wof:placetype":"venue"
},
  "geometry": {"coordinates":[-5.9832577705,43.2504386902],"type":"Point"}
}