{
  "type": "Feature",
  "properties": {
    "iso:country":"ES",
    "sg:address":"Calle de Albi\u00d1ana, 18",
    "sg:city":"Alcasar",
    "sg:orig_category":"Agencias Y Agentes Comerciales, Representantes",
    "sg:phone":"+34 966 49 50 12",
    "sg:postcode":"03725",
    "sg:province":"Alicante",
    "wof:name":"Lowe  Christopher",
    "wof:placetype":"venue"
},
  "geometry": {"coordinates":[0.1433400065,38.7083473206],"type":"Point"}
}