{
  "type": "Feature",
  "properties": {
    "iso:country":"ES",
    "sg:address":"Calle de Andujar, 4",
    "sg:city":"Alcala Henares",
    "sg:classifiers":[
        {
            "category":"Autos & Motor Vehicles",
            "subcategory":"Automobile Sales",
            "type":"Retail Goods"
        }
    ],
    "sg:phone":"+34 918 88 34 09",
    "sg:postcode":"28804",
    "sg:province":"Madrid",
    "wof:name":"Autoescuelas Oromar-ta S.l.",
    "wof:placetype":"venue"
},
  "geometry": {"coordinates":[-3.3459129333,40.488155365],"type":"Point"}
}