{
  "type": "Feature",
  "properties": {
    "iso:country":"ES",
    "sg:address":"Avda Irmans Otero Goday, S/n",
    "sg:city":"Grove",
    "sg:orig_category":"Construcciones Navales Y Fluviales",
    "sg:phone":"+34 986 73 28 05",
    "sg:postcode":"36980",
    "sg:province":"Pontevedra",
    "wof:name":"Garrido Fernandez Jose",
    "wof:placetype":"venue"
},
  "geometry": {"coordinates":[-8.8657264709,42.498210907],"type":"Point"}
}