{
  "type": "Feature",
  "properties": {
    "iso:country":"ES",
    "sg:address":"Calle de Virgen De Las Angustias, S/n",
    "sg:city":"Villanueva Algaidas",
    "sg:orig_category":"Estancos",
    "sg:phone":"+34 952 74 43 25",
    "sg:postcode":"29310",
    "sg:province":"M\u00e1laga",
    "wof:name":"Ropero Arrabal Maria Vedruna",
    "wof:placetype":"venue"
},
  "geometry": {"coordinates":[-4.4500899315,37.1828231812],"type":"Point"}
}