{
  "type": "Feature",
  "properties": {
    "iso:country":"ES",
    "sg:address":"Calle de Garcia Lorca, 30",
    "sg:city":"Castejon",
    "sg:orig_category":"Pintura Y Barniz (al Por Menor)",
    "sg:phone":"+34 948 77 01 95",
    "sg:postcode":"31590",
    "sg:province":"Navarra",
    "wof:name":"Amo Antolin Florentino Del",
    "wof:placetype":"venue"
},
  "geometry": {"coordinates":[-1.6882324219,42.1683349609],"type":"Point"}
}