{
  "type": "Feature",
  "properties": {
    "addr:full":"Real, 17 Villasrubias Salamanca 37522",
    "addr:housenumber":"17",
    "addr:postcode":"37522",
    "addr:street":"Real",
    "iso:country":"ES",
    "sg:address":"Real, 17",
    "sg:city":"Villasrubias",
    "sg:orig_category":"Cajas Para Embalar",
    "sg:phone":"+34 923 48 66 08",
    "sg:postcode":"37522",
    "sg:province":"Salamanca",
    "wof:name":"Caja Rural Provincial De Salamanca",
    "wof:placetype":"venue"
},
  "geometry": {"coordinates":[-6.6404790878,40.3388404846],"type":"Point"}
}