{
  "type": "Feature",
  "properties": {
    "iso:country":"ES",
    "sg:address":"Plaz Doctor Torrens, 8",
    "sg:city":"Valencia",
    "sg:orig_category":"Empresas De Portes Y Mensajer\u00cda",
    "sg:phone":"+34 963 34 85 50",
    "sg:postcode":"46006",
    "sg:province":"Valencia",
    "wof:name":"Noguero Inclan Juan Antonio",
    "wof:placetype":"venue"
},
  "geometry": {"coordinates":[-0.3643920124,39.4576072693],"type":"Point"}
}