{
  "type": "Feature",
  "properties": {
    "iso:country":"ES",
    "sg:address":"Calle de Maria De Molina, 7",
    "sg:city":"Valladolid",
    "sg:orig_category":"Cadenas, Estaciones, Cableados Para Radio Y Televisi\u00d3n",
    "sg:phone":"+34 902 36 04 73",
    "sg:postcode":"47001",
    "sg:province":"Valladolid",
    "wof:name":"Omicron Software S.l.",
    "wof:placetype":"venue"
},
  "geometry": {"coordinates":[-4.7301301956,41.6494750977],"type":"Point"}
}