{
  "type": "Feature",
  "properties": {
    "iso:country":"ES",
    "sg:address":"Av Jaume Iii, 24",
    "sg:city":"Palma",
    "sg:orig_category":"Bisuter\u00cda, Joyer\u00cda, Relojer\u00cda (al Por Menor)",
    "sg:phone":"+34 971 71 70 54",
    "sg:postcode":"07012",
    "sg:province":"Islas Baleares",
    "wof:name":"Moreno Baltasar Enrique",
    "wof:placetype":"venue"
},
  "geometry": {"coordinates":[2.6430609226,39.5726127625],"type":"Point"}
}