{
  "type": "Feature",
  "properties": {
    "iso:country":"ES",
    "sg:address":"Avda Coru\u00d1a, 18",
    "sg:city":"Friol",
    "sg:orig_category":"Ingenier\u00cda, Centros De Estudios (diversos)",
    "sg:phone":"+34 982 37 10 42",
    "sg:postcode":"27220",
    "sg:province":"Lugo",
    "wof:name":"Trevin Ramallal Soledad",
    "wof:placetype":"venue"
},
  "geometry": {"coordinates":[-7.7798857689,43.0251045227],"type":"Point"}
}