{
  "type": "Feature",
  "properties": {
    "iso:country":"ES",
    "sg:address":"San Juan, 1",
    "sg:city":"San Juan De Mozarrifar",
    "sg:orig_category":"Alimentaci\u00d3n General (al Por Menor)",
    "sg:phone":"+34 976 15 02 75",
    "sg:postcode":"50820",
    "sg:province":"Zaragoza",
    "wof:name":"Laforga Ena Pilar",
    "wof:placetype":"venue"
},
  "geometry": {"coordinates":[-0.8413689733,41.7173118591],"type":"Point"}
}