{
  "type": "Feature",
  "properties": {
    "addr:full":"Calle de Republica Argentina, 8 Ponferrada Le\u00f3n 24400",
    "addr:housenumber":"8",
    "addr:postcode":"24400",
    "addr:street":"Calle De Republica Argentina",
    "iso:country":"ES",
    "sg:address":"Calle de Republica Argentina, 8",
    "sg:city":"Ponferrada",
    "sg:orig_category":"Sociedades, Compa\u00d1\u00cdas Aseguradoras",
    "sg:phone":"+34 987 41 02 94",
    "sg:postcode":"24400",
    "sg:province":"Le\u00f3n",
    "sg:website":"www.ocaso.es",
    "wof:name":"Ocaso S.a. Compa\u00f1ia De Seguros Y Reaseguros",
    "wof:placetype":"venue"
},
  "geometry": {"coordinates":[-6.6005568504,42.547706604],"type":"Point"}
}