{
  "type": "Feature",
  "properties": {
    "iso:country":"ES",
    "sg:address":"Calle de Armengual De La Mota, 8",
    "sg:city":"Malaga",
    "sg:orig_category":"Retoques De Vestidos",
    "sg:phone":"+34 952 28 45 51",
    "sg:postcode":"29007",
    "sg:province":"M\u00e1laga",
    "wof:name":"Arreglos Moda S.c",
    "wof:placetype":"venue"
},
  "geometry": {"coordinates":[-4.4293575287,36.7183952332],"type":"Point"}
}