{
  "type": "Feature",
  "properties": {
    "addr:full":"Ptda Altabix, 99 Elche Alicante 03291",
    "addr:housenumber":"99",
    "addr:postcode":"03291",
    "addr:street":"Ptda Altabix",
    "iso:country":"ES",
    "sg:address":"Ptda Altabix, 99",
    "sg:city":"Elche",
    "sg:orig_category":"Art\u00cdculos De Limpieza Y De Cocina (fabricaci\u00d3n, Al Por Mayor)",
    "sg:phone":"+34 965 42 68 83",
    "sg:postcode":"03291",
    "sg:province":"Alicante",
    "wof:name":"Palao Pons Carmelo",
    "wof:placetype":"venue"
},
  "geometry": {"coordinates":[-0.6765189767,38.2994346619],"type":"Point"}
}