{
  "type": "Feature",
  "properties": {
    "iso:country":"ES",
    "sg:address":"Ca\u00f1os, 19",
    "sg:city":"Lucena",
    "sg:orig_category":"Arreglo, Reparaci\u00d3n, Piezas Sueltas De Televisi\u00d3n, V\u00cddeo, Hi",
    "sg:phone":"+34 957 50 23 53",
    "sg:postcode":"14900",
    "sg:province":"C\u00f3rdoba",
    "wof:name":"Lara Romero Jose",
    "wof:placetype":"venue"
},
  "geometry": {"coordinates":[-4.484858036,37.4119186401],"type":"Point"}
}