{
  "type": "Feature",
  "properties": {
    "addr:full":"Urb Poligono Juncaril, S/n Albolote Granada 18220",
    "addr:housenumber":"s / n",
    "addr:postcode":"18220",
    "addr:street":"Urb Poligono Juncaril",
    "iso:country":"ES",
    "sg:address":"Urb Poligono Juncaril, S/n",
    "sg:city":"Albolote",
    "sg:orig_category":"Negocio De Metales No Ferrosos",
    "sg:phone":"+34 958 43 05 09",
    "sg:postcode":"18220",
    "sg:province":"Granada",
    "wof:name":"Gallego Vilar S.a.",
    "wof:placetype":"venue"
},
  "geometry": {"coordinates":[-3.6521849632,37.3158683777],"type":"Point"}
}