{
  "type": "Feature",
  "properties": {
    "addr:full":"Calle de Virgen De Monserrat, 21 Mancha Real Ja\u00e9n 23100",
    "addr:housenumber":"21",
    "addr:postcode":"23100",
    "addr:street":"Calle De Virgen De Monserrat",
    "iso:country":"ES",
    "sg:address":"Calle de Virgen De Monserrat, 21",
    "sg:city":"Mancha Real",
    "sg:orig_category":"Cristaler\u00cdas",
    "sg:phone":"+34 953 35 11 18",
    "sg:postcode":"23100",
    "sg:province":"Ja\u00e9n",
    "wof:name":"Magocrist S.l.",
    "wof:placetype":"venue"
},
  "geometry": {"coordinates":[-3.6047899723,37.7873420715],"type":"Point"}
}