{
  "type": "Feature",
  "properties": {
    "addr:full":"Avda Padre Huidobro, Km. 0012,5 Madrid Madrid 28...",
    "addr:housenumber":"28 ...",
    "addr:street":"Avda Padre Huidobro Km. 0012,5;Madrid",
    "iso:country":"ES",
    "sg:address":"Avda Padre Huidobro, Km. 0012,5",
    "sg:city":"Madrid",
    "sg:orig_category":"Supermercados Y Hipermercados",
    "sg:phone":"+34 917 08 92 00",
    "sg:postcode":"28...",
    "sg:province":"Madrid",
    "sg:website":"www.hipercor.es",
    "wof:name":"Hipercor S.a.",
    "wof:placetype":"venue"
},
  "geometry": {"coordinates":[-3.7057740688,40.42029953],"type":"Point"}
}