{
  "type": "Feature",
  "properties": {
    "iso:country":"ES",
    "sg:address":"Carrer de Comte Gomez De Orbaneja, 18",
    "sg:city":"Segur Calafell",
    "sg:orig_category":"Ropa De Hogar (al Por Menor)",
    "sg:phone":"+34 977 16 04 79",
    "sg:postcode":"43882",
    "sg:province":"Tarragona",
    "wof:name":"Bitassa Ben Enfilada S.l",
    "wof:placetype":"venue"
},
  "geometry": {"coordinates":[1.5981800556,41.2034416199],"type":"Point"}
}