{
  "type": "Feature",
  "properties": {
    "iso:country":"ES",
    "sg:address":"Plaz Altozano, 5",
    "sg:city":"Albacete",
    "sg:orig_category":"Cl\u00cdnicas Dentales",
    "sg:phone":"+34 967 52 12 69",
    "sg:postcode":"02001",
    "sg:province":"Albacete",
    "wof:name":"Prestaciones Odontologicas Albacetenses S.l.",
    "wof:placetype":"venue"
},
  "geometry": {"coordinates":[-1.8544709682,38.9945869446],"type":"Point"}
}