{
  "type": "Feature",
  "properties": {
    "addr:full":"Carrer de Valles, 105 Granollers Barcelona 08401",
    "addr:housenumber":"105",
    "addr:postcode":"08401",
    "addr:street":"Carrer De Valles",
    "iso:country":"ES",
    "sg:address":"Carrer de Valles, 105",
    "sg:city":"Granollers",
    "sg:orig_category":"Institutos M\u00c9dicos",
    "sg:phone":"+34 938 79 07 92",
    "sg:postcode":"08401",
    "sg:province":"Barcelona",
    "wof:name":"Amex S.a.",
    "wof:placetype":"venue"
},
  "geometry": {"coordinates":[2.2865827084,41.6002998352],"type":"Point"}
}