{
  "type": "Feature",
  "properties": {
    "iso:country":"ES",
    "sg:address":"Calle de Hermanos Bohorquez Gomez, 4",
    "sg:city":"Ubrique",
    "sg:orig_category":"Inmobiliaria (agencias)",
    "sg:phone":"+34 956 46 23 80",
    "sg:postcode":"11600",
    "sg:province":"C\u00e1diz",
    "wof:name":"Gestion Inmobiliaria Candela S.l",
    "wof:placetype":"venue"
},
  "geometry": {"coordinates":[-5.4464712143,36.6768836975],"type":"Point"}
}