{
  "type": "Feature",
  "properties": {
    "addr:full":"Carrer de Balmes, 63 Barcelona Barcelona 08007",
    "addr:housenumber":"63",
    "addr:postcode":"08007",
    "addr:street":"Carrer De Balmes",
    "iso:country":"ES",
    "sg:address":"Carrer de Balmes, 63",
    "sg:city":"Barcelona",
    "sg:orig_category":"Dibujantes (diversos)",
    "sg:phone":"+34 934 53 01 50",
    "sg:postcode":"08007",
    "sg:province":"Barcelona",
    "wof:name":"La Llar Del Pi S.c.c.l.",
    "wof:placetype":"venue"
},
  "geometry": {"coordinates":[2.1615629196,41.3899230957],"type":"Point"}
}