{
  "type": "Feature",
  "properties": {
    "addr:full":"Calle de Madrigal De La Vera, 11 Madrid Madrid 28044",
    "addr:housenumber":"11",
    "addr:postcode":"madrid;28044",
    "addr:street":"Calle De Madrigal De La Vera",
    "iso:country":"ES",
    "sg:address":"Calle de Madrigal De La Vera, 11",
    "sg:city":"Madrid",
    "sg:orig_category":"Cer\u00c1micas: Material Y Suministros",
    "sg:phone":"+34 917 05 39 64",
    "sg:postcode":"28044",
    "sg:province":"Madrid",
    "wof:name":"Bedill S.l.",
    "wof:placetype":"venue"
},
  "geometry": {"coordinates":[-3.7798190117,40.3773384094],"type":"Point"}
}