{
  "type": "Feature",
  "properties": {
    "iso:country":"ES",
    "sg:address":"Calle de Gabika Monte, 4",
    "sg:city":"Bilbao",
    "sg:orig_category":"Mensajer\u00cda Express, Portes Internacionales",
    "sg:phone":"+34 944 10 33 66",
    "sg:postcode":"48003",
    "sg:province":"Vizcaya",
    "wof:name":"Tour Mensajeros Bizkaia S.l.",
    "wof:placetype":"venue"
},
  "geometry": {"coordinates":[-2.930918932,43.2483062744],"type":"Point"}
}