{
  "type": "Feature",
  "properties": {
    "iso:country":"ES",
    "sg:address":"Calle de Antonio Canovas Del Castillo, 107",
    "sg:city":"Leganes",
    "sg:orig_category":"Empresas De Carpinter\u00cda Met\u00c1lica",
    "sg:phone":"+34 916 93 08 53",
    "sg:postcode":"28914",
    "sg:province":"Madrid",
    "wof:name":"Fabricacion Ceyma S.l",
    "wof:placetype":"venue"
},
  "geometry": {"coordinates":[-3.7798745632,40.3221282959],"type":"Point"}
}