{
  "type": "Feature",
  "properties": {
    "iso:country":"ES",
    "sg:address":"Plaz Salvador, 4",
    "sg:city":"Valladolid",
    "sg:orig_category":"Internados & Ense\u00d1anza Privada",
    "sg:phone":"+34 983 30 50 11",
    "sg:postcode":"47002",
    "sg:province":"Valladolid",
    "wof:name":"Comunidad En Residencia Esclavas Del Sgdo Corazon De Jesus Provincia De Castilla",
    "wof:placetype":"venue"
},
  "geometry": {"coordinates":[-4.7249178886,41.650592804],"type":"Point"}
}