{
  "type": "Feature",
  "properties": {
    "addr:full":"Calle de Puerto De La Cruz Verde, 4 Madrid Madrid 28045",
    "addr:housenumber":"4",
    "addr:postcode":"28045",
    "addr:street":"Calle De Puerto;Verde",
    "iso:country":"ES",
    "sg:address":"Calle de Puerto De La Cruz Verde, 4",
    "sg:city":"Madrid",
    "sg:orig_category":"Inform\u00c1tica: Consultores",
    "sg:phone":"+34 915 06 06 65",
    "sg:postcode":"28045",
    "sg:province":"Madrid",
    "wof:name":"Netcom Xxi Informatica Y Comunicaciones S.l.",
    "wof:placetype":"venue"
},
  "geometry": {"coordinates":[-3.6875915527,40.3875160217],"type":"Point"}
}