{
  "type": "Feature",
  "properties": {
    "iso:country":"ES",
    "sg:address":"Rbla Mestre Torrents, 85",
    "sg:city":"Roca Valles",
    "sg:orig_category":"Agencias Y Asesores De Publicidad",
    "sg:phone":"+34 938 42 12 30",
    "sg:postcode":"08430",
    "sg:province":"Barcelona",
    "wof:name":"Publiforma 90 S.l.",
    "wof:placetype":"venue"
},
  "geometry": {"coordinates":[2.3248240948,41.5861053467],"type":"Point"}
}