{
  "type": "Feature",
  "properties": {
    "iso:country":"ES",
    "sg:address":"Coto Da Lagoa, S/n",
    "sg:city":"Atios",
    "sg:orig_category":"Explotaci\u00d3n De Canteras",
    "sg:phone":"+34 981 48 62 57",
    "sg:postcode":"15552",
    "sg:province":"A Coru\u00f1a",
    "wof:name":"Veiga Lopez Angel",
    "wof:placetype":"venue"
},
  "geometry": {"coordinates":[-8.1421136856,43.6080055237],"type":"Point"}
}