{
  "type": "Feature",
  "properties": {
    "addr:full":"Calle de Nicolas Estevanez, 20 Arrecife Las Palmas 35500",
    "addr:housenumber":"20",
    "addr:postcode":"35500",
    "addr:street":"Calle De Nicolas Estevanez",
    "iso:country":"ES",
    "sg:address":"Calle de Nicolas Estevanez, 20",
    "sg:city":"Arrecife",
    "sg:orig_category":"Alquiler De Veh\u00cdculos: Turismos Y Utilitarios",
    "sg:phone":"+34 928 81 23 83",
    "sg:postcode":"35500",
    "sg:province":"Las Palmas",
    "wof:name":"Duque Autos S.l.",
    "wof:placetype":"venue"
},
  "geometry": {"coordinates":[-13.5444488525,28.9798851013],"type":"Point"}
}