{
  "type": "Feature",
  "properties": {
    "iso:country":"ES",
    "sg:address":"Carrer de Sant Jaume, 27",
    "sg:city":"Sabadell",
    "sg:orig_category":"Molduras, Junquillos, Listones Y Molduras Perforadas",
    "sg:phone":"+34 937 25 01 42",
    "sg:postcode":"08201",
    "sg:province":"Barcelona",
    "wof:name":"Sant Jaume Catering Sl",
    "wof:placetype":"venue"
},
  "geometry": {"coordinates":[2.1045320034,41.5461807251],"type":"Point"}
}