{
  "type": "Feature",
  "properties": {
    "addr:full":"Calle de Viento, 3 Ontinar Salz Zaragoza 50810",
    "addr:housenumber":"3",
    "addr:postcode":"50810",
    "addr:street":"Calle De Viento",
    "iso:country":"ES",
    "sg:address":"Calle de Viento, 3",
    "sg:city":"Ontinar Salz",
    "sg:orig_category":"Producci\u00d3n, Venta De Productos De Agricultura Biol\u00d3gica",
    "sg:phone":"+34 976 69 30 26",
    "sg:postcode":"50810",
    "sg:province":"Zaragoza",
    "wof:name":"Sociedad Agraria De Transformacion Num 2225 Virgen Del Salz",
    "wof:placetype":"venue"
},
  "geometry": {"coordinates":[-0.7689290047,41.8769378662],"type":"Point"}
}