{
  "type": "Feature",
  "properties": {
    "addr:full":"Prim Tte Alcalde R Zamora, 12 Gelves Sevilla 41120",
    "addr:housenumber":"12",
    "addr:postcode":"41120",
    "addr:street":"R Zamora",
    "iso:country":"ES",
    "sg:address":"Prim Tte Alcalde R Zamora, 12",
    "sg:city":"Gelves",
    "sg:orig_category":"Agencias Y Agentes Comerciales, Representantes",
    "sg:phone":"+34 955 76 20 72",
    "sg:postcode":"41120",
    "sg:province":"Sevilla",
    "wof:name":"Gomez Cid Mercedes",
    "wof:placetype":"venue"
},
  "geometry": {"coordinates":[-6.0273938179,37.3386917114],"type":"Point"}
}