{
  "type": "Feature",
  "properties": {
    "iso:country":"ES",
    "sg:address":"Plaz Socorro Del, S/n",
    "sg:city":"Ronda",
    "sg:orig_category":"Aparcamientos (infraestructuras, Accesorios)",
    "sg:phone":"+34 952 87 73 84",
    "sg:postcode":"29400",
    "sg:province":"M\u00e1laga",
    "wof:name":"Renta Comercial S.a.",
    "wof:placetype":"venue"
},
  "geometry": {"coordinates":[-5.1662788391,36.7417945862],"type":"Point"}
}