{
  "type": "Feature",
  "properties": {
    "iso:country":"ES",
    "sg:address":"Calle de San Anton, 8",
    "sg:city":"Aceuchal",
    "sg:orig_category":"Ingeniero",
    "sg:phone":"+34 924 68 07 76",
    "sg:postcode":"06207",
    "sg:province":"Badajoz",
    "wof:name":"Epsilon Eridani Cb",
    "wof:placetype":"venue"
},
  "geometry": {"coordinates":[-6.4891901016,38.6452522278],"type":"Point"}
}