{
  "type": "Feature",
  "properties": {
    "addr:full":"Calle de Enkartaciones, 12 Barakaldo Vizcaya 48902",
    "addr:housenumber":"12",
    "addr:postcode":"48902",
    "addr:street":"Calle De Enkartaciones",
    "iso:country":"ES",
    "sg:address":"Calle de Enkartaciones, 12",
    "sg:city":"Barakaldo",
    "sg:orig_category":"Molduras, Junquillos, Listones Y Molduras Perforadas",
    "sg:phone":"+34 944 37 55 53",
    "sg:postcode":"48902",
    "sg:province":"Vizcaya",
    "wof:name":"Natalia Martin Hoyos",
    "wof:placetype":"venue"
},
  "geometry": {"coordinates":[-2.9911527634,43.2968635559],"type":"Point"}
}