{
  "type": "Feature",
  "properties": {
    "addr:full":"Calle de Juan Ramon Jimenez (de), S/n Mejorada Campo Madrid 28840",
    "addr:postcode":"28840",
    "addr:street":"Calle De Juan Ramon Jimenez De S / N Mejorada Campo",
    "iso:country":"ES",
    "sg:address":"Calle de Juan Ramon Jimenez (de), S/n",
    "sg:city":"Mejorada Campo",
    "sg:orig_category":"Reciclaje, Tratamiento De Tejidos",
    "sg:phone":"+34 916 79 34 48",
    "sg:postcode":"28840",
    "sg:province":"Madrid",
    "wof:name":"Rivero Solano Daniel",
    "wof:placetype":"venue"
},
  "geometry": {"coordinates":[-3.4855639935,40.3967285156],"type":"Point"}
}