{
  "type": "Feature",
  "properties": {
    "iso:country":"ES",
    "sg:address":"Plaz Caudillo, 2",
    "sg:city":"Pe\u00f1iscola",
    "sg:orig_category":"Art\u00cdculos De Regalo (al Por Menor)",
    "sg:phone":"+34 964 48 00 44",
    "sg:postcode":"12598",
    "sg:province":"Castell\u00f3n",
    "wof:name":"Marketing Y Distribucion Habitania S.l.",
    "wof:placetype":"venue"
},
  "geometry": {"coordinates":[-0.0456800014,39.9851417542],"type":"Point"}
}