{
  "type": "Feature",
  "properties": {
    "iso:country":"ES",
    "sg:address":"Carrer de Parlament, 4",
    "sg:city":"Amposta",
    "sg:orig_category":"Zapatos (al Por Menor)",
    "sg:phone":"+34 977 70 35 01",
    "sg:postcode":"43870",
    "sg:province":"Tarragona",
    "wof:name":"Jimenez Marco Neus",
    "wof:placetype":"venue"
},
  "geometry": {"coordinates":[0.5796300173,40.7113456726],"type":"Point"}
}