{
  "type": "Feature",
  "properties": {
    "iso:country":"ES",
    "sg:address":"C/ Santa Anna, 133",
    "sg:city":"Cerdanyola Valles",
    "sg:orig_category":"Distribuci\u00d3n De Petr\u00d3leo Y Derivados",
    "sg:phone":"+34 935 92 09 40",
    "sg:postcode":"08290",
    "sg:province":"Barcelona",
    "wof:name":"Sabater-nuri Carburants S.a.",
    "wof:placetype":"venue"
},
  "geometry": {"coordinates":[2.1246910095,41.5004844666],"type":"Point"}
}