{
  "type": "Feature",
  "properties": {
    "addr:full":"Pase Rosales, 26 Zaragoza Zaragoza 50008",
    "addr:housenumber":"26",
    "addr:postcode":"50008",
    "addr:street":"Rosales",
    "iso:country":"ES",
    "sg:address":"Pase Rosales, 26",
    "sg:city":"Zaragoza",
    "sg:orig_category":"Ense\u00d1anza, Formaci\u00d3n Profesional: Aprendizaje",
    "sg:phone":"+34 976 42 03 87",
    "sg:postcode":"50008",
    "sg:province":"Zaragoza",
    "wof:name":"Arzobispado De Zaragoza",
    "wof:placetype":"venue"
},
  "geometry": {"coordinates":[-0.8783608079,41.6398887634],"type":"Point"}
}