{
  "type": "Feature",
  "properties": {
    "addr:full":"Avda Buenos Aires-estacion De Guadix, 48 Estacion De Guadix Granada 18500",
    "addr:housenumber":"48",
    "addr:postcode":"18500",
    "addr:street":"Avda Buenos Aires-Estacion;Estacion De;Granada",
    "iso:country":"ES",
    "sg:address":"Avda Buenos Aires-estacion De Guadix, 48",
    "sg:city":"Estacion De Guadix",
    "sg:orig_category":"Sociedades Y Organismos Burs\u00c1tiles",
    "sg:phone":"+34 958 66 54 69",
    "sg:postcode":"18500",
    "sg:province":"Granada",
    "wof:name":"Salamanca Herrera Rosario",
    "wof:placetype":"venue"
},
  "geometry": {"coordinates":[-3.1343688965,37.303894043],"type":"Point"}
}