{
  "type": "Feature",
  "properties": {
    "addr:full":"Carr Dr. Bernadi Font I Quetglas, S/n Sineu Islas Baleares 07510",
    "addr:housenumber":"s / n",
    "addr:postcode":"07510",
    "addr:street":"Carr Dr. Bernadi",
    "iso:country":"ES",
    "sg:address":"Carr Dr. Bernadi Font I Quetglas, S/n",
    "sg:city":"Sineu",
    "sg:orig_category":"Carpinteros",
    "sg:phone":"+34 971 85 50 21",
    "sg:postcode":"07510",
    "sg:province":"Islas Baleares",
    "wof:name":"Carpinteria Pons Sinen S.l.",
    "wof:placetype":"venue"
},
  "geometry": {"coordinates":[3.0153250694,39.6455078125],"type":"Point"}
}