{
  "type": "Feature",
  "properties": {
    "iso:country":"ES",
    "sg:address":"Calle de Santa Teresa, 23",
    "sg:city":"Barraco",
    "sg:orig_category":"Carnicer\u00cdas, Carnicer\u00cdas",
    "sg:phone":"+34 920 28 10 20",
    "sg:postcode":"05110",
    "sg:province":"\u00c1vila",
    "wof:name":"Toribio Arribas Francisco",
    "wof:placetype":"venue"
},
  "geometry": {"coordinates":[-4.6440200806,40.476360321],"type":"Point"}
}