{
  "type": "Feature",
  "properties": {
    "iso:country":"ES",
    "sg:address":"Calle de Tenerife (de), 15",
    "sg:city":"Humanes De Madrid",
    "sg:orig_category":"Animales (al Por Menor)",
    "sg:phone":"+34 916 09 78 10",
    "sg:postcode":"28970",
    "sg:province":"Madrid",
    "wof:name":"Zoo Borneo S.l.",
    "wof:placetype":"venue"
},
  "geometry": {"coordinates":[-3.8165562153,40.2701835632],"type":"Point"}
}