{
  "type": "Feature",
  "properties": {
    "addr:full":"Ctra Playas, S/n Tias Las Palmas 35572",
    "addr:housenumber":"s / n",
    "addr:postcode":"35572",
    "addr:street":"Ctra Playas",
    "iso:country":"ES",
    "sg:address":"Ctra Playas, S/n",
    "sg:city":"Tias",
    "sg:orig_category":"Supermercados Y Hipermercados",
    "sg:phone":"+34 928 51 31 63",
    "sg:postcode":"35572",
    "sg:province":"Las Palmas",
    "wof:name":"Cozerpa S.l.",
    "wof:placetype":"venue"
},
  "geometry": {"coordinates":[-13.6521291733,28.9543895721],"type":"Point"}
}