{
  "type": "Feature",
  "properties": {
    "iso:country":"ES",
    "sg:address":"La Cumbre, S/n",
    "sg:city":"Almerimar",
    "sg:orig_category":"Productos Fitosanitarios (negocio, Aplicaci\u00d3n)",
    "sg:phone":"+34 950 60 77 45",
    "sg:postcode":"04711",
    "sg:province":"Almer\u00eda",
    "wof:name":"Agrar Plantas Del Sur S.a.",
    "wof:placetype":"venue"
},
  "geometry": {"coordinates":[-2.8053731918,36.7086143494],"type":"Point"}
}