{
  "type": "Feature",
  "properties": {
    "iso:country":"ES",
    "sg:address":"Calle de Vazquez De Mella, 31",
    "sg:city":"Madrid",
    "sg:orig_category":"Carb\u00d3n, Carb\u00d3n De Madera (al Por Mayor)",
    "sg:phone":"+34 913 67 74 59",
    "sg:postcode":"28017",
    "sg:province":"Madrid",
    "wof:name":"Romero Diaz Maroto Luis",
    "wof:placetype":"venue"
},
  "geometry": {"coordinates":[-3.6391210556,40.4346008301],"type":"Point"}
}