{
  "type": "Feature",
  "properties": {
    "iso:country":"ES",
    "sg:address":"Calle de Horno, 6",
    "sg:city":"Huetor-santillan",
    "sg:orig_category":"Estancos",
    "sg:phone":"+34 958 54 62 40",
    "sg:postcode":"18183",
    "sg:province":"Granada",
    "wof:name":"Hita Sanchez Pilar",
    "wof:placetype":"venue"
},
  "geometry": {"coordinates":[-3.5174889565,37.2182807922],"type":"Point"}
}