{
  "type": "Feature",
  "properties": {
    "addr:full":"Calle de Maestro Cebrian, 3 Jaen Ja\u00e9n 23008",
    "addr:housenumber":"3;jae\u0301n",
    "addr:postcode":"23008",
    "addr:street":"Calle De Maestro Cebrian",
    "iso:country":"ES",
    "sg:address":"Calle de Maestro Cebrian, 3",
    "sg:city":"Jaen",
    "sg:orig_category":"Estancos",
    "sg:phone":"+34 953 26 35 25",
    "sg:postcode":"23008",
    "sg:province":"Ja\u00e9n",
    "wof:name":"Martinez Garcia Eufrasio Rafael",
    "wof:placetype":"venue"
},
  "geometry": {"coordinates":[-3.7845981121,37.7755432129],"type":"Point"}
}