{
  "type": "Feature",
  "properties": {
    "addr:full":"Calle de Baron Del Solar, 20 Jumilla Murcia 30520",
    "addr:housenumber":"20",
    "addr:postcode":"30520",
    "addr:street":"Calle De Baron Del Solar",
    "iso:country":"ES",
    "sg:address":"Calle de Baron Del Solar, 20",
    "sg:city":"Jumilla",
    "sg:orig_category":"Farmacias",
    "sg:phone":"+34 968 78 23 15",
    "sg:postcode":"30520",
    "sg:province":"Murcia",
    "wof:name":"Mazuelas Garcia Manuel",
    "wof:placetype":"venue"
},
  "geometry": {"coordinates":[-1.3368026018,38.4775047302],"type":"Point"}
}