{
  "type": "Feature",
  "properties": {
    "addr:full":"Rua Cervantes, 20 Foz Lugo 27780",
    "addr:housenumber":"20",
    "addr:postcode":"27780",
    "addr:street":"Rua Cervantes",
    "iso:country":"ES",
    "sg:address":"Rua Cervantes, 20",
    "sg:city":"Foz",
    "sg:orig_category":"Peluqueros: De Se\u00d1oras",
    "sg:phone":"+34 982 13 22 43",
    "sg:postcode":"27780",
    "sg:province":"Lugo",
    "wof:name":"Basanta Neira Jose Luis",
    "wof:placetype":"venue"
},
  "geometry": {"coordinates":[-7.2613739967,43.5743751526],"type":"Point"}
}