{
  "type": "Feature",
  "properties": {
    "iso:country":"ES",
    "sg:address":"Pg Maritim De Comarruga, 33",
    "sg:city":"Barri Maritim De Comarruga",
    "sg:orig_category":"Agencias Y Asesores De Publicidad",
    "sg:phone":"+34 977 68 21 05",
    "sg:postcode":"43880",
    "sg:province":"Tarragona",
    "wof:name":"Millan Calero Javier",
    "wof:placetype":"venue"
},
  "geometry": {"coordinates":[1.5386699438,41.1833496094],"type":"Point"}
}