{
  "type": "Feature",
  "properties": {
    "addr:full":"Pl Alfons Xii (d'), 5 Tortosa Tarragona 43500",
    "addr:housenumber":"5",
    "addr:postcode":"43500",
    "addr:street":"Pl;Xii;'",
    "iso:country":"ES",
    "sg:address":"Pl Alfons Xii (d'), 5",
    "sg:city":"Tortosa",
    "sg:orig_category":"Muebles, Minoristas",
    "sg:phone":"+34 977 44 24 72",
    "sg:postcode":"43500",
    "sg:province":"Tarragona",
    "sg:website":"www.treku.es",
    "wof:name":"Valles Prada Maria Dolores",
    "wof:placetype":"venue"
},
  "geometry": {"coordinates":[0.5228859782,40.8589134216],"type":"Point"}
}