{
  "type": "Feature",
  "properties": {
    "iso:country":"ES",
    "sg:address":"Calle de Brasil, 28",
    "sg:city":"Torrejon Ardoz",
    "sg:orig_category":"Guarder\u00cdas",
    "sg:phone":"+34 916 76 00 14",
    "sg:postcode":"28850",
    "sg:province":"Madrid",
    "wof:name":"Gonzalez Braojos Susana",
    "wof:placetype":"venue"
},
  "geometry": {"coordinates":[-3.4617807865,40.4652519226],"type":"Point"}
}