{
  "type": "Feature",
  "properties": {
    "iso:country":"ES",
    "sg:address":"Calle de Arroyo, 31",
    "sg:city":"Toledo",
    "sg:orig_category":"Compresores",
    "sg:phone":"+34 925 21 15 10",
    "sg:postcode":"45006",
    "sg:province":"Toledo",
    "wof:name":"Excavaciones Guio Acevedo S.l",
    "wof:placetype":"venue"
},
  "geometry": {"coordinates":[-4.0032000542,39.8607978821],"type":"Point"}
}