{
  "type": "Feature",
  "properties": {
    "addr:full":"Centro Comercial Plaza, 16 Nueva Andalucia M\u00e1laga 29660",
    "addr:housenumber":"16",
    "addr:postcode":"29660",
    "addr:street":"Nueva Andalucia Ma\u0301Laga",
    "iso:country":"ES",
    "sg:address":"Centro Comercial Plaza, 16",
    "sg:city":"Nueva Andalucia",
    "sg:orig_category":"Moquetas, Alfombras (al Por Menor)",
    "sg:phone":"+34 952 81 52 42",
    "sg:postcode":"29660",
    "sg:province":"M\u00e1laga",
    "wof:name":"Bazar Shirin S.l.",
    "wof:placetype":"venue"
},
  "geometry": {"coordinates":[-4.9572491646,36.4902381897],"type":"Point"}
}