{
  "type": "Feature",
  "properties": {
    "addr:full":"Avda I(p Campollano), 53 Albacete Albacete 02006",
    "addr:housenumber":"53",
    "addr:postcode":"02006",
    "addr:street":"Avda I P Campollano",
    "iso:country":"ES",
    "sg:address":"Avda I(p Campollano), 53",
    "sg:city":"Albacete",
    "sg:orig_category":"Agentes, Concesionarios Y Sucursales De Veh\u00cdculos",
    "sg:phone":"+34 967 24 79 45",
    "sg:postcode":"02006",
    "sg:province":"Albacete",
    "wof:name":"Grupauto Albacete S.l.",
    "wof:placetype":"venue"
},
  "geometry": {"coordinates":[-1.8999890089,38.9776191711],"type":"Point"}
}