{
  "type": "Feature",
  "properties": {
    "addr:full":"Calle de Diaz Huertas, 9 Cordoba C\u00f3rdoba 14012",
    "addr:housenumber":"9",
    "addr:postcode":"14012",
    "addr:street":"Calle De Diaz Huertas;Co\u0301Rdoba",
    "iso:country":"ES",
    "sg:address":"Calle de Diaz Huertas, 9",
    "sg:city":"Cordoba",
    "sg:orig_category":"Negocio De Materiales De Construcci\u00d3n",
    "sg:phone":"+34 957 27 36 31",
    "sg:postcode":"14012",
    "sg:province":"C\u00f3rdoba",
    "wof:name":"Alicatados Y Pavimentos Cordobeses S.l.",
    "wof:placetype":"venue"
},
  "geometry": {"coordinates":[-4.7793879509,37.9105834961],"type":"Point"}
}