{
  "type": "Feature",
  "properties": {
    "iso:country":"ES",
    "sg:address":"Rua Urogalo, 3",
    "sg:city":"Sarro",
    "sg:orig_category":"Agencias Y Agentes Comerciales, Representantes",
    "sg:phone":"+34 981 66 57 55",
    "sg:postcode":"15176",
    "sg:province":"La Coru\u00f1a",
    "wof:name":"Rodriguez Lamas Jose Fernando",
    "wof:placetype":"venue"
},
  "geometry": {"coordinates":[-8.3265943527,43.3246536255],"type":"Point"}
}