{
  "type": "Feature",
  "properties": {
    "addr:full":"Carrer de L'avenir, 6 Barcelona Barcelona 08006",
    "addr:housenumber":"6",
    "addr:postcode":"08006",
    "addr:street":"Carrer De L'Avenir",
    "iso:country":"ES",
    "sg:address":"Carrer de L'avenir, 6",
    "sg:city":"Barcelona",
    "sg:orig_category":"Audiovisuales (producci\u00d3n, Edici\u00d3n, Realizaci\u00d3n)",
    "sg:phone":"+34 934 58 07 27",
    "sg:postcode":"08006",
    "sg:province":"Barcelona",
    "sg:website":"www.elterrat.com",
    "wof:name":"El Terrat De Produccions S.l.",
    "wof:placetype":"venue"
},
  "geometry": {"coordinates":[2.149749279,41.3975334167],"type":"Point"}
}