{
  "type": "Feature",
  "properties": {
    "addr:full":"Calle de Juan Antonio De La Bella, 27 Antilla Huelva 21449",
    "addr:housenumber":"27",
    "addr:postcode":"21449",
    "addr:street":"Calle De Juan Antonio De La Bella",
    "iso:country":"ES",
    "sg:address":"Calle de Juan Antonio De La Bella, 27",
    "sg:city":"Antilla",
    "sg:orig_category":"M\u00c9dicos: Estomatolog\u00cda",
    "sg:phone":"+34 959 48 07 91",
    "sg:postcode":"21449",
    "sg:province":"Huelva",
    "wof:name":"Carrasco Marquez Jose",
    "wof:placetype":"venue"
},
  "geometry": {"coordinates":[-7.2120881081,37.2059059143],"type":"Point"}
}