{
  "type": "Feature",
  "properties": {
    "addr:full":"Calle de Orense, 10 Alacant Alicante 03003",
    "addr:housenumber":"10",
    "addr:postcode":"03003",
    "addr:street":"Calle De Orense",
    "iso:country":"ES",
    "sg:address":"Calle de Orense, 10",
    "sg:city":"Alacant",
    "sg:orig_category":"Desinfecci\u00d3n, Desinsectaci\u00d3n, Desratizaci\u00d3n",
    "sg:phone":"+34 965 22 91 26",
    "sg:postcode":"03003",
    "sg:province":"Alicante",
    "wof:name":"Kurylek De March Zofia",
    "wof:placetype":"venue"
},
  "geometry": {"coordinates":[-0.4904710054,38.3396034241],"type":"Point"}
}