{
  "type": "Feature",
  "properties": {
    "addr:full":"Calle de Palleter, 65 Valencia Valencia 46008",
    "addr:housenumber":"65",
    "addr:postcode":"46008",
    "addr:street":"Calle De Palleter",
    "iso:country":"ES",
    "sg:address":"Calle de Palleter, 65",
    "sg:city":"Valencia",
    "sg:orig_category":"Importaci\u00d3n",
    "sg:phone":"+34 963 82 28 66",
    "sg:postcode":"46008",
    "sg:province":"Valencia",
    "wof:name":"Benser Optic S.l.",
    "wof:placetype":"venue"
},
  "geometry": {"coordinates":[-0.388722986,39.4722175598],"type":"Point"}
}