{
  "type": "Feature",
  "properties": {
    "addr:full":"Avda Portugal, 38 Ba\u00d1eza Le\u00f3n 24750",
    "addr:housenumber":"38",
    "addr:postcode":"24750",
    "addr:street":"Avda Portugal;Leo\u0301N",
    "iso:country":"ES",
    "sg:address":"Avda Portugal, 38",
    "sg:city":"Ba\u00d1eza",
    "sg:orig_category":"M\u00c1rmoles, Granitos Y Piedras Naturales",
    "sg:phone":"+34 987 64 26 30",
    "sg:postcode":"24750",
    "sg:province":"Le\u00f3n",
    "wof:name":"Calvo Rodriguez Candido",
    "wof:placetype":"venue"
},
  "geometry": {"coordinates":[-5.9242091179,42.3069114685],"type":"Point"}
}