{
  "type": "Feature",
  "properties": {
    "iso:country":"ES",
    "sg:address":"Rua Juan Xxiii, 19",
    "sg:city":"Ourense",
    "sg:orig_category":"Centros P\u00dablicos De Formaci\u00d3n Profesional Y T\u00c9cnica",
    "sg:phone":"+34 988 21 09 33",
    "sg:postcode":"32003",
    "sg:province":"Ourense",
    "wof:name":"Colegio Oficial De Medicos De Ourense",
    "wof:placetype":"venue"
},
  "geometry": {"coordinates":[-7.8655920029,42.3411941528],"type":"Point"}
}