{
  "type": "Feature",
  "properties": {
    "iso:country":"ES",
    "sg:address":"Carrer de Girona, 213",
    "sg:city":"Terrassa",
    "sg:orig_category":"Panader\u00cdas, Panader\u00cdas",
    "sg:phone":"+34 937 85 51 92",
    "sg:postcode":"08226",
    "sg:province":"Barcelona",
    "wof:name":"Pasteleria Paris S.l.",
    "wof:placetype":"venue"
},
  "geometry": {"coordinates":[2.022480011,41.5763282776],"type":"Point"}
}