{
  "type": "Feature",
  "properties": {
    "iso:country":"ES",
    "sg:address":"Avda Lope De Figueroa, 27",
    "sg:city":"Alcala Henares",
    "sg:orig_category":"Art\u00cdculos De Regalo (al Por Menor)",
    "sg:phone":"+34 918 83 27 42",
    "sg:postcode":"28804",
    "sg:province":"Madrid",
    "wof:name":"Cesped C.b.",
    "wof:placetype":"venue"
},
  "geometry": {"coordinates":[-3.3535780907,40.4836578369],"type":"Point"}
}