{
  "type": "Feature",
  "properties": {
    "addr:full":"Calle de San Jose, 76 San Jose Rinconada Sevilla 41300",
    "addr:postcode":"41300",
    "addr:street":"Calle De San;76",
    "iso:country":"ES",
    "sg:address":"Calle de San Jose, 76",
    "sg:city":"San Jose Rinconada",
    "sg:orig_category":"Bancos",
    "sg:phone":"+34 954 79 03 00",
    "sg:postcode":"41300",
    "sg:province":"Sevilla",
    "sg:website":"www.bancoandalucia.es",
    "wof:name":"Banco De Andalucia",
    "wof:placetype":"venue"
},
  "geometry": {"coordinates":[-5.9436969757,37.4820594788],"type":"Point"}
}