{
  "type": "Feature",
  "properties": {
    "addr:full":"Carr Riumors, S/n Figueres Girona 17600",
    "addr:housenumber":"s",
    "addr:postcode":"17600",
    "addr:street":"Carr Riumors;/ N",
    "iso:country":"ES",
    "sg:address":"Carr Riumors, S/n",
    "sg:city":"Figueres",
    "sg:orig_category":"Peluquer\u00cdas, Peluquer\u00cda Mixta",
    "sg:phone":"+34 972 67 38 04",
    "sg:postcode":"17600",
    "sg:province":"Girona",
    "wof:name":"Ruiz Garcia Concepcion",
    "wof:placetype":"venue"
},
  "geometry": {"coordinates":[2.9681251049,42.2621154785],"type":"Point"}
}