{
  "type": "Feature",
  "properties": {
    "iso:country":"ES",
    "sg:address":"Calle de Alday, S/n",
    "sg:city":"Malia\u00d1o",
    "sg:orig_category":"Edici\u00d3n De Diarios, Revistas, Boletines",
    "sg:phone":"+34 942 25 12 38",
    "sg:postcode":"39600",
    "sg:province":"Cantabria",
    "wof:name":"Sistemas Tecnicos De Loterias Del Estado",
    "wof:placetype":"venue"
},
  "geometry": {"coordinates":[-3.8376090527,43.4216461182],"type":"Point"}
}