{
  "type": "Feature",
  "properties": {
    "addr:full":"Cmno Consuegra, S/n Urda Toledo 45480",
    "addr:housenumber":"s / n",
    "addr:postcode":"45480",
    "addr:street":"Cmno Consuegra",
    "iso:country":"ES",
    "sg:address":"Cmno Consuegra, S/n",
    "sg:city":"Urda",
    "sg:orig_category":"Empresas De Carpinter\u00cda De Madera",
    "sg:phone":"+34 925 47 40 49",
    "sg:postcode":"45480",
    "sg:province":"Toledo",
    "wof:name":"Terminaciones En Madera Leyma S.l.",
    "wof:placetype":"venue"
},
  "geometry": {"coordinates":[-3.716504097,39.4137649536],"type":"Point"}
}