{
  "type": "Feature",
  "properties": {
    "iso:country":"ES",
    "sg:address":"Calle de Gran Canaria (de), 21",
    "sg:city":"Humanes De Madrid",
    "sg:orig_category":"Colchones (fabricaci\u00d3n, Al Por Mayor, Al Por Menor)",
    "sg:phone":"+34 916 90 71 57",
    "sg:postcode":"28970",
    "sg:province":"Madrid",
    "wof:name":"Decoracion Y Descanso S.l.",
    "wof:placetype":"venue"
},
  "geometry": {"coordinates":[-3.8148839474,40.2722206116],"type":"Point"}
}