{
  "type": "Feature",
  "properties": {
    "addr:full":"Carr Lleida, 146 Alpicat Lleida 25110",
    "addr:housenumber":"146",
    "addr:postcode":"25110",
    "addr:street":"Carr Lleida",
    "iso:country":"ES",
    "sg:address":"Carr Lleida, 146",
    "sg:city":"Alpicat",
    "sg:orig_category":"Molduras, Junquillos, Listones Y Molduras Perforadas",
    "sg:phone":"+34 973 73 74 28",
    "sg:postcode":"25110",
    "sg:province":"Lleida",
    "wof:name":"Fernandez Sanchez Josefa",
    "wof:placetype":"venue"
},
  "geometry": {"coordinates":[0.5297340155,41.6597290039],"type":"Point"}
}