{
  "type": "Feature",
  "properties": {
    "addr:full":"Plaz Constitucion, 12 Nore\u00f1a Asturias 33180",
    "addr:housenumber":"12",
    "addr:postcode":"33180",
    "addr:street":"Constitucion;Asturias",
    "iso:country":"ES",
    "sg:address":"Plaz Constitucion, 12",
    "sg:city":"Nore\u00f1a",
    "sg:orig_category":"Promotores Constructores",
    "sg:phone":"+34 985 74 16 90",
    "sg:postcode":"33180",
    "sg:province":"Asturias",
    "wof:name":"Promociones Alfre S.l.",
    "wof:placetype":"venue"
},
  "geometry": {"coordinates":[-5.7067170143,43.394115448],"type":"Point"}
}