{
  "type": "Feature",
  "properties": {
    "addr:full":"Calle de Pilar, S/n Palomar De Arroyos Teruel 44708",
    "addr:housenumber":"s / n",
    "addr:postcode":"44708",
    "addr:street":"Calle De Pilar",
    "iso:country":"ES",
    "sg:address":"Calle de Pilar, S/n",
    "sg:city":"Palomar De Arroyos",
    "sg:orig_category":"Transportes Por V\u00cdas Navegables",
    "sg:phone":"+34 978 75 31 15",
    "sg:postcode":"44708",
    "sg:province":"Teruel",
    "wof:name":"Andres Lafuente Nemesio",
    "wof:placetype":"venue"
},
  "geometry": {"coordinates":[-0.7512179017,40.7799186707],"type":"Point"}
}