{
  "type": "Feature",
  "properties": {
    "iso:country":"ES",
    "sg:address":"Calle de Miguel De Unamuno, 32",
    "sg:city":"Palencia",
    "sg:orig_category":"Fabricaci\u00d3n, Venta, Instalaci\u00d3n De R\u00d3tulos, De R\u00d3tulos Luminosos",
    "sg:phone":"+34 979 71 04 52",
    "sg:postcode":"34004",
    "sg:province":"Palencia",
    "wof:name":"Rodriguez Vivar Miguel Angel",
    "wof:placetype":"venue"
},
  "geometry": {"coordinates":[-4.5202789307,42.003238678],"type":"Point"}
}