{
  "type": "Feature",
  "properties": {
    "iso:country":"ES",
    "sg:address":"Calle de General Benavent Garcia, 9",
    "sg:city":"Alcazar S. Juan",
    "sg:orig_category":"Electrodom\u00c9sticos (fabricaci\u00d3n, Al Por Mayor)",
    "sg:phone":"+34 926 54 11 06",
    "sg:postcode":"13600",
    "sg:province":"Ciudad Real",
    "wof:name":"Tajuelo Pe\u00f1uela Antonio",
    "wof:placetype":"venue"
},
  "geometry": {"coordinates":[-3.2147490978,39.3913040161],"type":"Point"}
}