{
  "type": "Feature",
  "properties": {
    "iso:country":"ES",
    "sg:address":"Carrer de Sant Pere, 35",
    "sg:city":"Constanti",
    "sg:orig_category":"Chapister\u00cda",
    "sg:phone":"+34 977 52 19 30",
    "sg:postcode":"43120",
    "sg:province":"Tarragona",
    "wof:name":"Carrocerias Masdeu S.l.",
    "wof:placetype":"venue"
},
  "geometry": {"coordinates":[1.2125480175,41.1523361206],"type":"Point"}
}