{
  "type": "Feature",
  "properties": {
    "addr:full":"Cra Malaga-cadiz, S/n Mijas Costa M\u00e1laga 29649",
    "addr:housenumber":"s / n",
    "addr:postcode":"29649",
    "iso:country":"ES",
    "sg:address":"Cra Malaga-cadiz, S/n",
    "sg:city":"Mijas Costa",
    "sg:orig_category":"Supermercados Y Hipermercados",
    "sg:phone":"+34 952 93 19 97",
    "sg:postcode":"29649",
    "sg:province":"M\u00e1laga",
    "wof:name":"G.m. Supermercados S.l.",
    "wof:placetype":"venue"
},
  "geometry": {"coordinates":[-4.7338290215,36.4882316589],"type":"Point"}
}