{
  "type": "Feature",
  "properties": {
    "addr:full":"Avda Estacion, 7 Madrid Madrid 28023",
    "addr:housenumber":"7",
    "addr:postcode":"madrid;28023",
    "addr:street":"Avda Estacion",
    "iso:country":"ES",
    "sg:address":"Avda Estacion, 7",
    "sg:city":"Madrid",
    "sg:orig_category":"Inmobiliaria (agencias)",
    "sg:phone":"+34 913 07 70 76",
    "sg:postcode":"28023",
    "sg:province":"Madrid",
    "wof:name":"Serna Sanchez Margarita",
    "wof:placetype":"venue"
},
  "geometry": {"coordinates":[-3.8365619183,40.4737968445],"type":"Point"}
}