{
  "type": "Feature",
  "properties": {
    "addr:full":"Calle de Pais Valencia, 61 Borriol Castell\u00f3n 12190",
    "addr:housenumber":"61",
    "addr:postcode":"12190",
    "addr:street":"Calle De Pais Valencia",
    "iso:country":"ES",
    "sg:address":"Calle de Pais Valencia, 61",
    "sg:city":"Borriol",
    "sg:orig_category":"Bazares, Art\u00cdculos De Limpieza Y De Cocina (al Por Menor)",
    "sg:phone":"+34 964 32 11 72",
    "sg:postcode":"12190",
    "sg:province":"Castell\u00f3n",
    "wof:name":"Bazar La Torre C.b",
    "wof:placetype":"venue"
},
  "geometry": {"coordinates":[-0.0724899992,40.0421943665],"type":"Point"}
}