{
  "type": "Feature",
  "properties": {
    "addr:full":"Avda Concepcion Arenal, S/n Praia Pontevedra 36950",
    "addr:housenumber":"s / n",
    "addr:postcode":"36950",
    "addr:street":"Avda Concepcion Arenal",
    "iso:country":"ES",
    "sg:address":"Avda Concepcion Arenal, S/n",
    "sg:city":"Praia",
    "sg:orig_category":"Carnicer\u00cdas, Carnicer\u00cdas",
    "sg:phone":"+34 986 31 29 88",
    "sg:postcode":"36950",
    "sg:province":"Pontevedra",
    "wof:name":"Soaje Portela Juan Diego",
    "wof:placetype":"venue"
},
  "geometry": {"coordinates":[-8.738442421,42.2772254944],"type":"Point"}
}