{
  "type": "Feature",
  "properties": {
    "addr:full":"Ctra Cobre (al), S/n Algeciras C\u00e1diz 11206",
    "addr:housenumber":"s / n;ca\u0301diz",
    "addr:postcode":"11206",
    "addr:street":"Ctra Cobre Al",
    "iso:country":"ES",
    "sg:address":"Ctra Cobre (al), S/n",
    "sg:city":"Algeciras",
    "sg:orig_category":"Institutos M\u00c9dicos",
    "sg:phone":"+34 956 58 03 26",
    "sg:postcode":"11206",
    "sg:province":"C\u00e1diz",
    "wof:name":"Servicio Andaluz De Salud",
    "wof:placetype":"venue"
},
  "geometry": {"coordinates":[-5.4568829536,36.1133422852],"type":"Point"}
}