{
  "type": "Feature",
  "properties": {
    "addr:full":"Calle de Pedreras, 144 Linea De La Concepcion C\u00e1diz 11300",
    "addr:housenumber":"144",
    "addr:postcode":"11300",
    "addr:street":"Calle De Pedreras;Ca\u0301Diz",
    "iso:country":"ES",
    "sg:address":"Calle de Pedreras, 144",
    "sg:city":"Linea De La Concepcion",
    "sg:orig_category":"Cristaler\u00cdas",
    "sg:phone":"+34 956 76 30 08",
    "sg:postcode":"11300",
    "sg:province":"C\u00e1diz",
    "wof:name":"Cristaleria Mocasa S.l.",
    "wof:placetype":"venue"
},
  "geometry": {"coordinates":[-5.3560957909,36.1685295105],"type":"Point"}
}