{
  "type": "Feature",
  "properties": {
    "addr:full":"Ctra Cordoba-malaga, Km. 0043,0 Montilla C\u00f3rdoba 14550",
    "addr:postcode":"14550",
    "addr:street":"Ctra Cordoba-Malaga Km. 0043,0;Co\u0301Rdoba",
    "iso:country":"ES",
    "sg:address":"Ctra Cordoba-malaga, Km. 0043,0",
    "sg:city":"Montilla",
    "sg:orig_category":"Mec\u00c1nico Del Autom\u00d3vil",
    "sg:phone":"+34 957 66 43 59",
    "sg:postcode":"14550",
    "sg:province":"C\u00f3rdoba",
    "wof:name":"Talleres Luque Mu\u00d1oz Sl",
    "wof:placetype":"venue"
},
  "geometry": {"coordinates":[-4.6605410576,37.5884437561],"type":"Point"}
}