{
  "type": "Feature",
  "properties": {
    "iso:country":"ES",
    "sg:address":"Calle de Carretero, 63",
    "sg:city":"Coria Rio",
    "sg:orig_category":"Pescader\u00cdas (al Por Menor)",
    "sg:phone":"+34 954 77 63 37",
    "sg:postcode":"41100",
    "sg:province":"Sevilla",
    "wof:name":"Pineda Herrera Ismael",
    "wof:placetype":"venue"
},
  "geometry": {"coordinates":[-6.0597596169,37.2877807617],"type":"Point"}
}