{
  "type": "Feature",
  "properties": {
    "addr:full":"Avda Fragoso, 28 Vigo Pontevedra 36210",
    "addr:housenumber":"28",
    "addr:postcode":"36210",
    "addr:street":"Avda Fragoso",
    "iso:country":"ES",
    "sg:address":"Avda Fragoso, 28",
    "sg:city":"Vigo",
    "sg:orig_category":"Tapicer\u00cdas",
    "sg:phone":"+34 986 21 16 00",
    "sg:postcode":"36210",
    "sg:province":"Pontevedra",
    "wof:name":"Rial Estevez Maria Josefina",
    "wof:placetype":"venue"
},
  "geometry": {"coordinates":[-8.7340326309,42.2183647156],"type":"Point"}
}