{
  "type": "Feature",
  "properties": {
    "iso:country":"ES",
    "sg:address":"Calle de Isabel La Catolica, 1",
    "sg:city":"Aguilas",
    "sg:orig_category":"Loter\u00cda Y T\u00d3mbola",
    "sg:phone":"+34 968 44 78 80",
    "sg:postcode":"30880",
    "sg:province":"Murcia",
    "wof:name":"Cazorla Sicilia Dolores",
    "wof:placetype":"venue"
},
  "geometry": {"coordinates":[-1.5819280148,37.4033737183],"type":"Point"}
}