{
  "type": "Feature",
  "properties": {
    "iso:country":"ES",
    "sg:address":"Carr Bisbe Ramon De Torrella, 1",
    "sg:city":"Muro",
    "sg:orig_category":"Iglesia Cat\u00d3lica",
    "sg:phone":"+34 971 53 70 22",
    "sg:postcode":"07440",
    "sg:province":"Islas Baleares",
    "wof:name":"Obispado De Mallorca",
    "wof:placetype":"venue"
},
  "geometry": {"coordinates":[3.0578100681,39.7373886108],"type":"Point"}
}