{
  "type": "Feature",
  "properties": {
    "iso:country":"ES",
    "sg:address":"Carr Doctor Valenti, 1",
    "sg:city":"Torroella Montgri",
    "sg:orig_category":"M\u00c9dicos: Estomatolog\u00cda",
    "sg:phone":"+34 972 75 72 16",
    "sg:postcode":"17257",
    "sg:province":"Girona",
    "wof:name":"Hontangas Canela Joan",
    "wof:placetype":"venue"
},
  "geometry": {"coordinates":[3.1034500599,42.0303268433],"type":"Point"}
}