{
  "type": "Feature",
  "properties": {
    "iso:country":"ES",
    "sg:address":"Calle de Colon, 12",
    "sg:city":"Miajadas",
    "sg:orig_category":"Electricidad: Instaladores",
    "sg:phone":"+34 927 16 06 21",
    "sg:postcode":"10100",
    "sg:province":"C\u00e1ceres",
    "wof:name":"Moreno Calvo Alcira",
    "wof:placetype":"venue"
},
  "geometry": {"coordinates":[-5.9089479446,39.1534042358],"type":"Point"}
}