{
  "type": "Feature",
  "properties": {
    "iso:country":"ES",
    "sg:address":"Calle de Cervantes, 95",
    "sg:city":"Pto. Rosario",
    "sg:orig_category":"Empresas De Carpinter\u00cda",
    "sg:phone":"+34 928 85 89 09",
    "sg:postcode":"35600",
    "sg:province":"Las Palmas",
    "wof:name":"Helyo's S.c.p.",
    "wof:placetype":"venue"
},
  "geometry": {"coordinates":[-13.8691720963,28.5004138947],"type":"Point"}
}