{
  "type": "Feature",
  "properties": {
    "addr:full":"Calle de San Bernardo, 19 Gijon Asturias 33201",
    "addr:housenumber":"19",
    "addr:postcode":"33201",
    "addr:street":"Calle De San Bernardo",
    "iso:country":"ES",
    "sg:address":"Calle de San Bernardo, 19",
    "sg:city":"Gijon",
    "sg:orig_category":"Art\u00cdculos De Decoraci\u00d3n",
    "sg:phone":"+34 985 34 50 60",
    "sg:postcode":"33201",
    "sg:province":"Asturias",
    "wof:name":"Carballo Quiros Maria Carmen",
    "wof:placetype":"venue"
},
  "geometry": {"coordinates":[-5.6618437767,43.543346405],"type":"Point"}
}