{
  "type": "Feature",
  "properties": {
    "addr:full":"Carr Teodor Canet, 4 Port D'alcudia Islas Baleares 07410",
    "addr:housenumber":"4",
    "addr:postcode":"07410",
    "addr:street":"Carr Teodor Canet",
    "iso:country":"ES",
    "sg:address":"Carr Teodor Canet, 4",
    "sg:city":"Port D'alcudia",
    "sg:orig_category":"Estancos",
    "sg:phone":"+34 971 54 81 69",
    "sg:postcode":"07410",
    "sg:province":"Islas Baleares",
    "wof:name":"Jofre Esto\u00f1xo Angela Maria",
    "wof:placetype":"venue"
},
  "geometry": {"coordinates":[3.1319789886,39.8451919556],"type":"Point"}
}