{
  "type": "Feature",
  "properties": {
    "addr:full":"Calle de Sotillo, 23 Madrid Madrid 28043",
    "addr:housenumber":"23",
    "addr:postcode":"madrid;28043",
    "addr:street":"Calle De Sotillo",
    "iso:country":"ES",
    "sg:address":"Calle de Sotillo, 23",
    "sg:city":"Madrid",
    "sg:orig_category":"Asesor\u00cda Sobre Comunicaci\u00d3n De Empresas",
    "sg:phone":"+34 917 59 43 55",
    "sg:postcode":"28043",
    "sg:province":"Madrid",
    "wof:name":"Trading Y Consultoria Internacional S.l.",
    "wof:placetype":"venue"
},
  "geometry": {"coordinates":[-3.6373150349,40.4572944641],"type":"Point"}
}