{
  "type": "Feature",
  "properties": {
    "iso:country":"ES",
    "sg:address":"Calle de Escultor Jose Capuz, 35",
    "sg:city":"Valencia",
    "sg:orig_category":"Panader\u00cdas, Panader\u00cdas",
    "sg:phone":"+34 963 33 33 38",
    "sg:postcode":"46006",
    "sg:province":"Valencia",
    "wof:name":"Panaderia Chari Cb",
    "wof:placetype":"venue"
},
  "geometry": {"coordinates":[-0.3608630002,39.4593353271],"type":"Point"}
}