{
  "type": "Feature",
  "properties": {
    "addr:full":"C/ Illueca, S/n Elche Alicante 03205",
    "addr:housenumber":"s / n",
    "addr:postcode":"03205",
    "addr:street":"C / Illueca",
    "iso:country":"ES",
    "sg:address":"C/ Illueca, S/n",
    "sg:city":"Elche",
    "sg:orig_category":"Zapatos: Material, Suministros, Accesorios (fabricaci\u00d3n, Al Por Mayor)",
    "sg:phone":"+34 965 43 78 41",
    "sg:postcode":"03205",
    "sg:province":"Alicante",
    "wof:name":"Mercantil Aparados Caridad S.l.",
    "wof:placetype":"venue"
},
  "geometry": {"coordinates":[-0.7135660052,38.2803993225],"type":"Point"}
}