{
  "type": "Feature",
  "properties": {
    "addr:full":"Carrer de Rossello, 257 Barcelona Barcelona 08008",
    "addr:housenumber":"257",
    "addr:postcode":"08008",
    "addr:street":"Carrer De Rossello",
    "iso:country":"ES",
    "sg:address":"Carrer de Rossello, 257",
    "sg:city":"Barcelona",
    "sg:orig_category":"Centros Empresariales",
    "sg:phone":"+34 932 17 87 98",
    "sg:postcode":"08008",
    "sg:province":"Barcelona",
    "wof:name":"Sphere Finance S.l.",
    "wof:placetype":"venue"
},
  "geometry": {"coordinates":[2.1597900391,41.395362854],"type":"Point"}
}