{
  "type": "Feature",
  "properties": {
    "addr:full":"G.v. Marques Del Turia, 52 Valencia Valencia 46005",
    "addr:housenumber":"52",
    "addr:postcode":"46005",
    "addr:street":"Turia",
    "iso:country":"ES",
    "sg:address":"G.v. Marques Del Turia, 52",
    "sg:city":"Valencia",
    "sg:orig_category":"Promotores Constructores",
    "sg:phone":"+34 963 33 09 67",
    "sg:postcode":"46005",
    "sg:province":"Valencia",
    "wof:name":"Pevasa 21, S.a.",
    "wof:placetype":"venue"
},
  "geometry": {"coordinates":[-0.3682810068,39.4669265747],"type":"Point"}
}