{
  "type": "Feature",
  "properties": {
    "iso:country":"ES",
    "sg:address":"Ctra. Madrid-plasencia, Km. 0100,2",
    "sg:city":"Mijares",
    "sg:orig_category":"Cerrajer\u00cda, Ferrallista",
    "sg:phone":"+34 920 37 71 01",
    "sg:postcode":"05461",
    "sg:province":"\u00c1vila",
    "wof:name":"Sanchez Manzano Urbano",
    "wof:placetype":"venue"
},
  "geometry": {"coordinates":[-4.8363962173,40.2978515625],"type":"Point"}
}