{
  "type": "Feature",
  "properties": {
    "iso:country":"ES",
    "sg:address":"Calle de Infante Don Fernando, 43",
    "sg:city":"Antequera",
    "sg:orig_category":"Centros Empresariales",
    "sg:phone":"+34 952 70 52 34",
    "sg:postcode":"29200",
    "sg:province":"M\u00e1laga",
    "sg:website":"www.araldi.es",
    "wof:name":"Araldi S.l.",
    "wof:placetype":"venue"
},
  "geometry": {"coordinates":[-4.5625152588,37.0190353394],"type":"Point"}
}