{
  "type": "Feature",
  "properties": {
    "iso:country":"ES",
    "sg:address":"Avda Mariano Vicen, 27",
    "sg:city":"Soria",
    "sg:orig_category":"Reposter\u00cdas",
    "sg:phone":"+34 975 21 49 80",
    "sg:postcode":"42003",
    "sg:province":"Soria",
    "wof:name":"Emilio Garcia Anton S.c",
    "wof:placetype":"venue"
},
  "geometry": {"coordinates":[-2.4696559906,41.7597312927],"type":"Point"}
}