{
  "type": "Feature",
  "properties": {
    "addr:full":"Zurrupitieta Kalea, 26 Jundiz \u00c1lava 01015",
    "addr:housenumber":"26",
    "addr:postcode":"01015",
    "addr:street":"Zurrupitieta Kalea;A\u0301Lava",
    "iso:country":"ES",
    "sg:address":"Zurrupitieta Kalea, 26",
    "sg:city":"Jundiz",
    "sg:orig_category":"Servicios Diversos",
    "sg:phone":"+34 945 29 08 36",
    "sg:postcode":"01015",
    "sg:province":"\u00c1lava",
    "sg:website":"www.escor.es",
    "wof:name":"Contenedores Escor Vitoria S. L.",
    "wof:placetype":"venue"
},
  "geometry": {"coordinates":[-2.7296190262,42.8452186584],"type":"Point"}
}