{
  "type": "Feature",
  "properties": {
    "addr:full":"Calle de Alhondiga (la), 19 Sahagun Le\u00f3n 24320",
    "addr:housenumber":"19",
    "addr:postcode":"24320",
    "addr:street":"Calle De Alhondiga La;Leo\u0301N",
    "iso:country":"ES",
    "sg:address":"Calle de Alhondiga (la), 19",
    "sg:city":"Sahagun",
    "sg:orig_category":"Asesor\u00cda Fiscal Y Jur\u00cddica",
    "sg:phone":"+34 987 78 02 13",
    "sg:postcode":"24320",
    "sg:province":"Le\u00f3n",
    "wof:name":"Rivera Fernandez Luis Angel",
    "wof:placetype":"venue"
},
  "geometry": {"coordinates":[-5.0296158791,42.3721733093],"type":"Point"}
}