{
  "type": "Feature",
  "properties": {
    "iso:country":"ES",
    "sg:address":"Carrer de Major, 55",
    "sg:city":"Riudoms",
    "sg:orig_category":"Asesor\u00cda Fiscal Y Jur\u00cddica",
    "sg:phone":"+34 977 76 84 95",
    "sg:postcode":"43330",
    "sg:province":"Tarragona",
    "wof:name":"Carbonell Associats Proces Dades",
    "wof:placetype":"venue"
},
  "geometry": {"coordinates":[1.0512479544,41.1377944946],"type":"Point"}
}