{
  "type": "Feature",
  "properties": {
    "addr:full":"Estd Balneario (do), 106 Verin Ourense 32600",
    "addr:housenumber":"106",
    "addr:postcode":"32600",
    "addr:street":"Verin Ourense",
    "iso:country":"ES",
    "sg:address":"Estd Balneario (do), 106",
    "sg:city":"Verin",
    "sg:orig_category":"Hoteles",
    "sg:phone":"+34 988 41 02 80",
    "sg:postcode":"32600",
    "sg:province":"Ourense",
    "wof:name":"Os Amigos S.c.",
    "wof:placetype":"venue"
},
  "geometry": {"coordinates":[-7.435254097,41.9402198792],"type":"Point"}
}