{
  "type": "Feature",
  "properties": {
    "iso:country":"ES",
    "sg:address":"Calle de Cristobal Lozano, S/n",
    "sg:city":"Hellin",
    "sg:orig_category":"Alquiler De V\u00cddeo",
    "sg:phone":"+34 967 30 12 39",
    "sg:postcode":"02400",
    "sg:province":"Albacete",
    "wof:name":"Gestion Del Video 10 S.l.",
    "wof:placetype":"venue"
},
  "geometry": {"coordinates":[-1.7007023096,38.5067481995],"type":"Point"}
}