{
  "type": "Feature",
  "properties": {
    "addr:full":"Cra Madrid-cadiz-pi Valderrepiso, S/n Bailen Ja\u00e9n 23710",
    "addr:housenumber":"s",
    "addr:postcode":"23710",
    "addr:street":"/ N;Jae\u0301N",
    "iso:country":"ES",
    "sg:address":"Cra Madrid-cadiz-pi Valderrepiso, S/n",
    "sg:city":"Bailen",
    "sg:orig_category":"Suministros Para Carrocer\u00cdas",
    "sg:phone":"+34 953 67 82 82",
    "sg:postcode":"23710",
    "sg:province":"Ja\u00e9n",
    "wof:name":"Mecanica Sagosa De Bailen S.l.",
    "wof:placetype":"venue"
},
  "geometry": {"coordinates":[-3.7710540295,38.0965309143],"type":"Point"}
}