{
  "type": "Feature",
  "properties": {
    "iso:country":"ES",
    "sg:address":"San Martin, 11",
    "sg:city":"Rey Aurelio",
    "sg:orig_category":"Fabricaci\u00d3n, Alquiler, Venta De Encofrados",
    "sg:phone":"+34 985 65 65 75",
    "sg:postcode":"33958",
    "sg:province":"Asturias",
    "wof:name":"Encofrados Blimea S.l.",
    "wof:placetype":"venue"
},
  "geometry": {"coordinates":[-5.621175766,43.2832641602],"type":"Point"}
}