{
  "type": "Feature",
  "properties": {
    "iso:country":"ES",
    "sg:address":"El Ferrocarril, S/n",
    "sg:city":"Camas",
    "sg:orig_category":"Reciclaje Y Tratamiento De Desechos Varios",
    "sg:phone":"+34 955 98 00 71",
    "sg:postcode":"41900",
    "sg:province":"Sevilla",
    "wof:name":"Ayuntamiento De Camas",
    "wof:placetype":"venue"
},
  "geometry": {"coordinates":[-6.0368289948,37.4029541016],"type":"Point"}
}