{
  "type": "Feature",
  "properties": {
    "iso:country":"ES",
    "sg:address":"Calle de Estacion, 72",
    "sg:city":"Tomelloso",
    "sg:orig_category":"Vinos Y Licores (venta Al Por Menor)",
    "sg:phone":"+34 926 51 01 53",
    "sg:postcode":"13700",
    "sg:province":"Ciudad Real",
    "wof:name":"Vinumar S. A.",
    "wof:placetype":"venue"
},
  "geometry": {"coordinates":[-3.0289731026,39.1533355713],"type":"Point"}
}