{
  "type": "Feature",
  "properties": {
    "iso:country":"ES",
    "sg:address":"Pase Revellin (del), 17",
    "sg:city":"Ceuta",
    "sg:orig_category":"Sociedades, Compa\u00d1\u00cdas Aseguradoras",
    "sg:phone":"+34 956 51 11 36",
    "sg:postcode":"51001",
    "sg:province":"Ceuta",
    "sg:website":"www.ocaso.es",
    "wof:name":"Ocaso S.a. Compa\u00f1ia De Seguros Y Reaseguros",
    "wof:placetype":"venue"
},
  "geometry": {"coordinates":[-5.3302302361,35.8947601318],"type":"Point"}
}