{
  "type": "Feature",
  "properties": {
    "addr:full":"Plaz Gernikako Arbola, S/n Elorrio Vizcaya 48230",
    "addr:housenumber":"s / n",
    "addr:postcode":"48230",
    "addr:street":"Plaz Gernikako Arbola",
    "iso:country":"ES",
    "sg:address":"Plaz Gernikako Arbola, S/n",
    "sg:city":"Elorrio",
    "sg:orig_category":"Iglesia Cat\u00d3lica",
    "sg:phone":"+34 946 82 02 28",
    "sg:postcode":"48230",
    "sg:province":"Vizcaya",
    "wof:name":"Obispado De Bilbao",
    "wof:placetype":"venue"
},
  "geometry": {"coordinates":[-2.5428469181,43.1303977966],"type":"Point"}
}