{
  "type": "Feature",
  "properties": {
    "iso:country":"ES",
    "sg:address":"Calle de Cordoba, 14",
    "sg:city":"Ubeda",
    "sg:orig_category":"Laboratorios Y Cl\u00cdnicas Veterinarias",
    "sg:phone":"+34 953 75 38 45",
    "sg:postcode":"23400",
    "sg:province":"Ja\u00e9n",
    "wof:name":"Barrionuevo Sanchez Juan Luis",
    "wof:placetype":"venue"
},
  "geometry": {"coordinates":[-3.3735349178,38.0123176575],"type":"Point"}
}