{
  "type": "Feature",
  "properties": {
    "addr:full":"C.v. Godella, 8 Valencia Valencia 46025",
    "addr:housenumber":"8",
    "addr:postcode":"46025",
    "addr:street":"Godella",
    "iso:country":"ES",
    "sg:address":"C.v. Godella, 8",
    "sg:city":"Valencia",
    "sg:orig_category":"Servidores Y Editores De Bases De Datos",
    "sg:phone":"+34 963 65 90 62",
    "sg:postcode":"46025",
    "sg:province":"Valencia",
    "sg:website":"www.selered.com",
    "wof:name":"Selered Plg S.l.",
    "wof:placetype":"venue"
},
  "geometry": {"coordinates":[-0.3769130111,39.4687919617],"type":"Point"}
}