{
  "type": "Feature",
  "properties": {
    "iso:country":"ES",
    "sg:address":"Dr Fco Grande Covian, 4",
    "sg:city":"Osuna",
    "sg:orig_category":"Retoques De Vestidos",
    "sg:phone":"+34 954 81 25 94",
    "sg:postcode":"41640",
    "sg:province":"Sevilla",
    "wof:name":"Dominguez Perez Rosario",
    "wof:placetype":"venue"
},
  "geometry": {"coordinates":[-5.0935091972,37.2330284119],"type":"Point"}
}