{
  "type": "Feature",
  "properties": {
    "iso:country":"ES",
    "sg:address":"Calle de Ibrahin, 10",
    "sg:city":"Malaga",
    "sg:classifiers":[
        {
            "category":"Autos & Motor Vehicles",
            "subcategory":"Automobile Sales",
            "type":"Retail Goods"
        }
    ],
    "sg:phone":"+34 952 27 59 44",
    "sg:postcode":"29010",
    "sg:province":"M\u00e1laga",
    "wof:name":"Grupo Guia S.l.",
    "wof:placetype":"venue"
},
  "geometry": {"coordinates":[-4.4419522285,36.7293167114],"type":"Point"}
}