{
  "type": "Feature",
  "properties": {
    "addr:full":"Calle de Torrelaguna, 119 Sevilla Sevilla 41016",
    "addr:housenumber":"119",
    "addr:postcode":"41016",
    "addr:street":"Calle De Torrelaguna",
    "iso:country":"ES",
    "sg:address":"Calle de Torrelaguna, 119",
    "sg:city":"Sevilla",
    "sg:orig_category":"Empresas De Carpinter\u00cda Met\u00c1lica",
    "sg:phone":"+34 954 40 09 30",
    "sg:postcode":"41016",
    "sg:province":"Sevilla",
    "wof:name":"Luque Galbarro Francisco",
    "wof:placetype":"venue"
},
  "geometry": {"coordinates":[-5.9021191597,37.3852500916],"type":"Point"}
}