{
  "type": "Feature",
  "properties": {
    "addr:full":"Carrer de Vene\u00c7uela, 83 Granollers Barcelona 08402",
    "addr:housenumber":"83",
    "addr:postcode":"08402",
    "addr:street":"Carrer De Venec\u0327Uela",
    "iso:country":"ES",
    "sg:address":"Carrer de Vene\u00c7uela, 83",
    "sg:city":"Granollers",
    "sg:orig_category":"Prendas Y Chalecos De Punto (al Por Menor)",
    "sg:phone":"+34 938 70 13 57",
    "sg:postcode":"08402",
    "sg:province":"Barcelona",
    "wof:name":"Maymo Porredon Jaime",
    "wof:placetype":"venue"
},
  "geometry": {"coordinates":[2.2986700535,41.6066513062],"type":"Point"}
}