{
  "type": "Feature",
  "properties": {
    "iso:country":"ES",
    "sg:address":"Otalora Lizentziaduna Kalea, 2",
    "sg:city":"Arrasate",
    "sg:orig_category":"Tiendas De Grano, Frutas Y Legumbres Secas (al Por Menor)",
    "sg:phone":"+34 943 79 69 34",
    "sg:postcode":"20500",
    "sg:province":"Guip\u00f9zcoa",
    "wof:name":"Bedia Arregui Eduardo",
    "wof:placetype":"venue"
},
  "geometry": {"coordinates":[-2.4870829582,43.066078186],"type":"Point"}
}