{
  "type": "Feature",
  "properties": {
    "addr:full":"Cro Gas (del), 13 Reus Tarragona 43204",
    "addr:postcode":"43204",
    "iso:country":"ES",
    "sg:address":"Cro Gas (del), 13",
    "sg:city":"Reus",
    "sg:orig_category":"Jardiner\u00cdas, Vegetales, Art\u00cdculos De Jardiner\u00cda (al Por Menor)",
    "sg:phone":"+34 977 77 38 72",
    "sg:postcode":"43204",
    "sg:province":"Tarragona",
    "wof:name":"Balanya Parra Carles",
    "wof:placetype":"venue"
},
  "geometry": {"coordinates":[1.113517046,41.152305603],"type":"Point"}
}