{
  "type": "Feature",
  "properties": {
    "addr:full":"Calle de Fernando Primo De Rivera, 13 Santa Cruz De Tenerife Santa Cruz De Tenerife 38006",
    "addr:housenumber":"13",
    "addr:postcode":"38006",
    "addr:street":"Calle De Fernando Primo De Rivera",
    "iso:country":"ES",
    "sg:address":"Calle de Fernando Primo De Rivera, 13",
    "sg:city":"Santa Cruz De Tenerife",
    "sg:orig_category":"Panader\u00cdas, Panader\u00cdas",
    "sg:phone":"+34 922 28 28 11",
    "sg:postcode":"38006",
    "sg:province":"Santa Cruz De Tenerife",
    "wof:name":"Torres Torres Alfredo",
    "wof:placetype":"venue"
},
  "geometry": {"coordinates":[-16.2618331909,28.4684925079],"type":"Point"}
}