{
  "type": "Feature",
  "properties": {
    "iso:country":"ES",
    "sg:address":"C/ Doctor Ferran, 104",
    "sg:city":"Elche",
    "sg:orig_category":"Electricidad (montaje, Ensamblaje De Componentes)",
    "sg:phone":"+34 965 46 39 78",
    "sg:postcode":"03201",
    "sg:province":"Alicante",
    "wof:name":"Taller Electromecanico Miguel S.l.",
    "wof:placetype":"venue"
},
  "geometry": {"coordinates":[-0.7100600004,38.263961792],"type":"Point"}
}