{
  "type": "Feature",
  "properties": {
    "iso:country":"ES",
    "sg:address":"Valle Belagua, 57",
    "sg:city":"Lomas",
    "sg:orig_category":"Promotores Constructores",
    "sg:phone":"+34 916 33 14 69",
    "sg:postcode":"28669",
    "sg:province":"Madrid",
    "wof:name":"Viacasa S.l.",
    "wof:placetype":"venue"
},
  "geometry": {"coordinates":[-3.888365984,40.4338722229],"type":"Point"}
}