{
  "type": "Feature",
  "properties": {
    "addr:full":"Calle de Agua, 33 Coria C\u00e1ceres 10800",
    "addr:housenumber":"33",
    "addr:postcode":"10800",
    "addr:street":"Calle De Agua;Ca\u0301Ceres",
    "iso:country":"ES",
    "sg:address":"Calle de Agua, 33",
    "sg:city":"Coria",
    "sg:orig_category":"Restaurantes",
    "sg:phone":"+34 927 50 38 83",
    "sg:postcode":"10800",
    "sg:province":"C\u00e1ceres",
    "wof:name":"Serrano Miguel Maria Rosa",
    "wof:placetype":"venue"
},
  "geometry": {"coordinates":[-6.5367298126,39.9878768921],"type":"Point"}
}