{
  "type": "Feature",
  "properties": {
    "addr:full":"Carrer de Saclosa, 40 Manresa Barcelona 08241",
    "addr:housenumber":"40",
    "addr:postcode":"08241",
    "addr:street":"Carrer De Saclosa",
    "iso:country":"ES",
    "sg:address":"Carrer de Saclosa, 40",
    "sg:city":"Manresa",
    "sg:orig_category":"Frutas, Legumbres Frescas Y Tempranas (al Por Menor)",
    "sg:phone":"+34 938 72 87 61",
    "sg:postcode":"08241",
    "sg:province":"Barcelona",
    "wof:name":"Oller Lozano Luisa",
    "wof:placetype":"venue"
},
  "geometry": {"coordinates":[1.8201489449,41.7287597656],"type":"Point"}
}