{
  "type": "Feature",
  "properties": {
    "iso:country":"ES",
    "sg:address":"Avda Principe Felipe, Del, 18",
    "sg:city":"Talavera Reina",
    "sg:orig_category":"Zapatos (al Por Menor)",
    "sg:phone":"+34 925 81 51 11",
    "sg:postcode":"45600",
    "sg:province":"Toledo",
    "wof:name":"Espada Redajo Inmaculada",
    "wof:placetype":"venue"
},
  "geometry": {"coordinates":[-4.8326292038,39.9584884644],"type":"Point"}
}