{
  "type": "Feature",
  "properties": {
    "addr:full":"Bard Huechar, S/n Huechar Almer\u00eda 04400",
    "addr:postcode":"04400",
    "addr:street":"Huechar S / N Huechar Almeri\u0301A",
    "iso:country":"ES",
    "sg:address":"Bard Huechar, S/n",
    "sg:city":"Huechar",
    "sg:orig_category":"Ingeniero",
    "sg:phone":"+34 950 64 13 20",
    "sg:postcode":"04400",
    "sg:province":"Almer\u00eda",
    "wof:name":"Empresa De Gestion Medio Ambiental S.a.",
    "wof:placetype":"venue"
},
  "geometry": {"coordinates":[-2.5715889931,36.9589881897],"type":"Point"}
}