{
  "type": "Feature",
  "properties": {
    "addr:full":"Carrer de Boters, 47 Carrer De Baix -plana De Can Periquet Barcelona 08184",
    "addr:housenumber":"47",
    "addr:postcode":"08184",
    "addr:street":"Carrer De Boters;Carrer De Baix Plana De Can Periquet",
    "iso:country":"ES",
    "sg:address":"Carrer de Boters, 47",
    "sg:city":"Carrer De Baix -plana De Can Periquet",
    "sg:orig_category":"Contenedores (mercanc\u00cdas)",
    "sg:phone":"+34 938 64 31 55",
    "sg:postcode":"08184",
    "sg:province":"Barcelona",
    "wof:name":"Marques Ruiz Montserrat",
    "wof:placetype":"venue"
},
  "geometry": {"coordinates":[2.1748530865,41.5814743042],"type":"Point"}
}