{
  "type": "Feature",
  "properties": {
    "iso:country":"ES",
    "sg:address":"Av Pais Valencia, 10",
    "sg:city":"Benissa",
    "sg:orig_category":"Droguer\u00cdas (al Por Menor)",
    "sg:phone":"+34 965 73 08 35",
    "sg:postcode":"03720",
    "sg:province":"Alicante",
    "wof:name":"Servicio Y Color Ondara S.l.",
    "wof:placetype":"venue"
},
  "geometry": {"coordinates":[0.0577020012,38.71641922],"type":"Point"}
}