{
  "type": "Feature",
  "properties": {
    "iso:country":"ES",
    "sg:address":"Calle de Fray Luis Urbano, 52",
    "sg:city":"Zaragoza",
    "sg:orig_category":"Quincaller\u00cda (al Por Menor)",
    "sg:phone":"+34 976 49 80 39",
    "sg:postcode":"50002",
    "sg:province":"Zaragoza",
    "wof:name":"Gallego Gomez Francisco",
    "wof:placetype":"venue"
},
  "geometry": {"coordinates":[-0.8593834043,41.644241333],"type":"Point"}
}