{
  "type": "Feature",
  "properties": {
    "iso:country":"ES",
    "sg:address":"Avda Castilla, 19",
    "sg:city":"Cangas Onis",
    "sg:orig_category":"Promotores Constructores",
    "sg:phone":"+34 985 94 70 59",
    "sg:postcode":"33550",
    "sg:province":"Asturias",
    "wof:name":"Empresa Cabraliega De Construccion Y Obra Publica S.l.",
    "wof:placetype":"venue"
},
  "geometry": {"coordinates":[-5.1308507919,43.3477020264],"type":"Point"}
}