{
  "type": "Feature",
  "properties": {
    "iso:country":"ES",
    "sg:address":"Glorieta De Cervantes, 21",
    "sg:city":"Villanueva Fuente",
    "sg:orig_category":"Transportes Por V\u00cdas Navegables",
    "sg:phone":"+34 967 39 60 81",
    "sg:postcode":"13330",
    "sg:province":"Ciudad Real",
    "wof:name":"Cerro Moreno Manuel",
    "wof:placetype":"venue"
},
  "geometry": {"coordinates":[-2.6951749325,38.6934356689],"type":"Point"}
}