{
  "type": "Feature",
  "properties": {
    "addr:full":"Calle de Ba\u00d1os, 11 Albacete Albacete 02004",
    "addr:housenumber":"11",
    "addr:postcode":"02004",
    "addr:street":"Calle De Ban\u0303Os",
    "iso:country":"ES",
    "sg:address":"Calle de Ba\u00d1os, 11",
    "sg:city":"Albacete",
    "sg:orig_category":"Pintura Y Barniz (al Por Menor)",
    "sg:phone":"+34 967 50 46 93",
    "sg:postcode":"02004",
    "sg:province":"Albacete",
    "wof:name":"Nieto Nu\u00f1ez Manuel",
    "wof:placetype":"venue"
},
  "geometry": {"coordinates":[-1.8601038456,38.995098114],"type":"Point"}
}