{
  "type": "Feature",
  "properties": {
    "iso:country":"ES",
    "sg:address":"Ctra Nal 340, S/n",
    "sg:city":"Barri Maritim Coma-ruga",
    "sg:orig_category":"Deportes N\u00c1uticos, Acu\u00c1ticos Y Subacu\u00c1ticos: Art\u00cdculos Y Equipo (al Por Menor)",
    "sg:phone":"+34 977 68 00 02",
    "sg:postcode":"43880",
    "sg:province":"Tarragona",
    "wof:name":"Nautica Comarruga S.l.",
    "wof:placetype":"venue"
},
  "geometry": {"coordinates":[1.5386699438,41.1833496094],"type":"Point"}
}