{
  "type": "Feature",
  "properties": {
    "iso:country":"ES",
    "sg:address":"Rua San Amaro, 23",
    "sg:city":"Ferrol",
    "sg:orig_category":"Art\u00cdculos De Regalo (al Por Menor)",
    "sg:phone":"+34 981 32 62 28",
    "sg:postcode":"15403",
    "sg:province":"La Coru\u00f1a",
    "wof:name":"Menta Y Chocolate S.l.",
    "wof:placetype":"venue"
},
  "geometry": {"coordinates":[-8.2293930054,43.4844322205],"type":"Point"}
}