{
  "type": "Feature",
  "properties": {
    "addr:full":"Alsilla(pol Vi), 8 Silla Valencia 46460",
    "addr:postcode":"46460",
    "iso:country":"ES",
    "sg:address":"Alsilla(pol Vi), 8",
    "sg:city":"Silla",
    "sg:orig_category":"Quincaller\u00cda (al Por Menor)",
    "sg:phone":"+34 961 21 11 17",
    "sg:postcode":"46460",
    "sg:province":"Valencia",
    "wof:name":"Grupo Dankami S.l.",
    "wof:placetype":"venue"
},
  "geometry": {"coordinates":[-0.4030939937,39.3510513306],"type":"Point"}
}