{
  "type": "Feature",
  "properties": {
    "iso:country":"ES",
    "sg:address":"Calle de Alfaro, 12",
    "sg:city":"Pinto",
    "sg:orig_category":"Molduras, Junquillos, Listones Y Molduras Perforadas",
    "sg:phone":"+34 916 92 84 07",
    "sg:postcode":"28320",
    "sg:province":"Madrid",
    "wof:name":"Fuentes Lopez Jose Maria",
    "wof:placetype":"venue"
},
  "geometry": {"coordinates":[-3.6974525452,40.2444267273],"type":"Point"}
}