{
  "type": "Feature",
  "properties": {
    "addr:full":"Praj Urbanova, 2 Urbanova Alicante 03008",
    "addr:housenumber":"2",
    "addr:postcode":"03008",
    "addr:street":"Urbanova",
    "iso:country":"ES",
    "sg:address":"Praj Urbanova, 2",
    "sg:city":"Urbanova",
    "sg:orig_category":"Poller\u00cda Y Caza (al Por Menor)",
    "sg:phone":"+34 965 18 86 05",
    "sg:postcode":"03008",
    "sg:province":"Alicante",
    "wof:name":"Berna Albert Jose",
    "wof:placetype":"venue"
},
  "geometry": {"coordinates":[-0.5224840045,38.2840309143],"type":"Point"}
}