{
  "type": "Feature",
  "properties": {
    "addr:full":"Calle de Boclin, S/n Almunia De Do\u00e7a Godina Zaragoza 50100",
    "addr:housenumber":"s / n",
    "addr:postcode":"50100",
    "addr:street":"Calle De Boclin",
    "iso:country":"ES",
    "sg:address":"Calle de Boclin, S/n",
    "sg:city":"Almunia De Do\u00e7a Godina",
    "sg:orig_category":"Sindicatos De Trabajadores",
    "sg:phone":"+34 976 81 24 98",
    "sg:postcode":"50100",
    "sg:province":"Zaragoza",
    "wof:name":"Sindicato Riegos Acequias Nueva Y Griu",
    "wof:placetype":"venue"
},
  "geometry": {"coordinates":[-1.375115037,41.4779815674],"type":"Point"}
}