{
  "type": "Feature",
  "properties": {
    "addr:full":"Cmno Monte, 21 Madrid Madrid 28042",
    "addr:housenumber":"21",
    "addr:postcode":"madrid;28042",
    "addr:street":"Cmno Monte",
    "iso:country":"ES",
    "sg:address":"Cmno Monte, 21",
    "sg:city":"Madrid",
    "sg:orig_category":"Droguer\u00cdas (al Por Menor)",
    "sg:phone":"+34 913 05 62 41",
    "sg:postcode":"28042",
    "sg:province":"Madrid",
    "wof:name":"Albesco Aromas Naturales S.l.",
    "wof:placetype":"venue"
},
  "geometry": {"coordinates":[-3.5562570095,40.4895401001],"type":"Point"}
}