{
  "type": "Feature",
  "properties": {
    "addr:full":"Praz Eugenio Fadrique, 1 Vigo Pontevedra 36208",
    "addr:housenumber":"1",
    "addr:postcode":"36208",
    "addr:street":"Praz Eugenio Fadrique",
    "iso:country":"ES",
    "sg:address":"Praz Eugenio Fadrique, 1",
    "sg:city":"Vigo",
    "sg:orig_category":"Carnicer\u00cdas, Carnicer\u00cdas",
    "sg:phone":"+34 986 29 66 53",
    "sg:postcode":"36208",
    "sg:province":"Pontevedra",
    "wof:name":"Otero Comesa\u00f1a Manuel",
    "wof:placetype":"venue"
},
  "geometry": {"coordinates":[-8.7359991074,42.2242584229],"type":"Point"}
}