{
  "type": "Feature",
  "properties": {
    "addr:full":"Calle de Doctor Manzanares, 2 Oca\u00f1a Toledo 45300",
    "addr:housenumber":"2",
    "addr:postcode":"45300",
    "addr:street":"Calle De Doctor Manzanares",
    "iso:country":"ES",
    "sg:address":"Calle de Doctor Manzanares, 2",
    "sg:city":"Oca\u00f1a",
    "sg:orig_category":"Tiendas De Grano, Frutas Y Legumbres Secas (al Por Menor)",
    "sg:phone":"+34 925 12 05 60",
    "sg:postcode":"45300",
    "sg:province":"Toledo",
    "wof:name":"Molina Cobos Juan Carlos",
    "wof:placetype":"venue"
},
  "geometry": {"coordinates":[-3.4938569069,39.9587478638],"type":"Point"}
}