{
  "type": "Feature",
  "properties": {
    "iso:country":"ES",
    "sg:address":"Carrer de Proven\u00c7a, 325",
    "sg:city":"Barcelona",
    "sg:orig_category":"Molduras, Junquillos, Listones Y Molduras Perforadas",
    "sg:phone":"+34 934 59 38 83",
    "sg:postcode":"08037",
    "sg:province":"Barcelona",
    "wof:name":"Martinez Cortes Jose Manuel",
    "wof:placetype":"venue"
},
  "geometry": {"coordinates":[2.1672000885,41.3992500305],"type":"Point"}
}