{
  "type": "Feature",
  "properties": {
    "addr:full":"Calle de Dolores, 6 Baza Granada 18800",
    "addr:housenumber":"6",
    "addr:postcode":"18800",
    "addr:street":"Calle De Dolores",
    "iso:country":"ES",
    "sg:address":"Calle de Dolores, 6",
    "sg:city":"Baza",
    "sg:orig_category":"Ropa Para Se\u00d1oras Y Caballeros (al Por Menor)",
    "sg:phone":"+34 958 70 00 17",
    "sg:postcode":"18800",
    "sg:province":"Granada",
    "wof:name":"Comercial Andaluza Textil C.b.",
    "wof:placetype":"venue"
},
  "geometry": {"coordinates":[-2.7735824585,37.4906044006],"type":"Point"}
}