{
  "type": "Feature",
  "properties": {
    "addr:full":"Calle de Carneros, 4 Santa Cruz De Mudela Ciudad Real 13730",
    "addr:housenumber":"4",
    "addr:postcode":"13730",
    "addr:street":"Calle De Carneros",
    "iso:country":"ES",
    "sg:address":"Calle de Carneros, 4",
    "sg:city":"Santa Cruz De Mudela",
    "sg:orig_category":"Molduras, Junquillos, Listones Y Molduras Perforadas",
    "sg:phone":"+34 926 34 28 44",
    "sg:postcode":"13730",
    "sg:province":"Ciudad Real",
    "wof:name":"Hernandez Hernandez Jose Luis",
    "wof:placetype":"venue"
},
  "geometry": {"coordinates":[-3.4683594704,38.6436920166],"type":"Point"}
}