{
  "type": "Feature",
  "properties": {
    "iso:country":"ES",
    "sg:address":"Calle de Iparragirre, 8",
    "sg:city":"Donostia-san Sebastian",
    "sg:orig_category":"Pescader\u00cdas (al Por Menor)",
    "sg:phone":"+34 943 29 22 01",
    "sg:postcode":"20001",
    "sg:province":"Guip\u00f9zcoa",
    "wof:name":"Fernandez Mendizabal Bernardo",
    "wof:placetype":"venue"
},
  "geometry": {"coordinates":[-1.9752739668,43.3222045898],"type":"Point"}
}