{
  "type": "Feature",
  "properties": {
    "addr:full":"Calle de Isabel La Catolica, 2 Talayuelas Cuenca 16320",
    "addr:housenumber":"2",
    "addr:postcode":"16320",
    "addr:street":"Calle De Isabel La Catolica",
    "iso:country":"ES",
    "sg:address":"Calle de Isabel La Catolica, 2",
    "sg:city":"Talayuelas",
    "sg:orig_category":"Molduras, Junquillos, Listones Y Molduras Perforadas",
    "sg:phone":"+34 969 36 32 05",
    "sg:postcode":"16320",
    "sg:province":"Cuenca",
    "wof:name":"Huerta Crespo Jose Luis",
    "wof:placetype":"venue"
},
  "geometry": {"coordinates":[-1.2840210199,39.8478279114],"type":"Point"}
}