{
  "type": "Feature",
  "properties": {
    "addr:full":"Calle de Velazquez, 28 Benidorm Alicante 03500",
    "addr:housenumber":"28",
    "addr:postcode":"03500",
    "addr:street":"Calle De Velazquez",
    "iso:country":"ES",
    "sg:address":"Calle de Velazquez, 28",
    "sg:city":"Benidorm",
    "sg:orig_category":"Pintura Y Barniz (al Por Menor)",
    "sg:phone":"+34 965 86 61 18",
    "sg:postcode":"03500",
    "sg:province":"Alicante",
    "wof:name":"Comercial Beyser S. L.",
    "wof:placetype":"venue"
},
  "geometry": {"coordinates":[-0.1339759976,38.5434646606],"type":"Point"}
}