{
  "type": "Feature",
  "properties": {
    "addr:full":"Calle de Manuel Andujar, 4 Andujar Ja\u00e9n 23740",
    "addr:housenumber":"4",
    "addr:postcode":"23740",
    "addr:street":"Calle De Manuel Andujar",
    "iso:country":"ES",
    "sg:address":"Calle de Manuel Andujar, 4",
    "sg:city":"Andujar",
    "sg:orig_category":"Organizaciones Internacionales",
    "sg:phone":"+34 953 51 26 56",
    "sg:postcode":"23740",
    "sg:province":"Ja\u00e9n",
    "wof:name":"Cruz Roja Espa\u00f1ola",
    "wof:placetype":"venue"
},
  "geometry": {"coordinates":[-4.0450439453,38.0364265442],"type":"Point"}
}