{
  "type": "Feature",
  "properties": {
    "iso:country":"ES",
    "sg:address":"Avda Lentiscares, S/n",
    "sg:city":"Navarrete",
    "sg:orig_category":"Empresas De Carpinter\u00cda De Madera",
    "sg:phone":"+34 941 44 05 27",
    "sg:postcode":"26370",
    "sg:province":"La Rioja",
    "wof:name":"Saenz Casas Pedro",
    "wof:placetype":"venue"
},
  "geometry": {"coordinates":[-2.5741341114,42.4418487549],"type":"Point"}
}