{
  "type": "Feature",
  "properties": {
    "iso:country":"ES",
    "sg:address":"Cartagena-manga, Km. 0017,2",
    "sg:city":"Algar",
    "sg:orig_category":"Distribuci\u00d3n De Petr\u00d3leo Y Derivados",
    "sg:phone":"+34 968 13 51 50",
    "sg:postcode":"30366",
    "sg:province":"Murcia",
    "wof:name":"Adridan S.l.",
    "wof:placetype":"venue"
},
  "geometry": {"coordinates":[-1.1298867464,37.9834747314],"type":"Point"}
}