{
  "type": "Feature",
  "properties": {
    "iso:country":"ES",
    "sg:address":"Calle de Zamora, 15",
    "sg:city":"Puerto Cruz",
    "sg:orig_category":"Agencias De Viajes",
    "sg:phone":"+34 922 38 14 63",
    "sg:postcode":"38400",
    "sg:province":"Santa Cruz De Tenerife",
    "wof:name":"Pool Mayorista De Excursiones S.l",
    "wof:placetype":"venue"
},
  "geometry": {"coordinates":[-16.5472145081,28.4157123566],"type":"Point"}
}