{
  "type": "Feature",
  "properties": {
    "iso:country":"ES",
    "sg:address":"Talabarteros (p I El Torno), 10",
    "sg:city":"Utrera",
    "sg:orig_category":"Empresas De Carpinter\u00cda Met\u00c1lica",
    "sg:phone":"+34 954 86 07 15",
    "sg:postcode":"41710",
    "sg:province":"Sevilla",
    "wof:name":"Carpinteria Metalica Dominguez S.l.",
    "wof:placetype":"venue"
},
  "geometry": {"coordinates":[-5.7941842079,37.1982650757],"type":"Point"}
}