{
  "type": "Feature",
  "properties": {
    "addr:full":"Avda Brillante (del), 26 Cordoba C\u00f3rdoba 14012",
    "addr:housenumber":"26",
    "addr:postcode":"14012",
    "addr:street":"Avda Brillante Del;Co\u0301Rdoba",
    "iso:country":"ES",
    "sg:address":"Avda Brillante (del), 26",
    "sg:city":"Cordoba",
    "sg:orig_category":"Panader\u00cdas, Panader\u00cdas",
    "sg:phone":"+34 957 27 23 11",
    "sg:postcode":"14012",
    "sg:province":"C\u00f3rdoba",
    "wof:name":"Briots S.l.",
    "wof:placetype":"venue"
},
  "geometry": {"coordinates":[-4.7857952118,37.8979072571],"type":"Point"}
}