{
  "type": "Feature",
  "properties": {
    "iso:country":"ES",
    "sg:address":"Aldatze Kalea, 4",
    "sg:city":"Eibar",
    "sg:orig_category":"Fabricaci\u00d3n De Moldes Y Modelos",
    "sg:phone":"+34 943 20 31 03",
    "sg:postcode":"20600",
    "sg:province":"Guip\u00f9zcoa",
    "wof:name":"Grabados Garate Eskulan, S.l.",
    "wof:placetype":"venue"
},
  "geometry": {"coordinates":[-2.4712719917,43.1864891052],"type":"Point"}
}