{
  "type": "Feature",
  "properties": {
    "addr:full":"Barr Arechaga, S/n Mimetiz Vizcaya 48860",
    "addr:housenumber":"s / n",
    "addr:postcode":"48860",
    "addr:street":"Barr Arechaga",
    "iso:country":"ES",
    "sg:address":"Barr Arechaga, S/n",
    "sg:city":"Mimetiz",
    "sg:orig_category":"Empresas De Carpinter\u00cda",
    "sg:phone":"+34 946 39 15 44",
    "sg:postcode":"48860",
    "sg:province":"Vizcaya",
    "wof:name":"Agudo Quirante Jesus Maria",
    "wof:placetype":"venue"
},
  "geometry": {"coordinates":[-3.1478514671,43.1993026733],"type":"Point"}
}