{
  "type": "Feature",
  "properties": {
    "addr:full":"Carrer de Mallorca, 236 Barcelona Barcelona 08008",
    "addr:housenumber":"236",
    "addr:postcode":"08008",
    "addr:street":"Carrer De Mallorca",
    "iso:country":"ES",
    "sg:address":"Carrer de Mallorca, 236",
    "sg:city":"Barcelona",
    "sg:orig_category":"Doctores En Medicina",
    "sg:phone":"+34 932 15 77 93",
    "sg:postcode":"08008",
    "sg:province":"Barcelona",
    "wof:name":"Autonell Caldentey Jaime",
    "wof:placetype":"venue"
},
  "geometry": {"coordinates":[2.1609020233,41.3924026489],"type":"Point"}
}