{
  "type": "Feature",
  "properties": {
    "iso:country":"ES",
    "sg:address":"Calle de Ibaigane, 15",
    "sg:city":"Getxo",
    "sg:orig_category":"M\u00c9dicos: Endocrinolog\u00cda Y Metabolismo",
    "sg:phone":"+34 944 64 12 38",
    "sg:postcode":"48930",
    "sg:province":"Vizcaya",
    "wof:name":"Jose Luis Benito Mu\u00f1oz (centro Endocrino Getxo)",
    "wof:placetype":"venue"
},
  "geometry": {"coordinates":[-3.0095818043,43.3259506226],"type":"Point"}
}