{
  "type": "Feature",
  "properties": {
    "iso:country":"ES",
    "sg:address":"Calle de Cristo, 24",
    "sg:city":"Fuente Maestre",
    "sg:orig_category":"Art\u00cdculos Funerarios (al Por Menor)",
    "sg:phone":"+34 924 53 14 09",
    "sg:postcode":"06360",
    "sg:province":"Badajoz",
    "wof:name":"Llamazares Rico Maria",
    "wof:placetype":"venue"
},
  "geometry": {"coordinates":[-6.4506816864,38.5254859924],"type":"Point"}
}