{
  "type": "Feature",
  "properties": {
    "iso:country":"ES",
    "sg:address":"Calle de Ayelo De Rugat, 1",
    "sg:city":"Valencia",
    "sg:orig_category":"Agencias Y Agentes Comerciales, Representantes",
    "sg:phone":"+34 963 34 01 72",
    "sg:postcode":"46013",
    "sg:province":"Valencia",
    "wof:name":"Llovera Lance Joaquin",
    "wof:placetype":"venue"
},
  "geometry": {"coordinates":[-0.3698619902,39.4514732361],"type":"Point"}
}