{
  "type": "Feature",
  "properties": {
    "iso:country":"ES",
    "sg:address":"Calle de Arco De Avila, 15",
    "sg:city":"Arevalo",
    "sg:orig_category":"Cr\u00cda De Animales",
    "sg:phone":"+34 920 30 01 10",
    "sg:postcode":"05200",
    "sg:province":"\u00c1vila",
    "wof:name":"Fuente Izquierdo Tomas De La",
    "wof:placetype":"venue"
},
  "geometry": {"coordinates":[-4.7186155319,41.06016922],"type":"Point"}
}