{
  "type": "Feature",
  "properties": {
    "addr:full":"Calle de Estanco, 1 Madrigueras Albacete 02230",
    "addr:housenumber":"1",
    "addr:postcode":"02230",
    "addr:street":"Calle De Estanco",
    "iso:country":"ES",
    "sg:address":"Calle de Estanco, 1",
    "sg:city":"Madrigueras",
    "sg:orig_category":"M\u00c9dicos: Estomatolog\u00cda",
    "sg:phone":"+34 967 48 46 71",
    "sg:postcode":"02230",
    "sg:province":"Albacete",
    "wof:name":"Camara Montesinos Encarnacion",
    "wof:placetype":"venue"
},
  "geometry": {"coordinates":[-1.800358057,39.2365760803],"type":"Point"}
}