{
  "type": "Feature",
  "properties": {
    "addr:full":"Calle de Misterios, 65 Madrid Madrid 28027",
    "addr:housenumber":"65",
    "addr:postcode":"madrid;28027",
    "addr:street":"Calle De Misterios",
    "iso:country":"ES",
    "sg:address":"Calle de Misterios, 65",
    "sg:city":"Madrid",
    "sg:orig_category":"Arquitectos",
    "sg:phone":"+34 913 77 00 19",
    "sg:postcode":"28027",
    "sg:province":"Madrid",
    "sg:website":"www.abc-arquitectos.com",
    "wof:name":"Abc Arquitectos Colegiados Asociados S.l.",
    "wof:placetype":"venue"
},
  "geometry": {"coordinates":[-3.641698,40.440655],"type":"Point"}
}