{
  "type": "Feature",
  "properties": {
    "iso:country":"ES",
    "sg:address":"Avda Mediterraneo, S/n",
    "sg:city":"Benidorm",
    "sg:orig_category":"Estancos",
    "sg:phone":"+34 966 80 87 25",
    "sg:postcode":"03500",
    "sg:province":"Alicante",
    "wof:name":"Perez Grau Maria",
    "wof:placetype":"venue"
},
  "geometry": {"coordinates":[-0.1239840016,38.5371551514],"type":"Point"}
}