{
  "type": "Feature",
  "properties": {
    "addr:full":"Carrer de Salinas, 4 Barcelona Barcelona 08024",
    "addr:housenumber":"4",
    "addr:postcode":"08024",
    "addr:street":"Carrer De Salinas",
    "iso:country":"ES",
    "sg:address":"Carrer de Salinas, 4",
    "sg:city":"Barcelona",
    "sg:orig_category":"Grafistas",
    "sg:phone":"+34 932 13 33 56",
    "sg:postcode":"08024",
    "sg:province":"Barcelona",
    "wof:name":"Morte Segarra Eusebi",
    "wof:placetype":"venue"
},
  "geometry": {"coordinates":[2.1576440334,41.4063911438],"type":"Point"}
}