{
  "type": "Feature",
  "properties": {
    "iso:country":"ES",
    "sg:address":"Calle de Torpedero Tucuman, 27",
    "sg:city":"Madrid",
    "sg:orig_category":"Ingenier\u00cda, Centros De Estudios (diversos)",
    "sg:phone":"+34 913 59 49 48",
    "sg:postcode":"28016",
    "sg:province":"Madrid",
    "wof:name":"Chapartegui Gonzalez Eduardo",
    "wof:placetype":"venue"
},
  "geometry": {"coordinates":[-3.6721251011,40.4632644653],"type":"Point"}
}