{
  "type": "Feature",
  "properties": {
    "addr:full":"Calle de San Jose, 8 S. Jose Valle C\u00e1diz 11580",
    "addr:housenumber":"8",
    "addr:postcode":"11580",
    "addr:street":"Calle De San Jose;Jose;Ca\u0301Diz",
    "iso:country":"ES",
    "sg:address":"Calle de San Jose, 8",
    "sg:city":"S. Jose Valle",
    "sg:orig_category":"Comercio De Piezas De Recambio Y De Accesorios De Veh\u00cdculos, Veh\u00cdculos Industriales",
    "sg:phone":"+34 956 16 08 04",
    "sg:postcode":"11580",
    "sg:province":"C\u00e1diz",
    "wof:name":"Silleros Fernandez Juana",
    "wof:placetype":"venue"
},
  "geometry": {"coordinates":[-5.7999110222,36.6059455872],"type":"Point"}
}