{
  "type": "Feature",
  "properties": {
    "iso:country":"ES",
    "sg:address":"Calle de San Gerardo, 26",
    "sg:city":"Madrid",
    "sg:orig_category":"Estancos",
    "sg:phone":"+34 913 16 93 21",
    "sg:postcode":"28035",
    "sg:province":"Madrid",
    "wof:name":"Garcia Sastre Maria Del Pilar",
    "wof:placetype":"venue"
},
  "geometry": {"coordinates":[-3.7220549583,40.4680862427],"type":"Point"}
}