{
  "type": "Feature",
  "properties": {
    "iso:country":"ES",
    "sg:address":"Ptda La Hoya, 157",
    "sg:city":"Elche",
    "sg:orig_category":"Distribuci\u00d3n De Petr\u00d3leo Y Derivados",
    "sg:phone":"+34 965 45 41 95",
    "sg:postcode":"03295",
    "sg:province":"Alicante",
    "wof:name":"Anton Orts Jose",
    "wof:placetype":"venue"
},
  "geometry": {"coordinates":[-0.6429250836,38.3055953979],"type":"Point"}
}