{
  "type": "Feature",
  "properties": {
    "iso:country":"ES",
    "sg:address":"Calle de Bixente Kapanaga, 9",
    "sg:city":"Iurreta",
    "sg:orig_category":"Electricidad: Instaladores",
    "sg:phone":"+34 946 20 19 46",
    "sg:postcode":"48215",
    "sg:province":"Vizcaya",
    "wof:name":"Jauregui Aldazabal Juan Carlos",
    "wof:placetype":"venue"
},
  "geometry": {"coordinates":[-2.6367518902,43.1744537354],"type":"Point"}
}