{
  "type": "Feature",
  "properties": {
    "iso:country":"ES",
    "sg:address":"Calle de Soto, 17",
    "sg:city":"Valladolid",
    "sg:orig_category":"Fotograf\u00cda Y Cine: Aparatos, Pel\u00cdculas Y Accesorios (fabricaci\u00d3n, Al Por Mayor)",
    "sg:phone":"+34 983 26 77 19",
    "sg:postcode":"47010",
    "sg:province":"Valladolid",
    "wof:name":"Taaboada Vilari\u00f1o Elena Susana",
    "wof:placetype":"venue"
},
  "geometry": {"coordinates":[-4.7190628052,41.6622009277],"type":"Point"}
}