{
  "type": "Feature",
  "properties": {
    "addr:full":"Calle de Benarabe, 3 Castellon Castell\u00f3n 12005",
    "addr:housenumber":"3",
    "addr:postcode":"12005",
    "addr:street":"Calle De Benarabe;Castello\u0301N",
    "iso:country":"ES",
    "sg:address":"Calle de Benarabe, 3",
    "sg:city":"Castellon",
    "sg:orig_category":"Bisuter\u00cda, Joyer\u00cda, Relojer\u00cda (al Por Menor)",
    "sg:phone":"+34 964 22 93 57",
    "sg:postcode":"12005",
    "sg:province":"Castell\u00f3n",
    "wof:name":"Ordo\u00f1o Joyeros S.l.",
    "wof:placetype":"venue"
},
  "geometry": {"coordinates":[-0.0348381996,39.9793052673],"type":"Point"}
}