{
  "type": "Feature",
  "properties": {
    "iso:country":"ES",
    "sg:address":"Ctra Madrid Toledo (1-3), Km. 0034,0",
    "sg:city":"Illescas",
    "sg:orig_category":"Fabricaci\u00d3n De Muebles",
    "sg:phone":"+34 925 54 17 54",
    "sg:postcode":"45200",
    "sg:province":"Toledo",
    "wof:name":"Paz Moyano Francisco",
    "wof:placetype":"venue"
},
  "geometry": {"coordinates":[-3.8594288826,40.1091804504],"type":"Point"}
}