{
  "type": "Feature",
  "properties": {
    "addr:full":"Carrer de Vi, 12 Palma Islas Baleares 07012",
    "addr:housenumber":"12",
    "addr:postcode":"07012",
    "addr:street":"Carrer De Vi",
    "iso:country":"ES",
    "sg:address":"Carrer de Vi, 12",
    "sg:city":"Palma",
    "sg:orig_category":"Internados & Ense\u00d1anza Privada",
    "sg:phone":"+34 971 71 89 02",
    "sg:postcode":"07012",
    "sg:province":"Islas Baleares",
    "wof:name":"Padres Teatinos",
    "wof:placetype":"venue"
},
  "geometry": {"coordinates":[2.6437609196,39.5702171326],"type":"Point"}
}