{
  "type": "Feature",
  "properties": {
    "iso:country":"ES",
    "sg:address":"Calle de Burgo Nuevo, 20",
    "sg:city":"Le\u00f3n",
    "sg:orig_category":"Abogados",
    "sg:phone":"+34 987 21 27 75",
    "sg:postcode":"24001",
    "sg:province":"Le\u00f3n",
    "wof:name":"Perez Perez Maria-pilar",
    "wof:placetype":"venue"
},
  "geometry": {"coordinates":[-5.5728158951,42.5965919495],"type":"Point"}
}