{
  "type": "Feature",
  "properties": {
    "iso:country":"ES",
    "sg:address":"Plaz Independencia De La, 5",
    "sg:city":"Torremolinos",
    "sg:orig_category":"Zapatos (al Por Menor)",
    "sg:phone":"+34 952 38 49 64",
    "sg:postcode":"29620",
    "sg:province":"M\u00e1laga",
    "wof:name":"Ojeda Estrada Jose Miguel",
    "wof:placetype":"venue"
},
  "geometry": {"coordinates":[-4.4998540878,36.6244087219],"type":"Point"}
}