{
  "type": "Feature",
  "properties": {
    "iso:country":"ES",
    "sg:address":"Raval, S/n",
    "sg:city":"Vilanova De Meia",
    "sg:orig_category":"Cr\u00cda De Animales",
    "sg:phone":"+34 973 41 52 13",
    "sg:postcode":"25735",
    "sg:province":"Lleida",
    "wof:name":"Igramsa S.l.",
    "wof:placetype":"venue"
},
  "geometry": {"coordinates":[1.0229979753,41.9942703247],"type":"Point"}
}