{
  "type": "Feature",
  "properties": {
    "addr:full":"Carre De Los Sanchez, 14 Aljucer Murcia 30152",
    "addr:housenumber":"14",
    "addr:postcode":"30152",
    "addr:street":"Carre;Los Sanchez",
    "iso:country":"ES",
    "sg:address":"Carre De Los Sanchez, 14",
    "sg:city":"Aljucer",
    "sg:orig_category":"Doctores En Medicina",
    "sg:phone":"+34 968 25 11 28",
    "sg:postcode":"30152",
    "sg:province":"Murcia",
    "wof:name":"Mi\u00d1ano Sarabia Diego Anton",
    "wof:placetype":"venue"
},
  "geometry": {"coordinates":[-1.1452490091,37.9643058777],"type":"Point"}
}