{
  "type": "Feature",
  "properties": {
    "iso:country":"ES",
    "sg:address":"Pg. E. Prat Riba, 16",
    "sg:city":"El Masnou",
    "sg:orig_category":"Asociaciones, Organismos Culturales Y Socioeducativos",
    "sg:phone":"+34 935 55 66 00",
    "sg:postcode":"08320",
    "sg:province":"Barcelona",
    "wof:name":"Ajuntament Del Masnou",
    "wof:placetype":"venue"
},
  "geometry": {"coordinates":[2.3205037117,41.4793739319],"type":"Point"}
}