{
  "type": "Feature",
  "properties": {
    "addr:full":"C/ Sant Lloren\u00c7, 17 Alcoi Alicante 03801",
    "addr:housenumber":"17",
    "addr:postcode":"03801",
    "addr:street":"C / Sant Llorenc\u0327",
    "iso:country":"ES",
    "sg:address":"C/ Sant Lloren\u00c7, 17",
    "sg:city":"Alcoi",
    "sg:orig_category":"Doctores En Medicina",
    "sg:phone":"+34 965 54 70 26",
    "sg:postcode":"03801",
    "sg:province":"Alicante",
    "wof:name":"Blanes Pastor Fernando",
    "wof:placetype":"venue"
},
  "geometry": {"coordinates":[-0.4739980102,38.6973762512],"type":"Point"}
}