{
  "type": "Feature",
  "properties": {
    "iso:country":"ES",
    "sg:address":"Doctor Lopez Astray, 24",
    "sg:city":"Laracha",
    "sg:orig_category":"Negocio De Materiales De Construcci\u00d3n",
    "sg:phone":"+34 981 60 51 82",
    "sg:postcode":"15145",
    "sg:province":"La Coru\u00f1a",
    "wof:name":"Carballedo Lozano Jose David",
    "wof:placetype":"venue"
},
  "geometry": {"coordinates":[-8.5800485611,43.2471542358],"type":"Point"}
}