{
  "type": "Feature",
  "properties": {
    "iso:country":"ES",
    "sg:address":"Calle de Rio Cinca, 42",
    "sg:city":"Zaragoza",
    "sg:orig_category":"Barcos",
    "sg:phone":"+34 976 44 07 22",
    "sg:postcode":"50003",
    "sg:province":"Zaragoza",
    "wof:name":"Hermanos Zapata Del Rio S.a.",
    "wof:placetype":"venue"
},
  "geometry": {"coordinates":[-0.901350975,41.6601905823],"type":"Point"}
}