{
  "type": "Feature",
  "properties": {
    "iso:country":"ES",
    "sg:address":"Rua Nova De Abaixo, 12",
    "sg:city":"Santiago De Compostela",
    "sg:orig_category":"Arreglo, Reparaci\u00d3n, Piezas Sueltas De Televisi\u00d3n, V\u00cddeo, Hi",
    "sg:phone":"+34 981 59 15 68",
    "sg:postcode":"15706",
    "sg:province":"La Coru\u00f1a",
    "wof:name":"Garcia Mosquera Juan Manuel",
    "wof:placetype":"venue"
},
  "geometry": {"coordinates":[-8.5500459671,42.8751029968],"type":"Point"}
}