{
  "type": "Feature",
  "properties": {
    "iso:country":"ES",
    "sg:address":"Ramiro Lindado, 2",
    "sg:city":"Arahal",
    "sg:orig_category":"\u00d3ptica: Instrumentos (fabricaci\u00d3n)",
    "sg:phone":"+34 954 84 10 11",
    "sg:postcode":"41600",
    "sg:province":"Sevilla",
    "wof:name":"Anpe",
    "wof:placetype":"venue"
},
  "geometry": {"coordinates":[-5.5455183983,37.2619895935],"type":"Point"}
}