{
  "type": "Feature",
  "properties": {
    "addr:full":"Carrer de La Rambla, 91 Barcelona Barcelona 08002",
    "addr:housenumber":"91",
    "addr:postcode":"08002",
    "addr:street":"Carrer De La Rambla",
    "iso:country":"ES",
    "sg:address":"Carrer de La Rambla, 91",
    "sg:city":"Barcelona",
    "sg:orig_category":"Frutas, Legumbres Frescas Y Tempranas (al Por Menor)",
    "sg:phone":"+34 933 17 03 29",
    "sg:postcode":"08002",
    "sg:province":"Barcelona",
    "wof:name":"Soley Castellvi Eduard",
    "wof:placetype":"venue"
},
  "geometry": {"coordinates":[2.1722240448,41.3820838928],"type":"Point"}
}