{
  "type": "Feature",
  "properties": {
    "addr:full":"C/ Benito Perez Galdos, 43 Elche Alicante 03201",
    "addr:housenumber":"43",
    "addr:postcode":"03201",
    "addr:street":"C / Benito Perez Galdos",
    "iso:country":"ES",
    "sg:address":"C/ Benito Perez Galdos, 43",
    "sg:city":"Elche",
    "sg:orig_category":"Carpinteros",
    "sg:phone":"+34 966 66 44 77",
    "sg:postcode":"03201",
    "sg:province":"Alicante",
    "wof:name":"Eurosistemas Y Montajes Del Mediterraneo S.l",
    "wof:placetype":"venue"
},
  "geometry": {"coordinates":[-0.7075669765,38.2662887573],"type":"Point"}
}