{
  "type": "Feature",
  "properties": {
    "iso:country":"ES",
    "sg:address":"Pase Alberto Palacios, 48",
    "sg:city":"Madrid",
    "sg:orig_category":"\u00d3ptica: Instrumentos (fabricaci\u00d3n)",
    "sg:phone":"+34 917 95 25 74",
    "sg:postcode":"28021",
    "sg:province":"Madrid",
    "wof:name":"Optica Emi S.l.",
    "wof:placetype":"venue"
},
  "geometry": {"coordinates":[-3.7131710052,40.3446388245],"type":"Point"}
}