{
  "type": "Feature",
  "properties": {
    "iso:country":"ES",
    "sg:address":"Calle de Medico Cortes, 6",
    "sg:city":"Sax",
    "sg:classifiers":[
        {
            "category":"Personal",
            "subcategory":"Barber",
            "type":"Services"
        }
    ],
    "sg:phone":"+34 966 96 71 36",
    "sg:postcode":"03630",
    "sg:province":"Alicante",
    "sg:tags":[
        "caballeros",
        "de",
        "peluqueros"
    ],
    "wof:name":"Almendros Calero Francisco",
    "wof:placetype":"venue"
},
  "geometry": {"coordinates":[-0.8176701069,38.5381546021],"type":"Point"}
}