{
  "type": "Feature",
  "properties": {
    "addr:full":"Calle de Claudio Coello, 116 Madrid Madrid 28006",
    "addr:housenumber":"116",
    "addr:postcode":"28006",
    "addr:street":"Calle De Claudio Coello",
    "iso:country":"ES",
    "sg:address":"Calle de Claudio Coello, 116",
    "sg:city":"Madrid",
    "sg:orig_category":"Supermercados Y Hipermercados",
    "sg:phone":"+34 914 11 61 40",
    "sg:postcode":"28006",
    "sg:province":"Madrid",
    "sg:website":"www.capraboacasa.com",
    "wof:name":"Caprabo S.a.",
    "wof:placetype":"venue"
},
  "geometry": {"coordinates":[-3.685325861,40.4363517761],"type":"Point"}
}