{
  "type": "Feature",
  "properties": {
    "iso:country":"ES",
    "sg:address":"Ctra Toledo-orgaz, Km. 0028,3",
    "sg:city":"Mora",
    "sg:orig_category":"F\u00c1bricas De Ladrillo Y Tejas",
    "sg:phone":"+34 925 30 09 80",
    "sg:postcode":"45400",
    "sg:province":"Toledo",
    "wof:name":"Ceramica Millas Hijos S. A.",
    "wof:placetype":"venue"
},
  "geometry": {"coordinates":[-3.7761490345,39.6838340759],"type":"Point"}
}