{
  "type": "Feature",
  "properties": {
    "iso:country":"ES",
    "sg:address":"Carr Huelva, 17",
    "sg:city":"Barrio De Los Dolores",
    "sg:orig_category":"Empresas De Carpinter\u00cda De Madera",
    "sg:phone":"+34 961 30 01 68",
    "sg:postcode":"46113",
    "sg:province":"Valencia",
    "wof:name":"Industrias H.r.g. S.l.",
    "wof:placetype":"venue"
},
  "geometry": {"coordinates":[-0.3963840008,39.5565376282],"type":"Point"}
}