{
  "type": "Feature",
  "properties": {
    "iso:country":"ES",
    "sg:address":"Santiago Kalea, 19",
    "sg:city":"Azpeitia",
    "sg:orig_category":"Puertas Y Portales",
    "sg:phone":"+34 943 81 64 95",
    "sg:postcode":"20730",
    "sg:province":"Guip\u00f9zcoa",
    "wof:name":"Villanueva Abalia I\u00f1aki",
    "wof:placetype":"venue"
},
  "geometry": {"coordinates":[-2.2656719685,43.1853675842],"type":"Point"}
}