{
  "type": "Feature",
  "properties": {
    "iso:country":"ES",
    "sg:address":"Cno. Cementerio, 1",
    "sg:city":"Alfajarin",
    "sg:orig_category":"Productos Qu\u00cdmicos (fabricaci\u00d3n, Al Por Mayor)",
    "sg:phone":"+34 976 10 01 43",
    "sg:postcode":"50172",
    "sg:province":"Zaragoza",
    "wof:name":"Sociedad Aragonesa Especialidades Quimicas S.a.",
    "wof:placetype":"venue"
},
  "geometry": {"coordinates":[-0.7011680007,41.6085472107],"type":"Point"}
}