{
  "type": "Feature",
  "properties": {
    "addr:full":"Carr Roger De Lluria, 16 Lleida Lleida 25005",
    "addr:housenumber":"16",
    "addr:postcode":"25005",
    "addr:street":"Carr Roger De Lluria",
    "iso:country":"ES",
    "sg:address":"Carr Roger De Lluria, 16",
    "sg:city":"Lleida",
    "sg:orig_category":"Alquiler De Veh\u00cdculos: Turismos Y Utilitarios",
    "sg:phone":"+34 973 26 06 40",
    "sg:postcode":"25005",
    "sg:province":"Lleida",
    "wof:name":"Teruel Benitez Felip",
    "wof:placetype":"venue"
},
  "geometry": {"coordinates":[0.635176003,41.6203346252],"type":"Point"}
}