{
  "type": "Feature",
  "properties": {
    "addr:full":"Carrer de Sant Francesc, 30 Terrassa Barcelona 08221",
    "addr:housenumber":"30",
    "addr:postcode":"08221",
    "addr:street":"Carrer De Sant Francesc",
    "iso:country":"ES",
    "sg:address":"Carrer de Sant Francesc, 30",
    "sg:city":"Terrassa",
    "sg:orig_category":"Muebles, Minoristas",
    "sg:phone":"+34 937 80 17 19",
    "sg:postcode":"08221",
    "sg:province":"Barcelona",
    "wof:name":"Sellares Satlari Roser",
    "wof:placetype":"venue"
},
  "geometry": {"coordinates":[2.012622118,41.5588302612],"type":"Point"}
}