{
  "type": "Feature",
  "properties": {
    "iso:country":"ES",
    "sg:address":"Calle de Campo Real, 3",
    "sg:city":"Alcala Henares",
    "sg:orig_category":"Tintes (fabricaci\u00d3n, Al Por Mayor)",
    "sg:phone":"+34 918 82 45 94",
    "sg:postcode":"28806",
    "sg:province":"Madrid",
    "wof:name":"Cresiymar S.l.",
    "wof:placetype":"venue"
},
  "geometry": {"coordinates":[-3.3787488937,40.4960823059],"type":"Point"}
}