{
  "type": "Feature",
  "properties": {
    "addr:full":"Carrer de Laberint, 2 Barcelona Barcelona 08005",
    "addr:housenumber":"2",
    "addr:postcode":"08005",
    "addr:street":"Carrer De Laberint",
    "iso:country":"ES",
    "sg:address":"Carrer de Laberint, 2",
    "sg:city":"Barcelona",
    "sg:orig_category":"Ingenier\u00cda, Centros De Estudios (diversos)",
    "sg:phone":"+34 932 21 55 27",
    "sg:postcode":"08005",
    "sg:province":"Barcelona",
    "wof:name":"Cm-vinco S.l.",
    "wof:placetype":"venue"
},
  "geometry": {"coordinates":[2.2070629597,41.3994674683],"type":"Point"}
}