{
  "type": "Feature",
  "properties": {
    "iso:country":"ES",
    "sg:address":"Calle de Tejares, 10",
    "sg:city":"Bonillo",
    "sg:orig_category":"Supermercados Y Hipermercados",
    "sg:phone":"+34 967 37 10 12",
    "sg:postcode":"02610",
    "sg:province":"Albacete",
    "wof:name":"Rodas Cano Natalio",
    "wof:placetype":"venue"
},
  "geometry": {"coordinates":[-2.535777092,38.952495575],"type":"Point"}
}