{
  "type": "Feature",
  "properties": {
    "addr:full":"Carrer de Gran De Sant Andreu, 181 Barcelona Barcelona 08030",
    "addr:housenumber":"181",
    "addr:postcode":"08030",
    "addr:street":"Carrer De Gran De Sant Andreu",
    "iso:country":"ES",
    "sg:address":"Carrer de Gran De Sant Andreu, 181",
    "sg:city":"Barcelona",
    "sg:orig_category":"Ense\u00d1anza: Comercio, Gesti\u00d3n, Inform\u00c1tica",
    "sg:phone":"+34 933 46 12 16",
    "sg:postcode":"08030",
    "sg:province":"Barcelona",
    "wof:name":"Iniciatives Sant Andreu S. L.",
    "wof:placetype":"venue"
},
  "geometry": {"coordinates":[2.1891410351,41.4329795837],"type":"Point"}
}