{
  "type": "Feature",
  "properties": {
    "addr:full":"Calle de Juan De Austria, 67 Grao Castell\u00f3n 12100",
    "addr:housenumber":"67",
    "addr:postcode":"12100",
    "addr:street":"Calle De Juan De Austria;Castello\u0301N",
    "iso:country":"ES",
    "sg:address":"Calle de Juan De Austria, 67",
    "sg:city":"Grao",
    "sg:orig_category":"Cajas Y Embalajes De Madera",
    "sg:phone":"+34 964 28 28 16",
    "sg:postcode":"12100",
    "sg:province":"Castell\u00f3n",
    "wof:name":"Envases Dauden S. L.",
    "wof:placetype":"venue"
},
  "geometry": {"coordinates":[0.0176999997,39.9888801575],"type":"Point"}
}