{
  "type": "Feature",
  "properties": {
    "iso:country":"ES",
    "sg:address":"Carrer de Angel Guimera, 7",
    "sg:city":"S. Cugat Valles",
    "sg:orig_category":"Peluquer\u00cdas, Peluquer\u00cda Mixta",
    "sg:phone":"+34 935 89 12 18",
    "sg:postcode":"08172",
    "sg:province":"Barcelona",
    "wof:name":"Beauty Estilismo Y Peluqueria S.c.p.",
    "wof:placetype":"venue"
},
  "geometry": {"coordinates":[2.0795490742,41.4674682617],"type":"Point"}
}