{
  "type": "Feature",
  "properties": {
    "iso:country":"ES",
    "sg:address":"Calle de Santisima Trinidad, S/n",
    "sg:city":"Barrios",
    "sg:orig_category":"Iglesia Cat\u00d3lica",
    "sg:phone":"+34 956 62 00 05",
    "sg:postcode":"11370",
    "sg:province":"C\u00e1diz",
    "wof:name":"Parroquia San Isidro",
    "wof:placetype":"venue"
},
  "geometry": {"coordinates":[-5.4927930832,36.1848945618],"type":"Point"}
}