{
  "type": "Feature",
  "properties": {
    "iso:country":"ES",
    "sg:address":"Calle de General Garcia Escamez, 232",
    "sg:city":"Arrecife",
    "sg:orig_category":"Supermercados Y Hipermercados",
    "sg:phone":"+34 928 80 69 08",
    "sg:postcode":"35500",
    "sg:province":"Las Palmas",
    "wof:name":"Supermercados Marcial S.l.",
    "wof:placetype":"venue"
},
  "geometry": {"coordinates":[-13.5575265884,28.966091156],"type":"Point"}
}