{
  "type": "Feature",
  "properties": {
    "addr:full":"Carr Elcano, 23 Puerto De Pollen\u00c7a Islas Baleares 07470",
    "addr:housenumber":"23",
    "addr:postcode":"07470",
    "addr:street":"Carr Elcano",
    "iso:country":"ES",
    "sg:address":"Carr Elcano, 23",
    "sg:city":"Puerto De Pollen\u00c7a",
    "sg:orig_category":"Empresas De Labores Complejas De Carga Y Descarga, Montaje Con Elevadores",
    "sg:phone":"+34 971 86 80 87",
    "sg:postcode":"07470",
    "sg:province":"Islas Baleares",
    "wof:name":"Scuba Mallorca S.l.",
    "wof:placetype":"venue"
},
  "geometry": {"coordinates":[3.0821900368,39.9063034058],"type":"Point"}
}