{
  "type": "Feature",
  "properties": {
    "addr:full":"Calle de Picayo, 6 Cenizate Albacete 02247",
    "addr:housenumber":"6",
    "addr:postcode":"02247",
    "addr:street":"Calle De Picayo",
    "iso:country":"ES",
    "sg:address":"Calle de Picayo, 6",
    "sg:city":"Cenizate",
    "sg:orig_category":"Fabricaci\u00d3n De Su\u00c9ters Y Chalecos De Punto",
    "sg:phone":"+34 967 48 20 25",
    "sg:postcode":"02247",
    "sg:province":"Albacete",
    "wof:name":"Perez Tornero Enrique",
    "wof:placetype":"venue"
},
  "geometry": {"coordinates":[-1.6622109413,39.3030853271],"type":"Point"}
}