{
  "type": "Feature",
  "properties": {
    "iso:country":"ES",
    "sg:address":"Calle de Bigastro, S/n",
    "sg:city":"Alacant",
    "sg:orig_category":"Empresas De Carpinter\u00cda Met\u00c1lica",
    "sg:phone":"+34 965 10 11 03",
    "sg:postcode":"03008",
    "sg:province":"Alicante",
    "wof:name":"Arroniz Y Paquito S.l.",
    "wof:placetype":"venue"
},
  "geometry": {"coordinates":[-0.5113148093,38.3307609558],"type":"Point"}
}