{
  "type": "Feature",
  "properties": {
    "iso:country":"ES",
    "sg:address":"Calle de Naval La, 102",
    "sg:city":"Palmas De Gran Canaria",
    "sg:orig_category":"M\u00c9dicos: Pediatr\u00cda. Enfermedades De Los Ni\u00d1os",
    "sg:phone":"+34 928 46 19 50",
    "sg:postcode":"35008",
    "sg:province":"Las Palmas",
    "wof:name":"Gonzalez Diaz Esteban",
    "wof:placetype":"venue"
},
  "geometry": {"coordinates":[-15.4262676239,28.1494293213],"type":"Point"}
}