{
  "type": "Feature",
  "properties": {
    "addr:full":"Calle de Jose Grollo, 57 Valencia Valencia 46025",
    "addr:housenumber":"57",
    "addr:postcode":"46025",
    "addr:street":"Calle De Jose Grollo",
    "iso:country":"ES",
    "sg:address":"Calle de Jose Grollo, 57",
    "sg:city":"Valencia",
    "sg:orig_category":"Centros De Coordinaci\u00d3n",
    "sg:phone":"+34 963 40 42 09",
    "sg:postcode":"46025",
    "sg:province":"Valencia",
    "sg:website":"www.asgeval.com",
    "wof:name":"Asgeval S.l.",
    "wof:placetype":"venue"
},
  "geometry": {"coordinates":[-0.3889622092,39.5013160706],"type":"Point"}
}