{
  "type": "Feature",
  "properties": {
    "iso:country":"ES",
    "sg:address":"Carrer de Nou De La Rambla, 120",
    "sg:city":"Barcelona",
    "sg:orig_category":"Caf\u00c9s, Bares, Cervecer\u00cdas",
    "sg:phone":"+34 934 42 43 78",
    "sg:postcode":"08004",
    "sg:province":"Barcelona",
    "wof:name":"Pinto Garcia Francisco",
    "wof:placetype":"venue"
},
  "geometry": {"coordinates":[2.1691229343,41.3743247986],"type":"Point"}
}