{
  "type": "Feature",
  "properties": {
    "iso:country":"ES",
    "sg:address":"Avda Molinos (de Los), 9",
    "sg:city":"Cordoba",
    "sg:orig_category":"M\u00c9dicos: Estomatolog\u00cda",
    "sg:phone":"+34 957 47 03 53",
    "sg:postcode":"14001",
    "sg:province":"C\u00f3rdoba",
    "wof:name":"Moreno Cabello Pedro Angel",
    "wof:placetype":"venue"
},
  "geometry": {"coordinates":[-4.7795557976,37.8917503357],"type":"Point"}
}