{
  "type": "Feature",
  "properties": {
    "iso:country":"ES",
    "sg:address":"Ctra. Palma-alcudia, Km. 0012,3",
    "sg:city":"Sta. Maria Cami",
    "sg:orig_category":"Semiller\u00cdas",
    "sg:phone":"+34 971 62 15 46",
    "sg:postcode":"07320",
    "sg:province":"Islas Baleares",
    "wof:name":"Vivers Santa Maria S.a.t.",
    "wof:placetype":"venue"
},
  "geometry": {"coordinates":[2.8595013618,39.6859741211],"type":"Point"}
}