{
  "type": "Feature",
  "properties": {
    "addr:full":"Calle de Rollo, S/n Carbajales De Alba Zamora 49160",
    "addr:housenumber":"s / n",
    "addr:postcode":"49160",
    "addr:street":"Calle De Rollo",
    "iso:country":"ES",
    "sg:address":"Calle de Rollo, S/n",
    "sg:city":"Carbajales De Alba",
    "sg:orig_category":"Carnicer\u00cdas, Carnicer\u00cdas",
    "sg:phone":"+34 980 58 50 49",
    "sg:postcode":"49160",
    "sg:province":"Zamora",
    "wof:name":"Gallego Gago Dacio",
    "wof:placetype":"venue"
},
  "geometry": {"coordinates":[-5.9970841408,41.6531715393],"type":"Point"}
}