{
  "type": "Feature",
  "properties": {
    "iso:country":"ES",
    "sg:address":"Avda Vilalba (de), 84",
    "sg:city":"Rabade",
    "sg:orig_category":"Talleres: Ropa A Medida",
    "sg:phone":"+34 982 39 00 28",
    "sg:postcode":"27370",
    "sg:province":"Lugo",
    "wof:name":"Fernandez Pieiro Jose Luis",
    "wof:placetype":"venue"
},
  "geometry": {"coordinates":[-7.6279511452,43.1205711365],"type":"Point"}
}