{
  "type": "Feature",
  "properties": {
    "addr:full":"Nubes, 7 Leganes Madrid 28918",
    "addr:housenumber":"7",
    "addr:postcode":"28918",
    "addr:street":"Nubes",
    "iso:country":"ES",
    "sg:address":"Nubes, 7",
    "sg:city":"Leganes",
    "sg:orig_category":"Bater\u00cdas",
    "sg:phone":"+34 914 88 02 47",
    "sg:postcode":"28918",
    "sg:province":"Madrid",
    "sg:website":"www.fiamm.com",
    "wof:name":"Distribuidora Acumulatores Madrid S.a.",
    "wof:placetype":"venue"
},
  "geometry": {"coordinates":[-3.7982749939,40.3470497131],"type":"Point"}
}