{
  "type": "Feature",
  "properties": {
    "iso:country":"ES",
    "sg:address":"Poli Industrial C/m, S/n",
    "sg:city":"Rozas De Madrid",
    "sg:orig_category":"Metales (labores, Pulido)",
    "sg:phone":"+34 917 10 41 62",
    "sg:postcode":"28230",
    "sg:province":"Madrid",
    "wof:name":"Suministros Metran S.l.",
    "wof:placetype":"venue"
},
  "geometry": {"coordinates":[-3.8913800716,40.5247497559],"type":"Point"}
}