{
  "type": "Feature",
  "properties": {
    "iso:country":"ES",
    "sg:address":"Cmno Casares, 3",
    "sg:city":"Estepona",
    "sg:orig_category":"Transporte En General",
    "sg:phone":"+34 952 79 54 02",
    "sg:postcode":"29680",
    "sg:province":"M\u00e1laga",
    "wof:name":"Servicios Especiales S.a.",
    "wof:placetype":"venue"
},
  "geometry": {"coordinates":[-5.1478409767,36.4272117615],"type":"Point"}
}