{
  "type": "Feature",
  "properties": {
    "iso:country":"ES",
    "sg:address":"Carrer de Vila-real, 13",
    "sg:city":"Amposta",
    "sg:orig_category":"Carnicer\u00cdas, Carnicer\u00cdas",
    "sg:phone":"+34 977 70 07 69",
    "sg:postcode":"43870",
    "sg:province":"Tarragona",
    "wof:name":"Ferre Tomas Lourdes",
    "wof:placetype":"venue"
},
  "geometry": {"coordinates":[0.5769850016,40.7143516541],"type":"Point"}
}