{
  "type": "Feature",
  "properties": {
    "addr:full":"Calle de San Fernando, S/n Estepona M\u00e1laga 29680",
    "addr:housenumber":"/ n",
    "addr:postcode":"29680",
    "addr:street":"Calle De San Fernando S",
    "iso:country":"ES",
    "sg:address":"Calle de San Fernando, S/n",
    "sg:city":"Estepona",
    "sg:orig_category":"Inform\u00c1tica, Ofim\u00c1tica (estudios, Asesor\u00cda, Ingenier\u00cda, Formaci\u00d3n)",
    "sg:phone":"+34 952 80 23 37",
    "sg:postcode":"29680",
    "sg:province":"M\u00e1laga",
    "sg:website":"www.surwebinformatica.com",
    "wof:name":"Surweb Informatica S.l.",
    "wof:placetype":"venue"
},
  "geometry": {"coordinates":[-5.150534153,36.4287948608],"type":"Point"}
}