{
  "type": "Feature",
  "properties": {
    "addr:full":"Calle de Cabo San Vicente, 10 Alcorcon Madrid 28924",
    "addr:housenumber":"10",
    "addr:postcode":"28924",
    "addr:street":"Calle De Cabo San Vicente",
    "iso:country":"ES",
    "sg:address":"Calle de Cabo San Vicente, 10",
    "sg:city":"Alcorcon",
    "sg:orig_category":"Arquitectos",
    "sg:phone":"+34 916 19 91 70",
    "sg:postcode":"28924",
    "sg:province":"Madrid",
    "wof:name":"Gomez Gonzalez Juan Manuel",
    "wof:placetype":"venue"
},
  "geometry": {"coordinates":[-3.8160033226,40.3528671265],"type":"Point"}
}