{
  "type": "Feature",
  "properties": {
    "iso:country":"ES",
    "sg:address":"Pl. Sant Pere Nou, S/n",
    "sg:city":"Alaior",
    "sg:orig_category":"Transportes Por V\u00cdas Navegables",
    "sg:phone":"+34 971 37 13 16",
    "sg:postcode":"07730",
    "sg:province":"Islas Baleares",
    "wof:name":"Mascaro Morera Bernardo Luis",
    "wof:placetype":"venue"
},
  "geometry": {"coordinates":[4.1386799812,39.9387283325],"type":"Point"}
}