{
  "type": "Feature",
  "properties": {
    "iso:country":"ES",
    "sg:address":"Calle de Colcha, 4",
    "sg:city":"Granada",
    "sg:orig_category":"Servicios De Telecomunicaciones",
    "sg:phone":"+34 958 21 58 32",
    "sg:postcode":"18009",
    "sg:province":"Granada",
    "wof:name":"El Khihal Ahmed",
    "wof:placetype":"venue"
},
  "geometry": {"coordinates":[-3.596539259,37.1755638123],"type":"Point"}
}