{
  "type": "Feature",
  "properties": {
    "iso:country":"ES",
    "sg:address":"Calle de Cuba, S/n",
    "sg:city":"Elda",
    "sg:orig_category":"Carnicer\u00cdas, Carnicer\u00cdas",
    "sg:phone":"+34 965 38 85 99",
    "sg:postcode":"03600",
    "sg:province":"Alicante",
    "wof:name":"Martinez Alonso Maria",
    "wof:placetype":"venue"
},
  "geometry": {"coordinates":[-0.7910063863,38.4696846008],"type":"Point"}
}