{
  "type": "Feature",
  "properties": {
    "iso:country":"ES",
    "sg:address":"Av. Zaragoza, 2",
    "sg:city":"Iru\u00f1a",
    "sg:orig_category":"Inmobiliaria (agencias)",
    "sg:phone":"+34 948 29 16 66",
    "sg:postcode":"31003",
    "sg:province":"Navarra",
    "sg:website":"www.irular.com",
    "wof:name":"Inmobiliaria Irular S.l.",
    "wof:placetype":"venue"
},
  "geometry": {"coordinates":[-1.6432579756,42.8125038147],"type":"Point"}
}