{
  "type": "Feature",
  "properties": {
    "addr:full":"Pg Maritim, 24 Ciutadella Menorca Islas Baleares 07760",
    "addr:housenumber":"24",
    "addr:postcode":"07760",
    "addr:street":"Pg Maritim",
    "iso:country":"ES",
    "sg:address":"Pg Maritim, 24",
    "sg:city":"Ciutadella Menorca",
    "sg:orig_category":"Promotores Constructores",
    "sg:phone":"+34 971 38 33 58",
    "sg:postcode":"07760",
    "sg:province":"Islas Baleares",
    "wof:name":"Inversiones Y Desarrollo Menorquin S.l.",
    "wof:placetype":"venue"
},
  "geometry": {"coordinates":[3.8342130184,39.9946403503],"type":"Point"}
}