{
  "type": "Feature",
  "properties": {
    "addr:full":"Calle de Reyes Magos, 18 Madrid Madrid 28009",
    "addr:housenumber":"18",
    "addr:postcode":"madrid;28009",
    "addr:street":"Calle De Reyes Magos",
    "iso:country":"ES",
    "sg:address":"Calle de Reyes Magos, 18",
    "sg:city":"Madrid",
    "sg:orig_category":"Comidas Por Encargo, Organizaci\u00d3n De Recepciones",
    "sg:phone":"+34 915 01 77 58",
    "sg:postcode":"28009",
    "sg:province":"Madrid",
    "wof:name":"Parre\u00f1o Navarro Jose Joaquin",
    "wof:placetype":"venue"
},
  "geometry": {"coordinates":[-3.6750690937,40.4109382629],"type":"Point"}
}