{
  "type": "Feature",
  "properties": {
    "iso:country":"ES",
    "sg:address":"Calle de Haya, 3",
    "sg:city":"Madrid",
    "sg:orig_category":"Lencer\u00cda Femenina, Corseter\u00cda, Trajes De Ba\u00d1o (al Por Menor)",
    "sg:phone":"+34 915 08 80 48",
    "sg:postcode":"28044",
    "sg:province":"Madrid",
    "wof:name":"Neha Colecciones S.l.",
    "wof:placetype":"venue"
},
  "geometry": {"coordinates":[-3.7470839024,40.368057251],"type":"Point"}
}