{
  "type": "Feature",
  "properties": {
    "iso:country":"ES",
    "sg:address":"Avda Nuestra Se\u00d1ora De Fatima, 102",
    "sg:city":"Madrid",
    "sg:orig_category":"Comunidades Religiosas",
    "sg:phone":"+34 914 65 18 31",
    "sg:postcode":"28047",
    "sg:province":"Madrid",
    "wof:name":"Oblatas Del Santisimo Redentor Religiosas Provincia De Zaragoza Curi",
    "wof:placetype":"venue"
},
  "geometry": {"coordinates":[-3.7489919662,40.3787269592],"type":"Point"}
}