{
  "type": "Feature",
  "properties": {
    "iso:country":"ES",
    "sg:address":"Calle de Jovellanos, 7",
    "sg:city":"Malaga",
    "sg:orig_category":"Asociaciones, Organismos Culturales Y Socioeducativos",
    "sg:phone":"+34 952 32 51 95",
    "sg:postcode":"29002",
    "sg:province":"M\u00e1laga",
    "wof:name":"Pe\u00f1a Recreativa Los Cabales",
    "wof:placetype":"venue"
},
  "geometry": {"coordinates":[-4.4304499626,36.7129821777],"type":"Point"}
}