{
  "type": "Feature",
  "properties": {
    "addr:full":"Casa Rectoral, S/n Cartella Girona 17199",
    "addr:housenumber":"s",
    "addr:postcode":"17199",
    "addr:street":"/ N Cartella",
    "iso:country":"ES",
    "sg:address":"Casa Rectoral, S/n",
    "sg:city":"Cartella",
    "sg:orig_category":"Asociaciones, Organismos Culturales Y Socioeducativos",
    "sg:phone":"+34 972 42 86 10",
    "sg:postcode":"17199",
    "sg:province":"Girona",
    "wof:name":"Ateneu De La Vall De Llemena",
    "wof:placetype":"venue"
},
  "geometry": {"coordinates":[2.759503603,41.9906082153],"type":"Point"}
}