{
  "type": "Feature",
  "properties": {
    "iso:country":"ES",
    "sg:address":"Calle de Antonio Rosique, S/n",
    "sg:city":"Algar",
    "sg:orig_category":"Empresas De Pintura Y Revestimientos",
    "sg:phone":"+34 968 13 60 88",
    "sg:postcode":"30366",
    "sg:province":"Murcia",
    "wof:name":"Sanmartin Albaladejo Antonio",
    "wof:placetype":"venue"
},
  "geometry": {"coordinates":[-0.8649839759,37.649936676],"type":"Point"}
}