{
  "type": "Feature",
  "properties": {
    "iso:country":"ES",
    "sg:address":"Avda Pio Xii, 15",
    "sg:city":"Madrid",
    "sg:orig_category":"Guarder\u00cdas",
    "sg:phone":"+34 913 59 02 60",
    "sg:postcode":"28016",
    "sg:province":"Madrid",
    "wof:name":"Sequeira Martins Otilia Maria",
    "wof:placetype":"venue"
},
  "geometry": {"coordinates":[-3.6743350029,40.4730262756],"type":"Point"}
}