{
  "type": "Feature",
  "properties": {
    "iso:country":"ES",
    "sg:address":"Calle de Marcelo Usera, 124",
    "sg:city":"Madrid",
    "sg:orig_category":"\u00d3ptica: Instrumentos (fabricaci\u00d3n)",
    "sg:phone":"+34 915 00 36 18",
    "sg:postcode":"28026",
    "sg:province":"Madrid",
    "wof:name":"Vision Mb Bruno S.l.",
    "wof:placetype":"venue"
},
  "geometry": {"coordinates":[-3.7099599838,40.385433197],"type":"Point"}
}