{
  "type": "Feature",
  "properties": {
    "addr:full":"Calle de San Jose, 17 Valle Trapaga Vizcaya 48510",
    "addr:housenumber":"17",
    "addr:postcode":"48510",
    "addr:street":"Calle De San;Trapaga",
    "iso:country":"ES",
    "sg:address":"Calle de San Jose, 17",
    "sg:city":"Valle Trapaga",
    "sg:orig_category":"Confiter\u00cdas, Chocolater\u00cdas (al Por Menor)",
    "sg:phone":"+34 944 92 11 33",
    "sg:postcode":"48510",
    "sg:province":"Vizcaya",
    "wof:name":"Gloria Lucia Aragones Frias - Confituras Aingeru",
    "wof:placetype":"venue"
},
  "geometry": {"coordinates":[-3.0336771011,43.30286026],"type":"Point"}
}