{
  "type": "Feature",
  "properties": {
    "iso:country":"ES",
    "sg:address":"Carrer de Diputacio, 127",
    "sg:city":"Barcelona",
    "sg:orig_category":"Tintorer\u00cdas, Limpieza En Seco",
    "sg:phone":"+34 934 53 56 61",
    "sg:postcode":"08015",
    "sg:province":"Barcelona",
    "wof:name":"Plana Ortega Maria Dolores",
    "wof:placetype":"venue"
},
  "geometry": {"coordinates":[2.156799078,41.3828811646],"type":"Point"}
}