{
  "type": "Feature",
  "properties": {
    "addr:full":"C/ Joan I Lluis Mulet, 1 Arenal Islas Baleares 07600",
    "addr:housenumber":"1",
    "addr:postcode":"07600",
    "addr:street":"C / Joan I Lluis Mulet",
    "iso:country":"ES",
    "sg:address":"C/ Joan I Lluis Mulet, 1",
    "sg:city":"Arenal",
    "sg:orig_category":"Sindicatos De Trabajadores",
    "sg:phone":"+34 971 44 17 84",
    "sg:postcode":"07600",
    "sg:province":"Islas Baleares",
    "wof:name":"Union General De Trabajadores",
    "wof:placetype":"venue"
},
  "geometry": {"coordinates":[2.752327919,39.5086097717],"type":"Point"}
}