{
  "type": "Feature",
  "properties": {
    "iso:country":"ES",
    "sg:address":"Calle de Perez Galdos, 12",
    "sg:city":"Bilbao",
    "sg:orig_category":"Lencer\u00cda Femenina, Corseter\u00cda, Trajes De Ba\u00d1o (al Por Menor)",
    "sg:phone":"+34 944 22 08 80",
    "sg:postcode":"48010",
    "sg:province":"Vizcaya",
    "wof:name":"Maria Flor Borde Cantero",
    "wof:placetype":"venue"
},
  "geometry": {"coordinates":[-2.9426050186,43.2592391968],"type":"Point"}
}