{
  "type": "Feature",
  "properties": {
    "iso:country":"ES",
    "sg:address":"Carrer de Angel Vidal, 4",
    "sg:city":"Sitges",
    "sg:orig_category":"Zapatos (al Por Menor)",
    "sg:phone":"+34 938 94 04 08",
    "sg:postcode":"08870",
    "sg:province":"Barcelona",
    "wof:name":"Pa\u00f1ella Balsells Carmen",
    "wof:placetype":"venue"
},
  "geometry": {"coordinates":[1.8098950386,41.236530304],"type":"Point"}
}