{
  "type": "Feature",
  "properties": {
    "iso:country":"ES",
    "sg:address":"Calle de Davalos Y Altamirano, 13",
    "sg:city":"Merida",
    "sg:orig_category":"Peluqueros: De Se\u00d1oras",
    "sg:phone":"+34 924 30 03 65",
    "sg:postcode":"06800",
    "sg:province":"Badajoz",
    "wof:name":"Rodriguez Gomez Juana",
    "wof:placetype":"venue"
},
  "geometry": {"coordinates":[-6.3435630798,38.9158363342],"type":"Point"}
}