{
  "type": "Feature",
  "properties": {
    "addr:full":"Rua Do Pi\u00f1eiral, S/n Pontes Garcia Rodriguez La Coru\u00f1a 15320",
    "addr:housenumber":"s",
    "addr:postcode":"15320",
    "addr:street":"Rua Do Pin\u0303Eiral;/ N Pontes Garcia Rodriguez La Corun\u0303A",
    "iso:country":"ES",
    "sg:address":"Rua Do Pi\u00f1eiral, S/n",
    "sg:city":"Pontes Garcia Rodriguez",
    "sg:orig_category":"Agentes, Concesionarios Y Sucursales De Veh\u00cdculos",
    "sg:phone":"+34 981 45 11 00",
    "sg:postcode":"15320",
    "sg:province":"La Coru\u00f1a",
    "wof:name":"Autos Lobelle S.l.",
    "wof:placetype":"venue"
},
  "geometry": {"coordinates":[-7.8666782379,43.4506530762],"type":"Point"}
}