{
  "type": "Feature",
  "properties": {
    "addr:full":"Calle de Heno, 12 Madrid Madrid 28026",
    "addr:housenumber":"12",
    "addr:postcode":"madrid;28026",
    "addr:street":"Calle De Heno",
    "iso:country":"ES",
    "sg:address":"Calle de Heno, 12",
    "sg:city":"Madrid",
    "sg:orig_category":"Empresarios",
    "sg:phone":"+34 915 60 87 56",
    "sg:postcode":"28026",
    "sg:province":"Madrid",
    "wof:name":"Semser Sl",
    "wof:placetype":"venue"
},
  "geometry": {"coordinates":[-3.7166490555,40.3777999878],"type":"Point"}
}