{
  "type": "Feature",
  "properties": {
    "addr:full":"Carrer de Salmeron, 203 Terrassa Barcelona 08226",
    "addr:housenumber":"203",
    "addr:postcode":"08226",
    "addr:street":"Carrer De Salmeron",
    "iso:country":"ES",
    "sg:address":"Carrer de Salmeron, 203",
    "sg:city":"Terrassa",
    "sg:orig_category":"Molduras, Junquillos, Listones Y Molduras Perforadas",
    "sg:phone":"+34 937 83 45 21",
    "sg:postcode":"08226",
    "sg:province":"Barcelona",
    "wof:name":"Gijon Nieto Ana",
    "wof:placetype":"venue"
},
  "geometry": {"coordinates":[2.021130085,41.5696372986],"type":"Point"}
}