{
  "type": "Feature",
  "properties": {
    "addr:full":"Calle de Cirilo Amoros, 69 Valencia Valencia 46004",
    "addr:housenumber":"69",
    "addr:postcode":"46004",
    "addr:street":"Calle De Cirilo Amoros",
    "iso:country":"ES",
    "sg:address":"Calle de Cirilo Amoros, 69",
    "sg:city":"Valencia",
    "sg:orig_category":"Procuradores",
    "sg:phone":"+34 963 94 38 72",
    "sg:postcode":"46004",
    "sg:province":"Valencia",
    "wof:name":"Consejo Valenciano De Colegios De Procuradores De La Comunidad De Valencia",
    "wof:placetype":"venue"
},
  "geometry": {"coordinates":[-0.3668991029,39.4692649841],"type":"Point"}
}