{
  "type": "Feature",
  "properties": {
    "addr:full":"Carrer de Joan Maragall, 5 Martorell Barcelona 08760",
    "addr:housenumber":"5",
    "addr:postcode":"08760",
    "addr:street":"Carrer De Joan Maragall",
    "iso:country":"ES",
    "sg:address":"Carrer de Joan Maragall, 5",
    "sg:city":"Martorell",
    "sg:orig_category":"Frutas, Legumbres Frescas Y Tempranas (al Por Menor)",
    "sg:phone":"+34 937 76 61 48",
    "sg:postcode":"08760",
    "sg:province":"Barcelona",
    "wof:name":"Frutas Roura S.a.",
    "wof:placetype":"venue"
},
  "geometry": {"coordinates":[1.9152350426,41.4774856567],"type":"Point"}
}