{
  "type": "Feature",
  "properties": {
    "iso:country":"ES",
    "sg:address":"Calle de San Roque, 1",
    "sg:city":"Portugalete",
    "sg:orig_category":"Sociedades, Compa\u00d1\u00cdas Aseguradoras",
    "sg:phone":"+34 944 96 17 86",
    "sg:postcode":"48920",
    "sg:province":"Vizcaya",
    "wof:name":"Gil Arostegui Alberto",
    "wof:placetype":"venue"
},
  "geometry": {"coordinates":[-3.0181820393,43.3194236755],"type":"Point"}
}