{
  "type": "Feature",
  "properties": {
    "iso:country":"ES",
    "sg:address":"Calle de Adolfo Castillo Genzor, 4",
    "sg:city":"Burgo Ebro",
    "sg:orig_category":"Puertas Y Portales",
    "sg:phone":"+34 976 10 42 00",
    "sg:postcode":"50730",
    "sg:province":"Zaragoza",
    "wof:name":"Simebro S.l.",
    "wof:placetype":"venue"
},
  "geometry": {"coordinates":[-0.7422180176,41.5695762634],"type":"Point"}
}