{
  "type": "Feature",
  "properties": {
    "iso:country":"ES",
    "sg:address":"Calle de Alfonso De Castro, 6",
    "sg:city":"Salamanca",
    "sg:orig_category":"M\u00c9dicos: Gastroenterolog\u00cda Y Hepatolog\u00cda (aparato Digestivo)",
    "sg:phone":"+34 923 22 82 47",
    "sg:postcode":"37005",
    "sg:province":"Salamanca",
    "wof:name":"Gutierrez Alonso Jose Luis",
    "wof:placetype":"venue"
},
  "geometry": {"coordinates":[-5.6602525711,40.972114563],"type":"Point"}
}