{
  "type": "Feature",
  "properties": {
    "addr:full":"Po Prieto Moreno, 8 Almu\u00f1ecar Granada 18690",
    "addr:housenumber":"8",
    "addr:postcode":"18690",
    "addr:street":"Moreno",
    "iso:country":"ES",
    "sg:address":"Po Prieto Moreno, 8",
    "sg:city":"Almu\u00f1ecar",
    "sg:orig_category":"Inmobiliaria (agencias)",
    "sg:phone":"+34 958 88 07 65",
    "sg:postcode":"18690",
    "sg:province":"Granada",
    "wof:name":"Jeronimo Martin Juan Carlos",
    "wof:placetype":"venue"
},
  "geometry": {"coordinates":[-3.6934239864,36.7297058105],"type":"Point"}
}