{
  "type": "Feature",
  "properties": {
    "iso:country":"ES",
    "sg:address":"Carr Licorers, 125",
    "sg:city":"Cabaneta",
    "sg:orig_category":"Alumbrados",
    "sg:phone":"+34 971 60 55 06",
    "sg:postcode":"07141",
    "sg:province":"Islas Baleares",
    "sg:website":"www.trui.es",
    "wof:name":"Trui Espectaculos S.l.",
    "wof:placetype":"venue"
},
  "geometry": {"coordinates":[2.7445349693,39.6195487976],"type":"Point"}
}