{
  "type": "Feature",
  "properties": {
    "addr:full":"Av Paisos Catalans, 20 Reus Tarragona 43202",
    "addr:housenumber":"20",
    "addr:postcode":"43202",
    "addr:street":"Av Paisos Catalans",
    "iso:country":"ES",
    "sg:address":"Av Paisos Catalans, 20",
    "sg:city":"Reus",
    "sg:orig_category":"Negocio De Materiales De Construcci\u00d3n",
    "sg:phone":"+34 977 32 39 81",
    "sg:postcode":"43202",
    "sg:province":"Tarragona",
    "wof:name":"Geral C.b.",
    "wof:placetype":"venue"
},
  "geometry": {"coordinates":[1.0967880487,41.1563301086],"type":"Point"}
}