{
  "type": "Feature",
  "properties": {
    "iso:country":"ES",
    "sg:address":"Avda Constitucion, 50",
    "sg:city":"Callosa Segura",
    "sg:orig_category":"Chapister\u00cda",
    "sg:phone":"+34 965 31 04 92",
    "sg:postcode":"03360",
    "sg:province":"Alicante",
    "wof:name":"Guilabert Zaragoza Pascual",
    "wof:placetype":"venue"
},
  "geometry": {"coordinates":[-0.87786901,38.1289901733],"type":"Point"}
}