{
  "type": "Feature",
  "properties": {
    "iso:country":"ES",
    "sg:address":"Calle de Kapelamendi, 4",
    "sg:city":"Vitoria-gasteiz",
    "sg:orig_category":"Cajas Y Embalajes De Pl\u00c1stico",
    "sg:phone":"+34 945 25 61 06",
    "sg:postcode":"01013",
    "sg:province":"\u00c1lava",
    "wof:name":"Sacos Y Carton Santiba\u00f1ez S.c.",
    "wof:placetype":"venue"
},
  "geometry": {"coordinates":[-2.6452209949,42.8676452637],"type":"Point"}
}