{
  "type": "Feature",
  "properties": {
    "iso:country":"ES",
    "sg:address":"Calle de Pe\u00d1uelas, 1",
    "sg:city":"Constantina",
    "sg:orig_category":"Forjas Y Altos Hornos",
    "sg:phone":"+34 955 88 13 70",
    "sg:postcode":"41450",
    "sg:province":"Sevilla",
    "wof:name":"Florido Melendez Fernando",
    "wof:placetype":"venue"
},
  "geometry": {"coordinates":[-5.61936903,37.8689002991],"type":"Point"}
}