{
  "type": "Feature",
  "properties": {
    "iso:country":"ES",
    "sg:address":"Calle de Gobernador Viejo, 15",
    "sg:city":"Valencia",
    "sg:orig_category":"M\u00c9dicos: Neurolog\u00cda",
    "sg:phone":"+34 963 15 40 79",
    "sg:postcode":"46003",
    "sg:province":"Valencia",
    "wof:name":"Goberna Ortiz Enrique",
    "wof:placetype":"venue"
},
  "geometry": {"coordinates":[-0.3717057109,39.4748802185],"type":"Point"}
}