{
  "type": "Feature",
  "properties": {
    "iso:country":"ES",
    "sg:address":"Calle de Ordicia, 11",
    "sg:city":"Madrid",
    "sg:orig_category":"Alquiler De V\u00cddeo",
    "sg:phone":"+34 917 46 32 63",
    "sg:postcode":"28041",
    "sg:province":"Madrid",
    "wof:name":"Mavik Video S.l",
    "wof:placetype":"venue"
},
  "geometry": {"coordinates":[-3.713917017,40.3664932251],"type":"Point"}
}