{
  "type": "Feature",
  "properties": {
    "addr:full":"Calle de Playa, S/n Pto Real C\u00e1diz 11510",
    "addr:housenumber":"/ n",
    "addr:postcode":"11510",
    "addr:street":"Calle De Playa S;Pto;Ca\u0301Diz",
    "iso:country":"ES",
    "sg:address":"Calle de Playa, S/n",
    "sg:city":"Pto Real",
    "sg:orig_category":"Inform\u00c1tica, Ofim\u00c1tica (estudios, Asesor\u00cda, Ingenier\u00cda, Formaci\u00d3n)",
    "sg:phone":"+34 956 47 52 40",
    "sg:postcode":"11510",
    "sg:province":"C\u00e1diz",
    "wof:name":"Pascual Rodriguez Silvia",
    "wof:placetype":"venue"
},
  "geometry": {"coordinates":[-6.1991491318,36.5311737061],"type":"Point"}
}