{
  "type": "Feature",
  "properties": {
    "addr:full":"Calle de Santa Maria Micaela, S/n Malaga M\u00e1laga 29013",
    "addr:housenumber":"s",
    "addr:postcode":"29013",
    "addr:street":"Calle De Santa;Micaela;/ N;Ma\u0301Laga",
    "iso:country":"ES",
    "sg:address":"Calle de Santa Maria Micaela, S/n",
    "sg:city":"Malaga",
    "sg:orig_category":"Servicios Gsm",
    "sg:phone":"+34 952 26 56 58",
    "sg:postcode":"29013",
    "sg:province":"M\u00e1laga",
    "sg:website":"www.orellanacm.com",
    "wof:name":"Orellana Comunicaciones S.l.",
    "wof:placetype":"venue"
},
  "geometry": {"coordinates":[-4.4173688889,36.7318267822],"type":"Point"}
}