{
  "type": "Feature",
  "properties": {
    "addr:full":"Calle de Vado (del), 26 Tres Cantos Madrid 28760",
    "addr:housenumber":"26",
    "addr:postcode":"28760",
    "addr:street":"Calle De Vado Del",
    "iso:country":"ES",
    "sg:address":"Calle de Vado (del), 26",
    "sg:city":"Tres Cantos",
    "sg:orig_category":"Ense\u00d1anza: Idiomas",
    "sg:phone":"+34 918 04 01 30",
    "sg:postcode":"28760",
    "sg:province":"Madrid",
    "wof:name":"Mitchell  Gail Colette Dunbar",
    "wof:placetype":"venue"
},
  "geometry": {"coordinates":[-3.7013800144,40.5980148315],"type":"Point"}
}