{
  "type": "Feature",
  "properties": {
    "addr:full":"Carrer de Pou Del Gla\u00c7, 8 Olot Girona 17800",
    "addr:housenumber":"8",
    "addr:postcode":"17800",
    "addr:street":"Carrer De Pou Del Glac\u0327",
    "iso:country":"ES",
    "sg:address":"Carrer de Pou Del Gla\u00c7, 8",
    "sg:city":"Olot",
    "sg:orig_category":"Arquitectos",
    "sg:phone":"+34 972 27 21 30",
    "sg:postcode":"17800",
    "sg:province":"Girona",
    "wof:name":"Bosch Barges Ester",
    "wof:placetype":"venue"
},
  "geometry": {"coordinates":[2.4817180634,42.1810722351],"type":"Point"}
}