{
  "type": "Feature",
  "properties": {
    "addr:full":"Riera Targa, 73 Vilassar Dalt Barcelona 08339",
    "addr:housenumber":"73",
    "addr:postcode":"08339",
    "addr:street":"Riera Targa;Dalt Barcelona",
    "iso:country":"ES",
    "sg:address":"Riera Targa, 73",
    "sg:city":"Vilassar Dalt",
    "sg:orig_category":"Dorados, Plater\u00cda (orfebrer\u00cda)",
    "sg:phone":"+34 937 50 74 15",
    "sg:postcode":"08339",
    "sg:province":"Barcelona",
    "sg:website":"www.joyerosyocari.com",
    "wof:name":"Plata Liquida S.l",
    "wof:placetype":"venue"
},
  "geometry": {"coordinates":[2.3607499599,41.5184631348],"type":"Point"}
}