{
  "type": "Feature",
  "properties": {
    "iso:country":"ES",
    "sg:address":"Calle de Puerto De Los Leones, 1",
    "sg:city":"Majadahonda",
    "sg:orig_category":"Agencias De Trabajo Temporal",
    "sg:phone":"+34 916 34 61 41",
    "sg:postcode":"28220",
    "sg:province":"Madrid",
    "wof:name":"Itsa Ges Empresa De Trabajo Temporal S.l.",
    "wof:placetype":"venue"
},
  "geometry": {"coordinates":[-3.8754720688,40.4751663208],"type":"Point"}
}