{
  "type": "Feature",
  "properties": {
    "addr:full":"Calle de General Franco, 1 Espartinas Sevilla 41807",
    "addr:housenumber":"1",
    "addr:postcode":"41807",
    "addr:street":"Calle De General Franco",
    "iso:country":"ES",
    "sg:address":"Calle de General Franco, 1",
    "sg:city":"Espartinas",
    "sg:orig_category":"Iglesia Cat\u00d3lica",
    "sg:phone":"+34 954 11 44 64",
    "sg:postcode":"41807",
    "sg:province":"Sevilla",
    "wof:name":"Parroquia Nuestra Se\u00f1ora De La Asuncion",
    "wof:placetype":"venue"
},
  "geometry": {"coordinates":[-6.1248888969,37.382850647],"type":"Point"}
}