{
  "type": "Feature",
  "properties": {
    "addr:full":"Calle de Soria, 8 Briviesca Burgos 09240",
    "addr:housenumber":"8",
    "addr:postcode":"09240",
    "addr:street":"Calle De Soria",
    "iso:country":"ES",
    "sg:address":"Calle de Soria, 8",
    "sg:city":"Briviesca",
    "sg:orig_category":"Metales (labores, Pulido)",
    "sg:phone":"+34 947 59 11 72",
    "sg:postcode":"09240",
    "sg:province":"Burgos",
    "wof:name":"Estampaciones Aguirre S.a.",
    "wof:placetype":"venue"
},
  "geometry": {"coordinates":[-3.3199551105,42.5594978333],"type":"Point"}
}