{
  "type": "Feature",
  "properties": {
    "iso:country":"ES",
    "sg:address":"Avda Marinera, 51",
    "sg:city":"Costacabana",
    "sg:orig_category":"Mec\u00c1nico Del Autom\u00d3vil",
    "sg:phone":"+34 950 29 11 36",
    "sg:postcode":"04120",
    "sg:province":"Almer\u00eda",
    "wof:name":"Castillo Hermanos,s.l.",
    "wof:placetype":"venue"
},
  "geometry": {"coordinates":[-2.3868908882,36.8344573975],"type":"Point"}
}