{
  "type": "Feature",
  "properties": {
    "addr:full":"Calle de Braille, 7 Merida Badajoz 06800",
    "addr:housenumber":"7",
    "addr:postcode":"06800",
    "addr:street":"Calle De Braille",
    "iso:country":"ES",
    "sg:address":"Calle de Braille, 7",
    "sg:city":"Merida",
    "sg:orig_category":"Ense\u00d1anza: Peluquer\u00cda Est\u00c9tica",
    "sg:phone":"+34 924 31 27 59",
    "sg:postcode":"06800",
    "sg:province":"Badajoz",
    "wof:name":"Gonzalez Alonso Visitacion",
    "wof:placetype":"venue"
},
  "geometry": {"coordinates":[-6.3450808525,38.9185218811],"type":"Point"}
}