{
  "type": "Feature",
  "properties": {
    "iso:country":"ES",
    "sg:address":"Calle de Alfonso Viii, 41",
    "sg:city":"Cuenca",
    "sg:orig_category":"Turismo",
    "sg:phone":"+34 969 23 55 99",
    "sg:postcode":"16001",
    "sg:province":"Cuenca",
    "sg:website":"www.turalia.com",
    "wof:name":"Turalia Iniciativas Turisticas S.l.",
    "wof:placetype":"venue"
},
  "geometry": {"coordinates":[-2.130147934,40.0769767761],"type":"Point"}
}