{
  "type": "Feature",
  "properties": {
    "addr:full":"Calle de Arzobispo Marcelo Gonzalez, 24 Valladolid Valladolid 47007",
    "addr:housenumber":"24",
    "addr:postcode":"47007",
    "addr:street":"Calle De Arzobispo Marcelo Gonzalez",
    "iso:country":"ES",
    "sg:address":"Calle de Arzobispo Marcelo Gonzalez, 24",
    "sg:city":"Valladolid",
    "sg:orig_category":"Empresarios",
    "sg:phone":"+34 983 45 66 34",
    "sg:postcode":"47007",
    "sg:province":"Valladolid",
    "wof:name":"Fundacion Cauce",
    "wof:placetype":"venue"
},
  "geometry": {"coordinates":[-4.7378568649,41.6348419189],"type":"Point"}
}