{
  "type": "Feature",
  "properties": {
    "iso:country":"ES",
    "sg:address":"Pol Ind Casas Nuevas, S/n",
    "sg:city":"Setenil",
    "sg:orig_category":"Perfumer\u00cda Y Cosm\u00c9tica (fabricaci\u00d3n, Al Por Mayor)",
    "sg:phone":"+34 956 13 45 38",
    "sg:postcode":"11692",
    "sg:province":"C\u00e1diz",
    "wof:name":"Oleoesencias S.c.a.",
    "wof:placetype":"venue"
},
  "geometry": {"coordinates":[-5.1695389748,36.8657188416],"type":"Point"}
}