{
  "type": "Feature",
  "properties": {
    "iso:country":"ES",
    "sg:address":"Plaz Pablo Guaza Pastor, 6",
    "sg:city":"Alar Del Rey",
    "sg:classifiers":[
        {
            "category":"Taxi",
            "type":"Transportation"
        }
    ],
    "sg:phone":"+34 979 13 31 09",
    "sg:postcode":"34480",
    "sg:province":"Palencia",
    "wof:name":"Garcia Regaliza Marcelino",
    "wof:placetype":"venue"
},
  "geometry": {"coordinates":[-4.3096518517,42.6588172913],"type":"Point"}
}