{
  "type": "Feature",
  "properties": {
    "addr:full":"Calle de Rabadan, 6 Torredonjimeno Ja\u00e9n 23650",
    "addr:housenumber":"6",
    "addr:postcode":"23650",
    "addr:street":"Calle De Rabadan",
    "iso:country":"ES",
    "sg:address":"Calle de Rabadan, 6",
    "sg:city":"Torredonjimeno",
    "sg:orig_category":"Alimentaci\u00d3n General (al Por Menor)",
    "sg:phone":"+34 953 57 22 54",
    "sg:postcode":"23650",
    "sg:province":"Ja\u00e9n",
    "wof:name":"Sanchez Font Francisco",
    "wof:placetype":"venue"
},
  "geometry": {"coordinates":[-3.9583249092,37.766456604],"type":"Point"}
}