{
  "type": "Feature",
  "properties": {
    "iso:country":"ES",
    "sg:address":"Ctra. General, 76",
    "sg:city":"Oural",
    "sg:orig_category":"Agricultura: Abastecimiento Y Cosechado (negocio)",
    "sg:phone":"+34 982 54 66 29",
    "sg:postcode":"27392",
    "sg:province":"Lugo",
    "wof:name":"Caldas Lopez Miguel",
    "wof:placetype":"venue"
},
  "geometry": {"coordinates":[-7.4538698196,42.722984314],"type":"Point"}
}