{
  "type": "Feature",
  "properties": {
    "addr:full":"Calle de Cuchilleria, 94 Vitoria-gasteiz \u00c1lava 01001",
    "addr:housenumber":"94",
    "addr:postcode":"01001",
    "addr:street":"Calle De Cuchilleria",
    "iso:country":"ES",
    "sg:address":"Calle de Cuchilleria, 94",
    "sg:city":"Vitoria-gasteiz",
    "sg:orig_category":"Asociaciones Humanitarias, De Cooperaci\u00d3n, De Acci\u00d3n Social",
    "sg:phone":"+34 945 26 90 12",
    "sg:postcode":"01001",
    "sg:province":"\u00c1lava",
    "wof:name":"Gizarterako",
    "wof:placetype":"venue"
},
  "geometry": {"coordinates":[-2.6717600822,42.8509216309],"type":"Point"}
}