{
  "type": "Feature",
  "properties": {
    "iso:country":"ES",
    "sg:address":"Calle de Independencia, 3",
    "sg:city":"Vitoria-gasteiz",
    "sg:orig_category":"Caf\u00c9s, Bares, Cervecer\u00cdas",
    "sg:phone":"+34 945 14 63 21",
    "sg:postcode":"01005",
    "sg:province":"\u00c1lava",
    "wof:name":"Servidenda S.a.",
    "wof:placetype":"venue"
},
  "geometry": {"coordinates":[-2.6697919369,42.8449897766],"type":"Point"}
}