{
  "type": "Feature",
  "properties": {
    "addr:full":"Gatomorto, 65 Sta. Maria De Xeve Pontevedra 36151",
    "addr:housenumber":"65",
    "addr:postcode":"36151",
    "addr:street":"Gatomorto;Maria",
    "iso:country":"ES",
    "sg:address":"Gatomorto, 65",
    "sg:city":"Sta. Maria De Xeve",
    "sg:classifiers":[
        {
            "category":"Manufacturing",
            "subcategory":"Building Materials",
            "type":"Manufacturing & Wholesale Goods"
        }
    ],
    "sg:phone":"+34 986 87 92 16",
    "sg:postcode":"36151",
    "sg:province":"Pontevedra",
    "sg:tags":[
        "cemento",
        "y",
        "de",
        "fabricaci\u00d3n",
        "cal"
    ],
    "wof:name":"Rivas Sobral Jesus Manuel",
    "wof:placetype":"venue"
},
  "geometry": {"coordinates":[-8.6209402084,42.4811553955],"type":"Point"}
}