{
  "type": "Feature",
  "properties": {
    "iso:country":"ES",
    "sg:address":"Carrer de Mare Molas, 65",
    "sg:city":"Reus",
    "sg:orig_category":"Electricidad, Electr\u00d3nica: Material Y Suministros (al Por Mayor)",
    "sg:phone":"+34 977 31 02 70",
    "sg:postcode":"43202",
    "sg:province":"Tarragona",
    "wof:name":"Aguilo Nomen S.c.p.",
    "wof:placetype":"venue"
},
  "geometry": {"coordinates":[1.0982929468,41.1503295898],"type":"Point"}
}