{
  "type": "Feature",
  "properties": {
    "iso:country":"ES",
    "sg:address":"Rua Coru\u00d1a, 10",
    "sg:city":"Ourense",
    "sg:orig_category":"Zapatos (al Por Menor)",
    "sg:phone":"+34 988 25 35 01",
    "sg:postcode":"32005",
    "sg:province":"Ourense",
    "wof:name":"Calvi\u00f1o Novoa Felix",
    "wof:placetype":"venue"
},
  "geometry": {"coordinates":[-7.8637561798,42.3304252625],"type":"Point"}
}