{
  "type": "Feature",
  "properties": {
    "addr:full":"Pg Lloren\u00c7 Serra, 49 Santa Coloma De Gramenet Barcelona 08922",
    "addr:housenumber":"49",
    "addr:postcode":"08922",
    "addr:street":"Pg Llorenc\u0327 Serra",
    "iso:country":"ES",
    "sg:address":"Pg Lloren\u00c7 Serra, 49",
    "sg:city":"Santa Coloma De Gramenet",
    "sg:orig_category":"Agentes, Concesionarios Y Sucursales De Veh\u00cdculos",
    "sg:phone":"+34 934 66 18 61",
    "sg:postcode":"08922",
    "sg:province":"Barcelona",
    "wof:name":"Auto Rami S.l.",
    "wof:placetype":"venue"
},
  "geometry": {"coordinates":[2.2045309544,41.4499931335],"type":"Point"}
}