{
  "type": "Feature",
  "properties": {
    "iso:country":"ES",
    "sg:address":"Carr Argenteria, 13",
    "sg:city":"Girona",
    "sg:orig_category":"Bisuter\u00cda, Joyer\u00cda, Relojer\u00cda (al Por Menor)",
    "sg:phone":"+34 972 22 76 48",
    "sg:postcode":"17004",
    "sg:province":"Girona",
    "wof:name":"Crespo Cortinas Francisco De Borja",
    "wof:placetype":"venue"
},
  "geometry": {"coordinates":[2.8244140148,41.9849815369],"type":"Point"}
}