{
  "type": "Feature",
  "properties": {
    "iso:country":"ES",
    "sg:address":"Logrosa, 18",
    "sg:city":"Logrosa",
    "sg:orig_category":"Centros Empresariales",
    "sg:phone":"+34 981 88 51 19",
    "sg:postcode":"15830",
    "sg:province":"La Coru\u00f1a",
    "wof:name":"Atrio Gonzalez Alfredo Jesus",
    "wof:placetype":"venue"
},
  "geometry": {"coordinates":[-8.7368841171,42.9089660645],"type":"Point"}
}