{
  "type": "Feature",
  "properties": {
    "iso:country":"ES",
    "sg:address":"Carrer de Cami Ral, 41",
    "sg:city":"Esparreguera",
    "sg:orig_category":"Bebidas",
    "sg:phone":"+34 937 70 87 35",
    "sg:postcode":"08292",
    "sg:province":"Barcelona",
    "wof:name":"Realespar S.l.",
    "wof:placetype":"venue"
},
  "geometry": {"coordinates":[1.8712849617,41.5335845947],"type":"Point"}
}