{
  "type": "Feature",
  "properties": {
    "iso:country":"ES",
    "sg:address":"Cno. Cementerio, S/n",
    "sg:city":"Andujar",
    "sg:orig_category":"Cementerios",
    "sg:phone":"+34 953 51 21 14",
    "sg:postcode":"23740",
    "sg:province":"Ja\u00e9n",
    "wof:name":"Ayuntamiento De Andujar",
    "wof:placetype":"venue"
},
  "geometry": {"coordinates":[-4.1113605499,37.9769706726],"type":"Point"}
}