{
  "type": "Feature",
  "properties": {
    "iso:country":"ES",
    "sg:address":"Calle de Jolastokieta, 1 B",
    "sg:city":"Getxo",
    "sg:orig_category":"Pescader\u00cdas (al Por Menor)",
    "sg:phone":"+34 944 63 69 23",
    "sg:postcode":"48930",
    "sg:province":"Vizcaya",
    "wof:name":"Emilio Gonzalez Lopez",
    "wof:placetype":"venue"
},
  "geometry": {"coordinates":[-3.0068490505,43.3258285522],"type":"Point"}
}