{
  "type": "Feature",
  "properties": {
    "iso:country":"ES",
    "sg:address":"Calle de Victor Hevia, 27",
    "sg:city":"Oviedo",
    "sg:orig_category":"Importaci\u00d3n",
    "sg:phone":"+34 985 27 03 10",
    "sg:postcode":"33012",
    "sg:province":"Asturias",
    "wof:name":"Ambra Importaciones S.l.",
    "wof:placetype":"venue"
},
  "geometry": {"coordinates":[-5.8647656441,43.3677253723],"type":"Point"}
}