{
  "type": "Feature",
  "properties": {
    "iso:country":"ES",
    "sg:address":"Plaz Charco, S/n",
    "sg:city":"Montoro",
    "sg:classifiers":[
        {
            "category":"Taxi",
            "type":"Transportation"
        }
    ],
    "sg:phone":"+34 957 16 03 49",
    "sg:postcode":"14600",
    "sg:province":"C\u00f3rdoba",
    "wof:name":"Ayuntamiento De Montoro",
    "wof:placetype":"venue"
},
  "geometry": {"coordinates":[-4.3830528259,38.0235290527],"type":"Point"}
}