{
  "type": "Feature",
  "properties": {
    "iso:country":"ES",
    "sg:address":"Avda San Amador, 84",
    "sg:city":"Martos",
    "sg:orig_category":"M\u00c9dicos: An\u00c1lisis Cl\u00cdnicos",
    "sg:phone":"+34 953 55 10 18",
    "sg:postcode":"23600",
    "sg:province":"Ja\u00e9n",
    "wof:name":"Barranco Navero Manuel",
    "wof:placetype":"venue"
},
  "geometry": {"coordinates":[-3.9768800735,37.7192497253],"type":"Point"}
}