{
  "type": "Feature",
  "properties": {
    "addr:full":"Carrer de Ciutat De Balaguer, 10 Barcelona Barcelona 08022",
    "addr:housenumber":"10",
    "addr:postcode":"08022",
    "addr:street":"Carrer De Ciutat De Balaguer",
    "iso:country":"ES",
    "sg:address":"Carrer de Ciutat De Balaguer, 10",
    "sg:city":"Barcelona",
    "sg:orig_category":"Producci\u00d3n, Distribuci\u00d3n De Electricidad",
    "sg:phone":"+34 932 11 24 04",
    "sg:postcode":"08022",
    "sg:province":"Barcelona",
    "wof:name":"Gasvall General D' Instal.lacions S.l.",
    "wof:placetype":"venue"
},
  "geometry": {"coordinates":[2.1366450787,41.4024085999],"type":"Point"}
}