{
  "type": "Feature",
  "properties": {
    "addr:full":"Calle de Bereterretxe, 10 Altzaga Vizcaya 48950",
    "addr:housenumber":"10",
    "addr:postcode":"48950",
    "addr:street":"Calle De Bereterretxe",
    "iso:country":"ES",
    "sg:address":"Calle de Bereterretxe, 10",
    "sg:city":"Altzaga",
    "sg:orig_category":"Forjas Y Altos Hornos",
    "sg:phone":"+34 944 17 02 53",
    "sg:postcode":"48950",
    "sg:province":"Vizcaya",
    "wof:name":"Adrian Rodriguez Gamero Y Otros S.cv.",
    "wof:placetype":"venue"
},
  "geometry": {"coordinates":[-2.9738337994,43.3019676208],"type":"Point"}
}