{
  "type": "Feature",
  "properties": {
    "addr:full":"Calle de Sociedad, 12 San Bartolome Murcia 30004",
    "addr:housenumber":"12",
    "addr:postcode":"30004",
    "addr:street":"Calle De Sociedad",
    "iso:country":"ES",
    "sg:address":"Calle de Sociedad, 12",
    "sg:city":"San Bartolome",
    "sg:orig_category":"Importaci\u00d3n, Exportaci\u00d3n Y Comercios De Productos Textiles",
    "sg:phone":"+34 968 21 86 54",
    "sg:postcode":"30004",
    "sg:province":"Murcia",
    "wof:name":"Jerez Hernandez Salvador",
    "wof:placetype":"venue"
},
  "geometry": {"coordinates":[-1.1308549643,37.9844856262],"type":"Point"}
}