{
  "type": "Feature",
  "properties": {
    "iso:country":"ES",
    "sg:address":"Avda Corbaceiras (las), 58",
    "sg:city":"Pontevedra",
    "sg:orig_category":"Promotores Constructores",
    "sg:phone":"+34 986 86 63 09",
    "sg:postcode":"36002",
    "sg:province":"Pontevedra",
    "wof:name":"De Montes Empresa Constructora S.l.",
    "wof:placetype":"venue"
},
  "geometry": {"coordinates":[-8.6233987808,42.4448699951],"type":"Point"}
}