{
  "type": "Feature",
  "properties": {
    "iso:country":"ES",
    "sg:address":"Ctra. Jerez-arcos, Km. 0012,0",
    "sg:city":"Jerez",
    "sg:orig_category":"Deportes Diversos",
    "sg:phone":"+34 956 15 11 00",
    "sg:postcode":"11...",
    "sg:province":"C\u00e1diz",
    "sg:website":"www.circuitodejerez.com",
    "wof:name":"Circuito De Jerez S.l.",
    "wof:placetype":"venue"
},
  "geometry": {"coordinates":[-6.1348700523,36.6909408569],"type":"Point"}
}