{
  "type": "Feature",
  "properties": {
    "iso:country":"ES",
    "sg:address":"Calle de Andalucia De Iznalloz, 34",
    "sg:city":"Iznalloz",
    "sg:orig_category":"Caf\u00c9s, Bares, Cervecer\u00cdas",
    "sg:phone":"+34 958 39 62 85",
    "sg:postcode":"18550",
    "sg:province":"Granada",
    "wof:name":"Rodriguez Moreno Rafael",
    "wof:placetype":"venue"
},
  "geometry": {"coordinates":[-3.5610260963,37.4360160828],"type":"Point"}
}