{
  "type": "Feature",
  "properties": {
    "addr:full":"Calle de Segundo Izpizua, 8 Donostia-san Sebastian Guip\u00f9zcoa 20001",
    "addr:housenumber":"8",
    "addr:postcode":"20001",
    "addr:street":"Calle De Segundo Izpizua",
    "iso:country":"ES",
    "sg:address":"Calle de Segundo Izpizua, 8",
    "sg:city":"Donostia-san Sebastian",
    "sg:orig_category":"Institutos De Belleza",
    "sg:phone":"+34 943 29 14 14",
    "sg:postcode":"20001",
    "sg:province":"Guip\u00f9zcoa",
    "wof:name":"Llamas Pajares Basilisa",
    "wof:placetype":"venue"
},
  "geometry": {"coordinates":[-1.9720220566,43.3252792358],"type":"Point"}
}