{
  "type": "Feature",
  "properties": {
    "iso:country":"ES",
    "sg:address":"Carrer de Reina Elionor, 13",
    "sg:city":"Sabadell",
    "sg:orig_category":"Suministros Para Hoteles",
    "sg:phone":"+34 937 15 58 98",
    "sg:postcode":"08205",
    "sg:province":"Barcelona",
    "wof:name":"Vives Lopez S.l.",
    "wof:placetype":"venue"
},
  "geometry": {"coordinates":[2.1020050049,41.5412101746],"type":"Point"}
}