{
  "type": "Feature",
  "properties": {
    "addr:full":"Calle de Toribio Alzaga, 15 Donostia-san Sebastian Guip\u00f9zcoa 20011",
    "addr:housenumber":"15",
    "addr:postcode":"20011",
    "addr:street":"Calle De Toribio Alzaga",
    "iso:country":"ES",
    "sg:address":"Calle de Toribio Alzaga, 15",
    "sg:city":"Donostia-san Sebastian",
    "sg:orig_category":"Inform\u00c1tica: Material Y Suministros",
    "sg:phone":"+34 943 45 89 62",
    "sg:postcode":"20011",
    "sg:province":"Guip\u00f9zcoa",
    "wof:name":"Sistemas Informaticos Castilla S.l.",
    "wof:placetype":"venue"
},
  "geometry": {"coordinates":[-1.9721139669,43.3044204712],"type":"Point"}
}