{
  "type": "Feature",
  "properties": {
    "addr:full":"Calle de Malaga, 7 Mijas M\u00e1laga 29650",
    "addr:housenumber":"7",
    "addr:postcode":"29650",
    "addr:street":"Calle De Malaga",
    "iso:country":"ES",
    "sg:address":"Calle de Malaga, 7",
    "sg:city":"Mijas",
    "sg:orig_category":"Bisuter\u00cda, Joyer\u00cda, Relojer\u00cda (al Por Menor)",
    "sg:phone":"+34 952 48 53 09",
    "sg:postcode":"29650",
    "sg:province":"M\u00e1laga",
    "wof:name":"Garcia Millan Juan",
    "wof:placetype":"venue"
},
  "geometry": {"coordinates":[-4.6386289597,36.595287323],"type":"Point"}
}