{
  "type": "Feature",
  "properties": {
    "iso:country":"ES",
    "sg:address":"Carr Sant Antoni, 73",
    "sg:city":"Vilavella",
    "sg:orig_category":"Promotores Constructores",
    "sg:phone":"+34 964 67 72 09",
    "sg:postcode":"12526",
    "sg:province":"Castell\u00f3n",
    "wof:name":"Carratala Sales Jose",
    "wof:placetype":"venue"
},
  "geometry": {"coordinates":[-0.0456800014,39.9851417542],"type":"Point"}
}