{
  "type": "Feature",
  "properties": {
    "addr:full":"Cmno Via Vieja De Lezama, 39 Bilbao Vizcaya 48007",
    "addr:housenumber":"39",
    "addr:postcode":"48007",
    "addr:street":"Cmno Via Vieja De Lezama",
    "iso:country":"ES",
    "sg:address":"Cmno Via Vieja De Lezama, 39",
    "sg:city":"Bilbao",
    "sg:orig_category":"Empresas De Carpinter\u00cda De Madera",
    "sg:phone":"+34 944 06 21 15",
    "sg:postcode":"48007",
    "sg:province":"Vizcaya",
    "wof:name":"Carpinteria Ebanisteria Redondo Sl",
    "wof:placetype":"venue"
},
  "geometry": {"coordinates":[-2.9139060974,43.2660636902],"type":"Point"}
}