{
  "type": "Feature",
  "properties": {
    "iso:country":"ES",
    "sg:address":"Calle de Fuero De Cuenca, S/n",
    "sg:city":"Moratalla",
    "sg:orig_category":"Aguas (distribuci\u00d3n, Servicios)",
    "sg:phone":"+34 968 70 61 51",
    "sg:postcode":"30440",
    "sg:province":"Murcia",
    "wof:name":"Aqualia Gestion Integral Del Agua S.a.",
    "wof:placetype":"venue"
},
  "geometry": {"coordinates":[-1.8911280632,38.1859931946],"type":"Point"}
}