{
  "type": "Feature",
  "properties": {
    "iso:country":"ES",
    "sg:address":"Afueras, S/n",
    "sg:city":"Campanet",
    "sg:orig_category":"Parques De Atracciones Y Centros De Esparcimiento",
    "sg:phone":"+34 971 51 66 25",
    "sg:postcode":"07310",
    "sg:province":"Islas Baleares",
    "wof:name":"Fondo Para La Conservacion Del Buitre Negro",
    "wof:placetype":"venue"
},
  "geometry": {"coordinates":[2.9658000469,39.7748908997],"type":"Point"}
}