{
  "type": "Feature",
  "properties": {
    "iso:country":"ES",
    "sg:address":"Calle de Cristobal De Franchy, 10",
    "sg:city":"Orotava",
    "sg:orig_category":"Arquitectos",
    "sg:phone":"+34 922 33 48 24",
    "sg:postcode":"38300",
    "sg:province":"Santa Cruz De Tenerife",
    "wof:name":"Quono Arquitectos S.l.",
    "wof:placetype":"venue"
},
  "geometry": {"coordinates":[-16.5289421082,28.3943061829],"type":"Point"}
}