{
  "type": "Feature",
  "properties": {
    "addr:full":"Av. Petroleo, 34 Leganes Madrid 28918",
    "addr:housenumber":"34",
    "addr:postcode":"28918",
    "addr:street":"Av. Petroleo",
    "iso:country":"ES",
    "sg:address":"Av. Petroleo, 34",
    "sg:city":"Leganes",
    "sg:orig_category":"Grafistas",
    "sg:phone":"+34 914 88 02 10",
    "sg:postcode":"28918",
    "sg:province":"Madrid",
    "wof:name":"Creativos Y Dise\u00f1o Grafico Europeos S.l.",
    "wof:placetype":"venue"
},
  "geometry": {"coordinates":[-3.7996900082,40.352230072],"type":"Point"}
}