{
  "type": "Feature",
  "properties": {
    "addr:full":"Calle de Hilario Perez, 13 Santo Domingo De La Calzada La Rioja 26250",
    "addr:housenumber":"13",
    "addr:postcode":"26250",
    "addr:street":"Calle De Hilario Perez;Rioja",
    "iso:country":"ES",
    "sg:address":"Calle de Hilario Perez, 13",
    "sg:city":"Santo Domingo De La Calzada",
    "sg:orig_category":"Carnicer\u00cdas, Carnicer\u00cdas",
    "sg:phone":"+34 941 34 09 29",
    "sg:postcode":"26250",
    "sg:province":"La Rioja",
    "wof:name":"Javier Garcia Metola Y Otra Cdad",
    "wof:placetype":"venue"
},
  "geometry": {"coordinates":[-2.9538319111,42.4407691956],"type":"Point"}
}