{
  "type": "Feature",
  "properties": {
    "iso:country":"ES",
    "sg:address":"Calle de General Franco, 13",
    "sg:city":"Alar Del Rey",
    "sg:orig_category":"Bancos",
    "sg:phone":"+34 979 13 34 09",
    "sg:postcode":"34480",
    "sg:province":"Palencia",
    "sg:website":"www.gruposantander.es",
    "wof:name":"Bt Espa\u00d1a Compa\u00d1ia De Servicios Globales De Telecomunicaciones S.a.u.",
    "wof:placetype":"venue"
},
  "geometry": {"coordinates":[-4.309887886,42.659450531],"type":"Point"}
}