{
  "type": "Feature",
  "properties": {
    "addr:full":"Calle de Antioco, 21 Ceuta Ceuta 51001",
    "addr:housenumber":"21",
    "addr:postcode":"51001",
    "addr:street":"Calle De Antioco",
    "iso:country":"ES",
    "sg:address":"Calle de Antioco, 21",
    "sg:city":"Ceuta",
    "sg:orig_category":"Bazares, Art\u00cdculos De Limpieza Y De Cocina (al Por Menor)",
    "sg:phone":"+34 956 51 89 07",
    "sg:postcode":"51001",
    "sg:province":"Ceuta",
    "wof:name":"Chandiram Mulchand Daryanani",
    "wof:placetype":"venue"
},
  "geometry": {"coordinates":[-5.3092236519,35.8881912231],"type":"Point"}
}