{
  "type": "Feature",
  "properties": {
    "iso:country":"ES",
    "sg:address":"Carrer de Girona, 109",
    "sg:city":"Barcelona",
    "sg:orig_category":"Cajas Para Embalar",
    "sg:phone":"+34 934 58 83 01",
    "sg:postcode":"08009",
    "sg:province":"Barcelona",
    "wof:name":"Cajamar",
    "wof:placetype":"venue"
},
  "geometry": {"coordinates":[2.1683490276,41.3967437744],"type":"Point"}
}