{
  "type": "Feature",
  "properties": {
    "addr:full":"Calle de Caridad, 34 Pozuelo De Alarcon Madrid 28224",
    "addr:housenumber":"34",
    "addr:postcode":"28224",
    "addr:street":"Calle De Caridad",
    "iso:country":"ES",
    "sg:address":"Calle de Caridad, 34",
    "sg:city":"Pozuelo De Alarcon",
    "sg:orig_category":"Asilos De Ancianos. Centros Privados",
    "sg:phone":"+34 913 51 09 18",
    "sg:postcode":"28224",
    "sg:province":"Madrid",
    "wof:name":"Residencia Alarcon .",
    "wof:placetype":"venue"
},
  "geometry": {"coordinates":[-3.7986519337,40.4436569214],"type":"Point"}
}