{
  "type": "Feature",
  "properties": {
    "iso:country":"ES",
    "sg:address":"Av Catalunya, 29",
    "sg:city":"Alfarras",
    "sg:orig_category":"\u00d3ptica: Instrumentos (fabricaci\u00d3n)",
    "sg:phone":"+34 973 76 06 89",
    "sg:postcode":"25120",
    "sg:province":"Lleida",
    "wof:name":"Borras Optics S.l.",
    "wof:placetype":"venue"
},
  "geometry": {"coordinates":[0.569945991,41.8291015625],"type":"Point"}
}