{
  "type": "Feature",
  "properties": {
    "addr:full":"Ama Kandida Etorbidea, 21 Andoain Guip\u00f9zcoa 20140",
    "addr:housenumber":"21",
    "addr:postcode":"20140",
    "addr:street":"Ama Kandida Etorbidea;Guipu\u0300Zcoa",
    "iso:country":"ES",
    "sg:address":"Ama Kandida Etorbidea, 21",
    "sg:city":"Andoain",
    "sg:orig_category":"Productos Qu\u00cdmicos (fabricaci\u00d3n, Al Por Mayor)",
    "sg:phone":"+34 943 59 00 14",
    "sg:postcode":"20140",
    "sg:province":"Guip\u00f9zcoa",
    "wof:name":"Jose Maria Insausti S.l.",
    "wof:placetype":"venue"
},
  "geometry": {"coordinates":[-2.0194408894,43.222618103],"type":"Point"}
}