{
  "type": "Feature",
  "properties": {
    "addr:full":"Calle de Antonio Cachero, 6 Gijon Asturias 33209",
    "addr:housenumber":"6",
    "addr:postcode":"33209",
    "addr:street":"Calle De Antonio Cachero",
    "iso:country":"ES",
    "sg:address":"Calle de Antonio Cachero, 6",
    "sg:city":"Gijon",
    "sg:orig_category":"Pescader\u00cdas (al Por Menor)",
    "sg:phone":"+34 985 39 03 19",
    "sg:postcode":"33209",
    "sg:province":"Asturias",
    "wof:name":"Cuervo Calderon Maria Del Carmen",
    "wof:placetype":"venue"
},
  "geometry": {"coordinates":[-5.6590929031,43.5347671509],"type":"Point"}
}