{
  "type": "Feature",
  "properties": {
    "iso:country":"ES",
    "sg:address":"Carrer de Guell I Ferrer, 37",
    "sg:city":"Sabadell",
    "sg:orig_category":"Construcci\u00d3n Mec\u00c1nica",
    "sg:phone":"+34 937 11 28 07",
    "sg:postcode":"08203",
    "sg:province":"Barcelona",
    "wof:name":"Pe\u00f1a Roman Indalecio",
    "wof:placetype":"venue"
},
  "geometry": {"coordinates":[2.115309,41.5388259888],"type":"Point"}
}