{
  "type": "Feature",
  "properties": {
    "addr:full":"Carrer de Guell I Ferrer, 177 Sabadell Barcelona 08203",
    "addr:housenumber":"177",
    "addr:postcode":"08203",
    "addr:street":"Carrer De Guell I Ferrer",
    "iso:country":"ES",
    "sg:address":"Carrer de Guell I Ferrer, 177",
    "sg:city":"Sabadell",
    "sg:orig_category":"Reciclaje, Desguace De Veh\u00cdculos",
    "sg:phone":"+34 937 10 02 30",
    "sg:postcode":"08203",
    "sg:province":"Barcelona",
    "wof:name":"Garcia Gonzalez Domingo",
    "wof:placetype":"venue"
},
  "geometry": {"coordinates":[2.1178300381,41.5336418152],"type":"Point"}
}