{
  "type": "Feature",
  "properties": {
    "iso:country":"ES",
    "sg:address":"Ctra, Puesto Rubio, S/n",
    "sg:city":"Santa Maria Aguila",
    "sg:orig_category":"Servicio De Salud",
    "sg:phone":"+34 950 58 32 40",
    "sg:postcode":"04710",
    "sg:province":"Almer\u00eda",
    "wof:name":"Aguaconfort Hydrotec S.l.",
    "wof:placetype":"venue"
},
  "geometry": {"coordinates":[-2.7544960976,36.7629699707],"type":"Point"}
}