{
  "type": "Feature",
  "properties": {
    "addr:full":"Rua San Roque (de), 21 Santiago De Compostela La Coru\u00f1a 15704",
    "addr:housenumber":"21",
    "addr:postcode":"15704",
    "addr:street":"Rua San Roque De;Corun\u0303A",
    "iso:country":"ES",
    "sg:address":"Rua San Roque (de), 21",
    "sg:city":"Santiago De Compostela",
    "sg:orig_category":"Farmacias",
    "sg:phone":"+34 981 58 22 33",
    "sg:postcode":"15704",
    "sg:province":"La Coru\u00f1a",
    "wof:name":"Farmacia Herederos De Mafalda Gonzalez Carrero",
    "wof:placetype":"venue"
},
  "geometry": {"coordinates":[-8.5418539047,42.8841323853],"type":"Point"}
}