{
  "type": "Feature",
  "properties": {
    "addr:full":"Carr Filoleg Sanchis Guarner, 10 Petrer Alicante 03610",
    "addr:housenumber":"10",
    "addr:postcode":"03610",
    "addr:street":"Carr Filoleg;Guarner",
    "iso:country":"ES",
    "sg:address":"Carr Filoleg Sanchis Guarner, 10",
    "sg:city":"Petrer",
    "sg:orig_category":"Comercio, Reparaci\u00d3n De Bicicletas, De Motocicletas, De Accesorios",
    "sg:phone":"+34 965 37 75 22",
    "sg:postcode":"03610",
    "sg:province":"Alicante",
    "wof:name":"Biciesport Poli S.l.",
    "wof:placetype":"venue"
},
  "geometry": {"coordinates":[-0.7820360065,38.4809761047],"type":"Point"}
}