{
  "type": "Feature",
  "properties": {
    "iso:country":"ES",
    "sg:address":"Rua Xeneral Pardi\u00d1as (do), 18",
    "sg:city":"Santiago De Compostela",
    "sg:orig_category":"Notarios",
    "sg:phone":"+34 981 55 34 32",
    "sg:postcode":"15701",
    "sg:province":"La Coru\u00f1a",
    "wof:name":"Pardo Garcia Hector Ramiro",
    "wof:placetype":"venue"
},
  "geometry": {"coordinates":[-8.5459947586,42.8748970032],"type":"Point"}
}