{
  "type": "Feature",
  "properties": {
    "addr:full":"Primero De Mayo, 7 Huesa Ja\u00e9n 23487",
    "addr:housenumber":"7",
    "addr:postcode":"23487",
    "addr:street":"Primero;Mayo",
    "iso:country":"ES",
    "sg:address":"Primero De Mayo, 7",
    "sg:city":"Huesa",
    "sg:orig_category":"Quincaller\u00cda (al Por Menor)",
    "sg:phone":"+34 953 71 55 08",
    "sg:postcode":"23487",
    "sg:province":"Ja\u00e9n",
    "wof:name":"Zamora Esquinas Jose Manuel",
    "wof:placetype":"venue"
},
  "geometry": {"coordinates":[-3.0771353245,37.7646980286],"type":"Point"}
}