{
  "type": "Feature",
  "properties": {
    "iso:country":"ES",
    "sg:address":"Carr Creueta, S/n",
    "sg:city":"Guissona",
    "sg:orig_category":"Electricidad Veh\u00cdculo",
    "sg:phone":"+34 973 55 02 92",
    "sg:postcode":"25210",
    "sg:province":"Lleida",
    "wof:name":"Barbero Hernando Pascual",
    "wof:placetype":"venue"
},
  "geometry": {"coordinates":[1.2918950319,41.7836799622],"type":"Point"}
}