{
  "type": "Feature",
  "properties": {
    "addr:full":"Calle de Real, 143 S. Fernando C\u00e1diz 11100",
    "addr:housenumber":"143",
    "addr:postcode":"11100",
    "addr:street":"Calle De Real;S. Fernando Ca\u0301Diz",
    "iso:country":"ES",
    "sg:address":"Calle de Real, 143",
    "sg:city":"S. Fernando",
    "sg:orig_category":"Farmacias",
    "sg:phone":"+34 956 88 19 33",
    "sg:postcode":"11100",
    "sg:province":"C\u00e1diz",
    "wof:name":"Campos Ba\u00f1ales Jose Carlos",
    "wof:placetype":"venue"
},
  "geometry": {"coordinates":[-6.1974987984,36.4646224976],"type":"Point"}
}