{
  "type": "Feature",
  "properties": {
    "addr:full":"Avda Aguilera, 22 Alacant Alicante 03...",
    "addr:housenumber":"22;03 ...",
    "addr:street":"Avda Aguilera;Alicante",
    "iso:country":"ES",
    "sg:address":"Avda Aguilera, 22",
    "sg:city":"Alacant",
    "sg:classifiers":[
        {
            "category":"Communications",
            "type":"Services"
        }
    ],
    "sg:phone":"+34 965 22 36 00",
    "sg:postcode":"03...",
    "sg:province":"Alicante",
    "sg:tags":[
        "televisiones",
        "y",
        "radio"
    ],
    "wof:name":"Radio Televisio Valenciana",
    "wof:placetype":"venue"
},
  "geometry": {"coordinates":[-0.5038599968,38.3429756165],"type":"Point"}
}