{
  "type": "Feature",
  "properties": {
    "iso:country":"ES",
    "sg:address":"Poligono Industrial Aldayturriaga, 4",
    "sg:city":"Amurrio",
    "sg:orig_category":"Empresas De Carpinter\u00cda",
    "sg:phone":"+34 945 39 34 28",
    "sg:postcode":"01470",
    "sg:province":"\u00c1lava",
    "wof:name":"Aluminios Valle De Ayala S.l.",
    "wof:placetype":"venue"
},
  "geometry": {"coordinates":[-2.9475662708,43.0302124023],"type":"Point"}
}