{
  "type": "Feature",
  "properties": {
    "iso:country":"ES",
    "sg:address":"Avda Leganes, 21",
    "sg:city":"Alcorcon",
    "sg:orig_category":"Sindicatos De Trabajadores",
    "sg:phone":"+34 916 11 02 02",
    "sg:postcode":"28924",
    "sg:province":"Madrid",
    "wof:name":"Union Sindical Madrid Region De Comisiones Obreras",
    "wof:placetype":"venue"
},
  "geometry": {"coordinates":[-3.8159999847,40.346912384],"type":"Point"}
}