{
  "type": "Feature",
  "properties": {
    "iso:country":"ES",
    "sg:address":"Avda Vigo, 246",
    "sg:city":"Laredo",
    "sg:orig_category":"Prot\u00c9sicos Dentales",
    "sg:phone":"+34 986 45 19 80",
    "sg:postcode":"36320",
    "sg:province":"Pontevedra",
    "wof:name":"Manuel Enrique Delgado S.l.u.",
    "wof:placetype":"venue"
},
  "geometry": {"coordinates":[-8.6428003311,42.4304618835],"type":"Point"}
}