{
  "type": "Feature",
  "properties": {
    "addr:full":"Calle de Ramon Y Cajal, 2 Torrent Valencia 46900",
    "addr:housenumber":"2",
    "addr:postcode":"46900",
    "addr:street":"Calle De Ramon Y Cajal;Valencia",
    "iso:country":"ES",
    "sg:address":"Calle de Ramon Y Cajal, 2",
    "sg:city":"Torrent",
    "sg:orig_category":"Relojer\u00cda (al Por Menor, Reparaci\u00d3n)",
    "sg:phone":"+34 961 55 05 98",
    "sg:postcode":"46900",
    "sg:province":"Valencia",
    "wof:name":"Garcia Morant Teresa",
    "wof:placetype":"venue"
},
  "geometry": {"coordinates":[-0.4662989974,39.4371185303],"type":"Point"}
}