{
  "type": "Feature",
  "properties": {
    "iso:country":"ES",
    "sg:address":"San Crist\u00f3bal, 21",
    "sg:city":"Montanejos",
    "sg:orig_category":"Electrodom\u00c9sticos (al Por Menor)",
    "sg:phone":"+34 964 13 10 81",
    "sg:postcode":"12448",
    "sg:province":"Castell\u00f3n",
    "wof:name":"Vicente Valero Montanejos S.l.",
    "wof:placetype":"venue"
},
  "geometry": {"coordinates":[-0.5234130025,40.0671844482],"type":"Point"}
}