{
  "type": "Feature",
  "properties": {
    "addr:full":"Calle de Albareda, 76 Palmas De Gran Canaria Las Palmas 35008",
    "addr:housenumber":"76",
    "addr:postcode":"35008",
    "addr:street":"Calle De Albareda",
    "iso:country":"ES",
    "sg:address":"Calle de Albareda, 76",
    "sg:city":"Palmas De Gran Canaria",
    "sg:orig_category":"Bisuter\u00cda, Joyer\u00cda, Relojer\u00cda (al Por Menor)",
    "sg:phone":"+34 928 46 45 87",
    "sg:postcode":"35008",
    "sg:province":"Las Palmas",
    "wof:name":"Quintana Santana Jose Oriol",
    "wof:placetype":"venue"
},
  "geometry": {"coordinates":[-15.4293460846,28.1477241516],"type":"Point"}
}