{
  "type": "Feature",
  "properties": {
    "iso:country":"ES",
    "sg:address":"Calle de Paz, 13",
    "sg:city":"Yebenes",
    "sg:orig_category":"Supermercados Y Hipermercados",
    "sg:phone":"+34 925 32 01 59",
    "sg:postcode":"45470",
    "sg:province":"Toledo",
    "wof:name":"Carsagralosan S.l.",
    "wof:placetype":"venue"
},
  "geometry": {"coordinates":[-3.8702089787,39.5812301636],"type":"Point"}
}