{
  "type": "Feature",
  "properties": {
    "addr:full":"Pase Olivos (de Los), 128 Parque Coimbra Madrid 28935",
    "addr:housenumber":"128",
    "addr:postcode":"28935",
    "iso:country":"ES",
    "sg:address":"Pase Olivos (de Los), 128",
    "sg:city":"Parque Coimbra",
    "sg:orig_category":"Frutas, Legumbres Frescas Y Tempranas (al Por Menor)",
    "sg:phone":"+34 914 96 95 71",
    "sg:postcode":"28935",
    "sg:province":"Madrid",
    "wof:name":"Garcia Ricote Jose Manuel",
    "wof:placetype":"venue"
},
  "geometry": {"coordinates":[-3.9356191158,40.3006896973],"type":"Point"}
}