{
  "type": "Feature",
  "properties": {
    "addr:full":"Carrer de Francesc Macia, 12 Berga-ciudad Barcelona 08600",
    "addr:housenumber":"12",
    "addr:postcode":"08600",
    "addr:street":"Carrer De Francesc Macia;Barcelona",
    "iso:country":"ES",
    "sg:address":"Carrer de Francesc Macia, 12",
    "sg:city":"Berga-ciudad",
    "sg:orig_category":"Cr\u00cda De Animales",
    "sg:phone":"+34 938 22 00 92",
    "sg:postcode":"08600",
    "sg:province":"Barcelona",
    "wof:name":"Ramaders De Muntanya Del Bergueda S.c.c.l.",
    "wof:placetype":"venue"
},
  "geometry": {"coordinates":[1.8459039927,42.0984916687],"type":"Point"}
}