{
  "type": "Feature",
  "properties": {
    "iso:country":"ES",
    "sg:address":"Cm\u00d1o Ameixeira, 1",
    "sg:city":"Ameixeira",
    "sg:orig_category":"Asociaciones Y Clubs Deportivos",
    "sg:phone":"+34 986 21 11 11",
    "sg:postcode":"36212",
    "sg:province":"Pontevedra",
    "wof:name":"Arenas De Alcabre S.c.d.",
    "wof:placetype":"venue"
},
  "geometry": {"coordinates":[-8.6480531693,42.4336204529],"type":"Point"}
}