{
  "type": "Feature",
  "properties": {
    "addr:full":"Calle de Estambrera, 13 Logro\u00f1o La Rioja 26006",
    "addr:housenumber":"13",
    "addr:postcode":"26006",
    "addr:street":"Calle De Estambrera;Rioja",
    "iso:country":"ES",
    "sg:address":"Calle de Estambrera, 13",
    "sg:city":"Logro\u00f1o",
    "sg:orig_category":"Farmacias",
    "sg:phone":"+34 941 24 37 81",
    "sg:postcode":"26006",
    "sg:province":"La Rioja",
    "wof:name":"Esteban Delgado Maria Dolores",
    "wof:placetype":"venue"
},
  "geometry": {"coordinates":[-2.4351940155,42.4559898376],"type":"Point"}
}