{
  "type": "Feature",
  "properties": {
    "iso:country":"ES",
    "sg:address":"Calle de Florian Rey, 7",
    "sg:city":"Zaragoza",
    "sg:orig_category":"Muebles, Minoristas",
    "sg:phone":"+34 976 29 00 70",
    "sg:postcode":"50002",
    "sg:province":"Zaragoza",
    "wof:name":"Perez Ardid Maria Cristina",
    "wof:placetype":"venue"
},
  "geometry": {"coordinates":[-0.8621469736,41.6492233276],"type":"Point"}
}