{
  "type": "Feature",
  "properties": {
    "addr:full":"Carrer de Balmes, 255 Barcelona Barcelona 08006",
    "addr:housenumber":"255",
    "addr:postcode":"08006",
    "addr:street":"Carrer De Balmes",
    "iso:country":"ES",
    "sg:address":"Carrer de Balmes, 255",
    "sg:city":"Barcelona",
    "sg:orig_category":"Ropa Para Ni\u00d1os (al Por Menor)",
    "sg:phone":"+34 932 18 83 31",
    "sg:postcode":"08006",
    "sg:province":"Barcelona",
    "wof:name":"Baby Blue S.l.",
    "wof:placetype":"venue"
},
  "geometry": {"coordinates":[2.1491189003,41.3999595642],"type":"Point"}
}