{
  "type": "Feature",
  "properties": {
    "iso:country":"ES",
    "sg:address":"Carr Sant Jaume, 7",
    "sg:city":"Mollerussa",
    "sg:orig_category":"Fabricaci\u00d3n De Juguetes Autom\u00c1ticos",
    "sg:phone":"+34 973 71 11 25",
    "sg:postcode":"25230",
    "sg:province":"Lleida",
    "wof:name":"Rodalmatic S.l.",
    "wof:placetype":"venue"
},
  "geometry": {"coordinates":[0.897044003,41.6275444031],"type":"Point"}
}