{
  "type": "Feature",
  "properties": {
    "addr:full":"Calle de Capuchinos, 58 Toro Zamora 49800",
    "addr:housenumber":"58",
    "addr:postcode":"49800",
    "addr:street":"Calle De Capuchinos",
    "iso:country":"ES",
    "sg:address":"Calle de Capuchinos, 58",
    "sg:city":"Toro",
    "sg:orig_category":"Alimentaci\u00d3n General (al Por Menor)",
    "sg:phone":"+34 980 69 03 83",
    "sg:postcode":"49800",
    "sg:province":"Zamora",
    "wof:name":"Caballero Calvo Millan",
    "wof:placetype":"venue"
},
  "geometry": {"coordinates":[-5.3980212212,41.5257072449],"type":"Point"}
}