{
  "type": "Feature",
  "properties": {
    "addr:full":"Calvo Sotelo, 9 Maceda Ourense 32700",
    "addr:housenumber":"9",
    "addr:postcode":"32700",
    "addr:street":"Calvo Sotelo",
    "iso:country":"ES",
    "sg:address":"Calvo Sotelo, 9",
    "sg:city":"Maceda",
    "sg:orig_category":"Electricidad, Electr\u00d3nica: Suministros (al Por Menor)",
    "sg:phone":"+34 988 46 32 06",
    "sg:postcode":"32700",
    "sg:province":"Ourense",
    "wof:name":"Gonzalez Carballo Enrique",
    "wof:placetype":"venue"
},
  "geometry": {"coordinates":[-7.6509618759,42.2707633972],"type":"Point"}
}