{
  "type": "Feature",
  "properties": {
    "addr:full":"Calle de San Diego, 14 Cartagena Murcia 30202",
    "addr:housenumber":"14",
    "addr:postcode":"30202",
    "addr:street":"Calle De San Diego",
    "iso:country":"ES",
    "sg:address":"Calle de San Diego, 14",
    "sg:city":"Cartagena",
    "sg:orig_category":"Alimentaci\u00d3n General (al Por Menor)",
    "sg:phone":"+34 968 50 46 87",
    "sg:postcode":"30202",
    "sg:province":"Murcia",
    "wof:name":"Diaz Sanchez Jose",
    "wof:placetype":"venue"
},
  "geometry": {"coordinates":[-0.9801369905,37.6031227112],"type":"Point"}
}