{
  "type": "Feature",
  "properties": {
    "addr:full":"Carrer de Perot Rocaguinarda, S/n Vic Barcelona 08500",
    "addr:housenumber":"s / n",
    "addr:postcode":"08500",
    "addr:street":"Carrer De Perot Rocaguinarda",
    "iso:country":"ES",
    "sg:address":"Carrer de Perot Rocaguinarda, S/n",
    "sg:city":"Vic",
    "sg:orig_category":"Transportes Por Carretera: Lotes Completos, Mercanc\u00cdas Diversas",
    "sg:phone":"+34 938 89 43 36",
    "sg:postcode":"08500",
    "sg:province":"Barcelona",
    "wof:name":"Snack Ventures S. A.",
    "wof:placetype":"venue"
},
  "geometry": {"coordinates":[2.2467360497,41.9285125732],"type":"Point"}
}