{
  "type": "Feature",
  "properties": {
    "iso:country":"ES",
    "sg:address":"Calle de Comendador, 2",
    "sg:city":"Azuqueca Henares",
    "sg:orig_category":"Fotocopias, Reprograf\u00cda",
    "sg:phone":"+34 949 27 72 25",
    "sg:postcode":"19200",
    "sg:province":"Guadalajara",
    "wof:name":"Copymur Servicios Reprograficos Y Digitales S.l.",
    "wof:placetype":"venue"
},
  "geometry": {"coordinates":[-3.2659449577,40.5636711121],"type":"Point"}
}