{
  "type": "Feature",
  "properties": {
    "iso:country":"ES",
    "sg:address":"Plaz Iglesia, 4",
    "sg:city":"Alpera",
    "sg:orig_category":"Alimentaci\u00d3n General (al Por Menor)",
    "sg:phone":"+34 967 33 01 34",
    "sg:postcode":"02690",
    "sg:province":"Albacete",
    "wof:name":"Fernandez Garcia Francisco",
    "wof:placetype":"venue"
},
  "geometry": {"coordinates":[-1.230610013,38.95936203],"type":"Point"}
}