{
  "type": "Feature",
  "properties": {
    "iso:country":"ES",
    "sg:address":"Carrer de Jacint Verdaguer, 37",
    "sg:city":"Ametlla Mar",
    "sg:orig_category":"Contenedores (mercanc\u00cdas)",
    "sg:phone":"+34 977 45 60 57",
    "sg:postcode":"43860",
    "sg:province":"Tarragona",
    "wof:name":"Ca\u00f1agueral Marti Juan",
    "wof:placetype":"venue"
},
  "geometry": {"coordinates":[0.8035640121,40.8860206604],"type":"Point"}
}