{
  "type": "Feature",
  "properties": {
    "addr:full":"Calle de Placido Pe\u00d1a, 69 Vilalba Lugo 27800",
    "addr:housenumber":"69",
    "addr:postcode":"27800",
    "addr:street":"Calle De Placido Pen\u0303A",
    "iso:country":"ES",
    "sg:address":"Calle de Placido Pe\u00d1a, 69",
    "sg:city":"Vilalba",
    "sg:orig_category":"Peluqueros: De Se\u00d1oras",
    "sg:phone":"+34 982 51 03 71",
    "sg:postcode":"27800",
    "sg:province":"Lugo",
    "wof:name":"Rodriguez Pereira Mercedes",
    "wof:placetype":"venue"
},
  "geometry": {"coordinates":[-7.6791801453,43.3012008667],"type":"Point"}
}