{
  "type": "Feature",
  "properties": {
    "iso:country":"ES",
    "sg:address":"Calle de Enrique Borras, 18",
    "sg:city":"Madrid",
    "sg:orig_category":"Promotores Constructores",
    "sg:phone":"+34 915 26 18 58",
    "sg:postcode":"28011",
    "sg:province":"Madrid",
    "wof:name":"Reforma Y Construcciones Alcorcon S.a.",
    "wof:placetype":"venue"
},
  "geometry": {"coordinates":[-3.7434794903,40.4071807861],"type":"Point"}
}