{
  "type": "Feature",
  "properties": {
    "iso:country":"ES",
    "sg:address":"Avda Prado Boyal, 7",
    "sg:city":"Laguna Duero",
    "sg:orig_category":"Electrodom\u00c9sticos (al Por Menor)",
    "sg:phone":"+34 983 54 47 73",
    "sg:postcode":"47140",
    "sg:province":"Valladolid",
    "wof:name":"Teso Sanchez Angel",
    "wof:placetype":"venue"
},
  "geometry": {"coordinates":[-4.7237858772,41.5914230347],"type":"Point"}
}