{
  "type": "Feature",
  "properties": {
    "iso:country":"ES",
    "sg:address":"Barr Larzabal",
    "sg:city":"Errenteria",
    "sg:orig_category":"Centros M\u00c9dicos Y Sociales, Dispensarios",
    "sg:phone":"+34 943 00 78 00",
    "sg:postcode":"20100",
    "sg:province":"Guip\u00f9zcoa",
    "wof:name":"Osakidetza",
    "wof:placetype":"venue"
},
  "geometry": {"coordinates":[-1.8838690519,43.309841156],"type":"Point"}
}