{
  "type": "Feature",
  "properties": {
    "iso:country":"ES",
    "sg:address":"Calle de Salud (la), 6",
    "sg:city":"Torquemada",
    "sg:orig_category":"Fabricaci\u00d3n De Quesos",
    "sg:phone":"+34 979 80 03 03",
    "sg:postcode":"34230",
    "sg:province":"Palencia",
    "wof:name":"Gamazo Carreras Matias",
    "wof:placetype":"venue"
},
  "geometry": {"coordinates":[-4.3208680153,42.0310249329],"type":"Point"}
}