{
  "type": "Feature",
  "properties": {
    "iso:country":"ES",
    "sg:address":"Montepequeno, S/n",
    "sg:city":"Boiro",
    "sg:orig_category":"Centros Empresariales",
    "sg:phone":"+34 981 84 67 01",
    "sg:postcode":"15930",
    "sg:province":"La Coru\u00f1a",
    "wof:name":"Asociacion De Productos Mejilloneros Ria De Barra\u00f1a",
    "wof:placetype":"venue"
},
  "geometry": {"coordinates":[-8.9355735779,42.6803779602],"type":"Point"}
}