{
  "type": "Feature",
  "properties": {
    "addr:full":"Av Pompeu Fabra, S/n Empuriabrava Girona 17487",
    "addr:housenumber":"s",
    "addr:postcode":"17487",
    "addr:street":"Av Pompeu;/ N Empuriabrava",
    "iso:country":"ES",
    "sg:address":"Av Pompeu Fabra, S/n",
    "sg:city":"Empuriabrava",
    "sg:orig_category":"Importaci\u00d3n",
    "sg:phone":"+34 972 45 61 32",
    "sg:postcode":"17487",
    "sg:province":"Girona",
    "wof:name":"Util Europa 2002 S.l.",
    "wof:placetype":"venue"
},
  "geometry": {"coordinates":[3.1248450279,42.2398033142],"type":"Point"}
}