{
  "type": "Feature",
  "properties": {
    "addr:full":"Carrer de Industria, 80 Barcelona Barcelona 08025",
    "addr:housenumber":"80",
    "addr:postcode":"08025",
    "addr:street":"Carrer De Industria",
    "iso:country":"ES",
    "sg:address":"Carrer de Industria, 80",
    "sg:city":"Barcelona",
    "sg:orig_category":"Farmacias",
    "sg:phone":"+34 934 57 06 20",
    "sg:postcode":"08025",
    "sg:province":"Barcelona",
    "wof:name":"Segarra Gurria Federico",
    "wof:placetype":"venue"
},
  "geometry": {"coordinates":[2.1697630882,41.405872345],"type":"Point"}
}