{
  "type": "Feature",
  "properties": {
    "iso:country":"ES",
    "sg:address":"Calle de Santa Lucia, 15",
    "sg:city":"Aranda Duero",
    "sg:orig_category":"Bazares, Art\u00cdculos De Limpieza Y De Cocina (al Por Menor)",
    "sg:phone":"+34 947 50 72 08",
    "sg:postcode":"09400",
    "sg:province":"Burgos",
    "wof:name":"Castilla De Paz Jose Angel",
    "wof:placetype":"venue"
},
  "geometry": {"coordinates":[-3.6889948845,41.6699256897],"type":"Point"}
}