{
  "type": "Feature",
  "properties": {
    "iso:country":"ES",
    "sg:address":"Calle de Galicia, 54",
    "sg:city":"Catarroja",
    "sg:orig_category":"Carnicer\u00cdas, Carnicer\u00cdas",
    "sg:phone":"+34 961 27 23 80",
    "sg:postcode":"46470",
    "sg:province":"Valencia",
    "wof:name":"Sanjuan Guillem Ramon",
    "wof:placetype":"venue"
},
  "geometry": {"coordinates":[-0.4060710073,39.4023933411],"type":"Point"}
}