{
  "type": "Feature",
  "properties": {
    "iso:country":"ES",
    "sg:address":"Rbla Egara, 190",
    "sg:city":"Terrassa",
    "sg:orig_category":"Asociaciones, Organismos Culturales Y Socioeducativos",
    "sg:phone":"+34 937 88 88 30",
    "sg:postcode":"08221",
    "sg:province":"Barcelona",
    "wof:name":"Penya Barcelonista 1900",
    "wof:placetype":"venue"
},
  "geometry": {"coordinates":[2.0081079006,41.5627708435],"type":"Point"}
}