{
  "type": "Feature",
  "properties": {
    "addr:full":"Calle de Estrella Polar, 36 Quintanadue\u00f1as Burgos 09197",
    "addr:housenumber":"36",
    "addr:postcode":"09197",
    "addr:street":"Calle De Estrella Polar",
    "iso:country":"ES",
    "sg:address":"Calle de Estrella Polar, 36",
    "sg:city":"Quintanadue\u00f1as",
    "sg:orig_category":"Empresas De Carpinter\u00cda",
    "sg:phone":"+34 947 29 25 48",
    "sg:postcode":"09197",
    "sg:province":"Burgos",
    "wof:name":"Gutierrez Caama\u00f1o Francisco Javier",
    "wof:placetype":"venue"
},
  "geometry": {"coordinates":[-3.7139539719,42.4089889526],"type":"Point"}
}