{
  "type": "Feature",
  "properties": {
    "iso:country":"ES",
    "sg:address":"Avda Universidad, 31",
    "sg:city":"Leganes",
    "sg:orig_category":"Estilistas Y Estudios De Estilo De Corte Y Confecci\u00d3n",
    "sg:phone":"+34 916 94 52 27",
    "sg:postcode":"28911",
    "sg:province":"Madrid",
    "wof:name":"Diaz Bravo Venerando",
    "wof:placetype":"venue"
},
  "geometry": {"coordinates":[-3.7681701183,40.3312797546],"type":"Point"}
}