{
  "type": "Feature",
  "properties": {
    "addr:full":"Carrer de Industria, 284 Barcelona Barcelona 08026",
    "addr:housenumber":"284",
    "addr:postcode":"08026",
    "addr:street":"Carrer De Industria",
    "iso:country":"ES",
    "sg:address":"Carrer de Industria, 284",
    "sg:city":"Barcelona",
    "sg:orig_category":"Carnicer\u00cdas, Carnicer\u00cdas",
    "sg:phone":"+34 934 35 19 31",
    "sg:postcode":"08026",
    "sg:province":"Barcelona",
    "wof:name":"Sanchez Navarro Concepcion",
    "wof:placetype":"venue"
},
  "geometry": {"coordinates":[2.1806819439,41.4142570496],"type":"Point"}
}