{
  "type": "Feature",
  "properties": {
    "addr:full":"Calle de Arraez, Km. 0063,0 Facinas C\u00e1diz 11391",
    "addr:postcode":"11391",
    "addr:street":"Calle De Arraez Km. 0063,0 Facinas Ca\u0301Diz",
    "iso:country":"ES",
    "sg:address":"Calle de Arraez, Km. 0063,0",
    "sg:city":"Facinas",
    "sg:orig_category":"Cr\u00cda De Animales",
    "sg:phone":"+34 956 23 62 15",
    "sg:postcode":"11391",
    "sg:province":"C\u00e1diz",
    "wof:name":"Agropecuaria Los Altos De Arraez S.l.",
    "wof:placetype":"venue"
},
  "geometry": {"coordinates":[-5.7003712654,36.1432876587],"type":"Point"}
}