{
  "type": "Feature",
  "properties": {
    "iso:country":"ES",
    "sg:address":"Carrer de Marques De Sentmenat, 64",
    "sg:city":"Barcelona",
    "sg:orig_category":"Ingenier\u00cda, Centros De Estudios (diversos)",
    "sg:phone":"+34 933 21 66 19",
    "sg:postcode":"08029",
    "sg:province":"Barcelona",
    "wof:name":"Escriba Serra Juan",
    "wof:placetype":"venue"
},
  "geometry": {"coordinates":[2.1383769512,41.3851356506],"type":"Point"}
}