{
  "type": "Feature",
  "properties": {
    "iso:country":"ES",
    "sg:address":"Calle de Sacramento (del), 18",
    "sg:city":"San Sebastian De Los Reyes",
    "sg:orig_category":"Muebles, Minoristas",
    "sg:phone":"+34 916 53 75 89",
    "sg:postcode":"28700",
    "sg:province":"Madrid",
    "wof:name":"Ramos Martin Julian Manuel",
    "wof:placetype":"venue"
},
  "geometry": {"coordinates":[-3.6299769878,40.5453224182],"type":"Point"}
}