{
  "type": "Feature",
  "properties": {
    "addr:full":"Calle de Obras Publicas, 1 Villarcayo Burgos 09550",
    "addr:housenumber":"1",
    "addr:postcode":"09550",
    "addr:street":"Calle De Obras Publicas",
    "iso:country":"ES",
    "sg:address":"Calle de Obras Publicas, 1",
    "sg:city":"Villarcayo",
    "sg:orig_category":"Agentes Generales De Seguros",
    "sg:phone":"+34 947 13 10 05",
    "sg:postcode":"09550",
    "sg:province":"Burgos",
    "wof:name":"Seguteler Ortiz S.l.",
    "wof:placetype":"venue"
},
  "geometry": {"coordinates":[-3.5727319717,42.9354324341],"type":"Point"}
}