{
  "type": "Feature",
  "properties": {
    "addr:full":"Carrer de Cervantes, 34 Sabadell Barcelona 08201",
    "addr:housenumber":"34",
    "addr:postcode":"08201",
    "addr:street":"Carrer De Cervantes",
    "iso:country":"ES",
    "sg:address":"Carrer de Cervantes, 34",
    "sg:city":"Sabadell",
    "sg:orig_category":"Cables Y Hilos El\u00c9ctricos (fabricaci\u00d3n, Al Por Mayor)",
    "sg:phone":"+34 937 20 51 19",
    "sg:postcode":"08201",
    "sg:province":"Barcelona",
    "sg:website":"www.urkunde.com",
    "wof:name":"Urkunde S.a.",
    "wof:placetype":"venue"
},
  "geometry": {"coordinates":[2.1097950935,41.5415534973],"type":"Point"}
}