{
  "type": "Feature",
  "properties": {
    "iso:country":"ES",
    "sg:address":"Carr Leonor Servera, 35",
    "sg:city":"Cala Ratjada",
    "sg:orig_category":"Juegos Y Juguetes (al Por Menor)",
    "sg:phone":"+34 971 58 82 56",
    "sg:postcode":"07590",
    "sg:province":"Islas Baleares",
    "wof:name":"Lloren\u00c7 Vi\u00c7ens S.l.",
    "wof:placetype":"venue"
},
  "geometry": {"coordinates":[3.460848093,39.7106285095],"type":"Point"}
}