{
  "type": "Feature",
  "properties": {
    "iso:country":"ES",
    "sg:address":"Plaz San Juan, S/n",
    "sg:city":"Llerena",
    "sg:orig_category":"Iglesia Cat\u00d3lica",
    "sg:phone":"+34 924 87 23 25",
    "sg:postcode":"06900",
    "sg:province":"Badajoz",
    "wof:name":"Parroquia Nuestra Se\u00f1ora De La Granada",
    "wof:placetype":"venue"
},
  "geometry": {"coordinates":[-6.0147337914,38.2373352051],"type":"Point"}
}