{
  "type": "Feature",
  "properties": {
    "iso:country":"ES",
    "sg:address":"Calle de Zamora, 16",
    "sg:city":"Medina Campo",
    "sg:orig_category":"Molduras, Junquillos, Listones Y Molduras Perforadas",
    "sg:phone":"+34 983 80 49 94",
    "sg:postcode":"47400",
    "sg:province":"Valladolid",
    "wof:name":"Nieto De La Fuente Jose Alberto",
    "wof:placetype":"venue"
},
  "geometry": {"coordinates":[-4.9194288254,41.3067207336],"type":"Point"}
}