{
  "type": "Feature",
  "properties": {
    "addr:full":"Avda Jaime I, 6 Vall D'uixo Castell\u00f3n 12600",
    "addr:housenumber":"6",
    "addr:postcode":"12600",
    "addr:street":"Avda Jaime I",
    "iso:country":"ES",
    "sg:address":"Avda Jaime I, 6",
    "sg:city":"Vall D'uixo",
    "sg:orig_category":"Minerales (al Por Mayor)",
    "sg:phone":"+34 964 69 68 49",
    "sg:postcode":"12600",
    "sg:province":"Castell\u00f3n",
    "wof:name":"Ukracas Materias Primas S.l.",
    "wof:placetype":"venue"
},
  "geometry": {"coordinates":[-0.0482099988,39.992477417],"type":"Point"}
}