{
  "type": "Feature",
  "properties": {
    "iso:country":"ES",
    "sg:address":"Calle de Andres Mellado, 85",
    "sg:city":"Madrid",
    "sg:orig_category":"Peluqueros: De Se\u00d1oras",
    "sg:phone":"+34 913 99 45 99",
    "sg:postcode":"28003",
    "sg:province":"Madrid",
    "wof:name":"Gutierrez Perez Maria De Los Angeles",
    "wof:placetype":"venue"
},
  "geometry": {"coordinates":[-3.7140161991,40.440574646],"type":"Point"}
}