{
  "type": "Feature",
  "properties": {
    "iso:country":"ES",
    "sg:address":"Carrer de Roger De Flor, 57",
    "sg:city":"Granollers",
    "sg:orig_category":"Seguridad En El Trabajo Y Prevenci\u00d3n De Riesgos Laborales",
    "sg:phone":"+34 938 79 37 07",
    "sg:postcode":"08401",
    "sg:province":"Barcelona",
    "wof:name":"Prevengrup Prevencio Integral S.l.",
    "wof:placetype":"venue"
},
  "geometry": {"coordinates":[2.2834539413,41.6078262329],"type":"Point"}
}