{
  "type": "Feature",
  "properties": {
    "addr:full":"Calle de Ponzano, 39 Madrid Madrid 28003",
    "addr:housenumber":"39",
    "addr:postcode":"madrid;28003",
    "addr:street":"Calle De Ponzano",
    "iso:country":"ES",
    "sg:address":"Calle de Ponzano, 39",
    "sg:city":"Madrid",
    "sg:classifiers":[
        {
            "category":"Professional",
            "subcategory":"Management & Consulting",
            "type":"Services"
        }
    ],
    "sg:phone":"+34 913 99 15 15",
    "sg:postcode":"28003",
    "sg:province":"Madrid",
    "sg:tags":[
        "asesor\u00cda",
        "en",
        "marketing"
    ],
    "sg:website":"www.verticalmarketing.es",
    "wof:name":"Vertical Promotional Marketing S.l.",
    "wof:placetype":"venue"
},
  "geometry": {"coordinates":[-3.6993999481,40.4400062561],"type":"Point"}
}