{
  "type": "Feature",
  "properties": {
    "iso:country":"ES",
    "sg:address":"Calle de Calvo Sotelo, 5",
    "sg:city":"Velayos",
    "sg:orig_category":"Frutas Y Legumbres Frescas (al Por Mayor)",
    "sg:phone":"+34 920 20 02 42",
    "sg:postcode":"05295",
    "sg:province":"\u00c1vila",
    "wof:name":"Mu\u00f1oz Martin Salvador",
    "wof:placetype":"venue"
},
  "geometry": {"coordinates":[-4.6234502792,40.8397254944],"type":"Point"}
}