{
  "type": "Feature",
  "properties": {
    "addr:full":"Calle de Belchite, S/n Ciudad Real Ciudad Real 13001",
    "addr:housenumber":"s / n",
    "addr:postcode":"13001",
    "addr:street":"Calle De Belchite",
    "iso:country":"ES",
    "sg:address":"Calle de Belchite, S/n",
    "sg:city":"Ciudad Real",
    "sg:orig_category":"Aparcamientos (infraestructuras, Accesorios)",
    "sg:phone":"+34 926 22 20 11",
    "sg:postcode":"13001",
    "sg:province":"Ciudad Real",
    "wof:name":"Cominidad De Propietarios De Cocheras Av. La Mancha",
    "wof:placetype":"venue"
},
  "geometry": {"coordinates":[-3.9307522774,38.9812927246],"type":"Point"}
}