{
  "type": "Feature",
  "properties": {
    "addr:full":"Calle de Tejera (la), 22 Soria Soria 42001",
    "addr:housenumber":"22",
    "addr:postcode":"42001",
    "addr:street":"Calle De Tejera La",
    "iso:country":"ES",
    "sg:address":"Calle de Tejera (la), 22",
    "sg:city":"Soria",
    "sg:orig_category":"Radiocomunicaciones, Telefon\u00cda M\u00d3vil, Radiomensajer\u00cda: Servicios, Comercializaci\u00d3n",
    "sg:phone":"+34 975 24 04 05",
    "sg:postcode":"42001",
    "sg:province":"Soria",
    "wof:name":"Spacio Celular S.l.",
    "wof:placetype":"venue"
},
  "geometry": {"coordinates":[-2.4696397781,41.7662353516],"type":"Point"}
}