{
  "type": "Feature",
  "properties": {
    "addr:full":"Barr Ambasaguas, 2 Ambasaguas Vizcaya 48891",
    "addr:housenumber":"2",
    "addr:postcode":"48891",
    "addr:street":"Ambasaguas",
    "iso:country":"ES",
    "sg:address":"Barr Ambasaguas, 2",
    "sg:city":"Ambasaguas",
    "sg:orig_category":"Distribuci\u00d3n De Petr\u00d3leo Y Derivados",
    "sg:phone":"+34 946 80 61 73",
    "sg:postcode":"48891",
    "sg:province":"Vizcaya",
    "wof:name":"Matienzo Palacio Juan Jose",
    "wof:placetype":"venue"
},
  "geometry": {"coordinates":[-3.3572590351,43.2212486267],"type":"Point"}
}