{
  "type": "Feature",
  "properties": {
    "addr:full":"Calle de Heliodoro Fernandez, 25 Colindres Cantabria 39750",
    "addr:housenumber":"25",
    "addr:postcode":"39750",
    "addr:street":"Calle De Heliodoro Fernandez",
    "iso:country":"ES",
    "sg:address":"Calle de Heliodoro Fernandez, 25",
    "sg:city":"Colindres",
    "sg:orig_category":"Fabricaci\u00d3n, Venta De Cuadros, Accesorios Para Enmarcar",
    "sg:phone":"+34 942 65 09 28",
    "sg:postcode":"39750",
    "sg:province":"Cantabria",
    "wof:name":"Torre Corro Antonio",
    "wof:placetype":"venue"
},
  "geometry": {"coordinates":[-3.4525239468,43.3955841064],"type":"Point"}
}