{
  "type": "Feature",
  "properties": {
    "addr:full":"Calle de Brive, 8 Toledo Toledo 45005",
    "addr:housenumber":"8",
    "addr:postcode":"45005",
    "addr:street":"Calle De Brive",
    "iso:country":"ES",
    "sg:address":"Calle de Brive, 8",
    "sg:city":"Toledo",
    "sg:orig_category":"Ortopedia General",
    "sg:phone":"+34 925 22 71 92",
    "sg:postcode":"45005",
    "sg:province":"Toledo",
    "wof:name":"Garcia Bahon Agustin",
    "wof:placetype":"venue"
},
  "geometry": {"coordinates":[-4.0314221382,39.8698654175],"type":"Point"}
}