{
  "type": "Feature",
  "properties": {
    "addr:full":"Calle de Malena, 32 Medina Campo Valladolid 47400",
    "addr:housenumber":"32",
    "addr:postcode":"47400",
    "addr:street":"Calle De Malena",
    "iso:country":"ES",
    "sg:address":"Calle de Malena, 32",
    "sg:city":"Medina Campo",
    "sg:orig_category":"Electrodom\u00c9sticos (al Por Menor)",
    "sg:phone":"+34 983 83 73 62",
    "sg:postcode":"47400",
    "sg:province":"Valladolid",
    "wof:name":"Paniagua Carmona Jose Manuel",
    "wof:placetype":"venue"
},
  "geometry": {"coordinates":[-4.9186792374,41.3043365479],"type":"Point"}
}