{
  "type": "Feature",
  "properties": {
    "addr:full":"Calle de Troncon, 33 Fuengirola M\u00e1laga 29640",
    "addr:housenumber":"33",
    "addr:postcode":"29640",
    "addr:street":"Calle De Troncon;Ma\u0301Laga",
    "iso:country":"ES",
    "sg:address":"Calle de Troncon, 33",
    "sg:city":"Fuengirola",
    "sg:classifiers":[
        {
            "category":"Personal",
            "subcategory":"Barber",
            "type":"Services"
        }
    ],
    "sg:phone":"+34 952 47 70 46",
    "sg:postcode":"29640",
    "sg:province":"M\u00e1laga",
    "sg:tags":[
        "caballeros",
        "de",
        "peluqueros"
    ],
    "wof:name":"Serrano Morales Rafael",
    "wof:placetype":"venue"
},
  "geometry": {"coordinates":[-4.6250858307,36.5371437073],"type":"Point"}
}