{
  "type": "Feature",
  "properties": {
    "iso:country":"ES",
    "sg:address":"Alberto Sanchez, 8",
    "sg:city":"Albox",
    "sg:orig_category":"Estancos",
    "sg:phone":"+34 950 43 02 07",
    "sg:postcode":"04800",
    "sg:province":"Almer\u00eda",
    "wof:name":"Marmol Oller Pedro",
    "wof:placetype":"venue"
},
  "geometry": {"coordinates":[-2.1464920044,37.3883247375],"type":"Point"}
}