{
  "type": "Feature",
  "properties": {
    "iso:country":"ES",
    "sg:address":"Avda Profesor Floriano Cumbre\u00d1o, 1",
    "sg:city":"Caceres",
    "sg:orig_category":"Papeler\u00cdas, Librer\u00cdas",
    "sg:phone":"+34 927 23 72 97",
    "sg:postcode":"10005",
    "sg:province":"C\u00e1ceres",
    "wof:name":"Pintado Vidal Cristina",
    "wof:placetype":"venue"
},
  "geometry": {"coordinates":[-6.3852090836,39.4654693604],"type":"Point"}
}