{
  "type": "Feature",
  "properties": {
    "iso:country":"ES",
    "sg:address":"Plaz Europa, 23",
    "sg:city":"Torrejon Ardoz",
    "sg:orig_category":"Cl\u00cdnicas Dentales",
    "sg:phone":"+34 916 75 55 60",
    "sg:postcode":"28850",
    "sg:province":"Madrid",
    "wof:name":"Astradental S.l.",
    "wof:placetype":"venue"
},
  "geometry": {"coordinates":[-3.4729008675,40.4490776062],"type":"Point"}
}