{
  "type": "Feature",
  "properties": {
    "addr:full":"Calle de Alday, S/n Malia\u00d1o Cantabria 39600",
    "addr:housenumber":"s / n",
    "addr:postcode":"39600",
    "addr:street":"Calle De Alday",
    "iso:country":"ES",
    "sg:address":"Calle de Alday, S/n",
    "sg:city":"Malia\u00d1o",
    "sg:orig_category":"Ropa De Hogar (al Por Menor)",
    "sg:phone":"+34 942 25 23 45",
    "sg:postcode":"39600",
    "sg:province":"Cantabria",
    "sg:website":"www.zarahome.com",
    "wof:name":"Zara Home Espa\u00d1a S.a.",
    "wof:placetype":"venue"
},
  "geometry": {"coordinates":[-3.8376090527,43.4216461182],"type":"Point"}
}