{
  "type": "Feature",
  "properties": {
    "iso:country":"ES",
    "sg:address":"Calle de Alferez Barreiro, 26",
    "sg:city":"Baiona",
    "sg:classifiers":[
        {
            "category":"Recreation",
            "type":"Entertainment"
        }
    ],
    "sg:phone":"+34 986 38 50 36",
    "sg:postcode":"36300",
    "sg:province":"Pontevedra",
    "sg:tags":[
        "caza",
        "pr\u00c1ctica",
        "la",
        "de",
        "pesca",
        "y"
    ],
    "wof:name":"Cofradia Pescadores La Anunciada",
    "wof:placetype":"venue"
},
  "geometry": {"coordinates":[-8.8475265503,42.1189537048],"type":"Point"}
}