{
  "type": "Feature",
  "properties": {
    "addr:full":"Calle de Sevilla, 22 Villaviciosa Cordoba C\u00f3rdoba 14300",
    "addr:housenumber":"22",
    "addr:postcode":"14300",
    "addr:street":"Calle De Sevilla",
    "iso:country":"ES",
    "sg:address":"Calle de Sevilla, 22",
    "sg:city":"Villaviciosa Cordoba",
    "sg:orig_category":"Aguas (distribuci\u00d3n, Servicios)",
    "sg:phone":"+34 957 36 00 72",
    "sg:postcode":"14300",
    "sg:province":"C\u00f3rdoba",
    "wof:name":"Junta De Andalucia",
    "wof:placetype":"venue"
},
  "geometry": {"coordinates":[-5.0159888268,38.0754547119],"type":"Point"}
}