{
  "type": "Feature",
  "properties": {
    "iso:country":"ES",
    "sg:address":"Calle de Andalucia, 3",
    "sg:city":"Torreperogil",
    "sg:orig_category":"Promotores Constructores",
    "sg:phone":"+34 953 77 63 90",
    "sg:postcode":"23320",
    "sg:province":"Ja\u00e9n",
    "wof:name":"Construcciones Morasur",
    "wof:placetype":"venue"
},
  "geometry": {"coordinates":[-3.2911949158,38.0347900391],"type":"Point"}
}