{
  "type": "Feature",
  "properties": {
    "addr:full":"C/ D'allemand, 54 Sant Lluis Islas Baleares 07710",
    "addr:housenumber":"54",
    "addr:postcode":"07710",
    "addr:street":"C / D'Allemand",
    "iso:country":"ES",
    "sg:address":"C/ D'allemand, 54",
    "sg:city":"Sant Lluis",
    "sg:orig_category":"Empresas De Carpinter\u00cda De Madera",
    "sg:phone":"+34 971 15 09 18",
    "sg:postcode":"07710",
    "sg:province":"Islas Baleares",
    "wof:name":"Llana Orfila Juan De La",
    "wof:placetype":"venue"
},
  "geometry": {"coordinates":[4.2262802124,39.8251991272],"type":"Point"}
}