{
  "type": "Feature",
  "properties": {
    "addr:full":"Tarragona, 9 Teia Barcelona 08329",
    "addr:housenumber":"9",
    "addr:postcode":"08329",
    "addr:street":"Tarragona",
    "iso:country":"ES",
    "sg:address":"Tarragona, 9",
    "sg:city":"Teia",
    "sg:orig_category":"Dom\u00d3tica",
    "sg:phone":"+34 935 55 73 07",
    "sg:postcode":"08329",
    "sg:province":"Barcelona",
    "wof:name":"Umbra3000 S.l.",
    "wof:placetype":"venue"
},
  "geometry": {"coordinates":[2.3152461052,41.4907455444],"type":"Point"}
}