{
  "type": "Feature",
  "properties": {
    "addr:full":"Plaz Extremadura, 46 Cabezuela Valle C\u00e1ceres 10610",
    "addr:housenumber":"46",
    "addr:postcode":"10610",
    "addr:street":"Plaz Extremadura;Ca\u0301Ceres",
    "iso:country":"ES",
    "sg:address":"Plaz Extremadura, 46",
    "sg:city":"Cabezuela Valle",
    "sg:orig_category":"Agricultura: Abastecimiento Y Cosechado (negocio)",
    "sg:phone":"+34 927 47 27 57",
    "sg:postcode":"10610",
    "sg:province":"C\u00e1ceres",
    "wof:name":"Comercial Agricola Don Rufino, S.l.",
    "wof:placetype":"venue"
},
  "geometry": {"coordinates":[-5.8069238663,40.1921615601],"type":"Point"}
}