{
  "type": "Feature",
  "properties": {
    "addr:full":"Avda Pablo Iglesias, 50 Gijon Asturias 33205",
    "addr:housenumber":"50",
    "addr:postcode":"33205",
    "addr:street":"Avda Pablo Iglesias",
    "iso:country":"ES",
    "sg:address":"Avda Pablo Iglesias, 50",
    "sg:city":"Gijon",
    "sg:orig_category":"Costureras",
    "sg:phone":"+34 985 33 57 43",
    "sg:postcode":"33205",
    "sg:province":"Asturias",
    "wof:name":"Moral Doncel Teresa",
    "wof:placetype":"venue"
},
  "geometry": {"coordinates":[-5.6545410156,43.5354919434],"type":"Point"}
}