{
  "type": "Feature",
  "properties": {
    "addr:full":"Avda Marconi, S/n Madrid Madrid 28021",
    "addr:housenumber":"s / n",
    "addr:postcode":"28021",
    "addr:street":"Avda Marconi",
    "iso:country":"ES",
    "sg:address":"Avda Marconi, S/n",
    "sg:city":"Madrid",
    "sg:orig_category":"Artes Gr\u00c1ficas, Artes Pl\u00c1sticas (curso)",
    "sg:phone":"+34 917 98 50 09",
    "sg:postcode":"28021",
    "sg:province":"Madrid",
    "wof:name":"Imbarza Ii Troquelados S.l.",
    "wof:placetype":"venue"
},
  "geometry": {"coordinates":[-3.695168972,40.3340301514],"type":"Point"}
}