{
  "type": "Feature",
  "properties": {
    "iso:country":"ES",
    "sg:address":"Avda Aragon, 33",
    "sg:city":"Valencia",
    "sg:orig_category":"Edici\u00d3n De Diarios, Revistas, Boletines",
    "sg:phone":"+34 963 89 09 49",
    "sg:postcode":"46010",
    "sg:province":"Valencia",
    "wof:name":"Promociones Y Ediciones Culturales S.a.",
    "wof:placetype":"venue"
},
  "geometry": {"coordinates":[-0.3570010066,39.4745941162],"type":"Point"}
}