{
  "type": "Feature",
  "properties": {
    "addr:full":"Ptda Miralbo, 18 Cocentaina Alicante 03820",
    "addr:housenumber":"18",
    "addr:postcode":"03820",
    "addr:street":"Ptda Miralbo",
    "iso:country":"ES",
    "sg:address":"Ptda Miralbo, 18",
    "sg:city":"Cocentaina",
    "sg:orig_category":"Mataderos De Poller\u00cda",
    "sg:phone":"+34 965 59 11 28",
    "sg:postcode":"03820",
    "sg:province":"Alicante",
    "wof:name":"Aves Cocentaina S.l.",
    "wof:placetype":"venue"
},
  "geometry": {"coordinates":[-0.4408037066,38.7255172729],"type":"Point"}
}