{
  "type": "Feature",
  "properties": {
    "addr:full":"Lugar Estacion, S/n Algeciras C\u00e1diz 11207",
    "addr:postcode":"11207",
    "addr:street":"Lugar Estacion S / N;Ca\u0301Diz",
    "iso:country":"ES",
    "sg:address":"Lugar Estacion, S/n",
    "sg:city":"Algeciras",
    "sg:orig_category":"Caf\u00c9s, Bares, Cervecer\u00cdas",
    "sg:phone":"+34 956 63 10 05",
    "sg:postcode":"11207",
    "sg:province":"C\u00e1diz",
    "wof:name":"Casta\u00f1o Pe\u00f1alver Luis",
    "wof:placetype":"venue"
},
  "geometry": {"coordinates":[-5.4324541092,36.0734519958],"type":"Point"}
}