{
  "type": "Feature",
  "properties": {
    "addr:full":"Calle de Barandiaran, 9 Barakaldo Vizcaya 48903",
    "addr:housenumber":"9",
    "addr:postcode":"48903",
    "addr:street":"Calle De Barandiaran",
    "iso:country":"ES",
    "sg:address":"Calle de Barandiaran, 9",
    "sg:city":"Barakaldo",
    "sg:orig_category":"Bisuter\u00cda, Joyer\u00cda, Relojer\u00cda (al Por Menor)",
    "sg:phone":"+34 944 82 09 17",
    "sg:postcode":"48903",
    "sg:province":"Vizcaya",
    "wof:name":"Miguel Angel Nieto Nieto",
    "wof:placetype":"venue"
},
  "geometry": {"coordinates":[-2.9839980602,43.2853813171],"type":"Point"}
}