{
  "type": "Feature",
  "properties": {
    "iso:country":"ES",
    "sg:address":"Calle de Viento, S/n",
    "sg:city":"Madrid",
    "sg:orig_category":"Transporte En General",
    "sg:phone":"+34 917 47 45 17",
    "sg:postcode":"28022",
    "sg:province":"Madrid",
    "wof:name":"Benito Garcia Adoracion",
    "wof:placetype":"venue"
},
  "geometry": {"coordinates":[-3.571680069,40.4422798157],"type":"Point"}
}