{
  "type": "Feature",
  "properties": {
    "iso:country":"ES",
    "sg:address":"Avda Puente De Carlos Iii, 41",
    "sg:city":"Reinosa",
    "sg:orig_category":"Negocio De Materiales De Construcci\u00d3n",
    "sg:phone":"+34 942 75 11 97",
    "sg:postcode":"39200",
    "sg:province":"Cantabria",
    "wof:name":"Galerias Reison S.cv.",
    "wof:placetype":"venue"
},
  "geometry": {"coordinates":[-4.1393961906,42.9971961975],"type":"Point"}
}