{
  "type": "Feature",
  "properties": {
    "iso:country":"ES",
    "sg:address":"Plaz Basconia, 1",
    "sg:city":"Malaga",
    "sg:orig_category":"Reposter\u00cdas",
    "sg:phone":"+34 952 61 45 99",
    "sg:postcode":"29010",
    "sg:province":"M\u00e1laga",
    "wof:name":"Boutique Del Pan La Pelusa C.b.",
    "wof:placetype":"venue"
},
  "geometry": {"coordinates":[-4.4373350143,36.7227516174],"type":"Point"}
}