{
  "type": "Feature",
  "properties": {
    "iso:country":"ES",
    "sg:address":"Calle de Fuenlabrada, 11",
    "sg:city":"Alcorcon",
    "sg:orig_category":"Panader\u00cdas, Panader\u00cdas",
    "sg:phone":"+34 916 44 03 17",
    "sg:postcode":"28921",
    "sg:province":"Madrid",
    "wof:name":"Lahoz Gonzalez Francisco Andres",
    "wof:placetype":"venue"
},
  "geometry": {"coordinates":[-3.8268022537,40.3455619812],"type":"Point"}
}