{
  "type": "Feature",
  "properties": {
    "addr:full":"Carrer de Pare Llaurador, 112 Terrassa Barcelona 08224",
    "addr:housenumber":"112",
    "addr:postcode":"08224",
    "addr:street":"Carrer De Pare Llaurador",
    "iso:country":"ES",
    "sg:address":"Carrer de Pare Llaurador, 112",
    "sg:city":"Terrassa",
    "sg:orig_category":"Arquitectos",
    "sg:phone":"+34 937 80 75 98",
    "sg:postcode":"08224",
    "sg:province":"Barcelona",
    "wof:name":"Atm Arquitectura/tecnologia/mediambient S.l.",
    "wof:placetype":"venue"
},
  "geometry": {"coordinates":[2.0039732456,41.5640830994],"type":"Point"}
}