{
  "type": "Feature",
  "properties": {
    "addr:full":"Carrer de Aleixar (cami De L'), 59 Reus Tarragona 43202",
    "addr:housenumber":"59",
    "addr:postcode":"43202",
    "addr:street":"Carrer De Aleixar Cami De L '",
    "iso:country":"ES",
    "sg:address":"Carrer de Aleixar (cami De L'), 59",
    "sg:city":"Reus",
    "sg:orig_category":"Suministros Y Materiales Industriales",
    "sg:phone":"+34 977 33 29 97",
    "sg:postcode":"43202",
    "sg:province":"Tarragona",
    "wof:name":"Episer S.l.",
    "wof:placetype":"venue"
},
  "geometry": {"coordinates":[1.1001540422,41.157283783],"type":"Point"}
}