{
  "type": "Feature",
  "properties": {
    "iso:country":"ES",
    "sg:address":"Pase Castellana, 15",
    "sg:city":"Madrid",
    "sg:orig_category":"Centros Empresariales",
    "sg:phone":"+34 915 77 48 71",
    "sg:postcode":"28046",
    "sg:province":"Madrid",
    "wof:name":"Asociacion Circulo De Empresarios",
    "wof:placetype":"venue"
},
  "geometry": {"coordinates":[-3.6900887489,40.4281845093],"type":"Point"}
}