{
  "type": "Feature",
  "properties": {
    "iso:country":"ES",
    "sg:address":"Calle de Sanlucar De Barrameda, S/n",
    "sg:city":"Huelva",
    "sg:orig_category":"Universidades",
    "sg:phone":"+34 959 28 54 44",
    "sg:postcode":"21001",
    "sg:province":"Huelva",
    "wof:name":"Patronato Del Centro Provincial De La Universidad Nacional De Educacion A Distancia En Huelva Mec",
    "wof:placetype":"venue"
},
  "geometry": {"coordinates":[-6.957988739,37.2544898987],"type":"Point"}
}