{
  "type": "Feature",
  "properties": {
    "iso:country":"ES",
    "sg:address":"Calle de Viveros, 2",
    "sg:city":"Logro\u00f1o",
    "sg:orig_category":"Agencias Y Agentes Comerciales, Representantes",
    "sg:phone":"+34 941 22 31 15",
    "sg:postcode":"26005",
    "sg:province":"La Rioja",
    "wof:name":"Murua Alvarez Fernando Tomas",
    "wof:placetype":"venue"
},
  "geometry": {"coordinates":[-2.4593300819,42.4637794495],"type":"Point"}
}