{
  "type": "Feature",
  "properties": {
    "iso:country":"ES",
    "sg:address":"Avda Santa Cruz, 66",
    "sg:city":"San Isidro",
    "sg:orig_category":"Farmacias",
    "sg:phone":"+34 922 39 23 45",
    "sg:postcode":"38611",
    "sg:province":"Santa Cruz De Tenerife",
    "wof:name":"Duro Garcia Concepcion Eva",
    "wof:placetype":"venue"
},
  "geometry": {"coordinates":[-16.5587081909,28.0799808502],"type":"Point"}
}