{
  "type": "Feature",
  "properties": {
    "addr:full":"Calle de Cervera Del Rio Alhama, 2 Haro La Rioja 26200",
    "addr:housenumber":"2",
    "addr:postcode":"26200",
    "addr:street":"Calle De Cervera Del;Alhama",
    "iso:country":"ES",
    "sg:address":"Calle de Cervera Del Rio Alhama, 2",
    "sg:city":"Haro",
    "sg:orig_category":"Transportes Por V\u00cdas Navegables",
    "sg:phone":"+34 941 30 38 46",
    "sg:postcode":"26200",
    "sg:province":"La Rioja",
    "wof:name":"Fernandez Garcia Lorenzo",
    "wof:placetype":"venue"
},
  "geometry": {"coordinates":[-2.8483595848,42.5719947815],"type":"Point"}
}