{
  "type": "Feature",
  "properties": {
    "addr:full":"Calle de Rodio, 20 Sevilla Sevilla 41007",
    "addr:housenumber":"20",
    "addr:postcode":"41007",
    "addr:street":"Calle De Rodio",
    "iso:country":"ES",
    "sg:address":"Calle de Rodio, 20",
    "sg:city":"Sevilla",
    "sg:orig_category":"Asesor\u00cda De Formaci\u00d3n Y Gesti\u00d3n De Personal",
    "sg:phone":"+34 954 35 09 26",
    "sg:postcode":"41007",
    "sg:province":"Sevilla",
    "wof:name":"Gestion Empresarial Jolvi S.l.",
    "wof:placetype":"venue"
},
  "geometry": {"coordinates":[-5.9557538033,37.4075813293],"type":"Point"}
}