{
  "type": "Feature",
  "properties": {
    "iso:country":"ES",
    "sg:address":"Rua Ervedelo, 61",
    "sg:city":"Ourense",
    "sg:orig_category":"Peluquer\u00cdas, Peluquer\u00cda Mixta",
    "sg:phone":"+34 988 24 64 34",
    "sg:postcode":"32002",
    "sg:province":"Ourense",
    "wof:name":"Castro Mendez Maria Del Rosario",
    "wof:placetype":"venue"
},
  "geometry": {"coordinates":[-7.8735589981,42.3409996033],"type":"Point"}
}