{
  "type": "Feature",
  "properties": {
    "addr:full":"Calle de Cachorro, 9 Ibros Ja\u00e9n 23450",
    "addr:housenumber":"9",
    "addr:postcode":"23450",
    "addr:street":"Calle De Cachorro;Jae\u0301N",
    "iso:country":"ES",
    "sg:address":"Calle de Cachorro, 9",
    "sg:city":"Ibros",
    "sg:orig_category":"Telas Y Sedas (al Por Menor)",
    "sg:phone":"+34 953 76 60 55",
    "sg:postcode":"23450",
    "sg:province":"Ja\u00e9n",
    "wof:name":"Garrido Fernandez Gonzalo",
    "wof:placetype":"venue"
},
  "geometry": {"coordinates":[-3.5306766033,38.0420341492],"type":"Point"}
}