{
  "type": "Feature",
  "properties": {
    "iso:country":"ES",
    "sg:address":"Carr Isaac Peral, 30",
    "sg:city":"Port D'andratx",
    "sg:orig_category":"Ropa Para Se\u00d1oras (al Por Menor)",
    "sg:phone":"+34 971 67 18 65",
    "sg:postcode":"07157",
    "sg:province":"Islas Baleares",
    "wof:name":"Licoppe  Lesley",
    "wof:placetype":"venue"
},
  "geometry": {"coordinates":[2.3895709515,39.5443496704],"type":"Point"}
}