{
  "type": "Feature",
  "properties": {
    "addr:full":"Pase Bertsol. Txirrita, 18 Donostia-san Sebastian Guip\u00f9zcoa 20017",
    "addr:housenumber":"18",
    "addr:postcode":"20017",
    "addr:street":"Txirrita",
    "iso:country":"ES",
    "sg:address":"Pase Bertsol. Txirrita, 18",
    "sg:city":"Donostia-san Sebastian",
    "sg:orig_category":"Ense\u00d1anza: Idiomas",
    "sg:phone":"+34 943 39 43 77",
    "sg:postcode":"20017",
    "sg:province":"Guip\u00f9zcoa",
    "wof:name":"Next Lingo S.l.l.",
    "wof:placetype":"venue"
},
  "geometry": {"coordinates":[-1.9388669729,43.3147544861],"type":"Point"}
}