{
  "type": "Feature",
  "properties": {
    "iso:country":"ES",
    "sg:address":"Avda Orihuela, 8",
    "sg:city":"Almoradi",
    "sg:orig_category":"Ropa Para Se\u00d1oras Y Caballeros (al Por Menor)",
    "sg:phone":"+34 965 70 09 56",
    "sg:postcode":"03160",
    "sg:province":"Alicante",
    "wof:name":"Esther Avila S.l.",
    "wof:placetype":"venue"
},
  "geometry": {"coordinates":[-0.7968000174,38.1053848267],"type":"Point"}
}