{
  "type": "Feature",
  "properties": {
    "iso:country":"ES",
    "sg:address":"Calle de Toledo, 5",
    "sg:city":"Salamanca",
    "sg:orig_category":"Comercio De Cuadros, L\u00c1minas Y Reproducciones De Obras De Arte",
    "sg:phone":"+34 923 12 44 84",
    "sg:postcode":"37005",
    "sg:province":"Salamanca",
    "wof:name":"Gonzalez Estevez Jose",
    "wof:placetype":"venue"
},
  "geometry": {"coordinates":[-5.6598792076,40.9721984863],"type":"Point"}
}