{
  "type": "Feature",
  "properties": {
    "addr:full":"Ctra Madrid-irun, Km. 0242,7 Burgos Burgos 09007",
    "addr:postcode":"09007",
    "addr:street":"Ctra Madrid-Irun Km. 0242,7",
    "iso:country":"ES",
    "sg:address":"Ctra Madrid-irun, Km. 0242,7",
    "sg:city":"Burgos",
    "sg:orig_category":"Especias Finas (al Por Menor)",
    "sg:phone":"+34 947 48 36 34",
    "sg:postcode":"09007",
    "sg:province":"Burgos",
    "wof:name":"Especias Arco S.a.",
    "wof:placetype":"venue"
},
  "geometry": {"coordinates":[-3.6633379459,42.35496521],"type":"Point"}
}