{
  "type": "Feature",
  "properties": {
    "iso:country":"ES",
    "sg:address":"Via Trafico Pesado-p I La Paz, S/n",
    "sg:city":"Huelva",
    "sg:orig_category":"Transportes Por Carretera: Lotes Completos, Mercanc\u00cdas Diversas",
    "sg:phone":"+34 959 23 07 11",
    "sg:postcode":"21003",
    "sg:province":"Huelva",
    "wof:name":"Vtg Rail Espa\u00d1a S.l.",
    "wof:placetype":"venue"
},
  "geometry": {"coordinates":[-6.9464111328,37.2552108765],"type":"Point"}
}