{
  "type": "Feature",
  "properties": {
    "addr:full":"Avda Buenavista De, S/n Oviedo Asturias 33006",
    "addr:housenumber":"/ n",
    "addr:postcode":"33006",
    "addr:street":"Avda Buenavista De S",
    "iso:country":"ES",
    "sg:address":"Avda Buenavista De, S/n",
    "sg:city":"Oviedo",
    "sg:orig_category":"Ense\u00d1anza, Formaci\u00d3n Profesional: Aprendizaje",
    "sg:phone":"+34 985 24 33 62",
    "sg:postcode":"33006",
    "sg:province":"Asturias",
    "wof:name":"Sindicato Unificado Policia",
    "wof:placetype":"venue"
},
  "geometry": {"coordinates":[-5.8644747734,43.3593292236],"type":"Point"}
}