{
  "type": "Feature",
  "properties": {
    "addr:full":"Calle de Quart, 52 Valencia Valencia 46001",
    "addr:housenumber":"52",
    "addr:postcode":"46001",
    "addr:street":"Calle De Quart",
    "iso:country":"ES",
    "sg:address":"Calle de Quart, 52",
    "sg:city":"Valencia",
    "sg:orig_category":"Tapones Y Art\u00cdculos De Corcho",
    "sg:phone":"+34 963 91 21 14",
    "sg:postcode":"46001",
    "sg:province":"Valencia",
    "wof:name":"Gomez Segarra Jose Ramon",
    "wof:placetype":"venue"
},
  "geometry": {"coordinates":[-0.3830929995,39.4759712219],"type":"Point"}
}