{
  "type": "Feature",
  "properties": {
    "addr:full":"Avda Constitucion (la), 21 Sevilla Sevilla 41004",
    "addr:housenumber":"21",
    "addr:postcode":"41004",
    "addr:street":"Avda Constitucion La",
    "iso:country":"ES",
    "sg:address":"Avda Constitucion (la), 21",
    "sg:city":"Sevilla",
    "sg:orig_category":"Art\u00cdculos De Regalo (al Por Menor)",
    "sg:phone":"+34 954 22 14 08",
    "sg:postcode":"41004",
    "sg:province":"Sevilla",
    "wof:name":"Espejo Guerrero Ana",
    "wof:placetype":"venue"
},
  "geometry": {"coordinates":[-5.9934310913,37.3833694458],"type":"Point"}
}