{
  "type": "Feature",
  "properties": {
    "addr:full":"Poli Rubira Sola, S/n Macael Almer\u00eda 04867",
    "addr:housenumber":"/ n",
    "addr:postcode":"04867",
    "addr:street":"Sola S",
    "iso:country":"ES",
    "sg:address":"Poli Rubira Sola, S/n",
    "sg:city":"Macael",
    "sg:orig_category":"Metales (labores, Pulido)",
    "sg:phone":"+34 950 44 51 03",
    "sg:postcode":"04867",
    "sg:province":"Almer\u00eda",
    "wof:name":"Hierros Filabres S.l.",
    "wof:placetype":"venue"
},
  "geometry": {"coordinates":[-2.3024399281,37.3340568542],"type":"Point"}
}