{
  "type": "Feature",
  "properties": {
    "addr:full":"Calle de Retiro, 21 Ceclavin C\u00e1ceres 10870",
    "addr:housenumber":"21",
    "addr:postcode":"10870",
    "addr:street":"Calle De Retiro;Ca\u0301Ceres",
    "iso:country":"ES",
    "sg:address":"Calle de Retiro, 21",
    "sg:city":"Ceclavin",
    "sg:classifiers":[
        {
            "category":"Taxi",
            "type":"Transportation"
        }
    ],
    "sg:phone":"+34 927 39 30 96",
    "sg:postcode":"10870",
    "sg:province":"C\u00e1ceres",
    "wof:name":"Nu\u00f1ez De Sande Aquilino",
    "wof:placetype":"venue"
},
  "geometry": {"coordinates":[-6.7758688927,39.8213691711],"type":"Point"}
}