{
  "type": "Feature",
  "properties": {
    "iso:country":"ES",
    "sg:address":"Calle de Ramon Y Cajal, 29",
    "sg:city":"Huelma",
    "sg:orig_category":"Relojer\u00cda (al Por Menor, Reparaci\u00d3n)",
    "sg:phone":"+34 953 39 03 15",
    "sg:postcode":"23560",
    "sg:province":"Ja\u00e9n",
    "wof:name":"Diaz Fernandez Blas",
    "wof:placetype":"venue"
},
  "geometry": {"coordinates":[-3.4581758976,37.6489067078],"type":"Point"}
}