{
  "type": "Feature",
  "properties": {
    "iso:country":"ES",
    "sg:address":"Pl Universitat, 9",
    "sg:city":"Barcelona",
    "sg:orig_category":"Cuidado Del Cabello",
    "sg:phone":"+34 933 17 63 47",
    "sg:postcode":"08007",
    "sg:province":"Barcelona",
    "wof:name":"Sucesores De Andre Van Der Plassche S.l.",
    "wof:placetype":"venue"
},
  "geometry": {"coordinates":[2.1645750999,41.3856964111],"type":"Point"}
}