{
  "type": "Feature",
  "properties": {
    "addr:full":"Avda Zumalacarregui, 103 Bilbao Vizcaya 48007",
    "addr:housenumber":"103",
    "addr:postcode":"48007",
    "addr:street":"Avda Zumalacarregui",
    "iso:country":"ES",
    "sg:address":"Avda Zumalacarregui, 103",
    "sg:city":"Bilbao",
    "sg:orig_category":"Sociedades, Compa\u00d1\u00cdas Aseguradoras",
    "sg:phone":"+34 944 46 44 66",
    "sg:postcode":"48007",
    "sg:province":"Vizcaya",
    "wof:name":"Jose Maria Trevilla-angel Alvarez C. B.",
    "wof:placetype":"venue"
},
  "geometry": {"coordinates":[-2.9148991108,43.2612380981],"type":"Point"}
}