{
  "type": "Feature",
  "properties": {
    "iso:country":"ES",
    "sg:address":"Calle de Rio Alberche, S/n",
    "sg:city":"Poligono Sta M. De Benquerencia",
    "sg:orig_category":"Reposter\u00cdas",
    "sg:phone":"+34 925 23 37 41",
    "sg:postcode":"45007",
    "sg:province":"Toledo",
    "wof:name":"Artesania Industrial Panadera S.a.",
    "wof:placetype":"venue"
},
  "geometry": {"coordinates":[-4.0244760513,39.8567771912],"type":"Point"}
}