{
  "type": "Feature",
  "properties": {
    "addr:full":"Calle de Vistalmar, 6 Torremolinos M\u00e1laga 29620",
    "addr:housenumber":"6",
    "addr:postcode":"29620",
    "addr:street":"Calle De Vistalmar;Ma\u0301Laga",
    "iso:country":"ES",
    "sg:address":"Calle de Vistalmar, 6",
    "sg:city":"Torremolinos",
    "sg:orig_category":"Guarder\u00cdas",
    "sg:phone":"+34 952 38 25 13",
    "sg:postcode":"29620",
    "sg:province":"M\u00e1laga",
    "wof:name":"Ramos Corona Maria Dolores",
    "wof:placetype":"venue"
},
  "geometry": {"coordinates":[-4.492005825,36.6326980591],"type":"Point"}
}