{
  "type": "Feature",
  "properties": {
    "addr:full":"Calle de Fernandez De La Puente, 19 Badajoz Badajoz 06001",
    "addr:housenumber":"19",
    "addr:postcode":"06001",
    "addr:street":"Calle De Fernandez De La Puente",
    "iso:country":"ES",
    "sg:address":"Calle de Fernandez De La Puente, 19",
    "sg:city":"Badajoz",
    "sg:orig_category":"Inmobiliaria (agencias)",
    "sg:phone":"+34 924 24 86 13",
    "sg:postcode":"06001",
    "sg:province":"Badajoz",
    "wof:name":"Inmoverde De Guadiana S.l.",
    "wof:placetype":"venue"
},
  "geometry": {"coordinates":[-6.9758591652,38.8761291504],"type":"Point"}
}