{
  "type": "Feature",
  "properties": {
    "addr:full":"Pase Campo Volantin, 37 Bilbao Vizcaya 48...",
    "addr:housenumber":"37;48 ...",
    "addr:street":"Volantin;Vizcaya",
    "iso:country":"ES",
    "sg:address":"Pase Campo Volantin, 37",
    "sg:city":"Bilbao",
    "sg:orig_category":"Ense\u00d1anza, Formaci\u00d3n Profesional: Aprendizaje",
    "sg:phone":"+34 944 87 12 07",
    "sg:postcode":"48...",
    "sg:province":"Vizcaya",
    "wof:name":"Autoridad Portuaria De Bilbao",
    "wof:placetype":"venue"
},
  "geometry": {"coordinates":[-2.9305109978,43.2692680359],"type":"Point"}
}