{
  "type": "Feature",
  "properties": {
    "addr:full":"Calle de Roa De La Vega, 33 Le\u00f3n Le\u00f3n 24001",
    "addr:housenumber":"33",
    "addr:postcode":"24001",
    "addr:street":"Calle De Roa De La Vega;Leo\u0301N",
    "iso:country":"ES",
    "sg:address":"Calle de Roa De La Vega, 33",
    "sg:city":"Le\u00f3n",
    "sg:orig_category":"Ropa Para Se\u00d1oras (al Por Menor)",
    "sg:phone":"+34 987 24 39 36",
    "sg:postcode":"24001",
    "sg:province":"Le\u00f3n",
    "wof:name":"Gutierrez Martin Julian",
    "wof:placetype":"venue"
},
  "geometry": {"coordinates":[-5.5784888268,42.5979804993],"type":"Point"}
}