{
  "type": "Feature",
  "properties": {
    "iso:country":"ES",
    "sg:address":"Carr Raval, 19",
    "sg:city":"Bisbal D'emporda",
    "sg:orig_category":"Pizzer\u00cdas",
    "sg:phone":"+34 972 64 38 50",
    "sg:postcode":"17100",
    "sg:province":"Girona",
    "wof:name":"Pizzeria El Raig S.c.",
    "wof:placetype":"venue"
},
  "geometry": {"coordinates":[2.8087899685,41.9701538086],"type":"Point"}
}