{
  "type": "Feature",
  "properties": {
    "iso:country":"ES",
    "sg:address":"Carrer de Sant Ramon, 4",
    "sg:city":"Capellades",
    "sg:orig_category":"Camiser\u00cda Y Ropa Interior Masculina (al Por Menor)",
    "sg:phone":"+34 938 01 09 84",
    "sg:postcode":"08786",
    "sg:province":"Barcelona",
    "wof:name":"Rabasa Hortet Alberto",
    "wof:placetype":"venue"
},
  "geometry": {"coordinates":[-97.78224945069999,45.7040786743],"type":"Point"}
}