{
  "type": "Feature",
  "properties": {
    "iso:country":"ES",
    "sg:address":"Pta Marchena, 3",
    "sg:city":"Carmona",
    "sg:orig_category":"Ebanister\u00cda",
    "sg:phone":"+34 954 14 08 18",
    "sg:postcode":"41410",
    "sg:province":"Sevilla",
    "wof:name":"Carpinteria Gar S.l.",
    "wof:placetype":"venue"
},
  "geometry": {"coordinates":[-5.643157959,37.4659461975],"type":"Point"}
}