{
  "type": "Feature",
  "properties": {
    "iso:country":"ES",
    "sg:address":"Avda Fernandez Ladreda, 10",
    "sg:city":"Le\u00f3n",
    "sg:orig_category":"Fabricaci\u00d3n E Instalaci\u00d3n De Cajas Fuertes",
    "sg:phone":"+34 987 25 24 89",
    "sg:postcode":"24005",
    "sg:province":"Le\u00f3n",
    "wof:name":"Blanco Antu\u00f1a Blanca Nieves",
    "wof:placetype":"venue"
},
  "geometry": {"coordinates":[-5.5622701645,42.5874023438],"type":"Point"}
}