{
  "type": "Feature",
  "properties": {
    "iso:country":"ES",
    "sg:address":"Calle de Hileras, 5",
    "sg:city":"Madrid",
    "sg:orig_category":"Peluqueros: De Se\u00d1oras",
    "sg:phone":"+34 915 48 35 15",
    "sg:postcode":"28013",
    "sg:province":"Madrid",
    "wof:name":"Vimez Puebla Guillermina",
    "wof:placetype":"venue"
},
  "geometry": {"coordinates":[-3.7084400654,40.4170799255],"type":"Point"}
}