{
  "type": "Feature",
  "properties": {
    "addr:full":"Carretera Palencia-tina Menor, S/n Puentenansa Cantabria 39554",
    "addr:housenumber":"s / n",
    "addr:postcode":"39554",
    "addr:street":"Carretera Palencia-Tina Menor",
    "iso:country":"ES",
    "sg:address":"Carretera Palencia-tina Menor, S/n",
    "sg:city":"Puentenansa",
    "sg:orig_category":"Cajas De Ahorro",
    "sg:phone":"+34 942 72 80 10",
    "sg:postcode":"39554",
    "sg:province":"Cantabria",
    "sg:website":"www.cajacantabria.es",
    "wof:name":"Cableuropa",
    "wof:placetype":"venue"
},
  "geometry": {"coordinates":[-4.4067897797,43.2545547485],"type":"Point"}
}