{
  "type": "Feature",
  "properties": {
    "addr:full":"Avda Portugal, 12 Zamora Zamora 49015",
    "addr:housenumber":"12",
    "addr:postcode":"49015",
    "addr:street":"Avda Portugal",
    "iso:country":"ES",
    "sg:address":"Avda Portugal, 12",
    "sg:city":"Zamora",
    "sg:orig_category":"Agentes Generales De Seguros",
    "sg:phone":"+34 980 53 11 00",
    "sg:postcode":"49015",
    "sg:province":"Zamora",
    "wof:name":"Villafranca Covarrubias Miguel",
    "wof:placetype":"venue"
},
  "geometry": {"coordinates":[-5.7404270172,41.5065116882],"type":"Point"}
}