{
  "type": "Feature",
  "properties": {
    "addr:full":"Carrer de Lope De Vega, 68 Sabadell Barcelona 08204",
    "addr:housenumber":"68",
    "addr:postcode":"08204",
    "addr:street":"Carrer De Lope De Vega",
    "iso:country":"ES",
    "sg:address":"Carrer de Lope De Vega, 68",
    "sg:city":"Sabadell",
    "sg:orig_category":"Reposter\u00cdas",
    "sg:phone":"+34 937 10 38 35",
    "sg:postcode":"08204",
    "sg:province":"Barcelona",
    "wof:name":"Alba Granados Jose",
    "wof:placetype":"venue"
},
  "geometry": {"coordinates":[2.1182236671,41.5300559998],"type":"Point"}
}