{
  "type": "Feature",
  "properties": {
    "iso:country":"ES",
    "sg:address":"Calle de Jorge Juan, 40",
    "sg:city":"Madrid",
    "sg:orig_category":"Cr\u00cda De Animales",
    "sg:phone":"+34 915 76 80 27",
    "sg:postcode":"28001",
    "sg:province":"Madrid",
    "wof:name":"Sanchez Arjona Sanchez Javier",
    "wof:placetype":"venue"
},
  "geometry": {"coordinates":[-3.6821539402,40.4235496521],"type":"Point"}
}