{
  "type": "Feature",
  "properties": {
    "addr:full":"Calle de Illescas, 32 Madrid Madrid 28024",
    "addr:housenumber":"32",
    "addr:postcode":"madrid;28024",
    "addr:street":"Calle De Illescas",
    "iso:country":"ES",
    "sg:address":"Calle de Illescas, 32",
    "sg:city":"Madrid",
    "sg:orig_category":"Artes Gr\u00c1ficas, Artes Pl\u00c1sticas (curso)",
    "sg:phone":"+34 917 18 01 89",
    "sg:postcode":"28024",
    "sg:province":"Madrid",
    "wof:name":"Fernandez Serna Maria Del Carmen",
    "wof:placetype":"venue"
},
  "geometry": {"coordinates":[-3.763628006,40.3962936401],"type":"Point"}
}