{
  "type": "Feature",
  "properties": {
    "addr:full":"Trva Ruanova, S/n Ribadeo Lugo 27700",
    "addr:housenumber":"s / n",
    "addr:postcode":"27700",
    "addr:street":"Trva Ruanova",
    "iso:country":"ES",
    "sg:address":"Trva Ruanova, S/n",
    "sg:city":"Ribadeo",
    "sg:orig_category":"Asociaciones, Organismos Culturales Y Socioeducativos",
    "sg:phone":"+34 982 12 04 07",
    "sg:postcode":"27700",
    "sg:province":"Lugo",
    "wof:name":"Concello De Ribadeo",
    "wof:placetype":"venue"
},
  "geometry": {"coordinates":[-7.0403847694,43.5336265564],"type":"Point"}
}