{
  "type": "Feature",
  "properties": {
    "addr:full":"Calle de Feijoo, 5 Madrid Madrid 28010",
    "addr:housenumber":"5",
    "addr:postcode":"28010",
    "addr:street":"Calle De Feijoo",
    "iso:country":"ES",
    "sg:address":"Calle de Feijoo, 5",
    "sg:city":"Madrid",
    "sg:orig_category":"Empresarios",
    "sg:phone":"+34 914 47 73 29",
    "sg:postcode":"28010",
    "sg:province":"Madrid",
    "wof:name":"Monterde Rodriguez Coral",
    "wof:placetype":"venue"
},
  "geometry": {"coordinates":[-3.7034890652,40.4349899292],"type":"Point"}
}