{
  "type": "Feature",
  "properties": {
    "addr:full":"Calle de Mayor, 15 Salvatierra O Agurain \u00c1lava 01200",
    "addr:housenumber":"15",
    "addr:postcode":"01200",
    "addr:street":"Calle De Mayor;A\u0301Lava",
    "iso:country":"ES",
    "sg:address":"Calle de Mayor, 15",
    "sg:city":"Salvatierra O Agurain",
    "sg:orig_category":"Molduras, Junquillos, Listones Y Molduras Perforadas",
    "sg:phone":"+34 945 30 08 30",
    "sg:postcode":"01200",
    "sg:province":"\u00c1lava",
    "wof:name":"Naranjo Beiztegui S.c.",
    "wof:placetype":"venue"
},
  "geometry": {"coordinates":[-2.3900980949,42.8541069031],"type":"Point"}
}