{
  "type": "Feature",
  "properties": {
    "iso:country":"ES",
    "sg:address":"C/ Maximilia Thous, 96",
    "sg:city":"Elche",
    "sg:orig_category":"Asesor\u00cda Sobre Comunicaci\u00d3n De Empresas",
    "sg:phone":"+34 966 63 48 82",
    "sg:postcode":"03204",
    "sg:province":"Alicante",
    "wof:name":"Espuelas Cantero Santiago",
    "wof:placetype":"venue"
},
  "geometry": {"coordinates":[-0.7060490251,38.2575759888],"type":"Point"}
}