{
  "type": "Feature",
  "properties": {
    "addr:full":"Calle de Academico Saraza, 10 Cordoba C\u00f3rdoba 14012",
    "addr:housenumber":"10",
    "addr:postcode":"14012",
    "addr:street":"Calle De Academico Saraza;Co\u0301Rdoba",
    "iso:country":"ES",
    "sg:address":"Calle de Academico Saraza, 10",
    "sg:city":"Cordoba",
    "sg:orig_category":"Carnicer\u00cdas, Carnicer\u00cdas",
    "sg:phone":"+34 957 28 30 19",
    "sg:postcode":"14012",
    "sg:province":"C\u00f3rdoba",
    "wof:name":"Carnes Los Seis S.l.",
    "wof:placetype":"venue"
},
  "geometry": {"coordinates":[-4.7804551125,37.9089775085],"type":"Point"}
}