{
  "type": "Feature",
  "properties": {
    "iso:country":"ES",
    "sg:address":"Calle de Axular, 5",
    "sg:city":"Barakaldo",
    "sg:classifiers":[
        {
            "category":"Personal",
            "subcategory":"Barber",
            "type":"Services"
        }
    ],
    "sg:phone":"+34 944 99 22 84",
    "sg:postcode":"48902",
    "sg:province":"Vizcaya",
    "sg:tags":[
        "caballeros",
        "de",
        "peluqueros"
    ],
    "wof:name":"Francisco Gomez Santos",
    "wof:placetype":"venue"
},
  "geometry": {"coordinates":[-2.993011713,43.29114151],"type":"Point"}
}