{
  "type": "Feature",
  "properties": {
    "addr:full":"Avda Zuberoa, 14 Bilbao Vizcaya 48012",
    "addr:housenumber":"14",
    "addr:postcode":"48012",
    "addr:street":"Avda Zuberoa",
    "iso:country":"ES",
    "sg:address":"Avda Zuberoa, 14",
    "sg:city":"Bilbao",
    "sg:orig_category":"Molduras, Junquillos, Listones Y Molduras Perforadas",
    "sg:phone":"+34 944 22 10 85",
    "sg:postcode":"48012",
    "sg:province":"Vizcaya",
    "wof:name":"Garcia Fernandez Faustina",
    "wof:placetype":"venue"
},
  "geometry": {"coordinates":[-2.9352788925,43.2547492981],"type":"Point"}
}