{
  "type": "Feature",
  "properties": {
    "iso:country":"ES",
    "sg:address":"Avda Miraflores Del Palo, 2",
    "sg:city":"Malaga",
    "sg:orig_category":"Empresas De Carpinter\u00cda Met\u00c1lica",
    "sg:phone":"+34 952 29 34 70",
    "sg:postcode":"29018",
    "sg:province":"M\u00e1laga",
    "wof:name":"Garcia Martin Jose Antonio",
    "wof:placetype":"venue"
},
  "geometry": {"coordinates":[-4.3543357849,36.721244812],"type":"Point"}
}