{
  "type": "Feature",
  "properties": {
    "iso:country":"ES",
    "sg:address":"Calle de Libertad, 86",
    "sg:city":"Monesterio",
    "sg:orig_category":"Peluqueros: De Se\u00d1oras",
    "sg:phone":"+34 924 51 73 08",
    "sg:postcode":"06260",
    "sg:province":"Badajoz",
    "wof:name":"Granadero Garrote Purificacion",
    "wof:placetype":"venue"
},
  "geometry": {"coordinates":[-6.275302887,38.0864524841],"type":"Point"}
}