{
  "type": "Feature",
  "properties": {
    "iso:country":"ES",
    "sg:address":"Carrer de Mariano Benlliure, 6",
    "sg:city":"Ondara",
    "sg:orig_category":"Hoteles",
    "sg:phone":"+34 965 76 63 13",
    "sg:postcode":"03760",
    "sg:province":"Alicante",
    "wof:name":"Hotel Ramis S.l.",
    "wof:placetype":"venue"
},
  "geometry": {"coordinates":[0.0145300003,38.8284988403],"type":"Point"}
}