{
  "type": "Feature",
  "properties": {
    "addr:full":"Ctra Madrid, 1 Soria Soria 42005",
    "addr:housenumber":"1",
    "addr:postcode":"42005",
    "addr:street":"Ctra Madrid",
    "iso:country":"ES",
    "sg:address":"Ctra Madrid, 1",
    "sg:city":"Soria",
    "sg:orig_category":"Art\u00cdculos De Decoraci\u00d3n (fabricaci\u00d3n Y Al Por Mayor)",
    "sg:phone":"+34 975 23 31 40",
    "sg:postcode":"42005",
    "sg:province":"Soria",
    "wof:name":"Simexpor S.l.",
    "wof:placetype":"venue"
},
  "geometry": {"coordinates":[-2.4770569801,41.7543754578],"type":"Point"}
}