{
  "type": "Feature",
  "properties": {
    "addr:full":"Calle de Federico Balart, 13 Mula Murcia 30170",
    "addr:housenumber":"13",
    "addr:postcode":"30170",
    "addr:street":"Calle De Federico Balart",
    "iso:country":"ES",
    "sg:address":"Calle de Federico Balart, 13",
    "sg:city":"Mula",
    "sg:orig_category":"Inmobiliaria (agencias)",
    "sg:phone":"+34 968 66 27 35",
    "sg:postcode":"30170",
    "sg:province":"Murcia",
    "sg:website":"www.boludacaballero.com",
    "wof:name":"Boluda Caballero S.l.",
    "wof:placetype":"venue"
},
  "geometry": {"coordinates":[-1.4932750463,38.0397148132],"type":"Point"}
}