{
  "type": "Feature",
  "properties": {
    "addr:full":"Ptda Regatell, S/n Alcora Castell\u00f3n 12110",
    "addr:housenumber":"s / n",
    "addr:postcode":"12110",
    "addr:street":"Ptda Regatell;Alcora Castello\u0301N",
    "iso:country":"ES",
    "sg:address":"Ptda Regatell, S/n",
    "sg:city":"Alcora",
    "sg:orig_category":"Arenas, Guijarros Y Granulados",
    "sg:phone":"+34 964 38 63 50",
    "sg:postcode":"12110",
    "sg:province":"Castell\u00f3n",
    "wof:name":"Atomizadas De Alcora S.a.",
    "wof:placetype":"venue"
},
  "geometry": {"coordinates":[-0.2150872946,40.0733642578],"type":"Point"}
}