{
  "type": "Feature",
  "properties": {
    "iso:country":"ES",
    "sg:address":"Sta Teresa De Jornet, 47",
    "sg:city":"Osma",
    "sg:orig_category":"Obras Y Organismos Sociales",
    "sg:phone":"+34 975 34 08 67",
    "sg:postcode":"42300",
    "sg:province":"Soria",
    "wof:name":"Asilo Hermanitas De Los Ancianos",
    "wof:placetype":"venue"
},
  "geometry": {"coordinates":[-3.0754244328,41.588760376],"type":"Point"}
}