{
  "type": "Feature",
  "properties": {
    "iso:country":"ES",
    "sg:address":"Pl Forjador, S/n",
    "sg:city":"Castellar Valles",
    "sg:orig_category":"Fabricaci\u00d3n De Pastas Alimentarias",
    "sg:phone":"+34 937 14 21 45",
    "sg:postcode":"08211",
    "sg:province":"Barcelona",
    "wof:name":"Navarro Hernandez Enrique",
    "wof:placetype":"venue"
},
  "geometry": {"coordinates":[2.0835499763,41.6127548218],"type":"Point"}
}