{
  "type": "Feature",
  "properties": {
    "iso:country":"ES",
    "sg:address":"Carrer de Doctor Marti I Julia, 89",
    "sg:city":"Hospitalet Llobregat",
    "sg:orig_category":"Carnicer\u00cdas, Carnicer\u00cdas",
    "sg:phone":"+34 934 49 10 49",
    "sg:postcode":"08903",
    "sg:province":"Barcelona",
    "wof:name":"Bcn Distribucion Alte S.c.p",
    "wof:placetype":"venue"
},
  "geometry": {"coordinates":[2.1237111092,41.3725547791],"type":"Point"}
}