{
  "type": "Feature",
  "properties": {
    "addr:full":"Cta. Valdesangil, S/n Bejar Salamanca 37700",
    "addr:housenumber":"s / n",
    "addr:postcode":"37700",
    "addr:street":"Valdesangil",
    "iso:country":"ES",
    "sg:address":"Cta. Valdesangil, S/n",
    "sg:city":"Bejar",
    "sg:orig_category":"M\u00c1rmoles, Granitos Y Piedras Naturales",
    "sg:phone":"+34 923 40 24 19",
    "sg:postcode":"37700",
    "sg:province":"Salamanca",
    "wof:name":"Marmoles San Juan Bejar C B",
    "wof:placetype":"venue"
},
  "geometry": {"coordinates":[-5.7591128349,40.3904571533],"type":"Point"}
}