{
  "type": "Feature",
  "properties": {
    "iso:country":"ES",
    "sg:address":"Calle de Carrero Micalet, 17",
    "sg:city":"Riba-roja Turia",
    "sg:orig_category":"Peluquer\u00cdas, Peluquer\u00cda Mixta",
    "sg:phone":"+34 961 65 39 15",
    "sg:postcode":"46190",
    "sg:province":"Valencia",
    "wof:name":"Isi & Mar Peluqueros S.l.",
    "wof:placetype":"venue"
},
  "geometry": {"coordinates":[-0.5706191063,39.5459594727],"type":"Point"}
}