{
  "type": "Feature",
  "properties": {
    "addr:full":"Pl Sardana (la), 1 Torello Barcelona 08570",
    "addr:housenumber":"1",
    "addr:postcode":"08570",
    "addr:street":"Sardana La",
    "iso:country":"ES",
    "sg:address":"Pl Sardana (la), 1",
    "sg:city":"Torello",
    "sg:orig_category":"Cajas De Ahorro",
    "sg:phone":"+34 938 59 22 11",
    "sg:postcode":"08570",
    "sg:province":"Barcelona",
    "sg:website":"www.caixacatalunya.es",
    "wof:name":"Caixa D'estalvis De Catalunya",
    "wof:placetype":"venue"
},
  "geometry": {"coordinates":[2.2540800571,42.0519943237],"type":"Point"}
}