{
  "type": "Feature",
  "properties": {
    "iso:country":"ES",
    "sg:address":"Avda Portugal, 135",
    "sg:city":"Salamanca",
    "sg:orig_category":"Pintura Y Barniz (al Por Menor)",
    "sg:phone":"+34 923 25 53 73",
    "sg:postcode":"37006",
    "sg:province":"Salamanca",
    "wof:name":"Hogar Del Pintor Ii S.l.",
    "wof:placetype":"venue"
},
  "geometry": {"coordinates":[-5.6653409004,40.9727630615],"type":"Point"}
}