{
  "type": "Feature",
  "properties": {
    "iso:country":"ES",
    "sg:address":"Carr Porta Sant Miquel, 6",
    "sg:city":"Xativa",
    "sg:orig_category":"Laboratorios Y Cl\u00cdnicas Veterinarias",
    "sg:phone":"+34 962 27 33 56",
    "sg:postcode":"46800",
    "sg:province":"Valencia",
    "wof:name":"Martinez Navalon Raul",
    "wof:placetype":"venue"
},
  "geometry": {"coordinates":[-0.5256260037,38.988899231],"type":"Point"}
}