{
  "type": "Feature",
  "properties": {
    "addr:full":"Calle de Salitre, 26 Cartagena Murcia 30205",
    "addr:housenumber":"26",
    "addr:postcode":"30205",
    "addr:street":"Calle De Salitre",
    "iso:country":"ES",
    "sg:address":"Calle de Salitre, 26",
    "sg:city":"Cartagena",
    "sg:orig_category":"Retoques De Vestidos",
    "sg:phone":"+34 968 52 13 90",
    "sg:postcode":"30205",
    "sg:province":"Murcia",
    "wof:name":"Arregos A Medida Mid,s.l.l",
    "wof:placetype":"venue"
},
  "geometry": {"coordinates":[-0.9881308079,37.6048583984],"type":"Point"}
}