{
  "type": "Feature",
  "properties": {
    "addr:full":"Calle de San Cayetano, 4 Madrid Madrid 28005",
    "addr:housenumber":"4",
    "addr:postcode":"28005",
    "addr:street":"Calle De San Cayetano",
    "iso:country":"ES",
    "sg:address":"Calle de San Cayetano, 4",
    "sg:city":"Madrid",
    "sg:orig_category":"Fabricaci\u00d3n, Venta De Cuadros, Accesorios Para Enmarcar",
    "sg:phone":"+34 915 27 85 88",
    "sg:postcode":"28005",
    "sg:province":"Madrid",
    "wof:name":"Galerias Minguez S.l.",
    "wof:placetype":"venue"
},
  "geometry": {"coordinates":[-3.7064950466,40.4095306396],"type":"Point"}
}