{
  "type": "Feature",
  "properties": {
    "addr:full":"Ctra. Coru\u00f1a, Km. 0039,0 Collado Villalba Madrid 28400",
    "addr:postcode":"28400",
    "addr:street":"Ctra. Corun\u0303A Km. 0039,0",
    "iso:country":"ES",
    "sg:address":"Ctra. Coru\u00f1a, Km. 0039,0",
    "sg:city":"Collado Villalba",
    "sg:orig_category":"Inmobiliaria (agencias)",
    "sg:phone":"+34 918 51 44 35",
    "sg:postcode":"28400",
    "sg:province":"Madrid",
    "wof:name":"Inmomagerit Herraez S.l.",
    "wof:placetype":"venue"
},
  "geometry": {"coordinates":[-4.0064492226,40.6153297424],"type":"Point"}
}