{
  "type": "Feature",
  "properties": {
    "addr:full":"Calle de Garran, 8 Najera La Rioja 26300",
    "addr:housenumber":"8",
    "addr:postcode":"26300",
    "addr:street":"Calle De Garran;Rioja",
    "iso:country":"ES",
    "sg:address":"Calle de Garran, 8",
    "sg:city":"Najera",
    "sg:orig_category":"Ropa Para Se\u00d1oras Y Caballeros (al Por Menor)",
    "sg:phone":"+34 941 36 22 51",
    "sg:postcode":"26300",
    "sg:province":"La Rioja",
    "wof:name":"Rigoletto S.c.",
    "wof:placetype":"venue"
},
  "geometry": {"coordinates":[-2.7351410389,42.4165534973],"type":"Point"}
}