{
  "type": "Feature",
  "properties": {
    "addr:full":"Pl Creu Alta, S/n Sabadell Barcelona 08208",
    "addr:housenumber":"s",
    "addr:postcode":"08208",
    "addr:street":"Pl Creu Alta;/ N",
    "iso:country":"ES",
    "sg:address":"Pl Creu Alta, S/n",
    "sg:city":"Sabadell",
    "sg:orig_category":"Iglesia Cat\u00d3lica",
    "sg:phone":"+34 937 16 14 70",
    "sg:postcode":"08208",
    "sg:province":"Barcelona",
    "wof:name":"Parroquia De San Vicente",
    "wof:placetype":"venue"
},
  "geometry": {"coordinates":[2.1019101143,41.5558815002],"type":"Point"}
}