{
  "type": "Feature",
  "properties": {
    "iso:country":"ES",
    "sg:address":"Calle de Mayor, 4",
    "sg:city":"San Esteban De Litera",
    "sg:orig_category":"Farmacias",
    "sg:phone":"+34 974 43 02 76",
    "sg:postcode":"22512",
    "sg:province":"Huesca",
    "wof:name":"Castan Castillo Ana Maria",
    "wof:placetype":"venue"
},
  "geometry": {"coordinates":[0.3262189925,41.9049301147],"type":"Point"}
}