{
  "type": "Feature",
  "properties": {
    "iso:country":"ES",
    "sg:address":"Avda Fontes, 9",
    "sg:city":"Torre-pacheco",
    "sg:orig_category":"Promotores Constructores",
    "sg:phone":"+34 968 58 55 75",
    "sg:postcode":"30700",
    "sg:province":"Murcia",
    "wof:name":"Aniceto Saura Olmos Y Martos Saura Olmos C.b.",
    "wof:placetype":"venue"
},
  "geometry": {"coordinates":[-0.9569203854,37.7384490967],"type":"Point"}
}