{
  "type": "Feature",
  "properties": {
    "addr:full":"Calle de Merida, 8 Madrid Madrid 28030",
    "addr:housenumber":"8",
    "addr:postcode":"madrid;28030",
    "addr:street":"Calle De Merida",
    "iso:country":"ES",
    "sg:address":"Calle de Merida, 8",
    "sg:city":"Madrid",
    "sg:orig_category":"Cl\u00cdnicas M\u00c9dicas",
    "sg:phone":"+34 913 71 10 80",
    "sg:postcode":"28030",
    "sg:province":"Madrid",
    "wof:name":"Ruiz Cotoli Silvia",
    "wof:placetype":"venue"
},
  "geometry": {"coordinates":[-3.6368210316,40.4074058533],"type":"Point"}
}