{
  "type": "Feature",
  "properties": {
    "addr:full":"Calle de Velazquez, 20 San Lorenzo De El Escorial Madrid 28200",
    "addr:housenumber":"20",
    "addr:postcode":"28200",
    "addr:street":"Calle De Velazquez",
    "iso:country":"ES",
    "sg:address":"Calle de Velazquez, 20",
    "sg:city":"San Lorenzo De El Escorial",
    "sg:orig_category":"Ropa De Trabajo Y Profesionales (fabricaci\u00d3n, Al Por Mayor)",
    "sg:phone":"+34 918 96 90 21",
    "sg:postcode":"28200",
    "sg:province":"Madrid",
    "wof:name":"Paramo Textil S.c.",
    "wof:placetype":"venue"
},
  "geometry": {"coordinates":[-4.1443572044,40.5937080383],"type":"Point"}
}