{
  "type": "Feature",
  "properties": {
    "addr:full":"Calle de Doctor Jaime Vera, 2 Salamanca Salamanca 37007",
    "addr:housenumber":"2",
    "addr:postcode":"37007",
    "addr:street":"Calle De Doctor Jaime Vera",
    "iso:country":"ES",
    "sg:address":"Calle de Doctor Jaime Vera, 2",
    "sg:city":"Salamanca",
    "sg:orig_category":"Inform\u00c1tica, Ofim\u00c1tica (estudios, Asesor\u00cda, Ingenier\u00cda, Formaci\u00d3n)",
    "sg:phone":"+34 923 28 26 19",
    "sg:postcode":"37007",
    "sg:province":"Salamanca",
    "wof:name":"\u00d1 Si S.coop.",
    "wof:placetype":"venue"
},
  "geometry": {"coordinates":[-5.6682662964,40.9707107544],"type":"Point"}
}