{
  "type": "Feature",
  "properties": {
    "addr:full":"Os Carballi\u00f1os, S/n Vilatuxe Pontevedra 36519",
    "addr:housenumber":"s",
    "addr:postcode":"36519",
    "addr:street":"/ N",
    "iso:country":"ES",
    "sg:address":"Os Carballi\u00f1os, S/n",
    "sg:city":"Vilatuxe",
    "sg:orig_category":"Centros De Educaci\u00d3n Especial",
    "sg:phone":"+34 986 78 30 94",
    "sg:postcode":"36519",
    "sg:province":"Pontevedra",
    "wof:name":"Ayuntamiento De Lalin-colegio Publico De Villatuje",
    "wof:placetype":"venue"
},
  "geometry": {"coordinates":[-8.1904354095,42.6054496765],"type":"Point"}
}