{
  "type": "Feature",
  "properties": {
    "iso:country":"ES",
    "sg:address":"Calle de Soria, 19",
    "sg:city":"Benavente",
    "sg:orig_category":"Fabricaci\u00d3n De Ventanas",
    "sg:phone":"+34 980 63 07 97",
    "sg:postcode":"49600",
    "sg:province":"Zamora",
    "wof:name":"Arribas Requejo Antonio",
    "wof:placetype":"venue"
},
  "geometry": {"coordinates":[-5.6773509979,42.0072517395],"type":"Point"}
}