{
  "type": "Feature",
  "properties": {
    "iso:country":"ES",
    "sg:address":"Carrer de Lope De Vega, 290",
    "sg:city":"Barcelona",
    "sg:orig_category":"Institutos De Belleza",
    "sg:phone":"+34 933 07 53 28",
    "sg:postcode":"08018",
    "sg:province":"Barcelona",
    "wof:name":"Soteras Girbau Maria Isabel",
    "wof:placetype":"venue"
},
  "geometry": {"coordinates":[2.1932868958,41.4124107361],"type":"Point"}
}