{
  "type": "Feature",
  "properties": {
    "iso:country":"ES",
    "sg:address":"Avda Fermin Salvochea, 26",
    "sg:city":"Barriada Rio San Pedro",
    "sg:orig_category":"Peluquer\u00cdas, Peluquer\u00cda Mixta",
    "sg:phone":"+34 956 47 82 23",
    "sg:postcode":"11519",
    "sg:province":"C\u00e1diz",
    "wof:name":"Collantes Reina Rosario",
    "wof:placetype":"venue"
},
  "geometry": {"coordinates":[-6.2277288437,36.5223617554],"type":"Point"}
}