{
  "type": "Feature",
  "properties": {
    "iso:country":"ES",
    "sg:address":"A Cancela, 30",
    "sg:city":"Cancela",
    "sg:orig_category":"Charcuter\u00cdas (al Por Mayor)",
    "sg:phone":"+34 986 86 34 56",
    "sg:postcode":"36143",
    "sg:province":"Pontevedra",
    "wof:name":"Carnicas El Ma\u00f1o S.l.",
    "wof:placetype":"venue"
},
  "geometry": {"coordinates":[-8.6421194077,42.4087219238],"type":"Point"}
}