{
  "type": "Feature",
  "properties": {
    "addr:full":"Carrer de Tres D'abril, 37 S. Boi Llobregat Barcelona 08830",
    "addr:housenumber":"37",
    "addr:postcode":"08830",
    "addr:street":"Carrer De Tres D'Abril",
    "iso:country":"ES",
    "sg:address":"Carrer de Tres D'abril, 37",
    "sg:city":"S. Boi Llobregat",
    "sg:orig_category":"Carnicer\u00cdas, Carnicer\u00cdas",
    "sg:phone":"+34 936 40 17 38",
    "sg:postcode":"08830",
    "sg:province":"Barcelona",
    "wof:name":"Gallardo Cabrera Miguel",
    "wof:placetype":"venue"
},
  "geometry": {"coordinates":[2.0428183079,41.3405838013],"type":"Point"}
}