{
  "type": "Feature",
  "properties": {
    "addr:full":"Calle de Balleneros, 10 Donostia-san Sebastian Guip\u00f9zcoa 20011",
    "addr:housenumber":"10",
    "addr:postcode":"20011",
    "addr:street":"Calle De Balleneros",
    "iso:country":"ES",
    "sg:address":"Calle de Balleneros, 10",
    "sg:city":"Donostia-san Sebastian",
    "sg:orig_category":"Ropa Para Se\u00d1oras (al Por Menor)",
    "sg:phone":"+34 943 47 20 89",
    "sg:postcode":"20011",
    "sg:province":"Guip\u00f9zcoa",
    "wof:name":"Irastorza Mitxelena Franciska",
    "wof:placetype":"venue"
},
  "geometry": {"coordinates":[-1.9746352434,43.3049278259],"type":"Point"}
}