{
  "type": "Feature",
  "properties": {
    "iso:country":"ES",
    "sg:address":"Av Tres-cents Cinc, 12",
    "sg:city":"Castelldefels",
    "sg:orig_category":"Art\u00cdculos De Decoraci\u00d3n",
    "sg:phone":"+34 936 36 13 46",
    "sg:postcode":"08860",
    "sg:province":"Barcelona",
    "wof:name":"Baix Llobregt Inversions Reunidas Sl",
    "wof:placetype":"venue"
},
  "geometry": {"coordinates":[1.9784450531,41.2793083191],"type":"Point"}
}