{
  "type": "Feature",
  "properties": {
    "iso:country":"ES",
    "sg:address":"Pla\u00c7 Major, 7",
    "sg:city":"Almatret",
    "sg:orig_category":"Instalaci\u00d3n De Calefacci\u00d3n Industrial",
    "sg:phone":"+34 973 13 80 60",
    "sg:postcode":"25179",
    "sg:province":"Lleida",
    "wof:name":"Valles Valles Jordi",
    "wof:placetype":"venue"
},
  "geometry": {"coordinates":[0.5079349875,41.3652992249],"type":"Point"}
}