{
  "type": "Feature",
  "properties": {
    "iso:country":"ES",
    "sg:address":"Laubide Auzoa, 19",
    "sg:city":"Legazpi",
    "sg:orig_category":"Art\u00cdculos De Decoraci\u00d3n",
    "sg:phone":"+34 943 73 10 17",
    "sg:postcode":"20230",
    "sg:province":"Guip\u00f9zcoa",
    "wof:name":"Carrasco Valhondo Diego",
    "wof:placetype":"venue"
},
  "geometry": {"coordinates":[-2.3370070457,43.0572280884],"type":"Point"}
}