{
  "type": "Feature",
  "properties": {
    "iso:country":"ES",
    "sg:address":"Pla\u00c7 Concordia, 11",
    "sg:city":"Burjassot",
    "sg:orig_category":"Ortopedia General",
    "sg:phone":"+34 963 90 47 48",
    "sg:postcode":"46100",
    "sg:province":"Valencia",
    "wof:name":"Marin Bataller Rosa",
    "wof:placetype":"venue"
},
  "geometry": {"coordinates":[-0.4154520035,39.5131797791],"type":"Point"}
}