{
  "type": "Feature",
  "properties": {
    "addr:full":"Ctra Avileses, S/n Balsicas Murcia 30591",
    "addr:housenumber":"s / n",
    "addr:postcode":"30591",
    "addr:street":"Ctra Avileses",
    "iso:country":"ES",
    "sg:address":"Ctra Avileses, S/n",
    "sg:city":"Balsicas",
    "sg:orig_category":"Hormig\u00d3n (m\u00c1quinas E Instalaci\u00d3n)",
    "sg:phone":"+34 968 58 10 01",
    "sg:postcode":"30591",
    "sg:province":"Murcia",
    "wof:name":"Hormigones Mar Menor S.l.",
    "wof:placetype":"venue"
},
  "geometry": {"coordinates":[-0.9508939981,37.8170852661],"type":"Point"}
}