{
  "type": "Feature",
  "properties": {
    "addr:full":"Calle de Lealtad, 3 Santander Cantabria 39002",
    "addr:housenumber":"3",
    "addr:postcode":"39002",
    "addr:street":"Calle De Lealtad",
    "iso:country":"ES",
    "sg:address":"Calle de Lealtad, 3",
    "sg:city":"Santander",
    "sg:orig_category":"Ropa Para Se\u00d1oras (al Por Menor)",
    "sg:phone":"+34 942 36 58 25",
    "sg:postcode":"39002",
    "sg:province":"Cantabria",
    "sg:website":"www.angelschlesser.com",
    "wof:name":"Shlesser Santander S.l.",
    "wof:placetype":"venue"
},
  "geometry": {"coordinates":[-3.8082180023,43.46251297],"type":"Point"}
}