{
  "type": "Feature",
  "properties": {
    "addr:full":"La Hoguera, 35 Castelseras Teruel 44630",
    "addr:housenumber":"35",
    "addr:postcode":"44630",
    "addr:street":"Castelseras Teruel",
    "iso:country":"ES",
    "sg:address":"La Hoguera, 35",
    "sg:city":"Castelseras",
    "sg:orig_category":"Pintura, Barniz, Productos Asimilables (fabricaci\u00d3n, Al Por Mayor)",
    "sg:phone":"+34 978 87 70 67",
    "sg:postcode":"44630",
    "sg:province":"Teruel",
    "wof:name":"Obon Ceperuelo Cesar Jesus",
    "wof:placetype":"venue"
},
  "geometry": {"coordinates":[-0.1446930021,40.9844512939],"type":"Point"}
}