{
  "type": "Feature",
  "properties": {
    "iso:country":"ES",
    "sg:address":"Calle de Ancha, 77",
    "sg:city":"Puertollano",
    "sg:orig_category":"Promotores Constructores",
    "sg:phone":"+34 926 43 27 76",
    "sg:postcode":"13500",
    "sg:province":"Ciudad Real",
    "wof:name":"Ancha Puertollano Promociones Inmobiliarias S.l.",
    "wof:placetype":"venue"
},
  "geometry": {"coordinates":[-4.1102662086,38.6917800903],"type":"Point"}
}