{
  "type": "Feature",
  "properties": {
    "addr:full":"Carr Avinyonet, 45 Figueres Girona 17600",
    "addr:housenumber":"45",
    "addr:postcode":"17600",
    "addr:street":"Carr Avinyonet",
    "iso:country":"ES",
    "sg:address":"Carr Avinyonet, 45",
    "sg:city":"Figueres",
    "sg:orig_category":"Alimentaci\u00d3n General (al Por Menor)",
    "sg:phone":"+34 972 50 48 79",
    "sg:postcode":"17600",
    "sg:province":"Girona",
    "wof:name":"Gonzalez Enriquez Jose",
    "wof:placetype":"venue"
},
  "geometry": {"coordinates":[2.9524331093,42.2651824951],"type":"Point"}
}