{
  "type": "Feature",
  "properties": {
    "iso:country":"ES",
    "sg:address":"Calle de San Anton, S/n",
    "sg:city":"Navarredondilla",
    "sg:orig_category":"Ambulancias",
    "sg:phone":"+34 920 29 74 26",
    "sg:postcode":"05120",
    "sg:province":"\u00c1vila",
    "wof:name":"Funeraria Victorio Gonzalez S.l.",
    "wof:placetype":"venue"
},
  "geometry": {"coordinates":[-4.8186187744,40.4558601379],"type":"Point"}
}