{
  "type": "Feature",
  "properties": {
    "addr:full":"Avda. Andalucia, 67 Torreperogil Ja\u00e9n 23320",
    "addr:housenumber":"67",
    "addr:postcode":"23320",
    "addr:street":"Avda. Andalucia",
    "iso:country":"ES",
    "sg:address":"Avda. Andalucia, 67",
    "sg:city":"Torreperogil",
    "sg:orig_category":"Telas Y Sedas (al Por Menor)",
    "sg:phone":"+34 953 77 61 34",
    "sg:postcode":"23320",
    "sg:province":"Ja\u00e9n",
    "wof:name":"Hermanos Gaitan Moreno C.b.",
    "wof:placetype":"venue"
},
  "geometry": {"coordinates":[-3.3150045872,38.0692100525],"type":"Point"}
}