{
  "type": "Feature",
  "properties": {
    "addr:full":"Explanada De La Bas\u00edlica, S/n Covadonga Asturias 33589",
    "addr:housenumber":"s",
    "addr:postcode":"33589",
    "addr:street":"/ N Covadonga",
    "iso:country":"ES",
    "sg:address":"Explanada De La Bas\u00edlica, S/n",
    "sg:city":"Covadonga",
    "sg:orig_category":"Museos",
    "sg:phone":"+34 985 84 60 06",
    "sg:postcode":"33589",
    "sg:province":"Asturias",
    "wof:name":"Santuario De Covadonga",
    "wof:placetype":"venue"
},
  "geometry": {"coordinates":[-5.0950269699,43.3541221619],"type":"Point"}
}