{
  "type": "Feature",
  "properties": {
    "iso:country":"ES",
    "sg:address":"Calle de Camino De Velez, S/n",
    "sg:city":"Benamargosa",
    "sg:orig_category":"Frutas Y Legumbres Secas (al Por Mayor)",
    "sg:phone":"+34 952 51 72 51",
    "sg:postcode":"29718",
    "sg:province":"M\u00e1laga",
    "wof:name":"Hermanos Gutierrez C. B.",
    "wof:placetype":"venue"
},
  "geometry": {"coordinates":[-4.1923899651,36.8320770264],"type":"Point"}
}