{
  "type": "Feature",
  "properties": {
    "addr:full":"Ctra Zaragoza, Km. 0152,0 Soria Soria 42004",
    "addr:postcode":"42004",
    "addr:street":"Ctra Zaragoza Km. 0152,0",
    "iso:country":"ES",
    "sg:address":"Ctra Zaragoza, Km. 0152,0",
    "sg:city":"Soria",
    "sg:orig_category":"Albergues",
    "sg:phone":"+34 975 21 34 24",
    "sg:postcode":"42004",
    "sg:province":"Soria",
    "wof:name":"Venta Valcorba C.b.",
    "wof:placetype":"venue"
},
  "geometry": {"coordinates":[-2.4691669941,41.7646598816],"type":"Point"}
}