{
  "type": "Feature",
  "properties": {
    "iso:country":"ES",
    "sg:address":"Avgd Denia, 68",
    "sg:city":"Orba",
    "sg:orig_category":"Fotograf\u00cda Art\u00cdstica Y Retratos",
    "sg:phone":"+34 965 58 31 92",
    "sg:postcode":"03790",
    "sg:province":"Alicante",
    "wof:name":"Oliver Mas Pedro",
    "wof:placetype":"venue"
},
  "geometry": {"coordinates":[-0.0606079996,38.7821922302],"type":"Point"}
}