{
  "type": "Feature",
  "properties": {
    "iso:country":"ES",
    "sg:address":"Ctra Logro\u00d1o, S/n",
    "sg:city":"Oyon-oion",
    "sg:orig_category":"Negocio De Madera",
    "sg:phone":"+34 945 60 11 10",
    "sg:postcode":"01320",
    "sg:province":"\u00c1lava",
    "wof:name":"Ascorbe Martinez Roberto",
    "wof:placetype":"venue"
},
  "geometry": {"coordinates":[-2.4354658127,42.4951591492],"type":"Point"}
}