{
  "type": "Feature",
  "properties": {
    "addr:full":"Avda Alicante, S/n Villena Alicante 03400",
    "addr:housenumber":"s / n",
    "addr:postcode":"03400",
    "addr:street":"Avda Alicante",
    "iso:country":"ES",
    "sg:address":"Avda Alicante, S/n",
    "sg:city":"Villena",
    "sg:orig_category":"Aguas (distribuci\u00d3n, Servicios)",
    "sg:phone":"+34 965 34 81 66",
    "sg:postcode":"03400",
    "sg:province":"Alicante",
    "wof:name":"Comunidad De Regantes De La Huerta Y Partidas",
    "wof:placetype":"venue"
},
  "geometry": {"coordinates":[-0.8560829759,38.6293373108],"type":"Point"}
}