{
  "type": "Feature",
  "properties": {
    "iso:country":"ES",
    "sg:address":"Bard Nuestra Se\u00d1ora Del Rosario, S/n",
    "sg:city":"Brenes",
    "sg:orig_category":"Panader\u00cdas, Panader\u00cdas",
    "sg:phone":"+34 955 65 38 92",
    "sg:postcode":"41310",
    "sg:province":"Sevilla",
    "wof:name":"Campos Olivero Inmaculada",
    "wof:placetype":"venue"
},
  "geometry": {"coordinates":[-5.873128891,37.548084259],"type":"Point"}
}