{
  "type": "Feature",
  "properties": {
    "iso:country":"ES",
    "sg:address":"Calle de San Roque, S/n",
    "sg:city":"Valdepe\u00e7as De La Sierra",
    "sg:orig_category":"Empresas De Impermeabilizaci\u00d3n",
    "sg:phone":"+34 949 85 42 71",
    "sg:postcode":"19184",
    "sg:province":"Guadalajara",
    "wof:name":"Fibrasierra S.l.",
    "wof:placetype":"venue"
},
  "geometry": {"coordinates":[-3.3869190216,40.9076881409],"type":"Point"}
}