{
  "type": "Feature",
  "properties": {
    "iso:country":"ES",
    "sg:address":"Calle de Ca\u00d1o (el), S/n",
    "sg:city":"San Pedro De Valderaduey",
    "sg:orig_category":"Centros De Educaci\u00d3n Especial",
    "sg:phone":"+34 987 78 72 61",
    "sg:postcode":"24328",
    "sg:province":"Le\u00f3n",
    "wof:name":"Ayuntamiento De Cea",
    "wof:placetype":"venue"
},
  "geometry": {"coordinates":[-4.9730811119,42.4656181335],"type":"Point"}
}