{
  "type": "Feature",
  "properties": {
    "addr:full":"Camino Viejo Simancas, S/n Valladolid Valladolid 47008",
    "addr:housenumber":"s / n",
    "addr:postcode":"47008",
    "addr:street":"Camino Viejo Simancas",
    "iso:country":"ES",
    "sg:address":"Camino Viejo Simancas, S/n",
    "sg:city":"Valladolid",
    "sg:orig_category":"Ropa Para Ni\u00d1os (al Por Menor)",
    "sg:phone":"+34 983 23 58 92",
    "sg:postcode":"47008",
    "sg:province":"Valladolid",
    "sg:website":"www.charanga.es",
    "wof:name":"Milla Med S.a.",
    "wof:placetype":"venue"
},
  "geometry": {"coordinates":[-4.7458910942,41.6271781921],"type":"Point"}
}