{
  "type": "Feature",
  "properties": {
    "iso:country":"ES",
    "sg:address":"Calle de Padre Manjon, 20",
    "sg:city":"Valladolid",
    "sg:orig_category":"Papeler\u00cdas: Art\u00cdculos (al Por Mayor)",
    "sg:phone":"+34 983 47 67 19",
    "sg:postcode":"47012",
    "sg:province":"Valladolid",
    "wof:name":"Papeleria Urbana 24 S.l.l.",
    "wof:placetype":"venue"
},
  "geometry": {"coordinates":[-4.7184019089,41.6406364441],"type":"Point"}
}