{
  "type": "Feature",
  "properties": {
    "addr:full":"Camino De Caba\u00f1era, S/n Pe\u00f1aflor Zaragoza 50193",
    "addr:housenumber":"s",
    "addr:postcode":"50193",
    "addr:street":"Camino De Caban\u0303Era;/ N Pen\u0303Aflor",
    "iso:country":"ES",
    "sg:address":"Camino De Caba\u00f1era, S/n",
    "sg:city":"Pe\u00f1aflor",
    "sg:orig_category":"Poller\u00cda Y Caza (al Por Menor)",
    "sg:phone":"+34 976 15 41 36",
    "sg:postcode":"50193",
    "sg:province":"Zaragoza",
    "wof:name":"Avicola Cresna S.l.",
    "wof:placetype":"venue"
},
  "geometry": {"coordinates":[-0.7979719043,41.760433197],"type":"Point"}
}