{
  "type": "Feature",
  "properties": {
    "addr:full":"Calle de Nu\u00d1ez De La Pe\u00d1a, 3 San Cristobal De La Laguna Santa Cruz De Tenerife 38201",
    "addr:housenumber":"3",
    "addr:postcode":"38201",
    "addr:street":"Calle De Nun\u0303Ez De La Pen\u0303A",
    "iso:country":"ES",
    "sg:address":"Calle de Nu\u00d1ez De La Pe\u00d1a, 3",
    "sg:city":"San Cristobal De La Laguna",
    "sg:orig_category":"Centros Comerciales Y Grandes Tiendas",
    "sg:phone":"+34 922 25 25 04",
    "sg:postcode":"38201",
    "sg:province":"Santa Cruz De Tenerife",
    "wof:name":"Delgado Gomez Maria Cristina",
    "wof:placetype":"venue"
},
  "geometry": {"coordinates":[-16.317358017,28.4899673462],"type":"Point"}
}