{
  "type": "Feature",
  "properties": {
    "iso:country":"ES",
    "sg:address":"Calle de Carreteria, 17",
    "sg:city":"Almagro",
    "sg:orig_category":"Inmobiliaria (agencias)",
    "sg:phone":"+34 926 26 12 82",
    "sg:postcode":"13270",
    "sg:province":"Ciudad Real",
    "wof:name":"Aranda Ruiz Martin",
    "wof:placetype":"venue"
},
  "geometry": {"coordinates":[-3.7158041,38.8875312805],"type":"Point"}
}