{
  "type": "Feature",
  "properties": {
    "iso:country":"ES",
    "sg:address":"Calle de Zalagarda, 7",
    "sg:city":"Cabanillas Campo",
    "sg:orig_category":"Asistencia Social",
    "sg:phone":"+34 949 32 40 31",
    "sg:postcode":"19171",
    "sg:province":"Guadalajara",
    "wof:name":"Casa Tutelada Las Jaras",
    "wof:placetype":"venue"
},
  "geometry": {"coordinates":[-3.2357079983,40.6405677795],"type":"Point"}
}