{
  "type": "Feature",
  "properties": {
    "addr:full":"Calle de Virgen Almudena, 3 Pagan Murcia 30740",
    "addr:housenumber":"3",
    "addr:postcode":"30740",
    "addr:street":"Calle De Virgen Almudena",
    "iso:country":"ES",
    "sg:address":"Calle de Virgen Almudena, 3",
    "sg:city":"Pagan",
    "sg:orig_category":"Inmobiliaria (agencias)",
    "sg:phone":"+34 968 18 81 46",
    "sg:postcode":"30740",
    "sg:province":"Murcia",
    "wof:name":"Robles Marin Maria",
    "wof:placetype":"venue"
},
  "geometry": {"coordinates":[-0.7906730175,37.8155937195],"type":"Point"}
}