{
  "type": "Feature",
  "properties": {
    "addr:full":"Ctra Madrid-toledo, Km. 0012,5 Getafe Madrid 28905",
    "addr:postcode":"28905",
    "addr:street":"Ctra Madrid-Toledo Km. 0012,5",
    "iso:country":"ES",
    "sg:address":"Ctra Madrid-toledo, Km. 0012,5",
    "sg:city":"Getafe",
    "sg:orig_category":"Bancos",
    "sg:phone":"+34 916 01 94 29",
    "sg:postcode":"28905",
    "sg:province":"Madrid",
    "wof:name":"Banco Popular Espa\u00f1ol S.a.",
    "wof:placetype":"venue"
},
  "geometry": {"coordinates":[-3.7310590744,40.3048782349],"type":"Point"}
}