{
  "type": "Feature",
  "properties": {
    "iso:country":"ES",
    "sg:address":"Calle de San Fructuoso, 3",
    "sg:city":"Alcala Henares",
    "sg:orig_category":"Farmacias",
    "sg:phone":"+34 918 88 32 75",
    "sg:postcode":"28802",
    "sg:province":"Madrid",
    "wof:name":"Molina Castro Consuelo",
    "wof:placetype":"venue"
},
  "geometry": {"coordinates":[-3.3768861294,40.4764595032],"type":"Point"}
}