{
  "type": "Feature",
  "properties": {
    "addr:full":"Calle de Gran Via, 62 Madrid Madrid 28013",
    "addr:housenumber":"62",
    "addr:postcode":"madrid;28013",
    "addr:street":"Calle De Gran Via",
    "iso:country":"ES",
    "sg:address":"Calle de Gran Via, 62",
    "sg:city":"Madrid",
    "sg:orig_category":"Edici\u00d3n De Diarios, Revistas, Boletines",
    "sg:phone":"+34 915 47 07 10",
    "sg:postcode":"28013",
    "sg:province":"Madrid",
    "sg:website":"www.curtediciones.com",
    "wof:name":"Curt Ediciones S.a.",
    "wof:placetype":"venue"
},
  "geometry": {"coordinates":[-3.7084589005,40.4220275879],"type":"Point"}
}