{
  "type": "Feature",
  "properties": {
    "addr:full":"F. Gorriti, 20 Iru\u00f1a Navarra 31004",
    "addr:housenumber":"20",
    "addr:postcode":"31004",
    "addr:street":"F. Gorriti",
    "iso:country":"ES",
    "sg:address":"F. Gorriti, 20",
    "sg:city":"Iru\u00f1a",
    "sg:orig_category":"Fabricaci\u00d3n, Venta De Cuadros, Accesorios Para Enmarcar",
    "sg:phone":"+34 948 24 50 15",
    "sg:postcode":"31004",
    "sg:province":"Navarra",
    "wof:name":"Iparraguirre Martija Maria Concepcion",
    "wof:placetype":"venue"
},
  "geometry": {"coordinates":[-1.6363389492,42.8117790222],"type":"Point"}
}