{
  "type": "Feature",
  "properties": {
    "addr:full":"Pleamar, S/n Torrevieja Alicante 03180",
    "addr:housenumber":"s / n",
    "addr:postcode":"03180",
    "addr:street":"Pleamar",
    "iso:country":"ES",
    "sg:address":"Pleamar, S/n",
    "sg:city":"Torrevieja",
    "sg:orig_category":"Promotores Constructores",
    "sg:phone":"+34 965 70 88 42",
    "sg:postcode":"03180",
    "sg:province":"Alicante",
    "wof:name":"Se\u00f1orio De Punta Prima S.a.",
    "wof:placetype":"venue"
},
  "geometry": {"coordinates":[-0.7098339796,37.9481506348],"type":"Point"}
}