{
  "type": "Feature",
  "properties": {
    "addr:full":"Carrer de Biblioteca, 21 Pineda Mar Barcelona 08397",
    "addr:housenumber":"21",
    "addr:postcode":"08397",
    "addr:street":"Carrer De Biblioteca;Barcelona",
    "iso:country":"ES",
    "sg:address":"Carrer de Biblioteca, 21",
    "sg:city":"Pineda Mar",
    "sg:orig_category":"Tapicer\u00cdas",
    "sg:phone":"+34 937 67 17 60",
    "sg:postcode":"08397",
    "sg:province":"Barcelona",
    "wof:name":"Velasco Ramiro Pedro",
    "wof:placetype":"venue"
},
  "geometry": {"coordinates":[2.6903469563,41.6250267029],"type":"Point"}
}