{
  "type": "Feature",
  "properties": {
    "iso:country":"ES",
    "sg:address":"Calle de Maximo Parra, 2",
    "sg:city":"Almansa",
    "sg:orig_category":"Zapatos: Material, Suministros, Accesorios (fabricaci\u00d3n, Al Por Mayor)",
    "sg:phone":"+34 967 34 27 06",
    "sg:postcode":"02640",
    "sg:province":"Albacete",
    "wof:name":"Calzados Toval S.l.",
    "wof:placetype":"venue"
},
  "geometry": {"coordinates":[-1.1036189795,38.8773002625],"type":"Point"}
}