{
  "type": "Feature",
  "properties": {
    "addr:full":"Carrer de Pare Rodes, 18 Barcelona Barcelona 08042",
    "addr:housenumber":"18",
    "addr:postcode":"08042",
    "addr:street":"Carrer De Pare Rodes",
    "iso:country":"ES",
    "sg:address":"Carrer de Pare Rodes, 18",
    "sg:city":"Barcelona",
    "sg:orig_category":"Transporte En General",
    "sg:phone":"+34 933 59 60 80",
    "sg:postcode":"08042",
    "sg:province":"Barcelona",
    "wof:name":"Almuni Vallejo Alberto",
    "wof:placetype":"venue"
},
  "geometry": {"coordinates":[2.1749908924,41.4402198792],"type":"Point"}
}