{
  "type": "Feature",
  "properties": {
    "iso:country":"ES",
    "sg:address":"Av Pais Valencia, 27",
    "sg:city":"Alcoi",
    "sg:orig_category":"Abogados",
    "sg:phone":"+34 965 54 05 79",
    "sg:postcode":"03801",
    "sg:province":"Alicante",
    "wof:name":"Gimeno Perez De Leon Francisco Javier",
    "wof:placetype":"venue"
},
  "geometry": {"coordinates":[-0.476752013,38.6962776184],"type":"Point"}
}