{
  "type": "Feature",
  "properties": {
    "iso:country":"ES",
    "sg:address":"Calle de Barberan Y Collar, 5",
    "sg:city":"Onil",
    "sg:orig_category":"Promotores Constructores",
    "sg:phone":"+34 966 55 70 10",
    "sg:postcode":"03430",
    "sg:province":"Alicante",
    "wof:name":"Torgi S.l.",
    "wof:placetype":"venue"
},
  "geometry": {"coordinates":[-0.672894001,38.6304893494],"type":"Point"}
}