{
  "type": "Feature",
  "properties": {
    "addr:full":"Avda Bartolome Esteban, 38 Alca\u00f1iz Teruel 44600",
    "addr:housenumber":"38",
    "addr:postcode":"44600",
    "addr:street":"Avda Bartolome Esteban",
    "iso:country":"ES",
    "sg:address":"Avda Bartolome Esteban, 38",
    "sg:city":"Alca\u00f1iz",
    "sg:orig_category":"Contenedores (mercanc\u00cdas)",
    "sg:phone":"+34 978 87 09 16",
    "sg:postcode":"44600",
    "sg:province":"Teruel",
    "wof:name":"Transportes Serrano Del Mar De Las Matas S.l",
    "wof:placetype":"venue"
},
  "geometry": {"coordinates":[-0.1425600052,41.0560646057],"type":"Point"}
}