{
  "type": "Feature",
  "properties": {
    "addr:full":"Calle de De Los Herreros, 50 Benavente Zamora 49600",
    "addr:housenumber":"50",
    "addr:postcode":"49600",
    "addr:street":"Calle De De Los Herreros",
    "iso:country":"ES",
    "sg:address":"Calle de De Los Herreros, 50",
    "sg:city":"Benavente",
    "sg:orig_category":"Telas Para Tapizar, Cortinas, Pasamaner\u00cda (fabricaci\u00d3n, Al Por Mayor)",
    "sg:phone":"+34 980 63 70 69",
    "sg:postcode":"49600",
    "sg:province":"Zamora",
    "wof:name":"Bueno Escobar Azucena",
    "wof:placetype":"venue"
},
  "geometry": {"coordinates":[-5.6782112122,42.0038146973],"type":"Point"}
}