{
  "type": "Feature",
  "properties": {
    "iso:country":"ES",
    "sg:address":"Los Llanillos, S/n",
    "sg:city":"Carrizal",
    "sg:orig_category":"El Hogar: Amueblado, Acondicionamiento, Decoraci\u00d3n Y Mantenimiento",
    "sg:phone":"+34 928 73 40 02",
    "sg:postcode":"35240",
    "sg:province":"Las Palmas",
    "sg:website":"www.honoriodavila.com",
    "wof:name":"Honorio Davila S.l.",
    "wof:placetype":"venue"
},
  "geometry": {"coordinates":[-15.4050254822,27.9261436462],"type":"Point"}
}