{
  "type": "Feature",
  "properties": {
    "iso:country":"ES",
    "sg:address":"Avda Doctor Corachan, 11",
    "sg:city":"Chiva",
    "sg:orig_category":"Aceites Y Grasas Alimentarias (fabricaci\u00d3n, Al Por Mayor)",
    "sg:phone":"+34 962 52 26 12",
    "sg:postcode":"46370",
    "sg:province":"Valencia",
    "wof:name":"Cooperativa Valencina Molino Aceitero",
    "wof:placetype":"venue"
},
  "geometry": {"coordinates":[-0.7149919868,39.4719810486],"type":"Point"}
}