{
  "type": "Feature",
  "properties": {
    "iso:country":"ES",
    "sg:address":"Calle de Mayor, 11",
    "sg:city":"Almoradi",
    "sg:orig_category":"Ropa Para Se\u00d1oras (al Por Menor)",
    "sg:phone":"+34 965 70 20 14",
    "sg:postcode":"03160",
    "sg:province":"Alicante",
    "wof:name":"Arnau Ortuo Dolores",
    "wof:placetype":"venue"
},
  "geometry": {"coordinates":[-0.7928838134,38.1085510254],"type":"Point"}
}