{
  "type": "Feature",
  "properties": {
    "addr:full":"C/ Fila Navarros, 43 Alcoi Alicante 03801",
    "addr:housenumber":"43",
    "addr:postcode":"03801",
    "addr:street":"C / Fila Navarros",
    "iso:country":"ES",
    "sg:address":"C/ Fila Navarros, 43",
    "sg:city":"Alcoi",
    "sg:orig_category":"Fabricaci\u00d3n De Telas Y Sedas",
    "sg:phone":"+34 965 54 73 31",
    "sg:postcode":"03801",
    "sg:province":"Alicante",
    "wof:name":"Vanguardia Textil S.l.",
    "wof:placetype":"venue"
},
  "geometry": {"coordinates":[-0.4763970077,38.6834983826],"type":"Point"}
}