{
  "type": "Feature",
  "properties": {
    "addr:full":"Av Comunitat Valenciana, 4 Altea Alicante 03590",
    "addr:housenumber":"4",
    "addr:postcode":"03590",
    "addr:street":"Av Comunitat",
    "iso:country":"ES",
    "sg:address":"Av Comunitat Valenciana, 4",
    "sg:city":"Altea",
    "sg:orig_category":"Inmobiliaria (agencias)",
    "sg:phone":"+34 965 84 03 03",
    "sg:postcode":"03590",
    "sg:province":"Alicante",
    "wof:name":"Salvador Marti E Hijos S.l.",
    "wof:placetype":"venue"
},
  "geometry": {"coordinates":[-0.0484340005,38.60414505],"type":"Point"}
}