{
  "type": "Feature",
  "properties": {
    "addr:full":"Calle de Juan Carlos I, 2 Pe\u00e7arroya-pueblonuevo C\u00f3rdoba 14200",
    "addr:housenumber":"2",
    "addr:postcode":"14200",
    "addr:street":"Calle De Juan Carlos I;Co\u0301Rdoba",
    "iso:country":"ES",
    "sg:address":"Calle de Juan Carlos I, 2",
    "sg:city":"Pe\u00e7arroya-pueblonuevo",
    "sg:orig_category":"Ropa Para Se\u00d1oras Y Caballeros (al Por Menor)",
    "sg:phone":"+34 957 56 00 64",
    "sg:postcode":"14200",
    "sg:province":"C\u00f3rdoba",
    "wof:name":"Garcia Caballero Joaquin",
    "wof:placetype":"venue"
},
  "geometry": {"coordinates":[-5.2650279999,38.2983818054],"type":"Point"}
}