{
  "type": "Feature",
  "properties": {
    "addr:full":"Plaz Zorita, S/n Alcala Henares Madrid 28805",
    "addr:housenumber":"s / n",
    "addr:postcode":"28805",
    "iso:country":"ES",
    "sg:address":"Plaz Zorita, S/n",
    "sg:city":"Alcala Henares",
    "sg:orig_category":"Bisuter\u00cda, Joyer\u00cda, Relojer\u00cda (al Por Menor)",
    "sg:phone":"+34 918 83 11 77",
    "sg:postcode":"28805",
    "sg:province":"Madrid",
    "wof:name":"Yag\u00fce Joyeros S.l.",
    "wof:placetype":"venue"
},
  "geometry": {"coordinates":[-3.3316004276,40.5011558533],"type":"Point"}
}