{
  "type": "Feature",
  "properties": {
    "iso:country":"ES",
    "sg:address":"Rua Sor Lucia, 3",
    "sg:city":"Pontevedra",
    "sg:orig_category":"Comunidades Religiosas",
    "sg:phone":"+34 986 84 40 49",
    "sg:postcode":"36002",
    "sg:province":"Pontevedra",
    "wof:name":"Casa Del Inmaculado Corazon De Maria",
    "wof:placetype":"venue"
},
  "geometry": {"coordinates":[-8.6464252472,42.4339332581],"type":"Point"}
}