{
  "type": "Feature",
  "properties": {
    "iso:country":"ES",
    "sg:address":"Calle de Faro, 2",
    "sg:city":"Roquetas Mar",
    "sg:orig_category":"Mercer\u00cda, Lencer\u00cda (al Por Menor)",
    "sg:phone":"+34 950 32 85 27",
    "sg:postcode":"04740",
    "sg:province":"Almer\u00eda",
    "wof:name":"Gallardo Fuentes Maria Encarnacion",
    "wof:placetype":"venue"
},
  "geometry": {"coordinates":[-2.6083333492,36.7560348511],"type":"Point"}
}