{
  "type": "Feature",
  "properties": {
    "addr:full":"Carretera De Ejido-berja, Km. 0010,0 Dalias Almer\u00eda 04750",
    "addr:postcode":"04750",
    "addr:street":"Carretera De Ejido-Berja Km. 0010,0 Dalias Almeri\u0301A",
    "iso:country":"ES",
    "sg:address":"Carretera De Ejido-berja, Km. 0010,0",
    "sg:city":"Dalias",
    "sg:orig_category":"Ferreter\u00cda (diversos)",
    "sg:phone":"+34 950 49 46 71",
    "sg:postcode":"04750",
    "sg:province":"Almer\u00eda",
    "wof:name":"Dalicon S.a.",
    "wof:placetype":"venue"
},
  "geometry": {"coordinates":[-2.8728890419,36.8234138489],"type":"Point"}
}