{
  "type": "Feature",
  "properties": {
    "addr:full":"Calle de Rio Segura, S/n Ceuti Murcia 30562",
    "addr:housenumber":"s / n",
    "addr:postcode":"30562",
    "addr:street":"Calle De Rio Segura",
    "iso:country":"ES",
    "sg:address":"Calle de Rio Segura, S/n",
    "sg:city":"Ceuti",
    "sg:orig_category":"Inmobiliaria (agencias)",
    "sg:phone":"+34 968 69 48 95",
    "sg:postcode":"30562",
    "sg:province":"Murcia",
    "wof:name":"Lopez Sanchez Josefa",
    "wof:placetype":"venue"
},
  "geometry": {"coordinates":[-1.268944025,38.0857696533],"type":"Point"}
}