{
  "type": "Feature",
  "properties": {
    "iso:country":"ES",
    "sg:address":"Av Francesc Riera, 14",
    "sg:city":"Martorell",
    "sg:orig_category":"Electricidad: Instaladores",
    "sg:phone":"+34 937 75 00 57",
    "sg:postcode":"08760",
    "sg:province":"Barcelona",
    "wof:name":"Instalaciones Raser S.l.",
    "wof:placetype":"venue"
},
  "geometry": {"coordinates":[1.9133540392,41.4809112549],"type":"Point"}
}