{
  "type": "Feature",
  "properties": {
    "addr:full":"Campo De Futbol, 1 Talayuela C\u00e1ceres 10310",
    "addr:postcode":"10310",
    "addr:street":"Ca\u0301Ceres",
    "iso:country":"ES",
    "sg:address":"Campo De Futbol, 1",
    "sg:city":"Talayuela",
    "sg:orig_category":"Insecticidas, Fumigaci\u00d3n",
    "sg:phone":"+34 927 57 81 55",
    "sg:postcode":"10310",
    "sg:province":"C\u00e1ceres",
    "wof:name":"Francisco Domingo S.l.",
    "wof:placetype":"venue"
},
  "geometry": {"coordinates":[-5.610019207,39.9897003174],"type":"Point"}
}