{
  "type": "Feature",
  "properties": {
    "addr:full":"Calle de Padre Feijoo, 1 Coru\u00d1a La Coru\u00f1a 15004",
    "addr:housenumber":"1",
    "addr:postcode":"15004",
    "addr:street":"Calle De Padre Feijoo;La Corun\u0303A",
    "iso:country":"ES",
    "sg:address":"Calle de Padre Feijoo, 1",
    "sg:city":"Coru\u00d1a",
    "sg:orig_category":"Veh\u00cdculos De Ocasi\u00d3n",
    "sg:phone":"+34 981 12 60 64",
    "sg:postcode":"15004",
    "sg:province":"La Coru\u00f1a",
    "wof:name":"Auto Avion S.a.",
    "wof:placetype":"venue"
},
  "geometry": {"coordinates":[-8.4059915543,43.3648796082],"type":"Point"}
}