{
  "type": "Feature",
  "properties": {
    "addr:full":"Calle de Renueva, 23 Benavente Zamora 49600",
    "addr:housenumber":"23",
    "addr:postcode":"49600",
    "addr:street":"Calle De Renueva",
    "iso:country":"ES",
    "sg:address":"Calle de Renueva, 23",
    "sg:city":"Benavente",
    "sg:orig_category":"Asesor\u00cda De Formaci\u00d3n Y Gesti\u00d3n De Personal",
    "sg:phone":"+34 980 63 08 03",
    "sg:postcode":"49600",
    "sg:province":"Zamora",
    "wof:name":"Tejerina Fernandez Jose Luis",
    "wof:placetype":"venue"
},
  "geometry": {"coordinates":[-5.6758561134,42.0004234314],"type":"Point"}
}