{
  "type": "Feature",
  "properties": {
    "iso:country":"ES",
    "sg:address":"Calle de Constitucion (de La), 3",
    "sg:city":"Navalcarnero",
    "sg:orig_category":"Inmobiliaria (agencias)",
    "sg:phone":"+34 918 11 53 09",
    "sg:postcode":"28600",
    "sg:province":"Madrid",
    "wof:name":"Exclusivas Tegoz S.a.",
    "wof:placetype":"venue"
},
  "geometry": {"coordinates":[-3.9977469444,40.2893180847],"type":"Point"}
}