{
  "type": "Feature",
  "properties": {
    "addr:full":"Palacio De Los Ovalle, S/n Pino De Tormes Salamanca 37170",
    "addr:housenumber":"s / n",
    "addr:postcode":"37170",
    "iso:country":"ES",
    "sg:address":"Palacio De Los Ovalle, S/n",
    "sg:city":"Pino De Tormes",
    "sg:orig_category":"Cr\u00cda De Animales",
    "sg:phone":"+34 923 16 01 75",
    "sg:postcode":"37170",
    "sg:province":"Salamanca",
    "wof:name":"Hermanos Pati\u00f1o Arrospide C.b.",
    "wof:placetype":"venue"
},
  "geometry": {"coordinates":[-5.8872480392,41.025302887],"type":"Point"}
}