{
  "type": "Feature",
  "properties": {
    "iso:country":"ES",
    "sg:address":"Avda Fuente De Los Ba\u00f1os, 1",
    "sg:city":"Montanejos",
    "sg:orig_category":"Transportes Por Carretera: Lotes Completos, Mercanc\u00cdas Diversas",
    "sg:phone":"+34 964 13 10 55",
    "sg:postcode":"12448",
    "sg:province":"Castell\u00f3n",
    "wof:name":"Fajardo Lopez Juan Jose",
    "wof:placetype":"venue"
},
  "geometry": {"coordinates":[-0.5232009888,40.0683364868],"type":"Point"}
}