{
  "type": "Feature",
  "properties": {
    "iso:country":"ES",
    "sg:address":"S. Isidro, 12",
    "sg:city":"Genoves",
    "sg:orig_category":"Turismo: Lugares, Circuitos Y Curiosidades",
    "sg:phone":"+34 962 22 93 54",
    "sg:postcode":"46894",
    "sg:province":"Valencia",
    "wof:name":"Centro Excursionista De Genoves",
    "wof:placetype":"venue"
},
  "geometry": {"coordinates":[-0.4699240029,38.9900856018],"type":"Point"}
}