{
  "type": "Feature",
  "properties": {
    "addr:full":"Carrer de Progres, 47 Pineda Mar Barcelona 08397",
    "addr:housenumber":"47",
    "addr:postcode":"08397",
    "addr:street":"Carrer De Progres;Barcelona",
    "iso:country":"ES",
    "sg:address":"Carrer de Progres, 47",
    "sg:city":"Pineda Mar",
    "sg:orig_category":"Molduras, Junquillos, Listones Y Molduras Perforadas",
    "sg:phone":"+34 937 67 16 46",
    "sg:postcode":"08397",
    "sg:province":"Barcelona",
    "wof:name":"Diaz Plaza Juan",
    "wof:placetype":"venue"
},
  "geometry": {"coordinates":[2.6952860355,41.6251602173],"type":"Point"}
}