{
  "type": "Feature",
  "properties": {
    "iso:country":"ES",
    "sg:address":"Ibarra Kalea, 6",
    "sg:city":"Bergara",
    "sg:orig_category":"Acero: Productos Sider\u00dargicos Y Transformados (fabricaci\u00d3n, Negocio)",
    "sg:phone":"+34 943 76 19 40",
    "sg:postcode":"20570",
    "sg:province":"Guip\u00f9zcoa",
    "wof:name":"Aceralia Largos Perfiles Bergara S. A.",
    "wof:placetype":"venue"
},
  "geometry": {"coordinates":[-2.4232037067,43.1055755615],"type":"Point"}
}