{
  "type": "Feature",
  "properties": {
    "iso:country":"ES",
    "sg:address":"Carr Tres Creus, 3",
    "sg:city":"S. Hilari Sacalm",
    "sg:orig_category":"Patatas (al Por Mayor)",
    "sg:phone":"+34 972 86 86 05",
    "sg:postcode":"17403",
    "sg:province":"Girona",
    "wof:name":"Valls Juvanteny Joan",
    "wof:placetype":"venue"
},
  "geometry": {"coordinates":[2.5062429905,41.8811607361],"type":"Point"}
}