{
  "type": "Feature",
  "properties": {
    "iso:country":"ES",
    "sg:address":"Calle de Rio De Oro, 46",
    "sg:city":"Gijon",
    "sg:orig_category":"Art\u00cdculos De Aluminio",
    "sg:phone":"+34 985 16 43 23",
    "sg:postcode":"33209",
    "sg:province":"Asturias",
    "wof:name":"Anlisa Sl",
    "wof:placetype":"venue"
},
  "geometry": {"coordinates":[-5.663441658,43.5288467407],"type":"Point"}
}