{
  "type": "Feature",
  "properties": {
    "addr:full":"Pg Mar, De La, S/n S. Antoni Portmany Islas Baleares 07820",
    "addr:postcode":"07820",
    "addr:street":"Pg Mar De La S / N S. Antoni Portmany",
    "iso:country":"ES",
    "sg:address":"Pg Mar, De La, S/n",
    "sg:city":"S. Antoni Portmany",
    "sg:orig_category":"Barcos",
    "sg:phone":"+34 971 34 52 99",
    "sg:postcode":"07820",
    "sg:province":"Islas Baleares",
    "wof:name":"Eurolineas Maritimas S.a.l.",
    "wof:placetype":"venue"
},
  "geometry": {"coordinates":[1.5188339949,39.1094055176],"type":"Point"}
}