{
  "type": "Feature",
  "properties": {
    "addr:full":"Calle de Asociacion, 20 Almatriche Alto Las Palmas 35018",
    "addr:housenumber":"20",
    "addr:postcode":"35018",
    "addr:street":"Calle De Asociacion",
    "iso:country":"ES",
    "sg:address":"Calle de Asociacion, 20",
    "sg:city":"Almatriche Alto",
    "sg:orig_category":"Fabricaci\u00d3n, Venta, Instalaci\u00d3n De R\u00d3tulos, De R\u00d3tulos Luminosos",
    "sg:phone":"+34 928 25 20 39",
    "sg:postcode":"35018",
    "sg:province":"Las Palmas",
    "wof:name":"Luminosos & Rotulos 2000 S.l.",
    "wof:placetype":"venue"
},
  "geometry": {"coordinates":[-15.4300060272,28.1248226166],"type":"Point"}
}