{
  "type": "Feature",
  "properties": {
    "iso:country":"ES",
    "sg:address":"Calle de Paredes De Nava, 25",
    "sg:city":"Madrid",
    "sg:orig_category":"Carnicer\u00cdas, Carnicer\u00cdas",
    "sg:phone":"+34 913 06 10 39",
    "sg:postcode":"28017",
    "sg:province":"Madrid",
    "wof:name":"Mayorga Pinilla Jose Joaquin",
    "wof:placetype":"venue"
},
  "geometry": {"coordinates":[-3.627161026,40.4201393127],"type":"Point"}
}