{
  "type": "Feature",
  "properties": {
    "addr:full":"Calle de Rodriguez Chico, 1 Nava Rey Valladolid 47500",
    "addr:housenumber":"1",
    "addr:postcode":"47500",
    "addr:street":"Calle De Rodriguez Chico",
    "iso:country":"ES",
    "sg:address":"Calle de Rodriguez Chico, 1",
    "sg:city":"Nava Rey",
    "sg:orig_category":"Florister\u00cdas",
    "sg:phone":"+34 983 85 05 16",
    "sg:postcode":"47500",
    "sg:province":"Valladolid",
    "wof:name":"Carnicer Moro Jose Luis",
    "wof:placetype":"venue"
},
  "geometry": {"coordinates":[-5.0855798721,41.3315391541],"type":"Point"}
}