{
  "type": "Feature",
  "properties": {
    "addr:full":"Calle de Mirador Del Duero, 6 Zamora Zamora 49017",
    "addr:housenumber":"6",
    "addr:postcode":"49017",
    "addr:street":"Calle De Mirador Del Duero",
    "iso:country":"ES",
    "sg:address":"Calle de Mirador Del Duero, 6",
    "sg:city":"Zamora",
    "sg:orig_category":"Molduras, Junquillos, Listones Y Molduras Perforadas",
    "sg:phone":"+34 980 51 04 79",
    "sg:postcode":"49017",
    "sg:province":"Zamora",
    "wof:name":"Garcia Furones Isidro",
    "wof:placetype":"venue"
},
  "geometry": {"coordinates":[-5.7327208519,41.5045166016],"type":"Point"}
}