{
  "type": "Feature",
  "properties": {
    "addr:full":"Calle de Jacinto Verdaguer, 6 Madrid Madrid 28019",
    "addr:housenumber":"6",
    "addr:postcode":"28019",
    "addr:street":"Calle De Jacinto Verdaguer",
    "iso:country":"ES",
    "sg:address":"Calle de Jacinto Verdaguer, 6",
    "sg:city":"Madrid",
    "sg:orig_category":"Electrodom\u00c9sticos (al Por Menor)",
    "sg:phone":"+34 915 65 11 14",
    "sg:postcode":"28019",
    "sg:province":"Madrid",
    "wof:name":"Cesteros Sanchez Jose",
    "wof:placetype":"venue"
},
  "geometry": {"coordinates":[-3.7145678997,40.3962631226],"type":"Point"}
}