{
  "type": "Feature",
  "properties": {
    "addr:full":"Carrer de Deu I Mata, 14 Barcelona Barcelona 08014",
    "addr:housenumber":"14",
    "addr:postcode":"08014",
    "addr:street":"Carrer De Deu I Mata",
    "iso:country":"ES",
    "sg:address":"Carrer de Deu I Mata, 14",
    "sg:city":"Barcelona",
    "sg:orig_category":"Arquitectos",
    "sg:phone":"+34 934 39 13 14",
    "sg:postcode":"08014",
    "sg:province":"Barcelona",
    "wof:name":"Garcia Lopez Eduard",
    "wof:placetype":"venue"
},
  "geometry": {"coordinates":[2.1318390369,41.3861312866],"type":"Point"}
}