{
  "type": "Feature",
  "properties": {
    "addr:full":"Rua Nazario Abel, 51 Lugo Lugo 27004",
    "addr:housenumber":"51",
    "addr:postcode":"27004",
    "addr:street":"Rua Nazario Abel",
    "iso:country":"ES",
    "sg:address":"Rua Nazario Abel, 51",
    "sg:city":"Lugo",
    "sg:orig_category":"Empresas De Pintura Y Revestimientos",
    "sg:phone":"+34 982 21 68 25",
    "sg:postcode":"27004",
    "sg:province":"Lugo",
    "wof:name":"Cabado Pena Jesus",
    "wof:placetype":"venue"
},
  "geometry": {"coordinates":[-7.5692920685,43.0146522522],"type":"Point"}
}