{
  "type": "Feature",
  "properties": {
    "addr:full":"Pg Maritim, 1 Port D'alcudia Islas Baleares 07410",
    "addr:housenumber":"1",
    "addr:postcode":"07410",
    "addr:street":"Pg Maritim",
    "iso:country":"ES",
    "sg:address":"Pg Maritim, 1",
    "sg:city":"Port D'alcudia",
    "sg:orig_category":"Agencias Y Agentes Comerciales, Representantes",
    "sg:phone":"+34 971 54 58 97",
    "sg:postcode":"07410",
    "sg:province":"Islas Baleares",
    "wof:name":"Bisboats 2003 S.l.",
    "wof:placetype":"venue"
},
  "geometry": {"coordinates":[3.1326169968,39.841758728],"type":"Point"}
}