{
  "type": "Feature",
  "properties": {
    "addr:full":"Pl Olimpia, 14 Sabadell Barcelona 08206",
    "addr:housenumber":"14",
    "addr:postcode":"08206",
    "addr:street":"Pl Olimpia",
    "iso:country":"ES",
    "sg:address":"Pl Olimpia, 14",
    "sg:city":"Sabadell",
    "sg:orig_category":"Abogados",
    "sg:phone":"+34 937 24 04 46",
    "sg:postcode":"08206",
    "sg:province":"Barcelona",
    "wof:name":"Umbert Canals Silvia",
    "wof:placetype":"venue"
},
  "geometry": {"coordinates":[2.0908288956,41.5549430847],"type":"Point"}
}