{
  "type": "Feature",
  "properties": {
    "addr:full":"Plaz Federico Garcia Lorca, 1 Torremolinos M\u00e1laga 29620",
    "addr:housenumber":"1",
    "addr:postcode":"29620",
    "addr:street":"Plaz Federico Garcia Lorca;Ma\u0301Laga",
    "iso:country":"ES",
    "sg:address":"Plaz Federico Garcia Lorca, 1",
    "sg:city":"Torremolinos",
    "sg:orig_category":"Florister\u00cdas",
    "sg:phone":"+34 952 05 01 85",
    "sg:postcode":"29620",
    "sg:province":"M\u00e1laga",
    "wof:name":"Martinez Marti Alicia",
    "wof:placetype":"venue"
},
  "geometry": {"coordinates":[-4.5147438049,36.6066474915],"type":"Point"}
}