{
  "type": "Feature",
  "properties": {
    "iso:country":"ES",
    "sg:address":"Calle de Jose Del Toro, 10",
    "sg:city":"Cadiz",
    "sg:orig_category":"Zapatos (al Por Menor)",
    "sg:phone":"+34 956 22 03 00",
    "sg:postcode":"11004",
    "sg:province":"C\u00e1diz",
    "wof:name":"Daniela S.l.",
    "wof:placetype":"venue"
},
  "geometry": {"coordinates":[-6.2960882187,36.532787323],"type":"Point"}
}