{
  "type": "Feature",
  "properties": {
    "iso:country":"ES",
    "sg:address":"Calle de Angel Rendueles, 1",
    "sg:city":"Candas",
    "sg:orig_category":"Ense\u00d1anza: Profesiones Art\u00cdsticas",
    "sg:phone":"+34 985 87 13 76",
    "sg:postcode":"33430",
    "sg:province":"Asturias",
    "wof:name":"Destellos Fotografia S.l.",
    "wof:placetype":"venue"
},
  "geometry": {"coordinates":[-5.7652521133,43.5895576477],"type":"Point"}
}