{
  "type": "Feature",
  "properties": {
    "iso:country":"ES",
    "sg:address":"Pla\u00c7 Peixateria, 17",
    "sg:city":"Vilanova I La Geltru",
    "sg:orig_category":"Ense\u00d1anza: Comercio, Gesti\u00d3n, Inform\u00c1tica",
    "sg:phone":"+34 938 14 07 90",
    "sg:postcode":"08800",
    "sg:province":"Barcelona",
    "wof:name":"Sede\u00f1o Medina Francisco",
    "wof:placetype":"venue"
},
  "geometry": {"coordinates":[1.7269899845,41.226474762],"type":"Point"}
}