{
  "type": "Feature",
  "properties": {
    "addr:full":"Carrer de Bullidors, 7 Balco Barcelona 08211",
    "addr:housenumber":"7",
    "addr:postcode":"08211",
    "addr:street":"Carrer De Bullidors;Barcelona",
    "iso:country":"ES",
    "sg:address":"Carrer de Bullidors, 7",
    "sg:city":"Balco",
    "sg:orig_category":"Empresas De Pintura Y Revestimientos",
    "sg:phone":"+34 937 14 77 68",
    "sg:postcode":"08211",
    "sg:province":"Barcelona",
    "wof:name":"Acabados Bielsa S.l.",
    "wof:placetype":"venue"
},
  "geometry": {"coordinates":[2.073429,41.638664],"type":"Point"}
}