{
  "type": "Feature",
  "properties": {
    "addr:full":"Benjamin De Tudela, 27 Iru\u00f1a Navarra 31008",
    "addr:housenumber":"27",
    "addr:postcode":"31008",
    "addr:street":"Irun\u0303A Navarra",
    "iso:country":"ES",
    "sg:address":"Benjamin De Tudela, 27",
    "sg:city":"Iru\u00f1a",
    "sg:orig_category":"Electrodom\u00c9sticos (al Por Menor)",
    "sg:phone":"+34 948 19 71 01",
    "sg:postcode":"31008",
    "sg:province":"Navarra",
    "wof:name":"Elektra S.a.",
    "wof:placetype":"venue"
},
  "geometry": {"coordinates":[-1.6742949486,42.8089637756],"type":"Point"}
}