{
  "type": "Feature",
  "properties": {
    "addr:full":"Calle de Sanchez Vera, 9 Cuenca Cuenca 16002",
    "addr:housenumber":"9",
    "addr:postcode":"16002",
    "addr:street":"Calle De Sanchez Vera",
    "iso:country":"ES",
    "sg:address":"Calle de Sanchez Vera, 9",
    "sg:city":"Cuenca",
    "sg:orig_category":"Ense\u00d1anza Variada",
    "sg:phone":"+34 969 21 45 74",
    "sg:postcode":"16002",
    "sg:province":"Cuenca",
    "wof:name":"Huerta Galvez Antonio",
    "wof:placetype":"venue"
},
  "geometry": {"coordinates":[-2.1378350258,40.0728340149],"type":"Point"}
}