{
  "type": "Feature",
  "properties": {
    "iso:country":"ES",
    "sg:address":"Carr Arquebisbe Polou, 7",
    "sg:city":"Gandia",
    "sg:orig_category":"Producci\u00d3n, Distribuci\u00d3n De Electricidad",
    "sg:phone":"+34 962 87 17 72",
    "sg:postcode":"46700",
    "sg:province":"Valencia",
    "wof:name":"Sendra Berto Francisco Jose",
    "wof:placetype":"venue"
},
  "geometry": {"coordinates":[-0.1913339943,38.960735321],"type":"Point"}
}