{
  "type": "Feature",
  "properties": {
    "iso:country":"ES",
    "sg:address":"Tudela-mojados, S/n",
    "sg:city":"Aldeamayor S. Martin",
    "sg:orig_category":"Controles De Edificaci\u00d3n (construcci\u00d3n, Seguridad)",
    "sg:phone":"+34 983 48 00 77",
    "sg:postcode":"47162",
    "sg:province":"Valladolid",
    "wof:name":"Fadesa Inmobiliaria S.a.",
    "wof:placetype":"venue"
},
  "geometry": {"coordinates":[-4.6361689568,41.515625],"type":"Point"}
}