{
  "type": "Feature",
  "properties": {
    "addr:full":"Carrer de Guifre El Pelos, 27 Viladecans Barcelona 08840",
    "addr:housenumber":"27",
    "addr:postcode":"08840",
    "addr:street":"Carrer De Guifre El Pelos",
    "iso:country":"ES",
    "sg:address":"Carrer de Guifre El Pelos, 27",
    "sg:city":"Viladecans",
    "sg:orig_category":"Tiendas De Grano, Frutas Y Legumbres Secas (al Por Menor)",
    "sg:phone":"+34 936 58 04 81",
    "sg:postcode":"08840",
    "sg:province":"Barcelona",
    "wof:name":"Caro Velez Gaspar",
    "wof:placetype":"venue"
},
  "geometry": {"coordinates":[2.0251049995,41.3168983459],"type":"Point"}
}