{
  "type": "Feature",
  "properties": {
    "iso:country":"ES",
    "sg:address":"Calle de Gabriel Y Galan, 2",
    "sg:city":"Talayuela",
    "sg:orig_category":"Peluquer\u00cdas, Peluquer\u00cda Mixta",
    "sg:phone":"+34 927 55 15 33",
    "sg:postcode":"10310",
    "sg:province":"C\u00e1ceres",
    "wof:name":"Lopez Garcia Elsa",
    "wof:placetype":"venue"
},
  "geometry": {"coordinates":[-5.610019207,39.9897003174],"type":"Point"}
}