{
  "type": "Feature",
  "properties": {
    "iso:country":"ES",
    "sg:address":"Carrer de Rector Joanico, 78",
    "sg:city":"S. Andreu Barca",
    "sg:orig_category":"Agencias De Trabajo Temporal",
    "sg:phone":"+34 936 35 66 66",
    "sg:postcode":"08740",
    "sg:province":"Barcelona",
    "sg:website":"www.gruponorte.com",
    "wof:name":"Forsel S.a.",
    "wof:placetype":"venue"
},
  "geometry": {"coordinates":[1.9798500538,41.444568634],"type":"Point"}
}