{
  "type": "Feature",
  "properties": {
    "iso:country":"ES",
    "sg:address":"Plaz Constitucion, S/n",
    "sg:city":"Dos Hermanas",
    "sg:orig_category":"Inversiones",
    "sg:phone":"+34 955 67 58 37",
    "sg:postcode":"41700",
    "sg:province":"Sevilla",
    "wof:name":"Uniko Centro Inmobiliario S.l.",
    "wof:placetype":"venue"
},
  "geometry": {"coordinates":[-5.9281339645,37.2829055786],"type":"Point"}
}