{
  "type": "Feature",
  "properties": {
    "iso:country":"ES",
    "sg:address":"Trva San Juan, 1",
    "sg:city":"Obanos",
    "sg:orig_category":"Centros De Educaci\u00d3n Especial",
    "sg:phone":"+34 948 34 46 40",
    "sg:postcode":"31151",
    "sg:province":"Navarra",
    "wof:name":"Ayuntamiento De Obanos",
    "wof:placetype":"venue"
},
  "geometry": {"coordinates":[-1.7843362093,42.6813316345],"type":"Point"}
}