{
  "type": "Feature",
  "properties": {
    "iso:country":"ES",
    "sg:address":"Calle de Gaztambide, 26",
    "sg:city":"Madrid",
    "sg:orig_category":"Masajistas Kinesiterapeutas",
    "sg:phone":"+34 915 49 05 36",
    "sg:postcode":"28015",
    "sg:province":"Madrid",
    "wof:name":"Lopez Garcia Maria Rosario",
    "wof:placetype":"venue"
},
  "geometry": {"coordinates":[-3.7155070305,40.4339370728],"type":"Point"}
}