{
  "type": "Feature",
  "properties": {
    "iso:country":"ES",
    "sg:address":"Calle de Barriada Del Santo, 1",
    "sg:city":"Bargas",
    "sg:orig_category":"Asilos De Ancianos. Centros Privados",
    "sg:phone":"+34 925 49 31 43",
    "sg:postcode":"45593",
    "sg:province":"Toledo",
    "wof:name":"Casilfer S.l.",
    "wof:placetype":"venue"
},
  "geometry": {"coordinates":[-4.0190382004,39.9421081543],"type":"Point"}
}