{
  "type": "Feature",
  "properties": {
    "iso:country":"ES",
    "sg:address":"Calle de Vallehermoso, 75",
    "sg:city":"Madrid",
    "sg:orig_category":"Laboratorios Dentales",
    "sg:phone":"+34 915 33 52 71",
    "sg:postcode":"28015",
    "sg:province":"Madrid",
    "wof:name":"Del Castillo Rebollo Ceferino",
    "wof:placetype":"venue"
},
  "geometry": {"coordinates":[-3.7084839344,40.438369751],"type":"Point"}
}