{
  "type": "Feature",
  "properties": {
    "addr:full":"Pol Ind El Oliveral, 10 P. I. El Oliveral Valencia 46190",
    "addr:housenumber":"10",
    "addr:postcode":"46190",
    "addr:street":"Oliveral;I. El Oliveral",
    "iso:country":"ES",
    "sg:address":"Pol Ind El Oliveral, 10",
    "sg:city":"P. I. El Oliveral",
    "sg:orig_category":"Inform\u00c1tica: Mantenimiento Y Reparaci\u00d3n De Ordenadores",
    "sg:phone":"+34 961 66 51 25",
    "sg:postcode":"46190",
    "sg:province":"Valencia",
    "wof:name":"Poas Mantenimiento, S.l.",
    "wof:placetype":"venue"
},
  "geometry": {"coordinates":[-0.5698940158,39.5458450317],"type":"Point"}
}