{
  "type": "Feature",
  "properties": {
    "iso:country":"ES",
    "sg:address":"Carr Sant Llatzer, 48",
    "sg:city":"Figueres",
    "sg:orig_category":"Florister\u00cdas",
    "sg:phone":"+34 972 50 62 31",
    "sg:postcode":"17600",
    "sg:province":"Girona",
    "wof:name":"Moreno Martin Rosa Alejandra",
    "wof:placetype":"venue"
},
  "geometry": {"coordinates":[2.9662759304,42.2649459839],"type":"Point"}
}