{
  "type": "Feature",
  "properties": {
    "addr:full":"Avda Juan Carlos I, 17 Zaragoza Zaragoza 50009",
    "addr:housenumber":"17",
    "addr:postcode":"50009",
    "addr:street":"Avda Juan Carlos I",
    "iso:country":"ES",
    "sg:address":"Avda Juan Carlos I, 17",
    "sg:city":"Zaragoza",
    "sg:orig_category":"M\u00c9dicos: Cirug\u00cda Cardiovascular Y Tor\u00c1cica",
    "sg:phone":"+34 976 55 82 31",
    "sg:postcode":"50009",
    "sg:province":"Zaragoza",
    "wof:name":"Ibarra Pelaez Fernando",
    "wof:placetype":"venue"
},
  "geometry": {"coordinates":[-0.909258008,41.6416168213],"type":"Point"}
}