{
  "type": "Feature",
  "properties": {
    "iso:country":"ES",
    "sg:address":"Calle de Julio Palacios, 17",
    "sg:city":"Madrid",
    "sg:orig_category":"Abogados",
    "sg:phone":"+34 913 14 47 94",
    "sg:postcode":"28029",
    "sg:province":"Madrid",
    "wof:name":"Abello Herrero Maria Jose",
    "wof:placetype":"venue"
},
  "geometry": {"coordinates":[-3.695059,40.482712],"type":"Point"}
}