{
  "type": "Feature",
  "properties": {
    "addr:full":"Calle de Hamarretxeta, 20 Pasai Antxo Guip\u00f9zcoa 20110",
    "addr:housenumber":"20",
    "addr:postcode":"20110",
    "addr:street":"Calle De Hamarretxeta;Guipu\u0300Zcoa",
    "iso:country":"ES",
    "sg:address":"Calle de Hamarretxeta, 20",
    "sg:city":"Pasai Antxo",
    "sg:orig_category":"Molduras, Junquillos, Listones Y Molduras Perforadas",
    "sg:phone":"+34 943 51 07 50",
    "sg:postcode":"20110",
    "sg:province":"Guip\u00f9zcoa",
    "wof:name":"Teciruna S.l.",
    "wof:placetype":"venue"
},
  "geometry": {"coordinates":[-1.9180799723,43.3164138794],"type":"Point"}
}