{
  "type": "Feature",
  "properties": {
    "addr:full":"Trinidad De Rojas, 37 Antequera M\u00e1laga 29200",
    "addr:postcode":"29200",
    "addr:street":"Ma\u0301Laga",
    "iso:country":"ES",
    "sg:address":"Trinidad De Rojas, 37",
    "sg:city":"Antequera",
    "sg:orig_category":"Peluqueros: De Se\u00d1oras",
    "sg:phone":"+34 952 84 16 20",
    "sg:postcode":"29200",
    "sg:province":"M\u00e1laga",
    "wof:name":"Rojas Morente Miguel Angel",
    "wof:placetype":"venue"
},
  "geometry": {"coordinates":[-4.5598640442,37.0171051025],"type":"Point"}
}