{
  "type": "Feature",
  "properties": {
    "iso:country":"ES",
    "sg:address":"Avda Ernestina Otero, 40",
    "sg:city":"Redondela",
    "sg:orig_category":"Carnicer\u00cdas, Carnicer\u00cdas",
    "sg:phone":"+34 986 40 10 60",
    "sg:postcode":"36800",
    "sg:province":"Pontevedra",
    "wof:name":"Rubin Cabanelas Jose Luis",
    "wof:placetype":"venue"
},
  "geometry": {"coordinates":[-8.6096057892,42.2845191956],"type":"Point"}
}