{
  "type": "Feature",
  "properties": {
    "addr:full":"Calle de Arteagoiti Kalea, S/n Elexalde Vizcaya 48970",
    "addr:housenumber":"s / n",
    "addr:postcode":"48970",
    "addr:street":"Calle De Arteagoiti Kalea",
    "iso:country":"ES",
    "sg:address":"Calle de Arteagoiti Kalea, S/n",
    "sg:city":"Elexalde",
    "sg:orig_category":"Montaje (empresas De)",
    "sg:phone":"+34 944 40 97 03",
    "sg:postcode":"48970",
    "sg:province":"Vizcaya",
    "wof:name":"Montajes Aurki S.l.",
    "wof:placetype":"venue"
},
  "geometry": {"coordinates":[-2.8910405636,43.2250518799],"type":"Point"}
}