{
  "type": "Feature",
  "properties": {
    "addr:full":"Carrer de Rutlla (la), 17 Terrassa Barcelona 08221",
    "addr:housenumber":"17",
    "addr:postcode":"08221",
    "addr:street":"Carrer De Rutlla La",
    "iso:country":"ES",
    "sg:address":"Carrer de Rutlla (la), 17",
    "sg:city":"Terrassa",
    "sg:orig_category":"Fabricaci\u00d3n De Muebles",
    "sg:phone":"+34 937 84 09 59",
    "sg:postcode":"08221",
    "sg:province":"Barcelona",
    "wof:name":"Interiores Y Dise\u00f1o S.l.",
    "wof:placetype":"venue"
},
  "geometry": {"coordinates":[2.0118970871,41.5613327026],"type":"Point"}
}