{
  "type": "Feature",
  "properties": {
    "iso:country":"ES",
    "sg:address":"Av Guissona, 2",
    "sg:city":"Cervera",
    "sg:orig_category":"Fiesta: Art\u00cdculos De (al Por Menor)",
    "sg:phone":"+34 973 53 30 06",
    "sg:postcode":"25200",
    "sg:province":"Lleida",
    "wof:name":"Whasa S.c.p.",
    "wof:placetype":"venue"
},
  "geometry": {"coordinates":[1.2717757225,41.6751441956],"type":"Point"}
}