{
  "type": "Feature",
  "properties": {
    "addr:full":"Calle de Muro De Santa Ana, 4 Valencia Valencia 46003",
    "addr:housenumber":"4",
    "addr:postcode":"46003",
    "addr:street":"Calle De Muro De Santa Ana",
    "iso:country":"ES",
    "sg:address":"Calle de Muro De Santa Ana, 4",
    "sg:city":"Valencia",
    "sg:orig_category":"Estancos",
    "sg:phone":"+34 963 91 88 49",
    "sg:postcode":"46003",
    "sg:province":"Valencia",
    "wof:name":"Benavent Gallart Joaquin",
    "wof:placetype":"venue"
},
  "geometry": {"coordinates":[-0.3745659888,39.4785270691],"type":"Point"}
}