{
  "type": "Feature",
  "properties": {
    "addr:full":"Calle de Elche, 14 Petrer Alicante 03610",
    "addr:housenumber":"14",
    "addr:postcode":"03610",
    "addr:street":"Calle De Elche",
    "iso:country":"ES",
    "sg:address":"Calle de Elche, 14",
    "sg:city":"Petrer",
    "sg:orig_category":"Cueros Y Pieles (al Por Mayor)",
    "sg:phone":"+34 966 95 03 84",
    "sg:postcode":"03610",
    "sg:province":"Alicante",
    "wof:name":"Nepalia S.l.",
    "wof:placetype":"venue"
},
  "geometry": {"coordinates":[-0.7731289864,38.4793281555],"type":"Point"}
}