{
  "type": "Feature",
  "properties": {
    "addr:full":"Calle de Santiago, 17 Valladolid Valladolid 47001",
    "addr:housenumber":"17",
    "addr:postcode":"47001",
    "addr:street":"Calle De Santiago",
    "iso:country":"ES",
    "sg:address":"Calle de Santiago, 17",
    "sg:city":"Valladolid",
    "sg:orig_category":"Inmobiliaria (agencias)",
    "sg:phone":"+34 983 35 26 99",
    "sg:postcode":"47001",
    "sg:province":"Valladolid",
    "sg:website":"www.diursa.es",
    "wof:name":"Dise\u00f1os Urbanos S.a.",
    "wof:placetype":"venue"
},
  "geometry": {"coordinates":[-4.7287240028,41.6498336792],"type":"Point"}
}