{
  "type": "Feature",
  "properties": {
    "addr:full":"Calle de Doctor Nacher, 23 Chiva Valencia 46370",
    "addr:housenumber":"23",
    "addr:postcode":"46370",
    "addr:street":"Calle De Doctor Nacher",
    "iso:country":"ES",
    "sg:address":"Calle de Doctor Nacher, 23",
    "sg:city":"Chiva",
    "sg:orig_category":"Cajas De Ahorro",
    "sg:phone":"+34 962 52 45 03",
    "sg:postcode":"46370",
    "sg:province":"Valencia",
    "wof:name":"Caja De Ahorros Del Mediterraneo",
    "wof:placetype":"venue"
},
  "geometry": {"coordinates":[-0.7173349857,39.4715461731],"type":"Point"}
}