{
  "type": "Feature",
  "properties": {
    "addr:full":"C/ Balmes, 28 Ripollet Barcelona 08291",
    "addr:housenumber":"28",
    "addr:postcode":"08291",
    "addr:street":"C / Balmes",
    "iso:country":"ES",
    "sg:address":"C/ Balmes, 28",
    "sg:city":"Ripollet",
    "sg:orig_category":"Peluqueros: De Se\u00d1oras",
    "sg:phone":"+34 936 92 70 18",
    "sg:postcode":"08291",
    "sg:province":"Barcelona",
    "wof:name":"Lopez Garcia Silvia",
    "wof:placetype":"venue"
},
  "geometry": {"coordinates":[2.1538660526,41.4966583252],"type":"Point"}
}