{
  "type": "Feature",
  "properties": {
    "iso:country":"ES",
    "sg:address":"Calle de Doctor Esquerdo, 6",
    "sg:city":"Madrid",
    "sg:orig_category":"Diplomas Diversos",
    "sg:phone":"+34 914 01 94 93",
    "sg:postcode":"28028",
    "sg:province":"Madrid",
    "wof:name":"Surroca Carrascosa Alfredo",
    "wof:placetype":"venue"
},
  "geometry": {"coordinates":[-3.6686866283,40.4268531799],"type":"Point"}
}