{
  "type": "Feature",
  "properties": {
    "addr:full":"Rua Ricardo Santos, 12 Florida Pontevedra 36960",
    "addr:housenumber":"12",
    "addr:postcode":"36960",
    "addr:street":"Rua Ricardo Santos;Pontevedra",
    "iso:country":"ES",
    "sg:address":"Rua Ricardo Santos, 12",
    "sg:city":"Florida",
    "sg:orig_category":"Asistencia Y Seguros De Automovilistas Y Turistas",
    "sg:phone":"+34 986 69 07 83",
    "sg:postcode":"36960",
    "sg:province":"Pontevedra",
    "wof:name":"Asistencia Tombelo S.l.",
    "wof:placetype":"venue"
},
  "geometry": {"coordinates":[-8.6480531693,42.4336204529],"type":"Point"}
}