{
  "type": "Feature",
  "properties": {
    "iso:country":"ES",
    "sg:address":"Carrer de Sant Genis, 156",
    "sg:city":"Terrassa",
    "sg:orig_category":"Telas Para Tapizar, Cortinas, Pasamaner\u00cda (fabricaci\u00d3n, Al Por Mayor)",
    "sg:phone":"+34 937 31 06 49",
    "sg:postcode":"08221",
    "sg:province":"Barcelona",
    "wof:name":"Pe\u00f1a Arjona Luisa",
    "wof:placetype":"venue"
},
  "geometry": {"coordinates":[2.0172600746,41.5600318909],"type":"Point"}
}