{
  "type": "Feature",
  "properties": {
    "iso:country":"ES",
    "sg:address":"Calle de Aguetol, 7",
    "sg:city":"Madrid",
    "sg:orig_category":"Mensajer\u00cda Express, Portes Internacionales",
    "sg:phone":"+34 917 48 10 86",
    "sg:postcode":"28042",
    "sg:province":"Madrid",
    "sg:website":"www.gestair.es",
    "wof:name":"Gestair S.a.",
    "wof:placetype":"venue"
},
  "geometry": {"coordinates":[-3.5829539299,40.4702949524],"type":"Point"}
}