{
  "type": "Feature",
  "properties": {
    "iso:country":"ES",
    "sg:address":"Carrer de Pla De Balenya, 2",
    "sg:city":"Vic",
    "sg:orig_category":"M\u00c9dicos: Estomatolog\u00cda",
    "sg:phone":"+34 938 86 32 57",
    "sg:postcode":"08500",
    "sg:province":"Barcelona",
    "wof:name":"Conill Vila Joaquin",
    "wof:placetype":"venue"
},
  "geometry": {"coordinates":[2.255163908,41.9323158264],"type":"Point"}
}