{
  "type": "Feature",
  "properties": {
    "iso:country":"ES",
    "sg:address":"Rua Oliva (la), 28",
    "sg:city":"Pontevedra",
    "sg:orig_category":"Electrodom\u00c9sticos (al Por Menor)",
    "sg:phone":"+34 986 85 14 28",
    "sg:postcode":"36001",
    "sg:province":"Pontevedra",
    "wof:name":"Aldao Perandones Juan Francisco",
    "wof:placetype":"venue"
},
  "geometry": {"coordinates":[-8.6455383301,42.4297637939],"type":"Point"}
}