{
  "type": "Feature",
  "properties": {
    "addr:full":"Carrer de Galileu, 363 Terrassa Barcelona 08224",
    "addr:housenumber":"363",
    "addr:postcode":"08224",
    "addr:street":"Carrer De Galileu",
    "iso:country":"ES",
    "sg:address":"Carrer de Galileu, 363",
    "sg:city":"Terrassa",
    "sg:orig_category":"Asesor\u00cda Fiscal Y Jur\u00cddica",
    "sg:phone":"+34 937 80 55 51",
    "sg:postcode":"08224",
    "sg:province":"Barcelona",
    "wof:name":"Info Gestio Aj Assesors Sccl",
    "wof:placetype":"venue"
},
  "geometry": {"coordinates":[2.0055339336,41.5672225952],"type":"Point"}
}