{
  "type": "Feature",
  "properties": {
    "addr:full":"Calle de Eras Bajas De Pinos Puente, 4 Pinos-puente Granada 18240",
    "addr:housenumber":"4",
    "addr:postcode":"18240",
    "addr:street":"Calle De Eras Bajas De Pinos Puente",
    "iso:country":"ES",
    "sg:address":"Calle de Eras Bajas De Pinos Puente, 4",
    "sg:city":"Pinos-puente",
    "sg:orig_category":"Reposter\u00cdas",
    "sg:phone":"+34 958 45 21 50",
    "sg:postcode":"18240",
    "sg:province":"Granada",
    "wof:name":"Panaderia Montoro Lopez S.l.",
    "wof:placetype":"venue"
},
  "geometry": {"coordinates":[-3.7521839142,37.2517814636],"type":"Point"}
}