{
  "type": "Feature",
  "properties": {
    "iso:country":"ES",
    "sg:address":"Avda Salinetas (de), 10",
    "sg:city":"Petrer",
    "sg:orig_category":"Asesor\u00cda De Formaci\u00d3n Y Gesti\u00d3n De Personal",
    "sg:phone":"+34 966 95 05 58",
    "sg:postcode":"03610",
    "sg:province":"Alicante",
    "wof:name":"Roman Perez Jose Antonio",
    "wof:placetype":"venue"
},
  "geometry": {"coordinates":[-0.7710379958,38.4797134399],"type":"Point"}
}