{
  "type": "Feature",
  "properties": {
    "iso:country":"ES",
    "sg:address":"Av Hospital, 1",
    "sg:city":"S. Celoni",
    "sg:orig_category":"Cueros Y Pieles (al Por Mayor)",
    "sg:phone":"+34 938 67 02 85",
    "sg:postcode":"08470",
    "sg:province":"Barcelona",
    "wof:name":"Hercopell S.a.",
    "wof:placetype":"venue"
},
  "geometry": {"coordinates":[2.4869499207,41.6875686646],"type":"Point"}
}