{
  "type": "Feature",
  "properties": {
    "addr:full":"Barrena Kalea, 24 Eibar Guip\u00f9zcoa 20600",
    "addr:housenumber":"24",
    "addr:postcode":"20600",
    "addr:street":"Barrena Kalea;Guipu\u0300Zcoa",
    "iso:country":"ES",
    "sg:address":"Barrena Kalea, 24",
    "sg:city":"Eibar",
    "sg:orig_category":"Delegados, Agentes De Tr\u00c1nsito, Auxiliares De Transporte Internacional",
    "sg:phone":"+34 943 12 70 97",
    "sg:postcode":"20600",
    "sg:province":"Guip\u00f9zcoa",
    "wof:name":"San Miguel Garraioak S.l.",
    "wof:placetype":"venue"
},
  "geometry": {"coordinates":[-2.4561018944,43.1894950867],"type":"Point"}
}