{
  "type": "Feature",
  "properties": {
    "iso:country":"ES",
    "sg:address":"Carrer de Llull, 82",
    "sg:city":"Barcelona",
    "sg:orig_category":"Sociedades, Compa\u00d1\u00cdas Aseguradoras",
    "sg:phone":"+34 934 85 04 41",
    "sg:postcode":"08005",
    "sg:province":"Barcelona",
    "wof:name":"Poblenou Vila Olimpica S.l.",
    "wof:placetype":"venue"
},
  "geometry": {"coordinates":[2.1945810318,41.3953132629],"type":"Point"}
}