{
  "type": "Feature",
  "properties": {
    "iso:country":"ES",
    "sg:address":"Rua Doctor Casares, 122",
    "sg:city":"Monforte De Lemos",
    "sg:orig_category":"Inform\u00c1tica: Material Y Suministros",
    "sg:phone":"+34 982 41 07 39",
    "sg:postcode":"27400",
    "sg:province":"Lugo",
    "sg:website":"www.inficopylugo.com",
    "wof:name":"Infocopy Lugo C.b.",
    "wof:placetype":"venue"
},
  "geometry": {"coordinates":[-7.5172939301,42.5221710205],"type":"Point"}
}