{
  "type": "Feature",
  "properties": {
    "addr:full":"Calle de Padre Claret, 10 Palencia Palencia 34004",
    "addr:housenumber":"10",
    "addr:postcode":"34004",
    "addr:street":"Calle De Padre Claret",
    "iso:country":"ES",
    "sg:address":"Calle de Padre Claret, 10",
    "sg:city":"Palencia",
    "sg:orig_category":"Centros De Educaci\u00d3n Especial",
    "sg:phone":"+34 979 72 20 80",
    "sg:postcode":"34004",
    "sg:province":"Palencia",
    "wof:name":"Colegio Publico Padre Claret",
    "wof:placetype":"venue"
},
  "geometry": {"coordinates":[-4.5241031647,42.0065422058],"type":"Point"}
}