{
  "type": "Feature",
  "properties": {
    "addr:full":"Calle de Chabusquillo (el), 18 Cable Las Palmas 35500",
    "addr:housenumber":"18",
    "addr:postcode":"35500",
    "addr:street":"Calle De Chabusquillo El;Cable Las Palmas",
    "iso:country":"ES",
    "sg:address":"Calle de Chabusquillo (el), 18",
    "sg:city":"Cable",
    "sg:orig_category":"Farmacias",
    "sg:phone":"+34 928 81 66 20",
    "sg:postcode":"35500",
    "sg:province":"Las Palmas",
    "wof:name":"Lopez Hernandez Maria Del Carmen",
    "wof:placetype":"venue"
},
  "geometry": {"coordinates":[-13.5720329285,28.9608726501],"type":"Point"}
}