{
  "type": "Feature",
  "properties": {
    "addr:full":"Avda Constitucion, 29 Membrilla Ciudad Real 13230",
    "addr:housenumber":"29",
    "addr:postcode":"13230",
    "addr:street":"Avda Constitucion",
    "iso:country":"ES",
    "sg:address":"Avda Constitucion, 29",
    "sg:city":"Membrilla",
    "sg:orig_category":"Ropa Para Se\u00d1oras Y Caballeros (al Por Menor)",
    "sg:phone":"+34 926 63 73 12",
    "sg:postcode":"13230",
    "sg:province":"Ciudad Real",
    "wof:name":"Romero De Avila Bueno Ramon",
    "wof:placetype":"venue"
},
  "geometry": {"coordinates":[-3.3456590176,38.9756202698],"type":"Point"}
}