{
  "type": "Feature",
  "properties": {
    "addr:full":"Pg Sant Joan, 177 Barcelona Barcelona 08037",
    "addr:housenumber":"177",
    "addr:postcode":"08037",
    "addr:street":"Pg Sant Joan",
    "iso:country":"ES",
    "sg:address":"Pg Sant Joan, 177",
    "sg:city":"Barcelona",
    "sg:orig_category":"Agencias De Relaciones P\u00dablicas",
    "sg:phone":"+34 934 57 14 16",
    "sg:postcode":"08037",
    "sg:province":"Barcelona",
    "sg:website":"www.disbauja.com",
    "wof:name":"Relaciones Publicas Y Comunicacion Antse Group S.l.",
    "wof:placetype":"venue"
},
  "geometry": {"coordinates":[2.1642448902,41.4030342102],"type":"Point"}
}