{
  "type": "Feature",
  "properties": {
    "addr:full":"Carrer de Sant Antoni, 16 Mataro Barcelona 08301",
    "addr:housenumber":"16",
    "addr:postcode":"08301",
    "addr:street":"Carrer De Sant Antoni",
    "iso:country":"ES",
    "sg:address":"Carrer de Sant Antoni, 16",
    "sg:city":"Mataro",
    "sg:orig_category":"Empresarios",
    "sg:phone":"+34 937 90 34 32",
    "sg:postcode":"08301",
    "sg:province":"Barcelona",
    "wof:name":"Rabassa Martin Andres Avelino",
    "wof:placetype":"venue"
},
  "geometry": {"coordinates":[2.446297884,41.5373077393],"type":"Point"}
}