{
  "type": "Feature",
  "properties": {
    "iso:country":"ES",
    "sg:address":"Calle de Puerta De Valencia, 13",
    "sg:city":"Cuenca",
    "sg:orig_category":"Carnicer\u00cdas, Carnicer\u00cdas",
    "sg:phone":"+34 969 23 12 47",
    "sg:postcode":"16001",
    "sg:province":"Cuenca",
    "wof:name":"Moreno Mu\u00f1oz Miguel Angel",
    "wof:placetype":"venue"
},
  "geometry": {"coordinates":[-2.131747961,40.0736961365],"type":"Point"}
}