{
  "type": "Feature",
  "properties": {
    "addr:full":"Carrer de Merce Rodoreda, 5 Martorell Barcelona 08760",
    "addr:housenumber":"5",
    "addr:postcode":"08760",
    "addr:street":"Carrer De Merce Rodoreda",
    "iso:country":"ES",
    "sg:address":"Carrer de Merce Rodoreda, 5",
    "sg:city":"Martorell",
    "sg:orig_category":"Delegados, Agentes De Tr\u00c1nsito, Auxiliares De Transporte Internacional",
    "sg:phone":"+34 937 74 02 84",
    "sg:postcode":"08760",
    "sg:province":"Barcelona",
    "wof:name":"Montoro Soriano Jesus",
    "wof:placetype":"venue"
},
  "geometry": {"coordinates":[1.91652596,41.4759368896],"type":"Point"}
}