{
  "type": "Feature",
  "properties": {
    "addr:full":"Rua Diego Pazos, 7 Sarria Lugo 27600",
    "addr:housenumber":"7",
    "addr:postcode":"27600",
    "addr:street":"Rua Diego Pazos",
    "iso:country":"ES",
    "sg:address":"Rua Diego Pazos, 7",
    "sg:city":"Sarria",
    "sg:orig_category":"Ropa Y Accesorios",
    "sg:phone":"+34 982 53 50 57",
    "sg:postcode":"27600",
    "sg:province":"Lugo",
    "sg:website":"www.revitex.com",
    "wof:name":"Almacenes Revitex S.l.",
    "wof:placetype":"venue"
},
  "geometry": {"coordinates":[-7.4120845795,42.7781639099],"type":"Point"}
}