{
  "type": "Feature",
  "properties": {
    "addr:full":"Carr Marques Del Turia, 1 Silla Valencia 46460",
    "addr:housenumber":"1",
    "addr:postcode":"46460",
    "addr:street":"Carr Marques Del Turia",
    "iso:country":"ES",
    "sg:address":"Carr Marques Del Turia, 1",
    "sg:city":"Silla",
    "sg:orig_category":"Carnicer\u00cdas, Carnicer\u00cdas",
    "sg:phone":"+34 961 20 05 55",
    "sg:postcode":"46460",
    "sg:province":"Valencia",
    "wof:name":"Garcia Rodriguez Pedro",
    "wof:placetype":"venue"
},
  "geometry": {"coordinates":[-0.4104290009,39.3570785522],"type":"Point"}
}