{
  "type": "Feature",
  "properties": {
    "iso:country":"ES",
    "sg:address":"Carrer de Esglesia (l'), 16",
    "sg:city":"Terrassa",
    "sg:orig_category":"Iglesia Cat\u00d3lica",
    "sg:phone":"+34 937 33 70 95",
    "sg:postcode":"08221",
    "sg:province":"Barcelona",
    "wof:name":"Diocesi De Terrasa",
    "wof:placetype":"venue"
},
  "geometry": {"coordinates":[2.0116209984,41.5616226196],"type":"Point"}
}