{
  "type": "Feature",
  "properties": {
    "iso:country":"ES",
    "sg:address":"Ctra Luis Verde, 2",
    "sg:city":"Luis Verde",
    "sg:orig_category":"Transportes Por Carretera: Lotes Completos, Mercanc\u00cdas Diversas",
    "sg:phone":"+34 928 70 50 28",
    "sg:postcode":"35217",
    "sg:province":"Las Palmas",
    "wof:name":"Monzon Martel Francisco",
    "wof:placetype":"venue"
},
  "geometry": {"coordinates":[-15.4973392487,27.9911899567],"type":"Point"}
}