{
  "type": "Feature",
  "properties": {
    "iso:country":"ES",
    "sg:address":"C/ Major, 37",
    "sg:city":"Inca",
    "sg:orig_category":"Ropa Para Se\u00d1oras Y Caballeros (al Por Menor)",
    "sg:phone":"+34 971 88 37 18",
    "sg:postcode":"07300",
    "sg:province":"Islas Baleares",
    "sg:website":"www.adolfodominguez.com",
    "wof:name":"Gonzalez Del Rey Maria",
    "wof:placetype":"venue"
},
  "geometry": {"coordinates":[2.9104800224,39.7212791443],"type":"Point"}
}