{
  "type": "Feature",
  "properties": {
    "iso:country":"ES",
    "sg:address":"Ctra Arbucies, S/n",
    "sg:city":"Breda",
    "sg:orig_category":"Muebles, Minoristas",
    "sg:phone":"+34 972 87 08 52",
    "sg:postcode":"17400",
    "sg:province":"Girona",
    "wof:name":"Galerias Del Moble S. A.",
    "wof:placetype":"venue"
},
  "geometry": {"coordinates":[2.5595769882,41.7538490295],"type":"Point"}
}