{
  "type": "Feature",
  "properties": {
    "addr:full":"Pl Madrid, S/n Palma Islas Baleares 07011",
    "addr:housenumber":"s",
    "addr:postcode":"07011",
    "addr:street":"Pl Madrid;/ N",
    "iso:country":"ES",
    "sg:address":"Pl Madrid, S/n",
    "sg:city":"Palma",
    "sg:orig_category":"Aparcamientos (infraestructuras, Accesorios)",
    "sg:phone":"+34 971 28 92 39",
    "sg:postcode":"07011",
    "sg:province":"Islas Baleares",
    "wof:name":"Dornier S.a.",
    "wof:placetype":"venue"
},
  "geometry": {"coordinates":[2.6402380466,39.5781097412],"type":"Point"}
}