{
  "type": "Feature",
  "properties": {
    "addr:full":"Calle de A, 26 Pol. Plano-las Canales Zaragoza 50430",
    "addr:housenumber":"26",
    "addr:postcode":"50430",
    "addr:street":"Calle De A;Pol. Plano-Las Canales",
    "iso:country":"ES",
    "sg:address":"Calle de A, 26",
    "sg:city":"Pol. Plano-las Canales",
    "sg:orig_category":"Productos Qu\u00cdmicos (fabricaci\u00d3n, Al Por Mayor)",
    "sg:phone":"+34 976 12 63 67",
    "sg:postcode":"50430",
    "sg:province":"Zaragoza",
    "wof:name":"Viamonte S.a.",
    "wof:placetype":"venue"
},
  "geometry": {"coordinates":[-0.9965239763,41.5399703979],"type":"Point"}
}