{
  "type": "Feature",
  "properties": {
    "iso:country":"ES",
    "sg:address":"Calle de Badostain, 24",
    "sg:city":"Huarte O Uharte",
    "sg:orig_category":"Delegados, Agentes De Tr\u00c1nsito, Auxiliares De Transporte Internacional",
    "sg:phone":"+34 948 33 39 00",
    "sg:postcode":"31620",
    "sg:province":"Navarra",
    "wof:name":"Transportes Oberena S.c.l.",
    "wof:placetype":"venue"
},
  "geometry": {"coordinates":[-1.6050490141,42.8258056641],"type":"Point"}
}