{
  "type": "Feature",
  "properties": {
    "iso:country":"ES",
    "sg:address":"Rua Bedoya, 14",
    "sg:city":"Ourense",
    "sg:orig_category":"Ropa Para Ni\u00d1os (al Por Menor)",
    "sg:phone":"+34 988 25 56 72",
    "sg:postcode":"32004",
    "sg:province":"Ourense",
    "wof:name":"Conde Ojea Pilar",
    "wof:placetype":"venue"
},
  "geometry": {"coordinates":[-7.8613080978,42.3398513794],"type":"Point"}
}