{
  "type": "Feature",
  "properties": {
    "addr:full":"Rcial Heliopolis, 1 La Antilla Huelva 21449",
    "addr:housenumber":"1",
    "addr:postcode":"21449",
    "addr:street":"Heliopolis",
    "iso:country":"ES",
    "sg:address":"Rcial Heliopolis, 1",
    "sg:city":"La Antilla",
    "sg:orig_category":"Electricidad: Instaladores",
    "sg:phone":"+34 959 48 01 65",
    "sg:postcode":"21449",
    "sg:province":"Huelva",
    "wof:name":"Perez Leal Jose Manuel",
    "wof:placetype":"venue"
},
  "geometry": {"coordinates":[-7.2509040833,37.2072601318],"type":"Point"}
}