{
  "type": "Feature",
  "properties": {
    "addr:full":"Calle de Borrancho, 5 Soto Marina Cantabria 39110",
    "addr:housenumber":"5",
    "addr:postcode":"39110",
    "addr:street":"Calle De Borrancho",
    "iso:country":"ES",
    "sg:address":"Calle de Borrancho, 5",
    "sg:city":"Soto Marina",
    "sg:orig_category":"Fabrica De Cer\u00c1micas",
    "sg:phone":"+34 942 57 80 06",
    "sg:postcode":"39110",
    "sg:province":"Cantabria",
    "sg:website":"www.hipalip.es",
    "wof:name":"Hispano Italiana De Revestimientos S. A.",
    "wof:placetype":"venue"
},
  "geometry": {"coordinates":[-3.887897253,43.4651947021],"type":"Point"}
}