{
  "type": "Feature",
  "properties": {
    "iso:country":"ES",
    "sg:address":"Carr Felip Ii, 1",
    "sg:city":"Badalona",
    "sg:orig_category":"Frutas, Legumbres Frescas Y Tempranas (al Por Menor)",
    "sg:phone":"+34 933 87 55 94",
    "sg:postcode":"08917",
    "sg:province":"Barcelona",
    "wof:name":"Rueda Martin Estrella",
    "wof:placetype":"venue"
},
  "geometry": {"coordinates":[2.2362179756,41.4519271851],"type":"Point"}
}