{
  "type": "Feature",
  "properties": {
    "iso:country":"ES",
    "sg:address":"Carrer de Valencia, 535",
    "sg:city":"Barcelona",
    "sg:orig_category":"Asesor\u00cda Sobre Comunicaci\u00d3n De Empresas",
    "sg:phone":"+34 932 45 13 86",
    "sg:postcode":"08013",
    "sg:province":"Barcelona",
    "wof:name":"Asesores Lester S.l.",
    "wof:placetype":"venue"
},
  "geometry": {"coordinates":[2.1818323135,41.4066200256],"type":"Point"}
}