{
  "type": "Feature",
  "properties": {
    "iso:country":"ES",
    "sg:address":"Calle de Hernan Cortes, 5",
    "sg:city":"Villanueva Serena",
    "sg:orig_category":"Chapister\u00cda",
    "sg:phone":"+34 924 84 06 27",
    "sg:postcode":"06700",
    "sg:province":"Badajoz",
    "wof:name":"Gutierrez Garcia Francisco Jose",
    "wof:placetype":"venue"
},
  "geometry": {"coordinates":[-5.7927889824,38.9734992981],"type":"Point"}
}