{
  "type": "Feature",
  "properties": {
    "iso:country":"ES",
    "sg:address":"Carrer de Forn Del Raco, 1",
    "sg:city":"Palma",
    "sg:orig_category":"Centros De Coordinaci\u00d3n",
    "sg:phone":"+34 971 72 93 53",
    "sg:postcode":"07001",
    "sg:province":"Islas Baleares",
    "wof:name":"Brunet Comas Francisca",
    "wof:placetype":"venue"
},
  "geometry": {"coordinates":[2.6512019634,39.5712852478],"type":"Point"}
}