{
  "type": "Feature",
  "properties": {
    "iso:country":"ES",
    "sg:address":"Cmno Epila (miralbueno), 90",
    "sg:city":"Zaragoza",
    "sg:orig_category":"Carb\u00d3n, Carb\u00d3n De Madera (al Por Mayor)",
    "sg:phone":"+34 976 31 16 15",
    "sg:postcode":"50011",
    "sg:province":"Zaragoza",
    "wof:name":"Alvarez Alvarez Julio",
    "wof:placetype":"venue"
},
  "geometry": {"coordinates":[-1.0011901855,41.6566925049],"type":"Point"}
}