{
  "type": "Feature",
  "properties": {
    "addr:full":"Sotiello De Arriba, S/n Cenero Asturias 33393",
    "addr:housenumber":"s / n",
    "addr:postcode":"33393",
    "addr:street":"Arriba",
    "iso:country":"ES",
    "sg:address":"Sotiello De Arriba, S/n",
    "sg:city":"Cenero",
    "sg:orig_category":"Cr\u00cda De Animales",
    "sg:phone":"+34 985 16 70 64",
    "sg:postcode":"33393",
    "sg:province":"Asturias",
    "wof:name":"Menendez Hevia Ana Maria",
    "wof:placetype":"venue"
},
  "geometry": {"coordinates":[-5.7263522148,43.507850647],"type":"Point"}
}