{
  "type": "Feature",
  "properties": {
    "iso:country":"ES",
    "sg:address":"Avda Jose Fari\u00d1a, 6",
    "sg:city":"Huelva",
    "sg:orig_category":"Centros M\u00c9dicos Y Sociales, Dispensarios",
    "sg:phone":"+34 959 23 07 44",
    "sg:postcode":"21006",
    "sg:province":"Huelva",
    "wof:name":"Acu\u00f1a Vega Manuel",
    "wof:placetype":"venue"
},
  "geometry": {"coordinates":[-6.9340214729,37.2589683533],"type":"Point"}
}