{
  "type": "Feature",
  "properties": {
    "addr:full":"Calle de Padre Huesca, 54 Huesca Huesca 22002",
    "addr:housenumber":"54",
    "addr:postcode":"22002",
    "addr:street":"Calle De Padre Huesca",
    "iso:country":"ES",
    "sg:address":"Calle de Padre Huesca, 54",
    "sg:city":"Huesca",
    "sg:orig_category":"Tapicer\u00cdas",
    "sg:phone":"+34 974 24 40 95",
    "sg:postcode":"22002",
    "sg:province":"Huesca",
    "sg:website":"www.gastorsan.com",
    "wof:name":"Torrente Sanroman Angel Gaspar",
    "wof:placetype":"venue"
},
  "geometry": {"coordinates":[-0.4064083099,42.1350402832],"type":"Point"}
}