{
  "type": "Feature",
  "properties": {
    "addr:full":"Carrer de Sant Joan, 32 Ametlla Mar Tarragona 43860",
    "addr:housenumber":"32",
    "addr:postcode":"43860",
    "addr:street":"Carrer De Sant Joan",
    "iso:country":"ES",
    "sg:address":"Carrer de Sant Joan, 32",
    "sg:city":"Ametlla Mar",
    "sg:orig_category":"Carnicer\u00cdas, Carnicer\u00cdas",
    "sg:phone":"+34 977 45 68 13",
    "sg:postcode":"43860",
    "sg:province":"Tarragona",
    "wof:name":"Carns Margalef S.l.",
    "wof:placetype":"venue"
},
  "geometry": {"coordinates":[0.8030269742,40.8844032288],"type":"Point"}
}