{
  "type": "Feature",
  "properties": {
    "addr:full":"Calle de Tenerife, 101 Monta\u00e7a Roja Las Palmas 35580",
    "addr:housenumber":"101",
    "addr:postcode":"35580",
    "addr:street":"Calle De Tenerife",
    "iso:country":"ES",
    "sg:address":"Calle de Tenerife, 101",
    "sg:city":"Monta\u00e7a Roja",
    "sg:orig_category":"Bancos",
    "sg:phone":"+34 928 51 84 43",
    "sg:postcode":"35580",
    "sg:province":"Las Palmas",
    "wof:name":"Banca March S.a.",
    "wof:placetype":"venue"
},
  "geometry": {"coordinates":[-13.8307790756,28.8657550812],"type":"Point"}
}