{
  "type": "Feature",
  "properties": {
    "addr:full":"C/ Nou, 12 Banyoles Girona 17820",
    "addr:housenumber":"12",
    "addr:postcode":"17820",
    "addr:street":"C / Nou",
    "iso:country":"ES",
    "sg:address":"C/ Nou, 12",
    "sg:city":"Banyoles",
    "sg:orig_category":"Empresarios",
    "sg:phone":"+34 972 57 06 45",
    "sg:postcode":"17820",
    "sg:province":"Girona",
    "wof:name":"Constructor Y Restaurador Juan Vi\u00f1as S.l.",
    "wof:placetype":"venue"
},
  "geometry": {"coordinates":[2.767729044,42.1196708679],"type":"Point"}
}