{
  "type": "Feature",
  "properties": {
    "addr:full":"Avda Navarro Reverter, 6 Valencia Valencia 46004",
    "addr:housenumber":"6",
    "addr:postcode":"46004",
    "addr:street":"Avda Navarro Reverter",
    "iso:country":"ES",
    "sg:address":"Avda Navarro Reverter, 6",
    "sg:city":"Valencia",
    "sg:orig_category":"M\u00c9dicos: Reumatolog\u00cda",
    "sg:phone":"+34 963 34 49 37",
    "sg:postcode":"46004",
    "sg:province":"Valencia",
    "wof:name":"Corts Giner Juan Ramon",
    "wof:placetype":"venue"
},
  "geometry": {"coordinates":[-0.3673740029,39.4712486267],"type":"Point"}
}