{
  "type": "Feature",
  "properties": {
    "addr:full":"Calle de Virgen De La Soledad, 15 Badajoz Badajoz 06001",
    "addr:housenumber":"15",
    "addr:postcode":"06001",
    "addr:street":"Calle De Virgen De La Soledad",
    "iso:country":"ES",
    "sg:address":"Calle de Virgen De La Soledad, 15",
    "sg:city":"Badajoz",
    "sg:orig_category":"Quincaller\u00cda (al Por Menor)",
    "sg:phone":"+34 924 22 45 70",
    "sg:postcode":"06001",
    "sg:province":"Badajoz",
    "wof:name":"Rodriguez Rodriguez Eladio",
    "wof:placetype":"venue"
},
  "geometry": {"coordinates":[-6.9707989693,38.8796005249],"type":"Point"}
}