{
  "type": "Feature",
  "properties": {
    "iso:country":"ES",
    "sg:address":"Castillo-gazteleku, 25",
    "sg:city":"Iru\u00f1a",
    "sg:orig_category":"M\u00c9dicos: Estomatolog\u00cda",
    "sg:phone":"+34 948 22 38 88",
    "sg:postcode":"31001",
    "sg:province":"Navarra",
    "wof:name":"Sainz De Murieta Iriarte Ignacio",
    "wof:placetype":"venue"
},
  "geometry": {"coordinates":[-1.6437540054,42.81275177],"type":"Point"}
}