{
  "type": "Feature",
  "properties": {
    "addr:full":"Av Joan Carles I, 62 Gava Barcelona 08850",
    "addr:housenumber":"62",
    "addr:postcode":"08850",
    "addr:street":"Av Joan Carles I",
    "iso:country":"ES",
    "sg:address":"Av Joan Carles I, 62",
    "sg:city":"Gava",
    "sg:orig_category":"Molduras, Junquillos, Listones Y Molduras Perforadas",
    "sg:phone":"+34 936 62 64 95",
    "sg:postcode":"08850",
    "sg:province":"Barcelona",
    "wof:name":"Blasco Celma Raquel",
    "wof:placetype":"venue"
},
  "geometry": {"coordinates":[2.0009400845,41.2994499207],"type":"Point"}
}