{
  "type": "Feature",
  "properties": {
    "addr:full":"Avda Florez Estrada, 9 Grado Asturias 33820",
    "addr:housenumber":"9",
    "addr:postcode":"33820",
    "addr:street":"Avda Florez Estrada",
    "iso:country":"ES",
    "sg:address":"Avda Florez Estrada, 9",
    "sg:city":"Grado",
    "sg:orig_category":"Arreglo, Reparaci\u00d3n, Piezas Sueltas De Televisi\u00d3n, V\u00cddeo, Hi",
    "sg:phone":"+34 985 75 01 81",
    "sg:postcode":"33820",
    "sg:province":"Asturias",
    "wof:name":"Mosconia S.l.",
    "wof:placetype":"venue"
},
  "geometry": {"coordinates":[-6.0781550407,43.3856086731],"type":"Point"}
}