{
  "type": "Feature",
  "properties": {
    "iso:country":"ES",
    "sg:address":"La Cierva, S/n",
    "sg:city":"Zamora",
    "sg:orig_category":"Empresarios",
    "sg:phone":"+34 980 55 71 04",
    "sg:postcode":"49025",
    "sg:province":"Zamora",
    "sg:website":"www.intras.es",
    "wof:name":"Fundacion Intras",
    "wof:placetype":"venue"
},
  "geometry": {"coordinates":[-5.7571687698,41.5140113831],"type":"Point"}
}