{
  "type": "Feature",
  "properties": {
    "addr:full":"Calle de Jose Maria Peman, 8 Alhama Murcia Murcia 30840",
    "addr:housenumber":"8",
    "addr:postcode":"30840",
    "addr:street":"Calle De Jose Maria Peman",
    "iso:country":"ES",
    "sg:address":"Calle de Jose Maria Peman, 8",
    "sg:city":"Alhama Murcia",
    "sg:orig_category":"Formaci\u00d3n Continuada (variada)",
    "sg:phone":"+34 968 63 14 73",
    "sg:postcode":"30840",
    "sg:province":"Murcia",
    "wof:name":"Robles Mayol Antonio",
    "wof:placetype":"venue"
},
  "geometry": {"coordinates":[-1.4303929806,37.8452682495],"type":"Point"}
}