{
  "type": "Feature",
  "properties": {
    "iso:country":"ES",
    "sg:address":"Carrer de Jose Millan Gonzalez, 17",
    "sg:city":"Barcelona",
    "sg:orig_category":"Asociaciones, Organismos Culturales Y Socioeducativos",
    "sg:phone":"+34 932 85 06 19",
    "sg:postcode":"08024",
    "sg:province":"Barcelona",
    "wof:name":"Local Social Raimon Casellas",
    "wof:placetype":"venue"
},
  "geometry": {"coordinates":[2.1594219208,41.4163131714],"type":"Point"}
}