{
  "type": "Feature",
  "properties": {
    "iso:country":"ES",
    "sg:address":"Calle de Jose Hernandez Alfonso, 18",
    "sg:city":"Santa Cruz De Tenerife",
    "sg:orig_category":"Estancos",
    "sg:phone":"+34 922 22 73 68",
    "sg:postcode":"38003",
    "sg:province":"Santa Cruz De Tenerife",
    "wof:name":"Abreu Alonso Carmen Rosa",
    "wof:placetype":"venue"
},
  "geometry": {"coordinates":[-16.253162,28.461641],"type":"Point"}
}