{
  "type": "Feature",
  "properties": {
    "addr:full":"Calle de Ramon Y Cajal, 13 Mieres Asturias 33600",
    "addr:housenumber":"13",
    "addr:postcode":"33600",
    "addr:street":"Calle De Ramon Y Cajal",
    "iso:country":"ES",
    "sg:address":"Calle de Ramon Y Cajal, 13",
    "sg:city":"Mieres",
    "sg:orig_category":"Cervezas, Bebidas (al Por Mayor)",
    "sg:phone":"+34 985 46 82 70",
    "sg:postcode":"33600",
    "sg:province":"Asturias",
    "wof:name":"Mierense De Bebidas  S. Coop.",
    "wof:placetype":"venue"
},
  "geometry": {"coordinates":[-5.7731890678,43.2444152832],"type":"Point"}
}