{
  "type": "Feature",
  "properties": {
    "addr:full":"Ctra Villaverde, S/n Santa Maria Del Campo Burgos 09342",
    "addr:housenumber":"s / n",
    "addr:postcode":"09342",
    "addr:street":"Ctra Villaverde",
    "iso:country":"ES",
    "sg:address":"Ctra Villaverde, S/n",
    "sg:city":"Santa Maria Del Campo",
    "sg:orig_category":"Negocio De Materiales De Construcci\u00d3n",
    "sg:phone":"+34 947 17 40 22",
    "sg:postcode":"09342",
    "sg:province":"Burgos",
    "wof:name":"Hermoso Diez Lo Y Dos Mas S.c.",
    "wof:placetype":"venue"
},
  "geometry": {"coordinates":[-4.0275092125,42.0878486633],"type":"Point"}
}