{
  "type": "Feature",
  "properties": {
    "iso:country":"ES",
    "sg:address":"Carr Sta Joaquima Vedruna, 15",
    "sg:city":"Igualada",
    "sg:orig_category":"Prendas Y Chalecos De Punto (al Por Menor)",
    "sg:phone":"+34 938 05 25 66",
    "sg:postcode":"08700",
    "sg:province":"Barcelona",
    "wof:name":"Claramunt Vives Eduard",
    "wof:placetype":"venue"
},
  "geometry": {"coordinates":[1.6247650385,41.5775680542],"type":"Point"}
}