{
  "type": "Feature",
  "properties": {
    "iso:country":"ES",
    "sg:address":"Calle de Sant Jaume, 77",
    "sg:city":"Santa Eulalia",
    "sg:orig_category":"Ropa Para Se\u00d1oras Y Caballeros (al Por Menor)",
    "sg:phone":"+34 971 33 62 24",
    "sg:postcode":"07840",
    "sg:province":"Islas Baleares",
    "wof:name":"Prat Hernandez Jose Antonio",
    "wof:placetype":"venue"
},
  "geometry": {"coordinates":[1.5358450413,38.9859962463],"type":"Point"}
}