{
  "type": "Feature",
  "properties": {
    "addr:full":"Calle de Perez Bayer, 11 Valencia Valencia 46002",
    "addr:housenumber":"11",
    "addr:postcode":"46002",
    "addr:street":"Calle De Perez Bayer",
    "iso:country":"ES",
    "sg:address":"Calle de Perez Bayer, 11",
    "sg:city":"Valencia",
    "sg:orig_category":"M\u00c9dicos: Medicina Interna",
    "sg:phone":"+34 963 51 45 64",
    "sg:postcode":"46002",
    "sg:province":"Valencia",
    "wof:name":"Pascual-leone Pascual Alvaro",
    "wof:placetype":"venue"
},
  "geometry": {"coordinates":[-0.3713249862,39.4699554443],"type":"Point"}
}