{
  "type": "Feature",
  "properties": {
    "iso:country":"ES",
    "sg:address":"Carrer de Rocaberti, 11",
    "sg:city":"Barcelona",
    "sg:orig_category":"Locales Y Clases De Danza",
    "sg:phone":"+34 932 04 93 39",
    "sg:postcode":"08017",
    "sg:province":"Barcelona",
    "wof:name":"Garza Diaz Barriga Ligeya",
    "wof:placetype":"venue"
},
  "geometry": {"coordinates":[2.125138998,41.397064209],"type":"Point"}
}