{
  "type": "Feature",
  "properties": {
    "iso:country":"ES",
    "sg:address":"Avda Ramon Ferreiro, 3",
    "sg:city":"Lugo",
    "sg:orig_category":"M\u00c9dicos: Ginecolog\u00cda Y Obstetricia",
    "sg:phone":"+34 982 25 32 22",
    "sg:postcode":"27002",
    "sg:province":"Lugo",
    "wof:name":"Seoane Rodriguez Pablo",
    "wof:placetype":"venue"
},
  "geometry": {"coordinates":[-7.5550022125,43.0055046082],"type":"Point"}
}