{
  "type": "Feature",
  "properties": {
    "iso:country":"ES",
    "sg:address":"Carr Sant Joan (de), 3",
    "sg:city":"Albaida",
    "sg:orig_category":"Agentes Generales De Seguros",
    "sg:phone":"+34 962 39 02 03",
    "sg:postcode":"46860",
    "sg:province":"Valencia",
    "wof:name":"Albert Giner Fernando",
    "wof:placetype":"venue"
},
  "geometry": {"coordinates":[-0.5186526179,38.8404197693],"type":"Point"}
}