{
  "type": "Feature",
  "properties": {
    "addr:full":"Calle de Lauaxeta Olerkari, 37 Mungia Vizcaya 48100",
    "addr:housenumber":"37",
    "addr:postcode":"48100",
    "addr:street":"Calle De Lauaxeta Olerkari",
    "iso:country":"ES",
    "sg:address":"Calle de Lauaxeta Olerkari, 37",
    "sg:city":"Mungia",
    "sg:orig_category":"T\u00c9cnicos Veterinarios",
    "sg:phone":"+34 946 74 09 86",
    "sg:postcode":"48100",
    "sg:province":"Vizcaya",
    "wof:name":"Irade Isasi Ibargaray Y Gustavo Mu\u00f1oz S.c.",
    "wof:placetype":"venue"
},
  "geometry": {"coordinates":[-2.8512589931,43.3572273254],"type":"Point"}
}