{
  "type": "Feature",
  "properties": {
    "addr:full":"Carrer de Mossen Marti, 2 Valls Tarragona 43800",
    "addr:housenumber":"2",
    "addr:postcode":"43800",
    "addr:street":"Carrer De Mossen Marti",
    "iso:country":"ES",
    "sg:address":"Carrer de Mossen Marti, 2",
    "sg:city":"Valls",
    "sg:orig_category":"Dibujantes (diversos)",
    "sg:phone":"+34 977 60 42 02",
    "sg:postcode":"43800",
    "sg:province":"Tarragona",
    "wof:name":"Cuines I Despatxos Benaiges S.l.",
    "wof:placetype":"venue"
},
  "geometry": {"coordinates":[1.2507580519,41.2914428711],"type":"Point"}
}