{
  "type": "Feature",
  "properties": {
    "addr:full":"Carrer de Jonqueres, 18 Barcelona Barcelona 08003",
    "addr:housenumber":"18",
    "addr:postcode":"08003",
    "addr:street":"Carrer De Jonqueres",
    "iso:country":"ES",
    "sg:address":"Carrer de Jonqueres, 18",
    "sg:city":"Barcelona",
    "sg:orig_category":"M\u00c9dicos: Ginecolog\u00cda Y Obstetricia",
    "sg:phone":"+34 933 10 60 83",
    "sg:postcode":"08003",
    "sg:province":"Barcelona",
    "wof:name":"Gonce Mellgren Anna",
    "wof:placetype":"venue"
},
  "geometry": {"coordinates":[2.1738688946,41.3888816833],"type":"Point"}
}