{
  "type": "Feature",
  "properties": {
    "iso:country":"ES",
    "sg:address":"Pl Octavia, 4",
    "sg:city":"S. Cugat Valles",
    "sg:orig_category":"Inmobiliaria (agencias)",
    "sg:phone":"+34 935 89 49 31",
    "sg:postcode":"08172",
    "sg:province":"Barcelona",
    "wof:name":"Verir Inmobiliaria-service S.l.",
    "wof:placetype":"venue"
},
  "geometry": {"coordinates":[2.0839018822,41.4733657837],"type":"Point"}
}