{
  "type": "Feature",
  "properties": {
    "iso:country":"ES",
    "sg:address":"Calle de Don Pedro Infinito, 21",
    "sg:city":"Palmas De Gran Canaria",
    "sg:orig_category":"Bisuter\u00cda, Joyer\u00cda, Relojer\u00cda (al Por Menor)",
    "sg:phone":"+34 928 25 79 33",
    "sg:postcode":"35012",
    "sg:province":"Las Palmas",
    "wof:name":"Marcos Hernandez Jose Victor",
    "wof:placetype":"venue"
},
  "geometry": {"coordinates":[-15.4316864014,28.1099758148],"type":"Point"}
}