{
  "type": "Feature",
  "properties": {
    "addr:full":"Calle de Conde De Salvatierra, 27 Valencia Valencia 46004",
    "addr:housenumber":"27",
    "addr:postcode":"46004",
    "addr:street":"Calle De Conde De Salvatierra",
    "iso:country":"ES",
    "sg:address":"Calle de Conde De Salvatierra, 27",
    "sg:city":"Valencia",
    "sg:orig_category":"Estancos",
    "sg:phone":"+34 963 52 97 35",
    "sg:postcode":"46004",
    "sg:province":"Valencia",
    "wof:name":"Perez Garcia Pilar",
    "wof:placetype":"venue"
},
  "geometry": {"coordinates":[-0.3678086102,39.4691734314],"type":"Point"}
}