{
  "type": "Feature",
  "properties": {
    "addr:full":"Plaza De Garcia Haro, 1 Albox Almer\u00eda 04800",
    "addr:housenumber":"1",
    "addr:postcode":"04800",
    "addr:street":"Haro",
    "iso:country":"ES",
    "sg:address":"Plaza De Garcia Haro, 1",
    "sg:city":"Albox",
    "sg:orig_category":"Farmacias",
    "sg:phone":"+34 950 43 00 37",
    "sg:postcode":"04800",
    "sg:province":"Almer\u00eda",
    "wof:name":"Miron Lopez Felix Luis",
    "wof:placetype":"venue"
},
  "geometry": {"coordinates":[-2.1475739479,37.3895301819],"type":"Point"}
}