{
  "type": "Feature",
  "properties": {
    "iso:country":"ES",
    "sg:address":"Calle de Trinidad Grund, 22",
    "sg:city":"Malaga",
    "sg:orig_category":"Agentes Generales De Seguros",
    "sg:phone":"+34 952 21 14 33",
    "sg:postcode":"29001",
    "sg:province":"M\u00e1laga",
    "wof:name":"Sosa Montesinos Jose Luis De",
    "wof:placetype":"venue"
},
  "geometry": {"coordinates":[-4.4230570793,36.7170066833],"type":"Point"}
}