{
  "type": "Feature",
  "properties": {
    "iso:country":"ES",
    "sg:address":"Carr Sant Pol, 1",
    "sg:city":"Sant Joan De Les Abadesses",
    "sg:orig_category":"Molduras, Junquillos, Listones Y Molduras Perforadas",
    "sg:phone":"+34 972 72 00 52",
    "sg:postcode":"17860",
    "sg:province":"Girona",
    "wof:name":"Caparros Marce Jordi",
    "wof:placetype":"venue"
},
  "geometry": {"coordinates":[2.2854809761,42.2338752747],"type":"Point"}
}