{
  "type": "Feature",
  "properties": {
    "addr:full":"Ctra Nacional Tres Tres Dos, Km. 0155,0 Altea Alicante 03590",
    "addr:postcode":"03590",
    "addr:street":"Ctra Nacional Tres Tres Dos Km. 0155,0",
    "iso:country":"ES",
    "sg:address":"Ctra Nacional Tres Tres Dos, Km. 0155,0",
    "sg:city":"Altea",
    "sg:orig_category":"Venta, Colocaci\u00d3n, Reparaci\u00d3n De Parabrisas, Techos Descapotables",
    "sg:phone":"+34 966 88 14 09",
    "sg:postcode":"03590",
    "sg:province":"Alicante",
    "sg:website":"www.autoglassaltaya-sl.com",
    "wof:name":"Autoglass Altaya S.l.",
    "wof:placetype":"venue"
},
  "geometry": {"coordinates":[-0.0522690006,38.601108551],"type":"Point"}
}