{
  "type": "Feature",
  "properties": {
    "addr:full":"Ronda Tinajerias, 19 Lucena C\u00f3rdoba 14900",
    "addr:housenumber":"19",
    "addr:postcode":"14900",
    "addr:street":"Ronda Tinajerias",
    "iso:country":"ES",
    "sg:address":"Ronda Tinajerias, 19",
    "sg:city":"Lucena",
    "sg:orig_category":"Seguridad En El Trabajo Y Prevenci\u00d3n De Riesgos Laborales",
    "sg:phone":"+34 957 51 05 92",
    "sg:postcode":"14900",
    "sg:province":"C\u00f3rdoba",
    "wof:name":"Abf Proteccion S.l.l.",
    "wof:placetype":"venue"
},
  "geometry": {"coordinates":[-4.479097,37.412369],"type":"Point"}
}