{
  "type": "Feature",
  "properties": {
    "iso:country":"ES",
    "sg:address":"Cmno Viejo De Garrucha, 3",
    "sg:city":"Carboneras",
    "sg:orig_category":"Agencias Y Agentes Comerciales, Representantes",
    "sg:phone":"+34 950 13 07 47",
    "sg:postcode":"04140",
    "sg:province":"Almer\u00eda",
    "wof:name":"Diaz Hernandez Ana",
    "wof:placetype":"venue"
},
  "geometry": {"coordinates":[-1.8905390501,37.0027656555],"type":"Point"}
}