{
  "type": "Feature",
  "properties": {
    "addr:full":"Pla\u00c7 Sant Pere, 9 Lleida Lleida 25005",
    "addr:housenumber":"9",
    "addr:postcode":"25005",
    "addr:street":"Sant Pere",
    "iso:country":"ES",
    "sg:address":"Pla\u00c7 Sant Pere, 9",
    "sg:city":"Lleida",
    "sg:orig_category":"Carnicer\u00cdas, Carnicer\u00cdas",
    "sg:phone":"+34 973 23 17 37",
    "sg:postcode":"25005",
    "sg:province":"Lleida",
    "wof:name":"Carns Puig-gros S.l.",
    "wof:placetype":"venue"
},
  "geometry": {"coordinates":[0.6289430261,41.6362724304],"type":"Point"}
}