{
  "type": "Feature",
  "properties": {
    "iso:country":"ES",
    "sg:address":"Carr Lepanto, 1",
    "sg:city":"Alboraya",
    "sg:orig_category":"Madera (al Por Menor)",
    "sg:phone":"+34 963 17 10 46",
    "sg:postcode":"46120",
    "sg:province":"Valencia",
    "wof:name":"Primewood 1999 S.l.",
    "wof:placetype":"venue"
},
  "geometry": {"coordinates":[-0.3517900109,39.4971313477],"type":"Point"}
}