{
  "type": "Feature",
  "properties": {
    "addr:full":"Calle de San Bernardo, 7 Guadalajara Guadalajara 19005",
    "addr:housenumber":"7",
    "addr:postcode":"19005",
    "addr:street":"Calle De San Bernardo",
    "iso:country":"ES",
    "sg:address":"Calle de San Bernardo, 7",
    "sg:city":"Guadalajara",
    "sg:orig_category":"Cueros Y Pieles (al Por Mayor)",
    "sg:phone":"+34 949 22 08 44",
    "sg:postcode":"19005",
    "sg:province":"Guadalajara",
    "wof:name":"Ruano Caballo Alfonso",
    "wof:placetype":"venue"
},
  "geometry": {"coordinates":[-3.1609470844,40.6354446411],"type":"Point"}
}