{
  "type": "Feature",
  "properties": {
    "iso:country":"ES",
    "sg:address":"Avda Peru (del), 23",
    "sg:city":"Cadiz",
    "sg:orig_category":"Pescader\u00cdas (al Por Menor)",
    "sg:phone":"+34 956 26 18 58",
    "sg:postcode":"11007",
    "sg:province":"C\u00e1diz",
    "wof:name":"Recio Carame Jose Manuel",
    "wof:placetype":"venue"
},
  "geometry": {"coordinates":[-6.275534153,36.5153656006],"type":"Point"}
}