{
  "type": "Feature",
  "properties": {
    "iso:country":"ES",
    "sg:address":"Avda Francisco Pi Y Margall, 100",
    "sg:city":"Madrid",
    "sg:orig_category":"Artes Gr\u00c1ficas, Artes Pl\u00c1sticas (curso)",
    "sg:phone":"+34 917 50 04 19",
    "sg:postcode":"28050",
    "sg:province":"Madrid",
    "wof:name":"Vip Grafic S.l.",
    "wof:placetype":"venue"
},
  "geometry": {"coordinates":[-3.6621689796,40.4926948547],"type":"Point"}
}