{
  "type": "Feature",
  "properties": {
    "addr:full":"Ctra Trescientos Veintidos, S/n Xativa Valencia 46800",
    "addr:housenumber":"s",
    "addr:postcode":"46800",
    "addr:street":"Ctra Trescientos Veintidos;/ N",
    "iso:country":"ES",
    "sg:address":"Ctra Trescientos Veintidos, S/n",
    "sg:city":"Xativa",
    "sg:orig_category":"Reciclaje Y Tratamiento De Desechos Varios",
    "sg:phone":"+34 962 28 02 51",
    "sg:postcode":"46800",
    "sg:province":"Valencia",
    "wof:name":"Lacados Y Decoracion Ferrando S.l",
    "wof:placetype":"venue"
},
  "geometry": {"coordinates":[-0.5200830102,38.9934272766],"type":"Point"}
}