{
  "type": "Feature",
  "properties": {
    "addr:full":"Av Princep D'asturies, 12 Barcelona Barcelona 08012",
    "addr:housenumber":"12",
    "addr:postcode":"08012",
    "addr:street":"Av Princep D'Asturies",
    "iso:country":"ES",
    "sg:address":"Av Princep D'asturies, 12",
    "sg:city":"Barcelona",
    "sg:orig_category":"Doctores En Medicina",
    "sg:phone":"+34 934 15 95 69",
    "sg:postcode":"08012",
    "sg:province":"Barcelona",
    "wof:name":"Camon Solsona Rosendo",
    "wof:placetype":"venue"
},
  "geometry": {"coordinates":[2.1505541801,41.4023399353],"type":"Point"}
}