{
  "type": "Feature",
  "properties": {
    "iso:country":"ES",
    "sg:address":"Avgd Del Comte De Torrefiel, 1",
    "sg:city":"Ontinyent",
    "sg:orig_category":"Peluquer\u00cdas, Peluquer\u00cda Mixta",
    "sg:phone":"+34 962 38 54 27",
    "sg:postcode":"46870",
    "sg:province":"Valencia",
    "wof:name":"Mancebo Gomez Daniel",
    "wof:placetype":"venue"
},
  "geometry": {"coordinates":[-0.6104620099,38.8203964233],"type":"Point"}
}