{
  "type": "Feature",
  "properties": {
    "addr:full":"Calle de Pio Xii, 6 Llodio \u00c1lava 01400",
    "addr:housenumber":"6",
    "addr:postcode":"01400",
    "addr:street":"Calle De Pio Xii",
    "iso:country":"ES",
    "sg:address":"Calle de Pio Xii, 6",
    "sg:city":"Llodio",
    "sg:orig_category":"Bisuter\u00cda, Joyer\u00cda, Relojer\u00cda (al Por Menor)",
    "sg:phone":"+34 946 72 41 71",
    "sg:postcode":"01400",
    "sg:province":"\u00c1lava",
    "sg:website":"www.mijoyeria.com",
    "wof:name":"Ainz Ibarra Juan Jose",
    "wof:placetype":"venue"
},
  "geometry": {"coordinates":[-2.9623966217,43.1428146362],"type":"Point"}
}