{
  "type": "Feature",
  "properties": {
    "addr:full":"Calle de Ramon Llull, 19 Valencia Valencia 46021",
    "addr:housenumber":"19",
    "addr:postcode":"46021",
    "addr:street":"Calle De Ramon Llull",
    "iso:country":"ES",
    "sg:address":"Calle de Ramon Llull, 19",
    "sg:city":"Valencia",
    "sg:orig_category":"Centros Empresariales",
    "sg:phone":"+34 963 61 02 69",
    "sg:postcode":"46021",
    "sg:province":"Valencia",
    "wof:name":"Fernandez Villalba Maria Del Mar",
    "wof:placetype":"venue"
},
  "geometry": {"coordinates":[-0.347153008,39.4761962891],"type":"Point"}
}