{
  "type": "Feature",
  "properties": {
    "addr:full":"Avda Mediterraneo, 14 Madrid Madrid 28007",
    "addr:housenumber":"14",
    "addr:postcode":"madrid;28007",
    "addr:street":"Avda Mediterraneo",
    "iso:country":"ES",
    "sg:address":"Avda Mediterraneo, 14",
    "sg:city":"Madrid",
    "sg:orig_category":"Centros Empresariales",
    "sg:phone":"+34 914 34 80 05",
    "sg:postcode":"28007",
    "sg:province":"Madrid",
    "wof:name":"Amformad",
    "wof:placetype":"venue"
},
  "geometry": {"coordinates":[-3.6759490967,40.4072341919],"type":"Point"}
}