{
  "type": "Feature",
  "properties": {
    "iso:country":"ES",
    "sg:address":"Calle de Poeta Llorente, 55",
    "sg:city":"Pobla Vallbona",
    "sg:orig_category":"Peluqueros: De Se\u00d1oras",
    "sg:phone":"+34 962 76 04 40",
    "sg:postcode":"46185",
    "sg:province":"Valencia",
    "wof:name":"Mestre Pelecha Jose",
    "wof:placetype":"venue"
},
  "geometry": {"coordinates":[-0.5517039895,39.5917358398],"type":"Point"}
}