{
  "type": "Feature",
  "properties": {
    "iso:country":"ES",
    "sg:address":"Calle de Coronel Osuna, 16",
    "sg:city":"Malaga",
    "sg:orig_category":"Cristaler\u00cdas",
    "sg:phone":"+34 952 32 42 19",
    "sg:postcode":"29006",
    "sg:province":"M\u00e1laga",
    "wof:name":"Acrisol S.l.",
    "wof:placetype":"venue"
},
  "geometry": {"coordinates":[-4.4493656158,36.7101745605],"type":"Point"}
}