{
  "type": "Feature",
  "properties": {
    "addr:full":"Calle de Buenos Aires, 1 Palmas De Gran Canaria Las Palmas 35002",
    "addr:housenumber":"1",
    "addr:postcode":"35002",
    "addr:street":"Calle De Buenos Aires",
    "iso:country":"ES",
    "sg:address":"Calle de Buenos Aires, 1",
    "sg:city":"Palmas De Gran Canaria",
    "sg:orig_category":"M\u00c9dicos: Cirug\u00cda Urol\u00d3gica",
    "sg:phone":"+34 928 36 13 79",
    "sg:postcode":"35002",
    "sg:province":"Las Palmas",
    "wof:name":"Ponce Socorro Jose Maria",
    "wof:placetype":"venue"
},
  "geometry": {"coordinates":[-15.417514801,28.1080665588],"type":"Point"}
}