{
  "type": "Feature",
  "properties": {
    "iso:country":"ES",
    "sg:address":"Carr Davant, 17",
    "sg:city":"Alcarras",
    "sg:orig_category":"Alquiler De V\u00cddeo",
    "sg:phone":"+34 973 79 04 75",
    "sg:postcode":"25180",
    "sg:province":"Lleida",
    "wof:name":"Miret Tarrago Josep",
    "wof:placetype":"venue"
},
  "geometry": {"coordinates":[0.5282099843,41.5634155273],"type":"Point"}
}