{
  "type": "Feature",
  "properties": {
    "addr:full":"Avda Antibioticos, 71 Armunia Le\u00f3n 24009",
    "addr:housenumber":"71",
    "addr:postcode":"24009",
    "addr:street":"Avda Antibioticos;Leo\u0301N",
    "iso:country":"ES",
    "sg:address":"Avda Antibioticos, 71",
    "sg:city":"Armunia",
    "sg:orig_category":"Venta, Montaje De Neum\u00c1ticos",
    "sg:phone":"+34 987 21 66 65",
    "sg:postcode":"24009",
    "sg:province":"Le\u00f3n",
    "sg:website":"www.pginas-amarillas.es",
    "wof:name":"Diez Moran Isabel",
    "wof:placetype":"venue"
},
  "geometry": {"coordinates":[-5.5828309059,42.573261261],"type":"Point"}
}