{
  "type": "Feature",
  "properties": {
    "addr:full":"Avda Borbolla (la), 67 Sevilla Sevilla 41013",
    "addr:housenumber":"67",
    "addr:postcode":"41013",
    "addr:street":"Avda Borbolla La",
    "iso:country":"ES",
    "sg:address":"Avda Borbolla (la), 67",
    "sg:city":"Sevilla",
    "sg:orig_category":"Fisioterapia",
    "sg:phone":"+34 954 23 38 58",
    "sg:postcode":"41013",
    "sg:province":"Sevilla",
    "wof:name":"Codina Lanaspa Dolors",
    "wof:placetype":"venue"
},
  "geometry": {"coordinates":[-5.9853038788,37.3713912964],"type":"Point"}
}