{
  "type": "Feature",
  "properties": {
    "addr:full":"Calle de Cedros, 6 Malaga M\u00e1laga 29018",
    "addr:housenumber":"6",
    "addr:postcode":"29018",
    "addr:street":"Calle De Cedros;Ma\u0301Laga",
    "iso:country":"ES",
    "sg:address":"Calle de Cedros, 6",
    "sg:city":"Malaga",
    "sg:orig_category":"Electricidad, Electr\u00d3nica: Material Y Suministros (al Por Mayor)",
    "sg:phone":"+34 952 29 67 31",
    "sg:postcode":"29018",
    "sg:province":"M\u00e1laga",
    "wof:name":"Instrumatic Espa\u00f1ola S.a.",
    "wof:placetype":"venue"
},
  "geometry": {"coordinates":[-4.2282781601,36.7152938843],"type":"Point"}
}