{
  "type": "Feature",
  "properties": {
    "iso:country":"ES",
    "sg:address":"Cmno Epila (miralbueno), 27",
    "sg:city":"Zaragoza",
    "sg:orig_category":"Empresas De Carpinter\u00cda Met\u00c1lica",
    "sg:phone":"+34 976 53 83 69",
    "sg:postcode":"50011",
    "sg:province":"Zaragoza",
    "wof:name":"Aragonesa Instalaciones Roncales Sl",
    "wof:placetype":"venue"
},
  "geometry": {"coordinates":[-1.0011901855,41.6566925049],"type":"Point"}
}