{
  "type": "Feature",
  "properties": {
    "iso:country":"ES",
    "sg:address":"Calle de San Toribio, 6",
    "sg:city":"Madrid",
    "sg:orig_category":"Equipo De Refrigeraci\u00d3n Industrial",
    "sg:phone":"+34 913 80 32 46",
    "sg:postcode":"28031",
    "sg:province":"Madrid",
    "sg:website":"www.frimetal.es",
    "wof:name":"Frimetal S.a.",
    "wof:placetype":"venue"
},
  "geometry": {"coordinates":[-3.6352651119,40.3801307678],"type":"Point"}
}