{
  "type": "Feature",
  "properties": {
    "iso:country":"ES",
    "sg:address":"Carrer de Gracia, 114",
    "sg:city":"Sabadell",
    "sg:orig_category":"Producci\u00d3n, Venta De Productos De Agricultura Biol\u00d3gica",
    "sg:phone":"+34 937 26 84 37",
    "sg:postcode":"08201",
    "sg:province":"Barcelona",
    "wof:name":"Equisetum Arvense S.l.",
    "wof:placetype":"venue"
},
  "geometry": {"coordinates":[2.105328083,41.5499801636],"type":"Point"}
}