{
  "type": "Feature",
  "properties": {
    "iso:country":"ES",
    "sg:address":"Calle de Brasil (de), S/n",
    "sg:city":"Alcorcon",
    "sg:orig_category":"Agentes, Concesionarios Y Sucursales De Veh\u00cdculos",
    "sg:phone":"+34 916 21 04 90",
    "sg:postcode":"28922",
    "sg:province":"Madrid",
    "wof:name":"Citycar Sur S.a.",
    "wof:placetype":"venue"
},
  "geometry": {"coordinates":[-3.8258318901,40.3566131592],"type":"Point"}
}