{
  "type": "Feature",
  "properties": {
    "iso:country":"ES",
    "sg:address":"Carrer de Bonavista, 44",
    "sg:city":"S. Just Desvern",
    "sg:orig_category":"Peluqueros: De Se\u00d1oras",
    "sg:phone":"+34 933 71 12 29",
    "sg:postcode":"08960",
    "sg:province":"Barcelona",
    "wof:name":"Vives Casals Rosa",
    "wof:placetype":"venue"
},
  "geometry": {"coordinates":[2.077760458,41.3821907043],"type":"Point"}
}