{
  "type": "Feature",
  "properties": {
    "addr:full":"Calle de Gaztelu, 11 Donostia-san Sebastian Guip\u00f9zcoa 20013",
    "addr:housenumber":"11",
    "addr:postcode":"20013",
    "addr:street":"Calle De Gaztelu",
    "iso:country":"ES",
    "sg:address":"Calle de Gaztelu, 11",
    "sg:city":"Donostia-san Sebastian",
    "sg:orig_category":"Asociaciones, Organismos Culturales Y Socioeducativos",
    "sg:phone":"+34 943 29 10 90",
    "sg:postcode":"20013",
    "sg:province":"Guip\u00f9zcoa",
    "wof:name":"Kideak Kultur Ekintzak S.l.",
    "wof:placetype":"venue"
},
  "geometry": {"coordinates":[-1.9569493532,43.3190498352],"type":"Point"}
}