{
  "type": "Feature",
  "properties": {
    "iso:country":"ES",
    "sg:address":"Rbla Onze De Setembre, 33",
    "sg:city":"Barcelona",
    "sg:orig_category":"Frutas, Legumbres Frescas Y Tempranas (al Por Menor)",
    "sg:phone":"+34 933 45 78 26",
    "sg:postcode":"08030",
    "sg:province":"Barcelona",
    "wof:name":"Morales Timbela Mario Rene",
    "wof:placetype":"venue"
},
  "geometry": {"coordinates":[2.1930770874,41.4302864075],"type":"Point"}
}