{
  "type": "Feature",
  "properties": {
    "addr:full":"Rua Caldeireria (da), 38 Santiago De Compostela La Coru\u00f1a 15703",
    "addr:housenumber":"38",
    "addr:postcode":"15703",
    "addr:street":"Rua Caldeireria Da;Corun\u0303A",
    "iso:country":"ES",
    "sg:address":"Rua Caldeireria (da), 38",
    "sg:city":"Santiago De Compostela",
    "sg:orig_category":"Confecci\u00d3n (fabricaci\u00d3n, Al Por Mayor)",
    "sg:phone":"+34 981 58 15 94",
    "sg:postcode":"15703",
    "sg:province":"La Coru\u00f1a",
    "wof:name":"Garabal S. L.",
    "wof:placetype":"venue"
},
  "geometry": {"coordinates":[-8.5428676605,42.8789482117],"type":"Point"}
}