{
  "type": "Feature",
  "properties": {
    "iso:country":"ES",
    "sg:address":"Calle de Reyes Huertas, 22",
    "sg:city":"Pe\u00f1alsordo",
    "sg:orig_category":"Equitaci\u00d3n: Guarnicioner\u00cda, Equipo (al Por Menor)",
    "sg:phone":"+34 924 61 40 39",
    "sg:postcode":"06610",
    "sg:province":"Badajoz",
    "wof:name":"Bayon Cabanillas Pedro",
    "wof:placetype":"venue"
},
  "geometry": {"coordinates":[-5.1125321388,38.8211708069],"type":"Point"}
}