{
  "type": "Feature",
  "properties": {
    "addr:full":"Carrer de Gran De Sant Andreu, 139 Barcelona Barcelona 08030",
    "addr:housenumber":"139",
    "addr:postcode":"08030",
    "addr:street":"Carrer De Gran De Sant Andreu",
    "iso:country":"ES",
    "sg:address":"Carrer de Gran De Sant Andreu, 139",
    "sg:city":"Barcelona",
    "sg:orig_category":"Estilistas Y Estudios De Estilo De Corte Y Confecci\u00d3n",
    "sg:phone":"+34 933 46 68 53",
    "sg:postcode":"08030",
    "sg:province":"Barcelona",
    "wof:name":"Nadal Sirvent Josefa",
    "wof:placetype":"venue"
},
  "geometry": {"coordinates":[2.1891798973,41.4317131042],"type":"Point"}
}