{
  "type": "Feature",
  "properties": {
    "iso:country":"ES",
    "sg:address":"Calle de Mendez Nu\u00d1ez, 1",
    "sg:city":"Pozuelo De Alarcon",
    "sg:orig_category":"Urbanistas",
    "sg:phone":"+34 913 52 64 59",
    "sg:postcode":"28223",
    "sg:province":"Madrid",
    "wof:name":"Cirqlar Arquitectura Y Urbanismo S.l.",
    "wof:placetype":"venue"
},
  "geometry": {"coordinates":[-3.8181378841,40.4332542419],"type":"Point"}
}