{
  "type": "Feature",
  "properties": {
    "iso:country":"ES",
    "sg:address":"Carrer de Rios Rosas, 35",
    "sg:city":"Barcelona",
    "sg:orig_category":"Hilaturas, Hilos Y Actividades Relacionadas",
    "sg:phone":"+34 932 68 86 90",
    "sg:postcode":"08006",
    "sg:province":"Barcelona",
    "wof:name":"Comercial Algodonera Juan Mata S. A.",
    "wof:placetype":"venue"
},
  "geometry": {"coordinates":[2.143376112,41.4041442871],"type":"Point"}
}