{
  "type": "Feature",
  "properties": {
    "addr:full":"Calle de San Gerardo, 32 Madrid Madrid 28035",
    "addr:housenumber":"32",
    "addr:postcode":"madrid;28035",
    "addr:street":"Calle De San Gerardo",
    "iso:country":"ES",
    "sg:address":"Calle de San Gerardo, 32",
    "sg:city":"Madrid",
    "sg:orig_category":"Edici\u00d3n De Diarios, Revistas, Boletines",
    "sg:phone":"+34 913 86 24 92",
    "sg:postcode":"28035",
    "sg:province":"Madrid",
    "wof:name":"Castejon Duran Maria Nieves",
    "wof:placetype":"venue"
},
  "geometry": {"coordinates":[-3.722276926,40.46824646],"type":"Point"}
}