{
  "type": "Feature",
  "properties": {
    "iso:country":"ES",
    "sg:address":"Calle de Doctor Bonardell, 9",
    "sg:city":"Alcazar S. Juan",
    "sg:orig_category":"Inform\u00c1tica (estudios, Servicios, Asesor\u00cda, Formaci\u00d3n)",
    "sg:phone":"+34 926 58 81 18",
    "sg:postcode":"13600",
    "sg:province":"Ciudad Real",
    "wof:name":"Mecanizacion Y Calculo S.a.",
    "wof:placetype":"venue"
},
  "geometry": {"coordinates":[-3.2156476974,39.3885498047],"type":"Point"}
}