{
  "type": "Feature",
  "properties": {
    "addr:full":"Outeiro A. Sesamo, 1 Outeiro De Abaixo La Coru\u00f1a 15189",
    "addr:housenumber":"1",
    "addr:postcode":"15189",
    "addr:street":"Outeiro;Sesamo;Abaixo;Corun\u0303A",
    "iso:country":"ES",
    "sg:address":"Outeiro A. Sesamo, 1",
    "sg:city":"Outeiro De Abaixo",
    "sg:orig_category":"Empresas De Carpinter\u00cda De Madera",
    "sg:phone":"+34 981 67 72 95",
    "sg:postcode":"15189",
    "sg:province":"La Coru\u00f1a",
    "wof:name":"Garcia Garcia Francisco Javier",
    "wof:placetype":"venue"
},
  "geometry": {"coordinates":[-8.3897981644,43.2883262634],"type":"Point"}
}