{
  "type": "Feature",
  "properties": {
    "iso:country":"ES",
    "sg:address":"Pase Castellana, 54",
    "sg:city":"Madrid",
    "sg:orig_category":"M\u00c9dicos: Oftalmolog\u00cda",
    "sg:phone":"+34 914 11 11 11",
    "sg:postcode":"28046",
    "sg:province":"Madrid",
    "sg:website":"www.clinicanovovision.com",
    "wof:name":"Novoftal S.l.",
    "wof:placetype":"venue"
},
  "geometry": {"coordinates":[-3.6883690357,40.435874939],"type":"Point"}
}