{
  "type": "Feature",
  "properties": {
    "iso:country":"ES",
    "sg:address":"Calle de Llanterner, 2",
    "sg:city":"Teulada",
    "sg:orig_category":"Veh\u00cdculos De Ocasi\u00d3n",
    "sg:phone":"+34 965 74 15 86",
    "sg:postcode":"03725",
    "sg:province":"Alicante",
    "sg:website":"www.autoelite.es",
    "wof:name":"Autoelite Teulada S.l.",
    "wof:placetype":"venue"
},
  "geometry": {"coordinates":[0.0938799977,38.7283439636],"type":"Point"}
}