{
  "type": "Feature",
  "properties": {
    "addr:full":"C/ Blas Valero, 74 Elche Alicante 03201",
    "addr:housenumber":"74",
    "addr:postcode":"03201",
    "addr:street":"C / Blas Valero",
    "iso:country":"ES",
    "sg:address":"C/ Blas Valero, 74",
    "sg:city":"Elche",
    "sg:orig_category":"Centros De Adelgazamiento Y De Est\u00c9tica",
    "sg:phone":"+34 966 67 42 48",
    "sg:postcode":"03201",
    "sg:province":"Alicante",
    "wof:name":"Fisioelx S.l.",
    "wof:placetype":"venue"
},
  "geometry": {"coordinates":[-0.701300025,38.2688827515],"type":"Point"}
}