{
  "type": "Feature",
  "properties": {
    "addr:full":"Calle de Peral, 4 Sevilla Sevilla 41002",
    "addr:housenumber":"4",
    "addr:postcode":"41002",
    "addr:street":"Calle De Peral",
    "iso:country":"ES",
    "sg:address":"Calle de Peral, 4",
    "sg:city":"Sevilla",
    "sg:orig_category":"Transportes Por Carretera: Lotes Completos, Mercanc\u00cdas Diversas",
    "sg:phone":"+34 954 37 39 33",
    "sg:postcode":"41002",
    "sg:province":"Sevilla",
    "wof:name":"Brocal Velazquez Antonio",
    "wof:placetype":"venue"
},
  "geometry": {"coordinates":[-5.9932332039,37.4005470276],"type":"Point"}
}