{
  "type": "Feature",
  "properties": {
    "addr:full":"Urb Paraiso (el), S/n Paraiso-barronal M\u00e1laga 29680",
    "addr:postcode":"29680",
    "addr:street":"Urb;El S / N Paraiso-Barronal Ma\u0301Laga",
    "iso:country":"ES",
    "sg:address":"Urb Paraiso (el), S/n",
    "sg:city":"Paraiso-barronal",
    "sg:orig_category":"Inmobiliaria (agencias)",
    "sg:phone":"+34 952 88 70 45",
    "sg:postcode":"29680",
    "sg:province":"M\u00e1laga",
    "sg:website":"www.interinvestmarbella.com",
    "wof:name":"Kilshannig Investments S.l.",
    "wof:placetype":"venue"
},
  "geometry": {"coordinates":[-5.1452140808,36.4275817871],"type":"Point"}
}