{
  "type": "Feature",
  "properties": {
    "iso:country":"ES",
    "sg:address":"Calle de Alfonso Xi, 18",
    "sg:city":"Algeciras",
    "sg:orig_category":"M\u00c9dicos: Geriatr\u00cda, Gerontolog\u00cda (enfermedades De La Tercera Edad)",
    "sg:phone":"+34 956 66 42 27",
    "sg:postcode":"11201",
    "sg:province":"C\u00e1diz",
    "wof:name":"Navarro Moreno Carlos",
    "wof:placetype":"venue"
},
  "geometry": {"coordinates":[-5.4397826195,36.135761261],"type":"Point"}
}