{
  "type": "Feature",
  "properties": {
    "iso:country":"ES",
    "sg:address":"Calle de Secretario Artiles, 3",
    "sg:city":"Palmas De Gran Canaria",
    "sg:orig_category":"Postigos, Persianas Y Celos\u00cdas",
    "sg:phone":"+34 928 26 91 18",
    "sg:postcode":"35007",
    "sg:province":"Las Palmas",
    "wof:name":"Persianas Persigrad S.l.",
    "wof:placetype":"venue"
},
  "geometry": {"coordinates":[-15.4317293167,28.1358356476],"type":"Point"}
}