{
  "type": "Feature",
  "properties": {
    "iso:country":"ES",
    "sg:address":"Barr Peruri, 33",
    "sg:city":"Peruri",
    "sg:orig_category":"Lencer\u00cda Femenina, Corseter\u00cda, Trajes De Ba\u00d1o (al Por Menor)",
    "sg:phone":"+34 944 60 13 71",
    "sg:postcode":"48940",
    "sg:province":"Vizcaya",
    "sg:website":"www.etam.com",
    "wof:name":"Industria Franco Espa\u00f1ola De Moda S.a.",
    "wof:placetype":"venue"
},
  "geometry": {"coordinates":[-2.9860789776,43.3275489807],"type":"Point"}
}