{
  "type": "Feature",
  "properties": {
    "addr:full":"Rua Quintian, S/n Ourense Ourense 32001",
    "addr:housenumber":"s",
    "addr:postcode":"32001",
    "addr:street":"Rua Quintian;/ N",
    "iso:country":"ES",
    "sg:address":"Rua Quintian, S/n",
    "sg:city":"Ourense",
    "sg:orig_category":"Muebles Y Accesorios Para Cocinas Y Cuartos De Ba\u00d1o (al Por Menor)",
    "sg:phone":"+34 988 21 36 92",
    "sg:postcode":"32001",
    "sg:province":"Ourense",
    "wof:name":"Fontaneria Trigo Novoa S.l.",
    "wof:placetype":"venue"
},
  "geometry": {"coordinates":[-7.8715991974,42.3524284363],"type":"Point"}
}