{
  "type": "Feature",
  "properties": {
    "addr:full":"Calle de Iglesia, 33 Navaluenga \u00c1vila 05100",
    "addr:housenumber":"33",
    "addr:postcode":"05100",
    "addr:street":"Calle De Iglesia",
    "iso:country":"ES",
    "sg:address":"Calle de Iglesia, 33",
    "sg:city":"Navaluenga",
    "sg:orig_category":"Cajas De Ahorro",
    "sg:phone":"+34 920 28 60 43",
    "sg:postcode":"05100",
    "sg:province":"\u00c1vila",
    "wof:name":"Caja De Avila",
    "wof:placetype":"venue"
},
  "geometry": {"coordinates":[-4.7080287933,40.4113082886],"type":"Point"}
}