{
  "type": "Feature",
  "properties": {
    "addr:full":"Calle de Mayor, 42 Castellon Castell\u00f3n 12001",
    "addr:housenumber":"42",
    "addr:postcode":"12001",
    "addr:street":"Calle De Mayor",
    "iso:country":"ES",
    "sg:address":"Calle de Mayor, 42",
    "sg:city":"Castellon",
    "sg:orig_category":"Abogados",
    "sg:phone":"+34 964 26 02 06",
    "sg:postcode":"12001",
    "sg:province":"Castell\u00f3n",
    "wof:name":"Olucha Torrella Inmaculada",
    "wof:placetype":"venue"
},
  "geometry": {"coordinates":[-0.0390900001,39.9866714478],"type":"Point"}
}