{
  "type": "Feature",
  "properties": {
    "addr:full":"Carr Joan Pau Climent, 11 Villafranca Cid Castell\u00f3n 12150",
    "addr:housenumber":"11",
    "addr:postcode":"12150",
    "addr:street":"Carr Joan Pau Climent",
    "iso:country":"ES",
    "sg:address":"Carr Joan Pau Climent, 11",
    "sg:city":"Villafranca Cid",
    "sg:orig_category":"Plomeros",
    "sg:phone":"+34 964 44 14 08",
    "sg:postcode":"12150",
    "sg:province":"Castell\u00f3n",
    "wof:name":"Andres Alos Jesus",
    "wof:placetype":"venue"
},
  "geometry": {"coordinates":[-0.2573210001,40.4292488098],"type":"Point"}
}