{
  "type": "Feature",
  "properties": {
    "iso:country":"ES",
    "sg:address":"Centro Comercial Bonaire, S/n",
    "sg:city":"Aldaia",
    "sg:orig_category":"Alquiler De V\u00cddeo",
    "sg:phone":"+34 961 92 13 19",
    "sg:postcode":"46960",
    "sg:province":"Valencia",
    "wof:name":"Carameleria Dols S.l.",
    "wof:placetype":"venue"
},
  "geometry": {"coordinates":[-0.4853590131,39.4696578979],"type":"Point"}
}