{
  "type": "Feature",
  "properties": {
    "iso:country":"ES",
    "sg:address":"Avgd Bolero De Carlet, (del), 1",
    "sg:city":"Carlet",
    "sg:orig_category":"\u00d3ptica: Instrumentos (fabricaci\u00d3n)",
    "sg:phone":"+34 962 99 32 21",
    "sg:postcode":"46240",
    "sg:province":"Valencia",
    "wof:name":"Bellot Coa C.b.",
    "wof:placetype":"venue"
},
  "geometry": {"coordinates":[-0.5194870234,39.22240448],"type":"Point"}
}