{
  "type": "Feature",
  "properties": {
    "addr:full":"C. Vidal Barraquer, 28 Reus Tarragona 43205",
    "addr:housenumber":"28",
    "addr:postcode":"43205",
    "addr:street":"C. Vidal Barraquer",
    "iso:country":"ES",
    "sg:address":"C. Vidal Barraquer, 28",
    "sg:city":"Reus",
    "sg:orig_category":"Fabricaci\u00d3n De Art\u00cdculos Para Papeler\u00cdas",
    "sg:phone":"+34 977 75 08 83",
    "sg:postcode":"43205",
    "sg:province":"Tarragona",
    "wof:name":"Simo Ma\u00f1e Vicente",
    "wof:placetype":"venue"
},
  "geometry": {"coordinates":[1.107929945,41.1519889832],"type":"Point"}
}