{
  "type": "Feature",
  "properties": {
    "iso:country":"ES",
    "sg:address":"Calle de Ramon Y Cajal, 27",
    "sg:city":"Pina De Ebro",
    "sg:orig_category":"Sindicatos De Trabajadores",
    "sg:phone":"+34 976 16 51 57",
    "sg:postcode":"50750",
    "sg:province":"Zaragoza",
    "wof:name":"Sindicato De Riegos De Los Llanos",
    "wof:placetype":"venue"
},
  "geometry": {"coordinates":[-0.5305889845,41.4886016846],"type":"Point"}
}