{
  "type": "Feature",
  "properties": {
    "addr:full":"Perez De Ayala, S/n Granada Granada 18007",
    "addr:housenumber":"s / n",
    "addr:postcode":"18007",
    "iso:country":"ES",
    "sg:address":"Perez De Ayala, S/n",
    "sg:city":"Granada",
    "sg:orig_category":"Colchones (fabricaci\u00d3n, Al Por Mayor, Al Por Menor)",
    "sg:phone":"+34 958 12 28 53",
    "sg:postcode":"18007",
    "sg:province":"Granada",
    "wof:name":"Pinel Garcia Manuel",
    "wof:placetype":"venue"
},
  "geometry": {"coordinates":[-3.5925838947,37.1581497192],"type":"Point"}
}