{
  "type": "Feature",
  "properties": {
    "addr:full":"Calle de Dicenta, 3 Calatayud Zaragoza 50300",
    "addr:housenumber":"3",
    "addr:postcode":"50300",
    "addr:street":"Calle De Dicenta",
    "iso:country":"ES",
    "sg:address":"Calle de Dicenta, 3",
    "sg:city":"Calatayud",
    "sg:orig_category":"Perfumer\u00cda (al Por Menor)",
    "sg:phone":"+34 976 88 57 80",
    "sg:postcode":"50300",
    "sg:province":"Zaragoza",
    "wof:name":"Latorre Jansana Maria Jose",
    "wof:placetype":"venue"
},
  "geometry": {"coordinates":[-1.6433775425,41.352897644],"type":"Point"}
}