{
  "type": "Feature",
  "properties": {
    "addr:full":"Calle de Antonio Cuevas Belmonte, 10 Albacete Albacete 02006",
    "addr:housenumber":"10",
    "addr:postcode":"02006",
    "addr:street":"Calle De Antonio Cuevas Belmonte",
    "iso:country":"ES",
    "sg:address":"Calle de Antonio Cuevas Belmonte, 10",
    "sg:city":"Albacete",
    "sg:orig_category":"Internados & Ense\u00d1anza Privada",
    "sg:phone":"+34 967 23 52 89",
    "sg:postcode":"02006",
    "sg:province":"Albacete",
    "wof:name":"Colegio Monserrat",
    "wof:placetype":"venue"
},
  "geometry": {"coordinates":[-1.8694022894,38.9900894165],"type":"Point"}
}