{
  "type": "Feature",
  "properties": {
    "addr:full":"Carrer de Sant Lluis, 37 Barcelona Barcelona 08012",
    "addr:housenumber":"37",
    "addr:postcode":"08012",
    "addr:street":"Carrer De Sant Lluis",
    "iso:country":"ES",
    "sg:address":"Carrer de Sant Lluis, 37",
    "sg:city":"Barcelona",
    "sg:orig_category":"Pizzer\u00cdas",
    "sg:phone":"+34 932 10 29 53",
    "sg:postcode":"08012",
    "sg:province":"Barcelona",
    "wof:name":"Sanchez Gomez Jose Luis",
    "wof:placetype":"venue"
},
  "geometry": {"coordinates":[2.1597790718,41.4052963257],"type":"Point"}
}