{
  "type": "Feature",
  "properties": {
    "iso:country":"ES",
    "sg:address":"Calle de Don Juan De Austria, 49",
    "sg:city":"Almazora",
    "sg:orig_category":"Transportes Por V\u00cdas Navegables",
    "sg:phone":"+34 964 55 08 46",
    "sg:postcode":"12550",
    "sg:province":"Castell\u00f3n",
    "wof:name":"Montiel Serrano Santos",
    "wof:placetype":"venue"
},
  "geometry": {"coordinates":[-0.0668606013,39.9496383667],"type":"Point"}
}