{
  "type": "Feature",
  "properties": {
    "addr:full":"Calle de Ortega Munilla, 22 Malaga M\u00e1laga 29017",
    "addr:housenumber":"22",
    "addr:postcode":"29017",
    "addr:street":"Calle De Ortega Munilla;Ma\u0301Laga",
    "iso:country":"ES",
    "sg:address":"Calle de Ortega Munilla, 22",
    "sg:city":"Malaga",
    "sg:classifiers":[
        {
            "category":"Personal",
            "subcategory":"Barber",
            "type":"Services"
        }
    ],
    "sg:phone":"+34 952 29 00 79",
    "sg:postcode":"29017",
    "sg:province":"M\u00e1laga",
    "sg:tags":[
        "caballeros",
        "de",
        "peluqueros"
    ],
    "wof:name":"Olmo Cespedes Jose",
    "wof:placetype":"venue"
},
  "geometry": {"coordinates":[-4.3604707718,36.7201805115],"type":"Point"}
}