{
  "type": "Feature",
  "properties": {
    "iso:country":"ES",
    "sg:address":"Avda Mediterraneo (del), 143",
    "sg:city":"Rincon Victoria",
    "sg:orig_category":"Muebles, Minoristas",
    "sg:phone":"+34 952 97 80 27",
    "sg:postcode":"29730",
    "sg:province":"M\u00e1laga",
    "wof:name":"Muebles Y Electrodomesticos Pardo S.l.",
    "wof:placetype":"venue"
},
  "geometry": {"coordinates":[-4.279668808,36.7145004272],"type":"Point"}
}