{
  "type": "Feature",
  "properties": {
    "addr:full":"Calle de Foro, 3 Fuente Del Rey Sevilla 41700",
    "addr:housenumber":"3",
    "addr:postcode":"41700",
    "addr:street":"Calle De Foro",
    "iso:country":"ES",
    "sg:address":"Calle de Foro, 3",
    "sg:city":"Fuente Del Rey",
    "sg:orig_category":"Trabajos De Plastificado, Encolado, Pel\u00cdculas Trasparentes",
    "sg:phone":"+34 954 93 08 46",
    "sg:postcode":"41700",
    "sg:province":"Sevilla",
    "wof:name":"Plasresur S.a.",
    "wof:placetype":"venue"
},
  "geometry": {"coordinates":[-5.9756040573,37.3112182617],"type":"Point"}
}