{
  "type": "Feature",
  "properties": {
    "addr:full":"Calle de Butarque, 15 Leganes Madrid 28911",
    "addr:housenumber":"15",
    "addr:postcode":"28911",
    "addr:street":"Calle De Butarque",
    "iso:country":"ES",
    "sg:address":"Calle de Butarque, 15",
    "sg:city":"Leganes",
    "sg:orig_category":"Universidades",
    "sg:phone":"+34 916 86 10 54",
    "sg:postcode":"28911",
    "sg:province":"Madrid",
    "wof:name":"Universidad Sur - Carlos Iii",
    "wof:placetype":"venue"
},
  "geometry": {"coordinates":[-3.7656009197,40.3308372498],"type":"Point"}
}