{
  "type": "Feature",
  "properties": {
    "addr:full":"Calle de Fernan Caballero, 11 Sevilla Sevilla 41001",
    "addr:housenumber":"11",
    "addr:postcode":"41001",
    "addr:street":"Calle De Fernan Caballero",
    "iso:country":"ES",
    "sg:address":"Calle de Fernan Caballero, 11",
    "sg:city":"Sevilla",
    "sg:orig_category":"M\u00c9dicos: An\u00c1lisis Cl\u00cdnicos",
    "sg:phone":"+34 954 21 27 68",
    "sg:postcode":"41001",
    "sg:province":"Sevilla",
    "wof:name":"Gayoso Gomez Fidel",
    "wof:placetype":"venue"
},
  "geometry": {"coordinates":[-5.9982328415,37.3917388916],"type":"Point"}
}