{
  "type": "Feature",
  "properties": {
    "addr:full":"Calle de Freneria, 2 Catedral Murcia 30004",
    "addr:housenumber":"2",
    "addr:postcode":"30004",
    "addr:street":"Calle De Freneria",
    "iso:country":"ES",
    "sg:address":"Calle de Freneria, 2",
    "sg:city":"Catedral",
    "sg:orig_category":"Bisuter\u00cda, Joyer\u00cda, Relojer\u00cda (al Por Menor)",
    "sg:phone":"+34 968 21 79 29",
    "sg:postcode":"30004",
    "sg:province":"Murcia",
    "sg:website":"www.solercia.es",
    "wof:name":"Solercia Joyeros S.l.",
    "wof:placetype":"venue"
},
  "geometry": {"coordinates":[-1.1298867464,37.9834747314],"type":"Point"}
}