{
  "type": "Feature",
  "properties": {
    "addr:full":"Calle de Mayor, 65 Barco De Avila \u00c1vila 05600",
    "addr:housenumber":"65",
    "addr:postcode":"05600",
    "addr:street":"Calle De Mayor;A\u0301Vila",
    "iso:country":"ES",
    "sg:address":"Calle de Mayor, 65",
    "sg:city":"Barco De Avila",
    "sg:orig_category":"Droguer\u00cdas (al Por Menor)",
    "sg:phone":"+34 920 34 00 61",
    "sg:postcode":"05600",
    "sg:province":"\u00c1vila",
    "wof:name":"Vaquero Sanchez Agustin",
    "wof:placetype":"venue"
},
  "geometry": {"coordinates":[-5.5239500999,40.358543396],"type":"Point"}
}