{
  "type": "Feature",
  "properties": {
    "iso:country":"ES",
    "sg:address":"Carrer de Francesc Santacana, 12",
    "sg:city":"Martorell",
    "sg:orig_category":"Librer\u00cdas",
    "sg:phone":"+34 937 74 21 91",
    "sg:postcode":"08760",
    "sg:province":"Barcelona",
    "wof:name":"Carafi Sans Maria Eulalia",
    "wof:placetype":"venue"
},
  "geometry": {"coordinates":[1.927760005,41.4740905762],"type":"Point"}
}