{
  "type": "Feature",
  "properties": {
    "addr:full":"Calle de Torreta (la), 4 Elda Alicante 03600",
    "addr:housenumber":"4",
    "addr:postcode":"03600",
    "addr:street":"Calle De Torreta La",
    "iso:country":"ES",
    "sg:address":"Calle de Torreta (la), 4",
    "sg:city":"Elda",
    "sg:orig_category":"Mec\u00c1nico Del Autom\u00d3vil",
    "sg:phone":"+34 965 38 70 00",
    "sg:postcode":"03600",
    "sg:province":"Alicante",
    "wof:name":"Blazquez Escudero Antonio",
    "wof:placetype":"venue"
},
  "geometry": {"coordinates":[-0.794081986,38.4909858704],"type":"Point"}
}