{
  "type": "Feature",
  "properties": {
    "addr:full":"Carr De Salvador Tormo, 24 Ontinyent Valencia 46870",
    "addr:housenumber":"24",
    "addr:postcode":"46870",
    "addr:street":"Carr De Salvador Tormo",
    "iso:country":"ES",
    "sg:address":"Carr De Salvador Tormo, 24",
    "sg:city":"Ontinyent",
    "sg:orig_category":"Electrodom\u00c9sticos (al Por Menor)",
    "sg:phone":"+34 962 38 03 71",
    "sg:postcode":"46870",
    "sg:province":"Valencia",
    "wof:name":"Tv. Pastor S.l.",
    "wof:placetype":"venue"
},
  "geometry": {"coordinates":[-0.6018760204,38.8228530884],"type":"Point"}
}