{
  "type": "Feature",
  "properties": {
    "addr:full":"Av Ballester, 23 Viladecans Barcelona 08840",
    "addr:housenumber":"23",
    "addr:postcode":"08840",
    "addr:street":"Av Ballester",
    "iso:country":"ES",
    "sg:address":"Av Ballester, 23",
    "sg:city":"Viladecans",
    "sg:orig_category":"Animales: Material Y Suministros Para (fabricaci\u00d3n, Al Por Mayor)",
    "sg:phone":"+34 936 37 57 98",
    "sg:postcode":"08840",
    "sg:province":"Barcelona",
    "wof:name":"Feliu Checa S.l.",
    "wof:placetype":"venue"
},
  "geometry": {"coordinates":[2.0077259541,41.3190994263],"type":"Point"}
}