{
  "type": "Feature",
  "properties": {
    "iso:country":"ES",
    "sg:address":"Carrer de Lisboa, 8",
    "sg:city":"Barcelona",
    "sg:orig_category":"Estancos",
    "sg:phone":"+34 934 20 12 09",
    "sg:postcode":"08032",
    "sg:province":"Barcelona",
    "wof:name":"Campo Gracia Maria Dolores",
    "wof:placetype":"venue"
},
  "geometry": {"coordinates":[2.1587820053,41.4297218323],"type":"Point"}
}