{
  "type": "Feature",
  "properties": {
    "addr:full":"Calle de Toro, 52 Salamanca Salamanca 37002",
    "addr:housenumber":"52",
    "addr:postcode":"37002",
    "addr:street":"Calle De Toro",
    "iso:country":"ES",
    "sg:address":"Calle de Toro, 52",
    "sg:city":"Salamanca",
    "sg:orig_category":"Electrodom\u00c9sticos (al Por Menor)",
    "sg:phone":"+34 923 26 17 37",
    "sg:postcode":"37002",
    "sg:province":"Salamanca",
    "wof:name":"Garcia Martin Antonio",
    "wof:placetype":"venue"
},
  "geometry": {"coordinates":[-5.6617469788,40.9671669006],"type":"Point"}
}