{
  "type": "Feature",
  "properties": {
    "iso:country":"ES",
    "sg:address":"Barr Campo De La Iglesia, 73",
    "sg:city":"Bello",
    "sg:orig_category":"Molduras, Junquillos, Listones Y Molduras Perforadas",
    "sg:phone":"+34 985 48 60 14",
    "sg:postcode":"33686",
    "sg:province":"Asturias",
    "wof:name":"Gonzalez Rodriguez Azucena",
    "wof:placetype":"venue"
},
  "geometry": {"coordinates":[-5.6228342056,43.1615257263],"type":"Point"}
}