{
  "type": "Feature",
  "properties": {
    "addr:full":"Calle de Pancho Guerra, 18 Palmas De Gran Canaria Las Palmas 35014",
    "addr:postcode":"35014",
    "addr:street":"Calle De Pancho Guerra 18",
    "iso:country":"ES",
    "sg:address":"Calle de Pancho Guerra, 18",
    "sg:city":"Palmas De Gran Canaria",
    "sg:orig_category":"Inmobiliaria (agencias)",
    "sg:phone":"+34 928 43 34 00",
    "sg:postcode":"35014",
    "sg:province":"Las Palmas",
    "wof:name":"Yudaya S.l.",
    "wof:placetype":"venue"
},
  "geometry": {"coordinates":[-15.4260110855,28.1106700897],"type":"Point"}
}