{
  "type": "Feature",
  "properties": {
    "addr:full":"Carr Carme, 121 Almacelles Lleida 25100",
    "addr:housenumber":"121",
    "addr:postcode":"25100",
    "addr:street":"Carr Carme",
    "iso:country":"ES",
    "sg:address":"Carr Carme, 121",
    "sg:city":"Almacelles",
    "sg:orig_category":"Chapister\u00cda",
    "sg:phone":"+34 973 74 04 51",
    "sg:postcode":"25100",
    "sg:province":"Lleida",
    "wof:name":"Mur Gil Jose",
    "wof:placetype":"venue"
},
  "geometry": {"coordinates":[0.442907989,41.726940155],"type":"Point"}
}