{
  "type": "Feature",
  "properties": {
    "iso:country":"ES",
    "sg:address":"Calle de Vicente Regueral, 3",
    "sg:city":"Pola De Lena",
    "sg:orig_category":"Peluquer\u00cdas, Peluquer\u00cda Mixta",
    "sg:phone":"+34 985 49 70 89",
    "sg:postcode":"33630",
    "sg:province":"Asturias",
    "wof:name":"Nogueira Mota Marina",
    "wof:placetype":"venue"
},
  "geometry": {"coordinates":[-5.8276109695,43.1610641479],"type":"Point"}
}