{
  "type": "Feature",
  "properties": {
    "addr:full":"Av Tres-cents, 21 Castelldefels Barcelona 08860",
    "addr:housenumber":"21",
    "addr:postcode":"08860",
    "addr:street":"Av Tres-Cents",
    "iso:country":"ES",
    "sg:address":"Av Tres-cents, 21",
    "sg:city":"Castelldefels",
    "sg:orig_category":"Inmobiliaria (agencias)",
    "sg:phone":"+34 936 64 56 78",
    "sg:postcode":"08860",
    "sg:province":"Barcelona",
    "sg:website":"www.fincamontemar.com",
    "wof:name":"Fincas Montemar S. L.",
    "wof:placetype":"venue"
},
  "geometry": {"coordinates":[1.9278570414,41.2629699707],"type":"Point"}
}