{
  "type": "Feature",
  "properties": {
    "addr:full":"Calle de Candalija, 10 Zaragoza Zaragoza 50003",
    "addr:housenumber":"10",
    "addr:postcode":"50003",
    "addr:street":"Calle De Candalija",
    "iso:country":"ES",
    "sg:address":"Calle de Candalija, 10",
    "sg:city":"Zaragoza",
    "sg:orig_category":"Compraventa De Antig\u00dcedades",
    "sg:phone":"+34 976 29 68 67",
    "sg:postcode":"50003",
    "sg:province":"Zaragoza",
    "wof:name":"Garcia Gutierrez Manuel Juan",
    "wof:placetype":"venue"
},
  "geometry": {"coordinates":[-0.8816897869,41.6543693542],"type":"Point"}
}