{
  "type": "Feature",
  "properties": {
    "addr:full":"Moll Rellotge, S/n Barcelona Barcelona 08039",
    "addr:housenumber":"s / n",
    "addr:postcode":"08039",
    "addr:street":"Rellotge",
    "iso:country":"ES",
    "sg:address":"Moll Rellotge, S/n",
    "sg:city":"Barcelona",
    "sg:classifiers":[
        {
            "category":"Recreation",
            "type":"Entertainment"
        }
    ],
    "sg:phone":"+34 932 21 77 45",
    "sg:postcode":"08039",
    "sg:province":"Barcelona",
    "sg:tags":[
        "caza",
        "pr\u00c1ctica",
        "la",
        "de",
        "pesca",
        "y"
    ],
    "wof:name":"Cofradia De Pescadores De Barcelona",
    "wof:placetype":"venue"
},
  "geometry": {"coordinates":[2.1773600578,41.3800582886],"type":"Point"}
}