{
  "type": "Feature",
  "properties": {
    "addr:full":"Calle de Masustegi, 17 Bilbao Vizcaya 48006",
    "addr:housenumber":"17",
    "addr:postcode":"48006",
    "addr:street":"Calle De Masustegi",
    "iso:country":"ES",
    "sg:address":"Calle de Masustegi, 17",
    "sg:city":"Bilbao",
    "sg:orig_category":"Material Y Suministros Para Fotocopiadoras, Reprograf\u00cda",
    "sg:phone":"+34 944 79 05 44",
    "sg:postcode":"48006",
    "sg:province":"Vizcaya",
    "wof:name":"Lankidego Lantalde S. L.",
    "wof:placetype":"venue"
},
  "geometry": {"coordinates":[-2.9137470722,43.2572517395],"type":"Point"}
}