{
  "type": "Feature",
  "properties": {
    "addr:full":"Calle de Verdinal, 2 Cantalejo Segovia 40320",
    "addr:housenumber":"2",
    "addr:postcode":"40320",
    "addr:street":"Calle De Verdinal",
    "iso:country":"ES",
    "sg:address":"Calle de Verdinal, 2",
    "sg:city":"Cantalejo",
    "sg:orig_category":"Bares, Piano",
    "sg:phone":"+34 921 52 14 11",
    "sg:postcode":"40320",
    "sg:province":"Segovia",
    "wof:name":"Cb Tocamadera",
    "wof:placetype":"venue"
},
  "geometry": {"coordinates":[-3.9246349335,41.2573432922],"type":"Point"}
}