{
  "type": "Feature",
  "properties": {
    "iso:country":"ES",
    "sg:address":"Des Sol, 27",
    "sg:city":"Santanyi",
    "sg:orig_category":"Internados & Ense\u00d1anza Privada",
    "sg:phone":"+34 971 65 43 61",
    "sg:postcode":"07650",
    "sg:province":"Islas Baleares",
    "wof:name":"Colegio Obispo Vergel",
    "wof:placetype":"venue"
},
  "geometry": {"coordinates":[3.1274299622,39.3544082642],"type":"Point"}
}