{
  "type": "Feature",
  "properties": {
    "addr:full":"Muelle Raices, S/n Aviles Asturias 33408",
    "addr:housenumber":"s / n",
    "addr:postcode":"33408",
    "addr:street":"Raices",
    "iso:country":"ES",
    "sg:address":"Muelle Raices, S/n",
    "sg:city":"Aviles",
    "sg:orig_category":"Transportes Mar\u00cdtimos",
    "sg:phone":"+34 985 52 02 23",
    "sg:postcode":"33408",
    "sg:province":"Asturias",
    "wof:name":"Estibas Y Consignaciones Guixar S.a.",
    "wof:placetype":"venue"
},
  "geometry": {"coordinates":[-5.9211349487,43.5584754944],"type":"Point"}
}