{
  "type": "Feature",
  "properties": {
    "iso:country":"ES",
    "sg:address":"Calle de Alvaro Fernandez Suarez, 6",
    "sg:city":"Vegadeo",
    "sg:orig_category":"Electrodom\u00c9sticos (al Por Menor)",
    "sg:phone":"+34 985 47 66 26",
    "sg:postcode":"33770",
    "sg:province":"Asturias",
    "wof:name":"Villaveiran Fernandez Maria Dolores",
    "wof:placetype":"venue"
},
  "geometry": {"coordinates":[-7.0475239754,43.4644584656],"type":"Point"}
}