{
  "type": "Feature",
  "properties": {
    "addr:full":"Carrer de Gaiarre, 84 Barcelona Barcelona 08014",
    "addr:housenumber":"84",
    "addr:postcode":"08014",
    "addr:street":"Carrer De Gaiarre",
    "iso:country":"ES",
    "sg:address":"Carrer de Gaiarre, 84",
    "sg:city":"Barcelona",
    "sg:orig_category":"Molduras, Junquillos, Listones Y Molduras Perforadas",
    "sg:phone":"+34 933 31 38 88",
    "sg:postcode":"08014",
    "sg:province":"Barcelona",
    "wof:name":"Soluciones Integrales Hormargla Sl",
    "wof:placetype":"venue"
},
  "geometry": {"coordinates":[2.1410849094,41.3721656799],"type":"Point"}
}