{
  "type": "Feature",
  "properties": {
    "addr:full":"De La Plaza, 11 Iniesta Cuenca 16235",
    "addr:housenumber":"11",
    "addr:postcode":"16235",
    "iso:country":"ES",
    "sg:address":"De La Plaza, 11",
    "sg:city":"Iniesta",
    "sg:orig_category":"Perfumer\u00cda (al Por Menor)",
    "sg:phone":"+34 967 49 12 91",
    "sg:postcode":"16235",
    "sg:province":"Cuenca",
    "wof:name":"Perfumerias 2000 S.l.",
    "wof:placetype":"venue"
},
  "geometry": {"coordinates":[-1.7489440441,39.4435081482],"type":"Point"}
}