{
  "type": "Feature",
  "properties": {
    "iso:country":"ES",
    "sg:address":"Avda Isabel Ii De, 12",
    "sg:city":"Donostia-san Sebastian",
    "sg:orig_category":"Sales (al Por Mayor)",
    "sg:phone":"+34 943 46 76 46",
    "sg:postcode":"20011",
    "sg:province":"Guip\u00f9zcoa",
    "wof:name":"Herbomelisa S.l.",
    "wof:placetype":"venue"
},
  "geometry": {"coordinates":[-1.9769837856,43.3041267395],"type":"Point"}
}