{
  "type": "Feature",
  "properties": {
    "iso:country":"ES",
    "sg:address":"Pase San Nicolas De Francia, 3",
    "sg:city":"Calatayud",
    "sg:orig_category":"Sociedades, Compa\u00d1\u00cdas Aseguradoras",
    "sg:phone":"+34 976 88 70 40",
    "sg:postcode":"50300",
    "sg:province":"Zaragoza",
    "wof:name":"Ocaso S.a.compa\u00f1ia De Seguros Y Reaseguros",
    "wof:placetype":"venue"
},
  "geometry": {"coordinates":[-1.6387790442,41.3527488708],"type":"Point"}
}