{
  "type": "Feature",
  "properties": {
    "addr:full":"Calle de Vidal Lucas Cuadrado, 6 Badajoz Badajoz 06009",
    "addr:housenumber":"6",
    "addr:postcode":"06009",
    "addr:street":"Calle De Vidal Lucas Cuadrado",
    "iso:country":"ES",
    "sg:address":"Calle de Vidal Lucas Cuadrado, 6",
    "sg:city":"Badajoz",
    "sg:orig_category":"Carnicer\u00cdas, Carnicer\u00cdas",
    "sg:phone":"+34 924 24 03 54",
    "sg:postcode":"06009",
    "sg:province":"Badajoz",
    "wof:name":"Garcia Gomez Jose Manuel",
    "wof:placetype":"venue"
},
  "geometry": {"coordinates":[-6.9532718658,38.8694534302],"type":"Point"}
}