{
  "type": "Feature",
  "properties": {
    "addr:full":"Calle de Padre Manjon, 4 Elda Alicante 03600",
    "addr:housenumber":"4",
    "addr:postcode":"03600",
    "addr:street":"Calle De Padre Manjon",
    "iso:country":"ES",
    "sg:address":"Calle de Padre Manjon, 4",
    "sg:city":"Elda",
    "sg:orig_category":"Asesor\u00cda Sobre Comunicaci\u00d3n De Empresas",
    "sg:phone":"+34 965 38 26 88",
    "sg:postcode":"03600",
    "sg:province":"Alicante",
    "wof:name":"Asesoria Blamar S.l.",
    "wof:placetype":"venue"
},
  "geometry": {"coordinates":[-0.7954037189,38.4749984741],"type":"Point"}
}