{
  "type": "Feature",
  "properties": {
    "addr:full":"Calle de Etxegorri Kalea, 5 Erandio Vizcaya 48950",
    "addr:housenumber":"5",
    "addr:postcode":"48950",
    "addr:street":"Calle De Etxegorri Kalea",
    "iso:country":"ES",
    "sg:address":"Calle de Etxegorri Kalea, 5",
    "sg:city":"Erandio",
    "sg:orig_category":"Restaurantes",
    "sg:phone":"+34 944 67 55 54",
    "sg:postcode":"48950",
    "sg:province":"Vizcaya",
    "wof:name":"Degustacion Etxegorri",
    "wof:placetype":"venue"
},
  "geometry": {"coordinates":[-2.9841909409,43.3159828186],"type":"Point"}
}