{
  "type": "Feature",
  "properties": {
    "iso:country":"ES",
    "sg:address":"Los Olivos, 13",
    "sg:city":"Tomares",
    "sg:orig_category":"Alquiler De V\u00cddeo",
    "sg:phone":"+34 954 15 66 13",
    "sg:postcode":"41940",
    "sg:province":"Sevilla",
    "wof:name":"Guerrero Cabrera Maria Luisa",
    "wof:placetype":"venue"
},
  "geometry": {"coordinates":[-6.0459890366,37.3781700134],"type":"Point"}
}