{
  "type": "Feature",
  "properties": {
    "iso:country":"ES",
    "sg:address":"Ctra. Sant Carles, Km. 0009,0",
    "sg:city":"Sta. Eularia Riu",
    "sg:orig_category":"Mec\u00c1nico Del Autom\u00d3vil",
    "sg:phone":"+34 971 33 06 52",
    "sg:postcode":"07840",
    "sg:province":"Islas Baleares",
    "wof:name":"Taller Poll S.l.",
    "wof:placetype":"venue"
},
  "geometry": {"coordinates":[1.5341850519,38.9850311279],"type":"Point"}
}