{
  "type": "Feature",
  "properties": {
    "iso:country":"ES",
    "sg:address":"Avda. Arteixo, 80",
    "sg:city":"A Coru\u00f1a",
    "sg:orig_category":"Electricidad: Instaladores",
    "sg:phone":"+34 981 24 97 68",
    "sg:postcode":"15007",
    "sg:province":"La Coru\u00f1a",
    "wof:name":"Barreiro Gonzalez Juan",
    "wof:placetype":"venue"
},
  "geometry": {"coordinates":[-8.4135866165,43.3564949036],"type":"Point"}
}