{
  "type": "Feature",
  "properties": {
    "iso:country":"ES",
    "sg:address":"Psaj San Gregorio, 1",
    "sg:city":"Soria",
    "sg:orig_category":"Pescader\u00cdas (al Por Menor)",
    "sg:phone":"+34 975 23 17 30",
    "sg:postcode":"42002",
    "sg:province":"Soria",
    "wof:name":"Martin Lindo Jesus",
    "wof:placetype":"venue"
},
  "geometry": {"coordinates":[-2.4683389664,41.7678260803],"type":"Point"}
}