{
  "type": "Feature",
  "properties": {
    "iso:country":"ES",
    "sg:address":"Lago, 157",
    "sg:city":"Turon",
    "sg:orig_category":"Peluqueros: De Se\u00d1oras",
    "sg:phone":"+34 985 43 22 01",
    "sg:postcode":"33610",
    "sg:province":"Asturias",
    "wof:name":"Zapico Suarez Maria Del Carmen",
    "wof:placetype":"venue"
},
  "geometry": {"coordinates":[-5.9832577705,43.2504386902],"type":"Point"}
}