{
  "type": "Feature",
  "properties": {
    "addr:full":"Carrer de Campoamor, S/n Castell Bendinat Islas Baleares 07181",
    "addr:housenumber":"s / n",
    "addr:postcode":"07181",
    "addr:street":"Carrer De Campoamor",
    "iso:country":"ES",
    "sg:address":"Carrer de Campoamor, S/n",
    "sg:city":"Castell Bendinat",
    "sg:orig_category":"Restaurantes",
    "sg:phone":"+34 971 70 00 97",
    "sg:postcode":"07181",
    "sg:province":"Islas Baleares",
    "wof:name":"Nominacion S.l.",
    "wof:placetype":"venue"
},
  "geometry": {"coordinates":[2.5352098942,39.5245780945],"type":"Point"}
}