{
  "type": "Feature",
  "properties": {
    "addr:full":"Urb El Carril, 1 Busot Alicante 03111",
    "addr:housenumber":"1",
    "addr:postcode":"03111",
    "addr:street":"Urb El Carril",
    "iso:country":"ES",
    "sg:address":"Urb El Carril, 1",
    "sg:city":"Busot",
    "sg:orig_category":"Promotores Constructores",
    "sg:phone":"+34 965 97 52 64",
    "sg:postcode":"03111",
    "sg:province":"Alicante",
    "wof:name":"Macache S.l.",
    "wof:placetype":"venue"
},
  "geometry": {"coordinates":[-0.4268090129,38.4777984619],"type":"Point"}
}