{
  "type": "Feature",
  "properties": {
    "addr:full":"Calle de Sevilla, 13 Ejido Almer\u00eda 04700",
    "addr:housenumber":"13 ejido",
    "addr:postcode":"04700",
    "addr:street":"Calle De Sevilla;Almeri\u0301A",
    "iso:country":"ES",
    "sg:address":"Calle de Sevilla, 13",
    "sg:city":"Ejido",
    "sg:orig_category":"Fotocopias, Reprograf\u00cda",
    "sg:phone":"+34 950 57 11 77",
    "sg:postcode":"04700",
    "sg:province":"Almer\u00eda",
    "wof:name":"Medina Saez Marta",
    "wof:placetype":"venue"
},
  "geometry": {"coordinates":[-2.8166298866,36.7723312378],"type":"Point"}
}