{
  "type": "Feature",
  "properties": {
    "addr:full":"Calle de Era, S/n Pobladura De Aliste Zamora 49522",
    "addr:housenumber":"s / n",
    "addr:postcode":"49522",
    "addr:street":"Calle De Era;Zamora",
    "iso:country":"ES",
    "sg:address":"Calle de Era, S/n",
    "sg:city":"Pobladura De Aliste",
    "sg:orig_category":"Escayola Y Productos De Escayola (fabricaci\u00d3n, Al Por Mayor)",
    "sg:phone":"+34 980 68 35 31",
    "sg:postcode":"49522",
    "sg:province":"Zamora",
    "wof:name":"Sanabria Vara Miguel",
    "wof:placetype":"venue"
},
  "geometry": {"coordinates":[-6.3315138817,41.848651886],"type":"Point"}
}