{
  "type": "Feature",
  "properties": {
    "iso:country":"ES",
    "sg:address":"Plaz Ramon Benito Ace\u00d1a, 3",
    "sg:city":"Soria",
    "sg:orig_category":"Perfumer\u00cda (al Por Menor)",
    "sg:phone":"+34 975 22 73 02",
    "sg:postcode":"42002",
    "sg:province":"Soria",
    "wof:name":"Ruiz Borque Pablo",
    "wof:placetype":"venue"
},
  "geometry": {"coordinates":[-2.4683339596,41.7645225525],"type":"Point"}
}