{
  "type": "Feature",
  "properties": {
    "addr:full":"Calle de Carmelo Etxegarai, 2 Donostia-san Sebastian Guip\u00f9zcoa 20018",
    "addr:housenumber":"2",
    "addr:postcode":"20018",
    "addr:street":"Calle De Carmelo Etxegarai",
    "iso:country":"ES",
    "sg:address":"Calle de Carmelo Etxegarai, 2",
    "sg:city":"Donostia-san Sebastian",
    "sg:orig_category":"Agencias De Viajes",
    "sg:phone":"+34 943 31 35 26",
    "sg:postcode":"20018",
    "sg:province":"Guip\u00f9zcoa",
    "sg:website":"www.viajeseroski.es",
    "wof:name":"Viajes Eroski S.a.",
    "wof:placetype":"venue"
},
  "geometry": {"coordinates":[-2.0055999756,43.3118171692],"type":"Point"}
}