{
  "type": "Feature",
  "properties": {
    "addr:full":"Crri Esparza, 104 Arboleja Murcia 30009",
    "addr:housenumber":"104",
    "addr:postcode":"30009",
    "addr:street":"Esparza",
    "iso:country":"ES",
    "sg:address":"Crri Esparza, 104",
    "sg:city":"Arboleja",
    "sg:orig_category":"Retoques De Vestidos",
    "sg:phone":"+34 968 29 87 45",
    "sg:postcode":"30009",
    "sg:province":"Murcia",
    "wof:name":"Composturas Del Segura S.l",
    "wof:placetype":"venue"
},
  "geometry": {"coordinates":[-1.1528439522,37.9883460999],"type":"Point"}
}