{
  "type": "Feature",
  "properties": {
    "iso:country":"ES",
    "sg:address":"La Magdalena, 9",
    "sg:city":"Naredo Fenar",
    "sg:orig_category":"Ferreter\u00cda Artesanal",
    "sg:phone":"+34 987 59 10 11",
    "sg:postcode":"24839",
    "sg:province":"Le\u00f3n",
    "wof:name":"Gonzalez Porto Saul",
    "wof:placetype":"venue"
},
  "geometry": {"coordinates":[-5.506729126,42.8396606445],"type":"Point"}
}