{
  "type": "Feature",
  "properties": {
    "addr:full":"Rua Coru\u00d1a, 27 Vigo Pontevedra 36208",
    "addr:housenumber":"27",
    "addr:postcode":"36208",
    "addr:street":"Rua Corun\u0303A",
    "iso:country":"ES",
    "sg:address":"Rua Coru\u00d1a, 27",
    "sg:city":"Vigo",
    "sg:orig_category":"Distribuci\u00d3n De Petr\u00d3leo Y Derivados",
    "sg:phone":"+34 986 20 00 95",
    "sg:postcode":"36208",
    "sg:province":"Pontevedra",
    "wof:name":"Franjopesca S.l.",
    "wof:placetype":"venue"
},
  "geometry": {"coordinates":[-8.7366504669,42.2252159119],"type":"Point"}
}