{
  "type": "Feature",
  "properties": {
    "addr:full":"Calle de Fermin Calbeton, 5 Donostia-san Sebastian Guip\u00f9zcoa 20003",
    "addr:housenumber":"5",
    "addr:postcode":"20003",
    "addr:street":"Calle De Fermin Calbeton",
    "iso:country":"ES",
    "sg:address":"Calle de Fermin Calbeton, 5",
    "sg:city":"Donostia-san Sebastian",
    "sg:orig_category":"Camas (al Por Menor)",
    "sg:phone":"+34 943 43 04 70",
    "sg:postcode":"20003",
    "sg:province":"Guip\u00f9zcoa",
    "wof:name":"Inchausti Gonzalez Jose Antonio",
    "wof:placetype":"venue"
},
  "geometry": {"coordinates":[-1.983438015,43.3233261108],"type":"Point"}
}