{
  "type": "Feature",
  "properties": {
    "addr:full":"Calle de Huesca, 2 Guadalajara Guadalajara 19005",
    "addr:housenumber":"2",
    "addr:postcode":"19005",
    "addr:street":"Calle De Huesca",
    "iso:country":"ES",
    "sg:address":"Calle de Huesca, 2",
    "sg:city":"Guadalajara",
    "sg:orig_category":"Agentes Generales De Seguros",
    "sg:phone":"+34 949 21 72 70",
    "sg:postcode":"19005",
    "sg:province":"Guadalajara",
    "wof:name":"Alcazar Alda Alfonso",
    "wof:placetype":"venue"
},
  "geometry": {"coordinates":[-3.1544103622,40.6351928711],"type":"Point"}
}