{
  "type": "Feature",
  "properties": {
    "addr:full":"Plaz Salvador El, 2 Santa Rosalia-maqueda M\u00e1laga 29591",
    "addr:postcode":"29591",
    "addr:street":"El;Santa;Ma\u0301Laga",
    "iso:country":"ES",
    "sg:address":"Plaz Salvador El, 2",
    "sg:city":"Santa Rosalia-maqueda",
    "sg:orig_category":"Alquiler De V\u00cddeo",
    "sg:phone":"+34 952 43 46 98",
    "sg:postcode":"29591",
    "sg:province":"M\u00e1laga",
    "wof:name":"Mora Ortiz Francisco",
    "wof:placetype":"venue"
},
  "geometry": {"coordinates":[-4.542953968,36.7268447876],"type":"Point"}
}