{
  "type": "Feature",
  "properties": {
    "addr:full":"C/ Sant Ramon, 117 Cerdanyola Valles Barcelona 08290",
    "addr:housenumber":"117",
    "addr:postcode":"08290",
    "addr:street":"C / Sant Ramon;Valles Barcelona",
    "iso:country":"ES",
    "sg:address":"C/ Sant Ramon, 117",
    "sg:city":"Cerdanyola Valles",
    "sg:orig_category":"Ropa Para Se\u00d1oras (al Por Menor)",
    "sg:phone":"+34 935 80 59 91",
    "sg:postcode":"08290",
    "sg:province":"Barcelona",
    "wof:name":"Il Termometro Moda S.l.",
    "wof:placetype":"venue"
},
  "geometry": {"coordinates":[2.1470150948,41.4924812317],"type":"Point"}
}