{
  "type": "Feature",
  "properties": {
    "iso:country":"ES",
    "sg:address":"Luga Faramontaos, S/n",
    "sg:city":"Faramontaos",
    "sg:orig_category":"Agricultores, Agricultores",
    "sg:phone":"+34 988 40 85 33",
    "sg:postcode":"32637",
    "sg:province":"Ourense",
    "wof:name":"Cooperativa Agroganadera La Piuca Ii",
    "wof:placetype":"venue"
},
  "geometry": {"coordinates":[-7.7096171379,42.0376586914],"type":"Point"}
}