{
  "type": "Feature",
  "properties": {
    "addr:full":"Calle de Rastrojo, 1 Valladolid Valladolid 47014",
    "addr:housenumber":"1",
    "addr:postcode":"47014",
    "addr:street":"Calle De Rastrojo",
    "iso:country":"ES",
    "sg:address":"Calle de Rastrojo, 1",
    "sg:city":"Valladolid",
    "sg:orig_category":"Peluqueros: De Se\u00d1oras",
    "sg:phone":"+34 983 34 49 80",
    "sg:postcode":"47014",
    "sg:province":"Valladolid",
    "wof:name":"Studio Model Look S.l.",
    "wof:placetype":"venue"
},
  "geometry": {"coordinates":[-4.7448687553,41.6502838135],"type":"Point"}
}