{
  "type": "Feature",
  "properties": {
    "iso:country":"ES",
    "sg:address":"Carretera Cordoba-valencia, Km. 0226,0",
    "sg:city":"Puente Genave",
    "sg:orig_category":"Material Y Herramientas Agr\u00cdcolas",
    "sg:phone":"+34 953 43 53 29",
    "sg:postcode":"23350",
    "sg:province":"Ja\u00e9n",
    "wof:name":"Valiente Pe\u00f1a Juan",
    "wof:placetype":"venue"
},
  "geometry": {"coordinates":[-2.8030788898,38.3562431335],"type":"Point"}
}