{
  "type": "Feature",
  "properties": {
    "iso:country":"ES",
    "sg:address":"Avda Simon Bolivar, S/n",
    "sg:city":"Malaga",
    "sg:orig_category":"Comercio De Cuadros, L\u00c1minas Y Reproducciones De Obras De Arte",
    "sg:phone":"+34 952 39 55 12",
    "sg:postcode":"29011",
    "sg:province":"M\u00e1laga",
    "wof:name":"Infantes Cortes Antonia",
    "wof:placetype":"venue"
},
  "geometry": {"coordinates":[-4.4335756302,36.7331809998],"type":"Point"}
}