{
  "type": "Feature",
  "properties": {
    "iso:country":"ES",
    "sg:address":"Carrer de Julia Alvarez, 1",
    "sg:city":"Palma",
    "sg:orig_category":"Alquiler De V\u00cddeo",
    "sg:phone":"+34 971 75 70 68",
    "sg:postcode":"07004",
    "sg:province":"Islas Baleares",
    "wof:name":"Astaiza Zu\u00d1iga Niyireth",
    "wof:placetype":"venue"
},
  "geometry": {"coordinates":[2.6540570259,39.5798149109],"type":"Point"}
}