{
  "type": "Feature",
  "properties": {
    "addr:full":"Calle de Gonzalez Garbin, 21 Almeria Almer\u00eda 04001",
    "addr:housenumber":"21",
    "addr:postcode":"04001",
    "addr:street":"Calle De Gonzalez Garbin",
    "iso:country":"ES",
    "sg:address":"Calle de Gonzalez Garbin, 21",
    "sg:city":"Almeria",
    "sg:orig_category":"Cajas Para Embalar",
    "sg:phone":"+34 950 28 16 71",
    "sg:postcode":"04001",
    "sg:province":"Almer\u00eda",
    "wof:name":"Cajamar",
    "wof:placetype":"venue"
},
  "geometry": {"coordinates":[-2.4616470337,36.84116745],"type":"Point"}
}