{
  "type": "Feature",
  "properties": {
    "addr:full":"Calle de Urbano Gonzalez Serrano, 65 Navalmoral Mata C\u00e1ceres 10300",
    "addr:housenumber":"65",
    "addr:postcode":"10300",
    "addr:street":"Calle De Urbano Gonzalez Serrano;Ca\u0301Ceres",
    "iso:country":"ES",
    "sg:address":"Calle de Urbano Gonzalez Serrano, 65",
    "sg:city":"Navalmoral Mata",
    "sg:orig_category":"Promotores Constructores",
    "sg:phone":"+34 927 53 06 07",
    "sg:postcode":"10300",
    "sg:province":"C\u00e1ceres",
    "sg:website":"www.areacyo.com",
    "wof:name":"Area Cyo S.a.",
    "wof:placetype":"venue"
},
  "geometry": {"coordinates":[-5.5437598228,39.8914260864],"type":"Point"}
}