{
  "type": "Feature",
  "properties": {
    "addr:full":"Calle de Dunas (las), 18 Cabezo Santa Cruz De Tenerife 38612",
    "addr:housenumber":"18",
    "addr:postcode":"38612",
    "addr:street":"Calle De Dunas Las",
    "iso:country":"ES",
    "sg:address":"Calle de Dunas (las), 18",
    "sg:city":"Cabezo",
    "sg:orig_category":"Arquitectos",
    "sg:phone":"+34 922 17 73 39",
    "sg:postcode":"38612",
    "sg:province":"Santa Cruz De Tenerife",
    "wof:name":"Chinea Arteaga Carlos Javier",
    "wof:placetype":"venue"
},
  "geometry": {"coordinates":[-16.2548561096,28.4698104858],"type":"Point"}
}