{
  "type": "Feature",
  "properties": {
    "iso:country":"ES",
    "sg:address":"Calle de Escolta Real, 12",
    "sg:city":"Donostia-san Sebastian",
    "sg:orig_category":"Centros De Educaci\u00d3n Especial",
    "sg:phone":"+34 943 21 73 24",
    "sg:postcode":"20008",
    "sg:province":"Guip\u00f9zcoa",
    "wof:name":"Gobierno Vasco-delegacion Territorial De Educacion",
    "wof:placetype":"venue"
},
  "geometry": {"coordinates":[-2.0015799999,43.3129234314],"type":"Point"}
}