{
  "type": "Feature",
  "properties": {
    "iso:country":"ES",
    "sg:address":"C/ Torres Quevedo, 63",
    "sg:city":"Elche",
    "sg:orig_category":"Electricidad: Instaladores",
    "sg:phone":"+34 966 63 58 02",
    "sg:postcode":"03204",
    "sg:province":"Alicante",
    "wof:name":"Electro Maquinaria Ilicitana S.l.",
    "wof:placetype":"venue"
},
  "geometry": {"coordinates":[-0.7067790031,38.2599143982],"type":"Point"}
}