{
  "type": "Feature",
  "properties": {
    "iso:country":"ES",
    "sg:address":"Carrer de Quarter De Simancas, 24",
    "sg:city":"Barcelona",
    "sg:orig_category":"Farmacias",
    "sg:phone":"+34 933 54 74 27",
    "sg:postcode":"08042",
    "sg:province":"Barcelona",
    "wof:name":"Farmacia Carrio Diaz S.c.p.",
    "wof:placetype":"venue"
},
  "geometry": {"coordinates":[2.1756839752,41.4456443787],"type":"Point"}
}