{
  "type": "Feature",
  "properties": {
    "addr:full":"Calle de Santa Clara, 24 Zamora Zamora 49014",
    "addr:housenumber":"24",
    "addr:postcode":"49014",
    "addr:street":"Calle De Santa Clara",
    "iso:country":"ES",
    "sg:address":"Calle de Santa Clara, 24",
    "sg:city":"Zamora",
    "sg:orig_category":"Prot\u00c9sicos Dentales",
    "sg:phone":"+34 980 51 91 00",
    "sg:postcode":"49014",
    "sg:province":"Zamora",
    "wof:name":"Perez-moro Rodriguez Francisco",
    "wof:placetype":"venue"
},
  "geometry": {"coordinates":[-5.7429089546,41.5062255859],"type":"Point"}
}