{
  "type": "Feature",
  "properties": {
    "iso:country":"ES",
    "sg:address":"Calle de Luis Armi\u00d1an, S/n",
    "sg:city":"Nava",
    "sg:orig_category":"Quincaller\u00cda (al Por Menor)",
    "sg:phone":"+34 985 71 61 04",
    "sg:postcode":"33529",
    "sg:province":"Asturias",
    "wof:name":"Ferreteria Honorio S.l",
    "wof:placetype":"venue"
},
  "geometry": {"coordinates":[-5.5052242279,43.3586730957],"type":"Point"}
}