{
  "type": "Feature",
  "properties": {
    "iso:country":"ES",
    "sg:address":"Avgd Prat De La Riba, 33",
    "sg:city":"Lleida",
    "sg:orig_category":"M\u00c9dicos: Cirug\u00cda Urol\u00d3gica",
    "sg:phone":"+34 973 24 34 13",
    "sg:postcode":"25008",
    "sg:province":"Lleida",
    "wof:name":"Torrente Castro Federico",
    "wof:placetype":"venue"
},
  "geometry": {"coordinates":[0.6231639981,41.6208457947],"type":"Point"}
}