{
  "type": "Feature",
  "properties": {
    "iso:country":"ES",
    "sg:address":"Carrer de Dalia, 38",
    "sg:city":"Barcelona",
    "sg:orig_category":"Sales (al Por Mayor)",
    "sg:phone":"+34 932 89 20 80",
    "sg:postcode":"08004",
    "sg:province":"Barcelona",
    "wof:name":"M.k. Alcon Food Marketing S.l.",
    "wof:placetype":"venue"
},
  "geometry": {"coordinates":[2.1452479362,41.3698425293],"type":"Point"}
}