{
  "type": "Feature",
  "properties": {
    "addr:full":"Calle de Valencia, 4 Torviscas Bajo Santa Cruz De Tenerife 38660",
    "addr:housenumber":"4",
    "addr:postcode":"38660",
    "addr:street":"Calle De Valencia",
    "iso:country":"ES",
    "sg:address":"Calle de Valencia, 4",
    "sg:city":"Torviscas Bajo",
    "sg:orig_category":"Supermercados Y Hipermercados",
    "sg:phone":"+34 922 71 45 73",
    "sg:postcode":"38660",
    "sg:province":"Santa Cruz De Tenerife",
    "wof:name":"Dinosol Supermercados S.l.",
    "wof:placetype":"venue"
},
  "geometry": {"coordinates":[-16.2645397186,28.4603843689],"type":"Point"}
}