{
  "type": "Feature",
  "properties": {
    "iso:country":"ES",
    "sg:address":"Carr Pi Margall, 57",
    "sg:city":"Palafrugell",
    "sg:orig_category":"Supermercados Y Hipermercados",
    "sg:phone":"+34 972 30 05 89",
    "sg:postcode":"17200",
    "sg:province":"Girona",
    "wof:name":"Oller Riembau Pedro",
    "wof:placetype":"venue"
},
  "geometry": {"coordinates":[3.1645410061,41.9190711975],"type":"Point"}
}