{
  "type": "Feature",
  "properties": {
    "addr:full":"Carrer de Aurora, 19 Premia Mar Barcelona 08330",
    "addr:housenumber":"19",
    "addr:postcode":"08330",
    "addr:street":"Carrer De Aurora",
    "iso:country":"ES",
    "sg:address":"Carrer de Aurora, 19",
    "sg:city":"Premia Mar",
    "sg:orig_category":"Electricidad: Instaladores",
    "sg:phone":"+34 937 51 18 05",
    "sg:postcode":"08330",
    "sg:province":"Barcelona",
    "wof:name":"Nicolau Ribera Jose",
    "wof:placetype":"venue"
},
  "geometry": {"coordinates":[2.3581829071,41.490940094],"type":"Point"}
}