{
  "type": "Feature",
  "properties": {
    "iso:country":"ES",
    "sg:address":"C/ Pou Florit, 94",
    "sg:city":"Porreres",
    "sg:orig_category":"Supermercados Y Hipermercados",
    "sg:phone":"+34 971 16 80 94",
    "sg:postcode":"07260",
    "sg:province":"Islas Baleares",
    "wof:name":"Insular General Alimentaria S.a.",
    "wof:placetype":"venue"
},
  "geometry": {"coordinates":[3.0255799294,39.5142097473],"type":"Point"}
}