{
  "type": "Feature",
  "properties": {
    "addr:full":"Ctra. Madrid-irun, S/n Madrigalejo Monte Burgos 09390",
    "addr:housenumber":"s / n",
    "addr:postcode":"09390",
    "addr:street":"Ctra. Madrid-Irun",
    "iso:country":"ES",
    "sg:address":"Ctra. Madrid-irun, S/n",
    "sg:city":"Madrigalejo Monte",
    "sg:orig_category":"Material Y Herramientas Agr\u00cdcolas",
    "sg:phone":"+34 947 17 31 17",
    "sg:postcode":"09390",
    "sg:province":"Burgos",
    "wof:name":"Maquinaria Agricola Revilla S.l.",
    "wof:placetype":"venue"
},
  "geometry": {"coordinates":[-3.720361948,42.0803222656],"type":"Point"}
}