{
  "type": "Feature",
  "properties": {
    "iso:country":"ES",
    "sg:address":"Carrer de Sant Miquel, 41",
    "sg:city":"Esparreguera",
    "sg:orig_category":"Comercio, Reparaci\u00d3n De Motocicletas, Bicicletas Y Piezas Sueltas",
    "sg:phone":"+34 937 77 57 75",
    "sg:postcode":"08292",
    "sg:province":"Barcelona",
    "wof:name":"Arcas Arcas Magdalena",
    "wof:placetype":"venue"
},
  "geometry": {"coordinates":[1.8696503639,41.5362472534],"type":"Point"}
}