{
  "type": "Feature",
  "properties": {
    "iso:country":"ES",
    "sg:address":"Plaz Temple (el), S/n",
    "sg:city":"Ponferrada",
    "sg:orig_category":"Seguridad Social",
    "sg:phone":"+34 987 40 95 01",
    "sg:postcode":"24400",
    "sg:province":"Le\u00f3n",
    "sg:website":"www.fremap.es",
    "wof:name":"Fremap Mutua De Accidentes De Trabajo Y Enferm.profes.de S.s.61",
    "wof:placetype":"venue"
},
  "geometry": {"coordinates":[-6.5918879509,42.5430908203],"type":"Point"}
}