{
  "type": "Feature",
  "properties": {
    "addr:full":"Carrer de Avila, 129 Barcelona Barcelona 08018",
    "addr:housenumber":"129",
    "addr:postcode":"08018",
    "addr:street":"Carrer De Avila",
    "iso:country":"ES",
    "sg:address":"Carrer de Avila, 129",
    "sg:city":"Barcelona",
    "sg:orig_category":"Papeler\u00cdas: Art\u00cdculos (al Por Mayor)",
    "sg:phone":"+34 933 00 55 11",
    "sg:postcode":"08018",
    "sg:province":"Barcelona",
    "sg:website":"www.noguerayvintro.com",
    "wof:name":"Noguera Y Vintro S. A.",
    "wof:placetype":"venue"
},
  "geometry": {"coordinates":[2.1915829182,41.3996543884],"type":"Point"}
}