{
  "type": "Feature",
  "properties": {
    "iso:country":"ES",
    "sg:address":"Calle de Guridi, 7",
    "sg:city":"Chopera",
    "sg:orig_category":"Ingenier\u00cda, Centros De Estudios (industria)",
    "sg:phone":"+34 916 40 61 72",
    "sg:postcode":"28230",
    "sg:province":"Madrid",
    "sg:website":"www.alceingenieria.net",
    "wof:name":"Alce Ingenieria S.l.",
    "wof:placetype":"venue"
},
  "geometry": {"coordinates":[-3.9064950943,40.5056343079],"type":"Point"}
}