{
  "type": "Feature",
  "properties": {
    "addr:full":"Calle de Condes De Crespo Rascon, 35 Salamanca Salamanca 37002",
    "addr:housenumber":"35",
    "addr:postcode":"37002",
    "addr:street":"Calle De Condes De Crespo Rascon",
    "iso:country":"ES",
    "sg:address":"Calle de Condes De Crespo Rascon, 35",
    "sg:city":"Salamanca",
    "sg:orig_category":"Agentes De Seguros",
    "sg:phone":"+34 923 21 75 00",
    "sg:postcode":"37002",
    "sg:province":"Salamanca",
    "wof:name":"Luis Nieto Y B.g. S.l.",
    "wof:placetype":"venue"
},
  "geometry": {"coordinates":[-5.6649365425,40.9685821533],"type":"Point"}
}