{
  "type": "Feature",
  "properties": {
    "addr:full":"Rua Pablo Iglesias, 3 Boiro La Coru\u00f1a 15930",
    "addr:housenumber":"3",
    "addr:postcode":"15930",
    "addr:street":"Rua Pablo Iglesias;La Corun\u0303A",
    "iso:country":"ES",
    "sg:address":"Rua Pablo Iglesias, 3",
    "sg:city":"Boiro",
    "sg:orig_category":"Peluqueros: De Se\u00d1oras",
    "sg:phone":"+34 981 84 49 04",
    "sg:postcode":"15930",
    "sg:province":"La Coru\u00f1a",
    "wof:name":"Outeiral Miguez Maria Dolores",
    "wof:placetype":"venue"
},
  "geometry": {"coordinates":[-8.8857870102,42.6459732056],"type":"Point"}
}