{
  "type": "Feature",
  "properties": {
    "addr:full":"Pase Chopera (de La), 176 Alcobendas Madrid 28100",
    "addr:housenumber":"176",
    "addr:postcode":"28100",
    "addr:street":"Alcobendas",
    "iso:country":"ES",
    "sg:address":"Pase Chopera (de La), 176",
    "sg:city":"Alcobendas",
    "sg:orig_category":"Zapatos (al Por Menor)",
    "sg:phone":"+34 916 61 08 49",
    "sg:postcode":"28100",
    "sg:province":"Madrid",
    "wof:name":"Sanz Iglesias Pilar",
    "wof:placetype":"venue"
},
  "geometry": {"coordinates":[-3.6568140984,40.5451583862],"type":"Point"}
}