{
  "type": "Feature",
  "properties": {
    "addr:full":"Calle de Rio De La Plata, 24 Talavera Reina Toledo 45600",
    "addr:housenumber":"24",
    "addr:postcode":"45600",
    "addr:street":"Calle De Rio De La Plata",
    "iso:country":"ES",
    "sg:address":"Calle de Rio De La Plata, 24",
    "sg:city":"Talavera Reina",
    "sg:orig_category":"Agentes Generales De Seguros",
    "sg:phone":"+34 925 81 19 37",
    "sg:postcode":"45600",
    "sg:province":"Toledo",
    "wof:name":"Blanco Illan Maria Blanca",
    "wof:placetype":"venue"
},
  "geometry": {"coordinates":[-4.815928936,39.9671287537],"type":"Point"}
}