{
  "type": "Feature",
  "properties": {
    "iso:country":"ES",
    "sg:address":"Calle de Cuenca, 10",
    "sg:city":"Utebo",
    "sg:orig_category":"Mec\u00c1nico Del Autom\u00d3vil",
    "sg:phone":"+34 976 77 05 85",
    "sg:postcode":"50180",
    "sg:province":"Zaragoza",
    "wof:name":"Embid Guillen Angel",
    "wof:placetype":"venue"
},
  "geometry": {"coordinates":[-0.9974070191,41.7116622925],"type":"Point"}
}