{
  "type": "Feature",
  "properties": {
    "addr:full":"Plaza, 49 Ferreries Islas Baleares 07750",
    "addr:housenumber":"49",
    "addr:postcode":"07750",
    "iso:country":"ES",
    "sg:address":"Plaza, 49",
    "sg:city":"Ferreries",
    "sg:orig_category":"Administraciones Regionales, Departamentales Y Locales",
    "sg:phone":"+34 971 37 30 03",
    "sg:postcode":"07750",
    "sg:province":"Islas Baleares",
    "sg:website":"www.ajferreries.org",
    "wof:name":"Ajuntament De Ferreries",
    "wof:placetype":"venue"
},
  "geometry": {"coordinates":[3.9980485439,39.9843063354],"type":"Point"}
}