{
  "type": "Feature",
  "properties": {
    "addr:full":"Rua Reis Magos, 40 Domiron La Coru\u00f1a 15570",
    "addr:housenumber":"40",
    "addr:postcode":"15570",
    "addr:street":"Rua Reis Magos;La Corun\u0303A",
    "iso:country":"ES",
    "sg:address":"Rua Reis Magos, 40",
    "sg:city":"Domiron",
    "sg:orig_category":"Inmobiliaria (agencias)",
    "sg:phone":"+34 981 39 30 28",
    "sg:postcode":"15570",
    "sg:province":"La Coru\u00f1a",
    "wof:name":"G Y R San Marcos S.l.",
    "wof:placetype":"venue"
},
  "geometry": {"coordinates":[-8.1647539139,43.5165405273],"type":"Point"}
}