{
  "type": "Feature",
  "properties": {
    "addr:full":"Av Baro, 15 Barcelona Barcelona 08024",
    "addr:housenumber":"15",
    "addr:postcode":"08024",
    "addr:street":"Av Baro",
    "iso:country":"ES",
    "sg:address":"Av Baro, 15",
    "sg:city":"Barcelona",
    "sg:orig_category":"Pescader\u00cdas (al Por Menor)",
    "sg:phone":"+34 932 84 57 58",
    "sg:postcode":"08024",
    "sg:province":"Barcelona",
    "wof:name":"Oliva Vidal Maria De Los Angeles",
    "wof:placetype":"venue"
},
  "geometry": {"coordinates":[2.1611959934,41.4155845642],"type":"Point"}
}