{
  "type": "Feature",
  "properties": {
    "addr:full":"Avda Cruz Roja Espa\u00d1ola (de La), S/n Cuenca Cuenca 16002",
    "addr:housenumber":"/ n",
    "addr:postcode":"16002",
    "addr:street":"Avda Cruz Roja Espan\u0303Ola De La S",
    "iso:country":"ES",
    "sg:address":"Avda Cruz Roja Espa\u00d1ola (de La), S/n",
    "sg:city":"Cuenca",
    "sg:orig_category":"Transporte En General",
    "sg:phone":"+34 969 22 51 11",
    "sg:postcode":"16002",
    "sg:province":"Cuenca",
    "wof:name":"Hermanos Belinchon S.a.",
    "wof:placetype":"venue"
},
  "geometry": {"coordinates":[-2.1614289284,40.0741081238],"type":"Point"}
}