{
  "type": "Feature",
  "properties": {
    "addr:full":"Calle de Jorge Juan, 10 Alacant Alicante 03002",
    "addr:housenumber":"10",
    "addr:postcode":"03002",
    "addr:street":"Calle De Jorge Juan",
    "iso:country":"ES",
    "sg:address":"Calle de Jorge Juan, 10",
    "sg:city":"Alacant",
    "sg:orig_category":"Centros Empresariales",
    "sg:phone":"+34 965 14 12 81",
    "sg:postcode":"03002",
    "sg:province":"Alicante",
    "wof:name":"Prosant Multiservicios S.l.",
    "wof:placetype":"venue"
},
  "geometry": {"coordinates":[-0.4796609879,38.3456878662],"type":"Point"}
}