{
  "type": "Feature",
  "properties": {
    "addr:full":"Barranco Manzano, S/n Torrox-costa M\u00e1laga 29793",
    "addr:housenumber":"s",
    "addr:postcode":"29793",
    "addr:street":"/ N Torrox-Costa Ma\u0301Laga",
    "iso:country":"ES",
    "sg:address":"Barranco Manzano, S/n",
    "sg:city":"Torrox-costa",
    "sg:orig_category":"Flores Y Plantas Naturales (al Por Mayor)",
    "sg:phone":"+34 952 53 21 56",
    "sg:postcode":"29793",
    "sg:province":"M\u00e1laga",
    "wof:name":"Semilleros Saliplant S.l.",
    "wof:placetype":"venue"
},
  "geometry": {"coordinates":[-3.9633140564,36.7310066223],"type":"Point"}
}