{
  "type": "Feature",
  "properties": {
    "addr:full":"Pg Terraple, 32 Molins Rei Barcelona 08750",
    "addr:housenumber":"32",
    "addr:postcode":"08750",
    "addr:street":"Pg Terraple;Barcelona",
    "iso:country":"ES",
    "sg:address":"Pg Terraple, 32",
    "sg:city":"Molins Rei",
    "sg:orig_category":"Electrodom\u00c9sticos (al Por Menor)",
    "sg:phone":"+34 936 68 81 00",
    "sg:postcode":"08750",
    "sg:province":"Barcelona",
    "wof:name":"Electro Galery S.l.",
    "wof:placetype":"venue"
},
  "geometry": {"coordinates":[2.0155420303,41.4118843079],"type":"Point"}
}