{
  "type": "Feature",
  "properties": {
    "addr:full":"Calle de Moral De La Magdalena, 22 Granada Granada 18002",
    "addr:housenumber":"22",
    "addr:postcode":"18002",
    "addr:street":"Calle De Moral De La Magdalena",
    "iso:country":"ES",
    "sg:address":"Calle de Moral De La Magdalena, 22",
    "sg:city":"Granada",
    "sg:orig_category":"Peluquer\u00cdas, Peluquer\u00cda Mixta",
    "sg:phone":"+34 958 52 15 98",
    "sg:postcode":"18002",
    "sg:province":"Granada",
    "wof:name":"Militao Tavares Nunes",
    "wof:placetype":"venue"
},
  "geometry": {"coordinates":[-3.6027851105,37.1735725403],"type":"Point"}
}