{
  "type": "Feature",
  "properties": {
    "iso:country":"ES",
    "sg:address":"Calle de Argentina, S/n",
    "sg:city":"Alcala Henares",
    "sg:orig_category":"Maquinaria Para Industrias Diversas",
    "sg:phone":"+34 918 02 00 05",
    "sg:postcode":"28806",
    "sg:province":"Madrid",
    "wof:name":"Vol Rental S.a.",
    "wof:placetype":"venue"
},
  "geometry": {"coordinates":[-3.3964090347,40.4961357117],"type":"Point"}
}