{
  "type": "Feature",
  "properties": {
    "addr:full":"Calle de Manzanilla, 20 Chucena Huelva 21891",
    "addr:housenumber":"20",
    "addr:postcode":"21891",
    "addr:street":"Calle De Manzanilla",
    "iso:country":"ES",
    "sg:address":"Calle de Manzanilla, 20",
    "sg:city":"Chucena",
    "sg:orig_category":"Farmacias",
    "sg:phone":"+34 959 42 41 07",
    "sg:postcode":"21891",
    "sg:province":"Huelva",
    "wof:name":"Lopez Lopez Francisca Maria",
    "wof:placetype":"venue"
},
  "geometry": {"coordinates":[-6.3941655159,37.3624267578],"type":"Point"}
}