{
  "type": "Feature",
  "properties": {
    "addr:full":"Carrer de Sant Magi (de), 10 Tarragona Tarragona 43004",
    "addr:housenumber":"10",
    "addr:postcode":"43004",
    "addr:street":"Carrer De Sant Magi De",
    "iso:country":"ES",
    "sg:address":"Carrer de Sant Magi (de), 10",
    "sg:city":"Tarragona",
    "sg:orig_category":"Delegados, Agentes De Tr\u00c1nsito, Auxiliares De Transporte Internacional",
    "sg:phone":"+34 977 22 15 01",
    "sg:postcode":"43004",
    "sg:province":"Tarragona",
    "wof:name":"Urdi-trans S.l.",
    "wof:placetype":"venue"
},
  "geometry": {"coordinates":[1.2497819662,41.1125717163],"type":"Point"}
}