{
  "type": "Feature",
  "properties": {
    "addr:full":"Carrer de Ceramica, 33 Garriga Barcelona 08530",
    "addr:housenumber":"33",
    "addr:postcode":"08530",
    "addr:street":"Carrer De Ceramica",
    "iso:country":"ES",
    "sg:address":"Carrer de Ceramica, 33",
    "sg:city":"Garriga",
    "sg:orig_category":"Electromec\u00c1nica",
    "sg:phone":"+34 938 71 54 87",
    "sg:postcode":"08530",
    "sg:province":"Barcelona",
    "wof:name":"Gotanegra Ruiz Xavier",
    "wof:placetype":"venue"
},
  "geometry": {"coordinates":[2.282490015,41.6797294617],"type":"Point"}
}