{
  "type": "Feature",
  "properties": {
    "iso:country":"ES",
    "sg:address":"Plaz Mancha (de La), 16",
    "sg:city":"Puertollano",
    "sg:orig_category":"Droguer\u00cdas (al Por Menor)",
    "sg:phone":"+34 926 43 12 66",
    "sg:postcode":"13500",
    "sg:province":"Ciudad Real",
    "wof:name":"Mu\u00f1oz Pati\u00f1o Julian",
    "wof:placetype":"venue"
},
  "geometry": {"coordinates":[-4.1098189354,38.6953048706],"type":"Point"}
}