{
  "type": "Feature",
  "properties": {
    "iso:country":"ES",
    "sg:address":"Pda Castell, S/n",
    "sg:city":"Figueres",
    "sg:orig_category":"Promotores Constructores",
    "sg:phone":"+34 972 51 45 85",
    "sg:postcode":"17600",
    "sg:province":"Girona",
    "wof:name":"Consorcio Castillo De San Fernando",
    "wof:placetype":"venue"
},
  "geometry": {"coordinates":[2.9570000172,42.2692260742],"type":"Point"}
}