{
  "type": "Feature",
  "properties": {
    "addr:full":"Carrer de Farigola (de La), 28 Poligon Industrial Castellbisbal Sur Barcelona 08755",
    "addr:housenumber":"28",
    "addr:postcode":"08755",
    "addr:street":"Carrer De Farigola De La;Industrial",
    "iso:country":"ES",
    "sg:address":"Carrer de Farigola (de La), 28",
    "sg:city":"Poligon Industrial Castellbisbal Sur",
    "sg:orig_category":"Promotores Constructores",
    "sg:phone":"+34 937 71 11 82",
    "sg:postcode":"08755",
    "sg:province":"Barcelona",
    "wof:name":"Fachadas Osorio 2000 S.l.",
    "wof:placetype":"venue"
},
  "geometry": {"coordinates":[1.9888099432,41.4662094116],"type":"Point"}
}