{
  "type": "Feature",
  "properties": {
    "iso:country":"ES",
    "sg:address":"Calle de Andres Alvarez Caballero (de), 9",
    "sg:city":"Humanes De Madrid",
    "sg:orig_category":"Panader\u00cdas, Pasteler\u00cdas, Boller\u00cda Industriale (fabricaci\u00d3n, Al Por Mayor)",
    "sg:phone":"+34 916 90 89 34",
    "sg:postcode":"28970",
    "sg:province":"Madrid",
    "wof:name":"El Asador En Casa, S.l.",
    "wof:placetype":"venue"
},
  "geometry": {"coordinates":[-3.8152620792,40.2751960754],"type":"Point"}
}