{
  "type": "Feature",
  "properties": {
    "addr:full":"Pl Beat Salvador, 6 Mataro Barcelona 08301",
    "addr:housenumber":"6",
    "addr:postcode":"08301",
    "addr:street":"Pl;Salvador",
    "iso:country":"ES",
    "sg:address":"Pl Beat Salvador, 6",
    "sg:city":"Mataro",
    "sg:orig_category":"Ense\u00d1anza: Profesiones Art\u00cdsticas",
    "sg:phone":"+34 937 55 10 41",
    "sg:postcode":"08301",
    "sg:province":"Barcelona",
    "wof:name":"Cruz Buch Margarita",
    "wof:placetype":"venue"
},
  "geometry": {"coordinates":[2.4474499226,41.5398788452],"type":"Point"}
}