{
  "type": "Feature",
  "properties": {
    "addr:full":"Rua San Clemente (de), 8 Santiago De Compostela La Coru\u00f1a 15705",
    "addr:housenumber":"8",
    "addr:postcode":"15705",
    "addr:street":"Rua San Clemente De;Corun\u0303A",
    "iso:country":"ES",
    "sg:address":"Rua San Clemente (de), 8",
    "sg:city":"Santiago De Compostela",
    "sg:orig_category":"Caf\u00c9s, Bares, Cervecer\u00cdas",
    "sg:phone":"+34 981 57 30 14",
    "sg:postcode":"15705",
    "sg:province":"La Coru\u00f1a",
    "wof:name":"Mosquera Nieto Maria Jesus",
    "wof:placetype":"venue"
},
  "geometry": {"coordinates":[-8.5471134186,42.8791160583],"type":"Point"}
}