{
  "type": "Feature",
  "properties": {
    "iso:country":"ES",
    "sg:address":"Calle de Pintor Gisbert, 37",
    "sg:city":"Alacant",
    "sg:orig_category":"Asesor\u00cda De Formaci\u00d3n Y Gesti\u00d3n De Personal",
    "sg:phone":"+34 965 92 38 80",
    "sg:postcode":"03005",
    "sg:province":"Alicante",
    "wof:name":"Martinez Y Carbonell Asociados S.l.",
    "wof:placetype":"venue"
},
  "geometry": {"coordinates":[-0.4974519908,38.3478851318],"type":"Point"}
}