{
  "type": "Feature",
  "properties": {
    "addr:full":"Calle de Alfonso Xiii, 19 Dolores Murcia 30310",
    "addr:housenumber":"19",
    "addr:postcode":"30310",
    "addr:street":"Calle De Alfonso Xiii",
    "iso:country":"ES",
    "sg:address":"Calle de Alfonso Xiii, 19",
    "sg:city":"Dolores",
    "sg:orig_category":"Pintura Y Barniz (al Por Menor)",
    "sg:phone":"+34 968 53 01 11",
    "sg:postcode":"30310",
    "sg:province":"Murcia",
    "wof:name":"Vicente Diaz Sale S.l.",
    "wof:placetype":"venue"
},
  "geometry": {"coordinates":[-1.0071530342,37.6519165039],"type":"Point"}
}