{
  "type": "Feature",
  "properties": {
    "iso:country":"ES",
    "sg:address":"Ctra Cartagena, 71",
    "sg:city":"Torre-pacheco",
    "sg:orig_category":"Mec\u00c1nico Del Autom\u00d3vil",
    "sg:phone":"+34 968 57 83 87",
    "sg:postcode":"30700",
    "sg:province":"Murcia",
    "wof:name":"Jose Alcaraz Garcia S.l.",
    "wof:placetype":"venue"
},
  "geometry": {"coordinates":[-1.1333199739,37.9782829285],"type":"Point"}
}