{
  "type": "Feature",
  "properties": {
    "iso:country":"ES",
    "sg:address":"Calle de Claudio Coello, 69",
    "sg:city":"Madrid",
    "sg:orig_category":"Ropa Para Se\u00d1oras Y Caballeros (al Por Menor)",
    "sg:phone":"+34 914 35 09 77",
    "sg:postcode":"28001",
    "sg:province":"Madrid",
    "wof:name":"Puente Caruana Carmen De La",
    "wof:placetype":"venue"
},
  "geometry": {"coordinates":[-3.6860957146,40.4287261963],"type":"Point"}
}