{
  "type": "Feature",
  "properties": {
    "addr:full":"Carrer de Gombau, 6 Barcelona Barcelona 08003",
    "addr:housenumber":"6",
    "addr:postcode":"08003",
    "addr:street":"Carrer De Gombau",
    "iso:country":"ES",
    "sg:address":"Carrer de Gombau, 6",
    "sg:city":"Barcelona",
    "sg:orig_category":"Peluqueros: De Se\u00d1oras",
    "sg:phone":"+34 933 19 70 61",
    "sg:postcode":"08003",
    "sg:province":"Barcelona",
    "wof:name":"Santiago De Carvajal Altagracia",
    "wof:placetype":"venue"
},
  "geometry": {"coordinates":[2.1789059639,41.3866691589],"type":"Point"}
}