{
  "type": "Feature",
  "properties": {
    "iso:country":"ES",
    "sg:address":"Av Comas I Masferrer, 10",
    "sg:city":"Casco Urbano",
    "sg:orig_category":"Fabricaci\u00d3n De Quesos",
    "sg:phone":"+34 938 41 06 01",
    "sg:postcode":"08450",
    "sg:province":"Barcelona",
    "wof:name":"Formatgeria Mogent S.a.",
    "wof:placetype":"venue"
},
  "geometry": {"coordinates":[2.4019749165,41.6397705078],"type":"Point"}
}