{
  "type": "Feature",
  "properties": {
    "iso:country":"ES",
    "sg:address":"Calle de San Valerio, 15",
    "sg:city":"Ponferrada",
    "sg:orig_category":"Suministros Y Materiales Industriales",
    "sg:phone":"+34 987 40 94 33",
    "sg:postcode":"24400",
    "sg:province":"Le\u00f3n",
    "wof:name":"Suministros Industriales Del Tajo S.a.",
    "wof:placetype":"venue"
},
  "geometry": {"coordinates":[-6.5873641968,42.5465126038],"type":"Point"}
}