{
  "type": "Feature",
  "properties": {
    "addr:full":"Calle de Colon, 77 Yecla Murcia 30510",
    "addr:housenumber":"77",
    "addr:postcode":"30510",
    "addr:street":"Calle De Colon",
    "iso:country":"ES",
    "sg:address":"Calle de Colon, 77",
    "sg:city":"Yecla",
    "sg:orig_category":"Alquiler De V\u00cddeo",
    "sg:phone":"+34 968 79 60 92",
    "sg:postcode":"30510",
    "sg:province":"Murcia",
    "wof:name":"Constructora Y Promotora Puche-maza",
    "wof:placetype":"venue"
},
  "geometry": {"coordinates":[-1.1194466352,38.6150093079],"type":"Point"}
}