{
  "type": "Feature",
  "properties": {
    "addr:full":"Calle de Jose Vicario, 6 Alcala Henares Madrid 28804",
    "addr:postcode":"28804",
    "addr:street":"Calle De Jose Vicario 6",
    "iso:country":"ES",
    "sg:address":"Calle de Jose Vicario, 6",
    "sg:city":"Alcala Henares",
    "sg:orig_category":"Estudios, Instalaci\u00d3n De Climatizaci\u00d3n",
    "sg:phone":"+34 918 89 48 13",
    "sg:postcode":"28804",
    "sg:province":"Madrid",
    "wof:name":"Iberica De Conductos S.a.",
    "wof:placetype":"venue"
},
  "geometry": {"coordinates":[-3.3468570709,40.4905166626],"type":"Point"}
}