{
  "type": "Feature",
  "properties": {
    "iso:country":"ES",
    "sg:address":"Carrer de Mayor, 30",
    "sg:city":"Guardamar Segura",
    "sg:orig_category":"Inmobiliaria (agencias)",
    "sg:phone":"+34 966 72 63 37",
    "sg:postcode":"03140",
    "sg:province":"Alicante",
    "wof:name":"Arctico Cora Health & Care S.l.",
    "wof:placetype":"venue"
},
  "geometry": {"coordinates":[-0.6549751759,38.0918273926],"type":"Point"}
}