{
  "type": "Feature",
  "properties": {
    "iso:country":"ES",
    "sg:address":"Carrer de Banyeres, S/n",
    "sg:city":"Castalla",
    "sg:orig_category":"Empresas De Carpinter\u00cda Met\u00c1lica",
    "sg:phone":"+34 965 56 03 00",
    "sg:postcode":"03420",
    "sg:province":"Alicante",
    "wof:name":"Ferroart La Foia S.l.",
    "wof:placetype":"venue"
},
  "geometry": {"coordinates":[-0.6674990058,38.598865509],"type":"Point"}
}