{
  "type": "Feature",
  "properties": {
    "iso:country":"ES",
    "sg:address":"Avda Cruz Roja Espa\u00d1ola (de La), 35",
    "sg:city":"Cuenca",
    "sg:orig_category":"Centros Empresariales",
    "sg:phone":"+34 969 24 15 40",
    "sg:postcode":"16002",
    "sg:province":"Cuenca",
    "wof:name":"Campos De Cuenca",
    "wof:placetype":"venue"
},
  "geometry": {"coordinates":[-2.1632120609,40.0732498169],"type":"Point"}
}