{
  "type": "Feature",
  "properties": {
    "addr:full":"Calle de Jorge Juan, 70 Madrid Madrid 28009",
    "addr:housenumber":"70",
    "addr:postcode":"madrid;28009",
    "addr:street":"Calle De Jorge Juan",
    "iso:country":"ES",
    "sg:address":"Calle de Jorge Juan, 70",
    "sg:city":"Madrid",
    "sg:classifiers":[
        {
            "category":"Professional",
            "subcategory":"Management & Consulting",
            "type":"Services"
        }
    ],
    "sg:phone":"+34 915 78 35 42",
    "sg:postcode":"28009",
    "sg:province":"Madrid",
    "sg:tags":[
        "asesor\u00cda",
        "en",
        "marketing"
    ],
    "wof:name":"Jabel New Marquet S.l",
    "wof:placetype":"venue"
},
  "geometry": {"coordinates":[-3.6770889759,40.4233016968],"type":"Point"}
}