{
  "type": "Feature",
  "properties": {
    "iso:country":"ES",
    "sg:address":"Calle de San Vicente, 12",
    "sg:city":"Coru\u00d1a",
    "sg:orig_category":"Electrodom\u00c9sticos (al Por Menor)",
    "sg:phone":"+34 981 23 36 69",
    "sg:postcode":"15007",
    "sg:province":"La Coru\u00f1a",
    "wof:name":"Quintela Rodriguez Servando",
    "wof:placetype":"venue"
},
  "geometry": {"coordinates":[-8.4103393555,43.3555259705],"type":"Point"}
}