{
  "type": "Feature",
  "properties": {
    "addr:full":"Carrer de Smith (de), 34 Tarragona Tarragona 43005",
    "addr:housenumber":"34",
    "addr:postcode":"43005",
    "addr:street":"Carrer De Smith De",
    "iso:country":"ES",
    "sg:address":"Carrer de Smith (de), 34",
    "sg:city":"Tarragona",
    "sg:orig_category":"Oficinas Y Gesti\u00d3n De Inmuebles",
    "sg:phone":"+34 977 21 92 41",
    "sg:postcode":"43005",
    "sg:province":"Tarragona",
    "wof:name":"Jcma La Torre Blanca Servicios Inmobiliarios S.l.",
    "wof:placetype":"venue"
},
  "geometry": {"coordinates":[1.2439800501,41.1122207642],"type":"Point"}
}