{
  "type": "Feature",
  "properties": {
    "iso:country":"ES",
    "sg:address":"Calle de Doctor Fleming, 44",
    "sg:city":"Madrid",
    "sg:orig_category":"Farmacias",
    "sg:phone":"+34 913 59 95 23",
    "sg:postcode":"28036",
    "sg:province":"Madrid",
    "wof:name":"Garcia Gonzalez Soledad",
    "wof:placetype":"venue"
},
  "geometry": {"coordinates":[-3.6878678799,40.4610290527],"type":"Point"}
}