{
  "type": "Feature",
  "properties": {
    "iso:country":"ES",
    "sg:address":"Ctra Mesetas Las, 32",
    "sg:city":"Casablanca",
    "sg:orig_category":"Bebidas",
    "sg:phone":"+34 928 62 53 49",
    "sg:postcode":"35430",
    "sg:province":"Las Palmas",
    "wof:name":"Medina Perez Rafael",
    "wof:placetype":"venue"
},
  "geometry": {"coordinates":[-15.5624837875,28.1076145172],"type":"Point"}
}