{
  "type": "Feature",
  "properties": {
    "iso:country":"ES",
    "sg:address":"Poli Industrial Morea Sur, S/n",
    "sg:city":"Casco Viejo",
    "sg:orig_category":"Maquinaria Para Industrias Diversas",
    "sg:phone":"+34 948 31 08 79",
    "sg:postcode":"31191",
    "sg:province":"Navarra",
    "wof:name":"Obras Especiales De Navarra S.a.",
    "wof:placetype":"venue"
},
  "geometry": {"coordinates":[-1.6518089771,42.7533912659],"type":"Point"}
}