{
  "type": "Feature",
  "properties": {
    "addr:full":"Calle de Guayana, 10 Motril Granada 18600",
    "addr:housenumber":"10",
    "addr:postcode":"18600",
    "addr:street":"Calle De Guayana",
    "iso:country":"ES",
    "sg:address":"Calle de Guayana, 10",
    "sg:city":"Motril",
    "sg:orig_category":"Droguer\u00cdas (al Por Menor)",
    "sg:phone":"+34 958 60 90 95",
    "sg:postcode":"18600",
    "sg:province":"Granada",
    "wof:name":"Pinturas Antequera S.l.",
    "wof:placetype":"venue"
},
  "geometry": {"coordinates":[-3.5228898525,36.7444725037],"type":"Point"}
}