{
  "type": "Feature",
  "properties": {
    "addr:full":"Avda Andalucia, 15 Peligros Granada 18210",
    "addr:housenumber":"15",
    "addr:postcode":"18210",
    "addr:street":"Avda Andalucia",
    "iso:country":"ES",
    "sg:address":"Avda Andalucia, 15",
    "sg:city":"Peligros",
    "sg:orig_category":"Electricidad, Electr\u00d3nica: Suministros (al Por Menor)",
    "sg:phone":"+34 958 40 55 26",
    "sg:postcode":"18210",
    "sg:province":"Granada",
    "wof:name":"Radio Castilla S.a.",
    "wof:placetype":"venue"
},
  "geometry": {"coordinates":[-3.6257588863,37.2260017395],"type":"Point"}
}