{
  "type": "Feature",
  "properties": {
    "addr:full":"Ctra Bilbao-galdakao, 6 Bilbao Vizcaya 48004",
    "addr:housenumber":"6",
    "addr:postcode":"48004",
    "addr:street":"Ctra Bilbao-Galdakao",
    "iso:country":"ES",
    "sg:address":"Ctra Bilbao-galdakao, 6",
    "sg:city":"Bilbao",
    "sg:orig_category":"Agencias Y Asesores De Publicidad",
    "sg:phone":"+34 944 59 86 00",
    "sg:postcode":"48004",
    "sg:province":"Vizcaya",
    "sg:website":"www.bizkaia.net",
    "wof:name":"Mediasal 2000 S.a.",
    "wof:placetype":"venue"
},
  "geometry": {"coordinates":[-2.9015851021,43.2501564026],"type":"Point"}
}