{
  "type": "Feature",
  "properties": {
    "addr:full":"Plaz Virgen De Lepanto, 27 Castellar-oliveral Valencia 46026",
    "addr:housenumber":"27",
    "addr:postcode":"46026",
    "addr:street":"Plaz Virgen De Lepanto",
    "iso:country":"ES",
    "sg:address":"Plaz Virgen De Lepanto, 27",
    "sg:city":"Castellar-oliveral",
    "sg:orig_category":"M\u00c9dicos: Estomatolog\u00cda",
    "sg:phone":"+34 963 75 37 94",
    "sg:postcode":"46026",
    "sg:province":"Valencia",
    "wof:name":"Navarro Gilabert Francisco",
    "wof:placetype":"venue"
},
  "geometry": {"coordinates":[-0.3632889986,39.4293289185],"type":"Point"}
}