{
  "type": "Feature",
  "properties": {
    "iso:country":"ES",
    "sg:address":"Cust Valderremata, 33",
    "sg:city":"Valdemoro",
    "sg:orig_category":"Armarios Y Cuadros El\u00c9ctricos",
    "sg:phone":"+34 918 08 14 51",
    "sg:postcode":"28340",
    "sg:province":"Madrid",
    "wof:name":"Armarios De Distribucion Y Centro S.l.",
    "wof:placetype":"venue"
},
  "geometry": {"coordinates":[-3.6653945446,40.1909446716],"type":"Point"}
}