{
  "type": "Feature",
  "properties": {
    "iso:country":"ES",
    "sg:address":"Calle de San Cristobal, 102",
    "sg:city":"Merida",
    "sg:orig_category":"Material Y Suministros Para Perforaciones, Sondeos",
    "sg:phone":"+34 924 30 23 38",
    "sg:postcode":"06800",
    "sg:province":"Badajoz",
    "wof:name":"Gutierrez Jacinto Alfonso",
    "wof:placetype":"venue"
},
  "geometry": {"coordinates":[-6.3295459747,38.9304466248],"type":"Point"}
}