{
  "type": "Feature",
  "properties": {
    "addr:full":"Calle de Guaires, 5 Galdar Las Palmas 35460",
    "addr:housenumber":"5",
    "addr:postcode":"35460",
    "addr:street":"Calle De Guaires",
    "iso:country":"ES",
    "sg:address":"Calle de Guaires, 5",
    "sg:city":"Galdar",
    "sg:orig_category":"Agentes Generales De Seguros",
    "sg:phone":"+34 928 88 32 10",
    "sg:postcode":"35460",
    "sg:province":"Las Palmas",
    "wof:name":"Ramos Rodriguez Sebastian",
    "wof:placetype":"venue"
},
  "geometry": {"coordinates":[-15.6560573578,28.1444015503],"type":"Point"}
}