{
  "type": "Feature",
  "properties": {
    "addr:full":"Carrer de Ramon Turro, 287 Barcelona Barcelona 08019",
    "addr:housenumber":"287",
    "addr:postcode":"08019",
    "addr:street":"Carrer De Ramon Turro",
    "iso:country":"ES",
    "sg:address":"Carrer de Ramon Turro, 287",
    "sg:city":"Barcelona",
    "sg:orig_category":"Cajas De Ahorro",
    "sg:phone":"+34 933 03 43 63",
    "sg:postcode":"08019",
    "sg:province":"Barcelona",
    "wof:name":"Caja De Ahorros Y Monte De Piedad De Navarra",
    "wof:placetype":"venue"
},
  "geometry": {"coordinates":[2.2085990906,41.4043617249],"type":"Point"}
}