{
  "type": "Feature",
  "properties": {
    "iso:country":"ES",
    "sg:address":"Calle de Florez Estrada, S/n",
    "sg:city":"Pola Somiedo",
    "sg:orig_category":"Iglesia Cat\u00d3lica",
    "sg:phone":"+34 985 76 36 89",
    "sg:postcode":"33840",
    "sg:province":"Asturias",
    "wof:name":"Diocesis De Oviedo",
    "wof:placetype":"venue"
},
  "geometry": {"coordinates":[-6.258234024,43.0951652527],"type":"Point"}
}