{
  "type": "Feature",
  "properties": {
    "addr:full":"Avda Europa, 90 Malaga M\u00e1laga 29003",
    "addr:housenumber":"90",
    "addr:postcode":"29003",
    "addr:street":"Avda Europa;Ma\u0301Laga",
    "iso:country":"ES",
    "sg:address":"Avda Europa, 90",
    "sg:city":"Malaga",
    "sg:orig_category":"Bisuter\u00cda, Joyer\u00cda, Relojer\u00cda (al Por Menor)",
    "sg:phone":"+34 952 34 96 14",
    "sg:postcode":"29003",
    "sg:province":"M\u00e1laga",
    "wof:name":"Rodriguez Bueno Maria Teresa",
    "wof:placetype":"venue"
},
  "geometry": {"coordinates":[-4.4526991844,36.7001152039],"type":"Point"}
}