{
  "type": "Feature",
  "properties": {
    "iso:country":"ES",
    "sg:address":"Calle de Octavio Picon, 11",
    "sg:city":"Malaga",
    "sg:orig_category":"Promotores Constructores",
    "sg:phone":"+34 952 29 27 52",
    "sg:postcode":"29017",
    "sg:province":"M\u00e1laga",
    "wof:name":"General De Construcciones Y Servicios S.l.",
    "wof:placetype":"venue"
},
  "geometry": {"coordinates":[-4.3677940369,36.7234802246],"type":"Point"}
}