{
  "type": "Feature",
  "properties": {
    "addr:full":"Calle de Ancora, 9 Madrid Madrid 28045",
    "addr:housenumber":"9",
    "addr:postcode":"madrid;28045",
    "addr:street":"Calle De Ancora",
    "iso:country":"ES",
    "sg:address":"Calle de Ancora, 9",
    "sg:city":"Madrid",
    "sg:orig_category":"Peluquer\u00cdas, Peluquer\u00cda Mixta",
    "sg:phone":"+34 914 68 61 22",
    "sg:postcode":"28045",
    "sg:province":"Madrid",
    "wof:name":"Blasco Carretero Yolanda",
    "wof:placetype":"venue"
},
  "geometry": {"coordinates":[-3.6926701069,40.4030723572],"type":"Point"}
}