{
  "type": "Feature",
  "properties": {
    "addr:full":"Calle de Santander, 17 Coru\u00d1a A Coru\u00f1a 15007",
    "addr:housenumber":"17",
    "addr:postcode":"15007",
    "addr:street":"Calle De Santander;Corun\u0303A",
    "iso:country":"ES",
    "sg:address":"Calle de Santander, 17",
    "sg:city":"Coru\u00d1a",
    "sg:orig_category":"Laboratorios Y Trabajos De Fotograf\u00cda, V\u00cddeo Y Cine",
    "sg:phone":"+34 981 24 13 86",
    "sg:postcode":"15007",
    "sg:province":"A Coru\u00f1a",
    "sg:website":"www.serpremiga.com",
    "wof:name":"Serpremiga S.l.",
    "wof:placetype":"venue"
},
  "geometry": {"coordinates":[-8.408873558,43.3564910889],"type":"Point"}
}