{
  "type": "Feature",
  "properties": {
    "iso:country":"ES",
    "sg:address":"Calle de Ramon Pignatelli, 81",
    "sg:city":"Zaragoza",
    "sg:orig_category":"Peluqueros: De Se\u00d1oras",
    "sg:phone":"+34 976 28 27 59",
    "sg:postcode":"50004",
    "sg:province":"Zaragoza",
    "wof:name":"Allueva Per Maria Jose",
    "wof:placetype":"venue"
},
  "geometry": {"coordinates":[-0.889523387,41.6541976929],"type":"Point"}
}