{
  "type": "Feature",
  "properties": {
    "addr:full":"Calle de Do\u00d1a Catalina De Perea, 21 Utrera Sevilla 41710",
    "addr:housenumber":"21",
    "addr:postcode":"41710",
    "addr:street":"Calle De Don\u0303A Catalina De Perea",
    "iso:country":"ES",
    "sg:address":"Calle de Do\u00d1a Catalina De Perea, 21",
    "sg:city":"Utrera",
    "sg:orig_category":"Alimentaci\u00d3n General (al Por Menor)",
    "sg:phone":"+34 955 86 17 36",
    "sg:postcode":"41710",
    "sg:province":"Sevilla",
    "wof:name":"Caro Ruiz Teresa",
    "wof:placetype":"venue"
},
  "geometry": {"coordinates":[-5.7845849991,37.180431366],"type":"Point"}
}