{
  "type": "Feature",
  "properties": {
    "iso:country":"ES",
    "sg:address":"Ibaiondo Industrialdea, 7",
    "sg:city":"Ihurre",
    "sg:orig_category":"Electricidad Veh\u00cdculo",
    "sg:phone":"+34 943 88 32 12",
    "sg:postcode":"20212",
    "sg:province":"Guip\u00f9zcoa",
    "wof:name":"Auto Electricidad Illargui C. B.",
    "wof:placetype":"venue"
},
  "geometry": {"coordinates":[-2.2013700008,43.0282554626],"type":"Point"}
}