{
  "type": "Feature",
  "properties": {
    "iso:country":"ES",
    "sg:address":"Carrer de Sepulveda, 44",
    "sg:city":"Barcelona",
    "sg:orig_category":"Persianas Interiores, Exteriores",
    "sg:phone":"+34 934 26 86 50",
    "sg:postcode":"08015",
    "sg:province":"Barcelona",
    "sg:website":"www.paginasamarillas.es",
    "wof:name":"Sanz Narciso Vicente",
    "wof:placetype":"venue"
},
  "geometry": {"coordinates":[2.1545479298,41.3770332336],"type":"Point"}
}