{
  "type": "Feature",
  "properties": {
    "addr:full":"Calle de Iglesia, 5 Madrid Madrid 28019",
    "addr:housenumber":"5",
    "addr:postcode":"28019",
    "addr:street":"Calle De Iglesia",
    "iso:country":"ES",
    "sg:address":"Calle de Iglesia, 5",
    "sg:city":"Madrid",
    "sg:orig_category":"Laboratorios Y Cl\u00cdnicas Veterinarias",
    "sg:phone":"+34 914 72 38 04",
    "sg:postcode":"28019",
    "sg:province":"Madrid",
    "wof:name":"Palomar Gomez Jose-luis",
    "wof:placetype":"venue"
},
  "geometry": {"coordinates":[-3.7176880836,40.39585495],"type":"Point"}
}