{
  "type": "Feature",
  "properties": {
    "addr:full":"Av Alcoy, 78 Pego Alicante 03780",
    "addr:housenumber":"78",
    "addr:postcode":"03780",
    "addr:street":"Av Alcoy",
    "iso:country":"ES",
    "sg:address":"Av Alcoy, 78",
    "sg:city":"Pego",
    "sg:orig_category":"Empresas De Carpinter\u00cda De Madera",
    "sg:phone":"+34 965 57 10 22",
    "sg:postcode":"03780",
    "sg:province":"Alicante",
    "wof:name":"Puchol Puig Doroteo",
    "wof:placetype":"venue"
},
  "geometry": {"coordinates":[-0.1166009977,38.8458404541],"type":"Point"}
}