{
  "type": "Feature",
  "properties": {
    "iso:country":"ES",
    "sg:address":"Rua Baterias, 2",
    "sg:city":"Ferrol",
    "sg:orig_category":"Ense\u00d1anza, Formaci\u00d3n Profesional: Aprendizaje",
    "sg:phone":"+34 981 35 38 89",
    "sg:postcode":"15401",
    "sg:province":"La Coru\u00f1a",
    "wof:name":"Religiosas Oblatas Del Santisimo Redentor",
    "wof:placetype":"venue"
},
  "geometry": {"coordinates":[-8.2454023361,43.4803924561],"type":"Point"}
}