{
  "type": "Feature",
  "properties": {
    "addr:full":"Av Mestre Josep Bonay, 26 Palafrugell Girona 17200",
    "addr:housenumber":"26",
    "addr:postcode":"17200",
    "addr:street":"Av Mestre Josep Bonay",
    "iso:country":"ES",
    "sg:address":"Av Mestre Josep Bonay, 26",
    "sg:city":"Palafrugell",
    "sg:orig_category":"Psic\u00d3logos",
    "sg:phone":"+34 972 30 04 94",
    "sg:postcode":"17200",
    "sg:province":"Girona",
    "wof:name":"Comas Esteva Carlos",
    "wof:placetype":"venue"
},
  "geometry": {"coordinates":[3.1689300537,41.9221191406],"type":"Point"}
}