{
  "type": "Feature",
  "properties": {
    "addr:full":"Rua Xeneral Pardi\u00d1as (do), 6 Santiago De Compostela La Coru\u00f1a 15701",
    "addr:postcode":"15701",
    "addr:street":"Rua Xeneral;Corun\u0303A",
    "iso:country":"ES",
    "sg:address":"Rua Xeneral Pardi\u00d1as (do), 6",
    "sg:city":"Santiago De Compostela",
    "sg:orig_category":"Cajas De Ahorro",
    "sg:phone":"+34 981 58 24 66",
    "sg:postcode":"15701",
    "sg:province":"La Coru\u00f1a",
    "sg:website":"www.cajaespana.es",
    "wof:name":"Caja Espa\u00f1a De Inversiones Caja De Ahorros Y Monte De Piedad",
    "wof:placetype":"venue"
},
  "geometry": {"coordinates":[-8.5464382172,42.8761100769],"type":"Point"}
}