{
  "type": "Feature",
  "properties": {
    "iso:country":"ES",
    "sg:address":"Calle de Fuente De La Salud, S/n",
    "sg:city":"Jaen",
    "sg:orig_category":"Guarder\u00cdas",
    "sg:phone":"+34 953 27 20 65",
    "sg:postcode":"23006",
    "sg:province":"Ja\u00e9n",
    "wof:name":"Maria Dolores Quesada Bejar Y Otras Dos C.b.",
    "wof:placetype":"venue"
},
  "geometry": {"coordinates":[-3.8050940037,37.779624939],"type":"Point"}
}