{
  "type": "Feature",
  "properties": {
    "addr:full":"Calle de Enmedio, 13 Artziniega \u00c1lava 01474",
    "addr:housenumber":"13",
    "addr:postcode":"01474",
    "addr:street":"Calle De Enmedio;A\u0301Lava",
    "iso:country":"ES",
    "sg:address":"Calle de Enmedio, 13",
    "sg:city":"Artziniega",
    "sg:orig_category":"Peluqueros: De Se\u00d1oras",
    "sg:phone":"+34 945 39 66 73",
    "sg:postcode":"01474",
    "sg:province":"\u00c1lava",
    "wof:name":"Zubiete Villanueva Eva Maria",
    "wof:placetype":"venue"
},
  "geometry": {"coordinates":[-3.1289460659,43.1210479736],"type":"Point"}
}