{
  "type": "Feature",
  "properties": {
    "addr:full":"Calle de Tirante, 49 Villarrubia De Los Ojos Ciudad Real 13670",
    "addr:housenumber":"49",
    "addr:postcode":"13670",
    "addr:street":"Calle De Tirante",
    "iso:country":"ES",
    "sg:address":"Calle de Tirante, 49",
    "sg:city":"Villarrubia De Los Ojos",
    "sg:orig_category":"Art\u00cdculos De Decoraci\u00d3n",
    "sg:phone":"+34 926 89 63 23",
    "sg:postcode":"13670",
    "sg:province":"Ciudad Real",
    "wof:name":"Rodriguez Garcia-morato Lucinio",
    "wof:placetype":"venue"
},
  "geometry": {"coordinates":[-3.6079890728,39.2192497253],"type":"Point"}
}