{
  "type": "Feature",
  "properties": {
    "iso:country":"ES",
    "sg:address":"Carrer de Torrent I Garriga, 41",
    "sg:city":"Manlleu",
    "sg:orig_category":"Transportes Por V\u00cdas Navegables",
    "sg:phone":"+34 938 51 13 49",
    "sg:postcode":"08560",
    "sg:province":"Barcelona",
    "wof:name":"Soler Sala Jacinto",
    "wof:placetype":"venue"
},
  "geometry": {"coordinates":[2.2856369019,42.0060806274],"type":"Point"}
}