{
  "type": "Feature",
  "properties": {
    "iso:country":"ES",
    "sg:address":"Carrer de Castanys, 9",
    "sg:city":"Barcelona",
    "sg:orig_category":"Laboratorios Y Cl\u00cdnicas Veterinarias",
    "sg:phone":"+34 932 25 43 33",
    "sg:postcode":"08005",
    "sg:province":"Barcelona",
    "wof:name":"Centro Veterinario Sant Marti S.cv",
    "wof:placetype":"venue"
},
  "geometry": {"coordinates":[2.2052950859,41.4004592896],"type":"Point"}
}