{
  "type": "Feature",
  "properties": {
    "iso:country":"ES",
    "sg:address":"Muralla, 2",
    "sg:city":"Rocafort De Vallbona",
    "sg:orig_category":"Aceites Y Grasas Alimentarias (fabricaci\u00d3n, Al Por Mayor)",
    "sg:phone":"+34 973 33 00 87",
    "sg:postcode":"25344",
    "sg:province":"Lleida",
    "wof:name":"Cooperativa Del Campo",
    "wof:placetype":"venue"
},
  "geometry": {"coordinates":[1.0926549435,41.5542640686],"type":"Point"}
}