{
  "type": "Feature",
  "properties": {
    "iso:country":"ES",
    "sg:address":"Carrer de Santiago Rusi\u00d1ol, 17",
    "sg:city":"S. Cugat Valles",
    "sg:orig_category":"Agentes Generales De Seguros",
    "sg:phone":"+34 936 74 05 21",
    "sg:postcode":"08172",
    "sg:province":"Barcelona",
    "wof:name":"Vila Oristrell Maria",
    "wof:placetype":"venue"
},
  "geometry": {"coordinates":[2.0826280117,41.4723091125],"type":"Point"}
}