{
  "type": "Feature",
  "properties": {
    "addr:full":"Calle de Rosaura, 31 Palmas De Gran Canaria Las Palmas 35014",
    "addr:housenumber":"31",
    "addr:postcode":"35014",
    "addr:street":"Calle De Rosaura",
    "iso:country":"ES",
    "sg:address":"Calle de Rosaura, 31",
    "sg:city":"Palmas De Gran Canaria",
    "sg:orig_category":"Farmacias",
    "sg:phone":"+34 928 37 02 28",
    "sg:postcode":"35014",
    "sg:province":"Las Palmas",
    "wof:name":"Perera Rodriguez Sergio",
    "wof:placetype":"venue"
},
  "geometry": {"coordinates":[-15.4242515564,28.1090450287],"type":"Point"}
}