{
  "type": "Feature",
  "properties": {
    "iso:country":"ES",
    "sg:address":"Calle de Rosalia De Castro, 95",
    "sg:city":"Escairon",
    "sg:orig_category":"Mec\u00c1nico Del Autom\u00d3vil",
    "sg:phone":"+34 982 45 24 15",
    "sg:postcode":"27540",
    "sg:province":"Lugo",
    "wof:name":"Rois Gonzalez Luis",
    "wof:placetype":"venue"
},
  "geometry": {"coordinates":[-7.6355109215,42.5896263123],"type":"Point"}
}