{
  "type": "Feature",
  "properties": {
    "iso:country":"ES",
    "sg:address":"Calle de Riaza, 40",
    "sg:city":"Madrid",
    "sg:orig_category":"Molduras, Junquillos, Listones Y Molduras Perforadas",
    "sg:phone":"+34 913 57 53 24",
    "sg:postcode":"28023",
    "sg:province":"Madrid",
    "wof:name":"Carrera Quito Jorge",
    "wof:placetype":"venue"
},
  "geometry": {"coordinates":[-3.7841489315,40.4566688538],"type":"Point"}
}