{
  "type": "Feature",
  "properties": {
    "iso:country":"ES",
    "sg:address":"Calle de Conde Aranda, 122",
    "sg:city":"Zaragoza",
    "sg:orig_category":"Electrodom\u00c9sticos (al Por Menor)",
    "sg:phone":"+34 976 43 26 23",
    "sg:postcode":"50003",
    "sg:province":"Zaragoza",
    "wof:name":"Electrovideo Portillo S. L.",
    "wof:placetype":"venue"
},
  "geometry": {"coordinates":[-0.8916977048,41.6558761597],"type":"Point"}
}