{
  "type": "Feature",
  "properties": {
    "addr:full":"Pol Ind El Pi, S/n Muro Alcoy Alicante 03830",
    "addr:housenumber":"s",
    "addr:postcode":"03830",
    "addr:street":"/ N Muro",
    "iso:country":"ES",
    "sg:address":"Pol Ind El Pi, S/n",
    "sg:city":"Muro Alcoy",
    "sg:orig_category":"Confecci\u00d3n (fabricaci\u00d3n, Al Por Mayor)",
    "sg:phone":"+34 965 53 16 68",
    "sg:postcode":"03830",
    "sg:province":"Alicante",
    "sg:website":"www.muestrariosagullo.com",
    "wof:name":"Muestrarios Textiles Agullo S.l.",
    "wof:placetype":"venue"
},
  "geometry": {"coordinates":[-0.4414289892,38.7812538147],"type":"Point"}
}