{
  "type": "Feature",
  "properties": {
    "iso:country":"ES",
    "sg:address":"Carrer de Sant Vicent Ferrer, 20",
    "sg:city":"Crevillent",
    "sg:orig_category":"Panader\u00cdas, Panader\u00cdas",
    "sg:phone":"+34 966 68 18 24",
    "sg:postcode":"03330",
    "sg:province":"Alicante",
    "wof:name":"Pacremat S.l.",
    "wof:placetype":"venue"
},
  "geometry": {"coordinates":[-0.8065590262,38.2458648682],"type":"Point"}
}