{
  "type": "Feature",
  "properties": {
    "iso:country":"ES",
    "sg:address":"San Juan, 1",
    "sg:city":"Valverde",
    "sg:orig_category":"Agencias De Viajes",
    "sg:phone":"+34 922 55 00 38",
    "sg:postcode":"38910",
    "sg:province":"Santa Cruz De Tenerife",
    "wof:name":"Viajes Insular S.a.",
    "wof:placetype":"venue"
},
  "geometry": {"coordinates":[-17.8965358734,27.8241672516],"type":"Point"}
}