{
  "type": "Feature",
  "properties": {
    "addr:full":"Calle de Murga, 22 Palmas De Gran Canaria Las Palmas 35003",
    "addr:housenumber":"22",
    "addr:postcode":"35003",
    "addr:street":"Calle De Murga",
    "iso:country":"ES",
    "sg:address":"Calle de Murga, 22",
    "sg:city":"Palmas De Gran Canaria",
    "sg:orig_category":"Abogados",
    "sg:phone":"+34 928 36 54 99",
    "sg:postcode":"35003",
    "sg:province":"Las Palmas",
    "wof:name":"Romero Limi\u00f1ana Carmen",
    "wof:placetype":"venue"
},
  "geometry": {"coordinates":[-15.4190359116,28.1110076904],"type":"Point"}
}