{
  "type": "Feature",
  "properties": {
    "iso:country":"ES",
    "sg:address":"Carrer de Salvador Segui, 29",
    "sg:city":"Vilafranca Penedes",
    "sg:orig_category":"Inform\u00c1tica, Ofim\u00c1tica (estudios, Asesor\u00cda, Ingenier\u00cda, Formaci\u00d3n)",
    "sg:phone":"+34 938 92 32 39",
    "sg:postcode":"08720",
    "sg:province":"Barcelona",
    "wof:name":"Riera Bricolle Jordi",
    "wof:placetype":"venue"
},
  "geometry": {"coordinates":[1.7018059492,41.3554115295],"type":"Point"}
}