{
  "type": "Feature",
  "properties": {
    "iso:country":"ES",
    "sg:address":"Plaz Glorieta (la), 11",
    "sg:city":"Santa Pola",
    "sg:orig_category":"Farmacias",
    "sg:phone":"+34 965 41 11 84",
    "sg:postcode":"03130",
    "sg:province":"Alicante",
    "wof:name":"Bonmati Lucerga Juan",
    "wof:placetype":"venue"
},
  "geometry": {"coordinates":[-0.5565090179,38.190448761],"type":"Point"}
}