{
  "type": "Feature",
  "properties": {
    "addr:full":"Ctra Enllac Autopista, S/n Torredembarra Tarragona 43830",
    "addr:housenumber":"s",
    "addr:postcode":"43830",
    "addr:street":"Ctra Enllac Autopista;/ N",
    "iso:country":"ES",
    "sg:address":"Ctra Enllac Autopista, S/n",
    "sg:city":"Torredembarra",
    "sg:orig_category":"Carpinteros",
    "sg:phone":"+34 977 64 02 83",
    "sg:postcode":"43830",
    "sg:province":"Tarragona",
    "wof:name":"Inmasfe S.l.",
    "wof:placetype":"venue"
},
  "geometry": {"coordinates":[1.395424962,41.1436691284],"type":"Point"}
}