{
  "type": "Feature",
  "properties": {
    "iso:country":"ES",
    "sg:address":"Avda Gonzalo De Berceo, S/n",
    "sg:city":"Aldeanueva Ebro",
    "sg:orig_category":"Muebles",
    "sg:phone":"+34 941 16 36 39",
    "sg:postcode":"26559",
    "sg:province":"La Rioja",
    "wof:name":"Gonzalez Torres Jose Antonio",
    "wof:placetype":"venue"
},
  "geometry": {"coordinates":[-1.8923890591,42.2264862061],"type":"Point"}
}