{
  "type": "Feature",
  "properties": {
    "iso:country":"ES",
    "sg:address":"Calle de Viriato, 71",
    "sg:city":"Madrid",
    "sg:orig_category":"Centros Empresariales",
    "sg:phone":"+34 914 44 53 40",
    "sg:postcode":"28010",
    "sg:province":"Madrid",
    "wof:name":"Fray Lucca Consulting S.l",
    "wof:placetype":"venue"
},
  "geometry": {"coordinates":[-3.6954269409,40.4357185364],"type":"Point"}
}