{
  "type": "Feature",
  "properties": {
    "iso:country":"ES",
    "sg:address":"Calle de Gran Capitan, 34",
    "sg:city":"Huetor-tajar",
    "sg:orig_category":"M\u00c1quinas De Coser Y De Hacer Punto (al Por Mayor)",
    "sg:phone":"+34 958 33 35 70",
    "sg:postcode":"18360",
    "sg:province":"Granada",
    "wof:name":"Martin Rojas S. L.",
    "wof:placetype":"venue"
},
  "geometry": {"coordinates":[-4.0497732162,37.19688797],"type":"Point"}
}