{
  "type": "Feature",
  "properties": {
    "iso:country":"ES",
    "sg:address":"Carrer de Progres, 53",
    "sg:city":"Gava",
    "sg:orig_category":"Electricidad: Equipos Industriales, Componentes (fabricaci\u00d3n)",
    "sg:phone":"+34 936 33 34 40",
    "sg:postcode":"08850",
    "sg:province":"Barcelona",
    "wof:name":"Electrostocks Barnasut S.l.",
    "wof:placetype":"venue"
},
  "geometry": {"coordinates":[2.0115170479,41.2989578247],"type":"Point"}
}