{
  "type": "Feature",
  "properties": {
    "addr:full":"Puerto Pesquero, S/n Almeria Almer\u00eda 04002",
    "addr:housenumber":"s / n",
    "addr:postcode":"04002",
    "addr:street":"Pesquero",
    "iso:country":"ES",
    "sg:address":"Puerto Pesquero, S/n",
    "sg:city":"Almeria",
    "sg:orig_category":"Ingenier\u00cda, Centros De Estudios (diversos)",
    "sg:phone":"+34 950 26 29 33",
    "sg:postcode":"04002",
    "sg:province":"Almer\u00eda",
    "wof:name":"Desarrollos Industriales Y Aplicaciones",
    "wof:placetype":"venue"
},
  "geometry": {"coordinates":[-2.5000441074,36.8265953064],"type":"Point"}
}