{
  "type": "Feature",
  "properties": {
    "addr:full":"Carrer de Francesc Tarrega, 11 Barcelona Barcelona 08027",
    "addr:housenumber":"11",
    "addr:postcode":"08027",
    "addr:street":"Carrer De Francesc Tarrega",
    "iso:country":"ES",
    "sg:address":"Carrer de Francesc Tarrega, 11",
    "sg:city":"Barcelona",
    "sg:orig_category":"Servicios De Telecomunicaciones",
    "sg:phone":"+34 933 49 43 11",
    "sg:postcode":"08027",
    "sg:province":"Barcelona",
    "wof:name":"Vips Telecom S.l.",
    "wof:placetype":"venue"
},
  "geometry": {"coordinates":[2.1800510883,41.4223632812],"type":"Point"}
}