{
  "type": "Feature",
  "properties": {
    "iso:country":"ES",
    "sg:address":"Calle de Imasa, 14",
    "sg:city":"Cuervo De Sevilla",
    "sg:orig_category":"Bares, Piano",
    "sg:phone":"+34 955 97 60 12",
    "sg:postcode":"41749",
    "sg:province":"Sevilla",
    "wof:name":"Cardenas Granados C.b.",
    "wof:placetype":"venue"
},
  "geometry": {"coordinates":[-6.0348610878,36.8586006165],"type":"Point"}
}