{
  "type": "Feature",
  "properties": {
    "addr:full":"Calle de Isla Cabrera, 23 Valencia Valencia 46026",
    "addr:housenumber":"23",
    "addr:postcode":"46026",
    "addr:street":"Calle De Isla Cabrera",
    "iso:country":"ES",
    "sg:address":"Calle de Isla Cabrera, 23",
    "sg:city":"Valencia",
    "sg:orig_category":"Maquinaria Para Industrias Diversas",
    "sg:phone":"+34 963 57 95 87",
    "sg:postcode":"46026",
    "sg:province":"Valencia",
    "wof:name":"Escriche Esteban Vicente Ramon",
    "wof:placetype":"venue"
},
  "geometry": {"coordinates":[-0.3802669942,39.4493598938],"type":"Point"}
}