{
  "type": "Feature",
  "properties": {
    "iso:country":"ES",
    "sg:address":"Calle de Antonino Vera, 16",
    "sg:city":"Elda",
    "sg:orig_category":"Muebles, Minoristas",
    "sg:phone":"+34 965 38 90 93",
    "sg:postcode":"03600",
    "sg:province":"Alicante",
    "sg:website":"www.andreuworld.com",
    "wof:name":"Bernabe Y Gonzalez S.l.",
    "wof:placetype":"venue"
},
  "geometry": {"coordinates":[-0.791786015,38.47681427],"type":"Point"}
}