{
  "type": "Feature",
  "properties": {
    "addr:full":"Calle de Federico Garcia Lorca, 24 Lopera Ja\u00e9n 23780",
    "addr:housenumber":"24",
    "addr:postcode":"23780",
    "addr:street":"Calle De Federico Garcia Lorca",
    "iso:country":"ES",
    "sg:address":"Calle de Federico Garcia Lorca, 24",
    "sg:city":"Lopera",
    "sg:orig_category":"Notarios",
    "sg:phone":"+34 953 52 61 21",
    "sg:postcode":"23780",
    "sg:province":"Ja\u00e9n",
    "wof:name":"Diaz Pareja Antonio Rafael",
    "wof:placetype":"venue"
},
  "geometry": {"coordinates":[-4.2121558189,37.9446258545],"type":"Point"}
}