{
  "type": "Feature",
  "properties": {
    "addr:full":"Calle de Malvaloca, 1 Alcala Guadaira Sevilla 41500",
    "addr:housenumber":"1",
    "addr:postcode":"41500",
    "addr:street":"Calle De Malvaloca",
    "iso:country":"ES",
    "sg:address":"Calle de Malvaloca, 1",
    "sg:city":"Alcala Guadaira",
    "sg:orig_category":"Equipos De Marcado, Etiquetado",
    "sg:phone":"+34 955 68 06 67",
    "sg:postcode":"41500",
    "sg:province":"Sevilla",
    "wof:name":"Lopez Marin Antonio",
    "wof:placetype":"venue"
},
  "geometry": {"coordinates":[-5.846031189,37.3390312195],"type":"Point"}
}