{
  "type": "Feature",
  "properties": {
    "addr:full":"Carr Pla\u00c7a, 7 Felanitx Islas Baleares 07200",
    "addr:housenumber":"7",
    "addr:postcode":"07200",
    "addr:street":"Carr Plac\u0327A",
    "iso:country":"ES",
    "sg:address":"Carr Pla\u00c7a, 7",
    "sg:city":"Felanitx",
    "sg:orig_category":"Reposter\u00cdas",
    "sg:phone":"+34 971 58 03 33",
    "sg:postcode":"07200",
    "sg:province":"Islas Baleares",
    "wof:name":"Mas Bravo Apolonia",
    "wof:placetype":"venue"
},
  "geometry": {"coordinates":[3.1485350132,39.4697952271],"type":"Point"}
}