{
  "type": "Feature",
  "properties": {
    "iso:country":"ES",
    "sg:address":"Calle de Virgen De Consolacion, 7",
    "sg:city":"Utrera",
    "sg:orig_category":"Ropa Para Se\u00d1oras (al Por Menor)",
    "sg:phone":"+34 954 86 47 25",
    "sg:postcode":"41710",
    "sg:province":"Sevilla",
    "wof:name":"Fernandez Martinez Maria De Las Mercedes",
    "wof:placetype":"venue"
},
  "geometry": {"coordinates":[-5.7803740501,37.1819763184],"type":"Point"}
}