{
  "type": "Feature",
  "properties": {
    "addr:full":"Carrer de Arago, 20 Palma Islas Baleares 07006",
    "addr:housenumber":"20",
    "addr:postcode":"07006",
    "addr:street":"Carrer De Arago",
    "iso:country":"ES",
    "sg:address":"Carrer de Arago, 20",
    "sg:city":"Palma",
    "sg:orig_category":"Cajas De Ahorro",
    "sg:phone":"+34 971 77 53 80",
    "sg:postcode":"07006",
    "sg:province":"Islas Baleares",
    "wof:name":"Caja De Ahorros Y Monte De Piedad De Las Baleares",
    "wof:placetype":"venue"
},
  "geometry": {"coordinates":[2.6586699486,39.5745697021],"type":"Point"}
}