{
  "type": "Feature",
  "properties": {
    "iso:country":"ES",
    "sg:address":"Calle de Puentecillo, 27",
    "sg:city":"Madrid",
    "sg:orig_category":"Artes Gr\u00c1ficas, Artes Pl\u00c1sticas (curso)",
    "sg:phone":"+34 913 88 26 28",
    "sg:postcode":"28043",
    "sg:province":"Madrid",
    "wof:name":"Panificadora Martinmar S.l.",
    "wof:placetype":"venue"
},
  "geometry": {"coordinates":[-3.6451380253,40.4580497742],"type":"Point"}
}