{
  "type": "Feature",
  "properties": {
    "addr:full":"Calle de Cantos (los), 1 Alcorcon Madrid 28922",
    "addr:housenumber":"1",
    "addr:postcode":"28922",
    "addr:street":"Calle De Cantos Los",
    "iso:country":"ES",
    "sg:address":"Calle de Cantos (los), 1",
    "sg:city":"Alcorcon",
    "sg:orig_category":"Cl\u00cdnicas Dentales",
    "sg:phone":"+34 916 43 77 32",
    "sg:postcode":"28922",
    "sg:province":"Madrid",
    "wof:name":"Ceam Dental S.l.",
    "wof:placetype":"venue"
},
  "geometry": {"coordinates":[-3.8330080509,40.3435707092],"type":"Point"}
}