{
  "type": "Feature",
  "properties": {
    "iso:country":"ES",
    "sg:address":"Calle de Violin, 12",
    "sg:city":"Ejido",
    "sg:orig_category":"Inversiones",
    "sg:phone":"+34 950 57 23 62",
    "sg:postcode":"04700",
    "sg:province":"Almer\u00eda",
    "wof:name":"Garcia Sosa Rosario",
    "wof:placetype":"venue"
},
  "geometry": {"coordinates":[-2.8167440891,36.7676849365],"type":"Point"}
}