{
  "type": "Feature",
  "properties": {
    "addr:full":"Calle de Martinez Monta\u00d1es, S/n Dos Hermanas Sevilla 41700",
    "addr:housenumber":"s",
    "addr:postcode":"41700",
    "addr:street":"Calle De Martinez Montan\u0303Es;/ N Dos",
    "iso:country":"ES",
    "sg:address":"Calle de Martinez Monta\u00d1es, S/n",
    "sg:city":"Dos Hermanas",
    "sg:orig_category":"Molduras, Junquillos, Listones Y Molduras Perforadas",
    "sg:phone":"+34 955 66 13 35",
    "sg:postcode":"41700",
    "sg:province":"Sevilla",
    "wof:name":"United Services S.l.",
    "wof:placetype":"venue"
},
  "geometry": {"coordinates":[-5.9264969826,37.289516449],"type":"Point"}
}