{
  "type": "Feature",
  "properties": {
    "addr:full":"Calle de Alfonso Xiii, 12 Cordoba C\u00f3rdoba 14001",
    "addr:housenumber":"12",
    "addr:postcode":"14001",
    "addr:street":"Calle De Alfonso Xiii;Co\u0301Rdoba",
    "iso:country":"ES",
    "sg:address":"Calle de Alfonso Xiii, 12",
    "sg:city":"Cordoba",
    "sg:orig_category":"Abogados",
    "sg:phone":"+34 957 47 25 55",
    "sg:postcode":"14001",
    "sg:province":"C\u00f3rdoba",
    "wof:name":"Abogados Sanchez Y Garcia C.b",
    "wof:placetype":"venue"
},
  "geometry": {"coordinates":[-4.77783,37.885441],"type":"Point"}
}