{
  "type": "Feature",
  "properties": {
    "iso:country":"ES",
    "sg:address":"Carrer de Mayor, 6",
    "sg:city":"Guardamar Segura",
    "sg:orig_category":"Muebles, Minoristas",
    "sg:phone":"+34 965 72 43 14",
    "sg:postcode":"03140",
    "sg:province":"Alicante",
    "wof:name":"Procomobel S.l.",
    "wof:placetype":"venue"
},
  "geometry": {"coordinates":[-0.6540290117,38.086681366],"type":"Point"}
}