{
  "type": "Feature",
  "properties": {
    "addr:full":"Calle de Fermin Caballero, 12 Madrid Madrid 28034",
    "addr:housenumber":"12",
    "addr:postcode":"madrid;28034",
    "addr:street":"Calle De Fermin Caballero",
    "iso:country":"ES",
    "sg:address":"Calle de Fermin Caballero, 12",
    "sg:city":"Madrid",
    "sg:orig_category":"Centros Empresariales",
    "sg:phone":"+34 913 78 17 01",
    "sg:postcode":"28034",
    "sg:province":"Madrid",
    "wof:name":"Pablo Samaniego Valeriano De",
    "wof:placetype":"venue"
},
  "geometry": {"coordinates":[-3.6999390125,40.4869499207],"type":"Point"}
}