{
  "type": "Feature",
  "properties": {
    "addr:full":"Carr Cervantes, S/n Almacelles Lleida 25100",
    "addr:housenumber":"/ n",
    "addr:postcode":"25100",
    "addr:street":"Carr Cervantes S",
    "iso:country":"ES",
    "sg:address":"Carr Cervantes, S/n",
    "sg:city":"Almacelles",
    "sg:orig_category":"Productos Qu\u00cdmicos (fabricaci\u00d3n, Al Por Mayor)",
    "sg:phone":"+34 973 74 13 50",
    "sg:postcode":"25100",
    "sg:province":"Lleida",
    "sg:website":"www.promisol.com",
    "wof:name":"Promisol S.a.",
    "wof:placetype":"venue"
},
  "geometry": {"coordinates":[0.4378699958,41.7284507751],"type":"Point"}
}