{
  "type": "Feature",
  "properties": {
    "iso:country":"ES",
    "sg:address":"Cra Fuente De San Luis, 100",
    "sg:city":"Valencia",
    "sg:orig_category":"Molduras, Junquillos, Listones Y Molduras Perforadas",
    "sg:phone":"+34 963 74 87 75",
    "sg:postcode":"46013",
    "sg:province":"Valencia",
    "wof:name":"Mico Asensi Amparo",
    "wof:placetype":"venue"
},
  "geometry": {"coordinates":[-0.3709860146,39.4518814087],"type":"Point"}
}