{
  "type": "Feature",
  "properties": {
    "iso:country":"ES",
    "sg:address":"Calle de Platero Pedro De Bares, 13",
    "sg:city":"Cordoba",
    "sg:orig_category":"Condimentos, Especias, Vinagres, Salsas Preparadas (fabricaci\u00d3n, Al Por Mayor)",
    "sg:phone":"+34 957 26 91 01",
    "sg:postcode":"14007",
    "sg:province":"C\u00f3rdoba",
    "wof:name":"Zurera Hermanos S.l.",
    "wof:placetype":"venue"
},
  "geometry": {"coordinates":[-4.7606501579,37.8954048157],"type":"Point"}
}