{
  "type": "Feature",
  "properties": {
    "addr:full":"Pase Virgen De Linarejos, 48 Linares Ja\u00e9n 23700",
    "addr:housenumber":"48",
    "addr:postcode":"23700",
    "addr:street":"Jae\u0301N",
    "iso:country":"ES",
    "sg:address":"Pase Virgen De Linarejos, 48",
    "sg:city":"Linares",
    "sg:orig_category":"Supermercados Y Hipermercados",
    "sg:phone":"+34 953 65 79 52",
    "sg:postcode":"23700",
    "sg:province":"Ja\u00e9n",
    "wof:name":"Eko Linares S.a.l.",
    "wof:placetype":"venue"
},
  "geometry": {"coordinates":[-3.6323540211,38.0981941223],"type":"Point"}
}