{
  "type": "Feature",
  "properties": {
    "addr:full":"Avda Andalucia, 199 Estepona M\u00e1laga 29680",
    "addr:housenumber":"199",
    "addr:postcode":"29680",
    "addr:street":"Avda Andalucia",
    "iso:country":"ES",
    "sg:address":"Avda Andalucia, 199",
    "sg:city":"Estepona",
    "sg:orig_category":"Plomeros",
    "sg:phone":"+34 952 79 06 82",
    "sg:postcode":"29680",
    "sg:province":"M\u00e1laga",
    "wof:name":"Garcia Olid Luis",
    "wof:placetype":"venue"
},
  "geometry": {"coordinates":[-5.151055336,36.4283447266],"type":"Point"}
}