{
  "type": "Feature",
  "properties": {
    "addr:full":"Carrer de Angel Ara\u00d1o, 6 Viladecans Barcelona 08840",
    "addr:housenumber":"6",
    "addr:postcode":"08840",
    "addr:street":"Carrer De Angel Aran\u0303O",
    "iso:country":"ES",
    "sg:address":"Carrer de Angel Ara\u00d1o, 6",
    "sg:city":"Viladecans",
    "sg:orig_category":"Promotores Constructores",
    "sg:phone":"+34 936 58 09 58",
    "sg:postcode":"08840",
    "sg:province":"Barcelona",
    "wof:name":"Dolmen S.c.p.",
    "wof:placetype":"venue"
},
  "geometry": {"coordinates":[2.0167579651,41.3209991455],"type":"Point"}
}