{
  "type": "Feature",
  "properties": {
    "iso:country":"ES",
    "sg:address":"Urb R.nuevo Manzanares I, 23",
    "sg:city":"Manzanares",
    "sg:orig_category":"Peluqueros: De Se\u00d1oras",
    "sg:phone":"+34 926 61 08 11",
    "sg:postcode":"13200",
    "sg:province":"Ciudad Real",
    "wof:name":"Romero De Avila Martinez-zarco Jose Antonio",
    "wof:placetype":"venue"
},
  "geometry": {"coordinates":[-3.3593289852,38.9968795776],"type":"Point"}
}