{
  "type": "Feature",
  "properties": {
    "addr:full":"Carrer de Tormes, 3 Terrassa Barcelona 08226",
    "addr:housenumber":"3",
    "addr:postcode":"08226",
    "addr:street":"Carrer De Tormes",
    "iso:country":"ES",
    "sg:address":"Carrer de Tormes, 3",
    "sg:city":"Terrassa",
    "sg:orig_category":"Empresas De Carpinter\u00cda",
    "sg:phone":"+34 937 83 83 22",
    "sg:postcode":"08226",
    "sg:province":"Barcelona",
    "wof:name":"Construcciones Metalicas J. Perez S. A.",
    "wof:placetype":"venue"
},
  "geometry": {"coordinates":[2.0340969563,41.549369812],"type":"Point"}
}