{
  "type": "Feature",
  "properties": {
    "iso:country":"ES",
    "sg:address":"Calle de Virgen Del Carmen, 3",
    "sg:city":"Llodio",
    "sg:orig_category":"Reposter\u00cdas",
    "sg:phone":"+34 946 72 07 21",
    "sg:postcode":"01400",
    "sg:province":"\u00c1lava",
    "wof:name":"Mellado Iturrate Maria Antonia",
    "wof:placetype":"venue"
},
  "geometry": {"coordinates":[-2.9610469341,43.1431045532],"type":"Point"}
}