{
  "type": "Feature",
  "properties": {
    "iso:country":"ES",
    "sg:address":"Calle de Alejandro Villegas, 50",
    "sg:city":"Madrid",
    "sg:orig_category":"Guarder\u00cdas",
    "sg:phone":"+34 913 00 06 30",
    "sg:postcode":"28043",
    "sg:province":"Madrid",
    "wof:name":"Fernandez Otero Joaquin Maria",
    "wof:placetype":"venue"
},
  "geometry": {"coordinates":[-3.6490929127,40.4667778015],"type":"Point"}
}