{
  "type": "Feature",
  "properties": {
    "iso:country":"ES",
    "sg:address":"Rond Sud, S/n",
    "sg:city":"Figueres",
    "sg:orig_category":"Electricidad, Electr\u00d3nica: Suministros (al Por Menor)",
    "sg:phone":"+34 972 51 00 07",
    "sg:postcode":"17600",
    "sg:province":"Girona",
    "wof:name":"Banzai Electrodomesticos S.l.",
    "wof:placetype":"venue"
},
  "geometry": {"coordinates":[2.9581100941,42.2656898499],"type":"Point"}
}