{
  "type": "Feature",
  "properties": {
    "addr:full":"Avda Juan Garcia Navia Castrillon, 1 Viveiro Lugo 27850",
    "addr:housenumber":"1",
    "addr:postcode":"27850",
    "addr:street":"Avda Juan Garcia;Castrillon",
    "iso:country":"ES",
    "sg:address":"Avda Juan Garcia Navia Castrillon, 1",
    "sg:city":"Viveiro",
    "sg:orig_category":"Ense\u00d1anza: Comercio, Gesti\u00d3n, Inform\u00c1tica",
    "sg:phone":"+34 982 56 08 20",
    "sg:postcode":"27850",
    "sg:province":"Lugo",
    "wof:name":"Mejuto Urrutia Maria Del Carmen",
    "wof:placetype":"venue"
},
  "geometry": {"coordinates":[-7.5978188515,43.6580505371],"type":"Point"}
}