{
  "type": "Feature",
  "properties": {
    "addr:full":"Mercado Caba\u00f1al, S/n Valencia Valencia 46011",
    "addr:housenumber":"s / n",
    "addr:postcode":"46011",
    "iso:country":"ES",
    "sg:address":"Mercado Caba\u00f1al, S/n",
    "sg:city":"Valencia",
    "sg:orig_category":"Frutas, Legumbres Frescas Y Tempranas (al Por Menor)",
    "sg:phone":"+34 963 55 06 35",
    "sg:postcode":"46011",
    "sg:province":"Valencia",
    "wof:name":"Gines Ponce S.l.",
    "wof:placetype":"venue"
},
  "geometry": {"coordinates":[-0.3348590136,39.4612083435],"type":"Point"}
}