{
  "type": "Feature",
  "properties": {
    "addr:full":"Avda Tenor Fleta, 95 Zaragoza Zaragoza 50008",
    "addr:housenumber":"95",
    "addr:postcode":"50008",
    "addr:street":"Avda Tenor Fleta",
    "iso:country":"ES",
    "sg:address":"Avda Tenor Fleta, 95",
    "sg:city":"Zaragoza",
    "sg:orig_category":"Zapatos (al Por Menor)",
    "sg:phone":"+34 976 59 46 47",
    "sg:postcode":"50008",
    "sg:province":"Zaragoza",
    "wof:name":"Burriel Martinez Agustin",
    "wof:placetype":"venue"
},
  "geometry": {"coordinates":[-0.8769860268,41.6376075745],"type":"Point"}
}