{
  "type": "Feature",
  "properties": {
    "addr:full":"Calle de Lerida, 1 Logro\u00f1o La Rioja 26006",
    "addr:housenumber":"1",
    "addr:postcode":"26006",
    "addr:street":"Calle De Lerida;Rioja",
    "iso:country":"ES",
    "sg:address":"Calle de Lerida, 1",
    "sg:city":"Logro\u00f1o",
    "sg:orig_category":"Caf\u00c9s, Bares, Cervecer\u00cdas",
    "sg:phone":"+34 941 24 06 92",
    "sg:postcode":"26006",
    "sg:province":"La Rioja",
    "wof:name":"Opera Berceo 2003 S. L.",
    "wof:placetype":"venue"
},
  "geometry": {"coordinates":[-2.4207389355,42.4621391296],"type":"Point"}
}