{
  "type": "Feature",
  "properties": {
    "addr:full":"Calle de Artes Graficas (de Las), 26 Huesca Huesca 22006",
    "addr:housenumber":"26",
    "addr:postcode":"22006",
    "addr:street":"Calle De;Las",
    "iso:country":"ES",
    "sg:address":"Calle de Artes Graficas (de Las), 26",
    "sg:city":"Huesca",
    "sg:orig_category":"Aparatos, Material Y Suministros Para Laboratorios",
    "sg:phone":"+34 974 24 48 29",
    "sg:postcode":"22006",
    "sg:province":"Huesca",
    "wof:name":"Laboratorio De Ensayos Tecnicos S.a.",
    "wof:placetype":"venue"
},
  "geometry": {"coordinates":[-0.3841696084,42.1431884766],"type":"Point"}
}