{
  "type": "Feature",
  "properties": {
    "addr:full":"Alam Colon, 16 Malaga M\u00e1laga 29001",
    "addr:housenumber":"16",
    "addr:postcode":"29001",
    "addr:street":"Alam Colon;Ma\u0301Laga",
    "iso:country":"ES",
    "sg:address":"Alam Colon, 16",
    "sg:city":"Malaga",
    "sg:orig_category":"Profesiones M\u00c9dicas, Param\u00c9dicas",
    "sg:phone":"+34 952 22 95 93",
    "sg:postcode":"29001",
    "sg:province":"M\u00e1laga",
    "wof:name":"Souviron Lopez Margarita",
    "wof:placetype":"venue"
},
  "geometry": {"coordinates":[-4.4246897697,36.714931488],"type":"Point"}
}