{
  "type": "Feature",
  "properties": {
    "addr:full":"Ctra. Valencia, 89 Riba-roja Turia Valencia 46190",
    "addr:housenumber":"89",
    "addr:postcode":"46190",
    "addr:street":"Ctra. Valencia",
    "iso:country":"ES",
    "sg:address":"Ctra. Valencia, 89",
    "sg:city":"Riba-roja Turia",
    "sg:orig_category":"Quincaller\u00cda (al Por Menor)",
    "sg:phone":"+34 962 77 03 19",
    "sg:postcode":"46190",
    "sg:province":"Valencia",
    "wof:name":"Garcia Es...bricojardin S.l",
    "wof:placetype":"venue"
},
  "geometry": {"coordinates":[-0.5607519746,39.5446434021],"type":"Point"}
}