{
  "type": "Feature",
  "properties": {
    "addr:full":"La Ba\u00f1eza, Km. 0001,0 Ribaseca Le\u00f3n 24391",
    "addr:postcode":"24391",
    "addr:street":"Ban\u0303Eza Km. 0001,0 Ribaseca Leo\u0301N",
    "iso:country":"ES",
    "sg:address":"La Ba\u00f1eza, Km. 0001,0",
    "sg:city":"Ribaseca",
    "sg:orig_category":"Material Y Herramientas Agr\u00cdcolas",
    "sg:phone":"+34 987 28 13 68",
    "sg:postcode":"24391",
    "sg:province":"Le\u00f3n",
    "wof:name":"Comercial Grande S.l.",
    "wof:placetype":"venue"
},
  "geometry": {"coordinates":[-5.6244401932,42.5436477661],"type":"Point"}
}