{
  "type": "Feature",
  "properties": {
    "iso:country":"ES",
    "sg:address":"Ctra Palmar, 46",
    "sg:city":"Murcia",
    "sg:orig_category":"Grafistas",
    "sg:phone":"+34 968 35 06 22",
    "sg:postcode":"30010",
    "sg:province":"Murcia",
    "wof:name":"Pardo Comunicacion S.l",
    "wof:placetype":"venue"
},
  "geometry": {"coordinates":[-1.136531949,37.9723815918],"type":"Point"}
}