{
  "type": "Feature",
  "properties": {
    "addr:full":"Rua Ervedelo, 38 Ourense Ourense 32002",
    "addr:housenumber":"38",
    "addr:postcode":"32002",
    "addr:street":"Rua Ervedelo",
    "iso:country":"ES",
    "sg:address":"Rua Ervedelo, 38",
    "sg:city":"Ourense",
    "sg:orig_category":"Ropa Para Caballeros (al Por Menor)",
    "sg:phone":"+34 988 24 99 94",
    "sg:postcode":"32002",
    "sg:province":"Ourense",
    "wof:name":"Deza Gomez Rosario",
    "wof:placetype":"venue"
},
  "geometry": {"coordinates":[-7.8707289696,42.3397102356],"type":"Point"}
}