{
  "type": "Feature",
  "properties": {
    "iso:country":"ES",
    "sg:address":"Pase Extremadura, 49",
    "sg:city":"Madrid",
    "sg:orig_category":"Fabricaci\u00d3n De Productos Textiles Sin Tejer",
    "sg:phone":"+34 914 64 37 70",
    "sg:postcode":"28011",
    "sg:province":"Madrid",
    "wof:name":"Yustas Serrano Jesus",
    "wof:placetype":"venue"
},
  "geometry": {"coordinates":[-3.7300963402,40.4130210876],"type":"Point"}
}