{
  "type": "Feature",
  "properties": {
    "addr:full":"Finca Pedro Gomez, S/n Madrigal Vera C\u00e1ceres 10480",
    "addr:housenumber":"/ n",
    "addr:postcode":"10480",
    "addr:street":"Gomez S;Ca\u0301Ceres",
    "iso:country":"ES",
    "sg:address":"Finca Pedro Gomez, S/n",
    "sg:city":"Madrigal Vera",
    "sg:orig_category":"Cr\u00cda De Animales",
    "sg:phone":"+34 927 19 83 05",
    "sg:postcode":"10480",
    "sg:province":"C\u00e1ceres",
    "wof:name":"Dehesa De La Sierra S.l.",
    "wof:placetype":"venue"
},
  "geometry": {"coordinates":[-5.3663392067,40.1473236084],"type":"Point"}
}