{
  "type": "Feature",
  "properties": {
    "addr:full":"Calle de Ramon Y Cajal, 133 Robla Le\u00f3n 24640",
    "addr:housenumber":"133",
    "addr:postcode":"24640",
    "addr:street":"Calle De Ramon Y Cajal;Leo\u0301N",
    "iso:country":"ES",
    "sg:address":"Calle de Ramon Y Cajal, 133",
    "sg:city":"Robla",
    "sg:orig_category":"Electricidad (montaje, Ensamblaje De Componentes)",
    "sg:phone":"+34 987 57 03 26",
    "sg:postcode":"24640",
    "sg:province":"Le\u00f3n",
    "wof:name":"Autoelectricidad Manuel Suarez Diez E Hijos S.l.",
    "wof:placetype":"venue"
},
  "geometry": {"coordinates":[-5.6284275055,42.7941741943],"type":"Point"}
}