{
  "type": "Feature",
  "properties": {
    "addr:full":"Calle de Felipe Berge, 8 Alacant Alicante 03001",
    "addr:housenumber":"8",
    "addr:postcode":"03001",
    "addr:street":"Calle De Felipe Berge",
    "iso:country":"ES",
    "sg:address":"Calle de Felipe Berge, 8",
    "sg:city":"Alacant",
    "sg:orig_category":"Abogados",
    "sg:phone":"+34 965 20 19 43",
    "sg:postcode":"03001",
    "sg:province":"Alicante",
    "wof:name":"Quintanar Garrigos Maria Mercedes",
    "wof:placetype":"venue"
},
  "geometry": {"coordinates":[-0.4874300063,38.3451881409],"type":"Point"}
}