{
  "type": "Feature",
  "properties": {
    "addr:full":"Calle de Calderon De La Barca, 1 San Bartolome Murcia 30001",
    "addr:housenumber":"1",
    "addr:postcode":"30001",
    "addr:street":"Calle De Calderon De La Barca",
    "iso:country":"ES",
    "sg:address":"Calle de Calderon De La Barca, 1",
    "sg:city":"San Bartolome",
    "sg:orig_category":"Centros Empresariales",
    "sg:phone":"+34 968 22 54 91",
    "sg:postcode":"30001",
    "sg:province":"Murcia",
    "wof:name":"Asociacion De Empresas Medio Ambiente Region De Murcia",
    "wof:placetype":"venue"
},
  "geometry": {"coordinates":[-0.4617904127,38.4436988831],"type":"Point"}
}