{
  "type": "Feature",
  "properties": {
    "iso:country":"ES",
    "sg:address":"Calle de Antas, 2",
    "sg:city":"Pulpi",
    "sg:orig_category":"Asesor\u00cda Sobre Comunicaci\u00d3n De Empresas",
    "sg:phone":"+34 950 61 93 55",
    "sg:postcode":"04640",
    "sg:province":"Almer\u00eda",
    "wof:name":"Asfilaco Levante S.l.",
    "wof:placetype":"venue"
},
  "geometry": {"coordinates":[-1.750820756,37.4008140564],"type":"Point"}
}