{
  "type": "Feature",
  "properties": {
    "addr:full":"Ctra Villanueva-andujar, Km. 0093,7 Belalcazar C\u00f3rdoba 14280",
    "addr:postcode":"14280",
    "addr:street":"Ctra Villanueva-Andujar Km. 0093,7;Co\u0301Rdoba",
    "iso:country":"ES",
    "sg:address":"Ctra Villanueva-andujar, Km. 0093,7",
    "sg:city":"Belalcazar",
    "sg:orig_category":"Distribuci\u00d3n De Petr\u00d3leo Y Derivados",
    "sg:phone":"+34 957 14 60 31",
    "sg:postcode":"14280",
    "sg:province":"C\u00f3rdoba",
    "wof:name":"Hijos De Manuel Pla S.a.",
    "wof:placetype":"venue"
},
  "geometry": {"coordinates":[-5.1626439095,38.5788993835],"type":"Point"}
}