{
  "type": "Feature",
  "properties": {
    "iso:country":"ES",
    "sg:address":"Pg Colom, 138",
    "sg:city":"Ca'n Picafort",
    "sg:orig_category":"Doctores En Medicina",
    "sg:phone":"+34 971 85 05 91",
    "sg:postcode":"07458",
    "sg:province":"Islas Baleares",
    "wof:name":"Recreativos Dos M S.l.",
    "wof:placetype":"venue"
},
  "geometry": {"coordinates":[2.9117100239,39.6136398315],"type":"Point"}
}