{
  "type": "Feature",
  "properties": {
    "addr:full":"Calle de Alfereces Provisionales, 1 Jaen Ja\u00e9n 23005",
    "addr:housenumber":"1;jae\u0301n",
    "addr:postcode":"23005",
    "addr:street":"Calle De Alfereces Provisionales",
    "iso:country":"ES",
    "sg:address":"Calle de Alfereces Provisionales, 1",
    "sg:city":"Jaen",
    "sg:orig_category":"Agencias Y Agentes Comerciales, Representantes",
    "sg:phone":"+34 953 25 63 10",
    "sg:postcode":"23005",
    "sg:province":"Ja\u00e9n",
    "wof:name":"Garrido Martinez Jose",
    "wof:placetype":"venue"
},
  "geometry": {"coordinates":[-3.8222808838,37.7761688232],"type":"Point"}
}