{
  "type": "Feature",
  "properties": {
    "addr:full":"Asua-erreka Kalea, 2 Eibar Guip\u00f9zcoa 20600",
    "addr:housenumber":"2",
    "addr:postcode":"20600",
    "addr:street":"Asua-Erreka Kalea;Guipu\u0300Zcoa",
    "iso:country":"ES",
    "sg:address":"Asua-erreka Kalea, 2",
    "sg:city":"Eibar",
    "sg:orig_category":"Centros De Adelgazamiento Y De Est\u00c9tica",
    "sg:phone":"+34 943 12 71 53",
    "sg:postcode":"20600",
    "sg:province":"Guip\u00f9zcoa",
    "wof:name":"Suarez Rodriguez Maria Del Mar",
    "wof:placetype":"venue"
},
  "geometry": {"coordinates":[-2.4625411034,43.1877861023],"type":"Point"}
}