{
  "type": "Feature",
  "properties": {
    "iso:country":"ES",
    "sg:address":"Carr Juan Valera, 240",
    "sg:city":"Badalona",
    "sg:orig_category":"Fabricaci\u00d3n, Importaci\u00d3n De Material Y Sistemas De Telecomunicaciones",
    "sg:phone":"+34 933 99 63 58",
    "sg:postcode":"08914",
    "sg:province":"Barcelona",
    "wof:name":"Shafiq  Muhammad",
    "wof:placetype":"venue"
},
  "geometry": {"coordinates":[2.2225399017,41.4445457458],"type":"Point"}
}