{
  "type": "Feature",
  "properties": {
    "iso:country":"ES",
    "sg:address":"Avda Italia, 50",
    "sg:city":"Salamanca",
    "sg:orig_category":"Comercio, Reparaci\u00d3n De Motocicletas, Bicicletas Y Piezas Sueltas",
    "sg:phone":"+34 923 23 50 75",
    "sg:postcode":"37006",
    "sg:province":"Salamanca",
    "wof:name":"Araujo Ramos Antonio",
    "wof:placetype":"venue"
},
  "geometry": {"coordinates":[-5.6672239304,40.9719848633],"type":"Point"}
}