{
  "type": "Feature",
  "properties": {
    "addr:full":"Calle de Mayor, 190 Alcantarilla Murcia 30820",
    "addr:housenumber":"190",
    "addr:postcode":"30820",
    "addr:street":"Calle De Mayor",
    "iso:country":"ES",
    "sg:address":"Calle de Mayor, 190",
    "sg:city":"Alcantarilla",
    "sg:orig_category":"Confecci\u00d3n De Trajes Para Se\u00d1oras",
    "sg:phone":"+34 968 80 16 10",
    "sg:postcode":"30820",
    "sg:province":"Murcia",
    "wof:name":"Ruiz Bastida Benito",
    "wof:placetype":"venue"
},
  "geometry": {"coordinates":[-1.2184510231,37.9668159485],"type":"Point"}
}