{
  "type": "Feature",
  "properties": {
    "addr:full":"Avda Paz (de La), 4 Huesca Huesca 22003",
    "addr:housenumber":"4",
    "addr:postcode":"22003",
    "addr:street":"Avda Paz De La",
    "iso:country":"ES",
    "sg:address":"Avda Paz (de La), 4",
    "sg:city":"Huesca",
    "sg:orig_category":"Molduras, Junquillos, Listones Y Molduras Perforadas",
    "sg:phone":"+34 974 22 00 69",
    "sg:postcode":"22003",
    "sg:province":"Huesca",
    "wof:name":"Gracia Santuy Angel",
    "wof:placetype":"venue"
},
  "geometry": {"coordinates":[-0.4155569971,42.1391334534],"type":"Point"}
}