{
  "type": "Feature",
  "properties": {
    "iso:country":"ES",
    "sg:address":"Pase Extremadura, 72",
    "sg:city":"Madrid",
    "sg:orig_category":"Ropa Para Se\u00d1oras (al Por Menor)",
    "sg:phone":"+34 914 79 43 00",
    "sg:postcode":"28011",
    "sg:province":"Madrid",
    "wof:name":"Ana Sevillana Fashion S.l.",
    "wof:placetype":"venue"
},
  "geometry": {"coordinates":[-3.7310185432,40.412815094],"type":"Point"}
}