{
  "type": "Feature",
  "properties": {
    "iso:country":"ES",
    "sg:address":"Carrer de Roger De Flor, 24",
    "sg:city":"Barcelona",
    "sg:orig_category":"Molduras, Junquillos, Listones Y Molduras Perforadas",
    "sg:phone":"+34 933 00 24 50",
    "sg:postcode":"08018",
    "sg:province":"Barcelona",
    "wof:name":"Melgar Garcia Rosario",
    "wof:placetype":"venue"
},
  "geometry": {"coordinates":[2.1831710339,41.3910102844],"type":"Point"}
}