{
  "type": "Feature",
  "properties": {
    "iso:country":"ES",
    "sg:address":"El Chopo, 1",
    "sg:city":"Matalobos Paramo",
    "sg:orig_category":"Electricidad: Instaladores",
    "sg:phone":"+34 987 37 56 85",
    "sg:postcode":"24357",
    "sg:province":"Le\u00f3n",
    "wof:name":"Abella Carre\u00f1o Angel",
    "wof:placetype":"venue"
},
  "geometry": {"coordinates":[-5.814178,42.419071],"type":"Point"}
}