{
  "type": "Feature",
  "properties": {
    "addr:full":"Avda Santiago Galas, 2 Cabez\u00f3n Sal Cantabria 39500",
    "addr:housenumber":"2",
    "addr:postcode":"39500",
    "addr:street":"Avda Santiago Galas",
    "iso:country":"ES",
    "sg:address":"Avda Santiago Galas, 2",
    "sg:city":"Cabez\u00f3n Sal",
    "sg:orig_category":"Laboratorios Y Trabajos De Fotograf\u00cda, V\u00cddeo Y Cine",
    "sg:phone":"+34 942 70 12 50",
    "sg:postcode":"39500",
    "sg:province":"Cantabria",
    "wof:name":"Rodriguez Maestegui Laura",
    "wof:placetype":"venue"
},
  "geometry": {"coordinates":[-4.2301898003,43.3071746826],"type":"Point"}
}