{
  "type": "Feature",
  "properties": {
    "addr:full":"Calle de Gaston Castello, 16 Banyeres Mariola Alicante 03450",
    "addr:housenumber":"16",
    "addr:postcode":"03450",
    "addr:street":"Calle De Gaston Castello",
    "iso:country":"ES",
    "sg:address":"Calle de Gaston Castello, 16",
    "sg:city":"Banyeres Mariola",
    "sg:orig_category":"Fabricaci\u00d3n De Telas Y Sedas",
    "sg:phone":"+34 965 56 61 39",
    "sg:postcode":"03450",
    "sg:province":"Alicante",
    "wof:name":"Baldo Ribera Rafael",
    "wof:placetype":"venue"
},
  "geometry": {"coordinates":[-0.6538029909,38.7167625427],"type":"Point"}
}