{
  "type": "Feature",
  "properties": {
    "iso:country":"ES",
    "sg:address":"Carrer de Iluro, 98",
    "sg:city":"Mataro",
    "sg:orig_category":"Frutas, Legumbres Frescas Y Tempranas (al Por Menor)",
    "sg:phone":"+34 937 57 08 90",
    "sg:postcode":"08302",
    "sg:province":"Barcelona",
    "wof:name":"Medialdea Montalban Rosario",
    "wof:placetype":"venue"
},
  "geometry": {"coordinates":[2.4410390854,41.5351486206],"type":"Point"}
}