{
  "type": "Feature",
  "properties": {
    "addr:full":"Ctra. Casar De Caceres, Km. 0008,5 Casar Caceres C\u00e1ceres 10190",
    "addr:postcode":"10190",
    "addr:street":"Ctra. Casar De Caceres Km. 0008,5;Ca\u0301Ceres",
    "iso:country":"ES",
    "sg:address":"Ctra. Casar De Caceres, Km. 0008,5",
    "sg:city":"Casar Caceres",
    "sg:orig_category":"Distribuci\u00d3n De Petr\u00d3leo Y Derivados",
    "sg:phone":"+34 927 29 16 61",
    "sg:postcode":"10190",
    "sg:province":"C\u00e1ceres",
    "wof:name":"Estacion De Servicio La Casare\u00f1a S.l.",
    "wof:placetype":"venue"
},
  "geometry": {"coordinates":[-6.4156990051,39.5572166443],"type":"Point"}
}