{
  "type": "Feature",
  "properties": {
    "addr:full":"Calle de Octavio Paz, 16 Zaragoza Zaragoza 50018",
    "addr:housenumber":"16",
    "addr:postcode":"50018",
    "addr:street":"Calle De Octavio Paz",
    "iso:country":"ES",
    "sg:address":"Calle de Octavio Paz, 16",
    "sg:city":"Zaragoza",
    "sg:orig_category":"Empresas De Limpieza",
    "sg:phone":"+34 976 51 71 80",
    "sg:postcode":"50018",
    "sg:province":"Zaragoza",
    "wof:name":"Limpiezas Serrate Sl",
    "wof:placetype":"venue"
},
  "geometry": {"coordinates":[-0.8914089799,41.675151825],"type":"Point"}
}