{
  "type": "Feature",
  "properties": {
    "iso:country":"ES",
    "sg:address":"Caravaca, 88",
    "sg:city":"Lorca",
    "sg:orig_category":"Negocio De Madera",
    "sg:phone":"+34 968 46 20 99",
    "sg:postcode":"30800",
    "sg:province":"Murcia",
    "wof:name":"Antonio Lopez Ruiz S.l.",
    "wof:placetype":"venue"
},
  "geometry": {"coordinates":[-1.7006951571,37.6888122559],"type":"Point"}
}