{
  "type": "Feature",
  "properties": {
    "iso:country":"ES",
    "sg:address":"Calle de Gran Via, 26",
    "sg:city":"Donostia-san Sebastian",
    "sg:orig_category":"Ropa Para Se\u00d1oras Y Caballeros (al Por Menor)",
    "sg:phone":"+34 943 32 24 41",
    "sg:postcode":"20001",
    "sg:province":"Guip\u00f9zcoa",
    "wof:name":"Medrano Cabezudo Rosa Maria",
    "wof:placetype":"venue"
},
  "geometry": {"coordinates":[-1.9725110531,43.3229942322],"type":"Point"}
}