{
  "type": "Feature",
  "properties": {
    "iso:country":"ES",
    "sg:address":"Av Juli Garreta, 24",
    "sg:city":"S. Feliu Guixols",
    "sg:orig_category":"Radiocomunicaciones, Telefon\u00cda M\u00d3vil, Radiomensajer\u00cda: Servicios, Comercializaci\u00d3n",
    "sg:phone":"+34 972 32 73 00",
    "sg:postcode":"17220",
    "sg:province":"Girona",
    "wof:name":"Teliemporda S.l.",
    "wof:placetype":"venue"
},
  "geometry": {"coordinates":[3.0277729034,41.780330658],"type":"Point"}
}