{
  "type": "Feature",
  "properties": {
    "addr:full":"Av Josep Tarradellas, 136 Barcelona Barcelona 08029",
    "addr:housenumber":"136",
    "addr:postcode":"08029",
    "addr:street":"Av Josep Tarradellas",
    "iso:country":"ES",
    "sg:address":"Av Josep Tarradellas, 136",
    "sg:city":"Barcelona",
    "sg:orig_category":"Sociedades, Compa\u00d1\u00cdas Aseguradoras",
    "sg:phone":"+34 934 30 52 00",
    "sg:postcode":"08029",
    "sg:province":"Barcelona",
    "wof:name":"Mutua Reddis Matt Mutua De Accidentes De Trabajo Y Enfermedades Profesionales De La Seguridad Social",
    "wof:placetype":"venue"
},
  "geometry": {"coordinates":[2.144505024,41.3918418884],"type":"Point"}
}