{
  "type": "Feature",
  "properties": {
    "addr:full":"Calle de Lares, 3 Villanueva Serena Badajoz 06700",
    "addr:housenumber":"3",
    "addr:postcode":"06700",
    "addr:street":"Calle De Lares",
    "iso:country":"ES",
    "sg:address":"Calle de Lares, 3",
    "sg:city":"Villanueva Serena",
    "sg:orig_category":"Inmobiliaria (agencias)",
    "sg:phone":"+34 924 84 75 98",
    "sg:postcode":"06700",
    "sg:province":"Badajoz",
    "wof:name":"Eurocasa Cb",
    "wof:placetype":"venue"
},
  "geometry": {"coordinates":[-5.7980008125,38.9738883972],"type":"Point"}
}