{
  "type": "Feature",
  "properties": {
    "addr:full":"Calle de Pablo Pedro Astarloa Kalea, 15 Durango Vizcaya 48200",
    "addr:housenumber":"15",
    "addr:postcode":"48200",
    "addr:street":"Calle De Pablo Pedro Astarloa Kalea",
    "iso:country":"ES",
    "sg:address":"Calle de Pablo Pedro Astarloa Kalea, 15",
    "sg:city":"Durango",
    "sg:orig_category":"Ropa Para Ni\u00d1os (al Por Menor)",
    "sg:phone":"+34 946 23 26 32",
    "sg:postcode":"48200",
    "sg:province":"Vizcaya",
    "sg:website":"www.boboli.es",
    "wof:name":"Uribelarrea Uribelarrea Susana",
    "wof:placetype":"venue"
},
  "geometry": {"coordinates":[-2.629475832,43.1695213318],"type":"Point"}
}