{
  "type": "Feature",
  "properties": {
    "iso:country":"ES",
    "sg:address":"Calle de Duquesa De La Vega, 19",
    "sg:city":"Carde\u00f1a",
    "sg:orig_category":"Arquitectos",
    "sg:phone":"+34 957 17 44 97",
    "sg:postcode":"14445",
    "sg:province":"C\u00f3rdoba",
    "wof:name":"Merchan Torralbo Arturo",
    "wof:placetype":"venue"
},
  "geometry": {"coordinates":[-4.3565130234,38.2780685425],"type":"Point"}
}