{
  "type": "Feature",
  "properties": {
    "addr:full":"Calle de Siglo Xx, 3 Castro Urdiales Cantabria 39700",
    "addr:housenumber":"3",
    "addr:postcode":"39700",
    "addr:street":"Calle De Siglo Xx",
    "iso:country":"ES",
    "sg:address":"Calle de Siglo Xx, 3",
    "sg:city":"Castro Urdiales",
    "sg:orig_category":"Centros De Educaci\u00d3n Especial",
    "sg:phone":"+34 942 85 70 55",
    "sg:postcode":"39700",
    "sg:province":"Cantabria",
    "wof:name":"Colegio Publico De Educacion Infantil Y Primaria N\u00ba 5",
    "wof:placetype":"venue"
},
  "geometry": {"coordinates":[-3.2197370529,43.3840522766],"type":"Point"}
}