{
  "type": "Feature",
  "properties": {
    "addr:full":"Calle de Del Paso, 15 Gilena Sevilla 41565",
    "addr:housenumber":"15",
    "addr:postcode":"41565",
    "addr:street":"Calle De Del Paso",
    "iso:country":"ES",
    "sg:address":"Calle de Del Paso, 15",
    "sg:city":"Gilena",
    "sg:orig_category":"Librer\u00cdas",
    "sg:phone":"+34 955 82 67 23",
    "sg:postcode":"41565",
    "sg:province":"Sevilla",
    "wof:name":"Pozo Rodriguez Jose",
    "wof:placetype":"venue"
},
  "geometry": {"coordinates":[-4.9148836136,37.2504348755],"type":"Point"}
}