{
  "type": "Feature",
  "properties": {
    "iso:country":"ES",
    "sg:address":"Carrer de Sant Jaume (de), 5",
    "sg:city":"Vilassar De Mar",
    "sg:orig_category":"Reposter\u00cdas",
    "sg:phone":"+34 937 59 19 11",
    "sg:postcode":"08340",
    "sg:province":"Barcelona",
    "wof:name":"Maynou Viladrich Juan",
    "wof:placetype":"venue"
},
  "geometry": {"coordinates":[2.3894948959,41.5007705688],"type":"Point"}
}