{
  "type": "Feature",
  "properties": {
    "iso:country":"ES",
    "sg:address":"Calle de Alcalde Francisco Crespo, 1",
    "sg:city":"Le\u00f3n",
    "sg:orig_category":"Comercio De Piezas De Recambio Y De Accesorios De Veh\u00cdculos, Veh\u00cdculos Industriales",
    "sg:phone":"+34 987 21 14 04",
    "sg:postcode":"24005",
    "sg:province":"Le\u00f3n",
    "wof:name":"El Techa S.a.",
    "wof:placetype":"venue"
},
  "geometry": {"coordinates":[-5.5623035431,42.5902328491],"type":"Point"}
}