{
  "type": "Feature",
  "properties": {
    "addr:full":"Pase Ria, 1 Punta Umbria Huelva 21100",
    "addr:postcode":"21100",
    "addr:street":"Ria 1",
    "iso:country":"ES",
    "sg:address":"Pase Ria, 1",
    "sg:city":"Punta Umbria",
    "sg:orig_category":"Aparcamientos (infraestructuras, Accesorios)",
    "sg:phone":"+34 959 31 58 57",
    "sg:postcode":"21100",
    "sg:province":"Huelva",
    "wof:name":"Cintra Aparcamientos S.a.",
    "wof:placetype":"venue"
},
  "geometry": {"coordinates":[-6.9698939323,37.1816444397],"type":"Point"}
}