{
  "type": "Feature",
  "properties": {
    "iso:country":"ES",
    "sg:address":"Calle de Flores De Negron, 1",
    "sg:city":"Lucena",
    "sg:orig_category":"Papeler\u00cdas, Librer\u00cdas",
    "sg:phone":"+34 957 50 03 55",
    "sg:postcode":"14900",
    "sg:province":"C\u00f3rdoba",
    "wof:name":"Ca\u00f1ete Oca\u00f1a Diego",
    "wof:placetype":"venue"
},
  "geometry": {"coordinates":[-4.4826788902,37.4091186523],"type":"Point"}
}