{
  "type": "Feature",
  "properties": {
    "iso:country":"ES",
    "sg:address":"Calle de Cascanueces, 6",
    "sg:city":"Madrid",
    "sg:orig_category":"Importaci\u00d3n",
    "sg:phone":"+34 913 88 49 13",
    "sg:postcode":"28043",
    "sg:province":"Madrid",
    "wof:name":"Skylark International S. A.",
    "wof:placetype":"venue"
},
  "geometry": {"coordinates":[-3.6356599331,40.4556617737],"type":"Point"}
}