{
  "type": "Feature",
  "properties": {
    "addr:full":"Rua Campo Do Boy, 4 Pontevedra Pontevedra 36002",
    "addr:housenumber":"4",
    "addr:postcode":"36002",
    "addr:street":"Rua Campo",
    "iso:country":"ES",
    "sg:address":"Rua Campo Do Boy, 4",
    "sg:city":"Pontevedra",
    "sg:orig_category":"Ense\u00d1anza, Formaci\u00d3n Profesional: Aprendizaje",
    "sg:phone":"+34 986 84 63 16",
    "sg:postcode":"36002",
    "sg:province":"Pontevedra",
    "wof:name":"Oficina Tecnica De Inventariacion Catastral S. L.",
    "wof:placetype":"venue"
},
  "geometry": {"coordinates":[-8.6522531509,42.4305305481],"type":"Point"}
}