{
  "type": "Feature",
  "properties": {
    "addr:full":"Calle de Jose Antonio, 72 Serranillos \u00c1vila 05116",
    "addr:housenumber":"72",
    "addr:postcode":"05116",
    "addr:street":"Calle De Jose Antonio",
    "iso:country":"ES",
    "sg:address":"Calle de Jose Antonio, 72",
    "sg:city":"Serranillos",
    "sg:orig_category":"Farmacias",
    "sg:phone":"+34 920 28 91 17",
    "sg:postcode":"05116",
    "sg:province":"\u00c1vila",
    "wof:name":"Romero Mendoza Luis",
    "wof:placetype":"venue"
},
  "geometry": {"coordinates":[-4.9113960266,40.3363761902],"type":"Point"}
}