{
  "type": "Feature",
  "properties": {
    "iso:country":"ES",
    "sg:address":"Calle de Maestrat, 6",
    "sg:city":"Puerto",
    "sg:orig_category":"Supermercados Y Hipermercados",
    "sg:phone":"+34 962 68 36 26",
    "sg:postcode":"46520",
    "sg:province":"Valencia",
    "wof:name":"Distribuidora Internacional De Alimentacion S.a.",
    "wof:placetype":"venue"
},
  "geometry": {"coordinates":[-0.2318949997,39.6640777588],"type":"Point"}
}