{
  "type": "Feature",
  "properties": {
    "iso:country":"ES",
    "sg:address":"Calle de Abastos (de), 142",
    "sg:city":"Aranjuez",
    "sg:orig_category":"Loter\u00cda Y T\u00d3mbola",
    "sg:phone":"+34 918 01 16 33",
    "sg:postcode":"28300",
    "sg:province":"Madrid",
    "wof:name":"Escobar Jerez Gonzalo Antonio",
    "wof:placetype":"venue"
},
  "geometry": {"coordinates":[-3.598379612,40.0316925049],"type":"Point"}
}