{
  "type": "Feature",
  "properties": {
    "iso:country":"ES",
    "sg:address":"Calle de Boggiero, 118",
    "sg:city":"Zaragoza",
    "sg:orig_category":"Molduras, Junquillos, Listones Y Molduras Perforadas",
    "sg:phone":"+34 976 43 63 09",
    "sg:postcode":"50003",
    "sg:province":"Zaragoza",
    "wof:name":"Val Gomez Federico Jesus",
    "wof:placetype":"venue"
},
  "geometry": {"coordinates":[-0.8893117905,41.6559944153],"type":"Point"}
}