{
  "type": "Feature",
  "properties": {
    "addr:full":"Carrer de Barcelona, 14 Calella Barcelona 08370",
    "addr:housenumber":"14",
    "addr:postcode":"08370",
    "addr:street":"Carrer De Barcelona",
    "iso:country":"ES",
    "sg:address":"Carrer de Barcelona, 14",
    "sg:city":"Calella",
    "sg:orig_category":"Servicios De Higiene Y Peluquer\u00cda Para Perros Y Gatos",
    "sg:phone":"+34 937 66 41 50",
    "sg:postcode":"08370",
    "sg:province":"Barcelona",
    "wof:name":"Villegas Viles Marina",
    "wof:placetype":"venue"
},
  "geometry": {"coordinates":[2.6565959454,41.6125869751],"type":"Point"}
}