{
  "type": "Feature",
  "properties": {
    "addr:full":"Calle de Acisclo Diaz, 2 San Nicolas Murcia 30005",
    "addr:housenumber":"2",
    "addr:postcode":"30005",
    "addr:street":"Calle De Acisclo Diaz",
    "iso:country":"ES",
    "sg:address":"Calle de Acisclo Diaz, 2",
    "sg:city":"San Nicolas",
    "sg:orig_category":"M\u00c9dicos: Cardiolog\u00cda Y Afecciones Cardiovasculares",
    "sg:phone":"+34 968 28 50 34",
    "sg:postcode":"30005",
    "sg:province":"Murcia",
    "wof:name":"Valdes Chavarri Mariano",
    "wof:placetype":"venue"
},
  "geometry": {"coordinates":[-1.1323859692,37.9880027771],"type":"Point"}
}