{
  "type": "Feature",
  "properties": {
    "addr:full":"Av Girona, 7 S. Gregori Girona 17150",
    "addr:housenumber":"7",
    "addr:postcode":"17150",
    "addr:street":"Av Girona;S. Gregori",
    "iso:country":"ES",
    "sg:address":"Av Girona, 7",
    "sg:city":"S. Gregori",
    "sg:orig_category":"Carnicer\u00cdas, Carnicer\u00cdas",
    "sg:phone":"+34 972 42 81 76",
    "sg:postcode":"17150",
    "sg:province":"Girona",
    "wof:name":"Guardia Tarres Angel",
    "wof:placetype":"venue"
},
  "geometry": {"coordinates":[2.7614600658,41.9905090332],"type":"Point"}
}