{
  "type": "Feature",
  "properties": {
    "addr:full":"Calle de Barraix, 10 Valencia Valencia 46015",
    "addr:housenumber":"10",
    "addr:postcode":"46015",
    "addr:street":"Calle De Barraix",
    "iso:country":"ES",
    "sg:address":"Calle de Barraix, 10",
    "sg:city":"Valencia",
    "sg:orig_category":"Promotores Constructores",
    "sg:phone":"+34 963 49 11 07",
    "sg:postcode":"46015",
    "sg:province":"Valencia",
    "wof:name":"Comunidad De Propietarios Barraix 10",
    "wof:placetype":"venue"
},
  "geometry": {"coordinates":[-0.3974418044,39.4929199219],"type":"Point"}
}