{
  "type": "Feature",
  "properties": {
    "addr:full":"A Laxa, 33 Laxa Ourense 32417",
    "addr:housenumber":"33",
    "addr:postcode":"32417",
    "addr:street":"Laxa",
    "iso:country":"ES",
    "sg:address":"A Laxa, 33",
    "sg:city":"Laxa",
    "sg:orig_category":"Alimentaci\u00d3n General (al Por Menor)",
    "sg:phone":"+34 988 49 28 85",
    "sg:postcode":"32417",
    "sg:province":"Ourense",
    "wof:name":"Santamaria Gil Amalia",
    "wof:placetype":"venue"
},
  "geometry": {"coordinates":[-8.1362161636,42.2448577881],"type":"Point"}
}