{
  "type": "Feature",
  "properties": {
    "iso:country":"ES",
    "sg:address":"Barrio El Crucero, 25",
    "sg:city":"Gama",
    "sg:orig_category":"Empresas De Carpinter\u00cda De Madera",
    "sg:phone":"+34 942 64 20 44",
    "sg:postcode":"39790",
    "sg:province":"Cantabria",
    "wof:name":"Ruiz Hornedo Manuel Angel",
    "wof:placetype":"venue"
},
  "geometry": {"coordinates":[-3.5058469772,43.4200515747],"type":"Point"}
}