{
  "type": "Feature",
  "properties": {
    "iso:country":"ES",
    "sg:address":"Avda Espa\u00d1a (de), S/n",
    "sg:city":"San Eugenio Bajo",
    "sg:orig_category":"Inmobiliaria (agencias)",
    "sg:phone":"+34 922 71 46 45",
    "sg:postcode":"38660",
    "sg:province":"Santa Cruz De Tenerife",
    "wof:name":"Terranova Holiday Promotions International S.l.",
    "wof:placetype":"venue"
},
  "geometry": {"coordinates":[-16.7335681915,28.0807247162],"type":"Point"}
}