{
  "type": "Feature",
  "properties": {
    "addr:full":"Praz Igrexa, 1 Fene La Coru\u00f1a 15500",
    "addr:housenumber":"1",
    "addr:postcode":"15500",
    "addr:street":"Praz Igrexa;La Corun\u0303A",
    "iso:country":"ES",
    "sg:address":"Praz Igrexa, 1",
    "sg:city":"Fene",
    "sg:orig_category":"Centros Empresariales",
    "sg:phone":"+34 981 34 17 04",
    "sg:postcode":"15500",
    "sg:province":"La Coru\u00f1a",
    "wof:name":"Asociacion De Empresarios Iniciativa Empresarial Del Noroeste",
    "wof:placetype":"venue"
},
  "geometry": {"coordinates":[-8.1720991135,43.4653053284],"type":"Point"}
}