{
  "type": "Feature",
  "properties": {
    "iso:country":"ES",
    "sg:address":"Calle de Virgen De La Vega, 32",
    "sg:city":"Haro",
    "sg:orig_category":"Fabricaci\u00d3n, Instalaci\u00d3n Y Reparaci\u00d3n De Bombas",
    "sg:phone":"+34 941 31 03 89",
    "sg:postcode":"26200",
    "sg:province":"La Rioja",
    "wof:name":"Puelles Orive Miguel",
    "wof:placetype":"venue"
},
  "geometry": {"coordinates":[-2.8499670029,42.5768241882],"type":"Point"}
}