{
  "type": "Feature",
  "properties": {
    "iso:country":"ES",
    "sg:address":"Calle de Paloma, 4",
    "sg:city":"Zubia",
    "sg:orig_category":"Supermercados Y Hipermercados",
    "sg:phone":"+34 958 89 03 96",
    "sg:postcode":"18140",
    "sg:province":"Granada",
    "wof:name":"Molina Benitez Manuel",
    "wof:placetype":"venue"
},
  "geometry": {"coordinates":[-3.5784871578,37.1181144714],"type":"Point"}
}