{
  "type": "Feature",
  "properties": {
    "iso:country":"ES",
    "sg:address":"Mcdo Dr. Casas, S/n",
    "sg:city":"Zaragoza",
    "sg:orig_category":"Carnicer\u00cdas, Carnicer\u00cdas",
    "sg:phone":"+34 976 21 11 49",
    "sg:postcode":"50008",
    "sg:province":"Zaragoza",
    "wof:name":"Sorribas Retabe Rogelio",
    "wof:placetype":"venue"
},
  "geometry": {"coordinates":[-0.8835840225,41.6434440613],"type":"Point"}
}