{
  "type": "Feature",
  "properties": {
    "addr:full":"Pase Pastrana (de), 14 Alcala Henares Madrid 28803",
    "addr:postcode":"28803",
    "iso:country":"ES",
    "sg:address":"Pase Pastrana (de), 14",
    "sg:city":"Alcala Henares",
    "sg:orig_category":"Producci\u00d3n, Distribuci\u00d3n De Electricidad",
    "sg:phone":"+34 918 82 37 58",
    "sg:postcode":"28803",
    "sg:province":"Madrid",
    "wof:name":"Lopez Ferri Antonio",
    "wof:placetype":"venue"
},
  "geometry": {"coordinates":[-3.3670709133,40.4763336182],"type":"Point"}
}