{
  "type": "Feature",
  "properties": {
    "iso:country":"ES",
    "sg:address":"Avda Carlos I De, 8",
    "sg:city":"Donostia-san Sebastian",
    "sg:orig_category":"Doctores En Medicina",
    "sg:phone":"+34 943 45 25 35",
    "sg:postcode":"20011",
    "sg:province":"Guip\u00f9zcoa",
    "wof:name":"Ignacio Barrero Casares",
    "wof:placetype":"venue"
},
  "geometry": {"coordinates":[-1.9794123173,43.3055000305],"type":"Point"}
}