{
  "type": "Feature",
  "properties": {
    "addr:full":"Carrer de Armilla, 101 Armilla Granada 18100",
    "addr:housenumber":"101",
    "addr:postcode":"18100",
    "addr:street":"Carrer De Armilla",
    "iso:country":"ES",
    "sg:address":"Carrer de Armilla, 101",
    "sg:city":"Armilla",
    "sg:orig_category":"Promotores Constructores",
    "sg:phone":"+34 958 12 11 35",
    "sg:postcode":"18100",
    "sg:province":"Granada",
    "wof:name":"Promociones Y Contratas La Bolera S.l.",
    "wof:placetype":"venue"
},
  "geometry": {"coordinates":[-3.6143410206,37.1516227722],"type":"Point"}
}