{
  "type": "Feature",
  "properties": {
    "addr:full":"Ramil, S/n Ramil Lugo 27298",
    "addr:postcode":"27298",
    "addr:street":"S / N",
    "iso:country":"ES",
    "sg:address":"Ramil, S/n",
    "sg:city":"Ramil",
    "sg:orig_category":"Empresas De Desmonte",
    "sg:phone":"+34 982 21 58 76",
    "sg:postcode":"27298",
    "sg:province":"Lugo",
    "wof:name":"Prado Rois Ignacio",
    "wof:placetype":"venue"
},
  "geometry": {"coordinates":[-7.5915489197,43.0352363586],"type":"Point"}
}