{
  "type": "Feature",
  "properties": {
    "addr:full":"Calle de Reina, 136 Valencia Valencia 46011",
    "addr:housenumber":"136",
    "addr:postcode":"46011",
    "addr:street":"Calle De Reina",
    "iso:country":"ES",
    "sg:address":"Calle de Reina, 136",
    "sg:city":"Valencia",
    "sg:orig_category":"Centros De Coordinaci\u00d3n",
    "sg:phone":"+34 963 56 29 50",
    "sg:postcode":"46011",
    "sg:province":"Valencia",
    "wof:name":"Soler Canto Vicente",
    "wof:placetype":"venue"
},
  "geometry": {"coordinates":[-0.3285931051,39.4691238403],"type":"Point"}
}