{
  "type": "Feature",
  "properties": {
    "iso:country":"ES",
    "sg:address":"Avda Luis Urrengoetxea, 6",
    "sg:city":"Amorebieta",
    "sg:orig_category":"Fotocopias, Reprograf\u00cda",
    "sg:phone":"+34 946 30 88 62",
    "sg:postcode":"48340",
    "sg:province":"Vizcaya",
    "wof:name":"Ugarte Arroitajauregi Alexander",
    "wof:placetype":"venue"
},
  "geometry": {"coordinates":[-2.7334780693,43.2210197449],"type":"Point"}
}