{
  "type": "Feature",
  "properties": {
    "iso:country":"ES",
    "sg:address":"Trva Alfonso Vii, 6",
    "sg:city":"Coria",
    "sg:orig_category":"Tatuajes",
    "sg:phone":"+34 927 50 62 70",
    "sg:postcode":"10800",
    "sg:province":"C\u00e1ceres",
    "wof:name":"Garcia Blasco Maria Carmen",
    "wof:placetype":"venue"
},
  "geometry": {"coordinates":[-6.5384469032,39.9893531799],"type":"Point"}
}