{
  "type": "Feature",
  "properties": {
    "iso:country":"ES",
    "sg:address":"Calle de Santa Barbara, 20",
    "sg:city":"Totana",
    "sg:orig_category":"Ense\u00d1anza: Profesiones Art\u00cdsticas",
    "sg:phone":"+34 968 42 75 68",
    "sg:postcode":"30850",
    "sg:province":"Murcia",
    "wof:name":"Moreno Tudela Silvia",
    "wof:placetype":"venue"
},
  "geometry": {"coordinates":[-1.498239994,37.7702064514],"type":"Point"}
}