{
  "type": "Feature",
  "properties": {
    "addr:full":"Plaz Bib-rambla (de), 12 Granada Granada 18001",
    "addr:postcode":"18001",
    "addr:street":"Plaz",
    "iso:country":"ES",
    "sg:address":"Plaz Bib-rambla (de), 12",
    "sg:city":"Granada",
    "sg:orig_category":"Lencer\u00cda Femenina, Corseter\u00cda, Trajes De Ba\u00d1o (al Por Menor)",
    "sg:phone":"+34 958 26 36 52",
    "sg:postcode":"18001",
    "sg:province":"Granada",
    "wof:name":"Cambil Garcia Manuel",
    "wof:placetype":"venue"
},
  "geometry": {"coordinates":[-3.600315094,37.1753158569],"type":"Point"}
}