{
  "type": "Feature",
  "properties": {
    "addr:full":"Ctra Tarragona-san Sebastian, Km. 0130,3 Binefar Huesca 22500",
    "addr:postcode":"22500",
    "addr:street":"Ctra Tarragona-San Sebastian Km. 0130,3",
    "iso:country":"ES",
    "sg:address":"Ctra Tarragona-san Sebastian, Km. 0130,3",
    "sg:city":"Binefar",
    "sg:orig_category":"Construcci\u00d3n Mec\u00c1nica",
    "sg:phone":"+34 974 43 06 72",
    "sg:postcode":"22500",
    "sg:province":"Huesca",
    "wof:name":"Mecanicas Pema S.cv.",
    "wof:placetype":"venue"
},
  "geometry": {"coordinates":[0.2927800119,41.8499412537],"type":"Point"}
}