{
  "type": "Feature",
  "properties": {
    "iso:country":"ES",
    "sg:address":"Calle de Joaquin Maria Jalon, 15",
    "sg:city":"Valladolid",
    "sg:orig_category":"Quincaller\u00cda (al Por Menor)",
    "sg:phone":"+34 983 23 77 23",
    "sg:postcode":"47008",
    "sg:province":"Valladolid",
    "wof:name":"Lora Bastardo Angel",
    "wof:placetype":"venue"
},
  "geometry": {"coordinates":[-4.7408699989,41.6281585693],"type":"Point"}
}