{
  "type": "Feature",
  "properties": {
    "iso:country":"ES",
    "sg:address":"Calle de Mayor, 30",
    "sg:city":"Alesanco",
    "sg:orig_category":"Patatas (al Por Mayor)",
    "sg:phone":"+34 941 37 90 10",
    "sg:postcode":"26324",
    "sg:province":"La Rioja",
    "wof:name":"Jose Antonio Andres Rubio Y Otros Cdad",
    "wof:placetype":"venue"
},
  "geometry": {"coordinates":[-2.8193609715,42.4156913757],"type":"Point"}
}