{
  "type": "Feature",
  "properties": {
    "addr:full":"I. De La Cartuja, S/n Sevilla Sevilla 41092",
    "addr:housenumber":"s / n",
    "addr:postcode":"41092",
    "addr:street":"I. De La Cartuja",
    "iso:country":"ES",
    "sg:address":"I. De La Cartuja, S/n",
    "sg:city":"Sevilla",
    "sg:orig_category":"Empresarios",
    "sg:phone":"+34 954 46 75 06",
    "sg:postcode":"41092",
    "sg:province":"Sevilla",
    "wof:name":"Fundacion Biacs",
    "wof:placetype":"venue"
},
  "geometry": {"coordinates":[-6.0046668053,37.3963851929],"type":"Point"}
}