{
  "type": "Feature",
  "properties": {
    "addr:full":"Calle de Arrabal (el), 7 Cedrillas Teruel 44147",
    "addr:housenumber":"7",
    "addr:postcode":"44147",
    "addr:street":"Calle De Arrabal El",
    "iso:country":"ES",
    "sg:address":"Calle de Arrabal (el), 7",
    "sg:city":"Cedrillas",
    "sg:orig_category":"Plomeros",
    "sg:phone":"+34 978 77 41 91",
    "sg:postcode":"44147",
    "sg:province":"Teruel",
    "wof:name":"Fuentes Sanchez Serafin",
    "wof:placetype":"venue"
},
  "geometry": {"coordinates":[-0.8582394719,40.4354667664],"type":"Point"}
}