{
  "type": "Feature",
  "properties": {
    "iso:country":"ES",
    "sg:address":"Avda Andalucia (de), 32",
    "sg:city":"Estacion",
    "sg:orig_category":"Loter\u00cda Y T\u00d3mbola",
    "sg:phone":"+34 952 42 10 67",
    "sg:postcode":"29580",
    "sg:province":"M\u00e1laga",
    "wof:name":"Martin Mayo Rosa",
    "wof:placetype":"venue"
},
  "geometry": {"coordinates":[-4.6096692085,36.7364311218],"type":"Point"}
}