{
  "type": "Feature",
  "properties": {
    "iso:country":"ES",
    "sg:address":"Avda Bulevar De El Ejido, 269",
    "sg:city":"Ejido",
    "sg:orig_category":"Bisuter\u00cda, Joyer\u00cda, Relojer\u00cda (al Por Menor)",
    "sg:phone":"+34 950 48 14 55",
    "sg:postcode":"04700",
    "sg:province":"Almer\u00eda",
    "wof:name":"Jose Caro Joyeros S.l.",
    "wof:placetype":"venue"
},
  "geometry": {"coordinates":[-2.8058309555,36.7609977722],"type":"Point"}
}