{
  "type": "Feature",
  "properties": {
    "iso:country":"ES",
    "sg:address":"Calle de Pedro Tarquis Rodriguez, 2",
    "sg:city":"Santa Cruz De Tenerife",
    "sg:orig_category":"T\u00c9cnicos Veterinarios",
    "sg:phone":"+34 922 66 28 82",
    "sg:postcode":"38009",
    "sg:province":"Santa Cruz De Tenerife",
    "wof:name":"Corona Afonso Alejandra Pamela",
    "wof:placetype":"venue"
},
  "geometry": {"coordinates":[-17.7755756378,28.6416091919],"type":"Point"}
}