{
  "type": "Feature",
  "properties": {
    "iso:country":"ES",
    "sg:address":"Plaza Josu Murueta, 2",
    "sg:city":"Erandio",
    "sg:orig_category":"Molduras, Junquillos, Listones Y Molduras Perforadas",
    "sg:phone":"+34 944 17 02 08",
    "sg:postcode":"48950",
    "sg:province":"Vizcaya",
    "wof:name":"Julian Lamela Nieves",
    "wof:placetype":"venue"
},
  "geometry": {"coordinates":[-2.9835391045,43.3166275024],"type":"Point"}
}