{
  "type": "Feature",
  "properties": {
    "iso:country":"ES",
    "sg:address":"Calle de Espa\u00d1oleto, 26",
    "sg:city":"Madrid",
    "sg:orig_category":"Urbanistas",
    "sg:phone":"+34 913 10 11 71",
    "sg:postcode":"28010",
    "sg:province":"Madrid",
    "wof:name":"Homo Structor S.l.",
    "wof:placetype":"venue"
},
  "geometry": {"coordinates":[-3.6941430569,40.4310646057],"type":"Point"}
}