{
  "type": "Feature",
  "properties": {
    "addr:full":"Pg Joan Moreira (de), 7 Tortosa Tarragona 43500",
    "addr:postcode":"43500",
    "addr:street":"Pg Joan Moreira De",
    "iso:country":"ES",
    "sg:address":"Pg Joan Moreira (de), 7",
    "sg:city":"Tortosa",
    "sg:orig_category":"M\u00c1quinas De Escribir, M\u00c1quinas De Oficina (al Por Menor, Reparaci\u00d3n)",
    "sg:phone":"+34 977 44 93 67",
    "sg:postcode":"43500",
    "sg:province":"Tarragona",
    "wof:name":"Informatica San Jordi S.l.",
    "wof:placetype":"venue"
},
  "geometry": {"coordinates":[0.5181990266,40.8063468933],"type":"Point"}
}