{
  "type": "Feature",
  "properties": {
    "addr:full":"Calle de San Andres, S/n San Pedro Alcantara M\u00e1laga 29670",
    "addr:housenumber":"s / n",
    "addr:postcode":"29670",
    "addr:street":"Calle De San Andres",
    "iso:country":"ES",
    "sg:address":"Calle de San Andres, S/n",
    "sg:city":"San Pedro Alcantara",
    "sg:orig_category":"Costureras",
    "sg:phone":"+34 952 78 00 37",
    "sg:postcode":"29670",
    "sg:province":"M\u00e1laga",
    "wof:name":"Pareja Morales Isabel",
    "wof:placetype":"venue"
},
  "geometry": {"coordinates":[-4.988173008,36.484161377],"type":"Point"}
}