{
  "type": "Feature",
  "properties": {
    "iso:country":"ES",
    "sg:address":"Av Gava, S/n",
    "sg:city":"Viladecans",
    "sg:orig_category":"Librer\u00cdas",
    "sg:phone":"+34 936 58 18 78",
    "sg:postcode":"08840",
    "sg:province":"Barcelona",
    "wof:name":"Rosello Dominguez Jose Luis",
    "wof:placetype":"venue"
},
  "geometry": {"coordinates":[2.0172851086,41.3136558533],"type":"Point"}
}