{
  "type": "Feature",
  "properties": {
    "addr:full":"Calle de Jose Artes De Arcos, 14 Almeria Almer\u00eda 04004",
    "addr:housenumber":"14",
    "addr:postcode":"04004",
    "addr:street":"Calle De Jose Artes De Arcos",
    "iso:country":"ES",
    "sg:address":"Calle de Jose Artes De Arcos, 14",
    "sg:city":"Almeria",
    "sg:orig_category":"Caf\u00c9s, Bares, Cervecer\u00cdas",
    "sg:phone":"+34 950 24 39 25",
    "sg:postcode":"04004",
    "sg:province":"Almer\u00eda",
    "wof:name":"Caride Gonzalez Jose Manuel",
    "wof:placetype":"venue"
},
  "geometry": {"coordinates":[-2.4591488838,36.8366203308],"type":"Point"}
}