{
  "type": "Feature",
  "properties": {
    "iso:country":"ES",
    "sg:address":"Barcelona(urb Camposol), 13",
    "sg:city":"Mazarron",
    "sg:orig_category":"Peluquer\u00cdas, Peluquer\u00cda Mixta",
    "sg:phone":"+34 968 53 71 43",
    "sg:postcode":"30870",
    "sg:province":"Murcia",
    "wof:name":"Canovas Martinez Manuel",
    "wof:placetype":"venue"
},
  "geometry": {"coordinates":[-1.31378901,37.598865509],"type":"Point"}
}