{
  "type": "Feature",
  "properties": {
    "iso:country":"ES",
    "sg:address":"Carr Independencia, 251",
    "sg:city":"Badalona",
    "sg:orig_category":"Reposter\u00cdas",
    "sg:phone":"+34 933 83 61 52",
    "sg:postcode":"08915",
    "sg:province":"Barcelona",
    "wof:name":"Forn De Llenya Riera Sl",
    "wof:placetype":"venue"
},
  "geometry": {"coordinates":[2.2410230637,41.4611167908],"type":"Point"}
}