{
  "type": "Feature",
  "properties": {
    "addr:full":"Calle de Simancas, 40 Palmas De Gran Canaria Las Palmas 35010",
    "addr:housenumber":"40",
    "addr:postcode":"35010",
    "addr:street":"Calle De Simancas",
    "iso:country":"ES",
    "sg:address":"Calle de Simancas, 40",
    "sg:city":"Palmas De Gran Canaria",
    "sg:orig_category":"Venta, Colocaci\u00d3n, Reparaci\u00d3n De Radiadores Para Veh\u00cdculos",
    "sg:phone":"+34 928 26 91 43",
    "sg:postcode":"35010",
    "sg:province":"Las Palmas",
    "wof:name":"Morata Conesa Francisco",
    "wof:placetype":"venue"
},
  "geometry": {"coordinates":[-15.4454889297,28.1285419464],"type":"Point"}
}