{
  "type": "Feature",
  "properties": {
    "addr:full":"C/ Pau Ferran, 5 Tarrega Lleida 25300",
    "addr:housenumber":"5",
    "addr:postcode":"25300",
    "addr:street":"C / Pau Ferran",
    "iso:country":"ES",
    "sg:address":"C/ Pau Ferran, 5",
    "sg:city":"Tarrega",
    "sg:orig_category":"Institutos De Belleza",
    "sg:phone":"+34 973 31 38 01",
    "sg:postcode":"25300",
    "sg:province":"Lleida",
    "wof:name":"Martinez Pons Laura",
    "wof:placetype":"venue"
},
  "geometry": {"coordinates":[1.139171958,41.6526031494],"type":"Point"}
}