{
  "type": "Feature",
  "properties": {
    "iso:country":"ES",
    "sg:address":"Calle de Rivas, 24",
    "sg:city":"Sestao",
    "sg:orig_category":"Molduras, Junquillos, Listones Y Molduras Perforadas",
    "sg:phone":"+34 944 96 11 13",
    "sg:postcode":"48910",
    "sg:province":"Vizcaya",
    "wof:name":"Vazquez Lopez Amante",
    "wof:placetype":"venue"
},
  "geometry": {"coordinates":[-2.9902439117,43.3066902161],"type":"Point"}
}