{
  "type": "Feature",
  "properties": {
    "iso:country":"ES",
    "sg:address":"Calle de Doctor Mulero, 8",
    "sg:city":"Valle Trapaga",
    "sg:orig_category":"Mercer\u00cda, Lencer\u00cda (al Por Menor)",
    "sg:phone":"+34 944 92 10 01",
    "sg:postcode":"48510",
    "sg:province":"Vizcaya",
    "wof:name":"Luisa Pilar San Emeterio Bonatxea",
    "wof:placetype":"venue"
},
  "geometry": {"coordinates":[-3.036850214,43.3029975891],"type":"Point"}
}