{
  "type": "Feature",
  "properties": {
    "addr:full":"Carrer de Rossello, 23 Mataro Barcelona 08303",
    "addr:housenumber":"23",
    "addr:postcode":"08303",
    "addr:street":"Carrer De Rossello",
    "iso:country":"ES",
    "sg:address":"Carrer de Rossello, 23",
    "sg:city":"Mataro",
    "sg:orig_category":"Bisuter\u00cda, Joyer\u00cda, Relojer\u00cda (al Por Menor)",
    "sg:phone":"+34 937 98 31 36",
    "sg:postcode":"08303",
    "sg:province":"Barcelona",
    "wof:name":"Garcia Ubeda Miguel",
    "wof:placetype":"venue"
},
  "geometry": {"coordinates":[2.4249179363,41.5393028259],"type":"Point"}
}