{
  "type": "Feature",
  "properties": {
    "iso:country":"ES",
    "sg:address":"Calle de Pintor Balaca, 38",
    "sg:city":"Cartagena",
    "sg:orig_category":"Cl\u00cdnicas M\u00c9dicas",
    "sg:phone":"+34 968 52 63 12",
    "sg:postcode":"30204",
    "sg:province":"Murcia",
    "wof:name":"Ceretrur S.l.",
    "wof:placetype":"venue"
},
  "geometry": {"coordinates":[-0.9876090288,37.6088218689],"type":"Point"}
}