{
  "type": "Feature",
  "properties": {
    "iso:country":"ES",
    "sg:address":"Avgd Setze De Juliol, 9",
    "sg:city":"Burriana",
    "sg:orig_category":"Chapister\u00cda",
    "sg:phone":"+34 964 51 29 53",
    "sg:postcode":"12530",
    "sg:province":"Castell\u00f3n",
    "wof:name":"Talleres Rio Ana S.l.",
    "wof:placetype":"venue"
},
  "geometry": {"coordinates":[-0.078339003,39.8909912109],"type":"Point"}
}