{
  "type": "Feature",
  "properties": {
    "iso:country":"ES",
    "sg:address":"El Palacio, S/n",
    "sg:city":"San Esteban",
    "sg:orig_category":"Agencias Y Agentes Comerciales, Representantes",
    "sg:phone":"+34 985 78 32 15",
    "sg:postcode":"33162",
    "sg:province":"Asturias",
    "wof:name":"G.a.c.camino Palacio S.l.",
    "wof:placetype":"venue"
},
  "geometry": {"coordinates":[-5.8799290657,43.2809143066],"type":"Point"}
}