{
  "type": "Feature",
  "properties": {
    "iso:country":"ES",
    "sg:address":"Calle de General Bergareche, 5",
    "sg:city":"Irun",
    "sg:orig_category":"Supermercados Y Hipermercados",
    "sg:phone":"+34 943 63 17 38",
    "sg:postcode":"20304",
    "sg:province":"Guip\u00f9zcoa",
    "wof:name":"Aurole S.l.",
    "wof:placetype":"venue"
},
  "geometry": {"coordinates":[-1.7831840515,43.3408317566],"type":"Point"}
}