{
  "type": "Feature",
  "properties": {
    "iso:country":"ES",
    "sg:address":"Calle de San Roque, 5",
    "sg:city":"Ibi",
    "sg:orig_category":"Institutos De Belleza",
    "sg:phone":"+34 966 55 01 09",
    "sg:postcode":"03440",
    "sg:province":"Alicante",
    "wof:name":"Diva C.b.",
    "wof:placetype":"venue"
},
  "geometry": {"coordinates":[-0.5759909749,38.6250267029],"type":"Point"}
}