{
  "type": "Feature",
  "properties": {
    "addr:full":"Carrer de Llobateras, 86 Rubi Barcelona 08191",
    "addr:housenumber":"86",
    "addr:postcode":"08191",
    "addr:street":"Carrer De Llobateras",
    "iso:country":"ES",
    "sg:address":"Carrer de Llobateras, 86",
    "sg:city":"Rubi",
    "sg:orig_category":"Sales (al Por Mayor)",
    "sg:phone":"+34 935 88 18 28",
    "sg:postcode":"08191",
    "sg:province":"Barcelona",
    "wof:name":"Nyam-\u00d1am S.l.",
    "wof:placetype":"venue"
},
  "geometry": {"coordinates":[2.0346200466,41.4888534546],"type":"Point"}
}