{
  "type": "Feature",
  "properties": {
    "addr:full":"Avda Europa, 4 Toledo Toledo 45003",
    "addr:housenumber":"4",
    "addr:postcode":"45003",
    "addr:street":"Avda Europa",
    "iso:country":"ES",
    "sg:address":"Avda Europa, 4",
    "sg:city":"Toledo",
    "sg:orig_category":"Agricultores, Agricultores",
    "sg:phone":"+34 925 25 78 36",
    "sg:postcode":"45003",
    "sg:province":"Toledo",
    "wof:name":"Tello Integraciones Porcinas S.l.",
    "wof:placetype":"venue"
},
  "geometry": {"coordinates":[-4.0274147987,39.8712043762],"type":"Point"}
}