{
  "type": "Feature",
  "properties": {
    "addr:full":"Calle de Mayor, 53 Puntal Murcia 30100",
    "addr:housenumber":"53",
    "addr:postcode":"30100",
    "addr:street":"Calle De Mayor",
    "iso:country":"ES",
    "sg:address":"Calle de Mayor, 53",
    "sg:city":"Puntal",
    "sg:orig_category":"Agencias Y Agentes Comerciales, Representantes",
    "sg:phone":"+34 968 83 15 58",
    "sg:postcode":"30100",
    "sg:province":"Murcia",
    "wof:name":"Lopez Romero Manuel",
    "wof:placetype":"venue"
},
  "geometry": {"coordinates":[-1.1568490267,38.0140037537],"type":"Point"}
}