{
  "type": "Feature",
  "properties": {
    "iso:country":"ES",
    "sg:address":"Avda Europa (de), 4",
    "sg:city":"Alcobendas",
    "sg:orig_category":"Inversiones",
    "sg:phone":"+34 916 62 27 63",
    "sg:postcode":"28108",
    "sg:province":"Madrid",
    "wof:name":"Inversiones Goso S.a.",
    "wof:placetype":"venue"
},
  "geometry": {"coordinates":[-3.6602351665,40.5202102661],"type":"Point"}
}