{
  "type": "Feature",
  "properties": {
    "iso:country":"ES",
    "sg:address":"Calle de Iberre, 11",
    "sg:city":"Zangroiz",
    "sg:orig_category":"Ense\u00d1anza: Profesiones Art\u00cdsticas",
    "sg:phone":"+34 944 53 36 26",
    "sg:postcode":"48150",
    "sg:province":"Vizcaya",
    "wof:name":"Crespo Jimenez Pablo",
    "wof:placetype":"venue"
},
  "geometry": {"coordinates":[-2.9244790077,43.2990455627],"type":"Point"}
}