{
  "type": "Feature",
  "properties": {
    "addr:full":"Calle de Colon, 31 Palencia Palencia 34002",
    "addr:housenumber":"31",
    "addr:postcode":"34002",
    "addr:street":"Calle De Colon",
    "iso:country":"ES",
    "sg:address":"Calle de Colon, 31",
    "sg:city":"Palencia",
    "sg:orig_category":"Bisuter\u00cda, Joyer\u00cda, Relojer\u00cda (al Por Menor)",
    "sg:phone":"+34 979 74 55 23",
    "sg:postcode":"34002",
    "sg:province":"Palencia",
    "wof:name":"Pascual Tarancon S.l.",
    "wof:placetype":"venue"
},
  "geometry": {"coordinates":[-4.5311188698,42.0076522827],"type":"Point"}
}