{
  "type": "Feature",
  "properties": {
    "iso:country":"ES",
    "sg:address":"Pase Fernandez Vallejo, 31",
    "sg:city":"Torrelavega",
    "sg:orig_category":"Empresas De Pintura Y Revestimientos",
    "sg:phone":"+34 942 88 26 45",
    "sg:postcode":"39300",
    "sg:province":"Cantabria",
    "wof:name":"Pinturas Teran E Hijo S.l.",
    "wof:placetype":"venue"
},
  "geometry": {"coordinates":[-4.0459780693,43.3430633545],"type":"Point"}
}