{
  "type": "Feature",
  "properties": {
    "iso:country":"ES",
    "sg:address":"Calle de Estrasburgo, 16",
    "sg:city":"Sevilla",
    "sg:orig_category":"Fisioterapia",
    "sg:phone":"+34 954 23 83 85",
    "sg:postcode":"41012",
    "sg:province":"Sevilla",
    "wof:name":"Fisioterapia Los Bermejales S.c.",
    "wof:placetype":"venue"
},
  "geometry": {"coordinates":[-5.9789800644,37.3469467163],"type":"Point"}
}