{
  "type": "Feature",
  "properties": {
    "iso:country":"ES",
    "sg:address":"Calle de Santiago Alba, 8",
    "sg:city":"Valladolid",
    "sg:orig_category":"Agencias Y Agentes Comerciales, Representantes",
    "sg:phone":"+34 983 24 81 95",
    "sg:postcode":"47008",
    "sg:province":"Valladolid",
    "wof:name":"Garcia Saez Alejandro",
    "wof:placetype":"venue"
},
  "geometry": {"coordinates":[-4.7511692047,41.6097183228],"type":"Point"}
}