{
  "type": "Feature",
  "properties": {
    "addr:full":"Calle de San Salvador, 26 Huelva Huelva 21003",
    "addr:housenumber":"26",
    "addr:postcode":"21003",
    "addr:street":"Calle De San Salvador",
    "iso:country":"ES",
    "sg:address":"Calle de San Salvador, 26",
    "sg:city":"Huelva",
    "sg:orig_category":"Asesor\u00cda Sobre Comunicaci\u00d3n De Empresas",
    "sg:phone":"+34 959 24 12 77",
    "sg:postcode":"21003",
    "sg:province":"Huelva",
    "wof:name":"Fundacion Red Andalucia Emprende",
    "wof:placetype":"venue"
},
  "geometry": {"coordinates":[-6.9475398064,37.2570075989],"type":"Point"}
}