{
  "type": "Feature",
  "properties": {
    "iso:country":"ES",
    "sg:address":"Plaz Iglesia (de La), 1",
    "sg:city":"Huetor-vega",
    "sg:orig_category":"Fisioterapia",
    "sg:phone":"+34 958 30 34 16",
    "sg:postcode":"18198",
    "sg:province":"Granada",
    "wof:name":"Hattach  Houda",
    "wof:placetype":"venue"
},
  "geometry": {"coordinates":[-3.565666914,37.1467514038],"type":"Point"}
}