{
  "type": "Feature",
  "properties": {
    "addr:full":"Ctra Castellon, S/n Burgo Ebro Zaragoza 50730",
    "addr:housenumber":"s / n",
    "addr:postcode":"50730",
    "addr:street":"Ctra Castellon;Ebro",
    "iso:country":"ES",
    "sg:address":"Ctra Castellon, S/n",
    "sg:city":"Burgo Ebro",
    "sg:orig_category":"Refiner\u00cdas De Petr\u00d3leo",
    "sg:phone":"+34 976 10 50 76",
    "sg:postcode":"50730",
    "sg:province":"Zaragoza",
    "wof:name":"Repsol Ypf S.a.",
    "wof:placetype":"venue"
},
  "geometry": {"coordinates":[-0.7429590225,41.5727653503],"type":"Point"}
}