{
  "type": "Feature",
  "properties": {
    "addr:full":"Calle de Francisco Lastres, 5 Madrid Madrid 28028",
    "addr:housenumber":"5",
    "addr:postcode":"28028",
    "addr:street":"Calle De Francisco Lastres",
    "iso:country":"ES",
    "sg:address":"Calle de Francisco Lastres, 5",
    "sg:city":"Madrid",
    "sg:orig_category":"Organismos De Reclutamiento",
    "sg:phone":"+34 915 19 92 94",
    "sg:postcode":"28028",
    "sg:province":"Madrid",
    "wof:name":"Sainz Sastre Lucas",
    "wof:placetype":"venue"
},
  "geometry": {"coordinates":[-3.6644620895,40.424571991],"type":"Point"}
}