{
  "type": "Feature",
  "properties": {
    "addr:full":"Daoiz Y Velarde, 5 Trobajo Camino Le\u00f3n 24010",
    "addr:housenumber":"5",
    "addr:postcode":"24010",
    "addr:street":"Daoiz Y Velarde;Camino Leo\u0301N",
    "iso:country":"ES",
    "sg:address":"Daoiz Y Velarde, 5",
    "sg:city":"Trobajo Camino",
    "sg:orig_category":"T\u00c9cnicos Veterinarios",
    "sg:phone":"+34 987 80 48 45",
    "sg:postcode":"24010",
    "sg:province":"Le\u00f3n",
    "wof:name":"Gallego Infante Cipriano",
    "wof:placetype":"venue"
},
  "geometry": {"coordinates":[-5.5716600418,42.5981292725],"type":"Point"}
}