{
  "type": "Feature",
  "properties": {
    "iso:country":"ES",
    "sg:address":"Avda Cinca, S/n",
    "sg:city":"Barbastro",
    "sg:orig_category":"Ense\u00d1anza Secundaria: Colegios Y Escuelas Privadas",
    "sg:phone":"+34 974 31 17 38",
    "sg:postcode":"22300",
    "sg:province":"Huesca",
    "wof:name":"Ies Hermanos Argensola",
    "wof:placetype":"venue"
},
  "geometry": {"coordinates":[0.130885005,42.0344543457],"type":"Point"}
}