{
  "type": "Feature",
  "properties": {
    "addr:full":"Paraires, S/n Pol. Ind. Santiga Barcelona 08130",
    "addr:housenumber":"/ n",
    "addr:postcode":"08130",
    "addr:street":"Paraires S;Pol. Ind. Santiga",
    "iso:country":"ES",
    "sg:address":"Paraires, S/n",
    "sg:city":"Pol. Ind. Santiga",
    "sg:orig_category":"Chapister\u00cda",
    "sg:phone":"+34 937 18 15 17",
    "sg:postcode":"08130",
    "sg:province":"Barcelona",
    "wof:name":"Reche Lopez Miguel",
    "wof:placetype":"venue"
},
  "geometry": {"coordinates":[2.1802799702,41.5371818542],"type":"Point"}
}