{
  "type": "Feature",
  "properties": {
    "addr:full":"Avgd Alcalde Rovira Roure, 19 Lleida Lleida 25006",
    "addr:housenumber":"19",
    "addr:postcode":"25006",
    "addr:street":"Alcalde Rovira Roure",
    "iso:country":"ES",
    "sg:address":"Avgd Alcalde Rovira Roure, 19",
    "sg:city":"Lleida",
    "sg:orig_category":"Procuradores",
    "sg:phone":"+34 973 22 23 06",
    "sg:postcode":"25006",
    "sg:province":"Lleida",
    "wof:name":"Berdie Paba Maria Eugenia",
    "wof:placetype":"venue"
},
  "geometry": {"coordinates":[0.6178640127,41.621421814],"type":"Point"}
}