{
  "type": "Feature",
  "properties": {
    "iso:country":"ES",
    "sg:address":"Calle de Javier Del Quinto, 6",
    "sg:city":"Madrid",
    "sg:orig_category":"Alimentaci\u00d3n General (al Por Menor)",
    "sg:phone":"+34 913 81 89 14",
    "sg:postcode":"28043",
    "sg:province":"Madrid",
    "wof:name":"Isan Gestores S.l.",
    "wof:placetype":"venue"
},
  "geometry": {"coordinates":[-3.642179966,40.4655303955],"type":"Point"}
}