{
  "type": "Feature",
  "properties": {
    "addr:full":"Avda Islantilla, S/n Antilla Huelva 21449",
    "addr:housenumber":"/ n",
    "addr:postcode":"21449",
    "addr:street":"Avda Islantilla S",
    "iso:country":"ES",
    "sg:address":"Avda Islantilla, S/n",
    "sg:city":"Antilla",
    "sg:classifiers":[
        {
            "category":"Professional",
            "subcategory":"Management & Consulting",
            "type":"Services"
        }
    ],
    "sg:phone":"+34 959 48 65 05",
    "sg:postcode":"21449",
    "sg:province":"Huelva",
    "sg:tags":[
        "asesor\u00cda",
        "en",
        "marketing"
    ],
    "wof:name":"Alvarez Acu\u00f1a Mercedes",
    "wof:placetype":"venue"
},
  "geometry": {"coordinates":[-7.2315440178,37.2070236206],"type":"Point"}
}