{
  "type": "Feature",
  "properties": {
    "iso:country":"ES",
    "sg:address":"Carrer de Llobregat, 157",
    "sg:city":"Hospitalet Llobregat",
    "sg:orig_category":"Molduras, Junquillos, Listones Y Molduras Perforadas",
    "sg:phone":"+34 934 49 57 19",
    "sg:postcode":"08904",
    "sg:province":"Barcelona",
    "wof:name":"Ramos Ya\u00f1ez Maria",
    "wof:placetype":"venue"
},
  "geometry": {"coordinates":[2.12155509,41.3702354431],"type":"Point"}
}