{
  "type": "Feature",
  "properties": {
    "addr:full":"Calle de Felix Valverde Lillo, 15 Merida Badajoz 06800",
    "addr:housenumber":"15",
    "addr:postcode":"06800",
    "addr:street":"Calle De Felix Valverde Lillo",
    "iso:country":"ES",
    "sg:address":"Calle de Felix Valverde Lillo, 15",
    "sg:city":"Merida",
    "sg:orig_category":"Gases Comprimidos, Licuados Y Disueltos",
    "sg:phone":"+34 924 31 10 03",
    "sg:postcode":"06800",
    "sg:province":"Badajoz",
    "wof:name":"Mateos Y Garcia S.l.",
    "wof:placetype":"venue"
},
  "geometry": {"coordinates":[-6.3585958481,38.9129180908],"type":"Point"}
}