{
  "type": "Feature",
  "properties": {
    "addr:full":"Calle de Isla De Lobos, 16 Pto. Rosario Las Palmas 35600",
    "addr:housenumber":"16",
    "addr:postcode":"35600",
    "addr:street":"Calle De Isla De Lobos;Pto. Rosario Las",
    "iso:country":"ES",
    "sg:address":"Calle de Isla De Lobos, 16",
    "sg:city":"Pto. Rosario",
    "sg:orig_category":"M\u00c9dicos: Foniatr\u00cda Y Logopedia",
    "sg:phone":"+34 928 53 30 97",
    "sg:postcode":"35600",
    "sg:province":"Las Palmas",
    "wof:name":"Centro Logopedico El Espejo",
    "wof:placetype":"venue"
},
  "geometry": {"coordinates":[-13.86414814,28.5012207031],"type":"Point"}
}