{
  "type": "Feature",
  "properties": {
    "iso:country":"ES",
    "sg:address":"Miluze, S/n",
    "sg:city":"Iru\u00f1a",
    "sg:orig_category":"Carnes De Carnicer\u00cda (al Por Mayor)",
    "sg:phone":"+34 948 25 44 30",
    "sg:postcode":"31008",
    "sg:province":"Navarra",
    "wof:name":"Regalado Izurriaga Y Jose Igancio Y Ricardo",
    "wof:placetype":"venue"
},
  "geometry": {"coordinates":[-1.6739339828,42.8058586121],"type":"Point"}
}