{
  "type": "Feature",
  "properties": {
    "addr:full":"Plaz San Martin, 13 Plasencia C\u00e1ceres 10600",
    "addr:housenumber":"13",
    "addr:postcode":"10600",
    "addr:street":"Plaz San Martin;Ca\u0301Ceres",
    "iso:country":"ES",
    "sg:address":"Plaz San Martin, 13",
    "sg:city":"Plasencia",
    "sg:orig_category":"Arquitectos",
    "sg:phone":"+34 927 42 42 63",
    "sg:postcode":"10600",
    "sg:province":"C\u00e1ceres",
    "wof:name":"Valverde Lorenzo Luis Ramon",
    "wof:placetype":"venue"
},
  "geometry": {"coordinates":[-6.091468811,40.0298233032],"type":"Point"}
}