{
  "type": "Feature",
  "properties": {
    "addr:full":"Carrer de Montseny, 10 Barriada Nova Barcelona 08420",
    "addr:housenumber":"10",
    "addr:postcode":"08420",
    "addr:street":"Carrer De Montseny;Nova Barcelona",
    "iso:country":"ES",
    "sg:address":"Carrer de Montseny, 10",
    "sg:city":"Barriada Nova",
    "sg:orig_category":"Peluquer\u00cdas, Peluquer\u00cda Mixta",
    "sg:phone":"+34 938 49 24 20",
    "sg:postcode":"08420",
    "sg:province":"Barcelona",
    "wof:name":"Avila Roman Israel",
    "wof:placetype":"venue"
},
  "geometry": {"coordinates":[2.2783401012,41.6220207214],"type":"Point"}
}