{
  "type": "Feature",
  "properties": {
    "addr:full":"Calle de Armengual De La Mota, 27 Malaga M\u00e1laga 29007",
    "addr:housenumber":"27",
    "addr:postcode":"29007",
    "addr:street":"Calle De Armengual De La Mota;Ma\u0301Laga",
    "iso:country":"ES",
    "sg:address":"Calle de Armengual De La Mota, 27",
    "sg:city":"Malaga",
    "sg:orig_category":"Cl\u00cdnicas Dentales",
    "sg:phone":"+34 952 61 54 16",
    "sg:postcode":"29007",
    "sg:province":"M\u00e1laga",
    "wof:name":"Plus-dental S.l.",
    "wof:placetype":"venue"
},
  "geometry": {"coordinates":[-4.4292058945,36.7201004028],"type":"Point"}
}