{
  "type": "Feature",
  "properties": {
    "iso:country":"ES",
    "sg:address":"Calle de Real, 21",
    "sg:city":"S. Andres Rabanedo",
    "sg:orig_category":"Bebidas",
    "sg:phone":"+34 987 84 60 19",
    "sg:postcode":"24010",
    "sg:province":"Le\u00f3n",
    "wof:name":"Zerep Carbonicas Y Aguas S.a.",
    "wof:placetype":"venue"
},
  "geometry": {"coordinates":[-5.6163964272,42.6218566895],"type":"Point"}
}