{
  "type": "Feature",
  "properties": {
    "iso:country":"ES",
    "sg:address":"Urb Montebello, 17",
    "sg:city":"Barranc Fondo",
    "sg:orig_category":"Asociaciones Y Clubs Deportivos",
    "sg:phone":"+34 966 87 34 91",
    "sg:postcode":"03530",
    "sg:province":"Alicante",
    "wof:name":"Devesa Leal Rafael",
    "wof:placetype":"venue"
},
  "geometry": {"coordinates":[-0.1249789968,38.6157951355],"type":"Point"}
}