{
  "type": "Feature",
  "properties": {
    "addr:full":"Calle de Granado El, 5 Huelva Huelva 21007",
    "addr:housenumber":"5",
    "addr:postcode":"21007",
    "addr:street":"Calle De Granado El",
    "iso:country":"ES",
    "sg:address":"Calle de Granado El, 5",
    "sg:city":"Huelva",
    "sg:orig_category":"Mec\u00c1nico Del Autom\u00d3vil",
    "sg:phone":"+34 959 22 89 47",
    "sg:postcode":"21007",
    "sg:province":"Huelva",
    "wof:name":"Alonso Gomez Gonzalo",
    "wof:placetype":"venue"
},
  "geometry": {"coordinates":[-6.9282298088,37.2645187378],"type":"Point"}
}