{
  "type": "Feature",
  "properties": {
    "addr:full":"Carr Albera, 11 Figueres Girona 17600",
    "addr:housenumber":"11",
    "addr:postcode":"17600",
    "addr:street":"Carr Albera",
    "iso:country":"ES",
    "sg:address":"Carr Albera, 11",
    "sg:city":"Figueres",
    "sg:orig_category":"Supermercados Y Hipermercados",
    "sg:phone":"+34 972 50 43 78",
    "sg:postcode":"17600",
    "sg:province":"Girona",
    "wof:name":"Bague Ferrer Jose",
    "wof:placetype":"venue"
},
  "geometry": {"coordinates":[2.9579544067,42.2733650208],"type":"Point"}
}