{
  "type": "Feature",
  "properties": {
    "addr:full":"Calle de Teniente Ariza, 7 Herrera Sevilla 41567",
    "addr:housenumber":"7",
    "addr:postcode":"41567",
    "addr:street":"Calle De Teniente Ariza",
    "iso:country":"ES",
    "sg:address":"Calle de Teniente Ariza, 7",
    "sg:city":"Herrera",
    "sg:orig_category":"M\u00c9dicos: Estomatolog\u00cda",
    "sg:phone":"+34 954 01 20 04",
    "sg:postcode":"41567",
    "sg:province":"Sevilla",
    "wof:name":"Hidalgo Ledesma Matias",
    "wof:placetype":"venue"
},
  "geometry": {"coordinates":[-4.8506798744,37.3652076721],"type":"Point"}
}