{
  "type": "Feature",
  "properties": {
    "addr:full":"P. San Lorenzo, S/n Melilla Melilla 52006",
    "addr:housenumber":"s / n",
    "addr:postcode":"52006",
    "addr:street":"P. San Lorenzo",
    "iso:country":"ES",
    "sg:address":"P. San Lorenzo, S/n",
    "sg:city":"Melilla",
    "sg:orig_category":"Pr\u00c1ctica De Vela, Navegaci\u00d3n Y Deportes N\u00c1uticos Y Acu\u00c1ticos",
    "sg:phone":"+34 952 69 10 63",
    "sg:postcode":"52006",
    "sg:province":"Melilla",
    "wof:name":"Portel Servicios Telematicos S.a",
    "wof:placetype":"venue"
},
  "geometry": {"coordinates":[-2.9361999035,35.2828216553],"type":"Point"}
}