{
  "type": "Feature",
  "properties": {
    "iso:country":"ES",
    "sg:address":"Calle de Julian De Apraiz, 2",
    "sg:city":"Vitoria-gasteiz",
    "sg:orig_category":"Empresarios",
    "sg:phone":"+34 945 22 04 78",
    "sg:postcode":"01012",
    "sg:province":"\u00c1lava",
    "wof:name":"Saez De Lafuente Gochicoa Jose Ignacio",
    "wof:placetype":"venue"
},
  "geometry": {"coordinates":[-2.673789978,42.8531913757],"type":"Point"}
}