{
  "type": "Feature",
  "properties": {
    "addr:full":"Rbla Del Fondo, S/n Santa Coloma De Gramenet Barcelona 08922",
    "addr:housenumber":"s / n",
    "addr:postcode":"08922",
    "addr:street":"Rbla Del Fondo",
    "iso:country":"ES",
    "sg:address":"Rbla Del Fondo, S/n",
    "sg:city":"Santa Coloma De Gramenet",
    "sg:orig_category":"Promotores Constructores",
    "sg:phone":"+34 933 92 63 71",
    "sg:postcode":"08922",
    "sg:province":"Barcelona",
    "wof:name":"Duet Rambla Del Fondo S.a.",
    "wof:placetype":"venue"
},
  "geometry": {"coordinates":[2.216160059,41.4513244629],"type":"Point"}
}