{
  "type": "Feature",
  "properties": {
    "addr:full":"Calle de Real, 2 Torrelodones Madrid 28250",
    "addr:housenumber":"2",
    "addr:postcode":"28250",
    "addr:street":"Calle De Real",
    "iso:country":"ES",
    "sg:address":"Calle de Real, 2",
    "sg:city":"Torrelodones",
    "sg:orig_category":"Inmobiliaria (agencias)",
    "sg:phone":"+34 918 59 39 25",
    "sg:postcode":"28250",
    "sg:province":"Madrid",
    "wof:name":"Servicios Inmobiliarios Y Fiscales S.l.",
    "wof:placetype":"venue"
},
  "geometry": {"coordinates":[-3.9286739826,40.5758056641],"type":"Point"}
}