{
  "type": "Feature",
  "properties": {
    "addr:full":"Calle de Jose Gimeno Agius, 1 Segorbe Castell\u00f3n 12400",
    "addr:housenumber":"1",
    "addr:postcode":"12400",
    "addr:street":"Calle De Jose Gimeno Agius",
    "iso:country":"ES",
    "sg:address":"Calle de Jose Gimeno Agius, 1",
    "sg:city":"Segorbe",
    "sg:orig_category":"Comercios E Industrias (cesi\u00d3n Y Reactivaci\u00d3n)",
    "sg:phone":"+34 964 71 10 79",
    "sg:postcode":"12400",
    "sg:province":"Castell\u00f3n",
    "wof:name":"Bordon Pedro Fernando",
    "wof:placetype":"venue"
},
  "geometry": {"coordinates":[-0.4859760106,39.8511314392],"type":"Point"}
}