{
  "type": "Feature",
  "properties": {
    "iso:country":"ES",
    "sg:address":"Avda Pablo Iglesias, 7",
    "sg:city":"Tarancon",
    "sg:orig_category":"\u00d3ptica: Instrumentos (fabricaci\u00d3n)",
    "sg:phone":"+34 969 32 53 27",
    "sg:postcode":"16400",
    "sg:province":"Cuenca",
    "wof:name":"Optica Croma S.l.",
    "wof:placetype":"venue"
},
  "geometry": {"coordinates":[-3.0186090469,40.0075416565],"type":"Point"}
}