{
  "type": "Feature",
  "properties": {
    "iso:country":"ES",
    "sg:address":"Calle de Sindical, 2",
    "sg:city":"Arevalo",
    "sg:orig_category":"Promotores Constructores",
    "sg:phone":"+34 920 30 20 71",
    "sg:postcode":"05200",
    "sg:province":"\u00c1vila",
    "wof:name":"Reyper Pyc S.l.",
    "wof:placetype":"venue"
},
  "geometry": {"coordinates":[-4.7205238342,41.0587997437],"type":"Point"}
}