{
  "type": "Feature",
  "properties": {
    "addr:full":"Crri Gamarra, 7 Malaga M\u00e1laga 29010",
    "addr:housenumber":"7",
    "addr:postcode":"29010",
    "addr:street":"Gamarra;Ma\u0301Laga",
    "iso:country":"ES",
    "sg:address":"Crri Gamarra, 7",
    "sg:city":"Malaga",
    "sg:orig_category":"Cajas De Ahorro",
    "sg:phone":"+34 952 27 11 50",
    "sg:postcode":"29010",
    "sg:province":"M\u00e1laga",
    "wof:name":"Unicaja",
    "wof:placetype":"venue"
},
  "geometry": {"coordinates":[-4.4422187805,36.7226371765],"type":"Point"}
}