{
  "type": "Feature",
  "properties": {
    "addr:full":"Calle de Mendandia, S/n Ancin Navarra 31281",
    "addr:housenumber":"s",
    "addr:postcode":"31281",
    "addr:street":"Calle De Mendandia;/ N Ancin Navarra",
    "iso:country":"ES",
    "sg:address":"Calle de Mendandia, S/n",
    "sg:city":"Ancin",
    "sg:orig_category":"Empresas De Pintura Y Revestimientos",
    "sg:phone":"+34 948 53 41 39",
    "sg:postcode":"31281",
    "sg:province":"Navarra",
    "wof:name":"Fernandez Pillado Candido",
    "wof:placetype":"venue"
},
  "geometry": {"coordinates":[-2.1862239838,42.6613044739],"type":"Point"}
}