{
  "type": "Feature",
  "properties": {
    "addr:full":"Calle de Silvestre Perez, 8 Zaragoza Zaragoza 50002",
    "addr:housenumber":"8",
    "addr:postcode":"50002",
    "addr:street":"Calle De Silvestre Perez",
    "iso:country":"ES",
    "sg:address":"Calle de Silvestre Perez, 8",
    "sg:city":"Zaragoza",
    "sg:orig_category":"Molduras, Junquillos, Listones Y Molduras Perforadas",
    "sg:phone":"+34 976 42 10 35",
    "sg:postcode":"50002",
    "sg:province":"Zaragoza",
    "wof:name":"Orus Orcastegui Vicente",
    "wof:placetype":"venue"
},
  "geometry": {"coordinates":[-0.8621439934,41.6481285095],"type":"Point"}
}