{
  "type": "Feature",
  "properties": {
    "iso:country":"ES",
    "sg:address":"Trapani, 11",
    "sg:city":"Garrapinillos",
    "sg:orig_category":"Transportes Internacionales",
    "sg:phone":"+34 976 58 72 29",
    "sg:postcode":"50197",
    "sg:province":"Zaragoza",
    "sg:website":"www.grupesa.es",
    "wof:name":"W T Grupesa S.a.",
    "wof:placetype":"venue"
},
  "geometry": {"coordinates":[-0.9921603799,41.6460227966],"type":"Point"}
}