{
  "type": "Feature",
  "properties": {
    "iso:country":"ES",
    "sg:address":"Av Catalunya, 47",
    "sg:city":"Tarrega",
    "sg:orig_category":"Abogados",
    "sg:phone":"+34 973 31 07 62",
    "sg:postcode":"25300",
    "sg:province":"Lleida",
    "wof:name":"Tasies Beleta Ricardo",
    "wof:placetype":"venue"
},
  "geometry": {"coordinates":[1.1360529661,41.6475753784],"type":"Point"}
}