{
  "type": "Feature",
  "properties": {
    "iso:country":"ES",
    "sg:address":"Cm Vell Onda Castello, 10",
    "sg:city":"Vila-real",
    "sg:orig_category":"M\u00c1rmoles, Granitos Y Piedras Naturales",
    "sg:phone":"+34 964 53 14 21",
    "sg:postcode":"12540",
    "sg:province":"Castell\u00f3n",
    "wof:name":"Ros Valles Pedro",
    "wof:placetype":"venue"
},
  "geometry": {"coordinates":[-0.0937379971,39.9503326416],"type":"Point"}
}