{
  "type": "Feature",
  "properties": {
    "addr:full":"Carrer de Marquesos De Barbera, 42 Barbera Valles Barcelona 08210",
    "addr:housenumber":"42",
    "addr:postcode":"08210",
    "addr:street":"Carrer De Marquesos De Barbera",
    "iso:country":"ES",
    "sg:address":"Carrer de Marquesos De Barbera, 42",
    "sg:city":"Barbera Valles",
    "sg:orig_category":"Inform\u00c1tica (estudios, Servicios, Asesor\u00cda, Formaci\u00d3n)",
    "sg:phone":"+34 937 29 13 85",
    "sg:postcode":"08210",
    "sg:province":"Barcelona",
    "sg:website":"www.logicaltools.net",
    "wof:name":"Lot 98 S.l.",
    "wof:placetype":"venue"
},
  "geometry": {"coordinates":[2.11845994,41.5185089111],"type":"Point"}
}