{
  "type": "Feature",
  "properties": {
    "addr:full":"Carrer de Elkano, 33 Barcelona Barcelona 08004",
    "addr:housenumber":"33",
    "addr:postcode":"08004",
    "addr:street":"Carrer De Elkano",
    "iso:country":"ES",
    "sg:address":"Carrer de Elkano, 33",
    "sg:city":"Barcelona",
    "sg:orig_category":"Droguer\u00cdas (al Por Menor)",
    "sg:phone":"+34 933 29 82 39",
    "sg:postcode":"08004",
    "sg:province":"Barcelona",
    "wof:name":"Campanera Banus Jose Maria",
    "wof:placetype":"venue"
},
  "geometry": {"coordinates":[2.1628348827,41.3731460571],"type":"Point"}
}