{
  "type": "Feature",
  "properties": {
    "addr:full":"Cmno San Sebastian (de), 14 Boadilla Del Monte Madrid 28660",
    "addr:housenumber":"14",
    "addr:postcode":"28660",
    "addr:street":"Cmno San Sebastian De",
    "iso:country":"ES",
    "sg:address":"Cmno San Sebastian (de), 14",
    "sg:city":"Boadilla Del Monte",
    "sg:orig_category":"Peluquer\u00cdas, Peluquer\u00cda Mixta",
    "sg:phone":"+34 916 32 33 85",
    "sg:postcode":"28660",
    "sg:province":"Madrid",
    "wof:name":"Marinas Nevado Maria Del Carmen",
    "wof:placetype":"venue"
},
  "geometry": {"coordinates":[-3.8773078918,40.4077568054],"type":"Point"}
}