{
  "type": "Feature",
  "properties": {
    "addr:full":"Calle de Amezti, 7 Getxo Vizcaya 48990",
    "addr:housenumber":"7",
    "addr:postcode":"48990",
    "addr:street":"Calle De Amezti",
    "iso:country":"ES",
    "sg:address":"Calle de Amezti, 7",
    "sg:city":"Getxo",
    "sg:orig_category":"Peluquer\u00cdas, Peluquer\u00cda Mixta",
    "sg:phone":"+34 944 03 47 44",
    "sg:postcode":"48990",
    "sg:province":"Vizcaya",
    "wof:name":"Itziar Olabarria Intxausti (peluqueria)",
    "wof:placetype":"venue"
},
  "geometry": {"coordinates":[-3.01040411,43.3494224548],"type":"Point"}
}