{
  "type": "Feature",
  "properties": {
    "addr:full":"Avda Tenor Fleta, 40 Zaragoza Zaragoza 50007",
    "addr:housenumber":"40",
    "addr:postcode":"50007",
    "addr:street":"Avda Tenor Fleta",
    "iso:country":"ES",
    "sg:address":"Avda Tenor Fleta, 40",
    "sg:city":"Zaragoza",
    "sg:orig_category":"Bronceado Por Rayos Uva",
    "sg:phone":"+34 976 27 36 49",
    "sg:postcode":"50007",
    "sg:province":"Zaragoza",
    "sg:website":"www.solmania.com",
    "wof:name":"Elenma 2001 S.l.",
    "wof:placetype":"venue"
},
  "geometry": {"coordinates":[-0.8817999959,41.6398391724],"type":"Point"}
}