{
  "type": "Feature",
  "properties": {
    "iso:country":"ES",
    "sg:address":"Carrer de Maria Vidal (de), 308",
    "sg:city":"Vilassar De Mar",
    "sg:orig_category":"Flores Y Plantas Naturales (al Por Mayor)",
    "sg:phone":"+34 937 50 22 33",
    "sg:postcode":"08340",
    "sg:province":"Barcelona",
    "sg:website":"www.verdeespejo.com",
    "wof:name":"Espejo Romero Jose",
    "wof:placetype":"venue"
},
  "geometry": {"coordinates":[2.3879899979,41.5020217896],"type":"Point"}
}