{
  "type": "Feature",
  "properties": {
    "addr:full":"Guadalen, 1 Ubeda Ja\u00e9n 23400",
    "addr:housenumber":"1",
    "addr:postcode":"23400",
    "addr:street":"Guadalen;Jae\u0301N",
    "iso:country":"ES",
    "sg:address":"Guadalen, 1",
    "sg:city":"Ubeda",
    "sg:orig_category":"Supermercados Y Hipermercados",
    "sg:phone":"+34 953 75 20 64",
    "sg:postcode":"23400",
    "sg:province":"Ja\u00e9n",
    "wof:name":"Carrillo Sanchez Antonio",
    "wof:placetype":"venue"
},
  "geometry": {"coordinates":[-3.3685019016,38.0147895813],"type":"Point"}
}