{
  "type": "Feature",
  "properties": {
    "addr:full":"Presa De Eugui, S/n Eugi Navarra 31638",
    "addr:housenumber":"s / n",
    "addr:postcode":"31638",
    "iso:country":"ES",
    "sg:address":"Presa De Eugui, S/n",
    "sg:city":"Eugi",
    "sg:orig_category":"Aguas (distribuci\u00d3n, Servicios)",
    "sg:phone":"+34 948 30 42 28",
    "sg:postcode":"31638",
    "sg:province":"Navarra",
    "wof:name":"Confederacion Hidrografica Del Ebro",
    "wof:placetype":"venue"
},
  "geometry": {"coordinates":[-1.5039149523,42.9777565002],"type":"Point"}
}