{
  "type": "Feature",
  "properties": {
    "addr:full":"Calle de Virgen De Las Angustias, 37 Avila \u00c1vila 05005",
    "addr:housenumber":"37",
    "addr:postcode":"05005",
    "addr:street":"Calle De Virgen De Las Angustias;A\u0301Vila",
    "iso:country":"ES",
    "sg:address":"Calle de Virgen De Las Angustias, 37",
    "sg:city":"Avila",
    "sg:orig_category":"Agencias Y Agentes Comerciales, Representantes",
    "sg:phone":"+34 920 25 12 96",
    "sg:postcode":"05005",
    "sg:province":"\u00c1vila",
    "wof:name":"Segovia Lopez Francisco",
    "wof:placetype":"venue"
},
  "geometry": {"coordinates":[-4.6865181923,40.6605415344],"type":"Point"}
}