{
  "type": "Feature",
  "properties": {
    "addr:full":"Muel Ca\u00d1onero Dato, S/n Ceuta Ceuta 51001",
    "addr:postcode":"51001",
    "addr:street":"Dato S / N",
    "iso:country":"ES",
    "sg:address":"Muel Ca\u00d1onero Dato, S/n",
    "sg:city":"Ceuta",
    "sg:orig_category":"Empresas De Electricidad En General",
    "sg:phone":"+34 956 50 33 84",
    "sg:postcode":"51001",
    "sg:province":"Ceuta",
    "wof:name":"Endesa Servicios S.l. Sociedad Unipersonal",
    "wof:placetype":"venue"
},
  "geometry": {"coordinates":[-5.3302302361,35.8947601318],"type":"Point"}
}