{
  "type": "Feature",
  "properties": {
    "addr:full":"Carrer de Diputacio, 238 Barcelona Barcelona 08007",
    "addr:housenumber":"238",
    "addr:postcode":"08007",
    "addr:street":"Carrer De Diputacio",
    "iso:country":"ES",
    "sg:address":"Carrer de Diputacio, 238",
    "sg:city":"Barcelona",
    "sg:orig_category":"Fabricaci\u00d3n De Papel Para Embalar",
    "sg:phone":"+34 933 04 28 60",
    "sg:postcode":"08007",
    "sg:province":"Barcelona",
    "sg:website":"www.aliersa.com",
    "wof:name":"Alier S.a.",
    "wof:placetype":"venue"
},
  "geometry": {"coordinates":[2.1646978855,41.3886146545],"type":"Point"}
}