{
  "type": "Feature",
  "properties": {
    "addr:full":"Etxebarri Auzoa, 12 Etxebarri Guip\u00f9zcoa 20550",
    "addr:housenumber":"12",
    "addr:postcode":"20550",
    "addr:street":"Etxebarri Auzoa;Guipu\u0300Zcoa",
    "iso:country":"ES",
    "sg:address":"Etxebarri Auzoa, 12",
    "sg:city":"Etxebarri",
    "sg:orig_category":"Asociaciones Y Clubs Deportivos",
    "sg:phone":"+34 943 79 76 29",
    "sg:postcode":"20550",
    "sg:province":"Guip\u00f9zcoa",
    "wof:name":"Union Deportiva Aretxabaleta",
    "wof:placetype":"venue"
},
  "geometry": {"coordinates":[-2.5058889389,43.0299415588],"type":"Point"}
}