{
  "type": "Feature",
  "properties": {
    "iso:country":"ES",
    "sg:address":"Avda Rodriguez Acosta, 14",
    "sg:city":"Motril",
    "sg:orig_category":"Cr\u00cda De Animales",
    "sg:phone":"+34 958 82 51 71",
    "sg:postcode":"18600",
    "sg:province":"Granada",
    "wof:name":"Molero Torres Fermin Jesus",
    "wof:placetype":"venue"
},
  "geometry": {"coordinates":[-3.5146689415,36.74376297],"type":"Point"}
}