{
  "type": "Feature",
  "properties": {
    "addr:full":"Ctra Mairena-almensilla, S/n Mairena Aljarafe Sevilla 41927",
    "addr:housenumber":"s / n",
    "addr:postcode":"41927",
    "addr:street":"Ctra Mairena-Almensilla",
    "iso:country":"ES",
    "sg:address":"Ctra Mairena-almensilla, S/n",
    "sg:city":"Mairena Aljarafe",
    "sg:orig_category":"Cerrajer\u00cda, Ferrallista",
    "sg:phone":"+34 955 60 92 63",
    "sg:postcode":"41927",
    "sg:province":"Sevilla",
    "wof:name":"Cerrajeria Blanco S.l.",
    "wof:placetype":"venue"
},
  "geometry": {"coordinates":[-6.0626192093,37.3473587036],"type":"Point"}
}