{
  "type": "Feature",
  "properties": {
    "iso:country":"ES",
    "sg:address":"Plaz Almirante Bastarreche, 10",
    "sg:city":"Aduanas",
    "sg:orig_category":"Fabricaci\u00d3n De Muebles",
    "sg:phone":"+34 965 79 00 72",
    "sg:postcode":"03730",
    "sg:province":"Alicante",
    "wof:name":"Tarraula S.l.",
    "wof:placetype":"venue"
},
  "geometry": {"coordinates":[0.1822409928,38.7944526672],"type":"Point"}
}