{
  "type": "Feature",
  "properties": {
    "addr:full":"Pl. Rastro, 19 Almonacid De La Sierra Zaragoza 50108",
    "addr:housenumber":"19",
    "addr:postcode":"50108",
    "addr:street":"Rastro",
    "iso:country":"ES",
    "sg:address":"Pl. Rastro, 19",
    "sg:city":"Almonacid De La Sierra",
    "sg:orig_category":"Cajas Para Embalar",
    "sg:phone":"+34 976 62 71 67",
    "sg:postcode":"50108",
    "sg:province":"Zaragoza",
    "wof:name":"Caja Rural De Aragon S.coop Credito",
    "wof:placetype":"venue"
},
  "geometry": {"coordinates":[-1.3232690096,41.3975944519],"type":"Point"}
}