{
  "type": "Feature",
  "properties": {
    "iso:country":"ES",
    "sg:address":"Ctra. Madrid-valencia, Km. 0116,0",
    "sg:city":"Montalbo",
    "sg:orig_category":"Mec\u00c1nico Del Autom\u00d3vil",
    "sg:phone":"+34 969 13 00 32",
    "sg:postcode":"16440",
    "sg:province":"Cuenca",
    "wof:name":"Romero Cid Antonio",
    "wof:placetype":"venue"
},
  "geometry": {"coordinates":[-2.6693940163,39.8765182495],"type":"Point"}
}