{
  "type": "Feature",
  "properties": {
    "addr:full":"Calle de Chiva, 9 Cheste Valencia 46380",
    "addr:housenumber":"9",
    "addr:postcode":"46380",
    "addr:street":"Calle De Chiva",
    "iso:country":"ES",
    "sg:address":"Calle de Chiva, 9",
    "sg:city":"Cheste",
    "sg:orig_category":"Cajas De Ahorro",
    "sg:phone":"+34 962 51 16 77",
    "sg:postcode":"46380",
    "sg:province":"Valencia",
    "wof:name":"Caixa D'estalvis I Pensions De Barcelona",
    "wof:placetype":"venue"
},
  "geometry": {"coordinates":[-0.6848080158,39.4945335388],"type":"Point"}
}