{
  "type": "Feature",
  "properties": {
    "addr:full":"Calle de Garcia Lorca, 13 Alberic Valencia 46260",
    "addr:housenumber":"13",
    "addr:postcode":"46260",
    "addr:street":"Calle De Garcia Lorca",
    "iso:country":"ES",
    "sg:address":"Calle de Garcia Lorca, 13",
    "sg:city":"Alberic",
    "sg:orig_category":"Empresas De Carpinter\u00cda De Madera",
    "sg:phone":"+34 962 44 13 20",
    "sg:postcode":"46260",
    "sg:province":"Valencia",
    "wof:name":"Xym Armasons S.l.",
    "wof:placetype":"venue"
},
  "geometry": {"coordinates":[-0.5198441744,39.1179885864],"type":"Point"}
}