{
  "type": "Feature",
  "properties": {
    "addr:full":"Calle de Reinosa (de), 9 Fuenlabrada Madrid 28941",
    "addr:housenumber":"9",
    "addr:postcode":"28941",
    "addr:street":"Calle De Reinosa De",
    "iso:country":"ES",
    "sg:address":"Calle de Reinosa (de), 9",
    "sg:city":"Fuenlabrada",
    "sg:orig_category":"Limpieza Con Chorro De Arena Y Con Granalla, Pulido",
    "sg:phone":"+34 916 08 22 44",
    "sg:postcode":"28941",
    "sg:province":"Madrid",
    "wof:name":"Garcia Gallardo Vicente",
    "wof:placetype":"venue"
},
  "geometry": {"coordinates":[-3.8066420555,40.29945755],"type":"Point"}
}