{
  "type": "Feature",
  "properties": {
    "addr:full":"Calle de Miguel De Cervantes, 79 Chipiona C\u00e1diz 11550",
    "addr:housenumber":"79",
    "addr:postcode":"11550",
    "addr:street":"Calle De Miguel De Cervantes",
    "iso:country":"ES",
    "sg:address":"Calle de Miguel De Cervantes, 79",
    "sg:city":"Chipiona",
    "sg:orig_category":"Arreglo, Reparaci\u00d3n, Piezas Sueltas De Televisi\u00d3n, V\u00cddeo, Hi",
    "sg:phone":"+34 956 37 08 06",
    "sg:postcode":"11550",
    "sg:province":"C\u00e1diz",
    "wof:name":"Electronica Manuel Gomez S.l.",
    "wof:placetype":"venue"
},
  "geometry": {"coordinates":[-6.4325199127,36.7336845398],"type":"Point"}
}