{
  "type": "Feature",
  "properties": {
    "addr:full":"Carr Carles I, 28 Badalona Barcelona 08917",
    "addr:housenumber":"28",
    "addr:postcode":"08917",
    "addr:street":"Carr Carles I",
    "iso:country":"ES",
    "sg:address":"Carr Carles I, 28",
    "sg:city":"Badalona",
    "sg:orig_category":"Peluquer\u00cdas, Peluquer\u00cda Mixta",
    "sg:phone":"+34 933 83 11 08",
    "sg:postcode":"08917",
    "sg:province":"Barcelona",
    "wof:name":"Najar Jodar Maria",
    "wof:placetype":"venue"
},
  "geometry": {"coordinates":[2.2356250286,41.452205658],"type":"Point"}
}