{
  "type": "Feature",
  "properties": {
    "addr:full":"Avda Marques De Rozalejo, 19 Dolores Murcia 30739",
    "addr:housenumber":"19",
    "addr:postcode":"30739",
    "addr:street":"Avda Marques De Rozalejo",
    "iso:country":"ES",
    "sg:address":"Avda Marques De Rozalejo, 19",
    "sg:city":"Dolores",
    "sg:orig_category":"Sanatorios M\u00c9dico",
    "sg:phone":"+34 968 17 32 52",
    "sg:postcode":"30739",
    "sg:province":"Murcia",
    "wof:name":"Servicio Murciano De Salud Centros Provinciales",
    "wof:placetype":"venue"
},
  "geometry": {"coordinates":[-0.870396018,37.7791404724],"type":"Point"}
}