{
  "type": "Feature",
  "properties": {
    "iso:country":"ES",
    "sg:address":"Avda Ana De Viya, 10",
    "sg:city":"Cadiz",
    "sg:orig_category":"Parques De Atracciones Y Centros De Esparcimiento",
    "sg:phone":"+34 956 26 33 55",
    "sg:postcode":"11008",
    "sg:province":"C\u00e1diz",
    "wof:name":"Operadora Gaditana De Juegos S.a.",
    "wof:placetype":"venue"
},
  "geometry": {"coordinates":[-6.2807369232,36.512878418],"type":"Point"}
}