{
  "type": "Feature",
  "properties": {
    "addr:full":"Avda General Lopez Dominguez, 2 Marbella M\u00e1laga 29600",
    "addr:housenumber":"2",
    "addr:postcode":"29600",
    "addr:street":"Avda General Lopez Dominguez;Ma\u0301Laga",
    "iso:country":"ES",
    "sg:address":"Avda General Lopez Dominguez, 2",
    "sg:city":"Marbella",
    "sg:orig_category":"Fisioterapia",
    "sg:phone":"+34 952 89 81 61",
    "sg:postcode":"29600",
    "sg:province":"M\u00e1laga",
    "wof:name":"Wasniewski  Krystyna Teresa",
    "wof:placetype":"venue"
},
  "geometry": {"coordinates":[-4.8758192062,36.5111846924],"type":"Point"}
}