{
  "type": "Feature",
  "properties": {
    "addr:full":"Calle de Caldereros, 12 Villa Rio C\u00f3rdoba 14640",
    "addr:housenumber":"12",
    "addr:postcode":"14640",
    "addr:street":"Calle De Caldereros;Rio Co\u0301Rdoba",
    "iso:country":"ES",
    "sg:address":"Calle de Caldereros, 12",
    "sg:city":"Villa Rio",
    "sg:orig_category":"Empresas De Carpinter\u00cda De Madera",
    "sg:phone":"+34 957 17 74 55",
    "sg:postcode":"14640",
    "sg:province":"C\u00f3rdoba",
    "wof:name":"Abril Lozano Francisco",
    "wof:placetype":"venue"
},
  "geometry": {"coordinates":[-4.287393,37.981255],"type":"Point"}
}