{
  "type": "Feature",
  "properties": {
    "addr:full":"Calle de General Armero, 127 Fuentes De Andalucia Sevilla 41420",
    "addr:housenumber":"127",
    "addr:postcode":"41420",
    "addr:street":"Calle De General Armero",
    "iso:country":"ES",
    "sg:address":"Calle de General Armero, 127",
    "sg:city":"Fuentes De Andalucia",
    "sg:orig_category":"Comerciantes Al Por Mayor De Vinos, Licores Y Alcoholes",
    "sg:phone":"+34 954 83 71 09",
    "sg:postcode":"41420",
    "sg:province":"Sevilla",
    "wof:name":"Gomez Moreno Manuel",
    "wof:placetype":"venue"
},
  "geometry": {"coordinates":[-5.3445630074,37.4634132385],"type":"Point"}
}