{
  "type": "Feature",
  "properties": {
    "iso:country":"ES",
    "sg:address":"Calle de Urola, 4",
    "sg:city":"Zumarraga",
    "sg:orig_category":"Plomeros",
    "sg:phone":"+34 943 72 34 05",
    "sg:postcode":"20700",
    "sg:province":"Guip\u00f9zcoa",
    "wof:name":"Tome Garcia Francisco Manuel",
    "wof:placetype":"venue"
},
  "geometry": {"coordinates":[-2.3184220791,43.0887908936],"type":"Point"}
}