{
  "type": "Feature",
  "properties": {
    "addr:full":"Carrer de Casanova, 33 Barcelona Barcelona 08011",
    "addr:housenumber":"33",
    "addr:postcode":"08011",
    "addr:street":"Carrer De Casanova",
    "iso:country":"ES",
    "sg:address":"Carrer de Casanova, 33",
    "sg:city":"Barcelona",
    "sg:orig_category":"Muebles Y Accesorios Para Cocinas Y Cuartos De Ba\u00d1o (al Por Menor)",
    "sg:phone":"+34 934 54 52 39",
    "sg:postcode":"08011",
    "sg:province":"Barcelona",
    "wof:name":"Radua Remola Francisco",
    "wof:placetype":"venue"
},
  "geometry": {"coordinates":[2.1610479355,41.3835067749],"type":"Point"}
}