{
  "type": "Feature",
  "properties": {
    "addr:full":"Avda Constitucion, 52 Don Benito Badajoz 06400",
    "addr:housenumber":"52",
    "addr:postcode":"06400",
    "addr:street":"Avda Constitucion",
    "iso:country":"ES",
    "sg:address":"Avda Constitucion, 52",
    "sg:city":"Don Benito",
    "sg:orig_category":"Librer\u00cdas",
    "sg:phone":"+34 924 81 30 18",
    "sg:postcode":"06400",
    "sg:province":"Badajoz",
    "wof:name":"Pajares Gallego Gustavo",
    "wof:placetype":"venue"
},
  "geometry": {"coordinates":[-5.8627138138,38.9662666321],"type":"Point"}
}