{
  "type": "Feature",
  "properties": {
    "iso:country":"ES",
    "sg:address":"Av. Casablanca, 1",
    "sg:city":"Prado Rey",
    "sg:orig_category":"Ense\u00d1anza Variada",
    "sg:phone":"+34 915 18 96 91",
    "sg:postcode":"28223",
    "sg:province":"Madrid",
    "sg:website":"www.casarrubios.net",
    "wof:name":"Ignagua Center S.l",
    "wof:placetype":"venue"
},
  "geometry": {"coordinates":[-3.8146739006,40.4409713745],"type":"Point"}
}