{
  "type": "Feature",
  "properties": {
    "iso:country":"ES",
    "sg:address":"Calle de Carretera, 27",
    "sg:city":"Conil De La Frontera",
    "sg:orig_category":"Plomeros",
    "sg:phone":"+34 956 44 00 00",
    "sg:postcode":"11140",
    "sg:province":"C\u00e1diz",
    "wof:name":"Sanchez Ortiz Jose",
    "wof:placetype":"venue"
},
  "geometry": {"coordinates":[-6.0849871635,36.2797775269],"type":"Point"}
}