{
  "type": "Feature",
  "properties": {
    "iso:country":"ES",
    "sg:address":"Calle de Regulo, 18",
    "sg:city":"Zaragoza",
    "sg:orig_category":"Papeler\u00cdas, Librer\u00cdas",
    "sg:phone":"+34 976 75 38 87",
    "sg:postcode":"50012",
    "sg:province":"Zaragoza",
    "wof:name":"Alquezar Blasco Carlos",
    "wof:placetype":"venue"
},
  "geometry": {"coordinates":[-0.928674221,41.6383857727],"type":"Point"}
}