{
  "type": "Feature",
  "properties": {
    "iso:country":"ES",
    "sg:address":"Calle de Cachorro, 25",
    "sg:city":"Ibros",
    "sg:orig_category":"Farmacias",
    "sg:phone":"+34 953 76 71 83",
    "sg:postcode":"23450",
    "sg:province":"Ja\u00e9n",
    "wof:name":"Lendinez Aranda Elena",
    "wof:placetype":"venue"
},
  "geometry": {"coordinates":[-3.5306766033,38.0420341492],"type":"Point"}
}