{
  "type": "Feature",
  "properties": {
    "iso:country":"ES",
    "sg:address":"Rua Suafonte, 13",
    "sg:city":"Burela",
    "sg:orig_category":"Ense\u00d1anza, Formaci\u00d3n Profesional: Aprendizaje",
    "sg:phone":"+34 982 58 06 24",
    "sg:postcode":"27880",
    "sg:province":"Lugo",
    "wof:name":"Concello De Burela",
    "wof:placetype":"venue"
},
  "geometry": {"coordinates":[-7.3572130203,43.6567649841],"type":"Point"}
}