{
  "type": "Feature",
  "properties": {
    "iso:country":"ES",
    "sg:address":"Calle de Serrano, 86",
    "sg:city":"Madrid",
    "sg:orig_category":"Confecci\u00d3n De Trajes Para Se\u00d1oras",
    "sg:phone":"+34 915 75 79 34",
    "sg:postcode":"28006",
    "sg:province":"Madrid",
    "wof:name":"St. George Franchising S.l.",
    "wof:placetype":"venue"
},
  "geometry": {"coordinates":[-3.6867864132,40.4318161011],"type":"Point"}
}