{
  "type": "Feature",
  "properties": {
    "iso:country":"ES",
    "sg:address":"Calle de Esfinge, S/n",
    "sg:city":"Madrid",
    "sg:orig_category":"Asilos De Ancianos. Centros Privados",
    "sg:phone":"+34 917 41 17 62",
    "sg:postcode":"28022",
    "sg:province":"Madrid",
    "wof:name":"Residencia Nuestra Se\u00f1ora Del Pilar",
    "wof:placetype":"venue"
},
  "geometry": {"coordinates":[-3.6114439964,40.4467811584],"type":"Point"}
}