{
  "type": "Feature",
  "properties": {
    "addr:full":"Calle de Arroyadas, 7 Boecillo Valladolid 47151",
    "addr:housenumber":"7",
    "addr:postcode":"47151",
    "addr:street":"Calle De Arroyadas",
    "iso:country":"ES",
    "sg:address":"Calle de Arroyadas, 7",
    "sg:city":"Boecillo",
    "sg:orig_category":"Carnicer\u00cdas, Carnicer\u00cdas",
    "sg:phone":"+34 983 55 21 48",
    "sg:postcode":"47151",
    "sg:province":"Valladolid",
    "wof:name":"Alderete Ortega Elias",
    "wof:placetype":"venue"
},
  "geometry": {"coordinates":[-4.7017006874,41.5410728455],"type":"Point"}
}