{
  "type": "Feature",
  "properties": {
    "addr:full":"Avda Sevilla, 4 Don Benito Badajoz 06400",
    "addr:housenumber":"4",
    "addr:postcode":"06400",
    "addr:street":"Avda Sevilla",
    "iso:country":"ES",
    "sg:address":"Avda Sevilla, 4",
    "sg:city":"Don Benito",
    "sg:orig_category":"Electricidad, Electr\u00d3nica: Material Y Suministros (al Por Mayor)",
    "sg:phone":"+34 924 80 80 82",
    "sg:postcode":"06400",
    "sg:province":"Badajoz",
    "sg:website":"www.sumelex.net",
    "wof:name":"Sumelex Zafra S.l.",
    "wof:placetype":"venue"
},
  "geometry": {"coordinates":[-5.8753938675,38.953956604],"type":"Point"}
}