{
  "type": "Feature",
  "properties": {
    "iso:country":"ES",
    "sg:address":"Calle de San Telmo, 2",
    "sg:city":"Puerto Cruz",
    "sg:orig_category":"Importaci\u00d3n",
    "sg:phone":"+34 922 38 29 01",
    "sg:postcode":"38400",
    "sg:province":"Santa Cruz De Tenerife",
    "wof:name":"Martesan Tenerife S.l.",
    "wof:placetype":"venue"
},
  "geometry": {"coordinates":[-16.5478096008,28.4170608521],"type":"Point"}
}