{
  "type": "Feature",
  "properties": {
    "addr:full":"Calle de Pedro Cabanes, 5 Valencia Valencia 46019",
    "addr:housenumber":"5",
    "addr:postcode":"46019",
    "addr:street":"Calle De Pedro Cabanes",
    "iso:country":"ES",
    "sg:address":"Calle de Pedro Cabanes, 5",
    "sg:city":"Valencia",
    "sg:orig_category":"Inmobiliaria (agencias)",
    "sg:phone":"+34 963 65 23 02",
    "sg:postcode":"46019",
    "sg:province":"Valencia",
    "wof:name":"Meri Valin S.l.",
    "wof:placetype":"venue"
},
  "geometry": {"coordinates":[-0.3723750114,39.4952735901],"type":"Point"}
}