{
  "type": "Feature",
  "properties": {
    "iso:country":"ES",
    "sg:address":"Calle de Triste Condesa, 3",
    "sg:city":"Arenas San Pedro",
    "sg:orig_category":"Mercer\u00cda, Lencer\u00cda (al Por Menor)",
    "sg:phone":"+34 920 37 09 05",
    "sg:postcode":"05400",
    "sg:province":"\u00c1vila",
    "wof:name":"Burgos Mu\u00f1oz Maria Del Pilar",
    "wof:placetype":"venue"
},
  "geometry": {"coordinates":[-5.0905308723,40.2097396851],"type":"Point"}
}