{
  "type": "Feature",
  "properties": {
    "addr:full":"Calle de Cuartel, 8 Epila Zaragoza 50290",
    "addr:housenumber":"8",
    "addr:postcode":"50290",
    "addr:street":"Calle De Cuartel",
    "iso:country":"ES",
    "sg:address":"Calle de Cuartel, 8",
    "sg:city":"Epila",
    "sg:orig_category":"Promotores Constructores",
    "sg:phone":"+34 976 60 34 58",
    "sg:postcode":"50290",
    "sg:province":"Zaragoza",
    "wof:name":"Celaya Gomez Jose Antonio",
    "wof:placetype":"venue"
},
  "geometry": {"coordinates":[-1.2829084396,41.5989074707],"type":"Point"}
}