{
  "type": "Feature",
  "properties": {
    "addr:full":"Carrer de Sant Antoni Maria Claret, 178 Barcelona Barcelona 08025",
    "addr:housenumber":"178",
    "addr:postcode":"08025",
    "addr:street":"Carrer De Sant Antoni Maria Claret",
    "iso:country":"ES",
    "sg:address":"Carrer de Sant Antoni Maria Claret, 178",
    "sg:city":"Barcelona",
    "sg:classifiers":[
        {
            "category":"Personal",
            "subcategory":"Barber",
            "type":"Services"
        }
    ],
    "sg:phone":"+34 934 35 87 96",
    "sg:postcode":"08025",
    "sg:province":"Barcelona",
    "sg:tags":[
        "caballeros",
        "de",
        "peluqueros"
    ],
    "wof:name":"Sole Salles Pedro Juan",
    "wof:placetype":"venue"
},
  "geometry": {"coordinates":[2.172385931,41.4095916748],"type":"Point"}
}