{
  "type": "Feature",
  "properties": {
    "iso:country":"ES",
    "sg:address":"Carrer de Lourdes, 9",
    "sg:city":"Premia Mar",
    "sg:orig_category":"Ropa De Trabajo Y Profesionales (fabricaci\u00d3n, Al Por Mayor)",
    "sg:phone":"+34 937 54 95 32",
    "sg:postcode":"08330",
    "sg:province":"Barcelona",
    "wof:name":"T 2 S Iberica S.l.",
    "wof:placetype":"venue"
},
  "geometry": {"coordinates":[2.3539469242,41.4966583252],"type":"Point"}
}