{
  "type": "Feature",
  "properties": {
    "addr:full":"Avda Galicia De, 34 Luarca Asturias 33700",
    "addr:housenumber":"34",
    "addr:postcode":"33700",
    "addr:street":"Avda Galicia De",
    "iso:country":"ES",
    "sg:address":"Avda Galicia De, 34",
    "sg:city":"Luarca",
    "sg:orig_category":"Fisioterapia",
    "sg:phone":"+34 985 47 03 52",
    "sg:postcode":"33700",
    "sg:province":"Asturias",
    "wof:name":"Mendez Fernandez Noelia",
    "wof:placetype":"venue"
},
  "geometry": {"coordinates":[-6.5405840874,43.5432167053],"type":"Point"}
}