{
  "type": "Feature",
  "properties": {
    "addr:full":"Rond Muralla (da), 85 Lugo Lugo 27003",
    "addr:postcode":"27003",
    "addr:street":"Rond;Da",
    "iso:country":"ES",
    "sg:address":"Rond Muralla (da), 85",
    "sg:city":"Lugo",
    "sg:orig_category":"Fabricaci\u00d3n De Telas Y Sedas",
    "sg:phone":"+34 982 22 58 54",
    "sg:postcode":"27003",
    "sg:province":"Lugo",
    "wof:name":"Hijos De Fernando Bodelon S.l.",
    "wof:placetype":"venue"
},
  "geometry": {"coordinates":[-7.5763959885,43.0335426331],"type":"Point"}
}