{
  "type": "Feature",
  "properties": {
    "iso:country":"ES",
    "sg:address":"Rua Conde Pallares, 1",
    "sg:city":"Lugo",
    "sg:orig_category":"Material Did\u00c1ctico",
    "sg:phone":"+34 982 22 87 11",
    "sg:postcode":"27001",
    "sg:province":"Lugo",
    "wof:name":"Legido Souto Cristina",
    "wof:placetype":"venue"
},
  "geometry": {"coordinates":[-7.5572252274,43.0099105835],"type":"Point"}
}