{
  "type": "Feature",
  "properties": {
    "iso:country":"ES",
    "sg:address":"Carrer de Puigbarral, 22",
    "sg:city":"Terrassa",
    "sg:orig_category":"Muebles, Minoristas",
    "sg:phone":"+34 937 31 22 56",
    "sg:postcode":"08227",
    "sg:province":"Barcelona",
    "sg:website":"www.terrassadecoracio.com",
    "wof:name":"Terrassa Decoracio S.l.l.",
    "wof:placetype":"venue"
},
  "geometry": {"coordinates":[2.0355110168,41.5802841187],"type":"Point"}
}