{
  "type": "Feature",
  "properties": {
    "iso:country":"ES",
    "sg:address":"Trva Fray Gerundio De Campazas, 4",
    "sg:city":"Cistierna",
    "sg:orig_category":"Confecci\u00d3n De Trajes Para Se\u00d1oras",
    "sg:phone":"+34 987 70 02 79",
    "sg:postcode":"24800",
    "sg:province":"Le\u00f3n",
    "wof:name":"El Roblo Sdad Coop",
    "wof:placetype":"venue"
},
  "geometry": {"coordinates":[-5.1265640259,42.8039054871],"type":"Point"}
}