{
  "type": "Feature",
  "properties": {
    "addr:full":"Rua Uruguay (do), 9 Carballi\u00f1o Ourense 32500",
    "addr:housenumber":"9",
    "addr:postcode":"32500",
    "addr:street":"Rua Uruguay Do",
    "iso:country":"ES",
    "sg:address":"Rua Uruguay (do), 9",
    "sg:city":"Carballi\u00f1o",
    "sg:orig_category":"Cristaler\u00cdas",
    "sg:phone":"+34 988 27 53 22",
    "sg:postcode":"32500",
    "sg:province":"Ourense",
    "wof:name":"Piteira Bravo S.cv.",
    "wof:placetype":"venue"
},
  "geometry": {"coordinates":[-8.080904007,42.4311981201],"type":"Point"}
}