{
  "type": "Feature",
  "properties": {
    "iso:country":"ES",
    "sg:address":"Polig Industrial Puente Alto, S/n",
    "sg:city":"Orihuela",
    "sg:orig_category":"Carnes De Carnicer\u00cda (al Por Mayor)",
    "sg:phone":"+34 966 73 68 65",
    "sg:postcode":"03300",
    "sg:province":"Alicante",
    "wof:name":"Carnicas Monte Pinar S.l.",
    "wof:placetype":"venue"
},
  "geometry": {"coordinates":[-0.9448040128,38.0817642212],"type":"Point"}
}