{
  "type": "Feature",
  "properties": {
    "addr:full":"Calle de Primavera, 23 Arganda Madrid 28500",
    "addr:housenumber":"23",
    "addr:postcode":"28500",
    "addr:street":"Calle De Primavera",
    "iso:country":"ES",
    "sg:address":"Calle de Primavera, 23",
    "sg:city":"Arganda",
    "sg:orig_category":"Cajas Y Embalajes De Pl\u00c1stico",
    "sg:phone":"+34 918 71 93 63",
    "sg:postcode":"28500",
    "sg:province":"Madrid",
    "wof:name":"Fuentes Envases Plasticos S.l.",
    "wof:placetype":"venue"
},
  "geometry": {"coordinates":[-3.4883759022,40.3098220825],"type":"Point"}
}