{
  "type": "Feature",
  "properties": {
    "addr:full":"Carrer de Orosi (d'), 11 Tarragona Tarragona 43004",
    "addr:housenumber":"11",
    "addr:postcode":"43004",
    "addr:street":"Carrer De Orosi D '",
    "iso:country":"ES",
    "sg:address":"Carrer de Orosi (d'), 11",
    "sg:city":"Tarragona",
    "sg:orig_category":"Locales Deportivos",
    "sg:phone":"+34 977 21 17 08",
    "sg:postcode":"43004",
    "sg:province":"Tarragona",
    "sg:website":"www.grupsport.com",
    "wof:name":"Grup Tarraco Sport Sl",
    "wof:placetype":"venue"
},
  "geometry": {"coordinates":[1.2520849705,41.1120758057],"type":"Point"}
}