{
  "type": "Feature",
  "properties": {
    "addr:full":"Calle de Gutemberg, S/n Getafe Madrid 28906",
    "addr:housenumber":"s / n",
    "addr:postcode":"28906",
    "addr:street":"Calle De Gutemberg",
    "iso:country":"ES",
    "sg:address":"Calle de Gutemberg, S/n",
    "sg:city":"Getafe",
    "sg:orig_category":"Embalajes",
    "sg:phone":"+34 916 96 69 11",
    "sg:postcode":"28906",
    "sg:province":"Madrid",
    "sg:website":"www.nefab.com",
    "wof:name":"Nefab S.a.",
    "wof:placetype":"venue"
},
  "geometry": {"coordinates":[-3.6999049187,40.2959022522],"type":"Point"}
}