{
  "type": "Feature",
  "properties": {
    "addr:full":"Poligono Industrial De Bayas, S/n Miranda Ebro Burgos 09200",
    "addr:housenumber":"s / n",
    "addr:postcode":"09200",
    "addr:street":"Industrial;Bayas",
    "iso:country":"ES",
    "sg:address":"Poligono Industrial De Bayas, S/n",
    "sg:city":"Miranda Ebro",
    "sg:orig_category":"Bares, Piano",
    "sg:phone":"+34 947 31 40 21",
    "sg:postcode":"09200",
    "sg:province":"Burgos",
    "wof:name":"Liconorte S.l.",
    "wof:placetype":"venue"
},
  "geometry": {"coordinates":[-2.916533947,42.6962852478],"type":"Point"}
}