{
  "type": "Feature",
  "properties": {
    "iso:country":"ES",
    "sg:address":"Carrer de Major, 3",
    "sg:city":"Pobla De Massaluca",
    "sg:classifiers":[
        {
            "category":"Taxi",
            "type":"Transportation"
        }
    ],
    "sg:phone":"+34 977 43 97 64",
    "sg:postcode":"43783",
    "sg:province":"Tarragona",
    "wof:name":"Guimera Domenech Jose",
    "wof:placetype":"venue"
},
  "geometry": {"coordinates":[0.3537319899,41.1799507141],"type":"Point"}
}