{
  "type": "Feature",
  "properties": {
    "addr:full":"Calle de Granada, 2 Rincon Victoria M\u00e1laga 29730",
    "addr:housenumber":"2",
    "addr:postcode":"29730",
    "addr:street":"Calle De Granada;Ma\u0301Laga",
    "iso:country":"ES",
    "sg:address":"Calle de Granada, 2",
    "sg:city":"Rincon Victoria",
    "sg:orig_category":"Ropa Para Se\u00d1oras (al Por Menor)",
    "sg:phone":"+34 952 40 30 22",
    "sg:postcode":"29730",
    "sg:province":"M\u00e1laga",
    "wof:name":"Arresa Martos Ana Maria",
    "wof:placetype":"venue"
},
  "geometry": {"coordinates":[-4.2859511375,36.7172927856],"type":"Point"}
}