{
  "type": "Feature",
  "properties": {
    "iso:country":"ES",
    "sg:address":"Avda Marques De Sotelo, 4",
    "sg:city":"Valencia",
    "sg:orig_category":"Ropa Para Se\u00d1oras (al Por Menor)",
    "sg:phone":"+34 963 51 65 50",
    "sg:postcode":"46002",
    "sg:province":"Valencia",
    "wof:name":"Vila Magrinya Carlos",
    "wof:placetype":"venue"
},
  "geometry": {"coordinates":[-0.3770709932,39.4689025879],"type":"Point"}
}