{
  "type": "Feature",
  "properties": {
    "addr:full":"Calle de Morote, 4 Huescar Granada 18830",
    "addr:housenumber":"4",
    "addr:postcode":"18830",
    "addr:street":"Calle De Morote",
    "iso:country":"ES",
    "sg:address":"Calle de Morote, 4",
    "sg:city":"Huescar",
    "sg:orig_category":"\u00d3ptica: Instrumentos (fabricaci\u00d3n)",
    "sg:phone":"+34 958 74 25 92",
    "sg:postcode":"18830",
    "sg:province":"Granada",
    "wof:name":"Macizo Soria Ana Belen",
    "wof:placetype":"venue"
},
  "geometry": {"coordinates":[-2.5404698849,37.8090591431],"type":"Point"}
}