{
  "type": "Feature",
  "properties": {
    "addr:full":"Crt. Pe\u00f1as S. Pedro, S/n Albacete Albacete 02006",
    "addr:housenumber":"s / n",
    "addr:postcode":"02006",
    "addr:street":"Pen\u0303As;Pedro",
    "iso:country":"ES",
    "sg:address":"Crt. Pe\u00f1as S. Pedro, S/n",
    "sg:city":"Albacete",
    "sg:orig_category":"Semiller\u00cdas",
    "sg:phone":"+34 967 58 00 47",
    "sg:postcode":"02006",
    "sg:province":"Albacete",
    "wof:name":"Forestales Autoctonas S.l.",
    "wof:placetype":"venue"
},
  "geometry": {"coordinates":[-1.8641489744,38.9841651917],"type":"Point"}
}