{
  "type": "Feature",
  "properties": {
    "iso:country":"ES",
    "sg:address":"Calle de Puente Colgante, 65",
    "sg:city":"Valladolid",
    "sg:orig_category":"Comercio, Reparaci\u00d3n De Bicicletas, De Motocicletas, De Accesorios",
    "sg:phone":"+34 983 23 21 73",
    "sg:postcode":"47006",
    "sg:province":"Valladolid",
    "wof:name":"Chao Import S.l.",
    "wof:placetype":"venue"
},
  "geometry": {"coordinates":[-4.7396087646,41.6405448914],"type":"Point"}
}