{
  "type": "Feature",
  "properties": {
    "addr:full":"Calle de Lope De Rueda, 12 Madrid Madrid 28009",
    "addr:housenumber":"12",
    "addr:postcode":"madrid;28009",
    "addr:street":"Calle De Lope De Rueda",
    "iso:country":"ES",
    "sg:address":"Calle de Lope De Rueda, 12",
    "sg:city":"Madrid",
    "sg:orig_category":"Peluqueros: De Se\u00d1oras",
    "sg:phone":"+34 915 76 41 08",
    "sg:postcode":"28009",
    "sg:province":"Madrid",
    "wof:name":"Martinez Polo Matilde",
    "wof:placetype":"venue"
},
  "geometry": {"coordinates":[-3.6775639057,40.4229240417],"type":"Point"}
}