{
  "type": "Feature",
  "properties": {
    "iso:country":"ES",
    "sg:address":"Benisan\u00f3, 5",
    "sg:city":"Riba-roja Turia",
    "sg:orig_category":"Empresas De Carpinter\u00cda De Madera",
    "sg:phone":"+34 962 77 23 04",
    "sg:postcode":"46190",
    "sg:province":"Valencia",
    "wof:name":"Carpinteria Gaza C.b.",
    "wof:placetype":"venue"
},
  "geometry": {"coordinates":[-0.5653470159,39.543510437],"type":"Point"}
}