{
  "type": "Feature",
  "properties": {
    "addr:full":"Calle de Hilarion Eslava, 36 Madrid Madrid 28015",
    "addr:housenumber":"36",
    "addr:postcode":"madrid;28015",
    "addr:street":"Calle De Hilarion Eslava",
    "iso:country":"ES",
    "sg:address":"Calle de Hilarion Eslava, 36",
    "sg:city":"Madrid",
    "sg:orig_category":"Inmobiliaria (agencias)",
    "sg:phone":"+34 915 49 57 56",
    "sg:postcode":"28015",
    "sg:province":"Madrid",
    "wof:name":"Comunidad Garcia Esquinas S.l.",
    "wof:placetype":"venue"
},
  "geometry": {"coordinates":[-3.7164239883,40.4358863831],"type":"Point"}
}