{
  "type": "Feature",
  "properties": {
    "iso:country":"ES",
    "sg:address":"Avda Dacio Darias, 5",
    "sg:city":"Valverde",
    "sg:orig_category":"Supermercados Y Hipermercados",
    "sg:phone":"+34 922 55 02 18",
    "sg:postcode":"38910",
    "sg:province":"Santa Cruz De Tenerife",
    "wof:name":"Padron Morales Sinforiano",
    "wof:placetype":"venue"
},
  "geometry": {"coordinates":[-17.8970718384,27.8238143921],"type":"Point"}
}