{
  "type": "Feature",
  "properties": {
    "addr:full":"Calle de Cervantes, 59 Montehermoso C\u00e1ceres 10810",
    "addr:housenumber":"59",
    "addr:postcode":"10810",
    "addr:street":"Calle De Cervantes;Ca\u0301Ceres",
    "iso:country":"ES",
    "sg:address":"Calle de Cervantes, 59",
    "sg:city":"Montehermoso",
    "sg:orig_category":"Maquinaria Para Industrias Diversas",
    "sg:phone":"+34 927 67 51 38",
    "sg:postcode":"10810",
    "sg:province":"C\u00e1ceres",
    "wof:name":"Automaticos Laynez S.l.",
    "wof:placetype":"venue"
},
  "geometry": {"coordinates":[-6.3471579552,40.0876121521],"type":"Point"}
}