{
  "type": "Feature",
  "properties": {
    "addr:full":"Ctra. General, Km. 0138,0 Ballota Asturias 33158",
    "addr:postcode":"33158",
    "addr:street":"Ctra. General Km. 0138,0 Ballota Asturias",
    "iso:country":"ES",
    "sg:address":"Ctra. General, Km. 0138,0",
    "sg:city":"Ballota",
    "sg:classifiers":[
        {
            "category":"Banks & Credit Unions",
            "subcategory":"Bureau De Change",
            "type":"Services"
        }
    ],
    "sg:phone":"+34 985 59 82 52",
    "sg:postcode":"33158",
    "sg:province":"Asturias",
    "sg:tags":[
        "organismos",
        "control"
    ],
    "wof:name":"Investigacion Y Control De Calidad S.a.-fulcrum Planificacion, Analisis Y Proyectos S.a. U.t.e.",
    "wof:placetype":"venue"
},
  "geometry": {"coordinates":[-6.3312840462,43.551864624],"type":"Point"}
}