{
  "type": "Feature",
  "properties": {
    "iso:country":"ES",
    "sg:address":"Cra. Olot, 77",
    "sg:city":"Manlleu",
    "sg:orig_category":"Droguer\u00cdas (al Por Menor)",
    "sg:phone":"+34 938 51 43 06",
    "sg:postcode":"08560",
    "sg:province":"Barcelona",
    "wof:name":"Trias Tremolosa S.l.",
    "wof:placetype":"venue"
},
  "geometry": {"coordinates":[2.2942180634,42.0038223267],"type":"Point"}
}