{
  "type": "Feature",
  "properties": {
    "iso:country":"ES",
    "sg:address":"Calle de Cervantes, 3",
    "sg:city":"Esquivias",
    "sg:orig_category":"Pescader\u00cdas (al Por Menor)",
    "sg:phone":"+34 925 52 05 66",
    "sg:postcode":"45221",
    "sg:province":"Toledo",
    "wof:name":"Mateo Romero Fernando",
    "wof:placetype":"venue"
},
  "geometry": {"coordinates":[-3.7670772076,40.105556488],"type":"Point"}
}