{
  "type": "Feature",
  "properties": {
    "iso:country":"ES",
    "sg:address":"Trva Aguieira, 60",
    "sg:city":"Grove",
    "sg:orig_category":"Estudios Y Construcci\u00d3n De Acuarios Y Viveros",
    "sg:phone":"+34 986 73 18 85",
    "sg:postcode":"36980",
    "sg:province":"Pontevedra",
    "wof:name":"Castro E Hijos C.b.",
    "wof:placetype":"venue"
},
  "geometry": {"coordinates":[-8.8673887253,42.4969100952],"type":"Point"}
}