{
  "type": "Feature",
  "properties": {
    "addr:full":"Carrer de Marina, 123 Barcelona Barcelona 08013",
    "addr:housenumber":"123",
    "addr:postcode":"08013",
    "addr:street":"Carrer De Marina",
    "iso:country":"ES",
    "sg:address":"Carrer de Marina, 123",
    "sg:city":"Barcelona",
    "sg:orig_category":"Delegados, Agentes De Tr\u00c1nsito, Auxiliares De Transporte Internacional",
    "sg:phone":"+34 932 65 81 07",
    "sg:postcode":"08013",
    "sg:province":"Barcelona",
    "wof:name":"Trans J. Marti S.a.",
    "wof:placetype":"venue"
},
  "geometry": {"coordinates":[2.1841681004,41.3964767456],"type":"Point"}
}