{
  "type": "Feature",
  "properties": {
    "iso:country":"ES",
    "sg:address":"Carrer de Pere Codina I Mont, 1",
    "sg:city":"Lloret Mar",
    "sg:orig_category":"Vinos Y Licores (venta Al Por Menor)",
    "sg:phone":"+34 972 36 22 99",
    "sg:postcode":"17310",
    "sg:province":"Girona",
    "wof:name":"Abella-zijlstra C.b.",
    "wof:placetype":"venue"
},
  "geometry": {"coordinates":[2.835776,41.700344],"type":"Point"}
}