{
  "type": "Feature",
  "properties": {
    "iso:country":"ES",
    "sg:address":"Carrer de Evarist Arnus, 58",
    "sg:city":"Barcelona",
    "sg:orig_category":"Arquitectos",
    "sg:phone":"+34 933 30 49 94",
    "sg:postcode":"08014",
    "sg:province":"Barcelona",
    "wof:name":"Estudi D'arquitectura Fernandez Domingo S.l.",
    "wof:placetype":"venue"
},
  "geometry": {"coordinates":[2.1358680725,41.383480072],"type":"Point"}
}