{
  "type": "Feature",
  "properties": {
    "addr:full":"Pase Valdelasfuentes (de), 14 Alcobendas Madrid 28100",
    "addr:postcode":"28100",
    "iso:country":"ES",
    "sg:address":"Pase Valdelasfuentes (de), 14",
    "sg:city":"Alcobendas",
    "sg:orig_category":"Cl\u00cdnicas Dentales",
    "sg:phone":"+34 916 61 86 46",
    "sg:postcode":"28100",
    "sg:province":"Madrid",
    "wof:name":"Centro Odontoestomatologico Moderno S.l.",
    "wof:placetype":"venue"
},
  "geometry": {"coordinates":[-3.6421079636,40.5550460815],"type":"Point"}
}