{
  "type": "Feature",
  "properties": {
    "iso:country":"ES",
    "sg:address":"Cmno Elizondo Bidea, 5",
    "sg:city":"Zabaloetxe",
    "sg:orig_category":"Estancos",
    "sg:phone":"+34 944 53 06 89",
    "sg:postcode":"48180",
    "sg:province":"Vizcaya",
    "wof:name":"Arteta Sertucha Maria Pilar",
    "wof:placetype":"venue"
},
  "geometry": {"coordinates":[-2.9392166138,43.3139572144],"type":"Point"}
}