{
  "type": "Feature",
  "properties": {
    "iso:country":"ES",
    "sg:address":"Calle de Irala, 7",
    "sg:city":"Bilbao",
    "sg:orig_category":"Loter\u00cda Y T\u00d3mbola",
    "sg:phone":"+34 944 44 41 20",
    "sg:postcode":"48012",
    "sg:province":"Vizcaya",
    "wof:name":"Vidaurrazaga Vergara Maria Diana",
    "wof:placetype":"venue"
},
  "geometry": {"coordinates":[-2.9358797073,43.2557449341],"type":"Point"}
}