{
  "type": "Feature",
  "properties": {
    "iso:country":"ES",
    "sg:address":"Calle de Minerva, 131",
    "sg:city":"Madrid",
    "sg:orig_category":"Peluqueros: De Se\u00d1oras",
    "sg:phone":"+34 917 75 24 97",
    "sg:postcode":"28032",
    "sg:province":"Madrid",
    "wof:name":"Pau Sanchez Pedro",
    "wof:placetype":"venue"
},
  "geometry": {"coordinates":[-3.6071069241,40.3953819275],"type":"Point"}
}