{
  "type": "Feature",
  "properties": {
    "iso:country":"ES",
    "sg:address":"Avda Lisboa, 4",
    "sg:city":"Alcorcon",
    "sg:orig_category":"Mercer\u00cda, Lencer\u00cda (al Por Menor)",
    "sg:phone":"+34 916 10 27 37",
    "sg:postcode":"28924",
    "sg:province":"Madrid",
    "wof:name":"Volvoreta C.b.",
    "wof:placetype":"venue"
},
  "geometry": {"coordinates":[-3.821457386,40.3521270752],"type":"Point"}
}