{
  "type": "Feature",
  "properties": {
    "addr:full":"Carrer de Avellaneda, 16 Sabadell Barcelona 08201",
    "addr:housenumber":"16",
    "addr:postcode":"08201",
    "addr:street":"Carrer De Avellaneda",
    "iso:country":"ES",
    "sg:address":"Carrer de Avellaneda, 16",
    "sg:city":"Sabadell",
    "sg:orig_category":"Encuadernaci\u00d3n E Impresi\u00d3n De Folletos",
    "sg:phone":"+34 937 26 27 95",
    "sg:postcode":"08201",
    "sg:province":"Barcelona",
    "wof:name":"Monta\u00f1a Faure Luis",
    "wof:placetype":"venue"
},
  "geometry": {"coordinates":[2.1067750454,41.5439987183],"type":"Point"}
}