{
  "type": "Feature",
  "properties": {
    "iso:country":"ES",
    "sg:address":"Calle de Doctor Sirvent, 22",
    "sg:city":"Almoradi",
    "sg:orig_category":"Institutos De Belleza",
    "sg:phone":"+34 965 70 22 93",
    "sg:postcode":"03160",
    "sg:province":"Alicante",
    "wof:name":"Guillardini Ibarra Ana Belen",
    "wof:placetype":"venue"
},
  "geometry": {"coordinates":[-0.7885429263,38.1092948914],"type":"Point"}
}