{
  "type": "Feature",
  "properties": {
    "iso:country":"ES",
    "sg:address":"Calle de Muro De Santa Ana, 6",
    "sg:city":"Valencia",
    "sg:orig_category":"Caf\u00c9s, Bares, Cervecer\u00cdas",
    "sg:phone":"+34 963 91 93 41",
    "sg:postcode":"46003",
    "sg:province":"Valencia",
    "wof:name":"Emilia Garcia Lopez S.l.unipersonal",
    "wof:placetype":"venue"
},
  "geometry": {"coordinates":[-0.3745290041,39.4787330627],"type":"Point"}
}