{
  "type": "Feature",
  "properties": {
    "addr:full":"Avgd D'almansa, S/n Ontinyent Valencia 46870",
    "addr:housenumber":"s / n",
    "addr:postcode":"46870",
    "iso:country":"ES",
    "sg:address":"Avgd D'almansa, S/n",
    "sg:city":"Ontinyent",
    "sg:orig_category":"Ingenier\u00cda, Centros De Estudios (diversos)",
    "sg:phone":"+34 962 38 34 56",
    "sg:postcode":"46870",
    "sg:province":"Valencia",
    "wof:name":"Aparicio Llovet Fernando",
    "wof:placetype":"venue"
},
  "geometry": {"coordinates":[-0.6159402132,38.8211936951],"type":"Point"}
}