{
  "type": "Feature",
  "properties": {
    "iso:country":"ES",
    "sg:address":"Rbla Mestre Torrents, 43",
    "sg:city":"Roca Valles",
    "sg:orig_category":"Institutos De Belleza",
    "sg:phone":"+34 938 42 00 40",
    "sg:postcode":"08430",
    "sg:province":"Barcelona",
    "wof:name":"Garcia Ordo\u00f1ez Marta",
    "wof:placetype":"venue"
},
  "geometry": {"coordinates":[2.3245592117,41.584312439],"type":"Point"}
}