{
  "type": "Feature",
  "properties": {
    "iso:country":"ES",
    "sg:address":"Calle de Real, 38",
    "sg:city":"Fabero",
    "sg:orig_category":"Abogados",
    "sg:phone":"+34 987 55 11 00",
    "sg:postcode":"24420",
    "sg:province":"Le\u00f3n",
    "wof:name":"Fernandez Prieto Luis",
    "wof:placetype":"venue"
},
  "geometry": {"coordinates":[-6.6268701553,42.7666893005],"type":"Point"}
}