{
  "type": "Feature",
  "properties": {
    "addr:full":"Plaz Santa Marina, 22 Toro Zamora 49800",
    "addr:housenumber":"22",
    "addr:postcode":"49800",
    "addr:street":"Santa Marina",
    "iso:country":"ES",
    "sg:address":"Plaz Santa Marina, 22",
    "sg:city":"Toro",
    "sg:orig_category":"Carnicer\u00cdas, Carnicer\u00cdas",
    "sg:phone":"+34 980 69 25 98",
    "sg:postcode":"49800",
    "sg:province":"Zamora",
    "wof:name":"Salchicheria Santa Marina S.l.",
    "wof:placetype":"venue"
},
  "geometry": {"coordinates":[-5.3906588554,41.525844574],"type":"Point"}
}