{
  "type": "Feature",
  "properties": {
    "iso:country":"ES",
    "sg:address":"Carrer de Roger De Lluria, 106",
    "sg:city":"Terrassa",
    "sg:orig_category":"Servicios De Telecomunicaciones",
    "sg:phone":"+34 937 84 33 52",
    "sg:postcode":"08223",
    "sg:province":"Barcelona",
    "sg:website":"www.tecnimat.com",
    "wof:name":"Tecnimat Electronica Y Comunicaciones S.l.",
    "wof:placetype":"venue"
},
  "geometry": {"coordinates":[2.0134789944,41.5536880493],"type":"Point"}
}