{
  "type": "Feature",
  "properties": {
    "iso:country":"ES",
    "sg:address":"Calle de Alvaro De Albornoz, 22",
    "sg:city":"Gijon",
    "sg:orig_category":"Peluqueros: De Se\u00d1oras",
    "sg:phone":"+34 985 34 08 95",
    "sg:postcode":"33207",
    "sg:province":"Asturias",
    "wof:name":"Sanchez Perez Noelia",
    "wof:placetype":"venue"
},
  "geometry": {"coordinates":[-5.667620182,43.5364990234],"type":"Point"}
}