{
  "type": "Feature",
  "properties": {
    "addr:full":"Calle de Extramuros, 11 Piedrahita \u00c1vila 05500",
    "addr:housenumber":"11",
    "addr:postcode":"05500",
    "addr:street":"Calle De Extramuros",
    "iso:country":"ES",
    "sg:address":"Calle de Extramuros, 11",
    "sg:city":"Piedrahita",
    "sg:orig_category":"Venta, Instalaci\u00d3n De Calefacci\u00d3n",
    "sg:phone":"+34 920 36 02 28",
    "sg:postcode":"05500",
    "sg:province":"\u00c1vila",
    "wof:name":"Gonzalvez Aire Joaquin",
    "wof:placetype":"venue"
},
  "geometry": {"coordinates":[-5.3280305862,40.459072113],"type":"Point"}
}