{
  "type": "Feature",
  "properties": {
    "addr:full":"Calle de Almirante Cadarso, 31 Valencia Valencia 46005",
    "addr:housenumber":"31",
    "addr:postcode":"46005",
    "addr:street":"Calle De Almirante Cadarso",
    "iso:country":"ES",
    "sg:address":"Calle de Almirante Cadarso, 31",
    "sg:city":"Valencia",
    "sg:classifiers":[
        {
            "category":"Cinema",
            "subcategory":"Movie Theater",
            "type":"Entertainment"
        }
    ],
    "sg:phone":"+34 963 34 87 64",
    "sg:postcode":"46005",
    "sg:province":"Valencia",
    "sg:tags":[
        "salas",
        "de",
        "cine"
    ],
    "wof:name":"Olympia Metropolitana S.a.",
    "wof:placetype":"venue"
},
  "geometry": {"coordinates":[-0.3672128916,39.4641723633],"type":"Point"}
}