{
  "type": "Feature",
  "properties": {
    "addr:full":"Cust Gomerez (de), 29 Granada Granada 18009",
    "addr:postcode":"18009",
    "iso:country":"ES",
    "sg:address":"Cust Gomerez (de), 29",
    "sg:city":"Granada",
    "sg:orig_category":"Fabricaci\u00d3n De Instrumentos Y Accesorios Musicales",
    "sg:phone":"+34 958 22 63 69",
    "sg:postcode":"18009",
    "sg:province":"Granada",
    "wof:name":"Diaz Fernandez Francisco Manuel",
    "wof:placetype":"venue"
},
  "geometry": {"coordinates":[-3.5942070484,37.1761627197],"type":"Point"}
}