{
  "type": "Feature",
  "properties": {
    "iso:country":"ES",
    "sg:address":"Carr Major, 3",
    "sg:city":"Gualta",
    "sg:orig_category":"Alimentaci\u00d3n General (al Por Menor)",
    "sg:phone":"+34 972 75 88 85",
    "sg:postcode":"17257",
    "sg:province":"Girona",
    "wof:name":"Muriscot Llinas David",
    "wof:placetype":"venue"
},
  "geometry": {"coordinates":[3.1036310196,42.029914856],"type":"Point"}
}