{
  "type": "Feature",
  "properties": {
    "addr:full":"Carrer de Joaquim Capell, 12 Mataro Barcelona 08303",
    "addr:housenumber":"12",
    "addr:postcode":"08303",
    "addr:street":"Carrer De Joaquim Capell",
    "iso:country":"ES",
    "sg:address":"Carrer de Joaquim Capell, 12",
    "sg:city":"Mataro",
    "sg:orig_category":"Empresas De Carpinter\u00cda",
    "sg:phone":"+34 937 57 82 77",
    "sg:postcode":"08303",
    "sg:province":"Barcelona",
    "wof:name":"Aluminios Rotamax S.l.",
    "wof:placetype":"venue"
},
  "geometry": {"coordinates":[2.4333405495,41.5398216248],"type":"Point"}
}