{
  "type": "Feature",
  "properties": {
    "iso:country":"ES",
    "sg:address":"Calle de Doctor Grai\u00d1o Del, 4",
    "sg:city":"Aviles",
    "sg:orig_category":"Institutos De Belleza",
    "sg:phone":"+34 985 52 72 23",
    "sg:postcode":"33401",
    "sg:province":"Asturias",
    "sg:website":"www.esencialmediterraneo.com",
    "wof:name":"Fernandez Fernandez Pilar",
    "wof:placetype":"venue"
},
  "geometry": {"coordinates":[-5.9250535965,43.5566825867],"type":"Point"}
}