{
  "type": "Feature",
  "properties": {
    "addr:full":"Rua Galeras (das), 14 Santiago De Compostela La Coru\u00f1a 15705",
    "addr:housenumber":"14",
    "addr:postcode":"15705",
    "addr:street":"Rua Galeras Das;Corun\u0303A",
    "iso:country":"ES",
    "sg:address":"Rua Galeras (das), 14",
    "sg:city":"Santiago De Compostela",
    "sg:orig_category":"Farmacias",
    "sg:phone":"+34 981 58 53 51",
    "sg:postcode":"15705",
    "sg:province":"La Coru\u00f1a",
    "wof:name":"Ginarte Val Maria Inmaculada",
    "wof:placetype":"venue"
},
  "geometry": {"coordinates":[-8.5491228104,42.8810462952],"type":"Point"}
}