{
  "type": "Feature",
  "properties": {
    "iso:country":"ES",
    "sg:address":"Cristo Cedia, 10",
    "sg:city":"Carmona",
    "sg:orig_category":"Empresas De Carpinter\u00cda Met\u00c1lica",
    "sg:phone":"+34 954 14 14 52",
    "sg:postcode":"41410",
    "sg:province":"Sevilla",
    "wof:name":"Aluminios Infantes S.l.",
    "wof:placetype":"venue"
},
  "geometry": {"coordinates":[-5.6037464142,37.4634742737],"type":"Point"}
}