{
  "type": "Feature",
  "properties": {
    "addr:full":"Pg Maritim, 215 Castelldefels Barcelona 08860",
    "addr:housenumber":"215",
    "addr:postcode":"08860",
    "addr:street":"Pg Maritim",
    "iso:country":"ES",
    "sg:address":"Pg Maritim, 215",
    "sg:city":"Castelldefels",
    "sg:orig_category":"Radiocomunicaciones, Telefon\u00cda M\u00d3vil, Radiomensajer\u00cda: Servicios, Comercializaci\u00d3n",
    "sg:phone":"+34 936 45 25 18",
    "sg:postcode":"08860",
    "sg:province":"Barcelona",
    "wof:name":"Organizacion Privada S.l.",
    "wof:placetype":"venue"
},
  "geometry": {"coordinates":[1.9700939655,41.2658653259],"type":"Point"}
}