{
  "type": "Feature",
  "properties": {
    "iso:country":"ES",
    "sg:address":"Avda Jorge Vigon, 29",
    "sg:city":"Logro\u00f1o",
    "sg:orig_category":"Arquitectos",
    "sg:phone":"+34 941 25 74 13",
    "sg:postcode":"26003",
    "sg:province":"La Rioja",
    "wof:name":"Sabras Farias Julio",
    "wof:placetype":"venue"
},
  "geometry": {"coordinates":[-2.4412419796,42.4620285034],"type":"Point"}
}