{
  "type": "Feature",
  "properties": {
    "addr:full":"Carrer de Gomis, 17 Barcelona Barcelona 08023",
    "addr:housenumber":"17",
    "addr:postcode":"08023",
    "addr:street":"Carrer De Gomis",
    "iso:country":"ES",
    "sg:address":"Carrer de Gomis, 17",
    "sg:city":"Barcelona",
    "sg:orig_category":"Empresas De Carpinter\u00cda De Madera",
    "sg:phone":"+34 934 17 60 90",
    "sg:postcode":"08023",
    "sg:province":"Barcelona",
    "wof:name":"Sanchez Vila Enrique",
    "wof:placetype":"venue"
},
  "geometry": {"coordinates":[2.1415770054,41.4120750427],"type":"Point"}
}