{
  "type": "Feature",
  "properties": {
    "iso:country":"ES",
    "sg:address":"Calle de Alegria, 7",
    "sg:city":"Albacete",
    "sg:orig_category":"Oxigenoterapia",
    "sg:phone":"+34 967 50 55 72",
    "sg:postcode":"02005",
    "sg:province":"Albacete",
    "wof:name":"Oexite S.l.",
    "wof:placetype":"venue"
},
  "geometry": {"coordinates":[-1.8651752472,38.997882843],"type":"Point"}
}