{
  "type": "Feature",
  "properties": {
    "addr:full":"Calle de Arrabal, S/n Moron Almazan Soria 42223",
    "addr:housenumber":"s",
    "addr:postcode":"42223",
    "addr:street":"Calle De Arrabal;/ N",
    "iso:country":"ES",
    "sg:address":"Calle de Arrabal, S/n",
    "sg:city":"Moron Almazan",
    "sg:orig_category":"Cr\u00cda De Animales",
    "sg:phone":"+34 975 30 60 83",
    "sg:postcode":"42223",
    "sg:province":"Soria",
    "wof:name":"Rega\u00f1o Jimenez Santos",
    "wof:placetype":"venue"
},
  "geometry": {"coordinates":[-2.4129962921,41.4130935669],"type":"Point"}
}