{
  "type": "Feature",
  "properties": {
    "iso:country":"ES",
    "sg:address":"Calle de Honesto Batalon, 14",
    "sg:city":"Gijon",
    "sg:orig_category":"Artes Gr\u00c1ficas, Artes Pl\u00c1sticas (curso)",
    "sg:phone":"+34 985 34 76 19",
    "sg:postcode":"33201",
    "sg:province":"Asturias",
    "wof:name":"Litograficas Artenorte S.l.",
    "wof:placetype":"venue"
},
  "geometry": {"coordinates":[-5.6647529602,43.5478172302],"type":"Point"}
}