{
  "type": "Feature",
  "properties": {
    "iso:country":"ES",
    "sg:address":"Calle de San Luis, 136",
    "sg:city":"Sevilla",
    "sg:orig_category":"Estancos",
    "sg:phone":"+34 954 37 02 49",
    "sg:postcode":"41003",
    "sg:province":"Sevilla",
    "wof:name":"Castro Benitez Juan De",
    "wof:placetype":"venue"
},
  "geometry": {"coordinates":[-5.9886488914,37.4006004333],"type":"Point"}
}