{
  "type": "Feature",
  "properties": {
    "iso:country":"ES",
    "sg:address":"Calle de Lucientes, 21",
    "sg:city":"Malaga",
    "sg:orig_category":"Electricidad (montaje, Ensamblaje De Componentes)",
    "sg:phone":"+34 952 31 84 89",
    "sg:postcode":"29006",
    "sg:province":"M\u00e1laga",
    "wof:name":"Sanchez Meneses Francisco Javier",
    "wof:placetype":"venue"
},
  "geometry": {"coordinates":[-4.4377827644,36.7133712769],"type":"Point"}
}