{
  "type": "Feature",
  "properties": {
    "addr:full":"Carrer de Pompeu Fabra, 60 S. Quirze Valles Barcelona 08192",
    "addr:housenumber":"60",
    "addr:postcode":"08192",
    "addr:street":"Carrer De Pompeu Fabra",
    "iso:country":"ES",
    "sg:address":"Carrer de Pompeu Fabra, 60",
    "sg:city":"S. Quirze Valles",
    "sg:orig_category":"Alimentaci\u00d3n Animal (fabricaci\u00d3n, Al Por Mayor)",
    "sg:phone":"+34 937 21 04 13",
    "sg:postcode":"08192",
    "sg:province":"Barcelona",
    "wof:name":"Rabell Pujol Enrique",
    "wof:placetype":"venue"
},
  "geometry": {"coordinates":[2.0792798996,41.5335273743],"type":"Point"}
}