{
  "type": "Feature",
  "properties": {
    "addr:full":"Calle de Rodrigo Rebolledo, 3 Zaragoza Zaragoza 50002",
    "addr:housenumber":"3",
    "addr:postcode":"50002",
    "addr:street":"Calle De Rodrigo Rebolledo",
    "iso:country":"ES",
    "sg:address":"Calle de Rodrigo Rebolledo, 3",
    "sg:city":"Zaragoza",
    "sg:orig_category":"Comercio De Piezas De Recambio Y De Accesorios De Veh\u00cdculos, Veh\u00cdculos Industriales",
    "sg:phone":"+34 976 41 89 98",
    "sg:postcode":"50002",
    "sg:province":"Zaragoza",
    "wof:name":"Recambios Las Fuentes S.l.",
    "wof:placetype":"venue"
},
  "geometry": {"coordinates":[-0.8658109903,41.6464424133],"type":"Point"}
}