{
  "type": "Feature",
  "properties": {
    "addr:full":"Calle de Viriato, 29 Madrid Madrid 28010",
    "addr:housenumber":"29",
    "addr:postcode":"madrid;28010",
    "addr:street":"Calle De Viriato",
    "iso:country":"ES",
    "sg:address":"Calle de Viriato, 29",
    "sg:city":"Madrid",
    "sg:orig_category":"Bares, Piano",
    "sg:phone":"+34 915 94 47 78",
    "sg:postcode":"28010",
    "sg:province":"Madrid",
    "wof:name":"Asi Sea S.l.",
    "wof:placetype":"venue"
},
  "geometry": {"coordinates":[-3.7011516094,40.4359016418],"type":"Point"}
}