{
  "type": "Feature",
  "properties": {
    "addr:full":"Rua Principe, 22 Vigo Pontevedra 36202",
    "addr:housenumber":"22",
    "addr:postcode":"36202",
    "addr:street":"Rua Principe",
    "iso:country":"ES",
    "sg:address":"Rua Principe, 22",
    "sg:city":"Vigo",
    "sg:orig_category":"Reciclaje, Tratamiento De Tejidos",
    "sg:phone":"+34 986 43 28 44",
    "sg:postcode":"36202",
    "sg:province":"Pontevedra",
    "wof:name":"Telpes S.l.",
    "wof:placetype":"venue"
},
  "geometry": {"coordinates":[-8.7233476639,42.236946106],"type":"Point"}
}