{
  "type": "Feature",
  "properties": {
    "addr:full":"Avgd Marti Pujol, 223 Badalona Barcelona 08912",
    "addr:housenumber":"223",
    "addr:postcode":"08912",
    "addr:street":"Pujol",
    "iso:country":"ES",
    "sg:address":"Avgd Marti Pujol, 223",
    "sg:city":"Badalona",
    "sg:orig_category":"Estancos",
    "sg:phone":"+34 933 89 59 62",
    "sg:postcode":"08912",
    "sg:province":"Barcelona",
    "wof:name":"Pallas Garcia Jose",
    "wof:placetype":"venue"
},
  "geometry": {"coordinates":[2.2443730831,41.4513053894],"type":"Point"}
}