{
  "type": "Feature",
  "properties": {
    "addr:full":"Calle de Guzman El Bueno, 38 Madrid Madrid 28015",
    "addr:housenumber":"38",
    "addr:postcode":"madrid;28015",
    "addr:street":"Calle De Guzman El Bueno",
    "iso:country":"ES",
    "sg:address":"Calle de Guzman El Bueno, 38",
    "sg:city":"Madrid",
    "sg:orig_category":"Mec\u00c1nico Del Autom\u00d3vil",
    "sg:phone":"+34 915 43 96 62",
    "sg:postcode":"28015",
    "sg:province":"Madrid",
    "wof:name":"Machin Perdices Avelino",
    "wof:placetype":"venue"
},
  "geometry": {"coordinates":[-3.713078022,40.4346618652],"type":"Point"}
}