{
  "type": "Feature",
  "properties": {
    "addr:full":"Carrer de Avellaners, 12 Casc Urba Barcelona 08328",
    "addr:housenumber":"12;urba",
    "addr:postcode":"08328",
    "addr:street":"Carrer De Avellaners;Barcelona",
    "iso:country":"ES",
    "sg:address":"Carrer de Avellaners, 12",
    "sg:city":"Casc Urba",
    "sg:orig_category":"Aparatos E Instalaci\u00d3n De Regad\u00cdos",
    "sg:phone":"+34 935 40 82 59",
    "sg:postcode":"08328",
    "sg:province":"Barcelona",
    "wof:name":"Comercial De Productos Especializados Pa",
    "wof:placetype":"venue"
},
  "geometry": {"coordinates":[2.2950890064,41.491191864],"type":"Point"}
}