{
  "type": "Feature",
  "properties": {
    "iso:country":"ES",
    "sg:address":"Avgd Garrigues, 13",
    "sg:city":"Lleida",
    "sg:orig_category":"\u00d3pticos Optometristas (al Por Menor)",
    "sg:phone":"+34 973 21 64 42",
    "sg:postcode":"25001",
    "sg:province":"Lleida",
    "wof:name":"Xavier Vivas S.l.",
    "wof:placetype":"venue"
},
  "geometry": {"coordinates":[0.6319329143,41.6117782593],"type":"Point"}
}