{
  "type": "Feature",
  "properties": {
    "iso:country":"ES",
    "sg:address":"Calle de Cristobal Colon, 6",
    "sg:city":"Sanlucar Mayor",
    "sg:orig_category":"Restaurantes",
    "sg:phone":"+34 955 70 22 59",
    "sg:postcode":"41800",
    "sg:province":"Sevilla",
    "wof:name":"Pasaje Limones S.l.",
    "wof:placetype":"venue"
},
  "geometry": {"coordinates":[-6.2016324997,37.3878669739],"type":"Point"}
}