{
  "type": "Feature",
  "properties": {
    "addr:full":"Calle de Rey Pastor, 12 Logro\u00f1o La Rioja 26005",
    "addr:housenumber":"12",
    "addr:postcode":"26005",
    "addr:street":"Calle De Rey Pastor;Rioja",
    "iso:country":"ES",
    "sg:address":"Calle de Rey Pastor, 12",
    "sg:city":"Logro\u00f1o",
    "sg:orig_category":"Electrodom\u00c9sticos (al Por Menor)",
    "sg:phone":"+34 941 20 04 29",
    "sg:postcode":"26005",
    "sg:province":"La Rioja",
    "wof:name":"Hernandez Gomez Felicidad",
    "wof:placetype":"venue"
},
  "geometry": {"coordinates":[-2.456592083,42.4635734558],"type":"Point"}
}