{
  "type": "Feature",
  "properties": {
    "addr:full":"Carr Pau Casals, 10 Pla Parcial Platja Alicante 03580",
    "addr:housenumber":"10",
    "addr:postcode":"03580",
    "addr:street":"Carr Pau Casals",
    "iso:country":"ES",
    "sg:address":"Carr Pau Casals, 10",
    "sg:city":"Pla Parcial Platja",
    "sg:orig_category":"Agencias De Viajes",
    "sg:phone":"+34 966 86 41 91",
    "sg:postcode":"03580",
    "sg:province":"Alicante",
    "wof:name":"Haga Nor Reiser Espa\u00f1a S.l.",
    "wof:placetype":"venue"
},
  "geometry": {"coordinates":[-0.1017019972,38.5834732056],"type":"Point"}
}