{
  "type": "Feature",
  "properties": {
    "addr:full":"Avda Portugal, 6 Martina Le\u00f3n 24400",
    "addr:housenumber":"6",
    "addr:postcode":"24400",
    "addr:street":"Avda Portugal;Leo\u0301N",
    "iso:country":"ES",
    "sg:address":"Avda Portugal, 6",
    "sg:city":"Martina",
    "sg:orig_category":"Farmacias",
    "sg:phone":"+34 987 41 20 94",
    "sg:postcode":"24400",
    "sg:province":"Le\u00f3n",
    "wof:name":"Hernando Gonzalez Juana Maria",
    "wof:placetype":"venue"
},
  "geometry": {"coordinates":[-5.5717520714,42.5998764038],"type":"Point"}
}