{
  "type": "Feature",
  "properties": {
    "iso:country":"ES",
    "sg:address":"C/ Torrent, 28",
    "sg:city":"Cerdanyola Valles",
    "sg:orig_category":"Mec\u00c1nico Del Autom\u00d3vil",
    "sg:phone":"+34 936 92 24 31",
    "sg:postcode":"08290",
    "sg:province":"Barcelona",
    "wof:name":"Martos Medina Antonio",
    "wof:placetype":"venue"
},
  "geometry": {"coordinates":[2.1379480362,41.493106842],"type":"Point"}
}