{
  "type": "Feature",
  "properties": {
    "iso:country":"ES",
    "sg:address":"Calle de Fresadores, 3",
    "sg:city":"Alcamar",
    "sg:orig_category":"Carpinteros",
    "sg:phone":"+34 918 85 77 01",
    "sg:postcode":"28816",
    "sg:province":"Madrid",
    "wof:name":"Decomar-iroko S.l.",
    "wof:placetype":"venue"
},
  "geometry": {"coordinates":[-3.3876540661,40.5379562378],"type":"Point"}
}