{
  "type": "Feature",
  "properties": {
    "addr:full":"Carrer de Pla De Matabous, 36 Mas Rampinyo Barcelona 08110",
    "addr:housenumber":"36",
    "addr:postcode":"08110",
    "addr:street":"Carrer De Pla De Matabous",
    "iso:country":"ES",
    "sg:address":"Carrer de Pla De Matabous, 36",
    "sg:city":"Mas Rampinyo",
    "sg:orig_category":"Charcuter\u00cdas (al Por Mayor)",
    "sg:phone":"+34 935 64 14 78",
    "sg:postcode":"08110",
    "sg:province":"Barcelona",
    "wof:name":"Charcuteria Hispano-alemana S.l.",
    "wof:placetype":"venue"
},
  "geometry": {"coordinates":[2.1859691143,41.4872894287],"type":"Point"}
}