{
  "type": "Feature",
  "properties": {
    "addr:full":"Carrer de Aribau, 59 Barcelona Barcelona 08011",
    "addr:housenumber":"59",
    "addr:postcode":"08011",
    "addr:street":"Carrer De Aribau",
    "iso:country":"ES",
    "sg:address":"Carrer de Aribau, 59",
    "sg:city":"Barcelona",
    "sg:orig_category":"Muebles Y Accesorios Para Cocinas Y Cuartos De Ba\u00d1o (al Por Menor)",
    "sg:phone":"+34 934 53 59 65",
    "sg:postcode":"08011",
    "sg:province":"Barcelona",
    "wof:name":"Carbonell Hernando Elvira",
    "wof:placetype":"venue"
},
  "geometry": {"coordinates":[2.158921957,41.3885498047],"type":"Point"}
}