{
  "type": "Feature",
  "properties": {
    "addr:full":"Calle de Monte, 12 Villarta S. Juan Ciudad Real 13210",
    "addr:housenumber":"12",
    "addr:postcode":"13210",
    "addr:street":"Calle De Monte;Villarta S. Juan Ciudad Real",
    "iso:country":"ES",
    "sg:address":"Calle de Monte, 12",
    "sg:city":"Villarta S. Juan",
    "sg:orig_category":"Empresas De Pintura Y Revestimientos",
    "sg:phone":"+34 926 64 05 45",
    "sg:postcode":"13210",
    "sg:province":"Ciudad Real",
    "wof:name":"Garcia Carpintero Fernando",
    "wof:placetype":"venue"
},
  "geometry": {"coordinates":[-3.4261879921,39.2374305725],"type":"Point"}
}