{
  "type": "Feature",
  "properties": {
    "iso:country":"ES",
    "sg:address":"Rond Monte (del), 22",
    "sg:city":"Valfonda De Santa Ana",
    "sg:orig_category":"Electricidad: Instaladores",
    "sg:phone":"+34 974 39 03 23",
    "sg:postcode":"22255",
    "sg:province":"Huesca",
    "wof:name":"Electricidad Acin S.cv.",
    "wof:placetype":"venue"
},
  "geometry": {"coordinates":[-0.4344089925,41.9588890076],"type":"Point"}
}