{
  "type": "Feature",
  "properties": {
    "iso:country":"ES",
    "sg:address":"Carrer de Alaba, 61",
    "sg:city":"Barcelona",
    "sg:orig_category":"Dorados, Plater\u00cda (orfebrer\u00cda)",
    "sg:phone":"+34 934 85 34 26",
    "sg:postcode":"08005",
    "sg:province":"Barcelona",
    "sg:website":"www.rocacoll.com",
    "wof:name":"Roca Coll S.a.",
    "wof:placetype":"venue"
},
  "geometry": {"coordinates":[2.1949501038,41.3957099915],"type":"Point"}
}