{
  "type": "Feature",
  "properties": {
    "iso:country":"ES",
    "sg:address":"Carrer de Mossen Salvador Ritort I Faus, 1",
    "sg:city":"Tarragona",
    "sg:orig_category":"Arquitectos",
    "sg:phone":"+34 977 22 94 14",
    "sg:postcode":"43002",
    "sg:province":"Tarragona",
    "wof:name":"Navarro Blanch Francisco",
    "wof:placetype":"venue"
},
  "geometry": {"coordinates":[1.2511240244,41.1201667786],"type":"Point"}
}