{
  "type": "Feature",
  "properties": {
    "addr:full":"Calle de Gran Via, 80 Madrid Madrid 28013",
    "addr:housenumber":"80",
    "addr:postcode":"madrid;28013",
    "addr:street":"Calle De Gran Via",
    "iso:country":"ES",
    "sg:address":"Calle de Gran Via, 80",
    "sg:city":"Madrid",
    "sg:orig_category":"Psic\u00d3logos",
    "sg:phone":"+34 915 47 51 17",
    "sg:postcode":"28013",
    "sg:province":"Madrid",
    "sg:website":"www.psicogranvia.com",
    "wof:name":"Gomez Martinez Carmen",
    "wof:placetype":"venue"
},
  "geometry": {"coordinates":[-3.710637331,40.4232139587],"type":"Point"}
}