{
  "type": "Feature",
  "properties": {
    "iso:country":"ES",
    "sg:address":"Pg Zona Franca, 177",
    "sg:city":"Barcelona",
    "sg:orig_category":"Frutas, Legumbres Frescas Y Tempranas (al Por Menor)",
    "sg:phone":"+34 933 32 57 97",
    "sg:postcode":"08038",
    "sg:province":"Barcelona",
    "wof:name":"Actifot Zf S.l.",
    "wof:placetype":"venue"
},
  "geometry": {"coordinates":[2.1387169361,41.3604164124],"type":"Point"}
}