{
  "type": "Feature",
  "properties": {
    "iso:country":"ES",
    "sg:address":"Avda Portugal, 100",
    "sg:city":"Armunia",
    "sg:orig_category":"Flores Y Plantas Naturales (al Por Mayor)",
    "sg:phone":"+34 987 80 76 56",
    "sg:postcode":"24009",
    "sg:province":"Le\u00f3n",
    "wof:name":"Pastor De Leon Miguel Angel",
    "wof:placetype":"venue"
},
  "geometry": {"coordinates":[-5.5935587883,42.5842895508],"type":"Point"}
}