{
  "type": "Feature",
  "properties": {
    "addr:full":"Av Diagonal, 505 Barcelona Barcelona 08029",
    "addr:housenumber":"505",
    "addr:postcode":"08029",
    "addr:street":"Av Diagonal",
    "iso:country":"ES",
    "sg:address":"Av Diagonal, 505",
    "sg:city":"Barcelona",
    "sg:orig_category":"Telas Para Tapizar, Cortinas, Pasamaner\u00cda (fabricaci\u00d3n, Al Por Mayor)",
    "sg:phone":"+34 933 63 16 55",
    "sg:postcode":"08029",
    "sg:province":"Barcelona",
    "sg:website":"www.lienzogazules.com",
    "wof:name":"Dimenciorart S.l.",
    "wof:placetype":"venue"
},
  "geometry": {"coordinates":[2.1417849064,41.3915939331],"type":"Point"}
}