{
  "type": "Feature",
  "properties": {
    "iso:country":"ES",
    "sg:address":"Pase Diego Carro, 10",
    "sg:city":"Nueva-carteya",
    "sg:orig_category":"Transporte En General",
    "sg:phone":"+34 957 67 85 65",
    "sg:postcode":"14857",
    "sg:province":"C\u00f3rdoba",
    "wof:name":"Distribuciones Don Olivo S.l",
    "wof:placetype":"venue"
},
  "geometry": {"coordinates":[-4.4690508842,37.587059021],"type":"Point"}
}