{
  "type": "Feature",
  "properties": {
    "addr:full":"Av Catalunya, 37 Tarragona Tarragona 43002",
    "addr:housenumber":"37",
    "addr:postcode":"43002",
    "addr:street":"Av Catalunya",
    "iso:country":"ES",
    "sg:address":"Av Catalunya, 37",
    "sg:city":"Tarragona",
    "sg:orig_category":"Arreglo, Reparaci\u00d3n, Piezas Sueltas De Televisi\u00d3n, V\u00cddeo, Hi",
    "sg:phone":"+34 977 23 10 12",
    "sg:postcode":"43002",
    "sg:province":"Tarragona",
    "wof:name":"Servi Repar S.l.",
    "wof:placetype":"venue"
},
  "geometry": {"coordinates":[1.2481820583,41.1230278015],"type":"Point"}
}