{
  "type": "Feature",
  "properties": {
    "iso:country":"ES",
    "sg:address":"Carrer de Sant Isidre (de), 79",
    "sg:city":"S. Carles Rapita",
    "sg:orig_category":"Institutos De Belleza",
    "sg:phone":"+34 977 74 48 90",
    "sg:postcode":"43540",
    "sg:province":"Tarragona",
    "sg:website":"www.llongueras.com",
    "wof:name":"Barbera Figols Juan Jose",
    "wof:placetype":"venue"
},
  "geometry": {"coordinates":[0.5889449716,40.6168708801],"type":"Point"}
}