{
  "type": "Feature",
  "properties": {
    "iso:country":"ES",
    "sg:address":"Calle de Marques De Linares, 16",
    "sg:city":"Linares",
    "sg:orig_category":"\u00c1rboles Frutales",
    "sg:phone":"+34 953 69 11 90",
    "sg:postcode":"23700",
    "sg:province":"Ja\u00e9n",
    "wof:name":"Agricola De Castulo S.l.",
    "wof:placetype":"venue"
},
  "geometry": {"coordinates":[-3.6320457458,38.0934410095],"type":"Point"}
}