{
  "type": "Feature",
  "properties": {
    "addr:full":"Jaime, 9 Lucena C\u00f3rdoba 14900",
    "addr:housenumber":"9",
    "addr:postcode":"14900",
    "addr:street":"Jaime",
    "iso:country":"ES",
    "sg:address":"Jaime, 9",
    "sg:city":"Lucena",
    "sg:orig_category":"Abogados",
    "sg:phone":"+34 957 51 61 81",
    "sg:postcode":"14900",
    "sg:province":"C\u00f3rdoba",
    "wof:name":"Tetuan 53 S.l.",
    "wof:placetype":"venue"
},
  "geometry": {"coordinates":[-4.4871520996,37.4082756042],"type":"Point"}
}