{
  "type": "Feature",
  "properties": {
    "addr:full":"Cno De Las Erillas, S/n San J. Aznalfarache Sevilla 41920",
    "addr:housenumber":"s / n",
    "addr:postcode":"41920",
    "addr:street":"Cno De Las Erillas",
    "iso:country":"ES",
    "sg:address":"Cno De Las Erillas, S/n",
    "sg:city":"San J. Aznalfarache",
    "sg:orig_category":"Promotores Constructores",
    "sg:phone":"+34 954 27 60 37",
    "sg:postcode":"41920",
    "sg:province":"Sevilla",
    "wof:name":"Inversores Varios S.a.",
    "wof:placetype":"venue"
},
  "geometry": {"coordinates":[-6.0277690887,37.359916687],"type":"Point"}
}