{
  "type": "Feature",
  "properties": {
    "iso:country":"ES",
    "sg:address":"Calle de Huertos, 11",
    "sg:city":"Sagunt",
    "sg:orig_category":"Inmobiliaria (agencias)",
    "sg:phone":"+34 962 66 01 39",
    "sg:postcode":"46500",
    "sg:province":"Valencia",
    "wof:name":"Moros Zorio Carlos",
    "wof:placetype":"venue"
},
  "geometry": {"coordinates":[-0.2783089876,39.6799659729],"type":"Point"}
}