{
  "type": "Feature",
  "properties": {
    "addr:full":"Pase Direccion, 164 Madrid Madrid 28039",
    "addr:housenumber":"164",
    "addr:postcode":"madrid;28039",
    "iso:country":"ES",
    "sg:address":"Pase Direccion, 164",
    "sg:city":"Madrid",
    "sg:orig_category":"Empresas De Pintura Y Revestimientos",
    "sg:phone":"+34 914 50 38 66",
    "sg:postcode":"28039",
    "sg:province":"Madrid",
    "wof:name":"Aplicacion De Pinturas Holguin S.l.",
    "wof:placetype":"venue"
},
  "geometry": {"coordinates":[-3.705684185,40.4646873474],"type":"Point"}
}