{
  "type": "Feature",
  "properties": {
    "iso:country":"ES",
    "sg:address":"Pas Quint, 2",
    "sg:city":"Palma",
    "sg:orig_category":"Bisuter\u00cda, Joyer\u00cda, Relojer\u00cda (al Por Menor)",
    "sg:phone":"+34 971 71 41 78",
    "sg:postcode":"07001",
    "sg:province":"Islas Baleares",
    "wof:name":"Bonet Pla Francisco",
    "wof:placetype":"venue"
},
  "geometry": {"coordinates":[2.6488559246,39.5701637268],"type":"Point"}
}