{
  "type": "Feature",
  "properties": {
    "iso:country":"ES",
    "sg:address":"Ctra. General, S/n",
    "sg:city":"Cornellana",
    "sg:orig_category":"Coches Y Camiones (caja De Cambios, Embrague Y Frenos)",
    "sg:phone":"+34 985 83 42 61",
    "sg:postcode":"33850",
    "sg:province":"Asturias",
    "wof:name":"Rio Cortina Jose Angel Del",
    "wof:placetype":"venue"
},
  "geometry": {"coordinates":[-6.3453469276,43.4185028076],"type":"Point"}
}