{
  "type": "Feature",
  "properties": {
    "addr:full":"La Cerrada, 2 Barruelo Santullan Palencia 34820",
    "addr:postcode":"34820",
    "iso:country":"ES",
    "sg:address":"La Cerrada, 2",
    "sg:city":"Barruelo Santullan",
    "sg:orig_category":"Asociaciones, Organismos Culturales Y Socioeducativos",
    "sg:phone":"+34 979 60 72 94",
    "sg:postcode":"34820",
    "sg:province":"Palencia",
    "sg:website":"www.ayuntamiento.barruelo.com",
    "wof:name":"Ayuntamiento De Barruelo De Santullan",
    "wof:placetype":"venue"
},
  "geometry": {"coordinates":[-4.2860245705,42.9058914185],"type":"Point"}
}