{
  "type": "Feature",
  "properties": {
    "iso:country":"ES",
    "sg:address":"Carrer de Tuset, 25",
    "sg:city":"Barcelona",
    "sg:orig_category":"Notarios",
    "sg:phone":"+34 932 41 10 70",
    "sg:postcode":"08006",
    "sg:province":"Barcelona",
    "wof:name":"Sansalvado Chalaux Marc",
    "wof:placetype":"venue"
},
  "geometry": {"coordinates":[2.1508600712,41.3965454102],"type":"Point"}
}