{
  "type": "Feature",
  "properties": {
    "addr:full":"Calle de Rosario, 34 Caspe Zaragoza 50700",
    "addr:housenumber":"34",
    "addr:postcode":"50700",
    "addr:street":"Calle De Rosario",
    "iso:country":"ES",
    "sg:address":"Calle de Rosario, 34",
    "sg:city":"Caspe",
    "sg:orig_category":"Centros De Coordinaci\u00d3n",
    "sg:phone":"+34 976 63 94 75",
    "sg:postcode":"50700",
    "sg:province":"Zaragoza",
    "wof:name":"Cortes Buisan Maria Teresa",
    "wof:placetype":"venue"
},
  "geometry": {"coordinates":[-0.0412789993,41.2379684448],"type":"Point"}
}