{
  "type": "Feature",
  "properties": {
    "iso:country":"ES",
    "sg:address":"Calle de Aragon, 18",
    "sg:city":"Binefar",
    "sg:orig_category":"Electricidad: Instaladores",
    "sg:phone":"+34 974 42 95 03",
    "sg:postcode":"22500",
    "sg:province":"Huesca",
    "wof:name":"Electricidad Herrera S.cv.",
    "wof:placetype":"venue"
},
  "geometry": {"coordinates":[0.2980290055,41.8492965698],"type":"Point"}
}