{
  "type": "Feature",
  "properties": {
    "iso:country":"ES",
    "sg:address":"Avda De Bara\u00f1ain, 2",
    "sg:city":"Iru\u00f1a",
    "sg:orig_category":"Encuadernaci\u00d3n E Impresi\u00d3n De Folletos",
    "sg:phone":"+34 948 25 56 87",
    "sg:postcode":"31011",
    "sg:province":"Navarra",
    "wof:name":"Viana Ruiz Cesar",
    "wof:placetype":"venue"
},
  "geometry": {"coordinates":[-1.6550229788,42.8139457703],"type":"Point"}
}