{
  "type": "Feature",
  "properties": {
    "iso:country":"ES",
    "sg:address":"Calle de Felipe Fernandez Gonzalez, 16",
    "sg:city":"Valverde Vera",
    "sg:orig_category":"Centros Empresariales",
    "sg:phone":"+34 927 56 60 08",
    "sg:postcode":"10490",
    "sg:province":"C\u00e1ceres",
    "wof:name":"Casado Vadillo Angel Luis",
    "wof:placetype":"venue"
},
  "geometry": {"coordinates":[-5.5007991791,40.11926651],"type":"Point"}
}