{
  "type": "Feature",
  "properties": {
    "iso:country":"ES",
    "sg:address":"Calle de Molinos, 39",
    "sg:city":"Villarrobledo",
    "sg:orig_category":"Asesor\u00cda Fiscal Y Jur\u00cddica",
    "sg:phone":"+34 967 14 16 91",
    "sg:postcode":"02600",
    "sg:province":"Albacete",
    "wof:name":"Asesoria Requena S.l.",
    "wof:placetype":"venue"
},
  "geometry": {"coordinates":[-2.5993258953,39.2739982605],"type":"Point"}
}