{
  "type": "Feature",
  "properties": {
    "addr:full":"Calle de Angel Guimera, 21 Valencia Valencia 46008",
    "addr:housenumber":"21",
    "addr:postcode":"46008",
    "addr:street":"Calle De Angel Guimera",
    "iso:country":"ES",
    "sg:address":"Calle de Angel Guimera, 21",
    "sg:city":"Valencia",
    "sg:orig_category":"Inmobiliaria (agencias)",
    "sg:phone":"+34 963 82 00 22",
    "sg:postcode":"46008",
    "sg:province":"Valencia",
    "wof:name":"Torre 4 S.l.",
    "wof:placetype":"venue"
},
  "geometry": {"coordinates":[-0.3864625096,39.4700813293],"type":"Point"}
}