{
  "type": "Feature",
  "properties": {
    "iso:country":"ES",
    "sg:address":"Calle de Triunfo, 1",
    "sg:city":"Donostia-san Sebastian",
    "sg:orig_category":"Abogados",
    "sg:phone":"+34 943 46 09 46",
    "sg:postcode":"20007",
    "sg:province":"Guip\u00f9zcoa",
    "wof:name":"Olaizola Lavaud Gorka",
    "wof:placetype":"venue"
},
  "geometry": {"coordinates":[-1.9853440523,43.3166007996],"type":"Point"}
}