{
  "type": "Feature",
  "properties": {
    "addr:full":"Calle de Doctor Fleming, 1 Caceres C\u00e1ceres 10001",
    "addr:housenumber":"1",
    "addr:postcode":"10001",
    "addr:street":"Calle De Doctor Fleming;Ca\u0301Ceres",
    "iso:country":"ES",
    "sg:address":"Calle de Doctor Fleming, 1",
    "sg:city":"Caceres",
    "sg:orig_category":"Ingenier\u00cda, Centros De Estudios (diversos)",
    "sg:phone":"+34 927 21 08 72",
    "sg:postcode":"10001",
    "sg:province":"C\u00e1ceres",
    "wof:name":"Sebastian De Erice Sanchez-oca\u00f1a Francisco Javier",
    "wof:placetype":"venue"
},
  "geometry": {"coordinates":[-6.3792691231,39.472618103],"type":"Point"}
}