{
  "type": "Feature",
  "properties": {
    "addr:full":"Calle de Real, 40 Navas San Juan Ja\u00e9n 23240",
    "addr:housenumber":"40",
    "addr:postcode":"23240",
    "addr:street":"Calle De Real",
    "iso:country":"ES",
    "sg:address":"Calle de Real, 40",
    "sg:city":"Navas San Juan",
    "sg:orig_category":"Reposter\u00cdas",
    "sg:phone":"+34 953 68 95 08",
    "sg:postcode":"23240",
    "sg:province":"Ja\u00e9n",
    "wof:name":"Sociedad Cooperativa De Consumo Panadera San Isidro Labrador",
    "wof:placetype":"venue"
},
  "geometry": {"coordinates":[-3.3167619705,38.184261322],"type":"Point"}
}