{
  "type": "Feature",
  "properties": {
    "addr:full":"Calle de Pico Chilegua, 7 Madrid Madrid 28031",
    "addr:housenumber":"7",
    "addr:postcode":"madrid;28031",
    "addr:street":"Calle De Pico Chilegua",
    "iso:country":"ES",
    "sg:address":"Calle de Pico Chilegua, 7",
    "sg:city":"Madrid",
    "sg:orig_category":"Molduras, Junquillos, Listones Y Molduras Perforadas",
    "sg:phone":"+34 913 32 75 43",
    "sg:postcode":"28031",
    "sg:province":"Madrid",
    "wof:name":"Martin Gonzalez Carlos",
    "wof:placetype":"venue"
},
  "geometry": {"coordinates":[-3.618268013,40.3729782104],"type":"Point"}
}