{
  "type": "Feature",
  "properties": {
    "iso:country":"ES",
    "sg:address":"Ctra Nacional 601, Km. 0087,9",
    "sg:city":"Tabanera Luenga",
    "sg:orig_category":"Alimentaci\u00d3n General (al Por Mayor)",
    "sg:phone":"+34 921 56 19 25",
    "sg:postcode":"40291",
    "sg:province":"Segovia",
    "wof:name":"Piensos Nanpro S.a.",
    "wof:placetype":"venue"
},
  "geometry": {"coordinates":[-4.1943769455,41.104019165],"type":"Point"}
}