{
  "type": "Feature",
  "properties": {
    "iso:country":"ES",
    "sg:address":"Avda Almunia (la), 19",
    "sg:city":"Monzon",
    "sg:orig_category":"Contenedores (mercanc\u00cdas)",
    "sg:phone":"+34 974 40 24 90",
    "sg:postcode":"22400",
    "sg:province":"Huesca",
    "wof:name":"Hervas Alba Rafael",
    "wof:placetype":"venue"
},
  "geometry": {"coordinates":[0.191960007,41.9176712036],"type":"Point"}
}