{
  "type": "Feature",
  "properties": {
    "addr:full":"Asmesnal, S/n Alfaraz Zamora 49177",
    "addr:postcode":"49177",
    "addr:street":"Asmesnal S / N Alfaraz Zamora",
    "iso:country":"ES",
    "sg:address":"Asmesnal, S/n",
    "sg:city":"Alfaraz",
    "sg:orig_category":"Producci\u00d3n, Venta De Productos De Agricultura Biol\u00d3gica",
    "sg:phone":"+34 980 56 40 48",
    "sg:postcode":"49177",
    "sg:province":"Zamora",
    "wof:name":"Agropecuaria Soguino Y Asmesnal S.a.",
    "wof:placetype":"venue"
},
  "geometry": {"coordinates":[-5.9302778244,41.1969451904],"type":"Point"}
}