{
  "type": "Feature",
  "properties": {
    "addr:full":"Carrer de Onze De Setembre, 15 Piera Barcelona 08784",
    "addr:housenumber":"15",
    "addr:postcode":"08784",
    "addr:street":"Carrer De Onze De Setembre",
    "iso:country":"ES",
    "sg:address":"Carrer de Onze De Setembre, 15",
    "sg:city":"Piera",
    "sg:orig_category":"Materias Pl\u00c1sticas: Productos De Consumo Masivo (fabricaci\u00d3n, Al Por Mayor)",
    "sg:phone":"+34 937 78 84 09",
    "sg:postcode":"08784",
    "sg:province":"Barcelona",
    "wof:name":"Manufacturas Plasticas Balart S.c.p",
    "wof:placetype":"venue"
},
  "geometry": {"coordinates":[1.7513699532,41.5198097229],"type":"Point"}
}