{
  "type": "Feature",
  "properties": {
    "iso:country":"ES",
    "sg:address":"Arragueta Kalea, 3",
    "sg:city":"Eibar",
    "sg:orig_category":"Tejidos (al Por Menor)",
    "sg:phone":"+34 943 20 74 17",
    "sg:postcode":"20600",
    "sg:province":"Guip\u00f9zcoa",
    "wof:name":"Sastreria Azpiri , C.b",
    "wof:placetype":"venue"
},
  "geometry": {"coordinates":[-2.4833750725,43.1838722229],"type":"Point"}
}