{
  "type": "Feature",
  "properties": {
    "iso:country":"ES",
    "sg:address":"Jardines De La Duquesa, 28",
    "sg:city":"Manilva",
    "sg:orig_category":"Centros Empresariales",
    "sg:phone":"+34 952 89 09 98",
    "sg:postcode":"29692",
    "sg:province":"M\u00e1laga",
    "wof:name":"Affordable Housing Worlwide S.l.",
    "wof:placetype":"venue"
},
  "geometry": {"coordinates":[-5.2384138107,36.3421859741],"type":"Point"}
}