{
  "type": "Feature",
  "properties": {
    "iso:country":"ES",
    "sg:address":"Calle de Fray Luis De Leon, 13",
    "sg:city":"Barriada De Santiago",
    "sg:orig_category":"Alimentaci\u00d3n General (al Por Menor)",
    "sg:phone":"+34 968 16 96 82",
    "sg:postcode":"30319",
    "sg:province":"Murcia",
    "wof:name":"Cerezuela Martinez Gines",
    "wof:placetype":"venue"
},
  "geometry": {"coordinates":[-1.0223309994,37.6776695251],"type":"Point"}
}