{
  "type": "Feature",
  "properties": {
    "addr:full":"Calle de Cuevas Del Becerro, S/n Malaga M\u00e1laga 29006",
    "addr:housenumber":"s",
    "addr:postcode":"29006",
    "addr:street":"Calle De Cuevas Del Becerro;/ N;Ma\u0301Laga",
    "iso:country":"ES",
    "sg:address":"Calle de Cuevas Del Becerro, S/n",
    "sg:city":"Malaga",
    "sg:orig_category":"Deportes N\u00c1uticos, Acu\u00c1ticos Y Subacu\u00c1ticos: Art\u00cdculos Y Equipo (al Por Menor)",
    "sg:phone":"+34 952 03 87 14",
    "sg:postcode":"29006",
    "sg:province":"M\u00e1laga",
    "wof:name":"Beluga Nautic Sl",
    "wof:placetype":"venue"
},
  "geometry": {"coordinates":[-4.4648461342,36.7028312683],"type":"Point"}
}