{
  "type": "Feature",
  "properties": {
    "iso:country":"ES",
    "sg:address":"Carrer de Mundana (de), 8",
    "sg:city":"S. Carles Rapita",
    "sg:orig_category":"Muebles Y Accesorios Para Cocinas Y Cuartos De Ba\u00d1o (al Por Menor)",
    "sg:phone":"+34 977 74 47 53",
    "sg:postcode":"43540",
    "sg:province":"Tarragona",
    "wof:name":"Muebles De Cocina Plana Lledo S.l.",
    "wof:placetype":"venue"
},
  "geometry": {"coordinates":[0.593734026,40.6240158081],"type":"Point"}
}