{
  "type": "Feature",
  "properties": {
    "addr:full":"Alam Urquijo, 79 Bilbao Vizcaya 48013",
    "addr:housenumber":"79",
    "addr:postcode":"48013",
    "addr:street":"Alam Urquijo",
    "iso:country":"ES",
    "sg:address":"Alam Urquijo, 79",
    "sg:city":"Bilbao",
    "sg:orig_category":"Ropa De Trabajo Y Profesionales (al Por Menor)",
    "sg:phone":"+34 944 41 20 21",
    "sg:postcode":"48013",
    "sg:province":"Vizcaya",
    "sg:website":"www.bergaralaboral.com",
    "wof:name":"Bergara Vestuario Laboral S.l.",
    "wof:placetype":"venue"
},
  "geometry": {"coordinates":[-2.9464790821,43.2623214722],"type":"Point"}
}