{
  "type": "Feature",
  "properties": {
    "iso:country":"ES",
    "sg:address":"Calle de Lujan Perez, 9",
    "sg:city":"Villa De Moya",
    "sg:orig_category":"Sociedades, Compa\u00d1\u00cdas Aseguradoras",
    "sg:phone":"+34 928 61 07 17",
    "sg:postcode":"35420",
    "sg:province":"Las Palmas",
    "wof:name":"I.c.broker Correduria De Seguros S.l.",
    "wof:placetype":"venue"
},
  "geometry": {"coordinates":[-15.5831546783,28.1080493927],"type":"Point"}
}