{
  "type": "Feature",
  "properties": {
    "iso:country":"ES",
    "sg:address":"Rua Galicia, 23",
    "sg:city":"Noia",
    "sg:orig_category":"Electrodom\u00c9sticos (al Por Menor)",
    "sg:phone":"+34 981 82 24 47",
    "sg:postcode":"15200",
    "sg:province":"La Coru\u00f1a",
    "wof:name":"Electro Roxo S.l.",
    "wof:placetype":"venue"
},
  "geometry": {"coordinates":[-8.8866462708,42.7845954895],"type":"Point"}
}