{
  "type": "Feature",
  "properties": {
    "iso:country":"ES",
    "sg:address":"Calle de Gran Capitan, 6",
    "sg:city":"Melilla",
    "sg:orig_category":"Institutos De Belleza",
    "sg:phone":"+34 952 68 23 07",
    "sg:postcode":"52002",
    "sg:province":"Melilla",
    "wof:name":"Hoyo Mendez Laura",
    "wof:placetype":"venue"
},
  "geometry": {"coordinates":[-2.9430029392,35.2952880859],"type":"Point"}
}