{
  "type": "Feature",
  "properties": {
    "iso:country":"ES",
    "sg:address":"Calle de Eugenio Lopez Doriga, S/n",
    "sg:city":"Malia\u00d1o",
    "sg:orig_category":"Montaje (empresas De)",
    "sg:phone":"+34 942 33 79 31",
    "sg:postcode":"39600",
    "sg:province":"Cantabria",
    "wof:name":"Sertimon Cantabrico S.l.",
    "wof:placetype":"venue"
},
  "geometry": {"coordinates":[-3.8314139843,43.4184341431],"type":"Point"}
}