{
  "type": "Feature",
  "properties": {
    "iso:country":"ES",
    "sg:address":"Calle de Azalea, 28",
    "sg:city":"Arroyo De La Miel-benalmadena Costa",
    "sg:orig_category":"Inmobiliaria (agencias)",
    "sg:phone":"+34 952 57 51 57",
    "sg:postcode":"29631",
    "sg:province":"M\u00e1laga",
    "wof:name":"Guillamundegui  Bernardo Alberto",
    "wof:placetype":"venue"
},
  "geometry": {"coordinates":[-4.5520730019,36.5981254578],"type":"Point"}
}