{
  "type": "Feature",
  "properties": {
    "addr:full":"Calle de Cazalilla, 40 Jaen Ja\u00e9n 23009",
    "addr:housenumber":"40;jae\u0301n",
    "addr:postcode":"23009",
    "addr:street":"Calle De Cazalilla",
    "iso:country":"ES",
    "sg:address":"Calle de Cazalilla, 40",
    "sg:city":"Jaen",
    "sg:orig_category":"Agencias Y Agentes Comerciales, Representantes",
    "sg:phone":"+34 953 24 99 94",
    "sg:postcode":"23009",
    "sg:province":"Ja\u00e9n",
    "wof:name":"Hueso Perez Antonio",
    "wof:placetype":"venue"
},
  "geometry": {"coordinates":[-3.7873084545,37.7963867188],"type":"Point"}
}