{
  "type": "Feature",
  "properties": {
    "iso:country":"ES",
    "sg:address":"Ctra Villamediana, Km. 0004,0",
    "sg:city":"Murillo De Rio Leza",
    "sg:orig_category":"Producci\u00d3n De Champi\u00d1ones",
    "sg:phone":"+34 941 74 01 04",
    "sg:postcode":"26143",
    "sg:province":"La Rioja",
    "wof:name":"Tejada Espinosa S.l",
    "wof:placetype":"venue"
},
  "geometry": {"coordinates":[-2.3255090714,42.401058197],"type":"Point"}
}