{
  "type": "Feature",
  "properties": {
    "addr:full":"Volta 6, 190 S'horta Islas Baleares 07669",
    "addr:housenumber":"6",
    "addr:postcode":"190;07669",
    "addr:street":"Volta",
    "iso:country":"ES",
    "sg:address":"Volta 6, 190",
    "sg:city":"S'horta",
    "sg:orig_category":"Instalaci\u00d3n, Reparaci\u00d3n De Calefacci\u00d3n El\u00c9ctrica",
    "sg:phone":"+34 971 83 74 97",
    "sg:postcode":"07669",
    "sg:province":"Islas Baleares",
    "wof:name":"Dataread 2000 S.l.",
    "wof:placetype":"venue"
},
  "geometry": {"coordinates":[2.9117100239,39.6136398315],"type":"Point"}
}