{
  "type": "Feature",
  "properties": {
    "addr:full":"Calle de Hermanos Salas, 2 Corrales Cantabria 39400",
    "addr:housenumber":"2",
    "addr:postcode":"39400",
    "addr:street":"Calle De Hermanos Salas",
    "iso:country":"ES",
    "sg:address":"Calle de Hermanos Salas, 2",
    "sg:city":"Corrales",
    "sg:orig_category":"Mercer\u00cda, Lencer\u00cda (al Por Menor)",
    "sg:phone":"+34 942 83 11 87",
    "sg:postcode":"39400",
    "sg:province":"Cantabria",
    "wof:name":"Aguilar Del Rio Soledad",
    "wof:placetype":"venue"
},
  "geometry": {"coordinates":[-4.0672602654,43.2597808838],"type":"Point"}
}