{
  "type": "Feature",
  "properties": {
    "addr:full":"Calle de Real, 2 Berlanga Duero Soria 42360",
    "addr:housenumber":"2",
    "addr:postcode":"42360",
    "addr:street":"Calle De Real",
    "iso:country":"ES",
    "sg:address":"Calle de Real, 2",
    "sg:city":"Berlanga Duero",
    "sg:orig_category":"Ense\u00d1anza, Formaci\u00d3n Profesional: Aprendizaje",
    "sg:phone":"+34 975 34 30 31",
    "sg:postcode":"42360",
    "sg:province":"Soria",
    "wof:name":"Delegacion Territorial De Soria",
    "wof:placetype":"venue"
},
  "geometry": {"coordinates":[-2.860929966,41.4661560059],"type":"Point"}
}