{
  "type": "Feature",
  "properties": {
    "addr:full":"Calle de Santa Clara, 2 Jaen Ja\u00e9n 23004",
    "addr:housenumber":"2;jae\u0301n",
    "addr:postcode":"23004",
    "addr:street":"Calle De Santa Clara",
    "iso:country":"ES",
    "sg:address":"Calle de Santa Clara, 2",
    "sg:city":"Jaen",
    "sg:orig_category":"Encuadernaci\u00d3n E Impresi\u00d3n De Folletos",
    "sg:phone":"+34 953 23 88 18",
    "sg:postcode":"23004",
    "sg:province":"Ja\u00e9n",
    "wof:name":"Hernandez Peragon Rafael",
    "wof:placetype":"venue"
},
  "geometry": {"coordinates":[-3.7918429375,37.7699508667],"type":"Point"}
}