{
  "type": "Feature",
  "properties": {
    "iso:country":"ES",
    "sg:address":"C/ Alfons Xii, 21",
    "sg:city":"Banyoles",
    "sg:orig_category":"Papeler\u00cdas, Librer\u00cdas",
    "sg:phone":"+34 972 57 49 14",
    "sg:postcode":"17820",
    "sg:province":"Girona",
    "wof:name":"Banal Llaho Jordi",
    "wof:placetype":"venue"
},
  "geometry": {"coordinates":[2.7642509937,42.1173629761],"type":"Point"}
}