{
  "type": "Feature",
  "properties": {
    "iso:country":"ES",
    "sg:address":"Calle de Herrero, 33",
    "sg:city":"Castellon",
    "sg:orig_category":"Agencias De Trabajo Temporal",
    "sg:phone":"+34 964 24 74 40",
    "sg:postcode":"12005",
    "sg:province":"Castell\u00f3n",
    "wof:name":"Seleccion Laboral De Castellon Ett",
    "wof:placetype":"venue"
},
  "geometry": {"coordinates":[-0.0402989984,39.980178833],"type":"Point"}
}