{
  "type": "Feature",
  "properties": {
    "addr:full":"Calle de San Agustin, 46 Campillos M\u00e1laga 29320",
    "addr:housenumber":"46",
    "addr:postcode":"29320",
    "addr:street":"Calle De San Agustin",
    "iso:country":"ES",
    "sg:address":"Calle de San Agustin, 46",
    "sg:city":"Campillos",
    "sg:orig_category":"Carnicer\u00cdas, Carnicer\u00cdas",
    "sg:phone":"+34 952 72 43 85",
    "sg:postcode":"29320",
    "sg:province":"M\u00e1laga",
    "wof:name":"Aranda Conejo Rafael",
    "wof:placetype":"venue"
},
  "geometry": {"coordinates":[-4.8728094101,37.047492981],"type":"Point"}
}