{
  "type": "Feature",
  "properties": {
    "iso:country":"ES",
    "sg:address":"Ctra Sta Creu Calafell-barcelona, Km. 0056,0",
    "sg:city":"Segur Calafell",
    "sg:orig_category":"Cerrajer\u00cda, Ferrallista",
    "sg:phone":"+34 977 15 01 84",
    "sg:postcode":"43882",
    "sg:province":"Tarragona",
    "wof:name":"Bargas Fabregas Agustin De",
    "wof:placetype":"venue"
},
  "geometry": {"coordinates":[1.6017500162,41.1933441162],"type":"Point"}
}