{
  "type": "Feature",
  "properties": {
    "addr:full":"Avda Republica Argentina, 33 Sada A Coru\u00f1a 15160",
    "addr:housenumber":"33",
    "addr:postcode":"15160",
    "addr:street":"Avda Republica Argentina",
    "iso:country":"ES",
    "sg:address":"Avda Republica Argentina, 33",
    "sg:city":"Sada",
    "sg:orig_category":"Inform\u00c1tica, Ofim\u00c1tica (estudios, Asesor\u00cda, Ingenier\u00cda, Formaci\u00d3n)",
    "sg:phone":"+34 981 62 40 28",
    "sg:postcode":"15160",
    "sg:province":"A Coru\u00f1a",
    "wof:name":"System Sada S.l.",
    "wof:placetype":"venue"
},
  "geometry": {"coordinates":[-8.2522201538,43.3480644226],"type":"Point"}
}