{
  "type": "Feature",
  "properties": {
    "addr:full":"Calle de Antonio Garcia Moreno, S/n Camu\u00f1as Toledo 45720",
    "addr:housenumber":"s",
    "addr:postcode":"45720",
    "addr:street":"Calle De Antonio Garcia Moreno;/ N Camun\u0303As",
    "iso:country":"ES",
    "sg:address":"Calle de Antonio Garcia Moreno, S/n",
    "sg:city":"Camu\u00f1as",
    "sg:orig_category":"Producci\u00d3n De Huevos",
    "sg:phone":"+34 925 47 02 45",
    "sg:postcode":"45720",
    "sg:province":"Toledo",
    "wof:name":"Huevos Romero S.l.",
    "wof:placetype":"venue"
},
  "geometry": {"coordinates":[-3.4564647675,39.4305152893],"type":"Point"}
}