{
  "type": "Feature",
  "properties": {
    "addr:full":"Cami Golf, 42 S. Andreu Llavaneres Barcelona 08392",
    "addr:housenumber":"42",
    "addr:postcode":"08392",
    "addr:street":"Golf;S. Andreu Llavaneres Barcelona",
    "iso:country":"ES",
    "sg:address":"Cami Golf, 42",
    "sg:city":"S. Andreu Llavaneres",
    "sg:orig_category":"Fotocopias, Reprograf\u00cda",
    "sg:phone":"+34 937 92 77 21",
    "sg:postcode":"08392",
    "sg:province":"Barcelona",
    "wof:name":"Ofimatica Aplicada En Archivos Y Planos S.l.",
    "wof:placetype":"venue"
},
  "geometry": {"coordinates":[2.4848129749,41.5664978027],"type":"Point"}
}