{
  "type": "Feature",
  "properties": {
    "addr:full":"Calle de Acera Alonso Gomez De Figueroa, 35 Cordoba C\u00f3rdoba 14014",
    "addr:housenumber":"35",
    "addr:postcode":"14014",
    "addr:street":"Calle De Acera Alonso Gomez De Figueroa;Co\u0301Rdoba",
    "iso:country":"ES",
    "sg:address":"Calle de Acera Alonso Gomez De Figueroa, 35",
    "sg:city":"Cordoba",
    "sg:orig_category":"Supermercados Y Hipermercados",
    "sg:phone":"+34 957 25 63 50",
    "sg:postcode":"14014",
    "sg:province":"C\u00f3rdoba",
    "wof:name":"Vargas Reyes Carmelo",
    "wof:placetype":"venue"
},
  "geometry": {"coordinates":[-4.7624139786,37.9240608215],"type":"Point"}
}