{
  "type": "Feature",
  "properties": {
    "iso:country":"ES",
    "sg:address":"Avda Laza (de), 37",
    "sg:city":"Verin",
    "sg:orig_category":"Empresas De Carpinter\u00cda De Madera",
    "sg:phone":"+34 988 41 23 03",
    "sg:postcode":"32600",
    "sg:province":"Ourense",
    "wof:name":"Castro Castro Jose Lino",
    "wof:placetype":"venue"
},
  "geometry": {"coordinates":[-7.4333648682,41.9474754333],"type":"Point"}
}