{
  "type": "Feature",
  "properties": {
    "iso:country":"ES",
    "sg:address":"Avda Colmenar Viejo (de), 16",
    "sg:city":"San Sebastian De Los Reyes",
    "sg:orig_category":"Inmobiliaria (agencias)",
    "sg:phone":"+34 916 53 18 22",
    "sg:postcode":"28700",
    "sg:province":"Madrid",
    "sg:website":"www.citymadrid.com",
    "wof:name":"Rodriguez Gonzalez Luis Agustin",
    "wof:placetype":"venue"
},
  "geometry": {"coordinates":[-3.628978014,40.5455055237],"type":"Point"}
}