{
  "type": "Feature",
  "properties": {
    "addr:full":"Calle de Gloria (la), 1 Antequera M\u00e1laga 29200",
    "addr:housenumber":"1",
    "addr:postcode":"29200",
    "addr:street":"Calle De Gloria La",
    "iso:country":"ES",
    "sg:address":"Calle de Gloria (la), 1",
    "sg:city":"Antequera",
    "sg:classifiers":[
        {
            "category":"Arts & Performance",
            "subcategory":"Art Gallery",
            "type":"Entertainment"
        }
    ],
    "sg:phone":"+34 952 84 63 80",
    "sg:postcode":"29200",
    "sg:province":"M\u00e1laga",
    "sg:tags":[
        "arte",
        "de",
        "galer\u00cdas"
    ],
    "sg:website":"www.casaborne.com",
    "wof:name":"Jardines De Icaria S.l.",
    "wof:placetype":"venue"
},
  "geometry": {"coordinates":[-4.5616374016,37.0165519714],"type":"Point"}
}