{
  "type": "Feature",
  "properties": {
    "addr:full":"Calle de Arfe, 12 Sevilla Sevilla 41001",
    "addr:housenumber":"12",
    "addr:postcode":"41001",
    "addr:street":"Calle De Arfe",
    "iso:country":"ES",
    "sg:address":"Calle de Arfe, 12",
    "sg:city":"Sevilla",
    "sg:orig_category":"Alimentaci\u00d3n General (al Por Menor)",
    "sg:phone":"+34 954 22 00 37",
    "sg:postcode":"41001",
    "sg:province":"Sevilla",
    "wof:name":"Sanchez Mu\u00f1oz Agustin",
    "wof:placetype":"venue"
},
  "geometry": {"coordinates":[-5.9961795807,37.3861503601],"type":"Point"}
}