{
  "type": "Feature",
  "properties": {
    "addr:full":"Calle de Alamo (del), 1 Boadilla Del Monte Madrid 28660",
    "addr:housenumber":"1",
    "addr:postcode":"28660",
    "addr:street":"Calle De Alamo Del",
    "iso:country":"ES",
    "sg:address":"Calle de Alamo (del), 1",
    "sg:city":"Boadilla Del Monte",
    "sg:orig_category":"Loter\u00cda Y T\u00d3mbola",
    "sg:phone":"+34 916 32 35 27",
    "sg:postcode":"28660",
    "sg:province":"Madrid",
    "wof:name":"Sevilla Chicote Maria Jesus",
    "wof:placetype":"venue"
},
  "geometry": {"coordinates":[-3.8771910667,40.4058952332],"type":"Point"}
}