{
  "type": "Feature",
  "properties": {
    "addr:full":"Cno La Pea, S/n Vilamarxant Valencia 46191",
    "addr:housenumber":"s / n",
    "addr:postcode":"46191",
    "addr:street":"Cno La Pea",
    "iso:country":"ES",
    "sg:address":"Cno La Pea, S/n",
    "sg:city":"Vilamarxant",
    "sg:orig_category":"Pirotecnia (espect\u00c1culos)",
    "sg:phone":"+34 961 65 02 62",
    "sg:postcode":"46191",
    "sg:province":"Valencia",
    "wof:name":"Pirotecnia Esteve S.l.",
    "wof:placetype":"venue"
},
  "geometry": {"coordinates":[-0.6272540092,39.5677604675],"type":"Point"}
}