{
  "type": "Feature",
  "properties": {
    "addr:full":"Calle de Lagasca, 96 Madrid Madrid 28006",
    "addr:housenumber":"96",
    "addr:postcode":"madrid;28006",
    "addr:street":"Calle De Lagasca",
    "iso:country":"ES",
    "sg:address":"Calle de Lagasca, 96",
    "sg:city":"Madrid",
    "sg:orig_category":"Comisarios",
    "sg:phone":"+34 917 81 30 01",
    "sg:postcode":"28006",
    "sg:province":"Madrid",
    "wof:name":"Coarasa Torrente Maria",
    "wof:placetype":"venue"
},
  "geometry": {"coordinates":[-3.6845350266,40.431350708],"type":"Point"}
}