{
  "type": "Feature",
  "properties": {
    "iso:country":"ES",
    "sg:address":"Cmno Virgen Salud, S/n",
    "sg:city":"Baeza",
    "sg:orig_category":"Aceites Y Grasas Alimentarias (fabricaci\u00d3n, Al Por Mayor)",
    "sg:phone":"+34 953 74 41 45",
    "sg:postcode":"23440",
    "sg:province":"Ja\u00e9n",
    "wof:name":"Fabrica De Aceites Virgen De La Salud",
    "wof:placetype":"venue"
},
  "geometry": {"coordinates":[-3.4593040943,37.9995193481],"type":"Point"}
}