{
  "type": "Feature",
  "properties": {
    "addr:full":"Carrer de Alcantara, 22 Barcelona Barcelona 08042",
    "addr:housenumber":"22",
    "addr:postcode":"08042",
    "addr:street":"Carrer De Alcantara",
    "iso:country":"ES",
    "sg:address":"Carrer de Alcantara, 22",
    "sg:city":"Barcelona",
    "sg:orig_category":"Centros De Educaci\u00d3n Especial",
    "sg:phone":"+34 933 54 65 04",
    "sg:postcode":"08042",
    "sg:province":"Barcelona",
    "wof:name":"Ajuntament De Barcelona",
    "wof:placetype":"venue"
},
  "geometry": {"coordinates":[2.1726727486,41.446105957],"type":"Point"}
}