{
  "type": "Feature",
  "properties": {
    "iso:country":"ES",
    "sg:address":"Generalisimo, 45",
    "sg:city":"Villanueva Mesia",
    "sg:orig_category":"Trabajos De Perforaciones, Sondeos, Construcci\u00d3n De Pozos",
    "sg:phone":"+34 958 44 41 73",
    "sg:postcode":"18369",
    "sg:province":"Granada",
    "wof:name":"Duran Arroyo Francisco",
    "wof:placetype":"venue"
},
  "geometry": {"coordinates":[-4.011428833,37.2145957947],"type":"Point"}
}