{
  "type": "Feature",
  "properties": {
    "addr:full":"Cmno Ronda (de), 22 Granada Granada 18006",
    "addr:housenumber":"22",
    "addr:postcode":"18006",
    "addr:street":"Cmno Ronda De",
    "iso:country":"ES",
    "sg:address":"Cmno Ronda (de), 22",
    "sg:city":"Granada",
    "sg:orig_category":"Ropa De Trabajo Y Profesionales (al Por Menor)",
    "sg:phone":"+34 958 13 19 76",
    "sg:postcode":"18006",
    "sg:province":"Granada",
    "wof:name":"Castillo Sanchez Antonio",
    "wof:placetype":"venue"
},
  "geometry": {"coordinates":[-3.6028280258,37.1654815674],"type":"Point"}
}