{
  "type": "Feature",
  "properties": {
    "iso:country":"ES",
    "sg:address":"Carretera De La Albuera, Km. 0001,2",
    "sg:city":"Talavera Real",
    "sg:orig_category":"Agricultura: Abastecimiento Y Cosechado (negocio)",
    "sg:phone":"+34 924 44 16 57",
    "sg:postcode":"06140",
    "sg:province":"Badajoz",
    "wof:name":"Aldea Del Conde Sociedad Cooperativa Limitada",
    "wof:placetype":"venue"
},
  "geometry": {"coordinates":[-6.7764782906,38.8774909973],"type":"Point"}
}