{
  "type": "Feature",
  "properties": {
    "addr:full":"Calle de Maestro Perelle, 2 Totana Murcia 30850",
    "addr:housenumber":"2",
    "addr:postcode":"30850",
    "addr:street":"Calle De Maestro Perelle",
    "iso:country":"ES",
    "sg:address":"Calle de Maestro Perelle, 2",
    "sg:city":"Totana",
    "sg:orig_category":"Molduras, Junquillos, Listones Y Molduras Perforadas",
    "sg:phone":"+34 968 42 77 25",
    "sg:postcode":"30850",
    "sg:province":"Murcia",
    "wof:name":"Sanchez Perez Natalia",
    "wof:placetype":"venue"
},
  "geometry": {"coordinates":[-1.4997110367,37.7701873779],"type":"Point"}
}