{
  "type": "Feature",
  "properties": {
    "addr:full":"Calle de Herri Bide, 10 Mungia Vizcaya 48100",
    "addr:housenumber":"10",
    "addr:postcode":"48100",
    "addr:street":"Calle De Herri Bide",
    "iso:country":"ES",
    "sg:address":"Calle de Herri Bide, 10",
    "sg:city":"Mungia",
    "sg:orig_category":"Tintes (fabricaci\u00d3n, Al Por Mayor)",
    "sg:phone":"+34 946 15 66 11",
    "sg:postcode":"48100",
    "sg:province":"Vizcaya",
    "wof:name":"Tintoreria Jantzi-prest, Agustin Martinez Barbara",
    "wof:placetype":"venue"
},
  "geometry": {"coordinates":[-2.844353199,43.3553314209],"type":"Point"}
}