{
  "type": "Feature",
  "properties": {
    "iso:country":"ES",
    "sg:address":"Calle de Amadeo Desfilis, 11",
    "sg:city":"Valencia",
    "sg:orig_category":"Electrodom\u00c9sticos (al Por Menor)",
    "sg:phone":"+34 963 40 38 61",
    "sg:postcode":"46025",
    "sg:province":"Valencia",
    "wof:name":"Peinado Cano Aladino",
    "wof:placetype":"venue"
},
  "geometry": {"coordinates":[-0.3952584863,39.4991416931],"type":"Point"}
}