{
  "type": "Feature",
  "properties": {
    "addr:full":"Calle de Postigos De San Juan, 4 Salda\u00f1a Palencia 34100",
    "addr:housenumber":"4",
    "addr:postcode":"34100",
    "addr:street":"Calle De Postigos De San Juan",
    "iso:country":"ES",
    "sg:address":"Calle de Postigos De San Juan, 4",
    "sg:city":"Salda\u00f1a",
    "sg:orig_category":"Carnicer\u00cdas, Carnicer\u00cdas",
    "sg:phone":"+34 979 89 04 00",
    "sg:postcode":"34100",
    "sg:province":"Palencia",
    "wof:name":"Vega Roldan Jose",
    "wof:placetype":"venue"
},
  "geometry": {"coordinates":[-4.7374510765,42.5231285095],"type":"Point"}
}