{
  "type": "Feature",
  "properties": {
    "iso:country":"ES",
    "sg:address":"Rua Rei Don Garcia, 26",
    "sg:city":"Lugo",
    "sg:orig_category":"Complementos Para Pasteler\u00cdas, Confiter\u00cdas Y Chocolater\u00cdas",
    "sg:phone":"+34 982 22 00 09",
    "sg:postcode":"27002",
    "sg:province":"Lugo",
    "wof:name":"Exclusivas Nemesio S.l.",
    "wof:placetype":"venue"
},
  "geometry": {"coordinates":[-7.5494132042,43.0041465759],"type":"Point"}
}