{
  "type": "Feature",
  "properties": {
    "iso:country":"ES",
    "sg:address":"Carrer de Paris, 50",
    "sg:city":"Barcelona",
    "sg:orig_category":"Empresarios Y Productoras De Espect\u00c1culos",
    "sg:phone":"+34 934 39 81 99",
    "sg:postcode":"08029",
    "sg:province":"Barcelona",
    "wof:name":"Martin Carre\u00f1o Juana",
    "wof:placetype":"venue"
},
  "geometry": {"coordinates":[2.1437549591,41.3864021301],"type":"Point"}
}