{
  "type": "Feature",
  "properties": {
    "addr:full":"Plaz Paco Lopez Pina, 8 Petrer Alicante 03610",
    "addr:housenumber":"8",
    "addr:postcode":"03610",
    "addr:street":"Pina",
    "iso:country":"ES",
    "sg:address":"Plaz Paco Lopez Pina, 8",
    "sg:city":"Petrer",
    "sg:orig_category":"Laboratorios Y Cl\u00cdnicas Veterinarias",
    "sg:phone":"+34 966 95 55 15",
    "sg:postcode":"03610",
    "sg:province":"Alicante",
    "wof:name":"Hospital Veterinario Menescal S.l.",
    "wof:placetype":"venue"
},
  "geometry": {"coordinates":[-0.7835490108,38.4818382263],"type":"Point"}
}