{
  "type": "Feature",
  "properties": {
    "addr:full":"Carrer de Sentenero, 31 Novelda Alicante 03660",
    "addr:housenumber":"31",
    "addr:postcode":"03660",
    "addr:street":"Carrer De Sentenero",
    "iso:country":"ES",
    "sg:address":"Carrer de Sentenero, 31",
    "sg:city":"Novelda",
    "sg:orig_category":"Artes Gr\u00c1ficas, Artes Pl\u00c1sticas: Material Y Suministros (al Por Menor)",
    "sg:phone":"+34 965 60 76 53",
    "sg:postcode":"03660",
    "sg:province":"Alicante",
    "sg:website":"www.dcdcdcdc.com",
    "wof:name":"Dcdc Division Informatica S.l.",
    "wof:placetype":"venue"
},
  "geometry": {"coordinates":[-0.7628570199,38.3870048523],"type":"Point"}
}