{
  "type": "Feature",
  "properties": {
    "addr:full":"Calle de San Juan De La Pe\u00d1a, 15 Barbastro Huesca 22300",
    "addr:housenumber":"15",
    "addr:postcode":"22300",
    "addr:street":"Calle De San Juan;La Pen\u0303A",
    "iso:country":"ES",
    "sg:address":"Calle de San Juan De La Pe\u00d1a, 15",
    "sg:city":"Barbastro",
    "sg:orig_category":"Comadronas",
    "sg:phone":"+34 974 31 19 99",
    "sg:postcode":"22300",
    "sg:province":"Huesca",
    "wof:name":"Gonzalez Vidal Delfina",
    "wof:placetype":"venue"
},
  "geometry": {"coordinates":[0.1144260019,42.0369796753],"type":"Point"}
}