{
  "type": "Feature",
  "properties": {
    "addr:full":"Calle de Moral, 3 Campanario Badajoz 06460",
    "addr:housenumber":"3",
    "addr:postcode":"06460",
    "addr:street":"Calle De Moral",
    "iso:country":"ES",
    "sg:address":"Calle de Moral, 3",
    "sg:city":"Campanario",
    "sg:orig_category":"Internados & Ense\u00d1anza Privada",
    "sg:phone":"+34 924 83 10 04",
    "sg:postcode":"06460",
    "sg:province":"Badajoz",
    "wof:name":"Religiosas De La Providencia",
    "wof:placetype":"venue"
},
  "geometry": {"coordinates":[-5.6180667877,38.8650779724],"type":"Point"}
}