{
  "type": "Feature",
  "properties": {
    "addr:full":"Magallanes, S/n Quintana Serena Badajoz 06450",
    "addr:housenumber":"s / n",
    "addr:postcode":"06450",
    "addr:street":"Magallanes;Quintana Serena",
    "iso:country":"ES",
    "sg:address":"Magallanes, S/n",
    "sg:city":"Quintana Serena",
    "sg:orig_category":"M\u00c1quinas Y Herramientas Para Trabajar La Piedra",
    "sg:phone":"+34 924 77 71 82",
    "sg:postcode":"06450",
    "sg:province":"Badajoz",
    "wof:name":"Trejo Sanchez Gaspar",
    "wof:placetype":"venue"
},
  "geometry": {"coordinates":[-5.6758289337,38.7401847839],"type":"Point"}
}