{
  "type": "Feature",
  "properties": {
    "addr:full":"Carrer de Sant Just Desvern, 3 S. Joan Despi Barcelona 08970",
    "addr:housenumber":"3",
    "addr:postcode":"08970",
    "addr:street":"Carrer De Sant Just Desvern;S. Joan Despi",
    "iso:country":"ES",
    "sg:address":"Carrer de Sant Just Desvern, 3",
    "sg:city":"S. Joan Despi",
    "sg:orig_category":"Doctores En Medicina",
    "sg:phone":"+34 933 73 27 03",
    "sg:postcode":"08970",
    "sg:province":"Barcelona",
    "wof:name":"Parera Lopez Jose Luis",
    "wof:placetype":"venue"
},
  "geometry": {"coordinates":[2.0741589069,41.3692245483],"type":"Point"}
}