{
  "type": "Feature",
  "properties": {
    "iso:country":"ES",
    "sg:address":"Afueras, S/n",
    "sg:city":"S. Agusti Vedra",
    "sg:orig_category":"Frutas Y Legumbres Secas (al Por Mayor)",
    "sg:phone":"+34 971 80 03 49",
    "sg:postcode":"07839",
    "sg:province":"Islas Baleares",
    "wof:name":"Torres Ribas Juan",
    "wof:placetype":"venue"
},
  "geometry": {"coordinates":[1.3025970459,38.8642692566],"type":"Point"}
}