{
  "type": "Feature",
  "properties": {
    "iso:country":"ES",
    "sg:address":"Calle de Ciudad De Martos, 23",
    "sg:city":"Mora",
    "sg:orig_category":"Molduras, Junquillos, Listones Y Molduras Perforadas",
    "sg:phone":"+34 925 34 07 46",
    "sg:postcode":"45400",
    "sg:province":"Toledo",
    "wof:name":"La Zafra Hosteleria S.l.",
    "wof:placetype":"venue"
},
  "geometry": {"coordinates":[-3.7717351913,39.6854820251],"type":"Point"}
}