{
  "type": "Feature",
  "properties": {
    "addr:full":"Escuela Arte Y Oficios, 11 Barakaldo Vizcaya 48902",
    "addr:postcode":"48902",
    "iso:country":"ES",
    "sg:address":"Escuela Arte Y Oficios, 11",
    "sg:city":"Barakaldo",
    "sg:orig_category":"Caf\u00c9s, Bares, Cervecer\u00cdas",
    "sg:phone":"+34 944 78 16 36",
    "sg:postcode":"48902",
    "sg:province":"Vizcaya",
    "wof:name":"Ruiz Rodriguez Y Fco.javier Carrique Cb",
    "wof:placetype":"venue"
},
  "geometry": {"coordinates":[-2.982749939,43.3020439148],"type":"Point"}
}