{
  "type": "Feature",
  "properties": {
    "iso:country":"ES",
    "sg:address":"Calle de Pedro Antonio De Alarcon, 1",
    "sg:city":"Madrid",
    "sg:orig_category":"Empresas De Carpinter\u00cda Met\u00c1lica",
    "sg:phone":"+34 914 08 75 99",
    "sg:postcode":"28017",
    "sg:province":"Madrid",
    "wof:name":"Aluminios Camol C.b.",
    "wof:placetype":"venue"
},
  "geometry": {"coordinates":[-3.640853405,40.4275360107],"type":"Point"}
}