{
  "type": "Feature",
  "properties": {
    "iso:country":"ES",
    "sg:address":"C/ Major, 1",
    "sg:city":"S. Julia Ramis",
    "sg:orig_category":"Ense\u00d1anza, Formaci\u00d3n Profesional: Aprendizaje",
    "sg:phone":"+34 972 17 09 09",
    "sg:postcode":"17481",
    "sg:province":"Girona",
    "wof:name":"Ajuntament De Sant Julia De Ramis",
    "wof:placetype":"venue"
},
  "geometry": {"coordinates":[2.8252007961,42.0106620789],"type":"Point"}
}