{
  "type": "Feature",
  "properties": {
    "addr:full":"Diseminados, S/n Perdiguera Zaragoza 50161",
    "addr:housenumber":"s / n",
    "addr:postcode":"50161",
    "addr:street":"Diseminados",
    "iso:country":"ES",
    "sg:address":"Diseminados, S/n",
    "sg:city":"Perdiguera",
    "sg:orig_category":"Maquinaria Para Industrias Diversas",
    "sg:phone":"+34 976 16 86 30",
    "sg:postcode":"50161",
    "sg:province":"Zaragoza",
    "wof:name":"Delgado Prieto Lorenzo",
    "wof:placetype":"venue"
},
  "geometry": {"coordinates":[-0.6344789863,41.7515563965],"type":"Point"}
}