{
  "type": "Feature",
  "properties": {
    "addr:full":"La Cerrajera, 76 Cuenca Cuenca 16004",
    "addr:housenumber":"76",
    "addr:postcode":"16004",
    "iso:country":"ES",
    "sg:address":"La Cerrajera, 76",
    "sg:city":"Cuenca",
    "sg:orig_category":"Empresas De Carpinter\u00cda",
    "sg:phone":"+34 969 23 40 39",
    "sg:postcode":"16004",
    "sg:province":"Cuenca",
    "wof:name":"Martinez Poyatos Julian",
    "wof:placetype":"venue"
},
  "geometry": {"coordinates":[-2.1401889324,40.0516204834],"type":"Point"}
}