{
  "type": "Feature",
  "properties": {
    "addr:full":"Avda Andalucia, 41 Atarfe Granada 18230",
    "addr:housenumber":"41",
    "addr:postcode":"18230",
    "addr:street":"Avda Andalucia",
    "iso:country":"ES",
    "sg:address":"Avda Andalucia, 41",
    "sg:city":"Atarfe",
    "sg:orig_category":"Asesor\u00cda Sobre Comunicaci\u00d3n De Empresas",
    "sg:phone":"+34 958 43 84 72",
    "sg:postcode":"18230",
    "sg:province":"Granada",
    "wof:name":"Lucena Aguilera Jose Evaristo",
    "wof:placetype":"venue"
},
  "geometry": {"coordinates":[-3.686248064,37.222984314],"type":"Point"}
}