{
  "type": "Feature",
  "properties": {
    "addr:full":"Avgd Balmes, 44 Lleida Lleida 25006",
    "addr:housenumber":"44",
    "addr:postcode":"25006",
    "addr:street":"Avgd Balmes",
    "iso:country":"ES",
    "sg:address":"Avgd Balmes, 44",
    "sg:city":"Lleida",
    "sg:orig_category":"M\u00c9dicos: Neuropsiquiatr\u00cda",
    "sg:phone":"+34 973 23 33 64",
    "sg:postcode":"25006",
    "sg:province":"Lleida",
    "wof:name":"Pigem Palmes Jose",
    "wof:placetype":"venue"
},
  "geometry": {"coordinates":[0.6194379926,41.6190795898],"type":"Point"}
}