{
  "type": "Feature",
  "properties": {
    "iso:country":"ES",
    "sg:address":"Calle de Santa Barbara, 3",
    "sg:city":"Sevilla",
    "sg:orig_category":"Asociaciones, Organismos Culturales Y Socioeducativos",
    "sg:phone":"+34 954 38 52 06",
    "sg:postcode":"41002",
    "sg:province":"Sevilla",
    "wof:name":"Hermandad Antiguos Caballeros Legionarios",
    "wof:placetype":"venue"
},
  "geometry": {"coordinates":[-5.9949412346,37.3961715698],"type":"Point"}
}