{
  "type": "Feature",
  "properties": {
    "addr:full":"Calle de Siguenza (de), 5 Fuenlabrada Madrid 28946",
    "addr:housenumber":"5",
    "addr:postcode":"28946",
    "addr:street":"Calle De Siguenza De",
    "iso:country":"ES",
    "sg:address":"Calle de Siguenza (de), 5",
    "sg:city":"Fuenlabrada",
    "sg:orig_category":"Galvanizaci\u00d3n, Esta\u00d1ado, Emplomado",
    "sg:phone":"+34 916 90 12 98",
    "sg:postcode":"28946",
    "sg:province":"Madrid",
    "wof:name":"Recmak S.a.",
    "wof:placetype":"venue"
},
  "geometry": {"coordinates":[-3.7814486027,40.2820854187],"type":"Point"}
}