{
  "type": "Feature",
  "properties": {
    "iso:country":"ES",
    "sg:address":"Pol Ind Las Vaderas, 14",
    "sg:city":"Pilas",
    "sg:orig_category":"Chapister\u00cda",
    "sg:phone":"+34 954 75 05 95",
    "sg:postcode":"41840",
    "sg:province":"Sevilla",
    "wof:name":"J.j.car Chapa Y Pintura S.l.l.",
    "wof:placetype":"venue"
},
  "geometry": {"coordinates":[-6.3043088913,37.3053894043],"type":"Point"}
}