{
  "type": "Feature",
  "properties": {
    "iso:country":"ES",
    "sg:address":"Trva San Pelayo, 13",
    "sg:city":"Ermua",
    "sg:orig_category":"Supermercados Y Hipermercados",
    "sg:phone":"+34 943 03 19 34",
    "sg:postcode":"48260",
    "sg:province":"Vizcaya",
    "wof:name":"Autoservicio Mari",
    "wof:placetype":"venue"
},
  "geometry": {"coordinates":[-2.5047180653,43.1874084473],"type":"Point"}
}