{
  "type": "Feature",
  "properties": {
    "addr:full":"Calle de Gran Breta\u00d1a, S/n San Eugenio Bajo Santa Cruz De Tenerife 38660",
    "addr:housenumber":"s / n",
    "addr:postcode":"38660",
    "addr:street":"Calle De Gran Bretan\u0303A",
    "iso:country":"ES",
    "sg:address":"Calle de Gran Breta\u00d1a, S/n",
    "sg:city":"San Eugenio Bajo",
    "sg:orig_category":"Centros Comerciales Y Grandes Tiendas",
    "sg:phone":"+34 922 79 60 39",
    "sg:postcode":"38660",
    "sg:province":"Santa Cruz De Tenerife",
    "wof:name":"Pindoria  Ketan Khimji",
    "wof:placetype":"venue"
},
  "geometry": {"coordinates":[-16.7339782715,28.0762138367],"type":"Point"}
}