{
  "type": "Feature",
  "properties": {
    "addr:full":"Mercat Vall D'hebron, S/n Barcelona Barcelona 08032",
    "addr:housenumber":"s / n",
    "addr:postcode":"08032",
    "iso:country":"ES",
    "sg:address":"Mercat Vall D'hebron, S/n",
    "sg:city":"Barcelona",
    "sg:orig_category":"Carnicer\u00cdas, Carnicer\u00cdas",
    "sg:phone":"+34 934 28 09 34",
    "sg:postcode":"08032",
    "sg:province":"Barcelona",
    "wof:name":"Jordan Frances Miguel",
    "wof:placetype":"venue"
},
  "geometry": {"coordinates":[2.1606929302,41.429851532],"type":"Point"}
}