{
  "type": "Feature",
  "properties": {
    "iso:country":"ES",
    "sg:address":"Calle de Balbin Busto, 10",
    "sg:city":"Villaviciosa",
    "sg:orig_category":"Art\u00cdculos De Regalo (al Por Menor)",
    "sg:phone":"+34 985 89 30 20",
    "sg:postcode":"33300",
    "sg:province":"Asturias",
    "wof:name":"Por 4 Reales C.b.",
    "wof:placetype":"venue"
},
  "geometry": {"coordinates":[-5.4341349602,43.4806060791],"type":"Point"}
}