{
  "type": "Feature",
  "properties": {
    "addr:full":"Calle de Santa Adela, 63 Granada Granada 18007",
    "addr:housenumber":"63",
    "addr:postcode":"18007",
    "addr:street":"Calle De Santa Adela",
    "iso:country":"ES",
    "sg:address":"Calle de Santa Adela, 63",
    "sg:city":"Granada",
    "sg:orig_category":"Frutos Y Legumbres",
    "sg:phone":"+34 958 81 03 01",
    "sg:postcode":"18007",
    "sg:province":"Granada",
    "wof:name":"Frutas Aguilera S.l.",
    "wof:placetype":"venue"
},
  "geometry": {"coordinates":[-3.5995490551,37.1515655518],"type":"Point"}
}