{
  "type": "Feature",
  "properties": {
    "addr:full":"Cami Salard, 47 Palma Islas Baleares 07008",
    "addr:housenumber":"47",
    "addr:postcode":"07008",
    "addr:street":"Salard",
    "iso:country":"ES",
    "sg:address":"Cami Salard, 47",
    "sg:city":"Palma",
    "sg:orig_category":"Asociaciones Y Clubs Deportivos",
    "sg:phone":"+34 971 47 22 68",
    "sg:postcode":"07008",
    "sg:province":"Islas Baleares",
    "wof:name":"Obispado De Mallorca",
    "wof:placetype":"venue"
},
  "geometry": {"coordinates":[2.6814630032,39.5854072571],"type":"Point"}
}