{
  "type": "Feature",
  "properties": {
    "addr:full":"Calle de Pilar, 65 Almendralejo Badajoz 06200",
    "addr:housenumber":"65",
    "addr:postcode":"06200",
    "addr:street":"Calle De Pilar",
    "iso:country":"ES",
    "sg:address":"Calle de Pilar, 65",
    "sg:city":"Almendralejo",
    "sg:orig_category":"Carnicer\u00cdas, Carnicer\u00cdas",
    "sg:phone":"+34 924 66 72 22",
    "sg:postcode":"06200",
    "sg:province":"Badajoz",
    "sg:website":"www.jamonex.com",
    "wof:name":"Nogales Peguero Maria Del Carmen",
    "wof:placetype":"venue"
},
  "geometry": {"coordinates":[-6.4125590324,38.6835899353],"type":"Point"}
}