{
  "type": "Feature",
  "properties": {
    "iso:country":"ES",
    "sg:address":"Avda Primero De Mayo, 37",
    "sg:city":"Palmas De Gran Canaria",
    "sg:orig_category":"Cajas De Ahorro",
    "sg:phone":"+34 928 37 15 61",
    "sg:postcode":"35002",
    "sg:province":"Las Palmas",
    "wof:name":"Caja Insular De Ahorros De Canarias",
    "wof:placetype":"venue"
},
  "geometry": {"coordinates":[-15.4200563431,28.1056613922],"type":"Point"}
}