{
  "type": "Feature",
  "properties": {
    "iso:country":"ES",
    "sg:address":"Pase Alisas, 7",
    "sg:city":"Solares",
    "sg:orig_category":"Institutos De Belleza",
    "sg:phone":"+34 942 52 21 20",
    "sg:postcode":"39710",
    "sg:province":"Cantabria",
    "wof:name":"Vicente Baldor Margarita",
    "wof:placetype":"venue"
},
  "geometry": {"coordinates":[-3.7402191162,43.38463974],"type":"Point"}
}