{
  "type": "Feature",
  "properties": {
    "iso:country":"ES",
    "sg:address":"Calle de Elizasu, 14",
    "sg:city":"Donostia-san Sebastian",
    "sg:orig_category":"Ebanister\u00cda",
    "sg:phone":"+34 943 35 19 97",
    "sg:postcode":"20017",
    "sg:province":"Guip\u00f9zcoa",
    "wof:name":"Navarro Fernandez Jesus",
    "wof:placetype":"venue"
},
  "geometry": {"coordinates":[-1.9335298538,43.3153572083],"type":"Point"}
}