{
  "type": "Feature",
  "properties": {
    "iso:country":"ES",
    "sg:address":"Poli Poligono Industrial Quemadas, 105",
    "sg:city":"Quemadas",
    "sg:orig_category":"Alimentaci\u00d3n General (al Por Mayor)",
    "sg:phone":"+34 957 32 67 95",
    "sg:postcode":"14014",
    "sg:province":"C\u00f3rdoba",
    "wof:name":"Allfaro Exclusiva Alimentacion S.l",
    "wof:placetype":"venue"
},
  "geometry": {"coordinates":[-4.7791519165,37.884727478],"type":"Point"}
}