{
  "type": "Feature",
  "properties": {
    "iso:country":"ES",
    "sg:address":"Avda Ramon Y Cajal, 9",
    "sg:city":"Baiona",
    "sg:orig_category":"M\u00c9dicos: Estomatolog\u00cda",
    "sg:phone":"+34 986 35 72 58",
    "sg:postcode":"36300",
    "sg:province":"Pontevedra",
    "wof:name":"Cabello Vincent Jorge Enrique",
    "wof:placetype":"venue"
},
  "geometry": {"coordinates":[-97.78224945069999,45.7040786743],"type":"Point"}
}