{
  "type": "Feature",
  "properties": {
    "iso:country":"ES",
    "sg:address":"Avda Comercio, 27",
    "sg:city":"Illescas",
    "sg:orig_category":"Imprenta",
    "sg:phone":"+34 925 51 22 60",
    "sg:postcode":"45200",
    "sg:province":"Toledo",
    "wof:name":"Imprenta Grecoprint, S.l.",
    "wof:placetype":"venue"
},
  "geometry": {"coordinates":[-3.8536689281,40.1186904907],"type":"Point"}
}