{
  "type": "Feature",
  "properties": {
    "iso:country":"ES",
    "sg:address":"Calle de Zear-kalea, 19",
    "sg:city":"Markina-xemein",
    "sg:orig_category":"Molduras, Junquillos, Listones Y Molduras Perforadas",
    "sg:phone":"+34 946 16 92 65",
    "sg:postcode":"48270",
    "sg:province":"Vizcaya",
    "wof:name":"Eizaguirre Sololuce Carmelo",
    "wof:placetype":"venue"
},
  "geometry": {"coordinates":[-2.4968400002,43.267490387],"type":"Point"}
}