{
  "type": "Feature",
  "properties": {
    "addr:full":"Calle de Manuel Rodriguez Sinde, S/n Guarda Pontevedra 36780",
    "addr:housenumber":"s",
    "addr:postcode":"36780",
    "addr:street":"Calle De Manuel Rodriguez Sinde;/ N",
    "iso:country":"ES",
    "sg:address":"Calle de Manuel Rodriguez Sinde, S/n",
    "sg:city":"Guarda",
    "sg:orig_category":"Electrodom\u00c9sticos (al Por Menor)",
    "sg:phone":"+34 986 61 39 67",
    "sg:postcode":"36780",
    "sg:province":"Pontevedra",
    "wof:name":"Gonzalez Gonzalez Jesus",
    "wof:placetype":"venue"
},
  "geometry": {"coordinates":[-8.8713140488,41.9025039673],"type":"Point"}
}