{
  "type": "Feature",
  "properties": {
    "iso:country":"ES",
    "sg:address":"Avda Region Murciana, Km. 0001,5",
    "sg:city":"Carril De La Enera",
    "sg:orig_category":"Confecci\u00d3n De Trajes Para Se\u00d1oras",
    "sg:phone":"+34 968 25 70 00",
    "sg:postcode":"30011",
    "sg:province":"Murcia",
    "wof:name":"Nicchi Dise\u00d1o S.l.",
    "wof:placetype":"venue"
},
  "geometry": {"coordinates":[-1.1055790186,37.9783668518],"type":"Point"}
}