{
  "type": "Feature",
  "properties": {
    "iso:country":"ES",
    "sg:address":"Carr Port Grec, 40",
    "sg:city":"Empuriabrava",
    "sg:orig_category":"Institutos De Belleza",
    "sg:phone":"+34 972 45 01 51",
    "sg:postcode":"17487",
    "sg:province":"Girona",
    "wof:name":"Deprez  Philippe",
    "wof:placetype":"venue"
},
  "geometry": {"coordinates":[3.1070549488,42.2568092346],"type":"Point"}
}