{
  "type": "Feature",
  "properties": {
    "iso:country":"ES",
    "sg:address":"Carrer de Roger De Lluria, 15",
    "sg:city":"Barcelona",
    "sg:orig_category":"Farmacias",
    "sg:phone":"+34 933 17 37 91",
    "sg:postcode":"08010",
    "sg:province":"Barcelona",
    "wof:name":"Bouffard Fita Carina",
    "wof:placetype":"venue"
},
  "geometry": {"coordinates":[2.1718099117,41.3906974792],"type":"Point"}
}