{
  "type": "Feature",
  "properties": {
    "addr:full":"Doctor A Fleming, 14 Iru\u00f1a Navarra 31012",
    "addr:housenumber":"14",
    "addr:postcode":"31012",
    "addr:street":"Doctor A Fleming",
    "iso:country":"ES",
    "sg:address":"Doctor A Fleming, 14",
    "sg:city":"Iru\u00f1a",
    "sg:orig_category":"Inmobiliaria (agencias)",
    "sg:phone":"+34 948 12 67 47",
    "sg:postcode":"31012",
    "sg:province":"Navarra",
    "wof:name":"Beorlegui Zozaya Javier",
    "wof:placetype":"venue"
},
  "geometry": {"coordinates":[-1.6635329723,42.8233337402],"type":"Point"}
}