{
  "type": "Feature",
  "properties": {
    "iso:country":"ES",
    "sg:address":"Calle de Toledo, 6",
    "sg:city":"Ibi",
    "sg:orig_category":"Fabricaci\u00d3n De Juegos Y Juguetes",
    "sg:phone":"+34 966 55 05 90",
    "sg:postcode":"03440",
    "sg:province":"Alicante",
    "wof:name":"Sanz Morales Eladio",
    "wof:placetype":"venue"
},
  "geometry": {"coordinates":[-0.5849189758,38.6150817871],"type":"Point"}
}