{
  "type": "Feature",
  "properties": {
    "iso:country":"ES",
    "sg:address":"Rond Fonti\u00d1as (das), 199",
    "sg:city":"Lugo",
    "sg:orig_category":"Empresas De Impermeabilizaci\u00d3n",
    "sg:phone":"+34 982 22 02 67",
    "sg:postcode":"27002",
    "sg:province":"Lugo",
    "wof:name":"Lopez Lopez Roberto",
    "wof:placetype":"venue"
},
  "geometry": {"coordinates":[-7.5454959869,43.0039291382],"type":"Point"}
}