{
  "type": "Feature",
  "properties": {
    "addr:full":"Albufera, 4 Beniparrell Valencia 46469",
    "addr:postcode":"46469",
    "addr:street":"Albufera;Beniparrell",
    "iso:country":"ES",
    "sg:address":"Albufera, 4",
    "sg:city":"Beniparrell",
    "sg:orig_category":"Venta, Montaje De Neum\u00c1ticos",
    "sg:phone":"+34 961 20 13 03",
    "sg:postcode":"46469",
    "sg:province":"Valencia",
    "wof:name":"Yes Motor S.l.",
    "wof:placetype":"venue"
},
  "geometry": {"coordinates":[-0.4123207033,39.3803367615],"type":"Point"}
}