{
  "type": "Feature",
  "properties": {
    "iso:country":"ES",
    "sg:address":"Av Barbera, 394",
    "sg:city":"Sabadell",
    "sg:orig_category":"Ropa Para Se\u00d1oras Y Caballeros (al Por Menor)",
    "sg:phone":"+34 937 10 84 61",
    "sg:postcode":"08204",
    "sg:province":"Barcelona",
    "wof:name":"Garcia Dominguez Angela",
    "wof:placetype":"venue"
},
  "geometry": {"coordinates":[2.1175889969,41.5294418335],"type":"Point"}
}