{
  "type": "Feature",
  "properties": {
    "addr:full":"Avda Teodomiro, 26 Orihuela Alicante 03300",
    "addr:housenumber":"26",
    "addr:postcode":"03300",
    "addr:street":"Avda Teodomiro",
    "iso:country":"ES",
    "sg:address":"Avda Teodomiro, 26",
    "sg:city":"Orihuela",
    "sg:orig_category":"Ortopedia General",
    "sg:phone":"+34 965 30 35 95",
    "sg:postcode":"03300",
    "sg:province":"Alicante",
    "wof:name":"Ortopedia Precision S.l.",
    "wof:placetype":"venue"
},
  "geometry": {"coordinates":[-0.9447110295,38.0799407959],"type":"Point"}
}