{
  "type": "Feature",
  "properties": {
    "iso:country":"ES",
    "sg:address":"Atzieta Kalea, 2",
    "sg:city":"Hernani",
    "sg:orig_category":"Ense\u00d1anza: Profesiones Art\u00cdsticas",
    "sg:phone":"+34 943 33 19 15",
    "sg:postcode":"20120",
    "sg:province":"Guip\u00f9zcoa",
    "wof:name":"Torres Lopez Jose Antonio",
    "wof:placetype":"venue"
},
  "geometry": {"coordinates":[-1.9752839804,43.2647857666],"type":"Point"}
}