{
  "type": "Feature",
  "properties": {
    "iso:country":"ES",
    "sg:address":"Plaz Alberto Acero, 5",
    "sg:city":"Llodio",
    "sg:orig_category":"Peluquer\u00cdas, Peluquer\u00cda Mixta",
    "sg:phone":"+34 946 72 48 16",
    "sg:postcode":"01400",
    "sg:province":"\u00c1lava",
    "wof:name":"Sanchez Hernandez Yolanda",
    "wof:placetype":"venue"
},
  "geometry": {"coordinates":[-2.964247942,43.1413459778],"type":"Point"}
}