{
  "type": "Feature",
  "properties": {
    "addr:full":"Avda Principe De Asturias, 195 Gijon Asturias 33212",
    "addr:housenumber":"195",
    "addr:postcode":"33212",
    "addr:street":"Avda Principe De Asturias",
    "iso:country":"ES",
    "sg:address":"Avda Principe De Asturias, 195",
    "sg:city":"Gijon",
    "sg:orig_category":"Armas Y Municiones (fabricaci\u00d3n, Al Por Mayor)",
    "sg:phone":"+34 985 32 68 99",
    "sg:postcode":"33212",
    "sg:province":"Asturias",
    "wof:name":"Montajes Del Cantabrico S.l.",
    "wof:placetype":"venue"
},
  "geometry": {"coordinates":[-5.6908979416,43.5371437073],"type":"Point"}
}