{
  "type": "Feature",
  "properties": {
    "addr:full":"Plaz Constitucion, 3 Valverde De Llerena Badajoz 06927",
    "addr:housenumber":"3",
    "addr:postcode":"06927",
    "addr:street":"Constitucion",
    "iso:country":"ES",
    "sg:address":"Plaz Constitucion, 3",
    "sg:city":"Valverde De Llerena",
    "sg:orig_category":"Administraciones Regionales, Departamentales Y Locales",
    "sg:phone":"+34 924 89 80 01",
    "sg:postcode":"06927",
    "sg:province":"Badajoz",
    "wof:name":"Ayuntamiento De Valverde De Llerena",
    "wof:placetype":"venue"
},
  "geometry": {"coordinates":[-5.8224081993,38.2130241394],"type":"Point"}
}