{
  "type": "Feature",
  "properties": {
    "addr:full":"Cllo San Justo, S/n Toledo Toledo 45001",
    "addr:housenumber":"s / n",
    "addr:postcode":"45001",
    "addr:street":"Justo",
    "iso:country":"ES",
    "sg:address":"Cllo San Justo, S/n",
    "sg:city":"Toledo",
    "sg:orig_category":"Empresarios",
    "sg:phone":"+34 925 28 43 80",
    "sg:postcode":"45001",
    "sg:province":"Toledo",
    "sg:website":"www.fogtoledo.com",
    "wof:name":"Fundacion Jose Ortega Y Gasset",
    "wof:placetype":"venue"
},
  "geometry": {"coordinates":[-4.0216498375,39.8558425903],"type":"Point"}
}