{
  "type": "Feature",
  "properties": {
    "addr:full":"Calle de Ollerias, 2 Andujar Ja\u00e9n 23740",
    "addr:housenumber":"2",
    "addr:postcode":"23740",
    "addr:street":"Calle De Ollerias",
    "iso:country":"ES",
    "sg:address":"Calle de Ollerias, 2",
    "sg:city":"Andujar",
    "sg:orig_category":"Peluquer\u00cdas, Peluquer\u00cda Mixta",
    "sg:phone":"+34 953 51 30 40",
    "sg:postcode":"23740",
    "sg:province":"Ja\u00e9n",
    "wof:name":"Martinez Ales Virginia",
    "wof:placetype":"venue"
},
  "geometry": {"coordinates":[-4.0520467758,38.0375137329],"type":"Point"}
}