{
  "type": "Feature",
  "properties": {
    "addr:full":"Rua General Martitegui, 2 Pontevedra Pontevedra 36002",
    "addr:housenumber":"2",
    "addr:postcode":"36002",
    "addr:street":"Rua General Martitegui",
    "iso:country":"ES",
    "sg:address":"Rua General Martitegui, 2",
    "sg:city":"Pontevedra",
    "sg:orig_category":"Arquitectos",
    "sg:phone":"+34 986 85 62 62",
    "sg:postcode":"36002",
    "sg:province":"Pontevedra",
    "wof:name":"Barreiro Bujan Alfonso",
    "wof:placetype":"venue"
},
  "geometry": {"coordinates":[-8.6499385834,42.4325714111],"type":"Point"}
}