{
  "type": "Feature",
  "properties": {
    "iso:country":"ES",
    "sg:address":"Calle de Santa Clara, 26",
    "sg:city":"Zamora",
    "sg:orig_category":"Caf\u00c9s, Bares, Cervecer\u00cdas",
    "sg:phone":"+34 980 53 04 67",
    "sg:postcode":"49014",
    "sg:province":"Zamora",
    "wof:name":"Hosteleria Sanabresa S.l.",
    "wof:placetype":"venue"
},
  "geometry": {"coordinates":[-5.742128849,41.5064315796],"type":"Point"}
}