{
  "type": "Feature",
  "properties": {
    "addr:full":"Plaz General Mancha, 2 Alacant Alicante 03005",
    "addr:postcode":"03005",
    "addr:street":"Mancha",
    "iso:country":"ES",
    "sg:address":"Plaz General Mancha, 2",
    "sg:city":"Alacant",
    "sg:orig_category":"Alimentaci\u00d3n General (al Por Menor)",
    "sg:phone":"+34 965 22 98 93",
    "sg:postcode":"03005",
    "sg:province":"Alicante",
    "wof:name":"Tiendas Deshoras S.l.",
    "wof:placetype":"venue"
},
  "geometry": {"coordinates":[-0.4936339855,38.3481445312],"type":"Point"}
}