{
  "type": "Feature",
  "properties": {
    "addr:full":"Salut, 1 Olot Girona 17800",
    "addr:housenumber":"1",
    "addr:postcode":"17800",
    "addr:street":"Salut",
    "iso:country":"ES",
    "sg:address":"Salut, 1",
    "sg:city":"Olot",
    "sg:orig_category":"Empresas De Pintura Y Revestimientos",
    "sg:phone":"+34 972 26 15 00",
    "sg:postcode":"17800",
    "sg:province":"Girona",
    "wof:name":"Soy Colomer Estanis",
    "wof:placetype":"venue"
},
  "geometry": {"coordinates":[2.4935779572,42.1818771362],"type":"Point"}
}