{
  "type": "Feature",
  "properties": {
    "addr:full":"Carrer de Muntaner, 180 Barcelona Barcelona 08036",
    "addr:housenumber":"180",
    "addr:postcode":"08036",
    "addr:street":"Carrer De Muntaner",
    "iso:country":"ES",
    "sg:address":"Carrer de Muntaner, 180",
    "sg:city":"Barcelona",
    "sg:orig_category":"Organismos De Investigaciones Cient\u00cdficas Y T\u00c9cnicas",
    "sg:phone":"+34 934 10 24 37",
    "sg:postcode":"08036",
    "sg:province":"Barcelona",
    "wof:name":"Galton-centro De Investigaciones Psicologicas",
    "wof:placetype":"venue"
},
  "geometry": {"coordinates":[2.152256012,41.39220047],"type":"Point"}
}