{
  "type": "Feature",
  "properties": {
    "iso:country":"ES",
    "sg:address":"Calle de Juan Caro, 6",
    "sg:city":"Fuensalida",
    "sg:orig_category":"Confecci\u00d3n De Zapatos",
    "sg:phone":"+34 925 78 48 25",
    "sg:postcode":"45510",
    "sg:province":"Toledo",
    "wof:name":"Jonathan Shoes S.l.",
    "wof:placetype":"venue"
},
  "geometry": {"coordinates":[-4.2087769508,40.055103302],"type":"Point"}
}