{
  "type": "Feature",
  "properties": {
    "addr:full":"Calle de Miguel De Unamuno, 1 Zamora Zamora 49022",
    "addr:housenumber":"1",
    "addr:postcode":"49022",
    "addr:street":"Calle De Miguel De Unamuno",
    "iso:country":"ES",
    "sg:address":"Calle de Miguel De Unamuno, 1",
    "sg:city":"Zamora",
    "sg:orig_category":"M\u00c9dicos: Medicina Y Biolog\u00cda Del Deporte",
    "sg:phone":"+34 980 51 28 80",
    "sg:postcode":"49022",
    "sg:province":"Zamora",
    "wof:name":"Beneitez Ballesta Carlos",
    "wof:placetype":"venue"
},
  "geometry": {"coordinates":[-5.7377309799,41.5128631592],"type":"Point"}
}