{
  "type": "Feature",
  "properties": {
    "iso:country":"ES",
    "sg:address":"Calle de Moraleja De Enmedio, 2",
    "sg:city":"Humanes De Madrid",
    "sg:orig_category":"Empresas De Carpinter\u00cda De Madera",
    "sg:phone":"+34 916 90 58 52",
    "sg:postcode":"28970",
    "sg:province":"Madrid",
    "wof:name":"Cie S.l..",
    "wof:placetype":"venue"
},
  "geometry": {"coordinates":[-3.8327300549,40.2519760132],"type":"Point"}
}