{
  "type": "Feature",
  "properties": {
    "iso:country":"ES",
    "sg:address":"Cmno Spoleto, 7",
    "sg:city":"Tejina",
    "sg:orig_category":"Congelados: Productos Alimentarios (fabricaci\u00d3n, Al Por Mayor)",
    "sg:phone":"+34 922 15 08 78",
    "sg:postcode":"38260",
    "sg:province":"Santa Cruz De Tenerife",
    "wof:name":"Carniceros De Tenerife S.l.",
    "wof:placetype":"venue"
},
  "geometry": {"coordinates":[-16.3662166595,28.536693573],"type":"Point"}
}