{
  "type": "Feature",
  "properties": {
    "addr:full":"Ctra Ceuti (de), 30 Alguazas Murcia 30560",
    "addr:housenumber":"30",
    "addr:postcode":"30560",
    "addr:street":"Ctra Ceuti De",
    "iso:country":"ES",
    "sg:address":"Ctra Ceuti (de), 30",
    "sg:city":"Alguazas",
    "sg:orig_category":"Transportes Por V\u00cdas Navegables",
    "sg:phone":"+34 968 62 03 92",
    "sg:postcode":"30560",
    "sg:province":"Murcia",
    "wof:name":"Alfredo Ruiz Jimenes",
    "wof:placetype":"venue"
},
  "geometry": {"coordinates":[-1.2477780581,38.0537796021],"type":"Point"}
}