{
  "type": "Feature",
  "properties": {
    "addr:full":"Calle de Hermano Leon, 3 Mimetiz Vizcaya 48860",
    "addr:housenumber":"3",
    "addr:postcode":"48860",
    "addr:street":"Calle De Hermano Leon",
    "iso:country":"ES",
    "sg:address":"Calle de Hermano Leon, 3",
    "sg:city":"Mimetiz",
    "sg:orig_category":"Comercio De Piezas De Recambio Y De Accesorios De Veh\u00cdculos, Veh\u00cdculos Industriales",
    "sg:phone":"+34 946 39 14 29",
    "sg:postcode":"48860",
    "sg:province":"Vizcaya",
    "wof:name":"Hernandez Santiba\u00f1ez Aritz",
    "wof:placetype":"venue"
},
  "geometry": {"coordinates":[-3.1312179565,43.213508606],"type":"Point"}
}