{
  "type": "Feature",
  "properties": {
    "iso:country":"ES",
    "sg:address":"Avda Libertad (la), 25",
    "sg:city":"San Vicente Del Raspeig-sant Vicent Del Raspeig",
    "sg:orig_category":"Relojer\u00cda (al Por Menor, Reparaci\u00d3n)",
    "sg:phone":"+34 965 66 19 26",
    "sg:postcode":"03690",
    "sg:province":"Alicante",
    "wof:name":"Gadea Maldonado Jose Luis",
    "wof:placetype":"venue"
},
  "geometry": {"coordinates":[-0.5226759911,38.397403717],"type":"Point"}
}