{
  "type": "Feature",
  "properties": {
    "addr:full":"Calle de Malaga (de), 24 Fuenlabrada Madrid 28945",
    "addr:housenumber":"24",
    "addr:postcode":"28945",
    "addr:street":"Calle De Malaga De",
    "iso:country":"ES",
    "sg:address":"Calle de Malaga (de), 24",
    "sg:city":"Fuenlabrada",
    "sg:orig_category":"Ingeniero",
    "sg:phone":"+34 916 06 14 30",
    "sg:postcode":"28945",
    "sg:province":"Madrid",
    "wof:name":"Correas Lopez Marco Antonio",
    "wof:placetype":"venue"
},
  "geometry": {"coordinates":[-3.7944839001,40.288028717],"type":"Point"}
}