{
  "type": "Feature",
  "properties": {
    "addr:full":"Avda Santa Barbara, S/n Torre Bierzo Le\u00f3n 24370",
    "addr:housenumber":"/ n",
    "addr:postcode":"24370",
    "addr:street":"Avda Santa Barbara S;Leo\u0301N",
    "iso:country":"ES",
    "sg:address":"Avda Santa Barbara, S/n",
    "sg:city":"Torre Bierzo",
    "sg:orig_category":"Formaci\u00d3n Continuada (variada)",
    "sg:phone":"+34 987 53 60 69",
    "sg:postcode":"24370",
    "sg:province":"Le\u00f3n",
    "wof:name":"Rodriguez Feliz Julio",
    "wof:placetype":"venue"
},
  "geometry": {"coordinates":[-6.3286061287,42.5963401794],"type":"Point"}
}