{
  "type": "Feature",
  "properties": {
    "iso:country":"ES",
    "sg:address":"Pase Reina Sofia, Km. 0306,0",
    "sg:city":"Muela",
    "sg:orig_category":"Promotores Constructores",
    "sg:phone":"+34 976 14 80 03",
    "sg:postcode":"50196",
    "sg:province":"Zaragoza",
    "wof:name":"Promociones Santa Rosa S.a.",
    "wof:placetype":"venue"
},
  "geometry": {"coordinates":[-1.115334034,41.5763931274],"type":"Point"}
}