{
  "type": "Feature",
  "properties": {
    "iso:country":"ES",
    "sg:address":"Calle de Ciro Alegria, 1",
    "sg:city":"Malaga",
    "sg:orig_category":"Tubos Met\u00c1licos",
    "sg:phone":"+34 952 96 08 70",
    "sg:postcode":"29004",
    "sg:province":"M\u00e1laga",
    "wof:name":"Tubos Y Hierros Industriales S.a.",
    "wof:placetype":"venue"
},
  "geometry": {"coordinates":[-4.4828820229,36.6962356567],"type":"Point"}
}