{
  "type": "Feature",
  "properties": {
    "addr:full":"Plaz Sagrado Corazon De Jesus, Plaza, 5 Bilbao Vizcaya 48011",
    "addr:housenumber":"5",
    "addr:postcode":"48011",
    "iso:country":"ES",
    "sg:address":"Plaz Sagrado Corazon De Jesus, Plaza, 5",
    "sg:city":"Bilbao",
    "sg:orig_category":"Delegados, Agentes De Tr\u00c1nsito, Auxiliares De Transporte Internacional",
    "sg:phone":"+34 944 42 43 89",
    "sg:postcode":"48011",
    "sg:province":"Vizcaya",
    "sg:website":"www.asetravi.com",
    "wof:name":"Asociacion Empresarial Para La Gestion Del Transporte",
    "wof:placetype":"venue"
},
  "geometry": {"coordinates":[-2.9454658031,43.2652702332],"type":"Point"}
}