{
  "type": "Feature",
  "properties": {
    "iso:country":"ES",
    "sg:address":"Calle de Princesa, 10",
    "sg:city":"Madrid",
    "sg:orig_category":"Peluquer\u00cdas, Peluquer\u00cda Mixta",
    "sg:phone":"+34 915 42 55 05",
    "sg:postcode":"28008",
    "sg:province":"Madrid",
    "wof:name":"Osiris Enelar S.l.",
    "wof:placetype":"venue"
},
  "geometry": {"coordinates":[-3.712430954,40.4255447388],"type":"Point"}
}