{
  "type": "Feature",
  "properties": {
    "iso:country":"ES",
    "sg:address":"Calle de Real, 18",
    "sg:city":"Antigua",
    "sg:orig_category":"Desinfecci\u00d3n, Desinsectaci\u00d3n, Desratizaci\u00d3n",
    "sg:phone":"+34 928 87 81 36",
    "sg:postcode":"35630",
    "sg:province":"Las Palmas",
    "wof:name":"Airsol Canarias S.l.",
    "wof:placetype":"venue"
},
  "geometry": {"coordinates":[-14.0125598907,28.4228744507],"type":"Point"}
}