{
  "type": "Feature",
  "properties": {
    "addr:full":"Calle de San Mateo, 27 Alacant Alicante 03012",
    "addr:housenumber":"27",
    "addr:postcode":"03012",
    "addr:street":"Calle De San Mateo",
    "iso:country":"ES",
    "sg:address":"Calle de San Mateo, 27",
    "sg:city":"Alacant",
    "sg:orig_category":"Congelados: Productos Alimentarios (al Por Menor)",
    "sg:phone":"+34 965 25 20 03",
    "sg:postcode":"03012",
    "sg:province":"Alicante",
    "wof:name":"Galan Navarro Jesus",
    "wof:placetype":"venue"
},
  "geometry": {"coordinates":[-0.4783889949,38.3580207825],"type":"Point"}
}