{
  "type": "Feature",
  "properties": {
    "addr:full":"Calle de Rio Viejo, S/n Fuente Del Rey Sevilla 41700",
    "addr:housenumber":"s / n",
    "addr:postcode":"41700",
    "addr:street":"Calle De Rio Viejo",
    "iso:country":"ES",
    "sg:address":"Calle de Rio Viejo, S/n",
    "sg:city":"Fuente Del Rey",
    "sg:orig_category":"Vidrio, Fabricaci\u00d3n Y Comercio",
    "sg:phone":"+34 954 93 02 43",
    "sg:postcode":"41700",
    "sg:province":"Sevilla",
    "wof:name":"Guardian Glass Espa\u00f1a Central Vidriera S.l.",
    "wof:placetype":"venue"
},
  "geometry": {"coordinates":[-5.9756040573,37.3112182617],"type":"Point"}
}