{
  "type": "Feature",
  "properties": {
    "addr:full":"Rond Ponent, 13 Sabadell Barcelona 08206",
    "addr:housenumber":"13",
    "addr:postcode":"08206",
    "addr:street":"Rond Ponent",
    "iso:country":"ES",
    "sg:address":"Rond Ponent, 13",
    "sg:city":"Sabadell",
    "sg:orig_category":"Dietistas",
    "sg:phone":"+34 937 25 18 98",
    "sg:postcode":"08206",
    "sg:province":"Barcelona",
    "wof:name":"Ribo Coll Margarita",
    "wof:placetype":"venue"
},
  "geometry": {"coordinates":[2.0747048855,41.5592803955],"type":"Point"}
}