{
  "type": "Feature",
  "properties": {
    "iso:country":"ES",
    "sg:address":"Carrer de Balmes, 194",
    "sg:city":"Barcelona",
    "sg:orig_category":"Laboratorios Y Trabajos De Fotograf\u00cda, V\u00cddeo Y Cine",
    "sg:phone":"+34 932 18 85 38",
    "sg:postcode":"08006",
    "sg:province":"Barcelona",
    "wof:name":"Bonete Cabedo Jose Ramon",
    "wof:placetype":"venue"
},
  "geometry": {"coordinates":[2.1526660919,41.3970985413],"type":"Point"}
}