{
  "type": "Feature",
  "properties": {
    "iso:country":"ES",
    "sg:address":"Ctra Sagunto-burgos, Km. 0026,2",
    "sg:city":"Sot De Ferrer",
    "sg:orig_category":"Aluminio Y Aleaciones (producci\u00d3n, Transformaci\u00d3n, Negocio)",
    "sg:phone":"+34 964 13 27 13",
    "sg:postcode":"12489",
    "sg:province":"Castell\u00f3n",
    "wof:name":"Compania Valenciana De Aluminio Baux S.l.",
    "wof:placetype":"venue"
},
  "geometry": {"coordinates":[-0.4018499851,39.7978515625],"type":"Point"}
}