{
  "type": "Feature",
  "properties": {
    "iso:country":"ES",
    "sg:address":"Carretera Del Villar, S/n",
    "sg:city":"Puertollano",
    "sg:orig_category":"Empresarios",
    "sg:phone":"+34 926 42 08 07",
    "sg:postcode":"13500",
    "sg:province":"Ciudad Real",
    "wof:name":"Corchero Ure\u00f1a Santos",
    "wof:placetype":"venue"
},
  "geometry": {"coordinates":[-4.1042299271,38.6815910339],"type":"Point"}
}