{
  "type": "Feature",
  "properties": {
    "addr:full":"Av Sant Esteve, 37 Granollers Barcelona 08402",
    "addr:housenumber":"37",
    "addr:postcode":"08402",
    "addr:street":"Av Sant Esteve",
    "iso:country":"ES",
    "sg:address":"Av Sant Esteve, 37",
    "sg:city":"Granollers",
    "sg:orig_category":"Centros Empresariales",
    "sg:phone":"+34 938 79 55 36",
    "sg:postcode":"08402",
    "sg:province":"Barcelona",
    "wof:name":"Duna Tecnics S.a.",
    "wof:placetype":"venue"
},
  "geometry": {"coordinates":[2.290612936,41.6034393311],"type":"Point"}
}