{
  "type": "Feature",
  "properties": {
    "iso:country":"ES",
    "sg:address":"Carrer de Can Veri, 5",
    "sg:city":"Palma",
    "sg:orig_category":"Juristas Extranjeros",
    "sg:phone":"+34 971 21 33 02",
    "sg:postcode":"07001",
    "sg:province":"Islas Baleares",
    "wof:name":"Neue Juristische Consulting S.l.u.",
    "wof:placetype":"venue"
},
  "geometry": {"coordinates":[2.6484160423,39.569934845],"type":"Point"}
}