{
  "type": "Feature",
  "properties": {
    "iso:country":"ES",
    "sg:address":"Calle de Olvera, 19",
    "sg:city":"Ubeda",
    "sg:orig_category":"Promotores Constructores",
    "sg:phone":"+34 953 75 13 42",
    "sg:postcode":"23400",
    "sg:province":"Ja\u00e9n",
    "wof:name":"Agricola Lombardo S.l.",
    "wof:placetype":"venue"
},
  "geometry": {"coordinates":[-3.3781383038,38.0183982849],"type":"Point"}
}