{
  "type": "Feature",
  "properties": {
    "iso:country":"ES",
    "sg:address":"Calle de Malaga, 5",
    "sg:city":"Teruel",
    "sg:orig_category":"Electrodom\u00c9sticos (al Por Menor)",
    "sg:phone":"+34 978 60 49 63",
    "sg:postcode":"44002",
    "sg:province":"Teruel",
    "wof:name":"Electroter S.a.",
    "wof:placetype":"venue"
},
  "geometry": {"coordinates":[-1.103572011,40.3376083374],"type":"Point"}
}