{
  "type": "Feature",
  "properties": {
    "addr:full":"Calle de Santa Victoria, 8 Cordoba C\u00f3rdoba 14003",
    "addr:housenumber":"8",
    "addr:postcode":"14003",
    "addr:street":"Calle De Santa Victoria;Co\u0301Rdoba",
    "iso:country":"ES",
    "sg:address":"Calle de Santa Victoria, 8",
    "sg:city":"Cordoba",
    "sg:orig_category":"Talleres De Corte Y Confecci\u00d3n",
    "sg:phone":"+34 957 48 32 11",
    "sg:postcode":"14003",
    "sg:province":"C\u00f3rdoba",
    "wof:name":"Manuel J. Ponce Dise\u00f1o S.l.",
    "wof:placetype":"venue"
},
  "geometry": {"coordinates":[-4.7791519165,37.8829689026],"type":"Point"}
}