{
  "type": "Feature",
  "properties": {
    "iso:country":"ES",
    "sg:address":"Cmno Prados, 37",
    "sg:city":"Malaga",
    "sg:orig_category":"Alimentaci\u00d3n General (al Por Menor)",
    "sg:phone":"+34 952 36 02 04",
    "sg:postcode":"29006",
    "sg:province":"M\u00e1laga",
    "wof:name":"Hernandez Garcia Antonia",
    "wof:placetype":"venue"
},
  "geometry": {"coordinates":[-4.4751729965,36.6988639832],"type":"Point"}
}