{
  "type": "Feature",
  "properties": {
    "addr:full":"Pase Duque De Mandas, 45 Donostia-san Sebastian Guip\u00f9zcoa 20012",
    "addr:housenumber":"45",
    "addr:postcode":"20012",
    "addr:street":"Mandas",
    "iso:country":"ES",
    "sg:address":"Pase Duque De Mandas, 45",
    "sg:city":"Donostia-san Sebastian",
    "sg:orig_category":"Bisuter\u00cda, Joyer\u00cda, Relojer\u00cda (al Por Menor)",
    "sg:phone":"+34 943 27 50 18",
    "sg:postcode":"20012",
    "sg:province":"Guip\u00f9zcoa",
    "wof:name":"Hermanos Zabalegui C.b.",
    "wof:placetype":"venue"
},
  "geometry": {"coordinates":[-1.9794000387,43.3173789978],"type":"Point"}
}