{
  "type": "Feature",
  "properties": {
    "iso:country":"ES",
    "sg:address":"Calle de Canalejas, 12",
    "sg:city":"Arrecife",
    "sg:orig_category":"Inmobiliaria (agencias)",
    "sg:phone":"+34 928 80 07 17",
    "sg:postcode":"35500",
    "sg:province":"Las Palmas",
    "wof:name":"I.g. Integral S.l.",
    "wof:placetype":"venue"
},
  "geometry": {"coordinates":[-13.5523099899,28.9584407806],"type":"Point"}
}