{
  "type": "Feature",
  "properties": {
    "iso:country":"ES",
    "sg:address":"Alameda Alfonso Xii, S/n",
    "sg:city":"Carmona",
    "sg:orig_category":"Lecher\u00cdas",
    "sg:phone":"+34 954 19 08 84",
    "sg:postcode":"41410",
    "sg:province":"Sevilla",
    "wof:name":"Explotacion Ganadera Hermanos Romeros S.c.",
    "wof:placetype":"venue"
},
  "geometry": {"coordinates":[-5.6417770386,37.4687156677],"type":"Point"}
}