{
  "type": "Feature",
  "properties": {
    "iso:country":"ES",
    "sg:address":"Calle de Mayor, 27",
    "sg:city":"Teruel",
    "sg:orig_category":"Alimentaci\u00d3n General (al Por Menor)",
    "sg:phone":"+34 978 60 40 29",
    "sg:postcode":"44003",
    "sg:province":"Teruel",
    "wof:name":"Martin Villarroya Pascual",
    "wof:placetype":"venue"
},
  "geometry": {"coordinates":[-1.1039750576,40.345199585],"type":"Point"}
}