{
  "type": "Feature",
  "properties": {
    "addr:full":"Llano Morales, S/n Torredonjimeno Ja\u00e9n 23650",
    "addr:housenumber":"s / n",
    "addr:postcode":"23650",
    "iso:country":"ES",
    "sg:address":"Llano Morales, S/n",
    "sg:city":"Torredonjimeno",
    "sg:orig_category":"Droguer\u00cdas (al Por Menor)",
    "sg:phone":"+34 953 57 20 60",
    "sg:postcode":"23650",
    "sg:province":"Ja\u00e9n",
    "wof:name":"Almacenes Illana S.l.",
    "wof:placetype":"venue"
},
  "geometry": {"coordinates":[-3.9622430801,37.7702980042],"type":"Point"}
}