{
  "type": "Feature",
  "properties": {
    "addr:full":"Calle de Agirre Miramon, 5 Donostia-san Sebastian Guip\u00f9zcoa 20002",
    "addr:housenumber":"5",
    "addr:postcode":"20002",
    "addr:street":"Calle De Agirre Miramon",
    "iso:country":"ES",
    "sg:address":"Calle de Agirre Miramon, 5",
    "sg:city":"Donostia-san Sebastian",
    "sg:orig_category":"Comercio, Reparaci\u00d3n De Motocicletas, Bicicletas Y Piezas Sueltas",
    "sg:phone":"+34 943 28 66 18",
    "sg:postcode":"20002",
    "sg:province":"Guip\u00f9zcoa",
    "wof:name":"Stilmoto Guipuzcoa S. L.",
    "wof:placetype":"venue"
},
  "geometry": {"coordinates":[-1.9779210091,43.3227043152],"type":"Point"}
}