{
  "type": "Feature",
  "properties": {
    "addr:full":"Avda Antonio Alzaga, 51 Santurtzi Vizcaya 48980",
    "addr:housenumber":"51",
    "addr:postcode":"48980",
    "addr:street":"Avda Antonio Alzaga",
    "iso:country":"ES",
    "sg:address":"Avda Antonio Alzaga, 51",
    "sg:city":"Santurtzi",
    "sg:orig_category":"Plomeros",
    "sg:phone":"+34 944 83 47 61",
    "sg:postcode":"48980",
    "sg:province":"Vizcaya",
    "wof:name":"Martinez Martinez Esteban",
    "wof:placetype":"venue"
},
  "geometry": {"coordinates":[-3.0382618904,43.3219223022],"type":"Point"}
}