{
  "type": "Feature",
  "properties": {
    "iso:country":"ES",
    "sg:address":"Carrer de Sant Carles, 20",
    "sg:city":"Barcelona",
    "sg:orig_category":"Laboratorios Y Cl\u00cdnicas Veterinarias",
    "sg:phone":"+34 932 21 50 69",
    "sg:postcode":"08003",
    "sg:province":"Barcelona",
    "wof:name":"Anso Clinicas Veterinarias,s.c.p.",
    "wof:placetype":"venue"
},
  "geometry": {"coordinates":[2.1897566319,41.3792304993],"type":"Point"}
}