{
  "type": "Feature",
  "properties": {
    "iso:country":"ES",
    "sg:address":"Cruce De Mohedas, S/n",
    "sg:city":"Mohedas",
    "sg:orig_category":"Empresas De Carpinter\u00cda",
    "sg:phone":"+34 927 67 35 73",
    "sg:postcode":"10664",
    "sg:province":"C\u00e1ceres",
    "wof:name":"Mari Sabata Laura",
    "wof:placetype":"venue"
},
  "geometry": {"coordinates":[-6.2028841972,40.2671508789],"type":"Point"}
}