{
  "type": "Feature",
  "properties": {
    "addr:full":"Avgd Catalunya, S/n Badalona Barcelona 08917",
    "addr:housenumber":"s / n",
    "addr:postcode":"08917",
    "iso:country":"ES",
    "sg:address":"Avgd Catalunya, S/n",
    "sg:city":"Badalona",
    "sg:orig_category":"Asilos De Ancianos. Centros Privados",
    "sg:phone":"+34 933 83 01 57",
    "sg:postcode":"08917",
    "sg:province":"Barcelona",
    "wof:name":"Mutual Gestion Integral S.l.",
    "wof:placetype":"venue"
},
  "geometry": {"coordinates":[2.2299849987,41.4530563354],"type":"Point"}
}