{
  "type": "Feature",
  "properties": {
    "iso:country":"ES",
    "sg:address":"Calle de Alamicos, 79",
    "sg:city":"Cantoria",
    "sg:orig_category":"Transportes Por V\u00cdas Navegables",
    "sg:phone":"+34 950 43 61 67",
    "sg:postcode":"04850",
    "sg:province":"Almer\u00eda",
    "wof:name":"Transportes Diaz Granero S.l.",
    "wof:placetype":"venue"
},
  "geometry": {"coordinates":[-2.1955659389,37.3529014587],"type":"Point"}
}