{
  "type": "Feature",
  "properties": {
    "iso:country":"ES",
    "sg:address":"Calle de Corona De Aragon, 13",
    "sg:city":"Barbastro",
    "sg:orig_category":"Complementos De Vestir (al Por Menor)",
    "sg:phone":"+34 974 31 29 82",
    "sg:postcode":"22300",
    "sg:province":"Huesca",
    "wof:name":"Ayape Rull Maria Teresa",
    "wof:placetype":"venue"
},
  "geometry": {"coordinates":[0.1278209984,42.036026001],"type":"Point"}
}