{
  "type": "Feature",
  "properties": {
    "addr:full":"Calle de San Damian, 12 Cuenca Cuenca 16003",
    "addr:housenumber":"12",
    "addr:postcode":"16003",
    "addr:street":"Calle De San Damian",
    "iso:country":"ES",
    "sg:address":"Calle de San Damian, 12",
    "sg:city":"Cuenca",
    "sg:orig_category":"Hoteles",
    "sg:phone":"+34 969 22 90 82",
    "sg:postcode":"16003",
    "sg:province":"Cuenca",
    "wof:name":"Sevilla Olivares Carmen",
    "wof:placetype":"venue"
},
  "geometry": {"coordinates":[-2.1477160454,40.0704498291],"type":"Point"}
}