{
  "type": "Feature",
  "properties": {
    "iso:country":"ES",
    "sg:address":"Mont-roig, S/n",
    "sg:city":"Cambrils",
    "sg:orig_category":"Material Y Suministros Para Horticultura, Arboricultura",
    "sg:phone":"+34 977 36 20 01",
    "sg:postcode":"43850",
    "sg:province":"Tarragona",
    "wof:name":"Horticultura Bellmunt S. A.",
    "wof:placetype":"venue"
},
  "geometry": {"coordinates":[1.0671700239,41.0676651001],"type":"Point"}
}