{
  "type": "Feature",
  "properties": {
    "addr:full":"Plaz Americas, 8 Badajoz Badajoz 06011",
    "addr:housenumber":"8",
    "addr:postcode":"06011",
    "addr:street":"Plaz Americas",
    "iso:country":"ES",
    "sg:address":"Plaz Americas, 8",
    "sg:city":"Badajoz",
    "sg:orig_category":"Moda",
    "sg:phone":"+34 924 26 23 68",
    "sg:postcode":"06011",
    "sg:province":"Badajoz",
    "wof:name":"Calzados Kast'y Sl.",
    "wof:placetype":"venue"
},
  "geometry": {"coordinates":[-7.1200389862,38.803768158],"type":"Point"}
}