{
  "type": "Feature",
  "properties": {
    "addr:full":"Pase General Davila, 138 Santander Cantabria 39006",
    "addr:housenumber":"138",
    "addr:postcode":"39006",
    "iso:country":"ES",
    "sg:address":"Pase General Davila, 138",
    "sg:city":"Santander",
    "sg:orig_category":"Cl\u00cdnicas Dentales",
    "sg:phone":"+34 942 21 83 31",
    "sg:postcode":"39006",
    "sg:province":"Cantabria",
    "wof:name":"Clinica Dental Prado San Roque S.c.",
    "wof:placetype":"venue"
},
  "geometry": {"coordinates":[-3.8076050282,43.4673347473],"type":"Point"}
}