{
  "type": "Feature",
  "properties": {
    "iso:country":"ES",
    "sg:address":"Calle de Blasco De Garay, 55",
    "sg:city":"Madrid",
    "sg:orig_category":"Psic\u00d3logos",
    "sg:phone":"+34 915 43 76 22",
    "sg:postcode":"28015",
    "sg:province":"Madrid",
    "wof:name":"Sanchez-palencia Ramos Santiago",
    "wof:placetype":"venue"
},
  "geometry": {"coordinates":[-3.7113456726,40.4365158081],"type":"Point"}
}