{
  "type": "Feature",
  "properties": {
    "addr:full":"Carr Manacor, De, 19 Campos Islas Baleares 07630",
    "addr:postcode":"07630",
    "addr:street":"Carr",
    "iso:country":"ES",
    "sg:address":"Carr Manacor, De, 19",
    "sg:city":"Campos",
    "sg:orig_category":"Reposter\u00cdas",
    "sg:phone":"+34 971 65 23 24",
    "sg:postcode":"07630",
    "sg:province":"Islas Baleares",
    "wof:name":"Vadell Tomas Gabriel",
    "wof:placetype":"venue"
},
  "geometry": {"coordinates":[3.0143458843,39.4343414307],"type":"Point"}
}