{
  "type": "Feature",
  "properties": {
    "iso:country":"ES",
    "sg:address":"Av. Quinta (urb Cinco Estrellas), S/n",
    "sg:city":"El Catllar",
    "sg:orig_category":"Centros Empresariales",
    "sg:phone":"+34 977 62 63 39",
    "sg:postcode":"43764",
    "sg:province":"Tarragona",
    "wof:name":"Aguirre Alava Gurutze",
    "wof:placetype":"venue"
},
  "geometry": {"coordinates":[1.2987349033,41.183139801],"type":"Point"}
}