{
  "type": "Feature",
  "properties": {
    "iso:country":"ES",
    "sg:address":"Calle de Nazaret, 1",
    "sg:city":"Coru\u00d1a",
    "sg:orig_category":"Concepci\u00d3n Y Realizaci\u00d3n De Maquetas Profesionales Y Prototipos",
    "sg:phone":"+34 981 23 73 09",
    "sg:postcode":"15007",
    "sg:province":"La Coru\u00f1a",
    "wof:name":"Rodriguez Arias Carlos",
    "wof:placetype":"venue"
},
  "geometry": {"coordinates":[-8.7951183319,42.9959411621],"type":"Point"}
}