{
  "type": "Feature",
  "properties": {
    "iso:country":"ES",
    "sg:address":"Ctra. Cuenca, S/n",
    "sg:city":"Torre Baja",
    "sg:orig_category":"Mataderos Y Talleres De Despiezado",
    "sg:phone":"+34 978 78 30 34",
    "sg:postcode":"46143",
    "sg:province":"Valencia",
    "wof:name":"Carnes Rosello S.l.",
    "wof:placetype":"venue"
},
  "geometry": {"coordinates":[-1.2601009607,40.0947799683],"type":"Point"}
}