{
  "type": "Feature",
  "properties": {
    "addr:full":"Calle de Calderon, 6 Denia Alicante 03700",
    "addr:housenumber":"6",
    "addr:postcode":"03700",
    "addr:street":"Calle De Calderon",
    "iso:country":"ES",
    "sg:address":"Calle de Calderon, 6",
    "sg:city":"Denia",
    "sg:orig_category":"Abogados",
    "sg:phone":"+34 966 42 08 62",
    "sg:postcode":"03700",
    "sg:province":"Alicante",
    "wof:name":"Perez Lopez Juan Bernardo",
    "wof:placetype":"venue"
},
  "geometry": {"coordinates":[0.1113929972,38.8407363892],"type":"Point"}
}