{
  "type": "Feature",
  "properties": {
    "iso:country":"ES",
    "sg:address":"Carr Vinya Del Mar, De La, 29",
    "sg:city":"Cala Millor",
    "sg:orig_category":"Servicios Gsm",
    "sg:phone":"+34 971 81 42 05",
    "sg:postcode":"07560",
    "sg:province":"Islas Baleares",
    "wof:name":"Multiempre S.l.",
    "wof:placetype":"venue"
},
  "geometry": {"coordinates":[3.3823208809,39.6012229919],"type":"Point"}
}