{
  "type": "Feature",
  "properties": {
    "addr:full":"Calle de Modesto Lafuente, 43 Aguilar Campoo Palencia 34800",
    "addr:housenumber":"43",
    "addr:postcode":"34800",
    "addr:street":"Calle De Modesto Lafuente",
    "iso:country":"ES",
    "sg:address":"Calle de Modesto Lafuente, 43",
    "sg:city":"Aguilar Campoo",
    "sg:orig_category":"Consultas M\u00c9dicas",
    "sg:phone":"+34 979 12 24 25",
    "sg:postcode":"34800",
    "sg:province":"Palencia",
    "wof:name":"Clinica Aguilar S.l.",
    "wof:placetype":"venue"
},
  "geometry": {"coordinates":[-4.2625288963,42.7944412231],"type":"Point"}
}