{
  "type": "Feature",
  "properties": {
    "iso:country":"ES",
    "sg:address":"Calle de Epifanio Lupion, 18",
    "sg:city":"Albu\u00f1ol",
    "sg:orig_category":"Iglesia Cat\u00d3lica",
    "sg:phone":"+34 958 82 60 35",
    "sg:postcode":"18700",
    "sg:province":"Granada",
    "wof:name":"Parroquia De San Patricio",
    "wof:placetype":"venue"
},
  "geometry": {"coordinates":[-3.2017612457,36.7909851074],"type":"Point"}
}