{
  "type": "Feature",
  "properties": {
    "addr:full":"P Mu\u00f1oz Torres, 2 Sevilla Sevilla 41005",
    "addr:housenumber":"2",
    "addr:postcode":"41005",
    "addr:street":"Torres",
    "iso:country":"ES",
    "sg:address":"P Mu\u00f1oz Torres, 2",
    "sg:city":"Sevilla",
    "sg:orig_category":"Fabricaci\u00d3n, Importaci\u00d3n De L\u00c1mparas Y Bombillas",
    "sg:phone":"+34 954 92 04 93",
    "sg:postcode":"41005",
    "sg:province":"Sevilla",
    "wof:name":"Manuel Martin Caballero S.l.",
    "wof:placetype":"venue"
},
  "geometry": {"coordinates":[-5.9841809273,37.3936767578],"type":"Point"}
}