{
  "type": "Feature",
  "properties": {
    "addr:full":"Calle de Chiva, 16 Valencia Valencia 46018",
    "addr:housenumber":"16",
    "addr:postcode":"46018",
    "addr:street":"Calle De Chiva",
    "iso:country":"ES",
    "sg:address":"Calle de Chiva, 16",
    "sg:city":"Valencia",
    "sg:orig_category":"Cursos Particulares, Asistencia Escolar",
    "sg:phone":"+34 963 84 08 44",
    "sg:postcode":"46018",
    "sg:province":"Valencia",
    "wof:name":"Boodhoo  Dharumdeo",
    "wof:placetype":"venue"
},
  "geometry": {"coordinates":[-0.3902570009,39.4653968811],"type":"Point"}
}