{
  "type": "Feature",
  "properties": {
    "addr:full":"Ctra Calaf (de), S/n Ponts Lleida 25740",
    "addr:postcode":"25740",
    "addr:street":"Ctra Calaf De S / N",
    "iso:country":"ES",
    "sg:address":"Ctra Calaf (de), S/n",
    "sg:city":"Ponts",
    "sg:orig_category":"Mec\u00c1nico Del Autom\u00d3vil",
    "sg:phone":"+34 973 46 10 68",
    "sg:postcode":"25740",
    "sg:province":"Lleida",
    "wof:name":"Jose Serra Llordes Y Jaime Cinca Torrent C.b.",
    "wof:placetype":"venue"
},
  "geometry": {"coordinates":[1.1891249418,41.912021637],"type":"Point"}
}