{
  "type": "Feature",
  "properties": {
    "addr:full":"Afores, S/n S. Privat Bas Girona 17178",
    "addr:housenumber":"s",
    "addr:postcode":"17178",
    "addr:street":"Afores;/ N S. Privat Bas Girona",
    "iso:country":"ES",
    "sg:address":"Afores, S/n",
    "sg:city":"S. Privat Bas",
    "sg:orig_category":"Ense\u00d1anza, Formaci\u00d3n Profesional: Aprendizaje",
    "sg:phone":"+34 972 69 32 02",
    "sg:postcode":"17178",
    "sg:province":"Girona",
    "wof:name":"Ajuntament De La Vall D'en Bas",
    "wof:placetype":"venue"
},
  "geometry": {"coordinates":[2.4570012093,42.1183547974],"type":"Point"}
}