{
  "type": "Feature",
  "properties": {
    "addr:full":"Calle de Plomo, 17 Estacion Madrid 28400",
    "addr:housenumber":"17 estacion",
    "addr:postcode":"28400",
    "addr:street":"Calle De Plomo",
    "iso:country":"ES",
    "sg:address":"Calle de Plomo, 17",
    "sg:city":"Estacion",
    "sg:orig_category":"Papel (al Por Mayor)",
    "sg:phone":"+34 918 51 51 28",
    "sg:postcode":"28400",
    "sg:province":"Madrid",
    "wof:name":"Kovi Tecnica S.l.",
    "wof:placetype":"venue"
},
  "geometry": {"coordinates":[-4.0212111473,40.6256332397],"type":"Point"}
}