{
  "type": "Feature",
  "properties": {
    "addr:full":"Calle de Federico Mayor Zaragoza, 10 Cuenca Cuenca 16002",
    "addr:housenumber":"10",
    "addr:postcode":"16002",
    "addr:street":"Calle De Federico Mayor Zaragoza",
    "iso:country":"ES",
    "sg:address":"Calle de Federico Mayor Zaragoza, 10",
    "sg:city":"Cuenca",
    "sg:orig_category":"M\u00c9dicos: Alergolog\u00cda",
    "sg:phone":"+34 969 22 62 60",
    "sg:postcode":"16002",
    "sg:province":"Cuenca",
    "wof:name":"Viojumila Alergias S.l.",
    "wof:placetype":"venue"
},
  "geometry": {"coordinates":[-2.1493039131,40.0727653503],"type":"Point"}
}