{
  "type": "Feature",
  "properties": {
    "addr:full":"Calle de Miguel Iscar, 5 Valladolid Valladolid 47001",
    "addr:housenumber":"5",
    "addr:postcode":"47001",
    "addr:street":"Calle De Miguel Iscar",
    "iso:country":"ES",
    "sg:address":"Calle de Miguel Iscar, 5",
    "sg:city":"Valladolid",
    "sg:orig_category":"\u00d3ptica: Instrumentos (fabricaci\u00d3n)",
    "sg:phone":"+34 983 35 74 99",
    "sg:postcode":"47001",
    "sg:province":"Valladolid",
    "wof:name":"Santos Bobillo Jose Luis",
    "wof:placetype":"venue"
},
  "geometry": {"coordinates":[-4.7284941673,41.6484527588],"type":"Point"}
}