{
  "type": "Feature",
  "properties": {
    "addr:full":"Luga Campons, 12 Campons La Coru\u00f1a 15181",
    "addr:housenumber":"12",
    "addr:postcode":"15181",
    "addr:street":"Campons;La Corun\u0303A",
    "iso:country":"ES",
    "sg:address":"Luga Campons, 12",
    "sg:city":"Campons",
    "sg:orig_category":"Chapister\u00cda",
    "sg:phone":"+34 981 67 45 15",
    "sg:postcode":"15181",
    "sg:province":"La Coru\u00f1a",
    "wof:name":"Iglesias Naya Josefina",
    "wof:placetype":"venue"
},
  "geometry": {"coordinates":[-8.3443889618,43.291721344],"type":"Point"}
}