{
  "type": "Feature",
  "properties": {
    "iso:country":"ES",
    "sg:address":"Calle de Escritor Castilla Aguayo, 4",
    "sg:city":"Cordoba",
    "sg:orig_category":"Universidades",
    "sg:phone":"+34 957 22 21 00",
    "sg:postcode":"14...",
    "sg:province":"C\u00f3rdoba",
    "sg:website":"www.etea.com",
    "wof:name":"Instituto Social Agrario",
    "wof:placetype":"venue"
},
  "geometry": {"coordinates":[-4.7884635925,37.86901474],"type":"Point"}
}