{
  "type": "Feature",
  "properties": {
    "addr:full":"Av Torrent Gornal, 68 Hospitalet Llobregat Barcelona 08904",
    "addr:housenumber":"68",
    "addr:postcode":"08904",
    "addr:street":"Av;Gornal",
    "iso:country":"ES",
    "sg:address":"Av Torrent Gornal, 68",
    "sg:city":"Hospitalet Llobregat",
    "sg:orig_category":"Panader\u00cdas, Panader\u00cdas",
    "sg:phone":"+34 933 33 83 38",
    "sg:postcode":"08904",
    "sg:province":"Barcelona",
    "wof:name":"Gutierrez Quijada Manuel",
    "wof:placetype":"venue"
},
  "geometry": {"coordinates":[2.1138939857,41.3721084595],"type":"Point"}
}