{
  "type": "Feature",
  "properties": {
    "addr:full":"Barr Nuevo, 9 Pradera Navalhorno Segovia 40100",
    "addr:housenumber":"9",
    "addr:postcode":"40100",
    "addr:street":"Nuevo",
    "iso:country":"ES",
    "sg:address":"Barr Nuevo, 9",
    "sg:city":"Pradera Navalhorno",
    "sg:orig_category":"Promotores Constructores",
    "sg:phone":"+34 921 47 02 23",
    "sg:postcode":"40100",
    "sg:province":"Segovia",
    "wof:name":"Abad Dorrego Pedro",
    "wof:placetype":"venue"
},
  "geometry": {"coordinates":[-4.119209,40.949429],"type":"Point"}
}