{
  "type": "Feature",
  "properties": {
    "iso:country":"ES",
    "sg:address":"Calle de Juan Antonio Fernandez, 22",
    "sg:city":"Tudela",
    "sg:orig_category":"Muebles, Minoristas",
    "sg:phone":"+34 948 82 19 43",
    "sg:postcode":"31500",
    "sg:province":"Navarra",
    "wof:name":"Muebles Eneriz S.l.",
    "wof:placetype":"venue"
},
  "geometry": {"coordinates":[-1.6041599512,42.0598907471],"type":"Point"}
}