{
  "type": "Feature",
  "properties": {
    "addr:full":"Calle de Comandante Izarduy, 30 Vitoria-gasteiz \u00c1lava 01006",
    "addr:housenumber":"30",
    "addr:postcode":"01006",
    "addr:street":"Calle De Comandante Izarduy",
    "iso:country":"ES",
    "sg:address":"Calle de Comandante Izarduy, 30",
    "sg:city":"Vitoria-gasteiz",
    "sg:orig_category":"Farmacias",
    "sg:phone":"+34 945 13 61 31",
    "sg:postcode":"01006",
    "sg:province":"\u00c1lava",
    "wof:name":"Farmacia Manuel Rivero",
    "wof:placetype":"venue"
},
  "geometry": {"coordinates":[-2.6692512035,42.8364143372],"type":"Point"}
}