{
  "type": "Feature",
  "properties": {
    "iso:country":"ES",
    "sg:address":"Avda Marques De Figueroa, 1",
    "sg:city":"Ameneiral",
    "sg:orig_category":"M\u00c9dicos: Estomatolog\u00cda",
    "sg:phone":"+34 981 34 02 60",
    "sg:postcode":"15500",
    "sg:province":"A Coru\u00f1a",
    "wof:name":"Santagada Fox Jorge Alberto",
    "wof:placetype":"venue"
},
  "geometry": {"coordinates":[-8.1644191742,43.4750747681],"type":"Point"}
}