{
  "type": "Feature",
  "properties": {
    "addr:full":"Calle de Jaume I, 1 Paiporta Valencia 46200",
    "addr:housenumber":"1",
    "addr:postcode":"46200",
    "addr:street":"Calle De Jaume I",
    "iso:country":"ES",
    "sg:address":"Calle de Jaume I, 1",
    "sg:city":"Paiporta",
    "sg:orig_category":"\u00d3ptica: Instrumentos (fabricaci\u00d3n)",
    "sg:phone":"+34 963 97 22 36",
    "sg:postcode":"46200",
    "sg:province":"Valencia",
    "wof:name":"Centro De Vision Valencianos S. L.",
    "wof:placetype":"venue"
},
  "geometry": {"coordinates":[-0.4173670113,39.4301300049],"type":"Point"}
}