{
  "type": "Feature",
  "properties": {
    "addr:full":"Carrer de Ventura Gassol, 29 Masnou Barcelona 08320",
    "addr:housenumber":"29",
    "addr:postcode":"08320",
    "addr:street":"Carrer De Ventura Gassol",
    "iso:country":"ES",
    "sg:address":"Carrer de Ventura Gassol, 29",
    "sg:city":"Masnou",
    "sg:orig_category":"Guarder\u00cdas",
    "sg:phone":"+34 935 55 57 11",
    "sg:postcode":"08320",
    "sg:province":"Barcelona",
    "wof:name":"Duran Mas Carmen",
    "wof:placetype":"venue"
},
  "geometry": {"coordinates":[2.3092300892,41.4802970886],"type":"Point"}
}