{
  "type": "Feature",
  "properties": {
    "addr:full":"Calle de Pedro Castillo Westerling, 5 Palmas De Gran Canaria Las Palmas 35008",
    "addr:housenumber":"5",
    "addr:postcode":"35008",
    "addr:street":"Calle De Pedro Castillo Westerling",
    "iso:country":"ES",
    "sg:address":"Calle de Pedro Castillo Westerling, 5",
    "sg:city":"Palmas De Gran Canaria",
    "sg:orig_category":"Distribuci\u00d3n De Petr\u00d3leo Y Derivados",
    "sg:phone":"+34 928 27 96 02",
    "sg:postcode":"35008",
    "sg:province":"Las Palmas",
    "sg:website":"www.sanguzvel.com",
    "wof:name":"Sanchez Y Guzman S.a.",
    "wof:placetype":"venue"
},
  "geometry": {"coordinates":[-15.4303722382,28.1433849335],"type":"Point"}
}