{
  "type": "Feature",
  "properties": {
    "addr:full":"Calle de Anzuola, 2 Madrid Madrid 28002",
    "addr:housenumber":"2",
    "addr:postcode":"28002",
    "addr:street":"Calle De Anzuola",
    "iso:country":"ES",
    "sg:address":"Calle de Anzuola, 2",
    "sg:city":"Madrid",
    "sg:orig_category":"Asesor\u00cda Fiscal Y Jur\u00cddica",
    "sg:phone":"+34 914 13 06 55",
    "sg:postcode":"28002",
    "sg:province":"Madrid",
    "sg:website":"www.sindicatodelcobro.com",
    "wof:name":"Sindicato De Cobro",
    "wof:placetype":"venue"
},
  "geometry": {"coordinates":[-3.670855999,40.4428672791],"type":"Point"}
}