{
  "type": "Feature",
  "properties": {
    "iso:country":"ES",
    "sg:address":"Calle de Llano De Sierra, S/n",
    "sg:city":"Arrieta",
    "sg:orig_category":"Distribuci\u00d3n De Petr\u00d3leo Y Derivados",
    "sg:phone":"+34 928 84 80 80",
    "sg:postcode":"35542",
    "sg:province":"Las Palmas",
    "wof:name":"Hermanos Betancort Hernandez S.l.",
    "wof:placetype":"venue"
},
  "geometry": {"coordinates":[-13.4617147446,29.1312942505],"type":"Point"}
}