{
  "type": "Feature",
  "properties": {
    "addr:full":"C/ Olot, 11 Urbanitzacio Vescomtat De Cabanyes Girona 17251",
    "addr:housenumber":"11",
    "addr:postcode":"17251",
    "addr:street":"C / Olot",
    "iso:country":"ES",
    "sg:address":"C/ Olot, 11",
    "sg:city":"Urbanitzacio Vescomtat De Cabanyes",
    "sg:orig_category":"Material Y Suministros Para Perforaciones, Sondeos",
    "sg:phone":"+34 972 66 07 99",
    "sg:postcode":"17251",
    "sg:province":"Girona",
    "wof:name":"Martinez Mellado Angel",
    "wof:placetype":"venue"
},
  "geometry": {"coordinates":[3.07406497,41.861656189],"type":"Point"}
}