{
  "type": "Feature",
  "properties": {
    "addr:full":"Plaz Santo Domingo De Guzman, 9 Valencia Valencia 46017",
    "addr:housenumber":"9",
    "addr:postcode":"46017",
    "addr:street":"Guzman",
    "iso:country":"ES",
    "sg:address":"Plaz Santo Domingo De Guzman, 9",
    "sg:city":"Valencia",
    "sg:orig_category":"M\u00c1rmoles, Granitos Y Piedras Naturales",
    "sg:phone":"+34 963 77 21 80",
    "sg:postcode":"46017",
    "sg:province":"Valencia",
    "wof:name":"Teruel Izquierdo Francisco",
    "wof:placetype":"venue"
},
  "geometry": {"coordinates":[-0.39567101,39.4473342896],"type":"Point"}
}