{
  "type": "Feature",
  "properties": {
    "addr:full":"Calle de Luisa Fernanda, 23 Madrid Madrid 28008",
    "addr:housenumber":"23",
    "addr:postcode":"madrid;28008",
    "addr:street":"Calle De Luisa Fernanda",
    "iso:country":"ES",
    "sg:address":"Calle de Luisa Fernanda, 23",
    "sg:city":"Madrid",
    "sg:orig_category":"Caf\u00c9s, Bares, Cervecer\u00cdas",
    "sg:phone":"+34 915 47 45 15",
    "sg:postcode":"28008",
    "sg:province":"Madrid",
    "sg:website":"www.vienacapellanes.com",
    "wof:name":"Viena Reposteria Capellanes S. A.",
    "wof:placetype":"venue"
},
  "geometry": {"coordinates":[-3.7153749466,40.4251213074],"type":"Point"}
}