{
  "type": "Feature",
  "properties": {
    "addr:full":"Carr Ciutat De Pamplona, 61 Sueca Valencia 46410",
    "addr:housenumber":"61",
    "addr:postcode":"46410",
    "addr:street":"Carr Ciutat De Pamplona",
    "iso:country":"ES",
    "sg:address":"Carr Ciutat De Pamplona, 61",
    "sg:city":"Sueca",
    "sg:orig_category":"Inmobiliaria (agencias)",
    "sg:phone":"+34 961 71 00 95",
    "sg:postcode":"46410",
    "sg:province":"Valencia",
    "wof:name":"Promotora Cab De Faro Sl",
    "wof:placetype":"venue"
},
  "geometry": {"coordinates":[-0.2987889946,39.1995811462],"type":"Point"}
}