{
  "type": "Feature",
  "properties": {
    "iso:country":"ES",
    "sg:address":"Urb Zahonera (la), 78",
    "sg:city":"Estacion Ferrea",
    "sg:orig_category":"Electricidad: Instaladores",
    "sg:phone":"+34 956 78 60 78",
    "sg:postcode":"11368",
    "sg:province":"C\u00e1diz",
    "wof:name":"Umbria Perales Juan",
    "wof:placetype":"venue"
},
  "geometry": {"coordinates":[-5.4333500862,36.2157821655],"type":"Point"}
}