{
  "type": "Feature",
  "properties": {
    "addr:full":"Calle de Gobelaurre, 15 Getxo Vizcaya 48930",
    "addr:housenumber":"15",
    "addr:postcode":"48930",
    "addr:street":"Calle De Gobelaurre",
    "iso:country":"ES",
    "sg:address":"Calle de Gobelaurre, 15",
    "sg:city":"Getxo",
    "sg:orig_category":"Cristaler\u00cdas",
    "sg:phone":"+34 944 63 56 84",
    "sg:postcode":"48930",
    "sg:province":"Vizcaya",
    "wof:name":"Carlos Mateo Iglesias",
    "wof:placetype":"venue"
},
  "geometry": {"coordinates":[-3.0068490505,43.3258285522],"type":"Point"}
}