{
  "type": "Feature",
  "properties": {
    "iso:country":"ES",
    "sg:address":"Calle de General Medrano De Miguel, 12",
    "sg:city":"Guadalajara",
    "sg:orig_category":"Venta, Instalaci\u00d3n De Calefacci\u00d3n",
    "sg:phone":"+34 949 22 33 43",
    "sg:postcode":"19003",
    "sg:province":"Guadalajara",
    "wof:name":"Sociedad Cooperativa De Consumo Calorcope",
    "wof:placetype":"venue"
},
  "geometry": {"coordinates":[-3.1743659973,40.6310462952],"type":"Point"}
}