{
  "type": "Feature",
  "properties": {
    "addr:full":"El Medio, S/n Val San Lorenzo Le\u00f3n 24717",
    "addr:housenumber":"s / n",
    "addr:postcode":"24717",
    "addr:street":"El Medio;Leo\u0301N",
    "iso:country":"ES",
    "sg:address":"El Medio, S/n",
    "sg:city":"Val San Lorenzo",
    "sg:orig_category":"Maquinaria Para Industrias Diversas",
    "sg:phone":"+34 987 63 51 21",
    "sg:postcode":"24717",
    "sg:province":"Le\u00f3n",
    "wof:name":"Martinez Perez Manuel",
    "wof:placetype":"venue"
},
  "geometry": {"coordinates":[-6.1217088699,42.4166603088],"type":"Point"}
}