{
  "type": "Feature",
  "properties": {
    "addr:full":"Pg Carretera, 17 Benidorm Alicante 03500",
    "addr:housenumber":"17",
    "addr:postcode":"03500",
    "addr:street":"Carretera",
    "iso:country":"ES",
    "sg:address":"Pg Carretera, 17",
    "sg:city":"Benidorm",
    "sg:orig_category":"M\u00c9dicos: Oftalmolog\u00cda",
    "sg:phone":"+34 966 80 44 11",
    "sg:postcode":"03500",
    "sg:province":"Alicante",
    "sg:website":"www.clinicapalomares.com",
    "wof:name":"Centro Oftalmologico Altea S.l.",
    "wof:placetype":"venue"
},
  "geometry": {"coordinates":[-0.1304910034,38.5364303589],"type":"Point"}
}