{
  "type": "Feature",
  "properties": {
    "iso:country":"ES",
    "sg:address":"Calle de Virgen De Los Milagros, 70",
    "sg:city":"Puerto De Santa Maria",
    "sg:orig_category":"Inmobiliaria (agencias)",
    "sg:phone":"+34 956 85 19 36",
    "sg:postcode":"11500",
    "sg:province":"C\u00e1diz",
    "sg:website":"www.larga70.com",
    "wof:name":"Murol S.a.",
    "wof:placetype":"venue"
},
  "geometry": {"coordinates":[-6.2242059708,36.6007118225],"type":"Point"}
}