{
  "type": "Feature",
  "properties": {
    "iso:country":"ES",
    "sg:address":"Pl Ind Campo Alto, S/n",
    "sg:city":"Elda",
    "sg:orig_category":"Carnes De Carnicer\u00cda (al Por Mayor)",
    "sg:phone":"+34 965 39 07 65",
    "sg:postcode":"03600",
    "sg:province":"Alicante",
    "wof:name":"Almacen Frigorifico Hermanos Requena S.l.",
    "wof:placetype":"venue"
},
  "geometry": {"coordinates":[-0.7904639244,38.4780349731],"type":"Point"}
}