{
  "type": "Feature",
  "properties": {
    "iso:country":"ES",
    "sg:address":"Carrer de Constitucio, 156",
    "sg:city":"Barcelona",
    "sg:orig_category":"Confecci\u00d3n De Trajes Para Se\u00d1oras",
    "sg:phone":"+34 934 21 94 13",
    "sg:postcode":"08014",
    "sg:province":"Barcelona",
    "wof:name":"Espinosa Vico Maria Dolores",
    "wof:placetype":"venue"
},
  "geometry": {"coordinates":[2.1323680878,41.3688430786],"type":"Point"}
}