{
  "type": "Feature",
  "properties": {
    "iso:country":"ES",
    "sg:address":"Calle de Alcadozo, 7",
    "sg:city":"Albacete",
    "sg:orig_category":"Fabricaci\u00d3n De Enlosados, Soler\u00cdas",
    "sg:phone":"+34 967 50 25 98",
    "sg:postcode":"02006",
    "sg:province":"Albacete",
    "wof:name":"Azulejos Y Pavimentos El Moro S.l.",
    "wof:placetype":"venue"
},
  "geometry": {"coordinates":[-1.8693760633,38.9777412415],"type":"Point"}
}