{
  "type": "Feature",
  "properties": {
    "addr:full":"Carrer de Consell De Cent, 573 Barcelona Barcelona 08013",
    "addr:housenumber":"573",
    "addr:postcode":"08013",
    "addr:street":"Carrer De Consell De Cent",
    "iso:country":"ES",
    "sg:address":"Carrer de Consell De Cent, 573",
    "sg:city":"Barcelona",
    "sg:orig_category":"Farmacias",
    "sg:phone":"+34 932 31 52 60",
    "sg:postcode":"08013",
    "sg:province":"Barcelona",
    "wof:name":"Xuriguera Hernandez Javier",
    "wof:placetype":"venue"
},
  "geometry": {"coordinates":[2.1834135056,41.4043884277],"type":"Point"}
}