{
  "type": "Feature",
  "properties": {
    "iso:country":"ES",
    "sg:address":"Calle de Tridente, S/n",
    "sg:city":"Alacant",
    "sg:orig_category":"Agencias Y Agentes Comerciales, Representantes",
    "sg:phone":"+34 965 26 59 76",
    "sg:postcode":"03540",
    "sg:province":"Alicante",
    "wof:name":"Ferrandiz Reus Vicente",
    "wof:placetype":"venue"
},
  "geometry": {"coordinates":[-0.4253990054,38.3664855957],"type":"Point"}
}