{
  "type": "Feature",
  "properties": {
    "iso:country":"ES",
    "sg:address":"Calle de Dionisio Guardiola, 35",
    "sg:city":"Albacete",
    "sg:orig_category":"M\u00c9dicos: Pediatr\u00cda. Enfermedades De Los Ni\u00d1os",
    "sg:phone":"+34 967 22 29 36",
    "sg:postcode":"02003",
    "sg:province":"Albacete",
    "wof:name":"Gonzalez Moral Jose Joaquin",
    "wof:placetype":"venue"
},
  "geometry": {"coordinates":[-1.8581475019,38.9922332764],"type":"Point"}
}