{
  "type": "Feature",
  "properties": {
    "addr:full":"Calle de Cuatro Reyes, 5 Huesca Huesca 22001",
    "addr:housenumber":"5",
    "addr:postcode":"22001",
    "addr:street":"Calle De Cuatro Reyes",
    "iso:country":"ES",
    "sg:address":"Calle de Cuatro Reyes, 5",
    "sg:city":"Huesca",
    "sg:orig_category":"Cer\u00c1mica Art\u00cdstica Y Decorativa",
    "sg:phone":"+34 974 23 29 23",
    "sg:postcode":"22001",
    "sg:province":"Huesca",
    "wof:name":"Ainoza Roman Olga Maria",
    "wof:placetype":"venue"
},
  "geometry": {"coordinates":[-0.4070285857,42.1380691528],"type":"Point"}
}