{
  "type": "Feature",
  "properties": {
    "iso:country":"ES",
    "sg:address":"Ctra Sierra Alhamilla, 98",
    "sg:city":"Almeria",
    "sg:orig_category":"Caf\u00c9s, Bares, Cervecer\u00cdas",
    "sg:phone":"+34 950 25 27 86",
    "sg:postcode":"04009",
    "sg:province":"Almer\u00eda",
    "wof:name":"Cafeteria Anden S.l.",
    "wof:placetype":"venue"
},
  "geometry": {"coordinates":[-2.3886790276,36.8506851196],"type":"Point"}
}