{
  "type": "Feature",
  "properties": {
    "iso:country":"ES",
    "sg:address":"Can Masala, S/n",
    "sg:city":"S. Esteve Guialbes",
    "sg:orig_category":"Fabricaci\u00d3n Y Refinado De Az\u00dacares",
    "sg:phone":"+34 972 19 32 00",
    "sg:postcode":"17468",
    "sg:province":"Girona",
    "wof:name":"Bortrep S.l.",
    "wof:placetype":"venue"
},
  "geometry": {"coordinates":[2.8884160519,42.1389427185],"type":"Point"}
}