{
  "type": "Feature",
  "properties": {
    "addr:full":"Calle de Antonio Navas Lopez, 13 Puente-genil C\u00f3rdoba 14500",
    "addr:housenumber":"13",
    "addr:postcode":"14500",
    "addr:street":"Calle De Antonio Navas Lopez;Co\u0301Rdoba",
    "iso:country":"ES",
    "sg:address":"Calle de Antonio Navas Lopez, 13",
    "sg:city":"Puente-genil",
    "sg:orig_category":"Peluquer\u00cdas, Peluquer\u00cda Mixta",
    "sg:phone":"+34 957 60 49 10",
    "sg:postcode":"14500",
    "sg:province":"C\u00f3rdoba",
    "wof:name":"Ca\u00f1ete Marin Adolfo",
    "wof:placetype":"venue"
},
  "geometry": {"coordinates":[-4.766125679,37.3925666809],"type":"Point"}
}