{
  "type": "Feature",
  "properties": {
    "addr:full":"Calle de Magallanes, 45 Santander Cantabria 39007",
    "addr:housenumber":"45",
    "addr:postcode":"39007",
    "addr:street":"Calle De Magallanes",
    "iso:country":"ES",
    "sg:address":"Calle de Magallanes, 45",
    "sg:city":"Santander",
    "sg:orig_category":"Centros De Educaci\u00d3n Especial",
    "sg:phone":"+34 942 23 24 22",
    "sg:postcode":"39007",
    "sg:province":"Cantabria",
    "wof:name":"Colegio Publico Magallanes",
    "wof:placetype":"venue"
},
  "geometry": {"coordinates":[-3.8164389133,43.4619407654],"type":"Point"}
}