{
  "type": "Feature",
  "properties": {
    "addr:full":"Resid Acapulco, 2 Sevilla Sevilla 41020",
    "addr:housenumber":"2",
    "addr:postcode":"41020",
    "iso:country":"ES",
    "sg:address":"Resid Acapulco, 2",
    "sg:city":"Sevilla",
    "sg:orig_category":"Asilos De Ancianos. Centros Privados",
    "sg:phone":"+34 954 67 11 46",
    "sg:postcode":"41020",
    "sg:province":"Sevilla",
    "sg:website":"www.residenciaferrusola.com",
    "wof:name":"Ferrusola Santiago Angeles",
    "wof:placetype":"venue"
},
  "geometry": {"coordinates":[-5.9404969215,37.3995399475],"type":"Point"}
}