{
  "type": "Feature",
  "properties": {
    "iso:country":"ES",
    "sg:address":"Rua Escolas (das), 2",
    "sg:city":"Entoma",
    "sg:orig_category":"Empresas De Carpinter\u00cda",
    "sg:phone":"+34 988 33 53 05",
    "sg:postcode":"32313",
    "sg:province":"Ourense",
    "wof:name":"Arias Arias Joaquin",
    "wof:placetype":"venue"
},
  "geometry": {"coordinates":[-6.9367752075,42.4220962524],"type":"Point"}
}