{
  "type": "Feature",
  "properties": {
    "addr:full":"Carrer de Ramon Y Cajal, 132 Barcelona Barcelona 08024",
    "addr:housenumber":"132",
    "addr:postcode":"08024",
    "addr:street":"Carrer De Ramon Y Cajal",
    "iso:country":"ES",
    "sg:address":"Carrer de Ramon Y Cajal, 132",
    "sg:city":"Barcelona",
    "sg:orig_category":"Centros De Educaci\u00d3n Especial",
    "sg:phone":"+34 932 19 84 62",
    "sg:postcode":"08024",
    "sg:province":"Barcelona",
    "wof:name":"Garcia Guerra Victoria",
    "wof:placetype":"venue"
},
  "geometry": {"coordinates":[2.1622850895,41.4046592712],"type":"Point"}
}