{
  "type": "Feature",
  "properties": {
    "addr:full":"Carrer de Vicari Joaquim Fus, 119 Palma Islas Baleares 07006",
    "addr:housenumber":"119",
    "addr:postcode":"07006",
    "addr:street":"Carrer De Vicari Joaquim Fus",
    "iso:country":"ES",
    "sg:address":"Carrer de Vicari Joaquim Fus, 119",
    "sg:city":"Palma",
    "sg:orig_category":"Laboratorios Farmac\u00c9uticos",
    "sg:phone":"+34 971 24 08 18",
    "sg:postcode":"07006",
    "sg:province":"Islas Baleares",
    "wof:name":"Morey Ballester Pedro Juan",
    "wof:placetype":"venue"
},
  "geometry": {"coordinates":[2.6758289337,39.5584716797],"type":"Point"}
}