{
  "type": "Feature",
  "properties": {
    "iso:country":"ES",
    "sg:address":"Calle de Anastasia Santamaria, 5",
    "sg:city":"Palencia",
    "sg:orig_category":"Mec\u00c1nico Del Autom\u00d3vil",
    "sg:phone":"+34 979 74 47 38",
    "sg:postcode":"34003",
    "sg:province":"Palencia",
    "wof:name":"Rodriguez Rojo Gerardo",
    "wof:placetype":"venue"
},
  "geometry": {"coordinates":[-4.5344138145,42.0178833008],"type":"Point"}
}