{
  "type": "Feature",
  "properties": {
    "iso:country":"ES",
    "sg:address":"Carr Cuenca (barri Porta), 8",
    "sg:city":"Barri De Porta",
    "sg:orig_category":"Supermercados Y Hipermercados",
    "sg:phone":"+34 961 54 96 08",
    "sg:postcode":"46930",
    "sg:province":"Valencia",
    "wof:name":"Serrano Ortiz Manuela",
    "wof:placetype":"venue"
},
  "geometry": {"coordinates":[-0.4601689875,39.47706604],"type":"Point"}
}