{
  "type": "Feature",
  "properties": {
    "addr:full":"Calle de Suarez Valdes, 17 Grado Asturias 33820",
    "addr:housenumber":"17",
    "addr:postcode":"33820",
    "addr:street":"Calle De Suarez Valdes",
    "iso:country":"ES",
    "sg:address":"Calle de Suarez Valdes, 17",
    "sg:city":"Grado",
    "sg:orig_category":"Reposter\u00cdas",
    "sg:phone":"+34 985 75 28 75",
    "sg:postcode":"33820",
    "sg:province":"Asturias",
    "wof:name":"Perez Rodriguez Ana",
    "wof:placetype":"venue"
},
  "geometry": {"coordinates":[-6.0692439079,43.3872261047],"type":"Point"}
}