{
  "type": "Feature",
  "properties": {
    "iso:country":"ES",
    "sg:address":"Avda Balneario (do), 23",
    "sg:city":"Carballi\u00f1o",
    "sg:orig_category":"Electricidad: Instaladores",
    "sg:phone":"+34 988 27 07 63",
    "sg:postcode":"32500",
    "sg:province":"Ourense",
    "wof:name":"Casas Lopez Manuel",
    "wof:placetype":"venue"
},
  "geometry": {"coordinates":[-8.0793771744,42.434387207],"type":"Point"}
}