{
  "type": "Feature",
  "properties": {
    "addr:full":"Carrer de Gran Via De Lluis Companys, 186 Premia Mar Barcelona 08330",
    "addr:housenumber":"186",
    "addr:postcode":"08330",
    "addr:street":"Carrer De Gran Via De Lluis Companys",
    "iso:country":"ES",
    "sg:address":"Carrer de Gran Via De Lluis Companys, 186",
    "sg:city":"Premia Mar",
    "sg:orig_category":"Molduras, Junquillos, Listones Y Molduras Perforadas",
    "sg:phone":"+34 937 51 29 90",
    "sg:postcode":"08330",
    "sg:province":"Barcelona",
    "wof:name":"Cea Vegas Jose Maria",
    "wof:placetype":"venue"
},
  "geometry": {"coordinates":[2.353110075,41.4906196594],"type":"Point"}
}