{
  "type": "Feature",
  "properties": {
    "iso:country":"ES",
    "sg:address":"Calle de Gregorio Aurre, 11",
    "sg:city":"Langreo",
    "sg:orig_category":"Inmobiliaria (agencias)",
    "sg:phone":"+34 985 67 33 84",
    "sg:postcode":"33930",
    "sg:province":"Asturias",
    "wof:name":"Puerta Menendez Victor Jose",
    "wof:placetype":"venue"
},
  "geometry": {"coordinates":[-5.6915302277,43.3081626892],"type":"Point"}
}