{
  "type": "Feature",
  "properties": {
    "iso:country":"ES",
    "sg:address":"Calle de Cipres, 4",
    "sg:city":"Arganda",
    "sg:orig_category":"Suministros Y Materiales Industriales",
    "sg:phone":"+34 918 70 05 51",
    "sg:postcode":"28500",
    "sg:province":"Madrid",
    "wof:name":"Industrias Josvir S.l.",
    "wof:placetype":"venue"
},
  "geometry": {"coordinates":[-3.4629259109,40.3133888245],"type":"Point"}
}