{
  "type": "Feature",
  "properties": {
    "addr:full":"Carrer de Canarias, 3 Torreta Barcelona 08430",
    "addr:housenumber":"3",
    "addr:postcode":"08430",
    "addr:street":"Carrer De Canarias;Barcelona",
    "iso:country":"ES",
    "sg:address":"Carrer de Canarias, 3",
    "sg:city":"Torreta",
    "sg:orig_category":"Institutos De Belleza",
    "sg:phone":"+34 938 70 15 46",
    "sg:postcode":"08430",
    "sg:province":"Barcelona",
    "wof:name":"Marti Illa Teresa",
    "wof:placetype":"venue"
},
  "geometry": {"coordinates":[2.3271899223,41.5986404419],"type":"Point"}
}