{
  "type": "Feature",
  "properties": {
    "addr:full":"Carrer de Mare Molas, 14 Reus Tarragona 43202",
    "addr:housenumber":"14",
    "addr:postcode":"43202",
    "addr:street":"Carrer De Mare Molas",
    "iso:country":"ES",
    "sg:address":"Carrer de Mare Molas, 14",
    "sg:city":"Reus",
    "sg:orig_category":"Zapatos (al Por Menor)",
    "sg:phone":"+34 977 31 47 57",
    "sg:postcode":"43202",
    "sg:province":"Tarragona",
    "wof:name":"Navarro Ramirez Elvira",
    "wof:placetype":"venue"
},
  "geometry": {"coordinates":[1.1020870209,41.1514472961],"type":"Point"}
}