{
  "type": "Feature",
  "properties": {
    "addr:full":"Carr Palauet, 58 Lleida Lleida 25001",
    "addr:housenumber":"58",
    "addr:postcode":"25001",
    "addr:street":"Carr Palauet",
    "iso:country":"ES",
    "sg:address":"Carr Palauet, 58",
    "sg:city":"Lleida",
    "sg:orig_category":"Calzados Ortop\u00c9dicos",
    "sg:phone":"+34 973 20 04 89",
    "sg:postcode":"25001",
    "sg:province":"Lleida",
    "wof:name":"Confeccion De Elasticos S.l.",
    "wof:placetype":"venue"
},
  "geometry": {"coordinates":[0.6449549794,41.6072463989],"type":"Point"}
}