{
  "type": "Feature",
  "properties": {
    "addr:full":"Carrer de Santa Marta, 13 Castelldefels Barcelona 08860",
    "addr:housenumber":"13",
    "addr:postcode":"08860",
    "addr:street":"Carrer De Santa Marta",
    "iso:country":"ES",
    "sg:address":"Carrer de Santa Marta, 13",
    "sg:city":"Castelldefels",
    "sg:orig_category":"Cl\u00cdnicas Dentales",
    "sg:phone":"+34 936 65 18 58",
    "sg:postcode":"08860",
    "sg:province":"Barcelona",
    "wof:name":"De Pe\u00f1a Apolito Ivan",
    "wof:placetype":"venue"
},
  "geometry": {"coordinates":[1.9782810211,41.2864608765],"type":"Point"}
}