{
  "type": "Feature",
  "properties": {
    "addr:full":"Calle de Nueva, S/n Adeje Santa Cruz De Tenerife 38670",
    "addr:housenumber":"s / n",
    "addr:postcode":"38670",
    "addr:street":"Calle De Nueva",
    "iso:country":"ES",
    "sg:address":"Calle de Nueva, S/n",
    "sg:city":"Adeje",
    "sg:orig_category":"Inmobiliaria (agencias)",
    "sg:phone":"+34 922 78 09 12",
    "sg:postcode":"38670",
    "sg:province":"Santa Cruz De Tenerife",
    "wof:name":"Nasierma S.l.",
    "wof:placetype":"venue"
},
  "geometry": {"coordinates":[-16.7254371643,28.1205024719],"type":"Point"}
}