{
  "type": "Feature",
  "properties": {
    "addr:full":"Rbla Salvador Sama, 51 Vilanova I La Geltru Barcelona 08800",
    "addr:housenumber":"51",
    "addr:postcode":"08800",
    "addr:street":"Rbla Salvador Sama",
    "iso:country":"ES",
    "sg:address":"Rbla Salvador Sama, 51",
    "sg:city":"Vilanova I La Geltru",
    "sg:orig_category":"Inmobiliaria (agencias)",
    "sg:phone":"+34 938 15 16 66",
    "sg:postcode":"08800",
    "sg:province":"Barcelona",
    "wof:name":"Nevot Sanso Manuel",
    "wof:placetype":"venue"
},
  "geometry": {"coordinates":[1.7238559723,41.2214279175],"type":"Point"}
}