{
  "type": "Feature",
  "properties": {
    "iso:country":"ES",
    "sg:address":"Calle de San Ignacio De Loyola, 23",
    "sg:city":"Vitoria-gasteiz",
    "sg:orig_category":"Art\u00cdculos De Decoraci\u00d3n",
    "sg:phone":"+34 945 14 11 75",
    "sg:postcode":"01001",
    "sg:province":"\u00c1lava",
    "wof:name":"Dise\u00f1os San Prudencio Decoracion S.l.",
    "wof:placetype":"venue"
},
  "geometry": {"coordinates":[-2.6728069782,42.8529319763],"type":"Point"}
}