{
  "type": "Feature",
  "properties": {
    "addr:full":"Calle de Pablo Picasso, 13 Catral Alicante 03158",
    "addr:housenumber":"13",
    "addr:postcode":"03158",
    "addr:street":"Calle De Pablo Picasso",
    "iso:country":"ES",
    "sg:address":"Calle de Pablo Picasso, 13",
    "sg:city":"Catral",
    "sg:orig_category":"Agencias Y Agentes Comerciales, Representantes",
    "sg:phone":"+34 966 78 71 28",
    "sg:postcode":"03158",
    "sg:province":"Alicante",
    "wof:name":"Representaciones J.& M.catral.s.l.",
    "wof:placetype":"venue"
},
  "geometry": {"coordinates":[-0.8036230206,38.1610221863],"type":"Point"}
}