{
  "type": "Feature",
  "properties": {
    "addr:full":"Calle de Morote, 10 Huescar Granada 18830",
    "addr:housenumber":"10",
    "addr:postcode":"18830",
    "addr:street":"Calle De Morote",
    "iso:country":"ES",
    "sg:address":"Calle de Morote, 10",
    "sg:city":"Huescar",
    "sg:orig_category":"Producci\u00d3n, Distribuci\u00d3n De Gas Butano Y Propano",
    "sg:phone":"+34 958 74 01 15",
    "sg:postcode":"18830",
    "sg:province":"Granada",
    "wof:name":"Jose Ramon Noguera S.a.",
    "wof:placetype":"venue"
},
  "geometry": {"coordinates":[-2.5444617271,37.8080940247],"type":"Point"}
}