{
  "type": "Feature",
  "properties": {
    "iso:country":"ES",
    "sg:address":"Ctra. Cuenca, S/n",
    "sg:city":"Mira",
    "sg:orig_category":"Cooperativas Agr\u00cdcolas",
    "sg:phone":"+34 969 34 00 08",
    "sg:postcode":"16393",
    "sg:province":"Cuenca",
    "wof:name":"Cooperativa Agricola San Antonio Abad",
    "wof:placetype":"venue"
},
  "geometry": {"coordinates":[-1.4402439594,39.7191848755],"type":"Point"}
}