{
  "type": "Feature",
  "properties": {
    "addr:full":"Abastos, S/n Avila \u00c1vila 05001",
    "addr:housenumber":"s / n",
    "addr:postcode":"05001",
    "addr:street":"Abastos;A\u0301Vila",
    "iso:country":"ES",
    "sg:address":"Abastos, S/n",
    "sg:city":"Avila",
    "sg:orig_category":"Poller\u00cda Y Caza (al Por Menor)",
    "sg:phone":"+34 920 21 18 07",
    "sg:postcode":"05001",
    "sg:province":"\u00c1vila",
    "wof:name":"Aves Vazquez S.l.",
    "wof:placetype":"venue"
},
  "geometry": {"coordinates":[-4.6398692131,40.638092041],"type":"Point"}
}