{
  "type": "Feature",
  "properties": {
    "iso:country":"ES",
    "sg:address":"Ctra Bormujos-mairena, S/n",
    "sg:city":"Bormujos",
    "sg:orig_category":"Empresarios",
    "sg:phone":"+34 955 72 20 39",
    "sg:postcode":"41930",
    "sg:province":"Sevilla",
    "wof:name":"Constructora Myp Algarafe S.l.",
    "wof:placetype":"venue"
},
  "geometry": {"coordinates":[-6.0955691338,37.3610038757],"type":"Point"}
}