{
  "type": "Feature",
  "properties": {
    "iso:country":"ES",
    "sg:address":"Barr Carbonaire C/2, 59",
    "sg:city":"Vall D'uixo",
    "sg:orig_category":"Alquiler De Gr\u00daas",
    "sg:phone":"+34 964 66 68 96",
    "sg:postcode":"12600",
    "sg:province":"Castell\u00f3n",
    "wof:name":"Gruas La Vall S.l.",
    "wof:placetype":"venue"
},
  "geometry": {"coordinates":[-0.0360242017,39.9860687256],"type":"Point"}
}