{
  "type": "Feature",
  "properties": {
    "addr:full":"Avda Constitucion (la), 21 Sevilla Sevilla 41004",
    "addr:housenumber":"21",
    "addr:postcode":"41004",
    "addr:street":"Avda Constitucion La",
    "iso:country":"ES",
    "sg:address":"Avda Constitucion (la), 21",
    "sg:city":"Sevilla",
    "sg:orig_category":"Abogados",
    "sg:phone":"+34 954 27 83 19",
    "sg:postcode":"41004",
    "sg:province":"Sevilla",
    "wof:name":"Despacho Albi\u00f1ana Y Suarez De Lezo S.l.",
    "wof:placetype":"venue"
},
  "geometry": {"coordinates":[-5.9934310913,37.3833694458],"type":"Point"}
}