{
  "type": "Feature",
  "properties": {
    "iso:country":"ES",
    "sg:address":"Pg Verdaguer, 66",
    "sg:city":"Igualada",
    "sg:orig_category":"Sociedades, Compa\u00d1\u00cdas Aseguradoras",
    "sg:phone":"+34 938 04 05 00",
    "sg:postcode":"08700",
    "sg:province":"Barcelona",
    "wof:name":"Guma Puiggros Jose",
    "wof:placetype":"venue"
},
  "geometry": {"coordinates":[1.6170699596,41.5795402527],"type":"Point"}
}