{
  "type": "Feature",
  "properties": {
    "iso:country":"ES",
    "sg:address":"Calle de Hornos Caleros (de Los), 58",
    "sg:city":"Avila",
    "sg:classifiers":[
        {
            "category":"Manufacturing",
            "subcategory":"Building Materials",
            "type":"Manufacturing & Wholesale Goods"
        }
    ],
    "sg:phone":"+34 920 25 68 25",
    "sg:postcode":"05003",
    "sg:province":"\u00c1vila",
    "sg:tags":[
        "cemento",
        "y",
        "de",
        "fabricaci\u00d3n",
        "cal"
    ],
    "wof:name":"Comunidad De Propietarios Hornos Caleros 58",
    "wof:placetype":"venue"
},
  "geometry": {"coordinates":[-4.6761441231,40.6504211426],"type":"Point"}
}