{
  "type": "Feature",
  "properties": {
    "iso:country":"ES",
    "sg:address":"Pol. Valdefuentes, S/n",
    "sg:city":"Pepino",
    "sg:orig_category":"Calefacci\u00d3n Central: Material (fabricaci\u00d3n, Al Por Mayor)",
    "sg:phone":"+34 925 70 95 34",
    "sg:postcode":"45638",
    "sg:province":"Toledo",
    "wof:name":"Suministros Calta S.l.",
    "wof:placetype":"venue"
},
  "geometry": {"coordinates":[-4.803000927,40.0316200256],"type":"Point"}
}