{
  "type": "Feature",
  "properties": {
    "iso:country":"ES",
    "sg:address":"Avda Blas Infante, 8",
    "sg:city":"Arroyo De La Miel-benalmadena Costa",
    "sg:orig_category":"Institutos De Belleza",
    "sg:phone":"+34 952 44 48 88",
    "sg:postcode":"29631",
    "sg:province":"M\u00e1laga",
    "wof:name":"Chacon Gonzalez Francisca",
    "wof:placetype":"venue"
},
  "geometry": {"coordinates":[-4.5348558426,36.5988578796],"type":"Point"}
}