{
  "type": "Feature",
  "properties": {
    "addr:full":"Pg Miramar, 33 Cambrils Tarragona 43850",
    "addr:housenumber":"33",
    "addr:postcode":"43850",
    "addr:street":"Pg Miramar",
    "iso:country":"ES",
    "sg:address":"Pg Miramar, 33",
    "sg:city":"Cambrils",
    "sg:orig_category":"Comercio De Minerales, F\u00d3siles Y Conchas",
    "sg:phone":"+34 977 36 13 94",
    "sg:postcode":"43850",
    "sg:province":"Tarragona",
    "wof:name":"Restaurant Casa Matilde S.l.",
    "wof:placetype":"venue"
},
  "geometry": {"coordinates":[1.0630249977,41.0657081604],"type":"Point"}
}