{
  "type": "Feature",
  "properties": {
    "addr:full":"Carr Castell, 11 Solsona Lleida 25280",
    "addr:housenumber":"11",
    "addr:postcode":"25280",
    "addr:street":"Carr Castell",
    "iso:country":"ES",
    "sg:address":"Carr Castell, 11",
    "sg:city":"Solsona",
    "sg:orig_category":"Comerciantes Al Por Mayor De Vinos, Licores Y Alcoholes",
    "sg:phone":"+34 973 48 01 67",
    "sg:postcode":"25280",
    "sg:province":"Lleida",
    "wof:name":"La Vinicola S. A.",
    "wof:placetype":"venue"
},
  "geometry": {"coordinates":[1.5176899433,41.9943847656],"type":"Point"}
}