{
  "type": "Feature",
  "properties": {
    "addr:full":"Carrer de Doctor Ferran, S/n Reus Tarragona 43202",
    "addr:housenumber":"s / n",
    "addr:postcode":"43202",
    "addr:street":"Carrer De Doctor Ferran",
    "iso:country":"ES",
    "sg:address":"Carrer de Doctor Ferran, S/n",
    "sg:city":"Reus",
    "sg:orig_category":"Ba\u00d1os Y Duchas P\u00dablicos",
    "sg:phone":"+34 977 33 30 14",
    "sg:postcode":"43202",
    "sg:province":"Tarragona",
    "wof:name":"Reus Esport I Lleure S.a.",
    "wof:placetype":"venue"
},
  "geometry": {"coordinates":[1.0976849794,41.1542739868],"type":"Point"}
}