{
  "type": "Feature",
  "properties": {
    "iso:country":"ES",
    "sg:address":"Avda Txori Erri, 38",
    "sg:city":"Basozabal",
    "sg:orig_category":"Suministros Y Materiales Industriales",
    "sg:phone":"+34 944 53 20 00",
    "sg:postcode":"48150",
    "sg:province":"Vizcaya",
    "wof:name":"Lubricacion Centralizada De Limon S.a.",
    "wof:placetype":"venue"
},
  "geometry": {"coordinates":[-2.9249958992,43.2989730835],"type":"Point"}
}