{
  "type": "Feature",
  "properties": {
    "addr:full":"Avda Portugal, 13 Olivenza Badajoz 06100",
    "addr:housenumber":"13",
    "addr:postcode":"06100",
    "addr:street":"Avda Portugal",
    "iso:country":"ES",
    "sg:address":"Avda Portugal, 13",
    "sg:city":"Olivenza",
    "sg:orig_category":"Herboristas (al Por Menor)",
    "sg:phone":"+34 924 49 15 26",
    "sg:postcode":"06100",
    "sg:province":"Badajoz",
    "wof:name":"Becerra Fernandez Catalina",
    "wof:placetype":"venue"
},
  "geometry": {"coordinates":[-7.1025390625,38.6847000122],"type":"Point"}
}