{
  "type": "Feature",
  "properties": {
    "addr:full":"Carrer de Rovello, 361 Tres Cales Tarragona 43860",
    "addr:housenumber":"361",
    "addr:postcode":"43860",
    "addr:street":"Carrer De Rovello",
    "iso:country":"ES",
    "sg:address":"Carrer de Rovello, 361",
    "sg:city":"Tres Cales",
    "sg:orig_category":"Promotores Constructores",
    "sg:phone":"+34 977 49 32 16",
    "sg:postcode":"43860",
    "sg:province":"Tarragona",
    "wof:name":"Coleman  Kavin Ronald",
    "wof:placetype":"venue"
},
  "geometry": {"coordinates":[0.8034560084,40.9148025513],"type":"Point"}
}