{
  "type": "Feature",
  "properties": {
    "addr:full":"Calle de Lugo, S/n Arzua La Coru\u00f1a 15810",
    "addr:housenumber":"s / n",
    "addr:postcode":"15810",
    "addr:street":"Calle De Lugo;La Corun\u0303A",
    "iso:country":"ES",
    "sg:address":"Calle de Lugo, S/n",
    "sg:city":"Arzua",
    "sg:orig_category":"Combustibles: Fuel",
    "sg:phone":"+34 981 50 10 82",
    "sg:postcode":"15810",
    "sg:province":"La Coru\u00f1a",
    "wof:name":"Estacion De Servicio Teiraboa S.l.",
    "wof:placetype":"venue"
},
  "geometry": {"coordinates":[-8.1552124023,42.9291992188],"type":"Point"}
}