{
  "type": "Feature",
  "properties": {
    "addr:full":"Carrer de Congost, 16 Mollet Valles Barcelona 08100",
    "addr:housenumber":"16",
    "addr:postcode":"08100",
    "addr:street":"Carrer De Congost",
    "iso:country":"ES",
    "sg:address":"Carrer de Congost, 16",
    "sg:city":"Mollet Valles",
    "sg:orig_category":"Fabricaci\u00d3n De Art\u00cdculos Y Equipos Deportivos Y De Ocio",
    "sg:phone":"+34 935 93 73 44",
    "sg:postcode":"08100",
    "sg:province":"Barcelona",
    "wof:name":"Ciro Sport S.l.",
    "wof:placetype":"venue"
},
  "geometry": {"coordinates":[2.2310500145,41.5548095703],"type":"Point"}
}