{
  "type": "Feature",
  "properties": {
    "iso:country":"ES",
    "sg:address":"Avda Utrera, 52",
    "sg:city":"Palacios Y Villafranca",
    "sg:orig_category":"Producci\u00d3n, Distribuci\u00d3n De Electricidad",
    "sg:phone":"+34 955 81 16 68",
    "sg:postcode":"41720",
    "sg:province":"Sevilla",
    "wof:name":"Mu\u00f1oz Macias Rosario",
    "wof:placetype":"venue"
},
  "geometry": {"coordinates":[-5.9218001366,37.15965271],"type":"Point"}
}