{
  "type": "Feature",
  "properties": {
    "addr:full":"Ctra Burgos Santander, 22 Sotopalacios Burgos 09140",
    "addr:housenumber":"22",
    "addr:postcode":"09140",
    "addr:street":"Ctra Burgos Santander",
    "iso:country":"ES",
    "sg:address":"Ctra Burgos Santander, 22",
    "sg:city":"Sotopalacios",
    "sg:orig_category":"Farmacias",
    "sg:phone":"+34 947 44 11 96",
    "sg:postcode":"09140",
    "sg:province":"Burgos",
    "wof:name":"Lopez De Abechuco Torio Jose Miguel",
    "wof:placetype":"venue"
},
  "geometry": {"coordinates":[-3.6831541061,42.4509162903],"type":"Point"}
}