{
  "type": "Feature",
  "properties": {
    "iso:country":"ES",
    "sg:address":"Baja Navarra, 2",
    "sg:city":"Estella",
    "sg:orig_category":"Abogados",
    "sg:phone":"+34 948 55 01 96",
    "sg:postcode":"31200",
    "sg:province":"Navarra",
    "wof:name":"Elorza Rojo Javier",
    "wof:placetype":"venue"
},
  "geometry": {"coordinates":[-2.0320410728,42.6718978882],"type":"Point"}
}