{
  "type": "Feature",
  "properties": {
    "addr:full":"Calle de Corona De Aragon, 19 Calamocha Teruel 44200",
    "addr:housenumber":"19",
    "addr:postcode":"44200",
    "addr:street":"Calle De Corona De Aragon",
    "iso:country":"ES",
    "sg:address":"Calle de Corona De Aragon, 19",
    "sg:city":"Calamocha",
    "sg:classifiers":[
        {
            "category":"Personal",
            "subcategory":"Barber",
            "type":"Services"
        }
    ],
    "sg:phone":"+34 978 73 05 65",
    "sg:postcode":"44200",
    "sg:province":"Teruel",
    "sg:tags":[
        "caballeros",
        "de",
        "peluqueros"
    ],
    "wof:name":"Hernandez Galve Jose Maria",
    "wof:placetype":"venue"
},
  "geometry": {"coordinates":[-1.2971323729,40.9185256958],"type":"Point"}
}