{
  "type": "Feature",
  "properties": {
    "iso:country":"ES",
    "sg:address":"Calle de Juan Sebastian Elkano, 20",
    "sg:city":"Kurtzea",
    "sg:orig_category":"Peluqueros: De Se\u00d1oras",
    "sg:phone":"+34 944 56 20 57",
    "sg:postcode":"48960",
    "sg:province":"Vizcaya",
    "wof:name":"Pinero Elices Maria Victoria",
    "wof:placetype":"venue"
},
  "geometry": {"coordinates":[-2.843818903,43.2288513184],"type":"Point"}
}