{
  "type": "Feature",
  "properties": {
    "iso:country":"ES",
    "sg:address":"Calle de Virgen Del Rocio, 7",
    "sg:city":"Utrera",
    "sg:orig_category":"Herboristas (al Por Menor)",
    "sg:phone":"+34 954 86 31 03",
    "sg:postcode":"41710",
    "sg:province":"Sevilla",
    "wof:name":"Arenas Garcia Manuel Salvador",
    "wof:placetype":"venue"
},
  "geometry": {"coordinates":[-5.7847080231,37.1798477173],"type":"Point"}
}