{
  "type": "Feature",
  "properties": {
    "iso:country":"ES",
    "sg:address":"Avda Mariano Hernandez Caro, S/n",
    "sg:city":"Roquetas Mar",
    "sg:orig_category":"Caf\u00c9s, Bares, Cervecer\u00cdas",
    "sg:phone":"+34 950 32 79 87",
    "sg:postcode":"04740",
    "sg:province":"Almer\u00eda",
    "wof:name":"Mochon Hernandez Jose Luis",
    "wof:placetype":"venue"
},
  "geometry": {"coordinates":[-2.6124989986,36.7638435364],"type":"Point"}
}