{
  "type": "Feature",
  "properties": {
    "iso:country":"ES",
    "sg:address":"Calle de Sanchez Morate, 17",
    "sg:city":"Getafe",
    "sg:orig_category":"Molduras, Junquillos, Listones Y Molduras Perforadas",
    "sg:phone":"+34 916 83 78 62",
    "sg:postcode":"28903",
    "sg:province":"Madrid",
    "wof:name":"Logo Diaz Maria",
    "wof:placetype":"venue"
},
  "geometry": {"coordinates":[-3.7245180607,40.3123588562],"type":"Point"}
}