{
  "type": "Feature",
  "properties": {
    "iso:country":"ES",
    "sg:address":"Calle de Clariano, 9",
    "sg:city":"Valencia",
    "sg:orig_category":"Peluquer\u00cdas, Peluquer\u00cda Mixta",
    "sg:phone":"+34 963 60 57 78",
    "sg:postcode":"46021",
    "sg:province":"Valencia",
    "wof:name":"Marcelo Barbera Julio Cesar",
    "wof:placetype":"venue"
},
  "geometry": {"coordinates":[-0.3519091904,39.4769287109],"type":"Point"}
}