{
  "type": "Feature",
  "properties": {
    "addr:full":"Avda Menesteo (de), 9 Puerto De Santa Maria C\u00e1diz 11500",
    "addr:postcode":"11500",
    "addr:street":"Avda Menesteo De 9;Ca\u0301Diz",
    "iso:country":"ES",
    "sg:address":"Avda Menesteo (de), 9",
    "sg:city":"Puerto De Santa Maria",
    "sg:orig_category":"Alimentaci\u00d3n General (al Por Menor)",
    "sg:phone":"+34 956 87 06 86",
    "sg:postcode":"11500",
    "sg:province":"C\u00e1diz",
    "wof:name":"Selma Garcia Manuel",
    "wof:placetype":"venue"
},
  "geometry": {"coordinates":[-6.2307519913,36.5919265747],"type":"Point"}
}