{
  "type": "Feature",
  "properties": {
    "iso:country":"ES",
    "sg:address":"Calle de Tapia De Casariego, 13",
    "sg:city":"Madrid",
    "sg:orig_category":"Centros De Educaci\u00d3n Especial",
    "sg:phone":"+34 913 07 19 66",
    "sg:postcode":"28023",
    "sg:province":"Madrid",
    "wof:name":"Pro-discapacitados De Aravaca",
    "wof:placetype":"venue"
},
  "geometry": {"coordinates":[-3.7740659714,40.4650115967],"type":"Point"}
}