{
  "type": "Feature",
  "properties": {
    "addr:full":"Calle de Juan Ramon Jimenez, 8 Salteras Sevilla 41909",
    "addr:housenumber":"8",
    "addr:postcode":"41909",
    "addr:street":"Calle De Juan Ramon Jimenez",
    "iso:country":"ES",
    "sg:address":"Calle de Juan Ramon Jimenez, 8",
    "sg:city":"Salteras",
    "sg:orig_category":"Arreglo, Reparaci\u00d3n, Piezas Sueltas De Televisi\u00d3n, V\u00cddeo, Hi",
    "sg:phone":"+34 955 70 74 60",
    "sg:postcode":"41909",
    "sg:province":"Sevilla",
    "wof:name":"Quintanilla Perez Daniel",
    "wof:placetype":"venue"
},
  "geometry": {"coordinates":[-6.1090779305,37.417881012],"type":"Point"}
}