{
  "type": "Feature",
  "properties": {
    "addr:full":"Carrer de Ignasi Iglesias, 105 Prat Llobregat Barcelona 08820",
    "addr:housenumber":"105",
    "addr:postcode":"08820",
    "addr:street":"Carrer De Ignasi Iglesias;Llobregat",
    "iso:country":"ES",
    "sg:address":"Carrer de Ignasi Iglesias, 105",
    "sg:city":"Prat Llobregat",
    "sg:orig_category":"Electricidad: Instaladores",
    "sg:phone":"+34 934 78 74 20",
    "sg:postcode":"08820",
    "sg:province":"Barcelona",
    "wof:name":"Estany Tomas Jose",
    "wof:placetype":"venue"
},
  "geometry": {"coordinates":[2.096683979,41.331363678],"type":"Point"}
}