{
  "type": "Feature",
  "properties": {
    "addr:full":"Calle de Conde De Haro, 5 Haro La Rioja 26200",
    "addr:housenumber":"5",
    "addr:postcode":"26200",
    "addr:street":"Calle De Conde De Haro",
    "iso:country":"ES",
    "sg:address":"Calle de Conde De Haro, 5",
    "sg:city":"Haro",
    "sg:orig_category":"Bebidas",
    "sg:phone":"+34 941 30 32 72",
    "sg:postcode":"26200",
    "sg:province":"La Rioja",
    "wof:name":"Rodriguez Alonso Francisco Jose",
    "wof:placetype":"venue"
},
  "geometry": {"coordinates":[-2.848082304,42.5762557983],"type":"Point"}
}