{
  "type": "Feature",
  "properties": {
    "iso:country":"ES",
    "sg:address":"Av Nucia (la), 13",
    "sg:city":"Altea",
    "sg:orig_category":"Panader\u00cdas, Panader\u00cdas",
    "sg:phone":"+34 965 84 47 10",
    "sg:postcode":"03590",
    "sg:province":"Alicante",
    "wof:name":"Panificadora Alteanense S.a",
    "wof:placetype":"venue"
},
  "geometry": {"coordinates":[-0.0520070009,38.6008453369],"type":"Point"}
}