{
  "type": "Feature",
  "properties": {
    "addr:full":"Calle de Ebanistas (de Los), 5 Velilla S.antonio Madrid 28891",
    "addr:housenumber":"5",
    "addr:postcode":"28891",
    "addr:street":"Calle De Ebanistas De Los",
    "iso:country":"ES",
    "sg:address":"Calle de Ebanistas (de Los), 5",
    "sg:city":"Velilla S.antonio",
    "sg:orig_category":"Artes Gr\u00c1ficas, Artes Pl\u00c1sticas (curso)",
    "sg:phone":"+34 916 60 90 16",
    "sg:postcode":"28891",
    "sg:province":"Madrid",
    "sg:website":"www.cepsa.es",
    "wof:name":"L V Tobar E Hijos S.l.",
    "wof:placetype":"venue"
},
  "geometry": {"coordinates":[-3.4764964581,40.3509902954],"type":"Point"}
}