{
  "type": "Feature",
  "properties": {
    "iso:country":"ES",
    "sg:address":"Carr Girona, 6",
    "sg:city":"Figueres",
    "sg:orig_category":"Ropa Para Se\u00d1oras (al Por Menor)",
    "sg:phone":"+34 972 50 04 01",
    "sg:postcode":"17600",
    "sg:province":"Girona",
    "wof:name":"Cristina Carbo Josep Maria",
    "wof:placetype":"venue"
},
  "geometry": {"coordinates":[2.9609940052,42.2670478821],"type":"Point"}
}