{
  "type": "Feature",
  "properties": {
    "addr:full":"Calle de San Vicente, 34 Barakaldo Vizcaya 48902",
    "addr:housenumber":"34",
    "addr:postcode":"48902",
    "addr:street":"Calle De San Vicente",
    "iso:country":"ES",
    "sg:address":"Calle de San Vicente, 34",
    "sg:city":"Barakaldo",
    "sg:orig_category":"Reposter\u00cdas",
    "sg:phone":"+34 944 37 35 91",
    "sg:postcode":"48902",
    "sg:province":"Vizcaya",
    "wof:name":"Sonia Martin Garcia",
    "wof:placetype":"venue"
},
  "geometry": {"coordinates":[-2.9949657917,43.2958221436],"type":"Point"}
}