{
  "type": "Feature",
  "properties": {
    "addr:full":"Avda Fisterra, 65 San Roque La Coru\u00f1a 15147",
    "addr:housenumber":"65",
    "addr:postcode":"15147",
    "addr:street":"Avda Fisterra;Roque;Corun\u0303A",
    "iso:country":"ES",
    "sg:address":"Avda Fisterra, 65",
    "sg:city":"San Roque",
    "sg:orig_category":"Contenedores Para Transporte De Mercanc\u00cdas",
    "sg:phone":"+34 981 73 35 27",
    "sg:postcode":"15147",
    "sg:province":"La Coru\u00f1a",
    "wof:name":"Construcciones Alejandro Martinez E Hijos",
    "wof:placetype":"venue"
},
  "geometry": {"coordinates":[-8.7350282669,43.1882362366],"type":"Point"}
}