{
  "type": "Feature",
  "properties": {
    "iso:country":"ES",
    "sg:address":"Calle de Victoria Balfe, 14",
    "sg:city":"Burgos",
    "sg:orig_category":"Maquinaria Para Industrias Diversas",
    "sg:phone":"+34 947 22 48 95",
    "sg:postcode":"09006",
    "sg:province":"Burgos",
    "wof:name":"Ruiz Villahoz S.l.",
    "wof:placetype":"venue"
},
  "geometry": {"coordinates":[-3.6807301044,42.3603096008],"type":"Point"}
}