{
  "type": "Feature",
  "properties": {
    "iso:country":"ES",
    "sg:address":"Plaz Barcelona, 14",
    "sg:city":"Salamanca",
    "sg:orig_category":"Lencer\u00cda Femenina, Corseter\u00cda, Trajes De Ba\u00d1o (al Por Menor)",
    "sg:phone":"+34 923 25 17 57",
    "sg:postcode":"37004",
    "sg:province":"Salamanca",
    "wof:name":"Armenteros Calvo Elisa",
    "wof:placetype":"venue"
},
  "geometry": {"coordinates":[-5.649292469,40.9740753174],"type":"Point"}
}