{
  "type": "Feature",
  "properties": {
    "addr:full":"Calle de Magdalena, 29 Oviedo Asturias 33009",
    "addr:housenumber":"29",
    "addr:postcode":"33009",
    "addr:street":"Calle De Magdalena",
    "iso:country":"ES",
    "sg:address":"Calle de Magdalena, 29",
    "sg:city":"Oviedo",
    "sg:orig_category":"Farmacias",
    "sg:phone":"+34 985 21 49 46",
    "sg:postcode":"33009",
    "sg:province":"Asturias",
    "wof:name":"De La Vega Mugica Maria Antonia",
    "wof:placetype":"venue"
},
  "geometry": {"coordinates":[-5.8451189995,43.3592796326],"type":"Point"}
}