{
  "type": "Feature",
  "properties": {
    "addr:full":"Calle de Luna, 39 Puerto De Santa Maria C\u00e1diz 11500",
    "addr:housenumber":"39",
    "addr:postcode":"11500",
    "addr:street":"Calle De Luna;Ca\u0301Diz",
    "iso:country":"ES",
    "sg:address":"Calle de Luna, 39",
    "sg:city":"Puerto De Santa Maria",
    "sg:orig_category":"Alquiler De Veh\u00cdculos: Turismos Y Utilitarios",
    "sg:phone":"+34 956 54 12 70",
    "sg:postcode":"11500",
    "sg:province":"C\u00e1diz",
    "sg:website":"www.bahiarentacar.com",
    "wof:name":"Bahia Rent A Car S.l.",
    "wof:placetype":"venue"
},
  "geometry": {"coordinates":[-6.2266039848,36.5990867615],"type":"Point"}
}