{
  "type": "Feature",
  "properties": {
    "addr:full":"Ctra Tacoronte Tejina, 11 Tacoronte Santa Cruz De Tenerife 38350",
    "addr:housenumber":"11",
    "addr:postcode":"38350",
    "addr:street":"Ctra Tacoronte Tejina",
    "iso:country":"ES",
    "sg:address":"Ctra Tacoronte Tejina, 11",
    "sg:city":"Tacoronte",
    "sg:orig_category":"Bazares, Art\u00cdculos De Limpieza Y De Cocina (al Por Menor)",
    "sg:phone":"+34 922 56 16 00",
    "sg:postcode":"38350",
    "sg:province":"Santa Cruz De Tenerife",
    "wof:name":"Marrero Castro Amadeo",
    "wof:placetype":"venue"
},
  "geometry": {"coordinates":[-16.4145374298,28.4777145386],"type":"Point"}
}