{
  "type": "Feature",
  "properties": {
    "addr:full":"Calle de Wenceslao Argumosa, 2 Guadalajara Guadalajara 19003",
    "addr:housenumber":"2",
    "addr:postcode":"19003",
    "addr:street":"Calle De Wenceslao Argumosa",
    "iso:country":"ES",
    "sg:address":"Calle de Wenceslao Argumosa, 2",
    "sg:city":"Guadalajara",
    "sg:classifiers":[
        {
            "category":"Autos & Motor Vehicles",
            "subcategory":"Automobile Sales",
            "type":"Retail Goods"
        }
    ],
    "sg:phone":"+34 949 21 91 70",
    "sg:postcode":"19003",
    "sg:province":"Guadalajara",
    "sg:website":"www.sancristobalguada.es",
    "wof:name":"San Cristobal Guadalajara S.a.l.",
    "wof:placetype":"venue"
},
  "geometry": {"coordinates":[-3.1639370918,40.6289863586],"type":"Point"}
}