{
  "type": "Feature",
  "properties": {
    "addr:full":"Calle de Escarcha, 17 Villanueva De Los Infantes Ciudad Real 13320",
    "addr:housenumber":"17",
    "addr:postcode":"13320",
    "addr:street":"Calle De Escarcha;Infantes",
    "iso:country":"ES",
    "sg:address":"Calle de Escarcha, 17",
    "sg:city":"Villanueva De Los Infantes",
    "sg:orig_category":"Mec\u00c1nico Del Autom\u00d3vil",
    "sg:phone":"+34 926 36 05 52",
    "sg:postcode":"13320",
    "sg:province":"Ciudad Real",
    "wof:name":"Talleres Vellon Y Simarro S.l.",
    "wof:placetype":"venue"
},
  "geometry": {"coordinates":[-3.0129089355,38.7400398254],"type":"Point"}
}