{
  "type": "Feature",
  "properties": {
    "iso:country":"ES",
    "sg:address":"Calle de Monta\u00d1a Chica, 2",
    "sg:city":"Cristianos",
    "sg:orig_category":"Congelados: Productos Alimentarios (al Por Menor)",
    "sg:phone":"+34 922 79 42 18",
    "sg:postcode":"38650",
    "sg:province":"Santa Cruz De Tenerife",
    "wof:name":"Congelados Acoran S.l.",
    "wof:placetype":"venue"
},
  "geometry": {"coordinates":[-16.7152385712,28.053850174],"type":"Point"}
}