{
  "type": "Feature",
  "properties": {
    "addr:full":"Calle de Elkano Tar Juan Sebastian, 3 Bermeo Vizcaya 48370",
    "addr:housenumber":"3",
    "addr:postcode":"48370",
    "addr:street":"Calle De Elkano Tar Juan Sebastian",
    "iso:country":"ES",
    "sg:address":"Calle de Elkano Tar Juan Sebastian, 3",
    "sg:city":"Bermeo",
    "sg:orig_category":"Motores Diessel",
    "sg:phone":"+34 946 18 70 27",
    "sg:postcode":"48370",
    "sg:province":"Vizcaya",
    "wof:name":"Motores Echevarria S.l.",
    "wof:placetype":"venue"
},
  "geometry": {"coordinates":[-2.7270441055,43.4184799194],"type":"Point"}
}