{
  "type": "Feature",
  "properties": {
    "iso:country":"ES",
    "sg:address":"Plaz Campillo, S/n",
    "sg:city":"Paredes Nava",
    "sg:orig_category":"Confecci\u00d3n De Ropa Interior",
    "sg:phone":"+34 979 83 00 74",
    "sg:postcode":"34300",
    "sg:province":"Palencia",
    "wof:name":"Parede\u00f1a Sociedad Cooperativa",
    "wof:placetype":"venue"
},
  "geometry": {"coordinates":[-4.6880588531,42.1550292969],"type":"Point"}
}