{
  "type": "Feature",
  "properties": {
    "iso:country":"ES",
    "sg:address":"Calle de Pepe Alba, 20",
    "sg:city":"Valencia",
    "sg:orig_category":"Desinfecci\u00d3n, Desinsectaci\u00d3n, Desratizaci\u00d3n",
    "sg:phone":"+34 963 30 50 78",
    "sg:postcode":"46022",
    "sg:province":"Valencia",
    "sg:website":"www.desinfeccionesalcora.com",
    "wof:name":"Desinfecciones Alcora S. A.",
    "wof:placetype":"venue"
},
  "geometry": {"coordinates":[-0.3473530114,39.4676551819],"type":"Point"}
}