{
  "type": "Feature",
  "properties": {
    "iso:country":"ES",
    "sg:address":"Calle de Dion Cassio, S/n",
    "sg:city":"Merida",
    "sg:orig_category":"Agencias Y Agentes Comerciales, Representantes",
    "sg:phone":"+34 924 31 55 92",
    "sg:postcode":"06800",
    "sg:province":"Badajoz",
    "wof:name":"Texeiras Vivas Antonio",
    "wof:placetype":"venue"
},
  "geometry": {"coordinates":[-6.342924118,38.9110794067],"type":"Point"}
}