{
  "type": "Feature",
  "properties": {
    "addr:full":"Cno. Fus, S/n Massanassa Valencia 46470",
    "addr:housenumber":"/ n",
    "addr:postcode":"46470",
    "addr:street":"Fus S",
    "iso:country":"ES",
    "sg:address":"Cno. Fus, S/n",
    "sg:city":"Massanassa",
    "sg:classifiers":[
        {
            "category":"Building & Trades",
            "subcategory":"Construction",
            "type":"Services"
        }
    ],
    "sg:phone":"+34 961 25 02 95",
    "sg:postcode":"46470",
    "sg:province":"Valencia",
    "sg:tags":[
        "calefacci\u00d3n",
        "central",
        "para",
        "de",
        "fabricaci\u00d3n",
        "caldera"
    ],
    "wof:name":"Ma\u00f1as Inox S.l.",
    "wof:placetype":"venue"
},
  "geometry": {"coordinates":[-0.389110297,39.4096183777],"type":"Point"}
}