{
  "type": "Feature",
  "properties": {
    "addr:full":"Calle de Evora, 6 Jerez De La Frontera C\u00e1diz 11402",
    "addr:housenumber":"6",
    "addr:postcode":"11402",
    "addr:street":"Calle De Evora",
    "iso:country":"ES",
    "sg:address":"Calle de Evora, 6",
    "sg:city":"Jerez De La Frontera",
    "sg:orig_category":"Bisuter\u00cda, Joyer\u00cda, Relojer\u00cda (al Por Menor)",
    "sg:phone":"+34 956 33 85 57",
    "sg:postcode":"11402",
    "sg:province":"C\u00e1diz",
    "wof:name":"Evora Inversiones S.l.",
    "wof:placetype":"venue"
},
  "geometry": {"coordinates":[-6.1344461441,36.6810531616],"type":"Point"}
}