{
  "type": "Feature",
  "properties": {
    "iso:country":"ES",
    "sg:address":"Calle de San Isidro, 9",
    "sg:city":"Majadahonda",
    "sg:orig_category":"Ropa Para Se\u00d1oras Y Caballeros (al Por Menor)",
    "sg:phone":"+34 916 38 56 18",
    "sg:postcode":"28220",
    "sg:province":"Madrid",
    "wof:name":"Zheng  Xiangwu",
    "wof:placetype":"venue"
},
  "geometry": {"coordinates":[-3.8712415695,40.4729614258],"type":"Point"}
}