{
  "type": "Feature",
  "properties": {
    "addr:full":"Plaz Cristo, 7 Torrijos Toledo 45500",
    "addr:housenumber":"7",
    "addr:postcode":"45500",
    "addr:street":"Cristo",
    "iso:country":"ES",
    "sg:address":"Plaz Cristo, 7",
    "sg:city":"Torrijos",
    "sg:orig_category":"Venta, Instalaci\u00d3n De Cocinas",
    "sg:phone":"+34 925 76 23 59",
    "sg:postcode":"45500",
    "sg:province":"Toledo",
    "wof:name":"La Perla Park C.b.",
    "wof:placetype":"venue"
},
  "geometry": {"coordinates":[-4.2850618362,39.9824829102],"type":"Point"}
}