{
  "type": "Feature",
  "properties": {
    "addr:full":"Pl. M. Sants, S/n Barcelona Barcelona 08038",
    "addr:housenumber":"s / n",
    "addr:postcode":"08038",
    "addr:street":"M. Sants",
    "iso:country":"ES",
    "sg:address":"Pl. M. Sants, S/n",
    "sg:city":"Barcelona",
    "sg:orig_category":"Carnicer\u00cdas, Carnicer\u00cdas",
    "sg:phone":"+34 933 31 05 21",
    "sg:postcode":"08038",
    "sg:province":"Barcelona",
    "wof:name":"Felipe Haro Jorge",
    "wof:placetype":"venue"
},
  "geometry": {"coordinates":[2.1389250755,41.3604545593],"type":"Point"}
}