{
  "type": "Feature",
  "properties": {
    "addr:full":"Carrer de Sant Vicent Ferrer, 31 Crevillent Alicante 03330",
    "addr:housenumber":"31",
    "addr:postcode":"03330",
    "addr:street":"Carrer De Sant Vicent Ferrer",
    "iso:country":"ES",
    "sg:address":"Carrer de Sant Vicent Ferrer, 31",
    "sg:city":"Crevillent",
    "sg:orig_category":"Plomeros",
    "sg:phone":"+34 965 40 15 65",
    "sg:postcode":"03330",
    "sg:province":"Alicante",
    "wof:name":"Soriano Galipienso Jose Maria",
    "wof:placetype":"venue"
},
  "geometry": {"coordinates":[-0.8049679995,38.2465248108],"type":"Point"}
}