{
  "type": "Feature",
  "properties": {
    "addr:full":"Calle de Deya, 22 Camas Sevilla 41900",
    "addr:housenumber":"22",
    "addr:postcode":"41900",
    "addr:street":"Calle De Deya",
    "iso:country":"ES",
    "sg:address":"Calle de Deya, 22",
    "sg:city":"Camas",
    "sg:orig_category":"Farmacias",
    "sg:phone":"+34 954 39 40 62",
    "sg:postcode":"41900",
    "sg:province":"Sevilla",
    "wof:name":"Galindo Farmacia S.a.",
    "wof:placetype":"venue"
},
  "geometry": {"coordinates":[-6.0342326164,37.4058456421],"type":"Point"}
}