{
  "type": "Feature",
  "properties": {
    "addr:full":"Rond Outeiro, 178 Coru\u00d1a La Coru\u00f1a 15007",
    "addr:housenumber":"178",
    "addr:postcode":"15007",
    "addr:street":"Outeiro;Corun\u0303A",
    "iso:country":"ES",
    "sg:address":"Rond Outeiro, 178",
    "sg:city":"Coru\u00d1a",
    "sg:orig_category":"Venta, Colocaci\u00d3n, Reparaci\u00d3n De Parabrisas, Techos Descapotables",
    "sg:phone":"+34 981 15 24 56",
    "sg:postcode":"15007",
    "sg:province":"La Coru\u00f1a",
    "sg:website":"www.guardianexpress.es",
    "wof:name":"Guardian Glass Express S.l.",
    "wof:placetype":"venue"
},
  "geometry": {"coordinates":[-8.4115686417,43.3556938171],"type":"Point"}
}