{
  "type": "Feature",
  "properties": {
    "iso:country":"ES",
    "sg:address":"Avda Tres Cruces, 19",
    "sg:city":"Valencia",
    "sg:orig_category":"Farmacias",
    "sg:phone":"+34 963 59 19 53",
    "sg:postcode":"46018",
    "sg:province":"Valencia",
    "wof:name":"Avi\u00f1o Bolinches Maria Amparo",
    "wof:placetype":"venue"
},
  "geometry": {"coordinates":[-0.4057410955,39.4684753418],"type":"Point"}
}