{
  "type": "Feature",
  "properties": {
    "iso:country":"ES",
    "sg:address":"Avda Reyes Catolicos, 51",
    "sg:city":"Dos Hermanas",
    "sg:orig_category":"Florister\u00cdas",
    "sg:phone":"+34 955 66 98 00",
    "sg:postcode":"41700",
    "sg:province":"Sevilla",
    "wof:name":"Garrido Arrabal Manuel",
    "wof:placetype":"venue"
},
  "geometry": {"coordinates":[-5.9249968529,37.2779464722],"type":"Point"}
}