{
  "type": "Feature",
  "properties": {
    "addr:full":"Av Paral.lel, 150 Barcelona Barcelona 08015",
    "addr:housenumber":"150",
    "addr:postcode":"08015",
    "addr:street":"Av Paral.Lel",
    "iso:country":"ES",
    "sg:address":"Av Paral.lel, 150",
    "sg:city":"Barcelona",
    "sg:orig_category":"Peluqueros: De Se\u00d1oras",
    "sg:phone":"+34 934 26 42 32",
    "sg:postcode":"08015",
    "sg:province":"Barcelona",
    "wof:name":"Gri\u00f1o Terral S.a.",
    "wof:placetype":"venue"
},
  "geometry": {"coordinates":[2.1582169533,41.3751602173],"type":"Point"}
}