{
  "type": "Feature",
  "properties": {
    "iso:country":"ES",
    "sg:address":"Carr Joanot Martorell, 34",
    "sg:city":"Quart Poblet",
    "sg:orig_category":"Sociedades, Compa\u00d1\u00cdas Aseguradoras",
    "sg:phone":"+34 961 53 07 07",
    "sg:postcode":"46930",
    "sg:province":"Valencia",
    "wof:name":"Cervera Garcia Cristina",
    "wof:placetype":"venue"
},
  "geometry": {"coordinates":[-0.4438279867,39.4824638367],"type":"Point"}
}