{
  "type": "Feature",
  "properties": {
    "iso:country":"ES",
    "sg:address":"Carrer de Reis Catolics (dels), 4",
    "sg:city":"Gata Gorgos",
    "sg:orig_category":"Asesor\u00cda Fiscal Y Jur\u00cddica",
    "sg:phone":"+34 965 75 76 16",
    "sg:postcode":"03740",
    "sg:province":"Alicante",
    "wof:name":"Carrio Consultores S.l.",
    "wof:placetype":"venue"
},
  "geometry": {"coordinates":[0.0853850022,38.7746047974],"type":"Point"}
}