{
  "type": "Feature",
  "properties": {
    "addr:full":"Calle de Navellos, 14 Valencia Valencia 46003",
    "addr:housenumber":"14",
    "addr:postcode":"46003",
    "addr:street":"Calle De Navellos",
    "iso:country":"ES",
    "sg:address":"Calle de Navellos, 14",
    "sg:city":"Valencia",
    "sg:orig_category":"Ceras Y Encaustos (fabricaci\u00d3n, Al Por Mayor)",
    "sg:phone":"+34 963 91 86 22",
    "sg:postcode":"46003",
    "sg:province":"Valencia",
    "wof:name":"Cirios Felipo S.l.",
    "wof:placetype":"venue"
},
  "geometry": {"coordinates":[-0.3747780025,39.4774703979],"type":"Point"}
}