{
  "type": "Feature",
  "properties": {
    "iso:country":"ES",
    "sg:address":"Carr Forn, 77",
    "sg:city":"Cala Ferrera",
    "sg:orig_category":"Agencias De Viajes",
    "sg:phone":"+34 971 65 98 45",
    "sg:postcode":"07669",
    "sg:province":"Islas Baleares",
    "wof:name":"Alcances 2012 S.l.",
    "wof:placetype":"venue"
},
  "geometry": {"coordinates":[2.8577105999,39.5341796875],"type":"Point"}
}