{
  "type": "Feature",
  "properties": {
    "iso:country":"ES",
    "sg:address":"Pase Zarategi De, 100",
    "sg:city":"Donostia-san Sebastian",
    "sg:orig_category":"Asilos De Ancianos. Centros Privados",
    "sg:phone":"+34 943 27 29 76",
    "sg:postcode":"20015",
    "sg:province":"Guip\u00f9zcoa",
    "wof:name":"Ute Uca Txara 1",
    "wof:placetype":"venue"
},
  "geometry": {"coordinates":[-1.9563059807,43.3141098022],"type":"Point"}
}