{
  "type": "Feature",
  "properties": {
    "iso:country":"ES",
    "sg:address":"Calle de Ricardo Ortiz, 10",
    "sg:city":"Madrid",
    "sg:orig_category":"Estancos",
    "sg:phone":"+34 913 56 57 41",
    "sg:postcode":"28017",
    "sg:province":"Madrid",
    "wof:name":"Palacios Bautista Maria Anunciacion",
    "wof:placetype":"venue"
},
  "geometry": {"coordinates":[-3.6581840515,40.4292144775],"type":"Point"}
}