{
  "type": "Feature",
  "properties": {
    "addr:full":"Nueva, 2 Baena C\u00f3rdoba 14850",
    "addr:housenumber":"2",
    "addr:postcode":"14850",
    "addr:street":"Nueva",
    "iso:country":"ES",
    "sg:address":"Nueva, 2",
    "sg:city":"Baena",
    "sg:orig_category":"Farmacias",
    "sg:phone":"+34 957 67 01 62",
    "sg:postcode":"14850",
    "sg:province":"C\u00f3rdoba",
    "wof:name":"De Prado Herrero Jorge",
    "wof:placetype":"venue"
},
  "geometry": {"coordinates":[-4.2387900352,37.6705245972],"type":"Point"}
}