{
  "type": "Feature",
  "properties": {
    "iso:country":"ES",
    "sg:address":"Avda San Pablo (de), 27",
    "sg:city":"Coslada",
    "sg:orig_category":"Productos Qu\u00cdmicos (fabricaci\u00d3n, Al Por Mayor)",
    "sg:phone":"+34 916 69 40 54",
    "sg:postcode":"28820",
    "sg:province":"Madrid",
    "wof:name":"Justesa Imagen S.a.",
    "wof:placetype":"venue"
},
  "geometry": {"coordinates":[-3.532063961,40.439655304],"type":"Point"}
}