{
  "type": "Feature",
  "properties": {
    "iso:country":"ES",
    "sg:address":"Calle de Maestro Bartolome, 7",
    "sg:city":"Jaen",
    "sg:orig_category":"Organizaciones Internacionales",
    "sg:phone":"+34 953 27 15 70",
    "sg:postcode":"23007",
    "sg:province":"Ja\u00e9n",
    "wof:name":"Caritas Interparroquial",
    "wof:placetype":"venue"
},
  "geometry": {"coordinates":[-3.7908558846,37.7776489258],"type":"Point"}
}