{
  "type": "Feature",
  "properties": {
    "addr:full":"Avgd Port, 19 Vila Joiosa Alicante 03570",
    "addr:housenumber":"19",
    "addr:postcode":"03570",
    "addr:street":"Vila Joiosa",
    "iso:country":"ES",
    "sg:address":"Avgd Port, 19",
    "sg:city":"Vila Joiosa",
    "sg:orig_category":"Caf\u00c9s, Bares, Cervecer\u00cdas",
    "sg:phone":"+34 966 81 02 18",
    "sg:postcode":"03570",
    "sg:province":"Alicante",
    "wof:name":"La Vila Colon S.l.",
    "wof:placetype":"venue"
},
  "geometry": {"coordinates":[-0.2327190042,38.505821228],"type":"Point"}
}