{
  "type": "Feature",
  "properties": {
    "iso:country":"ES",
    "sg:address":"Carrer de Navas De Tolosa, 296",
    "sg:city":"Barcelona",
    "sg:orig_category":"Cervecer\u00cdas",
    "sg:phone":"+34 933 49 19 70",
    "sg:postcode":"08027",
    "sg:province":"Barcelona",
    "wof:name":"Mantenimiento Y Servicios Bernal S.l.",
    "wof:placetype":"venue"
},
  "geometry": {"coordinates":[2.1858379841,41.4162406921],"type":"Point"}
}