{
  "type": "Feature",
  "properties": {
    "iso:country":"ES",
    "sg:address":"Calle de Torre Del Mar, 6",
    "sg:city":"Malaga",
    "sg:orig_category":"Electrodom\u00c9sticos (fabricaci\u00d3n, Al Por Mayor)",
    "sg:phone":"+34 952 23 05 60",
    "sg:postcode":"29004",
    "sg:province":"M\u00e1laga",
    "wof:name":"Activs Lucas S.l.",
    "wof:placetype":"venue"
},
  "geometry": {"coordinates":[-4.49715662,36.6980056763],"type":"Point"}
}