{
  "type": "Feature",
  "properties": {
    "iso:country":"ES",
    "sg:address":"Calle de Reyes, 8",
    "sg:city":"Madrid",
    "sg:orig_category":"Caf\u00c9s, Bares, Cervecer\u00cdas",
    "sg:phone":"+34 915 47 38 68",
    "sg:postcode":"28015",
    "sg:province":"Madrid",
    "wof:name":"Cocarrois S.l.",
    "wof:placetype":"venue"
},
  "geometry": {"coordinates":[-3.7095060349,40.4242935181],"type":"Point"}
}