{
  "type": "Feature",
  "properties": {
    "addr:full":"Via Augusta, 261 Barcelona Barcelona 08017",
    "addr:housenumber":"261",
    "addr:postcode":"08017",
    "addr:street":"Via Augusta",
    "iso:country":"ES",
    "sg:address":"Via Augusta, 261",
    "sg:city":"Barcelona",
    "sg:orig_category":"Agencias Y Agentes Comerciales, Representantes",
    "sg:phone":"+34 932 05 86 77",
    "sg:postcode":"08017",
    "sg:province":"Barcelona",
    "wof:name":"Mecanica Dayku-tech Espa\u00f1a S.l",
    "wof:placetype":"venue"
},
  "geometry": {"coordinates":[2.1321940422,41.3976211548],"type":"Point"}
}