{
  "type": "Feature",
  "properties": {
    "addr:full":"Carrer de Antoni Marques, 5 Palma Islas Baleares 07003",
    "addr:housenumber":"5",
    "addr:postcode":"07003",
    "addr:street":"Carrer De Antoni Marques",
    "iso:country":"ES",
    "sg:address":"Carrer de Antoni Marques, 5",
    "sg:city":"Palma",
    "sg:orig_category":"Muebles, Minoristas",
    "sg:phone":"+34 971 75 01 33",
    "sg:postcode":"07003",
    "sg:province":"Islas Baleares",
    "wof:name":"Moreno Del Salto Antonio",
    "wof:placetype":"venue"
},
  "geometry": {"coordinates":[2.6517488956,39.5796508789],"type":"Point"}
}