{
  "type": "Feature",
  "properties": {
    "iso:country":"ES",
    "sg:address":"Calle de Doctor Fleming, 3",
    "sg:city":"Castilleja Cuesta",
    "sg:orig_category":"Peluqueros: De Se\u00d1oras",
    "sg:phone":"+34 954 16 05 88",
    "sg:postcode":"41950",
    "sg:province":"Sevilla",
    "wof:name":"Montes Tovar Noelia",
    "wof:placetype":"venue"
},
  "geometry": {"coordinates":[-6.0571565628,37.3850860596],"type":"Point"}
}