{
  "type": "Feature",
  "properties": {
    "iso:country":"ES",
    "sg:address":"Calle de Aniceto Coloma, 36",
    "sg:city":"Almansa",
    "sg:orig_category":"Electricidad, Electr\u00d3nica: Suministros (al Por Menor)",
    "sg:phone":"+34 967 34 11 55",
    "sg:postcode":"02640",
    "sg:province":"Albacete",
    "wof:name":"Ruano Ruano Antonio",
    "wof:placetype":"venue"
},
  "geometry": {"coordinates":[-1.0977965593,38.86951828],"type":"Point"}
}