{
  "type": "Feature",
  "properties": {
    "addr:full":"Calle de Kanpatorrosteta Kalea, 3 Durango Vizcaya 48200",
    "addr:housenumber":"3",
    "addr:postcode":"48200",
    "addr:street":"Calle De Kanpatorrosteta Kalea",
    "iso:country":"ES",
    "sg:address":"Calle de Kanpatorrosteta Kalea, 3",
    "sg:city":"Durango",
    "sg:orig_category":"Sociedades, Compa\u00d1\u00cdas Aseguradoras",
    "sg:phone":"+34 946 81 92 00",
    "sg:postcode":"48200",
    "sg:province":"Vizcaya",
    "wof:name":"Garitaonandia Seguros C.b.",
    "wof:placetype":"venue"
},
  "geometry": {"coordinates":[-2.630975008,43.1683387756],"type":"Point"}
}