{
  "type": "Feature",
  "properties": {
    "addr:full":"Carrer de Terral, 26 Riudoms Tarragona 43330",
    "addr:housenumber":"26",
    "addr:postcode":"43330",
    "addr:street":"Carrer De Terral",
    "iso:country":"ES",
    "sg:address":"Carrer de Terral, 26",
    "sg:city":"Riudoms",
    "sg:orig_category":"Promotores Constructores",
    "sg:phone":"+34 977 85 14 28",
    "sg:postcode":"43330",
    "sg:province":"Tarragona",
    "wof:name":"Promocat Selrac S.l.",
    "wof:placetype":"venue"
},
  "geometry": {"coordinates":[1.0522149801,41.1348457336],"type":"Point"}
}