{
  "type": "Feature",
  "properties": {
    "iso:country":"ES",
    "sg:address":"Calle de Colon, 7",
    "sg:city":"Malaga",
    "sg:orig_category":"Empresas De Pintura Y Revestimientos",
    "sg:phone":"+34 952 26 45 00",
    "sg:postcode":"29014",
    "sg:province":"M\u00e1laga",
    "wof:name":"Merida Sabastro Diego",
    "wof:placetype":"venue"
},
  "geometry": {"coordinates":[-4.4220747948,36.7318725586],"type":"Point"}
}