{
  "type": "Feature",
  "properties": {
    "addr:full":"Carr Llibertat, 137 Vilanova I La Geltru Barcelona 08800",
    "addr:housenumber":"137",
    "addr:postcode":"08800",
    "addr:street":"Carr Llibertat",
    "iso:country":"ES",
    "sg:address":"Carr Llibertat, 137",
    "sg:city":"Vilanova I La Geltru",
    "sg:orig_category":"Carnicer\u00cdas, Carnicer\u00cdas",
    "sg:phone":"+34 938 15 52 79",
    "sg:postcode":"08800",
    "sg:province":"Barcelona",
    "wof:name":"Fernandez Llorca Maria Luz",
    "wof:placetype":"venue"
},
  "geometry": {"coordinates":[1.7294859886,41.2184867859],"type":"Point"}
}