{
  "type": "Feature",
  "properties": {
    "iso:country":"ES",
    "sg:address":"Calle de Doctor Lopez Pi\u00d1ero, 1",
    "sg:city":"Mula",
    "sg:orig_category":"Servicios Gsm",
    "sg:phone":"+34 968 66 43 75",
    "sg:postcode":"30170",
    "sg:province":"Murcia",
    "wof:name":"Sistemas Del Noroeste De Murcia S.l.",
    "wof:placetype":"venue"
},
  "geometry": {"coordinates":[-1.4935810566,38.0397377014],"type":"Point"}
}