{
  "type": "Feature",
  "properties": {
    "addr:full":"Ctra Montblanc (de), 8 Espluga Francoli Tarragona 43440",
    "addr:postcode":"43440",
    "addr:street":"Ctra Montblanc De 8 Espluga",
    "iso:country":"ES",
    "sg:address":"Ctra Montblanc (de), 8",
    "sg:city":"Espluga Francoli",
    "sg:orig_category":"Bebidas",
    "sg:phone":"+34 977 87 04 18",
    "sg:postcode":"43440",
    "sg:province":"Tarragona",
    "wof:name":"Franques Raurell Josep Maria",
    "wof:placetype":"venue"
},
  "geometry": {"coordinates":[1.1049230099,41.3961868286],"type":"Point"}
}