{
  "type": "Feature",
  "properties": {
    "iso:country":"ES",
    "sg:address":"Calle de Papa Luna, 7",
    "sg:city":"Segorbe",
    "sg:orig_category":"Reposter\u00cdas",
    "sg:phone":"+34 964 71 09 81",
    "sg:postcode":"12400",
    "sg:province":"Castell\u00f3n",
    "wof:name":"Perez Perez Vicente",
    "wof:placetype":"venue"
},
  "geometry": {"coordinates":[-0.4881739914,39.8531112671],"type":"Point"}
}