{
  "type": "Feature",
  "properties": {
    "addr:full":"Calle de Caba, 29 Albacete Albacete 02001",
    "addr:housenumber":"29",
    "addr:postcode":"02001",
    "addr:street":"Calle De Caba",
    "iso:country":"ES",
    "sg:address":"Calle de Caba, 29",
    "sg:city":"Albacete",
    "sg:orig_category":"Peluqueros: De Se\u00d1oras",
    "sg:phone":"+34 967 22 15 13",
    "sg:postcode":"02001",
    "sg:province":"Albacete",
    "wof:name":"Corcoles Romero Rocio",
    "wof:placetype":"venue"
},
  "geometry": {"coordinates":[-1.859604001,38.9937744141],"type":"Point"}
}