{
  "type": "Feature",
  "properties": {
    "addr:full":"Calle de Nuevo Laurel, 4 Naranjeros Santa Cruz De Tenerife 38340",
    "addr:housenumber":"4",
    "addr:postcode":"38340",
    "addr:street":"Calle De Nuevo Laurel",
    "iso:country":"ES",
    "sg:address":"Calle de Nuevo Laurel, 4",
    "sg:city":"Naranjeros",
    "sg:orig_category":"Ense\u00d1ante, Direcci\u00d3n",
    "sg:phone":"+34 922 56 15 53",
    "sg:postcode":"38340",
    "sg:province":"Santa Cruz De Tenerife",
    "wof:name":"Delgado Lara Gorgonio",
    "wof:placetype":"venue"
},
  "geometry": {"coordinates":[-16.3922348022,28.4853973389],"type":"Point"}
}