{
  "type": "Feature",
  "properties": {
    "addr:full":"Calle de Elche, S/n Sevilla Sevilla 41013",
    "addr:housenumber":"s / n",
    "addr:postcode":"41013",
    "addr:street":"Calle De Elche",
    "iso:country":"ES",
    "sg:address":"Calle de Elche, S/n",
    "sg:city":"Sevilla",
    "sg:orig_category":"Marketing Directo",
    "sg:phone":"+34 954 23 24 09",
    "sg:postcode":"41013",
    "sg:province":"Sevilla",
    "wof:name":"Atento Telecomunicaciones Espa\u00d1a S.a.u.",
    "wof:placetype":"venue"
},
  "geometry": {"coordinates":[-5.9747562408,37.3512763977],"type":"Point"}
}