{
  "type": "Feature",
  "properties": {
    "addr:full":"Ctra Alcobendas A Barajas, S/n Madrid Madrid 28042",
    "addr:housenumber":"s / n",
    "addr:postcode":"28042",
    "addr:street":"Ctra Alcobendas A Barajas",
    "iso:country":"ES",
    "sg:address":"Ctra Alcobendas A Barajas, S/n",
    "sg:city":"Madrid",
    "sg:orig_category":"Promotores Constructores",
    "sg:phone":"+34 913 05 40 32",
    "sg:postcode":"28042",
    "sg:province":"Madrid",
    "wof:name":"Dragados S.a.",
    "wof:placetype":"venue"
},
  "geometry": {"coordinates":[-3.5911579132,40.4696044922],"type":"Point"}
}