{
  "type": "Feature",
  "properties": {
    "addr:full":"Calle de Aitzbitarte, Pasaje De, 5 Errenteria Guip\u00f9zcoa 20100",
    "addr:housenumber":"5",
    "addr:postcode":"20100",
    "addr:street":"Calle De Aitzbitarte Pasaje De;Guipu\u0300Zcoa",
    "iso:country":"ES",
    "sg:address":"Calle de Aitzbitarte, Pasaje De, 5",
    "sg:city":"Errenteria",
    "sg:orig_category":"Asociaciones, Organismos Culturales Y Socioeducativos",
    "sg:phone":"+34 943 51 09 62",
    "sg:postcode":"20100",
    "sg:province":"Guip\u00f9zcoa",
    "wof:name":"Ekin Bi Ocio Y Tiempo Libre, S.l.",
    "wof:placetype":"venue"
},
  "geometry": {"coordinates":[-1.8909000158,43.3099517822],"type":"Point"}
}