{
  "type": "Feature",
  "properties": {
    "iso:country":"ES",
    "sg:address":"Calle de Marques De Bolarque, 20",
    "sg:city":"Langreo",
    "sg:orig_category":"Partidos Pol\u00cdticos",
    "sg:phone":"+34 985 69 77 01",
    "sg:postcode":"33930",
    "sg:province":"Asturias",
    "wof:name":"Partido Socialista Obrero Espa\u00f1ol",
    "wof:placetype":"venue"
},
  "geometry": {"coordinates":[-5.6952271461,43.3111763],"type":"Point"}
}