{
  "type": "Feature",
  "properties": {
    "iso:country":"ES",
    "sg:address":"Calle de Ulises, 9",
    "sg:city":"Valencia",
    "sg:orig_category":"Art\u00cdculos De Madera (fabricaci\u00d3n Y Al Por Mayor)",
    "sg:phone":"+34 963 72 97 39",
    "sg:postcode":"46022",
    "sg:province":"Valencia",
    "wof:name":"Montolio Perez Enrique",
    "wof:placetype":"venue"
},
  "geometry": {"coordinates":[-0.3426589966,39.4677581787],"type":"Point"}
}