{
  "type": "Feature",
  "properties": {
    "iso:country":"ES",
    "sg:address":"Carrer de Pescadors, 28",
    "sg:city":"Premia Mar",
    "sg:orig_category":"Arquitectos",
    "sg:phone":"+34 937 52 12 82",
    "sg:postcode":"08330",
    "sg:province":"Barcelona",
    "wof:name":"Garcia Jimenez Luis",
    "wof:placetype":"venue"
},
  "geometry": {"coordinates":[2.3655281067,41.4928245544],"type":"Point"}
}