{
  "type": "Feature",
  "properties": {
    "iso:country":"ES",
    "sg:address":"Calle de Almazara, 8",
    "sg:city":"Huercal Almeria",
    "sg:orig_category":"Fabricaci\u00d3n De Harinas, S\u00c9molas, Productos De Elaboraci\u00d3n Del Grano",
    "sg:phone":"+34 950 30 15 76",
    "sg:postcode":"04230",
    "sg:province":"Almer\u00eda",
    "wof:name":"Harinera Del Andarax S.a",
    "wof:placetype":"venue"
},
  "geometry": {"coordinates":[-2.4352867603,36.8821105957],"type":"Point"}
}