{
  "type": "Feature",
  "properties": {
    "addr:full":"Calle de Porvenir, 15 Sevilla Sevilla 41013",
    "addr:housenumber":"15",
    "addr:postcode":"41013",
    "addr:street":"Calle De Porvenir",
    "iso:country":"ES",
    "sg:address":"Calle de Porvenir, 15",
    "sg:city":"Sevilla",
    "sg:orig_category":"Ense\u00d1anza Variada",
    "sg:phone":"+34 954 23 38 38",
    "sg:postcode":"41013",
    "sg:province":"Sevilla",
    "sg:website":"www.iis-seville.org",
    "wof:name":"Dura Domenech Juan",
    "wof:placetype":"venue"
},
  "geometry": {"coordinates":[-5.9833431244,37.3729743958],"type":"Point"}
}