{
  "type": "Feature",
  "properties": {
    "iso:country":"ES",
    "sg:address":"Cami Son Rapinya, 14",
    "sg:city":"Vileta -son Rapinya",
    "sg:orig_category":"Centros De Reservas Hoteleras",
    "sg:phone":"+34 971 60 98 09",
    "sg:postcode":"07013",
    "sg:province":"Islas Baleares",
    "wof:name":"Serinco S.l.",
    "wof:placetype":"venue"
},
  "geometry": {"coordinates":[2.618035078,39.5852813721],"type":"Point"}
}