{
  "type": "Feature",
  "properties": {
    "iso:country":"ES",
    "sg:address":"Galicia(p I El Pastoret), 4",
    "sg:city":"Monovar",
    "sg:orig_category":"Ebanister\u00cda",
    "sg:phone":"+34 966 96 00 28",
    "sg:postcode":"03640",
    "sg:province":"Alicante",
    "wof:name":"Mu\u00f1oz Ribera Jose",
    "wof:placetype":"venue"
},
  "geometry": {"coordinates":[-0.8313900232,38.4465789795],"type":"Point"}
}