{
  "type": "Feature",
  "properties": {
    "iso:country":"ES",
    "sg:address":"Plaz Santa Barbara, 7",
    "sg:city":"Vitoria-gasteiz",
    "sg:orig_category":"Procuradores",
    "sg:phone":"+34 945 28 80 04",
    "sg:postcode":"01004",
    "sg:province":"\u00c1lava",
    "wof:name":"Sanchez Valdespina Constantino",
    "wof:placetype":"venue"
},
  "geometry": {"coordinates":[-2.6675798893,42.845249176],"type":"Point"}
}