{
  "type": "Feature",
  "properties": {
    "iso:country":"ES",
    "sg:address":"Carrer de L'alfambra, 14",
    "sg:city":"Barcelona",
    "sg:orig_category":"Agencias Y Agentes Comerciales, Representantes",
    "sg:phone":"+34 932 03 82 89",
    "sg:postcode":"08034",
    "sg:province":"Barcelona",
    "wof:name":"Braviz Marraco Antonio",
    "wof:placetype":"venue"
},
  "geometry": {"coordinates":[2.1125383377,41.3865318298],"type":"Point"}
}