{
  "type": "Feature",
  "properties": {
    "addr:full":"Calle de Doctor Rodriguez De La Fuente, 43 Valencia Valencia 46019",
    "addr:housenumber":"43",
    "addr:postcode":"46019",
    "addr:street":"Calle De Doctor Rodriguez De La Fuente",
    "iso:country":"ES",
    "sg:address":"Calle de Doctor Rodriguez De La Fuente, 43",
    "sg:city":"Valencia",
    "sg:orig_category":"Productos Refractarios (fabricaci\u00d3n, Al Por Mayor)",
    "sg:phone":"+34 963 65 16 62",
    "sg:postcode":"46019",
    "sg:province":"Valencia",
    "wof:name":"Moraga Perez Luis",
    "wof:placetype":"venue"
},
  "geometry": {"coordinates":[-0.3781285882,39.4977722168],"type":"Point"}
}