{
  "type": "Feature",
  "properties": {
    "iso:country":"ES",
    "sg:address":"Rbla Jaume I, 46",
    "sg:city":"Cambrils",
    "sg:orig_category":"Inmobiliaria (agencias)",
    "sg:phone":"+34 977 36 95 39",
    "sg:postcode":"43850",
    "sg:province":"Tarragona",
    "wof:name":"Euro-star 2000 Administracion Y Gestion S.l.",
    "wof:placetype":"venue"
},
  "geometry": {"coordinates":[1.0647890568,41.0663528442],"type":"Point"}
}