{
  "type": "Feature",
  "properties": {
    "iso:country":"ES",
    "sg:address":"Calle de Arana Tar Sabin, 15",
    "sg:city":"Ondarroa",
    "sg:orig_category":"Barbacoas Y Accesorios",
    "sg:phone":"+34 946 83 01 04",
    "sg:postcode":"48700",
    "sg:province":"Vizcaya",
    "wof:name":"Pe\u00f1a Manterola Jose Manuel",
    "wof:placetype":"venue"
},
  "geometry": {"coordinates":[-2.4282829762,43.3206710815],"type":"Point"}
}