{
  "type": "Feature",
  "properties": {
    "addr:full":"Calle de San Cristobal, 32 Puente-genil C\u00f3rdoba 14500",
    "addr:housenumber":"32",
    "addr:postcode":"14500",
    "addr:street":"Calle De San Cristobal;Co\u0301Rdoba",
    "iso:country":"ES",
    "sg:address":"Calle de San Cristobal, 32",
    "sg:city":"Puente-genil",
    "sg:orig_category":"Alquiler De V\u00cddeo",
    "sg:phone":"+34 957 60 70 21",
    "sg:postcode":"14500",
    "sg:province":"C\u00f3rdoba",
    "wof:name":"Chia Cejas Sergio",
    "wof:placetype":"venue"
},
  "geometry": {"coordinates":[-4.771282196,37.3889122009],"type":"Point"}
}