{
  "type": "Feature",
  "properties": {
    "addr:full":"Calle de Rafael Barez, 21 Coru\u00d1a La Coru\u00f1a 15009",
    "addr:housenumber":"21",
    "addr:postcode":"15009",
    "addr:street":"Calle De Rafael Barez;La Corun\u0303A",
    "iso:country":"ES",
    "sg:address":"Calle de Rafael Barez, 21",
    "sg:city":"Coru\u00d1a",
    "sg:orig_category":"Agencias Y Agentes Comerciales, Representantes",
    "sg:phone":"+34 981 28 52 67",
    "sg:postcode":"15009",
    "sg:province":"La Coru\u00f1a",
    "wof:name":"Lastra Perez Jose",
    "wof:placetype":"venue"
},
  "geometry": {"coordinates":[-8.398525238,43.346622467],"type":"Point"}
}