{
  "type": "Feature",
  "properties": {
    "iso:country":"ES",
    "sg:address":"Carr Anuncivay, 13",
    "sg:city":"Mao",
    "sg:orig_category":"Arquitectos",
    "sg:phone":"+34 971 35 26 96",
    "sg:postcode":"07702",
    "sg:province":"Islas Baleares",
    "wof:name":"Crespi Leon Francisco",
    "wof:placetype":"venue"
},
  "geometry": {"coordinates":[4.2656159401,39.8878326416],"type":"Point"}
}