{
  "type": "Feature",
  "properties": {
    "iso:country":"ES",
    "sg:address":"Pase Maritimo Rey De Espa\u00d1a, S/n",
    "sg:city":"Fuengirola",
    "sg:orig_category":"Peluqueros: De Se\u00d1oras",
    "sg:phone":"+34 952 46 19 07",
    "sg:postcode":"29640",
    "sg:province":"M\u00e1laga",
    "wof:name":"Galan Casero Rosa Isabel",
    "wof:placetype":"venue"
},
  "geometry": {"coordinates":[-4.6191391945,36.5422058105],"type":"Point"}
}