{
  "type": "Feature",
  "properties": {
    "iso:country":"ES",
    "sg:address":"Carrer de Sancho De Avila, 54",
    "sg:city":"Barcelona",
    "sg:orig_category":"Arreglo, Reparaci\u00d3n, Piezas Sueltas De Televisi\u00d3n, V\u00cddeo, Hi",
    "sg:phone":"+34 902 15 30 60",
    "sg:postcode":"08018",
    "sg:province":"Barcelona",
    "sg:website":"www.panasonic.es",
    "wof:name":"Panasonic Espa\u00d1a S.a.",
    "wof:placetype":"venue"
},
  "geometry": {"coordinates":[2.189964056,41.3985481262],"type":"Point"}
}