{
  "type": "Feature",
  "properties": {
    "iso:country":"ES",
    "sg:address":"Calle de Miguel De Cervantes, 8",
    "sg:city":"Herrera",
    "sg:orig_category":"Centros De Educaci\u00d3n Especial",
    "sg:phone":"+34 967 36 27 77",
    "sg:postcode":"02162",
    "sg:province":"Albacete",
    "wof:name":"Colegio Publico Rural Agrupado Los Llanos",
    "wof:placetype":"venue"
},
  "geometry": {"coordinates":[-2.1280078888,38.9628334045],"type":"Point"}
}