{
  "type": "Feature",
  "properties": {
    "iso:country":"ES",
    "sg:address":"Carr Germandat De Sant Sebastia, 36",
    "sg:city":"Seu D'urgell",
    "sg:orig_category":"Electrodom\u00c9sticos (fabricaci\u00d3n, Al Por Mayor)",
    "sg:phone":"+34 973 35 46 46",
    "sg:postcode":"25700",
    "sg:province":"Lleida",
    "wof:name":"Klinka S.l.",
    "wof:placetype":"venue"
},
  "geometry": {"coordinates":[0.6457189918,41.6027946472],"type":"Point"}
}