{
  "type": "Feature",
  "properties": {
    "iso:country":"ES",
    "sg:address":"Calle de Pico Balaitus, 5",
    "sg:city":"Madrid",
    "sg:orig_category":"Ropa Para Se\u00d1oras Y Caballeros (al Por Menor)",
    "sg:phone":"+34 917 40 55 49",
    "sg:postcode":"28035",
    "sg:province":"Madrid",
    "wof:name":"Sanchez Ruiz Angel",
    "wof:placetype":"venue"
},
  "geometry": {"coordinates":[-3.7208490372,40.4816741943],"type":"Point"}
}