{
  "type": "Feature",
  "properties": {
    "addr:full":"Plaz Platero, 12 Valverde Camino Huelva 21600",
    "addr:housenumber":"12",
    "addr:postcode":"21600",
    "addr:street":"Plaz Platero;Camino Huelva",
    "iso:country":"ES",
    "sg:address":"Plaz Platero, 12",
    "sg:city":"Valverde Camino",
    "sg:orig_category":"Relojer\u00cda (al Por Menor, Reparaci\u00d3n)",
    "sg:phone":"+34 959 55 27 24",
    "sg:postcode":"21600",
    "sg:province":"Huelva",
    "wof:name":"Lopez Arroyas Antonio Javier",
    "wof:placetype":"venue"
},
  "geometry": {"coordinates":[-6.7534661293,37.576335907],"type":"Point"}
}