{
  "type": "Feature",
  "properties": {
    "iso:country":"ES",
    "sg:address":"Av Miraflores, 20",
    "sg:city":"Hospitalet Llobregat",
    "sg:orig_category":"Droguer\u00cdas (al Por Menor)",
    "sg:phone":"+34 934 49 18 18",
    "sg:postcode":"08905",
    "sg:province":"Barcelona",
    "wof:name":"Miras Soto Jorge",
    "wof:placetype":"venue"
},
  "geometry": {"coordinates":[2.1113269329,41.3701133728],"type":"Point"}
}