{
  "type": "Feature",
  "properties": {
    "iso:country":"ES",
    "sg:address":"Calle de Colon, 44",
    "sg:city":"Valencia",
    "sg:orig_category":"Inmobiliaria (agencias)",
    "sg:phone":"+34 963 52 88 30",
    "sg:postcode":"46004",
    "sg:province":"Valencia",
    "wof:name":"Colon Urbana S.l.",
    "wof:placetype":"venue"
},
  "geometry": {"coordinates":[-0.371833086,39.4692153931],"type":"Point"}
}