{
  "type": "Feature",
  "properties": {
    "addr:full":"Calle de Centelles, Los, 43 Valencia Valencia 46006",
    "addr:housenumber":"43",
    "addr:postcode":"46006",
    "addr:street":"Calle De Centelles Los",
    "iso:country":"ES",
    "sg:address":"Calle de Centelles, Los, 43",
    "sg:city":"Valencia",
    "sg:classifiers":[
        {
            "category":"Casinos & Gambling",
            "type":"Entertainment"
        }
    ],
    "sg:phone":"+34 963 34 99 16",
    "sg:postcode":"46006",
    "sg:province":"Valencia",
    "sg:tags":[
        "locale",
        "de",
        "juego"
    ],
    "wof:name":"Arribas Y Lopez S. A.",
    "wof:placetype":"venue"
},
  "geometry": {"coordinates":[-0.3740420938,39.4588165283],"type":"Point"}
}