{
  "type": "Feature",
  "properties": {
    "iso:country":"ES",
    "sg:address":"Calle de General Chamorro Martinez, 4",
    "sg:city":"Sevilla",
    "sg:orig_category":"Bebidas",
    "sg:phone":"+34 954 35 30 33",
    "sg:postcode":"41008",
    "sg:province":"Sevilla",
    "wof:name":"Pelaez Ramos Jose",
    "wof:placetype":"venue"
},
  "geometry": {"coordinates":[-5.9716286659,37.4071159363],"type":"Point"}
}