{
  "type": "Feature",
  "properties": {
    "iso:country":"ES",
    "sg:address":"Ctra. Berbegal, Km. 0005,0",
    "sg:city":"Barbastro",
    "sg:orig_category":"Asociaciones Y Clubs Deportivos",
    "sg:phone":"+34 974 31 51 10",
    "sg:postcode":"22300",
    "sg:province":"Huesca",
    "wof:name":"Asociacion Para Los Deportes Aereos Del Alto Aragon",
    "wof:placetype":"venue"
},
  "geometry": {"coordinates":[0.1120525002,42.0352745056],"type":"Point"}
}