{
  "type": "Feature",
  "properties": {
    "addr:full":"Calle de San Francisco, 64 Santa Cruz De Tenerife Santa Cruz De Tenerife 38001",
    "addr:housenumber":"64",
    "addr:postcode":"38001",
    "addr:street":"Calle De San Francisco",
    "iso:country":"ES",
    "sg:address":"Calle de San Francisco, 64",
    "sg:city":"Santa Cruz De Tenerife",
    "sg:orig_category":"Laboratorios De An\u00c1lisis Agr\u00cdcolas Y De Biolog\u00cda Vegetal",
    "sg:phone":"+34 922 28 50 22",
    "sg:postcode":"38001",
    "sg:province":"Santa Cruz De Tenerife",
    "wof:name":"Canatec 35 S.l.",
    "wof:placetype":"venue"
},
  "geometry": {"coordinates":[-16.2483139038,28.4705123901],"type":"Point"}
}