{
  "type": "Feature",
  "properties": {
    "iso:country":"ES",
    "sg:address":"Avda Coru\u00d1a (la), 8",
    "sg:city":"Cangas",
    "sg:orig_category":"Discotecas Y Salas De Baile",
    "sg:phone":"+34 986 30 56 67",
    "sg:postcode":"36940",
    "sg:province":"Pontevedra",
    "wof:name":"Barroso Rial Peregrina",
    "wof:placetype":"venue"
},
  "geometry": {"coordinates":[-8.7857055664,42.2675247192],"type":"Point"}
}