{
  "type": "Feature",
  "properties": {
    "addr:full":"Avda Ramon Y Cajal, 79 Madrid Madrid 28016",
    "addr:housenumber":"79",
    "addr:postcode":"madrid;28016",
    "addr:street":"Avda Ramon Y Cajal",
    "iso:country":"ES",
    "sg:address":"Avda Ramon Y Cajal, 79",
    "sg:city":"Madrid",
    "sg:orig_category":"Empresas De Limpieza",
    "sg:phone":"+34 915 19 66 94",
    "sg:postcode":"28016",
    "sg:province":"Madrid",
    "wof:name":"Kuick Services S.l.",
    "wof:placetype":"venue"
},
  "geometry": {"coordinates":[-3.6668860912,40.452205658],"type":"Point"}
}