{
  "type": "Feature",
  "properties": {
    "iso:country":"ES",
    "sg:address":"Calle de Felix Lopez, 2",
    "sg:city":"Madrid",
    "sg:orig_category":"M\u00c9dicos: Estomatolog\u00cda",
    "sg:phone":"+34 915 25 35 14",
    "sg:postcode":"28025",
    "sg:province":"Madrid",
    "wof:name":"Rojas Morante Yolanda",
    "wof:placetype":"venue"
},
  "geometry": {"coordinates":[-3.7286770344,40.3847846985],"type":"Point"}
}