{
  "type": "Feature",
  "properties": {
    "iso:country":"ES",
    "sg:address":"Calle de San Rafael, 16",
    "sg:city":"S. Fernando",
    "sg:orig_category":"Florister\u00cdas",
    "sg:phone":"+34 956 88 29 07",
    "sg:postcode":"11100",
    "sg:province":"C\u00e1diz",
    "wof:name":"Asian Gonzalez Jose Manuel",
    "wof:placetype":"venue"
},
  "geometry": {"coordinates":[-6.195681572,36.4695625305],"type":"Point"}
}