{
  "type": "Feature",
  "properties": {
    "iso:country":"ES",
    "sg:address":"Calle de Magacela, 25",
    "sg:city":"Villanueva Serena",
    "sg:orig_category":"Artes Gr\u00c1ficas, Artes Pl\u00c1sticas (curso)",
    "sg:phone":"+34 924 84 13 91",
    "sg:postcode":"06700",
    "sg:province":"Badajoz",
    "wof:name":"Alonso Garcia Lucas",
    "wof:placetype":"venue"
},
  "geometry": {"coordinates":[-5.7986245155,38.9725494385],"type":"Point"}
}