{
  "type": "Feature",
  "properties": {
    "iso:country":"ES",
    "sg:address":"Crri Granainos, S/n",
    "sg:city":"Purisima -barriomar",
    "sg:orig_category":"Delegados, Agentes De Tr\u00c1nsito, Auxiliares De Transporte Internacional",
    "sg:phone":"+34 968 25 03 27",
    "sg:postcode":"30010",
    "sg:province":"Murcia",
    "wof:name":"Pellicer Rodriguez Andres",
    "wof:placetype":"venue"
},
  "geometry": {"coordinates":[-1.1507740021,37.9745788574],"type":"Point"}
}