{
  "type": "Feature",
  "properties": {
    "iso:country":"ES",
    "sg:address":"Ctra. Ncnal. Seiscientos Treinta, Km. 0478,0",
    "sg:city":"Plasencia",
    "sg:orig_category":"Empresarios",
    "sg:phone":"+34 927 42 43 93",
    "sg:postcode":"10600",
    "sg:province":"C\u00e1ceres",
    "wof:name":"Grupo De Pinturas Industriales S.a.",
    "wof:placetype":"venue"
},
  "geometry": {"coordinates":[-6.0898518562,40.0299453735],"type":"Point"}
}