{
  "type": "Feature",
  "properties": {
    "addr:full":"Carrer de Rubio I Ors, 2 Barcelona Barcelona 08041",
    "addr:housenumber":"2",
    "addr:postcode":"08041",
    "addr:street":"Carrer De Rubio;Ors",
    "iso:country":"ES",
    "sg:address":"Carrer de Rubio I Ors, 2",
    "sg:city":"Barcelona",
    "sg:orig_category":"Agencias Y Agentes Comerciales, Representantes",
    "sg:phone":"+34 934 35 59 46",
    "sg:postcode":"08041",
    "sg:province":"Barcelona",
    "wof:name":"Gil Aguilar Francisco",
    "wof:placetype":"venue"
},
  "geometry": {"coordinates":[2.1786830425,41.4210968018],"type":"Point"}
}