{
  "type": "Feature",
  "properties": {
    "iso:country":"ES",
    "sg:address":"Calle de Menendez Y Pelayo, 24",
    "sg:city":"Palmas De Gran Canaria",
    "sg:orig_category":"Artesan\u00cda",
    "sg:phone":"+34 928 23 39 37",
    "sg:postcode":"35006",
    "sg:province":"Las Palmas",
    "wof:name":"Juarez Rodriguez Miguel Angel",
    "wof:placetype":"venue"
},
  "geometry": {"coordinates":[-15.4313659668,28.1338615417],"type":"Point"}
}