{
  "type": "Feature",
  "properties": {
    "addr:full":"Carr Tora (de), 26 Cervera Lleida 25200",
    "addr:housenumber":"26",
    "addr:postcode":"25200",
    "addr:street":"Carr Tora De",
    "iso:country":"ES",
    "sg:address":"Carr Tora (de), 26",
    "sg:city":"Cervera",
    "sg:classifiers":[
        {
            "category":"Taxi",
            "type":"Transportation"
        }
    ],
    "sg:phone":"+34 973 53 04 49",
    "sg:postcode":"25200",
    "sg:province":"Lleida",
    "wof:name":"Nadal Cuadros Carlos",
    "wof:placetype":"venue"
},
  "geometry": {"coordinates":[1.2714600563,41.6712989807],"type":"Point"}
}