{
  "type": "Feature",
  "properties": {
    "addr:full":"Calle de Mario Cabre, 15 Madrid Madrid 28030",
    "addr:housenumber":"15",
    "addr:postcode":"madrid;28030",
    "addr:street":"Calle De Mario Cabre",
    "iso:country":"ES",
    "sg:address":"Calle de Mario Cabre, 15",
    "sg:city":"Madrid",
    "sg:orig_category":"Empresas De Carpinter\u00cda De Madera",
    "sg:phone":"+34 917 73 84 61",
    "sg:postcode":"28030",
    "sg:province":"Madrid",
    "wof:name":"Sanchez Sierra Doroteo",
    "wof:placetype":"venue"
},
  "geometry": {"coordinates":[-3.6358940601,40.4072494507],"type":"Point"}
}