{
  "type": "Feature",
  "properties": {
    "addr:full":"Avda Constitucion, 116 Villena Alicante 03400",
    "addr:housenumber":"116",
    "addr:postcode":"03400",
    "addr:street":"Avda Constitucion",
    "iso:country":"ES",
    "sg:address":"Avda Constitucion, 116",
    "sg:city":"Villena",
    "sg:orig_category":"Estancos",
    "sg:phone":"+34 965 81 42 73",
    "sg:postcode":"03400",
    "sg:province":"Alicante",
    "wof:name":"Gomez Hernandez Juan",
    "wof:placetype":"venue"
},
  "geometry": {"coordinates":[-0.8661670089,38.636932373],"type":"Point"}
}