{
  "type": "Feature",
  "properties": {
    "iso:country":"ES",
    "sg:address":"Carr Masia De La Cova, 168",
    "sg:city":"Manises",
    "sg:orig_category":"Importaci\u00d3n",
    "sg:phone":"+34 961 52 60 89",
    "sg:postcode":"46940",
    "sg:province":"Valencia",
    "wof:name":"J.p.sons Import S.l.",
    "wof:placetype":"venue"
},
  "geometry": {"coordinates":[-0.4642890096,39.4948883057],"type":"Point"}
}