{
  "type": "Feature",
  "properties": {
    "addr:full":"Calle de Taberna, 11 Marchamalo Guadalajara 19180",
    "addr:housenumber":"11",
    "addr:postcode":"19180",
    "addr:street":"Calle De Taberna",
    "iso:country":"ES",
    "sg:address":"Calle de Taberna, 11",
    "sg:city":"Marchamalo",
    "sg:orig_category":"\u00d3ptica: Instrumentos (fabricaci\u00d3n)",
    "sg:phone":"+34 949 25 23 13",
    "sg:postcode":"19180",
    "sg:province":"Guadalajara",
    "wof:name":"Atienza Tomeo S.l.",
    "wof:placetype":"venue"
},
  "geometry": {"coordinates":[-3.202722311,40.6691398621],"type":"Point"}
}