{
  "type": "Feature",
  "properties": {
    "iso:country":"ES",
    "sg:address":"Calle de San Esteban, 8",
    "sg:city":"Bearin",
    "sg:orig_category":"Iglesia Cat\u00d3lica",
    "sg:phone":"+34 948 55 05 99",
    "sg:postcode":"31179",
    "sg:province":"Navarra",
    "wof:name":"Parroquia De San Pedro",
    "wof:placetype":"venue"
},
  "geometry": {"coordinates":[-2.0257639885,42.6934394836],"type":"Point"}
}