{
  "type": "Feature",
  "properties": {
    "iso:country":"ES",
    "sg:address":"Calle de Doctor Fleming, 29",
    "sg:city":"Aspe",
    "sg:orig_category":"Contenedores (mercanc\u00cdas)",
    "sg:phone":"+34 965 49 51 65",
    "sg:postcode":"03680",
    "sg:province":"Alicante",
    "wof:name":"Transportes Galva\u00f1 Y Caparros S.l.",
    "wof:placetype":"venue"
},
  "geometry": {"coordinates":[-0.7659670115,38.3485832214],"type":"Point"}
}