{
  "type": "Feature",
  "properties": {
    "iso:country":"ES",
    "sg:address":"Avda Val Mi\u00d1or, 7",
    "sg:city":"Vilamean",
    "sg:orig_category":"Venta, Montaje De Neum\u00c1ticos",
    "sg:phone":"+34 986 36 57 46",
    "sg:postcode":"36350",
    "sg:province":"Pontevedra",
    "wof:name":"Anta Alvarez Juan Eligio",
    "wof:placetype":"venue"
},
  "geometry": {"coordinates":[-8.8064184189,42.141998291],"type":"Point"}
}