{
  "type": "Feature",
  "properties": {
    "addr:full":"Calle de Muro, 12 Valladolid Valladolid 47004",
    "addr:housenumber":"12",
    "addr:postcode":"47004",
    "addr:street":"Calle De Muro",
    "iso:country":"ES",
    "sg:address":"Calle de Muro, 12",
    "sg:city":"Valladolid",
    "sg:orig_category":"M\u00c9dicos: Ginecolog\u00cda Y Obstetricia",
    "sg:phone":"+34 983 30 21 90",
    "sg:postcode":"47004",
    "sg:province":"Valladolid",
    "wof:name":"Velasco Bernal Javier",
    "wof:placetype":"venue"
},
  "geometry": {"coordinates":[-4.7252240181,41.6463356018],"type":"Point"}
}