{
  "type": "Feature",
  "properties": {
    "iso:country":"ES",
    "sg:address":"Calle de Pablo Iglesias, 91",
    "sg:city":"Elda",
    "sg:orig_category":"Marroquiner\u00cda (confecci\u00d3n)",
    "sg:phone":"+34 966 98 08 65",
    "sg:postcode":"03600",
    "sg:province":"Alicante",
    "wof:name":"Vergara Justamante Jose Fernando",
    "wof:placetype":"venue"
},
  "geometry": {"coordinates":[-0.7930229902,38.4745864868],"type":"Point"}
}