{
  "type": "Feature",
  "properties": {
    "iso:country":"ES",
    "sg:address":"Calle de Joaquin Martinez Borreguero, 12",
    "sg:city":"Madrid",
    "sg:orig_category":"Cl\u00cdnicas Dentales",
    "sg:phone":"+34 914 69 01 70",
    "sg:postcode":"28019",
    "sg:province":"Madrid",
    "wof:name":"Clinica Dental Goal S.l.",
    "wof:placetype":"venue"
},
  "geometry": {"coordinates":[-3.7121710777,40.3916130066],"type":"Point"}
}