{
  "type": "Feature",
  "properties": {
    "iso:country":"ES",
    "sg:address":"Pol. Ind. Verdeguera, S/n",
    "sg:city":"Mora Ebre",
    "sg:orig_category":"Material Y Herramientas Agr\u00cdcolas",
    "sg:phone":"+34 977 40 10 88",
    "sg:postcode":"43740",
    "sg:province":"Tarragona",
    "wof:name":"Castells Boix Vicente Antonio",
    "wof:placetype":"venue"
},
  "geometry": {"coordinates":[0.6392750144,41.0884246826],"type":"Point"}
}