{
  "type": "Feature",
  "properties": {
    "iso:country":"ES",
    "sg:address":"Avda Burgos, 11",
    "sg:city":"Medina Pomar",
    "sg:orig_category":"M\u00c9dicos: Estomatolog\u00cda",
    "sg:phone":"+34 947 19 15 92",
    "sg:postcode":"09500",
    "sg:province":"Burgos",
    "wof:name":"Leivar Alonso De Porres Ramon",
    "wof:placetype":"venue"
},
  "geometry": {"coordinates":[-3.4858839512,42.9316596985],"type":"Point"}
}