{
  "type": "Feature",
  "properties": {
    "iso:country":"ES",
    "sg:address":"Calle de Gran Via, 26",
    "sg:city":"Majadahonda",
    "sg:orig_category":"\u00d3ptica: Instrumentos (fabricaci\u00d3n)",
    "sg:phone":"+34 916 38 48 56",
    "sg:postcode":"28220",
    "sg:province":"Madrid",
    "wof:name":"Pe\u00f1a Lazaro Javier",
    "wof:placetype":"venue"
},
  "geometry": {"coordinates":[-3.8717269897,40.4720001221],"type":"Point"}
}