{
  "type": "Feature",
  "properties": {
    "iso:country":"ES",
    "sg:address":"Calle de Jose De Galvez Y Aranda, S/n",
    "sg:city":"Cordoba",
    "sg:orig_category":"Fabricaci\u00d3n Y Comercio De M\u00c1quinas",
    "sg:phone":"+34 957 32 67 54",
    "sg:postcode":"14014",
    "sg:province":"C\u00f3rdoba",
    "wof:name":"Antonio Villar Olalla Sl",
    "wof:placetype":"venue"
},
  "geometry": {"coordinates":[-4.717148304,37.9043388367],"type":"Point"}
}