{
  "type": "Feature",
  "properties": {
    "addr:full":"Calle de Padre Luis Gordillo, 11 Palma Condado Huelva 21700",
    "addr:housenumber":"11",
    "addr:postcode":"21700",
    "addr:street":"Calle De Padre Luis Gordillo",
    "iso:country":"ES",
    "sg:address":"Calle de Padre Luis Gordillo, 11",
    "sg:city":"Palma Condado",
    "sg:orig_category":"Agencias Y Asesores De Publicidad",
    "sg:phone":"+34 959 40 21 69",
    "sg:postcode":"21700",
    "sg:province":"Huelva",
    "sg:website":"www.nmgrafic.com",
    "wof:name":"Nm Grafic Consulting S.l.",
    "wof:placetype":"venue"
},
  "geometry": {"coordinates":[-6.5538191795,37.3880004883],"type":"Point"}
}