{
  "type": "Feature",
  "properties": {
    "addr:full":"Calle de Rodrigo De Triana, 8 Marbella M\u00e1laga 29600",
    "addr:housenumber":"8",
    "addr:postcode":"29600",
    "addr:street":"Calle De Rodrigo De Triana;Ma\u0301Laga",
    "iso:country":"ES",
    "sg:address":"Calle de Rodrigo De Triana, 8",
    "sg:city":"Marbella",
    "sg:orig_category":"Alquiler De V\u00cddeo",
    "sg:phone":"+34 952 77 70 71",
    "sg:postcode":"29600",
    "sg:province":"M\u00e1laga",
    "wof:name":"Delgado Rivera Maria Del Carmen",
    "wof:placetype":"venue"
},
  "geometry": {"coordinates":[-4.8790807724,36.5100746155],"type":"Point"}
}