{
  "type": "Feature",
  "properties": {
    "iso:country":"ES",
    "sg:address":"Calle de Aguirre Maximo, 20",
    "sg:city":"Bilbao",
    "sg:orig_category":"Abogados",
    "sg:phone":"+34 944 42 36 81",
    "sg:postcode":"48011",
    "sg:province":"Vizcaya",
    "wof:name":"Cabrejas Llorente Jose Luis",
    "wof:placetype":"venue"
},
  "geometry": {"coordinates":[-2.9381120205,43.2627487183],"type":"Point"}
}