{
  "type": "Feature",
  "properties": {
    "addr:full":"Carrer de Pablo Iglesias, 71 Barcelona Barcelona 08016",
    "addr:housenumber":"71",
    "addr:postcode":"08016",
    "addr:street":"Carrer De Pablo Iglesias",
    "iso:country":"ES",
    "sg:address":"Carrer de Pablo Iglesias, 71",
    "sg:city":"Barcelona",
    "sg:orig_category":"Peluquer\u00cdas, Peluquer\u00cda Mixta",
    "sg:phone":"+34 933 59 81 31",
    "sg:postcode":"08016",
    "sg:province":"Barcelona",
    "wof:name":"Azogue Ramos S.c.p",
    "wof:placetype":"venue"
},
  "geometry": {"coordinates":[2.1824328899,41.4447669983],"type":"Point"}
}