{
  "type": "Feature",
  "properties": {
    "addr:full":"Calle de Ruzafa, 41 Valencia Valencia 46006",
    "addr:housenumber":"41",
    "addr:postcode":"46006",
    "addr:street":"Calle De Ruzafa",
    "iso:country":"ES",
    "sg:address":"Calle de Ruzafa, 41",
    "sg:city":"Valencia",
    "sg:orig_category":"Sanatorios M\u00c9dico",
    "sg:phone":"+34 963 74 23 79",
    "sg:postcode":"46006",
    "sg:province":"Valencia",
    "wof:name":"Generalitat Valenciana",
    "wof:placetype":"venue"
},
  "geometry": {"coordinates":[-0.3730620146,39.4643745422],"type":"Point"}
}