{
  "type": "Feature",
  "properties": {
    "addr:full":"Avda Ebro, 16 Agoncillo La Rioja 26509",
    "addr:housenumber":"16",
    "addr:postcode":"26509",
    "addr:street":"Avda Ebro;Rioja",
    "iso:country":"ES",
    "sg:address":"Avda Ebro, 16",
    "sg:city":"Agoncillo",
    "sg:orig_category":"Contenedores (mercanc\u00cdas)",
    "sg:phone":"+34 941 43 14 17",
    "sg:postcode":"26509",
    "sg:province":"La Rioja",
    "wof:name":"Transportes Hermanos Royo S.l.",
    "wof:placetype":"venue"
},
  "geometry": {"coordinates":[-2.1222639084,42.4031410217],"type":"Point"}
}