{
  "type": "Feature",
  "properties": {
    "addr:full":"Rua Velle (de), S/n Velle Ourense 32960",
    "addr:postcode":"32960",
    "addr:street":"Rua Velle De S / N Velle",
    "iso:country":"ES",
    "sg:address":"Rua Velle (de), S/n",
    "sg:city":"Velle",
    "sg:orig_category":"Fabricaci\u00d3n, Importaci\u00d3n De Material Y Sistemas De Telecomunicaciones",
    "sg:phone":"+34 988 24 05 79",
    "sg:postcode":"32960",
    "sg:province":"Ourense",
    "wof:name":"Grupalia Internet S.a.",
    "wof:placetype":"venue"
},
  "geometry": {"coordinates":[-7.8337731361,42.3690948486],"type":"Point"}
}