{
  "type": "Feature",
  "properties": {
    "iso:country":"ES",
    "sg:address":"Calle de Valdelacalzada, 28",
    "sg:city":"Montijo",
    "sg:orig_category":"Asesor\u00cda Sobre Comunicaci\u00d3n De Empresas",
    "sg:phone":"+34 924 45 33 30",
    "sg:postcode":"06480",
    "sg:province":"Badajoz",
    "wof:name":"E.f.g.asesores S.l.",
    "wof:placetype":"venue"
},
  "geometry": {"coordinates":[-6.6173791885,38.9072418213],"type":"Point"}
}