{
  "type": "Feature",
  "properties": {
    "iso:country":"ES",
    "sg:address":"Ptge Fontanelles, 9",
    "sg:city":"Barcelona",
    "sg:orig_category":"Abogados",
    "sg:phone":"+34 932 05 03 80",
    "sg:postcode":"08017",
    "sg:province":"Barcelona",
    "wof:name":"Gonzalez Xicota Montserrat",
    "wof:placetype":"venue"
},
  "geometry": {"coordinates":[2.1245720387,41.4007225037],"type":"Point"}
}