{
  "type": "Feature",
  "properties": {
    "iso:country":"ES",
    "sg:address":"Calle de Jorge Manrique, 1",
    "sg:city":"Guardo",
    "sg:orig_category":"Caf\u00c9s, Bares, Cervecer\u00cdas",
    "sg:phone":"+34 979 85 24 51",
    "sg:postcode":"34880",
    "sg:province":"Palencia",
    "wof:name":"Cafe Bar Triana S.l.",
    "wof:placetype":"venue"
},
  "geometry": {"coordinates":[-4.8473110199,42.7907104492],"type":"Point"}
}