{
  "type": "Feature",
  "properties": {
    "addr:full":"Carr Joaquin Blume, 4 Aldaia Valencia 46960",
    "addr:housenumber":"4",
    "addr:postcode":"46960",
    "addr:street":"Carr Joaquin Blume",
    "iso:country":"ES",
    "sg:address":"Carr Joaquin Blume, 4",
    "sg:city":"Aldaia",
    "sg:orig_category":"Fabrica De Cer\u00c1micas",
    "sg:phone":"+34 961 50 86 99",
    "sg:postcode":"46960",
    "sg:province":"Valencia",
    "wof:name":"Gregori Tortajada Maria Josefa",
    "wof:placetype":"venue"
},
  "geometry": {"coordinates":[-0.4604432881,39.4596939087],"type":"Point"}
}