{
  "type": "Feature",
  "properties": {
    "addr:full":"Calle de Picasent, 33 Alginet Valencia 46230",
    "addr:housenumber":"33",
    "addr:postcode":"46230",
    "addr:street":"Calle De Picasent",
    "iso:country":"ES",
    "sg:address":"Calle de Picasent, 33",
    "sg:city":"Alginet",
    "sg:orig_category":"Promotores Constructores",
    "sg:phone":"+34 961 75 09 36",
    "sg:postcode":"46230",
    "sg:province":"Valencia",
    "wof:name":"Ramon Mari Jose",
    "wof:placetype":"venue"
},
  "geometry": {"coordinates":[-0.4700750113,39.2665519714],"type":"Point"}
}