{
  "type": "Feature",
  "properties": {
    "addr:full":"Calle de Nieves (las), 20 Segovia Segovia 40003",
    "addr:housenumber":"20",
    "addr:postcode":"40003",
    "addr:street":"Calle De Nieves Las",
    "iso:country":"ES",
    "sg:address":"Calle de Nieves (las), 20",
    "sg:city":"Segovia",
    "sg:orig_category":"Alimentaci\u00d3n General (al Por Menor)",
    "sg:phone":"+34 921 43 54 80",
    "sg:postcode":"40003",
    "sg:province":"Segovia",
    "wof:name":"Velasco Vecino Mariano",
    "wof:placetype":"venue"
},
  "geometry": {"coordinates":[-4.1105771065,40.9553146362],"type":"Point"}
}