{
  "type": "Feature",
  "properties": {
    "iso:country":"ES",
    "sg:address":"Calle de Riosol, 5",
    "sg:city":"Le\u00f3n",
    "sg:orig_category":"Molduras, Junquillos, Listones Y Molduras Perforadas",
    "sg:phone":"+34 987 23 44 15",
    "sg:postcode":"24010",
    "sg:province":"Le\u00f3n",
    "wof:name":"Rodriguez Conejo Cipriano",
    "wof:placetype":"venue"
},
  "geometry": {"coordinates":[-5.5867199898,42.6027412415],"type":"Point"}
}