{
  "type": "Feature",
  "properties": {
    "addr:full":"Ctra. N. 340, Km. 0478,0 Tabernas Almer\u00eda 04200",
    "addr:postcode":"04200",
    "addr:street":"Ctra. N. 340 Km. 0478,0;Almeri\u0301A",
    "iso:country":"ES",
    "sg:address":"Ctra. N. 340, Km. 0478,0",
    "sg:city":"Tabernas",
    "sg:orig_category":"Cerrajer\u00cda, Ferrallista",
    "sg:phone":"+34 950 52 50 62",
    "sg:postcode":"04200",
    "sg:province":"Almer\u00eda",
    "wof:name":"Martinez Perez Juan Ramon",
    "wof:placetype":"venue"
},
  "geometry": {"coordinates":[-2.3244791031,37.1620903015],"type":"Point"}
}