{
  "type": "Feature",
  "properties": {
    "iso:country":"ES",
    "sg:address":"Avda Principes De Espa\u00d1a, 7",
    "sg:city":"Santa Cruz De Tenerife",
    "sg:orig_category":"Librer\u00cdas",
    "sg:phone":"+34 922 64 66 01",
    "sg:postcode":"38010",
    "sg:province":"Santa Cruz De Tenerife",
    "wof:name":"Cruz Pastor Margarita De La",
    "wof:placetype":"venue"
},
  "geometry": {"coordinates":[-16.2855453491,28.4527206421],"type":"Point"}
}