{
  "type": "Feature",
  "properties": {
    "iso:country":"ES",
    "sg:address":"Calle de Romero (del), 14",
    "sg:city":"Fuenlabrada",
    "sg:orig_category":"Muebles, Minoristas",
    "sg:phone":"+34 916 97 18 12",
    "sg:postcode":"28946",
    "sg:province":"Madrid",
    "wof:name":"Don Dise\u00d1o Madrid S.l.",
    "wof:placetype":"venue"
},
  "geometry": {"coordinates":[-3.752712965,40.2756347656],"type":"Point"}
}