{
  "type": "Feature",
  "properties": {
    "iso:country":"ES",
    "sg:address":"Urb Ciudad Quesada, S/n",
    "sg:city":"Ciudad Quesada",
    "sg:orig_category":"Edici\u00d3n De Diarios, Revistas, Boletines",
    "sg:phone":"+34 966 71 84 62",
    "sg:postcode":"03170",
    "sg:province":"Alicante",
    "wof:name":"Costa Vicente Pedro Jose",
    "wof:placetype":"venue"
},
  "geometry": {"coordinates":[-0.7292140126,38.0850296021],"type":"Point"}
}