{
  "type": "Feature",
  "properties": {
    "iso:country":"ES",
    "sg:address":"Carrer de Ausias Marc, 58",
    "sg:city":"Barcelona",
    "sg:orig_category":"Agencias De Aduana",
    "sg:phone":"+34 932 44 00 57",
    "sg:postcode":"08010",
    "sg:province":"Barcelona",
    "wof:name":"Saice S. A.",
    "wof:placetype":"venue"
},
  "geometry": {"coordinates":[2.178237915,41.3931274414],"type":"Point"}
}