{
  "type": "Feature",
  "properties": {
    "addr:full":"Carrer de Negrevernis, 14 Barcelona Barcelona 08034",
    "addr:housenumber":"14",
    "addr:postcode":"08034",
    "addr:street":"Carrer De Negrevernis",
    "iso:country":"ES",
    "sg:address":"Carrer de Negrevernis, 14",
    "sg:city":"Barcelona",
    "sg:orig_category":"Arquitectos",
    "sg:phone":"+34 932 04 38 85",
    "sg:postcode":"08034",
    "sg:province":"Barcelona",
    "wof:name":"Gri\u00f1o Sans Jordi",
    "wof:placetype":"venue"
},
  "geometry": {"coordinates":[2.12073493,41.3990859985],"type":"Point"}
}