{
  "type": "Feature",
  "properties": {
    "addr:full":"Carrer de Lluc, 5 Barcelona Barcelona 08016",
    "addr:housenumber":"5",
    "addr:postcode":"08016",
    "addr:street":"Carrer De Lluc",
    "iso:country":"ES",
    "sg:address":"Carrer de Lluc, 5",
    "sg:city":"Barcelona",
    "sg:orig_category":"Albergues",
    "sg:phone":"+34 933 59 81 58",
    "sg:postcode":"08016",
    "sg:province":"Barcelona",
    "wof:name":"Jesan International Barcelona S.c.p.",
    "wof:placetype":"venue"
},
  "geometry": {"coordinates":[2.1776659489,41.4381027222],"type":"Point"}
}