{
  "type": "Feature",
  "properties": {
    "iso:country":"ES",
    "sg:address":"Calle de Profesor Beltran Baguena, 4",
    "sg:city":"Valencia",
    "sg:orig_category":"Revestimiento De Suelos Industriales",
    "sg:phone":"+34 963 49 87 13",
    "sg:postcode":"46009",
    "sg:province":"Valencia",
    "sg:website":"www.artigo.com",
    "wof:name":"Artigo Iberica S.l.",
    "wof:placetype":"venue"
},
  "geometry": {"coordinates":[-0.3890551925,39.4804420471],"type":"Point"}
}