{
  "type": "Feature",
  "properties": {
    "iso:country":"ES",
    "sg:address":"Carrer de Sant Valeria, 7",
    "sg:city":"Casc Antic",
    "sg:orig_category":"Artes Gr\u00c1ficas, Artes Pl\u00c1sticas (curso)",
    "sg:phone":"+34 935 62 11 95",
    "sg:postcode":"08150",
    "sg:province":"Barcelona",
    "wof:name":"Cayuelas Gonzalez Raul",
    "wof:placetype":"venue"
},
  "geometry": {"coordinates":[2.2319469452,41.5694198608],"type":"Point"}
}