{
  "type": "Feature",
  "properties": {
    "iso:country":"ES",
    "sg:address":"Pl Fra Bernadi, 8",
    "sg:city":"Manlleu",
    "sg:orig_category":"Molduras, Junquillos, Listones Y Molduras Perforadas",
    "sg:phone":"+34 938 51 31 17",
    "sg:postcode":"08560",
    "sg:province":"Barcelona",
    "wof:name":"Parramon Cirera Domingo",
    "wof:placetype":"venue"
},
  "geometry": {"coordinates":[2.2838580608,41.9997520447],"type":"Point"}
}