{
  "type": "Feature",
  "properties": {
    "addr:full":"Calle de Alegria, 8 Madridejos Toledo 45710",
    "addr:housenumber":"8",
    "addr:postcode":"45710",
    "addr:street":"Calle De Alegria",
    "iso:country":"ES",
    "sg:address":"Calle de Alegria, 8",
    "sg:city":"Madridejos",
    "sg:orig_category":"Negocio De Materiales De Construcci\u00d3n",
    "sg:phone":"+34 925 46 38 36",
    "sg:postcode":"45710",
    "sg:province":"Toledo",
    "wof:name":"Garcia Due\u00f1as Josefa",
    "wof:placetype":"venue"
},
  "geometry": {"coordinates":[-3.5251357555,39.4681930542],"type":"Point"}
}