{
  "type": "Feature",
  "properties": {
    "iso:country":"ES",
    "sg:address":"Plaz Jardinillos (los), 8",
    "sg:city":"Jaen",
    "sg:orig_category":"Asesor\u00cda De Formaci\u00d3n Y Gesti\u00d3n De Personal",
    "sg:phone":"+34 953 26 68 10",
    "sg:postcode":"23003",
    "sg:province":"Ja\u00e9n",
    "wof:name":"Asesoria Tecnica Jiennense S.a.l.",
    "wof:placetype":"venue"
},
  "geometry": {"coordinates":[-3.7485873699,37.7440452576],"type":"Point"}
}