{
  "type": "Feature",
  "properties": {
    "iso:country":"ES",
    "sg:address":"Calle de Pozo Amarillo, 35",
    "sg:city":"Salamanca",
    "sg:orig_category":"Abogados",
    "sg:phone":"+34 923 21 41 81",
    "sg:postcode":"37001",
    "sg:province":"Salamanca",
    "wof:name":"Gomez Aparicio Francisco Enrique",
    "wof:placetype":"venue"
},
  "geometry": {"coordinates":[-5.6615700722,40.9664001465],"type":"Point"}
}