{
  "type": "Feature",
  "properties": {
    "iso:country":"ES",
    "sg:address":"Calle de Perugia, 3",
    "sg:city":"Granada",
    "sg:orig_category":"Sociedades, Compa\u00d1\u00cdas Aseguradoras",
    "sg:phone":"+34 958 81 26 44",
    "sg:postcode":"18007",
    "sg:province":"Granada",
    "wof:name":"J.avila Peritaciones Y Valoraciones S.l.",
    "wof:placetype":"venue"
},
  "geometry": {"coordinates":[-3.5970590115,37.1578445435],"type":"Point"}
}