{
  "type": "Feature",
  "properties": {
    "addr:full":"Calle de Ruiz De Moros, 11 Alca\u00f1iz Teruel 44600",
    "addr:housenumber":"11",
    "addr:postcode":"44600",
    "addr:street":"Calle De Ruiz De Moros",
    "iso:country":"ES",
    "sg:address":"Calle de Ruiz De Moros, 11",
    "sg:city":"Alca\u00f1iz",
    "sg:orig_category":"Venta, Instalaci\u00d3n De Calefacci\u00d3n",
    "sg:phone":"+34 978 83 25 37",
    "sg:postcode":"44600",
    "sg:province":"Teruel",
    "wof:name":"Tecnicas De Climatizacion Bajo Aragon S.l.u.",
    "wof:placetype":"venue"
},
  "geometry": {"coordinates":[-0.127324,41.0456466675],"type":"Point"}
}