{
  "type": "Feature",
  "properties": {
    "addr:full":"Calle de Izaro Monte, 3 Bilbao Vizcaya 48007",
    "addr:housenumber":"3",
    "addr:postcode":"48007",
    "addr:street":"Calle De Izaro Monte",
    "iso:country":"ES",
    "sg:address":"Calle de Izaro Monte, 3",
    "sg:city":"Bilbao",
    "sg:orig_category":"Farmacias",
    "sg:phone":"+34 944 00 15 85",
    "sg:postcode":"48007",
    "sg:province":"Vizcaya",
    "wof:name":"Isabel Ugalde Elorriaga - Farmacia",
    "wof:placetype":"venue"
},
  "geometry": {"coordinates":[-2.9204919338,43.2672233582],"type":"Point"}
}