{
  "type": "Feature",
  "properties": {
    "iso:country":"ES",
    "sg:address":"Calle de Padre Palau Y Quer, 20",
    "sg:city":"Valencia",
    "sg:orig_category":"Empresas De Limpieza",
    "sg:phone":"+34 963 49 23 26",
    "sg:postcode":"46009",
    "sg:province":"Valencia",
    "wof:name":"Mantylim S.a.",
    "wof:placetype":"venue"
},
  "geometry": {"coordinates":[-0.3760049045,39.484249115],"type":"Point"}
}