{
  "type": "Feature",
  "properties": {
    "addr:full":"Carrer de Pi I Margall, 58 Barcelona Barcelona 08025",
    "addr:housenumber":"58",
    "addr:postcode":"08025",
    "addr:street":"Carrer De Pi I Margall",
    "iso:country":"ES",
    "sg:address":"Carrer de Pi I Margall, 58",
    "sg:city":"Barcelona",
    "sg:orig_category":"Centros De Coordinaci\u00d3n",
    "sg:phone":"+34 932 84 00 69",
    "sg:postcode":"08025",
    "sg:province":"Barcelona",
    "wof:name":"Samper Esteras Y Asociados S.l.",
    "wof:placetype":"venue"
},
  "geometry": {"coordinates":[2.1639430523,41.4083175659],"type":"Point"}
}