{
  "type": "Feature",
  "properties": {
    "iso:country":"ES",
    "sg:address":"Luga Monserrat, 23",
    "sg:city":"Monserrat",
    "sg:orig_category":"Asilos De Ancianos. Centros Privados",
    "sg:phone":"+34 981 17 38 35",
    "sg:postcode":"15009",
    "sg:province":"La Coru\u00f1a",
    "wof:name":"Codina Boigues S.l.",
    "wof:placetype":"venue"
},
  "geometry": {"coordinates":[-8.3964595795,43.3701095581],"type":"Point"}
}