{
  "type": "Feature",
  "properties": {
    "addr:full":"Basarte Area, 6 Azpeitia Guip\u00f9zcoa 20730",
    "addr:housenumber":"6",
    "addr:postcode":"20730",
    "addr:street":"Basarte Area;Guipu\u0300Zcoa",
    "iso:country":"ES",
    "sg:address":"Basarte Area, 6",
    "sg:city":"Azpeitia",
    "sg:orig_category":"Empresas De Carpinter\u00cda",
    "sg:phone":"+34 943 85 05 05",
    "sg:postcode":"20730",
    "sg:province":"Guip\u00f9zcoa",
    "wof:name":"Angel Olaizola Otaegui Y Otro Cdad",
    "wof:placetype":"venue"
},
  "geometry": {"coordinates":[-2.2638750076,43.1857795715],"type":"Point"}
}