{
  "type": "Feature",
  "properties": {
    "iso:country":"ES",
    "sg:address":"Rua Conde Torrecedeira, 92",
    "sg:city":"Vigo",
    "sg:orig_category":"Ingeniero",
    "sg:phone":"+34 986 29 42 65",
    "sg:postcode":"36208",
    "sg:province":"Pontevedra",
    "wof:name":"Pellicer Caravaca Luis",
    "wof:placetype":"venue"
},
  "geometry": {"coordinates":[-8.734951973,42.2261047363],"type":"Point"}
}