{
  "type": "Feature",
  "properties": {
    "iso:country":"ES",
    "sg:address":"Calle de Sto.tomas, 13",
    "sg:city":"Alhama De Almeria",
    "sg:orig_category":"Alimentaci\u00d3n General (al Por Menor)",
    "sg:phone":"+34 950 64 02 06",
    "sg:postcode":"04400",
    "sg:province":"Almer\u00eda",
    "wof:name":"Perez Martinez Isabel",
    "wof:placetype":"venue"
},
  "geometry": {"coordinates":[-2.5690190792,36.9562454224],"type":"Point"}
}