{
  "type": "Feature",
  "properties": {
    "addr:full":"Carrer de Fontanella, 16 Barcelona Barcelona 08010",
    "addr:housenumber":"16",
    "addr:postcode":"08010",
    "addr:street":"Carrer De Fontanella",
    "iso:country":"ES",
    "sg:address":"Carrer de Fontanella, 16",
    "sg:city":"Barcelona",
    "sg:orig_category":"Lencer\u00cda Femenina, Corseter\u00cda, Trajes De Ba\u00d1o (al Por Menor)",
    "sg:phone":"+34 933 17 93 69",
    "sg:postcode":"08010",
    "sg:province":"Barcelona",
    "sg:website":"www.womensecret.com",
    "wof:name":"Cortefiel S.a.",
    "wof:placetype":"venue"
},
  "geometry": {"coordinates":[2.1726050377,41.38804245],"type":"Point"}
}