{
  "type": "Feature",
  "properties": {
    "iso:country":"ES",
    "sg:address":"Rond Universitat, 15",
    "sg:city":"Barcelona",
    "sg:orig_category":"Inmobiliaria (agencias)",
    "sg:phone":"+34 933 18 05 30",
    "sg:postcode":"08007",
    "sg:province":"Barcelona",
    "wof:name":"Gestincor Consultores S.a.",
    "wof:placetype":"venue"
},
  "geometry": {"coordinates":[2.1660809517,41.3865737915],"type":"Point"}
}