{
  "type": "Feature",
  "properties": {
    "iso:country":"ES",
    "sg:address":"Calle de Martires, 29",
    "sg:city":"Almendralejo",
    "sg:orig_category":"Abogados",
    "sg:phone":"+34 924 66 34 20",
    "sg:postcode":"06200",
    "sg:province":"Badajoz",
    "wof:name":"Rodriguez Amado Jose",
    "wof:placetype":"venue"
},
  "geometry": {"coordinates":[-6.4089512825,38.6810646057],"type":"Point"}
}