{
  "type": "Feature",
  "properties": {
    "addr:full":"Carr Tarragona, 13 Tremp Lleida 25620",
    "addr:housenumber":"13",
    "addr:postcode":"25620",
    "addr:street":"Carr Tarragona",
    "iso:country":"ES",
    "sg:address":"Carr Tarragona, 13",
    "sg:city":"Tremp",
    "sg:orig_category":"Muebles, Minoristas",
    "sg:phone":"+34 973 65 12 32",
    "sg:postcode":"25620",
    "sg:province":"Lleida",
    "wof:name":"Pascual Sanfeliu Rafael",
    "wof:placetype":"venue"
},
  "geometry": {"coordinates":[0.8934159875,42.1641159058],"type":"Point"}
}