{
  "type": "Feature",
  "properties": {
    "addr:full":"Plaz Camilo Jose Cela, 41 Ecija Sevilla 41400",
    "addr:housenumber":"41",
    "addr:postcode":"41400",
    "addr:street":"Camilo Jose Cela",
    "iso:country":"ES",
    "sg:address":"Plaz Camilo Jose Cela, 41",
    "sg:city":"Ecija",
    "sg:orig_category":"Arquitectos",
    "sg:phone":"+34 955 90 01 12",
    "sg:postcode":"41400",
    "sg:province":"Sevilla",
    "wof:name":"Dell'amico Otero Carlos Alberto",
    "wof:placetype":"venue"
},
  "geometry": {"coordinates":[-5.0884079933,37.5373344421],"type":"Point"}
}