{
  "type": "Feature",
  "properties": {
    "addr:full":"Avd Poeta M. Reina, 73 Puente-genil C\u00f3rdoba 14500",
    "addr:housenumber":"73",
    "addr:postcode":"14500",
    "addr:street":"Avd Poeta M. Reina;Co\u0301Rdoba",
    "iso:country":"ES",
    "sg:address":"Avd Poeta M. Reina, 73",
    "sg:city":"Puente-genil",
    "sg:orig_category":"Asociaciones Y Clubs Deportivos",
    "sg:phone":"+34 957 60 66 05",
    "sg:postcode":"14500",
    "sg:province":"C\u00f3rdoba",
    "wof:name":"Deportes La Perdiz Pontana S.l.",
    "wof:placetype":"venue"
},
  "geometry": {"coordinates":[-4.7655382156,37.3924064636],"type":"Point"}
}