{
  "type": "Feature",
  "properties": {
    "iso:country":"ES",
    "sg:address":"Rbla Celler, 27",
    "sg:city":"S. Cugat Valles",
    "sg:orig_category":"Florister\u00cdas",
    "sg:phone":"+34 935 90 16 90",
    "sg:postcode":"08172",
    "sg:province":"Barcelona",
    "wof:name":"Kalaplant S.l.",
    "wof:placetype":"venue"
},
  "geometry": {"coordinates":[2.0851199627,41.4712791443],"type":"Point"}
}