{
  "type": "Feature",
  "properties": {
    "addr:full":"Trva Juan Xxiii, 2 Chantada Lugo 27500",
    "addr:housenumber":"2",
    "addr:postcode":"27500",
    "addr:street":"Trva Juan Xxiii",
    "iso:country":"ES",
    "sg:address":"Trva Juan Xxiii, 2",
    "sg:city":"Chantada",
    "sg:orig_category":"Peluqueros: De Se\u00d1oras",
    "sg:phone":"+34 982 44 13 53",
    "sg:postcode":"27500",
    "sg:province":"Lugo",
    "wof:name":"Penas Sanchez Maria Esther",
    "wof:placetype":"venue"
},
  "geometry": {"coordinates":[-7.7691998482,42.6089172363],"type":"Point"}
}