{
  "type": "Feature",
  "properties": {
    "iso:country":"ES",
    "sg:address":"Calle de Carmen, 2",
    "sg:city":"Le\u00f3n",
    "sg:orig_category":"Complementos De Vestir (al Por Menor)",
    "sg:phone":"+34 987 22 11 76",
    "sg:postcode":"24001",
    "sg:province":"Le\u00f3n",
    "wof:name":"Puerta Casta\u00f1o Miguel",
    "wof:placetype":"venue"
},
  "geometry": {"coordinates":[-5.5879459381,42.5882720947],"type":"Point"}
}