{
  "type": "Feature",
  "properties": {
    "addr:full":"Calle de Miguel Fleta, S/n Pina De Ebro Zaragoza 50750",
    "addr:housenumber":"s / n",
    "addr:postcode":"50750",
    "addr:street":"Calle De Miguel Fleta",
    "iso:country":"ES",
    "sg:address":"Calle de Miguel Fleta, S/n",
    "sg:city":"Pina De Ebro",
    "sg:orig_category":"Supermercados Y Hipermercados",
    "sg:phone":"+34 976 16 51 44",
    "sg:postcode":"50750",
    "sg:province":"Zaragoza",
    "wof:name":"Alimentacion Pina S.c.",
    "wof:placetype":"venue"
},
  "geometry": {"coordinates":[-0.5266469717,41.4900093079],"type":"Point"}
}