{
  "type": "Feature",
  "properties": {
    "addr:full":"Calle de Lima, 63 Almeria Almer\u00eda 04007",
    "addr:housenumber":"63",
    "addr:postcode":"04007",
    "addr:street":"Calle De Lima",
    "iso:country":"ES",
    "sg:address":"Calle de Lima, 63",
    "sg:city":"Almeria",
    "sg:orig_category":"Molduras, Junquillos, Listones Y Molduras Perforadas",
    "sg:phone":"+34 950 15 01 38",
    "sg:postcode":"04007",
    "sg:province":"Almer\u00eda",
    "wof:name":"Espinosa Plaza Dolores Encarnacion",
    "wof:placetype":"venue"
},
  "geometry": {"coordinates":[-2.4494740963,36.8353271484],"type":"Point"}
}