{
  "type": "Feature",
  "properties": {
    "iso:country":"ES",
    "sg:address":"Calle de Pescadores, 97",
    "sg:city":"Don Benito",
    "sg:orig_category":"Farmacias",
    "sg:phone":"+34 924 80 06 84",
    "sg:postcode":"06400",
    "sg:province":"Badajoz",
    "wof:name":"Romero Lopez Maria Del Carmen",
    "wof:placetype":"venue"
},
  "geometry": {"coordinates":[-5.8687591553,38.9575881958],"type":"Point"}
}