{
  "type": "Feature",
  "properties": {
    "addr:full":"Calle de Impala, 1 Madrid Madrid 28033",
    "addr:housenumber":"1",
    "addr:postcode":"28033",
    "addr:street":"Calle De Impala",
    "iso:country":"ES",
    "sg:address":"Calle de Impala, 1",
    "sg:city":"Madrid",
    "sg:orig_category":"Laboratorios Y Cl\u00cdnicas Veterinarias",
    "sg:phone":"+34 913 81 32 34",
    "sg:postcode":"28033",
    "sg:province":"Madrid",
    "wof:name":"Sanchez-seco Muro Inmaculada",
    "wof:placetype":"venue"
},
  "geometry": {"coordinates":[-3.6365540028,40.4736747742],"type":"Point"}
}