{
  "type": "Feature",
  "properties": {
    "iso:country":"ES",
    "sg:address":"Calle de Tambre, 1",
    "sg:city":"Madrid",
    "sg:orig_category":"Inmobiliaria (agencias)",
    "sg:phone":"+34 917 45 11 50",
    "sg:postcode":"28002",
    "sg:province":"Madrid",
    "wof:name":"Villamena S.l.",
    "wof:placetype":"venue"
},
  "geometry": {"coordinates":[-3.6846120358,40.446811676],"type":"Point"}
}