{
  "type": "Feature",
  "properties": {
    "addr:full":"Calle de San Roque, 36 Rua De Valdeorras Ourense 32350",
    "addr:housenumber":"36",
    "addr:postcode":"32350",
    "addr:street":"Calle De San Roque;Rua De",
    "iso:country":"ES",
    "sg:address":"Calle de San Roque, 36",
    "sg:city":"Rua De Valdeorras",
    "sg:orig_category":"Productores Recolectores, Venta Directa De Vinos",
    "sg:phone":"+34 988 31 14 57",
    "sg:postcode":"32350",
    "sg:province":"Ourense",
    "wof:name":"Rodriguez Cao Blanca",
    "wof:placetype":"venue"
},
  "geometry": {"coordinates":[-7.1205739975,42.392490387],"type":"Point"}
}