{
  "type": "Feature",
  "properties": {
    "iso:country":"ES",
    "sg:address":"Calle de Ibaiondo, 5",
    "sg:city":"Ondarroa",
    "sg:orig_category":"Enfermeras: Consultas, Atenci\u00d3n A Domicilio",
    "sg:phone":"+34 946 83 31 30",
    "sg:postcode":"48700",
    "sg:province":"Vizcaya",
    "wof:name":"Cordoba Jorge Ismael",
    "wof:placetype":"venue"
},
  "geometry": {"coordinates":[-2.4320640564,43.3208580017],"type":"Point"}
}