{
  "type": "Feature",
  "properties": {
    "addr:full":"Calle de Emperatriz Eugenia, 5 Granada Granada 18002",
    "addr:housenumber":"5",
    "addr:postcode":"18002",
    "addr:street":"Calle De Emperatriz Eugenia",
    "iso:country":"ES",
    "sg:address":"Calle de Emperatriz Eugenia, 5",
    "sg:city":"Granada",
    "sg:orig_category":"Cajas De Ahorro",
    "sg:phone":"+34 958 29 21 90",
    "sg:postcode":"18002",
    "sg:province":"Granada",
    "sg:website":"www.lacaixa.es",
    "wof:name":"Caixa D'estalvis I Pensions De Barcelona",
    "wof:placetype":"venue"
},
  "geometry": {"coordinates":[-3.6063799858,37.1762809753],"type":"Point"}
}