{
  "type": "Feature",
  "properties": {
    "addr:full":"Calle de Posito, 2 Alia C\u00e1ceres 10137",
    "addr:housenumber":"2",
    "addr:postcode":"10137",
    "addr:street":"Calle De Posito;Ca\u0301Ceres",
    "iso:country":"ES",
    "sg:address":"Calle de Posito, 2",
    "sg:city":"Alia",
    "sg:orig_category":"Iglesia Cat\u00d3lica",
    "sg:phone":"+34 927 36 60 83",
    "sg:postcode":"10137",
    "sg:province":"C\u00e1ceres",
    "wof:name":"Parroquia Santa Catalina",
    "wof:placetype":"venue"
},
  "geometry": {"coordinates":[-5.2178578377,39.4507408142],"type":"Point"}
}