{
  "type": "Feature",
  "properties": {
    "addr:full":"Barr Santullan, S/n Santullan Cantabria 39706",
    "addr:housenumber":"s",
    "addr:postcode":"39706",
    "addr:street":"/ N",
    "iso:country":"ES",
    "sg:address":"Barr Santullan, S/n",
    "sg:city":"Santullan",
    "sg:orig_category":"Arenas, Guijarros Y Granulados",
    "sg:phone":"+34 942 87 90 13",
    "sg:postcode":"39706",
    "sg:province":"Cantabria",
    "wof:name":"Canteras De Santullan S. A.",
    "wof:placetype":"venue"
},
  "geometry": {"coordinates":[-3.2111320496,43.3472213745],"type":"Point"}
}