{
  "type": "Feature",
  "properties": {
    "addr:full":"C/ Sant Antoni, 9 Cerdanyola Valles Barcelona 08290",
    "addr:housenumber":"9",
    "addr:postcode":"08290",
    "addr:street":"C / Sant Antoni;Valles Barcelona",
    "iso:country":"ES",
    "sg:address":"C/ Sant Antoni, 9",
    "sg:city":"Cerdanyola Valles",
    "sg:orig_category":"Armaduras De Hormig\u00d3n",
    "sg:phone":"+34 936 92 73 08",
    "sg:postcode":"08290",
    "sg:province":"Barcelona",
    "wof:name":"Lacaba Urchaga Juan",
    "wof:placetype":"venue"
},
  "geometry": {"coordinates":[2.1376180649,41.4918289185],"type":"Point"}
}