{
  "type": "Feature",
  "properties": {
    "iso:country":"ES",
    "sg:address":"Avda Doctor Artero, 31",
    "sg:city":"Huesca",
    "sg:orig_category":"Electricidad, Electr\u00d3nica: Suministros (al Por Menor)",
    "sg:phone":"+34 974 21 88 90",
    "sg:postcode":"22004",
    "sg:province":"Huesca",
    "wof:name":"Inson S.a.",
    "wof:placetype":"venue"
},
  "geometry": {"coordinates":[-0.4163149893,42.1444969177],"type":"Point"}
}