{
  "type": "Feature",
  "properties": {
    "iso:country":"ES",
    "sg:address":"Calle de Libertad (de La), 7",
    "sg:city":"Alcobendas",
    "sg:orig_category":"Cajas De Ahorro",
    "sg:phone":"+34 916 53 14 07",
    "sg:postcode":"28100",
    "sg:province":"Madrid",
    "sg:website":"www.caixacatalunya.es",
    "wof:name":"Caixa D'estalvis De Catalunya",
    "wof:placetype":"venue"
},
  "geometry": {"coordinates":[-3.633893013,40.5407371521],"type":"Point"}
}