{
  "type": "Feature",
  "properties": {
    "addr:full":"Ct. Toledo-c. Real, Km. 0114,5 Yebenes Toledo 45470",
    "addr:postcode":"45470",
    "addr:street":"Real Km. 0114,5",
    "iso:country":"ES",
    "sg:address":"Ct. Toledo-c. Real, Km. 0114,5",
    "sg:city":"Yebenes",
    "sg:orig_category":"Control T\u00c9cnico De Veh\u00cdculos",
    "sg:phone":"+34 925 32 08 76",
    "sg:postcode":"45470",
    "sg:province":"Toledo",
    "wof:name":"Atisae",
    "wof:placetype":"venue"
},
  "geometry": {"coordinates":[-4.0244760513,39.8567771912],"type":"Point"}
}