{
  "type": "Feature",
  "properties": {
    "iso:country":"ES",
    "sg:address":"C/ Mar, 2",
    "sg:city":"Tossa",
    "sg:orig_category":"Molduras, Junquillos, Listones Y Molduras Perforadas",
    "sg:phone":"+34 972 34 03 89",
    "sg:postcode":"17320",
    "sg:province":"Girona",
    "wof:name":"Boada Matas Juan",
    "wof:placetype":"venue"
},
  "geometry": {"coordinates":[2.9322490692,41.7192268372],"type":"Point"}
}