{
  "type": "Feature",
  "properties": {
    "addr:full":"Calle de Herrerias, 14 Bilar \u00c1lava 01309",
    "addr:housenumber":"14",
    "addr:postcode":"01309",
    "addr:street":"Calle De Herrerias;A\u0301Lava",
    "iso:country":"ES",
    "sg:address":"Calle de Herrerias, 14",
    "sg:city":"Bilar",
    "sg:orig_category":"Farmacias",
    "sg:phone":"+34 945 60 41 34",
    "sg:postcode":"01309",
    "sg:province":"\u00c1lava",
    "wof:name":"Alberdi Juaristi Irene",
    "wof:placetype":"venue"
},
  "geometry": {"coordinates":[-2.5455868244,42.5694847107],"type":"Point"}
}