{
  "type": "Feature",
  "properties": {
    "addr:full":"Flor De Castilla Pl, 5 Tudela Duero Valladolid 47320",
    "addr:housenumber":"5;duero",
    "addr:postcode":"47320",
    "addr:street":"Pl",
    "iso:country":"ES",
    "sg:address":"Flor De Castilla Pl, 5",
    "sg:city":"Tudela Duero",
    "sg:orig_category":"Promotores Constructores",
    "sg:phone":"+34 983 52 28 04",
    "sg:postcode":"47320",
    "sg:province":"Valladolid",
    "wof:name":"Naves Industriales Vallisoletanas",
    "wof:placetype":"venue"
},
  "geometry": {"coordinates":[-4.454182148,41.507068634],"type":"Point"}
}