{
  "type": "Feature",
  "properties": {
    "iso:country":"ES",
    "sg:address":"Maestro Colas, 1",
    "sg:city":"Alpera",
    "sg:orig_category":"Estaciones De Servicio",
    "sg:phone":"+34 967 33 00 89",
    "sg:postcode":"02690",
    "sg:province":"Albacete",
    "wof:name":"Saez Egido Francisco",
    "wof:placetype":"venue"
},
  "geometry": {"coordinates":[-1.2297689915,38.9573745728],"type":"Point"}
}