{
  "type": "Feature",
  "properties": {
    "iso:country":"ES",
    "sg:address":"Ca. D'age, 12",
    "sg:city":"Puigcerda",
    "sg:orig_category":"Promotores Constructores",
    "sg:phone":"+34 972 88 30 06",
    "sg:postcode":"17520",
    "sg:province":"Girona",
    "wof:name":"Construcciones Y Reformas F Gonzalez Zafra S.l",
    "wof:placetype":"venue"
},
  "geometry": {"coordinates":[1.9281779528,42.4342803955],"type":"Point"}
}