{
  "type": "Feature",
  "properties": {
    "iso:country":"ES",
    "sg:address":"Calle de Oca, 31",
    "sg:city":"Madrid",
    "sg:orig_category":"Asociaciones, Organismos Culturales Y Socioeducativos",
    "sg:phone":"+34 915 25 48 88",
    "sg:postcode":"28025",
    "sg:province":"Madrid",
    "wof:name":"Cofradia Santisimo Sacramento Y Obras Asistenciales San Roque",
    "wof:placetype":"venue"
},
  "geometry": {"coordinates":[-3.735806942,40.389541626],"type":"Point"}
}