{
  "type": "Feature",
  "properties": {
    "addr:full":"Calle de Escritor Leiva Mu\u00d1oz, S/n Higueron C\u00f3rdoba 14193",
    "addr:housenumber":"s / n",
    "addr:postcode":"14193",
    "addr:street":"Calle De Escritor;Mun\u0303Oz;Higueron Co\u0301Rdoba",
    "iso:country":"ES",
    "sg:address":"Calle de Escritor Leiva Mu\u00d1oz, S/n",
    "sg:city":"Higueron",
    "sg:orig_category":"Ense\u00d1anza, Formaci\u00d3n Profesional: Aprendizaje",
    "sg:phone":"+34 957 32 95 11",
    "sg:postcode":"14193",
    "sg:province":"C\u00f3rdoba",
    "wof:name":"Junta De Andalucia-consejeria De Cultura",
    "wof:placetype":"venue"
},
  "geometry": {"coordinates":[-4.8510184288,37.8685188293],"type":"Point"}
}