{
  "type": "Feature",
  "properties": {
    "addr:full":"Calle de Juan De Medina, 10 Medina Pomar Burgos 09500",
    "addr:housenumber":"10",
    "addr:postcode":"09500",
    "addr:street":"Calle De Juan De Medina",
    "iso:country":"ES",
    "sg:address":"Calle de Juan De Medina, 10",
    "sg:city":"Medina Pomar",
    "sg:orig_category":"Empresas De Desmonte",
    "sg:phone":"+34 947 14 77 74",
    "sg:postcode":"09500",
    "sg:province":"Burgos",
    "wof:name":"Vivanco Pe\u00f1a Pablo",
    "wof:placetype":"venue"
},
  "geometry": {"coordinates":[-3.4863879681,42.9336204529],"type":"Point"}
}