{
  "type": "Feature",
  "properties": {
    "iso:country":"ES",
    "sg:address":"Carrer de Marina, 69",
    "sg:city":"Barcelona",
    "sg:orig_category":"Quincaller\u00cda (al Por Menor)",
    "sg:phone":"+34 933 09 02 46",
    "sg:postcode":"08005",
    "sg:province":"Barcelona",
    "wof:name":"Igual Marco Daniel",
    "wof:placetype":"venue"
},
  "geometry": {"coordinates":[2.1900041103,41.3922920227],"type":"Point"}
}