{
  "type": "Feature",
  "properties": {
    "addr:full":"Carrer de Josep Masgrau, 25 Cornella Llobregat Barcelona 08940",
    "addr:housenumber":"25",
    "addr:postcode":"08940",
    "addr:street":"Carrer De Josep Masgrau",
    "iso:country":"ES",
    "sg:address":"Carrer de Josep Masgrau, 25",
    "sg:city":"Cornella Llobregat",
    "sg:orig_category":"Electricidad: Instaladores",
    "sg:phone":"+34 932 61 91 71",
    "sg:postcode":"08940",
    "sg:province":"Barcelona",
    "wof:name":"Voltarc S.l.",
    "wof:placetype":"venue"
},
  "geometry": {"coordinates":[2.0737373829,41.3627853394],"type":"Point"}
}