{
  "type": "Feature",
  "properties": {
    "iso:country":"ES",
    "sg:address":"Carrer de Sant Pere, 67",
    "sg:city":"Lloret Mar",
    "sg:orig_category":"Hoteles",
    "sg:phone":"+34 972 36 51 00",
    "sg:postcode":"17310",
    "sg:province":"Girona",
    "wof:name":"Guitart Hotels S.a.",
    "wof:placetype":"venue"
},
  "geometry": {"coordinates":[2.8453059196,41.7018623352],"type":"Point"}
}