{
  "type": "Feature",
  "properties": {
    "iso:country":"ES",
    "sg:address":"Av Gaudi, S/n",
    "sg:city":"Rubi",
    "sg:orig_category":"Maquinaria Para Industrias Diversas",
    "sg:phone":"+34 935 86 17 90",
    "sg:postcode":"08191",
    "sg:province":"Barcelona",
    "sg:website":"www.iprocomsa.com",
    "wof:name":"Iprocom S.a.",
    "wof:placetype":"venue"
},
  "geometry": {"coordinates":[2.0096809864,41.5096092224],"type":"Point"}
}