{
  "type": "Feature",
  "properties": {
    "addr:full":"Calle de Jose Eguino, 7 Irun Guip\u00f9zcoa 20302",
    "addr:housenumber":"7",
    "addr:postcode":"20302",
    "addr:street":"Calle De Jose Eguino;Guipu\u0300Zcoa",
    "iso:country":"ES",
    "sg:address":"Calle de Jose Eguino, 7",
    "sg:city":"Irun",
    "sg:orig_category":"Ropa Para Se\u00d1oras (al Por Menor)",
    "sg:phone":"+34 943 61 83 16",
    "sg:postcode":"20302",
    "sg:province":"Guip\u00f9zcoa",
    "wof:name":"Arostegui Lasa Maria Dolores",
    "wof:placetype":"venue"
},
  "geometry": {"coordinates":[-1.7965699434,43.3375282288],"type":"Point"}
}