{
  "type": "Feature",
  "properties": {
    "iso:country":"ES",
    "sg:address":"Calle de Alloza, 72",
    "sg:city":"Castellon",
    "sg:orig_category":"Zapatos (al Por Menor)",
    "sg:phone":"+34 964 20 15 38",
    "sg:postcode":"12001",
    "sg:province":"Castell\u00f3n",
    "wof:name":"Betoret Parre\u00f1o Maria Teresa",
    "wof:placetype":"venue"
},
  "geometry": {"coordinates":[-0.0392818004,39.9866905212],"type":"Point"}
}