{
  "type": "Feature",
  "properties": {
    "iso:country":"ES",
    "sg:address":"Calle de Bravo Murillo, 122",
    "sg:city":"Madrid",
    "sg:orig_category":"Poller\u00cda Y Caza (al Por Menor)",
    "sg:phone":"+34 915 54 60 62",
    "sg:postcode":"28020",
    "sg:province":"Madrid",
    "wof:name":"Anton Lopez Santiago",
    "wof:placetype":"venue"
},
  "geometry": {"coordinates":[-3.5377447605,40.8245162964],"type":"Point"}
}