{
  "type": "Feature",
  "properties": {
    "addr:full":"Lindasol B Pblo Andaluz, 27 Marbella M\u00e1laga 29600",
    "addr:housenumber":"27",
    "addr:postcode":"29600",
    "addr:street":"Andaluz;Ma\u0301Laga",
    "iso:country":"ES",
    "sg:address":"Lindasol B Pblo Andaluz, 27",
    "sg:city":"Marbella",
    "sg:orig_category":"Doctores En Medicina",
    "sg:phone":"+34 952 92 41 44",
    "sg:postcode":"29600",
    "sg:province":"M\u00e1laga",
    "wof:name":"Servicios Medicos Medicard S.l.",
    "wof:placetype":"venue"
},
  "geometry": {"coordinates":[-4.8833007812,36.5079956055],"type":"Point"}
}