{
  "type": "Feature",
  "properties": {
    "addr:full":"Calle de Fray Luis De Leon, 15 Gijon Asturias 33208",
    "addr:housenumber":"15",
    "addr:postcode":"33208",
    "addr:street":"Calle De Fray Luis De Leon",
    "iso:country":"ES",
    "sg:address":"Calle de Fray Luis De Leon, 15",
    "sg:city":"Gijon",
    "sg:orig_category":"Agencias Y Agentes Comerciales, Representantes",
    "sg:phone":"+34 985 38 93 89",
    "sg:postcode":"33208",
    "sg:province":"Asturias",
    "wof:name":"Gonzalez Blanco Jose Maria",
    "wof:placetype":"venue"
},
  "geometry": {"coordinates":[-5.6668138504,43.5355072021],"type":"Point"}
}