{
  "type": "Feature",
  "properties": {
    "iso:country":"ES",
    "sg:address":"Ctra Leiza, 35",
    "sg:city":"Doneztebe",
    "sg:orig_category":"Empresas De Carpinter\u00cda De Madera",
    "sg:phone":"+34 948 45 02 11",
    "sg:postcode":"31740",
    "sg:province":"Navarra",
    "wof:name":"Juanotena Zurgindegia S.a.l.",
    "wof:placetype":"venue"
},
  "geometry": {"coordinates":[-1.6788890362,43.1352272034],"type":"Point"}
}