{
  "type": "Feature",
  "properties": {
    "iso:country":"ES",
    "sg:address":"Calle de Principe De Vergara, 97",
    "sg:city":"Madrid",
    "sg:orig_category":"Muebles, Minoristas",
    "sg:phone":"+34 915 62 22 36",
    "sg:postcode":"28006",
    "sg:province":"Madrid",
    "wof:name":"Muratel S. A.",
    "wof:placetype":"venue"
},
  "geometry": {"coordinates":[-3.6793210506,40.4370536804],"type":"Point"}
}