{
  "type": "Feature",
  "properties": {
    "iso:country":"ES",
    "sg:address":"Valin-pi\u00f1era, S/n",
    "sg:city":"Pi\u00f1era",
    "sg:orig_category":"Hielo Artificial (fabricaci\u00d3n, Distribuci\u00d3n)",
    "sg:phone":"+34 985 63 53 75",
    "sg:postcode":"33768",
    "sg:province":"Asturias",
    "wof:name":"Congelados Egea S.l.",
    "wof:placetype":"venue"
},
  "geometry": {"coordinates":[-6.9988479614,43.5273857117],"type":"Point"}
}