{
  "type": "Feature",
  "properties": {
    "iso:country":"ES",
    "sg:address":"Rua Diputacion, 15",
    "sg:city":"Verin",
    "sg:orig_category":"Abogados",
    "sg:phone":"+34 988 41 44 06",
    "sg:postcode":"32600",
    "sg:province":"Ourense",
    "wof:name":"Rodriguez Lamas Raul",
    "wof:placetype":"venue"
},
  "geometry": {"coordinates":[-7.4356088638,41.9377593994],"type":"Point"}
}