{
  "type": "Feature",
  "properties": {
    "addr:full":"Ctra Arevalo, 4 Berlanas \u00c1vila 05162",
    "addr:housenumber":"4",
    "addr:postcode":"05162",
    "addr:street":"Ctra Arevalo;A\u0301Vila",
    "iso:country":"ES",
    "sg:address":"Ctra Arevalo, 4",
    "sg:city":"Berlanas",
    "sg:orig_category":"Cajas De Ahorro",
    "sg:phone":"+34 920 26 62 28",
    "sg:postcode":"05162",
    "sg:province":"\u00c1vila",
    "sg:website":"www.cajaavila.com",
    "wof:name":"Caja De Avila",
    "wof:placetype":"venue"
},
  "geometry": {"coordinates":[-4.7620577812,40.7991027832],"type":"Point"}
}