{
  "type": "Feature",
  "properties": {
    "iso:country":"ES",
    "sg:address":"Plaz Nuestra Se\u00d1ora De Montemayor, S/n",
    "sg:city":"Moguer",
    "sg:orig_category":"Iglesia Cat\u00d3lica",
    "sg:phone":"+34 959 37 01 31",
    "sg:postcode":"21800",
    "sg:province":"Huelva",
    "wof:name":"Parroquia Nuestra Se\u00f1ora De La Granada",
    "wof:placetype":"venue"
},
  "geometry": {"coordinates":[-6.8355941772,37.2717857361],"type":"Point"}
}