{
  "type": "Feature",
  "properties": {
    "iso:country":"ES",
    "sg:address":"Ctra Guardo, Km. 0064,5",
    "sg:city":"Salda\u00f1a",
    "sg:orig_category":"Mec\u00c1nico Del Autom\u00d3vil",
    "sg:phone":"+34 979 89 05 47",
    "sg:postcode":"34100",
    "sg:province":"Palencia",
    "wof:name":"Merino Rueda Francisco Javier",
    "wof:placetype":"venue"
},
  "geometry": {"coordinates":[-4.7325606346,42.5272789001],"type":"Point"}
}