{
  "type": "Feature",
  "properties": {
    "addr:full":"Plaz Punto, 4 Huelva Huelva 21003",
    "addr:postcode":"21003",
    "iso:country":"ES",
    "sg:address":"Plaz Punto, 4",
    "sg:city":"Huelva",
    "sg:orig_category":"Fotocopias, Reprograf\u00cda",
    "sg:phone":"+34 959 54 09 29",
    "sg:postcode":"21003",
    "sg:province":"Huelva",
    "wof:name":"Bonanza Onubense S.l.",
    "wof:placetype":"venue"
},
  "geometry": {"coordinates":[-6.9495940208,37.256313324],"type":"Point"}
}