{
  "type": "Feature",
  "properties": {
    "addr:full":"Carrer de Garbi, 146 Pineda Mar Barcelona 08397",
    "addr:housenumber":"146",
    "addr:postcode":"08397",
    "addr:street":"Carrer De Garbi;Barcelona",
    "iso:country":"ES",
    "sg:address":"Carrer de Garbi, 146",
    "sg:city":"Pineda Mar",
    "sg:orig_category":"Venta, Montaje De Neum\u00c1ticos",
    "sg:phone":"+34 937 62 63 15",
    "sg:postcode":"08397",
    "sg:province":"Barcelona",
    "wof:name":"Neumatics Sanchez-pineda S.l.",
    "wof:placetype":"venue"
},
  "geometry": {"coordinates":[2.6739189625,41.6236686707],"type":"Point"}
}