{
  "type": "Feature",
  "properties": {
    "addr:full":"Calle de Concepcion Arenal, 42 Montijo Badajoz 06480",
    "addr:housenumber":"42",
    "addr:postcode":"06480",
    "addr:street":"Calle De Concepcion Arenal",
    "iso:country":"ES",
    "sg:address":"Calle de Concepcion Arenal, 42",
    "sg:city":"Montijo",
    "sg:orig_category":"Agentes, Concesionarios Y Sucursales De Veh\u00cdculos",
    "sg:phone":"+34 924 45 44 83",
    "sg:postcode":"06480",
    "sg:province":"Badajoz",
    "wof:name":"Talleres Albarran S.l",
    "wof:placetype":"venue"
},
  "geometry": {"coordinates":[-6.6182789803,38.9060287476],"type":"Point"}
}