{
  "type": "Feature",
  "properties": {
    "iso:country":"ES",
    "sg:address":"Calle de Mayor, 90",
    "sg:city":"Sangonera La Verde O Ermita Nueva",
    "sg:orig_category":"Librer\u00cdas",
    "sg:phone":"+34 968 86 68 06",
    "sg:postcode":"30833",
    "sg:province":"Murcia",
    "wof:name":"Zaragoza Serrano Asuncion",
    "wof:placetype":"venue"
},
  "geometry": {"coordinates":[-1.1298867464,37.9834747314],"type":"Point"}
}