{
  "type": "Feature",
  "properties": {
    "iso:country":"ES",
    "sg:address":"Calle de Zarandia, 4",
    "sg:city":"Huesca",
    "sg:orig_category":"Librer\u00cdas",
    "sg:phone":"+34 974 23 24 29",
    "sg:postcode":"22002",
    "sg:province":"Huesca",
    "wof:name":"Paul Tabue\u00f1a Elena",
    "wof:placetype":"venue"
},
  "geometry": {"coordinates":[-0.4080680013,42.1394844055],"type":"Point"}
}