{
  "type": "Feature",
  "properties": {
    "iso:country":"ES",
    "sg:address":"Calle de Andalucia, 48",
    "sg:city":"Paterna Campo",
    "sg:orig_category":"Empresas De Desmonte",
    "sg:phone":"+34 959 42 83 52",
    "sg:postcode":"21880",
    "sg:province":"Huelva",
    "wof:name":"Jedoza S.l.",
    "wof:placetype":"venue"
},
  "geometry": {"coordinates":[-6.40117836,37.4186668396],"type":"Point"}
}