{
  "type": "Feature",
  "properties": {
    "addr:full":"Calle de Iturribide, 43 Bilbao Vizcaya 48006",
    "addr:housenumber":"43",
    "addr:postcode":"48006",
    "addr:street":"Calle De Iturribide",
    "iso:country":"ES",
    "sg:address":"Calle de Iturribide, 43",
    "sg:city":"Bilbao",
    "sg:orig_category":"Electricidad: Instaladores",
    "sg:phone":"+34 944 16 08 78",
    "sg:postcode":"48006",
    "sg:province":"Vizcaya",
    "wof:name":"Arevalo Tejerina Enrique",
    "wof:placetype":"venue"
},
  "geometry": {"coordinates":[-2.9178164005,43.2573738098],"type":"Point"}
}