{
  "type": "Feature",
  "properties": {
    "addr:full":"Tres(pol Ind La Vila), S/n Novetle Valencia 46800",
    "addr:housenumber":"s / n",
    "addr:postcode":"46800",
    "iso:country":"ES",
    "sg:address":"Tres(pol Ind La Vila), S/n",
    "sg:city":"Novetle",
    "sg:orig_category":"Aparatos De Iluminaci\u00d3n (al Por Menor)",
    "sg:phone":"+34 962 27 64 53",
    "sg:postcode":"46800",
    "sg:province":"Valencia",
    "sg:website":"www.lampfordis.com",
    "wof:name":"Lampfordis S.l.u.",
    "wof:placetype":"venue"
},
  "geometry": {"coordinates":[-97.78224945069999,45.7040786743],"type":"Point"}
}