{
  "type": "Feature",
  "properties": {
    "iso:country":"ES",
    "sg:address":"Arquitectura, 14",
    "sg:city":"Can Cuias",
    "sg:orig_category":"Productos Qu\u00cdmicos (fabricaci\u00d3n, Al Por Mayor)",
    "sg:phone":"+34 935 65 06 92",
    "sg:postcode":"08110",
    "sg:province":"Barcelona",
    "sg:website":"www.sabo-esp.com",
    "wof:name":"Sociedad Anonima De Productos Quimicos Bottazzi Espa\u00f1ola",
    "wof:placetype":"venue"
},
  "geometry": {"coordinates":[2.1683700085,41.4672966003],"type":"Point"}
}