{
  "type": "Feature",
  "properties": {
    "addr:full":"Hortelano, 9 Murcia Murcia 30002",
    "addr:housenumber":"9",
    "addr:postcode":"30002",
    "addr:street":"Hortelano",
    "iso:country":"ES",
    "sg:address":"Hortelano, 9",
    "sg:city":"Murcia",
    "sg:orig_category":"Artes Gr\u00c1ficas, Artes Pl\u00c1sticas (curso)",
    "sg:phone":"+34 968 34 08 43",
    "sg:postcode":"30002",
    "sg:province":"Murcia",
    "wof:name":"Compo Rapid S.l",
    "wof:placetype":"venue"
},
  "geometry": {"coordinates":[-1.1313740015,37.9765548706],"type":"Point"}
}