{
  "type": "Feature",
  "properties": {
    "addr:full":"Pase San Roque (de), 46 Avila \u00c1vila 05003",
    "addr:postcode":"05003",
    "addr:street":"A\u0301Vila",
    "iso:country":"ES",
    "sg:address":"Pase San Roque (de), 46",
    "sg:city":"Avila",
    "sg:orig_category":"Sociedades, Compa\u00d1\u00cdas Aseguradoras",
    "sg:phone":"+34 920 35 22 42",
    "sg:postcode":"05003",
    "sg:province":"\u00c1vila",
    "wof:name":"J.lopez Porres Correduria De Seguros S.l.",
    "wof:placetype":"venue"
},
  "geometry": {"coordinates":[-4.6605348587,40.6271286011],"type":"Point"}
}