{
  "type": "Feature",
  "properties": {
    "iso:country":"ES",
    "sg:address":"Av Josep Molins, 22",
    "sg:city":"Hospitalet Llobregat",
    "sg:orig_category":"Guarder\u00cdas",
    "sg:phone":"+34 934 40 96 05",
    "sg:postcode":"08906",
    "sg:province":"Barcelona",
    "wof:name":"Llar D'infants La Gua-gua S.c.c.l.",
    "wof:placetype":"venue"
},
  "geometry": {"coordinates":[2.106511116,41.375213623],"type":"Point"}
}