{
  "type": "Feature",
  "properties": {
    "iso:country":"ES",
    "sg:address":"Convento, 39",
    "sg:city":"Beniparrell",
    "sg:orig_category":"Piezas Para Maquinaria Agr\u00cdcola",
    "sg:phone":"+34 961 21 27 87",
    "sg:postcode":"46469",
    "sg:province":"Valencia",
    "wof:name":"Indere S.l.",
    "wof:placetype":"venue"
},
  "geometry": {"coordinates":[-0.4038040042,39.3815383911],"type":"Point"}
}