{
  "type": "Feature",
  "properties": {
    "addr:full":"Calle de Mayor, 14 Reinosa Cantabria 39200",
    "addr:housenumber":"14",
    "addr:postcode":"39200",
    "addr:street":"Calle De Mayor",
    "iso:country":"ES",
    "sg:address":"Calle de Mayor, 14",
    "sg:city":"Reinosa",
    "sg:orig_category":"Fiesta: Art\u00cdculos De (al Por Menor)",
    "sg:phone":"+34 942 75 35 81",
    "sg:postcode":"39200",
    "sg:province":"Cantabria",
    "wof:name":"Prieto Grande Maria Teresa",
    "wof:placetype":"venue"
},
  "geometry": {"coordinates":[-4.1379451752,43.0005302429],"type":"Point"}
}