{
  "type": "Feature",
  "properties": {
    "addr:full":"Calle de Triana, 92 Palmas De Gran Canaria Las Palmas 35002",
    "addr:housenumber":"92",
    "addr:postcode":"35002",
    "addr:street":"Calle De Triana",
    "iso:country":"ES",
    "sg:address":"Calle de Triana, 92",
    "sg:city":"Palmas De Gran Canaria",
    "sg:orig_category":"Centros P\u00dablicos De Formaci\u00d3n Profesional Y T\u00c9cnica",
    "sg:phone":"+34 928 38 34 61",
    "sg:postcode":"35002",
    "sg:province":"Las Palmas",
    "wof:name":"Colegio Oficial De Graduados Sociales De Las Palmas De Gran Canaria",
    "wof:placetype":"venue"
},
  "geometry": {"coordinates":[-15.4164743423,28.1065654755],"type":"Point"}
}