{
  "type": "Feature",
  "properties": {
    "iso:country":"ES",
    "sg:address":"Calle de Escosura, 47-49",
    "sg:city":"Zaragoza",
    "sg:orig_category":"Centros Empresariales",
    "sg:phone":"+34 976 35 10 12",
    "sg:postcode":"50005",
    "sg:province":"Zaragoza",
    "wof:name":"Solanas Alcala M. Rosario",
    "wof:placetype":"venue"
},
  "geometry": {"coordinates":[-0.898735702,41.6483154297],"type":"Point"}
}