{
  "type": "Feature",
  "properties": {
    "iso:country":"ES",
    "sg:address":"Barr Vega, S/n",
    "sg:city":"Vega",
    "sg:orig_category":"M\u00c1rmoles, Granitos Y Piedras Naturales",
    "sg:phone":"+34 942 59 33 16",
    "sg:postcode":"39630",
    "sg:province":"Cantabria",
    "wof:name":"Marmoles Vega S.l.",
    "wof:placetype":"venue"
},
  "geometry": {"coordinates":[-3.7820117474,43.1589317322],"type":"Point"}
}