{
  "type": "Feature",
  "properties": {
    "iso:country":"ES",
    "sg:address":"Calle de Sagunto, 37",
    "sg:city":"Segorbe",
    "sg:orig_category":"Empresas De Carpinter\u00cda De Madera",
    "sg:phone":"+34 964 71 01 27",
    "sg:postcode":"12400",
    "sg:province":"Castell\u00f3n",
    "wof:name":"Carpinteria De Madera Cb",
    "wof:placetype":"venue"
},
  "geometry": {"coordinates":[-0.4887390137,39.8485107422],"type":"Point"}
}