{
  "type": "Feature",
  "properties": {
    "addr:full":"Avda Camilo Jose Cela, 5 Madrid Madrid 28028",
    "addr:housenumber":"5",
    "addr:postcode":"28028",
    "addr:street":"Avda Camilo Jose Cela",
    "iso:country":"ES",
    "sg:address":"Avda Camilo Jose Cela, 5",
    "sg:city":"Madrid",
    "sg:orig_category":"Maquinaria Para Industrias Diversas",
    "sg:phone":"+34 913 61 03 75",
    "sg:postcode":"28028",
    "sg:province":"Madrid",
    "wof:name":"Perez Carpinell Isabel",
    "wof:placetype":"venue"
},
  "geometry": {"coordinates":[-3.6678938866,40.4385910034],"type":"Point"}
}