{
  "type": "Feature",
  "properties": {
    "iso:country":"ES",
    "sg:address":"Avda Bele\u00d1a, S/n",
    "sg:city":"Guadalajara",
    "sg:orig_category":"Ense\u00d1anza Secundaria: Colegios Y Escuelas Privadas",
    "sg:phone":"+34 949 88 12 64",
    "sg:postcode":"19005",
    "sg:province":"Guadalajara",
    "wof:name":"Ies Aguas Vivas",
    "wof:placetype":"venue"
},
  "geometry": {"coordinates":[-3.1616559029,40.6382598877],"type":"Point"}
}