{
  "type": "Feature",
  "properties": {
    "iso:country":"ES",
    "sg:address":"Calle de General Espartero, 1",
    "sg:city":"Chillon",
    "sg:orig_category":"Confecci\u00d3n De Trajes Para Se\u00d1oras",
    "sg:phone":"+34 926 71 04 27",
    "sg:postcode":"13412",
    "sg:province":"Ciudad Real",
    "wof:name":"Confecciones La Esperanza",
    "wof:placetype":"venue"
},
  "geometry": {"coordinates":[-4.860268116,38.7959365845],"type":"Point"}
}