{
  "type": "Feature",
  "properties": {
    "iso:country":"ES",
    "sg:address":"Calle de Hierro, 4",
    "sg:city":"Palmas De Gran Canaria",
    "sg:orig_category":"Hosteler\u00cda, Empleados",
    "sg:phone":"+34 928 27 74 63",
    "sg:postcode":"35008",
    "sg:province":"Las Palmas",
    "wof:name":"Rossi  Franco Giacomo",
    "wof:placetype":"venue"
},
  "geometry": {"coordinates":[-15.4312038422,28.1436729431],"type":"Point"}
}