{
  "type": "Feature",
  "properties": {
    "addr:full":"Calle de Gutierre De Cetina, 36 Madrid Madrid 28017",
    "addr:housenumber":"36",
    "addr:postcode":"madrid;28017",
    "addr:street":"Calle De Gutierre De Cetina",
    "iso:country":"ES",
    "sg:address":"Calle de Gutierre De Cetina, 36",
    "sg:city":"Madrid",
    "sg:orig_category":"Estancos",
    "sg:phone":"+34 914 08 19 00",
    "sg:postcode":"28017",
    "sg:province":"Madrid",
    "wof:name":"Bravo Martin Maria",
    "wof:placetype":"venue"
},
  "geometry": {"coordinates":[-3.6426670551,40.4315834045],"type":"Point"}
}