{
  "type": "Feature",
  "properties": {
    "addr:full":"Calle de Sierra De Aracena, 47 Villanueva De La Ca\u00e7ada Madrid 28691",
    "addr:housenumber":"47",
    "addr:postcode":"28691",
    "addr:street":"Calle De Sierra De Aracena",
    "iso:country":"ES",
    "sg:address":"Calle de Sierra De Aracena, 47",
    "sg:city":"Villanueva De La Ca\u00e7ada",
    "sg:orig_category":"Comercio, Reparaci\u00d3n De Motocicletas, Bicicletas Y Piezas Sueltas",
    "sg:phone":"+34 918 11 86 96",
    "sg:postcode":"28691",
    "sg:province":"Madrid",
    "wof:name":"Todo Boxer S.l.",
    "wof:placetype":"venue"
},
  "geometry": {"coordinates":[-4.0075941086,40.4377670288],"type":"Point"}
}