{
  "type": "Feature",
  "properties": {
    "addr:full":"Avda Garat Txomin, 11 Bilbao Vizcaya 48004",
    "addr:housenumber":"11",
    "addr:postcode":"48004",
    "addr:street":"Avda Garat Txomin",
    "iso:country":"ES",
    "sg:address":"Avda Garat Txomin, 11",
    "sg:city":"Bilbao",
    "sg:orig_category":"Inform\u00c1tica: Material Y Suministros",
    "sg:phone":"+34 944 12 11 39",
    "sg:postcode":"48004",
    "sg:province":"Vizcaya",
    "wof:name":"Accesorios Software Y Hardware S.l.",
    "wof:placetype":"venue"
},
  "geometry": {"coordinates":[-2.906526804,43.2569961548],"type":"Point"}
}