{
  "type": "Feature",
  "properties": {
    "iso:country":"ES",
    "sg:address":"Calle de Enriqueta Lozano, 17",
    "sg:city":"Granada",
    "sg:orig_category":"Ense\u00d1anza: Idiomas",
    "sg:phone":"+34 958 29 37 32",
    "sg:postcode":"18009",
    "sg:province":"Granada",
    "wof:name":"Instituto Mediterraneo Sol S.l.",
    "wof:placetype":"venue"
},
  "geometry": {"coordinates":[-3.5954480171,37.1715202332],"type":"Point"}
}