{
  "type": "Feature",
  "properties": {
    "iso:country":"ES",
    "sg:address":"Avda Salvador Allende, 25",
    "sg:city":"Abanilla",
    "sg:orig_category":"Centros De Educaci\u00d3n Especial",
    "sg:phone":"+34 968 68 00 31",
    "sg:postcode":"30640",
    "sg:province":"Murcia",
    "wof:name":"Colegio Nacional Santisima Cruz",
    "wof:placetype":"venue"
},
  "geometry": {"coordinates":[-1.0392969847,38.2046737671],"type":"Point"}
}