{
  "type": "Feature",
  "properties": {
    "addr:full":"Calle de Morote, 15 Castril Granada 18816",
    "addr:housenumber":"15",
    "addr:postcode":"18816",
    "addr:street":"Calle De Morote",
    "iso:country":"ES",
    "sg:address":"Calle de Morote, 15",
    "sg:city":"Castril",
    "sg:orig_category":"Empresas De Carpinter\u00cda De Madera",
    "sg:phone":"+34 958 72 01 53",
    "sg:postcode":"18816",
    "sg:province":"Granada",
    "wof:name":"Sanchez Ruiz Jose Manuel",
    "wof:placetype":"venue"
},
  "geometry": {"coordinates":[-2.7794389725,37.7963752747],"type":"Point"}
}