{
  "type": "Feature",
  "properties": {
    "iso:country":"ES",
    "sg:address":"Calle de Arenas De Bilbao, 1",
    "sg:city":"Maravillas",
    "sg:orig_category":"Parques De Atracciones Y Centros De Esparcimiento",
    "sg:phone":"+34 971 74 46 36",
    "sg:postcode":"07610",
    "sg:province":"Islas Baleares",
    "wof:name":"Es Clots De Sarenal Sl",
    "wof:placetype":"venue"
},
  "geometry": {"coordinates":[2.737357378,39.5233879089],"type":"Point"}
}