{
  "type": "Feature",
  "properties": {
    "addr:full":"Calle de Valencia, 4 Cadiz C\u00e1diz 11009",
    "addr:housenumber":"4",
    "addr:postcode":"11009",
    "addr:street":"Calle De Valencia",
    "iso:country":"ES",
    "sg:address":"Calle de Valencia, 4",
    "sg:city":"Cadiz",
    "sg:orig_category":"Alimentaci\u00d3n General (al Por Menor)",
    "sg:phone":"+34 956 25 44 78",
    "sg:postcode":"11009",
    "sg:province":"C\u00e1diz",
    "wof:name":"Lopez Trujillo Florentina",
    "wof:placetype":"venue"
},
  "geometry": {"coordinates":[-6.2743840218,36.5087738037],"type":"Point"}
}