{
  "type": "Feature",
  "properties": {
    "iso:country":"ES",
    "sg:address":"Calle de Estudios, 3",
    "sg:city":"Madrid",
    "sg:orig_category":"Bazares, Art\u00cdculos De Limpieza Y De Cocina (al Por Menor)",
    "sg:phone":"+34 913 64 29 09",
    "sg:postcode":"28012",
    "sg:province":"Madrid",
    "wof:name":"Liu  Zhen",
    "wof:placetype":"venue"
},
  "geometry": {"coordinates":[-3.7072460651,40.4123191833],"type":"Point"}
}