{
  "type": "Feature",
  "properties": {
    "iso:country":"ES",
    "sg:address":"Calle de Martinez, 24",
    "sg:city":"Malaga",
    "sg:orig_category":"M\u00c9dicos: Estomatolog\u00cda",
    "sg:phone":"+34 952 60 97 80",
    "sg:postcode":"29005",
    "sg:province":"M\u00e1laga",
    "wof:name":"Poblaciones Fontes Rafael",
    "wof:placetype":"venue"
},
  "geometry": {"coordinates":[-4.4215869904,36.7183380127],"type":"Point"}
}