{
  "type": "Feature",
  "properties": {
    "addr:full":"Avda Castilla La Mancha, 8 Illescas Toledo 45200",
    "addr:housenumber":"8",
    "addr:postcode":"45200",
    "addr:street":"Avda Castilla La Mancha",
    "iso:country":"ES",
    "sg:address":"Avda Castilla La Mancha, 8",
    "sg:city":"Illescas",
    "sg:orig_category":"Estancos",
    "sg:phone":"+34 925 54 18 73",
    "sg:postcode":"45200",
    "sg:province":"Toledo",
    "wof:name":"San Miguel Manzanedo Carlos",
    "wof:placetype":"venue"
},
  "geometry": {"coordinates":[-3.8441810608,40.1289176941],"type":"Point"}
}