{
  "type": "Feature",
  "properties": {
    "addr:full":"Calle de Feria, 1 Puebla Almoradiel Toledo 45840",
    "addr:housenumber":"1",
    "addr:postcode":"45840",
    "addr:street":"Calle De Feria;Almoradiel",
    "iso:country":"ES",
    "sg:address":"Calle de Feria, 1",
    "sg:city":"Puebla Almoradiel",
    "sg:orig_category":"Aparatos De Iluminaci\u00d3n (al Por Menor)",
    "sg:phone":"+34 925 56 10 11",
    "sg:postcode":"45840",
    "sg:province":"Toledo",
    "wof:name":"Paver Decoracion S.l.",
    "wof:placetype":"venue"
},
  "geometry": {"coordinates":[-3.1151089668,39.598941803],"type":"Point"}
}