{
  "type": "Feature",
  "properties": {
    "iso:country":"ES",
    "sg:address":"Calle de Laurel, 8",
    "sg:city":"Montehermoso",
    "sg:orig_category":"Peluqueros: De Se\u00d1oras",
    "sg:phone":"+34 927 67 54 74",
    "sg:postcode":"10810",
    "sg:province":"C\u00e1ceres",
    "wof:name":"Hermoso Carpintero Vanesa",
    "wof:placetype":"venue"
},
  "geometry": {"coordinates":[-6.3510689735,40.0889205933],"type":"Point"}
}