{
  "type": "Feature",
  "properties": {
    "addr:full":"Carr Inmaculada, 6 Gandia Valencia 46700",
    "addr:housenumber":"6",
    "addr:postcode":"46700",
    "addr:street":"Carr Inmaculada;Valencia",
    "iso:country":"ES",
    "sg:address":"Carr Inmaculada, 6",
    "sg:city":"Gandia",
    "sg:orig_category":"Abogados",
    "sg:phone":"+34 962 87 62 16",
    "sg:postcode":"46700",
    "sg:province":"Valencia",
    "wof:name":"Gavila Valverde Inmaculada",
    "wof:placetype":"venue"
},
  "geometry": {"coordinates":[-0.1913339943,38.960735321],"type":"Point"}
}