{
  "type": "Feature",
  "properties": {
    "addr:full":"Calle de Puerta De Murcia, S/n Cartagena Murcia 30201",
    "addr:housenumber":"s / n",
    "addr:postcode":"30201",
    "addr:street":"Calle De Puerta De Murcia",
    "iso:country":"ES",
    "sg:address":"Calle de Puerta De Murcia, S/n",
    "sg:city":"Cartagena",
    "sg:orig_category":"Cajas De Ahorro",
    "sg:phone":"+34 968 52 96 08",
    "sg:postcode":"30201",
    "sg:province":"Murcia",
    "sg:website":"www.cajamurcia.es",
    "wof:name":"Caja De Ahorros De Murcia",
    "wof:placetype":"venue"
},
  "geometry": {"coordinates":[-0.9870839715,37.6020812988],"type":"Point"}
}