{
  "type": "Feature",
  "properties": {
    "addr:full":"Ctra Pandorado, 45 Astorga Le\u00f3n 24700",
    "addr:housenumber":"45",
    "addr:postcode":"24700",
    "addr:street":"Ctra Pandorado;Leo\u0301N",
    "iso:country":"ES",
    "sg:address":"Ctra Pandorado, 45",
    "sg:city":"Astorga",
    "sg:orig_category":"Contenedores (mercanc\u00cdas)",
    "sg:phone":"+34 987 61 51 84",
    "sg:postcode":"24700",
    "sg:province":"Le\u00f3n",
    "wof:name":"Gutierrez Cabezas Vicente",
    "wof:placetype":"venue"
},
  "geometry": {"coordinates":[-6.0450305939,42.5091438293],"type":"Point"}
}