{
  "type": "Feature",
  "properties": {
    "iso:country":"ES",
    "sg:address":"Calle de Cuatro Reyes, 10",
    "sg:city":"Huesca",
    "sg:orig_category":"Radiocomunicaciones, Telefon\u00cda M\u00d3vil, Radiomensajer\u00cda: Servicios, Comercializaci\u00d3n",
    "sg:phone":"+34 974 21 86 63",
    "sg:postcode":"22001",
    "sg:province":"Huesca",
    "wof:name":"Kilany  Yuusses",
    "wof:placetype":"venue"
},
  "geometry": {"coordinates":[-0.4069389999,42.138053894],"type":"Point"}
}