{
  "type": "Feature",
  "properties": {
    "iso:country":"ES",
    "sg:address":"Calle de Tres, S/n",
    "sg:city":"Ajalvir",
    "sg:orig_category":"Chapister\u00cda",
    "sg:phone":"+34 918 84 35 82",
    "sg:postcode":"28864",
    "sg:province":"Madrid",
    "wof:name":"Autocarvic S.l.",
    "wof:placetype":"venue"
},
  "geometry": {"coordinates":[-3.4803195,40.5277824402],"type":"Point"}
}