{
  "type": "Feature",
  "properties": {
    "iso:country":"ES",
    "sg:address":"Avda Montecillo, 5",
    "sg:city":"Humera-somosaguas-prado Del Rey",
    "sg:orig_category":"Importaci\u00d3n",
    "sg:phone":"+34 913 52 87 54",
    "sg:postcode":"28223",
    "sg:province":"Madrid",
    "wof:name":"Agencel S.l.",
    "wof:placetype":"venue"
},
  "geometry": {"coordinates":[-3.7820403576,40.4292640686],"type":"Point"}
}