{
  "type": "Feature",
  "properties": {
    "addr:full":"Calle de Miguel Artigas, 6 Santander Cantabria 39007",
    "addr:housenumber":"6",
    "addr:postcode":"39007",
    "addr:street":"Calle De Miguel Artigas",
    "iso:country":"ES",
    "sg:address":"Calle de Miguel Artigas, 6",
    "sg:city":"Santander",
    "sg:orig_category":"M\u00c9dicos: Estomatolog\u00cda",
    "sg:phone":"+34 942 31 01 10",
    "sg:postcode":"39007",
    "sg:province":"Cantabria",
    "wof:name":"Martinez Sanchez Fatima De La Cruz",
    "wof:placetype":"venue"
},
  "geometry": {"coordinates":[-3.8113179207,43.4623146057],"type":"Point"}
}