{
  "type": "Feature",
  "properties": {
    "addr:full":"Av Catalunya, S/n Sant Joan De Palamos Girona 17230",
    "addr:housenumber":"s",
    "addr:postcode":"17230",
    "addr:street":"Av Catalunya;/ N",
    "iso:country":"ES",
    "sg:address":"Av Catalunya, S/n",
    "sg:city":"Sant Joan De Palamos",
    "sg:orig_category":"Material Y Suministros Para Fotocopiadoras, Reprograf\u00cda",
    "sg:phone":"+34 972 60 05 07",
    "sg:postcode":"17230",
    "sg:province":"Girona",
    "wof:name":"Roige Equips D'oficina S.cv.",
    "wof:placetype":"venue"
},
  "geometry": {"coordinates":[3.1210360527,41.8528404236],"type":"Point"}
}