{
  "type": "Feature",
  "properties": {
    "addr:full":"Calle de Che Guevara, 24 Zubia Granada 18140",
    "addr:housenumber":"24",
    "addr:postcode":"18140",
    "addr:street":"Calle De Che Guevara",
    "iso:country":"ES",
    "sg:address":"Calle de Che Guevara, 24",
    "sg:city":"Zubia",
    "sg:orig_category":"Cine (producci\u00d3n, Realizaci\u00d3n)",
    "sg:phone":"+34 958 59 14 57",
    "sg:postcode":"18140",
    "sg:province":"Granada",
    "wof:name":"La Fabrica Onirica S.l.",
    "wof:placetype":"venue"
},
  "geometry": {"coordinates":[-3.5877699852,37.1189689636],"type":"Point"}
}