{
  "type": "Feature",
  "properties": {
    "iso:country":"ES",
    "sg:address":"Calle de Moral, 4",
    "sg:city":"Autol",
    "sg:orig_category":"Peluqueros: De Se\u00d1oras",
    "sg:phone":"+34 941 39 07 40",
    "sg:postcode":"26560",
    "sg:province":"La Rioja",
    "wof:name":"Jimenez Lopez De Murillas Leticia",
    "wof:placetype":"venue"
},
  "geometry": {"coordinates":[-2.0061161518,42.2149772644],"type":"Point"}
}