{
  "type": "Feature",
  "properties": {
    "addr:full":"Paseo Larrandia, 21 Gares Navarra 31100",
    "addr:housenumber":"21",
    "addr:postcode":"31100",
    "addr:street":"Paseo Larrandia;Navarra",
    "iso:country":"ES",
    "sg:address":"Paseo Larrandia, 21",
    "sg:city":"Gares",
    "sg:orig_category":"Maquinaria Para Industrias Diversas",
    "sg:phone":"+34 948 34 11 00",
    "sg:postcode":"31100",
    "sg:province":"Navarra",
    "wof:name":"Navarro Satrustegui Jose Luis",
    "wof:placetype":"venue"
},
  "geometry": {"coordinates":[-1.8169059753,42.6747894287],"type":"Point"}
}