{
  "type": "Feature",
  "properties": {
    "addr:full":"Calle de Colon, 1 Palencia Palencia 34002",
    "addr:housenumber":"1",
    "addr:postcode":"34002",
    "addr:street":"Calle De Colon",
    "iso:country":"ES",
    "sg:address":"Calle de Colon, 1",
    "sg:city":"Palencia",
    "sg:orig_category":"Lencer\u00cda Femenina, Corseter\u00cda, Trajes De Ba\u00d1o (al Por Menor)",
    "sg:phone":"+34 979 74 07 34",
    "sg:postcode":"34002",
    "sg:province":"Palencia",
    "wof:name":"Manuel Moreno Carmen",
    "wof:placetype":"venue"
},
  "geometry": {"coordinates":[-4.5315647125,42.0097236633],"type":"Point"}
}