{
  "type": "Feature",
  "properties": {
    "addr:full":"Avda General Fanjul, 82 Madrid Madrid 28044",
    "addr:housenumber":"82",
    "addr:postcode":"madrid;28044",
    "addr:street":"Avda General Fanjul",
    "iso:country":"ES",
    "sg:address":"Avda General Fanjul, 82",
    "sg:city":"Madrid",
    "sg:orig_category":"Molduras, Junquillos, Listones Y Molduras Perforadas",
    "sg:phone":"+34 917 06 90 46",
    "sg:postcode":"28044",
    "sg:province":"Madrid",
    "wof:name":"Arroyo Hernandez Maximo",
    "wof:placetype":"venue"
},
  "geometry": {"coordinates":[-3.7799882889,40.3819961548],"type":"Point"}
}