{
  "type": "Feature",
  "properties": {
    "iso:country":"ES",
    "sg:address":"Carr Major, 141",
    "sg:city":"Albalat Dels Sorells",
    "sg:orig_category":"Muebles Y Accesorios Para Cocinas Y Cuartos De Ba\u00d1o (al Por Menor)",
    "sg:phone":"+34 961 49 51 24",
    "sg:postcode":"46135",
    "sg:province":"Valencia",
    "wof:name":"Marmoles Pasvi Sl",
    "wof:placetype":"venue"
},
  "geometry": {"coordinates":[-0.3451069891,39.5451965332],"type":"Point"}
}