{
  "type": "Feature",
  "properties": {
    "iso:country":"ES",
    "sg:address":"Plaz Salvador (del), 1",
    "sg:city":"Segovia",
    "sg:orig_category":"Ense\u00d1anza Secundaria: Colegios Y Escuelas Privadas",
    "sg:phone":"+34 921 44 17 40",
    "sg:postcode":"40001",
    "sg:province":"Segovia",
    "wof:name":"Instituto De Ense\u00f1anza Secundaria Ezequiel Gonzalez",
    "wof:placetype":"venue"
},
  "geometry": {"coordinates":[-4.1144452095,40.9470405579],"type":"Point"}
}