{
  "type": "Feature",
  "properties": {
    "addr:full":"C/ Oliver, 26 Alcoi Alicante 03802",
    "addr:housenumber":"26",
    "addr:postcode":"03802",
    "addr:street":"C;Oliver",
    "iso:country":"ES",
    "sg:address":"C/ Oliver, 26",
    "sg:city":"Alcoi",
    "sg:orig_category":"Estancos",
    "sg:phone":"+34 965 33 05 32",
    "sg:postcode":"03802",
    "sg:province":"Alicante",
    "wof:name":"Moscardo Mompo Francisco Javier",
    "wof:placetype":"venue"
},
  "geometry": {"coordinates":[-0.485130012,38.6935501099],"type":"Point"}
}