{
  "type": "Feature",
  "properties": {
    "addr:full":"Calle de Huerva, 25 Zaragoza Zaragoza 50006",
    "addr:housenumber":"25",
    "addr:postcode":"50006",
    "addr:street":"Calle De Huerva",
    "iso:country":"ES",
    "sg:address":"Calle de Huerva, 25",
    "sg:city":"Zaragoza",
    "sg:orig_category":"Agentes Generales De Seguros",
    "sg:phone":"+34 976 27 11 68",
    "sg:postcode":"50006",
    "sg:province":"Zaragoza",
    "wof:name":"Liria Lafarga Francisco Javier",
    "wof:placetype":"venue"
},
  "geometry": {"coordinates":[-0.8910089731,41.6380691528],"type":"Point"}
}