{
  "type": "Feature",
  "properties": {
    "iso:country":"ES",
    "sg:address":"Calle de Marques, 10",
    "sg:city":"S. Clemente",
    "sg:orig_category":"Asilos De Ancianos. Centros Privados",
    "sg:phone":"+34 969 30 01 85",
    "sg:postcode":"16600",
    "sg:province":"Cuenca",
    "wof:name":"Asilo De Ancianos San Vicente De Paul",
    "wof:placetype":"venue"
},
  "geometry": {"coordinates":[-2.4271376133,39.4040985107],"type":"Point"}
}