{
  "type": "Feature",
  "properties": {
    "iso:country":"ES",
    "sg:address":"Carrer de Santalo, 43",
    "sg:city":"Barcelona",
    "sg:orig_category":"Asesores De Gesti\u00d3n Del Patrimonio",
    "sg:phone":"+34 932 00 21 36",
    "sg:postcode":"08021",
    "sg:province":"Barcelona",
    "wof:name":"Holm  Gustavo Christopher",
    "wof:placetype":"venue"
},
  "geometry": {"coordinates":[2.1450309753,41.3960876465],"type":"Point"}
}