{
  "type": "Feature",
  "properties": {
    "addr:full":"Av Serra, 32 Santa Maria De Palautordera Barcelona 08460",
    "addr:housenumber":"32",
    "addr:postcode":"08460",
    "addr:street":"Av Serra",
    "iso:country":"ES",
    "sg:address":"Av Serra, 32",
    "sg:city":"Santa Maria De Palautordera",
    "sg:orig_category":"Seguridad En El Trabajo Y Prevenci\u00d3n De Riesgos Laborales",
    "sg:phone":"+34 938 48 12 18",
    "sg:postcode":"08460",
    "sg:province":"Barcelona",
    "wof:name":"Iber Protexion Laboral S.l.",
    "wof:placetype":"venue"
},
  "geometry": {"coordinates":[-97.78224945069999,45.7040786743],"type":"Point"}
}