{
  "type": "Feature",
  "properties": {
    "addr:full":"Calle de Cervantes, 10 Oviedo Asturias 33004",
    "addr:housenumber":"10",
    "addr:postcode":"33004",
    "addr:street":"Calle De Cervantes",
    "iso:country":"ES",
    "sg:address":"Calle de Cervantes, 10",
    "sg:city":"Oviedo",
    "sg:orig_category":"Abogados",
    "sg:phone":"+34 985 24 54 61",
    "sg:postcode":"33004",
    "sg:province":"Asturias",
    "wof:name":"Rodriguez Arias Natalia",
    "wof:placetype":"venue"
},
  "geometry": {"coordinates":[-5.8557095528,43.3627052307],"type":"Point"}
}