{
  "type": "Feature",
  "properties": {
    "iso:country":"ES",
    "sg:address":"Avda Naciones (de), 32",
    "sg:city":"Fuenlabrada",
    "sg:orig_category":"Mercados De Productos Alimenticios",
    "sg:phone":"+34 916 08 22 66",
    "sg:postcode":"28943",
    "sg:province":"Madrid",
    "wof:name":"Fernando Pastor Sola Y Otros Cdad",
    "wof:placetype":"venue"
},
  "geometry": {"coordinates":[-3.8047111034,40.281993866],"type":"Point"}
}