{
  "type": "Feature",
  "properties": {
    "addr:full":"Avda Constitucion, 4 Nava Asturias 33520",
    "addr:housenumber":"4",
    "addr:postcode":"33520",
    "addr:street":"Avda Constitucion",
    "iso:country":"ES",
    "sg:address":"Avda Constitucion, 4",
    "sg:city":"Nava",
    "sg:orig_category":"Cajas De Ahorro",
    "sg:phone":"+34 985 71 84 21",
    "sg:postcode":"33520",
    "sg:province":"Asturias",
    "wof:name":"Caixa D'estalvis I Pensions De Barcelona",
    "wof:placetype":"venue"
},
  "geometry": {"coordinates":[-5.5018000603,43.3591842651],"type":"Point"}
}