{
  "type": "Feature",
  "properties": {
    "iso:country":"ES",
    "sg:address":"Ctra. Garnatilla, S/n",
    "sg:city":"Motril",
    "sg:orig_category":"Productos Fitosanitarios (negocio, Aplicaci\u00d3n)",
    "sg:phone":"+34 958 82 27 50",
    "sg:postcode":"18600",
    "sg:province":"Granada",
    "wof:name":"Servicios Agricolas Motril S.l.",
    "wof:placetype":"venue"
},
  "geometry": {"coordinates":[-3.4412539005,36.7427597046],"type":"Point"}
}