{
  "type": "Feature",
  "properties": {
    "iso:country":"ES",
    "sg:address":"Calle de Domingo J Navarro, 6",
    "sg:city":"Palmas De Gran Canaria",
    "sg:orig_category":"Laboratorios Y Trabajos De Fotograf\u00cda, V\u00cddeo Y Cine",
    "sg:phone":"+34 928 37 11 40",
    "sg:postcode":"35002",
    "sg:province":"Las Palmas",
    "wof:name":"Garcia Nu\u00f1ez Manuel",
    "wof:placetype":"venue"
},
  "geometry": {"coordinates":[-15.4172773361,28.107219696],"type":"Point"}
}