{
  "type": "Feature",
  "properties": {
    "addr:full":"Calle de Encinas (las), 14 Alcorcon Madrid 28922",
    "addr:housenumber":"14",
    "addr:postcode":"28922",
    "addr:street":"Calle De Encinas Las",
    "iso:country":"ES",
    "sg:address":"Calle de Encinas (las), 14",
    "sg:city":"Alcorcon",
    "sg:orig_category":"Agencias Y Agentes Comerciales, Representantes",
    "sg:phone":"+34 916 43 57 92",
    "sg:postcode":"28922",
    "sg:province":"Madrid",
    "wof:name":"Sanz Aguado Francisco",
    "wof:placetype":"venue"
},
  "geometry": {"coordinates":[-3.8362720013,40.3366775513],"type":"Point"}
}