{
  "type": "Feature",
  "properties": {
    "addr:full":"Avda Ciudad De Barcelona, 81 Madrid Madrid 28007",
    "addr:housenumber":"81",
    "addr:postcode":"madrid;28007",
    "addr:street":"Avda Ciudad De Barcelona",
    "iso:country":"ES",
    "sg:address":"Avda Ciudad De Barcelona, 81",
    "sg:city":"Madrid",
    "sg:orig_category":"Cooperativas Agr\u00cdcolas",
    "sg:phone":"+34 915 01 39 60",
    "sg:postcode":"28007",
    "sg:province":"Madrid",
    "sg:website":"www.agesul.com",
    "wof:name":"Agesul S.l.",
    "wof:placetype":"venue"
},
  "geometry": {"coordinates":[-3.6744921207,40.4010162354],"type":"Point"}
}