{
  "type": "Feature",
  "properties": {
    "iso:country":"ES",
    "sg:address":"Carrer de Sant Jordi, 16",
    "sg:city":"Roda Ter",
    "sg:orig_category":"Agricultores, Agricultores",
    "sg:phone":"+34 938 54 11 01",
    "sg:postcode":"08510",
    "sg:province":"Barcelona",
    "wof:name":"Explotacions Ramaderas Rovira S.l.",
    "wof:placetype":"venue"
},
  "geometry": {"coordinates":[2.3070189953,41.9843826294],"type":"Point"}
}