{
  "type": "Feature",
  "properties": {
    "iso:country":"ES",
    "sg:address":"Calle de Juan Francisco, 5",
    "sg:city":"Madrid",
    "sg:orig_category":"Molduras, Junquillos, Listones Y Molduras Perforadas",
    "sg:phone":"+34 914 72 75 32",
    "sg:postcode":"28025",
    "sg:province":"Madrid",
    "wof:name":"Ramirez Serrano Maria Mercedes",
    "wof:placetype":"venue"
},
  "geometry": {"coordinates":[-3.7313818932,40.3875274658],"type":"Point"}
}