{
  "type": "Feature",
  "properties": {
    "iso:country":"ES",
    "sg:address":"Calle de Balbino Orensanz, 25",
    "sg:city":"Zaragoza",
    "sg:orig_category":"Complementos Para Pasteler\u00cdas, Confiter\u00cdas Y Chocolater\u00cdas",
    "sg:phone":"+34 976 29 50 38",
    "sg:postcode":"50014",
    "sg:province":"Zaragoza",
    "wof:name":"Magen Garcia Antonio Fermin",
    "wof:placetype":"venue"
},
  "geometry": {"coordinates":[-0.8585957289,41.6571273804],"type":"Point"}
}