{
  "type": "Feature",
  "properties": {
    "addr:full":"Avda Principal, 61 Navas Del Marques \u00c1vila 05230",
    "addr:housenumber":"61",
    "addr:postcode":"05230",
    "addr:street":"Avda Principal",
    "iso:country":"ES",
    "sg:address":"Avda Principal, 61",
    "sg:city":"Navas Del Marques",
    "sg:orig_category":"Venta, Instalaci\u00d3n De Calefacci\u00d3n",
    "sg:phone":"+34 918 97 24 74",
    "sg:postcode":"05230",
    "sg:province":"\u00c1vila",
    "wof:name":"Incalsan Calefaccion C.d.",
    "wof:placetype":"venue"
},
  "geometry": {"coordinates":[-4.3334889412,40.6027450562],"type":"Point"}
}