{
  "type": "Feature",
  "properties": {
    "addr:full":"Calle de Almendros (los), 28 Azuqueca Henares Guadalajara 19200",
    "addr:housenumber":"28",
    "addr:postcode":"19200",
    "addr:street":"Calle De Almendros Los",
    "iso:country":"ES",
    "sg:address":"Calle de Almendros (los), 28",
    "sg:city":"Azuqueca Henares",
    "sg:orig_category":"Arreglo, Reparaci\u00d3n, Piezas Sueltas De Televisi\u00d3n, V\u00cddeo, Hi",
    "sg:phone":"+34 949 26 40 13",
    "sg:postcode":"19200",
    "sg:province":"Guadalajara",
    "wof:name":"Piedra Garcia Jose Miguel",
    "wof:placetype":"venue"
},
  "geometry": {"coordinates":[-3.2602350712,40.5670013428],"type":"Point"}
}