{
  "type": "Feature",
  "properties": {
    "addr:full":"Calle de Islas Filipinas, 1 Higuera De Las Due\u00e7as \u00c1vila 05427",
    "addr:housenumber":"1",
    "addr:postcode":"05427",
    "addr:street":"Calle De Islas Filipinas;A\u0301Vila",
    "iso:country":"ES",
    "sg:address":"Calle de Islas Filipinas, 1",
    "sg:city":"Higuera De Las Due\u00e7as",
    "sg:orig_category":"Centros De Educaci\u00d3n Especial",
    "sg:phone":"+34 918 67 31 16",
    "sg:postcode":"05427",
    "sg:province":"\u00c1vila",
    "wof:name":"Ayuntamiento De Higuera De Las Due\u00f1as",
    "wof:placetype":"venue"
},
  "geometry": {"coordinates":[-4.6015148163,40.2397232056],"type":"Point"}
}