{
  "type": "Feature",
  "properties": {
    "addr:full":"Mastin-p I Carretera Amarilla, 10 Sevilla Sevilla 41007",
    "addr:housenumber":"10",
    "addr:postcode":"41007",
    "addr:street":"Carretera Amarilla",
    "iso:country":"ES",
    "sg:address":"Mastin-p I Carretera Amarilla, 10",
    "sg:city":"Sevilla",
    "sg:orig_category":"Alimentaci\u00d3n General (al Por Mayor)",
    "sg:phone":"+34 954 51 87 33",
    "sg:postcode":"41007",
    "sg:province":"Sevilla",
    "wof:name":"Alimentacion Monserrat Jose Juan Cortes Serrano Y Asociados S.l.",
    "wof:placetype":"venue"
},
  "geometry": {"coordinates":[-5.9554004669,37.3921318054],"type":"Point"}
}