{
  "type": "Feature",
  "properties": {
    "addr:full":"Carr Xara, 29 Alcudia Islas Baleares 07400",
    "addr:housenumber":"29",
    "addr:postcode":"07400",
    "addr:street":"Carr Xara",
    "iso:country":"ES",
    "sg:address":"Carr Xara, 29",
    "sg:city":"Alcudia",
    "sg:orig_category":"Reparaci\u00d3n Y Restauraci\u00d3n De Objetos Diversos",
    "sg:phone":"+34 971 54 72 66",
    "sg:postcode":"07400",
    "sg:province":"Islas Baleares",
    "wof:name":"Neumatics Llabres Mayol",
    "wof:placetype":"venue"
},
  "geometry": {"coordinates":[3.1233251095,39.8516159058],"type":"Point"}
}