{
  "type": "Feature",
  "properties": {
    "addr:full":"Carrer de Riu De La Plata, 27 Lloret Mar Girona 17310",
    "addr:housenumber":"27",
    "addr:postcode":"17310",
    "addr:street":"Carrer De Riu De La Plata",
    "iso:country":"ES",
    "sg:address":"Carrer de Riu De La Plata, 27",
    "sg:city":"Lloret Mar",
    "sg:orig_category":"Supermercados Y Hipermercados",
    "sg:phone":"+34 972 37 34 52",
    "sg:postcode":"17310",
    "sg:province":"Girona",
    "wof:name":"Aldevi S.l.",
    "wof:placetype":"venue"
},
  "geometry": {"coordinates":[2.8236999512,41.9817962646],"type":"Point"}
}