{
  "type": "Feature",
  "properties": {
    "addr:full":"Calle de Ayala, 2 Torreperogil Ja\u00e9n 23320",
    "addr:housenumber":"2",
    "addr:postcode":"23320",
    "addr:street":"Calle De Ayala",
    "iso:country":"ES",
    "sg:address":"Calle de Ayala, 2",
    "sg:city":"Torreperogil",
    "sg:orig_category":"Ropa De Trabajo Y Profesionales (fabricaci\u00d3n, Al Por Mayor)",
    "sg:phone":"+34 953 77 61 81",
    "sg:postcode":"23320",
    "sg:province":"Ja\u00e9n",
    "wof:name":"Confecciones Samisa S.l.",
    "wof:placetype":"venue"
},
  "geometry": {"coordinates":[-3.2868309021,38.0367469788],"type":"Point"}
}