{
  "type": "Feature",
  "properties": {
    "addr:full":"Calle de Anzuelo, 40 Puerto Del Carmen Las Palmas 35510",
    "addr:housenumber":"40",
    "addr:postcode":"35510",
    "addr:street":"Calle De Anzuelo",
    "iso:country":"ES",
    "sg:address":"Calle de Anzuelo, 40",
    "sg:city":"Puerto Del Carmen",
    "sg:orig_category":"Bazares, Art\u00cdculos De Limpieza Y De Cocina (al Por Menor)",
    "sg:phone":"+34 928 51 49 89",
    "sg:postcode":"35510",
    "sg:province":"Las Palmas",
    "wof:name":"Jiangping Internacional S.l.",
    "wof:placetype":"venue"
},
  "geometry": {"coordinates":[-13.6533575058,28.9206790924],"type":"Point"}
}