{
  "type": "Feature",
  "properties": {
    "iso:country":"ES",
    "sg:address":"Carrer de Canon Mateu Rotger, 9",
    "sg:city":"Arenal",
    "sg:orig_category":"Reparaciones Y Remolcado De Veh\u00cdculos",
    "sg:phone":"+34 971 26 41 93",
    "sg:postcode":"07600",
    "sg:province":"Islas Baleares",
    "wof:name":"Sampol Roig Antonio",
    "wof:placetype":"venue"
},
  "geometry": {"coordinates":[2.753565073,39.5086135864],"type":"Point"}
}