{
  "type": "Feature",
  "properties": {
    "addr:full":"Rua Forni\u00d1os (dos), 64 Santiago De Compostela La Coru\u00f1a 15705",
    "addr:housenumber":"64",
    "addr:postcode":"15705",
    "addr:street":"Rua Fornin\u0303Os Dos;Corun\u0303A",
    "iso:country":"ES",
    "sg:address":"Rua Forni\u00d1os (dos), 64",
    "sg:city":"Santiago De Compostela",
    "sg:orig_category":"Servicios De Telecomunicaciones",
    "sg:phone":"+34 981 55 77 37",
    "sg:postcode":"15705",
    "sg:province":"La Coru\u00f1a",
    "sg:website":"www.isoluxwat.es",
    "wof:name":"Isolux Wat S.a.",
    "wof:placetype":"venue"
},
  "geometry": {"coordinates":[-8.5858488083,42.8696060181],"type":"Point"}
}