{
  "type": "Feature",
  "properties": {
    "iso:country":"ES",
    "sg:address":"Calle de Breton De Los Herreros, 35",
    "sg:city":"Madrid",
    "sg:orig_category":"Audiovisuales (producci\u00d3n, Edici\u00d3n, Realizaci\u00d3n)",
    "sg:phone":"+34 914 41 03 22",
    "sg:postcode":"28003",
    "sg:province":"Madrid",
    "sg:website":"www.documentales.net",
    "wof:name":"Argonauta Producciones S.l.",
    "wof:placetype":"venue"
},
  "geometry": {"coordinates":[-3.6975693703,40.4395370483],"type":"Point"}
}