{
  "type": "Feature",
  "properties": {
    "iso:country":"ES",
    "sg:address":"Julio Sesto, 3",
    "sg:city":"Calvario",
    "sg:orig_category":"Supermercados Y Hipermercados",
    "sg:phone":"+34 986 62 50 69",
    "sg:postcode":"36770",
    "sg:province":"Pontevedra",
    "wof:name":"Martinez Perez Ramon",
    "wof:placetype":"venue"
},
  "geometry": {"coordinates":[-8.4288873672,42.1177940369],"type":"Point"}
}