{
  "type": "Feature",
  "properties": {
    "addr:full":"Carrer de Mare De Deu De La Merce, 27 Santa Coloma De Gramenet Barcelona 08921",
    "addr:housenumber":"27",
    "addr:postcode":"08921",
    "addr:street":"Carrer De Mare De Deu De La Merce",
    "iso:country":"ES",
    "sg:address":"Carrer de Mare De Deu De La Merce, 27",
    "sg:city":"Santa Coloma De Gramenet",
    "sg:orig_category":"Electricidad: Instaladores",
    "sg:phone":"+34 934 66 32 36",
    "sg:postcode":"08921",
    "sg:province":"Barcelona",
    "sg:website":"www.construccionesortega.com",
    "wof:name":"Ortega Manzano Francisco",
    "wof:placetype":"venue"
},
  "geometry": {"coordinates":[2.2021589279,41.4519920349],"type":"Point"}
}