{
  "type": "Feature",
  "properties": {
    "addr:full":"Pase Revellin (del), 22 Ceuta Ceuta 51001",
    "addr:postcode":"51001",
    "iso:country":"ES",
    "sg:address":"Pase Revellin (del), 22",
    "sg:city":"Ceuta",
    "sg:orig_category":"Agencias De Viajes",
    "sg:phone":"+34 956 51 77 17",
    "sg:postcode":"51001",
    "sg:province":"Ceuta",
    "sg:website":"www.halconviajes.com",
    "wof:name":"Viajes Halcon S.a.",
    "wof:placetype":"venue"
},
  "geometry": {"coordinates":[-5.3302302361,35.8947601318],"type":"Point"}
}