{
  "type": "Feature",
  "properties": {
    "addr:full":"Pol Ind El Pino, 27 Sevilla Sevilla 41016",
    "addr:housenumber":"27",
    "addr:postcode":"41016",
    "addr:street":"El Pino",
    "iso:country":"ES",
    "sg:address":"Pol Ind El Pino, 27",
    "sg:city":"Sevilla",
    "sg:orig_category":"Molduras, Junquillos, Listones Y Molduras Perforadas",
    "sg:phone":"+34 954 25 20 54",
    "sg:postcode":"41016",
    "sg:province":"Sevilla",
    "wof:name":"Francisco Perez Gutierrez",
    "wof:placetype":"venue"
},
  "geometry": {"coordinates":[-5.9262089729,37.3770637512],"type":"Point"}
}