{
  "type": "Feature",
  "properties": {
    "addr:full":"Carrer de Consell De Cent, 91 Barcelona Barcelona 08015",
    "addr:housenumber":"91",
    "addr:postcode":"08015",
    "addr:street":"Carrer De Consell De Cent",
    "iso:country":"ES",
    "sg:address":"Carrer de Consell De Cent, 91",
    "sg:city":"Barcelona",
    "sg:orig_category":"Alimentaci\u00d3n General (al Por Menor)",
    "sg:phone":"+34 934 23 05 12",
    "sg:postcode":"08015",
    "sg:province":"Barcelona",
    "wof:name":"Pinto Sarri Asuncion",
    "wof:placetype":"venue"
},
  "geometry": {"coordinates":[2.1505959034,41.3799247742],"type":"Point"}
}