{
  "type": "Feature",
  "properties": {
    "addr:full":"Calle de Doctor Nicasio Benlloch, 1 Valencia Valencia 46009",
    "addr:housenumber":"1",
    "addr:postcode":"46009",
    "addr:street":"Calle De Doctor Nicasio Benlloch",
    "iso:country":"ES",
    "sg:address":"Calle de Doctor Nicasio Benlloch, 1",
    "sg:city":"Valencia",
    "sg:orig_category":"Agentes, Concesionarios Y Sucursales De Veh\u00cdculos",
    "sg:phone":"+34 963 49 76 29",
    "sg:postcode":"46009",
    "sg:province":"Valencia",
    "wof:name":"Olivares Tebar Roberto",
    "wof:placetype":"venue"
},
  "geometry": {"coordinates":[-0.3882234097,39.4870910645],"type":"Point"}
}