{
  "type": "Feature",
  "properties": {
    "iso:country":"ES",
    "sg:address":"Calle de Puerta Del Campo, 21",
    "sg:city":"Arganda",
    "sg:orig_category":"Escultores, Estatuarios E Imagineros",
    "sg:phone":"+34 918 71 09 52",
    "sg:postcode":"28500",
    "sg:province":"Madrid",
    "wof:name":"Rodriguez Vazquez Jose",
    "wof:placetype":"venue"
},
  "geometry": {"coordinates":[-3.4371199608,40.3030738831],"type":"Point"}
}