{
  "type": "Feature",
  "properties": {
    "iso:country":"ES",
    "sg:address":"Avda Fuenlabrada (de), 96",
    "sg:city":"Humanes De Madrid",
    "sg:orig_category":"Mudanzas",
    "sg:phone":"+34 916 04 89 61",
    "sg:postcode":"28970",
    "sg:province":"Madrid",
    "wof:name":"Mudanzas Y Transportes Jimenez S. L.",
    "wof:placetype":"venue"
},
  "geometry": {"coordinates":[-3.8132150173,40.2667236328],"type":"Point"}
}