{
  "type": "Feature",
  "properties": {
    "addr:full":"Avda Gaspar Aguilar, 19 Valencia Valencia 46007",
    "addr:housenumber":"19",
    "addr:postcode":"46007",
    "addr:street":"Avda Gaspar Aguilar",
    "iso:country":"ES",
    "sg:address":"Avda Gaspar Aguilar, 19",
    "sg:city":"Valencia",
    "sg:orig_category":"Copas, Insignias, Trofeos",
    "sg:phone":"+34 963 80 58 88",
    "sg:postcode":"46007",
    "sg:province":"Valencia",
    "wof:name":"Alvarez Mainero Francisco Javier",
    "wof:placetype":"venue"
},
  "geometry": {"coordinates":[-0.3891409934,39.4582901001],"type":"Point"}
}