{
  "type": "Feature",
  "properties": {
    "addr:full":"Carrer de Coma (la), 5 Morell Tarragona 43760",
    "addr:housenumber":"5",
    "addr:postcode":"43760",
    "addr:street":"Carrer De Coma La",
    "iso:country":"ES",
    "sg:address":"Carrer de Coma (la), 5",
    "sg:city":"Morell",
    "sg:orig_category":"Empresas De Carpinter\u00cda De Madera",
    "sg:phone":"+34 977 84 29 80",
    "sg:postcode":"43760",
    "sg:province":"Tarragona",
    "wof:name":"Guillemat Verderas Josep Maria",
    "wof:placetype":"venue"
},
  "geometry": {"coordinates":[1.2065999508,41.1918067932],"type":"Point"}
}