{
  "type": "Feature",
  "properties": {
    "iso:country":"ES",
    "sg:address":"Calle de Andres Mellado, 16",
    "sg:city":"Madrid",
    "sg:orig_category":"Servicios Gsm",
    "sg:phone":"+34 915 44 79 83",
    "sg:postcode":"28015",
    "sg:province":"Madrid",
    "sg:website":"www.bactel.es",
    "wof:name":"B.a.c.negocios S.l.",
    "wof:placetype":"venue"
},
  "geometry": {"coordinates":[-3.7143690586,40.4320259094],"type":"Point"}
}