{
  "type": "Feature",
  "properties": {
    "iso:country":"ES",
    "sg:address":"Avda Lerida (de), 11",
    "sg:city":"Monzon",
    "sg:orig_category":"Panader\u00cdas, Panader\u00cdas",
    "sg:phone":"+34 974 41 52 70",
    "sg:postcode":"22400",
    "sg:province":"Huesca",
    "wof:name":"Gonzalez Checa Francisco",
    "wof:placetype":"venue"
},
  "geometry": {"coordinates":[0.1937749982,41.9124832153],"type":"Point"}
}