{
  "type": "Feature",
  "properties": {
    "addr:full":"Avda Alfonso Vi, 6 Salamanca Salamanca 37005",
    "addr:housenumber":"6",
    "addr:postcode":"37005",
    "addr:street":"Avda Alfonso Vi",
    "iso:country":"ES",
    "sg:address":"Avda Alfonso Vi, 6",
    "sg:city":"Salamanca",
    "sg:orig_category":"Alimentaci\u00d3n General (al Por Menor)",
    "sg:phone":"+34 923 22 50 43",
    "sg:postcode":"37005",
    "sg:province":"Salamanca",
    "wof:name":"Perez Oliva Amable",
    "wof:placetype":"venue"
},
  "geometry": {"coordinates":[-5.6601848602,40.9756011963],"type":"Point"}
}