{
  "type": "Feature",
  "properties": {
    "addr:full":"Luga Xan Faba, 14 Campons A Coru\u00f1a 15181",
    "addr:housenumber":"14",
    "addr:postcode":"15181",
    "addr:street":"Faba;Corun\u0303A",
    "iso:country":"ES",
    "sg:address":"Luga Xan Faba, 14",
    "sg:city":"Campons",
    "sg:orig_category":"Ropa De Cuero Y De Piel (confecci\u00d3n, Al Por Mayor)",
    "sg:phone":"+34 981 61 31 05",
    "sg:postcode":"15181",
    "sg:province":"A Coru\u00f1a",
    "wof:name":"Vs Difusion S.l.",
    "wof:placetype":"venue"
},
  "geometry": {"coordinates":[-8.3566160202,43.2841720581],"type":"Point"}
}