{
  "type": "Feature",
  "properties": {
    "addr:full":"Calle de Pantaleon, 8 Marbella M\u00e1laga 29600",
    "addr:housenumber":"8",
    "addr:postcode":"29600",
    "addr:street":"Calle De Pantaleon;Ma\u0301Laga",
    "iso:country":"ES",
    "sg:address":"Calle de Pantaleon, 8",
    "sg:city":"Marbella",
    "sg:orig_category":"Confecci\u00d3n De Trajes Para Se\u00d1oras",
    "sg:phone":"+34 952 82 75 88",
    "sg:postcode":"29600",
    "sg:province":"M\u00e1laga",
    "wof:name":"Boutique Loymar S.c.",
    "wof:placetype":"venue"
},
  "geometry": {"coordinates":[-4.8854079247,36.5096435547],"type":"Point"}
}