{
  "type": "Feature",
  "properties": {
    "addr:full":"Calle de Fontan, 19 Oviedo Asturias 33009",
    "addr:housenumber":"19",
    "addr:postcode":"33009",
    "addr:street":"Calle De Fontan",
    "iso:country":"ES",
    "sg:address":"Calle de Fontan, 19",
    "sg:city":"Oviedo",
    "sg:orig_category":"Tiendas De Grano, Frutas Y Legumbres Secas (al Por Menor)",
    "sg:phone":"+34 985 22 62 63",
    "sg:postcode":"33009",
    "sg:province":"Asturias",
    "wof:name":"Caramelo Fontan C.b.",
    "wof:placetype":"venue"
},
  "geometry": {"coordinates":[-5.8463931084,43.3599243164],"type":"Point"}
}