{
  "type": "Feature",
  "properties": {
    "iso:country":"ES",
    "sg:address":"Avda Benalmadena, 30",
    "sg:city":"Torremolinos",
    "sg:orig_category":"Centros M\u00c9dicos Y Sociales, Dispensarios",
    "sg:phone":"+34 952 05 22 24",
    "sg:postcode":"29620",
    "sg:province":"M\u00e1laga",
    "wof:name":"Martin Salas Cristina",
    "wof:placetype":"venue"
},
  "geometry": {"coordinates":[-4.5178012848,36.6059341431],"type":"Point"}
}