{
  "type": "Feature",
  "properties": {
    "iso:country":"ES",
    "sg:address":"Calle de Cabo San Vicente, 2",
    "sg:city":"Alcorcon",
    "sg:orig_category":"Peluquer\u00cdas, Peluquer\u00cda Mixta",
    "sg:phone":"+34 916 11 46 68",
    "sg:postcode":"28924",
    "sg:province":"Madrid",
    "wof:name":"Moreno Robledo Laura",
    "wof:placetype":"venue"
},
  "geometry": {"coordinates":[-3.8174815178,40.3537483215],"type":"Point"}
}