{
  "type": "Feature",
  "properties": {
    "addr:full":"Carr Canonge Baranera, 54 Badalona Barcelona 08911",
    "addr:housenumber":"54",
    "addr:postcode":"08911",
    "addr:street":"Carr Canonge Baranera",
    "iso:country":"ES",
    "sg:address":"Carr Canonge Baranera, 54",
    "sg:city":"Badalona",
    "sg:orig_category":"Materias Pl\u00c1sticas: Productos De Consumo Masivo (fabricaci\u00d3n, Al Por Mayor)",
    "sg:phone":"+34 933 84 59 59",
    "sg:postcode":"08911",
    "sg:province":"Barcelona",
    "wof:name":"Dauder Xifre Laura",
    "wof:placetype":"venue"
},
  "geometry": {"coordinates":[2.2510108948,41.4501647949],"type":"Point"}
}