{
  "type": "Feature",
  "properties": {
    "iso:country":"ES",
    "sg:address":"Calle de Rio Manzanares, 23",
    "sg:city":"Illescas",
    "sg:orig_category":"Empresas De Desmonte",
    "sg:phone":"+34 925 51 14 12",
    "sg:postcode":"45200",
    "sg:province":"Toledo",
    "wof:name":"Hijos De Esteban Mora S.l.",
    "wof:placetype":"venue"
},
  "geometry": {"coordinates":[-3.8500890732,40.131061554],"type":"Point"}
}