{
  "type": "Feature",
  "properties": {
    "iso:country":"ES",
    "sg:address":"Calle de Doctor Castelo, 45",
    "sg:city":"Madrid",
    "sg:orig_category":"M\u00c9dicos: Ginecolog\u00cda Y Obstetricia",
    "sg:phone":"+34 915 74 36 82",
    "sg:postcode":"28009",
    "sg:province":"Madrid",
    "wof:name":"Martinez Martinez Mariano",
    "wof:placetype":"venue"
},
  "geometry": {"coordinates":[-3.6730811596,40.4202346802],"type":"Point"}
}