{
  "type": "Feature",
  "properties": {
    "addr:full":"Calle de San Fernando, 42 Dos Hermanas Sevilla 41700",
    "addr:housenumber":"42",
    "addr:postcode":"41700",
    "addr:street":"Calle De San Fernando",
    "iso:country":"ES",
    "sg:address":"Calle de San Fernando, 42",
    "sg:city":"Dos Hermanas",
    "sg:orig_category":"Asesor\u00cda Fiscal Y Jur\u00cddica",
    "sg:phone":"+34 955 66 51 54",
    "sg:postcode":"41700",
    "sg:province":"Sevilla",
    "wof:name":"Rosado Rivas Vicente",
    "wof:placetype":"venue"
},
  "geometry": {"coordinates":[-5.9173669815,37.2787361145],"type":"Point"}
}