{
  "type": "Feature",
  "properties": {
    "iso:country":"ES",
    "sg:address":"Ctra Calafell, 3",
    "sg:city":"Vendrell",
    "sg:orig_category":"Frutas Y Legumbres Frescas (al Por Mayor)",
    "sg:phone":"+34 977 66 42 63",
    "sg:postcode":"43700",
    "sg:province":"Tarragona",
    "wof:name":"Frutas Vendrell S.a.",
    "wof:placetype":"venue"
},
  "geometry": {"coordinates":[1.5408730507,41.22240448],"type":"Point"}
}