{
  "type": "Feature",
  "properties": {
    "iso:country":"ES",
    "sg:address":"Carrer de Segle Xx, 22",
    "sg:city":"Barcelona",
    "sg:orig_category":"Cer\u00c1micas: Material Y Suministros",
    "sg:phone":"+34 933 51 41 04",
    "sg:postcode":"08041",
    "sg:province":"Barcelona",
    "wof:name":"Cartanya Verdaguer Isabel",
    "wof:placetype":"venue"
},
  "geometry": {"coordinates":[2.1777260303,41.4228630066],"type":"Point"}
}