{
  "type": "Feature",
  "properties": {
    "iso:country":"ES",
    "sg:address":"Calle de Lago De Sanabria, 44",
    "sg:city":"Parla",
    "sg:orig_category":"Electricidad: Instaladores",
    "sg:phone":"+34 916 05 08 71",
    "sg:postcode":"28980",
    "sg:province":"Madrid",
    "wof:name":"Inizsa 2003 S.l.",
    "wof:placetype":"venue"
},
  "geometry": {"coordinates":[-3.7745110989,40.2479019165],"type":"Point"}
}