{
  "type": "Feature",
  "properties": {
    "addr:full":"Bda Zabal (p I Zabal Bajo), 88 La Linea C\u00e1diz 11300",
    "addr:postcode":"11300",
    "addr:street":"88",
    "iso:country":"ES",
    "sg:address":"Bda Zabal (p I Zabal Bajo), 88",
    "sg:city":"La Linea",
    "sg:orig_category":"Agentes, Concesionarios Y Sucursales De Veh\u00cdculos",
    "sg:phone":"+34 956 64 34 55",
    "sg:postcode":"11300",
    "sg:province":"C\u00e1diz",
    "wof:name":"Dumas Lopez Jose S.l.",
    "wof:placetype":"venue"
},
  "geometry": {"coordinates":[-5.3429989815,36.1873588562],"type":"Point"}
}