{
  "type": "Feature",
  "properties": {
    "addr:full":"Calle de Virgen De Los Desamparados, 56 Novelda Alicante 03660",
    "addr:housenumber":"56",
    "addr:postcode":"03660",
    "addr:street":"Calle De Virgen De Los Desamparados",
    "iso:country":"ES",
    "sg:address":"Calle de Virgen De Los Desamparados, 56",
    "sg:city":"Novelda",
    "sg:orig_category":"Charcuter\u00cdas (al Por Mayor)",
    "sg:phone":"+34 965 60 30 30",
    "sg:postcode":"03660",
    "sg:province":"Alicante",
    "wof:name":"Eustasio Garcia S.l.",
    "wof:placetype":"venue"
},
  "geometry": {"coordinates":[-0.7688980103,38.3828010559],"type":"Point"}
}