{
  "type": "Feature",
  "properties": {
    "addr:full":"Carrer de Feliu Tura, 49 Mollet Valles Barcelona 08100",
    "addr:housenumber":"49",
    "addr:postcode":"08100",
    "addr:street":"Carrer De Feliu Tura",
    "iso:country":"ES",
    "sg:address":"Carrer de Feliu Tura, 49",
    "sg:city":"Mollet Valles",
    "sg:orig_category":"Flores Y Plantas Naturales (al Por Mayor)",
    "sg:phone":"+34 935 70 83 24",
    "sg:postcode":"08100",
    "sg:province":"Barcelona",
    "wof:name":"Roldan Pacheco Julio",
    "wof:placetype":"venue"
},
  "geometry": {"coordinates":[2.2166249752,41.5438613892],"type":"Point"}
}