{
  "type": "Feature",
  "properties": {
    "addr:full":"Calle de Santiago Lope, 15 Benimamet-beniferri Valencia 46035",
    "addr:housenumber":"15",
    "addr:postcode":"46035",
    "addr:street":"Calle De Santiago Lope",
    "iso:country":"ES",
    "sg:address":"Calle de Santiago Lope, 15",
    "sg:city":"Benimamet-beniferri",
    "sg:orig_category":"Farmacias",
    "sg:phone":"+34 963 63 63 81",
    "sg:postcode":"46035",
    "sg:province":"Valencia",
    "wof:name":"Blasco Carbo Cb",
    "wof:placetype":"venue"
},
  "geometry": {"coordinates":[-0.4188109934,39.5037612915],"type":"Point"}
}