{
  "type": "Feature",
  "properties": {
    "addr:full":"Calle de Sierra De Gredos, 13 Ejido Almer\u00eda 04700",
    "addr:housenumber":"13 ejido",
    "addr:postcode":"04700",
    "addr:street":"Calle De Sierra De Gredos;Almeri\u0301A",
    "iso:country":"ES",
    "sg:address":"Calle de Sierra De Gredos, 13",
    "sg:city":"Ejido",
    "sg:orig_category":"Electrodom\u00c9sticos (al Por Menor)",
    "sg:phone":"+34 950 48 46 32",
    "sg:postcode":"04700",
    "sg:province":"Almer\u00eda",
    "wof:name":"Liria Cruz Clemente",
    "wof:placetype":"venue"
},
  "geometry": {"coordinates":[-2.8150599003,36.779045105],"type":"Point"}
}