{
  "type": "Feature",
  "properties": {
    "iso:country":"ES",
    "sg:address":"Pase Constitucion (de La), 20",
    "sg:city":"Aguilas",
    "sg:orig_category":"Arquitectos",
    "sg:phone":"+34 968 41 20 21",
    "sg:postcode":"30880",
    "sg:province":"Murcia",
    "wof:name":"Iba\u00f1ez Escarabajal Pedro",
    "wof:placetype":"venue"
},
  "geometry": {"coordinates":[-1.5839740038,37.4077987671],"type":"Point"}
}