{
  "type": "Feature",
  "properties": {
    "addr:full":"Calle de Peru, 12 Coslada Madrid 28820",
    "addr:housenumber":"12",
    "addr:postcode":"28820",
    "addr:street":"Calle De Peru",
    "iso:country":"ES",
    "sg:address":"Calle de Peru, 12",
    "sg:city":"Coslada",
    "sg:orig_category":"Peluquer\u00cdas, Peluquer\u00cda Mixta",
    "sg:phone":"+34 916 73 75 41",
    "sg:postcode":"28820",
    "sg:province":"Madrid",
    "wof:name":"Gonzalez Sanchez Arevalo Carolina",
    "wof:placetype":"venue"
},
  "geometry": {"coordinates":[-3.5446500778,40.4285392761],"type":"Point"}
}