{
  "type": "Feature",
  "properties": {
    "addr:full":"Av Doctor Joaquim Danes, 5 Olot Girona 17800",
    "addr:housenumber":"5",
    "addr:postcode":"17800",
    "addr:street":"Av Doctor Joaquim Danes",
    "iso:country":"ES",
    "sg:address":"Av Doctor Joaquim Danes, 5",
    "sg:city":"Olot",
    "sg:orig_category":"Promotores Constructores",
    "sg:phone":"+34 972 26 08 16",
    "sg:postcode":"17800",
    "sg:province":"Girona",
    "wof:name":"Comunitat Propietaris Doctor Danes 5",
    "wof:placetype":"venue"
},
  "geometry": {"coordinates":[2.4813320637,42.1824493408],"type":"Point"}
}