{
  "type": "Feature",
  "properties": {
    "addr:full":"Cmno Almonacid, S/n Alpartir Zaragoza 50109",
    "addr:housenumber":"s / n",
    "addr:postcode":"50109",
    "addr:street":"Cmno Almonacid",
    "iso:country":"ES",
    "sg:address":"Cmno Almonacid, S/n",
    "sg:city":"Alpartir",
    "sg:orig_category":"Doctores En Medicina",
    "sg:phone":"+34 976 81 32 52",
    "sg:postcode":"50109",
    "sg:province":"Zaragoza",
    "wof:name":"Catalan Rabinal Jesus",
    "wof:placetype":"venue"
},
  "geometry": {"coordinates":[-1.3803219795,41.4254951477],"type":"Point"}
}