{
  "type": "Feature",
  "properties": {
    "iso:country":"ES",
    "sg:address":"Carrer de Trinquet, 16",
    "sg:city":"Barcelona",
    "sg:orig_category":"Asesor\u00cda Sobre Comunicaci\u00d3n De Empresas",
    "sg:phone":"+34 932 03 41 51",
    "sg:postcode":"08034",
    "sg:province":"Barcelona",
    "wof:name":"Santass 2010 S.l.",
    "wof:placetype":"venue"
},
  "geometry": {"coordinates":[2.1209249496,41.3958435059],"type":"Point"}
}