{
  "type": "Feature",
  "properties": {
    "iso:country":"ES",
    "sg:address":"Avda Juan Ramon Jimenez, S/n",
    "sg:city":"Calasparra",
    "sg:orig_category":"Inmobiliaria (agencias)",
    "sg:phone":"+34 968 72 07 45",
    "sg:postcode":"30420",
    "sg:province":"Murcia",
    "wof:name":"Risue\u00f1o Moya Francisco",
    "wof:placetype":"venue"
},
  "geometry": {"coordinates":[-1.7092839479,38.2252960205],"type":"Point"}
}