{
  "type": "Feature",
  "properties": {
    "addr:full":"Calle de Preciados, 38 Madrid Madrid 28013",
    "addr:housenumber":"38",
    "addr:postcode":"madrid;28013",
    "addr:street":"Calle De Preciados",
    "iso:country":"ES",
    "sg:address":"Calle de Preciados, 38",
    "sg:city":"Madrid",
    "sg:orig_category":"Cervecer\u00cdas",
    "sg:phone":"+34 915 31 77 27",
    "sg:postcode":"28013",
    "sg:province":"Madrid",
    "wof:name":"Rodeiro Monteiro S.l.",
    "wof:placetype":"venue"
},
  "geometry": {"coordinates":[-3.7068109512,40.4198493958],"type":"Point"}
}