{
  "type": "Feature",
  "properties": {
    "addr:full":"Calle de Galileo, 53 Madrid Madrid 28015",
    "addr:housenumber":"53",
    "addr:postcode":"madrid;28015",
    "addr:street":"Calle De Galileo",
    "iso:country":"ES",
    "sg:address":"Calle de Galileo, 53",
    "sg:city":"Madrid",
    "sg:orig_category":"Electricidad Veh\u00cdculo",
    "sg:phone":"+34 915 49 14 70",
    "sg:postcode":"28015",
    "sg:province":"Madrid",
    "wof:name":"Garcia Olias Nieto Feliciano",
    "wof:placetype":"venue"
},
  "geometry": {"coordinates":[-3.7103610039,40.4353904724],"type":"Point"}
}