{
  "type": "Feature",
  "properties": {
    "addr:full":"Carr Joaquim Sorolla, 33 Centre Urba Girona 17500",
    "addr:housenumber":"33",
    "addr:postcode":"17500",
    "addr:street":"Carr Joaquim Sorolla;Centre Urba",
    "iso:country":"ES",
    "sg:address":"Carr Joaquim Sorolla, 33",
    "sg:city":"Centre Urba",
    "sg:orig_category":"Distribuci\u00d3n De Petr\u00d3leo Y Derivados",
    "sg:phone":"+34 972 71 44 33",
    "sg:postcode":"17500",
    "sg:province":"Girona",
    "wof:name":"Societat Catalana De Petrolis S.a.",
    "wof:placetype":"venue"
},
  "geometry": {"coordinates":[2.1959049702,42.1965866089],"type":"Point"}
}