{
  "type": "Feature",
  "properties": {
    "addr:full":"Rond De La Plazuela, 6 Rozas De Madrid Madrid 28230",
    "addr:housenumber":"6",
    "addr:postcode":"28230",
    "addr:street":"Rond De La Plazuela",
    "iso:country":"ES",
    "sg:address":"Rond De La Plazuela, 6",
    "sg:city":"Rozas De Madrid",
    "sg:orig_category":"Compraventa De Antig\u00dcedades",
    "sg:phone":"+34 916 37 40 43",
    "sg:postcode":"28230",
    "sg:province":"Madrid",
    "wof:name":"Lopez Zorrilla Ricardo",
    "wof:placetype":"venue"
},
  "geometry": {"coordinates":[-3.8913800716,40.5247497559],"type":"Point"}
}