{
  "type": "Feature",
  "properties": {
    "iso:country":"ES",
    "sg:address":"Calle de Narciso Gonzalez Cervera, 1",
    "sg:city":"Motril",
    "sg:orig_category":"Asesor\u00cdas Y Estudios Financieros",
    "sg:phone":"+34 958 60 47 23",
    "sg:postcode":"18600",
    "sg:province":"Granada",
    "wof:name":"Valladares Ruiz Juan Miguel",
    "wof:placetype":"venue"
},
  "geometry": {"coordinates":[-3.5180943012,36.7437019348],"type":"Point"}
}