{
  "type": "Feature",
  "properties": {
    "iso:country":"ES",
    "sg:address":"Cust Caidero (del), 7",
    "sg:city":"Granada",
    "sg:orig_category":"M\u00c9dicos: Cirug\u00cda Urol\u00d3gica",
    "sg:phone":"+34 958 22 69 36",
    "sg:postcode":"18009",
    "sg:province":"Granada",
    "wof:name":"Mariscal Megias Miguel",
    "wof:placetype":"venue"
},
  "geometry": {"coordinates":[-3.589247942,37.1699905396],"type":"Point"}
}