{
  "type": "Feature",
  "properties": {
    "addr:full":"Calle de Claudio Coello, 88 Madrid Madrid 28006",
    "addr:housenumber":"88",
    "addr:postcode":"madrid;28006",
    "addr:street":"Calle De Claudio Coello",
    "iso:country":"ES",
    "sg:address":"Calle de Claudio Coello, 88",
    "sg:city":"Madrid",
    "sg:orig_category":"Arquitectos",
    "sg:phone":"+34 915 77 13 77",
    "sg:postcode":"28006",
    "sg:province":"Madrid",
    "wof:name":"Javier Fuster Arquitectos S.l.",
    "wof:placetype":"venue"
},
  "geometry": {"coordinates":[-3.6857280731,40.4312705994],"type":"Point"}
}