{
  "type": "Feature",
  "properties": {
    "iso:country":"ES",
    "sg:address":"Avda Libertad, 6",
    "sg:city":"San Miguel",
    "sg:orig_category":"Iglesia Cat\u00d3lica",
    "sg:phone":"+34 968 23 92 86",
    "sg:postcode":"30009",
    "sg:province":"Murcia",
    "wof:name":"Obispado De Cartagena",
    "wof:placetype":"venue"
},
  "geometry": {"coordinates":[-1.1334389448,37.9899215698],"type":"Point"}
}