{
  "type": "Feature",
  "properties": {
    "addr:full":"Calle de Valencia, 23 Sagunt Valencia 46500",
    "addr:housenumber":"23",
    "addr:postcode":"46500",
    "addr:street":"Calle De Valencia",
    "iso:country":"ES",
    "sg:address":"Calle de Valencia, 23",
    "sg:city":"Sagunt",
    "sg:orig_category":"M\u00c9dicos: Radiolog\u00cda (radiodiagn\u00d3stico E Im\u00c1genes En Medicina)",
    "sg:phone":"+34 962 66 08 78",
    "sg:postcode":"46500",
    "sg:province":"Valencia",
    "wof:name":"Sancho Blesa Gonzalo",
    "wof:placetype":"venue"
},
  "geometry": {"coordinates":[-0.2727569938,39.6766586304],"type":"Point"}
}