{
  "type": "Feature",
  "properties": {
    "iso:country":"ES",
    "sg:address":"Calle de Nuestra Se\u00d1ora Del Aguila, 61",
    "sg:city":"Alcala Guadaira",
    "sg:orig_category":"Asesor\u00cda Sobre Comunicaci\u00d3n De Empresas",
    "sg:phone":"+34 955 68 59 28",
    "sg:postcode":"41500",
    "sg:province":"Sevilla",
    "wof:name":"First Jf Asesores S.l.",
    "wof:placetype":"venue"
},
  "geometry": {"coordinates":[-5.848274231,37.3346176147],"type":"Point"}
}