{
  "type": "Feature",
  "properties": {
    "addr:full":"Av. J. Antonio, 28 Huete Cuenca 16500",
    "addr:housenumber":"28",
    "addr:postcode":"16500",
    "addr:street":"Av. J. Antonio",
    "iso:country":"ES",
    "sg:address":"Av. J. Antonio, 28",
    "sg:city":"Huete",
    "sg:orig_category":"Promotores Constructores",
    "sg:phone":"+34 969 37 14 74",
    "sg:postcode":"16500",
    "sg:province":"Cuenca",
    "wof:name":"Prolomar 2000 S.l.",
    "wof:placetype":"venue"
},
  "geometry": {"coordinates":[-2.6883060932,40.1424255371],"type":"Point"}
}