{
  "type": "Feature",
  "properties": {
    "addr:full":"Calle de Camino Viejo De Leganes, 281 Madrid Madrid 28025",
    "addr:housenumber":"281",
    "addr:postcode":"28025",
    "addr:street":"Calle De Camino Viejo De Leganes",
    "iso:country":"ES",
    "sg:address":"Calle de Camino Viejo De Leganes, 281",
    "sg:city":"Madrid",
    "sg:orig_category":"Bazares, Art\u00cdculos De Limpieza Y De Cocina (al Por Menor)",
    "sg:phone":"+34 914 69 49 42",
    "sg:postcode":"28025",
    "sg:province":"Madrid",
    "wof:name":"Ye  Liang",
    "wof:placetype":"venue"
},
  "geometry": {"coordinates":[-3.7324419022,40.3792877197],"type":"Point"}
}