{
  "type": "Feature",
  "properties": {
    "iso:country":"ES",
    "sg:address":"Calle de Comadres (las), S/n",
    "sg:city":"Madrona",
    "sg:orig_category":"Contenedores (mercanc\u00cdas)",
    "sg:phone":"+34 921 48 50 76",
    "sg:postcode":"40154",
    "sg:province":"Segovia",
    "wof:name":"Sonlleva Fuentes Celio",
    "wof:placetype":"venue"
},
  "geometry": {"coordinates":[-4.1706457138,40.8975448608],"type":"Point"}
}