{
  "type": "Feature",
  "properties": {
    "addr:full":"Calle de Isaac Peral, 37 Chipiona C\u00e1diz 11550",
    "addr:housenumber":"37",
    "addr:postcode":"11550",
    "addr:street":"Calle De Isaac Peral",
    "iso:country":"ES",
    "sg:address":"Calle de Isaac Peral, 37",
    "sg:city":"Chipiona",
    "sg:orig_category":"Camiser\u00cda Y Ropa Interior Masculina (al Por Menor)",
    "sg:phone":"+34 956 37 27 29",
    "sg:postcode":"11550",
    "sg:province":"C\u00e1diz",
    "wof:name":"Andres Valverde S.c.",
    "wof:placetype":"venue"
},
  "geometry": {"coordinates":[-6.4356837273,36.7393264771],"type":"Point"}
}