{
  "type": "Feature",
  "properties": {
    "addr:full":"Calle de Constancia, 43 Malaga M\u00e1laga 29002",
    "addr:housenumber":"43",
    "addr:postcode":"29002",
    "addr:street":"Calle De Constancia;Ma\u0301Laga",
    "iso:country":"ES",
    "sg:address":"Calle de Constancia, 43",
    "sg:city":"Malaga",
    "sg:orig_category":"Perfumer\u00cda Y Cosm\u00c9tica (fabricaci\u00d3n, Al Por Mayor)",
    "sg:phone":"+34 952 33 22 77",
    "sg:postcode":"29002",
    "sg:province":"M\u00e1laga",
    "wof:name":"J M Conde S.l.",
    "wof:placetype":"venue"
},
  "geometry": {"coordinates":[-4.4283943176,36.7115821838],"type":"Point"}
}