{
  "type": "Feature",
  "properties": {
    "iso:country":"ES",
    "sg:address":"Av Can Serra, 105",
    "sg:city":"Hospitalet Llobregat",
    "sg:orig_category":"Internados & Ense\u00d1anza Privada",
    "sg:phone":"+34 934 38 61 04",
    "sg:postcode":"08906",
    "sg:province":"Barcelona",
    "wof:name":"Centro Educativo Fax",
    "wof:placetype":"venue"
},
  "geometry": {"coordinates":[2.1026740074,41.3670425415],"type":"Point"}
}