{
  "type": "Feature",
  "properties": {
    "iso:country":"ES",
    "sg:address":"C/ Diagonal, 3",
    "sg:city":"Elche",
    "sg:orig_category":"Talleres: Ropa A Medida",
    "sg:phone":"+34 965 46 23 46",
    "sg:postcode":"03206",
    "sg:province":"Alicante",
    "wof:name":"Roman Morales Jose",
    "wof:placetype":"venue"
},
  "geometry": {"coordinates":[-0.7046099901,38.2708625793],"type":"Point"}
}