{
  "type": "Feature",
  "properties": {
    "iso:country":"ES",
    "sg:address":"Calle de Goya, 83",
    "sg:city":"Madrid",
    "sg:orig_category":"Ropa Para Ni\u00d1os (al Por Menor)",
    "sg:phone":"+34 914 35 39 58",
    "sg:postcode":"28001",
    "sg:province":"Madrid",
    "sg:website":"www.mango.es",
    "wof:name":"Punto Fa S.l.",
    "wof:placetype":"venue"
},
  "geometry": {"coordinates":[-3.6776840687,40.4250144958],"type":"Point"}
}