{
  "type": "Feature",
  "properties": {
    "addr:full":"Calle de Ciudad De Manises, S/n Sevilla Sevilla 41020",
    "addr:housenumber":"s / n",
    "addr:postcode":"41020",
    "addr:street":"Calle De Ciudad De Manises",
    "iso:country":"ES",
    "sg:address":"Calle de Ciudad De Manises, S/n",
    "sg:city":"Sevilla",
    "sg:classifiers":[
        {
            "category":"Banks & Credit Unions",
            "subcategory":"Bureau De Change",
            "type":"Services"
        }
    ],
    "sg:phone":"+34 954 52 05 53",
    "sg:postcode":"41020",
    "sg:province":"Sevilla",
    "sg:tags":[
        "organismos",
        "control"
    ],
    "wof:name":"Centro De Estudios De Materiales Y Control De Obra S.a.",
    "wof:placetype":"venue"
},
  "geometry": {"coordinates":[-5.9317183495,37.4111404419],"type":"Point"}
}