{
  "type": "Feature",
  "properties": {
    "addr:full":"Ctra Rojales, S/n Daya Vieja Alicante 03177",
    "addr:housenumber":"s / n",
    "addr:postcode":"03177",
    "addr:street":"Ctra Rojales",
    "iso:country":"ES",
    "sg:address":"Ctra Rojales, S/n",
    "sg:city":"Daya Vieja",
    "sg:orig_category":"Promotores Constructores",
    "sg:phone":"+34 966 71 27 51",
    "sg:postcode":"03177",
    "sg:province":"Alicante",
    "wof:name":"Residencial Vista Alegre S.a.",
    "wof:placetype":"venue"
},
  "geometry": {"coordinates":[-0.6843640208,38.1279182434],"type":"Point"}
}