{
  "type": "Feature",
  "properties": {
    "addr:full":"Calle de Garcia Carrera, 5 Cadiz C\u00e1diz 11009",
    "addr:postcode":"11009",
    "addr:street":"Calle De Garcia Carrera 5;Ca\u0301Diz",
    "iso:country":"ES",
    "sg:address":"Calle de Garcia Carrera, 5",
    "sg:city":"Cadiz",
    "sg:orig_category":"Laboratorios Y Trabajos De Fotograf\u00cda, V\u00cddeo Y Cine",
    "sg:phone":"+34 956 26 48 11",
    "sg:postcode":"11009",
    "sg:province":"C\u00e1diz",
    "wof:name":"Garcia Bernal Ana",
    "wof:placetype":"venue"
},
  "geometry": {"coordinates":[-6.2780880928,36.5138206482],"type":"Point"}
}