{
  "type": "Feature",
  "properties": {
    "addr:full":"Carrer de Calabria, 171 Barcelona Barcelona 08015",
    "addr:housenumber":"171",
    "addr:postcode":"08015",
    "addr:street":"Carrer De Calabria",
    "iso:country":"ES",
    "sg:address":"Carrer de Calabria, 171",
    "sg:city":"Barcelona",
    "sg:orig_category":"Fabricaci\u00d3n De Motores El\u00c9ctricos",
    "sg:phone":"+34 932 26 67 70",
    "sg:postcode":"08015",
    "sg:province":"Barcelona",
    "sg:website":"www.kelvin.es",
    "wof:name":"Kelvin S.a.",
    "wof:placetype":"venue"
},
  "geometry": {"coordinates":[2.1509840488,41.38256073],"type":"Point"}
}