{
  "type": "Feature",
  "properties": {
    "addr:full":"La Farola, 8 Sta.ursula Santa Cruz De Tenerife 38390",
    "addr:housenumber":"8",
    "addr:postcode":"38390",
    "addr:street":"Farola",
    "iso:country":"ES",
    "sg:address":"La Farola, 8",
    "sg:city":"Sta.ursula",
    "sg:orig_category":"Fisioterapia",
    "sg:phone":"+34 922 33 78 70",
    "sg:postcode":"38390",
    "sg:province":"Santa Cruz De Tenerife",
    "wof:name":"Toste Gonzalez Ana Maria",
    "wof:placetype":"venue"
},
  "geometry": {"coordinates":[-16.4859371185,28.4294376373],"type":"Point"}
}