{
  "type": "Feature",
  "properties": {
    "iso:country":"ES",
    "sg:address":"Calle de Drago, S/n",
    "sg:city":"S. Fernando",
    "sg:orig_category":"Papeler\u00cdas, Librer\u00cdas",
    "sg:phone":"+34 956 59 56 58",
    "sg:postcode":"11100",
    "sg:province":"C\u00e1diz",
    "wof:name":"Butron Verdugo Juan",
    "wof:placetype":"venue"
},
  "geometry": {"coordinates":[-6.2009239197,36.469833374],"type":"Point"}
}