{
  "type": "Feature",
  "properties": {
    "addr:full":"A Igrexa, S/n Breto\u00f1a Lugo 27286",
    "addr:housenumber":"s / n",
    "addr:postcode":"27286",
    "addr:street":"A Igrexa",
    "iso:country":"ES",
    "sg:address":"A Igrexa, S/n",
    "sg:city":"Breto\u00f1a",
    "sg:orig_category":"Transportes De Autom\u00d3viles Y Otros Veh\u00cdculos",
    "sg:phone":"+34 982 34 90 98",
    "sg:postcode":"27286",
    "sg:province":"Lugo",
    "wof:name":"Vila Comendeiro Josefa",
    "wof:placetype":"venue"
},
  "geometry": {"coordinates":[-7.3240408897,43.3316688538],"type":"Point"}
}