{
  "type": "Feature",
  "properties": {
    "iso:country":"ES",
    "sg:address":"Calle de Conde De Salvatierra, 22",
    "sg:city":"Valencia",
    "sg:classifiers":[
        {
            "category":"Shopping",
            "subcategory":"Clothing, Apparel, & Fashions",
            "type":"Retail Goods"
        }
    ],
    "sg:phone":"+34 963 52 45 69",
    "sg:postcode":"46004",
    "sg:province":"Valencia",
    "sg:tags":[
        "boutique"
    ],
    "wof:name":"Cristina Correa S.l.",
    "wof:placetype":"venue"
},
  "geometry": {"coordinates":[-0.3680782914,39.4694976807],"type":"Point"}
}