{
  "type": "Feature",
  "properties": {
    "iso:country":"ES",
    "sg:address":"Avda Madrid, 210",
    "sg:city":"Mantelas",
    "sg:orig_category":"Agentes, Concesionarios Y Sucursales De Veh\u00cdculos",
    "sg:phone":"+34 986 26 56 10",
    "sg:postcode":"36318",
    "sg:province":"Pontevedra",
    "wof:name":"Gabisa Automocion S.l.",
    "wof:placetype":"venue"
},
  "geometry": {"coordinates":[-8.6480531693,42.4336204529],"type":"Point"}
}