{
  "type": "Feature",
  "properties": {
    "iso:country":"ES",
    "sg:address":"Calle de Salvador Dali (de), 31",
    "sg:city":"Mejorada Campo",
    "sg:orig_category":"Quincaller\u00cda (al Por Menor)",
    "sg:phone":"+34 916 68 00 54",
    "sg:postcode":"28840",
    "sg:province":"Madrid",
    "wof:name":"Herrero Lopez Pedro",
    "wof:placetype":"venue"
},
  "geometry": {"coordinates":[-3.4838440418,40.3967437744],"type":"Point"}
}