{
  "type": "Feature",
  "properties": {
    "iso:country":"ES",
    "sg:address":"Av Madrid, 102",
    "sg:city":"Barcelona",
    "sg:orig_category":"Inform\u00c1tica: Material Y Suministros",
    "sg:phone":"+34 934 09 79 10",
    "sg:postcode":"08028",
    "sg:province":"Barcelona",
    "wof:name":"Comercial De Software Y De Integracion Telefonica S.a.",
    "wof:placetype":"venue"
},
  "geometry": {"coordinates":[2.1280078888,41.3786201477],"type":"Point"}
}