{
  "type": "Feature",
  "properties": {
    "addr:full":"Calle de Jaime I, 8 Fraga Huesca 22520",
    "addr:housenumber":"8",
    "addr:postcode":"22520",
    "addr:street":"Calle De Jaime I",
    "iso:country":"ES",
    "sg:address":"Calle de Jaime I, 8",
    "sg:city":"Fraga",
    "sg:orig_category":"Promotores Constructores",
    "sg:phone":"+34 974 47 01 62",
    "sg:postcode":"22520",
    "sg:province":"Huesca",
    "wof:name":"Promociones Cortibarz S.l",
    "wof:placetype":"venue"
},
  "geometry": {"coordinates":[0.3379679918,41.5236320496],"type":"Point"}
}