{
  "type": "Feature",
  "properties": {
    "addr:full":"Cno. Sierra, 12 Alquian Almer\u00eda 04130",
    "addr:housenumber":"12",
    "addr:postcode":"04130",
    "addr:street":"Cno. Sierra;Almeri\u0301A",
    "iso:country":"ES",
    "sg:address":"Cno. Sierra, 12",
    "sg:city":"Alquian",
    "sg:orig_category":"Danza, Cursos, Asociaciones Y M\u00dasicos",
    "sg:phone":"+34 950 29 72 04",
    "sg:postcode":"04130",
    "sg:province":"Almer\u00eda",
    "wof:name":"Cervantes Lopez Manuel",
    "wof:placetype":"venue"
},
  "geometry": {"coordinates":[-2.3529150486,36.8523406982],"type":"Point"}
}