{
  "type": "Feature",
  "properties": {
    "addr:full":"Carrer de Roger De Flor, 178 Barcelona Barcelona 08013",
    "addr:housenumber":"178",
    "addr:postcode":"08013",
    "addr:street":"Carrer De Roger De Flor",
    "iso:country":"ES",
    "sg:address":"Carrer de Roger De Flor, 178",
    "sg:city":"Barcelona",
    "sg:orig_category":"Periodistas Profesionales",
    "sg:phone":"+34 932 31 82 09",
    "sg:postcode":"08013",
    "sg:province":"Barcelona",
    "wof:name":"Plaja Mateu Antonio",
    "wof:placetype":"venue"
},
  "geometry": {"coordinates":[2.1736900806,41.3981666565],"type":"Point"}
}