{
  "type": "Feature",
  "properties": {
    "addr:full":"Calle de Jose Manuel Fernandez Santiago, 2 Mombeltran \u00c1vila 05410",
    "addr:housenumber":"2",
    "addr:postcode":"05410",
    "addr:street":"Calle De Jose Manuel Fernandez Santiago;A\u0301Vila",
    "iso:country":"ES",
    "sg:address":"Calle de Jose Manuel Fernandez Santiago, 2",
    "sg:city":"Mombeltran",
    "sg:orig_category":"Asilos De Ancianos. Centros Privados",
    "sg:phone":"+34 920 38 65 33",
    "sg:postcode":"05410",
    "sg:province":"\u00c1vila",
    "wof:name":"Agrupacion De Centros Para Mayores S. L.",
    "wof:placetype":"venue"
},
  "geometry": {"coordinates":[-5.016055584,40.2587051392],"type":"Point"}
}