{
  "type": "Feature",
  "properties": {
    "addr:full":"Avda Alemania De, 24 Aviles Asturias 33401",
    "addr:housenumber":"24",
    "addr:postcode":"33401",
    "addr:street":"Avda Alemania De",
    "iso:country":"ES",
    "sg:address":"Avda Alemania De, 24",
    "sg:city":"Aviles",
    "sg:orig_category":"Mutuas De Seguros",
    "sg:phone":"+34 985 56 00 93",
    "sg:postcode":"33401",
    "sg:province":"Asturias",
    "wof:name":"Ibermutuamur",
    "wof:placetype":"venue"
},
  "geometry": {"coordinates":[-5.9278864861,43.5617752075],"type":"Point"}
}