{
  "type": "Feature",
  "properties": {
    "addr:full":"Carr Francesc Artau, 1 Girona Girona 17005",
    "addr:housenumber":"1",
    "addr:postcode":"17005",
    "addr:street":"Carr Francesc Artau",
    "iso:country":"ES",
    "sg:address":"Carr Francesc Artau, 1",
    "sg:city":"Girona",
    "sg:orig_category":"Empresas De Vigilancia, Guardia Y Protecci\u00d3n",
    "sg:phone":"+34 972 24 08 82",
    "sg:postcode":"17005",
    "sg:province":"Girona",
    "sg:website":"www.prosegur.es",
    "wof:name":"Prosegur Transports I Vigilancia",
    "wof:placetype":"venue"
},
  "geometry": {"coordinates":[2.8130710125,41.9787521362],"type":"Point"}
}