{
  "type": "Feature",
  "properties": {
    "addr:full":"Calle de Queipo De Llano, 25 Ubrique C\u00e1diz 11600",
    "addr:housenumber":"25",
    "addr:postcode":"11600",
    "addr:street":"Calle De Queipo De Llano;Ca\u0301Diz",
    "iso:country":"ES",
    "sg:address":"Calle de Queipo De Llano, 25",
    "sg:city":"Ubrique",
    "sg:orig_category":"Marroquiner\u00cda (confecci\u00d3n)",
    "sg:phone":"+34 956 46 26 28",
    "sg:postcode":"11600",
    "sg:province":"C\u00e1diz",
    "wof:name":"Ramos Villalobos S.l.",
    "wof:placetype":"venue"
},
  "geometry": {"coordinates":[-5.4475698471,36.6776618958],"type":"Point"}
}