{
  "type": "Feature",
  "properties": {
    "addr:full":"Calle de Cirilo Moreno, 42 Palmas De Gran Canaria Las Palmas 35007",
    "addr:postcode":"35007",
    "addr:street":"Calle De Cirilo Moreno 42",
    "iso:country":"ES",
    "sg:address":"Calle de Cirilo Moreno, 42",
    "sg:city":"Palmas De Gran Canaria",
    "sg:orig_category":"Centros Empresariales",
    "sg:phone":"+34 928 26 01 74",
    "sg:postcode":"35007",
    "sg:province":"Las Palmas",
    "wof:name":"Padron Alamo Tomas",
    "wof:placetype":"venue"
},
  "geometry": {"coordinates":[-15.4324226379,28.1367950439],"type":"Point"}
}