{
  "type": "Feature",
  "properties": {
    "addr:full":"Calle de Do\u00d1a Sol, 12 Carde\u00f1ajimeno Burgos 09193",
    "addr:housenumber":"12",
    "addr:postcode":"09193",
    "addr:street":"Calle De Don\u0303A Sol",
    "iso:country":"ES",
    "sg:address":"Calle de Do\u00d1a Sol, 12",
    "sg:city":"Carde\u00f1ajimeno",
    "sg:orig_category":"Agencias Y Agentes Comerciales, Representantes",
    "sg:phone":"+34 947 29 06 00",
    "sg:postcode":"09193",
    "sg:province":"Burgos",
    "wof:name":"Gayobar S.l",
    "wof:placetype":"venue"
},
  "geometry": {"coordinates":[-3.6187267303,42.3317070007],"type":"Point"}
}