{
  "type": "Feature",
  "properties": {
    "iso:country":"ES",
    "sg:address":"Avda Dos De Mayo (del), 37",
    "sg:city":"Mostoles",
    "sg:orig_category":"Frutas, Legumbres Frescas Y Tempranas (al Por Menor)",
    "sg:phone":"+34 916 13 60 41",
    "sg:postcode":"28934",
    "sg:province":"Madrid",
    "wof:name":"Gutierrez Exposito Ubaldo Jose",
    "wof:placetype":"venue"
},
  "geometry": {"coordinates":[-3.8713130951,40.3199729919],"type":"Point"}
}