{
  "type": "Feature",
  "properties": {
    "addr:full":"Pase Ronda, 1 Padilla De Abajo Burgos 09109",
    "addr:housenumber":"1",
    "addr:postcode":"09109",
    "addr:street":"Ronda",
    "iso:country":"ES",
    "sg:address":"Pase Ronda, 1",
    "sg:city":"Padilla De Abajo",
    "sg:orig_category":"Delegados, Agentes De Tr\u00c1nsito, Auxiliares De Transporte Internacional",
    "sg:phone":"+34 947 37 21 86",
    "sg:postcode":"09109",
    "sg:province":"Burgos",
    "wof:name":"Velasco Santamaria Angel",
    "wof:placetype":"venue"
},
  "geometry": {"coordinates":[-4.1790242195,42.4058685303],"type":"Point"}
}