{
  "type": "Feature",
  "properties": {
    "addr:full":"Calle de Hesperides, S/n Sevilla Sevilla 41008",
    "addr:housenumber":"s / n",
    "addr:postcode":"41008",
    "addr:street":"Calle De Hesperides",
    "iso:country":"ES",
    "sg:address":"Calle de Hesperides, S/n",
    "sg:city":"Sevilla",
    "sg:orig_category":"Agencias De Viajes",
    "sg:phone":"+34 954 35 08 69",
    "sg:postcode":"41008",
    "sg:province":"Sevilla",
    "sg:website":"www.grecomarviajes.com",
    "wof:name":"Grecomar Viajes S.l.",
    "wof:placetype":"venue"
},
  "geometry": {"coordinates":[-5.9683737755,37.3994293213],"type":"Point"}
}