{
  "type": "Feature",
  "properties": {
    "iso:country":"ES",
    "sg:address":"Av Llibertat, 114",
    "sg:city":"Elche",
    "sg:orig_category":"Farmacias",
    "sg:phone":"+34 965 46 17 22",
    "sg:postcode":"03205",
    "sg:province":"Alicante",
    "wof:name":"Serrano Ripoll Jose",
    "wof:placetype":"venue"
},
  "geometry": {"coordinates":[-0.710259974,38.2669754028],"type":"Point"}
}