{
  "type": "Feature",
  "properties": {
    "addr:full":"Carrer de Montblanc (de), 19 Torreforta Tarragona 43006",
    "addr:housenumber":"19",
    "addr:postcode":"43006",
    "addr:street":"Carrer De Montblanc De",
    "iso:country":"ES",
    "sg:address":"Carrer de Montblanc (de), 19",
    "sg:city":"Torreforta",
    "sg:orig_category":"Relojer\u00cda (al Por Menor, Reparaci\u00d3n)",
    "sg:phone":"+34 977 54 93 31",
    "sg:postcode":"43006",
    "sg:province":"Tarragona",
    "wof:name":"Lopez Abad Juan Jose",
    "wof:placetype":"venue"
},
  "geometry": {"coordinates":[1.2183049917,41.1176719666],"type":"Point"}
}