{
  "type": "Feature",
  "properties": {
    "iso:country":"ES",
    "sg:address":"Calle de Txofre, 11",
    "sg:city":"Donostia-san Sebastian",
    "sg:classifiers":[
        {
            "category":"Autos & Motor Vehicles",
            "subcategory":"Automobile Sales",
            "type":"Retail Goods"
        }
    ],
    "sg:phone":"+34 943 27 55 85",
    "sg:postcode":"20001",
    "sg:province":"Guip\u00f9zcoa",
    "wof:name":"Gidari Heziketa S.l.",
    "wof:placetype":"venue"
},
  "geometry": {"coordinates":[-1.9717229605,43.3236579895],"type":"Point"}
}