{
  "type": "Feature",
  "properties": {
    "iso:country":"ES",
    "sg:address":"Ptge Passatge Can Politic, 17",
    "sg:city":"Hospitalet Llobregat",
    "sg:orig_category":"Confecci\u00d3n De Corbatas",
    "sg:phone":"+34 935 11 37 67",
    "sg:postcode":"08907",
    "sg:province":"Barcelona",
    "sg:website":"www.ledoalberti.com",
    "wof:name":"Rodriguez Y Ponte S.a.",
    "wof:placetype":"venue"
},
  "geometry": {"coordinates":[2.1700499058,41.3857192993],"type":"Point"}
}