{
  "type": "Feature",
  "properties": {
    "addr:full":"Calle de Asalto, 25 Zaragoza Zaragoza 50002",
    "addr:housenumber":"25",
    "addr:postcode":"50002",
    "addr:street":"Calle De Asalto",
    "iso:country":"ES",
    "sg:address":"Calle de Asalto, 25",
    "sg:city":"Zaragoza",
    "sg:orig_category":"Promotores Constructores",
    "sg:phone":"+34 976 20 33 84",
    "sg:postcode":"50002",
    "sg:province":"Zaragoza",
    "wof:name":"Instalaciones Aragonesas De Ladryeso S.l.",
    "wof:placetype":"venue"
},
  "geometry": {"coordinates":[-0.8748245835,41.6492042542],"type":"Point"}
}