{
  "type": "Feature",
  "properties": {
    "addr:full":"Calle de Nuestra Se\u00d1ora De Ujue, 3 Santacara Navarra 31314",
    "addr:housenumber":"3",
    "addr:postcode":"31314",
    "addr:street":"Calle De Nuestra Sen\u0303Ora De Ujue",
    "iso:country":"ES",
    "sg:address":"Calle de Nuestra Se\u00d1ora De Ujue, 3",
    "sg:city":"Santacara",
    "sg:orig_category":"Centros De Coordinaci\u00d3n",
    "sg:phone":"+34 948 74 66 39",
    "sg:postcode":"31314",
    "sg:province":"Navarra",
    "wof:name":"Bergasa Asura Jose Manuel",
    "wof:placetype":"venue"
},
  "geometry": {"coordinates":[-1.5514730215,42.3753433228],"type":"Point"}
}