{
  "type": "Feature",
  "properties": {
    "iso:country":"ES",
    "sg:address":"Carrer de Sant Sebastia, 210",
    "sg:city":"Terrassa",
    "sg:orig_category":"Calderer\u00cda",
    "sg:phone":"+34 937 85 74 87",
    "sg:postcode":"08223",
    "sg:province":"Barcelona",
    "wof:name":"Caldereria Ramirez S. A.",
    "wof:placetype":"venue"
},
  "geometry": {"coordinates":[2.0085439682,41.5547447205],"type":"Point"}
}