{
  "type": "Feature",
  "properties": {
    "addr:full":"Txonta Kalea, 20 Eibar Guip\u00f9zcoa 20600",
    "addr:housenumber":"20",
    "addr:postcode":"20600",
    "addr:street":"Txonta Kalea;Guipu\u0300Zcoa",
    "iso:country":"ES",
    "sg:address":"Txonta Kalea, 20",
    "sg:city":"Eibar",
    "sg:orig_category":"Explosivos",
    "sg:phone":"+34 943 20 37 59",
    "sg:postcode":"20600",
    "sg:province":"Guip\u00f9zcoa",
    "wof:name":"Barrena Bostak S L",
    "wof:placetype":"venue"
},
  "geometry": {"coordinates":[-2.4625680447,43.1845588684],"type":"Point"}
}