{
  "type": "Feature",
  "properties": {
    "addr:full":"Avda Gregorio Diego, 1 Malaga M\u00e1laga 29004",
    "addr:housenumber":"1",
    "addr:postcode":"29004",
    "addr:street":"Avda Gregorio Diego;Ma\u0301Laga",
    "iso:country":"ES",
    "sg:address":"Avda Gregorio Diego, 1",
    "sg:city":"Malaga",
    "sg:orig_category":"Fabricaci\u00d3n De Juguetes Autom\u00c1ticos",
    "sg:phone":"+34 952 17 62 71",
    "sg:postcode":"29004",
    "sg:province":"M\u00e1laga",
    "wof:name":"Egasa Xxi S.a.",
    "wof:placetype":"venue"
},
  "geometry": {"coordinates":[-4.4547529221,36.6918678284],"type":"Point"}
}