{
  "type": "Feature",
  "properties": {
    "addr:full":"Cra Sevilla-p I San Diego, Km. 0636,6 Huelva Huelva 21007",
    "addr:postcode":"21007",
    "addr:street":"Diego Km. 0636,6",
    "iso:country":"ES",
    "sg:address":"Cra Sevilla-p I San Diego, Km. 0636,6",
    "sg:city":"Huelva",
    "sg:orig_category":"Maquinaria Para Industrias Diversas",
    "sg:phone":"+34 959 27 08 17",
    "sg:postcode":"21007",
    "sg:province":"Huelva",
    "wof:name":"Cabacon S.l.",
    "wof:placetype":"venue"
},
  "geometry": {"coordinates":[-6.9495940208,37.256313324],"type":"Point"}
}