{
  "type": "Feature",
  "properties": {
    "iso:country":"ES",
    "sg:address":"Plaz Ntra Sra Del Carmen, 9",
    "sg:city":"Zaragoza",
    "sg:orig_category":"Arquitectos",
    "sg:phone":"+34 976 22 20 68",
    "sg:postcode":"50004",
    "sg:province":"Zaragoza",
    "wof:name":"Castellot Marin Santiago",
    "wof:placetype":"venue"
},
  "geometry": {"coordinates":[-0.884329021,41.6510391235],"type":"Point"}
}