{
  "type": "Feature",
  "properties": {
    "addr:full":"Plaz Rastro (del), 2 Avila \u00c1vila 05001",
    "addr:postcode":"05001",
    "addr:street":"A\u0301Vila",
    "iso:country":"ES",
    "sg:address":"Plaz Rastro (del), 2",
    "sg:city":"Avila",
    "sg:orig_category":"Centros P\u00dablicos De Formaci\u00d3n Profesional Y T\u00c9cnica",
    "sg:phone":"+34 920 21 12 81",
    "sg:postcode":"05001",
    "sg:province":"\u00c1vila",
    "wof:name":"Colegio Provincial De Abogados",
    "wof:placetype":"venue"
},
  "geometry": {"coordinates":[-4.7007927895,40.654800415],"type":"Point"}
}