{
  "type": "Feature",
  "properties": {
    "addr:full":"Calle de San Vicente Martir, 16 Valencia Valencia 46002",
    "addr:housenumber":"16",
    "addr:postcode":"46002",
    "addr:street":"Calle De San Vicente Martir",
    "iso:country":"ES",
    "sg:address":"Calle de San Vicente Martir, 16",
    "sg:city":"Valencia",
    "sg:orig_category":"Comercios E Industrias (cesi\u00d3n Y Reactivaci\u00d3n)",
    "sg:phone":"+34 963 53 36 47",
    "sg:postcode":"46002",
    "sg:province":"Valencia",
    "wof:name":"A.chapa Y E.lluna Notarios, C.b.",
    "wof:placetype":"venue"
},
  "geometry": {"coordinates":[-0.3766750991,39.4724464417],"type":"Point"}
}