{
  "type": "Feature",
  "properties": {
    "addr:full":"S. Bertomeu, S/n Massalcoreig Lleida 25184",
    "addr:housenumber":"s",
    "addr:postcode":"25184",
    "addr:street":"/ N Massalcoreig",
    "iso:country":"ES",
    "sg:address":"S. Bertomeu, S/n",
    "sg:city":"Massalcoreig",
    "sg:orig_category":"Forjas Y Altos Hornos",
    "sg:phone":"+34 973 79 36 78",
    "sg:postcode":"25184",
    "sg:province":"Lleida",
    "wof:name":"Francisco Juste Guardiola-pablo Ambrosio Juste Guardiola C.b.",
    "wof:placetype":"venue"
},
  "geometry": {"coordinates":[0.3596400023,41.4597740173],"type":"Point"}
}