{
  "type": "Feature",
  "properties": {
    "iso:country":"ES",
    "sg:address":"Plaz Constitucion (la), 7",
    "sg:city":"Albacete",
    "sg:classifiers":[
        {
            "category":"Casinos & Gambling",
            "type":"Entertainment"
        }
    ],
    "sg:phone":"+34 967 24 59 39",
    "sg:postcode":"02002",
    "sg:province":"Albacete",
    "sg:tags":[
        "locale",
        "de",
        "juego"
    ],
    "wof:name":"Stin Espa\u00f1ola S.a.",
    "wof:placetype":"venue"
},
  "geometry": {"coordinates":[-1.8540610075,38.9950675964],"type":"Point"}
}