{
  "type": "Feature",
  "properties": {
    "addr:full":"Calle de General Tamayo, 29 Almeria Almer\u00eda 04002",
    "addr:housenumber":"29",
    "addr:postcode":"04002",
    "addr:street":"Calle De General Tamayo",
    "iso:country":"ES",
    "sg:address":"Calle de General Tamayo, 29",
    "sg:city":"Almeria",
    "sg:orig_category":"Artes Gr\u00c1ficas, Artes Pl\u00c1sticas: Material Y Suministros (al Por Menor)",
    "sg:phone":"+34 950 24 63 63",
    "sg:postcode":"04002",
    "sg:province":"Almer\u00eda",
    "sg:website":"www.gesycalandaucia.com",
    "wof:name":"Gesycal Andalucia S.l.",
    "wof:placetype":"venue"
},
  "geometry": {"coordinates":[-2.4646248817,36.8368682861],"type":"Point"}
}