{
  "type": "Feature",
  "properties": {
    "addr:full":"Calle de Cultura, 7 Molina Segura Murcia 30500",
    "addr:housenumber":"7",
    "addr:postcode":"30500",
    "addr:street":"Calle De Cultura",
    "iso:country":"ES",
    "sg:address":"Calle de Cultura, 7",
    "sg:city":"Molina Segura",
    "sg:orig_category":"Carnicer\u00cdas, Carnicer\u00cdas",
    "sg:phone":"+34 968 61 04 70",
    "sg:postcode":"30500",
    "sg:province":"Murcia",
    "wof:name":"Ruiz Dolera Jesus",
    "wof:placetype":"venue"
},
  "geometry": {"coordinates":[-1.2113039494,38.0511207581],"type":"Point"}
}