{
  "type": "Feature",
  "properties": {
    "iso:country":"ES",
    "sg:address":"Avda General Franco, 62",
    "sg:city":"Santa Uxia De Ribeira",
    "sg:orig_category":"Carnicer\u00cdas, Carnicer\u00cdas",
    "sg:phone":"+34 981 87 45 12",
    "sg:postcode":"15960",
    "sg:province":"La Coru\u00f1a",
    "wof:name":"Arnoso Sampedro Manuel Jose",
    "wof:placetype":"venue"
},
  "geometry": {"coordinates":[-8.9933700562,42.5599899292],"type":"Point"}
}