{
  "type": "Feature",
  "properties": {
    "iso:country":"ES",
    "sg:address":"Rua Calvo Sotelo, 180",
    "sg:city":"Sarria",
    "sg:orig_category":"Molduras, Junquillos, Listones Y Molduras Perforadas",
    "sg:phone":"+34 982 53 04 91",
    "sg:postcode":"27600",
    "sg:province":"Lugo",
    "wof:name":"Gonzalez Vazquez Carmen",
    "wof:placetype":"venue"
},
  "geometry": {"coordinates":[-7.4082288742,42.7770118713],"type":"Point"}
}