{
  "type": "Feature",
  "properties": {
    "addr:full":"Avda Eduardo Dato, 37 Sevilla Sevilla 41018",
    "addr:housenumber":"37",
    "addr:postcode":"41018",
    "addr:street":"Avda Eduardo Dato",
    "iso:country":"ES",
    "sg:address":"Avda Eduardo Dato, 37",
    "sg:city":"Sevilla",
    "sg:orig_category":"Cl\u00cdnicas M\u00c9dicas",
    "sg:phone":"+34 954 41 30 56",
    "sg:postcode":"41018",
    "sg:province":"Sevilla",
    "wof:name":"Merino Arcos Esther",
    "wof:placetype":"venue"
},
  "geometry": {"coordinates":[-5.9782438278,37.3839912415],"type":"Point"}
}