{
  "type": "Feature",
  "properties": {
    "addr:full":"Rua Ramon Del Valle Inclan, 103 Monforte De Lemos Lugo 27400",
    "addr:housenumber":"103",
    "addr:postcode":"27400",
    "addr:street":"Rua Ramon Del Valle Inclan",
    "iso:country":"ES",
    "sg:address":"Rua Ramon Del Valle Inclan, 103",
    "sg:city":"Monforte De Lemos",
    "sg:orig_category":"Molduras, Junquillos, Listones Y Molduras Perforadas",
    "sg:phone":"+34 982 41 04 89",
    "sg:postcode":"27400",
    "sg:province":"Lugo",
    "wof:name":"Garcia Nu\u00f1ez Jose Gilberto",
    "wof:placetype":"venue"
},
  "geometry": {"coordinates":[-7.4998106956,42.5240516663],"type":"Point"}
}