{
  "type": "Feature",
  "properties": {
    "iso:country":"ES",
    "sg:address":"Avda Generalisimo, 58",
    "sg:city":"Meira",
    "sg:orig_category":"Negocio De Materiales De Construcci\u00d3n",
    "sg:phone":"+34 982 33 00 02",
    "sg:postcode":"27240",
    "sg:province":"Lugo",
    "wof:name":"Almacenes Mendez S.l.",
    "wof:placetype":"venue"
},
  "geometry": {"coordinates":[-7.2943172455,43.2154541016],"type":"Point"}
}