{
  "type": "Feature",
  "properties": {
    "addr:full":"Carrer de Lorena, 93 Barcelona Barcelona 08042",
    "addr:housenumber":"93",
    "addr:postcode":"08042",
    "addr:street":"Carrer De Lorena",
    "iso:country":"ES",
    "sg:address":"Carrer de Lorena, 93",
    "sg:city":"Barcelona",
    "sg:orig_category":"Farmacias",
    "sg:phone":"+34 933 53 32 10",
    "sg:postcode":"08042",
    "sg:province":"Barcelona",
    "wof:name":"Roig Garriga Jose Maria",
    "wof:placetype":"venue"
},
  "geometry": {"coordinates":[2.1731619835,41.4378852844],"type":"Point"}
}