{
  "type": "Feature",
  "properties": {
    "addr:full":"Carr Pedraforca, S/n Solsona Lleida 25280",
    "addr:housenumber":"s / n",
    "addr:postcode":"25280",
    "addr:street":"Carr Pedraforca",
    "iso:country":"ES",
    "sg:address":"Carr Pedraforca, S/n",
    "sg:city":"Solsona",
    "sg:orig_category":"Ba\u00d1os Y Duchas P\u00dablicos",
    "sg:phone":"+34 973 48 25 24",
    "sg:postcode":"25280",
    "sg:province":"Lleida",
    "wof:name":"Espaigua S.l.",
    "wof:placetype":"venue"
},
  "geometry": {"coordinates":[1.5256099701,41.9958000183],"type":"Point"}
}