{
  "type": "Feature",
  "properties": {
    "addr:full":"Av. Del Istmo, 12 La Pared Las Palmas 35627",
    "addr:housenumber":"12",
    "addr:postcode":"35627",
    "addr:street":"Av. Del Istmo",
    "iso:country":"ES",
    "sg:address":"Av. Del Istmo, 12",
    "sg:city":"La Pared",
    "sg:orig_category":"Administradores De Bienes Y Delegados De Comunidades De Propietarios",
    "sg:phone":"+34 928 54 90 05",
    "sg:postcode":"35627",
    "sg:province":"Las Palmas",
    "wof:name":"Royal Coast S.l.",
    "wof:placetype":"venue"
},
  "geometry": {"coordinates":[-14.2158041,28.2136192322],"type":"Point"}
}