{
  "type": "Feature",
  "properties": {
    "iso:country":"ES",
    "sg:address":"Av. America, 7",
    "sg:city":"Alcorcon",
    "sg:orig_category":"Art\u00cdculos De Decoraci\u00d3n",
    "sg:phone":"+34 916 10 59 49",
    "sg:postcode":"28922",
    "sg:province":"Madrid",
    "sg:website":"www.lojadogatopreto.pt",
    "wof:name":"Aloja Do Gatopreto Espa\u00f1a S.r.l.",
    "wof:placetype":"venue"
},
  "geometry": {"coordinates":[-3.831130743,40.3590545654],"type":"Point"}
}