{
  "type": "Feature",
  "properties": {
    "iso:country":"ES",
    "sg:address":"Rua Illas Baleares, 16",
    "sg:city":"Vigo",
    "sg:orig_category":"Alquiler De Gr\u00daas",
    "sg:phone":"+34 986 49 30 52",
    "sg:postcode":"36203",
    "sg:province":"Pontevedra",
    "sg:website":"www.dematic.es",
    "wof:name":"Demag Cranes & Components S.a.u.",
    "wof:placetype":"venue"
},
  "geometry": {"coordinates":[-8.7236280441,42.2270317078],"type":"Point"}
}