{
  "type": "Feature",
  "properties": {
    "addr:full":"Calle de Vicente Andres Estelles, S/n Alaquas Valencia 46970",
    "addr:housenumber":"s",
    "addr:postcode":"46970",
    "addr:street":"Calle De Vicente Andres Estelles;/ N",
    "iso:country":"ES",
    "sg:address":"Calle de Vicente Andres Estelles, S/n",
    "sg:city":"Alaquas",
    "sg:orig_category":"Carnicer\u00cdas, Carnicer\u00cdas",
    "sg:phone":"+34 961 50 77 79",
    "sg:postcode":"46970",
    "sg:province":"Valencia",
    "wof:name":"Carpena Soriano Francisco",
    "wof:placetype":"venue"
},
  "geometry": {"coordinates":[-0.4612840116,39.455493927],"type":"Point"}
}