{
  "type": "Feature",
  "properties": {
    "addr:full":"Carrer de Balmes, 351 Barcelona Barcelona 08006",
    "addr:housenumber":"351",
    "addr:postcode":"08006",
    "addr:street":"Carrer De Balmes",
    "iso:country":"ES",
    "sg:address":"Carrer de Balmes, 351",
    "sg:city":"Barcelona",
    "sg:orig_category":"M\u00c1quinas, Material Y Suministros Para Cajas Y Embalajes",
    "sg:phone":"+34 934 17 32 35",
    "sg:postcode":"08006",
    "sg:province":"Barcelona",
    "wof:name":"Estesa S.l.",
    "wof:placetype":"venue"
},
  "geometry": {"coordinates":[2.1418869495,41.4038314819],"type":"Point"}
}