{
  "type": "Feature",
  "properties": {
    "iso:country":"ES",
    "sg:address":"Av Gaspar Bennazar, 73",
    "sg:city":"Palma",
    "sg:orig_category":"Organizaciones Internacionales",
    "sg:phone":"+34 971 29 50 00",
    "sg:postcode":"07004",
    "sg:province":"Islas Baleares",
    "sg:website":"www.cruzroja.es",
    "wof:name":"Cruz Roja Espa\u00f1ola",
    "wof:placetype":"venue"
},
  "geometry": {"coordinates":[2.653192997,39.5844421387],"type":"Point"}
}