{
  "type": "Feature",
  "properties": {
    "addr:full":"Calle de General Yag\u00fce, 10 Madrid Madrid 28020",
    "addr:housenumber":"10",
    "addr:postcode":"madrid;28020",
    "addr:street":"Calle De General Yaguee",
    "iso:country":"ES",
    "sg:address":"Calle de General Yag\u00fce, 10",
    "sg:city":"Madrid",
    "sg:orig_category":"Arquitectos",
    "sg:phone":"+34 915 55 03 75",
    "sg:postcode":"28020",
    "sg:province":"Madrid",
    "wof:name":"Lopez-pedraza Del Moral Miguel",
    "wof:placetype":"venue"
},
  "geometry": {"coordinates":[-3.6924471855,40.4562988281],"type":"Point"}
}