{
  "type": "Feature",
  "properties": {
    "iso:country":"ES",
    "sg:address":"Calle de Felix Apellaniz, 1",
    "sg:city":"Torrelavega",
    "sg:orig_category":"Zapatos (al Por Menor)",
    "sg:phone":"+34 942 89 08 42",
    "sg:postcode":"39300",
    "sg:province":"Cantabria",
    "wof:name":"San Emeterio Meana Maria Teresa",
    "wof:placetype":"venue"
},
  "geometry": {"coordinates":[-4.0464029312,43.3487129211],"type":"Point"}
}