{
  "type": "Feature",
  "properties": {
    "iso:country":"ES",
    "sg:address":"La Iglesia, 9",
    "sg:city":"Villavante",
    "sg:orig_category":"Molduras, Junquillos, Listones Y Molduras Perforadas",
    "sg:phone":"+34 987 38 80 27",
    "sg:postcode":"24393",
    "sg:province":"Le\u00f3n",
    "wof:name":"Calderon Vega Indalecio",
    "wof:placetype":"venue"
},
  "geometry": {"coordinates":[-5.8357028961,42.4621734619],"type":"Point"}
}