{
  "type": "Feature",
  "properties": {
    "addr:full":"Calle de Real, 21 San Sebastian De Los Reyes Madrid 28700",
    "addr:housenumber":"21",
    "addr:postcode":"28700",
    "addr:street":"Calle De Real",
    "iso:country":"ES",
    "sg:address":"Calle de Real, 21",
    "sg:city":"San Sebastian De Los Reyes",
    "sg:orig_category":"Mec\u00c1nico Del Autom\u00d3vil",
    "sg:phone":"+34 916 23 88 39",
    "sg:postcode":"28700",
    "sg:province":"Madrid",
    "wof:name":"Ramos Sanz Javier Tomas",
    "wof:placetype":"venue"
},
  "geometry": {"coordinates":[-3.6265668869,40.5463371277],"type":"Point"}
}