{
  "type": "Feature",
  "properties": {
    "addr:full":"Calle de Bazigorta, 4 Barakaldo Vizcaya 48903",
    "addr:housenumber":"4",
    "addr:postcode":"48903",
    "addr:street":"Calle De Bazigorta",
    "iso:country":"ES",
    "sg:address":"Calle de Bazigorta, 4",
    "sg:city":"Barakaldo",
    "sg:orig_category":"Molduras, Junquillos, Listones Y Molduras Perforadas",
    "sg:phone":"+34 944 99 37 89",
    "sg:postcode":"48903",
    "sg:province":"Vizcaya",
    "wof:name":"Alicia Martinez I\u00f1igo",
    "wof:placetype":"venue"
},
  "geometry": {"coordinates":[-2.9786026478,43.2903289795],"type":"Point"}
}