{
  "type": "Feature",
  "properties": {
    "addr:full":"Calle de Reyes Catolicos, 2 Elda Alicante 03600",
    "addr:housenumber":"2",
    "addr:postcode":"03600",
    "addr:street":"Calle De Reyes Catolicos",
    "iso:country":"ES",
    "sg:address":"Calle de Reyes Catolicos, 2",
    "sg:city":"Elda",
    "sg:orig_category":"Agencias De Viajes",
    "sg:phone":"+34 965 39 53 27",
    "sg:postcode":"03600",
    "sg:province":"Alicante",
    "sg:website":"www.viajesmarsans.es",
    "wof:name":"Viajes Marsans S.a.",
    "wof:placetype":"venue"
},
  "geometry": {"coordinates":[-0.7915620208,38.4802093506],"type":"Point"}
}