{
  "type": "Feature",
  "properties": {
    "iso:country":"ES",
    "sg:address":"Plaz Orconera, 6",
    "sg:city":"Valle Trapaga",
    "sg:orig_category":"Asilos De Ancianos. Centros Privados",
    "sg:phone":"+34 944 92 53 92",
    "sg:postcode":"48510",
    "sg:province":"Vizcaya",
    "wof:name":"Urgatzi S.l.",
    "wof:placetype":"venue"
},
  "geometry": {"coordinates":[-3.0369338989,43.3047294617],"type":"Point"}
}