{
  "type": "Feature",
  "properties": {
    "addr:full":"Calle de San Antonio Maria Claret, 10 Zaragoza Zaragoza 50005",
    "addr:housenumber":"10",
    "addr:postcode":"50005",
    "addr:street":"Calle De San;Maria Claret",
    "iso:country":"ES",
    "sg:address":"Calle de San Antonio Maria Claret, 10",
    "sg:city":"Zaragoza",
    "sg:orig_category":"Empresas De Vigilancia, Guardia Y Protecci\u00d3n",
    "sg:phone":"+34 976 55 08 16",
    "sg:postcode":"50005",
    "sg:province":"Zaragoza",
    "wof:name":"Securitas Seguridad Espa\u00f1a S.a.",
    "wof:placetype":"venue"
},
  "geometry": {"coordinates":[-0.8942630291,41.6458702087],"type":"Point"}
}