{
  "type": "Feature",
  "properties": {
    "iso:country":"ES",
    "sg:address":"Plaz Mayor, S/n",
    "sg:city":"Balbases",
    "sg:orig_category":"M\u00c9dicos: Radioterapia (radioterapia Como Opci\u00d3n Oncol\u00d3gica)",
    "sg:phone":"+34 947 16 55 91",
    "sg:postcode":"09119",
    "sg:province":"Burgos",
    "wof:name":"Andres Villa Miguel Angel",
    "wof:placetype":"venue"
},
  "geometry": {"coordinates":[-4.0624332428,42.2146835327],"type":"Point"}
}