{
  "type": "Feature",
  "properties": {
    "iso:country":"ES",
    "sg:address":"Rua Cervantes, 2",
    "sg:city":"Ourense",
    "sg:classifiers":[
        {
            "category":"Personal",
            "subcategory":"Barber",
            "type":"Services"
        }
    ],
    "sg:phone":"+34 988 24 12 73",
    "sg:postcode":"32005",
    "sg:province":"Ourense",
    "sg:tags":[
        "caballeros",
        "de",
        "peluqueros"
    ],
    "wof:name":"De La Torre Gonzalez Manuel",
    "wof:placetype":"venue"
},
  "geometry": {"coordinates":[-7.8641090393,42.3347625732],"type":"Point"}
}