{
  "type": "Feature",
  "properties": {
    "iso:country":"ES",
    "sg:address":"Calle de Alta, 3",
    "sg:city":"Ogijares",
    "sg:orig_category":"Iglesia Cat\u00d3lica",
    "sg:phone":"+34 958 59 70 77",
    "sg:postcode":"18151",
    "sg:province":"Granada",
    "wof:name":"Parroquia Nuestra Se\u00f1ora De La Cabeza",
    "wof:placetype":"venue"
},
  "geometry": {"coordinates":[-3.6095387936,37.1185951233],"type":"Point"}
}