{
  "type": "Feature",
  "properties": {
    "iso:country":"ES",
    "sg:address":"Carr Peralada, 8",
    "sg:city":"Figueres",
    "sg:orig_category":"Partidos Pol\u00cdticos",
    "sg:phone":"+34 972 51 61 66",
    "sg:postcode":"17600",
    "sg:province":"Girona",
    "wof:name":"Iniciativa Per Catalunya Verd",
    "wof:placetype":"venue"
},
  "geometry": {"coordinates":[2.9611325264,42.2675933838],"type":"Point"}
}