{
  "type": "Feature",
  "properties": {
    "addr:full":"Calle de Forcarey, 1 Coru\u00d1a La Coru\u00f1a 15002",
    "addr:housenumber":"1",
    "addr:postcode":"15002",
    "addr:street":"Calle De Forcarey;La Corun\u0303A",
    "iso:country":"ES",
    "sg:address":"Calle de Forcarey, 1",
    "sg:city":"Coru\u00d1a",
    "sg:orig_category":"Bordado, Marcado A Medida",
    "sg:phone":"+34 981 23 11 85",
    "sg:postcode":"15002",
    "sg:province":"La Coru\u00f1a",
    "wof:name":"Exposito Vaqueiro Maria Teresa",
    "wof:placetype":"venue"
},
  "geometry": {"coordinates":[-8.403626442,43.3776512146],"type":"Point"}
}