{
  "type": "Feature",
  "properties": {
    "iso:country":"ES",
    "sg:address":"Calle de Sagunto, 50",
    "sg:city":"Valencia",
    "sg:orig_category":"Producci\u00d3n, Distribuci\u00d3n De Electricidad",
    "sg:phone":"+34 963 47 02 91",
    "sg:postcode":"46009",
    "sg:province":"Valencia",
    "wof:name":"Estelles Just Jaime",
    "wof:placetype":"venue"
},
  "geometry": {"coordinates":[-0.3747340143,39.4841461182],"type":"Point"}
}