{
  "type": "Feature",
  "properties": {
    "iso:country":"ES",
    "sg:address":"Iturrilun Plaza, 5",
    "sg:city":"Zarautz",
    "sg:orig_category":"Agencias Y Asesores De Publicidad",
    "sg:phone":"+34 943 83 44 44",
    "sg:postcode":"20800",
    "sg:province":"Guip\u00f9zcoa",
    "sg:website":"www.bicom.es",
    "wof:name":"Bicom Publicidad Y Marketing S.l.",
    "wof:placetype":"venue"
},
  "geometry": {"coordinates":[-2.1776471138,43.2848129272],"type":"Point"}
}