{
  "type": "Feature",
  "properties": {
    "addr:full":"Calle de Grande, 19 S. Pedro Ceque Zamora 49628",
    "addr:housenumber":"19",
    "addr:postcode":"49628",
    "addr:street":"Calle De Grande;S. Pedro Ceque Zamora",
    "iso:country":"ES",
    "sg:address":"Calle de Grande, 19",
    "sg:city":"S. Pedro Ceque",
    "sg:orig_category":"Pescader\u00cdas (al Por Menor)",
    "sg:phone":"+34 980 64 14 04",
    "sg:postcode":"49628",
    "sg:province":"Zamora",
    "wof:name":"Charro Gonzalez Victorino",
    "wof:placetype":"venue"
},
  "geometry": {"coordinates":[-6.0710291862,42.0426712036],"type":"Point"}
}