{
  "type": "Feature",
  "properties": {
    "iso:country":"ES",
    "sg:address":"Calle de Fuente, S/n",
    "sg:city":"Quintanar Sierra",
    "sg:orig_category":"Asilos De Ancianos. Centros Privados",
    "sg:phone":"+34 947 39 51 13",
    "sg:postcode":"09670",
    "sg:province":"Burgos",
    "wof:name":"Asociacion Jub.y Pens.san Cristobal",
    "wof:placetype":"venue"
},
  "geometry": {"coordinates":[-3.0372292995,41.9834365845],"type":"Point"}
}