{
  "type": "Feature",
  "properties": {
    "addr:full":"Barr Coterillo, S/n Coterillo Cantabria 39849",
    "addr:housenumber":"s",
    "addr:postcode":"39849",
    "addr:street":"/ N",
    "iso:country":"ES",
    "sg:address":"Barr Coterillo, S/n",
    "sg:city":"Coterillo",
    "sg:orig_category":"Empresas De Electricidad En General",
    "sg:phone":"+34 942 63 40 60",
    "sg:postcode":"39849",
    "sg:province":"Cantabria",
    "wof:name":"Central Hidrolica De Coterillo S.cv.",
    "wof:placetype":"venue"
},
  "geometry": {"coordinates":[-3.4252030849,43.3393096924],"type":"Point"}
}