{
  "type": "Feature",
  "properties": {
    "iso:country":"ES",
    "sg:address":"Calle de Rey Amadeo, 14",
    "sg:city":"Quesa",
    "sg:orig_category":"Cooperativas Agr\u00cdcolas",
    "sg:phone":"+34 962 25 60 80",
    "sg:postcode":"46824",
    "sg:province":"Valencia",
    "wof:name":"Cooperativa Valenciana San Isidro Labrador",
    "wof:placetype":"venue"
},
  "geometry": {"coordinates":[-0.7401040196,39.1192512512],"type":"Point"}
}