{
  "type": "Feature",
  "properties": {
    "iso:country":"ES",
    "sg:address":"Calle de Capitan Gaona, 5",
    "sg:city":"Logro\u00f1o",
    "sg:orig_category":"Molduras, Junquillos, Listones Y Molduras Perforadas",
    "sg:phone":"+34 941 25 36 94",
    "sg:postcode":"26001",
    "sg:province":"La Rioja",
    "wof:name":"Jose Luis Abad Reinares Y Otro S.cv.",
    "wof:placetype":"venue"
},
  "geometry": {"coordinates":[-2.4411923885,42.4666786194],"type":"Point"}
}