{
  "type": "Feature",
  "properties": {
    "iso:country":"ES",
    "sg:address":"Carrer de Valencia, 15",
    "sg:city":"Senia",
    "sg:orig_category":"Talleres El\u00c9ctricos Para Veh\u00cdculos",
    "sg:phone":"+34 977 57 01 28",
    "sg:postcode":"43560",
    "sg:province":"Tarragona",
    "wof:name":"Selauto S.l.",
    "wof:placetype":"venue"
},
  "geometry": {"coordinates":[0.2838050127,40.6335144043],"type":"Point"}
}