{
  "type": "Feature",
  "properties": {
    "iso:country":"ES",
    "sg:address":"Calle de San Vicente Martir, 146",
    "sg:city":"Valencia",
    "sg:orig_category":"Productores Recolectores, Venta Directa De Vinos",
    "sg:phone":"+34 963 80 90 14",
    "sg:postcode":"46007",
    "sg:province":"Valencia",
    "sg:website":"www.torres.es",
    "wof:name":"Miguel Torres S.a.",
    "wof:placetype":"venue"
},
  "geometry": {"coordinates":[-0.382434994,39.4626274109],"type":"Point"}
}