{
  "type": "Feature",
  "properties": {
    "addr:full":"Calle de Papin, 13 Salamanca Salamanca 37007",
    "addr:housenumber":"13",
    "addr:postcode":"37007",
    "addr:street":"Calle De Papin",
    "iso:country":"ES",
    "sg:address":"Calle de Papin, 13",
    "sg:city":"Salamanca",
    "sg:orig_category":"Asociaciones, Organismos Culturales Y Socioeducativos",
    "sg:phone":"+34 923 22 92 16",
    "sg:postcode":"37007",
    "sg:province":"Salamanca",
    "wof:name":"Sociedad San Vicente De Paul En Espa\u00f1a.",
    "wof:placetype":"venue"
},
  "geometry": {"coordinates":[-5.6682419777,40.970123291],"type":"Point"}
}