{
  "type": "Feature",
  "properties": {
    "iso:country":"ES",
    "sg:address":"Carrer de Llacuna, 28",
    "sg:city":"Barcelona",
    "sg:orig_category":"Materias Pl\u00c1sticas: Art\u00cdculos Para La Industria",
    "sg:phone":"+34 934 85 13 31",
    "sg:postcode":"08005",
    "sg:province":"Barcelona",
    "wof:name":"Maiol Germans S.l.",
    "wof:placetype":"venue"
},
  "geometry": {"coordinates":[2.2012970448,41.3995132446],"type":"Point"}
}