{
  "type": "Feature",
  "properties": {
    "iso:country":"ES",
    "sg:address":"Calle de Alfonso Fernandez, 2",
    "sg:city":"Madrid",
    "sg:orig_category":"\u00d3ptica: Instrumentos (fabricaci\u00d3n)",
    "sg:phone":"+34 915 08 38 00",
    "sg:postcode":"28044",
    "sg:province":"Madrid",
    "wof:name":"Centro Optico Buenavista S.l.",
    "wof:placetype":"venue"
},
  "geometry": {"coordinates":[-3.7559018135,40.3682022095],"type":"Point"}
}