{
  "type": "Feature",
  "properties": {
    "iso:country":"ES",
    "sg:address":"Calle de Benito Guinea, 14",
    "sg:city":"Vitoria-gasteiz",
    "sg:orig_category":"Electromec\u00c1nica",
    "sg:phone":"+34 945 27 61 88",
    "sg:postcode":"01003",
    "sg:province":"\u00c1lava",
    "wof:name":"Electromecanica Judimendi,s.l.",
    "wof:placetype":"venue"
},
  "geometry": {"coordinates":[-2.662060976,42.8460388184],"type":"Point"}
}