{
  "type": "Feature",
  "properties": {
    "addr:full":"Calle de Pedro Teixeira, 8 Madrid Madrid 28020",
    "addr:housenumber":"8",
    "addr:postcode":"28020",
    "addr:street":"Calle De Pedro;Madrid",
    "iso:country":"ES",
    "sg:address":"Calle de Pedro Teixeira, 8",
    "sg:city":"Madrid",
    "sg:orig_category":"Inmobiliaria (agencias)",
    "sg:phone":"+34 915 55 11 14",
    "sg:postcode":"28020",
    "sg:province":"Madrid",
    "wof:name":"Atrio Parque Empresarial S.l.",
    "wof:placetype":"venue"
},
  "geometry": {"coordinates":[-3.6935870647,40.4549217224],"type":"Point"}
}