{
  "type": "Feature",
  "properties": {
    "addr:full":"Calle de Goya, 8 Santa Marta De Tormes Salamanca 37900",
    "addr:housenumber":"8",
    "addr:postcode":"37900",
    "addr:street":"Calle De Goya",
    "iso:country":"ES",
    "sg:address":"Calle de Goya, 8",
    "sg:city":"Santa Marta De Tormes",
    "sg:orig_category":"Carnicer\u00cdas, Carnicer\u00cdas",
    "sg:phone":"+34 923 20 09 07",
    "sg:postcode":"37900",
    "sg:province":"Salamanca",
    "wof:name":"Meson Varillas Manuel",
    "wof:placetype":"venue"
},
  "geometry": {"coordinates":[-5.6310138702,40.9489784241],"type":"Point"}
}