{
  "type": "Feature",
  "properties": {
    "addr:full":"Plaz Real, Del, 20 Castellon Castell\u00f3n 12001",
    "addr:postcode":"12001",
    "addr:street":"Castellon Castello\u0301N",
    "iso:country":"ES",
    "sg:address":"Plaz Real, Del, 20",
    "sg:city":"Castellon",
    "sg:orig_category":"Motocicletas (agentes, Concesionarios)",
    "sg:phone":"+34 964 21 33 26",
    "sg:postcode":"12001",
    "sg:province":"Castell\u00f3n",
    "wof:name":"Montesinos Gil Tomas",
    "wof:placetype":"venue"
},
  "geometry": {"coordinates":[-0.0390199982,39.9866409302],"type":"Point"}
}