{
  "type": "Feature",
  "properties": {
    "iso:country":"ES",
    "sg:address":"Avda Orcasur, 42",
    "sg:city":"Madrid",
    "sg:orig_category":"Internados & Ense\u00d1anza Privada",
    "sg:phone":"+34 913 17 02 37",
    "sg:postcode":"28041",
    "sg:province":"Madrid",
    "wof:name":"Colegio Maria Reina Hijas De Jesus",
    "wof:placetype":"venue"
},
  "geometry": {"coordinates":[-3.7020258904,40.3655700684],"type":"Point"}
}