{
  "type": "Feature",
  "properties": {
    "iso:country":"ES",
    "sg:address":"Avda Gran Via, 2",
    "sg:city":"Vigo",
    "sg:orig_category":"Peluqueros: De Se\u00d1oras",
    "sg:phone":"+34 986 43 44 06",
    "sg:postcode":"36203",
    "sg:province":"Pontevedra",
    "wof:name":"Isorna Lopez Camilo",
    "wof:placetype":"venue"
},
  "geometry": {"coordinates":[-8.7167367935,42.2344436646],"type":"Point"}
}