{
  "type": "Feature",
  "properties": {
    "iso:country":"ES",
    "sg:address":"Carrer de Doctor Fleming, 35",
    "sg:city":"S. Andreu Barca",
    "sg:orig_category":"Mec\u00c1nico Del Autom\u00d3vil",
    "sg:phone":"+34 936 53 34 01",
    "sg:postcode":"08740",
    "sg:province":"Barcelona",
    "wof:name":"Gonzalez Gimenez Rosendo",
    "wof:placetype":"venue"
},
  "geometry": {"coordinates":[1.9681710005,41.4475593567],"type":"Point"}
}