{
  "type": "Feature",
  "properties": {
    "iso:country":"ES",
    "sg:address":"Calle de Caballero De Rodas, 27",
    "sg:city":"Torrevieja",
    "sg:orig_category":"Arquitectos",
    "sg:phone":"+34 965 71 29 67",
    "sg:postcode":"03180",
    "sg:province":"Alicante",
    "wof:name":"Velazquez Arroyo Alberto",
    "wof:placetype":"venue"
},
  "geometry": {"coordinates":[-0.6833630204,37.9779052734],"type":"Point"}
}