{
  "type": "Feature",
  "properties": {
    "iso:country":"ES",
    "sg:address":"Calle de Leon Y Castillo, 39",
    "sg:city":"Pto. Rosario",
    "sg:orig_category":"Perfumer\u00cda (al Por Menor)",
    "sg:phone":"+34 928 85 87 76",
    "sg:postcode":"35600",
    "sg:province":"Las Palmas",
    "wof:name":"Magnolia Puerto S.c.p.",
    "wof:placetype":"venue"
},
  "geometry": {"coordinates":[-13.8649196625,28.5003261566],"type":"Point"}
}