{
  "type": "Feature",
  "properties": {
    "iso:country":"ES",
    "sg:address":"Carr Jonquera, 38",
    "sg:city":"Figueres",
    "sg:orig_category":"Reposter\u00cdas",
    "sg:phone":"+34 972 50 16 98",
    "sg:postcode":"17600",
    "sg:province":"Girona",
    "wof:name":"Forebre S.l.",
    "wof:placetype":"venue"
},
  "geometry": {"coordinates":[2.9601559639,42.2689208984],"type":"Point"}
}