{
  "type": "Feature",
  "properties": {
    "addr:full":"Avda Cami\u00d1o Frances (do), 4 Santiago De Compostela La Coru\u00f1a 15704",
    "addr:housenumber":"4",
    "addr:postcode":"15704",
    "addr:street":"Avda Camin\u0303O;Do;Corun\u0303A",
    "iso:country":"ES",
    "sg:address":"Avda Cami\u00d1o Frances (do), 4",
    "sg:city":"Santiago De Compostela",
    "sg:orig_category":"Centros Empresariales",
    "sg:phone":"+34 981 57 56 03",
    "sg:postcode":"15704",
    "sg:province":"La Coru\u00f1a",
    "sg:website":"www.estinga.com",
    "wof:name":"Estinga Servicios Sociales S.l.",
    "wof:placetype":"venue"
},
  "geometry": {"coordinates":[-8.526556015,42.8877220154],"type":"Point"}
}