{
  "type": "Feature",
  "properties": {
    "iso:country":"ES",
    "sg:address":"Carrer de Sequia Comtal, 5",
    "sg:city":"Barcelona",
    "sg:orig_category":"Bazares, Art\u00cdculos De Limpieza Y De Cocina (al Por Menor)",
    "sg:phone":"+34 932 32 67 05",
    "sg:postcode":"08018",
    "sg:province":"Barcelona",
    "wof:name":"Gonzalez Guillen Francisco Javier",
    "wof:placetype":"venue"
},
  "geometry": {"coordinates":[2.1880130768,41.4080200195],"type":"Point"}
}