{
  "type": "Feature",
  "properties": {
    "addr:full":"Pl. Mercat, S/n Vilanova Geltru Barcelona 08800",
    "addr:housenumber":"s / n",
    "addr:postcode":"08800",
    "addr:street":"Mercat;Geltru Barcelona",
    "iso:country":"ES",
    "sg:address":"Pl. Mercat, S/n",
    "sg:city":"Vilanova Geltru",
    "sg:orig_category":"Poller\u00cda Y Caza (al Por Menor)",
    "sg:phone":"+34 938 93 22 99",
    "sg:postcode":"08800",
    "sg:province":"Barcelona",
    "wof:name":"Maspons Feliu Emili",
    "wof:placetype":"venue"
},
  "geometry": {"coordinates":[1.7242449522,41.2228088379],"type":"Point"}
}