{
  "type": "Feature",
  "properties": {
    "iso:country":"ES",
    "sg:address":"Carrer de Valencia, 663",
    "sg:city":"Barcelona",
    "sg:orig_category":"Fabricaci\u00d3n De Sobres, Bolsas Y Fundas",
    "sg:phone":"+34 933 52 88 52",
    "sg:postcode":"08026",
    "sg:province":"Barcelona",
    "wof:name":"Cervantes Quesada Antonio",
    "wof:placetype":"venue"
},
  "geometry": {"coordinates":[2.1895360947,41.4125862122],"type":"Point"}
}