{
  "type": "Feature",
  "properties": {
    "iso:country":"ES",
    "sg:address":"C/ 29, 40",
    "sg:city":"Ca\u00d1ada",
    "sg:orig_category":"Administradores De Bienes Y Delegados De Comunidades De Propietarios",
    "sg:phone":"+34 961 32 16 16",
    "sg:postcode":"46182",
    "sg:province":"Valencia",
    "wof:name":"Marcbo S.a.",
    "wof:placetype":"venue"
},
  "geometry": {"coordinates":[-0.4852339923,39.5221443176],"type":"Point"}
}