{
  "type": "Feature",
  "properties": {
    "addr:full":"Calle de El Algabe\u00d1o, 115 Madrid Madrid 28043",
    "addr:housenumber":"115",
    "addr:postcode":"28043",
    "addr:street":"Calle De El Algaben\u0303O",
    "iso:country":"ES",
    "sg:address":"Calle de El Algabe\u00d1o, 115",
    "sg:city":"Madrid",
    "sg:classifiers":[
        {
            "category":"Autos & Motor Vehicles",
            "subcategory":"Automobile Sales",
            "type":"Retail Goods"
        }
    ],
    "sg:phone":"+34 913 88 77 30",
    "sg:postcode":"28043",
    "sg:province":"Madrid",
    "wof:name":"Encina Montero Francisco Javier",
    "wof:placetype":"venue"
},
  "geometry": {"coordinates":[-3.6261019707,40.4574012756],"type":"Point"}
}