{
  "type": "Feature",
  "properties": {
    "iso:country":"ES",
    "sg:address":"Calle de Nueva, 50",
    "sg:city":"Cabezas S. Juan",
    "sg:orig_category":"Peluqueros: De Se\u00d1oras",
    "sg:phone":"+34 955 87 07 32",
    "sg:postcode":"41730",
    "sg:province":"Sevilla",
    "wof:name":"Orozco Soria Rafael",
    "wof:placetype":"venue"
},
  "geometry": {"coordinates":[-5.9381151199,36.9841423035],"type":"Point"}
}