{
  "type": "Feature",
  "properties": {
    "addr:full":"Carrer de Mila I Fontanals, 104 Santa Coloma De Gramenet Barcelona 08922",
    "addr:housenumber":"104",
    "addr:postcode":"08922",
    "addr:street":"Carrer De Mila I Fontanals",
    "iso:country":"ES",
    "sg:address":"Carrer de Mila I Fontanals, 104",
    "sg:city":"Santa Coloma De Gramenet",
    "sg:orig_category":"Promotores Constructores",
    "sg:phone":"+34 933 91 13 34",
    "sg:postcode":"08922",
    "sg:province":"Barcelona",
    "wof:name":"Lopez Martinez San Andres S.l.",
    "wof:placetype":"venue"
},
  "geometry": {"coordinates":[2.2176909447,41.4502563477],"type":"Point"}
}