{
  "type": "Feature",
  "properties": {
    "addr:full":"Calle de Real Vieja, 63 San Sebastian De Los Reyes Madrid 28700",
    "addr:housenumber":"63",
    "addr:postcode":"28700",
    "addr:street":"Calle De Real Vieja",
    "iso:country":"ES",
    "sg:address":"Calle de Real Vieja, 63",
    "sg:city":"San Sebastian De Los Reyes",
    "sg:orig_category":"Asesor\u00cda Fiscal Y Jur\u00cddica",
    "sg:phone":"+34 916 51 69 00",
    "sg:postcode":"28700",
    "sg:province":"Madrid",
    "wof:name":"Sagol Asesores S.l.",
    "wof:placetype":"venue"
},
  "geometry": {"coordinates":[-3.6230070591,40.5486679077],"type":"Point"}
}