{
  "type": "Feature",
  "properties": {
    "iso:country":"ES",
    "sg:address":"Calle de Teide, 12",
    "sg:city":"Puerto Del Carmen",
    "sg:orig_category":"Inmobiliaria (agencias)",
    "sg:phone":"+34 928 51 12 98",
    "sg:postcode":"35510",
    "sg:province":"Las Palmas",
    "wof:name":"Inmobiliaria Real Estate San Gregorio S.l.",
    "wof:placetype":"venue"
},
  "geometry": {"coordinates":[-13.6722717285,28.9219474792],"type":"Point"}
}