{
  "type": "Feature",
  "properties": {
    "addr:full":"Calle de Lago Salado, 9 Madrid Madrid 28017",
    "addr:housenumber":"9",
    "addr:postcode":"madrid;28017",
    "addr:street":"Calle De Lago Salado",
    "iso:country":"ES",
    "sg:address":"Calle de Lago Salado, 9",
    "sg:city":"Madrid",
    "sg:orig_category":"Peluqueros: De Se\u00d1oras",
    "sg:phone":"+34 914 07 10 29",
    "sg:postcode":"28017",
    "sg:province":"Madrid",
    "wof:name":"Martinez Ramos Carmen",
    "wof:placetype":"venue"
},
  "geometry": {"coordinates":[-3.6371068954,40.4347000122],"type":"Point"}
}