{
  "type": "Feature",
  "properties": {
    "addr:full":"Carr Rectoria, 10 Alaro Islas Baleares 07340",
    "addr:housenumber":"10",
    "addr:postcode":"07340",
    "addr:street":"Carr Rectoria",
    "iso:country":"ES",
    "sg:address":"Carr Rectoria, 10",
    "sg:city":"Alaro",
    "sg:orig_category":"Iglesia Cat\u00d3lica",
    "sg:phone":"+34 971 51 00 47",
    "sg:postcode":"07340",
    "sg:province":"Islas Baleares",
    "wof:name":"Obispado De Mallorca",
    "wof:placetype":"venue"
},
  "geometry": {"coordinates":[2.7885849476,39.7052536011],"type":"Point"}
}