{
  "type": "Feature",
  "properties": {
    "addr:full":"Carr Corts Catalanes, 20 Lleida Lleida 25005",
    "addr:housenumber":"20",
    "addr:postcode":"25005",
    "addr:street":"Carr Corts Catalanes",
    "iso:country":"ES",
    "sg:address":"Carr Corts Catalanes, 20",
    "sg:city":"Lleida",
    "sg:orig_category":"Electricidad: Instaladores",
    "sg:phone":"+34 973 23 96 12",
    "sg:postcode":"25005",
    "sg:province":"Lleida",
    "wof:name":"Alba Visa Carlos",
    "wof:placetype":"venue"
},
  "geometry": {"coordinates":[0.6267892122,41.6257667542],"type":"Point"}
}