{
  "type": "Feature",
  "properties": {
    "iso:country":"ES",
    "sg:address":"Calle de Barco El, 14",
    "sg:city":"Arriondas",
    "sg:orig_category":"Formaci\u00d3n Continuada (variada)",
    "sg:phone":"+34 985 84 12 03",
    "sg:postcode":"33540",
    "sg:province":"Asturias",
    "wof:name":"Centro De Formacion Ocupacional Don Orione",
    "wof:placetype":"venue"
},
  "geometry": {"coordinates":[-5.1821274757,43.3918647766],"type":"Point"}
}