{
  "type": "Feature",
  "properties": {
    "iso:country":"ES",
    "sg:address":"Garraf (pol Ind Cantallops), S/n",
    "sg:city":"Lli\u00e7a Vall",
    "sg:orig_category":"Construcciones Met\u00c1licas",
    "sg:phone":"+34 938 44 56 40",
    "sg:postcode":"08185",
    "sg:province":"Barcelona",
    "wof:name":"Esetri S.l.",
    "wof:placetype":"venue"
},
  "geometry": {"coordinates":[2.2302498817,41.5783081055],"type":"Point"}
}