{
  "type": "Feature",
  "properties": {
    "iso:country":"ES",
    "sg:address":"Carr Juan Xxiii, 89",
    "sg:city":"Puerto De Pollen\u00c7a",
    "sg:orig_category":"Comercio, Reparaci\u00d3n De Bicicletas, De Motocicletas, De Accesorios",
    "sg:phone":"+34 971 86 47 84",
    "sg:postcode":"07470",
    "sg:province":"Islas Baleares",
    "wof:name":"Cerda March Martin",
    "wof:placetype":"venue"
},
  "geometry": {"coordinates":[3.0826599598,39.9063415527],"type":"Point"}
}