{
  "type": "Feature",
  "properties": {
    "addr:full":"Pl Bisaura, 7 S. Quirze Besora Barcelona 08580",
    "addr:housenumber":"7",
    "addr:postcode":"08580",
    "addr:street":"Pl Bisaura",
    "iso:country":"ES",
    "sg:address":"Pl Bisaura, 7",
    "sg:city":"S. Quirze Besora",
    "sg:orig_category":"Cester\u00cda (fabricaci\u00d3n)",
    "sg:phone":"+34 938 55 01 76",
    "sg:postcode":"08580",
    "sg:province":"Barcelona",
    "wof:name":"Subiran Bertran Rosa",
    "wof:placetype":"venue"
},
  "geometry": {"coordinates":[2.2178170681,42.1007881165],"type":"Point"}
}