{
  "type": "Feature",
  "properties": {
    "addr:full":"Charcas, 6 Horcajo Santiago Cuenca 16410",
    "addr:housenumber":"6",
    "addr:postcode":"16410",
    "addr:street":"Charcas;Cuenca",
    "iso:country":"ES",
    "sg:address":"Charcas, 6",
    "sg:city":"Horcajo Santiago",
    "sg:orig_category":"Electricidad: Instaladores",
    "sg:phone":"+34 969 12 82 25",
    "sg:postcode":"16410",
    "sg:province":"Cuenca",
    "wof:name":"Electricidad Garluz S.l.l.",
    "wof:placetype":"venue"
},
  "geometry": {"coordinates":[-2.9984769821,39.8482933044],"type":"Point"}
}