{
  "type": "Feature",
  "properties": {
    "iso:country":"ES",
    "sg:address":"Av Catalunya, 15",
    "sg:city":"Tarrega",
    "sg:orig_category":"Cajas De Ahorro",
    "sg:phone":"+34 973 50 20 27",
    "sg:postcode":"25300",
    "sg:province":"Lleida",
    "wof:name":"Caja De Ahorros Del Mediterraneo",
    "wof:placetype":"venue"
},
  "geometry": {"coordinates":[1.1393610239,41.6482810974],"type":"Point"}
}