{
  "type": "Feature",
  "properties": {
    "iso:country":"ES",
    "sg:address":"Avda Villanueva De Cordoba, 7",
    "sg:city":"Pozoblanco",
    "sg:orig_category":"Fotocopias, Reprograf\u00cda",
    "sg:phone":"+34 957 77 15 17",
    "sg:postcode":"14400",
    "sg:province":"C\u00f3rdoba",
    "sg:website":"www.el-semaforo.com",
    "wof:name":"Sicilia Bautista Nemesio",
    "wof:placetype":"venue"
},
  "geometry": {"coordinates":[-4.85085392,38.3810844421],"type":"Point"}
}