{
  "type": "Feature",
  "properties": {
    "addr:full":"Carr Aigueta, 1 Bisbal D'emporda Girona 17100",
    "addr:housenumber":"1",
    "addr:postcode":"17100",
    "addr:street":"Carr Aigueta",
    "iso:country":"ES",
    "sg:address":"Carr Aigueta, 1",
    "sg:city":"Bisbal D'emporda",
    "sg:classifiers":[
        {
            "category":"Autos & Motor Vehicles",
            "subcategory":"Automobile Sales",
            "type":"Retail Goods"
        }
    ],
    "sg:phone":"+34 972 64 28 23",
    "sg:postcode":"17100",
    "sg:province":"Girona",
    "wof:name":"Balaguer Vives Enrique",
    "wof:placetype":"venue"
},
  "geometry": {"coordinates":[2.8376150131,41.9890365601],"type":"Point"}
}