{
  "type": "Feature",
  "properties": {
    "iso:country":"ES",
    "sg:address":"Praz Maior, 30",
    "sg:city":"Lugo",
    "sg:orig_category":"Abogados",
    "sg:phone":"+34 982 22 85 51",
    "sg:postcode":"27001",
    "sg:province":"Lugo",
    "wof:name":"Varela Pintos Mauro",
    "wof:placetype":"venue"
},
  "geometry": {"coordinates":[-7.5552358627,43.0096817017],"type":"Point"}
}