{
  "type": "Feature",
  "properties": {
    "addr:full":"Calle de Ordo\u00d1ez, 15 Madrid Madrid 28029",
    "addr:housenumber":"15",
    "addr:postcode":"madrid;28029",
    "addr:street":"Calle De Ordon\u0303Ez",
    "iso:country":"ES",
    "sg:address":"Calle de Ordo\u00d1ez, 15",
    "sg:city":"Madrid",
    "sg:orig_category":"Promotores Constructores",
    "sg:phone":"+34 913 14 14 67",
    "sg:postcode":"28029",
    "sg:province":"Madrid",
    "wof:name":"Construcciones Rubau S.a.",
    "wof:placetype":"venue"
},
  "geometry": {"coordinates":[-3.6916489601,40.4732666016],"type":"Point"}
}