{
  "type": "Feature",
  "properties": {
    "addr:full":"C/ Pola, 25 Tossa Girona 17320",
    "addr:housenumber":"25",
    "addr:postcode":"17320",
    "addr:street":"C / Pola",
    "iso:country":"ES",
    "sg:address":"C/ Pola, 25",
    "sg:city":"Tossa",
    "sg:orig_category":"Florister\u00cdas",
    "sg:phone":"+34 972 34 11 11",
    "sg:postcode":"17320",
    "sg:province":"Girona",
    "wof:name":"Ferreres Conesa Joaquin",
    "wof:placetype":"venue"
},
  "geometry": {"coordinates":[2.9300830364,41.7212219238],"type":"Point"}
}