{
  "type": "Feature",
  "properties": {
    "addr:full":"Rua Lopez Ferreiro, 3 Ourense Ourense 32001",
    "addr:housenumber":"3",
    "addr:postcode":"32001",
    "addr:street":"Rua Lopez Ferreiro",
    "iso:country":"ES",
    "sg:address":"Rua Lopez Ferreiro, 3",
    "sg:city":"Ourense",
    "sg:orig_category":"Mec\u00c1nico Del Autom\u00d3vil",
    "sg:phone":"+34 988 21 44 45",
    "sg:postcode":"32001",
    "sg:province":"Ourense",
    "wof:name":"Taller Auto-agro S.l.",
    "wof:placetype":"venue"
},
  "geometry": {"coordinates":[-7.8696670532,42.3516616821],"type":"Point"}
}