{
  "type": "Feature",
  "properties": {
    "addr:full":"Plaz San Pedro (de), 8 Cordoba C\u00f3rdoba 14002",
    "addr:postcode":"14002",
    "addr:street":"Plaz San Pedro;Co\u0301Rdoba",
    "iso:country":"ES",
    "sg:address":"Plaz San Pedro (de), 8",
    "sg:city":"Cordoba",
    "sg:orig_category":"Dorados, Plater\u00cda (orfebrer\u00cda)",
    "sg:phone":"+34 957 43 23 53",
    "sg:postcode":"14002",
    "sg:province":"C\u00f3rdoba",
    "wof:name":"Bestgold S.l.",
    "wof:placetype":"venue"
},
  "geometry": {"coordinates":[-4.7710790634,37.8827590942],"type":"Point"}
}