{
  "type": "Feature",
  "properties": {
    "iso:country":"ES",
    "sg:address":"Calle de Progreso, 19",
    "sg:city":"Puerto Mazarron",
    "sg:orig_category":"Caf\u00c9s, Bares, Cervecer\u00cdas",
    "sg:phone":"+34 968 59 42 71",
    "sg:postcode":"30860",
    "sg:province":"Murcia",
    "wof:name":"Vivancos Garcia Jose",
    "wof:placetype":"venue"
},
  "geometry": {"coordinates":[-1.2588576078,37.5664749146],"type":"Point"}
}