{
  "type": "Feature",
  "properties": {
    "iso:country":"ES",
    "sg:address":"Fte Hierro, 2",
    "sg:city":"Iru\u00f1a",
    "sg:orig_category":"Cl\u00cdnicas Dentales",
    "sg:phone":"+34 948 17 09 66",
    "sg:postcode":"31007",
    "sg:province":"Navarra",
    "wof:name":"Claude Londaitz Jean",
    "wof:placetype":"venue"
},
  "geometry": {"coordinates":[-1.6533039808,42.809513092],"type":"Point"}
}