{
  "type": "Feature",
  "properties": {
    "addr:full":"Calle de Maestro Lleo, 8 Salamanca Salamanca 37008",
    "addr:housenumber":"8",
    "addr:postcode":"37008",
    "addr:street":"Calle De Maestro Lleo",
    "iso:country":"ES",
    "sg:address":"Calle de Maestro Lleo, 8",
    "sg:city":"Salamanca",
    "sg:orig_category":"Molduras, Junquillos, Listones Y Molduras Perforadas",
    "sg:phone":"+34 923 21 68 80",
    "sg:postcode":"37008",
    "sg:province":"Salamanca",
    "wof:name":"Gonzalez Martin Jose",
    "wof:placetype":"venue"
},
  "geometry": {"coordinates":[-5.661110878,40.9491844177],"type":"Point"}
}