{
  "type": "Feature",
  "properties": {
    "addr:full":"Prj Barreros, Km. 0011,0 Villarta Cuenca 16280",
    "addr:postcode":"16280",
    "addr:street":"Barreros Km. 0011,0",
    "iso:country":"ES",
    "sg:address":"Prj Barreros, Km. 0011,0",
    "sg:city":"Villarta",
    "sg:orig_category":"Producci\u00d3n De Champi\u00d1ones",
    "sg:phone":"+34 962 18 90 13",
    "sg:postcode":"16280",
    "sg:province":"Cuenca",
    "wof:name":"Cordobachamp Cooperativa",
    "wof:placetype":"venue"
},
  "geometry": {"coordinates":[-1.653695941,39.4396400452],"type":"Point"}
}