{
  "type": "Feature",
  "properties": {
    "addr:full":"Calle de Colombicultor, 1 Denia Alicante 03700",
    "addr:housenumber":"1",
    "addr:postcode":"03700",
    "addr:street":"Calle De Colombicultor",
    "iso:country":"ES",
    "sg:address":"Calle de Colombicultor, 1",
    "sg:city":"Denia",
    "sg:orig_category":"Material Y Suministros Para Perforaciones, Sondeos",
    "sg:phone":"+34 965 78 02 48",
    "sg:postcode":"03700",
    "sg:province":"Alicante",
    "wof:name":"Exca Trans S.l.",
    "wof:placetype":"venue"
},
  "geometry": {"coordinates":[0.1019442976,38.8406600952],"type":"Point"}
}