{
  "type": "Feature",
  "properties": {
    "addr:full":"Carr Major, 3 Palafrugell Girona 17200",
    "addr:housenumber":"3",
    "addr:postcode":"17200",
    "addr:street":"Carr Major",
    "iso:country":"ES",
    "sg:address":"Carr Major, 3",
    "sg:city":"Palafrugell",
    "sg:orig_category":"Restaurantes",
    "sg:phone":"+34 972 61 06 95",
    "sg:postcode":"17200",
    "sg:province":"Girona",
    "wof:name":"Ristorante Pizzeria L'arcobaleno S.l.",
    "wof:placetype":"venue"
},
  "geometry": {"coordinates":[3.1637270451,41.9170722961],"type":"Point"}
}