{
  "type": "Feature",
  "properties": {
    "iso:country":"ES",
    "sg:address":"Carrer de Valencia, 597",
    "sg:city":"Barcelona",
    "sg:orig_category":"Centros Empresariales",
    "sg:phone":"+34 932 65 77 07",
    "sg:postcode":"08026",
    "sg:province":"Barcelona",
    "sg:website":"www.proafi.es",
    "wof:name":"Profesionales De Actividades Fiscales S.l.",
    "wof:placetype":"venue"
},
  "geometry": {"coordinates":[2.1853039265,41.4093780518],"type":"Point"}
}