{
  "type": "Feature",
  "properties": {
    "addr:full":"Av Vives Llull, 115 Mao Islas Baleares 07703",
    "addr:housenumber":"115",
    "addr:postcode":"07703",
    "addr:street":"Av Vives Llull",
    "iso:country":"ES",
    "sg:address":"Av Vives Llull, 115",
    "sg:city":"Mao",
    "sg:orig_category":"Inmobiliaria (agencias)",
    "sg:phone":"+34 971 36 48 39",
    "sg:postcode":"07703",
    "sg:province":"Islas Baleares",
    "wof:name":"Fuca S.l.",
    "wof:placetype":"venue"
},
  "geometry": {"coordinates":[4.2533807755,39.8905220032],"type":"Point"}
}