{
  "type": "Feature",
  "properties": {
    "addr:full":"Pl Vila, 4 S. Adria Besos Barcelona 08930",
    "addr:housenumber":"4",
    "addr:postcode":"08930",
    "addr:street":"Pl Vila;Barcelona",
    "iso:country":"ES",
    "sg:address":"Pl Vila, 4",
    "sg:city":"S. Adria Besos",
    "sg:orig_category":"\u00d3ptica: Instrumentos (fabricaci\u00d3n)",
    "sg:phone":"+34 933 81 84 63",
    "sg:postcode":"08930",
    "sg:province":"Barcelona",
    "wof:name":"Llure Opticos S.l.",
    "wof:placetype":"venue"
},
  "geometry": {"coordinates":[2.2187950611,41.4310455322],"type":"Point"}
}