{
  "type": "Feature",
  "properties": {
    "iso:country":"ES",
    "sg:address":"Calle de Lopez De Hoyos, 145",
    "sg:city":"Madrid",
    "sg:orig_category":"Agencias Y Asesores De Publicidad",
    "sg:phone":"+34 914 56 44 00",
    "sg:postcode":"28...",
    "sg:province":"Madrid",
    "wof:name":"Ddb Madrid S.a.",
    "wof:placetype":"venue"
},
  "geometry": {"coordinates":[-3.6690990925,40.4477310181],"type":"Point"}
}