{
  "type": "Feature",
  "properties": {
    "addr:full":"Calle de Emilio Castelar, 3 Algeciras C\u00e1diz 11201",
    "addr:housenumber":"3;ca\u0301diz",
    "addr:postcode":"11201",
    "addr:street":"Calle De Emilio Castelar",
    "iso:country":"ES",
    "sg:address":"Calle de Emilio Castelar, 3",
    "sg:city":"Algeciras",
    "sg:orig_category":"M\u00c9dicos: Enfermedades De La Sangre (hematolog\u00cda)",
    "sg:phone":"+34 956 65 31 51",
    "sg:postcode":"11201",
    "sg:province":"C\u00e1diz",
    "wof:name":"Herederos Del Doctor Alarcon C.b.",
    "wof:placetype":"venue"
},
  "geometry": {"coordinates":[-5.4461297989,36.1291656494],"type":"Point"}
}