{
  "type": "Feature",
  "properties": {
    "iso:country":"ES",
    "sg:address":"Avda Parque (del), S/n",
    "sg:city":"Tres Cantos",
    "sg:orig_category":"Muebles, Minoristas",
    "sg:phone":"+34 918 03 27 79",
    "sg:postcode":"28760",
    "sg:province":"Madrid",
    "wof:name":"El Patio Grupo Empresarial S.l.",
    "wof:placetype":"venue"
},
  "geometry": {"coordinates":[-3.7136991024,40.6076087952],"type":"Point"}
}