{
  "type": "Feature",
  "properties": {
    "addr:full":"Calle de Higuera (la), S/n San Cristobal De La Laguna Santa Cruz De Tenerife 38202",
    "addr:housenumber":"/ n",
    "addr:postcode":"38202",
    "addr:street":"Calle De Higuera La S",
    "iso:country":"ES",
    "sg:address":"Calle de Higuera (la), S/n",
    "sg:city":"San Cristobal De La Laguna",
    "sg:orig_category":"Abogados",
    "sg:phone":"+34 922 25 90 70",
    "sg:postcode":"38202",
    "sg:province":"Santa Cruz De Tenerife",
    "wof:name":"Suarez Vega S.l",
    "wof:placetype":"venue"
},
  "geometry": {"coordinates":[-16.3201255798,28.4885959625],"type":"Point"}
}