{
  "type": "Feature",
  "properties": {
    "iso:country":"ES",
    "sg:address":"Bard Majaneque, 23",
    "sg:city":"Majaneque",
    "sg:orig_category":"Asociaciones, Organismos Culturales Y Socioeducativos",
    "sg:phone":"+34 957 32 80 24",
    "sg:postcode":"14193",
    "sg:province":"C\u00f3rdoba",
    "wof:name":"Asociacion Pe\u00f1a Cultural Caballo Al Andalus",
    "wof:placetype":"venue"
},
  "geometry": {"coordinates":[-4.8424720764,37.844078064],"type":"Point"}
}