{
  "type": "Feature",
  "properties": {
    "iso:country":"ES",
    "sg:address":"Avda Conde De Guadalhorce, 43",
    "sg:city":"Aviles",
    "sg:orig_category":"Empresas De Carpinter\u00cda De Madera",
    "sg:phone":"+34 985 52 22 96",
    "sg:postcode":"33401",
    "sg:province":"Asturias",
    "sg:website":"www.trescarp.com",
    "wof:name":"Carpinteria Trescarp S.l.",
    "wof:placetype":"venue"
},
  "geometry": {"coordinates":[-5.9222688675,43.5647697449],"type":"Point"}
}