{
  "type": "Feature",
  "properties": {
    "addr:full":"Rbla Rambla, 106 Sabadell Barcelona 08201",
    "addr:postcode":"08201",
    "addr:street":"Rambla 106",
    "iso:country":"ES",
    "sg:address":"Rbla Rambla, 106",
    "sg:city":"Sabadell",
    "sg:orig_category":"Estancos",
    "sg:phone":"+34 937 26 09 80",
    "sg:postcode":"08201",
    "sg:province":"Barcelona",
    "wof:name":"Torrens Alceda Agustin",
    "wof:placetype":"venue"
},
  "geometry": {"coordinates":[2.1103479862,41.5435562134],"type":"Point"}
}