{
  "type": "Feature",
  "properties": {
    "iso:country":"ES",
    "sg:address":"Carrer de Balmes, 232",
    "sg:city":"Barcelona",
    "sg:orig_category":"Agentes, Concesionarios Y Sucursales De Veh\u00cdculos",
    "sg:phone":"+34 932 17 77 97",
    "sg:postcode":"08006",
    "sg:province":"Barcelona",
    "sg:website":"www.acar-sa.com",
    "wof:name":"A-car S. A.",
    "wof:placetype":"venue"
},
  "geometry": {"coordinates":[2.1507642269,41.398979187],"type":"Point"}
}