{
  "type": "Feature",
  "properties": {
    "iso:country":"ES",
    "sg:address":"Calle de Plaza De Toros, 6",
    "sg:city":"Bargas",
    "sg:classifiers":[
        {
            "category":"Taxi",
            "type":"Transportation"
        }
    ],
    "sg:phone":"+34 925 35 70 78",
    "sg:postcode":"45593",
    "sg:province":"Toledo",
    "wof:name":"Gonzalez Diaz-villarejo Luis",
    "wof:placetype":"venue"
},
  "geometry": {"coordinates":[-4.0229067802,39.9379577637],"type":"Point"}
}