{
  "type": "Feature",
  "properties": {
    "iso:country":"ES",
    "sg:address":"Calle de Vasco Nu\u00d1ez, 2",
    "sg:city":"Badajoz",
    "sg:orig_category":"Ropa Para Se\u00d1oras Y Caballeros (al Por Menor)",
    "sg:phone":"+34 924 24 45 53",
    "sg:postcode":"06001",
    "sg:province":"Badajoz",
    "wof:name":"Urbano Cansado Alejandro",
    "wof:placetype":"venue"
},
  "geometry": {"coordinates":[-6.9731788635,38.877368927],"type":"Point"}
}