{
  "type": "Feature",
  "properties": {
    "addr:full":"E, 5 P. I. El Romeral Valencia 46340",
    "addr:housenumber":"5",
    "addr:postcode":"46340",
    "addr:street":"E;P. I. El",
    "iso:country":"ES",
    "sg:address":"E, 5",
    "sg:city":"P. I. El Romeral",
    "sg:orig_category":"Reciclaje, Desguace De Veh\u00cdculos",
    "sg:phone":"+34 962 30 46 75",
    "sg:postcode":"46340",
    "sg:province":"Valencia",
    "wof:name":"Auto Desguace Carmelo S.l.",
    "wof:placetype":"venue"
},
  "geometry": {"coordinates":[-1.1167860031,39.5035476685],"type":"Point"}
}