{
  "type": "Feature",
  "properties": {
    "iso:country":"ES",
    "sg:address":"Calle de Maria Diaz De Haro, 18",
    "sg:city":"Portugalete",
    "sg:orig_category":"Loter\u00cda Y T\u00d3mbola",
    "sg:phone":"+34 944 95 17 56",
    "sg:postcode":"48920",
    "sg:province":"Vizcaya",
    "wof:name":"Sevillano Gomez Isabel",
    "wof:placetype":"venue"
},
  "geometry": {"coordinates":[-3.0183160305,43.3228569031],"type":"Point"}
}