{
  "type": "Feature",
  "properties": {
    "addr:full":"Barr San Jose De Goikoa, 5 Erandio-goikoa Vizcaya 48950",
    "addr:housenumber":"5",
    "addr:postcode":"48950",
    "addr:street":"Jose;Goikoa",
    "iso:country":"ES",
    "sg:address":"Barr San Jose De Goikoa, 5",
    "sg:city":"Erandio-goikoa",
    "sg:orig_category":"Escaparatistas, Decoradores",
    "sg:phone":"+34 944 53 13 82",
    "sg:postcode":"48950",
    "sg:province":"Vizcaya",
    "wof:name":"Salcedo Puerta Ana Isabel",
    "wof:placetype":"venue"
},
  "geometry": {"coordinates":[-2.9509749413,43.3091506958],"type":"Point"}
}