{
  "type": "Feature",
  "properties": {
    "addr:full":"Calle de Carretas, 17 Motril Granada 18600",
    "addr:housenumber":"17",
    "addr:postcode":"18600",
    "addr:street":"Calle De Carretas",
    "iso:country":"ES",
    "sg:address":"Calle de Carretas, 17",
    "sg:city":"Motril",
    "sg:orig_category":"Abogados",
    "sg:phone":"+34 958 60 72 69",
    "sg:postcode":"18600",
    "sg:province":"Granada",
    "wof:name":"Perez Sanchez Jesus",
    "wof:placetype":"venue"
},
  "geometry": {"coordinates":[-3.5156335831,36.7477035522],"type":"Point"}
}