{
  "type": "Feature",
  "properties": {
    "addr:full":"Pg Gran Passeig Ronda, 122 Lleida Lleida 25008",
    "addr:housenumber":"122",
    "addr:postcode":"25008",
    "addr:street":"Pg Gran Passeig Ronda",
    "iso:country":"ES",
    "sg:address":"Pg Gran Passeig Ronda, 122",
    "sg:city":"Lleida",
    "sg:orig_category":"Ropa Y Accesorios",
    "sg:phone":"+34 973 22 50 01",
    "sg:postcode":"25008",
    "sg:province":"Lleida",
    "wof:name":"Jaborjabad S.l.",
    "wof:placetype":"venue"
},
  "geometry": {"coordinates":[0.6181849837,41.621673584],"type":"Point"}
}