{
  "type": "Feature",
  "properties": {
    "addr:full":"Avda Criptana, 18 Alcazar S. Juan Ciudad Real 13600",
    "addr:housenumber":"18",
    "addr:postcode":"13600",
    "addr:street":"Avda Criptana;Alcazar S. Juan Ciudad Real",
    "iso:country":"ES",
    "sg:address":"Avda Criptana, 18",
    "sg:city":"Alcazar S. Juan",
    "sg:orig_category":"Inform\u00c1tica (estudios, Servicios, Asesor\u00cda, Formaci\u00d3n)",
    "sg:phone":"+34 926 55 26 24",
    "sg:postcode":"13600",
    "sg:province":"Ciudad Real",
    "sg:website":"www.vivealcazar.com",
    "wof:name":"Reguillo Moreno",
    "wof:placetype":"venue"
},
  "geometry": {"coordinates":[-3.2058339119,39.3938064575],"type":"Point"}
}