{
  "type": "Feature",
  "properties": {
    "iso:country":"ES",
    "sg:address":"Carr Solana, 17",
    "sg:city":"Sentiu Sio",
    "sg:orig_category":"Arreglo, Reparaci\u00d3n, Piezas Sueltas De Televisi\u00d3n, V\u00cddeo, Hi",
    "sg:phone":"+34 973 42 40 17",
    "sg:postcode":"25617",
    "sg:province":"Lleida",
    "wof:name":"Batalla Merce Antonio",
    "wof:placetype":"venue"
},
  "geometry": {"coordinates":[0.8215039968,41.7888717651],"type":"Point"}
}