{
  "type": "Feature",
  "properties": {
    "addr:full":"Calle de San Clemente, 6 Madrid Madrid 28025",
    "addr:housenumber":"6",
    "addr:postcode":"28025",
    "addr:street":"Calle De San Clemente",
    "iso:country":"ES",
    "sg:address":"Calle de San Clemente, 6",
    "sg:city":"Madrid",
    "sg:orig_category":"Masajistas Kinesiterapeutas",
    "sg:phone":"+34 914 62 53 65",
    "sg:postcode":"28025",
    "sg:province":"Madrid",
    "wof:name":"Sanjuan Lopez-horcajuelos Maria Cruz",
    "wof:placetype":"venue"
},
  "geometry": {"coordinates":[-3.7315239906,40.3813095093],"type":"Point"}
}