{
  "type": "Feature",
  "properties": {
    "iso:country":"ES",
    "sg:address":"Avda Padre Isla, 11",
    "sg:city":"Le\u00f3n",
    "sg:orig_category":"Molduras, Junquillos, Listones Y Molduras Perforadas",
    "sg:phone":"+34 987 27 26 87",
    "sg:postcode":"24002",
    "sg:province":"Le\u00f3n",
    "wof:name":"Fernandez Bausela Geminiano",
    "wof:placetype":"venue"
},
  "geometry": {"coordinates":[-5.5728487968,42.5994300842],"type":"Point"}
}