{
  "type": "Feature",
  "properties": {
    "addr:full":"Calle de Huesca, 23 Madrid Madrid 28020",
    "addr:housenumber":"23",
    "addr:postcode":"madrid;28020",
    "addr:street":"Calle De Huesca",
    "iso:country":"ES",
    "sg:address":"Calle de Huesca, 23",
    "sg:city":"Madrid",
    "sg:orig_category":"Laboratorios Y Trabajos De Fotograf\u00cda, V\u00cddeo Y Cine",
    "sg:phone":"+34 915 71 43 14",
    "sg:postcode":"28020",
    "sg:province":"Madrid",
    "wof:name":"Copy-foto S.a.",
    "wof:placetype":"venue"
},
  "geometry": {"coordinates":[-3.6983399391,40.4580726624],"type":"Point"}
}