{
  "type": "Feature",
  "properties": {
    "iso:country":"ES",
    "sg:address":"Calle de Picos De Europa, 25",
    "sg:city":"Malaga",
    "sg:orig_category":"Maquinaria Y Herramientas Para Madera, Pvc, Aluminio Y Aperos (fabricaci\u00d3n, Comercio)",
    "sg:phone":"+34 952 29 25 85",
    "sg:postcode":"29018",
    "sg:province":"M\u00e1laga",
    "sg:website":"www.dentecno.com",
    "wof:name":"Dentecno S.l.",
    "wof:placetype":"venue"
},
  "geometry": {"coordinates":[-4.3545951843,36.724319458],"type":"Point"}
}