{
  "type": "Feature",
  "properties": {
    "iso:country":"ES",
    "sg:address":"Calle de Fray Juan De Zumarraga Kalea, 19",
    "sg:city":"Durango",
    "sg:orig_category":"Muebles Y Accesorios Para Cocinas Y Cuartos De Ba\u00d1o (al Por Menor)",
    "sg:phone":"+34 946 81 11 01",
    "sg:postcode":"48200",
    "sg:province":"Vizcaya",
    "sg:website":"www.paginas amarillas.es",
    "wof:name":"Larrabe Bilbao, S.l.",
    "wof:placetype":"venue"
},
  "geometry": {"coordinates":[-2.6371970177,43.1727981567],"type":"Point"}
}