{
  "type": "Feature",
  "properties": {
    "iso:country":"ES",
    "sg:address":"Calle de Salamanca, 25",
    "sg:city":"Valencia",
    "sg:orig_category":"Arquitectos",
    "sg:phone":"+34 963 34 60 37",
    "sg:postcode":"46005",
    "sg:province":"Valencia",
    "wof:name":"Martinez Escrig Francisco Miguel",
    "wof:placetype":"venue"
},
  "geometry": {"coordinates":[-0.3642480075,39.4664878845],"type":"Point"}
}