{
  "type": "Feature",
  "properties": {
    "addr:full":"Calle de Ercilla, 7 Bilbao Vizcaya 48009",
    "addr:housenumber":"7",
    "addr:postcode":"48009",
    "addr:street":"Calle De Ercilla",
    "iso:country":"ES",
    "sg:address":"Calle de Ercilla, 7",
    "sg:city":"Bilbao",
    "sg:orig_category":"Sociedades, Compa\u00d1\u00cdas Aseguradoras",
    "sg:phone":"+34 944 24 17 70",
    "sg:postcode":"48009",
    "sg:province":"Vizcaya",
    "sg:website":"www.seguroslagunaro.com",
    "wof:name":"Seguros Lagun Aro S.a.",
    "wof:placetype":"venue"
},
  "geometry": {"coordinates":[-2.9319159985,43.2642784119],"type":"Point"}
}