{
  "type": "Feature",
  "properties": {
    "iso:country":"ES",
    "sg:address":"Calle de Manuel Lerdo De Tejada, 37",
    "sg:city":"Ayamonte",
    "sg:classifiers":[
        {
            "category":"Personal",
            "subcategory":"Barber",
            "type":"Services"
        }
    ],
    "sg:phone":"+34 959 32 12 56",
    "sg:postcode":"21400",
    "sg:province":"Huelva",
    "sg:tags":[
        "caballeros",
        "de",
        "peluqueros"
    ],
    "wof:name":"Gomez Garcia Carlos Javier",
    "wof:placetype":"venue"
},
  "geometry": {"coordinates":[-7.4089541435,37.2168197632],"type":"Point"}
}