{
  "type": "Feature",
  "properties": {
    "iso:country":"ES",
    "sg:address":"Tafalla, 13",
    "sg:city":"Iru\u00f1a",
    "sg:orig_category":"Ropa Para Se\u00d1oras (al Por Menor)",
    "sg:phone":"+34 948 23 20 93",
    "sg:postcode":"31004",
    "sg:province":"Navarra",
    "wof:name":"Miguel Alonso Jose Luis De",
    "wof:placetype":"venue"
},
  "geometry": {"coordinates":[-1.6371289492,42.8121376038],"type":"Point"}
}