{
  "type": "Feature",
  "properties": {
    "iso:country":"ES",
    "sg:address":"Calle de Veracruz, 20",
    "sg:city":"Lucena",
    "sg:orig_category":"Lencer\u00cda Femenina, Corseter\u00cda, Trajes De Ba\u00d1o (al Por Menor)",
    "sg:phone":"+34 957 51 69 12",
    "sg:postcode":"14900",
    "sg:province":"C\u00f3rdoba",
    "wof:name":"Ca\u00f1ete Pineda Juan Antonio",
    "wof:placetype":"venue"
},
  "geometry": {"coordinates":[-4.4821667671,37.4096870422],"type":"Point"}
}