{
  "type": "Feature",
  "properties": {
    "iso:country":"ES",
    "sg:address":"Calle de Lerida, 8",
    "sg:city":"San Sebastian De Los Reyes",
    "sg:orig_category":"Guarder\u00cdas",
    "sg:phone":"+34 916 51 91 11",
    "sg:postcode":"28700",
    "sg:province":"Madrid",
    "wof:name":"Lazaro Caro Monserrat",
    "wof:placetype":"venue"
},
  "geometry": {"coordinates":[-3.638698101,40.5531044006],"type":"Point"}
}