{
  "type": "Feature",
  "properties": {
    "addr:full":"Calle de Esla, 7 Jerez De La Frontera C\u00e1diz 11405",
    "addr:housenumber":"7",
    "addr:postcode":"11405",
    "addr:street":"Calle De Esla",
    "iso:country":"ES",
    "sg:address":"Calle de Esla, 7",
    "sg:city":"Jerez De La Frontera",
    "sg:orig_category":"Chapister\u00cda",
    "sg:phone":"+34 956 33 01 88",
    "sg:postcode":"11405",
    "sg:province":"C\u00e1diz",
    "wof:name":"Mu\u00f1oz Garcia Diego",
    "wof:placetype":"venue"
},
  "geometry": {"coordinates":[-6.1064639091,36.6909065247],"type":"Point"}
}