{
  "type": "Feature",
  "properties": {
    "iso:country":"ES",
    "sg:address":"Carrer de Sevilla, 21",
    "sg:city":"Senia",
    "sg:orig_category":"Agencias Y Agentes Comerciales, Representantes",
    "sg:phone":"+34 977 57 00 73",
    "sg:postcode":"43560",
    "sg:province":"Tarragona",
    "wof:name":"Multiplo Di Carlo Pagano S.l.",
    "wof:placetype":"venue"
},
  "geometry": {"coordinates":[0.2847799957,40.6359901428],"type":"Point"}
}