{
  "type": "Feature",
  "properties": {
    "addr:full":"Calle de Santuario, 21 Valladolid Valladolid 47002",
    "addr:housenumber":"21",
    "addr:postcode":"47002",
    "addr:street":"Calle De Santuario",
    "iso:country":"ES",
    "sg:address":"Calle de Santuario, 21",
    "sg:city":"Valladolid",
    "sg:orig_category":"Molduras, Junquillos, Listones Y Molduras Perforadas",
    "sg:phone":"+34 983 20 44 45",
    "sg:postcode":"47002",
    "sg:province":"Valladolid",
    "wof:name":"Freyre Alvarez Jose Luis",
    "wof:placetype":"venue"
},
  "geometry": {"coordinates":[-4.7214097977,41.6497077942],"type":"Point"}
}