{
  "type": "Feature",
  "properties": {
    "addr:full":"Calle de Mayor-san Bartolome, 32 San Bartolome Alicante 03314",
    "addr:housenumber":"32",
    "addr:postcode":"03314",
    "addr:street":"Calle De Mayor-San Bartolome",
    "iso:country":"ES",
    "sg:address":"Calle de Mayor-san Bartolome, 32",
    "sg:city":"San Bartolome",
    "sg:orig_category":"Asesor\u00cda De Formaci\u00d3n Y Gesti\u00d3n De Personal",
    "sg:phone":"+34 965 36 70 06",
    "sg:postcode":"03314",
    "sg:province":"Alicante",
    "wof:name":"Asesoria Camara Rodriguez S.l.u.",
    "wof:placetype":"venue"
},
  "geometry": {"coordinates":[-0.8609601855,38.0937194824],"type":"Point"}
}