{
  "type": "Feature",
  "properties": {
    "iso:country":"ES",
    "sg:address":"Calle de Iturralde Kalea, 1",
    "sg:city":"Amurrio",
    "sg:orig_category":"Asociaciones, Organismos Culturales Y Socioeducativos",
    "sg:phone":"+34 945 89 24 37",
    "sg:postcode":"01470",
    "sg:province":"\u00c1lava",
    "wof:name":"Sociedad Recreativa Cultural Txokogorri",
    "wof:placetype":"venue"
},
  "geometry": {"coordinates":[-3.0016310215,43.0524902344],"type":"Point"}
}