{
  "type": "Feature",
  "properties": {
    "addr:full":"Lavandeira (pena), 2 Lavandeira Lugo 27160",
    "addr:housenumber":"2",
    "addr:postcode":"27160",
    "addr:street":"Pena",
    "iso:country":"ES",
    "sg:address":"Lavandeira (pena), 2",
    "sg:city":"Lavandeira",
    "sg:orig_category":"Agricultores, Agricultores",
    "sg:phone":"+34 982 30 45 30",
    "sg:postcode":"27160",
    "sg:province":"Lugo",
    "wof:name":"Ternera Gallega Arieiras S.l.",
    "wof:placetype":"venue"
},
  "geometry": {"coordinates":[-7.5056891441,42.970664978],"type":"Point"}
}