{
  "type": "Feature",
  "properties": {
    "addr:full":"Calle de Mateo Benigno De Moraza, 7 Vitoria-gasteiz \u00c1lava 01001",
    "addr:housenumber":"7",
    "addr:postcode":"01001",
    "addr:street":"Calle De Mateo Benigno De Moraza",
    "iso:country":"ES",
    "sg:address":"Calle de Mateo Benigno De Moraza, 7",
    "sg:city":"Vitoria-gasteiz",
    "sg:orig_category":"Art\u00cdculos De Regalo (al Por Menor)",
    "sg:phone":"+34 945 23 22 29",
    "sg:postcode":"01001",
    "sg:province":"\u00c1lava",
    "sg:website":"www.nonbait.com",
    "wof:name":"Santiago Salazar Rosario Isabel",
    "wof:placetype":"venue"
},
  "geometry": {"coordinates":[-2.6727609634,42.8471107483],"type":"Point"}
}