{
  "type": "Feature",
  "properties": {
    "addr:full":"Calle de Galan, 8 Salinas Asturias 33405",
    "addr:housenumber":"8",
    "addr:postcode":"33405",
    "addr:street":"Calle De Galan",
    "iso:country":"ES",
    "sg:address":"Calle de Galan, 8",
    "sg:city":"Salinas",
    "sg:orig_category":"Panader\u00cdas, Panader\u00cdas",
    "sg:phone":"+34 985 50 00 59",
    "sg:postcode":"33405",
    "sg:province":"Asturias",
    "wof:name":"Perez Galan Maria Luisa",
    "wof:placetype":"venue"
},
  "geometry": {"coordinates":[-5.9623703957,43.5758132935],"type":"Point"}
}