{
  "type": "Feature",
  "properties": {
    "iso:country":"ES",
    "sg:address":"Calle de Mosen Domingo Agudo, 38",
    "sg:city":"Zaragoza",
    "sg:orig_category":"Promotores Constructores",
    "sg:phone":"+34 976 51 27 40",
    "sg:postcode":"50015",
    "sg:province":"Zaragoza",
    "wof:name":"Construcciones Arevalo Zaragoza S.l.",
    "wof:placetype":"venue"
},
  "geometry": {"coordinates":[-0.8782680035,41.6622276306],"type":"Point"}
}