{
  "type": "Feature",
  "properties": {
    "iso:country":"ES",
    "sg:address":"Rua Progreso, S/n",
    "sg:city":"Sanxenxo",
    "sg:orig_category":"Quincaller\u00cda (al Por Menor)",
    "sg:phone":"+34 986 72 38 15",
    "sg:postcode":"36960",
    "sg:province":"Pontevedra",
    "wof:name":"Garcia Conde Manuel",
    "wof:placetype":"venue"
},
  "geometry": {"coordinates":[-8.8099403381,42.4041099548],"type":"Point"}
}