{
  "type": "Feature",
  "properties": {
    "iso:country":"ES",
    "sg:address":"Calle de Poligono Industrial, S/n",
    "sg:city":"Olvera",
    "sg:orig_category":"Negocio De Materiales De Construcci\u00d3n",
    "sg:phone":"+34 956 12 07 56",
    "sg:postcode":"11690",
    "sg:province":"C\u00e1diz",
    "wof:name":"Transportes Y Materiales Pruna S.l.",
    "wof:placetype":"venue"
},
  "geometry": {"coordinates":[-5.2556538582,36.9359931946],"type":"Point"}
}