{
  "type": "Feature",
  "properties": {
    "addr:full":"Calle de Europa, S/n Alcorcon Madrid 28922",
    "addr:housenumber":"s",
    "addr:postcode":"28922",
    "addr:street":"Calle De Europa;/ N Alcorcon",
    "iso:country":"ES",
    "sg:address":"Calle de Europa, S/n",
    "sg:city":"Alcorcon",
    "sg:orig_category":"Bisuter\u00cda, Joyer\u00cda, Relojer\u00cda (al Por Menor)",
    "sg:phone":"+34 916 89 00 41",
    "sg:postcode":"28922",
    "sg:province":"Madrid",
    "wof:name":"Argos Cue S.l.",
    "wof:placetype":"venue"
},
  "geometry": {"coordinates":[-3.8508262634,40.3481445312],"type":"Point"}
}