{
  "type": "Feature",
  "properties": {
    "addr:full":"Calle de Felipe Berge, 4 Alacant Alicante 03001",
    "addr:housenumber":"4",
    "addr:postcode":"03001",
    "addr:street":"Calle De Felipe Berge",
    "iso:country":"ES",
    "sg:address":"Calle de Felipe Berge, 4",
    "sg:city":"Alacant",
    "sg:orig_category":"Promotores Constructores",
    "sg:phone":"+34 965 21 62 82",
    "sg:postcode":"03001",
    "sg:province":"Alicante",
    "wof:name":"Akranova S.a.",
    "wof:placetype":"venue"
},
  "geometry": {"coordinates":[-0.487241298,38.345085144],"type":"Point"}
}