{
  "type": "Feature",
  "properties": {
    "addr:full":"Carretera Santander, Km. 0005,0 Villarrodrigo Regueras Le\u00f3n 24197",
    "addr:postcode":"24197",
    "addr:street":"Carretera Santander Km. 0005,0",
    "iso:country":"ES",
    "sg:address":"Carretera Santander, Km. 0005,0",
    "sg:city":"Villarrodrigo Regueras",
    "sg:orig_category":"Agentes, Concesionarios Y Sucursales De Veh\u00cdculos",
    "sg:phone":"+34 987 28 19 00",
    "sg:postcode":"24197",
    "sg:province":"Le\u00f3n",
    "sg:website":"www.paginasamarillas.es",
    "wof:name":"Aslemosa 4x4 S.l.",
    "wof:placetype":"venue"
},
  "geometry": {"coordinates":[-5.5407204628,42.6374320984],"type":"Point"}
}