{
  "type": "Feature",
  "properties": {
    "addr:full":"Ctra Hiniesta, 13 Zamora Zamora 49025",
    "addr:housenumber":"13",
    "addr:postcode":"49025",
    "addr:street":"Ctra Hiniesta",
    "iso:country":"ES",
    "sg:address":"Ctra Hiniesta, 13",
    "sg:city":"Zamora",
    "sg:orig_category":"Mec\u00c1nico Del Autom\u00d3vil",
    "sg:phone":"+34 980 53 34 13",
    "sg:postcode":"49025",
    "sg:province":"Zamora",
    "wof:name":"Abasolo Vi\u00f1uales Jesus",
    "wof:placetype":"venue"
},
  "geometry": {"coordinates":[-5.751235,41.508114],"type":"Point"}
}