{
  "type": "Feature",
  "properties": {
    "iso:country":"ES",
    "sg:address":"Calle de Parque, S/n",
    "sg:city":"San Cristobal De Entrevi\u00e7as",
    "sg:orig_category":"Bibliotecas, Mediatecas",
    "sg:phone":"+34 980 64 39 88",
    "sg:postcode":"49690",
    "sg:province":"Zamora",
    "wof:name":"Ayuntamiento De San Cristobal De Entrevi\u00f1as",
    "wof:placetype":"venue"
},
  "geometry": {"coordinates":[-5.6323919296,42.0469245911],"type":"Point"}
}