{
  "type": "Feature",
  "properties": {
    "addr:full":"Calle de Claustro (el), 7 Cifuentes Guadalajara 19420",
    "addr:housenumber":"7",
    "addr:postcode":"19420",
    "addr:street":"Calle De Claustro El",
    "iso:country":"ES",
    "sg:address":"Calle de Claustro (el), 7",
    "sg:city":"Cifuentes",
    "sg:orig_category":"Empresas De Desmonte",
    "sg:phone":"+34 949 81 10 34",
    "sg:postcode":"19420",
    "sg:province":"Guadalajara",
    "wof:name":"Batanero Garcia Miguel Angel",
    "wof:placetype":"venue"
},
  "geometry": {"coordinates":[-2.6234080791,40.786026001],"type":"Point"}
}