{
  "type": "Feature",
  "properties": {
    "addr:full":"Avda Fernandez Latorre, 25 Coru\u00d1a La Coru\u00f1a 15006",
    "addr:housenumber":"25",
    "addr:postcode":"15006",
    "addr:street":"Avda Fernandez Latorre;La Corun\u0303A",
    "iso:country":"ES",
    "sg:address":"Avda Fernandez Latorre, 25",
    "sg:city":"Coru\u00d1a",
    "sg:orig_category":"Electrodom\u00c9sticos (al Por Menor)",
    "sg:phone":"+34 981 24 50 16",
    "sg:postcode":"15006",
    "sg:province":"La Coru\u00f1a",
    "wof:name":"Candal Pardo Jose Manuel",
    "wof:placetype":"venue"
},
  "geometry": {"coordinates":[-8.4037399292,43.3591384888],"type":"Point"}
}