{
  "type": "Feature",
  "properties": {
    "iso:country":"ES",
    "sg:address":"Carr Traginers, 62",
    "sg:city":"Pobla",
    "sg:orig_category":"Agencias Y Agentes Comerciales, Representantes",
    "sg:phone":"+34 971 86 20 11",
    "sg:postcode":"07420",
    "sg:province":"Islas Baleares",
    "wof:name":"Kripsol Illes Balears S.l.",
    "wof:placetype":"venue"
},
  "geometry": {"coordinates":[3.025769949,39.7738304138],"type":"Point"}
}