{
  "type": "Feature",
  "properties": {
    "iso:country":"ES",
    "sg:address":"Calle de Anselmo Perez De Brito, 53",
    "sg:city":"Santa Cruz Palma",
    "sg:orig_category":"\u00d3pticos Optometristas (al Por Menor)",
    "sg:phone":"+34 922 42 01 23",
    "sg:postcode":"38700",
    "sg:province":"Santa Cruz De Tenerife",
    "wof:name":"Fernandez De La Cruz Efren Alejandro",
    "wof:placetype":"venue"
},
  "geometry": {"coordinates":[-17.7628116608,28.6852664948],"type":"Point"}
}