{
  "type": "Feature",
  "properties": {
    "addr:full":"Calle de Francisco Pacheco, 21 Malaga M\u00e1laga 29004",
    "addr:housenumber":"21",
    "addr:postcode":"29004",
    "addr:street":"Calle De Francisco Pacheco;Ma\u0301Laga",
    "iso:country":"ES",
    "sg:address":"Calle de Francisco Pacheco, 21",
    "sg:city":"Malaga",
    "sg:classifiers":[
        {
            "category":"Personal",
            "subcategory":"Barber",
            "type":"Services"
        }
    ],
    "sg:phone":"+34 952 17 33 58",
    "sg:postcode":"29004",
    "sg:province":"M\u00e1laga",
    "sg:tags":[
        "caballeros",
        "de",
        "peluqueros"
    ],
    "wof:name":"Cobos Figueroa Juan Bernardo",
    "wof:placetype":"venue"
},
  "geometry": {"coordinates":[-4.4493370056,36.6923522949],"type":"Point"}
}