{
  "type": "Feature",
  "properties": {
    "iso:country":"ES",
    "sg:address":"Carrer de Governador Gonzalez, 33",
    "sg:city":"Tarragona",
    "sg:orig_category":"Complementos De Vestir (al Por Menor)",
    "sg:phone":"+34 977 23 43 14",
    "sg:postcode":"43001",
    "sg:province":"Tarragona",
    "wof:name":"Ortiz Gomez Francisco",
    "wof:placetype":"venue"
},
  "geometry": {"coordinates":[1.2487030029,41.1163482666],"type":"Point"}
}