{
  "type": "Feature",
  "properties": {
    "addr:full":"Cami Vell De Canovellas, 9 Canovelles Barcelona 08420",
    "addr:housenumber":"9",
    "addr:postcode":"08420",
    "addr:street":"Cami Vell De Canovellas",
    "iso:country":"ES",
    "sg:address":"Cami Vell De Canovellas, 9",
    "sg:city":"Canovelles",
    "sg:orig_category":"Ropa De Hogar (al Por Menor)",
    "sg:phone":"+34 938 46 64 27",
    "sg:postcode":"08420",
    "sg:province":"Barcelona",
    "wof:name":"Ferrer Fernandez Jessica",
    "wof:placetype":"venue"
},
  "geometry": {"coordinates":[2.2828578949,41.6143760681],"type":"Point"}
}