{
  "type": "Feature",
  "properties": {
    "iso:country":"ES",
    "sg:address":"Cra. Nacional 230, Km. 0156,2",
    "sg:city":"Vielha",
    "sg:orig_category":"Ingenier\u00cda, Centros De Estudios (diversos)",
    "sg:phone":"+34 973 64 14 96",
    "sg:postcode":"25530",
    "sg:province":"Lleida",
    "wof:name":"Scrinser, S.a.",
    "wof:placetype":"venue"
},
  "geometry": {"coordinates":[0.793775022,42.70287323],"type":"Point"}
}