{
  "type": "Feature",
  "properties": {
    "iso:country":"ES",
    "sg:address":"Calle de San Pablo, 41",
    "sg:city":"Sevilla",
    "sg:orig_category":"Centros P\u00dablicos De Formaci\u00d3n Profesional Y T\u00c9cnica",
    "sg:phone":"+34 954 56 12 27",
    "sg:postcode":"41001",
    "sg:province":"Sevilla",
    "wof:name":"Colegio Oficial De Habilitados De Andalucia Occid.badajoz Y Canarias",
    "wof:placetype":"venue"
},
  "geometry": {"coordinates":[-5.9988808632,37.389705658],"type":"Point"}
}