{
  "type": "Feature",
  "properties": {
    "addr:full":"Cmno San Rafael, 2 Malaga M\u00e1laga 29006",
    "addr:housenumber":"2",
    "addr:postcode":"29006",
    "addr:street":"Cmno San Rafael;Ma\u0301Laga",
    "iso:country":"ES",
    "sg:address":"Cmno San Rafael, 2",
    "sg:city":"Malaga",
    "sg:orig_category":"Bisuter\u00cda, Joyer\u00cda, Relojer\u00cda (al Por Menor)",
    "sg:phone":"+34 952 32 12 37",
    "sg:postcode":"29006",
    "sg:province":"M\u00e1laga",
    "wof:name":"Cuenca Reyes Manuel",
    "wof:placetype":"venue"
},
  "geometry": {"coordinates":[-4.4414820671,36.7118682861],"type":"Point"}
}