{
  "type": "Feature",
  "properties": {
    "iso:country":"ES",
    "sg:address":"Rua C, S/n",
    "sg:city":"Barreiros",
    "sg:orig_category":"Congelados: Productos Alimentarios (fabricaci\u00d3n, Al Por Mayor)",
    "sg:phone":"+34 988 36 40 47",
    "sg:postcode":"32910",
    "sg:province":"Ourense",
    "wof:name":"Pesfrigo S.l.l.",
    "wof:placetype":"venue"
},
  "geometry": {"coordinates":[-7.8773641586,42.2747917175],"type":"Point"}
}