{
  "type": "Feature",
  "properties": {
    "iso:country":"ES",
    "sg:address":"Calle de Virgen Del Remedio, 5",
    "sg:city":"Novelda",
    "sg:orig_category":"Bares, Piano",
    "sg:phone":"+34 965 60 23 43",
    "sg:postcode":"03660",
    "sg:province":"Alicante",
    "wof:name":"Disco Pub Vendetta S.l.",
    "wof:placetype":"venue"
},
  "geometry": {"coordinates":[-0.7674239874,38.3812141418],"type":"Point"}
}