{
  "type": "Feature",
  "properties": {
    "addr:full":"Plaz Constitucion, 10 Pe\u00e7aranda De Bracamonte Salamanca 37300",
    "addr:housenumber":"10",
    "addr:postcode":"37300",
    "addr:street":"Constitucion",
    "iso:country":"ES",
    "sg:address":"Plaz Constitucion, 10",
    "sg:city":"Pe\u00e7aranda De Bracamonte",
    "sg:orig_category":"Art\u00cdculos De Regalo (al Por Menor)",
    "sg:phone":"+34 923 54 05 29",
    "sg:postcode":"37300",
    "sg:province":"Salamanca",
    "wof:name":"Padin Regalos S.l.",
    "wof:placetype":"venue"
},
  "geometry": {"coordinates":[-5.2017068863,40.9006233215],"type":"Point"}
}