{
  "type": "Feature",
  "properties": {
    "iso:country":"ES",
    "sg:address":"Pl Major, 1",
    "sg:city":"Riera Gaia",
    "sg:orig_category":"Centros De Educaci\u00d3n Especial",
    "sg:phone":"+34 977 65 50 00",
    "sg:postcode":"43762",
    "sg:province":"Tarragona",
    "wof:name":"Ajuntament De La Riera De Gaia",
    "wof:placetype":"venue"
},
  "geometry": {"coordinates":[1.3688212633,41.1448936462],"type":"Point"}
}