{
  "type": "Feature",
  "properties": {
    "addr:full":"Calle de Carlos Sole, 45 Madrid Madrid 28038",
    "addr:housenumber":"45",
    "addr:postcode":"madrid;28038",
    "addr:street":"Calle De Carlos Sole",
    "iso:country":"ES",
    "sg:address":"Calle de Carlos Sole, 45",
    "sg:city":"Madrid",
    "sg:orig_category":"Chapister\u00cda",
    "sg:phone":"+34 913 03 03 65",
    "sg:postcode":"28038",
    "sg:province":"Madrid",
    "wof:name":"Llanos Rebollo Santiago",
    "wof:placetype":"venue"
},
  "geometry": {"coordinates":[-3.6477050781,40.3918609619],"type":"Point"}
}