{
  "type": "Feature",
  "properties": {
    "addr:full":"Calle de Compositor Lehmberg Ruiz, 6 Malaga M\u00e1laga 29007",
    "addr:housenumber":"6",
    "addr:postcode":"29007",
    "addr:street":"Calle De Compositor Lehmberg Ruiz;Ma\u0301Laga",
    "iso:country":"ES",
    "sg:address":"Calle de Compositor Lehmberg Ruiz, 6",
    "sg:city":"Malaga",
    "sg:orig_category":"Centros Empresariales",
    "sg:phone":"+34 952 07 06 23",
    "sg:postcode":"29007",
    "sg:province":"M\u00e1laga",
    "wof:name":"Confederacion Empresarial Malague\u00f1a",
    "wof:placetype":"venue"
},
  "geometry": {"coordinates":[-4.4317989349,36.7178573608],"type":"Point"}
}