{
  "type": "Feature",
  "properties": {
    "addr:full":"Ctra Pulianas, 10 Pulianillas Granada 18197",
    "addr:housenumber":"10",
    "addr:postcode":"18197",
    "addr:street":"Ctra Pulianas",
    "iso:country":"ES",
    "sg:address":"Ctra Pulianas, 10",
    "sg:city":"Pulianillas",
    "sg:orig_category":"Empresas De Carpinter\u00cda Met\u00c1lica",
    "sg:phone":"+34 958 15 09 64",
    "sg:postcode":"18197",
    "sg:province":"Granada",
    "wof:name":"Talleres Mecanicos Ontiveros S.a.",
    "wof:placetype":"venue"
},
  "geometry": {"coordinates":[-3.6097240448,37.2210998535],"type":"Point"}
}