{
  "type": "Feature",
  "properties": {
    "addr:full":"Carrer de Andorra, 53 S. Boi Llobregat Barcelona 08830",
    "addr:housenumber":"53",
    "addr:postcode":"08830",
    "addr:street":"Carrer De Andorra",
    "iso:country":"ES",
    "sg:address":"Carrer de Andorra, 53",
    "sg:city":"S. Boi Llobregat",
    "sg:orig_category":"Elementos Para Suelos Prefabricados",
    "sg:phone":"+34 936 52 55 45",
    "sg:postcode":"08830",
    "sg:province":"Barcelona",
    "wof:name":"Parkestil Sociedad Cooperativa Limitada",
    "wof:placetype":"venue"
},
  "geometry": {"coordinates":[2.0449779034,41.3480606079],"type":"Point"}
}