{
  "type": "Feature",
  "properties": {
    "iso:country":"ES",
    "sg:address":"Carrer de Can Cuyas, 60",
    "sg:city":"Can Cuias",
    "sg:orig_category":"Materias Pl\u00c1sticas: Art\u00cdculos Para La Industria",
    "sg:phone":"+34 935 75 26 30",
    "sg:postcode":"08110",
    "sg:province":"Barcelona",
    "wof:name":"Suminco S. A.",
    "wof:placetype":"venue"
},
  "geometry": {"coordinates":[2.1817660332,41.4890899658],"type":"Point"}
}