{
  "type": "Feature",
  "properties": {
    "addr:full":"Calle de Oso, 10 Jerez De La Frontera C\u00e1diz 11405",
    "addr:housenumber":"10",
    "addr:postcode":"11405",
    "addr:street":"Calle De Oso",
    "iso:country":"ES",
    "sg:address":"Calle de Oso, 10",
    "sg:city":"Jerez De La Frontera",
    "sg:orig_category":"Mantenimiento Y Limpieza De Carreteras",
    "sg:phone":"+34 956 18 21 01",
    "sg:postcode":"11405",
    "sg:province":"C\u00e1diz",
    "wof:name":"Union De Limpiezas S.l.",
    "wof:placetype":"venue"
},
  "geometry": {"coordinates":[-6.1258268356,36.6899147034],"type":"Point"}
}