{
  "type": "Feature",
  "properties": {
    "addr:full":"Carrer de Envalira, 16 Cunit Tarragona 43881",
    "addr:housenumber":"16",
    "addr:postcode":"43881",
    "addr:street":"Carrer De Envalira",
    "iso:country":"ES",
    "sg:address":"Carrer de Envalira, 16",
    "sg:city":"Cunit",
    "sg:orig_category":"Empresas De Vigilancia, Guardia Y Protecci\u00d3n",
    "sg:phone":"+34 977 16 39 73",
    "sg:postcode":"43881",
    "sg:province":"Tarragona",
    "wof:name":"De Jesus Martin Hinojal Teresa",
    "wof:placetype":"venue"
},
  "geometry": {"coordinates":[1.616664052,41.2079277039],"type":"Point"}
}