{
  "type": "Feature",
  "properties": {
    "addr:full":"Avda Cid Campeador, 14 Burgos Burgos 09005",
    "addr:housenumber":"14",
    "addr:postcode":"09005",
    "addr:street":"Avda Cid Campeador",
    "iso:country":"ES",
    "sg:address":"Avda Cid Campeador, 14",
    "sg:city":"Burgos",
    "sg:orig_category":"Mutuas De Seguros",
    "sg:phone":"+34 947 27 90 63",
    "sg:postcode":"09005",
    "sg:province":"Burgos",
    "wof:name":"Fraternidad-muprespa Mutua De Accidentes De Trabajo Y Enfermedades Profesionales",
    "wof:placetype":"venue"
},
  "geometry": {"coordinates":[-3.6980009079,42.3451805115],"type":"Point"}
}