{
  "type": "Feature",
  "properties": {
    "addr:full":"Avda Justo Del Castillo Y Quintana, S/n Gijon Asturias 33203",
    "addr:housenumber":"s",
    "addr:postcode":"33203",
    "addr:street":"Avda Justo Del Castillo Y Quintana;/ N",
    "iso:country":"ES",
    "sg:address":"Avda Justo Del Castillo Y Quintana, S/n",
    "sg:city":"Gijon",
    "sg:orig_category":"Contenedores (mercanc\u00cdas)",
    "sg:phone":"+34 985 13 10 36",
    "sg:postcode":"33203",
    "sg:province":"Asturias",
    "wof:name":"Ute Atg",
    "wof:placetype":"venue"
},
  "geometry": {"coordinates":[-5.6349987984,43.5281105042],"type":"Point"}
}