{
  "type": "Feature",
  "properties": {
    "addr:full":"Calle de Latina, 4 Malaga M\u00e1laga 29006",
    "addr:housenumber":"4",
    "addr:postcode":"29006",
    "addr:street":"Calle De Latina;Ma\u0301Laga",
    "iso:country":"ES",
    "sg:address":"Calle de Latina, 4",
    "sg:city":"Malaga",
    "sg:orig_category":"Materias Pl\u00c1sticas: Productos De Consumo Masivo (fabricaci\u00d3n, Al Por Mayor)",
    "sg:phone":"+34 952 34 55 00",
    "sg:postcode":"29006",
    "sg:province":"M\u00e1laga",
    "wof:name":"Bolpla S.a.",
    "wof:placetype":"venue"
},
  "geometry": {"coordinates":[-4.4773840904,36.710975647],"type":"Point"}
}