{
  "type": "Feature",
  "properties": {
    "iso:country":"ES",
    "sg:address":"P Ind Risco Prieto, S/n",
    "sg:city":"Pto. Rosario",
    "sg:orig_category":"Construcciones Prefabricadas Y Desmontables",
    "sg:phone":"+34 928 85 50 21",
    "sg:postcode":"35600",
    "sg:province":"Las Palmas",
    "wof:name":"Prefabricados La Antigua S.l.",
    "wof:placetype":"venue"
},
  "geometry": {"coordinates":[-13.8644685745,28.5023498535],"type":"Point"}
}