{
  "type": "Feature",
  "properties": {
    "addr:full":"Calle de Cortelazor, 5 Huelva Huelva 21007",
    "addr:housenumber":"5",
    "addr:postcode":"21007",
    "addr:street":"Calle De Cortelazor",
    "iso:country":"ES",
    "sg:address":"Calle de Cortelazor, 5",
    "sg:city":"Huelva",
    "sg:orig_category":"Sociedades, Compa\u00d1\u00cdas Aseguradoras",
    "sg:phone":"+34 959 23 73 67",
    "sg:postcode":"21007",
    "sg:province":"Huelva",
    "wof:name":"Perintasa S.l.",
    "wof:placetype":"venue"
},
  "geometry": {"coordinates":[-6.9357819557,37.2557754517],"type":"Point"}
}