{
  "type": "Feature",
  "properties": {
    "addr:full":"Los Ballesteros, 16 Pilar Horadada Alicante 03190",
    "addr:housenumber":"16",
    "addr:postcode":"03190",
    "addr:street":"Los Ballesteros",
    "iso:country":"ES",
    "sg:address":"Los Ballesteros, 16",
    "sg:city":"Pilar Horadada",
    "sg:orig_category":"Agencias Y Agentes Comerciales, Representantes",
    "sg:phone":"+34 966 76 71 11",
    "sg:postcode":"03190",
    "sg:province":"Alicante",
    "wof:name":"Pilartrans S.l.",
    "wof:placetype":"venue"
},
  "geometry": {"coordinates":[-0.7898390293,37.8640213013],"type":"Point"}
}