{
  "type": "Feature",
  "properties": {
    "iso:country":"ES",
    "sg:address":"Avda Jose Luis Goyoaga, 8",
    "sg:city":"Altzaga",
    "sg:orig_category":"Inmobiliaria (agencias)",
    "sg:phone":"+34 944 17 10 45",
    "sg:postcode":"48950",
    "sg:province":"Vizcaya",
    "wof:name":"Comunidad De Propietarios Jose Luis Goyoaga,8",
    "wof:placetype":"venue"
},
  "geometry": {"coordinates":[-2.975933075,43.3000831604],"type":"Point"}
}