{
  "type": "Feature",
  "properties": {
    "iso:country":"ES",
    "sg:address":"Calle de Alcalde Lens, 35",
    "sg:city":"Coru\u00d1a",
    "sg:orig_category":"Abogados",
    "sg:phone":"+34 981 27 97 50",
    "sg:postcode":"15010",
    "sg:province":"La Coru\u00f1a",
    "wof:name":"Garcia Sanchez Lucia Maria",
    "wof:placetype":"venue"
},
  "geometry": {"coordinates":[-8.4202737808,43.3602180481],"type":"Point"}
}