{
  "type": "Feature",
  "properties": {
    "addr:full":"Monasterio Urdax, 6 Iru\u00f1a Navarra 31007",
    "addr:housenumber":"6",
    "addr:postcode":"31007",
    "addr:street":"Urdax",
    "iso:country":"ES",
    "sg:address":"Monasterio Urdax, 6",
    "sg:city":"Iru\u00f1a",
    "sg:orig_category":"Institutos De Belleza",
    "sg:phone":"+34 948 26 15 67",
    "sg:postcode":"31007",
    "sg:province":"Navarra",
    "wof:name":"Garciandia Flores Maria Aranzazu Y Maria Rosario S.cv.",
    "wof:placetype":"venue"
},
  "geometry": {"coordinates":[-1.6543678045,42.8107528687],"type":"Point"}
}