{
  "type": "Feature",
  "properties": {
    "addr:full":"Carrer de Miami, 2 Reus Tarragona 43205",
    "addr:housenumber":"2",
    "addr:postcode":"43205",
    "addr:street":"Carrer De Miami",
    "iso:country":"ES",
    "sg:address":"Carrer de Miami, 2",
    "sg:city":"Reus",
    "sg:orig_category":"Inform\u00c1tica, Ofim\u00c1tica (estudios, Asesor\u00cda, Ingenier\u00cda, Formaci\u00d3n)",
    "sg:phone":"+34 977 75 41 19",
    "sg:postcode":"43205",
    "sg:province":"Tarragona",
    "sg:website":"www.pctelecos.com",
    "wof:name":"Pc Telecos Reus S.l.",
    "wof:placetype":"venue"
},
  "geometry": {"coordinates":[1.1038689613,41.1470680237],"type":"Point"}
}