{
  "type": "Feature",
  "properties": {
    "iso:country":"ES",
    "sg:address":"Carrer de Germa Joaquim, 133",
    "sg:city":"Terrassa",
    "sg:orig_category":"Cer\u00c1micas: Material Y Suministros",
    "sg:phone":"+34 937 85 72 38",
    "sg:postcode":"08223",
    "sg:province":"Barcelona",
    "wof:name":"Sanitarios Can Palet S.l.",
    "wof:placetype":"venue"
},
  "geometry": {"coordinates":[2.0223600864,41.551738739],"type":"Point"}
}