{
  "type": "Feature",
  "properties": {
    "iso:country":"ES",
    "sg:address":"Calle de Maravedi, 4",
    "sg:city":"Sevilla",
    "sg:orig_category":"Audiovisuales: Material Y Accesorios (al Por Menor)",
    "sg:phone":"+34 954 25 32 42",
    "sg:postcode":"41006",
    "sg:province":"Sevilla",
    "wof:name":"Focus Point Ingenieria De Medios Audio Visuales S.l.",
    "wof:placetype":"venue"
},
  "geometry": {"coordinates":[-5.9493541718,37.3862419128],"type":"Point"}
}