{
  "type": "Feature",
  "properties": {
    "iso:country":"ES",
    "sg:address":"Urb. Pline, S/n",
    "sg:city":"Loja",
    "sg:orig_category":"Ense\u00d1anza Variada",
    "sg:phone":"+34 958 32 70 46",
    "sg:postcode":"18300",
    "sg:province":"Granada",
    "wof:name":"Academia Numero Uno S.l.",
    "wof:placetype":"venue"
},
  "geometry": {"coordinates":[-4.1718540192,37.1597938538],"type":"Point"}
}