{
  "type": "Feature",
  "properties": {
    "iso:country":"ES",
    "sg:address":"Plaz Isabel Ii, 3",
    "sg:city":"Albacete",
    "sg:orig_category":"Bisuter\u00cda, Joyer\u00cda, Relojer\u00cda (al Por Menor)",
    "sg:phone":"+34 967 50 19 25",
    "sg:postcode":"02005",
    "sg:province":"Albacete",
    "wof:name":"Francisco Ponce Lopez Y Otros Cdad",
    "wof:placetype":"venue"
},
  "geometry": {"coordinates":[-1.8614230156,39.0000076294],"type":"Point"}
}