{
  "type": "Feature",
  "properties": {
    "addr:full":"Avda Jose Rios Gil, S/n Cieza Murcia 30530",
    "addr:housenumber":"/ n",
    "addr:postcode":"30530",
    "addr:street":"Avda Jose Rios Gil S",
    "iso:country":"ES",
    "sg:address":"Avda Jose Rios Gil, S/n",
    "sg:city":"Cieza",
    "sg:orig_category":"Electricidad: Instaladores",
    "sg:phone":"+34 968 76 16 17",
    "sg:postcode":"30530",
    "sg:province":"Murcia",
    "wof:name":"Instalaciones Electricas Angel S.l",
    "wof:placetype":"venue"
},
  "geometry": {"coordinates":[-1.4113390446,38.2354507446],"type":"Point"}
}