{
  "type": "Feature",
  "properties": {
    "addr:full":"Carrer de Industria, 298 Barcelona Barcelona 08026",
    "addr:housenumber":"298",
    "addr:postcode":"08026",
    "addr:street":"Carrer De Industria",
    "iso:country":"ES",
    "sg:address":"Carrer de Industria, 298",
    "sg:city":"Barcelona",
    "sg:orig_category":"Cl\u00cdnicas Dentales",
    "sg:phone":"+34 933 47 46 75",
    "sg:postcode":"08026",
    "sg:province":"Barcelona",
    "wof:name":"Centre Medic Dental Sant Jordi S. L.",
    "wof:placetype":"venue"
},
  "geometry": {"coordinates":[2.1813189983,41.4147605896],"type":"Point"}
}