{
  "type": "Feature",
  "properties": {
    "addr:full":"Calle de Emilio Castelar, 33 Ecija Sevilla 41400",
    "addr:housenumber":"33",
    "addr:postcode":"41400",
    "addr:street":"Calle De Emilio Castelar",
    "iso:country":"ES",
    "sg:address":"Calle de Emilio Castelar, 33",
    "sg:city":"Ecija",
    "sg:orig_category":"Promotores Constructores",
    "sg:phone":"+34 954 83 10 00",
    "sg:postcode":"41400",
    "sg:province":"Sevilla",
    "wof:name":"Ramos Cabrera Juan",
    "wof:placetype":"venue"
},
  "geometry": {"coordinates":[-5.0774388313,37.5408287048],"type":"Point"}
}