{
  "type": "Feature",
  "properties": {
    "addr:full":"Reboredo, 12 Noalla Ourense 32901",
    "addr:housenumber":"12",
    "addr:postcode":"32901",
    "addr:street":"Reboredo",
    "iso:country":"ES",
    "sg:address":"Reboredo, 12",
    "sg:city":"Noalla",
    "sg:orig_category":"Mec\u00c1nico Del Autom\u00d3vil",
    "sg:phone":"+34 988 25 15 13",
    "sg:postcode":"32901",
    "sg:province":"Ourense",
    "wof:name":"Iglesias Camba Carlos",
    "wof:placetype":"venue"
},
  "geometry": {"coordinates":[-7.8334488869,42.2905006409],"type":"Point"}
}