{
  "type": "Feature",
  "properties": {
    "addr:full":"Crril Molina Nelva, 57 Puente Tocinos Murcia 30007",
    "addr:housenumber":"57",
    "addr:postcode":"30007",
    "addr:street":"Crril Molina Nelva",
    "iso:country":"ES",
    "sg:address":"Crril Molina Nelva, 57",
    "sg:city":"Puente Tocinos",
    "sg:orig_category":"Discotecas Y Salas De Baile",
    "sg:phone":"+34 968 20 29 43",
    "sg:postcode":"30007",
    "sg:province":"Murcia",
    "wof:name":"Exagono Murcia S.l.",
    "wof:placetype":"venue"
},
  "geometry": {"coordinates":[-1.1142389774,37.9970092773],"type":"Point"}
}