{
  "type": "Feature",
  "properties": {
    "addr:full":"Carrer de Torrent D'en Vidalet, 80 Barcelona Barcelona 08024",
    "addr:housenumber":"80",
    "addr:postcode":"08024",
    "addr:street":"Carrer De Torrent D'En Vidalet",
    "iso:country":"ES",
    "sg:address":"Carrer de Torrent D'en Vidalet, 80",
    "sg:city":"Barcelona",
    "sg:orig_category":"Electrodom\u00c9sticos (fabricaci\u00d3n, Al Por Mayor)",
    "sg:phone":"+34 902 15 33 20",
    "sg:postcode":"08024",
    "sg:province":"Barcelona",
    "sg:website":"www.gamor.net",
    "wof:name":"Productos Olmar S.a.",
    "wof:placetype":"venue"
},
  "geometry": {"coordinates":[2.1577849388,41.4054260254],"type":"Point"}
}