{
  "type": "Feature",
  "properties": {
    "addr:full":"Irunlarrea, 51 Iru\u00f1a Navarra 31008",
    "addr:housenumber":"51",
    "addr:postcode":"31008",
    "addr:street":"Irunlarrea",
    "iso:country":"ES",
    "sg:address":"Irunlarrea, 51",
    "sg:city":"Iru\u00f1a",
    "sg:orig_category":"Artes Gr\u00c1ficas, Artes Pl\u00c1sticas (curso)",
    "sg:phone":"+34 948 26 62 69",
    "sg:postcode":"31008",
    "sg:province":"Navarra",
    "wof:name":"Sara Perez Angel Maria",
    "wof:placetype":"venue"
},
  "geometry": {"coordinates":[-1.6734009981,42.8107833862],"type":"Point"}
}