{
  "type": "Feature",
  "properties": {
    "iso:country":"ES",
    "sg:address":"Calle de Linares, 8",
    "sg:city":"Cercedilla",
    "sg:orig_category":"Ingeniero",
    "sg:phone":"+34 918 52 39 27",
    "sg:postcode":"28470",
    "sg:province":"Madrid",
    "wof:name":"Aralar Cartografia S.l.",
    "wof:placetype":"venue"
},
  "geometry": {"coordinates":[-4.0583176613,40.735408783],"type":"Point"}
}