{
  "type": "Feature",
  "properties": {
    "addr:full":"Calle de San Mariano, 5 Madrid Madrid 28022",
    "addr:housenumber":"5",
    "addr:postcode":"28022",
    "addr:street":"Calle De San Mariano",
    "iso:country":"ES",
    "sg:address":"Calle de San Mariano, 5",
    "sg:city":"Madrid",
    "sg:orig_category":"Ropa Para Se\u00d1oras Y Caballeros (al Por Menor)",
    "sg:phone":"+34 913 20 18 26",
    "sg:postcode":"28022",
    "sg:province":"Madrid",
    "wof:name":"Piriz Cuadrado Juan Carlos",
    "wof:placetype":"venue"
},
  "geometry": {"coordinates":[-3.6136898994,40.4448471069],"type":"Point"}
}