{
  "type": "Feature",
  "properties": {
    "iso:country":"ES",
    "sg:address":"Urb. Abanico Plentzia, 44",
    "sg:city":"Isuskitza",
    "sg:orig_category":"Ropa Para Se\u00d1oras (al Por Menor)",
    "sg:phone":"+34 946 77 29 40",
    "sg:postcode":"48620",
    "sg:province":"Vizcaya",
    "wof:name":"Inracne S.l.",
    "wof:placetype":"venue"
},
  "geometry": {"coordinates":[-2.9458739758,43.4066467285],"type":"Point"}
}