{
  "type": "Feature",
  "properties": {
    "iso:country":"ES",
    "sg:address":"Reyes Catolicos, 104",
    "sg:city":"Dos Hermanas",
    "sg:orig_category":"Inmobiliaria (agencias)",
    "sg:phone":"+34 955 67 80 34",
    "sg:postcode":"41700",
    "sg:province":"Sevilla",
    "wof:name":"Gestion Fiscal Sur S.l.",
    "wof:placetype":"venue"
},
  "geometry": {"coordinates":[-5.9268941879,37.276512146],"type":"Point"}
}