{
  "type": "Feature",
  "properties": {
    "addr:full":"Calle de General Manuel Saavedra Palmeiro, 4 Badajoz Badajoz 06004",
    "addr:housenumber":"4",
    "addr:postcode":"06004",
    "addr:street":"Calle De General Manuel Saavedra Palmeiro",
    "iso:country":"ES",
    "sg:address":"Calle de General Manuel Saavedra Palmeiro, 4",
    "sg:city":"Badajoz",
    "sg:orig_category":"Lencer\u00cda Femenina, Corseter\u00cda, Trajes De Ba\u00d1o (al Por Menor)",
    "sg:phone":"+34 924 26 16 12",
    "sg:postcode":"06004",
    "sg:province":"Badajoz",
    "wof:name":"Gonzalez Hurtado Isabel",
    "wof:placetype":"venue"
},
  "geometry": {"coordinates":[-6.9755992889,38.8719711304],"type":"Point"}
}