{
  "type": "Feature",
  "properties": {
    "addr:full":"Avda Llano Castellano, 5 Madrid Madrid 28034",
    "addr:housenumber":"5",
    "addr:postcode":"28034",
    "addr:street":"Avda Llano Castellano",
    "iso:country":"ES",
    "sg:address":"Avda Llano Castellano, 5",
    "sg:city":"Madrid",
    "sg:orig_category":"Comadronas",
    "sg:phone":"+34 913 58 29 33",
    "sg:postcode":"28034",
    "sg:province":"Madrid",
    "wof:name":"Heras Pacheco Fe De Las",
    "wof:placetype":"venue"
},
  "geometry": {"coordinates":[-3.6845140457,40.4836807251],"type":"Point"}
}