{
  "type": "Feature",
  "properties": {
    "iso:country":"ES",
    "sg:address":"Avda Malvarrosa, 27",
    "sg:city":"Valencia",
    "sg:orig_category":"Juegos Y Juguetes (al Por Menor)",
    "sg:phone":"+34 963 71 88 29",
    "sg:postcode":"46011",
    "sg:province":"Valencia",
    "wof:name":"Navarro Gomez Juan",
    "wof:placetype":"venue"
},
  "geometry": {"coordinates":[-0.3281440139,39.476852417],"type":"Point"}
}