{
  "type": "Feature",
  "properties": {
    "addr:full":"Avda Castrelos, 401 Vigo Pontevedra 36213",
    "addr:housenumber":"401",
    "addr:postcode":"36213",
    "addr:street":"Avda Castrelos",
    "iso:country":"ES",
    "sg:address":"Avda Castrelos, 401",
    "sg:city":"Vigo",
    "sg:orig_category":"Transporte En General",
    "sg:phone":"+34 986 46 81 17",
    "sg:postcode":"36213",
    "sg:province":"Pontevedra",
    "wof:name":"Rebolo Eiras S.l.",
    "wof:placetype":"venue"
},
  "geometry": {"coordinates":[-8.7207965851,42.1945991516],"type":"Point"}
}