{
  "type": "Feature",
  "properties": {
    "iso:country":"ES",
    "sg:address":"Avda Peregrina, 15",
    "sg:city":"Bertamirans",
    "sg:orig_category":"Ense\u00d1anza Variada",
    "sg:phone":"+34 981 88 34 35",
    "sg:postcode":"15220",
    "sg:province":"La Coru\u00f1a",
    "wof:name":"Academia De Ense\u00f1anza De Galicia S.l.",
    "wof:placetype":"venue"
},
  "geometry": {"coordinates":[-8.65216,42.862019],"type":"Point"}
}