{
  "type": "Feature",
  "properties": {
    "iso:country":"ES",
    "sg:address":"Carrer de Rocafort, 130",
    "sg:city":"Barcelona",
    "sg:orig_category":"Cervecer\u00cdas",
    "sg:phone":"+34 934 26 03 07",
    "sg:postcode":"08015",
    "sg:province":"Barcelona",
    "wof:name":"Las Tres Erres S.c.p.",
    "wof:placetype":"venue"
},
  "geometry": {"coordinates":[2.1508250237,41.3813552856],"type":"Point"}
}