{
  "type": "Feature",
  "properties": {
    "addr:full":"Pl Oliveres, 2 Valldoreix Barcelona 08197",
    "addr:housenumber":"2",
    "addr:postcode":"08197",
    "addr:street":"Pl Oliveres;Barcelona",
    "iso:country":"ES",
    "sg:address":"Pl Oliveres, 2",
    "sg:city":"Valldoreix",
    "sg:orig_category":"Talleres: Ropa A Medida",
    "sg:phone":"+34 936 74 24 97",
    "sg:postcode":"08197",
    "sg:province":"Barcelona",
    "wof:name":"Orella Pinell Francesc",
    "wof:placetype":"venue"
},
  "geometry": {"coordinates":[2.0387179852,41.4547729492],"type":"Point"}
}