{
  "type": "Feature",
  "properties": {
    "addr:full":"Covas, S/n Forcarei Pontevedra 36559",
    "addr:housenumber":"s / n",
    "addr:postcode":"36559",
    "addr:street":"Covas",
    "iso:country":"ES",
    "sg:address":"Covas, S/n",
    "sg:city":"Forcarei",
    "sg:orig_category":"Producci\u00d3n De Abonos Y De Fertilizantes",
    "sg:phone":"+34 986 75 52 35",
    "sg:postcode":"36559",
    "sg:province":"Pontevedra",
    "wof:name":"Gonzalez Pichel Francisco",
    "wof:placetype":"venue"
},
  "geometry": {"coordinates":[-8.3239278793,42.5765457153],"type":"Point"}
}