{
  "type": "Feature",
  "properties": {
    "addr:full":"Calle de Hernando De Magallanes, 12 Cordoba C\u00f3rdoba 14010",
    "addr:housenumber":"12",
    "addr:postcode":"14010",
    "addr:street":"Calle De Hernando De Magallanes;Co\u0301Rdoba",
    "iso:country":"ES",
    "sg:address":"Calle de Hernando De Magallanes, 12",
    "sg:city":"Cordoba",
    "sg:orig_category":"Imprenta",
    "sg:phone":"+34 957 26 24 90",
    "sg:postcode":"14010",
    "sg:province":"C\u00f3rdoba",
    "wof:name":"Imprenta Puchol S.l.",
    "wof:placetype":"venue"
},
  "geometry": {"coordinates":[-4.7641310692,37.8838729858],"type":"Point"}
}