{
  "type": "Feature",
  "properties": {
    "iso:country":"ES",
    "sg:address":"Luga Laba\u00d1ou, S/n",
    "sg:city":"Coru\u00d1a",
    "sg:orig_category":"Energ\u00cda Solar Y Nuevas Energ\u00cdas (equipo, Estudios)",
    "sg:phone":"+34 981 14 40 24",
    "sg:postcode":"15011",
    "sg:province":"La Coru\u00f1a",
    "wof:name":"Alternativas Electricas S.l",
    "wof:placetype":"venue"
},
  "geometry": {"coordinates":[-8.4485845566,43.3661346436],"type":"Point"}
}