{
  "type": "Feature",
  "properties": {
    "addr:full":"Calle de Ana Maria, 52 Gijon Asturias 33209",
    "addr:housenumber":"52",
    "addr:postcode":"33209",
    "addr:street":"Calle De Ana Maria",
    "iso:country":"ES",
    "sg:address":"Calle de Ana Maria, 52",
    "sg:city":"Gijon",
    "sg:orig_category":"Afiladoras, Pulidoras Y Bru\u00d1idoras",
    "sg:phone":"+34 985 38 46 96",
    "sg:postcode":"33209",
    "sg:province":"Asturias",
    "wof:name":"Atienza Bengoa Santos",
    "wof:placetype":"venue"
},
  "geometry": {"coordinates":[-5.6647877693,43.5265808105],"type":"Point"}
}