{
  "type": "Feature",
  "properties": {
    "iso:country":"ES",
    "sg:address":"Plaz Euskadi De, 1",
    "sg:city":"Donostia-san Sebastian",
    "sg:orig_category":"Peluquer\u00cdas, Peluquer\u00cda Mixta",
    "sg:phone":"+34 943 32 01 89",
    "sg:postcode":"20002",
    "sg:province":"Guip\u00f9zcoa",
    "sg:website":"www.rizos.es",
    "wof:name":"Peluqueria Azul De Rizos",
    "wof:placetype":"venue"
},
  "geometry": {"coordinates":[-1.9774930477,43.3213653564],"type":"Point"}
}