{
  "type": "Feature",
  "properties": {
    "iso:country":"ES",
    "sg:address":"Plaz Constitucion (de La), 18",
    "sg:city":"Utrera",
    "sg:orig_category":"Librer\u00cdas",
    "sg:phone":"+34 955 86 16 77",
    "sg:postcode":"41710",
    "sg:province":"Sevilla",
    "wof:name":"Otero Vargas Juan Jose",
    "wof:placetype":"venue"
},
  "geometry": {"coordinates":[-5.7819747925,37.181476593],"type":"Point"}
}