{
  "type": "Feature",
  "properties": {
    "iso:country":"ES",
    "sg:address":"Avda Perez Galdos, 22",
    "sg:city":"Logro\u00f1o",
    "sg:orig_category":"Ropa Para Se\u00d1oras Y Caballeros (al Por Menor)",
    "sg:phone":"+34 941 24 87 21",
    "sg:postcode":"26002",
    "sg:province":"La Rioja",
    "wof:name":"Almacenes Gonzalez Cuevas S. A.",
    "wof:placetype":"venue"
},
  "geometry": {"coordinates":[-2.4482791424,42.4614372253],"type":"Point"}
}