{
  "type": "Feature",
  "properties": {
    "iso:country":"ES",
    "sg:address":"Carrer de Mare De Deu De L'esperanca, S/n",
    "sg:city":"Mataro",
    "sg:orig_category":"Ropa Para Se\u00d1oras Y Caballeros (al Por Menor)",
    "sg:phone":"+34 937 98 88 16",
    "sg:postcode":"08304",
    "sg:province":"Barcelona",
    "wof:name":"Masoller Caballero Maria",
    "wof:placetype":"venue"
},
  "geometry": {"coordinates":[2.4428360462,41.5490722656],"type":"Point"}
}