{
  "type": "Feature",
  "properties": {
    "iso:country":"ES",
    "sg:address":"Carrer de Sebastia Juan Arbo (de), S/n",
    "sg:city":"Tortosa",
    "sg:orig_category":"Pr\u00c9stamos Personales E Hipotecarios",
    "sg:phone":"+34 977 44 81 71",
    "sg:postcode":"43500",
    "sg:province":"Tarragona",
    "wof:name":"Andres Romero Maria Elisa",
    "wof:placetype":"venue"
},
  "geometry": {"coordinates":[0.5184465051,40.8042297363],"type":"Point"}
}