{
  "type": "Feature",
  "properties": {
    "addr:full":"Pase Mikeletegi De, 58 Donostia-san Sebastian Guip\u00f9zcoa 20009",
    "addr:housenumber":"58",
    "addr:postcode":"20009",
    "iso:country":"ES",
    "sg:address":"Pase Mikeletegi De, 58",
    "sg:city":"Donostia-san Sebastian",
    "sg:orig_category":"Ingeniero",
    "sg:phone":"+34 943 30 92 51",
    "sg:postcode":"20009",
    "sg:province":"Guip\u00f9zcoa",
    "sg:website":"www.traintic.com",
    "wof:name":"Traintic S.l.",
    "wof:placetype":"venue"
},
  "geometry": {"coordinates":[-1.9794000387,43.3173789978],"type":"Point"}
}