{
  "type": "Feature",
  "properties": {
    "iso:country":"ES",
    "sg:address":"La Fuente, S/n",
    "sg:city":"Melegis",
    "sg:orig_category":"Asociaciones, Organismos Culturales Y Socioeducativos",
    "sg:phone":"+34 958 79 36 34",
    "sg:postcode":"18658",
    "sg:province":"Granada",
    "wof:name":"Ayuntamiento De El Valle",
    "wof:placetype":"venue"
},
  "geometry": {"coordinates":[-3.5712513924,36.935218811],"type":"Point"}
}