{
  "type": "Feature",
  "properties": {
    "addr:full":"Ctra Aranzueque (de), S/n Loranca De Taju\u00e7a Guadalajara 19141",
    "addr:postcode":"19141",
    "addr:street":"Ctra Aranzueque De S / N",
    "iso:country":"ES",
    "sg:address":"Ctra Aranzueque (de), S/n",
    "sg:city":"Loranca De Taju\u00e7a",
    "sg:orig_category":"Aceites Y Grasas Alimentarias (fabricaci\u00d3n, Al Por Mayor)",
    "sg:phone":"+34 949 29 45 04",
    "sg:postcode":"19141",
    "sg:province":"Guadalajara",
    "wof:name":"Aceites Delgado S.l.",
    "wof:placetype":"venue"
},
  "geometry": {"coordinates":[-3.1664927006,40.6298179626],"type":"Point"}
}