{
  "type": "Feature",
  "properties": {
    "iso:country":"ES",
    "sg:address":"Calle de Apolonio Morales, 17",
    "sg:city":"Madrid",
    "sg:orig_category":"Arquitectos",
    "sg:phone":"+34 913 43 08 18",
    "sg:postcode":"28036",
    "sg:province":"Madrid",
    "wof:name":"Bunch S.l.",
    "wof:placetype":"venue"
},
  "geometry": {"coordinates":[-3.6821734905,40.4635009766],"type":"Point"}
}