{
  "type": "Feature",
  "properties": {
    "addr:full":"Calle de Ronda (de), 28 Boadilla Del Monte Madrid 28660",
    "addr:housenumber":"28",
    "addr:postcode":"28660",
    "addr:street":"Calle De Ronda De",
    "iso:country":"ES",
    "sg:address":"Calle de Ronda (de), 28",
    "sg:city":"Boadilla Del Monte",
    "sg:orig_category":"Jardiner\u00cdas, Vegetales, Art\u00cdculos De Jardiner\u00cda (al Por Menor)",
    "sg:phone":"+34 916 33 40 67",
    "sg:postcode":"28660",
    "sg:province":"Madrid",
    "wof:name":"Aurea Jardineria Y Paisajismo S.l.",
    "wof:placetype":"venue"
},
  "geometry": {"coordinates":[-3.8831009865,40.4026527405],"type":"Point"}
}