{
  "type": "Feature",
  "properties": {
    "iso:country":"ES",
    "sg:address":"Calle de Segovia, 15",
    "sg:city":"Alcala Henares",
    "sg:orig_category":"Peluqueros: De Se\u00d1oras",
    "sg:phone":"+34 918 82 98 50",
    "sg:postcode":"28804",
    "sg:province":"Madrid",
    "wof:name":"Perez Aguilera Rosa Maria",
    "wof:placetype":"venue"
},
  "geometry": {"coordinates":[-3.3516368866,40.4846878052],"type":"Point"}
}