{
  "type": "Feature",
  "properties": {
    "iso:country":"ES",
    "sg:address":"Calle de Doce De Octubre, 33",
    "sg:city":"Mieres",
    "sg:orig_category":"Empresas De Portes Y Mensajer\u00cda",
    "sg:phone":"+34 985 46 18 11",
    "sg:postcode":"33600",
    "sg:province":"Asturias",
    "wof:name":"Maria Purificacion Mendez Gayol",
    "wof:placetype":"venue"
},
  "geometry": {"coordinates":[-5.7736506462,43.2530555725],"type":"Point"}
}