{
  "type": "Feature",
  "properties": {
    "addr:full":"Calle de Cristo, 1 Bola\u00e7os De Calatrava Ciudad Real 13260",
    "addr:housenumber":"1",
    "addr:postcode":"13260",
    "addr:street":"Calle De Cristo",
    "iso:country":"ES",
    "sg:address":"Calle de Cristo, 1",
    "sg:city":"Bola\u00e7os De Calatrava",
    "sg:orig_category":"Mec\u00c1nico Del Autom\u00d3vil",
    "sg:phone":"+34 926 87 08 50",
    "sg:postcode":"13260",
    "sg:province":"Ciudad Real",
    "wof:name":"Diaz Gomez Jose Daniel",
    "wof:placetype":"venue"
},
  "geometry": {"coordinates":[-3.6695768833,38.9067726135],"type":"Point"}
}