{
  "type": "Feature",
  "properties": {
    "addr:full":"Calle de Ramon Y Cajal, 38 Bollullos Par Condado Huelva 21710",
    "addr:housenumber":"38",
    "addr:postcode":"21710",
    "addr:street":"Calle De Ramon Y Cajal",
    "iso:country":"ES",
    "sg:address":"Calle de Ramon Y Cajal, 38",
    "sg:city":"Bollullos Par Condado",
    "sg:orig_category":"Molduras, Junquillos, Listones Y Molduras Perforadas",
    "sg:phone":"+34 959 41 05 09",
    "sg:postcode":"21710",
    "sg:province":"Huelva",
    "wof:name":"Roldan Camacho Francisco",
    "wof:placetype":"venue"
},
  "geometry": {"coordinates":[-6.5380401611,37.3391647339],"type":"Point"}
}