{
  "type": "Feature",
  "properties": {
    "iso:country":"ES",
    "sg:address":"Rua Prado Lonia, 12",
    "sg:city":"Ourense",
    "sg:orig_category":"Audiovisuales (producci\u00d3n, Edici\u00d3n, Realizaci\u00d3n)",
    "sg:phone":"+34 988 24 49 33",
    "sg:postcode":"32004",
    "sg:province":"Ourense",
    "wof:name":"Liimaia Produccions S.l.",
    "wof:placetype":"venue"
},
  "geometry": {"coordinates":[-7.8497729301,42.3455200195],"type":"Point"}
}