{
  "type": "Feature",
  "properties": {
    "iso:country":"ES",
    "sg:address":"Calle de Terraza, 19",
    "sg:city":"Estepona",
    "sg:orig_category":"Bisuter\u00cda, Joyer\u00cda, Relojer\u00cda (al Por Menor)",
    "sg:phone":"+34 952 80 52 04",
    "sg:postcode":"29680",
    "sg:province":"M\u00e1laga",
    "wof:name":"Barbudo Joyeros S.l.",
    "wof:placetype":"venue"
},
  "geometry": {"coordinates":[-5.1452031136,36.4261741638],"type":"Point"}
}