{
  "type": "Feature",
  "properties": {
    "addr:full":"Calle de Bolseria, 23 Valencia Valencia 46001",
    "addr:housenumber":"23",
    "addr:postcode":"46001",
    "addr:street":"Calle De Bolseria",
    "iso:country":"ES",
    "sg:address":"Calle de Bolseria, 23",
    "sg:city":"Valencia",
    "sg:orig_category":"Cuchiller\u00cda (al Por Menor)",
    "sg:phone":"+34 963 91 24 87",
    "sg:postcode":"46001",
    "sg:province":"Valencia",
    "wof:name":"Rodriguez Taboada Antonio",
    "wof:placetype":"venue"
},
  "geometry": {"coordinates":[-0.3800502121,39.4755210876],"type":"Point"}
}