{
  "type": "Feature",
  "properties": {
    "addr:full":"Calle de Rio, 29 Sada La Coru\u00f1a 15160",
    "addr:housenumber":"29",
    "addr:postcode":"15160",
    "addr:street":"Calle De Rio;La",
    "iso:country":"ES",
    "sg:address":"Calle de Rio, 29",
    "sg:city":"Sada",
    "sg:orig_category":"Asociaciones Y Clubs Deportivos",
    "sg:phone":"+34 981 62 36 09",
    "sg:postcode":"15160",
    "sg:province":"La Coru\u00f1a",
    "wof:name":"Deportes A Fraga S.l.",
    "wof:placetype":"venue"
},
  "geometry": {"coordinates":[-8.2532997131,43.3490219116],"type":"Point"}
}