{
  "type": "Feature",
  "properties": {
    "iso:country":"ES",
    "sg:address":"Poli Miralcampo, S/n",
    "sg:city":"Azuqueca Henares",
    "sg:orig_category":"Molduras, Junquillos, Listones Y Molduras Perforadas",
    "sg:phone":"+34 949 26 67 42",
    "sg:postcode":"19200",
    "sg:province":"Guadalajara",
    "wof:name":"Perfiles Del Cabo S.a.",
    "wof:placetype":"venue"
},
  "geometry": {"coordinates":[-3.2677440643,40.5646400452],"type":"Point"}
}