{
  "type": "Feature",
  "properties": {
    "iso:country":"ES",
    "sg:address":"Carr Punta D'en Ramis, 16",
    "sg:city":"Platja D'aro",
    "sg:orig_category":"Inmobiliaria (agencias)",
    "sg:phone":"+34 972 81 65 65",
    "sg:postcode":"17250",
    "sg:province":"Girona",
    "wof:name":"2ac Rentas S.l.",
    "wof:placetype":"venue"
},
  "geometry": {"coordinates":[3.071884,41.821823],"type":"Point"}
}