{
  "type": "Feature",
  "properties": {
    "addr:full":"C/ Mandrava, 67 Inca Islas Baleares 07300",
    "addr:housenumber":"67",
    "addr:postcode":"07300",
    "addr:street":"C / Mandrava",
    "iso:country":"ES",
    "sg:address":"C/ Mandrava, 67",
    "sg:city":"Inca",
    "sg:orig_category":"Zapatos (al Por Mayor)",
    "sg:phone":"+34 971 50 36 46",
    "sg:postcode":"07300",
    "sg:province":"Islas Baleares",
    "wof:name":"Lopez Guerrero Luciano Miguel",
    "wof:placetype":"venue"
},
  "geometry": {"coordinates":[2.9208989143,39.7179527283],"type":"Point"}
}