{
  "type": "Feature",
  "properties": {
    "iso:country":"ES",
    "sg:address":"Calle de Merida, 2",
    "sg:city":"Montijo",
    "sg:orig_category":"Bisuter\u00cda, Joyer\u00cda, Relojer\u00cda (al Por Menor)",
    "sg:phone":"+34 924 45 59 13",
    "sg:postcode":"06480",
    "sg:province":"Badajoz",
    "wof:name":"Pulgar Sosa Manuel",
    "wof:placetype":"venue"
},
  "geometry": {"coordinates":[-6.6166782379,38.9032173157],"type":"Point"}
}