{
  "type": "Feature",
  "properties": {
    "iso:country":"ES",
    "sg:address":"Pl Catalunya, 9",
    "sg:city":"Manresa",
    "sg:orig_category":"Inform\u00c1tica (estudios, Servicios, Asesor\u00cda, Formaci\u00d3n)",
    "sg:phone":"+34 938 72 61 14",
    "sg:postcode":"08242",
    "sg:province":"Barcelona",
    "wof:name":"Forn De Pa Codina S.l.",
    "wof:placetype":"venue"
},
  "geometry": {"coordinates":[1.8196480274,41.7292251587],"type":"Point"}
}