{
  "type": "Feature",
  "properties": {
    "iso:country":"ES",
    "sg:address":"Carr Emilio Donat, D', 5",
    "sg:city":"Carcaixent",
    "sg:orig_category":"Cajas Y Embalajes De Madera",
    "sg:phone":"+34 962 43 10 05",
    "sg:postcode":"46740",
    "sg:province":"Valencia",
    "wof:name":"Fabrica Envases Madera S.l.",
    "wof:placetype":"venue"
},
  "geometry": {"coordinates":[-0.4547240138,39.1157035828],"type":"Point"}
}