{
  "type": "Feature",
  "properties": {
    "addr:full":"Calle de Virgen (de La), S/n Ciempozuelos Madrid 28350",
    "addr:housenumber":"/ n",
    "addr:postcode":"28350",
    "addr:street":"Calle De Virgen De La S",
    "iso:country":"ES",
    "sg:address":"Calle de Virgen (de La), S/n",
    "sg:city":"Ciempozuelos",
    "sg:orig_category":"Centros De Educaci\u00d3n Especial",
    "sg:phone":"+34 918 93 33 17",
    "sg:postcode":"28350",
    "sg:province":"Madrid",
    "wof:name":"Centro Comarcal De Educacion De Adultos De Aranjuez",
    "wof:placetype":"venue"
},
  "geometry": {"coordinates":[-3.6168239117,40.1578941345],"type":"Point"}
}