{
  "type": "Feature",
  "properties": {
    "iso:country":"ES",
    "sg:address":"Calle de General Garcia De La Herran, 36",
    "sg:city":"S. Fernando",
    "sg:orig_category":"Sociedades, Compa\u00d1\u00cdas Aseguradoras",
    "sg:phone":"+34 956 88 49 04",
    "sg:postcode":"11100",
    "sg:province":"C\u00e1diz",
    "wof:name":"Albarran Planelles Antonio",
    "wof:placetype":"venue"
},
  "geometry": {"coordinates":[-6.2005252838,36.4669342041],"type":"Point"}
}