{
  "type": "Feature",
  "properties": {
    "iso:country":"ES",
    "sg:address":"Carrer de Ulldecona, 2",
    "sg:city":"Barcelona",
    "sg:orig_category":"Contenedores (mercanc\u00cdas)",
    "sg:phone":"+34 932 23 36 89",
    "sg:postcode":"08038",
    "sg:province":"Barcelona",
    "sg:website":"www.campoy.com",
    "wof:name":"Hermanos Campoy Servicios Y Transportes S.l.",
    "wof:placetype":"venue"
},
  "geometry": {"coordinates":[2.1405351162,41.3499298096],"type":"Point"}
}