{
  "type": "Feature",
  "properties": {
    "addr:full":"Cmno Faro, 31 Alacant Alicante 03540",
    "addr:housenumber":"31",
    "addr:postcode":"03540",
    "addr:street":"Cmno Faro",
    "iso:country":"ES",
    "sg:address":"Cmno Faro, 31",
    "sg:city":"Alacant",
    "sg:orig_category":"Internados & Ense\u00d1anza Privada",
    "sg:phone":"+34 965 26 30 21",
    "sg:postcode":"03540",
    "sg:province":"Alicante",
    "wof:name":"Colegio Elisa Tomas Yusti",
    "wof:placetype":"venue"
},
  "geometry": {"coordinates":[-0.4282369912,38.3684196472],"type":"Point"}
}