{
  "type": "Feature",
  "properties": {
    "addr:full":"Ctra. Cementerio, S/n Iru\u00f1a Navarra 31011",
    "addr:housenumber":"s",
    "addr:postcode":"31011",
    "addr:street":"Ctra. Cementerio;/ N Irun\u0303A Navarra",
    "iso:country":"ES",
    "sg:address":"Ctra. Cementerio, S/n",
    "sg:city":"Iru\u00f1a",
    "sg:orig_category":"M\u00c1rmoles, Granitos Y Piedras Naturales",
    "sg:phone":"+34 948 26 00 98",
    "sg:postcode":"31011",
    "sg:province":"Navarra",
    "wof:name":"Iba\u00f1ez Pascual Luis",
    "wof:placetype":"venue"
},
  "geometry": {"coordinates":[-1.6647894382,42.8178405762],"type":"Point"}
}