{
  "type": "Feature",
  "properties": {
    "addr:full":"Praj Ombatillo, 8 Corella Navarra 31591",
    "addr:housenumber":"8",
    "addr:postcode":"31591",
    "addr:street":"Ombatillo",
    "iso:country":"ES",
    "sg:address":"Praj Ombatillo, 8",
    "sg:city":"Corella",
    "sg:orig_category":"Ropa De Trabajo Y Profesionales (al Por Menor)",
    "sg:phone":"+34 948 40 15 94",
    "sg:postcode":"31591",
    "sg:province":"Navarra",
    "sg:website":"www.ime-muyet.com",
    "wof:name":"Ines Mulliez Corella S.a.",
    "wof:placetype":"venue"
},
  "geometry": {"coordinates":[-1.7880990505,42.1150436401],"type":"Point"}
}