{
  "type": "Feature",
  "properties": {
    "iso:country":"ES",
    "sg:address":"Calle de Humanista Furio, 11",
    "sg:city":"Valencia",
    "sg:orig_category":"Peluquer\u00cdas, Peluquer\u00cda Mixta",
    "sg:phone":"+34 963 72 33 06",
    "sg:postcode":"46022",
    "sg:province":"Valencia",
    "sg:website":"www.fpeluqueros.com",
    "wof:name":"Folgado Saez Enrique",
    "wof:placetype":"venue"
},
  "geometry": {"coordinates":[-0.3451279998,39.4682312012],"type":"Point"}
}