{
  "type": "Feature",
  "properties": {
    "iso:country":"ES",
    "sg:address":"Calle de Santa Cruz De Ardoi Kalea, 27",
    "sg:city":"Zizur Mayor",
    "sg:orig_category":"Ropa Para Se\u00d1oras (al Por Menor)",
    "sg:phone":"+34 948 18 25 49",
    "sg:postcode":"31180",
    "sg:province":"Navarra",
    "wof:name":"Alonso Del Bosque Ulpiana",
    "wof:placetype":"venue"
},
  "geometry": {"coordinates":[-1.6906483173,42.7879600525],"type":"Point"}
}