{
  "type": "Feature",
  "properties": {
    "iso:country":"ES",
    "sg:address":"Calle de Avispas, S/n",
    "sg:city":"Illescas",
    "sg:orig_category":"Agentes Generales De Seguros",
    "sg:phone":"+34 925 51 23 56",
    "sg:postcode":"45200",
    "sg:province":"Toledo",
    "wof:name":"Somar 2005 Sl",
    "wof:placetype":"venue"
},
  "geometry": {"coordinates":[-3.8489897251,40.1248970032],"type":"Point"}
}