{
  "type": "Feature",
  "properties": {
    "iso:country":"ES",
    "sg:address":"Calle de Santiago Ramon Y Cajal, 27",
    "sg:city":"Cartagena",
    "sg:orig_category":"Arreglo, Reparaci\u00d3n, Piezas Sueltas De Televisi\u00d3n, V\u00cddeo, Hi",
    "sg:phone":"+34 968 31 55 83",
    "sg:postcode":"30204",
    "sg:province":"Murcia",
    "wof:name":"Reparaciones Electronicas Generales C.b.",
    "wof:placetype":"venue"
},
  "geometry": {"coordinates":[-0.9914709926,37.6113815308],"type":"Point"}
}