{
  "type": "Feature",
  "properties": {
    "iso:country":"ES",
    "sg:address":"Calle de Joaquin Perez Campos, 49",
    "sg:city":"Badajoz",
    "sg:orig_category":"Doctores En Medicina",
    "sg:phone":"+34 924 25 49 88",
    "sg:postcode":"06011",
    "sg:province":"Badajoz",
    "wof:name":"Calderon Cardo Francisco",
    "wof:placetype":"venue"
},
  "geometry": {"coordinates":[-6.9891691208,38.8638534546],"type":"Point"}
}