{
  "type": "Feature",
  "properties": {
    "addr:full":"Av Prat De La Riba, 180 Palleja Barcelona 08780",
    "addr:housenumber":"180",
    "addr:postcode":"08780",
    "addr:street":"Av Prat De La Riba",
    "iso:country":"ES",
    "sg:address":"Av Prat De La Riba, 180",
    "sg:city":"Palleja",
    "sg:orig_category":"Producci\u00d3n De Huevos",
    "sg:phone":"+34 936 63 20 09",
    "sg:postcode":"08780",
    "sg:province":"Barcelona",
    "wof:name":"Agustin Roig S.a.",
    "wof:placetype":"venue"
},
  "geometry": {"coordinates":[2.0009691715,41.4127960205],"type":"Point"}
}