{
  "type": "Feature",
  "properties": {
    "addr:full":"Calle de Leon Xiii, 93 Sevilla Sevilla 41009",
    "addr:housenumber":"93",
    "addr:postcode":"41009",
    "addr:street":"Calle De Leon Xiii",
    "iso:country":"ES",
    "sg:address":"Calle de Leon Xiii, 93",
    "sg:city":"Sevilla",
    "sg:orig_category":"Bancos",
    "sg:phone":"+34 954 37 18 60",
    "sg:postcode":"41009",
    "sg:province":"Sevilla",
    "wof:name":"Master Locutorios S.a.",
    "wof:placetype":"venue"
},
  "geometry": {"coordinates":[-5.9825391769,37.4066390991],"type":"Point"}
}