{
  "type": "Feature",
  "properties": {
    "iso:country":"ES",
    "sg:address":"Calle de Manipa, 48",
    "sg:city":"Madrid",
    "sg:orig_category":"Fabricaci\u00d3n De Bibliotecas Y Estanter\u00cdas",
    "sg:phone":"+34 913 77 00 99",
    "sg:postcode":"28027",
    "sg:province":"Madrid",
    "wof:name":"Sisthos Y Matra S.l.",
    "wof:placetype":"venue"
},
  "geometry": {"coordinates":[-3.6449520588,40.4411201477],"type":"Point"}
}