{
  "type": "Feature",
  "properties": {
    "addr:full":"Riera (la), 153 Mataro Barcelona 08302",
    "addr:housenumber":"153",
    "addr:postcode":"08302",
    "addr:street":"Riera;Mataro Barcelona",
    "iso:country":"ES",
    "sg:address":"Riera (la), 153",
    "sg:city":"Mataro",
    "sg:orig_category":"Preparaci\u00d3n De Fibras Textiles Naturales",
    "sg:phone":"+34 937 98 65 05",
    "sg:postcode":"08302",
    "sg:province":"Barcelona",
    "wof:name":"Vidal Marine Juan",
    "wof:placetype":"venue"
},
  "geometry": {"coordinates":[2.4439051151,41.5415153503],"type":"Point"}
}