{
  "type": "Feature",
  "properties": {
    "iso:country":"ES",
    "sg:address":"Avda Cinca, 42",
    "sg:city":"Barbastro",
    "sg:orig_category":"Electrodom\u00c9sticos (al Por Menor)",
    "sg:phone":"+34 974 31 34 06",
    "sg:postcode":"22300",
    "sg:province":"Huesca",
    "wof:name":"Arnillas Galindo Angel",
    "wof:placetype":"venue"
},
  "geometry": {"coordinates":[0.1318006068,42.0331954956],"type":"Point"}
}