{
  "type": "Feature",
  "properties": {
    "iso:country":"ES",
    "sg:address":"Carr Mestre Ridaura, (del), 16",
    "sg:city":"Carlet",
    "sg:orig_category":"Agencias Y Agentes Comerciales, Representantes",
    "sg:phone":"+34 962 53 14 85",
    "sg:postcode":"46240",
    "sg:province":"Valencia",
    "wof:name":"Sansixto Mendoza Jorge",
    "wof:placetype":"venue"
},
  "geometry": {"coordinates":[-0.5233399868,39.2286682129],"type":"Point"}
}