{
  "type": "Feature",
  "properties": {
    "addr:full":"Rua Santo Domingo, 1 Vigo Pontevedra 36204",
    "addr:housenumber":"1",
    "addr:postcode":"36204",
    "addr:street":"Rua Santo Domingo",
    "iso:country":"ES",
    "sg:address":"Rua Santo Domingo, 1",
    "sg:city":"Vigo",
    "sg:orig_category":"Guarder\u00cdas",
    "sg:phone":"+34 986 41 94 67",
    "sg:postcode":"36204",
    "sg:province":"Pontevedra",
    "wof:name":"Alvarez Somme Barbara",
    "wof:placetype":"venue"
},
  "geometry": {"coordinates":[-8.7130346298,42.2323455811],"type":"Point"}
}