{
  "type": "Feature",
  "properties": {
    "iso:country":"ES",
    "sg:address":"Carr Germa Juli, 8",
    "sg:city":"Badalona",
    "sg:orig_category":"Inmobiliaria (agencias)",
    "sg:phone":"+34 933 84 40 87",
    "sg:postcode":"08911",
    "sg:province":"Barcelona",
    "sg:website":"www.germajuly.com",
    "wof:name":"Germa Juli S.l.",
    "wof:placetype":"venue"
},
  "geometry": {"coordinates":[2.2495861053,41.4531669617],"type":"Point"}
}