{
  "type": "Feature",
  "properties": {
    "iso:country":"ES",
    "sg:address":"Calle de Eugenio Gross, 14",
    "sg:city":"Malaga",
    "sg:orig_category":"Inmobiliaria (agencias)",
    "sg:phone":"+34 952 27 61 58",
    "sg:postcode":"29009",
    "sg:province":"M\u00e1laga",
    "wof:name":"Dominguez Y Ravassa S.a.",
    "wof:placetype":"venue"
},
  "geometry": {"coordinates":[-4.4356870651,36.7225990295],"type":"Point"}
}