{
  "type": "Feature",
  "properties": {
    "addr:full":"Narciso Hernandez Vaquero, S/n Pola Somiedo Asturias 33840",
    "addr:postcode":"33840",
    "addr:street":"Narciso;S / N",
    "iso:country":"ES",
    "sg:address":"Narciso Hernandez Vaquero, S/n",
    "sg:city":"Pola Somiedo",
    "sg:orig_category":"Alquiler De Apartamentos",
    "sg:phone":"+34 985 76 39 98",
    "sg:postcode":"33840",
    "sg:province":"Asturias",
    "wof:name":"Garcia Tu\u00f1on Susana",
    "wof:placetype":"venue"
},
  "geometry": {"coordinates":[-6.258234024,43.0951652527],"type":"Point"}
}