{
  "type": "Feature",
  "properties": {
    "addr:full":"Calle de Menendez, 3 Novelda Alicante 03660",
    "addr:housenumber":"3",
    "addr:postcode":"03660",
    "addr:street":"Calle De Menendez",
    "iso:country":"ES",
    "sg:address":"Calle de Menendez, 3",
    "sg:city":"Novelda",
    "sg:orig_category":"Reposter\u00cdas",
    "sg:phone":"+34 965 60 20 79",
    "sg:postcode":"03660",
    "sg:province":"Alicante",
    "wof:name":"Francisco Beltra Martinez Y Otro C.b.",
    "wof:placetype":"venue"
},
  "geometry": {"coordinates":[-0.7658450007,38.3879165649],"type":"Point"}
}