{
  "type": "Feature",
  "properties": {
    "iso:country":"ES",
    "sg:address":"Calle de Gracia Gazulla, 4",
    "sg:city":"Zaragoza",
    "sg:orig_category":"Agencias Y Agentes Comerciales, Representantes",
    "sg:phone":"+34 976 51 86 13",
    "sg:postcode":"50015",
    "sg:province":"Zaragoza",
    "wof:name":"Pedro Laguna Allue S.l.",
    "wof:placetype":"venue"
},
  "geometry": {"coordinates":[-0.8783910275,41.6623458862],"type":"Point"}
}