{
  "type": "Feature",
  "properties": {
    "addr:full":"Calle de Santa Maria, 5 Errenteria Guip\u00f9zcoa 20100",
    "addr:housenumber":"5",
    "addr:postcode":"20100",
    "addr:street":"Calle De Santa Maria;Guipu\u0300Zcoa",
    "iso:country":"ES",
    "sg:address":"Calle de Santa Maria, 5",
    "sg:city":"Errenteria",
    "sg:orig_category":"Zapatos (al Por Menor)",
    "sg:phone":"+34 943 52 49 81",
    "sg:postcode":"20100",
    "sg:province":"Guip\u00f9zcoa",
    "wof:name":"Ecenarro Ugartemendia Sorcunde",
    "wof:placetype":"venue"
},
  "geometry": {"coordinates":[-1.8992910385,43.312625885],"type":"Point"}
}