{
  "type": "Feature",
  "properties": {
    "addr:full":"Pla\u00c7 Blanquer, 59 Inca Islas Baleares 07300",
    "addr:housenumber":"59",
    "addr:postcode":"07300",
    "addr:street":"Blanquer",
    "iso:country":"ES",
    "sg:address":"Pla\u00c7 Blanquer, 59",
    "sg:city":"Inca",
    "sg:orig_category":"Quincaller\u00cda (al Por Menor)",
    "sg:phone":"+34 971 50 44 02",
    "sg:postcode":"07300",
    "sg:province":"Islas Baleares",
    "wof:name":"Ferreteria Ferragut Bonet S.l.",
    "wof:placetype":"venue"
},
  "geometry": {"coordinates":[2.9061439037,39.7217025757],"type":"Point"}
}