{
  "type": "Feature",
  "properties": {
    "iso:country":"ES",
    "sg:address":"Calle de Isabel La Catolica, 20",
    "sg:city":"Alacant",
    "sg:orig_category":"Aud\u00cdfonos",
    "sg:phone":"+34 965 12 33 88",
    "sg:postcode":"03007",
    "sg:province":"Alicante",
    "wof:name":"Ionozon S. A.",
    "wof:placetype":"venue"
},
  "geometry": {"coordinates":[-0.4954299927,38.3414115906],"type":"Point"}
}