{
  "type": "Feature",
  "properties": {
    "addr:full":"Carr Montfalgars, 1 Girona Girona 17006",
    "addr:housenumber":"1",
    "addr:postcode":"17006",
    "addr:street":"Carr Montfalgars",
    "iso:country":"ES",
    "sg:address":"Carr Montfalgars, 1",
    "sg:city":"Girona",
    "sg:orig_category":"Edici\u00d3n De Diarios, Revistas, Boletines",
    "sg:phone":"+34 972 40 00 86",
    "sg:postcode":"17006",
    "sg:province":"Girona",
    "wof:name":"Comercial Grupo Anaya S.a.",
    "wof:placetype":"venue"
},
  "geometry": {"coordinates":[2.8021690845,41.9735183716],"type":"Point"}
}