{
  "type": "Feature",
  "properties": {
    "addr:full":"Carrer de Lluis Ribas, 33 Rubi Barcelona 08191",
    "addr:housenumber":"33",
    "addr:postcode":"08191",
    "addr:street":"Carrer De Lluis Ribas",
    "iso:country":"ES",
    "sg:address":"Carrer de Lluis Ribas, 33",
    "sg:city":"Rubi",
    "sg:orig_category":"Alimentaci\u00d3n General (al Por Menor)",
    "sg:phone":"+34 936 97 24 83",
    "sg:postcode":"08191",
    "sg:province":"Barcelona",
    "wof:name":"Garriga Marcet Maria Antonia",
    "wof:placetype":"venue"
},
  "geometry": {"coordinates":[2.0357899666,41.4889297485],"type":"Point"}
}