{
  "type": "Feature",
  "properties": {
    "addr:full":"Carr Honorato Juan, 6 Xativa Valencia 46800",
    "addr:housenumber":"6",
    "addr:postcode":"46800",
    "addr:street":"Carr Honorato Juan",
    "iso:country":"ES",
    "sg:address":"Carr Honorato Juan, 6",
    "sg:city":"Xativa",
    "sg:orig_category":"Promotores Constructores",
    "sg:phone":"+34 962 28 11 60",
    "sg:postcode":"46800",
    "sg:province":"Valencia",
    "wof:name":"Construcciones Giarex S.l.",
    "wof:placetype":"venue"
},
  "geometry": {"coordinates":[-0.5202950239,38.9925346375],"type":"Point"}
}