{
  "type": "Feature",
  "properties": {
    "iso:country":"ES",
    "sg:address":"Rond Xose Casti\u00d1eira (musico), 5",
    "sg:city":"Lugo",
    "sg:orig_category":"Ense\u00d1anza Variada",
    "sg:phone":"+34 982 28 47 04",
    "sg:postcode":"27002",
    "sg:province":"Lugo",
    "wof:name":"Conservatorio Profesional De Danza De Lugo",
    "wof:placetype":"venue"
},
  "geometry": {"coordinates":[-7.548268795,42.9990615845],"type":"Point"}
}