{
  "type": "Feature",
  "properties": {
    "addr:full":"Calle de San Anton, 29 Torre Juan Abad Ciudad Real 13344",
    "addr:housenumber":"29",
    "addr:postcode":"13344",
    "addr:street":"Calle De San Anton",
    "iso:country":"ES",
    "sg:address":"Calle de San Anton, 29",
    "sg:city":"Torre Juan Abad",
    "sg:orig_category":"Centros De Educaci\u00d3n Especial",
    "sg:phone":"+34 926 38 30 68",
    "sg:postcode":"13344",
    "sg:province":"Ciudad Real",
    "wof:name":"Colegio Publico Francisco De Quevedo",
    "wof:placetype":"venue"
},
  "geometry": {"coordinates":[-3.9229569435,38.9924926758],"type":"Point"}
}