{
  "type": "Feature",
  "properties": {
    "iso:country":"ES",
    "sg:address":"Calle de San Isidro, 21",
    "sg:city":"Xeraco",
    "sg:orig_category":"Pescader\u00cdas (al Por Menor)",
    "sg:phone":"+34 962 89 21 44",
    "sg:postcode":"46770",
    "sg:province":"Valencia",
    "wof:name":"Peix Fresc Montilla Y Lucio S.l.",
    "wof:placetype":"venue"
},
  "geometry": {"coordinates":[-0.2176990062,39.0351219177],"type":"Point"}
}