{
  "type": "Feature",
  "properties": {
    "addr:full":"Carrer de Independencia, 313 Barcelona Barcelona 08026",
    "addr:housenumber":"313",
    "addr:postcode":"08026",
    "addr:street":"Carrer De Independencia",
    "iso:country":"ES",
    "sg:address":"Carrer de Independencia, 313",
    "sg:city":"Barcelona",
    "sg:orig_category":"Agentes, Concesionarios Y Sucursales De Veh\u00cdculos",
    "sg:phone":"+34 934 56 37 76",
    "sg:postcode":"08026",
    "sg:province":"Barcelona",
    "wof:name":"Auto Independencia S. A.",
    "wof:placetype":"venue"
},
  "geometry": {"coordinates":[2.1816120148,41.408946991],"type":"Point"}
}