{
  "type": "Feature",
  "properties": {
    "iso:country":"ES",
    "sg:address":"Rua Barcelona, 20",
    "sg:city":"Vigo",
    "sg:orig_category":"Oficinas: Suministros Para (fabricaci\u00d3n, Al Por Mayor)",
    "sg:phone":"+34 986 41 19 41",
    "sg:postcode":"36203",
    "sg:province":"Pontevedra",
    "wof:name":"Profinsa Productos De Oficina E Informatica S.a.",
    "wof:placetype":"venue"
},
  "geometry": {"coordinates":[-8.7223863602,42.227104187],"type":"Point"}
}