{
  "type": "Feature",
  "properties": {
    "iso:country":"ES",
    "sg:address":"Calle de Don Benito, S/n",
    "sg:city":"Guare\u00f1a",
    "sg:orig_category":"Venta, Montaje De Neum\u00c1ticos",
    "sg:phone":"+34 924 35 04 27",
    "sg:postcode":"06470",
    "sg:province":"Badajoz",
    "wof:name":"Vargas Roman Juan Daniel",
    "wof:placetype":"venue"
},
  "geometry": {"coordinates":[-6.0951738358,38.8601036072],"type":"Point"}
}