{
  "type": "Feature",
  "properties": {
    "iso:country":"ES",
    "sg:address":"Avda Oporto, 16",
    "sg:city":"Madrid",
    "sg:orig_category":"Zapatos (al Por Menor)",
    "sg:phone":"+34 915 60 24 36",
    "sg:postcode":"28019",
    "sg:province":"Madrid",
    "wof:name":"Ce. Paquets S.l.",
    "wof:placetype":"venue"
},
  "geometry": {"coordinates":[-3.7209260464,40.3853034973],"type":"Point"}
}