{
  "type": "Feature",
  "properties": {
    "addr:full":"Calle de Alcalde Jose Maria Amo, 2 Huelva Huelva 21001",
    "addr:housenumber":"2",
    "addr:postcode":"21001",
    "addr:street":"Calle De Alcalde Jose Maria Amo",
    "iso:country":"ES",
    "sg:address":"Calle de Alcalde Jose Maria Amo, 2",
    "sg:city":"Huelva",
    "sg:orig_category":"Asesor\u00cda De Formaci\u00d3n Y Gesti\u00d3n De Personal",
    "sg:phone":"+34 959 28 52 72",
    "sg:postcode":"21001",
    "sg:province":"Huelva",
    "wof:name":"Sanchez Baez Manuel",
    "wof:placetype":"venue"
},
  "geometry": {"coordinates":[-6.9543623924,37.2556915283],"type":"Point"}
}