{
  "type": "Feature",
  "properties": {
    "iso:country":"ES",
    "sg:address":"Plaz Centenario Del, 3",
    "sg:city":"Donostia-san Sebastian",
    "sg:orig_category":"Obras Y Organismos Sociales",
    "sg:phone":"+34 943 47 08 26",
    "sg:postcode":"20006",
    "sg:province":"Guip\u00f9zcoa",
    "wof:name":"Emaus Fundacion Social",
    "wof:placetype":"venue"
},
  "geometry": {"coordinates":[-1.9793989658,43.3173866272],"type":"Point"}
}