{
  "type": "Feature",
  "properties": {
    "addr:full":"Calle de Molinos (los), 8 Buenavista Norte Santa Cruz De Tenerife 38480",
    "addr:housenumber":"8",
    "addr:postcode":"38480",
    "addr:street":"Calle De Molinos Los",
    "iso:country":"ES",
    "sg:address":"Calle de Molinos (los), 8",
    "sg:city":"Buenavista Norte",
    "sg:orig_category":"Arquitectos",
    "sg:phone":"+34 922 12 73 96",
    "sg:postcode":"38480",
    "sg:province":"Santa Cruz De Tenerife",
    "wof:name":"Garcia Del Rosario Amada",
    "wof:placetype":"venue"
},
  "geometry": {"coordinates":[-16.8514556885,28.3736801147],"type":"Point"}
}