{
  "type": "Feature",
  "properties": {
    "iso:country":"ES",
    "sg:address":"Calle de Cura (el), 20",
    "sg:city":"Torredonjimeno",
    "sg:orig_category":"Electricidad: Instaladores",
    "sg:phone":"+34 953 57 21 51",
    "sg:postcode":"23650",
    "sg:province":"Ja\u00e9n",
    "wof:name":"Oca\u00f1a Bueno Juan",
    "wof:placetype":"venue"
},
  "geometry": {"coordinates":[-3.9571444988,37.763381958],"type":"Point"}
}