{
  "type": "Feature",
  "properties": {
    "addr:full":"Rua Cal, 5 Quiroga Lugo 27320",
    "addr:housenumber":"5",
    "addr:postcode":"27320",
    "addr:street":"Rua Cal",
    "iso:country":"ES",
    "sg:address":"Rua Cal, 5",
    "sg:city":"Quiroga",
    "sg:orig_category":"Supermercados Y Hipermercados",
    "sg:phone":"+34 982 42 89 52",
    "sg:postcode":"27320",
    "sg:province":"Lugo",
    "wof:name":"Super Mercado M.c.c.b.",
    "wof:placetype":"venue"
},
  "geometry": {"coordinates":[-7.2736201286,42.4766540527],"type":"Point"}
}