{
  "type": "Feature",
  "properties": {
    "addr:full":"Calle de Angel, 12 Alconchel Badajoz 06131",
    "addr:housenumber":"12",
    "addr:postcode":"06131",
    "addr:street":"Calle De Angel",
    "iso:country":"ES",
    "sg:address":"Calle de Angel, 12",
    "sg:city":"Alconchel",
    "sg:orig_category":"T\u00c9cnicos Veterinarios",
    "sg:phone":"+34 924 42 00 43",
    "sg:postcode":"06131",
    "sg:province":"Badajoz",
    "wof:name":"Toribio Giron Manuel",
    "wof:placetype":"venue"
},
  "geometry": {"coordinates":[-7.0710268021,38.5159759521],"type":"Point"}
}