{
  "type": "Feature",
  "properties": {
    "iso:country":"ES",
    "sg:address":"Calle de Antonio Maura, 17",
    "sg:city":"Zaragoza",
    "sg:orig_category":"Colchones (fabricaci\u00d3n, Al Por Mayor, Al Por Menor)",
    "sg:phone":"+34 976 41 52 42",
    "sg:postcode":"50013",
    "sg:province":"Zaragoza",
    "wof:name":"Retaule, S.l.",
    "wof:placetype":"venue"
},
  "geometry": {"coordinates":[-0.8717330098,41.6406517029],"type":"Point"}
}