{
  "type": "Feature",
  "properties": {
    "iso:country":"ES",
    "sg:address":"Poli Tejerias Calle de Marcu, De La, S/n",
    "sg:city":"Calahorra",
    "sg:orig_category":"Plomeros",
    "sg:phone":"+34 941 13 26 90",
    "sg:postcode":"26500",
    "sg:province":"La Rioja",
    "wof:name":"Dicafonsa S.l.",
    "wof:placetype":"venue"
},
  "geometry": {"coordinates":[-1.9620640278,42.3058395386],"type":"Point"}
}