{
  "type": "Feature",
  "properties": {
    "iso:country":"ES",
    "sg:address":"Avda Mediterraneo, S/n",
    "sg:city":"Cuenca",
    "sg:orig_category":"Peluqueros: De Se\u00d1oras",
    "sg:phone":"+34 969 23 23 79",
    "sg:postcode":"16004",
    "sg:province":"Cuenca",
    "wof:name":"Madro\u00d1al Peluquerias S.l.",
    "wof:placetype":"venue"
},
  "geometry": {"coordinates":[-2.126019001,40.057056427],"type":"Point"}
}