{
  "type": "Feature",
  "properties": {
    "addr:full":"Cmno Ronda (de), 130 Granada Granada 18003",
    "addr:housenumber":"130",
    "addr:postcode":"18003",
    "addr:street":"Cmno Ronda De",
    "iso:country":"ES",
    "sg:address":"Cmno Ronda (de), 130",
    "sg:city":"Granada",
    "sg:orig_category":"Centros P\u00dablicos De Formaci\u00d3n Profesional Y T\u00c9cnica",
    "sg:phone":"+34 958 28 16 62",
    "sg:postcode":"18003",
    "sg:province":"Granada",
    "wof:name":"Colegio De Agentes Y Corredores De Seguros",
    "wof:placetype":"venue"
},
  "geometry": {"coordinates":[-3.6091148853,37.1762046814],"type":"Point"}
}