{
  "type": "Feature",
  "properties": {
    "iso:country":"ES",
    "sg:address":"Carrer de Sant Quirze, 6",
    "sg:city":"Terrassa",
    "sg:orig_category":"M\u00c9dicos: Pediatr\u00cda. Enfermedades De Los Ni\u00d1os",
    "sg:phone":"+34 937 84 11 29",
    "sg:postcode":"08221",
    "sg:province":"Barcelona",
    "wof:name":"Saenz Bernat Augusto",
    "wof:placetype":"venue"
},
  "geometry": {"coordinates":[2.0151131153,41.5607719421],"type":"Point"}
}