{
  "type": "Feature",
  "properties": {
    "addr:full":"Calle de Carravieja, 1 Villa Don Fadrique Toledo 45850",
    "addr:housenumber":"1 villa",
    "addr:postcode":"45850",
    "addr:street":"Calle De Carravieja",
    "iso:country":"ES",
    "sg:address":"Calle de Carravieja, 1",
    "sg:city":"Villa Don Fadrique",
    "sg:orig_category":"Centros De Educaci\u00d3n Especial",
    "sg:phone":"+34 925 19 57 87",
    "sg:postcode":"45850",
    "sg:province":"Toledo",
    "wof:name":"Colegio Nacional Mixto Ramon Y Cajal",
    "wof:placetype":"venue"
},
  "geometry": {"coordinates":[-3.2185685635,39.6212844849],"type":"Point"}
}