{
  "type": "Feature",
  "properties": {
    "iso:country":"ES",
    "sg:address":"Calle de Rio, 25",
    "sg:city":"Sada",
    "sg:orig_category":"Electrodom\u00c9sticos (al Por Menor)",
    "sg:phone":"+34 981 62 03 65",
    "sg:postcode":"15160",
    "sg:province":"La Coru\u00f1a",
    "wof:name":"Becerra Varela Francisco",
    "wof:placetype":"venue"
},
  "geometry": {"coordinates":[-8.2533359528,43.3489646912],"type":"Point"}
}