{
  "type": "Feature",
  "properties": {
    "iso:country":"ES",
    "sg:address":"Calle de Juan Tornero, 66",
    "sg:city":"Madrid",
    "sg:orig_category":"Centros Comerciales Y Grandes Tiendas",
    "sg:phone":"+34 914 70 04 08",
    "sg:postcode":"28011",
    "sg:province":"Madrid",
    "wof:name":"Uhu  Zebin",
    "wof:placetype":"venue"
},
  "geometry": {"coordinates":[-3.7297580242,40.4112052917],"type":"Point"}
}