{
  "type": "Feature",
  "properties": {
    "addr:full":"Ctra. Jumilla-yecla, Km. 0079,3 Fuente Pino Murcia 30528",
    "addr:postcode":"30528",
    "addr:street":"Ctra. Jumilla-Yecla Km. 0079,3 Fuente",
    "iso:country":"ES",
    "sg:address":"Ctra. Jumilla-yecla, Km. 0079,3",
    "sg:city":"Fuente Pino",
    "sg:orig_category":"Comerciantes Al Por Mayor De Vinos, Licores Y Alcoholes",
    "sg:phone":"+34 968 43 50 35",
    "sg:postcode":"30528",
    "sg:province":"Murcia",
    "wof:name":"Bodegas Delampa S.l.",
    "wof:placetype":"venue"
},
  "geometry": {"coordinates":[-1.2884540558,38.5438995361],"type":"Point"}
}