{
  "type": "Feature",
  "properties": {
    "addr:full":"Calle de Rua Antigua, 11 Salamanca Salamanca 37002",
    "addr:housenumber":"11",
    "addr:postcode":"37002",
    "addr:street":"Calle De Rua Antigua",
    "iso:country":"ES",
    "sg:address":"Calle de Rua Antigua, 11",
    "sg:city":"Salamanca",
    "sg:orig_category":"Molduras, Junquillos, Listones Y Molduras Perforadas",
    "sg:phone":"+34 923 21 00 35",
    "sg:postcode":"37002",
    "sg:province":"Salamanca",
    "wof:name":"Falta De Amor S.l.",
    "wof:placetype":"venue"
},
  "geometry": {"coordinates":[-5.6662988663,40.9625091553],"type":"Point"}
}