{
  "type": "Feature",
  "properties": {
    "addr:full":"Calle de Aluminio (pol. Ind. ), 13 Marbella M\u00e1laga 29600",
    "addr:housenumber":"13",
    "addr:postcode":"29600",
    "addr:street":"Calle De Aluminio Pol. Ind.;Ma\u0301Laga",
    "iso:country":"ES",
    "sg:address":"Calle de Aluminio (pol. Ind. ), 13",
    "sg:city":"Marbella",
    "sg:orig_category":"Motocicletas (agentes, Concesionarios)",
    "sg:phone":"+34 952 92 40 26",
    "sg:postcode":"29600",
    "sg:province":"M\u00e1laga",
    "sg:website":"www.harleymarbella.com",
    "wof:name":"Hot Dreams Marbella S.l.",
    "wof:placetype":"venue"
},
  "geometry": {"coordinates":[-4.7588043213,36.5039405823],"type":"Point"}
}