{
  "type": "Feature",
  "properties": {
    "iso:country":"ES",
    "sg:address":"Calle de San Jose Artesano (de), 2",
    "sg:city":"Alcobendas",
    "sg:orig_category":"Electricidad: Equipos Industriales, Componentes (fabricaci\u00d3n)",
    "sg:phone":"+34 916 57 22 15",
    "sg:postcode":"28108",
    "sg:province":"Madrid",
    "sg:website":"www.es.es",
    "wof:name":"Equipos Y Sistemas S. A.",
    "wof:placetype":"venue"
},
  "geometry": {"coordinates":[-3.6574718952,40.529712677],"type":"Point"}
}