{
  "type": "Feature",
  "properties": {
    "iso:country":"ES",
    "sg:address":"Calle de Teniente Carrer de Castillo Olivares, 10",
    "sg:city":"Palmas De Gran Canaria",
    "sg:orig_category":"Ense\u00d1anza: Idiomas",
    "sg:phone":"+34 928 20 35 22",
    "sg:postcode":"35011",
    "sg:province":"Las Palmas",
    "sg:website":"www.harven.coom",
    "wof:name":"Harven School Gran Canaria S.l.",
    "wof:placetype":"venue"
},
  "geometry": {"coordinates":[-15.4348115921,28.1241092682],"type":"Point"}
}