{
  "type": "Feature",
  "properties": {
    "iso:country":"ES",
    "sg:address":"Calle de Blas De Lezo, 9",
    "sg:city":"Malaga",
    "sg:orig_category":"Agencias Y Agentes Comerciales, Representantes",
    "sg:phone":"+34 952 27 01 82",
    "sg:postcode":"29011",
    "sg:province":"M\u00e1laga",
    "wof:name":"Morales Lopez Antonio",
    "wof:placetype":"venue"
},
  "geometry": {"coordinates":[-4.4347219467,36.7279701233],"type":"Point"}
}