{
  "type": "Feature",
  "properties": {
    "addr:full":"Bidebarrieta Kalea, 46 Eibar Guip\u00f9zcoa 20600",
    "addr:housenumber":"46",
    "addr:postcode":"20600",
    "addr:street":"Bidebarrieta Kalea;Guipu\u0300Zcoa",
    "iso:country":"ES",
    "sg:address":"Bidebarrieta Kalea, 46",
    "sg:city":"Eibar",
    "sg:orig_category":"Maquinaria Para Industrias Diversas",
    "sg:phone":"+34 943 20 65 59",
    "sg:postcode":"20600",
    "sg:province":"Guip\u00f9zcoa",
    "wof:name":"Ostarte, S.l.",
    "wof:placetype":"venue"
},
  "geometry": {"coordinates":[-2.4662730694,43.1855545044],"type":"Point"}
}