{
  "type": "Feature",
  "properties": {
    "addr:full":"Calle de Alonso Ramos, 9 Fuente Maestre Badajoz 06360",
    "addr:housenumber":"9",
    "addr:postcode":"06360",
    "addr:street":"Calle De Alonso Ramos",
    "iso:country":"ES",
    "sg:address":"Calle de Alonso Ramos, 9",
    "sg:city":"Fuente Maestre",
    "sg:orig_category":"Agencias De Prensa E Informaci\u00d3n",
    "sg:phone":"+34 924 53 03 26",
    "sg:postcode":"06360",
    "sg:province":"Badajoz",
    "wof:name":"Zambrano Lopez Antonio",
    "wof:placetype":"venue"
},
  "geometry": {"coordinates":[-6.4501180649,38.5279083252],"type":"Point"}
}