{
  "type": "Feature",
  "properties": {
    "iso:country":"ES",
    "sg:address":"Minerva",
    "sg:city":"Costa Del Silencio",
    "sg:orig_category":"Reposter\u00cdas",
    "sg:phone":"+34 922 78 39 56",
    "sg:postcode":"38630",
    "sg:province":"Santa Cruz De Tenerife",
    "wof:name":"Castillo Olivares Barberan Natalia Del",
    "wof:placetype":"venue"
},
  "geometry": {"coordinates":[-16.6419887543,28.0123100281],"type":"Point"}
}