{
  "type": "Feature",
  "properties": {
    "addr:full":"Calle de Adrian Pastor, 12 Alacant Alicante 03008",
    "addr:housenumber":"12",
    "addr:postcode":"03008",
    "addr:street":"Calle De Adrian Pastor",
    "iso:country":"ES",
    "sg:address":"Calle de Adrian Pastor, 12",
    "sg:city":"Alacant",
    "sg:orig_category":"Mec\u00c1nico Del Autom\u00d3vil",
    "sg:phone":"+34 965 28 54 24",
    "sg:postcode":"03008",
    "sg:province":"Alicante",
    "wof:name":"Morales Alfocea Miguel",
    "wof:placetype":"venue"
},
  "geometry": {"coordinates":[-0.5139958858,38.327796936],"type":"Point"}
}