{
  "type": "Feature",
  "properties": {
    "iso:country":"ES",
    "sg:address":"Carrer de Sants, 441",
    "sg:city":"Barcelona",
    "sg:orig_category":"Plomeros",
    "sg:phone":"+34 934 49 81 36",
    "sg:postcode":"08028",
    "sg:province":"Barcelona",
    "wof:name":"Morillo Torres Diego",
    "wof:placetype":"venue"
},
  "geometry": {"coordinates":[2.1221370697,41.3756065369],"type":"Point"}
}