{
  "type": "Feature",
  "properties": {
    "addr:full":"Calle de Jose Luis Fanjul Sion 'sionin', 1 Langreo Asturias 33900",
    "addr:housenumber":"1",
    "addr:postcode":"33900",
    "addr:street":"Calle De Jose Luis Fanjul Sion ' Sionin '",
    "iso:country":"ES",
    "sg:address":"Calle de Jose Luis Fanjul Sion 'sionin', 1",
    "sg:city":"Langreo",
    "sg:orig_category":"Transportes Por V\u00cdas Navegables",
    "sg:phone":"+34 985 69 87 86",
    "sg:postcode":"33900",
    "sg:province":"Asturias",
    "wof:name":"Garcia Rodriguez Amador",
    "wof:placetype":"venue"
},
  "geometry": {"coordinates":[-5.696395874,43.3111915588],"type":"Point"}
}