{
  "type": "Feature",
  "properties": {
    "addr:full":"Carrer de Mairo, 10 Roses Girona 17480",
    "addr:housenumber":"10",
    "addr:postcode":"17480",
    "addr:street":"Carrer De Mairo",
    "iso:country":"ES",
    "sg:address":"Carrer de Mairo, 10",
    "sg:city":"Roses",
    "sg:orig_category":"Ropa Para Se\u00d1oras Y Caballeros (al Por Menor)",
    "sg:phone":"+34 972 25 45 31",
    "sg:postcode":"17480",
    "sg:province":"Girona",
    "wof:name":"Blau Fosc S.l.",
    "wof:placetype":"venue"
},
  "geometry": {"coordinates":[3.1764419079,42.2615127563],"type":"Point"}
}