{
  "type": "Feature",
  "properties": {
    "iso:country":"ES",
    "sg:address":"Avgd Constitucio, 23",
    "sg:city":"Alaro",
    "sg:orig_category":"Sociedades, Compa\u00d1\u00cdas Aseguradoras",
    "sg:phone":"+34 971 51 02 08",
    "sg:postcode":"07340",
    "sg:province":"Islas Baleares",
    "wof:name":"Simonet Vidal Juan",
    "wof:placetype":"venue"
},
  "geometry": {"coordinates":[2.7916309834,39.7048721313],"type":"Point"}
}