{
  "type": "Feature",
  "properties": {
    "addr:full":"Ctra Almeria, S/n Guadix Granada 18500",
    "addr:housenumber":"s",
    "addr:postcode":"18500",
    "addr:street":"Ctra Almeria;/ N",
    "iso:country":"ES",
    "sg:address":"Ctra Almeria, S/n",
    "sg:city":"Guadix",
    "sg:orig_category":"Negocio De Materiales De Construcci\u00d3n",
    "sg:phone":"+34 958 66 17 29",
    "sg:postcode":"18500",
    "sg:province":"Granada",
    "wof:name":"Juan Salmeron E Hijos S.l.",
    "wof:placetype":"venue"
},
  "geometry": {"coordinates":[-3.1295189857,37.2985687256],"type":"Point"}
}