{
  "type": "Feature",
  "properties": {
    "addr:full":"Alqueria Moret, 9 Picanya Valencia 46210",
    "addr:postcode":"46210",
    "iso:country":"ES",
    "sg:address":"Alqueria Moret, 9",
    "sg:city":"Picanya",
    "sg:orig_category":"Electr\u00d3nica Profesional: Material Y Componentes (al Por Mayor)",
    "sg:phone":"+34 961 59 46 46",
    "sg:postcode":"46210",
    "sg:province":"Valencia",
    "sg:website":"www.fermaxsistemas.com",
    "wof:name":"Fermax Sistemas De Seguridad S.a.",
    "wof:placetype":"venue"
},
  "geometry": {"coordinates":[-0.427143991,39.4372406006],"type":"Point"}
}