{
  "type": "Feature",
  "properties": {
    "iso:country":"ES",
    "sg:address":"Calle de La Isla, 5",
    "sg:city":"Villasana Mena",
    "sg:orig_category":"Frutas, Legumbres Frescas Y Tempranas (al Por Menor)",
    "sg:phone":"+34 947 12 60 89",
    "sg:postcode":"09580",
    "sg:province":"Burgos",
    "wof:name":"Serrano Sainz-ezquerra Garbi\u00f1e",
    "wof:placetype":"venue"
},
  "geometry": {"coordinates":[-3.2843289375,43.100982666],"type":"Point"}
}