{
  "type": "Feature",
  "properties": {
    "addr:full":"Avda Rey Gunderico, 94 Castrocontrigo Le\u00f3n 24735",
    "addr:housenumber":"94",
    "addr:postcode":"24735",
    "addr:street":"Avda Rey Gunderico;Leo\u0301N",
    "iso:country":"ES",
    "sg:address":"Avda Rey Gunderico, 94",
    "sg:city":"Castrocontrigo",
    "sg:orig_category":"Fabricaci\u00d3n Y Venta De Autocares Y Autobuses",
    "sg:phone":"+34 987 66 01 16",
    "sg:postcode":"24735",
    "sg:province":"Le\u00f3n",
    "wof:name":"Gonzalez Dinelli Raul",
    "wof:placetype":"venue"
},
  "geometry": {"coordinates":[-6.1904520988,42.1829147339],"type":"Point"}
}