{
  "type": "Feature",
  "properties": {
    "iso:country":"ES",
    "sg:address":"Cjto Residencial Sierra Estepona, S/n",
    "sg:city":"Estepona",
    "sg:orig_category":"Electricidad: Instaladores",
    "sg:phone":"+34 952 79 81 55",
    "sg:postcode":"29680",
    "sg:province":"M\u00e1laga",
    "wof:name":"Electroclima Cazarez S.l",
    "wof:placetype":"venue"
},
  "geometry": {"coordinates":[-5.0768837929,36.4523544312],"type":"Point"}
}