{
  "type": "Feature",
  "properties": {
    "iso:country":"ES",
    "sg:address":"Bemantes, 22",
    "sg:city":"Bemantes",
    "sg:orig_category":"Caf\u00c9s, Bares, Cervecer\u00cdas",
    "sg:phone":"+34 981 78 27 53",
    "sg:postcode":"15635",
    "sg:province":"A Coru\u00f1a",
    "wof:name":"Vidal Vidal Delia",
    "wof:placetype":"venue"
},
  "geometry": {"coordinates":[-8.1701183319,43.3359489441],"type":"Point"}
}