{
  "type": "Feature",
  "properties": {
    "addr:full":"Av Sant Joan De Deu, 69 Playa De Calafell Tarragona 43820",
    "addr:housenumber":"69",
    "addr:postcode":"43820",
    "addr:street":"Av Sant Joan De Deu",
    "iso:country":"ES",
    "sg:address":"Av Sant Joan De Deu, 69",
    "sg:city":"Playa De Calafell",
    "sg:orig_category":"Inmobiliaria (agencias)",
    "sg:phone":"+34 977 69 03 22",
    "sg:postcode":"43820",
    "sg:province":"Tarragona",
    "wof:name":"Fincas M.suau S. L.",
    "wof:placetype":"venue"
},
  "geometry": {"coordinates":[1.5726150274,41.1872177124],"type":"Point"}
}