{
  "type": "Feature",
  "properties": {
    "addr:full":"Calle de Rioja, 14 Leganes Madrid 28915",
    "addr:housenumber":"14",
    "addr:postcode":"28915",
    "addr:street":"Calle De Rioja",
    "iso:country":"ES",
    "sg:address":"Calle de Rioja, 14",
    "sg:city":"Leganes",
    "sg:orig_category":"Venta, Instalaci\u00d3n, Reparaci\u00d3n De Antenas Para Televisi\u00d3n",
    "sg:phone":"+34 916 87 45 54",
    "sg:postcode":"28915",
    "sg:province":"Madrid",
    "wof:name":"Serrano De La Cruz Romero-davila Pedro Antonio",
    "wof:placetype":"venue"
},
  "geometry": {"coordinates":[-3.7561779022,40.3339538574],"type":"Point"}
}