{
  "type": "Feature",
  "properties": {
    "iso:country":"ES",
    "sg:address":"Via Augusta, 277",
    "sg:city":"Barcelona",
    "sg:orig_category":"Psic\u00d3logos",
    "sg:phone":"+34 932 05 04 36",
    "sg:postcode":"08017",
    "sg:province":"Barcelona",
    "wof:name":"Centre Assistencia De Salut Mental Scp",
    "wof:placetype":"venue"
},
  "geometry": {"coordinates":[2.1306500435,41.3976211548],"type":"Point"}
}