{
  "type": "Feature",
  "properties": {
    "addr:full":"Calle de Caspe, 25 Zaragoza Zaragoza 50017",
    "addr:housenumber":"25",
    "addr:postcode":"50017",
    "addr:street":"Calle De Caspe",
    "iso:country":"ES",
    "sg:address":"Calle de Caspe, 25",
    "sg:city":"Zaragoza",
    "sg:orig_category":"Promotores Constructores",
    "sg:phone":"+34 976 33 02 83",
    "sg:postcode":"50017",
    "sg:province":"Zaragoza",
    "wof:name":"Indrustrias Ferrer S.l.",
    "wof:placetype":"venue"
},
  "geometry": {"coordinates":[-0.9063019156,41.6506576538],"type":"Point"}
}