{
  "type": "Feature",
  "properties": {
    "addr:full":"Carrer de Cera, 28 Barcelona Barcelona 08001",
    "addr:housenumber":"28",
    "addr:postcode":"08001",
    "addr:street":"Carrer De Cera",
    "iso:country":"ES",
    "sg:address":"Carrer de Cera, 28",
    "sg:city":"Barcelona",
    "sg:orig_category":"Panader\u00cdas, Panader\u00cdas",
    "sg:phone":"+34 934 41 05 63",
    "sg:postcode":"08001",
    "sg:province":"Barcelona",
    "wof:name":"Aussain  Mazhar",
    "wof:placetype":"venue"
},
  "geometry": {"coordinates":[2.1656799316,41.3786506653],"type":"Point"}
}