{
  "type": "Feature",
  "properties": {
    "addr:full":"Av Constitucion, 21 Catral Alicante 03158",
    "addr:housenumber":"21",
    "addr:postcode":"03158",
    "addr:street":"Av Constitucion",
    "iso:country":"ES",
    "sg:address":"Av Constitucion, 21",
    "sg:city":"Catral",
    "sg:orig_category":"Ense\u00d1ante, Direcci\u00d3n",
    "sg:phone":"+34 965 72 31 09",
    "sg:postcode":"03158",
    "sg:province":"Alicante",
    "wof:name":"Latorre Ruiz Alfonso",
    "wof:placetype":"venue"
},
  "geometry": {"coordinates":[-0.800679028,38.1603317261],"type":"Point"}
}