{
  "type": "Feature",
  "properties": {
    "addr:full":"Calle de Matadero, 13 Tomelloso Ciudad Real 13700",
    "addr:housenumber":"13",
    "addr:postcode":"13700",
    "addr:street":"Calle De Matadero",
    "iso:country":"ES",
    "sg:address":"Calle de Matadero, 13",
    "sg:city":"Tomelloso",
    "sg:orig_category":"Molduras, Junquillos, Listones Y Molduras Perforadas",
    "sg:phone":"+34 926 51 09 38",
    "sg:postcode":"13700",
    "sg:province":"Ciudad Real",
    "wof:name":"Fercotel Explotacion De Telefonos Publicos S.l.",
    "wof:placetype":"venue"
},
  "geometry": {"coordinates":[-3.0334589481,39.1528892517],"type":"Point"}
}