{
  "type": "Feature",
  "properties": {
    "iso:country":"ES",
    "sg:address":"Carr Corbella, (de La), 10",
    "sg:city":"Carlet",
    "sg:orig_category":"Supermercados Y Hipermercados",
    "sg:phone":"+34 962 99 36 72",
    "sg:postcode":"46240",
    "sg:province":"Valencia",
    "wof:name":"Superdumbo S.l.",
    "wof:placetype":"venue"
},
  "geometry": {"coordinates":[-0.5228570104,39.2274208069],"type":"Point"}
}