{
  "type": "Feature",
  "properties": {
    "addr:full":"Calle de Cardenal Cienfuegos, 10 Oviedo Asturias 33007",
    "addr:housenumber":"10",
    "addr:postcode":"33007",
    "addr:street":"Calle De Cardenal Cienfuegos",
    "iso:country":"ES",
    "sg:address":"Calle de Cardenal Cienfuegos, 10",
    "sg:city":"Oviedo",
    "sg:orig_category":"Abogados",
    "sg:phone":"+34 985 27 74 63",
    "sg:postcode":"33007",
    "sg:province":"Asturias",
    "wof:name":"Gonzalez Sanz Modesto Nestor Andres",
    "wof:placetype":"venue"
},
  "geometry": {"coordinates":[-5.8503117561,43.3546714783],"type":"Point"}
}