{
  "type": "Feature",
  "properties": {
    "addr:full":"Calle de Carretera Vieja, S/n Barrios Luna Le\u00f3n 24148",
    "addr:housenumber":"s",
    "addr:postcode":"24148",
    "addr:street":"Calle De Carretera Vieja;/ N Barrios Luna Leo\u0301N",
    "iso:country":"ES",
    "sg:address":"Calle de Carretera Vieja, S/n",
    "sg:city":"Barrios Luna",
    "sg:orig_category":"Albergues",
    "sg:phone":"+34 987 58 14 14",
    "sg:postcode":"24148",
    "sg:province":"Le\u00f3n",
    "wof:name":"Rodriguez Moran Jose",
    "wof:placetype":"venue"
},
  "geometry": {"coordinates":[-5.5951399803,42.6092720032],"type":"Point"}
}