{
  "type": "Feature",
  "properties": {
    "iso:country":"ES",
    "sg:address":"Avda Julio Rodriguez Soto, 3",
    "sg:city":"Carballi\u00f1o",
    "sg:orig_category":"Centros Empresariales",
    "sg:phone":"+34 988 53 08 25",
    "sg:postcode":"32500",
    "sg:province":"Ourense",
    "wof:name":"Telefonia Termatel S.l.",
    "wof:placetype":"venue"
},
  "geometry": {"coordinates":[-8.0820627213,42.4274749756],"type":"Point"}
}