{
  "type": "Feature",
  "properties": {
    "addr:full":"Avda Sevilla, 14 Salteras Sevilla 41909",
    "addr:housenumber":"14",
    "addr:postcode":"41909",
    "addr:street":"Avda Sevilla",
    "iso:country":"ES",
    "sg:address":"Avda Sevilla, 14",
    "sg:city":"Salteras",
    "sg:orig_category":"Hosteler\u00cda, Empleados",
    "sg:phone":"+34 955 70 71 89",
    "sg:postcode":"41909",
    "sg:province":"Sevilla",
    "wof:name":"Meson Los Macias S.l.",
    "wof:placetype":"venue"
},
  "geometry": {"coordinates":[-6.1068048477,37.4175834656],"type":"Point"}
}