{
  "type": "Feature",
  "properties": {
    "addr:full":"Calle de Cavite, 25 Valencia Valencia 46011",
    "addr:housenumber":"25",
    "addr:postcode":"46011",
    "addr:street":"Calle De Cavite",
    "iso:country":"ES",
    "sg:address":"Calle de Cavite, 25",
    "sg:city":"Valencia",
    "sg:orig_category":"Cristaler\u00cdas",
    "sg:phone":"+34 963 55 40 20",
    "sg:postcode":"46011",
    "sg:province":"Valencia",
    "wof:name":"Arenas Rubio Jose",
    "wof:placetype":"venue"
},
  "geometry": {"coordinates":[-0.3268029988,39.4778213501],"type":"Point"}
}