{
  "type": "Feature",
  "properties": {
    "addr:full":"Avda Valladolid, 105 Soria Soria 42004",
    "addr:housenumber":"105",
    "addr:postcode":"42004",
    "addr:street":"Avda Valladolid",
    "iso:country":"ES",
    "sg:address":"Avda Valladolid, 105",
    "sg:city":"Soria",
    "sg:orig_category":"Cooperativas Agr\u00cdcolas",
    "sg:phone":"+34 975 23 36 21",
    "sg:postcode":"42004",
    "sg:province":"Soria",
    "wof:name":"Copiso Soria Sociedad Cooperativa",
    "wof:placetype":"venue"
},
  "geometry": {"coordinates":[-2.4864890575,41.7687606812],"type":"Point"}
}