{
  "type": "Feature",
  "properties": {
    "addr:full":"Calle de Joaquin Fernandez De Avila, 13 Pozuelo De Alarcon Madrid 28223",
    "addr:housenumber":"13",
    "addr:postcode":"28223",
    "addr:street":"Calle De Joaquin Fernandez De Avila",
    "iso:country":"ES",
    "sg:address":"Calle de Joaquin Fernandez De Avila, 13",
    "sg:city":"Pozuelo De Alarcon",
    "sg:orig_category":"Edici\u00d3n De Mapas, Gu\u00cdas Y Planos",
    "sg:phone":"+34 913 52 43 58",
    "sg:postcode":"28223",
    "sg:province":"Madrid",
    "sg:website":"www.infocarto.com",
    "wof:name":"Infocarto S.a.",
    "wof:placetype":"venue"
},
  "geometry": {"coordinates":[-3.8108079433,40.4416427612],"type":"Point"}
}