{
  "type": "Feature",
  "properties": {
    "iso:country":"ES",
    "sg:address":"Ctra. General, 33",
    "sg:city":"Guaza",
    "sg:orig_category":"Agentes, Concesionarios Y Sucursales De Veh\u00cdculos",
    "sg:phone":"+34 922 16 90 46",
    "sg:postcode":"38627",
    "sg:province":"Santa Cruz De Tenerife",
    "wof:name":"Autos Guaza Comercial De Servicios S.l.",
    "wof:placetype":"venue"
},
  "geometry": {"coordinates":[-16.6800937653,28.0790691376],"type":"Point"}
}