{
  "type": "Feature",
  "properties": {
    "iso:country":"ES",
    "sg:address":"Calle de Principe De Vergara, 148",
    "sg:city":"Madrid",
    "sg:orig_category":"Librer\u00cdas",
    "sg:phone":"+34 914 16 01 07",
    "sg:postcode":"28002",
    "sg:province":"Madrid",
    "wof:name":"Jimenez Rela\u00f1o Clara",
    "wof:placetype":"venue"
},
  "geometry": {"coordinates":[-3.6779980659,40.4462471008],"type":"Point"}
}