{
  "type": "Feature",
  "properties": {
    "addr:full":"Trva Buena Manchega, 1 Viso C\u00f3rdoba 14470",
    "addr:housenumber":"1",
    "addr:postcode":"14470",
    "addr:street":"Trva Buena Manchega;Co\u0301Rdoba",
    "iso:country":"ES",
    "sg:address":"Trva Buena Manchega, 1",
    "sg:city":"Viso",
    "sg:orig_category":"Sanatorios M\u00c9dico",
    "sg:phone":"+34 957 12 72 36",
    "sg:postcode":"14470",
    "sg:province":"C\u00f3rdoba",
    "wof:name":"Ayuntamiento De El Viso",
    "wof:placetype":"venue"
},
  "geometry": {"coordinates":[-4.7791519165,37.884727478],"type":"Point"}
}