{
  "type": "Feature",
  "properties": {
    "iso:country":"ES",
    "sg:address":"Carrer de Sant Honorat, 68",
    "sg:city":"Sabadell",
    "sg:orig_category":"Venta, Localizaci\u00d3n, Reparaci\u00d3n De Material E Instrumental M\u00c9dico",
    "sg:phone":"+34 937 45 93 49",
    "sg:postcode":"08202",
    "sg:province":"Barcelona",
    "sg:website":"www.coacb.com/sobregrau",
    "wof:name":"Sobregrau S.l.",
    "wof:placetype":"venue"
},
  "geometry": {"coordinates":[2.1110749245,41.552280426],"type":"Point"}
}