{
  "type": "Feature",
  "properties": {
    "addr:full":"Crri Molino Alfatego, S/n Molino Alfatego Murcia 30100",
    "addr:housenumber":"s",
    "addr:postcode":"30100",
    "addr:street":"/ N Molino Alfatego",
    "iso:country":"ES",
    "sg:address":"Crri Molino Alfatego, S/n",
    "sg:city":"Molino Alfatego",
    "sg:orig_category":"Lavado, Limpieza De Veh\u00cdculos",
    "sg:phone":"+34 968 85 90 15",
    "sg:postcode":"30100",
    "sg:province":"Murcia",
    "wof:name":"Centros De Lavado Capel S.l.",
    "wof:placetype":"venue"
},
  "geometry": {"coordinates":[-1.1428140402,38.0105895996],"type":"Point"}
}