{
  "type": "Feature",
  "properties": {
    "addr:full":"Calle de Carlos Fuentes, 57 Madrid Madrid 28047",
    "addr:housenumber":"57",
    "addr:postcode":"madrid;28047",
    "addr:street":"Calle De Carlos Fuentes",
    "iso:country":"ES",
    "sg:address":"Calle de Carlos Fuentes, 57",
    "sg:city":"Madrid",
    "sg:orig_category":"Propiedad Industrial: Patentes De Inventos, Marcas, Modelos, Dise\u00d1os",
    "sg:phone":"+34 914 63 86 57",
    "sg:postcode":"28047",
    "sg:province":"Madrid",
    "wof:name":"Fuente Del Tell Ignacia De La",
    "wof:placetype":"venue"
},
  "geometry": {"coordinates":[-3.7416491508,40.4027786255],"type":"Point"}
}