{
  "type": "Feature",
  "properties": {
    "addr:full":"Ctra Viver-p Burriana, Km. 0058,0 Apeadero Betxi Castell\u00f3n 12200",
    "addr:postcode":"12200",
    "addr:street":"Ctra Viver-P Burriana Km. 0058,0 Apeadero Betxi Castello\u0301N",
    "iso:country":"ES",
    "sg:address":"Ctra Viver-p Burriana, Km. 0058,0",
    "sg:city":"Apeadero Betxi",
    "sg:orig_category":"Edici\u00d3n De Diarios, Revistas, Boletines",
    "sg:phone":"+34 964 62 62 66",
    "sg:postcode":"12200",
    "sg:province":"Castell\u00f3n",
    "wof:name":"La Faenza Espa\u00f1a S.a.",
    "wof:placetype":"venue"
},
  "geometry": {"coordinates":[-0.2620640099,39.9651794434],"type":"Point"}
}