{
  "type": "Feature",
  "properties": {
    "addr:full":"Calle de Francisco Jimenez Lomas, 1 Malaga M\u00e1laga 29004",
    "addr:housenumber":"1",
    "addr:postcode":"29004",
    "addr:street":"Calle De Francisco Jimenez Lomas;Ma\u0301Laga",
    "iso:country":"ES",
    "sg:address":"Calle de Francisco Jimenez Lomas, 1",
    "sg:city":"Malaga",
    "sg:orig_category":"Animales (al Por Menor)",
    "sg:phone":"+34 952 23 80 30",
    "sg:postcode":"29004",
    "sg:province":"M\u00e1laga",
    "wof:name":"Moneo Alonso Julian Fernando",
    "wof:placetype":"venue"
},
  "geometry": {"coordinates":[-4.4443678856,36.6940727234],"type":"Point"}
}