{
  "type": "Feature",
  "properties": {
    "iso:country":"ES",
    "sg:address":"Rua Xeneral Pardi\u00d1as (do), 2",
    "sg:city":"Santiago De Compostela",
    "sg:orig_category":"Camiser\u00cda Y Ropa Interior Masculina (al Por Menor)",
    "sg:phone":"+34 981 57 50 58",
    "sg:postcode":"15701",
    "sg:province":"La Coru\u00f1a",
    "sg:website":"www.undercolorsofbenetton.com",
    "wof:name":"Galmag S.l.",
    "wof:placetype":"venue"
},
  "geometry": {"coordinates":[-8.5464363098,42.8766098022],"type":"Point"}
}