{
  "type": "Feature",
  "properties": {
    "addr:full":"Calle de Ancha, 26 Ponferrada Le\u00f3n 24400",
    "addr:housenumber":"26",
    "addr:postcode":"24400",
    "addr:street":"Calle De Ancha",
    "iso:country":"ES",
    "sg:address":"Calle de Ancha, 26",
    "sg:city":"Ponferrada",
    "sg:orig_category":"Peluqueros: De Se\u00d1oras",
    "sg:phone":"+34 987 42 81 06",
    "sg:postcode":"24400",
    "sg:province":"Le\u00f3n",
    "wof:name":"San Nicolas Pereira Margarita",
    "wof:placetype":"venue"
},
  "geometry": {"coordinates":[-6.5883450508,42.5468063354],"type":"Point"}
}