{
  "type": "Feature",
  "properties": {
    "addr:full":"Carrer de Xifre, 98 Barcelona Barcelona 08026",
    "addr:housenumber":"98",
    "addr:postcode":"08026",
    "addr:street":"Carrer De Xifre",
    "iso:country":"ES",
    "sg:address":"Carrer de Xifre, 98",
    "sg:city":"Barcelona",
    "sg:orig_category":"Imprenta",
    "sg:phone":"+34 934 33 05 70",
    "sg:postcode":"08026",
    "sg:province":"Barcelona",
    "wof:name":"Gomez Martinez Ana",
    "wof:placetype":"venue"
},
  "geometry": {"coordinates":[2.180670023,41.4111976624],"type":"Point"}
}