{
  "type": "Feature",
  "properties": {
    "addr:full":"Calle de Dos Huertos, 30 Algar Murcia 30366",
    "addr:housenumber":"30",
    "addr:postcode":"30366",
    "addr:street":"Calle De Dos Huertos",
    "iso:country":"ES",
    "sg:address":"Calle de Dos Huertos, 30",
    "sg:city":"Algar",
    "sg:orig_category":"Molduras, Junquillos, Listones Y Molduras Perforadas",
    "sg:phone":"+34 968 13 64 45",
    "sg:postcode":"30366",
    "sg:province":"Murcia",
    "wof:name":"Molino Ocio S.l.l.",
    "wof:placetype":"venue"
},
  "geometry": {"coordinates":[-0.8665705919,37.6453285217],"type":"Point"}
}