{
  "type": "Feature",
  "properties": {
    "addr:full":"Calle de Luz (de La), 3 Humanes De Madrid Madrid 28970",
    "addr:housenumber":"3",
    "addr:postcode":"28970",
    "addr:street":"Calle De Luz De La",
    "iso:country":"ES",
    "sg:address":"Calle de Luz (de La), 3",
    "sg:city":"Humanes De Madrid",
    "sg:orig_category":"Pescader\u00cdas (al Por Menor)",
    "sg:phone":"+34 916 04 85 84",
    "sg:postcode":"28970",
    "sg:province":"Madrid",
    "wof:name":"Orgaz Gaitan Jorge",
    "wof:placetype":"venue"
},
  "geometry": {"coordinates":[-3.8297169209,40.2522506714],"type":"Point"}
}