{
  "type": "Feature",
  "properties": {
    "iso:country":"ES",
    "sg:address":"Calle de Panaderos, 47",
    "sg:city":"Granada",
    "sg:orig_category":"Agencias De Viajes",
    "sg:phone":"+34 958 29 41 03",
    "sg:postcode":"18010",
    "sg:province":"Granada",
    "sg:website":"www.vivegranada.com",
    "wof:name":"Vivegranada S.l",
    "wof:placetype":"venue"
},
  "geometry": {"coordinates":[-3.5915489197,37.1825408936],"type":"Point"}
}