{
  "type": "Feature",
  "properties": {
    "iso:country":"ES",
    "sg:address":"Carrer de Doctor Ulles, 32",
    "sg:city":"Terrassa",
    "sg:orig_category":"Librer\u00cdas",
    "sg:phone":"+34 937 80 11 44",
    "sg:postcode":"08224",
    "sg:province":"Barcelona",
    "wof:name":"Margarit Coll Jordi",
    "wof:placetype":"venue"
},
  "geometry": {"coordinates":[2.0063159466,41.5619316101],"type":"Point"}
}