{
  "type": "Feature",
  "properties": {
    "iso:country":"ES",
    "sg:address":"Calle de Antonio Guardiola Saez (de), 21",
    "sg:city":"Aranjuez",
    "sg:orig_category":"Cerrajer\u00cda, Ferrallista",
    "sg:phone":"+34 918 91 15 60",
    "sg:postcode":"28300",
    "sg:province":"Madrid",
    "wof:name":"Ainos S.l Sistem",
    "wof:placetype":"venue"
},
  "geometry": {"coordinates":[-3.6148798466,40.0195922852],"type":"Point"}
}