{
  "type": "Feature",
  "properties": {
    "iso:country":"ES",
    "sg:address":"Pase Pe\u00d1itas (las), 96",
    "sg:city":"Espinar",
    "sg:orig_category":"Promotores Constructores",
    "sg:phone":"+34 921 18 22 85",
    "sg:postcode":"40400",
    "sg:province":"Segovia",
    "wof:name":"Construcciones Chaila S.l.",
    "wof:placetype":"venue"
},
  "geometry": {"coordinates":[-4.2472991943,40.7189331055],"type":"Point"}
}