{
  "type": "Feature",
  "properties": {
    "iso:country":"ES",
    "sg:address":"Carrer de Perpinya, 20",
    "sg:city":"Terrassa",
    "sg:orig_category":"M\u00c1rmoles, Granitos Y Piedras Naturales",
    "sg:phone":"+34 937 35 60 45",
    "sg:postcode":"08226",
    "sg:province":"Barcelona",
    "wof:name":"Decmar Valles S.l.",
    "wof:placetype":"venue"
},
  "geometry": {"coordinates":[2.0218389034,41.5829353333],"type":"Point"}
}