{
  "type": "Feature",
  "properties": {
    "iso:country":"ES",
    "sg:address":"Kale Ibaiondo, 9",
    "sg:city":"Alegria-dulantzi",
    "sg:orig_category":"Empresas De Portes Y Mensajer\u00cda",
    "sg:phone":"+34 945 40 05 00",
    "sg:postcode":"01240",
    "sg:province":"\u00c1lava",
    "wof:name":"Virtus Ruiz De Gauna Maria Isabel",
    "wof:placetype":"venue"
},
  "geometry": {"coordinates":[-2.5141289234,42.8400802612],"type":"Point"}
}