{
  "type": "Feature",
  "properties": {
    "iso:country":"ES",
    "sg:address":"Pg Manresa, 24",
    "sg:city":"Sabadell",
    "sg:orig_category":"\u00d3ptica: Instrumentos (fabricaci\u00d3n)",
    "sg:phone":"+34 937 25 93 64",
    "sg:postcode":"08202",
    "sg:province":"Barcelona",
    "wof:name":"Porta Serveis D'optica S.l.",
    "wof:placetype":"venue"
},
  "geometry": {"coordinates":[2.1084671021,41.5488166809],"type":"Point"}
}