{
  "type": "Feature",
  "properties": {
    "iso:country":"ES",
    "sg:address":"Pla\u00c7 Pilar, 5",
    "sg:city":"Igualada",
    "sg:orig_category":"Molduras, Junquillos, Listones Y Molduras Perforadas",
    "sg:phone":"+34 938 05 51 76",
    "sg:postcode":"08700",
    "sg:province":"Barcelona",
    "wof:name":"Luque Rodriguez Luis",
    "wof:placetype":"venue"
},
  "geometry": {"coordinates":[1.6182670593,41.5790596008],"type":"Point"}
}