{
  "type": "Feature",
  "properties": {
    "iso:country":"ES",
    "sg:address":"Calle de Conde De Romanones, 9",
    "sg:city":"Madrid",
    "sg:orig_category":"Abogados",
    "sg:phone":"+34 913 69 03 62",
    "sg:postcode":"28012",
    "sg:province":"Madrid",
    "wof:name":"Sanz Arranz Alicia",
    "wof:placetype":"venue"
},
  "geometry": {"coordinates":[-3.7046740055,40.4131813049],"type":"Point"}
}