{
  "type": "Feature",
  "properties": {
    "iso:country":"ES",
    "sg:address":"Pla\u00c7 Major, 8",
    "sg:city":"Atzeneta Maestrat",
    "sg:orig_category":"Iglesia Cat\u00d3lica",
    "sg:phone":"+34 964 37 03 36",
    "sg:postcode":"12132",
    "sg:province":"Castell\u00f3n",
    "wof:name":"Iglesia Parroquial De San Bartolome",
    "wof:placetype":"venue"
},
  "geometry": {"coordinates":[-0.1707289964,40.2165145874],"type":"Point"}
}