{
  "type": "Feature",
  "properties": {
    "addr:full":"Calle de Puente, 19 Aldeanueva De Barbarroya Toledo 45661",
    "addr:housenumber":"19",
    "addr:postcode":"45661",
    "addr:street":"Calle De Puente",
    "iso:country":"ES",
    "sg:address":"Calle de Puente, 19",
    "sg:city":"Aldeanueva De Barbarroya",
    "sg:orig_category":"Agricultura: Abastecimiento Y Cosechado (negocio)",
    "sg:phone":"+34 925 70 63 65",
    "sg:postcode":"45661",
    "sg:province":"Toledo",
    "wof:name":"Sat Explotaciones La Paloma",
    "wof:placetype":"venue"
},
  "geometry": {"coordinates":[-5.0241208076,39.7607269287],"type":"Point"}
}