{
  "type": "Feature",
  "properties": {
    "addr:full":"Urb Solana (la), 6 Adrada \u00c1vila 05430",
    "addr:postcode":"05430",
    "addr:street":"Urb;La 6",
    "iso:country":"ES",
    "sg:address":"Urb Solana (la), 6",
    "sg:city":"Adrada",
    "sg:orig_category":"Instalaci\u00d3n, Reparaci\u00d3n De Ascensores Y Montacargas",
    "sg:phone":"+34 918 67 02 91",
    "sg:postcode":"05430",
    "sg:province":"\u00c1vila",
    "wof:name":"Industria Basica De Ascensores S. A.",
    "wof:placetype":"venue"
},
  "geometry": {"coordinates":[-4.638753891,40.3024139404],"type":"Point"}
}