{
  "type": "Feature",
  "properties": {
    "addr:full":"Carr Independencia, 337 Badalona Barcelona 08915",
    "addr:housenumber":"337",
    "addr:postcode":"08915",
    "addr:street":"Carr Independencia",
    "iso:country":"ES",
    "sg:address":"Carr Independencia, 337",
    "sg:city":"Badalona",
    "sg:orig_category":"Centros Empresariales",
    "sg:phone":"+34 933 87 69 31",
    "sg:postcode":"08915",
    "sg:province":"Barcelona",
    "wof:name":"Alemany Tomas Montserrat",
    "wof:placetype":"venue"
},
  "geometry": {"coordinates":[2.2401344776,41.46326828],"type":"Point"}
}