{
  "type": "Feature",
  "properties": {
    "addr:full":"Calle de Nuestra Se\u00d1ora Del Rosario, 9 Mimetiz Vizcaya 48860",
    "addr:housenumber":"9",
    "addr:postcode":"48860",
    "addr:street":"Calle De Nuestra Sen\u0303Ora Del Rosario",
    "iso:country":"ES",
    "sg:address":"Calle de Nuestra Se\u00d1ora Del Rosario, 9",
    "sg:city":"Mimetiz",
    "sg:orig_category":"Bares, Piano",
    "sg:phone":"+34 946 39 01 40",
    "sg:postcode":"48860",
    "sg:province":"Vizcaya",
    "wof:name":"Mena Mauriz Jesus Maria",
    "wof:placetype":"venue"
},
  "geometry": {"coordinates":[-3.1326060295,43.2144012451],"type":"Point"}
}