{
  "type": "Feature",
  "properties": {
    "addr:full":"Calle de Leganitos, 47 Madrid Madrid 28013",
    "addr:housenumber":"47",
    "addr:postcode":"madrid;28013",
    "addr:street":"Calle De Leganitos",
    "iso:country":"ES",
    "sg:address":"Calle de Leganitos, 47",
    "sg:city":"Madrid",
    "sg:orig_category":"Suministros Para Hoteles",
    "sg:phone":"+34 915 41 63 90",
    "sg:postcode":"28013",
    "sg:province":"Madrid",
    "wof:name":"Compostela Beach S.a.",
    "wof:placetype":"venue"
},
  "geometry": {"coordinates":[-3.7111999989,40.4230194092],"type":"Point"}
}