{
  "type": "Feature",
  "properties": {
    "addr:full":"C/ Montcada, 31 Ripollet Barcelona 08291",
    "addr:housenumber":"31",
    "addr:postcode":"08291",
    "addr:street":"C / Montcada",
    "iso:country":"ES",
    "sg:address":"C/ Montcada, 31",
    "sg:city":"Ripollet",
    "sg:orig_category":"Florister\u00cdas",
    "sg:phone":"+34 936 91 68 01",
    "sg:postcode":"08291",
    "sg:province":"Barcelona",
    "wof:name":"Sancho Quiles Jaime",
    "wof:placetype":"venue"
},
  "geometry": {"coordinates":[2.1585700512,41.4968185425],"type":"Point"}
}