{
  "type": "Feature",
  "properties": {
    "addr:full":"Praz Maior, 12 Ourense Ourense 32005",
    "addr:housenumber":"12",
    "addr:postcode":"32005",
    "addr:street":"Praz Maior",
    "iso:country":"ES",
    "sg:address":"Praz Maior, 12",
    "sg:city":"Ourense",
    "sg:orig_category":"Artesan\u00cda",
    "sg:phone":"+34 988 22 17 46",
    "sg:postcode":"32005",
    "sg:province":"Ourense",
    "wof:name":"Asociacion Aixi\u00d1a-orense",
    "wof:placetype":"venue"
},
  "geometry": {"coordinates":[-7.8639388084,42.3357582092],"type":"Point"}
}