{
  "type": "Feature",
  "properties": {
    "iso:country":"ES",
    "sg:address":"Calle de Padre Marin, 11",
    "sg:city":"Logro\u00f1o",
    "sg:orig_category":"Peluqueros: De Se\u00d1oras",
    "sg:phone":"+34 941 25 09 73",
    "sg:postcode":"26004",
    "sg:province":"La Rioja",
    "wof:name":"Mazo Hernaez Maria Angeles",
    "wof:placetype":"venue"
},
  "geometry": {"coordinates":[-2.4309129715,42.4645843506],"type":"Point"}
}