{
  "type": "Feature",
  "properties": {
    "addr:full":"Carrer de Llauder, 5 Barcelona Barcelona 08003",
    "addr:housenumber":"5",
    "addr:postcode":"08003",
    "addr:street":"Carrer De Llauder",
    "iso:country":"ES",
    "sg:address":"Carrer de Llauder, 5",
    "sg:city":"Barcelona",
    "sg:orig_category":"Bisuter\u00cda, Joyer\u00cda, Relojer\u00cda (al Por Menor)",
    "sg:phone":"+34 933 15 29 56",
    "sg:postcode":"08003",
    "sg:province":"Barcelona",
    "wof:name":"Comercial Cetus 133 S.l.",
    "wof:placetype":"venue"
},
  "geometry": {"coordinates":[2.183453083,41.3815002441],"type":"Point"}
}