{
  "type": "Feature",
  "properties": {
    "addr:full":"Calle de Matarrosa, 32 Fuenlabrada Madrid 28947",
    "addr:housenumber":"32",
    "addr:postcode":"28947",
    "addr:street":"Calle De Matarrosa",
    "iso:country":"ES",
    "sg:address":"Calle de Matarrosa, 32",
    "sg:city":"Fuenlabrada",
    "sg:orig_category":"Productos Qu\u00cdmicos (fabricaci\u00d3n, Al Por Mayor)",
    "sg:phone":"+34 916 42 12 30",
    "sg:postcode":"28947",
    "sg:province":"Madrid",
    "wof:name":"Industrial Kern Espa\u00f1ola S.a.",
    "wof:placetype":"venue"
},
  "geometry": {"coordinates":[-3.7532989979,40.2643852234],"type":"Point"}
}