{
  "type": "Feature",
  "properties": {
    "addr:full":"Carrer de Ifni, 23 S. Adria Besos Barcelona 08930",
    "addr:housenumber":"23",
    "addr:postcode":"08930",
    "addr:street":"Carrer De Ifni;S. Adria Besos Barcelona",
    "iso:country":"ES",
    "sg:address":"Carrer de Ifni, 23",
    "sg:city":"S. Adria Besos",
    "sg:orig_category":"Productos Qu\u00cdmicos (fabricaci\u00d3n, Al Por Mayor)",
    "sg:phone":"+34 933 81 90 90",
    "sg:postcode":"08930",
    "sg:province":"Barcelona",
    "wof:name":"Tedenko S. A.",
    "wof:placetype":"venue"
},
  "geometry": {"coordinates":[2.2307178974,41.4292945862],"type":"Point"}
}