{
  "type": "Feature",
  "properties": {
    "addr:full":"Calle de Antonio Nebrija, 20 Le\u00f3n Le\u00f3n 24009",
    "addr:housenumber":"20",
    "addr:postcode":"24009",
    "addr:street":"Calle De Antonio Nebrija;Leo\u0301N",
    "iso:country":"ES",
    "sg:address":"Calle de Antonio Nebrija, 20",
    "sg:city":"Le\u00f3n",
    "sg:orig_category":"Delegados, Agentes De Tr\u00c1nsito, Auxiliares De Transporte Internacional",
    "sg:phone":"+34 987 24 34 75",
    "sg:postcode":"24009",
    "sg:province":"Le\u00f3n",
    "wof:name":"De Diego Iba\u00f1ez Mario Angel",
    "wof:placetype":"venue"
},
  "geometry": {"coordinates":[-5.5851650238,42.5993461609],"type":"Point"}
}