{
  "type": "Feature",
  "properties": {
    "addr:full":"Calle de Gomez Marcelo, 1 Ceuta Ceuta 51001",
    "addr:housenumber":"1",
    "addr:postcode":"51001",
    "addr:street":"Calle De Gomez Marcelo",
    "iso:country":"ES",
    "sg:address":"Calle de Gomez Marcelo, 1",
    "sg:city":"Ceuta",
    "sg:classifiers":[
        {
            "category":"Personal",
            "subcategory":"Barber",
            "type":"Services"
        }
    ],
    "sg:phone":"+34 956 51 56 26",
    "sg:postcode":"51001",
    "sg:province":"Ceuta",
    "sg:tags":[
        "caballeros",
        "de",
        "peluqueros"
    ],
    "wof:name":"El Marrouti  Hassan",
    "wof:placetype":"venue"
},
  "geometry": {"coordinates":[-5.3152198792,35.8887748718],"type":"Point"}
}