{
  "type": "Feature",
  "properties": {
    "addr:full":"Calle de Mena Motina, 4 Teruel Teruel 44003",
    "addr:housenumber":"4",
    "addr:postcode":"44003",
    "addr:street":"Calle De Mena Motina",
    "iso:country":"ES",
    "sg:address":"Calle de Mena Motina, 4",
    "sg:city":"Teruel",
    "sg:orig_category":"Electrodom\u00c9sticos (al Por Menor)",
    "sg:phone":"+34 978 60 49 36",
    "sg:postcode":"44003",
    "sg:province":"Teruel",
    "wof:name":"Pascual Martin Angel",
    "wof:placetype":"venue"
},
  "geometry": {"coordinates":[-1.1019159555,40.3414840698],"type":"Point"}
}