{
  "type": "Feature",
  "properties": {
    "iso:country":"ES",
    "sg:address":"Calle de Casa Jimenez, S/n",
    "sg:city":"Zaragoza",
    "sg:classifiers":[
        {
            "category":"Casinos & Gambling",
            "type":"Entertainment"
        }
    ],
    "sg:phone":"+34 976 21 32 99",
    "sg:postcode":"50004",
    "sg:province":"Zaragoza",
    "sg:tags":[
        "locale",
        "de",
        "juego"
    ],
    "sg:website":"www.grupocomar.com",
    "wof:name":"Casino De Zaragoza S.a.",
    "wof:placetype":"venue"
},
  "geometry": {"coordinates":[-0.8848295212,41.6501693726],"type":"Point"}
}