{
  "type": "Feature",
  "properties": {
    "iso:country":"ES",
    "sg:address":"Calle de Lobo, 6",
    "sg:city":"Yebenes",
    "sg:orig_category":"Agencias Y Agentes Comerciales, Representantes",
    "sg:phone":"+34 925 32 06 25",
    "sg:postcode":"45470",
    "sg:province":"Toledo",
    "wof:name":"Gomez Jimenez Alicia",
    "wof:placetype":"venue"
},
  "geometry": {"coordinates":[-3.8697290421,39.5791702271],"type":"Point"}
}