{
  "type": "Feature",
  "properties": {
    "iso:country":"ES",
    "sg:address":"Ctra Alcoy Alicante, 2",
    "sg:city":"Sella",
    "sg:orig_category":"Pintura, Barniz, Productos Asimilables (fabricaci\u00d3n, Al Por Mayor)",
    "sg:phone":"+34 965 87 92 04",
    "sg:postcode":"03579",
    "sg:province":"Alicante",
    "wof:name":"Llorca Asensi Vicente Tomas",
    "wof:placetype":"venue"
},
  "geometry": {"coordinates":[-0.2748140097,38.609539032],"type":"Point"}
}