{
  "type": "Feature",
  "properties": {
    "addr:full":"Calle de Armengual De La Mota, 36 Malaga M\u00e1laga 29007",
    "addr:housenumber":"36",
    "addr:postcode":"29007",
    "addr:street":"Calle De Armengual De La Mota;Ma\u0301Laga",
    "iso:country":"ES",
    "sg:address":"Calle de Armengual De La Mota, 36",
    "sg:city":"Malaga",
    "sg:orig_category":"Confecci\u00d3n De Trajes Para Se\u00d1oras",
    "sg:phone":"+34 952 61 13 91",
    "sg:postcode":"29007",
    "sg:province":"M\u00e1laga",
    "wof:name":"Rodriguez Laguna Carlos",
    "wof:placetype":"venue"
},
  "geometry": {"coordinates":[-4.4290165901,36.7213058472],"type":"Point"}
}