{
  "type": "Feature",
  "properties": {
    "iso:country":"ES",
    "sg:address":"Calle de Caracol, 3",
    "sg:city":"Teruel",
    "sg:orig_category":"Organizaciones Profesionales",
    "sg:phone":"+34 978 61 09 01",
    "sg:postcode":"44001",
    "sg:province":"Teruel",
    "wof:name":"Izquierdo Dolz Rafael",
    "wof:placetype":"venue"
},
  "geometry": {"coordinates":[-1.1059223413,40.342590332],"type":"Point"}
}