{
  "type": "Feature",
  "properties": {
    "iso:country":"ES",
    "sg:address":"Carretera De Nijar A San Jose, S/n",
    "sg:city":"Pozo Frailes",
    "sg:orig_category":"Molduras, Junquillos, Listones Y Molduras Perforadas",
    "sg:phone":"+34 950 38 01 83",
    "sg:postcode":"04117",
    "sg:province":"Almer\u00eda",
    "wof:name":"Gonzalez Salvador Angeles",
    "wof:placetype":"venue"
},
  "geometry": {"coordinates":[-2.4679217339,36.8401641846],"type":"Point"}
}