{
  "type": "Feature",
  "properties": {
    "iso:country":"ES",
    "sg:address":"Carrer de Creu Roja, 28",
    "sg:city":"Mataro",
    "sg:orig_category":"Poller\u00cda Y Caza (al Por Menor)",
    "sg:phone":"+34 937 99 46 33",
    "sg:postcode":"08304",
    "sg:province":"Barcelona",
    "wof:name":"Martin Dominguez Antonio",
    "wof:placetype":"venue"
},
  "geometry": {"coordinates":[2.4423680305,41.5489006042],"type":"Point"}
}