{
  "type": "Feature",
  "properties": {
    "iso:country":"ES",
    "sg:address":"Calle de Camino Viejo De Getafe (del), 64",
    "sg:city":"Fuenlabrada",
    "sg:orig_category":"Construcciones Met\u00c1licas",
    "sg:phone":"+34 916 90 16 71",
    "sg:postcode":"28946",
    "sg:province":"Madrid",
    "wof:name":"C Jene Torras S. L.",
    "wof:placetype":"venue"
},
  "geometry": {"coordinates":[-3.7774438858,40.2820892334],"type":"Point"}
}