{
  "type": "Feature",
  "properties": {
    "iso:country":"ES",
    "sg:address":"Calle de General Aranaz, 23",
    "sg:city":"Madrid",
    "sg:orig_category":"Institutos De Belleza",
    "sg:phone":"+34 913 20 34 10",
    "sg:postcode":"28027",
    "sg:province":"Madrid",
    "wof:name":"Le Palais C.b.",
    "wof:placetype":"venue"
},
  "geometry": {"coordinates":[-3.6374440193,40.4410896301],"type":"Point"}
}