{
  "type": "Feature",
  "properties": {
    "iso:country":"ES",
    "sg:address":"Trva Coru\u00d1a, 2",
    "sg:city":"Vigo",
    "sg:orig_category":"M\u00c9dicos: Estomatolog\u00cda",
    "sg:phone":"+34 986 20 35 52",
    "sg:postcode":"36211",
    "sg:province":"Pontevedra",
    "wof:name":"Arbor Otero Celsa",
    "wof:placetype":"venue"
},
  "geometry": {"coordinates":[-8.7302217484,42.2246208191],"type":"Point"}
}