{
  "type": "Feature",
  "properties": {
    "addr:full":"Calle de Alcolea, 15 Villafranca Cordoba C\u00f3rdoba 14420",
    "addr:housenumber":"15",
    "addr:postcode":"14420",
    "addr:street":"Calle De Alcolea",
    "iso:country":"ES",
    "sg:address":"Calle de Alcolea, 15",
    "sg:city":"Villafranca Cordoba",
    "sg:orig_category":"Farmacias",
    "sg:phone":"+34 957 19 00 45",
    "sg:postcode":"14420",
    "sg:province":"C\u00f3rdoba",
    "wof:name":"Maria Elena Mendez Diaz Y Maria Angeles Villarejo Ceballos C.b.",
    "wof:placetype":"venue"
},
  "geometry": {"coordinates":[-4.5450863838,37.9628181458],"type":"Point"}
}