{
  "type": "Feature",
  "properties": {
    "iso:country":"ES",
    "sg:address":"Ctra. General, S/n",
    "sg:city":"Borines",
    "sg:orig_category":"Aguas (distribuci\u00d3n, Servicios)",
    "sg:phone":"+34 985 70 72 58",
    "sg:postcode":"33583",
    "sg:province":"Asturias",
    "wof:name":"Aguas De Borines S. A.",
    "wof:placetype":"venue"
},
  "geometry": {"coordinates":[-5.29997015,43.3627700806],"type":"Point"}
}