{
  "type": "Feature",
  "properties": {
    "addr:full":"Pase Delicias (las), S/n Jerez De La Frontera C\u00e1diz 11406",
    "addr:postcode":"11406",
    "addr:street":"Las S / N",
    "iso:country":"ES",
    "sg:address":"Pase Delicias (las), S/n",
    "sg:city":"Jerez De La Frontera",
    "sg:orig_category":"Armas Y Municiones (fabricaci\u00d3n, Al Por Mayor)",
    "sg:phone":"+34 956 32 49 08",
    "sg:postcode":"11406",
    "sg:province":"C\u00e1diz",
    "wof:name":"Lechuga Sanchez Jose Antonio",
    "wof:placetype":"venue"
},
  "geometry": {"coordinates":[-6.1038489342,36.6860847473],"type":"Point"}
}