{
  "type": "Feature",
  "properties": {
    "addr:full":"Calle de Rio Bembezar, 8 Atalayuela Madrid 28906",
    "addr:housenumber":"8",
    "addr:postcode":"28906",
    "addr:street":"Calle De Rio Bembezar",
    "iso:country":"ES",
    "sg:address":"Calle de Rio Bembezar, 8",
    "sg:city":"Atalayuela",
    "sg:orig_category":"Cajas De Ahorro",
    "sg:phone":"+34 916 21 32 99",
    "sg:postcode":"28906",
    "sg:province":"Madrid",
    "wof:name":"Caixa D'estalvis I Pensions De Barcelona",
    "wof:placetype":"venue"
},
  "geometry": {"coordinates":[-3.7057700157,40.42029953],"type":"Point"}
}