{
  "type": "Feature",
  "properties": {
    "iso:country":"ES",
    "sg:address":"Av Roma, 151",
    "sg:city":"Barcelona",
    "sg:orig_category":"Peluquer\u00cdas, Peluquer\u00cda Mixta",
    "sg:phone":"+34 934 53 30 72",
    "sg:postcode":"08011",
    "sg:province":"Barcelona",
    "wof:name":"Jimenez Molina Eustasio",
    "wof:placetype":"venue"
},
  "geometry": {"coordinates":[2.1565060616,41.386554718],"type":"Point"}
}