{
  "type": "Feature",
  "properties": {
    "iso:country":"ES",
    "sg:address":"Calle de Pinarnegrillo, S/n",
    "sg:city":"Aldea Real",
    "sg:orig_category":"Agricultores, Agricultores",
    "sg:phone":"+34 921 12 20 83",
    "sg:postcode":"40293",
    "sg:province":"Segovia",
    "wof:name":"Los Estepares S.l.",
    "wof:placetype":"venue"
},
  "geometry": {"coordinates":[-4.1663341522,41.1851158142],"type":"Point"}
}