{
  "type": "Feature",
  "properties": {
    "addr:full":"Calle de Valle Gistain, S/n Monzon Huesca 22400",
    "addr:housenumber":"s",
    "addr:postcode":"22400",
    "addr:street":"Calle De Valle Gistain;/ N",
    "iso:country":"ES",
    "sg:address":"Calle de Valle Gistain, S/n",
    "sg:city":"Monzon",
    "sg:orig_category":"Promotores Constructores",
    "sg:phone":"+34 974 41 70 86",
    "sg:postcode":"22400",
    "sg:province":"Huesca",
    "wof:name":"Ute Variante Monzon",
    "wof:placetype":"venue"
},
  "geometry": {"coordinates":[0.1915819943,41.9130134583],"type":"Point"}
}