{
  "type": "Feature",
  "properties": {
    "addr:full":"Plaz Villa (la), 1 Sos Del Rey Catolico Zaragoza 50680",
    "addr:postcode":"50680",
    "addr:street":"Sos",
    "iso:country":"ES",
    "sg:address":"Plaz Villa (la), 1",
    "sg:city":"Sos Del Rey Catolico",
    "sg:orig_category":"Administraciones Regionales, Departamentales Y Locales",
    "sg:phone":"+34 948 88 80 65",
    "sg:postcode":"50680",
    "sg:province":"Zaragoza",
    "wof:name":"Ayuntamiento De Sos Del Rey Catolico",
    "wof:placetype":"venue"
},
  "geometry": {"coordinates":[-1.2313617468,42.4855041504],"type":"Point"}
}