{
  "type": "Feature",
  "properties": {
    "addr:full":"Carrer de Barcelona (de), 76 Salou Tarragona 43840",
    "addr:housenumber":"76",
    "addr:postcode":"43840",
    "addr:street":"Carrer De Barcelona De",
    "iso:country":"ES",
    "sg:address":"Carrer de Barcelona (de), 76",
    "sg:city":"Salou",
    "sg:orig_category":"Inmobiliaria (agencias)",
    "sg:phone":"+34 977 38 29 06",
    "sg:postcode":"43840",
    "sg:province":"Tarragona",
    "wof:name":"Gestion Inmobiliaria Barnamar S.l",
    "wof:placetype":"venue"
},
  "geometry": {"coordinates":[1.1324139833,41.0837059021],"type":"Point"}
}