{
  "type": "Feature",
  "properties": {
    "addr:full":"Carr Sant Pau, 31 Figueres Girona 17600",
    "addr:housenumber":"31",
    "addr:postcode":"17600",
    "addr:street":"Carr Sant Pau",
    "iso:country":"ES",
    "sg:address":"Carr Sant Pau, 31",
    "sg:city":"Figueres",
    "sg:orig_category":"Cajas De Ahorro",
    "sg:phone":"+34 972 67 86 23",
    "sg:postcode":"17600",
    "sg:province":"Girona",
    "sg:website":"www.lacaixa.es",
    "wof:name":"Caixa D'estalvis I Pensions De Barcelona",
    "wof:placetype":"venue"
},
  "geometry": {"coordinates":[2.9581100941,42.2656898499],"type":"Point"}
}