{
  "type": "Feature",
  "properties": {
    "iso:country":"ES",
    "sg:address":"Calle de Do\u00d1a Romera, 26",
    "sg:city":"Getafe",
    "sg:orig_category":"Transportes Por V\u00cdas Navegables",
    "sg:phone":"+34 916 82 96 84",
    "sg:postcode":"28901",
    "sg:province":"Madrid",
    "sg:website":"www.castillatrans.com",
    "wof:name":"Pascual Merino Francisco Javier",
    "wof:placetype":"venue"
},
  "geometry": {"coordinates":[-3.7303862572,40.3011665344],"type":"Point"}
}