{
  "type": "Feature",
  "properties": {
    "iso:country":"ES",
    "sg:address":"Calle de Muelle De Oriente, S/n",
    "sg:city":"Gijon",
    "sg:orig_category":"Restaurantes",
    "sg:phone":"+34 985 34 90 96",
    "sg:postcode":"33201",
    "sg:province":"Asturias",
    "wof:name":"Arroyo Alvarez S.l.",
    "wof:placetype":"venue"
},
  "geometry": {"coordinates":[-5.6640729904,43.5445022583],"type":"Point"}
}