{
  "type": "Feature",
  "properties": {
    "addr:full":"Calle de Queipo De Llano, S/n Santa Maria Del Tietar \u00c1vila 05429",
    "addr:postcode":"05429",
    "addr:street":"Calle De Queipo De Llano S / N;A\u0301Vila",
    "iso:country":"ES",
    "sg:address":"Calle de Queipo De Llano, S/n",
    "sg:city":"Santa Maria Del Tietar",
    "sg:orig_category":"Cr\u00cda De Bovinos",
    "sg:phone":"+34 918 66 20 75",
    "sg:postcode":"05429",
    "sg:province":"\u00c1vila",
    "wof:name":"Diaz Hernandez Polonio",
    "wof:placetype":"venue"
},
  "geometry": {"coordinates":[-97.78224945069999,45.7040786743],"type":"Point"}
}