{
  "type": "Feature",
  "properties": {
    "iso:country":"ES",
    "sg:address":"Carrer de Ferran, 22",
    "sg:city":"Barcelona",
    "sg:orig_category":"Perfumer\u00cda (al Por Menor)",
    "sg:phone":"+34 934 12 58 60",
    "sg:postcode":"08002",
    "sg:province":"Barcelona",
    "sg:website":"www.boris-reformy.com",
    "wof:name":"Santaana Vega Montserrat",
    "wof:placetype":"venue"
},
  "geometry": {"coordinates":[2.1753408909,41.3811798096],"type":"Point"}
}