{
  "type": "Feature",
  "properties": {
    "iso:country":"ES",
    "sg:address":"Garraf (pol Ind Cantallops), S/n",
    "sg:city":"Lli\u00e7a Vall",
    "sg:orig_category":"Fabricaci\u00d3n De Moldes Y Modelos",
    "sg:phone":"+34 938 44 53 22",
    "sg:postcode":"08185",
    "sg:province":"Barcelona",
    "wof:name":"Mol-sepi S.l.",
    "wof:placetype":"venue"
},
  "geometry": {"coordinates":[2.2302498817,41.5783081055],"type":"Point"}
}