{
  "type": "Feature",
  "properties": {
    "addr:full":"Pase Uribitarte, 13 Bilbao Vizcaya 48001",
    "addr:housenumber":"13",
    "addr:postcode":"48001",
    "addr:street":"Uribitarte",
    "iso:country":"ES",
    "sg:address":"Pase Uribitarte, 13",
    "sg:city":"Bilbao",
    "sg:orig_category":"Promotores Constructores",
    "sg:phone":"+34 944 24 55 35",
    "sg:postcode":"48001",
    "sg:province":"Vizcaya",
    "wof:name":"Loruri S.a.",
    "wof:placetype":"venue"
},
  "geometry": {"coordinates":[-2.929459095,43.265499115],"type":"Point"}
}