{
  "type": "Feature",
  "properties": {
    "addr:full":"Calle de Perez Carrillo, 1 Durcal Granada 18650",
    "addr:housenumber":"1",
    "addr:postcode":"18650",
    "addr:street":"Calle De Perez Carrillo",
    "iso:country":"ES",
    "sg:address":"Calle de Perez Carrillo, 1",
    "sg:city":"Durcal",
    "sg:orig_category":"Cajas De Ahorro",
    "sg:phone":"+34 958 78 18 08",
    "sg:postcode":"18650",
    "sg:province":"Granada",
    "sg:website":"www.lacaixa.es",
    "wof:name":"Caixa D'estalvis I Pensions De Barcelona",
    "wof:placetype":"venue"
},
  "geometry": {"coordinates":[-3.56696105,36.988067627],"type":"Point"}
}