{
  "type": "Feature",
  "properties": {
    "iso:country":"ES",
    "sg:address":"Calle de Natalio Rivas, 88",
    "sg:city":"Adra",
    "sg:orig_category":"Estancos",
    "sg:phone":"+34 950 40 04 42",
    "sg:postcode":"04770",
    "sg:province":"Almer\u00eda",
    "wof:name":"Fernandez Escudero Encarnacion",
    "wof:placetype":"venue"
},
  "geometry": {"coordinates":[-3.0194909573,36.7481498718],"type":"Point"}
}