{
  "type": "Feature",
  "properties": {
    "addr:full":"Carrer de Lleida, 7 Ampolla Tarragona 43895",
    "addr:housenumber":"7",
    "addr:postcode":"43895",
    "addr:street":"Carrer De Lleida",
    "iso:country":"ES",
    "sg:address":"Carrer de Lleida, 7",
    "sg:city":"Ampolla",
    "sg:orig_category":"Distribuci\u00d3n De Petr\u00d3leo Y Derivados",
    "sg:phone":"+34 977 46 00 25",
    "sg:postcode":"43895",
    "sg:province":"Tarragona",
    "wof:name":"Borras Lapeira Jose",
    "wof:placetype":"venue"
},
  "geometry": {"coordinates":[0.712059021,40.8127784729],"type":"Point"}
}