{
  "type": "Feature",
  "properties": {
    "addr:full":"Calle de Madre Maria Rosa Molas, S/n Quintanar Orden Toledo 45800",
    "addr:housenumber":"s / n",
    "addr:postcode":"45800",
    "addr:street":"Calle De Madre Maria;Molas",
    "iso:country":"ES",
    "sg:address":"Calle de Madre Maria Rosa Molas, S/n",
    "sg:city":"Quintanar Orden",
    "sg:classifiers":[
        {
            "category":"Food & Beverages",
            "subcategory":"Candy",
            "type":"Retail Goods"
        }
    ],
    "sg:phone":"+34 925 18 17 69",
    "sg:postcode":"45800",
    "sg:province":"Toledo",
    "sg:tags":[
        "confiter\u00cdas",
        "y",
        "de",
        "fabricaci\u00d3n",
        "chocolate"
    ],
    "wof:name":"Seofer Figueroa S. L.",
    "wof:placetype":"venue"
},
  "geometry": {"coordinates":[-3.0325639248,39.5883293152],"type":"Point"}
}