{
  "type": "Feature",
  "properties": {
    "addr:full":"Calle de Numancia, 30 Soria Soria 42001",
    "addr:housenumber":"30",
    "addr:postcode":"42001",
    "addr:street":"Calle De Numancia",
    "iso:country":"ES",
    "sg:address":"Calle de Numancia, 30",
    "sg:city":"Soria",
    "sg:orig_category":"Venta, Localizaci\u00d3n, Reparaci\u00d3n De Material E Instrumental M\u00c9dico",
    "sg:phone":"+34 975 21 39 54",
    "sg:postcode":"42001",
    "sg:province":"Soria",
    "wof:name":"Ortopedia Zaragoza S. L.",
    "wof:placetype":"venue"
},
  "geometry": {"coordinates":[-2.4679670334,41.7663497925],"type":"Point"}
}