{
  "type": "Feature",
  "properties": {
    "addr:full":"Calle de Santo Entierro, S/n S. Fernando C\u00e1diz 11100",
    "addr:housenumber":"s",
    "addr:postcode":"11100",
    "addr:street":"Calle De Santo Entierro;/ N S. Fernando Ca\u0301Diz",
    "iso:country":"ES",
    "sg:address":"Calle de Santo Entierro, S/n",
    "sg:city":"S. Fernando",
    "sg:orig_category":"Centros M\u00c9dicos Y Sociales, Dispensarios",
    "sg:phone":"+34 956 89 73 53",
    "sg:postcode":"11100",
    "sg:province":"C\u00e1diz",
    "wof:name":"Union Paralisis Cerebral",
    "wof:placetype":"venue"
},
  "geometry": {"coordinates":[-6.2062110901,36.4552497864],"type":"Point"}
}