{
  "type": "Feature",
  "properties": {
    "addr:full":"Calle de Pedro Aleixandre, 59 Valencia Valencia 46006",
    "addr:housenumber":"59",
    "addr:postcode":"46006",
    "addr:street":"Calle De Pedro Aleixandre",
    "iso:country":"ES",
    "sg:address":"Calle de Pedro Aleixandre, 59",
    "sg:city":"Valencia",
    "sg:orig_category":"Transportes Por Carretera: Lotes Completos, Mercanc\u00cdas Diversas",
    "sg:phone":"+34 963 11 13 70",
    "sg:postcode":"46006",
    "sg:province":"Valencia",
    "wof:name":"Gevasa S.a.",
    "wof:placetype":"venue"
},
  "geometry": {"coordinates":[-0.3599950075,39.4596176147],"type":"Point"}
}