{
  "type": "Feature",
  "properties": {
    "addr:full":"Calle de Trasmolinos, 14 Castro Rio C\u00f3rdoba 14840",
    "addr:housenumber":"14",
    "addr:postcode":"14840",
    "addr:street":"Calle De Trasmolinos;Rio Co\u0301Rdoba",
    "iso:country":"ES",
    "sg:address":"Calle de Trasmolinos, 14",
    "sg:city":"Castro Rio",
    "sg:orig_category":"Reparto A Domicilio De Productos Perecederos Y No Perecederos",
    "sg:phone":"+34 957 37 04 69",
    "sg:postcode":"14840",
    "sg:province":"C\u00f3rdoba",
    "wof:name":"Jupesa Alimentacion S.a.",
    "wof:placetype":"venue"
},
  "geometry": {"coordinates":[-4.4769291878,37.685760498],"type":"Point"}
}