{
  "type": "Feature",
  "properties": {
    "addr:full":"Rua Evaristo Correa Calderon, 64 Baralla Lugo 27680",
    "addr:housenumber":"64",
    "addr:postcode":"27680",
    "addr:street":"Rua Evaristo Correa Calderon",
    "iso:country":"ES",
    "sg:address":"Rua Evaristo Correa Calderon, 64",
    "sg:city":"Baralla",
    "sg:orig_category":"Material Y Suministros Para Veterinarios",
    "sg:phone":"+34 982 36 30 55",
    "sg:postcode":"27680",
    "sg:province":"Lugo",
    "wof:name":"Vali\u00f1o Varela Carmen",
    "wof:placetype":"venue"
},
  "geometry": {"coordinates":[-7.2504792213,42.8938598633],"type":"Point"}
}