{
  "type": "Feature",
  "properties": {
    "iso:country":"ES",
    "sg:address":"Ctra. Sineu, S/n",
    "sg:city":"Lloret Vistalegre",
    "sg:orig_category":"Cr\u00cda De Animales",
    "sg:phone":"+34 971 52 40 21",
    "sg:postcode":"07518",
    "sg:province":"Islas Baleares",
    "wof:name":"Comercial Coll Real S.l.",
    "wof:placetype":"venue"
},
  "geometry": {"coordinates":[2.9758861065,39.6176109314],"type":"Point"}
}