{
  "type": "Feature",
  "properties": {
    "addr:full":"Calle de Pablo Picasso, 17 Puente-genil C\u00f3rdoba 14500",
    "addr:housenumber":"17",
    "addr:postcode":"14500",
    "addr:street":"Calle De Pablo Picasso;Co\u0301Rdoba",
    "iso:country":"ES",
    "sg:address":"Calle de Pablo Picasso, 17",
    "sg:city":"Puente-genil",
    "sg:orig_category":"Transportes Por V\u00cdas Navegables",
    "sg:phone":"+34 957 60 13 01",
    "sg:postcode":"14500",
    "sg:province":"C\u00f3rdoba",
    "wof:name":"Transportes Granados Morillo S.l",
    "wof:placetype":"venue"
},
  "geometry": {"coordinates":[-4.7638449669,37.3917732239],"type":"Point"}
}