{
  "type": "Feature",
  "properties": {
    "addr:full":"Olakua Auzoa, 7 O\u00f1ati Guip\u00f9zcoa 20560",
    "addr:housenumber":"7",
    "addr:postcode":"20560",
    "addr:street":"Olakua Auzoa;Guipu\u0300Zcoa",
    "iso:country":"ES",
    "sg:address":"Olakua Auzoa, 7",
    "sg:city":"O\u00f1ati",
    "sg:orig_category":"Ense\u00d1anza Variada",
    "sg:phone":"+34 943 71 81 02",
    "sg:postcode":"20560",
    "sg:province":"Guip\u00f9zcoa",
    "wof:name":"Komalingua S.l.",
    "wof:placetype":"venue"
},
  "geometry": {"coordinates":[-2.4037969112,43.0318374634],"type":"Point"}
}