{
  "type": "Feature",
  "properties": {
    "addr:full":"Calle de Juanelo, 23 Madrid Madrid 28012",
    "addr:housenumber":"23",
    "addr:postcode":"madrid;28012",
    "addr:street":"Calle De Juanelo",
    "iso:country":"ES",
    "sg:address":"Calle de Juanelo, 23",
    "sg:city":"Madrid",
    "sg:orig_category":"Ropa Y Accesorios",
    "sg:phone":"+34 915 30 42 96",
    "sg:postcode":"28012",
    "sg:province":"Madrid",
    "wof:name":"Qing Jie S.l.",
    "wof:placetype":"venue"
},
  "geometry": {"coordinates":[-3.7066400051,40.410987854],"type":"Point"}
}