{
  "type": "Feature",
  "properties": {
    "iso:country":"ES",
    "sg:address":"Calle de Galileo, 29",
    "sg:city":"Madrid",
    "sg:orig_category":"Farmacias",
    "sg:phone":"+34 914 47 69 53",
    "sg:postcode":"28015",
    "sg:province":"Madrid",
    "wof:name":"Fernandez Gomez Rafael",
    "wof:placetype":"venue"
},
  "geometry": {"coordinates":[-3.7103846073,40.4326858521],"type":"Point"}
}