{
  "type": "Feature",
  "properties": {
    "addr:full":"Calle de Pintor Agrasot, 50 Orihuela Alicante 03300",
    "addr:housenumber":"50",
    "addr:postcode":"03300",
    "addr:street":"Calle De Pintor Agrasot",
    "iso:country":"ES",
    "sg:address":"Calle de Pintor Agrasot, 50",
    "sg:city":"Orihuela",
    "sg:orig_category":"Imprenta",
    "sg:phone":"+34 965 30 47 28",
    "sg:postcode":"03300",
    "sg:province":"Alicante",
    "wof:name":"Imprenta Oriolana Minerva S.l.",
    "wof:placetype":"venue"
},
  "geometry": {"coordinates":[-0.9397190213,38.0869598389],"type":"Point"}
}