{
  "type": "Feature",
  "properties": {
    "addr:full":"Carrer de Churruca, 6 Hospitalet Llobregat Barcelona 08906",
    "addr:housenumber":"6",
    "addr:postcode":"08906",
    "addr:street":"Carrer De Churruca",
    "iso:country":"ES",
    "sg:address":"Carrer de Churruca, 6",
    "sg:city":"Hospitalet Llobregat",
    "sg:orig_category":"Promotores Constructores",
    "sg:phone":"+34 934 38 76 39",
    "sg:postcode":"08906",
    "sg:province":"Barcelona",
    "wof:name":"Construcciones Renova S.c.p.",
    "wof:placetype":"venue"
},
  "geometry": {"coordinates":[2.1019020081,41.3760604858],"type":"Point"}
}