{
  "type": "Feature",
  "properties": {
    "addr:full":"Calle de Ansite, 80 Cruce De Arinaga Las Palmas 35118",
    "addr:housenumber":"80",
    "addr:postcode":"35118",
    "addr:street":"Calle De Ansite;Arinaga",
    "iso:country":"ES",
    "sg:address":"Calle de Ansite, 80",
    "sg:city":"Cruce De Arinaga",
    "sg:orig_category":"Farmacias",
    "sg:phone":"+34 928 18 10 42",
    "sg:postcode":"35118",
    "sg:province":"Las Palmas",
    "wof:name":"Valeron Martel Maria Isabel",
    "wof:placetype":"venue"
},
  "geometry": {"coordinates":[-15.4283294678,27.8782196045],"type":"Point"}
}