{
  "type": "Feature",
  "properties": {
    "addr:full":"Crt. Albacete, Km. 0069,4 Motilla Palancar Cuenca 16200",
    "addr:postcode":"16200",
    "addr:street":"Albacete Km. 0069,4",
    "iso:country":"ES",
    "sg:address":"Crt. Albacete, Km. 0069,4",
    "sg:city":"Motilla Palancar",
    "sg:orig_category":"Centros Empresariales",
    "sg:phone":"+34 969 33 13 26",
    "sg:postcode":"16200",
    "sg:province":"Cuenca",
    "wof:name":"Area De Servicios Motillana S.a.",
    "wof:placetype":"venue"
},
  "geometry": {"coordinates":[-1.9026776552,39.5571022034],"type":"Point"}
}