{
  "type": "Feature",
  "properties": {
    "iso:country":"ES",
    "sg:address":"Carrer de Saragossa (de), 6",
    "sg:city":"Salou",
    "sg:orig_category":"Ropa Para Se\u00d1oras Y Caballeros (al Por Menor)",
    "sg:phone":"+34 977 35 26 74",
    "sg:postcode":"43840",
    "sg:province":"Tarragona",
    "wof:name":"Carricondo Vinade Avelino",
    "wof:placetype":"venue"
},
  "geometry": {"coordinates":[1.1453050375,41.0734519958],"type":"Point"}
}