{
  "type": "Feature",
  "properties": {
    "addr:full":"Calle de Mejico, 2 Coslada Madrid 28820",
    "addr:housenumber":"2",
    "addr:postcode":"28820",
    "addr:street":"Calle De Mejico",
    "iso:country":"ES",
    "sg:address":"Calle de Mejico, 2",
    "sg:city":"Coslada",
    "sg:orig_category":"Empresas De Pintura Y Revestimientos",
    "sg:phone":"+34 916 73 92 82",
    "sg:postcode":"28820",
    "sg:province":"Madrid",
    "wof:name":"Jimenez Arroyo Jose",
    "wof:placetype":"venue"
},
  "geometry": {"coordinates":[-3.548058033,40.4228210449],"type":"Point"}
}