{
  "type": "Feature",
  "properties": {
    "iso:country":"ES",
    "sg:address":"Calle de Cervantes, 5",
    "sg:city":"Villanueva Cordoba",
    "sg:orig_category":"Asociaciones Y Clubs Deportivos",
    "sg:phone":"+34 957 12 08 08",
    "sg:postcode":"14440",
    "sg:province":"C\u00f3rdoba",
    "wof:name":"Armeria La Perdiz S.l.",
    "wof:placetype":"venue"
},
  "geometry": {"coordinates":[-4.6270856857,38.3215141296],"type":"Point"}
}