{
  "type": "Feature",
  "properties": {
    "addr:full":"Paulo Vi Auzunea, 6 Azpeitia Guip\u00f9zcoa 20730",
    "addr:housenumber":"6",
    "addr:postcode":"20730",
    "addr:street":"Paulo Vi Auzunea;Guipu\u0300Zcoa",
    "iso:country":"ES",
    "sg:address":"Paulo Vi Auzunea, 6",
    "sg:city":"Azpeitia",
    "sg:orig_category":"Ense\u00d1anza: Idiomas",
    "sg:phone":"+34 943 81 53 19",
    "sg:postcode":"20730",
    "sg:province":"Guip\u00f9zcoa",
    "wof:name":"Oclock Ingles Ikastetxea",
    "wof:placetype":"venue"
},
  "geometry": {"coordinates":[-2.2668409348,43.1811981201],"type":"Point"}
}