{
  "type": "Feature",
  "properties": {
    "addr:full":"Ctra Sevilla-huelva, Km. 0563,0 Espartinas Sevilla 41807",
    "addr:postcode":"41807",
    "addr:street":"Ctra Sevilla-Huelva Km. 0563,0",
    "iso:country":"ES",
    "sg:address":"Ctra Sevilla-huelva, Km. 0563,0",
    "sg:city":"Espartinas",
    "sg:orig_category":"Comunidades Religiosas",
    "sg:phone":"+34 954 11 39 12",
    "sg:postcode":"41807",
    "sg:province":"Sevilla",
    "wof:name":"Convento De Reverendos Padres Franciscan",
    "wof:placetype":"venue"
},
  "geometry": {"coordinates":[-6.1235818863,37.3828926086],"type":"Point"}
}