{
  "type": "Feature",
  "properties": {
    "iso:country":"ES",
    "sg:address":"Calle de Sorni, 18",
    "sg:city":"Valencia",
    "sg:orig_category":"Farmacias",
    "sg:phone":"+34 963 51 65 49",
    "sg:postcode":"46004",
    "sg:province":"Valencia",
    "wof:name":"Soler Llobell Roger",
    "wof:placetype":"venue"
},
  "geometry": {"coordinates":[-0.3684524894,39.4702377319],"type":"Point"}
}