{
  "type": "Feature",
  "properties": {
    "iso:country":"ES",
    "sg:address":"Avgd Miguel Hernandez, 38",
    "sg:city":"Benifaio",
    "sg:orig_category":"Cl\u00cdnicas Dentales",
    "sg:phone":"+34 961 79 40 50",
    "sg:postcode":"46450",
    "sg:province":"Valencia",
    "wof:name":"Clinica Dental Benifaio C.b.",
    "wof:placetype":"venue"
},
  "geometry": {"coordinates":[-0.4220300019,39.2844238281],"type":"Point"}
}