{
  "type": "Feature",
  "properties": {
    "iso:country":"ES",
    "sg:address":"Calle de Prieto Moreno, 26",
    "sg:city":"Zubia",
    "sg:orig_category":"Promotores Constructores",
    "sg:phone":"+34 958 59 10 18",
    "sg:postcode":"18140",
    "sg:province":"Granada",
    "wof:name":"Alguacil Diaz Enrique Javier",
    "wof:placetype":"venue"
},
  "geometry": {"coordinates":[-3.5851101875,37.1149253845],"type":"Point"}
}