{
  "type": "Feature",
  "properties": {
    "addr:full":"Carrer de Joan Prim, 74 Granollers Barcelona 08402",
    "addr:housenumber":"74",
    "addr:postcode":"08402",
    "addr:street":"Carrer De Joan Prim",
    "iso:country":"ES",
    "sg:address":"Carrer de Joan Prim, 74",
    "sg:city":"Granollers",
    "sg:orig_category":"Sociedades, Compa\u00d1\u00cdas Aseguradoras",
    "sg:phone":"+34 938 79 45 38",
    "sg:postcode":"08402",
    "sg:province":"Barcelona",
    "wof:name":"Seguros Catalana Occidente S.a. De Seguros Y Reaseguros",
    "wof:placetype":"venue"
},
  "geometry": {"coordinates":[2.2900168896,41.6117401123],"type":"Point"}
}