{
  "type": "Feature",
  "properties": {
    "addr:full":"Avda Vilaboa, S/n Vilaboa La Coru\u00f1a 15174",
    "addr:housenumber":"s / n",
    "addr:postcode":"15174",
    "addr:street":"Avda Vilaboa;La Corun\u0303A",
    "iso:country":"ES",
    "sg:address":"Avda Vilaboa, S/n",
    "sg:city":"Vilaboa",
    "sg:orig_category":"Ense\u00d1anza Secundaria: Colegios Y Escuelas Privadas",
    "sg:phone":"+34 981 66 36 24",
    "sg:postcode":"15174",
    "sg:province":"La Coru\u00f1a",
    "wof:name":"Calvi\u00f1o Seijas Monica",
    "wof:placetype":"venue"
},
  "geometry": {"coordinates":[-8.3827590942,43.3096084595],"type":"Point"}
}