{
  "type": "Feature",
  "properties": {
    "addr:full":"Calle de Cervantes, 26 Cuenca Cuenca 16004",
    "addr:housenumber":"26",
    "addr:postcode":"16004",
    "addr:street":"Calle De Cervantes",
    "iso:country":"ES",
    "sg:address":"Calle de Cervantes, 26",
    "sg:city":"Cuenca",
    "sg:orig_category":"Ropa Para Se\u00d1oras (al Por Menor)",
    "sg:phone":"+34 969 23 69 27",
    "sg:postcode":"16004",
    "sg:province":"Cuenca",
    "wof:name":"Modas Aplicate Siglo Xxi S.l.",
    "wof:placetype":"venue"
},
  "geometry": {"coordinates":[-2.1362679005,40.0704345703],"type":"Point"}
}