{
  "type": "Feature",
  "properties": {
    "addr:full":"Trva Puente Virrey, 55 Zaragoza Zaragoza 50007",
    "addr:housenumber":"55",
    "addr:postcode":"50007",
    "addr:street":"Trva Puente Virrey",
    "iso:country":"ES",
    "sg:address":"Trva Puente Virrey, 55",
    "sg:city":"Zaragoza",
    "sg:orig_category":"Empresarios",
    "sg:phone":"+34 976 27 42 79",
    "sg:postcode":"50007",
    "sg:province":"Zaragoza",
    "wof:name":"Balcaul S.l.",
    "wof:placetype":"venue"
},
  "geometry": {"coordinates":[-0.875138998,41.6349105835],"type":"Point"}
}