{
  "type": "Feature",
  "properties": {
    "addr:full":"Calle de Santo Domingo, S/n Jerez De La Frontera C\u00e1diz 11402",
    "addr:housenumber":"s / n",
    "addr:postcode":"11402",
    "addr:street":"Calle De Santo Domingo",
    "iso:country":"ES",
    "sg:address":"Calle de Santo Domingo, S/n",
    "sg:city":"Jerez De La Frontera",
    "sg:orig_category":"Muebles Y Accesorios Para Cocinas Y Cuartos De Ba\u00d1o (al Por Menor)",
    "sg:phone":"+34 956 33 61 74",
    "sg:postcode":"11402",
    "sg:province":"C\u00e1diz",
    "wof:name":"Ladron De Guevara Gonzalez Agustin",
    "wof:placetype":"venue"
},
  "geometry": {"coordinates":[-6.1343898773,36.6892166138],"type":"Point"}
}