{
  "type": "Feature",
  "properties": {
    "iso:country":"ES",
    "sg:address":"Calle de Plasencia, 6",
    "sg:city":"Montehermoso",
    "sg:orig_category":"Plomeros",
    "sg:phone":"+34 927 67 50 80",
    "sg:postcode":"10810",
    "sg:province":"C\u00e1ceres",
    "wof:name":"Hernandez Retortillo Juan Jose",
    "wof:placetype":"venue"
},
  "geometry": {"coordinates":[-6.3520870209,40.0872764587],"type":"Point"}
}