{
  "type": "Feature",
  "properties": {
    "addr:full":"Calle de Ferrocarril Minero, S/n Agua Amarga Almer\u00eda 04149",
    "addr:housenumber":"s / n",
    "addr:postcode":"04149",
    "addr:street":"Calle De Ferrocarril Minero;Almeri\u0301A",
    "iso:country":"ES",
    "sg:address":"Calle de Ferrocarril Minero, S/n",
    "sg:city":"Agua Amarga",
    "sg:orig_category":"Molduras, Junquillos, Listones Y Molduras Perforadas",
    "sg:phone":"+34 950 13 82 14",
    "sg:postcode":"04149",
    "sg:province":"Almer\u00eda",
    "wof:name":"Zamora Hernandez Francisco",
    "wof:placetype":"venue"
},
  "geometry": {"coordinates":[-1.9351005554,36.9409484863],"type":"Point"}
}