{
  "type": "Feature",
  "properties": {
    "iso:country":"ES",
    "sg:address":"Avda Valencia, 110",
    "sg:city":"Castellon",
    "sg:orig_category":"Venta, Instalaci\u00d3n De Calefacci\u00d3n",
    "sg:phone":"+34 964 21 96 33",
    "sg:postcode":"12006",
    "sg:province":"Castell\u00f3n",
    "wof:name":"Dava S.a.",
    "wof:placetype":"venue"
},
  "geometry": {"coordinates":[-0.1292939931,40.0168533325],"type":"Point"}
}