{
  "type": "Feature",
  "properties": {
    "iso:country":"ES",
    "sg:address":"Calle de Antonio Martelo, 10",
    "sg:city":"Malaga",
    "sg:orig_category":"Ropa Para Caballeros (al Por Menor)",
    "sg:phone":"+34 952 31 05 57",
    "sg:postcode":"29006",
    "sg:province":"M\u00e1laga",
    "wof:name":"Marin Fernandez Miguel",
    "wof:placetype":"venue"
},
  "geometry": {"coordinates":[-4.4411182404,36.7110023499],"type":"Point"}
}