{
  "type": "Feature",
  "properties": {
    "iso:country":"ES",
    "sg:address":"Calle de Arena (la), 4",
    "sg:city":"Galletas",
    "sg:orig_category":"Telas Y Sedas (al Por Menor)",
    "sg:phone":"+34 922 78 56 46",
    "sg:postcode":"38631",
    "sg:province":"Santa Cruz De Tenerife",
    "wof:name":"Herrera Rancel E Hijos S.l.",
    "wof:placetype":"venue"
},
  "geometry": {"coordinates":[-16.6537818909,28.008480072],"type":"Point"}
}