{
  "type": "Feature",
  "properties": {
    "addr:full":"Ctra Ingenio (del), 41 Almeria Almer\u00eda 04009",
    "addr:housenumber":"41",
    "addr:postcode":"04009",
    "addr:street":"Ctra Ingenio Del",
    "iso:country":"ES",
    "sg:address":"Ctra Ingenio (del), 41",
    "sg:city":"Almeria",
    "sg:orig_category":"Artes Gr\u00c1ficas, Artes Pl\u00c1sticas (curso)",
    "sg:phone":"+34 950 22 66 94",
    "sg:postcode":"04009",
    "sg:province":"Almer\u00eda",
    "wof:name":"Pascual Morales Francisca",
    "wof:placetype":"venue"
},
  "geometry": {"coordinates":[-2.4355390072,36.84400177],"type":"Point"}
}