{
  "type": "Feature",
  "properties": {
    "iso:country":"ES",
    "sg:address":"Calle de Doctor Moreno, 12",
    "sg:city":"Valladolid",
    "sg:orig_category":"Molduras, Junquillos, Listones Y Molduras Perforadas",
    "sg:phone":"+34 983 22 70 12",
    "sg:postcode":"47008",
    "sg:province":"Valladolid",
    "wof:name":"Mera Sanmartin Rafael",
    "wof:placetype":"venue"
},
  "geometry": {"coordinates":[-4.7403182983,41.6277961731],"type":"Point"}
}