{
  "type": "Feature",
  "properties": {
    "addr:full":"Av Bogatell, 23 Barcelona Barcelona 08005",
    "addr:housenumber":"23",
    "addr:postcode":"08005",
    "addr:street":"Av Bogatell",
    "iso:country":"ES",
    "sg:address":"Av Bogatell, 23",
    "sg:city":"Barcelona",
    "sg:orig_category":"Suministros Y Materiales Industriales",
    "sg:phone":"+34 932 21 12 23",
    "sg:postcode":"08005",
    "sg:province":"Barcelona",
    "sg:website":"www.deublin.com",
    "wof:name":"Deublin Iberica S.l.",
    "wof:placetype":"venue"
},
  "geometry": {"coordinates":[2.1961529255,41.3927383423],"type":"Point"}
}