{
  "type": "Feature",
  "properties": {
    "addr:full":"Calle de Juan De Herrera, 14 Santander Cantabria 39002",
    "addr:housenumber":"14",
    "addr:postcode":"39002",
    "addr:street":"Calle De Juan De Herrera",
    "iso:country":"ES",
    "sg:address":"Calle de Juan De Herrera, 14",
    "sg:city":"Santander",
    "sg:orig_category":"Ropa Para Se\u00d1oras Y Caballeros (al Por Menor)",
    "sg:phone":"+34 942 31 91 36",
    "sg:postcode":"39002",
    "sg:province":"Cantabria",
    "sg:website":"www.robertoverino.com",
    "wof:name":"Roberto Verino Difusion S.a.",
    "wof:placetype":"venue"
},
  "geometry": {"coordinates":[-3.8079829216,43.4619674683],"type":"Point"}
}