{
  "type": "Feature",
  "properties": {
    "iso:country":"ES",
    "sg:address":"Calle de Molino De Viento (del), S/n",
    "sg:city":"Colmenar Viejo",
    "sg:orig_category":"Caf\u00c9s, Bares, Cervecer\u00cdas",
    "sg:phone":"+34 918 45 95 87",
    "sg:postcode":"28770",
    "sg:province":"Madrid",
    "wof:name":"Fernandez Garcia Soledad",
    "wof:placetype":"venue"
},
  "geometry": {"coordinates":[-3.7731199265,40.6647148132],"type":"Point"}
}