{
  "type": "Feature",
  "properties": {
    "addr:full":"Avda Bulevar De El Ejido, S/n Ejido Almer\u00eda 04700",
    "addr:postcode":"04700",
    "addr:street":"Bulevar De El Ejido S / N Ejido Almeri\u0301A",
    "iso:country":"ES",
    "sg:address":"Avda Bulevar De El Ejido, S/n",
    "sg:city":"Ejido",
    "sg:orig_category":"Alimentaci\u00d3n General (al Por Menor)",
    "sg:phone":"+34 950 57 33 11",
    "sg:postcode":"04700",
    "sg:province":"Almer\u00eda",
    "wof:name":"Distribuidora Internacional De Alimentacion S.a.",
    "wof:placetype":"venue"
},
  "geometry": {"coordinates":[-2.8176040649,36.7727012634],"type":"Point"}
}