{
  "type": "Feature",
  "properties": {
    "iso:country":"ES",
    "sg:address":"Carrer de Corro, 263",
    "sg:city":"Granollers",
    "sg:orig_category":"Asesor\u00cda, Estudio Y Control Medioambiental",
    "sg:phone":"+34 938 46 78 79",
    "sg:postcode":"08401",
    "sg:province":"Barcelona",
    "wof:name":"Consultoria Ambiental Gesmat Sl",
    "wof:placetype":"venue"
},
  "geometry": {"coordinates":[2.2905449867,41.6167945862],"type":"Point"}
}