{
  "type": "Feature",
  "properties": {
    "addr:full":"Calle de Eras Del Cerrillo, 5 Ciudad Real Ciudad Real 13004",
    "addr:housenumber":"5",
    "addr:postcode":"13004",
    "addr:street":"Calle De Eras Del Cerrillo",
    "iso:country":"ES",
    "sg:address":"Calle de Eras Del Cerrillo, 5",
    "sg:city":"Ciudad Real",
    "sg:orig_category":"Aparcamientos (infraestructuras, Accesorios)",
    "sg:phone":"+34 926 27 34 42",
    "sg:postcode":"13004",
    "sg:province":"Ciudad Real",
    "wof:name":"Gn Impala S.l",
    "wof:placetype":"venue"
},
  "geometry": {"coordinates":[-3.9298830032,38.9779129028],"type":"Point"}
}