{
  "type": "Feature",
  "properties": {
    "addr:full":"Calle de Veracruz, 8 Tomelloso Ciudad Real 13700",
    "addr:housenumber":"8",
    "addr:postcode":"13700",
    "addr:street":"Calle De Veracruz",
    "iso:country":"ES",
    "sg:address":"Calle de Veracruz, 8",
    "sg:city":"Tomelloso",
    "sg:orig_category":"Alimentaci\u00d3n General (al Por Menor)",
    "sg:phone":"+34 926 51 10 19",
    "sg:postcode":"13700",
    "sg:province":"Ciudad Real",
    "wof:name":"Gamial S.l.",
    "wof:placetype":"venue"
},
  "geometry": {"coordinates":[-3.0196890831,39.158039093],"type":"Point"}
}