{
  "type": "Feature",
  "properties": {
    "addr:full":"Calle de Palacios, 29 Puerto De Santa Maria C\u00e1diz 11500",
    "addr:housenumber":"29",
    "addr:postcode":"11500",
    "addr:street":"Calle De Palacios;Ca\u0301Diz",
    "iso:country":"ES",
    "sg:address":"Calle de Palacios, 29",
    "sg:city":"Puerto De Santa Maria",
    "sg:orig_category":"Lencer\u00cda Femenina, Corseter\u00cda, Trajes De Ba\u00d1o (al Por Menor)",
    "sg:phone":"+34 956 87 61 66",
    "sg:postcode":"11500",
    "sg:province":"C\u00e1diz",
    "wof:name":"Guerrero Ortega Maria Del Carmen",
    "wof:placetype":"venue"
},
  "geometry": {"coordinates":[-6.2265992165,36.5980567932],"type":"Point"}
}