{
  "type": "Feature",
  "properties": {
    "addr:full":"Calle de Ayuntamiento, 1 Micereces Tera Zamora 49624",
    "addr:housenumber":"1",
    "addr:postcode":"49624",
    "addr:street":"Calle De Ayuntamiento;Zamora",
    "iso:country":"ES",
    "sg:address":"Calle de Ayuntamiento, 1",
    "sg:city":"Micereces Tera",
    "sg:orig_category":"Iglesia Cat\u00d3lica",
    "sg:phone":"+34 980 65 86 68",
    "sg:postcode":"49624",
    "sg:province":"Zamora",
    "wof:name":"Diocesis Astorga Administracion",
    "wof:placetype":"venue"
},
  "geometry": {"coordinates":[-5.8727035522,41.9878311157],"type":"Point"}
}