{
  "type": "Feature",
  "properties": {
    "iso:country":"ES",
    "sg:address":"Calle de Aligustre, 32",
    "sg:city":"Madrid",
    "sg:orig_category":"Mec\u00c1nico Del Autom\u00d3vil",
    "sg:phone":"+34 913 15 84 25",
    "sg:postcode":"28039",
    "sg:province":"Madrid",
    "wof:name":"Rodriguez De La Puente Eduardo",
    "wof:placetype":"venue"
},
  "geometry": {"coordinates":[-3.7048039436,40.4665527344],"type":"Point"}
}