{
  "type": "Feature",
  "properties": {
    "addr:full":"Pol Ind Fadrell, S/n Castello Plana Castell\u00f3n 12005",
    "addr:housenumber":"s",
    "addr:postcode":"12005",
    "addr:street":"/ N",
    "iso:country":"ES",
    "sg:address":"Pol Ind Fadrell, S/n",
    "sg:city":"Castello Plana",
    "sg:orig_category":"Aluminio Y Aleaciones (producci\u00d3n, Transformaci\u00d3n, Negocio)",
    "sg:phone":"+34 964 24 48 02",
    "sg:postcode":"12005",
    "sg:province":"Castell\u00f3n",
    "wof:name":"Paterno S.l.",
    "wof:placetype":"venue"
},
  "geometry": {"coordinates":[-0.0570270009,39.9575424194],"type":"Point"}
}