{
  "type": "Feature",
  "properties": {
    "iso:country":"ES",
    "sg:address":"Calle de Urraca, 29",
    "sg:city":"Valdelagua",
    "sg:orig_category":"Inform\u00c1tica: Consultores",
    "sg:phone":"+34 923 13 95 17",
    "sg:postcode":"37194",
    "sg:province":"Salamanca",
    "wof:name":"Cantero Y Soriano Asociados S.l.",
    "wof:placetype":"venue"
},
  "geometry": {"coordinates":[-5.6234240532,40.9329566956],"type":"Point"}
}