{
  "type": "Feature",
  "properties": {
    "iso:country":"ES",
    "sg:address":"Calle de Francisco Gonzalez Diaz, 3",
    "sg:city":"Palmas De Gran Canaria",
    "sg:orig_category":"M\u00c9dicos: Cirug\u00cda General",
    "sg:phone":"+34 928 24 35 49",
    "sg:postcode":"35005",
    "sg:province":"Las Palmas",
    "wof:name":"Sosa Benitez Esteban",
    "wof:placetype":"venue"
},
  "geometry": {"coordinates":[-15.4266271591,28.1210079193],"type":"Point"}
}