{
  "type": "Feature",
  "properties": {
    "addr:full":"Cami Passatemps, S/n Garriga Islas Baleares 07120",
    "addr:housenumber":"/ n",
    "addr:postcode":"07120",
    "addr:street":"Passatemps S",
    "iso:country":"ES",
    "sg:address":"Cami Passatemps, S/n",
    "sg:city":"Garriga",
    "sg:orig_category":"Iglesia Cat\u00d3lica",
    "sg:phone":"+34 971 43 91 20",
    "sg:postcode":"07120",
    "sg:province":"Islas Baleares",
    "wof:name":"Obispado De Mallorca",
    "wof:placetype":"venue"
},
  "geometry": {"coordinates":[2.655944109,39.6189918518],"type":"Point"}
}