{
  "type": "Feature",
  "properties": {
    "addr:full":"Avda Fernandez Latorre, S/n Coru\u00d1a La Coru\u00f1a 15006",
    "addr:housenumber":"s / n",
    "addr:postcode":"15006",
    "addr:street":"Avda Fernandez Latorre;La Corun\u0303A",
    "iso:country":"ES",
    "sg:address":"Avda Fernandez Latorre, S/n",
    "sg:city":"Coru\u00d1a",
    "sg:orig_category":"Bancos",
    "sg:phone":"+34 981 29 65 00",
    "sg:postcode":"15006",
    "sg:province":"La Coru\u00f1a",
    "wof:name":"Banco De Galicia",
    "wof:placetype":"venue"
},
  "geometry": {"coordinates":[-8.4039287567,43.3589439392],"type":"Point"}
}