{
  "type": "Feature",
  "properties": {
    "addr:full":"Calle de Manuel Murguia, 36 Coru\u00d1a La Coru\u00f1a 15011",
    "addr:housenumber":"36",
    "addr:postcode":"15011",
    "addr:street":"Calle De Manuel Murguia;Corun\u0303A",
    "iso:country":"ES",
    "sg:address":"Calle de Manuel Murguia, 36",
    "sg:city":"Coru\u00d1a",
    "sg:orig_category":"Venta, Alquiler De Instrumentos Y Accesorios De M\u00dasica",
    "sg:phone":"+34 981 26 30 67",
    "sg:postcode":"15011",
    "sg:province":"La Coru\u00f1a",
    "wof:name":"Musical Pontevedra S.l.",
    "wof:placetype":"venue"
},
  "geometry": {"coordinates":[-8.4187021255,43.3693275452],"type":"Point"}
}