{
  "type": "Feature",
  "properties": {
    "addr:full":"Calle de Salvador De Madariaga, 8 Badajoz Badajoz 06011",
    "addr:housenumber":"8",
    "addr:postcode":"06011",
    "addr:street":"Calle De Salvador De Madariaga",
    "iso:country":"ES",
    "sg:address":"Calle de Salvador De Madariaga, 8",
    "sg:city":"Badajoz",
    "sg:orig_category":"Importaci\u00d3n",
    "sg:phone":"+34 924 23 74 15",
    "sg:postcode":"06011",
    "sg:province":"Badajoz",
    "wof:name":"Suministrosimportaciones Y Mantenimientos Electronicos S.a.",
    "wof:placetype":"venue"
},
  "geometry": {"coordinates":[-6.9856114388,38.8650360107],"type":"Point"}
}