{
  "type": "Feature",
  "properties": {
    "addr:full":"Calle de San Jeronimo, 27 Granada Granada 18001",
    "addr:housenumber":"27",
    "addr:postcode":"18001",
    "addr:street":"Calle De San Jeronimo",
    "iso:country":"ES",
    "sg:address":"Calle de San Jeronimo, 27",
    "sg:city":"Granada",
    "sg:orig_category":"Empresarios",
    "sg:phone":"+34 958 20 65 08",
    "sg:postcode":"18001",
    "sg:province":"Granada",
    "wof:name":"Fundacion Euro-arabe De Altos Estudios",
    "wof:placetype":"venue"
},
  "geometry": {"coordinates":[-3.6012039185,37.1780891418],"type":"Point"}
}