{
  "type": "Feature",
  "properties": {
    "iso:country":"ES",
    "sg:address":"Calle de Rio Alberche, 50",
    "sg:city":"Poligono Sta M. De Benquerencia",
    "sg:orig_category":"Telas Y Sedas (al Por Menor)",
    "sg:phone":"+34 925 23 07 64",
    "sg:postcode":"45007",
    "sg:province":"Toledo",
    "wof:name":"Fernandez Lazaro Maria Del Sol",
    "wof:placetype":"venue"
},
  "geometry": {"coordinates":[-3.9446640015,39.867603302],"type":"Point"}
}