{
  "type": "Feature",
  "properties": {
    "iso:country":"ES",
    "sg:address":"Carr Josep Pla, 4",
    "sg:city":"Fornells-park",
    "sg:orig_category":"Internados & Ense\u00d1anza Privada",
    "sg:phone":"+34 972 47 60 65",
    "sg:postcode":"17458",
    "sg:province":"Girona",
    "sg:website":"www.saintgeorgeschool.es",
    "wof:name":"Saint George's School S.l.",
    "wof:placetype":"venue"
},
  "geometry": {"coordinates":[2.8099250793,41.9300727844],"type":"Point"}
}