{
  "type": "Feature",
  "properties": {
    "iso:country":"ES",
    "sg:address":"Carr Casas I Amigo, 74",
    "sg:city":"Badalona",
    "sg:orig_category":"Internados & Ense\u00d1anza Privada",
    "sg:phone":"+34 933 88 00 39",
    "sg:postcode":"08917",
    "sg:province":"Barcelona",
    "wof:name":"Colegi Montserrat S.l.",
    "wof:placetype":"venue"
},
  "geometry": {"coordinates":[2.2341299057,41.4509162903],"type":"Point"}
}