{
  "type": "Feature",
  "properties": {
    "iso:country":"ES",
    "sg:address":"Ctra. Gijon-sevilla, S/n",
    "sg:city":"Aldeaseca Armu\u00f1a",
    "sg:orig_category":"Asistencia Social",
    "sg:phone":"+34 923 25 07 27",
    "sg:postcode":"37189",
    "sg:province":"Salamanca",
    "wof:name":"Sociedad Salmantina Protectora De Animales Y Plantas",
    "wof:placetype":"venue"
},
  "geometry": {"coordinates":[-5.6705870628,41.0207595825],"type":"Point"}
}