{
  "type": "Feature",
  "properties": {
    "iso:country":"ES",
    "sg:address":"Carrer de Eusebi Guell, 140",
    "sg:city":"S. Boi Llobregat",
    "sg:orig_category":"Alimentaci\u00d3n General (al Por Mayor)",
    "sg:phone":"+34 936 54 49 51",
    "sg:postcode":"08830",
    "sg:province":"Barcelona",
    "wof:name":"Vivanco Diaz Nicasio",
    "wof:placetype":"venue"
},
  "geometry": {"coordinates":[2.0249783993,41.3464813232],"type":"Point"}
}