{
  "type": "Feature",
  "properties": {
    "addr:full":"Avda Espa\u00d1a, 26 Majadahonda Madrid 28220",
    "addr:housenumber":"26",
    "addr:postcode":"28220",
    "addr:street":"Avda Espan\u0303A",
    "iso:country":"ES",
    "sg:address":"Avda Espa\u00d1a, 26",
    "sg:city":"Majadahonda",
    "sg:orig_category":"Moda",
    "sg:phone":"+34 916 38 16 96",
    "sg:postcode":"28220",
    "sg:province":"Madrid",
    "wof:name":"La Casa Del Chaque S.l",
    "wof:placetype":"venue"
},
  "geometry": {"coordinates":[-3.868242979,40.4718208313],"type":"Point"}
}