{
  "type": "Feature",
  "properties": {
    "iso:country":"ES",
    "sg:address":"Ptor Delacroix, 4",
    "sg:city":"Los Narejos",
    "sg:orig_category":"Agencias Y Agentes Comerciales, Representantes",
    "sg:phone":"+34 968 58 25 03",
    "sg:postcode":"30710",
    "sg:province":"Murcia",
    "wof:name":"Billington  Simon Timothy",
    "wof:placetype":"venue"
},
  "geometry": {"coordinates":[-0.827188015,37.7569694519],"type":"Point"}
}