{
  "type": "Feature",
  "properties": {
    "iso:country":"ES",
    "sg:address":"Avda Primero De Mayo, 4",
    "sg:city":"Valle Trapaga",
    "sg:orig_category":"Asociaciones Y Clubs Deportivos",
    "sg:phone":"+34 944 92 13 07",
    "sg:postcode":"48510",
    "sg:province":"Vizcaya",
    "wof:name":"Duro Martinez Purificacion",
    "wof:placetype":"venue"
},
  "geometry": {"coordinates":[-3.037017107,43.3045654297],"type":"Point"}
}