{
  "type": "Feature",
  "properties": {
    "addr:full":"Ptda Patojo, 1 Villena Alicante 03400",
    "addr:housenumber":"1",
    "addr:postcode":"03400",
    "addr:street":"Ptda Patojo",
    "iso:country":"ES",
    "sg:address":"Ptda Patojo, 1",
    "sg:city":"Villena",
    "sg:orig_category":"Ingenier\u00cda, Centros De Estudios (diversos)",
    "sg:phone":"+34 965 97 90 72",
    "sg:postcode":"03400",
    "sg:province":"Alicante",
    "wof:name":"Explotaciones Hortofructicolas S.a.",
    "wof:placetype":"venue"
},
  "geometry": {"coordinates":[-0.8688759804,38.6403198242],"type":"Point"}
}