{
  "type": "Feature",
  "properties": {
    "addr:full":"Calle de Bermudez De Castro, 50 Oviedo Asturias 33011",
    "addr:housenumber":"50",
    "addr:postcode":"33011",
    "addr:street":"Calle De Bermudez De Castro",
    "iso:country":"ES",
    "sg:address":"Calle de Bermudez De Castro, 50",
    "sg:city":"Oviedo",
    "sg:orig_category":"Alquiler De V\u00cddeo",
    "sg:phone":"+34 985 11 91 46",
    "sg:postcode":"33011",
    "sg:province":"Asturias",
    "wof:name":"Ocioshop S.l.",
    "wof:placetype":"venue"
},
  "geometry": {"coordinates":[-5.8366184235,43.3718528748],"type":"Point"}
}