{
  "type": "Feature",
  "properties": {
    "iso:country":"ES",
    "sg:address":"Cami Trinidad, La, Km. 0004,6",
    "sg:city":"San Juan",
    "sg:orig_category":"Agricultura: Abastecimiento Y Cosechado (negocio)",
    "sg:phone":"+34 971 18 81 20",
    "sg:postcode":"07760",
    "sg:province":"Islas Baleares",
    "wof:name":"Bini Pati Vell S.r.m.",
    "wof:placetype":"venue"
},
  "geometry": {"coordinates":[3.8382499218,39.9930915833],"type":"Point"}
}