{
  "type": "Feature",
  "properties": {
    "addr:full":"Avda Industria (de La), 48 Coslada Madrid 28820",
    "addr:housenumber":"48",
    "addr:postcode":"28820",
    "addr:street":"Avda Industria De La",
    "iso:country":"ES",
    "sg:address":"Avda Industria (de La), 48",
    "sg:city":"Coslada",
    "sg:orig_category":"Agencias De Aduana",
    "sg:phone":"+34 916 69 54 57",
    "sg:postcode":"28820",
    "sg:province":"Madrid",
    "wof:name":"Maritima Del Estrecho S.a.",
    "wof:placetype":"venue"
},
  "geometry": {"coordinates":[-3.5499169827,40.4358711243],"type":"Point"}
}