{
  "type": "Feature",
  "properties": {
    "addr:full":"Carrer de Pi I Margall, 40 Molins Rei Barcelona 08750",
    "addr:housenumber":"40",
    "addr:postcode":"08750",
    "addr:street":"Carrer De Pi I Margall;Barcelona",
    "iso:country":"ES",
    "sg:address":"Carrer de Pi I Margall, 40",
    "sg:city":"Molins Rei",
    "sg:orig_category":"Electricidad: Instaladores",
    "sg:phone":"+34 936 68 05 49",
    "sg:postcode":"08750",
    "sg:province":"Barcelona",
    "wof:name":"Montajes Electricos Perea San Salvador S.l.",
    "wof:placetype":"venue"
},
  "geometry": {"coordinates":[2.0186591148,41.4090270996],"type":"Point"}
}