{
  "type": "Feature",
  "properties": {
    "iso:country":"ES",
    "sg:address":"Calle de Canteras Recias, 15",
    "sg:city":"Villamayor",
    "sg:orig_category":"Transportes Por Carretera: Lotes Completos, Mercanc\u00cdas Diversas",
    "sg:phone":"+34 923 28 65 41",
    "sg:postcode":"37185",
    "sg:province":"Salamanca",
    "wof:name":"Disjuga S.l",
    "wof:placetype":"venue"
},
  "geometry": {"coordinates":[-5.6944828033,40.9991035461],"type":"Point"}
}