{
  "type": "Feature",
  "properties": {
    "addr:full":"Plaz San Andres, 5 Jerez De La Frontera C\u00e1diz 11402",
    "addr:postcode":"11402",
    "addr:street":"Plaz San Andres 5",
    "iso:country":"ES",
    "sg:address":"Plaz San Andres, 5",
    "sg:city":"Jerez De La Frontera",
    "sg:orig_category":"Asesor\u00cda De Formaci\u00d3n Y Gesti\u00d3n De Personal",
    "sg:phone":"+34 956 32 36 53",
    "sg:postcode":"11402",
    "sg:province":"C\u00e1diz",
    "wof:name":"R.trujillo Asesores S.l.",
    "wof:placetype":"venue"
},
  "geometry": {"coordinates":[-6.1345949173,36.687297821],"type":"Point"}
}