{
  "type": "Feature",
  "properties": {
    "addr:full":"Carrer de Puig, 2 Argentona Barcelona 08310",
    "addr:housenumber":"2",
    "addr:postcode":"08310",
    "addr:street":"Carrer De Puig",
    "iso:country":"ES",
    "sg:address":"Carrer de Puig, 2",
    "sg:city":"Argentona",
    "sg:orig_category":"Mec\u00c1nico Del Autom\u00d3vil",
    "sg:phone":"+34 937 97 20 55",
    "sg:postcode":"08310",
    "sg:province":"Barcelona",
    "wof:name":"Poblet Fortuny Josep",
    "wof:placetype":"venue"
},
  "geometry": {"coordinates":[2.3992888927,41.5548248291],"type":"Point"}
}