{
  "type": "Feature",
  "properties": {
    "addr:full":"Rond Cendea De Cizur, 10 Bara\u00f1ain Navarra 31010",
    "addr:housenumber":"10",
    "addr:postcode":"31010",
    "addr:street":"Rond Cendea De Cizur",
    "iso:country":"ES",
    "sg:address":"Rond Cendea De Cizur, 10",
    "sg:city":"Bara\u00f1ain",
    "sg:orig_category":"Grafistas",
    "sg:phone":"+34 948 18 38 92",
    "sg:postcode":"31010",
    "sg:province":"Navarra",
    "sg:website":"www.mimeticaestudio.com",
    "wof:name":"Mimetica Comunicacion Y Creatividad",
    "wof:placetype":"venue"
},
  "geometry": {"coordinates":[-97.78224945069999,45.7040786743],"type":"Point"}
}