{
  "type": "Feature",
  "properties": {
    "addr:full":"Plaz Ensanche, S/n Bilbao Vizcaya 48009",
    "addr:housenumber":"s / n",
    "addr:postcode":"48009",
    "addr:street":"Ensanche",
    "iso:country":"ES",
    "sg:address":"Plaz Ensanche, S/n",
    "sg:city":"Bilbao",
    "sg:orig_category":"Frutas, Legumbres Frescas Y Tempranas (al Por Menor)",
    "sg:phone":"+34 944 23 40 15",
    "sg:postcode":"48009",
    "sg:province":"Vizcaya",
    "wof:name":"Sebastian Mu\u00f1oz Maria Esther",
    "wof:placetype":"venue"
},
  "geometry": {"coordinates":[-2.9313290119,43.2632904053],"type":"Point"}
}