{
  "type": "Feature",
  "properties": {
    "iso:country":"ES",
    "sg:address":"Calle de Pedro Icaza Aguirre, 21",
    "sg:city":"Santurtzi",
    "sg:orig_category":"Encuadernaci\u00d3n E Impresi\u00d3n De Folletos",
    "sg:phone":"+34 944 83 90 97",
    "sg:postcode":"48980",
    "sg:province":"Vizcaya",
    "wof:name":"Felix Aranburu Perez",
    "wof:placetype":"venue"
},
  "geometry": {"coordinates":[-3.0288910866,43.3261260986],"type":"Point"}
}