{
  "type": "Feature",
  "properties": {
    "iso:country":"ES",
    "sg:address":"Trasera De Los Mesones, 5",
    "sg:city":"Lerma",
    "sg:orig_category":"Centros Empresariales",
    "sg:phone":"+34 947 17 10 67",
    "sg:postcode":"09340",
    "sg:province":"Burgos",
    "wof:name":"Arauzo Sanz Manuel",
    "wof:placetype":"venue"
},
  "geometry": {"coordinates":[-3.7601697445,42.0264701843],"type":"Point"}
}