{
  "type": "Feature",
  "properties": {
    "iso:country":"ES",
    "sg:address":"Carrer de Xifre, 14",
    "sg:city":"Barcelona",
    "sg:orig_category":"Maquinaria Para Industrias Diversas",
    "sg:phone":"+34 932 31 73 76",
    "sg:postcode":"08026",
    "sg:province":"Barcelona",
    "wof:name":"Suministros Industriales Melis S.l.",
    "wof:placetype":"venue"
},
  "geometry": {"coordinates":[2.1836509705,41.4088859558],"type":"Point"}
}