{
  "type": "Feature",
  "properties": {
    "addr:full":"Av Saloria, 100 Seu D'urgell Lleida 25700",
    "addr:housenumber":"100",
    "addr:postcode":"25700",
    "addr:street":"Av Saloria",
    "iso:country":"ES",
    "sg:address":"Av Saloria, 100",
    "sg:city":"Seu D'urgell",
    "sg:orig_category":"Ense\u00d1anza, Formaci\u00d3n Profesional: Aprendizaje",
    "sg:phone":"+34 973 35 00 77",
    "sg:postcode":"25700",
    "sg:province":"Lleida",
    "sg:website":"www.mir.es",
    "wof:name":"Direccion General De La Policia",
    "wof:placetype":"venue"
},
  "geometry": {"coordinates":[0.6457189918,41.6027946472],"type":"Point"}
}