{
  "type": "Feature",
  "properties": {
    "iso:country":"ES",
    "sg:address":"Carrer de Doctor Trueta, 16",
    "sg:city":"S. Celoni",
    "sg:orig_category":"Institutos De Belleza",
    "sg:phone":"+34 938 67 34 72",
    "sg:postcode":"08470",
    "sg:province":"Barcelona",
    "wof:name":"Peraposch Seres Nuria",
    "wof:placetype":"venue"
},
  "geometry": {"coordinates":[2.4879159927,41.6852798462],"type":"Point"}
}