{
  "type": "Feature",
  "properties": {
    "iso:country":"ES",
    "sg:address":"Calle de Doctor Esquerdo, 8",
    "sg:city":"Madrid",
    "sg:orig_category":"Internados & Ense\u00d1anza Privada",
    "sg:phone":"+34 913 09 29 26",
    "sg:postcode":"28028",
    "sg:province":"Madrid",
    "wof:name":"Organizacion Profesional Espa\u00f1ola S.a.",
    "wof:placetype":"venue"
},
  "geometry": {"coordinates":[-3.6687066555,40.4266700745],"type":"Point"}
}