{
  "type": "Feature",
  "properties": {
    "iso:country":"ES",
    "sg:address":"G.v. Carles Iii, 58",
    "sg:city":"Barcelona",
    "sg:orig_category":"Centros M\u00c9dicos Y Sociales, Dispensarios",
    "sg:phone":"+34 934 11 12 89",
    "sg:postcode":"08028",
    "sg:province":"Barcelona",
    "wof:name":"Anton Torre\u00f1o Andres",
    "wof:placetype":"venue"
},
  "geometry": {"coordinates":[2.1279456615,41.3836135864],"type":"Point"}
}