{
  "type": "Feature",
  "properties": {
    "addr:full":"Carr Castell De Peralada, 22 Girona Girona 17003",
    "addr:housenumber":"22",
    "addr:postcode":"17003",
    "addr:street":"Carr Castell;Peralada",
    "iso:country":"ES",
    "sg:address":"Carr Castell De Peralada, 22",
    "sg:city":"Girona",
    "sg:orig_category":"Peluqueros: De Se\u00d1oras",
    "sg:phone":"+34 972 22 06 62",
    "sg:postcode":"17003",
    "sg:province":"Girona",
    "wof:name":"Escuder Marti Pietat",
    "wof:placetype":"venue"
},
  "geometry": {"coordinates":[2.8224639893,41.9708061218],"type":"Point"}
}