{
  "type": "Feature",
  "properties": {
    "addr:full":"Ctra Madrid-la Coru\u00d1a, Km. 0080,0 Villacastin Segovia 40150",
    "addr:postcode":"40150",
    "addr:street":"Ctra Madrid-La Corun\u0303A Km. 0080,0 Villacastin Segovia",
    "iso:country":"ES",
    "sg:address":"Ctra Madrid-la Coru\u00d1a, Km. 0080,0",
    "sg:city":"Villacastin",
    "sg:orig_category":"Distribuci\u00d3n De Petr\u00d3leo Y Derivados",
    "sg:phone":"+34 921 19 71 04",
    "sg:postcode":"40150",
    "sg:province":"Segovia",
    "sg:website":"www.cepsa.es",
    "wof:name":"Cedipsa Compa\u00d1ia Espa\u00d1ola Distribuidora De Petroleos S.a.",
    "wof:placetype":"venue"
},
  "geometry": {"coordinates":[-4.4138379097,40.7807350159],"type":"Point"}
}