{
  "type": "Feature",
  "properties": {
    "iso:country":"ES",
    "sg:address":"Calle de Discobolo, 37",
    "sg:city":"Madrid",
    "sg:orig_category":"Contenedores (mercanc\u00cdas)",
    "sg:phone":"+34 917 41 29 67",
    "sg:postcode":"28022",
    "sg:province":"Madrid",
    "wof:name":"Hernando Garcia Jose",
    "wof:placetype":"venue"
},
  "geometry": {"coordinates":[-3.6139628887,40.442363739],"type":"Point"}
}