{
  "type": "Feature",
  "properties": {
    "addr:full":"Los Llenares, 19 Carrizo Ribera Le\u00f3n 24270",
    "addr:housenumber":"19",
    "addr:postcode":"24270",
    "addr:street":"Llenares;Ribera",
    "iso:country":"ES",
    "sg:address":"Los Llenares, 19",
    "sg:city":"Carrizo Ribera",
    "sg:orig_category":"Delegados, Agentes De Tr\u00c1nsito, Auxiliares De Transporte Internacional",
    "sg:phone":"+34 987 35 82 01",
    "sg:postcode":"24270",
    "sg:province":"Le\u00f3n",
    "wof:name":"Transportes Alcoba De La Ribera S.l.",
    "wof:placetype":"venue"
},
  "geometry": {"coordinates":[-5.6029820442,42.3988380432],"type":"Point"}
}