{
  "type": "Feature",
  "properties": {
    "iso:country":"ES",
    "sg:address":"Calle de Ibarra, 21",
    "sg:city":"Barakaldo",
    "sg:orig_category":"Molduras, Junquillos, Listones Y Molduras Perforadas",
    "sg:phone":"+34 944 37 63 42",
    "sg:postcode":"48901",
    "sg:province":"Vizcaya",
    "wof:name":"Valeriano Avedillo Prieto",
    "wof:placetype":"venue"
},
  "geometry": {"coordinates":[-2.9844655991,43.2997703552],"type":"Point"}
}