{
  "type": "Feature",
  "properties": {
    "iso:country":"ES",
    "sg:address":"Carr Santander, 25",
    "sg:city":"Girona",
    "sg:orig_category":"Institutos De Belleza",
    "sg:phone":"+34 972 23 49 02",
    "sg:postcode":"17005",
    "sg:province":"Girona",
    "wof:name":"Martinez Rovira Ana Maria",
    "wof:placetype":"venue"
},
  "geometry": {"coordinates":[2.8142209053,41.9745903015],"type":"Point"}
}