{
  "type": "Feature",
  "properties": {
    "addr:full":"Carrer de Pallars, 220 Barcelona Barcelona 08005",
    "addr:housenumber":"220",
    "addr:postcode":"08005",
    "addr:street":"Carrer De Pallars",
    "iso:country":"ES",
    "sg:address":"Carrer de Pallars, 220",
    "sg:city":"Barcelona",
    "sg:orig_category":"Asesor\u00cdas En Comunicaci\u00d3n",
    "sg:phone":"+34 934 85 50 35",
    "sg:postcode":"08005",
    "sg:province":"Barcelona",
    "wof:name":"E.c.m. Xxi Asesores De Comunicaciones S.l.",
    "wof:placetype":"venue"
},
  "geometry": {"coordinates":[2.1993238926,41.4022026062],"type":"Point"}
}