{
  "type": "Feature",
  "properties": {
    "addr:full":"Calle de Carretera De Fuentelsaz, 47 Casar Guadalajara 19170",
    "addr:housenumber":"47",
    "addr:postcode":"19170",
    "addr:street":"Calle De Carretera De Fuentelsaz",
    "iso:country":"ES",
    "sg:address":"Calle de Carretera De Fuentelsaz, 47",
    "sg:city":"Casar",
    "sg:orig_category":"Abogados",
    "sg:phone":"+34 949 33 44 24",
    "sg:postcode":"19170",
    "sg:province":"Guadalajara",
    "wof:name":"Au\u00f1on Carriedo Luis Felipe",
    "wof:placetype":"venue"
},
  "geometry": {"coordinates":[-3.1664927006,40.6298179626],"type":"Point"}
}