{
  "type": "Feature",
  "properties": {
    "addr:full":"Cami Vilapou, S/n Olesa Montserrat Barcelona 08640",
    "addr:housenumber":"/ n",
    "addr:postcode":"08640",
    "addr:street":"Vilapou S",
    "iso:country":"ES",
    "sg:address":"Cami Vilapou, S/n",
    "sg:city":"Olesa Montserrat",
    "sg:orig_category":"Fibras De Vidrio",
    "sg:phone":"+34 937 78 63 08",
    "sg:postcode":"08640",
    "sg:province":"Barcelona",
    "sg:website":"www.magmacomposite.com",
    "wof:name":"Magma Composite S.l.",
    "wof:placetype":"venue"
},
  "geometry": {"coordinates":[1.8994450569,41.5400657654],"type":"Point"}
}