{
  "type": "Feature",
  "properties": {
    "addr:full":"Plaz San Leandro, 2 Sevilla Sevilla 41003",
    "addr:housenumber":"2",
    "addr:postcode":"41003",
    "addr:street":"Plaz San Leandro",
    "iso:country":"ES",
    "sg:address":"Plaz San Leandro, 2",
    "sg:city":"Sevilla",
    "sg:orig_category":"Arquitectos",
    "sg:phone":"+34 954 21 73 47",
    "sg:postcode":"41003",
    "sg:province":"Sevilla",
    "wof:name":"Martin Walls Damian",
    "wof:placetype":"venue"
},
  "geometry": {"coordinates":[-5.9883489609,37.3909797668],"type":"Point"}
}