{
  "type": "Feature",
  "properties": {
    "addr:full":"Pdnia Fuente Del Pino, 1 Fuente Pino Murcia 30528",
    "addr:housenumber":"1",
    "addr:postcode":"30528",
    "addr:street":"Del Pino",
    "iso:country":"ES",
    "sg:address":"Pdnia Fuente Del Pino, 1",
    "sg:city":"Fuente Pino",
    "sg:orig_category":"Conservas De Platos Cocinados (fabricaci\u00d3n, Al Por Mayor)",
    "sg:phone":"+34 968 75 99 52",
    "sg:postcode":"30528",
    "sg:province":"Murcia",
    "wof:name":"Juan Perez Marin S.a.",
    "wof:placetype":"venue"
},
  "geometry": {"coordinates":[-1.2884540558,38.5438995361],"type":"Point"}
}