{
  "type": "Feature",
  "properties": {
    "iso:country":"ES",
    "sg:address":"Plaz Poligono Industrial La Torrecilla, S/n",
    "sg:city":"Cordoba",
    "sg:orig_category":"Construcciones Met\u00c1licas",
    "sg:phone":"+34 957 34 31 05",
    "sg:postcode":"14013",
    "sg:province":"C\u00f3rdoba",
    "wof:name":"Talleres Mu\u00d1oz Carmona Sl",
    "wof:placetype":"venue"
},
  "geometry": {"coordinates":[-4.7784028053,37.8779411316],"type":"Point"}
}