{
  "type": "Feature",
  "properties": {
    "addr:full":"Carrer de Santa Anna, 8 Hospitalet Llobregat Barcelona 08901",
    "addr:housenumber":"8",
    "addr:postcode":"08901",
    "addr:street":"Carrer De Santa Anna",
    "iso:country":"ES",
    "sg:address":"Carrer de Santa Anna, 8",
    "sg:city":"Hospitalet Llobregat",
    "sg:orig_category":"Materias Pl\u00c1sticas: Art\u00cdculos Para La Industria",
    "sg:phone":"+34 933 38 28 15",
    "sg:postcode":"08901",
    "sg:province":"Barcelona",
    "wof:name":"Productos Plasticos Performantes 3p S.a.",
    "wof:placetype":"venue"
},
  "geometry": {"coordinates":[2.1013190746,41.3582801819],"type":"Point"}
}