{
  "type": "Feature",
  "properties": {
    "addr:full":"Avda Ebro, 14 Agoncillo La Rioja 26509",
    "addr:housenumber":"14",
    "addr:postcode":"26509",
    "addr:street":"Avda Ebro;Rioja",
    "iso:country":"ES",
    "sg:address":"Avda Ebro, 14",
    "sg:city":"Agoncillo",
    "sg:orig_category":"Goma: Productos De Uso Industrial (fabricaci\u00d3n, Al Por Mayor)",
    "sg:phone":"+34 941 48 63 62",
    "sg:postcode":"26509",
    "sg:province":"La Rioja",
    "sg:website":"www.cauchosebro.com",
    "wof:name":"Cauchos Ebro S.a.",
    "wof:placetype":"venue"
},
  "geometry": {"coordinates":[-2.1222639084,42.4031410217],"type":"Point"}
}