{
  "type": "Feature",
  "properties": {
    "addr:full":"Atalaya Alta, S/n Velez-malaga M\u00e1laga 29700",
    "addr:housenumber":"s / n",
    "addr:postcode":"29700",
    "addr:street":"Alta",
    "iso:country":"ES",
    "sg:address":"Atalaya Alta, S/n",
    "sg:city":"Velez-malaga",
    "sg:orig_category":"Ropa Para Se\u00d1oras Y Caballeros (al Por Menor)",
    "sg:phone":"+34 952 03 01 85",
    "sg:postcode":"29700",
    "sg:province":"M\u00e1laga",
    "wof:name":"Santiago Palacios Manuel",
    "wof:placetype":"venue"
},
  "geometry": {"coordinates":[-4.1014099121,36.7857284546],"type":"Point"}
}