{
  "type": "Feature",
  "properties": {
    "addr:full":"Calle de San Pedro El Verde, 12 Toledo Toledo 45004",
    "addr:housenumber":"12",
    "addr:postcode":"45004",
    "addr:street":"Calle De San Pedro El Verde",
    "iso:country":"ES",
    "sg:address":"Calle de San Pedro El Verde, 12",
    "sg:city":"Toledo",
    "sg:orig_category":"Arquitectos",
    "sg:phone":"+34 925 21 67 02",
    "sg:postcode":"45004",
    "sg:province":"Toledo",
    "wof:name":"Alvarez Ahedo Jose Ignacio",
    "wof:placetype":"venue"
},
  "geometry": {"coordinates":[-4.0421257019,39.8682594299],"type":"Point"}
}