{
  "type": "Feature",
  "properties": {
    "addr:full":"Calle de Santa Clara (de), 4 Lerma Burgos 09340",
    "addr:postcode":"09340",
    "addr:street":"Calle De Santa Clara De",
    "iso:country":"ES",
    "sg:address":"Calle de Santa Clara (de), 4",
    "sg:city":"Lerma",
    "sg:orig_category":"Supermercados Y Hipermercados",
    "sg:phone":"+34 947 17 11 98",
    "sg:postcode":"09340",
    "sg:province":"Burgos",
    "wof:name":"Rosa Maria Garcia Garcia Y Otro S.cv.",
    "wof:placetype":"venue"
},
  "geometry": {"coordinates":[-3.757142067,42.0264205933],"type":"Point"}
}