{
  "type": "Feature",
  "properties": {
    "addr:full":"Rua Santo Domingo, 64 Ourense Ourense 32003",
    "addr:housenumber":"64",
    "addr:postcode":"32003",
    "addr:street":"Rua Santo Domingo",
    "iso:country":"ES",
    "sg:address":"Rua Santo Domingo, 64",
    "sg:city":"Ourense",
    "sg:orig_category":"Controles De Edificaci\u00d3n (construcci\u00d3n, Seguridad)",
    "sg:phone":"+34 988 24 74 71",
    "sg:postcode":"32003",
    "sg:province":"Ourense",
    "wof:name":"Sofalco S.l.",
    "wof:placetype":"venue"
},
  "geometry": {"coordinates":[-7.8628211021,42.3401832581],"type":"Point"}
}