{
  "type": "Feature",
  "properties": {
    "iso:country":"ES",
    "sg:address":"Avda Peris Y Valero, 95",
    "sg:city":"Valencia",
    "sg:orig_category":"Alquiler De Veh\u00cdculos: Turismos Y Utilitarios",
    "sg:phone":"+34 963 34 60 22",
    "sg:postcode":"46006",
    "sg:province":"Valencia",
    "wof:name":"Flycar S.a.",
    "wof:placetype":"venue"
},
  "geometry": {"coordinates":[-0.3710390031,39.4590606689],"type":"Point"}
}