{
  "type": "Feature",
  "properties": {
    "addr:full":"Estd Ourense (de), 161 Pazos Ourense 32619",
    "addr:housenumber":"161",
    "addr:postcode":"32619",
    "addr:street":"Pazos Ourense",
    "iso:country":"ES",
    "sg:address":"Estd Ourense (de), 161",
    "sg:city":"Pazos",
    "sg:orig_category":"Mec\u00c1nico Del Autom\u00d3vil",
    "sg:phone":"+34 988 41 30 52",
    "sg:postcode":"32619",
    "sg:province":"Ourense",
    "wof:name":"Verauto Servi S.l.",
    "wof:placetype":"venue"
},
  "geometry": {"coordinates":[-7.4538340569,41.9393615723],"type":"Point"}
}