{
  "type": "Feature",
  "properties": {
    "addr:full":"Calle de Concepcion, S/n Urda Toledo 45480",
    "addr:housenumber":"s / n",
    "addr:postcode":"45480",
    "addr:street":"Calle De Concepcion",
    "iso:country":"ES",
    "sg:address":"Calle de Concepcion, S/n",
    "sg:city":"Urda",
    "sg:orig_category":"Bebidas",
    "sg:phone":"+34 925 47 24 11",
    "sg:postcode":"45480",
    "sg:province":"Toledo",
    "wof:name":"Distribuciones Villa S.l.",
    "wof:placetype":"venue"
},
  "geometry": {"coordinates":[-3.718763113,39.410446167],"type":"Point"}
}