{
  "type": "Feature",
  "properties": {
    "addr:full":"Calle de Garibai, 2 Donostia-san Sebastian Guip\u00f9zcoa 20004",
    "addr:housenumber":"2",
    "addr:postcode":"20004",
    "addr:street":"Calle De Garibai",
    "iso:country":"ES",
    "sg:address":"Calle de Garibai, 2",
    "sg:city":"Donostia-san Sebastian",
    "sg:orig_category":"Estilistas Y Estudios De Estilo De Corte Y Confecci\u00d3n",
    "sg:phone":"+34 943 42 01 81",
    "sg:postcode":"20004",
    "sg:province":"Guip\u00f9zcoa",
    "wof:name":"Nu\u00f1ez Uranga Ignacio",
    "wof:placetype":"venue"
},
  "geometry": {"coordinates":[-1.9843100309,43.321647644],"type":"Point"}
}