{
  "type": "Feature",
  "properties": {
    "iso:country":"ES",
    "sg:address":"Playa Comillas, 31",
    "sg:city":"Bonanza",
    "sg:orig_category":"Formaci\u00d3n A Distancia, Por Correspondencia",
    "sg:phone":"+34 916 32 67 68",
    "sg:postcode":"28669",
    "sg:province":"Madrid",
    "wof:name":"Veciana Forner Monserrat",
    "wof:placetype":"venue"
},
  "geometry": {"coordinates":[-3.8989849091,40.4515075684],"type":"Point"}
}