{
  "type": "Feature",
  "properties": {
    "iso:country":"ES",
    "sg:address":"Ctra Acceso Central Termica, S/n",
    "sg:city":"Palmones",
    "sg:orig_category":"Inform\u00c1tica: Material Y Suministros",
    "sg:phone":"+34 956 67 60 01",
    "sg:postcode":"11379",
    "sg:province":"C\u00e1diz",
    "wof:name":"Almacenes Len S.l.",
    "wof:placetype":"venue"
},
  "geometry": {"coordinates":[-5.4351553917,36.1841125488],"type":"Point"}
}