{
  "type": "Feature",
  "properties": {
    "addr:full":"Calle de Ruben Dario, 4 Valencia Valencia 46021",
    "addr:housenumber":"4",
    "addr:postcode":"46021",
    "addr:street":"Calle De Ruben Dario",
    "iso:country":"ES",
    "sg:address":"Calle de Ruben Dario, 4",
    "sg:city":"Valencia",
    "sg:orig_category":"Farmacias",
    "sg:phone":"+34 963 60 33 88",
    "sg:postcode":"46021",
    "sg:province":"Valencia",
    "wof:name":"Taura Montalar Margarita",
    "wof:placetype":"venue"
},
  "geometry": {"coordinates":[-0.3532749116,39.4765357971],"type":"Point"}
}