{
  "type": "Feature",
  "properties": {
    "iso:country":"ES",
    "sg:address":"Calle de Bernardino Obregon, 7",
    "sg:city":"Burgos",
    "sg:orig_category":"Asilos De Ancianos. Centros Privados",
    "sg:phone":"+34 947 26 83 57",
    "sg:postcode":"09001",
    "sg:province":"Burgos",
    "wof:name":"Centro Gerontologico De Burgos",
    "wof:placetype":"venue"
},
  "geometry": {"coordinates":[-3.7216379642,42.3379745483],"type":"Point"}
}