{
  "type": "Feature",
  "properties": {
    "iso:country":"ES",
    "sg:address":"Pase Estacion, S/n",
    "sg:city":"Veguellina Orbigo",
    "sg:orig_category":"Tiendas De Grano, Frutas Y Legumbres Secas (al Por Menor)",
    "sg:phone":"+34 987 37 43 75",
    "sg:postcode":"24350",
    "sg:province":"Le\u00f3n",
    "wof:name":"Regalos Y Frutos Secos Doly",
    "wof:placetype":"venue"
},
  "geometry": {"coordinates":[-5.8852372169,42.4383964539],"type":"Point"}
}