{
  "type": "Feature",
  "properties": {
    "addr:full":"Calle de Real, 36 Union Murcia 30360",
    "addr:housenumber":"36",
    "addr:postcode":"30360",
    "addr:street":"Calle De Real",
    "iso:country":"ES",
    "sg:address":"Calle de Real, 36",
    "sg:city":"Union",
    "sg:orig_category":"Fabricaci\u00d3n De Muebles",
    "sg:phone":"+34 968 54 08 41",
    "sg:postcode":"30360",
    "sg:province":"Murcia",
    "wof:name":"Manrubia Garcia Antonio",
    "wof:placetype":"venue"
},
  "geometry": {"coordinates":[-0.8765640259,37.6206550598],"type":"Point"}
}