{
  "type": "Feature",
  "properties": {
    "addr:full":"Avgd Alfons Xiii, 105 Badalona Barcelona 08912",
    "addr:housenumber":"105",
    "addr:postcode":"08912",
    "addr:street":"Alfons Xiii",
    "iso:country":"ES",
    "sg:address":"Avgd Alfons Xiii, 105",
    "sg:city":"Badalona",
    "sg:orig_category":"Comercio De Piezas De Recambio Y De Accesorios De Veh\u00cdculos, Veh\u00cdculos Industriales",
    "sg:phone":"+34 933 99 94 11",
    "sg:postcode":"08912",
    "sg:province":"Barcelona",
    "wof:name":"Euma S.l.",
    "wof:placetype":"venue"
},
  "geometry": {"coordinates":[2.2350530624,41.4428710938],"type":"Point"}
}