{
  "type": "Feature",
  "properties": {
    "addr:full":"Geraneos, 48 Mijas Costa M\u00e1laga 29649",
    "addr:housenumber":"48",
    "addr:postcode":"29649",
    "addr:street":"Geraneos",
    "iso:country":"ES",
    "sg:address":"Geraneos, 48",
    "sg:city":"Mijas Costa",
    "sg:orig_category":"Empresas De Carpinter\u00cda",
    "sg:phone":"+34 952 47 92 50",
    "sg:postcode":"29649",
    "sg:province":"M\u00e1laga",
    "wof:name":"Industrias Metalicas Eurosur S.l.",
    "wof:placetype":"venue"
},
  "geometry": {"coordinates":[-4.6411604881,36.5099143982],"type":"Point"}
}