{
  "type": "Feature",
  "properties": {
    "addr:full":"Avda Tenor Fleta, 59 Zaragoza Zaragoza 50008",
    "addr:housenumber":"59",
    "addr:postcode":"50008",
    "addr:street":"Avda Tenor Fleta",
    "iso:country":"ES",
    "sg:address":"Avda Tenor Fleta, 59",
    "sg:city":"Zaragoza",
    "sg:orig_category":"Electricidad: Instaladores",
    "sg:phone":"+34 976 13 34 52",
    "sg:postcode":"50008",
    "sg:province":"Zaragoza",
    "wof:name":"Josma Electrificaciones S.l.",
    "wof:placetype":"venue"
},
  "geometry": {"coordinates":[-0.8794289827,41.6389198303],"type":"Point"}
}