{
  "type": "Feature",
  "properties": {
    "addr:full":"Calle de Gayarre, 9 Calahorra La Rioja 26500",
    "addr:housenumber":"9",
    "addr:postcode":"26500",
    "addr:street":"Calle De Gayarre",
    "iso:country":"ES",
    "sg:address":"Calle de Gayarre, 9",
    "sg:city":"Calahorra",
    "sg:orig_category":"Confecci\u00d3n De Zapatos",
    "sg:phone":"+34 941 13 17 69",
    "sg:postcode":"26500",
    "sg:province":"La Rioja",
    "wof:name":"Valdepeas Rodriguez Maria Carmen",
    "wof:placetype":"venue"
},
  "geometry": {"coordinates":[-1.9696079493,42.3106842041],"type":"Point"}
}