{
  "type": "Feature",
  "properties": {
    "iso:country":"ES",
    "sg:address":"Calle de Carlota Navarrete, 27",
    "sg:city":"San Pedro Alcantara",
    "sg:orig_category":"Muebles Y Accesorios Para Cocinas Y Cuartos De Ba\u00d1o (al Por Menor)",
    "sg:phone":"+34 952 78 33 45",
    "sg:postcode":"29670",
    "sg:province":"M\u00e1laga",
    "wof:name":"Ocomor S.l.",
    "wof:placetype":"venue"
},
  "geometry": {"coordinates":[-4.9876508713,36.4847373962],"type":"Point"}
}