{
  "type": "Feature",
  "properties": {
    "addr:full":"Calle de Cristobal Monterde, 2 Alzira Valencia 46600",
    "addr:housenumber":"2",
    "addr:postcode":"46600",
    "addr:street":"Calle De Cristobal Monterde",
    "iso:country":"ES",
    "sg:address":"Calle de Cristobal Monterde, 2",
    "sg:city":"Alzira",
    "sg:orig_category":"Chapister\u00cda",
    "sg:phone":"+34 962 41 64 46",
    "sg:postcode":"46600",
    "sg:province":"Valencia",
    "wof:name":"Ramirez Vicent Joaquin",
    "wof:placetype":"venue"
},
  "geometry": {"coordinates":[-0.4282596111,39.1512031555],"type":"Point"}
}