{
  "type": "Feature",
  "properties": {
    "iso:country":"ES",
    "sg:address":"Calle de Autonomia, 74",
    "sg:city":"Bilbao",
    "sg:orig_category":"Empresas De Carpinter\u00cda De Madera",
    "sg:phone":"+34 944 41 33 43",
    "sg:postcode":"48012",
    "sg:province":"Vizcaya",
    "wof:name":"Susana Nieto Garcia",
    "wof:placetype":"venue"
},
  "geometry": {"coordinates":[-2.9470579624,43.2580108643],"type":"Point"}
}