{
  "type": "Feature",
  "properties": {
    "iso:country":"ES",
    "sg:address":"Calle de Escritora Gloria Fuertes, 10",
    "sg:city":"Cordoba",
    "sg:orig_category":"Empresas De Limpieza",
    "sg:phone":"+34 957 45 64 13",
    "sg:postcode":"14004",
    "sg:province":"C\u00f3rdoba",
    "wof:name":"M.c.cordobesa De Servicios S.l.",
    "wof:placetype":"venue"
},
  "geometry": {"coordinates":[-4.7937688828,37.8760948181],"type":"Point"}
}