{
  "type": "Feature",
  "properties": {
    "iso:country":"ES",
    "sg:address":"Pl Lluis Companys, 3",
    "sg:city":"Castellbisbal",
    "sg:orig_category":"Reposter\u00cdas",
    "sg:phone":"+34 937 72 14 15",
    "sg:postcode":"08755",
    "sg:province":"Barcelona",
    "wof:name":"Fresc I Calent S.l.",
    "wof:placetype":"venue"
},
  "geometry": {"coordinates":[1.9818099737,41.4785308838],"type":"Point"}
}