{
  "type": "Feature",
  "properties": {
    "addr:full":"Carr Coromina, 11 Bescano Girona 17162",
    "addr:housenumber":"11",
    "addr:postcode":"17162",
    "addr:street":"Carr Coromina",
    "iso:country":"ES",
    "sg:address":"Carr Coromina, 11",
    "sg:city":"Bescano",
    "sg:orig_category":"Peluqueros: De Se\u00d1oras",
    "sg:phone":"+34 972 44 01 55",
    "sg:postcode":"17162",
    "sg:province":"Girona",
    "wof:name":"Rovirola Prat Maria Teresa",
    "wof:placetype":"venue"
},
  "geometry": {"coordinates":[2.7393751144,41.9661865234],"type":"Point"}
}