{
  "type": "Feature",
  "properties": {
    "iso:country":"ES",
    "sg:address":"Ctra Madrid, 40",
    "sg:city":"Santa Marta De Tormes",
    "sg:orig_category":"Peluquer\u00cdas, Peluquer\u00cda Mixta",
    "sg:phone":"+34 923 20 02 52",
    "sg:postcode":"37900",
    "sg:province":"Salamanca",
    "wof:name":"Bellido Ruiz Maria Soledad",
    "wof:placetype":"venue"
},
  "geometry": {"coordinates":[-5.6291890144,40.9501304626],"type":"Point"}
}