{
  "type": "Feature",
  "properties": {
    "addr:full":"Calle de Arramele Kalea, 5 Tolosa Guip\u00f9zcoa 20400",
    "addr:housenumber":"5",
    "addr:postcode":"20400",
    "addr:street":"Calle De Arramele Kalea;Guipu\u0300Zcoa",
    "iso:country":"ES",
    "sg:address":"Calle de Arramele Kalea, 5",
    "sg:city":"Tolosa",
    "sg:orig_category":"Empresas De Carpinter\u00cda De Madera",
    "sg:phone":"+34 943 67 42 30",
    "sg:postcode":"20400",
    "sg:province":"Guip\u00f9zcoa",
    "wof:name":"Reguillaga Ugartemendia Tomas",
    "wof:placetype":"venue"
},
  "geometry": {"coordinates":[-2.0789339542,43.1339912415],"type":"Point"}
}