{
  "type": "Feature",
  "properties": {
    "iso:country":"ES",
    "sg:address":"Merkatondoa, 18",
    "sg:city":"Estella",
    "sg:orig_category":"Venta, Instalaci\u00d3n De Calefacci\u00d3n",
    "sg:phone":"+34 948 55 62 74",
    "sg:postcode":"31200",
    "sg:province":"Navarra",
    "wof:name":"Instalaciones Y Talleres Go\u00f1i S.l.",
    "wof:placetype":"venue"
},
  "geometry": {"coordinates":[-2.0302510262,42.6601715088],"type":"Point"}
}