{
  "type": "Feature",
  "properties": {
    "iso:country":"ES",
    "sg:address":"Carrer de Sugranyes, 78-82",
    "sg:city":"Barcelona",
    "sg:orig_category":"Piscinas, Accesorios, Suministros (fabricaci\u00d3n, Al Por Mayor)",
    "sg:phone":"+34 933 31 30 04",
    "sg:postcode":"08028",
    "sg:province":"Barcelona",
    "sg:website":"www.pentatoldo.net",
    "wof:name":"Penta Toldo S.l.",
    "wof:placetype":"venue"
},
  "geometry": {"coordinates":[2.1295690536,41.3724708557],"type":"Point"}
}