{
  "type": "Feature",
  "properties": {
    "addr:full":"Calle de Jose Maria Pereda, 39 Torrelavega Cantabria 39300",
    "addr:housenumber":"39",
    "addr:postcode":"39300",
    "addr:street":"Calle De Jose Maria Pereda",
    "iso:country":"ES",
    "sg:address":"Calle de Jose Maria Pereda, 39",
    "sg:city":"Torrelavega",
    "sg:orig_category":"Lencer\u00cda Femenina, Corseter\u00cda, Trajes De Ba\u00d1o (al Por Menor)",
    "sg:phone":"+34 942 83 50 85",
    "sg:postcode":"39300",
    "sg:province":"Cantabria",
    "wof:name":"New Chaker S.c",
    "wof:placetype":"venue"
},
  "geometry": {"coordinates":[-4.0492138863,43.351184845],"type":"Point"}
}