{
  "type": "Feature",
  "properties": {
    "addr:full":"Carrer de Salvador Estrem I Fa, 14 Falset Tarragona 43730",
    "addr:housenumber":"14",
    "addr:postcode":"43730",
    "addr:street":"Carrer De Salvador Estrem;Fa",
    "iso:country":"ES",
    "sg:address":"Carrer de Salvador Estrem I Fa, 14",
    "sg:city":"Falset",
    "sg:orig_category":"Ropa Para Se\u00d1oras Y Caballeros (al Por Menor)",
    "sg:phone":"+34 977 83 04 64",
    "sg:postcode":"43730",
    "sg:province":"Tarragona",
    "wof:name":"Coll Olive Alberto",
    "wof:placetype":"venue"
},
  "geometry": {"coordinates":[0.8215280175,41.1455497742],"type":"Point"}
}