{
  "type": "Feature",
  "properties": {
    "iso:country":"ES",
    "sg:address":"C/ Espanya, 38",
    "sg:city":"Puigcerda",
    "sg:orig_category":"Ropa De Hogar (al Por Menor)",
    "sg:phone":"+34 972 88 30 85",
    "sg:postcode":"17520",
    "sg:province":"Girona",
    "sg:website":"www.textura-interiors.com",
    "wof:name":"Textil Textura S.l.",
    "wof:placetype":"venue"
},
  "geometry": {"coordinates":[1.9275610447,42.4325904846],"type":"Point"}
}