{
  "type": "Feature",
  "properties": {
    "addr:full":"Avda. Canarias, S/n Realejos, Los Santa Cruz De Tenerife 38410",
    "addr:housenumber":"s / n",
    "addr:postcode":"38410",
    "addr:street":"Avda. Canarias",
    "iso:country":"ES",
    "sg:address":"Avda. Canarias, S/n",
    "sg:city":"Realejos, Los",
    "sg:orig_category":"M\u00c9dicos: Medicina General",
    "sg:phone":"+34 922 34 52 43",
    "sg:postcode":"38410",
    "sg:province":"Santa Cruz De Tenerife",
    "wof:name":"Marrero Martinez Irineo Celso",
    "wof:placetype":"venue"
},
  "geometry": {"coordinates":[-16.5806484222,28.3678607941],"type":"Point"}
}