{
  "type": "Feature",
  "properties": {
    "addr:full":"Rond Ponent, 2 Sabadell Barcelona 08201",
    "addr:housenumber":"2",
    "addr:postcode":"08201",
    "addr:street":"Rond Ponent",
    "iso:country":"ES",
    "sg:address":"Rond Ponent, 2",
    "sg:city":"Sabadell",
    "sg:orig_category":"Cajas De Ahorro",
    "sg:phone":"+34 937 26 13 99",
    "sg:postcode":"08201",
    "sg:province":"Barcelona",
    "wof:name":"Caixa D'estalvis I Pensions De Barcelona",
    "wof:placetype":"venue"
},
  "geometry": {"coordinates":[2.1000449657,41.5445518494],"type":"Point"}
}