{
  "type": "Feature",
  "properties": {
    "addr:full":"Avgd Vicente Blasco Iba\u00d1ez, 16 Aldaia Valencia 46960",
    "addr:housenumber":"16",
    "addr:postcode":"46960",
    "addr:street":"Vicente;Iban\u0303Ez",
    "iso:country":"ES",
    "sg:address":"Avgd Vicente Blasco Iba\u00d1ez, 16",
    "sg:city":"Aldaia",
    "sg:orig_category":"Serigraf\u00cda (material Y Suministros)",
    "sg:phone":"+34 961 51 78 94",
    "sg:postcode":"46960",
    "sg:province":"Valencia",
    "wof:name":"Conde Ribes Adan Jose",
    "wof:placetype":"venue"
},
  "geometry": {"coordinates":[-0.4593389928,39.464641571],"type":"Point"}
}