{
  "type": "Feature",
  "properties": {
    "addr:full":"Av Ave Maria, S/n Escala Girona 17130",
    "addr:housenumber":"/ n",
    "addr:postcode":"17130",
    "addr:street":"Av Ave Maria S",
    "iso:country":"ES",
    "sg:address":"Av Ave Maria, S/n",
    "sg:city":"Escala",
    "sg:orig_category":"Asociaciones Y Clubs Deportivos",
    "sg:phone":"+34 972 77 17 53",
    "sg:postcode":"17130",
    "sg:province":"Girona",
    "wof:name":"Barcelo Cifre Maria Carmen",
    "wof:placetype":"venue"
},
  "geometry": {"coordinates":[3.1333429813,42.123210907],"type":"Point"}
}