{
  "type": "Feature",
  "properties": {
    "iso:country":"ES",
    "sg:address":"Calle de San Roque, S/n",
    "sg:city":"Olivares De Jucar",
    "sg:orig_category":"Centros De Educaci\u00d3n Especial",
    "sg:phone":"+34 969 29 40 29",
    "sg:postcode":"16760",
    "sg:province":"Cuenca",
    "wof:name":"Colegio Rural Agrupado San Lorenzo De La Parrilla",
    "wof:placetype":"venue"
},
  "geometry": {"coordinates":[-2.3559160233,39.7597465515],"type":"Point"}
}