{
  "type": "Feature",
  "properties": {
    "iso:country":"ES",
    "sg:address":"Calle de Lanzarote, 1",
    "sg:city":"San Sebastian De Los Reyes",
    "sg:orig_category":"Financiaci\u00d3n Y Cr\u00c9ditos",
    "sg:phone":"+34 916 53 82 30",
    "sg:postcode":"28700",
    "sg:province":"Madrid",
    "wof:name":"Caja Caminos Sociedad Cooperativa De Credito",
    "wof:placetype":"venue"
},
  "geometry": {"coordinates":[-3.6235721111,40.5564804077],"type":"Point"}
}