{
  "type": "Feature",
  "properties": {
    "addr:full":"Barr Artebizkarra, 27 Mimetiz Vizcaya 48860",
    "addr:housenumber":"27",
    "addr:postcode":"48860",
    "addr:street":"Barr Artebizkarra",
    "iso:country":"ES",
    "sg:address":"Barr Artebizkarra, 27",
    "sg:city":"Mimetiz",
    "sg:orig_category":"Ropa Para Ni\u00d1os (al Por Menor)",
    "sg:phone":"+34 946 39 14 65",
    "sg:postcode":"48860",
    "sg:province":"Vizcaya",
    "wof:name":"Gonzalez Ramos Ana Isabel",
    "wof:placetype":"venue"
},
  "geometry": {"coordinates":[-3.1356720924,43.2126235962],"type":"Point"}
}