{
  "type": "Feature",
  "properties": {
    "iso:country":"ES",
    "sg:address":"Calle de Guadarrama, 29",
    "sg:city":"Navalcarnero",
    "sg:orig_category":"Contenedores (mercanc\u00cdas)",
    "sg:phone":"+34 918 11 14 32",
    "sg:postcode":"28600",
    "sg:province":"Madrid",
    "wof:name":"Fernandez Gutierrez Alfonso",
    "wof:placetype":"venue"
},
  "geometry": {"coordinates":[-4.0068740845,40.2925186157],"type":"Point"}
}