{
  "type": "Feature",
  "properties": {
    "addr:full":"Calle de Guayedra, 32 Palmas De Gran Canaria Las Palmas 35009",
    "addr:housenumber":"32",
    "addr:postcode":"35009",
    "addr:street":"Calle De Guayedra",
    "iso:country":"ES",
    "sg:address":"Calle de Guayedra, 32",
    "sg:city":"Palmas De Gran Canaria",
    "sg:orig_category":"Electricidad (montaje, Ensamblaje De Componentes)",
    "sg:phone":"+34 928 46 24 59",
    "sg:postcode":"35009",
    "sg:province":"Las Palmas",
    "wof:name":"Electromecanica Isleta S.c.p.",
    "wof:placetype":"venue"
},
  "geometry": {"coordinates":[-15.4248533249,28.1517181396],"type":"Point"}
}