{
  "type": "Feature",
  "properties": {
    "iso:country":"ES",
    "sg:address":"Poligono Mijares, 10",
    "sg:city":"Almassora",
    "sg:orig_category":"Rectificaci\u00d3n, Mecanizado, Fresado",
    "sg:phone":"+34 964 56 40 96",
    "sg:postcode":"12550",
    "sg:province":"Castell\u00f3n",
    "wof:name":"Mecanizados Bellsan S.l.",
    "wof:placetype":"venue"
},
  "geometry": {"coordinates":[-0.0631700009,39.9439582825],"type":"Point"}
}