{
  "type": "Feature",
  "properties": {
    "iso:country":"ES",
    "sg:address":"Carrer de Agricultura, 37",
    "sg:city":"Mollet Valles",
    "sg:orig_category":"Promotores Constructores",
    "sg:phone":"+34 935 70 29 56",
    "sg:postcode":"08100",
    "sg:province":"Barcelona",
    "wof:name":"Edificaciones Cabed S.a.",
    "wof:placetype":"venue"
},
  "geometry": {"coordinates":[2.2062540054,41.5451049805],"type":"Point"}
}