{
  "type": "Feature",
  "properties": {
    "iso:country":"ES",
    "sg:address":"Calle de Ba\u00d1eza (de La), 22",
    "sg:city":"Fuenlabrada",
    "sg:orig_category":"Pintura, Barniz, Productos Asimilables (fabricaci\u00d3n, Al Por Mayor)",
    "sg:phone":"+34 916 42 25 32",
    "sg:postcode":"28947",
    "sg:province":"Madrid",
    "wof:name":"F. Melero S. A.",
    "wof:placetype":"venue"
},
  "geometry": {"coordinates":[-3.7482020855,40.2663536072],"type":"Point"}
}