{
  "type": "Feature",
  "properties": {
    "iso:country":"ES",
    "sg:address":"Calle de Redonda, 37",
    "sg:city":"Rambla",
    "sg:orig_category":"Art\u00cdculos De Madera (fabricaci\u00d3n Y Al Por Mayor)",
    "sg:phone":"+34 957 68 24 31",
    "sg:postcode":"14540",
    "sg:province":"C\u00f3rdoba",
    "wof:name":"Muebles Jesus Gomez S.l.",
    "wof:placetype":"venue"
},
  "geometry": {"coordinates":[-4.7444868088,37.6043624878],"type":"Point"}
}