{
  "type": "Feature",
  "properties": {
    "addr:full":"Carr Canonge Sanxo, Del, 4 Son Servera Islas Baleares 07550",
    "addr:housenumber":"4",
    "addr:postcode":"07550",
    "addr:street":"Carr Canonge Sanxo Del",
    "iso:country":"ES",
    "sg:address":"Carr Canonge Sanxo, Del, 4",
    "sg:city":"Son Servera",
    "sg:orig_category":"Asociaciones Y Clubs Deportivos",
    "sg:phone":"+34 971 56 86 99",
    "sg:postcode":"07550",
    "sg:province":"Islas Baleares",
    "wof:name":"Exercici I Movimen S.l.",
    "wof:placetype":"venue"
},
  "geometry": {"coordinates":[3.3612439632,39.6203117371],"type":"Point"}
}