{
  "type": "Feature",
  "properties": {
    "addr:full":"Major, 29 Almacelles Lleida 25100",
    "addr:housenumber":"29",
    "addr:postcode":"25100",
    "addr:street":"Major",
    "iso:country":"ES",
    "sg:address":"Major, 29",
    "sg:city":"Almacelles",
    "sg:orig_category":"Agencias De Viajes",
    "sg:phone":"+34 973 74 05 71",
    "sg:postcode":"25100",
    "sg:province":"Lleida",
    "wof:name":"Viatjes Lauber Agencia Laura Berenguer S.l.",
    "wof:placetype":"venue"
},
  "geometry": {"coordinates":[0.4382199943,41.7305183411],"type":"Point"}
}