{
  "type": "Feature",
  "properties": {
    "iso:country":"ES",
    "sg:address":"Calle de Sierra De Gador, 3",
    "sg:city":"Gador",
    "sg:orig_category":"Lecher\u00cdas",
    "sg:phone":"+34 950 64 52 07",
    "sg:postcode":"04560",
    "sg:province":"Almer\u00eda",
    "wof:name":"Vidisa S.l.",
    "wof:placetype":"venue"
},
  "geometry": {"coordinates":[-2.4886660576,36.9514732361],"type":"Point"}
}