{
  "type": "Feature",
  "properties": {
    "addr:full":"Calle de San Cosme (de), S/n Navalcarnero Madrid 28600",
    "addr:housenumber":"s",
    "addr:postcode":"28600",
    "addr:street":"Calle De San;/ N",
    "iso:country":"ES",
    "sg:address":"Calle de San Cosme (de), S/n",
    "sg:city":"Navalcarnero",
    "sg:orig_category":"Asilos De Ancianos. Centros Privados",
    "sg:phone":"+34 918 11 28 28",
    "sg:postcode":"28600",
    "sg:province":"Madrid",
    "wof:name":"Residencia De La Asuncion S.l.",
    "wof:placetype":"venue"
},
  "geometry": {"coordinates":[-4.0052700043,40.2855415344],"type":"Point"}
}