{
  "type": "Feature",
  "properties": {
    "addr:full":"Calle de Padre Jesus De La Pasion, 2 Huelva Huelva 21004",
    "addr:housenumber":"2",
    "addr:postcode":"21004",
    "addr:street":"Calle De Padre Jesus De La Pasion",
    "iso:country":"ES",
    "sg:address":"Calle de Padre Jesus De La Pasion, 2",
    "sg:city":"Huelva",
    "sg:orig_category":"Peluqueros: De Se\u00d1oras",
    "sg:phone":"+34 959 28 01 81",
    "sg:postcode":"21004",
    "sg:province":"Huelva",
    "wof:name":"Alvarez Gonzalez Lourdes",
    "wof:placetype":"venue"
},
  "geometry": {"coordinates":[-6.9464111328,37.2631988525],"type":"Point"}
}