{
  "type": "Feature",
  "properties": {
    "iso:country":"ES",
    "sg:address":"Calle de Calatrava, 14",
    "sg:city":"Ciudad Real",
    "sg:orig_category":"Bazares, Art\u00cdculos De Limpieza Y De Cocina (al Por Menor)",
    "sg:phone":"+34 926 22 92 38",
    "sg:postcode":"13004",
    "sg:province":"Ciudad Real",
    "wof:name":"Heras Martinez Jose Ignacio De Las",
    "wof:placetype":"venue"
},
  "geometry": {"coordinates":[-3.9270164967,38.9875717163],"type":"Point"}
}