{
  "type": "Feature",
  "properties": {
    "addr:full":"Carr Juan Moreno, 18 Manuel Valencia 46660",
    "addr:housenumber":"18",
    "addr:postcode":"46660",
    "addr:street":"Carr Juan Moreno;Manuel Valencia",
    "iso:country":"ES",
    "sg:address":"Carr Juan Moreno, 18",
    "sg:city":"Manuel",
    "sg:orig_category":"Hielo Artificial (fabricaci\u00d3n, Distribuci\u00d3n)",
    "sg:phone":"+34 962 23 54 63",
    "sg:postcode":"46660",
    "sg:province":"Valencia",
    "wof:name":"Biosca Giner Vicente",
    "wof:placetype":"venue"
},
  "geometry": {"coordinates":[-0.4932869971,39.0511131287],"type":"Point"}
}