{
  "type": "Feature",
  "properties": {
    "addr:full":"Calle de Rufas, 20 Zaragoza Zaragoza 50001",
    "addr:housenumber":"20",
    "addr:postcode":"50001",
    "addr:street":"Calle De Rufas",
    "iso:country":"ES",
    "sg:address":"Calle de Rufas, 20",
    "sg:city":"Zaragoza",
    "sg:orig_category":"Inform\u00c1tica (estudios, Servicios, Asesor\u00cda, Formaci\u00d3n)",
    "sg:phone":"+34 976 21 53 84",
    "sg:postcode":"50001",
    "sg:province":"Zaragoza",
    "wof:name":"Aragonesa De Marketing Informacion Y Servicios S.l.",
    "wof:placetype":"venue"
},
  "geometry": {"coordinates":[-0.8779497743,41.6501655579],"type":"Point"}
}