{
  "type": "Feature",
  "properties": {
    "addr:full":"Avda Faro (el), 16 Castillo Bajo-conejito M\u00e1laga 29793",
    "addr:housenumber":"16",
    "addr:postcode":"29793",
    "addr:street":"Avda Faro El;Castillo Bajo-Conejito Ma\u0301Laga",
    "iso:country":"ES",
    "sg:address":"Avda Faro (el), 16",
    "sg:city":"Castillo Bajo-conejito",
    "sg:orig_category":"Molduras, Junquillos, Listones Y Molduras Perforadas",
    "sg:phone":"+34 952 53 03 79",
    "sg:postcode":"29793",
    "sg:province":"M\u00e1laga",
    "wof:name":"Jurado Zapata Miguel",
    "wof:placetype":"venue"
},
  "geometry": {"coordinates":[-4.4201598167,36.7183189392],"type":"Point"}
}