{
  "type": "Feature",
  "properties": {
    "iso:country":"ES",
    "sg:address":"Rua Sar (de), 10",
    "sg:city":"Santiago De Compostela",
    "sg:orig_category":"Empresarios Y Productoras De Espect\u00c1culos",
    "sg:phone":"+34 981 57 56 61",
    "sg:postcode":"15702",
    "sg:province":"A Coru\u00f1a",
    "wof:name":"Vidal Rodriguez Maria Teresa",
    "wof:placetype":"venue"
},
  "geometry": {"coordinates":[-8.538731575,42.8748168945],"type":"Point"}
}