{
  "type": "Feature",
  "properties": {
    "iso:country":"ES",
    "sg:address":"Pol Ind El Oliveral, 70",
    "sg:city":"P. I. El Oliveral",
    "sg:orig_category":"Embalajes",
    "sg:phone":"+34 961 66 86 52",
    "sg:postcode":"46190",
    "sg:province":"Valencia",
    "wof:name":"Flejateck S.l.",
    "wof:placetype":"venue"
},
  "geometry": {"coordinates":[-0.5698940158,39.5458450317],"type":"Point"}
}