{
  "type": "Feature",
  "properties": {
    "addr:full":"C. Buigas, 107 Sta. Eulalia Ron\u00e7ana Barcelona 08187",
    "addr:housenumber":"107",
    "addr:postcode":"08187",
    "addr:street":"Sta. Eulalia Ronc\u0327Ana",
    "iso:country":"ES",
    "sg:address":"C. Buigas, 107",
    "sg:city":"Sta. Eulalia Ron\u00e7ana",
    "sg:orig_category":"Iluminaci\u00d3n Industrial, Alumbrado P\u00dablico: Material (fabricaci\u00d3n, Importaci\u00d3n)",
    "sg:phone":"+34 938 44 97 07",
    "sg:postcode":"08187",
    "sg:province":"Barcelona",
    "wof:name":"Instalaciones Y Montajes Electricos Del Valles S.l.",
    "wof:placetype":"venue"
},
  "geometry": {"coordinates":[2.2322955132,41.6615371704],"type":"Point"}
}