{
  "type": "Feature",
  "properties": {
    "iso:country":"ES",
    "sg:address":"Carrer de Ivars D'urgell, 24",
    "sg:city":"Torre-romeu",
    "sg:orig_category":"Alimentaci\u00d3n General (al Por Menor)",
    "sg:phone":"+34 937 25 33 51",
    "sg:postcode":"08202",
    "sg:province":"Barcelona",
    "wof:name":"Vaca Delgado Manuel",
    "wof:placetype":"venue"
},
  "geometry": {"coordinates":[2.1272909641,41.5475578308],"type":"Point"}
}