{
  "type": "Feature",
  "properties": {
    "iso:country":"ES",
    "sg:address":"Avda Manuel Llaneza, 69",
    "sg:city":"Gijon",
    "sg:orig_category":"Venta, Colocaci\u00d3n, Reparaci\u00d3n De Parabrisas, Techos Descapotables",
    "sg:phone":"+34 985 14 88 78",
    "sg:postcode":"33208",
    "sg:province":"Asturias",
    "wof:name":"Samarsa S.a.",
    "wof:placetype":"venue"
},
  "geometry": {"coordinates":[-5.6671261787,43.5343856812],"type":"Point"}
}