{
  "type": "Feature",
  "properties": {
    "iso:country":"ES",
    "sg:address":"Ctra Segovia, Km. 0187,0",
    "sg:city":"Cisterniga",
    "sg:orig_category":"Cr\u00cda De Animales De Caza Menor",
    "sg:phone":"+34 983 48 00 64",
    "sg:postcode":"47193",
    "sg:province":"Valladolid",
    "wof:name":"Gefincaza S.l.",
    "wof:placetype":"venue"
},
  "geometry": {"coordinates":[-4.6859240532,41.6106681824],"type":"Point"}
}