{
  "type": "Feature",
  "properties": {
    "addr:full":"Calle de Jose Gestoso, 16 Sevilla Sevilla 41003",
    "addr:housenumber":"16",
    "addr:postcode":"41003",
    "addr:street":"Calle De Jose Gestoso",
    "iso:country":"ES",
    "sg:address":"Calle de Jose Gestoso, 16",
    "sg:city":"Sevilla",
    "sg:orig_category":"Art\u00cdculos De Regalo (al Por Menor)",
    "sg:phone":"+34 954 56 13 58",
    "sg:postcode":"41003",
    "sg:province":"Sevilla",
    "wof:name":"Plasticosur S.a.",
    "wof:placetype":"venue"
},
  "geometry": {"coordinates":[-5.9929690361,37.3936309814],"type":"Point"}
}