{
  "type": "Feature",
  "properties": {
    "iso:country":"ES",
    "sg:address":"Calle de Placido Pe\u00d1a, 35",
    "sg:city":"Vilalba",
    "sg:orig_category":"Electrodom\u00c9sticos (al Por Menor)",
    "sg:phone":"+34 982 51 02 01",
    "sg:postcode":"27800",
    "sg:province":"Lugo",
    "wof:name":"Gonzalez Cendan Antonio Carlos",
    "wof:placetype":"venue"
},
  "geometry": {"coordinates":[-7.678937912,43.30078125],"type":"Point"}
}