{
  "type": "Feature",
  "properties": {
    "iso:country":"ES",
    "sg:address":"Carrer de Xot, 14",
    "sg:city":"Can Palet De Vista Alegre",
    "sg:orig_category":"Lavado, Limpieza De Veh\u00cdculos",
    "sg:phone":"+34 937 88 54 60",
    "sg:postcode":"08224",
    "sg:province":"Barcelona",
    "wof:name":"Vicente Ruiz Alicia",
    "wof:placetype":"venue"
},
  "geometry": {"coordinates":[1.9906500578,41.5405235291],"type":"Point"}
}