{
  "type": "Feature",
  "properties": {
    "addr:full":"Carretera Senia, 7 Ulldecona Tarragona 43550",
    "addr:postcode":"43550",
    "addr:street":"Carretera Senia 7",
    "iso:country":"ES",
    "sg:address":"Carretera Senia, 7",
    "sg:city":"Ulldecona",
    "sg:orig_category":"Asesor\u00cda Fiscal Y Jur\u00cddica",
    "sg:phone":"+34 977 72 10 38",
    "sg:postcode":"43550",
    "sg:province":"Tarragona",
    "wof:name":"Gacomp Comunidad De Bienes",
    "wof:placetype":"venue"
},
  "geometry": {"coordinates":[0.4422160089,40.5968513489],"type":"Point"}
}