{
  "type": "Feature",
  "properties": {
    "iso:country":"ES",
    "sg:address":"Calle de Creu (la), 42",
    "sg:city":"Banyeres Mariola",
    "sg:orig_category":"Alimentaci\u00d3n General (al Por Menor)",
    "sg:phone":"+34 965 56 61 56",
    "sg:postcode":"03450",
    "sg:province":"Alicante",
    "wof:name":"Frances Frances Vicente",
    "wof:placetype":"venue"
},
  "geometry": {"coordinates":[-0.6561983824,38.7180328369],"type":"Point"}
}