{
  "type": "Feature",
  "properties": {
    "iso:country":"ES",
    "sg:address":"Calle de Guadalquivir, 11",
    "sg:city":"Lora Rio",
    "sg:orig_category":"Pod\u00d3logos: Pedicuros",
    "sg:phone":"+34 955 80 17 19",
    "sg:postcode":"41440",
    "sg:province":"Sevilla",
    "wof:name":"Alvarez Velarde Francisco",
    "wof:placetype":"venue"
},
  "geometry": {"coordinates":[-5.5241184235,37.6592636108],"type":"Point"}
}