{
  "type": "Feature",
  "properties": {
    "iso:country":"ES",
    "sg:address":"Carrer de Andorra, 88",
    "sg:city":"Sabadell",
    "sg:orig_category":"Suministros Para Hoteles",
    "sg:phone":"+34 937 16 76 63",
    "sg:postcode":"08207",
    "sg:province":"Barcelona",
    "wof:name":"Perez Martinez Alfonso",
    "wof:placetype":"venue"
},
  "geometry": {"coordinates":[2.0888330936,41.565196991],"type":"Point"}
}