{
  "type": "Feature",
  "properties": {
    "iso:country":"ES",
    "sg:address":"Calle de Moreno Nieto, 22",
    "sg:city":"Malaga",
    "sg:orig_category":"Empresas De Limpieza",
    "sg:phone":"+34 952 07 19 73",
    "sg:postcode":"29011",
    "sg:province":"M\u00e1laga",
    "wof:name":"Limpiezas Tecmalimp S.l.",
    "wof:placetype":"venue"
},
  "geometry": {"coordinates":[-4.4383912086,36.7302703857],"type":"Point"}
}