{
  "type": "Feature",
  "properties": {
    "iso:country":"ES",
    "sg:address":"Calle de Alloza, 13",
    "sg:city":"Castellon",
    "sg:orig_category":"Ropa Para Se\u00d1oras (al Por Menor)",
    "sg:phone":"+34 964 21 23 00",
    "sg:postcode":"12001",
    "sg:province":"Castell\u00f3n",
    "wof:name":"Ferrer Espallargas Lucia",
    "wof:placetype":"venue"
},
  "geometry": {"coordinates":[-0.0398851,39.9850311279],"type":"Point"}
}