{
  "type": "Feature",
  "properties": {
    "addr:full":"Avda Jose Martinez Gonzalez, 43 Elda Alicante 03600",
    "addr:housenumber":"43",
    "addr:postcode":"03600",
    "addr:street":"Avda Jose Martinez Gonzalez",
    "iso:country":"ES",
    "sg:address":"Avda Jose Martinez Gonzalez, 43",
    "sg:city":"Elda",
    "sg:orig_category":"Agencias De Viajes",
    "sg:phone":"+34 965 39 63 12",
    "sg:postcode":"03600",
    "sg:province":"Alicante",
    "sg:website":"www.halconviajes.com",
    "wof:name":"Viajes Halcon S.a.",
    "wof:placetype":"venue"
},
  "geometry": {"coordinates":[-0.7891799808,38.4766197205],"type":"Point"}
}