{
  "type": "Feature",
  "properties": {
    "addr:full":"Ctra Yecla, S/n Villena Alicante 03400",
    "addr:housenumber":"s / n",
    "addr:postcode":"03400",
    "addr:street":"Ctra Yecla",
    "iso:country":"ES",
    "sg:address":"Ctra Yecla, S/n",
    "sg:city":"Villena",
    "sg:orig_category":"Productores Recolectores, Venta Directa De Vinos",
    "sg:phone":"+34 965 81 33 87",
    "sg:postcode":"03400",
    "sg:province":"Alicante",
    "sg:website":"www.copvillena.com",
    "wof:name":"Bodega Cooperativa Nuestra Se\u00f1ora De Las Virtudes",
    "wof:placetype":"venue"
},
  "geometry": {"coordinates":[-0.8705040216,38.6358566284],"type":"Point"}
}