{
  "type": "Feature",
  "properties": {
    "addr:full":"Avda Alberto Alcocer, 39 Madrid Madrid 28016",
    "addr:housenumber":"39",
    "addr:postcode":"madrid;28016",
    "addr:street":"Alberto Alcocer",
    "iso:country":"ES",
    "sg:address":"Avda Alberto Alcocer, 39",
    "sg:city":"Madrid",
    "sg:orig_category":"Construcciones Met\u00c1licas",
    "sg:phone":"+34 913 45 22 00",
    "sg:postcode":"28016",
    "sg:province":"Madrid",
    "wof:name":"Eama S. A.",
    "wof:placetype":"venue"
},
  "geometry": {"coordinates":[-3.6817390919,40.4586830139],"type":"Point"}
}