{
  "type": "Feature",
  "properties": {
    "iso:country":"ES",
    "sg:address":"Calle de Anita Vindel, 40",
    "sg:city":"Madrid",
    "sg:orig_category":"Centros M\u00c9dicos Y Sociales, Dispensarios",
    "sg:phone":"+34 913 57 30 81",
    "sg:postcode":"28023",
    "sg:province":"Madrid",
    "wof:name":"Path Centro De Estudios Medicos",
    "wof:placetype":"venue"
},
  "geometry": {"coordinates":[-3.7860805988,40.4629936218],"type":"Point"}
}