{
  "type": "Feature",
  "properties": {
    "addr:full":"Av President Companys, 11 Mataro Barcelona 08302",
    "addr:housenumber":"11",
    "addr:postcode":"08302",
    "addr:street":"Av President Companys",
    "iso:country":"ES",
    "sg:address":"Av President Companys, 11",
    "sg:city":"Mataro",
    "sg:orig_category":"Reposter\u00cdas",
    "sg:phone":"+34 937 99 61 56",
    "sg:postcode":"08302",
    "sg:province":"Barcelona",
    "wof:name":"Vinagre Leo Juana",
    "wof:placetype":"venue"
},
  "geometry": {"coordinates":[2.4317340851,41.5356292725],"type":"Point"}
}