{
  "type": "Feature",
  "properties": {
    "iso:country":"ES",
    "sg:address":"Cabanillas Ii, 17",
    "sg:city":"Cabanillas Campo",
    "sg:orig_category":"Coches Y Camiones (caja De Cambios, Embrague Y Frenos)",
    "sg:phone":"+34 949 20 27 14",
    "sg:postcode":"19171",
    "sg:province":"Guadalajara",
    "wof:name":"Comercial Go-en S. A.",
    "wof:placetype":"venue"
},
  "geometry": {"coordinates":[-3.2374420166,40.6377639771],"type":"Point"}
}