{
  "type": "Feature",
  "properties": {
    "addr:full":"Calle de Sacramento, S/n Fuentes Nava Palencia 34337",
    "addr:housenumber":"s / n",
    "addr:postcode":"34337",
    "addr:street":"Calle De Sacramento",
    "iso:country":"ES",
    "sg:address":"Calle de Sacramento, S/n",
    "sg:city":"Fuentes Nava",
    "sg:orig_category":"Transportes Por V\u00cdas Navegables",
    "sg:phone":"+34 979 84 20 41",
    "sg:postcode":"34337",
    "sg:province":"Palencia",
    "wof:name":"Prieto Palazuelo Felipe",
    "wof:placetype":"venue"
},
  "geometry": {"coordinates":[-4.7819609642,42.0831604004],"type":"Point"}
}