{
  "type": "Feature",
  "properties": {
    "iso:country":"ES",
    "sg:address":"Carr Rafalet, Des, S/n",
    "sg:city":"Cala Millor",
    "sg:orig_category":"Iglesia Cat\u00d3lica",
    "sg:phone":"+34 971 58 67 36",
    "sg:postcode":"07560",
    "sg:province":"Islas Baleares",
    "wof:name":"Parroquia Nostra Senyora Dels Angels",
    "wof:placetype":"venue"
},
  "geometry": {"coordinates":[3.3733201027,39.5831794739],"type":"Point"}
}