{
  "type": "Feature",
  "properties": {
    "addr:full":"Urb La Ruana, S/n Dos Hermanas Sevilla 41700",
    "addr:postcode":"41700",
    "addr:street":"Ruana S / N Dos",
    "iso:country":"ES",
    "sg:address":"Urb La Ruana, S/n",
    "sg:city":"Dos Hermanas",
    "sg:orig_category":"Cr\u00cda De Cerdos",
    "sg:phone":"+34 955 66 70 96",
    "sg:postcode":"41700",
    "sg:province":"Sevilla",
    "wof:name":"Lopez Fernandez Manuel",
    "wof:placetype":"venue"
},
  "geometry": {"coordinates":[-5.9281339645,37.2829055786],"type":"Point"}
}