{
  "type": "Feature",
  "properties": {
    "iso:country":"ES",
    "sg:address":"Pase Chopera, 13",
    "sg:city":"Madrid",
    "sg:orig_category":"Farmacias",
    "sg:phone":"+34 914 73 86 68",
    "sg:postcode":"28045",
    "sg:province":"Madrid",
    "wof:name":"Diego Otero Martinez C.b.",
    "wof:placetype":"venue"
},
  "geometry": {"coordinates":[-3.7013120651,40.3960533142],"type":"Point"}
}