{
  "type": "Feature",
  "properties": {
    "addr:full":"Avda Tirajana (de), 39 San Fernando Las Palmas 35100",
    "addr:housenumber":"39",
    "addr:postcode":"35100",
    "addr:street":"Avda Tirajana De",
    "iso:country":"ES",
    "sg:address":"Avda Tirajana (de), 39",
    "sg:city":"San Fernando",
    "sg:orig_category":"Doctores En Medicina",
    "sg:phone":"+34 928 76 30 07",
    "sg:postcode":"35100",
    "sg:province":"Las Palmas",
    "wof:name":"Martins  Andreas",
    "wof:placetype":"venue"
},
  "geometry": {"coordinates":[-15.5842504501,28.0904903412],"type":"Point"}
}