{
  "type": "Feature",
  "properties": {
    "addr:full":"Carr Guix, 2 Vilanova I La Geltru Barcelona 08800",
    "addr:housenumber":"2",
    "addr:postcode":"08800",
    "addr:street":"Carr Guix",
    "iso:country":"ES",
    "sg:address":"Carr Guix, 2",
    "sg:city":"Vilanova I La Geltru",
    "sg:orig_category":"Aluminio Y Aleaciones (producci\u00d3n, Transformaci\u00d3n, Negocio)",
    "sg:phone":"+34 938 93 36 26",
    "sg:postcode":"08800",
    "sg:province":"Barcelona",
    "wof:name":"Tractaments Termics Sebastian S.l.",
    "wof:placetype":"venue"
},
  "geometry": {"coordinates":[1.7268999815,41.2211303711],"type":"Point"}
}