{
  "type": "Feature",
  "properties": {
    "addr:full":"Avda Roquetas, 297 Roquetas Mar Almer\u00eda 04740",
    "addr:housenumber":"297",
    "addr:postcode":"04740",
    "addr:street":"Avda Roquetas",
    "iso:country":"ES",
    "sg:address":"Avda Roquetas, 297",
    "sg:city":"Roquetas Mar",
    "sg:orig_category":"Centros De Cr\u00c9dito Inmobiliario",
    "sg:phone":"+34 950 32 31 17",
    "sg:postcode":"04740",
    "sg:province":"Almer\u00eda",
    "wof:name":"Arcos De La Romanilla S.a.",
    "wof:placetype":"venue"
},
  "geometry": {"coordinates":[-2.638466835,36.7327423096],"type":"Point"}
}