{
  "type": "Feature",
  "properties": {
    "iso:country":"ES",
    "sg:address":"Rua General Mola, 16",
    "sg:city":"Ordes",
    "sg:orig_category":"Abogados",
    "sg:phone":"+34 981 68 07 24",
    "sg:postcode":"15680",
    "sg:province":"La Coru\u00f1a",
    "wof:name":"Castro Pol Julio",
    "wof:placetype":"venue"
},
  "geometry": {"coordinates":[-8.4053487778,43.0793800354],"type":"Point"}
}