{
  "type": "Feature",
  "properties": {
    "addr:full":"Calle de Mesones, 28 Coin M\u00e1laga 29100",
    "addr:housenumber":"28",
    "addr:postcode":"29100",
    "addr:street":"Calle De Mesones;Ma\u0301Laga",
    "iso:country":"ES",
    "sg:address":"Calle de Mesones, 28",
    "sg:city":"Coin",
    "sg:orig_category":"Centros Empresariales",
    "sg:phone":"+34 952 45 33 06",
    "sg:postcode":"29100",
    "sg:province":"M\u00e1laga",
    "wof:name":"Asociacion De Jovenes Empresarios Y Profesionales De Coin",
    "wof:placetype":"venue"
},
  "geometry": {"coordinates":[-4.7602500916,36.6596298218],"type":"Point"}
}