{
  "type": "Feature",
  "properties": {
    "addr:full":"Av Navarra, S/n Montjuic Barcelona 08184",
    "addr:postcode":"08184",
    "addr:street":"Av Navarra S / N Montjuic",
    "iso:country":"ES",
    "sg:address":"Av Navarra, S/n",
    "sg:city":"Montjuic",
    "sg:orig_category":"Hielo Artificial (fabricaci\u00d3n, Distribuci\u00d3n)",
    "sg:phone":"+34 938 64 52 51",
    "sg:postcode":"08184",
    "sg:province":"Barcelona",
    "wof:name":"Friopalau S.l.",
    "wof:placetype":"venue"
},
  "geometry": {"coordinates":[2.1748299599,41.5814590454],"type":"Point"}
}