{
  "type": "Feature",
  "properties": {
    "addr:full":"Calle de Ganivet, 50 Iznalloz Granada 18550",
    "addr:housenumber":"50",
    "addr:postcode":"18550",
    "addr:street":"Calle De Ganivet",
    "iso:country":"ES",
    "sg:address":"Calle de Ganivet, 50",
    "sg:city":"Iznalloz",
    "sg:orig_category":"Carnicer\u00cdas, Carnicer\u00cdas",
    "sg:phone":"+34 958 39 62 16",
    "sg:postcode":"18550",
    "sg:province":"Granada",
    "wof:name":"Castilla Luzon Francisco",
    "wof:placetype":"venue"
},
  "geometry": {"coordinates":[-3.5250859261,37.3926582336],"type":"Point"}
}