{
  "type": "Feature",
  "properties": {
    "iso:country":"ES",
    "sg:address":"Calle de San Anton, 9",
    "sg:city":"Caceres",
    "sg:orig_category":"Asesor\u00cda Sobre Comunicaci\u00d3n De Empresas",
    "sg:phone":"+34 927 22 19 72",
    "sg:postcode":"10004",
    "sg:province":"C\u00e1ceres",
    "wof:name":"A.t.a.asesoria De Empresas S.l.",
    "wof:placetype":"venue"
},
  "geometry": {"coordinates":[-6.3755011559,39.472984314],"type":"Point"}
}