{
  "type": "Feature",
  "properties": {
    "addr:full":"Calle de Lepanto, 12 Xirivella Valencia 46950",
    "addr:housenumber":"12",
    "addr:postcode":"46950",
    "addr:street":"Calle De Lepanto",
    "iso:country":"ES",
    "sg:address":"Calle de Lepanto, 12",
    "sg:city":"Xirivella",
    "sg:orig_category":"Carnicer\u00cdas, Carnicer\u00cdas",
    "sg:phone":"+34 963 70 17 29",
    "sg:postcode":"46950",
    "sg:province":"Valencia",
    "wof:name":"Capilla Diaz Alfonso",
    "wof:placetype":"venue"
},
  "geometry": {"coordinates":[-0.4360840023,39.465007782],"type":"Point"}
}