{
  "type": "Feature",
  "properties": {
    "iso:country":"ES",
    "sg:address":"Av De Castilla, 72",
    "sg:city":"Parador Hortichuelas",
    "sg:orig_category":"Quincaller\u00cda (al Por Menor)",
    "sg:phone":"+34 950 34 19 07",
    "sg:postcode":"04720",
    "sg:province":"Almer\u00eda",
    "wof:name":"Jose Terriza Moro C.b.",
    "wof:placetype":"venue"
},
  "geometry": {"coordinates":[-2.5741510391,36.8138160706],"type":"Point"}
}