{
  "type": "Feature",
  "properties": {
    "addr:full":"Carretera De La Redonda, 3 Villanueva Reina Ja\u00e9n 23730",
    "addr:housenumber":"3",
    "addr:postcode":"23730",
    "addr:street":"Carretera De La Redonda;Reina Jae\u0301N",
    "iso:country":"ES",
    "sg:address":"Carretera De La Redonda, 3",
    "sg:city":"Villanueva Reina",
    "sg:orig_category":"Empresas De Carpinter\u00cda Met\u00c1lica",
    "sg:phone":"+34 953 53 70 77",
    "sg:postcode":"23730",
    "sg:province":"Ja\u00e9n",
    "wof:name":"Moreno Casado Jose",
    "wof:placetype":"venue"
},
  "geometry": {"coordinates":[-3.9198110104,38.0031738281],"type":"Point"}
}