{
  "type": "Feature",
  "properties": {
    "iso:country":"ES",
    "sg:address":"Calle de Maestro Zudaire, 3",
    "sg:city":"Estacion",
    "sg:orig_category":"Inform\u00c1tica: Consultores",
    "sg:phone":"+34 918 51 43 24",
    "sg:postcode":"28400",
    "sg:province":"Madrid",
    "wof:name":"Mooren Consultoria S.l.",
    "wof:placetype":"venue"
},
  "geometry": {"coordinates":[-4.0207929611,40.633266449],"type":"Point"}
}