{
  "type": "Feature",
  "properties": {
    "iso:country":"ES",
    "sg:address":"Avda Republica Argentina, 26",
    "sg:city":"Cordoba",
    "sg:orig_category":"Muebles",
    "sg:phone":"+34 957 41 19 25",
    "sg:postcode":"14004",
    "sg:province":"C\u00f3rdoba",
    "sg:website":"www.lasilladecordoba.com",
    "wof:name":"La Silla C.b.",
    "wof:placetype":"venue"
},
  "geometry": {"coordinates":[-4.7865128517,37.8842163086],"type":"Point"}
}