{
  "type": "Feature",
  "properties": {
    "addr:full":"Calle de San Cristobal, 24 Ecija Sevilla 41400",
    "addr:housenumber":"24",
    "addr:postcode":"41400",
    "addr:street":"Calle De San Cristobal",
    "iso:country":"ES",
    "sg:address":"Calle de San Cristobal, 24",
    "sg:city":"Ecija",
    "sg:orig_category":"Carnicer\u00cdas, Carnicer\u00cdas",
    "sg:phone":"+34 955 90 08 82",
    "sg:postcode":"41400",
    "sg:province":"Sevilla",
    "wof:name":"Productos Derivados Del Cerdo Parra S.l.",
    "wof:placetype":"venue"
},
  "geometry": {"coordinates":[-5.0831999779,37.546169281],"type":"Point"}
}