{
  "type": "Feature",
  "properties": {
    "addr:full":"Carrer de Casanova, 169 Barcelona Barcelona 08036",
    "addr:housenumber":"169",
    "addr:postcode":"08036",
    "addr:street":"Carrer De Casanova",
    "iso:country":"ES",
    "sg:address":"Carrer de Casanova, 169",
    "sg:city":"Barcelona",
    "sg:orig_category":"Molduras, Junquillos, Listones Y Molduras Perforadas",
    "sg:phone":"+34 934 10 49 13",
    "sg:postcode":"08036",
    "sg:province":"Barcelona",
    "wof:name":"Batrasal S.l.",
    "wof:placetype":"venue"
},
  "geometry": {"coordinates":[2.1501319408,41.3917617798],"type":"Point"}
}