{
  "type": "Feature",
  "properties": {
    "addr:full":"Calle de Alca\u00d1iz, S/n Huesca Huesca 22004",
    "addr:housenumber":"s",
    "addr:postcode":"22004",
    "addr:street":"Calle De Alcan\u0303Iz;/ N",
    "iso:country":"ES",
    "sg:address":"Calle de Alca\u00d1iz, S/n",
    "sg:city":"Huesca",
    "sg:orig_category":"Equipo De Refrigeraci\u00d3n Industrial",
    "sg:phone":"+34 974 21 03 96",
    "sg:postcode":"22004",
    "sg:province":"Huesca",
    "wof:name":"Hussmann Koxka S.l.",
    "wof:placetype":"venue"
},
  "geometry": {"coordinates":[-0.4167943001,42.1277427673],"type":"Point"}
}