{
  "type": "Feature",
  "properties": {
    "addr:full":"Calle de Mayor, 222 Raal Murcia 30139",
    "addr:housenumber":"222",
    "addr:postcode":"30139",
    "addr:street":"Calle De Mayor",
    "iso:country":"ES",
    "sg:address":"Calle de Mayor, 222",
    "sg:city":"Raal",
    "sg:orig_category":"Comercio, Reparaci\u00d3n De Bicicletas, De Motocicletas, De Accesorios",
    "sg:phone":"+34 968 81 01 92",
    "sg:postcode":"30139",
    "sg:province":"Murcia",
    "wof:name":"Gonzalez Martinez Francisco",
    "wof:placetype":"venue"
},
  "geometry": {"coordinates":[-1.0265899897,38.0407943726],"type":"Point"}
}