{
  "type": "Feature",
  "properties": {
    "iso:country":"ES",
    "sg:address":"Ctra. Gral-benia, S/n",
    "sg:city":"Onis",
    "sg:orig_category":"Cajas Para Embalar",
    "sg:phone":"+34 985 84 40 92",
    "sg:postcode":"33556",
    "sg:province":"Asturias",
    "wof:name":"Caja Rural De Asturias",
    "wof:placetype":"venue"
},
  "geometry": {"coordinates":[-4.9671940804,43.3350143433],"type":"Point"}
}