{
  "type": "Feature",
  "properties": {
    "addr:full":"Avgd Pius Xii, 3 Villarreal Castell\u00f3n 12540",
    "addr:housenumber":"3",
    "addr:postcode":"12540",
    "addr:street":"Xii",
    "iso:country":"ES",
    "sg:address":"Avgd Pius Xii, 3",
    "sg:city":"Villarreal",
    "sg:orig_category":"Abogados",
    "sg:phone":"+34 964 52 15 05",
    "sg:postcode":"12540",
    "sg:province":"Castell\u00f3n",
    "wof:name":"Agulleiro Gumbau Ricardo",
    "wof:placetype":"venue"
},
  "geometry": {"coordinates":[-0.1214234978,39.9298171997],"type":"Point"}
}