{
  "type": "Feature",
  "properties": {
    "addr:full":"Calle de Gran Via, 23 Salamanca Salamanca 37001",
    "addr:housenumber":"23",
    "addr:postcode":"37001",
    "addr:street":"Calle De Gran Via",
    "iso:country":"ES",
    "sg:address":"Calle de Gran Via, 23",
    "sg:city":"Salamanca",
    "sg:orig_category":"Fotograf\u00cda Y Cine: Aparatos, Pel\u00cdculas Y Accesorios (al Por Menor)",
    "sg:phone":"+34 923 26 67 95",
    "sg:postcode":"37001",
    "sg:province":"Salamanca",
    "wof:name":"Laso Prieto Guillermo",
    "wof:placetype":"venue"
},
  "geometry": {"coordinates":[-5.6591482162,40.9670562744],"type":"Point"}
}