{
  "type": "Feature",
  "properties": {
    "addr:full":"Calle de Molino Nuevo, 15 Villarrobledo Albacete 02600",
    "addr:housenumber":"15",
    "addr:postcode":"02600",
    "addr:street":"Calle De Molino Nuevo",
    "iso:country":"ES",
    "sg:address":"Calle de Molino Nuevo, 15",
    "sg:city":"Villarrobledo",
    "sg:orig_category":"Laboratorios Y Asesor\u00cda En Enolog\u00cda",
    "sg:phone":"+34 967 14 32 15",
    "sg:postcode":"02600",
    "sg:province":"Albacete",
    "wof:name":"Toro Alca\u00f1iz Pedro Antonio Del",
    "wof:placetype":"venue"
},
  "geometry": {"coordinates":[-2.6042346954,39.261592865],"type":"Point"}
}