{
  "type": "Feature",
  "properties": {
    "addr:full":"Calle de Edison, 57 Getafe Madrid 28906",
    "addr:housenumber":"57",
    "addr:postcode":"28906",
    "addr:street":"Calle De Edison",
    "iso:country":"ES",
    "sg:address":"Calle de Edison, 57",
    "sg:city":"Getafe",
    "sg:orig_category":"Venta, Alquiler De Grupos Electr\u00d3genos",
    "sg:phone":"+34 916 84 21 06",
    "sg:postcode":"28906",
    "sg:province":"Madrid",
    "sg:website":"www.himoinsa.com",
    "wof:name":"Himoinsa S.l.",
    "wof:placetype":"venue"
},
  "geometry": {"coordinates":[-3.6937744617,40.3023490906],"type":"Point"}
}