{
  "type": "Feature",
  "properties": {
    "iso:country":"ES",
    "sg:address":"Calle de Republica Dominicana, S/n",
    "sg:city":"Badajoz",
    "sg:orig_category":"Cajas De Ahorro",
    "sg:phone":"+34 924 24 15 04",
    "sg:postcode":"06011",
    "sg:province":"Badajoz",
    "sg:website":"www.cajaextremadura.es",
    "wof:name":"Caja De Ahorros Y Monte De Piedad De Extremadura",
    "wof:placetype":"venue"
},
  "geometry": {"coordinates":[-6.9868941307,38.8743209839],"type":"Point"}
}