{
  "type": "Feature",
  "properties": {
    "addr:full":"Luga Llonin, S/n Llonin Asturias 33578",
    "addr:housenumber":"s",
    "addr:postcode":"33578",
    "addr:street":"/ N Llonin Asturias",
    "iso:country":"ES",
    "sg:address":"Luga Llonin, S/n",
    "sg:city":"Llonin",
    "sg:orig_category":"Producci\u00d3n De Sidra",
    "sg:phone":"+34 985 41 58 86",
    "sg:postcode":"33578",
    "sg:province":"Asturias",
    "wof:name":"Cooperativa Rio Aliso Sociedad Cooperativa",
    "wof:placetype":"venue"
},
  "geometry": {"coordinates":[-4.7040839195,43.3326530457],"type":"Point"}
}