{
  "type": "Feature",
  "properties": {
    "addr:full":"Carrer de Fontanills, 25 Masnou Barcelona 08320",
    "addr:housenumber":"25",
    "addr:postcode":"08320",
    "addr:street":"Carrer De Fontanills",
    "iso:country":"ES",
    "sg:address":"Carrer de Fontanills, 25",
    "sg:city":"Masnou",
    "sg:orig_category":"Arreglo, Reparaci\u00d3n, Piezas Sueltas De Televisi\u00d3n, V\u00cddeo, Hi",
    "sg:phone":"+34 935 40 52 43",
    "sg:postcode":"08320",
    "sg:province":"Barcelona",
    "wof:name":"Promotienda S.l.",
    "wof:placetype":"venue"
},
  "geometry": {"coordinates":[2.3223888874,41.4821472168],"type":"Point"}
}