{
  "type": "Feature",
  "properties": {
    "iso:country":"ES",
    "sg:address":"Carrer de Gombau, 1",
    "sg:city":"Flix",
    "sg:orig_category":"Zapatos (al Por Menor)",
    "sg:phone":"+34 977 41 02 35",
    "sg:postcode":"43750",
    "sg:province":"Tarragona",
    "wof:name":"Perez Affonso Jaume Demetri",
    "wof:placetype":"venue"
},
  "geometry": {"coordinates":[0.5498840213,41.2316818237],"type":"Point"}
}