{
  "type": "Feature",
  "properties": {
    "iso:country":"ES",
    "sg:address":"Calle de Pedro Antonio De Alarcon, 37",
    "sg:city":"Granada",
    "sg:orig_category":"Laboratorios Farmac\u00c9uticos",
    "sg:phone":"+34 958 25 97 91",
    "sg:postcode":"18004",
    "sg:province":"Granada",
    "wof:name":"Ruiz Sequera Jose Maria",
    "wof:placetype":"venue"
},
  "geometry": {"coordinates":[-3.6062510014,37.1723556519],"type":"Point"}
}