{
  "type": "Feature",
  "properties": {
    "addr:full":"Praz Maior, 21 Lugo Lugo 27001",
    "addr:housenumber":"21",
    "addr:postcode":"27001",
    "addr:street":"Praz Maior",
    "iso:country":"ES",
    "sg:address":"Praz Maior, 21",
    "sg:city":"Lugo",
    "sg:orig_category":"Confecci\u00d3n (fabricaci\u00d3n, Al Por Mayor)",
    "sg:phone":"+34 982 22 67 01",
    "sg:postcode":"27001",
    "sg:province":"Lugo",
    "wof:name":"Miguelez Carballo Susana",
    "wof:placetype":"venue"
},
  "geometry": {"coordinates":[-7.5567851067,43.009311676],"type":"Point"}
}