{
  "type": "Feature",
  "properties": {
    "addr:full":"Plaz San Martin De Abenda\u00d1o, 4 Vitoria-gasteiz \u00c1lava 01009",
    "addr:housenumber":"4",
    "addr:postcode":"01009",
    "addr:street":"Plaz;Abendan\u0303O",
    "iso:country":"ES",
    "sg:address":"Plaz San Martin De Abenda\u00d1o, 4",
    "sg:city":"Vitoria-gasteiz",
    "sg:orig_category":"Peluqueros: De Se\u00d1oras",
    "sg:phone":"+34 945 24 24 10",
    "sg:postcode":"01009",
    "sg:province":"\u00c1lava",
    "wof:name":"Moraza Lopez Arkaute Mari Mar",
    "wof:placetype":"venue"
},
  "geometry": {"coordinates":[-2.6875550747,42.8520927429],"type":"Point"}
}