{
  "type": "Feature",
  "properties": {
    "iso:country":"ES",
    "sg:address":"Avda Gonzalez Mayo, 3",
    "sg:city":"Tineo",
    "sg:orig_category":"Telas Y Sedas (al Por Menor)",
    "sg:phone":"+34 985 80 10 67",
    "sg:postcode":"33870",
    "sg:province":"Asturias",
    "wof:name":"Garcia Diez Laureano Victor",
    "wof:placetype":"venue"
},
  "geometry": {"coordinates":[-6.416246891,43.3379364014],"type":"Point"}
}