{
  "type": "Feature",
  "properties": {
    "addr:full":"Calle de Pasos (los), 27 Redovan Alicante 03370",
    "addr:housenumber":"27",
    "addr:postcode":"03370",
    "addr:street":"Calle De Pasos Los;Alicante",
    "iso:country":"ES",
    "sg:address":"Calle de Pasos (los), 27",
    "sg:city":"Redovan",
    "sg:orig_category":"Fabricaci\u00d3n De Art\u00cdculos Y Equipos Deportivos Y De Ocio",
    "sg:phone":"+34 966 75 45 78",
    "sg:postcode":"03370",
    "sg:province":"Alicante",
    "wof:name":"Romario S.l.",
    "wof:placetype":"venue"
},
  "geometry": {"coordinates":[-0.9075790048,38.1163063049],"type":"Point"}
}