{
  "type": "Feature",
  "properties": {
    "addr:full":"Calle de Martinez De Escobar Los, 22 Palmas De Gran Canaria Las Palmas 35007",
    "addr:postcode":"35007",
    "addr:street":"Calle De Martinez De Escobar Los",
    "iso:country":"ES",
    "sg:address":"Calle de Martinez De Escobar Los, 22",
    "sg:city":"Palmas De Gran Canaria",
    "sg:orig_category":"Bazares, Art\u00cdculos De Limpieza Y De Cocina (al Por Menor)",
    "sg:phone":"+34 928 27 90 74",
    "sg:postcode":"35007",
    "sg:province":"Las Palmas",
    "wof:name":"Incomova S.l.",
    "wof:placetype":"venue"
},
  "geometry": {"coordinates":[-15.433218956,28.13829422],"type":"Point"}
}