{
  "type": "Feature",
  "properties": {
    "addr:full":"G.v. Fernando El Catolico, 70 Valencia Valencia 46008",
    "addr:housenumber":"70",
    "addr:postcode":"46008",
    "addr:street":"Fernando El Catolico",
    "iso:country":"ES",
    "sg:address":"G.v. Fernando El Catolico, 70",
    "sg:city":"Valencia",
    "sg:orig_category":"Administradores De Bienes Y Delegados De Comunidades De Propietarios",
    "sg:phone":"+34 963 91 95 48",
    "sg:postcode":"46008",
    "sg:province":"Valencia",
    "wof:name":"Azorin Colom Manuel Jose",
    "wof:placetype":"venue"
},
  "geometry": {"coordinates":[-0.3880563974,39.4748382568],"type":"Point"}
}