{
  "type": "Feature",
  "properties": {
    "addr:full":"Calle de Copo, 10 San Pedro Alcantara M\u00e1laga 29670",
    "addr:housenumber":"10",
    "addr:postcode":"29670",
    "addr:street":"Calle De Copo",
    "iso:country":"ES",
    "sg:address":"Calle de Copo, 10",
    "sg:city":"San Pedro Alcantara",
    "sg:orig_category":"Sociedades, Compa\u00d1\u00cdas Aseguradoras",
    "sg:phone":"+34 952 78 21 62",
    "sg:postcode":"29670",
    "sg:province":"M\u00e1laga",
    "wof:name":"Knight Insurance Brokers S.a.",
    "wof:placetype":"venue"
},
  "geometry": {"coordinates":[-4.9910140038,36.4845924377],"type":"Point"}
}