{
  "type": "Feature",
  "properties": {
    "addr:full":"Avda Diputacion, 78 Xove Lugo 27870",
    "addr:housenumber":"78",
    "addr:postcode":"27870",
    "addr:street":"Avda Diputacion",
    "iso:country":"ES",
    "sg:address":"Avda Diputacion, 78",
    "sg:city":"Xove",
    "sg:orig_category":"Librer\u00cdas",
    "sg:phone":"+34 982 59 23 02",
    "sg:postcode":"27870",
    "sg:province":"Lugo",
    "wof:name":"Rey Pardi\u00f1o Elena",
    "wof:placetype":"venue"
},
  "geometry": {"coordinates":[-7.5126390457,43.6849517822],"type":"Point"}
}