{
  "type": "Feature",
  "properties": {
    "iso:country":"ES",
    "sg:address":"Calle de Paloma, 19",
    "sg:city":"Madrid",
    "sg:orig_category":"Iglesia Cat\u00d3lica",
    "sg:phone":"+34 913 65 46 69",
    "sg:postcode":"28005",
    "sg:province":"Madrid",
    "wof:name":"Parroquia De La Virgen De La Paloma Y San Pedro El Real. Madrid",
    "wof:placetype":"venue"
},
  "geometry": {"coordinates":[-3.7118120193,40.4083518982],"type":"Point"}
}