{
  "type": "Feature",
  "properties": {
    "addr:full":"Calle de Luis Guedea, 15 Calatayud Zaragoza 50300",
    "addr:housenumber":"15",
    "addr:postcode":"50300",
    "addr:street":"Calle De Luis Guedea",
    "iso:country":"ES",
    "sg:address":"Calle de Luis Guedea, 15",
    "sg:city":"Calatayud",
    "sg:orig_category":"Talleres: Ropa A Medida",
    "sg:phone":"+34 976 88 28 37",
    "sg:postcode":"50300",
    "sg:province":"Zaragoza",
    "wof:name":"Arrue Vera Luis",
    "wof:placetype":"venue"
},
  "geometry": {"coordinates":[-1.6410981417,41.3522834778],"type":"Point"}
}