{
  "type": "Feature",
  "properties": {
    "iso:country":"ES",
    "sg:address":"Calle de Francos (los), 21",
    "sg:city":"Barrios",
    "sg:orig_category":"Colchones (fabricaci\u00d3n, Al Por Mayor, Al Por Menor)",
    "sg:phone":"+34 956 62 26 29",
    "sg:postcode":"11370",
    "sg:province":"C\u00e1diz",
    "wof:name":"Alcalup S.l.",
    "wof:placetype":"venue"
},
  "geometry": {"coordinates":[-5.4933381081,36.1837844849],"type":"Point"}
}