{
  "type": "Feature",
  "properties": {
    "addr:full":"Calle de Manuel De Falla, 23 Dos Hermanas Sevilla 41700",
    "addr:housenumber":"23",
    "addr:postcode":"41700",
    "addr:street":"Calle De Manuel De Falla",
    "iso:country":"ES",
    "sg:address":"Calle de Manuel De Falla, 23",
    "sg:city":"Dos Hermanas",
    "sg:orig_category":"Arreglo, Reparaci\u00d3n, Piezas Sueltas De Televisi\u00d3n, V\u00cddeo, Hi",
    "sg:phone":"+34 955 66 10 97",
    "sg:postcode":"41700",
    "sg:province":"Sevilla",
    "wof:name":"O.s.l-punto Y Numero Cero S.l.",
    "wof:placetype":"venue"
},
  "geometry": {"coordinates":[-5.9219908714,37.281375885],"type":"Point"}
}