{
  "type": "Feature",
  "properties": {
    "addr:full":"Calle de Portales, 75 Logro\u00f1o La Rioja 26001",
    "addr:housenumber":"75",
    "addr:postcode":"26001",
    "addr:street":"Calle De Portales;Rioja",
    "iso:country":"ES",
    "sg:address":"Calle de Portales, 75",
    "sg:city":"Logro\u00f1o",
    "sg:orig_category":"Mudanzas",
    "sg:phone":"+34 941 20 40 74",
    "sg:postcode":"26001",
    "sg:province":"La Rioja",
    "wof:name":"Mudar S.l.",
    "wof:placetype":"venue"
},
  "geometry": {"coordinates":[-2.4491391182,42.4661979675],"type":"Point"}
}