{
  "type": "Feature",
  "properties": {
    "addr:full":"Calle de Monegros, 81 Leganes Madrid 28915",
    "addr:housenumber":"81",
    "addr:postcode":"28915",
    "addr:street":"Calle De Monegros",
    "iso:country":"ES",
    "sg:address":"Calle de Monegros, 81",
    "sg:city":"Leganes",
    "sg:orig_category":"Peluqueros: De Se\u00d1oras",
    "sg:phone":"+34 916 86 11 51",
    "sg:postcode":"28915",
    "sg:province":"Madrid",
    "wof:name":"Quijorna Criado Maria Del Sagrario",
    "wof:placetype":"venue"
},
  "geometry": {"coordinates":[-3.7499320507,40.3365020752],"type":"Point"}
}