{
  "type": "Feature",
  "properties": {
    "iso:country":"ES",
    "sg:address":"Avda Casalduch, 17",
    "sg:city":"Castellon",
    "sg:orig_category":"Importaci\u00d3n",
    "sg:phone":"+34 964 22 27 68",
    "sg:postcode":"12005",
    "sg:province":"Castell\u00f3n",
    "wof:name":"Jimex Trading Company S.l.",
    "wof:placetype":"venue"
},
  "geometry": {"coordinates":[-0.0367249995,39.9809112549],"type":"Point"}
}