{
  "type": "Feature",
  "properties": {
    "iso:country":"ES",
    "sg:address":"Carr Olot, 4",
    "sg:city":"Figueres",
    "sg:orig_category":"Transporte En General",
    "sg:phone":"+34 972 50 04 69",
    "sg:postcode":"17600",
    "sg:province":"Girona",
    "wof:name":"Manera Cullell Jose",
    "wof:placetype":"venue"
},
  "geometry": {"coordinates":[2.9695270061,42.2669143677],"type":"Point"}
}