{
  "type": "Feature",
  "properties": {
    "addr:full":"Carrer de Fabrica, 43 Palma Islas Baleares 07013",
    "addr:housenumber":"43",
    "addr:postcode":"07013",
    "addr:street":"Carrer De Fabrica",
    "iso:country":"ES",
    "sg:address":"Carrer de Fabrica, 43",
    "sg:city":"Palma",
    "sg:orig_category":"Postigos, Persianas Y Celos\u00cdas",
    "sg:phone":"+34 971 28 32 46",
    "sg:postcode":"07013",
    "sg:province":"Islas Baleares",
    "wof:name":"Frau Mas Damian",
    "wof:placetype":"venue"
},
  "geometry": {"coordinates":[2.6375288963,39.5726318359],"type":"Point"}
}