{
  "type": "Feature",
  "properties": {
    "addr:full":"Calle de Ingeniero De La Cierva, 2 Malaga M\u00e1laga 29004",
    "addr:housenumber":"2",
    "addr:postcode":"29004",
    "addr:street":"Calle De Ingeniero;La Cierva;Ma\u0301Laga",
    "iso:country":"ES",
    "sg:address":"Calle de Ingeniero De La Cierva, 2",
    "sg:city":"Malaga",
    "sg:orig_category":"Asesor\u00cda De Formaci\u00d3n Y Gesti\u00d3n De Personal",
    "sg:phone":"+34 952 08 26 35",
    "sg:postcode":"29004",
    "sg:province":"M\u00e1laga",
    "wof:name":"Real Toro Francisco",
    "wof:placetype":"venue"
},
  "geometry": {"coordinates":[-4.4522848129,36.6968765259],"type":"Point"}
}