{
  "type": "Feature",
  "properties": {
    "addr:full":"Psaj Mallol, 16 Sevilla Sevilla 41003",
    "addr:housenumber":"16",
    "addr:postcode":"41003",
    "addr:street":"Mallol",
    "iso:country":"ES",
    "sg:address":"Psaj Mallol, 16",
    "sg:city":"Sevilla",
    "sg:orig_category":"M\u00dasica Diversa",
    "sg:phone":"+34 954 41 10 51",
    "sg:postcode":"41003",
    "sg:province":"Sevilla",
    "wof:name":"Asociacion Musica Antigua De Sevilla",
    "wof:placetype":"venue"
},
  "geometry": {"coordinates":[-5.985543251,37.3975372314],"type":"Point"}
}