{
  "type": "Feature",
  "properties": {
    "iso:country":"ES",
    "sg:address":"Calle de Concepcion, 14",
    "sg:city":"Puebla Calzada",
    "sg:orig_category":"Laboratorios Y Cl\u00cdnicas Veterinarias",
    "sg:phone":"+34 924 45 05 76",
    "sg:postcode":"06490",
    "sg:province":"Badajoz",
    "wof:name":"Moya Carre\u00f1o Antonio Manuel",
    "wof:placetype":"venue"
},
  "geometry": {"coordinates":[-6.6242179871,38.8921279907],"type":"Point"}
}