{
  "type": "Feature",
  "properties": {
    "iso:country":"ES",
    "sg:address":"Carrer de Tallers, 77",
    "sg:city":"Barcelona",
    "sg:orig_category":"Arquitectos",
    "sg:phone":"+34 933 42 59 00",
    "sg:postcode":"08001",
    "sg:province":"Barcelona",
    "wof:name":"Samso I Associats C.b.",
    "wof:placetype":"venue"
},
  "geometry": {"coordinates":[2.1663489342,41.3848495483],"type":"Point"}
}