{
  "type": "Feature",
  "properties": {
    "iso:country":"ES",
    "sg:address":"Carrer de Palau D'ametlla (de), 13",
    "sg:city":"Montornes Centre",
    "sg:orig_category":"Perfumer\u00cda (al Por Menor)",
    "sg:phone":"+34 935 68 02 43",
    "sg:postcode":"08170",
    "sg:province":"Barcelona",
    "wof:name":"Establecimientos Iris S.c.p.",
    "wof:placetype":"venue"
},
  "geometry": {"coordinates":[2.263240099,41.5383987427],"type":"Point"}
}