{
  "type": "Feature",
  "properties": {
    "addr:full":"Urb Molino (el), 17 Valles Cantabria 39590",
    "addr:postcode":"39590",
    "addr:street":"Urb Molino El",
    "iso:country":"ES",
    "sg:address":"Urb Molino (el), 17",
    "sg:city":"Valles",
    "sg:orig_category":"Delegados, Agentes De Tr\u00c1nsito, Auxiliares De Transporte Internacional",
    "sg:phone":"+34 942 82 11 19",
    "sg:postcode":"39590",
    "sg:province":"Cantabria",
    "wof:name":"Mantecon Lopez Jose Manuel",
    "wof:placetype":"venue"
},
  "geometry": {"coordinates":[-4.1317028999,43.3504219055],"type":"Point"}
}