{
  "type": "Feature",
  "properties": {
    "addr:full":"Avda Plutarco, 73 Malaga M\u00e1laga 29010",
    "addr:housenumber":"73",
    "addr:postcode":"29010",
    "addr:street":"Avda Plutarco;Ma\u0301Laga",
    "iso:country":"ES",
    "sg:address":"Avda Plutarco, 73",
    "sg:city":"Malaga",
    "sg:orig_category":"Cajas Para Embalar",
    "sg:phone":"+34 952 07 09 60",
    "sg:postcode":"29010",
    "sg:province":"M\u00e1laga",
    "sg:website":"www.cajamar.es",
    "wof:name":"Cajamar",
    "wof:placetype":"venue"
},
  "geometry": {"coordinates":[-4.4728488922,36.7208099365],"type":"Point"}
}