{
  "type": "Feature",
  "properties": {
    "iso:country":"ES",
    "sg:address":"Plaz Conde De Miranda, 1",
    "sg:city":"Madrid",
    "sg:orig_category":"Laboratorios Y Trabajos De Fotograf\u00cda, V\u00cddeo Y Cine",
    "sg:phone":"+34 915 48 21 88",
    "sg:postcode":"28005",
    "sg:province":"Madrid",
    "sg:website":"www.instantanea.net",
    "wof:name":"Instantanea Photo Agency S.l",
    "wof:placetype":"venue"
},
  "geometry": {"coordinates":[-3.709307909,40.4146652222],"type":"Point"}
}