{
  "type": "Feature",
  "properties": {
    "addr:full":"Calle de Victoria Merida Y Piret, 6 Malaga M\u00e1laga 29004",
    "addr:housenumber":"6",
    "addr:postcode":"29004",
    "addr:street":"Calle De Victoria Merida Y Piret;Ma\u0301Laga",
    "iso:country":"ES",
    "sg:address":"Calle de Victoria Merida Y Piret, 6",
    "sg:city":"Malaga",
    "sg:orig_category":"Cl\u00cdnicas Dentales",
    "sg:phone":"+34 952 23 01 00",
    "sg:postcode":"29004",
    "sg:province":"M\u00e1laga",
    "wof:name":"Lopez Ceres Jose Manuel",
    "wof:placetype":"venue"
},
  "geometry": {"coordinates":[-4.4454460144,36.6942062378],"type":"Point"}
}