{
  "type": "Feature",
  "properties": {
    "addr:full":"Pla\u00c7 Catalunya, 6 Girona Girona 17002",
    "addr:housenumber":"6",
    "addr:postcode":"17002",
    "iso:country":"ES",
    "sg:address":"Pla\u00c7 Catalunya, 6",
    "sg:city":"Girona",
    "sg:orig_category":"Inmobiliaria (agencias)",
    "sg:phone":"+34 972 21 93 04",
    "sg:postcode":"17002",
    "sg:province":"Girona",
    "wof:name":"Finques Molas S.l.",
    "wof:placetype":"venue"
},
  "geometry": {"coordinates":[2.8187448978,41.9808616638],"type":"Point"}
}