{
  "type": "Feature",
  "properties": {
    "addr:full":"Calle de Abanico, 16 Albacete Albacete 02006",
    "addr:housenumber":"16",
    "addr:postcode":"02006",
    "addr:street":"Calle De Abanico",
    "iso:country":"ES",
    "sg:address":"Calle de Abanico, 16",
    "sg:city":"Albacete",
    "sg:orig_category":"Promotores Constructores",
    "sg:phone":"+34 967 50 94 19",
    "sg:postcode":"02006",
    "sg:province":"Albacete",
    "wof:name":"Construcciones Y Excavaciones Coarsa S.l.",
    "wof:placetype":"venue"
},
  "geometry": {"coordinates":[-1.8704993725,38.9822463989],"type":"Point"}
}