{
  "type": "Feature",
  "properties": {
    "addr:full":"Sur, 2 Cortijos Abajo Ciudad Real 13427",
    "addr:postcode":"13427",
    "iso:country":"ES",
    "sg:address":"Sur, 2",
    "sg:city":"Cortijos Abajo",
    "sg:orig_category":"Asistencia Social",
    "sg:phone":"+34 926 80 84 55",
    "sg:postcode":"13427",
    "sg:province":"Ciudad Real",
    "wof:name":"Ayuntamiento De Los Cortijos De Abajo",
    "wof:placetype":"venue"
},
  "geometry": {"coordinates":[-4.043504715,39.3138580322],"type":"Point"}
}