{
  "type": "Feature",
  "properties": {
    "addr:full":"Cementerio, 20 Sta Olaja Ribera Le\u00f3n 24199",
    "addr:housenumber":"20",
    "addr:postcode":"24199",
    "iso:country":"ES",
    "sg:address":"Cementerio, 20",
    "sg:city":"Sta Olaja Ribera",
    "sg:classifiers":[
        {
            "category":"Manufacturing",
            "subcategory":"Metals",
            "type":"Manufacturing & Wholesale Goods"
        }
    ],
    "sg:phone":"+34 987 21 20 94",
    "sg:postcode":"24199",
    "sg:province":"Le\u00f3n",
    "sg:tags":[
        "en",
        "fundiciones"
    ],
    "wof:name":"Rebollo Alaiz Jose Javier",
    "wof:placetype":"venue"
},
  "geometry": {"coordinates":[-5.5527420044,42.5583229065],"type":"Point"}
}