{
  "type": "Feature",
  "properties": {
    "iso:country":"ES",
    "sg:address":"Urb Montornes, 319",
    "sg:city":"Voltants Montornes",
    "sg:orig_category":"Centros Empresariales",
    "sg:phone":"+34 964 39 83 62",
    "sg:postcode":"12560",
    "sg:province":"Castell\u00f3n",
    "wof:name":"Martinez Lopez Maria Mercedes C.b.",
    "wof:placetype":"venue"
},
  "geometry": {"coordinates":[0.0590550005,40.0523414612],"type":"Point"}
}