{
  "type": "Feature",
  "properties": {
    "addr:full":"Calle de Zubiaurre, 65 Donostia-san Sebastian Guip\u00f9zcoa 20015",
    "addr:housenumber":"65",
    "addr:postcode":"20015",
    "addr:street":"Calle De Zubiaurre",
    "iso:country":"ES",
    "sg:address":"Calle de Zubiaurre, 65",
    "sg:city":"Donostia-san Sebastian",
    "sg:orig_category":"Librer\u00cdas",
    "sg:phone":"+34 943 28 72 29",
    "sg:postcode":"20015",
    "sg:province":"Guip\u00f9zcoa",
    "wof:name":"Zabalza Pagola Julian",
    "wof:placetype":"venue"
},
  "geometry": {"coordinates":[-1.951811552,43.3198547363],"type":"Point"}
}