{
  "type": "Feature",
  "properties": {
    "iso:country":"ES",
    "sg:address":"Carrer de Born, 8",
    "sg:city":"Manresa",
    "sg:orig_category":"Doctores En Medicina",
    "sg:phone":"+34 938 72 17 05",
    "sg:postcode":"08241",
    "sg:province":"Barcelona",
    "wof:name":"Selga Brunet Urbici",
    "wof:placetype":"venue"
},
  "geometry": {"coordinates":[1.8246769905,41.7242279053],"type":"Point"}
}