{
  "type": "Feature",
  "properties": {
    "addr:full":"Carr Josep Pla, 2 Bisbal D'emporda Girona 17100",
    "addr:housenumber":"2",
    "addr:postcode":"17100",
    "addr:street":"Carr Josep Pla",
    "iso:country":"ES",
    "sg:address":"Carr Josep Pla, 2",
    "sg:city":"Bisbal D'emporda",
    "sg:orig_category":"Pr\u00c9stamos Personales E Hipotecarios",
    "sg:phone":"+34 972 64 02 49",
    "sg:postcode":"17100",
    "sg:province":"Girona",
    "wof:name":"Garcia Lopez Vicente Jose",
    "wof:placetype":"venue"
},
  "geometry": {"coordinates":[2.8221259117,41.9835357666],"type":"Point"}
}