{
  "type": "Feature",
  "properties": {
    "iso:country":"ES",
    "sg:address":"Avda Ntra. Sra. De Valvanera, 37",
    "sg:city":"Calahorra",
    "sg:orig_category":"Carnicer\u00cdas, Carnicer\u00cdas",
    "sg:phone":"+34 941 14 61 45",
    "sg:postcode":"26500",
    "sg:province":"La Rioja",
    "wof:name":"Argaiz Perez Maria Glay Del Carmen",
    "wof:placetype":"venue"
},
  "geometry": {"coordinates":[-1.9685826302,42.2785606384],"type":"Point"}
}