{
  "type": "Feature",
  "properties": {
    "iso:country":"ES",
    "sg:address":"Calle de Torre Alvarez, 11",
    "sg:city":"Vista Alegre",
    "sg:orig_category":"Consultores De Telecomunicaciones",
    "sg:phone":"+34 968 23 10 82",
    "sg:postcode":"30007",
    "sg:province":"Murcia",
    "wof:name":"Iniesta Lujan Francisco",
    "wof:placetype":"venue"
},
  "geometry": {"coordinates":[-1.1142389774,37.9970092773],"type":"Point"}
}