{
  "type": "Feature",
  "properties": {
    "iso:country":"ES",
    "sg:address":"Pase San Antonio (de), 6",
    "sg:city":"Fuenlabrada",
    "sg:orig_category":"Colchones (fabricaci\u00d3n, Al Por Mayor, Al Por Menor)",
    "sg:phone":"+34 916 90 57 48",
    "sg:postcode":"28945",
    "sg:province":"Madrid",
    "wof:name":"Balonga Jimenez Blanca Esther",
    "wof:placetype":"venue"
},
  "geometry": {"coordinates":[-3.7947189808,40.2852516174],"type":"Point"}
}