{
  "type": "Feature",
  "properties": {
    "iso:country":"ES",
    "sg:address":"Avda Jeronimo Roure, 51",
    "sg:city":"Puerto",
    "sg:orig_category":"Agentes, Concesionarios Y Sucursales De Veh\u00cdculos",
    "sg:phone":"+34 962 68 26 63",
    "sg:postcode":"46520",
    "sg:province":"Valencia",
    "wof:name":"Guconsa Auto S.a.",
    "wof:placetype":"venue"
},
  "geometry": {"coordinates":[-0.2273789048,39.6555862427],"type":"Point"}
}