{
  "type": "Feature",
  "properties": {
    "addr:full":"Calle de Santa Ana, 1 Villamayor Salamanca 37185",
    "addr:housenumber":"1",
    "addr:postcode":"37185",
    "addr:street":"Calle De Santa Ana",
    "iso:country":"ES",
    "sg:address":"Calle de Santa Ana, 1",
    "sg:city":"Villamayor",
    "sg:orig_category":"Promotores Constructores",
    "sg:phone":"+34 923 28 69 39",
    "sg:postcode":"37185",
    "sg:province":"Salamanca",
    "wof:name":"Ulticon 2004 S.l.",
    "wof:placetype":"venue"
},
  "geometry": {"coordinates":[-5.6959271431,40.9986190796],"type":"Point"}
}