{
  "type": "Feature",
  "properties": {
    "iso:country":"ES",
    "sg:address":"C/ Major, 338",
    "sg:city":"Salt",
    "sg:orig_category":"Mec\u00c1nico Del Autom\u00d3vil",
    "sg:phone":"+34 972 23 44 15",
    "sg:postcode":"17190",
    "sg:province":"Girona",
    "wof:name":"Lopez Rodriguez Antonio Tomas Lopez Rodr",
    "wof:placetype":"venue"
},
  "geometry": {"coordinates":[2.8000669479,41.9762611389],"type":"Point"}
}