{
  "type": "Feature",
  "properties": {
    "iso:country":"ES",
    "sg:address":"Plaz Mayor, 1",
    "sg:city":"Ayllon",
    "sg:orig_category":"Reposter\u00cdas",
    "sg:phone":"+34 921 55 33 31",
    "sg:postcode":"40520",
    "sg:province":"Segovia",
    "wof:name":"Sanz Mu\u00f1oz Fortunato",
    "wof:placetype":"venue"
},
  "geometry": {"coordinates":[-3.3560540676,41.376159668],"type":"Point"}
}