{
  "type": "Feature",
  "properties": {
    "iso:country":"ES",
    "sg:address":"Calle de Mayor, 14",
    "sg:city":"Torres Cotillas",
    "sg:orig_category":"Servicios De Telecomunicaciones",
    "sg:phone":"+34 968 62 65 82",
    "sg:postcode":"30565",
    "sg:province":"Murcia",
    "wof:name":"Pazmino  Mariela Del Carmen",
    "wof:placetype":"venue"
},
  "geometry": {"coordinates":[-1.2395490408,38.0263290405],"type":"Point"}
}