{
  "type": "Feature",
  "properties": {
    "addr:full":"Calle de Marquesa De Pinares, 29 Merida Badajoz 06800",
    "addr:housenumber":"29",
    "addr:postcode":"06800",
    "addr:street":"Calle De Marquesa De Pinares",
    "iso:country":"ES",
    "sg:address":"Calle de Marquesa De Pinares, 29",
    "sg:city":"Merida",
    "sg:orig_category":"Electrodom\u00c9sticos (al Por Menor)",
    "sg:phone":"+34 924 31 25 35",
    "sg:postcode":"06800",
    "sg:province":"Badajoz",
    "wof:name":"Reytol Electrodomesticos S.l.",
    "wof:placetype":"venue"
},
  "geometry": {"coordinates":[-6.3468108177,38.9212150574],"type":"Point"}
}