{
  "type": "Feature",
  "properties": {
    "addr:full":"Calle de Mayor, 38 Sucina Murcia 30590",
    "addr:housenumber":"38",
    "addr:postcode":"30590",
    "addr:street":"Calle De Mayor",
    "iso:country":"ES",
    "sg:address":"Calle de Mayor, 38",
    "sg:city":"Sucina",
    "sg:orig_category":"Iglesia Cat\u00d3lica",
    "sg:phone":"+34 968 37 05 10",
    "sg:postcode":"30590",
    "sg:province":"Murcia",
    "wof:name":"Obispado De Cartagena",
    "wof:placetype":"venue"
},
  "geometry": {"coordinates":[-0.9416790009,37.889591217],"type":"Point"}
}