{
  "type": "Feature",
  "properties": {
    "addr:full":"Calle de Dos De Mayo, 11 Calahorra La Rioja 26500",
    "addr:housenumber":"11",
    "addr:postcode":"26500",
    "addr:street":"Calle De Dos;Mayo",
    "iso:country":"ES",
    "sg:address":"Calle de Dos De Mayo, 11",
    "sg:city":"Calahorra",
    "sg:orig_category":"Venta, Instalaci\u00d3n, Reparaci\u00d3n De Antenas Para Televisi\u00d3n",
    "sg:phone":"+34 941 13 34 39",
    "sg:postcode":"26500",
    "sg:province":"La Rioja",
    "wof:name":"Jose Ramon Alvarez S.l.",
    "wof:placetype":"venue"
},
  "geometry": {"coordinates":[-1.9663097858,42.3060417175],"type":"Point"}
}