{
  "type": "Feature",
  "properties": {
    "addr:full":"Carrer de Cristofor Colom, 39 Cambrils Tarragona 43850",
    "addr:housenumber":"39",
    "addr:postcode":"43850",
    "addr:street":"Carrer De Cristofor Colom",
    "iso:country":"ES",
    "sg:address":"Carrer de Cristofor Colom, 39",
    "sg:city":"Cambrils",
    "sg:orig_category":"Inmobiliaria (agencias)",
    "sg:phone":"+34 977 79 26 98",
    "sg:postcode":"43850",
    "sg:province":"Tarragona",
    "wof:name":"Gestions Framar S.l.",
    "wof:placetype":"venue"
},
  "geometry": {"coordinates":[1.0608229637,41.0679550171],"type":"Point"}
}