{
  "type": "Feature",
  "properties": {
    "iso:country":"ES",
    "sg:address":"Calle de Alarcon, 7",
    "sg:city":"Barrio De Los Arocas",
    "sg:orig_category":"Centros De Educaci\u00d3n Especial",
    "sg:phone":"+34 968 30 16 53",
    "sg:postcode":"30006",
    "sg:province":"Murcia",
    "wof:name":"Colegio Publico Pintor Pedro Flores",
    "wof:placetype":"venue"
},
  "geometry": {"coordinates":[-1.0940823555,37.9973640442],"type":"Point"}
}