{
  "type": "Feature",
  "properties": {
    "addr:full":"Plaz Salvador, 2 Sevilla Sevilla 41004",
    "addr:housenumber":"2",
    "addr:postcode":"41004",
    "addr:street":"Salvador",
    "iso:country":"ES",
    "sg:address":"Plaz Salvador, 2",
    "sg:city":"Sevilla",
    "sg:orig_category":"Comercio De Minerales, F\u00d3siles Y Conchas",
    "sg:phone":"+34 954 22 61 22",
    "sg:postcode":"41004",
    "sg:province":"Sevilla",
    "wof:name":"Restaurantes Macadamias S.l.",
    "wof:placetype":"venue"
},
  "geometry": {"coordinates":[-5.9931540489,37.3903694153],"type":"Point"}
}