{
  "type": "Feature",
  "properties": {
    "addr:full":"Carrer de Felip Ii, 42 Barcelona Barcelona 08027",
    "addr:housenumber":"42",
    "addr:postcode":"08027",
    "addr:street":"Carrer De Felip Ii",
    "iso:country":"ES",
    "sg:address":"Carrer de Felip Ii, 42",
    "sg:city":"Barcelona",
    "sg:orig_category":"Inmobiliaria (agencias)",
    "sg:phone":"+34 933 49 59 01",
    "sg:postcode":"08027",
    "sg:province":"Barcelona",
    "sg:website":"www.donpiso.com",
    "wof:name":"Habitat Serinmo S.l.",
    "wof:placetype":"venue"
},
  "geometry": {"coordinates":[2.1897099018,41.4184761047],"type":"Point"}
}