{
  "type": "Feature",
  "properties": {
    "iso:country":"ES",
    "sg:address":"Avda Vilaoudriz, 42",
    "sg:city":"Pontenova",
    "sg:orig_category":"Autob\u00das (explotaci\u00d3n Y Servicios De)",
    "sg:phone":"+34 982 33 61 03",
    "sg:postcode":"27720",
    "sg:province":"Lugo",
    "wof:name":"Rodil S.l.",
    "wof:placetype":"venue"
},
  "geometry": {"coordinates":[-7.1766328812,43.3744239807],"type":"Point"}
}