{
  "type": "Feature",
  "properties": {
    "iso:country":"ES",
    "sg:address":"Calle de General Vives, 55",
    "sg:city":"Palmas De Gran Canaria",
    "sg:orig_category":"Bancos",
    "sg:phone":"+34 928 26 73 66",
    "sg:postcode":"35007",
    "sg:province":"Las Palmas",
    "wof:name":"Deutsche Bank S.a.e.",
    "wof:placetype":"venue"
},
  "geometry": {"coordinates":[-15.4312486649,28.1390209198],"type":"Point"}
}