{
  "type": "Feature",
  "properties": {
    "iso:country":"ES",
    "sg:address":"Calle de Ubitarte Kalea, 2",
    "sg:city":"Gernika-lumo",
    "sg:orig_category":"M\u00c9dicos: Estomatolog\u00cda",
    "sg:phone":"+34 946 25 76 47",
    "sg:postcode":"48300",
    "sg:province":"Vizcaya",
    "wof:name":"Solaguren Gabiola Ines",
    "wof:placetype":"venue"
},
  "geometry": {"coordinates":[-2.6787419319,43.311378479],"type":"Point"}
}