{
  "type": "Feature",
  "properties": {
    "iso:country":"ES",
    "sg:address":"Rua Ervedelo, 81",
    "sg:city":"Ourense",
    "sg:orig_category":"Alimentaci\u00d3n General (al Por Menor)",
    "sg:phone":"+34 988 22 76 49",
    "sg:postcode":"32002",
    "sg:province":"Ourense",
    "wof:name":"Barreal Gandara Camilo",
    "wof:placetype":"venue"
},
  "geometry": {"coordinates":[-7.8759298325,42.342048645],"type":"Point"}
}