{
  "type": "Feature",
  "properties": {
    "addr:full":"Av Madrid, 107 Barcelona Barcelona 08028",
    "addr:housenumber":"107",
    "addr:postcode":"08028",
    "addr:street":"Av Madrid",
    "iso:country":"ES",
    "sg:address":"Av Madrid, 107",
    "sg:city":"Barcelona",
    "sg:orig_category":"Iglesia Cat\u00d3lica",
    "sg:phone":"+34 933 39 85 79",
    "sg:postcode":"08028",
    "sg:province":"Barcelona",
    "wof:name":"Parroquia De Santa Tecla",
    "wof:placetype":"venue"
},
  "geometry": {"coordinates":[2.1281139851,41.3789176941],"type":"Point"}
}