{
  "type": "Feature",
  "properties": {
    "iso:country":"ES",
    "sg:address":"Avda Marques De Corbera, 31",
    "sg:city":"Madrid",
    "sg:orig_category":"Peluqueros: De Se\u00d1oras",
    "sg:phone":"+34 913 56 40 75",
    "sg:postcode":"28017",
    "sg:province":"Madrid",
    "wof:name":"Sevillano Peluqueros S.l.",
    "wof:placetype":"venue"
},
  "geometry": {"coordinates":[-3.6535201073,40.424823761],"type":"Point"}
}