{
  "type": "Feature",
  "properties": {
    "iso:country":"ES",
    "sg:address":"Ctra. Nacional 340, Km. 0074,0",
    "sg:city":"Benicassim",
    "sg:orig_category":"Internados & Ense\u00d1anza Privada",
    "sg:phone":"+34 964 39 85 12",
    "sg:postcode":"12560",
    "sg:province":"Castell\u00f3n",
    "wof:name":"Perales Valls Hipolito",
    "wof:placetype":"venue"
},
  "geometry": {"coordinates":[0.0457400009,40.0510292053],"type":"Point"}
}