{
  "type": "Feature",
  "properties": {
    "addr:full":"Bo. De Arriba, S/n Ballota Asturias 33158",
    "addr:housenumber":"s / n",
    "addr:postcode":"33158",
    "addr:street":"Arriba",
    "iso:country":"ES",
    "sg:address":"Bo. De Arriba, S/n",
    "sg:city":"Ballota",
    "sg:orig_category":"Sales (al Por Mayor)",
    "sg:phone":"+34 985 59 80 83",
    "sg:postcode":"33158",
    "sg:province":"Asturias",
    "wof:name":"Candano Arrojo Maria De Las Nieves",
    "wof:placetype":"venue"
},
  "geometry": {"coordinates":[-6.3312840462,43.551864624],"type":"Point"}
}