{
  "type": "Feature",
  "properties": {
    "iso:country":"ES",
    "sg:address":"Calle de Sebastian Elcano, 30",
    "sg:city":"Sevilla",
    "sg:orig_category":"Inform\u00c1tica, Ofim\u00c1tica (estudios, Asesor\u00cda, Ingenier\u00cda, Formaci\u00d3n)",
    "sg:phone":"+34 954 28 00 17",
    "sg:postcode":"41011",
    "sg:province":"Sevilla",
    "wof:name":"Jump Ordenadores Fl S.l.",
    "wof:placetype":"venue"
},
  "geometry": {"coordinates":[-5.9962120056,37.3744468689],"type":"Point"}
}