{
  "type": "Feature",
  "properties": {
    "addr:full":"Calle de Victoriano Bordonaba Gil, 9 Tudela Navarra 31500",
    "addr:housenumber":"9",
    "addr:postcode":"31500",
    "addr:street":"Calle De Victoriano Bordonaba Gil",
    "iso:country":"ES",
    "sg:address":"Calle de Victoriano Bordonaba Gil, 9",
    "sg:city":"Tudela",
    "sg:orig_category":"Bisuter\u00cda, Joyer\u00cda, Relojer\u00cda (al Por Menor)",
    "sg:phone":"+34 948 82 16 19",
    "sg:postcode":"31500",
    "sg:province":"Navarra",
    "wof:name":"Luis Y Laura Joyeros S.l.l.",
    "wof:placetype":"venue"
},
  "geometry": {"coordinates":[-1.6024609804,42.0532493591],"type":"Point"}
}