{
  "type": "Feature",
  "properties": {
    "iso:country":"ES",
    "sg:address":"Ctra Prats De Llu\u00c7anes, Km. 0003,6",
    "sg:city":"Sabadell",
    "sg:orig_category":"Cer\u00c1mica Art\u00cdstica Y Decorativa",
    "sg:phone":"+34 937 23 04 16",
    "sg:postcode":"08208",
    "sg:province":"Barcelona",
    "wof:name":"Duncan Bizcocho Y Decoracion S.l.",
    "wof:placetype":"venue"
},
  "geometry": {"coordinates":[2.1024479866,41.555431366],"type":"Point"}
}