{
  "type": "Feature",
  "properties": {
    "iso:country":"ES",
    "sg:address":"Calle de Francisco Silvela, 90",
    "sg:city":"Madrid",
    "sg:orig_category":"Psic\u00d3logos",
    "sg:phone":"+34 915 64 77 98",
    "sg:postcode":"28002",
    "sg:province":"Madrid",
    "wof:name":"Centro De Evaluacion Y Psicoterapia De Madrid",
    "wof:placetype":"venue"
},
  "geometry": {"coordinates":[-3.6777560711,40.4381523132],"type":"Point"}
}