{
  "type": "Feature",
  "properties": {
    "addr:full":"Calle de Conde De Halcon, 2 Sevilla Sevilla 41008",
    "addr:housenumber":"2",
    "addr:postcode":"41008",
    "addr:street":"Calle De Conde De Halcon",
    "iso:country":"ES",
    "sg:address":"Calle de Conde De Halcon, 2",
    "sg:city":"Sevilla",
    "sg:orig_category":"Alimentaci\u00d3n General (al Por Menor)",
    "sg:phone":"+34 954 35 93 67",
    "sg:postcode":"41008",
    "sg:province":"Sevilla",
    "wof:name":"Velarde Caro Francisco",
    "wof:placetype":"venue"
},
  "geometry": {"coordinates":[-5.9734978676,37.4006233215],"type":"Point"}
}