{
  "type": "Feature",
  "properties": {
    "addr:full":"Calle de Roque Barcia, 21 Huelva Huelva 21003",
    "addr:housenumber":"21",
    "addr:postcode":"21003",
    "addr:street":"Calle De Roque Barcia",
    "iso:country":"ES",
    "sg:address":"Calle de Roque Barcia, 21",
    "sg:city":"Huelva",
    "sg:orig_category":"Molduras, Junquillos, Listones Y Molduras Perforadas",
    "sg:phone":"+34 959 23 28 11",
    "sg:postcode":"21003",
    "sg:province":"Huelva",
    "wof:name":"Perez Velo Jose Maria",
    "wof:placetype":"venue"
},
  "geometry": {"coordinates":[-6.9368271828,37.2551078796],"type":"Point"}
}