{
  "type": "Feature",
  "properties": {
    "addr:full":"Calle de General Espartero, 14 Daimiel Ciudad Real 13250",
    "addr:housenumber":"14",
    "addr:postcode":"13250",
    "addr:street":"Calle De General Espartero",
    "iso:country":"ES",
    "sg:address":"Calle de General Espartero, 14",
    "sg:city":"Daimiel",
    "sg:orig_category":"Artes Gr\u00c1ficas, Artes Pl\u00c1sticas (curso)",
    "sg:phone":"+34 926 85 04 14",
    "sg:postcode":"13250",
    "sg:province":"Ciudad Real",
    "wof:name":"Itinerarte C.b.",
    "wof:placetype":"venue"
},
  "geometry": {"coordinates":[-3.6130588055,39.06798172],"type":"Point"}
}