{
  "type": "Feature",
  "properties": {
    "iso:country":"ES",
    "sg:address":"Calle de Juan Ramon Jimenez, 3",
    "sg:city":"Fuengirola",
    "sg:orig_category":"Institutos De Belleza",
    "sg:phone":"+34 952 59 35 06",
    "sg:postcode":"29640",
    "sg:province":"M\u00e1laga",
    "wof:name":"Elias  Maurizio",
    "wof:placetype":"venue"
},
  "geometry": {"coordinates":[-4.6209821701,36.5450363159],"type":"Point"}
}