{
  "type": "Feature",
  "properties": {
    "addr:full":"Plaz Irun De, 4 Donostia-san Sebastian Guip\u00f9zcoa 20011",
    "addr:postcode":"20011",
    "addr:street":"Plaz;De 4",
    "iso:country":"ES",
    "sg:address":"Plaz Irun De, 4",
    "sg:city":"Donostia-san Sebastian",
    "sg:orig_category":"Administradores De Bienes Y Delegados De Comunidades De Propietarios",
    "sg:phone":"+34 943 46 39 57",
    "sg:postcode":"20011",
    "sg:province":"Guip\u00f9zcoa",
    "wof:name":"Administraciones Carro-caballero, Sl",
    "wof:placetype":"venue"
},
  "geometry": {"coordinates":[-1.9794000387,43.3173789978],"type":"Point"}
}