{
  "type": "Feature",
  "properties": {
    "addr:full":"Avda Jablillo (el), 5 Costa Teguise Las Palmas 35509",
    "addr:housenumber":"5",
    "addr:postcode":"35509",
    "addr:street":"Avda Jablillo El",
    "iso:country":"ES",
    "sg:address":"Avda Jablillo (el), 5",
    "sg:city":"Costa Teguise",
    "sg:orig_category":"Bazares, Art\u00cdculos De Limpieza Y De Cocina (al Por Menor)",
    "sg:phone":"+34 928 59 11 44",
    "sg:postcode":"35509",
    "sg:province":"Las Palmas",
    "wof:name":"Al Lal El Mahi Amanan",
    "wof:placetype":"venue"
},
  "geometry": {"coordinates":[-13.4908666611,28.9956703186],"type":"Point"}
}