{
  "type": "Feature",
  "properties": {
    "iso:country":"ES",
    "sg:address":"Calle de Hospital, 30",
    "sg:city":"Valencia",
    "sg:orig_category":"Ropa Y Accesorios",
    "sg:phone":"+34 963 91 77 56",
    "sg:postcode":"46001",
    "sg:province":"Valencia",
    "wof:name":"Ramos Gascon Maria De Los Angeles",
    "wof:placetype":"venue"
},
  "geometry": {"coordinates":[-0.3829970062,39.4709701538],"type":"Point"}
}