{
  "type": "Feature",
  "properties": {
    "addr:full":"Avda Tecnica (de La), S/n Azuqueca Henares Guadalajara 19200",
    "addr:postcode":"19200",
    "addr:street":"Avda Tecnica De La S / N",
    "iso:country":"ES",
    "sg:address":"Avda Tecnica (de La), S/n",
    "sg:city":"Azuqueca Henares",
    "sg:orig_category":"Contenedores (mercanc\u00cdas)",
    "sg:phone":"+34 949 27 72 21",
    "sg:postcode":"19200",
    "sg:province":"Guadalajara",
    "wof:name":"Transportes Alcatrans S.l.",
    "wof:placetype":"venue"
},
  "geometry": {"coordinates":[-3.2643489838,40.5579986572],"type":"Point"}
}