{
  "type": "Feature",
  "properties": {
    "addr:full":"Calle de Celleruelo, 10 Pola De Siero Asturias 33510",
    "addr:housenumber":"10",
    "addr:postcode":"33510",
    "addr:street":"Calle De Celleruelo",
    "iso:country":"ES",
    "sg:address":"Calle de Celleruelo, 10",
    "sg:city":"Pola De Siero",
    "sg:orig_category":"Lencer\u00cda Femenina, Corseter\u00cda, Trajes De Ba\u00d1o (al Por Menor)",
    "sg:phone":"+34 985 72 16 04",
    "sg:postcode":"33510",
    "sg:province":"Asturias",
    "wof:name":"Garcia Gutierrez Maria Blanca",
    "wof:placetype":"venue"
},
  "geometry": {"coordinates":[-5.6620750427,43.3932418823],"type":"Point"}
}