{
  "type": "Feature",
  "properties": {
    "iso:country":"ES",
    "sg:address":"Avda Loring, 6",
    "sg:city":"Alacant",
    "sg:orig_category":"M\u00c9dicos: Cirug\u00cda General",
    "sg:phone":"+34 965 22 71 62",
    "sg:postcode":"03003",
    "sg:province":"Alicante",
    "wof:name":"Amaya Gallo Luciano Manuel",
    "wof:placetype":"venue"
},
  "geometry": {"coordinates":[-0.492759198,38.3382453918],"type":"Point"}
}