{
  "type": "Feature",
  "properties": {
    "iso:country":"ES",
    "sg:address":"Calle de Andres Cortina, 2",
    "sg:city":"Getxo",
    "sg:orig_category":"Decoraci\u00d3n: Instalaci\u00d3n Y Talleres",
    "sg:phone":"+34 944 91 08 87",
    "sg:postcode":"48990",
    "sg:province":"Vizcaya",
    "wof:name":"Jon Andoni Gerediaga Bilbao",
    "wof:placetype":"venue"
},
  "geometry": {"coordinates":[-3.0132331848,43.3521347046],"type":"Point"}
}