{
  "type": "Feature",
  "properties": {
    "addr:full":"Rua Vila De Noia, 62 Carballo A Coru\u00f1a 15100",
    "addr:housenumber":"62",
    "addr:postcode":"15100",
    "addr:street":"Rua Vila De Noia;Corun\u0303A",
    "iso:country":"ES",
    "sg:address":"Rua Vila De Noia, 62",
    "sg:city":"Carballo",
    "sg:orig_category":"Controles De Edificaci\u00d3n (construcci\u00d3n, Seguridad)",
    "sg:phone":"+34 981 75 55 42",
    "sg:postcode":"15100",
    "sg:province":"A Coru\u00f1a",
    "wof:name":"Villar Suarez Jose Antonio",
    "wof:placetype":"venue"
},
  "geometry": {"coordinates":[-8.6834392548,43.2178535461],"type":"Point"}
}