{
  "type": "Feature",
  "properties": {
    "iso:country":"ES",
    "sg:address":"Carrer de Sors, 25",
    "sg:city":"Barcelona",
    "sg:orig_category":"Alimentaci\u00d3n General (al Por Menor)",
    "sg:phone":"+34 932 13 05 34",
    "sg:postcode":"08024",
    "sg:province":"Barcelona",
    "wof:name":"Aparici Fabra Josep",
    "wof:placetype":"venue"
},
  "geometry": {"coordinates":[2.1583313942,41.4091949463],"type":"Point"}
}