{
  "type": "Feature",
  "properties": {
    "addr:full":"Calle de Silos, 1 Santaella C\u00f3rdoba 14546",
    "addr:housenumber":"1",
    "addr:postcode":"14546",
    "addr:street":"Calle De Silos;Co\u0301Rdoba",
    "iso:country":"ES",
    "sg:address":"Calle de Silos, 1",
    "sg:city":"Santaella",
    "sg:orig_category":"Contenedores (mercanc\u00cdas)",
    "sg:phone":"+34 957 31 31 50",
    "sg:postcode":"14546",
    "sg:province":"C\u00f3rdoba",
    "wof:name":"Transportes Jose Maria Sotelo Garcia S.l.",
    "wof:placetype":"venue"
},
  "geometry": {"coordinates":[-4.8432078362,37.5593490601],"type":"Point"}
}