{
  "type": "Feature",
  "properties": {
    "iso:country":"ES",
    "sg:address":"Lagar, S/n",
    "sg:city":"Alcazaren",
    "sg:orig_category":"Frutos Y Legumbres",
    "sg:phone":"+34 983 60 93 02",
    "sg:postcode":"47238",
    "sg:province":"Valladolid",
    "wof:name":"Horticolas Murillo S.l.",
    "wof:placetype":"venue"
},
  "geometry": {"coordinates":[-4.6726145744,41.3696670532],"type":"Point"}
}