{
  "type": "Feature",
  "properties": {
    "addr:full":"Carrer de Enric Granados, 99 Barcelona Barcelona 08008",
    "addr:housenumber":"99",
    "addr:postcode":"08008",
    "addr:street":"Carrer De Enric Granados",
    "iso:country":"ES",
    "sg:address":"Carrer de Enric Granados, 99",
    "sg:city":"Barcelona",
    "sg:orig_category":"Arquitectos",
    "sg:phone":"+34 932 38 53 38",
    "sg:postcode":"08008",
    "sg:province":"Barcelona",
    "wof:name":"Garcia Antunez Josep Lluis",
    "wof:placetype":"venue"
},
  "geometry": {"coordinates":[2.1557700634,41.3925819397],"type":"Point"}
}