{
  "type": "Feature",
  "properties": {
    "iso:country":"ES",
    "sg:address":"Calle de Doctor Mara\u00d1on, 11",
    "sg:city":"Mislata",
    "sg:orig_category":"Centros Empresariales",
    "sg:phone":"+34 963 13 44 20",
    "sg:postcode":"46920",
    "sg:province":"Valencia",
    "wof:name":"Tramoyeres Izquierdo Jose",
    "wof:placetype":"venue"
},
  "geometry": {"coordinates":[-0.4208920002,39.4727935791],"type":"Point"}
}