{
  "type": "Feature",
  "properties": {
    "iso:country":"ES",
    "sg:address":"Calle de Triana, 84",
    "sg:city":"Palmas De Gran Canaria",
    "sg:orig_category":"Ropa Para Se\u00d1oras (al Por Menor)",
    "sg:phone":"+34 928 36 94 17",
    "sg:postcode":"35002",
    "sg:province":"Las Palmas",
    "wof:name":"Summerfield S.a.",
    "wof:placetype":"venue"
},
  "geometry": {"coordinates":[-15.4163093567,28.106388092],"type":"Point"}
}