{
  "type": "Feature",
  "properties": {
    "iso:country":"ES",
    "sg:address":"Carr Alfons Xii, 6",
    "sg:city":"Badalona",
    "sg:orig_category":"Inmobiliaria (agencias)",
    "sg:phone":"+34 933 88 03 04",
    "sg:postcode":"08912",
    "sg:province":"Barcelona",
    "wof:name":"Fincas Rojas S.c.p.",
    "wof:placetype":"venue"
},
  "geometry": {"coordinates":[2.2435979843,41.4474639893],"type":"Point"}
}