{
  "type": "Feature",
  "properties": {
    "addr:full":"Carrer de Gallecs, 2 Mollet Valles Barcelona 08100",
    "addr:housenumber":"2",
    "addr:postcode":"08100",
    "addr:street":"Carrer De Gallecs",
    "iso:country":"ES",
    "sg:address":"Carrer de Gallecs, 2",
    "sg:city":"Mollet Valles",
    "sg:orig_category":"Sociedades, Compa\u00d1\u00cdas Aseguradoras",
    "sg:phone":"+34 935 70 55 33",
    "sg:postcode":"08100",
    "sg:province":"Barcelona",
    "wof:name":"Cercos Santin Vicens",
    "wof:placetype":"venue"
},
  "geometry": {"coordinates":[2.2109670639,41.5435066223],"type":"Point"}
}