{
  "type": "Feature",
  "properties": {
    "addr:full":"Avda Carlos I De, 18 Donostia-san Sebastian Guip\u00f9zcoa 20011",
    "addr:housenumber":"18",
    "addr:postcode":"20011",
    "addr:street":"Avda Carlos I De",
    "iso:country":"ES",
    "sg:address":"Avda Carlos I De, 18",
    "sg:city":"Donostia-san Sebastian",
    "sg:orig_category":"Peluqueros: De Se\u00d1oras",
    "sg:phone":"+34 943 46 31 70",
    "sg:postcode":"20011",
    "sg:province":"Guip\u00f9zcoa",
    "wof:name":"Bueno Martin Maria Teresa",
    "wof:placetype":"venue"
},
  "geometry": {"coordinates":[-1.9792259932,43.3042182922],"type":"Point"}
}