{
  "type": "Feature",
  "properties": {
    "addr:full":"Calle de Gabino Muriel, 1 Caceres C\u00e1ceres 10001",
    "addr:housenumber":"1",
    "addr:postcode":"10001",
    "addr:street":"Calle De Gabino Muriel;Ca\u0301Ceres",
    "iso:country":"ES",
    "sg:address":"Calle de Gabino Muriel, 1",
    "sg:city":"Caceres",
    "sg:orig_category":"Relojer\u00cda (al Por Menor, Reparaci\u00d3n)",
    "sg:phone":"+34 927 21 59 11",
    "sg:postcode":"10001",
    "sg:province":"C\u00e1ceres",
    "wof:name":"Gonzalez Teomiro Mariano",
    "wof:placetype":"venue"
},
  "geometry": {"coordinates":[-6.3798069954,39.4669380188],"type":"Point"}
}