{
  "type": "Feature",
  "properties": {
    "addr:full":"Pda Aguaoliva, S/n Vinaros Castell\u00f3n 12500",
    "addr:housenumber":"s / n",
    "addr:postcode":"12500",
    "iso:country":"ES",
    "sg:address":"Pda Aguaoliva, S/n",
    "sg:city":"Vinaros",
    "sg:orig_category":"Dise\u00d1o Industrial",
    "sg:phone":"+34 964 40 14 73",
    "sg:postcode":"12500",
    "sg:province":"Castell\u00f3n",
    "wof:name":"Hervas Gallego Maria Del Prado",
    "wof:placetype":"venue"
},
  "geometry": {"coordinates":[0.4749450088,40.4711990356],"type":"Point"}
}