{
  "type": "Feature",
  "properties": {
    "addr:full":"Plaz Espa\u00d1a, 3 Cabra C\u00f3rdoba 14940",
    "addr:housenumber":"3",
    "addr:postcode":"14940",
    "addr:street":"Plaz Espan\u0303A;Co\u0301Rdoba",
    "iso:country":"ES",
    "sg:address":"Plaz Espa\u00d1a, 3",
    "sg:city":"Cabra",
    "sg:orig_category":"Inmobiliaria (agencias)",
    "sg:phone":"+34 957 52 92 80",
    "sg:postcode":"14940",
    "sg:province":"C\u00f3rdoba",
    "wof:name":"Leader House Espa\u00f1a S.l.",
    "wof:placetype":"venue"
},
  "geometry": {"coordinates":[-4.4467329979,37.4725837708],"type":"Point"}
}