{
  "type": "Feature",
  "properties": {
    "iso:country":"ES",
    "sg:address":"Calle de Iglesia, 2",
    "sg:city":"Gondomar",
    "sg:orig_category":"Iglesia Cat\u00d3lica",
    "sg:phone":"+34 986 36 02 31",
    "sg:postcode":"36380",
    "sg:province":"Pontevedra",
    "wof:name":"Obispado Tui-vigo. Parroquia De Santa Maria De Vilaza",
    "wof:placetype":"venue"
},
  "geometry": {"coordinates":[-8.7577791214,42.1125106812],"type":"Point"}
}