{
  "type": "Feature",
  "properties": {
    "iso:country":"ES",
    "sg:address":"Calle de Alhamar, 25",
    "sg:city":"Granada",
    "sg:orig_category":"Inform\u00c1tica: Soportes De Informaci\u00d3n, Suministros & Accesorios",
    "sg:phone":"+34 958 25 39 50",
    "sg:postcode":"18005",
    "sg:province":"Granada",
    "wof:name":"Mecanograficas Granada S. C. L. Andaluza",
    "wof:placetype":"venue"
},
  "geometry": {"coordinates":[-3.6019668579,37.1689949036],"type":"Point"}
}