{
  "type": "Feature",
  "properties": {
    "iso:country":"ES",
    "sg:address":"Kale Barria, 44",
    "sg:city":"O\u00f1ati",
    "sg:orig_category":"Zapatos (al Por Menor)",
    "sg:phone":"+34 943 78 07 55",
    "sg:postcode":"20560",
    "sg:province":"Guip\u00f9zcoa",
    "wof:name":"Urcelay Pascual Felipe",
    "wof:placetype":"venue"
},
  "geometry": {"coordinates":[-2.4103929996,43.0312538147],"type":"Point"}
}