{
  "type": "Feature",
  "properties": {
    "iso:country":"ES",
    "sg:address":"Calle de Maldonado, 43",
    "sg:city":"Madrid",
    "sg:orig_category":"Centros Empresariales",
    "sg:phone":"+34 915 63 18 25",
    "sg:postcode":"28006",
    "sg:province":"Madrid",
    "wof:name":"Domenech Mans Jaime",
    "wof:placetype":"venue"
},
  "geometry": {"coordinates":[-3.6800079346,40.4338493347],"type":"Point"}
}