{
  "type": "Feature",
  "properties": {
    "addr:full":"Ctra. Madrid, Km. 0004,0 Alacant Alicante 03006",
    "addr:postcode":"03006",
    "addr:street":"Ctra. Madrid Km. 0004,0",
    "iso:country":"ES",
    "sg:address":"Ctra. Madrid, Km. 0004,0",
    "sg:city":"Alacant",
    "sg:orig_category":"Fabricaci\u00d3n, Importaci\u00d3n, Venta De Material De Telefon\u00cda, Peritelefon\u00cda",
    "sg:phone":"+34 965 11 32 41",
    "sg:postcode":"03006",
    "sg:province":"Alicante",
    "wof:name":"Telefonica Data Espa\u00d1a S.a.",
    "wof:placetype":"venue"
},
  "geometry": {"coordinates":[-0.4804739952,38.3440856934],"type":"Point"}
}