{
  "type": "Feature",
  "properties": {
    "iso:country":"ES",
    "sg:address":"Avda Al-nasir, 3",
    "sg:city":"Cordoba",
    "sg:orig_category":"Asesor\u00cdas Y Estudios Financieros",
    "sg:phone":"+34 957 34 00 80",
    "sg:postcode":"14006",
    "sg:province":"C\u00f3rdoba",
    "wof:name":"Crespo Priego Pedro",
    "wof:placetype":"venue"
},
  "geometry": {"coordinates":[-4.7746539116,37.895690918],"type":"Point"}
}