{
  "type": "Feature",
  "properties": {
    "iso:country":"ES",
    "sg:address":"Calle de Fray Ceferino, 26",
    "sg:city":"Oviedo",
    "sg:orig_category":"M\u00c9dicos: Medicina General Orientada A La Homeopat\u00cda",
    "sg:phone":"+34 985 20 83 58",
    "sg:postcode":"33001",
    "sg:province":"Asturias",
    "sg:website":"www.asturnat.com",
    "wof:name":"Guirado Aguirre Fernando",
    "wof:placetype":"venue"
},
  "geometry": {"coordinates":[-5.8504910469,43.3667869568],"type":"Point"}
}