{
  "type": "Feature",
  "properties": {
    "iso:country":"ES",
    "sg:address":"Ctra Murcia-alicante, Km. 0002,0",
    "sg:city":"Crevillent",
    "sg:orig_category":"Empresas De Carpinter\u00cda De Madera",
    "sg:phone":"+34 966 68 07 09",
    "sg:postcode":"03330",
    "sg:province":"Alicante",
    "wof:name":"Maig S.c.",
    "wof:placetype":"venue"
},
  "geometry": {"coordinates":[-0.8139619827,38.2384681702],"type":"Point"}
}