{
  "type": "Feature",
  "properties": {
    "addr:full":"Calle de Hacendita (la), 2 Dos Hermanas Sevilla 41700",
    "addr:housenumber":"2",
    "addr:postcode":"41700",
    "addr:street":"Calle De Hacendita La;Sevilla",
    "iso:country":"ES",
    "sg:address":"Calle de Hacendita (la), 2",
    "sg:city":"Dos Hermanas",
    "sg:orig_category":"Promotores Constructores",
    "sg:phone":"+34 955 67 61 80",
    "sg:postcode":"41700",
    "sg:province":"Sevilla",
    "wof:name":"Reyean S.l.",
    "wof:placetype":"venue"
},
  "geometry": {"coordinates":[-5.9265489578,37.2841644287],"type":"Point"}
}