{
  "type": "Feature",
  "properties": {
    "iso:country":"ES",
    "sg:address":"Calle de Rosa Seminario, S/n",
    "sg:city":"Doneztebe",
    "sg:orig_category":"Muebles, Minoristas",
    "sg:phone":"+34 948 45 02 58",
    "sg:postcode":"31740",
    "sg:province":"Navarra",
    "wof:name":"Tellechea Indacochea Cipriano Francisco",
    "wof:placetype":"venue"
},
  "geometry": {"coordinates":[-1.6657061577,43.1336784363],"type":"Point"}
}