{
  "type": "Feature",
  "properties": {
    "addr:full":"Calle de Danok Bat, 2 Portugalete Vizcaya 48920",
    "addr:housenumber":"bat 2",
    "addr:postcode":"48920",
    "addr:street":"Calle De Danok",
    "iso:country":"ES",
    "sg:address":"Calle de Danok Bat, 2",
    "sg:city":"Portugalete",
    "sg:orig_category":"Tapicer\u00cdas",
    "sg:phone":"+34 944 62 87 56",
    "sg:postcode":"48920",
    "sg:province":"Vizcaya",
    "wof:name":"Jose Antonio Lopez Gonzalez",
    "wof:placetype":"venue"
},
  "geometry": {"coordinates":[-3.0195610523,43.3227577209],"type":"Point"}
}