{
  "type": "Feature",
  "properties": {
    "iso:country":"ES",
    "sg:address":"Carrer de Vilanova, 12",
    "sg:city":"Manresa",
    "sg:orig_category":"Art\u00cdculos De Regalo (al Por Menor)",
    "sg:phone":"+34 938 76 84 35",
    "sg:postcode":"08241",
    "sg:province":"Barcelona",
    "wof:name":"Ruiz Ca\u00f1adas Maria Carme",
    "wof:placetype":"venue"
},
  "geometry": {"coordinates":[1.8241369724,41.7235679626],"type":"Point"}
}