{
  "type": "Feature",
  "properties": {
    "addr:full":"Avda Virgen Del Rocio, 1 San Pedro Alcantara M\u00e1laga 29670",
    "addr:housenumber":"1",
    "addr:postcode":"29670",
    "addr:street":"Avda Virgen Del Rocio",
    "iso:country":"ES",
    "sg:address":"Avda Virgen Del Rocio, 1",
    "sg:city":"San Pedro Alcantara",
    "sg:orig_category":"Edici\u00d3n De Diarios, Revistas, Boletines",
    "sg:phone":"+34 952 78 97 15",
    "sg:postcode":"29670",
    "sg:province":"M\u00e1laga",
    "wof:name":"Benitez Oriola Carmen",
    "wof:placetype":"venue"
},
  "geometry": {"coordinates":[-4.9953122139,36.4834442139],"type":"Point"}
}