{
  "type": "Feature",
  "properties": {
    "iso:country":"ES",
    "sg:address":"Plaz Santa Rita, 7",
    "sg:city":"Almeria",
    "sg:orig_category":"Aud\u00cdfonos",
    "sg:phone":"+34 950 27 02 20",
    "sg:postcode":"04004",
    "sg:province":"Almer\u00eda",
    "wof:name":"Optica Santa Rita S.c.a.",
    "wof:placetype":"venue"
},
  "geometry": {"coordinates":[-2.4608390331,36.8422698975],"type":"Point"}
}