{
  "type": "Feature",
  "properties": {
    "iso:country":"ES",
    "sg:address":"Calle de Principe (del), 20",
    "sg:city":"Aranjuez",
    "sg:orig_category":"M\u00c9dicos: Pediatr\u00cda. Enfermedades De Los Ni\u00d1os",
    "sg:phone":"+34 918 91 18 60",
    "sg:postcode":"28300",
    "sg:province":"Madrid",
    "wof:name":"Marin Rodriguez Alejandro",
    "wof:placetype":"venue"
},
  "geometry": {"coordinates":[-3.6008639336,40.0354728699],"type":"Point"}
}