{
  "type": "Feature",
  "properties": {
    "iso:country":"ES",
    "sg:address":"Plaz General Prim, 16",
    "sg:city":"Bailen",
    "sg:orig_category":"Inmobiliaria (agencias)",
    "sg:phone":"+34 953 67 80 70",
    "sg:postcode":"23710",
    "sg:province":"Ja\u00e9n",
    "wof:name":"Martinez Perez Angela",
    "wof:placetype":"venue"
},
  "geometry": {"coordinates":[-3.7843859196,38.0936660767],"type":"Point"}
}