{
  "type": "Feature",
  "properties": {
    "addr:full":"Calle de San Francisco, 14 Cadiz C\u00e1diz 11004",
    "addr:housenumber":"14",
    "addr:postcode":"11004",
    "addr:street":"Calle De San Francisco",
    "iso:country":"ES",
    "sg:address":"Calle de San Francisco, 14",
    "sg:city":"Cadiz",
    "sg:orig_category":"Fabricaci\u00d3n De Productos Textiles Sin Tejer",
    "sg:phone":"+34 956 22 20 02",
    "sg:postcode":"11004",
    "sg:province":"C\u00e1diz",
    "wof:name":"Macias Gonzalez Ana",
    "wof:placetype":"venue"
},
  "geometry": {"coordinates":[-6.2948131561,36.5336532593],"type":"Point"}
}