{
  "type": "Feature",
  "properties": {
    "iso:country":"ES",
    "sg:address":"Avda Murcia (de), S/n",
    "sg:city":"Jumilla",
    "sg:orig_category":"Agentes, Concesionarios Y Sucursales De Veh\u00cdculos",
    "sg:phone":"+34 968 78 00 57",
    "sg:postcode":"30520",
    "sg:province":"Murcia",
    "wof:name":"Simon Moreno Jose Maria",
    "wof:placetype":"venue"
},
  "geometry": {"coordinates":[-1.3183139563,38.4740791321],"type":"Point"}
}