{
  "type": "Feature",
  "properties": {
    "iso:country":"ES",
    "sg:address":"Carr Trencall (del), 28",
    "sg:city":"Lliria",
    "sg:orig_category":"Promotores Constructores",
    "sg:phone":"+34 962 79 27 04",
    "sg:postcode":"46160",
    "sg:province":"Valencia",
    "wof:name":"Garfasa S.l.",
    "wof:placetype":"venue"
},
  "geometry": {"coordinates":[-0.5913323164,39.6249580383],"type":"Point"}
}