{
  "type": "Feature",
  "properties": {
    "addr:full":"Calle de Povedilla, 10 Madrid Madrid 28009",
    "addr:housenumber":"10",
    "addr:postcode":"madrid;28009",
    "addr:street":"Calle De Povedilla",
    "iso:country":"ES",
    "sg:address":"Calle de Povedilla, 10",
    "sg:city":"Madrid",
    "sg:orig_category":"Peluqueros: De Se\u00d1oras",
    "sg:phone":"+34 915 04 61 19",
    "sg:postcode":"28009",
    "sg:province":"Madrid",
    "wof:name":"Izquierdo Fontecha Sara",
    "wof:placetype":"venue"
},
  "geometry": {"coordinates":[-3.6703100204,40.4239196777],"type":"Point"}
}