{
  "type": "Feature",
  "properties": {
    "iso:country":"ES",
    "sg:address":"Avda Primero De Mayo, 16",
    "sg:city":"Valle Trapaga",
    "sg:orig_category":"Mercer\u00cda, Lencer\u00cda (al Por Menor)",
    "sg:phone":"+34 944 92 18 54",
    "sg:postcode":"48510",
    "sg:province":"Vizcaya",
    "wof:name":"Merceria Celia (celia Torre)",
    "wof:placetype":"venue"
},
  "geometry": {"coordinates":[-3.0355210304,43.3028564453],"type":"Point"}
}