{
  "type": "Feature",
  "properties": {
    "addr:full":"Avda Primero De Mayo, 1 Palmas De Gran Canaria Las Palmas 35002",
    "addr:housenumber":"1",
    "addr:postcode":"35002",
    "addr:street":"Avda Primero De Mayo",
    "iso:country":"ES",
    "sg:address":"Avda Primero De Mayo, 1",
    "sg:city":"Palmas De Gran Canaria",
    "sg:orig_category":"Farmacias",
    "sg:phone":"+34 928 36 89 09",
    "sg:postcode":"35002",
    "sg:province":"Las Palmas",
    "wof:name":"Dominguez Trujillo Juan Carlos",
    "wof:placetype":"venue"
},
  "geometry": {"coordinates":[-15.4176597595,28.1021747589],"type":"Point"}
}