{
  "type": "Feature",
  "properties": {
    "addr:full":"Calle de San Felix, 29 Castellon Castell\u00f3n 12004",
    "addr:housenumber":"29",
    "addr:postcode":"12004",
    "addr:street":"Calle De San Felix",
    "iso:country":"ES",
    "sg:address":"Calle de San Felix, 29",
    "sg:city":"Castellon",
    "sg:orig_category":"Inform\u00c1tica (estudios, Servicios, Asesor\u00cda, Formaci\u00d3n)",
    "sg:phone":"+34 964 25 55 03",
    "sg:postcode":"12004",
    "sg:province":"Castell\u00f3n",
    "wof:name":"Distribucion De Ordenadores Y Software S. A.",
    "wof:placetype":"venue"
},
  "geometry": {"coordinates":[-0.0368059985,39.9893302917],"type":"Point"}
}