{
  "type": "Feature",
  "properties": {
    "addr:full":"Calle de Foncalada, 7 Oviedo Asturias 33002",
    "addr:housenumber":"7",
    "addr:postcode":"33002",
    "addr:street":"Calle De Foncalada",
    "iso:country":"ES",
    "sg:address":"Calle de Foncalada, 7",
    "sg:city":"Oviedo",
    "sg:orig_category":"Abogados",
    "sg:phone":"+34 985 21 20 85",
    "sg:postcode":"33002",
    "sg:province":"Asturias",
    "wof:name":"Menendez Diaz Juan",
    "wof:placetype":"venue"
},
  "geometry": {"coordinates":[-5.8468332291,43.3648719788],"type":"Point"}
}