{
  "type": "Feature",
  "properties": {
    "addr:full":"Calle de Nuestra Se\u00d1ora Del Carmen, 23 Prado Del Rey C\u00e1diz 11660",
    "addr:housenumber":"23",
    "addr:postcode":"11660",
    "addr:street":"Calle De Nuestra Sen\u0303Ora Del Carmen",
    "iso:country":"ES",
    "sg:address":"Calle de Nuestra Se\u00d1ora Del Carmen, 23",
    "sg:city":"Prado Del Rey",
    "sg:orig_category":"Cueros Y Pieles (al Por Mayor)",
    "sg:phone":"+34 956 72 32 27",
    "sg:postcode":"11660",
    "sg:province":"C\u00e1diz",
    "wof:name":"Perez Pi\u00f1a Manuel",
    "wof:placetype":"venue"
},
  "geometry": {"coordinates":[-5.5588970184,36.7873535156],"type":"Point"}
}