{
  "type": "Feature",
  "properties": {
    "iso:country":"ES",
    "sg:address":"Calle de Maria Teresa Saenz De Heredia, 11",
    "sg:city":"Madrid",
    "sg:orig_category":"Institutos De Belleza",
    "sg:phone":"+34 913 55 71 62",
    "sg:postcode":"28017",
    "sg:province":"Madrid",
    "wof:name":"Carre\u00f1o Cardenas Leti",
    "wof:placetype":"venue"
},
  "geometry": {"coordinates":[-3.654433012,40.4223327637],"type":"Point"}
}