{
  "type": "Feature",
  "properties": {
    "iso:country":"ES",
    "sg:address":"Calle de Mariano Ayala, 1",
    "sg:city":"Bollullos Par Condado",
    "sg:orig_category":"Abogados",
    "sg:phone":"+34 959 40 82 39",
    "sg:postcode":"21710",
    "sg:province":"Huelva",
    "wof:name":"Carrasco Espina Gema",
    "wof:placetype":"venue"
},
  "geometry": {"coordinates":[-6.5344109535,37.3381958008],"type":"Point"}
}