{
  "type": "Feature",
  "properties": {
    "iso:country":"ES",
    "sg:address":"Calle de Jabonerias, 7",
    "sg:city":"Cartagena",
    "sg:classifiers":[
        {
            "category":"Arts & Performance",
            "subcategory":"Art Gallery",
            "type":"Entertainment"
        }
    ],
    "sg:phone":"+34 968 50 31 97",
    "sg:postcode":"30201",
    "sg:province":"Murcia",
    "sg:tags":[
        "arte",
        "de",
        "galer\u00cdas"
    ],
    "wof:name":"Matran Bea Encarnacion",
    "wof:placetype":"venue"
},
  "geometry": {"coordinates":[-0.9880759716,37.6032104492],"type":"Point"}
}