{
  "type": "Feature",
  "properties": {
    "iso:country":"ES",
    "sg:address":"Av General Luque, 314",
    "sg:city":"Inca",
    "sg:orig_category":"Electrodom\u00c9sticos (al Por Menor)",
    "sg:phone":"+34 971 50 55 79",
    "sg:postcode":"07300",
    "sg:province":"Islas Baleares",
    "sg:website":"www.miro.es",
    "wof:name":"Establecimientos Miro S.l.",
    "wof:placetype":"venue"
},
  "geometry": {"coordinates":[2.9050250053,39.7150993347],"type":"Point"}
}