{
  "type": "Feature",
  "properties": {
    "addr:full":"Calle de Virgen Del Pilar, 3 Estacion Madrid 28400",
    "addr:housenumber":"3 estacion",
    "addr:postcode":"28400",
    "addr:street":"Calle De Virgen Del Pilar",
    "iso:country":"ES",
    "sg:address":"Calle de Virgen Del Pilar, 3",
    "sg:city":"Estacion",
    "sg:orig_category":"Venta, Alquiler De Toldos",
    "sg:phone":"+34 918 50 48 89",
    "sg:postcode":"28400",
    "sg:province":"Madrid",
    "sg:website":"www.construsider.com",
    "wof:name":"Construsider S.a.",
    "wof:placetype":"venue"
},
  "geometry": {"coordinates":[-3.9919650555,40.6455612183],"type":"Point"}
}