{
  "type": "Feature",
  "properties": {
    "addr:full":"Cuesta Correa, 116 Elviria M\u00e1laga 29604",
    "addr:housenumber":"116",
    "addr:postcode":"29604",
    "addr:street":"Cuesta Correa;Ma\u0301Laga",
    "iso:country":"ES",
    "sg:address":"Cuesta Correa, 116",
    "sg:city":"Elviria",
    "sg:orig_category":"Promotores Constructores",
    "sg:phone":"+34 952 83 98 20",
    "sg:postcode":"29604",
    "sg:province":"M\u00e1laga",
    "wof:name":"Snab Montemar S.l.",
    "wof:placetype":"venue"
},
  "geometry": {"coordinates":[-4.7747840881,36.4966812134],"type":"Point"}
}