{
  "type": "Feature",
  "properties": {
    "iso:country":"ES",
    "sg:address":"Calle de Iglesia, 11",
    "sg:city":"Motilla Palancar",
    "sg:orig_category":"Contenedores (mercanc\u00cdas)",
    "sg:phone":"+34 969 33 12 23",
    "sg:postcode":"16200",
    "sg:province":"Cuenca",
    "wof:name":"Maranpil S.l.",
    "wof:placetype":"venue"
},
  "geometry": {"coordinates":[-1.9092589617,39.5599594116],"type":"Point"}
}