{
  "type": "Feature",
  "properties": {
    "addr:full":"Plaz Constitucion (de La), S/n Alhama Murcia Murcia 30840",
    "addr:housenumber":"s",
    "addr:postcode":"30840",
    "addr:street":"/ N Alhama",
    "iso:country":"ES",
    "sg:address":"Plaz Constitucion (de La), S/n",
    "sg:city":"Alhama Murcia",
    "sg:orig_category":"Molduras, Junquillos, Listones Y Molduras Perforadas",
    "sg:phone":"+34 968 63 05 89",
    "sg:postcode":"30840",
    "sg:province":"Murcia",
    "wof:name":"Provencio Pe\u00f1a Bartolome",
    "wof:placetype":"venue"
},
  "geometry": {"coordinates":[-1.4241490364,37.8507995605],"type":"Point"}
}