{
  "type": "Feature",
  "properties": {
    "addr:full":"Avda Universidad, 11 Leganes Madrid 28911",
    "addr:housenumber":"11",
    "addr:postcode":"28911",
    "addr:street":"Avda Universidad",
    "iso:country":"ES",
    "sg:address":"Avda Universidad, 11",
    "sg:city":"Leganes",
    "sg:orig_category":"Tintes (fabricaci\u00d3n, Al Por Mayor)",
    "sg:phone":"+34 916 93 67 50",
    "sg:postcode":"28911",
    "sg:province":"Madrid",
    "wof:name":"Prada Martin S.l.",
    "wof:placetype":"venue"
},
  "geometry": {"coordinates":[-3.7640850544,40.3298149109],"type":"Point"}
}