{
  "type": "Feature",
  "properties": {
    "addr:full":"Pase Zorrilla, 348 Valladolid Valladolid 47008",
    "addr:housenumber":"348",
    "addr:postcode":"47008",
    "addr:street":"Zorrilla",
    "iso:country":"ES",
    "sg:address":"Pase Zorrilla, 348",
    "sg:city":"Valladolid",
    "sg:orig_category":"Supermercados Y Hipermercados",
    "sg:phone":"+34 983 24 58 91",
    "sg:postcode":"47008",
    "sg:province":"Valladolid",
    "wof:name":"Distribuciones Froiz S.a.",
    "wof:placetype":"venue"
},
  "geometry": {"coordinates":[-4.7484531403,41.6187019348],"type":"Point"}
}