{
  "type": "Feature",
  "properties": {
    "iso:country":"ES",
    "sg:address":"Calle de Serrana, S/n",
    "sg:city":"Dos Hermanas",
    "sg:orig_category":"Ense\u00d1anza, Formaci\u00d3n Profesional: Aprendizaje",
    "sg:phone":"+34 955 66 43 20",
    "sg:postcode":"41700",
    "sg:province":"Sevilla",
    "wof:name":"Patronato Municipal De Deportes",
    "wof:placetype":"venue"
},
  "geometry": {"coordinates":[-5.9138636589,37.2722091675],"type":"Point"}
}