{
  "type": "Feature",
  "properties": {
    "iso:country":"ES",
    "sg:address":"Calle de Laguna, 12",
    "sg:city":"Conil De La Frontera",
    "sg:orig_category":"Cajas De Ahorro",
    "sg:phone":"+34 956 44 03 86",
    "sg:postcode":"11140",
    "sg:province":"C\u00e1diz",
    "wof:name":"Caja San Fernando De Sevilla Y Jerez",
    "wof:placetype":"venue"
},
  "geometry": {"coordinates":[-6.0871338844,36.2782669067],"type":"Point"}
}