{
  "type": "Feature",
  "properties": {
    "addr:full":"Calle de Enrique De Labrit, 56 Sang\u00fcesa Navarra 31400",
    "addr:housenumber":"56",
    "addr:postcode":"31400",
    "addr:street":"Calle De Enrique De Labrit",
    "iso:country":"ES",
    "sg:address":"Calle de Enrique De Labrit, 56",
    "sg:city":"Sang\u00fcesa",
    "sg:orig_category":"Clases De M\u00dasica Y Canto",
    "sg:phone":"+34 948 87 11 91",
    "sg:postcode":"31400",
    "sg:province":"Navarra",
    "wof:name":"Escuela De Musica Juan Frances Iribarren",
    "wof:placetype":"venue"
},
  "geometry": {"coordinates":[-1.2833839655,42.5732536316],"type":"Point"}
}