{
  "type": "Feature",
  "properties": {
    "addr:full":"Ctra Llerena-utrera, Km. 0134,2 Carmona Sevilla 41410",
    "addr:postcode":"41410",
    "addr:street":"Ctra Llerena-Utrera Km. 0134,2",
    "iso:country":"ES",
    "sg:address":"Ctra Llerena-utrera, Km. 0134,2",
    "sg:city":"Carmona",
    "sg:orig_category":"Agentes, Concesionarios Y Sucursales De Camiones Y Veh\u00cdculos Industriales",
    "sg:phone":"+34 954 19 17 91",
    "sg:postcode":"41410",
    "sg:province":"Sevilla",
    "wof:name":"Turismos Y Camiones Del Sur S.l.",
    "wof:placetype":"venue"
},
  "geometry": {"coordinates":[-5.6433792114,37.4708709717],"type":"Point"}
}