{
  "type": "Feature",
  "properties": {
    "iso:country":"ES",
    "sg:address":"Calle de Bego\u00d1ako Andra Mari, 14",
    "sg:city":"Arizgoiti",
    "sg:orig_category":"Comercio De Cuadros, L\u00c1minas Y Reproducciones De Obras De Arte",
    "sg:phone":"+34 944 40 13 50",
    "sg:postcode":"48970",
    "sg:province":"Vizcaya",
    "wof:name":"Gallery Enmarcaciones S. L.",
    "wof:placetype":"venue"
},
  "geometry": {"coordinates":[-2.8864252567,43.2365570068],"type":"Point"}
}