{
  "type": "Feature",
  "properties": {
    "addr:full":"Kardaberaz Kalea, 49 Hernani Guip\u00f9zcoa 20120",
    "addr:housenumber":"49",
    "addr:postcode":"20120",
    "addr:street":"Kardaberaz Kalea;Guipu\u0300Zcoa",
    "iso:country":"ES",
    "sg:address":"Kardaberaz Kalea, 49",
    "sg:city":"Hernani",
    "sg:orig_category":"Alumbrados",
    "sg:phone":"+34 943 55 70 90",
    "sg:postcode":"20120",
    "sg:province":"Guip\u00f9zcoa",
    "wof:name":"Irigoyen Irizabal Jose Manuel",
    "wof:placetype":"venue"
},
  "geometry": {"coordinates":[-1.9739220142,43.2666244507],"type":"Point"}
}