{
  "type": "Feature",
  "properties": {
    "addr:full":"Carrer de Corominas, 25 Hospitalet Llobregat Barcelona 08902",
    "addr:housenumber":"25",
    "addr:postcode":"08902",
    "addr:street":"Carrer De Corominas",
    "iso:country":"ES",
    "sg:address":"Carrer de Corominas, 25",
    "sg:city":"Hospitalet Llobregat",
    "sg:orig_category":"Librer\u00cdas",
    "sg:phone":"+34 934 32 20 82",
    "sg:postcode":"08902",
    "sg:province":"Barcelona",
    "wof:name":"Comercial Distribuidora Magazine S. A.",
    "wof:placetype":"venue"
},
  "geometry": {"coordinates":[2.1207399368,41.3668365479],"type":"Point"}
}