{
  "type": "Feature",
  "properties": {
    "iso:country":"ES",
    "sg:address":"Carrer de Can Pantiquet, 24",
    "sg:city":"Mollet Valles",
    "sg:orig_category":"Promotores Constructores",
    "sg:phone":"+34 935 79 46 76",
    "sg:postcode":"08100",
    "sg:province":"Barcelona",
    "wof:name":"El Mon Del Gref I La Cuina",
    "wof:placetype":"venue"
},
  "geometry": {"coordinates":[2.2184898853,41.5442733765],"type":"Point"}
}