{
  "type": "Feature",
  "properties": {
    "addr:full":"Avda Primero De Mayo, 12 Puertollano Ciudad Real 13500",
    "addr:housenumber":"12",
    "addr:postcode":"13500",
    "addr:street":"Avda Primero De Mayo",
    "iso:country":"ES",
    "sg:address":"Avda Primero De Mayo, 12",
    "sg:city":"Puertollano",
    "sg:orig_category":"Doctores En Medicina",
    "sg:phone":"+34 926 43 14 49",
    "sg:postcode":"13500",
    "sg:province":"Ciudad Real",
    "wof:name":"Mu\u00f1oz Mata Juan Luis",
    "wof:placetype":"venue"
},
  "geometry": {"coordinates":[-4.1058588028,38.6857795715],"type":"Point"}
}