{
  "type": "Feature",
  "properties": {
    "addr:full":"Juan Gisasola Kalea, 12 Eibar Guip\u00f9zcoa 20600",
    "addr:housenumber":"12",
    "addr:postcode":"20600",
    "addr:street":"Juan Gisasola Kalea;Guipu\u0300Zcoa",
    "iso:country":"ES",
    "sg:address":"Juan Gisasola Kalea, 12",
    "sg:city":"Eibar",
    "sg:orig_category":"Tintes (fabricaci\u00d3n, Al Por Mayor)",
    "sg:phone":"+34 943 20 23 64",
    "sg:postcode":"20600",
    "sg:province":"Guip\u00f9zcoa",
    "wof:name":"Cuadrado Callejo Manuel",
    "wof:placetype":"venue"
},
  "geometry": {"coordinates":[-2.4717280865,43.1819000244],"type":"Point"}
}