{
  "type": "Feature",
  "properties": {
    "addr:full":"Carrer de Tortosa, 77 Terrassa Barcelona 08227",
    "addr:housenumber":"77",
    "addr:postcode":"08227",
    "addr:street":"Carrer De Tortosa",
    "iso:country":"ES",
    "sg:address":"Carrer de Tortosa, 77",
    "sg:city":"Terrassa",
    "sg:orig_category":"Reposter\u00cdas",
    "sg:phone":"+34 937 31 08 03",
    "sg:postcode":"08227",
    "sg:province":"Barcelona",
    "wof:name":"Forn Santa Llucia S.l.",
    "wof:placetype":"venue"
},
  "geometry": {"coordinates":[2.0379869938,41.5741271973],"type":"Point"}
}