{
  "type": "Feature",
  "properties": {
    "addr:full":"Calle de Francisco Cano Fontecha, 13 Tobarra Albacete 02500",
    "addr:housenumber":"13",
    "addr:postcode":"02500",
    "addr:street":"Calle De Francisco Cano Fontecha",
    "iso:country":"ES",
    "sg:address":"Calle de Francisco Cano Fontecha, 13",
    "sg:city":"Tobarra",
    "sg:orig_category":"Reposter\u00cdas",
    "sg:phone":"+34 967 32 53 64",
    "sg:postcode":"02500",
    "sg:province":"Albacete",
    "wof:name":"Panaderia Alcaraz S.l.",
    "wof:placetype":"venue"
},
  "geometry": {"coordinates":[-1.6868979931,38.5937767029],"type":"Point"}
}