{
  "type": "Feature",
  "properties": {
    "iso:country":"ES",
    "sg:address":"Calle de Jorge Juan, 82",
    "sg:city":"Madrid",
    "sg:orig_category":"Asesor\u00cda Sobre Comunicaci\u00d3n De Empresas",
    "sg:phone":"+34 915 76 54 22",
    "sg:postcode":"28009",
    "sg:province":"Madrid",
    "wof:name":"J.dos Estudios De Mercado S.l.",
    "wof:placetype":"venue"
},
  "geometry": {"coordinates":[-3.6753139496,40.423210144],"type":"Point"}
}