{
  "type": "Feature",
  "properties": {
    "iso:country":"ES",
    "sg:address":"Calle de Garcia Moreno, 19",
    "sg:city":"Viator",
    "sg:orig_category":"Promotores Constructores",
    "sg:phone":"+34 950 30 50 97",
    "sg:postcode":"04240",
    "sg:province":"Almer\u00eda",
    "wof:name":"Grupo Empresarial De Obras Civiles S.l.",
    "wof:placetype":"venue"
},
  "geometry": {"coordinates":[-2.4286503792,36.8907852173],"type":"Point"}
}