{
  "type": "Feature",
  "properties": {
    "iso:country":"ES",
    "sg:address":"Ctra Alicante, 33",
    "sg:city":"Esparragal",
    "sg:orig_category":"Aguas (distribuci\u00d3n, Servicios)",
    "sg:phone":"+34 968 85 35 26",
    "sg:postcode":"30163",
    "sg:province":"Murcia",
    "wof:name":"Cano Belmonte Antonio",
    "wof:placetype":"venue"
},
  "geometry": {"coordinates":[-1.0834419727,38.0496711731],"type":"Point"}
}