{
  "type": "Feature",
  "properties": {
    "iso:country":"ES",
    "sg:address":"Carrer de Riera, 5",
    "sg:city":"Palma",
    "sg:orig_category":"Empleado Administrativo",
    "sg:phone":"+34 971 72 08 26",
    "sg:postcode":"07003",
    "sg:province":"Islas Baleares",
    "wof:name":"Escandell Forteza Maria Del Carmen",
    "wof:placetype":"venue"
},
  "geometry": {"coordinates":[2.6505579948,39.5720405579],"type":"Point"}
}