{
  "type": "Feature",
  "properties": {
    "iso:country":"ES",
    "sg:address":"G.v. Lopez De Haro D. Diego, 60",
    "sg:city":"Bilbao",
    "sg:orig_category":"Inmobiliaria (agencias)",
    "sg:phone":"+34 944 42 48 31",
    "sg:postcode":"48011",
    "sg:province":"Vizcaya",
    "wof:name":"Goimendi 86 S.l.",
    "wof:placetype":"venue"
},
  "geometry": {"coordinates":[-2.9398550987,43.2642173767],"type":"Point"}
}