{
  "type": "Feature",
  "properties": {
    "addr:full":"Avda Espa\u00d1a (de), 86 Dos Hermanas Sevilla 41700",
    "addr:housenumber":"86",
    "addr:postcode":"41700",
    "addr:street":"Avda Espan\u0303A De",
    "iso:country":"ES",
    "sg:address":"Avda Espa\u00d1a (de), 86",
    "sg:city":"Dos Hermanas",
    "sg:orig_category":"Negocio De Materiales De Construcci\u00d3n",
    "sg:phone":"+34 955 66 10 08",
    "sg:postcode":"41700",
    "sg:province":"Sevilla",
    "wof:name":"Palomo Rodriguez Maria Jesus",
    "wof:placetype":"venue"
},
  "geometry": {"coordinates":[-5.9146308899,37.2830352783],"type":"Point"}
}