{
  "type": "Feature",
  "properties": {
    "addr:full":"Calle de Titos, 1 Burgos Burgos 09007",
    "addr:housenumber":"1",
    "addr:postcode":"09007",
    "addr:street":"Calle De Titos",
    "iso:country":"ES",
    "sg:address":"Calle de Titos, 1",
    "sg:city":"Burgos",
    "sg:orig_category":"Peluquer\u00cdas",
    "sg:phone":"+34 947 22 67 62",
    "sg:postcode":"09007",
    "sg:province":"Burgos",
    "sg:website":"www.paginasamarillas.es",
    "wof:name":"Garcia Barbeito S.c.",
    "wof:placetype":"venue"
},
  "geometry": {"coordinates":[-3.6495990753,42.344959259],"type":"Point"}
}