{
  "type": "Feature",
  "properties": {
    "addr:full":"Plaz Espa\u00d1a, 1 Aguilas Murcia 30880",
    "addr:housenumber":"1",
    "addr:postcode":"30880",
    "addr:street":"Plaz Espan\u0303A",
    "iso:country":"ES",
    "sg:address":"Plaz Espa\u00d1a, 1",
    "sg:city":"Aguilas",
    "sg:orig_category":"Asesor\u00cda Fiscal Y Jur\u00cddica",
    "sg:phone":"+34 968 44 80 56",
    "sg:postcode":"30880",
    "sg:province":"Murcia",
    "wof:name":"Aguilas Habitat S.l",
    "wof:placetype":"venue"
},
  "geometry": {"coordinates":[-1.5789994001,37.478969574],"type":"Point"}
}