{
  "type": "Feature",
  "properties": {
    "addr:full":"Ctra General Mao - Ciutadella, Km. 0039,0 Tudons Islas Baleares 07760",
    "addr:postcode":"07760",
    "addr:street":"Ctra General Mao Ciutadella Km. 0039,0 Tudons",
    "iso:country":"ES",
    "sg:address":"Ctra General Mao - Ciutadella, Km. 0039,0",
    "sg:city":"Tudons",
    "sg:orig_category":"Producci\u00d3n, Venta De Productos De Agricultura Biol\u00d3gica",
    "sg:phone":"+34 971 18 81 09",
    "sg:postcode":"07760",
    "sg:province":"Islas Baleares",
    "wof:name":"Tot Lluquet S.r.m.",
    "wof:placetype":"venue"
},
  "geometry": {"coordinates":[3.8416149616,40.0027542114],"type":"Point"}
}