{
  "type": "Feature",
  "properties": {
    "addr:full":"Avda General Mola, 19 Pozuelo De Alarcon Madrid 28224",
    "addr:housenumber":"19",
    "addr:postcode":"28224",
    "addr:street":"Avda General Mola",
    "iso:country":"ES",
    "sg:address":"Avda General Mola, 19",
    "sg:city":"Pozuelo De Alarcon",
    "sg:orig_category":"Flores Y Plantas Naturales (al Por Mayor)",
    "sg:phone":"+34 913 52 14 36",
    "sg:postcode":"28224",
    "sg:province":"Madrid",
    "wof:name":"Pascual Perez Manuel",
    "wof:placetype":"venue"
},
  "geometry": {"coordinates":[-3.7976179123,40.4505882263],"type":"Point"}
}