{
  "type": "Feature",
  "properties": {
    "addr:full":"Avda De Bara\u00f1ain, 52 Iru\u00f1a Navarra 31008",
    "addr:housenumber":"52",
    "addr:postcode":"31008",
    "addr:street":"Avda De Baran\u0303Ain",
    "iso:country":"ES",
    "sg:address":"Avda De Bara\u00f1ain, 52",
    "sg:city":"Iru\u00f1a",
    "sg:orig_category":"Reposter\u00cdas",
    "sg:phone":"+34 948 26 28 58",
    "sg:postcode":"31008",
    "sg:province":"Navarra",
    "wof:name":"Nicolas Lopez Vallejo Y Balduino Lopez Monta\u00f1es",
    "wof:placetype":"venue"
},
  "geometry": {"coordinates":[-1.6630009413,42.8109550476],"type":"Point"}
}