{
  "type": "Feature",
  "properties": {
    "iso:country":"ES",
    "sg:address":"Calle de Fonta\u00d1an, 12",
    "sg:city":"Le\u00f3n",
    "sg:orig_category":"Empresarios",
    "sg:phone":"+34 987 27 02 77",
    "sg:postcode":"24008",
    "sg:province":"Le\u00f3n",
    "wof:name":"Jordan Correia Yudite",
    "wof:placetype":"venue"
},
  "geometry": {"coordinates":[-5.5893654823,42.6136322021],"type":"Point"}
}