{
  "type": "Feature",
  "properties": {
    "iso:country":"ES",
    "sg:address":"Avda Miguel Manche\u00d1o, 55",
    "sg:city":"Arcos Frontera",
    "sg:orig_category":"Molduras, Junquillos, Listones Y Molduras Perforadas",
    "sg:phone":"+34 956 70 17 10",
    "sg:postcode":"11630",
    "sg:province":"C\u00e1diz",
    "wof:name":"Gil Doblado Manuel",
    "wof:placetype":"venue"
},
  "geometry": {"coordinates":[-5.8202872276,36.7495956421],"type":"Point"}
}