{
  "type": "Feature",
  "properties": {
    "iso:country":"ES",
    "sg:address":"Carr Marques De Caldes De Montbui, 123",
    "sg:city":"Girona",
    "sg:orig_category":"Ense\u00d1anza, Formaci\u00d3n Profesional: Aprendizaje",
    "sg:phone":"+34 972 22 34 42",
    "sg:postcode":"17003",
    "sg:province":"Girona",
    "wof:name":"Centre Academic Sarrats",
    "wof:placetype":"venue"
},
  "geometry": {"coordinates":[2.8229210377,41.9680671692],"type":"Point"}
}