{
  "type": "Feature",
  "properties": {
    "addr:full":"Calle de Almazan, 1 Soria Soria 42004",
    "addr:housenumber":"1",
    "addr:postcode":"42004",
    "addr:street":"Calle De Almazan",
    "iso:country":"ES",
    "sg:address":"Calle de Almazan, 1",
    "sg:city":"Soria",
    "sg:orig_category":"Aparatos E Instalaci\u00d3n De Regad\u00cdos",
    "sg:phone":"+34 975 21 30 84",
    "sg:postcode":"42004",
    "sg:province":"Soria",
    "wof:name":"Lopez Garcia Javier",
    "wof:placetype":"venue"
},
  "geometry": {"coordinates":[-2.4696757793,41.7584953308],"type":"Point"}
}