{
  "type": "Feature",
  "properties": {
    "addr:full":"Plaz Constitucion, 1 Canena Ja\u00e9n 23420",
    "addr:housenumber":"1",
    "addr:postcode":"23420",
    "addr:street":"Constitucion",
    "iso:country":"ES",
    "sg:address":"Plaz Constitucion, 1",
    "sg:city":"Canena",
    "sg:orig_category":"Iglesia Cat\u00d3lica",
    "sg:phone":"+34 953 77 01 78",
    "sg:postcode":"23420",
    "sg:province":"Ja\u00e9n",
    "wof:name":"Parroquia De La Inmaculada Concepcion",
    "wof:placetype":"venue"
},
  "geometry": {"coordinates":[-3.4805979729,38.0463943481],"type":"Point"}
}