{
  "type": "Feature",
  "properties": {
    "addr:full":"Carrer de Can Magi, 18 Barbera Valles Barcelona 08210",
    "addr:housenumber":"18",
    "addr:postcode":"08210",
    "addr:street":"Carrer De Can Magi",
    "iso:country":"ES",
    "sg:address":"Carrer de Can Magi, 18",
    "sg:city":"Barbera Valles",
    "sg:orig_category":"Metales (labores, Pulido)",
    "sg:phone":"+34 937 18 39 05",
    "sg:postcode":"08210",
    "sg:province":"Barcelona",
    "wof:name":"Talleres Auxiliares De Estampaciones S.l.",
    "wof:placetype":"venue"
},
  "geometry": {"coordinates":[2.1271760464,41.5150566101],"type":"Point"}
}