{
  "type": "Feature",
  "properties": {
    "addr:full":"Calle de Gordoniz, 30 Bilbao Vizcaya 48012",
    "addr:housenumber":"30",
    "addr:postcode":"48012",
    "addr:street":"Calle De Gordoniz",
    "iso:country":"ES",
    "sg:address":"Calle de Gordoniz, 30",
    "sg:city":"Bilbao",
    "sg:orig_category":"Zapatos (al Por Menor)",
    "sg:phone":"+34 944 44 39 33",
    "sg:postcode":"48012",
    "sg:province":"Vizcaya",
    "wof:name":"Rey Lema Maria Del Carmen",
    "wof:placetype":"venue"
},
  "geometry": {"coordinates":[-2.9425508976,43.2567214966],"type":"Point"}
}