{
  "type": "Feature",
  "properties": {
    "iso:country":"ES",
    "sg:address":"Carrer de Miquel De Roncali, 53",
    "sg:city":"Cornella Llobregat",
    "sg:orig_category":"Frutas, Legumbres Frescas Y Tempranas (al Por Menor)",
    "sg:phone":"+34 934 74 39 73",
    "sg:postcode":"08940",
    "sg:province":"Barcelona",
    "wof:name":"Pastor Diaz Joaquin",
    "wof:placetype":"venue"
},
  "geometry": {"coordinates":[2.0668599606,41.3535385132],"type":"Point"}
}