{
  "type": "Feature",
  "properties": {
    "iso:country":"ES",
    "sg:address":"Pla\u00c7 Pla\u00c7a De La Generalitat, 1",
    "sg:city":"Alzira",
    "sg:orig_category":"Cl\u00cdnicas Dentales",
    "sg:phone":"+34 962 41 96 12",
    "sg:postcode":"46600",
    "sg:province":"Valencia",
    "wof:name":"Hermanas Palanquez Orti C.b.",
    "wof:placetype":"venue"
},
  "geometry": {"coordinates":[-0.4378489852,39.1517295837],"type":"Point"}
}