{
  "type": "Feature",
  "properties": {
    "addr:full":"Carr Cuart, 72 Moncada Valencia 46113",
    "addr:housenumber":"72",
    "addr:postcode":"46113",
    "addr:street":"Carr Cuart",
    "iso:country":"ES",
    "sg:address":"Carr Cuart, 72",
    "sg:city":"Moncada",
    "sg:orig_category":"Cueros Y Pieles (al Por Mayor)",
    "sg:phone":"+34 961 30 15 72",
    "sg:postcode":"46113",
    "sg:province":"Valencia",
    "wof:name":"Golden Piel 3000 S.l.",
    "wof:placetype":"venue"
},
  "geometry": {"coordinates":[-0.3982529938,39.5452728271],"type":"Point"}
}