{
  "type": "Feature",
  "properties": {
    "iso:country":"ES",
    "sg:address":"Laurgain Auzoa, 36",
    "sg:city":"Laurgain",
    "sg:orig_category":"Materiales De Construcci\u00d3n (en General)",
    "sg:phone":"+34 943 13 26 79",
    "sg:postcode":"20809",
    "sg:province":"Guip\u00f9zcoa",
    "wof:name":"Comercial Urratz S.l.",
    "wof:placetype":"venue"
},
  "geometry": {"coordinates":[-2.1475191116,43.2376937866],"type":"Point"}
}