{
  "type": "Feature",
  "properties": {
    "addr:full":"Calle de Isla Cebu, 27 Alhama Murcia Murcia 30840",
    "addr:housenumber":"27",
    "addr:postcode":"30840",
    "addr:street":"Calle De Isla Cebu",
    "iso:country":"ES",
    "sg:address":"Calle de Isla Cebu, 27",
    "sg:city":"Alhama Murcia",
    "sg:orig_category":"Negocio De Enlosados, Soler\u00cdas",
    "sg:phone":"+34 968 63 27 89",
    "sg:postcode":"30840",
    "sg:province":"Murcia",
    "wof:name":"Vecoagres S.l.",
    "wof:placetype":"venue"
},
  "geometry": {"coordinates":[-1.4218369722,37.845905304],"type":"Point"}
}