{
  "type": "Feature",
  "properties": {
    "addr:full":"Carrer de Ponent (del), 1 Vila-seca Tarragona 43480",
    "addr:housenumber":"1",
    "addr:postcode":"43480",
    "addr:street":"Carrer De Ponent Del",
    "iso:country":"ES",
    "sg:address":"Carrer de Ponent (del), 1",
    "sg:city":"Vila-seca",
    "sg:orig_category":"Cr\u00cda De Animales",
    "sg:phone":"+34 977 39 01 35",
    "sg:postcode":"43480",
    "sg:province":"Tarragona",
    "wof:name":"Ber Canals Joan",
    "wof:placetype":"venue"
},
  "geometry": {"coordinates":[1.1437449455,41.1083602905],"type":"Point"}
}