{
  "type": "Feature",
  "properties": {
    "addr:full":"Carrer de Albert Einstein, 13 Castelldefels Barcelona 08860",
    "addr:housenumber":"13",
    "addr:postcode":"08860",
    "addr:street":"Carrer De Albert Einstein",
    "iso:country":"ES",
    "sg:address":"Carrer de Albert Einstein, 13",
    "sg:city":"Castelldefels",
    "sg:orig_category":"Inmobiliaria (agencias)",
    "sg:phone":"+34 936 64 64 65",
    "sg:postcode":"08860",
    "sg:province":"Barcelona",
    "wof:name":"Mundopiso Castelldefels S.l.",
    "wof:placetype":"venue"
},
  "geometry": {"coordinates":[1.9794579744,41.282119751],"type":"Point"}
}