{
  "type": "Feature",
  "properties": {
    "addr:full":"Carr Valencia, 4 Algemesi Valencia 46680",
    "addr:housenumber":"4",
    "addr:postcode":"46680",
    "addr:street":"Carr Valencia",
    "iso:country":"ES",
    "sg:address":"Carr Valencia, 4",
    "sg:city":"Algemesi",
    "sg:orig_category":"Sindicatos De Trabajadores",
    "sg:phone":"+34 962 42 11 08",
    "sg:postcode":"46680",
    "sg:province":"Valencia",
    "wof:name":"Comissions Obreres Del Pais Valencia",
    "wof:placetype":"venue"
},
  "geometry": {"coordinates":[-0.4391820133,39.1951065063],"type":"Point"}
}