{
  "type": "Feature",
  "properties": {
    "addr:full":"Calle de Diego Fernandez Herrera, 13 Jerez De La Frontera C\u00e1diz 11401",
    "addr:housenumber":"13",
    "addr:postcode":"11401",
    "addr:street":"Calle De Diego Fernandez Herrera",
    "iso:country":"ES",
    "sg:address":"Calle de Diego Fernandez Herrera, 13",
    "sg:city":"Jerez De La Frontera",
    "sg:orig_category":"Agencias Y Agentes Comerciales, Representantes",
    "sg:phone":"+34 956 33 56 61",
    "sg:postcode":"11401",
    "sg:province":"C\u00e1diz",
    "wof:name":"Perez Real Antonio",
    "wof:placetype":"venue"
},
  "geometry": {"coordinates":[-6.1289243698,36.6797218323],"type":"Point"}
}