{
  "type": "Feature",
  "properties": {
    "iso:country":"ES",
    "sg:address":"Calle de Ejercito Espa\u00d1ol, 19",
    "sg:city":"Melilla",
    "sg:orig_category":"Bazares, Art\u00cdculos De Limpieza Y De Cocina (al Por Menor)",
    "sg:phone":"+34 952 68 38 83",
    "sg:postcode":"52001",
    "sg:province":"Melilla",
    "wof:name":"Benhamu Benguigui Marcos",
    "wof:placetype":"venue"
},
  "geometry": {"coordinates":[-2.939852953,35.2941703796],"type":"Point"}
}