{
  "type": "Feature",
  "properties": {
    "iso:country":"ES",
    "sg:address":"Calle de Sancho Davila, 21",
    "sg:city":"Madrid",
    "sg:orig_category":"Asesor\u00cda Fiscal Y Jur\u00cddica",
    "sg:phone":"+34 913 55 43 97",
    "sg:postcode":"28028",
    "sg:province":"Madrid",
    "wof:name":"Sociedad Matritense De Asesoria Empresarial S.l.",
    "wof:placetype":"venue"
},
  "geometry": {"coordinates":[-3.6616849899,40.4266929626],"type":"Point"}
}