{
  "type": "Feature",
  "properties": {
    "addr:full":"Calle de Cordoba, 10 Malaga M\u00e1laga 29001",
    "addr:housenumber":"10",
    "addr:postcode":"29001",
    "addr:street":"Calle De Cordoba;Ma\u0301Laga",
    "iso:country":"ES",
    "sg:address":"Calle de Cordoba, 10",
    "sg:city":"Malaga",
    "sg:orig_category":"Servicio De Salud",
    "sg:phone":"+34 952 21 55 26",
    "sg:postcode":"29001",
    "sg:province":"M\u00e1laga",
    "wof:name":"Rodriguez Sanchez Matilde",
    "wof:placetype":"venue"
},
  "geometry": {"coordinates":[-4.4219579697,36.716129303],"type":"Point"}
}