{
  "type": "Feature",
  "properties": {
    "iso:country":"ES",
    "sg:address":"Calle de Eduardo Benot, 5",
    "sg:city":"Santander",
    "sg:orig_category":"Telas Para Tapizar, Cortinas, Pasamaner\u00cda (fabricaci\u00d3n, Al Por Mayor)",
    "sg:phone":"+34 942 21 01 47",
    "sg:postcode":"39003",
    "sg:province":"Cantabria",
    "wof:name":"Molinero Arias Blanca",
    "wof:placetype":"venue"
},
  "geometry": {"coordinates":[-3.8008310795,43.46301651],"type":"Point"}
}