{
  "type": "Feature",
  "properties": {
    "addr:full":"Carrer de Eusebi Estada, 107 Palma Islas Baleares 07004",
    "addr:housenumber":"107",
    "addr:postcode":"07004",
    "addr:street":"Carrer De Eusebi Estada",
    "iso:country":"ES",
    "sg:address":"Carrer de Eusebi Estada, 107",
    "sg:city":"Palma",
    "sg:orig_category":"Farmacias",
    "sg:phone":"+34 971 29 79 03",
    "sg:postcode":"07004",
    "sg:province":"Islas Baleares",
    "wof:name":"Munar Munar Antonio",
    "wof:placetype":"venue"
},
  "geometry": {"coordinates":[2.6623079777,39.5844192505],"type":"Point"}
}