{
  "type": "Feature",
  "properties": {
    "addr:full":"Cmno Hondo, 13 Torre Molina Murcia 30009",
    "addr:housenumber":"13",
    "addr:postcode":"30009",
    "addr:street":"Cmno Hondo",
    "iso:country":"ES",
    "sg:address":"Cmno Hondo, 13",
    "sg:city":"Torre Molina",
    "sg:orig_category":"Maquinaria Para Industrias Diversas",
    "sg:phone":"+34 968 28 00 14",
    "sg:postcode":"30009",
    "sg:province":"Murcia",
    "wof:name":"Hormigomur C.b.",
    "wof:placetype":"venue"
},
  "geometry": {"coordinates":[-1.1528439522,37.9883460999],"type":"Point"}
}