{
  "type": "Feature",
  "properties": {
    "iso:country":"ES",
    "sg:address":"Calle de Matia, 15",
    "sg:city":"Donostia-san Sebastian",
    "sg:orig_category":"Ropa Para Se\u00d1oras Y Caballeros (al Por Menor)",
    "sg:phone":"+34 943 21 23 60",
    "sg:postcode":"20008",
    "sg:province":"Guip\u00f9zcoa",
    "wof:name":"Elena Oteiza Larrea",
    "wof:placetype":"venue"
},
  "geometry": {"coordinates":[-2.0025150776,43.3134536743],"type":"Point"}
}