{
  "type": "Feature",
  "properties": {
    "iso:country":"ES",
    "sg:address":"Carrer de Miquel De Roncali, 67",
    "sg:city":"Cornella Llobregat",
    "sg:orig_category":"Ebanister\u00cda",
    "sg:phone":"+34 934 74 21 09",
    "sg:postcode":"08940",
    "sg:province":"Barcelona",
    "wof:name":"F Y F Carpinteria Ebanisteria",
    "wof:placetype":"venue"
},
  "geometry": {"coordinates":[2.0661389828,41.3531265259],"type":"Point"}
}