{
  "type": "Feature",
  "properties": {
    "iso:country":"ES",
    "sg:address":"Garmendi Auzunea, 18",
    "sg:city":"Azpeitia",
    "sg:orig_category":"Promotores Constructores",
    "sg:phone":"+34 943 15 17 29",
    "sg:postcode":"20730",
    "sg:province":"Guip\u00f9zcoa",
    "wof:name":"Construcciones Astiaran, S.l.",
    "wof:placetype":"venue"
},
  "geometry": {"coordinates":[-2.2634871006,43.1794815063],"type":"Point"}
}