{
  "type": "Feature",
  "properties": {
    "addr:full":"Calle de Mayor, 17 Quintanadue\u00f1as Burgos 09197",
    "addr:housenumber":"17",
    "addr:postcode":"09197",
    "addr:street":"Calle De Mayor",
    "iso:country":"ES",
    "sg:address":"Calle de Mayor, 17",
    "sg:city":"Quintanadue\u00f1as",
    "sg:orig_category":"Cajas De Ahorro",
    "sg:phone":"+34 947 29 27 16",
    "sg:postcode":"09197",
    "sg:province":"Burgos",
    "sg:website":"www.cajacirculo.es",
    "wof:name":"Caja De Ahorros Del Circulo Catolico Obrero De Burgos",
    "wof:placetype":"venue"
},
  "geometry": {"coordinates":[-3.7342131138,42.385181427],"type":"Point"}
}