{
  "type": "Feature",
  "properties": {
    "addr:full":"Av Argentina, 75 Palma Islas Baleares 07011",
    "addr:housenumber":"75",
    "addr:postcode":"07011",
    "addr:street":"Av Argentina",
    "iso:country":"ES",
    "sg:address":"Av Argentina, 75",
    "sg:city":"Palma",
    "sg:orig_category":"Zapatos (al Por Menor)",
    "sg:phone":"+34 971 45 41 18",
    "sg:postcode":"07011",
    "sg:province":"Islas Baleares",
    "wof:name":"Interbalear S. L.",
    "wof:placetype":"venue"
},
  "geometry": {"coordinates":[2.6407599449,39.5751686096],"type":"Point"}
}