{
  "type": "Feature",
  "properties": {
    "iso:country":"ES",
    "sg:address":"Pl Esglesia (de L'), S/n",
    "sg:city":"Altafulla",
    "sg:orig_category":"Iglesia Cat\u00d3lica",
    "sg:phone":"+34 977 65 01 42",
    "sg:postcode":"43893",
    "sg:province":"Tarragona",
    "wof:name":"Arquebisbat De Tarragona",
    "wof:placetype":"venue"
},
  "geometry": {"coordinates":[1.3759704828,41.1427001953],"type":"Point"}
}