{
  "type": "Feature",
  "properties": {
    "addr:full":"Calle de Berlanas, 11 Madrid Madrid 28047",
    "addr:housenumber":"11",
    "addr:postcode":"madrid;28047",
    "addr:street":"Calle De Berlanas",
    "iso:country":"ES",
    "sg:address":"Calle de Berlanas, 11",
    "sg:city":"Madrid",
    "sg:orig_category":"Trabajos De Soldaduras",
    "sg:phone":"+34 914 63 62 75",
    "sg:postcode":"28047",
    "sg:province":"Madrid",
    "wof:name":"E 2 R S.a.",
    "wof:placetype":"venue"
},
  "geometry": {"coordinates":[-3.752341032,40.4005622864],"type":"Point"}
}