{
  "type": "Feature",
  "properties": {
    "addr:full":"Calle de Luisa Biaggi Veira, 3 Esquivias Toledo 45221",
    "addr:housenumber":"3",
    "addr:postcode":"45221",
    "addr:street":"Calle De Luisa Biaggi Veira",
    "iso:country":"ES",
    "sg:address":"Calle de Luisa Biaggi Veira, 3",
    "sg:city":"Esquivias",
    "sg:orig_category":"Fabricaci\u00d3n De Tapices Y Moquetas Para Suelos Y Paredes",
    "sg:phone":"+34 925 52 00 46",
    "sg:postcode":"45221",
    "sg:province":"Toledo",
    "sg:website":"www paginasamarillas.es",
    "wof:name":"Terrazos La Ontanilla S.a.",
    "wof:placetype":"venue"
},
  "geometry": {"coordinates":[-3.7687551975,40.1021537781],"type":"Point"}
}