{
  "type": "Feature",
  "properties": {
    "iso:country":"ES",
    "sg:address":"Calle de Zumalacarregui, 17",
    "sg:city":"Gijon",
    "sg:orig_category":"Pintura, Barniz, Productos Asimilables (fabricaci\u00d3n, Al Por Mayor)",
    "sg:phone":"+34 985 32 51 44",
    "sg:postcode":"33212",
    "sg:province":"Asturias",
    "wof:name":"Asturlak S.l.",
    "wof:placetype":"venue"
},
  "geometry": {"coordinates":[-5.6844134331,43.5409011841],"type":"Point"}
}