{
  "type": "Feature",
  "properties": {
    "iso:country":"ES",
    "sg:address":"Urbanizacion Santa Barbara, S/n",
    "sg:city":"Rocafort",
    "sg:orig_category":"M\u00c9dicos: Cirug\u00cda General",
    "sg:phone":"+34 961 31 10 13",
    "sg:postcode":"46111",
    "sg:province":"Valencia",
    "wof:name":"Cano Ivorra Jose",
    "wof:placetype":"venue"
},
  "geometry": {"coordinates":[-0.4158790112,39.5420341492],"type":"Point"}
}