{
  "type": "Feature",
  "properties": {
    "addr:full":"Carr Escola Graduada, De S', 20 Binissalem Islas Baleares 07350",
    "addr:housenumber":"20",
    "addr:postcode":"07350",
    "addr:street":"Carr Escola Graduada De S '",
    "iso:country":"ES",
    "sg:address":"Carr Escola Graduada, De S', 20",
    "sg:city":"Binissalem",
    "sg:orig_category":"Bebidas",
    "sg:phone":"+34 971 87 00 10",
    "sg:postcode":"07350",
    "sg:province":"Islas Baleares",
    "wof:name":"Rosmo C.b.",
    "wof:placetype":"venue"
},
  "geometry": {"coordinates":[2.8373799324,39.6887702942],"type":"Point"}
}