{
  "type": "Feature",
  "properties": {
    "iso:country":"ES",
    "sg:address":"Calle de Concilio De Nicea, 12",
    "sg:city":"Cordoba",
    "sg:orig_category":"Bisuter\u00cda, Joyer\u00cda, Relojer\u00cda (al Por Menor)",
    "sg:phone":"+34 957 25 01 05",
    "sg:postcode":"14014",
    "sg:province":"C\u00f3rdoba",
    "wof:name":"Doblas C.b.",
    "wof:placetype":"venue"
},
  "geometry": {"coordinates":[-4.7573242188,37.8878440857],"type":"Point"}
}