{
  "type": "Feature",
  "properties": {
    "iso:country":"ES",
    "sg:address":"Ctra Carmona, S/n",
    "sg:city":"Marchena",
    "sg:orig_category":"Producci\u00d3n, Venta De Productos De Agricultura Biol\u00d3gica",
    "sg:phone":"+34 955 84 55 17",
    "sg:postcode":"41620",
    "sg:province":"Sevilla",
    "wof:name":"Agro Campa\u00f1a S.cv.",
    "wof:placetype":"venue"
},
  "geometry": {"coordinates":[-5.4147338867,37.3333740234],"type":"Point"}
}