{
  "type": "Feature",
  "properties": {
    "iso:country":"ES",
    "sg:address":"Avda Centro Excursionista Eldense, 3",
    "sg:city":"Elda",
    "sg:orig_category":"Cueros Y Pieles (al Por Mayor)",
    "sg:phone":"+34 965 39 69 94",
    "sg:postcode":"03600",
    "sg:province":"Alicante",
    "wof:name":"Curtidos Panadero Y Crespo S. L.",
    "wof:placetype":"venue"
},
  "geometry": {"coordinates":[-0.8062000275,38.4707984924],"type":"Point"}
}