{
  "type": "Feature",
  "properties": {
    "addr:full":"Calle de Juan Jose Martinez Seco, 48 Madrid Madrid 28021",
    "addr:housenumber":"48",
    "addr:postcode":"madrid;28021",
    "addr:street":"Calle De Juan Jose Martinez Seco",
    "iso:country":"ES",
    "sg:address":"Calle de Juan Jose Martinez Seco, 48",
    "sg:city":"Madrid",
    "sg:orig_category":"Laboratorios Y Trabajos De Fotograf\u00cda, V\u00cddeo Y Cine",
    "sg:phone":"+34 915 05 20 78",
    "sg:postcode":"28021",
    "sg:province":"Madrid",
    "wof:name":"Foto Aguilera S.l.",
    "wof:placetype":"venue"
},
  "geometry": {"coordinates":[-3.6889979839,40.3515319824],"type":"Point"}
}