{
  "type": "Feature",
  "properties": {
    "iso:country":"ES",
    "sg:address":"Calle de Flor De Papel, 11",
    "sg:city":"Sevilla",
    "sg:orig_category":"Suministros Y Materiales Industriales",
    "sg:phone":"+34 954 44 14 22",
    "sg:postcode":"41020",
    "sg:province":"Sevilla",
    "wof:name":"Senuam Suministros Industriales S.l.",
    "wof:placetype":"venue"
},
  "geometry": {"coordinates":[-5.9199290276,37.3945083618],"type":"Point"}
}