{
  "type": "Feature",
  "properties": {
    "iso:country":"ES",
    "sg:address":"Carretera Coroso, S/n",
    "sg:city":"Palmeira",
    "sg:orig_category":"Pescader\u00cdas (al Por Menor)",
    "sg:phone":"+34 981 83 81 63",
    "sg:postcode":"15950",
    "sg:province":"La Coru\u00f1a",
    "wof:name":"Pescados Moncho S.l.",
    "wof:placetype":"venue"
},
  "geometry": {"coordinates":[-8.9576444626,42.5836868286],"type":"Point"}
}