{
  "type": "Feature",
  "properties": {
    "addr:full":"Calle de Rosales, S/n Palma Rio C\u00f3rdoba 14700",
    "addr:postcode":"14700",
    "addr:street":"Calle De Rosales S / N Palma Rio Co\u0301Rdoba",
    "iso:country":"ES",
    "sg:address":"Calle de Rosales, S/n",
    "sg:city":"Palma Rio",
    "sg:orig_category":"Distribuci\u00d3n De Petr\u00d3leo Y Derivados",
    "sg:phone":"+34 957 64 65 25",
    "sg:postcode":"14700",
    "sg:province":"C\u00f3rdoba",
    "wof:name":"Fernandez Cruz Jose Carlos",
    "wof:placetype":"venue"
},
  "geometry": {"coordinates":[-5.2864141464,37.7020149231],"type":"Point"}
}