{
  "type": "Feature",
  "properties": {
    "iso:country":"ES",
    "sg:address":"Calle de Islas Malvinas, 5",
    "sg:city":"Salobre",
    "sg:orig_category":"Delegados, Agentes De Tr\u00c1nsito, Auxiliares De Transporte Internacional",
    "sg:phone":"+34 928 14 51 88",
    "sg:postcode":"35100",
    "sg:province":"Las Palmas",
    "wof:name":"Dicanin 2222 S.l.",
    "wof:placetype":"venue"
},
  "geometry": {"coordinates":[-15.4397096634,28.1302204132],"type":"Point"}
}