{
  "type": "Feature",
  "properties": {
    "iso:country":"ES",
    "sg:address":"Entrelagos, S/n",
    "sg:city":"Ruidera",
    "sg:orig_category":"Hoteles",
    "sg:phone":"+34 926 52 80 22",
    "sg:postcode":"13249",
    "sg:province":"Ciudad Real",
    "wof:name":"Hosteleria Capdevilla S.l.",
    "wof:placetype":"venue"
},
  "geometry": {"coordinates":[-2.8844890594,38.9768714905],"type":"Point"}
}