{
  "type": "Feature",
  "properties": {
    "addr:full":"Joaquin Potel, 1 Caldas De Reis Pontevedra 36650",
    "addr:housenumber":"1",
    "addr:postcode":"36650",
    "addr:street":"Potel",
    "iso:country":"ES",
    "sg:address":"Joaquin Potel, 1",
    "sg:city":"Caldas De Reis",
    "sg:orig_category":"Asesor\u00cda Sobre Comunicaci\u00d3n De Empresas",
    "sg:phone":"+34 986 53 08 32",
    "sg:postcode":"36650",
    "sg:province":"Pontevedra",
    "wof:name":"Suarez Gamallo Jose Manuel",
    "wof:placetype":"venue"
},
  "geometry": {"coordinates":[-8.6450166702,42.6034355164],"type":"Point"}
}