{
  "type": "Feature",
  "properties": {
    "iso:country":"ES",
    "sg:address":"Avda Alcalde Miguel Casta\u00d1o, 114",
    "sg:city":"Le\u00f3n",
    "sg:orig_category":"Centros De Educaci\u00d3n Especial",
    "sg:phone":"+34 987 20 88 98",
    "sg:postcode":"24005",
    "sg:province":"Le\u00f3n",
    "wof:name":"Colegio Publico Puente Castro",
    "wof:placetype":"venue"
},
  "geometry": {"coordinates":[-5.5578799248,42.5846633911],"type":"Point"}
}