{
  "type": "Feature",
  "properties": {
    "iso:country":"ES",
    "sg:address":"Calle de Cruz (la), 1",
    "sg:city":"Mutiloabeiti",
    "sg:orig_category":"Mec\u00c1nico Del Autom\u00d3vil",
    "sg:phone":"+34 948 24 97 15",
    "sg:postcode":"31192",
    "sg:province":"Navarra",
    "wof:name":"Urreta Olmedo Juan Jose",
    "wof:placetype":"venue"
},
  "geometry": {"coordinates":[-1.61650002,42.7894134521],"type":"Point"}
}