{
  "type": "Feature",
  "properties": {
    "addr:full":"Las Quemadillas, S/n Las Quemadillas C\u00f3rdoba 14014",
    "addr:housenumber":"s / n",
    "addr:postcode":"14014",
    "addr:street":"Las Quemadillas Co\u0301Rdoba",
    "iso:country":"ES",
    "sg:address":"Las Quemadillas, S/n",
    "sg:city":"Las Quemadillas",
    "sg:orig_category":"Gr\u00daas, Montacargas Y Elevadores Para Astilleros",
    "sg:phone":"+34 957 32 56 06",
    "sg:postcode":"14014",
    "sg:province":"C\u00f3rdoba",
    "wof:name":"Chica Rivilla Juan",
    "wof:placetype":"venue"
},
  "geometry": {"coordinates":[-4.7624139786,37.9240608215],"type":"Point"}
}