{
  "type": "Feature",
  "properties": {
    "iso:country":"ES",
    "sg:address":"Ctra Sevilla, S/n",
    "sg:city":"Utrera",
    "sg:orig_category":"Producci\u00d3n, Venta De Productos De Agricultura Biol\u00d3gica",
    "sg:phone":"+34 954 86 00 82",
    "sg:postcode":"41710",
    "sg:province":"Sevilla",
    "wof:name":"Pinganillo S.c.",
    "wof:placetype":"venue"
},
  "geometry": {"coordinates":[-5.7831039429,37.1834907532],"type":"Point"}
}