{
  "type": "Feature",
  "properties": {
    "addr:full":"Calle de San Isidro, 39 Tafalla Navarra 31300",
    "addr:housenumber":"39",
    "addr:postcode":"31300",
    "addr:street":"Calle De San Isidro",
    "iso:country":"ES",
    "sg:address":"Calle de San Isidro, 39",
    "sg:city":"Tafalla",
    "sg:orig_category":"Librer\u00cdas",
    "sg:phone":"+34 948 70 30 96",
    "sg:postcode":"31300",
    "sg:province":"Navarra",
    "sg:website":"www.gure-liburuak.com",
    "wof:name":"Gure Liburuak S.l.",
    "wof:placetype":"venue"
},
  "geometry": {"coordinates":[-1.6797540188,42.5242195129],"type":"Point"}
}