{
  "type": "Feature",
  "properties": {
    "addr:full":"Calle de San Sebastian, 87 Bonares Huelva 21830",
    "addr:housenumber":"87",
    "addr:postcode":"21830",
    "addr:street":"Calle De San Sebastian",
    "iso:country":"ES",
    "sg:address":"Calle de San Sebastian, 87",
    "sg:city":"Bonares",
    "sg:orig_category":"Contenedores (mercanc\u00cdas)",
    "sg:phone":"+34 959 36 63 36",
    "sg:postcode":"21830",
    "sg:province":"Huelva",
    "wof:name":"Romero Martin Juan Francisco",
    "wof:placetype":"venue"
},
  "geometry": {"coordinates":[-6.6768832207,37.3247795105],"type":"Point"}
}