{
  "type": "Feature",
  "properties": {
    "iso:country":"ES",
    "sg:address":"Calle de Zabalbide, 50",
    "sg:city":"Bilbao",
    "sg:orig_category":"Doctores En Medicina",
    "sg:phone":"+34 944 33 88 02",
    "sg:postcode":"48006",
    "sg:province":"Vizcaya",
    "wof:name":"Mu\u00f1oz Guerenabarrena Pablo Enrique",
    "wof:placetype":"venue"
},
  "geometry": {"coordinates":[-2.9177289009,43.2550430298],"type":"Point"}
}