{
  "type": "Feature",
  "properties": {
    "iso:country":"ES",
    "sg:address":"Mayor, S/n",
    "sg:city":"Cutanda",
    "sg:orig_category":"Centros De Educaci\u00d3n Especial",
    "sg:phone":"+34 978 73 50 56",
    "sg:postcode":"44210",
    "sg:province":"Teruel",
    "wof:name":"C.r.a.de El Poyodel Cid-d.g.a.-cutanda",
    "wof:placetype":"venue"
},
  "geometry": {"coordinates":[-1.1833490133,40.9333534241],"type":"Point"}
}