{
  "type": "Feature",
  "properties": {
    "iso:country":"ES",
    "sg:address":"Calle de Adelardo Covarsi, 1",
    "sg:city":"Badajoz",
    "sg:orig_category":"Arquitectos",
    "sg:phone":"+34 924 25 20 13",
    "sg:postcode":"06005",
    "sg:province":"Badajoz",
    "wof:name":"Saez Gervas David",
    "wof:placetype":"venue"
},
  "geometry": {"coordinates":[-6.9775285721,38.8741836548],"type":"Point"}
}