{
  "type": "Feature",
  "properties": {
    "iso:country":"ES",
    "sg:address":"Calle de Julio Saez De La Hoya, 1",
    "sg:city":"Burgos",
    "sg:orig_category":"Medias Y Calcetines (al Por Menor)",
    "sg:phone":"+34 947 21 88 77",
    "sg:postcode":"09005",
    "sg:province":"Burgos",
    "wof:name":"Barcena Castrillo Teodosio",
    "wof:placetype":"venue"
},
  "geometry": {"coordinates":[-3.6977419853,42.3453674316],"type":"Point"}
}