{
  "type": "Feature",
  "properties": {
    "addr:full":"Barrio De Elzaurdia, S/n Elzaurdia Navarra 31780",
    "addr:housenumber":"s",
    "addr:postcode":"31780",
    "addr:street":"Barrio;/ N Elzaurdia Navarra",
    "iso:country":"ES",
    "sg:address":"Barrio De Elzaurdia, S/n",
    "sg:city":"Elzaurdia",
    "sg:orig_category":"Molduras, Junquillos, Listones Y Molduras Perforadas",
    "sg:phone":"+34 948 63 13 40",
    "sg:postcode":"31780",
    "sg:province":"Navarra",
    "wof:name":"Eliyoso S.l.",
    "wof:placetype":"venue"
},
  "geometry": {"coordinates":[-1.6813839674,43.2808914185],"type":"Point"}
}