{
  "type": "Feature",
  "properties": {
    "addr:full":"Calle de Mota, 5 San Cristobal De Entrevi\u00e7as Zamora 49690",
    "addr:housenumber":"5",
    "addr:postcode":"49690",
    "addr:street":"Calle De Mota;Zamora",
    "iso:country":"ES",
    "sg:address":"Calle de Mota, 5",
    "sg:city":"San Cristobal De Entrevi\u00e7as",
    "sg:orig_category":"Alimentaci\u00d3n General (al Por Menor)",
    "sg:phone":"+34 980 64 35 35",
    "sg:postcode":"49690",
    "sg:province":"Zamora",
    "wof:name":"Huerga Madrid Maria",
    "wof:placetype":"venue"
},
  "geometry": {"coordinates":[-5.6344270706,42.0439453125],"type":"Point"}
}