{
  "type": "Feature",
  "properties": {
    "addr:full":"Calle de Beato Berrio Ochoa, 7 Logro\u00f1o La Rioja 26004",
    "addr:housenumber":"7",
    "addr:postcode":"26004",
    "addr:street":"Calle De Beato Berrio Ochoa;Rioja",
    "iso:country":"ES",
    "sg:address":"Calle de Beato Berrio Ochoa, 7",
    "sg:city":"Logro\u00f1o",
    "sg:orig_category":"Mec\u00c1nico Del Autom\u00d3vil",
    "sg:phone":"+34 941 24 11 72",
    "sg:postcode":"26004",
    "sg:province":"La Rioja",
    "wof:name":"Cordon Perez Miguel Angel",
    "wof:placetype":"venue"
},
  "geometry": {"coordinates":[-2.4291551113,42.4660606384],"type":"Point"}
}