{
  "type": "Feature",
  "properties": {
    "iso:country":"ES",
    "sg:address":"Pol Ind Palmera, S/n",
    "sg:city":"Sevilla",
    "sg:classifiers":[
        {
            "category":"Food & Beverages",
            "subcategory":"Candy",
            "type":"Retail Goods"
        }
    ],
    "sg:phone":"+34 954 69 35 61",
    "sg:postcode":"41014",
    "sg:province":"Sevilla",
    "sg:tags":[
        "confiter\u00cdas",
        "y",
        "de",
        "fabricaci\u00d3n",
        "chocolate"
    ],
    "wof:name":"Disromi Sur S.l.",
    "wof:placetype":"venue"
},
  "geometry": {"coordinates":[-5.9596791267,37.3278617859],"type":"Point"}
}