{
  "type": "Feature",
  "properties": {
    "iso:country":"ES",
    "sg:address":"Poligono Industrial, 5",
    "sg:city":"Andosilla",
    "sg:orig_category":"Imprenta",
    "sg:phone":"+34 948 69 03 37",
    "sg:postcode":"31261",
    "sg:province":"Navarra",
    "sg:website":"www.graficasandosilla.com",
    "wof:name":"Graficas Andosilla",
    "wof:placetype":"venue"
},
  "geometry": {"coordinates":[-1.9479709864,42.3728561401],"type":"Point"}
}