{
  "type": "Feature",
  "properties": {
    "iso:country":"ES",
    "sg:address":"Calle de Guadarrama, 16",
    "sg:city":"Galapagar",
    "sg:orig_category":"\u00d3ptica: Instrumentos (fabricaci\u00d3n)",
    "sg:phone":"+34 918 58 47 36",
    "sg:postcode":"28260",
    "sg:province":"Madrid",
    "wof:name":"Lorenzo Mendez Jose Carlos",
    "wof:placetype":"venue"
},
  "geometry": {"coordinates":[-4.0041937828,40.5789451599],"type":"Point"}
}