{
  "type": "Feature",
  "properties": {
    "addr:full":"Cust Santo Domingo, 11 Coru\u00d1a La Coru\u00f1a 15001",
    "addr:housenumber":"11",
    "addr:postcode":"15001",
    "addr:street":"Santo Domingo;La Corun\u0303A",
    "iso:country":"ES",
    "sg:address":"Cust Santo Domingo, 11",
    "sg:city":"Coru\u00d1a",
    "sg:orig_category":"Cajas De Ahorro",
    "sg:phone":"+34 981 20 58 12",
    "sg:postcode":"15001",
    "sg:province":"La Coru\u00f1a",
    "wof:name":"Bt Espa\u00d1a Compa\u00d1ia De Servicios Globales De Telecomunicaciones S.a.u.",
    "wof:placetype":"venue"
},
  "geometry": {"coordinates":[-8.3967437744,43.3701553345],"type":"Point"}
}