{
  "type": "Feature",
  "properties": {
    "addr:full":"Avda Boliches De Los, 80 Fuengirola M\u00e1laga 29640",
    "addr:postcode":"29640",
    "addr:street":"Avda Boliches De Los;Ma\u0301Laga",
    "iso:country":"ES",
    "sg:address":"Avda Boliches De Los, 80",
    "sg:city":"Fuengirola",
    "sg:orig_category":"Abogados",
    "sg:phone":"+34 952 47 56 24",
    "sg:postcode":"29640",
    "sg:province":"M\u00e1laga",
    "wof:name":"Smith  Elena Jose",
    "wof:placetype":"venue"
},
  "geometry": {"coordinates":[-4.6154341698,36.5513000488],"type":"Point"}
}