{
  "type": "Feature",
  "properties": {
    "iso:country":"ES",
    "sg:address":"Calle de Castillo De Gauzon, 6",
    "sg:city":"Piedras Blancas",
    "sg:orig_category":"Alquiler De V\u00cddeo",
    "sg:phone":"+34 985 53 26 94",
    "sg:postcode":"33450",
    "sg:province":"Asturias",
    "wof:name":"Melendi Carcedo Juan",
    "wof:placetype":"venue"
},
  "geometry": {"coordinates":[-5.9756245613,43.5613479614],"type":"Point"}
}