{
  "type": "Feature",
  "properties": {
    "addr:full":"Calle de Breton De Los Herreros, 31 Logro\u00f1o La Rioja 26001",
    "addr:housenumber":"31",
    "addr:postcode":"26001",
    "addr:street":"Calle De Breton De Los Herreros;Rioja",
    "iso:country":"ES",
    "sg:address":"Calle de Breton De Los Herreros, 31",
    "sg:city":"Logro\u00f1o",
    "sg:orig_category":"Ense\u00d1anza: Idiomas",
    "sg:phone":"+34 941 22 46 64",
    "sg:postcode":"26001",
    "sg:province":"La Rioja",
    "wof:name":"Lopez Hernando Angel Ramon",
    "wof:placetype":"venue"
},
  "geometry": {"coordinates":[-2.4496955872,42.4655532837],"type":"Point"}
}