{
  "type": "Feature",
  "properties": {
    "addr:full":"Carrer de D'amadeu Paltor, 26 Olesa Montserrat Barcelona 08640",
    "addr:housenumber":"26",
    "addr:postcode":"08640",
    "addr:street":"Carrer De D'Amadeu Paltor;Barcelona",
    "iso:country":"ES",
    "sg:address":"Carrer de D'amadeu Paltor, 26",
    "sg:city":"Olesa Montserrat",
    "sg:orig_category":"Transportes Por V\u00cdas Navegables",
    "sg:phone":"+34 937 78 73 40",
    "sg:postcode":"08640",
    "sg:province":"Barcelona",
    "wof:name":"Global Zar S.l.",
    "wof:placetype":"venue"
},
  "geometry": {"coordinates":[1.8365827799,41.5926704407],"type":"Point"}
}