{
  "type": "Feature",
  "properties": {
    "iso:country":"ES",
    "sg:address":"Calle de Alemania, 1",
    "sg:city":"Don Benito",
    "sg:orig_category":"Procuradores",
    "sg:phone":"+34 924 80 14 07",
    "sg:postcode":"06400",
    "sg:province":"Badajoz",
    "wof:name":"Merchan Cerrato Luisa Fernanda",
    "wof:placetype":"venue"
},
  "geometry": {"coordinates":[-5.8618087769,38.9581565857],"type":"Point"}
}