{
  "type": "Feature",
  "properties": {
    "iso:country":"ES",
    "sg:address":"Calle de Arenas De Igu\u00d1a, 1",
    "sg:city":"Madrid",
    "sg:orig_category":"Agencias Y Agentes Comerciales, Representantes",
    "sg:phone":"+34 917 78 94 97",
    "sg:postcode":"28038",
    "sg:province":"Madrid",
    "wof:name":"Cumpa Andrade Maria Elena",
    "wof:placetype":"venue"
},
  "geometry": {"coordinates":[-3.6471068859,40.3916320801],"type":"Point"}
}