{
  "type": "Feature",
  "properties": {
    "addr:full":"Carrer de Joan Badosa, 35 Roses Girona 17480",
    "addr:housenumber":"35",
    "addr:postcode":"17480",
    "addr:street":"Carrer De Joan Badosa",
    "iso:country":"ES",
    "sg:address":"Carrer de Joan Badosa, 35",
    "sg:city":"Roses",
    "sg:orig_category":"Art\u00cdculos De Regalo (al Por Menor)",
    "sg:phone":"+34 972 25 72 87",
    "sg:postcode":"17480",
    "sg:province":"Girona",
    "wof:name":"Subiros Puig Dolors",
    "wof:placetype":"venue"
},
  "geometry": {"coordinates":[3.1779448986,42.26121521],"type":"Point"}
}