{
  "type": "Feature",
  "properties": {
    "iso:country":"ES",
    "sg:address":"Carrer de Industria, 64",
    "sg:city":"Barcelona",
    "sg:orig_category":"M\u00c9dicos: Estomatolog\u00cda",
    "sg:phone":"+34 932 07 34 64",
    "sg:postcode":"08025",
    "sg:province":"Barcelona",
    "wof:name":"Mendoza Morales Antonio",
    "wof:placetype":"venue"
},
  "geometry": {"coordinates":[2.1689600945,41.4052772522],"type":"Point"}
}