{
  "type": "Feature",
  "properties": {
    "addr:full":"Carrer de Castell D'olimbroi, 2 Denia Alicante 03700",
    "addr:housenumber":"2",
    "addr:postcode":"03700",
    "addr:street":"Carrer De Castell D'Olimbroi",
    "iso:country":"ES",
    "sg:address":"Carrer de Castell D'olimbroi, 2",
    "sg:city":"Denia",
    "sg:orig_category":"Peluqueros: De Se\u00d1oras",
    "sg:phone":"+34 965 78 29 84",
    "sg:postcode":"03700",
    "sg:province":"Alicante",
    "wof:name":"Pallares Centelles Maria Encarnacion",
    "wof:placetype":"venue"
},
  "geometry": {"coordinates":[0.1048989967,38.8424682617],"type":"Point"}
}