{
  "type": "Feature",
  "properties": {
    "addr:full":"Calle de Diecinueve De Abril, 28 Dos Hermanas Sevilla 41700",
    "addr:housenumber":"28",
    "addr:postcode":"41700",
    "addr:street":"Calle De Diecinueve De Abril",
    "iso:country":"ES",
    "sg:address":"Calle de Diecinueve De Abril, 28",
    "sg:city":"Dos Hermanas",
    "sg:orig_category":"Artes Gr\u00c1ficas, Artes Pl\u00c1sticas (curso)",
    "sg:phone":"+34 955 67 90 52",
    "sg:postcode":"41700",
    "sg:province":"Sevilla",
    "sg:website":"www.micrapel.com",
    "wof:name":"Suministros Y Materiales Impresos S.l.",
    "wof:placetype":"venue"
},
  "geometry": {"coordinates":[-5.9333949089,37.2879524231],"type":"Point"}
}