{
  "type": "Feature",
  "properties": {
    "iso:country":"ES",
    "sg:address":"Calle de Montesa, 13",
    "sg:city":"Madrid",
    "sg:orig_category":"Art\u00cdculos De Decoraci\u00d3n",
    "sg:phone":"+34 915 19 78 80",
    "sg:postcode":"28006",
    "sg:province":"Madrid",
    "wof:name":"Artesania Y Decoracion Enebro S.l.",
    "wof:placetype":"venue"
},
  "geometry": {"coordinates":[-3.6723856926,40.4276618958],"type":"Point"}
}