{
  "type": "Feature",
  "properties": {
    "iso:country":"ES",
    "sg:address":"Cra. Roca, Km. 0003,2",
    "sg:city":"Cardedeu",
    "sg:orig_category":"Artes Gr\u00c1ficas, Artes Pl\u00c1sticas: Material Y Suministros (al Por Menor)",
    "sg:phone":"+34 938 71 27 75",
    "sg:postcode":"08440",
    "sg:province":"Barcelona",
    "sg:website":"www.valcocincinnatiinc.com",
    "wof:name":"Valco Cincinnati S.l.",
    "wof:placetype":"venue"
},
  "geometry": {"coordinates":[2.3589351177,41.6370544434],"type":"Point"}
}