{
  "type": "Feature",
  "properties": {
    "addr:full":"Ctra Logro\u00d1o, 25 Santo Domingo De La Calzada La Rioja 26250",
    "addr:housenumber":"25",
    "addr:postcode":"26250",
    "addr:street":"Ctra Logron\u0303O;Rioja",
    "iso:country":"ES",
    "sg:address":"Ctra Logro\u00d1o, 25",
    "sg:city":"Santo Domingo De La Calzada",
    "sg:orig_category":"Suministros Para Carrocer\u00cdas",
    "sg:phone":"+34 941 34 10 00",
    "sg:postcode":"26250",
    "sg:province":"La Rioja",
    "sg:website":"www.caravanas-rioja.es",
    "wof:name":"Caravanas Rioja S.l.",
    "wof:placetype":"venue"
},
  "geometry": {"coordinates":[-2.9376270771,42.4395103455],"type":"Point"}
}