{
  "type": "Feature",
  "properties": {
    "iso:country":"ES",
    "sg:address":"Calle de Enmedio, 116",
    "sg:city":"Castellon",
    "sg:orig_category":"Ropa Para Se\u00d1oras Y Caballeros (al Por Menor)",
    "sg:phone":"+34 964 23 21 70",
    "sg:postcode":"12001",
    "sg:province":"Castell\u00f3n",
    "wof:name":"Germans Barbera Belmonte S.l.",
    "wof:placetype":"venue"
},
  "geometry": {"coordinates":[-0.0377894007,39.9878349304],"type":"Point"}
}