{
  "type": "Feature",
  "properties": {
    "iso:country":"ES",
    "sg:address":"Avda Castilla, 27",
    "sg:city":"Guadalajara",
    "sg:orig_category":"Venta, Montaje De Neum\u00c1ticos",
    "sg:phone":"+34 949 23 04 90",
    "sg:postcode":"19002",
    "sg:province":"Guadalajara",
    "wof:name":"Jarbyn S.l.",
    "wof:placetype":"venue"
},
  "geometry": {"coordinates":[-3.1628463268,40.625377655],"type":"Point"}
}