{
  "type": "Feature",
  "properties": {
    "addr:full":"Carrer de Prat, 26 Barriada Nova Barcelona 08420",
    "addr:housenumber":"26",
    "addr:postcode":"08420",
    "addr:street":"Carrer De Prat;Nova Barcelona",
    "iso:country":"ES",
    "sg:address":"Carrer de Prat, 26",
    "sg:city":"Barriada Nova",
    "sg:orig_category":"Agentes Generales De Seguros",
    "sg:phone":"+34 938 46 65 05",
    "sg:postcode":"08420",
    "sg:province":"Barcelona",
    "wof:name":"Casta\u00f1o Domene Jose",
    "wof:placetype":"venue"
},
  "geometry": {"coordinates":[2.2783401012,41.6220207214],"type":"Point"}
}