{
  "type": "Feature",
  "properties": {
    "iso:country":"ES",
    "sg:address":"Avda San Gines, 93",
    "sg:city":"S. Gines",
    "sg:orig_category":"Discotecas Y Salas De Baile",
    "sg:phone":"+34 968 88 54 99",
    "sg:postcode":"30169",
    "sg:province":"Murcia",
    "wof:name":"Segis Arroces S.l.",
    "wof:placetype":"venue"
},
  "geometry": {"coordinates":[-1.1752769947,37.9537353516],"type":"Point"}
}