{
  "type": "Feature",
  "properties": {
    "addr:full":"Calle de Radio Peninsular (de), 4 Boadilla Del Monte Madrid 28660",
    "addr:postcode":"28660",
    "addr:street":"Calle De Radio",
    "iso:country":"ES",
    "sg:address":"Calle de Radio Peninsular (de), 4",
    "sg:city":"Boadilla Del Monte",
    "sg:orig_category":"Laboratorios Y Trabajos De Fotograf\u00cda, V\u00cddeo Y Cine",
    "sg:phone":"+34 916 32 26 70",
    "sg:postcode":"28660",
    "sg:province":"Madrid",
    "wof:name":"Casero Martin Juan",
    "wof:placetype":"venue"
},
  "geometry": {"coordinates":[-3.8775570393,40.4070281982],"type":"Point"}
}