{
  "type": "Feature",
  "properties": {
    "addr:full":"Carrer de Ribot I Serra, 226 Sabadell Barcelona 08208",
    "addr:housenumber":"226",
    "addr:postcode":"08208",
    "addr:street":"Carrer De Ribot I Serra",
    "iso:country":"ES",
    "sg:address":"Carrer de Ribot I Serra, 226",
    "sg:city":"Sabadell",
    "sg:orig_category":"Mec\u00c1nico Del Autom\u00d3vil",
    "sg:phone":"+34 937 17 40 52",
    "sg:postcode":"08208",
    "sg:province":"Barcelona",
    "wof:name":"Talleres Creu Alta S.l.",
    "wof:placetype":"venue"
},
  "geometry": {"coordinates":[2.103012085,41.5598907471],"type":"Point"}
}