{
  "type": "Feature",
  "properties": {
    "iso:country":"ES",
    "sg:address":"Cmno Santa Barbara, 1",
    "sg:city":"Alca\u00f1iz",
    "sg:orig_category":"Armas Y Municiones (fabricaci\u00d3n, Al Por Mayor)",
    "sg:phone":"+34 978 87 12 46",
    "sg:postcode":"44600",
    "sg:province":"Teruel",
    "wof:name":"Sport Nature S.c.",
    "wof:placetype":"venue"
},
  "geometry": {"coordinates":[-0.1379320025,41.0530548096],"type":"Point"}
}