{
  "type": "Feature",
  "properties": {
    "iso:country":"ES",
    "sg:address":"Calle de Cocheron De La Villa, S/n",
    "sg:city":"Madrid",
    "sg:orig_category":"Inmobiliaria (agencias)",
    "sg:phone":"+34 913 03 97 99",
    "sg:postcode":"28031",
    "sg:province":"Madrid",
    "sg:website":"www.coevisa.com",
    "wof:name":"Cogein S.a.",
    "wof:placetype":"venue"
},
  "geometry": {"coordinates":[-3.6350522041,40.3818778992],"type":"Point"}
}