{
  "type": "Feature",
  "properties": {
    "addr:full":"Calle de Covadonga, 11 Langreo Asturias 33900",
    "addr:housenumber":"11",
    "addr:postcode":"33900",
    "addr:street":"Calle De Covadonga",
    "iso:country":"ES",
    "sg:address":"Calle de Covadonga, 11",
    "sg:city":"Langreo",
    "sg:orig_category":"Fabricaci\u00d3n, Alquiler, Venta De Encofrados",
    "sg:phone":"+34 985 67 52 11",
    "sg:postcode":"33900",
    "sg:province":"Asturias",
    "wof:name":"Encofrados Alba Sl",
    "wof:placetype":"venue"
},
  "geometry": {"coordinates":[-5.6854562759,43.2980651855],"type":"Point"}
}