{
  "type": "Feature",
  "properties": {
    "iso:country":"ES",
    "sg:address":"Carrer de Miquel Arcas, 4",
    "sg:city":"Palma",
    "sg:orig_category":"Ense\u00d1anza Secundaria: Colegios Y Escuelas Privadas",
    "sg:phone":"+34 971 75 72 78",
    "sg:postcode":"07010",
    "sg:province":"Islas Baleares",
    "wof:name":"Instituto De Educacion Secundaria Madina Mayurqa",
    "wof:placetype":"venue"
},
  "geometry": {"coordinates":[2.6524689198,39.5882492065],"type":"Point"}
}