{
  "type": "Feature",
  "properties": {
    "addr:full":"Avda El Minero, 9 Gallarta Vizcaya 48500",
    "addr:housenumber":"9",
    "addr:postcode":"48500",
    "addr:street":"Avda El Minero",
    "iso:country":"ES",
    "sg:address":"Avda El Minero, 9",
    "sg:city":"Gallarta",
    "sg:orig_category":"Empresas De Pintura Y Revestimientos",
    "sg:phone":"+34 946 36 94 69",
    "sg:postcode":"48500",
    "sg:province":"Vizcaya",
    "wof:name":"Diez Alvarado Martin",
    "wof:placetype":"venue"
},
  "geometry": {"coordinates":[-3.0731749535,43.3145866394],"type":"Point"}
}