{
  "type": "Feature",
  "properties": {
    "addr:full":"Cmno O\u00d1atz Bidea, 6 Azpeitia Guip\u00f9zcoa 20730",
    "addr:housenumber":"6",
    "addr:postcode":"20730",
    "addr:street":"Cmno On\u0303Atz Bidea;Guipu\u0300Zcoa",
    "iso:country":"ES",
    "sg:address":"Cmno O\u00d1atz Bidea, 6",
    "sg:city":"Azpeitia",
    "sg:orig_category":"Empresas De Carpinter\u00cda De Madera",
    "sg:phone":"+34 943 81 16 81",
    "sg:postcode":"20730",
    "sg:province":"Guip\u00f9zcoa",
    "wof:name":"Otaegui Orbegozo Jose Luis",
    "wof:placetype":"venue"
},
  "geometry": {"coordinates":[-2.2643480301,43.176902771],"type":"Point"}
}