{
  "type": "Feature",
  "properties": {
    "addr:full":"Calle de Mayor, 14 Caspe Zaragoza 50700",
    "addr:housenumber":"14",
    "addr:postcode":"50700",
    "addr:street":"Calle De Mayor",
    "iso:country":"ES",
    "sg:address":"Calle de Mayor, 14",
    "sg:city":"Caspe",
    "sg:orig_category":"Bisuter\u00cda, Joyer\u00cda, Relojer\u00cda (al Por Menor)",
    "sg:phone":"+34 976 63 04 41",
    "sg:postcode":"50700",
    "sg:province":"Zaragoza",
    "wof:name":"Maza Oliva Emilio",
    "wof:placetype":"venue"
},
  "geometry": {"coordinates":[-0.0390280001,41.2363777161],"type":"Point"}
}