{
  "type": "Feature",
  "properties": {
    "addr:full":"Carrer de Bisbe Cabanelles, 4 Palma Islas Baleares 07005",
    "addr:housenumber":"4",
    "addr:postcode":"07005",
    "addr:street":"Carrer De Bisbe Cabanelles",
    "iso:country":"ES",
    "sg:address":"Carrer de Bisbe Cabanelles, 4",
    "sg:city":"Palma",
    "sg:orig_category":"Alimentaci\u00d3n General (al Por Menor)",
    "sg:phone":"+34 971 24 99 35",
    "sg:postcode":"07005",
    "sg:province":"Islas Baleares",
    "wof:name":"Germans Diallo",
    "wof:placetype":"venue"
},
  "geometry": {"coordinates":[2.6644799709,39.5754508972],"type":"Point"}
}