{
  "type": "Feature",
  "properties": {
    "addr:full":"Ctra Del Rocio, 188 Almonte Huelva 21730",
    "addr:housenumber":"188",
    "addr:postcode":"21730",
    "addr:street":"Ctra Del Rocio",
    "iso:country":"ES",
    "sg:address":"Ctra Del Rocio, 188",
    "sg:city":"Almonte",
    "sg:orig_category":"Porcelanas, Azulejos (fabricaci\u00d3n, Al Por Mayor)",
    "sg:phone":"+34 959 45 19 73",
    "sg:postcode":"21730",
    "sg:province":"Huelva",
    "wof:name":"Nublan De Servicios S.l.",
    "wof:placetype":"venue"
},
  "geometry": {"coordinates":[-6.5206050873,37.2564201355],"type":"Point"}
}