{
  "type": "Feature",
  "properties": {
    "iso:country":"ES",
    "sg:address":"Carr Monestir De Lavaix (del), 3",
    "sg:city":"Pont Suert",
    "sg:orig_category":"Mercer\u00cda, Lencer\u00cda (al Por Menor)",
    "sg:phone":"+34 973 69 04 40",
    "sg:postcode":"25520",
    "sg:province":"Lleida",
    "wof:name":"Mestre Figueruelo Eva",
    "wof:placetype":"venue"
},
  "geometry": {"coordinates":[0.7409290075,42.4083328247],"type":"Point"}
}