{
  "type": "Feature",
  "properties": {
    "addr:full":"Calle de Mare Nostrum, 65 Majadahonda Madrid 28220",
    "addr:housenumber":"65",
    "addr:postcode":"28220",
    "addr:street":"Calle De Mare Nostrum",
    "iso:country":"ES",
    "sg:address":"Calle de Mare Nostrum, 65",
    "sg:city":"Majadahonda",
    "sg:orig_category":"Doctores En Medicina",
    "sg:phone":"+34 916 79 60 08",
    "sg:postcode":"28220",
    "sg:province":"Madrid",
    "wof:name":"Sociedad Madrile\u00d1a De Microbiologia Clin",
    "wof:placetype":"venue"
},
  "geometry": {"coordinates":[-3.8716540337,40.4739151001],"type":"Point"}
}