{
  "type": "Feature",
  "properties": {
    "iso:country":"ES",
    "sg:address":"Pla\u00c7 Partidors (de), 1",
    "sg:city":"Lliria",
    "sg:classifiers":[
        {
            "category":"Taxi",
            "type":"Transportation"
        }
    ],
    "sg:phone":"+34 962 78 11 91",
    "sg:postcode":"46160",
    "sg:province":"Valencia",
    "wof:name":"Federacion Sindical De Trabajadoresaut.taxi",
    "wof:placetype":"venue"
},
  "geometry": {"coordinates":[-0.5952839851,39.6247406006],"type":"Point"}
}