{
  "type": "Feature",
  "properties": {
    "addr:full":"Calle de Canovas Del Castillo, 15 Ecija Sevilla 41400",
    "addr:housenumber":"15",
    "addr:postcode":"41400",
    "addr:street":"Calle De Canovas Del Castillo",
    "iso:country":"ES",
    "sg:address":"Calle de Canovas Del Castillo, 15",
    "sg:city":"Ecija",
    "sg:orig_category":"Electrodom\u00c9sticos (al Por Menor)",
    "sg:phone":"+34 955 90 49 07",
    "sg:postcode":"41400",
    "sg:province":"Sevilla",
    "wof:name":"Electro Factory Las Torres S.l.",
    "wof:placetype":"venue"
},
  "geometry": {"coordinates":[-5.0797367096,37.5388526917],"type":"Point"}
}