{
  "type": "Feature",
  "properties": {
    "addr:full":"Calle de Mercedes (las), 28 Arenas -areeta Vizcaya 48930",
    "addr:housenumber":"28;areeta",
    "addr:postcode":"48930",
    "addr:street":"Calle De Mercedes Las",
    "iso:country":"ES",
    "sg:address":"Calle de Mercedes (las), 28",
    "sg:city":"Arenas -areeta",
    "sg:orig_category":"Peluquer\u00cdas, Peluquer\u00cda Mixta",
    "sg:phone":"+34 944 64 19 41",
    "sg:postcode":"48930",
    "sg:province":"Vizcaya",
    "wof:name":"Diaz Varela Maria Del Pilar",
    "wof:placetype":"venue"
},
  "geometry": {"coordinates":[-3.0123200417,43.3273086548],"type":"Point"}
}