{
  "type": "Feature",
  "properties": {
    "iso:country":"ES",
    "sg:address":"Calle de Concepcion Arenal, 20",
    "sg:city":"Palmas De Gran Canaria",
    "sg:orig_category":"Abogados",
    "sg:phone":"+34 928 24 83 92",
    "sg:postcode":"35006",
    "sg:province":"Las Palmas",
    "wof:name":"Artiles Lopez Jesus Manuel",
    "wof:placetype":"venue"
},
  "geometry": {"coordinates":[-15.4347314835,28.1330738068],"type":"Point"}
}