{
  "type": "Feature",
  "properties": {
    "iso:country":"ES",
    "sg:address":"Pase Marina Espa\u00d1ola, 1",
    "sg:city":"Suances",
    "sg:orig_category":"Molduras, Junquillos, Listones Y Molduras Perforadas",
    "sg:phone":"+34 942 81 08 01",
    "sg:postcode":"39340",
    "sg:province":"Cantabria",
    "wof:name":"Sierra Gomez Jesus",
    "wof:placetype":"venue"
},
  "geometry": {"coordinates":[-4.0363759995,43.4330406189],"type":"Point"}
}