{
  "type": "Feature",
  "properties": {
    "iso:country":"ES",
    "sg:address":"Calle de Cristobal Iba\u00d1ez, S/n",
    "sg:city":"Maracena",
    "sg:orig_category":"Ropa Para Caballeros Y Se\u00d1oras (al Por Mayor)",
    "sg:phone":"+34 958 42 15 54",
    "sg:postcode":"18200",
    "sg:province":"Granada",
    "wof:name":"Alhambra Moda Sl",
    "wof:placetype":"venue"
},
  "geometry": {"coordinates":[-3.6431152821,37.203086853],"type":"Point"}
}