{
  "type": "Feature",
  "properties": {
    "addr:full":"Calle de Cuenca, 6 Catarroja Valencia 46470",
    "addr:housenumber":"6",
    "addr:postcode":"46470",
    "addr:street":"Calle De Cuenca",
    "iso:country":"ES",
    "sg:address":"Calle de Cuenca, 6",
    "sg:city":"Catarroja",
    "sg:orig_category":"Molduras, Junquillos, Listones Y Molduras Perforadas",
    "sg:phone":"+34 961 26 97 85",
    "sg:postcode":"46470",
    "sg:province":"Valencia",
    "wof:name":"Costa Mompo Carlos",
    "wof:placetype":"venue"
},
  "geometry": {"coordinates":[-0.4070602059,39.4048881531],"type":"Point"}
}