{
  "type": "Feature",
  "properties": {
    "addr:full":"Calle de Rubicon, 29 S. Bartolome Las Palmas 35550",
    "addr:housenumber":"29",
    "addr:postcode":"35550",
    "addr:street":"Calle De Rubicon;S. Bartolome Las",
    "iso:country":"ES",
    "sg:address":"Calle de Rubicon, 29",
    "sg:city":"S. Bartolome",
    "sg:orig_category":"Asistencia Domiciliaria",
    "sg:phone":"+34 928 52 03 59",
    "sg:postcode":"35550",
    "sg:province":"Las Palmas",
    "wof:name":"Gracia Gateu Ricardo",
    "wof:placetype":"venue"
},
  "geometry": {"coordinates":[-13.6090517044,29.0046367645],"type":"Point"}
}