{
  "type": "Feature",
  "properties": {
    "iso:country":"ES",
    "sg:address":"Carrer de Assumpcio, 9",
    "sg:city":"Poblenou",
    "sg:orig_category":"Fabricaci\u00d3n De Su\u00c9ters Y Chalecos De Punto",
    "sg:phone":"+34 937 69 19 79",
    "sg:postcode":"08397",
    "sg:province":"Barcelona",
    "wof:name":"Su\u00f1er Vilaburges Rafael",
    "wof:placetype":"venue"
},
  "geometry": {"coordinates":[2.6749300957,41.6178245544],"type":"Point"}
}