{
  "type": "Feature",
  "properties": {
    "iso:country":"ES",
    "sg:address":"Carrer de Caro, 52",
    "sg:city":"Palma",
    "sg:orig_category":"Fabricaci\u00d3n De Muebles De Cocina",
    "sg:phone":"+34 971 73 03 79",
    "sg:postcode":"07013",
    "sg:province":"Islas Baleares",
    "wof:name":"Castillo Sureda Victoria Del",
    "wof:placetype":"venue"
},
  "geometry": {"coordinates":[2.6360900402,39.5738105774],"type":"Point"}
}