{
  "type": "Feature",
  "properties": {
    "iso:country":"ES",
    "sg:address":"Calle de Aledo, 5",
    "sg:city":"Totana",
    "sg:orig_category":"Tapicer\u00cdas",
    "sg:phone":"+34 968 42 27 54",
    "sg:postcode":"30850",
    "sg:province":"Murcia",
    "wof:name":"Ambit Palacios Enrique",
    "wof:placetype":"venue"
},
  "geometry": {"coordinates":[-1.4935367107,37.7735214233],"type":"Point"}
}