{
  "type": "Feature",
  "properties": {
    "iso:country":"ES",
    "sg:address":"Pase Isabel La Catolica, 25",
    "sg:city":"Valladolid",
    "sg:orig_category":"Ense\u00d1anza: Idiomas",
    "sg:phone":"+34 983 37 15 15",
    "sg:postcode":"47003",
    "sg:province":"Valladolid",
    "sg:website":"www.cem-tedisa.com",
    "wof:name":"Tejedor Y Diez S.l.",
    "wof:placetype":"venue"
},
  "geometry": {"coordinates":[-4.7313899994,41.6575775146],"type":"Point"}
}