{
  "type": "Feature",
  "properties": {
    "iso:country":"ES",
    "sg:address":"Avda Pio Xii, 21",
    "sg:city":"Madrid",
    "sg:orig_category":"Servicios Gsm",
    "sg:phone":"+34 913 45 69 81",
    "sg:postcode":"28016",
    "sg:province":"Madrid",
    "wof:name":"Telefonia Y Voz S.l.",
    "wof:placetype":"venue"
},
  "geometry": {"coordinates":[-3.6758260727,40.4632644653],"type":"Point"}
}