{
  "type": "Feature",
  "properties": {
    "iso:country":"ES",
    "sg:address":"Carrer de Sant Julia, 5",
    "sg:city":"Vilafranca Penedes",
    "sg:orig_category":"Molduras, Junquillos, Listones Y Molduras Perforadas",
    "sg:phone":"+34 938 17 02 73",
    "sg:postcode":"08720",
    "sg:province":"Barcelona",
    "wof:name":"Hernandez Coca,carmen",
    "wof:placetype":"venue"
},
  "geometry": {"coordinates":[1.6960769892,41.3454246521],"type":"Point"}
}