{
  "type": "Feature",
  "properties": {
    "iso:country":"ES",
    "sg:address":"Av Jaume I, 64",
    "sg:city":"Pego",
    "sg:orig_category":"Panader\u00cdas, Panader\u00cdas",
    "sg:phone":"+34 965 57 23 05",
    "sg:postcode":"03780",
    "sg:province":"Alicante",
    "wof:name":"Panificadora Pegolina S. L.",
    "wof:placetype":"venue"
},
  "geometry": {"coordinates":[-0.115470998,38.8385162354],"type":"Point"}
}