{
  "type": "Feature",
  "properties": {
    "iso:country":"ES",
    "sg:address":"Ctra. Lumbier, S/n",
    "sg:city":"Aibar",
    "sg:orig_category":"Productores Recolectores, Venta Directa De Vinos",
    "sg:phone":"+34 948 87 70 09",
    "sg:postcode":"31460",
    "sg:province":"Navarra",
    "wof:name":"Bodega Cooperativa Santo Cristo Del Amparo",
    "wof:placetype":"venue"
},
  "geometry": {"coordinates":[-1.3580390215,42.5939445496],"type":"Point"}
}