{
  "type": "Feature",
  "properties": {
    "addr:full":"Cra Trafali\u00d1as-bobar, S/n Bobar Almer\u00eda 04120",
    "addr:housenumber":"s",
    "addr:postcode":"04120",
    "addr:street":"/ N Bobar Almeri\u0301A",
    "iso:country":"ES",
    "sg:address":"Cra Trafali\u00d1as-bobar, S/n",
    "sg:city":"Bobar",
    "sg:orig_category":"Aguas (distribuci\u00d3n, Servicios)",
    "sg:phone":"+34 950 29 30 62",
    "sg:postcode":"04120",
    "sg:province":"Almer\u00eda",
    "wof:name":"Aqualia Gestion Integral Del Agua S.a.",
    "wof:placetype":"venue"
},
  "geometry": {"coordinates":[-2.4679217339,36.8401641846],"type":"Point"}
}