{
  "type": "Feature",
  "properties": {
    "iso:country":"ES",
    "sg:address":"Calle de Pintor Luis Alvarez, 9",
    "sg:city":"Cangas Narcea",
    "sg:orig_category":"Hielo Para Enfriar",
    "sg:phone":"+34 985 81 01 20",
    "sg:postcode":"33800",
    "sg:province":"Asturias",
    "wof:name":"Alonso Amago Enrique",
    "wof:placetype":"venue"
},
  "geometry": {"coordinates":[-6.5515675545,43.1790046692],"type":"Point"}
}