{
  "type": "Feature",
  "properties": {
    "addr:full":"Calle de Juan Ramon Jimenez, 12 Villa Rio C\u00f3rdoba 14640",
    "addr:housenumber":"12",
    "addr:postcode":"14640",
    "addr:street":"Calle De Juan Ramon Jimenez;Rio Co\u0301Rdoba",
    "iso:country":"ES",
    "sg:address":"Calle de Juan Ramon Jimenez, 12",
    "sg:city":"Villa Rio",
    "sg:orig_category":"Servicios Gsm",
    "sg:phone":"+34 957 17 79 65",
    "sg:postcode":"14640",
    "sg:province":"C\u00f3rdoba",
    "wof:name":"Teleur Villa Del Rio S.l.",
    "wof:placetype":"venue"
},
  "geometry": {"coordinates":[-4.2948999405,37.9820671082],"type":"Point"}
}