{
  "type": "Feature",
  "properties": {
    "iso:country":"ES",
    "sg:address":"Pol Ind El Silo, 3",
    "sg:city":"Sta Amalia",
    "sg:orig_category":"Mec\u00c1nico Del Autom\u00d3vil",
    "sg:phone":"+34 924 82 00 15",
    "sg:postcode":"06410",
    "sg:province":"Badajoz",
    "wof:name":"Cerezo Nieto Hector",
    "wof:placetype":"venue"
},
  "geometry": {"coordinates":[-6.0347437859,39.0760536194],"type":"Point"}
}