{
  "type": "Feature",
  "properties": {
    "addr:full":"Rua Algalia De Abaixo (da), 22 Santiago De Compostela La Coru\u00f1a 15704",
    "addr:housenumber":"22",
    "addr:postcode":"15704",
    "addr:street":"Rua Algalia De Abaixo Da;Corun\u0303A",
    "iso:country":"ES",
    "sg:address":"Rua Algalia De Abaixo (da), 22",
    "sg:city":"Santiago De Compostela",
    "sg:orig_category":"Caf\u00c9s, Bares, Cervecer\u00cdas",
    "sg:phone":"+34 981 58 69 86",
    "sg:postcode":"15704",
    "sg:province":"La Coru\u00f1a",
    "wof:name":"Antelo Rivas Mauro",
    "wof:placetype":"venue"
},
  "geometry": {"coordinates":[-8.5418634415,42.8822937012],"type":"Point"}
}