{
  "type": "Feature",
  "properties": {
    "addr:full":"Calle de Mayor, 19 Guadalajara Guadalajara 19001",
    "addr:housenumber":"19",
    "addr:postcode":"19001",
    "addr:street":"Calle De Mayor",
    "iso:country":"ES",
    "sg:address":"Calle de Mayor, 19",
    "sg:city":"Guadalajara",
    "sg:orig_category":"Farmacias",
    "sg:phone":"+34 949 21 10 54",
    "sg:postcode":"19001",
    "sg:province":"Guadalajara",
    "wof:name":"Farmacia Vicenti C.b.",
    "wof:placetype":"venue"
},
  "geometry": {"coordinates":[-3.2711269855,40.7131309509],"type":"Point"}
}