{
  "type": "Feature",
  "properties": {
    "iso:country":"ES",
    "sg:address":"Carr Sant Vicent De Paul (de), 28",
    "sg:city":"Lliria",
    "sg:classifiers":[
        {
            "category":"Autos & Motor Vehicles",
            "subcategory":"Automobile Sales",
            "type":"Retail Goods"
        }
    ],
    "sg:phone":"+34 962 78 03 24",
    "sg:postcode":"46160",
    "sg:province":"Valencia",
    "wof:name":"Grupo Quilez 1964 S.l.",
    "wof:placetype":"venue"
},
  "geometry": {"coordinates":[-0.5973420143,39.6281242371],"type":"Point"}
}