{
  "type": "Feature",
  "properties": {
    "iso:country":"ES",
    "sg:address":"Calle de Monasterio De Siresa, 1",
    "sg:city":"Zaragoza",
    "sg:orig_category":"Carnicer\u00cdas, Carnicer\u00cdas",
    "sg:phone":"+34 976 49 04 48",
    "sg:postcode":"50002",
    "sg:province":"Zaragoza",
    "wof:name":"Acosta Torres Emilio",
    "wof:placetype":"venue"
},
  "geometry": {"coordinates":[-0.8618273139,41.6472740173],"type":"Point"}
}