{
  "type": "Feature",
  "properties": {
    "iso:country":"ES",
    "sg:address":"Calle de Chavarri, 32",
    "sg:city":"Sestao",
    "sg:orig_category":"Peluqueros: De Se\u00d1oras",
    "sg:phone":"+34 944 95 05 49",
    "sg:postcode":"48910",
    "sg:province":"Vizcaya",
    "wof:name":"Maria Del Rosario Calleja Alba",
    "wof:placetype":"venue"
},
  "geometry": {"coordinates":[-3.0066080093,43.31224823],"type":"Point"}
}