{
  "type": "Feature",
  "properties": {
    "addr:full":"Calle de Santa Orosia, 15 Zaragoza Zaragoza 50010",
    "addr:housenumber":"15",
    "addr:postcode":"50010",
    "addr:street":"Calle De Santa Orosia",
    "iso:country":"ES",
    "sg:address":"Calle de Santa Orosia, 15",
    "sg:city":"Zaragoza",
    "sg:orig_category":"Enfermeras: Consultas, Atenci\u00d3n A Domicilio",
    "sg:phone":"+34 976 53 31 13",
    "sg:postcode":"50010",
    "sg:province":"Zaragoza",
    "wof:name":"Garcia Entrena Mercedes",
    "wof:placetype":"venue"
},
  "geometry": {"coordinates":[-0.9030309916,41.6556510925],"type":"Point"}
}