{
  "type": "Feature",
  "properties": {
    "addr:full":"Unidad, 2 La Herradura Granada 18697",
    "addr:postcode":"18697",
    "iso:country":"ES",
    "sg:address":"Unidad, 2",
    "sg:city":"La Herradura",
    "sg:orig_category":"Promotores Constructores",
    "sg:phone":"+34 958 64 01 99",
    "sg:postcode":"18697",
    "sg:province":"Granada",
    "wof:name":"Construcciones Hermanos Camacho De La Herradura S.l.",
    "wof:placetype":"venue"
},
  "geometry": {"coordinates":[-3.7394840717,36.73279953],"type":"Point"}
}