{
  "type": "Feature",
  "properties": {
    "addr:full":"Carrer de Bailen, 112 Barcelona Barcelona 08009",
    "addr:housenumber":"112",
    "addr:postcode":"08009",
    "addr:street":"Carrer De Bailen",
    "iso:country":"ES",
    "sg:address":"Carrer de Bailen, 112",
    "sg:city":"Barcelona",
    "sg:orig_category":"Arquitectos",
    "sg:phone":"+34 934 59 07 64",
    "sg:postcode":"08009",
    "sg:province":"Barcelona",
    "wof:name":"Romero Sabi Jordi",
    "wof:placetype":"venue"
},
  "geometry": {"coordinates":[2.170167923,41.3974761963],"type":"Point"}
}