{
  "type": "Feature",
  "properties": {
    "addr:full":"Calle de Fray Ceferino, 6 Oviedo Asturias 33001",
    "addr:housenumber":"6",
    "addr:postcode":"33001",
    "addr:street":"Calle De Fray Ceferino",
    "iso:country":"ES",
    "sg:address":"Calle de Fray Ceferino, 6",
    "sg:city":"Oviedo",
    "sg:orig_category":"Prendas De Cuero Y De Piel (al Por Menor)",
    "sg:phone":"+34 985 20 45 53",
    "sg:postcode":"33001",
    "sg:province":"Asturias",
    "wof:name":"Oviedo Piel S.l.",
    "wof:placetype":"venue"
},
  "geometry": {"coordinates":[-5.8524188995,43.3652954102],"type":"Point"}
}