{
  "type": "Feature",
  "properties": {
    "addr:full":"Av. Jose Antonio Agirre Lekube, 8 Apatamonasterio Vizcaya 48291",
    "addr:housenumber":"8",
    "addr:postcode":"48291",
    "addr:street":"Av. Jose Antonio Agirre Lekube",
    "iso:country":"ES",
    "sg:address":"Av. Jose Antonio Agirre Lekube, 8",
    "sg:city":"Apatamonasterio",
    "sg:orig_category":"Cristaler\u00cdas",
    "sg:phone":"+34 946 58 28 08",
    "sg:postcode":"48291",
    "sg:province":"Vizcaya",
    "wof:name":"Jose Antonio Y Carmelo Mariscurrena Eizagaechevarria Cb",
    "wof:placetype":"venue"
},
  "geometry": {"coordinates":[-2.5838088989,43.129234314],"type":"Point"}
}