{
  "type": "Feature",
  "properties": {
    "addr:full":"Calle de Elcano, 1 Bilbao Vizcaya 48009",
    "addr:housenumber":"1",
    "addr:postcode":"48009",
    "addr:street":"Calle De Elcano",
    "iso:country":"ES",
    "sg:address":"Calle de Elcano, 1",
    "sg:city":"Bilbao",
    "sg:orig_category":"Inmobiliaria (agencias)",
    "sg:phone":"+34 944 42 02 49",
    "sg:postcode":"48009",
    "sg:province":"Vizcaya",
    "wof:name":"Neinor Nuevos Espacios Industriales Del Norte S.a.",
    "wof:placetype":"venue"
},
  "geometry": {"coordinates":[-2.9363400936,43.2651519775],"type":"Point"}
}