{
  "type": "Feature",
  "properties": {
    "iso:country":"ES",
    "sg:address":"Plaz Palangre (del), 3",
    "sg:city":"Moraira",
    "sg:orig_category":"Centros M\u00c9dicos Y Sociales, Dispensarios",
    "sg:phone":"+34 965 74 51 02",
    "sg:postcode":"03724",
    "sg:province":"Alicante",
    "wof:name":"Augendenia S.r.l",
    "wof:placetype":"venue"
},
  "geometry": {"coordinates":[0.1354586035,38.7000770569],"type":"Point"}
}