{
  "type": "Feature",
  "properties": {
    "addr:full":"Calle de Aduana, 13 Irun Guip\u00f9zcoa 20303",
    "addr:housenumber":"13",
    "addr:postcode":"20303",
    "addr:street":"Calle De Aduana;Guipu\u0300Zcoa",
    "iso:country":"ES",
    "sg:address":"Calle de Aduana, 13",
    "sg:city":"Irun",
    "sg:orig_category":"Abogados",
    "sg:phone":"+34 943 61 96 21",
    "sg:postcode":"20303",
    "sg:province":"Guip\u00f9zcoa",
    "wof:name":"Fernandez De Casadevante Gil-rodrigo, J.a.",
    "wof:placetype":"venue"
},
  "geometry": {"coordinates":[-1.7973792553,43.3400650024],"type":"Point"}
}