{
  "type": "Feature",
  "properties": {
    "addr:full":"Pase Colon De, 9 Donostia-san Sebastian Guip\u00f9zcoa 20002",
    "addr:postcode":"20002",
    "iso:country":"ES",
    "sg:address":"Pase Colon De, 9",
    "sg:city":"Donostia-san Sebastian",
    "sg:orig_category":"Asociaciones Humanitarias, De Cooperaci\u00d3n, De Acci\u00d3n Social",
    "sg:phone":"+34 943 27 66 18",
    "sg:postcode":"20002",
    "sg:province":"Guip\u00f9zcoa",
    "wof:name":"Alcoholicos Anonimos",
    "wof:placetype":"venue"
},
  "geometry": {"coordinates":[-1.9794000387,43.3173789978],"type":"Point"}
}