{
  "type": "Feature",
  "properties": {
    "iso:country":"ES",
    "sg:address":"Calle de Cristobal Colon, 25",
    "sg:city":"Viso",
    "sg:orig_category":"Peluqueros: De Se\u00d1oras",
    "sg:phone":"+34 957 12 73 97",
    "sg:postcode":"14470",
    "sg:province":"C\u00f3rdoba",
    "wof:name":"Leon Garcia Jose Ramon",
    "wof:placetype":"venue"
},
  "geometry": {"coordinates":[-4.9567055702,38.4827194214],"type":"Point"}
}