{
  "type": "Feature",
  "properties": {
    "addr:full":"Calle de Trafalgar, 12 Conil De La Frontera C\u00e1diz 11140",
    "addr:housenumber":"12",
    "addr:postcode":"11140",
    "addr:street":"Calle De Trafalgar",
    "iso:country":"ES",
    "sg:address":"Calle de Trafalgar, 12",
    "sg:city":"Conil De La Frontera",
    "sg:orig_category":"Alimentaci\u00d3n General (al Por Menor)",
    "sg:phone":"+34 956 44 12 23",
    "sg:postcode":"11140",
    "sg:province":"C\u00e1diz",
    "wof:name":"Barroso Leal Manuel",
    "wof:placetype":"venue"
},
  "geometry": {"coordinates":[-6.0878109932,36.279750824],"type":"Point"}
}