{
  "type": "Feature",
  "properties": {
    "iso:country":"ES",
    "sg:address":"Ctra Barcelona, 166",
    "sg:city":"Cerdanyola Valles",
    "sg:orig_category":"Venta, Instalaci\u00d3n De Calefacci\u00d3n",
    "sg:phone":"+34 936 92 20 23",
    "sg:postcode":"08290",
    "sg:province":"Barcelona",
    "wof:name":"Asbert Carcas S.l.",
    "wof:placetype":"venue"
},
  "geometry": {"coordinates":[2.1473066807,41.493927002],"type":"Point"}
}