{
  "type": "Feature",
  "properties": {
    "iso:country":"ES",
    "sg:address":"Cantera Errepidea, S/n",
    "sg:city":"Asua-lauroeta",
    "sg:orig_category":"Trabajos De Perforaciones, Sondeos, Construcci\u00d3n De Pozos",
    "sg:phone":"+34 944 53 16 61",
    "sg:postcode":"48950",
    "sg:province":"Vizcaya",
    "wof:name":"Aroa Geotecnia Sll",
    "wof:placetype":"venue"
},
  "geometry": {"coordinates":[-2.945704937,43.2983398438],"type":"Point"}
}