{
  "type": "Feature",
  "properties": {
    "addr:full":"Calle de Triste Condesa, 18 Arenas San Pedro \u00c1vila 05400",
    "addr:housenumber":"18",
    "addr:postcode":"05400",
    "addr:street":"Calle De Triste Condesa;A\u0301Vila",
    "iso:country":"ES",
    "sg:address":"Calle de Triste Condesa, 18",
    "sg:city":"Arenas San Pedro",
    "sg:classifiers":[
        {
            "category":"Taxi",
            "type":"Transportation"
        }
    ],
    "sg:phone":"+34 920 37 09 67",
    "sg:postcode":"05400",
    "sg:province":"\u00c1vila",
    "wof:name":"Garcia Blazquez Jaime",
    "wof:placetype":"venue"
},
  "geometry": {"coordinates":[-5.0887489319,40.2098312378],"type":"Point"}
}