{
  "type": "Feature",
  "properties": {
    "addr:full":"Calle de Pedreras, 174 Linea De La Concepcion C\u00e1diz 11300",
    "addr:housenumber":"174",
    "addr:postcode":"11300",
    "addr:street":"Calle De Pedreras;Ca\u0301Diz",
    "iso:country":"ES",
    "sg:address":"Calle de Pedreras, 174",
    "sg:city":"Linea De La Concepcion",
    "sg:orig_category":"Centros De Educaci\u00d3n Especial",
    "sg:phone":"+34 956 76 68 03",
    "sg:postcode":"11300",
    "sg:province":"C\u00e1diz",
    "wof:name":"Junta De Andalucia",
    "wof:placetype":"venue"
},
  "geometry": {"coordinates":[-5.3563890457,36.1696586609],"type":"Point"}
}