{
  "type": "Feature",
  "properties": {
    "iso:country":"ES",
    "sg:address":"Rbla Girada (la), 33",
    "sg:city":"Vilafranca Penedes",
    "sg:orig_category":"Inform\u00c1tica (estudios, Servicios, Asesor\u00cda, Formaci\u00d3n)",
    "sg:phone":"+34 938 17 12 53",
    "sg:postcode":"08720",
    "sg:province":"Barcelona",
    "wof:name":"Horno Espirall S. A.",
    "wof:placetype":"venue"
},
  "geometry": {"coordinates":[1.7020299435,41.3395004272],"type":"Point"}
}