{
  "type": "Feature",
  "properties": {
    "iso:country":"ES",
    "sg:address":"Calle de Manzano, 3",
    "sg:city":"Tentegorra",
    "sg:orig_category":"Caf\u00c9s, Bares, Cervecer\u00cdas",
    "sg:phone":"+34 968 16 24 11",
    "sg:postcode":"30394",
    "sg:province":"Murcia",
    "wof:name":"Mayoral Morales Y Solana S.l",
    "wof:placetype":"venue"
},
  "geometry": {"coordinates":[-1.0402289629,37.6125068665],"type":"Point"}
}