{
  "type": "Feature",
  "properties": {
    "addr:full":"Calle de Escuelas (las), 1 Peal Becerro Ja\u00e9n 23460",
    "addr:housenumber":"1",
    "addr:postcode":"23460",
    "addr:street":"Calle De Escuelas Las",
    "iso:country":"ES",
    "sg:address":"Calle de Escuelas (las), 1",
    "sg:city":"Peal Becerro",
    "sg:orig_category":"Formaci\u00d3n Continuada (variada)",
    "sg:phone":"+34 953 71 63 09",
    "sg:postcode":"23460",
    "sg:province":"Ja\u00e9n",
    "wof:name":"Asesoria Gomez Y Saucedo S.l.",
    "wof:placetype":"venue"
},
  "geometry": {"coordinates":[-3.119533062,37.9149208069],"type":"Point"}
}