{
  "type": "Feature",
  "properties": {
    "addr:full":"Pl Sant Vicen\u00c7 De Sarria, 1 Barcelona Barcelona 08017",
    "addr:housenumber":"1",
    "addr:postcode":"08017",
    "addr:street":"Pl Sant Vicenc\u0327;Sarria",
    "iso:country":"ES",
    "sg:address":"Pl Sant Vicen\u00c7 De Sarria, 1",
    "sg:city":"Barcelona",
    "sg:orig_category":"Molduras, Junquillos, Listones Y Molduras Perforadas",
    "sg:phone":"+34 932 03 10 52",
    "sg:postcode":"08017",
    "sg:province":"Barcelona",
    "wof:name":"Soler Bono Xavier",
    "wof:placetype":"venue"
},
  "geometry": {"coordinates":[2.1240649223,41.3972053528],"type":"Point"}
}