{
  "type": "Feature",
  "properties": {
    "iso:country":"ES",
    "sg:address":"Calle de Menendez Pelayo, 15",
    "sg:city":"Abaran",
    "sg:orig_category":"Promotores Constructores",
    "sg:phone":"+34 968 45 04 80",
    "sg:postcode":"30550",
    "sg:province":"Murcia",
    "wof:name":"Construcciones Gea Candel S.l.",
    "wof:placetype":"venue"
},
  "geometry": {"coordinates":[-1.4014810324,38.2021560669],"type":"Point"}
}