{
  "type": "Feature",
  "properties": {
    "iso:country":"ES",
    "sg:address":"Plaz Espa\u00d1a, 1",
    "sg:city":"Aldeacentenera",
    "sg:orig_category":"Administraciones Regionales, Departamentales Y Locales",
    "sg:phone":"+34 927 31 40 27",
    "sg:postcode":"10251",
    "sg:province":"C\u00e1ceres",
    "wof:name":"Ayuntamiento De Aldeacentenera",
    "wof:placetype":"venue"
},
  "geometry": {"coordinates":[-5.6247668266,39.5366325378],"type":"Point"}
}