{
  "type": "Feature",
  "properties": {
    "addr:full":"Calle de Carniceros, 6 Valencia Valencia 46001",
    "addr:housenumber":"6",
    "addr:postcode":"46001",
    "addr:street":"Calle De Carniceros",
    "iso:country":"ES",
    "sg:address":"Calle de Carniceros, 6",
    "sg:city":"Valencia",
    "sg:orig_category":"Internados & Ense\u00d1anza Privada",
    "sg:phone":"+34 963 91 58 00",
    "sg:postcode":"46001",
    "sg:province":"Valencia",
    "wof:name":"Colegio Escuelas Pias",
    "wof:placetype":"venue"
},
  "geometry": {"coordinates":[-0.3821145892,39.473815918],"type":"Point"}
}