{
  "type": "Feature",
  "properties": {
    "iso:country":"ES",
    "sg:address":"Avda Europa, S/n",
    "sg:city":"Vista Alegre",
    "sg:orig_category":"M\u00c9dicos: Medicina General Orientada A La Homeopat\u00cda",
    "sg:phone":"+34 968 24 87 79",
    "sg:postcode":"30007",
    "sg:province":"Murcia",
    "wof:name":"Castejon Valero Pedro",
    "wof:placetype":"venue"
},
  "geometry": {"coordinates":[-1.1324989796,37.9974899292],"type":"Point"}
}