{
  "type": "Feature",
  "properties": {
    "iso:country":"ES",
    "sg:address":"Cmno Iriepal (taracena), S/n",
    "sg:city":"Taracena",
    "sg:orig_category":"Empresas De Desmonte",
    "sg:phone":"+34 949 22 03 66",
    "sg:postcode":"19193",
    "sg:province":"Guadalajara",
    "wof:name":"Desmontes Parejo S.l.",
    "wof:placetype":"venue"
},
  "geometry": {"coordinates":[-3.1264579296,40.6521148682],"type":"Point"}
}