{
  "type": "Feature",
  "properties": {
    "addr:full":"Calle de Hospital, 2 Do\u00e7a Mencia C\u00f3rdoba 14860",
    "addr:housenumber":"2",
    "addr:postcode":"14860",
    "addr:street":"Calle De Hospital;Co\u0301Rdoba",
    "iso:country":"ES",
    "sg:address":"Calle de Hospital, 2",
    "sg:city":"Do\u00e7a Mencia",
    "sg:orig_category":"Papeler\u00cdas, Librer\u00cdas",
    "sg:phone":"+34 957 67 60 69",
    "sg:postcode":"14860",
    "sg:province":"C\u00f3rdoba",
    "wof:name":"Salamanca Cubero Jacinto",
    "wof:placetype":"venue"
},
  "geometry": {"coordinates":[-4.3583540916,37.55493927],"type":"Point"}
}