{
  "type": "Feature",
  "properties": {
    "iso:country":"ES",
    "sg:address":"Poli Poligono Industrial Chinales, S/n",
    "sg:city":"Cordoba",
    "sg:orig_category":"Empresas De Carpinter\u00cda",
    "sg:phone":"+34 957 27 29 08",
    "sg:postcode":"14007",
    "sg:province":"C\u00f3rdoba",
    "wof:name":"El Arcangel Industrias Metalicas S. L.",
    "wof:placetype":"venue"
},
  "geometry": {"coordinates":[-4.7784028053,37.8779411316],"type":"Point"}
}