{
  "type": "Feature",
  "properties": {
    "iso:country":"ES",
    "sg:address":"Psaj Federico Garcia Lorca, 4",
    "sg:city":"Alhaurin Torre",
    "sg:orig_category":"Dibujantes (diversos)",
    "sg:phone":"+34 952 96 38 99",
    "sg:postcode":"29130",
    "sg:province":"M\u00e1laga",
    "wof:name":"Pollio  Marcos David",
    "wof:placetype":"venue"
},
  "geometry": {"coordinates":[-4.5667190552,36.6618614197],"type":"Point"}
}