{
  "type": "Feature",
  "properties": {
    "addr:full":"Avda Fuente Vieja, 6 Torresandino Burgos 09310",
    "addr:housenumber":"6",
    "addr:postcode":"09310",
    "addr:street":"Avda Fuente Vieja",
    "iso:country":"ES",
    "sg:address":"Avda Fuente Vieja, 6",
    "sg:city":"Torresandino",
    "sg:orig_category":"Cajas Para Embalar",
    "sg:phone":"+34 947 55 11 53",
    "sg:postcode":"09310",
    "sg:province":"Burgos",
    "wof:name":"Caja Rural De Burgos",
    "wof:placetype":"venue"
},
  "geometry": {"coordinates":[-3.9130671024,41.8284339905],"type":"Point"}
}