{
  "type": "Feature",
  "properties": {
    "iso:country":"ES",
    "sg:address":"Calle de Zabaleta, 5",
    "sg:city":"Donostia-san Sebastian",
    "sg:orig_category":"Iglesia Cat\u00d3lica",
    "sg:phone":"+34 943 28 50 00",
    "sg:postcode":"20002",
    "sg:province":"Guip\u00f9zcoa",
    "wof:name":"Obispado De San Sebastian",
    "wof:placetype":"venue"
},
  "geometry": {"coordinates":[-1.9765870571,43.3229598999],"type":"Point"}
}