{
  "type": "Feature",
  "properties": {
    "addr:full":"Calle de Soldevila, 9 Canet Lo Roig Castell\u00f3n 12350",
    "addr:housenumber":"9",
    "addr:postcode":"12350",
    "addr:street":"Calle De Soldevila",
    "iso:country":"ES",
    "sg:address":"Calle de Soldevila, 9",
    "sg:city":"Canet Lo Roig",
    "sg:orig_category":"Poller\u00cda Y Caza (al Por Menor)",
    "sg:phone":"+34 964 49 41 93",
    "sg:postcode":"12350",
    "sg:province":"Castell\u00f3n",
    "wof:name":"Salvador Vives Antonio",
    "wof:placetype":"venue"
},
  "geometry": {"coordinates":[0.2431010008,40.55052948],"type":"Point"}
}