{
  "type": "Feature",
  "properties": {
    "addr:full":"Avda Arcadio Pardi\u00d1as, 28 Burela Lugo 27880",
    "addr:housenumber":"28",
    "addr:postcode":"27880",
    "addr:street":"Avda Arcadio Pardin\u0303As",
    "iso:country":"ES",
    "sg:address":"Avda Arcadio Pardi\u00d1as, 28",
    "sg:city":"Burela",
    "sg:orig_category":"Postigos, Persianas Y Celos\u00cdas",
    "sg:phone":"+34 982 58 56 63",
    "sg:postcode":"27880",
    "sg:province":"Lugo",
    "wof:name":"Segade Dopazo Luis",
    "wof:placetype":"venue"
},
  "geometry": {"coordinates":[-7.355670929,43.6528549194],"type":"Point"}
}