{
  "type": "Feature",
  "properties": {
    "iso:country":"ES",
    "sg:address":"Calle de Aranda De Duero, 6",
    "sg:city":"Burgos",
    "sg:orig_category":"Farmacias",
    "sg:phone":"+34 947 26 27 77",
    "sg:postcode":"09002",
    "sg:province":"Burgos",
    "wof:name":"Torrijo Araoz Ramiro",
    "wof:placetype":"venue"
},
  "geometry": {"coordinates":[-3.7007043362,42.3375205994],"type":"Point"}
}