{
  "type": "Feature",
  "properties": {
    "addr:full":"Ctra Malaga (de), 146 Balanegra Almer\u00eda 04713",
    "addr:housenumber":"146",
    "addr:postcode":"04713",
    "addr:street":"Ctra Malaga De;Almeri\u0301A",
    "iso:country":"ES",
    "sg:address":"Ctra Malaga (de), 146",
    "sg:city":"Balanegra",
    "sg:orig_category":"Flores Y Plantas Naturales (al Por Mayor)",
    "sg:phone":"+34 950 40 63 88",
    "sg:postcode":"04713",
    "sg:province":"Almer\u00eda",
    "wof:name":"Camarena Melia Maria De Los Angeles",
    "wof:placetype":"venue"
},
  "geometry": {"coordinates":[-2.9070239067,36.7499694824],"type":"Point"}
}