{
  "type": "Feature",
  "properties": {
    "addr:full":"Calle de Rincon De La Victoria, 4 Madrid Madrid 28018",
    "addr:housenumber":"4",
    "addr:postcode":"28018",
    "addr:street":"Calle De Rincon De La Victoria",
    "iso:country":"ES",
    "sg:address":"Calle de Rincon De La Victoria, 4",
    "sg:city":"Madrid",
    "sg:orig_category":"Molduras, Junquillos, Listones Y Molduras Perforadas",
    "sg:phone":"+34 913 03 71 55",
    "sg:postcode":"28018",
    "sg:province":"Madrid",
    "wof:name":"Blazquez Calvo Francisco",
    "wof:placetype":"venue"
},
  "geometry": {"coordinates":[-3.6421859264,40.384098053],"type":"Point"}
}