{
  "type": "Feature",
  "properties": {
    "addr:full":"Avda Martires (de Los), 10 Montiel Ciudad Real 13326",
    "addr:housenumber":"10",
    "addr:postcode":"13326",
    "addr:street":"Avda Martires De Los",
    "iso:country":"ES",
    "sg:address":"Avda Martires (de Los), 10",
    "sg:city":"Montiel",
    "sg:orig_category":"Cajas Para Embalar",
    "sg:phone":"+34 926 35 30 92",
    "sg:postcode":"13326",
    "sg:province":"Ciudad Real",
    "sg:website":"www.ruralvia.es",
    "wof:name":"Caja Rural De Ciudad Real",
    "wof:placetype":"venue"
},
  "geometry": {"coordinates":[-2.8635780811,38.6974105835],"type":"Point"}
}