{
  "type": "Feature",
  "properties": {
    "addr:full":"Carr Sant Josep, 15 Sueca Valencia 46410",
    "addr:housenumber":"15",
    "addr:postcode":"46410",
    "addr:street":"Carr Sant Josep",
    "iso:country":"ES",
    "sg:address":"Carr Sant Josep, 15",
    "sg:city":"Sueca",
    "sg:orig_category":"Producci\u00d3n, Venta De Productos De Agricultura Biol\u00d3gica",
    "sg:phone":"+34 961 70 24 86",
    "sg:postcode":"46410",
    "sg:province":"Valencia",
    "wof:name":"Cutanda Perales Constancio",
    "wof:placetype":"venue"
},
  "geometry": {"coordinates":[-0.3128780127,39.201751709],"type":"Point"}
}