{
  "type": "Feature",
  "properties": {
    "addr:full":"Avda Pilos (dos), 8 Chantada Lugo 27500",
    "addr:housenumber":"8",
    "addr:postcode":"27500",
    "addr:street":"Avda Pilos Dos",
    "iso:country":"ES",
    "sg:address":"Avda Pilos (dos), 8",
    "sg:city":"Chantada",
    "sg:orig_category":"Alimentaci\u00d3n General (al Por Mayor)",
    "sg:phone":"+34 982 44 02 13",
    "sg:postcode":"27500",
    "sg:province":"Lugo",
    "wof:name":"Agrocampo Chantada S.l.",
    "wof:placetype":"venue"
},
  "geometry": {"coordinates":[-7.7960119247,42.6083450317],"type":"Point"}
}