{
  "type": "Feature",
  "properties": {
    "addr:full":"Calle de Condal, 83 Nerja M\u00e1laga 29780",
    "addr:housenumber":"83",
    "addr:postcode":"29780",
    "addr:street":"Calle De Condal",
    "iso:country":"ES",
    "sg:address":"Calle de Condal, 83",
    "sg:city":"Nerja",
    "sg:orig_category":"Abogados",
    "sg:phone":"+34 952 52 51 78",
    "sg:postcode":"29780",
    "sg:province":"M\u00e1laga",
    "wof:name":"Aranda Lopez Jose Denis",
    "wof:placetype":"venue"
},
  "geometry": {"coordinates":[-3.8741679192,36.7585411072],"type":"Point"}
}