{
  "type": "Feature",
  "properties": {
    "iso:country":"ES",
    "sg:address":"Calle de Monturiol, 13",
    "sg:city":"Grao",
    "sg:orig_category":"Empresas De Carpinter\u00cda De Madera",
    "sg:phone":"+34 964 28 60 09",
    "sg:postcode":"12100",
    "sg:province":"Castell\u00f3n",
    "wof:name":"Fusteria Rama Coop.valenciana Ltda.",
    "wof:placetype":"venue"
},
  "geometry": {"coordinates":[0.0176999997,39.9888801575],"type":"Point"}
}