{
  "type": "Feature",
  "properties": {
    "iso:country":"ES",
    "sg:address":"Calle de Murillo, 4",
    "sg:city":"Barakaldo",
    "sg:orig_category":"Empresas De Vigilancia, Guardia Y Protecci\u00d3n",
    "sg:phone":"+34 944 04 36 41",
    "sg:postcode":"48902",
    "sg:province":"Vizcaya",
    "wof:name":"Presercom 99. S.l",
    "wof:placetype":"venue"
},
  "geometry": {"coordinates":[-2.9985830784,43.2952575684],"type":"Point"}
}