{
  "type": "Feature",
  "properties": {
    "iso:country":"ES",
    "sg:address":"Calle de San Martin, S/n",
    "sg:city":"Paternain",
    "sg:orig_category":"Ebanister\u00cda",
    "sg:phone":"+34 948 35 31 41",
    "sg:postcode":"31190",
    "sg:province":"Navarra",
    "wof:name":"Mayayo Jimenez Juan Ignacio",
    "wof:placetype":"venue"
},
  "geometry": {"coordinates":[-1.7443486452,42.7848777771],"type":"Point"}
}