{
  "type": "Feature",
  "properties": {
    "addr:full":"Calle de Ministro Cornel, 2 Benasque Huesca 22440",
    "addr:housenumber":"2",
    "addr:postcode":"22440",
    "addr:street":"Calle De Ministro Cornel",
    "iso:country":"ES",
    "sg:address":"Calle de Ministro Cornel, 2",
    "sg:city":"Benasque",
    "sg:orig_category":"Molduras, Junquillos, Listones Y Molduras Perforadas",
    "sg:phone":"+34 974 55 20 92",
    "sg:postcode":"22440",
    "sg:province":"Huesca",
    "wof:name":"Saura Ballarin Jose Andres",
    "wof:placetype":"venue"
},
  "geometry": {"coordinates":[0.5240640044,42.6053009033],"type":"Point"}
}