{
  "type": "Feature",
  "properties": {
    "addr:full":"Cno. A. Molinos, S/n Baza Granada 18800",
    "addr:housenumber":"s",
    "addr:postcode":"18800",
    "addr:street":"Cno. A. Molinos;/ N",
    "iso:country":"ES",
    "sg:address":"Cno. A. Molinos, S/n",
    "sg:city":"Baza",
    "sg:orig_category":"Producci\u00d3n, Venta De Productos De Agricultura Biol\u00d3gica",
    "sg:phone":"+34 958 70 22 58",
    "sg:postcode":"18800",
    "sg:province":"Granada",
    "wof:name":"Agroganaderas Hermanos Valeros S.c.a.",
    "wof:placetype":"venue"
},
  "geometry": {"coordinates":[-2.771873951,37.4827575684],"type":"Point"}
}