{
  "type": "Feature",
  "properties": {
    "addr:full":"Pase Muro (del), 41 Ejea De Los Caballeros Zaragoza 50600",
    "addr:postcode":"50600",
    "addr:street":"Del",
    "iso:country":"ES",
    "sg:address":"Pase Muro (del), 41",
    "sg:city":"Ejea De Los Caballeros",
    "sg:orig_category":"Estancos",
    "sg:phone":"+34 976 66 78 29",
    "sg:postcode":"50600",
    "sg:province":"Zaragoza",
    "wof:name":"Alastuey Gimenez Teresa",
    "wof:placetype":"venue"
},
  "geometry": {"coordinates":[-1.1365014315,42.1257247925],"type":"Point"}
}