{
  "type": "Feature",
  "properties": {
    "addr:full":"Calle de Mezquita, 11 Madrid Madrid 28041",
    "addr:housenumber":"11",
    "addr:postcode":"madrid;28041",
    "addr:street":"Calle De Mezquita",
    "iso:country":"ES",
    "sg:address":"Calle de Mezquita, 11",
    "sg:city":"Madrid",
    "sg:orig_category":"Bazares, Art\u00cdculos De Limpieza Y De Cocina (al Por Menor)",
    "sg:phone":"+34 917 92 15 85",
    "sg:postcode":"28041",
    "sg:province":"Madrid",
    "wof:name":"Mayoral Molinero Leoncio",
    "wof:placetype":"venue"
},
  "geometry": {"coordinates":[-3.6905810833,40.3737487793],"type":"Point"}
}