{
  "type": "Feature",
  "properties": {
    "addr:full":"V\u00e9lez, 2 Almu\u00f1ecar Granada 18690",
    "addr:housenumber":"2",
    "addr:postcode":"18690",
    "addr:street":"Ve\u0301Lez",
    "iso:country":"ES",
    "sg:address":"V\u00e9lez, 2",
    "sg:city":"Almu\u00f1ecar",
    "sg:orig_category":"Telas Y Sedas (al Por Menor)",
    "sg:phone":"+34 958 63 10 72",
    "sg:postcode":"18690",
    "sg:province":"Granada",
    "wof:name":"Campos Cortes Jose",
    "wof:placetype":"venue"
},
  "geometry": {"coordinates":[-3.6914548874,36.7338294983],"type":"Point"}
}