{
  "type": "Feature",
  "properties": {
    "iso:country":"ES",
    "sg:address":"Carrer de Casanova, 103",
    "sg:city":"Barcelona",
    "sg:orig_category":"Agencias De Viajes",
    "sg:phone":"+34 933 23 90 86",
    "sg:postcode":"08011",
    "sg:province":"Barcelona",
    "wof:name":"Escardo & Franquesa S.l.",
    "wof:placetype":"venue"
},
  "geometry": {"coordinates":[2.1561899185,41.3873405457],"type":"Point"}
}