{
  "type": "Feature",
  "properties": {
    "addr:full":"Pase Alparrache (del), 18 Navalcarnero Madrid 28600",
    "addr:postcode":"28600",
    "iso:country":"ES",
    "sg:address":"Pase Alparrache (del), 18",
    "sg:city":"Navalcarnero",
    "sg:orig_category":"Promotores Constructores",
    "sg:phone":"+34 918 11 54 91",
    "sg:postcode":"28600",
    "sg:province":"Madrid",
    "wof:name":"Garcisan Construcciones Y Reformas Sl",
    "wof:placetype":"venue"
},
  "geometry": {"coordinates":[-4.0077986717,40.2899169922],"type":"Point"}
}