{
  "type": "Feature",
  "properties": {
    "addr:full":"Ctra General C-830 Izquierda, 34 Sauces Santa Cruz De Tenerife 38720",
    "addr:housenumber":"34",
    "addr:postcode":"38720",
    "addr:street":"Ctra General C-830 Izquierda",
    "iso:country":"ES",
    "sg:address":"Ctra General C-830 Izquierda, 34",
    "sg:city":"Sauces",
    "sg:orig_category":"Venta, Montaje De Neum\u00c1ticos",
    "sg:phone":"+34 922 45 15 75",
    "sg:postcode":"38720",
    "sg:province":"Santa Cruz De Tenerife",
    "sg:website":"www.vultesa.com",
    "wof:name":"Vultesa S.l.",
    "wof:placetype":"venue"
},
  "geometry": {"coordinates":[-17.7736644745,28.8064670563],"type":"Point"}
}