{
  "type": "Feature",
  "properties": {
    "addr:full":"Pl Diego De Leon, 6 Camarles Tarragona 43894",
    "addr:housenumber":"6",
    "addr:postcode":"43894",
    "addr:street":"Pl Diego De Leon",
    "iso:country":"ES",
    "sg:address":"Pl Diego De Leon, 6",
    "sg:city":"Camarles",
    "sg:orig_category":"Quincaller\u00cda (al Por Menor)",
    "sg:phone":"+34 977 47 03 51",
    "sg:postcode":"43894",
    "sg:province":"Tarragona",
    "wof:name":"Subministres Industrials Camarles S.l",
    "wof:placetype":"venue"
},
  "geometry": {"coordinates":[0.6708999872,40.7714042664],"type":"Point"}
}