{
  "type": "Feature",
  "properties": {
    "iso:country":"ES",
    "sg:address":"Carr Maigmo (el), 10",
    "sg:city":"Almafra",
    "sg:orig_category":"Cueros Y Pieles (al Por Mayor)",
    "sg:phone":"+34 966 95 29 32",
    "sg:postcode":"03610",
    "sg:province":"Alicante",
    "wof:name":"Comercial Terrelda S L",
    "wof:placetype":"venue"
},
  "geometry": {"coordinates":[-0.7731289864,38.4793281555],"type":"Point"}
}