{
  "type": "Feature",
  "properties": {
    "addr:full":"Carrer de Cala Estancia, 6 Can Pastilla Islas Baleares 07610",
    "addr:housenumber":"6",
    "addr:postcode":"07610",
    "addr:street":"Carrer De Cala Estancia",
    "iso:country":"ES",
    "sg:address":"Carrer de Cala Estancia, 6",
    "sg:city":"Can Pastilla",
    "sg:orig_category":"Asilos De Ancianos. Centros Privados",
    "sg:phone":"+34 971 26 00 03",
    "sg:postcode":"07610",
    "sg:province":"Islas Baleares",
    "wof:name":"Mendez Trincado Ana Isabel",
    "wof:placetype":"venue"
},
  "geometry": {"coordinates":[2.7150061131,39.5368690491],"type":"Point"}
}