{
  "type": "Feature",
  "properties": {
    "addr:full":"Calle de Bailen, 16 Alzira Valencia 46600",
    "addr:housenumber":"16",
    "addr:postcode":"46600",
    "addr:street":"Calle De Bailen",
    "iso:country":"ES",
    "sg:address":"Calle de Bailen, 16",
    "sg:city":"Alzira",
    "sg:orig_category":"Muebles, Minoristas",
    "sg:phone":"+34 962 41 19 46",
    "sg:postcode":"46600",
    "sg:province":"Valencia",
    "wof:name":"Carpena Martinez Jose",
    "wof:placetype":"venue"
},
  "geometry": {"coordinates":[-0.4348888099,39.1491737366],"type":"Point"}
}