{
  "type": "Feature",
  "properties": {
    "addr:full":"Calle de Sierra De Albarracin (de La), 11 Poligono De San Fernando De Henares Madrid 28830",
    "addr:housenumber":"11 poligono",
    "addr:postcode":"28830",
    "addr:street":"Calle De Sierra De Albarracin De La",
    "iso:country":"ES",
    "sg:address":"Calle de Sierra De Albarracin (de La), 11",
    "sg:city":"Poligono De San Fernando De Henares",
    "sg:orig_category":"Fabricaci\u00d3n Y Venta De Autocares Y Autobuses",
    "sg:phone":"+34 916 75 81 17",
    "sg:postcode":"28830",
    "sg:province":"Madrid",
    "wof:name":"Four-two-cleans S.l.",
    "wof:placetype":"venue"
},
  "geometry": {"coordinates":[-3.509059906,40.449836731],"type":"Point"}
}