{
  "type": "Feature",
  "properties": {
    "addr:full":"Los Cercados, S/n Cercados Ara\u00f1a Las Palmas 35290",
    "addr:housenumber":"s / n",
    "addr:postcode":"35290",
    "addr:street":"Los Cercados;Cercados Aran\u0303A Las Palmas",
    "iso:country":"ES",
    "sg:address":"Los Cercados, S/n",
    "sg:city":"Cercados Ara\u00f1a",
    "sg:orig_category":"Promotores Constructores",
    "sg:phone":"+34 928 12 90 09",
    "sg:postcode":"35290",
    "sg:province":"Las Palmas",
    "wof:name":"Winzinger S.l.",
    "wof:placetype":"venue"
},
  "geometry": {"coordinates":[-15.4300060272,28.1248226166],"type":"Point"}
}