{
  "type": "Feature",
  "properties": {
    "iso:country":"ES",
    "sg:address":"Calle de Sebastian Elcano, 15",
    "sg:city":"Zamora",
    "sg:orig_category":"Peluqueros: De Se\u00d1oras",
    "sg:phone":"+34 980 67 20 63",
    "sg:postcode":"49020",
    "sg:province":"Zamora",
    "wof:name":"Refoyo Llamas Pascuala",
    "wof:placetype":"venue"
},
  "geometry": {"coordinates":[-5.7301750183,41.5080413818],"type":"Point"}
}