{
  "type": "Feature",
  "properties": {
    "addr:full":"Antoni Frontera, 2 Portol Islas Baleares 07141",
    "addr:housenumber":"2",
    "addr:postcode":"07141",
    "addr:street":"Frontera;Islas",
    "iso:country":"ES",
    "sg:address":"Antoni Frontera, 2",
    "sg:city":"Portol",
    "sg:orig_category":"Textil",
    "sg:phone":"+34 971 60 20 32",
    "sg:postcode":"07141",
    "sg:province":"Islas Baleares",
    "wof:name":"Bonjoc Germans S.l.",
    "wof:placetype":"venue"
},
  "geometry": {"coordinates":[2.7445349693,39.6195487976],"type":"Point"}
}