{
  "type": "Feature",
  "properties": {
    "addr:full":"Avda Emilio Castelar, 72 S. Pedro Pinatar Murcia 30740",
    "addr:housenumber":"72",
    "addr:postcode":"30740",
    "addr:street":"Avda Emilio Castelar",
    "iso:country":"ES",
    "sg:address":"Avda Emilio Castelar, 72",
    "sg:city":"S. Pedro Pinatar",
    "sg:orig_category":"Cajas De Ahorro",
    "sg:phone":"+34 968 17 83 09",
    "sg:postcode":"30740",
    "sg:province":"Murcia",
    "wof:name":"Cajamar",
    "wof:placetype":"venue"
},
  "geometry": {"coordinates":[-0.7894250154,37.8320198059],"type":"Point"}
}