{
  "type": "Feature",
  "properties": {
    "iso:country":"ES",
    "sg:address":"Calle de Gravina, 3",
    "sg:city":"Huelva",
    "sg:orig_category":"\u00d3ptica: Instrumentos (fabricaci\u00d3n)",
    "sg:phone":"+34 959 24 86 70",
    "sg:postcode":"21001",
    "sg:province":"Huelva",
    "wof:name":"Centro Vision Urbano S.l.",
    "wof:placetype":"venue"
},
  "geometry": {"coordinates":[-6.9548721313,37.257396698],"type":"Point"}
}