{
  "type": "Feature",
  "properties": {
    "addr:full":"Urb Prado Robledo, S/n Piedralaves \u00c1vila 05440",
    "addr:housenumber":"s / n",
    "addr:postcode":"05440",
    "addr:street":"Urb Prado Robledo",
    "iso:country":"ES",
    "sg:address":"Urb Prado Robledo, S/n",
    "sg:city":"Piedralaves",
    "sg:orig_category":"Fabricaci\u00d3n De Bordados, Encajes Y Tules",
    "sg:phone":"+34 918 66 51 07",
    "sg:postcode":"05440",
    "sg:province":"\u00c1vila",
    "wof:name":"La Encajera Del Tietar S.a.",
    "wof:placetype":"venue"
},
  "geometry": {"coordinates":[-4.6928429604,40.3156967163],"type":"Point"}
}