{
  "type": "Feature",
  "properties": {
    "iso:country":"ES",
    "sg:address":"Calle de Real, 7",
    "sg:city":"Ugena",
    "sg:orig_category":"Puros, Cigarrillos Y Tabaco (al Por Menor)",
    "sg:phone":"+34 925 53 30 40",
    "sg:postcode":"45217",
    "sg:province":"Toledo",
    "wof:name":"Navarro Del Barrio Alfonso",
    "wof:placetype":"venue"
},
  "geometry": {"coordinates":[-3.878123045,40.155620575],"type":"Point"}
}