{
  "type": "Feature",
  "properties": {
    "iso:country":"ES",
    "sg:address":"Carr Metge Antoni Serra, Del, S/n",
    "sg:city":"Eivissa",
    "sg:classifiers":[
        {
            "category":"Cinema",
            "subcategory":"Movie Theater",
            "type":"Entertainment"
        }
    ],
    "sg:phone":"+34 971 39 25 58",
    "sg:postcode":"07800",
    "sg:province":"Islas Baleares",
    "sg:tags":[
        "salas",
        "de",
        "cine"
    ],
    "wof:name":"Cines Serra S.l.",
    "wof:placetype":"venue"
},
  "geometry": {"coordinates":[1.4313800335,38.9098892212],"type":"Point"}
}