{
  "type": "Feature",
  "properties": {
    "addr:full":"Basarte Area, S/n Azpeitia Guip\u00f9zcoa 20730",
    "addr:housenumber":"/ n",
    "addr:postcode":"20730",
    "addr:street":"Basarte Area;Guipu\u0300Zcoa",
    "iso:country":"ES",
    "sg:address":"Basarte Area, S/n",
    "sg:city":"Azpeitia",
    "sg:orig_category":"Metalurgia",
    "sg:phone":"+34 943 85 04 51",
    "sg:postcode":"20730",
    "sg:province":"Guip\u00f9zcoa",
    "wof:name":"Bibatman S.l.",
    "wof:placetype":"venue"
},
  "geometry": {"coordinates":[-2.2638750076,43.1857795715],"type":"Point"}
}