{
  "type": "Feature",
  "properties": {
    "addr:full":"Calle de Donoso Cortes, 15 Madrid Madrid 28015",
    "addr:housenumber":"15",
    "addr:postcode":"madrid;28015",
    "addr:street":"Calle De Donoso Cortes",
    "iso:country":"ES",
    "sg:address":"Calle de Donoso Cortes, 15",
    "sg:city":"Madrid",
    "sg:orig_category":"Estancos",
    "sg:phone":"+34 914 46 85 42",
    "sg:postcode":"28015",
    "sg:province":"Madrid",
    "wof:name":"Santos Serrano Jose Antonio",
    "wof:placetype":"venue"
},
  "geometry": {"coordinates":[-3.7072899342,40.4359970093],"type":"Point"}
}