{
  "type": "Feature",
  "properties": {
    "addr:full":"Ctra Valencia-ademuz, Km. 0026,0 Lliria Valencia 46160",
    "addr:postcode":"46160",
    "addr:street":"Ctra Valencia-Ademuz Km. 0026,0 Lliria",
    "iso:country":"ES",
    "sg:address":"Ctra Valencia-ademuz, Km. 0026,0",
    "sg:city":"Lliria",
    "sg:orig_category":"Arenas, Guijarros Y Granulados",
    "sg:phone":"+34 962 78 07 68",
    "sg:postcode":"46160",
    "sg:province":"Valencia",
    "wof:name":"Viguetas Y Aridos Lliria S.l.",
    "wof:placetype":"venue"
},
  "geometry": {"coordinates":[-0.6247159839,39.6471366882],"type":"Point"}
}