{
  "type": "Feature",
  "properties": {
    "iso:country":"ES",
    "sg:address":"Calle de Pinos (los), 12",
    "sg:city":"Cantalejo",
    "sg:orig_category":"Arquitectos",
    "sg:phone":"+34 921 52 03 74",
    "sg:postcode":"40320",
    "sg:province":"Segovia",
    "wof:name":"Benitez Montenegro Enrique",
    "wof:placetype":"venue"
},
  "geometry": {"coordinates":[-3.9185070992,41.2577934265],"type":"Point"}
}