{
  "type": "Feature",
  "properties": {
    "addr:full":"Avda Jose Rodriguez Ruano, 13 Almansa Albacete 02640",
    "addr:housenumber":"13",
    "addr:postcode":"02640",
    "addr:street":"Avda Jose Rodriguez Ruano",
    "iso:country":"ES",
    "sg:address":"Avda Jose Rodriguez Ruano, 13",
    "sg:city":"Almansa",
    "sg:orig_category":"Farmacias",
    "sg:phone":"+34 967 34 16 64",
    "sg:postcode":"02640",
    "sg:province":"Albacete",
    "wof:name":"Martinez Cabral Maria Luisa",
    "wof:placetype":"venue"
},
  "geometry": {"coordinates":[-1.0924799442,38.8658332825],"type":"Point"}
}