{
  "type": "Feature",
  "properties": {
    "addr:full":"Cmno Fabrica (de La), S/n Talamanca De Jarama Madrid 28160",
    "addr:postcode":"28160",
    "addr:street":"Cmno Fabrica De La S / N",
    "iso:country":"ES",
    "sg:address":"Cmno Fabrica (de La), S/n",
    "sg:city":"Talamanca De Jarama",
    "sg:orig_category":"Alimentaci\u00d3n General (al Por Mayor)",
    "sg:phone":"+34 918 41 72 05",
    "sg:postcode":"28160",
    "sg:province":"Madrid",
    "wof:name":"Toribio Gutierrez E Hijos S.l.",
    "wof:placetype":"venue"
},
  "geometry": {"coordinates":[-3.5119550228,40.7490692139],"type":"Point"}
}