{
  "type": "Feature",
  "properties": {
    "iso:country":"ES",
    "sg:address":"Carrer de Viladomat, 320",
    "sg:city":"Barcelona",
    "sg:orig_category":"Asesor\u00cda Sobre Comunicaci\u00d3n De Empresas",
    "sg:phone":"+34 933 21 11 50",
    "sg:postcode":"08029",
    "sg:province":"Barcelona",
    "wof:name":"Ae Assessors S.c.p.",
    "wof:placetype":"venue"
},
  "geometry": {"coordinates":[2.1439933777,41.3897361755],"type":"Point"}
}