{
  "type": "Feature",
  "properties": {
    "addr:full":"Guillermo Reina, 39 Huercal-overa Almer\u00eda 04600",
    "addr:housenumber":"39",
    "addr:postcode":"04600",
    "addr:street":"Guillermo Reina;Almeri\u0301A",
    "iso:country":"ES",
    "sg:address":"Guillermo Reina, 39",
    "sg:city":"Huercal-overa",
    "sg:orig_category":"Veh\u00cdculos De Ocasi\u00d3n",
    "sg:phone":"+34 950 47 16 46",
    "sg:postcode":"04600",
    "sg:province":"Almer\u00eda",
    "wof:name":"Guirao Perez Daniel",
    "wof:placetype":"venue"
},
  "geometry": {"coordinates":[-1.9437910318,37.3984489441],"type":"Point"}
}