{
  "type": "Feature",
  "properties": {
    "iso:country":"ES",
    "sg:address":"Calle de Luna, 47",
    "sg:city":"Puerto De Santa Maria",
    "sg:orig_category":"\u00d3ptica: Instrumentos (fabricaci\u00d3n)",
    "sg:phone":"+34 956 54 04 08",
    "sg:postcode":"11500",
    "sg:province":"C\u00e1diz",
    "wof:name":"Concha Viseras S.l.",
    "wof:placetype":"venue"
},
  "geometry": {"coordinates":[-6.2269558907,36.5992279053],"type":"Point"}
}