{
  "type": "Feature",
  "properties": {
    "iso:country":"ES",
    "sg:address":"Sidi A. Kader, 12",
    "sg:city":"Melilla",
    "sg:orig_category":"Tintes (fabricaci\u00d3n, Al Por Mayor)",
    "sg:phone":"+34 952 68 56 88",
    "sg:postcode":"52001",
    "sg:province":"Melilla",
    "wof:name":"Mohamed Bekain Abdeselam",
    "wof:placetype":"venue"
},
  "geometry": {"coordinates":[-2.9512500763,35.3091583252],"type":"Point"}
}