{
  "type": "Feature",
  "properties": {
    "iso:country":"ES",
    "sg:address":"Calle de Marineros, 59",
    "sg:city":"Poligono Industrial",
    "sg:orig_category":"M\u00c1rmoles, Granitos Y Piedras Naturales",
    "sg:phone":"+34 965 41 15 71",
    "sg:postcode":"03130",
    "sg:province":"Alicante",
    "wof:name":"Hermanos Irles Marmoles S.l.",
    "wof:placetype":"venue"
},
  "geometry": {"coordinates":[-0.5578309894,38.2048950195],"type":"Point"}
}