{
  "type": "Feature",
  "properties": {
    "iso:country":"ES",
    "sg:address":"Carrer de Ramon Muntaner, 49",
    "sg:city":"Palma",
    "sg:orig_category":"Peluquer\u00cdas, Peluquer\u00cda Mixta",
    "sg:phone":"+34 971 29 82 07",
    "sg:postcode":"07010",
    "sg:province":"Islas Baleares",
    "wof:name":"Sans Puig Laura",
    "wof:placetype":"venue"
},
  "geometry": {"coordinates":[2.6499140263,39.5837364197],"type":"Point"}
}