{
  "type": "Feature",
  "properties": {
    "addr:full":"Pg Gran Passeig Ronda, 6 Lleida Lleida 25002",
    "addr:housenumber":"6",
    "addr:postcode":"25002",
    "addr:street":"Pg Gran Passeig Ronda",
    "iso:country":"ES",
    "sg:address":"Pg Gran Passeig Ronda, 6",
    "sg:city":"Lleida",
    "sg:orig_category":"Carnicer\u00cdas, Carnicer\u00cdas",
    "sg:phone":"+34 973 28 20 42",
    "sg:postcode":"25002",
    "sg:province":"Lleida",
    "wof:name":"Art-carn S.c.p.",
    "wof:placetype":"venue"
},
  "geometry": {"coordinates":[0.6216008067,41.6107330322],"type":"Point"}
}