{
  "type": "Feature",
  "properties": {
    "iso:country":"ES",
    "sg:address":"Avgd Baixada Del Carme, 9",
    "sg:city":"Xativa",
    "sg:orig_category":"Fabricaci\u00d3n, Importaci\u00d3n De L\u00c1mparas Y Bombillas",
    "sg:phone":"+34 962 28 32 06",
    "sg:postcode":"46800",
    "sg:province":"Valencia",
    "wof:name":"Lopez Sanchis Maria Isabel",
    "wof:placetype":"venue"
},
  "geometry": {"coordinates":[-0.5200830102,38.9934272766],"type":"Point"}
}