{
  "type": "Feature",
  "properties": {
    "iso:country":"ES",
    "sg:address":"Calle de Juan Calzada Kalea, 75",
    "sg:city":"Gernika-lumo",
    "sg:orig_category":"Peluquer\u00cdas, Peluquer\u00cda Mixta",
    "sg:phone":"+34 946 25 02 36",
    "sg:postcode":"48300",
    "sg:province":"Vizcaya",
    "wof:name":"Zaira Quevedo Lara Y Maria Isabel Calvo Coca S.c.",
    "wof:placetype":"venue"
},
  "geometry": {"coordinates":[-2.6789581776,43.3172340393],"type":"Point"}
}