{
  "type": "Feature",
  "properties": {
    "addr:full":"Calle de Santa Teresa, 6 Alcala Henares Madrid 28803",
    "addr:housenumber":"6",
    "addr:postcode":"28803",
    "addr:street":"Calle De Santa Teresa",
    "iso:country":"ES",
    "sg:address":"Calle de Santa Teresa, 6",
    "sg:city":"Alcala Henares",
    "sg:orig_category":"Peluqueros: De Se\u00d1oras",
    "sg:phone":"+34 918 82 66 70",
    "sg:postcode":"28803",
    "sg:province":"Madrid",
    "wof:name":"Fernandez Sanchez Yolanda",
    "wof:placetype":"venue"
},
  "geometry": {"coordinates":[-3.3770689964,40.4736442566],"type":"Point"}
}