{
  "type": "Feature",
  "properties": {
    "iso:country":"ES",
    "sg:address":"G.v. Marques Del Turia, 50",
    "sg:city":"Valencia",
    "sg:orig_category":"Promotores Constructores",
    "sg:phone":"+34 963 95 86 65",
    "sg:postcode":"46005",
    "sg:province":"Valencia",
    "wof:name":"Impaes S. A.",
    "wof:placetype":"venue"
},
  "geometry": {"coordinates":[-0.3684110045,39.4668731689],"type":"Point"}
}