{
  "type": "Feature",
  "properties": {
    "addr:full":"Carr Biscaia, 48 Andratx Islas Baleares 07150",
    "addr:housenumber":"48",
    "addr:postcode":"07150",
    "addr:street":"Carr Biscaia",
    "iso:country":"ES",
    "sg:address":"Carr Biscaia, 48",
    "sg:city":"Andratx",
    "sg:orig_category":"Peluquer\u00cdas, Peluquer\u00cda Mixta",
    "sg:phone":"+34 971 23 63 12",
    "sg:postcode":"07150",
    "sg:province":"Islas Baleares",
    "wof:name":"Vera Santana Isabel",
    "wof:placetype":"venue"
},
  "geometry": {"coordinates":[2.4228799343,39.5626411438],"type":"Point"}
}