{
  "type": "Feature",
  "properties": {
    "iso:country":"ES",
    "sg:address":"Vilapouca, 3",
    "sg:city":"Soutelo",
    "sg:orig_category":"Centros Empresariales",
    "sg:phone":"+34 986 75 49 15",
    "sg:postcode":"36555",
    "sg:province":"Pontevedra",
    "wof:name":"Dispraco S.l.",
    "wof:placetype":"venue"
},
  "geometry": {"coordinates":[-8.3221940994,42.5436820984],"type":"Point"}
}