{
  "type": "Feature",
  "properties": {
    "iso:country":"ES",
    "sg:address":"Calle de Aluminio, 118",
    "sg:city":"Poligono Borondo",
    "sg:orig_category":"Hormig\u00d3n Listo Para Usar",
    "sg:phone":"+34 902 13 13 32",
    "sg:postcode":"28510",
    "sg:province":"Madrid",
    "wof:name":"Tru Madrid S.a.",
    "wof:placetype":"venue"
},
  "geometry": {"coordinates":[-3.3777239323,40.33776474],"type":"Point"}
}