{
  "type": "Feature",
  "properties": {
    "iso:country":"ES",
    "sg:address":"Pase Extremadura, 18",
    "sg:city":"Madrid",
    "sg:orig_category":"Peluquer\u00cdas, Peluquer\u00cda Mixta",
    "sg:phone":"+34 915 26 09 96",
    "sg:postcode":"28011",
    "sg:province":"Madrid",
    "wof:name":"Mayoral Y Ferrer S.l.",
    "wof:placetype":"venue"
},
  "geometry": {"coordinates":[-3.726320982,40.4139480591],"type":"Point"}
}