{
  "type": "Feature",
  "properties": {
    "addr:full":"Calle de Periodista Badia, 6 Valencia Valencia 46010",
    "addr:housenumber":"6",
    "addr:postcode":"46010",
    "addr:street":"Calle De Periodista Badia",
    "iso:country":"ES",
    "sg:address":"Calle de Periodista Badia, 6",
    "sg:city":"Valencia",
    "sg:orig_category":"M\u00c9dicos: Cirug\u00cda Pl\u00c1stica, Reconstructiva Y Est\u00c9tica",
    "sg:phone":"+34 963 60 12 85",
    "sg:postcode":"46010",
    "sg:province":"Valencia",
    "wof:name":"Codina Garcia Jose",
    "wof:placetype":"venue"
},
  "geometry": {"coordinates":[-0.3631950021,39.477355957],"type":"Point"}
}