{
  "type": "Feature",
  "properties": {
    "iso:country":"ES",
    "sg:address":"Carr Sta Caterina, 39",
    "sg:city":"Igualada",
    "sg:orig_category":"Agencias De Viajes",
    "sg:phone":"+34 938 06 60 32",
    "sg:postcode":"08700",
    "sg:province":"Barcelona",
    "wof:name":"Aqualata Tours S.l.",
    "wof:placetype":"venue"
},
  "geometry": {"coordinates":[1.6155207157,41.5814590454],"type":"Point"}
}