{
  "type": "Feature",
  "properties": {
    "iso:country":"ES",
    "sg:address":"Calle de Ollaga, 5",
    "sg:city":"Astrabudua",
    "sg:orig_category":"Molduras, Junquillos, Listones Y Molduras Perforadas",
    "sg:phone":"+34 944 67 67 39",
    "sg:postcode":"48950",
    "sg:province":"Vizcaya",
    "wof:name":"Gonzalez Rios Maria Antonia",
    "wof:placetype":"venue"
},
  "geometry": {"coordinates":[-2.9815249443,43.3164367676],"type":"Point"}
}