{
  "type": "Feature",
  "properties": {
    "iso:country":"ES",
    "sg:address":"Calle de Daganzo, 2",
    "sg:city":"Madrid",
    "sg:orig_category":"Arreglo, Reparaci\u00d3n, Piezas Sueltas De Televisi\u00d3n, V\u00cddeo, Hi",
    "sg:phone":"+34 915 19 44 78",
    "sg:postcode":"28002",
    "sg:province":"Madrid",
    "wof:name":"Mu\u00f1oz Bernardo Luis",
    "wof:placetype":"venue"
},
  "geometry": {"coordinates":[-3.6732339859,40.4412384033],"type":"Point"}
}