{
  "type": "Feature",
  "properties": {
    "addr:full":"Calle de Virgen De La Caridad, 2 Avila \u00c1vila 05005",
    "addr:housenumber":"2",
    "addr:postcode":"05005",
    "addr:street":"Calle De Virgen De La Caridad;A\u0301Vila",
    "iso:country":"ES",
    "sg:address":"Calle de Virgen De La Caridad, 2",
    "sg:city":"Avila",
    "sg:orig_category":"Agricultura: Abastecimiento Y Cosechado (negocio)",
    "sg:phone":"+34 920 22 82 60",
    "sg:postcode":"05005",
    "sg:province":"\u00c1vila",
    "wof:name":"Mo\u00f1ita Garcia Carmen",
    "wof:placetype":"venue"
},
  "geometry": {"coordinates":[-4.6908431053,40.6592102051],"type":"Point"}
}