{
  "type": "Feature",
  "properties": {
    "addr:full":"Carrer de Nacio, 21 Barcelona Barcelona 08026",
    "addr:housenumber":"21",
    "addr:postcode":"08026",
    "addr:street":"Carrer De Nacio",
    "iso:country":"ES",
    "sg:address":"Carrer de Nacio, 21",
    "sg:city":"Barcelona",
    "sg:orig_category":"Plomeros",
    "sg:phone":"+34 934 55 41 82",
    "sg:postcode":"08026",
    "sg:province":"Barcelona",
    "wof:name":"Hernandez Perez Antonio",
    "wof:placetype":"venue"
},
  "geometry": {"coordinates":[2.1856160164,41.4126815796],"type":"Point"}
}