{
  "type": "Feature",
  "properties": {
    "iso:country":"ES",
    "sg:address":"Carr Sant Pauli De Nola, 6",
    "sg:city":"Lleida",
    "sg:orig_category":"Carnicer\u00cdas, Carnicer\u00cdas",
    "sg:phone":"+34 973 21 15 08",
    "sg:postcode":"25001",
    "sg:province":"Lleida",
    "wof:name":"Solana Guillen Encarnacion",
    "wof:placetype":"venue"
},
  "geometry": {"coordinates":[0.6388959885,41.6057891846],"type":"Point"}
}