{
  "type": "Feature",
  "properties": {
    "iso:country":"ES",
    "sg:address":"Rua Sol, 48",
    "sg:city":"Carballo",
    "sg:orig_category":"Florister\u00cdas",
    "sg:phone":"+34 981 70 11 54",
    "sg:postcode":"15100",
    "sg:province":"A Coru\u00f1a",
    "wof:name":"Suarez Vazquez Maria Bego\u00f1a",
    "wof:placetype":"venue"
},
  "geometry": {"coordinates":[-8.688334465,43.2104034424],"type":"Point"}
}