{
  "type": "Feature",
  "properties": {
    "iso:country":"ES",
    "sg:address":"Carrer de Maria Fortuny, 5",
    "sg:city":"Santa Perpetua De Mogoda",
    "sg:orig_category":"Guarder\u00cdas",
    "sg:phone":"+34 935 60 04 89",
    "sg:postcode":"08130",
    "sg:province":"Barcelona",
    "wof:name":"Sala Mas Maria Luisa",
    "wof:placetype":"venue"
},
  "geometry": {"coordinates":[2.1820700169,41.5339393616],"type":"Point"}
}