{
  "type": "Feature",
  "properties": {
    "addr:full":"Pase Estacion (la), 16 Jaen Ja\u00e9n 23003",
    "addr:postcode":"23003",
    "addr:street":"Jae\u0301N",
    "iso:country":"ES",
    "sg:address":"Pase Estacion (la), 16",
    "sg:city":"Jaen",
    "sg:orig_category":"Bancos",
    "sg:phone":"+34 953 25 05 44",
    "sg:postcode":"23003",
    "sg:province":"Ja\u00e9n",
    "wof:name":"Banc Sabadell S.a.",
    "wof:placetype":"venue"
},
  "geometry": {"coordinates":[-3.7269899845,37.7898101807],"type":"Point"}
}