{
  "type": "Feature",
  "properties": {
    "addr:full":"Calle de Fragua, 3 Santa Marta De Tormes Salamanca 37900",
    "addr:housenumber":"3",
    "addr:postcode":"37900",
    "addr:street":"Calle De Fragua",
    "iso:country":"ES",
    "sg:address":"Calle de Fragua, 3",
    "sg:city":"Santa Marta De Tormes",
    "sg:orig_category":"Cerrajer\u00cda, Ferrallista",
    "sg:phone":"+34 923 20 02 32",
    "sg:postcode":"37900",
    "sg:province":"Salamanca",
    "wof:name":"Fraile Marcos Manuel",
    "wof:placetype":"venue"
},
  "geometry": {"coordinates":[-5.6309018135,40.9506492615],"type":"Point"}
}