{
  "type": "Feature",
  "properties": {
    "iso:country":"ES",
    "sg:address":"Calle de Iglesia, 19",
    "sg:city":"Codo\u00d1era",
    "sg:orig_category":"Cr\u00cda De Cerdos",
    "sg:phone":"+34 978 85 20 65",
    "sg:postcode":"44640",
    "sg:province":"Teruel",
    "wof:name":"Asociacipn De Criadores De Porcino De Teruel",
    "wof:placetype":"venue"
},
  "geometry": {"coordinates":[-0.0858708993,40.9334411621],"type":"Point"}
}