{
  "type": "Feature",
  "properties": {
    "addr:full":"Calle de Mayor, 1 Nules Castell\u00f3n 12520",
    "addr:housenumber":"1",
    "addr:postcode":"12520",
    "addr:street":"Calle De Mayor",
    "iso:country":"ES",
    "sg:address":"Calle de Mayor, 1",
    "sg:city":"Nules",
    "sg:orig_category":"Heladeros",
    "sg:phone":"+34 964 67 01 99",
    "sg:postcode":"12520",
    "sg:province":"Castell\u00f3n",
    "wof:name":"Beneito Vila Francisco",
    "wof:placetype":"venue"
},
  "geometry": {"coordinates":[-0.1566440016,39.8518486023],"type":"Point"}
}