{
  "type": "Feature",
  "properties": {
    "iso:country":"ES",
    "sg:address":"Luga Ayagaures, 47",
    "sg:city":"Ayagaures",
    "sg:orig_category":"Pescader\u00cdas (al Por Menor)",
    "sg:phone":"+34 928 14 40 46",
    "sg:postcode":"35109",
    "sg:province":"Las Palmas",
    "wof:name":"Perez Perez Pedro Serafin",
    "wof:placetype":"venue"
},
  "geometry": {"coordinates":[-15.6035785675,27.7709903717],"type":"Point"}
}