{
  "type": "Feature",
  "properties": {
    "addr:full":"Calle de Ramon Y Cajal, 8 Merida Badajoz 06800",
    "addr:housenumber":"8",
    "addr:postcode":"06800",
    "addr:street":"Calle De Ramon Y Cajal",
    "iso:country":"ES",
    "sg:address":"Calle de Ramon Y Cajal, 8",
    "sg:city":"Merida",
    "sg:orig_category":"Centros De Coordinaci\u00d3n",
    "sg:phone":"+34 924 31 11 93",
    "sg:postcode":"06800",
    "sg:province":"Badajoz",
    "wof:name":"Famingel S.l.",
    "wof:placetype":"venue"
},
  "geometry": {"coordinates":[-6.3513708115,38.9201812744],"type":"Point"}
}