{
  "type": "Feature",
  "properties": {
    "iso:country":"ES",
    "sg:address":"Chorente Torrago\u00f1a, 37",
    "sg:city":"Rianxo",
    "sg:orig_category":"Promotores Constructores",
    "sg:phone":"+34 981 84 38 26",
    "sg:postcode":"15920",
    "sg:province":"La Coru\u00f1a",
    "wof:name":"Magiter Sl",
    "wof:placetype":"venue"
},
  "geometry": {"coordinates":[-8.8172187805,42.6528091431],"type":"Point"}
}