{
  "type": "Feature",
  "properties": {
    "iso:country":"ES",
    "sg:address":"Carrer de Bruc, 68",
    "sg:city":"Barcelona",
    "sg:orig_category":"Doctores En Medicina",
    "sg:phone":"+34 934 88 35 56",
    "sg:postcode":"08009",
    "sg:province":"Barcelona",
    "wof:name":"Abadal Berini Joaquin",
    "wof:placetype":"venue"
},
  "geometry": {"coordinates":[2.170727,41.393459],"type":"Point"}
}