{
  "type": "Feature",
  "properties": {
    "iso:country":"ES",
    "sg:address":"Avda Ferrol, 43",
    "sg:city":"Pontedeume",
    "sg:orig_category":"Empresas De Pintura Y Revestimientos",
    "sg:phone":"+34 981 43 01 77",
    "sg:postcode":"15600",
    "sg:province":"La Coru\u00f1a",
    "wof:name":"Gonzalez Carpente Manuel Vicente",
    "wof:placetype":"venue"
},
  "geometry": {"coordinates":[-8.1763334274,43.4109535217],"type":"Point"}
}