{
  "type": "Feature",
  "properties": {
    "iso:country":"ES",
    "sg:address":"Avda Madrid (de), 7",
    "sg:city":"Petrer",
    "sg:orig_category":"Estancos",
    "sg:phone":"+34 965 37 59 31",
    "sg:postcode":"03610",
    "sg:province":"Alicante",
    "wof:name":"Navarro Tortosa Antonio",
    "wof:placetype":"venue"
},
  "geometry": {"coordinates":[-0.7838010192,38.4776000977],"type":"Point"}
}