{
  "type": "Feature",
  "properties": {
    "addr:full":"Plaz Coso (el), 3 Navarrete La Rioja 26370",
    "addr:postcode":"26370",
    "iso:country":"ES",
    "sg:address":"Plaz Coso (el), 3",
    "sg:city":"Navarrete",
    "sg:orig_category":"Cajas De Ahorro",
    "sg:phone":"+34 941 44 00 21",
    "sg:postcode":"26370",
    "sg:province":"La Rioja",
    "wof:name":"Caja De Ahorros De La Rioja",
    "wof:placetype":"venue"
},
  "geometry": {"coordinates":[-2.5627059937,42.4329109192],"type":"Point"}
}