{
  "type": "Feature",
  "properties": {
    "addr:full":"Avda Constitucion, 65 Boiro La Coru\u00f1a 15930",
    "addr:housenumber":"65",
    "addr:postcode":"15930",
    "addr:street":"Avda Constitucion;La Corun\u0303A",
    "iso:country":"ES",
    "sg:address":"Avda Constitucion, 65",
    "sg:city":"Boiro",
    "sg:orig_category":"Muebles, Minoristas",
    "sg:phone":"+34 981 84 87 20",
    "sg:postcode":"15930",
    "sg:province":"La Coru\u00f1a",
    "wof:name":"Muebles Guadalupe S.l.",
    "wof:placetype":"venue"
},
  "geometry": {"coordinates":[-8.8858356476,42.6451225281],"type":"Point"}
}