{
  "type": "Feature",
  "properties": {
    "addr:full":"Calle de Francisco Neila, 21 Santa Marta Badajoz 06150",
    "addr:housenumber":"21",
    "addr:postcode":"06150",
    "addr:street":"Calle De Francisco Neila",
    "iso:country":"ES",
    "sg:address":"Calle de Francisco Neila, 21",
    "sg:city":"Santa Marta",
    "sg:orig_category":"Cajas Para Embalar",
    "sg:phone":"+34 924 68 14 00",
    "sg:postcode":"06150",
    "sg:province":"Badajoz",
    "wof:name":"Caja Rural De Almendralejo",
    "wof:placetype":"venue"
},
  "geometry": {"coordinates":[-6.6250300407,38.6147689819],"type":"Point"}
}