{
  "type": "Feature",
  "properties": {
    "addr:full":"Plaz Marques De Estella, S/n Fuentes Nava Palencia 34337",
    "addr:housenumber":"s / n",
    "addr:postcode":"34337",
    "addr:street":"Marques",
    "iso:country":"ES",
    "sg:address":"Plaz Marques De Estella, S/n",
    "sg:city":"Fuentes Nava",
    "sg:orig_category":"Farmacias",
    "sg:phone":"+34 979 84 20 42",
    "sg:postcode":"34337",
    "sg:province":"Palencia",
    "wof:name":"Najera Salas Jose Luis",
    "wof:placetype":"venue"
},
  "geometry": {"coordinates":[-4.7798190117,42.081413269],"type":"Point"}
}