{
  "type": "Feature",
  "properties": {
    "iso:country":"ES",
    "sg:address":"Calle de Mayor, 36",
    "sg:city":"Albacete",
    "sg:orig_category":"Cl\u00cdnicas Dentales",
    "sg:phone":"+34 967 24 21 49",
    "sg:postcode":"02002",
    "sg:province":"Albacete",
    "wof:name":"Arcos Vidal Jose Ricardo",
    "wof:placetype":"venue"
},
  "geometry": {"coordinates":[-1.8553719521,38.993434906],"type":"Point"}
}