{
  "type": "Feature",
  "properties": {
    "addr:full":"Avda Villafranca, 3 Bembibre Le\u00f3n 24300",
    "addr:housenumber":"3",
    "addr:postcode":"24300",
    "addr:street":"Avda Villafranca;Leo\u0301N",
    "iso:country":"ES",
    "sg:address":"Avda Villafranca, 3",
    "sg:city":"Bembibre",
    "sg:orig_category":"Institutos De Belleza",
    "sg:phone":"+34 987 51 07 81",
    "sg:postcode":"24300",
    "sg:province":"Le\u00f3n",
    "wof:name":"Cuenya Garcia Maria Encina",
    "wof:placetype":"venue"
},
  "geometry": {"coordinates":[-6.4169821739,42.6150856018],"type":"Point"}
}