{
  "type": "Feature",
  "properties": {
    "iso:country":"ES",
    "sg:address":"Calle de Fajardo, 1",
    "sg:city":"Arrecife",
    "sg:orig_category":"Laboratorios Farmac\u00c9uticos",
    "sg:phone":"+34 928 81 71 00",
    "sg:postcode":"35500",
    "sg:province":"Las Palmas",
    "wof:name":"Armas Camejo Manuel",
    "wof:placetype":"venue"
},
  "geometry": {"coordinates":[-13.5495595932,28.9599590302],"type":"Point"}
}