{
  "type": "Feature",
  "properties": {
    "addr:full":"Carrer de Ausias March, 44 Guardamar Segura Alicante 03140",
    "addr:housenumber":"44",
    "addr:postcode":"03140",
    "addr:street":"Carrer De Ausias March",
    "iso:country":"ES",
    "sg:address":"Carrer de Ausias March, 44",
    "sg:city":"Guardamar Segura",
    "sg:orig_category":"Carnicer\u00cdas, Carnicer\u00cdas",
    "sg:phone":"+34 965 72 81 21",
    "sg:postcode":"03140",
    "sg:province":"Alicante",
    "wof:name":"Martinez Villa Francisco",
    "wof:placetype":"venue"
},
  "geometry": {"coordinates":[-0.6530100107,38.0883026123],"type":"Point"}
}