{
  "type": "Feature",
  "properties": {
    "addr:full":"Calle de Doctor Fermin Garrido, 4 Granada Granada 18012",
    "addr:housenumber":"4",
    "addr:postcode":"18012",
    "addr:street":"Calle De Doctor Fermin Garrido",
    "iso:country":"ES",
    "sg:address":"Calle de Doctor Fermin Garrido, 4",
    "sg:city":"Granada",
    "sg:orig_category":"Servicios De Telecomunicaciones",
    "sg:phone":"+34 958 16 30 00",
    "sg:postcode":"18012",
    "sg:province":"Granada",
    "wof:name":"Garcia Rodriguez Antonia",
    "wof:placetype":"venue"
},
  "geometry": {"coordinates":[-3.6083874702,37.1906394958],"type":"Point"}
}