{
  "type": "Feature",
  "properties": {
    "addr:full":"Calle de San Jaime, 1 Ag\u00fcero Huesca 22808",
    "addr:housenumber":"1",
    "addr:postcode":"22808",
    "addr:street":"Calle De San Jaime",
    "iso:country":"ES",
    "sg:address":"Calle de San Jaime, 1",
    "sg:city":"Ag\u00fcero",
    "sg:orig_category":"Museos",
    "sg:phone":"+34 974 38 04 89",
    "sg:postcode":"22808",
    "sg:province":"Huesca",
    "wof:name":"Ayuntamiento De Ag\u00fcero",
    "wof:placetype":"venue"
},
  "geometry": {"coordinates":[-0.7948510051,42.3559837341],"type":"Point"}
}