{
  "type": "Feature",
  "properties": {
    "iso:country":"ES",
    "sg:address":"Avda Pablo Lape\u00d1a, 9",
    "sg:city":"Alburquerque",
    "sg:orig_category":"Muebles, Minoristas",
    "sg:phone":"+34 924 40 12 78",
    "sg:postcode":"06510",
    "sg:province":"Badajoz",
    "wof:name":"Muebles Regino S.l.",
    "wof:placetype":"venue"
},
  "geometry": {"coordinates":[-6.999956131,39.217502594],"type":"Point"}
}