{
  "type": "Feature",
  "properties": {
    "iso:country":"ES",
    "sg:address":"Avda Pinares, Los, 77",
    "sg:city":"Saler",
    "sg:orig_category":"Deportes Y Programas De Aventura",
    "sg:phone":"+34 961 62 72 01",
    "sg:postcode":"46012",
    "sg:province":"Valencia",
    "wof:name":"Golfcab S.l.",
    "wof:placetype":"venue"
},
  "geometry": {"coordinates":[-0.2913190126,39.3012657166],"type":"Point"}
}