{
  "type": "Feature",
  "properties": {
    "iso:country":"ES",
    "sg:address":"Rua San Bernardo, 29",
    "sg:city":"Noia",
    "sg:orig_category":"Carnicer\u00cdas, Carnicer\u00cdas",
    "sg:phone":"+34 981 82 11 35",
    "sg:postcode":"15200",
    "sg:province":"La Coru\u00f1a",
    "wof:name":"Iglesias Abeijon Jose",
    "wof:placetype":"venue"
},
  "geometry": {"coordinates":[-8.8816194534,42.7869911194],"type":"Point"}
}