{
  "type": "Feature",
  "properties": {
    "addr:full":"Paseo De La Ermita, S/n Cala Huelva 21270",
    "addr:housenumber":"/ n",
    "addr:postcode":"21270",
    "addr:street":"Paseo De La Ermita S",
    "iso:country":"ES",
    "sg:address":"Paseo De La Ermita, S/n",
    "sg:city":"Cala",
    "sg:orig_category":"Centros De Educaci\u00d3n Especial",
    "sg:phone":"+34 959 19 10 56",
    "sg:postcode":"21270",
    "sg:province":"Huelva",
    "wof:name":"Junta De Andalucia",
    "wof:placetype":"venue"
},
  "geometry": {"coordinates":[-6.3146591187,37.9689598083],"type":"Point"}
}