{
  "type": "Feature",
  "properties": {
    "iso:country":"ES",
    "sg:address":"Calle de Juan De Balmaseda, 8",
    "sg:city":"Palencia",
    "sg:orig_category":"Ortopedia General",
    "sg:phone":"+34 979 71 00 32",
    "sg:postcode":"34004",
    "sg:province":"Palencia",
    "wof:name":"Sanymed 2m S.l.",
    "wof:placetype":"venue"
},
  "geometry": {"coordinates":[-4.5228328705,42.0033226013],"type":"Point"}
}