{
  "type": "Feature",
  "properties": {
    "iso:country":"ES",
    "sg:address":"Carr Mendez Nu\u00d1ez, 6",
    "sg:city":"Figueres",
    "sg:orig_category":"Lanas (al Por Menor)",
    "sg:phone":"+34 972 50 04 59",
    "sg:postcode":"17600",
    "sg:province":"Girona",
    "wof:name":"Casademont Maso Rosa",
    "wof:placetype":"venue"
},
  "geometry": {"coordinates":[2.9657890797,42.2659568787],"type":"Point"}
}