{
  "type": "Feature",
  "properties": {
    "iso:country":"ES",
    "sg:address":"Carr Del Music Martinez Valls, 69",
    "sg:city":"Ontinyent",
    "sg:orig_category":"Ropa Para Beb\u00c9s Y Ni\u00d1os (confecci\u00d3n, Al Por Mayor)",
    "sg:phone":"+34 962 91 50 42",
    "sg:postcode":"46870",
    "sg:province":"Valencia",
    "wof:name":"Comercial Textil Titella S.l.",
    "wof:placetype":"venue"
},
  "geometry": {"coordinates":[-0.6030989885,38.8258895874],"type":"Point"}
}