{
  "type": "Feature",
  "properties": {
    "iso:country":"ES",
    "sg:address":"Calle de Mazaroco, 17",
    "sg:city":"Puerto Cruz",
    "sg:orig_category":"Asesor\u00cda Sobre Comunicaci\u00d3n De Empresas",
    "sg:phone":"+34 922 38 60 14",
    "sg:postcode":"38400",
    "sg:province":"Santa Cruz De Tenerife",
    "wof:name":"Asesoria Laboconta S.l.",
    "wof:placetype":"venue"
},
  "geometry": {"coordinates":[-16.5535068512,28.4153938293],"type":"Point"}
}