{
  "type": "Feature",
  "properties": {
    "addr:full":"Avda Irun, 4 Arre Navarra 31194",
    "addr:housenumber":"4",
    "addr:postcode":"31194",
    "addr:street":"Avda Irun",
    "iso:country":"ES",
    "sg:address":"Avda Irun, 4",
    "sg:city":"Arre",
    "sg:orig_category":"Muebles, Minoristas",
    "sg:phone":"+34 948 33 10 00",
    "sg:postcode":"31194",
    "sg:province":"Navarra",
    "wof:name":"Mundo Mueble S.l.",
    "wof:placetype":"venue"
},
  "geometry": {"coordinates":[-1.6100120544,42.8402061462],"type":"Point"}
}