{
  "type": "Feature",
  "properties": {
    "iso:country":"ES",
    "sg:address":"Calle de Santa Ana, 1",
    "sg:city":"Valdealgorfa",
    "sg:orig_category":"Cajas Para Embalar",
    "sg:phone":"+34 978 85 72 83",
    "sg:postcode":"44594",
    "sg:province":"Teruel",
    "wof:name":"Caja Rural De Teruel",
    "wof:placetype":"venue"
},
  "geometry": {"coordinates":[-0.0343029983,40.9905014038],"type":"Point"}
}