{
  "type": "Feature",
  "properties": {
    "addr:full":"Rua Buenos Aires, 4 Melide La Coru\u00f1a 15800",
    "addr:housenumber":"4",
    "addr:postcode":"15800",
    "addr:street":"Rua Buenos Aires;La Corun\u0303A",
    "iso:country":"ES",
    "sg:address":"Rua Buenos Aires, 4",
    "sg:city":"Melide",
    "sg:orig_category":"Empresas De Carpinter\u00cda",
    "sg:phone":"+34 981 50 50 81",
    "sg:postcode":"15800",
    "sg:province":"La Coru\u00f1a",
    "wof:name":"Gomez Penas Jose Maria",
    "wof:placetype":"venue"
},
  "geometry": {"coordinates":[-8.010011673,42.9155311584],"type":"Point"}
}