{
  "type": "Feature",
  "properties": {
    "addr:full":"Calle de Faustekalea, S/n Durango Vizcaya 48200",
    "addr:housenumber":"s / n",
    "addr:postcode":"48200",
    "addr:street":"Calle De Faustekalea",
    "iso:country":"ES",
    "sg:address":"Calle de Faustekalea, S/n",
    "sg:city":"Durango",
    "sg:orig_category":"Semiller\u00cdas",
    "sg:phone":"+34 946 81 48 15",
    "sg:postcode":"48200",
    "sg:province":"Vizcaya",
    "wof:name":"Viveros F. Areitio S.a.",
    "wof:placetype":"venue"
},
  "geometry": {"coordinates":[-2.6218562126,43.1687088013],"type":"Point"}
}