{
  "type": "Feature",
  "properties": {
    "iso:country":"ES",
    "sg:address":"Ctra Jarandilla, 56",
    "sg:city":"Navalmoral Mata",
    "sg:orig_category":"Comercio De Piezas De Recambio Y De Accesorios De Veh\u00cdculos, Veh\u00cdculos Industriales",
    "sg:phone":"+34 927 53 22 58",
    "sg:postcode":"10300",
    "sg:province":"C\u00e1ceres",
    "wof:name":"Chamolunas S.l.",
    "wof:placetype":"venue"
},
  "geometry": {"coordinates":[-5.5453090668,39.8989715576],"type":"Point"}
}