{
  "type": "Feature",
  "properties": {
    "addr:full":"Avda La Libertad, 17 Barakaldo Vizcaya 48901",
    "addr:housenumber":"17",
    "addr:postcode":"48901",
    "addr:street":"Avda La Libertad",
    "iso:country":"ES",
    "sg:address":"Avda La Libertad, 17",
    "sg:city":"Barakaldo",
    "sg:orig_category":"Perfumer\u00cda (al Por Menor)",
    "sg:phone":"+34 944 37 21 21",
    "sg:postcode":"48901",
    "sg:province":"Vizcaya",
    "wof:name":"Maxima Jaen Panadero",
    "wof:placetype":"venue"
},
  "geometry": {"coordinates":[-2.9906289577,43.2965927124],"type":"Point"}
}