{
  "type": "Feature",
  "properties": {
    "addr:full":"Calle de Mayor, 35 Uceda Guadalajara 19187",
    "addr:housenumber":"35",
    "addr:postcode":"19187",
    "addr:street":"Calle De Mayor",
    "iso:country":"ES",
    "sg:address":"Calle de Mayor, 35",
    "sg:city":"Uceda",
    "sg:orig_category":"Droguer\u00cdas (al Por Menor)",
    "sg:phone":"+34 949 85 60 08",
    "sg:postcode":"19187",
    "sg:province":"Guadalajara",
    "wof:name":"Velasco Acevedo Antonio",
    "wof:placetype":"venue"
},
  "geometry": {"coordinates":[-3.4601500034,40.8412857056],"type":"Point"}
}