{
  "type": "Feature",
  "properties": {
    "iso:country":"ES",
    "sg:address":"Calle de Doctor Angel Olivares (de), 8",
    "sg:city":"Alcobendas",
    "sg:orig_category":"Peluquer\u00cdas, Peluquer\u00cda Mixta",
    "sg:phone":"+34 916 62 90 95",
    "sg:postcode":"28100",
    "sg:province":"Madrid",
    "wof:name":"Moratalla Gutierrez Carmen",
    "wof:placetype":"venue"
},
  "geometry": {"coordinates":[-3.6540267467,40.5495185852],"type":"Point"}
}