{
  "type": "Feature",
  "properties": {
    "iso:country":"ES",
    "sg:address":"Xardin Umbrio, S/n",
    "sg:city":"Vilanova Arousa",
    "sg:orig_category":"Peluqueros: De Se\u00d1oras",
    "sg:phone":"+34 986 56 11 84",
    "sg:postcode":"36620",
    "sg:province":"Pontevedra",
    "wof:name":"Ventoso Gonzalez Guadalupe",
    "wof:placetype":"venue"
},
  "geometry": {"coordinates":[-8.8285036087,42.5618782043],"type":"Point"}
}