{
  "type": "Feature",
  "properties": {
    "addr:full":"Calle de Colon, 13 Tui Pontevedra 36700",
    "addr:housenumber":"13",
    "addr:postcode":"36700",
    "addr:street":"Calle De Colon",
    "iso:country":"ES",
    "sg:address":"Calle de Colon, 13",
    "sg:city":"Tui",
    "sg:orig_category":"M\u00c9dicos: Estomatolog\u00cda",
    "sg:phone":"+34 986 62 79 27",
    "sg:postcode":"36700",
    "sg:province":"Pontevedra",
    "wof:name":"Martinez Fontan Maria Cristina",
    "wof:placetype":"venue"
},
  "geometry": {"coordinates":[-8.6475801468,42.0495605469],"type":"Point"}
}