{
  "type": "Feature",
  "properties": {
    "addr:full":"Calle de Fernandez De La Hoz, 12 Madrid Madrid 28010",
    "addr:housenumber":"12",
    "addr:postcode":"madrid;28010",
    "addr:street":"Calle De Fernandez De La Hoz",
    "iso:country":"ES",
    "sg:address":"Calle de Fernandez De La Hoz, 12",
    "sg:city":"Madrid",
    "sg:orig_category":"Sindicatos De Trabajadores",
    "sg:phone":"+34 913 10 44 55",
    "sg:postcode":"28010",
    "sg:province":"Madrid",
    "wof:name":"Federacion Minerometalurgica De Comisiones Obreras",
    "wof:placetype":"venue"
},
  "geometry": {"coordinates":[-3.6951868534,40.4306640625],"type":"Point"}
}