{
  "type": "Feature",
  "properties": {
    "addr:full":"Calle de Naciones, 12 Madrid Madrid 28006",
    "addr:housenumber":"12",
    "addr:postcode":"madrid;28006",
    "addr:street":"Calle De Naciones",
    "iso:country":"ES",
    "sg:address":"Calle de Naciones, 12",
    "sg:city":"Madrid",
    "sg:orig_category":"Negocio De Enlosados, Soler\u00cdas",
    "sg:phone":"+34 915 75 12 10",
    "sg:postcode":"28006",
    "sg:province":"Madrid",
    "wof:name":"Gonzalez Mu\u00f1oz Carlos",
    "wof:placetype":"venue"
},
  "geometry": {"coordinates":[-3.6733169556,40.4268074036],"type":"Point"}
}