{
  "type": "Feature",
  "properties": {
    "addr:full":"Calle de Alonso Alcala, 48 Alcala Real Ja\u00e9n 23680",
    "addr:housenumber":"48",
    "addr:postcode":"23680",
    "addr:street":"Calle De Alonso Alcala;Jae\u0301N",
    "iso:country":"ES",
    "sg:address":"Calle de Alonso Alcala, 48",
    "sg:city":"Alcala Real",
    "sg:orig_category":"Organizaciones Internacionales",
    "sg:phone":"+34 953 58 01 38",
    "sg:postcode":"23680",
    "sg:province":"Ja\u00e9n",
    "wof:name":"Caritas Diocesana De Accion Catolica",
    "wof:placetype":"venue"
},
  "geometry": {"coordinates":[-3.9260015488,37.4633522034],"type":"Point"}
}