{
  "type": "Feature",
  "properties": {
    "iso:country":"ES",
    "sg:address":"Calle de Oca\u00d1a, 88",
    "sg:city":"Madrid",
    "sg:orig_category":"Peluqueros: De Se\u00d1oras",
    "sg:phone":"+34 914 62 71 49",
    "sg:postcode":"28047",
    "sg:province":"Madrid",
    "wof:name":"Holgado Perez Maria De La Anunciacion",
    "wof:placetype":"venue"
},
  "geometry": {"coordinates":[-3.7522809505,40.3848457336],"type":"Point"}
}