{
  "type": "Feature",
  "properties": {
    "addr:full":"Carrer de Baro S M Sepulcre, 10 Palma Islas Baleares 07012",
    "addr:housenumber":"10",
    "addr:postcode":"07012",
    "addr:street":"Carrer De Baro S;Sepulcre",
    "iso:country":"ES",
    "sg:address":"Carrer de Baro S M Sepulcre, 10",
    "sg:city":"Palma",
    "sg:orig_category":"Lencer\u00cda Femenina, Corseter\u00cda, Trajes De Ba\u00d1o (al Por Menor)",
    "sg:phone":"+34 971 71 96 17",
    "sg:postcode":"07012",
    "sg:province":"Islas Baleares",
    "wof:name":"Camand Pujol Yolanda",
    "wof:placetype":"venue"
},
  "geometry": {"coordinates":[2.6443500519,39.5732955933],"type":"Point"}
}