{
  "type": "Feature",
  "properties": {
    "addr:full":"Calle de Tinte Bajo, 5 Sig\u00fcenza Guadalajara 19250",
    "addr:housenumber":"5",
    "addr:postcode":"19250",
    "addr:street":"Calle De Tinte Bajo",
    "iso:country":"ES",
    "sg:address":"Calle de Tinte Bajo, 5",
    "sg:city":"Sig\u00fcenza",
    "sg:orig_category":"Reposter\u00cdas",
    "sg:phone":"+34 949 39 32 23",
    "sg:postcode":"19250",
    "sg:province":"Guadalajara",
    "wof:name":"Luis Mijai Covei",
    "wof:placetype":"venue"
},
  "geometry": {"coordinates":[-2.6445589066,41.0634117126],"type":"Point"}
}