{
  "type": "Feature",
  "properties": {
    "iso:country":"ES",
    "sg:address":"Calle de Principe De Asturias, 12",
    "sg:city":"Petrer",
    "sg:orig_category":"Venta, Instalaci\u00d3n De Calefacci\u00d3n",
    "sg:phone":"+34 965 37 77 43",
    "sg:postcode":"03610",
    "sg:province":"Alicante",
    "wof:name":"Pina Clima S.l.",
    "wof:placetype":"venue"
},
  "geometry": {"coordinates":[-0.7789919972,38.4825248718],"type":"Point"}
}