{
  "type": "Feature",
  "properties": {
    "addr:full":"Carr Castell, 13 Talavera Lleida 25213",
    "addr:housenumber":"13",
    "addr:postcode":"25213",
    "addr:street":"Carr Castell",
    "iso:country":"ES",
    "sg:address":"Carr Castell, 13",
    "sg:city":"Talavera",
    "sg:orig_category":"Producci\u00d3n, Venta De Productos De Agricultura Biol\u00d3gica",
    "sg:phone":"+34 973 54 01 07",
    "sg:postcode":"25213",
    "sg:province":"Lleida",
    "wof:name":"Ramon Trullols S.l.",
    "wof:placetype":"venue"
},
  "geometry": {"coordinates":[1.3369519711,41.5816879272],"type":"Point"}
}