{
  "type": "Feature",
  "properties": {
    "addr:full":"Crtra. As 18, S/n Gijon Asturias 33211",
    "addr:housenumber":"18 s / n",
    "addr:postcode":"33211",
    "iso:country":"ES",
    "sg:address":"Crtra. As 18, S/n",
    "sg:city":"Gijon",
    "sg:orig_category":"Loter\u00cda Y T\u00d3mbola",
    "sg:phone":"+34 985 16 73 69",
    "sg:postcode":"33211",
    "sg:province":"Asturias",
    "wof:name":"Mu\u00f1iz Entrialgo Lourdes",
    "wof:placetype":"venue"
},
  "geometry": {"coordinates":[-5.6863942146,43.5233383179],"type":"Point"}
}