{
  "type": "Feature",
  "properties": {
    "iso:country":"ES",
    "sg:address":"Ctra Guipuzcoa, Km. 0005,0",
    "sg:city":"Berrioplano",
    "sg:orig_category":"Ropa Para Ni\u00d1os (al Por Menor)",
    "sg:phone":"+34 948 30 33 21",
    "sg:postcode":"31195",
    "sg:province":"Navarra",
    "sg:website":"www.ziraketan.com",
    "wof:name":"Ziraketan S.l.",
    "wof:placetype":"venue"
},
  "geometry": {"coordinates":[-1.6811271906,42.8428039551],"type":"Point"}
}