{
  "type": "Feature",
  "properties": {
    "addr:full":"Calle de Rio Ter, 5 Dolores Murcia 30310",
    "addr:housenumber":"5",
    "addr:postcode":"30310",
    "addr:street":"Calle De Rio Ter",
    "iso:country":"ES",
    "sg:address":"Calle de Rio Ter, 5",
    "sg:city":"Dolores",
    "sg:orig_category":"Complementos De Vestir (al Por Menor)",
    "sg:phone":"+34 968 51 68 29",
    "sg:postcode":"30310",
    "sg:province":"Murcia",
    "wof:name":"Lopez Checa Lidia",
    "wof:placetype":"venue"
},
  "geometry": {"coordinates":[-1.0051339865,37.6403884888],"type":"Point"}
}