{
  "type": "Feature",
  "properties": {
    "addr:full":"Ctra Chella, Km. 0004,0 Anna Valencia 46820",
    "addr:postcode":"46820",
    "addr:street":"Ctra Chella Km. 0004,0 Anna",
    "iso:country":"ES",
    "sg:address":"Ctra Chella, Km. 0004,0",
    "sg:city":"Anna",
    "sg:orig_category":"Agricultura: Abastecimiento Y Cosechado (negocio)",
    "sg:phone":"+34 962 92 22 00",
    "sg:postcode":"46820",
    "sg:province":"Valencia",
    "wof:name":"Agima Agricola S.l.",
    "wof:placetype":"venue"
},
  "geometry": {"coordinates":[-0.6505640745,39.0202598572],"type":"Point"}
}