{
  "type": "Feature",
  "properties": {
    "addr:full":"Avda Ca\u00d1a (la), 3 Algeciras C\u00e1diz 11203",
    "addr:housenumber":"3;ca\u0301diz",
    "addr:postcode":"11203",
    "addr:street":"Avda Can\u0303A La",
    "iso:country":"ES",
    "sg:address":"Avda Ca\u00d1a (la), 3",
    "sg:city":"Algeciras",
    "sg:orig_category":"Electricidad, Electr\u00d3nica: Suministros (al Por Menor)",
    "sg:phone":"+34 956 63 47 26",
    "sg:postcode":"11203",
    "sg:province":"C\u00e1diz",
    "wof:name":"Alcaide Delicado Jose Luis",
    "wof:placetype":"venue"
},
  "geometry": {"coordinates":[-5.5040016174,36.131477356],"type":"Point"}
}