{
  "type": "Feature",
  "properties": {
    "addr:full":"Avda Antona Garcia, 8 Toro Zamora 49800",
    "addr:housenumber":"8",
    "addr:postcode":"49800",
    "addr:street":"Avda Antona Garcia",
    "iso:country":"ES",
    "sg:address":"Avda Antona Garcia, 8",
    "sg:city":"Toro",
    "sg:orig_category":"Negocio De Madera",
    "sg:phone":"+34 980 69 01 84",
    "sg:postcode":"49800",
    "sg:province":"Zamora",
    "wof:name":"Ordax Morales Manuel",
    "wof:placetype":"venue"
},
  "geometry": {"coordinates":[-5.3865308762,41.5201263428],"type":"Point"}
}