{
  "type": "Feature",
  "properties": {
    "iso:country":"ES",
    "sg:address":"Carr Consolacio, 18",
    "sg:city":"Villarreal",
    "sg:orig_category":"Caf\u00c9s, Bares, Cervecer\u00cdas",
    "sg:phone":"+34 964 53 57 30",
    "sg:postcode":"12540",
    "sg:province":"Castell\u00f3n",
    "wof:name":"Gil Cheza C.b.",
    "wof:placetype":"venue"
},
  "geometry": {"coordinates":[-0.0952939987,39.9453048706],"type":"Point"}
}