{
  "type": "Feature",
  "properties": {
    "iso:country":"ES",
    "sg:address":"Carr Pi I Margall, 32",
    "sg:city":"Lleida",
    "sg:orig_category":"M\u00dasicos Int\u00c9rpretes",
    "sg:phone":"+34 973 23 48 79",
    "sg:postcode":"25004",
    "sg:province":"Lleida",
    "wof:name":"Monguilod Porqueras Juli",
    "wof:placetype":"venue"
},
  "geometry": {"coordinates":[0.6278100014,41.6213188171],"type":"Point"}
}