{
  "type": "Feature",
  "properties": {
    "addr:full":"Calle de Galicia, 19 Fuenlabrada Madrid 28942",
    "addr:housenumber":"19",
    "addr:postcode":"28942",
    "addr:street":"Calle De Galicia",
    "iso:country":"ES",
    "sg:address":"Calle de Galicia, 19",
    "sg:city":"Fuenlabrada",
    "sg:orig_category":"Peluquer\u00cdas, Peluquer\u00cda Mixta",
    "sg:phone":"+34 916 07 67 93",
    "sg:postcode":"28942",
    "sg:province":"Madrid",
    "wof:name":"Hernandez Ruiz Eugenio",
    "wof:placetype":"venue"
},
  "geometry": {"coordinates":[-3.8100595474,40.296081543],"type":"Point"}
}