{
  "type": "Feature",
  "properties": {
    "iso:country":"ES",
    "sg:address":"Calle de Manga De Gaban, 19",
    "sg:city":"Palma Rio",
    "sg:orig_category":"Lavado, Limpieza De Veh\u00cdculos",
    "sg:phone":"+34 957 64 32 07",
    "sg:postcode":"14700",
    "sg:province":"C\u00f3rdoba",
    "wof:name":"Mu\u00f1oz Leon Juan",
    "wof:placetype":"venue"
},
  "geometry": {"coordinates":[-5.28399086,37.6977272034],"type":"Point"}
}