{
  "type": "Feature",
  "properties": {
    "iso:country":"ES",
    "sg:address":"Calle de Santo Domingo, 12",
    "sg:city":"Puerto De Santa Maria",
    "sg:orig_category":"Asesor\u00cda Sobre Comunicaci\u00d3n De Empresas",
    "sg:phone":"+34 956 54 10 82",
    "sg:postcode":"11500",
    "sg:province":"C\u00e1diz",
    "wof:name":"Consultores Asociados De Andalucia S.l.",
    "wof:placetype":"venue"
},
  "geometry": {"coordinates":[-6.2270498276,36.5977401733],"type":"Point"}
}