{
  "type": "Feature",
  "properties": {
    "addr:full":"Av Pau Claris, 13 Martorell Barcelona 08760",
    "addr:housenumber":"13",
    "addr:postcode":"08760",
    "addr:street":"Av Pau Claris",
    "iso:country":"ES",
    "sg:address":"Av Pau Claris, 13",
    "sg:city":"Martorell",
    "sg:orig_category":"Distribuci\u00d3n De Petr\u00d3leo Y Derivados",
    "sg:phone":"+34 937 75 20 04",
    "sg:postcode":"08760",
    "sg:province":"Barcelona",
    "wof:name":"Repsol Ypf S.a.",
    "wof:placetype":"venue"
},
  "geometry": {"coordinates":[1.9253100157,41.4747085571],"type":"Point"}
}