{
  "type": "Feature",
  "properties": {
    "addr:full":"Ctra Perales-albares (de), Km. 0007,0 Caraba\u00d1a Madrid 28560",
    "addr:postcode":"28560",
    "addr:street":"Ctra Perales-Albares De Km. 0007,0",
    "iso:country":"ES",
    "sg:address":"Ctra Perales-albares (de), Km. 0007,0",
    "sg:city":"Caraba\u00d1a",
    "sg:orig_category":"Poller\u00cda Y Caza (al Por Menor)",
    "sg:phone":"+34 918 72 31 84",
    "sg:postcode":"28560",
    "sg:province":"Madrid",
    "wof:name":"Juan Redondo E Hijos S. A. T.",
    "wof:placetype":"venue"
},
  "geometry": {"coordinates":[-3.2343740463,40.2568740845],"type":"Point"}
}