{
  "type": "Feature",
  "properties": {
    "iso:country":"ES",
    "sg:address":"Calle de Juan Pacheco, S/n",
    "sg:city":"Albacete",
    "sg:orig_category":"Carnicer\u00cdas, Carnicer\u00cdas",
    "sg:phone":"+34 967 21 98 20",
    "sg:postcode":"02006",
    "sg:province":"Albacete",
    "wof:name":"Rodriguez Sierra Jesus",
    "wof:placetype":"venue"
},
  "geometry": {"coordinates":[-1.8429470062,38.9894371033],"type":"Point"}
}