{
  "type": "Feature",
  "properties": {
    "iso:country":"ES",
    "sg:address":"Calle de Kresaltzu, 9",
    "sg:city":"Arenas -areeta",
    "sg:orig_category":"M\u00c9dicos: Evaluaci\u00d3n Y Tratamiento Del Dolor",
    "sg:phone":"+34 944 80 22 83",
    "sg:postcode":"48930",
    "sg:province":"Vizcaya",
    "wof:name":"Vallejo Irastorza Jorge",
    "wof:placetype":"venue"
},
  "geometry": {"coordinates":[-2.6983869076,43.2204284668],"type":"Point"}
}