{
  "type": "Feature",
  "properties": {
    "addr:full":"Avda Santa Eulalia, 70 Totana Murcia 30850",
    "addr:housenumber":"70",
    "addr:postcode":"30850",
    "addr:street":"Avda Santa Eulalia",
    "iso:country":"ES",
    "sg:address":"Avda Santa Eulalia, 70",
    "sg:city":"Totana",
    "sg:orig_category":"Reposter\u00cdas",
    "sg:phone":"+34 968 42 07 80",
    "sg:postcode":"30850",
    "sg:province":"Murcia",
    "wof:name":"Lopez Molina Gines",
    "wof:placetype":"venue"
},
  "geometry": {"coordinates":[-1.5044939518,37.7734718323],"type":"Point"}
}