{
  "type": "Feature",
  "properties": {
    "addr:full":"Calle de Zamora, 50 Salamanca Salamanca 37002",
    "addr:housenumber":"50",
    "addr:postcode":"37002",
    "addr:street":"Calle De Zamora",
    "iso:country":"ES",
    "sg:address":"Calle de Zamora, 50",
    "sg:city":"Salamanca",
    "sg:orig_category":"M\u00c9dicos: Estomatolog\u00cda",
    "sg:phone":"+34 923 28 12 35",
    "sg:postcode":"37002",
    "sg:province":"Salamanca",
    "wof:name":"Peix Sanchez Manuel",
    "wof:placetype":"venue"
},
  "geometry": {"coordinates":[-5.6639041901,40.967666626],"type":"Point"}
}