{
  "type": "Feature",
  "properties": {
    "addr:full":"Avda Zumalacarregui, 48 Bilbao Vizcaya 48006",
    "addr:housenumber":"48",
    "addr:postcode":"48006",
    "addr:street":"Avda Zumalacarregui",
    "iso:country":"ES",
    "sg:address":"Avda Zumalacarregui, 48",
    "sg:city":"Bilbao",
    "sg:orig_category":"Ropa De Trabajo Y Profesionales (fabricaci\u00d3n, Al Por Mayor)",
    "sg:phone":"+34 944 11 60 29",
    "sg:postcode":"48006",
    "sg:province":"Vizcaya",
    "wof:name":"Jesus Lama Merino",
    "wof:placetype":"venue"
},
  "geometry": {"coordinates":[-2.9120800495,43.2568626404],"type":"Point"}
}