{
  "type": "Feature",
  "properties": {
    "iso:country":"ES",
    "sg:address":"El Calvario, 8",
    "sg:city":"Los Llanos Aridane",
    "sg:orig_category":"Centros Comerciales Y Grandes Tiendas",
    "sg:phone":"+34 922 40 23 65",
    "sg:postcode":"38760",
    "sg:province":"Santa Cruz De Tenerife",
    "wof:name":"Leon Cardenas Estrella",
    "wof:placetype":"venue"
},
  "geometry": {"coordinates":[-17.9088306427,28.6583518982],"type":"Point"}
}