{
  "type": "Feature",
  "properties": {
    "iso:country":"ES",
    "sg:address":"Avgd Pais Valencia, 2",
    "sg:city":"Betera",
    "sg:orig_category":"Promotores Constructores",
    "sg:phone":"+34 961 69 14 93",
    "sg:postcode":"46117",
    "sg:province":"Valencia",
    "wof:name":"Construcciones Camilo Y Angel S.l.",
    "wof:placetype":"venue"
},
  "geometry": {"coordinates":[-0.4664010108,39.5921859741],"type":"Point"}
}