{
  "type": "Feature",
  "properties": {
    "iso:country":"ES",
    "sg:address":"Pase Libertad De (la), 5",
    "sg:city":"Arnedo",
    "sg:orig_category":"Molduras, Junquillos, Listones Y Molduras Perforadas",
    "sg:phone":"+34 941 38 35 57",
    "sg:postcode":"26580",
    "sg:province":"La Rioja",
    "wof:name":"Julio Eguizabal Y Rocio S.c.",
    "wof:placetype":"venue"
},
  "geometry": {"coordinates":[-2.1006450653,42.2262573242],"type":"Point"}
}