{
  "type": "Feature",
  "properties": {
    "addr:full":"Calle de Olmo, 2 Puebla Alfinden Zaragoza 50171",
    "addr:housenumber":"2",
    "addr:postcode":"50171",
    "addr:street":"Calle De Olmo;Alfinden",
    "iso:country":"ES",
    "sg:address":"Calle de Olmo, 2",
    "sg:city":"Puebla Alfinden",
    "sg:orig_category":"Comercio De Piezas De Recambio Y De Accesorios De Veh\u00cdculos, Veh\u00cdculos Industriales",
    "sg:phone":"+34 976 10 84 94",
    "sg:postcode":"50171",
    "sg:province":"Zaragoza",
    "wof:name":"Aragonesa De Parabrisas S. A.",
    "wof:placetype":"venue"
},
  "geometry": {"coordinates":[-0.7671502829,41.6420478821],"type":"Point"}
}