{
  "type": "Feature",
  "properties": {
    "addr:full":"Rua Alfonso Senra, 139 Ordes La Coru\u00f1a 15680",
    "addr:housenumber":"139",
    "addr:postcode":"15680",
    "addr:street":"Rua Alfonso Senra;La Corun\u0303A",
    "iso:country":"ES",
    "sg:address":"Rua Alfonso Senra, 139",
    "sg:city":"Ordes",
    "sg:orig_category":"Farmacias",
    "sg:phone":"+34 981 68 07 37",
    "sg:postcode":"15680",
    "sg:province":"La Coru\u00f1a",
    "wof:name":"Li\u00f1ares Stolle Maria Jesus",
    "wof:placetype":"venue"
},
  "geometry": {"coordinates":[-8.4082765579,43.0750083923],"type":"Point"}
}