{
  "type": "Feature",
  "properties": {
    "iso:country":"ES",
    "sg:address":"Calle de Martin Belda, 6",
    "sg:city":"Cabra",
    "sg:orig_category":"Asesor\u00cda Fiscal Y Jur\u00cddica",
    "sg:phone":"+34 957 52 05 21",
    "sg:postcode":"14940",
    "sg:province":"C\u00f3rdoba",
    "wof:name":"Jimenez Luque Jose Manuel",
    "wof:placetype":"venue"
},
  "geometry": {"coordinates":[-4.4438800812,37.4715957642],"type":"Point"}
}