{
  "type": "Feature",
  "properties": {
    "addr:full":"Cmno Marquesa (de La), 1317 Retamar Almer\u00eda 04130",
    "addr:housenumber":"1317",
    "addr:postcode":"04130",
    "addr:street":"Cmno Marquesa De La",
    "iso:country":"ES",
    "sg:address":"Cmno Marquesa (de La), 1317",
    "sg:city":"Retamar",
    "sg:orig_category":"Invernaderos Y Semilleros",
    "sg:phone":"+34 950 20 83 66",
    "sg:postcode":"04130",
    "sg:province":"Almer\u00eda",
    "wof:name":"Contratas Agrarias S.l.",
    "wof:placetype":"venue"
},
  "geometry": {"coordinates":[-2.3529150486,36.8523406982],"type":"Point"}
}