{
  "type": "Feature",
  "properties": {
    "addr:full":"Carrer de Josep Anselm Clave, 12 Palma Islas Baleares 07002",
    "addr:housenumber":"12",
    "addr:postcode":"07002",
    "addr:street":"Carrer De Josep Anselm Clave",
    "iso:country":"ES",
    "sg:address":"Carrer de Josep Anselm Clave, 12",
    "sg:city":"Palma",
    "sg:orig_category":"Clubes, Asociaciones De Ocio",
    "sg:phone":"+34 971 42 57 37",
    "sg:postcode":"07002",
    "sg:province":"Islas Baleares",
    "wof:name":"Kenia Jovi Models S.l.",
    "wof:placetype":"venue"
},
  "geometry": {"coordinates":[2.6551189423,39.5729827881],"type":"Point"}
}