{
  "type": "Feature",
  "properties": {
    "addr:full":"Carr Pou Nou, S/n Palau D'anglesola Lleida 25243",
    "addr:housenumber":"s / n",
    "addr:postcode":"25243",
    "addr:street":"Carr Pou Nou",
    "iso:country":"ES",
    "sg:address":"Carr Pou Nou, S/n",
    "sg:city":"Palau D'anglesola",
    "sg:orig_category":"Doctores En Medicina",
    "sg:phone":"+34 973 60 17 45",
    "sg:postcode":"25243",
    "sg:province":"Lleida",
    "wof:name":"Rodoreda Meilan Isidro",
    "wof:placetype":"venue"
},
  "geometry": {"coordinates":[1.1051199436,41.649394989],"type":"Point"}
}