{
  "type": "Feature",
  "properties": {
    "iso:country":"ES",
    "sg:address":"Calle de Jose Luis Borau, 8",
    "sg:city":"Zaragoza",
    "sg:orig_category":"Inform\u00c1tica (estudios, Servicios, Asesor\u00cda, Formaci\u00d3n)",
    "sg:phone":"+34 976 51 10 81",
    "sg:postcode":"50018",
    "sg:province":"Zaragoza",
    "sg:website":"www.efeonline.com",
    "wof:name":"Informatica Empresarial Fornies-elorza S.l.",
    "wof:placetype":"venue"
},
  "geometry": {"coordinates":[-0.8813189864,41.6517295837],"type":"Point"}
}