{
  "type": "Feature",
  "properties": {
    "iso:country":"ES",
    "sg:address":"Praj Carretera De Almansa, Km. 0001,3",
    "sg:city":"Campo Arriba",
    "sg:orig_category":"Contenedores (mercanc\u00cdas)",
    "sg:phone":"+34 968 79 05 72",
    "sg:postcode":"30510",
    "sg:province":"Murcia",
    "wof:name":"Candela Transportes De Muebles Yecla S.l.",
    "wof:placetype":"venue"
},
  "geometry": {"coordinates":[-1.1149940491,38.6145591736],"type":"Point"}
}