{
  "type": "Feature",
  "properties": {
    "addr:full":"Calle de Alcala, 114 Madrid Madrid 28009",
    "addr:housenumber":"114",
    "addr:postcode":"28009",
    "addr:street":"Calle De Alcala",
    "iso:country":"ES",
    "sg:address":"Calle de Alcala, 114",
    "sg:city":"Madrid",
    "sg:orig_category":"Abogados",
    "sg:phone":"+34 915 76 49 53",
    "sg:postcode":"28009",
    "sg:province":"Madrid",
    "wof:name":"Fernandez De La Lama Enrique",
    "wof:placetype":"venue"
},
  "geometry": {"coordinates":[-3.6735262871,40.4257698059],"type":"Point"}
}