{
  "type": "Feature",
  "properties": {
    "iso:country":"ES",
    "sg:address":"Poligono Industrial, S/n",
    "sg:city":"Astorga",
    "sg:orig_category":"Negocio De Materiales De Construcci\u00d3n",
    "sg:phone":"+34 987 60 40 23",
    "sg:postcode":"24700",
    "sg:province":"Le\u00f3n",
    "wof:name":"Materiales De Construccion Alonso S.l.",
    "wof:placetype":"venue"
},
  "geometry": {"coordinates":[-6.0532841682,42.4577598572],"type":"Point"}
}