{
  "type": "Feature",
  "properties": {
    "addr:full":"Av Rhode, 123 Roses Girona 17480",
    "addr:housenumber":"123",
    "addr:postcode":"17480",
    "addr:street":"Av Rhode",
    "iso:country":"ES",
    "sg:address":"Av Rhode, 123",
    "sg:city":"Roses",
    "sg:orig_category":"Construcciones Prefabricadas Y Desmontables",
    "sg:phone":"+34 972 25 66 21",
    "sg:postcode":"17480",
    "sg:province":"Girona",
    "wof:name":"Construccions Sebatia Ripoll S.l.",
    "wof:placetype":"venue"
},
  "geometry": {"coordinates":[3.172369957,42.2646903992],"type":"Point"}
}