{
  "type": "Feature",
  "properties": {
    "addr:full":"Avda Castilla (de), 43 Escorial Madrid 28280",
    "addr:housenumber":"43",
    "addr:postcode":"28280",
    "addr:street":"Avda Castilla De",
    "iso:country":"ES",
    "sg:address":"Avda Castilla (de), 43",
    "sg:city":"Escorial",
    "sg:orig_category":"Eletrotecnica",
    "sg:phone":"+34 918 96 93 04",
    "sg:postcode":"28280",
    "sg:province":"Madrid",
    "wof:name":"Kahayan  Pablo Sergio",
    "wof:placetype":"venue"
},
  "geometry": {"coordinates":[-4.1281328201,40.5808944702],"type":"Point"}
}