{
  "type": "Feature",
  "properties": {
    "iso:country":"ES",
    "sg:address":"Carrer de Unio (de La), 58",
    "sg:city":"Tarragona",
    "sg:orig_category":"Estancos",
    "sg:phone":"+34 977 21 36 50",
    "sg:postcode":"43001",
    "sg:province":"Tarragona",
    "wof:name":"Martinez Marti Maria Del Carmen",
    "wof:placetype":"venue"
},
  "geometry": {"coordinates":[1.2509800196,41.1133918762],"type":"Point"}
}