{
  "type": "Feature",
  "properties": {
    "addr:full":"Calle de Pocarropa, S/n Benalua Guadix Granada 18510",
    "addr:housenumber":"s",
    "addr:postcode":"18510",
    "addr:street":"Calle De Pocarropa;/ N Benalua",
    "iso:country":"ES",
    "sg:address":"Calle de Pocarropa, S/n",
    "sg:city":"Benalua Guadix",
    "sg:orig_category":"Sanatorios M\u00c9dico",
    "sg:phone":"+34 958 69 63 14",
    "sg:postcode":"18510",
    "sg:province":"Granada",
    "wof:name":"Servicio Andaluz De Salud",
    "wof:placetype":"venue"
},
  "geometry": {"coordinates":[-3.1677539349,37.3504142761],"type":"Point"}
}