{
  "type": "Feature",
  "properties": {
    "addr:full":"Calle de Nava Y Grimon, 70 San Cristobal De La Laguna Santa Cruz De Tenerife 38201",
    "addr:housenumber":"70",
    "addr:postcode":"38201",
    "addr:street":"Calle De Nava Y Grimon",
    "iso:country":"ES",
    "sg:address":"Calle de Nava Y Grimon, 70",
    "sg:city":"San Cristobal De La Laguna",
    "sg:orig_category":"M\u00c9dicos: Oftalmolog\u00cda",
    "sg:phone":"+34 922 25 24 91",
    "sg:postcode":"38201",
    "sg:province":"Santa Cruz De Tenerife",
    "wof:name":"Martin Hernandez Rodrigo",
    "wof:placetype":"venue"
},
  "geometry": {"coordinates":[-16.3121929169,28.4925842285],"type":"Point"}
}