{
  "type": "Feature",
  "properties": {
    "iso:country":"ES",
    "sg:address":"Pl. Iglesia, S/n",
    "sg:city":"Jedula",
    "sg:orig_category":"Iglesia Cat\u00d3lica",
    "sg:phone":"+34 956 72 21 72",
    "sg:postcode":"11620",
    "sg:province":"C\u00e1diz",
    "wof:name":"Parroquia San Isidro Labrador",
    "wof:placetype":"venue"
},
  "geometry": {"coordinates":[-5.9320340157,36.7243881226],"type":"Point"}
}