{
  "type": "Feature",
  "properties": {
    "iso:country":"ES",
    "sg:address":"Calle de El Orden, 2",
    "sg:city":"Barakaldo",
    "sg:orig_category":"Abogados",
    "sg:phone":"+34 944 38 71 30",
    "sg:postcode":"48901",
    "sg:province":"Vizcaya",
    "wof:name":"Jose Antonio Bara\u00f1ano Cordon",
    "wof:placetype":"venue"
},
  "geometry": {"coordinates":[-2.9878621101,43.2988510132],"type":"Point"}
}