{
  "type": "Feature",
  "properties": {
    "iso:country":"ES",
    "sg:address":"Ctra Algarrobo, Km. 0002,2",
    "sg:city":"Algarrobo",
    "sg:orig_category":"Congelados: Productos Alimentarios (fabricaci\u00d3n, Al Por Mayor)",
    "sg:phone":"+34 952 55 27 85",
    "sg:postcode":"29750",
    "sg:province":"M\u00e1laga",
    "wof:name":"Gil Ruiz Juan Luis",
    "wof:placetype":"venue"
},
  "geometry": {"coordinates":[-4.038918972,36.7717437744],"type":"Point"}
}