{
  "type": "Feature",
  "properties": {
    "iso:country":"ES",
    "sg:address":"Via Portugal, 62",
    "sg:city":"Manacor",
    "sg:orig_category":"Electrodom\u00c9sticos (al Por Menor)",
    "sg:phone":"+34 971 84 30 47",
    "sg:postcode":"07500",
    "sg:province":"Islas Baleares",
    "wof:name":"Distribuidora Balear De Electrodomesticos S.a.",
    "wof:placetype":"venue"
},
  "geometry": {"coordinates":[3.2193009853,39.5681266785],"type":"Point"}
}