{
  "type": "Feature",
  "properties": {
    "iso:country":"ES",
    "sg:address":"Calle de Juan Ramon Jimenez, 7",
    "sg:city":"Sevilla",
    "sg:orig_category":"Arquitectos",
    "sg:phone":"+34 954 27 51 04",
    "sg:postcode":"41011",
    "sg:province":"Sevilla",
    "wof:name":"Gallardo Mu\u00f1oz Pablo",
    "wof:placetype":"venue"
},
  "geometry": {"coordinates":[-5.9986162186,37.3752708435],"type":"Point"}
}