{
  "type": "Feature",
  "properties": {
    "addr:full":"Calle de Capitan Haya, 9 Madrid Madrid 28020",
    "addr:housenumber":"9",
    "addr:postcode":"madrid;28020",
    "addr:street":"Calle De Capitan Haya",
    "iso:country":"ES",
    "sg:address":"Calle de Capitan Haya, 9",
    "sg:city":"Madrid",
    "sg:orig_category":"Sociedades, Compa\u00d1\u00cdas Aseguradoras",
    "sg:phone":"+34 915 56 09 75",
    "sg:postcode":"28020",
    "sg:province":"Madrid",
    "sg:website":"www.csmcorreduria.es",
    "wof:name":"Correduria De Seguros De Madrid S.a",
    "wof:placetype":"venue"
},
  "geometry": {"coordinates":[-3.6924264431,40.4547576904],"type":"Point"}
}