{
  "type": "Feature",
  "properties": {
    "iso:country":"ES",
    "sg:address":"Carrer de Merce, 32",
    "sg:city":"Premia Mar",
    "sg:orig_category":"Platos Preparados Refrigerados (fabricaci\u00d3n, Al Por Mayor)",
    "sg:phone":"+34 937 52 53 15",
    "sg:postcode":"08330",
    "sg:province":"Barcelona",
    "wof:name":"Matallana Alvarez Margarita",
    "wof:placetype":"venue"
},
  "geometry": {"coordinates":[2.3550128937,41.4951133728],"type":"Point"}
}