{
  "type": "Feature",
  "properties": {
    "addr:full":"Calle de Revolgo, S/n Santillana Cantabria 39330",
    "addr:housenumber":"s / n",
    "addr:postcode":"39330",
    "addr:street":"Calle De Revolgo",
    "iso:country":"ES",
    "sg:address":"Calle de Revolgo, S/n",
    "sg:city":"Santillana",
    "sg:orig_category":"Hoteles",
    "sg:phone":"+34 942 81 81 01",
    "sg:postcode":"39330",
    "sg:province":"Cantabria",
    "wof:name":"Fuentes Alvarez Francisco",
    "wof:placetype":"venue"
},
  "geometry": {"coordinates":[-4.1113791466,43.3883094788],"type":"Point"}
}