{
  "type": "Feature",
  "properties": {
    "addr:full":"Calle de Nueva, 32 Mairena Aljarafe Sevilla 41927",
    "addr:housenumber":"32",
    "addr:postcode":"41927",
    "addr:street":"Calle De Nueva",
    "iso:country":"ES",
    "sg:address":"Calle de Nueva, 32",
    "sg:city":"Mairena Aljarafe",
    "sg:orig_category":"Estancos",
    "sg:phone":"+34 954 18 18 50",
    "sg:postcode":"41927",
    "sg:province":"Sevilla",
    "wof:name":"Razo Garcia Manuel Felix",
    "wof:placetype":"venue"
},
  "geometry": {"coordinates":[-6.0641012192,37.3445472717],"type":"Point"}
}