{
  "type": "Feature",
  "properties": {
    "addr:full":"Calle de Estribor (de), 2 Humera-somosaguas-prado Del Rey Madrid 28223",
    "addr:postcode":"28223",
    "addr:street":"Calle De Estribor De 2 Humera-Somosaguas-Prado Del",
    "iso:country":"ES",
    "sg:address":"Calle de Estribor (de), 2",
    "sg:city":"Humera-somosaguas-prado Del Rey",
    "sg:orig_category":"Estudios De Grabaci\u00d3n Sonora",
    "sg:phone":"+34 913 52 14 32",
    "sg:postcode":"28223",
    "sg:province":"Madrid",
    "wof:name":"Multidesing",
    "wof:placetype":"venue"
},
  "geometry": {"coordinates":[-3.8007159233,40.4228096008],"type":"Point"}
}