{
  "type": "Feature",
  "properties": {
    "addr:full":"Carrer de Espronceda, 21 Barcelona Barcelona 08005",
    "addr:housenumber":"21",
    "addr:postcode":"08005",
    "addr:street":"Carrer De Espronceda",
    "iso:country":"ES",
    "sg:address":"Carrer de Espronceda, 21",
    "sg:city":"Barcelona",
    "sg:orig_category":"Textil",
    "sg:phone":"+34 934 59 13 03",
    "sg:postcode":"08005",
    "sg:province":"Barcelona",
    "sg:website":"www.eventop.com",
    "wof:name":"Eventop Carpas S.l.",
    "wof:placetype":"venue"
},
  "geometry": {"coordinates":[2.2086400986,41.4021644592],"type":"Point"}
}