{
  "type": "Feature",
  "properties": {
    "iso:country":"ES",
    "sg:address":"Avda Aguilera, 30",
    "sg:city":"Alacant",
    "sg:orig_category":"Renovaci\u00d3n Inmobiliaria",
    "sg:phone":"+34 965 98 65 69",
    "sg:postcode":"03006",
    "sg:province":"Alicante",
    "sg:website":"www.torremar.net",
    "wof:name":"Rehabilitacion Y Mantenimiento Alicante S.l.",
    "wof:placetype":"venue"
},
  "geometry": {"coordinates":[-0.5038599968,38.3429756165],"type":"Point"}
}