{
  "type": "Feature",
  "properties": {
    "iso:country":"ES",
    "sg:address":"Carr Pare Lluis Rodes, 35",
    "sg:city":"Santa Coloma De Farners",
    "sg:orig_category":"Compraventa De Antig\u00dcedades",
    "sg:phone":"+34 972 84 07 10",
    "sg:postcode":"17430",
    "sg:province":"Girona",
    "wof:name":"Valls Canaleta Salvador",
    "wof:placetype":"venue"
},
  "geometry": {"coordinates":[2.6631419659,41.8622512817],"type":"Point"}
}