{
  "type": "Feature",
  "properties": {
    "addr:full":"Avda Portugal, 26 Gijon Asturias 33207",
    "addr:housenumber":"26",
    "addr:postcode":"33207",
    "addr:street":"Avda Portugal",
    "iso:country":"ES",
    "sg:address":"Avda Portugal, 26",
    "sg:city":"Gijon",
    "sg:orig_category":"Panader\u00cdas, Panader\u00cdas",
    "sg:phone":"+34 984 19 14 09",
    "sg:postcode":"33207",
    "sg:province":"Asturias",
    "wof:name":"Rosgon Obrador S.l",
    "wof:placetype":"venue"
},
  "geometry": {"coordinates":[-5.6693291664,43.5383911133],"type":"Point"}
}