{
  "type": "Feature",
  "properties": {
    "addr:full":"Elkano Auzoa, 28 Elkano Guip\u00f9zcoa 20809",
    "addr:housenumber":"28",
    "addr:postcode":"20809",
    "addr:street":"Elkano Auzoa;Guipu\u0300Zcoa",
    "iso:country":"ES",
    "sg:address":"Elkano Auzoa, 28",
    "sg:city":"Elkano",
    "sg:orig_category":"Madera Para Construcci\u00d3n E Industria",
    "sg:phone":"+34 943 13 03 67",
    "sg:postcode":"20809",
    "sg:province":"Guip\u00f9zcoa",
    "wof:name":"Etxeberria Galarraga Estanis",
    "wof:placetype":"venue"
},
  "geometry": {"coordinates":[-2.1475191116,43.2376937866],"type":"Point"}
}