{
  "type": "Feature",
  "properties": {
    "iso:country":"ES",
    "sg:address":"Carrer de Mare De Deu De Montserrat, 15",
    "sg:city":"Masnou",
    "sg:orig_category":"Ventas Por Correspondencia Y A Distancia",
    "sg:phone":"+34 935 40 35 21",
    "sg:postcode":"08320",
    "sg:province":"Barcelona",
    "wof:name":"Okata Equipamiento Industrial S.a.",
    "wof:placetype":"venue"
},
  "geometry": {"coordinates":[2.3237199783,41.4809875488],"type":"Point"}
}