{
  "type": "Feature",
  "properties": {
    "addr:full":"Pl Osona, 6 Vic Barcelona 08500",
    "addr:postcode":"08500",
    "addr:street":"Osona",
    "iso:country":"ES",
    "sg:address":"Pl Osona, 6",
    "sg:city":"Vic",
    "sg:orig_category":"Molduras, Junquillos, Listones Y Molduras Perforadas",
    "sg:phone":"+34 938 85 58 01",
    "sg:postcode":"08500",
    "sg:province":"Barcelona",
    "wof:name":"Gonzalez Perez Dionisio",
    "wof:placetype":"venue"
},
  "geometry": {"coordinates":[2.2525210381,41.9338531494],"type":"Point"}
}