{
  "type": "Feature",
  "properties": {
    "addr:full":"La Redonda, 2 Melegis Granada 18658",
    "addr:housenumber":"2",
    "addr:postcode":"18658",
    "addr:street":"Redonda",
    "iso:country":"ES",
    "sg:address":"La Redonda, 2",
    "sg:city":"Melegis",
    "sg:orig_category":"Transportes Por Carretera: Lotes Completos, Mercanc\u00cdas Diversas",
    "sg:phone":"+34 958 79 36 52",
    "sg:postcode":"18658",
    "sg:province":"Granada",
    "wof:name":"Ruiz Sanchez Luis",
    "wof:placetype":"venue"
},
  "geometry": {"coordinates":[-3.5715179443,36.9363174438],"type":"Point"}
}