{
  "type": "Feature",
  "properties": {
    "iso:country":"ES",
    "sg:address":"Escultor Ferreiro, 7",
    "sg:city":"Noia",
    "sg:orig_category":"Molduras, Junquillos, Listones Y Molduras Perforadas",
    "sg:phone":"+34 981 82 01 52",
    "sg:postcode":"15200",
    "sg:province":"La Coru\u00f1a",
    "wof:name":"Albores Martinez Jose Ramon",
    "wof:placetype":"venue"
},
  "geometry": {"coordinates":[-8.8862657547,42.7830505371],"type":"Point"}
}