{
  "type": "Feature",
  "properties": {
    "iso:country":"ES",
    "sg:address":"Raval Sant Miquel, 10",
    "sg:city":"Vallmoll",
    "sg:orig_category":"Escayola Y Productos De Escayola (fabricaci\u00d3n, Al Por Mayor)",
    "sg:phone":"+34 977 63 74 19",
    "sg:postcode":"43144",
    "sg:province":"Tarragona",
    "wof:name":"Yeseros Vallmoll S.c.c.l",
    "wof:placetype":"venue"
},
  "geometry": {"coordinates":[1.2476439476,41.2427597046],"type":"Point"}
}