{
  "type": "Feature",
  "properties": {
    "iso:country":"ES",
    "sg:address":"Carr Mestre Sagrera, 2",
    "sg:city":"Palafrugell",
    "sg:orig_category":"Agencias Y Agentes Comerciales, Representantes",
    "sg:phone":"+34 972 30 01 48",
    "sg:postcode":"17200",
    "sg:province":"Girona",
    "wof:name":"Guitart Ferran Joan",
    "wof:placetype":"venue"
},
  "geometry": {"coordinates":[3.1555850506,41.9176597595],"type":"Point"}
}