{
  "type": "Feature",
  "properties": {
    "iso:country":"ES",
    "sg:address":"Calle de Hernan Cortes, 18",
    "sg:city":"Villanueva Serena",
    "sg:orig_category":"Muebles, Minoristas",
    "sg:phone":"+34 924 84 54 26",
    "sg:postcode":"06700",
    "sg:province":"Badajoz",
    "wof:name":"Ferca S.l.",
    "wof:placetype":"venue"
},
  "geometry": {"coordinates":[-5.7927889824,38.9734992981],"type":"Point"}
}