{
  "type": "Feature",
  "properties": {
    "iso:country":"ES",
    "sg:address":"Disem Torre Pavas, S/n",
    "sg:city":"Rinconada",
    "sg:orig_category":"Negocio De Metales No Ferrosos",
    "sg:phone":"+34 955 79 80 96",
    "sg:postcode":"41309",
    "sg:province":"Sevilla",
    "wof:name":"A.andaluza Metalurgica Ferre S.l.",
    "wof:placetype":"venue"
},
  "geometry": {"coordinates":[-5.996295,37.382641],"type":"Point"}
}