{
  "type": "Feature",
  "properties": {
    "addr:full":"Del Rio, 22 Villarmero Burgos 09197",
    "addr:housenumber":"22",
    "addr:postcode":"09197",
    "addr:street":"Del Rio",
    "iso:country":"ES",
    "sg:address":"Del Rio, 22",
    "sg:city":"Villarmero",
    "sg:orig_category":"Escayola Y Productos De Escayola (fabricaci\u00d3n, Al Por Mayor)",
    "sg:phone":"+34 947 29 21 29",
    "sg:postcode":"09197",
    "sg:province":"Burgos",
    "wof:name":"Decoraciones Ballesteros S.l.",
    "wof:placetype":"venue"
},
  "geometry": {"coordinates":[-3.7139539719,42.4089889526],"type":"Point"}
}