{
  "type": "Feature",
  "properties": {
    "iso:country":"ES",
    "sg:address":"Calle de Fernandez Del Campo, 14",
    "sg:city":"Bilbao",
    "sg:orig_category":"M\u00c9dicos: Psiquiatr\u00cda",
    "sg:phone":"+34 944 44 33 92",
    "sg:postcode":"48010",
    "sg:province":"Vizcaya",
    "wof:name":"Garcia Bravo Jesus",
    "wof:placetype":"venue"
},
  "geometry": {"coordinates":[-2.9338235855,43.2585487366],"type":"Point"}
}