{
  "type": "Feature",
  "properties": {
    "iso:country":"ES",
    "sg:address":"Praz Francisco Fernandez Del Riego, S/n",
    "sg:city":"Vigo",
    "sg:orig_category":"Complementos De Vestir (al Por Menor)",
    "sg:phone":"+34 986 42 33 00",
    "sg:postcode":"36203",
    "sg:province":"Pontevedra",
    "wof:name":"Ondas Vigo C.b.",
    "wof:placetype":"venue"
},
  "geometry": {"coordinates":[-8.7209844589,42.2310943604],"type":"Point"}
}