{
  "type": "Feature",
  "properties": {
    "addr:full":"Calle de Velez, 4 Puertollano Ciudad Real 13500",
    "addr:housenumber":"4",
    "addr:postcode":"13500",
    "addr:street":"Calle De Velez",
    "iso:country":"ES",
    "sg:address":"Calle de Velez, 4",
    "sg:city":"Puertollano",
    "sg:orig_category":"Ropa Para Caballeros (al Por Menor)",
    "sg:phone":"+34 926 42 30 51",
    "sg:postcode":"13500",
    "sg:province":"Ciudad Real",
    "wof:name":"Molinero Aliaga Inocencio",
    "wof:placetype":"venue"
},
  "geometry": {"coordinates":[-4.1083621979,38.6884460449],"type":"Point"}
}