{
  "type": "Feature",
  "properties": {
    "addr:full":"Calle de Pintor Zurbaran, 20 Caceres C\u00e1ceres 10004",
    "addr:housenumber":"20",
    "addr:postcode":"10004",
    "addr:street":"Calle De Pintor Zurbaran;Ca\u0301Ceres",
    "iso:country":"ES",
    "sg:address":"Calle de Pintor Zurbaran, 20",
    "sg:city":"Caceres",
    "sg:orig_category":"Electrodom\u00c9sticos (al Por Menor)",
    "sg:phone":"+34 927 24 64 92",
    "sg:postcode":"10004",
    "sg:province":"C\u00e1ceres",
    "wof:name":"Garcia Congregado Jose Maria",
    "wof:placetype":"venue"
},
  "geometry": {"coordinates":[-6.373693943,39.4768066406],"type":"Point"}
}