{
  "type": "Feature",
  "properties": {
    "addr:full":"Campo De Las Ruedas, S/n Noia La Coru\u00f1a 15200",
    "addr:housenumber":"s / n",
    "addr:postcode":"15200",
    "addr:street":"Ruedas;La Corun\u0303A",
    "iso:country":"ES",
    "sg:address":"Campo De Las Ruedas, S/n",
    "sg:city":"Noia",
    "sg:orig_category":"Asilos De Ancianos. Centros Privados",
    "sg:phone":"+34 981 82 17 02",
    "sg:postcode":"15200",
    "sg:province":"La Coru\u00f1a",
    "wof:name":"Fundacion Romero Blanco Monroy",
    "wof:placetype":"venue"
},
  "geometry": {"coordinates":[-8.8883037567,42.788608551],"type":"Point"}
}