{
  "type": "Feature",
  "properties": {
    "addr:full":"Calle de San Juan, S/n Quintanar Orden Toledo 45800",
    "addr:housenumber":"s / n",
    "addr:postcode":"45800",
    "addr:street":"Calle De San Juan",
    "iso:country":"ES",
    "sg:address":"Calle de San Juan, S/n",
    "sg:city":"Quintanar Orden",
    "sg:orig_category":"M\u00c1rmoles, Granitos Y Piedras Naturales",
    "sg:phone":"+34 925 18 15 80",
    "sg:postcode":"45800",
    "sg:province":"Toledo",
    "wof:name":"Tolpiedra Industrial S.l.",
    "wof:placetype":"venue"
},
  "geometry": {"coordinates":[-3.0456240177,39.5914764404],"type":"Point"}
}