{
  "type": "Feature",
  "properties": {
    "addr:full":"Av Graells, 8 S. Cugat Valles Barcelona 08173",
    "addr:housenumber":"8",
    "addr:postcode":"08173",
    "addr:street":"Av Graells;Barcelona",
    "iso:country":"ES",
    "sg:address":"Av Graells, 8",
    "sg:city":"S. Cugat Valles",
    "sg:orig_category":"Reposter\u00cdas",
    "sg:phone":"+34 936 75 36 56",
    "sg:postcode":"08173",
    "sg:province":"Barcelona",
    "wof:name":"Torres Pahissa Rosa",
    "wof:placetype":"venue"
},
  "geometry": {"coordinates":[2.0724720955,41.4777832031],"type":"Point"}
}