{
  "type": "Feature",
  "properties": {
    "iso:country":"ES",
    "sg:address":"Carrer de Anton Fortuny, 14",
    "sg:city":"Esplugues Llobregat",
    "sg:orig_category":"Goma: Materias Primas (producci\u00d3n, Distribuci\u00d3n)",
    "sg:phone":"+34 933 71 12 70",
    "sg:postcode":"08950",
    "sg:province":"Barcelona",
    "wof:name":"Sociedad Anonima Espa\u00d1ola De Tarjetas De Identificacion Y Credito",
    "wof:placetype":"venue"
},
  "geometry": {"coordinates":[2.0808799267,41.37733078],"type":"Point"}
}