{
  "type": "Feature",
  "properties": {
    "iso:country":"ES",
    "sg:address":"Estd Catabois, 205",
    "sg:city":"Ferrol",
    "sg:orig_category":"Flores Y Plantas Naturales (al Por Mayor)",
    "sg:phone":"+34 981 32 03 89",
    "sg:postcode":"15405",
    "sg:province":"A Coru\u00f1a",
    "wof:name":"Veiga Rodriguez Nicasio",
    "wof:placetype":"venue"
},
  "geometry": {"coordinates":[-8.2303543091,43.4962921143],"type":"Point"}
}