{
  "type": "Feature",
  "properties": {
    "addr:full":"Grup Iturribide, 13 Iturribide Vizcaya 48940",
    "addr:housenumber":"13",
    "addr:postcode":"48940",
    "addr:street":"Iturribide",
    "iso:country":"ES",
    "sg:address":"Grup Iturribide, 13",
    "sg:city":"Iturribide",
    "sg:orig_category":"Zapatos (al Por Menor)",
    "sg:phone":"+34 944 63 02 82",
    "sg:postcode":"48940",
    "sg:province":"Vizcaya",
    "wof:name":"Barado Alvarez Jose Maria",
    "wof:placetype":"venue"
},
  "geometry": {"coordinates":[-2.9860789776,43.3275489807],"type":"Point"}
}