{
  "type": "Feature",
  "properties": {
    "iso:country":"ES",
    "sg:address":"Ciudadela-ziudadela Kalea, 1",
    "sg:city":"Iru\u00f1a",
    "sg:orig_category":"Farmacias",
    "sg:phone":"+34 948 22 13 35",
    "sg:postcode":"31001",
    "sg:province":"Navarra",
    "wof:name":"Roitegui Azagra Maria Carmen",
    "wof:placetype":"venue"
},
  "geometry": {"coordinates":[-1.6477489471,42.815662384],"type":"Point"}
}