{
  "type": "Feature",
  "properties": {
    "addr:full":"Avda Barra\u00d1a, S/n Boiro La Coru\u00f1a 15930",
    "addr:housenumber":"s / n",
    "addr:postcode":"15930",
    "addr:street":"Avda Barran\u0303A;La Corun\u0303A",
    "iso:country":"ES",
    "sg:address":"Avda Barra\u00d1a, S/n",
    "sg:city":"Boiro",
    "sg:orig_category":"Alimentaci\u00d3n General (al Por Mayor)",
    "sg:phone":"+34 981 84 53 27",
    "sg:postcode":"15930",
    "sg:province":"La Coru\u00f1a",
    "wof:name":"Fernandez Somoza Marcelino",
    "wof:placetype":"venue"
},
  "geometry": {"coordinates":[-8.8831424713,42.6450157166],"type":"Point"}
}