{
  "type": "Feature",
  "properties": {
    "iso:country":"ES",
    "sg:address":"Calle de Tres Cruces, 2",
    "sg:city":"Llodio",
    "sg:orig_category":"Metales (labores, Pulido)",
    "sg:phone":"+34 946 72 05 33",
    "sg:postcode":"01400",
    "sg:province":"\u00c1lava",
    "wof:name":"Talleres Hiru Gurutzeta S.l.",
    "wof:placetype":"venue"
},
  "geometry": {"coordinates":[-2.9666318893,43.1366424561],"type":"Point"}
}