{
  "type": "Feature",
  "properties": {
    "iso:country":"ES",
    "sg:address":"Rua Coru\u00d1a, 4",
    "sg:city":"Ourense",
    "sg:orig_category":"Escayola Y Productos De Escayola (fabricaci\u00d3n, Al Por Mayor)",
    "sg:phone":"+34 988 23 87 60",
    "sg:postcode":"32005",
    "sg:province":"Ourense",
    "wof:name":"Conde Prol Ramon",
    "wof:placetype":"venue"
},
  "geometry": {"coordinates":[-7.8642458916,42.3303909302],"type":"Point"}
}