{
  "type": "Feature",
  "properties": {
    "iso:country":"ES",
    "sg:address":"Calle de Gonzalez Silva, S/n",
    "sg:city":"Cisterniga",
    "sg:orig_category":"Cajas De Ahorro",
    "sg:phone":"+34 983 40 12 16",
    "sg:postcode":"47193",
    "sg:province":"Valladolid",
    "sg:website":"www.cajaespana.es",
    "wof:name":"Caja Espa\u00f1a De Inversiones Caja De Ahorros Y Monte De Piedad",
    "wof:placetype":"venue"
},
  "geometry": {"coordinates":[-4.6860890388,41.611415863],"type":"Point"}
}