{
  "type": "Feature",
  "properties": {
    "iso:country":"ES",
    "sg:address":"Calle de San Anton, 34",
    "sg:city":"Granada",
    "sg:orig_category":"Abogados",
    "sg:phone":"+34 958 53 53 86",
    "sg:postcode":"18005",
    "sg:province":"Granada",
    "wof:name":"Lopez Gonzalez Maria Jose",
    "wof:placetype":"venue"
},
  "geometry": {"coordinates":[-3.5998620987,37.1706771851],"type":"Point"}
}