{
  "type": "Feature",
  "properties": {
    "addr:full":"Avgd Museros (de), 11 Massamagrell Valencia 46130",
    "addr:postcode":"46130",
    "iso:country":"ES",
    "sg:address":"Avgd Museros (de), 11",
    "sg:city":"Massamagrell",
    "sg:orig_category":"Agencias Y Agentes Comerciales, Representantes",
    "sg:phone":"+34 961 44 39 35",
    "sg:postcode":"46130",
    "sg:province":"Valencia",
    "wof:name":"Molla Garcia Jose Bernardo",
    "wof:placetype":"venue"
},
  "geometry": {"coordinates":[-0.3329139948,39.5671310425],"type":"Point"}
}