{
  "type": "Feature",
  "properties": {
    "iso:country":"ES",
    "sg:address":"Calle de Claudio Coello, 69",
    "sg:city":"Madrid",
    "sg:orig_category":"Sociedades, Compa\u00d1\u00cdas Aseguradoras",
    "sg:phone":"+34 913 08 15 05",
    "sg:postcode":"28006",
    "sg:province":"Madrid",
    "wof:name":"Grupo Empresarial Ribe Salat S.l.",
    "wof:placetype":"venue"
},
  "geometry": {"coordinates":[-3.6860957146,40.4287261963],"type":"Point"}
}