{
  "type": "Feature",
  "properties": {
    "iso:country":"ES",
    "sg:address":"Uribe Kalea, 3",
    "sg:city":"Arrasate",
    "sg:orig_category":"Inmobiliaria (agencias)",
    "sg:phone":"+34 943 79 39 99",
    "sg:postcode":"20500",
    "sg:province":"Guip\u00f9zcoa",
    "sg:website":"www.garaia.es",
    "wof:name":"Polo De Innovacion Garaia",
    "wof:placetype":"venue"
},
  "geometry": {"coordinates":[-2.4996359348,43.0616264343],"type":"Point"}
}