{
  "type": "Feature",
  "properties": {
    "iso:country":"ES",
    "sg:address":"Calle de Zufre, 1",
    "sg:city":"Ayamonte",
    "sg:orig_category":"M\u00c9dicos: An\u00c1lisis Cl\u00cdnicos",
    "sg:phone":"+34 959 47 06 92",
    "sg:postcode":"21400",
    "sg:province":"Huelva",
    "wof:name":"Rodriguez Revulta Angel",
    "wof:placetype":"venue"
},
  "geometry": {"coordinates":[-7.4032387733,37.2065353394],"type":"Point"}
}