{
  "type": "Feature",
  "properties": {
    "iso:country":"ES",
    "sg:address":"Antonio Garc\u00eda, 5",
    "sg:city":"Torre-pacheco",
    "sg:orig_category":"Promotores Constructores",
    "sg:phone":"+34 968 57 84 16",
    "sg:postcode":"30700",
    "sg:province":"Murcia",
    "sg:website":"www.ctpacheco.com",
    "wof:name":"Construcciones Torre Pacheco S. A.",
    "wof:placetype":"venue"
},
  "geometry": {"coordinates":[-0.9981930256,37.7873420715],"type":"Point"}
}