{
  "type": "Feature",
  "properties": {
    "addr:full":"Calle de Arcos, 5 Artola M\u00e1laga 29...",
    "addr:housenumber":"5;29 ...",
    "addr:street":"Calle De Arcos;Ma\u0301Laga",
    "iso:country":"ES",
    "sg:address":"Calle de Arcos, 5",
    "sg:city":"Artola",
    "sg:orig_category":"Administradores De Bienes Y Delegados De Comunidades De Propietarios",
    "sg:phone":"+34 952 76 23 42",
    "sg:postcode":"29...",
    "sg:province":"M\u00e1laga",
    "wof:name":"La Quinta Administracion S.a.",
    "wof:placetype":"venue"
},
  "geometry": {"coordinates":[-4.7787108421,36.4978065491],"type":"Point"}
}