{
  "type": "Feature",
  "properties": {
    "addr:full":"Pol Ind El Oliveral, 62 P. I. El Oliveral Valencia 46190",
    "addr:housenumber":"62 p.",
    "addr:postcode":"46190",
    "addr:street":"Oliveral;I. El Oliveral",
    "iso:country":"ES",
    "sg:address":"Pol Ind El Oliveral, 62",
    "sg:city":"P. I. El Oliveral",
    "sg:orig_category":"Deportes Y Ocio: Art\u00cdculos Y Ropas (al Por Menor Y Accesorios)",
    "sg:phone":"+34 961 66 55 10",
    "sg:postcode":"46190",
    "sg:province":"Valencia",
    "sg:website":"www.fitnessproyectfactory.com",
    "wof:name":"Fitness Project Mediterraneo S.l.",
    "wof:placetype":"venue"
},
  "geometry": {"coordinates":[-0.5698940158,39.5458450317],"type":"Point"}
}