{
  "type": "Feature",
  "properties": {
    "addr:full":"Calle de Colon, 7 Elda Alicante 03600",
    "addr:housenumber":"7",
    "addr:postcode":"03600",
    "addr:street":"Calle De Colon",
    "iso:country":"ES",
    "sg:address":"Calle de Colon, 7",
    "sg:city":"Elda",
    "sg:orig_category":"Arquitectos",
    "sg:phone":"+34 966 98 23 78",
    "sg:postcode":"03600",
    "sg:province":"Alicante",
    "wof:name":"Peiro Alarcon Miguel",
    "wof:placetype":"venue"
},
  "geometry": {"coordinates":[-0.7968068719,38.4788398743],"type":"Point"}
}