{
  "type": "Feature",
  "properties": {
    "addr:full":"Avda Ferrocarril, 17 Quel La Rioja 26570",
    "addr:housenumber":"17",
    "addr:postcode":"26570",
    "addr:street":"Avda Ferrocarril;Rioja",
    "iso:country":"ES",
    "sg:address":"Avda Ferrocarril, 17",
    "sg:city":"Quel",
    "sg:orig_category":"Promotores Constructores",
    "sg:phone":"+34 941 39 21 88",
    "sg:postcode":"26570",
    "sg:province":"La Rioja",
    "wof:name":"Construcciones Gatun S.l.",
    "wof:placetype":"venue"
},
  "geometry": {"coordinates":[-2.0502929688,42.2275390625],"type":"Point"}
}