{
  "type": "Feature",
  "properties": {
    "addr:full":"Carrer de Verge, 1 Barcelona Barcelona 08001",
    "addr:housenumber":"1",
    "addr:postcode":"08001",
    "addr:street":"Carrer De Verge",
    "iso:country":"ES",
    "sg:address":"Carrer de Verge, 1",
    "sg:city":"Barcelona",
    "sg:orig_category":"Tapicer\u00cdas",
    "sg:phone":"+34 933 18 74 42",
    "sg:postcode":"08001",
    "sg:province":"Barcelona",
    "wof:name":"Creaciones Marly S.l.",
    "wof:placetype":"venue"
},
  "geometry": {"coordinates":[2.1648209095,41.3835067749],"type":"Point"}
}