{
  "type": "Feature",
  "properties": {
    "iso:country":"ES",
    "sg:address":"Ctra Madrid-irun, Km. 0234,5",
    "sg:city":"Burgos",
    "sg:orig_category":"Bricolaje, Herramientas (al Por Menor)",
    "sg:phone":"+34 947 25 63 79",
    "sg:postcode":"09001",
    "sg:province":"Burgos",
    "sg:website":"www.atb-bricolajes.com",
    "wof:name":"Atb Norte S.l.",
    "wof:placetype":"venue"
},
  "geometry": {"coordinates":[-3.7017037868,42.3211631775],"type":"Point"}
}