{
  "type": "Feature",
  "properties": {
    "addr:full":"Pase General Martinez Campos, 44 Madrid Madrid 28010",
    "addr:housenumber":"44",
    "addr:postcode":"madrid;28010",
    "iso:country":"ES",
    "sg:address":"Pase General Martinez Campos, 44",
    "sg:city":"Madrid",
    "sg:orig_category":"Asesor\u00cdas Y Estudios Financieros",
    "sg:phone":"+34 913 08 13 91",
    "sg:postcode":"28010",
    "sg:province":"Madrid",
    "wof:name":"Toro Arrue Javier",
    "wof:placetype":"venue"
},
  "geometry": {"coordinates":[-3.6915030479,40.4350090027],"type":"Point"}
}