{
  "type": "Feature",
  "properties": {
    "iso:country":"ES",
    "sg:address":"Calle de Horno, 7",
    "sg:city":"Maracena",
    "sg:orig_category":"Supermercados Y Hipermercados",
    "sg:phone":"+34 958 41 24 72",
    "sg:postcode":"18200",
    "sg:province":"Granada",
    "wof:name":"Supergran S.a.",
    "wof:placetype":"venue"
},
  "geometry": {"coordinates":[-3.6337723732,37.207359314],"type":"Point"}
}