{
  "type": "Feature",
  "properties": {
    "addr:full":"G.v. Corts Catalanes, 611 Barcelona Barcelona 08007",
    "addr:housenumber":"611",
    "addr:postcode":"08007",
    "addr:street":"Catalanes",
    "iso:country":"ES",
    "sg:address":"G.v. Corts Catalanes, 611",
    "sg:city":"Barcelona",
    "sg:orig_category":"Administradores De Bienes Y Delegados De Comunidades De Propietarios",
    "sg:phone":"+34 933 02 46 26",
    "sg:postcode":"08007",
    "sg:province":"Barcelona",
    "wof:name":"Mateu Del Campo Juan De La Cruz",
    "wof:placetype":"venue"
},
  "geometry": {"coordinates":[2.1682751179,41.3897705078],"type":"Point"}
}