{
  "type": "Feature",
  "properties": {
    "iso:country":"ES",
    "sg:address":"Zaragoza, 94",
    "sg:city":"Juslibol",
    "sg:orig_category":"Librer\u00cdas",
    "sg:phone":"+34 976 73 42 07",
    "sg:postcode":"50191",
    "sg:province":"Zaragoza",
    "wof:name":"Aragonia Promociones Editoriales S.l.",
    "wof:placetype":"venue"
},
  "geometry": {"coordinates":[-0.8981416821,41.6926231384],"type":"Point"}
}