{
  "type": "Feature",
  "properties": {
    "iso:country":"ES",
    "sg:address":"Barr Pe\u00d1acastillo Campon, 22",
    "sg:city":"Pe\u00d1acastillo",
    "sg:orig_category":"Animales (al Por Menor)",
    "sg:phone":"+34 942 33 32 09",
    "sg:postcode":"39011",
    "sg:province":"Cantabria",
    "wof:name":"Tapia Hermanos S. L.",
    "wof:placetype":"venue"
},
  "geometry": {"coordinates":[-3.862869978,43.4475975037],"type":"Point"}
}