{
  "type": "Feature",
  "properties": {
    "iso:country":"ES",
    "sg:address":"Av Jacquard, 105",
    "sg:city":"Terrassa",
    "sg:orig_category":"Fabricaci\u00d3n De Jabones, Detergentes Y Lej\u00cdas",
    "sg:phone":"+34 937 85 72 49",
    "sg:postcode":"08222",
    "sg:province":"Barcelona",
    "wof:name":"Gonzalez Abad Salvador",
    "wof:placetype":"venue"
},
  "geometry": {"coordinates":[2.021707058,41.5641593933],"type":"Point"}
}