{
  "type": "Feature",
  "properties": {
    "addr:full":"Calle de Pozo (del), 32 Barco De Avila \u00c1vila 05600",
    "addr:housenumber":"32",
    "addr:postcode":"05600",
    "addr:street":"Calle De Pozo Del;A\u0301Vila",
    "iso:country":"ES",
    "sg:address":"Calle de Pozo (del), 32",
    "sg:city":"Barco De Avila",
    "sg:orig_category":"Supermercados Y Hipermercados",
    "sg:phone":"+34 920 34 07 96",
    "sg:postcode":"05600",
    "sg:province":"\u00c1vila",
    "wof:name":"Familar Moreno S.l.",
    "wof:placetype":"venue"
},
  "geometry": {"coordinates":[-5.5233039856,40.3561515808],"type":"Point"}
}