{
  "type": "Feature",
  "properties": {
    "iso:country":"ES",
    "sg:address":"Carrer de Ferreria, 2",
    "sg:city":"Palma",
    "sg:orig_category":"Electricidad: Equipos Industriales, Componentes (fabricaci\u00d3n)",
    "sg:phone":"+34 971 71 68 46",
    "sg:postcode":"07002",
    "sg:province":"Islas Baleares",
    "wof:name":"Juan Salom Miguel",
    "wof:placetype":"venue"
},
  "geometry": {"coordinates":[2.6547400951,39.5707359314],"type":"Point"}
}