{
  "type": "Feature",
  "properties": {
    "iso:country":"ES",
    "sg:address":"Comp Puerto Dep.l.campomanes, 12",
    "sg:city":"Galeras Bajas",
    "sg:orig_category":"Construcciones Navales Y Fluviales",
    "sg:phone":"+34 966 88 85 16",
    "sg:postcode":"03590",
    "sg:province":"Alicante",
    "wof:name":"Vicente Belliure Construcciones Navales",
    "wof:placetype":"venue"
},
  "geometry": {"coordinates":[-0.0506840013,38.6008338928],"type":"Point"}
}