{
  "type": "Feature",
  "properties": {
    "addr:full":"Ctra Nacional 340, Km. 0137,0 Torreguadiaro C\u00e1diz 11312",
    "addr:postcode":"11312",
    "addr:street":"Ctra Nacional 340 Km. 0137,0 Torreguadiaro Ca\u0301Diz",
    "iso:country":"ES",
    "sg:address":"Ctra Nacional 340, Km. 0137,0",
    "sg:city":"Torreguadiaro",
    "sg:orig_category":"Electricidad, Electr\u00d3nica: Suministros (al Por Menor)",
    "sg:phone":"+34 956 61 62 60",
    "sg:postcode":"11312",
    "sg:province":"C\u00e1diz",
    "wof:name":"Elitetronic S.l.",
    "wof:placetype":"venue"
},
  "geometry": {"coordinates":[-5.2928490639,36.3059196472],"type":"Point"}
}