{
  "type": "Feature",
  "properties": {
    "addr:full":"Trav Dalt, 35 Barcelona Barcelona 08024",
    "addr:housenumber":"35",
    "addr:postcode":"08024",
    "addr:street":"Trav Dalt",
    "iso:country":"ES",
    "sg:address":"Trav Dalt, 35",
    "sg:city":"Barcelona",
    "sg:orig_category":"Empresarios",
    "sg:phone":"+34 932 10 69 05",
    "sg:postcode":"08024",
    "sg:province":"Barcelona",
    "wof:name":"Fundacion Cultural Rssb Andalucia-espa\u00f1a",
    "wof:placetype":"venue"
},
  "geometry": {"coordinates":[2.1527440548,41.4088478088],"type":"Point"}
}