{
  "type": "Feature",
  "properties": {
    "iso:country":"ES",
    "sg:address":"Carr Major, 56",
    "sg:city":"Rossello",
    "sg:orig_category":"Distribuci\u00d3n De Petr\u00d3leo Y Derivados",
    "sg:phone":"+34 973 22 10 44",
    "sg:postcode":"25124",
    "sg:province":"Lleida",
    "wof:name":"Agip Espa\u00f1a S.a.",
    "wof:placetype":"venue"
},
  "geometry": {"coordinates":[0.59528929,41.6949386597],"type":"Point"}
}