{
  "type": "Feature",
  "properties": {
    "addr:full":"Calle de Mahon, 10 Matas-pinar-monte Rozas Madrid 28290",
    "addr:housenumber":"10",
    "addr:postcode":"28290",
    "addr:street":"Calle De Mahon",
    "iso:country":"ES",
    "sg:address":"Calle de Mahon, 10",
    "sg:city":"Matas-pinar-monte Rozas",
    "sg:orig_category":"Organismos De Turismo",
    "sg:phone":"+34 915 47 73 85",
    "sg:postcode":"28290",
    "sg:province":"Madrid",
    "wof:name":"Lactofresc S.l.",
    "wof:placetype":"venue"
},
  "geometry": {"coordinates":[-3.8985788822,40.5563697815],"type":"Point"}
}