{
  "type": "Feature",
  "properties": {
    "addr:full":"Plaz Carlos Iii, 1 Prado Del Rey C\u00e1diz 11660",
    "addr:postcode":"11660",
    "iso:country":"ES",
    "sg:address":"Plaz Carlos Iii, 1",
    "sg:city":"Prado Del Rey",
    "sg:orig_category":"Marroquiner\u00cda (confecci\u00d3n)",
    "sg:phone":"+34 956 72 30 12",
    "sg:postcode":"11660",
    "sg:province":"C\u00e1diz",
    "wof:name":"Rojas Blanco Francisco",
    "wof:placetype":"venue"
},
  "geometry": {"coordinates":[-5.5557088852,36.7894134521],"type":"Point"}
}