{
  "type": "Feature",
  "properties": {
    "iso:country":"ES",
    "sg:address":"Carr Mossen Anton, 5",
    "sg:city":"Badalona",
    "sg:orig_category":"\u00d3ptica: Instrumentos (fabricaci\u00d3n)",
    "sg:phone":"+34 933 84 52 11",
    "sg:postcode":"08912",
    "sg:province":"Barcelona",
    "wof:name":"Hispanoptica S. A",
    "wof:placetype":"venue"
},
  "geometry": {"coordinates":[2.2483410835,41.4466552734],"type":"Point"}
}