{
  "type": "Feature",
  "properties": {
    "addr:full":"A Brea, 15 Brea A Coru\u00f1a 15640",
    "addr:housenumber":"15",
    "addr:postcode":"15640",
    "addr:street":"Brea;Corun\u0303A",
    "iso:country":"ES",
    "sg:address":"A Brea, 15",
    "sg:city":"Brea",
    "sg:orig_category":"Asociaciones, Organismos Culturales Y Socioeducativos",
    "sg:phone":"+34 981 78 00 52",
    "sg:postcode":"15640",
    "sg:province":"A Coru\u00f1a",
    "wof:name":"Sociedad De Recreo E Instruccion De La Juventud De Guisamo",
    "wof:placetype":"venue"
},
  "geometry": {"coordinates":[-8.2682237625,43.2997894287],"type":"Point"}
}