{
  "type": "Feature",
  "properties": {
    "iso:country":"ES",
    "sg:address":"Calle de Colon, 68",
    "sg:city":"Segorbe",
    "sg:orig_category":"\u00d3ptica: Instrumentos (fabricaci\u00d3n)",
    "sg:phone":"+34 964 71 01 63",
    "sg:postcode":"12400",
    "sg:province":"Castell\u00f3n",
    "wof:name":"Optica Tena C.b.",
    "wof:placetype":"venue"
},
  "geometry": {"coordinates":[-0.489920795,39.8524856567],"type":"Point"}
}