{
  "type": "Feature",
  "properties": {
    "addr:full":"Calle de Silva, 20 Cedeira La Coru\u00f1a 15350",
    "addr:housenumber":"20",
    "addr:postcode":"15350",
    "addr:street":"Calle De Silva;La Corun\u0303A",
    "iso:country":"ES",
    "sg:address":"Calle de Silva, 20",
    "sg:city":"Cedeira",
    "sg:orig_category":"Pescader\u00cdas (al Por Menor)",
    "sg:phone":"+34 981 48 04 46",
    "sg:postcode":"15350",
    "sg:province":"La Coru\u00f1a",
    "wof:name":"Garcia Bello Elena",
    "wof:placetype":"venue"
},
  "geometry": {"coordinates":[-8.0517320633,43.6618461609],"type":"Point"}
}