{
  "type": "Feature",
  "properties": {
    "addr:full":"Ctra Alicante, S/n Grajuela Murcia 30730",
    "addr:housenumber":"s",
    "addr:postcode":"30730",
    "addr:street":"Ctra Alicante;/ N",
    "iso:country":"ES",
    "sg:address":"Ctra Alicante, S/n",
    "sg:city":"Grajuela",
    "sg:orig_category":"Supermercados Y Hipermercados",
    "sg:phone":"+34 968 54 71 00",
    "sg:postcode":"30730",
    "sg:province":"Murcia",
    "wof:name":"Erosmer Iberica S.a.",
    "wof:placetype":"venue"
},
  "geometry": {"coordinates":[-0.8377289772,37.8054389954],"type":"Point"}
}