{
  "type": "Feature",
  "properties": {
    "addr:full":"Carr Mossen Bartomeu, S/n Sant Joan Les Fonts Girona 17857",
    "addr:housenumber":"s",
    "addr:postcode":"17857",
    "addr:street":"Carr Mossen Bartomeu;/ N",
    "iso:country":"ES",
    "sg:address":"Carr Mossen Bartomeu, S/n",
    "sg:city":"Sant Joan Les Fonts",
    "sg:orig_category":"Promotores Constructores",
    "sg:phone":"+34 972 29 04 44",
    "sg:postcode":"17857",
    "sg:province":"Girona",
    "wof:name":"Construccions Sant Joan S.l.",
    "wof:placetype":"venue"
},
  "geometry": {"coordinates":[2.5139949322,42.2144813538],"type":"Point"}
}