{
  "type": "Feature",
  "properties": {
    "iso:country":"ES",
    "sg:address":"Bajo Vila, 99",
    "sg:city":"Torre D'en Besora",
    "sg:orig_category":"Empresarios",
    "sg:phone":"+34 964 44 60 33",
    "sg:postcode":"12161",
    "sg:province":"Castell\u00f3n",
    "wof:name":"Belles Villaplana Emilio",
    "wof:placetype":"venue"
},
  "geometry": {"coordinates":[-0.0786478966,40.3264007568],"type":"Point"}
}