{
  "type": "Feature",
  "properties": {
    "iso:country":"ES",
    "sg:address":"Calle de Rio, 29",
    "sg:city":"Argamasilla Calatrava",
    "sg:orig_category":"Promotores Constructores",
    "sg:phone":"+34 926 46 00 19",
    "sg:postcode":"13440",
    "sg:province":"Ciudad Real",
    "wof:name":"Construcciones Virgen De Gracia S.l.",
    "wof:placetype":"venue"
},
  "geometry": {"coordinates":[-4.0784788132,38.7269592285],"type":"Point"}
}