{
  "type": "Feature",
  "properties": {
    "iso:country":"ES",
    "sg:address":"Calle de Carranza, 16",
    "sg:city":"Madrid",
    "sg:orig_category":"Abogados",
    "sg:phone":"+34 915 91 26 43",
    "sg:postcode":"28004",
    "sg:province":"Madrid",
    "wof:name":"Despacho Rodriguez Alarcon S.l.",
    "wof:placetype":"venue"
},
  "geometry": {"coordinates":[-3.7043170929,40.4294891357],"type":"Point"}
}