{
  "type": "Feature",
  "properties": {
    "iso:country":"ES",
    "sg:address":"Los Arrieros, 1",
    "sg:city":"Olivares",
    "sg:orig_category":"Caf\u00c9s, Bares, Cervecer\u00cdas",
    "sg:phone":"+34 955 71 87 22",
    "sg:postcode":"41804",
    "sg:province":"Sevilla",
    "wof:name":"Diaz Guzman Rocio",
    "wof:placetype":"venue"
},
  "geometry": {"coordinates":[-6.153439045,37.4184074402],"type":"Point"}
}