{
  "type": "Feature",
  "properties": {
    "addr:full":"Avda Arias De Velasco, 4 Marbella M\u00e1laga 29600",
    "addr:housenumber":"4",
    "addr:postcode":"29600",
    "addr:street":"Avda Arias De Velasco;Ma\u0301Laga",
    "iso:country":"ES",
    "sg:address":"Avda Arias De Velasco, 4",
    "sg:city":"Marbella",
    "sg:orig_category":"Muebles, Minoristas",
    "sg:phone":"+34 952 86 82 38",
    "sg:postcode":"29600",
    "sg:province":"M\u00e1laga",
    "wof:name":"Distribuciones Lausilma S.l.",
    "wof:placetype":"venue"
},
  "geometry": {"coordinates":[-4.8855891228,36.5171394348],"type":"Point"}
}