{
  "type": "Feature",
  "properties": {
    "iso:country":"ES",
    "sg:address":"Calle de Medio De San Pedro, 9",
    "sg:city":"Viana",
    "sg:orig_category":"Restaurantes",
    "sg:phone":"+34 948 64 59 27",
    "sg:postcode":"31230",
    "sg:province":"Navarra",
    "wof:name":"Cobaneda Gomez Jesus",
    "wof:placetype":"venue"
},
  "geometry": {"coordinates":[-2.3729529381,42.514705658],"type":"Point"}
}