{
  "type": "Feature",
  "properties": {
    "addr:full":"Calle de Baltasar Gracian, 10 Zaragoza Zaragoza 50005",
    "addr:housenumber":"10",
    "addr:postcode":"50005",
    "addr:street":"Calle De Baltasar Gracian",
    "iso:country":"ES",
    "sg:address":"Calle de Baltasar Gracian, 10",
    "sg:city":"Zaragoza",
    "sg:orig_category":"Loter\u00cda Y T\u00d3mbola",
    "sg:phone":"+34 976 56 10 93",
    "sg:postcode":"50005",
    "sg:province":"Zaragoza",
    "wof:name":"Oliver Salas Juan",
    "wof:placetype":"venue"
},
  "geometry": {"coordinates":[-0.8939545751,41.6431999207],"type":"Point"}
}