{
  "type": "Feature",
  "properties": {
    "iso:country":"ES",
    "sg:address":"Calle de Gabriela Mistral, 10",
    "sg:city":"Madrid",
    "sg:orig_category":"Asesor\u00cda Sobre Comunicaci\u00d3n De Empresas",
    "sg:phone":"+34 913 16 60 16",
    "sg:postcode":"28035",
    "sg:province":"Madrid",
    "wof:name":"Dictamed I And I S.l.",
    "wof:placetype":"venue"
},
  "geometry": {"coordinates":[-3.736743927,40.4808578491],"type":"Point"}
}