{
  "type": "Feature",
  "properties": {
    "iso:country":"ES",
    "sg:address":"Calle de Suarez Somonte, 7",
    "sg:city":"Merida",
    "sg:orig_category":"Prendas Y Chalecos De Punto (al Por Menor)",
    "sg:phone":"+34 924 31 77 05",
    "sg:postcode":"06800",
    "sg:province":"Badajoz",
    "wof:name":"Comercial De Las Heras S.l.",
    "wof:placetype":"venue"
},
  "geometry": {"coordinates":[-6.34395504,38.9142341614],"type":"Point"}
}