{
  "type": "Feature",
  "properties": {
    "addr:full":"Calle de Buenavista, 8 Madrid Madrid 28012",
    "addr:housenumber":"8",
    "addr:postcode":"madrid;28012",
    "addr:street":"Calle De Buenavista",
    "iso:country":"ES",
    "sg:address":"Calle de Buenavista, 8",
    "sg:city":"Madrid",
    "sg:orig_category":"Serigraf\u00cda (material Y Suministros)",
    "sg:phone":"+34 914 68 58 47",
    "sg:postcode":"28012",
    "sg:province":"Madrid",
    "wof:name":"Gordillo Carreira Manuel",
    "wof:placetype":"venue"
},
  "geometry": {"coordinates":[-3.6984550953,40.4104232788],"type":"Point"}
}