{
  "type": "Feature",
  "properties": {
    "addr:full":"Aneto Pol Ind Valdeconsejo, 3 Cuarte Huerva Zaragoza 50410",
    "addr:housenumber":"3",
    "addr:postcode":"50410",
    "addr:street":"Valdeconsejo",
    "iso:country":"ES",
    "sg:address":"Aneto Pol Ind Valdeconsejo, 3",
    "sg:city":"Cuarte Huerva",
    "sg:orig_category":"Transporte En General",
    "sg:phone":"+34 976 46 30 55",
    "sg:postcode":"50410",
    "sg:province":"Zaragoza",
    "wof:name":"San Lamberto 2000 S.l.",
    "wof:placetype":"venue"
},
  "geometry": {"coordinates":[-0.9296389818,41.6074638367],"type":"Point"}
}