{
  "type": "Feature",
  "properties": {
    "iso:country":"ES",
    "sg:address":"Calle de San Roke, 12",
    "sg:city":"Elorrio",
    "sg:orig_category":"Asociaciones Y Clubs Deportivos",
    "sg:phone":"+34 946 23 18 29",
    "sg:postcode":"48230",
    "sg:province":"Vizcaya",
    "wof:name":"Club Deportivo Elorrio",
    "wof:placetype":"venue"
},
  "geometry": {"coordinates":[-2.5451610088,43.1272239685],"type":"Point"}
}