{
  "type": "Feature",
  "properties": {
    "addr:full":"Carr Teular Nou, S/n Beniarres Alicante 03850",
    "addr:housenumber":"s",
    "addr:postcode":"03850",
    "addr:street":"Carr Teular Nou;/ N Beniarres",
    "iso:country":"ES",
    "sg:address":"Carr Teular Nou, S/n",
    "sg:city":"Beniarres",
    "sg:orig_category":"Muebles Y Accesorios Para Cocinas Y Cuartos De Ba\u00d1o (al Por Menor)",
    "sg:phone":"+34 965 51 53 51",
    "sg:postcode":"03850",
    "sg:province":"Alicante",
    "wof:name":"Carpinteria Hnos.selles C.b",
    "wof:placetype":"venue"
},
  "geometry": {"coordinates":[-0.3762690127,38.82006073],"type":"Point"}
}