{
  "type": "Feature",
  "properties": {
    "iso:country":"ES",
    "sg:address":"Calle de Magallanes, 8",
    "sg:city":"Grao",
    "sg:orig_category":"Ropa Para Beb\u00c9s Y Ni\u00d1os (confecci\u00d3n, Al Por Mayor)",
    "sg:phone":"+34 964 28 05 18",
    "sg:postcode":"12100",
    "sg:province":"Castell\u00f3n",
    "wof:name":"Ferreres Bayarri Lidon",
    "wof:placetype":"venue"
},
  "geometry": {"coordinates":[0.0118739996,39.9729347229],"type":"Point"}
}