{
  "type": "Feature",
  "properties": {
    "addr:full":"Calle de Adrian Viudes, 2 Beniajan Murcia 30570",
    "addr:housenumber":"2",
    "addr:postcode":"30570",
    "addr:street":"Calle De Adrian Viudes",
    "iso:country":"ES",
    "sg:address":"Calle de Adrian Viudes, 2",
    "sg:city":"Beniajan",
    "sg:orig_category":"Asesor\u00cda De Formaci\u00d3n Y Gesti\u00d3n De Personal",
    "sg:phone":"+34 968 82 10 30",
    "sg:postcode":"30570",
    "sg:province":"Murcia",
    "wof:name":"Romero Nicolas Benigno Manuel",
    "wof:placetype":"venue"
},
  "geometry": {"coordinates":[-1.0663211346,37.9794692993],"type":"Point"}
}