{
  "type": "Feature",
  "properties": {
    "addr:full":"Ctra Berga, Km. 0000,7 S. Fruitos Bages Barcelona 08272",
    "addr:postcode":"08272",
    "addr:street":"Ctra Berga Km. 0000,7 S. Fruitos Bages Barcelona",
    "iso:country":"ES",
    "sg:address":"Ctra Berga, Km. 0000,7",
    "sg:city":"S. Fruitos Bages",
    "sg:orig_category":"Confiter\u00cda, Galletas Y Pastas, Chocolater\u00cda (al Por Mayor)",
    "sg:phone":"+34 938 77 18 85",
    "sg:postcode":"08272",
    "sg:province":"Barcelona",
    "sg:website":"www.lapolar.com",
    "wof:name":"Sala Salas S. A.",
    "wof:placetype":"venue"
},
  "geometry": {"coordinates":[1.8779350519,41.7520599365],"type":"Point"}
}