{
  "type": "Feature",
  "properties": {
    "addr:full":"Calle de Conde De Torrefiel, 48 Valencia Valencia 46019",
    "addr:housenumber":"48",
    "addr:postcode":"46019",
    "addr:street":"Calle De Conde De Torrefiel",
    "iso:country":"ES",
    "sg:address":"Calle de Conde De Torrefiel, 48",
    "sg:city":"Valencia",
    "sg:orig_category":"Imprenta",
    "sg:phone":"+34 963 65 13 91",
    "sg:postcode":"46019",
    "sg:province":"Valencia",
    "wof:name":"Mateo Mengod Maximiano",
    "wof:placetype":"venue"
},
  "geometry": {"coordinates":[-0.3765048981,39.4942512512],"type":"Point"}
}