{
  "type": "Feature",
  "properties": {
    "addr:full":"Av Goles De L'ebre, 11 Deltebre Tarragona 43580",
    "addr:housenumber":"11",
    "addr:postcode":"43580",
    "addr:street":"Av Goles De L'Ebre",
    "iso:country":"ES",
    "sg:address":"Av Goles De L'ebre, 11",
    "sg:city":"Deltebre",
    "sg:orig_category":"Restaurantes",
    "sg:phone":"+34 977 48 15 12",
    "sg:postcode":"43580",
    "sg:province":"Tarragona",
    "wof:name":"Ribesagra, S.l",
    "wof:placetype":"venue"
},
  "geometry": {"coordinates":[0.7251949906,40.7229270935],"type":"Point"}
}