{
  "type": "Feature",
  "properties": {
    "iso:country":"ES",
    "sg:address":"Carrer de Joan Carles I, 30",
    "sg:city":"Roda De Bara",
    "sg:orig_category":"Peluqueros: De Se\u00d1oras",
    "sg:phone":"+34 977 80 92 40",
    "sg:postcode":"43883",
    "sg:province":"Tarragona",
    "wof:name":"Vallve Carnice Magdalena",
    "wof:placetype":"venue"
},
  "geometry": {"coordinates":[1.4575500488,41.1855812073],"type":"Point"}
}