{
  "type": "Feature",
  "properties": {
    "iso:country":"ES",
    "sg:address":"Plaz Jose Antonio Vaca De Osma, 7",
    "sg:city":"San Pedro Arroyo",
    "sg:orig_category":"Iglesia Cat\u00d3lica",
    "sg:phone":"+34 920 24 00 34",
    "sg:postcode":"05350",
    "sg:province":"\u00c1vila",
    "wof:name":"Parroquia De San Pedro Apostol",
    "wof:placetype":"venue"
},
  "geometry": {"coordinates":[-4.8702588081,40.8017959595],"type":"Point"}
}