{
  "type": "Feature",
  "properties": {
    "addr:full":"Avda Ernesto Che Guevara, 17 Perillo La Coru\u00f1a 15172",
    "addr:housenumber":"17",
    "addr:postcode":"15172",
    "addr:street":"Avda Ernesto Che Guevara;Perillo La Corun\u0303A",
    "iso:country":"ES",
    "sg:address":"Avda Ernesto Che Guevara, 17",
    "sg:city":"Perillo",
    "sg:orig_category":"Sociedades, Compa\u00d1\u00cdas Aseguradoras",
    "sg:phone":"+34 981 63 73 02",
    "sg:postcode":"15172",
    "sg:province":"La Coru\u00f1a",
    "sg:website":"www.mapfre.com",
    "wof:name":"Mapfre Servicios De Informatica",
    "wof:placetype":"venue"
},
  "geometry": {"coordinates":[-8.3624725342,43.3389854431],"type":"Point"}
}