{
  "type": "Feature",
  "properties": {
    "iso:country":"ES",
    "sg:address":"Juego Bolos, S/n",
    "sg:city":"Valdorros",
    "sg:orig_category":"Trabajos De Perforaciones, Sondeos, Construcci\u00d3n De Pozos",
    "sg:phone":"+34 947 40 41 59",
    "sg:postcode":"09320",
    "sg:province":"Burgos",
    "wof:name":"Briongos Perforaciones Y Servicios S.l.",
    "wof:placetype":"venue"
},
  "geometry": {"coordinates":[-3.7093789577,42.1717453003],"type":"Point"}
}