{
  "type": "Feature",
  "properties": {
    "iso:country":"ES",
    "sg:address":"Avda Barcelona (de), 13",
    "sg:city":"Cordoba",
    "sg:orig_category":"Peluquer\u00cdas, Peluquer\u00cda Mixta",
    "sg:phone":"+34 957 26 88 31",
    "sg:postcode":"14010",
    "sg:province":"C\u00f3rdoba",
    "sg:website":"www.marcoaldany.com",
    "wof:name":"Inversiones Ca\u00d1oz S.l.",
    "wof:placetype":"venue"
},
  "geometry": {"coordinates":[-4.7639122009,37.8881645203],"type":"Point"}
}