{
  "type": "Feature",
  "properties": {
    "addr:full":"Calle de Arga\u00d1osa, 72 Oviedo Asturias 33013",
    "addr:housenumber":"72",
    "addr:postcode":"33013",
    "addr:street":"Calle De Argan\u0303Osa",
    "iso:country":"ES",
    "sg:address":"Calle de Arga\u00d1osa, 72",
    "sg:city":"Oviedo",
    "sg:classifiers":[
        {
            "category":"Autos & Motor Vehicles",
            "subcategory":"Automobile Sales",
            "type":"Retail Goods"
        }
    ],
    "sg:phone":"+34 985 23 48 02",
    "sg:postcode":"33013",
    "sg:province":"Asturias",
    "wof:name":"Fernandez Rodriguez Maria Inocencia",
    "wof:placetype":"venue"
},
  "geometry": {"coordinates":[-5.865424633,43.3649101257],"type":"Point"}
}