{
  "type": "Feature",
  "properties": {
    "addr:full":"Calle de Olvido, 45 Madrid Madrid 28026",
    "addr:housenumber":"45",
    "addr:postcode":"madrid;28026",
    "addr:street":"Calle De Olvido",
    "iso:country":"ES",
    "sg:address":"Calle de Olvido, 45",
    "sg:city":"Madrid",
    "sg:orig_category":"Tapicer\u00cdas",
    "sg:phone":"+34 914 75 94 33",
    "sg:postcode":"28026",
    "sg:province":"Madrid",
    "wof:name":"Estrada Lozano Manuel",
    "wof:placetype":"venue"
},
  "geometry": {"coordinates":[-3.7023429871,40.3847999573],"type":"Point"}
}