{
  "type": "Feature",
  "properties": {
    "iso:country":"ES",
    "sg:address":"Calle de India, 6",
    "sg:city":"Sevilla",
    "sg:orig_category":"Inform\u00c1tica Equipo Y Programas (al Por Mayor)",
    "sg:phone":"+34 954 40 67 11",
    "sg:postcode":"41020",
    "sg:province":"Sevilla",
    "sg:website":"www.servds.com",
    "wof:name":"Servicios De Desarrollo Y Soporte S.l.",
    "wof:placetype":"venue"
},
  "geometry": {"coordinates":[-5.9164991379,37.4077301025],"type":"Point"}
}