{
  "type": "Feature",
  "properties": {
    "addr:full":"Calle de Tudela, 15 Alfaro La Rioja 26540",
    "addr:housenumber":"15",
    "addr:postcode":"26540",
    "addr:street":"Calle De Tudela;Rioja",
    "iso:country":"ES",
    "sg:address":"Calle de Tudela, 15",
    "sg:city":"Alfaro",
    "sg:orig_category":"\u00d3ptica: Instrumentos (fabricaci\u00d3n)",
    "sg:phone":"+34 941 18 29 66",
    "sg:postcode":"26540",
    "sg:province":"La Rioja",
    "wof:name":"Romanos Segura Carlos",
    "wof:placetype":"venue"
},
  "geometry": {"coordinates":[-1.7501510382,42.1749153137],"type":"Point"}
}