{
  "type": "Feature",
  "properties": {
    "iso:country":"ES",
    "sg:address":"Carrer de Benifallet (de), 18",
    "sg:city":"Tortosa",
    "sg:orig_category":"Mec\u00c1nico Del Autom\u00d3vil",
    "sg:phone":"+34 977 44 01 61",
    "sg:postcode":"43500",
    "sg:province":"Tarragona",
    "wof:name":"Tallers Escurriola S.c.p.",
    "wof:placetype":"venue"
},
  "geometry": {"coordinates":[0.5230910182,40.8171806335],"type":"Point"}
}