{
  "type": "Feature",
  "properties": {
    "addr:full":"Ctra Loeches (de), S/n Arganda Madrid 28500",
    "addr:postcode":"28500",
    "addr:street":"Ctra Loeches De S / N",
    "iso:country":"ES",
    "sg:address":"Ctra Loeches (de), S/n",
    "sg:city":"Arganda",
    "sg:orig_category":"Estudios, Instalaci\u00d3n De Climatizaci\u00d3n",
    "sg:phone":"+34 918 70 32 44",
    "sg:postcode":"28500",
    "sg:province":"Madrid",
    "wof:name":"Cerme\u00f1o Sanchez Jesus",
    "wof:placetype":"venue"
},
  "geometry": {"coordinates":[-3.4440340996,40.3036651611],"type":"Point"}
}