{
  "type": "Feature",
  "properties": {
    "addr:full":"Avda Alemania, 76 Huelva Huelva 21001",
    "addr:housenumber":"76",
    "addr:postcode":"21001",
    "addr:street":"Avda Alemania",
    "iso:country":"ES",
    "sg:address":"Avda Alemania, 76",
    "sg:city":"Huelva",
    "sg:orig_category":"Fabrica, Negocio De Vidrieras, Productos Vidriados Y Espejos",
    "sg:phone":"+34 959 24 49 24",
    "sg:postcode":"21001",
    "sg:province":"Huelva",
    "wof:name":"Suarez Vazquez Jose Antonio",
    "wof:placetype":"venue"
},
  "geometry": {"coordinates":[-6.9537358284,37.2607498169],"type":"Point"}
}