{
  "type": "Feature",
  "properties": {
    "iso:country":"ES",
    "sg:address":"Av Isidre Marti, 4",
    "sg:city":"Esplugues Llobregat",
    "sg:orig_category":"Bisuter\u00cda, Joyer\u00cda, Relojer\u00cda (al Por Menor)",
    "sg:phone":"+34 934 73 11 38",
    "sg:postcode":"08950",
    "sg:province":"Barcelona",
    "wof:name":"Campillo Antonio Mercedes",
    "wof:placetype":"venue"
},
  "geometry": {"coordinates":[2.0845119953,41.3736381531],"type":"Point"}
}