{
  "type": "Feature",
  "properties": {
    "iso:country":"ES",
    "sg:address":"Calle de Regalado, 2",
    "sg:city":"Valladolid",
    "sg:orig_category":"Agencias Y Asesores De Publicidad",
    "sg:phone":"+34 983 20 59 72",
    "sg:postcode":"47001",
    "sg:province":"Valladolid",
    "wof:name":"Estudio Y Dise\u00d1o Grafico Contraste S.l.",
    "wof:placetype":"venue"
},
  "geometry": {"coordinates":[-4.7263989449,41.6512145996],"type":"Point"}
}