{
  "type": "Feature",
  "properties": {
    "iso:country":"ES",
    "sg:address":"Avda Region Murciana, 144",
    "sg:city":"Carril De La Enera",
    "sg:orig_category":"Juguetes Y Juegos (al Por Mayor)",
    "sg:phone":"+34 968 87 58 81",
    "sg:postcode":"30011",
    "sg:province":"Murcia",
    "sg:website":"www.jupesa.com",
    "wof:name":"Euromerca Levante S.l.",
    "wof:placetype":"venue"
},
  "geometry": {"coordinates":[-1.0986809731,37.9820213318],"type":"Point"}
}