{
  "type": "Feature",
  "properties": {
    "addr:full":"Calle de Silvano, 77 Madrid Madrid 28043",
    "addr:housenumber":"77",
    "addr:postcode":"madrid;28043",
    "addr:street":"Calle De Silvano",
    "iso:country":"ES",
    "sg:address":"Calle de Silvano, 77",
    "sg:city":"Madrid",
    "sg:orig_category":"Fabricaci\u00d3n De Sobres, Bolsas Y Fundas",
    "sg:phone":"+34 917 59 26 30",
    "sg:postcode":"28043",
    "sg:province":"Madrid",
    "wof:name":"Picongar S.l.",
    "wof:placetype":"venue"
},
  "geometry": {"coordinates":[-3.6377539635,40.4627380371],"type":"Point"}
}