{
  "type": "Feature",
  "properties": {
    "addr:full":"Avda Guardia Civil, 6 Albacete Albacete 02005",
    "addr:housenumber":"6",
    "addr:postcode":"02005",
    "addr:street":"Avda Guardia Civil",
    "iso:country":"ES",
    "sg:address":"Avda Guardia Civil, 6",
    "sg:city":"Albacete",
    "sg:orig_category":"Materiales De Construcci\u00d3n (en General)",
    "sg:phone":"+34 967 21 68 11",
    "sg:postcode":"02005",
    "sg:province":"Albacete",
    "wof:name":"Ladrillos Y Yesos S.a.",
    "wof:placetype":"venue"
},
  "geometry": {"coordinates":[-1.8579969406,38.9985733032],"type":"Point"}
}