{
  "type": "Feature",
  "properties": {
    "iso:country":"ES",
    "sg:address":"Carrer de Verdi, S/n",
    "sg:city":"Mas Rampinyo",
    "sg:orig_category":"Chapister\u00cda",
    "sg:phone":"+34 935 72 50 70",
    "sg:postcode":"08110",
    "sg:province":"Barcelona",
    "wof:name":"Diaz Esposito Antonio",
    "wof:placetype":"venue"
},
  "geometry": {"coordinates":[2.1802449226,41.4956283569],"type":"Point"}
}