{
  "type": "Feature",
  "properties": {
    "iso:country":"ES",
    "sg:address":"Calle de Taray, 28",
    "sg:city":"Villarrobledo",
    "sg:orig_category":"Frutas Y Legumbres Frescas (al Por Mayor)",
    "sg:phone":"+34 967 14 36 77",
    "sg:postcode":"02600",
    "sg:province":"Albacete",
    "wof:name":"Soler Tornero Juan Jose",
    "wof:placetype":"venue"
},
  "geometry": {"coordinates":[-2.6077477932,39.269367218],"type":"Point"}
}