{
  "type": "Feature",
  "properties": {
    "iso:country":"ES",
    "sg:address":"Avda Mancomunidad Del Norte, 13",
    "sg:city":"Atalaya",
    "sg:classifiers":[
        {
            "category":"Communications",
            "type":"Services"
        }
    ],
    "sg:phone":"+34 928 88 07 58",
    "sg:postcode":"35450",
    "sg:province":"Las Palmas",
    "sg:tags":[
        "televisiones",
        "y",
        "radio"
    ],
    "wof:name":"Informaciones Del Norte Gran Canario S.l.",
    "wof:placetype":"venue"
},
  "geometry": {"coordinates":[-15.6319208145,28.1403903961],"type":"Point"}
}