{
  "type": "Feature",
  "properties": {
    "addr:full":"Calle de Doctor Limon, 6 Puertollano Ciudad Real 13500",
    "addr:housenumber":"6",
    "addr:postcode":"13500",
    "addr:street":"Calle De Doctor Limon",
    "iso:country":"ES",
    "sg:address":"Calle de Doctor Limon, 6",
    "sg:city":"Puertollano",
    "sg:classifiers":[
        {
            "category":"Autos & Motor Vehicles",
            "subcategory":"Automobile Sales",
            "type":"Retail Goods"
        }
    ],
    "sg:phone":"+34 926 42 50 73",
    "sg:postcode":"13500",
    "sg:province":"Ciudad Real",
    "wof:name":"Auto Escuela San Rafael S. L.",
    "wof:placetype":"venue"
},
  "geometry": {"coordinates":[-4.1118369102,38.6866989136],"type":"Point"}
}