{
  "type": "Feature",
  "properties": {
    "iso:country":"ES",
    "sg:address":"Calle de Herminio Puertas, 68",
    "sg:city":"Madrid",
    "sg:orig_category":"Fabricaci\u00d3n De Taburetes, Sillas Y Sillones",
    "sg:phone":"+34 914 64 98 33",
    "sg:postcode":"28011",
    "sg:province":"Madrid",
    "sg:website":"www.castormunoz.com",
    "wof:name":"Castor Mu\u00f1oz S. A.",
    "wof:placetype":"venue"
},
  "geometry": {"coordinates":[-3.7358620167,40.4073181152],"type":"Point"}
}