{
  "type": "Feature",
  "properties": {
    "addr:full":"Carrer de Sant Josep, 49 Lloret Mar Girona 17310",
    "addr:housenumber":"49",
    "addr:postcode":"17310",
    "addr:street":"Carrer De Sant Josep",
    "iso:country":"ES",
    "sg:address":"Carrer de Sant Josep, 49",
    "sg:city":"Lloret Mar",
    "sg:orig_category":"Agencias De Viajes",
    "sg:phone":"+34 972 37 10 36",
    "sg:postcode":"17310",
    "sg:province":"Girona",
    "wof:name":"Meli Viajes Sl",
    "wof:placetype":"venue"
},
  "geometry": {"coordinates":[2.8461410999,41.7021636963],"type":"Point"}
}