{
  "type": "Feature",
  "properties": {
    "addr:full":"Calle de Francisco Vitoria, 30 Zaragoza Zaragoza 50008",
    "addr:housenumber":"30",
    "addr:postcode":"50008",
    "addr:street":"Calle De Francisco Vitoria",
    "iso:country":"ES",
    "sg:address":"Calle de Francisco Vitoria, 30",
    "sg:city":"Zaragoza",
    "sg:classifiers":[
        {
            "category":"Cinema",
            "subcategory":"Movie Theater",
            "type":"Entertainment"
        }
    ],
    "sg:phone":"+34 976 23 20 18",
    "sg:postcode":"50008",
    "sg:province":"Zaragoza",
    "sg:tags":[
        "salas",
        "de",
        "cine"
    ],
    "wof:name":"Los Cines De Zaragoza S. A.",
    "wof:placetype":"venue"
},
  "geometry": {"coordinates":[-0.8789659739,41.6447525024],"type":"Point"}
}