{
  "type": "Feature",
  "properties": {
    "iso:country":"ES",
    "sg:address":"Calle de Puebla (la), 9",
    "sg:city":"Palencia",
    "sg:orig_category":"Asistencia Social",
    "sg:phone":"+34 979 71 38 88",
    "sg:postcode":"34002",
    "sg:province":"Palencia",
    "wof:name":"Asociacion De Familiares De Enfermos De Alzheimer",
    "wof:placetype":"venue"
},
  "geometry": {"coordinates":[-4.52850914,42.0081825256],"type":"Point"}
}