{
  "type": "Feature",
  "properties": {
    "iso:country":"ES",
    "sg:address":"Kaleberria, 40",
    "sg:city":"Andoain",
    "sg:orig_category":"Delegados, Agentes De Tr\u00c1nsito, Auxiliares De Transporte Internacional",
    "sg:phone":"+34 943 59 23 56",
    "sg:postcode":"20140",
    "sg:province":"Guip\u00f9zcoa",
    "wof:name":"Azpiroz Juanena Juan Jose",
    "wof:placetype":"venue"
},
  "geometry": {"coordinates":[-2.020939827,43.2146682739],"type":"Point"}
}