{
  "type": "Feature",
  "properties": {
    "iso:country":"ES",
    "sg:address":"Calle de Encomienda, 6",
    "sg:city":"Solana",
    "sg:orig_category":"Carnes De Carnicer\u00cda (al Por Mayor)",
    "sg:phone":"+34 926 63 12 01",
    "sg:postcode":"13240",
    "sg:province":"Ciudad Real",
    "wof:name":"Pedrin E Hijos S.l.",
    "wof:placetype":"venue"
},
  "geometry": {"coordinates":[-3.239839077,38.9398117065],"type":"Point"}
}