{
  "type": "Feature",
  "properties": {
    "addr:full":"Carr Ferran Agullo, 10 Girona Girona 17001",
    "addr:housenumber":"10",
    "addr:postcode":"17001",
    "addr:street":"Carr Ferran Agullo",
    "iso:country":"ES",
    "sg:address":"Carr Ferran Agullo, 10",
    "sg:city":"Girona",
    "sg:orig_category":"Ropa Para Se\u00d1oras Y Caballeros (al Por Menor)",
    "sg:phone":"+34 972 22 65 72",
    "sg:postcode":"17001",
    "sg:province":"Girona",
    "wof:name":"Confeccions Tot Treball S.c.",
    "wof:placetype":"venue"
},
  "geometry": {"coordinates":[2.8191928864,41.9805793762],"type":"Point"}
}