{
  "type": "Feature",
  "properties": {
    "addr:full":"Calle de Miguel Moya, 9 Malaga M\u00e1laga 29017",
    "addr:housenumber":"9",
    "addr:postcode":"29017",
    "addr:street":"Calle De Miguel Moya;Ma\u0301Laga",
    "iso:country":"ES",
    "sg:address":"Calle de Miguel Moya, 9",
    "sg:city":"Malaga",
    "sg:orig_category":"Electrodom\u00c9sticos (al Por Menor)",
    "sg:phone":"+34 952 29 68 48",
    "sg:postcode":"29017",
    "sg:province":"M\u00e1laga",
    "wof:name":"Coypasa S.a.",
    "wof:placetype":"venue"
},
  "geometry": {"coordinates":[-4.3597040176,36.7202949524],"type":"Point"}
}