{
  "type": "Feature",
  "properties": {
    "iso:country":"ES",
    "sg:address":"Afueras, S/n",
    "sg:city":"El Calonge",
    "sg:orig_category":"Agricultores, Agricultores",
    "sg:phone":"+34 957 64 47 85",
    "sg:postcode":"14709",
    "sg:province":"C\u00f3rdoba",
    "wof:name":"Sotogordo S.l.",
    "wof:placetype":"venue"
},
  "geometry": {"coordinates":[-5.2409939766,37.7732696533],"type":"Point"}
}