{
  "type": "Feature",
  "properties": {
    "iso:country":"ES",
    "sg:address":"Calle de Palmas (las), 5",
    "sg:city":"Javea",
    "sg:orig_category":"Int\u00c9rpretes",
    "sg:phone":"+34 965 79 40 81",
    "sg:postcode":"03730",
    "sg:province":"Alicante",
    "wof:name":"Toye  Ronald David",
    "wof:placetype":"venue"
},
  "geometry": {"coordinates":[0.156893,38.7806739807],"type":"Point"}
}