{
  "type": "Feature",
  "properties": {
    "addr:full":"Ermuaran-bide Kalea, 12 Elgoibar Guip\u00f9zcoa 20870",
    "addr:housenumber":"12",
    "addr:postcode":"20870",
    "addr:street":"Ermuaran-Bide Kalea;Guipu\u0300Zcoa",
    "iso:country":"ES",
    "sg:address":"Ermuaran-bide Kalea, 12",
    "sg:city":"Elgoibar",
    "sg:orig_category":"Empresas De Carpinter\u00cda De Madera",
    "sg:phone":"+34 943 74 31 16",
    "sg:postcode":"20870",
    "sg:province":"Guip\u00f9zcoa",
    "wof:name":"Carpinteria Biena, S.l.",
    "wof:placetype":"venue"
},
  "geometry": {"coordinates":[-2.4108810425,43.2144546509],"type":"Point"}
}