{
  "type": "Feature",
  "properties": {
    "iso:country":"ES",
    "sg:address":"Calle de Dinamarca, 2",
    "sg:city":"Valencina Concepcion",
    "sg:orig_category":"Agencias Y Agentes Comerciales, Representantes",
    "sg:phone":"+34 955 72 83 12",
    "sg:postcode":"41907",
    "sg:province":"Sevilla",
    "wof:name":"Oria Peralias Antonio",
    "wof:placetype":"venue"
},
  "geometry": {"coordinates":[-6.0762634277,37.4095420837],"type":"Point"}
}