{
  "type": "Feature",
  "properties": {
    "iso:country":"ES",
    "sg:address":"Carrer de Riera Alta, 25",
    "sg:city":"Barcelona",
    "sg:orig_category":"Servicios De Higiene Y Peluquer\u00cda Para Perros Y Gatos",
    "sg:phone":"+34 933 29 81 50",
    "sg:postcode":"08001",
    "sg:province":"Barcelona",
    "wof:name":"Clinica Veterinaria Riera Alta S.l.",
    "wof:placetype":"venue"
},
  "geometry": {"coordinates":[2.1660349369,41.3804397583],"type":"Point"}
}