{
  "type": "Feature",
  "properties": {
    "addr:full":"Plaz Espa\u00d1a, S/n Jabalquinto Ja\u00e9n 23712",
    "addr:housenumber":"s / n",
    "addr:postcode":"23712",
    "addr:street":"Plaz Espan\u0303A",
    "iso:country":"ES",
    "sg:address":"Plaz Espa\u00d1a, S/n",
    "sg:city":"Jabalquinto",
    "sg:orig_category":"Cajas Para Embalar",
    "sg:phone":"+34 953 61 71 31",
    "sg:postcode":"23712",
    "sg:province":"Ja\u00e9n",
    "wof:name":"Caja Rural De Jaen",
    "wof:placetype":"venue"
},
  "geometry": {"coordinates":[-3.7230479717,38.0186347961],"type":"Point"}
}