{
  "type": "Feature",
  "properties": {
    "addr:full":"Calle de Negritas, 26 Valdemoro Madrid 28340",
    "addr:housenumber":"26",
    "addr:postcode":"28340",
    "addr:street":"Calle De Negritas",
    "iso:country":"ES",
    "sg:address":"Calle de Negritas, 26",
    "sg:city":"Valdemoro",
    "sg:orig_category":"Peluquer\u00cdas, Peluquer\u00cda Mixta",
    "sg:phone":"+34 918 09 52 25",
    "sg:postcode":"28340",
    "sg:province":"Madrid",
    "wof:name":"Quality Phone S.l.",
    "wof:placetype":"venue"
},
  "geometry": {"coordinates":[-3.6826899052,40.1917266846],"type":"Point"}
}