{
  "type": "Feature",
  "properties": {
    "addr:full":"Carrer de Espronceda, 310 Barcelona Barcelona 08027",
    "addr:housenumber":"310",
    "addr:postcode":"08027",
    "addr:street":"Carrer De Espronceda",
    "iso:country":"ES",
    "sg:address":"Carrer de Espronceda, 310",
    "sg:city":"Barcelona",
    "sg:orig_category":"Supermercados Y Hipermercados",
    "sg:phone":"+34 934 08 25 84",
    "sg:postcode":"08027",
    "sg:province":"Barcelona",
    "wof:name":"Supermercados Somar S.a.",
    "wof:placetype":"venue"
},
  "geometry": {"coordinates":[2.1901340485,41.4164886475],"type":"Point"}
}