{
  "type": "Feature",
  "properties": {
    "iso:country":"ES",
    "sg:address":"Avgd Espioca, 114",
    "sg:city":"Silla",
    "sg:orig_category":"Muebles",
    "sg:phone":"+34 961 20 24 81",
    "sg:postcode":"46460",
    "sg:province":"Valencia",
    "wof:name":"Esqueletajes Pardo S.l.",
    "wof:placetype":"venue"
},
  "geometry": {"coordinates":[-0.417858988,39.3685531616],"type":"Point"}
}