{
  "type": "Feature",
  "properties": {
    "addr:full":"G.v. Corts Catalanes, 1146 Barcelona Barcelona 08020",
    "addr:postcode":"1146;08020",
    "addr:street":"Catalanes",
    "iso:country":"ES",
    "sg:address":"G.v. Corts Catalanes, 1146",
    "sg:city":"Barcelona",
    "sg:orig_category":"Zapatos (al Por Menor)",
    "sg:phone":"+34 933 14 44 95",
    "sg:postcode":"08020",
    "sg:province":"Barcelona",
    "wof:name":"Campos Santalices Auria",
    "wof:placetype":"venue"
},
  "geometry": {"coordinates":[2.2068190575,41.4176521301],"type":"Point"}
}