{
  "type": "Feature",
  "properties": {
    "iso:country":"ES",
    "sg:address":"Aitzkorri Kalea, 22",
    "sg:city":"Legazpi",
    "sg:orig_category":"Costureras",
    "sg:phone":"+34 943 73 00 60",
    "sg:postcode":"20230",
    "sg:province":"Guip\u00f9zcoa",
    "wof:name":"Aztiria Agirre, Isabel (modista)",
    "wof:placetype":"venue"
},
  "geometry": {"coordinates":[-2.3356409073,43.0483551025],"type":"Point"}
}