{
  "type": "Feature",
  "properties": {
    "addr:full":"Ctra Barcelona, 465 Sabadell Barcelona 08204",
    "addr:housenumber":"465",
    "addr:postcode":"08204",
    "addr:street":"Ctra Barcelona",
    "iso:country":"ES",
    "sg:address":"Ctra Barcelona, 465",
    "sg:city":"Sabadell",
    "sg:orig_category":"Molduras, Junquillos, Listones Y Molduras Perforadas",
    "sg:phone":"+34 937 11 13 01",
    "sg:postcode":"08204",
    "sg:province":"Barcelona",
    "wof:name":"Altarriba Sanmarti Rita",
    "wof:placetype":"venue"
},
  "geometry": {"coordinates":[2.1128153801,41.5334396362],"type":"Point"}
}