{
  "type": "Feature",
  "properties": {
    "addr:full":"Calle de Sagasta, 40 Moron Frontera Sevilla 41530",
    "addr:housenumber":"40",
    "addr:postcode":"41530",
    "addr:street":"Calle De Sagasta",
    "iso:country":"ES",
    "sg:address":"Calle de Sagasta, 40",
    "sg:city":"Moron Frontera",
    "sg:orig_category":"Electricidad: Instaladores",
    "sg:phone":"+34 955 85 31 28",
    "sg:postcode":"41530",
    "sg:province":"Sevilla",
    "wof:name":"Electrificaciones Sancho S.l.",
    "wof:placetype":"venue"
},
  "geometry": {"coordinates":[-5.4556250572,37.1199531555],"type":"Point"}
}