{
  "type": "Feature",
  "properties": {
    "iso:country":"ES",
    "sg:address":"Zos, S/n",
    "sg:city":"Abavides",
    "sg:orig_category":"Piedra Natural",
    "sg:phone":"+34 988 40 90 36",
    "sg:postcode":"32694",
    "sg:province":"Ourense",
    "wof:name":"Construcciones Milucho S.l.",
    "wof:placetype":"venue"
},
  "geometry": {"coordinates":[-7.651693821,42.0421791077],"type":"Point"}
}