{
  "type": "Feature",
  "properties": {
    "iso:country":"ES",
    "sg:address":"Bo\u00f1ar, 1",
    "sg:city":"Puente Villarente",
    "sg:orig_category":"Distribuci\u00d3n De Petr\u00d3leo Y Derivados",
    "sg:phone":"+34 987 31 25 17",
    "sg:postcode":"24226",
    "sg:province":"Le\u00f3n",
    "sg:website":"www.paginasamarillas.es",
    "wof:name":"Petroesla S.l.",
    "wof:placetype":"venue"
},
  "geometry": {"coordinates":[-5.4851689339,42.5182266235],"type":"Point"}
}