{
  "type": "Feature",
  "properties": {
    "addr:full":"Calle de Juan Morales Navarro, 5 Santa Brigida Las Palmas 35300",
    "addr:housenumber":"5",
    "addr:postcode":"35300",
    "addr:street":"Calle De Juan;Navarro",
    "iso:country":"ES",
    "sg:address":"Calle de Juan Morales Navarro, 5",
    "sg:city":"Santa Brigida",
    "sg:orig_category":"Reposter\u00cdas",
    "sg:phone":"+34 928 64 44 57",
    "sg:postcode":"35300",
    "sg:province":"Las Palmas",
    "wof:name":"Panaderia Pulido S.l.",
    "wof:placetype":"venue"
},
  "geometry": {"coordinates":[-15.4989643097,28.0343437195],"type":"Point"}
}