{
  "type": "Feature",
  "properties": {
    "addr:full":"Calle de Mecanica, 2 Almendralejo Badajoz 06200",
    "addr:housenumber":"2",
    "addr:postcode":"06200",
    "addr:street":"Calle De Mecanica",
    "iso:country":"ES",
    "sg:address":"Calle de Mecanica, 2",
    "sg:city":"Almendralejo",
    "sg:orig_category":"Maquinaria Para Industrias Diversas",
    "sg:phone":"+34 924 67 12 57",
    "sg:postcode":"06200",
    "sg:province":"Badajoz",
    "sg:website":"www.nimogosa.com",
    "wof:name":"Nimo Gordillo S.a.",
    "wof:placetype":"venue"
},
  "geometry": {"coordinates":[-6.4092469215,38.6904373169],"type":"Point"}
}