{
  "type": "Feature",
  "properties": {
    "addr:full":"Calle de Iglesia, 10 Almedinilla C\u00f3rdoba 14812",
    "addr:housenumber":"10",
    "addr:postcode":"14812",
    "addr:street":"Calle De Iglesia",
    "iso:country":"ES",
    "sg:address":"Calle de Iglesia, 10",
    "sg:city":"Almedinilla",
    "sg:orig_category":"Iglesia Cat\u00d3lica",
    "sg:phone":"+34 957 70 31 12",
    "sg:postcode":"14812",
    "sg:province":"C\u00f3rdoba",
    "wof:name":"Parroquia De San Juan Bautista",
    "wof:placetype":"venue"
},
  "geometry": {"coordinates":[-4.0902118683,37.4395484924],"type":"Point"}
}