{
  "type": "Feature",
  "properties": {
    "addr:full":"Avda Goya, 96 Zaragoza Zaragoza 50004",
    "addr:housenumber":"96",
    "addr:postcode":"50004",
    "addr:street":"Avda Goya",
    "iso:country":"ES",
    "sg:address":"Avda Goya, 96",
    "sg:city":"Zaragoza",
    "sg:orig_category":"Molduras, Junquillos, Listones Y Molduras Perforadas",
    "sg:phone":"+34 976 23 35 03",
    "sg:postcode":"50004",
    "sg:province":"Zaragoza",
    "wof:name":"Wang  Xiaoping",
    "wof:placetype":"venue"
},
  "geometry": {"coordinates":[-0.8936504126,41.6476821899],"type":"Point"}
}