{
  "type": "Feature",
  "properties": {
    "addr:full":"Calle de Alfonso Xii, 7 Toledo Toledo 45002",
    "addr:housenumber":"7",
    "addr:postcode":"45002",
    "addr:street":"Calle De Alfonso Xii",
    "iso:country":"ES",
    "sg:address":"Calle de Alfonso Xii, 7",
    "sg:city":"Toledo",
    "sg:orig_category":"Doctores En Medicina",
    "sg:phone":"+34 925 21 15 40",
    "sg:postcode":"45002",
    "sg:province":"Toledo",
    "wof:name":"Gomez Alemany Alfonso",
    "wof:placetype":"venue"
},
  "geometry": {"coordinates":[-4.0263357162,39.8574523926],"type":"Point"}
}