{
  "type": "Feature",
  "properties": {
    "iso:country":"ES",
    "sg:address":"Calle de Poeta Alberola, 7",
    "sg:city":"Valencia",
    "sg:orig_category":"Arquitectos",
    "sg:phone":"+34 963 85 99 53",
    "sg:postcode":"46018",
    "sg:province":"Valencia",
    "wof:name":"Miranda Mallea Daniel",
    "wof:placetype":"venue"
},
  "geometry": {"coordinates":[-0.3934800029,39.4691772461],"type":"Point"}
}