{
  "type": "Feature",
  "properties": {
    "iso:country":"ES",
    "sg:address":"A (p I Polirrosa), 30",
    "sg:city":"Huelva",
    "sg:orig_category":"Muebles, Minoristas",
    "sg:phone":"+34 959 22 13 45",
    "sg:postcode":"21007",
    "sg:province":"Huelva",
    "wof:name":"Pilas Factory S.l.",
    "wof:placetype":"venue"
},
  "geometry": {"coordinates":[-6.9111089706,37.2726516724],"type":"Point"}
}