{
  "type": "Feature",
  "properties": {
    "iso:country":"ES",
    "sg:address":"Carrer de Diagonal Fivaller, 19",
    "sg:city":"Cardedeu",
    "sg:orig_category":"Relojer\u00cda (al Por Menor, Reparaci\u00d3n)",
    "sg:phone":"+34 938 46 19 67",
    "sg:postcode":"08440",
    "sg:province":"Barcelona",
    "wof:name":"Rifort S.c.p",
    "wof:placetype":"venue"
},
  "geometry": {"coordinates":[2.3568520546,41.6373252869],"type":"Point"}
}