{
  "type": "Feature",
  "properties": {
    "iso:country":"ES",
    "sg:address":"Calle de Marques De Estella, 21",
    "sg:city":"Lujar",
    "sg:orig_category":"Delegados, Agentes De Tr\u00c1nsito, Auxiliares De Transporte Internacional",
    "sg:phone":"+34 958 83 60 69",
    "sg:postcode":"18614",
    "sg:province":"Granada",
    "wof:name":"Rodriguez Melero Emilio Felix Ricardo",
    "wof:placetype":"venue"
},
  "geometry": {"coordinates":[-3.3878679276,36.7425498962],"type":"Point"}
}