{
  "type": "Feature",
  "properties": {
    "addr:full":"Carrer de Boix, 8 Cornella Llobregat Barcelona 08940",
    "addr:housenumber":"8",
    "addr:postcode":"08940",
    "addr:street":"Carrer De Boix",
    "iso:country":"ES",
    "sg:address":"Carrer de Boix, 8",
    "sg:city":"Cornella Llobregat",
    "sg:orig_category":"Centros De Coordinaci\u00d3n",
    "sg:phone":"+34 933 75 40 55",
    "sg:postcode":"08940",
    "sg:province":"Barcelona",
    "wof:name":"Gomez Perez Manuel",
    "wof:placetype":"venue"
},
  "geometry": {"coordinates":[2.0813360214,41.3628387451],"type":"Point"}
}