{
  "type": "Feature",
  "properties": {
    "addr:full":"Mitarte Kalea, 17 Aretxabaleta Guip\u00f9zcoa 20550",
    "addr:housenumber":"17",
    "addr:postcode":"20550",
    "addr:street":"Mitarte Kalea;Guipu\u0300Zcoa",
    "iso:country":"ES",
    "sg:address":"Mitarte Kalea, 17",
    "sg:city":"Aretxabaleta",
    "sg:orig_category":"Peluquer\u00cdas, Peluquer\u00cda Mixta",
    "sg:phone":"+34 943 53 32 44",
    "sg:postcode":"20550",
    "sg:province":"Guip\u00f9zcoa",
    "wof:name":"Cristina Fajardo Luis",
    "wof:placetype":"venue"
},
  "geometry": {"coordinates":[-2.5033740997,43.0338172913],"type":"Point"}
}