{
  "type": "Feature",
  "properties": {
    "iso:country":"ES",
    "sg:address":"Pase Delicias, 85",
    "sg:city":"Madrid",
    "sg:orig_category":"Ropa Para Se\u00d1oras (al Por Menor)",
    "sg:phone":"+34 915 28 43 59",
    "sg:postcode":"28045",
    "sg:province":"Madrid",
    "wof:name":"Desarrollos Loica S.l",
    "wof:placetype":"venue"
},
  "geometry": {"coordinates":[-3.694341898,40.3963012695],"type":"Point"}
}