{
  "type": "Feature",
  "properties": {
    "addr:full":"Calle de Delco, S/n Leganes Madrid 28914",
    "addr:housenumber":"s / n",
    "addr:postcode":"28914",
    "addr:street":"Calle De Delco",
    "iso:country":"ES",
    "sg:address":"Calle de Delco, S/n",
    "sg:city":"Leganes",
    "sg:orig_category":"Promotores Constructores",
    "sg:phone":"+34 914 98 71 90",
    "sg:postcode":"28914",
    "sg:province":"Madrid",
    "wof:name":"Dragados S A",
    "wof:placetype":"venue"
},
  "geometry": {"coordinates":[-3.7600076199,40.3192634583],"type":"Point"}
}