{
  "type": "Feature",
  "properties": {
    "addr:full":"Calle de Isidro Segovia, 13 Salamanca Salamanca 37007",
    "addr:housenumber":"13",
    "addr:postcode":"37007",
    "addr:street":"Calle De Isidro Segovia",
    "iso:country":"ES",
    "sg:address":"Calle de Isidro Segovia, 13",
    "sg:city":"Salamanca",
    "sg:orig_category":"Electrodom\u00c9sticos (al Por Menor)",
    "sg:phone":"+34 923 12 13 15",
    "sg:postcode":"37007",
    "sg:province":"Salamanca",
    "wof:name":"Miguel Blanco Rosa Maria",
    "wof:placetype":"venue"
},
  "geometry": {"coordinates":[-5.6657128334,40.97057724],"type":"Point"}
}