{
  "type": "Feature",
  "properties": {
    "iso:country":"ES",
    "sg:address":"Avda Democracia, 7",
    "sg:city":"Madrid",
    "sg:orig_category":"Radiocomunicaciones, Telefon\u00cda M\u00d3vil, Radiomensajer\u00cda: Servicios, Comercializaci\u00d3n",
    "sg:phone":"+34 913 32 40 04",
    "sg:postcode":"28031",
    "sg:province":"Madrid",
    "sg:website":"www.wwt.es",
    "wof:name":"World Wide Telephone S.l.",
    "wof:placetype":"venue"
},
  "geometry": {"coordinates":[-3.623904705,40.3859443665],"type":"Point"}
}