{
  "type": "Feature",
  "properties": {
    "iso:country":"ES",
    "sg:address":"Plaz Cine (del), 3",
    "sg:city":"Villanueva Mesia",
    "sg:orig_category":"Administraciones Regionales, Departamentales Y Locales",
    "sg:phone":"+34 958 44 40 05",
    "sg:postcode":"18369",
    "sg:province":"Granada",
    "wof:name":"Ayuntamiento De Villanueva De Mesias",
    "wof:placetype":"venue"
},
  "geometry": {"coordinates":[-4.0031518936,37.2244148254],"type":"Point"}
}