{
  "type": "Feature",
  "properties": {
    "addr:full":"Calle de Buenavista, 3 Portugalete Vizcaya 48920",
    "addr:housenumber":"3",
    "addr:postcode":"48920",
    "addr:street":"Calle De Buenavista",
    "iso:country":"ES",
    "sg:address":"Calle de Buenavista, 3",
    "sg:city":"Portugalete",
    "sg:orig_category":"Empresas De Carpinter\u00cda Met\u00c1lica",
    "sg:phone":"+34 944 83 51 56",
    "sg:postcode":"48920",
    "sg:province":"Vizcaya",
    "wof:name":"Irumetal S.coop.ltda.",
    "wof:placetype":"venue"
},
  "geometry": {"coordinates":[-3.029512167,43.3239898682],"type":"Point"}
}