{
  "type": "Feature",
  "properties": {
    "iso:country":"ES",
    "sg:address":"Trva Mendieta, 2",
    "sg:city":"Moreaga",
    "sg:orig_category":"Plomeros",
    "sg:phone":"+34 946 76 04 66",
    "sg:postcode":"48600",
    "sg:province":"Vizcaya",
    "wof:name":"Oviedo Ibarra Pedro",
    "wof:placetype":"venue"
},
  "geometry": {"coordinates":[-2.978579998,43.3822555542],"type":"Point"}
}