{
  "type": "Feature",
  "properties": {
    "addr:full":"Carr Estacio, 7 Sineu Islas Baleares 07510",
    "addr:housenumber":"7",
    "addr:postcode":"07510",
    "addr:street":"Carr Estacio",
    "iso:country":"ES",
    "sg:address":"Carr Estacio, 7",
    "sg:city":"Sineu",
    "sg:orig_category":"Serrer\u00cdas De Madera",
    "sg:phone":"+34 971 52 01 05",
    "sg:postcode":"07510",
    "sg:province":"Islas Baleares",
    "wof:name":"Ferriol Serra Catalina",
    "wof:placetype":"venue"
},
  "geometry": {"coordinates":[3.0138909817,39.6443405151],"type":"Point"}
}