{
  "type": "Feature",
  "properties": {
    "addr:full":"Calle de Lagasca, 38 Madrid Madrid 28001",
    "addr:housenumber":"38",
    "addr:postcode":"madrid;28001",
    "addr:street":"Calle De Lagasca",
    "iso:country":"ES",
    "sg:address":"Calle de Lagasca, 38",
    "sg:city":"Madrid",
    "sg:orig_category":"Empresas De Carpinter\u00cda De Madera",
    "sg:phone":"+34 915 75 26 26",
    "sg:postcode":"28001",
    "sg:province":"Madrid",
    "wof:name":"Dombriz Garcia Domingo",
    "wof:placetype":"venue"
},
  "geometry": {"coordinates":[-3.6852929592,40.4245491028],"type":"Point"}
}