{
  "type": "Feature",
  "properties": {
    "iso:country":"ES",
    "sg:address":"Ctra General Del Sur C-822, 12",
    "sg:city":"Tijoco Alto",
    "sg:orig_category":"Refiner\u00cdas De Petr\u00d3leo",
    "sg:phone":"+34 922 71 35 37",
    "sg:postcode":"38670",
    "sg:province":"Santa Cruz De Tenerife",
    "wof:name":"Prodalca Espa\u00f1a S.a.",
    "wof:placetype":"venue"
},
  "geometry": {"coordinates":[-16.724899292,28.1215400696],"type":"Point"}
}