{
  "type": "Feature",
  "properties": {
    "addr:full":"Ctra Alacant-alcoi, Km. 0105,0 Jijona Alicante 03100",
    "addr:postcode":"03100",
    "addr:street":"Ctra Alacant-Alcoi Km. 0105,0",
    "iso:country":"ES",
    "sg:address":"Ctra Alacant-alcoi, Km. 0105,0",
    "sg:city":"Jijona",
    "sg:orig_category":"Distribuci\u00d3n De Petr\u00d3leo Y Derivados",
    "sg:phone":"+34 965 61 32 18",
    "sg:postcode":"03100",
    "sg:province":"Alicante",
    "wof:name":"Estacion De Servicio Xixona S.l.",
    "wof:placetype":"venue"
},
  "geometry": {"coordinates":[-0.4973269999,38.5448608398],"type":"Point"}
}