{
  "type": "Feature",
  "properties": {
    "addr:full":"Carrer de Bisbe Cabanelles, 30 Palma Islas Baleares 07005",
    "addr:housenumber":"30",
    "addr:postcode":"07005",
    "addr:street":"Carrer De Bisbe Cabanelles",
    "iso:country":"ES",
    "sg:address":"Carrer de Bisbe Cabanelles, 30",
    "sg:city":"Palma",
    "sg:orig_category":"Retoques De Vestidos",
    "sg:phone":"+34 971 27 84 53",
    "sg:postcode":"07005",
    "sg:province":"Islas Baleares",
    "wof:name":"Repiso Gordiola Maria Antonia",
    "wof:placetype":"venue"
},
  "geometry": {"coordinates":[2.665667057,39.5762023926],"type":"Point"}
}