{
  "type": "Feature",
  "properties": {
    "iso:country":"ES",
    "sg:address":"Carrer de Luxemburg, 26",
    "sg:city":"Rubi",
    "sg:orig_category":"Aceros Especiales",
    "sg:phone":"+34 935 88 06 08",
    "sg:postcode":"08191",
    "sg:province":"Barcelona",
    "wof:name":"Aceros Llobregat S.a.",
    "wof:placetype":"venue"
},
  "geometry": {"coordinates":[2.0274829865,41.480266571],"type":"Point"}
}