{
  "type": "Feature",
  "properties": {
    "addr:full":"Calle de Gijon, 9 Piedras Blancas Asturias 33450",
    "addr:housenumber":"9",
    "addr:postcode":"33450",
    "addr:street":"Calle De Gijon",
    "iso:country":"ES",
    "sg:address":"Calle de Gijon, 9",
    "sg:city":"Piedras Blancas",
    "sg:orig_category":"Agencias Y Agentes Comerciales, Representantes",
    "sg:phone":"+34 985 53 11 56",
    "sg:postcode":"33450",
    "sg:province":"Asturias",
    "wof:name":"Manteca Fraile Jesus Fernando",
    "wof:placetype":"venue"
},
  "geometry": {"coordinates":[-5.9795007706,43.5595283508],"type":"Point"}
}