{
  "type": "Feature",
  "properties": {
    "addr:full":"Calle de General Casta\u00d1os, 51 C Portugalete Vizcaya 48920",
    "addr:housenumber":"51 c",
    "addr:postcode":"48920",
    "addr:street":"Calle De General Castan\u0303Os",
    "iso:country":"ES",
    "sg:address":"Calle de General Casta\u00d1os, 51 C",
    "sg:city":"Portugalete",
    "sg:orig_category":"Inform\u00c1tica (estudios, Servicios, Asesor\u00cda, Formaci\u00d3n)",
    "sg:phone":"+34 944 83 65 65",
    "sg:postcode":"48920",
    "sg:province":"Vizcaya",
    "sg:website":"www.asedoc.com",
    "wof:name":"Asedoc, C.b.",
    "wof:placetype":"venue"
},
  "geometry": {"coordinates":[-3.0222952366,43.3214569092],"type":"Point"}
}