{
  "type": "Feature",
  "properties": {
    "addr:full":"Calle de Josue Lillo, 10 Madrid Madrid 28053",
    "addr:housenumber":"10",
    "addr:postcode":"madrid;28053",
    "addr:street":"Calle De Josue Lillo",
    "iso:country":"ES",
    "sg:address":"Calle de Josue Lillo, 10",
    "sg:city":"Madrid",
    "sg:orig_category":"Empresas De Carpinter\u00cda",
    "sg:phone":"+34 913 81 94 30",
    "sg:postcode":"28053",
    "sg:province":"Madrid",
    "wof:name":"Trinidad Otero Ricardo",
    "wof:placetype":"venue"
},
  "geometry": {"coordinates":[-3.6688699722,40.3858184814],"type":"Point"}
}