{
  "type": "Feature",
  "properties": {
    "iso:country":"ES",
    "sg:address":"Pg Bonanova, 10",
    "sg:city":"Barcelona",
    "sg:orig_category":"Bisuter\u00cda, Joyer\u00cda, Relojer\u00cda (al Por Menor)",
    "sg:phone":"+34 934 17 63 10",
    "sg:postcode":"08022",
    "sg:province":"Barcelona",
    "wof:name":"H J Hofert S.a.",
    "wof:placetype":"venue"
},
  "geometry": {"coordinates":[2.1321649551,41.406085968],"type":"Point"}
}