{
  "type": "Feature",
  "properties": {
    "iso:country":"ES",
    "sg:address":"C/ Joaquin Martinez Macia, 60",
    "sg:city":"Elche",
    "sg:orig_category":"Empresas De Pintura Y Revestimientos",
    "sg:phone":"+34 965 43 55 70",
    "sg:postcode":"03205",
    "sg:province":"Alicante",
    "wof:name":"Azulalia De Decoraciones S.l.",
    "wof:placetype":"venue"
},
  "geometry": {"coordinates":[-0.7169089913,38.2674217224],"type":"Point"}
}