{
  "type": "Feature",
  "properties": {
    "addr:full":"Avda Celanova (de), 80 Valenza Ourense 32002",
    "addr:housenumber":"80",
    "addr:postcode":"32002",
    "addr:street":"Avda Celanova De",
    "iso:country":"ES",
    "sg:address":"Avda Celanova (de), 80",
    "sg:city":"Valenza",
    "sg:orig_category":"Transportes Por Carretera: Lotes Completos, Mercanc\u00cdas Diversas",
    "sg:phone":"+34 988 25 36 28",
    "sg:postcode":"32002",
    "sg:province":"Ourense",
    "wof:name":"Orensana De Firmes S.coop.",
    "wof:placetype":"venue"
},
  "geometry": {"coordinates":[-7.8812589645,42.3198204041],"type":"Point"}
}