{
  "type": "Feature",
  "properties": {
    "iso:country":"ES",
    "sg:address":"Calle de Real De Motril, 47",
    "sg:city":"Armilla",
    "sg:orig_category":"Arquitectos",
    "sg:phone":"+34 958 57 30 28",
    "sg:postcode":"18100",
    "sg:province":"Granada",
    "wof:name":"Escena Urbana S.l.",
    "wof:placetype":"venue"
},
  "geometry": {"coordinates":[-3.6264059544,37.142288208],"type":"Point"}
}