{
  "type": "Feature",
  "properties": {
    "addr:full":"Calle de Covadonga, 20 Langreo Asturias 33900",
    "addr:housenumber":"20",
    "addr:postcode":"33900",
    "addr:street":"Calle De Covadonga",
    "iso:country":"ES",
    "sg:address":"Calle de Covadonga, 20",
    "sg:city":"Langreo",
    "sg:orig_category":"Molduras, Junquillos, Listones Y Molduras Perforadas",
    "sg:phone":"+34 985 68 24 00",
    "sg:postcode":"33900",
    "sg:province":"Asturias",
    "wof:name":"Telefonos Publicos Y Privados S.l.",
    "wof:placetype":"venue"
},
  "geometry": {"coordinates":[-5.6860141754,43.2982902527],"type":"Point"}
}