{
  "type": "Feature",
  "properties": {
    "addr:full":"Rua Sarmiento, 51 Pontevedra Pontevedra 36002",
    "addr:housenumber":"51",
    "addr:postcode":"36002",
    "addr:street":"Rua Sarmiento",
    "iso:country":"ES",
    "sg:address":"Rua Sarmiento, 51",
    "sg:city":"Pontevedra",
    "sg:orig_category":"Iglesia Cat\u00d3lica",
    "sg:phone":"+34 986 85 13 75",
    "sg:postcode":"36002",
    "sg:province":"Pontevedra",
    "wof:name":"Arzobispado De Santiago",
    "wof:placetype":"venue"
},
  "geometry": {"coordinates":[-8.6433124542,42.4329223633],"type":"Point"}
}