{
  "type": "Feature",
  "properties": {
    "addr:full":"Pase Basilios (de Los), 2 Granada Granada 18008",
    "addr:postcode":"18008",
    "iso:country":"ES",
    "sg:address":"Pase Basilios (de Los), 2",
    "sg:city":"Granada",
    "sg:orig_category":"Ense\u00d1anza Variada",
    "sg:phone":"+34 958 81 20 47",
    "sg:postcode":"18008",
    "sg:province":"Granada",
    "wof:name":"Centro De Estudios Academicos S. A.",
    "wof:placetype":"venue"
},
  "geometry": {"coordinates":[-3.5951368809,37.1682395935],"type":"Point"}
}