{
  "type": "Feature",
  "properties": {
    "iso:country":"ES",
    "sg:address":"Avda Isabel De Moctezuma, 35",
    "sg:city":"Caceres",
    "sg:orig_category":"Tapicer\u00cdas",
    "sg:phone":"+34 927 21 62 62",
    "sg:postcode":"10005",
    "sg:province":"C\u00e1ceres",
    "wof:name":"Rodriguez Miguel Jose",
    "wof:placetype":"venue"
},
  "geometry": {"coordinates":[-6.3784489632,39.4636306763],"type":"Point"}
}