{
  "type": "Feature",
  "properties": {
    "addr:full":"Carrer de Violant D'hongria, 30 Sant Pere I Sant Pau Tarragona 43007",
    "addr:housenumber":"30",
    "addr:postcode":"43007",
    "addr:street":"Carrer De Violant D'Hongria",
    "iso:country":"ES",
    "sg:address":"Carrer de Violant D'hongria, 30",
    "sg:city":"Sant Pere I Sant Pau",
    "sg:orig_category":"Laboratorios Y Trabajos De Fotograf\u00cda, V\u00cddeo Y Cine",
    "sg:phone":"+34 977 20 32 82",
    "sg:postcode":"43007",
    "sg:province":"Tarragona",
    "wof:name":"Olmo Menacho Manuel",
    "wof:placetype":"venue"
},
  "geometry": {"coordinates":[1.2591320276,41.1399307251],"type":"Point"}
}