{
  "type": "Feature",
  "properties": {
    "iso:country":"ES",
    "sg:address":"Calle de Isabel La Catolica, 8",
    "sg:city":"Priego Cordoba",
    "sg:orig_category":"Armas Y Municiones (fabricaci\u00d3n, Al Por Mayor)",
    "sg:phone":"+34 957 70 18 11",
    "sg:postcode":"14800",
    "sg:province":"C\u00f3rdoba",
    "wof:name":"Lopez Bermudez Jose Antonio",
    "wof:placetype":"venue"
},
  "geometry": {"coordinates":[-4.1929821968,37.4385566711],"type":"Point"}
}