{
  "type": "Feature",
  "properties": {
    "iso:country":"ES",
    "sg:address":"Calle de San Andres, 10",
    "sg:city":"Laguardia",
    "sg:orig_category":"Caf\u00c9s, Bares, Cervecer\u00cdas",
    "sg:phone":"+34 945 62 12 47",
    "sg:postcode":"01300",
    "sg:province":"\u00c1lava",
    "wof:name":"Rodriguez Juandeaburre Julio",
    "wof:placetype":"venue"
},
  "geometry": {"coordinates":[-2.5844590664,42.5535507202],"type":"Point"}
}