{
  "type": "Feature",
  "properties": {
    "addr:full":"Carrer de L'escorial, 174 Barcelona Barcelona 08024",
    "addr:housenumber":"174",
    "addr:postcode":"08024",
    "addr:street":"Carrer De L'Escorial",
    "iso:country":"ES",
    "sg:address":"Carrer de L'escorial, 174",
    "sg:city":"Barcelona",
    "sg:orig_category":"Agencias Y Agentes Comerciales, Representantes",
    "sg:phone":"+34 932 19 50 27",
    "sg:postcode":"08024",
    "sg:province":"Barcelona",
    "wof:name":"Blasco Plaza Jose",
    "wof:placetype":"venue"
},
  "geometry": {"coordinates":[2.1581468582,41.4106674194],"type":"Point"}
}