{
  "type": "Feature",
  "properties": {
    "addr:full":"Calle de San Jose, 21 Enguera Valencia 46810",
    "addr:housenumber":"21",
    "addr:postcode":"46810",
    "addr:street":"Calle De San",
    "iso:country":"ES",
    "sg:address":"Calle de San Jose, 21",
    "sg:city":"Enguera",
    "sg:orig_category":"Empresas De Desmonte",
    "sg:phone":"+34 962 22 51 31",
    "sg:postcode":"46810",
    "sg:province":"Valencia",
    "wof:name":"Transformaciones Gomespa S.l.",
    "wof:placetype":"venue"
},
  "geometry": {"coordinates":[-0.6866559982,38.9808502197],"type":"Point"}
}