{
  "type": "Feature",
  "properties": {
    "addr:full":"Avda Fuente San Francisco, 2 Ubrique C\u00e1diz 11600",
    "addr:housenumber":"2",
    "addr:postcode":"11600",
    "addr:street":"Avda Fuente San Francisco;Ca\u0301Diz",
    "iso:country":"ES",
    "sg:address":"Avda Fuente San Francisco, 2",
    "sg:city":"Ubrique",
    "sg:orig_category":"Marroquiner\u00cda (confecci\u00d3n)",
    "sg:phone":"+34 956 46 35 02",
    "sg:postcode":"11600",
    "sg:province":"C\u00e1diz",
    "wof:name":"Creaciones Torrefer S.l.",
    "wof:placetype":"venue"
},
  "geometry": {"coordinates":[-5.4481940269,36.6668395996],"type":"Point"}
}