{
  "type": "Feature",
  "properties": {
    "addr:full":"Calle de Remedios, 12 Santa Cruz De La Zarza Toledo 45370",
    "addr:housenumber":"12",
    "addr:postcode":"45370",
    "addr:street":"Calle De Remedios",
    "iso:country":"ES",
    "sg:address":"Calle de Remedios, 12",
    "sg:city":"Santa Cruz De La Zarza",
    "sg:orig_category":"Ropa De Trabajo Y Profesionales (fabricaci\u00d3n, Al Por Mayor)",
    "sg:phone":"+34 925 12 57 90",
    "sg:postcode":"45370",
    "sg:province":"Toledo",
    "wof:name":"Confecciones Karma Xxi S.l.",
    "wof:placetype":"venue"
},
  "geometry": {"coordinates":[-3.1891388893,39.9788513184],"type":"Point"}
}