{
  "type": "Feature",
  "properties": {
    "iso:country":"ES",
    "sg:address":"Aldapeta Kalea, 1",
    "sg:city":"Zarautz",
    "sg:orig_category":"Centros De Educaci\u00d3n Especial",
    "sg:phone":"+34 943 89 43 24",
    "sg:postcode":"20800",
    "sg:province":"Guip\u00f9zcoa",
    "wof:name":"Gobierno Vasco-eusko Jaurlaritza",
    "wof:placetype":"venue"
},
  "geometry": {"coordinates":[-2.1786499023,43.2848815918],"type":"Point"}
}