{
  "type": "Feature",
  "properties": {
    "iso:country":"ES",
    "sg:address":"Calle de Quevedo, 6",
    "sg:city":"Valencia",
    "sg:orig_category":"Agencias De Trabajo Temporal",
    "sg:phone":"+34 963 53 20 40",
    "sg:postcode":"46001",
    "sg:province":"Valencia",
    "sg:website":"www.accessett.com",
    "wof:name":"Empleo Express Empresa De Trabajo Temporal S.l.",
    "wof:placetype":"venue"
},
  "geometry": {"coordinates":[-0.3804329932,39.4699134827],"type":"Point"}
}