{
  "type": "Feature",
  "properties": {
    "addr:full":"Calle de Ciudad De Martos, 23 Mora Toledo 45400",
    "addr:housenumber":"23",
    "addr:postcode":"45400",
    "addr:street":"Calle De Ciudad De Martos",
    "iso:country":"ES",
    "sg:address":"Calle de Ciudad De Martos, 23",
    "sg:city":"Mora",
    "sg:orig_category":"M\u00c9dicos: Estomatolog\u00cda",
    "sg:phone":"+34 925 34 02 97",
    "sg:postcode":"45400",
    "sg:province":"Toledo",
    "wof:name":"Aguilar Roldan Marta",
    "wof:placetype":"venue"
},
  "geometry": {"coordinates":[-3.7717351913,39.6854820251],"type":"Point"}
}