{
  "type": "Feature",
  "properties": {
    "addr:full":"Calle de Camino Viejo De Getafe (del), 18 Fuenlabrada Madrid 28946",
    "addr:housenumber":"18",
    "addr:postcode":"28946",
    "addr:street":"Calle De Camino Viejo De Getafe Del",
    "iso:country":"ES",
    "sg:address":"Calle de Camino Viejo De Getafe (del), 18",
    "sg:city":"Fuenlabrada",
    "sg:orig_category":"Equipo De Refrigeraci\u00d3n Industrial",
    "sg:phone":"+34 916 06 07 55",
    "sg:postcode":"28946",
    "sg:province":"Madrid",
    "wof:name":"Sevenfri S.l.",
    "wof:placetype":"venue"
},
  "geometry": {"coordinates":[-3.7928040028,40.2826004028],"type":"Point"}
}