{
  "type": "Feature",
  "properties": {
    "iso:country":"ES",
    "sg:address":"Calle de San Francisco, 29",
    "sg:city":"Puerto Lumbreras",
    "sg:orig_category":"Medicamentos",
    "sg:phone":"+34 968 40 20 31",
    "sg:postcode":"30890",
    "sg:province":"Murcia",
    "wof:name":"Garcia Caballero Matilde Gloria",
    "wof:placetype":"venue"
},
  "geometry": {"coordinates":[-1.8019039631,37.5663757324],"type":"Point"}
}