{
  "type": "Feature",
  "properties": {
    "addr:full":"Avda Daroca, 60 Madrid Madrid 28017",
    "addr:housenumber":"60",
    "addr:postcode":"madrid;28017",
    "addr:street":"Avda Daroca",
    "iso:country":"ES",
    "sg:address":"Avda Daroca, 60",
    "sg:city":"Madrid",
    "sg:orig_category":"Formaci\u00d3n Continuada (variada)",
    "sg:phone":"+34 914 04 75 04",
    "sg:postcode":"28017",
    "sg:province":"Madrid",
    "wof:name":"Organismo Autonomo De Informatica Y Comunicaciones De La Comunidad De Madrid",
    "wof:placetype":"venue"
},
  "geometry": {"coordinates":[-3.6534099579,40.429397583],"type":"Point"}
}