{
  "type": "Feature",
  "properties": {
    "iso:country":"ES",
    "sg:address":"Calle de Marina, 31",
    "sg:city":"Huelva",
    "sg:orig_category":"Farmacias",
    "sg:phone":"+34 959 24 72 20",
    "sg:postcode":"21001",
    "sg:province":"Huelva",
    "wof:name":"Pereda Lopez Maria Del Pilar",
    "wof:placetype":"venue"
},
  "geometry": {"coordinates":[-6.9565081596,37.2558326721],"type":"Point"}
}