{
  "type": "Feature",
  "properties": {
    "iso:country":"ES",
    "sg:address":"Calle de Real De Coello, 27",
    "sg:city":"Monte Lentiscal",
    "sg:orig_category":"Agencias Y Agentes Comerciales, Representantes",
    "sg:phone":"+34 928 35 00 68",
    "sg:postcode":"35310",
    "sg:province":"Las Palmas",
    "wof:name":"Bonny Miranda Jose Juan",
    "wof:placetype":"venue"
},
  "geometry": {"coordinates":[-15.4726085663,28.0494346619],"type":"Point"}
}