{
  "type": "Feature",
  "properties": {
    "iso:country":"ES",
    "sg:address":"Calle de Valdelacueva (de), 5",
    "sg:city":"Meco",
    "sg:orig_category":"Cueros Y Pieles (al Por Mayor)",
    "sg:phone":"+34 918 86 00 80",
    "sg:postcode":"28880",
    "sg:province":"Madrid",
    "wof:name":"Saturnino Sanchez S.l.",
    "wof:placetype":"venue"
},
  "geometry": {"coordinates":[-3.3227119446,40.5545768738],"type":"Point"}
}