{
  "type": "Feature",
  "properties": {
    "iso:country":"ES",
    "sg:address":"Calle de San Pelayo, S/n",
    "sg:city":"Cangas Onis",
    "sg:orig_category":"Librer\u00cdas",
    "sg:phone":"+34 985 84 82 47",
    "sg:postcode":"33550",
    "sg:province":"Asturias",
    "wof:name":"Herrero Lopez Jose Manuel",
    "wof:placetype":"venue"
},
  "geometry": {"coordinates":[-5.1288371086,43.3498344421],"type":"Point"}
}