{
  "type": "Feature",
  "properties": {
    "iso:country":"ES",
    "sg:address":"Carrer de M D Sales, 37",
    "sg:city":"Viladecans",
    "sg:orig_category":"Cerrajer\u00cda, Ferrallista",
    "sg:phone":"+34 936 59 36 82",
    "sg:postcode":"08840",
    "sg:province":"Barcelona",
    "wof:name":"Gomez Aracil Jose Luis",
    "wof:placetype":"venue"
},
  "geometry": {"coordinates":[2.021805048,41.3167800903],"type":"Point"}
}