{
  "type": "Feature",
  "properties": {
    "addr:full":"Calle de Fueros, S/n Oyon-oion \u00c1lava 01320",
    "addr:postcode":"01320",
    "addr:street":"Calle De Fueros S / N Oyon-Oion A\u0301Lava",
    "iso:country":"ES",
    "sg:address":"Calle de Fueros, S/n",
    "sg:city":"Oyon-oion",
    "sg:orig_category":"Internados & Ense\u00d1anza Privada",
    "sg:phone":"+34 945 60 12 06",
    "sg:postcode":"01320",
    "sg:province":"\u00c1lava",
    "wof:name":"San Vicente Sociedad Cooperativa De Consumo",
    "wof:placetype":"venue"
},
  "geometry": {"coordinates":[-2.4350540638,42.5055236816],"type":"Point"}
}