{
  "type": "Feature",
  "properties": {
    "iso:country":"ES",
    "sg:address":"Calle de Doctor Mu\u00d1oz Seca, S/n",
    "sg:city":"Puerto De Santa Maria",
    "sg:orig_category":"Distribuci\u00d3n De Petr\u00d3leo Y Derivados",
    "sg:phone":"+34 956 87 65 86",
    "sg:postcode":"11500",
    "sg:province":"C\u00e1diz",
    "wof:name":"Romero Cueva S.l.",
    "wof:placetype":"venue"
},
  "geometry": {"coordinates":[-6.2275528908,36.6003684998],"type":"Point"}
}