{
  "type": "Feature",
  "properties": {
    "addr:full":"Plaz San Pedro Y San Pablo (de), 3 Coslada Madrid 28820",
    "addr:postcode":"28820",
    "addr:street":"Plaz San Pedro Y San Pablo",
    "iso:country":"ES",
    "sg:address":"Plaz San Pedro Y San Pablo (de), 3",
    "sg:city":"Coslada",
    "sg:orig_category":"Peluqueros: De Se\u00d1oras",
    "sg:phone":"+34 916 69 39 12",
    "sg:postcode":"28820",
    "sg:province":"Madrid",
    "wof:name":"Solis Morales Amparo",
    "wof:placetype":"venue"
},
  "geometry": {"coordinates":[-3.5668718815,40.4260101318],"type":"Point"}
}