{
  "type": "Feature",
  "properties": {
    "iso:country":"ES",
    "sg:address":"Calle de Virgen De Los Reyes, 22",
    "sg:city":"Palacios Y Villafranca",
    "sg:orig_category":"Alimentaci\u00d3n General (al Por Menor)",
    "sg:phone":"+34 955 81 57 68",
    "sg:postcode":"41720",
    "sg:province":"Sevilla",
    "wof:name":"Morillo Mu\u00f1oz Miguel",
    "wof:placetype":"venue"
},
  "geometry": {"coordinates":[-5.9182510376,37.1601409912],"type":"Point"}
}