{
  "type": "Feature",
  "properties": {
    "addr:full":"Calle de Montenegro, 14 Almeria Almer\u00eda 04008",
    "addr:housenumber":"14",
    "addr:postcode":"04008",
    "addr:street":"Calle De Montenegro",
    "iso:country":"ES",
    "sg:address":"Calle de Montenegro, 14",
    "sg:city":"Almeria",
    "sg:orig_category":"Comercio De Piezas De Recambio Y De Accesorios De Veh\u00cdculos, Veh\u00cdculos Industriales",
    "sg:phone":"+34 950 28 10 34",
    "sg:postcode":"04008",
    "sg:province":"Almer\u00eda",
    "wof:name":"Autorecambio Ure\u00f1a Almeria S.a.l.",
    "wof:placetype":"venue"
},
  "geometry": {"coordinates":[-2.4552459717,36.8544883728],"type":"Point"}
}