{
  "type": "Feature",
  "properties": {
    "iso:country":"ES",
    "sg:address":"Calle de Francisco De Quevedo, 14",
    "sg:city":"Zaragoza",
    "sg:orig_category":"Madera Para Construcci\u00d3n E Industria",
    "sg:phone":"+34 976 41 33 50",
    "sg:postcode":"50013",
    "sg:province":"Zaragoza",
    "sg:website":"www.aresapavimentos.com",
    "wof:name":"Aragonesa De Revestimientos S. A.",
    "wof:placetype":"venue"
},
  "geometry": {"coordinates":[-0.8653584123,41.6409835815],"type":"Point"}
}