{
  "type": "Feature",
  "properties": {
    "addr:full":"Calle de Riego, 19 Zamora Zamora 49004",
    "addr:housenumber":"19",
    "addr:postcode":"49004",
    "addr:street":"Calle De Riego",
    "iso:country":"ES",
    "sg:address":"Calle de Riego, 19",
    "sg:city":"Zamora",
    "sg:orig_category":"Procuradores",
    "sg:phone":"+34 980 51 96 83",
    "sg:postcode":"49004",
    "sg:province":"Zamora",
    "wof:name":"Alonso Hernandez Enrique",
    "wof:placetype":"venue"
},
  "geometry": {"coordinates":[-5.7475056648,41.5049171448],"type":"Point"}
}