{
  "type": "Feature",
  "properties": {
    "addr:full":"Calle de Maestro Juan Marin De Vargas, 4 Cabezas S. Juan Sevilla 41730",
    "addr:housenumber":"4",
    "addr:postcode":"41730",
    "addr:street":"Calle De Maestro Juan Marin De Vargas;S.",
    "iso:country":"ES",
    "sg:address":"Calle de Maestro Juan Marin De Vargas, 4",
    "sg:city":"Cabezas S. Juan",
    "sg:orig_category":"Ropa Para Ni\u00d1os (al Por Menor)",
    "sg:phone":"+34 955 87 21 12",
    "sg:postcode":"41730",
    "sg:province":"Sevilla",
    "wof:name":"Guerrero Silva Juan Benito",
    "wof:placetype":"venue"
},
  "geometry": {"coordinates":[-5.9365491867,36.9817962646],"type":"Point"}
}