{
  "type": "Feature",
  "properties": {
    "iso:country":"ES",
    "sg:address":"Rua Costa, 2",
    "sg:city":"Galindra",
    "sg:orig_category":"Estilistas Y Estudios De Estilo De Corte Y Confecci\u00d3n",
    "sg:phone":"+34 986 29 28 13",
    "sg:postcode":"36213",
    "sg:province":"Pontevedra",
    "wof:name":"Cabaleiro Fernandez Bernardo",
    "wof:placetype":"venue"
},
  "geometry": {"coordinates":[-8.7210121155,42.1948318481],"type":"Point"}
}