{
  "type": "Feature",
  "properties": {
    "iso:country":"ES",
    "sg:address":"Avda Constitucion, 118",
    "sg:city":"Madridejos",
    "sg:orig_category":"Armas Y Municiones (fabricaci\u00d3n, Al Por Mayor)",
    "sg:phone":"+34 925 46 03 94",
    "sg:postcode":"45710",
    "sg:province":"Toledo",
    "wof:name":"Lopez Alonso Maximo",
    "wof:placetype":"venue"
},
  "geometry": {"coordinates":[-3.5336658955,39.4755630493],"type":"Point"}
}