{
  "type": "Feature",
  "properties": {
    "addr:full":"Avda Constitucion (de La), 50 Alcala Rio Sevilla 41200",
    "addr:housenumber":"50",
    "addr:postcode":"41200",
    "addr:street":"Avda Constitucion De La",
    "iso:country":"ES",
    "sg:address":"Avda Constitucion (de La), 50",
    "sg:city":"Alcala Rio",
    "sg:orig_category":"Quincaller\u00cda (al Por Menor)",
    "sg:phone":"+34 954 78 00 46",
    "sg:postcode":"41200",
    "sg:province":"Sevilla",
    "wof:name":"Gallardo Noguera Gregorio",
    "wof:placetype":"venue"
},
  "geometry": {"coordinates":[-5.984585762,37.5183982849],"type":"Point"}
}