{
  "type": "Feature",
  "properties": {
    "addr:full":"Pase Alberto Palacios, 21 Madrid Madrid 28021",
    "addr:housenumber":"21",
    "addr:postcode":"madrid;28021",
    "addr:street":"Alberto Palacios",
    "iso:country":"ES",
    "sg:address":"Pase Alberto Palacios, 21",
    "sg:city":"Madrid",
    "sg:orig_category":"Panader\u00cdas, Panader\u00cdas",
    "sg:phone":"+34 917 97 17 10",
    "sg:postcode":"28021",
    "sg:province":"Madrid",
    "wof:name":"Martinez Frias Julian",
    "wof:placetype":"venue"
},
  "geometry": {"coordinates":[-3.7123138905,40.3430862427],"type":"Point"}
}