{
  "type": "Feature",
  "properties": {
    "addr:full":"Pase Ezequiel Gonzalez, 24 Segovia Segovia 40002",
    "addr:housenumber":"24",
    "addr:postcode":"40002",
    "addr:street":"Gonzalez",
    "iso:country":"ES",
    "sg:address":"Pase Ezequiel Gonzalez, 24",
    "sg:city":"Segovia",
    "sg:orig_category":"Agentes Generales De Seguros",
    "sg:phone":"+34 921 42 64 27",
    "sg:postcode":"40002",
    "sg:province":"Segovia",
    "sg:website":"www.paginasamarillas.es",
    "wof:name":"Carretero Arribas S.l.",
    "wof:placetype":"venue"
},
  "geometry": {"coordinates":[-4.1206607819,40.9438896179],"type":"Point"}
}