{
  "type": "Feature",
  "properties": {
    "iso:country":"ES",
    "sg:address":"Co. De La Iglesia, 12",
    "sg:city":"Navelgas",
    "sg:classifiers":[
        {
            "category":"Taxi",
            "type":"Transportation"
        }
    ],
    "sg:phone":"+34 985 80 60 46",
    "sg:postcode":"33873",
    "sg:province":"Asturias",
    "wof:name":"Gayo Garcia Marcial",
    "wof:placetype":"venue"
},
  "geometry": {"coordinates":[-6.5324959755,43.4251785278],"type":"Point"}
}