{
  "type": "Feature",
  "properties": {
    "addr:full":"Calle de Tirso De Molina, 62 Yebenes Toledo 45470",
    "addr:housenumber":"62",
    "addr:postcode":"45470",
    "addr:street":"Calle De Tirso De Molina",
    "iso:country":"ES",
    "sg:address":"Calle de Tirso De Molina, 62",
    "sg:city":"Yebenes",
    "sg:orig_category":"Empresas De Carpinter\u00cda De Madera",
    "sg:phone":"+34 925 34 82 78",
    "sg:postcode":"45470",
    "sg:province":"Toledo",
    "wof:name":"Carpinteria Morsol S.l.l.",
    "wof:placetype":"venue"
},
  "geometry": {"coordinates":[-3.8730390072,39.578666687],"type":"Point"}
}