{
  "type": "Feature",
  "properties": {
    "addr:full":"Carrer de Paris, 172 Barcelona Barcelona 08036",
    "addr:housenumber":"172",
    "addr:postcode":"08036",
    "addr:street":"Carrer De Paris",
    "iso:country":"ES",
    "sg:address":"Carrer de Paris, 172",
    "sg:city":"Barcelona",
    "sg:orig_category":"Compraventa De Antig\u00dcedades",
    "sg:phone":"+34 934 10 35 73",
    "sg:postcode":"08036",
    "sg:province":"Barcelona",
    "wof:name":"J & B Antiques S.c.p.",
    "wof:placetype":"venue"
},
  "geometry": {"coordinates":[2.1522901058,41.392742157],"type":"Point"}
}