{
  "type": "Feature",
  "properties": {
    "addr:full":"Ctra Mojonera A San Agustin, 175 Mojonera Almer\u00eda 04745",
    "addr:housenumber":"175",
    "addr:postcode":"04745",
    "addr:street":"Ctra Mojonera A San Agustin",
    "iso:country":"ES",
    "sg:address":"Ctra Mojonera A San Agustin, 175",
    "sg:city":"Mojonera",
    "sg:orig_category":"Insecticidas, Fumigaci\u00d3n",
    "sg:phone":"+34 950 33 15 99",
    "sg:postcode":"04745",
    "sg:province":"Almer\u00eda",
    "wof:name":"Comercial Agricola Romagro S.l.",
    "wof:placetype":"venue"
},
  "geometry": {"coordinates":[-2.6811990738,36.7550849915],"type":"Point"}
}