{
  "type": "Feature",
  "properties": {
    "addr:full":"C/ Solars, 11 Elche Alicante 03203",
    "addr:housenumber":"11",
    "addr:postcode":"03203",
    "addr:street":"C / Solars",
    "iso:country":"ES",
    "sg:address":"C/ Solars, 11",
    "sg:city":"Elche",
    "sg:orig_category":"Sociedades, Compa\u00d1\u00cdas Aseguradoras",
    "sg:phone":"+34 966 61 00 82",
    "sg:postcode":"03203",
    "sg:province":"Alicante",
    "wof:name":"Solars S.l.",
    "wof:placetype":"venue"
},
  "geometry": {"coordinates":[-0.6968870163,38.2636947632],"type":"Point"}
}