{
  "type": "Feature",
  "properties": {
    "addr:full":"Carrer de Rossello, 75 S. Boi Llobregat Barcelona 08830",
    "addr:housenumber":"75",
    "addr:postcode":"08830",
    "addr:street":"Carrer De Rossello",
    "iso:country":"ES",
    "sg:address":"Carrer de Rossello, 75",
    "sg:city":"S. Boi Llobregat",
    "sg:orig_category":"Supermercados Y Hipermercados",
    "sg:phone":"+34 936 30 53 49",
    "sg:postcode":"08830",
    "sg:province":"Barcelona",
    "wof:name":"Supermercados Carretero S. L",
    "wof:placetype":"venue"
},
  "geometry": {"coordinates":[2.0276949406,41.3474502563],"type":"Point"}
}