{
  "type": "Feature",
  "properties": {
    "addr:full":"Calle de Marques De Quintanar, 11 Baiona Pontevedra 36300",
    "addr:housenumber":"11",
    "addr:postcode":"36300",
    "addr:street":"Calle De Marques De Quintanar",
    "iso:country":"ES",
    "sg:address":"Calle de Marques De Quintanar, 11",
    "sg:city":"Baiona",
    "sg:orig_category":"Inmobiliaria (agencias)",
    "sg:phone":"+34 986 35 62 15",
    "sg:postcode":"36300",
    "sg:province":"Pontevedra",
    "wof:name":"Fincas Rodriguez C.b.",
    "wof:placetype":"venue"
},
  "geometry": {"coordinates":[-97.78224945069999,45.7040786743],"type":"Point"}
}