{
  "type": "Feature",
  "properties": {
    "iso:country":"ES",
    "sg:address":"Calle de Canales, S/n",
    "sg:city":"Malaga",
    "sg:orig_category":"Barcos",
    "sg:phone":"+34 952 31 08 92",
    "sg:postcode":"29002",
    "sg:province":"M\u00e1laga",
    "sg:website":"www.shiprovision.com",
    "wof:name":"Shiprovision Co S.a.",
    "wof:placetype":"venue"
},
  "geometry": {"coordinates":[-4.4270339012,36.7115745544],"type":"Point"}
}