{
  "type": "Feature",
  "properties": {
    "addr:full":"Olaso Kalea, 30 Elgoibar Guip\u00f9zcoa 20870",
    "addr:housenumber":"30",
    "addr:postcode":"20870",
    "addr:street":"Olaso Kalea;Guipu\u0300Zcoa",
    "iso:country":"ES",
    "sg:address":"Olaso Kalea, 30",
    "sg:city":"Elgoibar",
    "sg:orig_category":"Muebles, Minoristas",
    "sg:phone":"+34 943 74 42 87",
    "sg:postcode":"20870",
    "sg:province":"Guip\u00f9zcoa",
    "wof:name":"Dabrio Paez Andres",
    "wof:placetype":"venue"
},
  "geometry": {"coordinates":[-2.4227399826,43.2067108154],"type":"Point"}
}