{
  "type": "Feature",
  "properties": {
    "iso:country":"ES",
    "sg:address":"Ctra. Medellin, Km. 0048,5",
    "sg:city":"Almoharin",
    "sg:orig_category":"Venta, Instalaci\u00d3n De Cocinas",
    "sg:phone":"+34 927 38 60 50",
    "sg:postcode":"10132",
    "sg:province":"C\u00e1ceres",
    "wof:name":"Cortes Gonzalez Jacinto",
    "wof:placetype":"venue"
},
  "geometry": {"coordinates":[-6.0440888405,39.1764564514],"type":"Point"}
}