{
  "type": "Feature",
  "properties": {
    "addr:full":"Calle de Dos De Mayo, 1 San Bartolome Alicante 03314",
    "addr:housenumber":"1",
    "addr:postcode":"03314",
    "addr:street":"Calle De Dos De Mayo",
    "iso:country":"ES",
    "sg:address":"Calle de Dos De Mayo, 1",
    "sg:city":"San Bartolome",
    "sg:orig_category":"Asociaciones Y Clubs Deportivos",
    "sg:phone":"+34 966 77 60 69",
    "sg:postcode":"03314",
    "sg:province":"Alicante",
    "wof:name":"Azulgrana San Bartolome",
    "wof:placetype":"venue"
},
  "geometry": {"coordinates":[-0.861579895,38.0942955017],"type":"Point"}
}