{
  "type": "Feature",
  "properties": {
    "addr:full":"Calle de San Anton, 1 Fuentes Ebro Zaragoza 50740",
    "addr:housenumber":"1",
    "addr:postcode":"50740",
    "addr:street":"Calle De San Anton",
    "iso:country":"ES",
    "sg:address":"Calle de San Anton, 1",
    "sg:city":"Fuentes Ebro",
    "sg:orig_category":"Agricultores, Agricultores",
    "sg:phone":"+34 976 16 07 17",
    "sg:postcode":"50740",
    "sg:province":"Zaragoza",
    "wof:name":"Naharro Sanchez Jose Miguel",
    "wof:placetype":"venue"
},
  "geometry": {"coordinates":[-0.6293500066,41.5131912231],"type":"Point"}
}