{
  "type": "Feature",
  "properties": {
    "iso:country":"ES",
    "sg:address":"Calle de Villanueva, S/n",
    "sg:city":"Carde\u00f1a",
    "sg:orig_category":"Cr\u00cda De Animales",
    "sg:phone":"+34 957 33 61 38",
    "sg:postcode":"14445",
    "sg:province":"C\u00f3rdoba",
    "wof:name":"Dehesa De Navalazarza S.l",
    "wof:placetype":"venue"
},
  "geometry": {"coordinates":[-4.3252191544,38.2721748352],"type":"Point"}
}