{
  "type": "Feature",
  "properties": {
    "iso:country":"ES",
    "sg:address":"Praj El Campu, S/n",
    "sg:city":"Lepe",
    "sg:orig_category":"Arboricultura Y Producci\u00d3n De Frutas",
    "sg:phone":"+34 959 38 04 48",
    "sg:postcode":"21440",
    "sg:province":"Huelva",
    "wof:name":"Torruella Vilella Pere",
    "wof:placetype":"venue"
},
  "geometry": {"coordinates":[-7.2029190063,37.255241394],"type":"Point"}
}