{
  "type": "Feature",
  "properties": {
    "addr:full":"Avda Ntra. Se\u00d1ora Del Carmen, S/n Corralejo Playa Las Palmas 35660",
    "addr:housenumber":"s / n",
    "addr:postcode":"35660",
    "addr:street":"Avda Ntra. Sen\u0303Ora Del Carmen;Playa Las Palmas",
    "iso:country":"ES",
    "sg:address":"Avda Ntra. Se\u00d1ora Del Carmen, S/n",
    "sg:city":"Corralejo Playa",
    "sg:orig_category":"Discotecas Y Salas De Baile",
    "sg:phone":"+34 928 53 70 67",
    "sg:postcode":"35660",
    "sg:province":"Las Palmas",
    "wof:name":"Hen 2 Ton",
    "wof:placetype":"venue"
},
  "geometry": {"coordinates":[-13.8689088821,28.7360801697],"type":"Point"}
}