{
  "type": "Feature",
  "properties": {
    "iso:country":"ES",
    "sg:address":"Ctra Guixa, 10",
    "sg:city":"Vic",
    "sg:orig_category":"Centros De Coordinaci\u00d3n",
    "sg:phone":"+34 938 85 00 70",
    "sg:postcode":"08500",
    "sg:province":"Barcelona",
    "wof:name":"Gestoria Pujols S.c.p.",
    "wof:placetype":"venue"
},
  "geometry": {"coordinates":[2.2527270317,41.9245376587],"type":"Point"}
}