{
  "type": "Feature",
  "properties": {
    "addr:full":"Carrer de Anselm Clave, 5 Granollers Barcelona 08402",
    "addr:housenumber":"5",
    "addr:postcode":"08402",
    "addr:street":"Carrer De Anselm Clave",
    "iso:country":"ES",
    "sg:address":"Carrer de Anselm Clave, 5",
    "sg:city":"Granollers",
    "sg:orig_category":"Trabajos De Topograf\u00cda",
    "sg:phone":"+34 938 70 28 97",
    "sg:postcode":"08402",
    "sg:province":"Barcelona",
    "wof:name":"Sertur Serveis S.c.p.",
    "wof:placetype":"venue"
},
  "geometry": {"coordinates":[2.2891259193,41.6081466675],"type":"Point"}
}