{
  "type": "Feature",
  "properties": {
    "iso:country":"ES",
    "sg:address":"Calle de Cardenal Marcelo Spinola, 8",
    "sg:city":"Madrid",
    "sg:orig_category":"Bancos",
    "sg:phone":"+34 917 66 21 22",
    "sg:postcode":"28016",
    "sg:province":"Madrid",
    "wof:name":"Societe Generale Sucursal En Espa\u00f1a",
    "wof:placetype":"venue"
},
  "geometry": {"coordinates":[-3.6699075699,40.4671211243],"type":"Point"}
}