{
  "type": "Feature",
  "properties": {
    "addr:full":"Calle de Arte Mayor De La Seda, 21 Valencia Valencia 46018",
    "addr:housenumber":"21",
    "addr:postcode":"46018",
    "addr:street":"Calle De Arte Mayor De La Seda",
    "iso:country":"ES",
    "sg:address":"Calle de Arte Mayor De La Seda, 21",
    "sg:city":"Valencia",
    "sg:orig_category":"Alimentaci\u00d3n General (al Por Menor)",
    "sg:phone":"+34 963 70 46 70",
    "sg:postcode":"46018",
    "sg:province":"Valencia",
    "wof:name":"Sanchis Requeni Jose",
    "wof:placetype":"venue"
},
  "geometry": {"coordinates":[-0.3975315094,39.4699859619],"type":"Point"}
}