{
  "type": "Feature",
  "properties": {
    "iso:country":"ES",
    "sg:address":"Calle de Victoria (la), 2",
    "sg:city":"Ecija",
    "sg:orig_category":"Contenedores (mercanc\u00cdas)",
    "sg:phone":"+34 954 83 13 25",
    "sg:postcode":"41400",
    "sg:province":"Sevilla",
    "wof:name":"Marin Garcia Mariano",
    "wof:placetype":"venue"
},
  "geometry": {"coordinates":[-5.0802688599,37.5365600586],"type":"Point"}
}