{
  "type": "Feature",
  "properties": {
    "addr:full":"Donibane Kalea, 6 Lezo Guip\u00f9zcoa 20100",
    "addr:housenumber":"6",
    "addr:postcode":"20100",
    "addr:street":"Donibane Kalea;Guipu\u0300Zcoa",
    "iso:country":"ES",
    "sg:address":"Donibane Kalea, 6",
    "sg:city":"Lezo",
    "sg:orig_category":"Farmacias",
    "sg:phone":"+34 943 34 45 56",
    "sg:postcode":"20100",
    "sg:province":"Guip\u00f9zcoa",
    "wof:name":"Rodriguez Zarzuelo Teresa",
    "wof:placetype":"venue"
},
  "geometry": {"coordinates":[-1.9001330137,43.3208694458],"type":"Point"}
}