{
  "type": "Feature",
  "properties": {
    "iso:country":"ES",
    "sg:address":"Av Josep Tarradellas, 46",
    "sg:city":"Viladecans",
    "sg:orig_category":"Reposter\u00cdas",
    "sg:phone":"+34 936 37 81 93",
    "sg:postcode":"08840",
    "sg:province":"Barcelona",
    "wof:name":"Forn De Pa Castelldefels S.l.",
    "wof:placetype":"venue"
},
  "geometry": {"coordinates":[2.0157170296,41.3126907349],"type":"Point"}
}