{
  "type": "Feature",
  "properties": {
    "addr:full":"Carr Marti Rubi-secretari, 18 Cabaneta Islas Baleares 07141",
    "addr:housenumber":"18",
    "addr:postcode":"07141",
    "addr:street":"Carr Marti Rubi-Secretari;Islas",
    "iso:country":"ES",
    "sg:address":"Carr Marti Rubi-secretari, 18",
    "sg:city":"Cabaneta",
    "sg:orig_category":"Agencias Y Agentes Comerciales, Representantes",
    "sg:phone":"+34 971 79 72 21",
    "sg:postcode":"07141",
    "sg:province":"Islas Baleares",
    "wof:name":"Palmer Vallejo Jose Miguel",
    "wof:placetype":"venue"
},
  "geometry": {"coordinates":[2.7445349693,39.6195487976],"type":"Point"}
}