{
  "type": "Feature",
  "properties": {
    "addr:full":"Calle de Ascension Lopez Pereira (de), 2 Colmenar Viejo Madrid 28770",
    "addr:postcode":"28770",
    "addr:street":"Calle De",
    "iso:country":"ES",
    "sg:address":"Calle de Ascension Lopez Pereira (de), 2",
    "sg:city":"Colmenar Viejo",
    "sg:classifiers":[
        {
            "category":"Professional",
            "subcategory":"Research",
            "type":"Services"
        }
    ],
    "sg:phone":"+34 918 45 31 97",
    "sg:postcode":"28770",
    "sg:province":"Madrid",
    "sg:tags":[
        "mercado",
        "de",
        "estudios"
    ],
    "wof:name":"Data Report S.l",
    "wof:placetype":"venue"
},
  "geometry": {"coordinates":[-3.7684729099,40.6681213379],"type":"Point"}
}