{
  "type": "Feature",
  "properties": {
    "iso:country":"ES",
    "sg:address":"Calle de Rey Sancho El Fuerte, 4",
    "sg:city":"Puerto",
    "sg:orig_category":"Maquinaria Neum\u00c1tica",
    "sg:phone":"+34 962 69 02 21",
    "sg:postcode":"46520",
    "sg:province":"Valencia",
    "wof:name":"Hidraulica Morvedre S.l.",
    "wof:placetype":"venue"
},
  "geometry": {"coordinates":[-0.2330809981,39.6648902893],"type":"Point"}
}