{
  "type": "Feature",
  "properties": {
    "iso:country":"ES",
    "sg:address":"Calle de Guerrero Julian Sanchez, 1",
    "sg:city":"Zamora",
    "sg:orig_category":"Cooperativas Agr\u00cdcolas",
    "sg:phone":"+34 980 51 07 15",
    "sg:postcode":"49016",
    "sg:province":"Zamora",
    "wof:name":"Servicios Agrarios La Union S.l.",
    "wof:placetype":"venue"
},
  "geometry": {"coordinates":[-5.7384800911,41.5038070679],"type":"Point"}
}