{
  "type": "Feature",
  "properties": {
    "addr:full":"Plaz Pedro Davila, 8 Avila \u00c1vila 05001",
    "addr:housenumber":"8",
    "addr:postcode":"05001",
    "addr:street":"Davila;A\u0301Vila",
    "iso:country":"ES",
    "sg:address":"Plaz Pedro Davila, 8",
    "sg:city":"Avila",
    "sg:orig_category":"Asesor\u00cda Fiscal Y Jur\u00cddica",
    "sg:phone":"+34 920 22 37 97",
    "sg:postcode":"05001",
    "sg:province":"\u00c1vila",
    "wof:name":"Martin Fernandez Carlos",
    "wof:placetype":"venue"
},
  "geometry": {"coordinates":[-4.7004737854,40.6551628113],"type":"Point"}
}