{
  "type": "Feature",
  "properties": {
    "addr:full":"Calle de Manuel Perez Navarro, 7 Palmas De Gran Canaria Las Palmas 35014",
    "addr:housenumber":"7",
    "addr:postcode":"35014",
    "addr:street":"Calle De Manuel Perez Navarro",
    "iso:country":"ES",
    "sg:address":"Calle de Manuel Perez Navarro, 7",
    "sg:city":"Palmas De Gran Canaria",
    "sg:orig_category":"Electricidad, Electr\u00d3nica: Material Y Suministros (al Por Mayor)",
    "sg:phone":"+34 928 38 04 44",
    "sg:postcode":"35014",
    "sg:province":"Las Palmas",
    "wof:name":"Santana Castro Jose Juan",
    "wof:placetype":"venue"
},
  "geometry": {"coordinates":[-15.4309778214,28.1044368744],"type":"Point"}
}