{
  "type": "Feature",
  "properties": {
    "iso:country":"ES",
    "sg:address":"Pol. Industrial, S/n",
    "sg:city":"Soraluze-placencia Armas",
    "sg:orig_category":"Fabricaci\u00d3n De Pernos, Tornillos Y Clavos",
    "sg:phone":"+34 943 75 12 45",
    "sg:postcode":"20590",
    "sg:province":"Guip\u00f9zcoa",
    "wof:name":"Urrestarazu Aristi Alejandro",
    "wof:placetype":"venue"
},
  "geometry": {"coordinates":[-2.2066218853,43.16746521],"type":"Point"}
}