{
  "type": "Feature",
  "properties": {
    "iso:country":"ES",
    "sg:address":"Calle de Doctores Castroviejo, 25",
    "sg:city":"Logro\u00f1o",
    "sg:orig_category":"Fotograf\u00cda Art\u00cdstica Y Retratos",
    "sg:phone":"+34 941 24 13 13",
    "sg:postcode":"26003",
    "sg:province":"La Rioja",
    "wof:name":"Aragon Lago Alvaro",
    "wof:placetype":"venue"
},
  "geometry": {"coordinates":[-2.4412031174,42.4625854492],"type":"Point"}
}