{
  "type": "Feature",
  "properties": {
    "addr:full":"Calle de Marques De La Valdavia (del), 40 Alcobendas Madrid 28100",
    "addr:postcode":"28100",
    "addr:street":"Calle De Marques De La Valdavia Del;Alcobendas",
    "iso:country":"ES",
    "sg:address":"Calle de Marques De La Valdavia (del), 40",
    "sg:city":"Alcobendas",
    "sg:orig_category":"Cajas De Ahorro",
    "sg:phone":"+34 916 53 40 67",
    "sg:postcode":"28100",
    "sg:province":"Madrid",
    "sg:website":"www.caja-granada.es",
    "wof:name":"Cajagranada",
    "wof:placetype":"venue"
},
  "geometry": {"coordinates":[-3.638160944,40.542350769],"type":"Point"}
}