{
  "type": "Feature",
  "properties": {
    "iso:country":"ES",
    "sg:address":"Carrer de Joaquim Valls, 118",
    "sg:city":"Barcelona",
    "sg:orig_category":"Confecci\u00d3n De Ropa Interior",
    "sg:phone":"+34 933 50 68 45",
    "sg:postcode":"08042",
    "sg:province":"Barcelona",
    "wof:name":"Martinez Linares Susana Cristina",
    "wof:placetype":"venue"
},
  "geometry": {"coordinates":[2.1772949696,41.4452095032],"type":"Point"}
}