{
  "type": "Feature",
  "properties": {
    "addr:full":"Calle de Suarez Guerra, 6 Santa Cruz De Tenerife Santa Cruz De Tenerife 38003",
    "addr:housenumber":"6",
    "addr:postcode":"38003",
    "addr:street":"Calle De Suarez Guerra",
    "iso:country":"ES",
    "sg:address":"Calle de Suarez Guerra, 6",
    "sg:city":"Santa Cruz De Tenerife",
    "sg:orig_category":"Textil",
    "sg:phone":"+34 922 28 96 83",
    "sg:postcode":"38003",
    "sg:province":"Santa Cruz De Tenerife",
    "wof:name":"Almazan Vieira Maria De Gracia",
    "wof:placetype":"venue"
},
  "geometry": {"coordinates":[-16.2534713745,28.4674701691],"type":"Point"}
}