{
  "type": "Feature",
  "properties": {
    "addr:full":"Calle de Alfonso Decimo El Sabio, 6 Cuellar Segovia 40200",
    "addr:housenumber":"6",
    "addr:postcode":"40200",
    "addr:street":"Calle De Alfonso Decimo El Sabio",
    "iso:country":"ES",
    "sg:address":"Calle de Alfonso Decimo El Sabio, 6",
    "sg:city":"Cuellar",
    "sg:orig_category":"Chapister\u00cda",
    "sg:phone":"+34 921 14 06 48",
    "sg:postcode":"40200",
    "sg:province":"Segovia",
    "wof:name":"Varas C.b. Chapa Y Pintura",
    "wof:placetype":"venue"
},
  "geometry": {"coordinates":[-4.3105888367,41.3964881897],"type":"Point"}
}