{
  "type": "Feature",
  "properties": {
    "addr:full":"Calle de Maria Luna, 11 Zaragoza Zaragoza 50015",
    "addr:housenumber":"11",
    "addr:postcode":"50015",
    "addr:street":"Calle De Maria Luna",
    "iso:country":"ES",
    "sg:address":"Calle de Maria Luna, 11",
    "sg:city":"Zaragoza",
    "sg:orig_category":"Laboratorios",
    "sg:phone":"+34 976 73 15 33",
    "sg:postcode":"50015",
    "sg:province":"Zaragoza",
    "wof:name":"Zeu Inmunotec S.l.",
    "wof:placetype":"venue"
},
  "geometry": {"coordinates":[-0.887201786,41.6816749573],"type":"Point"}
}