{
  "type": "Feature",
  "properties": {
    "iso:country":"ES",
    "sg:address":"Pase Estacion, 34",
    "sg:city":"Tarancon",
    "sg:orig_category":"M\u00c9dicos: Cardiolog\u00cda Y Afecciones Cardiovasculares",
    "sg:phone":"+34 969 32 06 36",
    "sg:postcode":"16400",
    "sg:province":"Cuenca",
    "wof:name":"Lopez Delgado Ramon",
    "wof:placetype":"venue"
},
  "geometry": {"coordinates":[-3.0081911087,40.0077018738],"type":"Point"}
}