{
  "type": "Feature",
  "properties": {
    "addr:full":"Cmno Azagador, S/n Monforte Cid Alicante 03670",
    "addr:housenumber":"s",
    "addr:postcode":"03670",
    "addr:street":"Cmno Azagador;/ N",
    "iso:country":"ES",
    "sg:address":"Cmno Azagador, S/n",
    "sg:city":"Monforte Cid",
    "sg:orig_category":"Producci\u00d3n De Abonos Y De Fertilizantes",
    "sg:phone":"+34 965 62 06 57",
    "sg:postcode":"03670",
    "sg:province":"Alicante",
    "wof:name":"Coop Valenciana Agricola Monforte Del Cid",
    "wof:placetype":"venue"
},
  "geometry": {"coordinates":[-0.7296299934,38.3807296753],"type":"Point"}
}