{
  "type": "Feature",
  "properties": {
    "addr:full":"Avda Industria (de La), 47 Fuenlabrada Madrid 28947",
    "addr:housenumber":"47",
    "addr:postcode":"28947",
    "addr:street":"Avda Industria De La",
    "iso:country":"ES",
    "sg:address":"Avda Industria (de La), 47",
    "sg:city":"Fuenlabrada",
    "sg:orig_category":"Alquiler De Veh\u00cdculos: Turismos Y Utilitarios",
    "sg:phone":"+34 916 90 87 70",
    "sg:postcode":"28947",
    "sg:province":"Madrid",
    "sg:website":"www.ancora.com",
    "wof:name":"Automoviles Ancora S.l.",
    "wof:placetype":"venue"
},
  "geometry": {"coordinates":[-3.7620966434,40.2704620361],"type":"Point"}
}