{
  "type": "Feature",
  "properties": {
    "iso:country":"ES",
    "sg:address":"Carretera Cordoba-valencia, Km. 0151,8",
    "sg:city":"Ubeda",
    "sg:orig_category":"Refiner\u00cdas De Petr\u00d3leo",
    "sg:phone":"+34 953 75 66 08",
    "sg:postcode":"23400",
    "sg:province":"Ja\u00e9n",
    "wof:name":"Martinez Garrido Francisco",
    "wof:placetype":"venue"
},
  "geometry": {"coordinates":[-3.3619389534,38.0198287964],"type":"Point"}
}