{
  "type": "Feature",
  "properties": {
    "addr:full":"Avda Habana, 8 Pontes Garcia Rodriguez La Coru\u00f1a 15320",
    "addr:housenumber":"8",
    "addr:postcode":"15320",
    "addr:street":"Avda Habana;Rodriguez;Corun\u0303A",
    "iso:country":"ES",
    "sg:address":"Avda Habana, 8",
    "sg:city":"Pontes Garcia Rodriguez",
    "sg:orig_category":"Asesor\u00cda Sobre Comunicaci\u00d3n De Empresas",
    "sg:phone":"+34 981 45 17 99",
    "sg:postcode":"15320",
    "sg:province":"La Coru\u00f1a",
    "wof:name":"Asesoria Vila Das Pontes S.l.n.e.",
    "wof:placetype":"venue"
},
  "geometry": {"coordinates":[-7.8477287292,43.4487075806],"type":"Point"}
}