{
  "type": "Feature",
  "properties": {
    "addr:full":"Travesia Del Rio, 1 Velez-malaga M\u00e1laga 29700",
    "addr:housenumber":"1",
    "addr:postcode":"29700",
    "addr:street":"Travesia Del Rio",
    "iso:country":"ES",
    "sg:address":"Travesia Del Rio, 1",
    "sg:city":"Velez-malaga",
    "sg:orig_category":"Ropa Para Ni\u00d1os (al Por Menor)",
    "sg:phone":"+34 952 50 13 24",
    "sg:postcode":"29700",
    "sg:province":"M\u00e1laga",
    "wof:name":"Delgado Diaz Herminia",
    "wof:placetype":"venue"
},
  "geometry": {"coordinates":[-4.1049690247,36.7808113098],"type":"Point"}
}