{
  "type": "Feature",
  "properties": {
    "addr:full":"Avda Santiago, 43 Vista Alegre Murcia 30007",
    "addr:housenumber":"43",
    "addr:postcode":"30007",
    "addr:street":"Avda Santiago",
    "iso:country":"ES",
    "sg:address":"Avda Santiago, 43",
    "sg:city":"Vista Alegre",
    "sg:orig_category":"Cajas De Ahorro",
    "sg:phone":"+34 968 27 15 19",
    "sg:postcode":"30007",
    "sg:province":"Murcia",
    "wof:name":"Caja De Ahorros Del Mediterraneo",
    "wof:placetype":"venue"
},
  "geometry": {"coordinates":[-1.1256439686,38.0004730225],"type":"Point"}
}