{
  "type": "Feature",
  "properties": {
    "addr:full":"Av Espanya, 8 Eivissa Islas Baleares 07800",
    "addr:housenumber":"8",
    "addr:postcode":"07800",
    "addr:street":"Av Espanya",
    "iso:country":"ES",
    "sg:address":"Av Espanya, 8",
    "sg:city":"Eivissa",
    "sg:orig_category":"Caf\u00c9s, Bares, Cervecer\u00cdas",
    "sg:phone":"+34 971 39 98 63",
    "sg:postcode":"07800",
    "sg:province":"Islas Baleares",
    "wof:name":"Maxisana S.l.",
    "wof:placetype":"venue"
},
  "geometry": {"coordinates":[1.4315849543,38.9088287354],"type":"Point"}
}