{
  "type": "Feature",
  "properties": {
    "addr:full":"Avda Virgen De Cala, 1 Cala Huelva 21270",
    "addr:housenumber":"1",
    "addr:postcode":"21270",
    "addr:street":"Avda Virgen De Cala",
    "iso:country":"ES",
    "sg:address":"Avda Virgen De Cala, 1",
    "sg:city":"Cala",
    "sg:orig_category":"Empresas De Electricidad En General",
    "sg:phone":"+34 959 19 10 34",
    "sg:postcode":"21270",
    "sg:province":"Huelva",
    "wof:name":"Vazquez Zapata Manuel",
    "wof:placetype":"venue"
},
  "geometry": {"coordinates":[-6.3160510063,37.9720611572],"type":"Point"}
}