{
  "type": "Feature",
  "properties": {
    "addr:full":"Calle de Innovacion, 23 Mairena Aljarafe Sevilla 41927",
    "addr:housenumber":"23",
    "addr:postcode":"41927",
    "addr:street":"Calle De Innovacion",
    "iso:country":"ES",
    "sg:address":"Calle de Innovacion, 23",
    "sg:city":"Mairena Aljarafe",
    "sg:orig_category":"Fabricaci\u00d3n, Instalaci\u00d3n Y Reparaci\u00d3n De Bombas",
    "sg:phone":"+34 954 18 41 52",
    "sg:postcode":"41927",
    "sg:province":"Sevilla",
    "sg:website":"www.bonbarpinze.com",
    "wof:name":"Electrobombas S.l.",
    "wof:placetype":"venue"
},
  "geometry": {"coordinates":[-6.0559191704,37.3561096191],"type":"Point"}
}