{
  "type": "Feature",
  "properties": {
    "addr:full":"Calle de Paso (el), 4 Almunia De Do\u00e7a Godina Zaragoza 50100",
    "addr:housenumber":"4",
    "addr:postcode":"50100",
    "addr:street":"Calle De Paso El",
    "iso:country":"ES",
    "sg:address":"Calle de Paso (el), 4",
    "sg:city":"Almunia De Do\u00e7a Godina",
    "sg:orig_category":"Cajas De Ahorro",
    "sg:phone":"+34 976 60 08 84",
    "sg:postcode":"50100",
    "sg:province":"Zaragoza",
    "wof:name":"Caja De Ahorros Y Monte De Piedad De Zaragoza Aragon Y Rioja",
    "wof:placetype":"venue"
},
  "geometry": {"coordinates":[-1.3741810322,41.4756011963],"type":"Point"}
}