{
  "type": "Feature",
  "properties": {
    "iso:country":"ES",
    "sg:address":"Avda Torrelobaton, 10",
    "sg:city":"Tordesillas",
    "sg:orig_category":"Centros De Educaci\u00d3n Especial",
    "sg:phone":"+34 983 79 77 01",
    "sg:postcode":"47100",
    "sg:province":"Valladolid",
    "wof:name":"Colegio Publico Comarcal Pedro I",
    "wof:placetype":"venue"
},
  "geometry": {"coordinates":[-4.9976592064,41.5077362061],"type":"Point"}
}