{
  "type": "Feature",
  "properties": {
    "addr:full":"Ctra Ollauri, S/n Hormilla La Rioja 26223",
    "addr:housenumber":"s",
    "addr:postcode":"26223",
    "addr:street":"Ctra Ollauri;/ N Hormilla;Rioja",
    "iso:country":"ES",
    "sg:address":"Ctra Ollauri, S/n",
    "sg:city":"Hormilla",
    "sg:orig_category":"Forjas Y Altos Hornos",
    "sg:phone":"+34 941 41 78 46",
    "sg:postcode":"26223",
    "sg:province":"La Rioja",
    "wof:name":"Ezcurra Martinez Julian",
    "wof:placetype":"venue"
},
  "geometry": {"coordinates":[-2.7296469212,42.4551086426],"type":"Point"}
}