{
  "type": "Feature",
  "properties": {
    "iso:country":"ES",
    "sg:address":"Carrer de Xaloc, S/n",
    "sg:city":"Terrassa",
    "sg:orig_category":"Librer\u00cdas",
    "sg:phone":"+34 937 35 36 16",
    "sg:postcode":"08226",
    "sg:province":"Barcelona",
    "wof:name":"Martos Martos Dolores",
    "wof:placetype":"venue"
},
  "geometry": {"coordinates":[2.0185201168,41.578704834],"type":"Point"}
}