{
  "type": "Feature",
  "properties": {
    "addr:full":"Cami Valldeix (de), 28 Mataro Barcelona 08304",
    "addr:postcode":"08304",
    "addr:street":"Mataro Barcelona",
    "iso:country":"ES",
    "sg:address":"Cami Valldeix (de), 28",
    "sg:city":"Mataro",
    "sg:orig_category":"Reparaciones Y Remolcado De Veh\u00cdculos",
    "sg:phone":"+34 937 90 53 24",
    "sg:postcode":"08304",
    "sg:province":"Barcelona",
    "wof:name":"Gonzalez Contreras Jose",
    "wof:placetype":"venue"
},
  "geometry": {"coordinates":[2.4433119297,41.5697898865],"type":"Point"}
}