{
  "type": "Feature",
  "properties": {
    "addr:full":"Calle de Capitan Angosto Gomez Castrillon (del), 70 Aranjuez Madrid 28300",
    "addr:housenumber":"70",
    "addr:postcode":"28300",
    "addr:street":"Calle De Capitan Angosto Gomez Castrillon Del",
    "iso:country":"ES",
    "sg:address":"Calle de Capitan Angosto Gomez Castrillon (del), 70",
    "sg:city":"Aranjuez",
    "sg:orig_category":"Cl\u00cdnicas M\u00c9dicas",
    "sg:phone":"+34 918 92 44 35",
    "sg:postcode":"28300",
    "sg:province":"Madrid",
    "wof:name":"Hernandez Sanchez Maria Del Carmen",
    "wof:placetype":"venue"
},
  "geometry": {"coordinates":[-3.602009058,40.0329208374],"type":"Point"}
}