{
  "type": "Feature",
  "properties": {
    "iso:country":"ES",
    "sg:address":"Carr Antartida, De L', 16",
    "sg:city":"Mao",
    "sg:orig_category":"C\u00c1maras De Comercio E Industria, Oficios, Agricultura",
    "sg:phone":"+34 971 36 09 02",
    "sg:postcode":"07703",
    "sg:province":"Islas Baleares",
    "wof:name":"Vila Server Anunciado",
    "wof:placetype":"venue"
},
  "geometry": {"coordinates":[4.256811142,39.8789787292],"type":"Point"}
}