{
  "type": "Feature",
  "properties": {
    "iso:country":"ES",
    "sg:address":"Askain Karrika, 1",
    "sg:city":"Bera",
    "sg:orig_category":"Molduras, Junquillos, Listones Y Molduras Perforadas",
    "sg:phone":"+34 948 63 08 10",
    "sg:postcode":"31780",
    "sg:province":"Navarra",
    "wof:name":"Larrechea Ordoqui Miguel Maria",
    "wof:placetype":"venue"
},
  "geometry": {"coordinates":[-1.6859890223,43.2749252319],"type":"Point"}
}