{
  "type": "Feature",
  "properties": {
    "iso:country":"ES",
    "sg:address":"Calle de Ibaiondo Kalea, 5",
    "sg:city":"Tolosa",
    "sg:orig_category":"Asistencia Social",
    "sg:phone":"+34 943 67 42 98",
    "sg:postcode":"20400",
    "sg:province":"Guip\u00f9zcoa",
    "wof:name":"Atzegi Asociacion Guipuzcoana En Favor De Las Personas Con Deficiencia Mental",
    "wof:placetype":"venue"
},
  "geometry": {"coordinates":[-2.0789339542,43.1339912415],"type":"Point"}
}