{
  "type": "Feature",
  "properties": {
    "addr:full":"Calle de Ruamayor, 9 Santander Cantabria 39008",
    "addr:housenumber":"9",
    "addr:postcode":"39008",
    "addr:street":"Calle De Ruamayor",
    "iso:country":"ES",
    "sg:address":"Calle de Ruamayor, 9",
    "sg:city":"Santander",
    "sg:orig_category":"Inmobiliaria (agencias)",
    "sg:phone":"+34 942 21 22 56",
    "sg:postcode":"39008",
    "sg:province":"Cantabria",
    "wof:name":"Promociones Urdu\u00f1a S.l.",
    "wof:placetype":"venue"
},
  "geometry": {"coordinates":[-3.8093950748,43.4604721069],"type":"Point"}
}