{
  "type": "Feature",
  "properties": {
    "addr:full":"Calle de Juan Xxiii, 2 Tudela Duero Valladolid 47320",
    "addr:housenumber":"2;duero",
    "addr:postcode":"47320",
    "addr:street":"Calle De Juan Xxiii",
    "iso:country":"ES",
    "sg:address":"Calle de Juan Xxiii, 2",
    "sg:city":"Tudela Duero",
    "sg:orig_category":"Alimentaci\u00d3n General (al Por Menor)",
    "sg:phone":"+34 983 52 02 83",
    "sg:postcode":"47320",
    "sg:province":"Valladolid",
    "wof:name":"Roman Garcia Maria Victoria",
    "wof:placetype":"venue"
},
  "geometry": {"coordinates":[-4.5870938301,41.5858459473],"type":"Point"}
}