{
  "type": "Feature",
  "properties": {
    "addr:full":"Calle de Fray Luis De Leon, 23 Valladolid Valladolid 47002",
    "addr:housenumber":"23",
    "addr:postcode":"47002",
    "addr:street":"Calle De Fray Luis De Leon",
    "iso:country":"ES",
    "sg:address":"Calle de Fray Luis De Leon, 23",
    "sg:city":"Valladolid",
    "sg:orig_category":"Servidores Y Editores De Bases De Datos",
    "sg:phone":"+34 983 39 10 76",
    "sg:postcode":"47002",
    "sg:province":"Valladolid",
    "wof:name":"Martin Nu\u00f1ez Maria Isabel",
    "wof:placetype":"venue"
},
  "geometry": {"coordinates":[-4.7212948799,41.6505432129],"type":"Point"}
}