{
  "type": "Feature",
  "properties": {
    "iso:country":"ES",
    "sg:address":"Calle de Reforma, 5",
    "sg:city":"Valdepe\u00f1as",
    "sg:orig_category":"Estancos",
    "sg:phone":"+34 926 32 16 47",
    "sg:postcode":"13300",
    "sg:province":"Ciudad Real",
    "wof:name":"Lopez-tello Sanchez-molero Zacarias",
    "wof:placetype":"venue"
},
  "geometry": {"coordinates":[-3.3810009956,38.7606582642],"type":"Point"}
}