{
  "type": "Feature",
  "properties": {
    "addr:full":"Calle de Fuente Del Berro, 11 Madrid Madrid 28009",
    "addr:housenumber":"11",
    "addr:postcode":"madrid;28009",
    "addr:street":"Calle De Fuente Del Berro",
    "iso:country":"ES",
    "sg:address":"Calle de Fuente Del Berro, 11",
    "sg:city":"Madrid",
    "sg:orig_category":"Arquitectos",
    "sg:phone":"+34 914 02 89 39",
    "sg:postcode":"28009",
    "sg:province":"Madrid",
    "wof:name":"Castillejo Gomez Jorge",
    "wof:placetype":"venue"
},
  "geometry": {"coordinates":[-3.6706259251,40.4262580872],"type":"Point"}
}