{
  "type": "Feature",
  "properties": {
    "addr:full":"Calle de Angel Quintanilla Ulla, 2 Badajoz Badajoz 06011",
    "addr:housenumber":"2",
    "addr:postcode":"06011",
    "addr:street":"Calle De Angel Quintanilla Ulla",
    "iso:country":"ES",
    "sg:address":"Calle de Angel Quintanilla Ulla, 2",
    "sg:city":"Badajoz",
    "sg:orig_category":"Peluqueros: De Se\u00d1oras",
    "sg:phone":"+34 924 24 28 79",
    "sg:postcode":"06011",
    "sg:province":"Badajoz",
    "wof:name":"Campos Tejero Santos Felix",
    "wof:placetype":"venue"
},
  "geometry": {"coordinates":[-6.9880609512,38.8705177307],"type":"Point"}
}