{
  "type": "Feature",
  "properties": {
    "addr:full":"Calle de Saenz De Quejana, 21 Beas Segura Ja\u00e9n 23280",
    "addr:housenumber":"21",
    "addr:postcode":"23280",
    "addr:street":"Calle De Saenz De Quejana",
    "iso:country":"ES",
    "sg:address":"Calle de Saenz De Quejana, 21",
    "sg:city":"Beas Segura",
    "sg:orig_category":"Empresas De Carpinter\u00cda Met\u00c1lica",
    "sg:phone":"+34 953 42 48 53",
    "sg:postcode":"23280",
    "sg:province":"Ja\u00e9n",
    "wof:name":"Garrido Gonzalez Jacinta",
    "wof:placetype":"venue"
},
  "geometry": {"coordinates":[-2.8934121132,38.2544174194],"type":"Point"}
}