{
  "type": "Feature",
  "properties": {
    "addr:full":"Calle de Camino Viejo De Mirandilla, S/n Merida Badajoz 06800",
    "addr:housenumber":"s",
    "addr:postcode":"06800",
    "addr:street":"Calle De Camino Viejo De Mirandilla;/ N",
    "iso:country":"ES",
    "sg:address":"Calle de Camino Viejo De Mirandilla, S/n",
    "sg:city":"Merida",
    "sg:orig_category":"Alimentaci\u00d3n General (al Por Menor)",
    "sg:phone":"+34 924 30 16 57",
    "sg:postcode":"06800",
    "sg:province":"Badajoz",
    "wof:name":"Hermanos Sardi\u00f1a Cb",
    "wof:placetype":"venue"
},
  "geometry": {"coordinates":[-6.3651571274,38.9394264221],"type":"Point"}
}