{
  "type": "Feature",
  "properties": {
    "addr:full":"Calle de San Isidro, 19 Vinaros Castell\u00f3n 12500",
    "addr:housenumber":"19",
    "addr:postcode":"12500",
    "addr:street":"Calle De San Isidro",
    "iso:country":"ES",
    "sg:address":"Calle de San Isidro, 19",
    "sg:city":"Vinaros",
    "sg:orig_category":"Ropa Para Se\u00d1oras Y Caballeros (al Por Menor)",
    "sg:phone":"+34 964 40 79 78",
    "sg:postcode":"12500",
    "sg:province":"Castell\u00f3n",
    "wof:name":"Sabater Costarrosa Alicia",
    "wof:placetype":"venue"
},
  "geometry": {"coordinates":[0.4749450088,40.4711990356],"type":"Point"}
}