{
  "type": "Feature",
  "properties": {
    "addr:full":"Calle de Pozo (el), S/n San Cristobal De La Laguna Santa Cruz De Tenerife 38201",
    "addr:housenumber":"/ n",
    "addr:postcode":"38201",
    "addr:street":"Calle De Pozo El S",
    "iso:country":"ES",
    "sg:address":"Calle de Pozo (el), S/n",
    "sg:city":"San Cristobal De La Laguna",
    "sg:orig_category":"Pr\u00c9stamos Personales E Hipotecarios",
    "sg:phone":"+34 922 26 35 12",
    "sg:postcode":"38201",
    "sg:province":"Santa Cruz De Tenerife",
    "wof:name":"Linares-rivas Lalaguna Octavio",
    "wof:placetype":"venue"
},
  "geometry": {"coordinates":[-16.3218746185,28.491476059],"type":"Point"}
}