{
  "type": "Feature",
  "properties": {
    "iso:country":"ES",
    "sg:address":"Calle de Antonio De Cabezon, 17",
    "sg:city":"Madrid",
    "sg:orig_category":"Jefes De Obra Y Construcciones",
    "sg:phone":"+34 913 72 11 36",
    "sg:postcode":"28034",
    "sg:province":"Madrid",
    "wof:name":"Orfisa Ikc S.a.l. En Constitucion",
    "wof:placetype":"venue"
},
  "geometry": {"coordinates":[-3.6799311638,40.489276886],"type":"Point"}
}