{
  "type": "Feature",
  "properties": {
    "addr:full":"Carrer de Anselm Clave, 36 Granollers Barcelona 08400",
    "addr:housenumber":"36",
    "addr:postcode":"08400",
    "addr:street":"Carrer De Anselm Clave",
    "iso:country":"ES",
    "sg:address":"Carrer de Anselm Clave, 36",
    "sg:city":"Granollers",
    "sg:orig_category":"Librer\u00cdas",
    "sg:phone":"+34 935 10 65 08",
    "sg:postcode":"08400",
    "sg:province":"Barcelona",
    "wof:name":"L\u00d3pez S\u00c1nchez Crescencio",
    "wof:placetype":"venue"
},
  "geometry": {"coordinates":[2.2889099121,41.6079521179],"type":"Point"}
}