{
  "type": "Feature",
  "properties": {
    "iso:country":"ES",
    "sg:address":"Condado Lagar, 5",
    "sg:city":"Pobra Carami\u00f1al",
    "sg:orig_category":"Servidores Y Editores De Bases De Datos",
    "sg:phone":"+34 981 83 39 62",
    "sg:postcode":"15940",
    "sg:province":"La Coru\u00f1a",
    "wof:name":"El Muelle Servicios Hosting S.l.",
    "wof:placetype":"venue"
},
  "geometry": {"coordinates":[-8.9388437271,42.6042404175],"type":"Point"}
}