{
  "type": "Feature",
  "properties": {
    "iso:country":"ES",
    "sg:address":"Calle de San Antonio, 47",
    "sg:city":"Albacete",
    "sg:orig_category":"Asociaciones Humanitarias, De Cooperaci\u00d3n, De Acci\u00d3n Social",
    "sg:phone":"+34 967 21 70 09",
    "sg:postcode":"02001",
    "sg:province":"Albacete",
    "wof:name":"Asociacion Comision Catolica Espa\u00f1ola De Migracion",
    "wof:placetype":"venue"
},
  "geometry": {"coordinates":[-1.8531000614,38.9980545044],"type":"Point"}
}