{
  "type": "Feature",
  "properties": {
    "iso:country":"ES",
    "sg:address":"Calle de Ramiro De Maeztu, 37",
    "sg:city":"Almeria",
    "sg:orig_category":"Porcelanas, Azulejos (fabricaci\u00d3n, Al Por Mayor)",
    "sg:phone":"+34 950 14 53 25",
    "sg:postcode":"04009",
    "sg:province":"Almer\u00eda",
    "sg:website":"www.keraben.com",
    "wof:name":"Keraben Tiendas S.l.",
    "wof:placetype":"venue"
},
  "geometry": {"coordinates":[-2.4468390942,36.8471298218],"type":"Point"}
}