{
  "type": "Feature",
  "properties": {
    "iso:country":"ES",
    "sg:address":"Calle de Larga, 48",
    "sg:city":"Trebujena",
    "sg:orig_category":"Librer\u00cdas",
    "sg:phone":"+34 956 39 55 05",
    "sg:postcode":"11560",
    "sg:province":"C\u00e1diz",
    "wof:name":"Dianez Herrera Miguel",
    "wof:placetype":"venue"
},
  "geometry": {"coordinates":[-6.1743888855,36.8700027466],"type":"Point"}
}