{
  "type": "Feature",
  "properties": {
    "iso:country":"ES",
    "sg:address":"Calle de Cruces, 26",
    "sg:city":"Puertollano",
    "sg:orig_category":"Ense\u00d1anza, Formaci\u00d3n Profesional: Aprendizaje",
    "sg:phone":"+34 926 41 00 82",
    "sg:postcode":"13500",
    "sg:province":"Ciudad Real",
    "wof:name":"Direccion General De La Policia D.n.i.",
    "wof:placetype":"venue"
},
  "geometry": {"coordinates":[-4.111125946,38.689289093],"type":"Point"}
}