{
  "type": "Feature",
  "properties": {
    "iso:country":"ES",
    "sg:address":"Calle de Cruz De Salas, 9",
    "sg:city":"Borja",
    "sg:orig_category":"Comercio, Reparaci\u00d3n De Motocicletas, Bicicletas Y Piezas Sueltas",
    "sg:phone":"+34 976 85 28 00",
    "sg:postcode":"50540",
    "sg:province":"Zaragoza",
    "wof:name":"Motodimas S.c.",
    "wof:placetype":"venue"
},
  "geometry": {"coordinates":[-1.5332354307,41.830696106],"type":"Point"}
}