{
  "type": "Feature",
  "properties": {
    "iso:country":"ES",
    "sg:address":"Carr Calvario, 85",
    "sg:city":"Betera",
    "sg:orig_category":"Agencias Y Agentes Comerciales, Representantes",
    "sg:phone":"+34 961 60 12 63",
    "sg:postcode":"46117",
    "sg:province":"Valencia",
    "wof:name":"Ricart Ferrando Paloma",
    "wof:placetype":"venue"
},
  "geometry": {"coordinates":[-0.457118988,39.5894393921],"type":"Point"}
}