{
  "type": "Feature",
  "properties": {
    "addr:full":"Calle de Alzania, 1 Alsasua Navarra 31800",
    "addr:housenumber":"1",
    "addr:postcode":"31800",
    "addr:street":"Calle De Alzania",
    "iso:country":"ES",
    "sg:address":"Calle de Alzania, 1",
    "sg:city":"Alsasua",
    "sg:orig_category":"M\u00c9dicos: Estomatolog\u00cda",
    "sg:phone":"+34 948 46 82 32",
    "sg:postcode":"31800",
    "sg:province":"Navarra",
    "wof:name":"Vignolo Milazzo Gustavo Leopoldo",
    "wof:placetype":"venue"
},
  "geometry": {"coordinates":[-2.1705520153,42.8934020996],"type":"Point"}
}