{
  "type": "Feature",
  "properties": {
    "addr:full":"Calle de San Lorenzo, 28 Soria Soria 42002",
    "addr:housenumber":"28",
    "addr:postcode":"42002",
    "addr:street":"Calle De San Lorenzo",
    "iso:country":"ES",
    "sg:address":"Calle de San Lorenzo, 28",
    "sg:city":"Soria",
    "sg:orig_category":"Arquitectos",
    "sg:phone":"+34 975 23 00 43",
    "sg:postcode":"42002",
    "sg:province":"Soria",
    "wof:name":"Palomar Molina Javier Jose",
    "wof:placetype":"venue"
},
  "geometry": {"coordinates":[-2.4601709843,41.7641944885],"type":"Point"}
}