{
  "type": "Feature",
  "properties": {
    "iso:country":"ES",
    "sg:address":"Calle de San Quirico, 8",
    "sg:city":"Valdeolivas",
    "sg:orig_category":"Peluquer\u00cdas, Peluquer\u00cda Mixta",
    "sg:phone":"+34 969 31 70 90",
    "sg:postcode":"16813",
    "sg:province":"Cuenca",
    "wof:name":"Rebollo Lopez Sonia",
    "wof:placetype":"venue"
},
  "geometry": {"coordinates":[-2.4445340633,40.504776001],"type":"Point"}
}