{
  "type": "Feature",
  "properties": {
    "addr:full":"Avda Reyes De Espa\u00d1a, 26 Salamanca Salamanca 37008",
    "addr:housenumber":"26",
    "addr:postcode":"37008",
    "addr:street":"Avda Reyes De Espan\u0303A",
    "iso:country":"ES",
    "sg:address":"Avda Reyes De Espa\u00d1a, 26",
    "sg:city":"Salamanca",
    "sg:orig_category":"Estancos",
    "sg:phone":"+34 923 21 72 75",
    "sg:postcode":"37008",
    "sg:province":"Salamanca",
    "wof:name":"Hernandez Arias Jose",
    "wof:placetype":"venue"
},
  "geometry": {"coordinates":[-5.6654500961,40.9578170776],"type":"Point"}
}