{
  "type": "Feature",
  "properties": {
    "iso:country":"ES",
    "sg:address":"Calle de Martin Cortes, 18",
    "sg:city":"Zaragoza",
    "sg:orig_category":"Agencias Y Asesores De Publicidad",
    "sg:phone":"+34 976 46 73 13",
    "sg:postcode":"50005",
    "sg:province":"Zaragoza",
    "wof:name":"Imagen Comunicacion Y Marketing Empresarial S.l.",
    "wof:placetype":"venue"
},
  "geometry": {"coordinates":[-0.8995980024,41.648235321],"type":"Point"}
}