{
  "type": "Feature",
  "properties": {
    "iso:country":"ES",
    "sg:address":"Pase Estacion, 41",
    "sg:city":"Salamanca",
    "sg:orig_category":"Tintes (fabricaci\u00d3n, Al Por Mayor)",
    "sg:phone":"+34 923 25 82 76",
    "sg:postcode":"37004",
    "sg:province":"Salamanca",
    "wof:name":"Magisor Tintoreria S.l",
    "wof:placetype":"venue"
},
  "geometry": {"coordinates":[-5.6548891068,40.9698295593],"type":"Point"}
}