{
  "type": "Feature",
  "properties": {
    "iso:country":"ES",
    "sg:address":"Avda Elvas, S/n",
    "sg:city":"Badajoz",
    "sg:orig_category":"Ense\u00d1anza, Formaci\u00d3n Profesional: Aprendizaje",
    "sg:phone":"+34 924 27 21 21",
    "sg:postcode":"06006",
    "sg:province":"Badajoz",
    "sg:website":"www.unex.es",
    "wof:name":"Universidad De Extremadura",
    "wof:placetype":"venue"
},
  "geometry": {"coordinates":[-7.0134840012,38.8817253113],"type":"Point"}
}