{
  "type": "Feature",
  "properties": {
    "iso:country":"ES",
    "sg:address":"Calle de Franja, 2",
    "sg:city":"Coru\u00d1a",
    "sg:orig_category":"Cervecer\u00cdas",
    "sg:phone":"+34 981 22 57 13",
    "sg:postcode":"15001",
    "sg:province":"A Coru\u00f1a",
    "wof:name":"Satzler  Klaus Willi",
    "wof:placetype":"venue"
},
  "geometry": {"coordinates":[-8.3985471725,43.3706245422],"type":"Point"}
}