{
  "type": "Feature",
  "properties": {
    "addr:full":"Calle de Grande, 49 Quintanar Orden Toledo 45800",
    "addr:housenumber":"49",
    "addr:postcode":"45800",
    "addr:street":"Calle De Grande",
    "iso:country":"ES",
    "sg:address":"Calle de Grande, 49",
    "sg:city":"Quintanar Orden",
    "sg:orig_category":"Supermercados Y Hipermercados",
    "sg:phone":"+34 925 56 45 59",
    "sg:postcode":"45800",
    "sg:province":"Toledo",
    "sg:website":"www.mercadona.es",
    "wof:name":"Mercadona S.a.",
    "wof:placetype":"venue"
},
  "geometry": {"coordinates":[-3.0415759087,39.5940818787],"type":"Point"}
}