{
  "type": "Feature",
  "properties": {
    "iso:country":"ES",
    "sg:address":"Av Madrid, 142",
    "sg:city":"Barcelona",
    "sg:orig_category":"Electricidad: Equipos Industriales, Componentes (fabricaci\u00d3n)",
    "sg:phone":"+34 933 30 85 53",
    "sg:postcode":"08028",
    "sg:province":"Barcelona",
    "wof:name":"Electro-stocks Condal S.l.",
    "wof:placetype":"venue"
},
  "geometry": {"coordinates":[2.1302609444,41.3798027039],"type":"Point"}
}