{
  "type": "Feature",
  "properties": {
    "addr:full":"Calle de Padre Javier De Valladolid, 1 Le\u00f3n Le\u00f3n 24005",
    "addr:housenumber":"1",
    "addr:postcode":"24005",
    "addr:street":"Calle De Padre Javier De Valladolid;Leo\u0301N",
    "iso:country":"ES",
    "sg:address":"Calle de Padre Javier De Valladolid, 1",
    "sg:city":"Le\u00f3n",
    "sg:orig_category":"Asesor\u00cda Fiscal Y Jur\u00cddica",
    "sg:phone":"+34 987 26 31 22",
    "sg:postcode":"24005",
    "sg:province":"Le\u00f3n",
    "wof:name":"Gutierrez Alaiz Covadonga",
    "wof:placetype":"venue"
},
  "geometry": {"coordinates":[-5.5699782372,42.5923233032],"type":"Point"}
}