{
  "type": "Feature",
  "properties": {
    "addr:full":"Calle de Barquillas De Lope, S/n Cadiz C\u00e1diz 11002",
    "addr:housenumber":"/ n",
    "addr:postcode":"11002",
    "addr:street":"Calle De Barquillas De Lope S",
    "iso:country":"ES",
    "sg:address":"Calle de Barquillas De Lope, S/n",
    "sg:city":"Cadiz",
    "sg:orig_category":"Mec\u00c1nico Del Autom\u00d3vil",
    "sg:phone":"+34 956 21 35 91",
    "sg:postcode":"11002",
    "sg:province":"C\u00e1diz",
    "wof:name":"Sociedad Cooperativa Andaluza Autos El Balon",
    "wof:placetype":"venue"
},
  "geometry": {"coordinates":[-6.3037490845,36.532371521],"type":"Point"}
}