{
  "type": "Feature",
  "properties": {
    "iso:country":"ES",
    "sg:address":"Calle de Carmen, 17",
    "sg:city":"Madrid",
    "sg:orig_category":"Asesor\u00cda Fiscal Y Jur\u00cddica",
    "sg:phone":"+34 915 31 00 89",
    "sg:postcode":"28013",
    "sg:province":"Madrid",
    "wof:name":"Contera Y Sacristan S.l.",
    "wof:placetype":"venue"
},
  "geometry": {"coordinates":[-3.704366684,40.4183731079],"type":"Point"}
}