{
  "type": "Feature",
  "properties": {
    "iso:country":"ES",
    "sg:address":"Carrer de Joan Jorba, 2",
    "sg:city":"Manresa",
    "sg:orig_category":"Equipo De Refrigeraci\u00d3n Industrial",
    "sg:phone":"+34 938 77 16 20",
    "sg:postcode":"08241",
    "sg:province":"Barcelona",
    "wof:name":"Startfred S.l.",
    "wof:placetype":"venue"
},
  "geometry": {"coordinates":[1.8302999735,41.727935791],"type":"Point"}
}