{
  "type": "Feature",
  "properties": {
    "iso:country":"ES",
    "sg:address":"Carr Valencia, 48",
    "sg:city":"Picanya",
    "sg:orig_category":"Agentes, Concesionarios Y Sucursales De Veh\u00cdculos",
    "sg:phone":"+34 961 59 02 42",
    "sg:postcode":"46210",
    "sg:province":"Valencia",
    "wof:name":"Talleres Hermanos Rubio S.l.",
    "wof:placetype":"venue"
},
  "geometry": {"coordinates":[-0.4306640029,39.4387550354],"type":"Point"}
}