{
  "type": "Feature",
  "properties": {
    "iso:country":"ES",
    "sg:address":"Carrer de Numero 4 Zona Franca, 16",
    "sg:city":"Barcelona",
    "sg:orig_category":"Empresas De Limpieza",
    "sg:phone":"+34 934 13 65 95",
    "sg:postcode":"08...",
    "sg:province":"Barcelona",
    "wof:name":"Cespa Compa\u00d1ia De Servicios Publicos Auxiliares S.a.",
    "wof:placetype":"venue"
},
  "geometry": {"coordinates":[2.1354699135,41.328830719],"type":"Point"}
}