{
  "type": "Feature",
  "properties": {
    "iso:country":"ES",
    "sg:address":"Calle de Espoz Y Mina, 22",
    "sg:city":"Albacete",
    "sg:orig_category":"Ropa Para Se\u00d1oras Y Caballeros (al Por Menor)",
    "sg:phone":"+34 967 22 41 99",
    "sg:postcode":"02004",
    "sg:province":"Albacete",
    "wof:name":"Iba\u00f1ez Herrero Julio",
    "wof:placetype":"venue"
},
  "geometry": {"coordinates":[-1.8687399626,38.9942169189],"type":"Point"}
}