{
  "type": "Feature",
  "properties": {
    "iso:country":"ES",
    "sg:address":"Calle de Doctor Fleming, 39",
    "sg:city":"Madrid",
    "sg:orig_category":"Tintes (fabricaci\u00d3n, Al Por Mayor)",
    "sg:phone":"+34 913 59 10 83",
    "sg:postcode":"28036",
    "sg:province":"Madrid",
    "wof:name":"Tintorerias Amaya S. A.",
    "wof:placetype":"venue"
},
  "geometry": {"coordinates":[-3.6878156662,40.4620399475],"type":"Point"}
}