{
  "type": "Feature",
  "properties": {
    "addr:full":"Avda Aragon, 2 Valencia Valencia 46021",
    "addr:housenumber":"2",
    "addr:postcode":"46021",
    "addr:street":"Avda Aragon",
    "iso:country":"ES",
    "sg:address":"Avda Aragon, 2",
    "sg:city":"Valencia",
    "sg:orig_category":"Agentes, Concesionarios Y Sucursales De Veh\u00cdculos",
    "sg:phone":"+34 963 37 02 57",
    "sg:postcode":"46021",
    "sg:province":"Valencia",
    "wof:name":"Valley Motors S.a.",
    "wof:placetype":"venue"
},
  "geometry": {"coordinates":[-0.3600310087,39.4685974121],"type":"Point"}
}