{
  "type": "Feature",
  "properties": {
    "iso:country":"ES",
    "sg:address":"Plaz Barranco (del), 10",
    "sg:city":"Cullar",
    "sg:orig_category":"Molduras, Junquillos, Listones Y Molduras Perforadas",
    "sg:phone":"+34 958 73 07 71",
    "sg:postcode":"18850",
    "sg:province":"Granada",
    "wof:name":"Navarro Valdivieso Emilio",
    "wof:placetype":"venue"
},
  "geometry": {"coordinates":[-2.5727388859,37.5834617615],"type":"Point"}
}