{
  "type": "Feature",
  "properties": {
    "addr:full":"Avda Constitucion, 108 Cistierna Le\u00f3n 24800",
    "addr:housenumber":"108",
    "addr:postcode":"24800",
    "addr:street":"Avda Constitucion;Leo\u0301N",
    "iso:country":"ES",
    "sg:address":"Avda Constitucion, 108",
    "sg:city":"Cistierna",
    "sg:orig_category":"Bisuter\u00cda, Joyer\u00cda, Relojer\u00cda (al Por Menor)",
    "sg:phone":"+34 987 70 11 21",
    "sg:postcode":"24800",
    "sg:province":"Le\u00f3n",
    "wof:name":"Joyeria Jaime S.l.",
    "wof:placetype":"venue"
},
  "geometry": {"coordinates":[-5.1297702789,42.8072929382],"type":"Point"}
}