{
  "type": "Feature",
  "properties": {
    "iso:country":"ES",
    "sg:address":"Avda Juan Carlos I, 87",
    "sg:city":"Pedro Mu\u00e7oz",
    "sg:orig_category":"Fabricaci\u00d3n De Tapices Y Moquetas Para Suelos Y Paredes",
    "sg:phone":"+34 926 58 64 57",
    "sg:postcode":"13620",
    "sg:province":"Ciudad Real",
    "wof:name":"Gabriel Ortiz S.l.",
    "wof:placetype":"venue"
},
  "geometry": {"coordinates":[-2.9435389042,39.402015686],"type":"Point"}
}