{
  "type": "Feature",
  "properties": {
    "iso:country":"ES",
    "sg:address":"Calle de Alheli, 17",
    "sg:city":"Humanes De Madrid",
    "sg:orig_category":"Empresas De Carpinter\u00cda De Madera",
    "sg:phone":"+34 916 06 01 36",
    "sg:postcode":"28970",
    "sg:province":"Madrid",
    "wof:name":"Industrias Rubio Guzman S.l.",
    "wof:placetype":"venue"
},
  "geometry": {"coordinates":[-3.8347480297,40.2682876587],"type":"Point"}
}