{
  "type": "Feature",
  "properties": {
    "addr:full":"Calle de Augusto Junquera, 19 Oviedo Asturias 33012",
    "addr:housenumber":"19",
    "addr:postcode":"33012",
    "addr:street":"Calle De Augusto Junquera",
    "iso:country":"ES",
    "sg:address":"Calle de Augusto Junquera, 19",
    "sg:city":"Oviedo",
    "sg:orig_category":"Fabricaci\u00d3n De Peines Y De Accesorios De Peluquer\u00cda",
    "sg:phone":"+34 985 11 06 82",
    "sg:postcode":"33012",
    "sg:province":"Asturias",
    "wof:name":"Sanz-abarrio Distribuciones S.l.",
    "wof:placetype":"venue"
},
  "geometry": {"coordinates":[-5.8538799286,43.3704223633],"type":"Point"}
}