{
  "type": "Feature",
  "properties": {
    "iso:country":"ES",
    "sg:address":"Av Madrid, 153",
    "sg:city":"Barcelona",
    "sg:orig_category":"Asesor\u00cda Sobre Comunicaci\u00d3n De Empresas",
    "sg:phone":"+34 934 11 05 17",
    "sg:postcode":"08028",
    "sg:province":"Barcelona",
    "wof:name":"Serge Gabinet Tecnic S.l.",
    "wof:placetype":"venue"
},
  "geometry": {"coordinates":[2.1313118935,41.380607605],"type":"Point"}
}