{
  "type": "Feature",
  "properties": {
    "iso:country":"ES",
    "sg:address":"Avda Suspiro Del Moro, 2",
    "sg:city":"Otura",
    "sg:orig_category":"Caf\u00c9s, Bares, Cervecer\u00cdas",
    "sg:phone":"+34 958 55 50 93",
    "sg:postcode":"18630",
    "sg:province":"Granada",
    "wof:name":"Compa\u00f1ia Granadina De Telefonos A Monedas S.l.",
    "wof:placetype":"venue"
},
  "geometry": {"coordinates":[-3.6352438927,37.0911598206],"type":"Point"}
}