{
  "type": "Feature",
  "properties": {
    "iso:country":"ES",
    "sg:address":"Calle de Nuria, 93",
    "sg:city":"Madrid",
    "sg:orig_category":"Asesor\u00cda Sobre Comunicaci\u00d3n De Empresas",
    "sg:phone":"+34 917 35 18 05",
    "sg:postcode":"28034",
    "sg:province":"Madrid",
    "wof:name":"Coello Gomez Jose Luis",
    "wof:placetype":"venue"
},
  "geometry": {"coordinates":[-3.7134718895,40.496181488],"type":"Point"}
}