{
  "type": "Feature",
  "properties": {
    "iso:country":"ES",
    "sg:address":"Plaz Pintor Amalio Garcia Del Moral, 6",
    "sg:city":"Sevilla",
    "sg:orig_category":"Abogados Especialistas En Derecho Fiscal",
    "sg:phone":"+34 954 64 81 18",
    "sg:postcode":"41005",
    "sg:province":"Sevilla",
    "wof:name":"Abogado Contable Y Asociados S.l.",
    "wof:placetype":"venue"
},
  "geometry": {"coordinates":[-5.964754,37.379311],"type":"Point"}
}