{
  "type": "Feature",
  "properties": {
    "iso:country":"ES",
    "sg:address":"Pase Sixto Celorrio, 22",
    "sg:city":"Calatayud",
    "sg:orig_category":"Muebles, Minoristas",
    "sg:phone":"+34 976 88 20 16",
    "sg:postcode":"50300",
    "sg:province":"Zaragoza",
    "wof:name":"Rodriguez Gutierrez Teofilo",
    "wof:placetype":"venue"
},
  "geometry": {"coordinates":[-1.6426689625,41.349609375],"type":"Point"}
}