{
  "type": "Feature",
  "properties": {
    "iso:country":"ES",
    "sg:address":"Avda Rosalia De Castro, 35",
    "sg:city":"Santa Uxia De Ribeira",
    "sg:orig_category":"Frutas, Legumbres Frescas Y Tempranas (al Por Menor)",
    "sg:phone":"+34 981 87 09 28",
    "sg:postcode":"15960",
    "sg:province":"La Coru\u00f1a",
    "wof:name":"Frucogal Frutera Comercial Gallega S.l.",
    "wof:placetype":"venue"
},
  "geometry": {"coordinates":[-8.9932422638,42.5544548035],"type":"Point"}
}