{
  "type": "Feature",
  "properties": {
    "iso:country":"ES",
    "sg:address":"Afores, S/n",
    "sg:city":"Roquetes",
    "sg:orig_category":"Industria Qu\u00cdmica",
    "sg:phone":"+34 977 50 07 08",
    "sg:postcode":"43520",
    "sg:province":"Tarragona",
    "wof:name":"Rosello-figueras Y Accensi Jose Maria",
    "wof:placetype":"venue"
},
  "geometry": {"coordinates":[0.5002449751,40.8249855042],"type":"Point"}
}