{
  "type": "Feature",
  "properties": {
    "iso:country":"ES",
    "sg:address":"Avda Jose Antonio Tavio, S/n",
    "sg:city":"Costa Del Silencio",
    "sg:orig_category":"Peluquer\u00cdas, Peluquer\u00cda Mixta",
    "sg:phone":"+34 922 78 54 76",
    "sg:postcode":"38630",
    "sg:province":"Santa Cruz De Tenerife",
    "wof:name":"Young  Lisa Valerie",
    "wof:placetype":"venue"
},
  "geometry": {"coordinates":[-16.6469402313,28.0121498108],"type":"Point"}
}