{
  "type": "Feature",
  "properties": {
    "iso:country":"ES",
    "sg:address":"Disem. Pantano De Alcora, 43",
    "sg:city":"Alcora",
    "sg:orig_category":"Serigraf\u00cda (material Y Suministros)",
    "sg:phone":"+34 964 36 16 32",
    "sg:postcode":"12110",
    "sg:province":"Castell\u00f3n",
    "wof:name":"De Renovales Ramon Ignacio",
    "wof:placetype":"venue"
},
  "geometry": {"coordinates":[-0.2178789973,40.0734786987],"type":"Point"}
}