{
  "type": "Feature",
  "properties": {
    "iso:country":"ES",
    "sg:address":"Avda Sur (del), 56",
    "sg:city":"Granada",
    "sg:orig_category":"Ense\u00d1ante, Direcci\u00d3n",
    "sg:phone":"+34 958 27 43 90",
    "sg:postcode":"18014",
    "sg:province":"Granada",
    "wof:name":"Morales Calvo Gregorio",
    "wof:placetype":"venue"
},
  "geometry": {"coordinates":[-3.613697052,37.1881332397],"type":"Point"}
}