{
  "type": "Feature",
  "properties": {
    "addr:full":"Avda Iparralde, 7 Irun Guip\u00f9zcoa 20304",
    "addr:housenumber":"7",
    "addr:postcode":"20304",
    "addr:street":"Avda Iparralde;Guipu\u0300Zcoa",
    "iso:country":"ES",
    "sg:address":"Avda Iparralde, 7",
    "sg:city":"Irun",
    "sg:orig_category":"Carnicer\u00cdas, Carnicer\u00cdas",
    "sg:phone":"+34 943 62 45 71",
    "sg:postcode":"20304",
    "sg:province":"Guip\u00f9zcoa",
    "wof:name":"Alberdi Arruabarrena Maria Del Carmen",
    "wof:placetype":"venue"
},
  "geometry": {"coordinates":[-1.7877639532,43.3457183838],"type":"Point"}
}