{
  "type": "Feature",
  "properties": {
    "addr:full":"Cno. Carril, S/n Elda Alicante 03600",
    "addr:postcode":"03600",
    "addr:street":"Carril S / N",
    "iso:country":"ES",
    "sg:address":"Cno. Carril, S/n",
    "sg:city":"Elda",
    "sg:orig_category":"Farmacias",
    "sg:phone":"+34 965 38 38 14",
    "sg:postcode":"03600",
    "sg:province":"Alicante",
    "wof:name":"Arce Amat Gabriel",
    "wof:placetype":"venue"
},
  "geometry": {"coordinates":[-0.7878531218,38.4597129822],"type":"Point"}
}