{
  "type": "Feature",
  "properties": {
    "iso:country":"ES",
    "sg:address":"Calle de Constitucion (de La), 36",
    "sg:city":"Alcobendas",
    "sg:orig_category":"Bisuter\u00cda, Joyer\u00cda, Relojer\u00cda (al Por Menor)",
    "sg:phone":"+34 916 53 73 38",
    "sg:postcode":"28100",
    "sg:province":"Madrid",
    "wof:name":"Isidro Baena Ana Belen",
    "wof:placetype":"venue"
},
  "geometry": {"coordinates":[-3.6363739967,40.5423965454],"type":"Point"}
}