{
  "type": "Feature",
  "properties": {
    "addr:full":"Carrer de Gremi De Boneters, 37 Poligon Industrial De Son Castello Islas Baleares 07009",
    "addr:housenumber":"37",
    "addr:postcode":"07009",
    "addr:street":"Carrer De Gremi De Boneters;Islas",
    "iso:country":"ES",
    "sg:address":"Carrer de Gremi De Boneters, 37",
    "sg:city":"Poligon Industrial De Son Castello",
    "sg:orig_category":"Construcciones Met\u00c1licas",
    "sg:phone":"+34 971 43 09 48",
    "sg:postcode":"07009",
    "sg:province":"Islas Baleares",
    "wof:name":"Estructuras Metalicas Ca\u00f1ellas S.l.",
    "wof:placetype":"venue"
},
  "geometry": {"coordinates":[2.6776249409,39.6072845459],"type":"Point"}
}