{
  "type": "Feature",
  "properties": {
    "iso:country":"ES",
    "sg:address":"Luga Finca Fuente Pizarro, S/n",
    "sg:city":"Collado Villalba",
    "sg:orig_category":"Industria Qu\u00cdmica",
    "sg:phone":"+34 918 50 06 17",
    "sg:postcode":"28400",
    "sg:province":"Madrid",
    "wof:name":"Vacas Rodriguez Luis Antonio",
    "wof:placetype":"venue"
},
  "geometry": {"coordinates":[-3.9848558903,40.6366844177],"type":"Point"}
}