{
  "type": "Feature",
  "properties": {
    "iso:country":"ES",
    "sg:address":"Calle de Sevilla, 19",
    "sg:city":"Malaga",
    "sg:orig_category":"Art\u00cdculos De Regalo (al Por Menor)",
    "sg:phone":"+34 952 61 12 26",
    "sg:postcode":"29009",
    "sg:province":"M\u00e1laga",
    "wof:name":"Morales Samper Amelia",
    "wof:placetype":"venue"
},
  "geometry": {"coordinates":[-4.4296441078,36.7253303528],"type":"Point"}
}