{
  "type": "Feature",
  "properties": {
    "addr:full":"Calle de Monse\u00d1or Martinez Somalo, 9 Ba\u00e7os De Rio Tobia La Rioja 26320",
    "addr:housenumber":"9",
    "addr:postcode":"26320",
    "addr:street":"Calle De Monsen\u0303Or;Somalo;Tobia;Rioja",
    "iso:country":"ES",
    "sg:address":"Calle de Monse\u00d1or Martinez Somalo, 9",
    "sg:city":"Ba\u00e7os De Rio Tobia",
    "sg:orig_category":"Contenedores (mercanc\u00cdas)",
    "sg:phone":"+34 941 37 42 71",
    "sg:postcode":"26320",
    "sg:province":"La Rioja",
    "wof:name":"Torre Perez Primo De",
    "wof:placetype":"venue"
},
  "geometry": {"coordinates":[-2.758234024,42.3322563171],"type":"Point"}
}