{
  "type": "Feature",
  "properties": {
    "addr:full":"Calle de Mayor, S/n Artieda Zaragoza 50683",
    "addr:housenumber":"s / n",
    "addr:postcode":"50683",
    "addr:street":"Calle De Mayor;Artieda",
    "iso:country":"ES",
    "sg:address":"Calle de Mayor, S/n",
    "sg:city":"Artieda",
    "sg:orig_category":"Agricultores, Agricultores",
    "sg:phone":"+34 948 43 93 02",
    "sg:postcode":"50683",
    "sg:province":"Zaragoza",
    "wof:name":"Sociedad Agraria De Transformacion N-631 La Parra",
    "wof:placetype":"venue"
},
  "geometry": {"coordinates":[-0.9835519791,42.5864982605],"type":"Point"}
}