{
  "type": "Feature",
  "properties": {
    "addr:full":"Calle de Manuel Maria De Arjona, 2 Cordoba C\u00f3rdoba 14001",
    "addr:housenumber":"2",
    "addr:postcode":"14001",
    "addr:street":"Calle De Manuel Maria De Arjona;Co\u0301Rdoba",
    "iso:country":"ES",
    "sg:address":"Calle de Manuel Maria De Arjona, 2",
    "sg:city":"Cordoba",
    "sg:orig_category":"Arquitectos",
    "sg:phone":"+34 957 48 43 41",
    "sg:postcode":"14001",
    "sg:province":"C\u00f3rdoba",
    "wof:name":"Fernandez Requena Rafael",
    "wof:placetype":"venue"
},
  "geometry": {"coordinates":[-4.77957201,37.8883056641],"type":"Point"}
}