{
  "type": "Feature",
  "properties": {
    "addr:full":"Urb Puerto Caleta, 16 Caleta Velez M\u00e1laga 29751",
    "addr:housenumber":"16",
    "addr:postcode":"29751",
    "addr:street":"Urb Puerto Caleta;Ma\u0301Laga",
    "iso:country":"ES",
    "sg:address":"Urb Puerto Caleta, 16",
    "sg:city":"Caleta Velez",
    "sg:orig_category":"Distribuci\u00d3n De Petr\u00d3leo Y Derivados",
    "sg:phone":"+34 952 55 05 76",
    "sg:postcode":"29751",
    "sg:province":"M\u00e1laga",
    "wof:name":"Pescados Costa Del Sol S.l.",
    "wof:placetype":"venue"
},
  "geometry": {"coordinates":[-4.0726838112,36.7514686584],"type":"Point"}
}