{
  "type": "Feature",
  "properties": {
    "iso:country":"ES",
    "sg:address":"Calle de Corredera (la), 50",
    "sg:city":"Montilla",
    "sg:orig_category":"Formaci\u00d3n Continuada (variada)",
    "sg:phone":"+34 957 65 09 26",
    "sg:postcode":"14550",
    "sg:province":"C\u00f3rdoba",
    "wof:name":"Pino Asesoria S.l.",
    "wof:placetype":"venue"
},
  "geometry": {"coordinates":[-4.6387248039,37.5883483887],"type":"Point"}
}