{
  "type": "Feature",
  "properties": {
    "addr:full":"Calle de Doctor Serrano, 5 Valencia Valencia 46006",
    "addr:housenumber":"5",
    "addr:postcode":"46006",
    "addr:street":"Calle De Doctor Serrano",
    "iso:country":"ES",
    "sg:address":"Calle de Doctor Serrano, 5",
    "sg:city":"Valencia",
    "sg:orig_category":"Bisuter\u00cda, Joyer\u00cda, Relojer\u00cda (al Por Menor)",
    "sg:phone":"+34 963 73 73 45",
    "sg:postcode":"46006",
    "sg:province":"Valencia",
    "wof:name":"Perez Ruiz Andres",
    "wof:placetype":"venue"
},
  "geometry": {"coordinates":[0.0627529025,38.8276901245],"type":"Point"}
}