{
  "type": "Feature",
  "properties": {
    "iso:country":"ES",
    "sg:address":"Carrer de Francesc Sancho, 2",
    "sg:city":"Palma",
    "sg:orig_category":"Arquitectos",
    "sg:phone":"+34 971 75 49 05",
    "sg:postcode":"07004",
    "sg:province":"Islas Baleares",
    "wof:name":"Cirerol Ferrer Pedro",
    "wof:placetype":"venue"
},
  "geometry": {"coordinates":[2.6573500633,39.5795097351],"type":"Point"}
}