{
  "type": "Feature",
  "properties": {
    "iso:country":"ES",
    "sg:address":"Carrer de Vilamirosa, 24",
    "sg:city":"Manlleu",
    "sg:orig_category":"Institutos De Belleza",
    "sg:phone":"+34 938 51 43 27",
    "sg:postcode":"08560",
    "sg:province":"Barcelona",
    "wof:name":"Gorchs Prats Esther",
    "wof:placetype":"venue"
},
  "geometry": {"coordinates":[2.2796199322,42.0015411377],"type":"Point"}
}