{
  "type": "Feature",
  "properties": {
    "addr:full":"Calle de Luis Chamizo, 23 Guare\u00f1a Badajoz 06470",
    "addr:housenumber":"23",
    "addr:postcode":"06470",
    "addr:street":"Calle De Luis Chamizo",
    "iso:country":"ES",
    "sg:address":"Calle de Luis Chamizo, 23",
    "sg:city":"Guare\u00f1a",
    "sg:orig_category":"Alimentaci\u00d3n General (al Por Menor)",
    "sg:phone":"+34 924 35 09 85",
    "sg:postcode":"06470",
    "sg:province":"Badajoz",
    "wof:name":"Superalvarez C.l.",
    "wof:placetype":"venue"
},
  "geometry": {"coordinates":[-6.0999522209,38.8586387634],"type":"Point"}
}