{
  "type": "Feature",
  "properties": {
    "addr:full":"Calle de Gardenia, 16 Alcala Henares Madrid 28803",
    "addr:housenumber":"16",
    "addr:postcode":"28803",
    "addr:street":"Calle De Gardenia",
    "iso:country":"ES",
    "sg:address":"Calle de Gardenia, 16",
    "sg:city":"Alcala Henares",
    "sg:orig_category":"Asociaciones, Organismos Culturales Y Socioeducativos",
    "sg:phone":"+34 918 83 68 56",
    "sg:postcode":"28803",
    "sg:province":"Madrid",
    "wof:name":"Club De Pensionistas Y Jubilados Reyes Catolicos",
    "wof:placetype":"venue"
},
  "geometry": {"coordinates":[-3.3725891113,40.4741744995],"type":"Point"}
}