{
  "type": "Feature",
  "properties": {
    "iso:country":"ES",
    "sg:address":"Alqueria Del Gordo, S/n",
    "sg:city":"Benifaraig",
    "sg:orig_category":"Aguas (distribuci\u00d3n, Servicios)",
    "sg:phone":"+34 963 90 26 36",
    "sg:postcode":"46016",
    "sg:province":"Valencia",
    "wof:name":"Cooperativa Valenciana Limitada De Consumo Llosetes",
    "wof:placetype":"venue"
},
  "geometry": {"coordinates":[-0.3847639859,39.530330658],"type":"Point"}
}