{
  "type": "Feature",
  "properties": {
    "iso:country":"ES",
    "sg:address":"Avda Castros (los), 57",
    "sg:city":"Santander",
    "sg:orig_category":"M\u00c1quinas De Escribir, M\u00c1quinas De Oficina (al Por Menor, Reparaci\u00d3n)",
    "sg:phone":"+34 942 21 40 15",
    "sg:postcode":"39005",
    "sg:province":"Cantabria",
    "wof:name":"Rodriguez De Pablo Juan Jose",
    "wof:placetype":"venue"
},
  "geometry": {"coordinates":[-3.8022110462,43.4704551697],"type":"Point"}
}