{
  "type": "Feature",
  "properties": {
    "addr:full":"Calle de Portugalete (de), 43 Pozuelo De Alarcon Madrid 28223",
    "addr:housenumber":"43",
    "addr:postcode":"28223",
    "addr:street":"Calle De Portugalete De",
    "iso:country":"ES",
    "sg:address":"Calle de Portugalete (de), 43",
    "sg:city":"Pozuelo De Alarcon",
    "sg:orig_category":"Asesor\u00cdas Y Estudios Financieros",
    "sg:phone":"+34 913 52 17 72",
    "sg:postcode":"28223",
    "sg:province":"Madrid",
    "wof:name":"Martinez-aldama Martinez Primitivo",
    "wof:placetype":"venue"
},
  "geometry": {"coordinates":[-3.8118610382,40.4394454956],"type":"Point"}
}