{
  "type": "Feature",
  "properties": {
    "addr:full":"Calle de Samaria, 8 Madrid Madrid 28009",
    "addr:housenumber":"8",
    "addr:postcode":"madrid;28009",
    "addr:street":"Calle De Samaria",
    "iso:country":"ES",
    "sg:address":"Calle de Samaria, 8",
    "sg:city":"Madrid",
    "sg:orig_category":"Artes: Servicios En General",
    "sg:phone":"+34 915 73 72 16",
    "sg:postcode":"28009",
    "sg:province":"Madrid",
    "wof:name":"Aken Arte S.l.",
    "wof:placetype":"venue"
},
  "geometry": {"coordinates":[-3.6724879742,40.4127845764],"type":"Point"}
}