{
  "type": "Feature",
  "properties": {
    "addr:full":"Carr Jaume I, 35 S. Francesc Formentera Islas Baleares 07860",
    "addr:housenumber":"35",
    "addr:postcode":"07860",
    "addr:street":"Carr Jaume I;S. Francesc",
    "iso:country":"ES",
    "sg:address":"Carr Jaume I, 35",
    "sg:city":"S. Francesc Formentera",
    "sg:orig_category":"Cajas De Ahorro",
    "sg:phone":"+34 971 32 21 59",
    "sg:postcode":"07860",
    "sg:province":"Islas Baleares",
    "wof:name":"Caixa D'estalvis I Pensions De Barcelona",
    "wof:placetype":"venue"
},
  "geometry": {"coordinates":[1.4309200048,38.7072410583],"type":"Point"}
}