{
  "type": "Feature",
  "properties": {
    "addr:full":"Pla\u00c7 Pax, 2 Felanitx Islas Baleares 07200",
    "addr:housenumber":"2",
    "addr:postcode":"07200",
    "addr:street":"Pax",
    "iso:country":"ES",
    "sg:address":"Pla\u00c7 Pax, 2",
    "sg:city":"Felanitx",
    "sg:orig_category":"Producci\u00d3n, Distribuci\u00d3n De Gas Butano Y Propano",
    "sg:phone":"+34 971 58 08 77",
    "sg:postcode":"07200",
    "sg:province":"Islas Baleares",
    "wof:name":"Marimon Piza Bernardo",
    "wof:placetype":"venue"
},
  "geometry": {"coordinates":[3.1485040188,39.469543457],"type":"Point"}
}