{
  "type": "Feature",
  "properties": {
    "addr:full":"Calle de Simon Hernandez (de), 53 Mostoles Madrid 28936",
    "addr:housenumber":"53",
    "addr:postcode":"28936",
    "addr:street":"Calle De Simon Hernandez De",
    "iso:country":"ES",
    "sg:address":"Calle de Simon Hernandez (de), 53",
    "sg:city":"Mostoles",
    "sg:orig_category":"Lencer\u00cda Femenina, Corseter\u00cda, Trajes De Ba\u00d1o (al Por Menor)",
    "sg:phone":"+34 916 46 91 11",
    "sg:postcode":"28936",
    "sg:province":"Madrid",
    "wof:name":"Villatoro Arquero Dolores",
    "wof:placetype":"venue"
},
  "geometry": {"coordinates":[-3.8527541161,40.3186073303],"type":"Point"}
}