{
  "type": "Feature",
  "properties": {
    "addr:full":"Avda Arboleda (de La), 5 Escorial Madrid 28280",
    "addr:housenumber":"5",
    "addr:postcode":"28280",
    "addr:street":"Avda Arboleda De La",
    "iso:country":"ES",
    "sg:address":"Avda Arboleda (de La), 5",
    "sg:city":"Escorial",
    "sg:orig_category":"Serigraf\u00cda (material Y Suministros)",
    "sg:phone":"+34 918 96 11 34",
    "sg:postcode":"28280",
    "sg:province":"Madrid",
    "wof:name":"Martin Blanco Jose Andres",
    "wof:placetype":"venue"
},
  "geometry": {"coordinates":[-4.1293392181,40.5837173462],"type":"Point"}
}