{
  "type": "Feature",
  "properties": {
    "addr:full":"Itturrin, 9 Lezo Guip\u00f9zcoa 20100",
    "addr:housenumber":"9",
    "addr:postcode":"20100",
    "addr:street":"Itturrin;Guipu\u0300Zcoa",
    "iso:country":"ES",
    "sg:address":"Itturrin, 9",
    "sg:city":"Lezo",
    "sg:orig_category":"Maquinaria Para Industrias Diversas",
    "sg:phone":"+34 943 49 45 38",
    "sg:postcode":"20100",
    "sg:province":"Guip\u00f9zcoa",
    "wof:name":"Mecanizados Bado S.a.l.",
    "wof:placetype":"venue"
},
  "geometry": {"coordinates":[-1.8686239719,43.3229179382],"type":"Point"}
}