{
  "type": "Feature",
  "properties": {
    "addr:full":"Ctra. General, 41 Valle S. Lorenzo Santa Cruz De Tenerife 38626",
    "addr:housenumber":"41",
    "addr:postcode":"38626",
    "addr:street":"Ctra. General;S. Lorenzo",
    "iso:country":"ES",
    "sg:address":"Ctra. General, 41",
    "sg:city":"Valle S. Lorenzo",
    "sg:orig_category":"Quincaller\u00cda (al Por Menor)",
    "sg:phone":"+34 922 76 60 89",
    "sg:postcode":"38626",
    "sg:province":"Santa Cruz De Tenerife",
    "wof:name":"Arteaga Mora Felix",
    "wof:placetype":"venue"
},
  "geometry": {"coordinates":[-16.6717090607,28.1179447174],"type":"Point"}
}