{
  "type": "Feature",
  "properties": {
    "iso:country":"ES",
    "sg:address":"C/ Puig Del Anar, 20",
    "sg:city":"Son Macia",
    "sg:orig_category":"Alimentaci\u00d3n General (al Por Mayor)",
    "sg:phone":"+34 971 84 42 91",
    "sg:postcode":"07509",
    "sg:province":"Islas Baleares",
    "wof:name":"Sureda Fons Y Otros Cdad",
    "wof:placetype":"venue"
},
  "geometry": {"coordinates":[3.2165999413,39.5135307312],"type":"Point"}
}