{
  "type": "Feature",
  "properties": {
    "iso:country":"ES",
    "sg:address":"Carrer de Enten\u00c7a, 162",
    "sg:city":"Barcelona",
    "sg:orig_category":"Carnicer\u00cdas, Carnicer\u00cdas",
    "sg:phone":"+34 934 30 15 27",
    "sg:postcode":"08029",
    "sg:province":"Barcelona",
    "wof:name":"Balasch",
    "wof:placetype":"venue"
},
  "geometry": {"coordinates":[2.1458466053,41.3832359314],"type":"Point"}
}