{
  "type": "Feature",
  "properties": {
    "iso:country":"ES",
    "sg:address":"Carrer de L'agricultura, 250",
    "sg:city":"Barcelona",
    "sg:orig_category":"Alimentaci\u00d3n General (al Por Menor)",
    "sg:phone":"+34 933 14 70 59",
    "sg:postcode":"08020",
    "sg:province":"Barcelona",
    "wof:name":"Tena Subira Ramon",
    "wof:placetype":"venue"
},
  "geometry": {"coordinates":[2.2010064125,41.4183502197],"type":"Point"}
}