{
  "type": "Feature",
  "properties": {
    "addr:full":"Calle de Infantes, 20 Ronda M\u00e1laga 29400",
    "addr:housenumber":"20",
    "addr:postcode":"29400",
    "addr:street":"Calle De Infantes;Ronda Ma\u0301Laga",
    "iso:country":"ES",
    "sg:address":"Calle de Infantes, 20",
    "sg:city":"Ronda",
    "sg:orig_category":"Transportes Ferroviarios",
    "sg:phone":"+34 952 87 16 62",
    "sg:postcode":"29400",
    "sg:province":"M\u00e1laga",
    "wof:name":"Moreno Chantar Maria Auxiliadora",
    "wof:placetype":"venue"
},
  "geometry": {"coordinates":[-5.1637630463,36.7449035645],"type":"Point"}
}