{
  "type": "Feature",
  "properties": {
    "iso:country":"ES",
    "sg:address":"Calle de San Juan, 25",
    "sg:city":"Gernika-lumo",
    "sg:orig_category":"Agentes Generales De Seguros",
    "sg:phone":"+34 946 25 44 50",
    "sg:postcode":"48300",
    "sg:province":"Vizcaya",
    "wof:name":"Gondra Salcines Elkarkideak S.l.",
    "wof:placetype":"venue"
},
  "geometry": {"coordinates":[-2.6769061089,43.3167457581],"type":"Point"}
}