{
  "type": "Feature",
  "properties": {
    "iso:country":"ES",
    "sg:address":"La Gerra, S/n",
    "sg:city":"Sierrapando",
    "sg:orig_category":"Empresarios",
    "sg:phone":"+34 942 80 35 78",
    "sg:postcode":"39317",
    "sg:province":"Cantabria",
    "wof:name":"Antonio Sangiao S.l.",
    "wof:placetype":"venue"
},
  "geometry": {"coordinates":[-4.0345673561,43.3432006836],"type":"Point"}
}