{
  "type": "Feature",
  "properties": {
    "iso:country":"ES",
    "sg:address":"Calle de Alejo Carpentier, 2",
    "sg:city":"Maracena",
    "sg:orig_category":"Ingeniero",
    "sg:phone":"+34 958 41 52 37",
    "sg:postcode":"18200",
    "sg:province":"Granada",
    "wof:name":"Jimena Molina Miguel Angel",
    "wof:placetype":"venue"
},
  "geometry": {"coordinates":[-3.6303713322,37.2094726562],"type":"Point"}
}