{
  "type": "Feature",
  "properties": {
    "addr:full":"Carr Solarium, 20 Palafrugell Girona 17200",
    "addr:housenumber":"20",
    "addr:postcode":"17200",
    "addr:street":"Carr Solarium",
    "iso:country":"ES",
    "sg:address":"Carr Solarium, 20",
    "sg:city":"Palafrugell",
    "sg:orig_category":"Promotores Constructores",
    "sg:phone":"+34 972 30 04 54",
    "sg:postcode":"17200",
    "sg:province":"Girona",
    "wof:name":"Enadobra S.l.",
    "wof:placetype":"venue"
},
  "geometry": {"coordinates":[3.1681909561,41.9184608459],"type":"Point"}
}