{
  "type": "Feature",
  "properties": {
    "addr:full":"Calle de Hospital, 8 Consuegra Toledo 45700",
    "addr:housenumber":"8",
    "addr:postcode":"45700",
    "addr:street":"Calle De Hospital",
    "iso:country":"ES",
    "sg:address":"Calle de Hospital, 8",
    "sg:city":"Consuegra",
    "sg:classifiers":[
        {
            "category":"Personal",
            "subcategory":"Barber",
            "type":"Services"
        }
    ],
    "sg:phone":"+34 925 48 12 60",
    "sg:postcode":"45700",
    "sg:province":"Toledo",
    "sg:tags":[
        "caballeros",
        "de",
        "peluqueros"
    ],
    "wof:name":"Alamo Del Alamo Jesus Angel Del",
    "wof:placetype":"venue"
},
  "geometry": {"coordinates":[-3.6065320969,39.4596824646],"type":"Point"}
}