{
  "type": "Feature",
  "properties": {
    "iso:country":"ES",
    "sg:address":"Carrer de Ferran Valls I Taberner, 3",
    "sg:city":"Barcelona",
    "sg:orig_category":"M\u00c9dicos: Cirug\u00cda Ortop\u00c9dica Y Traumatolog\u00cda",
    "sg:phone":"+34 934 14 71 72",
    "sg:postcode":"08006",
    "sg:province":"Barcelona",
    "wof:name":"Mora Guix Jose Maria",
    "wof:placetype":"venue"
},
  "geometry": {"coordinates":[2.1419289112,41.4023208618],"type":"Point"}
}