{
  "type": "Feature",
  "properties": {
    "iso:country":"ES",
    "sg:address":"Rua Pastoriza (da), 18",
    "sg:city":"Santiago De Compostela",
    "sg:orig_category":"Farmacias",
    "sg:phone":"+34 981 58 33 69",
    "sg:postcode":"15704",
    "sg:province":"La Coru\u00f1a",
    "wof:name":"Reymondez Collazo Maria Del Pilar",
    "wof:placetype":"venue"
},
  "geometry": {"coordinates":[-8.5368556976,42.8880462646],"type":"Point"}
}