{
  "type": "Feature",
  "properties": {
    "iso:country":"ES",
    "sg:address":"Carr Ramon Y Cajal, 41",
    "sg:city":"Lleida",
    "sg:orig_category":"Reposter\u00cdas",
    "sg:phone":"+34 973 26 30 25",
    "sg:postcode":"25003",
    "sg:province":"Lleida",
    "wof:name":"Castellvi Roig Maximo",
    "wof:placetype":"venue"
},
  "geometry": {"coordinates":[0.6166650057,41.6159286499],"type":"Point"}
}