{
  "type": "Feature",
  "properties": {
    "addr:full":"Calle de Fray Manuel De Roan, 6 Ossa Montiel Albacete 02611",
    "addr:housenumber":"6",
    "addr:postcode":"02611",
    "addr:street":"Calle De Fray Manuel De Roan;Montiel",
    "iso:country":"ES",
    "sg:address":"Calle de Fray Manuel De Roan, 6",
    "sg:city":"Ossa Montiel",
    "sg:orig_category":"Confecci\u00d3n (fabricaci\u00d3n, Al Por Mayor)",
    "sg:phone":"+34 967 37 73 63",
    "sg:postcode":"02611",
    "sg:province":"Albacete",
    "wof:name":"Confecciones Victorina Victoria E Hijos S.l.",
    "wof:placetype":"venue"
},
  "geometry": {"coordinates":[-2.7452991009,38.9671516418],"type":"Point"}
}