{
  "type": "Feature",
  "properties": {
    "addr:full":"Calle de Coso Alto (a), S/n Guadalcanal Sevilla 41390",
    "addr:housenumber":"s / n",
    "addr:postcode":"41390",
    "addr:street":"Calle De Coso Alto A",
    "iso:country":"ES",
    "sg:address":"Calle de Coso Alto (a), S/n",
    "sg:city":"Guadalcanal",
    "sg:orig_category":"T\u00c9cnicos Veterinarios",
    "sg:phone":"+34 954 88 68 24",
    "sg:postcode":"41390",
    "sg:province":"Sevilla",
    "wof:name":"A.d.s.g. Nuestra Se\u00f1ora De Guaditoca",
    "wof:placetype":"venue"
},
  "geometry": {"coordinates":[-5.8141121864,38.090637207],"type":"Point"}
}