{
  "type": "Feature",
  "properties": {
    "iso:country":"ES",
    "sg:address":"Calle de Granada, 48",
    "sg:city":"Rute",
    "sg:orig_category":"Fisioterapia",
    "sg:phone":"+34 957 53 84 65",
    "sg:postcode":"14960",
    "sg:province":"C\u00f3rdoba",
    "wof:name":"Caballero Mangas Antonia",
    "wof:placetype":"venue"
},
  "geometry": {"coordinates":[-4.3688611984,37.3229103088],"type":"Point"}
}