{
  "type": "Feature",
  "properties": {
    "iso:country":"ES",
    "sg:address":"Carrer de Mare De Deu Dels Angels, 49",
    "sg:city":"Mataro",
    "sg:orig_category":"Empresarios",
    "sg:phone":"+34 937 98 92 10",
    "sg:postcode":"08304",
    "sg:province":"Barcelona",
    "wof:name":"Parareda Bigas Joaquin",
    "wof:placetype":"venue"
},
  "geometry": {"coordinates":[2.4433538914,41.5500679016],"type":"Point"}
}