{
  "type": "Feature",
  "properties": {
    "addr:full":"Pase San Juan Bosco, 37 Monzon Huesca 22400",
    "addr:housenumber":"37",
    "addr:postcode":"22400",
    "addr:street":"San Juan Bosco",
    "iso:country":"ES",
    "sg:address":"Pase San Juan Bosco, 37",
    "sg:city":"Monzon",
    "sg:orig_category":"Inform\u00c1tica: Material Y Suministros",
    "sg:phone":"+34 974 41 78 56",
    "sg:postcode":"22400",
    "sg:province":"Huesca",
    "sg:website":"www.stlmonzon.com",
    "wof:name":"Stl Monzon Trade S.l.u.",
    "wof:placetype":"venue"
},
  "geometry": {"coordinates":[0.1869260073,41.9158782959],"type":"Point"}
}