{
  "type": "Feature",
  "properties": {
    "addr:full":"Quintana, S/n Quintana Pontevedra 36818",
    "addr:housenumber":"s / n",
    "addr:postcode":"36818",
    "addr:street":"Quintana",
    "iso:country":"ES",
    "sg:address":"Quintana, S/n",
    "sg:city":"Quintana",
    "sg:orig_category":"Iglesia Cat\u00d3lica",
    "sg:phone":"+34 986 40 19 58",
    "sg:postcode":"36818",
    "sg:province":"Pontevedra",
    "wof:name":"Obispado Tui-vigo. Parroquia De Santa Maria De Reboreda",
    "wof:placetype":"venue"
},
  "geometry": {"coordinates":[-8.609254837,42.3069534302],"type":"Point"}
}