{
  "type": "Feature",
  "properties": {
    "addr:full":"Carrer de Bruc, 59 Barcelona Barcelona 08009",
    "addr:housenumber":"59",
    "addr:postcode":"08009",
    "addr:street":"Carrer De Bruc",
    "iso:country":"ES",
    "sg:address":"Carrer de Bruc, 59",
    "sg:city":"Barcelona",
    "sg:orig_category":"Cajas De Ahorro",
    "sg:phone":"+34 934 87 60 43",
    "sg:postcode":"08009",
    "sg:province":"Barcelona",
    "wof:name":"Caixa D'estalvis De Catalunya",
    "wof:placetype":"venue"
},
  "geometry": {"coordinates":[2.1704719067,41.3934364319],"type":"Point"}
}