{
  "type": "Feature",
  "properties": {
    "iso:country":"ES",
    "sg:address":"Calle de San Ignacio De Loyola, 3",
    "sg:city":"Zaragoza",
    "sg:orig_category":"Abogados",
    "sg:phone":"+34 976 22 75 06",
    "sg:postcode":"50008",
    "sg:province":"Zaragoza",
    "wof:name":"Miguel Perez Jose Alfonso De",
    "wof:placetype":"venue"
},
  "geometry": {"coordinates":[-0.8824290037,41.6474266052],"type":"Point"}
}