{
  "type": "Feature",
  "properties": {
    "addr:full":"Calle de Palma, 4 Orgaz Toledo 45450",
    "addr:housenumber":"4",
    "addr:postcode":"45450",
    "addr:street":"Calle De Palma",
    "iso:country":"ES",
    "sg:address":"Calle de Palma, 4",
    "sg:city":"Orgaz",
    "sg:orig_category":"Supermercados Y Hipermercados",
    "sg:phone":"+34 925 34 72 40",
    "sg:postcode":"45450",
    "sg:province":"Toledo",
    "wof:name":"Autoservicio Aljame S.l.",
    "wof:placetype":"venue"
},
  "geometry": {"coordinates":[-3.8768270016,39.6497840881],"type":"Point"}
}