{
  "type": "Feature",
  "properties": {
    "iso:country":"ES",
    "sg:address":"Ctra. Estacion, 25",
    "sg:city":"Sta. Cruz Mudela",
    "sg:orig_category":"Transportes Por Carretera: Lotes Completos, Mercanc\u00cdas Diversas",
    "sg:phone":"+34 926 34 22 80",
    "sg:postcode":"13730",
    "sg:province":"Ciudad Real",
    "wof:name":"Castro Jimenez Gloria",
    "wof:placetype":"venue"
},
  "geometry": {"coordinates":[-3.4650518894,38.6419334412],"type":"Point"}
}