{
  "type": "Feature",
  "properties": {
    "iso:country":"ES",
    "sg:address":"Calle de San Bernardo, 20",
    "sg:city":"Madrid",
    "sg:orig_category":"Relojer\u00cda (al Por Menor, Reparaci\u00d3n)",
    "sg:phone":"+34 915 22 00 37",
    "sg:postcode":"28015",
    "sg:province":"Madrid",
    "sg:website":"www.geresa.com",
    "wof:name":"General De Relojeria S.a.",
    "wof:placetype":"venue"
},
  "geometry": {"coordinates":[-3.7074298859,40.4228744507],"type":"Point"}
}