{
  "type": "Feature",
  "properties": {
    "addr:full":"Calle de Benemerito C.guardia Civil, 1 Logro\u00f1o La Rioja 26005",
    "addr:housenumber":"1",
    "addr:postcode":"26005",
    "addr:street":"Calle De Benemerito;Civil;Rioja",
    "iso:country":"ES",
    "sg:address":"Calle de Benemerito C.guardia Civil, 1",
    "sg:city":"Logro\u00f1o",
    "sg:orig_category":"Carnicer\u00cdas, Carnicer\u00cdas",
    "sg:phone":"+34 941 22 56 18",
    "sg:postcode":"26005",
    "sg:province":"La Rioja",
    "wof:name":"Diaz Besga Jose Luis",
    "wof:placetype":"venue"
},
  "geometry": {"coordinates":[-2.4527618885,42.4650344849],"type":"Point"}
}