{
  "type": "Feature",
  "properties": {
    "iso:country":"ES",
    "sg:address":"Carrer de Parcers, 2",
    "sg:city":"Molins Rei",
    "sg:orig_category":"Molduras, Junquillos, Listones Y Molduras Perforadas",
    "sg:phone":"+34 936 68 52 87",
    "sg:postcode":"08750",
    "sg:province":"Barcelona",
    "wof:name":"L'ancora Daurada S.l.",
    "wof:placetype":"venue"
},
  "geometry": {"coordinates":[2.0139620304,41.4155158997],"type":"Point"}
}