{
  "type": "Feature",
  "properties": {
    "iso:country":"ES",
    "sg:address":"Rua Rosalia De Castro, 6",
    "sg:city":"Pobra Trives",
    "sg:orig_category":"Notarios",
    "sg:phone":"+34 988 33 24 42",
    "sg:postcode":"32780",
    "sg:province":"Ourense",
    "wof:name":"Ilustre Colegio Notarial De La Coru\u00d1a",
    "wof:placetype":"venue"
},
  "geometry": {"coordinates":[-7.2529859543,42.3367652893],"type":"Point"}
}