{
  "type": "Feature",
  "properties": {
    "addr:full":"Pg Gracia, 55 Barcelona Barcelona 08007",
    "addr:housenumber":"55",
    "addr:postcode":"08007",
    "addr:street":"Pg Gracia",
    "iso:country":"ES",
    "sg:address":"Pg Gracia, 55",
    "sg:city":"Barcelona",
    "sg:orig_category":"Inform\u00c1tica (estudios, Servicios, Asesor\u00cda, Formaci\u00d3n)",
    "sg:phone":"+34 934 88 09 49",
    "sg:postcode":"08007",
    "sg:province":"Barcelona",
    "sg:website":"www.smart-vision.net",
    "wof:name":"Tecnologias De Reconocimiento S.a.",
    "wof:placetype":"venue"
},
  "geometry": {"coordinates":[2.1639490128,41.392539978],"type":"Point"}
}