{
  "type": "Feature",
  "properties": {
    "addr:full":"Tor. Tortuguer (els Pinetons), 5 Ripollet Barcelona 08291",
    "addr:housenumber":"5",
    "addr:postcode":"08291",
    "addr:street":"Pinetons",
    "iso:country":"ES",
    "sg:address":"Tor. Tortuguer (els Pinetons), 5",
    "sg:city":"Ripollet",
    "sg:orig_category":"Importaci\u00d3n",
    "sg:phone":"+34 935 80 50 16",
    "sg:postcode":"08291",
    "sg:province":"Barcelona",
    "wof:name":"N2v S.a.l.",
    "wof:placetype":"venue"
},
  "geometry": {"coordinates":[2.1489770412,41.5094833374],"type":"Point"}
}