{
  "type": "Feature",
  "properties": {
    "iso:country":"ES",
    "sg:address":"Carr Monges, 7",
    "sg:city":"Puerto De Pollen\u00c7a",
    "sg:classifiers":[
        {
            "category":"Retail",
            "subcategory":"Event Space",
            "type":"Services"
        }
    ],
    "sg:phone":"+34 971 86 72 55",
    "sg:postcode":"07470",
    "sg:province":"Islas Baleares",
    "sg:tags":[
        "planchas",
        "surf",
        "alquiler",
        "de",
        "vela",
        "kayak",
        "barcos",
        "canoes",
        "y"
    ],
    "sg:website":"www.cmcharter.com",
    "wof:name":"Claus Meyer Charter Mallorca Sl",
    "wof:placetype":"venue"
},
  "geometry": {"coordinates":[3.0821900368,39.9063034058],"type":"Point"}
}