{
  "type": "Feature",
  "properties": {
    "addr:full":"Carrer de Ramon Berenguer Primer, S/n Santa Perpetua De Mogoda Barcelona 08130",
    "addr:housenumber":"s / n",
    "addr:postcode":"08130",
    "addr:street":"Carrer De Ramon Berenguer Primer",
    "iso:country":"ES",
    "sg:address":"Carrer de Ramon Berenguer Primer, S/n",
    "sg:city":"Santa Perpetua De Mogoda",
    "sg:orig_category":"Art\u00cdculos De Madera (fabricaci\u00d3n Y Al Por Mayor)",
    "sg:phone":"+34 935 60 05 00",
    "sg:postcode":"08130",
    "sg:province":"Barcelona",
    "wof:name":"Muebles Modular Santa Maria S.l.",
    "wof:placetype":"venue"
},
  "geometry": {"coordinates":[2.1621201038,41.5339202881],"type":"Point"}
}