{
  "type": "Feature",
  "properties": {
    "iso:country":"ES",
    "sg:address":"Avda Mediterraneo, 12",
    "sg:city":"Salobre\u00f1a",
    "sg:orig_category":"Construcciones Met\u00c1licas",
    "sg:phone":"+34 958 61 01 14",
    "sg:postcode":"18680",
    "sg:province":"Granada",
    "wof:name":"Estructuras Y Ferrallas Alabarce S.l.",
    "wof:placetype":"venue"
},
  "geometry": {"coordinates":[-3.5826239586,36.7424049377],"type":"Point"}
}