{
  "type": "Feature",
  "properties": {
    "iso:country":"ES",
    "sg:address":"Avda Asia, 1",
    "sg:city":"Gran Alacant",
    "sg:orig_category":"Inmobiliaria (agencias)",
    "sg:phone":"+34 966 69 81 25",
    "sg:postcode":"03130",
    "sg:province":"Alicante",
    "wof:name":"Tres Gran Alacant S.l.",
    "wof:placetype":"venue"
},
  "geometry": {"coordinates":[-0.5565090179,38.190448761],"type":"Point"}
}