{
  "type": "Feature",
  "properties": {
    "addr:full":"Calle de Escritor Fernandez Franco, 3 Cordoba C\u00f3rdoba 14007",
    "addr:housenumber":"3",
    "addr:postcode":"14007",
    "addr:street":"Calle De Escritor Fernandez Franco;Co\u0301Rdoba",
    "iso:country":"ES",
    "sg:address":"Calle de Escritor Fernandez Franco, 3",
    "sg:city":"Cordoba",
    "sg:orig_category":"Ropa Para Se\u00d1oras (al Por Menor)",
    "sg:phone":"+34 957 25 20 93",
    "sg:postcode":"14007",
    "sg:province":"C\u00f3rdoba",
    "wof:name":"Duran Merino Manuel",
    "wof:placetype":"venue"
},
  "geometry": {"coordinates":[-4.756319046,37.8953094482],"type":"Point"}
}