{
  "type": "Feature",
  "properties": {
    "addr:full":"Ctra Almensilla, S/n Mairena Aljarafe Sevilla 41927",
    "addr:housenumber":"s / n",
    "addr:postcode":"41927",
    "addr:street":"Ctra Almensilla",
    "iso:country":"ES",
    "sg:address":"Ctra Almensilla, S/n",
    "sg:city":"Mairena Aljarafe",
    "sg:orig_category":"Frutas Y Legumbres Frescas (al Por Mayor)",
    "sg:phone":"+34 955 60 97 12",
    "sg:postcode":"41927",
    "sg:province":"Sevilla",
    "wof:name":"Euroliva S. A.",
    "wof:placetype":"venue"
},
  "geometry": {"coordinates":[-6.0697741508,37.3381614685],"type":"Point"}
}