{
  "type": "Feature",
  "properties": {
    "iso:country":"ES",
    "sg:address":"Calle de Libreros, 33",
    "sg:city":"Alcala Henares",
    "sg:orig_category":"Iglesia Cat\u00d3lica",
    "sg:phone":"+34 918 88 01 64",
    "sg:postcode":"28801",
    "sg:province":"Madrid",
    "wof:name":"Obispado De Alcala De Henares",
    "wof:placetype":"venue"
},
  "geometry": {"coordinates":[-3.3625121117,40.4845161438],"type":"Point"}
}