{
  "type": "Feature",
  "properties": {
    "iso:country":"ES",
    "sg:address":"Carr Picapedrers, 3",
    "sg:city":"Vilanova I La Geltru",
    "sg:orig_category":"Promotores Constructores",
    "sg:phone":"+34 938 93 61 25",
    "sg:postcode":"08800",
    "sg:province":"Barcelona",
    "wof:name":"Tecnic Instal.lacions S.c.c.l.",
    "wof:placetype":"venue"
},
  "geometry": {"coordinates":[1.7207900286,41.2243347168],"type":"Point"}
}