{
  "type": "Feature",
  "properties": {
    "addr:full":"Calle de Luis Ruiz, 88 Madrid Madrid 28017",
    "addr:housenumber":"88",
    "addr:postcode":"madrid;28017",
    "addr:street":"Calle De Luis Ruiz",
    "iso:country":"ES",
    "sg:address":"Calle de Luis Ruiz, 88",
    "sg:city":"Madrid",
    "sg:orig_category":"Agencias De Viajes",
    "sg:phone":"+34 914 40 05 17",
    "sg:postcode":"28017",
    "sg:province":"Madrid",
    "wof:name":"Robles Gutierrez David",
    "wof:placetype":"venue"
},
  "geometry": {"coordinates":[-3.6355359554,40.4271430969],"type":"Point"}
}