{
  "type": "Feature",
  "properties": {
    "iso:country":"ES",
    "sg:address":"Calle de Joaquin Mercado, 5",
    "sg:city":"Santisteban Puerto",
    "sg:orig_category":"Papeler\u00cdas, Librer\u00cdas",
    "sg:phone":"+34 953 40 14 91",
    "sg:postcode":"23250",
    "sg:province":"Ja\u00e9n",
    "wof:name":"Sagra Diaz Luis",
    "wof:placetype":"venue"
},
  "geometry": {"coordinates":[-3.2068729401,38.2478866577],"type":"Point"}
}