{
  "type": "Feature",
  "properties": {
    "iso:country":"ES",
    "sg:address":"Rua Progreso, 8",
    "sg:city":"Melide",
    "sg:orig_category":"Farmacias",
    "sg:phone":"+34 981 50 53 07",
    "sg:postcode":"15800",
    "sg:province":"La Coru\u00f1a",
    "wof:name":"Luis Lopez E Hijos,s.l",
    "wof:placetype":"venue"
},
  "geometry": {"coordinates":[-8.0155220032,42.913684845],"type":"Point"}
}