{
  "type": "Feature",
  "properties": {
    "addr:full":"Plaz Coton, 14 Negreira La Coru\u00f1a 15830",
    "addr:housenumber":"14",
    "addr:postcode":"15830",
    "addr:street":"Plaz Coton;La Corun\u0303A",
    "iso:country":"ES",
    "sg:address":"Plaz Coton, 14",
    "sg:city":"Negreira",
    "sg:orig_category":"Agencias De Viajes",
    "sg:phone":"+34 981 88 52 13",
    "sg:postcode":"15830",
    "sg:province":"La Coru\u00f1a",
    "wof:name":"Agencia De Viajes Tambre S.l.",
    "wof:placetype":"venue"
},
  "geometry": {"coordinates":[-8.8252506256,42.9020614624],"type":"Point"}
}