{
  "type": "Feature",
  "properties": {
    "iso:country":"ES",
    "sg:address":"Calle de General Solchaga, 72",
    "sg:city":"Valladolid",
    "sg:orig_category":"Maquinaria Para Industrias Diversas",
    "sg:phone":"+34 983 23 17 42",
    "sg:postcode":"47008",
    "sg:province":"Valladolid",
    "sg:website":"www.tecnicalor.com",
    "wof:name":"Hidrobomba S.l.",
    "wof:placetype":"venue"
},
  "geometry": {"coordinates":[-4.7338838577,41.6258049011],"type":"Point"}
}