{
  "type": "Feature",
  "properties": {
    "addr:full":"Praj Chinas (las), S/n Vera Almer\u00eda 04620",
    "addr:housenumber":"/ n;almeri\u0301a",
    "addr:postcode":"04620",
    "addr:street":"Las S",
    "iso:country":"ES",
    "sg:address":"Praj Chinas (las), S/n",
    "sg:city":"Vera",
    "sg:orig_category":"Control T\u00c9cnico De Veh\u00cdculos",
    "sg:phone":"+34 950 39 17 26",
    "sg:postcode":"04620",
    "sg:province":"Almer\u00eda",
    "wof:name":"Verificaciones Industriales De Andalucia S.a.",
    "wof:placetype":"venue"
},
  "geometry": {"coordinates":[-1.8488399982,37.2383613586],"type":"Point"}
}