{
  "type": "Feature",
  "properties": {
    "iso:country":"ES",
    "sg:address":"Calle de Isla De Arosa, 9",
    "sg:city":"Madrid",
    "sg:orig_category":"Inform\u00c1tica: Soportes De Informaci\u00d3n, Suministros & Accesorios",
    "sg:phone":"+34 917 38 55 66",
    "sg:postcode":"28035",
    "sg:province":"Madrid",
    "wof:name":"Fernandez Rodriguez David",
    "wof:placetype":"venue"
},
  "geometry": {"coordinates":[-3.7168729305,40.4795951843],"type":"Point"}
}