{
  "type": "Feature",
  "properties": {
    "addr:full":"Rincon De Loix, 24 Benidorm Alicante 03500",
    "addr:housenumber":"24",
    "addr:postcode":"03500",
    "iso:country":"ES",
    "sg:address":"Rincon De Loix, 24",
    "sg:city":"Benidorm",
    "sg:orig_category":"Panader\u00cdas, Panader\u00cdas",
    "sg:phone":"+34 965 86 01 64",
    "sg:postcode":"03500",
    "sg:province":"Alicante",
    "sg:website":"www.alarconsfood.com",
    "wof:name":"Alarcons Foods Sl",
    "wof:placetype":"venue"
},
  "geometry": {"coordinates":[-0.1020419002,38.5447692871],"type":"Point"}
}