{
  "type": "Feature",
  "properties": {
    "iso:country":"ES",
    "sg:address":"Rbla A\u00d1aza (de), S/n",
    "sg:city":"A\u00d1aza",
    "sg:orig_category":"Peluqueros: De Se\u00d1oras",
    "sg:phone":"+34 922 68 52 42",
    "sg:postcode":"38111",
    "sg:province":"Santa Cruz De Tenerife",
    "wof:name":"Peluqueria Celis",
    "wof:placetype":"venue"
},
  "geometry": {"coordinates":[-16.3035106659,28.4221992493],"type":"Point"}
}