{
  "type": "Feature",
  "properties": {
    "addr:full":"Avda Tolosa De, 103 Donostia-san Sebastian Guip\u00f9zcoa 20018",
    "addr:housenumber":"103",
    "addr:postcode":"20018",
    "addr:street":"Avda Tolosa De",
    "iso:country":"ES",
    "sg:address":"Avda Tolosa De, 103",
    "sg:city":"Donostia-san Sebastian",
    "sg:orig_category":"M\u00c9dicos: Geriatr\u00cda, Gerontolog\u00cda (enfermedades De La Tercera Edad)",
    "sg:phone":"+34 943 21 04 71",
    "sg:postcode":"20018",
    "sg:province":"Guip\u00f9zcoa",
    "wof:name":"Consulta De Geriatria",
    "wof:placetype":"venue"
},
  "geometry": {"coordinates":[-2.0029520988,43.2836837769],"type":"Point"}
}