{
  "type": "Feature",
  "properties": {
    "addr:full":"Calle de Valle De Abdalajis, 20 Malaga M\u00e1laga 29006",
    "addr:housenumber":"20",
    "addr:postcode":"29006",
    "addr:street":"Calle De Valle De Abdalajis;Ma\u0301Laga",
    "iso:country":"ES",
    "sg:address":"Calle de Valle De Abdalajis, 20",
    "sg:city":"Malaga",
    "sg:orig_category":"Farmacias",
    "sg:phone":"+34 952 33 29 49",
    "sg:postcode":"29006",
    "sg:province":"M\u00e1laga",
    "wof:name":"Lopez Hernandez Jesus Felipe",
    "wof:placetype":"venue"
},
  "geometry": {"coordinates":[-4.4488940239,36.7095718384],"type":"Point"}
}