{
  "type": "Feature",
  "properties": {
    "iso:country":"ES",
    "sg:address":"Carr Fray Gabriel Ripolles, S/n",
    "sg:city":"Cabanes",
    "sg:orig_category":"Empresarios",
    "sg:phone":"+34 964 33 12 05",
    "sg:postcode":"12180",
    "sg:province":"Castell\u00f3n",
    "wof:name":"Garcia Martinez Manuel",
    "wof:placetype":"venue"
},
  "geometry": {"coordinates":[0.0412000008,40.155670166],"type":"Point"}
}