{
  "type": "Feature",
  "properties": {
    "iso:country":"ES",
    "sg:address":"Calle de Fueros, 18",
    "sg:city":"Vitoria-gasteiz",
    "sg:orig_category":"Ingenier\u00cda, Centros De Estudios (diversos)",
    "sg:phone":"+34 945 14 30 08",
    "sg:postcode":"01005",
    "sg:province":"\u00c1lava",
    "wof:name":"Oina Industrial S.a.",
    "wof:placetype":"venue"
},
  "geometry": {"coordinates":[-2.6700723171,42.8434677124],"type":"Point"}
}