{
  "type": "Feature",
  "properties": {
    "addr:full":"Carrer de Primavera, 35 Hospitalet Llobregat Barcelona 08905",
    "addr:housenumber":"35",
    "addr:postcode":"08905",
    "addr:street":"Carrer De Primavera",
    "iso:country":"ES",
    "sg:address":"Carrer de Primavera, 35",
    "sg:city":"Hospitalet Llobregat",
    "sg:orig_category":"Molduras, Junquillos, Listones Y Molduras Perforadas",
    "sg:phone":"+34 933 34 66 30",
    "sg:postcode":"08905",
    "sg:province":"Barcelona",
    "wof:name":"Camilo Amores Francisco",
    "wof:placetype":"venue"
},
  "geometry": {"coordinates":[2.1101000309,41.3695487976],"type":"Point"}
}