{
  "type": "Feature",
  "properties": {
    "addr:full":"Avda Herrera Oria, S/n Ubrique C\u00e1diz 11600",
    "addr:housenumber":"s / n",
    "addr:postcode":"11600",
    "addr:street":"Avda Herrera Oria;Ca\u0301Diz",
    "iso:country":"ES",
    "sg:address":"Avda Herrera Oria, S/n",
    "sg:city":"Ubrique",
    "sg:orig_category":"Edici\u00d3n De Diarios, Revistas, Boletines",
    "sg:phone":"+34 956 46 33 70",
    "sg:postcode":"11600",
    "sg:province":"C\u00e1diz",
    "sg:website":"www.treveris.es",
    "wof:name":"Editorial Treveris S.l.",
    "wof:placetype":"venue"
},
  "geometry": {"coordinates":[-5.4453787804,36.6791992188],"type":"Point"}
}