{
  "type": "Feature",
  "properties": {
    "addr:full":"Calle de Zabaleta, 60 Madrid Madrid 28002",
    "addr:housenumber":"60",
    "addr:postcode":"madrid;28002",
    "addr:street":"Calle De Zabaleta",
    "iso:country":"ES",
    "sg:address":"Calle de Zabaleta, 60",
    "sg:city":"Madrid",
    "sg:orig_category":"Librer\u00cdas",
    "sg:phone":"+34 915 19 15 39",
    "sg:postcode":"28002",
    "sg:province":"Madrid",
    "wof:name":"Publicaciones Directas S.l.",
    "wof:placetype":"venue"
},
  "geometry": {"coordinates":[-3.6723620892,40.4430351257],"type":"Point"}
}