{
  "type": "Feature",
  "properties": {
    "iso:country":"ES",
    "sg:address":"Calle de Padre Urbano, 41",
    "sg:city":"Valencia",
    "sg:classifiers":[
        {
            "category":"Personal",
            "subcategory":"Barber",
            "type":"Services"
        }
    ],
    "sg:phone":"+34 963 65 80 46",
    "sg:postcode":"46009",
    "sg:province":"Valencia",
    "sg:tags":[
        "caballeros",
        "de",
        "peluqueros"
    ],
    "wof:name":"Mu\u00f1oz Lerin Manuel",
    "wof:placetype":"venue"
},
  "geometry": {"coordinates":[-0.3708420098,39.4886741638],"type":"Point"}
}