{
  "type": "Feature",
  "properties": {
    "iso:country":"ES",
    "sg:address":"Calle de Sierpe Baja, 1",
    "sg:city":"Granada",
    "sg:orig_category":"Ropa Para Caballeros (al Por Menor)",
    "sg:phone":"+34 958 26 35 31",
    "sg:postcode":"18001",
    "sg:province":"Granada",
    "wof:name":"Castilla Sanchez Luis",
    "wof:placetype":"venue"
},
  "geometry": {"coordinates":[-3.6004440784,37.1741409302],"type":"Point"}
}