{
  "type": "Feature",
  "properties": {
    "addr:full":"Carrer de Providencia, 53 S. Boi Llobregat Barcelona 08830",
    "addr:housenumber":"53",
    "addr:postcode":"08830",
    "addr:street":"Carrer De Providencia",
    "iso:country":"ES",
    "sg:address":"Carrer de Providencia, 53",
    "sg:city":"S. Boi Llobregat",
    "sg:orig_category":"Florister\u00cdas",
    "sg:phone":"+34 936 30 17 31",
    "sg:postcode":"08830",
    "sg:province":"Barcelona",
    "wof:name":"Lopez Boada Yolanda",
    "wof:placetype":"venue"
},
  "geometry": {"coordinates":[2.0293610096,41.3500404358],"type":"Point"}
}