{
  "type": "Feature",
  "properties": {
    "addr:full":"Calle de Vicario, 7 Alcublas Valencia 46172",
    "addr:postcode":"46172",
    "addr:street":"Calle De Vicario 7",
    "iso:country":"ES",
    "sg:address":"Calle de Vicario, 7",
    "sg:city":"Alcublas",
    "sg:orig_category":"Discotecas Y Salas De Baile",
    "sg:phone":"+34 962 70 42 32",
    "sg:postcode":"46172",
    "sg:province":"Valencia",
    "wof:name":"Civera Aparicio Jose Maria",
    "wof:placetype":"venue"
},
  "geometry": {"coordinates":[-0.7031499743,39.797618866],"type":"Point"}
}