{
  "type": "Feature",
  "properties": {
    "iso:country":"ES",
    "sg:address":"Calle de Do\u00d1ana (de), 20",
    "sg:city":"Humanes De Madrid",
    "sg:orig_category":"Fabricaci\u00d3n, Instalaci\u00d3n De Armarios",
    "sg:phone":"+34 916 15 51 70",
    "sg:postcode":"28970",
    "sg:province":"Madrid",
    "wof:name":"Vargas Sanchez Juan Antonio",
    "wof:placetype":"venue"
},
  "geometry": {"coordinates":[-3.8195259571,40.2695846558],"type":"Point"}
}