{
  "type": "Feature",
  "properties": {
    "iso:country":"ES",
    "sg:address":"Calle de Luis Chamizo, 15",
    "sg:city":"Puebla Del Prior",
    "sg:orig_category":"Cr\u00cda De Animales",
    "sg:phone":"+34 924 53 64 30",
    "sg:postcode":"06229",
    "sg:province":"Badajoz",
    "wof:name":"Europorcino Perera S.a.l.",
    "wof:placetype":"venue"
},
  "geometry": {"coordinates":[-6.1956119537,38.569568634],"type":"Point"}
}