{
  "type": "Feature",
  "properties": {
    "iso:country":"ES",
    "sg:address":"Calle de Puebla De Mexico, 5",
    "sg:city":"Talavera Reina",
    "sg:orig_category":"Empresas De Pintura Y Revestimientos",
    "sg:phone":"+34 925 80 32 99",
    "sg:postcode":"45600",
    "sg:province":"Toledo",
    "wof:name":"Poly Pint S.l.",
    "wof:placetype":"venue"
},
  "geometry": {"coordinates":[-4.844435215,39.9577293396],"type":"Point"}
}