{
  "type": "Feature",
  "properties": {
    "addr:full":"Ptge Cala Morlanda, 3 Palma Islas Baleares 07009",
    "addr:housenumber":"3",
    "addr:postcode":"07009",
    "addr:street":"Ptge Cala Morlanda",
    "iso:country":"ES",
    "sg:address":"Ptge Cala Morlanda, 3",
    "sg:city":"Palma",
    "sg:orig_category":"Molduras, Junquillos, Listones Y Molduras Perforadas",
    "sg:phone":"+34 971 47 70 27",
    "sg:postcode":"07009",
    "sg:province":"Islas Baleares",
    "wof:name":"Navio Del Castillo Jose",
    "wof:placetype":"venue"
},
  "geometry": {"coordinates":[2.6780290604,39.597328186],"type":"Point"}
}