{
  "type": "Feature",
  "properties": {
    "addr:full":"Carr Josep M Quadrado, 28 Ciutadella Menorca Islas Baleares 07760",
    "addr:housenumber":"28",
    "addr:postcode":"07760",
    "addr:street":"Carr Josep M Quadrado",
    "iso:country":"ES",
    "sg:address":"Carr Josep M Quadrado, 28",
    "sg:city":"Ciutadella Menorca",
    "sg:orig_category":"Art\u00cdculos De Regalo (al Por Menor)",
    "sg:phone":"+34 971 38 53 79",
    "sg:postcode":"07760",
    "sg:province":"Islas Baleares",
    "wof:name":"Marti Ramon Maria Antonia",
    "wof:placetype":"venue"
},
  "geometry": {"coordinates":[3.8416149616,40.0027542114],"type":"Point"}
}