{
  "type": "Feature",
  "properties": {
    "iso:country":"ES",
    "sg:address":"Calle de Romeral, 5",
    "sg:city":"Rozas De Madrid",
    "sg:orig_category":"Librer\u00cdas",
    "sg:phone":"+34 916 36 09 34",
    "sg:postcode":"28230",
    "sg:province":"Madrid",
    "wof:name":"Papeleria Las Rozas S.l.",
    "wof:placetype":"venue"
},
  "geometry": {"coordinates":[-3.8734400272,40.4929695129],"type":"Point"}
}