{
  "type": "Feature",
  "properties": {
    "addr:full":"C/ Sant Pere Claver, 5 Tarrega Lleida 25300",
    "addr:housenumber":"5",
    "addr:postcode":"25300",
    "addr:street":"C / Sant;Claver",
    "iso:country":"ES",
    "sg:address":"C/ Sant Pere Claver, 5",
    "sg:city":"Tarrega",
    "sg:orig_category":"Importaci\u00d3n",
    "sg:phone":"+34 973 31 04 09",
    "sg:postcode":"25300",
    "sg:province":"Lleida",
    "wof:name":"Raja  Shezad",
    "wof:placetype":"venue"
},
  "geometry": {"coordinates":[1.1430799961,41.6438140869],"type":"Point"}
}