{
  "type": "Feature",
  "properties": {
    "addr:full":"Calle de Alvarez Abellan, 19 Madrid Madrid 28025",
    "addr:housenumber":"19",
    "addr:postcode":"madrid;28025",
    "addr:street":"Calle De Alvarez Abellan",
    "iso:country":"ES",
    "sg:address":"Calle de Alvarez Abellan, 19",
    "sg:city":"Madrid",
    "sg:orig_category":"Chapister\u00cda",
    "sg:phone":"+34 914 65 56 39",
    "sg:postcode":"28025",
    "sg:province":"Madrid",
    "wof:name":"Chapa Y Pintura Marpe S.l.",
    "wof:placetype":"venue"
},
  "geometry": {"coordinates":[-3.7321557999,40.3850364685],"type":"Point"}
}