{
  "type": "Feature",
  "properties": {
    "iso:country":"ES",
    "sg:address":"Calle de General Riera, 138",
    "sg:city":"Palma",
    "sg:orig_category":"Chapister\u00cda",
    "sg:phone":"+34 971 20 66 17",
    "sg:postcode":"07010",
    "sg:province":"Islas Baleares",
    "wof:name":"Jaume Marin Jeronimo",
    "wof:placetype":"venue"
},
  "geometry": {"coordinates":[2.644931078,39.5915718079],"type":"Point"}
}