{
  "type": "Feature",
  "properties": {
    "iso:country":"ES",
    "sg:address":"Calle de Miguel De Cervantes, 9",
    "sg:city":"Teruel",
    "sg:orig_category":"Cr\u00cda De Corderos Y De Cabras",
    "sg:phone":"+34 978 60 56 28",
    "sg:postcode":"44002",
    "sg:province":"Teruel",
    "wof:name":"Carnicas Vimai S.l.",
    "wof:placetype":"venue"
},
  "geometry": {"coordinates":[-1.1037060022,40.3318252563],"type":"Point"}
}