{
  "type": "Feature",
  "properties": {
    "addr:full":"Cmno Meatzeta, S/n Usansolo Vizcaya 48960",
    "addr:housenumber":"s",
    "addr:postcode":"48960",
    "addr:street":"Cmno Meatzeta;/ N",
    "iso:country":"ES",
    "sg:address":"Cmno Meatzeta, S/n",
    "sg:city":"Usansolo",
    "sg:orig_category":"Centros De Educaci\u00d3n Especial",
    "sg:phone":"+34 944 56 56 39",
    "sg:postcode":"48960",
    "sg:province":"Vizcaya",
    "wof:name":"Gobierno Vasco-eusko Jaurlaritza",
    "wof:placetype":"venue"
},
  "geometry": {"coordinates":[-2.8231399059,43.2195243835],"type":"Point"}
}