{
  "type": "Feature",
  "properties": {
    "iso:country":"ES",
    "sg:address":"Av Galicia, 6",
    "sg:city":"Jonquera",
    "sg:orig_category":"Electrodom\u00c9sticos (al Por Menor)",
    "sg:phone":"+34 972 55 58 38",
    "sg:postcode":"17700",
    "sg:province":"Girona",
    "wof:name":"Electrodomestics Mas Morato S.l.",
    "wof:placetype":"venue"
},
  "geometry": {"coordinates":[2.8817451,42.3987846375],"type":"Point"}
}