{
  "type": "Feature",
  "properties": {
    "iso:country":"ES",
    "sg:address":"Carrer de Parcel.les, 8",
    "sg:city":"Maravillas",
    "sg:orig_category":"Bares, Piano",
    "sg:phone":"+34 971 26 75 55",
    "sg:postcode":"07610",
    "sg:province":"Islas Baleares",
    "wof:name":"Guacamac Insula S.l.",
    "wof:placetype":"venue"
},
  "geometry": {"coordinates":[2.7302839756,39.5303039551],"type":"Point"}
}