{
  "type": "Feature",
  "properties": {
    "iso:country":"ES",
    "sg:address":"Calle de Oviedo, 2",
    "sg:city":"Mostoles",
    "sg:orig_category":"Institutos De Belleza",
    "sg:phone":"+34 916 17 32 24",
    "sg:postcode":"28934",
    "sg:province":"Madrid",
    "wof:name":"Miguel Alvarez Maria Jose Piedad",
    "wof:placetype":"venue"
},
  "geometry": {"coordinates":[-3.8720920086,40.320854187],"type":"Point"}
}