{
  "type": "Feature",
  "properties": {
    "iso:country":"ES",
    "sg:address":"Calle de Fuenlabrada, 14",
    "sg:city":"Getafe",
    "sg:orig_category":"Ense\u00d1anza: Idiomas",
    "sg:phone":"+34 916 83 90 26",
    "sg:postcode":"28901",
    "sg:province":"Madrid",
    "wof:name":"Garcia Ortiz Jose",
    "wof:placetype":"venue"
},
  "geometry": {"coordinates":[-3.7337577343,40.3038406372],"type":"Point"}
}