{
  "type": "Feature",
  "properties": {
    "addr:full":"Crta. Tudela-azagra, S/n Fontellas Navarra 31512",
    "addr:housenumber":"s",
    "addr:postcode":"31512",
    "addr:street":"Crta. Tudela-Azagra;/ N",
    "iso:country":"ES",
    "sg:address":"Crta. Tudela-azagra, S/n",
    "sg:city":"Fontellas",
    "sg:orig_category":"Transportes Por Carretera: Lotes Completos, Mercanc\u00cdas Diversas",
    "sg:phone":"+34 948 41 02 44",
    "sg:postcode":"31512",
    "sg:province":"Navarra",
    "wof:name":"Ribertrans S.c.l.",
    "wof:placetype":"venue"
},
  "geometry": {"coordinates":[-1.5819790363,42.0298309326],"type":"Point"}
}