{
  "type": "Feature",
  "properties": {
    "iso:country":"ES",
    "sg:address":"Carrer de Industria, 22",
    "sg:city":"Mas Rampinyo",
    "sg:orig_category":"Deportes N\u00c1uticos, Acu\u00c1ticos Y Subacu\u00c1ticos: Art\u00cdculos Y Equipo (al Por Menor)",
    "sg:phone":"+34 935 64 86 60",
    "sg:postcode":"08110",
    "sg:province":"Barcelona",
    "wof:name":"Herrainox S.l.",
    "wof:placetype":"venue"
},
  "geometry": {"coordinates":[2.1796140671,41.4921951294],"type":"Point"}
}