{
  "type": "Feature",
  "properties": {
    "addr:full":"Carrer de Gran De Gracia, 186 Barcelona Barcelona 08012",
    "addr:housenumber":"186",
    "addr:postcode":"08012",
    "addr:street":"Carrer De Gran De Gracia",
    "iso:country":"ES",
    "sg:address":"Carrer de Gran De Gracia, 186",
    "sg:city":"Barcelona",
    "sg:orig_category":"Frutas Y Legumbres Frescas (al Por Mayor)",
    "sg:phone":"+34 934 15 51 08",
    "sg:postcode":"08012",
    "sg:province":"Barcelona",
    "wof:name":"Suministres Horticoles S. A.",
    "wof:placetype":"venue"
},
  "geometry": {"coordinates":[2.1524710655,41.4030227661],"type":"Point"}
}