{
  "type": "Feature",
  "properties": {
    "iso:country":"ES",
    "sg:address":"Urb El Prado, 63",
    "sg:city":"Merida",
    "sg:orig_category":"Delegados, Agentes De Tr\u00c1nsito, Auxiliares De Transporte Internacional",
    "sg:phone":"+34 924 37 15 20",
    "sg:postcode":"06800",
    "sg:province":"Badajoz",
    "wof:name":"Transportes Azkar S.a.",
    "wof:placetype":"venue"
},
  "geometry": {"coordinates":[-6.3464841843,38.916053772],"type":"Point"}
}