{
  "type": "Feature",
  "properties": {
    "addr:full":"Carrer de Sant Roc, 25 Mollet Valles Barcelona 08100",
    "addr:housenumber":"25",
    "addr:postcode":"08100",
    "addr:street":"Carrer De Sant Roc",
    "iso:country":"ES",
    "sg:address":"Carrer de Sant Roc, 25",
    "sg:city":"Mollet Valles",
    "sg:orig_category":"Reposter\u00cdas",
    "sg:phone":"+34 935 93 12 58",
    "sg:postcode":"08100",
    "sg:province":"Barcelona",
    "wof:name":"Corbalan Ruiz Manuel",
    "wof:placetype":"venue"
},
  "geometry": {"coordinates":[2.2179019451,41.5448799133],"type":"Point"}
}