{
  "type": "Feature",
  "properties": {
    "addr:full":"Calle de Sierra (la), 12 Villaquilambre Le\u00f3n 24008",
    "addr:housenumber":"12",
    "addr:postcode":"24008",
    "addr:street":"Calle De Sierra La",
    "iso:country":"ES",
    "sg:address":"Calle de Sierra (la), 12",
    "sg:city":"Villaquilambre",
    "sg:orig_category":"Reposter\u00cdas",
    "sg:phone":"+34 987 28 32 64",
    "sg:postcode":"24008",
    "sg:province":"Le\u00f3n",
    "wof:name":"Lorden Liebana Mariano",
    "wof:placetype":"venue"
},
  "geometry": {"coordinates":[-5.5570340157,42.6394042969],"type":"Point"}
}