{
  "type": "Feature",
  "properties": {
    "iso:country":"ES",
    "sg:address":"Calle de Mesas, 27",
    "sg:city":"Villarrobledo",
    "sg:orig_category":"Cerrajer\u00cda, Ferrallista",
    "sg:phone":"+34 967 14 72 80",
    "sg:postcode":"02600",
    "sg:province":"Albacete",
    "sg:website":"www.bonillodiaz.com",
    "wof:name":"Bonillo Diaz S.l.",
    "wof:placetype":"venue"
},
  "geometry": {"coordinates":[-2.6132369041,39.2704048157],"type":"Point"}
}