{
  "type": "Feature",
  "properties": {
    "addr:full":"Les Debanadores, 32 Ontinyent Valencia 46870",
    "addr:housenumber":"32",
    "addr:postcode":"46870",
    "iso:country":"ES",
    "sg:address":"Les Debanadores, 32",
    "sg:city":"Ontinyent",
    "sg:orig_category":"Fabricaci\u00d3n, Venta De Cuadros, Accesorios Para Enmarcar",
    "sg:phone":"+34 962 38 43 13",
    "sg:postcode":"46870",
    "sg:province":"Valencia",
    "wof:name":"Moreno Ribera Rafael Ricardo",
    "wof:placetype":"venue"
},
  "geometry": {"coordinates":[-0.6030989885,38.8258895874],"type":"Point"}
}