{
  "type": "Feature",
  "properties": {
    "addr:full":"Urb Santa Margarita, S/n Marbella M\u00e1laga 29600",
    "addr:housenumber":"s / n",
    "addr:postcode":"29600",
    "addr:street":"Urb Santa Margarita;Ma\u0301Laga",
    "iso:country":"ES",
    "sg:address":"Urb Santa Margarita, S/n",
    "sg:city":"Marbella",
    "sg:orig_category":"Centros Empresariales",
    "sg:phone":"+34 952 90 31 85",
    "sg:postcode":"29600",
    "sg:province":"M\u00e1laga",
    "wof:name":"Dhalmenhy S.l.",
    "wof:placetype":"venue"
},
  "geometry": {"coordinates":[-4.9143362045,36.5054244995],"type":"Point"}
}