{
  "type": "Feature",
  "properties": {
    "addr:full":"Calle de Cantarranas, 49 Alhaurin Torre M\u00e1laga 29130",
    "addr:housenumber":"49",
    "addr:postcode":"29130",
    "addr:street":"Calle De Cantarranas",
    "iso:country":"ES",
    "sg:address":"Calle de Cantarranas, 49",
    "sg:city":"Alhaurin Torre",
    "sg:orig_category":"Cristaler\u00cdas",
    "sg:phone":"+34 952 96 04 43",
    "sg:postcode":"29130",
    "sg:province":"M\u00e1laga",
    "wof:name":"Juan Moreno Mu\u00f1oz S.l.",
    "wof:placetype":"venue"
},
  "geometry": {"coordinates":[-4.5592026711,36.6630592346],"type":"Point"}
}