{
  "type": "Feature",
  "properties": {
    "addr:full":"Calle de Cuba, 3 Vitoria-gasteiz \u00c1lava 01012",
    "addr:housenumber":"3",
    "addr:postcode":"01012",
    "addr:street":"Calle De Cuba",
    "iso:country":"ES",
    "sg:address":"Calle de Cuba, 3",
    "sg:city":"Vitoria-gasteiz",
    "sg:orig_category":"Peluqueros: De Se\u00d1oras",
    "sg:phone":"+34 945 25 82 69",
    "sg:postcode":"01012",
    "sg:province":"\u00c1lava",
    "wof:name":"Mu\u00f1oz Rubiano Luisa",
    "wof:placetype":"venue"
},
  "geometry": {"coordinates":[-2.6800718307,42.8582000732],"type":"Point"}
}