{
  "type": "Feature",
  "properties": {
    "addr:full":"Avgd Prat De La Riba, 49 Lleida Lleida 25008",
    "addr:housenumber":"49",
    "addr:postcode":"25008",
    "addr:street":"La Riba",
    "iso:country":"ES",
    "sg:address":"Avgd Prat De La Riba, 49",
    "sg:city":"Lleida",
    "sg:classifiers":[
        {
            "category":"Personal",
            "subcategory":"Barber",
            "type":"Services"
        }
    ],
    "sg:phone":"+34 973 22 43 41",
    "sg:postcode":"25008",
    "sg:province":"Lleida",
    "sg:tags":[
        "caballeros",
        "de",
        "peluqueros"
    ],
    "wof:name":"Domenech Ganau Abel Mario",
    "wof:placetype":"venue"
},
  "geometry": {"coordinates":[0.6242250204,41.6212882996],"type":"Point"}
}