{
  "type": "Feature",
  "properties": {
    "addr:full":"Santa Ana Albaida, 18 Santa Ana Albaida C\u00f3rdoba 14011",
    "addr:housenumber":"18",
    "addr:postcode":"14011",
    "addr:street":"Albaida",
    "iso:country":"ES",
    "sg:address":"Santa Ana Albaida, 18",
    "sg:city":"Santa Ana Albaida",
    "sg:orig_category":"Materias Pl\u00c1sticas: Productos De Consumo Masivo (fabricaci\u00d3n, Al Por Mayor)",
    "sg:phone":"+34 957 28 28 27",
    "sg:postcode":"14011",
    "sg:province":"C\u00f3rdoba",
    "wof:name":"Viedma Godino Manuel",
    "wof:placetype":"venue"
},
  "geometry": {"coordinates":[-4.8999910355,37.9277877808],"type":"Point"}
}