{
  "type": "Feature",
  "properties": {
    "iso:country":"ES",
    "sg:address":"Carrer de Rossello, 216",
    "sg:city":"Barcelona",
    "sg:orig_category":"Inmobiliaria (agencias)",
    "sg:phone":"+34 934 87 09 93",
    "sg:postcode":"08008",
    "sg:province":"Barcelona",
    "wof:name":"Imisa S. A.",
    "wof:placetype":"venue"
},
  "geometry": {"coordinates":[2.1592400074,41.3945617676],"type":"Point"}
}