{
  "type": "Feature",
  "properties": {
    "addr:full":"Calle de Iru\u00d1alde, 8 Berriozar Navarra 31013",
    "addr:housenumber":"8",
    "addr:postcode":"31013",
    "addr:street":"Calle De Irun\u0303Alde",
    "iso:country":"ES",
    "sg:address":"Calle de Iru\u00d1alde, 8",
    "sg:city":"Berriozar",
    "sg:orig_category":"Promotores Constructores",
    "sg:phone":"+34 948 30 02 29",
    "sg:postcode":"31013",
    "sg:province":"Navarra",
    "wof:name":"Morales Toro Felipe",
    "wof:placetype":"venue"
},
  "geometry": {"coordinates":[-1.6750119925,42.8368988037],"type":"Point"}
}