{
  "type": "Feature",
  "properties": {
    "iso:country":"ES",
    "sg:address":"Calle de Roque Calero Fajardo, 7",
    "sg:city":"Pto. Rosario",
    "sg:orig_category":"Garajes De Veh\u00cdculos",
    "sg:phone":"+34 928 85 91 77",
    "sg:postcode":"35600",
    "sg:province":"Las Palmas",
    "wof:name":"Hernandez Vera Jose Manuel",
    "wof:placetype":"venue"
},
  "geometry": {"coordinates":[-13.8676319122,28.5020008087],"type":"Point"}
}