{
  "type": "Feature",
  "properties": {
    "addr:full":"Mestre Benages, 4 Sedavi Valencia 46910",
    "addr:housenumber":"4",
    "addr:postcode":"46910",
    "addr:street":"Benages",
    "iso:country":"ES",
    "sg:address":"Mestre Benages, 4",
    "sg:city":"Sedavi",
    "sg:orig_category":"Expertos Contables, Revisores De Cuentas",
    "sg:phone":"+34 963 96 20 48",
    "sg:postcode":"46910",
    "sg:province":"Valencia",
    "wof:name":"Baixauli Chornet Josefa",
    "wof:placetype":"venue"
},
  "geometry": {"coordinates":[-0.3867915869,39.4251251221],"type":"Point"}
}