{
  "type": "Feature",
  "properties": {
    "addr:full":"Calle de Abdon Bordoy (de), 40 Aranjuez Madrid 28300",
    "addr:housenumber":"40",
    "addr:postcode":"28300",
    "addr:street":"Calle De Abdon Bordoy De",
    "iso:country":"ES",
    "sg:address":"Calle de Abdon Bordoy (de), 40",
    "sg:city":"Aranjuez",
    "sg:orig_category":"Caf\u00c9s, Bares, Cervecer\u00cdas",
    "sg:phone":"+34 918 91 83 29",
    "sg:postcode":"28300",
    "sg:province":"Madrid",
    "wof:name":"Diezma Molina Luis Angel",
    "wof:placetype":"venue"
},
  "geometry": {"coordinates":[-3.5946404934,40.0303878784],"type":"Point"}
}