{
  "type": "Feature",
  "properties": {
    "iso:country":"ES",
    "sg:address":"Calle de Cronista Carlos Valcarcel, 3",
    "sg:city":"Santa Maria De Gracia",
    "sg:orig_category":"Telas Y Sedas (al Por Menor)",
    "sg:phone":"+34 968 23 88 12",
    "sg:postcode":"30008",
    "sg:province":"Murcia",
    "wof:name":"Sanchez Esteban Rosario",
    "wof:placetype":"venue"
},
  "geometry": {"coordinates":[-1.1298867464,37.9834747314],"type":"Point"}
}