{
  "type": "Feature",
  "properties": {
    "addr:full":"Poligono 9, S/n Montu\u00efri Islas Baleares 07230",
    "addr:housenumber":"s / n",
    "addr:postcode":"07230",
    "addr:street":"Poligono 9",
    "iso:country":"ES",
    "sg:address":"Poligono 9, S/n",
    "sg:city":"Montu\u00efri",
    "sg:orig_category":"Organismos De Turismo",
    "sg:phone":"+34 971 64 41 92",
    "sg:postcode":"07230",
    "sg:province":"Islas Baleares",
    "wof:name":"Ribas Moll Antonio",
    "wof:placetype":"venue"
},
  "geometry": {"coordinates":[2.9797410965,39.5655670166],"type":"Point"}
}