{
  "type": "Feature",
  "properties": {
    "iso:country":"ES",
    "sg:address":"Ctra Ba\u00d1os (los), S/n",
    "sg:city":"Mahoya",
    "sg:orig_category":"Centros De Educaci\u00d3n Especial",
    "sg:phone":"+34 968 68 04 25",
    "sg:postcode":"30640",
    "sg:province":"Murcia",
    "wof:name":"Colegio Publico 3 De Mayo",
    "wof:placetype":"venue"
},
  "geometry": {"coordinates":[-1.0593090057,38.2154808044],"type":"Point"}
}