{
  "type": "Feature",
  "properties": {
    "addr:full":"Carr Carmel, 52 Palamos Girona 17230",
    "addr:housenumber":"52",
    "addr:postcode":"17230",
    "addr:street":"Carr Carmel",
    "iso:country":"ES",
    "sg:address":"Carr Carmel, 52",
    "sg:city":"Palamos",
    "sg:orig_category":"Inform\u00c1tica, Ofim\u00c1tica (estudios, Asesor\u00cda, Ingenier\u00cda, Formaci\u00d3n)",
    "sg:phone":"+34 972 60 08 50",
    "sg:postcode":"17230",
    "sg:province":"Girona",
    "sg:website":"www.grupo-sil.com",
    "wof:name":"Sil Palamos S.l.",
    "wof:placetype":"venue"
},
  "geometry": {"coordinates":[3.1279499531,41.8473548889],"type":"Point"}
}