{
  "type": "Feature",
  "properties": {
    "addr:full":"Avda Rey Don Jaime, 62 Castellon Castell\u00f3n 12001",
    "addr:housenumber":"62",
    "addr:postcode":"12001",
    "addr:street":"Avda Rey Don Jaime",
    "iso:country":"ES",
    "sg:address":"Avda Rey Don Jaime, 62",
    "sg:city":"Castellon",
    "sg:orig_category":"Institutos De Belleza",
    "sg:phone":"+34 964 25 55 69",
    "sg:postcode":"12001",
    "sg:province":"Castell\u00f3n",
    "wof:name":"Gonzalez-espresati Amian Maria Del Carmen",
    "wof:placetype":"venue"
},
  "geometry": {"coordinates":[-0.0390199982,39.9866409302],"type":"Point"}
}