{
  "type": "Feature",
  "properties": {
    "addr:full":"Ctra Cari\u00d1ena, S/n Almunia De Do\u00e7a Godina Zaragoza 50100",
    "addr:housenumber":"s / n",
    "addr:postcode":"50100",
    "addr:street":"Ctra Carin\u0303Ena",
    "iso:country":"ES",
    "sg:address":"Ctra Cari\u00d1ena, S/n",
    "sg:city":"Almunia De Do\u00e7a Godina",
    "sg:orig_category":"Producci\u00d3n, Venta De Productos De Agricultura Biol\u00d3gica",
    "sg:phone":"+34 976 60 05 40",
    "sg:postcode":"50100",
    "sg:province":"Zaragoza",
    "wof:name":"Bueno Lajusticia Juan Jose",
    "wof:placetype":"venue"
},
  "geometry": {"coordinates":[-1.3716549873,41.4743041992],"type":"Point"}
}