{
  "type": "Feature",
  "properties": {
    "iso:country":"ES",
    "sg:address":"Carr Germanes Massanet, 3",
    "sg:city":"Figueres",
    "sg:orig_category":"Complementos De Vestir (al Por Menor)",
    "sg:phone":"+34 972 50 70 67",
    "sg:postcode":"17600",
    "sg:province":"Girona",
    "sg:website":"www.tous.com",
    "wof:name":"Tous Joiers Girona S.l.",
    "wof:placetype":"venue"
},
  "geometry": {"coordinates":[2.9620060921,42.2678108215],"type":"Point"}
}