{
  "type": "Feature",
  "properties": {
    "addr:full":"Malpaises, S/n Malpaises Santa Cruz De Tenerife 38738",
    "addr:postcode":"38738",
    "addr:street":"Malpaises S / N Malpaises",
    "iso:country":"ES",
    "sg:address":"Malpaises, S/n",
    "sg:city":"Malpaises",
    "sg:orig_category":"Venta, Montaje De Neum\u00c1ticos",
    "sg:phone":"+34 922 42 80 23",
    "sg:postcode":"38738",
    "sg:province":"Santa Cruz De Tenerife",
    "wof:name":"Centros De Ahorro San Martin S.l.",
    "wof:placetype":"venue"
},
  "geometry": {"coordinates":[-17.8155479431,28.5352420807],"type":"Point"}
}