{
  "type": "Feature",
  "properties": {
    "iso:country":"ES",
    "sg:address":"Plaz Mayor, 2",
    "sg:city":"Santos Humosa",
    "sg:orig_category":"Administraciones Regionales, Departamentales Y Locales",
    "sg:phone":"+34 918 84 80 01",
    "sg:postcode":"28817",
    "sg:province":"Madrid",
    "wof:name":"Ayuntamiento Los Santos De La Humosa",
    "wof:placetype":"venue"
},
  "geometry": {"coordinates":[-3.2578394413,40.5018615723],"type":"Point"}
}