{
  "type": "Feature",
  "properties": {
    "addr:full":"Calle de Ciscar, 52 Valencia Valencia 46005",
    "addr:housenumber":"52",
    "addr:postcode":"46005",
    "addr:street":"Calle De Ciscar",
    "iso:country":"ES",
    "sg:address":"Calle de Ciscar, 52",
    "sg:city":"Valencia",
    "sg:orig_category":"Ropa Para Ni\u00d1os (al Por Menor)",
    "sg:phone":"+34 963 95 99 46",
    "sg:postcode":"46005",
    "sg:province":"Valencia",
    "wof:name":"Perellon Marti Rosario",
    "wof:placetype":"venue"
},
  "geometry": {"coordinates":[-0.3644460142,39.4642601013],"type":"Point"}
}