{
  "type": "Feature",
  "properties": {
    "addr:full":"Calle de Calderon De La Barca (de), S/n Navalcarnero Madrid 28600",
    "addr:postcode":"28600",
    "addr:street":"Calle De Calderon De La Barca De S / N",
    "iso:country":"ES",
    "sg:address":"Calle de Calderon De La Barca (de), S/n",
    "sg:city":"Navalcarnero",
    "sg:orig_category":"Carnicer\u00cdas, Carnicer\u00cdas",
    "sg:phone":"+34 918 11 26 80",
    "sg:postcode":"28600",
    "sg:province":"Madrid",
    "wof:name":"Leal Lopez Jose Luis",
    "wof:placetype":"venue"
},
  "geometry": {"coordinates":[-4.0131258965,40.2861633301],"type":"Point"}
}