{
  "type": "Feature",
  "properties": {
    "addr:full":"Ctra Puente Ayuda, Km. 0011,0 Olivenza Badajoz 06100",
    "addr:postcode":"06100",
    "addr:street":"Ctra Puente Ayuda Km. 0011,0",
    "iso:country":"ES",
    "sg:address":"Ctra Puente Ayuda, Km. 0011,0",
    "sg:city":"Olivenza",
    "sg:orig_category":"Productores Recolectores, Venta Directa De Vinos",
    "sg:phone":"+34 924 12 62 80",
    "sg:postcode":"06100",
    "sg:province":"Badajoz",
    "wof:name":"Sat Las Mesas Del Rio",
    "wof:placetype":"venue"
},
  "geometry": {"coordinates":[-7.0980839729,38.6843605042],"type":"Point"}
}