{
  "type": "Feature",
  "properties": {
    "addr:full":"Calle de Maria Cristina, 1 Santander Cantabria 39001",
    "addr:housenumber":"1",
    "addr:postcode":"39001",
    "addr:street":"Calle De Maria Cristina",
    "iso:country":"ES",
    "sg:address":"Calle de Maria Cristina, 1",
    "sg:city":"Santander",
    "sg:orig_category":"Mercer\u00cda, Lencer\u00cda (al Por Menor)",
    "sg:phone":"+34 942 22 59 34",
    "sg:postcode":"39001",
    "sg:province":"Cantabria",
    "wof:name":"Magaldi Dosuna Veronica Yasmina",
    "wof:placetype":"venue"
},
  "geometry": {"coordinates":[-3.8074979782,43.4663467407],"type":"Point"}
}