{
  "type": "Feature",
  "properties": {
    "addr:full":"Avda Galtzaraborda, 55 Errenteria Guip\u00f9zcoa 20100",
    "addr:housenumber":"55",
    "addr:postcode":"20100",
    "addr:street":"Avda Galtzaraborda;Guipu\u0300Zcoa",
    "iso:country":"ES",
    "sg:address":"Avda Galtzaraborda, 55",
    "sg:city":"Errenteria",
    "sg:orig_category":"Fotograf\u00cda Art\u00cdstica Y Retratos",
    "sg:phone":"+34 943 51 32 82",
    "sg:postcode":"20100",
    "sg:province":"Guip\u00f9zcoa",
    "wof:name":"Rosa Maria Novo  (foto Gabin)",
    "wof:placetype":"venue"
},
  "geometry": {"coordinates":[-1.9121400118,43.3112487793],"type":"Point"}
}