{
  "type": "Feature",
  "properties": {
    "addr:full":"Avda Castillo, 87 Lora Rio Sevilla 41440",
    "addr:housenumber":"87",
    "addr:postcode":"41440",
    "addr:street":"Avda Castillo;Rio Sevilla",
    "iso:country":"ES",
    "sg:address":"Avda Castillo, 87",
    "sg:city":"Lora Rio",
    "sg:orig_category":"Agentes, Concesionarios Y Sucursales De Veh\u00cdculos",
    "sg:phone":"+34 955 80 27 29",
    "sg:postcode":"41440",
    "sg:province":"Sevilla",
    "wof:name":"Hijos De Francisco Barrios Sanchez",
    "wof:placetype":"venue"
},
  "geometry": {"coordinates":[-5.534052372,37.65599823],"type":"Point"}
}