{
  "type": "Feature",
  "properties": {
    "iso:country":"ES",
    "sg:address":"Calle de San Marcial, 50",
    "sg:city":"Donostia-san Sebastian",
    "sg:orig_category":"M\u00c9dicos: Estomatolog\u00cda",
    "sg:phone":"+34 943 42 93 93",
    "sg:postcode":"20005",
    "sg:province":"Guip\u00f9zcoa",
    "wof:name":"Ortiz De Arti\u00f1ano Kutz Pedro",
    "wof:placetype":"venue"
},
  "geometry": {"coordinates":[-1.9842319489,43.3180732727],"type":"Point"}
}