{
  "type": "Feature",
  "properties": {
    "addr:full":"Carr Pau Claris, 16 Lleida Lleida 25008",
    "addr:housenumber":"16",
    "addr:postcode":"25008",
    "addr:street":"Carr Pau Claris",
    "iso:country":"ES",
    "sg:address":"Carr Pau Claris, 16",
    "sg:city":"Lleida",
    "sg:orig_category":"Venta, Instalaci\u00d3n, Reparaci\u00d3n De Antenas Para Televisi\u00d3n",
    "sg:phone":"+34 973 23 84 25",
    "sg:postcode":"25008",
    "sg:province":"Lleida",
    "wof:name":"Lopez Pontaque Antonio",
    "wof:placetype":"venue"
},
  "geometry": {"coordinates":[0.6213700175,41.6220588684],"type":"Point"}
}