{
  "type": "Feature",
  "properties": {
    "iso:country":"ES",
    "sg:address":"Avda Ebro, 65",
    "sg:city":"Agoncillo",
    "sg:orig_category":"Contenedores (mercanc\u00cdas)",
    "sg:phone":"+34 941 48 61 21",
    "sg:postcode":"26509",
    "sg:province":"La Rioja",
    "wof:name":"Car Volum S.l.",
    "wof:placetype":"venue"
},
  "geometry": {"coordinates":[-2.1222639084,42.4031410217],"type":"Point"}
}