{
  "type": "Feature",
  "properties": {
    "addr:full":"Avda Apostoles, 11 Madrid Madrid 28011",
    "addr:housenumber":"11",
    "addr:postcode":"madrid;28011",
    "addr:street":"Avda Apostoles",
    "iso:country":"ES",
    "sg:address":"Avda Apostoles, 11",
    "sg:city":"Madrid",
    "sg:orig_category":"Poller\u00cda Y Caza (al Por Menor)",
    "sg:phone":"+34 914 79 58 20",
    "sg:postcode":"28011",
    "sg:province":"Madrid",
    "wof:name":"Perez Palazuelos Carlos",
    "wof:placetype":"venue"
},
  "geometry": {"coordinates":[-3.7395329475,40.4060211182],"type":"Point"}
}