{
  "type": "Feature",
  "properties": {
    "addr:full":"Mayor-nagusia Kalea, 74 Iru\u00f1a Navarra 31001",
    "addr:housenumber":"74",
    "addr:postcode":"31001",
    "addr:street":"Mayor-Nagusia Kalea",
    "iso:country":"ES",
    "sg:address":"Mayor-nagusia Kalea, 74",
    "sg:city":"Iru\u00f1a",
    "sg:orig_category":"Iglesia Cat\u00d3lica",
    "sg:phone":"+34 948 22 53 71",
    "sg:postcode":"31001",
    "sg:province":"Navarra",
    "wof:name":"Parroquia De San Lorenzo",
    "wof:placetype":"venue"
},
  "geometry": {"coordinates":[-1.6490240097,42.817150116],"type":"Point"}
}