{
  "type": "Feature",
  "properties": {
    "addr:full":"Calle de Santo Domingo, 140 Victoria Acentejo Santa Cruz De Tenerife 38380",
    "addr:housenumber":"140",
    "addr:postcode":"38380",
    "addr:street":"Calle De Santo Domingo",
    "iso:country":"ES",
    "sg:address":"Calle de Santo Domingo, 140",
    "sg:city":"Victoria Acentejo",
    "sg:orig_category":"Cr\u00cda De Animales",
    "sg:phone":"+34 922 58 21 79",
    "sg:postcode":"38380",
    "sg:province":"Santa Cruz De Tenerife",
    "wof:name":"Distribuciones Teide Zoo S.l.",
    "wof:placetype":"venue"
},
  "geometry": {"coordinates":[-16.4764118195,28.4340553284],"type":"Point"}
}