{
  "type": "Feature",
  "properties": {
    "iso:country":"ES",
    "sg:address":"Carrer de Colom, 13",
    "sg:city":"Sabadell",
    "sg:orig_category":"Farmacias",
    "sg:phone":"+34 937 25 07 77",
    "sg:postcode":"08201",
    "sg:province":"Barcelona",
    "wof:name":"Crusafont Sabate Ana Maria",
    "wof:placetype":"venue"
},
  "geometry": {"coordinates":[2.1056079865,41.5469703674],"type":"Point"}
}