{
  "type": "Feature",
  "properties": {
    "addr:full":"Calle de San Ramon, 66 Churriana Vega Granada 18194",
    "addr:housenumber":"66",
    "addr:postcode":"18194",
    "addr:street":"Calle De San Ramon",
    "iso:country":"ES",
    "sg:address":"Calle de San Ramon, 66",
    "sg:city":"Churriana Vega",
    "sg:orig_category":"Molduras, Junquillos, Listones Y Molduras Perforadas",
    "sg:phone":"+34 958 57 00 61",
    "sg:postcode":"18194",
    "sg:province":"Granada",
    "wof:name":"Megias Salas Jose Manuel",
    "wof:placetype":"venue"
},
  "geometry": {"coordinates":[-3.6773679256,37.1503562927],"type":"Point"}
}