{
  "type": "Feature",
  "properties": {
    "addr:full":"Calle de Martin De Los Heros, 17 Madrid Madrid 28008",
    "addr:housenumber":"17",
    "addr:postcode":"madrid;28008",
    "addr:street":"Calle De Martin De Los Heros",
    "iso:country":"ES",
    "sg:address":"Calle de Martin De Los Heros, 17",
    "sg:city":"Madrid",
    "sg:orig_category":"Ropa Para Ni\u00d1os (al Por Menor)",
    "sg:phone":"+34 915 42 34 06",
    "sg:postcode":"28008",
    "sg:province":"Madrid",
    "wof:name":"Molinos Alcantara Natalia",
    "wof:placetype":"venue"
},
  "geometry": {"coordinates":[-3.7142004967,40.4251441956],"type":"Point"}
}