{
  "type": "Feature",
  "properties": {
    "addr:full":"Av America, 136 Mataro Barcelona 08304",
    "addr:housenumber":"136",
    "addr:postcode":"08304",
    "addr:street":"Av America",
    "iso:country":"ES",
    "sg:address":"Av America, 136",
    "sg:city":"Mataro",
    "sg:orig_category":"Institutos De Belleza",
    "sg:phone":"+34 937 90 63 64",
    "sg:postcode":"08304",
    "sg:province":"Barcelona",
    "wof:name":"Centro Estetica Shir-kham S.l.",
    "wof:placetype":"venue"
},
  "geometry": {"coordinates":[2.4519629478,41.5468864441],"type":"Point"}
}