{
  "type": "Feature",
  "properties": {
    "iso:country":"ES",
    "sg:address":"Carr Teuleries, 10",
    "sg:city":"Lleida",
    "sg:orig_category":"Audiovisuales, Tv, Hi",
    "sg:phone":"+34 973 22 43 47",
    "sg:postcode":"25004",
    "sg:province":"Lleida",
    "wof:name":"Uroz Gonzalez Neus",
    "wof:placetype":"venue"
},
  "geometry": {"coordinates":[0.6214939952,41.6194152832],"type":"Point"}
}