{
  "type": "Feature",
  "properties": {
    "addr:full":"Carrer de Barcelona, 150 S. Fost Campsentelles Barcelona 08105",
    "addr:housenumber":"150",
    "addr:postcode":"08105",
    "addr:street":"Carrer De Barcelona;S. Fost",
    "iso:country":"ES",
    "sg:address":"Carrer de Barcelona, 150",
    "sg:city":"S. Fost Campsentelles",
    "sg:orig_category":"Fabricaci\u00d3n De Moldes Y Modelos",
    "sg:phone":"+34 935 79 00 55",
    "sg:postcode":"08105",
    "sg:province":"Barcelona",
    "wof:name":"Industrias Plaspe S.l.",
    "wof:placetype":"venue"
},
  "geometry": {"coordinates":[2.2235069275,41.5291366577],"type":"Point"}
}