{
  "type": "Feature",
  "properties": {
    "iso:country":"ES",
    "sg:address":"Calle de Bravo Murillo, 25",
    "sg:city":"Madrid",
    "sg:orig_category":"Farmacias",
    "sg:phone":"+34 914 46 35 78",
    "sg:postcode":"28015",
    "sg:province":"Madrid",
    "wof:name":"Dominguez Chillon Milagros",
    "wof:placetype":"venue"
},
  "geometry": {"coordinates":[-3.7043364048,40.4358978271],"type":"Point"}
}