{
  "type": "Feature",
  "properties": {
    "iso:country":"ES",
    "sg:address":"Avda Pintor Portela, 38",
    "sg:city":"Cartagena",
    "sg:orig_category":"Inform\u00c1tica: Material Y Suministros",
    "sg:phone":"+34 968 50 01 76",
    "sg:postcode":"30203",
    "sg:province":"Murcia",
    "wof:name":"Overlay S.a.l.",
    "wof:placetype":"venue"
},
  "geometry": {"coordinates":[-0.972217977,37.6102676392],"type":"Point"}
}