{
  "type": "Feature",
  "properties": {
    "iso:country":"ES",
    "sg:address":"Pol Ind La Vi\u00f1a, 34",
    "sg:city":"Algaba",
    "sg:orig_category":"Paneles De Madera: Contrachapados, Fibras, Particulados, Estratificados (fabricaci\u00d3n, Venta)",
    "sg:phone":"+34 954 38 42 58",
    "sg:postcode":"41980",
    "sg:province":"Sevilla",
    "wof:name":"Marco Gutierrez Alvaro",
    "wof:placetype":"venue"
},
  "geometry": {"coordinates":[-6.0153942108,37.4607162476],"type":"Point"}
}