{
  "type": "Feature",
  "properties": {
    "addr:full":"Calle de San Sebastian, 46 Santa Cruz De Mudela Ciudad Real 13730",
    "addr:housenumber":"46",
    "addr:postcode":"13730",
    "addr:street":"Calle De San Sebastian",
    "iso:country":"ES",
    "sg:address":"Calle de San Sebastian, 46",
    "sg:city":"Santa Cruz De Mudela",
    "sg:orig_category":"Congelados: Productos Alimentarios (al Por Menor)",
    "sg:phone":"+34 926 33 12 97",
    "sg:postcode":"13730",
    "sg:province":"Ciudad Real",
    "wof:name":"Martinez Nieto Brigida",
    "wof:placetype":"venue"
},
  "geometry": {"coordinates":[-3.4628090858,38.642250061],"type":"Point"}
}