{
  "type": "Feature",
  "properties": {
    "iso:country":"ES",
    "sg:address":"Calle de Almarza, 66",
    "sg:city":"Madrid",
    "sg:orig_category":"Instalaci\u00d3n De Sanitarios",
    "sg:phone":"+34 913 83 84 03",
    "sg:postcode":"28033",
    "sg:province":"Madrid",
    "sg:website":"www.alianzahispanoamericanadereiki.org",
    "wof:name":"Moraga Rodriguez Antonio",
    "wof:placetype":"venue"
},
  "geometry": {"coordinates":[-3.6605734825,40.4684906006],"type":"Point"}
}