{
  "type": "Feature",
  "properties": {
    "addr:full":"Carrer de Monterols, 10 Reus Tarragona 43201",
    "addr:housenumber":"10",
    "addr:postcode":"43201",
    "addr:street":"Carrer De Monterols",
    "iso:country":"ES",
    "sg:address":"Carrer de Monterols, 10",
    "sg:city":"Reus",
    "sg:orig_category":"Ense\u00d1anza Variada",
    "sg:phone":"+34 977 34 13 02",
    "sg:postcode":"43201",
    "sg:province":"Tarragona",
    "wof:name":"Academia De Ingles Tower English C.b.",
    "wof:placetype":"venue"
},
  "geometry": {"coordinates":[1.108072,41.155319],"type":"Point"}
}