{
  "type": "Feature",
  "properties": {
    "addr:full":"Avda Recomba (de La), 1 Leganes Madrid 28914",
    "addr:housenumber":"1",
    "addr:postcode":"28914",
    "addr:street":"Avda Recomba De La",
    "iso:country":"ES",
    "sg:address":"Avda Recomba (de La), 1",
    "sg:city":"Leganes",
    "sg:orig_category":"Tratamiento De Metales",
    "sg:phone":"+34 916 81 38 00",
    "sg:postcode":"28914",
    "sg:province":"Madrid",
    "wof:name":"Trategal S. L.",
    "wof:placetype":"venue"
},
  "geometry": {"coordinates":[-3.7786369324,40.3098106384],"type":"Point"}
}