{
  "type": "Feature",
  "properties": {
    "addr:full":"Calle de Segovia, 11 S. Pedro Pinatar Murcia 30740",
    "addr:housenumber":"11",
    "addr:postcode":"30740",
    "addr:street":"Calle De Segovia;S. Pedro",
    "iso:country":"ES",
    "sg:address":"Calle de Segovia, 11",
    "sg:city":"S. Pedro Pinatar",
    "sg:orig_category":"Empresas De Carpinter\u00cda De Madera",
    "sg:phone":"+34 968 18 08 94",
    "sg:postcode":"30740",
    "sg:province":"Murcia",
    "wof:name":"Tarraga Zapata Antonio",
    "wof:placetype":"venue"
},
  "geometry": {"coordinates":[-0.7879700065,37.8333091736],"type":"Point"}
}