{
  "type": "Feature",
  "properties": {
    "iso:country":"ES",
    "sg:address":"Calle de Del Ca\u00d1o, 1",
    "sg:city":"Garciaz",
    "sg:classifiers":[
        {
            "category":"Taxi",
            "type":"Transportation"
        }
    ],
    "sg:phone":"+34 927 33 20 39",
    "sg:postcode":"10250",
    "sg:province":"C\u00e1ceres",
    "wof:name":"Fernandez Holgado Jacinta",
    "wof:placetype":"venue"
},
  "geometry": {"coordinates":[-5.6285295486,39.4131469727],"type":"Point"}
}