{
  "type": "Feature",
  "properties": {
    "iso:country":"ES",
    "sg:address":"Avda Monforte, 1",
    "sg:city":"Chantada",
    "sg:orig_category":"Parafarmacias",
    "sg:phone":"+34 982 46 20 96",
    "sg:postcode":"27500",
    "sg:province":"Lugo",
    "wof:name":"Tomba Pacio C.b.",
    "wof:placetype":"venue"
},
  "geometry": {"coordinates":[-7.7580590248,42.6079902649],"type":"Point"}
}