{
  "type": "Feature",
  "properties": {
    "addr:full":"Calle de Roteta Goikoa, 2 Donostia-san Sebastian Guip\u00f9zcoa 20017",
    "addr:housenumber":"2",
    "addr:postcode":"20017",
    "addr:street":"Calle De Roteta Goikoa",
    "iso:country":"ES",
    "sg:address":"Calle de Roteta Goikoa, 2",
    "sg:city":"Donostia-san Sebastian",
    "sg:orig_category":"Ropa Para Se\u00d1oras (al Por Menor)",
    "sg:phone":"+34 943 35 00 29",
    "sg:postcode":"20017",
    "sg:province":"Guip\u00f9zcoa",
    "wof:name":"Montes Curto Maria Josefa",
    "wof:placetype":"venue"
},
  "geometry": {"coordinates":[-1.9304300547,43.3179206848],"type":"Point"}
}