{
  "type": "Feature",
  "properties": {
    "iso:country":"ES",
    "sg:address":"Calle de Bodegones, 14",
    "sg:city":"Cartagena",
    "sg:classifiers":[
        {
            "category":"Casinos & Gambling",
            "type":"Entertainment"
        }
    ],
    "sg:phone":"+34 968 52 55 77",
    "sg:postcode":"30201",
    "sg:province":"Murcia",
    "sg:tags":[
        "locale",
        "de",
        "juego"
    ],
    "wof:name":"Casino De Cartagena",
    "wof:placetype":"venue"
},
  "geometry": {"coordinates":[-0.9865161777,37.5998802185],"type":"Point"}
}