{
  "type": "Feature",
  "properties": {
    "addr:full":"Calle de Enmedio, 21 Torrejon Ardoz Madrid 28850",
    "addr:housenumber":"21",
    "addr:postcode":"28850",
    "addr:street":"Calle De Enmedio",
    "iso:country":"ES",
    "sg:address":"Calle de Enmedio, 21",
    "sg:city":"Torrejon Ardoz",
    "sg:orig_category":"\u00d3ptica: Instrumentos (fabricaci\u00d3n)",
    "sg:phone":"+34 916 56 85 28",
    "sg:postcode":"28850",
    "sg:province":"Madrid",
    "wof:name":"Opticas San Gabino 2025 S.l.",
    "wof:placetype":"venue"
},
  "geometry": {"coordinates":[-3.4789009094,40.4572219849],"type":"Point"}
}