{
  "type": "Feature",
  "properties": {
    "addr:full":"Calle de Lezeaga, 8 Bilbao Vizcaya 48002",
    "addr:housenumber":"8",
    "addr:postcode":"48002",
    "addr:street":"Calle De Lezeaga",
    "iso:country":"ES",
    "sg:address":"Calle de Lezeaga, 8",
    "sg:city":"Bilbao",
    "sg:orig_category":"Explotaci\u00d3n De Canteras",
    "sg:phone":"+34 944 27 44 04",
    "sg:postcode":"48002",
    "sg:province":"Vizcaya",
    "wof:name":"Hormigones Basurto S.l.",
    "wof:placetype":"venue"
},
  "geometry": {"coordinates":[-2.955714941,43.2592315674],"type":"Point"}
}