{
  "type": "Feature",
  "properties": {
    "addr:full":"Avda Toledo, S/n Estepona M\u00e1laga 29680",
    "addr:postcode":"29680",
    "addr:street":"Avda Toledo S / N;Ma\u0301Laga",
    "iso:country":"ES",
    "sg:address":"Avda Toledo, S/n",
    "sg:city":"Estepona",
    "sg:orig_category":"Muebles Y Accesorios Para Cocinas Y Cuartos De Ba\u00d1o (al Por Menor)",
    "sg:phone":"+34 951 31 81 77",
    "sg:postcode":"29680",
    "sg:province":"M\u00e1laga",
    "wof:name":"Martinez Exposito Asuncion",
    "wof:placetype":"venue"
},
  "geometry": {"coordinates":[-5.1403484344,36.4305725098],"type":"Point"}
}