{
  "type": "Feature",
  "properties": {
    "iso:country":"ES",
    "sg:address":"Carr Borrassa, 6",
    "sg:city":"Figueres",
    "sg:orig_category":"Librer\u00cdas",
    "sg:phone":"+34 972 51 14 25",
    "sg:postcode":"17600",
    "sg:province":"Girona",
    "wof:name":"Casta\u00f1e Vilagran Roser",
    "wof:placetype":"venue"
},
  "geometry": {"coordinates":[2.966283083,42.2599105835],"type":"Point"}
}