{
  "type": "Feature",
  "properties": {
    "addr:full":"Plaz Mayor, 4 Aldeaseca De Armu\u00e7a Salamanca 37189",
    "addr:housenumber":"4",
    "addr:postcode":"37189",
    "addr:street":"Plaz Mayor",
    "iso:country":"ES",
    "sg:address":"Plaz Mayor, 4",
    "sg:city":"Aldeaseca De Armu\u00e7a",
    "sg:orig_category":"Caf\u00c9s, Bares, Cervecer\u00cdas",
    "sg:phone":"+34 923 24 66 04",
    "sg:postcode":"37189",
    "sg:province":"Salamanca",
    "wof:name":"Mori\u00f1igo Santos Ramiro",
    "wof:placetype":"venue"
},
  "geometry": {"coordinates":[-5.6705870628,41.0207595825],"type":"Point"}
}