{
  "type": "Feature",
  "properties": {
    "addr:full":"Carr Mallorca, De, 31 Sant Ferran De Ses Roques Islas Baleares 07871",
    "addr:housenumber":"31",
    "addr:postcode":"07871",
    "addr:street":"Carr Mallorca De",
    "iso:country":"ES",
    "sg:address":"Carr Mallorca, De, 31",
    "sg:city":"Sant Ferran De Ses Roques",
    "sg:orig_category":"Tatuajes",
    "sg:phone":"+34 971 32 88 93",
    "sg:postcode":"07871",
    "sg:province":"Islas Baleares",
    "wof:name":"Puntito Formentera Cb",
    "wof:placetype":"venue"
},
  "geometry": {"coordinates":[1.4565550089,38.7221031189],"type":"Point"}
}