{
  "type": "Feature",
  "properties": {
    "addr:full":"Calle de Real, 55 Lanjaron Granada 18420",
    "addr:housenumber":"55",
    "addr:postcode":"18420",
    "addr:street":"Calle De Real",
    "iso:country":"ES",
    "sg:address":"Calle de Real, 55",
    "sg:city":"Lanjaron",
    "sg:orig_category":"Peluqueros: De Se\u00d1oras",
    "sg:phone":"+34 958 77 08 00",
    "sg:postcode":"18420",
    "sg:province":"Granada",
    "wof:name":"Alvarez Berrido Purificacion",
    "wof:placetype":"venue"
},
  "geometry": {"coordinates":[-3.4827980995,36.9178199768],"type":"Point"}
}