{
  "type": "Feature",
  "properties": {
    "addr:full":"Calle de Naturalista Victor Lopez Seoane, 9 Coru\u00d1a La Coru\u00f1a 15007",
    "addr:housenumber":"9",
    "addr:postcode":"15007",
    "addr:street":"Calle De Naturalista Victor Lopez Seoane;La Corun\u0303A",
    "iso:country":"ES",
    "sg:address":"Calle de Naturalista Victor Lopez Seoane, 9",
    "sg:city":"Coru\u00d1a",
    "sg:orig_category":"Abogados",
    "sg:phone":"+34 981 15 05 11",
    "sg:postcode":"15007",
    "sg:province":"La Coru\u00f1a",
    "wof:name":"Alonso Pizzi Ramon",
    "wof:placetype":"venue"
},
  "geometry": {"coordinates":[-8.4115686417,43.3556938171],"type":"Point"}
}