{
  "type": "Feature",
  "properties": {
    "addr:full":"Calle de Urazurrutia, 3 Bilbao Vizcaya 48003",
    "addr:housenumber":"3",
    "addr:postcode":"48003",
    "addr:street":"Calle De Urazurrutia",
    "iso:country":"ES",
    "sg:address":"Calle de Urazurrutia, 3",
    "sg:city":"Bilbao",
    "sg:orig_category":"Cajas De Ahorro",
    "sg:phone":"+34 944 15 23 04",
    "sg:postcode":"48003",
    "sg:province":"Vizcaya",
    "wof:name":"Bilbao Bizkaia Kutxa",
    "wof:placetype":"venue"
},
  "geometry": {"coordinates":[-2.9230420589,43.2540092468],"type":"Point"}
}