{
  "type": "Feature",
  "properties": {
    "addr:full":"Calle de Juan Perez Delgado Nijota, S/n Santa Cruz De Tenerife Santa Cruz De Tenerife 38006",
    "addr:housenumber":"/ n",
    "addr:postcode":"38006",
    "addr:street":"Calle De Juan;Delgado;S",
    "iso:country":"ES",
    "sg:address":"Calle de Juan Perez Delgado Nijota, S/n",
    "sg:city":"Santa Cruz De Tenerife",
    "sg:orig_category":"Agencias Y Agentes Comerciales, Representantes",
    "sg:phone":"+34 922 27 33 36",
    "sg:postcode":"38006",
    "sg:province":"Santa Cruz De Tenerife",
    "wof:name":"De La Barcena Jaubert Jose",
    "wof:placetype":"venue"
},
  "geometry": {"coordinates":[-16.2664356232,28.4728012085],"type":"Point"}
}