{
  "type": "Feature",
  "properties": {
    "iso:country":"ES",
    "sg:address":"Avda Ronda De Pio Xii, S/n",
    "sg:city":"Sevilla",
    "sg:orig_category":"Ropa Para Se\u00d1oras Y Caballeros (al Por Menor)",
    "sg:phone":"+34 954 35 40 30",
    "sg:postcode":"41008",
    "sg:province":"Sevilla",
    "wof:name":"Mu\u00f1oz Gonzalez Maria Del Carmen",
    "wof:placetype":"venue"
},
  "geometry": {"coordinates":[-5.9781990051,37.4040489197],"type":"Point"}
}