{
  "type": "Feature",
  "properties": {
    "addr:full":"Ctra Estacion (de La), 19 Almodovar Del Rio C\u00f3rdoba 14720",
    "addr:housenumber":"19",
    "addr:postcode":"14720",
    "addr:street":"Ctra Estacion De La;Co\u0301Rdoba",
    "iso:country":"ES",
    "sg:address":"Ctra Estacion (de La), 19",
    "sg:city":"Almodovar Del Rio",
    "sg:orig_category":"Caf\u00c9s, Bares, Cervecer\u00cdas",
    "sg:phone":"+34 957 71 37 54",
    "sg:postcode":"14720",
    "sg:province":"C\u00f3rdoba",
    "wof:name":"Pasteleria Roldan Hnos.s.l.",
    "wof:placetype":"venue"
},
  "geometry": {"coordinates":[-5.0171217918,37.8124580383],"type":"Point"}
}