{
  "type": "Feature",
  "properties": {
    "iso:country":"ES",
    "sg:address":"Carr Jaume I, 5",
    "sg:city":"Girona",
    "sg:orig_category":"Asesor\u00cda Sobre Comunicaci\u00d3n De Empresas",
    "sg:phone":"+34 972 22 47 34",
    "sg:postcode":"17001",
    "sg:province":"Girona",
    "wof:name":"Assessoria M.girones S.l.",
    "wof:placetype":"venue"
},
  "geometry": {"coordinates":[2.8219475746,41.9854469299],"type":"Point"}
}