{
  "type": "Feature",
  "properties": {
    "iso:country":"ES",
    "sg:address":"Calle de Villa De Cedeira, 3",
    "sg:city":"Coru\u00d1a",
    "sg:orig_category":"Promotores Constructores",
    "sg:phone":"+34 981 13 98 16",
    "sg:postcode":"15006",
    "sg:province":"La Coru\u00f1a",
    "wof:name":"Alcuba S.a.",
    "wof:placetype":"venue"
},
  "geometry": {"coordinates":[-8.3923826218,43.3547134399],"type":"Point"}
}