{
  "type": "Feature",
  "properties": {
    "iso:country":"ES",
    "sg:address":"Pol Ind Son Rossynol, 2",
    "sg:city":"Pol.ind.son Castello",
    "sg:orig_category":"Materiales De Aislamiento T\u00c9rmico Y Ac\u00dastico",
    "sg:phone":"+34 971 43 29 31",
    "sg:postcode":"07009",
    "sg:province":"Islas Baleares",
    "sg:website":"www.insobalear.com",
    "wof:name":"Cubiertas Aligeradas De Baleares S.l.",
    "wof:placetype":"venue"
},
  "geometry": {"coordinates":[2.6741399765,39.6011390686],"type":"Point"}
}