{
  "type": "Feature",
  "properties": {
    "iso:country":"ES",
    "sg:address":"Calle de Fuentes Las, 3",
    "sg:city":"Llanes",
    "sg:orig_category":"Muebles, Minoristas",
    "sg:phone":"+34 985 40 03 68",
    "sg:postcode":"33500",
    "sg:province":"Asturias",
    "wof:name":"Somohano Martinez Fernando",
    "wof:placetype":"venue"
},
  "geometry": {"coordinates":[-4.7571043968,43.4192352295],"type":"Point"}
}