{
  "type": "Feature",
  "properties": {
    "iso:country":"ES",
    "sg:address":"Carrer de Santa Anna, 10",
    "sg:city":"Valls",
    "sg:orig_category":"Alimentaci\u00d3n General (al Por Menor)",
    "sg:phone":"+34 977 60 25 72",
    "sg:postcode":"43800",
    "sg:province":"Tarragona",
    "wof:name":"Guell Leal Magi",
    "wof:placetype":"venue"
},
  "geometry": {"coordinates":[1.2504259348,41.2849464417],"type":"Point"}
}