{
  "type": "Feature",
  "properties": {
    "iso:country":"ES",
    "sg:address":"Ctra Vella (sant Celoni), 66",
    "sg:city":"S. Celoni",
    "sg:orig_category":"Agentes Generales De Seguros",
    "sg:phone":"+34 938 67 05 12",
    "sg:postcode":"08470",
    "sg:province":"Barcelona",
    "wof:name":"Pascual Vives Agustin",
    "wof:placetype":"venue"
},
  "geometry": {"coordinates":[2.4914200306,41.6880187988],"type":"Point"}
}