{
  "type": "Feature",
  "properties": {
    "addr:full":"Calle de Jesus, 17 Valencia Valencia 46007",
    "addr:housenumber":"17",
    "addr:postcode":"46007",
    "addr:street":"Calle De Jesus",
    "iso:country":"ES",
    "sg:address":"Calle de Jesus, 17",
    "sg:city":"Valencia",
    "sg:orig_category":"Fabricaci\u00d3n De Su\u00c9ters Y Chalecos De Punto",
    "sg:phone":"+34 963 52 81 07",
    "sg:postcode":"46007",
    "sg:province":"Valencia",
    "wof:name":"Romero Valls Jose Vicente",
    "wof:placetype":"venue"
},
  "geometry": {"coordinates":[-0.3819719851,39.4676246643],"type":"Point"}
}