{
  "type": "Feature",
  "properties": {
    "iso:country":"ES",
    "sg:address":"Av Doctor Mara\u00d1on, 11",
    "sg:city":"Barcelona",
    "sg:orig_category":"Juegos Y Juguetes (al Por Menor)",
    "sg:phone":"+34 933 34 79 51",
    "sg:postcode":"08028",
    "sg:province":"Barcelona",
    "wof:name":"Federacio Catalana De Bitlles",
    "wof:placetype":"venue"
},
  "geometry": {"coordinates":[2.1162290573,41.3808135986],"type":"Point"}
}