{
  "type": "Feature",
  "properties": {
    "iso:country":"ES",
    "sg:address":"Calle de Santiago, 33",
    "sg:city":"Villafranca De Los Barros",
    "sg:orig_category":"Cerrajer\u00cda, Ferrallista",
    "sg:phone":"+34 924 52 62 97",
    "sg:postcode":"06220",
    "sg:province":"Badajoz",
    "wof:name":"Moreno Cabrera Alvaro",
    "wof:placetype":"venue"
},
  "geometry": {"coordinates":[-6.3402290344,38.5617904663],"type":"Point"}
}