{
  "type": "Feature",
  "properties": {
    "iso:country":"ES",
    "sg:address":"Pl Major, 1",
    "sg:city":"Flix",
    "sg:classifiers":[
        {
            "category":"Personal",
            "subcategory":"Barber",
            "type":"Services"
        }
    ],
    "sg:phone":"+34 977 41 01 61",
    "sg:postcode":"43750",
    "sg:province":"Tarragona",
    "sg:tags":[
        "caballeros",
        "de",
        "peluqueros"
    ],
    "wof:name":"Sans Mulet Francisco",
    "wof:placetype":"venue"
},
  "geometry": {"coordinates":[0.5502200127,41.2317581177],"type":"Point"}
}