{
  "type": "Feature",
  "properties": {
    "addr:full":"Calle de Maria Guerrero, 27 Zaragoza Zaragoza 50009",
    "addr:housenumber":"27",
    "addr:postcode":"50009",
    "addr:street":"Calle De Maria Guerrero",
    "iso:country":"ES",
    "sg:address":"Calle de Maria Guerrero, 27",
    "sg:city":"Zaragoza",
    "sg:classifiers":[
        {
            "category":"Personal",
            "subcategory":"Barber",
            "type":"Services"
        }
    ],
    "sg:phone":"+34 976 75 10 05",
    "sg:postcode":"50009",
    "sg:province":"Zaragoza",
    "sg:tags":[
        "caballeros",
        "de",
        "peluqueros"
    ],
    "wof:name":"Martinez Dominguez Pedro",
    "wof:placetype":"venue"
},
  "geometry": {"coordinates":[-0.9106420279,41.6438941956],"type":"Point"}
}