{
  "type": "Feature",
  "properties": {
    "iso:country":"ES",
    "sg:address":"Rebordaos(s. Caetano), 27",
    "sg:city":"Rebordaos",
    "sg:orig_category":"Carnicer\u00cdas, Carnicer\u00cdas",
    "sg:phone":"+34 981 57 66 87",
    "sg:postcode":"15890",
    "sg:province":"A Coru\u00f1a",
    "wof:name":"Vazquez Lopez Amparo",
    "wof:placetype":"venue"
},
  "geometry": {"coordinates":[-8.5329589844,42.9210243225],"type":"Point"}
}