{
  "type": "Feature",
  "properties": {
    "addr:full":"Calle de Nogalte, 14 San Jose Murcia 30800",
    "addr:housenumber":"14",
    "addr:postcode":"30800",
    "addr:street":"Calle De Nogalte",
    "iso:country":"ES",
    "sg:address":"Calle de Nogalte, 14",
    "sg:city":"San Jose",
    "sg:orig_category":"Marroquiner\u00cda (confecci\u00d3n)",
    "sg:phone":"+34 968 46 64 41",
    "sg:postcode":"30800",
    "sg:province":"Murcia",
    "wof:name":"Mota Camacho Juan Carlos",
    "wof:placetype":"venue"
},
  "geometry": {"coordinates":[-1.6905640364,37.680557251],"type":"Point"}
}