{
  "type": "Feature",
  "properties": {
    "iso:country":"ES",
    "sg:address":"Calle de Moreno Nieto, 3",
    "sg:city":"Campillo Llerena",
    "sg:orig_category":"Charcuter\u00cdas (al Por Mayor)",
    "sg:phone":"+34 924 77 03 41",
    "sg:postcode":"06443",
    "sg:province":"Badajoz",
    "wof:name":"Nogales Verjano Antonio",
    "wof:placetype":"venue"
},
  "geometry": {"coordinates":[-5.8273391724,38.5011863708],"type":"Point"}
}