{
  "type": "Feature",
  "properties": {
    "addr:full":"Pla\u00c7 Federico Pareja, 11 Ciutadella Menorca Islas Baleares 07760",
    "addr:housenumber":"11",
    "addr:postcode":"07760",
    "addr:street":"Pareja",
    "iso:country":"ES",
    "sg:address":"Pla\u00c7 Federico Pareja, 11",
    "sg:city":"Ciutadella Menorca",
    "sg:orig_category":"Quincaller\u00cda (al Por Menor)",
    "sg:phone":"+34 971 38 61 61",
    "sg:postcode":"07760",
    "sg:province":"Islas Baleares",
    "wof:name":"Ferreteria Emilio C. B.",
    "wof:placetype":"venue"
},
  "geometry": {"coordinates":[3.8398919106,40.0039787292],"type":"Point"}
}