{
  "type": "Feature",
  "properties": {
    "addr:full":"Av Borbo, 13 Barcelona Barcelona 08031",
    "addr:housenumber":"13",
    "addr:postcode":"08031",
    "addr:street":"Av Borbo",
    "iso:country":"ES",
    "sg:address":"Av Borbo, 13",
    "sg:city":"Barcelona",
    "sg:orig_category":"Institutos De Belleza",
    "sg:phone":"+34 934 08 49 99",
    "sg:postcode":"08031",
    "sg:province":"Barcelona",
    "wof:name":"Centro De Belleza Y Estetica Helena S.l.",
    "wof:placetype":"venue"
},
  "geometry": {"coordinates":[2.1754310131,41.4271965027],"type":"Point"}
}