{
  "type": "Feature",
  "properties": {
    "addr:full":"Av Garraf, 11 Vilanova I La Geltru Barcelona 08800",
    "addr:housenumber":"11",
    "addr:postcode":"08800",
    "addr:street":"Av Garraf",
    "iso:country":"ES",
    "sg:address":"Av Garraf, 11",
    "sg:city":"Vilanova I La Geltru",
    "sg:orig_category":"Cristaler\u00cdas",
    "sg:phone":"+34 938 14 31 22",
    "sg:postcode":"08800",
    "sg:province":"Barcelona",
    "wof:name":"Rascon Navarro Andres",
    "wof:placetype":"venue"
},
  "geometry": {"coordinates":[1.7292239666,41.2229652405],"type":"Point"}
}