{
  "type": "Feature",
  "properties": {
    "addr:full":"Calle de Antonio Trueba Kalea, 13 Erandio Vizcaya 48950",
    "addr:housenumber":"13",
    "addr:postcode":"48950",
    "addr:street":"Calle De Antonio Trueba Kalea",
    "iso:country":"ES",
    "sg:address":"Calle de Antonio Trueba Kalea, 13",
    "sg:city":"Erandio",
    "sg:orig_category":"Molduras, Junquillos, Listones Y Molduras Perforadas",
    "sg:phone":"+34 944 67 26 99",
    "sg:postcode":"48950",
    "sg:province":"Vizcaya",
    "wof:name":"Manuel Garcia Garcia",
    "wof:placetype":"venue"
},
  "geometry": {"coordinates":[-2.9754214287,43.3019180298],"type":"Point"}
}