{
  "type": "Feature",
  "properties": {
    "addr:full":"Poli Valsolo, 4 Illueca Zaragoza 50250",
    "addr:housenumber":"4",
    "addr:postcode":"50250",
    "addr:street":"Valsolo",
    "iso:country":"ES",
    "sg:address":"Poli Valsolo, 4",
    "sg:city":"Illueca",
    "sg:orig_category":"M\u00c1quinas Para Recortar Y Pegar",
    "sg:phone":"+34 976 82 20 83",
    "sg:postcode":"50250",
    "sg:province":"Zaragoza",
    "wof:name":"Tecopel S.l.l.",
    "wof:placetype":"venue"
},
  "geometry": {"coordinates":[-1.6350140572,41.5382957458],"type":"Point"}
}