{
  "type": "Feature",
  "properties": {
    "addr:full":"Calle de Moriscos, 40 Cordoba C\u00f3rdoba 14001",
    "addr:housenumber":"40",
    "addr:postcode":"14001",
    "addr:street":"Calle De Moriscos;Co\u0301Rdoba",
    "iso:country":"ES",
    "sg:address":"Calle de Moriscos, 40",
    "sg:city":"Cordoba",
    "sg:orig_category":"Frutas, Legumbres Frescas Y Tempranas (al Por Menor)",
    "sg:phone":"+34 957 48 88 28",
    "sg:postcode":"14001",
    "sg:province":"C\u00f3rdoba",
    "wof:name":"Casta\u00f1o Moya Jose",
    "wof:placetype":"venue"
},
  "geometry": {"coordinates":[-4.7720527649,37.8905105591],"type":"Point"}
}