{
  "type": "Feature",
  "properties": {
    "iso:country":"ES",
    "sg:address":"Calle de Arenas De San Juan, 17",
    "sg:city":"Socuellamos",
    "sg:orig_category":"Agencias Y Asesores De Publicidad",
    "sg:phone":"+34 926 53 12 27",
    "sg:postcode":"13630",
    "sg:province":"Ciudad Real",
    "wof:name":"100 Por 100 Cay. S.l.u.",
    "wof:placetype":"venue"
},
  "geometry": {"coordinates":[-2.791626,39.281181],"type":"Point"}
}