{
  "type": "Feature",
  "properties": {
    "iso:country":"ES",
    "sg:address":"La Plaza, S/n",
    "sg:city":"S. Pedro Romeral",
    "sg:orig_category":"Cajas De Ahorro",
    "sg:phone":"+34 942 59 54 78",
    "sg:postcode":"39686",
    "sg:province":"Cantabria",
    "sg:website":"www.cajacantabria.es",
    "wof:name":"Cableuropa",
    "wof:placetype":"venue"
},
  "geometry": {"coordinates":[-3.8471479416,43.168598175],"type":"Point"}
}