{
  "type": "Feature",
  "properties": {
    "addr:full":"Calle de Guisando, 11 Madrid Madrid 28035",
    "addr:housenumber":"11",
    "addr:postcode":"madrid;28035",
    "addr:street":"Calle De Guisando",
    "iso:country":"ES",
    "sg:address":"Calle de Guisando, 11",
    "sg:city":"Madrid",
    "sg:orig_category":"Ingenier\u00cda, Centros De Estudios (diversos)",
    "sg:phone":"+34 913 16 15 25",
    "sg:postcode":"28035",
    "sg:province":"Madrid",
    "wof:name":"Navarro Garrido Virgilio",
    "wof:placetype":"venue"
},
  "geometry": {"coordinates":[-3.7297084332,40.4675750732],"type":"Point"}
}