{
  "type": "Feature",
  "properties": {
    "addr:full":"Poli Aldea Moret, S/n Caceres C\u00e1ceres 10003",
    "addr:housenumber":"s / n",
    "addr:postcode":"10003",
    "addr:street":"Moret;Ca\u0301Ceres",
    "iso:country":"ES",
    "sg:address":"Poli Aldea Moret, S/n",
    "sg:city":"Caceres",
    "sg:orig_category":"Venta, Alquiler, Mantenimiento De Calderas",
    "sg:phone":"+34 927 23 30 48",
    "sg:postcode":"10003",
    "sg:province":"C\u00e1ceres",
    "wof:name":"Rectimeca S. A.",
    "wof:placetype":"venue"
},
  "geometry": {"coordinates":[-6.3720030785,39.4745063782],"type":"Point"}
}