{
  "type": "Feature",
  "properties": {
    "addr:full":"Ctra Yanguas, S/n Cantimpalos Segovia 40360",
    "addr:housenumber":"s",
    "addr:postcode":"40360",
    "addr:street":"Ctra Yanguas;/ N Cantimpalos Segovia",
    "iso:country":"ES",
    "sg:address":"Ctra Yanguas, S/n",
    "sg:city":"Cantimpalos",
    "sg:orig_category":"Charcuter\u00cdas (al Por Menor)",
    "sg:phone":"+34 921 49 60 57",
    "sg:postcode":"40360",
    "sg:province":"Segovia",
    "wof:name":"Jesus Palomo E Hijos S.l.",
    "wof:placetype":"venue"
},
  "geometry": {"coordinates":[-4.1623039246,41.0722122192],"type":"Point"}
}