{
  "type": "Feature",
  "properties": {
    "addr:full":"Calle de Dali, 7 Roquetas Mar Almer\u00eda 04740",
    "addr:housenumber":"7",
    "addr:postcode":"04740",
    "addr:street":"Calle De Dali",
    "iso:country":"ES",
    "sg:address":"Calle de Dali, 7",
    "sg:city":"Roquetas Mar",
    "sg:orig_category":"Alimentaci\u00d3n General (al Por Menor)",
    "sg:phone":"+34 950 32 85 97",
    "sg:postcode":"04740",
    "sg:province":"Almer\u00eda",
    "wof:name":"Lopez Lafuente Rafael",
    "wof:placetype":"venue"
},
  "geometry": {"coordinates":[-2.6057343483,36.764881134],"type":"Point"}
}