{
  "type": "Feature",
  "properties": {
    "addr:full":"Calle de Mayor, 8 Jaca Huesca 22700",
    "addr:housenumber":"8",
    "addr:postcode":"22700",
    "addr:street":"Calle De Mayor",
    "iso:country":"ES",
    "sg:address":"Calle de Mayor, 8",
    "sg:city":"Jaca",
    "sg:orig_category":"Herboristas (al Por Menor)",
    "sg:phone":"+34 974 35 59 29",
    "sg:postcode":"22700",
    "sg:province":"Huesca",
    "wof:name":"Compaire Zaborras Ana Isabel",
    "wof:placetype":"venue"
},
  "geometry": {"coordinates":[-0.5496590137,42.5693588257],"type":"Point"}
}