{
  "type": "Feature",
  "properties": {
    "addr:full":"Av Gava, 68 Viladecans Barcelona 08840",
    "addr:housenumber":"68",
    "addr:postcode":"08840",
    "addr:street":"Av Gava",
    "iso:country":"ES",
    "sg:address":"Av Gava, 68",
    "sg:city":"Viladecans",
    "sg:orig_category":"Flores Y Plantas Naturales (al Por Mayor)",
    "sg:phone":"+34 936 58 68 03",
    "sg:postcode":"08840",
    "sg:province":"Barcelona",
    "wof:name":"Gomez Dorado Clara",
    "wof:placetype":"venue"
},
  "geometry": {"coordinates":[2.0104780197,41.308807373],"type":"Point"}
}