{
  "type": "Feature",
  "properties": {
    "iso:country":"ES",
    "sg:address":"Calle de San Millan, 15",
    "sg:city":"Logro\u00f1o",
    "sg:orig_category":"Electrodom\u00c9sticos (al Por Menor)",
    "sg:phone":"+34 941 23 75 71",
    "sg:postcode":"26004",
    "sg:province":"La Rioja",
    "sg:website":"www.remble.com",
    "wof:name":"Remle S.a.",
    "wof:placetype":"venue"
},
  "geometry": {"coordinates":[-2.4330289364,42.4658584595],"type":"Point"}
}