{
  "type": "Feature",
  "properties": {
    "addr:full":"C/ Bosc Tancat, 29 Cerdanyola Valles Barcelona 08290",
    "addr:housenumber":"29",
    "addr:postcode":"08290",
    "addr:street":"C / Bosc Tancat;Valles Barcelona",
    "iso:country":"ES",
    "sg:address":"C/ Bosc Tancat, 29",
    "sg:city":"Cerdanyola Valles",
    "sg:orig_category":"Suministros Para Hoteles",
    "sg:phone":"+34 936 91 07 12",
    "sg:postcode":"08290",
    "sg:province":"Barcelona",
    "wof:name":"Fiore Di Napoli S.a.",
    "wof:placetype":"venue"
},
  "geometry": {"coordinates":[2.1470150948,41.4924812317],"type":"Point"}
}