{
  "type": "Feature",
  "properties": {
    "iso:country":"ES",
    "sg:address":"Pase Damas (las), 32",
    "sg:city":"Zaragoza",
    "sg:orig_category":"Zapatos (al Por Menor)",
    "sg:phone":"+34 976 23 55 50",
    "sg:postcode":"50008",
    "sg:province":"Zaragoza",
    "wof:name":"Soto Viamonte Jose Luis",
    "wof:placetype":"venue"
},
  "geometry": {"coordinates":[-0.8834530115,41.6440849304],"type":"Point"}
}