{
  "type": "Feature",
  "properties": {
    "iso:country":"ES",
    "sg:address":"Calle de Pirineos (de Los), 2",
    "sg:city":"Mejorada Campo",
    "sg:orig_category":"Arreglo, Reparaci\u00d3n, Piezas Sueltas De Televisi\u00d3n, V\u00cddeo, Hi",
    "sg:phone":"+34 916 79 02 52",
    "sg:postcode":"28840",
    "sg:province":"Madrid",
    "wof:name":"Garcia Saez Benito",
    "wof:placetype":"venue"
},
  "geometry": {"coordinates":[-3.4816260338,40.3900566101],"type":"Point"}
}