{
  "type": "Feature",
  "properties": {
    "addr:full":"Carr Mariana Pineda, 51 Burjassot Valencia 46100",
    "addr:housenumber":"51",
    "addr:postcode":"46100",
    "addr:street":"Carr Mariana Pineda",
    "iso:country":"ES",
    "sg:address":"Carr Mariana Pineda, 51",
    "sg:city":"Burjassot",
    "sg:orig_category":"Carnicer\u00cdas, Carnicer\u00cdas",
    "sg:phone":"+34 963 63 84 60",
    "sg:postcode":"46100",
    "sg:province":"Valencia",
    "wof:name":"Castillo Cabrelles Miguel",
    "wof:placetype":"venue"
},
  "geometry": {"coordinates":[-0.4088050127,39.5061759949],"type":"Point"}
}