{
  "type": "Feature",
  "properties": {
    "iso:country":"ES",
    "sg:address":"Calle de Sierra De Tortejada, 9",
    "sg:city":"Madrid",
    "sg:orig_category":"Cerrajer\u00cda, Ferrallista",
    "sg:phone":"+34 913 32 23 54",
    "sg:postcode":"28031",
    "sg:province":"Madrid",
    "wof:name":"Garcia Garcia Modesto",
    "wof:placetype":"venue"
},
  "geometry": {"coordinates":[-3.6173698902,40.3720550537],"type":"Point"}
}