{
  "type": "Feature",
  "properties": {
    "addr:full":"Avda Reina Victoria, 72 Madrid Madrid 28003",
    "addr:housenumber":"72",
    "addr:postcode":"madrid;28003",
    "addr:street":"Avda Reina Victoria",
    "iso:country":"ES",
    "sg:address":"Avda Reina Victoria, 72",
    "sg:city":"Madrid",
    "sg:orig_category":"Sociedades, Compa\u00d1\u00cdas Aseguradoras",
    "sg:phone":"+34 915 34 04 44",
    "sg:postcode":"28003",
    "sg:province":"Madrid",
    "sg:website":"www.mutuasport.com",
    "wof:name":"Mutua De Seguros Deportivos",
    "wof:placetype":"venue"
},
  "geometry": {"coordinates":[-3.7143750191,40.4460945129],"type":"Point"}
}