{
  "type": "Feature",
  "properties": {
    "addr:full":"Pl. Espa\u00f1a, 20 Leganes Madrid 28911",
    "addr:housenumber":"20",
    "addr:postcode":"28911",
    "addr:street":"Pl. Espan\u0303A",
    "iso:country":"ES",
    "sg:address":"Pl. Espa\u00f1a, 20",
    "sg:city":"Leganes",
    "sg:orig_category":"Asesor\u00cda Fiscal Y Jur\u00cddica",
    "sg:phone":"+34 916 93 23 00",
    "sg:postcode":"28911",
    "sg:province":"Madrid",
    "wof:name":"Torija Y Arroyo S.l.",
    "wof:placetype":"venue"
},
  "geometry": {"coordinates":[-3.7650110722,40.3284072876],"type":"Point"}
}