{
  "type": "Feature",
  "properties": {
    "iso:country":"ES",
    "sg:address":"Av Constitucio, 30",
    "sg:city":"Castelldefels",
    "sg:orig_category":"Cajas De Ahorro",
    "sg:phone":"+34 936 64 04 54",
    "sg:postcode":"08860",
    "sg:province":"Barcelona",
    "sg:website":"www.lacaixa.es",
    "wof:name":"Caixa D'estalvis I Pensions De Barcelona",
    "wof:placetype":"venue"
},
  "geometry": {"coordinates":[1.9881420135,41.2872200012],"type":"Point"}
}