{
  "type": "Feature",
  "properties": {
    "addr:full":"Pol Ind El Ejido, 137 Osuna Sevilla 41640",
    "addr:housenumber":"137",
    "addr:postcode":"41640",
    "addr:street":"Ejido",
    "iso:country":"ES",
    "sg:address":"Pol Ind El Ejido, 137",
    "sg:city":"Osuna",
    "sg:orig_category":"Inform\u00c1tica (estudios, Servicios, Asesor\u00cda, Formaci\u00d3n)",
    "sg:phone":"+34 955 91 76 68",
    "sg:postcode":"41640",
    "sg:province":"Sevilla",
    "wof:name":"Velasco Haro S.l.",
    "wof:placetype":"venue"
},
  "geometry": {"coordinates":[-5.1028141975,37.2371253967],"type":"Point"}
}