{
  "type": "Feature",
  "properties": {
    "iso:country":"ES",
    "sg:address":"Carrer de Est, 14",
    "sg:city":"Buvisa",
    "sg:orig_category":"Material Y Accesorios Para Soldaduras",
    "sg:phone":"+34 937 52 45 17",
    "sg:postcode":"08338",
    "sg:province":"Barcelona",
    "wof:name":"Braxton Biddle,s.l.",
    "wof:placetype":"venue"
},
  "geometry": {"coordinates":[2.3460769653,41.505153656],"type":"Point"}
}