{
  "type": "Feature",
  "properties": {
    "addr:full":"Calle de Peiro, 15 Borriol Castell\u00f3n 12190",
    "addr:housenumber":"15",
    "addr:postcode":"12190",
    "addr:street":"Calle De Peiro",
    "iso:country":"ES",
    "sg:address":"Calle de Peiro, 15",
    "sg:city":"Borriol",
    "sg:orig_category":"Promotores Constructores",
    "sg:phone":"+34 964 32 12 77",
    "sg:postcode":"12190",
    "sg:province":"Castell\u00f3n",
    "wof:name":"Perez Sanchez Vicente",
    "wof:placetype":"venue"
},
  "geometry": {"coordinates":[-0.0679280013,40.0424613953],"type":"Point"}
}