{
  "type": "Feature",
  "properties": {
    "iso:country":"ES",
    "sg:address":"Calle de Teodoro Cuesta, 13",
    "sg:city":"Mieres",
    "sg:orig_category":"Grafistas",
    "sg:phone":"+34 985 45 23 36",
    "sg:postcode":"33600",
    "sg:province":"Asturias",
    "sg:website":"www.wenaewe.com",
    "wof:name":"Wenaewe C.b.",
    "wof:placetype":"venue"
},
  "geometry": {"coordinates":[-5.772069931,43.2500038147],"type":"Point"}
}