{
  "type": "Feature",
  "properties": {
    "addr:full":"Coiron(coiro), 4 Coiron La Coru\u00f1a 15145",
    "addr:housenumber":"4",
    "addr:postcode":"15145",
    "addr:street":"Coiron Coiro;Coiron La Corun\u0303A",
    "iso:country":"ES",
    "sg:address":"Coiron(coiro), 4",
    "sg:city":"Coiron",
    "sg:orig_category":"Asesor\u00cda De Formaci\u00d3n Y Gesti\u00d3n De Personal",
    "sg:phone":"+34 981 60 58 05",
    "sg:postcode":"15145",
    "sg:province":"La Coru\u00f1a",
    "wof:name":"Castro Loureda Consuelo",
    "wof:placetype":"venue"
},
  "geometry": {"coordinates":[-8.5813436508,43.2482681274],"type":"Point"}
}