{
  "type": "Feature",
  "properties": {
    "addr:full":"Calle de Ramon Y Cajal, 28 Don Benito Badajoz 06400",
    "addr:housenumber":"28",
    "addr:postcode":"06400",
    "addr:street":"Calle De Ramon Y Cajal",
    "iso:country":"ES",
    "sg:address":"Calle de Ramon Y Cajal, 28",
    "sg:city":"Don Benito",
    "sg:orig_category":"Arquitectos",
    "sg:phone":"+34 924 80 10 72",
    "sg:postcode":"06400",
    "sg:province":"Badajoz",
    "wof:name":"Eddea Arquitectos Extremadura S.l.",
    "wof:placetype":"venue"
},
  "geometry": {"coordinates":[-5.8614788055,38.9564552307],"type":"Point"}
}