{
  "type": "Feature",
  "properties": {
    "iso:country":"ES",
    "sg:address":"Ctra. Malaga, S/n",
    "sg:city":"Chauchina",
    "sg:orig_category":"Aeropuertos Y Servicios Aeroportuarios",
    "sg:phone":"+34 958 24 52 00",
    "sg:postcode":"18330",
    "sg:province":"Granada",
    "sg:website":"www.aena.es",
    "wof:name":"Aeropuertos Espa\u00d1oles Y Navegacion Aerea",
    "wof:placetype":"venue"
},
  "geometry": {"coordinates":[-3.7262268066,37.1913642883],"type":"Point"}
}