{
  "type": "Feature",
  "properties": {
    "iso:country":"ES",
    "sg:address":"Calle de Padilla, 5",
    "sg:city":"Madrid",
    "sg:orig_category":"Ropa Para Se\u00d1oras (al Por Menor)",
    "sg:phone":"+34 915 77 17 73",
    "sg:postcode":"28006",
    "sg:province":"Madrid",
    "wof:name":"Elisa Rivera S.l.",
    "wof:placetype":"venue"
},
  "geometry": {"coordinates":[-3.6859350204,40.4318161011],"type":"Point"}
}