{
  "type": "Feature",
  "properties": {
    "iso:country":"ES",
    "sg:address":"Carrer de Napols, 87",
    "sg:city":"Barcelona",
    "sg:orig_category":"Florister\u00cdas",
    "sg:phone":"+34 932 46 16 17",
    "sg:postcode":"08013",
    "sg:province":"Barcelona",
    "wof:name":"Xavier Botey S.l.",
    "wof:placetype":"venue"
},
  "geometry": {"coordinates":[2.1810309887,41.3939590454],"type":"Point"}
}