{
  "type": "Feature",
  "properties": {
    "iso:country":"ES",
    "sg:address":"Calle de Luciano Pita, 19",
    "sg:city":"Ortigueira",
    "sg:orig_category":"Abogados",
    "sg:phone":"+34 981 42 20 41",
    "sg:postcode":"15330",
    "sg:province":"La Coru\u00f1a",
    "wof:name":"Fernandez Franco Salvador",
    "wof:placetype":"venue"
},
  "geometry": {"coordinates":[-7.8535299301,43.6840133667],"type":"Point"}
}