{
  "type": "Feature",
  "properties": {
    "iso:country":"ES",
    "sg:address":"Avda Cruz De Los Pajares, 1",
    "sg:city":"Miajadas",
    "sg:orig_category":"Comercio, Reparaci\u00d3n De Bicicletas, De Motocicletas, De Accesorios",
    "sg:phone":"+34 927 16 01 33",
    "sg:postcode":"10100",
    "sg:province":"C\u00e1ceres",
    "wof:name":"Izquierdo Sanchez Agustin",
    "wof:placetype":"venue"
},
  "geometry": {"coordinates":[-5.9141139984,39.1475334167],"type":"Point"}
}