{
  "type": "Feature",
  "properties": {
    "addr:full":"Calle de Caridad, 1 Valladolid Valladolid 47001",
    "addr:housenumber":"1",
    "addr:postcode":"47001",
    "addr:street":"Calle De Caridad",
    "iso:country":"ES",
    "sg:address":"Calle de Caridad, 1",
    "sg:city":"Valladolid",
    "sg:orig_category":"Asesor\u00cda Sobre Comunicaci\u00d3n De Empresas",
    "sg:phone":"+34 983 36 17 19",
    "sg:postcode":"47001",
    "sg:province":"Valladolid",
    "wof:name":"Rafael Lopez Consultores S.l.l.",
    "wof:placetype":"venue"
},
  "geometry": {"coordinates":[-4.730304718,41.6516494751],"type":"Point"}
}