{
  "type": "Feature",
  "properties": {
    "iso:country":"ES",
    "sg:address":"Calle de Longares, 46",
    "sg:city":"Madrid",
    "sg:orig_category":"Empresas De Carpinter\u00cda",
    "sg:phone":"+34 913 06 71 36",
    "sg:postcode":"28022",
    "sg:province":"Madrid",
    "wof:name":"Talleres Cd De Aluminios Y Automatismos S.l.",
    "wof:placetype":"venue"
},
  "geometry": {"coordinates":[-3.609596014,40.4264259338],"type":"Point"}
}