{
  "type": "Feature",
  "properties": {
    "addr:full":"Rua Nova De Caranza, 125 Ferrol La Coru\u00f1a 15404",
    "addr:housenumber":"125",
    "addr:postcode":"15404",
    "addr:street":"Rua Nova De Caranza;La Corun\u0303A",
    "iso:country":"ES",
    "sg:address":"Rua Nova De Caranza, 125",
    "sg:city":"Ferrol",
    "sg:orig_category":"T\u00c9cnicos Veterinarios",
    "sg:phone":"+34 981 37 21 42",
    "sg:postcode":"15404",
    "sg:province":"La Coru\u00f1a",
    "wof:name":"Perez Portilla Maria Onelia",
    "wof:placetype":"venue"
},
  "geometry": {"coordinates":[-8.2173490524,43.4889831543],"type":"Point"}
}