{
  "type": "Feature",
  "properties": {
    "addr:full":"Carr Fuerteventura, 29 Calella Girona 17210",
    "addr:housenumber":"29",
    "addr:postcode":"17210",
    "addr:street":"Carr Fuerteventura",
    "iso:country":"ES",
    "sg:address":"Carr Fuerteventura, 29",
    "sg:city":"Calella",
    "sg:orig_category":"Agencias Y Agentes Comerciales, Representantes",
    "sg:phone":"+34 972 61 47 43",
    "sg:postcode":"17210",
    "sg:province":"Girona",
    "wof:name":"Vert Presas Teresa",
    "wof:placetype":"venue"
},
  "geometry": {"coordinates":[3.1834840775,41.8935050964],"type":"Point"}
}