{
  "type": "Feature",
  "properties": {
    "iso:country":"ES",
    "sg:address":"Calle de Palafox, 14",
    "sg:city":"Madrid",
    "sg:orig_category":"Masajistas Kinesiterapeutas",
    "sg:phone":"+34 914 45 16 59",
    "sg:postcode":"28010",
    "sg:province":"Madrid",
    "wof:name":"Sporterapy S.l.",
    "wof:placetype":"venue"
},
  "geometry": {"coordinates":[-3.7013568878,40.431602478],"type":"Point"}
}