{
  "type": "Feature",
  "properties": {
    "addr:full":"Calle de Federico Olmeda, 31 Burgos Burgos 09006",
    "addr:housenumber":"31",
    "addr:postcode":"09006",
    "addr:street":"Calle De Federico Olmeda",
    "iso:country":"ES",
    "sg:address":"Calle de Federico Olmeda, 31",
    "sg:city":"Burgos",
    "sg:orig_category":"Peluquer\u00cdas, Peluquer\u00cda Mixta",
    "sg:phone":"+34 947 22 72 94",
    "sg:postcode":"09006",
    "sg:province":"Burgos",
    "wof:name":"Arroyo Casta\u00f1eda Pilar",
    "wof:placetype":"venue"
},
  "geometry": {"coordinates":[-3.6900815964,42.3509674072],"type":"Point"}
}