{
  "type": "Feature",
  "properties": {
    "addr:full":"Pol Ind Las Labradas, S/n Tudela Navarra 31500",
    "addr:postcode":"31500",
    "addr:street":"Labradas S / N",
    "iso:country":"ES",
    "sg:address":"Pol Ind Las Labradas, S/n",
    "sg:city":"Tudela",
    "sg:orig_category":"Fabricaci\u00d3n De Productos L\u00c1cteos Y Derivados",
    "sg:phone":"+34 948 82 14 86",
    "sg:postcode":"31500",
    "sg:province":"Navarra",
    "wof:name":"Anyfre S.l.",
    "wof:placetype":"venue"
},
  "geometry": {"coordinates":[-1.4821481705,42.1872329712],"type":"Point"}
}