{
  "type": "Feature",
  "properties": {
    "iso:country":"ES",
    "sg:address":"Calle de Ramon Y Cajal, 34",
    "sg:city":"Coru\u00d1a",
    "sg:orig_category":"Abogados",
    "sg:phone":"+34 981 28 11 77",
    "sg:postcode":"15006",
    "sg:province":"La Coru\u00f1a",
    "wof:name":"Rego Perez Maria Benita",
    "wof:placetype":"venue"
},
  "geometry": {"coordinates":[-8.4032535553,43.3549842834],"type":"Point"}
}