{
  "type": "Feature",
  "properties": {
    "iso:country":"ES",
    "sg:address":"Calle de Principe, 3",
    "sg:city":"Madrid",
    "sg:orig_category":"Inmobiliaria (agencias)",
    "sg:phone":"+34 914 20 36 40",
    "sg:postcode":"28012",
    "sg:province":"Madrid",
    "wof:name":"Mu\u00f1oz Espada Joaquin",
    "wof:placetype":"venue"
},
  "geometry": {"coordinates":[-3.7001900673,40.4162101746],"type":"Point"}
}