{
  "type": "Feature",
  "properties": {
    "addr:full":"Calle de Cantones, 21 Almendralejo Badajoz 06200",
    "addr:housenumber":"21",
    "addr:postcode":"06200",
    "addr:street":"Calle De Cantones",
    "iso:country":"ES",
    "sg:address":"Calle de Cantones, 21",
    "sg:city":"Almendralejo",
    "sg:orig_category":"Reposter\u00cdas",
    "sg:phone":"+34 924 66 59 55",
    "sg:postcode":"06200",
    "sg:province":"Badajoz",
    "wof:name":"Guisado Gomez Sixta",
    "wof:placetype":"venue"
},
  "geometry": {"coordinates":[-6.4054818153,38.6821708679],"type":"Point"}
}