{
  "type": "Feature",
  "properties": {
    "addr:full":"Calle de Jerusalen, 24 Alacant Alicante 03001",
    "addr:housenumber":"24",
    "addr:postcode":"03001",
    "addr:street":"Calle De Jerusalen",
    "iso:country":"ES",
    "sg:address":"Calle de Jerusalen, 24",
    "sg:city":"Alacant",
    "sg:orig_category":"Bisuter\u00cda, Joyer\u00cda, Relojer\u00cda (al Por Menor)",
    "sg:phone":"+34 965 20 59 70",
    "sg:postcode":"03001",
    "sg:province":"Alicante",
    "wof:name":"Otero Otero Ofelia",
    "wof:placetype":"venue"
},
  "geometry": {"coordinates":[-0.487116009,38.3453216553],"type":"Point"}
}