{
  "type": "Feature",
  "properties": {
    "iso:country":"ES",
    "sg:address":"Calle de Apolo Xi, 1",
    "sg:city":"Benidorm",
    "sg:orig_category":"Panader\u00cdas, Panader\u00cdas",
    "sg:phone":"+34 965 85 23 99",
    "sg:postcode":"03500",
    "sg:province":"Alicante",
    "wof:name":"Perez Berenguer Pedro",
    "wof:placetype":"venue"
},
  "geometry": {"coordinates":[-0.1314812005,38.5393371582],"type":"Point"}
}