{
  "type": "Feature",
  "properties": {
    "addr:full":"Calle de Mexico, 20 Arrecife Las Palmas 35500",
    "addr:housenumber":"20",
    "addr:postcode":"35500",
    "addr:street":"Calle De Mexico",
    "iso:country":"ES",
    "sg:address":"Calle de Mexico, 20",
    "sg:city":"Arrecife",
    "sg:orig_category":"Reposter\u00cdas",
    "sg:phone":"+34 928 81 68 80",
    "sg:postcode":"35500",
    "sg:province":"Las Palmas",
    "wof:name":"Jonay S. L.",
    "wof:placetype":"venue"
},
  "geometry": {"coordinates":[-13.556476593,28.9612293243],"type":"Point"}
}