{
  "type": "Feature",
  "properties": {
    "addr:full":"Carr Raval, 8 Pobla Segur Lleida 25500",
    "addr:housenumber":"8",
    "addr:postcode":"25500",
    "addr:street":"Carr Raval",
    "iso:country":"ES",
    "sg:address":"Carr Raval, 8",
    "sg:city":"Pobla Segur",
    "sg:orig_category":"Carnicer\u00cdas, Carnicer\u00cdas",
    "sg:phone":"+34 973 68 00 97",
    "sg:postcode":"25500",
    "sg:province":"Lleida",
    "wof:name":"Bellera Olle Luis",
    "wof:placetype":"venue"
},
  "geometry": {"coordinates":[0.9664350152,42.2486915588],"type":"Point"}
}