{
  "type": "Feature",
  "properties": {
    "addr:full":"Carr Tenor Alonso, 78 Godella Valencia 46110",
    "addr:housenumber":"78",
    "addr:postcode":"46110",
    "addr:street":"Carr Tenor Alonso",
    "iso:country":"ES",
    "sg:address":"Carr Tenor Alonso, 78",
    "sg:city":"Godella",
    "sg:orig_category":"Imprenta",
    "sg:phone":"+34 963 63 07 71",
    "sg:postcode":"46110",
    "sg:province":"Valencia",
    "wof:name":"Lazo Impresores S.l.",
    "wof:placetype":"venue"
},
  "geometry": {"coordinates":[-0.4115790129,39.5183105469],"type":"Point"}
}