{
  "type": "Feature",
  "properties": {
    "iso:country":"ES",
    "sg:address":"Paulino Caballero, 12",
    "sg:city":"Iru\u00f1a",
    "sg:orig_category":"Venta, Instalaci\u00d3n De Cocinas",
    "sg:phone":"+34 948 23 64 76",
    "sg:postcode":"31003",
    "sg:province":"Navarra",
    "wof:name":"Ruiz Huici Francisco",
    "wof:placetype":"venue"
},
  "geometry": {"coordinates":[-1.6399879456,42.8123893738],"type":"Point"}
}