{
  "type": "Feature",
  "properties": {
    "addr:full":"Pda Cala Puntal, S/n Vinaros Castell\u00f3n 12500",
    "addr:housenumber":"s / n",
    "addr:postcode":"12500",
    "addr:street":"Puntal",
    "iso:country":"ES",
    "sg:address":"Pda Cala Puntal, S/n",
    "sg:city":"Vinaros",
    "sg:orig_category":"Delegados, Agentes De Tr\u00c1nsito, Auxiliares De Transporte Internacional",
    "sg:phone":"+34 964 49 62 97",
    "sg:postcode":"12500",
    "sg:province":"Castell\u00f3n",
    "wof:name":"Sanz Miralles Jaime",
    "wof:placetype":"venue"
},
  "geometry": {"coordinates":[0.4546850026,40.4500846863],"type":"Point"}
}