{
  "type": "Feature",
  "properties": {
    "addr:full":"Santuario Guayente, S/n Sahun Huesca 22468",
    "addr:housenumber":"s",
    "addr:postcode":"22468",
    "addr:street":"/ N Sahun",
    "iso:country":"ES",
    "sg:address":"Santuario Guayente, S/n",
    "sg:city":"Sahun",
    "sg:orig_category":"Asociaciones, Organismos Culturales Y Socioeducativos",
    "sg:phone":"+34 974 55 21 48",
    "sg:postcode":"22468",
    "sg:province":"Huesca",
    "wof:name":"Asociacion Guayente El Remos",
    "wof:placetype":"venue"
},
  "geometry": {"coordinates":[0.469109714,42.6088027954],"type":"Point"}
}