{
  "type": "Feature",
  "properties": {
    "iso:country":"ES",
    "sg:address":"Calle de Santa Clara, 1",
    "sg:city":"Villarrobledo",
    "sg:orig_category":"Producci\u00d3n, Distribuci\u00d3n De Gas Butano Y Propano",
    "sg:phone":"+34 967 14 00 86",
    "sg:postcode":"02600",
    "sg:province":"Albacete",
    "wof:name":"Herederos De Jose Cebrian S.l.",
    "wof:placetype":"venue"
},
  "geometry": {"coordinates":[-2.6027693748,39.2655105591],"type":"Point"}
}