{
  "type": "Feature",
  "properties": {
    "iso:country":"ES",
    "sg:address":"Ptge Dos De Maig, 20",
    "sg:city":"Barcelona",
    "sg:orig_category":"Ropa De Hogar (al Por Menor)",
    "sg:phone":"+34 934 35 63 73",
    "sg:postcode":"08041",
    "sg:province":"Barcelona",
    "wof:name":"Gallifa Faro Josep",
    "wof:placetype":"venue"
},
  "geometry": {"coordinates":[2.1750199795,41.4175033569],"type":"Point"}
}