{
  "type": "Feature",
  "properties": {
    "addr:full":"Calle de Zafra, 32 Feria Badajoz 06390",
    "addr:housenumber":"32",
    "addr:postcode":"06390",
    "addr:street":"Calle De Zafra",
    "iso:country":"ES",
    "sg:address":"Calle de Zafra, 32",
    "sg:city":"Feria",
    "sg:orig_category":"Plomeros",
    "sg:phone":"+34 924 69 41 03",
    "sg:postcode":"06390",
    "sg:province":"Badajoz",
    "wof:name":"Felipe Gomez Quirico",
    "wof:placetype":"venue"
},
  "geometry": {"coordinates":[-6.5624699593,38.5131492615],"type":"Point"}
}