{
  "type": "Feature",
  "properties": {
    "iso:country":"ES",
    "sg:address":"Pg Verdaguer, 199",
    "sg:city":"Igualada",
    "sg:orig_category":"Supermercados Y Hipermercados",
    "sg:phone":"+34 938 05 57 67",
    "sg:postcode":"08700",
    "sg:province":"Barcelona",
    "wof:name":"Grup Supeco Maxor S L",
    "wof:placetype":"venue"
},
  "geometry": {"coordinates":[1.6311240196,41.5779571533],"type":"Point"}
}