{
  "type": "Feature",
  "properties": {
    "iso:country":"ES",
    "sg:address":"Calle de Enmedio, 90",
    "sg:city":"Castellon",
    "sg:orig_category":"M\u00c9dicos: Ginecolog\u00cda Y Obstetricia",
    "sg:phone":"+34 964 23 12 22",
    "sg:postcode":"12001",
    "sg:province":"Castell\u00f3n",
    "wof:name":"Goberna Burquera Javier",
    "wof:placetype":"venue"
},
  "geometry": {"coordinates":[-0.0382071994,39.9871177673],"type":"Point"}
}