{
  "type": "Feature",
  "properties": {
    "iso:country":"ES",
    "sg:address":"Calle de Juan Del Olmo, 55",
    "sg:city":"Almeria",
    "sg:orig_category":"Centros Empresariales",
    "sg:phone":"+34 950 27 59 93",
    "sg:postcode":"04003",
    "sg:province":"Almer\u00eda",
    "wof:name":"Multiservicios Lozaronda S.l.",
    "wof:placetype":"venue"
},
  "geometry": {"coordinates":[-2.4653770924,36.8461875916],"type":"Point"}
}