{
  "type": "Feature",
  "properties": {
    "addr:full":"C/ Sant Marti, 45 Riudarenes Girona 17421",
    "addr:housenumber":"45",
    "addr:postcode":"17421",
    "addr:street":"C / Sant Marti",
    "iso:country":"ES",
    "sg:address":"C/ Sant Marti, 45",
    "sg:city":"Riudarenes",
    "sg:orig_category":"Inform\u00c1tica (estudios, Servicios, Asesor\u00cda, Formaci\u00d3n)",
    "sg:phone":"+34 972 16 45 52",
    "sg:postcode":"17421",
    "sg:province":"Girona",
    "wof:name":"Puig Lloveras Joaquima",
    "wof:placetype":"venue"
},
  "geometry": {"coordinates":[2.7224509716,41.8221893311],"type":"Point"}
}