{
  "type": "Feature",
  "properties": {
    "iso:country":"ES",
    "sg:address":"Calle de Locutorio, S/n",
    "sg:city":"Sanlucar De Barrameda",
    "sg:orig_category":"Empresas De Carpinter\u00cda De Madera",
    "sg:phone":"+34 956 36 25 16",
    "sg:postcode":"11540",
    "sg:province":"C\u00e1diz",
    "wof:name":"Ramirez Blanca Jose Walter",
    "wof:placetype":"venue"
},
  "geometry": {"coordinates":[-6.3554439545,36.777545929],"type":"Point"}
}