{
  "type": "Feature",
  "properties": {
    "iso:country":"ES",
    "sg:address":"Calle de Cereros, 17",
    "sg:city":"Zaragoza",
    "sg:orig_category":"Inform\u00c1tica (estudios, Servicios, Asesor\u00cda, Formaci\u00d3n)",
    "sg:phone":"+34 976 43 03 13",
    "sg:postcode":"50003",
    "sg:province":"Zaragoza",
    "wof:name":"Compuven S.l.",
    "wof:placetype":"venue"
},
  "geometry": {"coordinates":[-0.890355587,41.6570701599],"type":"Point"}
}