{
  "type": "Feature",
  "properties": {
    "iso:country":"ES",
    "sg:address":"Avda Abrantes, 87",
    "sg:city":"Madrid",
    "sg:orig_category":"Quincaller\u00cda (al Por Menor)",
    "sg:phone":"+34 914 69 89 16",
    "sg:postcode":"28025",
    "sg:province":"Madrid",
    "sg:website":"www.ferreteriairisarri.es",
    "wof:name":"Ferreteria Irisarri S.l.",
    "wof:placetype":"venue"
},
  "geometry": {"coordinates":[-3.7356550694,40.3746109009],"type":"Point"}
}