{
  "type": "Feature",
  "properties": {
    "addr:full":"Cmno Nuevo De San Nicolas, 7 Granada Granada 18010",
    "addr:housenumber":"7",
    "addr:postcode":"18010",
    "addr:street":"Cmno Nuevo De San",
    "iso:country":"ES",
    "sg:address":"Cmno Nuevo De San Nicolas, 7",
    "sg:city":"Granada",
    "sg:orig_category":"Farmacias",
    "sg:phone":"+34 958 27 89 45",
    "sg:postcode":"18010",
    "sg:province":"Granada",
    "wof:name":"Sanroma Mendizabal Ana",
    "wof:placetype":"venue"
},
  "geometry": {"coordinates":[-3.5932090282,37.181312561],"type":"Point"}
}