{
  "type": "Feature",
  "properties": {
    "addr:full":"Ptda Carrascot (el), S/n Olleria Valencia 46850",
    "addr:postcode":"46850",
    "addr:street":"Ptda Carrascot El S / N",
    "iso:country":"ES",
    "sg:address":"Ptda Carrascot (el), S/n",
    "sg:city":"Olleria",
    "sg:orig_category":"Agencias Y Agentes Comerciales, Representantes",
    "sg:phone":"+34 962 20 22 75",
    "sg:postcode":"46850",
    "sg:province":"Valencia",
    "wof:name":"Mossega Textil S.l.",
    "wof:placetype":"venue"
},
  "geometry": {"coordinates":[-0.5478360057,38.9096603394],"type":"Point"}
}