{
  "type": "Feature",
  "properties": {
    "addr:full":"Avda Puente De Carlos Iii, 37 Reinosa Cantabria 39200",
    "addr:housenumber":"37",
    "addr:postcode":"39200",
    "addr:street":"Avda Puente De Carlos Iii",
    "iso:country":"ES",
    "sg:address":"Avda Puente De Carlos Iii, 37",
    "sg:city":"Reinosa",
    "sg:orig_category":"Florister\u00cdas",
    "sg:phone":"+34 942 75 26 91",
    "sg:postcode":"39200",
    "sg:province":"Cantabria",
    "wof:name":"Gutierrez Garcia Aniano",
    "wof:placetype":"venue"
},
  "geometry": {"coordinates":[-4.1393961906,42.9971961975],"type":"Point"}
}