{
  "type": "Feature",
  "properties": {
    "addr:full":"Ctra. Puigpunyent, 2 Sa Vileta Islas Baleares 07011",
    "addr:housenumber":"2",
    "addr:postcode":"07011",
    "addr:street":"Ctra. Puigpunyent;Vileta",
    "iso:country":"ES",
    "sg:address":"Ctra. Puigpunyent, 2",
    "sg:city":"Sa Vileta",
    "sg:orig_category":"Equitaci\u00d3n Y Centros De H\u00cdpica",
    "sg:phone":"+34 971 79 85 78",
    "sg:postcode":"07011",
    "sg:province":"Islas Baleares",
    "wof:name":"Club Escuela Equitacion Son Gual S.l.",
    "wof:placetype":"venue"
},
  "geometry": {"coordinates":[2.6271300316,39.5906105042],"type":"Point"}
}