{
  "type": "Feature",
  "properties": {
    "addr:full":"Av Catalunya, 17 Cervera Lleida 25200",
    "addr:housenumber":"17",
    "addr:postcode":"25200",
    "addr:street":"Av Catalunya",
    "iso:country":"ES",
    "sg:address":"Av Catalunya, 17",
    "sg:city":"Cervera",
    "sg:orig_category":"Ense\u00d1anza Variada",
    "sg:phone":"+34 973 53 18 77",
    "sg:postcode":"25200",
    "sg:province":"Lleida",
    "wof:name":"Academia Madern S.c.p.",
    "wof:placetype":"venue"
},
  "geometry": {"coordinates":[1.2734286785,41.6717376709],"type":"Point"}
}