{
  "type": "Feature",
  "properties": {
    "iso:country":"ES",
    "sg:address":"Avda Raza (la), 2",
    "sg:city":"Sevilla",
    "sg:orig_category":"Tapones Y Art\u00cdculos De Corcho",
    "sg:phone":"+34 954 23 88 30",
    "sg:postcode":"41012",
    "sg:province":"Sevilla",
    "wof:name":"Corcho Y Piel S.l.",
    "wof:placetype":"venue"
},
  "geometry": {"coordinates":[-5.9894590378,37.3666000366],"type":"Point"}
}