{
  "type": "Feature",
  "properties": {
    "addr:full":"Avda Hytasa, 57 Sevilla Sevilla 41006",
    "addr:housenumber":"57",
    "addr:postcode":"41006",
    "addr:street":"Avda Hytasa",
    "iso:country":"ES",
    "sg:address":"Avda Hytasa, 57",
    "sg:city":"Sevilla",
    "sg:orig_category":"Farmacias",
    "sg:phone":"+34 954 63 52 88",
    "sg:postcode":"41006",
    "sg:province":"Sevilla",
    "wof:name":"Osma Alonso Pasion",
    "wof:placetype":"venue"
},
  "geometry": {"coordinates":[-5.9599919319,37.3706817627],"type":"Point"}
}