{
  "type": "Feature",
  "properties": {
    "iso:country":"ES",
    "sg:address":"Ctra. Yuncos, Km. 0001,0",
    "sg:city":"Cedillo Condado",
    "sg:orig_category":"Empresas De Carpinter\u00cda",
    "sg:phone":"+34 925 50 87 76",
    "sg:postcode":"45214",
    "sg:province":"Toledo",
    "wof:name":"Aluminios Garcia Fernandez S.l.",
    "wof:placetype":"venue"
},
  "geometry": {"coordinates":[-3.9420824051,40.0659484863],"type":"Point"}
}