{
  "type": "Feature",
  "properties": {
    "addr:full":"Calle de Padre Camara, 8 Salamanca Salamanca 37004",
    "addr:housenumber":"8",
    "addr:postcode":"37004",
    "addr:street":"Calle De Padre Camara",
    "iso:country":"ES",
    "sg:address":"Calle de Padre Camara, 8",
    "sg:city":"Salamanca",
    "sg:orig_category":"Muebles, Minoristas",
    "sg:phone":"+34 923 25 80 36",
    "sg:postcode":"37004",
    "sg:province":"Salamanca",
    "wof:name":"Comercial Joga S.a.",
    "wof:placetype":"venue"
},
  "geometry": {"coordinates":[-5.6583528519,40.9700698853],"type":"Point"}
}