{
  "type": "Feature",
  "properties": {
    "iso:country":"ES",
    "sg:address":"Ctra. Oropesa, 27",
    "sg:city":"Candeleda",
    "sg:orig_category":"Mec\u00c1nico Del Autom\u00d3vil",
    "sg:phone":"+34 920 38 01 22",
    "sg:postcode":"05480",
    "sg:province":"\u00c1vila",
    "wof:name":"Autos Candeleda S.l.",
    "wof:placetype":"venue"
},
  "geometry": {"coordinates":[-5.2322301865,40.1393127441],"type":"Point"}
}