{
  "type": "Feature",
  "properties": {
    "iso:country":"ES",
    "sg:address":"Ctra Castellar, 55",
    "sg:city":"Terrassa",
    "sg:orig_category":"Agencias De Viajes",
    "sg:phone":"+34 937 36 39 10",
    "sg:postcode":"08222",
    "sg:province":"Barcelona",
    "sg:website":"www.marsans.es",
    "wof:name":"Viajes Marsans S.a.",
    "wof:placetype":"venue"
},
  "geometry": {"coordinates":[2.0232839584,41.5656661987],"type":"Point"}
}