{
  "type": "Feature",
  "properties": {
    "iso:country":"ES",
    "sg:address":"Carrer de Soler I March, 5",
    "sg:city":"Manresa",
    "sg:orig_category":"Servicios Y Funcionarios De Polic\u00cda",
    "sg:phone":"+34 938 74 99 10",
    "sg:postcode":"08242",
    "sg:province":"Barcelona",
    "sg:website":"www.mir.es",
    "wof:name":"Direccion General De La Policia",
    "wof:placetype":"venue"
},
  "geometry": {"coordinates":[1.8248900175,41.7310066223],"type":"Point"}
}