{
  "type": "Feature",
  "properties": {
    "iso:country":"ES",
    "sg:address":"Urb. San Miguel, 6",
    "sg:city":"A Carida",
    "sg:orig_category":"Quincaller\u00cda (al Por Menor)",
    "sg:phone":"+34 985 63 75 14",
    "sg:postcode":"33750",
    "sg:province":"Asturias",
    "wof:name":"Alonso Mendez Jose Jesus",
    "wof:placetype":"venue"
},
  "geometry": {"coordinates":[-5.9832577705,43.2504386902],"type":"Point"}
}