{
  "type": "Feature",
  "properties": {
    "iso:country":"ES",
    "sg:address":"Plaz Virgen (de La), 11",
    "sg:city":"Hijar",
    "sg:orig_category":"Venta, Instalaci\u00d3n De Calefacci\u00d3n",
    "sg:phone":"+34 978 82 02 15",
    "sg:postcode":"44530",
    "sg:province":"Teruel",
    "wof:name":"Turon Molias Pedro Jose",
    "wof:placetype":"venue"
},
  "geometry": {"coordinates":[-0.4508099854,41.173625946],"type":"Point"}
}