{
  "type": "Feature",
  "properties": {
    "iso:country":"ES",
    "sg:address":"Calle de Duque De Ahumada, 3",
    "sg:city":"Toledo",
    "sg:orig_category":"Pod\u00d3logos: Pedicuros",
    "sg:phone":"+34 925 21 66 41",
    "sg:postcode":"45005",
    "sg:province":"Toledo",
    "wof:name":"Ortopedia Toledo C.b.",
    "wof:placetype":"venue"
},
  "geometry": {"coordinates":[-4.0359325409,39.8723487854],"type":"Point"}
}