{
  "type": "Feature",
  "properties": {
    "iso:country":"ES",
    "sg:address":"Calle de Sol Del, 9",
    "sg:city":"Tineo",
    "sg:orig_category":"Alimentaci\u00d3n General (al Por Menor)",
    "sg:phone":"+34 985 80 17 80",
    "sg:postcode":"33870",
    "sg:province":"Asturias",
    "wof:name":"Mantequera De Tineo S. A.",
    "wof:placetype":"venue"
},
  "geometry": {"coordinates":[-6.4165468216,43.3338775635],"type":"Point"}
}