{
  "type": "Feature",
  "properties": {
    "addr:full":"Ctra. Murgis, S/n Ejido Almer\u00eda 04700",
    "addr:housenumber":"s",
    "addr:postcode":"04700",
    "addr:street":"Ctra. Murgis;/ N Ejido Almeri\u0301A",
    "iso:country":"ES",
    "sg:address":"Ctra. Murgis, S/n",
    "sg:city":"Ejido",
    "sg:orig_category":"Cementerios",
    "sg:phone":"+34 950 48 65 25",
    "sg:postcode":"04700",
    "sg:province":"Almer\u00eda",
    "wof:name":"Ayuntamiento De El Ejido",
    "wof:placetype":"venue"
},
  "geometry": {"coordinates":[-2.8089163303,36.7774085999],"type":"Point"}
}