{
  "type": "Feature",
  "properties": {
    "addr:full":"Carrer de Industria, 24 Tona Barcelona 08551",
    "addr:housenumber":"24",
    "addr:postcode":"08551",
    "addr:street":"Carrer De Industria",
    "iso:country":"ES",
    "sg:address":"Carrer de Industria, 24",
    "sg:city":"Tona",
    "sg:orig_category":"Puertas Y Portales",
    "sg:phone":"+34 938 12 57 42",
    "sg:postcode":"08551",
    "sg:province":"Barcelona",
    "sg:website":"www.pcmadera.com",
    "wof:name":"Puertas Cortafuego Madera S.l.",
    "wof:placetype":"venue"
},
  "geometry": {"coordinates":[2.2355620861,41.8516693115],"type":"Point"}
}