{
  "type": "Feature",
  "properties": {
    "iso:country":"ES",
    "sg:address":"Calle de Guardilama, 17",
    "sg:city":"Puerto Del Carmen",
    "sg:orig_category":"Ropa Para Se\u00d1oras Y Caballeros (al Por Menor)",
    "sg:phone":"+34 928 84 12 59",
    "sg:postcode":"35510",
    "sg:province":"Las Palmas",
    "sg:website":"www.incognito.ws",
    "wof:name":"Chighannoa S.l.",
    "wof:placetype":"venue"
},
  "geometry": {"coordinates":[-13.667339325,28.9226837158],"type":"Point"}
}