{
  "type": "Feature",
  "properties": {
    "addr:full":"Calle de Caraba\u00d1a, 18 Alcala Henares Madrid 28806",
    "addr:housenumber":"18",
    "addr:postcode":"28806",
    "addr:street":"Calle De Caraban\u0303A",
    "iso:country":"ES",
    "sg:address":"Calle de Caraba\u00d1a, 18",
    "sg:city":"Alcala Henares",
    "sg:orig_category":"Puertas Y Portales",
    "sg:phone":"+34 918 83 18 12",
    "sg:postcode":"28806",
    "sg:province":"Madrid",
    "sg:website":"www.kone.com",
    "wof:name":"Kone Elevadores S.a.",
    "wof:placetype":"venue"
},
  "geometry": {"coordinates":[-3.3653481007,40.4905471802],"type":"Point"}
}