{
  "type": "Feature",
  "properties": {
    "addr:full":"Calle de Constitucion, 9 Caspe Zaragoza 50700",
    "addr:housenumber":"9",
    "addr:postcode":"50700",
    "addr:street":"Calle De Constitucion",
    "iso:country":"ES",
    "sg:address":"Calle de Constitucion, 9",
    "sg:city":"Caspe",
    "sg:orig_category":"Chapister\u00cda",
    "sg:phone":"+34 976 63 32 91",
    "sg:postcode":"50700",
    "sg:province":"Zaragoza",
    "wof:name":"Buisan Franco Francisco",
    "wof:placetype":"venue"
},
  "geometry": {"coordinates":[-0.1274659932,41.2623100281],"type":"Point"}
}