{
  "type": "Feature",
  "properties": {
    "addr:full":"Avda Jose Gines Fernandez, 1 Rosales Sevilla 41330",
    "addr:housenumber":"1",
    "addr:postcode":"41330",
    "addr:street":"Avda Jose Gines Fernandez",
    "iso:country":"ES",
    "sg:address":"Avda Jose Gines Fernandez, 1",
    "sg:city":"Rosales",
    "sg:orig_category":"Cajas Para Embalar",
    "sg:phone":"+34 955 64 61 27",
    "sg:postcode":"41330",
    "sg:province":"Sevilla",
    "wof:name":"Caja Rural Del Sur Sociedad Cooperativa",
    "wof:placetype":"venue"
},
  "geometry": {"coordinates":[-5.7319440842,37.5898590088],"type":"Point"}
}