{
  "type": "Feature",
  "properties": {
    "iso:country":"ES",
    "sg:address":"Calle de San Francisco, 20",
    "sg:city":"Donostia-san Sebastian",
    "sg:orig_category":"Ropa Para Se\u00d1oras (al Por Menor)",
    "sg:phone":"+34 943 29 76 85",
    "sg:postcode":"20001",
    "sg:province":"Guip\u00f9zcoa",
    "wof:name":"Sanchez Villaron Francisco",
    "wof:placetype":"venue"
},
  "geometry": {"coordinates":[-1.9736939669,43.3237342834],"type":"Point"}
}