{
  "type": "Feature",
  "properties": {
    "addr:full":"Calle de Santa Engracia, 107 Madrid Madrid 28010",
    "addr:housenumber":"107",
    "addr:postcode":"28010",
    "addr:street":"Calle De Santa Engracia",
    "iso:country":"ES",
    "sg:address":"Calle de Santa Engracia, 107",
    "sg:city":"Madrid",
    "sg:orig_category":"Farmacias",
    "sg:phone":"+34 914 47 62 47",
    "sg:postcode":"28010",
    "sg:province":"Madrid",
    "wof:name":"Jorba De La Fuente Gregorio",
    "wof:placetype":"venue"
},
  "geometry": {"coordinates":[-3.6997420788,40.4370689392],"type":"Point"}
}