{
  "type": "Feature",
  "properties": {
    "addr:full":"Calle de Valle De Broto, 1 Zaragoza Zaragoza 50015",
    "addr:housenumber":"1",
    "addr:postcode":"50015",
    "addr:street":"Calle De Valle De Broto",
    "iso:country":"ES",
    "sg:address":"Calle de Valle De Broto, 1",
    "sg:city":"Zaragoza",
    "sg:orig_category":"Molduras, Junquillos, Listones Y Molduras Perforadas",
    "sg:phone":"+34 976 51 27 80",
    "sg:postcode":"50015",
    "sg:province":"Zaragoza",
    "wof:name":"Urue\u00f1a Fernandez Delfina",
    "wof:placetype":"venue"
},
  "geometry": {"coordinates":[-0.8722839952,41.6663589478],"type":"Point"}
}