{
  "type": "Feature",
  "properties": {
    "iso:country":"ES",
    "sg:address":"Pase Ruise\u00d1ores, 41",
    "sg:city":"Zaragoza",
    "sg:orig_category":"Inmobiliaria (agencias)",
    "sg:phone":"+34 976 37 43 12",
    "sg:postcode":"50006",
    "sg:province":"Zaragoza",
    "wof:name":"Promotora Inmobiliaria M-3 S.a.",
    "wof:placetype":"venue"
},
  "geometry": {"coordinates":[-0.8889859915,41.6363334656],"type":"Point"}
}