{
  "type": "Feature",
  "properties": {
    "addr:full":"Carrer de Major, 19 Mataro Barcelona 08303",
    "addr:housenumber":"19",
    "addr:postcode":"08303",
    "addr:street":"Carrer De Major",
    "iso:country":"ES",
    "sg:address":"Carrer de Major, 19",
    "sg:city":"Mataro",
    "sg:orig_category":"Peluquer\u00cdas, Peluquer\u00cda Mixta",
    "sg:phone":"+34 937 98 43 66",
    "sg:postcode":"08303",
    "sg:province":"Barcelona",
    "wof:name":"Gonzalez Gonzalez Patricio",
    "wof:placetype":"venue"
},
  "geometry": {"coordinates":[2.4265611172,41.5410919189],"type":"Point"}
}