{
  "type": "Feature",
  "properties": {
    "addr:full":"Plaz Comuneros (de Los), 6 Coslada Madrid 28820",
    "addr:housenumber":"6",
    "addr:postcode":"28820",
    "addr:street":"Plaz Comuneros De Los",
    "iso:country":"ES",
    "sg:address":"Plaz Comuneros (de Los), 6",
    "sg:city":"Coslada",
    "sg:orig_category":"Caf\u00c9s, Bares, Cervecer\u00cdas",
    "sg:phone":"+34 916 73 81 36",
    "sg:postcode":"28820",
    "sg:province":"Madrid",
    "wof:name":"Cytasa Comunicaciones S.l.",
    "wof:placetype":"venue"
},
  "geometry": {"coordinates":[-3.5645070076,40.4260902405],"type":"Point"}
}