{
  "type": "Feature",
  "properties": {
    "iso:country":"ES",
    "sg:address":"Pl Corona, 5",
    "sg:city":"Granollers",
    "sg:orig_category":"M\u00c9dicos: Pediatr\u00cda. Enfermedades De Los Ni\u00d1os",
    "sg:phone":"+34 938 70 47 40",
    "sg:postcode":"08402",
    "sg:province":"Barcelona",
    "wof:name":"Tura Pou Gines",
    "wof:placetype":"venue"
},
  "geometry": {"coordinates":[2.2886099815,41.6059989929],"type":"Point"}
}