{
  "type": "Feature",
  "properties": {
    "iso:country":"ES",
    "sg:address":"Avda Castros (los), 1",
    "sg:city":"Santander",
    "sg:orig_category":"Asesor\u00cda Fiscal Y Jur\u00cddica",
    "sg:phone":"+34 942 27 39 03",
    "sg:postcode":"39005",
    "sg:province":"Cantabria",
    "sg:website":"www.atriusasociados.com",
    "wof:name":"Atrius Asociados Sa.",
    "wof:placetype":"venue"
},
  "geometry": {"coordinates":[-3.7853212357,43.4738197327],"type":"Point"}
}