{
  "type": "Feature",
  "properties": {
    "iso:country":"ES",
    "sg:address":"Calle de Pintor Mu\u00d1oz Barberan, 2",
    "sg:city":"Palmar  O Lugar De Don Juan",
    "sg:orig_category":"Panader\u00cdas, Panader\u00cdas",
    "sg:phone":"+34 968 88 00 88",
    "sg:postcode":"30120",
    "sg:province":"Murcia",
    "wof:name":"Confiteria Pasteleria La Gloria S.l.",
    "wof:placetype":"venue"
},
  "geometry": {"coordinates":[-1.1302490234,37.9829597473],"type":"Point"}
}