{
  "type": "Feature",
  "properties": {
    "iso:country":"ES",
    "sg:address":"Calle de Iturleku, 12",
    "sg:city":"Berreagamendi",
    "sg:orig_category":"Pescader\u00cdas (al Por Menor)",
    "sg:phone":"+34 946 74 22 51",
    "sg:postcode":"48100",
    "sg:province":"Vizcaya",
    "wof:name":"Pescaderias Borge S.l.",
    "wof:placetype":"venue"
},
  "geometry": {"coordinates":[-2.8465230465,43.3247146606],"type":"Point"}
}