{
  "type": "Feature",
  "properties": {
    "addr:full":"Avgd Alcalde Porqueres, 43 Lleida Lleida 25008",
    "addr:housenumber":"43",
    "addr:postcode":"25008",
    "addr:street":"Alcalde Porqueres",
    "iso:country":"ES",
    "sg:address":"Avgd Alcalde Porqueres, 43",
    "sg:city":"Lleida",
    "sg:orig_category":"Iglesias Evang\u00c9licas",
    "sg:phone":"+34 973 23 32 67",
    "sg:postcode":"25008",
    "sg:province":"Lleida",
    "wof:name":"Iglesia Evangelica Bautista",
    "wof:placetype":"venue"
},
  "geometry": {"coordinates":[0.6228209734,41.62474823],"type":"Point"}
}