{
  "type": "Feature",
  "properties": {
    "addr:full":"Calle de Getaria, 4 Donostia-san Sebastian Guip\u00f9zcoa 20005",
    "addr:housenumber":"4",
    "addr:postcode":"20005",
    "addr:street":"Calle De Getaria",
    "iso:country":"ES",
    "sg:address":"Calle de Getaria, 4",
    "sg:city":"Donostia-san Sebastian",
    "sg:orig_category":"Trajes Y Adornos De Boda (confecci\u00d3n, Al Por Menor)",
    "sg:phone":"+34 943 42 59 82",
    "sg:postcode":"20005",
    "sg:province":"Guip\u00f9zcoa",
    "wof:name":"Chivite Fernandez Miguel",
    "wof:placetype":"venue"
},
  "geometry": {"coordinates":[-1.9813040495,43.3188552856],"type":"Point"}
}