{
  "type": "Feature",
  "properties": {
    "iso:country":"ES",
    "sg:address":"Ctra. Puente Chico, S/n",
    "sg:city":"Los Barrios",
    "sg:orig_category":"Ingenier\u00cda, Centros De Estudios (diversos)",
    "sg:phone":"+34 956 62 33 34",
    "sg:postcode":"11370",
    "sg:province":"C\u00e1diz",
    "sg:website":"www.geolen.es",
    "wof:name":"Geolen Ingenieria S.l.",
    "wof:placetype":"venue"
},
  "geometry": {"coordinates":[-5.5407299995,36.2001647949],"type":"Point"}
}