{
  "type": "Feature",
  "properties": {
    "addr:full":"Avda Andalucia, 41 Puebla De Los Infantes Sevilla 41479",
    "addr:housenumber":"41",
    "addr:postcode":"41479",
    "addr:street":"Avda Andalucia",
    "iso:country":"ES",
    "sg:address":"Avda Andalucia, 41",
    "sg:city":"Puebla De Los Infantes",
    "sg:orig_category":"Carnicer\u00cdas, Carnicer\u00cdas",
    "sg:phone":"+34 954 80 87 47",
    "sg:postcode":"41479",
    "sg:province":"Sevilla",
    "wof:name":"Almenara Lopez Ana Maria",
    "wof:placetype":"venue"
},
  "geometry": {"coordinates":[-5.3874030113,37.7796173096],"type":"Point"}
}