{
  "type": "Feature",
  "properties": {
    "addr:full":"Calle de Mar (del), S/n Vera Almer\u00eda 04620",
    "addr:housenumber":"/ n;almeri\u0301a",
    "addr:postcode":"04620",
    "addr:street":"Calle De;Del S",
    "iso:country":"ES",
    "sg:address":"Calle de Mar (del), S/n",
    "sg:city":"Vera",
    "sg:orig_category":"Asesor\u00cda Fiscal Y Jur\u00cddica",
    "sg:phone":"+34 950 39 06 01",
    "sg:postcode":"04620",
    "sg:province":"Almer\u00eda",
    "wof:name":"Hidalgo Fernandez Bartolome",
    "wof:placetype":"venue"
},
  "geometry": {"coordinates":[-1.8687889576,37.2485542297],"type":"Point"}
}