{
  "type": "Feature",
  "properties": {
    "addr:full":"Calle de General Santocildes, 4 Burgos Burgos 09003",
    "addr:housenumber":"4",
    "addr:postcode":"09003",
    "addr:street":"Calle De General Santocildes",
    "iso:country":"ES",
    "sg:address":"Calle de General Santocildes, 4",
    "sg:city":"Burgos",
    "sg:orig_category":"Lencer\u00cda Femenina, Corseter\u00cda, Trajes De Ba\u00d1o (al Por Menor)",
    "sg:phone":"+34 947 26 71 31",
    "sg:postcode":"09003",
    "sg:province":"Burgos",
    "wof:name":"Ana Maria Lucaya Casals S.l.",
    "wof:placetype":"venue"
},
  "geometry": {"coordinates":[-3.6996591091,42.3432044983],"type":"Point"}
}