{
  "type": "Feature",
  "properties": {
    "iso:country":"ES",
    "sg:address":"Calle de Mari, 5",
    "sg:city":"Donostia-san Sebastian",
    "sg:orig_category":"Asociaciones, Organismos Culturales Y Socioeducativos",
    "sg:phone":"+34 943 43 17 93",
    "sg:postcode":"20003",
    "sg:province":"Guip\u00f9zcoa",
    "wof:name":"Sociedad Euskal-billera",
    "wof:placetype":"venue"
},
  "geometry": {"coordinates":[-1.9866549969,43.3223953247],"type":"Point"}
}