{
  "type": "Feature",
  "properties": {
    "iso:country":"ES",
    "sg:address":"Plaz Fuente Nueva, 2",
    "sg:city":"Martos",
    "sg:orig_category":"Art\u00cdculos De Regalo (al Por Menor)",
    "sg:phone":"+34 953 70 01 26",
    "sg:postcode":"23600",
    "sg:province":"Ja\u00e9n",
    "wof:name":"Delgado Barranco Francisco",
    "wof:placetype":"venue"
},
  "geometry": {"coordinates":[-3.9701869488,37.7225837708],"type":"Point"}
}