{
  "type": "Feature",
  "properties": {
    "iso:country":"ES",
    "sg:address":"Pase Habana, 190",
    "sg:city":"Madrid",
    "sg:orig_category":"Abogados",
    "sg:phone":"+34 913 59 70 90",
    "sg:postcode":"28036",
    "sg:province":"Madrid",
    "wof:name":"Dominguez Fernandez Ana Maria",
    "wof:placetype":"venue"
},
  "geometry": {"coordinates":[-3.6803290844,40.4615898132],"type":"Point"}
}