{
  "type": "Feature",
  "properties": {
    "addr:full":"Calle de Sevilla, 2 Trigueros Huelva 21620",
    "addr:housenumber":"2",
    "addr:postcode":"21620",
    "addr:street":"Calle De Sevilla",
    "iso:country":"ES",
    "sg:address":"Calle de Sevilla, 2",
    "sg:city":"Trigueros",
    "sg:orig_category":"Cooperativas Agr\u00cdcolas",
    "sg:phone":"+34 959 30 51 96",
    "sg:postcode":"21620",
    "sg:province":"Huelva",
    "wof:name":"Cooperativa Olivares San Antonio Abad",
    "wof:placetype":"venue"
},
  "geometry": {"coordinates":[-6.8299279213,37.3829994202],"type":"Point"}
}