{
  "type": "Feature",
  "properties": {
    "addr:full":"Calle de Paralela A La Palmera, 8 Vall D'uixo Castell\u00f3n 12600",
    "addr:housenumber":"8",
    "addr:postcode":"12600",
    "addr:street":"Calle De Paralela A La Palmera",
    "iso:country":"ES",
    "sg:address":"Calle de Paralela A La Palmera, 8",
    "sg:city":"Vall D'uixo",
    "sg:orig_category":"Plomeros",
    "sg:phone":"+34 964 69 13 14",
    "sg:postcode":"12600",
    "sg:province":"Castell\u00f3n",
    "wof:name":"Fontaneria Castilla S.l.",
    "wof:placetype":"venue"
},
  "geometry": {"coordinates":[-0.0482099988,39.992477417],"type":"Point"}
}