{
  "type": "Feature",
  "properties": {
    "addr:full":"Rbla Rambla, 22 Sabadell Barcelona 08201",
    "addr:housenumber":"22",
    "addr:postcode":"08201",
    "addr:street":"Rambla",
    "iso:country":"ES",
    "sg:address":"Rbla Rambla, 22",
    "sg:city":"Sabadell",
    "sg:orig_category":"Cajas De Ahorro",
    "sg:phone":"+34 937 26 74 33",
    "sg:postcode":"08201",
    "sg:province":"Barcelona",
    "sg:website":"www.bancaja.es",
    "wof:name":"Caja De Ahorros De Valencia Castellon Y Alicante",
    "wof:placetype":"venue"
},
  "geometry": {"coordinates":[2.1093239784,41.5456123352],"type":"Point"}
}