{
  "type": "Feature",
  "properties": {
    "addr:full":"Calle de Alcalde Blazquez, 13 Cadiz C\u00e1diz 11012",
    "addr:housenumber":"13",
    "addr:postcode":"11012",
    "addr:street":"Calle De Alcalde Blazquez",
    "iso:country":"ES",
    "sg:address":"Calle de Alcalde Blazquez, 13",
    "sg:city":"Cadiz",
    "sg:orig_category":"Iglesia Cat\u00d3lica",
    "sg:phone":"+34 956 28 00 56",
    "sg:postcode":"11012",
    "sg:province":"C\u00e1diz",
    "wof:name":"Parroquia Nuestra Se\u00f1ora De La Asuncion",
    "wof:placetype":"venue"
},
  "geometry": {"coordinates":[-6.2734894753,36.5102081299],"type":"Point"}
}