{
  "type": "Feature",
  "properties": {
    "iso:country":"ES",
    "sg:address":"Carr Sant Lloren\u00c7, 7",
    "sg:city":"Solsona",
    "sg:orig_category":"Contenedores (mercanc\u00cdas)",
    "sg:phone":"+34 973 48 13 68",
    "sg:postcode":"25280",
    "sg:province":"Lleida",
    "wof:name":"Serviexpres Del Solsones S.l.",
    "wof:placetype":"venue"
},
  "geometry": {"coordinates":[1.5186200142,41.9953193665],"type":"Point"}
}