{
  "type": "Feature",
  "properties": {
    "addr:full":"Ctra Salamanca, 5 Bejar Salamanca 37700",
    "addr:housenumber":"5",
    "addr:postcode":"37700",
    "addr:street":"Ctra Salamanca",
    "iso:country":"ES",
    "sg:address":"Ctra Salamanca, 5",
    "sg:city":"Bejar",
    "sg:orig_category":"Oficinas De Turismo, Asociaciones De Iniciativa",
    "sg:phone":"+34 923 40 30 05",
    "sg:postcode":"37700",
    "sg:province":"Salamanca",
    "sg:website":"www.ayuntamientobejar.com",
    "wof:name":"Ayuntamiento De Bejar",
    "wof:placetype":"venue"
},
  "geometry": {"coordinates":[-5.7490091324,40.3899536133],"type":"Point"}
}