{
  "type": "Feature",
  "properties": {
    "addr:full":"Calle de Amargura, 5 Herrera Sevilla 41567",
    "addr:housenumber":"5",
    "addr:postcode":"41567",
    "addr:street":"Calle De Amargura",
    "iso:country":"ES",
    "sg:address":"Calle de Amargura, 5",
    "sg:city":"Herrera",
    "sg:orig_category":"Reposter\u00cdas",
    "sg:phone":"+34 954 01 32 61",
    "sg:postcode":"41567",
    "sg:province":"Sevilla",
    "wof:name":"Caceres Cornejo Jose",
    "wof:placetype":"venue"
},
  "geometry": {"coordinates":[-4.8494057655,37.3670043945],"type":"Point"}
}