{
  "type": "Feature",
  "properties": {
    "addr:full":"Av Sant Narcis, 111 Girona Girona 17005",
    "addr:housenumber":"111",
    "addr:postcode":"17005",
    "addr:street":"Av Sant Narcis",
    "iso:country":"ES",
    "sg:address":"Av Sant Narcis, 111",
    "sg:city":"Girona",
    "sg:orig_category":"Motocicletas (agentes, Concesionarios)",
    "sg:phone":"+34 972 40 03 04",
    "sg:postcode":"17005",
    "sg:province":"Girona",
    "sg:website":"www.motostrafach.com",
    "wof:name":"Motos Trafach S.l.",
    "wof:placetype":"venue"
},
  "geometry": {"coordinates":[2.8114900589,41.9696426392],"type":"Point"}
}