{
  "type": "Feature",
  "properties": {
    "addr:full":"Carrer de Vallespir, S/n Barcelona Barcelona 08014",
    "addr:housenumber":"s / n",
    "addr:postcode":"08014",
    "addr:street":"Carrer De Vallespir",
    "iso:country":"ES",
    "sg:address":"Carrer de Vallespir, S/n",
    "sg:city":"Barcelona",
    "sg:orig_category":"Centros De Educaci\u00d3n Especial",
    "sg:phone":"+34 934 91 48 17",
    "sg:postcode":"08014",
    "sg:province":"Barcelona",
    "wof:name":"Ajuntament De Barcelona",
    "wof:placetype":"venue"
},
  "geometry": {"coordinates":[2.1354987621,41.381778717],"type":"Point"}
}