{
  "type": "Feature",
  "properties": {
    "addr:full":"Calle de Salobral D (cha), 5 Madrid Madrid 28045",
    "addr:housenumber":"5",
    "addr:postcode":"28045",
    "addr:street":"Calle De Salobral D Cha",
    "iso:country":"ES",
    "sg:address":"Calle de Salobral D (cha), 5",
    "sg:city":"Madrid",
    "sg:orig_category":"Estancos",
    "sg:phone":"+34 915 30 23 12",
    "sg:postcode":"28045",
    "sg:province":"Madrid",
    "wof:name":"Fernandez Maya Francisco",
    "wof:placetype":"venue"
},
  "geometry": {"coordinates":[-3.7057740688,40.42029953],"type":"Point"}
}