{
  "type": "Feature",
  "properties": {
    "addr:full":"Calle de Daoiz Y Velarde, 79 A\u00e7over De Tajo Toledo 45250",
    "addr:housenumber":"79",
    "addr:postcode":"45250",
    "addr:street":"Calle De Daoiz Y Velarde",
    "iso:country":"ES",
    "sg:address":"Calle de Daoiz Y Velarde, 79",
    "sg:city":"A\u00e7over De Tajo",
    "sg:orig_category":"Materiales De Aislamiento T\u00c9rmico Y Ac\u00dastico",
    "sg:phone":"+34 925 50 63 04",
    "sg:postcode":"45250",
    "sg:province":"Toledo",
    "wof:name":"Ortega Diaz Jose Daoiz",
    "wof:placetype":"venue"
},
  "geometry": {"coordinates":[-3.7634861469,39.9882316589],"type":"Point"}
}