{
  "type": "Feature",
  "properties": {
    "addr:full":"Praz Riestra, 1 Caeira Pontevedra 36005",
    "addr:housenumber":"1",
    "addr:postcode":"36005",
    "addr:street":"Riestra",
    "iso:country":"ES",
    "sg:address":"Praz Riestra, 1",
    "sg:city":"Caeira",
    "sg:orig_category":"Abogados",
    "sg:phone":"+34 986 87 32 58",
    "sg:postcode":"36005",
    "sg:province":"Pontevedra",
    "wof:name":"Garcia Basanta Maria Dolores",
    "wof:placetype":"venue"
},
  "geometry": {"coordinates":[-8.6331739426,42.4493751526],"type":"Point"}
}