{
  "type": "Feature",
  "properties": {
    "iso:country":"ES",
    "sg:address":"Calle de Burgo De Osma, 25",
    "sg:city":"Aranda Duero",
    "sg:orig_category":"Venta, Instalaci\u00d3n De Calefacci\u00d3n",
    "sg:phone":"+34 947 50 78 86",
    "sg:postcode":"09400",
    "sg:province":"Burgos",
    "wof:name":"Instalaciones Bm S.l.",
    "wof:placetype":"venue"
},
  "geometry": {"coordinates":[-3.6886940002,41.6674766541],"type":"Point"}
}