{
  "type": "Feature",
  "properties": {
    "iso:country":"ES",
    "sg:address":"Calle de Juan Ramon Jimenez, 17",
    "sg:city":"Trigueros",
    "sg:orig_category":"Mec\u00c1nico Del Autom\u00d3vil",
    "sg:phone":"+34 959 30 51 15",
    "sg:postcode":"21620",
    "sg:province":"Huelva",
    "wof:name":"Taller Mecanico San Miguel S.l.",
    "wof:placetype":"venue"
},
  "geometry": {"coordinates":[-6.8315029144,37.3822021484],"type":"Point"}
}