{
  "type": "Feature",
  "properties": {
    "iso:country":"ES",
    "sg:address":"Carrer de Sant Pere, 46",
    "sg:city":"Lloret Mar",
    "sg:orig_category":"Regalos, Souvenires (fabricaci\u00d3n, Al Por Mayor)",
    "sg:phone":"+34 972 36 02 46",
    "sg:postcode":"17310",
    "sg:province":"Girona",
    "wof:name":"Navlani  Kishan Chand",
    "wof:placetype":"venue"
},
  "geometry": {"coordinates":[2.8460879326,41.7010269165],"type":"Point"}
}