{
  "type": "Feature",
  "properties": {
    "addr:full":"Avda Italia, 59 Huelva Huelva 21001",
    "addr:housenumber":"59",
    "addr:postcode":"21001",
    "addr:street":"Avda Italia",
    "iso:country":"ES",
    "sg:address":"Avda Italia, 59",
    "sg:city":"Huelva",
    "sg:orig_category":"Molduras, Junquillos, Listones Y Molduras Perforadas",
    "sg:phone":"+34 959 24 99 72",
    "sg:postcode":"21001",
    "sg:province":"Huelva",
    "wof:name":"Bar Expres C.b.",
    "wof:placetype":"venue"
},
  "geometry": {"coordinates":[-6.9513487816,37.2536582947],"type":"Point"}
}