{
  "type": "Feature",
  "properties": {
    "addr:full":"Av Alemanya, 34 Segur Calafell Tarragona 43882",
    "addr:housenumber":"34",
    "addr:postcode":"43882",
    "addr:street":"Av Alemanya",
    "iso:country":"ES",
    "sg:address":"Av Alemanya, 34",
    "sg:city":"Segur Calafell",
    "sg:orig_category":"M\u00c9dicos: Foniatr\u00cda Y Logopedia",
    "sg:phone":"+34 977 16 44 09",
    "sg:postcode":"43882",
    "sg:province":"Tarragona",
    "wof:name":"Borras Martinez De Azcoytia Crisanto",
    "wof:placetype":"venue"
},
  "geometry": {"coordinates":[1.601770997,41.2009010315],"type":"Point"}
}