{
  "type": "Feature",
  "properties": {
    "addr:full":"Avda Canal Imperial, S/n Gallur Zaragoza 50650",
    "addr:housenumber":"s / n",
    "addr:postcode":"50650",
    "addr:street":"Avda Canal Imperial",
    "iso:country":"ES",
    "sg:address":"Avda Canal Imperial, S/n",
    "sg:city":"Gallur",
    "sg:orig_category":"Sindicatos Y Colegios Profesionales",
    "sg:phone":"+34 976 86 42 90",
    "sg:postcode":"50650",
    "sg:province":"Zaragoza",
    "wof:name":"Asin Guedea Jose Maria",
    "wof:placetype":"venue"
},
  "geometry": {"coordinates":[-1.3115497828,41.8666992188],"type":"Point"}
}