{
  "type": "Feature",
  "properties": {
    "addr:full":"Riera Bisbe Pol, 33 Arenys Mar Barcelona 08350",
    "addr:housenumber":"33",
    "addr:postcode":"08350",
    "addr:street":"Riera Bisbe Pol",
    "iso:country":"ES",
    "sg:address":"Riera Bisbe Pol, 33",
    "sg:city":"Arenys Mar",
    "sg:orig_category":"Heladeros",
    "sg:phone":"+34 937 92 33 52",
    "sg:postcode":"08350",
    "sg:province":"Barcelona",
    "wof:name":"Viuda E Hijos De R. Giner S.a.",
    "wof:placetype":"venue"
},
  "geometry": {"coordinates":[2.5506539345,41.5800819397],"type":"Point"}
}