{
  "type": "Feature",
  "properties": {
    "iso:country":"ES",
    "sg:address":"Calle de Marques De Teverga, S/n",
    "sg:city":"Aviles",
    "sg:orig_category":"Aparatos, Material Y Suministros Para Laboratorios",
    "sg:phone":"+34 985 56 12 14",
    "sg:postcode":"33401",
    "sg:province":"Asturias",
    "wof:name":"Fernandez Rapado-productos Quimicos S. A.",
    "wof:placetype":"venue"
},
  "geometry": {"coordinates":[-5.9243597984,43.5707817078],"type":"Point"}
}