{
  "type": "Feature",
  "properties": {
    "addr:full":"Calle de Don Juan De Aragon, 8 Zaragoza Zaragoza 50001",
    "addr:housenumber":"8",
    "addr:postcode":"50001",
    "addr:street":"Calle De Don Juan De Aragon",
    "iso:country":"ES",
    "sg:address":"Calle de Don Juan De Aragon, 8",
    "sg:city":"Zaragoza",
    "sg:orig_category":"Asociaciones, Organismos Culturales Y Socioeducativos",
    "sg:phone":"+34 976 39 95 13",
    "sg:postcode":"50001",
    "sg:province":"Zaragoza",
    "wof:name":"Asociacion Cultural Liberazion",
    "wof:placetype":"venue"
},
  "geometry": {"coordinates":[-0.8755304217,41.6536827087],"type":"Point"}
}