{
  "type": "Feature",
  "properties": {
    "addr:full":"Carr Jaume Roca I Delpech, 4 Girona Girona 17004",
    "addr:housenumber":"4",
    "addr:postcode":"17004",
    "addr:street":"Carr Jaume Roca I Delpech",
    "iso:country":"ES",
    "sg:address":"Carr Jaume Roca I Delpech, 4",
    "sg:city":"Girona",
    "sg:orig_category":"M\u00c9dicos: Ginecolog\u00cda Y Obstetricia",
    "sg:phone":"+34 972 22 73 47",
    "sg:postcode":"17004",
    "sg:province":"Girona",
    "wof:name":"Sabria Rius Jose",
    "wof:placetype":"venue"
},
  "geometry": {"coordinates":[2.8247079849,41.9788017273],"type":"Point"}
}