{
  "type": "Feature",
  "properties": {
    "iso:country":"ES",
    "sg:address":"Avda Ausias March, 25",
    "sg:city":"Alaquas",
    "sg:orig_category":"Estancos",
    "sg:phone":"+34 961 50 99 86",
    "sg:postcode":"46970",
    "sg:province":"Valencia",
    "wof:name":"Blanch Cabeza Jesus",
    "wof:placetype":"venue"
},
  "geometry": {"coordinates":[-0.4569320083,39.4554138184],"type":"Point"}
}