{
  "type": "Feature",
  "properties": {
    "addr:full":"Calle de Quart, 79 Valencia Valencia 46008",
    "addr:housenumber":"79",
    "addr:postcode":"46008",
    "addr:street":"Calle De Quart",
    "iso:country":"ES",
    "sg:address":"Calle de Quart, 79",
    "sg:city":"Valencia",
    "sg:orig_category":"Metalurgia",
    "sg:phone":"+34 963 91 06 38",
    "sg:postcode":"46008",
    "sg:province":"Valencia",
    "wof:name":"Lizandara Pascual Ramon",
    "wof:placetype":"venue"
},
  "geometry": {"coordinates":[-0.3855225146,39.4754714966],"type":"Point"}
}