{
  "type": "Feature",
  "properties": {
    "addr:full":"Calle de Elcano, 16 Bilbao Vizcaya 48008",
    "addr:housenumber":"16",
    "addr:postcode":"48008",
    "addr:street":"Calle De Elcano",
    "iso:country":"ES",
    "sg:address":"Calle de Elcano, 16",
    "sg:city":"Bilbao",
    "sg:orig_category":"Abogados",
    "sg:phone":"+34 944 79 57 00",
    "sg:postcode":"48008",
    "sg:province":"Vizcaya",
    "wof:name":"Saenz Cortabarria Rafael",
    "wof:placetype":"venue"
},
  "geometry": {"coordinates":[-2.9339931011,43.260925293],"type":"Point"}
}