{
  "type": "Feature",
  "properties": {
    "addr:full":"Poli Cortijo Real - Plg.indust., 13 Algeciras C\u00e1diz 11206",
    "addr:housenumber":"13;ca\u0301diz",
    "addr:postcode":"11206",
    "addr:street":"Plg.Indust.",
    "iso:country":"ES",
    "sg:address":"Poli Cortijo Real - Plg.indust., 13",
    "sg:city":"Algeciras",
    "sg:orig_category":"Contenedores (mercanc\u00cdas)",
    "sg:phone":"+34 956 57 90 35",
    "sg:postcode":"11206",
    "sg:province":"C\u00e1diz",
    "wof:name":"Hermanos Rosa Calero S.l.",
    "wof:placetype":"venue"
},
  "geometry": {"coordinates":[-5.4882678986,36.1051139832],"type":"Point"}
}