{
  "type": "Feature",
  "properties": {
    "iso:country":"ES",
    "sg:address":"Monte, 150",
    "sg:city":"Mos",
    "sg:orig_category":"Supermercados Y Hipermercados",
    "sg:phone":"+34 986 33 04 73",
    "sg:postcode":"36418",
    "sg:province":"Pontevedra",
    "wof:name":"Maceira Porto Jose",
    "wof:placetype":"venue"
},
  "geometry": {"coordinates":[-8.6279449463,42.1765670776],"type":"Point"}
}