{
  "type": "Feature",
  "properties": {
    "addr:full":"Calle de Victor Fernandez, 4 Santa Lucia Le\u00f3n 24650",
    "addr:housenumber":"4",
    "addr:postcode":"24650",
    "addr:street":"Calle De Victor Fernandez;Leo\u0301N",
    "iso:country":"ES",
    "sg:address":"Calle de Victor Fernandez, 4",
    "sg:city":"Santa Lucia",
    "sg:orig_category":"Mercer\u00cda, Lencer\u00cda (al Por Menor)",
    "sg:phone":"+34 987 58 62 15",
    "sg:postcode":"24650",
    "sg:province":"Le\u00f3n",
    "wof:name":"Garcia Lombas Oscar Andres",
    "wof:placetype":"venue"
},
  "geometry": {"coordinates":[-5.638944149,42.873626709],"type":"Point"}
}