{
  "type": "Feature",
  "properties": {
    "addr:full":"Carrer de Prat De La Riba, 30 Castellar Valles Barcelona 08211",
    "addr:housenumber":"30",
    "addr:postcode":"08211",
    "addr:street":"Carrer De Prat De La Riba",
    "iso:country":"ES",
    "sg:address":"Carrer de Prat De La Riba, 30",
    "sg:city":"Castellar Valles",
    "sg:orig_category":"Ense\u00d1anza: Profesiones Art\u00cdsticas",
    "sg:phone":"+34 937 14 67 65",
    "sg:postcode":"08211",
    "sg:province":"Barcelona",
    "wof:name":"Corredor Navarro Cristobal",
    "wof:placetype":"venue"
},
  "geometry": {"coordinates":[2.0905640125,41.612449646],"type":"Point"}
}