{
  "type": "Feature",
  "properties": {
    "addr:full":"Calle de Santa Eulalia, 21 Merida Badajoz 06800",
    "addr:housenumber":"21",
    "addr:postcode":"06800",
    "addr:street":"Calle De Santa Eulalia",
    "iso:country":"ES",
    "sg:address":"Calle de Santa Eulalia, 21",
    "sg:city":"Merida",
    "sg:orig_category":"Empresas De Limpieza",
    "sg:phone":"+34 924 30 32 00",
    "sg:postcode":"06800",
    "sg:province":"Badajoz",
    "wof:name":"Limpiezas Merida S.l.",
    "wof:placetype":"venue"
},
  "geometry": {"coordinates":[-6.3447318077,38.9170188904],"type":"Point"}
}