{
  "type": "Feature",
  "properties": {
    "addr:full":"Urb Las Torres, S/n Roda De Bara Tarragona 43883",
    "addr:postcode":"43883",
    "addr:street":"Urb Las Torres S / N",
    "iso:country":"ES",
    "sg:address":"Urb Las Torres, S/n",
    "sg:city":"Roda De Bara",
    "sg:orig_category":"Empresas De Carpinter\u00cda",
    "sg:phone":"+34 977 26 04 61",
    "sg:postcode":"43883",
    "sg:province":"Tarragona",
    "wof:name":"Elias Baldrich Jaume",
    "wof:placetype":"venue"
},
  "geometry": {"coordinates":[1.4600640535,41.1879272461],"type":"Point"}
}