{
  "type": "Feature",
  "properties": {
    "addr:full":"Ctra. Son Carrio, 15 Son Moro Islas Baleares 07560",
    "addr:housenumber":"15",
    "addr:postcode":"07560",
    "addr:street":"Ctra. Son Carrio",
    "iso:country":"ES",
    "sg:address":"Ctra. Son Carrio, 15",
    "sg:city":"Son Moro",
    "sg:orig_category":"Alquiler De Veh\u00cdculos: Turismos Y Utilitarios",
    "sg:phone":"+34 971 58 58 03",
    "sg:postcode":"07560",
    "sg:province":"Islas Baleares",
    "wof:name":"Sun Innova Cala Millor S.l.",
    "wof:placetype":"venue"
},
  "geometry": {"coordinates":[3.3733510971,39.5831985474],"type":"Point"}
}