{
  "type": "Feature",
  "properties": {
    "iso:country":"ES",
    "sg:address":"Calle de Ramon Y Cajal, S/n",
    "sg:city":"Granada",
    "sg:orig_category":"Doctores En Medicina",
    "sg:phone":"+34 958 27 05 68",
    "sg:postcode":"18003",
    "sg:province":"Granada",
    "wof:name":"Barranco Bueno Pedro",
    "wof:placetype":"venue"
},
  "geometry": {"coordinates":[-3.6155090332,37.1827316284],"type":"Point"}
}