{
  "type": "Feature",
  "properties": {
    "iso:country":"ES",
    "sg:address":"Trav De Gracia, 62",
    "sg:city":"Barcelona",
    "sg:orig_category":"Complementos De Vestir (al Por Menor)",
    "sg:phone":"+34 932 09 36 44",
    "sg:postcode":"08006",
    "sg:province":"Barcelona",
    "wof:name":"Alar Metales Preciosos S. L.",
    "wof:placetype":"venue"
},
  "geometry": {"coordinates":[2.1645276546,41.3926963806],"type":"Point"}
}