{
  "type": "Feature",
  "properties": {
    "iso:country":"ES",
    "sg:address":"Carrer de Mare De Deu Del Corredor, 5",
    "sg:city":"Mataro",
    "sg:orig_category":"Bisuter\u00cda, Joyer\u00cda, Relojer\u00cda (al Por Menor)",
    "sg:phone":"+34 937 57 88 90",
    "sg:postcode":"08303",
    "sg:province":"Barcelona",
    "wof:name":"Bosakor S.l.",
    "wof:placetype":"venue"
},
  "geometry": {"coordinates":[2.426306963,41.5376319885],"type":"Point"}
}