{
  "type": "Feature",
  "properties": {
    "iso:country":"ES",
    "sg:address":"Calle de Miguel Marrero Rodriguez, 63",
    "sg:city":"Arguineguin",
    "sg:orig_category":"Cajas De Ahorro",
    "sg:phone":"+34 928 15 12 07",
    "sg:postcode":"35120",
    "sg:province":"Las Palmas",
    "sg:website":"www.lacaixa.es",
    "wof:name":"Caixa D'estalvis I Pensions De Barcelona",
    "wof:placetype":"venue"
},
  "geometry": {"coordinates":[-15.6818790436,27.7585601807],"type":"Point"}
}