{
  "type": "Feature",
  "properties": {
    "iso:country":"ES",
    "sg:address":"Calle de Lentisco, S/n",
    "sg:city":"Almeria",
    "sg:orig_category":"Arreglo, Reparaci\u00d3n, Piezas Sueltas De Televisi\u00d3n, V\u00cddeo, Hi",
    "sg:phone":"+34 950 27 08 20",
    "sg:postcode":"04007",
    "sg:province":"Almer\u00eda",
    "wof:name":"Sat Electronica Mediterraneo S.l.",
    "wof:placetype":"venue"
},
  "geometry": {"coordinates":[-2.4468340874,36.8350448608],"type":"Point"}
}