{
  "type": "Feature",
  "properties": {
    "addr:full":"Pg Bonanova, 77 Barcelona Barcelona 08017",
    "addr:housenumber":"77",
    "addr:postcode":"08017",
    "addr:street":"Pg Bonanova",
    "iso:country":"ES",
    "sg:address":"Pg Bonanova, 77",
    "sg:city":"Barcelona",
    "sg:orig_category":"Inform\u00c1tica (estudios, Servicios, Asesor\u00cda, Formaci\u00d3n)",
    "sg:phone":"+34 934 34 01 35",
    "sg:postcode":"08017",
    "sg:province":"Barcelona",
    "wof:name":"Multicom Sistemas Electronicos De Comunicacion S.l.",
    "wof:placetype":"venue"
},
  "geometry": {"coordinates":[2.126404047,41.4025497437],"type":"Point"}
}