{
  "type": "Feature",
  "properties": {
    "addr:full":"Calle de Rodriguez Arias, 71 Bilbao Vizcaya 48013",
    "addr:housenumber":"71",
    "addr:postcode":"48013",
    "addr:street":"Calle De Rodriguez Arias",
    "iso:country":"ES",
    "sg:address":"Calle de Rodriguez Arias, 71",
    "sg:city":"Bilbao",
    "sg:orig_category":"Agencias Y Agentes Comerciales, Representantes",
    "sg:phone":"+34 944 42 09 97",
    "sg:postcode":"48013",
    "sg:province":"Vizcaya",
    "wof:name":"Badiola Rodriguez Justo Antonio",
    "wof:placetype":"venue"
},
  "geometry": {"coordinates":[-2.9451086521,43.2640342712],"type":"Point"}
}