{
  "type": "Feature",
  "properties": {
    "iso:country":"ES",
    "sg:address":"Calle de Tramontana, 12",
    "sg:city":"Humera-somosaguas-prado Del Rey",
    "sg:orig_category":"Arquitectos",
    "sg:phone":"+34 915 18 12 30",
    "sg:postcode":"28223",
    "sg:province":"Madrid",
    "wof:name":"Estudio Martin Caballero S.l.",
    "wof:placetype":"venue"
},
  "geometry": {"coordinates":[-3.7928900719,40.4063034058],"type":"Point"}
}