{
  "type": "Feature",
  "properties": {
    "addr:full":"Avda Simon Nieto, 11 Palencia Palencia 34005",
    "addr:housenumber":"11",
    "addr:postcode":"34005",
    "addr:street":"Avda Simon Nieto",
    "iso:country":"ES",
    "sg:address":"Avda Simon Nieto, 11",
    "sg:city":"Palencia",
    "sg:orig_category":"Prot\u00c9sicos Dentales",
    "sg:phone":"+34 979 17 04 08",
    "sg:postcode":"34005",
    "sg:province":"Palencia",
    "wof:name":"Montes Gonzalez Luis Angel",
    "wof:placetype":"venue"
},
  "geometry": {"coordinates":[-4.5367279053,42.0156211853],"type":"Point"}
}