{
  "type": "Feature",
  "properties": {
    "addr:full":"Carrer de Serra I Moret, S/n Mataro Barcelona 08302",
    "addr:housenumber":"s",
    "addr:postcode":"08302",
    "addr:street":"Carrer De Serra I Moret;/ N Mataro Barcelona",
    "iso:country":"ES",
    "sg:address":"Carrer de Serra I Moret, S/n",
    "sg:city":"Mataro",
    "sg:orig_category":"Mataderos De Poller\u00cda",
    "sg:phone":"+34 937 57 75 59",
    "sg:postcode":"08302",
    "sg:province":"Barcelona",
    "wof:name":"Escorxador D'aus Torrent I Fills S.a.",
    "wof:placetype":"venue"
},
  "geometry": {"coordinates":[2.4286708832,41.5319671631],"type":"Point"}
}