{
  "type": "Feature",
  "properties": {
    "addr:full":"Calle de Martires, 128 Roda Albacete 02630",
    "addr:housenumber":"128",
    "addr:postcode":"02630",
    "addr:street":"Calle De Martires",
    "iso:country":"ES",
    "sg:address":"Calle de Martires, 128",
    "sg:city":"Roda",
    "sg:orig_category":"Centros Empresariales",
    "sg:phone":"+34 967 54 80 83",
    "sg:postcode":"02630",
    "sg:province":"Albacete",
    "wof:name":"Almacenes Papel Roda S.l.",
    "wof:placetype":"venue"
},
  "geometry": {"coordinates":[-2.1664710045,39.2100410461],"type":"Point"}
}