{
  "type": "Feature",
  "properties": {
    "iso:country":"ES",
    "sg:address":"Carrer de Comte D'urgell, 234",
    "sg:city":"Barcelona",
    "sg:orig_category":"Mec\u00c1nico Del Autom\u00d3vil",
    "sg:phone":"+34 934 39 10 21",
    "sg:postcode":"08036",
    "sg:province":"Barcelona",
    "wof:name":"Diaz Ma\u00f1as Santiago",
    "wof:placetype":"venue"
},
  "geometry": {"coordinates":[2.1488261223,41.3894958496],"type":"Point"}
}