{
  "type": "Feature",
  "properties": {
    "iso:country":"ES",
    "sg:address":"Avda Islantilla, S/n",
    "sg:city":"Antilla",
    "sg:orig_category":"Inmobiliaria (agencias)",
    "sg:phone":"+34 959 48 64 53",
    "sg:postcode":"21449",
    "sg:province":"Huelva",
    "wof:name":"Bayo Expertos E Inmobiliarios S.l.",
    "wof:placetype":"venue"
},
  "geometry": {"coordinates":[-7.2509040833,37.2072601318],"type":"Point"}
}