{
  "type": "Feature",
  "properties": {
    "iso:country":"ES",
    "sg:address":"Ctra Sarria De Dalt, S/n",
    "sg:city":"Sarria Ter",
    "sg:orig_category":"Centros De Educaci\u00d3n Especial",
    "sg:phone":"+34 972 17 07 18",
    "sg:postcode":"17840",
    "sg:province":"Girona",
    "wof:name":"C.e.i.p. Montserrat",
    "wof:placetype":"venue"
},
  "geometry": {"coordinates":[2.8154098988,42.0127105713],"type":"Point"}
}