{
  "type": "Feature",
  "properties": {
    "iso:country":"ES",
    "sg:address":"Calle de Deltebre, 4",
    "sg:city":"Reinosa",
    "sg:orig_category":"Pescader\u00cdas (al Por Menor)",
    "sg:phone":"+34 942 75 16 89",
    "sg:postcode":"39200",
    "sg:province":"Cantabria",
    "wof:name":"Herrero Lamela Jose Antonio",
    "wof:placetype":"venue"
},
  "geometry": {"coordinates":[-4.1358971596,43.0002059937],"type":"Point"}
}