{
  "type": "Feature",
  "properties": {
    "addr:full":"Avda Cantabria, S/n Burgos Burgos 09006",
    "addr:housenumber":"s / n",
    "addr:postcode":"09006",
    "addr:street":"Avda Cantabria",
    "iso:country":"ES",
    "sg:address":"Avda Cantabria, S/n",
    "sg:city":"Burgos",
    "sg:orig_category":"Centros De Educaci\u00d3n Especial",
    "sg:phone":"+34 947 21 91 84",
    "sg:postcode":"09006",
    "sg:province":"Burgos",
    "wof:name":"Colegio Publico Francisco De Vitoria",
    "wof:placetype":"venue"
},
  "geometry": {"coordinates":[-3.6880528927,42.3477287292],"type":"Point"}
}