{
  "type": "Feature",
  "properties": {
    "addr:full":"Avda Burgos, 26 Badia Del Valles Barcelona 08214",
    "addr:housenumber":"26",
    "addr:postcode":"08214",
    "addr:street":"Avda Burgos",
    "iso:country":"ES",
    "sg:address":"Avda Burgos, 26",
    "sg:city":"Badia Del Valles",
    "sg:orig_category":"Partidos Pol\u00cdticos",
    "sg:phone":"+34 937 29 20 00",
    "sg:postcode":"08214",
    "sg:province":"Barcelona",
    "wof:name":"Partit Socialista De Catalunya",
    "wof:placetype":"venue"
},
  "geometry": {"coordinates":[2.1154088974,41.5085067749],"type":"Point"}
}