{
  "type": "Feature",
  "properties": {
    "iso:country":"ES",
    "sg:address":"Calle de Sagasta, 37",
    "sg:city":"San Pedro",
    "sg:orig_category":"Fabricaci\u00d3n, Venta De Cuadros, Accesorios Para Enmarcar",
    "sg:phone":"+34 968 28 35 81",
    "sg:postcode":"30005",
    "sg:province":"Murcia",
    "wof:name":"Cuadros Cantos S.l.",
    "wof:placetype":"venue"
},
  "geometry": {"coordinates":[-1.1363589764,37.9861297607],"type":"Point"}
}