{
  "type": "Feature",
  "properties": {
    "iso:country":"ES",
    "sg:address":"Calle de San Antonio, 2",
    "sg:city":"Vitoria-gasteiz",
    "sg:orig_category":"Urbanistas",
    "sg:phone":"+34 945 15 48 29",
    "sg:postcode":"01005",
    "sg:province":"\u00c1lava",
    "wof:name":"Gestion Urbanistica Alava 2000 S.l.",
    "wof:placetype":"venue"
},
  "geometry": {"coordinates":[-2.6743578911,42.8450889587],"type":"Point"}
}