{
  "type": "Feature",
  "properties": {
    "iso:country":"ES",
    "sg:address":"Carrer de Guifre El Pelos, 44",
    "sg:city":"Viladecans",
    "sg:orig_category":"Asociaciones Y Clubs Deportivos",
    "sg:phone":"+34 936 58 90 62",
    "sg:postcode":"08840",
    "sg:province":"Barcelona",
    "wof:name":"Trilles Mu\u00f1oz Leopoldo",
    "wof:placetype":"venue"
},
  "geometry": {"coordinates":[2.0266110897,41.31772995],"type":"Point"}
}