{
  "type": "Feature",
  "properties": {
    "addr:full":"Calle de Camino De Santiago, 6 Ponferrada Le\u00f3n 24400",
    "addr:housenumber":"6",
    "addr:postcode":"24400",
    "addr:street":"Calle De Camino De Santiago",
    "iso:country":"ES",
    "sg:address":"Calle de Camino De Santiago, 6",
    "sg:city":"Ponferrada",
    "sg:orig_category":"Arquitectos",
    "sg:phone":"+34 987 41 65 11",
    "sg:postcode":"24400",
    "sg:province":"Le\u00f3n",
    "wof:name":"Mari\u00d1as Armesto Miguel Angel",
    "wof:placetype":"venue"
},
  "geometry": {"coordinates":[-6.5987529755,42.5481987],"type":"Point"}
}