{
  "type": "Feature",
  "properties": {
    "iso:country":"ES",
    "sg:address":"Calle de Fita, 2",
    "sg:city":"Zaragoza",
    "sg:orig_category":"Perfumer\u00cda (al Por Menor)",
    "sg:phone":"+34 976 23 83 15",
    "sg:postcode":"50005",
    "sg:province":"Zaragoza",
    "wof:name":"Muguet S. C.",
    "wof:placetype":"venue"
},
  "geometry": {"coordinates":[-0.8899683952,41.6463127136],"type":"Point"}
}