{
  "type": "Feature",
  "properties": {
    "addr:full":"Avda Cordoba, 28 Don Benito Badajoz 06400",
    "addr:housenumber":"28",
    "addr:postcode":"06400",
    "addr:street":"Avda Cordoba",
    "iso:country":"ES",
    "sg:address":"Avda Cordoba, 28",
    "sg:city":"Don Benito",
    "sg:orig_category":"Persianas Interiores, Exteriores",
    "sg:phone":"+34 924 81 35 75",
    "sg:postcode":"06400",
    "sg:province":"Badajoz",
    "wof:name":"Gomez Gomez Damian",
    "wof:placetype":"venue"
},
  "geometry": {"coordinates":[-5.8525190353,38.9605865479],"type":"Point"}
}