{
  "type": "Feature",
  "properties": {
    "iso:country":"ES",
    "sg:address":"Pol. Can Fatjo Dels Hurons, S/n",
    "sg:city":"Cerdanyola Valles",
    "sg:orig_category":"Fabrica De Cer\u00c1micas",
    "sg:phone":"+34 935 80 60 34",
    "sg:postcode":"08290",
    "sg:province":"Barcelona",
    "sg:website":"www.almar.es",
    "wof:name":"Almar Productos Ceramicos S.a.",
    "wof:placetype":"venue"
},
  "geometry": {"coordinates":[2.1699187756,41.3879165649],"type":"Point"}
}