{
  "type": "Feature",
  "properties": {
    "iso:country":"ES",
    "sg:address":"Franciscano, 9",
    "sg:city":"Galdar",
    "sg:orig_category":"Cl\u00cdnicas M\u00c9dicas",
    "sg:phone":"+34 928 89 52 64",
    "sg:postcode":"35460",
    "sg:province":"Las Palmas",
    "wof:name":"Centro De Rehabilitacion De Galdar S.l.",
    "wof:placetype":"venue"
},
  "geometry": {"coordinates":[-15.6490325928,28.1460075378],"type":"Point"}
}