{
  "type": "Feature",
  "properties": {
    "iso:country":"ES",
    "sg:address":"Ctra Fondillo Del, S/n",
    "sg:city":"Fondillo",
    "sg:orig_category":"Ingenier\u00cda, Centros De Estudios (industria)",
    "sg:phone":"+34 928 35 69 05",
    "sg:postcode":"35017",
    "sg:province":"Las Palmas",
    "wof:name":"Mayor Calderin Manuel",
    "wof:placetype":"venue"
},
  "geometry": {"coordinates":[-15.4646606445,28.054693222],"type":"Point"}
}