{
  "type": "Feature",
  "properties": {
    "addr:full":"Calle de San Carlos, 5 Maracena Granada 18200",
    "addr:housenumber":"5",
    "addr:postcode":"18200",
    "addr:street":"Calle De San Carlos",
    "iso:country":"ES",
    "sg:address":"Calle de San Carlos, 5",
    "sg:city":"Maracena",
    "sg:orig_category":"Ropa Para Se\u00d1oras (al Por Menor)",
    "sg:phone":"+34 958 42 03 60",
    "sg:postcode":"18200",
    "sg:province":"Granada",
    "wof:name":"Zine El Abibine  Naima",
    "wof:placetype":"venue"
},
  "geometry": {"coordinates":[-3.6357960701,37.2072486877],"type":"Point"}
}