{
  "type": "Feature",
  "properties": {
    "addr:full":"Carrer de Sant Francesc, 29 Reus Tarragona 43205",
    "addr:housenumber":"29",
    "addr:postcode":"43205",
    "addr:street":"Carrer De Sant Francesc",
    "iso:country":"ES",
    "sg:address":"Carrer de Sant Francesc, 29",
    "sg:city":"Reus",
    "sg:orig_category":"Ingenier\u00cda, Centros De Estudios (diversos)",
    "sg:phone":"+34 977 32 33 74",
    "sg:postcode":"43205",
    "sg:province":"Tarragona",
    "wof:name":"Fonts Marti Enrique",
    "wof:placetype":"venue"
},
  "geometry": {"coordinates":[1.1078170538,41.1524734497],"type":"Point"}
}