{
  "type": "Feature",
  "properties": {
    "addr:full":"Carrer de Marcelino Menendez Pelayo, 37 Cornella Llobregat Barcelona 08940",
    "addr:housenumber":"37",
    "addr:postcode":"08940",
    "addr:street":"Carrer De Marcelino Menendez Pelayo",
    "iso:country":"ES",
    "sg:address":"Carrer de Marcelino Menendez Pelayo, 37",
    "sg:city":"Cornella Llobregat",
    "sg:orig_category":"T\u00c9cnicos Veterinarios",
    "sg:phone":"+34 934 74 04 04",
    "sg:postcode":"08940",
    "sg:province":"Barcelona",
    "wof:name":"Ferrer De Miquel Enric",
    "wof:placetype":"venue"
},
  "geometry": {"coordinates":[2.0725569725,41.3542556763],"type":"Point"}
}