{
  "type": "Feature",
  "properties": {
    "iso:country":"ES",
    "sg:address":"Calle de Martires, 14",
    "sg:city":"Torrelavega",
    "sg:orig_category":"Pescader\u00cdas (al Por Menor)",
    "sg:phone":"+34 942 88 07 75",
    "sg:postcode":"39300",
    "sg:province":"Cantabria",
    "wof:name":"Ruiz Moya Manuel",
    "wof:placetype":"venue"
},
  "geometry": {"coordinates":[-4.0480918884,43.3523101807],"type":"Point"}
}