{
  "type": "Feature",
  "properties": {
    "iso:country":"ES",
    "sg:address":"Avda Faro, 53",
    "sg:city":"Playa",
    "sg:orig_category":"Impresiones Sobre Tela",
    "sg:phone":"+34 964 31 12 38",
    "sg:postcode":"12594",
    "sg:province":"Castell\u00f3n",
    "wof:name":"Corrales Jimenez Faustino",
    "wof:placetype":"venue"
},
  "geometry": {"coordinates":[0.135344997,40.0945358276],"type":"Point"}
}