{
  "type": "Feature",
  "properties": {
    "addr:full":"Ferrocarril, 1 Avila \u00c1vila 05001",
    "addr:housenumber":"1",
    "addr:postcode":"05001",
    "addr:street":"Ferrocarril;A\u0301Vila",
    "iso:country":"ES",
    "sg:address":"Ferrocarril, 1",
    "sg:city":"Avila",
    "sg:orig_category":"Centros De Coordinaci\u00d3n",
    "sg:phone":"+34 920 22 93 01",
    "sg:postcode":"05001",
    "sg:province":"\u00c1vila",
    "wof:name":"Martin Sanz Antonio Javier",
    "wof:placetype":"venue"
},
  "geometry": {"coordinates":[-4.6844649315,40.6573486328],"type":"Point"}
}