{
  "type": "Feature",
  "properties": {
    "iso:country":"ES",
    "sg:address":"Pl Porta Pintada, 6",
    "sg:city":"Palma",
    "sg:orig_category":"Oficinas De Cambio",
    "sg:phone":"+34 971 72 46 86",
    "sg:postcode":"07002",
    "sg:province":"Islas Baleares",
    "wof:name":"Fast Exchange S.l.",
    "wof:placetype":"venue"
},
  "geometry": {"coordinates":[2.6531178951,39.5755310059],"type":"Point"}
}