{
  "type": "Feature",
  "properties": {
    "addr:full":"Calle de Olmo, 35 Minaya Albacete 02620",
    "addr:housenumber":"35",
    "addr:postcode":"02620",
    "addr:street":"Calle De Olmo",
    "iso:country":"ES",
    "sg:address":"Calle de Olmo, 35",
    "sg:city":"Minaya",
    "sg:orig_category":"Art\u00cdculos De Decoraci\u00d3n",
    "sg:phone":"+34 967 45 00 20",
    "sg:postcode":"02620",
    "sg:province":"Albacete",
    "wof:name":"Casa Hogar Mercedes S.l.",
    "wof:placetype":"venue"
},
  "geometry": {"coordinates":[-2.3216319084,39.2727508545],"type":"Point"}
}