{
  "type": "Feature",
  "properties": {
    "addr:full":"Calle de Jesus Nazareno, 17 Chiclana De La Frontera C\u00e1diz 11130",
    "addr:housenumber":"17",
    "addr:postcode":"11130",
    "addr:street":"Calle De Jesus Nazareno",
    "iso:country":"ES",
    "sg:address":"Calle de Jesus Nazareno, 17",
    "sg:city":"Chiclana De La Frontera",
    "sg:orig_category":"Asesor\u00cda Sobre Comunicaci\u00d3n De Empresas",
    "sg:phone":"+34 956 53 08 36",
    "sg:postcode":"11130",
    "sg:province":"C\u00e1diz",
    "wof:name":"Gestion 10 Cb",
    "wof:placetype":"venue"
},
  "geometry": {"coordinates":[-6.1494240761,36.4188957214],"type":"Point"}
}