{
  "type": "Feature",
  "properties": {
    "iso:country":"ES",
    "sg:address":"Pg Tolra, 2",
    "sg:city":"Castellar Valles",
    "sg:orig_category":"Internados & Ense\u00d1anza Privada",
    "sg:phone":"+34 937 15 94 27",
    "sg:postcode":"08211",
    "sg:province":"Barcelona",
    "wof:name":"Hermanas Dominicas",
    "wof:placetype":"venue"
},
  "geometry": {"coordinates":[2.0876049995,41.618473053],"type":"Point"}
}