{
  "type": "Feature",
  "properties": {
    "addr:full":"Ruer Figueiri\u00d1as (das), 5 Santiago De Compostela La Coru\u00f1a 15705",
    "addr:postcode":"15705",
    "addr:street":"Corun\u0303A",
    "iso:country":"ES",
    "sg:address":"Ruer Figueiri\u00d1as (das), 5",
    "sg:city":"Santiago De Compostela",
    "sg:orig_category":"Asociaciones De Vecinos, Centros De Juventud",
    "sg:phone":"+34 981 55 43 21",
    "sg:postcode":"15705",
    "sg:province":"La Coru\u00f1a",
    "wof:name":"Asociacion De Desenvolvimiento Rural Sar-ulla",
    "wof:placetype":"venue"
},
  "geometry": {"coordinates":[-8.5226707458,42.9105796814],"type":"Point"}
}