{
  "type": "Feature",
  "properties": {
    "addr:full":"Calle de Ponent, 30 Urbanizacion Llano De Los Pastores Alicante 03111",
    "addr:housenumber":"30",
    "addr:postcode":"03111",
    "addr:street":"Calle De Ponent;Urbanizacion Llano De",
    "iso:country":"ES",
    "sg:address":"Calle de Ponent, 30",
    "sg:city":"Urbanizacion Llano De Los Pastores",
    "sg:orig_category":"Venta, Instalaci\u00d3n De Calefacci\u00d3n",
    "sg:phone":"+34 965 69 95 97",
    "sg:postcode":"03111",
    "sg:province":"Alicante",
    "wof:name":"Jopac Clima S.l.",
    "wof:placetype":"venue"
},
  "geometry": {"coordinates":[-0.4196340144,38.4808959961],"type":"Point"}
}