{
  "type": "Feature",
  "properties": {
    "addr:full":"Ctra. Albal, Km. 0002,6 Torrent Valencia 46900",
    "addr:postcode":"46900",
    "addr:street":"Ctra. Albal Km. 0002,6;Valencia",
    "iso:country":"ES",
    "sg:address":"Ctra. Albal, Km. 0002,6",
    "sg:city":"Torrent",
    "sg:orig_category":"Semiller\u00cdas",
    "sg:phone":"+34 961 55 87 59",
    "sg:postcode":"46900",
    "sg:province":"Valencia",
    "wof:name":"Viveros Mesado Sat 8882",
    "wof:placetype":"venue"
},
  "geometry": {"coordinates":[-0.4653796852,39.4341087341],"type":"Point"}
}