{
  "type": "Feature",
  "properties": {
    "addr:full":"Calle de Maestro Nicolas, 21 Le\u00f3n Le\u00f3n 24005",
    "addr:housenumber":"21",
    "addr:postcode":"24005",
    "addr:street":"Calle De Maestro Nicolas;Leo\u0301N",
    "iso:country":"ES",
    "sg:address":"Calle de Maestro Nicolas, 21",
    "sg:city":"Le\u00f3n",
    "sg:orig_category":"Peluquer\u00cdas, Peluquer\u00cda Mixta",
    "sg:phone":"+34 987 26 25 69",
    "sg:postcode":"24005",
    "sg:province":"Le\u00f3n",
    "wof:name":"Sanchez Vallina Vicente",
    "wof:placetype":"venue"
},
  "geometry": {"coordinates":[-5.5691728592,42.5875015259],"type":"Point"}
}