{
  "type": "Feature",
  "properties": {
    "iso:country":"ES",
    "sg:address":"Avda Mediterraneo, 67",
    "sg:city":"Teulada",
    "sg:orig_category":"Cer\u00c1micas: Material Y Suministros",
    "sg:phone":"+34 965 74 05 28",
    "sg:postcode":"03725",
    "sg:province":"Alicante",
    "wof:name":"Hermanos Llobell S.l.",
    "wof:placetype":"venue"
},
  "geometry": {"coordinates":[0.1009299979,38.727481842],"type":"Point"}
}