{
  "type": "Feature",
  "properties": {
    "iso:country":"ES",
    "sg:address":"Carrer de Sant Tomas, 4",
    "sg:city":"Olot",
    "sg:orig_category":"M\u00c9dicos: Psiquiatr\u00cda",
    "sg:phone":"+34 972 26 18 62",
    "sg:postcode":"17800",
    "sg:province":"Girona",
    "wof:name":"Pujiula Ribera Jordi",
    "wof:placetype":"venue"
},
  "geometry": {"coordinates":[2.4887430668,42.1818199158],"type":"Point"}
}