{
  "type": "Feature",
  "properties": {
    "iso:country":"ES",
    "sg:address":"Avda Santa Amalia, 22",
    "sg:city":"Fuengirola",
    "sg:orig_category":"Arquitectos",
    "sg:phone":"+34 952 58 62 97",
    "sg:postcode":"29640",
    "sg:province":"M\u00e1laga",
    "wof:name":"Caballero Garcia Adela",
    "wof:placetype":"venue"
},
  "geometry": {"coordinates":[-4.6273331642,36.5319786072],"type":"Point"}
}