{
  "type": "Feature",
  "properties": {
    "iso:country":"ES",
    "sg:address":"Calle de Dr Fleming (del), 33",
    "sg:city":"Coslada",
    "sg:orig_category":"T\u00c9cnicos Veterinarios",
    "sg:phone":"+34 916 71 21 66",
    "sg:postcode":"28820",
    "sg:province":"Madrid",
    "wof:name":"Perez Molpeceres Sergio",
    "wof:placetype":"venue"
},
  "geometry": {"coordinates":[-3.5651621819,40.4238548279],"type":"Point"}
}