{
  "type": "Feature",
  "properties": {
    "iso:country":"ES",
    "sg:address":"Carr Nou, 45",
    "sg:city":"Caldes Malavella",
    "sg:orig_category":"Alquiler De V\u00cddeo",
    "sg:phone":"+34 972 47 26 18",
    "sg:postcode":"17455",
    "sg:province":"Girona",
    "wof:name":"Cinema Bussines S.c.p.",
    "wof:placetype":"venue"
},
  "geometry": {"coordinates":[2.8018240929,41.8385505676],"type":"Point"}
}