{
  "type": "Feature",
  "properties": {
    "addr:full":"Carrer de Santa Helena, 6 Reus Tarragona 43202",
    "addr:housenumber":"6",
    "addr:postcode":"43202",
    "addr:street":"Carrer De Santa Helena",
    "iso:country":"ES",
    "sg:address":"Carrer de Santa Helena, 6",
    "sg:city":"Reus",
    "sg:orig_category":"Carnicer\u00cdas, Carnicer\u00cdas",
    "sg:phone":"+34 977 31 61 87",
    "sg:postcode":"43202",
    "sg:province":"Tarragona",
    "wof:name":"Bernal Victoria Jose Manuel",
    "wof:placetype":"venue"
},
  "geometry": {"coordinates":[1.1039119959,41.1587982178],"type":"Point"}
}