{
  "type": "Feature",
  "properties": {
    "iso:country":"ES",
    "sg:address":"Guia (randufe), S/n",
    "sg:city":"Guia",
    "sg:orig_category":"Poller\u00cda Y Caza (al Por Menor)",
    "sg:phone":"+34 986 60 11 47",
    "sg:postcode":"36713",
    "sg:province":"Pontevedra",
    "wof:name":"Gonzalez Iglesias Fortunato Joaquin",
    "wof:placetype":"venue"
},
  "geometry": {"coordinates":[-8.6658506393,42.0539283752],"type":"Point"}
}