{
  "type": "Feature",
  "properties": {
    "addr:full":"Calle de Bergantin, 14 Pasito Blanco Las Palmas 35100",
    "addr:housenumber":"14",
    "addr:postcode":"35100",
    "addr:street":"Calle De Bergantin;Blanco",
    "iso:country":"ES",
    "sg:address":"Calle de Bergantin, 14",
    "sg:city":"Pasito Blanco",
    "sg:orig_category":"M\u00c9dicos: Anatom\u00cda Patol\u00d3gica Y Citolog\u00cda",
    "sg:phone":"+34 928 14 00 42",
    "sg:postcode":"35100",
    "sg:province":"Las Palmas",
    "wof:name":"Benitez Falcon Oreste",
    "wof:placetype":"venue"
},
  "geometry": {"coordinates":[-15.6260433197,27.7484912872],"type":"Point"}
}