{
  "type": "Feature",
  "properties": {
    "addr:full":"Carr Xativa, 9 Moncada Valencia 46113",
    "addr:housenumber":"9",
    "addr:postcode":"46113",
    "addr:street":"Carr Xativa",
    "iso:country":"ES",
    "sg:address":"Carr Xativa, 9",
    "sg:city":"Moncada",
    "sg:orig_category":"Asesor\u00cda Fiscal Y Jur\u00cddica",
    "sg:phone":"+34 961 30 17 31",
    "sg:postcode":"46113",
    "sg:province":"Valencia",
    "wof:name":"Bertomeu Guijarro Jose Daniel",
    "wof:placetype":"venue"
},
  "geometry": {"coordinates":[-0.3982529938,39.5452728271],"type":"Point"}
}