{
  "type": "Feature",
  "properties": {
    "addr:full":"Calle de Baldomero Fernandez, 6 Oviedo Asturias 33006",
    "addr:housenumber":"6",
    "addr:postcode":"33006",
    "addr:street":"Calle De Baldomero Fernandez",
    "iso:country":"ES",
    "sg:address":"Calle de Baldomero Fernandez, 6",
    "sg:city":"Oviedo",
    "sg:orig_category":"Laboratorios Y Trabajos De Fotograf\u00cda, V\u00cddeo Y Cine",
    "sg:phone":"+34 985 25 38 92",
    "sg:postcode":"33006",
    "sg:province":"Asturias",
    "wof:name":"Marfoto Servicios Fotografico S.l.",
    "wof:placetype":"venue"
},
  "geometry": {"coordinates":[-5.8604044914,43.3558616638],"type":"Point"}
}