{
  "type": "Feature",
  "properties": {
    "addr:full":"Carrer de Valencia, 18 Barcelona Barcelona 08015",
    "addr:housenumber":"18",
    "addr:postcode":"08015",
    "addr:street":"Carrer De Valencia",
    "iso:country":"ES",
    "sg:address":"Carrer de Valencia, 18",
    "sg:city":"Barcelona",
    "sg:orig_category":"Reposter\u00cdas",
    "sg:phone":"+34 932 26 33 71",
    "sg:postcode":"08015",
    "sg:province":"Barcelona",
    "wof:name":"Frupanet S.l.",
    "wof:placetype":"venue"
},
  "geometry": {"coordinates":[2.1458990574,41.3793945312],"type":"Point"}
}