{
  "type": "Feature",
  "properties": {
    "iso:country":"ES",
    "sg:address":"Avda Gaspar Aguilar, 107",
    "sg:city":"Valencia",
    "sg:orig_category":"Farmacias",
    "sg:phone":"+34 963 78 10 83",
    "sg:postcode":"46017",
    "sg:province":"Valencia",
    "wof:name":"Hermanos Folgado Martin C.b.",
    "wof:placetype":"venue"
},
  "geometry": {"coordinates":[-0.3932659924,39.4518432617],"type":"Point"}
}