{
  "type": "Feature",
  "properties": {
    "addr:full":"Isasi Kalea, 35 Eibar Guip\u00f9zcoa 20600",
    "addr:housenumber":"35",
    "addr:postcode":"20600",
    "addr:street":"Isasi Kalea;Guipu\u0300Zcoa",
    "iso:country":"ES",
    "sg:address":"Isasi Kalea, 35",
    "sg:city":"Eibar",
    "sg:orig_category":"Ropa Para Ni\u00d1os (al Por Menor)",
    "sg:phone":"+34 943 20 78 16",
    "sg:postcode":"20600",
    "sg:province":"Guip\u00f9zcoa",
    "wof:name":"Aristondo Lujua Aitziber",
    "wof:placetype":"venue"
},
  "geometry": {"coordinates":[-2.4770567417,43.1837005615],"type":"Point"}
}