{
  "type": "Feature",
  "properties": {
    "addr:full":"Pol Ind Los Pocicos, 4 Cuevas Almanzora Almer\u00eda 04610",
    "addr:housenumber":"4",
    "addr:postcode":"04610",
    "addr:street":"Los Pocicos;Almeri\u0301A",
    "iso:country":"ES",
    "sg:address":"Pol Ind Los Pocicos, 4",
    "sg:city":"Cuevas Almanzora",
    "sg:orig_category":"Ferreter\u00cda (diversos)",
    "sg:phone":"+34 950 45 70 20",
    "sg:postcode":"04610",
    "sg:province":"Almer\u00eda",
    "wof:name":"Bcn Comercial Ferrica S.a.",
    "wof:placetype":"venue"
},
  "geometry": {"coordinates":[-1.8781139851,37.2911911011],"type":"Point"}
}