{
  "type": "Feature",
  "properties": {
    "addr:full":"Carrer de Ample, 21 Barcelona Barcelona 08002",
    "addr:housenumber":"21",
    "addr:postcode":"08002",
    "addr:street":"Carrer De Ample",
    "iso:country":"ES",
    "sg:address":"Carrer de Ample, 21",
    "sg:city":"Barcelona",
    "sg:orig_category":"Alimentaci\u00d3n General (al Por Menor)",
    "sg:phone":"+34 933 17 43 13",
    "sg:postcode":"08002",
    "sg:province":"Barcelona",
    "wof:name":"Palol Gatius Carlos",
    "wof:placetype":"venue"
},
  "geometry": {"coordinates":[2.1793880463,41.3796882629],"type":"Point"}
}