{
  "type": "Feature",
  "properties": {
    "iso:country":"ES",
    "sg:address":"Rua Carlos Iii, 12",
    "sg:city":"Becerrea",
    "sg:orig_category":"Alimentaci\u00d3n General (al Por Menor)",
    "sg:phone":"+34 982 36 02 32",
    "sg:postcode":"27640",
    "sg:province":"Lugo",
    "wof:name":"Distribuciones Froiz S.a.",
    "wof:placetype":"venue"
},
  "geometry": {"coordinates":[-7.1613059044,42.8526229858],"type":"Point"}
}