{
  "type": "Feature",
  "properties": {
    "addr:full":"Calle de Real Alta, 9 Ogijares Granada 18151",
    "addr:housenumber":"9",
    "addr:postcode":"18151",
    "addr:street":"Calle De Real Alta",
    "iso:country":"ES",
    "sg:address":"Calle de Real Alta, 9",
    "sg:city":"Ogijares",
    "sg:orig_category":"Bancos",
    "sg:phone":"+34 958 50 91 18",
    "sg:postcode":"18151",
    "sg:province":"Granada",
    "wof:name":"Caja Rural De Granada",
    "wof:placetype":"venue"
},
  "geometry": {"coordinates":[-3.6067550182,37.1217727661],"type":"Point"}
}