{
  "type": "Feature",
  "properties": {
    "addr:full":"Rua Colon, 3 Verin Ourense 32600",
    "addr:housenumber":"3",
    "addr:postcode":"32600",
    "addr:street":"Rua Colon",
    "iso:country":"ES",
    "sg:address":"Rua Colon, 3",
    "sg:city":"Verin",
    "sg:orig_category":"Agencias Y Agentes Comerciales, Representantes",
    "sg:phone":"+34 988 41 26 30",
    "sg:postcode":"32600",
    "sg:province":"Ourense",
    "wof:name":"Boss Estudio Empresarial S. L.",
    "wof:placetype":"venue"
},
  "geometry": {"coordinates":[-7.4367761612,41.9379844666],"type":"Point"}
}