{
  "type": "Feature",
  "properties": {
    "addr:full":"Calle de Siglo Xx, 15 S. Roque C\u00e1diz 11360",
    "addr:housenumber":"15",
    "addr:postcode":"11360",
    "addr:street":"Calle De Siglo Xx;S. Roque Ca\u0301Diz",
    "iso:country":"ES",
    "sg:address":"Calle de Siglo Xx, 15",
    "sg:city":"S. Roque",
    "sg:orig_category":"Promotores Constructores",
    "sg:phone":"+34 956 78 14 82",
    "sg:postcode":"11360",
    "sg:province":"C\u00e1diz",
    "wof:name":"Sant-obra S.l.",
    "wof:placetype":"venue"
},
  "geometry": {"coordinates":[-5.3844389915,36.2093315125],"type":"Point"}
}