{
  "type": "Feature",
  "properties": {
    "iso:country":"ES",
    "sg:address":"Calle de Jose Antonio, 9",
    "sg:city":"Seijo",
    "sg:orig_category":"Librer\u00cdas",
    "sg:phone":"+34 986 62 21 31",
    "sg:postcode":"36740",
    "sg:province":"Pontevedra",
    "wof:name":"Carrera Alvarez Mercedes",
    "wof:placetype":"venue"
},
  "geometry": {"coordinates":[-8.731048584,41.9869499207],"type":"Point"}
}