{
  "type": "Feature",
  "properties": {
    "iso:country":"ES",
    "sg:address":"Calle de Manuel De Falla, 16",
    "sg:city":"Almonte",
    "sg:orig_category":"Bisuter\u00cda, Joyer\u00cda, Relojer\u00cda (al Por Menor)",
    "sg:phone":"+34 959 40 77 51",
    "sg:postcode":"21730",
    "sg:province":"Huelva",
    "sg:website":"www.italjoya.cjb.net",
    "wof:name":"Taller Joyeros Ital S.l.",
    "wof:placetype":"venue"
},
  "geometry": {"coordinates":[-6.5148034096,37.262008667],"type":"Point"}
}