{
  "type": "Feature",
  "properties": {
    "iso:country":"ES",
    "sg:address":"Calle de Uralde, 6",
    "sg:city":"Iurreta",
    "sg:orig_category":"Ingeniero",
    "sg:phone":"+34 946 20 43 56",
    "sg:postcode":"48215",
    "sg:province":"Vizcaya",
    "wof:name":"Svp Broadcast Microwave S.l.",
    "wof:placetype":"venue"
},
  "geometry": {"coordinates":[-2.6367590427,43.174030304],"type":"Point"}
}