{
  "type": "Feature",
  "properties": {
    "iso:country":"ES",
    "sg:address":"Calle de Juan De La Cierva, 22",
    "sg:city":"Arganda",
    "sg:orig_category":"Ropa Para Ni\u00d1os (al Por Menor)",
    "sg:phone":"+34 918 70 45 63",
    "sg:postcode":"28500",
    "sg:province":"Madrid",
    "wof:name":"Ruiz Fernandez Antonio Jesus",
    "wof:placetype":"venue"
},
  "geometry": {"coordinates":[-3.4409620762,40.3016433716],"type":"Point"}
}