{
  "type": "Feature",
  "properties": {
    "addr:full":"Ctra. Fuente Cantos, S/n Montemolin Badajoz 06291",
    "addr:housenumber":"s / n",
    "addr:postcode":"06291",
    "addr:street":"Ctra. Fuente Cantos",
    "iso:country":"ES",
    "sg:address":"Ctra. Fuente Cantos, S/n",
    "sg:city":"Montemolin",
    "sg:orig_category":"Agricultores, Agricultores",
    "sg:phone":"+34 924 51 00 75",
    "sg:postcode":"06291",
    "sg:province":"Badajoz",
    "wof:name":"Cosme Marin Luis Alfonso",
    "wof:placetype":"venue"
},
  "geometry": {"coordinates":[-6.213075161,38.1552886963],"type":"Point"}
}