{
  "type": "Feature",
  "properties": {
    "addr:full":"Ctra Madrid Irun, 2 Lerma Burgos 09340",
    "addr:housenumber":"2",
    "addr:postcode":"09340",
    "addr:street":"Ctra Madrid",
    "iso:country":"ES",
    "sg:address":"Ctra Madrid Irun, 2",
    "sg:city":"Lerma",
    "sg:orig_category":"Frutas Y Legumbres Frescas (al Por Mayor)",
    "sg:phone":"+34 947 17 01 92",
    "sg:postcode":"09340",
    "sg:province":"Burgos",
    "wof:name":"Serrano Paramo Jose Ramon",
    "wof:placetype":"venue"
},
  "geometry": {"coordinates":[-3.7584710121,42.0313110352],"type":"Point"}
}