{
  "type": "Feature",
  "properties": {
    "addr:full":"Calle de Zaragoza, 9 Sevilla Sevilla 41001",
    "addr:housenumber":"9",
    "addr:postcode":"41001",
    "addr:street":"Calle De Zaragoza",
    "iso:country":"ES",
    "sg:address":"Calle de Zaragoza, 9",
    "sg:city":"Sevilla",
    "sg:orig_category":"M\u00c9dicos: Psiquiatr\u00cda",
    "sg:phone":"+34 954 22 34 21",
    "sg:postcode":"41001",
    "sg:province":"Sevilla",
    "wof:name":"Lopez Cano Soledad",
    "wof:placetype":"venue"
},
  "geometry": {"coordinates":[-5.9985179901,37.3889694214],"type":"Point"}
}