{
  "type": "Feature",
  "properties": {
    "iso:country":"ES",
    "sg:address":"Calle de Nueva, 11",
    "sg:city":"Yepes",
    "sg:orig_category":"Negocio De Materiales De Construcci\u00d3n",
    "sg:phone":"+34 925 15 55 57",
    "sg:postcode":"45313",
    "sg:province":"Toledo",
    "wof:name":"Verdugo Moya Jose Carlos",
    "wof:placetype":"venue"
},
  "geometry": {"coordinates":[-3.6287469864,39.9000473022],"type":"Point"}
}