{
  "type": "Feature",
  "properties": {
    "addr:full":"Calle de Deprit Lasa Amadeo, 4 Bilbao Vizcaya 48006",
    "addr:housenumber":"4",
    "addr:postcode":"48006",
    "addr:street":"Calle De Deprit;Amadeo",
    "iso:country":"ES",
    "sg:address":"Calle de Deprit Lasa Amadeo, 4",
    "sg:city":"Bilbao",
    "sg:orig_category":"Electricidad, Electr\u00d3nica: Material Y Suministros (al Por Mayor)",
    "sg:phone":"+34 944 12 70 22",
    "sg:postcode":"48006",
    "sg:province":"Vizcaya",
    "wof:name":"Bizkaia Del Automatico S.l.",
    "wof:placetype":"venue"
},
  "geometry": {"coordinates":[-2.9172749519,43.2592506409],"type":"Point"}
}