{
  "type": "Feature",
  "properties": {
    "iso:country":"ES",
    "sg:address":"Iturriotz Kalea, 21",
    "sg:city":"Arrasate",
    "sg:orig_category":"Ropa Para Se\u00d1oras (al Por Menor)",
    "sg:phone":"+34 943 71 17 40",
    "sg:postcode":"20500",
    "sg:province":"Guip\u00f9zcoa",
    "wof:name":"Zulaica Aramendi Margarita",
    "wof:placetype":"venue"
},
  "geometry": {"coordinates":[-2.4902193546,43.0654449463],"type":"Point"}
}