{
  "type": "Feature",
  "properties": {
    "addr:full":"Calle de Santillana Del Mar (de), 14 Boadilla Del Monte Madrid 28660",
    "addr:postcode":"28660",
    "addr:street":"Calle De Santillana",
    "iso:country":"ES",
    "sg:address":"Calle de Santillana Del Mar (de), 14",
    "sg:city":"Boadilla Del Monte",
    "sg:orig_category":"Fabricaci\u00d3n De Peines Y De Accesorios De Peluquer\u00cda",
    "sg:phone":"+34 916 32 08 50",
    "sg:postcode":"28660",
    "sg:province":"Madrid",
    "wof:name":"Molera Esteban Jose Javier",
    "wof:placetype":"venue"
},
  "geometry": {"coordinates":[-3.8801269531,40.4049491882],"type":"Point"}
}