{
  "type": "Feature",
  "properties": {
    "addr:full":"Ctra M-511 (villaviciosa-boadilla), Km. 0002,7 Arco Iris Madrid 28670",
    "addr:postcode":"28670",
    "addr:street":"Ctra M-511 Villaviciosa-Boadilla Km. 0002,7",
    "iso:country":"ES",
    "sg:address":"Ctra M-511 (villaviciosa-boadilla), Km. 0002,7",
    "sg:city":"Arco Iris",
    "sg:orig_category":"Karting",
    "sg:phone":"+34 916 16 24 39",
    "sg:postcode":"28670",
    "sg:province":"Madrid",
    "wof:name":"Auto Subasta Park S.l.",
    "wof:placetype":"venue"
},
  "geometry": {"coordinates":[-3.7003455162,40.4166908264],"type":"Point"}
}