{
  "type": "Feature",
  "properties": {
    "addr:full":"Calle de Gandhi, 15 Madrid Madrid 28017",
    "addr:housenumber":"15",
    "addr:postcode":"madrid;28017",
    "addr:street":"Calle De Gandhi",
    "iso:country":"ES",
    "sg:address":"Calle de Gandhi, 15",
    "sg:city":"Madrid",
    "sg:orig_category":"Arreglo, Reparaci\u00d3n, Piezas Sueltas De Televisi\u00d3n, V\u00cddeo, Hi",
    "sg:phone":"+34 917 54 13 92",
    "sg:postcode":"28017",
    "sg:province":"Madrid",
    "wof:name":"Universal Service S.a.l.",
    "wof:placetype":"venue"
},
  "geometry": {"coordinates":[-3.6353900433,40.4239425659],"type":"Point"}
}