{
  "type": "Feature",
  "properties": {
    "iso:country":"ES",
    "sg:address":"Calle de Sierra Del Madro\u00d1o, 10",
    "sg:city":"Malaga",
    "sg:orig_category":"Electricidad, Electr\u00d3nica: Material Y Suministros (al Por Mayor)",
    "sg:phone":"+34 952 33 26 66",
    "sg:postcode":"29003",
    "sg:province":"M\u00e1laga",
    "wof:name":"Novosystem S.l.",
    "wof:placetype":"venue"
},
  "geometry": {"coordinates":[-4.4501781464,36.6981658936],"type":"Point"}
}