{
  "type": "Feature",
  "properties": {
    "iso:country":"ES",
    "sg:address":"Plaz Ntra.sra.peana, 2",
    "sg:city":"Borja",
    "sg:orig_category":"Florister\u00cdas",
    "sg:phone":"+34 976 85 22 21",
    "sg:postcode":"50540",
    "sg:province":"Zaragoza",
    "wof:name":"Ruiz Corellano Juan Jose",
    "wof:placetype":"venue"
},
  "geometry": {"coordinates":[-1.5324150324,41.8349304199],"type":"Point"}
}