{
  "type": "Feature",
  "properties": {
    "addr:full":"Calle de Alcalde Espi\u00d1eira, S/n Curtis-estacion La Coru\u00f1a 15379",
    "addr:housenumber":"s",
    "addr:postcode":"15379",
    "addr:street":"Calle De Alcalde Espin\u0303Eira;/ N Curtis-Estacion La Corun\u0303A",
    "iso:country":"ES",
    "sg:address":"Calle de Alcalde Espi\u00d1eira, S/n",
    "sg:city":"Curtis-estacion",
    "sg:orig_category":"Molduras, Junquillos, Listones Y Molduras Perforadas",
    "sg:phone":"+34 981 78 64 27",
    "sg:postcode":"15379",
    "sg:province":"La Coru\u00f1a",
    "wof:name":"Freire Perez Jose Luis",
    "wof:placetype":"venue"
},
  "geometry": {"coordinates":[-8.1443376541,43.1230239868],"type":"Point"}
}