{
  "type": "Feature",
  "properties": {
    "addr:full":"Pase Alfonso Xiii, 16 Cartagena Murcia 30201",
    "addr:housenumber":"16",
    "addr:postcode":"30201",
    "addr:street":"Alfonso Xiii",
    "iso:country":"ES",
    "sg:address":"Pase Alfonso Xiii, 16",
    "sg:city":"Cartagena",
    "sg:orig_category":"Cajas De Ahorro",
    "sg:phone":"+34 968 33 01 52",
    "sg:postcode":"30201",
    "sg:province":"Murcia",
    "sg:website":"www.cajamurcia.es",
    "wof:name":"Comunidad Regantes Campo De Cartagena",
    "wof:placetype":"venue"
},
  "geometry": {"coordinates":[-0.8610739708,37.719329834],"type":"Point"}
}