{
  "type": "Feature",
  "properties": {
    "addr:full":"Calle de San Anton, 13 Granada Granada 18005",
    "addr:housenumber":"13",
    "addr:postcode":"18005",
    "addr:street":"Calle De San Anton",
    "iso:country":"ES",
    "sg:address":"Calle de San Anton, 13",
    "sg:city":"Granada",
    "sg:orig_category":"Electrodom\u00c9sticos (al Por Menor)",
    "sg:phone":"+34 958 25 37 22",
    "sg:postcode":"18005",
    "sg:province":"Granada",
    "wof:name":"Carvia Gutierrez Maria Angustia",
    "wof:placetype":"venue"
},
  "geometry": {"coordinates":[-3.5999209881,37.1723670959],"type":"Point"}
}