{
  "type": "Feature",
  "properties": {
    "addr:full":"Calle de Huelva, 7 Ronda M\u00e1laga 29400",
    "addr:housenumber":"7",
    "addr:postcode":"29400",
    "addr:street":"Calle De Huelva;Ronda Ma\u0301Laga",
    "iso:country":"ES",
    "sg:address":"Calle de Huelva, 7",
    "sg:city":"Ronda",
    "sg:orig_category":"Tarjetas De Cr\u00c9dito, De Pago, De Identidad",
    "sg:phone":"+34 952 87 90 89",
    "sg:postcode":"29400",
    "sg:province":"M\u00e1laga",
    "wof:name":"Gestion De Actividades Y Servicios Empresariales S.a.",
    "wof:placetype":"venue"
},
  "geometry": {"coordinates":[-5.1593317986,36.7490577698],"type":"Point"}
}