{
  "type": "Feature",
  "properties": {
    "addr:full":"Avda Cervantes, 6 Caceres C\u00e1ceres 10005",
    "addr:housenumber":"6",
    "addr:postcode":"10005",
    "addr:street":"Avda Cervantes;Ca\u0301Ceres",
    "iso:country":"ES",
    "sg:address":"Avda Cervantes, 6",
    "sg:city":"Caceres",
    "sg:orig_category":"Contenedores (mercanc\u00cdas)",
    "sg:phone":"+34 927 24 14 65",
    "sg:postcode":"10005",
    "sg:province":"C\u00e1ceres",
    "wof:name":"Bermejo Servan Fernando",
    "wof:placetype":"venue"
},
  "geometry": {"coordinates":[-6.3667459488,39.4545249939],"type":"Point"}
}