{
  "type": "Feature",
  "properties": {
    "iso:country":"ES",
    "sg:address":"Carrer de Rossello, 258",
    "sg:city":"Barcelona",
    "sg:orig_category":"M\u00c9dicos: Cirug\u00cda Cardiovascular Y Tor\u00c1cica",
    "sg:phone":"+34 932 15 39 69",
    "sg:postcode":"08037",
    "sg:province":"Barcelona",
    "wof:name":"Miquel Abbad Carlos",
    "wof:placetype":"venue"
},
  "geometry": {"coordinates":[2.1622869968,41.3969421387],"type":"Point"}
}