{
  "type": "Feature",
  "properties": {
    "iso:country":"ES",
    "sg:address":"Ctra Sevilla-malaga, Km. 0004,9",
    "sg:city":"Sevilla",
    "sg:orig_category":"Delegados, Agentes De Tr\u00c1nsito, Auxiliares De Transporte Internacional",
    "sg:phone":"+34 954 52 50 39",
    "sg:postcode":"41016",
    "sg:province":"Sevilla",
    "wof:name":"Gamertrans Sur S.l.",
    "wof:placetype":"venue"
},
  "geometry": {"coordinates":[-6.0018129349,37.3876953125],"type":"Point"}
}