{
  "type": "Feature",
  "properties": {
    "addr:full":"Avda Navarra, 99 Zaragoza Zaragoza 50017",
    "addr:housenumber":"99",
    "addr:postcode":"50017",
    "addr:street":"Avda Navarra",
    "iso:country":"ES",
    "sg:address":"Avda Navarra, 99",
    "sg:city":"Zaragoza",
    "sg:orig_category":"Motocicletas (agentes, Concesionarios)",
    "sg:phone":"+34 976 32 64 12",
    "sg:postcode":"50017",
    "sg:province":"Zaragoza",
    "sg:website":"www.poketbikesracing46.com",
    "wof:name":"Modrego Antolin Carlos",
    "wof:placetype":"venue"
},
  "geometry": {"coordinates":[-0.9105529785,41.6560211182],"type":"Point"}
}