{
  "type": "Feature",
  "properties": {
    "addr:full":"Carr Primitiu Artigas, 22 Torroella Montgri Girona 17257",
    "addr:housenumber":"22",
    "addr:postcode":"17257",
    "addr:street":"Carr Primitiu Artigas",
    "iso:country":"ES",
    "sg:address":"Carr Primitiu Artigas, 22",
    "sg:city":"Torroella Montgri",
    "sg:classifiers":[
        {
            "category":"Arts & Performance",
            "subcategory":"Art Gallery",
            "type":"Entertainment"
        }
    ],
    "sg:phone":"+34 972 76 18 77",
    "sg:postcode":"17257",
    "sg:province":"Girona",
    "sg:tags":[
        "arte",
        "de",
        "galer\u00cdas"
    ],
    "wof:name":"Bosch Farrero Marti",
    "wof:placetype":"venue"
},
  "geometry": {"coordinates":[3.1034500599,42.0303268433],"type":"Point"}
}