{
  "type": "Feature",
  "properties": {
    "iso:country":"ES",
    "sg:address":"Av Joan Miro, 138",
    "sg:city":"Palma",
    "sg:orig_category":"Asociaciones Y Clubs Deportivos",
    "sg:phone":"+34 971 45 03 12",
    "sg:postcode":"07015",
    "sg:province":"Islas Baleares",
    "wof:name":"Llumasanes S.l",
    "wof:placetype":"venue"
},
  "geometry": {"coordinates":[2.6231589317,39.558177948],"type":"Point"}
}