{
  "type": "Feature",
  "properties": {
    "addr:full":"Avda Espa\u00d1a (de), 125 Dos Hermanas Sevilla 41700",
    "addr:housenumber":"125",
    "addr:postcode":"41700",
    "addr:street":"Avda Espan\u0303A De;Sevilla",
    "iso:country":"ES",
    "sg:address":"Avda Espa\u00d1a (de), 125",
    "sg:city":"Dos Hermanas",
    "sg:orig_category":"Empresas De Carpinter\u00cda De Madera",
    "sg:phone":"+34 955 66 49 30",
    "sg:postcode":"41700",
    "sg:province":"Sevilla",
    "wof:name":"Ferrimadera S.l.",
    "wof:placetype":"venue"
},
  "geometry": {"coordinates":[-5.915157795,37.2867774963],"type":"Point"}
}