{
  "type": "Feature",
  "properties": {
    "addr:full":"Calle de Gran Via, 26 Sax Alicante 03630",
    "addr:housenumber":"26",
    "addr:postcode":"03630",
    "addr:street":"Calle De Gran Via",
    "iso:country":"ES",
    "sg:address":"Calle de Gran Via, 26",
    "sg:city":"Sax",
    "sg:orig_category":"Reposter\u00cdas",
    "sg:phone":"+34 965 47 41 30",
    "sg:postcode":"03630",
    "sg:province":"Alicante",
    "wof:name":"Panaderia El Cano S.l.",
    "wof:placetype":"venue"
},
  "geometry": {"coordinates":[-0.8192750216,38.5361404419],"type":"Point"}
}