{
  "type": "Feature",
  "properties": {
    "iso:country":"ES",
    "sg:address":"Carr Migdia, 9",
    "sg:city":"Girona",
    "sg:orig_category":"Peluquer\u00cdas",
    "sg:phone":"+34 972 22 48 89",
    "sg:postcode":"17002",
    "sg:province":"Girona",
    "wof:name":"Neclatea S.l.",
    "wof:placetype":"venue"
},
  "geometry": {"coordinates":[2.8210759163,41.9769554138],"type":"Point"}
}