{
  "type": "Feature",
  "properties": {
    "iso:country":"ES",
    "sg:address":"C/ Trinquet, 12",
    "sg:city":"Elche",
    "sg:orig_category":"Centros Empresariales",
    "sg:phone":"+34 966 61 32 08",
    "sg:postcode":"03202",
    "sg:province":"Alicante",
    "wof:name":"Asociacion Comerciantes Independientes De Elche",
    "wof:placetype":"venue"
},
  "geometry": {"coordinates":[-0.696604073,38.2668571472],"type":"Point"}
}