{
  "type": "Feature",
  "properties": {
    "iso:country":"ES",
    "sg:address":"Carretera Pedernoso, 6",
    "sg:city":"Las Mesas",
    "sg:orig_category":"Polideportivos",
    "sg:phone":"+34 967 15 55 22",
    "sg:postcode":"16650",
    "sg:province":"Cuenca",
    "wof:name":"Ayuntamiento De Las Mesas",
    "wof:placetype":"venue"
},
  "geometry": {"coordinates":[-2.7674269676,39.3904571533],"type":"Point"}
}