{
  "type": "Feature",
  "properties": {
    "addr:full":"Rbla Llibertat, 25 Girona Girona 17004",
    "addr:housenumber":"25",
    "addr:postcode":"17004",
    "addr:street":"Rbla Llibertat",
    "iso:country":"ES",
    "sg:address":"Rbla Llibertat, 25",
    "sg:city":"Girona",
    "sg:orig_category":"Peluquer\u00cdas",
    "sg:phone":"+34 972 21 23 21",
    "sg:postcode":"17004",
    "sg:province":"Girona",
    "wof:name":"Sanchez Algarrada Sonia",
    "wof:placetype":"venue"
},
  "geometry": {"coordinates":[2.8239939213,41.9842338562],"type":"Point"}
}