{
  "type": "Feature",
  "properties": {
    "iso:country":"ES",
    "sg:address":"Avda Tierno Galvan, 26",
    "sg:city":"Puerto Mazarron",
    "sg:orig_category":"Inmobiliaria (agencias)",
    "sg:phone":"+34 968 33 20 09",
    "sg:postcode":"30860",
    "sg:province":"Murcia",
    "sg:website":"www.proser2000.com",
    "wof:name":"Proser 2000 S.l.",
    "wof:placetype":"venue"
},
  "geometry": {"coordinates":[-1.2605090141,37.5637207031],"type":"Point"}
}