{
  "type": "Feature",
  "properties": {
    "addr:full":"Calle de Rio Segre, 1 Alcorcon Madrid 28923",
    "addr:housenumber":"1",
    "addr:postcode":"28923",
    "addr:street":"Calle De Rio Segre",
    "iso:country":"ES",
    "sg:address":"Calle de Rio Segre, 1",
    "sg:city":"Alcorcon",
    "sg:orig_category":"Fotocopias, Reprograf\u00cda",
    "sg:phone":"+34 916 11 19 17",
    "sg:postcode":"28923",
    "sg:province":"Madrid",
    "wof:name":"Imtal Reprografia S.l.",
    "wof:placetype":"venue"
},
  "geometry": {"coordinates":[-3.8149769306,40.3450927734],"type":"Point"}
}