{
  "type": "Feature",
  "properties": {
    "iso:country":"ES",
    "sg:address":"Calle de Arroyo Del Olivar, 60",
    "sg:city":"Madrid",
    "sg:orig_category":"Estancos",
    "sg:phone":"+34 914 77 11 16",
    "sg:postcode":"28053",
    "sg:province":"Madrid",
    "wof:name":"Gil Garcia Adolfo",
    "wof:placetype":"venue"
},
  "geometry": {"coordinates":[-3.6616597176,40.3919181824],"type":"Point"}
}