{
  "type": "Feature",
  "properties": {
    "addr:full":"Kale Agurain, 3 Alegria-dulantzi \u00c1lava 01240",
    "addr:housenumber":"3",
    "addr:postcode":"01240",
    "addr:street":"Kale Agurain;A\u0301Lava",
    "iso:country":"ES",
    "sg:address":"Kale Agurain, 3",
    "sg:city":"Alegria-dulantzi",
    "sg:orig_category":"Asilos De Ancianos. Centros Privados",
    "sg:phone":"+34 945 40 06 83",
    "sg:postcode":"01240",
    "sg:province":"\u00c1lava",
    "wof:name":"Mikelats S.c.",
    "wof:placetype":"venue"
},
  "geometry": {"coordinates":[-2.5149989128,42.842338562],"type":"Point"}
}