{
  "type": "Feature",
  "properties": {
    "iso:country":"ES",
    "sg:address":"Calle de Mitxelena, 2",
    "sg:city":"Altzaga",
    "sg:orig_category":"Ropa Para Se\u00d1oras (al Por Menor)",
    "sg:phone":"+34 944 67 08 44",
    "sg:postcode":"48950",
    "sg:province":"Vizcaya",
    "wof:name":"Somoza Sangil Pilar",
    "wof:placetype":"venue"
},
  "geometry": {"coordinates":[-2.9741065502,43.3031730652],"type":"Point"}
}