{
  "type": "Feature",
  "properties": {
    "iso:country":"ES",
    "sg:address":"Carrer de L'espaseria, 4",
    "sg:city":"Barcelona",
    "sg:orig_category":"Peluquer\u00cdas, Peluquer\u00cda Mixta",
    "sg:phone":"+34 933 10 00 46",
    "sg:postcode":"08003",
    "sg:province":"Barcelona",
    "wof:name":"Calzados Lamolla S.a.",
    "wof:placetype":"venue"
},
  "geometry": {"coordinates":[2.1821267605,41.3833885193],"type":"Point"}
}