{
  "type": "Feature",
  "properties": {
    "addr:full":"Plaz Constitucion, 1 Vilalba Lugo 27800",
    "addr:postcode":"27800",
    "addr:street":"Constitucion",
    "iso:country":"ES",
    "sg:address":"Plaz Constitucion, 1",
    "sg:city":"Vilalba",
    "sg:orig_category":"Administraciones Regionales, Departamentales Y Locales",
    "sg:phone":"+34 982 51 03 05",
    "sg:postcode":"27800",
    "sg:province":"Lugo",
    "wof:name":"Ayuntamiento De Vilalba-secretaria",
    "wof:placetype":"venue"
},
  "geometry": {"coordinates":[-7.6803164482,43.2972831726],"type":"Point"}
}