{
  "type": "Feature",
  "properties": {
    "iso:country":"ES",
    "sg:address":"Rua Reveriano Soutullo, 42",
    "sg:city":"Redondela",
    "sg:orig_category":"Fabricaci\u00d3n, Venta De Cuadros, Accesorios Para Enmarcar",
    "sg:phone":"+34 986 40 13 74",
    "sg:postcode":"36800",
    "sg:province":"Pontevedra",
    "wof:name":"Marcos Souto S.l.",
    "wof:placetype":"venue"
},
  "geometry": {"coordinates":[-8.6082544327,42.2826385498],"type":"Point"}
}