{
  "type": "Feature",
  "properties": {
    "addr:full":"Ctra Huesca, S/n Antillon Huesca 22133",
    "addr:housenumber":"s / n",
    "addr:postcode":"22133",
    "addr:street":"Ctra Huesca",
    "iso:country":"ES",
    "sg:address":"Ctra Huesca, S/n",
    "sg:city":"Antillon",
    "sg:orig_category":"Maquinaria Para Industrias Diversas",
    "sg:phone":"+34 974 26 03 35",
    "sg:postcode":"22133",
    "sg:province":"Huesca",
    "wof:name":"Latapia Vi\u00f1uales Antonio",
    "wof:placetype":"venue"
},
  "geometry": {"coordinates":[-0.1894990057,42.0562438965],"type":"Point"}
}