{
  "type": "Feature",
  "properties": {
    "iso:country":"ES",
    "sg:address":"Calle de Marimanta, 10",
    "sg:city":"Jerez De La Frontera",
    "sg:orig_category":"Farmacias",
    "sg:phone":"+34 956 34 27 14",
    "sg:postcode":"11401",
    "sg:province":"C\u00e1diz",
    "wof:name":"Llorente Piriz Maria",
    "wof:placetype":"venue"
},
  "geometry": {"coordinates":[-6.130466938,36.6798744202],"type":"Point"}
}