{
  "type": "Feature",
  "properties": {
    "iso:country":"ES",
    "sg:address":"Ctra. Benasque, S/n",
    "sg:city":"Villanova",
    "sg:orig_category":"Forjas Y Altos Hornos",
    "sg:phone":"+34 974 55 33 34",
    "sg:postcode":"22467",
    "sg:province":"Huesca",
    "wof:name":"Hermanos Plaza S.c.",
    "wof:placetype":"venue"
},
  "geometry": {"coordinates":[0.47161901,42.551361084],"type":"Point"}
}