{
  "type": "Feature",
  "properties": {
    "iso:country":"ES",
    "sg:address":"Av Valencia, 84",
    "sg:city":"Molins Rei",
    "sg:orig_category":"Promotores Constructores",
    "sg:phone":"+34 936 80 30 24",
    "sg:postcode":"08750",
    "sg:province":"Barcelona",
    "wof:name":"Tuberias Y Accesorios De P.v.c. Mo-mar S.l.",
    "wof:placetype":"venue"
},
  "geometry": {"coordinates":[2.0159790516,41.4097061157],"type":"Point"}
}