{
  "type": "Feature",
  "properties": {
    "addr:full":"Calle de Hermanos Garcia Noblejas, 190 Madrid Madrid 28037",
    "addr:housenumber":"190",
    "addr:postcode":"28037",
    "addr:street":"Calle De Hermanos Garcia Noblejas",
    "iso:country":"ES",
    "sg:address":"Calle de Hermanos Garcia Noblejas, 190",
    "sg:city":"Madrid",
    "sg:orig_category":"Peluquer\u00cdas, Peluquer\u00cda Mixta",
    "sg:phone":"+34 913 06 96 48",
    "sg:postcode":"28037",
    "sg:province":"Madrid",
    "wof:name":"Reguera Martinez Beatriz",
    "wof:placetype":"venue"
},
  "geometry": {"coordinates":[-3.6246809959,40.4190063477],"type":"Point"}
}