{
  "type": "Feature",
  "properties": {
    "iso:country":"ES",
    "sg:address":"Ctra. Zafra, Km. 0004,0",
    "sg:city":"Feria",
    "sg:orig_category":"Cr\u00cda De Animales",
    "sg:phone":"+34 924 69 41 52",
    "sg:postcode":"06390",
    "sg:province":"Badajoz",
    "wof:name":"Ganados Becerra S.l.",
    "wof:placetype":"venue"
},
  "geometry": {"coordinates":[-6.487238884,38.4895896912],"type":"Point"}
}