{
  "type": "Feature",
  "properties": {
    "iso:country":"ES",
    "sg:address":"Rbla Celler, 99",
    "sg:city":"S. Cugat Valles",
    "sg:orig_category":"Comercio, Reparaci\u00d3n De Motocicletas, Bicicletas Y Piezas Sueltas",
    "sg:phone":"+34 936 74 20 08",
    "sg:postcode":"08172",
    "sg:province":"Barcelona",
    "wof:name":"Xaus Rafi Miguel",
    "wof:placetype":"venue"
},
  "geometry": {"coordinates":[2.0900652409,41.4720573425],"type":"Point"}
}