{
  "type": "Feature",
  "properties": {
    "addr:full":"C/ Almansa, 7 Elche Alicante 03291",
    "addr:housenumber":"7",
    "addr:postcode":"03291",
    "addr:street":"C / Almansa",
    "iso:country":"ES",
    "sg:address":"C/ Almansa, 7",
    "sg:city":"Elche",
    "sg:orig_category":"Bordado, Marcado A Medida",
    "sg:phone":"+34 966 66 23 78",
    "sg:postcode":"03291",
    "sg:province":"Alicante",
    "wof:name":"Bordados La Dama S.l.",
    "wof:placetype":"venue"
},
  "geometry": {"coordinates":[-0.7151600122,38.2808036804],"type":"Point"}
}