{
  "type": "Feature",
  "properties": {
    "addr:full":"Calle de Ciscar, 32 Valencia Valencia 46005",
    "addr:housenumber":"32",
    "addr:postcode":"46005",
    "addr:street":"Calle De Ciscar",
    "iso:country":"ES",
    "sg:address":"Calle de Ciscar, 32",
    "sg:city":"Valencia",
    "sg:orig_category":"M\u00c9dicos: Medicina Interna",
    "sg:phone":"+34 963 73 01 00",
    "sg:postcode":"46005",
    "sg:province":"Valencia",
    "wof:name":"Tari Tello Rosa Maria",
    "wof:placetype":"venue"
},
  "geometry": {"coordinates":[-0.365447998,39.4654197693],"type":"Point"}
}