{
  "type": "Feature",
  "properties": {
    "iso:country":"ES",
    "sg:address":"La Rivera-ibaialde Kalea, 1",
    "sg:city":"Abetxuko",
    "sg:orig_category":"Art\u00cdculos De Regalo (al Por Menor)",
    "sg:phone":"+34 945 12 38 39",
    "sg:postcode":"01013",
    "sg:province":"\u00c1lava",
    "wof:name":"Alonso Del Orza Gustavo",
    "wof:placetype":"venue"
},
  "geometry": {"coordinates":[-2.6754357815,42.8745727539],"type":"Point"}
}