{
  "type": "Feature",
  "properties": {
    "addr:full":"Cust San Cristobal, S/n Valladolid Valladolid 47012",
    "addr:postcode":"47012",
    "addr:street":"San Cristobal S / N",
    "iso:country":"ES",
    "sg:address":"Cust San Cristobal, S/n",
    "sg:city":"Valladolid",
    "sg:classifiers":[
        {
            "category":"Communications",
            "type":"Services"
        }
    ],
    "sg:phone":"+34 983 39 82 64",
    "sg:postcode":"47012",
    "sg:province":"Valladolid",
    "sg:tags":[
        "televisiones",
        "y",
        "radio"
    ],
    "wof:name":"Radio Nacional De Espa\u00f1a S.a.",
    "wof:placetype":"venue"
},
  "geometry": {"coordinates":[-4.695494175,41.6288452148],"type":"Point"}
}