{
  "type": "Feature",
  "properties": {
    "addr:full":"Avda. De La Estacion, S/n Sobradelo Ourense 32330",
    "addr:postcode":"32330",
    "addr:street":"Avda. De La Estacion S / N",
    "iso:country":"ES",
    "sg:address":"Avda. De La Estacion, S/n",
    "sg:city":"Sobradelo",
    "sg:orig_category":"Pizzer\u00cdas",
    "sg:phone":"+34 988 33 50 41",
    "sg:postcode":"32330",
    "sg:province":"Ourense",
    "wof:name":"Pizarras Lomba S.l.",
    "wof:placetype":"venue"
},
  "geometry": {"coordinates":[-6.9207801819,42.3918495178],"type":"Point"}
}