{
  "type": "Feature",
  "properties": {
    "addr:full":"Plaz Constitucion (la), 5 Alcorcon Madrid 28925",
    "addr:postcode":"28925",
    "addr:street":"Constitucion La 5 Alcorcon",
    "iso:country":"ES",
    "sg:address":"Plaz Constitucion (la), 5",
    "sg:city":"Alcorcon",
    "sg:orig_category":"Asociaciones Humanitarias, De Cooperaci\u00d3n, De Acci\u00d3n Social",
    "sg:phone":"+34 916 11 91 52",
    "sg:postcode":"28925",
    "sg:province":"Madrid",
    "wof:name":"Asociacion De Parkinson James Parkinson",
    "wof:placetype":"venue"
},
  "geometry": {"coordinates":[-3.8136224747,40.3542480469],"type":"Point"}
}