{
  "type": "Feature",
  "properties": {
    "iso:country":"ES",
    "sg:address":"Calle de Cuesta Del Molino, S/n",
    "sg:city":"Puente-genil",
    "sg:orig_category":"Frutas Y Legumbres Frescas (al Por Mayor)",
    "sg:phone":"+34 957 60 05 29",
    "sg:postcode":"14500",
    "sg:province":"C\u00f3rdoba",
    "wof:name":"Frutas Trivi\u00f1o Luna S.l.",
    "wof:placetype":"venue"
},
  "geometry": {"coordinates":[-4.7705054283,37.3940963745],"type":"Point"}
}