{
  "type": "Feature",
  "properties": {
    "iso:country":"ES",
    "sg:address":"Calle de Conde De Gondomar, 3",
    "sg:city":"Cordoba",
    "sg:orig_category":"Promotores Constructores",
    "sg:phone":"+34 957 47 22 84",
    "sg:postcode":"14003",
    "sg:province":"C\u00f3rdoba",
    "wof:name":"Empresas Y Fincas S.a.",
    "wof:placetype":"venue"
},
  "geometry": {"coordinates":[-4.7801828384,37.8844490051],"type":"Point"}
}