{
  "type": "Feature",
  "properties": {
    "addr:full":"Calle de Pico De Almanzor, 17 Salamanca Salamanca 37008",
    "addr:housenumber":"17",
    "addr:postcode":"37008",
    "addr:street":"Calle De Pico De Almanzor",
    "iso:country":"ES",
    "sg:address":"Calle de Pico De Almanzor, 17",
    "sg:city":"Salamanca",
    "sg:orig_category":"Contenedores (mercanc\u00cdas)",
    "sg:phone":"+34 923 19 27 73",
    "sg:postcode":"37008",
    "sg:province":"Salamanca",
    "wof:name":"Martin Martin Aristonico",
    "wof:placetype":"venue"
},
  "geometry": {"coordinates":[-5.672118187,40.9510002136],"type":"Point"}
}