{
  "type": "Feature",
  "properties": {
    "addr:full":"Calle de Alfareria, 125 Sevilla Sevilla 41010",
    "addr:housenumber":"125",
    "addr:postcode":"41010",
    "addr:street":"Calle De Alfareria",
    "iso:country":"ES",
    "sg:address":"Calle de Alfareria, 125",
    "sg:city":"Sevilla",
    "sg:orig_category":"Ba\u00d1os Y Duchas P\u00dablicos",
    "sg:phone":"+34 954 34 01 22",
    "sg:postcode":"41010",
    "sg:province":"Sevilla",
    "wof:name":"Piscina Mar Del Fervid Sevilla S.l.",
    "wof:placetype":"venue"
},
  "geometry": {"coordinates":[-6.0089716911,37.3882980347],"type":"Point"}
}