{
  "type": "Feature",
  "properties": {
    "addr:full":"Calle de Calderon, 7 Madrid Madrid 28042",
    "addr:housenumber":"7",
    "addr:postcode":"madrid;28042",
    "addr:street":"Calle De Calderon",
    "iso:country":"ES",
    "sg:address":"Calle de Calderon, 7",
    "sg:city":"Madrid",
    "sg:orig_category":"Tintes (fabricaci\u00d3n, Al Por Mayor)",
    "sg:phone":"+34 913 29 24 85",
    "sg:postcode":"28042",
    "sg:province":"Madrid",
    "wof:name":"Lumbreras Galarzo Amparo",
    "wof:placetype":"venue"
},
  "geometry": {"coordinates":[-3.5837161541,40.4708900452],"type":"Point"}
}