{
  "type": "Feature",
  "properties": {
    "iso:country":"ES",
    "sg:address":"Villarmide, S/n",
    "sg:city":"Senande",
    "sg:orig_category":"Electrodom\u00c9sticos (al Por Menor)",
    "sg:phone":"+34 981 75 06 54",
    "sg:postcode":"15125",
    "sg:province":"La Coru\u00f1a",
    "wof:name":"Martinez Ozon Jose Fernando",
    "wof:placetype":"venue"
},
  "geometry": {"coordinates":[-9.1517896652,43.0451126099],"type":"Point"}
}