{
  "type": "Feature",
  "properties": {
    "addr:full":"Calle de Doctor Velez, 17 S. Martin Camino Le\u00f3n 24393",
    "addr:housenumber":"17",
    "addr:postcode":"24393",
    "addr:street":"Calle De Doctor Velez;S. Martin Camino Leo\u0301N",
    "iso:country":"ES",
    "sg:address":"Calle de Doctor Velez, 17",
    "sg:city":"S. Martin Camino",
    "sg:orig_category":"Producci\u00d3n De Abonos Y De Fertilizantes",
    "sg:phone":"+34 987 37 85 47",
    "sg:postcode":"24393",
    "sg:province":"Le\u00f3n",
    "wof:name":"Gonzalez San Martin S.l.",
    "wof:placetype":"venue"
},
  "geometry": {"coordinates":[-5.8116340637,42.4937820435],"type":"Point"}
}