{
  "type": "Feature",
  "properties": {
    "iso:country":"ES",
    "sg:address":"Calle de Llano Ponte, 10",
    "sg:city":"Aviles",
    "sg:orig_category":"Farmacias",
    "sg:phone":"+34 985 54 35 40",
    "sg:postcode":"33402",
    "sg:province":"Asturias",
    "wof:name":"Carlos Escobedo Sela Y Miguel Escobedo S",
    "wof:placetype":"venue"
},
  "geometry": {"coordinates":[-5.9195251465,43.5554046631],"type":"Point"}
}