{
  "type": "Feature",
  "properties": {
    "iso:country":"ES",
    "sg:address":"Calle de Lope De Vega, 56",
    "sg:city":"Albacete",
    "sg:orig_category":"Mec\u00c1nico Del Autom\u00d3vil",
    "sg:phone":"+34 967 23 09 55",
    "sg:postcode":"02005",
    "sg:province":"Albacete",
    "wof:name":"Diaz Martinez Juan",
    "wof:placetype":"venue"
},
  "geometry": {"coordinates":[-1.8697060347,38.9997444153],"type":"Point"}
}