{
  "type": "Feature",
  "properties": {
    "iso:country":"ES",
    "sg:address":"Calle de Primo De Rivera, 14",
    "sg:city":"Caspe",
    "sg:orig_category":"Ense\u00d1anza: Comercio, Gesti\u00d3n, Inform\u00c1tica",
    "sg:phone":"+34 976 63 96 40",
    "sg:postcode":"50700",
    "sg:province":"Zaragoza",
    "wof:name":"Inforcaspe",
    "wof:placetype":"venue"
},
  "geometry": {"coordinates":[-0.0425189994,41.2394981384],"type":"Point"}
}