{
  "type": "Feature",
  "properties": {
    "iso:country":"ES",
    "sg:address":"Carrer de Arquebisbe Aspareg, S/n",
    "sg:city":"Palma",
    "sg:orig_category":"Reposter\u00cdas",
    "sg:phone":"+34 971 27 48 09",
    "sg:postcode":"07007",
    "sg:province":"Islas Baleares",
    "wof:name":"Alfaro Coll Maria Ines",
    "wof:placetype":"venue"
},
  "geometry": {"coordinates":[2.6663188934,39.5755958557],"type":"Point"}
}