{
  "type": "Feature",
  "properties": {
    "addr:full":"Calle de Amistad, 14 Madrid Madrid 28025",
    "addr:housenumber":"14",
    "addr:postcode":"madrid;28025",
    "addr:street":"Calle De Amistad",
    "iso:country":"ES",
    "sg:address":"Calle de Amistad, 14",
    "sg:city":"Madrid",
    "sg:orig_category":"Artes Gr\u00c1ficas, Artes Pl\u00c1sticas (curso)",
    "sg:phone":"+34 915 25 81 25",
    "sg:postcode":"28025",
    "sg:province":"Madrid",
    "wof:name":"Graficos Y Textos S.l.",
    "wof:placetype":"venue"
},
  "geometry": {"coordinates":[-3.7383387089,40.389705658],"type":"Point"}
}