{
  "type": "Feature",
  "properties": {
    "iso:country":"ES",
    "sg:address":"Calle de Francisco Puerta Gonzalez-conde, 7",
    "sg:city":"Bullas",
    "sg:orig_category":"Asociaciones Y Clubs Deportivos",
    "sg:phone":"+34 968 65 52 46",
    "sg:postcode":"30180",
    "sg:province":"Murcia",
    "wof:name":"Ruiz Escamez Jose",
    "wof:placetype":"venue"
},
  "geometry": {"coordinates":[-1.6673339605,38.0496139526],"type":"Point"}
}