{
  "type": "Feature",
  "properties": {
    "addr:full":"Calle de Magdalena (de La), 3 Baeza Ja\u00e9n 23440",
    "addr:housenumber":"3",
    "addr:postcode":"23440",
    "addr:street":"Calle De Magdalena De La",
    "iso:country":"ES",
    "sg:address":"Calle de Magdalena (de La), 3",
    "sg:city":"Baeza",
    "sg:orig_category":"Electrodom\u00c9sticos (al Por Menor)",
    "sg:phone":"+34 953 74 17 41",
    "sg:postcode":"23440",
    "sg:province":"Ja\u00e9n",
    "wof:name":"Santos Rueda Andres",
    "wof:placetype":"venue"
},
  "geometry": {"coordinates":[-3.4681370258,37.9957466125],"type":"Point"}
}