{
  "type": "Feature",
  "properties": {
    "iso:country":"ES",
    "sg:address":"Calle de Jose Zorrilla, 19",
    "sg:city":"Segovia",
    "sg:orig_category":"Art\u00cdculos De Regalo (al Por Menor)",
    "sg:phone":"+34 921 43 00 25",
    "sg:postcode":"40002",
    "sg:province":"Segovia",
    "wof:name":"Martin Pascual Nuria",
    "wof:placetype":"venue"
},
  "geometry": {"coordinates":[-4.1155991554,40.9428100586],"type":"Point"}
}