{
  "type": "Feature",
  "properties": {
    "addr:full":"Matias Montero, S/n Pozuelo De Zarzon C\u00e1ceres 10813",
    "addr:housenumber":"s / n",
    "addr:postcode":"10813",
    "addr:street":"Matias Montero;Ca\u0301Ceres",
    "iso:country":"ES",
    "sg:address":"Matias Montero, S/n",
    "sg:city":"Pozuelo De Zarzon",
    "sg:classifiers":[
        {
            "category":"Taxi",
            "type":"Transportation"
        }
    ],
    "sg:phone":"+34 927 44 81 61",
    "sg:postcode":"10813",
    "sg:province":"C\u00e1ceres",
    "wof:name":"Martin Martin Francisco",
    "wof:placetype":"venue"
},
  "geometry": {"coordinates":[-6.4148287773,40.1499595642],"type":"Point"}
}