{
  "type": "Feature",
  "properties": {
    "addr:full":"Urbanizacion Laguna Beach, 1 Torrox-costa M\u00e1laga 29793",
    "addr:housenumber":"1",
    "addr:postcode":"29793",
    "addr:street":"Torrox-Costa Ma\u0301Laga",
    "iso:country":"ES",
    "sg:address":"Urbanizacion Laguna Beach, 1",
    "sg:city":"Torrox-costa",
    "sg:orig_category":"Papeler\u00cdas, Librer\u00cdas",
    "sg:phone":"+34 952 53 25 99",
    "sg:postcode":"29793",
    "sg:province":"M\u00e1laga",
    "wof:name":"Molina Ales Laura",
    "wof:placetype":"venue"
},
  "geometry": {"coordinates":[-3.9737811089,36.7323799133],"type":"Point"}
}