{
  "type": "Feature",
  "properties": {
    "iso:country":"ES",
    "sg:address":"Plaz Constitucion, 3",
    "sg:city":"Alozaina",
    "sg:orig_category":"Empresarios",
    "sg:phone":"+34 952 48 01 40",
    "sg:postcode":"29567",
    "sg:province":"M\u00e1laga",
    "wof:name":"Fundacion Red Andalucia Emprende",
    "wof:placetype":"venue"
},
  "geometry": {"coordinates":[-4.8563241959,36.7279548645],"type":"Point"}
}