{
  "type": "Feature",
  "properties": {
    "iso:country":"ES",
    "sg:address":"Carr Santos Justo Y Pastor, 36",
    "sg:city":"Manises",
    "sg:orig_category":"Agentes, Concesionarios Y Sucursales De Veh\u00cdculos",
    "sg:phone":"+34 961 54 58 69",
    "sg:postcode":"46940",
    "sg:province":"Valencia",
    "wof:name":"Talleres Andres Perez S.l.",
    "wof:placetype":"venue"
},
  "geometry": {"coordinates":[-0.4676690102,39.4938964844],"type":"Point"}
}