{
  "type": "Feature",
  "properties": {
    "iso:country":"ES",
    "sg:address":"Avda Juventudes Musicales, 1",
    "sg:city":"Sevilla",
    "sg:orig_category":"Edici\u00d3n De Diarios, Revistas, Boletines",
    "sg:phone":"+34 954 38 02 22",
    "sg:postcode":"41009",
    "sg:province":"Sevilla",
    "sg:website":"www.signaturaediciones.com",
    "wof:name":"Signatura Ediciones De Andalucia S.l.",
    "wof:placetype":"venue"
},
  "geometry": {"coordinates":[-5.984336853,37.4135780334],"type":"Point"}
}