{
  "type": "Feature",
  "properties": {
    "addr:full":"Calle de Laguna, 10 Toscas-chorrico Murcia 30500",
    "addr:housenumber":"10",
    "addr:postcode":"30500",
    "addr:street":"Calle De Laguna",
    "iso:country":"ES",
    "sg:address":"Calle de Laguna, 10",
    "sg:city":"Toscas-chorrico",
    "sg:orig_category":"Hielo Artificial (fabricaci\u00d3n, Distribuci\u00d3n)",
    "sg:phone":"+34 968 61 10 05",
    "sg:postcode":"30500",
    "sg:province":"Murcia",
    "wof:name":"Comercial Y Distribuidora De Congelados Prevegel S.l.",
    "wof:placetype":"venue"
},
  "geometry": {"coordinates":[-1.1830840111,38.0650901794],"type":"Point"}
}