{
  "type": "Feature",
  "properties": {
    "iso:country":"ES",
    "sg:address":"Rua Bautizados (dos), 3",
    "sg:city":"Santiago De Compostela",
    "sg:orig_category":"Agencias Y Agentes Comerciales, Representantes",
    "sg:phone":"+34 981 57 05 52",
    "sg:postcode":"15702",
    "sg:province":"La Coru\u00f1a",
    "wof:name":"Compa\u00d1ia Empresarial Pacios S.l.",
    "wof:placetype":"venue"
},
  "geometry": {"coordinates":[-8.5453720093,42.8773002625],"type":"Point"}
}