{
  "type": "Feature",
  "properties": {
    "iso:country":"ES",
    "sg:address":"Calle de Casta\u00d1o (el), 9",
    "sg:city":"Algeciras",
    "sg:orig_category":"Farmacias",
    "sg:phone":"+34 956 66 40 76",
    "sg:postcode":"11205",
    "sg:province":"C\u00e1diz",
    "wof:name":"Nu\u00f1ez Fluxa Juan Jose",
    "wof:placetype":"venue"
},
  "geometry": {"coordinates":[-5.4586172104,36.1550521851],"type":"Point"}
}