{
  "type": "Feature",
  "properties": {
    "addr:full":"Ptda Altabix, 120 Elche Alicante 03291",
    "addr:housenumber":"120",
    "addr:postcode":"03291",
    "addr:street":"Ptda Altabix",
    "iso:country":"ES",
    "sg:address":"Ptda Altabix, 120",
    "sg:city":"Elche",
    "sg:orig_category":"Reciclaje, Tratamiento De Tejidos",
    "sg:phone":"+34 965 42 61 20",
    "sg:postcode":"03291",
    "sg:province":"Alicante",
    "wof:name":"Dipesvi S.l.",
    "wof:placetype":"venue"
},
  "geometry": {"coordinates":[-0.6860749722,38.299079895],"type":"Point"}
}