{
  "type": "Feature",
  "properties": {
    "iso:country":"ES",
    "sg:address":"Calle de Gomez Oca\u00d1a, 5",
    "sg:city":"Malaga",
    "sg:orig_category":"Chapister\u00cda",
    "sg:phone":"+34 952 28 10 91",
    "sg:postcode":"29007",
    "sg:province":"M\u00e1laga",
    "wof:name":"Cornejo Y Morales S.a.",
    "wof:placetype":"venue"
},
  "geometry": {"coordinates":[-4.4512348175,36.7214126587],"type":"Point"}
}