{
  "type": "Feature",
  "properties": {
    "addr:full":"Calle de Turia, 11 Meliana Valencia 46133",
    "addr:housenumber":"11",
    "addr:postcode":"46133",
    "addr:street":"Calle De Turia",
    "iso:country":"ES",
    "sg:address":"Calle de Turia, 11",
    "sg:city":"Meliana",
    "sg:orig_category":"Tapiceros Y Tapiceros",
    "sg:phone":"+34 961 49 20 05",
    "sg:postcode":"46133",
    "sg:province":"Valencia",
    "wof:name":"Perez Baixauli Vicente",
    "wof:placetype":"venue"
},
  "geometry": {"coordinates":[-0.3526290059,39.5264587402],"type":"Point"}
}