{
  "type": "Feature",
  "properties": {
    "addr:full":"Calle de San Isidro, 2 Sonseca Toledo 45100",
    "addr:housenumber":"2",
    "addr:postcode":"45100",
    "addr:street":"Calle De San Isidro",
    "iso:country":"ES",
    "sg:address":"Calle de San Isidro, 2",
    "sg:city":"Sonseca",
    "sg:orig_category":"Confecci\u00d3n (fabricaci\u00d3n, Al Por Mayor)",
    "sg:phone":"+34 925 38 09 01",
    "sg:postcode":"45100",
    "sg:province":"Toledo",
    "wof:name":"Martin Sanchez Benito",
    "wof:placetype":"venue"
},
  "geometry": {"coordinates":[-3.9681999683,39.6754875183],"type":"Point"}
}