{
  "type": "Feature",
  "properties": {
    "iso:country":"ES",
    "sg:address":"Avda Denia, 32",
    "sg:city":"Alacant",
    "sg:orig_category":"Fabricaci\u00d3n, Importaci\u00d3n, Venta De Material De Telefon\u00cda, Peritelefon\u00cda",
    "sg:phone":"+34 965 22 01 56",
    "sg:postcode":"03016",
    "sg:province":"Alicante",
    "sg:website":"www.eurodigitalphones.es",
    "wof:name":"Mobile Phone Comunicaciones S.l.",
    "wof:placetype":"venue"
},
  "geometry": {"coordinates":[-0.4705969989,38.3565597534],"type":"Point"}
}