{
  "type": "Feature",
  "properties": {
    "addr:full":"Presa Finisterre, S/n Villanueva Bogas Toledo 45410",
    "addr:housenumber":"s",
    "addr:postcode":"45410",
    "addr:street":"Presa Finisterre;/ N",
    "iso:country":"ES",
    "sg:address":"Presa Finisterre, S/n",
    "sg:city":"Villanueva Bogas",
    "sg:orig_category":"Aguas (distribuci\u00d3n, Servicios)",
    "sg:phone":"+34 925 59 41 31",
    "sg:postcode":"45410",
    "sg:province":"Toledo",
    "wof:name":"Confederacion Hidrografica Del Tajo",
    "wof:placetype":"venue"
},
  "geometry": {"coordinates":[-3.6554911137,39.7226333618],"type":"Point"}
}