{
  "type": "Feature",
  "properties": {
    "iso:country":"ES",
    "sg:address":"Calle de Pablo Picasso, 3",
    "sg:city":"Alhama Granada",
    "sg:orig_category":"Cr\u00cda De Cerdos",
    "sg:phone":"+34 958 36 07 49",
    "sg:postcode":"18120",
    "sg:province":"Granada",
    "wof:name":"Ganadera Javier Martin Sl",
    "wof:placetype":"venue"
},
  "geometry": {"coordinates":[-3.9911999702,37.0054893494],"type":"Point"}
}