{
  "type": "Feature",
  "properties": {
    "addr:full":"Calle de Portal Del Rey, 22 Vitoria-gasteiz \u00c1lava 01001",
    "addr:housenumber":"22",
    "addr:postcode":"01001",
    "addr:street":"Calle De Portal Del Rey",
    "iso:country":"ES",
    "sg:address":"Calle de Portal Del Rey, 22",
    "sg:city":"Vitoria-gasteiz",
    "sg:orig_category":"Instalaci\u00d3n, Reparaci\u00d3n De Ascensores Y Montacargas",
    "sg:phone":"+34 945 25 18 03",
    "sg:postcode":"01001",
    "sg:province":"\u00c1lava",
    "wof:name":"Olbea Eleva S.l.",
    "wof:placetype":"venue"
},
  "geometry": {"coordinates":[-2.6679480076,42.8467979431],"type":"Point"}
}