{
  "type": "Feature",
  "properties": {
    "iso:country":"ES",
    "sg:address":"Rua Ronda Don Bosco, 29",
    "sg:city":"Vigo",
    "sg:orig_category":"Fiesta: Art\u00cdculos De (al Por Menor)",
    "sg:phone":"+34 986 43 13 70",
    "sg:postcode":"36202",
    "sg:province":"Pontevedra",
    "wof:name":"Gomez Casal Crisanto",
    "wof:placetype":"venue"
},
  "geometry": {"coordinates":[-8.7237701416,42.2352180481],"type":"Point"}
}