{
  "type": "Feature",
  "properties": {
    "iso:country":"ES",
    "sg:address":"Calle de Alonso Cano, 70",
    "sg:city":"Madrid",
    "sg:orig_category":"Centros Empresariales",
    "sg:phone":"+34 915 53 11 50",
    "sg:postcode":"28003",
    "sg:province":"Madrid",
    "wof:name":"Gestion Empresarial Iberica S.l.",
    "wof:placetype":"venue"
},
  "geometry": {"coordinates":[-3.6973316669,40.443775177],"type":"Point"}
}