{
  "type": "Feature",
  "properties": {
    "iso:country":"ES",
    "sg:address":"Carrer de Piferrer, 148",
    "sg:city":"Barcelona",
    "sg:orig_category":"Supermercados Y Hipermercados",
    "sg:phone":"+34 932 76 81 86",
    "sg:postcode":"08016",
    "sg:province":"Barcelona",
    "wof:name":"Maycas Alimentacion S.l.",
    "wof:placetype":"venue"
},
  "geometry": {"coordinates":[2.1776549816,41.4324378967],"type":"Point"}
}