{
  "type": "Feature",
  "properties": {
    "addr:full":"Carr Industria, 12 Palamos Girona 17230",
    "addr:housenumber":"12",
    "addr:postcode":"17230",
    "addr:street":"Carr Industria",
    "iso:country":"ES",
    "sg:address":"Carr Industria, 12",
    "sg:city":"Palamos",
    "sg:orig_category":"Asesor\u00cda Sobre Comunicaci\u00d3n De Empresas",
    "sg:phone":"+34 972 60 12 13",
    "sg:postcode":"17230",
    "sg:province":"Girona",
    "wof:name":"Aspime S.l.",
    "wof:placetype":"venue"
},
  "geometry": {"coordinates":[3.1286585331,41.8495597839],"type":"Point"}
}