{
  "type": "Feature",
  "properties": {
    "iso:country":"ES",
    "sg:address":"Carrer de Lugo, 46",
    "sg:city":"Barcelona",
    "sg:orig_category":"Prendas Y Chalecos De Punto (al Por Menor)",
    "sg:phone":"+34 934 20 36 02",
    "sg:postcode":"08032",
    "sg:province":"Barcelona",
    "wof:name":"Pujol Morell Montserrat",
    "wof:placetype":"venue"
},
  "geometry": {"coordinates":[2.1559870243,41.423286438],"type":"Point"}
}