{
  "type": "Feature",
  "properties": {
    "iso:country":"ES",
    "sg:address":"Calle de Valladolid (de), 24",
    "sg:city":"Humanes De Madrid",
    "sg:orig_category":"Tapicer\u00cdas",
    "sg:phone":"+34 916 90 59 63",
    "sg:postcode":"28970",
    "sg:province":"Madrid",
    "wof:name":"Garcia Garcia Clara",
    "wof:placetype":"venue"
},
  "geometry": {"coordinates":[-3.8169291019,40.2753715515],"type":"Point"}
}