{
  "type": "Feature",
  "properties": {
    "iso:country":"ES",
    "sg:address":"Calle de Carril De Venus, 4",
    "sg:city":"Cortijos",
    "sg:orig_category":"Delineantes",
    "sg:phone":"+34 918 12 98 67",
    "sg:postcode":"28609",
    "sg:province":"Madrid",
    "wof:name":"Eed3 Dise\u00f1o Circuitos Impresos S.l.",
    "wof:placetype":"venue"
},
  "geometry": {"coordinates":[-4.0545315742,40.3478507996],"type":"Point"}
}