{
  "type": "Feature",
  "properties": {
    "addr:full":"Bda Arenitas, S/n Herrera Sevilla 41567",
    "addr:housenumber":"s / n",
    "addr:postcode":"41567",
    "iso:country":"ES",
    "sg:address":"Bda Arenitas, S/n",
    "sg:city":"Herrera",
    "sg:orig_category":"Frutas Y Legumbres Frescas (al Por Mayor)",
    "sg:phone":"+34 954 01 34 53",
    "sg:postcode":"41567",
    "sg:province":"Sevilla",
    "wof:name":"Pineda Humanes Nicolas",
    "wof:placetype":"venue"
},
  "geometry": {"coordinates":[-4.8506789207,37.3627128601],"type":"Point"}
}