{
  "type": "Feature",
  "properties": {
    "addr:full":"Pase Igeldo De, S/n Donostia-san Sebastian Guip\u00f9zcoa 20008",
    "addr:housenumber":"s",
    "addr:postcode":"20008",
    "addr:street":"/ N",
    "iso:country":"ES",
    "sg:address":"Pase Igeldo De, S/n",
    "sg:city":"Donostia-san Sebastian",
    "sg:classifiers":[
        {
            "category":"Communications",
            "type":"Services"
        }
    ],
    "sg:phone":"+34 943 21 23 04",
    "sg:postcode":"20008",
    "sg:province":"Guip\u00f9zcoa",
    "sg:tags":[
        "televisiones",
        "y",
        "radio"
    ],
    "wof:name":"Sociedad Espa\u00f1ola De Radiodifusion Radio San Sebastian",
    "wof:placetype":"venue"
},
  "geometry": {"coordinates":[-2.0145559311,43.3180541992],"type":"Point"}
}