{
  "type": "Feature",
  "properties": {
    "addr:full":"Calle de Isidro Rodriguez, 22 Riaza Segovia 40500",
    "addr:housenumber":"22",
    "addr:postcode":"40500",
    "addr:street":"Calle De Isidro Rodriguez",
    "iso:country":"ES",
    "sg:address":"Calle de Isidro Rodriguez, 22",
    "sg:city":"Riaza",
    "sg:orig_category":"Hoteles",
    "sg:phone":"+34 921 55 00 51",
    "sg:postcode":"40500",
    "sg:province":"Segovia",
    "wof:name":"Casaquemada De Riaza S.l.",
    "wof:placetype":"venue"
},
  "geometry": {"coordinates":[-3.4807589054,41.2790985107],"type":"Point"}
}