{
  "type": "Feature",
  "properties": {
    "addr:full":"Calle de San Amador, 15 Torrent Valencia 46900",
    "addr:housenumber":"15",
    "addr:postcode":"46900",
    "addr:street":"Calle De San Amador;Valencia",
    "iso:country":"ES",
    "sg:address":"Calle de San Amador, 15",
    "sg:city":"Torrent",
    "sg:orig_category":"Molduras, Junquillos, Listones Y Molduras Perforadas",
    "sg:phone":"+34 961 56 12 30",
    "sg:postcode":"46900",
    "sg:province":"Valencia",
    "wof:name":"Cercos Garcia Miguel Angel",
    "wof:placetype":"venue"
},
  "geometry": {"coordinates":[-0.4604769945,39.4361190796],"type":"Point"}
}