{
  "type": "Feature",
  "properties": {
    "iso:country":"ES",
    "sg:address":"Carrer de Sant Sebastia, 201",
    "sg:city":"Terrassa",
    "sg:orig_category":"Automatizaci\u00d3n De Procesos Industriales Y De Edificaci\u00d3n (estudios, Instalaci\u00d3n)",
    "sg:phone":"+34 937 85 34 03",
    "sg:postcode":"08223",
    "sg:province":"Barcelona",
    "wof:name":"Mitormat S. L.",
    "wof:placetype":"venue"
},
  "geometry": {"coordinates":[2.0117590427,41.5550689697],"type":"Point"}
}