{
  "type": "Feature",
  "properties": {
    "iso:country":"ES",
    "sg:address":"Calle de Secoya, 28",
    "sg:city":"Madrid",
    "sg:orig_category":"Elementos Para Suelos Prefabricados",
    "sg:phone":"+34 915 08 91 47",
    "sg:postcode":"28044",
    "sg:province":"Madrid",
    "sg:website":"www.parquetscamara.com",
    "wof:name":"Camara Arias Juan Angel",
    "wof:placetype":"venue"
},
  "geometry": {"coordinates":[-3.7476050854,40.3688278198],"type":"Point"}
}