{
  "type": "Feature",
  "properties": {
    "addr:full":"Carrer de Mollerussa, 1 Barcelona Barcelona 08030",
    "addr:housenumber":"1",
    "addr:postcode":"08030",
    "addr:street":"Carrer De Mollerussa",
    "iso:country":"ES",
    "sg:address":"Carrer de Mollerussa, 1",
    "sg:city":"Barcelona",
    "sg:orig_category":"Centros De Educaci\u00d3n Especial",
    "sg:phone":"+34 933 45 69 47",
    "sg:postcode":"08030",
    "sg:province":"Barcelona",
    "wof:name":"Ajuntament De Barcelona",
    "wof:placetype":"venue"
},
  "geometry": {"coordinates":[2.2028312683,41.4384613037],"type":"Point"}
}