{
  "type": "Feature",
  "properties": {
    "iso:country":"ES",
    "sg:address":"Trabajadero Segunda, 12",
    "sg:city":"Sanlucar",
    "sg:orig_category":"Agencias Y Agentes Comerciales, Representantes",
    "sg:phone":"+34 956 36 10 26",
    "sg:postcode":"11540",
    "sg:province":"C\u00e1diz",
    "wof:name":"Manuel Cuevas Jurado S.l.",
    "wof:placetype":"venue"
},
  "geometry": {"coordinates":[-6.3523588181,36.7729988098],"type":"Point"}
}