{
  "type": "Feature",
  "properties": {
    "addr:full":"Rua Policarpo Sanz, 38 Vigo Pontevedra 36202",
    "addr:housenumber":"38",
    "addr:postcode":"36202",
    "addr:street":"Rua Policarpo Sanz",
    "iso:country":"ES",
    "sg:address":"Rua Policarpo Sanz, 38",
    "sg:city":"Vigo",
    "sg:orig_category":"Agentes Generales De Seguros",
    "sg:phone":"+34 986 43 35 02",
    "sg:postcode":"36202",
    "sg:province":"Pontevedra",
    "wof:name":"Rodriguez-grandjean Lopez-valcarcel Julio",
    "wof:placetype":"venue"
},
  "geometry": {"coordinates":[-8.722949028,42.2375106812],"type":"Point"}
}