{
  "type": "Feature",
  "properties": {
    "addr:full":"Calle de Cervantes, 29 Viso C\u00f3rdoba 14470",
    "addr:housenumber":"29",
    "addr:postcode":"14470",
    "addr:street":"Calle De Cervantes",
    "iso:country":"ES",
    "sg:address":"Calle de Cervantes, 29",
    "sg:city":"Viso",
    "sg:orig_category":"Ingeniero",
    "sg:phone":"+34 957 12 76 32",
    "sg:postcode":"14470",
    "sg:province":"C\u00f3rdoba",
    "wof:name":"Moreno Moreno Manuel",
    "wof:placetype":"venue"
},
  "geometry": {"coordinates":[-4.9532089233,38.4826316833],"type":"Point"}
}