{
  "type": "Feature",
  "properties": {
    "addr:full":"Avda Madrid, 19 Torrejon Ardoz Madrid 28850",
    "addr:housenumber":"19",
    "addr:postcode":"28850",
    "addr:street":"Avda Madrid",
    "iso:country":"ES",
    "sg:address":"Avda Madrid, 19",
    "sg:city":"Torrejon Ardoz",
    "sg:orig_category":"Laboratorios Y Cl\u00cdnicas Veterinarias",
    "sg:phone":"+34 916 76 47 40",
    "sg:postcode":"28850",
    "sg:province":"Madrid",
    "wof:name":"Centro Veterinario Torrejon C.b.",
    "wof:placetype":"venue"
},
  "geometry": {"coordinates":[-3.4671299458,40.4642601013],"type":"Point"}
}