{
  "type": "Feature",
  "properties": {
    "addr:full":"Calle de Lilas (las), 6 Villablino Le\u00f3n 24100",
    "addr:housenumber":"6",
    "addr:postcode":"24100",
    "addr:street":"Calle De Lilas Las",
    "iso:country":"ES",
    "sg:address":"Calle de Lilas (las), 6",
    "sg:city":"Villablino",
    "sg:orig_category":"Asesor\u00cda Sobre Comunicaci\u00d3n De Empresas",
    "sg:phone":"+34 987 47 24 18",
    "sg:postcode":"24100",
    "sg:province":"Le\u00f3n",
    "wof:name":"Suarez Pastor Jose Luis",
    "wof:placetype":"venue"
},
  "geometry": {"coordinates":[-6.3174591064,42.9381484985],"type":"Point"}
}