{
  "type": "Feature",
  "properties": {
    "iso:country":"ES",
    "sg:address":"Ctra General, Km. 0051,8",
    "sg:city":"Zalamea Real",
    "sg:orig_category":"Bares, Piano",
    "sg:phone":"+34 959 56 15 54",
    "sg:postcode":"21640",
    "sg:province":"Huelva",
    "wof:name":"Nu\u00f1ez Bola\u00f1os Vicente",
    "wof:placetype":"venue"
},
  "geometry": {"coordinates":[-6.6560411453,37.6767959595],"type":"Point"}
}