{
  "type": "Feature",
  "properties": {
    "addr:full":"Trva Juan Navarro, 8 Tarazona Zaragoza 50500",
    "addr:housenumber":"8",
    "addr:postcode":"50500",
    "addr:street":"Trva Juan Navarro",
    "iso:country":"ES",
    "sg:address":"Trva Juan Navarro, 8",
    "sg:city":"Tarazona",
    "sg:orig_category":"Molduras, Junquillos, Listones Y Molduras Perforadas",
    "sg:phone":"+34 976 64 45 01",
    "sg:postcode":"50500",
    "sg:province":"Zaragoza",
    "wof:name":"Lavena Del Valle Felix",
    "wof:placetype":"venue"
},
  "geometry": {"coordinates":[-1.7252290249,41.9046134949],"type":"Point"}
}