{
  "type": "Feature",
  "properties": {
    "iso:country":"ES",
    "sg:address":"Rua San Roque, S/n",
    "sg:city":"Vilagarcia",
    "sg:orig_category":"Ense\u00d1anza Secundaria: Colegios Y Escuelas Privadas",
    "sg:phone":"+34 986 50 10 00",
    "sg:postcode":"36600",
    "sg:province":"Pontevedra",
    "wof:name":"Xunta De Galicia",
    "wof:placetype":"venue"
},
  "geometry": {"coordinates":[-8.7629318237,42.5945777893],"type":"Point"}
}