{
  "type": "Feature",
  "properties": {
    "iso:country":"ES",
    "sg:address":"Carrer de Pintor Fortuny, 2",
    "sg:city":"Llagosta",
    "sg:orig_category":"Carnicer\u00cdas, Carnicer\u00cdas",
    "sg:phone":"+34 935 60 39 04",
    "sg:postcode":"08120",
    "sg:province":"Barcelona",
    "wof:name":"Montero Roman Marta",
    "wof:placetype":"venue"
},
  "geometry": {"coordinates":[2.1943190098,41.5111618042],"type":"Point"}
}