{
  "type": "Feature",
  "properties": {
    "addr:full":"Afueras, S/n Cala Vedella Islas Baleares 07830",
    "addr:postcode":"07830",
    "addr:street":"Afueras S / N Cala Vedella",
    "iso:country":"ES",
    "sg:address":"Afueras, S/n",
    "sg:city":"Cala Vedella",
    "sg:orig_category":"Alquiler De Veh\u00cdculos: Turismos Y Utilitarios",
    "sg:phone":"+34 971 80 80 81",
    "sg:postcode":"07830",
    "sg:province":"Islas Baleares",
    "wof:name":"Betacar Ibiza S.a.",
    "wof:placetype":"venue"
},
  "geometry": {"coordinates":[1.2473909855,38.9164390564],"type":"Point"}
}