{
  "type": "Feature",
  "properties": {
    "addr:full":"Calle de Canovas Del Castillo, 21 Santa Eulalia Murcia 30003",
    "addr:housenumber":"21",
    "addr:postcode":"30003",
    "addr:street":"Calle De Canovas Del Castillo",
    "iso:country":"ES",
    "sg:address":"Calle de Canovas Del Castillo, 21",
    "sg:city":"Santa Eulalia",
    "sg:orig_category":"Frutos Y Legumbres",
    "sg:phone":"+34 968 21 25 03",
    "sg:postcode":"30003",
    "sg:province":"Murcia",
    "wof:name":"Blanco Casales Romualdo",
    "wof:placetype":"venue"
},
  "geometry": {"coordinates":[-1.1248929501,37.9845924377],"type":"Point"}
}