{
  "type": "Feature",
  "properties": {
    "addr:full":"Calle de Almogia, 20 Malaga M\u00e1laga 29007",
    "addr:housenumber":"20",
    "addr:postcode":"29007",
    "addr:street":"Calle De Almogia;Ma\u0301Laga",
    "iso:country":"ES",
    "sg:address":"Calle de Almogia, 20",
    "sg:city":"Malaga",
    "sg:orig_category":"Tapicer\u00cdas",
    "sg:phone":"+34 952 33 13 29",
    "sg:postcode":"29007",
    "sg:province":"M\u00e1laga",
    "wof:name":"Tapiceria Hermanos Rodriguez S.l.",
    "wof:placetype":"venue"
},
  "geometry": {"coordinates":[-4.4542341232,36.7162513733],"type":"Point"}
}