{
  "type": "Feature",
  "properties": {
    "iso:country":"ES",
    "sg:address":"Calle de Garcia Prieto, 2",
    "sg:city":"Luarca",
    "sg:orig_category":"Peluqueros: De Se\u00d1oras",
    "sg:phone":"+34 985 64 05 88",
    "sg:postcode":"33700",
    "sg:province":"Asturias",
    "wof:name":"Kelpie Cb",
    "wof:placetype":"venue"
},
  "geometry": {"coordinates":[-6.5354070663,43.5420951843],"type":"Point"}
}