{
  "type": "Feature",
  "properties": {
    "addr:full":"Carr Sant Miquel, S/n Vila-sana Lleida 25245",
    "addr:housenumber":"s",
    "addr:postcode":"25245",
    "addr:street":"Carr Sant Miquel;/ N Vila-Sana",
    "iso:country":"ES",
    "sg:address":"Carr Sant Miquel, S/n",
    "sg:city":"Vila-sana",
    "sg:orig_category":"Promotores Constructores",
    "sg:phone":"+34 973 60 29 69",
    "sg:postcode":"25245",
    "sg:province":"Lleida",
    "wof:name":"Sobrevals Balcells Jaime",
    "wof:placetype":"venue"
},
  "geometry": {"coordinates":[0.9291939735,41.6635398865],"type":"Point"}
}