{
  "type": "Feature",
  "properties": {
    "iso:country":"ES",
    "sg:address":"Carrer de Comer\u00c7, 13",
    "sg:city":"Viladecans",
    "sg:orig_category":"Aparcamientos (infraestructuras, Accesorios)",
    "sg:phone":"+34 936 58 09 40",
    "sg:postcode":"08840",
    "sg:province":"Barcelona",
    "wof:name":"Clares Briculle Jesus",
    "wof:placetype":"venue"
},
  "geometry": {"coordinates":[2.0065569878,41.3112983704],"type":"Point"}
}