{
  "type": "Feature",
  "properties": {
    "addr:full":"Plaz Ejercito, 7 Avila \u00c1vila 05001",
    "addr:housenumber":"7",
    "addr:postcode":"05001",
    "addr:street":"Ejercito;A\u0301Vila",
    "iso:country":"ES",
    "sg:address":"Plaz Ejercito, 7",
    "sg:city":"Avila",
    "sg:orig_category":"Partidos Pol\u00cdticos",
    "sg:phone":"+34 920 25 27 37",
    "sg:postcode":"05001",
    "sg:province":"\u00c1vila",
    "wof:name":"Partido Popular",
    "wof:placetype":"venue"
},
  "geometry": {"coordinates":[-4.6943979263,40.6539077759],"type":"Point"}
}