{
  "type": "Feature",
  "properties": {
    "addr:full":"C/ Major, 6 Tarrega Lleida 25300",
    "addr:housenumber":"6",
    "addr:postcode":"25300",
    "addr:street":"C / Major",
    "iso:country":"ES",
    "sg:address":"C/ Major, 6",
    "sg:city":"Tarrega",
    "sg:orig_category":"Dietistas",
    "sg:phone":"+34 973 50 00 19",
    "sg:postcode":"25300",
    "sg:province":"Lleida",
    "wof:name":"Ardanuy Tarrat Concepcion",
    "wof:placetype":"venue"
},
  "geometry": {"coordinates":[1.1393339634,41.6460762024],"type":"Point"}
}