{
  "type": "Feature",
  "properties": {
    "addr:full":"Calle de Explorador Andres, 44 Valencia Valencia 46022",
    "addr:housenumber":"44",
    "addr:postcode":"46022",
    "addr:street":"Calle De Explorador Andres",
    "iso:country":"ES",
    "sg:address":"Calle de Explorador Andres, 44",
    "sg:city":"Valencia",
    "sg:orig_category":"Electricidad: Instaladores",
    "sg:phone":"+34 963 56 47 65",
    "sg:postcode":"46022",
    "sg:province":"Valencia",
    "wof:name":"Maset Gil Maria Lourdes",
    "wof:placetype":"venue"
},
  "geometry": {"coordinates":[-0.3438059986,39.4710693359],"type":"Point"}
}