{
  "type": "Feature",
  "properties": {
    "addr:full":"Areizaga Kalea, 4 Urretxu Guip\u00f9zcoa 20700",
    "addr:housenumber":"4",
    "addr:postcode":"20700",
    "addr:street":"Areizaga Kalea;Guipu\u0300Zcoa",
    "iso:country":"ES",
    "sg:address":"Areizaga Kalea, 4",
    "sg:city":"Urretxu",
    "sg:orig_category":"Caf\u00c9s, Bares, Cervecer\u00cdas",
    "sg:phone":"+34 943 72 19 66",
    "sg:postcode":"20700",
    "sg:province":"Guip\u00f9zcoa",
    "wof:name":"Soraluce Elduayen Juan Ramon",
    "wof:placetype":"venue"
},
  "geometry": {"coordinates":[-2.3139309883,43.0916862488],"type":"Point"}
}