{
  "type": "Feature",
  "properties": {
    "iso:country":"ES",
    "sg:address":"Calle de Regueira, 3",
    "sg:city":"Forcarei",
    "sg:orig_category":"C\u00c1maras De Comercio E Industria, Oficios, Agricultura",
    "sg:phone":"+34 986 75 41 21",
    "sg:postcode":"36550",
    "sg:province":"Pontevedra",
    "wof:name":"Villaverde Rivas Selvina Hortensia",
    "wof:placetype":"venue"
},
  "geometry": {"coordinates":[-8.3503198624,42.5894813538],"type":"Point"}
}