{
  "type": "Feature",
  "properties": {
    "iso:country":"ES",
    "sg:address":"Calle de Pedro Antonio De Alarcon, 19",
    "sg:city":"Granada",
    "sg:orig_category":"M\u00c9dicos: Estomatolog\u00cda",
    "sg:phone":"+34 958 53 66 26",
    "sg:postcode":"18005",
    "sg:province":"Granada",
    "wof:name":"Reyes Botella Candela",
    "wof:placetype":"venue"
},
  "geometry": {"coordinates":[-3.6049799919,37.1704063416],"type":"Point"}
}