{
  "type": "Feature",
  "properties": {
    "iso:country":"ES",
    "sg:address":"Calle de San Pedro Bautista, 29",
    "sg:city":"San Esteban Del Valle",
    "sg:orig_category":"Peluquer\u00cdas, Peluquer\u00cda Mixta",
    "sg:phone":"+34 920 38 33 98",
    "sg:postcode":"05412",
    "sg:province":"\u00c1vila",
    "wof:name":"Gonzalez Degano Pepi",
    "wof:placetype":"venue"
},
  "geometry": {"coordinates":[-4.9805288315,40.2729682922],"type":"Point"}
}