{
  "type": "Feature",
  "properties": {
    "addr:full":"C/ Fenoll, 1 Paterna Valencia 46980",
    "addr:housenumber":"1",
    "addr:postcode":"46980",
    "addr:street":"C / Fenoll",
    "iso:country":"ES",
    "sg:address":"C/ Fenoll, 1",
    "sg:city":"Paterna",
    "sg:orig_category":"Importaci\u00d3n",
    "sg:phone":"+34 961 35 71 42",
    "sg:postcode":"46980",
    "sg:province":"Valencia",
    "wof:name":"Cires S.l.",
    "wof:placetype":"venue"
},
  "geometry": {"coordinates":[-0.4313870072,39.5137672424],"type":"Point"}
}