{
  "type": "Feature",
  "properties": {
    "iso:country":"ES",
    "sg:address":"Carr Major, 51",
    "sg:city":"Jonquera",
    "sg:classifiers":[
        {
            "category":"Personal",
            "subcategory":"Barber",
            "type":"Services"
        }
    ],
    "sg:phone":"+34 972 55 46 24",
    "sg:postcode":"17700",
    "sg:province":"Girona",
    "sg:tags":[
        "caballeros",
        "de",
        "peluqueros"
    ],
    "wof:name":"Batlle Gosa Jose",
    "wof:placetype":"venue"
},
  "geometry": {"coordinates":[2.8718750477,42.4159698486],"type":"Point"}
}