{
  "type": "Feature",
  "properties": {
    "iso:country":"ES",
    "sg:address":"Calle de Comandante Seva, 24",
    "sg:city":"Sant Joan D'alacant",
    "sg:orig_category":"Contenedores (mercanc\u00cdas)",
    "sg:phone":"+34 965 65 61 96",
    "sg:postcode":"03550",
    "sg:province":"Alicante",
    "wof:name":"Lopez Martinez Antonio",
    "wof:placetype":"venue"
},
  "geometry": {"coordinates":[-0.4367497861,38.4022865295],"type":"Point"}
}