{
  "type": "Feature",
  "properties": {
    "iso:country":"ES",
    "sg:address":"Rua Canceleiro, 9",
    "sg:city":"Vigo",
    "sg:orig_category":"Agencias Y Agentes Comerciales, Representantes",
    "sg:phone":"+34 986 43 11 12",
    "sg:postcode":"36201",
    "sg:province":"Pontevedra",
    "wof:name":"Teijeiro Susavilla Domingo",
    "wof:placetype":"venue"
},
  "geometry": {"coordinates":[-8.7139701843,42.2375946045],"type":"Point"}
}