{
  "type": "Feature",
  "properties": {
    "iso:country":"ES",
    "sg:address":"Pl Sant Jordi, 1",
    "sg:city":"Manresa",
    "sg:orig_category":"Mutuas De Seguros",
    "sg:phone":"+34 938 77 64 55",
    "sg:postcode":"08241",
    "sg:province":"Barcelona",
    "wof:name":"Montepio De Conductors Sant Cristofol Manresa-berga",
    "wof:placetype":"venue"
},
  "geometry": {"coordinates":[1.830294013,41.7274627686],"type":"Point"}
}