{
  "type": "Feature",
  "properties": {
    "iso:country":"ES",
    "sg:address":"Calle de Luis Garcia, 7",
    "sg:city":"Villena",
    "sg:orig_category":"Gases Industriales",
    "sg:phone":"+34 965 80 77 36",
    "sg:postcode":"03400",
    "sg:province":"Alicante",
    "wof:name":"Garijo Esteban Salvador",
    "wof:placetype":"venue"
},
  "geometry": {"coordinates":[-0.8646630049,38.6365966797],"type":"Point"}
}