{
  "type": "Feature",
  "properties": {
    "iso:country":"ES",
    "sg:address":"Calle de Aguacate, 1",
    "sg:city":"Almu\u00f1ecar",
    "sg:orig_category":"Mec\u00c1nico Del Autom\u00d3vil",
    "sg:phone":"+34 958 63 09 79",
    "sg:postcode":"18690",
    "sg:province":"Granada",
    "wof:name":"Orce Casilla Francisco",
    "wof:placetype":"venue"
},
  "geometry": {"coordinates":[-3.6896429062,36.7382087708],"type":"Point"}
}