{
  "type": "Feature",
  "properties": {
    "iso:country":"ES",
    "sg:address":"Av. Pio Xii, 33",
    "sg:city":"Iru\u00f1a",
    "sg:orig_category":"Arquitectos",
    "sg:phone":"+34 948 25 51 12",
    "sg:postcode":"31008",
    "sg:province":"Navarra",
    "wof:name":"Ezponda Olaverri Jesus Maria",
    "wof:placetype":"venue"
},
  "geometry": {"coordinates":[-1.6587510109,42.8087158203],"type":"Point"}
}