{
  "type": "Feature",
  "properties": {
    "addr:full":"Carrer de Gremi De Sabaters, 49 Poligon Industrial De Son Castello Islas Baleares 07009",
    "addr:housenumber":"49",
    "addr:postcode":"07009",
    "addr:street":"Carrer De Gremi De Sabaters;Islas",
    "iso:country":"ES",
    "sg:address":"Carrer de Gremi De Sabaters, 49",
    "sg:city":"Poligon Industrial De Son Castello",
    "sg:orig_category":"Electricidad: Equipos Industriales, Componentes (fabricaci\u00d3n)",
    "sg:phone":"+34 971 43 12 95",
    "sg:postcode":"07009",
    "sg:province":"Islas Baleares",
    "sg:website":"www.puigcercos.com",
    "wof:name":"Electrica Puigcercos S. A.",
    "wof:placetype":"venue"
},
  "geometry": {"coordinates":[2.6741399765,39.6011390686],"type":"Point"}
}