{
  "type": "Feature",
  "properties": {
    "iso:country":"ES",
    "sg:address":"Calle de Requejo, 10",
    "sg:city":"Moralina",
    "sg:orig_category":"Fabrica De Cer\u00c1micas",
    "sg:phone":"+34 980 61 60 37",
    "sg:postcode":"49253",
    "sg:province":"Zamora",
    "wof:name":"Grupo Paco Mateos S.a.",
    "wof:placetype":"venue"
},
  "geometry": {"coordinates":[-6.1338849068,41.4897842407],"type":"Point"}
}