{
  "type": "Feature",
  "properties": {
    "addr:full":"Ctra Fuente Del Omet, 2 Fuente Omet Valencia 46229",
    "addr:housenumber":"2",
    "addr:postcode":"46229",
    "addr:street":"Ctra Fuente Del Omet",
    "iso:country":"ES",
    "sg:address":"Ctra Fuente Del Omet, 2",
    "sg:city":"Fuente Omet",
    "sg:orig_category":"Cueros Y Pieles (al Por Mayor)",
    "sg:phone":"+34 961 24 28 84",
    "sg:postcode":"46229",
    "sg:province":"Valencia",
    "wof:name":"Benjumea Ballester Maria Josefa",
    "wof:placetype":"venue"
},
  "geometry": {"coordinates":[-0.4648770094,39.3493232727],"type":"Point"}
}