{
  "type": "Feature",
  "properties": {
    "iso:country":"ES",
    "sg:address":"Calle de Jeronima Llorente, 17",
    "sg:city":"Madrid",
    "sg:orig_category":"Molduras, Junquillos, Listones Y Molduras Perforadas",
    "sg:phone":"+34 914 50 10 69",
    "sg:postcode":"28039",
    "sg:province":"Madrid",
    "wof:name":"Mu\u00f1oz Lafuente Felix",
    "wof:placetype":"venue"
},
  "geometry": {"coordinates":[-3.7056570053,40.4556427002],"type":"Point"}
}