{
  "type": "Feature",
  "properties": {
    "iso:country":"ES",
    "sg:address":"Calle de Castelar, 13",
    "sg:city":"Rota",
    "sg:orig_category":"Ropa Para Ni\u00d1os (al Por Menor)",
    "sg:phone":"+34 956 81 56 51",
    "sg:postcode":"11520",
    "sg:province":"C\u00e1diz",
    "wof:name":"Pazos Ca\u00f1as Antonio",
    "wof:placetype":"venue"
},
  "geometry": {"coordinates":[-6.3585639,36.6195259094],"type":"Point"}
}