{
  "type": "Feature",
  "properties": {
    "addr:full":"Pase Ermita Del Santo, 22 Madrid Madrid 28011",
    "addr:housenumber":"22",
    "addr:postcode":"madrid;28011",
    "iso:country":"ES",
    "sg:address":"Pase Ermita Del Santo, 22",
    "sg:city":"Madrid",
    "sg:orig_category":"Agencias Y Agentes Comerciales, Representantes",
    "sg:phone":"+34 914 79 13 55",
    "sg:postcode":"28011",
    "sg:province":"Madrid",
    "wof:name":"Martin Pinto Luis Santiago",
    "wof:placetype":"venue"
},
  "geometry": {"coordinates":[-3.724421978,40.4061203003],"type":"Point"}
}