{
  "type": "Feature",
  "properties": {
    "addr:full":"Urb Algarrobillo, S/n Valencina Concepcion Sevilla 41907",
    "addr:housenumber":"s",
    "addr:postcode":"41907",
    "addr:street":"Urb Algarrobillo;/ N Valencina",
    "iso:country":"ES",
    "sg:address":"Urb Algarrobillo, S/n",
    "sg:city":"Valencina Concepcion",
    "sg:orig_category":"Arquitectos",
    "sg:phone":"+34 955 72 17 50",
    "sg:postcode":"41907",
    "sg:province":"Sevilla",
    "wof:name":"Rodriguez De Pineda Pedro Luis",
    "wof:placetype":"venue"
},
  "geometry": {"coordinates":[-6.0776147842,37.4170455933],"type":"Point"}
}