{
  "type": "Feature",
  "properties": {
    "iso:country":"ES",
    "sg:address":"Pl Iglesia, S/n",
    "sg:city":"Rojales",
    "sg:orig_category":"Iglesia Cat\u00d3lica",
    "sg:phone":"+34 966 71 51 88",
    "sg:postcode":"03170",
    "sg:province":"Alicante",
    "wof:name":"Parroquia De San Pedro Apostol",
    "wof:placetype":"venue"
},
  "geometry": {"coordinates":[-0.7230949998,38.0889968872],"type":"Point"}
}