{
  "type": "Feature",
  "properties": {
    "addr:full":"Calle de Postas, 29 Vitoria-gasteiz \u00c1lava 01004",
    "addr:housenumber":"29",
    "addr:postcode":"01004",
    "addr:street":"Calle De Postas",
    "iso:country":"ES",
    "sg:address":"Calle de Postas, 29",
    "sg:city":"Vitoria-gasteiz",
    "sg:orig_category":"Asesor\u00cda Fiscal Y Jur\u00cddica",
    "sg:phone":"+34 945 27 84 64",
    "sg:postcode":"01004",
    "sg:province":"\u00c1lava",
    "wof:name":"Arnaiz Lopez Estibaliz",
    "wof:placetype":"venue"
},
  "geometry": {"coordinates":[-2.668633461,42.8456497192],"type":"Point"}
}