{
  "type": "Feature",
  "properties": {
    "addr:full":"Calle de Coso, 56 Siles Ja\u00e9n 23380",
    "addr:housenumber":"56",
    "addr:postcode":"23380",
    "addr:street":"Calle De Coso",
    "iso:country":"ES",
    "sg:address":"Calle de Coso, 56",
    "sg:city":"Siles",
    "sg:orig_category":"Estancos",
    "sg:phone":"+34 953 49 00 34",
    "sg:postcode":"23380",
    "sg:province":"Ja\u00e9n",
    "wof:name":"Martinez Olivares Valentin",
    "wof:placetype":"venue"
},
  "geometry": {"coordinates":[-2.5824754238,38.3880996704],"type":"Point"}
}