{
  "type": "Feature",
  "properties": {
    "iso:country":"ES",
    "sg:address":"Avda Lusitania, 7",
    "sg:city":"Merida",
    "sg:orig_category":"Agencias Y Agentes Comerciales, Representantes",
    "sg:phone":"+34 924 31 43 09",
    "sg:postcode":"06800",
    "sg:province":"Badajoz",
    "wof:name":"Olivera Bravo Angel",
    "wof:placetype":"venue"
},
  "geometry": {"coordinates":[-6.3331990242,38.9122886658],"type":"Point"}
}