{
  "type": "Feature",
  "properties": {
    "iso:country":"ES",
    "sg:address":"Gta Cuatro Caminos, 6",
    "sg:city":"Madrid",
    "sg:orig_category":"Promotores Constructores",
    "sg:phone":"+34 915 14 03 00",
    "sg:postcode":"28...",
    "sg:province":"Madrid",
    "wof:name":"Promociones Y Construcciones S.a.",
    "wof:placetype":"venue"
},
  "geometry": {"coordinates":[-3.7042849064,40.447013855],"type":"Point"}
}