{
  "type": "Feature",
  "properties": {
    "iso:country":"ES",
    "sg:address":"Avda Cruz Roja (la), S/n",
    "sg:city":"Jerez De La Frontera",
    "sg:orig_category":"\u00d3ptica: Instrumentos (fabricaci\u00d3n)",
    "sg:phone":"+34 956 30 04 52",
    "sg:postcode":"11407",
    "sg:province":"C\u00e1diz",
    "wof:name":"Blazquez Gil Rosario",
    "wof:placetype":"venue"
},
  "geometry": {"coordinates":[-6.13478899,36.6972160339],"type":"Point"}
}