{
  "type": "Feature",
  "properties": {
    "iso:country":"ES",
    "sg:address":"Carrer de Forn Del Vidre, 2",
    "sg:city":"Molins Rei",
    "sg:orig_category":"Promotores Constructores",
    "sg:phone":"+34 936 68 53 81",
    "sg:postcode":"08750",
    "sg:province":"Barcelona",
    "wof:name":"Cp Forn Del Vidre;2",
    "wof:placetype":"venue"
},
  "geometry": {"coordinates":[2.0164849758,41.414604187],"type":"Point"}
}