{
  "type": "Feature",
  "properties": {
    "addr:full":"Carretera De Sevilla, Km. 0121,6 Ronda M\u00e1laga 29400",
    "addr:postcode":"29400",
    "addr:street":"Carretera De Sevilla Km. 0121,6 Ronda Ma\u0301Laga",
    "iso:country":"ES",
    "sg:address":"Carretera De Sevilla, Km. 0121,6",
    "sg:city":"Ronda",
    "sg:orig_category":"Aceites Y Grasas Alimentarias (fabricaci\u00d3n, Al Por Mayor)",
    "sg:phone":"+34 952 87 30 35",
    "sg:postcode":"29400",
    "sg:province":"M\u00e1laga",
    "wof:name":"Sociedad Cooperativa Andaluza Agricola Almazara Ronda",
    "wof:placetype":"venue"
},
  "geometry": {"coordinates":[-5.1662788391,36.7417945862],"type":"Point"}
}