{
  "type": "Feature",
  "properties": {
    "iso:country":"ES",
    "sg:address":"Poli Poligono Industrial Fuente Santa, 47",
    "sg:city":"Loja",
    "sg:orig_category":"Veh\u00cdculos De Ocasi\u00d3n",
    "sg:phone":"+34 958 32 22 46",
    "sg:postcode":"18300",
    "sg:province":"Granada",
    "wof:name":"Olid Jimenez Manuel",
    "wof:placetype":"venue"
},
  "geometry": {"coordinates":[-4.1505270004,37.1690177917],"type":"Point"}
}