{
  "type": "Feature",
  "properties": {
    "addr:full":"Calle de Etxezuri, 4 Algorta Vizcaya 48992",
    "addr:housenumber":"4",
    "addr:postcode":"48992",
    "addr:street":"Calle De Etxezuri",
    "iso:country":"ES",
    "sg:address":"Calle de Etxezuri, 4",
    "sg:city":"Algorta",
    "sg:orig_category":"Doctores En Medicina",
    "sg:phone":"+34 944 60 59 97",
    "sg:postcode":"48992",
    "sg:province":"Vizcaya",
    "wof:name":"Gil Lang Guillermo",
    "wof:placetype":"venue"
},
  "geometry": {"coordinates":[-3.002661705,43.3338661194],"type":"Point"}
}