{
  "type": "Feature",
  "properties": {
    "iso:country":"ES",
    "sg:address":"Calle de Don Vicente Gallart 'arcipreste', 24",
    "sg:city":"Valencia",
    "sg:orig_category":"Producci\u00d3n De Champi\u00d1ones",
    "sg:phone":"+34 963 24 09 46",
    "sg:postcode":"46011",
    "sg:province":"Valencia",
    "wof:name":"Nando Silvestre S.l.",
    "wof:placetype":"venue"
},
  "geometry": {"coordinates":[-0.330134213,39.473033905],"type":"Point"}
}