{
  "type": "Feature",
  "properties": {
    "iso:country":"ES",
    "sg:address":"Calle de Periodista Gago Jimenez, 1",
    "sg:city":"Cordoba",
    "sg:orig_category":"Centros De Educaci\u00d3n Especial",
    "sg:phone":"+34 957 25 70 93",
    "sg:postcode":"14010",
    "sg:province":"C\u00f3rdoba",
    "wof:name":"Junta De Andalucia-colegio Nacional Algafequi",
    "wof:placetype":"venue"
},
  "geometry": {"coordinates":[-4.760035038,37.8865966797],"type":"Point"}
}