{
  "type": "Feature",
  "properties": {
    "iso:country":"ES",
    "sg:address":"Rua San Roque, 23",
    "sg:city":"Xinzo De Limia",
    "sg:orig_category":"Relojer\u00cda (al Por Menor, Reparaci\u00d3n)",
    "sg:phone":"+34 988 46 06 56",
    "sg:postcode":"32630",
    "sg:province":"Ourense",
    "wof:name":"Diaz Manjon Juan",
    "wof:placetype":"venue"
},
  "geometry": {"coordinates":[-7.7268419266,42.0618972778],"type":"Point"}
}