{
  "type": "Feature",
  "properties": {
    "addr:full":"Rua Norias (das), 17 Lugo Lugo 27001",
    "addr:housenumber":"17",
    "addr:postcode":"27001",
    "addr:street":"Rua Norias Das",
    "iso:country":"ES",
    "sg:address":"Rua Norias (das), 17",
    "sg:city":"Lugo",
    "sg:orig_category":"Bancos",
    "sg:phone":"+34 982 22 62 12",
    "sg:postcode":"27001",
    "sg:province":"Lugo",
    "sg:website":"www.bancopopular.es",
    "wof:name":"Banco Popular Espa\u00f1ol",
    "wof:placetype":"venue"
},
  "geometry": {"coordinates":[-7.5536627769,43.0111045837],"type":"Point"}
}