{
  "type": "Feature",
  "properties": {
    "iso:country":"ES",
    "sg:address":"Plaz San Pablo, 4",
    "sg:city":"Valladolid",
    "sg:orig_category":"Internados & Ense\u00d1anza Privada",
    "sg:phone":"+34 983 35 66 99",
    "sg:postcode":"47011",
    "sg:province":"Valladolid",
    "wof:name":"Padres Dominicos San Gregorio",
    "wof:placetype":"venue"
},
  "geometry": {"coordinates":[-4.7250318527,41.6571617126],"type":"Point"}
}