{
  "type": "Feature",
  "properties": {
    "addr:full":"Pl Catalunya, 4 Barcelona Barcelona 08002",
    "addr:housenumber":"4",
    "addr:postcode":"08002",
    "addr:street":"Pl Catalunya",
    "iso:country":"ES",
    "sg:address":"Pl Catalunya, 4",
    "sg:city":"Barcelona",
    "sg:orig_category":"Agencias De Viajes",
    "sg:phone":"+34 933 01 99 02",
    "sg:postcode":"08002",
    "sg:province":"Barcelona",
    "sg:website":"www.viajar.com",
    "wof:name":"Yacom Travel S.l.",
    "wof:placetype":"venue"
},
  "geometry": {"coordinates":[2.1695275307,41.3864364624],"type":"Point"}
}