{
  "type": "Feature",
  "properties": {
    "iso:country":"ES",
    "sg:address":"Calle de Emilio Ferrari, 33",
    "sg:city":"Madrid",
    "sg:orig_category":"Empresas De Carpinter\u00cda",
    "sg:phone":"+34 914 07 98 04",
    "sg:postcode":"28017",
    "sg:province":"Madrid",
    "wof:name":"Industrias Marquino S.l.",
    "wof:placetype":"venue"
},
  "geometry": {"coordinates":[-3.6423459053,40.4330101013],"type":"Point"}
}