{
  "type": "Feature",
  "properties": {
    "addr:full":"Avda Maria Auxiliadora, 4 Badajoz Badajoz 06011",
    "addr:housenumber":"4",
    "addr:postcode":"06011",
    "addr:street":"Avda Maria Auxiliadora",
    "iso:country":"ES",
    "sg:address":"Avda Maria Auxiliadora, 4",
    "sg:city":"Badajoz",
    "sg:orig_category":"Iglesia Cat\u00d3lica",
    "sg:phone":"+34 924 20 76 84",
    "sg:postcode":"06011",
    "sg:province":"Badajoz",
    "wof:name":"Parroquia Maria Auxiliadora",
    "wof:placetype":"venue"
},
  "geometry": {"coordinates":[-6.9795298576,38.8688545227],"type":"Point"}
}