{
  "type": "Feature",
  "properties": {
    "iso:country":"ES",
    "sg:address":"Tafalla, 16",
    "sg:city":"Iru\u00f1a",
    "sg:orig_category":"Molduras, Junquillos, Listones Y Molduras Perforadas",
    "sg:phone":"+34 948 24 50 01",
    "sg:postcode":"31004",
    "sg:province":"Navarra",
    "wof:name":"Villanueva Aspilche Jose Javier",
    "wof:placetype":"venue"
},
  "geometry": {"coordinates":[-1.6375169754,42.81224823],"type":"Point"}
}