{
  "type": "Feature",
  "properties": {
    "addr:full":"Calle de Leopoldo Alas Clarin, 15 Mieres Asturias 33600",
    "addr:housenumber":"15",
    "addr:postcode":"33600",
    "addr:street":"Calle De Leopoldo Alas Clarin",
    "iso:country":"ES",
    "sg:address":"Calle de Leopoldo Alas Clarin, 15",
    "sg:city":"Mieres",
    "sg:orig_category":"M\u00c9dicos: Estomatolog\u00cda",
    "sg:phone":"+34 985 46 85 46",
    "sg:postcode":"33600",
    "sg:province":"Asturias",
    "wof:name":"San Narciso Aguinaco Jaime",
    "wof:placetype":"venue"
},
  "geometry": {"coordinates":[-5.7731342316,43.2491874695],"type":"Point"}
}