{
  "type": "Feature",
  "properties": {
    "iso:country":"ES",
    "sg:address":"Carrer de Ricart, 42",
    "sg:city":"S. Adria Besos",
    "sg:orig_category":"Institutos De Belleza",
    "sg:phone":"+34 934 62 60 73",
    "sg:postcode":"08930",
    "sg:province":"Barcelona",
    "wof:name":"Ramos Mendez Laura",
    "wof:placetype":"venue"
},
  "geometry": {"coordinates":[2.2193109989,41.4293785095],"type":"Point"}
}