{
  "type": "Feature",
  "properties": {
    "iso:country":"ES",
    "sg:address":"Calle de Alvaro Martin Diaz, 22",
    "sg:city":"Cuesta",
    "sg:orig_category":"Centros M\u00c9dicos Y Sociales, Dispensarios",
    "sg:phone":"+34 922 66 07 78",
    "sg:postcode":"38320",
    "sg:province":"Santa Cruz De Tenerife",
    "wof:name":"Salud Care Canarias S.l.",
    "wof:placetype":"venue"
},
  "geometry": {"coordinates":[-16.2936210632,28.4688110352],"type":"Point"}
}