{
  "type": "Feature",
  "properties": {
    "iso:country":"ES",
    "sg:address":"Santiago Ramon Y Cajal, 51",
    "sg:city":"Zaragoza",
    "sg:orig_category":"Inmobiliaria (agencias)",
    "sg:phone":"+34 976 43 54 00",
    "sg:postcode":"50004",
    "sg:province":"Zaragoza",
    "wof:name":"Hogares Nuevos Zaragoza S.l.",
    "wof:placetype":"venue"
},
  "geometry": {"coordinates":[-0.8861579895,41.6512680054],"type":"Point"}
}