{
  "type": "Feature",
  "properties": {
    "addr:full":"Z. Ppe. De Gales, S/n Isla Mayor Sevilla 41140",
    "addr:housenumber":"s / n",
    "addr:postcode":"41140",
    "iso:country":"ES",
    "sg:address":"Z. Ppe. De Gales, S/n",
    "sg:city":"Isla Mayor",
    "sg:orig_category":"Crust\u00c1ceos Y Almejas (al Por Mayor)",
    "sg:phone":"+34 955 77 31 32",
    "sg:postcode":"41140",
    "sg:province":"Sevilla",
    "wof:name":"Alfocan S.a.",
    "wof:placetype":"venue"
},
  "geometry": {"coordinates":[-6.1739115715,37.0725708008],"type":"Point"}
}