{
  "type": "Feature",
  "properties": {
    "addr:full":"Av Josep Fontcuberta, 117 Caldes Montbui Barcelona 08140",
    "addr:housenumber":"117",
    "addr:postcode":"08140",
    "addr:street":"Av Josep Fontcuberta;Montbui Barcelona",
    "iso:country":"ES",
    "sg:address":"Av Josep Fontcuberta, 117",
    "sg:city":"Caldes Montbui",
    "sg:orig_category":"Centros De Coordinaci\u00d3n",
    "sg:phone":"+34 938 62 69 25",
    "sg:postcode":"08140",
    "sg:province":"Barcelona",
    "wof:name":"Hablemos S.l.",
    "wof:placetype":"venue"
},
  "geometry": {"coordinates":[2.1705598831,41.6338806152],"type":"Point"}
}