{
  "type": "Feature",
  "properties": {
    "iso:country":"ES",
    "sg:address":"Pl. Major, 43",
    "sg:city":"Castelldefels",
    "sg:orig_category":"Electrodom\u00c9sticos (al Por Menor)",
    "sg:phone":"+34 936 65 61 51",
    "sg:postcode":"08860",
    "sg:province":"Barcelona",
    "wof:name":"Mahia Gomez Antonio Jesus",
    "wof:placetype":"venue"
},
  "geometry": {"coordinates":[1.9278570414,41.2629699707],"type":"Point"}
}