{
  "type": "Feature",
  "properties": {
    "addr:full":"Barr Isuskiza, 241 Isuskiza Vizcaya 48620",
    "addr:housenumber":"241",
    "addr:postcode":"48620",
    "addr:street":"Isuskiza Vizcaya",
    "iso:country":"ES",
    "sg:address":"Barr Isuskiza, 241",
    "sg:city":"Isuskiza",
    "sg:orig_category":"Empresas De Limpieza",
    "sg:phone":"+34 946 77 32 31",
    "sg:postcode":"48620",
    "sg:province":"Vizcaya",
    "wof:name":"Clean Internacional S. A.",
    "wof:placetype":"venue"
},
  "geometry": {"coordinates":[-2.9458739758,43.4066467285],"type":"Point"}
}