{
  "type": "Feature",
  "properties": {
    "addr:full":"Av Diagonal, 366 Barcelona Barcelona 08013",
    "addr:housenumber":"366",
    "addr:postcode":"08013",
    "addr:street":"Av Diagonal",
    "iso:country":"ES",
    "sg:address":"Av Diagonal, 366",
    "sg:city":"Barcelona",
    "sg:orig_category":"Carnicer\u00cdas, Carnicer\u00cdas",
    "sg:phone":"+34 934 58 05 76",
    "sg:postcode":"08013",
    "sg:province":"Barcelona",
    "wof:name":"Gracia Monzon Joaquin",
    "wof:placetype":"venue"
},
  "geometry": {"coordinates":[2.1713323593,41.3996887207],"type":"Point"}
}