{
  "type": "Feature",
  "properties": {
    "addr:full":"Calle de Cartagena, 69 Madrid Madrid 28028",
    "addr:housenumber":"69",
    "addr:postcode":"madrid;28028",
    "addr:street":"Calle De Cartagena",
    "iso:country":"ES",
    "sg:address":"Calle de Cartagena, 69",
    "sg:city":"Madrid",
    "sg:orig_category":"Ropa Para Caballeros (al Por Menor)",
    "sg:phone":"+34 913 56 79 46",
    "sg:postcode":"28028",
    "sg:province":"Madrid",
    "wof:name":"Sanz Martin Maria Teresa",
    "wof:placetype":"venue"
},
  "geometry": {"coordinates":[-3.6708331108,40.4368896484],"type":"Point"}
}