{
  "type": "Feature",
  "properties": {
    "iso:country":"ES",
    "sg:address":"Calle de Amatista, 6",
    "sg:city":"Urbanizacion Mediterraneo",
    "sg:orig_category":"Panader\u00cdas, Panader\u00cdas",
    "sg:phone":"+34 968 51 42 81",
    "sg:postcode":"30310",
    "sg:province":"Murcia",
    "wof:name":"Lopez Perez Francisco",
    "wof:placetype":"venue"
},
  "geometry": {"coordinates":[-1.1298867464,37.9834747314],"type":"Point"}
}