{
  "type": "Feature",
  "properties": {
    "addr:full":"Calle de Julian Calvo, 2 San Pedro Murcia 30004",
    "addr:housenumber":"2",
    "addr:postcode":"30004",
    "addr:street":"Calle De Julian Calvo",
    "iso:country":"ES",
    "sg:address":"Calle de Julian Calvo, 2",
    "sg:city":"San Pedro",
    "sg:orig_category":"Animales (al Por Menor)",
    "sg:phone":"+34 968 21 33 09",
    "sg:postcode":"30004",
    "sg:province":"Murcia",
    "wof:name":"Molina Navarro Antonio",
    "wof:placetype":"venue"
},
  "geometry": {"coordinates":[-1.1356413364,37.9848594666],"type":"Point"}
}