{
  "type": "Feature",
  "properties": {
    "addr:full":"Calle de Ciempozuelos, 27 Getafe Madrid 28904",
    "addr:housenumber":"27",
    "addr:postcode":"28904",
    "addr:street":"Calle De Ciempozuelos",
    "iso:country":"ES",
    "sg:address":"Calle de Ciempozuelos, 27",
    "sg:city":"Getafe",
    "sg:orig_category":"Imprenta",
    "sg:phone":"+34 916 95 53 67",
    "sg:postcode":"28904",
    "sg:province":"Madrid",
    "wof:name":"Lozano Arroyo Agustin",
    "wof:placetype":"venue"
},
  "geometry": {"coordinates":[-3.7348964214,40.3024139404],"type":"Point"}
}