{
  "type": "Feature",
  "properties": {
    "iso:country":"ES",
    "sg:address":"Calle de Veril, 10",
    "sg:city":"Pto. Rosario",
    "sg:classifiers":[
        {
            "category":"Banks & Credit Unions",
            "subcategory":"Bureau De Change",
            "type":"Services"
        }
    ],
    "sg:phone":"+34 928 85 83 83",
    "sg:postcode":"35600",
    "sg:province":"Las Palmas",
    "sg:tags":[
        "organismos",
        "control"
    ],
    "sg:website":"www.icinco.com",
    "wof:name":"Instituto Canario De Investigaciones En La Construccion S.a.",
    "wof:placetype":"venue"
},
  "geometry": {"coordinates":[-13.8644685745,28.5023498535],"type":"Point"}
}