{
  "type": "Feature",
  "properties": {
    "addr:full":"Calle de Andalucia, 30 Moguer Huelva 21800",
    "addr:housenumber":"30",
    "addr:postcode":"21800",
    "addr:street":"Calle De Andalucia",
    "iso:country":"ES",
    "sg:address":"Calle de Andalucia, 30",
    "sg:city":"Moguer",
    "sg:orig_category":"Art\u00cdculos Funerarios (al Por Menor)",
    "sg:phone":"+34 959 37 20 73",
    "sg:postcode":"21800",
    "sg:province":"Huelva",
    "wof:name":"Funeraria La Paz S.l.",
    "wof:placetype":"venue"
},
  "geometry": {"coordinates":[-6.8395504951,37.2749061584],"type":"Point"}
}