{
  "type": "Feature",
  "properties": {
    "iso:country":"ES",
    "sg:address":"Calle de Villalmanzo, 16",
    "sg:city":"Madrid",
    "sg:orig_category":"Aparcamientos (infraestructuras, Accesorios)",
    "sg:phone":"+34 917 76 43 90",
    "sg:postcode":"28032",
    "sg:province":"Madrid",
    "wof:name":"Garaje Villalmanzo S.l.",
    "wof:placetype":"venue"
},
  "geometry": {"coordinates":[-3.6074140072,40.4044647217],"type":"Point"}
}