{
  "type": "Feature",
  "properties": {
    "addr:full":"Calle de Valdebernardo, 33 Madrid Madrid 28030",
    "addr:housenumber":"33",
    "addr:postcode":"madrid;28030",
    "addr:street":"Calle De Valdebernardo",
    "iso:country":"ES",
    "sg:address":"Calle de Valdebernardo, 33",
    "sg:city":"Madrid",
    "sg:orig_category":"Molduras, Junquillos, Listones Y Molduras Perforadas",
    "sg:phone":"+34 917 72 24 72",
    "sg:postcode":"28030",
    "sg:province":"Madrid",
    "wof:name":"Nalbandyan  Laura",
    "wof:placetype":"venue"
},
  "geometry": {"coordinates":[-3.6327478886,40.4024391174],"type":"Point"}
}