{
  "type": "Feature",
  "properties": {
    "iso:country":"ES",
    "sg:address":"Calle de Rafael Lucenqui, 15",
    "sg:city":"Badajoz",
    "sg:orig_category":"Papeler\u00cdas: Art\u00cdculos (al Por Mayor)",
    "sg:phone":"+34 924 23 55 75",
    "sg:postcode":"06004",
    "sg:province":"Badajoz",
    "wof:name":"Martinez Moreno Manuel",
    "wof:placetype":"venue"
},
  "geometry": {"coordinates":[-6.9751667976,38.870098114],"type":"Point"}
}