{
  "type": "Feature",
  "properties": {
    "addr:full":"Calle de Orense, 11 Madrid Madrid 28020",
    "addr:housenumber":"11",
    "addr:postcode":"madrid;28020",
    "addr:street":"Calle De Orense",
    "iso:country":"ES",
    "sg:address":"Calle de Orense, 11",
    "sg:city":"Madrid",
    "sg:orig_category":"Agencias De Viajes",
    "sg:phone":"+34 902 25 00 24",
    "sg:postcode":"28020",
    "sg:province":"Madrid",
    "sg:website":"www.hotel-pass.com",
    "wof:name":"Faster Iberica S.a.",
    "wof:placetype":"venue"
},
  "geometry": {"coordinates":[-3.6955590248,40.4483299255],"type":"Point"}
}