{
  "type": "Feature",
  "properties": {
    "addr:full":"Calle de Sol, 34 Plasencia C\u00e1ceres 10600",
    "addr:housenumber":"34",
    "addr:postcode":"10600",
    "addr:street":"Calle De Sol;Ca\u0301Ceres",
    "iso:country":"ES",
    "sg:address":"Calle de Sol, 34",
    "sg:city":"Plasencia",
    "sg:orig_category":"Bisuter\u00cda, Joyer\u00cda, Relojer\u00cda (al Por Menor)",
    "sg:phone":"+34 927 41 24 09",
    "sg:postcode":"10600",
    "sg:province":"C\u00e1ceres",
    "wof:name":"Garcia Lopez Francisco Jesus",
    "wof:placetype":"venue"
},
  "geometry": {"coordinates":[-6.0864601135,40.030708313],"type":"Point"}
}