{
  "type": "Feature",
  "properties": {
    "addr:full":"Ctra Madrid Coru\u00d1a, S/n Villalpando Zamora 49630",
    "addr:housenumber":"s",
    "addr:postcode":"49630",
    "addr:street":"Ctra Madrid Corun\u0303A;/ N",
    "iso:country":"ES",
    "sg:address":"Ctra Madrid Coru\u00d1a, S/n",
    "sg:city":"Villalpando",
    "sg:orig_category":"Empresas De Carpinter\u00cda Met\u00c1lica",
    "sg:phone":"+34 980 66 04 74",
    "sg:postcode":"49630",
    "sg:province":"Zamora",
    "wof:name":"Nu\u00f1ez Zamora Javier",
    "wof:placetype":"venue"
},
  "geometry": {"coordinates":[-5.4135689735,41.8648910522],"type":"Point"}
}