{
  "type": "Feature",
  "properties": {
    "iso:country":"ES",
    "sg:address":"Calle de Santa Eufemia, S/n",
    "sg:city":"Santacara",
    "sg:orig_category":"Pescader\u00cdas (al Por Menor)",
    "sg:phone":"+34 948 74 60 32",
    "sg:postcode":"31314",
    "sg:province":"Navarra",
    "wof:name":"Blazquiz Garde Elias",
    "wof:placetype":"venue"
},
  "geometry": {"coordinates":[-1.5500789881,42.3745498657],"type":"Point"}
}