{
  "type": "Feature",
  "properties": {
    "iso:country":"ES",
    "sg:address":"Calle de Algemesi, 32",
    "sg:city":"Madrid",
    "sg:orig_category":"Peluquer\u00cdas, Peluquer\u00cda Mixta",
    "sg:phone":"+34 917 47 42 14",
    "sg:postcode":"28042",
    "sg:province":"Madrid",
    "wof:name":"Barea Raimundez Juana",
    "wof:placetype":"venue"
},
  "geometry": {"coordinates":[-3.5839285851,40.4721298218],"type":"Point"}
}