{
  "type": "Feature",
  "properties": {
    "addr:full":"Cmno San Vicente, S/n Lastrilla Segovia 40196",
    "addr:housenumber":"s / n",
    "addr:postcode":"40196",
    "addr:street":"Cmno San Vicente",
    "iso:country":"ES",
    "sg:address":"Cmno San Vicente, S/n",
    "sg:city":"Lastrilla",
    "sg:orig_category":"Restaurantes",
    "sg:phone":"+34 921 44 49 08",
    "sg:postcode":"40196",
    "sg:province":"Segovia",
    "wof:name":"M. Aragoneses M. S.l.",
    "wof:placetype":"venue"
},
  "geometry": {"coordinates":[-4.1075425148,40.9651107788],"type":"Point"}
}