{
  "type": "Feature",
  "properties": {
    "iso:country":"ES",
    "sg:address":"Avda Doctor Meca, 92",
    "sg:city":"Puerto Mazarron",
    "sg:orig_category":"Mec\u00c1nico Del Autom\u00d3vil",
    "sg:phone":"+34 968 59 43 08",
    "sg:postcode":"30860",
    "sg:province":"Murcia",
    "wof:name":"Picon Vivancos Andres",
    "wof:placetype":"venue"
},
  "geometry": {"coordinates":[-1.2632210255,37.5693855286],"type":"Point"}
}