{
  "type": "Feature",
  "properties": {
    "addr:full":"Ptge Maluquer, 5 Barcelona Barcelona 08022",
    "addr:housenumber":"5",
    "addr:postcode":"08022",
    "addr:street":"Ptge Maluquer",
    "iso:country":"ES",
    "sg:address":"Ptge Maluquer, 5",
    "sg:city":"Barcelona",
    "sg:orig_category":"Asesor\u00cda Fiscal Y Jur\u00cddica",
    "sg:phone":"+34 932 11 71 48",
    "sg:postcode":"08022",
    "sg:province":"Barcelona",
    "wof:name":"Perez-cela Gomez Juan Jacobo",
    "wof:placetype":"venue"
},
  "geometry": {"coordinates":[2.1367719173,41.4085731506],"type":"Point"}
}