{
  "type": "Feature",
  "properties": {
    "iso:country":"ES",
    "sg:address":"Carrer de Eladi Homs, 5",
    "sg:city":"Cambrils Badia",
    "sg:orig_category":"Empresas De Limpieza",
    "sg:phone":"+34 977 36 28 43",
    "sg:postcode":"43850",
    "sg:province":"Tarragona",
    "wof:name":"Vicente Abad Felipa",
    "wof:placetype":"venue"
},
  "geometry": {"coordinates":[1.0706119537,41.071685791],"type":"Point"}
}