{
  "type": "Feature",
  "properties": {
    "iso:country":"ES",
    "sg:address":"Carr Primavera, 31",
    "sg:city":"Badalona",
    "sg:orig_category":"Ebanister\u00cda",
    "sg:phone":"+34 933 88 74 09",
    "sg:postcode":"08918",
    "sg:province":"Barcelona",
    "wof:name":"Lomas S. Cv.",
    "wof:placetype":"venue"
},
  "geometry": {"coordinates":[2.2252810001,41.4310264587],"type":"Point"}
}