{
  "type": "Feature",
  "properties": {
    "addr:full":"Calle de Lope De Haro, 22 Madrid Madrid 28039",
    "addr:housenumber":"22",
    "addr:postcode":"madrid;28039",
    "addr:street":"Calle De Lope De Haro",
    "iso:country":"ES",
    "sg:address":"Calle de Lope De Haro, 22",
    "sg:city":"Madrid",
    "sg:classifiers":[
        {
            "category":"Personal",
            "subcategory":"Barber",
            "type":"Services"
        }
    ],
    "sg:phone":"+34 915 70 23 87",
    "sg:postcode":"28039",
    "sg:province":"Madrid",
    "sg:tags":[
        "caballeros",
        "de",
        "peluqueros"
    ],
    "wof:name":"Gonzalez Redondo Carlos",
    "wof:placetype":"venue"
},
  "geometry": {"coordinates":[-3.7036819458,40.45703125],"type":"Point"}
}