{
  "type": "Feature",
  "properties": {
    "addr:full":"Calle de Santa Maria, 1 Tordesillas Valladolid 47100",
    "addr:housenumber":"1",
    "addr:postcode":"47100",
    "addr:street":"Calle De Santa Maria",
    "iso:country":"ES",
    "sg:address":"Calle de Santa Maria, 1",
    "sg:city":"Tordesillas",
    "sg:orig_category":"Farmacias",
    "sg:phone":"+34 983 77 05 81",
    "sg:postcode":"47100",
    "sg:province":"Valladolid",
    "wof:name":"Peral Puparelli Manuel",
    "wof:placetype":"venue"
},
  "geometry": {"coordinates":[-5.0373511314,41.5326919556],"type":"Point"}
}