{
  "type": "Feature",
  "properties": {
    "iso:country":"ES",
    "sg:address":"Calle de Orense, 18",
    "sg:city":"Madrid",
    "sg:orig_category":"Cajas De Ahorro",
    "sg:phone":"+34 915 55 22 54",
    "sg:postcode":"28020",
    "sg:province":"Madrid",
    "sg:website":"www.cajaespana.es",
    "wof:name":"Caja Espa\u00f1a De Inversiones Caja De Ahorros Y Monte De Piedad",
    "wof:placetype":"venue"
},
  "geometry": {"coordinates":[-3.6950469017,40.4500007629],"type":"Point"}
}