{
  "type": "Feature",
  "properties": {
    "addr:full":"Calle de Maestro Falla, 25 Castellon Castell\u00f3n 12005",
    "addr:housenumber":"25",
    "addr:postcode":"12005",
    "addr:street":"Calle De Maestro Falla",
    "iso:country":"ES",
    "sg:address":"Calle de Maestro Falla, 25",
    "sg:city":"Castellon",
    "sg:orig_category":"Peluqueros: De Se\u00d1oras",
    "sg:phone":"+34 964 23 80 14",
    "sg:postcode":"12005",
    "sg:province":"Castell\u00f3n",
    "wof:name":"Ruiz Garcia Beatriz",
    "wof:placetype":"venue"
},
  "geometry": {"coordinates":[-0.0342859998,39.9805755615],"type":"Point"}
}