{
  "type": "Feature",
  "properties": {
    "iso:country":"ES",
    "sg:address":"Carrer de L'espaseria, 14",
    "sg:city":"Barcelona",
    "sg:orig_category":"Bisuter\u00cda, Joyer\u00cda, Relojer\u00cda (al Por Menor)",
    "sg:phone":"+34 932 68 47 86",
    "sg:postcode":"08003",
    "sg:province":"Barcelona",
    "wof:name":"Argudo Lloret Margarita",
    "wof:placetype":"venue"
},
  "geometry": {"coordinates":[2.1824216843,41.3832550049],"type":"Point"}
}