{
  "type": "Feature",
  "properties": {
    "addr:full":"Carrer de Girona, 311 Granollers Barcelona 08402",
    "addr:housenumber":"311",
    "addr:postcode":"08402",
    "addr:street":"Carrer De Girona",
    "iso:country":"ES",
    "sg:address":"Carrer de Girona, 311",
    "sg:city":"Granollers",
    "sg:orig_category":"Farmacias",
    "sg:phone":"+34 938 49 17 16",
    "sg:postcode":"08402",
    "sg:province":"Barcelona",
    "wof:name":"Pardo Rodriguez Maria Pilar",
    "wof:placetype":"venue"
},
  "geometry": {"coordinates":[2.2936789989,41.6196632385],"type":"Point"}
}