{
  "type": "Feature",
  "properties": {
    "addr:full":"Carr Eiximenis, 7 Girona Girona 17001",
    "addr:housenumber":"7",
    "addr:postcode":"17001",
    "addr:street":"Carr Eiximenis",
    "iso:country":"ES",
    "sg:address":"Carr Eiximenis, 7",
    "sg:city":"Girona",
    "sg:orig_category":"Centros De Educaci\u00d3n Especial",
    "sg:phone":"+34 972 20 29 74",
    "sg:postcode":"17001",
    "sg:province":"Girona",
    "wof:name":"Ceip Eiximenis",
    "wof:placetype":"venue"
},
  "geometry": {"coordinates":[2.8216600418,41.9839782715],"type":"Point"}
}