{
  "type": "Feature",
  "properties": {
    "iso:country":"ES",
    "sg:address":"Calle de Alhondiga, 39",
    "sg:city":"Granada",
    "sg:orig_category":"Bisuter\u00cda, Joyer\u00cda, Relojer\u00cda (al Por Menor)",
    "sg:phone":"+34 958 53 60 18",
    "sg:postcode":"18001",
    "sg:province":"Granada",
    "wof:name":"Bisbe Barcelo Angela",
    "wof:placetype":"venue"
},
  "geometry": {"coordinates":[-3.6018149853,37.1756324768],"type":"Point"}
}