{
  "type": "Feature",
  "properties": {
    "iso:country":"ES",
    "sg:address":"Calle de Colegio Catalino, 8",
    "sg:city":"Granada",
    "sg:orig_category":"Mercer\u00cda, Lencer\u00cda (al Por Menor)",
    "sg:phone":"+34 958 26 60 03",
    "sg:postcode":"18001",
    "sg:province":"Granada",
    "wof:name":"Roca Lopez Angelica",
    "wof:placetype":"venue"
},
  "geometry": {"coordinates":[-3.5999138355,37.1757087708],"type":"Point"}
}