{
  "type": "Feature",
  "properties": {
    "iso:country":"ES",
    "sg:address":"Makatzena Kalea, 17",
    "sg:city":"Arrasate",
    "sg:orig_category":"Empresas De Pintura Y Revestimientos",
    "sg:phone":"+34 943 79 99 43",
    "sg:postcode":"20500",
    "sg:province":"Guip\u00f9zcoa",
    "wof:name":"Tena Ignacio Bernardo",
    "wof:placetype":"venue"
},
  "geometry": {"coordinates":[-2.4844090939,43.0691299438],"type":"Point"}
}