{
  "type": "Feature",
  "properties": {
    "iso:country":"ES",
    "sg:address":"Calle de Fontecha, 3",
    "sg:city":"Daimiel",
    "sg:orig_category":"Confecci\u00d3n (fabricaci\u00d3n, Al Por Mayor)",
    "sg:phone":"+34 926 85 01 71",
    "sg:postcode":"13250",
    "sg:province":"Ciudad Real",
    "wof:name":"Pe\u00f1a Cano Manuel",
    "wof:placetype":"venue"
},
  "geometry": {"coordinates":[-3.6128089428,39.0687408447],"type":"Point"}
}