{
  "type": "Feature",
  "properties": {
    "iso:country":"ES",
    "sg:address":"Ptge Arraona, S/n",
    "sg:city":"Barbera Valles",
    "sg:orig_category":"Accesorios Para Tintorer\u00cdas, Limpieza En Seco",
    "sg:phone":"+34 937 29 04 56",
    "sg:postcode":"08210",
    "sg:province":"Barcelona",
    "sg:website":"www.laundrysystems.electrolux.es",
    "wof:name":"Electrolux Profesional S.l.",
    "wof:placetype":"venue"
},
  "geometry": {"coordinates":[2.1467978954,41.5267906189],"type":"Point"}
}