{
  "type": "Feature",
  "properties": {
    "addr:full":"Carr Virgen Del Remedio, 28 Olleria Valencia 46850",
    "addr:housenumber":"28",
    "addr:postcode":"46850",
    "addr:street":"Carr Virgen Del Remedio",
    "iso:country":"ES",
    "sg:address":"Carr Virgen Del Remedio, 28",
    "sg:city":"Olleria",
    "sg:orig_category":"Alimentaci\u00d3n General (al Por Menor)",
    "sg:phone":"+34 962 20 03 23",
    "sg:postcode":"46850",
    "sg:province":"Valencia",
    "wof:name":"Grau Del Oro Manuel",
    "wof:placetype":"venue"
},
  "geometry": {"coordinates":[-0.5506489873,38.9127960205],"type":"Point"}
}