{
  "type": "Feature",
  "properties": {
    "addr:full":"Calle de Cadiz, 7 Santander Cantabria 39002",
    "addr:housenumber":"7",
    "addr:postcode":"39002",
    "addr:street":"Calle De Cadiz",
    "iso:country":"ES",
    "sg:address":"Calle de Cadiz, 7",
    "sg:city":"Santander",
    "sg:orig_category":"Procuradores",
    "sg:phone":"+34 942 22 77 38",
    "sg:postcode":"39002",
    "sg:province":"Cantabria",
    "wof:name":"Arce Alonso Maximiliano",
    "wof:placetype":"venue"
},
  "geometry": {"coordinates":[-3.809776783,43.459728241],"type":"Point"}
}