{
  "type": "Feature",
  "properties": {
    "iso:country":"ES",
    "sg:address":"Calle de Menendez Pidal, 25",
    "sg:city":"Ca\u00e7ete De Las Torres",
    "sg:orig_category":"Carnicer\u00cdas, Carnicer\u00cdas",
    "sg:phone":"+34 957 18 32 91",
    "sg:postcode":"14660",
    "sg:province":"C\u00f3rdoba",
    "wof:name":"Garcia Delgado Juan Miguel",
    "wof:placetype":"venue"
},
  "geometry": {"coordinates":[-4.3157100677,37.8680305481],"type":"Point"}
}