{
  "type": "Feature",
  "properties": {
    "addr:full":"Calle de Concejal Garcia Feo, S/n Palmas De Gran Canaria Las Palmas 35011",
    "addr:postcode":"35011",
    "addr:street":"Calle De Concejal Garcia Feo S / N",
    "iso:country":"ES",
    "sg:address":"Calle de Concejal Garcia Feo, S/n",
    "sg:city":"Palmas De Gran Canaria",
    "sg:orig_category":"Bancos",
    "sg:phone":"+34 928 27 07 00",
    "sg:postcode":"35011",
    "sg:province":"Las Palmas",
    "sg:website":"www.bancozaragozano.es",
    "wof:name":"Barclays Bank S.a.e.",
    "wof:placetype":"venue"
},
  "geometry": {"coordinates":[-15.4387073517,28.1223621368],"type":"Point"}
}