{
  "type": "Feature",
  "properties": {
    "addr:full":"Calle de Calderon De La Barca, 3 Valladolid Valladolid 47010",
    "addr:housenumber":"3",
    "addr:postcode":"47010",
    "addr:street":"Calle De Calderon De La Barca",
    "iso:country":"ES",
    "sg:address":"Calle de Calderon De La Barca, 3",
    "sg:city":"Valladolid",
    "sg:orig_category":"Peluqueros: De Se\u00d1oras",
    "sg:phone":"+34 983 26 45 38",
    "sg:postcode":"47010",
    "sg:province":"Valladolid",
    "wof:name":"Fernandez Gonzalez Maria Dolores",
    "wof:placetype":"venue"
},
  "geometry": {"coordinates":[-4.7253460884,41.6611251831],"type":"Point"}
}