{
  "type": "Feature",
  "properties": {
    "addr:full":"Pg Estacio (de L'), 1 Montblanc Tarragona 43400",
    "addr:housenumber":"1",
    "addr:postcode":"43400",
    "addr:street":"Pg Estacio De L '",
    "iso:country":"ES",
    "sg:address":"Pg Estacio (de L'), 1",
    "sg:city":"Montblanc",
    "sg:orig_category":"Fabricaci\u00d3n, Venta, Instalaci\u00d3n De R\u00d3tulos, De R\u00d3tulos Luminosos",
    "sg:phone":"+34 977 86 25 22",
    "sg:postcode":"43400",
    "sg:province":"Tarragona",
    "wof:name":"Parrilla Jove Angel",
    "wof:placetype":"venue"
},
  "geometry": {"coordinates":[1.1659350395,41.375919342],"type":"Point"}
}