{
  "type": "Feature",
  "properties": {
    "addr:full":"Ctra Borja-rueda, 34 Ainzon Zaragoza 50570",
    "addr:housenumber":"34",
    "addr:postcode":"50570",
    "addr:street":"Ctra Borja-Rueda",
    "iso:country":"ES",
    "sg:address":"Ctra Borja-rueda, 34",
    "sg:city":"Ainzon",
    "sg:orig_category":"Empresas De Carpinter\u00cda",
    "sg:phone":"+34 976 86 85 02",
    "sg:postcode":"50570",
    "sg:province":"Zaragoza",
    "wof:name":"Royo Lafuente Jose Fermin",
    "wof:placetype":"venue"
},
  "geometry": {"coordinates":[-1.5176349878,41.8189239502],"type":"Point"}
}