{
  "type": "Feature",
  "properties": {
    "addr:full":"Calle de Juan Ramon Jimenez, 21 Valencia Valencia 46006",
    "addr:housenumber":"21",
    "addr:postcode":"46006",
    "addr:street":"Calle De Juan Ramon Jimenez",
    "iso:country":"ES",
    "sg:address":"Calle de Juan Ramon Jimenez, 21",
    "sg:city":"Valencia",
    "sg:orig_category":"Agencias Y Agentes Comerciales, Representantes",
    "sg:phone":"+34 963 74 60 85",
    "sg:postcode":"46006",
    "sg:province":"Valencia",
    "wof:name":"Leon Guillen Rufino",
    "wof:placetype":"venue"
},
  "geometry": {"coordinates":[-0.3759199977,39.4550704956],"type":"Point"}
}