{
  "type": "Feature",
  "properties": {
    "iso:country":"ES",
    "sg:address":"Av Costa Brava, 23",
    "sg:city":"Cor\u00e7a",
    "sg:orig_category":"Distribuci\u00d3n De Petr\u00d3leo Y Derivados",
    "sg:phone":"+34 972 63 04 99",
    "sg:postcode":"17121",
    "sg:province":"Girona",
    "wof:name":"Estacio Servei Corsa",
    "wof:placetype":"venue"
},
  "geometry": {"coordinates":[3.0151700974,41.9888916016],"type":"Point"}
}