{
  "type": "Feature",
  "properties": {
    "iso:country":"ES",
    "sg:address":"Ctra. Velilla S. Antonio, Km. 0002,1",
    "sg:city":"Mejorada Campo",
    "sg:orig_category":"Artes Gr\u00c1ficas, Artes Pl\u00c1sticas (curso)",
    "sg:phone":"+34 916 79 36 64",
    "sg:postcode":"28840",
    "sg:province":"Madrid",
    "wof:name":"Archigal S.a.",
    "wof:placetype":"venue"
},
  "geometry": {"coordinates":[-3.4902169704,40.395980835],"type":"Point"}
}