{
  "type": "Feature",
  "properties": {
    "addr:full":"Carr President Macia, 51 Palamos Girona 17230",
    "addr:housenumber":"51",
    "addr:postcode":"17230",
    "addr:street":"Carr President Macia",
    "iso:country":"ES",
    "sg:address":"Carr President Macia, 51",
    "sg:city":"Palamos",
    "sg:orig_category":"Asesor\u00cda Sobre Comunicaci\u00d3n De Empresas",
    "sg:phone":"+34 972 31 56 32",
    "sg:postcode":"17230",
    "sg:province":"Girona",
    "sg:website":"www.tax.es",
    "wof:name":"Palamos Assessors S.l.",
    "wof:placetype":"venue"
},
  "geometry": {"coordinates":[3.1235840321,41.8493003845],"type":"Point"}
}