{
  "type": "Feature",
  "properties": {
    "iso:country":"ES",
    "sg:address":"Mte Mendaur, 10",
    "sg:city":"Iru\u00f1a",
    "sg:orig_category":"Molduras, Junquillos, Listones Y Molduras Perforadas",
    "sg:phone":"+34 948 24 92 93",
    "sg:postcode":"31006",
    "sg:province":"Navarra",
    "wof:name":"Gil Segura Jose",
    "wof:placetype":"venue"
},
  "geometry": {"coordinates":[-1.6299338341,42.8059120178],"type":"Point"}
}