{
  "type": "Feature",
  "properties": {
    "iso:country":"ES",
    "sg:address":"Calle de Jose Antonio, 10",
    "sg:city":"Vecinos",
    "sg:orig_category":"Carnicer\u00cdas, Carnicer\u00cdas",
    "sg:phone":"+34 923 38 23 71",
    "sg:postcode":"37452",
    "sg:province":"Salamanca",
    "wof:name":"Guillen Sanchez Amparo",
    "wof:placetype":"venue"
},
  "geometry": {"coordinates":[-5.8812417984,40.7321395874],"type":"Point"}
}