{
  "type": "Feature",
  "properties": {
    "iso:country":"ES",
    "sg:address":"Calle de Primero De Mayo, 16",
    "sg:city":"Zubia",
    "sg:orig_category":"Supermercados Y Hipermercados",
    "sg:phone":"+34 958 89 11 35",
    "sg:postcode":"18140",
    "sg:province":"Granada",
    "wof:name":"Dinosol Supermercados S.l.",
    "wof:placetype":"venue"
},
  "geometry": {"coordinates":[-3.5841209888,37.1179428101],"type":"Point"}
}