{
  "type": "Feature",
  "properties": {
    "iso:country":"ES",
    "sg:address":"Calle de Carril Del Picon, 11",
    "sg:city":"Granada",
    "sg:orig_category":"Zapatos (al Por Menor)",
    "sg:phone":"+34 958 29 40 02",
    "sg:postcode":"18002",
    "sg:province":"Granada",
    "wof:name":"Garcia-duarte Duro Maria Del Carmen",
    "wof:placetype":"venue"
},
  "geometry": {"coordinates":[-3.6057338715,37.1770057678],"type":"Point"}
}