{
  "type": "Feature",
  "properties": {
    "addr:full":"Calle de Mayor, S/n Carde\u00f1ajimeno Burgos 09193",
    "addr:housenumber":"s",
    "addr:postcode":"09193",
    "addr:street":"Calle De Mayor;/ N Carden\u0303Ajimeno",
    "iso:country":"ES",
    "sg:address":"Calle de Mayor, S/n",
    "sg:city":"Carde\u00f1ajimeno",
    "sg:orig_category":"Farmacias",
    "sg:phone":"+34 947 48 42 08",
    "sg:postcode":"09193",
    "sg:province":"Burgos",
    "wof:name":"Rojo Escudero Cristina",
    "wof:placetype":"venue"
},
  "geometry": {"coordinates":[-3.619478941,42.3305664062],"type":"Point"}
}