{
  "type": "Feature",
  "properties": {
    "iso:country":"ES",
    "sg:address":"Avgd Exercit, 32",
    "sg:city":"Lleida",
    "sg:orig_category":"Agentes, Concesionarios Y Sucursales De Veh\u00cdculos",
    "sg:phone":"+34 973 28 02 05",
    "sg:postcode":"25091",
    "sg:province":"Lleida",
    "wof:name":"Ilermotor S.l.",
    "wof:placetype":"venue"
},
  "geometry": {"coordinates":[0.6138494015,41.6063919067],"type":"Point"}
}