{
  "type": "Feature",
  "properties": {
    "addr:full":"Carrer de Mallorca, 183 Barcelona Barcelona 08036",
    "addr:housenumber":"183",
    "addr:postcode":"08036",
    "addr:street":"Carrer De Mallorca",
    "iso:country":"ES",
    "sg:address":"Carrer de Mallorca, 183",
    "sg:city":"Barcelona",
    "sg:orig_category":"Expertos Contables, Revisores De Cuentas",
    "sg:phone":"+34 933 23 85 15",
    "sg:postcode":"08036",
    "sg:province":"Barcelona",
    "sg:website":"www.seraudit.es",
    "wof:name":"Seraudit Auditores S.l.",
    "wof:placetype":"venue"
},
  "geometry": {"coordinates":[2.1565079689,41.3894805908],"type":"Point"}
}