{
  "type": "Feature",
  "properties": {
    "iso:country":"ES",
    "sg:address":"Calle de Arcos, 27",
    "sg:city":"Jerez De La Frontera",
    "sg:orig_category":"M\u00c1quinas De Coser Y De Hacer Punto (al Por Mayor)",
    "sg:phone":"+34 956 33 65 95",
    "sg:postcode":"11402",
    "sg:province":"C\u00e1diz",
    "wof:name":"Guzman Garcia Rosa Natividad",
    "wof:placetype":"venue"
},
  "geometry": {"coordinates":[-6.1336121559,36.6836700439],"type":"Point"}
}