{
  "type": "Feature",
  "properties": {
    "addr:full":"Calle de Brasil, 33 Valencia Valencia 46018",
    "addr:housenumber":"33",
    "addr:postcode":"46018",
    "addr:street":"Calle De Brasil",
    "iso:country":"ES",
    "sg:address":"Calle de Brasil, 33",
    "sg:city":"Valencia",
    "sg:orig_category":"Estancos",
    "sg:phone":"+34 963 79 84 28",
    "sg:postcode":"46018",
    "sg:province":"Valencia",
    "wof:name":"Merino Barbosa Juana",
    "wof:placetype":"venue"
},
  "geometry": {"coordinates":[-0.3972569108,39.4714241028],"type":"Point"}
}