{
  "type": "Feature",
  "properties": {
    "iso:country":"ES",
    "sg:address":"Calle de Juntas Generales, 38",
    "sg:city":"Vitoria-gasteiz",
    "sg:orig_category":"Librer\u00cdas",
    "sg:phone":"+34 945 17 04 52",
    "sg:postcode":"01010",
    "sg:province":"\u00c1lava",
    "wof:name":"Quintana Rodriguez Rebeca",
    "wof:placetype":"venue"
},
  "geometry": {"coordinates":[-2.6998240948,42.8534507751],"type":"Point"}
}