{
  "type": "Feature",
  "properties": {
    "iso:country":"ES",
    "sg:address":"Zarugalde Kalea, 16",
    "sg:city":"Arrasate",
    "sg:orig_category":"M\u00c9dicos: Estomatolog\u00cda",
    "sg:phone":"+34 943 77 12 63",
    "sg:postcode":"20500",
    "sg:province":"Guip\u00f9zcoa",
    "wof:name":"Lorenzo Martin Rafael",
    "wof:placetype":"venue"
},
  "geometry": {"coordinates":[-2.4928450584,43.0657920837],"type":"Point"}
}