{
  "type": "Feature",
  "properties": {
    "iso:country":"ES",
    "sg:address":"Carrer de Emperador August, 5",
    "sg:city":"Tarragona",
    "sg:orig_category":"Organismos De Turismo",
    "sg:phone":"+34 977 22 08 62",
    "sg:postcode":"43003",
    "sg:province":"Tarragona",
    "wof:name":"Associacio D'apartamens Turistics De La Costa Daurada",
    "wof:placetype":"venue"
},
  "geometry": {"coordinates":[1.2638318539,41.1168708801],"type":"Point"}
}