{
  "type": "Feature",
  "properties": {
    "iso:country":"ES",
    "sg:address":"Calle de Juan Sebastian Elcano, 3",
    "sg:city":"Leganes",
    "sg:orig_category":"Caf\u00c9s, Bares, Cervecer\u00cdas",
    "sg:phone":"+34 916 89 45 65",
    "sg:postcode":"28911",
    "sg:province":"Madrid",
    "wof:name":"Alonso Rodriguez Benedicta",
    "wof:placetype":"venue"
},
  "geometry": {"coordinates":[-3.7684819698,40.3230743408],"type":"Point"}
}