{
  "type": "Feature",
  "properties": {
    "iso:country":"ES",
    "sg:address":"Calle de San Francisco, 34",
    "sg:city":"Quintanar Orden",
    "sg:orig_category":"Papeler\u00cdas, Librer\u00cdas",
    "sg:phone":"+34 925 56 49 23",
    "sg:postcode":"45800",
    "sg:province":"Toledo",
    "wof:name":"Gonzalez Aguilar Luisa",
    "wof:placetype":"venue"
},
  "geometry": {"coordinates":[-3.0422589779,39.5935211182],"type":"Point"}
}