{
  "type": "Feature",
  "properties": {
    "addr:full":"Calle de Jose Picon, 28 Madrid Madrid 28028",
    "addr:housenumber":"28",
    "addr:postcode":"madrid;28028",
    "addr:street":"Calle De Jose Picon",
    "iso:country":"ES",
    "sg:address":"Calle de Jose Picon, 28",
    "sg:city":"Madrid",
    "sg:orig_category":"Artes Gr\u00c1ficas, Artes Pl\u00c1sticas: Material Y Suministros (al Por Menor)",
    "sg:phone":"+34 913 55 95 82",
    "sg:postcode":"28028",
    "sg:province":"Madrid",
    "wof:name":"Mbingu S.l.",
    "wof:placetype":"venue"
},
  "geometry": {"coordinates":[-3.6707429886,40.4360923767],"type":"Point"}
}