{
  "type": "Feature",
  "properties": {
    "iso:country":"ES",
    "sg:address":"Calle de Santa Gema, 3",
    "sg:city":"Mairena Alcor",
    "sg:orig_category":"Empresas De Pintura Y Revestimientos",
    "sg:phone":"+34 955 94 32 47",
    "sg:postcode":"41510",
    "sg:province":"Sevilla",
    "wof:name":"Pinturas Gutisur S.l.",
    "wof:placetype":"venue"
},
  "geometry": {"coordinates":[-5.7521696091,37.3680915833],"type":"Point"}
}