{
  "type": "Feature",
  "properties": {
    "addr:full":"Plaz Movimiento Ciudadano, 1 Madrid Madrid 28041",
    "addr:housenumber":"1",
    "addr:postcode":"28041",
    "iso:country":"ES",
    "sg:address":"Plaz Movimiento Ciudadano, 1",
    "sg:city":"Madrid",
    "sg:orig_category":"Artesan\u00cda",
    "sg:phone":"+34 913 41 41 66",
    "sg:postcode":"28041",
    "sg:province":"Madrid",
    "wof:name":"Alonso Morte Maria Mercedes",
    "wof:placetype":"venue"
},
  "geometry": {"coordinates":[-3.7083191872,40.3702964783],"type":"Point"}
}