{
  "type": "Feature",
  "properties": {
    "addr:full":"Carr Del Dos De Maig, 85 Ontinyent Valencia 46870",
    "addr:housenumber":"85",
    "addr:postcode":"46870",
    "addr:street":"Carr Del Dos De Maig",
    "iso:country":"ES",
    "sg:address":"Carr Del Dos De Maig, 85",
    "sg:city":"Ontinyent",
    "sg:orig_category":"Empresas De Carpinter\u00cda De Madera",
    "sg:phone":"+34 962 38 03 19",
    "sg:postcode":"46870",
    "sg:province":"Valencia",
    "wof:name":"Eulalia Tormo Rafael",
    "wof:placetype":"venue"
},
  "geometry": {"coordinates":[-0.6030989885,38.8258895874],"type":"Point"}
}