{
  "type": "Feature",
  "properties": {
    "iso:country":"ES",
    "sg:address":"Calle de San Vicente San Matias, 11",
    "sg:city":"Taco",
    "sg:orig_category":"Transporte En General",
    "sg:phone":"+34 922 62 36 17",
    "sg:postcode":"38108",
    "sg:province":"Santa Cruz De Tenerife",
    "wof:name":"Suministros Anambro S.l",
    "wof:placetype":"venue"
},
  "geometry": {"coordinates":[-16.2988090515,28.4412841797],"type":"Point"}
}