{
  "type": "Feature",
  "properties": {
    "iso:country":"ES",
    "sg:address":"Avda. Finisterre, 195",
    "sg:city":"A Coru\u00f1a",
    "sg:orig_category":"Moquetas, Alfombras (al Por Menor)",
    "sg:phone":"+34 981 24 27 85",
    "sg:postcode":"15010",
    "sg:province":"La Coru\u00f1a",
    "wof:name":"El Palacio De Las Alfombras S.l.",
    "wof:placetype":"venue"
},
  "geometry": {"coordinates":[-8.416431427,43.3605308533],"type":"Point"}
}