{
  "type": "Feature",
  "properties": {
    "iso:country":"ES",
    "sg:address":"Ctra. Jimena, Km. 0008,0",
    "sg:city":"S. Martin",
    "sg:orig_category":"T\u00c9cnicos Veterinarios",
    "sg:phone":"+34 956 61 85 36",
    "sg:postcode":"11340",
    "sg:province":"C\u00e1diz",
    "wof:name":"Sanchez Rios Jose Joaquin",
    "wof:placetype":"venue"
},
  "geometry": {"coordinates":[-5.3190140724,36.3409385681],"type":"Point"}
}