{
  "type": "Feature",
  "properties": {
    "iso:country":"ES",
    "sg:address":"Carrer de Reding (de), 18",
    "sg:city":"Tarragona",
    "sg:orig_category":"Costureras",
    "sg:phone":"+34 977 21 51 78",
    "sg:postcode":"43001",
    "sg:province":"Tarragona",
    "wof:name":"Ronda Barrera Concepcion",
    "wof:placetype":"venue"
},
  "geometry": {"coordinates":[1.2500859499,41.1152572632],"type":"Point"}
}