{
  "type": "Feature",
  "properties": {
    "addr:full":"Avda Madrid, 77 Becerrea Lugo 27640",
    "addr:housenumber":"77",
    "addr:postcode":"27640",
    "addr:street":"Avda Madrid",
    "iso:country":"ES",
    "sg:address":"Avda Madrid, 77",
    "sg:city":"Becerrea",
    "sg:orig_category":"Distribuci\u00d3n De Petr\u00d3leo Y Derivados",
    "sg:phone":"+34 982 36 00 22",
    "sg:postcode":"27640",
    "sg:province":"Lugo",
    "wof:name":"Estacion De Servicio Rutancares S.l.",
    "wof:placetype":"venue"
},
  "geometry": {"coordinates":[-7.1606140137,42.8534202576],"type":"Point"}
}