{
  "type": "Feature",
  "properties": {
    "iso:country":"ES",
    "sg:address":"Calle de Constitucion, 8",
    "sg:city":"Cabrerizos",
    "sg:orig_category":"Farmacias",
    "sg:phone":"+34 923 28 90 59",
    "sg:postcode":"37193",
    "sg:province":"Salamanca",
    "wof:name":"Astudillo Sagrado Encarnacion",
    "wof:placetype":"venue"
},
  "geometry": {"coordinates":[-5.6088757515,40.9787979126],"type":"Point"}
}