{
  "type": "Feature",
  "properties": {
    "iso:country":"ES",
    "sg:address":"Carrer de Lleo Xiii, 62",
    "sg:city":"Terrassa",
    "sg:orig_category":"Peluqueros: De Se\u00d1oras",
    "sg:phone":"+34 937 83 79 08",
    "sg:postcode":"08222",
    "sg:province":"Barcelona",
    "wof:name":"Salon De Belleza Nerea",
    "wof:placetype":"venue"
},
  "geometry": {"coordinates":[2.0261280537,41.5662727356],"type":"Point"}
}