{
  "type": "Feature",
  "properties": {
    "addr:full":"Avda Portugal, 122 Chantada Lugo 27500",
    "addr:housenumber":"122",
    "addr:postcode":"27500",
    "addr:street":"Avda Portugal",
    "iso:country":"ES",
    "sg:address":"Avda Portugal, 122",
    "sg:city":"Chantada",
    "sg:orig_category":"Electrodom\u00c9sticos (al Por Menor)",
    "sg:phone":"+34 982 44 07 77",
    "sg:postcode":"27500",
    "sg:province":"Lugo",
    "wof:name":"Lopez Lopez Jose Manuel",
    "wof:placetype":"venue"
},
  "geometry": {"coordinates":[-7.7778477669,42.6096458435],"type":"Point"}
}