{
  "type": "Feature",
  "properties": {
    "iso:country":"ES",
    "sg:address":"Via Augusta, 33",
    "sg:city":"Barcelona",
    "sg:orig_category":"M\u00c9dicos: Medicina Interna",
    "sg:phone":"+34 934 15 42 29",
    "sg:postcode":"08006",
    "sg:province":"Barcelona",
    "wof:name":"Villalta Blanch Jaime",
    "wof:placetype":"venue"
},
  "geometry": {"coordinates":[2.1537640095,41.3977088928],"type":"Point"}
}