{
  "type": "Feature",
  "properties": {
    "addr:full":"Ctra. A.-punta Umbria, S/n Aljaraque Huelva 21110",
    "addr:housenumber":"s / n",
    "addr:postcode":"21110",
    "addr:street":"Ctra. A.-Punta Umbria",
    "iso:country":"ES",
    "sg:address":"Ctra. A.-punta Umbria, S/n",
    "sg:city":"Aljaraque",
    "sg:orig_category":"Distribuci\u00d3n De Petr\u00d3leo Y Derivados",
    "sg:phone":"+34 959 31 60 73",
    "sg:postcode":"21110",
    "sg:province":"Huelva",
    "wof:name":"Estacion De Servicio Perez Rodriguez S.l.",
    "wof:placetype":"venue"
},
  "geometry": {"coordinates":[-7.0131778717,37.2766227722],"type":"Point"}
}