{
  "type": "Feature",
  "properties": {
    "iso:country":"ES",
    "sg:address":"Pla\u00c7 Major, S/n",
    "sg:city":"Ventallo",
    "sg:orig_category":"Administraciones Regionales, Departamentales Y Locales",
    "sg:phone":"+34 972 79 31 56",
    "sg:postcode":"17473",
    "sg:province":"Girona",
    "wof:name":"Ajuntament De Ventallo",
    "wof:placetype":"venue"
},
  "geometry": {"coordinates":[3.0275802612,42.1470794678],"type":"Point"}
}