{
  "type": "Feature",
  "properties": {
    "addr:full":"Calle de Menacho, 47 Badajoz Badajoz 06001",
    "addr:housenumber":"47",
    "addr:postcode":"06001",
    "addr:street":"Calle De Menacho",
    "iso:country":"ES",
    "sg:address":"Calle de Menacho, 47",
    "sg:city":"Badajoz",
    "sg:orig_category":"Electricidad: Instaladores",
    "sg:phone":"+34 924 24 63 05",
    "sg:postcode":"06001",
    "sg:province":"Badajoz",
    "wof:name":"Quirante Gomez Salvador Angel",
    "wof:placetype":"venue"
},
  "geometry": {"coordinates":[-6.9747190475,38.8761825562],"type":"Point"}
}