{
  "type": "Feature",
  "properties": {
    "iso:country":"ES",
    "sg:address":"Carrer de Emili Darder,batle, 53",
    "sg:city":"Palma",
    "sg:orig_category":"Procuradores",
    "sg:phone":"+34 971 73 20 17",
    "sg:postcode":"07013",
    "sg:province":"Islas Baleares",
    "wof:name":"Diez Blanco Maria Jose",
    "wof:placetype":"venue"
},
  "geometry": {"coordinates":[2.637116909,39.576839447],"type":"Point"}
}