{
  "type": "Feature",
  "properties": {
    "addr:full":"Av Alegries, 4 Lloret Mar Girona 17310",
    "addr:housenumber":"4",
    "addr:postcode":"17310",
    "addr:street":"Av Alegries",
    "iso:country":"ES",
    "sg:address":"Av Alegries, 4",
    "sg:city":"Lloret Mar",
    "sg:orig_category":"Negocio De Materiales De Construcci\u00d3n",
    "sg:phone":"+34 972 34 93 26",
    "sg:postcode":"17310",
    "sg:province":"Girona",
    "wof:name":"Carmona E Hijos S.a.",
    "wof:placetype":"venue"
},
  "geometry": {"coordinates":[2.831553936,41.7110900879],"type":"Point"}
}