{
  "type": "Feature",
  "properties": {
    "iso:country":"ES",
    "sg:address":"Rua Infantas, 1",
    "sg:city":"Cambados",
    "sg:orig_category":"Discotecas Y Salas De Baile",
    "sg:phone":"+34 986 54 36 74",
    "sg:postcode":"36630",
    "sg:province":"Pontevedra",
    "wof:name":"Hermanos Daporta Fernandez S. L.",
    "wof:placetype":"venue"
},
  "geometry": {"coordinates":[-8.8145885468,42.5141944885],"type":"Point"}
}