{
  "type": "Feature",
  "properties": {
    "addr:full":"Exconvento, 5 Monovar Alicante 03640",
    "addr:housenumber":"5",
    "addr:postcode":"03640",
    "addr:street":"Exconvento;Alicante",
    "iso:country":"ES",
    "sg:address":"Exconvento, 5",
    "sg:city":"Monovar",
    "sg:orig_category":"Droguer\u00cdas (al Por Menor)",
    "sg:phone":"+34 965 47 11 50",
    "sg:postcode":"03640",
    "sg:province":"Alicante",
    "wof:name":"Persegdro S.l.",
    "wof:placetype":"venue"
},
  "geometry": {"coordinates":[-0.8426520228,38.4369544983],"type":"Point"}
}