{
  "type": "Feature",
  "properties": {
    "addr:full":"Plaz Padre Lasa, 3 Tudela Navarra 31500",
    "addr:postcode":"31500",
    "iso:country":"ES",
    "sg:address":"Plaz Padre Lasa, 3",
    "sg:city":"Tudela",
    "sg:classifiers":[
        {
            "category":"Personal",
            "subcategory":"Barber",
            "type":"Services"
        }
    ],
    "sg:phone":"+34 948 82 84 61",
    "sg:postcode":"31500",
    "sg:province":"Navarra",
    "sg:tags":[
        "caballeros",
        "de",
        "peluqueros"
    ],
    "wof:name":"Aguirre Redrado Esteban",
    "wof:placetype":"venue"
},
  "geometry": {"coordinates":[-1.6030710936,42.0549659729],"type":"Point"}
}