{
  "type": "Feature",
  "properties": {
    "addr:full":"Luga Vistalegre, S/n Vistalegre Asturias 33791",
    "addr:housenumber":"s / n",
    "addr:postcode":"33791",
    "iso:country":"ES",
    "sg:address":"Luga Vistalegre, S/n",
    "sg:city":"Vistalegre",
    "sg:orig_category":"Bebidas",
    "sg:phone":"+34 985 64 04 11",
    "sg:postcode":"33791",
    "sg:province":"Asturias",
    "wof:name":"Suarez Garcia Jose",
    "wof:placetype":"venue"
},
  "geometry": {"coordinates":[-6.5494170189,43.5371437073],"type":"Point"}
}