{
  "type": "Feature",
  "properties": {
    "iso:country":"ES",
    "sg:address":"Calle de Marrajo, 4",
    "sg:city":"Corralejo",
    "sg:classifiers":[
        {
            "category":"Taxi",
            "type":"Transportation"
        }
    ],
    "sg:phone":"+34 928 53 74 41",
    "sg:postcode":"35660",
    "sg:province":"Las Palmas",
    "wof:name":"Asociacion Profesional De Taxis De Corralejos",
    "wof:placetype":"venue"
},
  "geometry": {"coordinates":[-13.8655967712,28.743396759],"type":"Point"}
}