{
  "type": "Feature",
  "properties": {
    "addr:full":"Calle de Bolivia, 64 Zaragoza Zaragoza 50010",
    "addr:housenumber":"64",
    "addr:postcode":"50010",
    "addr:street":"Calle De Bolivia",
    "iso:country":"ES",
    "sg:address":"Calle de Bolivia, 64",
    "sg:city":"Zaragoza",
    "sg:orig_category":"Inmobiliaria (agencias)",
    "sg:phone":"+34 976 34 71 86",
    "sg:postcode":"50010",
    "sg:province":"Zaragoza",
    "wof:name":"Interpiso Ven S.l.",
    "wof:placetype":"venue"
},
  "geometry": {"coordinates":[-0.9008142948,41.6511878967],"type":"Point"}
}