{
  "type": "Feature",
  "properties": {
    "iso:country":"ES",
    "sg:address":"Calle de Arzobispo Marcelo Gonzalez, 22",
    "sg:city":"Valladolid",
    "sg:orig_category":"Plomeros",
    "sg:phone":"+34 983 23 16 44",
    "sg:postcode":"47007",
    "sg:province":"Valladolid",
    "wof:name":"Duque Express S.l.",
    "wof:placetype":"venue"
},
  "geometry": {"coordinates":[-4.7377352715,41.6351623535],"type":"Point"}
}