{
  "type": "Feature",
  "properties": {
    "iso:country":"ES",
    "sg:address":"Avda Blas Perez Gonzalez, S/n",
    "sg:city":"Puerto Cruz",
    "sg:orig_category":"Frutas, Legumbres Frescas Y Tempranas (al Por Menor)",
    "sg:phone":"+34 922 38 60 10",
    "sg:postcode":"38400",
    "sg:province":"Santa Cruz De Tenerife",
    "wof:name":"Perez Siverio Vicente Carmelo",
    "wof:placetype":"venue"
},
  "geometry": {"coordinates":[-16.5564193726,28.4114151001],"type":"Point"}
}