{
  "type": "Feature",
  "properties": {
    "iso:country":"ES",
    "sg:address":"Calle de Julio Moreno Davila, S/n",
    "sg:city":"Granada",
    "sg:orig_category":"Ense\u00d1anza: Profesiones Art\u00cdsticas",
    "sg:phone":"+34 958 15 70 54",
    "sg:postcode":"18011",
    "sg:province":"Granada",
    "wof:name":"Silles Perez Miguel Angel",
    "wof:placetype":"venue"
},
  "geometry": {"coordinates":[-3.5986940861,37.2031555176],"type":"Point"}
}