{
  "type": "Feature",
  "properties": {
    "iso:country":"ES",
    "sg:address":"Avda Pintor Joaquin Sorolla, 30",
    "sg:city":"Malaga",
    "sg:orig_category":"Guarder\u00cdas",
    "sg:phone":"+34 952 22 14 70",
    "sg:postcode":"29016",
    "sg:province":"M\u00e1laga",
    "wof:name":"Romero De Los Reyes 2001 S.l.",
    "wof:placetype":"venue"
},
  "geometry": {"coordinates":[-4.3940219879,36.7233734131],"type":"Point"}
}