{
  "type": "Feature",
  "properties": {
    "addr:full":"C/ Peru, 12 Alcoi Alicante 03803",
    "addr:housenumber":"12",
    "addr:postcode":"03803",
    "addr:street":"C / Peru",
    "iso:country":"ES",
    "sg:address":"C/ Peru, 12",
    "sg:city":"Alcoi",
    "sg:orig_category":"Escayola Y Productos De Escayola (fabricaci\u00d3n, Al Por Mayor)",
    "sg:phone":"+34 965 33 34 80",
    "sg:postcode":"03803",
    "sg:province":"Alicante",
    "wof:name":"Bernabeu Sempere Adoracion",
    "wof:placetype":"venue"
},
  "geometry": {"coordinates":[-0.4827449918,38.7004241943],"type":"Point"}
}