{
  "type": "Feature",
  "properties": {
    "addr:full":"Calle de Cerrajeria, 4 Talavera Reina Toledo 45600",
    "addr:housenumber":"4",
    "addr:postcode":"45600",
    "addr:street":"Calle De Cerrajeria",
    "iso:country":"ES",
    "sg:address":"Calle de Cerrajeria, 4",
    "sg:city":"Talavera Reina",
    "sg:orig_category":"Trabajos De Soldaduras",
    "sg:phone":"+34 925 81 77 38",
    "sg:postcode":"45600",
    "sg:province":"Toledo",
    "wof:name":"Alsima Uno S.l.",
    "wof:placetype":"venue"
},
  "geometry": {"coordinates":[-4.8453555107,39.9556007385],"type":"Point"}
}