{
  "type": "Feature",
  "properties": {
    "iso:country":"ES",
    "sg:address":"Calle de Nueva, 7",
    "sg:city":"A\u00d1ora",
    "sg:orig_category":"Asesor\u00cda Fiscal Y Jur\u00cddica",
    "sg:phone":"+34 957 15 10 15",
    "sg:postcode":"14450",
    "sg:province":"C\u00f3rdoba",
    "wof:name":"Gomez Espejo Jose Maria",
    "wof:placetype":"venue"
},
  "geometry": {"coordinates":[-4.9016060829,38.4087753296],"type":"Point"}
}