{
  "type": "Feature",
  "properties": {
    "iso:country":"ES",
    "sg:address":"Carr Rois De Corella, 5",
    "sg:city":"Sueca",
    "sg:orig_category":"Reposter\u00cdas",
    "sg:phone":"+34 961 71 07 82",
    "sg:postcode":"46410",
    "sg:province":"Valencia",
    "wof:name":"Oviedo Vi\u00f1oles Juan Antonio",
    "wof:placetype":"venue"
},
  "geometry": {"coordinates":[-0.307844013,39.1995315552],"type":"Point"}
}