{
  "type": "Feature",
  "properties": {
    "iso:country":"ES",
    "sg:address":"Pg Maragall, 305",
    "sg:city":"Barcelona",
    "sg:orig_category":"Molduras, Junquillos, Listones Y Molduras Perforadas",
    "sg:phone":"+34 934 29 65 24",
    "sg:postcode":"08032",
    "sg:province":"Barcelona",
    "wof:name":"Caravita  Angelo",
    "wof:placetype":"venue"
},
  "geometry": {"coordinates":[2.1702830791,41.4269828796],"type":"Point"}
}