{
  "type": "Feature",
  "properties": {
    "iso:country":"ES",
    "sg:address":"Calle de Caridad, 1",
    "sg:city":"Valladolid",
    "sg:orig_category":"Prot\u00c9sicos Dentales",
    "sg:phone":"+34 983 33 20 56",
    "sg:postcode":"47001",
    "sg:province":"Valladolid",
    "wof:name":"Mardones Cuadrillero Luis Manuel",
    "wof:placetype":"venue"
},
  "geometry": {"coordinates":[-4.730304718,41.6516494751],"type":"Point"}
}