{
  "type": "Feature",
  "properties": {
    "iso:country":"ES",
    "sg:address":"Noroeste(p Ind), S/n",
    "sg:city":"Bullas",
    "sg:orig_category":"Chapister\u00cda",
    "sg:phone":"+34 968 65 38 33",
    "sg:postcode":"30180",
    "sg:province":"Murcia",
    "wof:name":"Auto Chapa Marsoni S.l.",
    "wof:placetype":"venue"
},
  "geometry": {"coordinates":[-1.6343749762,38.0616569519],"type":"Point"}
}