{
  "type": "Feature",
  "properties": {
    "addr:full":"Ctra. Toledo, 20 Noez Toledo 45162",
    "addr:housenumber":"20",
    "addr:postcode":"45162",
    "addr:street":"Ctra. Toledo",
    "iso:country":"ES",
    "sg:address":"Ctra. Toledo, 20",
    "sg:city":"Noez",
    "sg:orig_category":"Paneles De Madera: Contrachapados, Fibras, Particulados, Estratificados (fabricaci\u00d3n, Venta)",
    "sg:phone":"+34 925 37 42 43",
    "sg:postcode":"45162",
    "sg:province":"Toledo",
    "sg:website":"www.tarimastoledo.com",
    "wof:name":"Tarimas Toledo S.l.",
    "wof:placetype":"venue"
},
  "geometry": {"coordinates":[-4.184073925,39.742515564],"type":"Point"}
}