{
  "type": "Feature",
  "properties": {
    "iso:country":"ES",
    "sg:address":"Calle de Isla Menorca-la Regia, 3",
    "sg:city":"Urbanizacion La Regia",
    "sg:orig_category":"Molduras, Junquillos, Listones Y Molduras Perforadas",
    "sg:phone":"+34 965 32 21 29",
    "sg:postcode":"03189",
    "sg:province":"Alicante",
    "wof:name":"Locutorio E Internet D&g S.l.",
    "wof:placetype":"venue"
},
  "geometry": {"coordinates":[-0.7416210175,37.9123191833],"type":"Point"}
}