{
  "type": "Feature",
  "properties": {
    "addr:full":"Avgd Vicent Mortes Alfonso, 1 Paterna Valencia 46980",
    "addr:housenumber":"1",
    "addr:postcode":"46980",
    "addr:street":"Alfonso",
    "iso:country":"ES",
    "sg:address":"Avgd Vicent Mortes Alfonso, 1",
    "sg:city":"Paterna",
    "sg:orig_category":"Cajas De Ahorro",
    "sg:phone":"+34 961 38 47 11",
    "sg:postcode":"46980",
    "sg:province":"Valencia",
    "wof:name":"Caixa D'estalvis De Catalunya",
    "wof:placetype":"venue"
},
  "geometry": {"coordinates":[-0.4459390044,39.5051002502],"type":"Point"}
}