{
  "type": "Feature",
  "properties": {
    "iso:country":"ES",
    "sg:address":"Carrer de Schubert, 32",
    "sg:city":"Rubi",
    "sg:orig_category":"Fabricaci\u00d3n De Moldes Y Modelos",
    "sg:phone":"+34 936 97 02 11",
    "sg:postcode":"08191",
    "sg:province":"Barcelona",
    "wof:name":"Plasticos Marbe S.l.",
    "wof:placetype":"venue"
},
  "geometry": {"coordinates":[2.0191431046,41.4734153748],"type":"Point"}
}