{
  "type": "Feature",
  "properties": {
    "iso:country":"ES",
    "sg:address":"Rua Oliva (la), 8",
    "sg:city":"Pontevedra",
    "sg:orig_category":"Abogados",
    "sg:phone":"+34 986 85 21 20",
    "sg:postcode":"36001",
    "sg:province":"Pontevedra",
    "wof:name":"Lino Alvarez-qui\u00f1ones Jose F.",
    "wof:placetype":"venue"
},
  "geometry": {"coordinates":[-8.644536972,42.4305038452],"type":"Point"}
}