{
  "type": "Feature",
  "properties": {
    "addr:full":"Calle de Esteban De Arteaga, 4 Madrid Madrid 28019",
    "addr:housenumber":"4",
    "addr:postcode":"28019",
    "addr:street":"Calle De Esteban De Arteaga",
    "iso:country":"ES",
    "sg:address":"Calle de Esteban De Arteaga, 4",
    "sg:city":"Madrid",
    "sg:orig_category":"Empresas De Carpinter\u00cda",
    "sg:phone":"+34 914 69 26 02",
    "sg:postcode":"28019",
    "sg:province":"Madrid",
    "wof:name":"Fernandez Saugar Angel",
    "wof:placetype":"venue"
},
  "geometry": {"coordinates":[-3.7094764709,40.3954200745],"type":"Point"}
}