{
  "type": "Feature",
  "properties": {
    "iso:country":"ES",
    "sg:address":"Urb Los Conejos, 2",
    "sg:city":"Conejos",
    "sg:orig_category":"Electrodom\u00c9sticos (al Por Menor)",
    "sg:phone":"+34 968 61 98 82",
    "sg:postcode":"30500",
    "sg:province":"Murcia",
    "wof:name":"Antiempa\u00f1antes De Espejos Herga S.l.",
    "wof:placetype":"venue"
},
  "geometry": {"coordinates":[-1.1298867464,37.9834747314],"type":"Point"}
}