{
  "type": "Feature",
  "properties": {
    "iso:country":"ES",
    "sg:address":"Avda Miguel Escudero Arevalo, S/n",
    "sg:city":"Corella",
    "sg:orig_category":"Distribuci\u00d3n De Petr\u00d3leo Y Derivados",
    "sg:phone":"+34 948 78 02 07",
    "sg:postcode":"31591",
    "sg:province":"Navarra",
    "wof:name":"Perez De Arriluce Suso Basilio",
    "wof:placetype":"venue"
},
  "geometry": {"coordinates":[-1.7828840017,42.1147460938],"type":"Point"}
}