{
  "type": "Feature",
  "properties": {
    "addr:full":"Av Paral.lel, 95 Barcelona Barcelona 08004",
    "addr:housenumber":"95",
    "addr:postcode":"08004",
    "addr:street":"Av Paral.Lel",
    "iso:country":"ES",
    "sg:address":"Av Paral.lel, 95",
    "sg:city":"Barcelona",
    "sg:orig_category":"Asociaciones, Organismos Culturales Y Socioeducativos",
    "sg:phone":"+34 933 29 86 57",
    "sg:postcode":"08004",
    "sg:province":"Barcelona",
    "wof:name":"Associacio Gent Gran Santa Madrona",
    "wof:placetype":"venue"
},
  "geometry": {"coordinates":[2.1650147438,41.3749313354],"type":"Point"}
}