{
  "type": "Feature",
  "properties": {
    "iso:country":"ES",
    "sg:address":"Ctra. Madrid-salamanca, Km. 0147,8",
    "sg:city":"Chaherrero",
    "sg:orig_category":"Distribuci\u00d3n De Petr\u00d3leo Y Derivados",
    "sg:phone":"+34 920 23 92 26",
    "sg:postcode":"05309",
    "sg:province":"\u00c1vila",
    "wof:name":"Hermanos Cruz S.l.",
    "wof:placetype":"venue"
},
  "geometry": {"coordinates":[-4.9361290932,40.8839988708],"type":"Point"}
}