{
  "type": "Feature",
  "properties": {
    "addr:full":"Calle de Cuatro Amigos, 5 Madrid Madrid 28029",
    "addr:housenumber":"5",
    "addr:postcode":"28029",
    "addr:street":"Calle De Cuatro Amigos",
    "iso:country":"ES",
    "sg:address":"Calle de Cuatro Amigos, 5",
    "sg:city":"Madrid",
    "sg:orig_category":"Peluquer\u00cdas, Peluquer\u00cda Mixta",
    "sg:phone":"+34 913 15 66 55",
    "sg:postcode":"28029",
    "sg:province":"Madrid",
    "wof:name":"Lopez Garvi Juan",
    "wof:placetype":"venue"
},
  "geometry": {"coordinates":[-3.6910953522,40.4660720825],"type":"Point"}
}