{
  "type": "Feature",
  "properties": {
    "iso:country":"ES",
    "sg:address":"Avda Angeles (de Los), 22",
    "sg:city":"Getafe",
    "sg:orig_category":"Fabricaci\u00d3n, Instalaci\u00d3n De Armarios",
    "sg:phone":"+34 916 01 81 91",
    "sg:postcode":"28903",
    "sg:province":"Madrid",
    "wof:name":"Ducal Armarios S.l.l",
    "wof:placetype":"venue"
},
  "geometry": {"coordinates":[-3.7198829651,40.309261322],"type":"Point"}
}