{
  "type": "Feature",
  "properties": {
    "addr:full":"Res El Arenal Urb, S/n Punta Umbria Huelva 21100",
    "addr:housenumber":"s / n",
    "addr:postcode":"21100",
    "addr:street":"Urb",
    "iso:country":"ES",
    "sg:address":"Res El Arenal Urb, S/n",
    "sg:city":"Punta Umbria",
    "sg:orig_category":"Promotores Constructores",
    "sg:phone":"+34 959 65 90 46",
    "sg:postcode":"21100",
    "sg:province":"Huelva",
    "wof:name":"Agrupacion De Promotores De Punta Umbria S.a.",
    "wof:placetype":"venue"
},
  "geometry": {"coordinates":[-6.9960923195,37.2083358765],"type":"Point"}
}