{
  "type": "Feature",
  "properties": {
    "iso:country":"ES",
    "sg:address":"Calle de San Patricio, 10",
    "sg:city":"Catedral",
    "sg:orig_category":"Arquitectos",
    "sg:phone":"+34 968 21 21 35",
    "sg:postcode":"30004",
    "sg:province":"Murcia",
    "wof:name":"Abril Camacho Torrecilla S.l.",
    "wof:placetype":"venue"
},
  "geometry": {"coordinates":[-1.131067,37.983486],"type":"Point"}
}