{
  "type": "Feature",
  "properties": {
    "addr:full":"Calle de Padre Huesca, 39 Huesca Huesca 22002",
    "addr:housenumber":"39",
    "addr:postcode":"22002",
    "addr:street":"Calle De Padre Huesca",
    "iso:country":"ES",
    "sg:address":"Calle de Padre Huesca, 39",
    "sg:city":"Huesca",
    "sg:orig_category":"Arquitectos",
    "sg:phone":"+34 974 24 10 65",
    "sg:postcode":"22002",
    "sg:province":"Huesca",
    "wof:name":"Huesca Toda Obra S.l.",
    "wof:placetype":"venue"
},
  "geometry": {"coordinates":[-0.4063119888,42.1350669861],"type":"Point"}
}