{
  "type": "Feature",
  "properties": {
    "addr:full":"Calle de Portugal, 15 Arcos Frontera C\u00e1diz 11630",
    "addr:housenumber":"15",
    "addr:postcode":"11630",
    "addr:street":"Calle De Portugal",
    "iso:country":"ES",
    "sg:address":"Calle de Portugal, 15",
    "sg:city":"Arcos Frontera",
    "sg:orig_category":"M\u00c9dicos: Estomatolog\u00cda",
    "sg:phone":"+34 956 70 23 57",
    "sg:postcode":"11630",
    "sg:province":"C\u00e1diz",
    "wof:name":"Orgambides Gomez Juan Jose",
    "wof:placetype":"venue"
},
  "geometry": {"coordinates":[-5.8141860962,36.7544631958],"type":"Point"}
}