{
  "type": "Feature",
  "properties": {
    "addr:full":"Urbanizacion Colonia Pino, 200 Torrent Valencia 46900",
    "addr:housenumber":"200",
    "addr:postcode":"46900",
    "addr:street":"Urbanizacion Colonia Pino;Valencia",
    "iso:country":"ES",
    "sg:address":"Urbanizacion Colonia Pino, 200",
    "sg:city":"Torrent",
    "sg:orig_category":"Promotores Constructores",
    "sg:phone":"+34 961 57 58 11",
    "sg:postcode":"46900",
    "sg:province":"Valencia",
    "wof:name":"Construcciones Y Reformas Hermanos Garcia S.l.",
    "wof:placetype":"venue"
},
  "geometry": {"coordinates":[-0.4623290002,39.441619873],"type":"Point"}
}