{
  "type": "Feature",
  "properties": {
    "iso:country":"ES",
    "sg:address":"Calle de Conde Don Vela, 2",
    "sg:city":"Vitoria-gasteiz",
    "sg:orig_category":"Empresas De Pintura Y Revestimientos",
    "sg:phone":"+34 945 22 29 07",
    "sg:postcode":"01009",
    "sg:province":"\u00c1lava",
    "wof:name":"Rodriguez Marquinez Fernando",
    "wof:placetype":"venue"
},
  "geometry": {"coordinates":[-2.6874899864,42.8571662903],"type":"Point"}
}