{
  "type": "Feature",
  "properties": {
    "addr:full":"Rua Ramon Gonzalez, 50 Porri\u00f1o Pontevedra 36400",
    "addr:housenumber":"50",
    "addr:postcode":"36400",
    "addr:street":"Rua Ramon Gonzalez",
    "iso:country":"ES",
    "sg:address":"Rua Ramon Gonzalez, 50",
    "sg:city":"Porri\u00f1o",
    "sg:orig_category":"Fabricaci\u00d3n De Productos Textiles Sin Tejer",
    "sg:phone":"+34 986 33 40 13",
    "sg:postcode":"36400",
    "sg:province":"Pontevedra",
    "wof:name":"Vieito Fernandez Angeles",
    "wof:placetype":"venue"
},
  "geometry": {"coordinates":[-8.6208343506,42.1607093811],"type":"Point"}
}