{
  "type": "Feature",
  "properties": {
    "addr:full":"Miravalles, 7 Iru\u00f1a Navarra 31015",
    "addr:housenumber":"7",
    "addr:postcode":"31015",
    "addr:street":"Miravalles",
    "iso:country":"ES",
    "sg:address":"Miravalles, 7",
    "sg:city":"Iru\u00f1a",
    "sg:orig_category":"Mercer\u00cda, Lencer\u00cda (al Por Menor)",
    "sg:phone":"+34 948 14 41 38",
    "sg:postcode":"31015",
    "sg:province":"Navarra",
    "wof:name":"Ramirez Noain Maria Carmen",
    "wof:placetype":"venue"
},
  "geometry": {"coordinates":[-1.6257940531,42.8300971985],"type":"Point"}
}