{
  "type": "Feature",
  "properties": {
    "iso:country":"ES",
    "sg:address":"Calle de Virgen De Lluc, 4",
    "sg:city":"Madrid",
    "sg:orig_category":"Persianas Interiores, Exteriores",
    "sg:phone":"+34 914 05 06 51",
    "sg:postcode":"28027",
    "sg:province":"Madrid",
    "wof:name":"Ye  Liping",
    "wof:placetype":"venue"
},
  "geometry": {"coordinates":[-3.6554985046,40.4345283508],"type":"Point"}
}