{
  "type": "Feature",
  "properties": {
    "addr:full":"Calle de Alejandro Vi, 4 Valencia Valencia 46005",
    "addr:housenumber":"4",
    "addr:postcode":"46005",
    "addr:street":"Calle De Alejandro Vi",
    "iso:country":"ES",
    "sg:address":"Calle de Alejandro Vi, 4",
    "sg:city":"Valencia",
    "sg:orig_category":"Inmobiliaria (agencias)",
    "sg:phone":"+34 963 73 56 81",
    "sg:postcode":"46005",
    "sg:province":"Valencia",
    "wof:name":"Arenos 2000 S.l.",
    "wof:placetype":"venue"
},
  "geometry": {"coordinates":[-0.364716202,39.4625740051],"type":"Point"}
}