{
  "type": "Feature",
  "properties": {
    "addr:full":"Calle de Arturo Soria, 307 Madrid Madrid 28033",
    "addr:housenumber":"307",
    "addr:postcode":"28033",
    "addr:street":"Calle De Arturo Soria",
    "iso:country":"ES",
    "sg:address":"Calle de Arturo Soria, 307",
    "sg:city":"Madrid",
    "sg:orig_category":"Carnicer\u00cdas, Carnicer\u00cdas",
    "sg:phone":"+34 913 02 82 73",
    "sg:postcode":"28033",
    "sg:province":"Madrid",
    "wof:name":"Hilario Garcia S.l.",
    "wof:placetype":"venue"
},
  "geometry": {"coordinates":[-3.6687505245,40.4786109924],"type":"Point"}
}