{
  "type": "Feature",
  "properties": {
    "iso:country":"ES",
    "sg:address":"Calle de Carretera De Almeria, 27",
    "sg:city":"Adra",
    "sg:orig_category":"Mec\u00c1nico Del Autom\u00d3vil",
    "sg:phone":"+34 950 56 05 20",
    "sg:postcode":"04770",
    "sg:province":"Almer\u00eda",
    "wof:name":"Autos Joseba S L L",
    "wof:placetype":"venue"
},
  "geometry": {"coordinates":[-2.998388052,36.7483940125],"type":"Point"}
}