{
  "type": "Feature",
  "properties": {
    "addr:full":"Carrer de Aristides Maillol, 3 Barcelona Barcelona 08028",
    "addr:housenumber":"3",
    "addr:postcode":"08028",
    "addr:street":"Carrer De Aristides Maillol",
    "iso:country":"ES",
    "sg:address":"Carrer de Aristides Maillol, 3",
    "sg:city":"Barcelona",
    "sg:orig_category":"Agencias Y Agentes Comerciales, Representantes",
    "sg:phone":"+34 934 48 95 00",
    "sg:postcode":"08028",
    "sg:province":"Barcelona",
    "wof:name":"Soportes Tecnicos S.a.",
    "wof:placetype":"venue"
},
  "geometry": {"coordinates":[2.120994091,41.3781929016],"type":"Point"}
}