{
  "type": "Feature",
  "properties": {
    "addr:full":"Avda Cuerpos De Obras Publicas, 4 Santo Domingo De La Calzada La Rioja 26250",
    "addr:housenumber":"4",
    "addr:postcode":"26250",
    "addr:street":"Avda Cuerpos;Santo;Calzada;Rioja",
    "iso:country":"ES",
    "sg:address":"Avda Cuerpos De Obras Publicas, 4",
    "sg:city":"Santo Domingo De La Calzada",
    "sg:orig_category":"Droguer\u00cdas (al Por Menor)",
    "sg:phone":"+34 941 34 28 46",
    "sg:postcode":"26250",
    "sg:province":"La Rioja",
    "wof:name":"Mendiola Ortega S.l.",
    "wof:placetype":"venue"
},
  "geometry": {"coordinates":[-2.9541339874,42.4394760132],"type":"Point"}
}