{
  "type": "Feature",
  "properties": {
    "iso:country":"ES",
    "sg:address":"Calle de Capitan Arenas, 8",
    "sg:city":"Guadalajara",
    "sg:orig_category":"Contables",
    "sg:phone":"+34 949 22 11 45",
    "sg:postcode":"19003",
    "sg:province":"Guadalajara",
    "wof:name":"Sanz Andres Carmelo",
    "wof:placetype":"venue"
},
  "geometry": {"coordinates":[-3.1658129692,40.6294250488],"type":"Point"}
}