{
  "type": "Feature",
  "properties": {
    "addr:full":"Calle de Jesus Del Gran Poder, 22 Madrid Madrid 28026",
    "addr:housenumber":"22",
    "addr:postcode":"madrid;28026",
    "addr:street":"Calle De Jesus Del Gran Poder",
    "iso:country":"ES",
    "sg:address":"Calle de Jesus Del Gran Poder, 22",
    "sg:city":"Madrid",
    "sg:orig_category":"Chapister\u00cda",
    "sg:phone":"+34 914 76 80 80",
    "sg:postcode":"28026",
    "sg:province":"Madrid",
    "wof:name":"Talleres Martin Vargas S.l.",
    "wof:placetype":"venue"
},
  "geometry": {"coordinates":[-3.7022941113,40.3873596191],"type":"Point"}
}