{
  "type": "Feature",
  "properties": {
    "addr:full":"Calle de Albeniz, 6 Cordoba C\u00f3rdoba 14005",
    "addr:housenumber":"6",
    "addr:postcode":"14005",
    "addr:street":"Calle De Albeniz;Co\u0301Rdoba",
    "iso:country":"ES",
    "sg:address":"Calle de Albeniz, 6",
    "sg:city":"Cordoba",
    "sg:orig_category":"Art\u00cdculos De Decoraci\u00d3n",
    "sg:phone":"+34 957 45 68 74",
    "sg:postcode":"14005",
    "sg:province":"C\u00f3rdoba",
    "wof:name":"Moral Sendra Jose Carlos",
    "wof:placetype":"venue"
},
  "geometry": {"coordinates":[-4.7896399498,37.884513855],"type":"Point"}
}