{
  "type": "Feature",
  "properties": {
    "addr:full":"Prol Tarragona, S/n Banyoles Girona 17820",
    "addr:postcode":"17820",
    "addr:street":"Prol Tarragona S / N",
    "iso:country":"ES",
    "sg:address":"Prol Tarragona, S/n",
    "sg:city":"Banyoles",
    "sg:orig_category":"Empresas De Pintura Y Revestimientos",
    "sg:phone":"+34 972 57 41 63",
    "sg:postcode":"17820",
    "sg:province":"Girona",
    "wof:name":"Latorre Jimeno Jose",
    "wof:placetype":"venue"
},
  "geometry": {"coordinates":[2.7734367847,42.1145095825],"type":"Point"}
}