{
  "type": "Feature",
  "properties": {
    "iso:country":"ES",
    "sg:address":"Calle de Ignacio Zuloaga, 2",
    "sg:city":"Velez-malaga",
    "sg:orig_category":"Ferreter\u00cda (diversos)",
    "sg:phone":"+34 952 54 96 64",
    "sg:postcode":"29700",
    "sg:province":"M\u00e1laga",
    "wof:name":"Ferrallados Hidalgo S.l.",
    "wof:placetype":"venue"
},
  "geometry": {"coordinates":[-4.0964241028,36.7623939514],"type":"Point"}
}