{
  "type": "Feature",
  "properties": {
    "iso:country":"ES",
    "sg:address":"Calle de Plata, 22",
    "sg:city":"Toledo",
    "sg:orig_category":"M\u00c9dicos: Cirug\u00cda General",
    "sg:phone":"+34 925 22 82 21",
    "sg:postcode":"45001",
    "sg:province":"Toledo",
    "wof:name":"Perea Garcia Miguel",
    "wof:placetype":"venue"
},
  "geometry": {"coordinates":[-4.0233259201,39.8591003418],"type":"Point"}
}