{
  "type": "Feature",
  "properties": {
    "addr:full":"Tiburzio Anitua Kalea, 23 Eibar Guip\u00f9zcoa 20600",
    "addr:housenumber":"23",
    "addr:postcode":"20600",
    "addr:street":"Tiburzio Anitua Kalea;Guipu\u0300Zcoa",
    "iso:country":"ES",
    "sg:address":"Tiburzio Anitua Kalea, 23",
    "sg:city":"Eibar",
    "sg:orig_category":"Carnicer\u00cdas, Carnicer\u00cdas",
    "sg:phone":"+34 943 70 16 91",
    "sg:postcode":"20600",
    "sg:province":"Guip\u00f9zcoa",
    "wof:name":"Barrutia Zabaleta Fernando",
    "wof:placetype":"venue"
},
  "geometry": {"coordinates":[-2.4861209393,43.1813812256],"type":"Point"}
}