{
  "type": "Feature",
  "properties": {
    "addr:full":"Calle de Hermanos Trueba, 59 Madrid Madrid 28018",
    "addr:housenumber":"59",
    "addr:postcode":"madrid;28018",
    "addr:street":"Calle De Hermanos Trueba",
    "iso:country":"ES",
    "sg:address":"Calle de Hermanos Trueba, 59",
    "sg:city":"Madrid",
    "sg:orig_category":"Mec\u00c1nico Del Autom\u00d3vil",
    "sg:phone":"+34 915 07 68 28",
    "sg:postcode":"28018",
    "sg:province":"Madrid",
    "sg:website":"www.jinesauto.com",
    "wof:name":"Gines Auto S.l.",
    "wof:placetype":"venue"
},
  "geometry": {"coordinates":[-3.6621239185,40.3866233826],"type":"Point"}
}