{
  "type": "Feature",
  "properties": {
    "addr:full":"Carrer de Cristofol Despuig (de), 23 Tortosa Tarragona 43500",
    "addr:housenumber":"23",
    "addr:postcode":"43500",
    "addr:street":"Carrer De Cristofol Despuig De",
    "iso:country":"ES",
    "sg:address":"Carrer de Cristofol Despuig (de), 23",
    "sg:city":"Tortosa",
    "sg:orig_category":"Servicios De Telecomunicaciones",
    "sg:phone":"+34 977 44 81 13",
    "sg:postcode":"43500",
    "sg:province":"Tarragona",
    "sg:website":"www.al-pi.com",
    "wof:name":"Catalana De Telecomunicaciones Societat Operadora De Xarnes S.a.",
    "wof:placetype":"venue"
},
  "geometry": {"coordinates":[0.5231099725,40.8088645935],"type":"Point"}
}