{
  "type": "Feature",
  "properties": {
    "addr:full":"Calle de De Los Carros, 12 Coria C\u00e1ceres 10800",
    "addr:housenumber":"12",
    "addr:postcode":"10800",
    "addr:street":"Calle De De Los Carros;Ca\u0301Ceres",
    "iso:country":"ES",
    "sg:address":"Calle de De Los Carros, 12",
    "sg:city":"Coria",
    "sg:orig_category":"Promotores Constructores",
    "sg:phone":"+34 927 50 44 29",
    "sg:postcode":"10800",
    "sg:province":"C\u00e1ceres",
    "wof:name":"Gomez Alonso Francisco Jose",
    "wof:placetype":"venue"
},
  "geometry": {"coordinates":[-6.5397224426,39.9866065979],"type":"Point"}
}