{
  "type": "Feature",
  "properties": {
    "addr:full":"Carr Santa Barbara, 11 Blanes Girona 17300",
    "addr:housenumber":"11",
    "addr:postcode":"17300",
    "addr:street":"Carr Santa Barbara",
    "iso:country":"ES",
    "sg:address":"Carr Santa Barbara, 11",
    "sg:city":"Blanes",
    "sg:orig_category":"\u00d3ptica: Instrumentos (fabricaci\u00d3n)",
    "sg:phone":"+34 972 35 06 73",
    "sg:postcode":"17300",
    "sg:province":"Girona",
    "wof:name":"Planells Torrent Salvador",
    "wof:placetype":"venue"
},
  "geometry": {"coordinates":[2.7917840481,41.6769599915],"type":"Point"}
}