{
  "type": "Feature",
  "properties": {
    "iso:country":"ES",
    "sg:address":"Calle de Cronista Martin Jimenez, 1",
    "sg:city":"Ecija",
    "sg:orig_category":"Producci\u00d3n, Distribuci\u00d3n De Electricidad",
    "sg:phone":"+34 954 83 12 04",
    "sg:postcode":"41400",
    "sg:province":"Sevilla",
    "wof:name":"Cantarero Fernandez Manuel",
    "wof:placetype":"venue"
},
  "geometry": {"coordinates":[-5.0799183846,37.5379676819],"type":"Point"}
}