{
  "type": "Feature",
  "properties": {
    "addr:full":"Calle de Artibai, 10 Ondarroa Vizcaya 48700",
    "addr:housenumber":"10",
    "addr:postcode":"48700",
    "addr:street":"Calle De Artibai",
    "iso:country":"ES",
    "sg:address":"Calle de Artibai, 10",
    "sg:city":"Ondarroa",
    "sg:orig_category":"Asociaciones, Organismos Culturales Y Socioeducativos",
    "sg:phone":"+34 946 83 21 69",
    "sg:postcode":"48700",
    "sg:province":"Vizcaya",
    "wof:name":"Uxola Kultur Elkartea",
    "wof:placetype":"venue"
},
  "geometry": {"coordinates":[-2.426803112,43.3191833496],"type":"Point"}
}