{
  "type": "Feature",
  "properties": {
    "addr:full":"Avenida De Cantabria, 22 Torrelavega Cantabria 39300",
    "addr:housenumber":"22",
    "addr:postcode":"39300",
    "addr:street":"Avenida De Cantabria",
    "iso:country":"ES",
    "sg:address":"Avenida De Cantabria, 22",
    "sg:city":"Torrelavega",
    "sg:orig_category":"Puertas Y Portales",
    "sg:phone":"+34 942 89 31 76",
    "sg:postcode":"39300",
    "sg:province":"Cantabria",
    "wof:name":"Borbolla Gutierrez Miguel",
    "wof:placetype":"venue"
},
  "geometry": {"coordinates":[-4.0537929535,43.3419151306],"type":"Point"}
}