{
  "type": "Feature",
  "properties": {
    "addr:full":"Carrer de Andrea Doria, 12 Palma Islas Baleares 07014",
    "addr:housenumber":"12",
    "addr:postcode":"07014",
    "addr:street":"Carrer De Andrea Doria",
    "iso:country":"ES",
    "sg:address":"Carrer de Andrea Doria, 12",
    "sg:city":"Palma",
    "sg:orig_category":"Herboristas (al Por Menor)",
    "sg:phone":"+34 971 73 24 71",
    "sg:postcode":"07014",
    "sg:province":"Islas Baleares",
    "wof:name":"Aguilera Molina Encarnacion",
    "wof:placetype":"venue"
},
  "geometry": {"coordinates":[2.6309485435,39.5706062317],"type":"Point"}
}