{
  "type": "Feature",
  "properties": {
    "iso:country":"ES",
    "sg:address":"Urb Vaguadas, 31",
    "sg:city":"Vaguadas",
    "sg:orig_category":"Ense\u00d1anza Variada",
    "sg:phone":"+34 924 26 85 69",
    "sg:postcode":"06010",
    "sg:province":"Badajoz",
    "sg:website":"www.asociaciongeografica.com",
    "wof:name":"Asociacion De Act.naturaleza Geografica",
    "wof:placetype":"venue"
},
  "geometry": {"coordinates":[-6.9702835083,38.8785972595],"type":"Point"}
}