{
  "type": "Feature",
  "properties": {
    "iso:country":"ES",
    "sg:address":"Plaz Santiago Arolo Vi\u00d1as, S/n",
    "sg:city":"Badajoz",
    "sg:orig_category":"Iglesia Cat\u00d3lica",
    "sg:phone":"+34 924 25 48 60",
    "sg:postcode":"06008",
    "sg:province":"Badajoz",
    "wof:name":"Parroquia De San Roque",
    "wof:placetype":"venue"
},
  "geometry": {"coordinates":[-6.9586439133,38.8806838989],"type":"Point"}
}