{
  "type": "Feature",
  "properties": {
    "addr:full":"Calle de Esteban Mora, 43 Madrid Madrid 28027",
    "addr:housenumber":"43",
    "addr:postcode":"madrid;28027",
    "addr:street":"Calle De Esteban Mora",
    "iso:country":"ES",
    "sg:address":"Calle de Esteban Mora, 43",
    "sg:city":"Madrid",
    "sg:orig_category":"Peluqueros: De Se\u00d1oras",
    "sg:phone":"+34 914 03 97 10",
    "sg:postcode":"28027",
    "sg:province":"Madrid",
    "wof:name":"Castillo Almansa Caridad",
    "wof:placetype":"venue"
},
  "geometry": {"coordinates":[-3.6542069912,40.4389038086],"type":"Point"}
}