{
  "type": "Feature",
  "properties": {
    "iso:country":"ES",
    "sg:address":"Calle de Monasterio De La Rabida, 4",
    "sg:city":"Rinconada",
    "sg:orig_category":"Gr\u00daas, Montacargas Y Elevadores Para Astilleros",
    "sg:phone":"+34 955 79 78 66",
    "sg:postcode":"41309",
    "sg:province":"Sevilla",
    "wof:name":"Rioja Perez Jose",
    "wof:placetype":"venue"
},
  "geometry": {"coordinates":[-5.9800591469,37.4917755127],"type":"Point"}
}