{
  "type": "Feature",
  "properties": {
    "iso:country":"ES",
    "sg:address":"Pla\u00c7 Marques De Camps, 5",
    "sg:city":"Girona",
    "sg:orig_category":"Juegos Y Juguetes (al Por Menor)",
    "sg:phone":"+34 972 20 07 47",
    "sg:postcode":"17001",
    "sg:province":"Girona",
    "wof:name":"Mili's Girona S. L.",
    "wof:placetype":"venue"
},
  "geometry": {"coordinates":[2.8191139698,41.9824714661],"type":"Point"}
}