{
  "type": "Feature",
  "properties": {
    "iso:country":"ES",
    "sg:address":"Calle de Luis Chamizo, 8",
    "sg:city":"Badajoz",
    "sg:orig_category":"Promotores Constructores",
    "sg:phone":"+34 924 27 28 09",
    "sg:postcode":"06006",
    "sg:province":"Badajoz",
    "wof:name":"Solis Recuero Josefa",
    "wof:placetype":"venue"
},
  "geometry": {"coordinates":[-6.9874286652,38.885307312],"type":"Point"}
}