{
  "type": "Feature",
  "properties": {
    "addr:full":"Calle de Alonso Garrote, 8 Astorga Le\u00f3n 24700",
    "addr:housenumber":"8",
    "addr:postcode":"24700",
    "addr:street":"Calle De Alonso Garrote;Leo\u0301N",
    "iso:country":"ES",
    "sg:address":"Calle de Alonso Garrote, 8",
    "sg:city":"Astorga",
    "sg:orig_category":"Electrodom\u00c9sticos (al Por Menor)",
    "sg:phone":"+34 987 61 53 05",
    "sg:postcode":"24700",
    "sg:province":"Le\u00f3n",
    "wof:name":"Electrodomesticos La Luna S.l.",
    "wof:placetype":"venue"
},
  "geometry": {"coordinates":[-6.0542502403,42.4554672241],"type":"Point"}
}