{
  "type": "Feature",
  "properties": {
    "addr:full":"Av Tres-cents Disset, 58 Castelldefels Barcelona 08860",
    "addr:housenumber":"58",
    "addr:postcode":"08860",
    "addr:street":"Av Tres-Cents Disset",
    "iso:country":"ES",
    "sg:address":"Av Tres-cents Disset, 58",
    "sg:city":"Castelldefels",
    "sg:orig_category":"Goma: Productos De Uso Industrial (fabricaci\u00d3n, Al Por Mayor)",
    "sg:phone":"+34 936 65 09 95",
    "sg:postcode":"08860",
    "sg:province":"Barcelona",
    "wof:name":"Manufacturados Espa\u00d1oles De Resinas Fluoradas S.l.",
    "wof:placetype":"venue"
},
  "geometry": {"coordinates":[1.9278570414,41.2629699707],"type":"Point"}
}