{
  "type": "Feature",
  "properties": {
    "addr:full":"Carrer de Enginyer Moncunill, 103 Hospitalet Llobregat Barcelona 08905",
    "addr:housenumber":"103",
    "addr:postcode":"08905",
    "addr:street":"Carrer De Enginyer Moncunill",
    "iso:country":"ES",
    "sg:address":"Carrer de Enginyer Moncunill, 103",
    "sg:city":"Hospitalet Llobregat",
    "sg:orig_category":"Iglesia Cat\u00d3lica",
    "sg:phone":"+34 934 40 07 45",
    "sg:postcode":"08905",
    "sg:province":"Barcelona",
    "wof:name":"Parroquia Nuestra Se\u00f1ora De La Luz",
    "wof:placetype":"venue"
},
  "geometry": {"coordinates":[2.1082201004,41.369644165],"type":"Point"}
}