{
  "type": "Feature",
  "properties": {
    "iso:country":"ES",
    "sg:address":"Doctor Huarte De San Juan, 5",
    "sg:city":"Estella",
    "sg:orig_category":"Arquitectos",
    "sg:phone":"+34 948 55 23 19",
    "sg:postcode":"31200",
    "sg:province":"Navarra",
    "wof:name":"Lezaun Munarriz Miguel",
    "wof:placetype":"venue"
},
  "geometry": {"coordinates":[-2.0352931023,42.6719322205],"type":"Point"}
}