{
  "type": "Feature",
  "properties": {
    "iso:country":"ES",
    "sg:address":"Calle de Mahora, 10",
    "sg:city":"Madrigueras",
    "sg:orig_category":"Ropa Para Caballeros (al Por Menor)",
    "sg:phone":"+34 967 48 41 96",
    "sg:postcode":"02230",
    "sg:province":"Albacete",
    "wof:name":"Atienzar Cantos Jose",
    "wof:placetype":"venue"
},
  "geometry": {"coordinates":[-1.7985085249,39.2366905212],"type":"Point"}
}