{
  "type": "Feature",
  "properties": {
    "addr:full":"Send Garres, 115 Garres Murcia 30158",
    "addr:housenumber":"115",
    "addr:postcode":"30158",
    "addr:street":"Send Garres",
    "iso:country":"ES",
    "sg:address":"Send Garres, 115",
    "sg:city":"Garres",
    "sg:orig_category":"Empresas De Carpinter\u00cda Met\u00c1lica",
    "sg:phone":"+34 968 87 38 84",
    "sg:postcode":"30158",
    "sg:province":"Murcia",
    "wof:name":"Carpinteria Metalica Regional C.b.",
    "wof:placetype":"venue"
},
  "geometry": {"coordinates":[-1.1302499771,37.9829597473],"type":"Point"}
}