{
  "type": "Feature",
  "properties": {
    "iso:country":"ES",
    "sg:address":"Musico Vicente Sanchiz, S/n",
    "sg:city":"Lorcha",
    "sg:orig_category":"Papel (al Por Mayor)",
    "sg:phone":"+34 965 51 25 06",
    "sg:postcode":"03860",
    "sg:province":"Alicante",
    "wof:name":"Servipapel S. L.",
    "wof:placetype":"venue"
},
  "geometry": {"coordinates":[-0.3088490069,38.8422431946],"type":"Point"}
}