{
  "type": "Feature",
  "properties": {
    "iso:country":"ES",
    "sg:address":"Calle de Jose Antonio, 35",
    "sg:city":"Galvez",
    "sg:orig_category":"Molduras, Junquillos, Listones Y Molduras Perforadas",
    "sg:phone":"+34 925 40 01 15",
    "sg:postcode":"45164",
    "sg:province":"Toledo",
    "wof:name":"Picaporte Merida Victor",
    "wof:placetype":"venue"
},
  "geometry": {"coordinates":[-4.2740058899,39.7031440735],"type":"Point"}
}