{
  "type": "Feature",
  "properties": {
    "iso:country":"ES",
    "sg:address":"Calle de Mornes, 14",
    "sg:city":"Zaragoza",
    "sg:orig_category":"Internados & Ense\u00d1anza Privada",
    "sg:phone":"+34 976 27 27 50",
    "sg:postcode":"50007",
    "sg:province":"Zaragoza",
    "wof:name":"Hijas De Maria Auxiliadora Instituto Salesianas De San Juan Bosco Inspectoria Nuestra Se\u00f1ora Del Pil",
    "wof:placetype":"venue"
},
  "geometry": {"coordinates":[-0.879998982,41.6361618042],"type":"Point"}
}