{
  "type": "Feature",
  "properties": {
    "addr:full":"Rua Albari\u00d1o (do), 20 Cambados Pontevedra 36630",
    "addr:housenumber":"20",
    "addr:postcode":"36630",
    "addr:street":"Rua Albarin\u0303O Do",
    "iso:country":"ES",
    "sg:address":"Rua Albari\u00d1o (do), 20",
    "sg:city":"Cambados",
    "sg:orig_category":"Art\u00cdculos De Decoraci\u00d3n",
    "sg:phone":"+34 986 52 44 76",
    "sg:postcode":"36630",
    "sg:province":"Pontevedra",
    "wof:name":"Santorum Jueguen Manuel",
    "wof:placetype":"venue"
},
  "geometry": {"coordinates":[-8.8142194748,42.5129051208],"type":"Point"}
}