{
  "type": "Feature",
  "properties": {
    "addr:full":"Calle de Puerta De Velez, 5 Almu\u00f1ecar Granada 18690",
    "addr:housenumber":"5",
    "addr:postcode":"18690",
    "addr:street":"Calle De Puerta De Velez",
    "iso:country":"ES",
    "sg:address":"Calle de Puerta De Velez, 5",
    "sg:city":"Almu\u00f1ecar",
    "sg:orig_category":"Estilistas Y Estudios De Estilo De Corte Y Confecci\u00d3n",
    "sg:phone":"+34 958 63 90 58",
    "sg:postcode":"18690",
    "sg:province":"Granada",
    "wof:name":"Gomez Carmona Dolores",
    "wof:placetype":"venue"
},
  "geometry": {"coordinates":[-3.6930320263,36.7336921692],"type":"Point"}
}