{
  "type": "Feature",
  "properties": {
    "addr:full":"Pg Elx, 43 Crevillent Alicante 03330",
    "addr:housenumber":"43",
    "addr:postcode":"03330",
    "addr:street":"Pg Elx",
    "iso:country":"ES",
    "sg:address":"Pg Elx, 43",
    "sg:city":"Crevillent",
    "sg:orig_category":"Productos Qu\u00cdmicos (fabricaci\u00d3n, Al Por Mayor)",
    "sg:phone":"+34 965 40 48 03",
    "sg:postcode":"03330",
    "sg:province":"Alicante",
    "wof:name":"Brugues S.a.",
    "wof:placetype":"venue"
},
  "geometry": {"coordinates":[-0.801379025,38.2479705811],"type":"Point"}
}