{
  "type": "Feature",
  "properties": {
    "addr:full":"Carrer de Santa Joaquima De Vedruna, 10 Tarragona Tarragona 43002",
    "addr:housenumber":"10",
    "addr:postcode":"43002",
    "addr:street":"Carrer De Santa Joaquima De Vedruna",
    "iso:country":"ES",
    "sg:address":"Carrer de Santa Joaquima De Vedruna, 10",
    "sg:city":"Tarragona",
    "sg:orig_category":"Internados & Ense\u00d1anza Privada",
    "sg:phone":"+34 977 21 79 79",
    "sg:postcode":"43002",
    "sg:province":"Tarragona",
    "wof:name":"Fundacio Cultural Privada Sagrat Cor De Jesus",
    "wof:placetype":"venue"
},
  "geometry": {"coordinates":[1.2484029531,41.120765686],"type":"Point"}
}