{
  "type": "Feature",
  "properties": {
    "iso:country":"ES",
    "sg:address":"Plaz Pinazo, S/n",
    "sg:city":"Madrid",
    "sg:orig_category":"Carnicer\u00cdas, Carnicer\u00cdas",
    "sg:phone":"+34 917 96 09 05",
    "sg:postcode":"28021",
    "sg:province":"Madrid",
    "wof:name":"Jimenez Dominguez Juan Jose",
    "wof:placetype":"venue"
},
  "geometry": {"coordinates":[-3.6910290718,40.3425483704],"type":"Point"}
}