{
  "type": "Feature",
  "properties": {
    "iso:country":"ES",
    "sg:address":"Pol Ind Sentbenet Baix, 26",
    "sg:city":"Alcoi",
    "sg:orig_category":"Electricidad: Equipos Industriales, Componentes (fabricaci\u00d3n)",
    "sg:phone":"+34 965 33 67 66",
    "sg:postcode":"03804",
    "sg:province":"Alicante",
    "wof:name":"Luis Molina Miro S.l.",
    "wof:placetype":"venue"
},
  "geometry": {"coordinates":[-0.4732739925,38.6984100342],"type":"Point"}
}