{
  "type": "Feature",
  "properties": {
    "iso:country":"ES",
    "sg:address":"Calle de Luis Cabrera, 34",
    "sg:city":"Madrid",
    "sg:orig_category":"Procuradores",
    "sg:phone":"+34 915 64 89 09",
    "sg:postcode":"28002",
    "sg:province":"Madrid",
    "wof:name":"Moya Gomez Eduardo",
    "wof:placetype":"venue"
},
  "geometry": {"coordinates":[-3.6755769253,40.4420204163],"type":"Point"}
}