{
  "type": "Feature",
  "properties": {
    "iso:country":"ES",
    "sg:address":"Calle de San Miguel, 31",
    "sg:city":"Orkoien",
    "sg:orig_category":"Iglesia Cat\u00d3lica",
    "sg:phone":"+34 948 32 53 82",
    "sg:postcode":"31160",
    "sg:province":"Navarra",
    "wof:name":"Parroquia De San Miguel De Orcoyen",
    "wof:placetype":"venue"
},
  "geometry": {"coordinates":[-1.7087730169,42.8247947693],"type":"Point"}
}