{
  "type": "Feature",
  "properties": {
    "iso:country":"ES",
    "sg:address":"Ctra Vic, 211",
    "sg:city":"Manresa",
    "sg:orig_category":"Equipos De Marcado, Etiquetado",
    "sg:phone":"+34 938 74 80 25",
    "sg:postcode":"08243",
    "sg:province":"Barcelona",
    "sg:website":"www-vinil4.com",
    "wof:name":"Vinil-4 S.l.",
    "wof:placetype":"venue"
},
  "geometry": {"coordinates":[1.8389159441,41.7335472107],"type":"Point"}
}