{
  "type": "Feature",
  "properties": {
    "addr:full":"Puerto De Denia, S/n Denia Alicante 03700",
    "addr:housenumber":"s / n",
    "addr:postcode":"03700",
    "addr:street":"Puerto De Denia",
    "iso:country":"ES",
    "sg:address":"Puerto De Denia, S/n",
    "sg:city":"Denia",
    "sg:orig_category":"Deportes N\u00c1uticos, Acu\u00c1ticos Y Subacu\u00c1ticos: Art\u00cdculos Y Equipo (al Por Menor)",
    "sg:phone":"+34 966 42 50 09",
    "sg:postcode":"03700",
    "sg:province":"Alicante",
    "sg:website":"www.juanbelliure.com",
    "wof:name":"Andrea Yates S.l.",
    "wof:placetype":"venue"
},
  "geometry": {"coordinates":[0.1142399013,38.8410758972],"type":"Point"}
}