{
  "type": "Feature",
  "properties": {
    "addr:full":"Carr Arago, 79 Eivissa Islas Baleares 07800",
    "addr:housenumber":"79",
    "addr:postcode":"07800",
    "addr:street":"Carr Arago",
    "iso:country":"ES",
    "sg:address":"Carr Arago, 79",
    "sg:city":"Eivissa",
    "sg:orig_category":"Peluqueros: De Se\u00d1oras",
    "sg:phone":"+34 971 30 66 69",
    "sg:postcode":"07800",
    "sg:province":"Islas Baleares",
    "wof:name":"Peluqueria Bellver S.l.",
    "wof:placetype":"venue"
},
  "geometry": {"coordinates":[1.4259699583,38.9079055786],"type":"Point"}
}