{
  "type": "Feature",
  "properties": {
    "iso:country":"ES",
    "sg:address":"Calle de Almas, 67",
    "sg:city":"Benaguasil",
    "sg:orig_category":"Cl\u00cdnicas Dentales",
    "sg:phone":"+34 962 73 01 01",
    "sg:postcode":"46180",
    "sg:province":"Valencia",
    "wof:name":"Correcher Parras Francisco Javier",
    "wof:placetype":"venue"
},
  "geometry": {"coordinates":[-0.6156793833,39.5933952332],"type":"Point"}
}