{
  "type": "Feature",
  "properties": {
    "iso:country":"ES",
    "sg:address":"Carrer de Enric Granados, 111",
    "sg:city":"Barcelona",
    "sg:orig_category":"Psic\u00d3logos",
    "sg:phone":"+34 934 16 00 23",
    "sg:postcode":"08008",
    "sg:province":"Barcelona",
    "wof:name":"Alvarez Ramos Mercedes",
    "wof:placetype":"venue"
},
  "geometry": {"coordinates":[2.1554033756,41.3930625916],"type":"Point"}
}