{
  "type": "Feature",
  "properties": {
    "addr:full":"Calle de San Gregorio, 15 Madrid Madrid 28004",
    "addr:housenumber":"15",
    "addr:postcode":"madrid;28004",
    "addr:street":"Calle De San Gregorio",
    "iso:country":"ES",
    "sg:address":"Calle de San Gregorio, 15",
    "sg:city":"Madrid",
    "sg:orig_category":"Institutos De Belleza",
    "sg:phone":"+34 913 19 53 38",
    "sg:postcode":"28004",
    "sg:province":"Madrid",
    "sg:website":"www.globallasercorporal.com",
    "wof:name":"Global Laser Corporal S.c.",
    "wof:placetype":"venue"
},
  "geometry": {"coordinates":[-3.6972770691,40.4239082336],"type":"Point"}
}