{
  "type": "Feature",
  "properties": {
    "iso:country":"ES",
    "sg:address":"Sostoa-tarren Kalea, 6",
    "sg:city":"Eibar",
    "sg:orig_category":"Tiendas De Grano, Frutas Y Legumbres Secas (al Por Menor)",
    "sg:phone":"+34 943 20 70 42",
    "sg:postcode":"20600",
    "sg:province":"Guip\u00f9zcoa",
    "wof:name":"Corbillon Nanin Octavio",
    "wof:placetype":"venue"
},
  "geometry": {"coordinates":[-2.4738481045,43.1822471619],"type":"Point"}
}