{
  "type": "Feature",
  "properties": {
    "addr:full":"Calle de Arzobispo Sanchis, 68 Alginet Valencia 46230",
    "addr:housenumber":"68",
    "addr:postcode":"46230",
    "addr:street":"Calle De Arzobispo Sanchis",
    "iso:country":"ES",
    "sg:address":"Calle de Arzobispo Sanchis, 68",
    "sg:city":"Alginet",
    "sg:orig_category":"Promotores Constructores",
    "sg:phone":"+34 961 75 07 67",
    "sg:postcode":"46230",
    "sg:province":"Valencia",
    "wof:name":"Martinez Llin Alejandro",
    "wof:placetype":"venue"
},
  "geometry": {"coordinates":[-0.4661107063,39.2616691589],"type":"Point"}
}