{
  "type": "Feature",
  "properties": {
    "addr:full":"Avda Reina Mercedes, 59 Sevilla Sevilla 41012",
    "addr:housenumber":"59",
    "addr:postcode":"41012",
    "addr:street":"Avda Reina Mercedes",
    "iso:country":"ES",
    "sg:address":"Avda Reina Mercedes, 59",
    "sg:city":"Sevilla",
    "sg:orig_category":"Cajas De Ahorro",
    "sg:phone":"+34 954 61 76 35",
    "sg:postcode":"41012",
    "sg:province":"Sevilla",
    "wof:name":"Caja De Ahorros Y Monte De Piedad De Cordoba",
    "wof:placetype":"venue"
},
  "geometry": {"coordinates":[-5.9860501289,37.3569412231],"type":"Point"}
}