{
  "type": "Feature",
  "properties": {
    "addr:full":"Calle de Benitez, 2 Campanario Badajoz 06460",
    "addr:housenumber":"2",
    "addr:postcode":"06460",
    "addr:street":"Calle De Benitez",
    "iso:country":"ES",
    "sg:address":"Calle de Benitez, 2",
    "sg:city":"Campanario",
    "sg:orig_category":"Asesor\u00cda Fiscal Y Jur\u00cddica",
    "sg:phone":"+34 924 83 12 12",
    "sg:postcode":"06460",
    "sg:province":"Badajoz",
    "wof:name":"Diaz Diaz Antonio Ventura",
    "wof:placetype":"venue"
},
  "geometry": {"coordinates":[-5.61805439,38.8632011414],"type":"Point"}
}