{
  "type": "Feature",
  "properties": {
    "addr:full":"Carr Josep Maria Sert, 10 Badalona Barcelona 08911",
    "addr:housenumber":"10",
    "addr:postcode":"08911",
    "addr:street":"Carr Josep Maria Sert",
    "iso:country":"ES",
    "sg:address":"Carr Josep Maria Sert, 10",
    "sg:city":"Badalona",
    "sg:orig_category":"Albergues",
    "sg:phone":"+34 933 84 46 91",
    "sg:postcode":"08911",
    "sg:province":"Barcelona",
    "wof:name":"Madness S. A.",
    "wof:placetype":"venue"
},
  "geometry": {"coordinates":[2.2626199722,41.4595718384],"type":"Point"}
}