{
  "type": "Feature",
  "properties": {
    "addr:full":"Plaz Rey (del), 8 Cartagena Murcia 30201",
    "addr:postcode":"30201",
    "addr:street":"Plaz;Del",
    "iso:country":"ES",
    "sg:address":"Plaz Rey (del), 8",
    "sg:city":"Cartagena",
    "sg:orig_category":"Abogados",
    "sg:phone":"+34 968 52 36 11",
    "sg:postcode":"30201",
    "sg:province":"Murcia",
    "wof:name":"Delegido Carrion Estanislao",
    "wof:placetype":"venue"
},
  "geometry": {"coordinates":[-0.8610739708,37.719329834],"type":"Point"}
}