{
  "type": "Feature",
  "properties": {
    "iso:country":"ES",
    "sg:address":"Calle de Blas Infante, 7",
    "sg:city":"Fuente",
    "sg:orig_category":"Empresas De Desmonte",
    "sg:phone":"+34 950 46 40 27",
    "sg:postcode":"04640",
    "sg:province":"Almer\u00eda",
    "wof:name":"Cuenca Cano Francisco",
    "wof:placetype":"venue"
},
  "geometry": {"coordinates":[-1.7492389679,37.3914604187],"type":"Point"}
}