{
  "type": "Feature",
  "properties": {
    "iso:country":"ES",
    "sg:address":"Desvio Distante, S/n",
    "sg:city":"Huercal Almeria",
    "sg:orig_category":"Desinfecci\u00d3n, Desinsectaci\u00d3n, Desratizaci\u00d3n",
    "sg:phone":"+34 950 30 33 86",
    "sg:postcode":"04230",
    "sg:province":"Almer\u00eda",
    "wof:name":"Insecticidas Quipons S.l.",
    "wof:placetype":"venue"
},
  "geometry": {"coordinates":[-2.4370388985,36.8798294067],"type":"Point"}
}