{
  "type": "Feature",
  "properties": {
    "iso:country":"ES",
    "sg:address":"Calle de Alcalde Martinez De La Ossa, 2",
    "sg:city":"Albacete",
    "sg:orig_category":"Deportes Diversos",
    "sg:phone":"+34 967 52 15 46",
    "sg:postcode":"02001",
    "sg:province":"Albacete",
    "wof:name":"Federacion Castellano Manchega De Tiro Olimpico De Albacete",
    "wof:placetype":"venue"
},
  "geometry": {"coordinates":[-1.8527542353,38.9985656738],"type":"Point"}
}