{
  "type": "Feature",
  "properties": {
    "addr:full":"Calle de San Roque, 20 Zaragoza Zaragoza 50010",
    "addr:housenumber":"20",
    "addr:postcode":"50010",
    "addr:street":"Calle De San Roque",
    "iso:country":"ES",
    "sg:address":"Calle de San Roque, 20",
    "sg:city":"Zaragoza",
    "sg:orig_category":"Bares, Piano",
    "sg:phone":"+34 976 30 65 64",
    "sg:postcode":"50010",
    "sg:province":"Zaragoza",
    "wof:name":"Tt Informatica",
    "wof:placetype":"venue"
},
  "geometry": {"coordinates":[-0.9028499722,41.651550293],"type":"Point"}
}