{
  "type": "Feature",
  "properties": {
    "addr:full":"Moli, 59 Museros Valencia 46136",
    "addr:housenumber":"59",
    "addr:postcode":"46136",
    "addr:street":"Moli",
    "iso:country":"ES",
    "sg:address":"Moli, 59",
    "sg:city":"Museros",
    "sg:orig_category":"Promotores Constructores",
    "sg:phone":"+34 961 44 43 85",
    "sg:postcode":"46136",
    "sg:province":"Valencia",
    "wof:name":"Villes De Museros S.l.",
    "wof:placetype":"venue"
},
  "geometry": {"coordinates":[-0.3432089984,39.5621795654],"type":"Point"}
}