{
  "type": "Feature",
  "properties": {
    "addr:full":"Los Linares, 8 Jimenez Jamuz Le\u00f3n 24767",
    "addr:housenumber":"8",
    "addr:postcode":"24767",
    "addr:street":"Los Linares;Leo\u0301N",
    "iso:country":"ES",
    "sg:address":"Los Linares, 8",
    "sg:city":"Jimenez Jamuz",
    "sg:orig_category":"T\u00c9cnicos Veterinarios",
    "sg:phone":"+34 987 66 42 41",
    "sg:postcode":"24767",
    "sg:province":"Le\u00f3n",
    "wof:name":"Manovel Lopez Enrique",
    "wof:placetype":"venue"
},
  "geometry": {"coordinates":[-5.9310421944,42.2663192749],"type":"Point"}
}