{
  "type": "Feature",
  "properties": {
    "addr:full":"Calle de Manuel Uribe, 12 Madrid Madrid 28033",
    "addr:housenumber":"12",
    "addr:postcode":"madrid;28033",
    "addr:street":"Calle De Manuel Uribe",
    "iso:country":"ES",
    "sg:address":"Calle de Manuel Uribe, 12",
    "sg:city":"Madrid",
    "sg:orig_category":"Laboratorios Farmac\u00c9uticos",
    "sg:phone":"+34 913 88 38 80",
    "sg:postcode":"28033",
    "sg:province":"Madrid",
    "wof:name":"Montaner Garcia Joaquin",
    "wof:placetype":"venue"
},
  "geometry": {"coordinates":[-3.6610090733,40.4642295837],"type":"Point"}
}