{
  "type": "Feature",
  "properties": {
    "addr:full":"Calle de Kanpatorrosteta Kalea, 9 Durango Vizcaya 48200",
    "addr:housenumber":"9",
    "addr:postcode":"48200",
    "addr:street":"Calle De Kanpatorrosteta Kalea",
    "iso:country":"ES",
    "sg:address":"Calle de Kanpatorrosteta Kalea, 9",
    "sg:city":"Durango",
    "sg:orig_category":"Tintorer\u00cdas, Limpieza En Seco",
    "sg:phone":"+34 946 21 84 18",
    "sg:postcode":"48200",
    "sg:province":"Vizcaya",
    "wof:name":"Loizate Soloeta I\u00f1aki",
    "wof:placetype":"venue"
},
  "geometry": {"coordinates":[-2.6300799847,43.1681289673],"type":"Point"}
}