{
  "type": "Feature",
  "properties": {
    "addr:full":"Calle de Joaquin De La Torre, 3 Huelva Huelva 21004",
    "addr:housenumber":"3",
    "addr:postcode":"21004",
    "addr:street":"Calle De Joaquin De La Torre",
    "iso:country":"ES",
    "sg:address":"Calle de Joaquin De La Torre, 3",
    "sg:city":"Huelva",
    "sg:orig_category":"Impuestos, Tesoro P\u00dablico",
    "sg:phone":"+34 959 23 72 20",
    "sg:postcode":"21004",
    "sg:province":"Huelva",
    "wof:name":"Garcia Maestre Jose",
    "wof:placetype":"venue"
},
  "geometry": {"coordinates":[-6.9410037994,37.2570114136],"type":"Point"}
}