{
  "type": "Feature",
  "properties": {
    "addr:full":"Pol Ind Las Vi\u00f1as, S/n Orellana Vieja Badajoz 06740",
    "addr:housenumber":"/ n",
    "addr:postcode":"06740",
    "addr:street":"Vin\u0303As S",
    "iso:country":"ES",
    "sg:address":"Pol Ind Las Vi\u00f1as, S/n",
    "sg:city":"Orellana Vieja",
    "sg:orig_category":"Cerrajer\u00cda, Ferrallista",
    "sg:phone":"+34 924 86 67 76",
    "sg:postcode":"06740",
    "sg:province":"Badajoz",
    "wof:name":"Talleres Siberia Extreme\u00f1a S.l.",
    "wof:placetype":"venue"
},
  "geometry": {"coordinates":[-5.5316791534,39.0018997192],"type":"Point"}
}