{
  "type": "Feature",
  "properties": {
    "addr:full":"Carrer de Mossen Jaume Sala, 1 Mataro Barcelona 08302",
    "addr:housenumber":"1",
    "addr:postcode":"08302",
    "addr:street":"Carrer De Mossen Jaume Sala",
    "iso:country":"ES",
    "sg:address":"Carrer de Mossen Jaume Sala, 1",
    "sg:city":"Mataro",
    "sg:orig_category":"Molduras, Junquillos, Listones Y Molduras Perforadas",
    "sg:phone":"+34 937 99 23 04",
    "sg:postcode":"08302",
    "sg:province":"Barcelona",
    "wof:name":"Gonzalez Martorell Monserrat",
    "wof:placetype":"venue"
},
  "geometry": {"coordinates":[2.4439051151,41.5415153503],"type":"Point"}
}