{
  "type": "Feature",
  "properties": {
    "addr:full":"Calle de Fuenterrabia, 38 Donostia-san Sebastian Guip\u00f9zcoa 20005",
    "addr:housenumber":"38",
    "addr:postcode":"20005",
    "addr:street":"Calle De Fuenterrabia",
    "iso:country":"ES",
    "sg:address":"Calle de Fuenterrabia, 38",
    "sg:city":"Donostia-san Sebastian",
    "sg:orig_category":"Agencias Y Asesores De Publicidad",
    "sg:phone":"+34 943 47 20 00",
    "sg:postcode":"20005",
    "sg:province":"Guip\u00f9zcoa",
    "wof:name":"Bi An Bi Donosti S.l.",
    "wof:placetype":"venue"
},
  "geometry": {"coordinates":[-1.9808950424,43.3167686462],"type":"Point"}
}