{
  "type": "Feature",
  "properties": {
    "iso:country":"ES",
    "sg:address":"General Morales, 5",
    "sg:city":"Arjona",
    "sg:orig_category":"M\u00c9dicos: Estomatolog\u00cda",
    "sg:phone":"+34 953 52 38 41",
    "sg:postcode":"23760",
    "sg:province":"Ja\u00e9n",
    "wof:name":"Feliz Beltre Marisa Antonia",
    "wof:placetype":"venue"
},
  "geometry": {"coordinates":[-4.0537018776,37.9369125366],"type":"Point"}
}