{
  "type": "Feature",
  "properties": {
    "iso:country":"ES",
    "sg:address":"Calle de Santa Cruz, 8",
    "sg:city":"Ecija",
    "sg:orig_category":"Promotores Constructores",
    "sg:phone":"+34 955 90 42 48",
    "sg:postcode":"41400",
    "sg:province":"Sevilla",
    "wof:name":"Amador Millan Eduardo",
    "wof:placetype":"venue"
},
  "geometry": {"coordinates":[-5.0804371834,37.5424995422],"type":"Point"}
}