{
  "type": "Feature",
  "properties": {
    "iso:country":"ES",
    "sg:address":"Calle de San Basilio, 28",
    "sg:city":"Cordoba",
    "sg:orig_category":"Iglesia Cat\u00d3lica",
    "sg:phone":"+34 957 29 33 95",
    "sg:postcode":"14004",
    "sg:province":"C\u00f3rdoba",
    "wof:name":"Parroquia Nuestra Se\u00f1ora De La Paz",
    "wof:placetype":"venue"
},
  "geometry": {"coordinates":[-4.7841992378,37.8762207031],"type":"Point"}
}