{
  "type": "Feature",
  "properties": {
    "addr:full":"Calle de Generalisimo, 34 Santa Cruz Del Retamar Toledo 45513",
    "addr:housenumber":"34",
    "addr:postcode":"45513",
    "addr:street":"Calle De Generalisimo",
    "iso:country":"ES",
    "sg:address":"Calle de Generalisimo, 34",
    "sg:city":"Santa Cruz Del Retamar",
    "sg:classifiers":[
        {
            "category":"Manufacturing",
            "subcategory":"Building Materials",
            "type":"Manufacturing & Wholesale Goods"
        }
    ],
    "sg:phone":"+34 925 79 42 64",
    "sg:postcode":"45513",
    "sg:province":"Toledo",
    "sg:tags":[
        "cemento",
        "y",
        "de",
        "fabricaci\u00d3n",
        "cal"
    ],
    "wof:name":"Martin Fernandez Jesus",
    "wof:placetype":"venue"
},
  "geometry": {"coordinates":[-4.2381267548,40.1189079285],"type":"Point"}
}