{
  "type": "Feature",
  "properties": {
    "addr:full":"Crta. Sampayo-barxelas, S/n Carballal Ourense 32357",
    "addr:housenumber":"s",
    "addr:postcode":"32357",
    "addr:street":"Crta. Sampayo-Barxelas;/ N",
    "iso:country":"ES",
    "sg:address":"Crta. Sampayo-barxelas, S/n",
    "sg:city":"Carballal",
    "sg:orig_category":"Asesor\u00cda Sobre Comunicaci\u00d3n De Empresas",
    "sg:phone":"+34 988 31 12 51",
    "sg:postcode":"32357",
    "sg:province":"Ourense",
    "wof:name":"Brion S.a.",
    "wof:placetype":"venue"
},
  "geometry": {"coordinates":[-7.0962882042,42.3699989319],"type":"Point"}
}