{
  "type": "Feature",
  "properties": {
    "iso:country":"ES",
    "sg:address":"Calle de Cervantes, 78",
    "sg:city":"Mairena Alcor",
    "sg:orig_category":"Contenedores (mercanc\u00cdas)",
    "sg:phone":"+34 955 74 65 94",
    "sg:postcode":"41510",
    "sg:province":"Sevilla",
    "wof:name":"Transportes Juanje S.l.",
    "wof:placetype":"venue"
},
  "geometry": {"coordinates":[-5.7573637962,37.3717079163],"type":"Point"}
}