{
  "type": "Feature",
  "properties": {
    "iso:country":"ES",
    "sg:address":"Pl Quince Agosto, 7",
    "sg:city":"Palma Condado",
    "sg:orig_category":"Producci\u00d3n, Distribuci\u00d3n De Gas Butano Y Propano",
    "sg:phone":"+34 959 40 18 21",
    "sg:postcode":"21700",
    "sg:province":"Huelva",
    "wof:name":"Butagas 2000s.l.",
    "wof:placetype":"venue"
},
  "geometry": {"coordinates":[-6.556842804,37.3890342712],"type":"Point"}
}