{
  "type": "Feature",
  "properties": {
    "addr:full":"Carrer de Dalt/alcalde Saturnino Pujadas, 78 Roca Valles Barcelona 08430",
    "addr:housenumber":"78",
    "addr:postcode":"08430",
    "addr:street":"Carrer De;/ Alcalde Saturnino Pujadas;Barcelona",
    "iso:country":"ES",
    "sg:address":"Carrer de Dalt/alcalde Saturnino Pujadas, 78",
    "sg:city":"Roca Valles",
    "sg:orig_category":"Bordado, Marcado A Medida",
    "sg:phone":"+34 938 42 42 25",
    "sg:postcode":"08430",
    "sg:province":"Barcelona",
    "sg:website":"www.brodatslaroca.com",
    "wof:name":"Brodats La Roca S.l.",
    "wof:placetype":"venue"
},
  "geometry": {"coordinates":[2.3268830776,41.5907287598],"type":"Point"}
}