{
  "type": "Feature",
  "properties": {
    "addr:full":"Serra Perenxisa, 20 Aldaia Valencia 46960",
    "addr:housenumber":"20",
    "addr:postcode":"46960",
    "addr:street":"Perenxisa",
    "iso:country":"ES",
    "sg:address":"Serra Perenxisa, 20",
    "sg:city":"Aldaia",
    "sg:orig_category":"Vidrio, Fabricaci\u00d3n Y Comercio",
    "sg:phone":"+34 961 98 84 45",
    "sg:postcode":"46960",
    "sg:province":"Valencia",
    "wof:name":"Crisdur S.l.",
    "wof:placetype":"venue"
},
  "geometry": {"coordinates":[-0.4661409855,39.4723968506],"type":"Point"}
}