{
  "type": "Feature",
  "properties": {
    "addr:full":"Calle de Juan Ramon Jimenez, 8 Santiago Ribera Murcia 30720",
    "addr:housenumber":"8",
    "addr:postcode":"30720",
    "addr:street":"Calle De Juan Ramon Jimenez",
    "iso:country":"ES",
    "sg:address":"Calle de Juan Ramon Jimenez, 8",
    "sg:city":"Santiago Ribera",
    "sg:orig_category":"Material Y Suministros Para Horticultura, Arboricultura",
    "sg:phone":"+34 968 19 51 25",
    "sg:postcode":"30720",
    "sg:province":"Murcia",
    "wof:name":"Lonja Mar Menor S.l.",
    "wof:placetype":"venue"
},
  "geometry": {"coordinates":[-0.8063409925,37.7991600037],"type":"Point"}
}