{
  "type": "Feature",
  "properties": {
    "addr:full":"Calle de Magnus Blikstad, 43 Gijon Asturias 33207",
    "addr:housenumber":"43",
    "addr:postcode":"33207",
    "addr:street":"Calle De Magnus Blikstad",
    "iso:country":"ES",
    "sg:address":"Calle de Magnus Blikstad, 43",
    "sg:city":"Gijon",
    "sg:orig_category":"Agencias Y Agentes Comerciales, Representantes",
    "sg:phone":"+34 985 34 84 04",
    "sg:postcode":"33207",
    "sg:province":"Asturias",
    "wof:name":"Comercial Martinez Y Castro S. L.",
    "wof:placetype":"venue"
},
  "geometry": {"coordinates":[-5.668115139,43.5367736816],"type":"Point"}
}