{
  "type": "Feature",
  "properties": {
    "iso:country":"ES",
    "sg:address":"Calle de Pio Xii, 13",
    "sg:city":"Santiago El Mayor",
    "sg:orig_category":"M\u00c9dicos: Estomatolog\u00cda",
    "sg:phone":"+34 968 34 17 50",
    "sg:postcode":"30012",
    "sg:province":"Murcia",
    "wof:name":"Santana De Garcia Ana Rosaura",
    "wof:placetype":"venue"
},
  "geometry": {"coordinates":[-1.1225060225,37.9720153809],"type":"Point"}
}