{
  "type": "Feature",
  "properties": {
    "iso:country":"ES",
    "sg:address":"Avda Perez Galdos, 45",
    "sg:city":"Valencia",
    "sg:orig_category":"M\u00c9dicos: Otorrinolaringolog\u00cda",
    "sg:phone":"+34 963 85 74 58",
    "sg:postcode":"46018",
    "sg:province":"Valencia",
    "wof:name":"Mallea Ca\u00f1izares Ismael",
    "wof:placetype":"venue"
},
  "geometry": {"coordinates":[-0.3895959854,39.4658813477],"type":"Point"}
}