{
  "type": "Feature",
  "properties": {
    "addr:full":"Carrer de Lope De Vega, 269 Barcelona Barcelona 08018",
    "addr:housenumber":"269",
    "addr:postcode":"08018",
    "addr:street":"Carrer De Lope De Vega",
    "iso:country":"ES",
    "sg:address":"Carrer de Lope De Vega, 269",
    "sg:city":"Barcelona",
    "sg:orig_category":"Mec\u00c1nico Del Autom\u00d3vil",
    "sg:phone":"+34 933 07 16 17",
    "sg:postcode":"08018",
    "sg:province":"Barcelona",
    "wof:name":"E.f.e.m. Autotalleres S.l.",
    "wof:placetype":"venue"
},
  "geometry": {"coordinates":[2.1938319206,41.4116020203],"type":"Point"}
}