{
  "type": "Feature",
  "properties": {
    "iso:country":"ES",
    "sg:address":"Pereiro Nuevo, S/n",
    "sg:city":"Mezquita",
    "sg:orig_category":"Autob\u00das (explotaci\u00d3n Y Servicios De)",
    "sg:phone":"+34 988 42 55 95",
    "sg:postcode":"32549",
    "sg:province":"Ourense",
    "wof:name":"Perez Giralda Marcelino",
    "wof:placetype":"venue"
},
  "geometry": {"coordinates":[-7.0450391769,42.010925293],"type":"Point"}
}