{
  "type": "Feature",
  "properties": {
    "addr:full":"Rua Franco (do), 14 Santiago De Compostela La Coru\u00f1a 15702",
    "addr:housenumber":"14",
    "addr:postcode":"15702",
    "addr:street":"Rua Franco Do;Corun\u0303A",
    "iso:country":"ES",
    "sg:address":"Rua Franco (do), 14",
    "sg:city":"Santiago De Compostela",
    "sg:orig_category":"Bisuter\u00cda, Joyer\u00cda, Relojer\u00cda (al Por Menor)",
    "sg:phone":"+34 981 58 32 52",
    "sg:postcode":"15702",
    "sg:province":"La Coru\u00f1a",
    "wof:name":"Porto Mella Jesus",
    "wof:placetype":"venue"
},
  "geometry": {"coordinates":[-8.5452594757,42.8785896301],"type":"Point"}
}