{
  "type": "Feature",
  "properties": {
    "addr:full":"Rua Irmans Fdez Alvarez, 25 Verin Ourense 32600",
    "addr:housenumber":"25",
    "addr:postcode":"32600",
    "addr:street":"Rua Irmans Fdez Alvarez",
    "iso:country":"ES",
    "sg:address":"Rua Irmans Fdez Alvarez, 25",
    "sg:city":"Verin",
    "sg:orig_category":"Telas Y Sedas (al Por Menor)",
    "sg:phone":"+34 988 41 06 32",
    "sg:postcode":"32600",
    "sg:province":"Ourense",
    "wof:name":"Prieto Carrajo Rosa",
    "wof:placetype":"venue"
},
  "geometry": {"coordinates":[-7.4348092079,41.942199707],"type":"Point"}
}