{
  "type": "Feature",
  "properties": {
    "iso:country":"ES",
    "sg:address":"Calle de Carretas, 7",
    "sg:city":"Herrera",
    "sg:orig_category":"Molduras, Junquillos, Listones Y Molduras Perforadas",
    "sg:phone":"+34 954 01 26 46",
    "sg:postcode":"41567",
    "sg:province":"Sevilla",
    "wof:name":"Benjumea Garcia Felix",
    "wof:placetype":"venue"
},
  "geometry": {"coordinates":[-4.8489809036,37.3659934998],"type":"Point"}
}