{
  "type": "Feature",
  "properties": {
    "iso:country":"ES",
    "sg:address":"Avda Portugal De, 37",
    "sg:city":"Rosal Frontera",
    "sg:orig_category":"Artesan\u00cda",
    "sg:phone":"+34 959 14 13 71",
    "sg:postcode":"21250",
    "sg:province":"Huelva",
    "wof:name":"Soria Macias Ana Maria",
    "wof:placetype":"venue"
},
  "geometry": {"coordinates":[-7.2189888954,37.9680595398],"type":"Point"}
}