{
  "type": "Feature",
  "properties": {
    "iso:country":"ES",
    "sg:address":"Avda Ca\u00d1ada Toledana, 36",
    "sg:city":"Gri\u00f1on",
    "sg:orig_category":"Goma: Productos De Uso Industrial (fabricaci\u00d3n, Al Por Mayor)",
    "sg:phone":"+34 918 14 13 64",
    "sg:postcode":"28971",
    "sg:province":"Madrid",
    "wof:name":"Cauchos Y Bandas S.l.",
    "wof:placetype":"venue"
},
  "geometry": {"coordinates":[-3.857323885,40.2163314819],"type":"Point"}
}