{
  "type": "Feature",
  "properties": {
    "iso:country":"ES",
    "sg:address":"Carrer de Garbi, S/n",
    "sg:city":"Can Volart",
    "sg:orig_category":"Cerrajer\u00cda, Ferrallista",
    "sg:phone":"+34 935 62 33 55",
    "sg:postcode":"08150",
    "sg:province":"Barcelona",
    "wof:name":"Kalea Trade S.l.",
    "wof:placetype":"venue"
},
  "geometry": {"coordinates":[2.2293000221,41.5678787231],"type":"Point"}
}