{
  "type": "Feature",
  "properties": {
    "iso:country":"ES",
    "sg:address":"Carrer de Bonavista, S/n",
    "sg:city":"Montcada Centre",
    "sg:orig_category":"Congelados: Productos Alimentarios (al Por Menor)",
    "sg:phone":"+34 935 75 03 71",
    "sg:postcode":"08110",
    "sg:province":"Barcelona",
    "wof:name":"Rodriguez Berenguer Maria Victoria",
    "wof:placetype":"venue"
},
  "geometry": {"coordinates":[2.1904120445,41.4858474731],"type":"Point"}
}