{
  "type": "Feature",
  "properties": {
    "addr:full":"Ctra S. Martin Pusa, Km. 0006,0 Malpica Tajo Toledo 45692",
    "addr:postcode":"45692",
    "addr:street":"Ctra S. Martin Pusa Km. 0006,0",
    "iso:country":"ES",
    "sg:address":"Ctra S. Martin Pusa, Km. 0006,0",
    "sg:city":"Malpica Tajo",
    "sg:orig_category":"Productores Recolectores, Venta Directa De Vinos",
    "sg:phone":"+34 925 87 71 11",
    "sg:postcode":"45692",
    "sg:province":"Toledo",
    "wof:name":"Pagos De Familia Marques De Gri\u00f1on S.a.",
    "wof:placetype":"venue"
},
  "geometry": {"coordinates":[-4.5501289368,39.8998908997],"type":"Point"}
}