{
  "type": "Feature",
  "properties": {
    "iso:country":"ES",
    "sg:address":"Urb Villamartin, S/n",
    "sg:city":"Villa Martin",
    "sg:orig_category":"Administradores De Bienes Y Delegados De Comunidades De Propietarios",
    "sg:phone":"+34 966 76 50 97",
    "sg:postcode":"03189",
    "sg:province":"Alicante",
    "wof:name":"Hernandez Sopena Jesus",
    "wof:placetype":"venue"
},
  "geometry": {"coordinates":[-0.737613976,37.9488296509],"type":"Point"}
}