{
  "type": "Feature",
  "properties": {
    "addr:full":"Avda Albufera, 323 Madrid Madrid 28031",
    "addr:housenumber":"323",
    "addr:postcode":"28031",
    "addr:street":"Avda Albufera",
    "iso:country":"ES",
    "sg:address":"Avda Albufera, 323",
    "sg:city":"Madrid",
    "sg:orig_category":"Ingenier\u00cda, Centros De Estudios (diversos)",
    "sg:phone":"+34 917 51 75 75",
    "sg:postcode":"28031",
    "sg:province":"Madrid",
    "wof:name":"Venturo Xxi S.a.",
    "wof:placetype":"venue"
},
  "geometry": {"coordinates":[-3.6342360973,40.3850669861],"type":"Point"}
}