{
  "type": "Feature",
  "properties": {
    "iso:country":"ES",
    "sg:address":"Pl Sales I Ferre, 16",
    "sg:city":"Ulldecona",
    "sg:orig_category":"Deportes Y Ocio: Art\u00cdculos Y Ropas (al Por Menor Y Accesorios)",
    "sg:phone":"+34 977 72 07 52",
    "sg:postcode":"43550",
    "sg:province":"Tarragona",
    "wof:name":"Segura Juni Teresa",
    "wof:placetype":"venue"
},
  "geometry": {"coordinates":[0.4456399977,40.5960197449],"type":"Point"}
}