{
  "type": "Feature",
  "properties": {
    "iso:country":"ES",
    "sg:address":"Calle de Blasco De Garay, 44",
    "sg:city":"Madrid",
    "sg:orig_category":"Bazares, Art\u00cdculos De Limpieza Y De Cocina (al Por Menor)",
    "sg:phone":"+34 915 44 97 19",
    "sg:postcode":"28015",
    "sg:province":"Madrid",
    "wof:name":"Zhang  Xiao Zhou",
    "wof:placetype":"venue"
},
  "geometry": {"coordinates":[-3.7113099098,40.4345169067],"type":"Point"}
}