{
  "type": "Feature",
  "properties": {
    "addr:full":"Carr Joan Peiro, 7 Badalona Barcelona 08911",
    "addr:housenumber":"7",
    "addr:postcode":"08911",
    "addr:street":"Carr Joan Peiro",
    "iso:country":"ES",
    "sg:address":"Carr Joan Peiro, 7",
    "sg:city":"Badalona",
    "sg:orig_category":"Suministros Y Materiales Industriales",
    "sg:phone":"+34 934 64 43 54",
    "sg:postcode":"08911",
    "sg:province":"Barcelona",
    "wof:name":"Difeuro S.l.",
    "wof:placetype":"venue"
},
  "geometry": {"coordinates":[2.2555921078,41.4537696838],"type":"Point"}
}