{
  "type": "Feature",
  "properties": {
    "addr:full":"Calle de Ramiro (del), 22 Collado Mediano Madrid 28450",
    "addr:housenumber":"22",
    "addr:postcode":"28450",
    "addr:street":"Calle De Ramiro Del",
    "iso:country":"ES",
    "sg:address":"Calle de Ramiro (del), 22",
    "sg:city":"Collado Mediano",
    "sg:orig_category":"Telefon\u00cda: Instaladores Varios",
    "sg:phone":"+34 918 59 84 02",
    "sg:postcode":"28450",
    "sg:province":"Madrid",
    "wof:name":"Telpasin S.l.",
    "wof:placetype":"venue"
},
  "geometry": {"coordinates":[-4.0465540886,40.6911430359],"type":"Point"}
}