{
  "type": "Feature",
  "properties": {
    "addr:full":"Oikia Auzoa, 27 Oikia Guip\u00f9zcoa 20759",
    "addr:housenumber":"27",
    "addr:postcode":"20759",
    "addr:street":"Oikia Auzoa;Guipu\u0300Zcoa",
    "iso:country":"ES",
    "sg:address":"Oikia Auzoa, 27",
    "sg:city":"Oikia",
    "sg:orig_category":"Centros De Educaci\u00d3n Especial",
    "sg:phone":"+34 943 86 20 46",
    "sg:postcode":"20759",
    "sg:province":"Guip\u00f9zcoa",
    "wof:name":"Gobierno Vasco-eusko Jaurlaritza",
    "wof:placetype":"venue"
},
  "geometry": {"coordinates":[-2.2405719757,43.2877807617],"type":"Point"}
}