{
  "type": "Feature",
  "properties": {
    "addr:full":"Carrer de Muntaner, 393 Barcelona Barcelona 08021",
    "addr:housenumber":"393",
    "addr:postcode":"08021",
    "addr:street":"Carrer De Muntaner",
    "iso:country":"ES",
    "sg:address":"Carrer de Muntaner, 393",
    "sg:city":"Barcelona",
    "sg:classifiers":[
        {
            "category":"Professional",
            "subcategory":"Management & Consulting",
            "type":"Services"
        }
    ],
    "sg:phone":"+34 932 01 79 76",
    "sg:postcode":"08021",
    "sg:province":"Barcelona",
    "sg:tags":[
        "asesor\u00cda",
        "en",
        "marketing"
    ],
    "wof:name":"Sereijo Pinto Concha",
    "wof:placetype":"venue"
},
  "geometry": {"coordinates":[2.1419739723,41.399684906],"type":"Point"}
}