{
  "type": "Feature",
  "properties": {
    "addr:full":"Calle de Luis I, S/n Madrid Madrid 28031",
    "addr:housenumber":"s / n",
    "addr:postcode":"28031",
    "addr:street":"Calle De Luis I",
    "iso:country":"ES",
    "sg:address":"Calle de Luis I, S/n",
    "sg:city":"Madrid",
    "sg:orig_category":"Mec\u00c1nico Del Autom\u00d3vil",
    "sg:phone":"+34 913 80 06 97",
    "sg:postcode":"28031",
    "sg:province":"Madrid",
    "wof:name":"Jaf Propiedad S.l.",
    "wof:placetype":"venue"
},
  "geometry": {"coordinates":[-3.6445939541,40.3756713867],"type":"Point"}
}