{
  "type": "Feature",
  "properties": {
    "addr:full":"Avda Vicentes (los), 27 Torres Cotillas Murcia 30565",
    "addr:housenumber":"27",
    "addr:postcode":"30565",
    "addr:street":"Avda Vicentes Los",
    "iso:country":"ES",
    "sg:address":"Avda Vicentes (los), 27",
    "sg:city":"Torres Cotillas",
    "sg:orig_category":"Mec\u00c1nico Del Autom\u00d3vil",
    "sg:phone":"+34 968 62 33 16",
    "sg:postcode":"30565",
    "sg:province":"Murcia",
    "wof:name":"Lopez Vicente Manuel",
    "wof:placetype":"venue"
},
  "geometry": {"coordinates":[-1.2376999855,38.0229949951],"type":"Point"}
}