{
  "type": "Feature",
  "properties": {
    "addr:full":"Calle de Nafarroa, 13 Arizgoiti Vizcaya 48970",
    "addr:housenumber":"13",
    "addr:postcode":"48970",
    "addr:street":"Calle De Nafarroa",
    "iso:country":"ES",
    "sg:address":"Calle de Nafarroa, 13",
    "sg:city":"Arizgoiti",
    "sg:orig_category":"Perfumer\u00cda (al Por Menor)",
    "sg:phone":"+34 944 49 28 85",
    "sg:postcode":"48970",
    "sg:province":"Vizcaya",
    "wof:name":"Del Barrio Rojo Mertxe",
    "wof:placetype":"venue"
},
  "geometry": {"coordinates":[-2.8872189522,43.2376327515],"type":"Point"}
}