{
  "type": "Feature",
  "properties": {
    "addr:full":"Calle de Ortega Y Gasset, 33 Ponferrada Le\u00f3n 24400",
    "addr:housenumber":"33",
    "addr:postcode":"24400",
    "addr:street":"Calle De Ortega Y Gasset",
    "iso:country":"ES",
    "sg:address":"Calle de Ortega Y Gasset, 33",
    "sg:city":"Ponferrada",
    "sg:orig_category":"Electricidad: Instaladores",
    "sg:phone":"+34 987 41 77 63",
    "sg:postcode":"24400",
    "sg:province":"Le\u00f3n",
    "wof:name":"Alvarez Santin Pedro",
    "wof:placetype":"venue"
},
  "geometry": {"coordinates":[-6.5979943275,42.5439414978],"type":"Point"}
}