{
  "type": "Feature",
  "properties": {
    "addr:full":"Calle de Adoratrices, S/n Guadalajara Guadalajara 19002",
    "addr:housenumber":"s",
    "addr:postcode":"19002",
    "addr:street":"Calle De Adoratrices;/ N",
    "iso:country":"ES",
    "sg:address":"Calle de Adoratrices, S/n",
    "sg:city":"Guadalajara",
    "sg:orig_category":"Centros De Educaci\u00d3n Especial",
    "sg:phone":"+34 949 22 64 97",
    "sg:postcode":"19002",
    "sg:province":"Guadalajara",
    "wof:name":"Colegio Nacional Parvulario Badiel",
    "wof:placetype":"venue"
},
  "geometry": {"coordinates":[-3.1544775963,40.624080658],"type":"Point"}
}