{
  "type": "Feature",
  "properties": {
    "addr:full":"Avda Valle, 45 Plasencia C\u00e1ceres 10600",
    "addr:housenumber":"45",
    "addr:postcode":"10600",
    "addr:street":"Avda Valle;Ca\u0301Ceres",
    "iso:country":"ES",
    "sg:address":"Avda Valle, 45",
    "sg:city":"Plasencia",
    "sg:orig_category":"Edici\u00d3n De Diarios, Revistas, Boletines",
    "sg:phone":"+34 927 42 16 44",
    "sg:postcode":"10600",
    "sg:province":"C\u00e1ceres",
    "wof:name":"Productora Video-graficas Del Norte De Extremadura S.l.",
    "wof:placetype":"venue"
},
  "geometry": {"coordinates":[-6.0789408684,40.0328865051],"type":"Point"}
}