{
  "type": "Feature",
  "properties": {
    "iso:country":"ES",
    "sg:address":"Ave Maria, S/n",
    "sg:city":"Benalmadena-costa",
    "sg:orig_category":"Fabricaci\u00d3n De Juguetes Autom\u00c1ticos",
    "sg:phone":"+34 952 96 49 53",
    "sg:postcode":"29630",
    "sg:province":"M\u00e1laga",
    "wof:name":"Keabeech Espa\u00f1a S.l.",
    "wof:placetype":"venue"
},
  "geometry": {"coordinates":[-4.5356488228,36.5860481262],"type":"Point"}
}