{
  "type": "Feature",
  "properties": {
    "addr:full":"Calle de Veintitres De Abril, 29 Zaragoza Zaragoza 50014",
    "addr:housenumber":"29",
    "addr:postcode":"50014",
    "addr:street":"Calle De Veintitres De Abril",
    "iso:country":"ES",
    "sg:address":"Calle de Veintitres De Abril, 29",
    "sg:city":"Zaragoza",
    "sg:orig_category":"Tubos Y Tuber\u00cdas De Goma Y Pl\u00c1stico (fabricaci\u00d3n, Al Por Mayor)",
    "sg:phone":"+34 976 47 34 21",
    "sg:postcode":"50014",
    "sg:province":"Zaragoza",
    "wof:name":"Instalaciones Dario Lopez S. L.",
    "wof:placetype":"venue"
},
  "geometry": {"coordinates":[-0.853488028,41.6701698303],"type":"Point"}
}