{
  "type": "Feature",
  "properties": {
    "iso:country":"ES",
    "sg:address":"Rua Jose Casal, 2",
    "sg:city":"Pontevedra",
    "sg:orig_category":"Plomeros",
    "sg:phone":"+34 986 84 54 76",
    "sg:postcode":"36002",
    "sg:province":"Pontevedra",
    "wof:name":"Asistencia No Fogar S.l.",
    "wof:placetype":"venue"
},
  "geometry": {"coordinates":[-8.6402750015,42.4279327393],"type":"Point"}
}