{
  "type": "Feature",
  "properties": {
    "iso:country":"ES",
    "sg:address":"Barr Miralbueno, 73",
    "sg:city":"Zaragoza",
    "sg:orig_category":"Cr\u00cda De Animales",
    "sg:phone":"+34 976 33 87 94",
    "sg:postcode":"50011",
    "sg:province":"Zaragoza",
    "wof:name":"San Juan Garrapinillos S.c.l.",
    "wof:placetype":"venue"
},
  "geometry": {"coordinates":[-0.9312989712,41.65858078],"type":"Point"}
}