{
  "type": "Feature",
  "properties": {
    "addr:full":"Calle de Doctor Martin Lagos, 4 Granada Granada 18005",
    "addr:housenumber":"4",
    "addr:postcode":"18005",
    "addr:street":"Calle De Doctor Martin Lagos",
    "iso:country":"ES",
    "sg:address":"Calle de Doctor Martin Lagos, 4",
    "sg:city":"Granada",
    "sg:orig_category":"Congelados: Productos Alimentarios (fabricaci\u00d3n, Al Por Mayor)",
    "sg:phone":"+34 958 26 68 57",
    "sg:postcode":"18005",
    "sg:province":"Granada",
    "wof:name":"Ortiz Sanchez-ca\u00f1ete Antonio",
    "wof:placetype":"venue"
},
  "geometry": {"coordinates":[-3.602304697,37.171546936],"type":"Point"}
}