{
  "type": "Feature",
  "properties": {
    "iso:country":"ES",
    "sg:address":"Luga Ciudad Jardin Virgen Del Milagro, 23",
    "sg:city":"Ciudad Jardin Virgen Del Milagro",
    "sg:orig_category":"Molduras, Junquillos, Listones Y Molduras Perforadas",
    "sg:phone":"+34 979 77 68 88",
    "sg:postcode":"34190",
    "sg:province":"Palencia",
    "wof:name":"Latorre Crespo Carlos Manuel",
    "wof:placetype":"venue"
},
  "geometry": {"coordinates":[-4.5164442062,41.9515914917],"type":"Point"}
}