{
  "type": "Feature",
  "properties": {
    "iso:country":"ES",
    "sg:address":"Ctra Castalla, 25",
    "sg:city":"Sax",
    "sg:orig_category":"Postigos, Persianas Y Celos\u00cdas",
    "sg:phone":"+34 965 47 41 42",
    "sg:postcode":"03630",
    "sg:province":"Alicante",
    "wof:name":"Chico Ponce Juan",
    "wof:placetype":"venue"
},
  "geometry": {"coordinates":[-0.8163440228,38.5433158875],"type":"Point"}
}