{
  "type": "Feature",
  "properties": {
    "iso:country":"ES",
    "sg:address":"Avda Manuel Llaneza, 2",
    "sg:city":"Gijon",
    "sg:orig_category":"Servicios Gsm",
    "sg:phone":"+34 985 14 87 30",
    "sg:postcode":"33205",
    "sg:province":"Asturias",
    "wof:name":"Europark Telecomunicaciones S.l.",
    "wof:placetype":"venue"
},
  "geometry": {"coordinates":[-5.6597480774,43.5364532471],"type":"Point"}
}