{
  "type": "Feature",
  "properties": {
    "addr:full":"Avda Concordia, 6 Tui Pontevedra 36700",
    "addr:housenumber":"6",
    "addr:postcode":"36700",
    "addr:street":"Avda Concordia",
    "iso:country":"ES",
    "sg:address":"Avda Concordia, 6",
    "sg:city":"Tui",
    "sg:orig_category":"Caf\u00c9s, Bares, Cervecer\u00cdas",
    "sg:phone":"+34 986 60 17 28",
    "sg:postcode":"36700",
    "sg:province":"Pontevedra",
    "wof:name":"Cafe Nevada C.b.",
    "wof:placetype":"venue"
},
  "geometry": {"coordinates":[-8.6448440552,42.0485496521],"type":"Point"}
}