{
  "type": "Feature",
  "properties": {
    "addr:full":"Carrer de Calatrava, 72 Barcelona Barcelona 08017",
    "addr:housenumber":"72",
    "addr:postcode":"08017",
    "addr:street":"Carrer De Calatrava",
    "iso:country":"ES",
    "sg:address":"Carrer de Calatrava, 72",
    "sg:city":"Barcelona",
    "sg:orig_category":"Arquitectos",
    "sg:phone":"+34 934 17 65 48",
    "sg:postcode":"08017",
    "sg:province":"Barcelona",
    "sg:website":"www.rigola.com",
    "wof:name":"Rigola Vilageliu Juan",
    "wof:placetype":"venue"
},
  "geometry": {"coordinates":[2.1283090115,41.4017372131],"type":"Point"}
}