{
  "type": "Feature",
  "properties": {
    "iso:country":"ES",
    "sg:address":"Calle de Hipica, 1",
    "sg:city":"Valladolid",
    "sg:orig_category":"Caf\u00c9s, Bares, Cervecer\u00cdas",
    "sg:phone":"+34 983 27 68 75",
    "sg:postcode":"47007",
    "sg:province":"Valladolid",
    "wof:name":"Gonzalez Nieto Jose Miguel",
    "wof:placetype":"venue"
},
  "geometry": {"coordinates":[-4.7384848595,41.6375808716],"type":"Point"}
}