{
  "type": "Feature",
  "properties": {
    "addr:full":"Calle de Iglesia, 18 Ataquines Valladolid 47210",
    "addr:housenumber":"18",
    "addr:postcode":"47210",
    "addr:street":"Calle De Iglesia",
    "iso:country":"ES",
    "sg:address":"Calle de Iglesia, 18",
    "sg:city":"Ataquines",
    "sg:orig_category":"Cajas Para Embalar",
    "sg:phone":"+34 983 81 55 28",
    "sg:postcode":"47210",
    "sg:province":"Valladolid",
    "wof:name":"Caja Rural Del Duero",
    "wof:placetype":"venue"
},
  "geometry": {"coordinates":[-4.8040251732,41.1818237305],"type":"Point"}
}