{
  "type": "Feature",
  "properties": {
    "addr:full":"Calle de Maestro Faus, 5 Granada Granada 18008",
    "addr:housenumber":"5",
    "addr:postcode":"18008",
    "addr:street":"Calle De Maestro Faus",
    "iso:country":"ES",
    "sg:address":"Calle de Maestro Faus, 5",
    "sg:city":"Granada",
    "sg:orig_category":"Asociaciones, Organismos Culturales Y Socioeducativos",
    "sg:phone":"+34 958 18 45 79",
    "sg:postcode":"18008",
    "sg:province":"Granada",
    "wof:name":"Asde Scouts Andalucia",
    "wof:placetype":"venue"
},
  "geometry": {"coordinates":[-3.5874493122,37.1599884033],"type":"Point"}
}