{
  "type": "Feature",
  "properties": {
    "addr:full":"Plaz Consejo, S/n Salteras Sevilla 41909",
    "addr:housenumber":"s / n",
    "addr:postcode":"41909",
    "iso:country":"ES",
    "sg:address":"Plaz Consejo, S/n",
    "sg:city":"Salteras",
    "sg:orig_category":"Ense\u00d1anza, Formaci\u00d3n Profesional: Aprendizaje",
    "sg:phone":"+34 955 70 77 60",
    "sg:postcode":"41909",
    "sg:province":"Sevilla",
    "wof:name":"Ayuntamiento De Salteras",
    "wof:placetype":"venue"
},
  "geometry": {"coordinates":[-6.1071691513,37.4179992676],"type":"Point"}
}