{
  "type": "Feature",
  "properties": {
    "iso:country":"ES",
    "sg:address":"Calle de Santa Barbara, 9",
    "sg:city":"Solana De Los Barros",
    "sg:orig_category":"Supermercados Y Hipermercados",
    "sg:phone":"+34 924 68 41 44",
    "sg:postcode":"06209",
    "sg:province":"Badajoz",
    "wof:name":"Gonzalez Nieto Manuel",
    "wof:placetype":"venue"
},
  "geometry": {"coordinates":[-6.5371041298,38.7253456116],"type":"Point"}
}