{
  "type": "Feature",
  "properties": {
    "addr:full":"Calle de Santa Lucia, 90 Valladolid Valladolid 47005",
    "addr:housenumber":"90",
    "addr:postcode":"47005",
    "addr:street":"Calle De Santa Lucia",
    "iso:country":"ES",
    "sg:address":"Calle de Santa Lucia, 90",
    "sg:city":"Valladolid",
    "sg:orig_category":"Librer\u00cdas",
    "sg:phone":"+34 983 20 98 68",
    "sg:postcode":"47005",
    "sg:province":"Valladolid",
    "wof:name":"Hermanos Palacios C.b.",
    "wof:placetype":"venue"
},
  "geometry": {"coordinates":[-4.7156581879,41.6505737305],"type":"Point"}
}