{
  "type": "Feature",
  "properties": {
    "addr:full":"Ctra Villaviciosa (c-5114) (de), Km. 0002,7 Mostoles Madrid 28935",
    "addr:postcode":"c-5114;28935",
    "addr:street":"Ctra Villaviciosa;De Km. 0002,7 Mostoles",
    "iso:country":"ES",
    "sg:address":"Ctra Villaviciosa (c-5114) (de), Km. 0002,7",
    "sg:city":"Mostoles",
    "sg:orig_category":"Mec\u00c1nico Del Autom\u00d3vil",
    "sg:phone":"+34 916 13 67 63",
    "sg:postcode":"28935",
    "sg:province":"Madrid",
    "wof:name":"Fernandez Ortiz Anastasio",
    "wof:placetype":"venue"
},
  "geometry": {"coordinates":[-3.9280939102,40.3081817627],"type":"Point"}
}