{
  "type": "Feature",
  "properties": {
    "iso:country":"ES",
    "sg:address":"Dulce Maria Loinaz, 13",
    "sg:city":"Beasain",
    "sg:orig_category":"Notarios",
    "sg:phone":"+34 943 16 07 05",
    "sg:postcode":"20200",
    "sg:province":"Guip\u00f9zcoa",
    "wof:name":"Melendo Martinea Mariano Pablo",
    "wof:placetype":"venue"
},
  "geometry": {"coordinates":[-2.1944589615,43.0469207764],"type":"Point"}
}