{
  "type": "Feature",
  "properties": {
    "iso:country":"ES",
    "sg:address":"Avgd Catalunya, 17",
    "sg:city":"Lleida",
    "sg:orig_category":"Ropa De Hogar (al Por Menor)",
    "sg:phone":"+34 973 27 09 67",
    "sg:postcode":"25002",
    "sg:province":"Lleida",
    "wof:name":"Textil Cadena S.a.",
    "wof:placetype":"venue"
},
  "geometry": {"coordinates":[0.6198999882,41.6117591858],"type":"Point"}
}