{
  "type": "Feature",
  "properties": {
    "iso:country":"ES",
    "sg:address":"Primero De Mayo, 39",
    "sg:city":"Huesa",
    "sg:orig_category":"Bisuter\u00cda, Joyer\u00cda, Relojer\u00cda (al Por Menor)",
    "sg:phone":"+34 953 71 56 88",
    "sg:postcode":"23487",
    "sg:province":"Ja\u00e9n",
    "wof:name":"Gallardo Reche Mario Clemente",
    "wof:placetype":"venue"
},
  "geometry": {"coordinates":[-3.0765490532,37.7653007507],"type":"Point"}
}