{
  "type": "Feature",
  "properties": {
    "iso:country":"ES",
    "sg:address":"Calle de Cuevas Del Valle, 28",
    "sg:city":"Madrid",
    "sg:orig_category":"Promotores Constructores",
    "sg:phone":"+34 917 08 05 60",
    "sg:postcode":"28023",
    "sg:province":"Madrid",
    "sg:website":"www.globaliza.com",
    "wof:name":"Ediciones Globaliza S.l.",
    "wof:placetype":"venue"
},
  "geometry": {"coordinates":[-3.8359715939,40.4727630615],"type":"Point"}
}