{
  "type": "Feature",
  "properties": {
    "iso:country":"ES",
    "sg:address":"Calle de Fray Martin De Valencia, 4",
    "sg:city":"Valencia De Don Juan",
    "sg:orig_category":"Supermercados Y Hipermercados",
    "sg:phone":"+34 987 75 02 37",
    "sg:postcode":"24200",
    "sg:province":"Le\u00f3n",
    "wof:name":"Garcia Gaitero Nuria",
    "wof:placetype":"venue"
},
  "geometry": {"coordinates":[-5.517824173,42.2978172302],"type":"Point"}
}