{
  "type": "Feature",
  "properties": {
    "iso:country":"ES",
    "sg:address":"Avda Andes, 50",
    "sg:city":"Madrid",
    "sg:orig_category":"Supermercados Y Hipermercados",
    "sg:phone":"+34 913 24 88 00",
    "sg:postcode":"28...",
    "sg:province":"Madrid",
    "sg:website":"www.hipercor.es",
    "wof:name":"Hipercor S.a.",
    "wof:placetype":"venue"
},
  "geometry": {"coordinates":[-3.618211031,40.4566383362],"type":"Point"}
}