{
  "type": "Feature",
  "properties": {
    "iso:country":"ES",
    "sg:address":"Calle de Reyes Catolicos, 10",
    "sg:city":"Avila",
    "sg:orig_category":"Peleter\u00cdas",
    "sg:phone":"+34 920 25 02 99",
    "sg:postcode":"05001",
    "sg:province":"\u00c1vila",
    "wof:name":"Sanchez Mu\u00f1oz Angel",
    "wof:placetype":"venue"
},
  "geometry": {"coordinates":[-4.699256897,40.6558265686],"type":"Point"}
}