{
  "type": "Feature",
  "properties": {
    "iso:country":"ES",
    "sg:address":"Calle de Automovil, 76",
    "sg:city":"Yuncler",
    "sg:orig_category":"Control T\u00c9cnico De Veh\u00cdculos",
    "sg:phone":"+34 925 53 19 30",
    "sg:postcode":"45529",
    "sg:province":"Toledo",
    "wof:name":"Itv La Sagra S.l.",
    "wof:placetype":"venue"
},
  "geometry": {"coordinates":[-3.9171214104,40.0484313965],"type":"Point"}
}