{
  "type": "Feature",
  "properties": {
    "iso:country":"ES",
    "sg:address":"Plaz Luceros (los), 16",
    "sg:city":"Alacant",
    "sg:orig_category":"Caf\u00c9s, Bares, Cervecer\u00cdas",
    "sg:phone":"+34 965 14 40 87",
    "sg:postcode":"03004",
    "sg:province":"Alicante",
    "wof:name":"Espla Y Martinez S.l. Cocteleria Nic",
    "wof:placetype":"venue"
},
  "geometry": {"coordinates":[-0.4903210104,38.3464698792],"type":"Point"}
}