{
  "type": "Feature",
  "properties": {
    "addr:full":"Cami Pla De La Ginesta, S/n Palafolls Barcelona 08389",
    "addr:housenumber":"s / n",
    "addr:postcode":"08389",
    "addr:street":"Cami Pla De La Ginesta",
    "iso:country":"ES",
    "sg:address":"Cami Pla De La Ginesta, S/n",
    "sg:city":"Palafolls",
    "sg:orig_category":"Invernaderos Y Semilleros",
    "sg:phone":"+34 937 65 73 01",
    "sg:postcode":"08389",
    "sg:province":"Barcelona",
    "wof:name":"Riera Malet Eloi",
    "wof:placetype":"venue"
},
  "geometry": {"coordinates":[2.7497739792,41.6659660339],"type":"Point"}
}