{
  "type": "Feature",
  "properties": {
    "iso:country":"ES",
    "sg:address":"San Roque Club, 83",
    "sg:city":"S. Roque",
    "sg:orig_category":"Inmobiliaria (agencias)",
    "sg:phone":"+34 956 61 30 03",
    "sg:postcode":"11360",
    "sg:province":"C\u00e1diz",
    "wof:name":"Sunmountains Industry S.l.",
    "wof:placetype":"venue"
},
  "geometry": {"coordinates":[-5.3897438049,36.209690094],"type":"Point"}
}