{
  "type": "Feature",
  "properties": {
    "iso:country":"ES",
    "sg:address":"Cetreria, 22",
    "sg:city":"Molino Hoz",
    "sg:orig_category":"Inmobiliaria (agencias)",
    "sg:phone":"+34 917 08 44 07",
    "sg:postcode":"28230",
    "sg:province":"Madrid",
    "wof:name":"Vitalia 92 Patrimonial S.l.",
    "wof:placetype":"venue"
},
  "geometry": {"coordinates":[-3.9364755154,40.5344543457],"type":"Point"}
}