{
  "type": "Feature",
  "properties": {
    "addr:full":"Calle de Cracovia, 1 Madrid Madrid 28022",
    "addr:housenumber":"1",
    "addr:postcode":"28022",
    "addr:street":"Calle De Cracovia",
    "iso:country":"ES",
    "sg:address":"Calle de Cracovia, 1",
    "sg:city":"Madrid",
    "sg:orig_category":"Seguridad En El Trabajo Y Prevenci\u00d3n De Riesgos Laborales",
    "sg:phone":"+34 913 06 42 38",
    "sg:postcode":"28022",
    "sg:province":"Madrid",
    "wof:name":"Asistencia Tecnica Seguridad Calidad Y Medio Ambiente S.l.",
    "wof:placetype":"venue"
},
  "geometry": {"coordinates":[-3.6065773964,40.4236602783],"type":"Point"}
}