{
  "type": "Feature",
  "properties": {
    "addr:full":"Calle de Nueva, 21 B Villabona Guip\u00f9zcoa 20150",
    "addr:housenumber":"21 b",
    "addr:postcode":"20150",
    "addr:street":"Calle De Nueva;Guipu\u0300Zcoa",
    "iso:country":"ES",
    "sg:address":"Calle de Nueva, 21 B",
    "sg:city":"Villabona",
    "sg:orig_category":"Peluquer\u00cdas, Peluquer\u00cda Mixta",
    "sg:phone":"+34 943 69 18 24",
    "sg:postcode":"20150",
    "sg:province":"Guip\u00f9zcoa",
    "wof:name":"Peluqueria Felix - Felix Y Gelatxo, S.l.",
    "wof:placetype":"venue"
},
  "geometry": {"coordinates":[-2.0486390591,43.2030830383],"type":"Point"}
}