{
  "type": "Feature",
  "properties": {
    "iso:country":"ES",
    "sg:address":"Av Mallorca (sol Mallorca), S/n",
    "sg:city":"Sol De Mallorca",
    "sg:orig_category":"Promotores Constructores",
    "sg:phone":"+34 971 13 14 02",
    "sg:postcode":"07181",
    "sg:province":"Islas Baleares",
    "wof:name":"Dragados S.a.",
    "wof:placetype":"venue"
},
  "geometry": {"coordinates":[2.5221049786,39.479598999],"type":"Point"}
}