{
  "type": "Feature",
  "properties": {
    "addr:full":"Calle de Sancho Ramirez, 10 Sabi\u00f1anigo Huesca 22600",
    "addr:housenumber":"10",
    "addr:postcode":"22600",
    "addr:street":"Calle De Sancho Ramirez",
    "iso:country":"ES",
    "sg:address":"Calle de Sancho Ramirez, 10",
    "sg:city":"Sabi\u00f1anigo",
    "sg:orig_category":"Transportes Por V\u00cdas Navegables",
    "sg:phone":"+34 974 48 07 95",
    "sg:postcode":"22600",
    "sg:province":"Huesca",
    "wof:name":"Diez Vera Pedro",
    "wof:placetype":"venue"
},
  "geometry": {"coordinates":[-0.3628390133,42.5200386047],"type":"Point"}
}