{
  "type": "Feature",
  "properties": {
    "iso:country":"ES",
    "sg:address":"Carrer de Santa Engracia, 62",
    "sg:city":"Barcelona",
    "sg:orig_category":"Fabricaci\u00d3n De Moldes Y Modelos",
    "sg:phone":"+34 932 76 07 44",
    "sg:postcode":"08016",
    "sg:province":"Barcelona",
    "wof:name":"Molec S.l.",
    "wof:placetype":"venue"
},
  "geometry": {"coordinates":[2.178550005,41.4406929016],"type":"Point"}
}