{
  "type": "Feature",
  "properties": {
    "iso:country":"ES",
    "sg:address":"Calle de General Jimenez Castellanos, 16",
    "sg:city":"Montilla",
    "sg:orig_category":"Abogados",
    "sg:phone":"+34 957 65 05 05",
    "sg:postcode":"14550",
    "sg:province":"C\u00f3rdoba",
    "wof:name":"Climent Pedraza Joaquin",
    "wof:placetype":"venue"
},
  "geometry": {"coordinates":[-4.639439106,37.5854225159],"type":"Point"}
}