{
  "type": "Feature",
  "properties": {
    "iso:country":"ES",
    "sg:address":"Calle de Baron De Finestrat, 3",
    "sg:city":"Alacant",
    "sg:orig_category":"Inmobiliaria (agencias)",
    "sg:phone":"+34 965 14 17 74",
    "sg:postcode":"03001",
    "sg:province":"Alicante",
    "wof:name":"Ecor S.l",
    "wof:placetype":"venue"
},
  "geometry": {"coordinates":[-0.4844082892,38.3444328308],"type":"Point"}
}