{
  "type": "Feature",
  "properties": {
    "addr:full":"Calle de Luis Feito, 41 Madrid Madrid 28047",
    "addr:housenumber":"41",
    "addr:postcode":"madrid;28047",
    "addr:street":"Calle De Luis Feito",
    "iso:country":"ES",
    "sg:address":"Calle de Luis Feito, 41",
    "sg:city":"Madrid",
    "sg:orig_category":"Sellos De Goma Y Met\u00c1licos",
    "sg:phone":"+34 914 66 75 05",
    "sg:postcode":"28047",
    "sg:province":"Madrid",
    "wof:name":"Alcazar Sanchez Dolores",
    "wof:placetype":"venue"
},
  "geometry": {"coordinates":[-3.7449438572,40.3918457031],"type":"Point"}
}