{
  "type": "Feature",
  "properties": {
    "iso:country":"ES",
    "sg:address":"Avgd Blondel, 50",
    "sg:city":"Lleida",
    "sg:orig_category":"Confecci\u00d3n De Trajes Para Se\u00d1oras",
    "sg:phone":"+34 973 24 59 01",
    "sg:postcode":"25002",
    "sg:province":"Lleida",
    "wof:name":"Valenti Pomes Teresa",
    "wof:placetype":"venue"
},
  "geometry": {"coordinates":[0.6249150038,41.6132164001],"type":"Point"}
}