{
  "type": "Feature",
  "properties": {
    "addr:full":"Calle de Julian Camarillo, 38 Madrid Madrid 28037",
    "addr:housenumber":"38",
    "addr:postcode":"madrid;28037",
    "addr:street":"Calle De Julian Camarillo",
    "iso:country":"ES",
    "sg:address":"Calle de Julian Camarillo, 38",
    "sg:city":"Madrid",
    "sg:orig_category":"Venta, Colocaci\u00d3n, Reparaci\u00d3n De Parabrisas, Techos Descapotables",
    "sg:phone":"+34 917 54 59 11",
    "sg:postcode":"28037",
    "sg:province":"Madrid",
    "wof:name":"Gabriel Arevalillo Martinez S.l.",
    "wof:placetype":"venue"
},
  "geometry": {"coordinates":[-3.6224620342,40.4364280701],"type":"Point"}
}