{
  "type": "Feature",
  "properties": {
    "iso:country":"ES",
    "sg:address":"Carrer de Rossello, 105",
    "sg:city":"Mataro",
    "sg:orig_category":"Confecci\u00d3n (fabricaci\u00d3n, Al Por Mayor)",
    "sg:phone":"+34 937 99 16 96",
    "sg:postcode":"08303",
    "sg:province":"Barcelona",
    "wof:name":"Franco Carmona Rosario",
    "wof:placetype":"venue"
},
  "geometry": {"coordinates":[2.4270780087,41.5368309021],"type":"Point"}
}