{
  "type": "Feature",
  "properties": {
    "iso:country":"ES",
    "sg:address":"Pol. Ind. Castilla, S/n",
    "sg:city":"Pol. Ind. Castilla",
    "sg:orig_category":"Metales (labores, Pulido)",
    "sg:phone":"+34 962 51 40 28",
    "sg:postcode":"46380",
    "sg:province":"Valencia",
    "wof:name":"Solimar Food Ingredients S.l.",
    "wof:placetype":"venue"
},
  "geometry": {"coordinates":[-0.6874480247,39.4945602417],"type":"Point"}
}