{
  "type": "Feature",
  "properties": {
    "addr:full":"Calle de Quero, 13 Madrid Madrid 28024",
    "addr:housenumber":"13",
    "addr:postcode":"madrid;28024",
    "addr:street":"Calle De Quero",
    "iso:country":"ES",
    "sg:address":"Calle de Quero, 13",
    "sg:city":"Madrid",
    "sg:orig_category":"Cerrajer\u00cda, Ferrallista",
    "sg:phone":"+34 915 09 88 02",
    "sg:postcode":"28024",
    "sg:province":"Madrid",
    "wof:name":"Caballero Lopez Manuel",
    "wof:placetype":"venue"
},
  "geometry": {"coordinates":[-3.7609529495,40.3918876648],"type":"Point"}
}