{
  "type": "Feature",
  "properties": {
    "addr:full":"Calle de Trinidad, 95 Malaga M\u00e1laga 29009",
    "addr:housenumber":"95",
    "addr:postcode":"29009",
    "addr:street":"Calle De Trinidad;Ma\u0301Laga",
    "iso:country":"ES",
    "sg:address":"Calle de Trinidad, 95",
    "sg:city":"Malaga",
    "sg:orig_category":"Comunidades Religiosas",
    "sg:phone":"+34 952 30 26 51",
    "sg:postcode":"29009",
    "sg:province":"M\u00e1laga",
    "wof:name":"Muy Ilustre Y Venerable Cofradia De Nazarenos De Nuestro Padre",
    "wof:placetype":"venue"
},
  "geometry": {"coordinates":[-4.4310507774,36.7241859436],"type":"Point"}
}