{
  "type": "Feature",
  "properties": {
    "addr:full":"Calle de Calvario, 97 Rota C\u00e1diz 11520",
    "addr:housenumber":"97",
    "addr:postcode":"11520",
    "addr:street":"Calle De Calvario;Ca\u0301Diz",
    "iso:country":"ES",
    "sg:address":"Calle de Calvario, 97",
    "sg:city":"Rota",
    "sg:orig_category":"Cristaler\u00cdas",
    "sg:phone":"+34 956 81 02 48",
    "sg:postcode":"11520",
    "sg:province":"C\u00e1diz",
    "wof:name":"Rubin Sanchez Marcelino",
    "wof:placetype":"venue"
},
  "geometry": {"coordinates":[-6.3565630913,36.6238250732],"type":"Point"}
}