{
  "type": "Feature",
  "properties": {
    "addr:full":"Calle de Gustavo Adolfo Becquer, 5 Alhaurin Torre M\u00e1laga 29130",
    "addr:housenumber":"5",
    "addr:postcode":"29130",
    "addr:street":"Calle De Gustavo Adolfo Becquer",
    "iso:country":"ES",
    "sg:address":"Calle de Gustavo Adolfo Becquer, 5",
    "sg:city":"Alhaurin Torre",
    "sg:orig_category":"Negocio De Materiales De Construcci\u00d3n",
    "sg:phone":"+34 952 42 63 16",
    "sg:postcode":"29130",
    "sg:province":"M\u00e1laga",
    "wof:name":"Jose Benitez Cantero Material De Construccion Sl",
    "wof:placetype":"venue"
},
  "geometry": {"coordinates":[-4.5642690659,36.6598892212],"type":"Point"}
}