{
  "type": "Feature",
  "properties": {
    "iso:country":"ES",
    "sg:address":"Major, S/n",
    "sg:city":"Estana",
    "sg:orig_category":"Venta, Instalaci\u00d3n De Cocinas",
    "sg:phone":"+34 973 51 53 45",
    "sg:postcode":"25725",
    "sg:province":"Lleida",
    "wof:name":"Pages Valls Luis",
    "wof:placetype":"venue"
},
  "geometry": {"coordinates":[1.7050800323,42.3546257019],"type":"Point"}
}