{
  "type": "Feature",
  "properties": {
    "iso:country":"ES",
    "sg:address":"Calle de Carrera La, 5",
    "sg:city":"Ojen",
    "sg:orig_category":"Administraciones Regionales, Departamentales Y Locales",
    "sg:phone":"+34 952 88 10 03",
    "sg:postcode":"29610",
    "sg:province":"M\u00e1laga",
    "wof:name":"Ayuntamiento De Ojen",
    "wof:placetype":"venue"
},
  "geometry": {"coordinates":[-4.8562679291,36.5642433167],"type":"Point"}
}