{
  "type": "Feature",
  "properties": {
    "iso:country":"ES",
    "sg:address":"Calle de Coslada, 7",
    "sg:city":"Madrid",
    "sg:orig_category":"Locales Y Clases De Danza",
    "sg:phone":"+34 913 55 25 83",
    "sg:postcode":"28028",
    "sg:province":"Madrid",
    "wof:name":"Roche Rubio Carmen",
    "wof:placetype":"venue"
},
  "geometry": {"coordinates":[-3.6751418114,40.437461853],"type":"Point"}
}