{
  "type": "Feature",
  "properties": {
    "addr:full":"Carr Triassa, 5 Angles Girona 17160",
    "addr:housenumber":"5",
    "addr:postcode":"17160",
    "addr:street":"Carr Triassa",
    "iso:country":"ES",
    "sg:address":"Carr Triassa, 5",
    "sg:city":"Angles",
    "sg:orig_category":"Transporte En General",
    "sg:phone":"+34 972 42 00 15",
    "sg:postcode":"17160",
    "sg:province":"Girona",
    "wof:name":"Bassa Julia Jordi",
    "wof:placetype":"venue"
},
  "geometry": {"coordinates":[2.6416389942,41.956905365],"type":"Point"}
}