{
  "type": "Feature",
  "properties": {
    "addr:full":"Telleria Kalea, 13 Bergara Guip\u00f9zcoa 20570",
    "addr:housenumber":"13",
    "addr:postcode":"20570",
    "addr:street":"Telleria Kalea;Guipu\u0300Zcoa",
    "iso:country":"ES",
    "sg:address":"Telleria Kalea, 13",
    "sg:city":"Bergara",
    "sg:orig_category":"Maquinaria Para Industrias Diversas",
    "sg:phone":"+34 943 76 10 36",
    "sg:postcode":"20570",
    "sg:province":"Guip\u00f9zcoa",
    "wof:name":"Ikankronitek S.l.",
    "wof:placetype":"venue"
},
  "geometry": {"coordinates":[-2.4233329296,43.1255264282],"type":"Point"}
}