{
  "type": "Feature",
  "properties": {
    "iso:country":"ES",
    "sg:address":"Calle de Sanchez Madrigal, 4",
    "sg:city":"San Bartolome",
    "sg:orig_category":"Abogados",
    "sg:phone":"+34 968 22 12 38",
    "sg:postcode":"30004",
    "sg:province":"Murcia",
    "wof:name":"Salzillo Consultoria Integral S.l.",
    "wof:placetype":"venue"
},
  "geometry": {"coordinates":[-1.1301629543,37.9852027893],"type":"Point"}
}