{
  "type": "Feature",
  "properties": {
    "addr:full":"Ctra Puig Major, Des, S/n Horta Islas Baleares 07100",
    "addr:postcode":"07100",
    "addr:street":"Ctra Puig Major Des S / N",
    "iso:country":"ES",
    "sg:address":"Ctra Puig Major, Des, S/n",
    "sg:city":"Horta",
    "sg:orig_category":"Agencias Y Agentes Comerciales, Representantes",
    "sg:phone":"+34 971 63 18 78",
    "sg:postcode":"07100",
    "sg:province":"Islas Baleares",
    "wof:name":"Construccions I Promocions S'anglada Soller S.l.",
    "wof:placetype":"venue"
},
  "geometry": {"coordinates":[2.7147779465,39.7659072876],"type":"Point"}
}