{
  "type": "Feature",
  "properties": {
    "addr:full":"Calle de Ambrosio Ballesteros, 11 Torrijos Toledo 45500",
    "addr:housenumber":"11",
    "addr:postcode":"45500",
    "addr:street":"Calle De Ambrosio Ballesteros",
    "iso:country":"ES",
    "sg:address":"Calle de Ambrosio Ballesteros, 11",
    "sg:city":"Torrijos",
    "sg:orig_category":"Loter\u00cda Y T\u00d3mbola",
    "sg:phone":"+34 925 76 28 63",
    "sg:postcode":"45500",
    "sg:province":"Toledo",
    "wof:name":"Martin Gomez-aguero Antonio",
    "wof:placetype":"venue"
},
  "geometry": {"coordinates":[-4.2818622589,39.9826927185],"type":"Point"}
}