{
  "type": "Feature",
  "properties": {
    "iso:country":"ES",
    "sg:address":"Avda Manuel Quiroga, 8",
    "sg:city":"Barco",
    "sg:classifiers":[
        {
            "category":"Professional",
            "subcategory":"Management & Consulting",
            "type":"Services"
        }
    ],
    "sg:phone":"+34 988 32 66 04",
    "sg:postcode":"32300",
    "sg:province":"Ourense",
    "sg:tags":[
        "asesor\u00cda",
        "en",
        "marketing"
    ],
    "wof:name":"Gonzalez Prendes Angel Antonio",
    "wof:placetype":"venue"
},
  "geometry": {"coordinates":[-6.9802031517,42.4157943726],"type":"Point"}
}