{
  "type": "Feature",
  "properties": {
    "addr:full":"Calle de Guadarrama, 1 Rozas De Madrid Madrid 28230",
    "addr:housenumber":"1",
    "addr:postcode":"28230",
    "addr:street":"Calle De Guadarrama",
    "iso:country":"ES",
    "sg:address":"Calle de Guadarrama, 1",
    "sg:city":"Rozas De Madrid",
    "sg:orig_category":"Servicios De Higiene Y Peluquer\u00cda Para Perros Y Gatos",
    "sg:phone":"+34 916 37 81 50",
    "sg:postcode":"28230",
    "sg:province":"Madrid",
    "wof:name":"Romero Jurado Maria Jose",
    "wof:placetype":"venue"
},
  "geometry": {"coordinates":[-3.8730552197,40.4942626953],"type":"Point"}
}