{
  "type": "Feature",
  "properties": {
    "iso:country":"ES",
    "sg:address":"Calle de Virgen De Los Remedios, 24",
    "sg:city":"Villarrasa",
    "sg:orig_category":"Procuradores",
    "sg:phone":"+34 959 41 93 53",
    "sg:postcode":"21850",
    "sg:province":"Huelva",
    "wof:name":"Hinojosa De Guzman Ana Maria",
    "wof:placetype":"venue"
},
  "geometry": {"coordinates":[-6.6072378159,37.3894195557],"type":"Point"}
}