{
  "type": "Feature",
  "properties": {
    "addr:full":"Ctra Madrid, S/n Olmedo Valladolid 47410",
    "addr:housenumber":"s",
    "addr:postcode":"47410",
    "addr:street":"Ctra Madrid;/ N",
    "iso:country":"ES",
    "sg:address":"Ctra Madrid, S/n",
    "sg:city":"Olmedo",
    "sg:orig_category":"Distribuci\u00d3n De Petr\u00d3leo Y Derivados",
    "sg:phone":"+34 983 60 02 29",
    "sg:postcode":"47410",
    "sg:province":"Valladolid",
    "wof:name":"Agip Espa\u00d1a S.a.",
    "wof:placetype":"venue"
},
  "geometry": {"coordinates":[-4.6813368797,41.2851333618],"type":"Point"}
}