{
  "type": "Feature",
  "properties": {
    "addr:full":"Calle de Gardenia, 40 Estrella Las Palmas 35212",
    "addr:housenumber":"40",
    "addr:postcode":"35212",
    "addr:street":"Calle De Gardenia",
    "iso:country":"ES",
    "sg:address":"Calle de Gardenia, 40",
    "sg:city":"Estrella",
    "sg:orig_category":"Agencias Y Agentes Comerciales, Representantes",
    "sg:phone":"+34 928 13 20 88",
    "sg:postcode":"35212",
    "sg:province":"Las Palmas",
    "wof:name":"Gonzalez Robatto Fernandez Rafael",
    "wof:placetype":"venue"
},
  "geometry": {"coordinates":[-15.3815155029,28.0137329102],"type":"Point"}
}