{
  "type": "Feature",
  "properties": {
    "addr:full":"Calle de F. Toribio De Motolinia, 6 Zamora Zamora 49007",
    "addr:housenumber":"6",
    "addr:postcode":"49007",
    "addr:street":"Calle De F. Toribio De Motolinia",
    "iso:country":"ES",
    "sg:address":"Calle de F. Toribio De Motolinia, 6",
    "sg:city":"Zamora",
    "sg:orig_category":"Cr\u00cda De Animales",
    "sg:phone":"+34 980 52 35 62",
    "sg:postcode":"49007",
    "sg:province":"Zamora",
    "wof:name":"Colino Aguilar Enrique",
    "wof:placetype":"venue"
},
  "geometry": {"coordinates":[-5.7437601089,41.5091972351],"type":"Point"}
}