{
  "type": "Feature",
  "properties": {
    "addr:full":"Calle de San Juan De Letran, 2 Malaga M\u00e1laga 29012",
    "addr:housenumber":"2",
    "addr:postcode":"29012",
    "addr:street":"Calle De San;Malaga Ma\u0301Laga",
    "iso:country":"ES",
    "sg:address":"Calle de San Juan De Letran, 2",
    "sg:city":"Malaga",
    "sg:classifiers":[
        {
            "category":"Autos & Motor Vehicles",
            "subcategory":"Automobile Sales",
            "type":"Retail Goods"
        }
    ],
    "sg:phone":"+34 952 22 58 33",
    "sg:postcode":"29012",
    "sg:province":"M\u00e1laga",
    "wof:name":"Florido Luque Juan Antonio",
    "wof:placetype":"venue"
},
  "geometry": {"coordinates":[-4.417825222,36.7238998413],"type":"Point"}
}