{
  "type": "Feature",
  "properties": {
    "addr:full":"Avda Enrique Tierno Galvan (de), 7 Mejorada Campo Madrid 28840",
    "addr:postcode":"28840",
    "addr:street":"Avda Enrique Tierno",
    "iso:country":"ES",
    "sg:address":"Avda Enrique Tierno Galvan (de), 7",
    "sg:city":"Mejorada Campo",
    "sg:orig_category":"Juegos Y Juguetes (al Por Menor)",
    "sg:phone":"+34 916 68 01 28",
    "sg:postcode":"28840",
    "sg:province":"Madrid",
    "wof:name":"Alcol Y Vazquez S.l.",
    "wof:placetype":"venue"
},
  "geometry": {"coordinates":[-3.4854102135,40.3986320496],"type":"Point"}
}