{
  "type": "Feature",
  "properties": {
    "addr:full":"Calle de Ocho De Enero Kalea, 2 Gernika-lumo Vizcaya 48300",
    "addr:housenumber":"2",
    "addr:postcode":"48300",
    "addr:street":"Calle De Ocho De Enero Kalea",
    "iso:country":"ES",
    "sg:address":"Calle de Ocho De Enero Kalea, 2",
    "sg:city":"Gernika-lumo",
    "sg:orig_category":"Abogados",
    "sg:phone":"+34 946 25 84 57",
    "sg:postcode":"48300",
    "sg:province":"Vizcaya",
    "wof:name":"Dominguez Insausti Jose Luis",
    "wof:placetype":"venue"
},
  "geometry": {"coordinates":[-2.6774170399,43.3153877258],"type":"Point"}
}