{
  "type": "Feature",
  "properties": {
    "iso:country":"ES",
    "sg:address":"Carr Sant Isidre, 8",
    "sg:city":"Sant Joan De Les Abadesses",
    "sg:orig_category":"Organismos De Reclutamiento",
    "sg:phone":"+34 972 72 22 31",
    "sg:postcode":"17860",
    "sg:province":"Girona",
    "wof:name":"Human Side S.l.",
    "wof:placetype":"venue"
},
  "geometry": {"coordinates":[2.286634922,42.2347755432],"type":"Point"}
}