{
  "type": "Feature",
  "properties": {
    "addr:full":"Calle de Santa Matilde, 10 Madrid Madrid 28039",
    "addr:housenumber":"10",
    "addr:postcode":"madrid;28039",
    "addr:street":"Calle De Santa Matilde",
    "iso:country":"ES",
    "sg:address":"Calle de Santa Matilde, 10",
    "sg:city":"Madrid",
    "sg:orig_category":"Imprenta",
    "sg:phone":"+34 914 59 94 40",
    "sg:postcode":"28039",
    "sg:province":"Madrid",
    "wof:name":"Blas Gonzalez Enrique De",
    "wof:placetype":"venue"
},
  "geometry": {"coordinates":[-3.7078990936,40.4500617981],"type":"Point"}
}