{
  "type": "Feature",
  "properties": {
    "addr:full":"Ctra Malaga (de), 126 Granada Granada 18015",
    "addr:housenumber":"126",
    "addr:postcode":"18015",
    "addr:street":"Ctra Malaga De",
    "iso:country":"ES",
    "sg:address":"Ctra Malaga (de), 126",
    "sg:city":"Granada",
    "sg:orig_category":"Aparatos, Material Y Suministros Para Laboratorios",
    "sg:phone":"+34 958 27 76 29",
    "sg:postcode":"18015",
    "sg:province":"Granada",
    "wof:name":"Inquebor S.a.",
    "wof:placetype":"venue"
},
  "geometry": {"coordinates":[-3.6299889088,37.18983078],"type":"Point"}
}