{
  "type": "Feature",
  "properties": {
    "addr:full":"Carrer de Capita Arenas, 38 Barcelona Barcelona 08034",
    "addr:housenumber":"38",
    "addr:postcode":"08034",
    "addr:street":"Carrer De Capita Arenas",
    "iso:country":"ES",
    "sg:address":"Carrer de Capita Arenas, 38",
    "sg:city":"Barcelona",
    "sg:orig_category":"M\u00c9dicos: Anatom\u00cda Patol\u00d3gica Y Citolog\u00cda",
    "sg:phone":"+34 932 04 39 91",
    "sg:postcode":"08034",
    "sg:province":"Barcelona",
    "wof:name":"Anapat Sl",
    "wof:placetype":"venue"
},
  "geometry": {"coordinates":[2.1255464554,41.391544342],"type":"Point"}
}