{
  "type": "Feature",
  "properties": {
    "iso:country":"ES",
    "sg:address":"Calle de Calera, 9",
    "sg:city":"Burgos",
    "sg:orig_category":"Asociaciones, Instituciones De Consumidores Y Usuarios",
    "sg:phone":"+34 947 20 46 97",
    "sg:postcode":"09002",
    "sg:province":"Burgos",
    "wof:name":"Asociacion De Inquilinos",
    "wof:placetype":"venue"
},
  "geometry": {"coordinates":[-3.7014226913,42.3391265869],"type":"Point"}
}