{
  "type": "Feature",
  "properties": {
    "addr:full":"Carrer de Vidriers (dels), 24 Vendrell Tarragona 43700",
    "addr:housenumber":"24",
    "addr:postcode":"43700",
    "addr:street":"Carrer De Vidriers Dels",
    "iso:country":"ES",
    "sg:address":"Carrer de Vidriers (dels), 24",
    "sg:city":"Vendrell",
    "sg:orig_category":"Inmobiliaria (agencias)",
    "sg:phone":"+34 977 66 25 88",
    "sg:postcode":"43700",
    "sg:province":"Tarragona",
    "sg:website":"www.tecnodeco.com",
    "wof:name":"Tecnoarredo S.l.",
    "wof:placetype":"venue"
},
  "geometry": {"coordinates":[1.5313500166,41.2315216064],"type":"Point"}
}