{
  "type": "Feature",
  "properties": {
    "addr:full":"Carrascal, 8 Beniparrell Valencia 46469",
    "addr:housenumber":"8",
    "addr:postcode":"46469",
    "addr:street":"Carrascal",
    "iso:country":"ES",
    "sg:address":"Carrascal, 8",
    "sg:city":"Beniparrell",
    "sg:orig_category":"Fabricaci\u00d3n Y Distribuci\u00d3n De Colas, Masillas Y Encoladoras",
    "sg:phone":"+34 961 21 35 15",
    "sg:postcode":"46469",
    "sg:province":"Valencia",
    "sg:website":"www.quimicastamar.com",
    "wof:name":"Industria Quimica Tamar S.l.",
    "wof:placetype":"venue"
},
  "geometry": {"coordinates":[-0.4069446921,39.383895874],"type":"Point"}
}