{
  "type": "Feature",
  "properties": {
    "addr:full":"Calle de Doctor Manuel Diaz Munio, 18 Castro Urdiales Cantabria 39700",
    "addr:housenumber":"18",
    "addr:postcode":"39700",
    "addr:street":"Calle De Doctor Manuel Diaz Munio",
    "iso:country":"ES",
    "sg:address":"Calle de Doctor Manuel Diaz Munio, 18",
    "sg:city":"Castro Urdiales",
    "sg:orig_category":"Asociaciones Y Clubs Deportivos",
    "sg:phone":"+34 942 86 46 57",
    "sg:postcode":"39700",
    "sg:province":"Cantabria",
    "wof:name":"Sociedad Cantabra De Gimnasios S.l.",
    "wof:placetype":"venue"
},
  "geometry": {"coordinates":[-3.2174830437,43.3796195984],"type":"Point"}
}