{
  "type": "Feature",
  "properties": {
    "addr:full":"Carrer de Valencia, 319 Barcelona Barcelona 08009",
    "addr:housenumber":"319",
    "addr:postcode":"08009",
    "addr:street":"Carrer De Valencia",
    "iso:country":"ES",
    "sg:address":"Carrer de Valencia, 319",
    "sg:city":"Barcelona",
    "sg:orig_category":"Platos Preparados Refrigerados (fabricaci\u00d3n, Al Por Mayor)",
    "sg:phone":"+34 934 57 67 71",
    "sg:postcode":"08009",
    "sg:province":"Barcelona",
    "wof:name":"Poll-bo S.l.",
    "wof:placetype":"venue"
},
  "geometry": {"coordinates":[2.1683130264,41.3966636658],"type":"Point"}
}