{
  "type": "Feature",
  "properties": {
    "addr:full":"Carr Bassa Bona, 55 Almacelles Lleida 25100",
    "addr:housenumber":"55",
    "addr:postcode":"25100",
    "addr:street":"Carr Bassa Bona",
    "iso:country":"ES",
    "sg:address":"Carr Bassa Bona, 55",
    "sg:city":"Almacelles",
    "sg:orig_category":"Empresas De Carpinter\u00cda De Madera",
    "sg:phone":"+34 973 74 13 66",
    "sg:postcode":"25100",
    "sg:province":"Lleida",
    "wof:name":"Aldabo Vilamajo Sebastian",
    "wof:placetype":"venue"
},
  "geometry": {"coordinates":[0.4355893135,41.7336349487],"type":"Point"}
}