{
  "type": "Feature",
  "properties": {
    "addr:full":"Calle de Cronista Crespin Cuesta, 52 Victoria C\u00f3rdoba 14140",
    "addr:housenumber":"52",
    "addr:postcode":"14140",
    "addr:street":"Calle De Cronista Crespin Cuesta;Co\u0301Rdoba",
    "iso:country":"ES",
    "sg:address":"Calle de Cronista Crespin Cuesta, 52",
    "sg:city":"Victoria",
    "sg:orig_category":"Negocio De Materiales De Construcci\u00d3n",
    "sg:phone":"+34 957 30 81 92",
    "sg:postcode":"14140",
    "sg:province":"C\u00f3rdoba",
    "wof:name":"Manuel Galvez Mu\u00f1oz",
    "wof:placetype":"venue"
},
  "geometry": {"coordinates":[-4.8547053337,37.6837081909],"type":"Point"}
}