{
  "type": "Feature",
  "properties": {
    "addr:full":"Abelenda (pontellas), S/n Porri\u00f1o Pontevedra 36412",
    "addr:postcode":"36412",
    "addr:street":"Pontellas S / N",
    "iso:country":"ES",
    "sg:address":"Abelenda (pontellas), S/n",
    "sg:city":"Porri\u00f1o",
    "sg:orig_category":"Electrodom\u00c9sticos (al Por Menor)",
    "sg:phone":"+34 986 33 02 37",
    "sg:postcode":"36412",
    "sg:province":"Pontevedra",
    "wof:name":"Comercial Bugarin S.l",
    "wof:placetype":"venue"
},
  "geometry": {"coordinates":[-8.6552791595,42.1265144348],"type":"Point"}
}