{
  "type": "Feature",
  "properties": {
    "iso:country":"ES",
    "sg:address":"Pg Son Mas, 2",
    "sg:city":"Andratx",
    "sg:orig_category":"Pescader\u00cdas (al Por Menor)",
    "sg:phone":"+34 971 23 50 83",
    "sg:postcode":"07150",
    "sg:province":"Islas Baleares",
    "wof:name":"Pescados Paquita S.l.unipersonal",
    "wof:placetype":"venue"
},
  "geometry": {"coordinates":[2.4222929478,39.5758094788],"type":"Point"}
}