{
  "type": "Feature",
  "properties": {
    "addr:full":"Carrer de Amalia Soler, 5 Vilafranca Penedes Barcelona 08720",
    "addr:housenumber":"5",
    "addr:postcode":"08720",
    "addr:street":"Carrer De Amalia Soler;Penedes Barcelona",
    "iso:country":"ES",
    "sg:address":"Carrer de Amalia Soler, 5",
    "sg:city":"Vilafranca Penedes",
    "sg:orig_category":"Arquitectos",
    "sg:phone":"+34 938 19 90 44",
    "sg:postcode":"08720",
    "sg:province":"Barcelona",
    "wof:name":"Oller Recasens Josep Maria",
    "wof:placetype":"venue"
},
  "geometry": {"coordinates":[1.7015930414,41.3437232971],"type":"Point"}
}