{
  "type": "Feature",
  "properties": {
    "iso:country":"ES",
    "sg:address":"Carrer de Sant Esteve, 4",
    "sg:city":"Olot",
    "sg:orig_category":"Bisuter\u00cda, Joyer\u00cda, Relojer\u00cda (al Por Menor)",
    "sg:phone":"+34 972 26 83 83",
    "sg:postcode":"17800",
    "sg:province":"Girona",
    "wof:name":"Ferres Grabolosa Carme",
    "wof:placetype":"venue"
},
  "geometry": {"coordinates":[2.4892859459,42.1823310852],"type":"Point"}
}