{
  "type": "Feature",
  "properties": {
    "addr:full":"Calle de Arguelles, 17 Jerez De La Frontera C\u00e1diz 11401",
    "addr:housenumber":"17",
    "addr:postcode":"11401",
    "addr:street":"Calle De Arguelles",
    "iso:country":"ES",
    "sg:address":"Calle de Arguelles, 17",
    "sg:city":"Jerez De La Frontera",
    "sg:orig_category":"Ense\u00d1anza Variada",
    "sg:phone":"+34 956 33 41 08",
    "sg:postcode":"11401",
    "sg:province":"C\u00e1diz",
    "wof:name":"Maria Martin S.l.",
    "wof:placetype":"venue"
},
  "geometry": {"coordinates":[-6.1262454987,36.6775436401],"type":"Point"}
}