{
  "type": "Feature",
  "properties": {
    "addr:full":"Norte, 31 Norte Pontevedra 36939",
    "addr:postcode":"36939",
    "addr:street":"Norte 31 Norte",
    "iso:country":"ES",
    "sg:address":"Norte, 31",
    "sg:city":"Norte",
    "sg:classifiers":[
        {
            "category":"Recreation",
            "type":"Entertainment"
        }
    ],
    "sg:phone":"+34 986 32 30 66",
    "sg:postcode":"36939",
    "sg:province":"Pontevedra",
    "sg:tags":[
        "caza",
        "pr\u00c1ctica",
        "la",
        "de",
        "pesca",
        "y"
    ],
    "wof:name":"Pesca Bueu S.l.",
    "wof:placetype":"venue"
},
  "geometry": {"coordinates":[-8.7823858261,42.3033218384],"type":"Point"}
}