{
  "type": "Feature",
  "properties": {
    "iso:country":"ES",
    "sg:address":"Calle de Marques De San Juan, 11",
    "sg:city":"Valencia",
    "sg:orig_category":"Fisioterapia",
    "sg:phone":"+34 963 48 79 31",
    "sg:postcode":"46015",
    "sg:province":"Valencia",
    "wof:name":"Fisioturia Cb",
    "wof:placetype":"venue"
},
  "geometry": {"coordinates":[-0.3954280019,39.4786109924],"type":"Point"}
}