{
  "type": "Feature",
  "properties": {
    "addr:full":"Calle de Torrelaguna, 125 Madrid Madrid 28043",
    "addr:housenumber":"125",
    "addr:postcode":"28043",
    "addr:street":"Calle De Torrelaguna",
    "iso:country":"ES",
    "sg:address":"Calle de Torrelaguna, 125",
    "sg:city":"Madrid",
    "sg:orig_category":"Abogados",
    "sg:phone":"+34 914 13 50 45",
    "sg:postcode":"28043",
    "sg:province":"Madrid",
    "wof:name":"Catala Fernandez Marcelo",
    "wof:placetype":"venue"
},
  "geometry": {"coordinates":[-3.6607129574,40.4547615051],"type":"Point"}
}