{
  "type": "Feature",
  "properties": {
    "iso:country":"ES",
    "sg:address":"Calle de Libertad, 3",
    "sg:city":"Hellin",
    "sg:orig_category":"Madera (al Por Menor)",
    "sg:phone":"+34 967 30 21 23",
    "sg:postcode":"02400",
    "sg:province":"Albacete",
    "wof:name":"Lozano Sanchez Ramon",
    "wof:placetype":"venue"
},
  "geometry": {"coordinates":[-1.7028590441,38.5191345215],"type":"Point"}
}