{
  "type": "Feature",
  "properties": {
    "iso:country":"ES",
    "sg:address":"Calle de Alcalde Garcia Sanchez, 16",
    "sg:city":"Rota",
    "sg:orig_category":"Bisuter\u00cda, Joyer\u00cda, Relojer\u00cda (al Por Menor)",
    "sg:phone":"+34 956 81 09 64",
    "sg:postcode":"11520",
    "sg:province":"C\u00e1diz",
    "wof:name":"Vidal Gonzalez Diego",
    "wof:placetype":"venue"
},
  "geometry": {"coordinates":[-6.359899044,36.6197891235],"type":"Point"}
}