{
  "type": "Feature",
  "properties": {
    "addr:full":"Afores, S/n Vall Bianya Girona 17813",
    "addr:housenumber":"s / n",
    "addr:postcode":"17813",
    "addr:street":"Afores",
    "iso:country":"ES",
    "sg:address":"Afores, S/n",
    "sg:city":"Vall Bianya",
    "sg:classifiers":[
        {
            "category":"Manufacturing",
            "subcategory":"Building Materials",
            "type":"Manufacturing & Wholesale Goods"
        }
    ],
    "sg:phone":"+34 972 29 31 85",
    "sg:postcode":"17813",
    "sg:province":"Girona",
    "sg:tags":[
        "cemento",
        "y",
        "de",
        "fabricaci\u00d3n",
        "cal"
    ],
    "sg:website":"www.rodio.com",
    "wof:name":"Ute Collabos",
    "wof:placetype":"venue"
},
  "geometry": {"coordinates":[2.4543850422,42.2110366821],"type":"Point"}
}