{
  "type": "Feature",
  "properties": {
    "iso:country":"ES",
    "sg:address":"Carrer de Santa Madrona, 5",
    "sg:city":"Barcelona",
    "sg:orig_category":"Grafistas",
    "sg:phone":"+34 934 41 34 00",
    "sg:postcode":"08001",
    "sg:province":"Barcelona",
    "wof:name":"A.c. Retols Disseny S. L.",
    "wof:placetype":"venue"
},
  "geometry": {"coordinates":[2.1711549759,41.3756332397],"type":"Point"}
}