{
  "type": "Feature",
  "properties": {
    "addr:full":"Calle de Zumalakarregi Kalea, 18 Durango Vizcaya 48200",
    "addr:housenumber":"18",
    "addr:postcode":"48200",
    "addr:street":"Calle De Zumalakarregi Kalea",
    "iso:country":"ES",
    "sg:address":"Calle de Zumalakarregi Kalea, 18",
    "sg:city":"Durango",
    "sg:orig_category":"Asesor\u00cda Fiscal Y Jur\u00cddica",
    "sg:phone":"+34 946 81 86 36",
    "sg:postcode":"48200",
    "sg:province":"Vizcaya",
    "wof:name":"Gual Asesoria Oficial S. L.",
    "wof:placetype":"venue"
},
  "geometry": {"coordinates":[-2.6325509548,43.1685180664],"type":"Point"}
}