{
  "type": "Feature",
  "properties": {
    "iso:country":"ES",
    "sg:address":"Plaz Constitucion (la), 21",
    "sg:city":"Constantina",
    "sg:orig_category":"Peluqueros: De Se\u00d1oras",
    "sg:phone":"+34 955 88 13 93",
    "sg:postcode":"41450",
    "sg:province":"Sevilla",
    "wof:name":"Dominguez Cals Juan Pedro",
    "wof:placetype":"venue"
},
  "geometry": {"coordinates":[-5.6205692291,37.8749313354],"type":"Point"}
}