{
  "type": "Feature",
  "properties": {
    "addr:full":"Portocubelo, S/n Lira La Coru\u00f1a 15292",
    "addr:housenumber":"/ n",
    "addr:postcode":"15292",
    "addr:street":"Portocubelo S;Lira La Corun\u0303A",
    "iso:country":"ES",
    "sg:address":"Portocubelo, S/n",
    "sg:city":"Lira",
    "sg:orig_category":"Estudios Y Construcci\u00d3n De Acuarios Y Viveros",
    "sg:phone":"+34 981 76 11 05",
    "sg:postcode":"15292",
    "sg:province":"La Coru\u00f1a",
    "wof:name":"Curropesca S.l.",
    "wof:placetype":"venue"
},
  "geometry": {"coordinates":[-9.1201143265,42.774848938],"type":"Point"}
}