{
  "type": "Feature",
  "properties": {
    "addr:full":"Toro-norte, 5 Toro Zamora 49800",
    "addr:housenumber":"5",
    "addr:postcode":"49800",
    "addr:street":"Toro-Norte",
    "iso:country":"ES",
    "sg:address":"Toro-norte, 5",
    "sg:city":"Toro",
    "sg:orig_category":"Distribuci\u00d3n De Petr\u00d3leo Y Derivados",
    "sg:phone":"+34 980 69 47 78",
    "sg:postcode":"49800",
    "sg:province":"Zamora",
    "sg:website":"www.discomtes.es",
    "wof:name":"Discomtes Zamora S.l.",
    "wof:placetype":"venue"
},
  "geometry": {"coordinates":[-5.3906588554,41.525844574],"type":"Point"}
}