{
  "type": "Feature",
  "properties": {
    "addr:full":"Calle de Fresno, 5 Utrera Sevilla 41710",
    "addr:housenumber":"5",
    "addr:postcode":"41710",
    "addr:street":"Calle De Fresno",
    "iso:country":"ES",
    "sg:address":"Calle de Fresno, 5",
    "sg:city":"Utrera",
    "sg:orig_category":"Empresas De Carpinter\u00cda",
    "sg:phone":"+34 955 86 40 18",
    "sg:postcode":"41710",
    "sg:province":"Sevilla",
    "wof:name":"Perez Troncoso Juan",
    "wof:placetype":"venue"
},
  "geometry": {"coordinates":[-5.781083107,37.1861152649],"type":"Point"}
}