{
  "type": "Feature",
  "properties": {
    "iso:country":"ES",
    "sg:address":"Calle de Villarroel, 38",
    "sg:city":"Torrejon Ardoz",
    "sg:orig_category":"Discotecas Y Salas De Baile",
    "sg:phone":"+34 916 78 08 46",
    "sg:postcode":"28850",
    "sg:province":"Madrid",
    "wof:name":"Perez Rodriguez Jose",
    "wof:placetype":"venue"
},
  "geometry": {"coordinates":[-3.4580996037,40.4432983398],"type":"Point"}
}