{
  "type": "Feature",
  "properties": {
    "iso:country":"ES",
    "sg:address":"Avda Principal, 87",
    "sg:city":"Navas Del Marques",
    "sg:orig_category":"Carnicer\u00cdas, Carnicer\u00cdas",
    "sg:phone":"+34 918 97 14 22",
    "sg:postcode":"05230",
    "sg:province":"\u00c1vila",
    "wof:name":"Barbero Rodriguez David",
    "wof:placetype":"venue"
},
  "geometry": {"coordinates":[-4.3335318565,40.6028747559],"type":"Point"}
}