{
  "type": "Feature",
  "properties": {
    "addr:full":"Calle de Cigue\u00d1a (la), 28 Logro\u00f1o La Rioja 26004",
    "addr:housenumber":"28",
    "addr:postcode":"26004",
    "addr:street":"Calle De Ciguen\u0303A La;Rioja",
    "iso:country":"ES",
    "sg:address":"Calle de Cigue\u00d1a (la), 28",
    "sg:city":"Logro\u00f1o",
    "sg:orig_category":"Venta, Instalaci\u00d3n, Reparaci\u00d3n De Antenas Para Televisi\u00d3n",
    "sg:phone":"+34 941 24 35 00",
    "sg:postcode":"26004",
    "sg:province":"La Rioja",
    "wof:name":"Hernandez Murga Servando",
    "wof:placetype":"venue"
},
  "geometry": {"coordinates":[-2.4317581654,42.4650382996],"type":"Point"}
}