{
  "type": "Feature",
  "properties": {
    "addr:full":"Calle de Damaso Alonso, 5 Torrenueva Granada 18720",
    "addr:housenumber":"5",
    "addr:postcode":"18720",
    "addr:street":"Calle De Damaso Alonso",
    "iso:country":"ES",
    "sg:address":"Calle de Damaso Alonso, 5",
    "sg:city":"Torrenueva",
    "sg:orig_category":"Asociaciones Y Clubs Deportivos",
    "sg:phone":"+34 958 83 57 68",
    "sg:postcode":"18720",
    "sg:province":"Granada",
    "wof:name":"Sanchez Correa German",
    "wof:placetype":"venue"
},
  "geometry": {"coordinates":[-3.4887747765,36.7030258179],"type":"Point"}
}