{
  "type": "Feature",
  "properties": {
    "iso:country":"ES",
    "sg:address":"Autopista A Sesenta Y Seis, Km. 0025,0",
    "sg:city":"Rioseco De Tapia",
    "sg:orig_category":"Autopistas (explotaci\u00d3n, Guardia Civil Y Polic\u00cda)",
    "sg:phone":"+34 987 58 12 92",
    "sg:postcode":"24275",
    "sg:province":"Le\u00f3n",
    "wof:name":"El Mastins S.l.",
    "wof:placetype":"venue"
},
  "geometry": {"coordinates":[-5.7921690941,42.7282752991],"type":"Point"}
}