{
  "type": "Feature",
  "properties": {
    "iso:country":"ES",
    "sg:address":"Calle de Buensuceso, 40",
    "sg:city":"Granada",
    "sg:orig_category":"Maquinaria Para Industrias Diversas",
    "sg:phone":"+34 958 26 68 05",
    "sg:postcode":"18002",
    "sg:province":"Granada",
    "wof:name":"Mochon Romero Luis",
    "wof:placetype":"venue"
},
  "geometry": {"coordinates":[-3.6049230099,37.1742286682],"type":"Point"}
}