{
  "type": "Feature",
  "properties": {
    "iso:country":"ES",
    "sg:address":"Bo Besanguiz, S/n",
    "sg:city":"San Roman",
    "sg:orig_category":"Cr\u00cda De Animales",
    "sg:phone":"+34 946 25 55 58",
    "sg:postcode":"48392",
    "sg:province":"Vizcaya",
    "wof:name":"Ajuriagoika Aldana Itziar",
    "wof:placetype":"venue"
},
  "geometry": {"coordinates":[-2.6983149052,43.2783432007],"type":"Point"}
}