{
  "type": "Feature",
  "properties": {
    "iso:country":"ES",
    "sg:address":"Calle de Torre De Ugao, 5",
    "sg:city":"Ugao-miraballes",
    "sg:orig_category":"Pescader\u00cdas (al Por Menor)",
    "sg:phone":"+34 946 48 12 30",
    "sg:postcode":"48490",
    "sg:province":"Vizcaya",
    "wof:name":"Vizcarguenaga Otaola Jose Pablo",
    "wof:placetype":"venue"
},
  "geometry": {"coordinates":[-2.9021663666,43.1816711426],"type":"Point"}
}