{
  "type": "Feature",
  "properties": {
    "addr:full":"Calle de San Anton, 5 Almodovar Campo Ciudad Real 13580",
    "addr:housenumber":"5",
    "addr:postcode":"13580",
    "addr:street":"Calle De San Anton;Campo",
    "iso:country":"ES",
    "sg:address":"Calle de San Anton, 5",
    "sg:city":"Almodovar Campo",
    "sg:orig_category":"Art\u00cdculos De Regalo (al Por Menor)",
    "sg:phone":"+34 926 48 33 12",
    "sg:postcode":"13580",
    "sg:province":"Ciudad Real",
    "wof:name":"Vi\u00f1as Del Burgo Andres",
    "wof:placetype":"venue"
},
  "geometry": {"coordinates":[-4.1753287315,38.7116699219],"type":"Point"}
}