{
  "type": "Feature",
  "properties": {
    "iso:country":"ES",
    "sg:address":"Carrer de Galio, 1",
    "sg:city":"Magaluf",
    "sg:orig_category":"Caf\u00c9s, Bares, Cervecer\u00cdas",
    "sg:phone":"+34 971 13 15 12",
    "sg:postcode":"07181",
    "sg:province":"Islas Baleares",
    "wof:name":"Victoria Morais S.l.",
    "wof:placetype":"venue"
},
  "geometry": {"coordinates":[2.5344130993,39.5096282959],"type":"Point"}
}