{
  "type": "Feature",
  "properties": {
    "addr:full":"Calle de Juan Anton, 2 Madrid Madrid 28011",
    "addr:housenumber":"2",
    "addr:postcode":"28011",
    "addr:street":"Calle De Juan Anton",
    "iso:country":"ES",
    "sg:address":"Calle de Juan Anton, 2",
    "sg:city":"Madrid",
    "sg:orig_category":"Agencias Y Agentes Comerciales, Representantes",
    "sg:phone":"+34 914 63 92 94",
    "sg:postcode":"28011",
    "sg:province":"Madrid",
    "wof:name":"Hipoazteca S.l.",
    "wof:placetype":"venue"
},
  "geometry": {"coordinates":[-3.7372291088,40.410282135],"type":"Point"}
}