{
  "type": "Feature",
  "properties": {
    "addr:full":"Carr Vinyaters, Dels, 5 Consell Islas Baleares 07330",
    "addr:housenumber":"5",
    "addr:postcode":"07330",
    "addr:street":"Carr Vinyaters Dels",
    "iso:country":"ES",
    "sg:address":"Carr Vinyaters, Dels, 5",
    "sg:city":"Consell",
    "sg:orig_category":"Empresas De Carpinter\u00cda De Madera",
    "sg:phone":"+34 971 14 21 60",
    "sg:postcode":"07330",
    "sg:province":"Islas Baleares",
    "wof:name":"Pol Piza Sabastian",
    "wof:placetype":"venue"
},
  "geometry": {"coordinates":[2.8145840168,39.6686973572],"type":"Point"}
}