{
  "type": "Feature",
  "properties": {
    "iso:country":"ES",
    "sg:address":"Rua Molinera, 7",
    "sg:city":"Lalin",
    "sg:orig_category":"Frutas Y Legumbres Frescas (al Por Mayor)",
    "sg:phone":"+34 986 78 10 43",
    "sg:postcode":"36500",
    "sg:province":"Pontevedra",
    "wof:name":"Frujorge S.l.",
    "wof:placetype":"venue"
},
  "geometry": {"coordinates":[-8.1129713058,42.6598434448],"type":"Point"}
}