{
  "type": "Feature",
  "properties": {
    "addr:full":"Av Catalunya, 137 Casc Antic Barcelona 08150",
    "addr:housenumber":"137",
    "addr:postcode":"08150",
    "addr:street":"Av Catalunya",
    "iso:country":"ES",
    "sg:address":"Av Catalunya, 137",
    "sg:city":"Casc Antic",
    "sg:orig_category":"Frutas, Legumbres Frescas Y Tempranas (al Por Menor)",
    "sg:phone":"+34 935 73 08 18",
    "sg:postcode":"08150",
    "sg:province":"Barcelona",
    "wof:name":"Salas Gonzalez Albert",
    "wof:placetype":"venue"
},
  "geometry": {"coordinates":[2.2319469452,41.5694198608],"type":"Point"}
}