{
  "type": "Feature",
  "properties": {
    "iso:country":"ES",
    "sg:address":"Calle de Navarra, 3",
    "sg:city":"Madrid",
    "sg:orig_category":"Alimentaci\u00d3n General (al Por Menor)",
    "sg:phone":"+34 914 59 28 16",
    "sg:postcode":"28039",
    "sg:province":"Madrid",
    "wof:name":"Hao Hua Wu",
    "wof:placetype":"venue"
},
  "geometry": {"coordinates":[-3.7031245232,40.4535217285],"type":"Point"}
}