{
  "type": "Feature",
  "properties": {
    "iso:country":"ES",
    "sg:address":"Avda Ruzafa, 8",
    "sg:city":"Benidorm",
    "sg:orig_category":"Institutos De Belleza",
    "sg:phone":"+34 966 80 49 53",
    "sg:postcode":"03500",
    "sg:province":"Alicante",
    "wof:name":"Centro De Belleza Zambra S.l.",
    "wof:placetype":"venue"
},
  "geometry": {"coordinates":[-0.1739459932,38.5365180969],"type":"Point"}
}