{
  "type": "Feature",
  "properties": {
    "iso:country":"ES",
    "sg:address":"Calle de Luciente, 13",
    "sg:city":"Madrid",
    "sg:orig_category":"Fabricaci\u00d3n De Enlosados, Soler\u00cdas",
    "sg:phone":"+34 913 65 52 37",
    "sg:postcode":"28005",
    "sg:province":"Madrid",
    "wof:name":"Azulejos Nadal S.l.",
    "wof:placetype":"venue"
},
  "geometry": {"coordinates":[-3.7113461494,40.4104766846],"type":"Point"}
}