{
  "type": "Feature",
  "properties": {
    "iso:country":"ES",
    "sg:address":"Carr Adoberies, 7",
    "sg:city":"Tremp",
    "sg:orig_category":"Insecticidas, Fumigaci\u00d3n",
    "sg:phone":"+34 973 65 09 64",
    "sg:postcode":"25620",
    "sg:province":"Lleida",
    "wof:name":"Llados Farre Concepcio",
    "wof:placetype":"venue"
},
  "geometry": {"coordinates":[0.8942300081,42.1695785522],"type":"Point"}
}