{
  "type": "Feature",
  "properties": {
    "addr:full":"Cmno Isasi, 24 Llodio \u00c1lava 01400",
    "addr:housenumber":"24",
    "addr:postcode":"01400",
    "addr:street":"Cmno Isasi",
    "iso:country":"ES",
    "sg:address":"Cmno Isasi, 24",
    "sg:city":"Llodio",
    "sg:orig_category":"Afiladoras, Pulidoras Y Bru\u00d1idoras",
    "sg:phone":"+34 946 72 44 53",
    "sg:postcode":"01400",
    "sg:province":"\u00c1lava",
    "wof:name":"Suarez Martinez Victoriano",
    "wof:placetype":"venue"
},
  "geometry": {"coordinates":[-2.9712109566,43.1509933472],"type":"Point"}
}