{
  "type": "Feature",
  "properties": {
    "addr:full":"Calle de Pedro Unanue, 14 Madrid Madrid 28045",
    "addr:housenumber":"14",
    "addr:postcode":"madrid;28045",
    "addr:street":"Calle De Pedro Unanue",
    "iso:country":"ES",
    "sg:address":"Calle de Pedro Unanue, 14",
    "sg:city":"Madrid",
    "sg:orig_category":"Ense\u00d1ante, Direcci\u00d3n",
    "sg:phone":"+34 914 68 18 11",
    "sg:postcode":"28045",
    "sg:province":"Madrid",
    "wof:name":"Dominguez Gomez Sebastiana",
    "wof:placetype":"venue"
},
  "geometry": {"coordinates":[-3.6949439049,40.403465271],"type":"Point"}
}