{
  "type": "Feature",
  "properties": {
    "addr:full":"Avd Poeta M. Reina, 93 Puente-genil C\u00f3rdoba 14500",
    "addr:housenumber":"93",
    "addr:postcode":"14500",
    "addr:street":"Avd Poeta M. Reina;Co\u0301Rdoba",
    "iso:country":"ES",
    "sg:address":"Avd Poeta M. Reina, 93",
    "sg:city":"Puente-genil",
    "sg:orig_category":"Molduras, Junquillos, Listones Y Molduras Perforadas",
    "sg:phone":"+34 957 60 10 44",
    "sg:postcode":"14500",
    "sg:province":"C\u00f3rdoba",
    "wof:name":"Gambin Ramon Manuel",
    "wof:placetype":"venue"
},
  "geometry": {"coordinates":[-4.7646889687,37.3928565979],"type":"Point"}
}