{
  "type": "Feature",
  "properties": {
    "addr:full":"Calle de Fuente Del Tesoro, 56 Sierra Nevada Granada 18196",
    "addr:housenumber":"56",
    "addr:postcode":"18196",
    "addr:street":"Calle De Fuente Del Tesoro;Sierra Nevada Granada",
    "iso:country":"ES",
    "sg:address":"Calle de Fuente Del Tesoro, 56",
    "sg:city":"Sierra Nevada",
    "sg:orig_category":"Inmobiliaria (agencias)",
    "sg:phone":"+34 958 48 14 09",
    "sg:postcode":"18196",
    "sg:province":"Granada",
    "wof:name":"Inmobiliaria Del Veleta S.l.",
    "wof:placetype":"venue"
},
  "geometry": {"coordinates":[-3.4015190601,37.0969848633],"type":"Point"}
}