{
  "type": "Feature",
  "properties": {
    "iso:country":"ES",
    "sg:address":"Calle de Puente De Muerte Y Vida (del), 1",
    "sg:city":"Segovia",
    "sg:orig_category":"Camiser\u00cda Y Ropa Interior Masculina (al Por Menor)",
    "sg:phone":"+34 921 42 53 21",
    "sg:postcode":"40005",
    "sg:province":"Segovia",
    "wof:name":"Jimenez Y Lorca S.l.",
    "wof:placetype":"venue"
},
  "geometry": {"coordinates":[-4.1165480614,40.9447021484],"type":"Point"}
}