{
  "type": "Feature",
  "properties": {
    "iso:country":"ES",
    "sg:address":"Ctra Arta, 2",
    "sg:city":"Port D'alcudia",
    "sg:orig_category":"Restaurantes",
    "sg:phone":"+34 971 54 85 16",
    "sg:postcode":"07410",
    "sg:province":"Islas Baleares",
    "wof:name":"Tang Lau Fiu Tong",
    "wof:placetype":"venue"
},
  "geometry": {"coordinates":[3.120937109,39.8396034241],"type":"Point"}
}