{
  "type": "Feature",
  "properties": {
    "addr:full":"Calle de Miguel De Cervantes, 16 Orotava Santa Cruz De Tenerife 38300",
    "addr:housenumber":"16",
    "addr:postcode":"38300",
    "addr:street":"Calle De Miguel De Cervantes",
    "iso:country":"ES",
    "sg:address":"Calle de Miguel De Cervantes, 16",
    "sg:city":"Orotava",
    "sg:orig_category":"Centros Empresariales",
    "sg:phone":"+34 922 32 38 24",
    "sg:postcode":"38300",
    "sg:province":"Santa Cruz De Tenerife",
    "wof:name":"Hernandez Buendia Antonio",
    "wof:placetype":"venue"
},
  "geometry": {"coordinates":[-16.5184326172,28.3924617767],"type":"Point"}
}