{
  "type": "Feature",
  "properties": {
    "addr:full":"Calle de Barranquet, 12 Chilches Castell\u00f3n 12592",
    "addr:housenumber":"12",
    "addr:postcode":"12592",
    "addr:street":"Calle De Barranquet",
    "iso:country":"ES",
    "sg:address":"Calle de Barranquet, 12",
    "sg:city":"Chilches",
    "sg:orig_category":"Negocio De Materiales De Construcci\u00d3n",
    "sg:phone":"+34 964 59 03 46",
    "sg:postcode":"12592",
    "sg:province":"Castell\u00f3n",
    "wof:name":"Fabio Alemany S.l.",
    "wof:placetype":"venue"
},
  "geometry": {"coordinates":[-0.1452547014,39.8087806702],"type":"Point"}
}