{
  "type": "Feature",
  "properties": {
    "addr:full":"Carrer de Ausias Marc, 163 Barcelona Barcelona 08013",
    "addr:housenumber":"163",
    "addr:postcode":"08013",
    "addr:street":"Carrer De Ausias Marc",
    "iso:country":"ES",
    "sg:address":"Carrer de Ausias Marc, 163",
    "sg:city":"Barcelona",
    "sg:orig_category":"Farmacias",
    "sg:phone":"+34 932 45 00 64",
    "sg:postcode":"08013",
    "sg:province":"Barcelona",
    "wof:name":"Canal Torras Maria Montserrat",
    "wof:placetype":"venue"
},
  "geometry": {"coordinates":[2.1843709946,41.3980903625],"type":"Point"}
}