{
  "type": "Feature",
  "properties": {
    "iso:country":"ES",
    "sg:address":"Carr Casetes, 33",
    "sg:city":"Massamagrell",
    "sg:orig_category":"Reposter\u00cdas",
    "sg:phone":"+34 961 44 10 76",
    "sg:postcode":"46130",
    "sg:province":"Valencia",
    "wof:name":"Campos Carbonell Teresa",
    "wof:placetype":"venue"
},
  "geometry": {"coordinates":[-0.3325619996,39.5714111328],"type":"Point"}
}