{
  "type": "Feature",
  "properties": {
    "addr:full":"Calle de Ingeniero Bryant, S/n Flota Murcia 30007",
    "addr:housenumber":"s / n",
    "addr:postcode":"30007",
    "addr:street":"Calle De Ingeniero Bryant",
    "iso:country":"ES",
    "sg:address":"Calle de Ingeniero Bryant, S/n",
    "sg:city":"Flota",
    "sg:orig_category":"Ingenier\u00cda, Centros De Estudios (diversos)",
    "sg:phone":"+34 968 24 28 01",
    "sg:postcode":"30007",
    "sg:province":"Murcia",
    "wof:name":"O.t.k. Ingenieros S.l.",
    "wof:placetype":"venue"
},
  "geometry": {"coordinates":[-1.1142389774,37.9970092773],"type":"Point"}
}