{
  "type": "Feature",
  "properties": {
    "addr:full":"Avda Doctor Garcia Tapia, 66 Madrid Madrid 28030",
    "addr:housenumber":"66",
    "addr:postcode":"madrid;28030",
    "addr:street":"Avda Doctor Garcia Tapia",
    "iso:country":"ES",
    "sg:address":"Avda Doctor Garcia Tapia, 66",
    "sg:city":"Madrid",
    "sg:orig_category":"Asociaciones, Organismos Culturales Y Socioeducativos",
    "sg:phone":"+34 914 39 08 04",
    "sg:postcode":"28030",
    "sg:province":"Madrid",
    "wof:name":"Federacion Espa\u00f1ola De Camping Y Caravaning",
    "wof:placetype":"venue"
},
  "geometry": {"coordinates":[-3.6533300877,40.4121284485],"type":"Point"}
}