{
  "type": "Feature",
  "properties": {
    "iso:country":"ES",
    "sg:address":"Calle de Calinda, 1",
    "sg:city":"Valladolid",
    "sg:orig_category":"Art\u00cdculos De Madera (fabricaci\u00d3n Y Al Por Mayor)",
    "sg:phone":"+34 983 20 06 20",
    "sg:postcode":"47012",
    "sg:province":"Valladolid",
    "sg:website":"www.avema.es/julsot",
    "wof:name":"Julsot S.l.",
    "wof:placetype":"venue"
},
  "geometry": {"coordinates":[-4.6760396957,41.6359100342],"type":"Point"}
}