{
  "type": "Feature",
  "properties": {
    "iso:country":"ES",
    "sg:address":"Calle de El Belimbre, 53",
    "sg:city":"Santa Maria De Huerta",
    "sg:orig_category":"Electricidad: Instaladores",
    "sg:phone":"+34 975 32 74 77",
    "sg:postcode":"42260",
    "sg:province":"Soria",
    "wof:name":"Milla Perez Jesus",
    "wof:placetype":"venue"
},
  "geometry": {"coordinates":[-2.1783490181,41.2594795227],"type":"Point"}
}