{
  "type": "Feature",
  "properties": {
    "addr:full":"Calle de Sol, 20 Coru\u00d1a La Coru\u00f1a 15003",
    "addr:housenumber":"20",
    "addr:postcode":"15003",
    "addr:street":"Calle De Sol;La Corun\u0303A",
    "iso:country":"ES",
    "sg:address":"Calle de Sol, 20",
    "sg:city":"Coru\u00d1a",
    "sg:orig_category":"Ingenier\u00cda, Centros De Estudios (diversos)",
    "sg:phone":"+34 981 21 03 06",
    "sg:postcode":"15003",
    "sg:province":"La Coru\u00f1a",
    "wof:name":"Camprubi Arque Juan Maria",
    "wof:placetype":"venue"
},
  "geometry": {"coordinates":[-8.4024600983,43.3724975586],"type":"Point"}
}