{
  "type": "Feature",
  "properties": {
    "addr:full":"Calle de Castillo De Aysa, 4 Madrid Madrid 28043",
    "addr:housenumber":"4",
    "addr:postcode":"28043",
    "addr:street":"Calle De Castillo;Aysa",
    "iso:country":"ES",
    "sg:address":"Calle de Castillo De Aysa, 4",
    "sg:city":"Madrid",
    "sg:orig_category":"Contenedores (mercanc\u00cdas)",
    "sg:phone":"+34 913 00 02 12",
    "sg:postcode":"28043",
    "sg:province":"Madrid",
    "wof:name":"Velpa S.a.",
    "wof:placetype":"venue"
},
  "geometry": {"coordinates":[-3.6335420609,40.458026886],"type":"Point"}
}