{
  "type": "Feature",
  "properties": {
    "iso:country":"ES",
    "sg:address":"Calle de Sierra Gador, 41",
    "sg:city":"Madrid",
    "sg:orig_category":"Molduras, Junquillos, Listones Y Molduras Perforadas",
    "sg:phone":"+34 913 31 13 24",
    "sg:postcode":"28031",
    "sg:province":"Madrid",
    "wof:name":"Sanz Ramirez Jose Maria",
    "wof:placetype":"venue"
},
  "geometry": {"coordinates":[-3.6258590221,40.377620697],"type":"Point"}
}