{
  "type": "Feature",
  "properties": {
    "addr:full":"Ctra Casalarreina, 33 Zarraton La Rioja 26291",
    "addr:housenumber":"33",
    "addr:postcode":"26291",
    "addr:street":"Ctra Casalarreina;Rioja",
    "iso:country":"ES",
    "sg:address":"Ctra Casalarreina, 33",
    "sg:city":"Zarraton",
    "sg:orig_category":"Ferreter\u00cda Artesanal",
    "sg:phone":"+34 941 32 43 20",
    "sg:postcode":"26291",
    "sg:province":"La Rioja",
    "wof:name":"Hijos De Alejandro Tofe S.cv.",
    "wof:placetype":"venue"
},
  "geometry": {"coordinates":[-2.8898940086,42.482509613],"type":"Point"}
}