{
  "type": "Feature",
  "properties": {
    "addr:full":"Av Pere El Cerimonios, 81 Reus Tarragona 43205",
    "addr:housenumber":"81",
    "addr:postcode":"43205",
    "addr:street":"Av Pere El Cerimonios",
    "iso:country":"ES",
    "sg:address":"Av Pere El Cerimonios, 81",
    "sg:city":"Reus",
    "sg:orig_category":"Reposter\u00cdas",
    "sg:phone":"+34 977 75 49 48",
    "sg:postcode":"43205",
    "sg:province":"Tarragona",
    "wof:name":"Germipa S. L.",
    "wof:placetype":"venue"
},
  "geometry": {"coordinates":[1.1065709591,41.1469268799],"type":"Point"}
}