{
  "type": "Feature",
  "properties": {
    "addr:full":"Carr Pintor Ferrer Cabrera, 3 Cullera Valencia 46400",
    "addr:housenumber":"3",
    "addr:postcode":"46400",
    "addr:street":"Carr Pintor Ferrer Cabrera",
    "iso:country":"ES",
    "sg:address":"Carr Pintor Ferrer Cabrera, 3",
    "sg:city":"Cullera",
    "sg:orig_category":"Pizzer\u00cdas",
    "sg:phone":"+34 961 72 18 05",
    "sg:postcode":"46400",
    "sg:province":"Valencia",
    "wof:name":"Ficcus Restauracion S.l.",
    "wof:placetype":"venue"
},
  "geometry": {"coordinates":[-0.245656997,39.1639976501],"type":"Point"}
}