{
  "type": "Feature",
  "properties": {
    "iso:country":"ES",
    "sg:address":"Calle de Cartagena, 23",
    "sg:city":"Linea De La Concepcion",
    "sg:orig_category":"Farmacias",
    "sg:phone":"+34 956 17 27 85",
    "sg:postcode":"11300",
    "sg:province":"C\u00e1diz",
    "wof:name":"Sanchez Medina Maria De Los Angeles",
    "wof:placetype":"venue"
},
  "geometry": {"coordinates":[-5.3387975693,36.1764907837],"type":"Point"}
}