{
  "type": "Feature",
  "properties": {
    "iso:country":"ES",
    "sg:address":"Carrer de Mallorca, 468",
    "sg:city":"Barcelona",
    "sg:orig_category":"Farmacias",
    "sg:phone":"+34 932 32 94 56",
    "sg:postcode":"08013",
    "sg:province":"Barcelona",
    "wof:name":"Puig De Dou Maria",
    "wof:placetype":"venue"
},
  "geometry": {"coordinates":[2.1785600185,41.4056549072],"type":"Point"}
}