{
  "type": "Feature",
  "properties": {
    "addr:full":"Pase Alcalde Sanchez Prados, S/n Ceuta Ceuta 51001",
    "addr:housenumber":"s",
    "addr:postcode":"51001",
    "addr:street":"Alcalde;Prados;/ N",
    "iso:country":"ES",
    "sg:address":"Pase Alcalde Sanchez Prados, S/n",
    "sg:city":"Ceuta",
    "sg:orig_category":"Diarios, Revistas Y Boletines (suscripciones)",
    "sg:phone":"+34 956 51 76 43",
    "sg:postcode":"51001",
    "sg:province":"Ceuta",
    "wof:name":"Garre Barnet Carlos",
    "wof:placetype":"venue"
},
  "geometry": {"coordinates":[-5.3148088455,35.8882064819],"type":"Point"}
}