{
  "type": "Feature",
  "properties": {
    "addr:full":"Plaz Espa\u00d1a, 2 Leganes Madrid 28911",
    "addr:housenumber":"2",
    "addr:postcode":"28911",
    "addr:street":"Plaz Espan\u0303A",
    "iso:country":"ES",
    "sg:address":"Plaz Espa\u00d1a, 2",
    "sg:city":"Leganes",
    "sg:classifiers":[
        {
            "category":"Personal",
            "subcategory":"Barber",
            "type":"Services"
        }
    ],
    "sg:phone":"+34 916 94 96 81",
    "sg:postcode":"28911",
    "sg:province":"Madrid",
    "sg:tags":[
        "caballeros",
        "de",
        "peluqueros"
    ],
    "wof:name":"Borrero Casanova Sebastian",
    "wof:placetype":"venue"
},
  "geometry": {"coordinates":[-3.7649979591,40.3278541565],"type":"Point"}
}