{
  "type": "Feature",
  "properties": {
    "addr:full":"Carr Carme, 271 Girona Girona 17004",
    "addr:housenumber":"271",
    "addr:postcode":"17004",
    "addr:street":"Carr Carme",
    "iso:country":"ES",
    "sg:address":"Carr Carme, 271",
    "sg:city":"Girona",
    "sg:orig_category":"Agencias Y Agentes Comerciales, Representantes",
    "sg:phone":"+34 972 21 43 32",
    "sg:postcode":"17004",
    "sg:province":"Girona",
    "wof:name":"Sole Celiu Jordi",
    "wof:placetype":"venue"
},
  "geometry": {"coordinates":[2.8303849697,41.9741744995],"type":"Point"}
}