{
  "type": "Feature",
  "properties": {
    "addr:full":"Calle de Zortziko, 4 Berriozar Navarra 31013",
    "addr:housenumber":"4",
    "addr:postcode":"31013",
    "addr:street":"Calle De Zortziko",
    "iso:country":"ES",
    "sg:address":"Calle de Zortziko, 4",
    "sg:city":"Berriozar",
    "sg:orig_category":"Supermercados Y Hipermercados",
    "sg:phone":"+34 948 30 01 79",
    "sg:postcode":"31013",
    "sg:province":"Navarra",
    "wof:name":"Ramirez Garcia Fernando",
    "wof:placetype":"venue"
},
  "geometry": {"coordinates":[-1.6677060127,42.8332443237],"type":"Point"}
}