{
  "type": "Feature",
  "properties": {
    "iso:country":"ES",
    "sg:address":"Carrer de Torrassa (de La), S/n",
    "sg:city":"Salou",
    "sg:orig_category":"Producci\u00d3n De Abonos Y De Fertilizantes",
    "sg:phone":"+34 977 38 31 79",
    "sg:postcode":"43840",
    "sg:province":"Tarragona",
    "wof:name":"Magrisa Soluciones Agricolas S. L.",
    "wof:placetype":"venue"
},
  "geometry": {"coordinates":[1.1495649815,41.0665817261],"type":"Point"}
}