{
  "type": "Feature",
  "properties": {
    "addr:full":"Calle de Cristo, 6 Consuegra Toledo 45700",
    "addr:housenumber":"6",
    "addr:postcode":"45700",
    "addr:street":"Calle De Cristo",
    "iso:country":"ES",
    "sg:address":"Calle de Cristo, 6",
    "sg:city":"Consuegra",
    "sg:orig_category":"Cl\u00cdnicas Dentales",
    "sg:phone":"+34 925 48 06 58",
    "sg:postcode":"45700",
    "sg:province":"Toledo",
    "wof:name":"Ortiz Merino Antonio",
    "wof:placetype":"venue"
},
  "geometry": {"coordinates":[-3.6069796085,39.4595336914],"type":"Point"}
}