{
  "type": "Feature",
  "properties": {
    "addr:full":"Av Enric Prat De La Riba, 4 Prat Llobregat Barcelona 08820",
    "addr:housenumber":"4",
    "addr:postcode":"08820",
    "addr:street":"Av Enric Prat De La Riba;Llobregat",
    "iso:country":"ES",
    "sg:address":"Av Enric Prat De La Riba, 4",
    "sg:city":"Prat Llobregat",
    "sg:orig_category":"Mec\u00c1nico Del Autom\u00d3vil",
    "sg:phone":"+34 933 70 99 02",
    "sg:postcode":"08820",
    "sg:province":"Barcelona",
    "wof:name":"Tamayo Ortiz Manuel",
    "wof:placetype":"venue"
},
  "geometry": {"coordinates":[2.0919849873,41.3307952881],"type":"Point"}
}