{
  "type": "Feature",
  "properties": {
    "addr:full":"Carrer de Buscarons, 22 Barcelona Barcelona 08022",
    "addr:housenumber":"22",
    "addr:postcode":"08022",
    "addr:street":"Carrer De Buscarons",
    "iso:country":"ES",
    "sg:address":"Carrer de Buscarons, 22",
    "sg:city":"Barcelona",
    "sg:orig_category":"Psic\u00d3logos",
    "sg:phone":"+34 934 34 24 80",
    "sg:postcode":"08022",
    "sg:province":"Barcelona",
    "wof:name":"De Los Santos Arnau Alicia",
    "wof:placetype":"venue"
},
  "geometry": {"coordinates":[2.1383099556,41.4061012268],"type":"Point"}
}