{
  "type": "Feature",
  "properties": {
    "iso:country":"ES",
    "sg:address":"Carrer de Doctor Pi I Sunyer, 17",
    "sg:city":"Roses",
    "sg:orig_category":"Arquitectos",
    "sg:phone":"+34 972 15 31 12",
    "sg:postcode":"17480",
    "sg:province":"Girona",
    "wof:name":"Taller Estudi D'arquitectura Tecnica S.l.",
    "wof:placetype":"venue"
},
  "geometry": {"coordinates":[3.1753818989,42.2623901367],"type":"Point"}
}