{
  "type": "Feature",
  "properties": {
    "addr:full":"Cruce Carreteras, S/n Cornellana Asturias 33850",
    "addr:housenumber":"s / n",
    "addr:postcode":"33850",
    "iso:country":"ES",
    "sg:address":"Cruce Carreteras, S/n",
    "sg:city":"Cornellana",
    "sg:orig_category":"Distribuci\u00d3n De Petr\u00d3leo Y Derivados",
    "sg:phone":"+34 985 83 40 88",
    "sg:postcode":"33850",
    "sg:province":"Asturias",
    "wof:name":"Estacion De Servicio Camper C.b.",
    "wof:placetype":"venue"
},
  "geometry": {"coordinates":[-6.3453469276,43.4185028076],"type":"Point"}
}