{
  "type": "Feature",
  "properties": {
    "addr:full":"Av Torrent, D'es, 10 Manacor Islas Baleares 07500",
    "addr:housenumber":"10",
    "addr:postcode":"07500",
    "addr:street":"Av Torrent D'Es",
    "iso:country":"ES",
    "sg:address":"Av Torrent, D'es, 10",
    "sg:city":"Manacor",
    "sg:orig_category":"Ense\u00d1anza: Comercio, Gesti\u00d3n, Inform\u00c1tica",
    "sg:phone":"+34 971 55 22 41",
    "sg:postcode":"07500",
    "sg:province":"Islas Baleares",
    "sg:website":"www.aula-digital.com",
    "wof:name":"Aula Digital Manacor S.l.",
    "wof:placetype":"venue"
},
  "geometry": {"coordinates":[3.2087171078,39.5662155151],"type":"Point"}
}