{
  "type": "Feature",
  "properties": {
    "addr:full":"Cro Sant Joan, 35 S. Feliu Guixols Girona 17220",
    "addr:housenumber":"35",
    "addr:postcode":"17220",
    "addr:street":"Joan;S. Feliu Guixols",
    "iso:country":"ES",
    "sg:address":"Cro Sant Joan, 35",
    "sg:city":"S. Feliu Guixols",
    "sg:orig_category":"Institutos De Belleza",
    "sg:phone":"+34 972 32 14 90",
    "sg:postcode":"17220",
    "sg:province":"Girona",
    "wof:name":"Turro Vicens Rosa",
    "wof:placetype":"venue"
},
  "geometry": {"coordinates":[3.0284759998,41.7813262939],"type":"Point"}
}