{
  "type": "Feature",
  "properties": {
    "addr:full":"Ctro Cial Miramar, S/n Fuengirola M\u00e1laga 29640",
    "addr:housenumber":"s / n",
    "addr:postcode":"29640",
    "addr:street":"Ma\u0301Laga",
    "iso:country":"ES",
    "sg:address":"Ctro Cial Miramar, S/n",
    "sg:city":"Fuengirola",
    "sg:classifiers":[
        {
            "category":"Casinos & Gambling",
            "type":"Entertainment"
        }
    ],
    "sg:phone":"+34 952 58 81 00",
    "sg:postcode":"29640",
    "sg:province":"M\u00e1laga",
    "sg:tags":[
        "locale",
        "de",
        "juego"
    ],
    "sg:website":"www.logohobby.es",
    "wof:name":"Logistica Del Hobby S.a.",
    "wof:placetype":"venue"
},
  "geometry": {"coordinates":[-4.6330537796,36.5426368713],"type":"Point"}
}