{
  "type": "Feature",
  "properties": {
    "addr:full":"Avda La Estacion, 82 Ortuella Vizcaya 48530",
    "addr:housenumber":"82",
    "addr:postcode":"48530",
    "addr:street":"Avda La Estacion",
    "iso:country":"ES",
    "sg:address":"Avda La Estacion, 82",
    "sg:city":"Ortuella",
    "sg:orig_category":"Molduras, Junquillos, Listones Y Molduras Perforadas",
    "sg:phone":"+34 946 64 21 90",
    "sg:postcode":"48530",
    "sg:province":"Vizcaya",
    "wof:name":"Pedro Palacios Amparo De",
    "wof:placetype":"venue"
},
  "geometry": {"coordinates":[-3.0591239929,43.3112258911],"type":"Point"}
}