{
  "type": "Feature",
  "properties": {
    "iso:country":"ES",
    "sg:address":"Calle de Jose Maria Peman, 21",
    "sg:city":"Elda",
    "sg:orig_category":"Asesor\u00cda Sobre Comunicaci\u00d3n De Empresas",
    "sg:phone":"+34 965 38 16 91",
    "sg:postcode":"03600",
    "sg:province":"Alicante",
    "wof:name":"Garcia Soriano Lourdes",
    "wof:placetype":"venue"
},
  "geometry": {"coordinates":[-0.7932199836,38.4766311646],"type":"Point"}
}