{
  "type": "Feature",
  "properties": {
    "addr:full":"Calle de Bailen, 12 Vall D'uixo Castell\u00f3n 12600",
    "addr:housenumber":"12",
    "addr:postcode":"12600",
    "addr:street":"Calle De Bailen",
    "iso:country":"ES",
    "sg:address":"Calle de Bailen, 12",
    "sg:city":"Vall D'uixo",
    "sg:orig_category":"Tiendas De Grano, Frutas Y Legumbres Secas (al Por Menor)",
    "sg:phone":"+34 964 66 16 60",
    "sg:postcode":"12600",
    "sg:province":"Castell\u00f3n",
    "wof:name":"Frutos Secos Cocot S.l.",
    "wof:placetype":"venue"
},
  "geometry": {"coordinates":[-0.2405309975,39.8234176636],"type":"Point"}
}