{
  "type": "Feature",
  "properties": {
    "addr:full":"Barr Presmanes, 93 Gajano Cantabria 39792",
    "addr:housenumber":"93",
    "addr:postcode":"39792",
    "iso:country":"ES",
    "sg:address":"Barr Presmanes, 93",
    "sg:city":"Gajano",
    "sg:orig_category":"Vinos Y Licores (venta Al Por Menor)",
    "sg:phone":"+34 942 50 24 19",
    "sg:postcode":"39792",
    "sg:province":"Cantabria",
    "wof:name":"Saiz Marina Jose Maria",
    "wof:placetype":"venue"
},
  "geometry": {"coordinates":[-3.7661499977,43.4118690491],"type":"Point"}
}