{
  "type": "Feature",
  "properties": {
    "iso:country":"ES",
    "sg:address":"Alam Principal, 17",
    "sg:city":"Malaga",
    "sg:orig_category":"Fabricaci\u00d3n De Juegos Y Juguetes",
    "sg:phone":"+34 952 60 95 71",
    "sg:postcode":"29001",
    "sg:province":"M\u00e1laga",
    "wof:name":"Comercial Recreativos Malaga S.a.",
    "wof:placetype":"venue"
},
  "geometry": {"coordinates":[-4.422249794,36.7173957825],"type":"Point"}
}