{
  "type": "Feature",
  "properties": {
    "iso:country":"ES",
    "sg:address":"Las Mariposas, 11",
    "sg:city":"Palmanova",
    "sg:orig_category":"Asesor\u00cda Sobre Comunicaci\u00d3n De Empresas",
    "sg:phone":"+34 971 68 18 52",
    "sg:postcode":"07181",
    "sg:province":"Islas Baleares",
    "wof:name":"Universal Consulting S. A.",
    "wof:placetype":"venue"
},
  "geometry": {"coordinates":[2.5352098942,39.5245780945],"type":"Point"}
}