{
  "type": "Feature",
  "properties": {
    "addr:full":"Carretera De Figueras, S/n Barres Asturias 33794",
    "addr:housenumber":"s / n",
    "addr:postcode":"33794",
    "addr:street":"Carretera De Figueras",
    "iso:country":"ES",
    "sg:address":"Carretera De Figueras, S/n",
    "sg:city":"Barres",
    "sg:orig_category":"Venta, Alquiler De Toldos",
    "sg:phone":"+34 985 62 30 23",
    "sg:postcode":"33794",
    "sg:province":"Asturias",
    "wof:name":"Lastra Yanes Jose",
    "wof:placetype":"venue"
},
  "geometry": {"coordinates":[-7.0207791328,43.539642334],"type":"Point"}
}