{
  "type": "Feature",
  "properties": {
    "iso:country":"ES",
    "sg:address":"Carrer de Comte D'urgell, 171",
    "sg:city":"Barcelona",
    "sg:orig_category":"M\u00c9dicos: Cirug\u00cda Urol\u00d3gica",
    "sg:phone":"+34 934 53 60 80",
    "sg:postcode":"08036",
    "sg:province":"Barcelona",
    "wof:name":"Guardia Vidal Jose",
    "wof:placetype":"venue"
},
  "geometry": {"coordinates":[2.1505863667,41.3881416321],"type":"Point"}
}