{
  "type": "Feature",
  "properties": {
    "addr:full":"Avgd Sants Patrons, 19 Alzira Valencia 46600",
    "addr:housenumber":"19",
    "addr:postcode":"46600",
    "addr:street":"Patrons",
    "iso:country":"ES",
    "sg:address":"Avgd Sants Patrons, 19",
    "sg:city":"Alzira",
    "sg:orig_category":"Promotores Constructores",
    "sg:phone":"+34 962 40 21 65",
    "sg:postcode":"46600",
    "sg:province":"Valencia",
    "wof:name":"Doserval S.l.",
    "wof:placetype":"venue"
},
  "geometry": {"coordinates":[-0.4380410016,39.1513748169],"type":"Point"}
}