{
  "type": "Feature",
  "properties": {
    "iso:country":"ES",
    "sg:address":"Calle de Pelayo, 46",
    "sg:city":"Paiporta",
    "sg:orig_category":"\u00d3ptica: Instrumentos (fabricaci\u00d3n)",
    "sg:phone":"+34 963 97 20 68",
    "sg:postcode":"46200",
    "sg:province":"Valencia",
    "wof:name":"Mico Chofre Inmaculada",
    "wof:placetype":"venue"
},
  "geometry": {"coordinates":[-0.4162780046,39.42527771],"type":"Point"}
}