{
  "type": "Feature",
  "properties": {
    "addr:full":"Calle de Doctor Fco. Vazquez Limon, 17 Huelva Huelva 21002",
    "addr:housenumber":"17",
    "addr:postcode":"21002",
    "addr:street":"Calle De Doctor Fco. Vazquez Limon",
    "iso:country":"ES",
    "sg:address":"Calle de Doctor Fco. Vazquez Limon, 17",
    "sg:city":"Huelva",
    "sg:orig_category":"Contables",
    "sg:phone":"+34 959 24 33 89",
    "sg:postcode":"21002",
    "sg:province":"Huelva",
    "sg:website":"www.avilesyasesores.com",
    "wof:name":"Prieto Aviles Jose Manuel",
    "wof:placetype":"venue"
},
  "geometry": {"coordinates":[-6.9504380226,37.2722816467],"type":"Point"}
}