{
  "type": "Feature",
  "properties": {
    "iso:country":"ES",
    "sg:address":"Pase Florencio Marcos, 13",
    "sg:city":"Salamanca",
    "sg:orig_category":"Transportes Por V\u00cdas Navegables",
    "sg:phone":"+34 923 19 50 35",
    "sg:postcode":"37008",
    "sg:province":"Salamanca",
    "wof:name":"Hernandez Coronado Santos",
    "wof:placetype":"venue"
},
  "geometry": {"coordinates":[-5.6811141968,40.9574737549],"type":"Point"}
}