{
  "type": "Feature",
  "properties": {
    "iso:country":"ES",
    "sg:address":"C/ Cami (el), 48",
    "sg:city":"Alcoi",
    "sg:orig_category":"Perfumer\u00cda (al Por Menor)",
    "sg:phone":"+34 965 54 30 86",
    "sg:postcode":"03801",
    "sg:province":"Alicante",
    "wof:name":"Gisbert Segura Juan Jose",
    "wof:placetype":"venue"
},
  "geometry": {"coordinates":[-0.4757179916,38.6925506592],"type":"Point"}
}