{
  "type": "Feature",
  "properties": {
    "addr:full":"Calle de Astorga, 16 Alcorcon Madrid 28925",
    "addr:housenumber":"16",
    "addr:postcode":"28925",
    "addr:street":"Calle De Astorga",
    "iso:country":"ES",
    "sg:address":"Calle de Astorga, 16",
    "sg:city":"Alcorcon",
    "sg:orig_category":"Centros M\u00c9dicos Y Sociales, Dispensarios",
    "sg:phone":"+34 916 42 50 49",
    "sg:postcode":"28925",
    "sg:province":"Madrid",
    "wof:name":"Centro Medico Godoy Tundidor S.l.",
    "wof:placetype":"venue"
},
  "geometry": {"coordinates":[-3.8204660416,40.3548316956],"type":"Point"}
}