{
  "type": "Feature",
  "properties": {
    "addr:full":"Calle de Santiago Apostol, 4 Burgos Burgos 09007",
    "addr:housenumber":"4",
    "addr:postcode":"09007",
    "addr:street":"Calle De Santiago Apostol",
    "iso:country":"ES",
    "sg:address":"Calle de Santiago Apostol, 4",
    "sg:city":"Burgos",
    "sg:orig_category":"Metalurgia",
    "sg:phone":"+34 947 24 23 11",
    "sg:postcode":"09007",
    "sg:province":"Burgos",
    "wof:name":"Iba\u00f1ez Camarero Jesus",
    "wof:placetype":"venue"
},
  "geometry": {"coordinates":[-3.6748940945,42.3495178223],"type":"Point"}
}