{
  "type": "Feature",
  "properties": {
    "iso:country":"ES",
    "sg:address":"Calle de San Carlos, 60",
    "sg:city":"Alacant",
    "sg:orig_category":"Tapicer\u00cdas",
    "sg:phone":"+34 965 21 03 93",
    "sg:postcode":"03012",
    "sg:province":"Alicante",
    "wof:name":"Fuentes Bernabeu Jesus",
    "wof:placetype":"venue"
},
  "geometry": {"coordinates":[-0.4824590087,38.3534660339],"type":"Point"}
}