{
  "type": "Feature",
  "properties": {
    "iso:country":"ES",
    "sg:address":"Carr Sant Antoni, 35",
    "sg:city":"Figueres",
    "sg:orig_category":"M\u00c9dicos: Estomatolog\u00cda",
    "sg:phone":"+34 972 67 44 56",
    "sg:postcode":"17600",
    "sg:province":"Girona",
    "wof:name":"Jacoby Masferrer Francoise",
    "wof:placetype":"venue"
},
  "geometry": {"coordinates":[2.9646639824,42.2646255493],"type":"Point"}
}