{
  "type": "Feature",
  "properties": {
    "addr:full":"Carr Marina (la), 28 Cullera Valencia 46400",
    "addr:housenumber":"28",
    "addr:postcode":"46400",
    "addr:street":"Carr Marina La",
    "iso:country":"ES",
    "sg:address":"Carr Marina (la), 28",
    "sg:city":"Cullera",
    "sg:orig_category":"Agencias Y Asesores De Publicidad",
    "sg:phone":"+34 961 72 61 72",
    "sg:postcode":"46400",
    "sg:province":"Valencia",
    "wof:name":"Publichip S.l.",
    "wof:placetype":"venue"
},
  "geometry": {"coordinates":[-0.253226012,39.162197113],"type":"Point"}
}