{
  "type": "Feature",
  "properties": {
    "addr:full":"C/ Joan Maragall, 22 Tarrega Lleida 25300",
    "addr:housenumber":"22",
    "addr:postcode":"25300",
    "addr:street":"C / Joan Maragall",
    "iso:country":"ES",
    "sg:address":"C/ Joan Maragall, 22",
    "sg:city":"Tarrega",
    "sg:orig_category":"Fotocopias, Reprograf\u00cda",
    "sg:phone":"+34 973 31 14 70",
    "sg:postcode":"25300",
    "sg:province":"Lleida",
    "wof:name":"Gene Puiggene Maria Inmaculada",
    "wof:placetype":"venue"
},
  "geometry": {"coordinates":[1.1420918703,41.645980835],"type":"Point"}
}