{
  "type": "Feature",
  "properties": {
    "addr:full":"Calle de Moriles, 1 Parla Madrid 28980",
    "addr:housenumber":"1",
    "addr:postcode":"28980",
    "addr:street":"Calle De Moriles",
    "iso:country":"ES",
    "sg:address":"Calle de Moriles, 1",
    "sg:city":"Parla",
    "sg:orig_category":"Muebles, Minoristas",
    "sg:phone":"+34 916 98 53 33",
    "sg:postcode":"28980",
    "sg:province":"Madrid",
    "wof:name":"Kaiser Qui\u00f1ones Ernesto",
    "wof:placetype":"venue"
},
  "geometry": {"coordinates":[-3.7639257908,40.2532615662],"type":"Point"}
}