{
  "type": "Feature",
  "properties": {
    "addr:full":"Calle de Lorenza Correa, 17 Madrid Madrid 28039",
    "addr:housenumber":"17",
    "addr:postcode":"madrid;28039",
    "addr:street":"Calle De Lorenza Correa",
    "iso:country":"ES",
    "sg:address":"Calle de Lorenza Correa, 17",
    "sg:city":"Madrid",
    "sg:orig_category":"Cerrajer\u00cda, Ferrallista",
    "sg:phone":"+34 914 50 64 27",
    "sg:postcode":"28039",
    "sg:province":"Madrid",
    "wof:name":"Perez Martin Teofilo",
    "wof:placetype":"venue"
},
  "geometry": {"coordinates":[-3.7070360184,40.4536590576],"type":"Point"}
}