{
  "type": "Feature",
  "properties": {
    "addr:full":"Calle de Parque (del), 22 Huesca Huesca 22002",
    "addr:housenumber":"22",
    "addr:postcode":"22002",
    "addr:street":"Calle De Parque Del",
    "iso:country":"ES",
    "sg:address":"Calle de Parque (del), 22",
    "sg:city":"Huesca",
    "sg:orig_category":"Asilos De Ancianos. Centros Privados",
    "sg:phone":"+34 974 22 95 41",
    "sg:postcode":"22002",
    "sg:province":"Huesca",
    "wof:name":"Geriatrico El Parque Sll",
    "wof:placetype":"venue"
},
  "geometry": {"coordinates":[-0.4103290141,42.1366081238],"type":"Point"}
}