{
  "type": "Feature",
  "properties": {
    "addr:full":"Ctra Ledesma, 120 Salamanca Salamanca 37006",
    "addr:housenumber":"120",
    "addr:postcode":"37006",
    "addr:street":"Ctra Ledesma",
    "iso:country":"ES",
    "sg:address":"Ctra Ledesma, 120",
    "sg:city":"Salamanca",
    "sg:orig_category":"Laboratorios Y Trabajos De Fotograf\u00cda, V\u00cddeo Y Cine",
    "sg:phone":"+34 923 25 50 47",
    "sg:postcode":"37006",
    "sg:province":"Salamanca",
    "wof:name":"Chip Foto Estudio S.l",
    "wof:placetype":"venue"
},
  "geometry": {"coordinates":[-5.6758999825,40.977596283],"type":"Point"}
}