{
  "type": "Feature",
  "properties": {
    "addr:full":"Carrer de Catalunya, 22 Martorelles Barcelona 08107",
    "addr:housenumber":"22",
    "addr:postcode":"08107",
    "addr:street":"Carrer De Catalunya",
    "iso:country":"ES",
    "sg:address":"Carrer de Catalunya, 22",
    "sg:city":"Martorelles",
    "sg:orig_category":"Delineantes",
    "sg:phone":"+34 935 79 37 61",
    "sg:postcode":"08107",
    "sg:province":"Barcelona",
    "wof:name":"Sisal S.coop C.l.",
    "wof:placetype":"venue"
},
  "geometry": {"coordinates":[2.2342000008,41.528591156],"type":"Point"}
}