{
  "type": "Feature",
  "properties": {
    "addr:full":"Calle de Mayor, 34 Cangas Narcea Asturias 33800",
    "addr:housenumber":"34",
    "addr:postcode":"33800",
    "addr:street":"Calle De Mayor",
    "iso:country":"ES",
    "sg:address":"Calle de Mayor, 34",
    "sg:city":"Cangas Narcea",
    "sg:orig_category":"Estancos",
    "sg:phone":"+34 985 81 05 64",
    "sg:postcode":"33800",
    "sg:province":"Asturias",
    "wof:name":"Avello Florez Jorge",
    "wof:placetype":"venue"
},
  "geometry": {"coordinates":[-6.5513038635,43.178691864],"type":"Point"}
}