{
  "type": "Feature",
  "properties": {
    "iso:country":"ES",
    "sg:address":"Pl Sants Martirs (dels), 5",
    "sg:city":"Vic",
    "sg:orig_category":"Fiesta: Art\u00cdculos De (al Por Menor)",
    "sg:phone":"+34 938 89 04 84",
    "sg:postcode":"08500",
    "sg:province":"Barcelona",
    "wof:name":"Manli I Mes S.l.",
    "wof:placetype":"venue"
},
  "geometry": {"coordinates":[2.2577269077,41.9308433533],"type":"Point"}
}