{
  "type": "Feature",
  "properties": {
    "iso:country":"ES",
    "sg:address":"Cta. Era, 4",
    "sg:city":"Itrabo",
    "sg:orig_category":"T\u00c9cnicos Veterinarios",
    "sg:phone":"+34 958 62 14 55",
    "sg:postcode":"18612",
    "sg:province":"Granada",
    "wof:name":"Moe  Lars",
    "wof:placetype":"venue"
},
  "geometry": {"coordinates":[-3.6394760609,36.8004951477],"type":"Point"}
}