{
  "type": "Feature",
  "properties": {
    "addr:full":"Av Pau, De Sa, 121 Sant Lluis Islas Baleares 07710",
    "addr:housenumber":"121",
    "addr:postcode":"07710",
    "addr:street":"Av Pau De Sa",
    "iso:country":"ES",
    "sg:address":"Av Pau, De Sa, 121",
    "sg:city":"Sant Lluis",
    "sg:orig_category":"Centros Comerciales Y Grandes Tiendas",
    "sg:phone":"+34 971 15 14 69",
    "sg:postcode":"07710",
    "sg:province":"Islas Baleares",
    "wof:name":"Mercadal Calvade Carolina",
    "wof:placetype":"venue"
},
  "geometry": {"coordinates":[4.2691421509,39.8487739563],"type":"Point"}
}