{
  "type": "Feature",
  "properties": {
    "iso:country":"ES",
    "sg:address":"Major, S/n",
    "sg:city":"Rofes",
    "sg:orig_category":"Agricultores, Agricultores",
    "sg:phone":"+34 938 97 60 97",
    "sg:postcode":"08779",
    "sg:province":"Barcelona",
    "wof:name":"Granja Albet S.l.",
    "wof:placetype":"venue"
},
  "geometry": {"coordinates":[1.5342299938,41.4725799561],"type":"Point"}
}