{
  "type": "Feature",
  "properties": {
    "iso:country":"ES",
    "sg:address":"Psaj Nou Alacant, S/n",
    "sg:city":"Alacant",
    "sg:orig_category":"Empresas De Carpinter\u00cda",
    "sg:phone":"+34 965 24 38 38",
    "sg:postcode":"03014",
    "sg:province":"Alicante",
    "wof:name":"Cerezo Perez Miguel Angel",
    "wof:placetype":"venue"
},
  "geometry": {"coordinates":[-0.4838539958,38.3647499084],"type":"Point"}
}