{
  "type": "Feature",
  "properties": {
    "addr:full":"Ctra Terrassa, 290 Sabadell Barcelona 08206",
    "addr:housenumber":"290",
    "addr:postcode":"08206",
    "addr:street":"Ctra Terrassa",
    "iso:country":"ES",
    "sg:address":"Ctra Terrassa, 290",
    "sg:city":"Sabadell",
    "sg:orig_category":"Materiales De Aislamiento T\u00c9rmico Y Ac\u00dastico",
    "sg:phone":"+34 937 26 37 95",
    "sg:postcode":"08206",
    "sg:province":"Barcelona",
    "wof:name":"Control Solar Del Valles S.l.",
    "wof:placetype":"venue"
},
  "geometry": {"coordinates":[2.0912768841,41.5469093323],"type":"Point"}
}