{
  "type": "Feature",
  "properties": {
    "iso:country":"ES",
    "sg:address":"Calle de Libertad, 26",
    "sg:city":"Gijon",
    "sg:orig_category":"Agencias Y Agentes Comerciales, Representantes",
    "sg:phone":"+34 985 34 11 79",
    "sg:postcode":"33206",
    "sg:province":"Asturias",
    "wof:name":"Avenda\u00f1o Gutierrez Anselmo",
    "wof:placetype":"venue"
},
  "geometry": {"coordinates":[-5.6639785767,43.5398864746],"type":"Point"}
}