{
  "type": "Feature",
  "properties": {
    "iso:country":"ES",
    "sg:address":"Via Trajana, 50",
    "sg:city":"Barcelona",
    "sg:orig_category":"Molduras, Junquillos, Listones Y Molduras Perforadas",
    "sg:phone":"+34 933 05 40 90",
    "sg:postcode":"08020",
    "sg:province":"Barcelona",
    "wof:name":"Rubio Milan Regino",
    "wof:placetype":"venue"
},
  "geometry": {"coordinates":[2.2001509666,41.4287071228],"type":"Point"}
}