{
  "type": "Feature",
  "properties": {
    "addr:full":"Calle de Jaime I El Conquistador, S/n Parla Madrid 28980",
    "addr:housenumber":"s",
    "addr:postcode":"28980",
    "addr:street":"Calle De Jaime I El Conquistador;/ N",
    "iso:country":"ES",
    "sg:address":"Calle de Jaime I El Conquistador, S/n",
    "sg:city":"Parla",
    "sg:orig_category":"Centros De Educaci\u00d3n Especial",
    "sg:phone":"+34 916 05 26 89",
    "sg:postcode":"28980",
    "sg:province":"Madrid",
    "wof:name":"Comunidad Autonoma De Madrid-centros De Educacion",
    "wof:placetype":"venue"
},
  "geometry": {"coordinates":[-3.7665948868,40.2345161438],"type":"Point"}
}