{
  "type": "Feature",
  "properties": {
    "addr:full":"Calle de Argensola, 30 Madrid Madrid 28004",
    "addr:housenumber":"30",
    "addr:postcode":"madrid;28004",
    "addr:street":"Calle De Argensola",
    "iso:country":"ES",
    "sg:address":"Calle de Argensola, 30",
    "sg:city":"Madrid",
    "sg:orig_category":"Abogados",
    "sg:phone":"+34 913 10 22 34",
    "sg:postcode":"28004",
    "sg:province":"Madrid",
    "wof:name":"Argensola Asesores S.l.",
    "wof:placetype":"venue"
},
  "geometry": {"coordinates":[-3.6949806213,40.4251670837],"type":"Point"}
}