{
  "type": "Feature",
  "properties": {
    "addr:full":"Rua Garcia Olloqui, 4 Vigo Pontevedra 36201",
    "addr:housenumber":"4",
    "addr:postcode":"36201",
    "addr:street":"Rua Garcia Olloqui",
    "iso:country":"ES",
    "sg:address":"Rua Garcia Olloqui, 4",
    "sg:city":"Vigo",
    "sg:orig_category":"Asociaciones Y Clubs Deportivos",
    "sg:phone":"+34 986 22 77 42",
    "sg:postcode":"36201",
    "sg:province":"Pontevedra",
    "wof:name":"Asociacion Espa\u00d1ola De Titulados Nautico-pesquera",
    "wof:placetype":"venue"
},
  "geometry": {"coordinates":[-8.7242670059,42.2399330139],"type":"Point"}
}