{
  "type": "Feature",
  "properties": {
    "addr:full":"Rua Ferreiri\u00d1o, 7 Lugo Lugo 27003",
    "addr:housenumber":"7",
    "addr:postcode":"27003",
    "addr:street":"Rua Ferreirin\u0303O",
    "iso:country":"ES",
    "sg:address":"Rua Ferreiri\u00d1o, 7",
    "sg:city":"Lugo",
    "sg:orig_category":"Comercio De Piezas De Recambio Y De Accesorios De Veh\u00cdculos, Veh\u00cdculos Industriales",
    "sg:phone":"+34 982 20 09 17",
    "sg:postcode":"27003",
    "sg:province":"Lugo",
    "sg:website":"www.impormovil.es",
    "wof:name":"Comercial Impormovil S.a.",
    "wof:placetype":"venue"
},
  "geometry": {"coordinates":[-7.5680708885,43.0254898071],"type":"Point"}
}