{
  "type": "Feature",
  "properties": {
    "iso:country":"ES",
    "sg:address":"Calle de Nicolas Salmeron, 40",
    "sg:city":"Valladolid",
    "sg:orig_category":"Seguridad En El Trabajo Y Prevenci\u00d3n De Riesgos Laborales",
    "sg:phone":"+34 983 34 42 96",
    "sg:postcode":"47004",
    "sg:province":"Valladolid",
    "wof:name":"Malga Servicios Empresariales S.l.",
    "wof:placetype":"venue"
},
  "geometry": {"coordinates":[-4.7178320885,41.6467132568],"type":"Point"}
}