{
  "type": "Feature",
  "properties": {
    "addr:full":"Carr Francesc Layret, 108 Badalona Barcelona 08911",
    "addr:housenumber":"108",
    "addr:postcode":"08911",
    "addr:street":"Carr Francesc Layret",
    "iso:country":"ES",
    "sg:address":"Carr Francesc Layret, 108",
    "sg:city":"Badalona",
    "sg:orig_category":"El Hogar: Amueblado, Acondicionamiento, Decoraci\u00d3n Y Mantenimiento",
    "sg:phone":"+34 933 84 20 50",
    "sg:postcode":"08911",
    "sg:province":"Barcelona",
    "wof:name":"Llull Campos Alberto",
    "wof:placetype":"venue"
},
  "geometry": {"coordinates":[2.2491919994,41.4515838623],"type":"Point"}
}