{
  "type": "Feature",
  "properties": {
    "iso:country":"ES",
    "sg:address":"Calle de Puentezuelas, 28",
    "sg:city":"Granada",
    "sg:orig_category":"Peluquer\u00cdas, Peluquer\u00cda Mixta",
    "sg:phone":"+34 958 26 59 49",
    "sg:postcode":"18002",
    "sg:province":"Granada",
    "wof:name":"Prov-red C.b",
    "wof:placetype":"venue"
},
  "geometry": {"coordinates":[-3.6024084091,37.1744194031],"type":"Point"}
}