{
  "type": "Feature",
  "properties": {
    "iso:country":"ES",
    "sg:address":"Cno. Los Silos, S/n",
    "sg:city":"Villafranca Caballeros",
    "sg:orig_category":"Maquinaria Para Industrias Diversas",
    "sg:phone":"+34 926 57 87 58",
    "sg:postcode":"45730",
    "sg:province":"Toledo",
    "wof:name":"Niema 78 Sl",
    "wof:placetype":"venue"
},
  "geometry": {"coordinates":[-3.3565769196,39.4263534546],"type":"Point"}
}