{
  "type": "Feature",
  "properties": {
    "iso:country":"ES",
    "sg:address":"Cra. Puigcerda, S/n",
    "sg:city":"Adrall",
    "sg:orig_category":"Compraventa De Antig\u00dcedades",
    "sg:phone":"+34 973 38 72 98",
    "sg:postcode":"25797",
    "sg:province":"Lleida",
    "wof:name":"Steina S.l.",
    "wof:placetype":"venue"
},
  "geometry": {"coordinates":[1.4120600224,42.3354797363],"type":"Point"}
}