{
  "type": "Feature",
  "properties": {
    "addr:full":"Avgd Blasco Iba\u00d1ez, 24 Quart Poblet Valencia 46930",
    "addr:housenumber":"24",
    "addr:postcode":"46930",
    "addr:street":"Iban\u0303Ez;Poblet",
    "iso:country":"ES",
    "sg:address":"Avgd Blasco Iba\u00d1ez, 24",
    "sg:city":"Quart Poblet",
    "sg:orig_category":"Empresas De Estuco",
    "sg:phone":"+34 961 53 07 92",
    "sg:postcode":"46930",
    "sg:province":"Valencia",
    "wof:name":"Pinturas Chimo S.l.",
    "wof:placetype":"venue"
},
  "geometry": {"coordinates":[-0.4419890046,39.482711792],"type":"Point"}
}