{
  "type": "Feature",
  "properties": {
    "iso:country":"ES",
    "sg:address":"Carrer de Riera, 3",
    "sg:city":"Vic",
    "sg:orig_category":"Papeler\u00cdas, Librer\u00cdas",
    "sg:phone":"+34 938 85 25 61",
    "sg:postcode":"08500",
    "sg:province":"Barcelona",
    "wof:name":"Pietx Raurell Manuel",
    "wof:placetype":"venue"
},
  "geometry": {"coordinates":[2.2539510727,41.9300384521],"type":"Point"}
}