{
  "type": "Feature",
  "properties": {
    "iso:country":"ES",
    "sg:address":"Ctra. Poza Sal, 12",
    "sg:city":"Burgos",
    "sg:orig_category":"Farmacias",
    "sg:phone":"+34 947 48 48 36",
    "sg:postcode":"09007",
    "sg:province":"Burgos",
    "wof:name":"Eva Gutierrez Gutierrez Y Avelino Rodriguez Hervella S.cv.",
    "wof:placetype":"venue"
},
  "geometry": {"coordinates":[-3.6653249264,42.3556175232],"type":"Point"}
}