{
  "type": "Feature",
  "properties": {
    "iso:country":"ES",
    "sg:address":"Carrer de Industria, 7",
    "sg:city":"S. Esteve Sesrovires",
    "sg:orig_category":"Transportes Por Carretera: Lotes Completos, Mercanc\u00cdas Diversas",
    "sg:phone":"+34 937 71 52 72",
    "sg:postcode":"08635",
    "sg:province":"Barcelona",
    "wof:name":"Tutichip S.a.",
    "wof:placetype":"venue"
},
  "geometry": {"coordinates":[1.8731199503,41.4965515137],"type":"Point"}
}