{
  "type": "Feature",
  "properties": {
    "addr:full":"Cra Valldemossa, 4 Palma Islas Baleares 07010",
    "addr:housenumber":"4",
    "addr:postcode":"07010",
    "addr:street":"Valldemossa",
    "iso:country":"ES",
    "sg:address":"Cra Valldemossa, 4",
    "sg:city":"Palma",
    "sg:orig_category":"Farmacias",
    "sg:phone":"+34 971 75 50 14",
    "sg:postcode":"07010",
    "sg:province":"Islas Baleares",
    "wof:name":"Farmacia M.lluch C.lluch Cb",
    "wof:placetype":"venue"
},
  "geometry": {"coordinates":[2.6511750221,39.5858459473],"type":"Point"}
}