{
  "type": "Feature",
  "properties": {
    "iso:country":"ES",
    "sg:address":"Pase Zorrilla, 190",
    "sg:city":"Valladolid",
    "sg:orig_category":"Productores Recolectores, Venta Directa De Vinos",
    "sg:phone":"+34 983 23 36 38",
    "sg:postcode":"47006",
    "sg:province":"Valladolid",
    "wof:name":"Herrero Del Moral Julio",
    "wof:placetype":"venue"
},
  "geometry": {"coordinates":[-4.7430710793,41.6291313171],"type":"Point"}
}