{
  "type": "Feature",
  "properties": {
    "iso:country":"ES",
    "sg:address":"Calle de Algue\u00d1a, S/n",
    "sg:city":"Alacant",
    "sg:orig_category":"Transporte En General",
    "sg:phone":"+34 965 10 04 23",
    "sg:postcode":"03008",
    "sg:province":"Alicante",
    "wof:name":"Carreras Almacenaje Y Distribucion S.a.",
    "wof:placetype":"venue"
},
  "geometry": {"coordinates":[-0.5354434252,38.3015136719],"type":"Point"}
}