{
  "type": "Feature",
  "properties": {
    "iso:country":"ES",
    "sg:address":"Calle de Virgen De La Capilla, 11",
    "sg:city":"Jaen",
    "sg:orig_category":"Cl\u00cdnicas Dentales",
    "sg:phone":"+34 953 24 15 23",
    "sg:postcode":"23001",
    "sg:province":"Ja\u00e9n",
    "sg:website":"www.clinicadentalcarlosfernandez.com",
    "wof:name":"Carlos Maria Fernandez Ortega Y Otros C.b.",
    "wof:placetype":"venue"
},
  "geometry": {"coordinates":[-3.7868869305,37.7686729431],"type":"Point"}
}