{
  "type": "Feature",
  "properties": {
    "iso:country":"ES",
    "sg:address":"Carrer de Llull, 395",
    "sg:city":"Barcelona",
    "sg:orig_category":"Centros Empresariales",
    "sg:phone":"+34 933 07 13 67",
    "sg:postcode":"08019",
    "sg:province":"Barcelona",
    "wof:name":"Barea Navea Antonio",
    "wof:placetype":"venue"
},
  "geometry": {"coordinates":[2.2166950703,41.4122848511],"type":"Point"}
}