{
  "type": "Feature",
  "properties": {
    "addr:full":"Calle de Cinco Caballeros, 9 Cordoba C\u00f3rdoba 14007",
    "addr:housenumber":"9",
    "addr:postcode":"14007",
    "addr:street":"Calle De Cinco Caballeros;Co\u0301Rdoba",
    "iso:country":"ES",
    "sg:address":"Calle de Cinco Caballeros, 9",
    "sg:city":"Cordoba",
    "sg:orig_category":"Farmacias",
    "sg:phone":"+34 957 25 20 84",
    "sg:postcode":"14007",
    "sg:province":"C\u00f3rdoba",
    "sg:website":"www.cincocaballero.com",
    "wof:name":"De Priego Gonzalez De Canales Juan Antonio",
    "wof:placetype":"venue"
},
  "geometry": {"coordinates":[-4.7637748718,37.8946456909],"type":"Point"}
}