{
  "type": "Feature",
  "properties": {
    "iso:country":"ES",
    "sg:address":"Calle de Jose Lopez Tafall, S/n",
    "sg:city":"Jaen",
    "sg:orig_category":"Electricidad: Instaladores",
    "sg:phone":"+34 953 22 17 11",
    "sg:postcode":"23007",
    "sg:province":"Ja\u00e9n",
    "wof:name":"Robles Luque Jose Luis",
    "wof:placetype":"venue"
},
  "geometry": {"coordinates":[-3.7935340405,37.7743263245],"type":"Point"}
}