{
  "type": "Feature",
  "properties": {
    "addr:full":"Calle de Victor Serna, S/n Fuengirola M\u00e1laga 29640",
    "addr:postcode":"29640",
    "addr:street":"Calle De Victor Serna S / N;Ma\u0301Laga",
    "iso:country":"ES",
    "sg:address":"Calle de Victor Serna, S/n",
    "sg:city":"Fuengirola",
    "sg:orig_category":"Ingeniero",
    "sg:phone":"+34 952 47 49 40",
    "sg:postcode":"29640",
    "sg:province":"M\u00e1laga",
    "wof:name":"Ron Robles Ricardo",
    "wof:placetype":"venue"
},
  "geometry": {"coordinates":[-4.6264038086,36.5377655029],"type":"Point"}
}