{
  "type": "Feature",
  "properties": {
    "iso:country":"ES",
    "sg:address":"Calle de Gitanos, 3",
    "sg:city":"Puerto Lumbreras",
    "sg:orig_category":"Agencias Y Agentes Comerciales, Representantes",
    "sg:phone":"+34 968 40 25 89",
    "sg:postcode":"30890",
    "sg:province":"Murcia",
    "wof:name":"Representaciones Leonardo Parra",
    "wof:placetype":"venue"
},
  "geometry": {"coordinates":[-1.8108659983,37.5563468933],"type":"Point"}
}