{
  "type": "Feature",
  "properties": {
    "addr:full":"Pto. Punta Portals, 44 Portals Nous Islas Baleares 07181",
    "addr:housenumber":"44",
    "addr:postcode":"07181",
    "addr:street":"Portals",
    "iso:country":"ES",
    "sg:address":"Pto. Punta Portals, 44",
    "sg:city":"Portals Nous",
    "sg:orig_category":"Higiene, Belleza: Art\u00cdculos (al Por Menor)",
    "sg:phone":"+34 971 67 77 42",
    "sg:postcode":"07181",
    "sg:province":"Islas Baleares",
    "wof:name":"Specific Apotecary S.l.",
    "wof:placetype":"venue"
},
  "geometry": {"coordinates":[2.5721600056,39.5352096558],"type":"Point"}
}