{
  "type": "Feature",
  "properties": {
    "iso:country":"ES",
    "sg:address":"Calle de Francisco Aritio, 117",
    "sg:city":"Guadalajara",
    "sg:orig_category":"Maquinaria Para Industrias Diversas",
    "sg:phone":"+34 949 20 27 60",
    "sg:postcode":"19004",
    "sg:province":"Guadalajara",
    "wof:name":"Illana Automocion S.l.",
    "wof:placetype":"venue"
},
  "geometry": {"coordinates":[-3.197865963,40.6256599426],"type":"Point"}
}