{
  "type": "Feature",
  "properties": {
    "addr:full":"Calle de Jorge Juan, 5 Madrid Madrid 28028",
    "addr:housenumber":"5",
    "addr:postcode":"28028",
    "addr:street":"Calle De Jorge Juan",
    "iso:country":"ES",
    "sg:address":"Calle de Jorge Juan, 5",
    "sg:city":"Madrid",
    "sg:orig_category":"Financiaci\u00d3n Y Cr\u00c9ditos",
    "sg:phone":"+34 914 26 12 61",
    "sg:postcode":"28028",
    "sg:province":"Madrid",
    "wof:name":"Corporacionj.m.aristrains.l.",
    "wof:placetype":"venue"
},
  "geometry": {"coordinates":[-3.6687989235,40.4230194092],"type":"Point"}
}