{
  "type": "Feature",
  "properties": {
    "addr:full":"Calle de Cabo De Finisterre, 12 Arganda Madrid 28500",
    "addr:housenumber":"12",
    "addr:postcode":"28500",
    "addr:street":"Calle De Cabo De Finisterre",
    "iso:country":"ES",
    "sg:address":"Calle de Cabo De Finisterre, 12",
    "sg:city":"Arganda",
    "sg:orig_category":"Electricidad: Instaladores",
    "sg:phone":"+34 918 71 24 70",
    "sg:postcode":"28500",
    "sg:province":"Madrid",
    "wof:name":"Instalaciones Electricas Marpesa S.l.",
    "wof:placetype":"venue"
},
  "geometry": {"coordinates":[-3.475070715,40.3119506836],"type":"Point"}
}