{
  "type": "Feature",
  "properties": {
    "addr:full":"Plaz Conde, 3 Toledo Toledo 45002",
    "addr:housenumber":"3",
    "addr:postcode":"45002",
    "addr:street":"Conde",
    "iso:country":"ES",
    "sg:address":"Plaz Conde, 3",
    "sg:city":"Toledo",
    "sg:orig_category":"Artesan\u00cda",
    "sg:phone":"+34 925 25 00 34",
    "sg:postcode":"45002",
    "sg:province":"Toledo",
    "wof:name":"Artesania Morales S.l.",
    "wof:placetype":"venue"
},
  "geometry": {"coordinates":[-4.0284070969,39.856590271],"type":"Point"}
}