{
  "type": "Feature",
  "properties": {
    "addr:full":"Calle de Malaka, S/n Malaga M\u00e1laga 29190",
    "addr:housenumber":"s",
    "addr:postcode":"29190",
    "addr:street":"Calle De Malaka;/ N;Ma\u0301Laga",
    "iso:country":"ES",
    "sg:address":"Calle de Malaka, S/n",
    "sg:city":"Malaga",
    "sg:orig_category":"Arquitectos",
    "sg:phone":"+34 952 43 11 75",
    "sg:postcode":"29190",
    "sg:province":"M\u00e1laga",
    "wof:name":"Gallego Nu\u00f1ez Isidro",
    "wof:placetype":"venue"
},
  "geometry": {"coordinates":[-4.4692392349,36.7357406616],"type":"Point"}
}