{
  "type": "Feature",
  "properties": {
    "addr:full":"Avda Lapurdi, 7 Bilbao Vizcaya 48012",
    "addr:housenumber":"7",
    "addr:postcode":"48012",
    "addr:street":"Avda Lapurdi",
    "iso:country":"ES",
    "sg:address":"Avda Lapurdi, 7",
    "sg:city":"Bilbao",
    "sg:orig_category":"Impresi\u00d3n Digital",
    "sg:phone":"+34 944 43 04 91",
    "sg:postcode":"48012",
    "sg:province":"Vizcaya",
    "wof:name":"Servicios Graficos Sermai, S.l.l.",
    "wof:placetype":"venue"
},
  "geometry": {"coordinates":[-2.9348330498,43.2556762695],"type":"Point"}
}