{
  "type": "Feature",
  "properties": {
    "addr:full":"Calle de Cadiz, 9 Santander Cantabria 39002",
    "addr:housenumber":"9",
    "addr:postcode":"39002",
    "addr:street":"Calle De Cadiz",
    "iso:country":"ES",
    "sg:address":"Calle de Cadiz, 9",
    "sg:city":"Santander",
    "sg:orig_category":"Quincaller\u00cda (al Por Menor)",
    "sg:phone":"+34 942 31 29 54",
    "sg:postcode":"39002",
    "sg:province":"Cantabria",
    "wof:name":"Gomez Lavin Hermanos S.a.",
    "wof:placetype":"venue"
},
  "geometry": {"coordinates":[-3.8096251488,43.4597702026],"type":"Point"}
}