{
  "type": "Feature",
  "properties": {
    "addr:full":"Calle de Beatriz De Silva, 10 Ceuta Ceuta 51001",
    "addr:housenumber":"10",
    "addr:postcode":"51001",
    "addr:street":"Calle De Beatriz De Silva",
    "iso:country":"ES",
    "sg:address":"Calle de Beatriz De Silva, 10",
    "sg:city":"Ceuta",
    "sg:orig_category":"Institutos De Belleza",
    "sg:phone":"+34 856 20 00 64",
    "sg:postcode":"51001",
    "sg:province":"Ceuta",
    "wof:name":"Garcia Morilla Virginia Maria",
    "wof:placetype":"venue"
},
  "geometry": {"coordinates":[-5.3074727058,35.8868865967],"type":"Point"}
}