{
  "type": "Feature",
  "properties": {
    "iso:country":"ES",
    "sg:address":"Calle de Joaquin Collar, 4",
    "sg:city":"Vitoria-gasteiz",
    "sg:orig_category":"Arquitectos",
    "sg:phone":"+34 945 28 36 66",
    "sg:postcode":"01002",
    "sg:province":"\u00c1lava",
    "wof:name":"Grama, S.a.",
    "wof:placetype":"venue"
},
  "geometry": {"coordinates":[-2.6555290222,42.8519821167],"type":"Point"}
}