{
  "type": "Feature",
  "properties": {
    "addr:full":"Carrer de Major (sant Celoni), 140 S. Celoni Barcelona 08470",
    "addr:housenumber":"140",
    "addr:postcode":"08470",
    "addr:street":"Carrer De Major Sant Celoni;S. Celoni Barcelona",
    "iso:country":"ES",
    "sg:address":"Carrer de Major (sant Celoni), 140",
    "sg:city":"S. Celoni",
    "sg:orig_category":"Marroquiner\u00cda (confecci\u00d3n)",
    "sg:phone":"+34 938 67 10 48",
    "sg:postcode":"08470",
    "sg:province":"Barcelona",
    "wof:name":"Ninou Palau Maria Teresa",
    "wof:placetype":"venue"
},
  "geometry": {"coordinates":[2.4913320541,41.689617157],"type":"Point"}
}