{
  "type": "Feature",
  "properties": {
    "iso:country":"ES",
    "sg:address":"Plaz San Martin De La Ascension, 1",
    "sg:city":"Bilbao",
    "sg:orig_category":"Peluqueros: De Se\u00d1oras",
    "sg:phone":"+34 944 11 98 30",
    "sg:postcode":"48004",
    "sg:province":"Vizcaya",
    "wof:name":"Nerea Perez Fernandez",
    "wof:placetype":"venue"
},
  "geometry": {"coordinates":[-2.9106750488,43.2532310486],"type":"Point"}
}