{
  "type": "Feature",
  "properties": {
    "addr:full":"Calle de San Juan, 9 Burgos Burgos 09003",
    "addr:housenumber":"9",
    "addr:postcode":"09003",
    "addr:street":"Calle De San Juan",
    "iso:country":"ES",
    "sg:address":"Calle de San Juan, 9",
    "sg:city":"Burgos",
    "sg:orig_category":"Abogados",
    "sg:phone":"+34 947 26 43 89",
    "sg:postcode":"09003",
    "sg:province":"Burgos",
    "wof:name":"Ruiz Calleja Luis",
    "wof:placetype":"venue"
},
  "geometry": {"coordinates":[-3.699420929,42.3429908752],"type":"Point"}
}