{
  "type": "Feature",
  "properties": {
    "iso:country":"ES",
    "sg:address":"Rua Nueva, 3",
    "sg:city":"Coru\u00d1a",
    "sg:orig_category":"Bisuter\u00cda, Joyer\u00cda, Relojer\u00cda (al Por Menor)",
    "sg:phone":"+34 981 21 23 76",
    "sg:postcode":"15003",
    "sg:province":"La Coru\u00f1a",
    "wof:name":"Ferre\u00d1o Oro S.l",
    "wof:placetype":"venue"
},
  "geometry": {"coordinates":[-8.4025316238,43.3690414429],"type":"Point"}
}