{
  "type": "Feature",
  "properties": {
    "addr:full":"Ctra Nacional 340, Km. 0056,7 Villarreal Castell\u00f3n 12540",
    "addr:postcode":"12540",
    "addr:street":"Ctra Nacional 340 Km. 0056,7;Castello\u0301N",
    "iso:country":"ES",
    "sg:address":"Ctra Nacional 340, Km. 0056,7",
    "sg:city":"Villarreal",
    "sg:orig_category":"Fabrica De Cer\u00c1micas",
    "sg:phone":"+34 964 53 33 60",
    "sg:postcode":"12540",
    "sg:province":"Castell\u00f3n",
    "wof:name":"Novogres S. A.",
    "wof:placetype":"venue"
},
  "geometry": {"coordinates":[-0.0952939987,39.9453048706],"type":"Point"}
}