{
  "type": "Feature",
  "properties": {
    "iso:country":"ES",
    "sg:address":"Prje Centenares, S/n",
    "sg:city":"Castielfabib",
    "sg:orig_category":"Cooperativas Agr\u00cdcolas",
    "sg:phone":"+34 978 78 35 04",
    "sg:postcode":"46141",
    "sg:province":"Valencia",
    "wof:name":"Ceaga Sdad. Cooperativa Valenciana",
    "wof:placetype":"venue"
},
  "geometry": {"coordinates":[-1.3042340279,40.1294937134],"type":"Point"}
}