{
  "type": "Feature",
  "properties": {
    "iso:country":"ES",
    "sg:address":"Avda Cadiz (de), 64",
    "sg:city":"Cordoba",
    "sg:orig_category":"Agencias Y Asesores De Publicidad",
    "sg:phone":"+34 957 42 05 66",
    "sg:postcode":"14013",
    "sg:province":"C\u00f3rdoba",
    "wof:name":"Info-imagen S.l.",
    "wof:placetype":"venue"
},
  "geometry": {"coordinates":[-4.7805104256,37.8681259155],"type":"Point"}
}