{
  "type": "Feature",
  "properties": {
    "iso:country":"ES",
    "sg:address":"Rua Casiano Martinez, 37",
    "sg:city":"Vigo",
    "sg:orig_category":"Electricidad: Instaladores",
    "sg:phone":"+34 986 23 18 73",
    "sg:postcode":"36208",
    "sg:province":"Pontevedra",
    "wof:name":"Gonzalez Arjones Jose Antonio Y Otro Cdad",
    "wof:placetype":"venue"
},
  "geometry": {"coordinates":[-8.756480217,42.2233276367],"type":"Point"}
}