{
  "type": "Feature",
  "properties": {
    "iso:country":"ES",
    "sg:address":"Carr D. Juan Antonio Baldovi, 9",
    "sg:city":"Benidorm",
    "sg:orig_category":"Supermercados Y Hipermercados",
    "sg:phone":"+34 965 86 53 86",
    "sg:postcode":"03500",
    "sg:province":"Alicante",
    "sg:website":"www.mercadona.es",
    "wof:name":"Mercadona S A",
    "wof:placetype":"venue"
},
  "geometry": {"coordinates":[-0.1743289977,38.5408058167],"type":"Point"}
}