{
  "type": "Feature",
  "properties": {
    "addr:full":"Calle de San Quirce, 8 Valladolid Valladolid 47003",
    "addr:housenumber":"8",
    "addr:postcode":"47003",
    "addr:street":"Calle De San Quirce",
    "iso:country":"ES",
    "sg:address":"Calle de San Quirce, 8",
    "sg:city":"Valladolid",
    "sg:orig_category":"Molduras, Junquillos, Listones Y Molduras Perforadas",
    "sg:phone":"+34 983 35 43 29",
    "sg:postcode":"47003",
    "sg:province":"Valladolid",
    "wof:name":"Perez Bermejo Francisco Javier",
    "wof:placetype":"venue"
},
  "geometry": {"coordinates":[-4.7285628319,41.6571960449],"type":"Point"}
}