{
  "type": "Feature",
  "properties": {
    "addr:full":"Plaz San Roque, 5 Llanes Asturias 33500",
    "addr:postcode":"33500",
    "addr:street":"Plaz San",
    "iso:country":"ES",
    "sg:address":"Plaz San Roque, 5",
    "sg:city":"Llanes",
    "sg:orig_category":"Quincaller\u00cda (al Por Menor)",
    "sg:phone":"+34 985 40 10 68",
    "sg:postcode":"33500",
    "sg:province":"Asturias",
    "wof:name":"Rodriguez Sobrino Rosa Clara",
    "wof:placetype":"venue"
},
  "geometry": {"coordinates":[-4.7549939156,43.4207191467],"type":"Point"}
}