{
  "type": "Feature",
  "properties": {
    "addr:full":"Carrer de Mare De Deu Dels Munts, 8 Vic Barcelona 08500",
    "addr:housenumber":"8",
    "addr:postcode":"08500",
    "addr:street":"Carrer De Mare De Deu;Munts",
    "iso:country":"ES",
    "sg:address":"Carrer de Mare De Deu Dels Munts, 8",
    "sg:city":"Vic",
    "sg:orig_category":"Chapister\u00cda",
    "sg:phone":"+34 938 86 16 68",
    "sg:postcode":"08500",
    "sg:province":"Barcelona",
    "wof:name":"Sala Canals Pedro",
    "wof:placetype":"venue"
},
  "geometry": {"coordinates":[2.2655920982,41.9357452393],"type":"Point"}
}