{
  "type": "Feature",
  "properties": {
    "iso:country":"ES",
    "sg:address":"Carrer de Escoles, 2",
    "sg:city":"Vila-rodona",
    "sg:orig_category":"Pescader\u00cdas (al Por Menor)",
    "sg:phone":"+34 977 63 84 12",
    "sg:postcode":"43814",
    "sg:province":"Tarragona",
    "wof:name":"Domenech Rivas Antonio",
    "wof:placetype":"venue"
},
  "geometry": {"coordinates":[1.3582099676,41.3088150024],"type":"Point"}
}