{
  "type": "Feature",
  "properties": {
    "addr:full":"Calle de Iru\u00d1a, 1 Bilbao Vizcaya 48014",
    "addr:housenumber":"1",
    "addr:postcode":"48014",
    "addr:street":"Calle De Irun\u0303A",
    "iso:country":"ES",
    "sg:address":"Calle de Iru\u00d1a, 1",
    "sg:city":"Bilbao",
    "sg:orig_category":"Agentes, Concesionarios Y Sucursales De Veh\u00cdculos",
    "sg:phone":"+34 944 76 53 80",
    "sg:postcode":"48014",
    "sg:province":"Vizcaya",
    "sg:website":"www.leioawagen.es",
    "wof:name":"Leioa Wagen S.a.",
    "wof:placetype":"venue"
},
  "geometry": {"coordinates":[-2.9493429661,43.2683258057],"type":"Point"}
}