{
  "type": "Feature",
  "properties": {
    "iso:country":"ES",
    "sg:address":"Carrer de Major, 89",
    "sg:city":"Centre",
    "sg:orig_category":"Cerrajer\u00cda, Ferrallista",
    "sg:phone":"+34 936 83 11 50",
    "sg:postcode":"08759",
    "sg:province":"Barcelona",
    "wof:name":"Materiales Para La Construccion La Valliranense S.l.",
    "wof:placetype":"venue"
},
  "geometry": {"coordinates":[1.9203499556,41.380191803],"type":"Point"}
}