{
  "type": "Feature",
  "properties": {
    "iso:country":"ES",
    "sg:address":"Avda Andalucia, S/n",
    "sg:city":"Castilleja Campo",
    "sg:orig_category":"Transportes Frigor\u00cdficos",
    "sg:phone":"+34 954 75 54 81",
    "sg:postcode":"41810",
    "sg:province":"Sevilla",
    "wof:name":"Rodriguez Fernandez Manuel",
    "wof:placetype":"venue"
},
  "geometry": {"coordinates":[-6.3374037743,37.3878517151],"type":"Point"}
}