{
  "type": "Feature",
  "properties": {
    "iso:country":"ES",
    "sg:address":"Calle de Cruz De Piedra Del Realejo, 8",
    "sg:city":"Granada",
    "sg:orig_category":"Frutas Y Legumbres Frescas (al Por Mayor)",
    "sg:phone":"+34 958 20 03 02",
    "sg:postcode":"18010",
    "sg:province":"Granada",
    "wof:name":"Frutas Alhambra S.l.",
    "wof:placetype":"venue"
},
  "geometry": {"coordinates":[-3.5509073734,37.1906700134],"type":"Point"}
}