{
  "type": "Feature",
  "properties": {
    "addr:full":"Carrer de Calderon De La Barca, 9 S. Pere Ribes Barcelona 08810",
    "addr:housenumber":"9",
    "addr:postcode":"08810",
    "addr:street":"Carrer De Calderon De La Barca;S. Pere Ribes Barcelona",
    "iso:country":"ES",
    "sg:address":"Carrer de Calderon De La Barca, 9",
    "sg:city":"S. Pere Ribes",
    "sg:orig_category":"M\u00c9dicos: Ginecolog\u00cda Y Obstetricia",
    "sg:phone":"+34 938 96 29 45",
    "sg:postcode":"08810",
    "sg:province":"Barcelona",
    "wof:name":"Roig Miret Ignasi",
    "wof:placetype":"venue"
},
  "geometry": {"coordinates":[1.7746829987,41.2603034973],"type":"Point"}
}