{
  "type": "Feature",
  "properties": {
    "addr:full":"Calle de Josefina Mayor, 28 Goro Las Palmas 35215",
    "addr:housenumber":"28",
    "addr:postcode":"35215",
    "addr:street":"Calle De Josefina Mayor",
    "iso:country":"ES",
    "sg:address":"Calle de Josefina Mayor, 28",
    "sg:city":"Goro",
    "sg:orig_category":"Transportes Por Carretera: Lotes Completos, Mercanc\u00cdas Diversas",
    "sg:phone":"+34 928 70 00 01",
    "sg:postcode":"35215",
    "sg:province":"Las Palmas",
    "sg:website":"www.covenca.com",
    "wof:name":"Solatron S.l.",
    "wof:placetype":"venue"
},
  "geometry": {"coordinates":[-15.393327713,27.9689941406],"type":"Point"}
}