{
  "type": "Feature",
  "properties": {
    "addr:full":"Pque. Tecn. De Asturias, 34 Cayes Asturias 33428",
    "addr:housenumber":"34",
    "addr:postcode":"33428",
    "iso:country":"ES",
    "sg:address":"Pque. Tecn. De Asturias, 34",
    "sg:city":"Cayes",
    "sg:orig_category":"Inmobiliaria (agencias)",
    "sg:phone":"+34 985 26 15 32",
    "sg:postcode":"33428",
    "sg:province":"Asturias",
    "wof:name":"Inmobiliaria Toreno S.a",
    "wof:placetype":"venue"
},
  "geometry": {"coordinates":[-5.8358402252,43.4143867493],"type":"Point"}
}