{
  "type": "Feature",
  "properties": {
    "addr:full":"Avda Moncalvillo (del), 1 Logro\u00f1o La Rioja 26007",
    "addr:housenumber":"1",
    "addr:postcode":"26007",
    "addr:street":"Avda Moncalvillo Del;Rioja",
    "iso:country":"ES",
    "sg:address":"Avda Moncalvillo (del), 1",
    "sg:city":"Logro\u00f1o",
    "sg:orig_category":"Deportes Diversos",
    "sg:phone":"+34 941 50 50 20",
    "sg:postcode":"26007",
    "sg:province":"La Rioja",
    "wof:name":"Federacion Riojana De Atletismo De Logro\u00f1o",
    "wof:placetype":"venue"
},
  "geometry": {"coordinates":[-2.5187389851,42.4914894104],"type":"Point"}
}