{
  "type": "Feature",
  "properties": {
    "iso:country":"ES",
    "sg:address":"Calle de Alava, 2",
    "sg:city":"Llodio",
    "sg:orig_category":"Fabricaci\u00d3n De Sobres, Bolsas Y Fundas",
    "sg:phone":"+34 946 72 02 71",
    "sg:postcode":"01400",
    "sg:province":"\u00c1lava",
    "wof:name":"Alonso Alonso Agustin",
    "wof:placetype":"venue"
},
  "geometry": {"coordinates":[-2.9675571918,43.1460380554],"type":"Point"}
}