{
  "type": "Feature",
  "properties": {
    "addr:full":"Veintiocho De Febrero, 2 Santiponce Sevilla 41970",
    "addr:housenumber":"2",
    "addr:postcode":"41970",
    "addr:street":"Veintiocho;Febrero",
    "iso:country":"ES",
    "sg:address":"Veintiocho De Febrero, 2",
    "sg:city":"Santiponce",
    "sg:orig_category":"Materias Pl\u00c1sticas: Art\u00cdculos Para La Industria",
    "sg:phone":"+34 955 99 68 08",
    "sg:postcode":"41970",
    "sg:province":"Sevilla",
    "wof:name":"Union Plastics S. A.",
    "wof:placetype":"venue"
},
  "geometry": {"coordinates":[-6.0385842323,37.434841156],"type":"Point"}
}