{
  "type": "Feature",
  "properties": {
    "iso:country":"ES",
    "sg:address":"Carrer de Cal Gerrer, S/n",
    "sg:city":"Rubi",
    "sg:orig_category":"Poller\u00cda Y Caza (al Por Menor)",
    "sg:phone":"+34 936 99 96 53",
    "sg:postcode":"08191",
    "sg:province":"Barcelona",
    "wof:name":"Vivancos Roura Juan",
    "wof:placetype":"venue"
},
  "geometry": {"coordinates":[2.0349955559,41.4889755249],"type":"Point"}
}