{
  "type": "Feature",
  "properties": {
    "iso:country":"ES",
    "sg:address":"Carr Migdia, 48",
    "sg:city":"Girona",
    "sg:orig_category":"Asesor\u00cda Fiscal Y Jur\u00cddica",
    "sg:phone":"+34 972 22 61 89",
    "sg:postcode":"17002",
    "sg:province":"Girona",
    "wof:name":"Lope Cufi Olga",
    "wof:placetype":"venue"
},
  "geometry": {"coordinates":[2.8187448978,41.9808616638],"type":"Point"}
}