{
  "type": "Feature",
  "properties": {
    "addr:full":"Avda Pablo Iglesias, 37 Madrid Madrid 28039",
    "addr:housenumber":"37",
    "addr:postcode":"madrid;28039",
    "addr:street":"Avda Pablo Iglesias",
    "iso:country":"ES",
    "sg:address":"Avda Pablo Iglesias, 37",
    "sg:city":"Madrid",
    "sg:orig_category":"Jardiner\u00cdas, Vegetales, Art\u00cdculos De Jardiner\u00cda (al Por Menor)",
    "sg:phone":"+34 915 36 11 86",
    "sg:postcode":"28039",
    "sg:province":"Madrid",
    "wof:name":"Prada Garcia Maximo",
    "wof:placetype":"venue"
},
  "geometry": {"coordinates":[-3.7091829777,40.4482955933],"type":"Point"}
}