{
  "type": "Feature",
  "properties": {
    "iso:country":"ES",
    "sg:address":"Plaza Alfonso X El Sabio, 8",
    "sg:city":"Valdes",
    "sg:orig_category":"Cajas De Ahorro",
    "sg:phone":"+34 985 47 04 79",
    "sg:postcode":"33700",
    "sg:province":"Asturias",
    "sg:website":"www.cajastur.es",
    "wof:name":"Caja De Ahorros De Asturias",
    "wof:placetype":"venue"
},
  "geometry": {"coordinates":[-6.5359787941,43.5441894531],"type":"Point"}
}