{
  "type": "Feature",
  "properties": {
    "addr:full":"Carrer de Mossen Jacint Verdaguer, 80 Santa Coloma De Gramenet Barcelona 08923",
    "addr:housenumber":"80",
    "addr:postcode":"08923",
    "addr:street":"Carrer De Mossen Jacint Verdaguer",
    "iso:country":"ES",
    "sg:address":"Carrer de Mossen Jacint Verdaguer, 80",
    "sg:city":"Santa Coloma De Gramenet",
    "sg:orig_category":"Panader\u00cdas, Panader\u00cdas",
    "sg:phone":"+34 934 66 29 26",
    "sg:postcode":"08923",
    "sg:province":"Barcelona",
    "wof:name":"Panificadora San Carlos S.a.",
    "wof:placetype":"venue"
},
  "geometry": {"coordinates":[2.2125198841,41.4475708008],"type":"Point"}
}