{
  "type": "Feature",
  "properties": {
    "addr:full":"Uriburu Kalea, 11 Arrasate Guip\u00f9zcoa 20500",
    "addr:housenumber":"11",
    "addr:postcode":"20500",
    "addr:street":"Uriburu Kalea;Guipu\u0300Zcoa",
    "iso:country":"ES",
    "sg:address":"Uriburu Kalea, 11",
    "sg:city":"Arrasate",
    "sg:orig_category":"Promotores Constructores",
    "sg:phone":"+34 943 79 95 84",
    "sg:postcode":"20500",
    "sg:province":"Guip\u00f9zcoa",
    "wof:name":"Alba\u00f1ileria Y Construcciones Gorbea S.l.",
    "wof:placetype":"venue"
},
  "geometry": {"coordinates":[-2.4990825653,43.0624427795],"type":"Point"}
}