{
  "type": "Feature",
  "properties": {
    "iso:country":"ES",
    "sg:address":"Ctra Monta\u00d1a (la), 36",
    "sg:city":"Monta\u00d1eta",
    "sg:orig_category":"Peluquer\u00cdas, Peluquer\u00cda Mixta",
    "sg:phone":"+34 922 34 27 05",
    "sg:postcode":"38419",
    "sg:province":"Santa Cruz De Tenerife",
    "wof:name":"Gymbel S.c.",
    "wof:placetype":"venue"
},
  "geometry": {"coordinates":[-16.5607452393,28.3888816833],"type":"Point"}
}