{
  "type": "Feature",
  "properties": {
    "addr:full":"Rua Corgo, 91 Grove Pontevedra 36980",
    "addr:housenumber":"91",
    "addr:postcode":"36980",
    "addr:street":"Rua Corgo;Grove Pontevedra",
    "iso:country":"ES",
    "sg:address":"Rua Corgo, 91",
    "sg:city":"Grove",
    "sg:orig_category":"Pescader\u00cdas (al Por Menor)",
    "sg:phone":"+34 986 73 07 40",
    "sg:postcode":"36980",
    "sg:province":"Pontevedra",
    "wof:name":"Gonzalez Valeiras Maria Sol",
    "wof:placetype":"venue"
},
  "geometry": {"coordinates":[-8.8653488159,42.4964790344],"type":"Point"}
}