{
  "type": "Feature",
  "properties": {
    "addr:full":"La Ambilla, S/n Calahorra La Rioja 26500",
    "addr:housenumber":"s / n",
    "addr:postcode":"26500",
    "iso:country":"ES",
    "sg:address":"La Ambilla, S/n",
    "sg:city":"Calahorra",
    "sg:orig_category":"Invernaderos Y Semilleros",
    "sg:phone":"+34 941 74 30 34",
    "sg:postcode":"26500",
    "sg:province":"La Rioja",
    "wof:name":"Olivan Garcia Jose Manuel",
    "wof:placetype":"venue"
},
  "geometry": {"coordinates":[-1.9498690367,42.2919387817],"type":"Point"}
}