{
  "type": "Feature",
  "properties": {
    "iso:country":"ES",
    "sg:address":"Cami Muntanya, 2",
    "sg:city":"Pol Indu Marratxi",
    "sg:orig_category":"Piscinas, Accesorios, Suministros (fabricaci\u00d3n, Al Por Mayor)",
    "sg:phone":"+34 971 60 55 67",
    "sg:postcode":"07141",
    "sg:province":"Islas Baleares",
    "wof:name":"Astral Pool Espa\u00d1a S.a.u.",
    "wof:placetype":"venue"
},
  "geometry": {"coordinates":[2.7521929741,39.6421279907],"type":"Point"}
}