{
  "type": "Feature",
  "properties": {
    "addr:full":"Avda Gasteiz, 53 Vitoria-gasteiz \u00c1lava 01008",
    "addr:housenumber":"53",
    "addr:postcode":"01008",
    "addr:street":"Avda Gasteiz",
    "iso:country":"ES",
    "sg:address":"Avda Gasteiz, 53",
    "sg:city":"Vitoria-gasteiz",
    "sg:orig_category":"Juristas",
    "sg:phone":"+34 945 24 83 23",
    "sg:postcode":"01008",
    "sg:province":"\u00c1lava",
    "wof:name":"Rubio Cabrerizo Nieves",
    "wof:placetype":"venue"
},
  "geometry": {"coordinates":[-2.6817200184,42.8483581543],"type":"Point"}
}