{
  "type": "Feature",
  "properties": {
    "addr:full":"Cmno Collet, 72 Castellon De La Plana Castell\u00f3n 12004",
    "addr:housenumber":"72",
    "addr:postcode":"12004",
    "addr:street":"Cmno Collet",
    "iso:country":"ES",
    "sg:address":"Cmno Collet, 72",
    "sg:city":"Castellon De La Plana",
    "sg:orig_category":"Asistencia Social",
    "sg:phone":"+34 964 73 00 60",
    "sg:postcode":"12004",
    "sg:province":"Castell\u00f3n",
    "wof:name":"Hijas De La Caridad De San Vicente De Paul",
    "wof:placetype":"venue"
},
  "geometry": {"coordinates":[0.0330299996,40.0113639832],"type":"Point"}
}