{
  "type": "Feature",
  "properties": {
    "addr:full":"Calle de Leandro Navarro, 10 Mora Toledo 45400",
    "addr:housenumber":"10",
    "addr:postcode":"45400",
    "addr:street":"Calle De Leandro Navarro",
    "iso:country":"ES",
    "sg:address":"Calle de Leandro Navarro, 10",
    "sg:city":"Mora",
    "sg:orig_category":"Fabricaci\u00d3n De Muebles",
    "sg:phone":"+34 925 30 08 46",
    "sg:postcode":"45400",
    "sg:province":"Toledo",
    "wof:name":"Muebles Palencia S.a.l. Y La Boutique De Las Cortinas S.l. U.t.e.",
    "wof:placetype":"venue"
},
  "geometry": {"coordinates":[-3.7740700245,39.684337616],"type":"Point"}
}