{
  "type": "Feature",
  "properties": {
    "addr:full":"Calle de Diputacion, 5 Ermua Vizcaya 48260",
    "addr:housenumber":"5",
    "addr:postcode":"48260",
    "addr:street":"Calle De Diputacion",
    "iso:country":"ES",
    "sg:address":"Calle de Diputacion, 5",
    "sg:city":"Ermua",
    "sg:orig_category":"Molduras, Junquillos, Listones Y Molduras Perforadas",
    "sg:phone":"+34 943 17 19 89",
    "sg:postcode":"48260",
    "sg:province":"Vizcaya",
    "wof:name":"Barona Monasterio Elena",
    "wof:placetype":"venue"
},
  "geometry": {"coordinates":[-2.5047519207,43.186668396],"type":"Point"}
}