{
  "type": "Feature",
  "properties": {
    "addr:full":"Avda Jeronimo Roure, 47 Puerto Valencia 46520",
    "addr:housenumber":"47",
    "addr:postcode":"46520",
    "addr:street":"Avda Jeronimo Roure",
    "iso:country":"ES",
    "sg:address":"Avda Jeronimo Roure, 47",
    "sg:city":"Puerto",
    "sg:orig_category":"Chapister\u00cda",
    "sg:phone":"+34 962 67 26 53",
    "sg:postcode":"46520",
    "sg:province":"Valencia",
    "wof:name":"Rustarazo Berja Jose",
    "wof:placetype":"venue"
},
  "geometry": {"coordinates":[-0.2245189995,39.6594085693],"type":"Point"}
}