{
  "type": "Feature",
  "properties": {
    "addr:full":"Calle de Treinta De Mayo, 23 San Pedro De Bre\u00e7a Alta Santa Cruz De Tenerife 38712",
    "addr:housenumber":"23",
    "addr:postcode":"38712",
    "addr:street":"Calle De Treinta De Mayo",
    "iso:country":"ES",
    "sg:address":"Calle de Treinta De Mayo, 23",
    "sg:city":"San Pedro De Bre\u00e7a Alta",
    "sg:orig_category":"Agencias De Viajes",
    "sg:phone":"+34 922 43 80 94",
    "sg:postcode":"38712",
    "sg:province":"Santa Cruz De Tenerife",
    "wof:name":"Viajes Kiara S.l.l.",
    "wof:placetype":"venue"
},
  "geometry": {"coordinates":[-17.7672138214,28.6476554871],"type":"Point"}
}