{
  "type": "Feature",
  "properties": {
    "iso:country":"ES",
    "sg:address":"Calle de Carretero, 1",
    "sg:city":"Coria Rio",
    "sg:orig_category":"Farmacias",
    "sg:phone":"+34 954 77 00 69",
    "sg:postcode":"41100",
    "sg:province":"Sevilla",
    "wof:name":"Farmacia Santa Maria C.b.",
    "wof:placetype":"venue"
},
  "geometry": {"coordinates":[-6.0536646843,37.2856712341],"type":"Point"}
}