{
  "type": "Feature",
  "properties": {
    "iso:country":"ES",
    "sg:address":"Plaz San Salvador, S/n",
    "sg:city":"Quintanilla Somoza",
    "sg:orig_category":"Asilos De Ancianos. Centros Privados",
    "sg:phone":"+34 987 60 16 96",
    "sg:postcode":"24717",
    "sg:province":"Le\u00f3n",
    "wof:name":"Gonzalez Sanchez Pilar",
    "wof:placetype":"venue"
},
  "geometry": {"coordinates":[-6.118844986,42.4167747498],"type":"Point"}
}