{
  "type": "Feature",
  "properties": {
    "addr:full":"Carr Canalejas, 11 Vila Joiosa Alicante 03570",
    "addr:housenumber":"11",
    "addr:postcode":"03570",
    "addr:street":"Carr Canalejas",
    "iso:country":"ES",
    "sg:address":"Carr Canalejas, 11",
    "sg:city":"Vila Joiosa",
    "sg:orig_category":"Perfumer\u00cda Y Cosm\u00c9tica (fabricaci\u00d3n, Al Por Mayor)",
    "sg:phone":"+34 965 89 04 77",
    "sg:postcode":"03570",
    "sg:province":"Alicante",
    "wof:name":"Rodriguez Olivares Maria Angeles",
    "wof:placetype":"venue"
},
  "geometry": {"coordinates":[-0.7466139793,38.3102035522],"type":"Point"}
}