{
  "type": "Feature",
  "properties": {
    "addr:full":"Carr S Josep, 80 Igualada Barcelona 08700",
    "addr:housenumber":"80",
    "addr:postcode":"08700",
    "addr:street":"Carr S Josep",
    "iso:country":"ES",
    "sg:address":"Carr S Josep, 80",
    "sg:city":"Igualada",
    "sg:orig_category":"Carnicer\u00cdas, Carnicer\u00cdas",
    "sg:phone":"+34 938 04 30 38",
    "sg:postcode":"08700",
    "sg:province":"Barcelona",
    "wof:name":"Maria Iba\u00d1ez Domenech",
    "wof:placetype":"venue"
},
  "geometry": {"coordinates":[1.6236490011,41.5828094482],"type":"Point"}
}