{
  "type": "Feature",
  "properties": {
    "iso:country":"ES",
    "sg:address":"Calle de San Miguel, 13",
    "sg:city":"Olmedo",
    "sg:orig_category":"Promotores Constructores",
    "sg:phone":"+34 983 60 08 74",
    "sg:postcode":"47410",
    "sg:province":"Valladolid",
    "wof:name":"Andrea Carromero Juan Antonio De",
    "wof:placetype":"venue"
},
  "geometry": {"coordinates":[-4.6871113777,41.2863769531],"type":"Point"}
}