{
  "type": "Feature",
  "properties": {
    "iso:country":"ES",
    "sg:address":"Aiguadol\u00e7 (amarres), 13",
    "sg:city":"Sitges",
    "sg:orig_category":"Fabricaci\u00d3n, Reparaci\u00d3n Y Mantenimiento De Construcciones Navales Y Fluviales",
    "sg:phone":"+34 938 94 70 95",
    "sg:postcode":"08870",
    "sg:province":"Barcelona",
    "wof:name":"Marcolor-aiguadol\u00e7 S.c.p.",
    "wof:placetype":"venue"
},
  "geometry": {"coordinates":[1.8199939728,41.2375869751],"type":"Point"}
}