{
  "type": "Feature",
  "properties": {
    "iso:country":"ES",
    "sg:address":"Calle de Matadero, S/n",
    "sg:city":"Puebla Almoradiel",
    "sg:orig_category":"Piedra Natural",
    "sg:phone":"+34 925 17 83 75",
    "sg:postcode":"45840",
    "sg:province":"Toledo",
    "sg:website":"www.mygreunidos.com",
    "wof:name":"Marmoles Y Granitos Reunidos S.l.",
    "wof:placetype":"venue"
},
  "geometry": {"coordinates":[-3.1244590282,39.5964508057],"type":"Point"}
}