{
  "type": "Feature",
  "properties": {
    "iso:country":"ES",
    "sg:address":"Plaz Puerto Rubio, 20",
    "sg:city":"Madrid",
    "sg:orig_category":"\u00d3ptica: Instrumentos (fabricaci\u00d3n)",
    "sg:phone":"+34 914 33 60 14",
    "sg:postcode":"28053",
    "sg:province":"Madrid",
    "wof:name":"Anjusa Fomento S.l.",
    "wof:placetype":"venue"
},
  "geometry": {"coordinates":[-3.6676530838,40.3963241577],"type":"Point"}
}