{
  "type": "Feature",
  "properties": {
    "iso:country":"ES",
    "sg:address":"Calle de Iglesias, 43",
    "sg:city":"Caravaca Cruz",
    "sg:orig_category":"Transportes Por Carretera: Lotes Completos, Mercanc\u00cdas Diversas",
    "sg:phone":"+34 968 70 73 80",
    "sg:postcode":"30400",
    "sg:province":"Murcia",
    "wof:name":"Lopez Gimenez Maria Carmen",
    "wof:placetype":"venue"
},
  "geometry": {"coordinates":[-1.8635710478,38.1059341431],"type":"Point"}
}