{
  "type": "Feature",
  "properties": {
    "addr:full":"Calle de San Antonio, 6 Montehermoso C\u00e1ceres 10810",
    "addr:housenumber":"6",
    "addr:postcode":"10810",
    "addr:street":"Calle De San Antonio;Ca\u0301Ceres",
    "iso:country":"ES",
    "sg:address":"Calle de San Antonio, 6",
    "sg:city":"Montehermoso",
    "sg:orig_category":"Cr\u00cda De Animales",
    "sg:phone":"+34 927 43 01 79",
    "sg:postcode":"10810",
    "sg:province":"C\u00e1ceres",
    "wof:name":"Martin Dominguez Celestino",
    "wof:placetype":"venue"
},
  "geometry": {"coordinates":[-6.3503952026,40.089881897],"type":"Point"}
}