{
  "type": "Feature",
  "properties": {
    "addr:full":"Carrer de Coma (de La), 2 Constanti Tarragona 43120",
    "addr:housenumber":"2",
    "addr:postcode":"43120",
    "addr:street":"Carrer De Coma De La",
    "iso:country":"ES",
    "sg:address":"Carrer de Coma (de La), 2",
    "sg:city":"Constanti",
    "sg:orig_category":"Notarios",
    "sg:phone":"+34 977 52 40 30",
    "sg:postcode":"43120",
    "sg:province":"Tarragona",
    "wof:name":"Pajares Sanchez Francisco Javier",
    "wof:placetype":"venue"
},
  "geometry": {"coordinates":[1.2171089649,41.1520614624],"type":"Point"}
}