{
  "type": "Feature",
  "properties": {
    "iso:country":"ES",
    "sg:address":"Calle de Rabida, 23",
    "sg:city":"Palos Frontera",
    "sg:orig_category":"Cobro De Pr\u00c9stamos",
    "sg:phone":"+34 959 35 12 64",
    "sg:postcode":"21810",
    "sg:province":"Huelva",
    "wof:name":"Servicio Provincial De Recaudacion Y Gestion Tributaria",
    "wof:placetype":"venue"
},
  "geometry": {"coordinates":[-6.8938570023,37.2281227112],"type":"Point"}
}