{
  "type": "Feature",
  "properties": {
    "iso:country":"ES",
    "sg:address":"Calle de Puerta Osuna, 66",
    "sg:city":"Arahal",
    "sg:orig_category":"Promotores Constructores",
    "sg:phone":"+34 954 84 17 92",
    "sg:postcode":"41600",
    "sg:province":"Sevilla",
    "wof:name":"Galan Montilla Manuel",
    "wof:placetype":"venue"
},
  "geometry": {"coordinates":[-5.5399541855,37.2620735168],"type":"Point"}
}