{
  "type": "Feature",
  "properties": {
    "addr:full":"Calle de Legazpi, 8 Donostia-san Sebastian Guip\u00f9zcoa 20004",
    "addr:housenumber":"8",
    "addr:postcode":"20004",
    "addr:street":"Calle De Legazpi",
    "iso:country":"ES",
    "sg:address":"Calle de Legazpi, 8",
    "sg:city":"Donostia-san Sebastian",
    "sg:orig_category":"Ropa Para Ni\u00d1os (al Por Menor)",
    "sg:phone":"+34 943 43 15 50",
    "sg:postcode":"20004",
    "sg:province":"Guip\u00f9zcoa",
    "wof:name":"Josefina Serrano Ropa S.l.",
    "wof:placetype":"venue"
},
  "geometry": {"coordinates":[-1.9824850559,43.3219490051],"type":"Point"}
}