{
  "type": "Feature",
  "properties": {
    "addr:full":"Calle de Camino De Casarrubios, 9 Navalcarnero Madrid 28600",
    "addr:housenumber":"9",
    "addr:postcode":"28600",
    "addr:street":"Calle De Camino De Casarrubios",
    "iso:country":"ES",
    "sg:address":"Calle de Camino De Casarrubios, 9",
    "sg:city":"Navalcarnero",
    "sg:orig_category":"Negocio De Enlosados, Soler\u00cdas",
    "sg:phone":"+34 918 11 12 58",
    "sg:postcode":"28600",
    "sg:province":"Madrid",
    "wof:name":"Sevillano Carde\u00f1a Tomas",
    "wof:placetype":"venue"
},
  "geometry": {"coordinates":[-4.0074911118,40.2892875671],"type":"Point"}
}