{
  "type": "Feature",
  "properties": {
    "iso:country":"ES",
    "sg:address":"Calle de Galicia, 1",
    "sg:city":"Casetas",
    "sg:orig_category":"Chapister\u00cda",
    "sg:phone":"+34 976 77 13 73",
    "sg:postcode":"50620",
    "sg:province":"Zaragoza",
    "wof:name":"Futurauto S.c",
    "wof:placetype":"venue"
},
  "geometry": {"coordinates":[-1.0247573853,41.7183189392],"type":"Point"}
}