{
  "type": "Feature",
  "properties": {
    "addr:full":"Carrer de Regomir, 1 Barcelona Barcelona 08002",
    "addr:housenumber":"1",
    "addr:postcode":"08002",
    "addr:street":"Carrer De Regomir",
    "iso:country":"ES",
    "sg:address":"Carrer de Regomir, 1",
    "sg:city":"Barcelona",
    "sg:orig_category":"Talleres: Ropa A Medida",
    "sg:phone":"+34 933 15 17 58",
    "sg:postcode":"08002",
    "sg:province":"Barcelona",
    "wof:name":"Leal Garcia Marino",
    "wof:placetype":"venue"
},
  "geometry": {"coordinates":[2.1789119244,41.3815956116],"type":"Point"}
}