{
  "type": "Feature",
  "properties": {
    "addr:full":"Carpinteros (pi Villa Rota P P Tres), 20 Rota C\u00e1diz 11520",
    "addr:housenumber":"20",
    "addr:postcode":"11520",
    "addr:street":"Rota Ca\u0301Diz",
    "iso:country":"ES",
    "sg:address":"Carpinteros (pi Villa Rota P P Tres), 20",
    "sg:city":"Rota",
    "sg:orig_category":"Cerrajer\u00cda, Ferrallista",
    "sg:phone":"+34 956 81 24 66",
    "sg:postcode":"11520",
    "sg:province":"C\u00e1diz",
    "wof:name":"Ruiz-henestrosa Bernal Manuel",
    "wof:placetype":"venue"
},
  "geometry": {"coordinates":[-6.3641328812,36.6322822571],"type":"Point"}
}