{
  "type": "Feature",
  "properties": {
    "addr:full":"Calle de Batalla De Las Flores, 5 Mazarron Murcia 30870",
    "addr:housenumber":"5",
    "addr:postcode":"30870",
    "addr:street":"Calle De Batalla De Las Flores",
    "iso:country":"ES",
    "sg:address":"Calle de Batalla De Las Flores, 5",
    "sg:city":"Mazarron",
    "sg:orig_category":"Fabricaci\u00d3n De Distribuidores Autom\u00c1ticos",
    "sg:phone":"+34 968 59 08 96",
    "sg:postcode":"30870",
    "sg:province":"Murcia",
    "wof:name":"Ortiz Mu\u00f1oz Juan Gregorio",
    "wof:placetype":"venue"
},
  "geometry": {"coordinates":[-1.314209342,37.6045913696],"type":"Point"}
}