{
  "type": "Feature",
  "properties": {
    "addr:full":"Praj Barranco Molax, 26 Barranco Molax Murcia 30550",
    "addr:housenumber":"26",
    "addr:postcode":"30550",
    "addr:street":"Molax",
    "iso:country":"ES",
    "sg:address":"Praj Barranco Molax, 26",
    "sg:city":"Barranco Molax",
    "sg:orig_category":"Cajas Y Embalajes De Cart\u00d3n Y Papel",
    "sg:phone":"+34 968 45 04 43",
    "sg:postcode":"30550",
    "sg:province":"Murcia",
    "wof:name":"Servicios De Envases Montados S.l.",
    "wof:placetype":"venue"
},
  "geometry": {"coordinates":[-1.3944859505,38.2074737549],"type":"Point"}
}