{
  "type": "Feature",
  "properties": {
    "addr:full":"Calle de Ramon Y Cajal, 11 Bolbaite Valencia 46822",
    "addr:housenumber":"11",
    "addr:postcode":"46822",
    "addr:street":"Calle De Ramon Y Cajal",
    "iso:country":"ES",
    "sg:address":"Calle de Ramon Y Cajal, 11",
    "sg:city":"Bolbaite",
    "sg:orig_category":"Aceites Y Grasas Alimentarias (fabricaci\u00d3n, Al Por Mayor)",
    "sg:phone":"+34 962 22 30 15",
    "sg:postcode":"46822",
    "sg:province":"Valencia",
    "wof:name":"Cooperativa Agricola De Bolbaite Coop.v",
    "wof:placetype":"venue"
},
  "geometry": {"coordinates":[-0.674695015,39.0614395142],"type":"Point"}
}