{
  "type": "Feature",
  "properties": {
    "iso:country":"ES",
    "sg:address":"Calle de Gran Via, 36",
    "sg:city":"Madrid",
    "sg:orig_category":"Ropa Y Accesorios",
    "sg:phone":"+34 915 21 21 94",
    "sg:postcode":"28013",
    "sg:province":"Madrid",
    "wof:name":"Alonso Mayoral Ricardo",
    "wof:placetype":"venue"
},
  "geometry": {"coordinates":[-3.7040274143,40.420135498],"type":"Point"}
}