{
  "type": "Feature",
  "properties": {
    "iso:country":"ES",
    "sg:address":"Carr Nazareno, 71",
    "sg:city":"Oliva",
    "sg:orig_category":"Cr\u00cda De Perros Y De Gatos",
    "sg:phone":"+34 962 85 09 18",
    "sg:postcode":"46780",
    "sg:province":"Valencia",
    "wof:name":"Masquefa Sansaloni Vicente",
    "wof:placetype":"venue"
},
  "geometry": {"coordinates":[-0.1180580035,38.9169311523],"type":"Point"}
}