{
  "type": "Feature",
  "properties": {
    "addr:full":"Calle de Barrio Chico, S/n Villanueva De Los Infantes Ciudad Real 13320",
    "addr:housenumber":"s",
    "addr:postcode":"13320",
    "addr:street":"Calle De Barrio Chico;/ N;Infantes",
    "iso:country":"ES",
    "sg:address":"Calle de Barrio Chico, S/n",
    "sg:city":"Villanueva De Los Infantes",
    "sg:orig_category":"Transportes Por Carretera: Lotes Completos, Mercanc\u00cdas Diversas",
    "sg:phone":"+34 926 36 00 13",
    "sg:postcode":"13320",
    "sg:province":"Ciudad Real",
    "wof:name":"Gonzalez Sarrion S.a.",
    "wof:placetype":"venue"
},
  "geometry": {"coordinates":[-3.0095160007,38.7335739136],"type":"Point"}
}