{
  "type": "Feature",
  "properties": {
    "iso:country":"ES",
    "sg:address":"Calle de Sol, Del, 7",
    "sg:city":"Talavera Reina",
    "sg:orig_category":"Alquiler De Casas Y Habitaciones Amuebladas",
    "sg:phone":"+34 925 81 16 70",
    "sg:postcode":"45600",
    "sg:province":"Toledo",
    "wof:name":"Ciudadela Residencia Universitaria S.l.",
    "wof:placetype":"venue"
},
  "geometry": {"coordinates":[-4.8326292038,39.9584884644],"type":"Point"}
}