{
  "type": "Feature",
  "properties": {
    "iso:country":"ES",
    "sg:address":"Avda Parque (del), 18",
    "sg:city":"Fuentidue\u00e7a De Tajo",
    "sg:orig_category":"Fabricaci\u00d3n De Juguetes Autom\u00c1ticos",
    "sg:phone":"+34 918 72 81 88",
    "sg:postcode":"28597",
    "sg:province":"Madrid",
    "wof:name":"Automaticos Navelsa S.l.",
    "wof:placetype":"venue"
},
  "geometry": {"coordinates":[-3.1575810909,40.1166648865],"type":"Point"}
}