{
  "type": "Feature",
  "properties": {
    "addr:full":"Calle de Profesor Juan Tadeo Cabrera, 30 Pto. Rosario Las Palmas 35600",
    "addr:housenumber":"30",
    "addr:postcode":"35600",
    "addr:street":"Calle De Profesor Juan Tadeo Cabrera;Pto. Rosario Las",
    "iso:country":"ES",
    "sg:address":"Calle de Profesor Juan Tadeo Cabrera, 30",
    "sg:city":"Pto. Rosario",
    "sg:orig_category":"Inmobiliaria (agencias)",
    "sg:phone":"+34 928 53 30 06",
    "sg:postcode":"35600",
    "sg:province":"Las Palmas",
    "wof:name":"Adarvis Sl",
    "wof:placetype":"venue"
},
  "geometry": {"coordinates":[-13.8634357452,28.4975662231],"type":"Point"}
}