{
  "type": "Feature",
  "properties": {
    "iso:country":"ES",
    "sg:address":"Trav. Calle de A, 2",
    "sg:city":"Mutiloabeiti",
    "sg:orig_category":"Instalaci\u00d3n, Reparaci\u00d3n De Ascensores Y Montacargas",
    "sg:phone":"+34 948 23 04 23",
    "sg:postcode":"31192",
    "sg:province":"Navarra",
    "sg:website":"www.muguerzaingenieros.com",
    "wof:name":"Kone S.a.",
    "wof:placetype":"venue"
},
  "geometry": {"coordinates":[-1.6151809692,42.7892303467],"type":"Point"}
}