{
  "type": "Feature",
  "properties": {
    "addr:full":"Calle de Sor Valentina Miron, 26 Plasencia C\u00e1ceres 10600",
    "addr:housenumber":"26",
    "addr:postcode":"10600",
    "addr:street":"Calle De Sor Valentina Miron;Ca\u0301Ceres",
    "iso:country":"ES",
    "sg:address":"Calle de Sor Valentina Miron, 26",
    "sg:city":"Plasencia",
    "sg:orig_category":"Art\u00cdculos De Decoraci\u00d3n",
    "sg:phone":"+34 927 42 12 53",
    "sg:postcode":"10600",
    "sg:province":"C\u00e1ceres",
    "wof:name":"Marianton Decor S.l.",
    "wof:placetype":"venue"
},
  "geometry": {"coordinates":[-6.0900449753,40.0326881409],"type":"Point"}
}