{
  "type": "Feature",
  "properties": {
    "iso:country":"ES",
    "sg:address":"Rua Laureano Pelaez, 21",
    "sg:city":"Verin",
    "sg:orig_category":"Agentes Generales De Seguros",
    "sg:phone":"+34 988 41 17 83",
    "sg:postcode":"32600",
    "sg:province":"Ourense",
    "wof:name":"Morais Castro Julio",
    "wof:placetype":"venue"
},
  "geometry": {"coordinates":[-7.4367609024,41.9379386902],"type":"Point"}
}