{
  "type": "Feature",
  "properties": {
    "iso:country":"ES",
    "sg:address":"Calle de San Antonio, 22",
    "sg:city":"Vitoria-gasteiz",
    "sg:orig_category":"Tapicer\u00cdas",
    "sg:phone":"+34 945 06 52 22",
    "sg:postcode":"01005",
    "sg:province":"\u00c1lava",
    "wof:name":"Arnute, S.l.",
    "wof:placetype":"venue"
},
  "geometry": {"coordinates":[-2.674500227,42.843120575],"type":"Point"}
}