{
  "type": "Feature",
  "properties": {
    "iso:country":"ES",
    "sg:address":"Calle de Anastasio Mateo, 15",
    "sg:city":"Villamediana Iregua",
    "sg:orig_category":"Cerrajer\u00cda, Ferrallista",
    "sg:phone":"+34 941 43 51 37",
    "sg:postcode":"26142",
    "sg:province":"La Rioja",
    "wof:name":"Pueyo Saenz Juan Cruz Del",
    "wof:placetype":"venue"
},
  "geometry": {"coordinates":[-2.4184439182,42.4274940491],"type":"Point"}
}