{
  "type": "Feature",
  "properties": {
    "iso:country":"ES",
    "sg:address":"Calle de Sagrado Corazon, 10",
    "sg:city":"Gijon",
    "sg:orig_category":"Ense\u00d1anza Variada",
    "sg:phone":"+34 985 14 02 04",
    "sg:postcode":"33205",
    "sg:province":"Asturias",
    "sg:website":"www.desto@deusto.e.telefonica.net",
    "wof:name":"Gomez Diaz Jose Javier",
    "wof:placetype":"venue"
},
  "geometry": {"coordinates":[-5.6569008827,43.5338783264],"type":"Point"}
}