{
  "type": "Feature",
  "properties": {
    "addr:full":"Carrer de Manuel De Falla, 38 Barbera Valles Barcelona 08210",
    "addr:housenumber":"38",
    "addr:postcode":"08210",
    "addr:street":"Carrer De Manuel De Falla",
    "iso:country":"ES",
    "sg:address":"Carrer de Manuel De Falla, 38",
    "sg:city":"Barbera Valles",
    "sg:orig_category":"Agentes Generales De Seguros",
    "sg:phone":"+34 937 18 38 28",
    "sg:postcode":"08210",
    "sg:province":"Barcelona",
    "wof:name":"Gestions I Assegurances Ab S.l.",
    "wof:placetype":"venue"
},
  "geometry": {"coordinates":[2.1237699986,41.516620636],"type":"Point"}
}