{
  "type": "Feature",
  "properties": {
    "iso:country":"ES",
    "sg:address":"Av Diagonal, 399",
    "sg:city":"Barcelona",
    "sg:orig_category":"Agencias Y Asesores De Publicidad",
    "sg:phone":"+34 932 38 54 80",
    "sg:postcode":"08008",
    "sg:province":"Barcelona",
    "sg:website":"www.generalcrea.com",
    "wof:name":"General De Creatividad S.a",
    "wof:placetype":"venue"
},
  "geometry": {"coordinates":[2.1570611,41.3956947327],"type":"Point"}
}