{
  "type": "Feature",
  "properties": {
    "addr:full":"Carrer de Menendez Pidal, 2 Mataro Barcelona 08304",
    "addr:housenumber":"2",
    "addr:postcode":"08304",
    "addr:street":"Carrer De Menendez Pidal",
    "iso:country":"ES",
    "sg:address":"Carrer de Menendez Pidal, 2",
    "sg:city":"Mataro",
    "sg:orig_category":"Zapatos (al Por Menor)",
    "sg:phone":"+34 937 96 31 02",
    "sg:postcode":"08304",
    "sg:province":"Barcelona",
    "wof:name":"Mu\u00f1oz Perez Antonia",
    "wof:placetype":"venue"
},
  "geometry": {"coordinates":[2.452575922,41.5477027893],"type":"Point"}
}