{
  "type": "Feature",
  "properties": {
    "addr:full":"Luga Pazos, S/n Lestedo La Coru\u00f1a 15881",
    "addr:housenumber":"s",
    "addr:postcode":"15881",
    "addr:street":"Pazos;/ N Lestedo La Corun\u0303A",
    "iso:country":"ES",
    "sg:address":"Luga Pazos, S/n",
    "sg:city":"Lestedo",
    "sg:orig_category":"Venta, Instalaci\u00d3n De Calefacci\u00d3n",
    "sg:phone":"+34 981 50 20 39",
    "sg:postcode":"15881",
    "sg:province":"La Coru\u00f1a",
    "wof:name":"Instalaciones Mopisca Galicia S.l.",
    "wof:placetype":"venue"
},
  "geometry": {"coordinates":[-8.4128170013,42.8135566711],"type":"Point"}
}