{
  "type": "Feature",
  "properties": {
    "iso:country":"ES",
    "sg:address":"Calle de Miguel Fluiters, 21",
    "sg:city":"Guadalajara",
    "sg:orig_category":"Loter\u00cda Y T\u00d3mbola",
    "sg:phone":"+34 949 21 17 79",
    "sg:postcode":"19001",
    "sg:province":"Guadalajara",
    "wof:name":"Moya Barra Inmaculada",
    "wof:placetype":"venue"
},
  "geometry": {"coordinates":[-3.1676280499,40.6346855164],"type":"Point"}
}