{
  "type": "Feature",
  "properties": {
    "iso:country":"ES",
    "sg:address":"Plaz Durangoko Plateruen Plaza, 1",
    "sg:city":"Durango",
    "sg:orig_category":"Organizaci\u00d3n De Actos, Seminarios Y Congresos",
    "sg:phone":"+34 946 20 27 89",
    "sg:postcode":"48200",
    "sg:province":"Vizcaya",
    "sg:website":"www.errai.com",
    "wof:name":"Errai C.b.",
    "wof:placetype":"venue"
},
  "geometry": {"coordinates":[-2.6117420197,43.194644928],"type":"Point"}
}