{
  "type": "Feature",
  "properties": {
    "addr:full":"Avda Madrid (de), 84 Avila \u00c1vila 05001",
    "addr:housenumber":"84",
    "addr:postcode":"05001",
    "addr:street":"Avda Madrid De;A\u0301Vila",
    "iso:country":"ES",
    "sg:address":"Avda Madrid (de), 84",
    "sg:city":"Avila",
    "sg:orig_category":"Distribuci\u00d3n De Petr\u00d3leo Y Derivados",
    "sg:phone":"+34 920 25 70 84",
    "sg:postcode":"05001",
    "sg:province":"\u00c1vila",
    "wof:name":"Donoctano S. A.",
    "wof:placetype":"venue"
},
  "geometry": {"coordinates":[-4.7049150467,40.6595153809],"type":"Point"}
}