{
  "type": "Feature",
  "properties": {
    "iso:country":"ES",
    "sg:address":"Avda San Ignacio, 16",
    "sg:city":"Le\u00f3n",
    "sg:orig_category":"Plomeros",
    "sg:phone":"+34 987 24 65 11",
    "sg:postcode":"24010",
    "sg:province":"Le\u00f3n",
    "wof:name":"Fonca Y Coba S.l.",
    "wof:placetype":"venue"
},
  "geometry": {"coordinates":[-5.5895471573,42.6041069031],"type":"Point"}
}