{
  "type": "Feature",
  "properties": {
    "addr:full":"Carrer de Mediterrani, 8 Crevillent Alicante 03330",
    "addr:housenumber":"8",
    "addr:postcode":"03330",
    "addr:street":"Carrer De Mediterrani",
    "iso:country":"ES",
    "sg:address":"Carrer de Mediterrani, 8",
    "sg:city":"Crevillent",
    "sg:orig_category":"Peluquer\u00cdas, Peluquer\u00cda Mixta",
    "sg:phone":"+34 965 40 60 55",
    "sg:postcode":"03330",
    "sg:province":"Alicante",
    "wof:name":"Arronis Valero Carmen",
    "wof:placetype":"venue"
},
  "geometry": {"coordinates":[-0.8039556146,38.2456932068],"type":"Point"}
}