{
  "type": "Feature",
  "properties": {
    "addr:full":"Empetrol, S/n Pobla Mafumet Tarragona 43140",
    "addr:housenumber":"/ n",
    "addr:postcode":"43140",
    "addr:street":"Empetrol S",
    "iso:country":"ES",
    "sg:address":"Empetrol, S/n",
    "sg:city":"Pobla Mafumet",
    "sg:orig_category":"Resinas Sint\u00c9ticas (fabricaci\u00d3n, Al Por Mayor)",
    "sg:phone":"+34 977 84 07 19",
    "sg:postcode":"43140",
    "sg:province":"Tarragona",
    "wof:name":"Hispavic Iberica",
    "wof:placetype":"venue"
},
  "geometry": {"coordinates":[1.2092289925,41.1888885498],"type":"Point"}
}