{
  "type": "Feature",
  "properties": {
    "addr:full":"Carrer de Doctor Pi I Molist, 97 Barcelona Barcelona 08031",
    "addr:housenumber":"97",
    "addr:postcode":"08031",
    "addr:street":"Carrer De Doctor Pi I Molist",
    "iso:country":"ES",
    "sg:address":"Carrer de Doctor Pi I Molist, 97",
    "sg:city":"Barcelona",
    "sg:orig_category":"Dietistas",
    "sg:phone":"+34 933 59 96 34",
    "sg:postcode":"08031",
    "sg:province":"Barcelona",
    "wof:name":"Espada Gavila Raquel",
    "wof:placetype":"venue"
},
  "geometry": {"coordinates":[2.1723840237,41.4344596863],"type":"Point"}
}