{
  "type": "Feature",
  "properties": {
    "iso:country":"ES",
    "sg:address":"Calle de Musico Peydro, 28",
    "sg:city":"Valencia",
    "sg:orig_category":"Art\u00cdculos De Regalo (al Por Menor)",
    "sg:phone":"+34 963 52 31 48",
    "sg:postcode":"46001",
    "sg:province":"Valencia",
    "wof:name":"Barbato  Michelarcangelo",
    "wof:placetype":"venue"
},
  "geometry": {"coordinates":[-0.3784210086,39.4716796875],"type":"Point"}
}