{
  "type": "Feature",
  "properties": {
    "addr:full":"Calle de Plaza (de La), 1 Chumillas Cuenca 16131",
    "addr:housenumber":"1",
    "addr:postcode":"16131",
    "addr:street":"Calle De Plaza De La",
    "iso:country":"ES",
    "sg:address":"Calle de Plaza (de La), 1",
    "sg:city":"Chumillas",
    "sg:orig_category":"Ense\u00d1anza, Formaci\u00d3n Profesional: Aprendizaje",
    "sg:phone":"+34 969 20 32 61",
    "sg:postcode":"16131",
    "sg:province":"Cuenca",
    "wof:name":"Ayuntamiento",
    "wof:placetype":"venue"
},
  "geometry": {"coordinates":[-2.0320885181,39.7715187073],"type":"Point"}
}