{
  "type": "Feature",
  "properties": {
    "iso:country":"ES",
    "sg:address":"Avda Salvador Allende, 2",
    "sg:city":"Fortuna",
    "sg:orig_category":"Loter\u00cda Y T\u00d3mbola",
    "sg:phone":"+34 968 68 55 57",
    "sg:postcode":"30620",
    "sg:province":"Murcia",
    "wof:name":"Llinares Llinares Beatriz",
    "wof:placetype":"venue"
},
  "geometry": {"coordinates":[-1.1245609522,38.1781997681],"type":"Point"}
}