{
  "type": "Feature",
  "properties": {
    "iso:country":"ES",
    "sg:address":"Pl Jeroni Gelpi I Novell (de), 3",
    "sg:city":"Vilassar De Mar",
    "sg:orig_category":"Ense\u00d1anza: Profesiones Art\u00cdsticas",
    "sg:phone":"+34 937 50 22 02",
    "sg:postcode":"08340",
    "sg:province":"Barcelona",
    "wof:name":"Villier Ribas Jordi",
    "wof:placetype":"venue"
},
  "geometry": {"coordinates":[2.3907299042,41.5019264221],"type":"Point"}
}