{
  "type": "Feature",
  "properties": {
    "addr:full":"Calle de Huerta (la), 13 Alcorcon Madrid 28921",
    "addr:housenumber":"13",
    "addr:postcode":"28921",
    "addr:street":"Calle De Huerta La",
    "iso:country":"ES",
    "sg:address":"Calle de Huerta (la), 13",
    "sg:city":"Alcorcon",
    "sg:orig_category":"Pintura Y Barniz (al Por Menor)",
    "sg:phone":"+34 916 43 28 91",
    "sg:postcode":"28921",
    "sg:province":"Madrid",
    "wof:name":"E.r.p. Decoban S.l.",
    "wof:placetype":"venue"
},
  "geometry": {"coordinates":[-3.8251330853,40.3451652527],"type":"Point"}
}