{
  "type": "Feature",
  "properties": {
    "iso:country":"ES",
    "sg:address":"Calle de Pez Volador, 26",
    "sg:city":"Madrid",
    "sg:orig_category":"Inmobiliaria (agencias)",
    "sg:phone":"+34 914 09 57 47",
    "sg:postcode":"28007",
    "sg:province":"Madrid",
    "wof:name":"Goypaz S.l.",
    "wof:placetype":"venue"
},
  "geometry": {"coordinates":[-3.6671218872,40.4135437012],"type":"Point"}
}