{
  "type": "Feature",
  "properties": {
    "iso:country":"ES",
    "sg:address":"Calle de Pino (del), 12",
    "sg:city":"Arganda",
    "sg:orig_category":"Protecci\u00d3n De Madera",
    "sg:phone":"+34 918 75 70 39",
    "sg:postcode":"28500",
    "sg:province":"Madrid",
    "wof:name":"Tecmasa",
    "wof:placetype":"venue"
},
  "geometry": {"coordinates":[-3.4635772705,40.3138809204],"type":"Point"}
}