{
  "type": "Feature",
  "properties": {
    "iso:country":"ES",
    "sg:address":"Avda Portus Illicitanus, 15",
    "sg:city":"Santa Pola",
    "sg:orig_category":"Caf\u00c9s, Bares, Cervecer\u00cdas",
    "sg:phone":"+34 966 69 16 11",
    "sg:postcode":"03130",
    "sg:province":"Alicante",
    "wof:name":"Bonmati Luchoro Francisco Manuel",
    "wof:placetype":"venue"
},
  "geometry": {"coordinates":[-0.5616379976,38.1934242249],"type":"Point"}
}