{
  "type": "Feature",
  "properties": {
    "addr:full":"Rua Eugenio Carre, 2 Arteixo La Coru\u00f1a 15142",
    "addr:housenumber":"2",
    "addr:postcode":"15142",
    "addr:street":"Rua Eugenio Carre;La Corun\u0303A",
    "iso:country":"ES",
    "sg:address":"Rua Eugenio Carre, 2",
    "sg:city":"Arteixo",
    "sg:orig_category":"Quincaller\u00cda (al Por Menor)",
    "sg:phone":"+34 981 60 19 44",
    "sg:postcode":"15142",
    "sg:province":"La Coru\u00f1a",
    "wof:name":"Fontan Liste Luis David",
    "wof:placetype":"venue"
},
  "geometry": {"coordinates":[-8.5099601746,43.3034515381],"type":"Point"}
}