{
  "type": "Feature",
  "properties": {
    "addr:full":"Calle de Leon Y Castillo, 48 Palmas De Gran Canaria Las Palmas 35003",
    "addr:postcode":"35003",
    "addr:street":"Calle De Leon Y Castillo 48",
    "iso:country":"ES",
    "sg:address":"Calle de Leon Y Castillo, 48",
    "sg:city":"Palmas De Gran Canaria",
    "sg:orig_category":"Platos Preparados Refrigerados (fabricaci\u00d3n, Al Por Mayor)",
    "sg:phone":"+34 928 36 99 61",
    "sg:postcode":"35003",
    "sg:province":"Las Palmas",
    "wof:name":"Garcia Darias Enrique",
    "wof:placetype":"venue"
},
  "geometry": {"coordinates":[-15.4191761017,28.1115760803],"type":"Point"}
}