{
  "type": "Feature",
  "properties": {
    "addr:full":"Calle de Marianao, 53 Salto Del Negro Las Palmas 35016",
    "addr:housenumber":"53",
    "addr:postcode":"35016",
    "addr:street":"Calle De Marianao;Del Negro",
    "iso:country":"ES",
    "sg:address":"Calle de Marianao, 53",
    "sg:city":"Salto Del Negro",
    "sg:orig_category":"Agentes, Concesionarios Y Sucursales De Veh\u00cdculos",
    "sg:phone":"+34 928 32 30 55",
    "sg:postcode":"35016",
    "sg:province":"Las Palmas",
    "wof:name":"Jose Antonio Suarez Pe\u00f1ate S.l.",
    "wof:placetype":"venue"
},
  "geometry": {"coordinates":[-15.4298229218,28.0609531403],"type":"Point"}
}