{
  "type": "Feature",
  "properties": {
    "addr:full":"Calle de Segismundo Moret, 69 Malaga M\u00e1laga 29011",
    "addr:housenumber":"69",
    "addr:postcode":"29011",
    "addr:street":"Calle De Segismundo Moret;Ma\u0301Laga",
    "iso:country":"ES",
    "sg:address":"Calle de Segismundo Moret, 69",
    "sg:city":"Malaga",
    "sg:orig_category":"Comercio De Mobiliario De Oficina",
    "sg:phone":"+34 952 27 88 93",
    "sg:postcode":"29011",
    "sg:province":"M\u00e1laga",
    "wof:name":"Oficero S.l.",
    "wof:placetype":"venue"
},
  "geometry": {"coordinates":[-4.4391112328,36.7286911011],"type":"Point"}
}