{
  "type": "Feature",
  "properties": {
    "addr:full":"S Galvez Arce(s J De La Vega), S/n Beniajan Murcia 30570",
    "addr:housenumber":"s",
    "addr:postcode":"30570",
    "addr:street":"S Galvez Arce S J De La Vega;/ N",
    "iso:country":"ES",
    "sg:address":"S Galvez Arce(s J De La Vega), S/n",
    "sg:city":"Beniajan",
    "sg:orig_category":"Asociaciones, Organismos Culturales Y Socioeducativos",
    "sg:phone":"+34 968 82 10 32",
    "sg:postcode":"30570",
    "sg:province":"Murcia",
    "wof:name":"Centro De La Tercera Edad San Jose De La Vega",
    "wof:placetype":"venue"
},
  "geometry": {"coordinates":[-1.0715739727,37.9755134583],"type":"Point"}
}