{
  "type": "Feature",
  "properties": {
    "addr:full":"Ctra. Madrid(poligono), S/n Valdelafuente Le\u00f3n 24227",
    "addr:postcode":"24227",
    "addr:street":"Ctra. Madrid Poligono S / N Valdelafuente Leo\u0301N",
    "iso:country":"ES",
    "sg:address":"Ctra. Madrid(poligono), S/n",
    "sg:city":"Valdelafuente",
    "sg:orig_category":"Agentes, Concesionarios Y Sucursales De Veh\u00cdculos",
    "sg:phone":"+34 987 21 82 31",
    "sg:postcode":"24227",
    "sg:province":"Le\u00f3n",
    "sg:website":"www.alfaromeo.es",
    "wof:name":"Automoviles J.j. S.l.",
    "wof:placetype":"venue"
},
  "geometry": {"coordinates":[-5.5140891075,42.5692138672],"type":"Point"}
}