{
  "type": "Feature",
  "properties": {
    "iso:country":"ES",
    "sg:address":"Avda Cinca, 3",
    "sg:city":"Barbastro",
    "sg:orig_category":"Mercer\u00cda, Lencer\u00cda (al Por Menor)",
    "sg:phone":"+34 974 31 03 73",
    "sg:postcode":"22300",
    "sg:province":"Huesca",
    "wof:name":"Pena Playan Rosa",
    "wof:placetype":"venue"
},
  "geometry": {"coordinates":[0.1311099976,42.0341186523],"type":"Point"}
}