{
  "type": "Feature",
  "properties": {
    "addr:full":"Calle de Hilanderas, 2 Irun Guip\u00f9zcoa 20303",
    "addr:housenumber":"2",
    "addr:postcode":"20303",
    "addr:street":"Calle De Hilanderas;Guipu\u0300Zcoa",
    "iso:country":"ES",
    "sg:address":"Calle de Hilanderas, 2",
    "sg:city":"Irun",
    "sg:orig_category":"Art\u00cdculos De Madera (fabricaci\u00d3n Y Al Por Mayor)",
    "sg:phone":"+34 943 63 15 82",
    "sg:postcode":"20303",
    "sg:province":"Guip\u00f9zcoa",
    "wof:name":"Martinez Santabarbara Claudio",
    "wof:placetype":"venue"
},
  "geometry": {"coordinates":[-1.8040039539,43.3350067139],"type":"Point"}
}