{
  "type": "Feature",
  "properties": {
    "iso:country":"ES",
    "sg:address":"Avda Juan Carlos I, 72",
    "sg:city":"Sese\u00f1a",
    "sg:orig_category":"Promotores Constructores",
    "sg:phone":"+34 918 95 71 09",
    "sg:postcode":"45223",
    "sg:province":"Toledo",
    "wof:name":"Promociones Y Construcciones Ventascons S.l.",
    "wof:placetype":"venue"
},
  "geometry": {"coordinates":[-3.6866440773,40.1030235291],"type":"Point"}
}