{
  "type": "Feature",
  "properties": {
    "addr:full":"Calle de Cartagena De Indias, 8 Cartagena Murcia 30204",
    "addr:housenumber":"8",
    "addr:postcode":"30204",
    "addr:street":"Calle De Cartagena De Indias",
    "iso:country":"ES",
    "sg:address":"Calle de Cartagena De Indias, 8",
    "sg:city":"Cartagena",
    "sg:orig_category":"Dise\u00d1o Industrial",
    "sg:phone":"+34 968 50 25 05",
    "sg:postcode":"30204",
    "sg:province":"Murcia",
    "wof:name":"Garcia Garcia Manuel",
    "wof:placetype":"venue"
},
  "geometry": {"coordinates":[-0.9856047034,37.608341217],"type":"Point"}
}