{
  "type": "Feature",
  "properties": {
    "iso:country":"ES",
    "sg:address":"Calle de Ignacio Gomez Millan, S/n",
    "sg:city":"Sevilla",
    "sg:orig_category":"Asociaciones Y Clubs Deportivos",
    "sg:phone":"+34 954 33 88 08",
    "sg:postcode":"41010",
    "sg:province":"Sevilla",
    "sg:website":"www.galisport.com",
    "wof:name":"Galisur Sport S.l.",
    "wof:placetype":"venue"
},
  "geometry": {"coordinates":[-6.0083889961,37.3844642639],"type":"Point"}
}