{
  "type": "Feature",
  "properties": {
    "addr:full":"Avda Cardenal Herrera Oria, 427 Madrid Madrid 28035",
    "addr:housenumber":"427",
    "addr:postcode":"28035",
    "addr:street":"Avda Cardenal Herrera Oria",
    "iso:country":"ES",
    "sg:address":"Avda Cardenal Herrera Oria, 427",
    "sg:city":"Madrid",
    "sg:orig_category":"Acuicultura",
    "sg:phone":"+34 913 73 00 17",
    "sg:postcode":"28035",
    "sg:province":"Madrid",
    "wof:name":"Cang S. A.",
    "wof:placetype":"venue"
},
  "geometry": {"coordinates":[-3.7361590862,40.477180481],"type":"Point"}
}