{
  "type": "Feature",
  "properties": {
    "iso:country":"ES",
    "sg:address":"Avda Asturias, 39",
    "sg:city":"Vegadeo",
    "sg:orig_category":"Centros Empresariales",
    "sg:phone":"+34 985 47 60 24",
    "sg:postcode":"33770",
    "sg:province":"Asturias",
    "wof:name":"Mon Rodriguez Adela",
    "wof:placetype":"venue"
},
  "geometry": {"coordinates":[-7.0484790802,43.4647407532],"type":"Point"}
}