{
  "type": "Feature",
  "properties": {
    "iso:country":"ES",
    "sg:address":"Av Francesc Macia, 37",
    "sg:city":"Sabadell",
    "sg:classifiers":[
        {
            "category":"Cinema",
            "subcategory":"Movie Theater",
            "type":"Entertainment"
        }
    ],
    "sg:phone":"+34 937 23 99 75",
    "sg:postcode":"08206",
    "sg:province":"Barcelona",
    "sg:tags":[
        "salas",
        "de",
        "cine"
    ],
    "wof:name":"Multicinemes Eix Macia S.a.",
    "wof:placetype":"venue"
},
  "geometry": {"coordinates":[2.0972299576,41.5571098328],"type":"Point"}
}