{
  "type": "Feature",
  "properties": {
    "addr:full":"Avda Principe De Asturias, 94 Villaviciosa Odon Madrid 28670",
    "addr:housenumber":"94",
    "addr:postcode":"28670",
    "addr:street":"Avda Principe De Asturias;Odon",
    "iso:country":"ES",
    "sg:address":"Avda Principe De Asturias, 94",
    "sg:city":"Villaviciosa Odon",
    "sg:orig_category":"Sociedades, Compa\u00d1\u00cdas Aseguradoras",
    "sg:phone":"+34 916 65 75 33",
    "sg:postcode":"28670",
    "sg:province":"Madrid",
    "wof:name":"Acendro Asesores 2000 S.l.",
    "wof:placetype":"venue"
},
  "geometry": {"coordinates":[-3.9084341526,40.3597488403],"type":"Point"}
}