{
  "type": "Feature",
  "properties": {
    "iso:country":"ES",
    "sg:address":"Muelle La Galera-p I Pto Algecira, S/n",
    "sg:city":"Algeciras",
    "sg:orig_category":"Barcos",
    "sg:phone":"+34 956 63 17 08",
    "sg:postcode":"11201",
    "sg:province":"C\u00e1diz",
    "wof:name":"Sociedad Estatal De Estiba Y Desestiba S.a.",
    "wof:placetype":"venue"
},
  "geometry": {"coordinates":[-5.4526491165,36.1276016235],"type":"Point"}
}