{
  "type": "Feature",
  "properties": {
    "iso:country":"ES",
    "sg:address":"Calle de San Juan Bosco, 51",
    "sg:city":"Malaga",
    "sg:orig_category":"Reposter\u00cdas",
    "sg:phone":"+34 952 25 28 49",
    "sg:postcode":"29014",
    "sg:province":"M\u00e1laga",
    "wof:name":"Fabrica Y Distribucion De Pan Malaga S.l.",
    "wof:placetype":"venue"
},
  "geometry": {"coordinates":[-4.4224600792,36.7343597412],"type":"Point"}
}