{
  "type": "Feature",
  "properties": {
    "addr:full":"Ctra Nacional 340, S/n Cambrils Tarragona 43850",
    "addr:housenumber":"s / n",
    "addr:postcode":"43850",
    "addr:street":"Ctra Nacional 340",
    "iso:country":"ES",
    "sg:address":"Ctra Nacional 340, S/n",
    "sg:city":"Cambrils",
    "sg:orig_category":"Semiller\u00cdas",
    "sg:phone":"+34 977 36 19 79",
    "sg:postcode":"43850",
    "sg:province":"Tarragona",
    "wof:name":"Cort Ramon Pablo",
    "wof:placetype":"venue"
},
  "geometry": {"coordinates":[1.0611100197,41.0672683716],"type":"Point"}
}