{
  "type": "Feature",
  "properties": {
    "addr:full":"Calle de Armengual De La Mota, 30 Malaga M\u00e1laga 29007",
    "addr:housenumber":"30",
    "addr:postcode":"29007",
    "addr:street":"Calle De Armengual De La Mota;Ma\u0301Laga",
    "iso:country":"ES",
    "sg:address":"Calle de Armengual De La Mota, 30",
    "sg:city":"Malaga",
    "sg:orig_category":"Dietistas",
    "sg:phone":"+34 952 39 21 39",
    "sg:postcode":"29007",
    "sg:province":"M\u00e1laga",
    "sg:website":"www.naturhouse.com",
    "wof:name":"Kiluva Diet S.l.",
    "wof:placetype":"venue"
},
  "geometry": {"coordinates":[-4.4290919304,36.7207984924],"type":"Point"}
}