{
  "type": "Feature",
  "properties": {
    "addr:full":"Carrer de Arenys, 22 Barcelona Barcelona 08035",
    "addr:housenumber":"22",
    "addr:postcode":"08035",
    "addr:street":"Carrer De Arenys",
    "iso:country":"ES",
    "sg:address":"Carrer de Arenys, 22",
    "sg:city":"Barcelona",
    "sg:orig_category":"Cajas De Ahorro",
    "sg:phone":"+34 932 12 14 00",
    "sg:postcode":"08035",
    "sg:province":"Barcelona",
    "wof:name":"Caixa D'estalvis I Pensions De Barcelona",
    "wof:placetype":"venue"
},
  "geometry": {"coordinates":[2.1424019337,41.4218559265],"type":"Point"}
}