{
  "type": "Feature",
  "properties": {
    "addr:full":"Carr Salelles, 9 Gandia Valencia 46700",
    "addr:housenumber":"9",
    "addr:postcode":"46700",
    "addr:street":"Carr Salelles;Valencia",
    "iso:country":"ES",
    "sg:address":"Carr Salelles, 9",
    "sg:city":"Gandia",
    "sg:orig_category":"Restaurantes",
    "sg:phone":"+34 962 96 15 76",
    "sg:postcode":"46700",
    "sg:province":"Valencia",
    "wof:name":"Garcia Zaldivar Angel",
    "wof:placetype":"venue"
},
  "geometry": {"coordinates":[-0.1913339943,38.960735321],"type":"Point"}
}