{
  "type": "Feature",
  "properties": {
    "addr:full":"C/ Teatre, 18 Inca Islas Baleares 07300",
    "addr:housenumber":"18",
    "addr:postcode":"07300",
    "addr:street":"C / Teatre",
    "iso:country":"ES",
    "sg:address":"C/ Teatre, 18",
    "sg:city":"Inca",
    "sg:orig_category":"Electrodom\u00c9sticos (al Por Menor)",
    "sg:phone":"+34 971 50 08 85",
    "sg:postcode":"07300",
    "sg:province":"Islas Baleares",
    "wof:name":"Campins Fiol Jose",
    "wof:placetype":"venue"
},
  "geometry": {"coordinates":[2.9091639519,39.7228126526],"type":"Point"}
}