{
  "type": "Feature",
  "properties": {
    "addr:full":"Calle de Cinco De Junio, 33 Cari\u00f1ena Zaragoza 50400",
    "addr:housenumber":"33",
    "addr:postcode":"50400",
    "addr:street":"Calle De Cinco De Junio",
    "iso:country":"ES",
    "sg:address":"Calle de Cinco De Junio, 33",
    "sg:city":"Cari\u00f1ena",
    "sg:orig_category":"Promotores Constructores",
    "sg:phone":"+34 976 62 07 26",
    "sg:postcode":"50400",
    "sg:province":"Zaragoza",
    "wof:name":"Yus Gimeno Antonio",
    "wof:placetype":"venue"
},
  "geometry": {"coordinates":[-1.2239789963,41.3363418579],"type":"Point"}
}