{
  "type": "Feature",
  "properties": {
    "iso:country":"ES",
    "sg:address":"Calle de General Serrano, 37",
    "sg:city":"Santa Cruz De Mudela",
    "sg:orig_category":"Florister\u00cdas",
    "sg:phone":"+34 926 34 22 77",
    "sg:postcode":"13730",
    "sg:province":"Ciudad Real",
    "wof:name":"Dols Laguna Jose Antonio",
    "wof:placetype":"venue"
},
  "geometry": {"coordinates":[-3.4610669613,38.6385993958],"type":"Point"}
}