{
  "type": "Feature",
  "properties": {
    "addr:full":"Calle de Santo Domingo, 9 Jerez De La Frontera C\u00e1diz 11402",
    "addr:housenumber":"9",
    "addr:postcode":"11402",
    "addr:street":"Calle De Santo Domingo",
    "iso:country":"ES",
    "sg:address":"Calle de Santo Domingo, 9",
    "sg:city":"Jerez De La Frontera",
    "sg:orig_category":"Ense\u00d1anza, Formaci\u00d3n Profesional: Aprendizaje",
    "sg:phone":"+34 956 33 33 04",
    "sg:postcode":"11402",
    "sg:province":"C\u00e1diz",
    "wof:name":"Saje",
    "wof:placetype":"venue"
},
  "geometry": {"coordinates":[-6.1325941086,36.6906318665],"type":"Point"}
}