{
  "type": "Feature",
  "properties": {
    "iso:country":"ES",
    "sg:address":"Pase Maritimo Rey De Espa\u00d1a, 98",
    "sg:city":"Fuengirola",
    "sg:orig_category":"Molduras, Junquillos, Listones Y Molduras Perforadas",
    "sg:phone":"+34 952 66 07 10",
    "sg:postcode":"29640",
    "sg:province":"M\u00e1laga",
    "wof:name":"Sancendis  Michael",
    "wof:placetype":"venue"
},
  "geometry": {"coordinates":[-4.6183099747,36.5441894531],"type":"Point"}
}