{
  "type": "Feature",
  "properties": {
    "addr:full":"Avda Ris, 55 Noja Cantabria 39180",
    "addr:housenumber":"55",
    "addr:postcode":"39180",
    "addr:street":"Avda Ris",
    "iso:country":"ES",
    "sg:address":"Avda Ris, 55",
    "sg:city":"Noja",
    "sg:orig_category":"Molduras, Junquillos, Listones Y Molduras Perforadas",
    "sg:phone":"+34 942 63 08 85",
    "sg:postcode":"39180",
    "sg:province":"Cantabria",
    "wof:name":"Minguez Aguado Bego\u00f1a",
    "wof:placetype":"venue"
},
  "geometry": {"coordinates":[-3.5284039974,43.48046875],"type":"Point"}
}