{
  "type": "Feature",
  "properties": {
    "iso:country":"ES",
    "sg:address":"Calle de Santo (el), 7",
    "sg:city":"Villamartin",
    "sg:orig_category":"Centros Empresariales",
    "sg:phone":"+34 956 73 18 86",
    "sg:postcode":"11650",
    "sg:province":"C\u00e1diz",
    "wof:name":"Asociacion De Comerciantes De Villamartin",
    "wof:placetype":"venue"
},
  "geometry": {"coordinates":[-5.6423192024,36.8605728149],"type":"Point"}
}