{
  "type": "Feature",
  "properties": {
    "addr:full":"Calle de San Juan, S/n Huetor-tajar Granada 18360",
    "addr:housenumber":"s / n",
    "addr:postcode":"18360",
    "addr:street":"Calle De San Juan",
    "iso:country":"ES",
    "sg:address":"Calle de San Juan, S/n",
    "sg:city":"Huetor-tajar",
    "sg:orig_category":"Centros De Educaci\u00d3n Especial",
    "sg:phone":"+34 958 33 30 50",
    "sg:postcode":"18360",
    "sg:province":"Granada",
    "wof:name":"Junta De Andalucia",
    "wof:placetype":"venue"
},
  "geometry": {"coordinates":[-4.0458340645,37.1987190247],"type":"Point"}
}