{
  "type": "Feature",
  "properties": {
    "addr:full":"Calle de Parroco Antonio Pardo, 22 Santa Cruz De Mudela Ciudad Real 13730",
    "addr:housenumber":"22",
    "addr:postcode":"13730",
    "addr:street":"Calle De Parroco Antonio Pardo",
    "iso:country":"ES",
    "sg:address":"Calle de Parroco Antonio Pardo, 22",
    "sg:city":"Santa Cruz De Mudela",
    "sg:orig_category":"Aparatos De Iluminaci\u00d3n (al Por Menor)",
    "sg:phone":"+34 926 34 21 26",
    "sg:postcode":"13730",
    "sg:province":"Ciudad Real",
    "wof:name":"Electrotecnia Rodero S.l.",
    "wof:placetype":"venue"
},
  "geometry": {"coordinates":[-3.4601259232,38.6394500732],"type":"Point"}
}