{
  "type": "Feature",
  "properties": {
    "addr:full":"Cra. S. Antoni Vilamajor, 58 Llinars Valles Barcelona 08450",
    "addr:housenumber":"58",
    "addr:postcode":"08450",
    "addr:street":"Cra. S. Antoni Vilamajor;Valles Barcelona",
    "iso:country":"ES",
    "sg:address":"Cra. S. Antoni Vilamajor, 58",
    "sg:city":"Llinars Valles",
    "sg:orig_category":"Venta, Colocaci\u00d3n, Reparaci\u00d3n De Parabrisas, Techos Descapotables",
    "sg:phone":"+34 938 41 27 41",
    "sg:postcode":"08450",
    "sg:province":"Barcelona",
    "wof:name":"Tarrats Perez Alberto",
    "wof:placetype":"venue"
},
  "geometry": {"coordinates":[2.4019749165,41.6397705078],"type":"Point"}
}