{
  "type": "Feature",
  "properties": {
    "addr:full":"Pg Camp Del Roure, 52 Terrassa Barcelona 08227",
    "addr:housenumber":"52",
    "addr:postcode":"08227",
    "addr:street":"Pg;Roure",
    "iso:country":"ES",
    "sg:address":"Pg Camp Del Roure, 52",
    "sg:city":"Terrassa",
    "sg:orig_category":"Asesor\u00cda Fiscal Y Jur\u00cddica",
    "sg:phone":"+34 937 30 80 03",
    "sg:postcode":"08227",
    "sg:province":"Barcelona",
    "wof:name":"La Gripia Assessores S.l.",
    "wof:placetype":"venue"
},
  "geometry": {"coordinates":[2.0395200253,41.5697517395],"type":"Point"}
}