{
  "type": "Feature",
  "properties": {
    "iso:country":"ES",
    "sg:address":"Velazquez, 126",
    "sg:city":"Madrid",
    "sg:orig_category":"Asistencia Domiciliaria",
    "sg:phone":"+34 915 61 57 40",
    "sg:postcode":"28006",
    "sg:province":"Madrid",
    "wof:name":"Servicios De Teleasistencia S.a.",
    "wof:placetype":"venue"
},
  "geometry": {"coordinates":[-3.6828670502,40.4373016357],"type":"Point"}
}