{
  "type": "Feature",
  "properties": {
    "addr:full":"Carrer de Balmes, 236 Barcelona Barcelona 08006",
    "addr:housenumber":"236",
    "addr:postcode":"08006",
    "addr:street":"Carrer De Balmes",
    "iso:country":"ES",
    "sg:address":"Carrer de Balmes, 236",
    "sg:city":"Barcelona",
    "sg:orig_category":"Transportes Mar\u00cdtimos",
    "sg:phone":"+34 932 17 15 10",
    "sg:postcode":"08006",
    "sg:province":"Barcelona",
    "wof:name":"Apl Liner Agencies Espa\u00f1a S.l.",
    "wof:placetype":"venue"
},
  "geometry": {"coordinates":[2.1506061554,41.399143219],"type":"Point"}
}