{
  "type": "Feature",
  "properties": {
    "addr:full":"Calle de Candasnos De, 15 Fraga Huesca 22520",
    "addr:housenumber":"15",
    "addr:postcode":"22520",
    "addr:street":"Calle De Candasnos De",
    "iso:country":"ES",
    "sg:address":"Calle de Candasnos De, 15",
    "sg:city":"Fraga",
    "sg:orig_category":"Promotores Constructores",
    "sg:phone":"+34 974 47 35 76",
    "sg:postcode":"22520",
    "sg:province":"Huesca",
    "wof:name":"Subcomunidad De Propietarios Escalera Ii",
    "wof:placetype":"venue"
},
  "geometry": {"coordinates":[0.3405410945,41.5224266052],"type":"Point"}
}