{
  "type": "Feature",
  "properties": {
    "addr:full":"Calle de Almazara, 1 Santomera Murcia 30140",
    "addr:housenumber":"1",
    "addr:postcode":"30140",
    "addr:street":"Calle De Almazara",
    "iso:country":"ES",
    "sg:address":"Calle de Almazara, 1",
    "sg:city":"Santomera",
    "sg:orig_category":"Carnicer\u00cdas, Carnicer\u00cdas",
    "sg:phone":"+34 968 86 51 16",
    "sg:postcode":"30140",
    "sg:province":"Murcia",
    "wof:name":"Serrano Andugar Pio",
    "wof:placetype":"venue"
},
  "geometry": {"coordinates":[-1.0471260548,38.0629959106],"type":"Point"}
}