{
  "type": "Feature",
  "properties": {
    "iso:country":"ES",
    "sg:address":"Calle de Fuencarral, 105",
    "sg:city":"Madrid",
    "sg:orig_category":"M\u00c1quinas De Escribir, M\u00c1quinas De Oficina (al Por Menor, Reparaci\u00d3n)",
    "sg:phone":"+34 914 48 94 41",
    "sg:postcode":"28004",
    "sg:province":"Madrid",
    "wof:name":"Rodriguez Mojon Jose Maria",
    "wof:placetype":"venue"
},
  "geometry": {"coordinates":[-3.7023060322,40.4283638],"type":"Point"}
}