{
  "type": "Feature",
  "properties": {
    "addr:full":"Avda Montes De Oca (de Los), 19 San Sebastian De Los Reyes Madrid 28700",
    "addr:housenumber":"19",
    "addr:postcode":"28700",
    "addr:street":"Avda Montes De Oca De Los",
    "iso:country":"ES",
    "sg:address":"Avda Montes De Oca (de Los), 19",
    "sg:city":"San Sebastian De Los Reyes",
    "sg:orig_category":"Acero: Productos Sider\u00dargicos Y Transformados (fabricaci\u00d3n, Negocio)",
    "sg:phone":"+34 916 59 02 06",
    "sg:postcode":"28700",
    "sg:province":"Madrid",
    "wof:name":"Glual Madrid S.l.",
    "wof:placetype":"venue"
},
  "geometry": {"coordinates":[-3.6112220287,40.5518684387],"type":"Point"}
}