{
  "type": "Feature",
  "properties": {
    "addr:full":"Carrer de Rafael De Casanova, 52 Sant Vicen\u00c7 Dels Horts Barcelona 08620",
    "addr:housenumber":"52",
    "addr:postcode":"08620",
    "addr:street":"Carrer De Rafael De Casanova",
    "iso:country":"ES",
    "sg:address":"Carrer de Rafael De Casanova, 52",
    "sg:city":"Sant Vicen\u00c7 Dels Horts",
    "sg:orig_category":"Peluquer\u00cdas, Peluquer\u00cda Mixta",
    "sg:phone":"+34 936 56 23 62",
    "sg:postcode":"08620",
    "sg:province":"Barcelona",
    "wof:name":"Valls Riu Jose Maria",
    "wof:placetype":"venue"
},
  "geometry": {"coordinates":[2.0100059509,41.3928833008],"type":"Point"}
}