{
  "type": "Feature",
  "properties": {
    "addr:full":"Calle de Jacinto Benavente, 12 Jamilena Ja\u00e9n 23658",
    "addr:housenumber":"12",
    "addr:postcode":"23658",
    "addr:street":"Calle De Jacinto Benavente",
    "iso:country":"ES",
    "sg:address":"Calle de Jacinto Benavente, 12",
    "sg:city":"Jamilena",
    "sg:orig_category":"Carnicer\u00cdas, Carnicer\u00cdas",
    "sg:phone":"+34 953 56 63 39",
    "sg:postcode":"23658",
    "sg:province":"Ja\u00e9n",
    "wof:name":"Barranco Perez Maria Dolores",
    "wof:placetype":"venue"
},
  "geometry": {"coordinates":[-3.9109370708,37.7491073608],"type":"Point"}
}