{
  "type": "Feature",
  "properties": {
    "iso:country":"ES",
    "sg:address":"Carrer de Casanova, 63",
    "sg:city":"Barcelona",
    "sg:orig_category":"Institutos De Belleza",
    "sg:phone":"+34 934 51 50 65",
    "sg:postcode":"08011",
    "sg:province":"Barcelona",
    "wof:name":"Seemsa",
    "wof:placetype":"venue"
},
  "geometry": {"coordinates":[2.1588289738,41.385181427],"type":"Point"}
}