{
  "type": "Feature",
  "properties": {
    "iso:country":"ES",
    "sg:address":"Carrer de Antoni De Capmany, 10",
    "sg:city":"Mataro",
    "sg:orig_category":"Mec\u00c1nico Del Autom\u00d3vil",
    "sg:phone":"+34 937 96 02 49",
    "sg:postcode":"08301",
    "sg:province":"Barcelona",
    "wof:name":"Camps Rovira Miquel",
    "wof:placetype":"venue"
},
  "geometry": {"coordinates":[2.4509489536,41.5415649414],"type":"Point"}
}