{
  "type": "Feature",
  "properties": {
    "iso:country":"ES",
    "sg:address":"Camino Viejo Simancas, S/n",
    "sg:city":"Valladolid",
    "sg:orig_category":"Ense\u00d1anza, Formaci\u00d3n Profesional: Aprendizaje",
    "sg:phone":"+34 983 23 55 06",
    "sg:postcode":"47008",
    "sg:province":"Valladolid",
    "wof:name":"Colegio Mayor Menendez Pelayo",
    "wof:placetype":"venue"
},
  "geometry": {"coordinates":[-4.7458910942,41.6271781921],"type":"Point"}
}