{
  "type": "Feature",
  "properties": {
    "iso:country":"ES",
    "sg:address":"Rua Voltafolgueiras, S/n",
    "sg:city":"Becerrea",
    "sg:orig_category":"Lavado, Limpieza De Veh\u00cdculos",
    "sg:phone":"+34 982 36 08 10",
    "sg:postcode":"27640",
    "sg:province":"Lugo",
    "wof:name":"Lage Lage Alberto Luis",
    "wof:placetype":"venue"
},
  "geometry": {"coordinates":[-7.1622071266,42.8534240723],"type":"Point"}
}