{
  "type": "Feature",
  "properties": {
    "addr:full":"Calle de Santa Isabel, 23 Alcazares Murcia 30710",
    "addr:housenumber":"23",
    "addr:postcode":"30710",
    "addr:street":"Calle De Santa Isabel",
    "iso:country":"ES",
    "sg:address":"Calle de Santa Isabel, 23",
    "sg:city":"Alcazares",
    "sg:orig_category":"Reciclaje Y Tratamiento De Desechos Varios",
    "sg:phone":"+34 968 17 02 32",
    "sg:postcode":"30710",
    "sg:province":"Murcia",
    "wof:name":"Urbaser S.a.",
    "wof:placetype":"venue"
},
  "geometry": {"coordinates":[-0.8504719734,37.7390594482],"type":"Point"}
}