{
  "type": "Feature",
  "properties": {
    "addr:full":"Avda Ricardo Soriano, 13 Marbella M\u00e1laga 29600",
    "addr:housenumber":"13",
    "addr:postcode":"29600",
    "addr:street":"Avda Ricardo Soriano;Ma\u0301Laga",
    "iso:country":"ES",
    "sg:address":"Avda Ricardo Soriano, 13",
    "sg:city":"Marbella",
    "sg:orig_category":"Doctores En Medicina",
    "sg:phone":"+34 952 77 13 38",
    "sg:postcode":"29600",
    "sg:province":"M\u00e1laga",
    "wof:name":"Ignalejor S.l.",
    "wof:placetype":"venue"
},
  "geometry": {"coordinates":[-4.8884139061,36.5098190308],"type":"Point"}
}