{
  "type": "Feature",
  "properties": {
    "addr:full":"Calle de General Aguilera, 2 Ciudad Real Ciudad Real 13001",
    "addr:housenumber":"2",
    "addr:postcode":"13001",
    "addr:street":"Calle De General Aguilera",
    "iso:country":"ES",
    "sg:address":"Calle de General Aguilera, 2",
    "sg:city":"Ciudad Real",
    "sg:orig_category":"Centros De Coordinaci\u00d3n",
    "sg:phone":"+34 926 21 75 11",
    "sg:postcode":"13001",
    "sg:province":"Ciudad Real",
    "wof:name":"Pons Consutores Registrales S.a.",
    "wof:placetype":"venue"
},
  "geometry": {"coordinates":[-3.9282824993,38.9846115112],"type":"Point"}
}