{
  "type": "Feature",
  "properties": {
    "addr:full":"Calle de Gran Via, 51 Hellin Albacete 02400",
    "addr:housenumber":"51",
    "addr:postcode":"02400",
    "addr:street":"Calle De Gran Via",
    "iso:country":"ES",
    "sg:address":"Calle de Gran Via, 51",
    "sg:city":"Hellin",
    "sg:orig_category":"Centros De Educaci\u00d3n Especial",
    "sg:phone":"+34 967 30 77 80",
    "sg:postcode":"02400",
    "sg:province":"Albacete",
    "wof:name":"Colegio Publico Nuestra Se\u00f1ora Del Rosario",
    "wof:placetype":"venue"
},
  "geometry": {"coordinates":[-1.6935590506,38.5087203979],"type":"Point"}
}