{
  "type": "Feature",
  "properties": {
    "iso:country":"ES",
    "sg:address":"Plaz Mayor, S/n",
    "sg:city":"Bonillo",
    "sg:classifiers":[
        {
            "category":"Casinos & Gambling",
            "type":"Entertainment"
        }
    ],
    "sg:phone":"+34 967 37 00 03",
    "sg:postcode":"02610",
    "sg:province":"Albacete",
    "sg:tags":[
        "locale",
        "de",
        "juego"
    ],
    "wof:name":"Sociedad De Cazadores",
    "wof:placetype":"venue"
},
  "geometry": {"coordinates":[-2.5415890217,38.9515419006],"type":"Point"}
}