{
  "type": "Feature",
  "properties": {
    "iso:country":"ES",
    "sg:address":"Rbla Mestre Torrents, 74",
    "sg:city":"Roca Valles",
    "sg:orig_category":"Electricidad: Instaladores",
    "sg:phone":"+34 938 42 45 33",
    "sg:postcode":"08430",
    "sg:province":"Barcelona",
    "wof:name":"Instal-servi Godayol S.l.",
    "wof:placetype":"venue"
},
  "geometry": {"coordinates":[2.3249890804,41.5864028931],"type":"Point"}
}