{
  "type": "Feature",
  "properties": {
    "addr:full":"Calle de Espolon, 12 Mojados Valladolid 47250",
    "addr:housenumber":"12",
    "addr:postcode":"47250",
    "addr:street":"Calle De Espolon",
    "iso:country":"ES",
    "sg:address":"Calle de Espolon, 12",
    "sg:city":"Mojados",
    "sg:orig_category":"Arreglo, Instalaci\u00d3n Y Acondicionamiento De Talleres",
    "sg:phone":"+34 983 60 76 69",
    "sg:postcode":"47250",
    "sg:province":"Valladolid",
    "wof:name":"Ayuntamiento De Mojados",
    "wof:placetype":"venue"
},
  "geometry": {"coordinates":[-4.6632561684,41.4336547852],"type":"Point"}
}