{
  "type": "Feature",
  "properties": {
    "iso:country":"ES",
    "sg:address":"Carr Castanyet, 103",
    "sg:city":"Santa Coloma De Farners",
    "sg:orig_category":"Prendas Y Chalecos De Punto (al Por Menor)",
    "sg:phone":"+34 972 84 04 48",
    "sg:postcode":"17430",
    "sg:province":"Girona",
    "wof:name":"Llobet Font Maria",
    "wof:placetype":"venue"
},
  "geometry": {"coordinates":[2.6569681168,41.8669929504],"type":"Point"}
}