{
  "type": "Feature",
  "properties": {
    "addr:full":"Rua Santa Maria, 30 Viana Navarra 31230",
    "addr:housenumber":"30",
    "addr:postcode":"31230",
    "addr:street":"Rua Santa Maria",
    "iso:country":"ES",
    "sg:address":"Rua Santa Maria, 30",
    "sg:city":"Viana",
    "sg:orig_category":"Cl\u00cdnicas Dentales",
    "sg:phone":"+34 948 64 56 93",
    "sg:postcode":"31230",
    "sg:province":"Navarra",
    "wof:name":"Hoursouripe Zalaberry Martin",
    "wof:placetype":"venue"
},
  "geometry": {"coordinates":[-2.3724679947,42.5140380859],"type":"Point"}
}