{
  "type": "Feature",
  "properties": {
    "addr:full":"Avda Mairena, 2 San Juan De Aznalfarache Sevilla 41920",
    "addr:housenumber":"2",
    "addr:postcode":"41920",
    "addr:street":"Avda Mairena",
    "iso:country":"ES",
    "sg:address":"Avda Mairena, 2",
    "sg:city":"San Juan De Aznalfarache",
    "sg:orig_category":"Sociedades, Compa\u00d1\u00cdas Aseguradoras",
    "sg:phone":"+34 954 76 11 22",
    "sg:postcode":"41920",
    "sg:province":"Sevilla",
    "wof:name":"Ulgar Y Moreno Correduria De Seguros S.l.",
    "wof:placetype":"venue"
},
  "geometry": {"coordinates":[-6.0378441811,37.3574256897],"type":"Point"}
}