{
  "type": "Feature",
  "properties": {
    "iso:country":"ES",
    "sg:address":"Calle de Juan Ramon Jimenez, S/n",
    "sg:city":"Palmas De Gran Canaria",
    "sg:orig_category":"Complementos De Vestir (al Por Menor)",
    "sg:phone":"+34 928 20 47 65",
    "sg:postcode":"35011",
    "sg:province":"Las Palmas",
    "wof:name":"Melian Hernandez Santiago",
    "wof:placetype":"venue"
},
  "geometry": {"coordinates":[-15.4355449677,28.1151542664],"type":"Point"}
}