{
  "type": "Feature",
  "properties": {
    "addr:full":"Calle de Fuencarral, 15 Madrid Madrid 28004",
    "addr:housenumber":"15",
    "addr:postcode":"madrid;28004",
    "addr:street":"Calle De Fuencarral",
    "iso:country":"ES",
    "sg:address":"Calle de Fuencarral, 15",
    "sg:city":"Madrid",
    "sg:orig_category":"Fabricaci\u00d3n De Bolsos Y Bolsos De Tela",
    "sg:phone":"+34 915 23 13 00",
    "sg:postcode":"28004",
    "sg:province":"Madrid",
    "sg:website":"www.blancoint.com",
    "wof:name":"Vagtex S. L.",
    "wof:placetype":"venue"
},
  "geometry": {"coordinates":[-3.7014770508,40.4209289551],"type":"Point"}
}