{
  "type": "Feature",
  "properties": {
    "addr:full":"Carrer de Esglesia, 3 Calafell Tarragona 43820",
    "addr:housenumber":"3",
    "addr:postcode":"43820",
    "addr:street":"Carrer De Esglesia",
    "iso:country":"ES",
    "sg:address":"Carrer de Esglesia, 3",
    "sg:city":"Calafell",
    "sg:orig_category":"Aguas (distribuci\u00d3n, Servicios)",
    "sg:phone":"+34 977 69 49 55",
    "sg:postcode":"43820",
    "sg:province":"Tarragona",
    "sg:website":"www.sorea/calafell.es",
    "wof:name":"Sorea S.a.",
    "wof:placetype":"venue"
},
  "geometry": {"coordinates":[1.5689189434,41.2015190125],"type":"Point"}
}