{
  "type": "Feature",
  "properties": {
    "iso:country":"ES",
    "sg:address":"Calle de Escuelas Pias, 2",
    "sg:city":"Logro\u00f1o",
    "sg:orig_category":"Electricidad: Instaladores",
    "sg:phone":"+34 941 26 05 68",
    "sg:postcode":"26004",
    "sg:province":"La Rioja",
    "wof:name":"Ortiz Alonso Antonio",
    "wof:placetype":"venue"
},
  "geometry": {"coordinates":[-2.4373850822,42.4659309387],"type":"Point"}
}