{
  "type": "Feature",
  "properties": {
    "iso:country":"ES",
    "sg:address":"Carrer de Proven\u00c7a, 4",
    "sg:city":"Sant Sadurni D'anoia",
    "sg:orig_category":"Armas Y Municiones (fabricaci\u00d3n, Al Por Mayor)",
    "sg:phone":"+34 938 91 06 53",
    "sg:postcode":"08770",
    "sg:province":"Barcelona",
    "wof:name":"Sanchez Gallardo Antonio",
    "wof:placetype":"venue"
},
  "geometry": {"coordinates":[1.6083999872,41.6151885986],"type":"Point"}
}