{
  "type": "Feature",
  "properties": {
    "addr:full":"Calle de Enrique Mari\u00d1as Romero Periodista, 2 Coru\u00d1a La Coru\u00f1a 15009",
    "addr:housenumber":"2",
    "addr:postcode":"15009",
    "addr:street":"Calle De Enrique Marin\u0303As Romero Periodista;La Corun\u0303A",
    "iso:country":"ES",
    "sg:address":"Calle de Enrique Mari\u00d1as Romero Periodista, 2",
    "sg:city":"Coru\u00d1a",
    "sg:orig_category":"Arquitectos",
    "sg:phone":"+34 981 13 72 65",
    "sg:postcode":"15009",
    "sg:province":"La Coru\u00f1a",
    "wof:name":"Rico Ortega Agustin",
    "wof:placetype":"venue"
},
  "geometry": {"coordinates":[-8.4042072296,43.3402061462],"type":"Point"}
}