{
  "type": "Feature",
  "properties": {
    "iso:country":"ES",
    "sg:address":"Avda Abrantes, 45",
    "sg:city":"Madrid",
    "sg:orig_category":"Sindicatos Y Colegios Profesionales",
    "sg:phone":"+34 915 65 14 68",
    "sg:postcode":"28025",
    "sg:province":"Madrid",
    "wof:name":"Asociacion De Educadores Las Alamedillas",
    "wof:placetype":"venue"
},
  "geometry": {"coordinates":[-3.7264409065,40.380771637],"type":"Point"}
}