{
  "type": "Feature",
  "properties": {
    "addr:full":"Cust Molinos, 7 Granada Granada 18008",
    "addr:housenumber":"7",
    "addr:postcode":"18008",
    "iso:country":"ES",
    "sg:address":"Cust Molinos, 7",
    "sg:city":"Granada",
    "sg:orig_category":"Empresarios Y Productoras De Espect\u00c1culos",
    "sg:phone":"+34 958 22 70 66",
    "sg:postcode":"18008",
    "sg:province":"Granada",
    "wof:name":"Pascual Garrido Jose Antonio",
    "wof:placetype":"venue"
},
  "geometry": {"coordinates":[-3.5886380672,37.1684265137],"type":"Point"}
}