{
  "type": "Feature",
  "properties": {
    "addr:full":"Calle de Redolins, 47 Palmar Valencia 46012",
    "addr:housenumber":"47",
    "addr:postcode":"46012",
    "addr:street":"Calle De Redolins",
    "iso:country":"ES",
    "sg:address":"Calle de Redolins, 47",
    "sg:city":"Palmar",
    "sg:orig_category":"Asesor\u00cda Fiscal Y Jur\u00cddica",
    "sg:phone":"+34 961 62 02 11",
    "sg:postcode":"46012",
    "sg:province":"Valencia",
    "wof:name":"Asebasvi S.l.",
    "wof:placetype":"venue"
},
  "geometry": {"coordinates":[-0.3181720972,39.307975769],"type":"Point"}
}