{
  "type": "Feature",
  "properties": {
    "iso:country":"ES",
    "sg:address":"Calle de Marti, 16",
    "sg:city":"Aguilas",
    "sg:orig_category":"Plomeros",
    "sg:phone":"+34 968 49 32 24",
    "sg:postcode":"30880",
    "sg:province":"Murcia",
    "wof:name":"Ramirez Robles Alfonso",
    "wof:placetype":"venue"
},
  "geometry": {"coordinates":[-1.5823819637,37.4077568054],"type":"Point"}
}