{
  "type": "Feature",
  "properties": {
    "iso:country":"ES",
    "sg:address":"Ctra Barcelona, 444",
    "sg:city":"Sabadell",
    "sg:orig_category":"Zapatos (al Por Menor)",
    "sg:phone":"+34 937 12 41 36",
    "sg:postcode":"08203",
    "sg:province":"Barcelona",
    "wof:name":"Shoes Gestion S.a.",
    "wof:placetype":"venue"
},
  "geometry": {"coordinates":[2.1141579151,41.5318603516],"type":"Point"}
}