{
  "type": "Feature",
  "properties": {
    "iso:country":"ES",
    "sg:address":"Plaz Vicente Iborra, 6",
    "sg:city":"Valencia",
    "sg:orig_category":"Centros Comerciales Y Grandes Tiendas",
    "sg:phone":"+34 963 91 15 97",
    "sg:postcode":"46003",
    "sg:province":"Valencia",
    "wof:name":"Deposito Dental Dentival S.l.",
    "wof:placetype":"venue"
},
  "geometry": {"coordinates":[-0.3815419972,39.4770698547],"type":"Point"}
}