{
  "type": "Feature",
  "properties": {
    "iso:country":"ES",
    "sg:address":"Ctra Almaden A Posadas (de), Km. 0017,0",
    "sg:city":"Villaviciosa Cordoba",
    "sg:orig_category":"Reciclaje, Tratamiento De Pl\u00c1sticos",
    "sg:phone":"+34 957 72 20 82",
    "sg:postcode":"14300",
    "sg:province":"C\u00f3rdoba",
    "wof:name":"Empresa De Gestion Medio Ambiental S.a.",
    "wof:placetype":"venue"
},
  "geometry": {"coordinates":[-5.0143089294,38.0761260986],"type":"Point"}
}