{
  "type": "Feature",
  "properties": {
    "iso:country":"ES",
    "sg:address":"Pol. Industrial, 2",
    "sg:city":"Jodar",
    "sg:orig_category":"Bares, Piano",
    "sg:phone":"+34 953 78 52 13",
    "sg:postcode":"23500",
    "sg:province":"Ja\u00e9n",
    "wof:name":"Vilches Lopez Rafael",
    "wof:placetype":"venue"
},
  "geometry": {"coordinates":[-3.3526489735,37.8448600769],"type":"Point"}
}