{
  "type": "Feature",
  "properties": {
    "iso:country":"ES",
    "sg:address":"Calle de Isla Amboto, 12",
    "sg:city":"Puerto",
    "sg:orig_category":"Promotores Constructores",
    "sg:phone":"+34 962 67 94 34",
    "sg:postcode":"46520",
    "sg:province":"Valencia",
    "wof:name":"Construcciones Codigama S.l.",
    "wof:placetype":"venue"
},
  "geometry": {"coordinates":[-0.2102800012,39.6642570496],"type":"Point"}
}