{
  "type": "Feature",
  "properties": {
    "addr:full":"Moll, 13 Sta. Pola Alicante 03130",
    "addr:housenumber":"13",
    "addr:postcode":"03130",
    "addr:street":"Moll;Pola",
    "iso:country":"ES",
    "sg:address":"Moll, 13",
    "sg:city":"Sta. Pola",
    "sg:orig_category":"Ropa Para Se\u00d1oras Y Caballeros (al Por Menor)",
    "sg:phone":"+34 965 41 62 39",
    "sg:postcode":"03130",
    "sg:province":"Alicante",
    "wof:name":"Laureano Bru Bolmati C.b",
    "wof:placetype":"venue"
},
  "geometry": {"coordinates":[-0.5565090179,38.190448761],"type":"Point"}
}