{
  "type": "Feature",
  "properties": {
    "iso:country":"ES",
    "sg:address":"Carr Polop, 18",
    "sg:city":"Vila Joiosa",
    "sg:orig_category":"Institutos De Belleza",
    "sg:phone":"+34 966 85 13 32",
    "sg:postcode":"03570",
    "sg:province":"Alicante",
    "wof:name":"Gallego Herreiz Virtudes",
    "wof:placetype":"venue"
},
  "geometry": {"coordinates":[-0.2327190042,38.505821228],"type":"Point"}
}