{
  "type": "Feature",
  "properties": {
    "iso:country":"ES",
    "sg:address":"Calle de Real, 13",
    "sg:city":"Langa Duero",
    "sg:orig_category":"Molduras, Junquillos, Listones Y Molduras Perforadas",
    "sg:phone":"+34 975 35 31 96",
    "sg:postcode":"42320",
    "sg:province":"Soria",
    "wof:name":"Berlanga Leon Cesar",
    "wof:placetype":"venue"
},
  "geometry": {"coordinates":[-3.4015591145,41.6100692749],"type":"Point"}
}