{
  "type": "Feature",
  "properties": {
    "addr:full":"Plaz Napoles Y Sicilia, 5 Valencia Valencia 46...",
    "addr:housenumber":"5",
    "addr:street":"Sicilia;Valencia",
    "iso:country":"ES",
    "sg:address":"Plaz Napoles Y Sicilia, 5",
    "sg:city":"Valencia",
    "sg:orig_category":"Sindicatos De Trabajadores",
    "sg:phone":"+34 963 88 21 00",
    "sg:postcode":"46...",
    "sg:province":"Valencia",
    "wof:name":"Comissions Obreres Del Pais Valencia",
    "wof:placetype":"venue"
},
  "geometry": {"coordinates":[-0.3727299869,39.4758834839],"type":"Point"}
}