{
  "type": "Feature",
  "properties": {
    "iso:country":"ES",
    "sg:address":"Calle de Angulema, 12",
    "sg:city":"Vitoria-gasteiz",
    "sg:orig_category":"Grafistas",
    "sg:phone":"+34 945 27 40 49",
    "sg:postcode":"01004",
    "sg:province":"\u00c1lava",
    "wof:name":"Barrasa Alonso Maria Angeles",
    "wof:placetype":"venue"
},
  "geometry": {"coordinates":[-2.6666491032,42.8424797058],"type":"Point"}
}