{
  "type": "Feature",
  "properties": {
    "addr:full":"Calle de Corredera, S/n Arroyomolinos C\u00e1ceres 10161",
    "addr:housenumber":"s / n",
    "addr:postcode":"10161",
    "addr:street":"Calle De Corredera",
    "iso:country":"ES",
    "sg:address":"Calle de Corredera, S/n",
    "sg:city":"Arroyomolinos",
    "sg:orig_category":"Asociaciones, Organismos Culturales Y Socioeducativos",
    "sg:phone":"+34 927 38 51 83",
    "sg:postcode":"10161",
    "sg:province":"C\u00e1ceres",
    "wof:name":"Ayuntamiento De Arroyomolinos De Montanez",
    "wof:placetype":"venue"
},
  "geometry": {"coordinates":[-6.1613202095,39.1828994751],"type":"Point"}
}