{
  "type": "Feature",
  "properties": {
    "addr:full":"Rua Cami\u00d1o Real (do), 13 Lugo Lugo 27004",
    "addr:postcode":"27004",
    "addr:street":"Rua Camin\u0303O",
    "iso:country":"ES",
    "sg:address":"Rua Cami\u00d1o Real (do), 13",
    "sg:city":"Lugo",
    "sg:orig_category":"Talleres De Corte Y Confecci\u00d3n",
    "sg:phone":"+34 982 25 53 77",
    "sg:postcode":"27004",
    "sg:province":"Lugo",
    "wof:name":"Rivera Rodriguez Isabel",
    "wof:placetype":"venue"
},
  "geometry": {"coordinates":[-7.5608811378,43.0146331787],"type":"Point"}
}