{
  "type": "Feature",
  "properties": {
    "iso:country":"ES",
    "sg:address":"Barrio Contranquil, S/n",
    "sg:city":"Cangas Onis",
    "sg:orig_category":"Restaurantes",
    "sg:phone":"+34 985 84 94 45",
    "sg:postcode":"33550",
    "sg:province":"Asturias",
    "wof:name":"Etxyzarretinez Hosteleria S.l.l.",
    "wof:placetype":"venue"
},
  "geometry": {"coordinates":[-5.1302790642,43.3507957458],"type":"Point"}
}