{
  "type": "Feature",
  "properties": {
    "addr:full":"Plaz Euskadi, 1 Irun Guip\u00f9zcoa 20305",
    "addr:housenumber":"1",
    "addr:postcode":"20305",
    "addr:street":"Plaz Euskadi;Guipu\u0300Zcoa",
    "iso:country":"ES",
    "sg:address":"Plaz Euskadi, 1",
    "sg:city":"Irun",
    "sg:orig_category":"Mayoristas E Intermediarios En Alcoholes",
    "sg:phone":"+34 943 63 36 66",
    "sg:postcode":"20305",
    "sg:province":"Guip\u00f9zcoa",
    "wof:name":"Diaz Vicente Ruth",
    "wof:placetype":"venue"
},
  "geometry": {"coordinates":[-1.7593419552,43.3429908752],"type":"Point"}
}