{
  "type": "Feature",
  "properties": {
    "iso:country":"ES",
    "sg:address":"C/ Escoles, 12",
    "sg:city":"Cerdanyola Valles",
    "sg:orig_category":"Alquiler De V\u00cddeo",
    "sg:phone":"+34 936 91 32 50",
    "sg:postcode":"08290",
    "sg:province":"Barcelona",
    "wof:name":"Video Carrie S.l",
    "wof:placetype":"venue"
},
  "geometry": {"coordinates":[2.1470150948,41.4924812317],"type":"Point"}
}