{
  "type": "Feature",
  "properties": {
    "addr:full":"Carrer de Blasco Iba\u00d1ez, 15 Crevillent Alicante 03330",
    "addr:housenumber":"15",
    "addr:postcode":"03330",
    "addr:street":"Carrer De Blasco Iban\u0303Ez",
    "iso:country":"ES",
    "sg:address":"Carrer de Blasco Iba\u00d1ez, 15",
    "sg:city":"Crevillent",
    "sg:orig_category":"\u00d3ptica: Instrumentos (fabricaci\u00d3n)",
    "sg:phone":"+34 965 40 43 93",
    "sg:postcode":"03330",
    "sg:province":"Alicante",
    "wof:name":"Martinez Martinez Luis Enrique",
    "wof:placetype":"venue"
},
  "geometry": {"coordinates":[-0.8099079728,38.2481842041],"type":"Point"}
}