{
  "type": "Feature",
  "properties": {
    "addr:full":"Calle de Simon De Colonia, 3 Aranda Duero Burgos 09400",
    "addr:housenumber":"3",
    "addr:postcode":"09400",
    "addr:street":"Calle De Simon De Colonia",
    "iso:country":"ES",
    "sg:address":"Calle de Simon De Colonia, 3",
    "sg:city":"Aranda Duero",
    "sg:orig_category":"Instalaci\u00d3n, Reparaci\u00d3n De Ascensores Y Montacargas",
    "sg:phone":"+34 947 51 15 48",
    "sg:postcode":"09400",
    "sg:province":"Burgos",
    "sg:website":"www.otis.com",
    "wof:name":"Zardoya Otis S. A.",
    "wof:placetype":"venue"
},
  "geometry": {"coordinates":[-3.6923749447,41.6678733826],"type":"Point"}
}