{
  "type": "Feature",
  "properties": {
    "addr:full":"Cornedo(sesamo), 20 Cornedo La Coru\u00f1a 15189",
    "addr:housenumber":"20",
    "addr:postcode":"15189",
    "addr:street":"Sesamo;Cornedo La Corun\u0303A",
    "iso:country":"ES",
    "sg:address":"Cornedo(sesamo), 20",
    "sg:city":"Cornedo",
    "sg:orig_category":"Empresas De Carpinter\u00cda De Madera",
    "sg:phone":"+34 981 67 79 03",
    "sg:postcode":"15189",
    "sg:province":"La Coru\u00f1a",
    "wof:name":"Barbeito Veira Remigio",
    "wof:placetype":"venue"
},
  "geometry": {"coordinates":[-8.3836765289,43.2728500366],"type":"Point"}
}