{
  "type": "Feature",
  "properties": {
    "addr:full":"Rbla San Pedro (de), 5 Biescas Huesca 22630",
    "addr:housenumber":"5",
    "addr:postcode":"22630",
    "addr:street":"Rbla San Pedro De",
    "iso:country":"ES",
    "sg:address":"Rbla San Pedro (de), 5",
    "sg:city":"Biescas",
    "sg:orig_category":"Caf\u00c9s, Bares, Cervecer\u00cdas",
    "sg:phone":"+34 974 49 56 30",
    "sg:postcode":"22630",
    "sg:province":"Huesca",
    "wof:name":"Campo Morlans Javier",
    "wof:placetype":"venue"
},
  "geometry": {"coordinates":[-0.324003011,42.6278076172],"type":"Point"}
}