{
  "type": "Feature",
  "properties": {
    "addr:full":"Calle de Goienkalea, 17 Durango Vizcaya 48200",
    "addr:housenumber":"17",
    "addr:postcode":"48200",
    "addr:street":"Calle De Goienkalea",
    "iso:country":"ES",
    "sg:address":"Calle de Goienkalea, 17",
    "sg:city":"Durango",
    "sg:orig_category":"Molduras, Junquillos, Listones Y Molduras Perforadas",
    "sg:phone":"+34 946 81 03 54",
    "sg:postcode":"48200",
    "sg:province":"Vizcaya",
    "wof:name":"Gallastegi Martinez Aritz",
    "wof:placetype":"venue"
},
  "geometry": {"coordinates":[-2.6314330101,43.1665802002],"type":"Point"}
}