{
  "type": "Feature",
  "properties": {
    "addr:full":"Calle de San Jose, 4 Burgos Burgos 09002",
    "addr:housenumber":"4",
    "addr:postcode":"09002",
    "addr:street":"Calle De San Jose",
    "iso:country":"ES",
    "sg:address":"Calle de San Jose, 4",
    "sg:city":"Burgos",
    "sg:orig_category":"Tejidos (al Por Menor)",
    "sg:phone":"+34 947 20 90 30",
    "sg:postcode":"09002",
    "sg:province":"Burgos",
    "wof:name":"El Rumbo Suministros Industriales S.l.l.",
    "wof:placetype":"venue"
},
  "geometry": {"coordinates":[-3.6944570541,42.3380851746],"type":"Point"}
}