{
  "type": "Feature",
  "properties": {
    "iso:country":"ES",
    "sg:address":"Carrer de Elisabets, 8",
    "sg:city":"Barcelona",
    "sg:orig_category":"Internados & Ense\u00d1anza Privada",
    "sg:phone":"+34 934 12 71 20",
    "sg:postcode":"08001",
    "sg:province":"Barcelona",
    "wof:name":"Fundacio Escola Vicenciana",
    "wof:placetype":"venue"
},
  "geometry": {"coordinates":[2.1684958935,41.383430481],"type":"Point"}
}