{
  "type": "Feature",
  "properties": {
    "iso:country":"ES",
    "sg:address":"Calle de Paredes (de), 11",
    "sg:city":"Fuenlabrada",
    "sg:orig_category":"Fabricaci\u00d3n De Cajas De Cart\u00d3n",
    "sg:phone":"+34 916 90 48 18",
    "sg:postcode":"28946",
    "sg:province":"Madrid",
    "wof:name":"Manufacturas Marber S.l.",
    "wof:placetype":"venue"
},
  "geometry": {"coordinates":[-3.7726130486,40.2807273865],"type":"Point"}
}