{
  "type": "Feature",
  "properties": {
    "addr:full":"Mercat Sant Josep, 40 Barcelona Barcelona 08002",
    "addr:housenumber":"40",
    "addr:postcode":"08002",
    "iso:country":"ES",
    "sg:address":"Mercat Sant Josep, 40",
    "sg:city":"Barcelona",
    "sg:orig_category":"Carnicer\u00cdas, Carnicer\u00cdas",
    "sg:phone":"+34 933 02 18 80",
    "sg:postcode":"08002",
    "sg:province":"Barcelona",
    "wof:name":"Gonzalez Castellano Jose Maria",
    "wof:placetype":"venue"
},
  "geometry": {"coordinates":[2.1723499298,41.3820495605],"type":"Point"}
}