{
  "type": "Feature",
  "properties": {
    "iso:country":"ES",
    "sg:address":"Avda Andalucia, 61",
    "sg:city":"Dos Hermanas",
    "sg:orig_category":"Florister\u00cdas",
    "sg:phone":"+34 955 66 56 57",
    "sg:postcode":"41700",
    "sg:province":"Sevilla",
    "wof:name":"Fernandez Garcia Maria De Los Angeles",
    "wof:placetype":"venue"
},
  "geometry": {"coordinates":[-5.9246201515,37.2813186646],"type":"Point"}
}