{
  "type": "Feature",
  "properties": {
    "iso:country":"ES",
    "sg:address":"Avda Costa Del Sol, 19",
    "sg:city":"Almu\u00f1ecar",
    "sg:orig_category":"Empresas De Carpinter\u00cda",
    "sg:phone":"+34 958 88 00 12",
    "sg:postcode":"18690",
    "sg:province":"Granada",
    "wof:name":"Alumistal S.l.",
    "wof:placetype":"venue"
},
  "geometry": {"coordinates":[-3.6941759586,36.7369995117],"type":"Point"}
}