{
  "type": "Feature",
  "properties": {
    "iso:country":"ES",
    "sg:address":"Plaz Espa\u00d1a, S/n",
    "sg:city":"Motril",
    "sg:orig_category":"Administraciones Regionales, Departamentales Y Locales",
    "sg:phone":"+34 958 83 83 69",
    "sg:postcode":"18600",
    "sg:province":"Granada",
    "wof:name":"Ayuntamiento De Motril",
    "wof:placetype":"venue"
},
  "geometry": {"coordinates":[-3.5205850601,36.745098114],"type":"Point"}
}