{
  "type": "Feature",
  "properties": {
    "iso:country":"ES",
    "sg:address":"Calle de Juan Antonio Dimas, S/n",
    "sg:city":"San Cristobal",
    "sg:orig_category":"Deportes Diversos",
    "sg:phone":"+34 968 44 32 39",
    "sg:postcode":"30800",
    "sg:province":"Murcia",
    "sg:website":"www.cnlorca.com",
    "wof:name":"Club Natacion Lorca",
    "wof:placetype":"venue"
},
  "geometry": {"coordinates":[-1.6905640364,37.680557251],"type":"Point"}
}