{
  "type": "Feature",
  "properties": {
    "addr:full":"Pl Canigo (del), 10 Mataro Barcelona 08303",
    "addr:postcode":"08303",
    "addr:street":"Pl Canigo Del 10 Mataro Barcelona",
    "iso:country":"ES",
    "sg:address":"Pl Canigo (del), 10",
    "sg:city":"Mataro",
    "sg:orig_category":"Molduras, Junquillos, Listones Y Molduras Perforadas",
    "sg:phone":"+34 937 57 58 56",
    "sg:postcode":"08303",
    "sg:province":"Barcelona",
    "wof:name":"Fernandez Carrasco Amadora",
    "wof:placetype":"venue"
},
  "geometry": {"coordinates":[2.4278950691,41.5434684753],"type":"Point"}
}