{
  "type": "Feature",
  "properties": {
    "iso:country":"ES",
    "sg:address":"Carr Sant Lleir, 8",
    "sg:city":"Lleida",
    "sg:orig_category":"Venta, Instalaci\u00d3n De Calefacci\u00d3n",
    "sg:phone":"+34 973 24 41 48",
    "sg:postcode":"25005",
    "sg:province":"Lleida",
    "wof:name":"Solaigua S.c.p.",
    "wof:placetype":"venue"
},
  "geometry": {"coordinates":[0.6302390099,41.6333503723],"type":"Point"}
}