{
  "type": "Feature",
  "properties": {
    "iso:country":"ES",
    "sg:address":"Calle de Miralparque, 13",
    "sg:city":"Arganda",
    "sg:orig_category":"Centros Comerciales Y Grandes Tiendas",
    "sg:phone":"+34 918 70 49 07",
    "sg:postcode":"28500",
    "sg:province":"Madrid",
    "wof:name":"Ye Liu Wan Bing",
    "wof:placetype":"venue"
},
  "geometry": {"coordinates":[-3.4423789978,40.3032264709],"type":"Point"}
}