{
  "type": "Feature",
  "properties": {
    "iso:country":"ES",
    "sg:address":"Avda Reconquista, 7",
    "sg:city":"Toledo",
    "sg:orig_category":"Bancos",
    "sg:phone":"+34 925 25 76 77",
    "sg:postcode":"45004",
    "sg:province":"Toledo",
    "wof:name":"Banc Sabadell S.a.",
    "wof:placetype":"venue"
},
  "geometry": {"coordinates":[-4.0290951729,39.866771698],"type":"Point"}
}