{
  "type": "Feature",
  "properties": {
    "addr:full":"Calle de Comandante Santa Pau, 8 Zaragoza Zaragoza 50008",
    "addr:housenumber":"8",
    "addr:postcode":"50008",
    "addr:street":"Calle De Comandante Santa Pau",
    "iso:country":"ES",
    "sg:address":"Calle de Comandante Santa Pau, 8",
    "sg:city":"Zaragoza",
    "sg:orig_category":"Arquitectos",
    "sg:phone":"+34 976 23 63 64",
    "sg:postcode":"50008",
    "sg:province":"Zaragoza",
    "wof:name":"Navarro Alduain Luis Fernando",
    "wof:placetype":"venue"
},
  "geometry": {"coordinates":[-0.884829402,41.6423225403],"type":"Point"}
}