{
  "type": "Feature",
  "properties": {
    "addr:full":"Avda Candido Lobera, 5 Melilla Melilla 52001",
    "addr:housenumber":"5",
    "addr:postcode":"52001",
    "addr:street":"Avda Candido Lobera",
    "iso:country":"ES",
    "sg:address":"Avda Candido Lobera, 5",
    "sg:city":"Melilla",
    "sg:orig_category":"Abogados",
    "sg:phone":"+34 952 68 24 21",
    "sg:postcode":"52001",
    "sg:province":"Melilla",
    "wof:name":"Pascual Vazquez Maria Concepcion",
    "wof:placetype":"venue"
},
  "geometry": {"coordinates":[-2.939729929,35.2941513062],"type":"Point"}
}