{
  "type": "Feature",
  "properties": {
    "iso:country":"ES",
    "sg:address":"Avda Juan Carlos I, Rey, 1",
    "sg:city":"Melilla",
    "sg:orig_category":"Empresarios",
    "sg:phone":"+34 952 68 32 26",
    "sg:postcode":"52001",
    "sg:province":"Melilla",
    "wof:name":"Garcia Albadalejo Antonio",
    "wof:placetype":"venue"
},
  "geometry": {"coordinates":[-2.9385650158,35.2927474976],"type":"Point"}
}