{
  "type": "Feature",
  "properties": {
    "iso:country":"ES",
    "sg:address":"La Rosa, 2",
    "sg:city":"Sta Cruz Tenerife",
    "sg:orig_category":"Inversiones",
    "sg:phone":"+34 922 53 11 14",
    "sg:postcode":"38002",
    "sg:province":"Santa Cruz De Tenerife",
    "wof:name":"Inversiones Las Teresitas S.l.",
    "wof:placetype":"venue"
},
  "geometry": {"coordinates":[-16.2504272461,28.4694881439],"type":"Point"}
}