{
  "type": "Feature",
  "properties": {
    "iso:country":"ES",
    "sg:address":"Calle de Calero Pita, 8",
    "sg:city":"Madrid",
    "sg:orig_category":"Muebles Y Accesorios Para Cocinas Y Cuartos De Ba\u00d1o (al Por Menor)",
    "sg:phone":"+34 914 77 92 80",
    "sg:postcode":"28053",
    "sg:province":"Madrid",
    "wof:name":"Davila Puerta Maria Paz",
    "wof:placetype":"venue"
},
  "geometry": {"coordinates":[-3.6704199314,40.38306427],"type":"Point"}
}