{
  "type": "Feature",
  "properties": {
    "iso:country":"ES",
    "sg:address":"Calle de Rubio, 4",
    "sg:city":"Cintruenigo",
    "sg:orig_category":"Productores Recolectores, Venta Directa De Vinos",
    "sg:phone":"+34 948 81 18 69",
    "sg:postcode":"31592",
    "sg:province":"Navarra",
    "wof:name":"Garbayo Alduan Damaso",
    "wof:placetype":"venue"
},
  "geometry": {"coordinates":[-1.8098150492,42.0796127319],"type":"Point"}
}