{
  "type": "Feature",
  "properties": {
    "iso:country":"ES",
    "sg:address":"Calle de Ca\u00d1averal, 89",
    "sg:city":"Madrid",
    "sg:orig_category":"Molduras, Junquillos, Listones Y Molduras Perforadas",
    "sg:phone":"+34 913 15 71 32",
    "sg:postcode":"28029",
    "sg:province":"Madrid",
    "wof:name":"Santos-garcia Gonzalez Ildefonso",
    "wof:placetype":"venue"
},
  "geometry": {"coordinates":[-3.6921761036,40.4708786011],"type":"Point"}
}