{
  "type": "Feature",
  "properties": {
    "addr:full":"Avda Coru\u00d1a (da), 253 Lugo Lugo 27003",
    "addr:housenumber":"253",
    "addr:postcode":"27003",
    "addr:street":"Avda Corun\u0303A Da",
    "iso:country":"ES",
    "sg:address":"Avda Coru\u00d1a (da), 253",
    "sg:city":"Lugo",
    "sg:orig_category":"Alimentaci\u00d3n General (al Por Menor)",
    "sg:phone":"+34 982 21 15 00",
    "sg:postcode":"27003",
    "sg:province":"Lugo",
    "wof:name":"Guntin Rodriguez Jose Luis",
    "wof:placetype":"venue"
},
  "geometry": {"coordinates":[-7.5651230812,43.0227241516],"type":"Point"}
}