{
  "type": "Feature",
  "properties": {
    "addr:full":"Av Madrid, 24 Crevillent Alicante 03330",
    "addr:housenumber":"24",
    "addr:postcode":"03330",
    "addr:street":"Av Madrid",
    "iso:country":"ES",
    "sg:address":"Av Madrid, 24",
    "sg:city":"Crevillent",
    "sg:orig_category":"Electricidad: Equipos Industriales, Componentes (fabricaci\u00d3n)",
    "sg:phone":"+34 965 40 31 50",
    "sg:postcode":"03330",
    "sg:province":"Alicante",
    "wof:name":"Instalaciones Electricas Candela S.l.",
    "wof:placetype":"venue"
},
  "geometry": {"coordinates":[-0.8101465702,38.2463378906],"type":"Point"}
}