{
  "type": "Feature",
  "properties": {
    "iso:country":"ES",
    "sg:address":"Plaz Querer (del), S/n",
    "sg:city":"Algeciras",
    "sg:orig_category":"Agencias Y Agentes Comerciales, Representantes",
    "sg:phone":"+34 956 63 46 28",
    "sg:postcode":"11204",
    "sg:province":"C\u00e1diz",
    "wof:name":"Lopez Ortega Juan",
    "wof:placetype":"venue"
},
  "geometry": {"coordinates":[-5.4725384712,36.1437492371],"type":"Point"}
}