{
  "type": "Feature",
  "properties": {
    "iso:country":"ES",
    "sg:address":"Calle de Corpus Christi, 6",
    "sg:city":"Valladolid",
    "sg:orig_category":"Laboratorios Y Trabajos De Fotograf\u00cda, V\u00cddeo Y Cine",
    "sg:phone":"+34 983 29 59 83",
    "sg:postcode":"47005",
    "sg:province":"Valladolid",
    "sg:website":"www.paisajesespanoles.es",
    "wof:name":"Lozano Pomar Gonzalo",
    "wof:placetype":"venue"
},
  "geometry": {"coordinates":[-4.7151560783,41.6544723511],"type":"Point"}
}