{
  "type": "Feature",
  "properties": {
    "addr:full":"Calle de Riquelme, 20 Santa Catalina Murcia 30005",
    "addr:housenumber":"20",
    "addr:postcode":"30005",
    "addr:street":"Calle De Riquelme",
    "iso:country":"ES",
    "sg:address":"Calle de Riquelme, 20",
    "sg:city":"Santa Catalina",
    "sg:orig_category":"Agencias Y Agentes Comerciales, Representantes",
    "sg:phone":"+34 968 21 75 78",
    "sg:postcode":"30005",
    "sg:province":"Murcia",
    "wof:name":"Representaciones Hernandez Sojo S.l.",
    "wof:placetype":"venue"
},
  "geometry": {"coordinates":[-1.1340049505,37.9855728149],"type":"Point"}
}