{
  "type": "Feature",
  "properties": {
    "iso:country":"ES",
    "sg:address":"Ctra Trujillo, 6",
    "sg:city":"Plasencia",
    "sg:orig_category":"Distribuci\u00d3n De Petr\u00d3leo Y Derivados",
    "sg:phone":"+34 927 42 33 41",
    "sg:postcode":"10600",
    "sg:province":"C\u00e1ceres",
    "wof:name":"Pescados Norte De Extremadura S.l.",
    "wof:placetype":"venue"
},
  "geometry": {"coordinates":[-6.0998048782,40.0126724243],"type":"Point"}
}