{
  "type": "Feature",
  "properties": {
    "addr:full":"Calle de Apolo, 42 Torrevieja Alicante 03180",
    "addr:housenumber":"42",
    "addr:postcode":"03180",
    "addr:street":"Calle De Apolo",
    "iso:country":"ES",
    "sg:address":"Calle de Apolo, 42",
    "sg:city":"Torrevieja",
    "sg:classifiers":[
        {
            "category":"Personal",
            "subcategory":"Barber",
            "type":"Services"
        }
    ],
    "sg:phone":"+34 965 71 11 79",
    "sg:postcode":"03180",
    "sg:province":"Alicante",
    "sg:tags":[
        "caballeros",
        "de",
        "peluqueros"
    ],
    "wof:name":"Lorca Alari David",
    "wof:placetype":"venue"
},
  "geometry": {"coordinates":[-0.6786007881,37.9786911011],"type":"Point"}
}