{
  "type": "Feature",
  "properties": {
    "iso:country":"ES",
    "sg:address":"Calle de Duero, 2",
    "sg:city":"Ajalvir",
    "sg:orig_category":"Contenedores (mercanc\u00cdas)",
    "sg:phone":"+34 918 84 30 97",
    "sg:postcode":"28864",
    "sg:province":"Madrid",
    "wof:name":"Gonzalez Delgado Felix",
    "wof:placetype":"venue"
},
  "geometry": {"coordinates":[-3.4813272953,40.5009689331],"type":"Point"}
}