{
  "type": "Feature",
  "properties": {
    "iso:country":"ES",
    "sg:address":"Calle de Molinico (el), 4",
    "sg:city":"Cuevas Almanzora",
    "sg:orig_category":"Guarder\u00cdas",
    "sg:phone":"+34 950 45 66 58",
    "sg:postcode":"04610",
    "sg:province":"Almer\u00eda",
    "wof:name":"Escuela Infantil Luis Siret S.c.a.",
    "wof:placetype":"venue"
},
  "geometry": {"coordinates":[-1.8773959875,37.2958450317],"type":"Point"}
}