{
  "type": "Feature",
  "properties": {
    "addr:full":"Avda Oviedo De, 47 Entrego Asturias 33940",
    "addr:housenumber":"47",
    "addr:postcode":"33940",
    "addr:street":"Avda Oviedo De",
    "iso:country":"ES",
    "sg:address":"Avda Oviedo De, 47",
    "sg:city":"Entrego",
    "sg:orig_category":"Ense\u00d1anza Variada",
    "sg:phone":"+34 985 66 07 55",
    "sg:postcode":"33940",
    "sg:province":"Asturias",
    "wof:name":"Academia Antares C.b.",
    "wof:placetype":"venue"
},
  "geometry": {"coordinates":[-5.645138,43.285526],"type":"Point"}
}