{
  "type": "Feature",
  "properties": {
    "iso:country":"ES",
    "sg:address":"Calle de San Pedro, 1",
    "sg:city":"Baluga",
    "sg:orig_category":"Supermercados Y Hipermercados",
    "sg:phone":"+34 946 10 47 43",
    "sg:postcode":"48190",
    "sg:province":"Vizcaya",
    "wof:name":"Juan Domingo Arteagabeitia Ruiz Y M\u00aa Dolores Jauregui Palacioc.b.",
    "wof:placetype":"venue"
},
  "geometry": {"coordinates":[-3.1545369625,43.2622108459],"type":"Point"}
}