{
  "type": "Feature",
  "properties": {
    "iso:country":"ES",
    "sg:address":"Calle de Sierra Nevada, 36",
    "sg:city":"Ejido",
    "sg:orig_category":"Alimentaci\u00d3n General (al Por Menor)",
    "sg:phone":"+34 950 48 66 02",
    "sg:postcode":"04700",
    "sg:province":"Almer\u00eda",
    "wof:name":"Sociedad Carmona Y Zu\u00d1iga S.l.",
    "wof:placetype":"venue"
},
  "geometry": {"coordinates":[-2.8159511089,36.780380249],"type":"Point"}
}