{
  "type": "Feature",
  "properties": {
    "iso:country":"ES",
    "sg:address":"Calle de Cervantes, 2",
    "sg:city":"Zamora",
    "sg:orig_category":"Transporte En General",
    "sg:phone":"+34 980 67 16 62",
    "sg:postcode":"49013",
    "sg:province":"Zamora",
    "wof:name":"Pinto Delgado Ignacio",
    "wof:placetype":"venue"
},
  "geometry": {"coordinates":[-5.7408661842,41.5100288391],"type":"Point"}
}