{
  "type": "Feature",
  "properties": {
    "iso:country":"ES",
    "sg:address":"Carrer de Nou, 2",
    "sg:city":"Can Castells",
    "sg:orig_category":"Peluquer\u00cdas, Peluquer\u00cda Mixta",
    "sg:phone":"+34 938 49 77 04",
    "sg:postcode":"08420",
    "sg:province":"Barcelona",
    "wof:name":"Perez Galvez Maria Pilar",
    "wof:placetype":"venue"
},
  "geometry": {"coordinates":[2.2783401012,41.6220207214],"type":"Point"}
}