{
  "type": "Feature",
  "properties": {
    "addr:full":"Solape\u00f1a, S/n Fuentes Asturias 33310",
    "addr:housenumber":"/ n",
    "addr:postcode":"33310",
    "addr:street":"Solapen\u0303A S",
    "iso:country":"ES",
    "sg:address":"Solape\u00f1a, S/n",
    "sg:city":"Fuentes",
    "sg:orig_category":"Explotaci\u00d3n De Canteras",
    "sg:phone":"+34 985 89 02 90",
    "sg:postcode":"33310",
    "sg:province":"Asturias",
    "wof:name":"Excavaciones Y Perforaciones Fuente S.l",
    "wof:placetype":"venue"
},
  "geometry": {"coordinates":[-5.4102787971,43.4167289734],"type":"Point"}
}