{
  "type": "Feature",
  "properties": {
    "iso:country":"ES",
    "sg:address":"Plaz San Andres, 3",
    "sg:city":"Cordoba",
    "sg:orig_category":"Bisuter\u00cda, Joyer\u00cda, Relojer\u00cda (al Por Menor)",
    "sg:phone":"+34 957 47 92 12",
    "sg:postcode":"14002",
    "sg:province":"C\u00f3rdoba",
    "wof:name":"Martinez Gonzalez Julio Antonio",
    "wof:placetype":"venue"
},
  "geometry": {"coordinates":[-4.7727999687,37.8863639832],"type":"Point"}
}