{
  "type": "Feature",
  "properties": {
    "addr:full":"Carrer de Doctor Carulla, 23 Cornella Llobregat Barcelona 08940",
    "addr:housenumber":"23",
    "addr:postcode":"08940",
    "addr:street":"Carrer De Doctor Carulla",
    "iso:country":"ES",
    "sg:address":"Carrer de Doctor Carulla, 23",
    "sg:city":"Cornella Llobregat",
    "sg:orig_category":"Escuelas Primarias Privadas",
    "sg:phone":"+34 933 77 01 37",
    "sg:postcode":"08940",
    "sg:province":"Barcelona",
    "wof:name":"Colegio Sagrada Familia En Cornella Doctrina Cristiana Prov Dep Curia General",
    "wof:placetype":"venue"
},
  "geometry": {"coordinates":[2.0724360943,41.3556671143],"type":"Point"}
}