{
  "type": "Feature",
  "properties": {
    "addr:full":"Calle de Agustina De Aragon, 1 Illueca Zaragoza 50250",
    "addr:housenumber":"1",
    "addr:postcode":"50250",
    "addr:street":"Calle De Agustina De Aragon",
    "iso:country":"ES",
    "sg:address":"Calle de Agustina De Aragon, 1",
    "sg:city":"Illueca",
    "sg:orig_category":"Plomeros",
    "sg:phone":"+34 976 82 22 19",
    "sg:postcode":"50250",
    "sg:province":"Zaragoza",
    "wof:name":"Salda\u00f1a Marco Santiago",
    "wof:placetype":"venue"
},
  "geometry": {"coordinates":[-1.6292022467,41.5373916626],"type":"Point"}
}