{
  "type": "Feature",
  "properties": {
    "iso:country":"ES",
    "sg:address":"Cra. Artesa, S/n",
    "sg:city":"Montblanc",
    "sg:orig_category":"Tapicer\u00cdas",
    "sg:phone":"+34 977 86 12 02",
    "sg:postcode":"43400",
    "sg:province":"Tarragona",
    "wof:name":"Tapimont S.l.",
    "wof:placetype":"venue"
},
  "geometry": {"coordinates":[1.1694400311,41.3705749512],"type":"Point"}
}