{
  "type": "Feature",
  "properties": {
    "addr:full":"Casta\u00f1ar, S/n Bejar Salamanca 37700",
    "addr:postcode":"37700",
    "addr:street":"Castan\u0303Ar S / N Bejar",
    "iso:country":"ES",
    "sg:address":"Casta\u00f1ar, S/n",
    "sg:city":"Bejar",
    "sg:orig_category":"Molduras, Junquillos, Listones Y Molduras Perforadas",
    "sg:phone":"+34 923 41 01 47",
    "sg:postcode":"37700",
    "sg:province":"Salamanca",
    "wof:name":"Sanchez Paso Miguel Angel",
    "wof:placetype":"venue"
},
  "geometry": {"coordinates":[-5.7658338547,40.3824653625],"type":"Point"}
}