{
  "type": "Feature",
  "properties": {
    "iso:country":"ES",
    "sg:address":"Calle de Pinto, 37",
    "sg:city":"Parla",
    "sg:orig_category":"Carnicer\u00cdas, Carnicer\u00cdas",
    "sg:phone":"+34 916 99 94 77",
    "sg:postcode":"28980",
    "sg:province":"Madrid",
    "wof:name":"Gomez Pulido Santiago",
    "wof:placetype":"venue"
},
  "geometry": {"coordinates":[-3.7674260139,40.2392501831],"type":"Point"}
}