{
  "type": "Feature",
  "properties": {
    "addr:full":"Calle de Narciso, 8 Girasoles Sevilla 41907",
    "addr:housenumber":"8",
    "addr:postcode":"41907",
    "addr:street":"Calle De Narciso",
    "iso:country":"ES",
    "sg:address":"Calle de Narciso, 8",
    "sg:city":"Girasoles",
    "sg:orig_category":"Confecci\u00d3n De Uniformes",
    "sg:phone":"+34 955 99 96 46",
    "sg:postcode":"41907",
    "sg:province":"Sevilla",
    "wof:name":"Martin Berdejo Antonio",
    "wof:placetype":"venue"
},
  "geometry": {"coordinates":[-6.0776147842,37.4170455933],"type":"Point"}
}