{
  "type": "Feature",
  "properties": {
    "iso:country":"ES",
    "sg:address":"Carretera de Valldemossa km 7,4 ParcBIT Edifici 17 D-9",
    "sg:city":"Palma de Mallorca",
    "sg:classifiers":[
        {
            "category":"Professional",
            "subcategory":"Computer Services",
            "type":"Services"
        }
    ],
    "sg:postcode":"07121",
    "sg:tags":[
        "contractors",
        "construction",
        "architecture",
        "interior-design",
        "renovation"
    ],
    "sg:website":"http://www.habitissimo.es",
    "wof:name":"Habitissimo",
    "wof:placetype":"venue"
},
  "geometry": {"coordinates":[2.651077,39.5857533],"type":"Point"}
}