{
  "type": "Feature",
  "properties": {
    "iso:country":"ES",
    "sg:address":"Plaza Soledad, S/n",
    "sg:city":"Cuellar",
    "sg:orig_category":"Sales (al Por Mayor)",
    "sg:phone":"+34 921 14 00 56",
    "sg:postcode":"40200",
    "sg:province":"Segovia",
    "wof:name":"General Espa\u00f1ola De Achicoria S.a.",
    "wof:placetype":"venue"
},
  "geometry": {"coordinates":[-4.3119688034,41.4013137817],"type":"Point"}
}