{
  "type": "Feature",
  "properties": {
    "iso:country":"ES",
    "sg:address":"Calle de Santander, S/n",
    "sg:city":"Corrales",
    "sg:orig_category":"Inmobiliaria (agencias)",
    "sg:phone":"+34 942 83 14 41",
    "sg:postcode":"39400",
    "sg:province":"Cantabria",
    "wof:name":"Mier Fernandez Pedro Luis",
    "wof:placetype":"venue"
},
  "geometry": {"coordinates":[-4.065308094,43.2675933838],"type":"Point"}
}