{
  "type": "Feature",
  "properties": {
    "iso:country":"ES",
    "sg:address":"Calle de Sevilla, 21",
    "sg:city":"Arcos Frontera",
    "sg:orig_category":"Cajas De Ahorro",
    "sg:phone":"+34 956 70 47 63",
    "sg:postcode":"11630",
    "sg:province":"C\u00e1diz",
    "wof:name":"Caixa D'estalvis I Pensions De Barcelona",
    "wof:placetype":"venue"
},
  "geometry": {"coordinates":[-5.8134489059,36.7536125183],"type":"Point"}
}