{
  "type": "Feature",
  "properties": {
    "iso:country":"ES",
    "sg:address":"Calle de Almendralejo, 15",
    "sg:city":"Merida",
    "sg:orig_category":"Inform\u00c1tica (estudios, Servicios, Asesor\u00cda, Formaci\u00d3n)",
    "sg:phone":"+34 924 30 31 25",
    "sg:postcode":"06800",
    "sg:province":"Badajoz",
    "wof:name":"Collado Giraldo Pedro Arsenio",
    "wof:placetype":"venue"
},
  "geometry": {"coordinates":[-6.3485708237,38.9183540344],"type":"Point"}
}