{
  "type": "Feature",
  "properties": {
    "iso:country":"ES",
    "sg:address":"Avda Manzanares, 74",
    "sg:city":"Madrid",
    "sg:orig_category":"Promotores Constructores",
    "sg:phone":"+34 915 65 63 03",
    "sg:postcode":"28019",
    "sg:province":"Madrid",
    "wof:name":"Toscare S.a.",
    "wof:placetype":"venue"
},
  "geometry": {"coordinates":[-3.7222468853,40.4005661011],"type":"Point"}
}