{
  "type": "Feature",
  "properties": {
    "iso:country":"ES",
    "sg:address":"Calle de Montevideo, S/n",
    "sg:city":"Alcala Henares",
    "sg:orig_category":"Audiovisuales: Material Y Accesorios (al Por Menor)",
    "sg:phone":"+34 918 30 03 45",
    "sg:postcode":"28806",
    "sg:province":"Madrid",
    "sg:website":"www.puertasdesonido.net",
    "wof:name":"A.s.puerta De Sonido S.l.",
    "wof:placetype":"venue"
},
  "geometry": {"coordinates":[-3.4103291035,40.5152587891],"type":"Point"}
}