{
  "type": "Feature",
  "properties": {
    "addr:full":"Ctra. Fatela, Km. 0005,5 Gata C\u00e1ceres 10860",
    "addr:postcode":"10860",
    "addr:street":"Ctra. Fatela Km. 0005,5 Gata Ca\u0301Ceres",
    "iso:country":"ES",
    "sg:address":"Ctra. Fatela, Km. 0005,5",
    "sg:city":"Gata",
    "sg:orig_category":"Aceites Y Grasas Alimentarias (fabricaci\u00d3n, Al Por Mayor)",
    "sg:phone":"+34 927 19 70 18",
    "sg:postcode":"10860",
    "sg:province":"C\u00e1ceres",
    "wof:name":"Agroindustrias La Fe S.a.",
    "wof:placetype":"venue"
},
  "geometry": {"coordinates":[-6.6031160355,40.2391471863],"type":"Point"}
}