{
  "type": "Feature",
  "properties": {
    "iso:country":"ES",
    "sg:address":"C/ Governador Padules, 8",
    "sg:city":"Tarrega",
    "sg:orig_category":"Bebidas",
    "sg:phone":"+34 973 31 04 32",
    "sg:postcode":"25300",
    "sg:province":"Lleida",
    "wof:name":"Distribuciones Urgell Segarra S.l",
    "wof:placetype":"venue"
},
  "geometry": {"coordinates":[1.1369689703,41.648399353],"type":"Point"}
}