{
  "type": "Feature",
  "properties": {
    "iso:country":"ES",
    "sg:address":"Luga Barranquillo Andres, 7",
    "sg:city":"Barranquillo Andres",
    "sg:orig_category":"Centros De Educaci\u00d3n Especial",
    "sg:phone":"+34 928 17 24 30",
    "sg:postcode":"35140",
    "sg:province":"Las Palmas",
    "wof:name":"Gobierno De Canarias",
    "wof:placetype":"venue"
},
  "geometry": {"coordinates":[-15.7237386703,27.8846378326],"type":"Point"}
}