{
  "type": "Feature",
  "properties": {
    "addr:full":"Calle de Marques De Santillana, 1 Guadalajara Guadalajara 19002",
    "addr:housenumber":"1",
    "addr:postcode":"19002",
    "addr:street":"Calle De Marques De Santillana",
    "iso:country":"ES",
    "sg:address":"Calle de Marques De Santillana, 1",
    "sg:city":"Guadalajara",
    "sg:orig_category":"Tapicer\u00cdas",
    "sg:phone":"+34 949 21 97 85",
    "sg:postcode":"19002",
    "sg:province":"Guadalajara",
    "wof:name":"Tapiceria Del Rio C.b.",
    "wof:placetype":"venue"
},
  "geometry": {"coordinates":[-3.1617910862,40.6284294128],"type":"Point"}
}