{
  "type": "Feature",
  "properties": {
    "addr:full":"Calle de Salve, 32 Torrijos Toledo 45500",
    "addr:housenumber":"32",
    "addr:postcode":"45500",
    "addr:street":"Calle De Salve",
    "iso:country":"ES",
    "sg:address":"Calle de Salve, 32",
    "sg:city":"Torrijos",
    "sg:orig_category":"Fabricaci\u00d3n De Ventanas",
    "sg:phone":"+34 925 77 09 20",
    "sg:postcode":"45500",
    "sg:province":"Toledo",
    "sg:website":"www.eufrasiopinto.com",
    "wof:name":"Eufrasio Pinto S.l.",
    "wof:placetype":"venue"
},
  "geometry": {"coordinates":[-4.2909288406,39.976688385],"type":"Point"}
}