{
  "type": "Feature",
  "properties": {
    "iso:country":"ES",
    "sg:address":"Paulino Caballero, 15",
    "sg:city":"Iru\u00f1a",
    "sg:orig_category":"Arquitectos",
    "sg:phone":"+34 948 21 09 63",
    "sg:postcode":"31002",
    "sg:province":"Navarra",
    "wof:name":"Ayesa Pascual Andres",
    "wof:placetype":"venue"
},
  "geometry": {"coordinates":[-1.640930295,42.813457489],"type":"Point"}
}