{
  "type": "Feature",
  "properties": {
    "iso:country":"ES",
    "sg:address":"Calle de Antonio Machado, 5",
    "sg:city":"Totana",
    "sg:orig_category":"Chapister\u00cda",
    "sg:phone":"+34 968 42 17 01",
    "sg:postcode":"30850",
    "sg:province":"Murcia",
    "wof:name":"Murcia Lopez Roque",
    "wof:placetype":"venue"
},
  "geometry": {"coordinates":[-1.4922524691,37.7728271484],"type":"Point"}
}