{
  "type": "Feature",
  "properties": {
    "iso:country":"ES",
    "sg:address":"Pg Ernest Mestre, 38",
    "sg:city":"Felanitx",
    "sg:orig_category":"Peluquer\u00cdas, Peluquer\u00cda Mixta",
    "sg:phone":"+34 971 55 65 39",
    "sg:postcode":"07200",
    "sg:province":"Islas Baleares",
    "wof:name":"Soler Portell Maria Antonia",
    "wof:placetype":"venue"
},
  "geometry": {"coordinates":[3.1447389126,39.4695968628],"type":"Point"}
}