{
  "type": "Feature",
  "properties": {
    "iso:country":"ES",
    "sg:address":"Calle de Arquitecto Yarza, 5",
    "sg:city":"Zaragoza",
    "sg:orig_category":"M\u00c9dicos: Cirug\u00cda Pl\u00c1stica, Reconstructiva Y Est\u00c9tica",
    "sg:phone":"+34 976 21 77 46",
    "sg:postcode":"50008",
    "sg:province":"Zaragoza",
    "wof:name":"Andreu Carilla Angel",
    "wof:placetype":"venue"
},
  "geometry": {"coordinates":[-0.8832902908,41.6474571228],"type":"Point"}
}