{
  "type": "Feature",
  "properties": {
    "iso:country":"ES",
    "sg:address":"Calle de Maria De Guzman, 56",
    "sg:city":"Madrid",
    "sg:orig_category":"M\u00c9dicos: Ginecolog\u00cda Y Obstetricia",
    "sg:phone":"+34 915 35 01 38",
    "sg:postcode":"28003",
    "sg:province":"Madrid",
    "wof:name":"Diego Cabanzon Antonio",
    "wof:placetype":"venue"
},
  "geometry": {"coordinates":[-3.6963450909,40.4438438416],"type":"Point"}
}