{
  "type": "Feature",
  "properties": {
    "addr:full":"Calle de C. Huerfanos Cristinos, 4 Toledo Toledo 45003",
    "addr:housenumber":"4",
    "addr:postcode":"45003",
    "addr:street":"Calle De C. Huerfanos Cristinos",
    "iso:country":"ES",
    "sg:address":"Calle de C. Huerfanos Cristinos, 4",
    "sg:city":"Toledo",
    "sg:orig_category":"Agencias Y Asesores De Publicidad",
    "sg:phone":"+34 925 28 05 44",
    "sg:postcode":"45003",
    "sg:province":"Toledo",
    "wof:name":"Sociedad Y Proyectos Inmobiliarios Reunidos S.l.",
    "wof:placetype":"venue"
},
  "geometry": {"coordinates":[-3.9827404022,39.8976478577],"type":"Point"}
}