{
  "type": "Feature",
  "properties": {
    "iso:country":"ES",
    "sg:address":"Avda Inmaculada Concepcion, 23",
    "sg:city":"Sauzal",
    "sg:orig_category":"Promotores Constructores",
    "sg:phone":"+34 922 57 12 85",
    "sg:postcode":"38360",
    "sg:province":"Santa Cruz De Tenerife",
    "wof:name":"Panornas S.l.",
    "wof:placetype":"venue"
},
  "geometry": {"coordinates":[-16.433927536,28.480014801],"type":"Point"}
}