{
  "type": "Feature",
  "properties": {
    "iso:country":"ES",
    "sg:address":"Plaz Mayor, 3",
    "sg:city":"Alcudia De Monteagud",
    "sg:orig_category":"Administraciones Regionales, Departamentales Y Locales",
    "sg:phone":"+34 950 52 33 54",
    "sg:postcode":"04276",
    "sg:province":"Almer\u00eda",
    "wof:name":"Ayuntamiento Alcudia De Monteagud",
    "wof:placetype":"venue"
},
  "geometry": {"coordinates":[-2.2664070129,37.2359542847],"type":"Point"}
}