{
  "type": "Feature",
  "properties": {
    "iso:country":"ES",
    "sg:address":"Calle de Virgen De Los Milagros, 49",
    "sg:city":"Puerto De Santa Maria",
    "sg:orig_category":"Art\u00cdculos De Decoraci\u00d3n",
    "sg:phone":"+34 956 54 14 32",
    "sg:postcode":"11500",
    "sg:province":"C\u00e1diz",
    "wof:name":"Gatica Garrido Maria",
    "wof:placetype":"venue"
},
  "geometry": {"coordinates":[-6.2237567902,36.600769043],"type":"Point"}
}