{
  "type": "Feature",
  "properties": {
    "addr:full":"Avda Pinar (del), S/n Alcorcon Madrid 28925",
    "addr:postcode":"28925",
    "addr:street":"Avda Pinar Del S / N Alcorcon",
    "iso:country":"ES",
    "sg:address":"Avda Pinar (del), S/n",
    "sg:city":"Alcorcon",
    "sg:orig_category":"Distribuci\u00d3n De Petr\u00d3leo Y Derivados",
    "sg:phone":"+34 914 86 04 84",
    "sg:postcode":"28925",
    "sg:province":"Madrid",
    "wof:name":"Gestion Punto Venta S.a.",
    "wof:placetype":"venue"
},
  "geometry": {"coordinates":[-3.8081541061,40.3442382812],"type":"Point"}
}