{
  "type": "Feature",
  "properties": {
    "addr:full":"Carrer de Corominas, 17 Hospitalet Llobregat Barcelona 08902",
    "addr:housenumber":"17",
    "addr:postcode":"08902",
    "addr:street":"Carrer De Corominas",
    "iso:country":"ES",
    "sg:address":"Carrer de Corominas, 17",
    "sg:city":"Hospitalet Llobregat",
    "sg:orig_category":"Electricidad: Instaladores",
    "sg:phone":"+34 934 31 03 05",
    "sg:postcode":"08902",
    "sg:province":"Barcelona",
    "wof:name":"G.d.o. Electric S.l.",
    "wof:placetype":"venue"
},
  "geometry": {"coordinates":[2.1208379269,41.3666191101],"type":"Point"}
}