{
  "type": "Feature",
  "properties": {
    "addr:full":"Calle de Caspe, 50 Zaragoza Zaragoza 50017",
    "addr:housenumber":"50",
    "addr:postcode":"50017",
    "addr:street":"Calle De Caspe",
    "iso:country":"ES",
    "sg:address":"Calle de Caspe, 50",
    "sg:city":"Zaragoza",
    "sg:orig_category":"Chapa Y Pintura Veh\u00cdculos",
    "sg:phone":"+34 976 34 05 56",
    "sg:postcode":"50017",
    "sg:province":"Zaragoza",
    "wof:name":"Marco Gregorio Ismael",
    "wof:placetype":"venue"
},
  "geometry": {"coordinates":[-0.9077523947,41.6511993408],"type":"Point"}
}