{
  "type": "Feature",
  "properties": {
    "iso:country":"ES",
    "sg:address":"Carrer de Feder Garcia Lorca, 21",
    "sg:city":"Palma",
    "sg:orig_category":"Tintorer\u00cdas, Limpieza En Seco",
    "sg:phone":"+34 971 28 31 02",
    "sg:postcode":"07014",
    "sg:province":"Islas Baleares",
    "wof:name":"Rio Casilda Ana Antonia Del",
    "wof:placetype":"venue"
},
  "geometry": {"coordinates":[2.6276938915,39.5653800964],"type":"Point"}
}