{
  "type": "Feature",
  "properties": {
    "iso:country":"ES",
    "sg:address":"Avda Generalisimo, 68",
    "sg:city":"Barbate",
    "sg:orig_category":"Electrodom\u00c9sticos (al Por Menor)",
    "sg:phone":"+34 956 43 01 80",
    "sg:postcode":"11160",
    "sg:province":"C\u00e1diz",
    "wof:name":"Conde Garcia Diego",
    "wof:placetype":"venue"
},
  "geometry": {"coordinates":[-5.9209618568,36.1907424927],"type":"Point"}
}