{
  "type": "Feature",
  "properties": {
    "addr:full":"Carrer de Lluis Jover (de), 62 Vilassar De Mar Barcelona 08340",
    "addr:housenumber":"62",
    "addr:postcode":"08340",
    "addr:street":"Carrer De Lluis Jover De",
    "iso:country":"ES",
    "sg:address":"Carrer de Lluis Jover (de), 62",
    "sg:city":"Vilassar De Mar",
    "sg:orig_category":"Supermercados Y Hipermercados",
    "sg:phone":"+34 937 50 11 66",
    "sg:postcode":"08340",
    "sg:province":"Barcelona",
    "wof:name":"Millor Preu Vilassar S.a.",
    "wof:placetype":"venue"
},
  "geometry": {"coordinates":[2.3863499165,41.508190155],"type":"Point"}
}