{
  "type": "Feature",
  "properties": {
    "addr:full":"Carrer de Filadors, 16 Sabadell Barcelona 08208",
    "addr:housenumber":"16",
    "addr:postcode":"08208",
    "addr:street":"Carrer De Filadors",
    "iso:country":"ES",
    "sg:address":"Carrer de Filadors, 16",
    "sg:city":"Sabadell",
    "sg:orig_category":"Procuradores",
    "sg:phone":"+34 937 23 08 48",
    "sg:postcode":"08208",
    "sg:province":"Barcelona",
    "wof:name":"Ribas Mercader Maria Dolores",
    "wof:placetype":"venue"
},
  "geometry": {"coordinates":[2.0991580486,41.5522117615],"type":"Point"}
}