{
  "type": "Feature",
  "properties": {
    "iso:country":"ES",
    "sg:address":"Calle de Nueva, 8",
    "sg:city":"Coslada",
    "sg:orig_category":"Procuradores",
    "sg:phone":"+34 916 73 29 15",
    "sg:postcode":"28820",
    "sg:province":"Madrid",
    "wof:name":"Reino Garcia Jose Francisco",
    "wof:placetype":"venue"
},
  "geometry": {"coordinates":[-3.5667800903,40.4256706238],"type":"Point"}
}