{
  "type": "Feature",
  "properties": {
    "addr:full":"Calle de Moreras, 2 Majadahonda Madrid 28220",
    "addr:housenumber":"2",
    "addr:postcode":"28220",
    "addr:street":"Calle De Moreras",
    "iso:country":"ES",
    "sg:address":"Calle de Moreras, 2",
    "sg:city":"Majadahonda",
    "sg:orig_category":"Bisuter\u00cda, Joyer\u00cda, Relojer\u00cda (al Por Menor)",
    "sg:phone":"+34 916 38 60 02",
    "sg:postcode":"28220",
    "sg:province":"Madrid",
    "wof:name":"Yague Dise\u00f1o S.l.",
    "wof:placetype":"venue"
},
  "geometry": {"coordinates":[-3.861030817,40.4593772888],"type":"Point"}
}