{
  "type": "Feature",
  "properties": {
    "addr:full":"Calle de Marques De Teverga, 10 Oviedo Asturias 33005",
    "addr:housenumber":"10",
    "addr:postcode":"33005",
    "addr:street":"Calle De Marques De Teverga",
    "iso:country":"ES",
    "sg:address":"Calle de Marques De Teverga, 10",
    "sg:city":"Oviedo",
    "sg:orig_category":"Abogados",
    "sg:phone":"+34 985 25 33 41",
    "sg:postcode":"33005",
    "sg:province":"Asturias",
    "wof:name":"Alvarez Fernandez-pe\u00f1a Jose Santiago",
    "wof:placetype":"venue"
},
  "geometry": {"coordinates":[-5.8556404114,43.3620376587],"type":"Point"}
}