{
  "type": "Feature",
  "properties": {
    "addr:full":"C/ Cronista Vicent Carbonell, 17 Alcoi Alicante 03802",
    "addr:housenumber":"17",
    "addr:postcode":"03802",
    "addr:street":"C / Cronista Vicent Carbonell",
    "iso:country":"ES",
    "sg:address":"C/ Cronista Vicent Carbonell, 17",
    "sg:city":"Alcoi",
    "sg:orig_category":"Hilaturas, Hilos Y Actividades Relacionadas",
    "sg:phone":"+34 965 52 59 69",
    "sg:postcode":"03802",
    "sg:province":"Alicante",
    "wof:name":"Filseda S. L.",
    "wof:placetype":"venue"
},
  "geometry": {"coordinates":[-0.4850428104,38.6982460022],"type":"Point"}
}