{
  "type": "Feature",
  "properties": {
    "addr:full":"Carr Maestro Giner, 31 Burjassot Valencia 46100",
    "addr:housenumber":"31",
    "addr:postcode":"46100",
    "addr:street":"Carr Maestro Giner",
    "iso:country":"ES",
    "sg:address":"Carr Maestro Giner, 31",
    "sg:city":"Burjassot",
    "sg:orig_category":"Cajas De Ahorro",
    "sg:phone":"+34 963 63 07 90",
    "sg:postcode":"46100",
    "sg:province":"Valencia",
    "sg:website":"www.bancaja.es",
    "wof:name":"Caja De Ahorros De Valencia Castellon Y Alicante",
    "wof:placetype":"venue"
},
  "geometry": {"coordinates":[-0.4099929929,39.5049324036],"type":"Point"}
}