{
  "type": "Feature",
  "properties": {
    "addr:full":"Cami Capellanets, 56 Mataro Barcelona 08303",
    "addr:housenumber":"56",
    "addr:postcode":"08303",
    "addr:street":"Capellanets",
    "iso:country":"ES",
    "sg:address":"Cami Capellanets, 56",
    "sg:city":"Mataro",
    "sg:orig_category":"Electricidad: Instalaciones Industriales",
    "sg:phone":"+34 937 41 51 10",
    "sg:postcode":"08303",
    "sg:province":"Barcelona",
    "wof:name":"Chepat S.l.",
    "wof:placetype":"venue"
},
  "geometry": {"coordinates":[2.426584959,41.5441322327],"type":"Point"}
}