{
  "type": "Feature",
  "properties": {
    "iso:country":"ES",
    "sg:address":"Pol Ind Son Llaut, 2",
    "sg:city":"Sta. Maria Cami",
    "sg:orig_category":"Productos Qu\u00cdmicos (fabricaci\u00d3n, Al Por Mayor)",
    "sg:phone":"+34 971 14 02 77",
    "sg:postcode":"07320",
    "sg:province":"Islas Baleares",
    "wof:name":"Sisinvert S.l.",
    "wof:placetype":"venue"
},
  "geometry": {"coordinates":[2.7729899883,39.6510467529],"type":"Point"}
}