{
  "type": "Feature",
  "properties": {
    "addr:full":"Carr Termens, S/n Vilanova Barca Lleida 25690",
    "addr:housenumber":"s",
    "addr:postcode":"25690",
    "addr:street":"Carr Termens;/ N",
    "iso:country":"ES",
    "sg:address":"Carr Termens, S/n",
    "sg:city":"Vilanova Barca",
    "sg:orig_category":"Agricultura: Abastecimiento Y Cosechado (negocio)",
    "sg:phone":"+34 973 19 11 25",
    "sg:postcode":"25690",
    "sg:province":"Lleida",
    "wof:name":"Verdu Sole Antonio",
    "wof:placetype":"venue"
},
  "geometry": {"coordinates":[0.7290250063,41.6892662048],"type":"Point"}
}