{
  "type": "Feature",
  "properties": {
    "iso:country":"ES",
    "sg:address":"Escorial, 4",
    "sg:city":"Ribeira-santa Uxia",
    "sg:orig_category":"Agentes Generales De Seguros",
    "sg:phone":"+34 981 87 25 55",
    "sg:postcode":"15960",
    "sg:province":"La Coru\u00f1a",
    "wof:name":"Sampedro Y Tato S.l",
    "wof:placetype":"venue"
},
  "geometry": {"coordinates":[-8.9932403564,42.555847168],"type":"Point"}
}