{
  "type": "Feature",
  "properties": {
    "addr:full":"Carr Industria, 2 S. Guim Freixenet Lleida 25270",
    "addr:housenumber":"2",
    "addr:postcode":"25270",
    "addr:street":"Carr Industria",
    "iso:country":"ES",
    "sg:address":"Carr Industria, 2",
    "sg:city":"S. Guim Freixenet",
    "sg:orig_category":"Empresas De Pintura Y Revestimientos",
    "sg:phone":"+34 973 55 62 58",
    "sg:postcode":"25270",
    "sg:province":"Lleida",
    "wof:name":"Pareta Arbat Juan",
    "wof:placetype":"venue"
},
  "geometry": {"coordinates":[1.3964250088,41.6603088379],"type":"Point"}
}