{
  "type": "Feature",
  "properties": {
    "iso:country":"ES",
    "sg:address":"Av Port, Del, 10",
    "sg:city":"Grao",
    "sg:orig_category":"Fabricaci\u00d3n De Enlosados, Soler\u00cdas",
    "sg:phone":"+34 964 58 05 45",
    "sg:postcode":"12593",
    "sg:province":"Castell\u00f3n",
    "wof:name":"Keramik & Logistik S.l.",
    "wof:placetype":"venue"
},
  "geometry": {"coordinates":[-0.1429889947,39.8067741394],"type":"Point"}
}