{
  "type": "Feature",
  "properties": {
    "addr:full":"Calle de Santa Aurea, 2 Madrid Madrid 28011",
    "addr:housenumber":"2",
    "addr:postcode":"28011",
    "addr:street":"Calle De Santa Aurea",
    "iso:country":"ES",
    "sg:address":"Calle de Santa Aurea, 2",
    "sg:city":"Madrid",
    "sg:orig_category":"Estancos",
    "sg:phone":"+34 914 64 99 92",
    "sg:postcode":"28011",
    "sg:province":"Madrid",
    "wof:name":"Gutierrez Rovira Yolanda",
    "wof:placetype":"venue"
},
  "geometry": {"coordinates":[-3.7350289822,40.4073295593],"type":"Point"}
}