{
  "type": "Feature",
  "properties": {
    "iso:country":"ES",
    "sg:address":"Calle de Ermita (la), 7",
    "sg:city":"Azuqueca Henares",
    "sg:orig_category":"Agencias Y Asesores De Publicidad",
    "sg:phone":"+34 949 26 24 97",
    "sg:postcode":"19200",
    "sg:province":"Guadalajara",
    "wof:name":"Promogu 2000 S.l.",
    "wof:placetype":"venue"
},
  "geometry": {"coordinates":[-3.2629988194,40.5700798035],"type":"Point"}
}