{
  "type": "Feature",
  "properties": {
    "iso:country":"ES",
    "sg:address":"Calle de Aramayona, 3",
    "sg:city":"Madrid",
    "sg:orig_category":"Asesor\u00cda, Estudio Y Control Medioambiental",
    "sg:phone":"+34 917 47 65 36",
    "sg:postcode":"28022",
    "sg:province":"Madrid",
    "wof:name":"Gepma Consultores Y Asesores S.l",
    "wof:placetype":"venue"
},
  "geometry": {"coordinates":[-3.578099966,40.4442100525],"type":"Point"}
}