{
  "type": "Feature",
  "properties": {
    "addr:full":"Calle Francisco Jose Arroyo, 6 Madrid 28042",
    "addr:housenumber":"6",
    "addr:postcode":"28042",
    "addr:street":"Calle Francisco Jose Arroyo",
    "iso:country":"ES",
    "sg:address":"Calle Francisco Jose Arroyo, 6",
    "sg:city":"Madrid",
    "sg:classifiers":[
        {
            "category":"Professional",
            "subcategory":"Computer Services",
            "type":"Services"
        }
    ],
    "sg:postcode":"28042",
    "sg:tags":[
        "travel"
    ],
    "sg:website":"http://www.cost4travel.com",
    "wof:name":"cost4travel",
    "wof:placetype":"venue"
},
  "geometry": {"coordinates":[-3.6149394,40.4528711],"type":"Point"}
}