{
  "type": "Feature",
  "properties": {
    "iso:country":"ES",
    "sg:address":"Calle de Camarena, 111",
    "sg:city":"Madrid",
    "sg:orig_category":"Peleter\u00cdas",
    "sg:phone":"+34 917 18 13 43",
    "sg:postcode":"28047",
    "sg:province":"Madrid",
    "sg:website":"www.carbajopiel.es",
    "wof:name":"Carbajo Campesino Victoriano",
    "wof:placetype":"venue"
},
  "geometry": {"coordinates":[-3.7556920052,40.3919563293],"type":"Point"}
}