{
  "type": "Feature",
  "properties": {
    "iso:country":"ES",
    "sg:address":"Calle de Castrillo De Aza, 16",
    "sg:city":"Madrid",
    "sg:orig_category":"Empresas De Carpinter\u00cda",
    "sg:phone":"+34 913 31 09 81",
    "sg:postcode":"28031",
    "sg:province":"Madrid",
    "wof:name":"Morato Cobe\u00f1a Jose",
    "wof:placetype":"venue"
},
  "geometry": {"coordinates":[-3.6093018055,40.3845062256],"type":"Point"}
}