{
  "type": "Feature",
  "properties": {
    "iso:country":"ES",
    "sg:address":"Carrer de Pare Palau (del), 7",
    "sg:city":"Tarragona",
    "sg:orig_category":"M\u00c9dicos: Neumolog\u00cda",
    "sg:phone":"+34 977 21 14 26",
    "sg:postcode":"43001",
    "sg:province":"Tarragona",
    "wof:name":"Alergo-res S.l.",
    "wof:placetype":"venue"
},
  "geometry": {"coordinates":[1.2463040352,41.1175079346],"type":"Point"}
}