{
  "type": "Feature",
  "properties": {
    "addr:full":"Ctra. Estacion, 78 Posada Asturias 33594",
    "addr:housenumber":"78",
    "addr:postcode":"33594",
    "addr:street":"Ctra. Estacion",
    "iso:country":"ES",
    "sg:address":"Ctra. Estacion, 78",
    "sg:city":"Posada",
    "sg:orig_category":"Transportes Ferroviarios",
    "sg:phone":"+34 985 40 79 82",
    "sg:postcode":"33594",
    "sg:province":"Asturias",
    "wof:name":"Ferrocarriles Espa\u00f1oles De Via Estrecha",
    "wof:placetype":"venue"
},
  "geometry": {"coordinates":[-4.8618822098,43.4186553955],"type":"Point"}
}