{
  "type": "Feature",
  "properties": {
    "addr:full":"Calle de Almacigo, S/n Paz Santa Cruz De Tenerife 38400",
    "addr:housenumber":"s / n",
    "addr:postcode":"38400",
    "addr:street":"Calle De Almacigo",
    "iso:country":"ES",
    "sg:address":"Calle de Almacigo, S/n",
    "sg:city":"Paz",
    "sg:orig_category":"Cl\u00cdnicas Dentales",
    "sg:phone":"+34 922 37 05 42",
    "sg:postcode":"38400",
    "sg:province":"Santa Cruz De Tenerife",
    "wof:name":"Muller-lehmann  Volker",
    "wof:placetype":"venue"
},
  "geometry": {"coordinates":[-16.2548561096,28.4698104858],"type":"Point"}
}