{
  "type": "Feature",
  "properties": {
    "addr:full":"Calle de Manuel Escabias, 4 Martos Ja\u00e9n 23600",
    "addr:housenumber":"4",
    "addr:postcode":"23600",
    "addr:street":"Calle De Manuel Escabias;Jae\u0301N",
    "iso:country":"ES",
    "sg:address":"Calle de Manuel Escabias, 4",
    "sg:city":"Martos",
    "sg:orig_category":"Profesiones M\u00c9dicas, Param\u00c9dicas",
    "sg:phone":"+34 953 70 07 47",
    "sg:postcode":"23600",
    "sg:province":"Ja\u00e9n",
    "wof:name":"Aceituno Carrasco Angel",
    "wof:placetype":"venue"
},
  "geometry": {"coordinates":[-3.9731738567,37.718006134],"type":"Point"}
}