{
  "type": "Feature",
  "properties": {
    "iso:country":"ES",
    "sg:address":"Avda Fontes, 13",
    "sg:city":"Torre-pacheco",
    "sg:orig_category":"Supermercados Y Hipermercados",
    "sg:phone":"+34 968 57 81 29",
    "sg:postcode":"30700",
    "sg:province":"Murcia",
    "wof:name":"Hermanas Mero\u00f1o C.b.",
    "wof:placetype":"venue"
},
  "geometry": {"coordinates":[-1.1302490234,37.9829597473],"type":"Point"}
}