{
  "type": "Feature",
  "properties": {
    "addr:full":"Calle de Mochas, 27 Vallelado Segovia 40213",
    "addr:housenumber":"27",
    "addr:postcode":"40213",
    "addr:street":"Calle De Mochas;Segovia",
    "iso:country":"ES",
    "sg:address":"Calle de Mochas, 27",
    "sg:city":"Vallelado",
    "sg:orig_category":"Cerrajer\u00cda, Ferrallista",
    "sg:phone":"+34 921 15 01 26",
    "sg:postcode":"40213",
    "sg:province":"Segovia",
    "wof:name":"Talleres Govi S.l.",
    "wof:placetype":"venue"
},
  "geometry": {"coordinates":[-4.4336290359,41.4068603516],"type":"Point"}
}