{
  "type": "Feature",
  "properties": {
    "addr:full":"Calle de Monteleon, 14 Madrid Madrid 28004",
    "addr:housenumber":"14",
    "addr:postcode":"madrid;28004",
    "addr:street":"Calle De Monteleon",
    "iso:country":"ES",
    "sg:address":"Calle de Monteleon, 14",
    "sg:city":"Madrid",
    "sg:orig_category":"Venta, Alquiler De Instrumentos Y Accesorios De M\u00dasica",
    "sg:phone":"+34 914 46 18 90",
    "sg:postcode":"28004",
    "sg:province":"Madrid",
    "wof:name":"Benito Aguado Angel",
    "wof:placetype":"venue"
},
  "geometry": {"coordinates":[-3.7048199177,40.4280166626],"type":"Point"}
}