{
  "type": "Feature",
  "properties": {
    "iso:country":"ES",
    "sg:address":"Calle de Porto Cristo, 8",
    "sg:city":"Alcorcon",
    "sg:orig_category":"Fabricaci\u00d3n De Mantequilla (al Por Mayor)",
    "sg:phone":"+34 916 11 87 99",
    "sg:postcode":"28924",
    "sg:province":"Madrid",
    "wof:name":"Gonzalez Molina Antonio",
    "wof:placetype":"venue"
},
  "geometry": {"coordinates":[-3.8168098927,40.3507041931],"type":"Point"}
}