{
  "type": "Feature",
  "properties": {
    "addr:full":"Calle de Biznaga, 45 Malaga M\u00e1laga 29017",
    "addr:housenumber":"45",
    "addr:postcode":"29017",
    "addr:street":"Calle De Biznaga;Ma\u0301Laga",
    "iso:country":"ES",
    "sg:address":"Calle de Biznaga, 45",
    "sg:city":"Malaga",
    "sg:orig_category":"Conservas De Pescados Y Salazones Mar\u00cdtimos (fabricaci\u00d3n, Al Por Mayor)",
    "sg:phone":"+34 952 29 01 97",
    "sg:postcode":"29017",
    "sg:province":"M\u00e1laga",
    "wof:name":"Acosta Navas Jose",
    "wof:placetype":"venue"
},
  "geometry": {"coordinates":[-4.3605904579,36.71925354],"type":"Point"}
}