{
  "type": "Feature",
  "properties": {
    "iso:country":"ES",
    "sg:address":"Carrer de Vallespir, 168",
    "sg:city":"Barcelona",
    "sg:orig_category":"Cine (producci\u00d3n, Realizaci\u00d3n)",
    "sg:phone":"+34 934 90 02 10",
    "sg:postcode":"08014",
    "sg:province":"Barcelona",
    "sg:website":"www.animados.com",
    "wof:name":"Animandus S.l.",
    "wof:placetype":"venue"
},
  "geometry": {"coordinates":[2.1344773769,41.3833198547],"type":"Point"}
}