{
  "type": "Feature",
  "properties": {
    "iso:country":"ES",
    "sg:address":"Calle de Callejon De Los Frailes, 8",
    "sg:city":"Cieza",
    "sg:orig_category":"Agencias De Viajes",
    "sg:phone":"+34 968 45 63 32",
    "sg:postcode":"30530",
    "sg:province":"Murcia",
    "wof:name":"Hobby Viajes S.l.",
    "wof:placetype":"venue"
},
  "geometry": {"coordinates":[-1.4230436087,38.2376937866],"type":"Point"}
}