{
  "type": "Feature",
  "properties": {
    "iso:country":"ES",
    "sg:address":"Carr San Fernando, 26",
    "sg:city":"Mao",
    "sg:orig_category":"Arquitectos",
    "sg:phone":"+34 971 35 47 20",
    "sg:postcode":"07702",
    "sg:province":"Islas Baleares",
    "wof:name":"Aru Arquitectura S.l.",
    "wof:placetype":"venue"
},
  "geometry": {"coordinates":[4.2666373253,39.8871002197],"type":"Point"}
}