{
  "type": "Feature",
  "properties": {
    "iso:country":"ES",
    "sg:address":"Rua Ribadavia (de), 1",
    "sg:city":"Carballi\u00f1o",
    "sg:orig_category":"Lavado, Limpieza De Veh\u00cdculos",
    "sg:phone":"+34 988 27 05 06",
    "sg:postcode":"32500",
    "sg:province":"Ourense",
    "wof:name":"Mosquera Gonzalez Hermenegildo",
    "wof:placetype":"venue"
},
  "geometry": {"coordinates":[-8.0796108246,42.4280891418],"type":"Point"}
}