{
  "type": "Feature",
  "properties": {
    "addr:full":"Calle de Quevedo, 7 Priego Cordoba C\u00f3rdoba 14800",
    "addr:housenumber":"7",
    "addr:postcode":"14800",
    "addr:street":"Calle De Quevedo;Cordoba Co\u0301Rdoba",
    "iso:country":"ES",
    "sg:address":"Calle de Quevedo, 7",
    "sg:city":"Priego Cordoba",
    "sg:orig_category":"Electricidad: Instaladores",
    "sg:phone":"+34 957 54 27 44",
    "sg:postcode":"14800",
    "sg:province":"C\u00f3rdoba",
    "wof:name":"Montajes Electricos Julio S.l.",
    "wof:placetype":"venue"
},
  "geometry": {"coordinates":[-4.1971421242,37.4415283203],"type":"Point"}
}