{
  "type": "Feature",
  "properties": {
    "addr:full":"Avda Presidente Carmona, 10 Madrid Madrid 28020",
    "addr:housenumber":"10",
    "addr:postcode":"madrid;28020",
    "addr:street":"Avda Presidente Carmona",
    "iso:country":"ES",
    "sg:address":"Avda Presidente Carmona, 10",
    "sg:city":"Madrid",
    "sg:orig_category":"Agencias Y Asesores De Publicidad",
    "sg:phone":"+34 915 79 69 59",
    "sg:postcode":"28020",
    "sg:province":"Madrid",
    "wof:name":"Imaging Comunicacion Visual S.l.",
    "wof:placetype":"venue"
},
  "geometry": {"coordinates":[-3.696876049,40.4542655945],"type":"Point"}
}