{
  "type": "Feature",
  "properties": {
    "addr:full":"Avgd Del Cami Nou, 252 Xirivella Valencia 46950",
    "addr:housenumber":"252",
    "addr:postcode":"46950",
    "addr:street":"Nou",
    "iso:country":"ES",
    "sg:address":"Avgd Del Cami Nou, 252",
    "sg:city":"Xirivella",
    "sg:orig_category":"Comercio De Hierro",
    "sg:phone":"+34 963 83 44 35",
    "sg:postcode":"46950",
    "sg:province":"Valencia",
    "wof:name":"Fundiciones Del Turia S.l.",
    "wof:placetype":"venue"
},
  "geometry": {"coordinates":[-0.4416710138,39.4616928101],"type":"Point"}
}