{
  "type": "Feature",
  "properties": {
    "addr:full":"Carrer de Girona, 84 Sabadell Barcelona 08202",
    "addr:housenumber":"84",
    "addr:postcode":"08202",
    "addr:street":"Carrer De Girona",
    "iso:country":"ES",
    "sg:address":"Carrer de Girona, 84",
    "sg:city":"Sabadell",
    "sg:orig_category":"Publicidad (soportes Y Gesti\u00d3n)",
    "sg:phone":"+34 937 10 98 01",
    "sg:postcode":"08202",
    "sg:province":"Barcelona",
    "sg:website":"www.crealfa.com",
    "wof:name":"Crealfa S.l.",
    "wof:placetype":"venue"
},
  "geometry": {"coordinates":[2.1079640388,41.5359764099],"type":"Point"}
}