{
  "type": "Feature",
  "properties": {
    "iso:country":"ES",
    "sg:address":"Calle de Eraso, 14",
    "sg:city":"Madrid",
    "sg:orig_category":"Mercados De Productos Alimenticios",
    "sg:phone":"+34 913 56 84 79",
    "sg:postcode":"28028",
    "sg:province":"Madrid",
    "wof:name":"Mercado De La Guindalera",
    "wof:placetype":"venue"
},
  "geometry": {"coordinates":[-3.6709589958,40.4340515137],"type":"Point"}
}