{
  "type": "Feature",
  "properties": {
    "addr:full":"Calle de Real, S/n Tejares Segovia 40314",
    "addr:housenumber":"s / n",
    "addr:postcode":"40314",
    "addr:street":"Calle De Real",
    "iso:country":"ES",
    "sg:address":"Calle de Real, S/n",
    "sg:city":"Tejares",
    "sg:orig_category":"Cr\u00cda De Animales",
    "sg:phone":"+34 921 53 31 10",
    "sg:postcode":"40314",
    "sg:province":"Segovia",
    "wof:name":"Sat 322-hermanos Chico",
    "wof:placetype":"venue"
},
  "geometry": {"coordinates":[-3.9077880383,41.4281349182],"type":"Point"}
}