{
  "type": "Feature",
  "properties": {
    "iso:country":"ES",
    "sg:address":"Calle de Sur, 2",
    "sg:city":"Moraleja Enmedio",
    "sg:orig_category":"Fabricaci\u00d3n De Moldes Y Modelos",
    "sg:phone":"+34 916 09 31 62",
    "sg:postcode":"28950",
    "sg:province":"Madrid",
    "wof:name":"Olmedo Tejedor Javier",
    "wof:placetype":"venue"
},
  "geometry": {"coordinates":[-3.8486778736,40.2644691467],"type":"Point"}
}