{
  "type": "Feature",
  "properties": {
    "addr:full":"Avda Valencia, Km. 0063,2 Castellon Castell\u00f3n 12006",
    "addr:postcode":"12006",
    "addr:street":"Avda Valencia Km. 0063,2 Castellon Castello\u0301N",
    "iso:country":"ES",
    "sg:address":"Avda Valencia, Km. 0063,2",
    "sg:city":"Castellon",
    "sg:orig_category":"Almacenes Frigor\u00cdficos",
    "sg:phone":"+34 964 21 49 85",
    "sg:postcode":"12006",
    "sg:province":"Castell\u00f3n",
    "wof:name":"Frutas Francisco S.l.",
    "wof:placetype":"venue"
},
  "geometry": {"coordinates":[-0.1292939931,40.0168533325],"type":"Point"}
}