{
  "type": "Feature",
  "properties": {
    "iso:country":"ES",
    "sg:address":"Calle de San David, 8",
    "sg:city":"Madrid",
    "sg:orig_category":"Prot\u00c9sicos Dentales",
    "sg:phone":"+34 914 60 19 70",
    "sg:postcode":"28019",
    "sg:province":"Madrid",
    "wof:name":"H. G. Dental C.b.",
    "wof:placetype":"venue"
},
  "geometry": {"coordinates":[-3.7072770596,40.3943710327],"type":"Point"}
}