{
  "type": "Feature",
  "properties": {
    "addr:full":"Calle de Mingo Ramos, 8 Trujillo C\u00e1ceres 10200",
    "addr:housenumber":"8",
    "addr:postcode":"10200",
    "addr:street":"Calle De Mingo Ramos;Ca\u0301Ceres",
    "iso:country":"ES",
    "sg:address":"Calle de Mingo Ramos, 8",
    "sg:city":"Trujillo",
    "sg:orig_category":"Arquitectos",
    "sg:phone":"+34 927 32 28 28",
    "sg:postcode":"10200",
    "sg:province":"C\u00e1ceres",
    "wof:name":"Diz Plaza Javier Maria",
    "wof:placetype":"venue"
},
  "geometry": {"coordinates":[-5.8804340363,39.4607620239],"type":"Point"}
}