{
  "type": "Feature",
  "properties": {
    "addr:full":"Plaza De Onesimo Redondo, 6 Guadix Granada 18500",
    "addr:housenumber":"6",
    "addr:postcode":"18500",
    "addr:street":"Redondo",
    "iso:country":"ES",
    "sg:address":"Plaza De Onesimo Redondo, 6",
    "sg:city":"Guadix",
    "sg:orig_category":"Panader\u00cdas, Panader\u00cdas",
    "sg:phone":"+34 958 66 05 07",
    "sg:postcode":"18500",
    "sg:province":"Granada",
    "wof:name":"Confiteria La Oriental S.l.",
    "wof:placetype":"venue"
},
  "geometry": {"coordinates":[-3.1343688965,37.303894043],"type":"Point"}
}