{
  "type": "Feature",
  "properties": {
    "iso:country":"ES",
    "sg:address":"Calle de San Francisco, 1",
    "sg:city":"Tafalla",
    "sg:orig_category":"Carnicer\u00cdas, Carnicer\u00cdas",
    "sg:phone":"+34 948 70 31 49",
    "sg:postcode":"31300",
    "sg:province":"Navarra",
    "wof:name":"Carniceria Luis S.cv.",
    "wof:placetype":"venue"
},
  "geometry": {"coordinates":[-1.6788510084,42.5243148804],"type":"Point"}
}