{
  "type": "Feature",
  "properties": {
    "iso:country":"ES",
    "sg:address":"Paseo San Cristobal, S/n",
    "sg:city":"Almu\u00f1ecar",
    "sg:orig_category":"Alquiler De Veh\u00cdculos: Turismos Y Utilitarios",
    "sg:phone":"+34 958 63 33 96",
    "sg:postcode":"18690",
    "sg:province":"Granada",
    "sg:website":"www.crowncarhire.com",
    "wof:name":"Aurigacrown Car Hire S.l.",
    "wof:placetype":"venue"
},
  "geometry": {"coordinates":[-3.7025830746,36.7340774536],"type":"Point"}
}