{
  "type": "Feature",
  "properties": {
    "iso:country":"ES",
    "sg:address":"Calle de Pelay Correa, 48",
    "sg:city":"Sevilla",
    "sg:orig_category":"Asociaciones Y Clubs Deportivos",
    "sg:phone":"+34 954 28 08 87",
    "sg:postcode":"41010",
    "sg:province":"Sevilla",
    "wof:name":"Lopez Fernandez Pedro",
    "wof:placetype":"venue"
},
  "geometry": {"coordinates":[-6.0004038811,37.3822135925],"type":"Point"}
}