{
  "type": "Feature",
  "properties": {
    "addr:full":"Ctra. Villaca\u00f1as, S/n Puebla Almoradiel Toledo 45840",
    "addr:housenumber":"s",
    "addr:postcode":"45840",
    "addr:street":"Ctra. Villacan\u0303As;/ N",
    "iso:country":"ES",
    "sg:address":"Ctra. Villaca\u00f1as, S/n",
    "sg:city":"Puebla Almoradiel",
    "sg:orig_category":"Productores Recolectores, Venta Directa De Vinos",
    "sg:phone":"+34 925 17 84 32",
    "sg:postcode":"45840",
    "sg:province":"Toledo",
    "wof:name":"Alcoholera De La Puebla S. A.",
    "wof:placetype":"venue"
},
  "geometry": {"coordinates":[-3.107858181,39.5417900085],"type":"Point"}
}