{
  "type": "Feature",
  "properties": {
    "iso:country":"ES",
    "sg:address":"Avda Judimendi, S/n",
    "sg:city":"Vitoria-gasteiz",
    "sg:orig_category":"Centros De Educaci\u00d3n Especial",
    "sg:phone":"+34 945 25 45 57",
    "sg:postcode":"01003",
    "sg:province":"\u00c1lava",
    "wof:name":"Colegio Judimendi-ayuntamiento",
    "wof:placetype":"venue"
},
  "geometry": {"coordinates":[-2.6613540649,42.8479309082],"type":"Point"}
}