{
  "type": "Feature",
  "properties": {
    "addr:full":"Carr Rosas (de Las), 23 Manises Valencia 46940",
    "addr:housenumber":"23",
    "addr:postcode":"46940",
    "addr:street":"Carr Rosas De Las",
    "iso:country":"ES",
    "sg:address":"Carr Rosas (de Las), 23",
    "sg:city":"Manises",
    "sg:orig_category":"Servicio De Salud",
    "sg:phone":"+34 961 54 03 79",
    "sg:postcode":"46940",
    "sg:province":"Valencia",
    "wof:name":"Aquasilk S.l.",
    "wof:placetype":"venue"
},
  "geometry": {"coordinates":[-0.4654910862,39.49193573],"type":"Point"}
}