{
  "type": "Feature",
  "properties": {
    "addr:full":"Carrer de Transversal, 33 Terrassa Barcelona 08225",
    "addr:housenumber":"33",
    "addr:postcode":"08225",
    "addr:street":"Carrer De Transversal",
    "iso:country":"ES",
    "sg:address":"Carrer de Transversal, 33",
    "sg:city":"Terrassa",
    "sg:orig_category":"M\u00c9dicos: Medicina General Orientada A La Acupuntura",
    "sg:phone":"+34 937 88 04 46",
    "sg:postcode":"08225",
    "sg:province":"Barcelona",
    "wof:name":"Choi Jung Myung-ho",
    "wof:placetype":"venue"
},
  "geometry": {"coordinates":[2.0043289661,41.5718612671],"type":"Point"}
}