{
  "type": "Feature",
  "properties": {
    "addr:full":"Calle de Teobaldo Power, 27 Santa Cruz De Tenerife Santa Cruz De Tenerife 38002",
    "addr:housenumber":"27",
    "addr:postcode":"38002",
    "addr:street":"Calle De Teobaldo Power",
    "iso:country":"ES",
    "sg:address":"Calle de Teobaldo Power, 27",
    "sg:city":"Santa Cruz De Tenerife",
    "sg:orig_category":"Ropa Para Ni\u00d1os (al Por Menor)",
    "sg:phone":"+34 922 24 58 16",
    "sg:postcode":"38002",
    "sg:province":"Santa Cruz De Tenerife",
    "wof:name":"Santos Perez Francisco",
    "wof:placetype":"venue"
},
  "geometry": {"coordinates":[-16.2515716553,28.4686965942],"type":"Point"}
}