{
  "type": "Feature",
  "properties": {
    "iso:country":"ES",
    "sg:address":"Calle de Rio Duero, 29",
    "sg:city":"Zaragoza",
    "sg:orig_category":"Asociaciones, Organismos Culturales Y Socioeducativos",
    "sg:phone":"+34 976 43 97 92",
    "sg:postcode":"50003",
    "sg:province":"Zaragoza",
    "wof:name":"Pe\u00f1a Forca",
    "wof:placetype":"venue"
},
  "geometry": {"coordinates":[-0.8985700011,41.6601142883],"type":"Point"}
}