{
  "type": "Feature",
  "properties": {
    "iso:country":"ES",
    "sg:address":"Calle de Blas De Otero, 15",
    "sg:city":"Albolote",
    "sg:orig_category":"Tapiceros Y Tapiceros",
    "sg:phone":"+34 958 46 72 68",
    "sg:postcode":"18220",
    "sg:province":"Granada",
    "wof:name":"Perez Romero Salvador",
    "wof:placetype":"venue"
},
  "geometry": {"coordinates":[-3.6530678272,37.2310142517],"type":"Point"}
}