{
  "type": "Feature",
  "properties": {
    "iso:country":"ES",
    "sg:address":"General Morales, 3",
    "sg:city":"Arjona",
    "sg:orig_category":"Supermercados Y Hipermercados",
    "sg:phone":"+34 953 51 81 97",
    "sg:postcode":"23760",
    "sg:province":"Ja\u00e9n",
    "wof:name":"Lara Garrido Diego",
    "wof:placetype":"venue"
},
  "geometry": {"coordinates":[-4.0537171364,37.9367904663],"type":"Point"}
}