{
  "type": "Feature",
  "properties": {
    "addr:full":"Kardaberaz Kalea, 39 Hernani Guip\u00f9zcoa 20120",
    "addr:housenumber":"39",
    "addr:postcode":"20120",
    "addr:street":"Kardaberaz Kalea;Guipu\u0300Zcoa",
    "iso:country":"ES",
    "sg:address":"Kardaberaz Kalea, 39",
    "sg:city":"Hernani",
    "sg:orig_category":"Carnicer\u00cdas, Carnicer\u00cdas",
    "sg:phone":"+34 943 55 27 87",
    "sg:postcode":"20120",
    "sg:province":"Guip\u00f9zcoa",
    "wof:name":"Putzueta Arategia S.l.",
    "wof:placetype":"venue"
},
  "geometry": {"coordinates":[-1.9744490385,43.2659378052],"type":"Point"}
}