{
  "type": "Feature",
  "properties": {
    "addr:full":"Avda Escolares (los), 1 Pulpi Almer\u00eda 04640",
    "addr:housenumber":"1",
    "addr:postcode":"04640",
    "addr:street":"Avda Escolares Los;Almeri\u0301A",
    "iso:country":"ES",
    "sg:address":"Avda Escolares (los), 1",
    "sg:city":"Pulpi",
    "sg:orig_category":"Cajas De Ahorro",
    "sg:phone":"+34 950 46 40 91",
    "sg:postcode":"04640",
    "sg:province":"Almer\u00eda",
    "sg:website":"www",
    "wof:name":"Cajagranada",
    "wof:placetype":"venue"
},
  "geometry": {"coordinates":[-1.7443929911,37.4112548828],"type":"Point"}
}