{
  "type": "Feature",
  "properties": {
    "iso:country":"ES",
    "sg:address":"Avda Agirre Lehendakaria, 48",
    "sg:city":"Basauri",
    "sg:orig_category":"Molduras, Junquillos, Listones Y Molduras Perforadas",
    "sg:phone":"+34 944 40 37 68",
    "sg:postcode":"48970",
    "sg:province":"Vizcaya",
    "wof:name":"Francisco Martin Gomez",
    "wof:placetype":"venue"
},
  "geometry": {"coordinates":[-2.8858420849,43.2369804382],"type":"Point"}
}