{
  "type": "Feature",
  "properties": {
    "addr:full":"Calle de Ahillones, S/n Madrid Madrid 28033",
    "addr:housenumber":"s / n",
    "addr:postcode":"28033",
    "addr:street":"Calle De Ahillones",
    "iso:country":"ES",
    "sg:address":"Calle de Ahillones, S/n",
    "sg:city":"Madrid",
    "sg:orig_category":"Frutas, Legumbres Frescas Y Tempranas (al Por Menor)",
    "sg:phone":"+34 917 63 11 76",
    "sg:postcode":"28033",
    "sg:province":"Madrid",
    "wof:name":"Solana Zuara Jose",
    "wof:placetype":"venue"
},
  "geometry": {"coordinates":[-3.6474285126,40.4759635925],"type":"Point"}
}