{
  "type": "Feature",
  "properties": {
    "iso:country":"ES",
    "sg:address":"Calle de Padre Marchena, 1",
    "sg:city":"Huelva",
    "sg:orig_category":"Diet\u00c9tica: Productos Biol\u00d3gicos, Naturales Y Diet\u00c9ticos (fabricaci\u00d3n, Al Por Mayor)",
    "sg:phone":"+34 959 24 91 13",
    "sg:postcode":"21003",
    "sg:province":"Huelva",
    "wof:name":"Cnv S.l.",
    "wof:placetype":"venue"
},
  "geometry": {"coordinates":[-6.946914196,37.2554359436],"type":"Point"}
}