{
  "type": "Feature",
  "properties": {
    "addr:full":"Calle de Mayor, S/n Tortola De Henares Guadalajara 19198",
    "addr:housenumber":"s",
    "addr:postcode":"19198",
    "addr:street":"Calle De Mayor;/ N Tortola",
    "iso:country":"ES",
    "sg:address":"Calle de Mayor, S/n",
    "sg:city":"Tortola De Henares",
    "sg:orig_category":"Promotores Constructores",
    "sg:phone":"+34 949 32 30 23",
    "sg:postcode":"19198",
    "sg:province":"Guadalajara",
    "wof:name":"Marcos Barahona Antonio",
    "wof:placetype":"venue"
},
  "geometry": {"coordinates":[-3.123404026,40.7059516907],"type":"Point"}
}