{
  "type": "Feature",
  "properties": {
    "addr:full":"Calle de Simon Ortiz, 6 Valencia Valencia 46008",
    "addr:housenumber":"6",
    "addr:postcode":"46008",
    "addr:street":"Calle De Simon Ortiz",
    "iso:country":"ES",
    "sg:address":"Calle de Simon Ortiz, 6",
    "sg:city":"Valencia",
    "sg:orig_category":"Publicidad (soportes Y Gesti\u00d3n)",
    "sg:phone":"+34 963 91 16 04",
    "sg:postcode":"46008",
    "sg:province":"Valencia",
    "sg:website":"www.ayllon.com",
    "wof:name":"Rotulos Ayllon S. A.",
    "wof:placetype":"venue"
},
  "geometry": {"coordinates":[-0.386285007,39.4729614258],"type":"Point"}
}