{
  "type": "Feature",
  "properties": {
    "addr:full":"Calle de San Francisco, 4 Molina Guadalajara 19300",
    "addr:housenumber":"4",
    "addr:postcode":"19300",
    "addr:street":"Calle De San Francisco",
    "iso:country":"ES",
    "sg:address":"Calle de San Francisco, 4",
    "sg:city":"Molina",
    "sg:orig_category":"Hormig\u00d3n Listo Para Usar",
    "sg:phone":"+34 949 83 16 97",
    "sg:postcode":"19300",
    "sg:province":"Guadalajara",
    "wof:name":"Carrasco Ibar Vidal",
    "wof:placetype":"venue"
},
  "geometry": {"coordinates":[-1.887673974,40.8431777954],"type":"Point"}
}