{
  "type": "Feature",
  "properties": {
    "addr:full":"Carrer de Nord, 78 Esplugues Llobregat Barcelona 08950",
    "addr:housenumber":"78",
    "addr:postcode":"08950",
    "addr:street":"Carrer De Nord",
    "iso:country":"ES",
    "sg:address":"Carrer de Nord, 78",
    "sg:city":"Esplugues Llobregat",
    "sg:orig_category":"Inform\u00c1tica: Mantenimiento Y Reparaci\u00d3n De Ordenadores",
    "sg:phone":"+34 902 12 03 14",
    "sg:postcode":"08950",
    "sg:province":"Barcelona",
    "sg:website":"www.soportemv.com",
    "wof:name":"Ampoc Espa\u00d1a S.a.",
    "wof:placetype":"venue"
},
  "geometry": {"coordinates":[2.081818819,41.3805732727],"type":"Point"}
}