{
  "type": "Feature",
  "properties": {
    "iso:country":"ES",
    "sg:address":"Calle de Merindades (las), 20",
    "sg:city":"Castejon",
    "sg:orig_category":"Farmacias",
    "sg:phone":"+34 948 81 43 52",
    "sg:postcode":"31590",
    "sg:province":"Navarra",
    "wof:name":"Solana Belloso Maria Rosario",
    "wof:placetype":"venue"
},
  "geometry": {"coordinates":[-1.6919491291,42.170211792],"type":"Point"}
}