{
  "type": "Feature",
  "properties": {
    "iso:country":"ES",
    "sg:address":"Calle de Pablo Iglesias, 112",
    "sg:city":"Elda",
    "sg:orig_category":"Agencias Y Asesores De Publicidad",
    "sg:phone":"+34 965 38 19 65",
    "sg:postcode":"03600",
    "sg:province":"Alicante",
    "wof:name":"Fernandez Beltra Felipe Jaime",
    "wof:placetype":"venue"
},
  "geometry": {"coordinates":[-0.7947000265,38.4744796753],"type":"Point"}
}