{
  "type": "Feature",
  "properties": {
    "addr:full":"Calle de Teniente General Gonzalez Del Yerro, 1 Monta\u00e7a Tenisca Santa Cruz De Tenerife 38760",
    "addr:housenumber":"1",
    "addr:postcode":"38760",
    "addr:street":"Calle De Teniente General Gonzalez Del Yerro",
    "iso:country":"ES",
    "sg:address":"Calle de Teniente General Gonzalez Del Yerro, 1",
    "sg:city":"Monta\u00e7a Tenisca",
    "sg:orig_category":"M\u00c9dicos: Medicina General Orientada A La Acupuntura",
    "sg:phone":"+34 922 40 18 50",
    "sg:postcode":"38760",
    "sg:province":"Santa Cruz De Tenerife",
    "wof:name":"Garcia Gonzalez Bruno",
    "wof:placetype":"venue"
},
  "geometry": {"coordinates":[-17.9139709473,28.6572132111],"type":"Point"}
}