{
  "type": "Feature",
  "properties": {
    "addr:full":"Calle de Narvaez, 58 Madrid Madrid 28009",
    "addr:housenumber":"58",
    "addr:postcode":"madrid;28009",
    "addr:street":"Calle De Narvaez",
    "iso:country":"ES",
    "sg:address":"Calle de Narvaez, 58",
    "sg:city":"Madrid",
    "sg:orig_category":"Carnicer\u00cdas, Carnicer\u00cdas",
    "sg:phone":"+34 915 74 00 37",
    "sg:postcode":"28009",
    "sg:province":"Madrid",
    "wof:name":"Yebenes Arbe Manuel",
    "wof:placetype":"venue"
},
  "geometry": {"coordinates":[-3.6763749123,40.4188919067],"type":"Point"}
}