{
  "type": "Feature",
  "properties": {
    "iso:country":"ES",
    "sg:address":"Avda Tolosa De, 21",
    "sg:city":"Donostia-san Sebastian",
    "sg:orig_category":"Arquitectos",
    "sg:phone":"+34 943 31 44 15",
    "sg:postcode":"20018",
    "sg:province":"Guip\u00f9zcoa",
    "wof:name":"Arquitectos Sin Fronteras Asfe",
    "wof:placetype":"venue"
},
  "geometry": {"coordinates":[-2.0080587864,43.3119850159],"type":"Point"}
}