{
  "type": "Feature",
  "properties": {
    "addr:full":"Calle de Juan Pi\u00d1ol, 6 Valencia Valencia 46019",
    "addr:housenumber":"6",
    "addr:postcode":"46019",
    "addr:street":"Calle De Juan Pin\u0303Ol",
    "iso:country":"ES",
    "sg:address":"Calle de Juan Pi\u00d1ol, 6",
    "sg:city":"Valencia",
    "sg:orig_category":"Plomeros",
    "sg:phone":"+34 963 65 50 10",
    "sg:postcode":"46019",
    "sg:province":"Valencia",
    "wof:name":"Oliver Mas Vicente",
    "wof:placetype":"venue"
},
  "geometry": {"coordinates":[-0.3778829873,39.4959335327],"type":"Point"}
}