{
  "type": "Feature",
  "properties": {
    "addr:full":"Carrer de Bobiles, 35 Hospitalet Llobregat Barcelona 08905",
    "addr:housenumber":"35",
    "addr:postcode":"08905",
    "addr:street":"Carrer De Bobiles",
    "iso:country":"ES",
    "sg:address":"Carrer de Bobiles, 35",
    "sg:city":"Hospitalet Llobregat",
    "sg:orig_category":"Transportes Por Carretera: Lotes Completos, Mercanc\u00cdas Diversas",
    "sg:phone":"+34 934 49 17 71",
    "sg:postcode":"08905",
    "sg:province":"Barcelona",
    "wof:name":"Octavio Perez S.l.",
    "wof:placetype":"venue"
},
  "geometry": {"coordinates":[2.1118209362,41.3706245422],"type":"Point"}
}