{
  "type": "Feature",
  "properties": {
    "addr:full":"Calle de Rodriguez De La Fuente, 24 Pizarra M\u00e1laga 29560",
    "addr:housenumber":"24",
    "addr:postcode":"29560",
    "addr:street":"Calle De Rodriguez De La Fuente",
    "iso:country":"ES",
    "sg:address":"Calle de Rodriguez De La Fuente, 24",
    "sg:city":"Pizarra",
    "sg:orig_category":"Fotograf\u00cda Art\u00cdstica Y Retratos",
    "sg:phone":"+34 952 48 39 50",
    "sg:postcode":"29560",
    "sg:province":"M\u00e1laga",
    "wof:name":"Espinosa Gallego Rafael",
    "wof:placetype":"venue"
},
  "geometry": {"coordinates":[-4.7096939087,36.765411377],"type":"Point"}
}