{
  "type": "Feature",
  "properties": {
    "addr:full":"Vred Alquiton (del), 15 Arganda Madrid 28500",
    "addr:postcode":"28500",
    "iso:country":"ES",
    "sg:address":"Vred Alquiton (del), 15",
    "sg:city":"Arganda",
    "sg:orig_category":"Venta, Reparaci\u00d3n, Localizaci\u00d3n De Balanzas Y De B\u00c1sculas",
    "sg:phone":"+34 918 71 97 82",
    "sg:postcode":"28500",
    "sg:province":"Madrid",
    "wof:name":"Balanzas Antonio Collado S.l.",
    "wof:placetype":"venue"
},
  "geometry": {"coordinates":[-3.4818394184,40.3063201904],"type":"Point"}
}