{
  "type": "Feature",
  "properties": {
    "iso:country":"ES",
    "sg:address":"Ctra Barcelona, 628",
    "sg:city":"Sabadell",
    "sg:orig_category":"Comercio, Reparaci\u00d3n De Bicicletas, De Motocicletas, De Accesorios",
    "sg:phone":"+34 937 12 02 63",
    "sg:postcode":"08204",
    "sg:province":"Barcelona",
    "wof:name":"Bicimueble Del Valle S.l.",
    "wof:placetype":"venue"
},
  "geometry": {"coordinates":[2.1165380478,41.5315666199],"type":"Point"}
}