{
  "type": "Feature",
  "properties": {
    "addr:full":"Avda. Plasencia, 1 Malpartida Plasencia C\u00e1ceres 10680",
    "addr:housenumber":"1;plasencia",
    "addr:postcode":"10680",
    "addr:street":"Avda. Plasencia;Ca\u0301Ceres",
    "iso:country":"ES",
    "sg:address":"Avda. Plasencia, 1",
    "sg:city":"Malpartida Plasencia",
    "sg:orig_category":"Bancos",
    "sg:phone":"+34 927 45 98 07",
    "sg:postcode":"10680",
    "sg:province":"C\u00e1ceres",
    "sg:website":"www.bancosimeon.com",
    "wof:name":"Banco Caixa Geral S.a.",
    "wof:placetype":"venue"
},
  "geometry": {"coordinates":[-6.065030098,40.0144615173],"type":"Point"}
}