{
  "type": "Feature",
  "properties": {
    "iso:country":"ES",
    "sg:address":"C/ Alvarez De Castro, 20",
    "sg:city":"Banyoles",
    "sg:orig_category":"Transporte En General",
    "sg:phone":"+34 972 57 45 30",
    "sg:postcode":"17820",
    "sg:province":"Girona",
    "wof:name":"Robert Massanas Adelina",
    "wof:placetype":"venue"
},
  "geometry": {"coordinates":[2.7645499706,42.1171913147],"type":"Point"}
}