{
  "type": "Feature",
  "properties": {
    "iso:country":"ES",
    "sg:address":"Pl Pubilla Cases, 7",
    "sg:city":"Hospitalet Llobregat",
    "sg:orig_category":"Zapatos (al Por Menor)",
    "sg:phone":"+34 934 38 71 84",
    "sg:postcode":"08906",
    "sg:province":"Barcelona",
    "wof:name":"Mu\u00f1oz Serrano Maria Manuela",
    "wof:placetype":"venue"
},
  "geometry": {"coordinates":[2.104115963,41.3743782043],"type":"Point"}
}