{
  "type": "Feature",
  "properties": {
    "addr:full":"Calle de Cisterniga, 10 Valladolid Valladolid 47005",
    "addr:housenumber":"10",
    "addr:postcode":"47005",
    "addr:street":"Calle De Cisterniga",
    "iso:country":"ES",
    "sg:address":"Calle de Cisterniga, 10",
    "sg:city":"Valladolid",
    "sg:orig_category":"Contenedores (mercanc\u00cdas)",
    "sg:phone":"+34 983 21 13 37",
    "sg:postcode":"47005",
    "sg:province":"Valladolid",
    "wof:name":"Alonso Asensio Jose Maria",
    "wof:placetype":"venue"
},
  "geometry": {"coordinates":[-4.7150936127,41.6467170715],"type":"Point"}
}