{
  "type": "Feature",
  "properties": {
    "iso:country":"ES",
    "sg:address":"Calle de Amor Hermoso, 70",
    "sg:city":"Madrid",
    "sg:orig_category":"Construcciones Met\u00c1licas",
    "sg:phone":"+34 914 76 19 51",
    "sg:postcode":"28026",
    "sg:province":"Madrid",
    "wof:name":"Sayago Martinez Oscar",
    "wof:placetype":"venue"
},
  "geometry": {"coordinates":[-3.7037620544,40.3837776184],"type":"Point"}
}