{
  "type": "Feature",
  "properties": {
    "iso:country":"ES",
    "sg:address":"Bidebarrieta Kalea, 7",
    "sg:city":"Eibar",
    "sg:orig_category":"Notarios",
    "sg:phone":"+34 943 20 20 22",
    "sg:postcode":"20600",
    "sg:province":"Guip\u00f9zcoa",
    "wof:name":"Garcia Aranaz Maria Dolores",
    "wof:placetype":"venue"
},
  "geometry": {"coordinates":[-2.4708330631,43.1849327087],"type":"Point"}
}