{
  "type": "Feature",
  "properties": {
    "addr:full":"Calle de Beato Juan De Avila, S/n Fuensalida Toledo 45510",
    "addr:postcode":"45510",
    "addr:street":"Calle De Beato Juan De Avila S / N",
    "iso:country":"ES",
    "sg:address":"Calle de Beato Juan De Avila, S/n",
    "sg:city":"Fuensalida",
    "sg:orig_category":"Poller\u00cda Y Caza (al Por Menor)",
    "sg:phone":"+34 925 78 59 27",
    "sg:postcode":"45510",
    "sg:province":"Toledo",
    "wof:name":"Pollerias Bonilla S.l.",
    "wof:placetype":"venue"
},
  "geometry": {"coordinates":[-4.2135925293,40.0488853455],"type":"Point"}
}