{
  "type": "Feature",
  "properties": {
    "iso:country":"ES",
    "sg:address":"Carrer de Maria Cubi, 76",
    "sg:city":"Barcelona",
    "sg:orig_category":"Estancos",
    "sg:phone":"+34 932 09 63 42",
    "sg:postcode":"08006",
    "sg:province":"Barcelona",
    "wof:name":"Sola Queralto Maria",
    "wof:placetype":"venue"
},
  "geometry": {"coordinates":[2.1484661102,41.3976707458],"type":"Point"}
}