{
  "type": "Feature",
  "properties": {
    "addr:full":"Plaz Cruz, S/n Aldeamayor S. Martin Valladolid 47162",
    "addr:housenumber":"s / n",
    "addr:postcode":"47162",
    "addr:street":"Plaz Cruz;Aldeamayor S. Martin",
    "iso:country":"ES",
    "sg:address":"Plaz Cruz, S/n",
    "sg:city":"Aldeamayor S. Martin",
    "sg:orig_category":"Cajas Para Embalar",
    "sg:phone":"+34 983 55 81 69",
    "sg:postcode":"47162",
    "sg:province":"Valladolid",
    "wof:name":"Caja Rural Del Duero",
    "wof:placetype":"venue"
},
  "geometry": {"coordinates":[-4.6361689568,41.515625],"type":"Point"}
}