{
  "type": "Feature",
  "properties": {
    "iso:country":"ES",
    "sg:address":"Calle de Puerta Del Parque, 2",
    "sg:city":"Arganda",
    "sg:orig_category":"Cl\u00cdnicas M\u00c9dicas",
    "sg:phone":"+34 918 70 24 73",
    "sg:postcode":"28500",
    "sg:province":"Madrid",
    "wof:name":"Asistencia Sanitaria Preventiva Ortopedica Y Rehabilitadora S.a.l.",
    "wof:placetype":"venue"
},
  "geometry": {"coordinates":[-3.4443802834,40.303604126],"type":"Point"}
}