{
  "type": "Feature",
  "properties": {
    "iso:country":"ES",
    "sg:address":"Calle de General Alvarez De Castro, 12",
    "sg:city":"Madrid",
    "sg:orig_category":"Organismos De Desarrollo",
    "sg:phone":"+34 914 45 64 58",
    "sg:postcode":"28010",
    "sg:province":"Madrid",
    "wof:name":"Guardans Cambo Ramon",
    "wof:placetype":"venue"
},
  "geometry": {"coordinates":[-3.7020237446,40.435043335],"type":"Point"}
}