{
  "type": "Feature",
  "properties": {
    "iso:country":"ES",
    "sg:address":"Luga Ca\u00d1on Del Aguila, S/n",
    "sg:city":"Ca\u00e7on Del Aguila",
    "sg:orig_category":"Art\u00cdculos De Regalo (al Por Menor)",
    "sg:phone":"+34 928 76 55 88",
    "sg:postcode":"35100",
    "sg:province":"Las Palmas",
    "wof:name":"Parque Ca\u00f1on Del Aguila S.l.",
    "wof:placetype":"venue"
},
  "geometry": {"coordinates":[-15.5310506821,27.7890224457],"type":"Point"}
}