{
  "type": "Feature",
  "properties": {
    "iso:country":"ES",
    "sg:address":"Calle de Francisco Silvela, 74",
    "sg:city":"Madrid",
    "sg:orig_category":"Telefon\u00cda: Instaladores Varios",
    "sg:phone":"+34 913 56 18 80",
    "sg:postcode":"28028",
    "sg:province":"Madrid",
    "wof:name":"Moto Costa D.m. S.l.",
    "wof:placetype":"venue"
},
  "geometry": {"coordinates":[-3.6756529808,40.4361190796],"type":"Point"}
}