{
  "type": "Feature",
  "properties": {
    "addr:full":"Pg Carme, 24 Vilanova I La Geltru Barcelona 08800",
    "addr:housenumber":"24",
    "addr:postcode":"08800",
    "addr:street":"Pg Carme",
    "iso:country":"ES",
    "sg:address":"Pg Carme, 24",
    "sg:city":"Vilanova I La Geltru",
    "sg:orig_category":"Electrodom\u00c9sticos (al Por Menor)",
    "sg:phone":"+34 938 15 16 76",
    "sg:postcode":"08800",
    "sg:province":"Barcelona",
    "wof:name":"Nueva Sin Nombre S.l.",
    "wof:placetype":"venue"
},
  "geometry": {"coordinates":[1.7268660069,41.2150993347],"type":"Point"}
}