{
  "type": "Feature",
  "properties": {
    "iso:country":"ES",
    "sg:address":"Calle de Pe\u00d1uelas, 3",
    "sg:city":"Marbella",
    "sg:orig_category":"Supermercados Y Hipermercados",
    "sg:phone":"+34 952 76 55 24",
    "sg:postcode":"29600",
    "sg:province":"M\u00e1laga",
    "wof:name":"Supermercado Divina Pastora S.l.",
    "wof:placetype":"venue"
},
  "geometry": {"coordinates":[-4.8817028999,36.5107307434],"type":"Point"}
}