{
  "type": "Feature",
  "properties": {
    "iso:country":"ES",
    "sg:address":"Calle de Zaballa, 4",
    "sg:city":"San Vicente De Barakaldo",
    "sg:orig_category":"M\u00c9dicos: Estomatolog\u00cda",
    "sg:phone":"+34 944 38 16 02",
    "sg:postcode":"48901",
    "sg:province":"Vizcaya",
    "wof:name":"Rode\u00f1o Diez Maria Teresa",
    "wof:placetype":"venue"
},
  "geometry": {"coordinates":[-3.0236361027,43.3172874451],"type":"Point"}
}