{
  "type": "Feature",
  "properties": {
    "addr:full":"Conturiz, S/n Conturiz Lugo 27160",
    "addr:postcode":"27160",
    "addr:street":"Conturiz S / N",
    "iso:country":"ES",
    "sg:address":"Conturiz, S/n",
    "sg:city":"Conturiz",
    "sg:orig_category":"Peleter\u00cdas",
    "sg:phone":"+34 982 30 43 89",
    "sg:postcode":"27160",
    "sg:province":"Lugo",
    "wof:name":"Adri Piel S.l.",
    "wof:placetype":"venue"
},
  "geometry": {"coordinates":[-7.5227079391,42.9797935486],"type":"Point"}
}