{
  "type": "Feature",
  "properties": {
    "iso:country":"ES",
    "sg:address":"Pl Prim, 14",
    "sg:city":"Reus",
    "sg:orig_category":"Abogados",
    "sg:phone":"+34 977 34 39 10",
    "sg:postcode":"43201",
    "sg:province":"Tarragona",
    "wof:name":"Huguet Tous Pedro Lluis",
    "wof:placetype":"venue"
},
  "geometry": {"coordinates":[1.1072230339,41.1558914185],"type":"Point"}
}