{
  "type": "Feature",
  "properties": {
    "iso:country":"ES",
    "sg:address":"Avda Gasteiz, 49",
    "sg:city":"Vitoria-gasteiz",
    "sg:orig_category":"Contenedores (mercanc\u00cdas)",
    "sg:phone":"+34 945 22 89 38",
    "sg:postcode":"01008",
    "sg:province":"\u00c1lava",
    "wof:name":"Casado Sabanza Angel",
    "wof:placetype":"venue"
},
  "geometry": {"coordinates":[-2.6818261147,42.847782135],"type":"Point"}
}