{
  "type": "Feature",
  "properties": {
    "iso:country":"ES",
    "sg:address":"Avda Pio Baroja, 25",
    "sg:city":"Infante Juan Manuel",
    "sg:orig_category":"Empresas De Vigilancia, Guardia Y Protecci\u00d3n",
    "sg:phone":"+34 968 34 31 60",
    "sg:postcode":"30011",
    "sg:province":"Murcia",
    "wof:name":"Sureste Seguridad S.l.",
    "wof:placetype":"venue"
},
  "geometry": {"coordinates":[-1.1211060286,37.978302002],"type":"Point"}
}