{
  "type": "Feature",
  "properties": {
    "iso:country":"ES",
    "sg:address":"Calle de Cuevas, 1",
    "sg:city":"Motril",
    "sg:orig_category":"Agencias De Viajes",
    "sg:phone":"+34 958 82 22 20",
    "sg:postcode":"18600",
    "sg:province":"Granada",
    "wof:name":"Viajes Jumantur S. A.",
    "wof:placetype":"venue"
},
  "geometry": {"coordinates":[-3.5163989067,36.7449302673],"type":"Point"}
}