{
  "type": "Feature",
  "properties": {
    "iso:country":"ES",
    "sg:address":"Calle de Granada, 75",
    "sg:city":"Rute",
    "sg:orig_category":"Molduras, Junquillos, Listones Y Molduras Perforadas",
    "sg:phone":"+34 957 53 80 51",
    "sg:postcode":"14960",
    "sg:province":"C\u00f3rdoba",
    "wof:name":"Ecija Garcia Francisco",
    "wof:placetype":"venue"
},
  "geometry": {"coordinates":[-4.3685588837,37.3227615356],"type":"Point"}
}