{
  "type": "Feature",
  "properties": {
    "iso:country":"ES",
    "sg:address":"Calle de Benabarra, 12",
    "sg:city":"Valle Trapaga",
    "sg:orig_category":"Peluqueros: De Se\u00d1oras",
    "sg:phone":"+34 944 92 03 81",
    "sg:postcode":"48510",
    "sg:province":"Vizcaya",
    "wof:name":"Maria Bego\u00f1a Gomez De Cadi\u00f1anos-peluqueria",
    "wof:placetype":"venue"
},
  "geometry": {"coordinates":[-3.0354406834,43.3050765991],"type":"Point"}
}