{
  "type": "Feature",
  "properties": {
    "iso:country":"ES",
    "sg:address":"Carrer de Major, 32",
    "sg:city":"Constanti",
    "sg:orig_category":"Inmobiliaria (agencias)",
    "sg:phone":"+34 977 52 06 07",
    "sg:postcode":"43120",
    "sg:province":"Tarragona",
    "wof:name":"Mar 2007 S.l.",
    "wof:placetype":"venue"
},
  "geometry": {"coordinates":[1.2138589621,41.1527824402],"type":"Point"}
}