{
  "type": "Feature",
  "properties": {
    "addr:full":"Ctra Madrid-irun (villafria), Km. 0244,5 Villafria Burgos 09192",
    "addr:postcode":"09192",
    "addr:street":"Ctra Madrid-Irun Villafria Km. 0244,5 Villafria",
    "iso:country":"ES",
    "sg:address":"Ctra Madrid-irun (villafria), Km. 0244,5",
    "sg:city":"Villafria",
    "sg:orig_category":"Estaciones Y Oficinas De Meteorolog\u00cda",
    "sg:phone":"+34 947 48 07 27",
    "sg:postcode":"09192",
    "sg:province":"Burgos",
    "sg:website":"www.inm.es",
    "wof:name":"Direccion General Del Instituto Nacional De Meteorologia",
    "wof:placetype":"venue"
},
  "geometry": {"coordinates":[-3.5749700069,42.3601303101],"type":"Point"}
}