{
  "type": "Feature",
  "properties": {
    "iso:country":"ES",
    "sg:address":"Calle de Postas, 16",
    "sg:city":"Aranda Duero",
    "sg:orig_category":"Asesor\u00cda Fiscal Y Jur\u00cddica",
    "sg:phone":"+34 947 50 03 48",
    "sg:postcode":"09400",
    "sg:province":"Burgos",
    "wof:name":"Escudero Asesoria Y Gestion S.a.l",
    "wof:placetype":"venue"
},
  "geometry": {"coordinates":[-3.6861379147,41.670211792],"type":"Point"}
}