{
  "type": "Feature",
  "properties": {
    "addr:full":"Calle de Coronel Jimenez, 55 Valle De Santa Ana Badajoz 06178",
    "addr:housenumber":"55",
    "addr:postcode":"06178",
    "addr:street":"Calle De Coronel Jimenez",
    "iso:country":"ES",
    "sg:address":"Calle de Coronel Jimenez, 55",
    "sg:city":"Valle De Santa Ana",
    "sg:orig_category":"Carnicer\u00cdas, Carnicer\u00cdas",
    "sg:phone":"+34 924 75 37 81",
    "sg:postcode":"06178",
    "sg:province":"Badajoz",
    "wof:name":"Torvisco Morcillo Hipolita",
    "wof:placetype":"venue"
},
  "geometry": {"coordinates":[-6.7884082794,38.3656616211],"type":"Point"}
}