{
  "type": "Feature",
  "properties": {
    "iso:country":"ES",
    "sg:address":"Calle de Timanfaya, S/n",
    "sg:city":"Alcorcon",
    "sg:orig_category":"Loter\u00cda Y T\u00d3mbola",
    "sg:phone":"+34 916 11 27 06",
    "sg:postcode":"28924",
    "sg:province":"Madrid",
    "wof:name":"Diaz Ayala Beatriz",
    "wof:placetype":"venue"
},
  "geometry": {"coordinates":[-3.8114340305,40.347568512],"type":"Point"}
}