{
  "type": "Feature",
  "properties": {
    "iso:country":"ES",
    "sg:address":"Praz Cabaceiros (dos), 10",
    "sg:city":"Maceda",
    "sg:orig_category":"Art\u00cdculos Funerarios (al Por Menor)",
    "sg:phone":"+34 988 46 31 23",
    "sg:postcode":"32700",
    "sg:province":"Ourense",
    "wof:name":"Borrajo Verisimo Jose Luis",
    "wof:placetype":"venue"
},
  "geometry": {"coordinates":[-7.6509618759,42.2707633972],"type":"Point"}
}