{
  "type": "Feature",
  "properties": {
    "addr:full":"Calle de Doctrinos, 18 Valladolid Valladolid 47001",
    "addr:housenumber":"18",
    "addr:postcode":"47001",
    "addr:street":"Calle De Doctrinos",
    "iso:country":"ES",
    "sg:address":"Calle de Doctrinos, 18",
    "sg:city":"Valladolid",
    "sg:orig_category":"Aparcamientos (infraestructuras, Accesorios)",
    "sg:phone":"+34 983 35 40 12",
    "sg:postcode":"47001",
    "sg:province":"Valladolid",
    "wof:name":"Alonso Doce C.b.",
    "wof:placetype":"venue"
},
  "geometry": {"coordinates":[-4.7322063446,41.649520874],"type":"Point"}
}