{
  "type": "Feature",
  "properties": {
    "iso:country":"ES",
    "sg:address":"Avda Principes De Espa\u00d1a, S/n",
    "sg:city":"Rota",
    "sg:orig_category":"Farmacias",
    "sg:phone":"+34 956 81 07 54",
    "sg:postcode":"11520",
    "sg:province":"C\u00e1diz",
    "wof:name":"Alonso Villaro Margarita",
    "wof:placetype":"venue"
},
  "geometry": {"coordinates":[-6.3777194023,36.6294136047],"type":"Point"}
}