{
  "type": "Feature",
  "properties": {
    "addr:full":"Calle de Sixto Celorrio, 1 Zaragoza Zaragoza 50015",
    "addr:housenumber":"1",
    "addr:postcode":"50015",
    "addr:street":"Calle De Sixto Celorrio",
    "iso:country":"ES",
    "sg:address":"Calle de Sixto Celorrio, 1",
    "sg:city":"Zaragoza",
    "sg:orig_category":"Agencias De Viajes",
    "sg:phone":"+34 976 52 16 34",
    "sg:postcode":"50015",
    "sg:province":"Zaragoza",
    "sg:website":"www.zaragozanote.zafirotours.es",
    "wof:name":"Gestion Turistica Aragonesa S.l.l.",
    "wof:placetype":"venue"
},
  "geometry": {"coordinates":[-0.8754289746,41.6590690613],"type":"Point"}
}