{
  "type": "Feature",
  "properties": {
    "iso:country":"ES",
    "sg:address":"Vva Cordoba, 43",
    "sg:city":"Pozoblanco",
    "sg:orig_category":"Agentes, Concesionarios Y Sucursales De Veh\u00cdculos",
    "sg:phone":"+34 957 77 09 09",
    "sg:postcode":"14400",
    "sg:province":"C\u00f3rdoba",
    "wof:name":"Automoviles Agudo Cantero S.l.",
    "wof:placetype":"venue"
},
  "geometry": {"coordinates":[-4.7484517097,38.2839393616],"type":"Point"}
}