{
  "type": "Feature",
  "properties": {
    "addr:full":"Avda Herencia, 21 Alcazar S. Juan Ciudad Real 13600",
    "addr:housenumber":"21",
    "addr:postcode":"13600",
    "addr:street":"Avda Herencia;Alcazar S. Juan Ciudad Real",
    "iso:country":"ES",
    "sg:address":"Avda Herencia, 21",
    "sg:city":"Alcazar S. Juan",
    "sg:orig_category":"Mec\u00c1nico Del Autom\u00d3vil",
    "sg:phone":"+34 926 55 08 31",
    "sg:postcode":"13600",
    "sg:province":"Ciudad Real",
    "wof:name":"Talleres Jeronimo Martinez S.a.",
    "wof:placetype":"venue"
},
  "geometry": {"coordinates":[-3.2183539867,39.3883552551],"type":"Point"}
}