{
  "type": "Feature",
  "properties": {
    "iso:country":"ES",
    "sg:address":"Carrer de Sant Antoni, 2",
    "sg:city":"Montcada Centre",
    "sg:orig_category":"Loter\u00cda Y T\u00d3mbola",
    "sg:phone":"+34 935 64 15 22",
    "sg:postcode":"08110",
    "sg:province":"Barcelona",
    "wof:name":"Benito Nu\u00f1ez-lagos Emma",
    "wof:placetype":"venue"
},
  "geometry": {"coordinates":[2.1864640713,41.4838066101],"type":"Point"}
}