{
  "type": "Feature",
  "properties": {
    "addr:full":"Calle de Obispo Osmundo, 1 Ponferrada Le\u00f3n 24400",
    "addr:housenumber":"1",
    "addr:postcode":"24400",
    "addr:street":"Calle De Obispo Osmundo",
    "iso:country":"ES",
    "sg:address":"Calle de Obispo Osmundo, 1",
    "sg:city":"Ponferrada",
    "sg:orig_category":"Molduras, Junquillos, Listones Y Molduras Perforadas",
    "sg:phone":"+34 987 41 11 69",
    "sg:postcode":"24400",
    "sg:province":"Le\u00f3n",
    "wof:name":"Teldespa\u00d1a S.l.",
    "wof:placetype":"venue"
},
  "geometry": {"coordinates":[-6.5888638496,42.5463485718],"type":"Point"}
}