{
  "type": "Feature",
  "properties": {
    "addr:full":"Ctra Valladolid, Km. 0004,0 Fuensalda\u00d1a Valladolid 47194",
    "addr:postcode":"47194",
    "addr:street":"Ctra Valladolid Km. 0004,0",
    "iso:country":"ES",
    "sg:address":"Ctra Valladolid, Km. 0004,0",
    "sg:city":"Fuensalda\u00d1a",
    "sg:orig_category":"Productos Alimentarios",
    "sg:phone":"+34 983 58 30 83",
    "sg:postcode":"47194",
    "sg:province":"Valladolid",
    "wof:name":"Productores Ganaderos Y Tecnicos Asociados S.a.",
    "wof:placetype":"venue"
},
  "geometry": {"coordinates":[-4.7626438141,41.7067947388],"type":"Point"}
}