{
  "type": "Feature",
  "properties": {
    "addr:full":"Barrenkalea, 18 Bergara Guip\u00f9zcoa 20570",
    "addr:housenumber":"18",
    "addr:postcode":"20570",
    "addr:street":"Barrenkalea;Guipu\u0300Zcoa",
    "iso:country":"ES",
    "sg:address":"Barrenkalea, 18",
    "sg:city":"Bergara",
    "sg:orig_category":"Partidos Pol\u00cdticos",
    "sg:phone":"+34 943 76 26 81",
    "sg:postcode":"20570",
    "sg:province":"Guip\u00f9zcoa",
    "wof:name":"Eusko Alkartasuna",
    "wof:placetype":"venue"
},
  "geometry": {"coordinates":[-2.413173914,43.1181182861],"type":"Point"}
}