{
  "type": "Feature",
  "properties": {
    "addr:full":"Calle de Vazquez Aroca, 31 Cordoba C\u00f3rdoba 14005",
    "addr:housenumber":"31",
    "addr:postcode":"14005",
    "addr:street":"Calle De;Aroca;Co\u0301Rdoba",
    "iso:country":"ES",
    "sg:address":"Calle de Vazquez Aroca, 31",
    "sg:city":"Cordoba",
    "sg:orig_category":"Fabricaci\u00d3n, Importaci\u00d3n De Material Y Sistemas De Telecomunicaciones",
    "sg:phone":"+34 957 23 20 96",
    "sg:postcode":"14005",
    "sg:province":"C\u00f3rdoba",
    "wof:name":"Garcia Delgado Rafael Pablo",
    "wof:placetype":"venue"
},
  "geometry": {"coordinates":[-4.7932991982,37.8834381104],"type":"Point"}
}