{
  "type": "Feature",
  "properties": {
    "iso:country":"ES",
    "sg:address":"Ctra Santiago (de), Km. 0250,0",
    "sg:city":"Tamallancos",
    "sg:orig_category":"Perfumer\u00cda, Art\u00cdculos De Ba\u00d1o (fabricaci\u00d3n, Al Por Mayor)",
    "sg:phone":"+34 988 28 10 32",
    "sg:postcode":"32102",
    "sg:province":"Ourense",
    "wof:name":"Almacenes Dromay S.l.",
    "wof:placetype":"venue"
},
  "geometry": {"coordinates":[-7.8932819366,42.4239692688],"type":"Point"}
}