{
  "type": "Feature",
  "properties": {
    "iso:country":"ES",
    "sg:address":"Rbla Prim, 166",
    "sg:city":"Barcelona",
    "sg:orig_category":"Mec\u00c1nica Y Herramientas De Precisi\u00d3n",
    "sg:phone":"+34 932 78 85 62",
    "sg:postcode":"08020",
    "sg:province":"Barcelona",
    "wof:name":"Meters Comunicaciones Y Software Sl",
    "wof:placetype":"venue"
},
  "geometry": {"coordinates":[2.2072949409,41.4208641052],"type":"Point"}
}