{
  "type": "Feature",
  "properties": {
    "iso:country":"ES",
    "sg:address":"Calle de Monasterio De Veruela, 6",
    "sg:city":"Sevilla",
    "sg:orig_category":"Electricidad: Instaladores",
    "sg:phone":"+34 954 38 87 87",
    "sg:postcode":"41009",
    "sg:province":"Sevilla",
    "wof:name":"Torres Mogrera Antonio",
    "wof:placetype":"venue"
},
  "geometry": {"coordinates":[-5.9867639542,37.4115715027],"type":"Point"}
}