{
  "type": "Feature",
  "properties": {
    "addr:full":"Avda Juan De Austria, 28 Alcala Henares Madrid 28804",
    "addr:housenumber":"28",
    "addr:postcode":"28804",
    "addr:street":"Avda Juan De Austria",
    "iso:country":"ES",
    "sg:address":"Avda Juan De Austria, 28",
    "sg:city":"Alcala Henares",
    "sg:orig_category":"Radiocomunicaciones, Telefon\u00cda M\u00d3vil, Radiomensajer\u00cda: Servicios, Comercializaci\u00d3n",
    "sg:phone":"+34 918 83 29 35",
    "sg:postcode":"28804",
    "sg:province":"Madrid",
    "wof:name":"Musleh  Nasser",
    "wof:placetype":"venue"
},
  "geometry": {"coordinates":[-3.3517611027,40.4870262146],"type":"Point"}
}