{
  "type": "Feature",
  "properties": {
    "addr:full":"Carrer de Varsovia, 162 Barcelona Barcelona 08041",
    "addr:housenumber":"162",
    "addr:postcode":"08041",
    "addr:street":"Carrer De Varsovia",
    "iso:country":"ES",
    "sg:address":"Carrer de Varsovia, 162",
    "sg:city":"Barcelona",
    "sg:orig_category":"Internados & Ense\u00d1anza Privada",
    "sg:phone":"+34 934 55 76 25",
    "sg:postcode":"08041",
    "sg:province":"Barcelona",
    "wof:name":"Escuela Parroquial Especial Nuestra Se\u00d1ora De Montserrat",
    "wof:placetype":"venue"
},
  "geometry": {"coordinates":[2.1718730927,41.4174880981],"type":"Point"}
}