{
  "type": "Feature",
  "properties": {
    "addr:full":"Avda Monte Igueldo, 25 Madrid Madrid 28053",
    "addr:housenumber":"25",
    "addr:postcode":"madrid;28053",
    "addr:street":"Avda Monte Igueldo",
    "iso:country":"ES",
    "sg:address":"Avda Monte Igueldo, 25",
    "sg:city":"Madrid",
    "sg:orig_category":"Cl\u00cdnicas Dentales",
    "sg:phone":"+34 914 33 55 20",
    "sg:postcode":"28053",
    "sg:province":"Madrid",
    "sg:website":"www.unidental2000.com",
    "wof:name":"Grupo Unidental 2000",
    "wof:placetype":"venue"
},
  "geometry": {"coordinates":[-3.6681630611,40.3964271545],"type":"Point"}
}