{
  "type": "Feature",
  "properties": {
    "addr:full":"Praz Isabel A Catolica, 2 Vigo Pontevedra 36204",
    "addr:housenumber":"2",
    "addr:postcode":"36204",
    "addr:street":"Catolica",
    "iso:country":"ES",
    "sg:address":"Praz Isabel A Catolica, 2",
    "sg:city":"Vigo",
    "sg:orig_category":"Agencias Y Agentes Comerciales, Representantes",
    "sg:phone":"+34 986 42 36 85",
    "sg:postcode":"36204",
    "sg:province":"Pontevedra",
    "wof:name":"Dapena Landin Manuel",
    "wof:placetype":"venue"
},
  "geometry": {"coordinates":[-8.7123680115,42.231136322],"type":"Point"}
}