{
  "type": "Feature",
  "properties": {
    "addr:full":"Ctra Irun (de), Km. 0014,5 Alcobendas Madrid 28108",
    "addr:postcode":"28108",
    "addr:street":"Ctra Irun De Km. 0014,5",
    "iso:country":"ES",
    "sg:address":"Ctra Irun (de), Km. 0014,5",
    "sg:city":"Alcobendas",
    "sg:orig_category":"Loter\u00cda Y T\u00d3mbola",
    "sg:phone":"+34 916 62 15 30",
    "sg:postcode":"28108",
    "sg:province":"Madrid",
    "wof:name":"Garcia Caro Perez Santos",
    "wof:placetype":"venue"
},
  "geometry": {"coordinates":[-3.6225941181,40.5358009338],"type":"Point"}
}