{
  "type": "Feature",
  "properties": {
    "addr:full":"Calle de San Francisco, 30 Villanueva Serena Badajoz 06700",
    "addr:housenumber":"30",
    "addr:postcode":"06700",
    "addr:street":"Calle De San Francisco",
    "iso:country":"ES",
    "sg:address":"Calle de San Francisco, 30",
    "sg:city":"Villanueva Serena",
    "sg:classifiers":[
        {
            "category":"Autos & Motor Vehicles",
            "subcategory":"Automobile Sales",
            "type":"Retail Goods"
        }
    ],
    "sg:phone":"+34 924 84 36 82",
    "sg:postcode":"06700",
    "sg:province":"Badajoz",
    "wof:name":"Autoescuela La Sirena S.l.",
    "wof:placetype":"venue"
},
  "geometry": {"coordinates":[-5.793762207,38.973033905],"type":"Point"}
}