{
  "type": "Feature",
  "properties": {
    "addr:full":"Rua Tras Santa Isabel (de), S/n Santiago De Compostela A Coru\u00f1a 15705",
    "addr:postcode":"15705",
    "addr:street":"Rua Tras Santa Isabel De S / N;Corun\u0303A",
    "iso:country":"ES",
    "sg:address":"Rua Tras Santa Isabel (de), S/n",
    "sg:city":"Santiago De Compostela",
    "sg:orig_category":"Asociaciones Y Clubs Deportivos",
    "sg:phone":"+34 981 58 12 20",
    "sg:postcode":"15705",
    "sg:province":"A Coru\u00f1a",
    "sg:website":"www.santaisabel.net",
    "wof:name":"Xestion De Actividades Deportivas E Espectaculos",
    "wof:placetype":"venue"
},
  "geometry": {"coordinates":[-8.5508871078,42.8858642578],"type":"Point"}
}