{
  "type": "Feature",
  "properties": {
    "iso:country":"ES",
    "sg:address":"Plaz Duquesa De Parcent, S/n",
    "sg:city":"Ronda",
    "sg:orig_category":"Administraciones Regionales, Departamentales Y Locales",
    "sg:phone":"+34 952 87 32 40",
    "sg:postcode":"29400",
    "sg:province":"M\u00e1laga",
    "sg:website":"www.ayto-ronda.org",
    "wof:name":"Ayuntamiento De Ronda",
    "wof:placetype":"venue"
},
  "geometry": {"coordinates":[-5.1655840874,36.7370185852],"type":"Point"}
}