{
  "type": "Feature",
  "properties": {
    "iso:country":"ES",
    "sg:address":"Calle de Juan De Herrera, 12",
    "sg:city":"Santander",
    "sg:orig_category":"Edici\u00d3n De Diarios, Revistas, Boletines",
    "sg:phone":"+34 942 36 15 05",
    "sg:postcode":"39002",
    "sg:province":"Cantabria",
    "wof:name":"Ediciones Finder S.l.",
    "wof:placetype":"venue"
},
  "geometry": {"coordinates":[-3.8081970215,43.4619865417],"type":"Point"}
}