{
  "type": "Feature",
  "properties": {
    "addr:full":"Calle de San Cayetano, 1 Alaquas Valencia 46970",
    "addr:housenumber":"1",
    "addr:postcode":"46970",
    "addr:street":"Calle De San Cayetano",
    "iso:country":"ES",
    "sg:address":"Calle de San Cayetano, 1",
    "sg:city":"Alaquas",
    "sg:orig_category":"Mec\u00c1nico Del Autom\u00d3vil",
    "sg:phone":"+34 961 98 83 80",
    "sg:postcode":"46970",
    "sg:province":"Valencia",
    "wof:name":"Latorre Lopez Antonio",
    "wof:placetype":"venue"
},
  "geometry": {"coordinates":[-0.4627310038,39.4597892761],"type":"Point"}
}