{
  "type": "Feature",
  "properties": {
    "iso:country":"ES",
    "sg:address":"Calle de Huertas De Abajo (de Las), S/n",
    "sg:city":"El Cruce",
    "sg:orig_category":"Inmobiliaria (agencias)",
    "sg:phone":"+34 916 58 11 11",
    "sg:postcode":"28860",
    "sg:province":"Madrid",
    "wof:name":"Inmobiliaria Joyma S.a.",
    "wof:placetype":"venue"
},
  "geometry": {"coordinates":[-3.5450429916,40.5005226135],"type":"Point"}
}