{
  "type": "Feature",
  "properties": {
    "addr:full":"Plaz Circular, 1 Vista Alegre Murcia 30008",
    "addr:housenumber":"1",
    "addr:postcode":"30008",
    "addr:street":"Plaz Circular",
    "iso:country":"ES",
    "sg:address":"Plaz Circular, 1",
    "sg:city":"Vista Alegre",
    "sg:orig_category":"Pe\u00d1as Y Asociaciones Varias",
    "sg:phone":"+34 968 20 45 00",
    "sg:postcode":"30008",
    "sg:province":"Murcia",
    "wof:name":"Gestion Inmobiliaria Novel Stamp S.l.",
    "wof:placetype":"venue"
},
  "geometry": {"coordinates":[-1.1303889751,37.9927940369],"type":"Point"}
}