{
  "type": "Feature",
  "properties": {
    "addr:full":"Carretera General, 116 Galdar Las Palmas 35460",
    "addr:housenumber":"116",
    "addr:postcode":"35460",
    "addr:street":"Carretera General",
    "iso:country":"ES",
    "sg:address":"Carretera General, 116",
    "sg:city":"Galdar",
    "sg:orig_category":"Supermercados Y Hipermercados",
    "sg:phone":"+34 928 55 17 86",
    "sg:postcode":"35460",
    "sg:province":"Las Palmas",
    "wof:name":"Santiago Leon Javier",
    "wof:placetype":"venue"
},
  "geometry": {"coordinates":[-15.6528720856,28.1450138092],"type":"Point"}
}