{
  "type": "Feature",
  "properties": {
    "addr:full":"Calle de San Blas, 41 Fuente Cantos Badajoz 06240",
    "addr:housenumber":"41",
    "addr:postcode":"06240",
    "addr:street":"Calle De San Blas",
    "iso:country":"ES",
    "sg:address":"Calle de San Blas, 41",
    "sg:city":"Fuente Cantos",
    "sg:orig_category":"Alimentaci\u00d3n General (al Por Menor)",
    "sg:phone":"+34 924 58 01 43",
    "sg:postcode":"06240",
    "sg:province":"Badajoz",
    "wof:name":"Castillo Magro Tadeo Jesus",
    "wof:placetype":"venue"
},
  "geometry": {"coordinates":[-6.3087902069,38.2426185608],"type":"Point"}
}