{
  "type": "Feature",
  "properties": {
    "iso:country":"ES",
    "sg:address":"Calle de Dionisio Perez, 1",
    "sg:city":"Puerto De Santa Maria",
    "sg:orig_category":"Bisuteros (fabricaci\u00d3n, Al Por Mayor)",
    "sg:phone":"+34 956 54 31 24",
    "sg:postcode":"11500",
    "sg:province":"C\u00e1diz",
    "wof:name":"Pe\u00f1a Soto Francisco",
    "wof:placetype":"venue"
},
  "geometry": {"coordinates":[-6.2321176529,36.6002349854],"type":"Point"}
}