{
  "type": "Feature",
  "properties": {
    "addr:full":"Pol Matola, 3 Elche Alicante 03296",
    "addr:housenumber":"3",
    "addr:postcode":"03296",
    "addr:street":"Matola",
    "iso:country":"ES",
    "sg:address":"Pol Matola, 3",
    "sg:city":"Elche",
    "sg:orig_category":"Automatizaci\u00d3n De Procesos Industriales Y De Edificaci\u00d3n (estudios, Instalaci\u00d3n)",
    "sg:phone":"+34 966 63 02 72",
    "sg:postcode":"03296",
    "sg:province":"Alicante",
    "wof:name":"Autoblock S.l.",
    "wof:placetype":"venue"
},
  "geometry": {"coordinates":[-0.7449640036,38.2285308838],"type":"Point"}
}