{
  "type": "Feature",
  "properties": {
    "addr:full":"Monte Lakartxela, 9 Iru\u00f1a Navarra 31006",
    "addr:housenumber":"9",
    "addr:postcode":"31006",
    "addr:street":"Lakartxela",
    "iso:country":"ES",
    "sg:address":"Monte Lakartxela, 9",
    "sg:city":"Iru\u00f1a",
    "sg:orig_category":"V\u00c1lvulas",
    "sg:phone":"+34 948 15 07 75",
    "sg:postcode":"31006",
    "sg:province":"Navarra",
    "wof:name":"Landeta Goiri Kepa",
    "wof:placetype":"venue"
},
  "geometry": {"coordinates":[-1.6343230009,42.8061027527],"type":"Point"}
}