{
  "type": "Feature",
  "properties": {
    "addr:full":"Calle de Sarria, 49 Madrid Madrid 28029",
    "addr:housenumber":"49",
    "addr:postcode":"madrid;28029",
    "addr:street":"Calle De Sarria",
    "iso:country":"ES",
    "sg:address":"Calle de Sarria, 49",
    "sg:city":"Madrid",
    "sg:orig_category":"Centros De Educaci\u00d3n Especial",
    "sg:phone":"+34 913 86 08 16",
    "sg:postcode":"28029",
    "sg:province":"Madrid",
    "wof:name":"Comunidad Autonoma De Madrid-centros De Educacion",
    "wof:placetype":"venue"
},
  "geometry": {"coordinates":[-3.7144050598,40.4747886658],"type":"Point"}
}