{
  "type": "Feature",
  "properties": {
    "addr:full":"Calle de Garcia Lorca, 8 Albaladejo Ciudad Real 13340",
    "addr:housenumber":"8",
    "addr:postcode":"albaladejo;13340",
    "addr:street":"Calle De Garcia Lorca",
    "iso:country":"ES",
    "sg:address":"Calle de Garcia Lorca, 8",
    "sg:city":"Albaladejo",
    "sg:orig_category":"Camiser\u00cda Y Ropa Interior Masculina (al Por Menor)",
    "sg:phone":"+34 926 38 76 11",
    "sg:postcode":"13340",
    "sg:province":"Ciudad Real",
    "wof:name":"Rodriguez Gonzalez Virtudes",
    "wof:placetype":"venue"
},
  "geometry": {"coordinates":[-2.8076710701,38.6160926819],"type":"Point"}
}