{
  "type": "Feature",
  "properties": {
    "addr:full":"Fontecova, 13 Lamas Pontevedra 36686",
    "addr:housenumber":"13",
    "addr:postcode":"36686",
    "addr:street":"Fontecova",
    "iso:country":"ES",
    "sg:address":"Fontecova, 13",
    "sg:city":"Lamas",
    "sg:orig_category":"Cr\u00cda De Bovinos",
    "sg:phone":"+34 986 58 82 38",
    "sg:postcode":"36686",
    "sg:province":"Pontevedra",
    "wof:name":"Gandeiria Conde Da Xesteira S.l.",
    "wof:placetype":"venue"
},
  "geometry": {"coordinates":[-8.491894722,42.6821098328],"type":"Point"}
}