{
  "type": "Feature",
  "properties": {
    "iso:country":"ES",
    "sg:address":"Jobre, S/n",
    "sg:city":"Xobre",
    "sg:orig_category":"Ense\u00d1anza, Formaci\u00d3n Profesional: Aprendizaje",
    "sg:phone":"+34 981 83 39 00",
    "sg:postcode":"15940",
    "sg:province":"La Coru\u00f1a",
    "wof:name":"Instituto De Educacion Secundaria A Pobra Do Carami\u00f1al",
    "wof:placetype":"venue"
},
  "geometry": {"coordinates":[-8.9388437271,42.6042404175],"type":"Point"}
}