{
  "type": "Feature",
  "properties": {
    "addr:full":"Avda Torcuato Fernandez Miranda, 52 Gijon Asturias 33203",
    "addr:housenumber":"52",
    "addr:postcode":"33203",
    "addr:street":"Avda Torcuato Fernandez Miranda",
    "iso:country":"ES",
    "sg:address":"Avda Torcuato Fernandez Miranda, 52",
    "sg:city":"Gijon",
    "sg:orig_category":"Agencias De Viajes",
    "sg:phone":"+34 985 33 82 34",
    "sg:postcode":"33203",
    "sg:province":"Asturias",
    "sg:website":"www.club-america.com",
    "wof:name":"Itamaraca S.a.",
    "wof:placetype":"venue"
},
  "geometry": {"coordinates":[-5.6396842003,43.5353240967],"type":"Point"}
}