{
  "type": "Feature",
  "properties": {
    "iso:country":"ES",
    "sg:address":"Avda Camilo Alonso Vega, 9",
    "sg:city":"Santander",
    "sg:orig_category":"Doctores En Medicina",
    "sg:phone":"+34 942 33 96 70",
    "sg:postcode":"39007",
    "sg:province":"Cantabria",
    "wof:name":"Pellon Willie Juan Eugenio",
    "wof:placetype":"venue"
},
  "geometry": {"coordinates":[-3.8265399933,43.4593429565],"type":"Point"}
}