{
  "type": "Feature",
  "properties": {
    "addr:full":"Carr Enric Granados, 23 Badalona Barcelona 08918",
    "addr:housenumber":"23",
    "addr:postcode":"08918",
    "addr:street":"Carr Enric Granados",
    "iso:country":"ES",
    "sg:address":"Carr Enric Granados, 23",
    "sg:city":"Badalona",
    "sg:orig_category":"Camiser\u00cda Y Ropa Interior Masculina (al Por Menor)",
    "sg:phone":"+34 933 97 35 97",
    "sg:postcode":"08918",
    "sg:province":"Barcelona",
    "wof:name":"Jimenez Jabalera Diego Antonio",
    "wof:placetype":"venue"
},
  "geometry": {"coordinates":[2.2246289253,41.4312858582],"type":"Point"}
}