{
  "type": "Feature",
  "properties": {
    "addr:full":"Avda Sierra (la), 2 Najera La Rioja 26300",
    "addr:housenumber":"2",
    "addr:postcode":"26300",
    "addr:street":"Avda Sierra La;Rioja",
    "iso:country":"ES",
    "sg:address":"Avda Sierra (la), 2",
    "sg:city":"Najera",
    "sg:orig_category":"Enfermeras: Consultas, Atenci\u00d3n A Domicilio",
    "sg:phone":"+34 941 36 38 16",
    "sg:postcode":"26300",
    "sg:province":"La Rioja",
    "wof:name":"Alguacial Ezquerro Maria Juliana",
    "wof:placetype":"venue"
},
  "geometry": {"coordinates":[-2.7275791168,42.4117546082],"type":"Point"}
}