{
  "type": "Feature",
  "properties": {
    "addr:full":"Calle de Ruiz De Salazar, 18 Le\u00f3n Le\u00f3n 24002",
    "addr:housenumber":"18",
    "addr:postcode":"24002",
    "addr:street":"Calle De Ruiz De Salazar;Leo\u0301N",
    "iso:country":"ES",
    "sg:address":"Calle de Ruiz De Salazar, 18",
    "sg:city":"Le\u00f3n",
    "sg:orig_category":"Encuadernaci\u00d3n E Impresi\u00d3n De Folletos",
    "sg:phone":"+34 987 23 88 22",
    "sg:postcode":"24002",
    "sg:province":"Le\u00f3n",
    "wof:name":"Tejuelo C.b.",
    "wof:placetype":"venue"
},
  "geometry": {"coordinates":[-5.5708661079,42.5990562439],"type":"Point"}
}