{
  "type": "Feature",
  "properties": {
    "iso:country":"ES",
    "sg:address":"Calle de Viera Y Clavijo, 12",
    "sg:city":"Arguineguin",
    "sg:orig_category":"Telas Y Sedas (al Por Menor)",
    "sg:phone":"+34 928 73 65 26",
    "sg:postcode":"35120",
    "sg:province":"Las Palmas",
    "wof:name":"Viju El Kilo De Arguineguin S.l",
    "wof:placetype":"venue"
},
  "geometry": {"coordinates":[-15.682759285,27.7612705231],"type":"Point"}
}