{
  "type": "Feature",
  "properties": {
    "iso:country":"ES",
    "sg:address":"Albar(la Bomba), S/n",
    "sg:city":"Ribera Molina",
    "sg:orig_category":"Fabricaci\u00d3n De Muebles Y De Accesorios De Cuartos De Ba\u00d1o",
    "sg:phone":"+34 968 64 94 63",
    "sg:postcode":"30508",
    "sg:province":"Murcia",
    "wof:name":"Tizba\u00f1o S.l.",
    "wof:placetype":"venue"
},
  "geometry": {"coordinates":[-1.2153710127,38.0174064636],"type":"Point"}
}