{
  "type": "Feature",
  "properties": {
    "addr:full":"Rambla F, S/n Mollerussa Lleida 25230",
    "addr:housenumber":"s / n",
    "addr:postcode":"25230",
    "addr:street":"Rambla F",
    "iso:country":"ES",
    "sg:address":"Rambla F, S/n",
    "sg:city":"Mollerussa",
    "sg:orig_category":"Ingenier\u00cda, Centros De Estudios (industria)",
    "sg:phone":"+34 973 71 02 20",
    "sg:postcode":"25230",
    "sg:province":"Lleida",
    "wof:name":"Farneman S.l.",
    "wof:placetype":"venue"
},
  "geometry": {"coordinates":[0.8936949968,41.6300392151],"type":"Point"}
}