{
  "type": "Feature",
  "properties": {
    "addr:full":"Calle de Doctor Ferran, 17 Albacete Albacete 02004",
    "addr:housenumber":"17",
    "addr:postcode":"02004",
    "addr:street":"Calle De Doctor Ferran",
    "iso:country":"ES",
    "sg:address":"Calle de Doctor Ferran, 17",
    "sg:city":"Albacete",
    "sg:orig_category":"Venta, Instalaci\u00d3n De Calefacci\u00d3n",
    "sg:phone":"+34 967 22 90 23",
    "sg:postcode":"02004",
    "sg:province":"Albacete",
    "wof:name":"Servigarra S.l.",
    "wof:placetype":"venue"
},
  "geometry": {"coordinates":[-1.862539053,38.9953765869],"type":"Point"}
}