{
  "type": "Feature",
  "properties": {
    "iso:country":"ES",
    "sg:address":"Calle de Miguel Angel, 1",
    "sg:city":"Madrid",
    "sg:orig_category":"Compraventa De Antig\u00dcedades",
    "sg:phone":"+34 913 10 07 25",
    "sg:postcode":"28010",
    "sg:province":"Madrid",
    "wof:name":"Garcia-mauri\u00f1o Pereda Luis",
    "wof:placetype":"venue"
},
  "geometry": {"coordinates":[-3.6914699078,40.4336509705],"type":"Point"}
}