{
  "type": "Feature",
  "properties": {
    "addr:full":"Plaz Estacion De La, 28 Aviles Asturias 33401",
    "addr:housenumber":"28",
    "addr:postcode":"33401",
    "iso:country":"ES",
    "sg:address":"Plaz Estacion De La, 28",
    "sg:city":"Aviles",
    "sg:orig_category":"Abogados",
    "sg:phone":"+34 985 55 17 93",
    "sg:postcode":"33401",
    "sg:province":"Asturias",
    "wof:name":"Juan Carlos Diez Villarreal",
    "wof:placetype":"venue"
},
  "geometry": {"coordinates":[-5.9211349487,43.5584754944],"type":"Point"}
}