{
  "type": "Feature",
  "properties": {
    "iso:country":"ES",
    "sg:address":"Carr Gabriel Ciscar, 32",
    "sg:city":"Oliva",
    "sg:orig_category":"Talleres: Ropa A Medida",
    "sg:phone":"+34 962 85 04 06",
    "sg:postcode":"46780",
    "sg:province":"Valencia",
    "wof:name":"Ferrer Mi\u00f1ana Fernando",
    "wof:placetype":"venue"
},
  "geometry": {"coordinates":[-0.1174120009,38.9179039001],"type":"Point"}
}