{
  "type": "Feature",
  "properties": {
    "iso:country":"ES",
    "sg:address":"Avda Espa\u00d1a, 5",
    "sg:city":"Corrales",
    "sg:classifiers":[
        {
            "category":"Autos & Motor Vehicles",
            "subcategory":"Automobile Sales",
            "type":"Retail Goods"
        }
    ],
    "sg:phone":"+34 942 83 12 46",
    "sg:postcode":"39400",
    "sg:province":"Cantabria",
    "wof:name":"Ramos Muriedas Jesus Alberto",
    "wof:placetype":"venue"
},
  "geometry": {"coordinates":[-4.0681390762,43.2584915161],"type":"Point"}
}