{
  "type": "Feature",
  "properties": {
    "iso:country":"ES",
    "sg:address":"Carrer de Cervantes, 3",
    "sg:city":"Amposta",
    "sg:orig_category":"Bares, Piano",
    "sg:phone":"+34 977 70 00 01",
    "sg:postcode":"43870",
    "sg:province":"Tarragona",
    "wof:name":"Corbera Ferre Jordi",
    "wof:placetype":"venue"
},
  "geometry": {"coordinates":[0.5770429969,40.7090835571],"type":"Point"}
}