{
  "type": "Feature",
  "properties": {
    "addr:full":"Avda Mediterraneo, 3 Benidorm Alicante 03500",
    "addr:housenumber":"3",
    "addr:postcode":"03500",
    "addr:street":"Avda Mediterraneo",
    "iso:country":"ES",
    "sg:address":"Avda Mediterraneo, 3",
    "sg:city":"Benidorm",
    "sg:orig_category":"Art\u00cdculos De Regalo (al Por Menor)",
    "sg:phone":"+34 965 85 25 44",
    "sg:postcode":"03500",
    "sg:province":"Alicante",
    "sg:website":"www.regalosmediterraneo.com",
    "wof:name":"Anajorfer Sl",
    "wof:placetype":"venue"
},
  "geometry": {"coordinates":[-0.1241255999,38.5371360779],"type":"Point"}
}