{
  "type": "Feature",
  "properties": {
    "addr:full":"Calle de Angel Sanchez Albaladejo, 4 Dolores Murcia 30739",
    "addr:housenumber":"4",
    "addr:postcode":"30739",
    "addr:street":"Calle De Angel Sanchez Albaladejo",
    "iso:country":"ES",
    "sg:address":"Calle de Angel Sanchez Albaladejo, 4",
    "sg:city":"Dolores",
    "sg:orig_category":"Producci\u00d3n De Abonos Y De Fertilizantes",
    "sg:phone":"+34 968 17 33 95",
    "sg:postcode":"30739",
    "sg:province":"Murcia",
    "wof:name":"Cosme Rodes S.l.",
    "wof:placetype":"venue"
},
  "geometry": {"coordinates":[-0.869309783,37.7778167725],"type":"Point"}
}