{
  "type": "Feature",
  "properties": {
    "addr:full":"Calle de General Oraa, 47 Madrid Madrid 28006",
    "addr:housenumber":"47",
    "addr:postcode":"madrid;28006",
    "addr:street":"Calle De General Oraa",
    "iso:country":"ES",
    "sg:address":"Calle de General Oraa, 47",
    "sg:city":"Madrid",
    "sg:orig_category":"Cursos Particulares, Asistencia Escolar",
    "sg:phone":"+34 915 62 40 74",
    "sg:postcode":"28006",
    "sg:province":"Madrid",
    "wof:name":"Espejel Jorquera Concepcion",
    "wof:placetype":"venue"
},
  "geometry": {"coordinates":[-3.6802771091,40.4361381531],"type":"Point"}
}