{
  "type": "Feature",
  "properties": {
    "iso:country":"ES",
    "sg:address":"Avda Coru\u00d1a, 12",
    "sg:city":"Pontedeume",
    "sg:orig_category":"M\u00c9dicos: Estomatolog\u00cda",
    "sg:phone":"+34 981 43 29 02",
    "sg:postcode":"15600",
    "sg:province":"La Coru\u00f1a",
    "wof:name":"Nu\u00f1ez Fernandez Amalia",
    "wof:placetype":"venue"
},
  "geometry": {"coordinates":[-8.1667547226,43.4045829773],"type":"Point"}
}