{
  "type": "Feature",
  "properties": {
    "addr:full":"Ctra Mojonera (la), 5 Cortijos De Marin Almer\u00eda 04740",
    "addr:housenumber":"5",
    "addr:postcode":"04740",
    "addr:street":"Ctra Mojonera La;Almeri\u0301A",
    "iso:country":"ES",
    "sg:address":"Ctra Mojonera (la), 5",
    "sg:city":"Cortijos De Marin",
    "sg:orig_category":"Electricidad: Instaladores",
    "sg:phone":"+34 950 32 54 69",
    "sg:postcode":"04740",
    "sg:province":"Almer\u00eda",
    "wof:name":"Asensio Martinez Francisco Daniel",
    "wof:placetype":"venue"
},
  "geometry": {"coordinates":[-2.6277637482,36.7621307373],"type":"Point"}
}