{
  "type": "Feature",
  "properties": {
    "iso:country":"ES",
    "sg:address":"Carrer de Arago, 145",
    "sg:city":"Palma",
    "sg:orig_category":"Tapicer\u00cdas",
    "sg:phone":"+34 971 24 39 11",
    "sg:postcode":"07005",
    "sg:province":"Islas Baleares",
    "sg:website":"www.tmaimi.com",
    "wof:name":"Ballester Barcelo Miguel",
    "wof:placetype":"venue"
},
  "geometry": {"coordinates":[2.6673700809,39.58177948],"type":"Point"}
}