{
  "type": "Feature",
  "properties": {
    "addr:full":"Ibarredi Kalea, 9 Jundiz \u00c1lava 01015",
    "addr:housenumber":"9",
    "addr:postcode":"01015",
    "addr:street":"Ibarredi Kalea;A\u0301Lava",
    "iso:country":"ES",
    "sg:address":"Ibarredi Kalea, 9",
    "sg:city":"Jundiz",
    "sg:orig_category":"Organizaciones Profesionales",
    "sg:phone":"+34 945 29 05 60",
    "sg:postcode":"01015",
    "sg:province":"\u00c1lava",
    "wof:name":"Pinturas Txomin S.l.",
    "wof:placetype":"venue"
},
  "geometry": {"coordinates":[-2.7283730507,42.8440895081],"type":"Point"}
}