{
  "type": "Feature",
  "properties": {
    "iso:country":"ES",
    "sg:address":"Calle de Perez Lugin, 17",
    "sg:city":"Coru\u00d1a",
    "sg:orig_category":"Doctores En Medicina",
    "sg:phone":"+34 981 27 83 62",
    "sg:postcode":"15011",
    "sg:province":"La Coru\u00f1a",
    "wof:name":"Ponte Cervigon Francisco",
    "wof:placetype":"venue"
},
  "geometry": {"coordinates":[-8.4157934189,43.3660354614],"type":"Point"}
}