{
  "type": "Feature",
  "properties": {
    "addr:full":"Calle de Bra\u00c7 Dels Horts, 13 Mislata Valencia 46920",
    "addr:housenumber":"13",
    "addr:postcode":"46920",
    "addr:street":"Calle De Brac\u0327 Dels Horts",
    "iso:country":"ES",
    "sg:address":"Calle de Bra\u00c7 Dels Horts, 13",
    "sg:city":"Mislata",
    "sg:orig_category":"Comercio De Piezas De Recambio Y De Accesorios De Veh\u00cdculos, Veh\u00cdculos Industriales",
    "sg:phone":"+34 963 70 25 99",
    "sg:postcode":"46920",
    "sg:province":"Valencia",
    "wof:name":"Recambios Juan S.l.",
    "wof:placetype":"venue"
},
  "geometry": {"coordinates":[-0.4217131138,39.4740333557],"type":"Point"}
}