{
  "type": "Feature",
  "properties": {
    "addr:full":"Calle de Hernandez Iglesias, 20 Madrid Madrid 28027",
    "addr:housenumber":"20",
    "addr:postcode":"madrid;28027",
    "addr:street":"Calle De Hernandez Iglesias",
    "iso:country":"ES",
    "sg:address":"Calle de Hernandez Iglesias, 20",
    "sg:city":"Madrid",
    "sg:orig_category":"Herramientas Manuales (fabricaci\u00d3n, Al Por Mayor)",
    "sg:phone":"+34 913 67 87 96",
    "sg:postcode":"28027",
    "sg:province":"Madrid",
    "wof:name":"Francisco Mu\u00f1oz Manuel De",
    "wof:placetype":"venue"
},
  "geometry": {"coordinates":[-3.6448009014,40.4418640137],"type":"Point"}
}