{
  "type": "Feature",
  "properties": {
    "iso:country":"ES",
    "sg:address":"Avda Moscatel, 4",
    "sg:city":"Torre Mar",
    "sg:orig_category":"Caf\u00c9s, Bares, Cervecer\u00cdas",
    "sg:phone":"+34 952 54 56 96",
    "sg:postcode":"29740",
    "sg:province":"M\u00e1laga",
    "wof:name":"Escalona Santiago Rafael",
    "wof:placetype":"venue"
},
  "geometry": {"coordinates":[-4.4171347618,36.7454071045],"type":"Point"}
}