{
  "type": "Feature",
  "properties": {
    "iso:country":"ES",
    "sg:address":"Barr Arraibi, 10",
    "sg:city":"Arraibi",
    "sg:orig_category":"Asociaciones Y Clubs Deportivos",
    "sg:phone":"+34 946 31 38 79",
    "sg:postcode":"48330",
    "sg:province":"Vizcaya",
    "wof:name":"Sociedad De Caza Y Pesca De Lemona",
    "wof:placetype":"venue"
},
  "geometry": {"coordinates":[-2.7691090107,43.2078361511],"type":"Point"}
}