{
  "type": "Feature",
  "properties": {
    "iso:country":"ES",
    "sg:address":"Calle de Eduardo Torroja (de), 3",
    "sg:city":"Mostoles",
    "sg:orig_category":"Empresas De Carpinter\u00cda De Madera",
    "sg:phone":"+34 916 46 84 98",
    "sg:postcode":"28936",
    "sg:province":"Madrid",
    "wof:name":"Gonzalo Casado Rubio Y Otros Cdad",
    "wof:placetype":"venue"
},
  "geometry": {"coordinates":[-3.8474693298,40.3179168701],"type":"Point"}
}