{
  "type": "Feature",
  "properties": {
    "iso:country":"ES",
    "sg:address":"Carrer de Antoni Roig (d'), 11",
    "sg:city":"Torredembarra",
    "sg:orig_category":"Frutas, Legumbres Frescas Y Tempranas (al Por Menor)",
    "sg:phone":"+34 977 64 22 61",
    "sg:postcode":"43830",
    "sg:province":"Tarragona",
    "wof:name":"Miracle Sole Jose",
    "wof:placetype":"venue"
},
  "geometry": {"coordinates":[1.3976659775,41.1443328857],"type":"Point"}
}