{
  "type": "Feature",
  "properties": {
    "addr:full":"Carrer de Teodor Gonzalez (de), 8 Tortosa Tarragona 43500",
    "addr:postcode":"43500",
    "addr:street":"Carrer De Teodor Gonzalez De",
    "iso:country":"ES",
    "sg:address":"Carrer de Teodor Gonzalez (de), 8",
    "sg:city":"Tortosa",
    "sg:orig_category":"Asesor\u00cda Fiscal Y Jur\u00cddica",
    "sg:phone":"+34 977 44 36 61",
    "sg:postcode":"43500",
    "sg:province":"Tarragona",
    "wof:name":"Mangrane-gari Consultors D'empreses S.l",
    "wof:placetype":"venue"
},
  "geometry": {"coordinates":[0.5197240114,40.8099136353],"type":"Point"}
}