{
  "type": "Feature",
  "properties": {
    "iso:country":"ES",
    "sg:address":"Calle de Poeta Jose Espronceda, 7",
    "sg:city":"Torrent",
    "sg:orig_category":"Fotograf\u00cda Art\u00cdstica Y Retratos",
    "sg:phone":"+34 961 57 48 07",
    "sg:postcode":"46900",
    "sg:province":"Valencia",
    "wof:name":"Ponce Garcia Fidel",
    "wof:placetype":"venue"
},
  "geometry": {"coordinates":[-0.4611580074,39.4383964539],"type":"Point"}
}