{
  "type": "Feature",
  "properties": {
    "iso:country":"ES",
    "sg:address":"Calle de Tomas Redondo, 1",
    "sg:city":"Madrid",
    "sg:orig_category":"Imprenta",
    "sg:phone":"+34 913 82 15 15",
    "sg:postcode":"28033",
    "sg:province":"Madrid",
    "wof:name":"Ctr Graficas S.l.",
    "wof:placetype":"venue"
},
  "geometry": {"coordinates":[-3.6297280788,40.4726524353],"type":"Point"}
}