{
  "type": "Feature",
  "properties": {
    "iso:country":"ES",
    "sg:address":"Carretera Madrid-coru\u00f1a, 2",
    "sg:city":"Villafranca Bierzo",
    "sg:orig_category":"Restaurantes",
    "sg:phone":"+34 987 54 25 06",
    "sg:postcode":"24500",
    "sg:province":"Le\u00f3n",
    "wof:name":"Capricho Bierzo S.l",
    "wof:placetype":"venue"
},
  "geometry": {"coordinates":[-6.8084750175,42.6093559265],"type":"Point"}
}