{
  "type": "Feature",
  "properties": {
    "addr:full":"Carrer de Escaladei (d'), 1 Salou Tarragona 43840",
    "addr:housenumber":"1",
    "addr:postcode":"43840",
    "addr:street":"Carrer De Escaladei D '",
    "iso:country":"ES",
    "sg:address":"Carrer de Escaladei (d'), 1",
    "sg:city":"Salou",
    "sg:orig_category":"Molduras, Junquillos, Listones Y Molduras Perforadas",
    "sg:phone":"+34 977 38 80 60",
    "sg:postcode":"43840",
    "sg:province":"Tarragona",
    "wof:name":"Bakaitis  Julius",
    "wof:placetype":"venue"
},
  "geometry": {"coordinates":[1.1400997639,41.0791358948],"type":"Point"}
}