{
  "type": "Feature",
  "properties": {
    "addr:full":"Samarango, 6 San Pedro Alcantara M\u00e1laga 29670",
    "addr:housenumber":"6",
    "addr:postcode":"29670",
    "addr:street":"Samarango",
    "iso:country":"ES",
    "sg:address":"Samarango, 6",
    "sg:city":"San Pedro Alcantara",
    "sg:orig_category":"Inmobiliaria (agencias)",
    "sg:phone":"+34 952 78 86 07",
    "sg:postcode":"29670",
    "sg:province":"M\u00e1laga",
    "wof:name":"J.l. Inversiones S.l.",
    "wof:placetype":"venue"
},
  "geometry": {"coordinates":[-4.9894766808,36.4856033325],"type":"Point"}
}