{
  "type": "Feature",
  "properties": {
    "iso:country":"ES",
    "sg:address":"Carrer de Guardiola I Feliu, 6",
    "sg:city":"Barcelona",
    "sg:orig_category":"Disfraces",
    "sg:phone":"+34 933 45 53 95",
    "sg:postcode":"08030",
    "sg:province":"Barcelona",
    "wof:name":"Bruno Vela Concepcion",
    "wof:placetype":"venue"
},
  "geometry": {"coordinates":[2.1894590855,41.4386482239],"type":"Point"}
}