{
  "type": "Feature",
  "properties": {
    "addr:full":"Cmno Esgaravita (de La), 34 Alcala Henares Madrid 28805",
    "addr:housenumber":"34",
    "addr:postcode":"28805",
    "addr:street":"Cmno Esgaravita De La",
    "iso:country":"ES",
    "sg:address":"Cmno Esgaravita (de La), 34",
    "sg:city":"Alcala Henares",
    "sg:orig_category":"Promotores Constructores",
    "sg:phone":"+34 918 77 17 95",
    "sg:postcode":"28805",
    "sg:province":"Madrid",
    "wof:name":"Armantinnna",
    "wof:placetype":"venue"
},
  "geometry": {"coordinates":[-3.3402180672,40.4960632324],"type":"Point"}
}