{
  "type": "Feature",
  "properties": {
    "iso:country":"ES",
    "sg:address":"Pase Constitucion, 36",
    "sg:city":"Alpera",
    "sg:orig_category":"Mec\u00c1nico Del Autom\u00d3vil",
    "sg:phone":"+34 967 33 00 64",
    "sg:postcode":"02690",
    "sg:province":"Albacete",
    "wof:name":"Castillo Lopez Juan Miguel",
    "wof:placetype":"venue"
},
  "geometry": {"coordinates":[-1.2333979607,38.958820343],"type":"Point"}
}