{
  "type": "Feature",
  "properties": {
    "addr:full":"Calle de Banderas De Castilla, 28 Torrijos Toledo 45500",
    "addr:housenumber":"28",
    "addr:postcode":"45500",
    "addr:street":"Calle De Banderas De Castilla",
    "iso:country":"ES",
    "sg:address":"Calle de Banderas De Castilla, 28",
    "sg:city":"Torrijos",
    "sg:orig_category":"Escayola Y Productos De Escayola (fabricaci\u00d3n, Al Por Mayor)",
    "sg:phone":"+34 925 76 40 63",
    "sg:postcode":"45500",
    "sg:province":"Toledo",
    "wof:name":"A. Rodriguez Techos Y Escayolas S.l.",
    "wof:placetype":"venue"
},
  "geometry": {"coordinates":[-4.2867937088,39.975353241],"type":"Point"}
}