{
  "type": "Feature",
  "properties": {
    "iso:country":"ES",
    "sg:address":"Carrer de Victoria, 4",
    "sg:city":"Barcelona",
    "sg:orig_category":"Albergues",
    "sg:phone":"+34 933 15 28 55",
    "sg:postcode":"08003",
    "sg:province":"Barcelona",
    "wof:name":"Caputxins Catalunya Curia Provincial",
    "wof:placetype":"venue"
},
  "geometry": {"coordinates":[2.1783618927,41.3889923096],"type":"Point"}
}