{
  "type": "Feature",
  "properties": {
    "iso:country":"ES",
    "sg:address":"Calle de Princesa Guacimara, 65",
    "sg:city":"Santa Cruz De Tenerife",
    "sg:orig_category":"Agencias Y Agentes Comerciales, Representantes",
    "sg:phone":"+34 922 20 67 56",
    "sg:postcode":"38008",
    "sg:province":"Santa Cruz De Tenerife",
    "wof:name":"Tato E Hijos S.l.",
    "wof:placetype":"venue"
},
  "geometry": {"coordinates":[-16.2703704834,28.4706077576],"type":"Point"}
}