{
  "type": "Feature",
  "properties": {
    "addr:full":"Calle de Do\u00d1a Juana I De Castilla, 24 Madrid Madrid 28027",
    "addr:housenumber":"24",
    "addr:postcode":"madrid;28027",
    "addr:street":"Calle De Don\u0303A",
    "iso:country":"ES",
    "sg:address":"Calle de Do\u00d1a Juana I De Castilla, 24",
    "sg:city":"Madrid",
    "sg:orig_category":"Moda",
    "sg:phone":"+34 917 41 73 57",
    "sg:postcode":"28027",
    "sg:province":"Madrid",
    "wof:name":"Cort Lantero Candela",
    "wof:placetype":"venue"
},
  "geometry": {"coordinates":[-3.6317200661,40.4464874268],"type":"Point"}
}