{
  "type": "Feature",
  "properties": {
    "addr:full":"Carr Combat, 26 Cervera Lleida 25200",
    "addr:housenumber":"26",
    "addr:postcode":"25200",
    "addr:street":"Carr Combat",
    "iso:country":"ES",
    "sg:address":"Carr Combat, 26",
    "sg:city":"Cervera",
    "sg:orig_category":"Electrodom\u00c9sticos (al Por Menor)",
    "sg:phone":"+34 973 53 02 70",
    "sg:postcode":"25200",
    "sg:province":"Lleida",
    "wof:name":"Video Servis S.a.",
    "wof:placetype":"venue"
},
  "geometry": {"coordinates":[1.2729029655,41.6711349487],"type":"Point"}
}