{
  "type": "Feature",
  "properties": {
    "addr:full":"Avgd Vicente Ferri, 15 Canals Valencia 46650",
    "addr:housenumber":"15",
    "addr:postcode":"46650",
    "addr:street":"Ferri",
    "iso:country":"ES",
    "sg:address":"Avgd Vicente Ferri, 15",
    "sg:city":"Canals",
    "sg:orig_category":"Reposter\u00cdas",
    "sg:phone":"+34 962 24 27 22",
    "sg:postcode":"46650",
    "sg:province":"Valencia",
    "wof:name":"Horno Rivelles S.l.",
    "wof:placetype":"venue"
},
  "geometry": {"coordinates":[-0.58564502,38.9632034302],"type":"Point"}
}