{
  "type": "Feature",
  "properties": {
    "addr:full":"Calle de Rio Mijares, 14 Onda Castell\u00f3n 12200",
    "addr:housenumber":"14",
    "addr:postcode":"12200",
    "addr:street":"Calle De Rio Mijares;Castello\u0301N",
    "iso:country":"ES",
    "sg:address":"Calle de Rio Mijares, 14",
    "sg:city":"Onda",
    "sg:classifiers":[
        {
            "category":"Personal",
            "subcategory":"Barber",
            "type":"Services"
        }
    ],
    "sg:phone":"+34 964 77 22 61",
    "sg:postcode":"12200",
    "sg:province":"Castell\u00f3n",
    "sg:tags":[
        "caballeros",
        "de",
        "peluqueros"
    ],
    "wof:name":"Ramos Ortells Salvador",
    "wof:placetype":"venue"
},
  "geometry": {"coordinates":[-0.2654359937,39.9665908813],"type":"Point"}
}