{
  "type": "Feature",
  "properties": {
    "iso:country":"ES",
    "sg:address":"C. Arenal, 1",
    "sg:city":"Pontes Garcia Rodriguez",
    "sg:orig_category":"M\u00c9dicos: Estomatolog\u00cda",
    "sg:phone":"+34 981 45 27 01",
    "sg:postcode":"15320",
    "sg:province":"La Coru\u00f1a",
    "wof:name":"Herranz Pena Placido",
    "wof:placetype":"venue"
},
  "geometry": {"coordinates":[-7.8519802094,43.4437828064],"type":"Point"}
}