{
  "type": "Feature",
  "properties": {
    "addr:full":"Carr Banys De La Moreria, 13 Xativa Valencia 46800",
    "addr:housenumber":"13",
    "addr:postcode":"46800",
    "addr:street":"Carr Banys De La Moreria",
    "iso:country":"ES",
    "sg:address":"Carr Banys De La Moreria, 13",
    "sg:city":"Xativa",
    "sg:orig_category":"Empresas De Carpinter\u00cda Met\u00c1lica",
    "sg:phone":"+34 962 27 51 43",
    "sg:postcode":"46800",
    "sg:province":"Valencia",
    "wof:name":"Carpinterol S.l.",
    "wof:placetype":"venue"
},
  "geometry": {"coordinates":[-0.5290589929,38.9861297607],"type":"Point"}
}