{
  "type": "Feature",
  "properties": {
    "iso:country":"ES",
    "sg:address":"Avda Principe De Asturias, 20",
    "sg:city":"Zamora",
    "sg:classifiers":[
        {
            "category":"Autos & Motor Vehicles",
            "subcategory":"Automobile Sales",
            "type":"Retail Goods"
        }
    ],
    "sg:phone":"+34 980 51 34 85",
    "sg:postcode":"49012",
    "sg:province":"Zamora",
    "wof:name":"Auto-escuela Viriato S.l.",
    "wof:placetype":"venue"
},
  "geometry": {"coordinates":[-5.7373490334,41.5107841492],"type":"Point"}
}