{
  "type": "Feature",
  "properties": {
    "addr:full":"Calle de Corredera, 21 Puerto Mazarron Murcia 30860",
    "addr:housenumber":"21",
    "addr:postcode":"30860",
    "addr:street":"Calle De Corredera",
    "iso:country":"ES",
    "sg:address":"Calle de Corredera, 21",
    "sg:city":"Puerto Mazarron",
    "sg:orig_category":"Confecci\u00d3n De Trajes Para Se\u00d1oras",
    "sg:phone":"+34 968 59 56 17",
    "sg:postcode":"30860",
    "sg:province":"Murcia",
    "wof:name":"Garcia Mendoza Pedro Antonio",
    "wof:placetype":"venue"
},
  "geometry": {"coordinates":[-1.2600742579,37.5644378662],"type":"Point"}
}