{
  "type": "Feature",
  "properties": {
    "addr:full":"Carrer de Aneto, S/n Barcelona Barcelona 08031",
    "addr:housenumber":"s / n",
    "addr:postcode":"08031",
    "addr:street":"Carrer De Aneto",
    "iso:country":"ES",
    "sg:address":"Carrer de Aneto, S/n",
    "sg:city":"Barcelona",
    "sg:orig_category":"Centros De Educaci\u00d3n Especial",
    "sg:phone":"+34 934 29 53 84",
    "sg:postcode":"08031",
    "sg:province":"Barcelona",
    "wof:name":"Ajuntament De Barcelona",
    "wof:placetype":"venue"
},
  "geometry": {"coordinates":[2.1716997623,41.4317703247],"type":"Point"}
}