{
  "type": "Feature",
  "properties": {
    "addr:full":"Calle de Libertad, 20 Bejar Salamanca 37700",
    "addr:housenumber":"20",
    "addr:postcode":"37700",
    "addr:street":"Calle De Libertad",
    "iso:country":"ES",
    "sg:address":"Calle de Libertad, 20",
    "sg:city":"Bejar",
    "sg:orig_category":"Carnicer\u00cdas, Carnicer\u00cdas",
    "sg:phone":"+34 923 40 14 05",
    "sg:postcode":"37700",
    "sg:province":"Salamanca",
    "wof:name":"Hernandez Izquierdo Jose Manuel",
    "wof:placetype":"venue"
},
  "geometry": {"coordinates":[-5.7635807991,40.3860244751],"type":"Point"}
}