{
  "type": "Feature",
  "properties": {
    "iso:country":"ES",
    "sg:address":"Avda Canarias, 322",
    "sg:city":"Vecindario",
    "sg:orig_category":"Servicios De Higiene Y Peluquer\u00cda Para Perros Y Gatos",
    "sg:phone":"+34 928 79 24 69",
    "sg:postcode":"35110",
    "sg:province":"Las Palmas",
    "wof:name":"Matias Suarez Juan Manuel",
    "wof:placetype":"venue"
},
  "geometry": {"coordinates":[-15.4444026947,27.845954895],"type":"Point"}
}