{
  "type": "Feature",
  "properties": {
    "addr:full":"Calle de Fonseca, 4 Salamanca Salamanca 37002",
    "addr:housenumber":"4",
    "addr:postcode":"37002",
    "addr:street":"Calle De Fonseca",
    "iso:country":"ES",
    "sg:address":"Calle de Fonseca, 4",
    "sg:city":"Salamanca",
    "sg:orig_category":"Asociaciones, Organismos Culturales Y Socioeducativos",
    "sg:phone":"+34 923 21 00 39",
    "sg:postcode":"37002",
    "sg:province":"Salamanca",
    "wof:name":"Asociacion Iberoamericana De Postgrado",
    "wof:placetype":"venue"
},
  "geometry": {"coordinates":[-5.6692857742,40.9656944275],"type":"Point"}
}