{
  "type": "Feature",
  "properties": {
    "iso:country":"ES",
    "sg:address":"Cmno Tximistarri De, 46",
    "sg:city":"Igeldo",
    "sg:classifiers":[
        {
            "category":"Manufacturing",
            "subcategory":"Metals",
            "type":"Manufacturing & Wholesale Goods"
        }
    ],
    "sg:phone":"+34 943 31 73 72",
    "sg:postcode":"20008",
    "sg:province":"Guip\u00f9zcoa",
    "sg:tags":[
        "en",
        "fundiciones"
    ],
    "wof:name":"Fundiciones Del Estanda S. A.",
    "wof:placetype":"venue"
},
  "geometry": {"coordinates":[-2.0392899513,43.3088798523],"type":"Point"}
}