{
  "type": "Feature",
  "properties": {
    "addr:full":"Carr Aitana, S/n Silla Valencia 46460",
    "addr:housenumber":"s / n",
    "addr:postcode":"46460",
    "addr:street":"Carr Aitana",
    "iso:country":"ES",
    "sg:address":"Carr Aitana, S/n",
    "sg:city":"Silla",
    "sg:orig_category":"Impermeabilizantes",
    "sg:phone":"+34 961 21 14 21",
    "sg:postcode":"46460",
    "sg:province":"Valencia",
    "wof:name":"Tabiques Pluviales Mediterraneo S.c.p.",
    "wof:placetype":"venue"
},
  "geometry": {"coordinates":[-0.4238590002,39.3545036316],"type":"Point"}
}