{
  "type": "Feature",
  "properties": {
    "addr:full":"Avda Santiago Madrigal, 17 Salamanca Salamanca 37003",
    "addr:housenumber":"17",
    "addr:postcode":"37003",
    "addr:street":"Avda Santiago Madrigal",
    "iso:country":"ES",
    "sg:address":"Avda Santiago Madrigal, 17",
    "sg:city":"Salamanca",
    "sg:orig_category":"Reposter\u00cdas",
    "sg:phone":"+34 923 18 27 55",
    "sg:postcode":"37003",
    "sg:province":"Salamanca",
    "wof:name":"Galiano Gonzalez Antonio",
    "wof:placetype":"venue"
},
  "geometry": {"coordinates":[-5.6399817467,40.970741272],"type":"Point"}
}