{
  "type": "Feature",
  "properties": {
    "addr:full":"R. Oveja Mayor, S/n Casar Palomero C\u00e1ceres 10640",
    "addr:housenumber":"s / n",
    "addr:postcode":"10640",
    "addr:street":"Oveja Mayor;Ca\u0301Ceres",
    "iso:country":"ES",
    "sg:address":"R. Oveja Mayor, S/n",
    "sg:city":"Casar Palomero",
    "sg:orig_category":"Frutas Y Legumbres Frescas (al Por Mayor)",
    "sg:phone":"+34 927 43 62 14",
    "sg:postcode":"10640",
    "sg:province":"C\u00e1ceres",
    "wof:name":"Cooperativa Cruz Bendita Olivarera",
    "wof:placetype":"venue"
},
  "geometry": {"coordinates":[-6.2573060989,40.2955513],"type":"Point"}
}