{
  "type": "Feature",
  "properties": {
    "iso:country":"ES",
    "sg:address":"Av Pau Casals, 44",
    "sg:city":"Jonquera",
    "sg:orig_category":"Mec\u00c1nico Del Autom\u00d3vil",
    "sg:phone":"+34 972 55 40 68",
    "sg:postcode":"17700",
    "sg:province":"Girona",
    "wof:name":"Cardoso Tomas Jose",
    "wof:placetype":"venue"
},
  "geometry": {"coordinates":[2.8697710037,42.4259414673],"type":"Point"}
}