{
  "type": "Feature",
  "properties": {
    "addr:full":"Carrer de Cami Vell De Sant Esteve, 33 Martorell Barcelona 08760",
    "addr:housenumber":"33",
    "addr:postcode":"08760",
    "addr:street":"Carrer De Cami Vell De Sant Esteve",
    "iso:country":"ES",
    "sg:address":"Carrer de Cami Vell De Sant Esteve, 33",
    "sg:city":"Martorell",
    "sg:orig_category":"Notarios",
    "sg:phone":"+34 937 74 32 00",
    "sg:postcode":"08760",
    "sg:province":"Barcelona",
    "wof:name":"Vazquez Atkinson Carlos",
    "wof:placetype":"venue"
},
  "geometry": {"coordinates":[1.9191169739,41.4781913757],"type":"Point"}
}