{
  "type": "Feature",
  "properties": {
    "addr:full":"Calle de Caupolican, 1 Caceres C\u00e1ceres 10005",
    "addr:housenumber":"1",
    "addr:postcode":"10005",
    "addr:street":"Calle De Caupolican;Ca\u0301Ceres",
    "iso:country":"ES",
    "sg:address":"Calle de Caupolican, 1",
    "sg:city":"Caceres",
    "sg:orig_category":"Electrodom\u00c9sticos (al Por Menor)",
    "sg:phone":"+34 927 22 14 69",
    "sg:postcode":"10005",
    "sg:province":"C\u00e1ceres",
    "sg:website":"www.iscamber.com",
    "wof:name":"Iscamber S.l.",
    "wof:placetype":"venue"
},
  "geometry": {"coordinates":[-6.3781857491,39.4627151489],"type":"Point"}
}