{
  "type": "Feature",
  "properties": {
    "iso:country":"ES",
    "sg:address":"Aita Lertxundi Kalea, 12",
    "sg:city":"Orio",
    "sg:orig_category":"Empresas De Limpieza",
    "sg:phone":"+34 943 13 16 75",
    "sg:postcode":"20810",
    "sg:province":"Guip\u00f9zcoa",
    "wof:name":"Limpiezas Biok Garbiketak Cd",
    "wof:placetype":"venue"
},
  "geometry": {"coordinates":[-2.1251831055,43.2766799927],"type":"Point"}
}