{
  "type": "Feature",
  "properties": {
    "iso:country":"ES",
    "sg:address":"Pol Ind Usila, S/n",
    "sg:city":"Ugao-miraballes",
    "sg:orig_category":"Centros Empresariales",
    "sg:phone":"+34 946 48 26 22",
    "sg:postcode":"48490",
    "sg:province":"Vizcaya",
    "wof:name":"Servicios Logisticos Aringar S.l.",
    "wof:placetype":"venue"
},
  "geometry": {"coordinates":[-2.9049639702,43.1779060364],"type":"Point"}
}