{
  "type": "Feature",
  "properties": {
    "iso:country":"ES",
    "sg:address":"Via Pasteur (de), 7",
    "sg:city":"Boisaca",
    "sg:orig_category":"Comercio De Piezas De Recambio Y De Accesorios De Veh\u00cdculos, Veh\u00cdculos Industriales",
    "sg:phone":"+34 981 51 99 80",
    "sg:postcode":"15890",
    "sg:province":"La Coru\u00f1a",
    "wof:name":"Federal Mogul Aftermarket Espa\u00c4 S.a.",
    "wof:placetype":"venue"
},
  "geometry": {"coordinates":[-8.4769210815,42.8835983276],"type":"Point"}
}