{
  "type": "Feature",
  "properties": {
    "iso:country":"ES",
    "sg:address":"Calle de Pedro Laborde, 11",
    "sg:city":"Madrid",
    "sg:orig_category":"Frutas, Legumbres Frescas Y Tempranas (al Por Menor)",
    "sg:phone":"+34 913 03 59 89",
    "sg:postcode":"28038",
    "sg:province":"Madrid",
    "wof:name":"Hermanos Benito-estomago S.a.",
    "wof:placetype":"venue"
},
  "geometry": {"coordinates":[-3.6474308968,40.389087677],"type":"Point"}
}