{
  "type": "Feature",
  "properties": {
    "iso:country":"ES",
    "sg:address":"Carrer de Rafael Alberti, 2",
    "sg:city":"Cas Catala-illetes",
    "sg:orig_category":"Delegados, Agentes De Tr\u00c1nsito, Auxiliares De Transporte Internacional",
    "sg:phone":"+34 971 70 22 09",
    "sg:postcode":"07181",
    "sg:province":"Islas Baleares",
    "wof:name":"Trans Orion S.l.",
    "wof:placetype":"venue"
},
  "geometry": {"coordinates":[2.5352098942,39.5245780945],"type":"Point"}
}