{
  "type": "Feature",
  "properties": {
    "addr:full":"Calle de Martinez Barrionuevo, 13 Malaga M\u00e1laga 29014",
    "addr:housenumber":"13",
    "addr:postcode":"29014",
    "addr:street":"Calle De Martinez Barrionuevo;Ma\u0301Laga",
    "iso:country":"ES",
    "sg:address":"Calle de Martinez Barrionuevo, 13",
    "sg:city":"Malaga",
    "sg:orig_category":"Servicios De Telecomunicaciones",
    "sg:phone":"+34 952 25 57 02",
    "sg:postcode":"29014",
    "sg:province":"M\u00e1laga",
    "wof:name":"Nuvitel.com,s.coop.and",
    "wof:placetype":"venue"
},
  "geometry": {"coordinates":[-4.4231491089,36.7306137085],"type":"Point"}
}