{
  "type": "Feature",
  "properties": {
    "addr:full":"As Airas, S/n Moreiras Ourense 32920",
    "addr:housenumber":"/ n",
    "addr:postcode":"32920",
    "addr:street":"Airas S",
    "iso:country":"ES",
    "sg:address":"As Airas, S/n",
    "sg:city":"Moreiras",
    "sg:orig_category":"Enfermeras: Consultas, Atenci\u00d3n A Domicilio",
    "sg:phone":"+34 988 26 22 04",
    "sg:postcode":"32920",
    "sg:province":"Ourense",
    "wof:name":"Padron Gil Concepcion",
    "wof:placetype":"venue"
},
  "geometry": {"coordinates":[-7.9516019821,42.2935142517],"type":"Point"}
}