{
  "type": "Feature",
  "properties": {
    "iso:country":"ES",
    "sg:address":"Ctra Rubi, 288",
    "sg:city":"Terrassa",
    "sg:orig_category":"Fabricaci\u00d3n De Telas Y Sedas",
    "sg:phone":"+34 937 88 43 16",
    "sg:postcode":"08228",
    "sg:province":"Barcelona",
    "wof:name":"Textil Roig S. A.",
    "wof:placetype":"venue"
},
  "geometry": {"coordinates":[2.0349860191,41.5328407288],"type":"Point"}
}