{
  "type": "Feature",
  "properties": {
    "addr:full":"Avda Alcora, 98 Castellon Castell\u00f3n 12006",
    "addr:housenumber":"98",
    "addr:postcode":"12006",
    "addr:street":"Avda Alcora",
    "iso:country":"ES",
    "sg:address":"Avda Alcora, 98",
    "sg:city":"Castellon",
    "sg:orig_category":"Plomeros",
    "sg:phone":"+34 964 34 00 97",
    "sg:postcode":"12006",
    "sg:province":"Castell\u00f3n",
    "wof:name":"Construcciones Edo Andres, S.l.",
    "wof:placetype":"venue"
},
  "geometry": {"coordinates":[-0.1292939931,40.0168533325],"type":"Point"}
}