{
  "type": "Feature",
  "properties": {
    "iso:country":"ES",
    "sg:address":"Calle de Madera, 30",
    "sg:city":"Madrid",
    "sg:orig_category":"Empresas De Carpinter\u00cda De Madera",
    "sg:phone":"+34 915 32 33 69",
    "sg:postcode":"28004",
    "sg:province":"Madrid",
    "wof:name":"Ballestin Lara Antolin",
    "wof:placetype":"venue"
},
  "geometry": {"coordinates":[-3.7037758827,40.4239044189],"type":"Point"}
}