{
  "type": "Feature",
  "properties": {
    "iso:country":"ES",
    "sg:address":"Calle de Emilio Martin Encinas (de), 15",
    "sg:city":"Coslada",
    "sg:orig_category":"Institutos De Belleza",
    "sg:phone":"+34 916 72 21 70",
    "sg:postcode":"28820",
    "sg:province":"Madrid",
    "wof:name":"Salon De Belleza Sacra S.l.",
    "wof:placetype":"venue"
},
  "geometry": {"coordinates":[-3.5645070076,40.4260902405],"type":"Point"}
}