{
  "type": "Feature",
  "properties": {
    "iso:country":"ES",
    "sg:address":"Calle de Julio, 26",
    "sg:city":"Gijon",
    "sg:orig_category":"Transporte En General",
    "sg:phone":"+34 985 16 00 74",
    "sg:postcode":"33209",
    "sg:province":"Asturias",
    "wof:name":"Perez Alvarez Francisco Javier",
    "wof:placetype":"venue"
},
  "geometry": {"coordinates":[-5.6650118828,43.5291061401],"type":"Point"}
}