{
  "type": "Feature",
  "properties": {
    "addr:full":"Calle de Gran Capitan, 37 Montijo Badajoz 06480",
    "addr:housenumber":"37",
    "addr:postcode":"06480",
    "addr:street":"Calle De Gran Capitan",
    "iso:country":"ES",
    "sg:address":"Calle de Gran Capitan, 37",
    "sg:city":"Montijo",
    "sg:orig_category":"Pescader\u00cdas (al Por Menor)",
    "sg:phone":"+34 924 45 58 26",
    "sg:postcode":"06480",
    "sg:province":"Badajoz",
    "wof:name":"Martin Fernandez Alvaro",
    "wof:placetype":"venue"
},
  "geometry": {"coordinates":[-6.6182441711,38.9135742188],"type":"Point"}
}