{
  "type": "Feature",
  "properties": {
    "iso:country":"ES",
    "sg:address":"Calle de Muelle, S/n",
    "sg:city":"Santa Pola",
    "sg:orig_category":"Deportes N\u00c1uticos, Acu\u00c1ticos Y Subacu\u00c1ticos: Art\u00cdculos Y Equipo (al Por Menor)",
    "sg:phone":"+34 965 41 44 47",
    "sg:postcode":"03130",
    "sg:province":"Alicante",
    "wof:name":"Marina Miramar Sa",
    "wof:placetype":"venue"
},
  "geometry": {"coordinates":[-0.5556973219,38.1915016174],"type":"Point"}
}