{
  "type": "Feature",
  "properties": {
    "addr:full":"Cmno Villordo El, S/n Benalmadena M\u00e1laga 29639",
    "addr:postcode":"29639",
    "addr:street":"Cmno Villordo El S / N;Ma\u0301Laga",
    "iso:country":"ES",
    "sg:address":"Cmno Villordo El, S/n",
    "sg:city":"Benalmadena",
    "sg:orig_category":"Centros Empresariales",
    "sg:phone":"+34 952 56 95 44",
    "sg:postcode":"29639",
    "sg:province":"M\u00e1laga",
    "wof:name":"North Umbrian S.l.",
    "wof:placetype":"venue"
},
  "geometry": {"coordinates":[-4.5707449913,36.5917205811],"type":"Point"}
}