{
  "type": "Feature",
  "properties": {
    "iso:country":"ES",
    "sg:address":"Bo Real Y Cuarto, 3",
    "sg:city":"Riocorvo",
    "sg:orig_category":"Chapister\u00cda",
    "sg:phone":"+34 942 81 95 54",
    "sg:postcode":"39460",
    "sg:province":"Cantabria",
    "wof:name":"Carrocerias Gomez S.c.",
    "wof:placetype":"venue"
},
  "geometry": {"coordinates":[-4.0711808205,43.3099975586],"type":"Point"}
}