{
  "type": "Feature",
  "properties": {
    "addr:full":"Avda Cardenal Herrera Oria, 266 Madrid Madrid 28035",
    "addr:housenumber":"266",
    "addr:postcode":"28035",
    "addr:street":"Avda Cardenal Herrera Oria",
    "iso:country":"ES",
    "sg:address":"Avda Cardenal Herrera Oria, 266",
    "sg:city":"Madrid",
    "sg:orig_category":"Supermercados Y Hipermercados",
    "sg:phone":"+34 913 16 17 80",
    "sg:postcode":"28035",
    "sg:province":"Madrid",
    "wof:name":"Dinosol Supermercados S.l.",
    "wof:placetype":"venue"
},
  "geometry": {"coordinates":[-3.7242650986,40.4797668457],"type":"Point"}
}