{
  "type": "Feature",
  "properties": {
    "addr:full":"Calle de Santiago, 83 Elizondo Navarra 31700",
    "addr:housenumber":"83",
    "addr:postcode":"31700",
    "addr:street":"Calle De Santiago;Navarra",
    "iso:country":"ES",
    "sg:address":"Calle de Santiago, 83",
    "sg:city":"Elizondo",
    "sg:orig_category":"Electricidad: Equipos Industriales, Componentes (fabricaci\u00d3n)",
    "sg:phone":"+34 948 58 12 61",
    "sg:postcode":"31700",
    "sg:province":"Navarra",
    "wof:name":"Suministros Electricos Elicetxe S.l.",
    "wof:placetype":"venue"
},
  "geometry": {"coordinates":[-1.5226365328,43.1408805847],"type":"Point"}
}