{
  "type": "Feature",
  "properties": {
    "addr:full":"Avda Constitucion, 63 Villena Alicante 03400",
    "addr:housenumber":"63",
    "addr:postcode":"03400",
    "addr:street":"Avda Constitucion",
    "iso:country":"ES",
    "sg:address":"Avda Constitucion, 63",
    "sg:city":"Villena",
    "sg:orig_category":"Televisi\u00d3n, V\u00cddeo: Aparatos Y Accesorios (venta)",
    "sg:phone":"+34 965 80 17 28",
    "sg:postcode":"03400",
    "sg:province":"Alicante",
    "wof:name":"V. Mico Ortu\u00f1o S.l.",
    "wof:placetype":"venue"
},
  "geometry": {"coordinates":[-0.8656182289,38.6349906921],"type":"Point"}
}