{
  "type": "Feature",
  "properties": {
    "iso:country":"ES",
    "sg:address":"Calle de Aguado, 11",
    "sg:city":"Gijon",
    "sg:orig_category":"Inmobiliaria (agencias)",
    "sg:phone":"+34 985 13 26 30",
    "sg:postcode":"33202",
    "sg:province":"Asturias",
    "wof:name":"Promociones Tu Techo 03 S.l",
    "wof:placetype":"venue"
},
  "geometry": {"coordinates":[-5.6498365402,43.5380783081],"type":"Point"}
}