{
  "type": "Feature",
  "properties": {
    "addr:full":"Prol. Vidal Barraquer, S/n Tarragona Tarragona 43005",
    "addr:housenumber":"s / n",
    "addr:postcode":"43005",
    "addr:street":"Prol. Vidal Barraquer",
    "iso:country":"ES",
    "sg:address":"Prol. Vidal Barraquer, S/n",
    "sg:city":"Tarragona",
    "sg:orig_category":"Cajas De Ahorro",
    "sg:phone":"+34 977 23 59 23",
    "sg:postcode":"43005",
    "sg:province":"Tarragona",
    "wof:name":"Caixa D'estalvis De Tarragona",
    "wof:placetype":"venue"
},
  "geometry": {"coordinates":[1.2403529882,41.1205329895],"type":"Point"}
}