{
  "type": "Feature",
  "properties": {
    "iso:country":"ES",
    "sg:address":"Carrer de Mallorca, 184",
    "sg:city":"Barcelona",
    "sg:orig_category":"Dibujantes (diversos)",
    "sg:phone":"+34 934 54 72 88",
    "sg:postcode":"08036",
    "sg:province":"Barcelona",
    "wof:name":"Lafuente Mollon Maria Teresa",
    "wof:placetype":"venue"
},
  "geometry": {"coordinates":[2.156842947,41.3893508911],"type":"Point"}
}