{
  "type": "Feature",
  "properties": {
    "addr:full":"Carr Valencia, 30 Manises Valencia 46940",
    "addr:housenumber":"30",
    "addr:postcode":"46940",
    "addr:street":"Carr Valencia",
    "iso:country":"ES",
    "sg:address":"Carr Valencia, 30",
    "sg:city":"Manises",
    "sg:orig_category":"Supermercados Y Hipermercados",
    "sg:phone":"+34 961 52 27 10",
    "sg:postcode":"46940",
    "sg:province":"Valencia",
    "wof:name":"Distribuidora Internacional De Alimentacion S.a.",
    "wof:placetype":"venue"
},
  "geometry": {"coordinates":[-0.4559009969,39.4901504517],"type":"Point"}
}