{
  "type": "Feature",
  "properties": {
    "iso:country":"ES",
    "sg:address":"Avda Villar Y Valle, 15",
    "sg:city":"Ribadesella",
    "sg:orig_category":"Asilos De Ancianos. Centros Privados",
    "sg:phone":"+34 985 85 75 86",
    "sg:postcode":"33560",
    "sg:province":"Asturias",
    "wof:name":"Hogar San Jose De La Monta\u00f1a",
    "wof:placetype":"venue"
},
  "geometry": {"coordinates":[-5.0565090179,43.4628753662],"type":"Point"}
}