{
  "type": "Feature",
  "properties": {
    "addr:full":"Calle de Vaguadas (de Las), 1 Nieves Toledo 45190",
    "addr:housenumber":"1",
    "addr:postcode":"45190",
    "addr:street":"Calle De Vaguadas De Las",
    "iso:country":"ES",
    "sg:address":"Calle de Vaguadas (de Las), 1",
    "sg:city":"Nieves",
    "sg:orig_category":"Farmacias",
    "sg:phone":"+34 925 27 89 14",
    "sg:postcode":"45190",
    "sg:province":"Toledo",
    "wof:name":"Martin Villareal Francisco Javier",
    "wof:placetype":"venue"
},
  "geometry": {"coordinates":[-3.9429790974,39.7946815491],"type":"Point"}
}