{
  "type": "Feature",
  "properties": {
    "iso:country":"ES",
    "sg:address":"Calle de Campi\u00d1a, 12",
    "sg:city":"Madrid",
    "sg:orig_category":"Farmacias",
    "sg:phone":"+34 917 86 01 76",
    "sg:postcode":"28053",
    "sg:province":"Madrid",
    "wof:name":"Martinez Moreno Victor Manuel",
    "wof:placetype":"venue"
},
  "geometry": {"coordinates":[-3.6699931622,40.3787155151],"type":"Point"}
}