{
  "type": "Feature",
  "properties": {
    "addr:full":"Avda Eugenio Dominguez Afonso, S/n San Eugenio Bajo Santa Cruz De Tenerife 38660",
    "addr:housenumber":"s / n",
    "addr:postcode":"38660",
    "addr:street":"Avda Eugenio Dominguez Afonso",
    "iso:country":"ES",
    "sg:address":"Avda Eugenio Dominguez Afonso, S/n",
    "sg:city":"San Eugenio Bajo",
    "sg:orig_category":"Promotores Constructores",
    "sg:phone":"+34 922 79 19 66",
    "sg:postcode":"38660",
    "sg:province":"Santa Cruz De Tenerife",
    "wof:name":"San Eugenio S. A.",
    "wof:placetype":"venue"
},
  "geometry": {"coordinates":[-16.7317714691,28.0760765076],"type":"Point"}
}