{
  "type": "Feature",
  "properties": {
    "iso:country":"ES",
    "sg:address":"Calle de Cine, 43",
    "sg:city":"Madrid",
    "sg:orig_category":"Electricidad: Instaladores",
    "sg:phone":"+34 917 11 42 51",
    "sg:postcode":"28024",
    "sg:province":"Madrid",
    "wof:name":"Electricidad Matias Meneses S.a.",
    "wof:placetype":"venue"
},
  "geometry": {"coordinates":[-3.774903059,40.3957672119],"type":"Point"}
}