{
  "type": "Feature",
  "properties": {
    "iso:country":"ES",
    "sg:address":"Carrer de Ferrocarrils Catalans, 103",
    "sg:city":"Barcelona",
    "sg:orig_category":"Centros Empresariales",
    "sg:phone":"+34 934 32 47 70",
    "sg:postcode":"08038",
    "sg:province":"Barcelona",
    "sg:website":"www.plastcat.com",
    "wof:name":"Plastcat S.l.",
    "wof:placetype":"venue"
},
  "geometry": {"coordinates":[2.1409139633,41.3615684509],"type":"Point"}
}