{
  "type": "Feature",
  "properties": {
    "addr:full":"Ctra Alicun (de), Km. 0003,5 Roquetas Mar Almer\u00eda 04740",
    "addr:postcode":"04740",
    "addr:street":"Ctra Alicun De Km. 0003,5",
    "iso:country":"ES",
    "sg:address":"Ctra Alicun (de), Km. 0003,5",
    "sg:city":"Roquetas Mar",
    "sg:orig_category":"Agentes, Concesionarios Y Sucursales De Veh\u00cdculos",
    "sg:phone":"+34 950 32 03 87",
    "sg:postcode":"04740",
    "sg:province":"Almer\u00eda",
    "wof:name":"Francisco Lopez Martinez S.l.",
    "wof:placetype":"venue"
},
  "geometry": {"coordinates":[-2.6124989986,36.7638435364],"type":"Point"}
}