{
  "type": "Feature",
  "properties": {
    "iso:country":"ES",
    "sg:address":"Calle de Aragon (de), 35",
    "sg:city":"Mejorada Campo",
    "sg:orig_category":"Barnizadores",
    "sg:phone":"+34 916 79 18 14",
    "sg:postcode":"28840",
    "sg:province":"Madrid",
    "wof:name":"Logi Automatizacion Y Control S.l.",
    "wof:placetype":"venue"
},
  "geometry": {"coordinates":[-3.4807934761,40.3858451843],"type":"Point"}
}