{
  "type": "Feature",
  "properties": {
    "iso:country":"ES",
    "sg:address":"Fco Bergamin, 26",
    "sg:city":"Iru\u00f1a",
    "sg:orig_category":"Peluqueros: De Se\u00d1oras",
    "sg:phone":"+34 948 23 31 87",
    "sg:postcode":"31004",
    "sg:province":"Navarra",
    "wof:name":"Villanueva Garcia Pedro",
    "wof:placetype":"venue"
},
  "geometry": {"coordinates":[-1.6437540054,42.81275177],"type":"Point"}
}