{
  "type": "Feature",
  "properties": {
    "addr:full":"Avda Virgen Del Pilar, 34 Pedrola Zaragoza 50690",
    "addr:housenumber":"34",
    "addr:postcode":"50690",
    "addr:street":"Avda Virgen Del Pilar",
    "iso:country":"ES",
    "sg:address":"Avda Virgen Del Pilar, 34",
    "sg:city":"Pedrola",
    "sg:orig_category":"Congelados: Productos Alimentarios (al Por Menor)",
    "sg:phone":"+34 976 61 50 92",
    "sg:postcode":"50690",
    "sg:province":"Zaragoza",
    "wof:name":"Congelados San Emeterio S.l.",
    "wof:placetype":"venue"
},
  "geometry": {"coordinates":[-1.2211799622,41.7861442566],"type":"Point"}
}