{
  "type": "Feature",
  "properties": {
    "iso:country":"ES",
    "sg:address":"Rua Fonte Dos Ca\u00d1os, S/n",
    "sg:city":"Maceda",
    "sg:orig_category":"Restaurantes",
    "sg:phone":"+34 988 46 34 09",
    "sg:postcode":"32700",
    "sg:province":"Ourense",
    "wof:name":"Galtelcom",
    "wof:placetype":"venue"
},
  "geometry": {"coordinates":[-7.5355553627,42.215221405],"type":"Point"}
}