{
  "type": "Feature",
  "properties": {
    "addr:full":"Barranquet, 1 Beniparrell Valencia 46469",
    "addr:housenumber":"1",
    "addr:postcode":"46469",
    "addr:street":"Barranquet",
    "iso:country":"ES",
    "sg:address":"Barranquet, 1",
    "sg:city":"Beniparrell",
    "sg:orig_category":"Centros Empresariales",
    "sg:phone":"+34 961 21 19 08",
    "sg:postcode":"46469",
    "sg:province":"Valencia",
    "wof:name":"Federacion Empresarial Madera Y Mueble Comunidad Valenciana",
    "wof:placetype":"venue"
},
  "geometry": {"coordinates":[-0.4116789997,39.383228302],"type":"Point"}
}