{
  "type": "Feature",
  "properties": {
    "addr:full":"Calle de Doctor Nacher, S/n Chiva Valencia 46370",
    "addr:housenumber":"s / n",
    "addr:postcode":"46370",
    "addr:street":"Calle De Doctor Nacher",
    "iso:country":"ES",
    "sg:address":"Calle de Doctor Nacher, S/n",
    "sg:city":"Chiva",
    "sg:orig_category":"Porcelanas, Azulejos (fabricaci\u00d3n, Al Por Mayor)",
    "sg:phone":"+34 962 52 21 28",
    "sg:postcode":"46370",
    "sg:province":"Valencia",
    "wof:name":"Azulejos Chiva S.l.",
    "wof:placetype":"venue"
},
  "geometry": {"coordinates":[-0.7142990232,39.4702606201],"type":"Point"}
}