{
  "type": "Feature",
  "properties": {
    "addr:full":"Calle de Tiburon, 1 Granada Granada 18015",
    "addr:housenumber":"1",
    "addr:postcode":"18015",
    "addr:street":"Calle De Tiburon",
    "iso:country":"ES",
    "sg:address":"Calle de Tiburon, 1",
    "sg:city":"Granada",
    "sg:orig_category":"Reposter\u00cdas",
    "sg:phone":"+34 958 29 10 58",
    "sg:postcode":"18015",
    "sg:province":"Granada",
    "wof:name":"Quesada Arco Luis",
    "wof:placetype":"venue"
},
  "geometry": {"coordinates":[-3.6356139183,37.1961364746],"type":"Point"}
}