{
  "type": "Feature",
  "properties": {
    "iso:country":"ES",
    "sg:address":"Calle de Derechos Humanos, 24",
    "sg:city":"Pizarra",
    "sg:orig_category":"Mayoristas E Intermediarios En Alcoholes",
    "sg:phone":"+34 952 48 36 92",
    "sg:postcode":"29560",
    "sg:province":"M\u00e1laga",
    "wof:name":"Esteban Martin Infantes S.l.",
    "wof:placetype":"venue"
},
  "geometry": {"coordinates":[-4.7095189095,36.7683296204],"type":"Point"}
}