{
  "type": "Feature",
  "properties": {
    "iso:country":"ES",
    "sg:address":"Avda Lugo (de), 98",
    "sg:city":"Taboada",
    "sg:orig_category":"Negocio De Materiales De Construcci\u00d3n",
    "sg:phone":"+34 982 46 53 07",
    "sg:postcode":"27550",
    "sg:province":"Lugo",
    "wof:name":"Rivas Rodriguez Jose",
    "wof:placetype":"venue"
},
  "geometry": {"coordinates":[-7.7629890442,42.7146148682],"type":"Point"}
}