{
  "type": "Feature",
  "properties": {
    "addr:full":"Auzoa Txaporta, 24 Gernika Vizcaya 48300",
    "addr:housenumber":"24",
    "addr:postcode":"48300",
    "addr:street":"Auzoa Txaporta",
    "iso:country":"ES",
    "sg:address":"Auzoa Txaporta, 24",
    "sg:city":"Gernika",
    "sg:orig_category":"Rectificaci\u00d3n, Mecanizado, Fresado",
    "sg:phone":"+34 946 25 04 31",
    "sg:postcode":"48300",
    "sg:province":"Vizcaya",
    "wof:name":"Accesorios Maquina Y Herramienta Ben S.l.",
    "wof:placetype":"venue"
},
  "geometry": {"coordinates":[-2.6802954674,43.3054122925],"type":"Point"}
}