{
  "type": "Feature",
  "properties": {
    "iso:country":"ES",
    "sg:address":"Calle de Luis De Gongora, 15",
    "sg:city":"Barriada De Santiago",
    "sg:orig_category":"Reposter\u00cdas",
    "sg:phone":"+34 968 16 97 18",
    "sg:postcode":"30319",
    "sg:province":"Murcia",
    "wof:name":"Moya Galindo Maria Del Carmen",
    "wof:placetype":"venue"
},
  "geometry": {"coordinates":[-1.0220810175,37.6771316528],"type":"Point"}
}