{
  "type": "Feature",
  "properties": {
    "addr:full":"Calle de Barratxi, 22 Vitoria-gasteiz \u00c1lava 01013",
    "addr:housenumber":"22",
    "addr:postcode":"01013",
    "addr:street":"Calle De Barratxi",
    "iso:country":"ES",
    "sg:address":"Calle de Barratxi, 22",
    "sg:city":"Vitoria-gasteiz",
    "sg:orig_category":"Lavado, Limpieza De Veh\u00cdculos",
    "sg:phone":"+34 945 25 56 58",
    "sg:postcode":"01013",
    "sg:province":"\u00c1lava",
    "wof:name":"Fernandez Cebranos Jose Luis",
    "wof:placetype":"venue"
},
  "geometry": {"coordinates":[-2.6473231316,42.8741149902],"type":"Point"}
}