{
  "type": "Feature",
  "properties": {
    "iso:country":"ES",
    "sg:address":"Avda Espa\u00d1a (de), S/n",
    "sg:city":"Coslada",
    "sg:orig_category":"Asociaciones Y Clubs Deportivos",
    "sg:phone":"+34 916 69 66 43",
    "sg:postcode":"28820",
    "sg:province":"Madrid",
    "wof:name":"Ayuntamiento De Coslada Patronato Deportivo Municipal",
    "wof:placetype":"venue"
},
  "geometry": {"coordinates":[-3.5621058941,40.4211845398],"type":"Point"}
}