{
  "type": "Feature",
  "properties": {
    "iso:country":"ES",
    "sg:address":"Carr Jardi, 42",
    "sg:city":"Vilanova I La Geltru",
    "sg:orig_category":"Maquinaria Para Industrias Diversas",
    "sg:phone":"+34 938 93 08 98",
    "sg:postcode":"08800",
    "sg:province":"Barcelona",
    "wof:name":"Terron Burgos Juan Manuel",
    "wof:placetype":"venue"
},
  "geometry": {"coordinates":[1.7219519615,41.2246055603],"type":"Point"}
}