{
  "type": "Feature",
  "properties": {
    "addr:full":"Calle de Paz, 1 Granada Granada 18002",
    "addr:housenumber":"1",
    "addr:postcode":"18002",
    "addr:street":"Calle De Paz",
    "iso:country":"ES",
    "sg:address":"Calle de Paz, 1",
    "sg:city":"Granada",
    "sg:orig_category":"Electrodom\u00c9sticos (fabricaci\u00d3n, Al Por Mayor)",
    "sg:phone":"+34 958 26 59 37",
    "sg:postcode":"18002",
    "sg:province":"Granada",
    "wof:name":"Hurtado Hurtado Antonio Pio",
    "wof:placetype":"venue"
},
  "geometry": {"coordinates":[-3.6018168926,37.1751327515],"type":"Point"}
}