{
  "type": "Feature",
  "properties": {
    "iso:country":"ES",
    "sg:address":"Rua Blanco Rajoy, 24",
    "sg:city":"Vimianzo",
    "sg:orig_category":"Material Y Suministros Para Veterinarios",
    "sg:phone":"+34 981 71 64 02",
    "sg:postcode":"15120",
    "sg:province":"La Coru\u00f1a",
    "wof:name":"Covega Agropecuaria S.l.",
    "wof:placetype":"venue"
},
  "geometry": {"coordinates":[-9.0328435898,43.1112251282],"type":"Point"}
}