{
  "type": "Feature",
  "properties": {
    "iso:country":"ES",
    "sg:address":"Calle de Moreno Nieto, 25",
    "sg:city":"Malaga",
    "sg:orig_category":"Asesor\u00cda Fiscal Y Jur\u00cddica",
    "sg:phone":"+34 952 39 99 55",
    "sg:postcode":"29011",
    "sg:province":"M\u00e1laga",
    "wof:name":"Gestoria Malague\u00f1a S.l.",
    "wof:placetype":"venue"
},
  "geometry": {"coordinates":[-4.4381628036,36.730140686],"type":"Point"}
}