{
  "type": "Feature",
  "properties": {
    "iso:country":"ES",
    "sg:address":"A Eirexa, 12",
    "sg:city":"Sisto",
    "sg:orig_category":"Cr\u00cda De Animales",
    "sg:phone":"+34 986 68 21 60",
    "sg:postcode":"36516",
    "sg:province":"Pontevedra",
    "wof:name":"Bendoiro S.a.t. N-923 Xuga",
    "wof:placetype":"venue"
},
  "geometry": {"coordinates":[-8.010225296,42.5994377136],"type":"Point"}
}