{
  "type": "Feature",
  "properties": {
    "iso:country":"ES",
    "sg:address":"Disem Pu\u00f1anilla, S/n",
    "sg:city":"La Puebla Rio",
    "sg:orig_category":"Producci\u00d3n, Venta De Productos De Agricultura Biol\u00d3gica",
    "sg:phone":"+34 955 95 05 66",
    "sg:postcode":"41130",
    "sg:province":"Sevilla",
    "wof:name":"Hermanos Olivera Pe\u00f1a S.c.",
    "wof:placetype":"venue"
},
  "geometry": {"coordinates":[-6.0651087761,37.2680435181],"type":"Point"}
}