{
  "type": "Feature",
  "properties": {
    "addr:full":"Calle de Talisio, 10 Madrid Madrid 28027",
    "addr:housenumber":"10",
    "addr:postcode":"madrid;28027",
    "addr:street":"Calle De Talisio",
    "iso:country":"ES",
    "sg:address":"Calle de Talisio, 10",
    "sg:city":"Madrid",
    "sg:orig_category":"Rectificaci\u00d3n, Mecanizado, Fresado",
    "sg:phone":"+34 913 68 04 78",
    "sg:postcode":"28027",
    "sg:province":"Madrid",
    "wof:name":"Talleres De Mecanizados Jlm S.a:",
    "wof:placetype":"venue"
},
  "geometry": {"coordinates":[-3.6444830894,40.438747406],"type":"Point"}
}