{
  "type": "Feature",
  "properties": {
    "iso:country":"ES",
    "sg:address":"Calle de Comercio (del), 10",
    "sg:city":"Tres Cantos",
    "sg:classifiers":[
        {
            "category":"Casinos & Gambling",
            "type":"Entertainment"
        }
    ],
    "sg:phone":"+34 918 04 95 17",
    "sg:postcode":"28760",
    "sg:province":"Madrid",
    "sg:tags":[
        "locale",
        "de",
        "juego"
    ],
    "wof:name":"Bolas De Colores S.l",
    "wof:placetype":"venue"
},
  "geometry": {"coordinates":[-3.7096829414,40.6004219055],"type":"Point"}
}