{
  "type": "Feature",
  "properties": {
    "addr:full":"Calle de Vistillas De San Juan, 16 Quintanar Orden Toledo 45800",
    "addr:housenumber":"16",
    "addr:postcode":"45800",
    "addr:street":"Calle De Vistillas De San Juan",
    "iso:country":"ES",
    "sg:address":"Calle de Vistillas De San Juan, 16",
    "sg:city":"Quintanar Orden",
    "sg:orig_category":"Flores Y Plantas Naturales (al Por Mayor)",
    "sg:phone":"+34 925 18 00 12",
    "sg:postcode":"45800",
    "sg:province":"Toledo",
    "wof:name":"Santos Serrano Francisca",
    "wof:placetype":"venue"
},
  "geometry": {"coordinates":[-3.0453689098,39.5929298401],"type":"Point"}
}