{
  "type": "Feature",
  "properties": {
    "iso:country":"ES",
    "sg:address":"Calle de Rambla (la), 42",
    "sg:city":"Cuevas Almanzora",
    "sg:orig_category":"Ropa Para Se\u00d1oras Y Caballeros (al Por Menor)",
    "sg:phone":"+34 950 45 72 36",
    "sg:postcode":"04610",
    "sg:province":"Almer\u00eda",
    "wof:name":"Campos Batlles Ana Maria",
    "wof:placetype":"venue"
},
  "geometry": {"coordinates":[-1.8785740137,37.295463562],"type":"Point"}
}