{
  "type": "Feature",
  "properties": {
    "addr:full":"Calle de Madrid, 53 Getafe Madrid 28901",
    "addr:housenumber":"53",
    "addr:postcode":"28901",
    "addr:street":"Calle De Madrid",
    "iso:country":"ES",
    "sg:address":"Calle de Madrid, 53",
    "sg:city":"Getafe",
    "sg:orig_category":"Deportes Y Ocio: Art\u00cdculos Y Ropas (al Por Menor Y Accesorios)",
    "sg:phone":"+34 916 81 14 85",
    "sg:postcode":"28901",
    "sg:province":"Madrid",
    "sg:website":"www.coroneltapioca.com",
    "wof:name":"Coronel Tapioca S.a.",
    "wof:placetype":"venue"
},
  "geometry": {"coordinates":[-3.7298378944,40.3077545166],"type":"Point"}
}