{
  "type": "Feature",
  "properties": {
    "iso:country":"ES",
    "sg:address":"Cmn Atalaya, S/n",
    "sg:city":"Sisante",
    "sg:orig_category":"Propiedad Industrial: Patentes De Inventos, Marcas, Modelos, Dise\u00d1os",
    "sg:phone":"+34 969 38 71 43",
    "sg:postcode":"16700",
    "sg:province":"Cuenca",
    "wof:name":"Hermanos Mota C.b.",
    "wof:placetype":"venue"
},
  "geometry": {"coordinates":[-2.2018790245,39.4109992981],"type":"Point"}
}