{
  "type": "Feature",
  "properties": {
    "addr:full":"Calle de Alonso Del Castillo, 1 Salamanca Salamanca 37003",
    "addr:housenumber":"1",
    "addr:postcode":"37003",
    "addr:street":"Calle De Alonso Del Castillo",
    "iso:country":"ES",
    "sg:address":"Calle de Alonso Del Castillo, 1",
    "sg:city":"Salamanca",
    "sg:orig_category":"Mec\u00c1nico Del Autom\u00d3vil",
    "sg:phone":"+34 923 18 08 72",
    "sg:postcode":"37003",
    "sg:province":"Salamanca",
    "wof:name":"Blanco Roncero Francisco",
    "wof:placetype":"venue"
},
  "geometry": {"coordinates":[-5.6492810249,40.9625701904],"type":"Point"}
}