{
  "type": "Feature",
  "properties": {
    "addr:full":"Calle de Real, 37 Churriana Vega Granada 18194",
    "addr:housenumber":"37",
    "addr:postcode":"18194",
    "addr:street":"Calle De Real",
    "iso:country":"ES",
    "sg:address":"Calle de Real, 37",
    "sg:city":"Churriana Vega",
    "sg:orig_category":"Molduras, Junquillos, Listones Y Molduras Perforadas",
    "sg:phone":"+34 958 57 11 52",
    "sg:postcode":"18194",
    "sg:province":"Granada",
    "wof:name":"Arroyo Cano Alberto",
    "wof:placetype":"venue"
},
  "geometry": {"coordinates":[-3.6344892979,37.0928153992],"type":"Point"}
}