{
  "type": "Feature",
  "properties": {
    "iso:country":"ES",
    "sg:address":"Av Tres-cents Dos, 17",
    "sg:city":"Castelldefels",
    "sg:orig_category":"Controles De Edificaci\u00d3n (construcci\u00d3n, Seguridad)",
    "sg:phone":"+34 936 36 73 15",
    "sg:postcode":"08860",
    "sg:province":"Barcelona",
    "wof:name":"Andamios Cuatro S.l.",
    "wof:placetype":"venue"
},
  "geometry": {"coordinates":[1.9767744541,41.2803878784],"type":"Point"}
}