{
  "type": "Feature",
  "properties": {
    "iso:country":"ES",
    "sg:address":"Avda Andalucia, 15",
    "sg:city":"Mairena Alcor",
    "sg:orig_category":"M\u00c9dicos: Estomatolog\u00cda",
    "sg:phone":"+34 955 74 47 54",
    "sg:postcode":"41510",
    "sg:province":"Sevilla",
    "wof:name":"Garcia Jimenez Manuel",
    "wof:placetype":"venue"
},
  "geometry": {"coordinates":[-5.751888752,37.3741188049],"type":"Point"}
}