{
  "type": "Feature",
  "properties": {
    "addr:full":"Av Alfonso Puchades, 2 Benidorm Alicante 03500",
    "addr:housenumber":"2",
    "addr:postcode":"03500",
    "addr:street":"Av Alfonso Puchades",
    "iso:country":"ES",
    "sg:address":"Av Alfonso Puchades, 2",
    "sg:city":"Benidorm",
    "sg:orig_category":"Mudanzas",
    "sg:phone":"+34 966 80 91 46",
    "sg:postcode":"03500",
    "sg:province":"Alicante",
    "wof:name":"Guerola Y Guardiola S.l.",
    "wof:placetype":"venue"
},
  "geometry": {"coordinates":[-0.1273992956,38.5428657532],"type":"Point"}
}