{
  "type": "Feature",
  "properties": {
    "iso:country":"ES",
    "sg:address":"Calle de Geranio, 32",
    "sg:city":"Puebla Alfinden",
    "sg:orig_category":"Fabricaci\u00d3n, Instalaci\u00d3n Y Reparaci\u00d3n De Bombas",
    "sg:phone":"+34 976 10 83 44",
    "sg:postcode":"50171",
    "sg:province":"Zaragoza",
    "wof:name":"Reboja S.l.",
    "wof:placetype":"venue"
},
  "geometry": {"coordinates":[-0.7687630057,41.6391067505],"type":"Point"}
}