{
  "type": "Feature",
  "properties": {
    "addr:full":"Plaz Economo Parera, 1 Palma Islas Baleares 07014",
    "addr:housenumber":"1",
    "addr:postcode":"07014",
    "addr:street":"Plaz Economo Parera",
    "iso:country":"ES",
    "sg:address":"Plaz Economo Parera, 1",
    "sg:city":"Palma",
    "sg:orig_category":"Ense\u00d1ante, Direcci\u00d3n",
    "sg:phone":"+34 971 73 12 24",
    "sg:postcode":"07014",
    "sg:province":"Islas Baleares",
    "wof:name":"Cayuelas Pastor Santiago",
    "wof:placetype":"venue"
},
  "geometry": {"coordinates":[2.6253900528,39.5600509644],"type":"Point"}
}