{
  "type": "Feature",
  "properties": {
    "iso:country":"ES",
    "sg:address":"Carr Valencia, 18",
    "sg:city":"Burjassot",
    "sg:orig_category":"Escotaduras, Torneados",
    "sg:phone":"+34 963 64 61 04",
    "sg:postcode":"46100",
    "sg:province":"Valencia",
    "wof:name":"Neumaticas Burjasot S.l.",
    "wof:placetype":"venue"
},
  "geometry": {"coordinates":[-0.4032309949,39.5020256042],"type":"Point"}
}