{
  "type": "Feature",
  "properties": {
    "addr:full":"Carrer de Valencia, 98 Barcelona Barcelona 08015",
    "addr:housenumber":"98",
    "addr:postcode":"08015",
    "addr:street":"Carrer De Valencia",
    "iso:country":"ES",
    "sg:address":"Carrer de Valencia, 98",
    "sg:city":"Barcelona",
    "sg:orig_category":"Inmobiliaria (agencias)",
    "sg:phone":"+34 932 26 26 10",
    "sg:postcode":"08015",
    "sg:province":"Barcelona",
    "sg:website":"www.habitatge.com",
    "wof:name":"Edurosta S.l.",
    "wof:placetype":"venue"
},
  "geometry": {"coordinates":[2.1503620148,41.3827476501],"type":"Point"}
}