{
  "type": "Feature",
  "properties": {
    "iso:country":"ES",
    "sg:address":"Calle de Beneficio, 60",
    "sg:city":"Almaraz De Duero",
    "sg:orig_category":"Farmacias",
    "sg:phone":"+34 980 55 41 28",
    "sg:postcode":"49180",
    "sg:province":"Zamora",
    "wof:name":"Arce Hidalgo Violeta",
    "wof:placetype":"venue"
},
  "geometry": {"coordinates":[-5.9169297218,41.4764938354],"type":"Point"}
}