{
  "type": "Feature",
  "properties": {
    "addr:full":"Rua Avenidas (as), S/n Vigo Pontevedra 36201",
    "addr:postcode":"36201",
    "addr:street":"Rua Avenidas As S / N",
    "iso:country":"ES",
    "sg:address":"Rua Avenidas (as), S/n",
    "sg:city":"Vigo",
    "sg:orig_category":"Asociaciones Y Clubs Deportivos",
    "sg:phone":"+34 986 44 74 41",
    "sg:postcode":"36201",
    "sg:province":"Pontevedra",
    "sg:website":"www.rcnauticovigo.com",
    "wof:name":"Real Club Nautico De Vigo",
    "wof:placetype":"venue"
},
  "geometry": {"coordinates":[-8.7273340225,42.2409439087],"type":"Point"}
}