{
  "type": "Feature",
  "properties": {
    "addr:full":"C/ Aladia, 21 Elche Alicante 03203",
    "addr:housenumber":"21",
    "addr:postcode":"03203",
    "addr:street":"C / Aladia",
    "iso:country":"ES",
    "sg:address":"C/ Aladia, 21",
    "sg:city":"Elche",
    "sg:orig_category":"Reposter\u00cdas",
    "sg:phone":"+34 965 42 32 34",
    "sg:postcode":"03203",
    "sg:province":"Alicante",
    "wof:name":"Panaderia Bolleria Alonso S.l.",
    "wof:placetype":"venue"
},
  "geometry": {"coordinates":[-0.6764230132,38.2649841309],"type":"Point"}
}