{
  "type": "Feature",
  "properties": {
    "addr:full":"Calle de Debussy, 4 Malaga M\u00e1laga 29011",
    "addr:housenumber":"4",
    "addr:postcode":"29011",
    "addr:street":"Calle De Debussy;Ma\u0301Laga",
    "iso:country":"ES",
    "sg:address":"Calle de Debussy, 4",
    "sg:city":"Malaga",
    "sg:orig_category":"Agencias Y Agentes Comerciales, Representantes",
    "sg:phone":"+34 952 39 79 05",
    "sg:postcode":"29011",
    "sg:province":"M\u00e1laga",
    "wof:name":"Collado Lara Juan Carlos",
    "wof:placetype":"venue"
},
  "geometry": {"coordinates":[-4.4267191887,36.7502098083],"type":"Point"}
}