{
  "type": "Feature",
  "properties": {
    "iso:country":"ES",
    "sg:address":"Calle de Vi\u00d1a Virgen, 4",
    "sg:city":"Madrid",
    "sg:orig_category":"Chapister\u00cda",
    "sg:phone":"+34 913 15 96 70",
    "sg:postcode":"28029",
    "sg:province":"Madrid",
    "wof:name":"Perez Fernandez Manuel",
    "wof:placetype":"venue"
},
  "geometry": {"coordinates":[-3.6939940453,40.4653434753],"type":"Point"}
}