{
  "type": "Feature",
  "properties": {
    "iso:country":"ES",
    "sg:address":"Calle de San Francisco, 6",
    "sg:city":"Molina Segura",
    "sg:orig_category":"Sindicatos De Trabajadores",
    "sg:phone":"+34 968 61 27 27",
    "sg:postcode":"30500",
    "sg:province":"Murcia",
    "wof:name":"Union General De Trabajadores",
    "wof:placetype":"venue"
},
  "geometry": {"coordinates":[-1.2121417522,38.0545730591],"type":"Point"}
}