{
  "type": "Feature",
  "properties": {
    "addr:full":"Calle de Santiago, 1 Cangas Pontevedra 36940",
    "addr:housenumber":"1",
    "addr:postcode":"36940",
    "addr:street":"Calle De Santiago",
    "iso:country":"ES",
    "sg:address":"Calle de Santiago, 1",
    "sg:city":"Cangas",
    "sg:orig_category":"Limpieza Industrial",
    "sg:phone":"+34 986 30 01 17",
    "sg:postcode":"36940",
    "sg:province":"Pontevedra",
    "wof:name":"Gonzalez Perez Jose Manuel",
    "wof:placetype":"venue"
},
  "geometry": {"coordinates":[-8.7850265503,42.2642593384],"type":"Point"}
}