{
  "type": "Feature",
  "properties": {
    "iso:country":"ES",
    "sg:address":"Calle de Martinez De Vega, 34",
    "sg:city":"Mieres",
    "sg:orig_category":"Fisioterapia",
    "sg:phone":"+34 985 45 37 10",
    "sg:postcode":"33600",
    "sg:province":"Asturias",
    "wof:name":"Marques Pelaez Jorge",
    "wof:placetype":"venue"
},
  "geometry": {"coordinates":[-5.7752318382,43.2482032776],"type":"Point"}
}