{
  "type": "Feature",
  "properties": {
    "iso:country":"ES",
    "sg:address":"Calle de Arna, S/n",
    "sg:city":"Somo",
    "sg:orig_category":"Heladeros",
    "sg:phone":"+34 942 51 04 66",
    "sg:postcode":"39140",
    "sg:province":"Cantabria",
    "wof:name":"Diaz Angulo Juan Antonio",
    "wof:placetype":"venue"
},
  "geometry": {"coordinates":[-3.740683794,43.4545478821],"type":"Point"}
}