{
  "type": "Feature",
  "properties": {
    "addr:full":"Calle de Chile, 10 Matas-pinar-monte Rozas Madrid 28290",
    "addr:housenumber":"10",
    "addr:postcode":"28290",
    "addr:street":"Calle De Chile",
    "iso:country":"ES",
    "sg:address":"Calle de Chile, 10",
    "sg:city":"Matas-pinar-monte Rozas",
    "sg:orig_category":"Importaci\u00d3n",
    "sg:phone":"+34 916 37 13 81",
    "sg:postcode":"28290",
    "sg:province":"Madrid",
    "sg:website":"www.cottier.com",
    "wof:name":"Libcom Iberica S.a.",
    "wof:placetype":"venue"
},
  "geometry": {"coordinates":[-3.9002776146,40.5435600281],"type":"Point"}
}