{
  "type": "Feature",
  "properties": {
    "iso:country":"ES",
    "sg:address":"Calle de Adolfo Rodriguez Jurado, 6",
    "sg:city":"Sevilla",
    "sg:orig_category":"Abogados",
    "sg:phone":"+34 954 56 37 34",
    "sg:postcode":"41001",
    "sg:province":"Sevilla",
    "wof:name":"Villegas Y Retamar S.l.",
    "wof:placetype":"venue"
},
  "geometry": {"coordinates":[-5.9937992096,37.3837394714],"type":"Point"}
}