{
  "type": "Feature",
  "properties": {
    "iso:country":"ES",
    "sg:address":"Calle de Castillo De Alcala De Guadaira, 13",
    "sg:city":"Sevilla",
    "sg:orig_category":"Molduras, Junquillos, Listones Y Molduras Perforadas",
    "sg:phone":"+34 954 61 67 49",
    "sg:postcode":"41013",
    "sg:province":"Sevilla",
    "wof:name":"Vazquez Mu\u00f1oz Francisco",
    "wof:placetype":"venue"
},
  "geometry": {"coordinates":[-5.977227211,37.3605270386],"type":"Point"}
}