{
  "type": "Feature",
  "properties": {
    "iso:country":"ES",
    "sg:address":"C/ Major, 163",
    "sg:city":"Salt",
    "sg:orig_category":"Peluqueros: De Se\u00d1oras",
    "sg:phone":"+34 972 23 91 03",
    "sg:postcode":"17190",
    "sg:province":"Girona",
    "wof:name":"Nous Estils C.b.",
    "wof:placetype":"venue"
},
  "geometry": {"coordinates":[2.7888898849,41.9748001099],"type":"Point"}
}