{
  "type": "Feature",
  "properties": {
    "addr:full":"Calle de Mendez Nu\u00d1ez, 5 Zaragoza Zaragoza 50003",
    "addr:housenumber":"5",
    "addr:postcode":"50003",
    "addr:street":"Calle De Mendez Nun\u0303Ez",
    "iso:country":"ES",
    "sg:address":"Calle de Mendez Nu\u00d1ez, 5",
    "sg:city":"Zaragoza",
    "sg:orig_category":"Bisuter\u00cda, Joyer\u00cda, Relojer\u00cda (al Por Menor)",
    "sg:phone":"+34 976 29 53 68",
    "sg:postcode":"50003",
    "sg:province":"Zaragoza",
    "wof:name":"Navarro Marsa Vicente",
    "wof:placetype":"venue"
},
  "geometry": {"coordinates":[-0.8803769946,41.6542358398],"type":"Point"}
}