{
  "type": "Feature",
  "properties": {
    "addr:full":"Avda Begonias, 29 Bormujos Sevilla 41930",
    "addr:housenumber":"29",
    "addr:postcode":"41930",
    "addr:street":"Avda Begonias",
    "iso:country":"ES",
    "sg:address":"Avda Begonias, 29",
    "sg:city":"Bormujos",
    "sg:orig_category":"Tapiceros Y Tapiceros",
    "sg:phone":"+34 955 72 58 73",
    "sg:postcode":"41930",
    "sg:province":"Sevilla",
    "wof:name":"Iba\u00f1ez Royo Mercedes",
    "wof:placetype":"venue"
},
  "geometry": {"coordinates":[-6.0632219315,37.3639678955],"type":"Point"}
}