{
  "type": "Feature",
  "properties": {
    "addr:full":"Calle de Adaro, 10 Gijon Asturias 33207",
    "addr:housenumber":"10",
    "addr:postcode":"33207",
    "addr:street":"Calle De Adaro",
    "iso:country":"ES",
    "sg:address":"Calle de Adaro, 10",
    "sg:city":"Gijon",
    "sg:orig_category":"Molduras, Junquillos, Listones Y Molduras Perforadas",
    "sg:phone":"+34 985 35 71 22",
    "sg:postcode":"33207",
    "sg:province":"Asturias",
    "wof:name":"Linde Del Campo Francisco",
    "wof:placetype":"venue"
},
  "geometry": {"coordinates":[-5.6681289673,43.5354881287],"type":"Point"}
}