{
  "type": "Feature",
  "properties": {
    "addr:full":"Carrer de Pedraforca, 241 Santpedor Barcelona 08251",
    "addr:housenumber":"241",
    "addr:postcode":"08251",
    "addr:street":"Carrer De Pedraforca",
    "iso:country":"ES",
    "sg:address":"Carrer de Pedraforca, 241",
    "sg:city":"Santpedor",
    "sg:orig_category":"Locales Y Clases De Danza",
    "sg:phone":"+34 938 27 32 16",
    "sg:postcode":"08251",
    "sg:province":"Barcelona",
    "wof:name":"Miralbell Izard Agnes",
    "wof:placetype":"venue"
},
  "geometry": {"coordinates":[1.8358199596,41.7871513367],"type":"Point"}
}