{
  "type": "Feature",
  "properties": {
    "addr:full":"Avda Santander, S/n Herrera Pisuerga Palencia 34400",
    "addr:housenumber":"s / n",
    "addr:postcode":"34400",
    "addr:street":"Avda Santander",
    "iso:country":"ES",
    "sg:address":"Avda Santander, S/n",
    "sg:city":"Herrera Pisuerga",
    "sg:orig_category":"Producci\u00d3n, Comercio De Cereales",
    "sg:phone":"+34 979 13 01 23",
    "sg:postcode":"34400",
    "sg:province":"Palencia",
    "wof:name":"Paramo Hidalgo Mauricio",
    "wof:placetype":"venue"
},
  "geometry": {"coordinates":[-4.3299050331,42.5994606018],"type":"Point"}
}