{
  "type": "Feature",
  "properties": {
    "addr:full":"Crt. G. Sevilla, 26 Almendralejo Badajoz 06200",
    "addr:housenumber":"26",
    "addr:postcode":"06200",
    "addr:street":"Crt. G. Sevilla",
    "iso:country":"ES",
    "sg:address":"Crt. G. Sevilla, 26",
    "sg:city":"Almendralejo",
    "sg:orig_category":"Mec\u00c1nico Del Autom\u00d3vil",
    "sg:phone":"+34 924 66 67 83",
    "sg:postcode":"06200",
    "sg:province":"Badajoz",
    "wof:name":"Extreauto S.a.l.",
    "wof:placetype":"venue"
},
  "geometry": {"coordinates":[-6.4050860405,38.6934776306],"type":"Point"}
}