{
  "type": "Feature",
  "properties": {
    "addr:full":"Calle de Padre Colunga, S/n Nore\u00f1a Asturias 33180",
    "addr:housenumber":"s",
    "addr:postcode":"33180",
    "addr:street":"Calle De Padre Colunga;/ N Noren\u0303A Asturias",
    "iso:country":"ES",
    "sg:address":"Calle de Padre Colunga, S/n",
    "sg:city":"Nore\u00f1a",
    "sg:orig_category":"Art\u00cdculos De Limpieza Y De Cocina (fabricaci\u00d3n, Al Por Mayor)",
    "sg:phone":"+34 985 74 24 39",
    "sg:postcode":"33180",
    "sg:province":"Asturias",
    "wof:name":"Gonzalez Mencias Ana",
    "wof:placetype":"venue"
},
  "geometry": {"coordinates":[-5.7055401802,43.3951644897],"type":"Point"}
}