{
  "type": "Feature",
  "properties": {
    "addr:full":"Cust Portugueses, 6 Toledo Toledo 45001",
    "addr:housenumber":"6",
    "addr:postcode":"45001",
    "addr:street":"Portugueses",
    "iso:country":"ES",
    "sg:address":"Cust Portugueses, 6",
    "sg:city":"Toledo",
    "sg:orig_category":"Loter\u00cda Y T\u00d3mbola",
    "sg:phone":"+34 925 22 06 62",
    "sg:postcode":"45001",
    "sg:province":"Toledo",
    "wof:name":"Benayas Sanchez-mascaraque Dolores Natividad",
    "wof:placetype":"venue"
},
  "geometry": {"coordinates":[-4.0224871635,39.8589134216],"type":"Point"}
}