{
  "type": "Feature",
  "properties": {
    "addr:full":"Calle de Juan Montalvo, 19 Madrid Madrid 28040",
    "addr:housenumber":"19",
    "addr:postcode":"madrid;28040",
    "addr:street":"Calle De Juan Montalvo",
    "iso:country":"ES",
    "sg:address":"Calle de Juan Montalvo, 19",
    "sg:city":"Madrid",
    "sg:orig_category":"Deportes Y Ocio: Art\u00cdculos Y Ropas (al Por Menor Y Accesorios)",
    "sg:phone":"+34 915 33 59 16",
    "sg:postcode":"28040",
    "sg:province":"Madrid",
    "wof:name":"Saez Gonzalez Miguel",
    "wof:placetype":"venue"
},
  "geometry": {"coordinates":[-3.7117199898,40.4471359253],"type":"Point"}
}