{
  "type": "Feature",
  "properties": {
    "addr:full":"Carrer de Major, 76 Castelldefels Barcelona 08860",
    "addr:housenumber":"76",
    "addr:postcode":"08860",
    "addr:street":"Carrer De Major",
    "iso:country":"ES",
    "sg:address":"Carrer de Major, 76",
    "sg:city":"Castelldefels",
    "sg:orig_category":"Promotores Constructores",
    "sg:phone":"+34 936 65 33 18",
    "sg:postcode":"08860",
    "sg:province":"Barcelona",
    "wof:name":"Construcciones Neivem 2000 S.l.",
    "wof:placetype":"venue"
},
  "geometry": {"coordinates":[1.9840860367,41.284992218],"type":"Point"}
}