{
  "type": "Feature",
  "properties": {
    "iso:country":"ES",
    "sg:address":"Avda Ferial, 12",
    "sg:city":"Aranda Duero",
    "sg:orig_category":"Productos Fitosanitarios (negocio, Aplicaci\u00d3n)",
    "sg:phone":"+34 947 50 18 54",
    "sg:postcode":"09400",
    "sg:province":"Burgos",
    "wof:name":"Comercial Agricola Ganadera S.l.",
    "wof:placetype":"venue"
},
  "geometry": {"coordinates":[-3.6848840714,41.6730499268],"type":"Point"}
}