{
  "type": "Feature",
  "properties": {
    "iso:country":"ES",
    "sg:address":"Crt. Valencia, 64",
    "sg:city":"Motilla Palancar",
    "sg:orig_category":"Mec\u00c1nico Del Autom\u00d3vil",
    "sg:phone":"+34 969 33 18 44",
    "sg:postcode":"16200",
    "sg:province":"Cuenca",
    "wof:name":"Bautista Monedero Agustin",
    "wof:placetype":"venue"
},
  "geometry": {"coordinates":[-1.9062039852,39.5607185364],"type":"Point"}
}