{
  "type": "Feature",
  "properties": {
    "addr:full":"Cno. Pompenillo, S/n Huesca Huesca 22099",
    "addr:postcode":"22099",
    "addr:street":"Pompenillo S / N",
    "iso:country":"ES",
    "sg:address":"Cno. Pompenillo, S/n",
    "sg:city":"Huesca",
    "sg:orig_category":"Reciclaje, Desguace De Veh\u00cdculos",
    "sg:phone":"+34 974 23 09 08",
    "sg:postcode":"22099",
    "sg:province":"Huesca",
    "wof:name":"Alonso Doto Jose",
    "wof:placetype":"venue"
},
  "geometry": {"coordinates":[-0.3884707987,42.094783783],"type":"Point"}
}