{
  "type": "Feature",
  "properties": {
    "addr:full":"Via Augusta, 200 Barcelona Barcelona 08021",
    "addr:housenumber":"200",
    "addr:postcode":"08021",
    "addr:street":"Via Augusta",
    "iso:country":"ES",
    "sg:address":"Via Augusta, 200",
    "sg:city":"Barcelona",
    "sg:orig_category":"Asesor\u00cda Sobre Comunicaci\u00d3n De Empresas",
    "sg:phone":"+34 932 40 51 35",
    "sg:postcode":"08021",
    "sg:province":"Barcelona",
    "sg:website":"www.egonzehnder.com",
    "wof:name":"Egon Zehnder International S.l.",
    "wof:placetype":"venue"
},
  "geometry": {"coordinates":[2.1411280632,41.3982009888],"type":"Point"}
}