{
  "type": "Feature",
  "properties": {
    "iso:country":"ES",
    "sg:address":"J. Echegaray, 8",
    "sg:city":"Parque Empresarial",
    "sg:orig_category":"Venta, Alquiler De V\u00cddeo",
    "sg:phone":"+34 916 40 45 70",
    "sg:postcode":"28232",
    "sg:province":"Madrid",
    "sg:website":"www.ubisoft.es",
    "wof:name":"Ubi Soft S.a.",
    "wof:placetype":"venue"
},
  "geometry": {"coordinates":[-3.9055240154,40.5182609558],"type":"Point"}
}