{
  "type": "Feature",
  "properties": {
    "iso:country":"ES",
    "sg:address":"Avgd Catalunya, S/n",
    "sg:city":"Espluga Calba",
    "sg:orig_category":"Distribuci\u00d3n De Petr\u00d3leo Y Derivados",
    "sg:phone":"+34 973 15 63 14",
    "sg:postcode":"25410",
    "sg:province":"Lleida",
    "wof:name":"Empresa Municipal D'urbanisme I Serveis De L'espluga Calva S.l.",
    "wof:placetype":"venue"
},
  "geometry": {"coordinates":[1.0044250488,41.4963111877],"type":"Point"}
}