{
  "type": "Feature",
  "properties": {
    "addr:full":"Avda Hispanidade, 72 Vigo Pontevedra 36203",
    "addr:housenumber":"72",
    "addr:postcode":"36203",
    "addr:street":"Avda Hispanidade",
    "iso:country":"ES",
    "sg:address":"Avda Hispanidade, 72",
    "sg:city":"Vigo",
    "sg:orig_category":"Cine (producci\u00d3n, Realizaci\u00d3n)",
    "sg:phone":"+34 986 41 57 65",
    "sg:postcode":"36203",
    "sg:province":"Pontevedra",
    "wof:name":"Via Lactea Filmes S.l.",
    "wof:placetype":"venue"
},
  "geometry": {"coordinates":[-8.7282371521,42.2272262573],"type":"Point"}
}