{
  "type": "Feature",
  "properties": {
    "iso:country":"ES",
    "sg:address":"Calle de Juan Sebastian Elcano, 42",
    "sg:city":"Albacete",
    "sg:orig_category":"Productores Recolectores, Venta Directa De Vinos",
    "sg:phone":"+34 967 22 37 41",
    "sg:postcode":"02005",
    "sg:province":"Albacete",
    "wof:name":"Simarro Lopez Jose",
    "wof:placetype":"venue"
},
  "geometry": {"coordinates":[-1.8622419834,38.9984283447],"type":"Point"}
}