{
  "type": "Feature",
  "properties": {
    "iso:country":"ES",
    "sg:address":"Carrer de Deu I Mata, 141",
    "sg:city":"Barcelona",
    "sg:orig_category":"Mec\u00c1nico Del Autom\u00d3vil",
    "sg:phone":"+34 934 39 79 37",
    "sg:postcode":"08029",
    "sg:province":"Barcelona",
    "wof:name":"Reina Adan Antonio",
    "wof:placetype":"venue"
},
  "geometry": {"coordinates":[2.1391921043,41.3905143738],"type":"Point"}
}