{
  "type": "Feature",
  "properties": {
    "iso:country":"ES",
    "sg:address":"Carrer de Esperan\u00c7a, 37",
    "sg:city":"Premia Mar",
    "sg:orig_category":"Rectificaci\u00d3n, Mecanizado, Fresado",
    "sg:phone":"+34 937 54 78 90",
    "sg:postcode":"08330",
    "sg:province":"Barcelona",
    "sg:website":"www.escodagrup.com/mesuper",
    "wof:name":"Construccions Mecaniques Escoda S.a.",
    "wof:placetype":"venue"
},
  "geometry": {"coordinates":[2.3587779999,41.4918327332],"type":"Point"}
}