{
  "type": "Feature",
  "properties": {
    "addr:full":"Calle de Torres Quevedo, 13 Linea De La Concepcion C\u00e1diz 11300",
    "addr:housenumber":"13",
    "addr:postcode":"11300",
    "addr:street":"Calle De Torres Quevedo;Ca\u0301Diz",
    "iso:country":"ES",
    "sg:address":"Calle de Torres Quevedo, 13",
    "sg:city":"Linea De La Concepcion",
    "sg:orig_category":"Farmacias",
    "sg:phone":"+34 956 17 18 96",
    "sg:postcode":"11300",
    "sg:province":"C\u00e1diz",
    "wof:name":"Navarro-clavijo C.b.",
    "wof:placetype":"venue"
},
  "geometry": {"coordinates":[-5.3634438515,36.1685256958],"type":"Point"}
}