{
  "type": "Feature",
  "properties": {
    "iso:country":"ES",
    "sg:address":"Cllo Alto Las Cuevas, 2",
    "sg:city":"Sanlucar De Barrameda",
    "sg:orig_category":"Supermercados Y Hipermercados",
    "sg:phone":"+34 956 36 11 81",
    "sg:postcode":"11540",
    "sg:province":"C\u00e1diz",
    "wof:name":"Pacheco Cordero Nuria",
    "wof:placetype":"venue"
},
  "geometry": {"coordinates":[-6.3437008858,36.7837524414],"type":"Point"}
}