{
  "type": "Feature",
  "properties": {
    "addr:full":"Calle de Sagasta, 2 Cadiz C\u00e1diz 11004",
    "addr:housenumber":"2",
    "addr:postcode":"11004",
    "addr:street":"Calle De Sagasta",
    "iso:country":"ES",
    "sg:address":"Calle de Sagasta, 2",
    "sg:city":"Cadiz",
    "sg:orig_category":"Pizzer\u00cdas",
    "sg:phone":"+34 956 22 32 63",
    "sg:postcode":"11004",
    "sg:province":"C\u00e1diz",
    "wof:name":"Calvo Fernandez Jose Antonio",
    "wof:placetype":"venue"
},
  "geometry": {"coordinates":[-6.2963480949,36.5342178345],"type":"Point"}
}