{
  "type": "Feature",
  "properties": {
    "iso:country":"ES",
    "sg:address":"Carrer de Enric Granados, 94",
    "sg:city":"Barcelona",
    "sg:orig_category":"Agencias Y Asesores De Publicidad",
    "sg:phone":"+34 932 37 40 05",
    "sg:postcode":"08008",
    "sg:province":"Barcelona",
    "wof:name":"Totem Taller Creatiu S.l",
    "wof:placetype":"venue"
},
  "geometry": {"coordinates":[2.1554899216,41.3931694031],"type":"Point"}
}