{
  "type": "Feature",
  "properties": {
    "iso:country":"ES",
    "sg:address":"Calle de Eduardo Marquina, 41",
    "sg:city":"Madrid",
    "sg:orig_category":"Inform\u00c1tica: Consultores",
    "sg:phone":"+34 915 69 64 26",
    "sg:postcode":"28019",
    "sg:province":"Madrid",
    "wof:name":"Linuxvixion S.l.",
    "wof:placetype":"venue"
},
  "geometry": {"coordinates":[-3.7097640038,40.3921813965],"type":"Point"}
}