{
  "type": "Feature",
  "properties": {
    "iso:country":"ES",
    "sg:address":"Calle de Fray Marcos De Niza, 7",
    "sg:city":"Sevilla",
    "sg:orig_category":"Bisuteros (fabricaci\u00d3n, Al Por Mayor)",
    "sg:phone":"+34 954 51 55 26",
    "sg:postcode":"41007",
    "sg:province":"Sevilla",
    "wof:name":"Ballesteros Montoro Rafael Manuel",
    "wof:placetype":"venue"
},
  "geometry": {"coordinates":[-5.9538989067,37.4033927917],"type":"Point"}
}