{
  "type": "Feature",
  "properties": {
    "addr:full":"Ctra Estacion, S/n Samper Calanda Teruel 44520",
    "addr:postcode":"44520",
    "addr:street":"Ctra Estacion S / N Samper",
    "iso:country":"ES",
    "sg:address":"Ctra Estacion, S/n",
    "sg:city":"Samper Calanda",
    "sg:orig_category":"Venta, Alquiler De Toldos",
    "sg:phone":"+34 978 82 25 04",
    "sg:postcode":"44520",
    "sg:province":"Teruel",
    "wof:name":"Fontaneria Calefaccion Y Construccion Perez Marco S.l.",
    "wof:placetype":"venue"
},
  "geometry": {"coordinates":[-0.3848930001,41.1877174377],"type":"Point"}
}