{
  "type": "Feature",
  "properties": {
    "addr:full":"Calle de Alemania, 4 Valencia Valencia 46010",
    "addr:housenumber":"4",
    "addr:postcode":"46010",
    "addr:street":"Calle De Alemania",
    "iso:country":"ES",
    "sg:address":"Calle de Alemania, 4",
    "sg:city":"Valencia",
    "sg:orig_category":"Centros Empresariales",
    "sg:phone":"+34 963 69 05 77",
    "sg:postcode":"46010",
    "sg:province":"Valencia",
    "wof:name":"Kadra Servicios Empresariales S.l",
    "wof:placetype":"venue"
},
  "geometry": {"coordinates":[-0.36188519,39.4810523987],"type":"Point"}
}