{
  "type": "Feature",
  "properties": {
    "addr:full":"Calle de Ramon Y Cajal, 5 Ciudad Real Ciudad Real 13001",
    "addr:housenumber":"5",
    "addr:postcode":"13001",
    "addr:street":"Calle De Ramon Y Cajal",
    "iso:country":"ES",
    "sg:address":"Calle de Ramon Y Cajal, 5",
    "sg:city":"Ciudad Real",
    "sg:orig_category":"Asesor\u00cda Sobre Comunicaci\u00d3n De Empresas",
    "sg:phone":"+34 926 23 23 62",
    "sg:postcode":"13001",
    "sg:province":"Ciudad Real",
    "wof:name":"Seficonta S.l.",
    "wof:placetype":"venue"
},
  "geometry": {"coordinates":[-3.9274749756,38.9839553833],"type":"Point"}
}