{
  "type": "Feature",
  "properties": {
    "addr:full":"Avda Alberto Alcocer, 46 Madrid Madrid 28016",
    "addr:housenumber":"46",
    "addr:postcode":"madrid;28016",
    "addr:street":"Alberto Alcocer",
    "iso:country":"ES",
    "sg:address":"Avda Alberto Alcocer, 46",
    "sg:city":"Madrid",
    "sg:orig_category":"Aeropuertos Y Servicios Aeroportuarios",
    "sg:phone":"+34 914 58 53 10",
    "sg:postcode":"28016",
    "sg:province":"Madrid",
    "wof:name":"Malasyan Airline System Berhard Sucursal En Espa\u00f1a",
    "wof:placetype":"venue"
},
  "geometry": {"coordinates":[-3.6775848866,40.4584197998],"type":"Point"}
}