{
  "type": "Feature",
  "properties": {
    "addr:full":"Carrer de Vilaros, 1 Barcelona Barcelona 08022",
    "addr:housenumber":"1",
    "addr:postcode":"08022",
    "addr:street":"Carrer De Vilaros",
    "iso:country":"ES",
    "sg:address":"Carrer de Vilaros, 1",
    "sg:city":"Barcelona",
    "sg:orig_category":"Ropa Para Se\u00d1oras (al Por Menor)",
    "sg:phone":"+34 934 18 72 11",
    "sg:postcode":"08022",
    "sg:province":"Barcelona",
    "wof:name":"Vila Riera Nuria",
    "wof:placetype":"venue"
},
  "geometry": {"coordinates":[2.1387839317,41.4054603577],"type":"Point"}
}