{
  "type": "Feature",
  "properties": {
    "iso:country":"ES",
    "sg:address":"Avgd Gran Avinguda Jaume I, 241",
    "sg:city":"Mas Dels Frares",
    "sg:orig_category":"Promotores Constructores",
    "sg:phone":"+34 964 39 25 48",
    "sg:postcode":"12560",
    "sg:province":"Castell\u00f3n",
    "wof:name":"Gres Luxor S.l.",
    "wof:placetype":"venue"
},
  "geometry": {"coordinates":[-0.0360242017,39.9860687256],"type":"Point"}
}