{
  "type": "Feature",
  "properties": {
    "addr:full":"Plaz Mayor, 16 Bembibre Le\u00f3n 24300",
    "addr:housenumber":"16",
    "addr:postcode":"24300",
    "addr:street":"Plaz Mayor;Leo\u0301N",
    "iso:country":"ES",
    "sg:address":"Plaz Mayor, 16",
    "sg:city":"Bembibre",
    "sg:orig_category":"Quincaller\u00cda (al Por Menor)",
    "sg:phone":"+34 987 51 00 07",
    "sg:postcode":"24300",
    "sg:province":"Le\u00f3n",
    "wof:name":"Rincon Otero Jose Manuel",
    "wof:placetype":"venue"
},
  "geometry": {"coordinates":[-6.4167990685,42.614944458],"type":"Point"}
}