{
  "type": "Feature",
  "properties": {
    "addr:full":"Calle de Gamon, Alameda De, 7 Errenteria Guip\u00f9zcoa 20100",
    "addr:housenumber":"7",
    "addr:postcode":"20100",
    "addr:street":"Calle De Gamon Alameda De;Guipu\u0300Zcoa",
    "iso:country":"ES",
    "sg:address":"Calle de Gamon, Alameda De, 7",
    "sg:city":"Errenteria",
    "sg:orig_category":"Sociedades, Compa\u00d1\u00cdas Aseguradoras",
    "sg:phone":"+34 943 52 17 92",
    "sg:postcode":"20100",
    "sg:province":"Guip\u00f9zcoa",
    "wof:name":"Zalacain Loyola Jose Maria",
    "wof:placetype":"venue"
},
  "geometry": {"coordinates":[-1.9139565229,43.3075790405],"type":"Point"}
}