{
  "type": "Feature",
  "properties": {
    "iso:country":"ES",
    "sg:address":"Calle de O\u00d1a, 131",
    "sg:city":"Madrid",
    "sg:orig_category":"Cajas De Ahorro",
    "sg:phone":"+34 913 83 31 12",
    "sg:postcode":"28050",
    "sg:province":"Madrid",
    "wof:name":"Caixa D'estalvis I Pensions De Barcelona",
    "wof:placetype":"venue"
},
  "geometry": {"coordinates":[-3.6626620293,40.4894714355],"type":"Point"}
}