{
  "type": "Feature",
  "properties": {
    "addr:full":"Calle de Prim, 1 Algeciras C\u00e1diz 11201",
    "addr:housenumber":"1;ca\u0301diz",
    "addr:postcode":"11201",
    "addr:street":"Calle De Prim",
    "iso:country":"ES",
    "sg:address":"Calle de Prim, 1",
    "sg:city":"Algeciras",
    "sg:orig_category":"Inmobiliaria (agencias)",
    "sg:phone":"+34 956 58 78 11",
    "sg:postcode":"11201",
    "sg:province":"C\u00e1diz",
    "sg:website":"www.calarena.com",
    "wof:name":"Playa Calarena Grupo Inmobiliario S.l",
    "wof:placetype":"venue"
},
  "geometry": {"coordinates":[-5.4468188286,36.129234314],"type":"Point"}
}