{
  "type": "Feature",
  "properties": {
    "iso:country":"ES",
    "sg:address":"Carrer de Ulldecona (d'), 23",
    "sg:city":"Tortosa",
    "sg:orig_category":"Abogados",
    "sg:phone":"+34 977 50 28 85",
    "sg:postcode":"43500",
    "sg:province":"Tarragona",
    "wof:name":"Fornos Castells Jose Enrique",
    "wof:placetype":"venue"
},
  "geometry": {"coordinates":[0.5175700188,40.8122596741],"type":"Point"}
}