{
  "type": "Feature",
  "properties": {
    "addr:full":"Polo Y Bernabe, 26 Quartell Valencia 46510",
    "addr:housenumber":"26",
    "addr:postcode":"46510",
    "addr:street":"Quartell",
    "iso:country":"ES",
    "sg:address":"Polo Y Bernabe, 26",
    "sg:city":"Quartell",
    "sg:orig_category":"Ropa Y Accesorios",
    "sg:phone":"+34 962 63 64 79",
    "sg:postcode":"46510",
    "sg:province":"Valencia",
    "wof:name":"Vadene Mascaros Vicente Miguel",
    "wof:placetype":"venue"
},
  "geometry": {"coordinates":[-0.2637580037,39.7389717102],"type":"Point"}
}