{
  "type": "Feature",
  "properties": {
    "iso:country":"ES",
    "sg:address":"Avda Libertad (de La), S/n",
    "sg:city":"Cordoba",
    "sg:orig_category":"Aparcamientos (infraestructuras, Accesorios)",
    "sg:phone":"+34 957 27 26 52",
    "sg:postcode":"14006",
    "sg:province":"C\u00f3rdoba",
    "wof:name":"Aparcamiento Gran Capitan",
    "wof:placetype":"venue"
},
  "geometry": {"coordinates":[-4.7843909264,37.8915100098],"type":"Point"}
}