{
  "type": "Feature",
  "properties": {
    "iso:country":"ES",
    "sg:address":"Calle de Aaiun, 11",
    "sg:city":"Alacant",
    "sg:orig_category":"Grafistas",
    "sg:phone":"+34 965 24 88 52",
    "sg:postcode":"03010",
    "sg:province":"Alicante",
    "wof:name":"Sociedad Limitada Graficas Artex",
    "wof:placetype":"venue"
},
  "geometry": {"coordinates":[-0.4853500128,38.3619270325],"type":"Point"}
}