{
  "type": "Feature",
  "properties": {
    "addr:full":"Calle de San Ignacio Kalea, 13 Erandio Vizcaya 48950",
    "addr:housenumber":"13",
    "addr:postcode":"48950",
    "addr:street":"Calle De San Ignacio Kalea",
    "iso:country":"ES",
    "sg:address":"Calle de San Ignacio Kalea, 13",
    "sg:city":"Erandio",
    "sg:orig_category":"Molduras, Junquillos, Listones Y Molduras Perforadas",
    "sg:phone":"+34 944 67 60 11",
    "sg:postcode":"48950",
    "sg:province":"Vizcaya",
    "wof:name":"Santi Taberna, S.l.",
    "wof:placetype":"venue"
},
  "geometry": {"coordinates":[-2.9750370979,43.304359436],"type":"Point"}
}