{
  "type": "Feature",
  "properties": {
    "addr:full":"Calle de Legion, La, 75 Melilla Melilla 52006",
    "addr:housenumber":"75",
    "addr:postcode":"52006",
    "addr:street":"Calle De Legion La",
    "iso:country":"ES",
    "sg:address":"Calle de Legion, La, 75",
    "sg:city":"Melilla",
    "sg:orig_category":"Molduras, Junquillos, Listones Y Molduras Perforadas",
    "sg:phone":"+34 952 67 21 11",
    "sg:postcode":"52006",
    "sg:province":"Melilla",
    "wof:name":"Amoretti Bauer Miguel Angel",
    "wof:placetype":"venue"
},
  "geometry": {"coordinates":[-2.9428670406,35.2758293152],"type":"Point"}
}