{
  "type": "Feature",
  "properties": {
    "addr:full":"Calle de Salitre San Miguel, S/n Guadix Granada 18500",
    "addr:housenumber":"s",
    "addr:postcode":"18500",
    "addr:street":"Calle De Salitre San Miguel;/ N",
    "iso:country":"ES",
    "sg:address":"Calle de Salitre San Miguel, S/n",
    "sg:city":"Guadix",
    "sg:orig_category":"Empresas De Carpinter\u00cda Met\u00c1lica",
    "sg:phone":"+34 958 66 36 92",
    "sg:postcode":"18500",
    "sg:province":"Granada",
    "wof:name":"Tejada Garcia Jesus",
    "wof:placetype":"venue"
},
  "geometry": {"coordinates":[-3.140152216,37.2976112366],"type":"Point"}
}