{
  "type": "Feature",
  "properties": {
    "iso:country":"ES",
    "sg:address":"Ctra Alacant (d'), 29",
    "sg:city":"Callosa D'en Sarria",
    "sg:orig_category":"Inmobiliaria (agencias)",
    "sg:phone":"+34 965 88 09 49",
    "sg:postcode":"03510",
    "sg:province":"Alicante",
    "wof:name":"Segui Soler Juan Bautista",
    "wof:placetype":"venue"
},
  "geometry": {"coordinates":[-0.1216380969,38.6482009888],"type":"Point"}
}