{
  "type": "Feature",
  "properties": {
    "addr:full":"Ctra Alfaro, 28 Tudela Navarra 31500",
    "addr:housenumber":"28",
    "addr:postcode":"31500",
    "addr:street":"Ctra Alfaro",
    "iso:country":"ES",
    "sg:address":"Ctra Alfaro, 28",
    "sg:city":"Tudela",
    "sg:orig_category":"Mec\u00c1nico Del Autom\u00d3vil",
    "sg:phone":"+34 948 82 19 41",
    "sg:postcode":"31500",
    "sg:province":"Navarra",
    "wof:name":"Sanchez Gracia Angel Maria",
    "wof:placetype":"venue"
},
  "geometry": {"coordinates":[-1.6189190149,42.0666923523],"type":"Point"}
}