{
  "type": "Feature",
  "properties": {
    "iso:country":"ES",
    "sg:address":"Carr Farmaceutic Gonzalez, 2",
    "sg:city":"Port D'andratx",
    "sg:orig_category":"Laboratorios Y Trabajos De Fotograf\u00cda, V\u00cddeo Y Cine",
    "sg:phone":"+34 971 67 17 17",
    "sg:postcode":"07157",
    "sg:province":"Islas Baleares",
    "wof:name":"Moragues Vila Juan",
    "wof:placetype":"venue"
},
  "geometry": {"coordinates":[2.4215099812,39.5746994019],"type":"Point"}
}