{
  "type": "Feature",
  "properties": {
    "iso:country":"ES",
    "sg:address":"Calle de Antonio Machado, S/n",
    "sg:city":"Torraos",
    "sg:orig_category":"Chapister\u00cda",
    "sg:phone":"+34 968 69 03 81",
    "sg:postcode":"30563",
    "sg:province":"Murcia",
    "wof:name":"Navarro Sanchez Domingo",
    "wof:placetype":"venue"
},
  "geometry": {"coordinates":[-1.280330658,38.0987663269],"type":"Point"}
}