{
  "type": "Feature",
  "properties": {
    "addr:full":"Rbla Rambla Nova, 42 Tarragona Tarragona 43004",
    "addr:housenumber":"42",
    "addr:postcode":"43004",
    "addr:street":"Rambla Nova",
    "iso:country":"ES",
    "sg:address":"Rbla Rambla Nova, 42",
    "sg:city":"Tarragona",
    "sg:orig_category":"Ropa Para Se\u00d1oras Y Caballeros (al Por Menor)",
    "sg:phone":"+34 977 22 60 27",
    "sg:postcode":"43004",
    "sg:province":"Tarragona",
    "wof:name":"Pluvinet Puigvert Sebastian",
    "wof:placetype":"venue"
},
  "geometry": {"coordinates":[1.2541049719,41.1169281006],"type":"Point"}
}