{
  "type": "Feature",
  "properties": {
    "addr:full":"Carrer de Bartomeu Rossello, 17 Palma Islas Baleares 07014",
    "addr:housenumber":"17",
    "addr:postcode":"07014",
    "addr:street":"Carrer De Bartomeu Rossello",
    "iso:country":"ES",
    "sg:address":"Carrer de Bartomeu Rossello, 17",
    "sg:city":"Palma",
    "sg:orig_category":"Florister\u00cdas",
    "sg:phone":"+34 971 28 00 16",
    "sg:postcode":"07014",
    "sg:province":"Islas Baleares",
    "wof:name":"Font Llopico Margarita",
    "wof:placetype":"venue"
},
  "geometry": {"coordinates":[2.6311628819,39.5717697144],"type":"Point"}
}