{
  "type": "Feature",
  "properties": {
    "iso:country":"ES",
    "sg:address":"Avda Hercules, 20",
    "sg:city":"Coru\u00d1a",
    "sg:orig_category":"Agencias Y Agentes Comerciales, Representantes",
    "sg:phone":"+34 981 22 75 65",
    "sg:postcode":"15002",
    "sg:province":"A Coru\u00f1a",
    "wof:name":"Suarez Babio Luis Enrique",
    "wof:placetype":"venue"
},
  "geometry": {"coordinates":[-8.3996629715,43.377117157],"type":"Point"}
}