{
  "type": "Feature",
  "properties": {
    "addr:full":"Rua San Roque, 90 Lugo Lugo 27002",
    "addr:housenumber":"90",
    "addr:postcode":"27002",
    "addr:street":"Rua San Roque",
    "iso:country":"ES",
    "sg:address":"Rua San Roque, 90",
    "sg:city":"Lugo",
    "sg:orig_category":"Aparcamientos (infraestructuras, Accesorios)",
    "sg:phone":"+34 982 22 10 38",
    "sg:postcode":"27002",
    "sg:province":"Lugo",
    "wof:name":"Lence Torres S.l.",
    "wof:placetype":"venue"
},
  "geometry": {"coordinates":[-7.5512070656,43.0058517456],"type":"Point"}
}