{
  "type": "Feature",
  "properties": {
    "addr:full":"Calle de Granados, Musico, S/n Melilla Melilla 52004",
    "addr:housenumber":"s / n",
    "addr:postcode":"52004",
    "addr:street":"Calle De Granados Musico",
    "iso:country":"ES",
    "sg:address":"Calle de Granados, Musico, S/n",
    "sg:city":"Melilla",
    "sg:orig_category":"Asociaciones Humanitarias, De Cooperaci\u00d3n, De Acci\u00d3n Social",
    "sg:phone":"+34 952 67 81 51",
    "sg:postcode":"52004",
    "sg:province":"Melilla",
    "wof:name":"Asociacion De Padres De Ni\u00f1os Especiales",
    "wof:placetype":"venue"
},
  "geometry": {"coordinates":[-2.9428510666,35.2879371643],"type":"Point"}
}