{
  "type": "Feature",
  "properties": {
    "addr:full":"Calle de Juan Xxiii, 11 Arganda Madrid 28500",
    "addr:housenumber":"11",
    "addr:postcode":"28500",
    "addr:street":"Calle De Juan Xxiii",
    "iso:country":"ES",
    "sg:address":"Calle de Juan Xxiii, 11",
    "sg:city":"Arganda",
    "sg:orig_category":"Telas Y Sedas (al Por Menor)",
    "sg:phone":"+34 918 70 10 47",
    "sg:postcode":"28500",
    "sg:province":"Madrid",
    "wof:name":"Rodriguez San Juan Pascual",
    "wof:placetype":"venue"
},
  "geometry": {"coordinates":[-3.4376459122,40.3001594543],"type":"Point"}
}