{
  "type": "Feature",
  "properties": {
    "iso:country":"ES",
    "sg:address":"Calle de Mozart, 15",
    "sg:city":"Madrid",
    "sg:orig_category":"Administradores De Bienes Y Delegados De Comunidades De Propietarios",
    "sg:phone":"+34 915 48 56 32",
    "sg:postcode":"28008",
    "sg:province":"Madrid",
    "wof:name":"Canto Alberca Angel",
    "wof:placetype":"venue"
},
  "geometry": {"coordinates":[-3.723197937,40.4237480164],"type":"Point"}
}