{
  "type": "Feature",
  "properties": {
    "iso:country":"ES",
    "sg:address":"Calle de Hacienda De Pavones, 194",
    "sg:city":"Madrid",
    "sg:orig_category":"Bisuter\u00cda, Joyer\u00cda, Relojer\u00cda (al Por Menor)",
    "sg:phone":"+34 917 72 47 59",
    "sg:postcode":"28030",
    "sg:province":"Madrid",
    "wof:name":"Luna Perez Victoria",
    "wof:placetype":"venue"
},
  "geometry": {"coordinates":[-3.6408047676,40.4019165039],"type":"Point"}
}