{
  "type": "Feature",
  "properties": {
    "iso:country":"ES",
    "sg:address":"Calle de Perez Diaz, 38",
    "sg:city":"Victoria Acentejo",
    "sg:orig_category":"Ense\u00d1anza, Formaci\u00d3n Profesional: Aprendizaje",
    "sg:phone":"+34 922 58 10 05",
    "sg:postcode":"38380",
    "sg:province":"Santa Cruz De Tenerife",
    "wof:name":"Ayuntamiento De La Victoria De Acentejo-area De Deportes",
    "wof:placetype":"venue"
},
  "geometry": {"coordinates":[-16.4677009583,28.4352893829],"type":"Point"}
}