{
  "type": "Feature",
  "properties": {
    "iso:country":"ES",
    "sg:address":"Av Reina Fabiola, 8",
    "sg:city":"Zona Costera",
    "sg:orig_category":"Productos Qu\u00cdmicos (fabricaci\u00d3n, Al Por Mayor)",
    "sg:phone":"+34 977 80 34 58",
    "sg:postcode":"43883",
    "sg:province":"Tarragona",
    "wof:name":"Foodfeed S.l.",
    "wof:placetype":"venue"
},
  "geometry": {"coordinates":[1.4810999632,41.1726493835],"type":"Point"}
}