{
  "type": "Feature",
  "properties": {
    "addr:full":"Avda Ciudad De Chiva, S/n Sevilla Sevilla 41019",
    "addr:housenumber":"s / n",
    "addr:postcode":"41019",
    "addr:street":"Avda Ciudad De Chiva",
    "iso:country":"ES",
    "sg:address":"Avda Ciudad De Chiva, S/n",
    "sg:city":"Sevilla",
    "sg:orig_category":"Fotograf\u00cda Publicitaria E Industrial",
    "sg:phone":"+34 954 25 88 45",
    "sg:postcode":"41019",
    "sg:province":"Sevilla",
    "wof:name":"Rogelio Studio S.l.",
    "wof:placetype":"venue"
},
  "geometry": {"coordinates":[-5.9311738014,37.412109375],"type":"Point"}
}