{
  "type": "Feature",
  "properties": {
    "addr:full":"Calle de Antonio Lopez, 30 S. Fernando C\u00e1diz 11100",
    "addr:postcode":"11100",
    "addr:street":"Calle De Antonio Lopez 30 S. Fernando Ca\u0301Diz",
    "iso:country":"ES",
    "sg:address":"Calle de Antonio Lopez, 30",
    "sg:city":"S. Fernando",
    "sg:orig_category":"Arquitectos",
    "sg:phone":"+34 956 89 02 12",
    "sg:postcode":"11100",
    "sg:province":"C\u00e1diz",
    "wof:name":"Toledo Bernal Rafael",
    "wof:placetype":"venue"
},
  "geometry": {"coordinates":[-6.1982831955,36.4662361145],"type":"Point"}
}