{
  "type": "Feature",
  "properties": {
    "addr:full":"Calle de D. Jose Lastiesas, S/n Sabi\u00f1anigo Huesca 22600",
    "addr:housenumber":"s / n",
    "addr:postcode":"22600",
    "addr:street":"Calle De D. Jose Lastiesas",
    "iso:country":"ES",
    "sg:address":"Calle de D. Jose Lastiesas, S/n",
    "sg:city":"Sabi\u00f1anigo",
    "sg:orig_category":"Delegados, Agentes De Tr\u00c1nsito, Auxiliares De Transporte Internacional",
    "sg:phone":"+34 974 48 22 15",
    "sg:postcode":"22600",
    "sg:province":"Huesca",
    "wof:name":"Ceresuela Eito Antonio",
    "wof:placetype":"venue"
},
  "geometry": {"coordinates":[-0.3576740026,42.5217552185],"type":"Point"}
}