{
  "type": "Feature",
  "properties": {
    "addr:full":"Calle de Sierra De Cazorla, 41 Viator Almer\u00eda 04240",
    "addr:housenumber":"41",
    "addr:postcode":"04240",
    "addr:street":"Calle De Sierra De Cazorla;Almeri\u0301A",
    "iso:country":"ES",
    "sg:address":"Calle de Sierra De Cazorla, 41",
    "sg:city":"Viator",
    "sg:orig_category":"Abrasivos Y Superabrasivos (fabricaci\u00d3n, Al Por Mayor)",
    "sg:phone":"+34 950 30 60 66",
    "sg:postcode":"04240",
    "sg:province":"Almer\u00eda",
    "wof:name":"Antonio Milan S.a.",
    "wof:placetype":"venue"
},
  "geometry": {"coordinates":[-2.4200348854,36.8842468262],"type":"Point"}
}