{
  "type": "Feature",
  "properties": {
    "iso:country":"ES",
    "sg:address":"Calle de Fray Norberto Del Prado, 43",
    "sg:city":"Pola De Laviana",
    "sg:orig_category":"Molduras, Junquillos, Listones Y Molduras Perforadas",
    "sg:phone":"+34 985 61 07 60",
    "sg:postcode":"33980",
    "sg:province":"Asturias",
    "wof:name":"Rodriguez Gonzalez Facundo",
    "wof:placetype":"venue"
},
  "geometry": {"coordinates":[-5.5613670349,43.2455024719],"type":"Point"}
}