{
  "type": "Feature",
  "properties": {
    "iso:country":"ES",
    "sg:address":"Carretera De Los Villares, Km. 0015,0",
    "sg:city":"Cerro Muriano",
    "sg:orig_category":"Aguas (distribuci\u00d3n, Servicios)",
    "sg:phone":"+34 957 35 03 43",
    "sg:postcode":"14350",
    "sg:province":"C\u00f3rdoba",
    "wof:name":"Empresa Municipal De Aguas De Cordoba S.a.",
    "wof:placetype":"venue"
},
  "geometry": {"coordinates":[-4.7704291344,38.0036849976],"type":"Point"}
}