{
  "type": "Feature",
  "properties": {
    "addr:full":"Calle de Meson De Paredes, 62 Madrid Madrid 28012",
    "addr:housenumber":"62",
    "addr:postcode":"madrid;28012",
    "addr:street":"Calle De Meson De Paredes",
    "iso:country":"ES",
    "sg:address":"Calle de Meson De Paredes, 62",
    "sg:city":"Madrid",
    "sg:orig_category":"Peluqueros: De Se\u00d1oras",
    "sg:phone":"+34 914 68 48 89",
    "sg:postcode":"28012",
    "sg:province":"Madrid",
    "wof:name":"Salvador Vega Maria Del Carmen",
    "wof:placetype":"venue"
},
  "geometry": {"coordinates":[-3.7036750317,40.4088478088],"type":"Point"}
}