{
  "type": "Feature",
  "properties": {
    "iso:country":"ES",
    "sg:address":"Calle de Japon, 12",
    "sg:city":"Alcorcon",
    "sg:orig_category":"Molduras, Junquillos, Listones Y Molduras Perforadas",
    "sg:phone":"+34 916 11 38 70",
    "sg:postcode":"28923",
    "sg:province":"Madrid",
    "wof:name":"Rodriguez Sanchez Angel Javier",
    "wof:placetype":"venue"
},
  "geometry": {"coordinates":[-3.8181378841,40.3451271057],"type":"Point"}
}