{
  "type": "Feature",
  "properties": {
    "iso:country":"ES",
    "sg:address":"Carrer de Sant Elies, 34",
    "sg:city":"Reus",
    "sg:orig_category":"Ense\u00d1anza: Idiomas",
    "sg:phone":"+34 977 33 07 75",
    "sg:postcode":"43201",
    "sg:province":"Tarragona",
    "wof:name":"Rodas Saporta Maria Consolacion",
    "wof:placetype":"venue"
},
  "geometry": {"coordinates":[1.1042209864,41.1570968628],"type":"Point"}
}