{
  "type": "Feature",
  "properties": {
    "iso:country":"ES",
    "sg:address":"Ctra Matarredonda, 8",
    "sg:city":"Estepa",
    "sg:orig_category":"Artes Gr\u00c1ficas, Artes Pl\u00c1sticas (curso)",
    "sg:phone":"+34 955 91 27 04",
    "sg:postcode":"41560",
    "sg:province":"Sevilla",
    "wof:name":"Imprenta Hermoso S.l.",
    "wof:placetype":"venue"
},
  "geometry": {"coordinates":[-4.8825011253,37.2972412109],"type":"Point"}
}