{
  "type": "Feature",
  "properties": {
    "iso:country":"ES",
    "sg:address":"Avda Mariano Hernandez Caro, 44",
    "sg:city":"Roquetas Mar",
    "sg:orig_category":"Peluquer\u00cdas, Peluquer\u00cda Mixta",
    "sg:phone":"+34 950 32 99 52",
    "sg:postcode":"04740",
    "sg:province":"Almer\u00eda",
    "wof:name":"Fernandez Molina Soledad",
    "wof:placetype":"venue"
},
  "geometry": {"coordinates":[-2.6124989986,36.7638435364],"type":"Point"}
}