{
  "type": "Feature",
  "properties": {
    "iso:country":"ES",
    "sg:address":"Carrer de L'almirall Churruca, 4",
    "sg:city":"Barcelona",
    "sg:orig_category":"Inmobiliaria (agencias)",
    "sg:phone":"+34 932 21 90 00",
    "sg:postcode":"08003",
    "sg:province":"Barcelona",
    "sg:website":"www.stecnocasa.com",
    "wof:name":"Estudi Barceloneta Mar S.l.",
    "wof:placetype":"venue"
},
  "geometry": {"coordinates":[2.1897237301,41.3790245056],"type":"Point"}
}