{
  "type": "Feature",
  "properties": {
    "addr:full":"Calle de Arroyo Hondo, 15 Velez-malaga M\u00e1laga 29700",
    "addr:housenumber":"15",
    "addr:postcode":"29700",
    "addr:street":"Calle De Arroyo Hondo",
    "iso:country":"ES",
    "sg:address":"Calle de Arroyo Hondo, 15",
    "sg:city":"Velez-malaga",
    "sg:orig_category":"M\u00c1quinas De Coser Y De Hacer Punto (al Por Mayor)",
    "sg:phone":"+34 952 50 18 52",
    "sg:postcode":"29700",
    "sg:province":"M\u00e1laga",
    "wof:name":"Rando Garcia Miguel",
    "wof:placetype":"venue"
},
  "geometry": {"coordinates":[-4.1029295921,36.7795295715],"type":"Point"}
}