{
  "type": "Feature",
  "properties": {
    "iso:country":"ES",
    "sg:address":"Calle de Norberto Cuesta Dutari, 3",
    "sg:city":"Salamanca",
    "sg:orig_category":"M\u00c1quinas De Escribir, M\u00c1quinas De Oficina (al Por Menor, Reparaci\u00d3n)",
    "sg:phone":"+34 923 26 76 28",
    "sg:postcode":"37007",
    "sg:province":"Salamanca",
    "sg:website":"www.campuesjobs.com",
    "wof:name":"Sistemas S.m.i S S.l",
    "wof:placetype":"venue"
},
  "geometry": {"coordinates":[-5.6723461151,40.9664230347],"type":"Point"}
}