{
  "type": "Feature",
  "properties": {
    "addr:full":"Calle de Azcarate, 6 Port D'andratx Islas Baleares 07157",
    "addr:housenumber":"6",
    "addr:postcode":"07157",
    "addr:street":"Calle De Azcarate",
    "iso:country":"ES",
    "sg:address":"Calle de Azcarate, 6",
    "sg:city":"Port D'andratx",
    "sg:orig_category":"Fabricaci\u00d3n, Reparaci\u00d3n Y Mantenimiento De Construcciones Navales Y Fluviales",
    "sg:phone":"+34 971 67 29 39",
    "sg:postcode":"07157",
    "sg:province":"Islas Baleares",
    "wof:name":"Oppenheim Stuart Eduardo",
    "wof:placetype":"venue"
},
  "geometry": {"coordinates":[2.3865675926,39.5431289673],"type":"Point"}
}