{
  "type": "Feature",
  "properties": {
    "addr:full":"Avda Fernandez Balsera De, 2 Aviles Asturias 33402",
    "addr:postcode":"33402",
    "addr:street":"Avda Fernandez",
    "iso:country":"ES",
    "sg:address":"Avda Fernandez Balsera De, 2",
    "sg:city":"Aviles",
    "sg:orig_category":"Agencias De Viajes",
    "sg:phone":"+34 985 52 78 26",
    "sg:postcode":"33402",
    "sg:province":"Asturias",
    "sg:website":"www.marsans.es",
    "wof:name":"Viajes Marsans S.a.",
    "wof:placetype":"venue"
},
  "geometry": {"coordinates":[-5.9259867668,43.5565490723],"type":"Point"}
}