{
  "type": "Feature",
  "properties": {
    "addr:full":"Calle de Casas Nuevas, 11 Guazamara Almer\u00eda 04647",
    "addr:housenumber":"11",
    "addr:postcode":"04647",
    "addr:street":"Calle De Casas Nuevas;Almeri\u0301A",
    "iso:country":"ES",
    "sg:address":"Calle de Casas Nuevas, 11",
    "sg:city":"Guazamara",
    "sg:orig_category":"Producci\u00d3n De Huevos",
    "sg:phone":"+34 950 39 60 17",
    "sg:postcode":"04647",
    "sg:province":"Almer\u00eda",
    "wof:name":"Huevos Guazamara S.l.",
    "wof:placetype":"venue"
},
  "geometry": {"coordinates":[-1.7667688131,37.3065299988],"type":"Point"}
}