{
  "type": "Feature",
  "properties": {
    "addr:full":"Carrer de Francesc Marti I M, 63 Palma Islas Baleares 07011",
    "addr:postcode":"07011",
    "addr:street":"Carrer De Francesc Marti;M",
    "iso:country":"ES",
    "sg:address":"Carrer de Francesc Marti I M, 63",
    "sg:city":"Palma",
    "sg:orig_category":"Molduras, Junquillos, Listones Y Molduras Perforadas",
    "sg:phone":"+34 971 73 75 10",
    "sg:postcode":"07011",
    "sg:province":"Islas Baleares",
    "wof:name":"Sistelcom-telemensaje S.a.",
    "wof:placetype":"venue"
},
  "geometry": {"coordinates":[2.6356189251,39.5843849182],"type":"Point"}
}