{
  "type": "Feature",
  "properties": {
    "iso:country":"ES",
    "sg:address":"Calle de Ebanisteria (la), 36",
    "sg:city":"Alacant",
    "sg:orig_category":"Vinos Y Licores (venta Al Por Menor)",
    "sg:phone":"+34 965 98 78 00",
    "sg:postcode":"03...",
    "sg:province":"Alicante",
    "sg:website":"www.maset.com",
    "wof:name":"Medios De Telemarketing S.l.",
    "wof:placetype":"venue"
},
  "geometry": {"coordinates":[-0.514210999,38.3344078064],"type":"Point"}
}