{
  "type": "Feature",
  "properties": {
    "iso:country":"ES",
    "sg:address":"Calle de Malvar, S/n",
    "sg:city":"Cuevas Provanco",
    "sg:orig_category":"Abogados",
    "sg:phone":"+34 921 52 72 05",
    "sg:postcode":"40239",
    "sg:province":"Segovia",
    "wof:name":"Andres Melero Angel",
    "wof:placetype":"venue"
},
  "geometry": {"coordinates":[-4.1192092896,40.9494285583],"type":"Point"}
}