{
  "type": "Feature",
  "properties": {
    "iso:country":"ES",
    "sg:address":"Carr Vallcalent, 34",
    "sg:city":"Lleida",
    "sg:orig_category":"Mec\u00c1nico Del Autom\u00d3vil",
    "sg:phone":"+34 973 27 26 50",
    "sg:postcode":"25006",
    "sg:province":"Lleida",
    "wof:name":"Masip Torrent Josep",
    "wof:placetype":"venue"
},
  "geometry": {"coordinates":[0.617299974,41.6178665161],"type":"Point"}
}