{
  "type": "Feature",
  "properties": {
    "iso:country":"ES",
    "sg:address":"Carrer de Consell De Cent, 22",
    "sg:city":"Terrassa",
    "sg:orig_category":"Fabricaci\u00d3n De Su\u00c9ters Y Chalecos De Punto",
    "sg:phone":"+34 937 35 71 79",
    "sg:postcode":"08226",
    "sg:province":"Barcelona",
    "wof:name":"Lopez Diaz Segundo Juan",
    "wof:placetype":"venue"
},
  "geometry": {"coordinates":[2.0202488899,41.5742073059],"type":"Point"}
}