{
  "type": "Feature",
  "properties": {
    "iso:country":"ES",
    "sg:address":"Cra. Olot, 61",
    "sg:city":"Manlleu",
    "sg:orig_category":"Farmacias",
    "sg:phone":"+34 938 51 25 95",
    "sg:postcode":"08560",
    "sg:province":"Barcelona",
    "wof:name":"Cornellas Falgueras Pio",
    "wof:placetype":"venue"
},
  "geometry": {"coordinates":[2.2937219143,42.0037689209],"type":"Point"}
}