{
  "type": "Feature",
  "properties": {
    "iso:country":"ES",
    "sg:address":"Ctra Istan, Km. 0000,9",
    "sg:city":"Marbella",
    "sg:orig_category":"Promotores Constructores",
    "sg:phone":"+34 952 82 21 57",
    "sg:postcode":"29600",
    "sg:province":"M\u00e1laga",
    "wof:name":"Sierra Blanca Properties S.l.",
    "wof:placetype":"venue"
},
  "geometry": {"coordinates":[-4.8833007812,36.5079956055],"type":"Point"}
}