{
  "type": "Feature",
  "properties": {
    "addr:full":"Ptge Tasso, 6 Barcelona Barcelona 08009",
    "addr:housenumber":"6",
    "addr:postcode":"08009",
    "addr:street":"Ptge Tasso",
    "iso:country":"ES",
    "sg:address":"Ptge Tasso, 6",
    "sg:city":"Barcelona",
    "sg:orig_category":"Construcci\u00d3n Mec\u00c1nica",
    "sg:phone":"+34 932 65 28 42",
    "sg:postcode":"08009",
    "sg:province":"Barcelona",
    "wof:name":"Decoletajes Jomis S.l.",
    "wof:placetype":"venue"
},
  "geometry": {"coordinates":[2.1742539406,41.3966255188],"type":"Point"}
}