{
  "type": "Feature",
  "properties": {
    "iso:country":"ES",
    "sg:address":"Calle de General Medrano De Miguel, 6",
    "sg:city":"Guadalajara",
    "sg:orig_category":"Ropa Para Se\u00d1oras Y Caballeros (al Por Menor)",
    "sg:phone":"+34 949 22 21 17",
    "sg:postcode":"19003",
    "sg:province":"Guadalajara",
    "wof:name":"Villalba Gallego Maria Isabel",
    "wof:placetype":"venue"
},
  "geometry": {"coordinates":[-3.1738069057,40.6312446594],"type":"Point"}
}