{
  "type": "Feature",
  "properties": {
    "iso:country":"ES",
    "sg:address":"Carrer de Gran Canaria, 1",
    "sg:city":"Granja",
    "sg:orig_category":"Venta, Instalaci\u00d3n De Calefacci\u00d3n",
    "sg:phone":"+34 977 54 96 06",
    "sg:postcode":"43006",
    "sg:province":"Tarragona",
    "wof:name":"Inst-mant Sal",
    "wof:placetype":"venue"
},
  "geometry": {"coordinates":[1.2209249735,41.1154441833],"type":"Point"}
}