{
  "type": "Feature",
  "properties": {
    "addr:full":"Av Cami De La Fita, S/n Sitges Barcelona 08870",
    "addr:housenumber":"s / n",
    "addr:postcode":"08870",
    "addr:street":"Av Cami De La Fita",
    "iso:country":"ES",
    "sg:address":"Av Cami De La Fita, S/n",
    "sg:city":"Sitges",
    "sg:orig_category":"Ense\u00d1anza Secundaria: Colegios Y Escuelas Privadas",
    "sg:phone":"+34 938 94 37 12",
    "sg:postcode":"08870",
    "sg:province":"Barcelona",
    "wof:name":"Centre De Telecomunicaciones De Catalunya",
    "wof:placetype":"venue"
},
  "geometry": {"coordinates":[1.7753950357,41.2280235291],"type":"Point"}
}