{
  "type": "Feature",
  "properties": {
    "addr:full":"Avda Juan Carlos I, 47 Puebla Almoradiel Toledo 45840",
    "addr:housenumber":"47",
    "addr:postcode":"45840",
    "addr:street":"Avda Juan Carlos I;Almoradiel",
    "iso:country":"ES",
    "sg:address":"Avda Juan Carlos I, 47",
    "sg:city":"Puebla Almoradiel",
    "sg:orig_category":"Quincaller\u00cda (al Por Menor)",
    "sg:phone":"+34 925 17 82 13",
    "sg:postcode":"45840",
    "sg:province":"Toledo",
    "wof:name":"Mu\u00f1oz Vaquero Jose Luis",
    "wof:placetype":"venue"
},
  "geometry": {"coordinates":[-3.108825922,39.598072052],"type":"Point"}
}