{
  "type": "Feature",
  "properties": {
    "iso:country":"ES",
    "sg:address":"Calle de Mulhacen, 26",
    "sg:city":"Urbanizacion Nueva Cartagena",
    "sg:orig_category":"Peluqueros: De Se\u00d1oras",
    "sg:phone":"+34 968 53 67 03",
    "sg:postcode":"30310",
    "sg:province":"Murcia",
    "wof:name":"Rodrigo Garcia Isabel",
    "wof:placetype":"venue"
},
  "geometry": {"coordinates":[-1.0064510107,37.6224250793],"type":"Point"}
}