{
  "type": "Feature",
  "properties": {
    "addr:full":"Calle de Trinidad, 41 Talavera Reina Toledo 45600",
    "addr:housenumber":"41",
    "addr:postcode":"45600",
    "addr:street":"Calle De Trinidad",
    "iso:country":"ES",
    "sg:address":"Calle de Trinidad, 41",
    "sg:city":"Talavera Reina",
    "sg:orig_category":"M\u00c9dicos: Estomatolog\u00cda",
    "sg:phone":"+34 925 80 97 61",
    "sg:postcode":"45600",
    "sg:province":"Toledo",
    "wof:name":"Macarro Cano Francisco Javier",
    "wof:placetype":"venue"
},
  "geometry": {"coordinates":[-4.8266921043,39.9635658264],"type":"Point"}
}