{
  "type": "Feature",
  "properties": {
    "iso:country":"ES",
    "sg:address":"Calle de Victoria Balfe, 6",
    "sg:city":"Burgos",
    "sg:orig_category":"Delegados, Agentes De Tr\u00c1nsito, Auxiliares De Transporte Internacional",
    "sg:phone":"+34 947 22 59 49",
    "sg:postcode":"09006",
    "sg:province":"Burgos",
    "wof:name":"Saiz Anton Maria Concepcion",
    "wof:placetype":"venue"
},
  "geometry": {"coordinates":[-3.6814160347,42.359954834],"type":"Point"}
}