{
  "type": "Feature",
  "properties": {
    "iso:country":"ES",
    "sg:address":"Calle de Libertad, 6",
    "sg:city":"Pe\u00e7aranda De Bracamonte",
    "sg:orig_category":"Empresas De Pintura Y Revestimientos",
    "sg:phone":"+34 923 54 14 74",
    "sg:postcode":"37300",
    "sg:province":"Salamanca",
    "wof:name":"Lagar De Manueles Alejandro Maximo",
    "wof:placetype":"venue"
},
  "geometry": {"coordinates":[-5.2017068863,40.9006233215],"type":"Point"}
}