{
  "type": "Feature",
  "properties": {
    "addr:full":"Calle de Republica Argentina, 21 Malaga M\u00e1laga 29016",
    "addr:housenumber":"21",
    "addr:postcode":"29016",
    "addr:street":"Calle De Republica Argentina;Ma\u0301Laga",
    "iso:country":"ES",
    "sg:address":"Calle de Republica Argentina, 21",
    "sg:city":"Malaga",
    "sg:orig_category":"Farmacias",
    "sg:phone":"+34 952 60 97 34",
    "sg:postcode":"29016",
    "sg:province":"M\u00e1laga",
    "wof:name":"Fernandez-canivell Toro Guillermo",
    "wof:placetype":"venue"
},
  "geometry": {"coordinates":[-4.3991532326,36.7277336121],"type":"Point"}
}