{
  "type": "Feature",
  "properties": {
    "iso:country":"ES",
    "sg:address":"El Condado, 97",
    "sg:city":"Condado",
    "sg:orig_category":"Negocio De Materiales De Construcci\u00d3n",
    "sg:phone":"+34 985 61 44 30",
    "sg:postcode":"33992",
    "sg:province":"Asturias",
    "wof:name":"Rubel 2000 S.l.",
    "wof:placetype":"venue"
},
  "geometry": {"coordinates":[-5.510201931,43.2515678406],"type":"Point"}
}