{
  "type": "Feature",
  "properties": {
    "iso:country":"ES",
    "sg:address":"Calle de Madrigal De Las Altas Torres, S/n",
    "sg:city":"Arevalo",
    "sg:orig_category":"Maquinaria Para Industrias Diversas",
    "sg:phone":"+34 920 30 02 08",
    "sg:postcode":"05200",
    "sg:province":"\u00c1vila",
    "wof:name":"Agromecanica Jemar S.l.",
    "wof:placetype":"venue"
},
  "geometry": {"coordinates":[-4.732278,41.074387],"type":"Point"}
}