{
  "type": "Feature",
  "properties": {
    "iso:country":"ES",
    "sg:address":"Av. Via Lusitana, 27",
    "sg:city":"Madrid",
    "sg:orig_category":"Ingenier\u00cda, Centros De Estudios (diversos)",
    "sg:phone":"+34 913 41 59 16",
    "sg:postcode":"28025",
    "sg:province":"Madrid",
    "sg:website":"www.inisod.com",
    "wof:name":"Ingenieria De Instalaciones Y Obras S.l.",
    "wof:placetype":"venue"
},
  "geometry": {"coordinates":[-3.731742382,40.3750762939],"type":"Point"}
}