{
  "type": "Feature",
  "properties": {
    "iso:country":"ES",
    "sg:address":"Avda Viana, 14",
    "sg:city":"Logro\u00f1o",
    "sg:orig_category":"Equitaci\u00d3n: Guarnicioner\u00cda, Equipo (al Por Menor)",
    "sg:phone":"+34 941 24 23 76",
    "sg:postcode":"26001",
    "sg:province":"La Rioja",
    "wof:name":"Navarro Almarza Carlos",
    "wof:placetype":"venue"
},
  "geometry": {"coordinates":[-2.4419209957,42.4681472778],"type":"Point"}
}