{
  "type": "Feature",
  "properties": {
    "addr:full":"Carr Tren, S/n Quart Girona 17242",
    "addr:housenumber":"s / n",
    "addr:postcode":"17242",
    "addr:street":"Carr Tren",
    "iso:country":"ES",
    "sg:address":"Carr Tren, S/n",
    "sg:city":"Quart",
    "sg:orig_category":"Centros De Educaci\u00d3n Especial",
    "sg:phone":"+34 972 46 93 81",
    "sg:postcode":"17242",
    "sg:province":"Girona",
    "wof:name":"C.e.i.p. Santa Margarida",
    "wof:placetype":"venue"
},
  "geometry": {"coordinates":[2.8420550823,41.9365539551],"type":"Point"}
}