{
  "type": "Feature",
  "properties": {
    "iso:country":"ES",
    "sg:address":"Calle de Do\u00d1a Alejandrina, 1",
    "sg:city":"Rafal",
    "sg:orig_category":"Cajas Para Embalar",
    "sg:phone":"+34 966 75 23 02",
    "sg:postcode":"03369",
    "sg:province":"Alicante",
    "sg:website":"www.ruralvia.com",
    "wof:name":"Caja Rural Central De Orihuela",
    "wof:placetype":"venue"
},
  "geometry": {"coordinates":[-0.8488559723,38.105091095],"type":"Point"}
}