{
  "type": "Feature",
  "properties": {
    "iso:country":"ES",
    "sg:address":"Avda Fernando De Castro, 48",
    "sg:city":"Sahagun",
    "sg:orig_category":"Ebanister\u00cda",
    "sg:phone":"+34 987 78 03 12",
    "sg:postcode":"24320",
    "sg:province":"Le\u00f3n",
    "wof:name":"Martinez Nicolas Francisco",
    "wof:placetype":"venue"
},
  "geometry": {"coordinates":[-5.0285148621,42.369644165],"type":"Point"}
}