{
  "type": "Feature",
  "properties": {
    "iso:country":"ES",
    "sg:address":"C/ Sant Antoni Maria Claret, 3",
    "sg:city":"Vilobi D'onyar",
    "sg:orig_category":"Promotores Constructores",
    "sg:phone":"+34 972 47 31 32",
    "sg:postcode":"17185",
    "sg:province":"Girona",
    "wof:name":"Pujol Felip Luis",
    "wof:placetype":"venue"
},
  "geometry": {"coordinates":[2.8190639019,41.9807014465],"type":"Point"}
}