{
  "type": "Feature",
  "properties": {
    "iso:country":"ES",
    "sg:address":"Calle de General Aranaz, 42",
    "sg:city":"Madrid",
    "sg:orig_category":"Maquinaria Para Industrias Diversas",
    "sg:phone":"+34 917 42 38 17",
    "sg:postcode":"28027",
    "sg:province":"Madrid",
    "wof:name":"Prototipos Industriales Y Fabricados Espa\u00f1oles S.l.",
    "wof:placetype":"venue"
},
  "geometry": {"coordinates":[-3.6379749775,40.4423561096],"type":"Point"}
}