{
  "type": "Feature",
  "properties": {
    "addr:full":"Carrer de Sol (del), 33 Tortosa Tarragona 43500",
    "addr:housenumber":"33",
    "addr:postcode":"43500",
    "addr:street":"Carrer De Sol Del",
    "iso:country":"ES",
    "sg:address":"Carrer de Sol (del), 33",
    "sg:city":"Tortosa",
    "sg:orig_category":"Molduras, Junquillos, Listones Y Molduras Perforadas",
    "sg:phone":"+34 977 51 02 49",
    "sg:postcode":"43500",
    "sg:province":"Tarragona",
    "wof:name":"Segarra Barreno Marcos",
    "wof:placetype":"venue"
},
  "geometry": {"coordinates":[0.5242620111,40.8182220459],"type":"Point"}
}