{
  "type": "Feature",
  "properties": {
    "iso:country":"ES",
    "sg:address":"Calle de Alfonso Xii, 22",
    "sg:city":"Porcuna",
    "sg:orig_category":"Internados & Ense\u00d1anza Privada",
    "sg:phone":"+34 953 54 41 05",
    "sg:postcode":"23790",
    "sg:province":"Ja\u00e9n",
    "wof:name":"Religiosas De San Jose",
    "wof:placetype":"venue"
},
  "geometry": {"coordinates":[-4.1849856377,37.8730354309],"type":"Point"}
}