{
  "type": "Feature",
  "properties": {
    "addr:full":"Avda Pelay Correa, S/n Alcala Guadaira Sevilla 41500",
    "addr:housenumber":"s",
    "addr:postcode":"41500",
    "addr:street":"Avda Pelay Correa;/ N",
    "iso:country":"ES",
    "sg:address":"Avda Pelay Correa, S/n",
    "sg:city":"Alcala Guadaira",
    "sg:orig_category":"Transportes Por Carretera: Lotes Completos, Mercanc\u00cdas Diversas",
    "sg:phone":"+34 955 61 48 88",
    "sg:postcode":"41500",
    "sg:province":"Sevilla",
    "wof:name":"Cash Sevilla S.a.",
    "wof:placetype":"venue"
},
  "geometry": {"coordinates":[-5.8714489937,37.3567962646],"type":"Point"}
}