{
  "type": "Feature",
  "properties": {
    "iso:country":"ES",
    "sg:address":"Ctra Tiemblo (del), 5",
    "sg:city":"Cebreros",
    "sg:orig_category":"Mec\u00c1nico Del Autom\u00d3vil",
    "sg:phone":"+34 918 63 05 26",
    "sg:postcode":"05260",
    "sg:province":"\u00c1vila",
    "wof:name":"Mu\u00f1oz Recio Amparo",
    "wof:placetype":"venue"
},
  "geometry": {"coordinates":[-4.4628858566,40.4528083801],"type":"Point"}
}