{
  "type": "Feature",
  "properties": {
    "addr:full":"Calle de Flor De Mayo, 2 Milagrosa Las Palmas 35196",
    "addr:housenumber":"2",
    "addr:postcode":"35196",
    "addr:street":"Calle De Flor De Mayo",
    "iso:country":"ES",
    "sg:address":"Calle de Flor De Mayo, 2",
    "sg:city":"Milagrosa",
    "sg:orig_category":"Chapister\u00cda",
    "sg:phone":"+34 928 67 72 68",
    "sg:postcode":"35196",
    "sg:province":"Las Palmas",
    "wof:name":"Hernandez Hernandez Ignacio",
    "wof:placetype":"venue"
},
  "geometry": {"coordinates":[-15.4397096634,28.1302204132],"type":"Point"}
}