{
  "type": "Feature",
  "properties": {
    "addr:full":"Ctra Calpe, 126 Rada Moraira Alicante 03724",
    "addr:housenumber":"126",
    "addr:postcode":"03724",
    "addr:street":"Ctra Calpe",
    "iso:country":"ES",
    "sg:address":"Ctra Calpe, 126",
    "sg:city":"Rada Moraira",
    "sg:orig_category":"Centros De Coordinaci\u00d3n",
    "sg:phone":"+34 965 74 46 30",
    "sg:postcode":"03724",
    "sg:province":"Alicante",
    "wof:name":"Asistencia Y Servicios El Portet S.a.",
    "wof:placetype":"venue"
},
  "geometry": {"coordinates":[0.1344861984,38.6891365051],"type":"Point"}
}