{
  "type": "Feature",
  "properties": {
    "iso:country":"ES",
    "sg:address":"Calle de Dafne, 3",
    "sg:city":"Alacant",
    "sg:orig_category":"Tapiceros Y Tapiceros",
    "sg:phone":"+34 965 15 46 33",
    "sg:postcode":"03016",
    "sg:province":"Alicante",
    "sg:website":"www.diestudio.com",
    "wof:name":"D.i.e. Estudio S.l.",
    "wof:placetype":"venue"
},
  "geometry": {"coordinates":[-0.4399495125,38.3630027771],"type":"Point"}
}