{
  "type": "Feature",
  "properties": {
    "iso:country":"ES",
    "sg:address":"Calle de San Agustin, 8",
    "sg:city":"Madrid",
    "sg:orig_category":"Agencias Y Asesores De Publicidad",
    "sg:phone":"+34 914 29 16 30",
    "sg:postcode":"28014",
    "sg:province":"Madrid",
    "sg:website":"www.publifax-appletown.com",
    "wof:name":"Publifax De Comunicaciones S.l.",
    "wof:placetype":"venue"
},
  "geometry": {"coordinates":[-3.6970829964,40.4147262573],"type":"Point"}
}