{
  "type": "Feature",
  "properties": {
    "addr:full":"Carrer de Lloma (la), 13 Muro Alcoy Alicante 03830",
    "addr:housenumber":"13",
    "addr:postcode":"03830",
    "addr:street":"Carrer De Lloma La",
    "iso:country":"ES",
    "sg:address":"Carrer de Lloma (la), 13",
    "sg:city":"Muro Alcoy",
    "sg:orig_category":"Ense\u00d1anza: Comercio, Gesti\u00d3n, Inform\u00c1tica",
    "sg:phone":"+34 966 54 40 11",
    "sg:postcode":"03830",
    "sg:province":"Alicante",
    "sg:website":"www.infotecsl.com",
    "wof:name":"Neosolvia S.l",
    "wof:placetype":"venue"
},
  "geometry": {"coordinates":[-0.4378280044,38.7814903259],"type":"Point"}
}