{
  "type": "Feature",
  "properties": {
    "addr:full":"Calle de General Franco, S/n Mondariz Pontevedra 36870",
    "addr:housenumber":"s / n",
    "addr:postcode":"36870",
    "addr:street":"Calle De General Franco",
    "iso:country":"ES",
    "sg:address":"Calle de General Franco, S/n",
    "sg:city":"Mondariz",
    "sg:orig_category":"Delegados, Agentes De Tr\u00c1nsito, Auxiliares De Transporte Internacional",
    "sg:phone":"+34 986 65 61 28",
    "sg:postcode":"36870",
    "sg:province":"Pontevedra",
    "wof:name":"Alvarez Sotelino Jose",
    "wof:placetype":"venue"
},
  "geometry": {"coordinates":[-8.4581623077,42.2322158813],"type":"Point"}
}