{
  "type": "Feature",
  "properties": {
    "addr:full":"Avda Aurora, 19 Malaga M\u00e1laga 29002",
    "addr:housenumber":"19",
    "addr:postcode":"29002",
    "addr:street":"Avda Aurora;Ma\u0301Laga",
    "iso:country":"ES",
    "sg:address":"Avda Aurora, 19",
    "sg:city":"Malaga",
    "sg:orig_category":"Muebles, Minoristas",
    "sg:phone":"+34 952 36 90 70",
    "sg:postcode":"29002",
    "sg:province":"M\u00e1laga",
    "wof:name":"Muebles Gutierrez Pardo S.l.",
    "wof:placetype":"venue"
},
  "geometry": {"coordinates":[-4.430978775,36.716003418],"type":"Point"}
}