{
  "type": "Feature",
  "properties": {
    "addr:full":"Pg Joan Miro, 10 Terrassa Barcelona 08222",
    "addr:housenumber":"10",
    "addr:postcode":"08222",
    "addr:street":"Pg Joan Miro",
    "iso:country":"ES",
    "sg:address":"Pg Joan Miro, 10",
    "sg:city":"Terrassa",
    "sg:orig_category":"Suministros Y Materiales Industriales",
    "sg:phone":"+34 937 36 10 30",
    "sg:postcode":"08222",
    "sg:province":"Barcelona",
    "wof:name":"Materiales Tecnyfluor S.l.",
    "wof:placetype":"venue"
},
  "geometry": {"coordinates":[2.0215649605,41.560508728],"type":"Point"}
}