{
  "type": "Feature",
  "properties": {
    "addr:full":"Calle de Piles, 13 Gijon Asturias 33203",
    "addr:housenumber":"13",
    "addr:postcode":"33203",
    "addr:street":"Calle De Piles",
    "iso:country":"ES",
    "sg:address":"Calle de Piles, 13",
    "sg:city":"Gijon",
    "sg:orig_category":"Institutos De Belleza",
    "sg:phone":"+34 985 33 32 49",
    "sg:postcode":"33203",
    "sg:province":"Asturias",
    "wof:name":"Ferrero Montiel Rosalia",
    "wof:placetype":"venue"
},
  "geometry": {"coordinates":[-5.6477541924,43.5379867554],"type":"Point"}
}