{
  "type": "Feature",
  "properties": {
    "iso:country":"ES",
    "sg:address":"Calle de Doctores Castroviejo, 1",
    "sg:city":"Logro\u00f1o",
    "sg:orig_category":"Telas Para Tapizar, Cortinas, Pasamaner\u00cda (fabricaci\u00d3n, Al Por Mayor)",
    "sg:phone":"+34 941 24 01 09",
    "sg:postcode":"26003",
    "sg:province":"La Rioja",
    "wof:name":"Pastor Mu\u00f1oz Pedro",
    "wof:placetype":"venue"
},
  "geometry": {"coordinates":[-2.4445710182,42.4634132385],"type":"Point"}
}