{
  "type": "Feature",
  "properties": {
    "iso:country":"ES",
    "sg:address":"Calle de Joaquin Costa, 4",
    "sg:city":"Borja",
    "sg:orig_category":"Asesor\u00cda Sobre Comunicaci\u00d3n De Empresas",
    "sg:phone":"+34 976 86 76 00",
    "sg:postcode":"50540",
    "sg:province":"Zaragoza",
    "wof:name":"Aser Asesoramiento Integral S.l.",
    "wof:placetype":"venue"
},
  "geometry": {"coordinates":[-1.5330789089,41.8340988159],"type":"Point"}
}