{
  "type": "Feature",
  "properties": {
    "iso:country":"ES",
    "sg:address":"Pl Carme (del), S/n",
    "sg:city":"Valls",
    "sg:orig_category":"Guarder\u00cdas",
    "sg:phone":"+34 977 60 60 01",
    "sg:postcode":"43800",
    "sg:province":"Tarragona",
    "wof:name":"Ajuntament De Valls",
    "wof:placetype":"venue"
},
  "geometry": {"coordinates":[1.2488820553,41.2822685242],"type":"Point"}
}