{
  "type": "Feature",
  "properties": {
    "iso:country":"ES",
    "sg:address":"Avda Virgen De Argeme, 49",
    "sg:city":"Coria",
    "sg:orig_category":"Motocicletas (agentes, Concesionarios)",
    "sg:phone":"+34 927 50 00 11",
    "sg:postcode":"10800",
    "sg:province":"C\u00e1ceres",
    "wof:name":"Donaire Garcia Maria Eugenia",
    "wof:placetype":"venue"
},
  "geometry": {"coordinates":[-6.5433421135,39.9939079285],"type":"Point"}
}