{
  "type": "Feature",
  "properties": {
    "iso:country":"ES",
    "sg:address":"Carrer de Jacint Verdaguer, 36",
    "sg:city":"Molins Rei",
    "sg:orig_category":"Centros Empresariales",
    "sg:phone":"+34 936 80 11 79",
    "sg:postcode":"08750",
    "sg:province":"Barcelona",
    "sg:website":"www.abaigua.com",
    "wof:name":"A D' Aigua 98 S.l.",
    "wof:placetype":"venue"
},
  "geometry": {"coordinates":[2.0570352077,41.368183136],"type":"Point"}
}