{
  "type": "Feature",
  "properties": {
    "iso:country":"ES",
    "sg:address":"Carrer de Sor Maria Torres, 18",
    "sg:city":"Espluga Francoli",
    "sg:orig_category":"Quincaller\u00cda (al Por Menor)",
    "sg:phone":"+34 977 87 02 13",
    "sg:postcode":"43440",
    "sg:province":"Tarragona",
    "wof:name":"Rosello Vendrell Josep Maria",
    "wof:placetype":"venue"
},
  "geometry": {"coordinates":[1.1012949944,41.3959999084],"type":"Point"}
}