{
  "type": "Feature",
  "properties": {
    "addr:full":"Ega\u00d1a Kalea, 2 Zarautz Guip\u00f9zcoa 20800",
    "addr:housenumber":"2",
    "addr:postcode":"20800",
    "addr:street":"Egan\u0303A Kalea;Guipu\u0300Zcoa",
    "iso:country":"ES",
    "sg:address":"Ega\u00d1a Kalea, 2",
    "sg:city":"Zarautz",
    "sg:orig_category":"Tapicer\u00cdas",
    "sg:phone":"+34 943 13 07 36",
    "sg:postcode":"20800",
    "sg:province":"Guip\u00f9zcoa",
    "wof:name":"Silvan Urruzola Pedro Maria",
    "wof:placetype":"venue"
},
  "geometry": {"coordinates":[-2.1749389172,43.2813110352],"type":"Point"}
}