{
  "type": "Feature",
  "properties": {
    "addr:full":"Calle de San Pedro, 22 Plasencia C\u00e1ceres 10600",
    "addr:housenumber":"22",
    "addr:postcode":"10600",
    "addr:street":"Calle De San Pedro;Ca\u0301Ceres",
    "iso:country":"ES",
    "sg:address":"Calle de San Pedro, 22",
    "sg:city":"Plasencia",
    "sg:orig_category":"Ingeniero",
    "sg:phone":"+34 927 42 42 30",
    "sg:postcode":"10600",
    "sg:province":"C\u00e1ceres",
    "wof:name":"Herrera Iglesias Rafael",
    "wof:placetype":"venue"
},
  "geometry": {"coordinates":[-6.086769104,40.0306816101],"type":"Point"}
}