{
  "type": "Feature",
  "properties": {
    "addr:full":"Calle de San Andres, 9 Almoradi Alicante 03160",
    "addr:postcode":"03160",
    "addr:street":"Calle De San Andres 9",
    "iso:country":"ES",
    "sg:address":"Calle de San Andres, 9",
    "sg:city":"Almoradi",
    "sg:classifiers":[
        {
            "category":"Autos & Motor Vehicles",
            "subcategory":"Automobile Sales",
            "type":"Retail Goods"
        }
    ],
    "sg:phone":"+34 966 78 18 44",
    "sg:postcode":"03160",
    "sg:province":"Alicante",
    "wof:name":"Lucas Seva Jose",
    "wof:placetype":"venue"
},
  "geometry": {"coordinates":[-0.7903289795,38.1093902588],"type":"Point"}
}