{
  "type": "Feature",
  "properties": {
    "iso:country":"ES",
    "sg:address":"Avda Burgos, Km. 0119,0",
    "sg:city":"Valladolid",
    "sg:orig_category":"Reciclaje, Desguace De Veh\u00cdculos",
    "sg:phone":"+34 983 33 34 63",
    "sg:postcode":"47009",
    "sg:province":"Valladolid",
    "wof:name":"Vargas Gil Eusebio",
    "wof:placetype":"venue"
},
  "geometry": {"coordinates":[-4.7232642174,41.6766624451],"type":"Point"}
}