{
  "type": "Feature",
  "properties": {
    "addr:full":"Ctra Madrid, 64 Santa Marta De Tormes Salamanca 37900",
    "addr:housenumber":"64",
    "addr:postcode":"37900",
    "addr:street":"Ctra Madrid",
    "iso:country":"ES",
    "sg:address":"Ctra Madrid, 64",
    "sg:city":"Santa Marta De Tormes",
    "sg:orig_category":"Bazares, Art\u00cdculos De Limpieza Y De Cocina (al Por Menor)",
    "sg:phone":"+34 923 20 04 36",
    "sg:postcode":"37900",
    "sg:province":"Salamanca",
    "wof:name":"Chamorro Perez Maria Jose",
    "wof:placetype":"venue"
},
  "geometry": {"coordinates":[-5.628018856,40.950088501],"type":"Point"}
}