{
  "type": "Feature",
  "properties": {
    "iso:country":"ES",
    "sg:address":"Avda Federico Anaya, 62",
    "sg:city":"Salamanca",
    "sg:orig_category":"Plomeros",
    "sg:phone":"+34 923 22 16 62",
    "sg:postcode":"37004",
    "sg:province":"Salamanca",
    "wof:name":"Barrado I\u00f1igo Jesus",
    "wof:placetype":"venue"
},
  "geometry": {"coordinates":[-5.6549339294,40.9757041931],"type":"Point"}
}