{
  "type": "Feature",
  "properties": {
    "iso:country":"ES",
    "sg:address":"Avda Miguel Rodriguez Bautista, 14",
    "sg:city":"Santa Uxia De Ribeira",
    "sg:orig_category":"Muebles, Minoristas",
    "sg:phone":"+34 981 83 57 35",
    "sg:postcode":"15960",
    "sg:province":"La Coru\u00f1a",
    "wof:name":"Complementos R.lago D2",
    "wof:placetype":"venue"
},
  "geometry": {"coordinates":[-8.9946966171,42.5566596985],"type":"Point"}
}