{
  "type": "Feature",
  "properties": {
    "addr:full":"Jose Gonzalez Forte, 2 Puerto Santiago Santa Cruz De Tenerife 38683",
    "addr:housenumber":"2",
    "addr:postcode":"38683",
    "addr:street":"Jose Gonzalez Forte",
    "iso:country":"ES",
    "sg:address":"Jose Gonzalez Forte, 2",
    "sg:city":"Puerto Santiago",
    "sg:orig_category":"Importaci\u00d3n",
    "sg:phone":"+34 922 86 01 16",
    "sg:postcode":"38683",
    "sg:province":"Santa Cruz De Tenerife",
    "wof:name":"Yaryan S.l.",
    "wof:placetype":"venue"
},
  "geometry": {"coordinates":[-16.8146114349,28.2961444855],"type":"Point"}
}