{
  "type": "Feature",
  "properties": {
    "addr:full":"Calle de Payo Gomez, 16 Coru\u00d1a La Coru\u00f1a 15004",
    "addr:housenumber":"16",
    "addr:postcode":"15004",
    "addr:street":"Calle De Payo Gomez;La Corun\u0303A",
    "iso:country":"ES",
    "sg:address":"Calle de Payo Gomez, 16",
    "sg:city":"Coru\u00d1a",
    "sg:orig_category":"Arquitectos",
    "sg:phone":"+34 981 22 73 16",
    "sg:postcode":"15004",
    "sg:province":"La Coru\u00f1a",
    "wof:name":"Medin Guyatt Roberto",
    "wof:placetype":"venue"
},
  "geometry": {"coordinates":[-8.4070949554,43.3672561646],"type":"Point"}
}