{
  "type": "Feature",
  "properties": {
    "addr:full":"Avda Euskadi Etorbidea, 9 Pasaia Guip\u00f9zcoa 20110",
    "addr:housenumber":"9",
    "addr:postcode":"20110",
    "addr:street":"Avda Euskadi Etorbidea;Guipu\u0300Zcoa",
    "iso:country":"ES",
    "sg:address":"Avda Euskadi Etorbidea, 9",
    "sg:city":"Pasaia",
    "sg:orig_category":"Perfumer\u00cda (al Por Menor)",
    "sg:phone":"+34 943 39 03 24",
    "sg:postcode":"20110",
    "sg:province":"Guip\u00f9zcoa",
    "wof:name":"Perfumeria Alvarez, Fernando Alvarez Isasti",
    "wof:placetype":"venue"
},
  "geometry": {"coordinates":[-1.9217879772,43.3260040283],"type":"Point"}
}