{
  "type": "Feature",
  "properties": {
    "iso:country":"ES",
    "sg:address":"Calle de Jeronimo Garcia Prado, 1",
    "sg:city":"Pola De Laviana",
    "sg:orig_category":"Administraci\u00d3n En Agricultura",
    "sg:phone":"+34 985 61 05 24",
    "sg:postcode":"33980",
    "sg:province":"Asturias",
    "wof:name":"Agrotecnia C.b",
    "wof:placetype":"venue"
},
  "geometry": {"coordinates":[-5.5623168945,43.2472991943],"type":"Point"}
}