{
  "type": "Feature",
  "properties": {
    "iso:country":"ES",
    "sg:address":"Calle de Argentina, 38",
    "sg:city":"Arrecife",
    "sg:orig_category":"Imprenta",
    "sg:phone":"+34 928 80 66 40",
    "sg:postcode":"35500",
    "sg:province":"Las Palmas",
    "wof:name":"Barcelo Rotulaciones S.l",
    "wof:placetype":"venue"
},
  "geometry": {"coordinates":[-13.5552854538,28.961769104],"type":"Point"}
}