{
  "type": "Feature",
  "properties": {
    "addr:full":"Estd Coru\u00d1a (da), 117 Lugo Lugo 27003",
    "addr:housenumber":"117",
    "addr:postcode":"27003",
    "iso:country":"ES",
    "sg:address":"Estd Coru\u00d1a (da), 117",
    "sg:city":"Lugo",
    "sg:orig_category":"Servicios De Telecomunicaciones",
    "sg:phone":"+34 982 24 31 38",
    "sg:postcode":"27003",
    "sg:province":"Lugo",
    "sg:website":"www.mampapel.com",
    "wof:name":"Mampatel S.l.",
    "wof:placetype":"venue"
},
  "geometry": {"coordinates":[-7.513894558,43.034614563],"type":"Point"}
}