{
  "type": "Feature",
  "properties": {
    "addr:full":"Carrer de Llevant, 41 Hospitalet Llobregat Barcelona 08905",
    "addr:housenumber":"41",
    "addr:postcode":"08905",
    "addr:street":"Carrer De Llevant",
    "iso:country":"ES",
    "sg:address":"Carrer de Llevant, 41",
    "sg:city":"Hospitalet Llobregat",
    "sg:orig_category":"Alimentaci\u00d3n General (al Por Menor)",
    "sg:phone":"+34 933 33 60 90",
    "sg:postcode":"08905",
    "sg:province":"Barcelona",
    "wof:name":"Tonjar Melendez Maria De Los Milagros",
    "wof:placetype":"venue"
},
  "geometry": {"coordinates":[2.1099131107,41.3733100891],"type":"Point"}
}