{
  "type": "Feature",
  "properties": {
    "iso:country":"ES",
    "sg:address":"Calle de Ntra Sra De Bego\u00d1a, 4",
    "sg:city":"Zaragoza",
    "sg:orig_category":"Peluquer\u00cdas, Peluquer\u00cda Mixta",
    "sg:phone":"+34 976 34 18 07",
    "sg:postcode":"50017",
    "sg:province":"Zaragoza",
    "wof:name":"Berna Lobera Sonia",
    "wof:placetype":"venue"
},
  "geometry": {"coordinates":[-0.9101369977,41.6512374878],"type":"Point"}
}