{
  "type": "Feature",
  "properties": {
    "iso:country":"ES",
    "sg:address":"Ctra Carretera Sant Roc, 9",
    "sg:city":"Hospitalet Llobregat",
    "sg:orig_category":"Maquinaria, Instalaci\u00d3n Y Equipo Para Garajes Y Estaciones De Servicio",
    "sg:phone":"+34 935 11 46 02",
    "sg:postcode":"08907",
    "sg:province":"Barcelona",
    "wof:name":"Isidro Herreiz S.l.",
    "wof:placetype":"venue"
},
  "geometry": {"coordinates":[2.1700499058,41.3857192993],"type":"Point"}
}