{
  "type": "Feature",
  "properties": {
    "addr:full":"Calle de Jose Antonio Primo De Rivera, 6 Valladolid Valladolid 47001",
    "addr:housenumber":"6",
    "addr:postcode":"47001",
    "addr:street":"Calle De Jose Antonio Primo De Rivera",
    "iso:country":"ES",
    "sg:address":"Calle de Jose Antonio Primo De Rivera, 6",
    "sg:city":"Valladolid",
    "sg:orig_category":"Agencias De Viajes",
    "sg:phone":"+34 983 38 00 14",
    "sg:postcode":"47001",
    "sg:province":"Valladolid",
    "wof:name":"Viajes Mundi Boy S. A.",
    "wof:placetype":"venue"
},
  "geometry": {"coordinates":[-4.7300839424,41.6528091431],"type":"Point"}
}