{
  "type": "Feature",
  "properties": {
    "iso:country":"ES",
    "sg:address":"Calle de Real, 13",
    "sg:city":"Rozas De Madrid",
    "sg:orig_category":"Muebles, Minoristas",
    "sg:phone":"+34 916 37 47 14",
    "sg:postcode":"28230",
    "sg:province":"Madrid",
    "sg:website":"www.hipercolchon.net",
    "wof:name":"Rozas Fabriconfort S.l.",
    "wof:placetype":"venue"
},
  "geometry": {"coordinates":[-3.8734710217,40.4925727844],"type":"Point"}
}