{
  "type": "Feature",
  "properties": {
    "addr:full":"J. L. Taboada, 1 Fuentes O\u00f1oro Salamanca 37480",
    "addr:housenumber":"1",
    "addr:postcode":"37480",
    "addr:street":"J.;Taboada",
    "iso:country":"ES",
    "sg:address":"J. L. Taboada, 1",
    "sg:city":"Fuentes O\u00f1oro",
    "sg:orig_category":"Iglesia Cat\u00d3lica",
    "sg:phone":"+34 923 47 30 36",
    "sg:postcode":"37480",
    "sg:province":"Salamanca",
    "wof:name":"Obispado De Ciudad Rodrigo",
    "wof:placetype":"venue"
},
  "geometry": {"coordinates":[-6.8109388351,40.5948791504],"type":"Point"}
}