{
  "type": "Feature",
  "properties": {
    "addr:full":"Calle de Luis Oliver, 15 Marbella M\u00e1laga 29600",
    "addr:housenumber":"15",
    "addr:postcode":"29600",
    "addr:street":"Calle De Luis Oliver;Ma\u0301Laga",
    "iso:country":"ES",
    "sg:address":"Calle de Luis Oliver, 15",
    "sg:city":"Marbella",
    "sg:orig_category":"Promotores Constructores",
    "sg:phone":"+34 952 86 68 64",
    "sg:postcode":"29600",
    "sg:province":"M\u00e1laga",
    "wof:name":"Promotora Distrito Marbella S.l.",
    "wof:placetype":"venue"
},
  "geometry": {"coordinates":[-4.8884019852,36.5088806152],"type":"Point"}
}