{
  "type": "Feature",
  "properties": {
    "iso:country":"ES",
    "sg:address":"Calle de Vi\u00f1a Vieja, 1",
    "sg:orig_category":"Arreglo, Reparaci\u00d3n, Piezas Sueltas De Televisi\u00d3n, V\u00cddeo, Hi",
    "sg:phone":"+34 944 03 09 23",
    "sg:postcode":"01400",
    "sg:province":"\u00c1lava",
    "wof:name":"Pagarbi",
    "wof:placetype":"venue"
},
  "geometry": {"coordinates":[-2.9647090435,43.1417808533],"type":"Point"}
}