{
  "type": "Feature",
  "properties": {
    "iso:country":"ES",
    "sg:address":"Calle de Alcolea, 48",
    "sg:city":"Villafranca Cordoba",
    "sg:orig_category":"Loter\u00cda Y T\u00d3mbola",
    "sg:phone":"+34 957 19 02 86",
    "sg:postcode":"14420",
    "sg:province":"C\u00f3rdoba",
    "wof:name":"Merino Quesada Inmaculada",
    "wof:placetype":"venue"
},
  "geometry": {"coordinates":[-4.5462493896,37.9612922668],"type":"Point"}
}