{
  "type": "Feature",
  "properties": {
    "addr:full":"Calle de Guzman El Bueno, 123 Madrid Madrid 28003",
    "addr:housenumber":"123",
    "addr:postcode":"28003",
    "addr:street":"Calle De Guzman El Bueno",
    "iso:country":"ES",
    "sg:address":"Calle de Guzman El Bueno, 123",
    "sg:city":"Madrid",
    "sg:orig_category":"Tintes (fabricaci\u00d3n, Al Por Mayor)",
    "sg:phone":"+34 915 34 51 05",
    "sg:postcode":"28003",
    "sg:province":"Madrid",
    "wof:name":"Sanchez Diaz Alfonso",
    "wof:placetype":"venue"
},
  "geometry": {"coordinates":[-3.7128019333,40.441822052],"type":"Point"}
}