{
  "type": "Feature",
  "properties": {
    "addr:full":"Calle de Conde De Romanones, 13 Madrid Madrid 28012",
    "addr:housenumber":"13",
    "addr:postcode":"madrid;28012",
    "addr:street":"Calle De Conde De Romanones",
    "iso:country":"ES",
    "sg:address":"Calle de Conde De Romanones, 13",
    "sg:city":"Madrid",
    "sg:orig_category":"Imprenta",
    "sg:phone":"+34 914 29 15 87",
    "sg:postcode":"28012",
    "sg:province":"Madrid",
    "wof:name":"Carmelitas Descalzos Provincia San Juan",
    "wof:placetype":"venue"
},
  "geometry": {"coordinates":[-3.7049744129,40.4128456116],"type":"Point"}
}