{
  "type": "Feature",
  "properties": {
    "iso:country":"ES",
    "sg:address":"Poli Albergueria (la), S/n",
    "sg:city":"Viana",
    "sg:orig_category":"Piedra Natural",
    "sg:phone":"+34 948 44 63 46",
    "sg:postcode":"31230",
    "sg:province":"Navarra",
    "wof:name":"Arquipiedra S.l.",
    "wof:placetype":"venue"
},
  "geometry": {"coordinates":[-2.3616201878,42.5070953369],"type":"Point"}
}