{
  "type": "Feature",
  "properties": {
    "addr:full":"Erguin Kalea, 11 Arrasate Guip\u00f9zcoa 20500",
    "addr:housenumber":"11",
    "addr:postcode":"20500",
    "addr:street":"Erguin Kalea;Guipu\u0300Zcoa",
    "iso:country":"ES",
    "sg:address":"Erguin Kalea, 11",
    "sg:city":"Arrasate",
    "sg:orig_category":"Empresas De Portes Y Mensajer\u00cda",
    "sg:phone":"+34 943 79 97 00",
    "sg:postcode":"20500",
    "sg:province":"Guip\u00f9zcoa",
    "wof:name":"Legemon S.l.",
    "wof:placetype":"venue"
},
  "geometry": {"coordinates":[-2.4983639717,43.0627555847],"type":"Point"}
}