{
  "type": "Feature",
  "properties": {
    "addr:full":"Estda. Ourense-santiago, S/n Cambeo Ourense 32100",
    "addr:housenumber":"s",
    "addr:postcode":"32100",
    "addr:street":"/ N",
    "iso:country":"ES",
    "sg:address":"Estda. Ourense-santiago, S/n",
    "sg:city":"Cambeo",
    "sg:orig_category":"Centros Comerciales Y Grandes Tiendas",
    "sg:phone":"+34 988 20 20 02",
    "sg:postcode":"32100",
    "sg:province":"Ourense",
    "wof:name":"Moure Corti\u00f1as Jose",
    "wof:placetype":"venue"
},
  "geometry": {"coordinates":[-7.852959156,42.3917961121],"type":"Point"}
}