{
  "type": "Feature",
  "properties": {
    "iso:country":"ES",
    "sg:address":"Avda Juan Xxiii, 15",
    "sg:city":"Palmas De Gran Canaria",
    "sg:orig_category":"Seguridad Social",
    "sg:phone":"+34 900 10 35 35",
    "sg:postcode":"35004",
    "sg:province":"Las Palmas",
    "sg:website":"www.seg-social.es",
    "wof:name":"Instituto Nacional De La Seguridad Social",
    "wof:placetype":"venue"
},
  "geometry": {"coordinates":[-15.4254608154,28.1195449829],"type":"Point"}
}