{
  "type": "Feature",
  "properties": {
    "addr:full":"Pg Maragall, 34 Barcelona Barcelona 08041",
    "addr:housenumber":"34",
    "addr:postcode":"08041",
    "addr:street":"Pg Maragall",
    "iso:country":"ES",
    "sg:address":"Pg Maragall, 34",
    "sg:city":"Barcelona",
    "sg:orig_category":"Confecci\u00d3n De Trajes Para Se\u00d1oras",
    "sg:phone":"+34 934 36 54 36",
    "sg:postcode":"08041",
    "sg:province":"Barcelona",
    "wof:name":"Calvi\u00f1o Calvo Delfina Lupita",
    "wof:placetype":"venue"
},
  "geometry": {"coordinates":[2.1808319092,41.4149360657],"type":"Point"}
}