{
  "type": "Feature",
  "properties": {
    "iso:country":"ES",
    "sg:address":"Ctra Nova, 127",
    "sg:city":"Garriga",
    "sg:orig_category":"Impresiones Sobre Tela",
    "sg:phone":"+34 902 18 02 98",
    "sg:postcode":"08530",
    "sg:province":"Barcelona",
    "sg:website":"www.poolack.com",
    "wof:name":"Interpoolack S.l.",
    "wof:placetype":"venue"
},
  "geometry": {"coordinates":[2.2841749191,41.6831016541],"type":"Point"}
}