{
  "type": "Feature",
  "properties": {
    "iso:country":"ES",
    "sg:address":"Carrer de Saiol, 10",
    "sg:city":"Moia",
    "sg:orig_category":"Institutos M\u00c9dicos",
    "sg:phone":"+34 938 20 91 74",
    "sg:postcode":"08180",
    "sg:province":"Barcelona",
    "wof:name":"Instituto Oftalmologico Integral S.l.",
    "wof:placetype":"venue"
},
  "geometry": {"coordinates":[2.0963349342,41.8075218201],"type":"Point"}
}