{
  "type": "Feature",
  "properties": {
    "addr:full":"Ctra Madrid (de), Km. 0379,0 Molina Segura Murcia 30500",
    "addr:postcode":"30500",
    "addr:street":"Ctra Madrid De Km. 0379,0 Molina",
    "iso:country":"ES",
    "sg:address":"Ctra Madrid (de), Km. 0379,0",
    "sg:city":"Molina Segura",
    "sg:orig_category":"Delegados, Agentes De Tr\u00c1nsito, Auxiliares De Transporte Internacional",
    "sg:phone":"+34 968 61 40 10",
    "sg:postcode":"30500",
    "sg:province":"Murcia",
    "wof:name":"Transportes Hernandez Y Hernandez S.l.",
    "wof:placetype":"venue"
},
  "geometry": {"coordinates":[-1.2119740248,38.0535736084],"type":"Point"}
}