{
  "type": "Feature",
  "properties": {
    "addr:full":"Calle de Villaescusa, 10 Madrid Madrid 28017",
    "addr:housenumber":"10",
    "addr:postcode":"madrid;28017",
    "addr:street":"Calle De Villaescusa",
    "iso:country":"ES",
    "sg:address":"Calle de Villaescusa, 10",
    "sg:city":"Madrid",
    "sg:orig_category":"Estudios, Instalaci\u00d3n De Climatizaci\u00d3n",
    "sg:phone":"+34 913 04 42 55",
    "sg:postcode":"28017",
    "sg:province":"Madrid",
    "wof:name":"Instalaciones Openclima S L",
    "wof:placetype":"venue"
},
  "geometry": {"coordinates":[-3.6333079338,40.4215431213],"type":"Point"}
}