{
  "type": "Feature",
  "properties": {
    "addr:full":"Carr Germanies, (de Les), S/n Carlet Valencia 46240",
    "addr:housenumber":"s",
    "addr:postcode":"46240",
    "addr:street":"Carr Germanies De Les;/ N",
    "iso:country":"ES",
    "sg:address":"Carr Germanies, (de Les), S/n",
    "sg:city":"Carlet",
    "sg:orig_category":"Mec\u00c1nico Del Autom\u00d3vil",
    "sg:phone":"+34 962 53 08 71",
    "sg:postcode":"46240",
    "sg:province":"Valencia",
    "wof:name":"Vicente Juan Martinez Lacal Y Manuel Gonzalez Fernandez Cdad",
    "wof:placetype":"venue"
},
  "geometry": {"coordinates":[-0.5146489739,39.2279396057],"type":"Point"}
}