{
  "type": "Feature",
  "properties": {
    "addr:full":"Toribio Etxebarria Kalea, 4 Eibar Guip\u00f9zcoa 20600",
    "addr:housenumber":"4",
    "addr:postcode":"20600",
    "addr:street":"Toribio Etxebarria Kalea;Guipu\u0300Zcoa",
    "iso:country":"ES",
    "sg:address":"Toribio Etxebarria Kalea, 4",
    "sg:city":"Eibar",
    "sg:orig_category":"M\u00c9dicos: Radioterapia (radioterapia Como Opci\u00d3n Oncol\u00d3gica)",
    "sg:phone":"+34 943 20 28 57",
    "sg:postcode":"20600",
    "sg:province":"Guip\u00f9zcoa",
    "wof:name":"Pedro Madina San Martin",
    "wof:placetype":"venue"
},
  "geometry": {"coordinates":[-2.472687006,43.1845474243],"type":"Point"}
}