{
  "type": "Feature",
  "properties": {
    "addr:full":"Carrer de Jaume Ninet, 12 Sabadell Barcelona 08208",
    "addr:housenumber":"12",
    "addr:postcode":"08208",
    "addr:street":"Carrer De Jaume Ninet",
    "iso:country":"ES",
    "sg:address":"Carrer de Jaume Ninet, 12",
    "sg:city":"Sabadell",
    "sg:orig_category":"Reposter\u00cdas",
    "sg:phone":"+34 937 16 15 53",
    "sg:postcode":"08208",
    "sg:province":"Barcelona",
    "wof:name":"Padilla Sanchez Jose Antonio",
    "wof:placetype":"venue"
},
  "geometry": {"coordinates":[2.1070349216,41.5652694702],"type":"Point"}
}