{
  "type": "Feature",
  "properties": {
    "iso:country":"ES",
    "sg:address":"Urkiola Kalea, 6",
    "sg:city":"Legizamon",
    "sg:orig_category":"Cerrajer\u00cda, Ferrallista",
    "sg:phone":"+34 944 16 57 10",
    "sg:postcode":"48450",
    "sg:province":"Vizcaya",
    "wof:name":"Herreria Y Cerrajeria Urdampilleta S.a.",
    "wof:placetype":"venue"
},
  "geometry": {"coordinates":[-2.9009649754,43.2455635071],"type":"Point"}
}