{
  "type": "Feature",
  "properties": {
    "addr:full":"Plaz Minero (el), 3 Fabero Le\u00f3n 24420",
    "addr:postcode":"24420",
    "addr:street":"Leo\u0301N",
    "iso:country":"ES",
    "sg:address":"Plaz Minero (el), 3",
    "sg:city":"Fabero",
    "sg:orig_category":"Electrodom\u00c9sticos (al Por Menor)",
    "sg:phone":"+34 987 55 00 05",
    "sg:postcode":"24420",
    "sg:province":"Le\u00f3n",
    "wof:name":"Cachon Martinez Manuel",
    "wof:placetype":"venue"
},
  "geometry": {"coordinates":[-6.6251740456,42.7678451538],"type":"Point"}
}