{
  "type": "Feature",
  "properties": {
    "addr:full":"Praz Compostela, 4 Santa Uxia De Ribeira La Coru\u00f1a 15960",
    "addr:housenumber":"4",
    "addr:postcode":"15960",
    "addr:street":"Praz Compostela;Corun\u0303A",
    "iso:country":"ES",
    "sg:address":"Praz Compostela, 4",
    "sg:city":"Santa Uxia De Ribeira",
    "sg:orig_category":"Laboratorios Y Trabajos De Fotograf\u00cda, V\u00cddeo Y Cine",
    "sg:phone":"+34 981 87 12 90",
    "sg:postcode":"15960",
    "sg:province":"La Coru\u00f1a",
    "wof:name":"Gonzalez Garcia Manuel",
    "wof:placetype":"venue"
},
  "geometry": {"coordinates":[-8.9963178635,42.583316803],"type":"Point"}
}