{
  "type": "Feature",
  "properties": {
    "addr:full":"Calle de Angel Samblancat, 40 Graus Huesca 22430",
    "addr:housenumber":"40",
    "addr:postcode":"22430",
    "addr:street":"Calle De Angel Samblancat",
    "iso:country":"ES",
    "sg:address":"Calle de Angel Samblancat, 40",
    "sg:city":"Graus",
    "sg:orig_category":"Negocio De Materiales De Construcci\u00d3n",
    "sg:phone":"+34 974 54 07 77",
    "sg:postcode":"22430",
    "sg:province":"Huesca",
    "wof:name":"Espa\u00f1ol Araguas Antonio",
    "wof:placetype":"venue"
},
  "geometry": {"coordinates":[0.3385209143,42.1907997131],"type":"Point"}
}