{
  "type": "Feature",
  "properties": {
    "addr:full":"Par. Duc, 1 Cadaques Girona 17488",
    "addr:housenumber":"1",
    "addr:postcode":"17488",
    "addr:street":"Cadaques Girona",
    "iso:country":"ES",
    "sg:address":"Par. Duc, 1",
    "sg:city":"Cadaques",
    "sg:orig_category":"Librer\u00cdas",
    "sg:phone":"+34 972 25 83 74",
    "sg:postcode":"17488",
    "sg:province":"Girona",
    "wof:name":"Ses Minves S. L.",
    "wof:placetype":"venue"
},
  "geometry": {"coordinates":[3.2777349949,42.2890510559],"type":"Point"}
}