{
  "type": "Feature",
  "properties": {
    "addr:full":"Ctra Bigastro, S/n Correntias Medias Alicante 03300",
    "addr:housenumber":"s / n",
    "addr:postcode":"03300",
    "addr:street":"Ctra Bigastro",
    "iso:country":"ES",
    "sg:address":"Ctra Bigastro, S/n",
    "sg:city":"Correntias Medias",
    "sg:orig_category":"Productos Fitosanitarios (negocio, Aplicaci\u00d3n)",
    "sg:phone":"+34 966 74 01 25",
    "sg:postcode":"03300",
    "sg:province":"Alicante",
    "wof:name":"Agromainsa S.l.",
    "wof:placetype":"venue"
},
  "geometry": {"coordinates":[-0.9218425155,38.0720672607],"type":"Point"}
}