{
  "type": "Feature",
  "properties": {
    "addr:full":"Plaz Campo Santo De Los Martires, 4 Cordoba C\u00f3rdoba 14004",
    "addr:housenumber":"4",
    "addr:postcode":"14004",
    "addr:street":"Los Martires;Co\u0301Rdoba",
    "iso:country":"ES",
    "sg:address":"Plaz Campo Santo De Los Martires, 4",
    "sg:city":"Cordoba",
    "sg:orig_category":"Florister\u00cdas",
    "sg:phone":"+34 957 29 36 89",
    "sg:postcode":"14004",
    "sg:province":"C\u00f3rdoba",
    "wof:name":"Serrano Moreno Jose",
    "wof:placetype":"venue"
},
  "geometry": {"coordinates":[-4.7822051048,37.8777656555],"type":"Point"}
}