{
  "type": "Feature",
  "properties": {
    "addr:full":"Calle de Ca\u00d1ada De Morcillo, S/n Molina Segura Murcia 30500",
    "addr:housenumber":"s",
    "addr:postcode":"30500",
    "addr:street":"Calle De Can\u0303Ada De Morcillo;/ N Molina",
    "iso:country":"ES",
    "sg:address":"Calle de Ca\u00d1ada De Morcillo, S/n",
    "sg:city":"Molina Segura",
    "sg:orig_category":"Papel, Reciclaje",
    "sg:phone":"+34 968 64 32 42",
    "sg:postcode":"30500",
    "sg:province":"Murcia",
    "wof:name":"Perez Andreu Antonio",
    "wof:placetype":"venue"
},
  "geometry": {"coordinates":[-1.2025660276,38.0610771179],"type":"Point"}
}