{
  "type": "Feature",
  "properties": {
    "addr:full":"Calle de Virgen Del Pilar, 4 Alagon Zaragoza 50630",
    "addr:housenumber":"4",
    "addr:postcode":"50630",
    "addr:street":"Calle De Virgen Del Pilar",
    "iso:country":"ES",
    "sg:address":"Calle de Virgen Del Pilar, 4",
    "sg:city":"Alagon",
    "sg:orig_category":"Doctores En Medicina",
    "sg:phone":"+34 976 61 23 19",
    "sg:postcode":"50630",
    "sg:province":"Zaragoza",
    "wof:name":"Romero Rios Maria Pilar",
    "wof:placetype":"venue"
},
  "geometry": {"coordinates":[-1.1150152683,41.765007019],"type":"Point"}
}