{
  "type": "Feature",
  "properties": {
    "addr:full":"Plaz Catedral (de La), S/n Hinojosa Del Duque C\u00f3rdoba 14270",
    "addr:housenumber":"s",
    "addr:postcode":"14270",
    "addr:street":"/ N;Co\u0301Rdoba",
    "iso:country":"ES",
    "sg:address":"Plaz Catedral (de La), S/n",
    "sg:city":"Hinojosa Del Duque",
    "sg:orig_category":"Iglesia Cat\u00d3lica",
    "sg:phone":"+34 957 14 05 74",
    "sg:postcode":"14270",
    "sg:province":"C\u00f3rdoba",
    "wof:name":"Parroquia De San Juan Bautista",
    "wof:placetype":"venue"
},
  "geometry": {"coordinates":[-5.1480998993,38.500705719],"type":"Point"}
}