{
  "type": "Feature",
  "properties": {
    "iso:country":"ES",
    "sg:address":"Calle de Tres De Agosto, 9",
    "sg:city":"Huelva",
    "sg:orig_category":"Ropa Para Se\u00d1oras (al Por Menor)",
    "sg:phone":"+34 959 25 13 01",
    "sg:postcode":"21003",
    "sg:province":"Huelva",
    "wof:name":"Sabeti  Fared",
    "wof:placetype":"venue"
},
  "geometry": {"coordinates":[-6.9504189491,37.2581443787],"type":"Point"}
}