{
  "type": "Feature",
  "properties": {
    "addr:full":"Plaz Tomas Zumalacarregui, 1 Alsasua Navarra 31800",
    "addr:housenumber":"1",
    "addr:postcode":"31800",
    "addr:street":"Plaz;Zumalacarregui",
    "iso:country":"ES",
    "sg:address":"Plaz Tomas Zumalacarregui, 1",
    "sg:city":"Alsasua",
    "sg:orig_category":"Reposter\u00cdas",
    "sg:phone":"+34 948 46 80 26",
    "sg:postcode":"31800",
    "sg:province":"Navarra",
    "wof:name":"Irigoyen Berasain Maria Dolores",
    "wof:placetype":"venue"
},
  "geometry": {"coordinates":[-2.1719760895,42.8943901062],"type":"Point"}
}