{
  "type": "Feature",
  "properties": {
    "addr:full":"Avda Trinidad (la), 26 San Cristobal De La Laguna Santa Cruz De Tenerife 38204",
    "addr:housenumber":"26",
    "addr:postcode":"38204",
    "addr:street":"Avda Trinidad La",
    "iso:country":"ES",
    "sg:address":"Avda Trinidad (la), 26",
    "sg:city":"San Cristobal De La Laguna",
    "sg:orig_category":"Agencias De Viajes",
    "sg:phone":"+34 922 63 32 22",
    "sg:postcode":"38204",
    "sg:province":"Santa Cruz De Tenerife",
    "sg:website":"www.barceloviajes.com",
    "wof:name":"Viajes Barcelo S.l.",
    "wof:placetype":"venue"
},
  "geometry": {"coordinates":[-16.3164653778,28.4863090515],"type":"Point"}
}