{
  "type": "Feature",
  "properties": {
    "addr:full":"Carrer de Higini Angles, 10 Tarragona Tarragona 43001",
    "addr:housenumber":"10",
    "addr:postcode":"43001",
    "addr:street":"Carrer De Higini Angles",
    "iso:country":"ES",
    "sg:address":"Carrer de Higini Angles, 10",
    "sg:city":"Tarragona",
    "sg:orig_category":"Ingenier\u00cda, Centros De Estudios (diversos)",
    "sg:phone":"+34 977 22 18 32",
    "sg:postcode":"43001",
    "sg:province":"Tarragona",
    "wof:name":"Paris Robuste Ramon",
    "wof:placetype":"venue"
},
  "geometry": {"coordinates":[1.2449899912,41.1174926758],"type":"Point"}
}