{
  "type": "Feature",
  "properties": {
    "iso:country":"ES",
    "sg:address":"Av Penedes, 7",
    "sg:city":"Munia",
    "sg:orig_category":"Producci\u00d3n De Huevos",
    "sg:phone":"+34 938 91 80 29",
    "sg:postcode":"08732",
    "sg:province":"Barcelona",
    "wof:name":"Coll S.c.p.",
    "wof:placetype":"venue"
},
  "geometry": {"coordinates":[1.59316504,41.2539710999],"type":"Point"}
}