{
  "type": "Feature",
  "properties": {
    "iso:country":"ES",
    "sg:address":"Ciudadela-ziudadela Kalea, 7",
    "sg:city":"Iru\u00f1a",
    "sg:orig_category":"Estancos",
    "sg:phone":"+34 948 22 21 35",
    "sg:postcode":"31001",
    "sg:province":"Navarra",
    "wof:name":"Garcia Lasheras Mercedes",
    "wof:placetype":"venue"
},
  "geometry": {"coordinates":[-1.6476830244,42.8156890869],"type":"Point"}
}