{
  "type": "Feature",
  "properties": {
    "iso:country":"ES",
    "sg:address":"Calle de Escolania Ni\u00d1os Cantores, S/n",
    "sg:city":"Guadix",
    "sg:orig_category":"Asesor\u00cda Sobre Comunicaci\u00d3n De Empresas",
    "sg:phone":"+34 958 66 90 46",
    "sg:postcode":"18500",
    "sg:province":"Granada",
    "wof:name":"Marcos Cadenas Jose Antonio",
    "wof:placetype":"venue"
},
  "geometry": {"coordinates":[-3.1350591183,37.301361084],"type":"Point"}
}