{
  "type": "Feature",
  "properties": {
    "iso:country":"ES",
    "sg:address":"Carr Sor Isabel De Villena, S/n",
    "sg:city":"Sueca",
    "sg:orig_category":"Promotores Constructores",
    "sg:phone":"+34 961 70 47 94",
    "sg:postcode":"46410",
    "sg:province":"Valencia",
    "wof:name":"Construcciones Rosicor S.l.",
    "wof:placetype":"venue"
},
  "geometry": {"coordinates":[-0.3148190081,39.205619812],"type":"Point"}
}