{
  "type": "Feature",
  "properties": {
    "addr:full":"Calle de Mayor, 5 Sisante Cuenca 16700",
    "addr:housenumber":"5",
    "addr:postcode":"16700",
    "addr:street":"Calle De Mayor",
    "iso:country":"ES",
    "sg:address":"Calle de Mayor, 5",
    "sg:city":"Sisante",
    "sg:orig_category":"Cl\u00cdnicas Dentales",
    "sg:phone":"+34 969 38 76 94",
    "sg:postcode":"16700",
    "sg:province":"Cuenca",
    "wof:name":"Orbident S.l.",
    "wof:placetype":"venue"
},
  "geometry": {"coordinates":[-2.2044479847,39.407585144],"type":"Point"}
}