{
  "type": "Feature",
  "properties": {
    "addr:full":"Carrer de Jovara, 221 Calella Barcelona 08370",
    "addr:housenumber":"221",
    "addr:postcode":"08370",
    "addr:street":"Carrer De Jovara",
    "iso:country":"ES",
    "sg:address":"Carrer de Jovara, 221",
    "sg:city":"Calella",
    "sg:orig_category":"Venta, Instalaci\u00d3n De Calefacci\u00d3n",
    "sg:phone":"+34 937 66 50 41",
    "sg:postcode":"08370",
    "sg:province":"Barcelona",
    "wof:name":"Insta%acions J. Nogueras S.l.",
    "wof:placetype":"venue"
},
  "geometry": {"coordinates":[2.6627790928,41.6142578125],"type":"Point"}
}