{
  "type": "Feature",
  "properties": {
    "iso:country":"ES",
    "sg:address":"Avda Generalisimo, 77",
    "sg:city":"Meira",
    "sg:orig_category":"Agricultura: Abastecimiento Y Cosechado (negocio)",
    "sg:phone":"+34 982 33 04 11",
    "sg:postcode":"27240",
    "sg:province":"Lugo",
    "wof:name":"Comercial Formaran S.l.",
    "wof:placetype":"venue"
},
  "geometry": {"coordinates":[-7.2963337898,43.2133216858],"type":"Point"}
}