{
  "type": "Feature",
  "properties": {
    "iso:country":"ES",
    "sg:address":"Av Antoni Maura, 24",
    "sg:city":"Palma",
    "sg:orig_category":"Ense\u00d1anza, Formaci\u00d3n Profesional: Aprendizaje",
    "sg:phone":"+34 971 42 58 10",
    "sg:postcode":"07012",
    "sg:province":"Islas Baleares",
    "wof:name":"Govern Balear",
    "wof:placetype":"venue"
},
  "geometry": {"coordinates":[2.6457660198,39.567855835],"type":"Point"}
}