{
  "type": "Feature",
  "properties": {
    "addr:full":"Avda Riato (del), S/n Motilla Palancar Cuenca 16200",
    "addr:housenumber":"/ n",
    "addr:postcode":"16200",
    "addr:street":"Avda Riato Del S",
    "iso:country":"ES",
    "sg:address":"Avda Riato (del), S/n",
    "sg:city":"Motilla Palancar",
    "sg:orig_category":"Asilos De Ancianos. Centros Privados",
    "sg:phone":"+34 969 33 16 49",
    "sg:postcode":"16200",
    "sg:province":"Cuenca",
    "wof:name":"Residencia Tercera Edad De Motilla Del Palancar S.l.",
    "wof:placetype":"venue"
},
  "geometry": {"coordinates":[-1.9119440317,39.5613708496],"type":"Point"}
}