{
  "type": "Feature",
  "properties": {
    "addr:full":"Calle de Segura, 49 Fregenal Sierra Badajoz 06340",
    "addr:housenumber":"49",
    "addr:postcode":"06340",
    "addr:street":"Calle De Segura",
    "iso:country":"ES",
    "sg:address":"Calle de Segura, 49",
    "sg:city":"Fregenal Sierra",
    "sg:orig_category":"T\u00c9cnicos Veterinarios",
    "sg:phone":"+34 924 72 01 47",
    "sg:postcode":"06340",
    "sg:province":"Badajoz",
    "wof:name":"Zoyco S.l.",
    "wof:placetype":"venue"
},
  "geometry": {"coordinates":[-6.6502361298,38.1690063477],"type":"Point"}
}