{
  "type": "Feature",
  "properties": {
    "iso:country":"ES",
    "sg:address":"Calle de Lain Calvo, 4",
    "sg:city":"Burgos",
    "sg:orig_category":"Ense\u00d1anza Variada",
    "sg:phone":"+34 947 20 29 17",
    "sg:postcode":"09003",
    "sg:province":"Burgos",
    "sg:website":"www.cidmultimedia.es/centro/",
    "wof:name":"Ruiz Vecino Gregorio",
    "wof:placetype":"venue"
},
  "geometry": {"coordinates":[-3.7019050121,42.3418540955],"type":"Point"}
}