{
  "type": "Feature",
  "properties": {
    "iso:country":"ES",
    "sg:address":"Urb Alamillo El, S/n",
    "sg:city":"Alamillo",
    "sg:orig_category":"Farmacias",
    "sg:phone":"+34 952 41 70 19",
    "sg:postcode":"29130",
    "sg:province":"M\u00e1laga",
    "wof:name":"Cantero Angulo Juan Jose",
    "wof:placetype":"venue"
},
  "geometry": {"coordinates":[-4.5667190552,36.6618614197],"type":"Point"}
}