{
  "type": "Feature",
  "properties": {
    "iso:country":"ES",
    "sg:address":"Calle de Vicente Aleixandre, S/n",
    "sg:city":"Infante Juan Manuel",
    "sg:orig_category":"Asociaciones, Organismos Culturales Y Socioeducativos",
    "sg:phone":"+34 968 25 91 21",
    "sg:postcode":"30011",
    "sg:province":"Murcia",
    "wof:name":"Centro Social De Los Mayores Infante Juan Manuel",
    "wof:placetype":"venue"
},
  "geometry": {"coordinates":[-1.1176290512,37.9794235229],"type":"Point"}
}