{
  "type": "Feature",
  "properties": {
    "iso:country":"ES",
    "sg:address":"Calle de Barcelona, S/n",
    "sg:city":"Coru\u00d1a",
    "sg:orig_category":"Carnicer\u00cdas, Carnicer\u00cdas",
    "sg:phone":"+34 981 26 89 24",
    "sg:postcode":"15010",
    "sg:province":"La Coru\u00f1a",
    "wof:name":"Rodriguez Novo Baldomero",
    "wof:placetype":"venue"
},
  "geometry": {"coordinates":[-8.4212684631,43.362121582],"type":"Point"}
}