{
  "type": "Feature",
  "properties": {
    "addr:full":"Plaz Del Kasko, 4 Sestao Vizcaya 48910",
    "addr:housenumber":"4",
    "addr:postcode":"48910",
    "addr:street":"Plaz;Kasko",
    "iso:country":"ES",
    "sg:address":"Plaz Del Kasko, 4",
    "sg:city":"Sestao",
    "sg:orig_category":"Ense\u00d1anza, Formaci\u00d3n Profesional: Aprendizaje",
    "sg:phone":"+34 944 72 90 00",
    "sg:postcode":"48910",
    "sg:province":"Vizcaya",
    "wof:name":"Ayuntamiento De Sestao",
    "wof:placetype":"venue"
},
  "geometry": {"coordinates":[-3.007666111,43.3094024658],"type":"Point"}
}