{
  "type": "Feature",
  "properties": {
    "addr:full":"Carrer de Sant Feliu, 2 Torello Barcelona 08570",
    "addr:housenumber":"2",
    "addr:postcode":"08570",
    "addr:street":"Carrer De Sant Feliu",
    "iso:country":"ES",
    "sg:address":"Carrer de Sant Feliu, 2",
    "sg:city":"Torello",
    "sg:orig_category":"Cervecer\u00cdas",
    "sg:phone":"+34 938 59 13 58",
    "sg:postcode":"08570",
    "sg:province":"Barcelona",
    "wof:name":"Rodriguez Segura Jose",
    "wof:placetype":"venue"
},
  "geometry": {"coordinates":[2.26273489,42.0465927124],"type":"Point"}
}