{
  "type": "Feature",
  "properties": {
    "iso:country":"ES",
    "sg:address":"Calle de General Elorza, 75",
    "sg:city":"Oviedo",
    "sg:orig_category":"Centros Comerciales Y Grandes Tiendas",
    "sg:phone":"+34 985 10 90 01",
    "sg:postcode":"33...",
    "sg:province":"Asturias",
    "sg:website":"www.elcorteingles.es",
    "wof:name":"El Corte Ingles S.a.",
    "wof:placetype":"venue"
},
  "geometry": {"coordinates":[-5.849178791,43.367023468],"type":"Point"}
}