{
  "type": "Feature",
  "properties": {
    "addr:full":"Ptda Almafra Baixa, 59 Almafra Alicante 03610",
    "addr:housenumber":"59",
    "addr:postcode":"03610",
    "addr:street":"Ptda Almafra Baixa;Alicante",
    "iso:country":"ES",
    "sg:address":"Ptda Almafra Baixa, 59",
    "sg:city":"Almafra",
    "sg:orig_category":"Guarder\u00cdas",
    "sg:phone":"+34 965 37 11 66",
    "sg:postcode":"03610",
    "sg:province":"Alicante",
    "wof:name":"Escuela Infantil Babysol S.%.",
    "wof:placetype":"venue"
},
  "geometry": {"coordinates":[-0.7859489918,38.489315033],"type":"Point"}
}