{
  "type": "Feature",
  "properties": {
    "addr:full":"Calle de Leon Gentico, 13 Arnedo La Rioja 26580",
    "addr:housenumber":"13",
    "addr:postcode":"26580",
    "addr:street":"Calle De Leon Gentico;Rioja",
    "iso:country":"ES",
    "sg:address":"Calle de Leon Gentico, 13",
    "sg:city":"Arnedo",
    "sg:orig_category":"Plomeros",
    "sg:phone":"+34 941 38 31 05",
    "sg:postcode":"26580",
    "sg:province":"La Rioja",
    "wof:name":"Ochoa Royo Jose",
    "wof:placetype":"venue"
},
  "geometry": {"coordinates":[-2.1013391018,42.2252807617],"type":"Point"}
}