{
  "type": "Feature",
  "properties": {
    "iso:country":"ES",
    "sg:address":"Avda Salobre\u00d1a, 5",
    "sg:city":"Motril",
    "sg:orig_category":"Contenedores (mercanc\u00cdas)",
    "sg:phone":"+34 958 60 16 13",
    "sg:postcode":"18600",
    "sg:province":"Granada",
    "wof:name":"Ruiz Garcia Gerardo",
    "wof:placetype":"venue"
},
  "geometry": {"coordinates":[-3.5202879906,36.7434234619],"type":"Point"}
}