{
  "type": "Feature",
  "properties": {
    "addr:full":"Carr Rutlla, 133 Girona Girona 17003",
    "addr:housenumber":"133",
    "addr:postcode":"17003",
    "addr:street":"Carr Rutlla",
    "iso:country":"ES",
    "sg:address":"Carr Rutlla, 133",
    "sg:city":"Girona",
    "sg:orig_category":"Pintura, Barniz, Productos Asimilables (fabricaci\u00d3n, Al Por Mayor)",
    "sg:phone":"+34 972 20 53 72",
    "sg:postcode":"17003",
    "sg:province":"Girona",
    "wof:name":"C. Del B. Insta%a Team S.l.",
    "wof:placetype":"venue"
},
  "geometry": {"coordinates":[2.821805954,41.9721870422],"type":"Point"}
}