{
  "type": "Feature",
  "properties": {
    "iso:country":"ES",
    "sg:address":"Calle de Feria, 152",
    "sg:city":"Sevilla",
    "sg:orig_category":"Fabricaci\u00d3n Y Comercio De M\u00c1quinas",
    "sg:phone":"+34 954 90 64 00",
    "sg:postcode":"41002",
    "sg:province":"Sevilla",
    "wof:name":"Rimonty S.l.",
    "wof:placetype":"venue"
},
  "geometry": {"coordinates":[-5.9916400909,37.4018936157],"type":"Point"}
}