{
  "type": "Feature",
  "properties": {
    "iso:country":"ES",
    "sg:address":"Calle de Marcelino Castillo, 4",
    "sg:city":"Madrid",
    "sg:orig_category":"Estudios, Instalaci\u00d3n De Climatizaci\u00d3n",
    "sg:phone":"+34 914 61 43 14",
    "sg:postcode":"28047",
    "sg:province":"Madrid",
    "wof:name":"Serma 94 S.l.",
    "wof:placetype":"venue"
},
  "geometry": {"coordinates":[-3.7430551052,40.3923797607],"type":"Point"}
}