{
  "type": "Feature",
  "properties": {
    "addr:full":"Calle de Real Vieja, 72 San Sebastian De Los Reyes Madrid 28700",
    "addr:housenumber":"72",
    "addr:postcode":"28700",
    "addr:street":"Calle De Real Vieja",
    "iso:country":"ES",
    "sg:address":"Calle de Real Vieja, 72",
    "sg:city":"San Sebastian De Los Reyes",
    "sg:orig_category":"Supermercados Y Hipermercados",
    "sg:phone":"+34 916 51 41 91",
    "sg:postcode":"28700",
    "sg:province":"Madrid",
    "wof:name":"Futurfam S.l.",
    "wof:placetype":"venue"
},
  "geometry": {"coordinates":[-3.6226849556,40.5486984253],"type":"Point"}
}