{
  "type": "Feature",
  "properties": {
    "iso:country":"ES",
    "sg:address":"Calle de Herradero, 1",
    "sg:city":"Cabanillas Campo",
    "sg:orig_category":"Laboratorios Y Trabajos De Fotograf\u00cda, V\u00cddeo Y Cine",
    "sg:phone":"+34 949 33 79 04",
    "sg:postcode":"19171",
    "sg:province":"Guadalajara",
    "wof:name":"Moratilla Bris Alvaro",
    "wof:placetype":"venue"
},
  "geometry": {"coordinates":[-3.2374420166,40.6377639771],"type":"Point"}
}