{
  "type": "Feature",
  "properties": {
    "iso:country":"ES",
    "sg:address":"Labrador, S/n",
    "sg:city":"Sese\u00f1a",
    "sg:orig_category":"Organizaciones Profesionales",
    "sg:phone":"+34 918 95 74 96",
    "sg:postcode":"45223",
    "sg:province":"Toledo",
    "sg:website":"www.marmolcompac.com",
    "wof:name":"Marmol Compac S. A.",
    "wof:placetype":"venue"
},
  "geometry": {"coordinates":[-3.6764581203,40.1057472229],"type":"Point"}
}