{
  "type": "Feature",
  "properties": {
    "addr:full":"Carnicerias, 1 Montealegre Castillo Albacete 02650",
    "addr:housenumber":"1",
    "addr:postcode":"02650",
    "addr:street":"Carnicerias",
    "iso:country":"ES",
    "sg:address":"Carnicerias, 1",
    "sg:city":"Montealegre Castillo",
    "sg:orig_category":"Radiocomunicaciones, Telefon\u00cda M\u00d3vil, Radiomensajer\u00cda: Servicios, Comercializaci\u00d3n",
    "sg:phone":"+34 967 33 65 00",
    "sg:postcode":"02650",
    "sg:province":"Albacete",
    "wof:name":"Rios Saritama Jose Isael",
    "wof:placetype":"venue"
},
  "geometry": {"coordinates":[-1.3244249821,38.787021637],"type":"Point"}
}