{
  "type": "Feature",
  "properties": {
    "iso:country":"ES",
    "sg:address":"Calle de Pea\u00d1a, 19",
    "sg:city":"Valencia",
    "sg:orig_category":"Fabricaci\u00d3n De Enlosados, Soler\u00cdas",
    "sg:phone":"+34 963 30 85 17",
    "sg:postcode":"46022",
    "sg:province":"Valencia",
    "wof:name":"Azulejos Puche S.l.",
    "wof:placetype":"venue"
},
  "geometry": {"coordinates":[-0.3387624025,39.4636116028],"type":"Point"}
}