{
  "type": "Feature",
  "properties": {
    "addr:full":"Calle de Labayo, S/n San Vitero Zamora 49523",
    "addr:housenumber":"s / n",
    "addr:postcode":"49523",
    "addr:street":"Calle De Labayo",
    "iso:country":"ES",
    "sg:address":"Calle de Labayo, S/n",
    "sg:city":"San Vitero",
    "sg:orig_category":"Molduras, Junquillos, Listones Y Molduras Perforadas",
    "sg:phone":"+34 980 68 14 10",
    "sg:postcode":"49523",
    "sg:province":"Zamora",
    "wof:name":"Lopez Esteban Santiago",
    "wof:placetype":"venue"
},
  "geometry": {"coordinates":[-6.3490524292,41.7744178772],"type":"Point"}
}