{
  "type": "Feature",
  "properties": {
    "iso:country":"ES",
    "sg:address":"Carr Ramon Basil, 8",
    "sg:city":"Figueres",
    "sg:orig_category":"Peluquer\u00cdas, Peluquer\u00cda Mixta",
    "sg:phone":"+34 972 67 40 96",
    "sg:postcode":"17600",
    "sg:province":"Girona",
    "wof:name":"Nova Imatge S.cv.",
    "wof:placetype":"venue"
},
  "geometry": {"coordinates":[2.9661300182,42.2706985474],"type":"Point"}
}