{
  "type": "Feature",
  "properties": {
    "addr:full":"Calle de Plazuela, 23 Sorihuela Salamanca 37777",
    "addr:housenumber":"23",
    "addr:postcode":"37777",
    "addr:street":"Calle De Plazuela",
    "iso:country":"ES",
    "sg:address":"Calle de Plazuela, 23",
    "sg:city":"Sorihuela",
    "sg:orig_category":"Iglesia Cat\u00d3lica",
    "sg:phone":"+34 923 41 36 82",
    "sg:postcode":"37777",
    "sg:province":"Salamanca",
    "wof:name":"Parroquia Nuestra Se\u00f1ora De La Asuncion",
    "wof:placetype":"venue"
},
  "geometry": {"coordinates":[-5.6763410568,40.4428901672],"type":"Point"}
}