{
  "type": "Feature",
  "properties": {
    "iso:country":"ES",
    "sg:address":"Rua Oliva (la), 16",
    "sg:city":"Pontevedra",
    "sg:orig_category":"Inmobiliaria (agencias)",
    "sg:phone":"+34 986 86 17 08",
    "sg:postcode":"36001",
    "sg:province":"Pontevedra",
    "wof:name":"Vidal Vidal Fermin",
    "wof:placetype":"venue"
},
  "geometry": {"coordinates":[-8.6448583603,42.4302520752],"type":"Point"}
}