{
  "type": "Feature",
  "properties": {
    "addr:full":"Calle de Aurora, 1 Castellar-oliveral Valencia 46026",
    "addr:housenumber":"1",
    "addr:postcode":"46026",
    "addr:street":"Calle De Aurora",
    "iso:country":"ES",
    "sg:address":"Calle de Aurora, 1",
    "sg:city":"Castellar-oliveral",
    "sg:orig_category":"Cervecer\u00cdas",
    "sg:phone":"+34 963 96 23 77",
    "sg:postcode":"46026",
    "sg:province":"Valencia",
    "wof:name":"Sistelcom-telemensaje S.a.",
    "wof:placetype":"venue"
},
  "geometry": {"coordinates":[-0.3640919924,39.4301643372],"type":"Point"}
}