{
  "type": "Feature",
  "properties": {
    "iso:country":"ES",
    "sg:address":"Plaz San Anacleto, 2",
    "sg:city":"Madrid",
    "sg:orig_category":"Inform\u00c1tica (estudios, Servicios, Asesor\u00cda, Formaci\u00d3n)",
    "sg:phone":"+34 913 07 03 03",
    "sg:postcode":"28023",
    "sg:province":"Madrid",
    "sg:website":"www.madrilan.es",
    "wof:name":"Alra Hispania S.l.",
    "wof:placetype":"venue"
},
  "geometry": {"coordinates":[-3.7825942039,40.4581375122],"type":"Point"}
}