{
  "type": "Feature",
  "properties": {
    "iso:country":"ES",
    "sg:address":"Calle de Angel Ganivet, 1",
    "sg:city":"Olula Rio",
    "sg:orig_category":"Inmobiliaria (agencias)",
    "sg:phone":"+34 950 44 01 22",
    "sg:postcode":"04860",
    "sg:province":"Almer\u00eda",
    "wof:name":"Tecnisan Olula S.l.",
    "wof:placetype":"venue"
},
  "geometry": {"coordinates":[-2.2981979847,37.3564872742],"type":"Point"}
}