{
  "type": "Feature",
  "properties": {
    "addr:full":"Calle de Kareaga Goikoa, 22 Arizgoiti Vizcaya 48970",
    "addr:housenumber":"22",
    "addr:postcode":"48970",
    "addr:street":"Calle De Kareaga Goikoa",
    "iso:country":"ES",
    "sg:address":"Calle de Kareaga Goikoa, 22",
    "sg:city":"Arizgoiti",
    "sg:orig_category":"Zapatos (al Por Menor)",
    "sg:phone":"+34 944 40 75 18",
    "sg:postcode":"48970",
    "sg:province":"Vizcaya",
    "wof:name":"Motila Lopez Yolanda",
    "wof:placetype":"venue"
},
  "geometry": {"coordinates":[-2.8951845169,43.2380027771],"type":"Point"}
}