{
  "type": "Feature",
  "properties": {
    "addr:full":"Calle de Lehendakari Agirre, 1 Intzuntza Vizcaya 48330",
    "addr:housenumber":"1",
    "addr:postcode":"48330",
    "addr:street":"Calle De Lehendakari Agirre",
    "iso:country":"ES",
    "sg:address":"Calle de Lehendakari Agirre, 1",
    "sg:city":"Intzuntza",
    "sg:orig_category":"Empresas De Portes Y Mensajer\u00cda",
    "sg:phone":"+34 946 31 36 34",
    "sg:postcode":"48330",
    "sg:province":"Vizcaya",
    "wof:name":"Legemon S.l.",
    "wof:placetype":"venue"
},
  "geometry": {"coordinates":[-2.7691090107,43.2078361511],"type":"Point"}
}