{
  "type": "Feature",
  "properties": {
    "iso:country":"ES",
    "sg:address":"Calle de Miguel Hernandez, 11",
    "sg:city":"Valdemoro",
    "sg:classifiers":[
        {
            "category":"Autos & Motor Vehicles",
            "subcategory":"Automobile Sales",
            "type":"Retail Goods"
        }
    ],
    "sg:phone":"+34 918 95 55 89",
    "sg:postcode":"28340",
    "sg:province":"Madrid",
    "wof:name":"Hernandez Rodriguez Jose Alvaro",
    "wof:placetype":"venue"
},
  "geometry": {"coordinates":[-3.6847960949,40.1932296753],"type":"Point"}
}