{
  "type": "Feature",
  "properties": {
    "addr:full":"Calle de Le\u00d1adores, S/n Barrio De La Vega Granada 18193",
    "addr:housenumber":"s / n",
    "addr:postcode":"18193",
    "addr:street":"Calle De Len\u0303Adores",
    "iso:country":"ES",
    "sg:address":"Calle de Le\u00d1adores, S/n",
    "sg:city":"Barrio De La Vega",
    "sg:classifiers":[
        {
            "category":"Taxi",
            "type":"Transportation"
        }
    ],
    "sg:phone":"+34 958 30 14 88",
    "sg:postcode":"18193",
    "sg:province":"Granada",
    "wof:name":"Marquez Rejon Antonio",
    "wof:placetype":"venue"
},
  "geometry": {"coordinates":[-3.5652940273,37.1288452148],"type":"Point"}
}