{
  "type": "Feature",
  "properties": {
    "addr:full":"Calle de Virgen De Guadalupe, 1 Montanchez C\u00e1ceres 10170",
    "addr:housenumber":"1",
    "addr:postcode":"10170",
    "addr:street":"Calle De Virgen De Guadalupe;Ca\u0301Ceres",
    "iso:country":"ES",
    "sg:address":"Calle de Virgen De Guadalupe, 1",
    "sg:city":"Montanchez",
    "sg:orig_category":"Autob\u00das (explotaci\u00d3n Y Servicios De)",
    "sg:phone":"+34 927 38 00 70",
    "sg:postcode":"10170",
    "sg:province":"C\u00e1ceres",
    "wof:name":"Autocares Solis S.a.",
    "wof:placetype":"venue"
},
  "geometry": {"coordinates":[-6.1497979164,39.2252998352],"type":"Point"}
}