{
  "type": "Feature",
  "properties": {
    "addr:full":"San Franzisko Kalea, 18 Elgoibar Guip\u00f9zcoa 20870",
    "addr:housenumber":"18",
    "addr:postcode":"20870",
    "addr:street":"San Franzisko Kalea;Guipu\u0300Zcoa",
    "iso:country":"ES",
    "sg:address":"San Franzisko Kalea, 18",
    "sg:city":"Elgoibar",
    "sg:orig_category":"Fabricaci\u00d3n, Venta De Productos Base Farmac\u00c9uticos",
    "sg:phone":"+34 943 74 12 93",
    "sg:postcode":"20870",
    "sg:province":"Guip\u00f9zcoa",
    "wof:name":"Yudego Zuazubizcar Elena",
    "wof:placetype":"venue"
},
  "geometry": {"coordinates":[-2.414355278,43.2155151367],"type":"Point"}
}