{
  "type": "Feature",
  "properties": {
    "iso:country":"ES",
    "sg:address":"Pl Santa Clara, S/n",
    "sg:city":"Vic",
    "sg:orig_category":"Aparcamientos (infraestructuras, Accesorios)",
    "sg:phone":"+34 938 89 28 37",
    "sg:postcode":"08500",
    "sg:province":"Barcelona",
    "wof:name":"Xarxa Comercial De Vic S.a.",
    "wof:placetype":"venue"
},
  "geometry": {"coordinates":[2.2554929256,41.9310264587],"type":"Point"}
}