{
  "type": "Feature",
  "properties": {
    "addr:full":"Calle de Real, 88 S. Fernando C\u00e1diz 11100",
    "addr:housenumber":"88",
    "addr:postcode":"11100",
    "addr:street":"Calle De Real;S. Fernando Ca\u0301Diz",
    "iso:country":"ES",
    "sg:address":"Calle de Real, 88",
    "sg:city":"S. Fernando",
    "sg:orig_category":"Florister\u00cdas",
    "sg:phone":"+34 956 59 40 81",
    "sg:postcode":"11100",
    "sg:province":"C\u00e1diz",
    "wof:name":"Martinez Martinez Ana Maria",
    "wof:placetype":"venue"
},
  "geometry": {"coordinates":[-6.1974020004,36.4649085999],"type":"Point"}
}