{
  "type": "Feature",
  "properties": {
    "addr:full":"Avda Constitucion (de La), 46 Mostoles Madrid 28931",
    "addr:housenumber":"46",
    "addr:postcode":"28931",
    "addr:street":"Avda Constitucion De La",
    "iso:country":"ES",
    "sg:address":"Avda Constitucion (de La), 46",
    "sg:city":"Mostoles",
    "sg:orig_category":"Fabricaci\u00d3n De Productos Textiles Sin Tejer",
    "sg:phone":"+34 916 13 84 51",
    "sg:postcode":"28931",
    "sg:province":"Madrid",
    "wof:name":"Galeria Lisboa S.l.",
    "wof:placetype":"venue"
},
  "geometry": {"coordinates":[-3.86226511,40.3254623413],"type":"Point"}
}