{
  "type": "Feature",
  "properties": {
    "addr:full":"Praz Eduardo Barreiros, 6 Ourense Ourense 32003",
    "addr:housenumber":"6",
    "addr:postcode":"32003",
    "addr:street":"Praz Eduardo Barreiros",
    "iso:country":"ES",
    "sg:address":"Praz Eduardo Barreiros, 6",
    "sg:city":"Ourense",
    "sg:orig_category":"Mutuas De Seguros",
    "sg:phone":"+34 988 51 12 01",
    "sg:postcode":"32003",
    "sg:province":"Ourense",
    "sg:website":"www.ibermutuamur.es",
    "wof:name":"Ibermutuamur",
    "wof:placetype":"venue"
},
  "geometry": {"coordinates":[-7.8661170006,42.3389396667],"type":"Point"}
}