{
  "type": "Feature",
  "properties": {
    "iso:country":"ES",
    "sg:address":"Calle de Vazquez Lopez, 42",
    "sg:city":"Huelva",
    "sg:orig_category":"Carnicer\u00cdas, Carnicer\u00cdas",
    "sg:phone":"+34 959 28 51 39",
    "sg:postcode":"21001",
    "sg:province":"Huelva",
    "wof:name":"Jamones Suarez Jabugo S.l.",
    "wof:placetype":"venue"
},
  "geometry": {"coordinates":[-6.952545166,37.2547645569],"type":"Point"}
}