{
  "type": "Feature",
  "properties": {
    "addr:full":"Ctra N-seiscientos Treinta(p I Casar De Caceres), Km. 0541,0 Casar Caceres C\u00e1ceres 10190",
    "addr:postcode":"10190",
    "addr:street":"Ctra N-Seiscientos Treinta;I;Caceres Km. 0541,0;Ca\u0301Ceres",
    "iso:country":"ES",
    "sg:address":"Ctra N-seiscientos Treinta(p I Casar De Caceres), Km. 0541,0",
    "sg:city":"Casar Caceres",
    "sg:orig_category":"Chapister\u00cda",
    "sg:phone":"+34 927 29 15 83",
    "sg:postcode":"10190",
    "sg:province":"C\u00e1ceres",
    "wof:name":"Gutierrez Rey Marcelino",
    "wof:placetype":"venue"
},
  "geometry": {"coordinates":[-6.4156990051,39.5572166443],"type":"Point"}
}