{
  "type": "Feature",
  "properties": {
    "iso:country":"ES",
    "sg:address":"Carr Jose Vidal Canet, De, 9",
    "sg:city":"Carcaixent",
    "sg:orig_category":"Centros De Reservas Hoteleras",
    "sg:phone":"+34 962 43 48 68",
    "sg:postcode":"46740",
    "sg:province":"Valencia",
    "wof:name":"Estrada Juan Juan Jose",
    "wof:placetype":"venue"
},
  "geometry": {"coordinates":[-0.4492819905,39.1248283386],"type":"Point"}
}