{
  "type": "Feature",
  "properties": {
    "addr:full":"Calle de Alcion, 24 Madrid Madrid 28019",
    "addr:housenumber":"24",
    "addr:postcode":"madrid;28019",
    "addr:street":"Calle De Alcion",
    "iso:country":"ES",
    "sg:address":"Calle de Alcion, 24",
    "sg:city":"Madrid",
    "sg:orig_category":"Molduras, Junquillos, Listones Y Molduras Perforadas",
    "sg:phone":"+34 914 72 59 24",
    "sg:postcode":"28019",
    "sg:province":"Madrid",
    "wof:name":"Recio Guijarro Pablo",
    "wof:placetype":"venue"
},
  "geometry": {"coordinates":[-3.735023737,40.3948059082],"type":"Point"}
}