{
  "type": "Feature",
  "properties": {
    "addr:full":"Marban(seijas), S/n Marban A Coru\u00f1a 15565",
    "addr:housenumber":"s",
    "addr:postcode":"15565",
    "addr:street":"/ N;Corun\u0303A",
    "iso:country":"ES",
    "sg:address":"Marban(seijas), S/n",
    "sg:city":"Marban",
    "sg:orig_category":"Reciclaje Y Tratamiento De Desechos Varios",
    "sg:phone":"+34 981 41 72 10",
    "sg:postcode":"15565",
    "sg:province":"A Coru\u00f1a",
    "wof:name":"Xiloga S.l.",
    "wof:placetype":"venue"
},
  "geometry": {"coordinates":[-7.8883252144,43.5476303101],"type":"Point"}
}