{
  "type": "Feature",
  "properties": {
    "iso:country":"ES",
    "sg:address":"Calle de Doctor Larrad, 26",
    "sg:city":"Castejon",
    "sg:orig_category":"Textil",
    "sg:phone":"+34 948 77 00 56",
    "sg:postcode":"31590",
    "sg:province":"Navarra",
    "wof:name":"Ebrotoldo S.l.",
    "wof:placetype":"venue"
},
  "geometry": {"coordinates":[-1.6878894567,42.1669273376],"type":"Point"}
}