{
  "type": "Feature",
  "properties": {
    "iso:country":"ES",
    "sg:address":"Calle de Mayor, 34",
    "sg:city":"Molina Segura",
    "sg:orig_category":"Estancos",
    "sg:phone":"+34 968 61 18 35",
    "sg:postcode":"30500",
    "sg:province":"Murcia",
    "wof:name":"Sandoval Vicente Antonia",
    "wof:placetype":"venue"
},
  "geometry": {"coordinates":[-1.2113419771,38.0521087646],"type":"Point"}
}