{
  "type": "Feature",
  "properties": {
    "addr:full":"Comarca De L'horta, 12 Aldaia Valencia 46960",
    "addr:housenumber":"12",
    "addr:postcode":"46960",
    "iso:country":"ES",
    "sg:address":"Comarca De L'horta, 12",
    "sg:city":"Aldaia",
    "sg:orig_category":"Productos Qu\u00cdmicos (fabricaci\u00d3n, Al Por Mayor)",
    "sg:phone":"+34 961 51 35 41",
    "sg:postcode":"46960",
    "sg:province":"Valencia",
    "wof:name":"Lumaser Cooperativa Valenciana",
    "wof:placetype":"venue"
},
  "geometry": {"coordinates":[-0.485751003,39.458896637],"type":"Point"}
}