{
  "type": "Feature",
  "properties": {
    "addr:full":"Avda Retamas (las), 10 Alcorcon Madrid 28922",
    "addr:housenumber":"10",
    "addr:postcode":"28922",
    "addr:street":"Avda Retamas Las",
    "iso:country":"ES",
    "sg:address":"Avda Retamas (las), 10",
    "sg:city":"Alcorcon",
    "sg:orig_category":"Electrodom\u00c9sticos (al Por Menor)",
    "sg:phone":"+34 916 43 27 50",
    "sg:postcode":"28922",
    "sg:province":"Madrid",
    "wof:name":"Gil Pescador Valentin",
    "wof:placetype":"venue"
},
  "geometry": {"coordinates":[-3.8364551067,40.3391036987],"type":"Point"}
}