{
  "type": "Feature",
  "properties": {
    "iso:country":"ES",
    "sg:address":"Calle de Luis De Ardila, 5",
    "sg:city":"S. Fernando",
    "sg:orig_category":"Comercio, Reparaci\u00d3n De Motocicletas, Bicicletas Y Piezas Sueltas",
    "sg:phone":"+34 956 59 13 05",
    "sg:postcode":"11100",
    "sg:province":"C\u00e1diz",
    "wof:name":"Garcia Lopez Salvador Marcelino",
    "wof:placetype":"venue"
},
  "geometry": {"coordinates":[-6.1961669922,36.4739151001],"type":"Point"}
}