{
  "type": "Feature",
  "properties": {
    "addr:full":"Pase Delicias, 50 Madrid Madrid 28045",
    "addr:housenumber":"50",
    "addr:postcode":"madrid;28045",
    "addr:street":"Delicias",
    "iso:country":"ES",
    "sg:address":"Pase Delicias, 50",
    "sg:city":"Madrid",
    "sg:orig_category":"Fotocopias, Reprograf\u00cda",
    "sg:phone":"+34 915 27 07 68",
    "sg:postcode":"28045",
    "sg:province":"Madrid",
    "wof:name":"Galan Lorente Maria Luisa",
    "wof:placetype":"venue"
},
  "geometry": {"coordinates":[-3.6940379143,40.4007148743],"type":"Point"}
}