{
  "type": "Feature",
  "properties": {
    "iso:country":"ES",
    "sg:address":"Pase Sixto Celorrio, 27",
    "sg:city":"Calatayud",
    "sg:orig_category":"Inmobiliaria (agencias)",
    "sg:phone":"+34 976 89 13 25",
    "sg:postcode":"50300",
    "sg:province":"Zaragoza",
    "wof:name":"Fincas Moscatel S.l",
    "wof:placetype":"venue"
},
  "geometry": {"coordinates":[-1.6428580284,41.3498535156],"type":"Point"}
}