{
  "type": "Feature",
  "properties": {
    "addr:full":"G.v. Marques Del Turia, 19 Valencia Valencia 46005",
    "addr:housenumber":"19",
    "addr:postcode":"46005",
    "addr:street":"Turia",
    "iso:country":"ES",
    "sg:address":"G.v. Marques Del Turia, 19",
    "sg:city":"Valencia",
    "sg:orig_category":"Aguas (distribuci\u00d3n, Servicios)",
    "sg:phone":"+34 963 51 21 14",
    "sg:postcode":"46005",
    "sg:province":"Valencia",
    "wof:name":"Empresa Mixta Valenciana De Aguas S.a.",
    "wof:placetype":"venue"
},
  "geometry": {"coordinates":[-0.372559011,39.4656715393],"type":"Point"}
}