{
  "type": "Feature",
  "properties": {
    "iso:country":"ES",
    "sg:address":"Plaz Hermenegildo Terrados (de), 2",
    "sg:city":"Jaen",
    "sg:orig_category":"Guarder\u00cdas",
    "sg:phone":"+34 953 27 52 48",
    "sg:postcode":"23008",
    "sg:province":"Ja\u00e9n",
    "wof:name":"Vazquez Flores Mariano",
    "wof:placetype":"venue"
},
  "geometry": {"coordinates":[-3.7906870842,37.7650947571],"type":"Point"}
}