{
  "type": "Feature",
  "properties": {
    "addr:full":"Avda Sanlucar (de), 13 Puerto De Santa Maria C\u00e1diz 11500",
    "addr:housenumber":"13",
    "addr:postcode":"11500",
    "addr:street":"Avda Sanlucar De;Ca\u0301Diz",
    "iso:country":"ES",
    "sg:address":"Avda Sanlucar (de), 13",
    "sg:city":"Puerto De Santa Maria",
    "sg:orig_category":"Comercio, Reparaci\u00d3n De Motocicletas, Bicicletas Y Piezas Sueltas",
    "sg:phone":"+34 956 87 76 77",
    "sg:postcode":"11500",
    "sg:province":"C\u00e1diz",
    "wof:name":"Moto Hobby Gra\u00f1a S.l.",
    "wof:placetype":"venue"
},
  "geometry": {"coordinates":[-6.2252907753,36.6046028137],"type":"Point"}
}