{
  "type": "Feature",
  "properties": {
    "iso:country":"ES",
    "sg:address":"Calle de Caceres, 5",
    "sg:city":"Alcorcon",
    "sg:orig_category":"Molduras, Junquillos, Listones Y Molduras Perforadas",
    "sg:phone":"+34 916 11 91 10",
    "sg:postcode":"28921",
    "sg:province":"Madrid",
    "wof:name":"Del Moral Perez Mariano",
    "wof:placetype":"venue"
},
  "geometry": {"coordinates":[-3.8322765827,40.3479995728],"type":"Point"}
}