{
  "type": "Feature",
  "properties": {
    "addr:full":"Calle de Tomares, 32 Camas Sevilla 41900",
    "addr:housenumber":"32",
    "addr:postcode":"41900",
    "addr:street":"Calle De Tomares",
    "iso:country":"ES",
    "sg:address":"Calle de Tomares, 32",
    "sg:city":"Camas",
    "sg:orig_category":"Artes Gr\u00c1ficas, Artes Pl\u00c1sticas: Material Y Suministros (al Por Menor)",
    "sg:phone":"+34 955 98 03 92",
    "sg:postcode":"41900",
    "sg:province":"Sevilla",
    "wof:name":"International Supplies Professional S.l.a.",
    "wof:placetype":"venue"
},
  "geometry": {"coordinates":[-6.0315561295,37.3850402832],"type":"Point"}
}