{
  "type": "Feature",
  "properties": {
    "addr:full":"Plaz Verin, 17 Madrid Madrid 28029",
    "addr:housenumber":"17",
    "addr:postcode":"madrid;28029",
    "addr:street":"Plaz Verin",
    "iso:country":"ES",
    "sg:address":"Plaz Verin, 17",
    "sg:city":"Madrid",
    "sg:orig_category":"Reposter\u00cdas",
    "sg:phone":"+34 917 30 83 69",
    "sg:postcode":"28029",
    "sg:province":"Madrid",
    "wof:name":"Hijos De Jose Rodriguez Chimeno S. A.",
    "wof:placetype":"venue"
},
  "geometry": {"coordinates":[-3.7094697952,40.4780807495],"type":"Point"}
}