{
  "type": "Feature",
  "properties": {
    "iso:country":"ES",
    "sg:address":"Ctra. Nal. C. Cinquanta Dos, S/n",
    "sg:city":"Puigcerda",
    "sg:orig_category":"Empresas De Carpinter\u00cda",
    "sg:phone":"+34 972 88 33 04",
    "sg:postcode":"17520",
    "sg:province":"Girona",
    "sg:website":"www.fudesa.com",
    "wof:name":"Fudesa Cerdanya S.l.",
    "wof:placetype":"venue"
},
  "geometry": {"coordinates":[1.9278999567,42.4336547852],"type":"Point"}
}