{
  "type": "Feature",
  "properties": {
    "iso:country":"ES",
    "sg:address":"Trav Corts, 174",
    "sg:city":"Barcelona",
    "sg:orig_category":"T\u00c9cnicos Veterinarios",
    "sg:phone":"+34 933 30 94 18",
    "sg:postcode":"08028",
    "sg:province":"Barcelona",
    "wof:name":"Crostan S.l.",
    "wof:placetype":"venue"
},
  "geometry": {"coordinates":[2.1280419827,41.3822784424],"type":"Point"}
}