{
  "type": "Feature",
  "properties": {
    "iso:country":"ES",
    "sg:address":"Calle de Baviera, S/n",
    "sg:city":"Carolina",
    "sg:orig_category":"Marroquiner\u00cda (confecci\u00d3n)",
    "sg:phone":"+34 953 68 14 44",
    "sg:postcode":"23200",
    "sg:province":"Ja\u00e9n",
    "wof:name":"Lingio Piel",
    "wof:placetype":"venue"
},
  "geometry": {"coordinates":[-3.6067624092,38.2814712524],"type":"Point"}
}