{
  "type": "Feature",
  "properties": {
    "addr:full":"Carrer de Watt, 1 Barbera Valles Barcelona 08210",
    "addr:housenumber":"1",
    "addr:postcode":"08210",
    "addr:street":"Carrer De Watt",
    "iso:country":"ES",
    "sg:address":"Carrer de Watt, 1",
    "sg:city":"Barbera Valles",
    "sg:orig_category":"Productos Qu\u00cdmicos (fabricaci\u00d3n, Al Por Mayor)",
    "sg:phone":"+34 937 19 15 59",
    "sg:postcode":"08210",
    "sg:province":"Barcelona",
    "wof:name":"Cisternas Del Valles S.a.",
    "wof:placetype":"venue"
},
  "geometry": {"coordinates":[2.1313989162,41.5153388977],"type":"Point"}
}