{
  "type": "Feature",
  "properties": {
    "addr:full":"Calle de Alcazar De Toledo, 5 Le\u00f3n Le\u00f3n 24001",
    "addr:housenumber":"5",
    "addr:postcode":"24001",
    "addr:street":"Calle De Alcazar De Toledo;Leo\u0301N",
    "iso:country":"ES",
    "sg:address":"Calle de Alcazar De Toledo, 5",
    "sg:city":"Le\u00f3n",
    "sg:orig_category":"Ropa Para Se\u00d1oras Y Caballeros (al Por Menor)",
    "sg:phone":"+34 987 22 55 15",
    "sg:postcode":"24001",
    "sg:province":"Le\u00f3n",
    "wof:name":"Grupo Massimo Dutti S.a.",
    "wof:placetype":"venue"
},
  "geometry": {"coordinates":[-5.5755405426,42.5978507996],"type":"Point"}
}