{
  "type": "Feature",
  "properties": {
    "iso:country":"ES",
    "sg:address":"Calle de Triunfo, 2",
    "sg:city":"Donostia-san Sebastian",
    "sg:orig_category":"Alquiler De Veh\u00cdculos: Turismos Y Utilitarios",
    "sg:phone":"+34 943 46 15 27",
    "sg:postcode":"20007",
    "sg:province":"Guip\u00f9zcoa",
    "wof:name":"Avis Alquile Un Coche S.a.",
    "wof:placetype":"venue"
},
  "geometry": {"coordinates":[-1.9855309725,43.316368103],"type":"Point"}
}