{
  "type": "Feature",
  "properties": {
    "addr:full":"Avda Do\u00d1a Urraca, 25 Salamanca Salamanca 37005",
    "addr:housenumber":"25",
    "addr:postcode":"37005",
    "addr:street":"Avda Don\u0303A Urraca",
    "iso:country":"ES",
    "sg:address":"Avda Do\u00d1a Urraca, 25",
    "sg:city":"Salamanca",
    "sg:orig_category":"Instalaci\u00d3n, Reparaci\u00d3n De Ascensores Y Montacargas",
    "sg:phone":"+34 923 24 47 75",
    "sg:postcode":"37005",
    "sg:province":"Salamanca",
    "sg:website":"www.zener.org",
    "wof:name":"Zener Elevadores Del Noroeste S.a.",
    "wof:placetype":"venue"
},
  "geometry": {"coordinates":[-5.6577658653,40.975315094],"type":"Point"}
}