{
  "type": "Feature",
  "properties": {
    "addr:full":"Calle de Triana, 86 Palmas De Gran Canaria Las Palmas 35002",
    "addr:housenumber":"86",
    "addr:postcode":"35002",
    "addr:street":"Calle De Triana",
    "iso:country":"ES",
    "sg:address":"Calle de Triana, 86",
    "sg:city":"Palmas De Gran Canaria",
    "sg:orig_category":"Empresas De Portes Y Mensajer\u00cda",
    "sg:phone":"+34 928 38 02 39",
    "sg:postcode":"35002",
    "sg:province":"Las Palmas",
    "wof:name":"Sarmiento Castellano Manuel Antonio",
    "wof:placetype":"venue"
},
  "geometry": {"coordinates":[-15.4163341522,28.1064395905],"type":"Point"}
}