{
  "type": "Feature",
  "properties": {
    "iso:country":"ES",
    "sg:address":"Parque Comercial Mojacar, S/n",
    "sg:city":"Mojacar",
    "sg:orig_category":"Ropa Para Beb\u00c9s Y Ni\u00d1os (confecci\u00d3n, Al Por Mayor)",
    "sg:phone":"+34 950 47 58 54",
    "sg:postcode":"04638",
    "sg:province":"Almer\u00eda",
    "wof:name":"De Nascimento Navarrete Maria Luisa",
    "wof:placetype":"venue"
},
  "geometry": {"coordinates":[-1.8467450142,37.1402359009],"type":"Point"}
}