{
  "type": "Feature",
  "properties": {
    "addr:full":"Cedros, 3 Serranillos Madrid 28979",
    "addr:housenumber":"3",
    "addr:postcode":"28979",
    "addr:street":"Cedros",
    "iso:country":"ES",
    "sg:address":"Cedros, 3",
    "sg:city":"Serranillos",
    "sg:orig_category":"Reciclaje Y Tratamiento De Desechos Varios",
    "sg:phone":"+34 918 10 30 85",
    "sg:postcode":"28979",
    "sg:province":"Madrid",
    "wof:name":"Madegan S.a.",
    "wof:placetype":"venue"
},
  "geometry": {"coordinates":[-3.8735060692,40.1975250244],"type":"Point"}
}