{
  "type": "Feature",
  "properties": {
    "addr:full":"Calle de Lope De Rueda, 44 Madrid Madrid 28009",
    "addr:housenumber":"44",
    "addr:postcode":"madrid;28009",
    "addr:street":"Calle De Lope De Rueda",
    "iso:country":"ES",
    "sg:address":"Calle de Lope De Rueda, 44",
    "sg:city":"Madrid",
    "sg:orig_category":"Molduras, Junquillos, Listones Y Molduras Perforadas",
    "sg:phone":"+34 915 73 22 43",
    "sg:postcode":"28009",
    "sg:province":"Madrid",
    "wof:name":"Lucharna",
    "wof:placetype":"venue"
},
  "geometry": {"coordinates":[-3.6778690815,40.4196777344],"type":"Point"}
}