{
  "type": "Feature",
  "properties": {
    "addr:full":"Av Miramar, 27 Arenal Islas Baleares 07600",
    "addr:housenumber":"27",
    "addr:postcode":"07600",
    "addr:street":"Av Miramar",
    "iso:country":"ES",
    "sg:address":"Av Miramar, 27",
    "sg:city":"Arenal",
    "sg:orig_category":"Art\u00cdculos De Regalo (al Por Menor)",
    "sg:phone":"+34 971 44 10 51",
    "sg:postcode":"07600",
    "sg:province":"Islas Baleares",
    "wof:name":"Amaya Gonzalez Custodia",
    "wof:placetype":"venue"
},
  "geometry": {"coordinates":[2.7509727478,39.500629425],"type":"Point"}
}