{
  "type": "Feature",
  "properties": {
    "addr:full":"Plaz Mayor, 14 Villalpando Zamora 49630",
    "addr:housenumber":"14",
    "addr:postcode":"49630",
    "addr:street":"Plaz Mayor",
    "iso:country":"ES",
    "sg:address":"Plaz Mayor, 14",
    "sg:city":"Villalpando",
    "sg:orig_category":"Molduras, Junquillos, Listones Y Molduras Perforadas",
    "sg:phone":"+34 980 66 00 91",
    "sg:postcode":"49630",
    "sg:province":"Zamora",
    "wof:name":"Burgos Vega Antonio",
    "wof:placetype":"venue"
},
  "geometry": {"coordinates":[-5.4135489464,41.8645172119],"type":"Point"}
}