{
  "type": "Feature",
  "properties": {
    "iso:country":"ES",
    "sg:address":"Calle de Trianilla, 44",
    "sg:city":"Mairena Alcor",
    "sg:orig_category":"Carnicer\u00cdas, Carnicer\u00cdas",
    "sg:phone":"+34 955 94 23 49",
    "sg:postcode":"41510",
    "sg:province":"Sevilla",
    "wof:name":"Hermanos Jimenez Madro\u00f1al S.l.",
    "wof:placetype":"venue"
},
  "geometry": {"coordinates":[-5.7480688095,37.3710098267],"type":"Point"}
}