{
  "type": "Feature",
  "properties": {
    "iso:country":"ES",
    "sg:address":"Calle de Marbella, 68",
    "sg:city":"Madrid",
    "sg:orig_category":"Organizaciones Profesionales",
    "sg:phone":"+34 917 34 43 29",
    "sg:postcode":"28034",
    "sg:province":"Madrid",
    "wof:name":"Areitio Rodriguez Pedro",
    "wof:placetype":"venue"
},
  "geometry": {"coordinates":[-3.7107145786,40.4973335266],"type":"Point"}
}