{
  "type": "Feature",
  "properties": {
    "iso:country":"ES",
    "sg:address":"Av Pau Casals, 37",
    "sg:city":"Castellbisbal",
    "sg:orig_category":"Cajas De Ahorro",
    "sg:phone":"+34 937 71 10 07",
    "sg:postcode":"08755",
    "sg:province":"Barcelona",
    "wof:name":"Caixa D'estalvis Sabadell",
    "wof:placetype":"venue"
},
  "geometry": {"coordinates":[1.9821590185,41.4769554138],"type":"Point"}
}