{
  "type": "Feature",
  "properties": {
    "iso:country":"ES",
    "sg:address":"Afueras, S/n",
    "sg:city":"Talayuela",
    "sg:orig_category":"Ense\u00d1anza Secundaria: Colegios Y Escuelas Privadas",
    "sg:phone":"+34 927 57 84 05",
    "sg:postcode":"10310",
    "sg:province":"C\u00e1ceres",
    "wof:name":"Instituto De Ense\u00f1anza Secundaria San Martin",
    "wof:placetype":"venue"
},
  "geometry": {"coordinates":[-5.4806342125,40.0309944153],"type":"Point"}
}