{
  "type": "Feature",
  "properties": {
    "iso:country":"ES",
    "sg:address":"Avda Sants De La Pedra, 73",
    "sg:city":"Sagunt",
    "sg:orig_category":"Empresarios",
    "sg:phone":"+34 962 66 13 25",
    "sg:postcode":"46500",
    "sg:province":"Valencia",
    "wof:name":"Ripolles Gorris Jose",
    "wof:placetype":"venue"
},
  "geometry": {"coordinates":[-0.2783980072,39.6825523376],"type":"Point"}
}