{
  "type": "Feature",
  "properties": {
    "addr:full":"Ctra. Madrid(poligono), S/n Valdelafuente Le\u00f3n 24227",
    "addr:postcode":"24227",
    "addr:street":"Ctra. Madrid Poligono S / N Valdelafuente Leo\u0301N",
    "iso:country":"ES",
    "sg:address":"Ctra. Madrid(poligono), S/n",
    "sg:city":"Valdelafuente",
    "sg:orig_category":"Distribuci\u00d3n De Petr\u00d3leo Y Derivados",
    "sg:phone":"+34 987 21 08 98",
    "sg:postcode":"24227",
    "sg:province":"Le\u00f3n",
    "wof:name":"Estacion De Servicio Nuevo Paramo S.a.",
    "wof:placetype":"venue"
},
  "geometry": {"coordinates":[-5.5140891075,42.5692138672],"type":"Point"}
}