{
  "type": "Feature",
  "properties": {
    "addr:full":"Carrer de Amilcar, 8 Arenal Islas Baleares 07600",
    "addr:housenumber":"8",
    "addr:postcode":"07600",
    "addr:street":"Carrer De Amilcar",
    "iso:country":"ES",
    "sg:address":"Carrer de Amilcar, 8",
    "sg:city":"Arenal",
    "sg:orig_category":"Bancos",
    "sg:phone":"+34 971 26 13 12",
    "sg:postcode":"07600",
    "sg:province":"Islas Baleares",
    "wof:name":"Banco De Credito Balear S.a.",
    "wof:placetype":"venue"
},
  "geometry": {"coordinates":[2.7526679039,39.5061569214],"type":"Point"}
}