{
  "type": "Feature",
  "properties": {
    "iso:country":"ES",
    "sg:address":"Calle de Rodriguez De Cepeda, 20",
    "sg:city":"Valencia",
    "sg:orig_category":"Consultor\u00cdas Diversas",
    "sg:phone":"+34 963 61 24 29",
    "sg:postcode":"46021",
    "sg:province":"Valencia",
    "wof:name":"Topin S.l.",
    "wof:placetype":"venue"
},
  "geometry": {"coordinates":[-0.3536795974,39.4687461853],"type":"Point"}
}