{
  "type": "Feature",
  "properties": {
    "iso:country":"ES",
    "sg:address":"Ctra Moraira-calpe, 79",
    "sg:city":"Teulada",
    "sg:orig_category":"Alquiler De Veh\u00cdculos: Turismos Y Utilitarios",
    "sg:phone":"+34 966 49 22 77",
    "sg:postcode":"03725",
    "sg:province":"Alicante",
    "wof:name":"Frank S Rent A Car S.l.",
    "wof:placetype":"venue"
},
  "geometry": {"coordinates":[0.1042950004,38.7289505005],"type":"Point"}
}