{
  "type": "Feature",
  "properties": {
    "addr:full":"Calle de Maria Guerrero, 33 Elda Alicante 03600",
    "addr:housenumber":"33",
    "addr:postcode":"03600",
    "addr:street":"Calle De Maria Guerrero",
    "iso:country":"ES",
    "sg:address":"Calle de Maria Guerrero, 33",
    "sg:city":"Elda",
    "sg:orig_category":"Int\u00c9rpretes",
    "sg:phone":"+34 965 38 48 23",
    "sg:postcode":"03600",
    "sg:province":"Alicante",
    "wof:name":"Marketing Services Idella S.l",
    "wof:placetype":"venue"
},
  "geometry": {"coordinates":[-0.7893790007,38.4773101807],"type":"Point"}
}