{
  "type": "Feature",
  "properties": {
    "iso:country":"ES",
    "sg:address":"Trav De Gracia, 90",
    "sg:city":"Barcelona",
    "sg:orig_category":"Complementos De Vestir (al Por Menor)",
    "sg:phone":"+34 932 37 93 37",
    "sg:postcode":"08006",
    "sg:province":"Barcelona",
    "wof:name":"Gasso Casademunt Pilar",
    "wof:placetype":"venue"
},
  "geometry": {"coordinates":[2.1618824005,41.3948745728],"type":"Point"}
}