{
  "type": "Feature",
  "properties": {
    "addr:full":"Calle de Venecia, 15 Sevilla Sevilla 41008",
    "addr:housenumber":"15",
    "addr:postcode":"41008",
    "addr:street":"Calle De Venecia",
    "iso:country":"ES",
    "sg:address":"Calle de Venecia, 15",
    "sg:city":"Sevilla",
    "sg:orig_category":"Formaci\u00d3n Continuada (variada)",
    "sg:phone":"+34 954 54 01 04",
    "sg:postcode":"41008",
    "sg:province":"Sevilla",
    "wof:name":"Catalan Herrera Luis",
    "wof:placetype":"venue"
},
  "geometry": {"coordinates":[-5.9787778854,37.3956222534],"type":"Point"}
}