{
  "type": "Feature",
  "properties": {
    "addr:full":"Carrer de Doctor Reig, 52 Viladecans Barcelona 08840",
    "addr:housenumber":"52",
    "addr:postcode":"08840",
    "addr:street":"Carrer De Doctor Reig",
    "iso:country":"ES",
    "sg:address":"Carrer de Doctor Reig, 52",
    "sg:city":"Viladecans",
    "sg:orig_category":"Comerciantes Al Por Mayor De Vinos, Licores Y Alcoholes",
    "sg:phone":"+34 936 58 15 47",
    "sg:postcode":"08840",
    "sg:province":"Barcelona",
    "wof:name":"Hermanos Segura S.c.p.",
    "wof:placetype":"venue"
},
  "geometry": {"coordinates":[2.013835907,41.3189277649],"type":"Point"}
}