{
  "type": "Feature",
  "properties": {
    "iso:country":"ES",
    "sg:address":"Carrer de Gentil I Vellet, 1",
    "sg:city":"Selva Del Camp",
    "sg:orig_category":"Supermercados Y Hipermercados",
    "sg:phone":"+34 977 76 63 97",
    "sg:postcode":"43470",
    "sg:province":"Tarragona",
    "wof:name":"Franquet Figuerola Maricel",
    "wof:placetype":"venue"
},
  "geometry": {"coordinates":[1.1374100447,41.2153091431],"type":"Point"}
}