{
  "type": "Feature",
  "properties": {
    "addr:full":"Calle de Toro, 84 Salamanca Salamanca 37002",
    "addr:housenumber":"84",
    "addr:postcode":"37002",
    "addr:street":"Calle De Toro",
    "iso:country":"ES",
    "sg:address":"Calle de Toro, 84",
    "sg:city":"Salamanca",
    "sg:orig_category":"Ropa Para Beb\u00c9s Y Ni\u00d1os (confecci\u00d3n, Al Por Mayor)",
    "sg:phone":"+34 923 26 31 83",
    "sg:postcode":"37002",
    "sg:province":"Salamanca",
    "wof:name":"Blanco Hernandez Maria Manuela",
    "wof:placetype":"venue"
},
  "geometry": {"coordinates":[-5.6603951454,40.9683494568],"type":"Point"}
}