{
  "type": "Feature",
  "properties": {
    "iso:country":"ES",
    "sg:address":"Carrer de Rois De Corella, 2",
    "sg:city":"Sabadell",
    "sg:orig_category":"Materias Pl\u00c1sticas: Productos De Consumo Masivo (fabricaci\u00d3n, Al Por Mayor)",
    "sg:phone":"+34 937 12 06 58",
    "sg:postcode":"08205",
    "sg:province":"Barcelona",
    "wof:name":"Plastisaba S. A.",
    "wof:placetype":"venue"
},
  "geometry": {"coordinates":[2.1004469395,41.5311546326],"type":"Point"}
}