{
  "type": "Feature",
  "properties": {
    "addr:full":"Av President Companys, 5 Besalu Girona 17850",
    "addr:housenumber":"5",
    "addr:postcode":"17850",
    "addr:street":"Av President Companys",
    "iso:country":"ES",
    "sg:address":"Av President Companys, 5",
    "sg:city":"Besalu",
    "sg:orig_category":"Empresas De Vigilancia, Guardia Y Protecci\u00d3n",
    "sg:phone":"+34 972 59 11 12",
    "sg:postcode":"17850",
    "sg:province":"Girona",
    "wof:name":"Mapfre Servicios De Informatica",
    "wof:placetype":"venue"
},
  "geometry": {"coordinates":[2.6977550983,42.2004699707],"type":"Point"}
}