{
  "type": "Feature",
  "properties": {
    "addr:full":"Pg Valldaura, 246 Barcelona Barcelona 08016",
    "addr:housenumber":"246",
    "addr:postcode":"08016",
    "addr:street":"Pg Valldaura",
    "iso:country":"ES",
    "sg:address":"Pg Valldaura, 246",
    "sg:city":"Barcelona",
    "sg:orig_category":"Fabricaci\u00d3n De Pernos, Tornillos Y Clavos",
    "sg:phone":"+34 933 53 05 81",
    "sg:postcode":"08016",
    "sg:province":"Barcelona",
    "sg:website":"www.celo.com",
    "wof:name":"Celo S.a.",
    "wof:placetype":"venue"
},
  "geometry": {"coordinates":[2.1777360439,41.4386329651],"type":"Point"}
}