{
  "type": "Feature",
  "properties": {
    "iso:country":"ES",
    "sg:address":"Calle de Zurbaran, 15",
    "sg:city":"Monte Vedat",
    "sg:orig_category":"Agencias Y Asesores De Publicidad",
    "sg:phone":"+34 961 58 11 94",
    "sg:postcode":"46901",
    "sg:province":"Valencia",
    "sg:website":"www.ztv.es/scpublicidad",
    "wof:name":"Costa Sayalero Silvia",
    "wof:placetype":"venue"
},
  "geometry": {"coordinates":[-0.5005760193,39.4262924194],"type":"Point"}
}