{
  "type": "Feature",
  "properties": {
    "iso:country":"ES",
    "sg:address":"Avda Del Mediterrani, 101",
    "sg:city":"Onda",
    "sg:orig_category":"Piedra, Vidrio, Cer\u00c1mica Y Porcelana",
    "sg:phone":"+34 964 72 26 09",
    "sg:postcode":"12200",
    "sg:province":"Castell\u00f3n",
    "wof:name":"Ceramica Karimex S.l.",
    "wof:placetype":"venue"
},
  "geometry": {"coordinates":[-0.2235829979,39.9599990845],"type":"Point"}
}