{
  "type": "Feature",
  "properties": {
    "addr:full":"Av Negrete, 14 Ciutadella Menorca Islas Baleares 07760",
    "addr:housenumber":"14",
    "addr:postcode":"07760",
    "addr:street":"Av Negrete",
    "iso:country":"ES",
    "sg:address":"Av Negrete, 14",
    "sg:city":"Ciutadella Menorca",
    "sg:orig_category":"Agentes Generales De Seguros",
    "sg:phone":"+34 971 38 58 21",
    "sg:postcode":"07760",
    "sg:province":"Islas Baleares",
    "wof:name":"D.segui Menorca Agencia De Seguros",
    "wof:placetype":"venue"
},
  "geometry": {"coordinates":[3.8386099339,39.9992675781],"type":"Point"}
}