{
  "type": "Feature",
  "properties": {
    "iso:country":"ES",
    "sg:address":"Cr Badajoz-valencia, 366",
    "sg:city":"Membrilla",
    "sg:orig_category":"Frutas Y Legumbres Frescas (al Por Mayor)",
    "sg:phone":"+34 926 63 68 59",
    "sg:postcode":"13230",
    "sg:province":"Ciudad Real",
    "wof:name":"Cotillas Y Barroso S.l.",
    "wof:placetype":"venue"
},
  "geometry": {"coordinates":[-3.3460190296,38.9749450684],"type":"Point"}
}