{
  "type": "Feature",
  "properties": {
    "iso:country":"ES",
    "sg:address":"Calle de Gran Via, S/n",
    "sg:city":"Zaragoza",
    "sg:orig_category":"Transportes Urbanos Y Regionales Para Personas",
    "sg:phone":"+34 976 22 64 71",
    "sg:postcode":"50004",
    "sg:province":"Zaragoza",
    "sg:website":"www.tusa.es",
    "wof:name":"Transportes Urbanos De Zaragoza S. A.",
    "wof:placetype":"venue"
},
  "geometry": {"coordinates":[-0.8892840147,41.645778656],"type":"Point"}
}