{
  "type": "Feature",
  "properties": {
    "iso:country":"ES",
    "sg:address":"Calle de Salvador Almenar, 2",
    "sg:city":"Valencia",
    "sg:orig_category":"Carnicer\u00cdas, Carnicer\u00cdas",
    "sg:phone":"+34 963 61 12 98",
    "sg:postcode":"46020",
    "sg:province":"Valencia",
    "wof:name":"Sanz Exposito Marcelino",
    "wof:placetype":"venue"
},
  "geometry": {"coordinates":[-0.3609809875,39.4881095886],"type":"Point"}
}