{
  "type": "Feature",
  "properties": {
    "iso:country":"ES",
    "sg:address":"Avda Ebro (del), 12",
    "sg:city":"Calahorra",
    "sg:orig_category":"Conservas De Legumbres (fabricaci\u00d3n, Al Por Mayor)",
    "sg:phone":"+34 941 13 02 93",
    "sg:postcode":"26500",
    "sg:province":"La Rioja",
    "wof:name":"Barriobero Hermanos S. L.",
    "wof:placetype":"venue"
},
  "geometry": {"coordinates":[-1.9556490183,42.3101119995],"type":"Point"}
}