{
  "type": "Feature",
  "properties": {
    "addr:full":"Calle de Velazquez, 15 Villaca\u00f1as Toledo 45860",
    "addr:housenumber":"15",
    "addr:postcode":"45860",
    "addr:street":"Calle De Velazquez",
    "iso:country":"ES",
    "sg:address":"Calle de Velazquez, 15",
    "sg:city":"Villaca\u00f1as",
    "sg:orig_category":"Sociedades, Compa\u00d1\u00cdas Aseguradoras",
    "sg:phone":"+34 925 56 03 08",
    "sg:postcode":"45860",
    "sg:province":"Toledo",
    "wof:name":"Ocaso S.a.compa\u00f1ia De Seguros Y Reaseguros",
    "wof:placetype":"venue"
},
  "geometry": {"coordinates":[-3.3321390152,39.6239204407],"type":"Point"}
}