{
  "type": "Feature",
  "properties": {
    "iso:country":"ES",
    "sg:address":"Carrer de Fusters (dels), 10",
    "sg:city":"Can Cuias",
    "sg:orig_category":"Fabricaci\u00d3n De Quesos",
    "sg:phone":"+34 935 72 42 17",
    "sg:postcode":"08110",
    "sg:province":"Barcelona",
    "wof:name":"El Pastoret De La Segarra S.l.",
    "wof:placetype":"venue"
},
  "geometry": {"coordinates":[2.1750249863,41.464553833],"type":"Point"}
}