{
  "type": "Feature",
  "properties": {
    "addr:full":"Avda Virgen De La Monta\u00d1a, 2 Caceres C\u00e1ceres 10004",
    "addr:housenumber":"2",
    "addr:postcode":"10004",
    "addr:street":"Avda Virgen De La Montan\u0303A;Ca\u0301Ceres",
    "iso:country":"ES",
    "sg:address":"Avda Virgen De La Monta\u00d1a, 2",
    "sg:city":"Caceres",
    "sg:orig_category":"Librer\u00cdas",
    "sg:phone":"+34 927 22 20 19",
    "sg:postcode":"10004",
    "sg:province":"C\u00e1ceres",
    "wof:name":"Sociedad Anonima De Distribucion Edicion Y Librerias",
    "wof:placetype":"venue"
},
  "geometry": {"coordinates":[-6.3767738342,39.4713134766],"type":"Point"}
}