{
  "type": "Feature",
  "properties": {
    "iso:country":"ES",
    "sg:address":"Urbieta Kalea, 6",
    "sg:city":"Hernani",
    "sg:orig_category":"Laboratorios Y Trabajos De Fotograf\u00cda, V\u00cddeo Y Cine",
    "sg:phone":"+34 943 33 61 16",
    "sg:postcode":"20120",
    "sg:province":"Guip\u00f9zcoa",
    "wof:name":"Xabier Echarri Arraras",
    "wof:placetype":"venue"
},
  "geometry": {"coordinates":[-1.975456953,43.2670516968],"type":"Point"}
}