{
  "type": "Feature",
  "properties": {
    "iso:country":"ES",
    "sg:address":"Ctra Aranda, 12",
    "sg:city":"Illueca",
    "sg:orig_category":"Confecci\u00d3n De Zapatos",
    "sg:phone":"+34 976 82 26 96",
    "sg:postcode":"50250",
    "sg:province":"Zaragoza",
    "wof:name":"Asociacion De Fabricantes De Calzado Y Afines",
    "wof:placetype":"venue"
},
  "geometry": {"coordinates":[-1.6297762394,41.537322998],"type":"Point"}
}