{
  "type": "Feature",
  "properties": {
    "iso:country":"ES",
    "sg:address":"Calle de Pablo Coso Calero, 64",
    "sg:city":"Bormujos",
    "sg:orig_category":"Mec\u00c1nico Del Autom\u00d3vil",
    "sg:phone":"+34 955 72 69 12",
    "sg:postcode":"41930",
    "sg:province":"Sevilla",
    "wof:name":"Serrano Blas Juan Jose",
    "wof:placetype":"venue"
},
  "geometry": {"coordinates":[-6.0766768456,37.3699378967],"type":"Point"}
}