{
  "type": "Feature",
  "properties": {
    "iso:country":"ES",
    "sg:address":"Calle de Estrella Agena, 2",
    "sg:city":"Sevilla",
    "sg:orig_category":"Desinfecci\u00d3n, Desinsectaci\u00d3n, Desratizaci\u00d3n",
    "sg:phone":"+34 954 94 76 47",
    "sg:postcode":"41015",
    "sg:province":"Sevilla",
    "wof:name":"Tecniplag C.s.a.",
    "wof:placetype":"venue"
},
  "geometry": {"coordinates":[-5.9700088501,37.4219589233],"type":"Point"}
}