{
  "type": "Feature",
  "properties": {
    "iso:country":"ES",
    "sg:address":"Carr Anna Tugas, 62",
    "sg:city":"Badalona",
    "sg:orig_category":"Guarder\u00cdas",
    "sg:phone":"+34 934 65 49 53",
    "sg:postcode":"08917",
    "sg:province":"Barcelona",
    "wof:name":"Serrano Toril Ana Maria",
    "wof:placetype":"venue"
},
  "geometry": {"coordinates":[2.2295229435,41.4568405151],"type":"Point"}
}