{
  "type": "Feature",
  "properties": {
    "addr:full":"Ctra Zorrotza-kastrexana, 9 Bilbao Vizcaya 48013",
    "addr:housenumber":"9",
    "addr:postcode":"48013",
    "addr:street":"Ctra Zorrotza-Kastrexana",
    "iso:country":"ES",
    "sg:address":"Ctra Zorrotza-kastrexana, 9",
    "sg:city":"Bilbao",
    "sg:orig_category":"Promotores Constructores",
    "sg:phone":"+34 944 42 28 16",
    "sg:postcode":"48013",
    "sg:province":"Vizcaya",
    "wof:name":"Construcciones Fhimasa S. A.",
    "wof:placetype":"venue"
},
  "geometry": {"coordinates":[-2.9719851017,43.2757949829],"type":"Point"}
}