{
  "type": "Feature",
  "properties": {
    "addr:full":"Avda Victor Gallego, 2 Zamora Zamora 49009",
    "addr:housenumber":"2",
    "addr:postcode":"49009",
    "addr:street":"Avda Victor Gallego",
    "iso:country":"ES",
    "sg:address":"Avda Victor Gallego, 2",
    "sg:city":"Zamora",
    "sg:orig_category":"Ropa De Hogar (al Por Menor)",
    "sg:phone":"+34 980 51 09 48",
    "sg:postcode":"49009",
    "sg:province":"Zamora",
    "wof:name":"Boizas S.l.",
    "wof:placetype":"venue"
},
  "geometry": {"coordinates":[-5.7427520752,41.5123062134],"type":"Point"}
}