{
  "type": "Feature",
  "properties": {
    "addr:full":"Calle de Manuel De Falla, 10 Armilla Granada 18100",
    "addr:housenumber":"10",
    "addr:postcode":"18100",
    "addr:street":"Calle De Manuel De Falla",
    "iso:country":"ES",
    "sg:address":"Calle de Manuel De Falla, 10",
    "sg:city":"Armilla",
    "sg:orig_category":"Fotograf\u00cda Y Cine: Aparatos, Pel\u00cdculas Y Accesorios (fabricaci\u00d3n, Al Por Mayor)",
    "sg:phone":"+34 958 57 13 86",
    "sg:postcode":"18100",
    "sg:province":"Granada",
    "wof:name":"Tetenal Espa\u00f1a S.l.",
    "wof:placetype":"venue"
},
  "geometry": {"coordinates":[-3.6244208813,37.1428413391],"type":"Point"}
}