{
  "type": "Feature",
  "properties": {
    "iso:country":"ES",
    "sg:address":"Avda Constitucion, 28",
    "sg:city":"Don Benito",
    "sg:orig_category":"Ropa Para Se\u00d1oras Y Caballeros (al Por Menor)",
    "sg:phone":"+34 924 80 37 90",
    "sg:postcode":"06400",
    "sg:province":"Badajoz",
    "sg:website":"www.pullbear.com",
    "wof:name":"Pull & Bear Espa\u00f1a S.a.",
    "wof:placetype":"venue"
},
  "geometry": {"coordinates":[-5.8627138138,38.9662666321],"type":"Point"}
}