{
  "type": "Feature",
  "properties": {
    "addr:full":"Carrer de Gremi Selleters, S/n Poligon Industrial De Son Castello Islas Baleares 07009",
    "addr:housenumber":"s / n",
    "addr:postcode":"07009",
    "addr:street":"Carrer De Gremi Selleters;Islas",
    "iso:country":"ES",
    "sg:address":"Carrer de Gremi Selleters, S/n",
    "sg:city":"Poligon Industrial De Son Castello",
    "sg:orig_category":"Productores Recolectores, Venta Directa De Vinos",
    "sg:phone":"+34 971 43 00 24",
    "sg:postcode":"07009",
    "sg:province":"Islas Baleares",
    "wof:name":"Navarro Bibiloni Juan Carlos",
    "wof:placetype":"venue"
},
  "geometry": {"coordinates":[2.6741399765,39.6011390686],"type":"Point"}
}