{
  "type": "Feature",
  "properties": {
    "iso:country":"ES",
    "sg:address":"Calle de Julia Pintor Lopez, 1",
    "sg:city":"Palma Rio",
    "sg:orig_category":"Cl\u00cdnicas Dentales",
    "sg:phone":"+34 957 64 48 59",
    "sg:postcode":"14700",
    "sg:province":"C\u00f3rdoba",
    "wof:name":"Garcias Dental S.l.",
    "wof:placetype":"venue"
},
  "geometry": {"coordinates":[-5.280163765,37.7002716064],"type":"Point"}
}