{
  "type": "Feature",
  "properties": {
    "addr:full":"Calle de Laureano Mediante, 6 Coru\u00d1a La Coru\u00f1a 15006",
    "addr:housenumber":"6",
    "addr:postcode":"15006",
    "addr:street":"Calle De Laureano Mediante;La Corun\u0303A",
    "iso:country":"ES",
    "sg:address":"Calle de Laureano Mediante, 6",
    "sg:city":"Coru\u00d1a",
    "sg:orig_category":"Chapister\u00cda",
    "sg:phone":"+34 981 28 79 55",
    "sg:postcode":"15006",
    "sg:province":"La Coru\u00f1a",
    "wof:name":"Lorenzo Otero Gerardo",
    "wof:placetype":"venue"
},
  "geometry": {"coordinates":[-8.394651413,43.3531303406],"type":"Point"}
}