{
  "type": "Feature",
  "properties": {
    "iso:country":"ES",
    "sg:address":"Calle de Real, 2",
    "sg:city":"Alcala Valle",
    "sg:orig_category":"Fotograf\u00cda Y Cine: Aparatos, Pel\u00cdculas Y Accesorios (fabricaci\u00d3n, Al Por Mayor)",
    "sg:phone":"+34 956 12 66 77",
    "sg:postcode":"11693",
    "sg:province":"C\u00e1diz",
    "wof:name":"Caballero Fernandez Pedro",
    "wof:placetype":"venue"
},
  "geometry": {"coordinates":[-5.1705899239,36.9033241272],"type":"Point"}
}