{
  "type": "Feature",
  "properties": {
    "addr:full":"Porta Sant Jordi, 2 Xativa Valencia 46800",
    "addr:housenumber":"2",
    "addr:postcode":"46800",
    "addr:street":"Sant Jordi",
    "iso:country":"ES",
    "sg:address":"Porta Sant Jordi, 2",
    "sg:city":"Xativa",
    "sg:orig_category":"Agencias Y Agentes Comerciales, Representantes",
    "sg:phone":"+34 962 28 33 01",
    "sg:postcode":"46800",
    "sg:province":"Valencia",
    "wof:name":"Martinez Luna Francisco Javier",
    "wof:placetype":"venue"
},
  "geometry": {"coordinates":[-0.523680985,38.9875335693],"type":"Point"}
}