{
  "type": "Feature",
  "properties": {
    "addr:full":"Calle de Joaquin Maria Jalon, 15 Valladolid Valladolid 47008",
    "addr:housenumber":"15",
    "addr:postcode":"47008",
    "addr:street":"Calle De Joaquin Maria Jalon",
    "iso:country":"ES",
    "sg:address":"Calle de Joaquin Maria Jalon, 15",
    "sg:city":"Valladolid",
    "sg:orig_category":"Ropa Para Se\u00d1oras (al Por Menor)",
    "sg:phone":"+34 983 22 75 19",
    "sg:postcode":"47008",
    "sg:province":"Valladolid",
    "wof:name":"Vera Fernandez-espina Jose Antonio",
    "wof:placetype":"venue"
},
  "geometry": {"coordinates":[-4.7408699989,41.6281585693],"type":"Point"}
}