{
  "type": "Feature",
  "properties": {
    "iso:country":"ES",
    "sg:address":"Pl Barcelona, 6",
    "sg:city":"S. Cugat Valles",
    "sg:orig_category":"Abogados",
    "sg:phone":"+34 935 89 38 41",
    "sg:postcode":"08172",
    "sg:province":"Barcelona",
    "wof:name":"Casta\u00f1eda Gonzalez Vicent",
    "wof:placetype":"venue"
},
  "geometry": {"coordinates":[2.0817189217,41.4694023132],"type":"Point"}
}