{
  "type": "Feature",
  "properties": {
    "addr:full":"Calle de Parras, 42 Pegalajar Ja\u00e9n 23110",
    "addr:housenumber":"42",
    "addr:postcode":"23110",
    "addr:street":"Calle De Parras;Jae\u0301N",
    "iso:country":"ES",
    "sg:address":"Calle de Parras, 42",
    "sg:city":"Pegalajar",
    "sg:orig_category":"Arquitectos",
    "sg:phone":"+34 953 36 04 31",
    "sg:postcode":"23110",
    "sg:province":"Ja\u00e9n",
    "wof:name":"Chocano Carrascosa Tomas",
    "wof:placetype":"venue"
},
  "geometry": {"coordinates":[-3.6534669399,37.7369728088],"type":"Point"}
}