{
  "type": "Feature",
  "properties": {
    "addr:full":"Carr Barcelona, 58 Balaguer Lleida 25600",
    "addr:housenumber":"58",
    "addr:postcode":"25600",
    "addr:street":"Carr Barcelona",
    "iso:country":"ES",
    "sg:address":"Carr Barcelona, 58",
    "sg:city":"Balaguer",
    "sg:orig_category":"Mataderos De Poller\u00cda",
    "sg:phone":"+34 973 44 60 85",
    "sg:postcode":"25600",
    "sg:province":"Lleida",
    "wof:name":"Bendicho Torrelles Antonio",
    "wof:placetype":"venue"
},
  "geometry": {"coordinates":[0.811169982,41.7877197266],"type":"Point"}
}