{
  "type": "Feature",
  "properties": {
    "iso:country":"ES",
    "sg:address":"Calle de Nazaret, 7",
    "sg:city":"Mostoles",
    "sg:orig_category":"Asesor\u00cda Fiscal Y Jur\u00cddica",
    "sg:phone":"+34 916 47 56 88",
    "sg:postcode":"28936",
    "sg:province":"Madrid",
    "wof:name":"Gefico Gestion S.l.",
    "wof:placetype":"venue"
},
  "geometry": {"coordinates":[-3.8543388844,40.3300323486],"type":"Point"}
}