{
  "type": "Feature",
  "properties": {
    "iso:country":"ES",
    "sg:address":"Calle de Escultor Joaquin Lucarini, 7",
    "sg:city":"Vitoria-gasteiz",
    "sg:orig_category":"Peluqueros: De Se\u00d1oras",
    "sg:phone":"+34 945 14 41 54",
    "sg:postcode":"01007",
    "sg:province":"\u00c1lava",
    "wof:name":"Galdos Elorza Ana Maria",
    "wof:placetype":"venue"
},
  "geometry": {"coordinates":[-2.6827054024,42.8382148743],"type":"Point"}
}