{
  "type": "Feature",
  "properties": {
    "iso:country":"ES",
    "sg:address":"Avda Cinta De La, 6",
    "sg:city":"Huelva",
    "sg:orig_category":"Aceros Inoxidables",
    "sg:phone":"+34 959 54 57 37",
    "sg:postcode":"21005",
    "sg:province":"Huelva",
    "wof:name":"Inoxidables Del Atlantico S.l.",
    "wof:placetype":"venue"
},
  "geometry": {"coordinates":[-6.9376912117,37.2753448486],"type":"Point"}
}