{
  "type": "Feature",
  "properties": {
    "addr:full":"Carrer de Aribau, 26 Barcelona Barcelona 08011",
    "addr:housenumber":"26",
    "addr:postcode":"08011",
    "addr:street":"Carrer De Aribau",
    "iso:country":"ES",
    "sg:address":"Carrer de Aribau, 26",
    "sg:city":"Barcelona",
    "sg:orig_category":"Inmobiliaria (agencias)",
    "sg:phone":"+34 934 51 00 09",
    "sg:postcode":"08011",
    "sg:province":"Barcelona",
    "wof:name":"U.r. Asesores Inmobiliarios S.l.",
    "wof:placetype":"venue"
},
  "geometry": {"coordinates":[2.1615378857,41.3869552612],"type":"Point"}
}