{
  "type": "Feature",
  "properties": {
    "addr:full":"Calle de Fernandez De Los Rios, 50 Madrid Madrid 28015",
    "addr:housenumber":"50",
    "addr:postcode":"madrid;28015",
    "addr:street":"Calle De Fernandez De Los Rios",
    "iso:country":"ES",
    "sg:address":"Calle de Fernandez De Los Rios, 50",
    "sg:city":"Madrid",
    "sg:orig_category":"Perfumer\u00cda (al Por Menor)",
    "sg:phone":"+34 915 49 10 22",
    "sg:postcode":"28015",
    "sg:province":"Madrid",
    "wof:name":"Cosmo Droguer S.l.",
    "wof:placetype":"venue"
},
  "geometry": {"coordinates":[-3.7105519772,40.4353408813],"type":"Point"}
}