{
  "type": "Feature",
  "properties": {
    "addr:full":"Calle de Arcipreste De Hita, 5 Majadahonda Madrid 28220",
    "addr:housenumber":"5",
    "addr:postcode":"28220",
    "addr:street":"Calle De Arcipreste De Hita",
    "iso:country":"ES",
    "sg:address":"Calle de Arcipreste De Hita, 5",
    "sg:city":"Majadahonda",
    "sg:orig_category":"Tapiceros Y Tapiceros",
    "sg:phone":"+34 916 38 38 43",
    "sg:postcode":"28220",
    "sg:province":"Madrid",
    "wof:name":"Pecos Mora Maria",
    "wof:placetype":"venue"
},
  "geometry": {"coordinates":[-3.8768885136,40.4734230042],"type":"Point"}
}