{
  "type": "Feature",
  "properties": {
    "iso:country":"ES",
    "sg:address":"Treinta Enero 1964, S/n",
    "sg:city":"Burgos",
    "sg:orig_category":"Fabricaci\u00d3n, Venta, Instalaci\u00d3n De R\u00d3tulos, De R\u00d3tulos Luminosos",
    "sg:phone":"+34 947 48 56 63",
    "sg:postcode":"09007",
    "sg:province":"Burgos",
    "sg:website":"www.neoncid.com",
    "wof:name":"Rotulos Neon Cid S. L.",
    "wof:placetype":"venue"
},
  "geometry": {"coordinates":[-3.6467239857,42.3613395691],"type":"Point"}
}