{
  "type": "Feature",
  "properties": {
    "addr:full":"Pla\u00c7 Catalunya, 19 Armentera Girona 17472",
    "addr:housenumber":"19",
    "addr:postcode":"17472",
    "addr:street":"Armentera Girona",
    "iso:country":"ES",
    "sg:address":"Pla\u00c7 Catalunya, 19",
    "sg:city":"Armentera",
    "sg:orig_category":"Librer\u00cdas",
    "sg:phone":"+34 972 52 08 16",
    "sg:postcode":"17472",
    "sg:province":"Girona",
    "wof:name":"Planas Quer Maria",
    "wof:placetype":"venue"
},
  "geometry": {"coordinates":[3.0744850636,42.1720161438],"type":"Point"}
}