{
  "type": "Feature",
  "properties": {
    "iso:country":"ES",
    "sg:address":"Calle de Fray Pedro Payo Pi\u00d1eiro, 16",
    "sg:city":"Casanova De Eiris",
    "sg:orig_category":"Reposter\u00cdas",
    "sg:phone":"+34 981 28 58 01",
    "sg:postcode":"15009",
    "sg:province":"La Coru\u00f1a",
    "wof:name":"La Espiga De Oro S.l.",
    "wof:placetype":"venue"
},
  "geometry": {"coordinates":[-8.39590168,43.3438835144],"type":"Point"}
}