{
  "type": "Feature",
  "properties": {
    "iso:country":"ES",
    "sg:address":"Calle de Santa Maria, 20",
    "sg:city":"Iscar",
    "sg:orig_category":"Mercer\u00cda, Lencer\u00cda (al Por Menor)",
    "sg:phone":"+34 983 61 21 65",
    "sg:postcode":"47420",
    "sg:province":"Valladolid",
    "wof:name":"Acebes Martin Marina",
    "wof:placetype":"venue"
},
  "geometry": {"coordinates":[-4.5328125954,41.3630447388],"type":"Point"}
}