{
  "type": "Feature",
  "properties": {
    "iso:country":"ES",
    "sg:address":"Cmno Hormigueras, 167",
    "sg:city":"Madrid",
    "sg:orig_category":"Fabricaci\u00d3n De Telas Y Sedas",
    "sg:phone":"+34 913 80 17 37",
    "sg:postcode":"28031",
    "sg:province":"Madrid",
    "wof:name":"Importaciones Rajus S.a.",
    "wof:placetype":"venue"
},
  "geometry": {"coordinates":[-3.6361010075,40.3767242432],"type":"Point"}
}