{
  "type": "Feature",
  "properties": {
    "iso:country":"ES",
    "sg:address":"Calle de San Francisco, 16",
    "sg:city":"Donostia-san Sebastian",
    "sg:orig_category":"Reposter\u00cdas",
    "sg:phone":"+34 943 29 09 01",
    "sg:postcode":"20001",
    "sg:province":"Guip\u00f9zcoa",
    "wof:name":"Oses Almandoz Maria Cristina",
    "wof:placetype":"venue"
},
  "geometry": {"coordinates":[-1.9738969803,43.3235969543],"type":"Point"}
}