{
  "type": "Feature",
  "properties": {
    "iso:country":"ES",
    "sg:address":"Calle de San Agustin, 12",
    "sg:city":"Orihuela",
    "sg:orig_category":"Agencias Y Asesores De Publicidad",
    "sg:phone":"+34 966 74 35 98",
    "sg:postcode":"03300",
    "sg:province":"Alicante",
    "wof:name":"Ortu\u00f1o Sanz Antonio",
    "wof:placetype":"venue"
},
  "geometry": {"coordinates":[-0.9473360181,38.082950592],"type":"Point"}
}