{
  "type": "Feature",
  "properties": {
    "iso:country":"ES",
    "sg:address":"Urb. Pago El Crucifijo, 11",
    "sg:city":"Huelma",
    "sg:orig_category":"Comercio De Piezas De Recambio Y De Accesorios De Veh\u00cdculos, Veh\u00cdculos Industriales",
    "sg:phone":"+34 953 39 22 83",
    "sg:postcode":"23560",
    "sg:province":"Ja\u00e9n",
    "wof:name":"Galiano Guzman Alfonso",
    "wof:placetype":"venue"
},
  "geometry": {"coordinates":[-3.4510040283,37.6479644775],"type":"Point"}
}