{
  "type": "Feature",
  "properties": {
    "iso:country":"ES",
    "sg:address":"Calle de Fuente Nueva, 5",
    "sg:city":"Granada",
    "sg:orig_category":"Peluqueros: De Se\u00d1oras",
    "sg:phone":"+34 958 20 02 91",
    "sg:postcode":"18001",
    "sg:province":"Granada",
    "wof:name":"Alvarez Quiros Teresa",
    "wof:placetype":"venue"
},
  "geometry": {"coordinates":[-3.6028857231,37.181842804],"type":"Point"}
}