{
  "type": "Feature",
  "properties": {
    "iso:country":"ES",
    "sg:address":"Calle de Ignacio Garcia Caba\u00d1as, 18",
    "sg:city":"Quismondo",
    "sg:orig_category":"Iglesia Cat\u00d3lica",
    "sg:phone":"+34 925 79 02 09",
    "sg:postcode":"45514",
    "sg:province":"Toledo",
    "wof:name":"Parroquia Nuestra Se\u00f1ora De La Asuncion",
    "wof:placetype":"venue"
},
  "geometry": {"coordinates":[-4.3243808746,40.1033592224],"type":"Point"}
}