{
  "type": "Feature",
  "properties": {
    "iso:country":"ES",
    "sg:address":"Barriada, 27",
    "sg:city":"Espiells",
    "sg:classifiers":[
        {
            "category":"Wholesale",
            "subcategory":"Construction Materials",
            "type":"Manufacturing & Wholesale Goods"
        }
    ],
    "sg:phone":"+34 938 91 06 08",
    "sg:postcode":"08770",
    "sg:province":"Barcelona",
    "sg:tags":[
        "de",
        "embotellado"
    ],
    "wof:name":"Della Toffola Iberica S.a.",
    "wof:placetype":"venue"
},
  "geometry": {"coordinates":[1.7857899666,41.4300994873],"type":"Point"}
}