{
  "type": "Feature",
  "properties": {
    "addr:full":"Pase Virgen De Linarejos, 2 Linares Ja\u00e9n 23700",
    "addr:housenumber":"2",
    "addr:postcode":"23700",
    "addr:street":"Jae\u0301N",
    "iso:country":"ES",
    "sg:address":"Pase Virgen De Linarejos, 2",
    "sg:city":"Linares",
    "sg:orig_category":"M\u00c9dicos: Ginecolog\u00cda Y Obstetricia",
    "sg:phone":"+34 953 69 73 03",
    "sg:postcode":"23700",
    "sg:province":"Ja\u00e9n",
    "wof:name":"Martinez Martinez Jose Maximiliano",
    "wof:placetype":"venue"
},
  "geometry": {"coordinates":[-3.6323540211,38.0981941223],"type":"Point"}
}