{
  "type": "Feature",
  "properties": {
    "iso:country":"ES",
    "sg:address":"Calle de Rafael Alberti, 28",
    "sg:city":"Priego Cordoba",
    "sg:orig_category":"Promotores Constructores",
    "sg:phone":"+34 957 70 06 06",
    "sg:postcode":"14800",
    "sg:province":"C\u00f3rdoba",
    "wof:name":"Osuna Avalos Jose",
    "wof:placetype":"venue"
},
  "geometry": {"coordinates":[-4.1990599632,37.4412689209],"type":"Point"}
}