{
  "type": "Feature",
  "properties": {
    "addr:full":"Carr Sant Jordi, 21 Bell-lloc D'urgell Lleida 25220",
    "addr:housenumber":"21",
    "addr:postcode":"25220",
    "addr:street":"Carr Sant Jordi",
    "iso:country":"ES",
    "sg:address":"Carr Sant Jordi, 21",
    "sg:city":"Bell-lloc D'urgell",
    "sg:orig_category":"Empresas De Pintura Y Revestimientos",
    "sg:phone":"+34 973 56 05 17",
    "sg:postcode":"25220",
    "sg:province":"Lleida",
    "wof:name":"Romero Balasch Manuel",
    "wof:placetype":"venue"
},
  "geometry": {"coordinates":[0.6423709989,41.6024589539],"type":"Point"}
}