{
  "type": "Feature",
  "properties": {
    "iso:country":"ES",
    "sg:address":"Avda Arquitecto Alfredo Simon, 28",
    "sg:city":"Puerto",
    "sg:orig_category":"Limpieza Con Chorro De Arena Y Con Granalla, Pulido",
    "sg:phone":"+34 962 68 16 30",
    "sg:postcode":"46520",
    "sg:province":"Valencia",
    "wof:name":"Rodrigo Ca\u00f1as Jose",
    "wof:placetype":"venue"
},
  "geometry": {"coordinates":[-0.2025949955,39.7040786743],"type":"Point"}
}