{
  "type": "Feature",
  "properties": {
    "iso:country":"ES",
    "sg:address":"Cami Antic De Tossa, 42",
    "sg:city":"Lloret Mar",
    "sg:orig_category":"Promotores Constructores",
    "sg:phone":"+34 972 36 99 08",
    "sg:postcode":"17310",
    "sg:province":"Girona",
    "wof:name":"Avio Casanova Maria Eva",
    "wof:placetype":"venue"
},
  "geometry": {"coordinates":[2.8640441895,41.7041320801],"type":"Point"}
}