{
  "type": "Feature",
  "properties": {
    "iso:country":"ES",
    "sg:address":"Carrer de Providencia, 48",
    "sg:city":"Barcelona",
    "sg:orig_category":"Colchones (fabricaci\u00d3n, Al Por Mayor, Al Por Menor)",
    "sg:phone":"+34 932 84 43 42",
    "sg:postcode":"08024",
    "sg:province":"Barcelona",
    "wof:name":"Estruch Bargallo Faustino",
    "wof:placetype":"venue"
},
  "geometry": {"coordinates":[2.1570539474,41.4066390991],"type":"Point"}
}