{
  "type": "Feature",
  "properties": {
    "iso:country":"ES",
    "sg:address":"Avda Italia, S/n",
    "sg:city":"Huelva",
    "sg:orig_category":"Sindicatos De Trabajadores",
    "sg:phone":"+34 959 24 79 66",
    "sg:postcode":"21001",
    "sg:province":"Huelva",
    "wof:name":"Sector Ferroviario De Comisiones Obreras",
    "wof:placetype":"venue"
},
  "geometry": {"coordinates":[-6.9541740417,37.2547416687],"type":"Point"}
}