{
  "type": "Feature",
  "properties": {
    "addr:full":"Carrer de Alfons Sala, 2 Olesa Montserrat Barcelona 08640",
    "addr:housenumber":"2",
    "addr:postcode":"08640",
    "addr:street":"Carrer De Alfons Sala;Barcelona",
    "iso:country":"ES",
    "sg:address":"Carrer de Alfons Sala, 2",
    "sg:city":"Olesa Montserrat",
    "sg:orig_category":"Bazares, Art\u00cdculos De Limpieza Y De Cocina (al Por Menor)",
    "sg:phone":"+34 937 78 69 59",
    "sg:postcode":"08640",
    "sg:province":"Barcelona",
    "wof:name":"Albala Cordoba Concepcion",
    "wof:placetype":"venue"
},
  "geometry": {"coordinates":[1.8936699629,41.5447807312],"type":"Point"}
}