{
  "type": "Feature",
  "properties": {
    "addr:full":"Calle de Pilar Miro, 6 Zaragoza Zaragoza 50011",
    "addr:housenumber":"6",
    "addr:postcode":"50011",
    "addr:street":"Calle De Pilar Miro",
    "iso:country":"ES",
    "sg:address":"Calle de Pilar Miro, 6",
    "sg:city":"Zaragoza",
    "sg:orig_category":"Agencias Y Agentes Comerciales, Representantes",
    "sg:phone":"+34 976 53 79 49",
    "sg:postcode":"50011",
    "sg:province":"Zaragoza",
    "wof:name":"Porfolio Sl",
    "wof:placetype":"venue"
},
  "geometry": {"coordinates":[-0.9206809998,41.649433136],"type":"Point"}
}