{
  "type": "Feature",
  "properties": {
    "addr:full":"Lugar Avileses(aparecida), 56 La Palma Murcia 30593",
    "addr:housenumber":"56",
    "addr:postcode":"30593",
    "addr:street":"Lugar Avileses Aparecida",
    "iso:country":"ES",
    "sg:address":"Lugar Avileses(aparecida), 56",
    "sg:city":"La Palma",
    "sg:orig_category":"Agricultura: Abastecimiento Y Cosechado (negocio)",
    "sg:phone":"+34 968 55 48 62",
    "sg:postcode":"30593",
    "sg:province":"Murcia",
    "wof:name":"Agricolas Antysa Sl",
    "wof:placetype":"venue"
},
  "geometry": {"coordinates":[-0.9617580175,37.689289093],"type":"Point"}
}