{
  "type": "Feature",
  "properties": {
    "addr:full":"Pl Jacint Verdaguer (d'en), 1 Tarragona Tarragona 43003",
    "addr:housenumber":"1",
    "addr:postcode":"43003",
    "addr:street":"Pl Jacint Verdaguer D'En",
    "iso:country":"ES",
    "sg:address":"Pl Jacint Verdaguer (d'en), 1",
    "sg:city":"Tarragona",
    "sg:orig_category":"Ropa Para Ni\u00d1os (al Por Menor)",
    "sg:phone":"+34 977 24 17 54",
    "sg:postcode":"43003",
    "sg:province":"Tarragona",
    "sg:website":"www.ikks.com",
    "wof:name":"Ikks Sportwear Spain S.a.",
    "wof:placetype":"venue"
},
  "geometry": {"coordinates":[1.2552579641,41.1155128479],"type":"Point"}
}