{
  "type": "Feature",
  "properties": {
    "iso:country":"ES",
    "sg:address":"Avda Cambados, 65",
    "sg:city":"Vilagarcia",
    "sg:orig_category":"Servicio De Salud",
    "sg:phone":"+34 986 50 55 96",
    "sg:postcode":"36600",
    "sg:province":"Pontevedra",
    "wof:name":"Comercial Rodriguez Y Costa S. L.",
    "wof:placetype":"venue"
},
  "geometry": {"coordinates":[-8.7652978897,42.5917396545],"type":"Point"}
}