{
  "type": "Feature",
  "properties": {
    "addr:full":"Pl Joan Serrats, 8 Martorell Barcelona 08760",
    "addr:housenumber":"8",
    "addr:postcode":"08760",
    "addr:street":"Pl Joan Serrats",
    "iso:country":"ES",
    "sg:address":"Pl Joan Serrats, 8",
    "sg:city":"Martorell",
    "sg:orig_category":"Muebles, Minoristas",
    "sg:phone":"+34 937 75 54 15",
    "sg:postcode":"08760",
    "sg:province":"Barcelona",
    "wof:name":"Garcia Iglesias Eduardo",
    "wof:placetype":"venue"
},
  "geometry": {"coordinates":[1.9173660278,41.4829025269],"type":"Point"}
}