{
  "type": "Feature",
  "properties": {
    "addr:full":"Calle de Antonio Machin, 90 Sevilla Sevilla 41009",
    "addr:housenumber":"90",
    "addr:postcode":"41009",
    "addr:street":"Calle De Antonio Machin",
    "iso:country":"ES",
    "sg:address":"Calle de Antonio Machin, 90",
    "sg:city":"Sevilla",
    "sg:orig_category":"Tapicer\u00cdas",
    "sg:phone":"+34 954 38 70 97",
    "sg:postcode":"41009",
    "sg:province":"Sevilla",
    "wof:name":"Pe\u00f1a Martos Antonio",
    "wof:placetype":"venue"
},
  "geometry": {"coordinates":[-5.983379364,37.4034538269],"type":"Point"}
}