{
  "type": "Feature",
  "properties": {
    "iso:country":"ES",
    "sg:address":"P Sarasate, 32",
    "sg:city":"Iru\u00f1a",
    "sg:orig_category":"Ense\u00d1anza: Profesiones Art\u00cdsticas",
    "sg:phone":"+34 948 22 43 43",
    "sg:postcode":"31001",
    "sg:province":"Navarra",
    "wof:name":"Ciaurriz Loperena Margarita",
    "wof:placetype":"venue"
},
  "geometry": {"coordinates":[-1.6444989443,42.8155899048],"type":"Point"}
}