{
  "type": "Feature",
  "properties": {
    "iso:country":"ES",
    "sg:address":"Calle de Real, S/n",
    "sg:city":"Bobia",
    "sg:orig_category":"Arenas, Guijarros Y Granulados",
    "sg:phone":"+34 987 58 10 90",
    "sg:postcode":"24124",
    "sg:province":"Le\u00f3n",
    "wof:name":"Arenas De Bobia S.l.",
    "wof:placetype":"venue"
},
  "geometry": {"coordinates":[-5.8409795761,42.7562522888],"type":"Point"}
}