{
  "type": "Feature",
  "properties": {
    "addr:full":"Calle de Carmen, 2 Pe\u00e7aranda De Bracamonte Salamanca 37300",
    "addr:housenumber":"2",
    "addr:postcode":"37300",
    "addr:street":"Calle De Carmen",
    "iso:country":"ES",
    "sg:address":"Calle de Carmen, 2",
    "sg:city":"Pe\u00e7aranda De Bracamonte",
    "sg:orig_category":"Librer\u00cdas",
    "sg:phone":"+34 923 54 09 14",
    "sg:postcode":"37300",
    "sg:province":"Salamanca",
    "wof:name":"Blazquez Monzon Ana Isabel",
    "wof:placetype":"venue"
},
  "geometry": {"coordinates":[-5.2033491135,40.9005203247],"type":"Point"}
}