{
  "type": "Feature",
  "properties": {
    "iso:country":"ES",
    "sg:address":"Carrer de Sagrament, 12",
    "sg:city":"Sant Feliu Llobregat",
    "sg:orig_category":"M\u00c9dicos: Estomatolog\u00cda",
    "sg:phone":"+34 936 66 62 50",
    "sg:postcode":"08980",
    "sg:province":"Barcelona",
    "wof:name":"Mestres Cortadellas Josep",
    "wof:placetype":"venue"
},
  "geometry": {"coordinates":[2.0457420349,41.3882713318],"type":"Point"}
}