{
  "type": "Feature",
  "properties": {
    "iso:country":"ES",
    "sg:address":"Carrer de Vista Alegre, 44",
    "sg:city":"Mataro",
    "sg:orig_category":"Molduras, Junquillos, Listones Y Molduras Perforadas",
    "sg:phone":"+34 937 99 01 02",
    "sg:postcode":"08304",
    "sg:province":"Barcelona",
    "wof:name":"Jimenez Medina Fernando",
    "wof:placetype":"venue"
},
  "geometry": {"coordinates":[2.4453730583,41.5534629822],"type":"Point"}
}