{
  "type": "Feature",
  "properties": {
    "addr:full":"Calle de Mesones, 4 Don Benito Badajoz 06400",
    "addr:housenumber":"4",
    "addr:postcode":"06400",
    "addr:street":"Calle De Mesones",
    "iso:country":"ES",
    "sg:address":"Calle de Mesones, 4",
    "sg:city":"Don Benito",
    "sg:orig_category":"Panader\u00cdas, Panader\u00cdas",
    "sg:phone":"+34 924 80 16 82",
    "sg:postcode":"06400",
    "sg:province":"Badajoz",
    "wof:name":"Casa Silva S.l.",
    "wof:placetype":"venue"
},
  "geometry": {"coordinates":[-5.8621268272,38.9535064697],"type":"Point"}
}