{
  "type": "Feature",
  "properties": {
    "addr:full":"Carrer de Pal, 8 Benidorm Alicante 03500",
    "addr:housenumber":"8",
    "addr:postcode":"03500",
    "addr:street":"Carrer De Pal",
    "iso:country":"ES",
    "sg:address":"Carrer de Pal, 8",
    "sg:city":"Benidorm",
    "sg:orig_category":"Ropa Para Se\u00d1oras Y Caballeros (al Por Menor)",
    "sg:phone":"+34 966 81 10 97",
    "sg:postcode":"03500",
    "sg:province":"Alicante",
    "wof:name":"Duran Garrido Ramon",
    "wof:placetype":"venue"
},
  "geometry": {"coordinates":[-0.1288149953,38.5363578796],"type":"Point"}
}