{
  "type": "Feature",
  "properties": {
    "addr:full":"Carrer de Ceramica, 19 Esparreguera Barcelona 08292",
    "addr:housenumber":"19",
    "addr:postcode":"08292",
    "addr:street":"Carrer De Ceramica",
    "iso:country":"ES",
    "sg:address":"Carrer de Ceramica, 19",
    "sg:city":"Esparreguera",
    "sg:orig_category":"Chapister\u00cda",
    "sg:phone":"+34 937 08 00 63",
    "sg:postcode":"08292",
    "sg:province":"Barcelona",
    "wof:name":"Autos Catalu\u00f1a 2006 S.l",
    "wof:placetype":"venue"
},
  "geometry": {"coordinates":[1.8762799501,41.5253601074],"type":"Point"}
}