{
  "type": "Feature",
  "properties": {
    "addr:full":"Calle de Villapalacios, 28 Madrid Madrid 28021",
    "addr:housenumber":"28",
    "addr:postcode":"madrid;28021",
    "addr:street":"Calle De Villapalacios",
    "iso:country":"ES",
    "sg:address":"Calle de Villapalacios, 28",
    "sg:city":"Madrid",
    "sg:orig_category":"Iglesias Evang\u00c9licas",
    "sg:phone":"+34 917 95 51 37",
    "sg:postcode":"28021",
    "sg:province":"Madrid",
    "wof:name":"Iglesia Evangelica Bautista",
    "wof:placetype":"venue"
},
  "geometry": {"coordinates":[-3.6891770363,40.3512916565],"type":"Point"}
}