{
  "type": "Feature",
  "properties": {
    "addr:full":"Av Riera, S/n S. Just Desvern Barcelona 08960",
    "addr:postcode":"08960",
    "addr:street":"Av Riera S / N",
    "iso:country":"ES",
    "sg:address":"Av Riera, S/n",
    "sg:city":"S. Just Desvern",
    "sg:orig_category":"Molduras, Junquillos, Listones Y Molduras Perforadas",
    "sg:phone":"+34 933 71 67 47",
    "sg:postcode":"08960",
    "sg:province":"Barcelona",
    "wof:name":"Baumatel S.l. L.",
    "wof:placetype":"venue"
},
  "geometry": {"coordinates":[2.0782721043,41.3850669861],"type":"Point"}
}