{
  "type": "Feature",
  "properties": {
    "addr:full":"Calle de Emiliano Barral, 10 Madrid Madrid 28043",
    "addr:housenumber":"10",
    "addr:postcode":"madrid;28043",
    "addr:street":"Calle De Emiliano Barral",
    "iso:country":"ES",
    "sg:address":"Calle de Emiliano Barral, 10",
    "sg:city":"Madrid",
    "sg:orig_category":"Escritores",
    "sg:phone":"+34 914 15 23 99",
    "sg:postcode":"28043",
    "sg:province":"Madrid",
    "wof:name":"Perandones Manuel Maria Agustina",
    "wof:placetype":"venue"
},
  "geometry": {"coordinates":[-3.6603550911,40.4494018555],"type":"Point"}
}