{
  "type": "Feature",
  "properties": {
    "addr:full":"Calle de Delicias, 12 Madrid Madrid 28045",
    "addr:housenumber":"12",
    "addr:postcode":"madrid;28045",
    "addr:street":"Calle De Delicias",
    "iso:country":"ES",
    "sg:address":"Calle de Delicias, 12",
    "sg:city":"Madrid",
    "sg:orig_category":"Fabricaci\u00d3n De Muebles",
    "sg:phone":"+34 914 67 18 61",
    "sg:postcode":"28045",
    "sg:province":"Madrid",
    "wof:name":"Domingo Nieto Decoracion S.l.",
    "wof:placetype":"venue"
},
  "geometry": {"coordinates":[-3.6942710876,40.4041481018],"type":"Point"}
}