{
  "type": "Feature",
  "properties": {
    "addr:full":"Calle de Mayor, 3 Villamuriel De Cerrato Palencia 34190",
    "addr:housenumber":"3",
    "addr:postcode":"34190",
    "addr:street":"Calle De Mayor",
    "iso:country":"ES",
    "sg:address":"Calle de Mayor, 3",
    "sg:city":"Villamuriel De Cerrato",
    "sg:orig_category":"Negocio De Materiales De Construcci\u00d3n",
    "sg:phone":"+34 979 77 63 28",
    "sg:postcode":"34190",
    "sg:province":"Palencia",
    "wof:name":"Confecres S.l.",
    "wof:placetype":"venue"
},
  "geometry": {"coordinates":[-4.5158390999,41.9479103088],"type":"Point"}
}