{
  "type": "Feature",
  "properties": {
    "addr:full":"Carrer de Raval De La Creu, 2 S. Just Desvern Barcelona 08960",
    "addr:housenumber":"2",
    "addr:postcode":"08960",
    "addr:street":"Carrer De Raval De La Creu",
    "iso:country":"ES",
    "sg:address":"Carrer de Raval De La Creu, 2",
    "sg:city":"S. Just Desvern",
    "sg:orig_category":"Alquiler De V\u00cddeo",
    "sg:phone":"+34 934 73 24 69",
    "sg:postcode":"08960",
    "sg:province":"Barcelona",
    "wof:name":"Torrijos Valera Manuel",
    "wof:placetype":"venue"
},
  "geometry": {"coordinates":[2.0784900188,41.383140564],"type":"Point"}
}