{
  "type": "Feature",
  "properties": {
    "iso:country":"ES",
    "sg:address":"Carrer de Sant Benet, 35",
    "sg:city":"S. Fruitos Bages",
    "sg:orig_category":"Loter\u00cda Y T\u00d3mbola",
    "sg:phone":"+34 938 76 02 16",
    "sg:postcode":"08272",
    "sg:province":"Barcelona",
    "wof:name":"Subirana Cortina Natividad",
    "wof:placetype":"venue"
},
  "geometry": {"coordinates":[1.8718210459,41.7508277893],"type":"Point"}
}