{
  "type": "Feature",
  "properties": {
    "iso:country":"ES",
    "sg:address":"C/ Ample, 24",
    "sg:city":"Cerdanyola Valles",
    "sg:orig_category":"Electricidad Veh\u00cdculo",
    "sg:phone":"+34 935 80 64 64",
    "sg:postcode":"08290",
    "sg:province":"Barcelona",
    "wof:name":"Noguera Feliu Josep",
    "wof:placetype":"venue"
},
  "geometry": {"coordinates":[2.1334180832,41.4907035828],"type":"Point"}
}