{
  "type": "Feature",
  "properties": {
    "iso:country":"ES",
    "sg:address":"Calle de Salamanca, 91",
    "sg:city":"Palmas De Gran Canaria",
    "sg:orig_category":"Ropa Para Se\u00d1oras (al Por Menor)",
    "sg:phone":"+34 928 31 59 04",
    "sg:postcode":"35016",
    "sg:province":"Las Palmas",
    "wof:name":"Tejera Navarro Ramon",
    "wof:placetype":"venue"
},
  "geometry": {"coordinates":[-15.4282693863,28.068529129],"type":"Point"}
}