{
  "type": "Feature",
  "properties": {
    "addr:full":"Calle de Autonomia, 41 Bilbao Vizcaya 48012",
    "addr:housenumber":"41",
    "addr:postcode":"48012",
    "addr:street":"Calle De Autonomia",
    "iso:country":"ES",
    "sg:address":"Calle de Autonomia, 41",
    "sg:city":"Bilbao",
    "sg:orig_category":"Florister\u00cdas",
    "sg:phone":"+34 944 44 84 70",
    "sg:postcode":"48012",
    "sg:province":"Vizcaya",
    "wof:name":"Zabala Urquijo Maria Aranzazu",
    "wof:placetype":"venue"
},
  "geometry": {"coordinates":[-2.9424521923,43.257598877],"type":"Point"}
}