{
  "type": "Feature",
  "properties": {
    "iso:country":"ES",
    "sg:address":"Calle de Abastos, 9",
    "sg:city":"Valencia",
    "sg:orig_category":"Transportes Internacionales",
    "sg:phone":"+34 963 16 45 20",
    "sg:postcode":"46011",
    "sg:province":"Valencia",
    "wof:name":"Global Logistics Providers S.l.",
    "wof:placetype":"venue"
},
  "geometry": {"coordinates":[-0.3350642025,39.4617996216],"type":"Point"}
}