{
  "type": "Feature",
  "properties": {
    "iso:country":"ES",
    "sg:address":"Calle de Amnistia, 2",
    "sg:city":"Madrid",
    "sg:orig_category":"T\u00c9cnicos Veterinarios",
    "sg:phone":"+34 915 41 56 29",
    "sg:postcode":"28013",
    "sg:province":"Madrid",
    "wof:name":"Gonzalez Herrero Rocio",
    "wof:placetype":"venue"
},
  "geometry": {"coordinates":[-3.7101137638,40.4173583984],"type":"Point"}
}