{
  "type": "Feature",
  "properties": {
    "iso:country":"ES",
    "sg:address":"Carr Andenes Del Puerto, S/n",
    "sg:city":"Eivissa",
    "sg:orig_category":"Transportes Mar\u00cdtimos",
    "sg:phone":"+34 971 31 25 48",
    "sg:postcode":"07800",
    "sg:province":"Islas Baleares",
    "sg:website":"www.umafisa.com",
    "wof:name":"Eurolineas Maritimas S.a.l.",
    "wof:placetype":"venue"
},
  "geometry": {"coordinates":[1.4188899994,38.9061164856],"type":"Point"}
}