{
  "type": "Feature",
  "properties": {
    "iso:country":"ES",
    "sg:address":"Ctra Matadepera, 87",
    "sg:city":"Terrassa",
    "sg:orig_category":"Arreglo, Reparaci\u00d3n, Piezas Sueltas De Televisi\u00d3n, V\u00cddeo, Hi",
    "sg:phone":"+34 937 35 68 56",
    "sg:postcode":"08225",
    "sg:province":"Barcelona",
    "wof:name":"Cevasat S.c.",
    "wof:placetype":"venue"
},
  "geometry": {"coordinates":[2.017884016,41.572353363],"type":"Point"}
}