{
  "type": "Feature",
  "properties": {
    "addr:full":"Calle de Ruise\u00d1ores, 13 Malaga M\u00e1laga 29190",
    "addr:housenumber":"13",
    "addr:postcode":"29190",
    "addr:street":"Calle De Ruisen\u0303Ores;Ma\u0301Laga",
    "iso:country":"ES",
    "sg:address":"Calle de Ruise\u00d1ores, 13",
    "sg:city":"Malaga",
    "sg:orig_category":"Estancos",
    "sg:phone":"+34 952 10 08 10",
    "sg:postcode":"29190",
    "sg:province":"M\u00e1laga",
    "wof:name":"Diez De La Cortina Nu\u00f1ez Antonio",
    "wof:placetype":"venue"
},
  "geometry": {"coordinates":[-4.4826688766,36.7335624695],"type":"Point"}
}