{
  "type": "Feature",
  "properties": {
    "addr:full":"Carrer de Filadors (dels), 12 Torredembarra Tarragona 43830",
    "addr:housenumber":"12",
    "addr:postcode":"43830",
    "addr:street":"Carrer De Filadors Dels",
    "iso:country":"ES",
    "sg:address":"Carrer de Filadors (dels), 12",
    "sg:city":"Torredembarra",
    "sg:orig_category":"Tintes (fabricaci\u00d3n, Al Por Mayor)",
    "sg:phone":"+34 977 64 53 29",
    "sg:postcode":"43830",
    "sg:province":"Tarragona",
    "wof:name":"Rovira Girol Jacinto",
    "wof:placetype":"venue"
},
  "geometry": {"coordinates":[1.4011189938,41.1452407837],"type":"Point"}
}