{
  "type": "Feature",
  "properties": {
    "iso:country":"ES",
    "sg:address":"Eucalipto, 19",
    "sg:city":"Los Cristianos",
    "sg:orig_category":"Juristas",
    "sg:phone":"+34 922 79 33 30",
    "sg:postcode":"38650",
    "sg:province":"Santa Cruz De Tenerife",
    "wof:name":"Torrijos Suarez Fernando Adrian",
    "wof:placetype":"venue"
},
  "geometry": {"coordinates":[-16.7182445526,28.0533027649],"type":"Point"}
}