{
  "type": "Feature",
  "properties": {
    "addr:full":"Avda Vallehermoso, S/n Azuqueca Henares Guadalajara 19200",
    "addr:housenumber":"s / n",
    "addr:postcode":"19200",
    "addr:street":"Avda Vallehermoso",
    "iso:country":"ES",
    "sg:address":"Avda Vallehermoso, S/n",
    "sg:city":"Azuqueca Henares",
    "sg:orig_category":"Fabricaci\u00d3n, Importaci\u00d3n, Venta De Material De Telefon\u00cda, Peritelefon\u00cda",
    "sg:phone":"+34 949 26 67 90",
    "sg:postcode":"19200",
    "sg:province":"Guadalajara",
    "wof:name":"J R V Navaltelecom S.l.",
    "wof:placetype":"venue"
},
  "geometry": {"coordinates":[-3.264993906,40.5747718811],"type":"Point"}
}