{
  "type": "Feature",
  "properties": {
    "iso:country":"ES",
    "sg:address":"Calle de Santa Teresa, 43",
    "sg:city":"Alzira",
    "sg:orig_category":"Producci\u00d3n, Venta De Productos De Agricultura Biol\u00d3gica",
    "sg:phone":"+34 962 40 13 02",
    "sg:postcode":"46600",
    "sg:province":"Valencia",
    "wof:name":"Tami Agricola C.b.",
    "wof:placetype":"venue"
},
  "geometry": {"coordinates":[-0.4390259981,39.1527938843],"type":"Point"}
}