{
  "type": "Feature",
  "properties": {
    "addr:full":"Calle de Cantera, 8 Becilla Valderaduey Valladolid 47670",
    "addr:housenumber":"8",
    "addr:postcode":"47670",
    "addr:street":"Calle De Cantera",
    "iso:country":"ES",
    "sg:address":"Calle de Cantera, 8",
    "sg:city":"Becilla Valderaduey",
    "sg:orig_category":"Iglesia Cat\u00d3lica",
    "sg:phone":"+34 983 74 61 52",
    "sg:postcode":"47670",
    "sg:province":"Valladolid",
    "wof:name":"Casa Parroquial",
    "wof:placetype":"venue"
},
  "geometry": {"coordinates":[-5.2184228897,42.100479126],"type":"Point"}
}