{
  "type": "Feature",
  "properties": {
    "iso:country":"ES",
    "sg:address":"Carrer de Carders, 44",
    "sg:city":"Barcelona",
    "sg:orig_category":"Farmacias",
    "sg:phone":"+34 933 19 88 55",
    "sg:postcode":"08003",
    "sg:province":"Barcelona",
    "wof:name":"Corominas Frigola Susana",
    "wof:placetype":"venue"
},
  "geometry": {"coordinates":[2.1805860996,41.387298584],"type":"Point"}
}