{
  "type": "Feature",
  "properties": {
    "iso:country":"ES",
    "sg:address":"Carretera, 62",
    "sg:city":"S. Andreu Barca",
    "sg:orig_category":"Hielo Artificial (fabricaci\u00d3n, Distribuci\u00d3n)",
    "sg:phone":"+34 936 82 05 57",
    "sg:postcode":"08740",
    "sg:province":"Barcelona",
    "wof:name":"Cubitos G Y O S.l.",
    "wof:placetype":"venue"
},
  "geometry": {"coordinates":[1.973369956,41.4486236572],"type":"Point"}
}