{
  "type": "Feature",
  "properties": {
    "iso:country":"ES",
    "sg:address":"Calle de Profesor Sainz Cantero, 5",
    "sg:city":"Granada",
    "sg:orig_category":"M\u00c9dicos: Cirug\u00cda Cardiovascular Y Tor\u00c1cica",
    "sg:phone":"+34 958 28 71 48",
    "sg:postcode":"18002",
    "sg:province":"Granada",
    "wof:name":"Calvelo Martinez Agustin",
    "wof:placetype":"venue"
},
  "geometry": {"coordinates":[-3.6068129539,37.1781044006],"type":"Point"}
}