{
  "type": "Feature",
  "properties": {
    "addr:full":"Calle de Mayor, 3 Burgo Osma Soria 42300",
    "addr:housenumber":"3",
    "addr:postcode":"42300",
    "addr:street":"Calle De Mayor",
    "iso:country":"ES",
    "sg:address":"Calle de Mayor, 3",
    "sg:city":"Burgo Osma",
    "sg:orig_category":"Procuradores",
    "sg:phone":"+34 975 34 13 60",
    "sg:postcode":"42300",
    "sg:province":"Soria",
    "wof:name":"Soria Palomar Piedad",
    "wof:placetype":"venue"
},
  "geometry": {"coordinates":[-3.0821423531,41.5818824768],"type":"Point"}
}