{
  "type": "Feature",
  "properties": {
    "iso:country":"ES",
    "sg:address":"Calle de Bordadoras, 35",
    "sg:city":"Dos Hermanas",
    "sg:orig_category":"Laboratorios Y Cl\u00cdnicas Veterinarias",
    "sg:phone":"+34 955 66 88 79",
    "sg:postcode":"41700",
    "sg:province":"Sevilla",
    "wof:name":"Carreto Vallejo Ernesto",
    "wof:placetype":"venue"
},
  "geometry": {"coordinates":[-5.9259114265,37.2717781067],"type":"Point"}
}