{
  "type": "Feature",
  "properties": {
    "addr:full":"Calle de Carcagente, 26 Castellon Castell\u00f3n 12005",
    "addr:housenumber":"26",
    "addr:postcode":"12005",
    "addr:street":"Calle De Carcagente",
    "iso:country":"ES",
    "sg:address":"Calle de Carcagente, 26",
    "sg:city":"Castellon",
    "sg:orig_category":"Empresas De Vigilancia, Guardia Y Protecci\u00d3n",
    "sg:phone":"+34 964 23 10 70",
    "sg:postcode":"12005",
    "sg:province":"Castell\u00f3n",
    "wof:name":"Gebisa Seguridad S.a.",
    "wof:placetype":"venue"
},
  "geometry": {"coordinates":[-0.0315598994,39.9803161621],"type":"Point"}
}