{
  "type": "Feature",
  "properties": {
    "iso:country":"ES",
    "sg:address":"Calle de Duquesa De La Victoria, 40",
    "sg:city":"Logro\u00f1o",
    "sg:orig_category":"Inmobiliaria (agencias)",
    "sg:phone":"+34 941 27 00 61",
    "sg:postcode":"26003",
    "sg:province":"La Rioja",
    "wof:name":"Pradoval Gestion Inmobiliaria S.l.",
    "wof:placetype":"venue"
},
  "geometry": {"coordinates":[-2.439053297,42.4647827148],"type":"Point"}
}