{
  "type": "Feature",
  "properties": {
    "iso:country":"ES",
    "sg:address":"Pol Ind Tres De Oros, S/n",
    "sg:city":"Arjona",
    "sg:orig_category":"Mec\u00c1nico Del Autom\u00d3vil",
    "sg:phone":"+34 953 51 80 66",
    "sg:postcode":"23760",
    "sg:province":"Ja\u00e9n",
    "wof:name":"Segovia Salcedo Miguel",
    "wof:placetype":"venue"
},
  "geometry": {"coordinates":[-4.0658540726,37.9382896423],"type":"Point"}
}