{
  "type": "Feature",
  "properties": {
    "addr:full":"Calle de Maestro Aguilar, 7 Valencia Valencia 46006",
    "addr:housenumber":"7",
    "addr:postcode":"46006",
    "addr:street":"Calle De Maestro Aguilar",
    "iso:country":"ES",
    "sg:address":"Calle de Maestro Aguilar, 7",
    "sg:city":"Valencia",
    "sg:orig_category":"Perfumer\u00cda (al Por Menor)",
    "sg:phone":"+34 963 73 92 32",
    "sg:postcode":"46006",
    "sg:province":"Valencia",
    "wof:name":"Sancho Badenas Amparo",
    "wof:placetype":"venue"
},
  "geometry": {"coordinates":[-0.370133996,39.4614334106],"type":"Point"}
}