{
  "type": "Feature",
  "properties": {
    "iso:country":"ES",
    "sg:address":"Calle de Soria, 6",
    "sg:city":"Moron Frontera",
    "sg:orig_category":"Ropa Para Beb\u00c9s Y Ni\u00d1os (confecci\u00d3n, Al Por Mayor)",
    "sg:phone":"+34 954 85 13 40",
    "sg:postcode":"41530",
    "sg:province":"Sevilla",
    "wof:name":"Mova Moda S.l.u.",
    "wof:placetype":"venue"
},
  "geometry": {"coordinates":[-5.4615755081,37.1198348999],"type":"Point"}
}