{
  "type": "Feature",
  "properties": {
    "iso:country":"ES",
    "sg:address":"Plaz Iglesia (de La), 14",
    "sg:city":"Linea De La Concepcion",
    "sg:orig_category":"Confecci\u00d3n De Trajes De Ba\u00d1o Y De Ropa De Playa",
    "sg:phone":"+34 956 76 38 75",
    "sg:postcode":"11300",
    "sg:province":"C\u00e1diz",
    "wof:name":"Villanueva Leon Jose",
    "wof:placetype":"venue"
},
  "geometry": {"coordinates":[-5.340939045,36.1683044434],"type":"Point"}
}