{
  "type": "Feature",
  "properties": {
    "iso:country":"ES",
    "sg:address":"Calle de Guayadeque, 31",
    "sg:city":"Palmas De Gran Canaria",
    "sg:orig_category":"Agencias Y Agentes Comerciales, Representantes",
    "sg:phone":"+34 928 46 43 52",
    "sg:postcode":"35009",
    "sg:province":"Las Palmas",
    "wof:name":"Figueroa Rodriguez Miguel",
    "wof:placetype":"venue"
},
  "geometry": {"coordinates":[-15.4299650192,28.1534309387],"type":"Point"}
}