{
  "type": "Feature",
  "properties": {
    "iso:country":"ES",
    "sg:address":"Carrer de Mulleras, 11",
    "sg:city":"Olot",
    "sg:orig_category":"Sociedades, Compa\u00d1\u00cdas Aseguradoras",
    "sg:phone":"+34 972 26 04 44",
    "sg:postcode":"17800",
    "sg:province":"Girona",
    "sg:website":"www.curosespigule.com",
    "wof:name":"Curos Espigule S.l.",
    "wof:placetype":"venue"
},
  "geometry": {"coordinates":[2.4872310162,42.1807899475],"type":"Point"}
}