{
  "type": "Feature",
  "properties": {
    "iso:country":"ES",
    "sg:address":"Carr Alcalde Juan Sancho, 11",
    "sg:city":"Oliva",
    "sg:orig_category":"Ropa Para Ni\u00d1os (al Por Menor)",
    "sg:phone":"+34 962 85 82 32",
    "sg:postcode":"46780",
    "sg:province":"Valencia",
    "wof:name":"Happy Baby C.b.",
    "wof:placetype":"venue"
},
  "geometry": {"coordinates":[-0.1206969991,38.9236106873],"type":"Point"}
}