{
  "type": "Feature",
  "properties": {
    "addr:full":"Ctra. Castellon, Km. 0002,8 Zaragoza Zaragoza 50013",
    "addr:postcode":"50013",
    "addr:street":"Ctra. Castellon Km. 0002,8",
    "iso:country":"ES",
    "sg:address":"Ctra. Castellon, Km. 0002,8",
    "sg:city":"Zaragoza",
    "sg:orig_category":"Comercio De Hierro",
    "sg:phone":"+34 976 42 28 40",
    "sg:postcode":"50013",
    "sg:province":"Zaragoza",
    "wof:name":"Industrias Lopez Soriano S.a.",
    "wof:placetype":"venue"
},
  "geometry": {"coordinates":[-0.847324729,41.6225280762],"type":"Point"}
}