{
  "type": "Feature",
  "properties": {
    "iso:country":"ES",
    "sg:address":"Avda Blas Infante, 2",
    "sg:city":"Utrera",
    "sg:orig_category":"Reposter\u00cdas",
    "sg:phone":"+34 955 86 52 92",
    "sg:postcode":"41710",
    "sg:province":"Sevilla",
    "wof:name":"Obando Lopez Francisco De Paula",
    "wof:placetype":"venue"
},
  "geometry": {"coordinates":[-5.7793469429,37.1875305176],"type":"Point"}
}