{
  "type": "Feature",
  "properties": {
    "iso:country":"ES",
    "sg:address":"Avda Algorta, 110",
    "sg:city":"Getxo",
    "sg:orig_category":"Bazares, Art\u00cdculos De Limpieza Y De Cocina (al Por Menor)",
    "sg:phone":"+34 944 60 34 76",
    "sg:postcode":"48990",
    "sg:province":"Vizcaya",
    "wof:name":"Rafael Romero Andres",
    "wof:placetype":"venue"
},
  "geometry": {"coordinates":[-3.0107760429,43.3513793945],"type":"Point"}
}