{
  "type": "Feature",
  "properties": {
    "addr:full":"Rbla Portalet, 12 S. Feliu Guixols Girona 17220",
    "addr:housenumber":"12",
    "addr:postcode":"17220",
    "addr:street":"Rbla Portalet;S. Feliu Guixols",
    "iso:country":"ES",
    "sg:address":"Rbla Portalet, 12",
    "sg:city":"S. Feliu Guixols",
    "sg:classifiers":[
        {
            "category":"Personal",
            "subcategory":"Barber",
            "type":"Services"
        }
    ],
    "sg:phone":"+34 972 32 56 40",
    "sg:postcode":"17220",
    "sg:province":"Girona",
    "sg:tags":[
        "caballeros",
        "de",
        "peluqueros"
    ],
    "wof:name":"Perruqueria El Portalet S.c",
    "wof:placetype":"venue"
},
  "geometry": {"coordinates":[3.0319130421,41.782081604],"type":"Point"}
}