{
  "type": "Feature",
  "properties": {
    "iso:country":"ES",
    "sg:address":"Calle de Bedel, 6",
    "sg:city":"Alcala Henares",
    "sg:orig_category":"Zapatos (al Por Menor)",
    "sg:phone":"+34 918 88 01 88",
    "sg:postcode":"28801",
    "sg:province":"Madrid",
    "wof:name":"Hontana Ollero Juan Luis",
    "wof:placetype":"venue"
},
  "geometry": {"coordinates":[-3.3633644581,40.4833679199],"type":"Point"}
}