{
  "type": "Feature",
  "properties": {
    "addr:full":"Plaz Constitucion (la), S/n Puebla Vicar Almer\u00eda 04738",
    "addr:postcode":"04738",
    "addr:street":"Constitucion La S / N",
    "iso:country":"ES",
    "sg:address":"Plaz Constitucion (la), S/n",
    "sg:city":"Puebla Vicar",
    "sg:classifiers":[
        {
            "category":"Communications",
            "type":"Services"
        }
    ],
    "sg:phone":"+34 950 55 43 83",
    "sg:postcode":"04738",
    "sg:province":"Almer\u00eda",
    "sg:tags":[
        "televisiones",
        "y",
        "radio"
    ],
    "wof:name":"Onda Nueva Radio S.l.",
    "wof:placetype":"venue"
},
  "geometry": {"coordinates":[-2.635559082,36.7998008728],"type":"Point"}
}