{
  "type": "Feature",
  "properties": {
    "addr:full":"Cuarteles, 12 Cerro Muriano C\u00f3rdoba 14350",
    "addr:housenumber":"12",
    "addr:postcode":"14350",
    "addr:street":"Cuarteles;Muriano Co\u0301Rdoba",
    "iso:country":"ES",
    "sg:address":"Cuarteles, 12",
    "sg:city":"Cerro Muriano",
    "sg:orig_category":"Pescader\u00cdas (al Por Menor)",
    "sg:phone":"+34 957 35 05 05",
    "sg:postcode":"14350",
    "sg:province":"C\u00f3rdoba",
    "wof:name":"Ortiz Galan Baldomero",
    "wof:placetype":"venue"
},
  "geometry": {"coordinates":[-4.7667369843,38.002948761],"type":"Point"}
}