{
  "type": "Feature",
  "properties": {
    "addr:full":"Plaz Ayuntamiento, S/n Toledo Toledo 45002",
    "addr:housenumber":"/ n",
    "addr:postcode":"45002",
    "addr:street":"S",
    "iso:country":"ES",
    "sg:address":"Plaz Ayuntamiento, S/n",
    "sg:city":"Toledo",
    "sg:orig_category":"Ense\u00d1anza, Formaci\u00d3n Profesional: Aprendizaje",
    "sg:phone":"+34 925 28 20 59",
    "sg:postcode":"45002",
    "sg:province":"Toledo",
    "wof:name":"Gerencia Territorial Ministerio De Justicia De Castilla La Mancha",
    "wof:placetype":"venue"
},
  "geometry": {"coordinates":[-4.0247654915,39.8569755554],"type":"Point"}
}