{
  "type": "Feature",
  "properties": {
    "addr:full":"Pl Osona, 8 Vic Barcelona 08500",
    "addr:postcode":"08500",
    "addr:street":"Osona",
    "iso:country":"ES",
    "sg:address":"Pl Osona, 8",
    "sg:city":"Vic",
    "sg:orig_category":"Laboratorios Dentales",
    "sg:phone":"+34 938 83 30 06",
    "sg:postcode":"08500",
    "sg:province":"Barcelona",
    "wof:name":"Marti Fabrego Ramon",
    "wof:placetype":"venue"
},
  "geometry": {"coordinates":[2.2382099628,41.9391555786],"type":"Point"}
}