{
  "type": "Feature",
  "properties": {
    "iso:country":"ES",
    "sg:address":"Calle de Cami Cebolla, 30",
    "sg:city":"Rafelbunyol",
    "sg:orig_category":"Fabricaci\u00d3n De Moldes Y Modelos",
    "sg:phone":"+34 961 41 15 58",
    "sg:postcode":"46138",
    "sg:province":"Valencia",
    "wof:name":"Matriceria Maype S.l.",
    "wof:placetype":"venue"
},
  "geometry": {"coordinates":[-0.3270308971,39.58826828],"type":"Point"}
}