{
  "type": "Feature",
  "properties": {
    "addr:full":"Avda Madrid, 15 Brihuega Guadalajara 19400",
    "addr:housenumber":"15",
    "addr:postcode":"19400",
    "addr:street":"Avda Madrid",
    "iso:country":"ES",
    "sg:address":"Avda Madrid, 15",
    "sg:city":"Brihuega",
    "sg:orig_category":"Transporte En General",
    "sg:phone":"+34 949 28 02 33",
    "sg:postcode":"19400",
    "sg:province":"Guadalajara",
    "wof:name":"Cuevas Cuevas Maria Lourdes",
    "wof:placetype":"venue"
},
  "geometry": {"coordinates":[-2.8716089725,40.762348175],"type":"Point"}
}