{
  "type": "Feature",
  "properties": {
    "addr:full":"Calle de Gregorio Mara\u00d1on, 3 Marbella M\u00e1laga 29600",
    "addr:housenumber":"3",
    "addr:postcode":"29600",
    "addr:street":"Calle De Gregorio Maran\u0303On;Ma\u0301Laga",
    "iso:country":"ES",
    "sg:address":"Calle de Gregorio Mara\u00d1on, 3",
    "sg:city":"Marbella",
    "sg:orig_category":"Peluquer\u00cdas, Peluquer\u00cda Mixta",
    "sg:phone":"+34 952 82 49 81",
    "sg:postcode":"29600",
    "sg:province":"M\u00e1laga",
    "wof:name":"Manfredi Otero Manuela",
    "wof:placetype":"venue"
},
  "geometry": {"coordinates":[-4.8961920738,36.5095710754],"type":"Point"}
}