{
  "type": "Feature",
  "properties": {
    "iso:country":"ES",
    "sg:address":"Avda Jacaranda, 31",
    "sg:city":"Bormujos",
    "sg:orig_category":"Centros Empresariales",
    "sg:phone":"+34 955 72 20 37",
    "sg:postcode":"41930",
    "sg:province":"Sevilla",
    "wof:name":"Herrerias Esteban Juan Manuel",
    "wof:placetype":"venue"
},
  "geometry": {"coordinates":[-6.0622639656,37.3635444641],"type":"Point"}
}