{
  "type": "Feature",
  "properties": {
    "iso:country":"ES",
    "sg:address":"Ctra M-103, Km. 0035,0",
    "sg:city":"Moraleja",
    "sg:orig_category":"Semiller\u00cdas",
    "sg:phone":"+34 918 41 77 91",
    "sg:postcode":"28160",
    "sg:province":"Madrid",
    "wof:name":"Pe\u00f1a Gonzalez Maria Del Mar",
    "wof:placetype":"venue"
},
  "geometry": {"coordinates":[-3.5078120232,40.7456016541],"type":"Point"}
}