{
  "type": "Feature",
  "properties": {
    "iso:country":"ES",
    "sg:address":"Calle de Regidor, 18",
    "sg:city":"Madridejos",
    "sg:orig_category":"Panader\u00cdas, Panader\u00cdas",
    "sg:phone":"+34 925 46 01 47",
    "sg:postcode":"45710",
    "sg:province":"Toledo",
    "wof:name":"Garcia-cano Gutierrez Gregorio",
    "wof:placetype":"venue"
},
  "geometry": {"coordinates":[-3.5307691097,39.4697113037],"type":"Point"}
}