{
  "type": "Feature",
  "properties": {
    "iso:country":"ES",
    "sg:address":"Carrer de Om, 10",
    "sg:city":"Barcelona",
    "sg:orig_category":"Albergues",
    "sg:phone":"+34 934 41 14 95",
    "sg:postcode":"08001",
    "sg:province":"Barcelona",
    "wof:name":"Caparros Lloret Juan",
    "wof:placetype":"venue"
},
  "geometry": {"coordinates":[2.1721200943,41.375869751],"type":"Point"}
}