{
  "type": "Feature",
  "properties": {
    "addr:full":"Avda Bruselas, 52 Madrid Madrid 28028",
    "addr:housenumber":"52",
    "addr:postcode":"madrid;28028",
    "addr:street":"Avda Bruselas",
    "iso:country":"ES",
    "sg:address":"Avda Bruselas, 52",
    "sg:city":"Madrid",
    "sg:orig_category":"Lencer\u00cda Femenina, Corseter\u00cda, Trajes De Ba\u00d1o (al Por Menor)",
    "sg:phone":"+34 917 26 96 71",
    "sg:postcode":"28028",
    "sg:province":"Madrid",
    "wof:name":"Barrena Valdivieso Maria Mercedes",
    "wof:placetype":"venue"
},
  "geometry": {"coordinates":[-3.6628780365,40.4386787415],"type":"Point"}
}