{
  "type": "Feature",
  "properties": {
    "iso:country":"ES",
    "sg:address":"Carrer de Andreu Vidal, 4",
    "sg:city":"S. Adria Besos",
    "sg:orig_category":"Asesor\u00cda Fiscal Y Jur\u00cddica",
    "sg:phone":"+34 934 62 62 57",
    "sg:postcode":"08930",
    "sg:province":"Barcelona",
    "wof:name":"Tomas Alvarez Juan",
    "wof:placetype":"venue"
},
  "geometry": {"coordinates":[2.2151529789,41.4328536987],"type":"Point"}
}