{
  "type": "Feature",
  "properties": {
    "addr:full":"Calle de Guadiana, S/n Puebla Calzada Badajoz 06490",
    "addr:housenumber":"s / n",
    "addr:postcode":"06490",
    "addr:street":"Calle De Guadiana;Calzada Badajoz",
    "iso:country":"ES",
    "sg:address":"Calle de Guadiana, S/n",
    "sg:city":"Puebla Calzada",
    "sg:orig_category":"Pistas Y Clases De Tenis",
    "sg:phone":"+34 924 45 08 46",
    "sg:postcode":"06490",
    "sg:province":"Badajoz",
    "wof:name":"Club De Tenis Puebla",
    "wof:placetype":"venue"
},
  "geometry": {"coordinates":[-6.6274738312,38.8880767822],"type":"Point"}
}