{
  "type": "Feature",
  "properties": {
    "iso:country":"ES",
    "sg:address":"Poli Rubira Sola, S/n",
    "sg:city":"Macael",
    "sg:orig_category":"Empresas De Carpinter\u00cda Met\u00c1lica",
    "sg:phone":"+34 950 44 50 88",
    "sg:postcode":"04867",
    "sg:province":"Almer\u00eda",
    "wof:name":"Hierros Pedro Y Manuel S.l.",
    "wof:placetype":"venue"
},
  "geometry": {"coordinates":[-2.3048915863,37.3322906494],"type":"Point"}
}