{
  "type": "Feature",
  "properties": {
    "iso:country":"ES",
    "sg:address":"Calle de Republica Argentina, 9",
    "sg:city":"Malaga",
    "sg:orig_category":"Asociaciones, Organismos Culturales Y Socioeducativos",
    "sg:phone":"+34 952 21 84 96",
    "sg:postcode":"29016",
    "sg:province":"M\u00e1laga",
    "wof:name":"Sociedad Excursionista De Malaga",
    "wof:placetype":"venue"
},
  "geometry": {"coordinates":[-4.3994398117,36.7265777588],"type":"Point"}
}