{
  "type": "Feature",
  "properties": {
    "iso:country":"ES",
    "sg:address":"Calle de Guzman El Bueno, 20",
    "sg:city":"Nerva",
    "sg:orig_category":"Supermercados Y Hipermercados",
    "sg:phone":"+34 959 58 00 32",
    "sg:postcode":"21670",
    "sg:province":"Huelva",
    "wof:name":"Dominguez Martin Feliciano",
    "wof:placetype":"venue"
},
  "geometry": {"coordinates":[-6.5453538895,37.6916046143],"type":"Point"}
}