{
  "type": "Feature",
  "properties": {
    "addr:full":"Carrer de Carme Galceran, 4 Molins Rei Barcelona 08750",
    "addr:housenumber":"4",
    "addr:postcode":"08750",
    "addr:street":"Carrer De Carme Galceran;Barcelona",
    "iso:country":"ES",
    "sg:address":"Carrer de Carme Galceran, 4",
    "sg:city":"Molins Rei",
    "sg:orig_category":"Artes Gr\u00c1ficas, Artes Pl\u00c1sticas (curso)",
    "sg:phone":"+34 936 68 55 21",
    "sg:postcode":"08750",
    "sg:province":"Barcelona",
    "wof:name":"Graficas Fabregas S.l.",
    "wof:placetype":"venue"
},
  "geometry": {"coordinates":[2.0209569931,41.4109649658],"type":"Point"}
}