{
  "type": "Feature",
  "properties": {
    "iso:country":"ES",
    "sg:address":"Calle de Monegros, 1",
    "sg:city":"Leganes",
    "sg:orig_category":"Asesor\u00cda Fiscal Y Jur\u00cddica",
    "sg:phone":"+34 916 88 50 44",
    "sg:postcode":"28915",
    "sg:province":"Madrid",
    "wof:name":"Garcia Casta\u00f1o Antonio",
    "wof:placetype":"venue"
},
  "geometry": {"coordinates":[-3.7555000782,40.3351173401],"type":"Point"}
}