{
  "type": "Feature",
  "properties": {
    "addr:full":"Calle de Alvaro De Bazan, 15 Valencia Valencia 46010",
    "addr:housenumber":"15",
    "addr:postcode":"46010",
    "addr:street":"Calle De Alvaro De Bazan",
    "iso:country":"ES",
    "sg:address":"Calle de Alvaro De Bazan, 15",
    "sg:city":"Valencia",
    "sg:orig_category":"Pescader\u00cdas (al Por Menor)",
    "sg:phone":"+34 963 69 25 33",
    "sg:postcode":"46010",
    "sg:province":"Valencia",
    "wof:name":"Peixcateria Valencia S.l.",
    "wof:placetype":"venue"
},
  "geometry": {"coordinates":[-0.3614925146,39.480796814],"type":"Point"}
}