{
  "type": "Feature",
  "properties": {
    "iso:country":"ES",
    "sg:address":"Calle de Mariano Vergara, 7",
    "sg:city":"Santa Eulalia",
    "sg:orig_category":"Peluqueros: De Se\u00d1oras",
    "sg:phone":"+34 968 21 74 58",
    "sg:postcode":"30003",
    "sg:province":"Murcia",
    "wof:name":"Chelso Satoca Regina",
    "wof:placetype":"venue"
},
  "geometry": {"coordinates":[-1.124557972,37.9856300354],"type":"Point"}
}