{
  "type": "Feature",
  "properties": {
    "addr:full":"Calle de Ventura Garcia Escobar, 1 Medina Rioseco Valladolid 47800",
    "addr:housenumber":"1",
    "addr:postcode":"47800",
    "addr:street":"Calle De Ventura Garcia Escobar",
    "iso:country":"ES",
    "sg:address":"Calle de Ventura Garcia Escobar, 1",
    "sg:city":"Medina Rioseco",
    "sg:orig_category":"Perfumer\u00cda (al Por Menor)",
    "sg:phone":"+34 983 70 12 30",
    "sg:postcode":"47800",
    "sg:province":"Valladolid",
    "wof:name":"Rubio Lopez Maria Jose",
    "wof:placetype":"venue"
},
  "geometry": {"coordinates":[-5.0430841446,41.8802261353],"type":"Point"}
}