{
  "type": "Feature",
  "properties": {
    "addr:full":"Ctra Nal Iii, Km. 0271,0 Utiel Valencia 46300",
    "addr:postcode":"46300",
    "addr:street":"Ctra Nal Iii Km. 0271,0",
    "iso:country":"ES",
    "sg:address":"Ctra Nal Iii, Km. 0271,0",
    "sg:city":"Utiel",
    "sg:orig_category":"Mataderos De Poller\u00cda",
    "sg:phone":"+34 962 17 02 81",
    "sg:postcode":"46300",
    "sg:province":"Valencia",
    "wof:name":"Laureano Sanchez Requena Lauria S. L.",
    "wof:placetype":"venue"
},
  "geometry": {"coordinates":[-1.2064390182,39.5707588196],"type":"Point"}
}