{
  "type": "Feature",
  "properties": {
    "iso:country":"ES",
    "sg:address":"Plaz Espa\u00d1a, 8",
    "sg:city":"Don Benito",
    "sg:orig_category":"Loter\u00cda Y T\u00d3mbola",
    "sg:phone":"+34 924 80 19 82",
    "sg:postcode":"06400",
    "sg:province":"Badajoz",
    "wof:name":"Sosa Peralta Manuel Maria",
    "wof:placetype":"venue"
},
  "geometry": {"coordinates":[-5.8618412018,38.9534492493],"type":"Point"}
}