{
  "type": "Feature",
  "properties": {
    "addr:full":"Av Catalunya, S/n Alcarras Lleida 25180",
    "addr:housenumber":"s",
    "addr:postcode":"25180",
    "addr:street":"Av Catalunya;/ N",
    "iso:country":"ES",
    "sg:address":"Av Catalunya, S/n",
    "sg:city":"Alcarras",
    "sg:orig_category":"Negocio De Materiales De Construcci\u00d3n",
    "sg:phone":"+34 973 79 03 38",
    "sg:postcode":"25180",
    "sg:province":"Lleida",
    "wof:name":"Materials Par'a La Construccio Ramon Tomas S.l.",
    "wof:placetype":"venue"
},
  "geometry": {"coordinates":[0.5240309834,41.5609703064],"type":"Point"}
}