{
  "type": "Feature",
  "properties": {
    "iso:country":"ES",
    "sg:address":"Ptge Marimon Asprer, 9",
    "sg:city":"Bisbal D'emporda",
    "sg:orig_category":"Ense\u00d1anza, Formaci\u00d3n Profesional: Aprendizaje",
    "sg:phone":"+34 972 64 25 93",
    "sg:postcode":"17100",
    "sg:province":"Girona",
    "wof:name":"Ajuntament De La Bisbal D'emporda",
    "wof:placetype":"venue"
},
  "geometry": {"coordinates":[3.0425977707,41.9439201355],"type":"Point"}
}