{
  "type": "Feature",
  "properties": {
    "iso:country":"ES",
    "sg:address":"Carrer de Pau Casals, 35",
    "sg:city":"Santa Perpetua De Mogoda",
    "sg:orig_category":"Partidos Pol\u00cdticos",
    "sg:phone":"+34 935 74 23 42",
    "sg:postcode":"08130",
    "sg:province":"Barcelona",
    "wof:name":"Iniciativa Per Catalunya",
    "wof:placetype":"venue"
},
  "geometry": {"coordinates":[2.1815900803,41.5325813293],"type":"Point"}
}