{
  "type": "Feature",
  "properties": {
    "iso:country":"ES",
    "sg:address":"Calle de Aquitania, 28",
    "sg:city":"Madrid",
    "sg:orig_category":"Alquiler De V\u00cddeo",
    "sg:phone":"+34 913 13 45 02",
    "sg:postcode":"28032",
    "sg:province":"Madrid",
    "wof:name":"Rinvalle S.l.",
    "wof:placetype":"venue"
},
  "geometry": {"coordinates":[-3.6154606342,40.4196014404],"type":"Point"}
}