{
  "type": "Feature",
  "properties": {
    "iso:country":"ES",
    "sg:address":"Carrer de Carretera, 13",
    "sg:city":"Aldover",
    "sg:orig_category":"Frutas, Legumbres Frescas Y Tempranas (al Por Menor)",
    "sg:phone":"+34 977 47 32 04",
    "sg:postcode":"43591",
    "sg:province":"Tarragona",
    "wof:name":"Pegueroles Pla Bernando",
    "wof:placetype":"venue"
},
  "geometry": {"coordinates":[0.4988299906,40.8806762695],"type":"Point"}
}