{
  "type": "Feature",
  "properties": {
    "addr:full":"Calle de Mariano Benlliure, 79 Sevilla Sevilla 41005",
    "addr:housenumber":"79",
    "addr:postcode":"41005",
    "addr:street":"Calle De Mariano Benlliure",
    "iso:country":"ES",
    "sg:address":"Calle de Mariano Benlliure, 79",
    "sg:city":"Sevilla",
    "sg:orig_category":"Centros Pms (psico",
    "sg:phone":"+34 954 57 20 14",
    "sg:postcode":"41005",
    "sg:province":"Sevilla",
    "wof:name":"Enlaze Sicopedagogico S.l.l.",
    "wof:placetype":"venue"
},
  "geometry": {"coordinates":[-5.9624271393,37.3824768066],"type":"Point"}
}