{
  "type": "Feature",
  "properties": {
    "iso:country":"ES",
    "sg:address":"Avda Padre Garcia Tejero, 7",
    "sg:city":"Sevilla",
    "sg:orig_category":"Arquitectos",
    "sg:phone":"+34 954 23 67 35",
    "sg:postcode":"41012",
    "sg:province":"Sevilla",
    "wof:name":"Lisabesur Arquitectos S.l.",
    "wof:placetype":"venue"
},
  "geometry": {"coordinates":[-5.9841718674,37.356464386],"type":"Point"}
}