{
  "type": "Feature",
  "properties": {
    "addr:full":"Cieza, S/n Molina Segura Murcia 30500",
    "addr:housenumber":"s",
    "addr:postcode":"30500",
    "addr:street":"Cieza;/ N Molina",
    "iso:country":"ES",
    "sg:address":"Cieza, S/n",
    "sg:city":"Molina Segura",
    "sg:orig_category":"Edici\u00d3n De Diarios, Revistas, Boletines",
    "sg:phone":"+34 968 61 11 87",
    "sg:postcode":"30500",
    "sg:province":"Murcia",
    "wof:name":"Ediciones Rueda J.m.",
    "wof:placetype":"venue"
},
  "geometry": {"coordinates":[-1.1876089573,38.0405197144],"type":"Point"}
}