{
  "type": "Feature",
  "properties": {
    "addr:full":"Avda Constitucion (la), 55 Algodonales C\u00e1diz 11680",
    "addr:housenumber":"55",
    "addr:postcode":"11680",
    "addr:street":"Avda Constitucion La",
    "iso:country":"ES",
    "sg:address":"Avda Constitucion (la), 55",
    "sg:city":"Algodonales",
    "sg:orig_category":"M\u00c9dicos: Estomatolog\u00cda",
    "sg:phone":"+34 956 13 74 22",
    "sg:postcode":"11680",
    "sg:province":"C\u00e1diz",
    "wof:name":"Ramirez Rico Antonio",
    "wof:placetype":"venue"
},
  "geometry": {"coordinates":[-5.4073939323,36.8804740906],"type":"Point"}
}