{
  "type": "Feature",
  "properties": {
    "addr:full":"Carrer de Francesc Macia, 90 Granollers Barcelona 08401",
    "addr:housenumber":"90",
    "addr:postcode":"08401",
    "addr:street":"Carrer De Francesc Macia",
    "iso:country":"ES",
    "sg:address":"Carrer de Francesc Macia, 90",
    "sg:city":"Granollers",
    "sg:orig_category":"Carnes De Carnicer\u00cda (al Por Mayor)",
    "sg:phone":"+34 938 70 00 93",
    "sg:postcode":"08401",
    "sg:province":"Barcelona",
    "wof:name":"Ripoll Vila Juan",
    "wof:placetype":"venue"
},
  "geometry": {"coordinates":[2.2910189629,41.6129379272],"type":"Point"}
}