{
  "type": "Feature",
  "properties": {
    "iso:country":"ES",
    "sg:address":"Av Rapita (de La), 6",
    "sg:city":"Amposta",
    "sg:orig_category":"Peluquer\u00cdas, Peluquer\u00cda Mixta",
    "sg:phone":"+34 977 70 49 29",
    "sg:postcode":"43870",
    "sg:province":"Tarragona",
    "wof:name":"Baz Navas Maria Jesus",
    "wof:placetype":"venue"
},
  "geometry": {"coordinates":[0.5800060034,40.7117805481],"type":"Point"}
}