{
  "type": "Feature",
  "properties": {
    "addr:full":"Calle de Albuera, 12 Badajoz Badajoz 06010",
    "addr:housenumber":"12",
    "addr:postcode":"06010",
    "addr:street":"Calle De Albuera",
    "iso:country":"ES",
    "sg:address":"Calle de Albuera, 12",
    "sg:city":"Badajoz",
    "sg:orig_category":"Internados & Ense\u00d1anza Privada",
    "sg:phone":"+34 924 23 47 82",
    "sg:postcode":"06010",
    "sg:province":"Badajoz",
    "wof:name":"Congregacion De Siervas De San Jose",
    "wof:placetype":"venue"
},
  "geometry": {"coordinates":[-6.9605455399,38.8707122803],"type":"Point"}
}