{
  "type": "Feature",
  "properties": {
    "addr:full":"Carr Casas I Amigo, 33 Badalona Barcelona 08917",
    "addr:housenumber":"33",
    "addr:postcode":"08917",
    "addr:street":"Carr Casas;Amigo",
    "iso:country":"ES",
    "sg:address":"Carr Casas I Amigo, 33",
    "sg:city":"Badalona",
    "sg:orig_category":"Limpieza Con Chorro De Arena Y Con Granalla, Pulido",
    "sg:phone":"+34 934 60 49 00",
    "sg:postcode":"08917",
    "sg:province":"Barcelona",
    "wof:name":"Aznar Fuertes Jaime",
    "wof:placetype":"venue"
},
  "geometry": {"coordinates":[2.2349183559,41.4501533508],"type":"Point"}
}