{
  "type": "Feature",
  "properties": {
    "addr:full":"Polig. De A Estrada, S/n Toedo Pontevedra 36682",
    "addr:postcode":"36682",
    "addr:street":"S / N",
    "iso:country":"ES",
    "sg:address":"Polig. De A Estrada, S/n",
    "sg:city":"Toedo",
    "sg:orig_category":"Fabricaci\u00d3n Y Comercio De M\u00c1quinas",
    "sg:phone":"+34 986 57 15 64",
    "sg:postcode":"36682",
    "sg:province":"Pontevedra",
    "wof:name":"Duran Gonzalez Jose",
    "wof:placetype":"venue"
},
  "geometry": {"coordinates":[-8.4540214539,42.7098999023],"type":"Point"}
}