{
  "type": "Feature",
  "properties": {
    "iso:country":"ES",
    "sg:address":"Avda Tirajana (de), S/n",
    "sg:city":"Playa Del Ingles",
    "sg:orig_category":"Centros Empresariales",
    "sg:phone":"+34 928 73 04 72",
    "sg:postcode":"35100",
    "sg:province":"Las Palmas",
    "sg:website":"www.ax/business.com",
    "wof:name":"Marrero Consulting S.l.",
    "wof:placetype":"venue"
},
  "geometry": {"coordinates":[-15.5820684433,27.7611446381],"type":"Point"}
}