{
  "type": "Feature",
  "properties": {
    "addr:full":"Av Rafael Casanova, 70 Mollet Valles Barcelona 08100",
    "addr:housenumber":"70",
    "addr:postcode":"08100",
    "addr:street":"Av Rafael Casanova",
    "iso:country":"ES",
    "sg:address":"Av Rafael Casanova, 70",
    "sg:city":"Mollet Valles",
    "sg:orig_category":"Panader\u00cdas, Panader\u00cdas",
    "sg:phone":"+34 935 93 01 98",
    "sg:postcode":"08100",
    "sg:province":"Barcelona",
    "wof:name":"Giralt Pastisseria I Fleca S.l.",
    "wof:placetype":"venue"
},
  "geometry": {"coordinates":[2.2166249752,41.5438613892],"type":"Point"}
}