{
  "type": "Feature",
  "properties": {
    "addr:full":"Calle de Gonzalez Palencia, 1 Horcajo Santiago Cuenca 16410",
    "addr:housenumber":"1",
    "addr:postcode":"16410",
    "addr:street":"Calle De Gonzalez Palencia;Cuenca",
    "iso:country":"ES",
    "sg:address":"Calle de Gonzalez Palencia, 1",
    "sg:city":"Horcajo Santiago",
    "sg:orig_category":"Quincaller\u00cda (al Por Menor)",
    "sg:phone":"+34 969 12 70 26",
    "sg:postcode":"16410",
    "sg:province":"Cuenca",
    "wof:name":"Arquero Lopez-solorzano Maria Mercedes",
    "wof:placetype":"venue"
},
  "geometry": {"coordinates":[-2.9978642464,39.8414306641],"type":"Point"}
}