{
  "type": "Feature",
  "properties": {
    "addr:full":"Avda Asturias, 18 Guardo Palencia 34880",
    "addr:housenumber":"18",
    "addr:postcode":"34880",
    "addr:street":"Avda Asturias",
    "iso:country":"ES",
    "sg:address":"Avda Asturias, 18",
    "sg:city":"Guardo",
    "sg:orig_category":"Procuradores",
    "sg:phone":"+34 979 85 01 03",
    "sg:postcode":"34880",
    "sg:province":"Palencia",
    "wof:name":"Valbuena Rodriguez Ana Isabel",
    "wof:placetype":"venue"
},
  "geometry": {"coordinates":[-4.8438220024,42.7907028198],"type":"Point"}
}