{
  "type": "Feature",
  "properties": {
    "addr:full":"Calle de Toledo, 20 Zaragoza Zaragoza 50005",
    "addr:housenumber":"20",
    "addr:postcode":"50005",
    "addr:street":"Calle De Toledo",
    "iso:country":"ES",
    "sg:address":"Calle de Toledo, 20",
    "sg:city":"Zaragoza",
    "sg:orig_category":"Venta, Instalaci\u00d3n De Calefacci\u00d3n",
    "sg:phone":"+34 976 35 44 91",
    "sg:postcode":"50005",
    "sg:province":"Zaragoza",
    "wof:name":"Cooperativa Aragonesa De Fontaneria Y Calefaccion Coop. Ltda.",
    "wof:placetype":"venue"
},
  "geometry": {"coordinates":[-0.8967859745,41.6479263306],"type":"Point"}
}