{
  "type": "Feature",
  "properties": {
    "iso:country":"ES",
    "sg:address":"Calle de Maria Auxiliadora, 14",
    "sg:city":"Cordoba",
    "sg:orig_category":"Bisuter\u00cda, Joyer\u00cda, Relojer\u00cda (al Por Menor)",
    "sg:phone":"+34 957 47 55 58",
    "sg:postcode":"14002",
    "sg:province":"C\u00f3rdoba",
    "wof:name":"Conde Vera S.a.",
    "wof:placetype":"venue"
},
  "geometry": {"coordinates":[-4.7670907974,37.8892860413],"type":"Point"}
}