{
  "type": "Feature",
  "properties": {
    "addr:full":"Calle de Comuneros De Castilla, 12 Avila \u00c1vila 05001",
    "addr:housenumber":"12",
    "addr:postcode":"05001",
    "addr:street":"Calle De Comuneros De Castilla;A\u0301Vila",
    "iso:country":"ES",
    "sg:address":"Calle de Comuneros De Castilla, 12",
    "sg:city":"Avila",
    "sg:orig_category":"Ropa Para Caballeros (al Por Menor)",
    "sg:phone":"+34 920 21 14 56",
    "sg:postcode":"05001",
    "sg:province":"\u00c1vila",
    "wof:name":"Sanchez Hernandez Julian Jesus",
    "wof:placetype":"venue"
},
  "geometry": {"coordinates":[-4.6994776726,40.6562728882],"type":"Point"}
}