{
  "type": "Feature",
  "properties": {
    "iso:country":"ES",
    "sg:address":"Rua Falperra, 26",
    "sg:city":"Vigo",
    "sg:orig_category":"Alimentaci\u00d3n General (al Por Menor)",
    "sg:phone":"+34 986 43 50 72",
    "sg:postcode":"36202",
    "sg:province":"Pontevedra",
    "wof:name":"Martinez Fernandez Josefa",
    "wof:placetype":"venue"
},
  "geometry": {"coordinates":[-8.7286777496,42.2347145081],"type":"Point"}
}