{
  "type": "Feature",
  "properties": {
    "addr:full":"Carrer de Balmes, 418 Barcelona Barcelona 08022",
    "addr:housenumber":"418",
    "addr:postcode":"08022",
    "addr:street":"Carrer De Balmes",
    "iso:country":"ES",
    "sg:address":"Carrer de Balmes, 418",
    "sg:city":"Barcelona",
    "sg:orig_category":"Asesor\u00cda Sobre Comunicaci\u00d3n De Empresas",
    "sg:phone":"+34 932 12 50 52",
    "sg:postcode":"08022",
    "sg:province":"Barcelona",
    "wof:name":"Urquizus S.l.",
    "wof:placetype":"venue"
},
  "geometry": {"coordinates":[2.1387710571,41.4068870544],"type":"Point"}
}