{
  "type": "Feature",
  "properties": {
    "addr:full":"Plaz Constitucion, 12 Calera Y Chozas Toledo 45595",
    "addr:housenumber":"12",
    "addr:postcode":"45595",
    "addr:street":"Constitucion",
    "iso:country":"ES",
    "sg:address":"Plaz Constitucion, 12",
    "sg:city":"Calera Y Chozas",
    "sg:orig_category":"Cajas Para Embalar",
    "sg:phone":"+34 925 84 61 56",
    "sg:postcode":"45595",
    "sg:province":"Toledo",
    "wof:name":"Caja Rural Provincial De Toledo",
    "wof:placetype":"venue"
},
  "geometry": {"coordinates":[-5.0072097778,39.8687896729],"type":"Point"}
}