{
  "type": "Feature",
  "properties": {
    "iso:country":"ES",
    "sg:address":"Avda Diputacion (de La), S/n",
    "sg:city":"Cordoba",
    "sg:orig_category":"Carnicer\u00cdas, Carnicer\u00cdas",
    "sg:phone":"+34 957 29 14 50",
    "sg:postcode":"14009",
    "sg:province":"C\u00f3rdoba",
    "wof:name":"Alcaide Garcia Cristobal",
    "wof:placetype":"venue"
},
  "geometry": {"coordinates":[-4.7729821205,37.8734817505],"type":"Point"}
}