{
  "type": "Feature",
  "properties": {
    "iso:country":"ES",
    "sg:address":"Calle de Metalurgicos (los), S/n",
    "sg:city":"Cordoba",
    "sg:orig_category":"Pintura Y Barniz (al Por Menor)",
    "sg:phone":"+34 957 44 14 95",
    "sg:postcode":"14014",
    "sg:province":"C\u00f3rdoba",
    "sg:website":"www.tarracol.com",
    "wof:name":"Pinturas Tarracol S.l.",
    "wof:placetype":"venue"
},
  "geometry": {"coordinates":[-4.7590742111,37.9036560059],"type":"Point"}
}