{
  "type": "Feature",
  "properties": {
    "iso:country":"ES",
    "sg:address":"Calle de Correos, 11",
    "sg:city":"Valladolid",
    "sg:orig_category":"Empleado Administrativo",
    "sg:phone":"+34 983 37 41 68",
    "sg:postcode":"47001",
    "sg:province":"Valladolid",
    "wof:name":"Ortega Paunero Jesus",
    "wof:placetype":"venue"
},
  "geometry": {"coordinates":[-4.7295441628,41.653087616],"type":"Point"}
}