{
  "type": "Feature",
  "properties": {
    "iso:country":"ES",
    "sg:address":"Calle de Cura Palanca, 11",
    "sg:city":"Valencia",
    "sg:orig_category":"Sociedades, Compa\u00d1\u00cdas Aseguradoras",
    "sg:phone":"+34 963 73 00 71",
    "sg:postcode":"46013",
    "sg:province":"Valencia",
    "wof:name":"Valoraciones Arce S.l.",
    "wof:placetype":"venue"
},
  "geometry": {"coordinates":[-0.3667390049,39.4446296692],"type":"Point"}
}