{
  "type": "Feature",
  "properties": {
    "iso:country":"ES",
    "sg:address":"Calle de Juan Gonzalez, 2",
    "sg:city":"Uru\u00f1uela",
    "sg:orig_category":"Iglesia Cat\u00d3lica",
    "sg:phone":"+34 941 41 70 67",
    "sg:postcode":"26313",
    "sg:province":"La Rioja",
    "wof:name":"Parroquia De Los Santos Servando Y Ge",
    "wof:placetype":"venue"
},
  "geometry": {"coordinates":[-2.7073149681,42.4421806335],"type":"Point"}
}