{
  "type": "Feature",
  "properties": {
    "addr:full":"Avda Paz, 237 Yecla Murcia 30510",
    "addr:housenumber":"237",
    "addr:postcode":"30510",
    "addr:street":"Avda Paz",
    "iso:country":"ES",
    "sg:address":"Avda Paz, 237",
    "sg:city":"Yecla",
    "sg:orig_category":"Alquiler De Veh\u00cdculos: Turismos Y Utilitarios",
    "sg:phone":"+34 968 75 33 36",
    "sg:postcode":"30510",
    "sg:province":"Murcia",
    "wof:name":"Furgonetas Demetrio S.l.",
    "wof:placetype":"venue"
},
  "geometry": {"coordinates":[-1.1372890472,38.6116905212],"type":"Point"}
}