{
  "type": "Feature",
  "properties": {
    "addr:full":"La Vi\u00f1uela, S/n Atarfe Granada 18230",
    "addr:housenumber":"/ n",
    "addr:postcode":"18230",
    "addr:street":"Vin\u0303Uela S",
    "iso:country":"ES",
    "sg:address":"La Vi\u00f1uela, S/n",
    "sg:city":"Atarfe",
    "sg:orig_category":"Venta, Instalaci\u00d3n, Mantenimiento De Chimeneas De Interior Y Accesorios",
    "sg:phone":"+34 958 43 62 64",
    "sg:postcode":"18230",
    "sg:province":"Granada",
    "wof:name":"Robles Lopez Cristobal",
    "wof:placetype":"venue"
},
  "geometry": {"coordinates":[-3.6856389046,37.2198791504],"type":"Point"}
}