{
  "type": "Feature",
  "properties": {
    "addr:full":"Calle de Ayala, 67 Madrid Madrid 28001",
    "addr:housenumber":"67",
    "addr:postcode":"madrid;28001",
    "addr:street":"Calle De Ayala",
    "iso:country":"ES",
    "sg:address":"Calle de Ayala, 67",
    "sg:city":"Madrid",
    "sg:orig_category":"Arquitectos",
    "sg:phone":"+34 914 44 80 00",
    "sg:postcode":"28001",
    "sg:province":"Madrid",
    "wof:name":"Garcia Alvarez Angel",
    "wof:placetype":"venue"
},
  "geometry": {"coordinates":[-3.6765215397,40.4273643494],"type":"Point"}
}