{
  "type": "Feature",
  "properties": {
    "addr:full":"Calle de Sebastian Herrera, 12 Madrid Madrid 28012",
    "addr:housenumber":"12",
    "addr:postcode":"madrid;28012",
    "addr:street":"Calle De Sebastian Herrera",
    "iso:country":"ES",
    "sg:address":"Calle de Sebastian Herrera, 12",
    "sg:city":"Madrid",
    "sg:orig_category":"Empresarios",
    "sg:phone":"+34 914 68 02 58",
    "sg:postcode":"28012",
    "sg:province":"Madrid",
    "wof:name":"Maforem",
    "wof:placetype":"venue"
},
  "geometry": {"coordinates":[-3.6988899708,40.403881073],"type":"Point"}
}