{
  "type": "Feature",
  "properties": {
    "iso:country":"ES",
    "sg:address":"Calle de Santo Domingo, 6",
    "sg:city":"G\u00fcimar",
    "sg:orig_category":"Peluquer\u00cdas, Peluquer\u00cda Mixta",
    "sg:phone":"+34 922 51 38 47",
    "sg:postcode":"38500",
    "sg:province":"Santa Cruz De Tenerife",
    "wof:name":"Afonso Hernandez Luis Eduardo",
    "wof:placetype":"venue"
},
  "geometry": {"coordinates":[-16.4110164642,28.3152294159],"type":"Point"}
}