{
  "type": "Feature",
  "properties": {
    "addr:full":"Calle de Trobika, 1 Mungia Vizcaya 48100",
    "addr:housenumber":"1",
    "addr:postcode":"48100",
    "addr:street":"Calle De Trobika",
    "iso:country":"ES",
    "sg:address":"Calle de Trobika, 1",
    "sg:city":"Mungia",
    "sg:orig_category":"Ense\u00d1anza, Formaci\u00d3n Profesional: Aprendizaje",
    "sg:phone":"+34 946 15 55 54",
    "sg:postcode":"48100",
    "sg:province":"Vizcaya",
    "wof:name":"Ayuntamiento De Mungia",
    "wof:placetype":"venue"
},
  "geometry": {"coordinates":[-2.8465397358,43.3544082642],"type":"Point"}
}