{
  "type": "Feature",
  "properties": {
    "addr:full":"Corredoira, 11 Merca Ourense 32830",
    "addr:housenumber":"11",
    "addr:postcode":"32830",
    "addr:street":"Corredoira",
    "iso:country":"ES",
    "sg:address":"Corredoira, 11",
    "sg:city":"Merca",
    "sg:orig_category":"Peluquer\u00cdas, Peluquer\u00cda Mixta",
    "sg:phone":"+34 988 26 01 41",
    "sg:postcode":"32830",
    "sg:province":"Ourense",
    "wof:name":"Carrera Carrera Josefina",
    "wof:placetype":"venue"
},
  "geometry": {"coordinates":[-7.8844590187,42.2212905884],"type":"Point"}
}