{
  "type": "Feature",
  "properties": {
    "iso:country":"ES",
    "sg:address":"Carrer de Fusina, 6",
    "sg:city":"Barcelona",
    "sg:orig_category":"Caf\u00c9s, Bares, Cervecer\u00cdas",
    "sg:phone":"+34 933 10 06 67",
    "sg:postcode":"08003",
    "sg:province":"Barcelona",
    "wof:name":"Juez Juez Angel",
    "wof:placetype":"venue"
},
  "geometry": {"coordinates":[2.1836819649,41.3865699768],"type":"Point"}
}