{
  "type": "Feature",
  "properties": {
    "iso:country":"ES",
    "sg:address":"Ctra Nacional 620, Km. 0081,0",
    "sg:city":"Calabazanos",
    "sg:orig_category":"Empresas De Hormig\u00d3n, Hormig\u00d3n Armado Y Pretensado",
    "sg:phone":"+34 979 76 10 06",
    "sg:postcode":"34190",
    "sg:province":"Palencia",
    "wof:name":"Prephor S.a.",
    "wof:placetype":"venue"
},
  "geometry": {"coordinates":[-4.5164442062,41.9515914917],"type":"Point"}
}