{
  "type": "Feature",
  "properties": {
    "iso:country":"ES",
    "sg:address":"Trav De Gracia, 229",
    "sg:city":"Barcelona",
    "sg:orig_category":"Dietistas",
    "sg:phone":"+34 932 85 10 64",
    "sg:postcode":"08012",
    "sg:province":"Barcelona",
    "wof:name":"Housediet S.l. Sociedad Unipersonal",
    "wof:placetype":"venue"
},
  "geometry": {"coordinates":[2.1509625912,41.4051170349],"type":"Point"}
}