{
  "type": "Feature",
  "properties": {
    "iso:country":"ES",
    "sg:address":"Calle de Bego\u00d1ako Andra Mari, 19",
    "sg:city":"Arizgoiti",
    "sg:orig_category":"Peluqueros: De Se\u00d1oras",
    "sg:phone":"+34 944 40 49 79",
    "sg:postcode":"48970",
    "sg:province":"Vizcaya",
    "wof:name":"Yolanda Aresty Urquiaga Y Fernando Sanchez Ruiz C.b.",
    "wof:placetype":"venue"
},
  "geometry": {"coordinates":[-2.8861112595,43.2365646362],"type":"Point"}
}