{
  "type": "Feature",
  "properties": {
    "addr:full":"Calle de General Garcia Escamez, 1 Arrecife Las Palmas 35500",
    "addr:housenumber":"1",
    "addr:postcode":"35500",
    "addr:street":"Calle De General Garcia Escamez",
    "iso:country":"ES",
    "sg:address":"Calle de General Garcia Escamez, 1",
    "sg:city":"Arrecife",
    "sg:orig_category":"Distribuci\u00d3n De Petr\u00d3leo Y Derivados",
    "sg:phone":"+34 928 80 62 01",
    "sg:postcode":"35500",
    "sg:province":"Las Palmas",
    "wof:name":"Hijos De Rafael Ramirez C.b.",
    "wof:placetype":"venue"
},
  "geometry": {"coordinates":[-13.5527029037,28.9625167847],"type":"Point"}
}