{
  "type": "Feature",
  "properties": {
    "addr:full":"Calle de Perez Galdos, 5 Oviedo Asturias 33012",
    "addr:housenumber":"5",
    "addr:postcode":"33012",
    "addr:street":"Calle De Perez Galdos",
    "iso:country":"ES",
    "sg:address":"Calle de Perez Galdos, 5",
    "sg:city":"Oviedo",
    "sg:orig_category":"Ferreter\u00cda (diversos)",
    "sg:phone":"+34 985 11 62 42",
    "sg:postcode":"33012",
    "sg:province":"Asturias",
    "wof:name":"Fernandez Vega Raul Fermin",
    "wof:placetype":"venue"
},
  "geometry": {"coordinates":[-5.8872261047,43.3708267212],"type":"Point"}
}