{
  "type": "Feature",
  "properties": {
    "addr:full":"Plaz Foruen Enparantza, S/n Zumaia Guip\u00f9zcoa 20750",
    "addr:housenumber":"s / n",
    "addr:postcode":"20750",
    "addr:street":"Foruen Enparantza;Guipu\u0300Zcoa",
    "iso:country":"ES",
    "sg:address":"Plaz Foruen Enparantza, S/n",
    "sg:city":"Zumaia",
    "sg:orig_category":"Pescader\u00cdas (al Por Menor)",
    "sg:phone":"+34 943 86 10 46",
    "sg:postcode":"20750",
    "sg:province":"Guip\u00f9zcoa",
    "wof:name":"Balenciaga Zubia Pedro",
    "wof:placetype":"venue"
},
  "geometry": {"coordinates":[-2.2582139969,43.2965507507],"type":"Point"}
}