{
  "type": "Feature",
  "properties": {
    "addr:full":"Calle de Santiago, 1 Nietos Murcia 30383",
    "addr:housenumber":"1",
    "addr:postcode":"30383",
    "addr:street":"Calle De Santiago",
    "iso:country":"ES",
    "sg:address":"Calle de Santiago, 1",
    "sg:city":"Nietos",
    "sg:orig_category":"Cajas Para Embalar",
    "sg:phone":"+34 968 13 31 32",
    "sg:postcode":"30383",
    "sg:province":"Murcia",
    "wof:name":"Cajamar",
    "wof:placetype":"venue"
},
  "geometry": {"coordinates":[-0.8088939786,37.6547164917],"type":"Point"}
}