{
  "type": "Feature",
  "properties": {
    "iso:country":"ES",
    "sg:address":"Calle de Casta Alvarez, 74",
    "sg:city":"Zaragoza",
    "sg:orig_category":"Inversiones",
    "sg:phone":"+34 976 28 41 11",
    "sg:postcode":"50003",
    "sg:province":"Zaragoza",
    "wof:name":"Senogu S.l.",
    "wof:placetype":"venue"
},
  "geometry": {"coordinates":[-0.885438025,41.6573066711],"type":"Point"}
}