{
  "type": "Feature",
  "properties": {
    "addr:full":"Calle de Manzana, 6 Valladolid Valladolid 47001",
    "addr:postcode":"47001",
    "addr:street":"Calle De Manzana",
    "iso:country":"ES",
    "sg:address":"Calle de Manzana, 6",
    "sg:city":"Valladolid",
    "sg:orig_category":"Agencias De Viajes",
    "sg:phone":"+34 983 35 65 52",
    "sg:postcode":"47001",
    "sg:province":"Valladolid",
    "wof:name":"Viajes Y Expediciones S.l.",
    "wof:placetype":"venue"
},
  "geometry": {"coordinates":[-4.7281870842,41.6528244019],"type":"Point"}
}