{
  "type": "Feature",
  "properties": {
    "iso:country":"ES",
    "sg:address":"Calle de Peru, 4",
    "sg:city":"Valladolid",
    "sg:orig_category":"Muebles, Minoristas",
    "sg:phone":"+34 983 30 30 51",
    "sg:postcode":"47004",
    "sg:province":"Valladolid",
    "wof:name":"Vaquerizo Mu\u00f1oz Juan Pablo",
    "wof:placetype":"venue"
},
  "geometry": {"coordinates":[-4.7264318466,41.6480407715],"type":"Point"}
}