{
  "type": "Feature",
  "properties": {
    "iso:country":"ES",
    "sg:address":"Calle de Alhondiga (la), 21",
    "sg:city":"Sahagun",
    "sg:orig_category":"Abogados",
    "sg:phone":"+34 987 78 00 60",
    "sg:postcode":"24320",
    "sg:province":"Le\u00f3n",
    "wof:name":"Gomez Dominguez Eusebio Carlos",
    "wof:placetype":"venue"
},
  "geometry": {"coordinates":[-5.0296158791,42.3721733093],"type":"Point"}
}