{
  "type": "Feature",
  "properties": {
    "iso:country":"ES",
    "sg:address":"Pase Heriz De, 38",
    "sg:city":"Donostia-san Sebastian",
    "sg:orig_category":"Asilos De Ancianos. Centros Privados",
    "sg:phone":"+34 943 21 09 05",
    "sg:postcode":"20008",
    "sg:province":"Guip\u00f9zcoa",
    "wof:name":"Residencia San Rafael",
    "wof:placetype":"venue"
},
  "geometry": {"coordinates":[-2.0402700901,43.3095817566],"type":"Point"}
}