{
  "type": "Feature",
  "properties": {
    "addr:full":"Calle de Morse, 14 Getafe Madrid 28906",
    "addr:housenumber":"14",
    "addr:postcode":"28906",
    "addr:street":"Calle De Morse",
    "iso:country":"ES",
    "sg:address":"Calle de Morse, 14",
    "sg:city":"Getafe",
    "sg:orig_category":"Carnicer\u00cdas, Carnicer\u00cdas",
    "sg:phone":"+34 916 65 18 64",
    "sg:postcode":"28906",
    "sg:province":"Madrid",
    "wof:name":"Leyva E Hijos S.a.",
    "wof:placetype":"venue"
},
  "geometry": {"coordinates":[-3.7004818916,40.3015022278],"type":"Point"}
}