{
  "type": "Feature",
  "properties": {
    "iso:country":"ES",
    "sg:address":"Calle de Fernandez De Isla, 8",
    "sg:city":"Santander",
    "sg:orig_category":"Maquinaria Para Industrias Diversas",
    "sg:phone":"+34 942 21 17 03",
    "sg:postcode":"39008",
    "sg:province":"Cantabria",
    "wof:name":"Sedano Edilla Luis",
    "wof:placetype":"venue"
},
  "geometry": {"coordinates":[-3.8127720356,43.461315155],"type":"Point"}
}