{
  "type": "Feature",
  "properties": {
    "addr:full":"Cmno Alto De La Carrera, 9 Fuenlabrada Madrid 28942",
    "addr:postcode":"28942",
    "addr:street":"Cmno Alto De La Carrera 9",
    "iso:country":"ES",
    "sg:address":"Cmno Alto De La Carrera, 9",
    "sg:city":"Fuenlabrada",
    "sg:orig_category":"Frutas Y Legumbres Frescas (al Por Mayor)",
    "sg:phone":"+34 916 07 38 95",
    "sg:postcode":"28942",
    "sg:province":"Madrid",
    "wof:name":"Barruz Gomez Antonio",
    "wof:placetype":"venue"
},
  "geometry": {"coordinates":[-3.8238449097,40.2971115112],"type":"Point"}
}