{
  "type": "Feature",
  "properties": {
    "iso:country":"ES",
    "sg:address":"Carr Arraval, 10",
    "sg:city":"Mao",
    "sg:orig_category":"Aparatos De Iluminaci\u00d3n (al Por Menor)",
    "sg:phone":"+34 971 36 24 40",
    "sg:postcode":"07701",
    "sg:province":"Islas Baleares",
    "wof:name":"Lamparas Andi S. L.",
    "wof:placetype":"venue"
},
  "geometry": {"coordinates":[4.2652549744,39.8881340027],"type":"Point"}
}