{
  "type": "Feature",
  "properties": {
    "addr:full":"Calle de Simon Bolivar, 78 Coru\u00d1a A Coru\u00f1a 15011",
    "addr:housenumber":"78",
    "addr:postcode":"15011",
    "addr:street":"Calle De Simon Bolivar;Corun\u0303A",
    "iso:country":"ES",
    "sg:address":"Calle de Simon Bolivar, 78",
    "sg:city":"Coru\u00d1a",
    "sg:orig_category":"Pe\u00d1as Y Asociaciones Varias",
    "sg:phone":"+34 981 12 92 11",
    "sg:postcode":"15011",
    "sg:province":"A Coru\u00f1a",
    "wof:name":"Tau Promociones S. A.",
    "wof:placetype":"venue"
},
  "geometry": {"coordinates":[-8.4344091415,43.3721504211],"type":"Point"}
}