{
  "type": "Feature",
  "properties": {
    "iso:country":"ES",
    "sg:address":"S. Sebastia, 11",
    "sg:city":"Palafrugell",
    "sg:orig_category":"M\u00c9dicos: Estomatolog\u00cda",
    "sg:phone":"+34 972 30 37 54",
    "sg:postcode":"17200",
    "sg:province":"Girona",
    "wof:name":"Gaset Borras Enric",
    "wof:placetype":"venue"
},
  "geometry": {"coordinates":[3.1597599983,41.9181594849],"type":"Point"}
}