{
  "type": "Feature",
  "properties": {
    "addr:full":"Plaz Mayor, 3 Monreal Campo Teruel 44300",
    "addr:housenumber":"3",
    "addr:postcode":"44300",
    "addr:street":"Plaz Mayor",
    "iso:country":"ES",
    "sg:address":"Plaz Mayor, 3",
    "sg:city":"Monreal Campo",
    "sg:orig_category":"Producci\u00d3n De Abonos Y De Fertilizantes",
    "sg:phone":"+34 978 86 30 88",
    "sg:postcode":"44300",
    "sg:province":"Teruel",
    "wof:name":"Rizos Toran Antonio",
    "wof:placetype":"venue"
},
  "geometry": {"coordinates":[-1.3579939604,40.7872505188],"type":"Point"}
}