{
  "type": "Feature",
  "properties": {
    "addr:full":"Calle de San Esteban, 35 Alkotz Navarra 31797",
    "addr:housenumber":"35",
    "addr:postcode":"31797",
    "addr:street":"Calle De San Esteban",
    "iso:country":"ES",
    "sg:address":"Calle de San Esteban, 35",
    "sg:city":"Alkotz",
    "sg:orig_category":"Asilos De Ancianos. Centros Privados",
    "sg:phone":"+34 948 30 50 85",
    "sg:postcode":"31797",
    "sg:province":"Navarra",
    "wof:name":"Hermanas Mercedarias De La Caridad",
    "wof:placetype":"venue"
},
  "geometry": {"coordinates":[-1.6957390308,42.9793548584],"type":"Point"}
}