{
  "type": "Feature",
  "properties": {
    "addr:full":"Calle de Lizarra, 15 Irun Guip\u00f9zcoa 20305",
    "addr:housenumber":"15",
    "addr:postcode":"20305",
    "addr:street":"Calle De Lizarra;Guipu\u0300Zcoa",
    "iso:country":"ES",
    "sg:address":"Calle de Lizarra, 15",
    "sg:city":"Irun",
    "sg:orig_category":"Revisi\u00d3n, Reconstrucci\u00d3n De M\u00c1quinas Y Herramientas",
    "sg:phone":"+34 943 61 34 42",
    "sg:postcode":"20305",
    "sg:province":"Guip\u00f9zcoa",
    "wof:name":"Suministros Anaiak, S.l.",
    "wof:placetype":"venue"
},
  "geometry": {"coordinates":[-1.8134549856,43.3384437561],"type":"Point"}
}