{
  "type": "Feature",
  "properties": {
    "addr:full":"Calle de Sancho Ramirez, 9 Sabi\u00f1anigo Huesca 22600",
    "addr:housenumber":"9",
    "addr:postcode":"22600",
    "addr:street":"Calle De Sancho Ramirez",
    "iso:country":"ES",
    "sg:address":"Calle de Sancho Ramirez, 9",
    "sg:city":"Sabi\u00f1anigo",
    "sg:orig_category":"Electricidad: Instaladores",
    "sg:phone":"+34 974 48 15 66",
    "sg:postcode":"22600",
    "sg:province":"Huesca",
    "wof:name":"Usieto Valiente Eduardo",
    "wof:placetype":"venue"
},
  "geometry": {"coordinates":[-0.3627560139,42.5200004578],"type":"Point"}
}