{
  "type": "Feature",
  "properties": {
    "addr:full":"Ctra La Umbria, S/n Aracena Huelva 21200",
    "addr:housenumber":"s / n",
    "addr:postcode":"21200",
    "addr:street":"Ctra La Umbria",
    "iso:country":"ES",
    "sg:address":"Ctra La Umbria, S/n",
    "sg:city":"Aracena",
    "sg:orig_category":"Producci\u00d3n, Venta De Productos De Agricultura Biol\u00d3gica",
    "sg:phone":"+34 959 50 12 68",
    "sg:postcode":"21200",
    "sg:province":"Huelva",
    "wof:name":"La Huerta Del Llano S.l.",
    "wof:placetype":"venue"
},
  "geometry": {"coordinates":[-6.5612440109,37.8929443359],"type":"Point"}
}