{
  "type": "Feature",
  "properties": {
    "addr:full":"Plaz Callao, 4 Madrid Madrid 28013",
    "addr:postcode":"4 madrid;28013",
    "iso:country":"ES",
    "sg:address":"Plaz Callao, 4",
    "sg:city":"Madrid",
    "sg:orig_category":"Abogados",
    "sg:phone":"+34 915 31 40 57",
    "sg:postcode":"28013",
    "sg:province":"Madrid",
    "wof:name":"Alajarin Rodriguez Juan Antonio",
    "wof:placetype":"venue"
},
  "geometry": {"coordinates":[-3.7058765888,40.4198570251],"type":"Point"}
}