{
  "type": "Feature",
  "properties": {
    "addr:full":"Calle de San Pedro Bautista, 3 Avila \u00c1vila 05005",
    "addr:housenumber":"3",
    "addr:postcode":"05005",
    "addr:street":"Calle De San;Bautista;A\u0301Vila",
    "iso:country":"ES",
    "sg:address":"Calle de San Pedro Bautista, 3",
    "sg:city":"Avila",
    "sg:orig_category":"Cajas De Ahorro",
    "sg:phone":"+34 920 22 47 35",
    "sg:postcode":"05005",
    "sg:province":"\u00c1vila",
    "sg:website":"www.lacaixa.es",
    "wof:name":"Caixa D'estalvis I Pensions De Barcelona",
    "wof:placetype":"venue"
},
  "geometry": {"coordinates":[-4.6919369698,40.6581726074],"type":"Point"}
}