{
  "type": "Feature",
  "properties": {
    "addr:full":"Calle de Domingo Beltran De Otazu, 61 Vitoria-gasteiz \u00c1lava 01012",
    "addr:housenumber":"61",
    "addr:postcode":"01012",
    "addr:street":"Calle De Domingo Beltran De Otazu",
    "iso:country":"ES",
    "sg:address":"Calle de Domingo Beltran De Otazu, 61",
    "sg:city":"Vitoria-gasteiz",
    "sg:orig_category":"Producci\u00d3n, Distribuci\u00d3n De Electricidad",
    "sg:phone":"+34 945 22 67 54",
    "sg:postcode":"01012",
    "sg:province":"\u00c1lava",
    "wof:name":"Eguren Vitoria S. A.",
    "wof:placetype":"venue"
},
  "geometry": {"coordinates":[-2.6764090061,42.854598999],"type":"Point"}
}