{
  "type": "Feature",
  "properties": {
    "iso:country":"ES",
    "sg:address":"Carrer de Aribau, 318",
    "sg:city":"Barcelona",
    "sg:orig_category":"Sociedades, Compa\u00d1\u00cdas Aseguradoras",
    "sg:phone":"+34 932 41 92 22",
    "sg:postcode":"08006",
    "sg:province":"Barcelona",
    "wof:name":"Crespo Rodriguez Alejandro",
    "wof:placetype":"venue"
},
  "geometry": {"coordinates":[2.1456139088,41.3994178772],"type":"Point"}
}