{
  "type": "Feature",
  "properties": {
    "addr:full":"Calle de Bario, 19 Madrid Madrid 28021",
    "addr:housenumber":"19",
    "addr:postcode":"madrid;28021",
    "addr:street":"Calle De Bario",
    "iso:country":"ES",
    "sg:address":"Calle de Bario, 19",
    "sg:city":"Madrid",
    "sg:orig_category":"Centros Empresariales",
    "sg:phone":"+34 915 05 74 43",
    "sg:postcode":"28021",
    "sg:province":"Madrid",
    "wof:name":"Bernardos Carrasco Jose Luis",
    "wof:placetype":"venue"
},
  "geometry": {"coordinates":[-3.6780788898,40.3476333618],"type":"Point"}
}