{
  "type": "Feature",
  "properties": {
    "iso:country":"ES",
    "sg:address":"Psaj Mallol, 12",
    "sg:city":"Sevilla",
    "sg:orig_category":"Artes Gr\u00c1ficas, Artes Pl\u00c1sticas (curso)",
    "sg:phone":"+34 954 53 15 79",
    "sg:postcode":"41003",
    "sg:province":"Sevilla",
    "wof:name":"Artes Graficas Javier S.l.",
    "wof:placetype":"venue"
},
  "geometry": {"coordinates":[-5.9857258797,37.3971939087],"type":"Point"}
}