{
  "type": "Feature",
  "properties": {
    "addr:full":"Carretera De Villalba, 12 Aceuchal Badajoz 06207",
    "addr:housenumber":"12",
    "addr:postcode":"06207",
    "addr:street":"Carretera De Villalba",
    "iso:country":"ES",
    "sg:address":"Carretera De Villalba, 12",
    "sg:city":"Aceuchal",
    "sg:orig_category":"Comercio De Piezas De Recambio Y De Accesorios De Veh\u00cdculos, Veh\u00cdculos Industriales",
    "sg:phone":"+34 924 68 01 82",
    "sg:postcode":"06207",
    "sg:province":"Badajoz",
    "wof:name":"Ribera Colin Juan",
    "wof:placetype":"venue"
},
  "geometry": {"coordinates":[-6.4819889069,38.6452445984],"type":"Point"}
}