{
  "type": "Feature",
  "properties": {
    "addr:full":"Carr Sant Manuel, 29 Mao Islas Baleares 07702",
    "addr:housenumber":"29",
    "addr:postcode":"07702",
    "addr:street":"Carr Sant Manuel",
    "iso:country":"ES",
    "sg:address":"Carr Sant Manuel, 29",
    "sg:city":"Mao",
    "sg:orig_category":"Electricidad (montaje, Ensamblaje De Componentes)",
    "sg:phone":"+34 971 36 26 33",
    "sg:postcode":"07702",
    "sg:province":"Islas Baleares",
    "wof:name":"Instalaciones Galopa S.l.",
    "wof:placetype":"venue"
},
  "geometry": {"coordinates":[4.265625,39.8903694153],"type":"Point"}
}