{
  "type": "Feature",
  "properties": {
    "addr:full":"Calle de Alcalde Salorio Suarez, 25 Coru\u00d1a La Coru\u00f1a 15010",
    "addr:housenumber":"25",
    "addr:postcode":"15010",
    "addr:street":"Calle De Alcalde Salorio Suarez;La Corun\u0303A",
    "iso:country":"ES",
    "sg:address":"Calle de Alcalde Salorio Suarez, 25",
    "sg:city":"Coru\u00d1a",
    "sg:orig_category":"Encuadernaci\u00d3n E Impresi\u00d3n De Folletos",
    "sg:phone":"+34 981 14 19 89",
    "sg:postcode":"15010",
    "sg:province":"La Coru\u00f1a",
    "wof:name":"Fernandez Carballeira Adrian",
    "wof:placetype":"venue"
},
  "geometry": {"coordinates":[-8.4249277115,43.3590126038],"type":"Point"}
}