{
  "type": "Feature",
  "properties": {
    "addr:full":"Calle de Castellon, 26 Segorbe Castell\u00f3n 12400",
    "addr:housenumber":"26",
    "addr:postcode":"12400",
    "addr:street":"Calle De Castellon",
    "iso:country":"ES",
    "sg:address":"Calle de Castellon, 26",
    "sg:city":"Segorbe",
    "sg:orig_category":"Carnicer\u00cdas, Carnicer\u00cdas",
    "sg:phone":"+34 964 71 09 43",
    "sg:postcode":"12400",
    "sg:province":"Castell\u00f3n",
    "wof:name":"Hermanos Lara Cdad.",
    "wof:placetype":"venue"
},
  "geometry": {"coordinates":[-0.4889596105,39.84998703],"type":"Point"}
}