{
  "type": "Feature",
  "properties": {
    "iso:country":"ES",
    "sg:address":"Calle de Mairena, 25",
    "sg:city":"Alcala Guadaira",
    "sg:orig_category":"Cajas De Ahorro",
    "sg:phone":"+34 955 69 90 30",
    "sg:postcode":"41500",
    "sg:province":"Sevilla",
    "wof:name":"Monte De Piedad Y Caja De Ahorros De Huelva Y Sevilla",
    "wof:placetype":"venue"
},
  "geometry": {"coordinates":[-5.8426122665,37.33801651],"type":"Point"}
}