{
  "type": "Feature",
  "properties": {
    "iso:country":"ES",
    "sg:address":"Calle de Gaztelumendi, 23",
    "sg:city":"Getxo",
    "sg:orig_category":"Molduras, Junquillos, Listones Y Molduras Perforadas",
    "sg:phone":"+34 944 30 01 40",
    "sg:postcode":"48990",
    "sg:province":"Vizcaya",
    "wof:name":"Francisco Higuero Leon",
    "wof:placetype":"venue"
},
  "geometry": {"coordinates":[-3.0079579353,43.3553009033],"type":"Point"}
}