{
  "type": "Feature",
  "properties": {
    "iso:country":"ES",
    "sg:address":"Calle de Yeserias, 19",
    "sg:city":"Ontigola",
    "sg:orig_category":"Electricidad: Instaladores",
    "sg:phone":"+34 925 12 72 66",
    "sg:postcode":"45340",
    "sg:province":"Toledo",
    "wof:name":"Jomarfran Electricidad S.l.",
    "wof:placetype":"venue"
},
  "geometry": {"coordinates":[-3.5724930763,40.0047531128],"type":"Point"}
}