{
  "type": "Feature",
  "properties": {
    "addr:full":"Carrer de Pompeu Fabra, S/n Arenys Mar Barcelona 08350",
    "addr:housenumber":"s / n",
    "addr:postcode":"08350",
    "addr:street":"Carrer De Pompeu",
    "iso:country":"ES",
    "sg:address":"Carrer de Pompeu Fabra, S/n",
    "sg:city":"Arenys Mar",
    "sg:orig_category":"Aspiradoras Dom\u00c9sticas",
    "sg:phone":"+34 937 92 27 02",
    "sg:postcode":"08350",
    "sg:province":"Barcelona",
    "wof:name":"Autocosmetic Morecar S.l.",
    "wof:placetype":"venue"
},
  "geometry": {"coordinates":[2.5469250679,41.5859184265],"type":"Point"}
}