{
  "type": "Feature",
  "properties": {
    "iso:country":"ES",
    "sg:address":"Calle de Roman Perez, 37",
    "sg:city":"Isla Cristina",
    "sg:orig_category":"Abogados",
    "sg:phone":"+34 959 33 01 93",
    "sg:postcode":"21410",
    "sg:province":"Huelva",
    "wof:name":"Jimenez Casanova Jose Maria",
    "wof:placetype":"venue"
},
  "geometry": {"coordinates":[-7.3292341232,37.207988739],"type":"Point"}
}