{
  "type": "Feature",
  "properties": {
    "addr:full":"Avda Redondela, 114 Igrexa Pontevedra 36320",
    "addr:housenumber":"114",
    "addr:postcode":"36320",
    "addr:street":"Avda Redondela",
    "iso:country":"ES",
    "sg:address":"Avda Redondela, 114",
    "sg:city":"Igrexa",
    "sg:orig_category":"Aluminio Y Aleaciones (producci\u00d3n, Transformaci\u00d3n, Negocio)",
    "sg:phone":"+34 986 45 27 59",
    "sg:postcode":"36320",
    "sg:province":"Pontevedra",
    "wof:name":"Sistemas Acdeal S.l.",
    "wof:placetype":"venue"
},
  "geometry": {"coordinates":[-8.6428003311,42.4304618835],"type":"Point"}
}