{
  "type": "Feature",
  "properties": {
    "iso:country":"ES",
    "sg:address":"Calle de Gil Perez, 20",
    "sg:city":"Calasparra",
    "sg:orig_category":"Paletas",
    "sg:phone":"+34 968 72 00 80",
    "sg:postcode":"30420",
    "sg:province":"Murcia",
    "wof:name":"Agustin Jesus Y Jose Luis Moreno Navarro C B",
    "wof:placetype":"venue"
},
  "geometry": {"coordinates":[-1.7051223516,38.2263526917],"type":"Point"}
}