{
  "type": "Feature",
  "properties": {
    "iso:country":"ES",
    "sg:address":"Avda Iparragirre, 16",
    "sg:city":"Santurtzi",
    "sg:orig_category":"Ense\u00d1anza: Idiomas",
    "sg:phone":"+34 944 04 72 21",
    "sg:postcode":"48980",
    "sg:province":"Vizcaya",
    "wof:name":"Elvira Burgos Doval (academia Big Ben Centro)",
    "wof:placetype":"venue"
},
  "geometry": {"coordinates":[-3.0360040665,43.3321075439],"type":"Point"}
}