{
  "type": "Feature",
  "properties": {
    "addr:full":"Extramuros, S/n Campillos M\u00e1laga 29320",
    "addr:postcode":"29320",
    "addr:street":"Extramuros S / N;Ma\u0301Laga",
    "iso:country":"ES",
    "sg:address":"Extramuros, S/n",
    "sg:city":"Campillos",
    "sg:orig_category":"Bebidas",
    "sg:phone":"+34 952 72 22 66",
    "sg:postcode":"29320",
    "sg:province":"M\u00e1laga",
    "wof:name":"Oca\u00f1a Vazquez Francisco",
    "wof:placetype":"venue"
},
  "geometry": {"coordinates":[-4.8648881912,37.0370178223],"type":"Point"}
}