{
  "type": "Feature",
  "properties": {
    "addr:full":"Calle de Gerardo Diego, 12 Tarancon Cuenca 16400",
    "addr:housenumber":"12",
    "addr:postcode":"16400",
    "addr:street":"Calle De Gerardo Diego",
    "iso:country":"ES",
    "sg:address":"Calle de Gerardo Diego, 12",
    "sg:city":"Tarancon",
    "sg:orig_category":"Agencias Y Agentes Comerciales, Representantes",
    "sg:phone":"+34 969 32 49 14",
    "sg:postcode":"16400",
    "sg:province":"Cuenca",
    "wof:name":"Eldu Electroaplicaciones S.a.",
    "wof:placetype":"venue"
},
  "geometry": {"coordinates":[-3.0161249638,40.0163612366],"type":"Point"}
}