{
  "type": "Feature",
  "properties": {
    "addr:full":"Cmno Aldaieta, 1 Astrabudua Vizcaya 48950",
    "addr:housenumber":"1",
    "addr:postcode":"48950",
    "addr:street":"Cmno Aldaieta",
    "iso:country":"ES",
    "sg:address":"Cmno Aldaieta, 1",
    "sg:city":"Astrabudua",
    "sg:orig_category":"Abogados",
    "sg:phone":"+34 944 67 00 32",
    "sg:postcode":"48950",
    "sg:province":"Vizcaya",
    "wof:name":"Olaia Gutierrez Ruiz Y Suri\u00f1e Lambea Aurrecoechea C.b.",
    "wof:placetype":"venue"
},
  "geometry": {"coordinates":[-2.9842820168,43.3146133423],"type":"Point"}
}