{
  "type": "Feature",
  "properties": {
    "addr:full":"Carr Joan Maragall, 10 Planoles Girona 17535",
    "addr:housenumber":"10",
    "addr:postcode":"17535",
    "addr:street":"Carr Joan Maragall",
    "iso:country":"ES",
    "sg:address":"Carr Joan Maragall, 10",
    "sg:city":"Planoles",
    "sg:orig_category":"Material Y Herramientas Agr\u00cdcolas",
    "sg:phone":"+34 972 73 60 34",
    "sg:postcode":"17535",
    "sg:province":"Girona",
    "wof:name":"Constans Rosell Juan",
    "wof:placetype":"venue"
},
  "geometry": {"coordinates":[2.1047949791,42.3179397583],"type":"Point"}
}