{
  "type": "Feature",
  "properties": {
    "iso:country":"ES",
    "sg:address":"Trva Convento, 6",
    "sg:city":"Gijon",
    "sg:orig_category":"Formaci\u00d3n Continuada (variada)",
    "sg:phone":"+34 985 34 62 65",
    "sg:postcode":"33202",
    "sg:province":"Asturias",
    "wof:name":"Garcia Prieto Andres Avelino",
    "wof:placetype":"venue"
},
  "geometry": {"coordinates":[-5.6590452194,43.5406532288],"type":"Point"}
}