{
  "type": "Feature",
  "properties": {
    "addr:full":"Cllo Alguacil, 6 Madrid Madrid 28038",
    "addr:housenumber":"6",
    "addr:postcode":"28038",
    "addr:street":"Alguacil",
    "iso:country":"ES",
    "sg:address":"Cllo Alguacil, 6",
    "sg:city":"Madrid",
    "sg:orig_category":"Radiocomunicaciones, Telefon\u00cda M\u00d3vil, Radiomensajer\u00cda: Servicios, Comercializaci\u00d3n",
    "sg:phone":"+34 913 28 40 32",
    "sg:postcode":"28038",
    "sg:province":"Madrid",
    "wof:name":"Multiservicios Universal Hir S.l.",
    "wof:placetype":"venue"
},
  "geometry": {"coordinates":[-3.6630299091,40.3958892822],"type":"Point"}
}