{
  "type": "Feature",
  "properties": {
    "iso:country":"ES",
    "sg:address":"Carrer de Doctor Trueta, 41",
    "sg:city":"Barcelona",
    "sg:orig_category":"Alquiler De V\u00cddeo",
    "sg:phone":"+34 932 21 96 50",
    "sg:postcode":"08005",
    "sg:province":"Barcelona",
    "wof:name":"Procobam",
    "wof:placetype":"venue"
},
  "geometry": {"coordinates":[2.1937708855,41.391544342],"type":"Point"}
}