{
  "type": "Feature",
  "properties": {
    "iso:country":"ES",
    "sg:address":"Ptda Seniola, 68",
    "sg:city":"Javea",
    "sg:orig_category":"Negocio De Materiales De Construcci\u00d3n",
    "sg:phone":"+34 965 79 58 65",
    "sg:postcode":"03730",
    "sg:province":"Alicante",
    "wof:name":"Azulejos El Cruce S.l.",
    "wof:placetype":"venue"
},
  "geometry": {"coordinates":[0.1668650061,38.7890739441],"type":"Point"}
}