{
  "type": "Feature",
  "properties": {
    "iso:country":"ES",
    "sg:address":"Calle de Florencio Rodriguez, 3",
    "sg:city":"Pola De Siero",
    "sg:orig_category":"Arquitectos",
    "sg:phone":"+34 985 72 19 58",
    "sg:postcode":"33510",
    "sg:province":"Asturias",
    "wof:name":"Roces Arbesu Juan",
    "wof:placetype":"venue"
},
  "geometry": {"coordinates":[-5.6601881981,43.3928489685],"type":"Point"}
}