{
  "type": "Feature",
  "properties": {
    "iso:country":"ES",
    "sg:address":"Carrer de Antonio Gaudi, 8",
    "sg:city":"Sant Vicen\u00c7 Dels Horts",
    "sg:orig_category":"Internados & Ense\u00d1anza Privada",
    "sg:phone":"+34 936 56 15 69",
    "sg:postcode":"08620",
    "sg:province":"Barcelona",
    "wof:name":"Asociacion Catolica De Padres De Familia",
    "wof:placetype":"venue"
},
  "geometry": {"coordinates":[2.0099360943,41.3614616394],"type":"Point"}
}