{
  "type": "Feature",
  "properties": {
    "addr:full":"C/ Angel Guimera, 72 Salt Girona 17190",
    "addr:housenumber":"72",
    "addr:postcode":"17190",
    "addr:street":"C / Angel Guimera",
    "iso:country":"ES",
    "sg:address":"C/ Angel Guimera, 72",
    "sg:city":"Salt",
    "sg:orig_category":"Empresas De Pintura Y Revestimientos",
    "sg:phone":"+34 972 23 35 37",
    "sg:postcode":"17190",
    "sg:province":"Girona",
    "wof:name":"Gispert Monteis Juan",
    "wof:placetype":"venue"
},
  "geometry": {"coordinates":[2.790088892,41.9742279053],"type":"Point"}
}