{
  "type": "Feature",
  "properties": {
    "addr:full":"Avda Portugal, 41 Talavera Reina Toledo 45600",
    "addr:housenumber":"41",
    "addr:postcode":"45600",
    "addr:street":"Avda Portugal",
    "iso:country":"ES",
    "sg:address":"Avda Portugal, 41",
    "sg:city":"Talavera Reina",
    "sg:orig_category":"Cristaler\u00cdas",
    "sg:phone":"+34 925 72 22 06",
    "sg:postcode":"45600",
    "sg:province":"Toledo",
    "wof:name":"Cristalera Iberica S. L.",
    "wof:placetype":"venue"
},
  "geometry": {"coordinates":[-4.8432679176,39.9581565857],"type":"Point"}
}