{
  "type": "Feature",
  "properties": {
    "addr:full":"Calle de Aeronave, 13 Madrid Madrid 28042",
    "addr:housenumber":"13",
    "addr:postcode":"madrid;28042",
    "addr:street":"Calle De Aeronave",
    "iso:country":"ES",
    "sg:address":"Calle de Aeronave, 13",
    "sg:city":"Madrid",
    "sg:orig_category":"Lencer\u00cda Femenina, Corseter\u00cda, Trajes De Ba\u00d1o (al Por Menor)",
    "sg:phone":"+34 913 29 48 09",
    "sg:postcode":"28042",
    "sg:province":"Madrid",
    "wof:name":"Alcaraz Molina Clementina",
    "wof:placetype":"venue"
},
  "geometry": {"coordinates":[-3.5864257812,40.4704666138],"type":"Point"}
}