{
  "type": "Feature",
  "properties": {
    "iso:country":"ES",
    "sg:address":"Calle de Antonio Maura, 37",
    "sg:city":"Oviedo",
    "sg:orig_category":"Empresas De Carpinter\u00cda De Madera",
    "sg:phone":"+34 985 25 87 02",
    "sg:postcode":"33012",
    "sg:province":"Asturias",
    "wof:name":"Gonzalez Garcia Jose Maria",
    "wof:placetype":"venue"
},
  "geometry": {"coordinates":[-5.8630976677,43.3650779724],"type":"Point"}
}