{
  "type": "Feature",
  "properties": {
    "addr:full":"Calle de Canalejas, 8 Marmolejo Ja\u00e9n 23770",
    "addr:housenumber":"8",
    "addr:postcode":"23770",
    "addr:street":"Calle De Canalejas;Jae\u0301N",
    "iso:country":"ES",
    "sg:address":"Calle de Canalejas, 8",
    "sg:city":"Marmolejo",
    "sg:orig_category":"Droguer\u00cdas (al Por Menor)",
    "sg:phone":"+34 953 54 00 59",
    "sg:postcode":"23770",
    "sg:province":"Ja\u00e9n",
    "wof:name":"Navarro Garcia Antonio",
    "wof:placetype":"venue"
},
  "geometry": {"coordinates":[-4.1725506783,38.0460662842],"type":"Point"}
}