{
  "type": "Feature",
  "properties": {
    "addr:full":"Carr Comte De Ribagor\u00c7a, S/n Villarreal Castell\u00f3n 12540",
    "addr:housenumber":"s",
    "addr:postcode":"12540",
    "addr:street":"Carr Comte De Ribagorc\u0327A;/ N;Castello\u0301N",
    "iso:country":"ES",
    "sg:address":"Carr Comte De Ribagor\u00c7a, S/n",
    "sg:city":"Villarreal",
    "sg:orig_category":"Centros De Educaci\u00d3n Especial",
    "sg:phone":"+34 964 52 14 76",
    "sg:postcode":"12540",
    "sg:province":"Castell\u00f3n",
    "wof:name":"Ajuntament De Vila-real",
    "wof:placetype":"venue"
},
  "geometry": {"coordinates":[-0.1060564965,39.9410934448],"type":"Point"}
}