{
  "type": "Feature",
  "properties": {
    "iso:country":"ES",
    "sg:address":"Calle de Doctor Fleming, 15",
    "sg:city":"Baena",
    "sg:orig_category":"Librer\u00cdas",
    "sg:phone":"+34 957 67 16 27",
    "sg:postcode":"14850",
    "sg:province":"C\u00f3rdoba",
    "wof:name":"Libreria Alba S.l.",
    "wof:placetype":"venue"
},
  "geometry": {"coordinates":[-4.3182845116,37.6172943115],"type":"Point"}
}