{
  "type": "Feature",
  "properties": {
    "iso:country":"ES",
    "sg:address":"Trva Colombia, 7",
    "sg:city":"Toledo",
    "sg:orig_category":"Alimentaci\u00d3n General (al Por Menor)",
    "sg:phone":"+34 925 22 10 92",
    "sg:postcode":"45004",
    "sg:province":"Toledo",
    "sg:website":"www.paginasamarillas.es",
    "wof:name":"Toledhogar S.l.",
    "wof:placetype":"venue"
},
  "geometry": {"coordinates":[-4.0319771767,39.8675842285],"type":"Point"}
}