{
  "type": "Feature",
  "properties": {
    "addr:full":"Ctra De Benasque, S/n Seira Huesca 22463",
    "addr:housenumber":"s / n",
    "addr:postcode":"22463",
    "addr:street":"Ctra De Benasque",
    "iso:country":"ES",
    "sg:address":"Ctra De Benasque, S/n",
    "sg:city":"Seira",
    "sg:orig_category":"Asociaciones, Organismos Culturales Y Socioeducativos",
    "sg:phone":"+34 974 55 34 67",
    "sg:postcode":"22463",
    "sg:province":"Huesca",
    "wof:name":"Circulo Recreativo De Seira",
    "wof:placetype":"venue"
},
  "geometry": {"coordinates":[0.4295910001,42.4803733826],"type":"Point"}
}