{
  "type": "Feature",
  "properties": {
    "iso:country":"ES",
    "sg:address":"Afueras, S/n",
    "sg:city":"Sta. Eularia Riu",
    "sg:orig_category":"Inmobiliaria (agencias)",
    "sg:phone":"+34 971 33 17 47",
    "sg:postcode":"07840",
    "sg:province":"Islas Baleares",
    "wof:name":"Daniels  Ingeborg Anna",
    "wof:placetype":"venue"
},
  "geometry": {"coordinates":[1.5341850519,38.9850311279],"type":"Point"}
}