{
  "type": "Feature",
  "properties": {
    "addr:full":"Calle de Serreria, 5 Valencia Valencia 46022",
    "addr:housenumber":"5",
    "addr:postcode":"46022",
    "addr:street":"Calle De Serreria",
    "iso:country":"ES",
    "sg:address":"Calle de Serreria, 5",
    "sg:city":"Valencia",
    "sg:orig_category":"Comercio, Reparaci\u00d3n De Bicicletas, De Motocicletas, De Accesorios",
    "sg:phone":"+34 963 30 20 49",
    "sg:postcode":"46022",
    "sg:province":"Valencia",
    "wof:name":"Latorre Martinez Luis Javier",
    "wof:placetype":"venue"
},
  "geometry": {"coordinates":[-0.3378779888,39.4625320435],"type":"Point"}
}