{
  "type": "Feature",
  "properties": {
    "addr:full":"Carr Catalunya, S/n Eivissa Islas Baleares 07800",
    "addr:housenumber":"s / n",
    "addr:postcode":"07800",
    "addr:street":"Carr Catalunya",
    "iso:country":"ES",
    "sg:address":"Carr Catalunya, S/n",
    "sg:city":"Eivissa",
    "sg:orig_category":"Caf\u00c9s, Bares, Cervecer\u00cdas",
    "sg:phone":"+34 971 39 21 61",
    "sg:postcode":"07800",
    "sg:province":"Islas Baleares",
    "wof:name":"Jacobs  Jean Willy",
    "wof:placetype":"venue"
},
  "geometry": {"coordinates":[1.4266049862,38.9088363647],"type":"Point"}
}