{
  "type": "Feature",
  "properties": {
    "addr:full":"Calle de Rigoberto Cortejoso, 14 Valladolid Valladolid 47...",
    "addr:housenumber":"14",
    "addr:street":"Calle De Rigoberto Cortejoso;Valladolid",
    "iso:country":"ES",
    "sg:address":"Calle de Rigoberto Cortejoso, 14",
    "sg:city":"Valladolid",
    "sg:orig_category":"Ense\u00d1anza, Formaci\u00d3n Profesional: Aprendizaje",
    "sg:phone":"+34 983 41 99 88",
    "sg:postcode":"47...",
    "sg:province":"Valladolid",
    "wof:name":"Junta De Castilla Y Leon",
    "wof:placetype":"venue"
},
  "geometry": {"coordinates":[-4.7321238518,41.6541938782],"type":"Point"}
}