{
  "type": "Feature",
  "properties": {
    "addr:full":"Ctra. Estacion, S/n Marmolejo Ja\u00e9n 23770",
    "addr:postcode":"23770",
    "addr:street":"Ctra. Estacion S / N;Jae\u0301N",
    "iso:country":"ES",
    "sg:address":"Ctra. Estacion, S/n",
    "sg:city":"Marmolejo",
    "sg:orig_category":"Negocio De Materiales De Construcci\u00d3n",
    "sg:phone":"+34 953 54 06 05",
    "sg:postcode":"23770",
    "sg:province":"Ja\u00e9n",
    "wof:name":"Ruiz Pedregosa Pedro",
    "wof:placetype":"venue"
},
  "geometry": {"coordinates":[-4.1698541641,38.0398750305],"type":"Point"}
}