{
  "type": "Feature",
  "properties": {
    "iso:country":"ES",
    "sg:address":"Calle de Faican Aitami, 13",
    "sg:city":"Galdar",
    "sg:orig_category":"Abogados",
    "sg:phone":"+34 928 88 15 23",
    "sg:postcode":"35460",
    "sg:province":"Las Palmas",
    "wof:name":"Suarez Rodriguez Juan Manuel",
    "wof:placetype":"venue"
},
  "geometry": {"coordinates":[-15.6565122604,28.1441001892],"type":"Point"}
}