{
  "type": "Feature",
  "properties": {
    "addr:full":"Calle de Libertad (de La), 39 Navalcarnero Madrid 28600",
    "addr:housenumber":"39",
    "addr:postcode":"28600",
    "addr:street":"Calle De Libertad De La",
    "iso:country":"ES",
    "sg:address":"Calle de Libertad (de La), 39",
    "sg:city":"Navalcarnero",
    "sg:orig_category":"Asesor\u00cda Sobre Comunicaci\u00d3n De Empresas",
    "sg:phone":"+34 918 11 01 38",
    "sg:postcode":"28600",
    "sg:province":"Madrid",
    "wof:name":"A B Consulting Y Asesores S.l.",
    "wof:placetype":"venue"
},
  "geometry": {"coordinates":[-4.013492,40.290577],"type":"Point"}
}