{
  "type": "Feature",
  "properties": {
    "addr:full":"Calle de Hinojos, 41 Rociana Condado Huelva 21720",
    "addr:housenumber":"41",
    "addr:postcode":"21720",
    "addr:street":"Calle De Hinojos",
    "iso:country":"ES",
    "sg:address":"Calle de Hinojos, 41",
    "sg:city":"Rociana Condado",
    "sg:orig_category":"Promotores Constructores",
    "sg:phone":"+34 959 41 61 99",
    "sg:postcode":"21720",
    "sg:province":"Huelva",
    "wof:name":"Santana Martin Juan Antonio",
    "wof:placetype":"venue"
},
  "geometry": {"coordinates":[-6.5954117775,37.3082351685],"type":"Point"}
}