{
  "type": "Feature",
  "properties": {
    "iso:country":"ES",
    "sg:address":"Calle de Cubilla (la), S/n",
    "sg:city":"Ci\u00f1era",
    "sg:orig_category":"Empresas De Pintura Y Revestimientos",
    "sg:phone":"+34 987 58 42 51",
    "sg:postcode":"24660",
    "sg:province":"Le\u00f3n",
    "wof:name":"Renedo Merino Jose Maria",
    "wof:placetype":"venue"
},
  "geometry": {"coordinates":[-5.6372671127,42.8862304688],"type":"Point"}
}