{
  "type": "Feature",
  "properties": {
    "addr:full":"Ctra Crevillente, Km. 0003,0 Elche Alicante 03205",
    "addr:postcode":"03205",
    "addr:street":"Ctra Crevillente Km. 0003,0",
    "iso:country":"ES",
    "sg:address":"Ctra Crevillente, Km. 0003,0",
    "sg:city":"Elche",
    "sg:orig_category":"Alquiler De Veh\u00cdculos: Turismos Y Utilitarios",
    "sg:phone":"+34 965 43 72 74",
    "sg:postcode":"03205",
    "sg:province":"Alicante",
    "wof:name":"Diesel Car S.a.",
    "wof:placetype":"venue"
},
  "geometry": {"coordinates":[-0.7237690091,38.2598762512],"type":"Point"}
}