{
  "type": "Feature",
  "properties": {
    "iso:country":"ES",
    "sg:address":"Avda Ramon Y Cajal, 29",
    "sg:city":"Fuengirola",
    "sg:orig_category":"Construcciones Navales Y Fluviales",
    "sg:phone":"+34 952 46 64 04",
    "sg:postcode":"29640",
    "sg:province":"M\u00e1laga",
    "wof:name":"Dina 1 S.l.",
    "wof:placetype":"venue"
},
  "geometry": {"coordinates":[-4.619453907,36.5460510254],"type":"Point"}
}