{
  "type": "Feature",
  "properties": {
    "iso:country":"ES",
    "sg:address":"Avda Doctor Artero Guirao, 114",
    "sg:city":"S. Pedro Pinatar",
    "sg:orig_category":"Comercio, Reparaci\u00d3n De Motocicletas, Bicicletas Y Piezas Sueltas",
    "sg:phone":"+34 968 18 04 94",
    "sg:postcode":"30740",
    "sg:province":"Murcia",
    "wof:name":"Galera Saez Pedro",
    "wof:placetype":"venue"
},
  "geometry": {"coordinates":[-0.7918791175,37.8350524902],"type":"Point"}
}