{
  "type": "Feature",
  "properties": {
    "iso:country":"ES",
    "sg:address":"Calle de San Juan (de), 7",
    "sg:city":"Colmenar Oreja",
    "sg:orig_category":"Productores Recolectores, Venta Directa De Vinos",
    "sg:phone":"+34 918 94 31 50",
    "sg:postcode":"28380",
    "sg:province":"Madrid",
    "wof:name":"Sociedad Agraria De Transformacion",
    "wof:placetype":"venue"
},
  "geometry": {"coordinates":[-3.3911190033,40.1117630005],"type":"Point"}
}