{
  "type": "Feature",
  "properties": {
    "iso:country":"ES",
    "sg:address":"Carr Del Music Martinez Valls, 45",
    "sg:city":"Ontinyent",
    "sg:orig_category":"Perfumer\u00cda (al Por Menor)",
    "sg:phone":"+34 962 38 48 99",
    "sg:postcode":"46870",
    "sg:province":"Valencia",
    "wof:name":"Miguel Bercher Sl",
    "wof:placetype":"venue"
},
  "geometry": {"coordinates":[-0.6025270224,38.8235855103],"type":"Point"}
}