{
  "type": "Feature",
  "properties": {
    "iso:country":"ES",
    "sg:address":"Calle de San Modesto, 44",
    "sg:city":"Madrid",
    "sg:orig_category":"Doctores En Medicina",
    "sg:phone":"+34 917 29 00 55",
    "sg:postcode":"28034",
    "sg:province":"Madrid",
    "wof:name":"Murube Del Castillo Juan",
    "wof:placetype":"venue"
},
  "geometry": {"coordinates":[-3.6965949535,40.488494873],"type":"Point"}
}