{
  "type": "Feature",
  "properties": {
    "addr:full":"Avda Angeles (los), 28 Loja Granada 18300",
    "addr:housenumber":"28 loja",
    "addr:postcode":"18300",
    "addr:street":"Avda Angeles Los",
    "iso:country":"ES",
    "sg:address":"Avda Angeles (los), 28",
    "sg:city":"Loja",
    "sg:orig_category":"Peluqueros: De Se\u00d1oras",
    "sg:phone":"+34 958 32 42 73",
    "sg:postcode":"18300",
    "sg:province":"Granada",
    "wof:name":"Carrillo Barragan Emilio",
    "wof:placetype":"venue"
},
  "geometry": {"coordinates":[-4.1463308334,37.1651039124],"type":"Point"}
}