{
  "type": "Feature",
  "properties": {
    "iso:country":"ES",
    "sg:address":"Carrer de Circumval.lacio, 1",
    "sg:city":"Sot Dels Nostris",
    "sg:orig_category":"Rectificaci\u00d3n, Mecanizado, Fresado",
    "sg:phone":"+34 938 43 90 85",
    "sg:postcode":"08185",
    "sg:province":"Barcelona",
    "wof:name":"Ultilmaber S.c.t.",
    "wof:placetype":"venue"
},
  "geometry": {"coordinates":[2.2364370823,41.5926132202],"type":"Point"}
}