{
  "type": "Feature",
  "properties": {
    "addr:full":"Calle de Vasco De Gama, 37 Villanueva De La Ca\u00e7ada Madrid 28691",
    "addr:housenumber":"37",
    "addr:postcode":"28691",
    "addr:street":"Calle De Vasco De Gama",
    "iso:country":"ES",
    "sg:address":"Calle de Vasco De Gama, 37",
    "sg:city":"Villanueva De La Ca\u00e7ada",
    "sg:orig_category":"Ense\u00d1ante, Direcci\u00d3n",
    "sg:phone":"+34 918 15 65 18",
    "sg:postcode":"28691",
    "sg:province":"Madrid",
    "wof:name":"Fernandez Richart Maria Fe",
    "wof:placetype":"venue"
},
  "geometry": {"coordinates":[-4.0087108612,40.4502182007],"type":"Point"}
}