{
  "type": "Feature",
  "properties": {
    "iso:country":"ES",
    "sg:address":"Avda Gutierrez Mellado, S/n",
    "sg:city":"Molina Segura",
    "sg:orig_category":"Industria Qu\u00cdmica",
    "sg:phone":"+34 968 61 04 04",
    "sg:postcode":"30500",
    "sg:province":"Murcia",
    "wof:name":"Amex S. A.",
    "wof:placetype":"venue"
},
  "geometry": {"coordinates":[-1.2074112892,38.0630149841],"type":"Point"}
}