{
  "type": "Feature",
  "properties": {
    "addr:full":"Calle de Segundo Flores, 11 Mocejon Toledo 45270",
    "addr:housenumber":"11",
    "addr:postcode":"45270",
    "addr:street":"Calle De Segundo Flores",
    "iso:country":"ES",
    "sg:address":"Calle de Segundo Flores, 11",
    "sg:city":"Mocejon",
    "sg:orig_category":"Producci\u00d3n, Venta De Productos De Agricultura Biol\u00d3gica",
    "sg:phone":"+34 925 36 03 51",
    "sg:postcode":"45270",
    "sg:province":"Toledo",
    "wof:name":"Moreno Aparicio Felipe",
    "wof:placetype":"venue"
},
  "geometry": {"coordinates":[-3.9104309082,39.9402580261],"type":"Point"}
}