{
  "type": "Feature",
  "properties": {
    "iso:country":"ES",
    "sg:address":"Rua Lamas Carvajal, 6",
    "sg:city":"Ourense",
    "sg:orig_category":"Bisuter\u00cda, Joyer\u00cda, Relojer\u00cda (al Por Menor)",
    "sg:phone":"+34 988 22 98 45",
    "sg:postcode":"32005",
    "sg:province":"Ourense",
    "wof:name":"Fuentefria Pereira Manuel",
    "wof:placetype":"venue"
},
  "geometry": {"coordinates":[-7.8640608788,42.3363265991],"type":"Point"}
}