{
  "type": "Feature",
  "properties": {
    "iso:country":"ES",
    "sg:address":"Carrer de Francisco Rover, 2",
    "sg:city":"Palma",
    "sg:orig_category":"M\u00c9dicos: Cirug\u00cda Ortop\u00c9dica Y Traumatolog\u00cda",
    "sg:phone":"+34 971 75 75 53",
    "sg:postcode":"07003",
    "sg:province":"Islas Baleares",
    "wof:name":"Llorente Cuadrado Jose Antonio",
    "wof:placetype":"venue"
},
  "geometry": {"coordinates":[2.6470189095,39.5801086426],"type":"Point"}
}