{
  "type": "Feature",
  "properties": {
    "addr:full":"Calle de Pedro Ruiz, 30 Briviesca Burgos 09240",
    "addr:housenumber":"30",
    "addr:postcode":"09240",
    "addr:street":"Calle De Pedro Ruiz",
    "iso:country":"ES",
    "sg:address":"Calle de Pedro Ruiz, 30",
    "sg:city":"Briviesca",
    "sg:orig_category":"Caf\u00c9s, Bares, Cervecer\u00cdas",
    "sg:phone":"+34 947 59 28 61",
    "sg:postcode":"09240",
    "sg:province":"Burgos",
    "wof:name":"Alvarez Martin Jose Manuel",
    "wof:placetype":"venue"
},
  "geometry": {"coordinates":[-3.3222484589,42.5522613525],"type":"Point"}
}