{
  "type": "Feature",
  "properties": {
    "iso:country":"ES",
    "sg:address":"Calle de Flor (de La), 5",
    "sg:city":"Campo Real",
    "sg:orig_category":"Limpieza Con Chorro De Arena Y Con Granalla, Pulido",
    "sg:phone":"+34 918 73 34 34",
    "sg:postcode":"28510",
    "sg:province":"Madrid",
    "wof:name":"Fuente Garcia Tomas De La",
    "wof:placetype":"venue"
},
  "geometry": {"coordinates":[-3.3833420277,40.3382034302],"type":"Point"}
}