{
  "type": "Feature",
  "properties": {
    "iso:country":"ES",
    "sg:address":"Calle de Alfredo L Jones, 5",
    "sg:city":"Palmas De Gran Canaria",
    "sg:orig_category":"Centros Empresariales",
    "sg:phone":"+34 928 22 38 95",
    "sg:postcode":"35008",
    "sg:province":"Las Palmas",
    "wof:name":"Nevalainen  Urho",
    "wof:placetype":"venue"
},
  "geometry": {"coordinates":[-15.4309329987,28.1421432495],"type":"Point"}
}