{
  "type": "Feature",
  "properties": {
    "iso:country":"ES",
    "sg:address":"Carr Santa Anna, 78",
    "sg:city":"Estartit",
    "sg:orig_category":"Panader\u00cdas, Panader\u00cdas",
    "sg:phone":"+34 972 75 10 26",
    "sg:postcode":"17258",
    "sg:province":"Girona",
    "wof:name":"Brugues Costabella Jose",
    "wof:placetype":"venue"
},
  "geometry": {"coordinates":[3.1995449066,42.053730011],"type":"Point"}
}