{
  "type": "Feature",
  "properties": {
    "addr:full":"Carrer de Riera, 57 Barriada Nova Barcelona 08420",
    "addr:housenumber":"57",
    "addr:postcode":"08420",
    "addr:street":"Carrer De Riera;Nova Barcelona",
    "iso:country":"ES",
    "sg:address":"Carrer de Riera, 57",
    "sg:city":"Barriada Nova",
    "sg:orig_category":"Estancos",
    "sg:phone":"+34 938 49 45 61",
    "sg:postcode":"08420",
    "sg:province":"Barcelona",
    "wof:name":"Forns Asturgo Rosa",
    "wof:placetype":"venue"
},
  "geometry": {"coordinates":[2.2780098915,41.6220703125],"type":"Point"}
}