{
  "type": "Feature",
  "properties": {
    "iso:country":"ES",
    "sg:address":"Calle de General Solchaga, 32",
    "sg:city":"Valladolid",
    "sg:orig_category":"Ferreter\u00cda (diversos)",
    "sg:phone":"+34 983 22 24 88",
    "sg:postcode":"47008",
    "sg:province":"Valladolid",
    "wof:name":"Prensal S.a.",
    "wof:placetype":"venue"
},
  "geometry": {"coordinates":[-4.7328629494,41.6290550232],"type":"Point"}
}