{
  "type": "Feature",
  "properties": {
    "iso:country":"ES",
    "sg:address":"Calle de Arroyo De Las Pilillas, 24",
    "sg:city":"Madrid",
    "sg:orig_category":"Estilistas Y Estudios De Estilo De Corte Y Confecci\u00d3n",
    "sg:phone":"+34 914 37 87 68",
    "sg:postcode":"28030",
    "sg:province":"Madrid",
    "wof:name":"Marty S. A.",
    "wof:placetype":"venue"
},
  "geometry": {"coordinates":[-3.6505868435,40.4082221985],"type":"Point"}
}