{
  "type": "Feature",
  "properties": {
    "addr:full":"Calle de Virgen Del Rosario, 12 Nules Castell\u00f3n 12520",
    "addr:housenumber":"12",
    "addr:postcode":"12520",
    "addr:street":"Calle De Virgen Del Rosario",
    "iso:country":"ES",
    "sg:address":"Calle de Virgen Del Rosario, 12",
    "sg:city":"Nules",
    "sg:orig_category":"C\u00c1maras De Comercio E Industria, Oficios, Agricultura",
    "sg:phone":"+34 964 67 20 06",
    "sg:postcode":"12520",
    "sg:province":"Castell\u00f3n",
    "wof:name":"Teinsa Cdad",
    "wof:placetype":"venue"
},
  "geometry": {"coordinates":[-0.1541839987,39.8532981873],"type":"Point"}
}