{
  "type": "Feature",
  "properties": {
    "addr:full":"Calle de Alfonso Diaz De Bustamante, 1 Caceres C\u00e1ceres 10001",
    "addr:housenumber":"1",
    "addr:postcode":"10001",
    "addr:street":"Calle De Alfonso Diaz De Bustamante;Ca\u0301Ceres",
    "iso:country":"ES",
    "sg:address":"Calle de Alfonso Diaz De Bustamante, 1",
    "sg:city":"Caceres",
    "sg:orig_category":"M\u00c9dicos: Neumolog\u00cda",
    "sg:phone":"+34 927 23 94 04",
    "sg:postcode":"10001",
    "sg:province":"C\u00e1ceres",
    "wof:name":"Masa Jimenez Juan Fernando",
    "wof:placetype":"venue"
},
  "geometry": {"coordinates":[-6.3898634911,39.4736480713],"type":"Point"}
}