{
  "type": "Feature",
  "properties": {
    "addr:full":"Calle de America, 2 Almeria Almer\u00eda 04007",
    "addr:housenumber":"2",
    "addr:postcode":"04007",
    "addr:street":"Calle De America",
    "iso:country":"ES",
    "sg:address":"Calle de America, 2",
    "sg:city":"Almeria",
    "sg:orig_category":"Artes Gr\u00c1ficas, Artes Pl\u00c1sticas: Material Y Suministros (al Por Menor)",
    "sg:phone":"+34 950 24 33 29",
    "sg:postcode":"04007",
    "sg:province":"Almer\u00eda",
    "wof:name":"Lusace Hispania S.l.unipersonal",
    "wof:placetype":"venue"
},
  "geometry": {"coordinates":[-2.4554936886,36.8311042786],"type":"Point"}
}