{
  "type": "Feature",
  "properties": {
    "addr:full":"Calle de Marruecos, S/n Jerez De La Frontera C\u00e1diz 11408",
    "addr:housenumber":"s",
    "addr:postcode":"11408",
    "addr:street":"Calle De Marruecos;/ N",
    "iso:country":"ES",
    "sg:address":"Calle de Marruecos, S/n",
    "sg:city":"Jerez De La Frontera",
    "sg:orig_category":"Estudios, Instalaci\u00d3n De Climatizaci\u00d3n",
    "sg:phone":"+34 956 14 41 77",
    "sg:postcode":"11408",
    "sg:province":"C\u00e1diz",
    "wof:name":"Humiclima Sur S.l.",
    "wof:placetype":"venue"
},
  "geometry": {"coordinates":[-6.1277570724,36.6631965637],"type":"Point"}
}