{
  "type": "Feature",
  "properties": {
    "iso:country":"ES",
    "sg:address":"Calle de Jamerdana, 2",
    "sg:city":"Sevilla",
    "sg:orig_category":"Regalos, Souvenires (fabricaci\u00d3n, Al Por Mayor)",
    "sg:phone":"+34 954 22 71 22",
    "sg:postcode":"41004",
    "sg:province":"Sevilla",
    "wof:name":"Jamerdana S.c.",
    "wof:placetype":"venue"
},
  "geometry": {"coordinates":[-5.9899630547,37.3854637146],"type":"Point"}
}