{
  "type": "Feature",
  "properties": {
    "addr:full":"Pulimentadoras, 16 Almansa Albacete 02640",
    "addr:housenumber":"16",
    "addr:postcode":"02640",
    "addr:street":"Pulimentadoras",
    "iso:country":"ES",
    "sg:address":"Pulimentadoras, 16",
    "sg:city":"Almansa",
    "sg:orig_category":"Zapatos: Material, Suministros, Accesorios (fabricaci\u00d3n, Al Por Mayor)",
    "sg:phone":"+34 967 34 04 69",
    "sg:postcode":"02640",
    "sg:province":"Albacete",
    "wof:name":"Schuh Plant S.l.",
    "wof:placetype":"venue"
},
  "geometry": {"coordinates":[-1.0956139565,38.8690605164],"type":"Point"}
}