{
  "type": "Feature",
  "properties": {
    "addr:full":"Calle de Profesor Lozano, 7 Palmas De Gran Canaria Las Palmas 35008",
    "addr:housenumber":"7",
    "addr:postcode":"35008",
    "addr:street":"Calle De Profesor Lozano",
    "iso:country":"ES",
    "sg:address":"Calle de Profesor Lozano, 7",
    "sg:city":"Palmas De Gran Canaria",
    "sg:orig_category":"Inversiones",
    "sg:phone":"+34 928 46 85 16",
    "sg:postcode":"35008",
    "sg:province":"Las Palmas",
    "wof:name":"Informaciones Canarias S.a.",
    "wof:placetype":"venue"
},
  "geometry": {"coordinates":[-15.4210786819,28.1545696259],"type":"Point"}
}