{
  "type": "Feature",
  "properties": {
    "iso:country":"ES",
    "sg:address":"Calle de Matias Perello, 55",
    "sg:city":"Valencia",
    "sg:orig_category":"Laboratorios Farmac\u00c9uticos",
    "sg:phone":"+34 963 74 14 66",
    "sg:postcode":"46005",
    "sg:province":"Valencia",
    "wof:name":"Bugeda Cabrera Antonio",
    "wof:placetype":"venue"
},
  "geometry": {"coordinates":[-0.3651939929,39.4627227783],"type":"Point"}
}