{
  "type": "Feature",
  "properties": {
    "iso:country":"ES",
    "sg:address":"Calle de Jardin De Los Alcores, S/n",
    "sg:city":"Mairena Alcor",
    "sg:orig_category":"Promotores Constructores",
    "sg:phone":"+34 955 94 36 43",
    "sg:postcode":"41510",
    "sg:province":"Sevilla",
    "wof:name":"Dosevi Sl",
    "wof:placetype":"venue"
},
  "geometry": {"coordinates":[-5.7530040741,37.3657035828],"type":"Point"}
}