{
  "type": "Feature",
  "properties": {
    "iso:country":"ES",
    "sg:address":"Ctra Valls, 79",
    "sg:city":"Vendrell",
    "sg:classifiers":[
        {
            "category":"Autos & Motor Vehicles",
            "subcategory":"Automobile Sales",
            "type":"Retail Goods"
        }
    ],
    "sg:phone":"+34 977 66 59 02",
    "sg:postcode":"43700",
    "sg:province":"Tarragona",
    "wof:name":"Auto-escola El Tancat S.l.",
    "wof:placetype":"venue"
},
  "geometry": {"coordinates":[1.5324639082,41.2257499695],"type":"Point"}
}