{
  "type": "Feature",
  "properties": {
    "iso:country":"ES",
    "sg:address":"Crta Motril Cruce Padul(p I La Paloma), Km. 0151,0",
    "sg:city":"Padul",
    "sg:orig_category":"Empresas De Carpinter\u00cda Met\u00c1lica",
    "sg:phone":"+34 958 79 07 66",
    "sg:postcode":"18640",
    "sg:province":"Granada",
    "wof:name":"Jose Padial Fernandez Y Otro C.b.",
    "wof:placetype":"venue"
},
  "geometry": {"coordinates":[-3.6279389858,37.0232009888],"type":"Point"}
}