{
  "type": "Feature",
  "properties": {
    "addr:full":"Ctra Palacios, Km. 0001,0 Utrera Sevilla 41710",
    "addr:postcode":"41710",
    "addr:street":"Ctra Palacios Km. 0001,0",
    "iso:country":"ES",
    "sg:address":"Ctra Palacios, Km. 0001,0",
    "sg:city":"Utrera",
    "sg:orig_category":"Contenedores (mercanc\u00cdas)",
    "sg:phone":"+34 954 86 19 19",
    "sg:postcode":"41710",
    "sg:province":"Sevilla",
    "wof:name":"Cotrau Sociedad Cooperativa Andaluza De Utrera",
    "wof:placetype":"venue"
},
  "geometry": {"coordinates":[-5.779173851,37.184223175],"type":"Point"}
}