{
  "type": "Feature",
  "properties": {
    "iso:country":"ES",
    "sg:address":"Calle de Galicia, 29",
    "sg:city":"Pto. Rosario",
    "sg:orig_category":"Organizaciones Internacionales",
    "sg:phone":"+34 928 85 94 78",
    "sg:postcode":"35600",
    "sg:province":"Las Palmas",
    "wof:name":"Asociacion Coordinadora Insular De Caritas De Fuerteventura",
    "wof:placetype":"venue"
},
  "geometry": {"coordinates":[-13.8711462021,28.5037078857],"type":"Point"}
}