{
  "type": "Feature",
  "properties": {
    "iso:country":"ES",
    "sg:address":"Rond Amantes, 1",
    "sg:city":"Puigmoreno",
    "sg:orig_category":"Frutas Y Legumbres Frescas (al Por Mayor)",
    "sg:phone":"+34 978 83 81 59",
    "sg:postcode":"44660",
    "sg:province":"Teruel",
    "wof:name":"Frutas Y Hermanos Soler.s.c.",
    "wof:placetype":"venue"
},
  "geometry": {"coordinates":[-1.1069096327,40.3441085815],"type":"Point"}
}