{
  "type": "Feature",
  "properties": {
    "addr:full":"Plaz Media Legua, 1 Nonduermas Murcia 30166",
    "addr:housenumber":"1",
    "addr:postcode":"30166",
    "addr:street":"Media Legua",
    "iso:country":"ES",
    "sg:address":"Plaz Media Legua, 1",
    "sg:city":"Nonduermas",
    "sg:orig_category":"Estancos",
    "sg:phone":"+34 968 25 04 14",
    "sg:postcode":"30166",
    "sg:province":"Murcia",
    "wof:name":"Vigueras Ruiz Josefa",
    "wof:placetype":"venue"
},
  "geometry": {"coordinates":[-1.1673840284,37.9729614258],"type":"Point"}
}