{
  "type": "Feature",
  "properties": {
    "iso:country":"ES",
    "sg:address":"Calle de Pasteur, 32",
    "sg:city":"Poligono Industrial Los Villares",
    "sg:orig_category":"Empresas De Carpinter\u00cda De Madera",
    "sg:phone":"+34 923 20 46 43",
    "sg:postcode":"37184",
    "sg:province":"Salamanca",
    "wof:name":"Carpinteria Y Ebanisteria Stilo Sl",
    "wof:placetype":"venue"
},
  "geometry": {"coordinates":[-5.6423239708,40.9885482788],"type":"Point"}
}