{
  "type": "Feature",
  "properties": {
    "addr:full":"Calle de Calixto Iii, 2 Valencia Valencia 46008",
    "addr:housenumber":"2",
    "addr:postcode":"46008",
    "addr:street":"Calle De Calixto Iii",
    "iso:country":"ES",
    "sg:address":"Calle de Calixto Iii, 2",
    "sg:city":"Valencia",
    "sg:orig_category":"Ropa Para Se\u00d1oras (al Por Menor)",
    "sg:phone":"+34 963 84 86 78",
    "sg:postcode":"46008",
    "sg:province":"Valencia",
    "wof:name":"March Andreu Maria Carmen",
    "wof:placetype":"venue"
},
  "geometry": {"coordinates":[-0.3870176971,39.4721336365],"type":"Point"}
}