{
  "type": "Feature",
  "properties": {
    "addr:full":"Calle de Cocherito De Bilbao, 13 Bilbao Vizcaya 48004",
    "addr:housenumber":"13",
    "addr:postcode":"48004",
    "addr:street":"Calle De Cocherito De Bilbao",
    "iso:country":"ES",
    "sg:address":"Calle de Cocherito De Bilbao, 13",
    "sg:city":"Bilbao",
    "sg:orig_category":"Cultos Diversos",
    "sg:phone":"+34 944 12 36 16",
    "sg:postcode":"48004",
    "sg:province":"Vizcaya",
    "wof:name":"Testigos Cristianos De Jehova",
    "wof:placetype":"venue"
},
  "geometry": {"coordinates":[-2.9098987579,43.2539787292],"type":"Point"}
}