{
  "type": "Feature",
  "properties": {
    "iso:country":"ES",
    "sg:address":"Plaz Andalucia, S/n",
    "sg:city":"Pozo Alcon",
    "sg:orig_category":"Ense\u00d1anza, Formaci\u00d3n Profesional: Aprendizaje",
    "sg:phone":"+34 953 71 82 93",
    "sg:postcode":"23485",
    "sg:province":"Ja\u00e9n",
    "wof:name":"Junta De Andalucia-consejeria De Cultura",
    "wof:placetype":"venue"
},
  "geometry": {"coordinates":[-2.936218977,37.7044410706],"type":"Point"}
}