{
  "type": "Feature",
  "properties": {
    "addr:full":"Av Almassera (l'), 29 San Vicente Del Raspeig-sant Vicent Del Raspeig Alicante 03690",
    "addr:housenumber":"29",
    "addr:postcode":"03690",
    "addr:street":"Av Almassera L '",
    "iso:country":"ES",
    "sg:address":"Av Almassera (l'), 29",
    "sg:city":"San Vicente Del Raspeig-sant Vicent Del Raspeig",
    "sg:orig_category":"Promotores Constructores",
    "sg:phone":"+34 965 66 53 47",
    "sg:postcode":"03690",
    "sg:province":"Alicante",
    "wof:name":"Torrealicante S.l.",
    "wof:placetype":"venue"
},
  "geometry": {"coordinates":[-0.513858974,38.395565033],"type":"Point"}
}