{
  "type": "Feature",
  "properties": {
    "addr:full":"Calle de Juan Pedro Gutierrez Higueras, S/n Jaen Ja\u00e9n 23005",
    "addr:housenumber":"/ n;jae\u0301n",
    "addr:postcode":"23005",
    "addr:street":"Calle De Juan;Higueras S",
    "iso:country":"ES",
    "sg:address":"Calle de Juan Pedro Gutierrez Higueras, S/n",
    "sg:city":"Jaen",
    "sg:orig_category":"Arquitectos",
    "sg:phone":"+34 953 22 13 93",
    "sg:postcode":"23005",
    "sg:province":"Ja\u00e9n",
    "wof:name":"Martinez Carrillo Manuel",
    "wof:placetype":"venue"
},
  "geometry": {"coordinates":[-3.7949440479,37.7755508423],"type":"Point"}
}