{
  "type": "Feature",
  "properties": {
    "iso:country":"ES",
    "sg:address":"Albuixech, S/n",
    "sg:city":"Museros",
    "sg:orig_category":"Cajas Y Embalajes De Madera",
    "sg:phone":"+34 961 45 20 62",
    "sg:postcode":"46136",
    "sg:province":"Valencia",
    "sg:website":"www.navarropascual.com",
    "wof:name":"Navarro Pascual S.l.",
    "wof:placetype":"venue"
},
  "geometry": {"coordinates":[-0.3382639885,39.5550193787],"type":"Point"}
}