{
  "type": "Feature",
  "properties": {
    "addr:full":"Trenbidearen Zumardia, 17 Azkoitia Guip\u00f9zcoa 20720",
    "addr:housenumber":"17",
    "addr:postcode":"20720",
    "addr:street":"Trenbidearen Zumardia;Guipu\u0300Zcoa",
    "iso:country":"ES",
    "sg:address":"Trenbidearen Zumardia, 17",
    "sg:city":"Azkoitia",
    "sg:orig_category":"Ingeniero",
    "sg:phone":"+34 943 00 00 02",
    "sg:postcode":"20720",
    "sg:province":"Guip\u00f9zcoa",
    "wof:name":"Urkain, S.l.",
    "wof:placetype":"venue"
},
  "geometry": {"coordinates":[-2.3068089485,43.1764183044],"type":"Point"}
}