{
  "type": "Feature",
  "properties": {
    "addr:full":"Ctra. Pamplona, S/n Sang\u00fcesa Navarra 31400",
    "addr:housenumber":"s / n",
    "addr:postcode":"31400",
    "addr:street":"Ctra. Pamplona",
    "iso:country":"ES",
    "sg:address":"Ctra. Pamplona, S/n",
    "sg:city":"Sang\u00fcesa",
    "sg:orig_category":"Papel (al Por Mayor)",
    "sg:phone":"+34 948 87 10 70",
    "sg:postcode":"31400",
    "sg:province":"Navarra",
    "wof:name":"Manipulados Irati S. A.",
    "wof:placetype":"venue"
},
  "geometry": {"coordinates":[-1.2806440592,42.5711250305],"type":"Point"}
}