{
  "type": "Feature",
  "properties": {
    "iso:country":"ES",
    "sg:address":"Calle de Camino Viejo De Elda, 18",
    "sg:city":"Petrer",
    "sg:orig_category":"Frutas Y Legumbres Frescas (al Por Mayor)",
    "sg:phone":"+34 965 37 49 76",
    "sg:postcode":"03610",
    "sg:province":"Alicante",
    "wof:name":"Caparros Hernandez Manuel",
    "wof:placetype":"venue"
},
  "geometry": {"coordinates":[-0.7835199833,38.4820823669],"type":"Point"}
}