{
  "type": "Feature",
  "properties": {
    "addr:full":"Calle de Doctor Jose Babe Delgado, 1 Alacant Alicante 03013",
    "addr:housenumber":"1",
    "addr:postcode":"03013",
    "addr:street":"Calle De Doctor Jose Babe Delgado",
    "iso:country":"ES",
    "sg:address":"Calle de Doctor Jose Babe Delgado, 1",
    "sg:city":"Alacant",
    "sg:orig_category":"Reposter\u00cdas",
    "sg:phone":"+34 965 26 62 17",
    "sg:postcode":"03013",
    "sg:province":"Alicante",
    "wof:name":"Cayuelas Alcaraz Alberto",
    "wof:placetype":"venue"
},
  "geometry": {"coordinates":[-0.4750092924,38.3564414978],"type":"Point"}
}