{
  "type": "Feature",
  "properties": {
    "addr:full":"Carrer de Bejar, 61 Barcelona Barcelona 08014",
    "addr:housenumber":"61",
    "addr:postcode":"08014",
    "addr:street":"Carrer De Bejar",
    "iso:country":"ES",
    "sg:address":"Carrer de Bejar, 61",
    "sg:city":"Barcelona",
    "sg:orig_category":"Material Y Suministros Para Fotocopiadoras, Reprograf\u00cda",
    "sg:phone":"+34 933 25 95 99",
    "sg:postcode":"08014",
    "sg:province":"Barcelona",
    "sg:website":"www.xerox.es",
    "wof:name":"Electronic Data System Espa\u00d1a S.a.",
    "wof:placetype":"venue"
},
  "geometry": {"coordinates":[2.1445560455,41.3777046204],"type":"Point"}
}