{
  "type": "Feature",
  "properties": {
    "addr:full":"Avda Remedios (los), 9 Realejo Alto Santa Cruz De Tenerife 38410",
    "addr:housenumber":"9",
    "addr:postcode":"38410",
    "addr:street":"Avda Remedios Los",
    "iso:country":"ES",
    "sg:address":"Avda Remedios (los), 9",
    "sg:city":"Realejo Alto",
    "sg:orig_category":"Ense\u00d1anza Variada",
    "sg:phone":"+34 922 34 54 06",
    "sg:postcode":"38410",
    "sg:province":"Santa Cruz De Tenerife",
    "wof:name":"Audio Studio S.l.",
    "wof:placetype":"venue"
},
  "geometry": {"coordinates":[-16.5832672119,28.380859375],"type":"Point"}
}