{
  "type": "Feature",
  "properties": {
    "addr:full":"Avda Alfonso X El Sabio, 13 Ciudad Real Ciudad Real 13001",
    "addr:housenumber":"13",
    "addr:postcode":"13001",
    "addr:street":"Avda Alfonso X El Sabio",
    "iso:country":"ES",
    "sg:address":"Avda Alfonso X El Sabio, 13",
    "sg:city":"Ciudad Real",
    "sg:orig_category":"Art\u00cdculos De Regalo (al Por Menor)",
    "sg:phone":"+34 926 21 15 49",
    "sg:postcode":"13001",
    "sg:province":"Ciudad Real",
    "wof:name":"Novoa Gonzalez Luis",
    "wof:placetype":"venue"
},
  "geometry": {"coordinates":[-3.9291229248,38.9842567444],"type":"Point"}
}