{
  "type": "Feature",
  "properties": {
    "iso:country":"ES",
    "sg:address":"Calle de Molinos, 1",
    "sg:city":"Campillos",
    "sg:orig_category":"Negocio De Materiales De Construcci\u00d3n",
    "sg:phone":"+34 952 72 22 17",
    "sg:postcode":"29320",
    "sg:province":"M\u00e1laga",
    "wof:name":"Hermanos Gallardo C.b.",
    "wof:placetype":"venue"
},
  "geometry": {"coordinates":[-4.8658342361,37.0474395752],"type":"Point"}
}