{
  "type": "Feature",
  "properties": {
    "iso:country":"ES",
    "sg:address":"Av Josep Tarradellas, 120",
    "sg:city":"Barcelona",
    "sg:orig_category":"Asesor\u00cda Sobre Comunicaci\u00d3n De Empresas",
    "sg:phone":"+34 934 10 73 28",
    "sg:postcode":"08029",
    "sg:province":"Barcelona",
    "wof:name":"Merino Nogales Begona",
    "wof:placetype":"venue"
},
  "geometry": {"coordinates":[2.1441969872,41.3911514282],"type":"Point"}
}