{
  "type": "Feature",
  "properties": {
    "addr:full":"Avda Portugal, 91 Golada Pontevedra 36379",
    "addr:housenumber":"91",
    "addr:postcode":"36379",
    "addr:street":"Avda Portugal",
    "iso:country":"ES",
    "sg:address":"Avda Portugal, 91",
    "sg:city":"Golada",
    "sg:orig_category":"Sanatorios M\u00c9dico",
    "sg:phone":"+34 986 35 26 00",
    "sg:postcode":"36379",
    "sg:province":"Pontevedra",
    "wof:name":"Sergas-atencion Primaria Area Sur Pontevedra",
    "wof:placetype":"venue"
},
  "geometry": {"coordinates":[-8.8124990463,42.1194648743],"type":"Point"}
}