{
  "type": "Feature",
  "properties": {
    "addr:full":"Calle de Secretario Carretero, 5 Cordoba C\u00f3rdoba 14004",
    "addr:housenumber":"5",
    "addr:postcode":"14004",
    "addr:street":"Calle De Secretario Carretero;Co\u0301Rdoba",
    "iso:country":"ES",
    "sg:address":"Calle de Secretario Carretero, 5",
    "sg:city":"Cordoba",
    "sg:orig_category":"M\u00c9dicos: Estomatolog\u00cda",
    "sg:phone":"+34 957 23 78 81",
    "sg:postcode":"14004",
    "sg:province":"C\u00f3rdoba",
    "wof:name":"Bellido Mu\u00f1oz Juan",
    "wof:placetype":"venue"
},
  "geometry": {"coordinates":[-4.7873029709,37.8848152161],"type":"Point"}
}