{
  "type": "Feature",
  "properties": {
    "iso:country":"ES",
    "sg:address":"Calle de Mar Mediterraneo (del), 40",
    "sg:city":"Poligono De San Fernando De Henares",
    "sg:orig_category":"Farmacias (repartici\u00d3n Y Al Por Mayor)",
    "sg:phone":"+34 916 77 38 63",
    "sg:postcode":"28830",
    "sg:province":"Madrid",
    "wof:name":"Almacenes Farmaceuticos Madrile\u00f1os S.a.",
    "wof:placetype":"venue"
},
  "geometry": {"coordinates":[-3.5366938114,40.4255332947],"type":"Point"}
}