{
  "type": "Feature",
  "properties": {
    "iso:country":"ES",
    "sg:address":"Carrer de Santa Cecilia, 5",
    "sg:city":"Sabadell",
    "sg:orig_category":"Iglesia Cat\u00d3lica",
    "sg:phone":"+34 937 12 33 30",
    "sg:postcode":"08204",
    "sg:province":"Barcelona",
    "wof:name":"Comunidad Franciscana",
    "wof:placetype":"venue"
},
  "geometry": {"coordinates":[2.1151230335,41.530254364],"type":"Point"}
}