{
  "type": "Feature",
  "properties": {
    "addr:full":"Carrer de Joan Marti, 10 S. Boi Llobregat Barcelona 08830",
    "addr:housenumber":"10",
    "addr:postcode":"08830",
    "addr:street":"Carrer De Joan Marti",
    "iso:country":"ES",
    "sg:address":"Carrer de Joan Marti, 10",
    "sg:city":"S. Boi Llobregat",
    "sg:orig_category":"M\u00c9dicos: Estomatolog\u00cda",
    "sg:phone":"+34 936 54 08 51",
    "sg:postcode":"08830",
    "sg:province":"Barcelona",
    "wof:name":"Traveria Morato Juan",
    "wof:placetype":"venue"
},
  "geometry": {"coordinates":[2.0349299908,41.3468284607],"type":"Point"}
}