{
  "type": "Feature",
  "properties": {
    "addr:full":"Calle de Carlos Sainz (de), 19 Leganes Madrid 28914",
    "addr:housenumber":"19",
    "addr:postcode":"28914",
    "addr:street":"Calle De Carlos Sainz De",
    "iso:country":"ES",
    "sg:address":"Calle de Carlos Sainz (de), 19",
    "sg:city":"Leganes",
    "sg:orig_category":"Alquiler De Veh\u00cdculos: Turismos Y Utilitarios",
    "sg:phone":"+34 914 98 72 27",
    "sg:postcode":"28914",
    "sg:province":"Madrid",
    "wof:name":"Lider Lease S.l.l.",
    "wof:placetype":"venue"
},
  "geometry": {"coordinates":[-3.7647750378,40.3177566528],"type":"Point"}
}