{
  "type": "Feature",
  "properties": {
    "iso:country":"ES",
    "sg:address":"Rua Magdalena, 33",
    "sg:city":"Ferrol",
    "sg:orig_category":"Peluqueros: De Se\u00d1oras",
    "sg:phone":"+34 981 35 04 86",
    "sg:postcode":"15402",
    "sg:province":"La Coru\u00f1a",
    "wof:name":"Sangiao Carneiro Purificacion",
    "wof:placetype":"venue"
},
  "geometry": {"coordinates":[-8.2300567627,43.4845962524],"type":"Point"}
}