{
  "type": "Feature",
  "properties": {
    "iso:country":"ES",
    "sg:address":"Calle de Polvoranca, 108",
    "sg:city":"Alcorcon",
    "sg:orig_category":"Bares, Piano",
    "sg:phone":"+34 916 43 69 28",
    "sg:postcode":"28923",
    "sg:province":"Madrid",
    "wof:name":"Mugica Rubio Jose Antonio",
    "wof:placetype":"venue"
},
  "geometry": {"coordinates":[-3.8189640045,40.3410415649],"type":"Point"}
}