{
  "type": "Feature",
  "properties": {
    "addr:full":"Carrer de Torreta, 44 S. Pere Ribes Barcelona 08810",
    "addr:housenumber":"44",
    "addr:postcode":"08810",
    "addr:street":"Carrer De Torreta;S. Pere Ribes Barcelona",
    "iso:country":"ES",
    "sg:address":"Carrer de Torreta, 44",
    "sg:city":"S. Pere Ribes",
    "sg:orig_category":"Comerciantes Al Por Mayor De Vinos, Licores Y Alcoholes",
    "sg:phone":"+34 938 96 34 03",
    "sg:postcode":"08810",
    "sg:province":"Barcelona",
    "wof:name":"Artigas Guasch Adoracion",
    "wof:placetype":"venue"
},
  "geometry": {"coordinates":[1.7771786451,41.2592201233],"type":"Point"}
}