{
  "type": "Feature",
  "properties": {
    "addr:full":"Rua Porta Da Vila, 10 Muros La Coru\u00f1a 15250",
    "addr:housenumber":"10",
    "addr:postcode":"15250",
    "addr:street":"Rua Porta Da Vila;La Corun\u0303A",
    "iso:country":"ES",
    "sg:address":"Rua Porta Da Vila, 10",
    "sg:city":"Muros",
    "sg:orig_category":"Sociedades, Compa\u00d1\u00cdas Aseguradoras",
    "sg:phone":"+34 981 76 21 00",
    "sg:postcode":"15250",
    "sg:province":"La Coru\u00f1a",
    "wof:name":"Mapfre Servicios De Informatica",
    "wof:placetype":"venue"
},
  "geometry": {"coordinates":[-9.0576505661,42.7748222351],"type":"Point"}
}