{
  "type": "Feature",
  "properties": {
    "addr:full":"Calle de Campomanes, 18 Oviedo Asturias 33008",
    "addr:housenumber":"18",
    "addr:postcode":"33008",
    "addr:street":"Calle De Campomanes",
    "iso:country":"ES",
    "sg:address":"Calle de Campomanes, 18",
    "sg:city":"Oviedo",
    "sg:orig_category":"Psic\u00d3logos",
    "sg:phone":"+34 985 22 93 44",
    "sg:postcode":"33008",
    "sg:province":"Asturias",
    "wof:name":"Pe\u00f1a Pesquera Graciela",
    "wof:placetype":"venue"
},
  "geometry": {"coordinates":[-5.845664978,43.358631134],"type":"Point"}
}