{
  "type": "Feature",
  "properties": {
    "iso:country":"ES",
    "sg:address":"Calle de Cea Bermudez, 24",
    "sg:city":"Madrid",
    "sg:orig_category":"Arquitectos",
    "sg:phone":"+34 914 56 05 77",
    "sg:postcode":"28003",
    "sg:province":"Madrid",
    "wof:name":"Martin De Lucio, Arquitectos",
    "wof:placetype":"venue"
},
  "geometry": {"coordinates":[-3.7084593773,40.4388237],"type":"Point"}
}