{
  "type": "Feature",
  "properties": {
    "iso:country":"ES",
    "sg:address":"Calle de Rafael Altamira, 26",
    "sg:city":"Alacant",
    "sg:orig_category":"Laboratorios Y Trabajos De Fotograf\u00cda, V\u00cddeo Y Cine",
    "sg:phone":"+34 965 21 69 25",
    "sg:postcode":"03002",
    "sg:province":"Alicante",
    "wof:name":"Fotocolor Altamira S.l.",
    "wof:placetype":"venue"
},
  "geometry": {"coordinates":[-0.4815790057,38.3449287415],"type":"Point"}
}