{
  "type": "Feature",
  "properties": {
    "addr:full":"Calle de Elche, 51 Santa Pola Alicante 03130",
    "addr:housenumber":"51",
    "addr:postcode":"03130",
    "addr:street":"Calle De Elche",
    "iso:country":"ES",
    "sg:address":"Calle de Elche, 51",
    "sg:city":"Santa Pola",
    "sg:orig_category":"Importaci\u00d3n",
    "sg:phone":"+34 966 69 23 37",
    "sg:postcode":"03130",
    "sg:province":"Alicante",
    "wof:name":"Congelados Ibermar S.l.",
    "wof:placetype":"venue"
},
  "geometry": {"coordinates":[-0.5565090179,38.190448761],"type":"Point"}
}