{
  "type": "Feature",
  "properties": {
    "addr:full":"Calle de Desfiladero De Los Arrudos, 8 Gijon Asturias 33211",
    "addr:housenumber":"8",
    "addr:postcode":"33211",
    "addr:street":"Calle De Desfiladero De Los Arrudos",
    "iso:country":"ES",
    "sg:address":"Calle de Desfiladero De Los Arrudos, 8",
    "sg:city":"Gijon",
    "sg:orig_category":"Electricidad: Instaladores",
    "sg:phone":"+34 985 30 16 08",
    "sg:postcode":"33211",
    "sg:province":"Asturias",
    "wof:name":"Instalaciones Electricas Sorbi S.l.",
    "wof:placetype":"venue"
},
  "geometry": {"coordinates":[-5.6803474426,43.5376815796],"type":"Point"}
}