{
  "type": "Feature",
  "properties": {
    "addr:full":"Carrer de Angel Guimera, 9 Manresa Barcelona 08241",
    "addr:housenumber":"9",
    "addr:postcode":"08241",
    "addr:street":"Carrer De Angel Guimera",
    "iso:country":"ES",
    "sg:address":"Carrer de Angel Guimera, 9",
    "sg:city":"Manresa",
    "sg:orig_category":"Ropa Para Se\u00d1oras Y Caballeros (al Por Menor)",
    "sg:phone":"+34 938 72 29 90",
    "sg:postcode":"08241",
    "sg:province":"Barcelona",
    "sg:website":"www.massimodutti.com",
    "wof:name":"Grupo Massimo Dutti S A",
    "wof:placetype":"venue"
},
  "geometry": {"coordinates":[1.8243670464,41.7257232666],"type":"Point"}
}