{
  "type": "Feature",
  "properties": {
    "addr:full":"Av Catalunya, 10 Anglesola Lleida 25320",
    "addr:housenumber":"10",
    "addr:postcode":"25320",
    "addr:street":"Av Catalunya",
    "iso:country":"ES",
    "sg:address":"Av Catalunya, 10",
    "sg:city":"Anglesola",
    "sg:orig_category":"Cajas De Ahorro",
    "sg:phone":"+34 973 30 82 91",
    "sg:postcode":"25320",
    "sg:province":"Lleida",
    "wof:name":"Caixa D'estalvis De Catalunya",
    "wof:placetype":"venue"
},
  "geometry": {"coordinates":[1.0837850571,41.6582374573],"type":"Point"}
}