{
  "type": "Feature",
  "properties": {
    "addr:full":"Calle de Alexander Fleming, 1 Errenteria Guip\u00f9zcoa 20100",
    "addr:housenumber":"1",
    "addr:postcode":"20100",
    "addr:street":"Calle De Alexander Fleming;Guipu\u0300Zcoa",
    "iso:country":"ES",
    "sg:address":"Calle de Alexander Fleming, 1",
    "sg:city":"Errenteria",
    "sg:orig_category":"Panader\u00cdas, Panader\u00cdas",
    "sg:phone":"+34 943 11 91 46",
    "sg:postcode":"20100",
    "sg:province":"Guip\u00f9zcoa",
    "wof:name":"Maria Angeles Hilera Ba\u00f1ares",
    "wof:placetype":"venue"
},
  "geometry": {"coordinates":[-1.8915777206,43.3102989197],"type":"Point"}
}