{
  "type": "Feature",
  "properties": {
    "iso:country":"ES",
    "sg:address":"Calle de Angeles (los), 7",
    "sg:city":"Cehegin",
    "sg:classifiers":[
        {
            "category":"Communications",
            "type":"Services"
        }
    ],
    "sg:phone":"+34 968 74 11 00",
    "sg:postcode":"30430",
    "sg:province":"Murcia",
    "sg:tags":[
        "televisiones",
        "y",
        "radio"
    ],
    "sg:website":"www.tvcehegin.com",
    "wof:name":"Importelevideo S.a.",
    "wof:placetype":"venue"
},
  "geometry": {"coordinates":[-1.7982709408,38.0895118713],"type":"Point"}
}