{
  "type": "Feature",
  "properties": {
    "iso:country":"ES",
    "sg:address":"Pase Alcalde Marques Del Contadero, S/n",
    "sg:city":"Sevilla",
    "sg:orig_category":"Obras Y Organismos Sociales",
    "sg:phone":"+34 954 21 50 91",
    "sg:postcode":"41001",
    "sg:province":"Sevilla",
    "wof:name":"Asociacion De Hogares Para Ni\u00f1os Privados De Ambiente Familiar",
    "wof:placetype":"venue"
},
  "geometry": {"coordinates":[-5.9978003502,37.3869552612],"type":"Point"}
}