{
  "type": "Feature",
  "properties": {
    "addr:full":"Ctra Navarrete (de), 12 Fuenmayor La Rioja 26360",
    "addr:housenumber":"12",
    "addr:postcode":"26360",
    "addr:street":"Ctra Navarrete De;Rioja",
    "iso:country":"ES",
    "sg:address":"Ctra Navarrete (de), 12",
    "sg:city":"Fuenmayor",
    "sg:orig_category":"Tubos Met\u00c1licos",
    "sg:phone":"+34 941 45 04 95",
    "sg:postcode":"26360",
    "sg:province":"La Rioja",
    "wof:name":"Montajes Inoxidables Moinox S.l.",
    "wof:placetype":"venue"
},
  "geometry": {"coordinates":[-2.5643351078,42.4638252258],"type":"Point"}
}