{
  "type": "Feature",
  "properties": {
    "addr:full":"Carr Miguel Hernandez, 10 Benetusser Valencia 46910",
    "addr:housenumber":"10",
    "addr:postcode":"46910",
    "addr:street":"Carr Miguel Hernandez",
    "iso:country":"ES",
    "sg:address":"Carr Miguel Hernandez, 10",
    "sg:city":"Benetusser",
    "sg:orig_category":"Peluqueros: De Se\u00d1oras",
    "sg:phone":"+34 963 96 49 91",
    "sg:postcode":"46910",
    "sg:province":"Valencia",
    "wof:name":"Cases Valero Maria Del Carmen",
    "wof:placetype":"venue"
},
  "geometry": {"coordinates":[-0.3961650133,39.4236679077],"type":"Point"}
}