{
  "type": "Feature",
  "properties": {
    "addr:full":"Calle de Joaquin Alonso Bonet, 12 Gijon Asturias 33206",
    "addr:housenumber":"12",
    "addr:postcode":"33206",
    "addr:street":"Calle De Joaquin Alonso Bonet",
    "iso:country":"ES",
    "sg:address":"Calle de Joaquin Alonso Bonet, 12",
    "sg:city":"Gijon",
    "sg:orig_category":"Fabricaci\u00d3n, Reparaci\u00d3n Y Mantenimiento De Construcciones Navales Y Fluviales",
    "sg:phone":"+34 985 35 78 73",
    "sg:postcode":"33206",
    "sg:province":"Asturias",
    "wof:name":"Alvarez Huerta Ricardo Luis",
    "wof:placetype":"venue"
},
  "geometry": {"coordinates":[-5.6680254936,43.5414428711],"type":"Point"}
}