{
  "type": "Feature",
  "properties": {
    "iso:country":"ES",
    "sg:address":"Carrer de Baix Del Tura, 4",
    "sg:city":"Olot",
    "sg:orig_category":"Reposter\u00cdas",
    "sg:phone":"+34 972 26 15 70",
    "sg:postcode":"17800",
    "sg:province":"Girona",
    "wof:name":"Espu\u00f1a Pastoret Jordi",
    "wof:placetype":"venue"
},
  "geometry": {"coordinates":[2.4909129143,42.1826324463],"type":"Point"}
}