{
  "type": "Feature",
  "properties": {
    "iso:country":"ES",
    "sg:address":"Calle de Minas, 37",
    "sg:city":"Alcorcon",
    "sg:orig_category":"Cristaler\u00cdas",
    "sg:phone":"+34 916 43 71 89",
    "sg:postcode":"28925",
    "sg:province":"Madrid",
    "wof:name":"Novograma Innovacion S.l.",
    "wof:placetype":"venue"
},
  "geometry": {"coordinates":[-3.8146049976,40.3367843628],"type":"Point"}
}