{
  "type": "Feature",
  "properties": {
    "addr:full":"Praz Ramon Cabanillas, 8 Cambados Pontevedra 36630",
    "addr:housenumber":"8",
    "addr:postcode":"36630",
    "addr:street":"Praz Ramon Cabanillas",
    "iso:country":"ES",
    "sg:address":"Praz Ramon Cabanillas, 8",
    "sg:city":"Cambados",
    "sg:orig_category":"\u00d3ptica: Instrumentos (fabricaci\u00d3n)",
    "sg:phone":"+34 986 54 23 65",
    "sg:postcode":"36630",
    "sg:province":"Pontevedra",
    "wof:name":"Fernandez Arnoso Jose Luis",
    "wof:placetype":"venue"
},
  "geometry": {"coordinates":[-8.8145637512,42.5146141052],"type":"Point"}
}