{
  "type": "Feature",
  "properties": {
    "addr:full":"Plaz Pradillo (del), 2 Mostoles Madrid 28934",
    "addr:postcode":"28934",
    "addr:street":"Plaz;Del 2 Mostoles",
    "iso:country":"ES",
    "sg:address":"Plaz Pradillo (del), 2",
    "sg:city":"Mostoles",
    "sg:orig_category":"Ropa Para Se\u00d1oras (al Por Menor)",
    "sg:phone":"+34 916 13 05 07",
    "sg:postcode":"28934",
    "sg:province":"Madrid",
    "wof:name":"Puchelino S. A.",
    "wof:placetype":"venue"
},
  "geometry": {"coordinates":[-3.8640010357,40.3224754333],"type":"Point"}
}