{
  "type": "Feature",
  "properties": {
    "iso:country":"ES",
    "sg:address":"Calle de Illescas, 133",
    "sg:city":"Madrid",
    "sg:orig_category":"Peluquer\u00cdas, Peluquer\u00cda Mixta",
    "sg:phone":"+34 917 19 42 03",
    "sg:postcode":"28024",
    "sg:province":"Madrid",
    "wof:name":"Gomez Davila Virginia",
    "wof:placetype":"venue"
},
  "geometry": {"coordinates":[-3.7618529797,40.3937454224],"type":"Point"}
}