{
  "type": "Feature",
  "properties": {
    "iso:country":"ES",
    "sg:address":"C/ Illes Balears, 32",
    "sg:city":"Paterna",
    "sg:orig_category":"Grafistas",
    "sg:phone":"+34 961 34 08 85",
    "sg:postcode":"46988",
    "sg:province":"Valencia",
    "wof:name":"Aragones Michavila Antonio",
    "wof:placetype":"venue"
},
  "geometry": {"coordinates":[-0.4664973915,39.5140457153],"type":"Point"}
}