{
  "type": "Feature",
  "properties": {
    "iso:country":"ES",
    "sg:address":"Carrer de Verge De La Paloma, 46",
    "sg:city":"Sabadell",
    "sg:orig_category":"Mec\u00c1nico Del Autom\u00d3vil",
    "sg:phone":"+34 937 11 72 55",
    "sg:postcode":"08204",
    "sg:province":"Barcelona",
    "sg:website":"www.ir-a.net/erasa",
    "wof:name":"Auto Talleres Erasa Srl",
    "wof:placetype":"venue"
},
  "geometry": {"coordinates":[2.1170198917,41.5256881714],"type":"Point"}
}