{
  "type": "Feature",
  "properties": {
    "iso:country":"ES",
    "sg:address":"Carrer de Bisbe Sivilla, 40",
    "sg:city":"Barcelona",
    "sg:orig_category":"Farmacias",
    "sg:phone":"+34 934 18 44 57",
    "sg:postcode":"08022",
    "sg:province":"Barcelona",
    "wof:name":"Codina Vazquez Maria Victoria",
    "wof:placetype":"venue"
},
  "geometry": {"coordinates":[2.1344900131,41.4042739868],"type":"Point"}
}