{
  "type": "Feature",
  "properties": {
    "addr:full":"Cno Polio, S/n Beniparrell Valencia 46469",
    "addr:housenumber":"s / n",
    "addr:postcode":"46469",
    "addr:street":"Cno Polio",
    "iso:country":"ES",
    "sg:address":"Cno Polio, S/n",
    "sg:city":"Beniparrell",
    "sg:orig_category":"Fabricaci\u00d3n De Taburetes, Sillas Y Sillones",
    "sg:phone":"+34 961 21 12 59",
    "sg:postcode":"46469",
    "sg:province":"Valencia",
    "sg:website":"www.cnnovamartin.com",
    "wof:name":"Innova Martin S.l.",
    "wof:placetype":"venue"
},
  "geometry": {"coordinates":[-0.4188640118,39.3784294128],"type":"Point"}
}