{
  "type": "Feature",
  "properties": {
    "addr:full":"Cami Font Del Sastre, S/n S. Hilari Sacalm Girona 17403",
    "addr:housenumber":"s",
    "addr:postcode":"17403",
    "addr:street":"/ N S.",
    "iso:country":"ES",
    "sg:address":"Cami Font Del Sastre, S/n",
    "sg:city":"S. Hilari Sacalm",
    "sg:orig_category":"Empresas De Carpinter\u00cda De Madera",
    "sg:phone":"+34 972 86 87 00",
    "sg:postcode":"17403",
    "sg:province":"Girona",
    "wof:name":"Insahil S. L.",
    "wof:placetype":"venue"
},
  "geometry": {"coordinates":[2.5134689808,41.8821105957],"type":"Point"}
}