{
  "type": "Feature",
  "properties": {
    "addr:full":"Calle de Cristo, 74 Torrejon Ardoz Madrid 28850",
    "addr:housenumber":"74",
    "addr:postcode":"28850",
    "addr:street":"Calle De Cristo",
    "iso:country":"ES",
    "sg:address":"Calle de Cristo, 74",
    "sg:city":"Torrejon Ardoz",
    "sg:orig_category":"Comunidades Religiosas",
    "sg:phone":"+34 916 75 30 73",
    "sg:postcode":"28850",
    "sg:province":"Madrid",
    "wof:name":"Hermandad Nuestra Se\u00f1ora Del Rosario",
    "wof:placetype":"venue"
},
  "geometry": {"coordinates":[-3.4814059734,40.4599952698],"type":"Point"}
}