{
  "type": "Feature",
  "properties": {
    "addr:full":"Carr Castella, 3 Eivissa Islas Baleares 07800",
    "addr:housenumber":"3",
    "addr:postcode":"07800",
    "addr:street":"Carr Castella",
    "iso:country":"ES",
    "sg:address":"Carr Castella, 3",
    "sg:city":"Eivissa",
    "sg:orig_category":"Abogados",
    "sg:phone":"+34 971 39 30 90",
    "sg:postcode":"07800",
    "sg:province":"Islas Baleares",
    "wof:name":"Guasch Ca\u00f1as Pedro",
    "wof:placetype":"venue"
},
  "geometry": {"coordinates":[1.4307750463,38.9098472595],"type":"Point"}
}