{
  "type": "Feature",
  "properties": {
    "addr:full":"Calle de San Ramon, 15 Barbastro Huesca 22300",
    "addr:housenumber":"15",
    "addr:postcode":"22300",
    "addr:street":"Calle De San Ramon",
    "iso:country":"ES",
    "sg:address":"Calle de San Ramon, 15",
    "sg:city":"Barbastro",
    "sg:orig_category":"Reposter\u00cdas",
    "sg:phone":"+34 974 31 50 95",
    "sg:postcode":"22300",
    "sg:province":"Huesca",
    "wof:name":"Enrique Sorian S.l.",
    "wof:placetype":"venue"
},
  "geometry": {"coordinates":[0.1244070008,42.0358810425],"type":"Point"}
}