{
  "type": "Feature",
  "properties": {
    "iso:country":"ES",
    "sg:address":"Avgd Del Comte De Torrefiel, 40",
    "sg:city":"Ontinyent",
    "sg:orig_category":"M\u00c1rmoles, Granitos Y Piedras Naturales",
    "sg:phone":"+34 962 38 18 32",
    "sg:postcode":"46870",
    "sg:province":"Valencia",
    "wof:name":"Marmoles Belda S.l.",
    "wof:placetype":"venue"
},
  "geometry": {"coordinates":[-0.6078130007,38.8169174194],"type":"Point"}
}