{
  "type": "Feature",
  "properties": {
    "iso:country":"ES",
    "sg:address":"Via Trajana, 25",
    "sg:city":"Barcelona",
    "sg:orig_category":"Cajas Y Embalajes De Pl\u00c1stico",
    "sg:phone":"+34 933 14 91 11",
    "sg:postcode":"08020",
    "sg:province":"Barcelona",
    "sg:website":"www.calmar.com",
    "wof:name":"Saint Gobain Calmar S.a.",
    "wof:placetype":"venue"
},
  "geometry": {"coordinates":[2.2049689293,41.4275360107],"type":"Point"}
}