{
  "type": "Feature",
  "properties": {
    "iso:country":"ES",
    "sg:address":"Calle de Tabares De Cala, 5",
    "sg:city":"San Cristobal De La Laguna",
    "sg:orig_category":"Moda",
    "sg:phone":"+34 922 25 09 09",
    "sg:postcode":"38201",
    "sg:province":"Santa Cruz De Tenerife",
    "wof:name":"Gonzalez Diaz Jose Antonio",
    "wof:placetype":"venue"
},
  "geometry": {"coordinates":[-16.3156013489,28.4885387421],"type":"Point"}
}