{
  "type": "Feature",
  "properties": {
    "addr:full":"Avda Monelos, 225 Coru\u00d1a La Coru\u00f1a 15009",
    "addr:housenumber":"225",
    "addr:postcode":"15009",
    "addr:street":"Avda Monelos;Corun\u0303A",
    "iso:country":"ES",
    "sg:address":"Avda Monelos, 225",
    "sg:city":"Coru\u00d1a",
    "sg:orig_category":"Promotores Constructores",
    "sg:phone":"+34 981 28 66 03",
    "sg:postcode":"15009",
    "sg:province":"La Coru\u00f1a",
    "wof:name":"Promotora De Viviendas Urbanas S. A.",
    "wof:placetype":"venue"
},
  "geometry": {"coordinates":[-8.3966035843,43.3423538208],"type":"Point"}
}