{
  "type": "Feature",
  "properties": {
    "addr:full":"Carrer de Miquel Blanch, 18 Castellbisbal Barcelona 08755",
    "addr:housenumber":"18",
    "addr:postcode":"08755",
    "addr:street":"Carrer De Miquel Blanch",
    "iso:country":"ES",
    "sg:address":"Carrer de Miquel Blanch, 18",
    "sg:city":"Castellbisbal",
    "sg:orig_category":"Cerrajer\u00cda, Ferrallista",
    "sg:phone":"+34 937 72 17 18",
    "sg:postcode":"08755",
    "sg:province":"Barcelona",
    "wof:name":"Construccions Meta%iques Castellbisbal S.l.",
    "wof:placetype":"venue"
},
  "geometry": {"coordinates":[1.9802399874,41.4737701416],"type":"Point"}
}