{
  "type": "Feature",
  "properties": {
    "addr:full":"Avda Conde De Guadalhorce, 91 Aviles Asturias 33401",
    "addr:housenumber":"91",
    "addr:postcode":"33401",
    "addr:street":"Avda Conde De Guadalhorce",
    "iso:country":"ES",
    "sg:address":"Avda Conde De Guadalhorce, 91",
    "sg:city":"Aviles",
    "sg:orig_category":"Electricidad, Electr\u00d3nica: Material Y Suministros (al Por Mayor)",
    "sg:phone":"+34 985 56 41 40",
    "sg:postcode":"33401",
    "sg:province":"Asturias",
    "wof:name":"Suministros Electromecanicos S. A.",
    "wof:placetype":"venue"
},
  "geometry": {"coordinates":[-5.9230999947,43.571182251],"type":"Point"}
}