{
  "type": "Feature",
  "properties": {
    "addr:full":"Carrer de Pintor Fortuny, 24 Barcelona Barcelona 08001",
    "addr:housenumber":"24",
    "addr:postcode":"08001",
    "addr:street":"Carrer De Pintor Fortuny",
    "iso:country":"ES",
    "sg:address":"Carrer de Pintor Fortuny, 24",
    "sg:city":"Barcelona",
    "sg:orig_category":"Sales (al Por Mayor)",
    "sg:phone":"+34 933 02 35 67",
    "sg:postcode":"08001",
    "sg:province":"Barcelona",
    "wof:name":"Caballero Vera Gemma",
    "wof:placetype":"venue"
},
  "geometry": {"coordinates":[2.1691360474,41.3827095032],"type":"Point"}
}