{
  "type": "Feature",
  "properties": {
    "iso:country":"ES",
    "sg:address":"Calle de Rodriguez Pintor, 30",
    "sg:city":"Motril",
    "sg:orig_category":"Fabricaci\u00d3n De Distribuidores Autom\u00c1ticos",
    "sg:phone":"+34 958 60 57 61",
    "sg:postcode":"18600",
    "sg:province":"Granada",
    "wof:name":"Maquinas De Cafe Y Grano S.l.",
    "wof:placetype":"venue"
},
  "geometry": {"coordinates":[-3.514439106,36.751449585],"type":"Point"}
}