{
  "type": "Feature",
  "properties": {
    "addr:full":"Calle de Gallur, 419 Madrid Madrid 28047",
    "addr:housenumber":"419",
    "addr:postcode":"28047",
    "addr:street":"Calle De Gallur",
    "iso:country":"ES",
    "sg:address":"Calle de Gallur, 419",
    "sg:city":"Madrid",
    "sg:orig_category":"Farmacias",
    "sg:phone":"+34 914 66 00 26",
    "sg:postcode":"28047",
    "sg:province":"Madrid",
    "wof:name":"Alonso Andres Maria Teresa",
    "wof:placetype":"venue"
},
  "geometry": {"coordinates":[-3.7391228676,40.3981285095],"type":"Point"}
}