{
  "type": "Feature",
  "properties": {
    "addr:full":"Calle de Juan De La Cierva, 29 Zaragoza Zaragoza 50014",
    "addr:housenumber":"29",
    "addr:postcode":"50014",
    "addr:street":"Calle De Juan De La Cierva",
    "iso:country":"ES",
    "sg:address":"Calle de Juan De La Cierva, 29",
    "sg:city":"Zaragoza",
    "sg:orig_category":"Empresas De Limpieza",
    "sg:phone":"+34 976 47 26 20",
    "sg:postcode":"50014",
    "sg:province":"Zaragoza",
    "wof:name":"Servicio Y Maquinaria Aragonesa S. A.",
    "wof:placetype":"venue"
},
  "geometry": {"coordinates":[-0.8614550233,41.6707191467],"type":"Point"}
}