{
  "type": "Feature",
  "properties": {
    "addr:full":"Calle de Panaderos, 58 Valladolid Valladolid 47004",
    "addr:housenumber":"58",
    "addr:postcode":"47004",
    "addr:street":"Calle De Panaderos",
    "iso:country":"ES",
    "sg:address":"Calle de Panaderos, 58",
    "sg:city":"Valladolid",
    "sg:orig_category":"Sindicatos De Trabajadores",
    "sg:phone":"+34 983 30 68 55",
    "sg:postcode":"47004",
    "sg:province":"Valladolid",
    "wof:name":"Union De Peque\u00f1os Agricultores",
    "wof:placetype":"venue"
},
  "geometry": {"coordinates":[-4.7224450111,41.6448440552],"type":"Point"}
}