{
  "type": "Feature",
  "properties": {
    "addr:full":"Mallutz Kalea, 3 Ordizia Guip\u00f9zcoa 20240",
    "addr:housenumber":"3",
    "addr:postcode":"20240",
    "addr:street":"Mallutz Kalea;Guipu\u0300Zcoa",
    "iso:country":"ES",
    "sg:address":"Mallutz Kalea, 3",
    "sg:city":"Ordizia",
    "sg:orig_category":"Aparcamientos (infraestructuras, Accesorios)",
    "sg:phone":"+34 943 88 66 22",
    "sg:postcode":"20240",
    "sg:province":"Guip\u00f9zcoa",
    "wof:name":"Garaje Txindoki S.l.",
    "wof:placetype":"venue"
},
  "geometry": {"coordinates":[-2.1750812531,43.0522575378],"type":"Point"}
}