{
  "type": "Feature",
  "properties": {
    "addr:full":"Calle de Dragaminas, 1 Palmones C\u00e1diz 11379",
    "addr:housenumber":"1",
    "addr:postcode":"11379",
    "addr:street":"Calle De Dragaminas;Ca\u0301Diz",
    "iso:country":"ES",
    "sg:address":"Calle de Dragaminas, 1",
    "sg:city":"Palmones",
    "sg:orig_category":"Electricidad: Instaladores",
    "sg:phone":"+34 956 67 82 21",
    "sg:postcode":"11379",
    "sg:province":"C\u00e1diz",
    "wof:name":"Maiinntec S.l.",
    "wof:placetype":"venue"
},
  "geometry": {"coordinates":[-5.4370045662,36.1804885864],"type":"Point"}
}