{
  "type": "Feature",
  "properties": {
    "addr:full":"Calle de Quiroga, 6 Arrecife Las Palmas 35500",
    "addr:housenumber":"6",
    "addr:postcode":"35500",
    "addr:street":"Calle De Quiroga",
    "iso:country":"ES",
    "sg:address":"Calle de Quiroga, 6",
    "sg:city":"Arrecife",
    "sg:orig_category":"Arquitectos",
    "sg:phone":"+34 928 81 08 54",
    "sg:postcode":"35500",
    "sg:province":"Las Palmas",
    "wof:name":"Delgado Quintero Epifaneo",
    "wof:placetype":"venue"
},
  "geometry": {"coordinates":[-13.548707962,28.9587192535],"type":"Point"}
}