{
  "type": "Feature",
  "properties": {
    "addr:full":"Irutasun Kalea, 1 Usurbil Guip\u00f9zcoa 20170",
    "addr:housenumber":"1",
    "addr:postcode":"20170",
    "addr:street":"Irutasun Kalea;Guipu\u0300Zcoa",
    "iso:country":"ES",
    "sg:address":"Irutasun Kalea, 1",
    "sg:city":"Usurbil",
    "sg:orig_category":"Abogados",
    "sg:phone":"+34 943 36 60 56",
    "sg:postcode":"20170",
    "sg:province":"Guip\u00f9zcoa",
    "wof:name":"Furundarena Etxeberria-berreiarza Lourdes",
    "wof:placetype":"venue"
},
  "geometry": {"coordinates":[-2.0509240627,43.2708282471],"type":"Point"}
}