{
  "type": "Feature",
  "properties": {
    "iso:country":"ES",
    "sg:address":"Avda Perez Galdos, 77",
    "sg:city":"Valencia",
    "sg:orig_category":"Agencias Y Asesores De Publicidad",
    "sg:phone":"+34 963 82 15 34",
    "sg:postcode":"46018",
    "sg:province":"Valencia",
    "sg:website":"www.conexionspot.es",
    "wof:name":"Conexion Spot S.l.",
    "wof:placetype":"venue"
},
  "geometry": {"coordinates":[-0.3922489882,39.4698791504],"type":"Point"}
}