{
  "type": "Feature",
  "properties": {
    "addr:full":"Ptda Garrachico, 18 Villafranqueza Alicante 03112",
    "addr:housenumber":"18",
    "addr:postcode":"03112",
    "addr:street":"Ptda Garrachico",
    "iso:country":"ES",
    "sg:address":"Ptda Garrachico, 18",
    "sg:city":"Villafranqueza",
    "sg:orig_category":"Cerrajer\u00cda, Ferrallista",
    "sg:phone":"+34 965 25 91 00",
    "sg:postcode":"03112",
    "sg:province":"Alicante",
    "sg:website":"www.ceur24.com",
    "wof:name":"Ceur24 S.l.",
    "wof:placetype":"venue"
},
  "geometry": {"coordinates":[-0.477075994,38.3986091614],"type":"Point"}
}