{
  "type": "Feature",
  "properties": {
    "iso:country":"ES",
    "sg:address":"Calle de Ubeda, 36",
    "sg:city":"Martos",
    "sg:orig_category":"Molduras, Junquillos, Listones Y Molduras Perforadas",
    "sg:phone":"+34 953 70 04 19",
    "sg:postcode":"23600",
    "sg:province":"Ja\u00e9n",
    "wof:name":"Rodriguez Ruiz Jose Manuel",
    "wof:placetype":"venue"
},
  "geometry": {"coordinates":[-3.9686288834,37.7082290649],"type":"Point"}
}