{
  "type": "Feature",
  "properties": {
    "iso:country":"ES",
    "sg:address":"Calle de Cervantes, 8",
    "sg:city":"Talavera Reina",
    "sg:orig_category":"Parafarmacias",
    "sg:phone":"+34 925 82 86 28",
    "sg:postcode":"45600",
    "sg:province":"Toledo",
    "wof:name":"Recio Aranda Maria Jose",
    "wof:placetype":"venue"
},
  "geometry": {"coordinates":[-4.8195266724,39.9631156921],"type":"Point"}
}