{
  "type": "Feature",
  "properties": {
    "iso:country":"ES",
    "sg:address":"Pase Aragon (de), 18",
    "sg:city":"Ateca",
    "sg:orig_category":"Negocio De Materiales De Construcci\u00d3n",
    "sg:phone":"+34 976 84 23 87",
    "sg:postcode":"50200",
    "sg:province":"Zaragoza",
    "wof:name":"Judez Urbano Cesar",
    "wof:placetype":"venue"
},
  "geometry": {"coordinates":[-1.7889089584,41.3299789429],"type":"Point"}
}