{
  "type": "Feature",
  "properties": {
    "iso:country":"ES",
    "sg:address":"Calle de Abajo, 1",
    "sg:city":"Quintana Serena",
    "sg:orig_category":"Bancos",
    "sg:phone":"+34 924 78 63 11",
    "sg:postcode":"06450",
    "sg:province":"Badajoz",
    "wof:name":"Banco Caixa Geral S.a.",
    "wof:placetype":"venue"
},
  "geometry": {"coordinates":[-5.6713070869,38.742401123],"type":"Point"}
}