{
  "type": "Feature",
  "properties": {
    "iso:country":"ES",
    "sg:address":"Rua Alfonso Senra, 40",
    "sg:city":"Ordes",
    "sg:orig_category":"Frutas, Legumbres Frescas Y Tempranas (al Por Menor)",
    "sg:phone":"+34 981 68 09 98",
    "sg:postcode":"15680",
    "sg:province":"La Coru\u00f1a",
    "wof:name":"Jose Leon Couso Y Antonio Leon Couso S.cv.",
    "wof:placetype":"venue"
},
  "geometry": {"coordinates":[-8.4056177139,43.0802459717],"type":"Point"}
}