{
  "type": "Feature",
  "properties": {
    "iso:country":"ES",
    "sg:address":"Calle de Xilaos, 1",
    "sg:city":"Cella",
    "sg:orig_category":"Cajas De Ahorro",
    "sg:phone":"+34 978 65 00 00",
    "sg:postcode":"44370",
    "sg:province":"Teruel",
    "wof:name":"Caja De Ahorros De La Inmaculada",
    "wof:placetype":"venue"
},
  "geometry": {"coordinates":[-1.2870210409,40.4540519714],"type":"Point"}
}