{
  "type": "Feature",
  "properties": {
    "iso:country":"ES",
    "sg:address":"Carrer de Mare De Deu Del Socors, 61",
    "sg:city":"Terrassa",
    "sg:orig_category":"Reposter\u00cdas",
    "sg:phone":"+34 937 83 89 25",
    "sg:postcode":"08222",
    "sg:province":"Barcelona",
    "wof:name":"Ros Martinez Emilio",
    "wof:placetype":"venue"
},
  "geometry": {"coordinates":[2.0297889709,41.5616188049],"type":"Point"}
}