{
  "type": "Feature",
  "properties": {
    "addr:full":"Calle de Colombia, 17 Toledo Toledo 45004",
    "addr:housenumber":"17",
    "addr:postcode":"45004",
    "addr:street":"Calle De Colombia",
    "iso:country":"ES",
    "sg:address":"Calle de Colombia, 17",
    "sg:city":"Toledo",
    "sg:orig_category":"Ropa Para Ni\u00d1os (al Por Menor)",
    "sg:phone":"+34 925 21 65 59",
    "sg:postcode":"45004",
    "sg:province":"Toledo",
    "wof:name":"Peques C. B.",
    "wof:placetype":"venue"
},
  "geometry": {"coordinates":[-4.0316500664,39.8679161072],"type":"Point"}
}