{
  "type": "Feature",
  "properties": {
    "addr:full":"Pol Ind El Ejido, S/n Osuna Sevilla 41640",
    "addr:postcode":"41640",
    "addr:street":"S / N",
    "iso:country":"ES",
    "sg:address":"Pol Ind El Ejido, S/n",
    "sg:city":"Osuna",
    "sg:orig_category":"Rectificaci\u00d3n, Mecanizado, Fresado",
    "sg:phone":"+34 955 82 11 63",
    "sg:postcode":"41640",
    "sg:province":"Sevilla",
    "wof:name":"Perez Navarro Rafael",
    "wof:placetype":"venue"
},
  "geometry": {"coordinates":[-5.1152839661,37.2390098572],"type":"Point"}
}