{
  "type": "Feature",
  "properties": {
    "addr:full":"Calle de San Andres, 12 Madrid Madrid 28004",
    "addr:housenumber":"12",
    "addr:postcode":"madrid;28004",
    "addr:street":"Calle De San Andres",
    "iso:country":"ES",
    "sg:address":"Calle de San Andres, 12",
    "sg:city":"Madrid",
    "sg:orig_category":"Audiovisuales, Tv, Hi",
    "sg:phone":"+34 915 22 77 67",
    "sg:postcode":"28004",
    "sg:province":"Madrid",
    "sg:website":"www.multi-arte.com",
    "wof:name":"Marte Producciones S.a.",
    "wof:placetype":"venue"
},
  "geometry": {"coordinates":[-3.7035999298,40.4265403748],"type":"Point"}
}