{
  "type": "Feature",
  "properties": {
    "iso:country":"ES",
    "sg:address":"Calle de San Agustin, 54",
    "sg:city":"Icod De Los Vinos",
    "sg:orig_category":"\u00d3ptica: Instrumentos (fabricaci\u00d3n)",
    "sg:phone":"+34 922 12 21 30",
    "sg:postcode":"38430",
    "sg:province":"Santa Cruz De Tenerife",
    "wof:name":"Centro Optico Icod S.l.",
    "wof:placetype":"venue"
},
  "geometry": {"coordinates":[-16.7164726257,28.3682518005],"type":"Point"}
}