{
  "type": "Feature",
  "properties": {
    "iso:country":"ES",
    "sg:address":"Calle de Triana, 99",
    "sg:city":"Palmas De Gran Canaria",
    "sg:orig_category":"\u00d3pticos Optometristas (al Por Menor)",
    "sg:phone":"+34 928 37 34 88",
    "sg:postcode":"35...",
    "sg:province":"Las Palmas",
    "wof:name":"Optica Herrera Cerpa S.a.",
    "wof:placetype":"venue"
},
  "geometry": {"coordinates":[-15.4170875549,28.1076793671],"type":"Point"}
}