{
  "type": "Feature",
  "properties": {
    "addr:full":"Calle de Virgen De Las Angustias, 34 Avila \u00c1vila 05005",
    "addr:housenumber":"34",
    "addr:postcode":"05005",
    "addr:street":"Calle De Virgen De Las Angustias;A\u0301Vila",
    "iso:country":"ES",
    "sg:address":"Calle de Virgen De Las Angustias, 34",
    "sg:city":"Avila",
    "sg:orig_category":"Agencias Y Agentes Comerciales, Representantes",
    "sg:phone":"+34 920 22 55 86",
    "sg:postcode":"05005",
    "sg:province":"\u00c1vila",
    "wof:name":"Jimenez Sanchez Juan Jose",
    "wof:placetype":"venue"
},
  "geometry": {"coordinates":[-4.6865458488,40.6602706909],"type":"Point"}
}