{
  "type": "Feature",
  "properties": {
    "iso:country":"ES",
    "sg:address":"Calle de Manuel Garcia, 13",
    "sg:city":"Coin",
    "sg:orig_category":"Carnicer\u00cdas, Carnicer\u00cdas",
    "sg:phone":"+34 952 45 08 79",
    "sg:postcode":"29100",
    "sg:province":"M\u00e1laga",
    "wof:name":"Berrocal Martin Juan Jesus",
    "wof:placetype":"venue"
},
  "geometry": {"coordinates":[-4.7568850517,36.6605606079],"type":"Point"}
}