{
  "type": "Feature",
  "properties": {
    "addr:full":"Calle de Granados, 2 Berja Almer\u00eda 04760",
    "addr:housenumber":"2",
    "addr:postcode":"04760",
    "addr:street":"Calle De Granados",
    "iso:country":"ES",
    "sg:address":"Calle de Granados, 2",
    "sg:city":"Berja",
    "sg:orig_category":"Cristaler\u00cdas",
    "sg:phone":"+34 950 49 20 67",
    "sg:postcode":"04760",
    "sg:province":"Almer\u00eda",
    "wof:name":"Sanchez Manrubia Ignacio",
    "wof:placetype":"venue"
},
  "geometry": {"coordinates":[-2.9476540089,36.8432350159],"type":"Point"}
}