{
  "type": "Feature",
  "properties": {
    "iso:country":"ES",
    "sg:address":"Pg Sant Joan, 91",
    "sg:city":"Barcelona",
    "sg:orig_category":"Farmacias (repartici\u00d3n Y Al Por Mayor)",
    "sg:phone":"+34 932 07 40 24",
    "sg:postcode":"08009",
    "sg:province":"Barcelona",
    "wof:name":"Laboratorios Thea S. A.",
    "wof:placetype":"venue"
},
  "geometry": {"coordinates":[2.170609951,41.3984642029],"type":"Point"}
}