{
  "type": "Feature",
  "properties": {
    "iso:country":"ES",
    "sg:address":"Calle de Ripa, 1",
    "sg:city":"Bilbao",
    "sg:orig_category":"Asesor\u00cda Sobre Comunicaci\u00d3n De Empresas",
    "sg:phone":"+34 944 24 66 59",
    "sg:postcode":"48001",
    "sg:province":"Vizcaya",
    "wof:name":"Lopez Totorika Consultores S.a.",
    "wof:placetype":"venue"
},
  "geometry": {"coordinates":[-2.9255940914,43.2606201172],"type":"Point"}
}