{
  "type": "Feature",
  "properties": {
    "addr:full":"Calle de Ibiza, 17 Madrid Madrid 28009",
    "addr:housenumber":"17",
    "addr:postcode":"madrid;28009",
    "addr:street":"Calle De Ibiza",
    "iso:country":"ES",
    "sg:address":"Calle de Ibiza, 17",
    "sg:city":"Madrid",
    "sg:orig_category":"Fotograf\u00cda Y Cine: Aparatos, Pel\u00cdculas Y Accesorios (fabricaci\u00d3n, Al Por Mayor)",
    "sg:phone":"+34 915 74 44 90",
    "sg:postcode":"28009",
    "sg:province":"Madrid",
    "wof:name":"Natur Aidland",
    "wof:placetype":"venue"
},
  "geometry": {"coordinates":[-3.6766018867,40.4184951782],"type":"Point"}
}