{
  "type": "Feature",
  "properties": {
    "iso:country":"ES",
    "sg:address":"Rua Comercio, 29",
    "sg:city":"Noia",
    "sg:orig_category":"Telas Y Sedas (al Por Menor)",
    "sg:phone":"+34 981 82 04 53",
    "sg:postcode":"15200",
    "sg:province":"La Coru\u00f1a",
    "wof:name":"Lamas Seijas Luis",
    "wof:placetype":"venue"
},
  "geometry": {"coordinates":[-8.887216568,42.7837409973],"type":"Point"}
}