{
  "type": "Feature",
  "properties": {
    "iso:country":"ES",
    "sg:address":"Carrer de Taronger, 4",
    "sg:city":"Palma",
    "sg:orig_category":"Contenedores (mercanc\u00cdas)",
    "sg:phone":"+34 971 47 24 43",
    "sg:postcode":"07008",
    "sg:province":"Islas Baleares",
    "wof:name":"Cervantes Marquez Maria Del Carmen",
    "wof:placetype":"venue"
},
  "geometry": {"coordinates":[2.6762180328,39.5880355835],"type":"Point"}
}