{
  "type": "Feature",
  "properties": {
    "iso:country":"ES",
    "sg:address":"Calle de Garcia Cabrelles, 32",
    "sg:city":"Melilla",
    "sg:orig_category":"Panader\u00cdas, Panader\u00cdas",
    "sg:phone":"+34 952 68 36 66",
    "sg:postcode":"52002",
    "sg:province":"Melilla",
    "wof:name":"Zaudi  Mustapha",
    "wof:placetype":"venue"
},
  "geometry": {"coordinates":[-2.9449179173,35.2958450317],"type":"Point"}
}