{
  "type": "Feature",
  "properties": {
    "addr:full":"Carr Bellprat, 33 Igualada Barcelona 08700",
    "addr:housenumber":"33",
    "addr:postcode":"08700",
    "addr:street":"Carr Bellprat",
    "iso:country":"ES",
    "sg:address":"Carr Bellprat, 33",
    "sg:city":"Igualada",
    "sg:orig_category":"Venta, Colocaci\u00d3n, Reparaci\u00d3n De Parabrisas, Techos Descapotables",
    "sg:phone":"+34 938 04 13 89",
    "sg:postcode":"08700",
    "sg:province":"Barcelona",
    "sg:website":"www.vidreracing.com",
    "wof:name":"Cristal Catalunya S.l",
    "wof:placetype":"venue"
},
  "geometry": {"coordinates":[1.6148710251,41.5875396729],"type":"Point"}
}