{
  "type": "Feature",
  "properties": {
    "addr:full":"Estd Coru\u00d1a (da), 62 Lugo Lugo 27003",
    "addr:postcode":"27003",
    "iso:country":"ES",
    "sg:address":"Estd Coru\u00d1a (da), 62",
    "sg:city":"Lugo",
    "sg:orig_category":"Agencias Y Asesores De Publicidad",
    "sg:phone":"+34 982 21 86 59",
    "sg:postcode":"27003",
    "sg:province":"Lugo",
    "wof:name":"Garcibel Lugo S.l.",
    "wof:placetype":"venue"
},
  "geometry": {"coordinates":[-7.5599198341,43.0167121887],"type":"Point"}
}