{
  "type": "Feature",
  "properties": {
    "iso:country":"ES",
    "sg:address":"C/ Pau Ferran, 17",
    "sg:city":"Tarrega",
    "sg:orig_category":"Construcci\u00d3n De Edificios Residenciales Y No Residenciales",
    "sg:phone":"+34 973 31 29 55",
    "sg:postcode":"25300",
    "sg:province":"Lleida",
    "wof:name":"Rius Obres I Contractes S.l.",
    "wof:placetype":"venue"
},
  "geometry": {"coordinates":[1.14041996,41.6528015137],"type":"Point"}
}