{
  "type": "Feature",
  "properties": {
    "addr:full":"Calle de Maldonado, 12 Santa Cruz Palma Santa Cruz De Tenerife 38700",
    "addr:housenumber":"12",
    "addr:postcode":"38700",
    "addr:street":"Calle De Maldonado",
    "iso:country":"ES",
    "sg:address":"Calle de Maldonado, 12",
    "sg:city":"Santa Cruz Palma",
    "sg:orig_category":"Electromec\u00c1nica",
    "sg:phone":"+34 922 41 39 41",
    "sg:postcode":"38700",
    "sg:province":"Santa Cruz De Tenerife",
    "wof:name":"Sanfiel Gonzalez Jose Luis",
    "wof:placetype":"venue"
},
  "geometry": {"coordinates":[-17.7601184845,28.6900806427],"type":"Point"}
}