{
  "type": "Feature",
  "properties": {
    "iso:country":"ES",
    "sg:address":"Matorral, 2",
    "sg:city":"Guadalupe",
    "sg:orig_category":"Centros Empresariales",
    "sg:phone":"+34 927 15 43 22",
    "sg:postcode":"10140",
    "sg:province":"C\u00e1ceres",
    "wof:name":"Villuercas Villa Turistica S.l.",
    "wof:placetype":"venue"
},
  "geometry": {"coordinates":[-5.3255457878,39.4564704895],"type":"Point"}
}