{
  "type": "Feature",
  "properties": {
    "addr:full":"Sect Escultores, 31 Tres Cantos Madrid 28760",
    "addr:housenumber":"31",
    "addr:postcode":"28760",
    "addr:street":"Escultores",
    "iso:country":"ES",
    "sg:address":"Sect Escultores, 31",
    "sg:city":"Tres Cantos",
    "sg:orig_category":"Procuradores",
    "sg:phone":"+34 918 04 03 80",
    "sg:postcode":"28760",
    "sg:province":"Madrid",
    "wof:name":"Bustos Pardo Teresa",
    "wof:placetype":"venue"
},
  "geometry": {"coordinates":[-3.7134420872,40.6143341064],"type":"Point"}
}