{
  "type": "Feature",
  "properties": {
    "addr:full":"Calle de Pizarro, 7 Tomelloso Ciudad Real 13700",
    "addr:housenumber":"7",
    "addr:postcode":"13700",
    "addr:street":"Calle De Pizarro",
    "iso:country":"ES",
    "sg:address":"Calle de Pizarro, 7",
    "sg:city":"Tomelloso",
    "sg:orig_category":"Fabrica De Charcuter\u00cda",
    "sg:phone":"+34 926 51 40 01",
    "sg:postcode":"13700",
    "sg:province":"Ciudad Real",
    "wof:name":"Nuevos Charcuteros S.l",
    "wof:placetype":"venue"
},
  "geometry": {"coordinates":[-3.0211930275,39.1688041687],"type":"Point"}
}