{
  "type": "Feature",
  "properties": {
    "addr:full":"Calle de Obispo Zarranz Y Pueyo, 24 Bejar Salamanca 37700",
    "addr:housenumber":"24",
    "addr:postcode":"37700",
    "addr:street":"Calle De Obispo Zarranz Y Pueyo",
    "iso:country":"ES",
    "sg:address":"Calle de Obispo Zarranz Y Pueyo, 24",
    "sg:city":"Bejar",
    "sg:orig_category":"Agentes, Concesionarios Y Sucursales De Veh\u00cdculos",
    "sg:phone":"+34 923 40 00 58",
    "sg:postcode":"37700",
    "sg:province":"Salamanca",
    "wof:name":"Auto Castro S.l.",
    "wof:placetype":"venue"
},
  "geometry": {"coordinates":[-5.7546591759,40.3856468201],"type":"Point"}
}