{
  "type": "Feature",
  "properties": {
    "iso:country":"ES",
    "sg:address":"Calle de Justa Garcia, 20",
    "sg:city":"Madrid",
    "sg:orig_category":"Molduras, Junquillos, Listones Y Molduras Perforadas",
    "sg:phone":"+34 914 75 10 11",
    "sg:postcode":"28026",
    "sg:province":"Madrid",
    "wof:name":"Sanz Esteban Inocente",
    "wof:placetype":"venue"
},
  "geometry": {"coordinates":[-3.7093551159,40.3814506531],"type":"Point"}
}