{
  "type": "Feature",
  "properties": {
    "addr:full":"Calle de Impresor Lambert Palmart, 6 Valencia Valencia 46022",
    "addr:housenumber":"6",
    "addr:postcode":"46022",
    "addr:street":"Calle De Impresor Lambert Palmart",
    "iso:country":"ES",
    "sg:address":"Calle de Impresor Lambert Palmart, 6",
    "sg:city":"Valencia",
    "sg:orig_category":"Marroquiner\u00cda (confecci\u00d3n)",
    "sg:phone":"+34 963 72 77 52",
    "sg:postcode":"46022",
    "sg:province":"Valencia",
    "wof:name":"Terrasa Gonzalez Irene",
    "wof:placetype":"venue"
},
  "geometry": {"coordinates":[-0.3447969854,39.4711914062],"type":"Point"}
}