{
  "type": "Feature",
  "properties": {
    "addr:full":"Carrer de Arquimedes, 1 Terrassa Barcelona 08224",
    "addr:housenumber":"1",
    "addr:postcode":"08224",
    "addr:street":"Carrer De Arquimedes",
    "iso:country":"ES",
    "sg:address":"Carrer de Arquimedes, 1",
    "sg:city":"Terrassa",
    "sg:orig_category":"Negocio De Materiales De Construcci\u00d3n",
    "sg:phone":"+34 937 88 65 62",
    "sg:postcode":"08224",
    "sg:province":"Barcelona",
    "wof:name":"Cohise Terrassa Sl.",
    "wof:placetype":"venue"
},
  "geometry": {"coordinates":[2.0061221123,41.5567474365],"type":"Point"}
}