{
  "type": "Feature",
  "properties": {
    "iso:country":"ES",
    "sg:address":"Calle de Antonio Saura, 2",
    "sg:city":"Zaragoza",
    "sg:orig_category":"Panader\u00cdas, Panader\u00cdas",
    "sg:phone":"+34 976 74 05 93",
    "sg:postcode":"50018",
    "sg:province":"Zaragoza",
    "wof:name":"Pasteleriasmanuel Segura S.l.",
    "wof:placetype":"venue"
},
  "geometry": {"coordinates":[-0.8872154951,41.6738777161],"type":"Point"}
}