{
  "type": "Feature",
  "properties": {
    "addr:full":"Pg Pare Claret, S/n Solsona Lleida 25280",
    "addr:housenumber":"s / n",
    "addr:postcode":"25280",
    "addr:street":"Pg Pare Claret",
    "iso:country":"ES",
    "sg:address":"Pg Pare Claret, S/n",
    "sg:city":"Solsona",
    "sg:orig_category":"Iglesia Cat\u00d3lica",
    "sg:phone":"+34 973 48 01 23",
    "sg:postcode":"25280",
    "sg:province":"Lleida",
    "wof:name":"Bisbat De Solsona",
    "wof:placetype":"venue"
},
  "geometry": {"coordinates":[1.5146150589,41.9943656921],"type":"Point"}
}