{
  "type": "Feature",
  "properties": {
    "addr:full":"Carrer de Sant Antoni Abat, 54 Barcelona Barcelona 08001",
    "addr:housenumber":"54",
    "addr:postcode":"08001",
    "addr:street":"Carrer De Sant Antoni Abat",
    "iso:country":"ES",
    "sg:address":"Carrer de Sant Antoni Abat, 54",
    "sg:city":"Barcelona",
    "sg:orig_category":"Internados & Ense\u00d1anza Privada",
    "sg:phone":"+34 934 41 77 89",
    "sg:postcode":"08001",
    "sg:province":"Barcelona",
    "wof:name":"Escuelas Pias De San Anton",
    "wof:placetype":"venue"
},
  "geometry": {"coordinates":[2.1634969711,41.3789405823],"type":"Point"}
}