{
  "type": "Feature",
  "properties": {
    "addr:full":"Felanitx, 33 Santanyi Islas Baleares 07650",
    "addr:housenumber":"33",
    "addr:postcode":"07650",
    "addr:street":"Felanitx",
    "iso:country":"ES",
    "sg:address":"Felanitx, 33",
    "sg:city":"Santanyi",
    "sg:orig_category":"Pintura Y Barniz (al Por Menor)",
    "sg:phone":"+34 971 64 21 28",
    "sg:postcode":"07650",
    "sg:province":"Islas Baleares",
    "wof:name":"Pinturex Balear Cb",
    "wof:placetype":"venue"
},
  "geometry": {"coordinates":[3.1293559074,39.3582801819],"type":"Point"}
}