{
  "type": "Feature",
  "properties": {
    "addr:full":"Carrer de Balmes, 9 Molins Rei Barcelona 08750",
    "addr:housenumber":"9",
    "addr:postcode":"08750",
    "addr:street":"Carrer De Balmes;Barcelona",
    "iso:country":"ES",
    "sg:address":"Carrer de Balmes, 9",
    "sg:city":"Molins Rei",
    "sg:orig_category":"Cl\u00cdnicas Dentales",
    "sg:phone":"+34 936 68 22 49",
    "sg:postcode":"08750",
    "sg:province":"Barcelona",
    "wof:name":"Medina Garrido Francisco Javier",
    "wof:placetype":"venue"
},
  "geometry": {"coordinates":[2.0164849758,41.414604187],"type":"Point"}
}