{
  "type": "Feature",
  "properties": {
    "iso:country":"ES",
    "sg:address":"Carrer de Argenters, 15",
    "sg:city":"Vic",
    "sg:orig_category":"Ropa Para Se\u00d1oras Y Caballeros (al Por Menor)",
    "sg:phone":"+34 938 86 06 37",
    "sg:postcode":"08500",
    "sg:province":"Barcelona",
    "wof:name":"Marin Guiteras Rafael",
    "wof:placetype":"venue"
},
  "geometry": {"coordinates":[2.2558970451,41.9301605225],"type":"Point"}
}