{
  "type": "Feature",
  "properties": {
    "addr:full":"Calle de San Antonio, 30 San Cristobal De La Laguna Santa Cruz De Tenerife 38202",
    "addr:housenumber":"30",
    "addr:postcode":"38202",
    "addr:street":"Calle De San Antonio",
    "iso:country":"ES",
    "sg:address":"Calle de San Antonio, 30",
    "sg:city":"San Cristobal De La Laguna",
    "sg:orig_category":"M\u00c9dicos: Otorrinolaringolog\u00cda",
    "sg:phone":"+34 922 63 12 13",
    "sg:postcode":"38202",
    "sg:province":"Santa Cruz De Tenerife",
    "wof:name":"Jimenez Garcia Antonio Maximo",
    "wof:placetype":"venue"
},
  "geometry": {"coordinates":[-16.3222808838,28.489112854],"type":"Point"}
}