{
  "type": "Feature",
  "properties": {
    "addr:full":"Avda Juan Sitges, S/n Salinas Asturias 33405",
    "addr:housenumber":"s / n",
    "addr:postcode":"33405",
    "addr:street":"Avda Juan Sitges",
    "iso:country":"ES",
    "sg:address":"Avda Juan Sitges, S/n",
    "sg:city":"Salinas",
    "sg:orig_category":"Oficinas De Turismo, Asociaciones De Iniciativa",
    "sg:phone":"+34 985 50 18 65",
    "sg:postcode":"33405",
    "sg:province":"Asturias",
    "wof:name":"Ayuntamiento De Castrillon",
    "wof:placetype":"venue"
},
  "geometry": {"coordinates":[-5.9653129578,43.5765228271],"type":"Point"}
}