{
  "type": "Feature",
  "properties": {
    "addr:full":"Carr Sant Manuel, 78 Mao Islas Baleares 07702",
    "addr:housenumber":"78",
    "addr:postcode":"07702",
    "addr:street":"Carr Sant Manuel",
    "iso:country":"ES",
    "sg:address":"Carr Sant Manuel, 78",
    "sg:city":"Mao",
    "sg:orig_category":"Reposter\u00cdas",
    "sg:phone":"+34 971 36 20 73",
    "sg:postcode":"07702",
    "sg:province":"Islas Baleares",
    "wof:name":"Lopez Falgueras Esperanza",
    "wof:placetype":"venue"
},
  "geometry": {"coordinates":[4.265625,39.8903694153],"type":"Point"}
}