{
  "type": "Feature",
  "properties": {
    "iso:country":"ES",
    "sg:address":"Carrer de Pere Iv, 94",
    "sg:city":"Barcelona",
    "sg:orig_category":"Empresas De Electricidad En General",
    "sg:phone":"+34 933 00 02 39",
    "sg:postcode":"08005",
    "sg:province":"Barcelona",
    "wof:name":"Control Energetico J.g.c.s.l.",
    "wof:placetype":"venue"
},
  "geometry": {"coordinates":[2.1938769817,41.3980560303],"type":"Point"}
}