{
  "type": "Feature",
  "properties": {
    "addr:full":"Calle de Clotilde Julia, 12 Santa Olalla Del Cala Huelva 21260",
    "addr:housenumber":"12",
    "addr:postcode":"21260",
    "addr:street":"Calle De Clotilde Julia",
    "iso:country":"ES",
    "sg:address":"Calle de Clotilde Julia, 12",
    "sg:city":"Santa Olalla Del Cala",
    "sg:orig_category":"Peluqueros: De Se\u00d1oras",
    "sg:phone":"+34 959 19 01 38",
    "sg:postcode":"21260",
    "sg:province":"Huelva",
    "wof:name":"Lopez Caballero Francisco",
    "wof:placetype":"venue"
},
  "geometry": {"coordinates":[-6.2297468185,37.9062461853],"type":"Point"}
}