{
  "type": "Feature",
  "properties": {
    "iso:country":"ES",
    "sg:address":"Calle de Jose Maria Garrido, 14",
    "sg:city":"Calahorra",
    "sg:orig_category":"Asesor\u00cda Sobre Comunicaci\u00d3n De Empresas",
    "sg:phone":"+34 941 14 80 17",
    "sg:postcode":"26500",
    "sg:province":"La Rioja",
    "wof:name":"Asesoria Y Servicios Moreno S.l.",
    "wof:placetype":"venue"
},
  "geometry": {"coordinates":[-1.9694266319,42.307559967],"type":"Point"}
}