{
  "type": "Feature",
  "properties": {
    "iso:country":"ES",
    "sg:address":"Carrer de Pare Gallissa, 5",
    "sg:city":"Vic",
    "sg:orig_category":"Ingeniero",
    "sg:phone":"+34 938 85 59 56",
    "sg:postcode":"08500",
    "sg:province":"Barcelona",
    "wof:name":"Aparicio Bardolet Enric",
    "wof:placetype":"venue"
},
  "geometry": {"coordinates":[2.2499287128,41.9328536987],"type":"Point"}
}