{
  "type": "Feature",
  "properties": {
    "addr:full":"Ctra Madrid-cadiz, S/n Carpio C\u00f3rdoba 14620",
    "addr:postcode":"14620",
    "addr:street":"Ctra Madrid-Cadiz S / N Carpio Co\u0301Rdoba",
    "iso:country":"ES",
    "sg:address":"Ctra Madrid-cadiz, S/n",
    "sg:city":"Carpio",
    "sg:orig_category":"Agricultores, Agricultores",
    "sg:phone":"+34 957 18 00 16",
    "sg:postcode":"14620",
    "sg:province":"C\u00f3rdoba",
    "wof:name":"Euroexplotaciones Agrarias S.a.",
    "wof:placetype":"venue"
},
  "geometry": {"coordinates":[-4.4988470078,37.9402809143],"type":"Point"}
}