{
  "type": "Feature",
  "properties": {
    "iso:country":"ES",
    "sg:address":"Avda Fuerzas Armadas (de Las), 2",
    "sg:city":"Tarifa",
    "sg:orig_category":"Promotores Constructores",
    "sg:phone":"+34 956 68 04 71",
    "sg:postcode":"11380",
    "sg:province":"C\u00e1diz",
    "wof:name":"Punta Leona S.l.",
    "wof:placetype":"venue"
},
  "geometry": {"coordinates":[-5.6068358421,36.0109443665],"type":"Point"}
}