{
  "type": "Feature",
  "properties": {
    "addr:full":"Calle de Bolue, 3 Algorta Vizcaya 48991",
    "addr:housenumber":"3",
    "addr:postcode":"48991",
    "addr:street":"Calle De Bolue",
    "iso:country":"ES",
    "sg:address":"Calle de Bolue, 3",
    "sg:city":"Algorta",
    "sg:orig_category":"Molduras, Junquillos, Listones Y Molduras Perforadas",
    "sg:phone":"+34 944 30 29 44",
    "sg:postcode":"48991",
    "sg:province":"Vizcaya",
    "wof:name":"Comunidad Matias Javier Marin Murillo-david Richard Coe",
    "wof:placetype":"venue"
},
  "geometry": {"coordinates":[-3.0087478161,43.3500747681],"type":"Point"}
}