{
  "type": "Feature",
  "properties": {
    "addr:full":"Avda Jose Mu\u00d1oz De Vargas, 4 Huelva Huelva 21006",
    "addr:housenumber":"4",
    "addr:postcode":"21006",
    "addr:street":"Avda Jose",
    "iso:country":"ES",
    "sg:address":"Avda Jose Mu\u00d1oz De Vargas, 4",
    "sg:city":"Huelva",
    "sg:orig_category":"\u00d3ptica: Instrumentos (fabricaci\u00d3n)",
    "sg:phone":"+34 959 23 33 83",
    "sg:postcode":"21006",
    "sg:province":"Huelva",
    "wof:name":"Garcia Quintana Francisco",
    "wof:placetype":"venue"
},
  "geometry": {"coordinates":[-6.9356741905,37.2638282776],"type":"Point"}
}