{
  "type": "Feature",
  "properties": {
    "addr:full":"Calle de San Isidro, 12 Talavera Reina Toledo 45600",
    "addr:housenumber":"12",
    "addr:postcode":"45600",
    "addr:street":"Calle De San Isidro",
    "iso:country":"ES",
    "sg:address":"Calle de San Isidro, 12",
    "sg:city":"Talavera Reina",
    "sg:orig_category":"Abogados",
    "sg:phone":"+34 925 80 44 18",
    "sg:postcode":"45600",
    "sg:province":"Toledo",
    "wof:name":"Gomez Gomez De Ag\u00fcero Ramiro",
    "wof:placetype":"venue"
},
  "geometry": {"coordinates":[-4.8268752098,39.9631538391],"type":"Point"}
}