{
  "type": "Feature",
  "properties": {
    "iso:country":"ES",
    "sg:address":"Plaz Quinta De La Paz, S/n",
    "sg:city":"Bonanza",
    "sg:orig_category":"Centros De Educaci\u00d3n Especial",
    "sg:phone":"+34 956 36 18 40",
    "sg:postcode":"11540",
    "sg:province":"C\u00e1diz",
    "wof:name":"Junta De Andalucia",
    "wof:placetype":"venue"
},
  "geometry": {"coordinates":[-6.3575987816,36.777721405],"type":"Point"}
}