{
  "type": "Feature",
  "properties": {
    "iso:country":"ES",
    "sg:address":"Pl Major, 13",
    "sg:city":"Vic",
    "sg:orig_category":"Relojer\u00cda (al Por Menor, Reparaci\u00d3n)",
    "sg:phone":"+34 938 86 22 69",
    "sg:postcode":"08500",
    "sg:province":"Barcelona",
    "wof:name":"Prat Portus Miquel",
    "wof:placetype":"venue"
},
  "geometry": {"coordinates":[2.2536690235,41.930480957],"type":"Point"}
}