{
  "type": "Feature",
  "properties": {
    "iso:country":"ES",
    "sg:address":"Ctra Madrid-cadiz, Km. 0653,0",
    "sg:city":"Puerto De Santa Maria",
    "sg:orig_category":"Bisuter\u00cda, Joyer\u00cda, Relojer\u00cda (al Por Menor)",
    "sg:phone":"+34 956 87 12 49",
    "sg:postcode":"11500",
    "sg:province":"C\u00e1diz",
    "wof:name":"Hijos De J.l.fernandez S.l.",
    "wof:placetype":"venue"
},
  "geometry": {"coordinates":[-6.2197542191,36.6056632996],"type":"Point"}
}