{
  "type": "Feature",
  "properties": {
    "iso:country":"ES",
    "sg:address":"Calle de Calvario, 5",
    "sg:city":"Purchil",
    "sg:orig_category":"Farmacias",
    "sg:phone":"+34 958 43 22 28",
    "sg:postcode":"18193",
    "sg:province":"Granada",
    "wof:name":"Lopez Quintana Susana",
    "wof:placetype":"venue"
},
  "geometry": {"coordinates":[-3.6658813953,37.1723060608],"type":"Point"}
}