{
  "type": "Feature",
  "properties": {
    "iso:country":"ES",
    "sg:address":"Plaz Ayuntamiento (del), 15",
    "sg:city":"Utrillas",
    "sg:orig_category":"Quincaller\u00cda (al Por Menor)",
    "sg:phone":"+34 978 75 71 04",
    "sg:postcode":"44760",
    "sg:province":"Teruel",
    "wof:name":"Pedro Repolles E Hijos S.l.",
    "wof:placetype":"venue"
},
  "geometry": {"coordinates":[-0.8442590237,40.8141403198],"type":"Point"}
}