{
  "type": "Feature",
  "properties": {
    "addr:full":"Avda Estados (de Los), 7 Fuenlabrada Madrid 28945",
    "addr:housenumber":"7",
    "addr:postcode":"28945",
    "addr:street":"Avda Estados De Los",
    "iso:country":"ES",
    "sg:address":"Avda Estados (de Los), 7",
    "sg:city":"Fuenlabrada",
    "sg:orig_category":"\u00d3ptica: Instrumentos (fabricaci\u00d3n)",
    "sg:phone":"+34 916 09 86 97",
    "sg:postcode":"28945",
    "sg:province":"Madrid",
    "wof:name":"Juez Cano Maria Dolores",
    "wof:placetype":"venue"
},
  "geometry": {"coordinates":[-3.7895109653,40.2879981995],"type":"Point"}
}