{
  "type": "Feature",
  "properties": {
    "addr:full":"Avda Constitucion, 9 Don Benito Badajoz 06400",
    "addr:housenumber":"9",
    "addr:postcode":"06400",
    "addr:street":"Avda Constitucion",
    "iso:country":"ES",
    "sg:address":"Avda Constitucion, 9",
    "sg:city":"Don Benito",
    "sg:orig_category":"Abogados",
    "sg:phone":"+34 924 80 13 20",
    "sg:postcode":"06400",
    "sg:province":"Badajoz",
    "wof:name":"Cidoncha Martin De Prado Antonio",
    "wof:placetype":"venue"
},
  "geometry": {"coordinates":[-5.8627138138,38.9662666321],"type":"Point"}
}