{
  "type": "Feature",
  "properties": {
    "iso:country":"ES",
    "sg:address":"Calle de Doctor Severo Ochoa, S/n",
    "sg:city":"Granada",
    "sg:orig_category":"Ense\u00d1anza, Formaci\u00d3n Profesional: Aprendizaje",
    "sg:phone":"+34 958 24 34 55",
    "sg:postcode":"18...",
    "sg:province":"Granada",
    "wof:name":"Universidad De Granada",
    "wof:placetype":"venue"
},
  "geometry": {"coordinates":[-3.6058490276,37.1820068359],"type":"Point"}
}