{
  "type": "Feature",
  "properties": {
    "iso:country":"ES",
    "sg:address":"Calle de Perez Galdos, 14",
    "sg:city":"Bilbao",
    "sg:orig_category":"Molduras, Junquillos, Listones Y Molduras Perforadas",
    "sg:phone":"+34 944 43 50 18",
    "sg:postcode":"48010",
    "sg:province":"Vizcaya",
    "wof:name":"Rodriguez Bouza Jose Luis",
    "wof:placetype":"venue"
},
  "geometry": {"coordinates":[-2.9429140091,43.2593078613],"type":"Point"}
}