{
  "type": "Feature",
  "properties": {
    "iso:country":"ES",
    "sg:address":"Carrer de Juan De Garay, 106",
    "sg:city":"Barcelona",
    "sg:orig_category":"Lavado, Limpieza De Veh\u00cdculos",
    "sg:phone":"+34 933 40 28 86",
    "sg:postcode":"08027",
    "sg:province":"Barcelona",
    "wof:name":"Piserra-park S.l.",
    "wof:placetype":"venue"
},
  "geometry": {"coordinates":[2.1858661175,41.4218940735],"type":"Point"}
}