{
  "type": "Feature",
  "properties": {
    "iso:country":"ES",
    "sg:address":"Real, 29",
    "sg:city":"Layna",
    "sg:orig_category":"Maquinaria Para Industrias Diversas",
    "sg:phone":"+34 975 32 25 83",
    "sg:postcode":"42249",
    "sg:province":"Soria",
    "wof:name":"Martinez Casado Abel",
    "wof:placetype":"venue"
},
  "geometry": {"coordinates":[-2.3034989834,41.0988807678],"type":"Point"}
}