{
  "type": "Feature",
  "properties": {
    "iso:country":"ES",
    "sg:address":"Carr Francesc Camprodon, 6",
    "sg:city":"Santa Coloma De Farners",
    "sg:orig_category":"Promotores Constructores",
    "sg:phone":"+34 972 84 16 95",
    "sg:postcode":"17430",
    "sg:province":"Girona",
    "wof:name":"Constructora Columba S. L.",
    "wof:placetype":"venue"
},
  "geometry": {"coordinates":[2.6689898968,41.8601913452],"type":"Point"}
}