{
  "type": "Feature",
  "properties": {
    "addr:full":"Plaz Uncibay, 1 Malaga M\u00e1laga 29008",
    "addr:housenumber":"1",
    "addr:postcode":"29008",
    "addr:street":"Plaz Uncibay;Ma\u0301Laga",
    "iso:country":"ES",
    "sg:address":"Plaz Uncibay, 1",
    "sg:city":"Malaga",
    "sg:orig_category":"M\u00c9dicos: Pediatr\u00cda. Enfermedades De Los Ni\u00d1os",
    "sg:phone":"+34 952 21 22 21",
    "sg:postcode":"29008",
    "sg:province":"M\u00e1laga",
    "wof:name":"Rio Mapelli Luis Del",
    "wof:placetype":"venue"
},
  "geometry": {"coordinates":[-4.419907093,36.7222862244],"type":"Point"}
}