{
  "type": "Feature",
  "properties": {
    "addr:full":"Carrer de Lleida, 28 Raval De Cristo Tarragona 43520",
    "addr:housenumber":"28",
    "addr:postcode":"43520",
    "addr:street":"Carrer De Lleida",
    "iso:country":"ES",
    "sg:address":"Carrer de Lleida, 28",
    "sg:city":"Raval De Cristo",
    "sg:orig_category":"Centros Empresariales",
    "sg:phone":"+34 977 50 26 63",
    "sg:postcode":"43520",
    "sg:province":"Tarragona",
    "wof:name":"Guerrero Bonet Montserrat",
    "wof:placetype":"venue"
},
  "geometry": {"coordinates":[0.5002449751,40.8249855042],"type":"Point"}
}