{
  "type": "Feature",
  "properties": {
    "iso:country":"ES",
    "sg:address":"Calle de Fajardo, 2",
    "sg:city":"Malaga",
    "sg:orig_category":"Venta, Alquiler De Instrumentos Y Accesorios De M\u00dasica",
    "sg:phone":"+34 952 22 58 99",
    "sg:postcode":"29005",
    "sg:province":"M\u00e1laga",
    "wof:name":"Malaga Musical Pbp S.l.",
    "wof:placetype":"venue"
},
  "geometry": {"coordinates":[-4.4243397713,36.721206665],"type":"Point"}
}