{
  "type": "Feature",
  "properties": {
    "iso:country":"ES",
    "sg:address":"Tras La Plaza, 28",
    "sg:city":"Tajueco",
    "sg:orig_category":"Alfarer\u00cda",
    "sg:phone":"+34 975 36 51 18",
    "sg:postcode":"42366",
    "sg:province":"Soria",
    "wof:name":"Almazan Romero Maximo",
    "wof:placetype":"venue"
},
  "geometry": {"coordinates":[-2.8493475914,41.5367622375],"type":"Point"}
}