{
  "type": "Feature",
  "properties": {
    "iso:country":"ES",
    "sg:address":"Ctra Camposancos, 66",
    "sg:city":"Verdeal",
    "sg:orig_category":"Quincaller\u00cda (al Por Menor)",
    "sg:phone":"+34 986 23 54 55",
    "sg:postcode":"36213",
    "sg:province":"Pontevedra",
    "wof:name":"Megalsa S.l.",
    "wof:placetype":"venue"
},
  "geometry": {"coordinates":[-8.7210121155,42.1948318481],"type":"Point"}
}