{
  "type": "Feature",
  "properties": {
    "addr:full":"Avda Aresti Gabriel, 9 Bilbao Vizcaya 48004",
    "addr:housenumber":"9",
    "addr:postcode":"48004",
    "addr:street":"Avda Aresti Gabriel",
    "iso:country":"ES",
    "sg:address":"Avda Aresti Gabriel, 9",
    "sg:city":"Bilbao",
    "sg:orig_category":"Cajas De Ahorro",
    "sg:phone":"+34 944 73 51 21",
    "sg:postcode":"48004",
    "sg:province":"Vizcaya",
    "wof:name":"Caixa D'estalvis I Pensions De Barcelona",
    "wof:placetype":"venue"
},
  "geometry": {"coordinates":[-2.908577919,43.2569236755],"type":"Point"}
}