{
  "type": "Feature",
  "properties": {
    "iso:country":"ES",
    "sg:address":"Calle de Fray Domingo De Benaocaz, 6",
    "sg:city":"Benaocaz",
    "sg:orig_category":"Producci\u00d3n, Venta De Productos De Agricultura Biol\u00d3gica",
    "sg:phone":"+34 956 12 56 30",
    "sg:postcode":"11612",
    "sg:province":"C\u00e1diz",
    "wof:name":"Asociacion Provincial De Agricultores Y Ganaderos",
    "wof:placetype":"venue"
},
  "geometry": {"coordinates":[-5.4217982292,36.700340271],"type":"Point"}
}