{
  "type": "Feature",
  "properties": {
    "addr:full":"Avda Doctor Artero Guirao, 46 S. Pedro Pinatar Murcia 30740",
    "addr:housenumber":"46",
    "addr:postcode":"30740",
    "addr:street":"Avda Doctor Artero Guirao",
    "iso:country":"ES",
    "sg:address":"Avda Doctor Artero Guirao, 46",
    "sg:city":"S. Pedro Pinatar",
    "sg:orig_category":"Piscinas, Accesorios, Suministros (fabricaci\u00d3n, Al Por Mayor)",
    "sg:phone":"+34 968 18 23 11",
    "sg:postcode":"30740",
    "sg:province":"Murcia",
    "wof:name":"Piscinas Torrevieja S.l.",
    "wof:placetype":"venue"
},
  "geometry": {"coordinates":[-0.7932540178,37.8340911865],"type":"Point"}
}