{
  "type": "Feature",
  "properties": {
    "iso:country":"ES",
    "sg:address":"Carrer de Escocia, 50",
    "sg:city":"Barcelona",
    "sg:orig_category":"Centros Empresariales",
    "sg:phone":"+34 933 51 47 67",
    "sg:postcode":"08016",
    "sg:province":"Barcelona",
    "wof:name":"Syldeval Serveis Per Comunitat S.l.",
    "wof:placetype":"venue"
},
  "geometry": {"coordinates":[2.1806409359,41.4288024902],"type":"Point"}
}