{
  "type": "Feature",
  "properties": {
    "iso:country":"ES",
    "sg:address":"Rua Santiago, 4",
    "sg:city":"Betanzos",
    "sg:orig_category":"Librer\u00cdas",
    "sg:phone":"+34 981 77 13 55",
    "sg:postcode":"15300",
    "sg:province":"La Coru\u00f1a",
    "wof:name":"Ares Suarez Segundo Javier",
    "wof:placetype":"venue"
},
  "geometry": {"coordinates":[-8.2117595673,43.2811203003],"type":"Point"}
}