{
  "type": "Feature",
  "properties": {
    "iso:country":"ES",
    "sg:address":"Calle de Trafalgar, 19",
    "sg:city":"Madrid",
    "sg:orig_category":"Iglesia Cat\u00d3lica",
    "sg:phone":"+34 914 48 99 05",
    "sg:postcode":"28010",
    "sg:province":"Madrid",
    "wof:name":"Parroquia De Santa Feliciana. Madrid",
    "wof:placetype":"venue"
},
  "geometry": {"coordinates":[-3.7008056641,40.4319915771],"type":"Point"}
}