{
  "type": "Feature",
  "properties": {
    "iso:country":"ES",
    "sg:address":"Calle de Remedio, 2",
    "sg:city":"Villalpardo",
    "sg:orig_category":"Cajas Para Embalar",
    "sg:phone":"+34 962 31 13 37",
    "sg:postcode":"16270",
    "sg:province":"Cuenca",
    "wof:name":"Caja Rural Provincial De Cuenca",
    "wof:placetype":"venue"
},
  "geometry": {"coordinates":[-1.6245499849,39.4723129272],"type":"Point"}
}