{
  "type": "Feature",
  "properties": {
    "iso:country":"ES",
    "sg:address":"Rua Velazquez Moreno, 34",
    "sg:city":"Vigo",
    "sg:orig_category":"Perfumer\u00cda (al Por Menor)",
    "sg:phone":"+34 986 43 34 08",
    "sg:postcode":"36202",
    "sg:province":"Pontevedra",
    "wof:name":"Melchor Viso Sucesores S.l.",
    "wof:placetype":"venue"
},
  "geometry": {"coordinates":[-8.7219142914,42.2361946106],"type":"Point"}
}