{
  "type": "Feature",
  "properties": {
    "addr:full":"Avgd Reina Sofia (de La), 1 Petrer Alicante 03610",
    "addr:postcode":"03610",
    "iso:country":"ES",
    "sg:address":"Avgd Reina Sofia (de La), 1",
    "sg:city":"Petrer",
    "sg:orig_category":"M\u00c9dicos: Estomatolog\u00cda",
    "sg:phone":"+34 966 95 31 01",
    "sg:postcode":"03610",
    "sg:province":"Alicante",
    "wof:name":"Gonzalez Sanchez Juan Antonio",
    "wof:placetype":"venue"
},
  "geometry": {"coordinates":[-0.7755609751,38.4795608521],"type":"Point"}
}