{
  "type": "Feature",
  "properties": {
    "iso:country":"ES",
    "sg:address":"Calle de Adriano Vi, 29",
    "sg:city":"Vitoria-gasteiz",
    "sg:orig_category":"Fisioterapia",
    "sg:phone":"+34 945 22 94 04",
    "sg:postcode":"01008",
    "sg:province":"\u00c1lava",
    "wof:name":"Trivi\u00cfo Garcia Maria Del Carmen Magdalena",
    "wof:placetype":"venue"
},
  "geometry": {"coordinates":[-2.6869859695,42.8488845825],"type":"Point"}
}