{
  "type": "Feature",
  "properties": {
    "iso:country":"ES",
    "sg:address":"Carrer de Pere D'artes, 8",
    "sg:city":"Barcelona",
    "sg:orig_category":"Fabricaci\u00d3n De Peines Y De Accesorios De Peluquer\u00cda",
    "sg:phone":"+34 933 58 00 02",
    "sg:postcode":"08031",
    "sg:province":"Barcelona",
    "wof:name":"Sanchez Salom Ana Maria",
    "wof:placetype":"venue"
},
  "geometry": {"coordinates":[2.1634440422,41.4322395325],"type":"Point"}
}