{
  "type": "Feature",
  "properties": {
    "iso:country":"ES",
    "sg:address":"Calle de Pedrera, 3",
    "sg:city":"Tarazona Mancha",
    "sg:orig_category":"Confecci\u00d3n (fabricaci\u00d3n, Al Por Mayor)",
    "sg:phone":"+34 967 48 01 85",
    "sg:postcode":"02100",
    "sg:province":"Albacete",
    "wof:name":"Cortinas Pepe",
    "wof:placetype":"venue"
},
  "geometry": {"coordinates":[-1.9124020338,39.2646751404],"type":"Point"}
}