{
  "type": "Feature",
  "properties": {
    "iso:country":"ES",
    "sg:address":"Calle de Larga, 25",
    "sg:city":"Cabaco",
    "sg:orig_category":"Administraciones Regionales, Departamentales Y Locales",
    "sg:phone":"+34 923 45 40 16",
    "sg:postcode":"37620",
    "sg:province":"Salamanca",
    "wof:name":"Ayuntamiento De El Cabaco",
    "wof:placetype":"venue"
},
  "geometry": {"coordinates":[-6.1257162094,40.5648918152],"type":"Point"}
}