{
  "type": "Feature",
  "properties": {
    "iso:country":"ES",
    "sg:address":"Calle de Fuencarral, 45",
    "sg:city":"Madrid",
    "sg:orig_category":"Ropa Para Ni\u00d1os (al Por Menor)",
    "sg:phone":"+34 915 32 92 70",
    "sg:postcode":"28004",
    "sg:province":"Madrid",
    "wof:name":"Vintage And Retro S.l.",
    "wof:placetype":"venue"
},
  "geometry": {"coordinates":[-3.70084095,40.4233436584],"type":"Point"}
}