{
  "type": "Feature",
  "properties": {
    "addr:full":"Calle de Valencia, 40 Onil Alicante 03430",
    "addr:housenumber":"40",
    "addr:postcode":"03430",
    "addr:street":"Calle De Valencia",
    "iso:country":"ES",
    "sg:address":"Calle de Valencia, 40",
    "sg:city":"Onil",
    "sg:orig_category":"Tratamientos De Conversi\u00d3n Qu\u00cdmica O Electrol\u00cdtica De Metales",
    "sg:phone":"+34 965 56 49 86",
    "sg:postcode":"03430",
    "sg:province":"Alicante",
    "wof:name":"Comive Electromoldeo S.l.",
    "wof:placetype":"venue"
},
  "geometry": {"coordinates":[-0.6723579764,38.6314239502],"type":"Point"}
}