{
  "type": "Feature",
  "properties": {
    "addr:full":"Calle de Maestra Adela Perez (de La), 7 Driebes Guadalajara 19116",
    "addr:housenumber":"7",
    "addr:postcode":"19116",
    "addr:street":"Calle De Maestra Adela Perez De La",
    "iso:country":"ES",
    "sg:address":"Calle de Maestra Adela Perez (de La), 7",
    "sg:city":"Driebes",
    "sg:orig_category":"Asilos De Ancianos. Centros Privados",
    "sg:phone":"+34 949 38 91 95",
    "sg:postcode":"19116",
    "sg:province":"Guadalajara",
    "wof:name":"M.j.r. Galisteo Zazo S.l.",
    "wof:placetype":"venue"
},
  "geometry": {"coordinates":[-3.0445539951,40.2453155518],"type":"Point"}
}