{
  "type": "Feature",
  "properties": {
    "addr:full":"Rua Silleda, 4 Ca\u00f1iza Pontevedra 36880",
    "addr:housenumber":"4",
    "addr:postcode":"36880",
    "addr:street":"Rua Silleda",
    "iso:country":"ES",
    "sg:address":"Rua Silleda, 4",
    "sg:city":"Ca\u00f1iza",
    "sg:orig_category":"Transportes Por Carretera: Lotes Completos, Mercanc\u00cdas Diversas",
    "sg:phone":"+34 986 66 33 39",
    "sg:postcode":"36880",
    "sg:province":"Pontevedra",
    "wof:name":"Ignacio De Las Cuevas S.a.",
    "wof:placetype":"venue"
},
  "geometry": {"coordinates":[-8.273182869,42.2129859924],"type":"Point"}
}