{
  "type": "Feature",
  "properties": {
    "addr:full":"Rua Gran Via Alfonso Ix, 27 Sarria Lugo 27600",
    "addr:housenumber":"27",
    "addr:postcode":"27600",
    "addr:street":"Rua Gran Via Alfonso Ix",
    "iso:country":"ES",
    "sg:address":"Rua Gran Via Alfonso Ix, 27",
    "sg:city":"Sarria",
    "sg:orig_category":"Prot\u00c9sicos Dentales",
    "sg:phone":"+34 982 53 31 56",
    "sg:postcode":"27600",
    "sg:province":"Lugo",
    "wof:name":"S.j. Protesicos Dentales",
    "wof:placetype":"venue"
},
  "geometry": {"coordinates":[-7.4135627747,42.7805595398],"type":"Point"}
}