{
  "type": "Feature",
  "properties": {
    "iso:country":"ES",
    "sg:address":"Carrer de Olzinelles, 118",
    "sg:city":"Barcelona",
    "sg:orig_category":"Electrodom\u00c9sticos (al Por Menor)",
    "sg:phone":"+34 933 32 47 95",
    "sg:postcode":"08014",
    "sg:province":"Barcelona",
    "wof:name":"Goma Artigas Elvira",
    "wof:placetype":"venue"
},
  "geometry": {"coordinates":[2.1375370026,41.3702049255],"type":"Point"}
}