{
  "type": "Feature",
  "properties": {
    "addr:full":"Calle de Paris, 52 Malaga M\u00e1laga 29006",
    "addr:housenumber":"52",
    "addr:postcode":"29006",
    "addr:street":"Calle De Paris;Ma\u0301Laga",
    "iso:country":"ES",
    "sg:address":"Calle de Paris, 52",
    "sg:city":"Malaga",
    "sg:orig_category":"Chapister\u00cda",
    "sg:phone":"+34 952 31 01 40",
    "sg:postcode":"29006",
    "sg:province":"M\u00e1laga",
    "wof:name":"Pinturauto Color S.l.",
    "wof:placetype":"venue"
},
  "geometry": {"coordinates":[-4.4725809097,36.7027626038],"type":"Point"}
}