{
  "type": "Feature",
  "properties": {
    "iso:country":"ES",
    "sg:address":"Ctra. Madrid-burgos E Irun, Km. 0024,0",
    "sg:city":"Ciudalcampo-race",
    "sg:orig_category":"Fabricaci\u00d3n De Jabones, Detergentes Y Lej\u00cdas",
    "sg:phone":"+34 916 57 09 95",
    "sg:postcode":"28707",
    "sg:province":"Madrid",
    "wof:name":"Gringo S.l.",
    "wof:placetype":"venue"
},
  "geometry": {"coordinates":[-3.5853872299,40.6208381653],"type":"Point"}
}