{
  "type": "Feature",
  "properties": {
    "iso:country":"ES",
    "sg:address":"Plaz Goya, S/n",
    "sg:city":"Ejea De Los Caballeros",
    "sg:orig_category":"Centros De Educaci\u00d3n Especial",
    "sg:phone":"+34 976 66 28 65",
    "sg:postcode":"50600",
    "sg:province":"Zaragoza",
    "wof:name":"Centro Comarcal De Adultos",
    "wof:placetype":"venue"
},
  "geometry": {"coordinates":[-1.1382750273,42.1269798279],"type":"Point"}
}