{
  "type": "Feature",
  "properties": {
    "iso:country":"ES",
    "sg:address":"G.v. Fernando El Catolico, 17",
    "sg:city":"Valencia",
    "sg:orig_category":"Agentes Generales De Seguros",
    "sg:phone":"+34 963 85 30 51",
    "sg:postcode":"46008",
    "sg:province":"Valencia",
    "wof:name":"Marti Navarro Fernando Maria",
    "wof:placetype":"venue"
},
  "geometry": {"coordinates":[-0.3856000006,39.4705352783],"type":"Point"}
}