{
  "type": "Feature",
  "properties": {
    "iso:country":"ES",
    "sg:address":"Carr Ermita, 64",
    "sg:city":"Benifaio",
    "sg:orig_category":"Arreglo, Reparaci\u00d3n, Piezas Sueltas De Televisi\u00d3n, V\u00cddeo, Hi",
    "sg:phone":"+34 961 78 03 99",
    "sg:postcode":"46450",
    "sg:province":"Valencia",
    "wof:name":"Selma Soler Jose Luis",
    "wof:placetype":"venue"
},
  "geometry": {"coordinates":[-0.4287599921,39.2824363708],"type":"Point"}
}