{
  "type": "Feature",
  "properties": {
    "addr:full":"Carrer de Enric Alzamora, 2 Palma Islas Baleares 07002",
    "addr:housenumber":"2",
    "addr:postcode":"07002",
    "addr:street":"Carrer De Enric Alzamora",
    "iso:country":"ES",
    "sg:address":"Carrer de Enric Alzamora, 2",
    "sg:city":"Palma",
    "sg:orig_category":"Administradores De Bienes Y Delegados De Comunidades De Propietarios",
    "sg:phone":"+34 971 28 86 10",
    "sg:postcode":"07002",
    "sg:province":"Islas Baleares",
    "wof:name":"Administraciones Inmobiliarias Artieda S.l.",
    "wof:placetype":"venue"
},
  "geometry": {"coordinates":[2.6548805237,39.5739860535],"type":"Point"}
}