{
  "type": "Feature",
  "properties": {
    "addr:full":"Avda Europa (de), 14 Montilla C\u00f3rdoba 14550",
    "addr:housenumber":"14",
    "addr:postcode":"14550",
    "addr:street":"Avda Europa De;Co\u0301Rdoba",
    "iso:country":"ES",
    "sg:address":"Avda Europa (de), 14",
    "sg:city":"Montilla",
    "sg:orig_category":"Distribuci\u00d3n De Petr\u00d3leo Y Derivados",
    "sg:phone":"+34 957 65 00 03",
    "sg:postcode":"14550",
    "sg:province":"C\u00f3rdoba",
    "sg:website":"www.cepsa.es",
    "wof:name":"Sendaconde S.l.",
    "wof:placetype":"venue"
},
  "geometry": {"coordinates":[-4.652654171,37.5796966553],"type":"Point"}
}