{
  "type": "Feature",
  "properties": {
    "iso:country":"ES",
    "sg:address":"Calle de Mayor, 9",
    "sg:city":"Burgo Osma",
    "sg:orig_category":"Cajas Para Embalar",
    "sg:phone":"+34 975 34 08 11",
    "sg:postcode":"42300",
    "sg:province":"Soria",
    "sg:website":"www.cajarural.com",
    "wof:name":"Caja Rural Provincial De Soria",
    "wof:placetype":"venue"
},
  "geometry": {"coordinates":[-3.067291975,41.5872612],"type":"Point"}
}