{
  "type": "Feature",
  "properties": {
    "addr:full":"Avda Arlanzon, 11 Burgos Burgos 09004",
    "addr:housenumber":"11",
    "addr:postcode":"09004",
    "addr:street":"Avda Arlanzon",
    "iso:country":"ES",
    "sg:address":"Avda Arlanzon, 11",
    "sg:city":"Burgos",
    "sg:orig_category":"Sociedades, Compa\u00d1\u00cdas Aseguradoras",
    "sg:phone":"+34 947 20 52 69",
    "sg:postcode":"09004",
    "sg:province":"Burgos",
    "wof:name":"Helvetia Compa\u00f1ia Suiza De Seguros Y Reaseguros S.a.",
    "wof:placetype":"venue"
},
  "geometry": {"coordinates":[-3.6959080696,42.3412590027],"type":"Point"}
}