{
  "type": "Feature",
  "properties": {
    "addr:full":"Calle de Do\u00d1a Gonzala Santana, 2 Salamanca Salamanca 37001",
    "addr:housenumber":"2",
    "addr:postcode":"37001",
    "addr:street":"Calle De Don\u0303A;Santana",
    "iso:country":"ES",
    "sg:address":"Calle de Do\u00d1a Gonzala Santana, 2",
    "sg:city":"Salamanca",
    "sg:orig_category":"Caf\u00c9s, Bares, Cervecer\u00cdas",
    "sg:phone":"+34 923 26 83 22",
    "sg:postcode":"37001",
    "sg:province":"Salamanca",
    "wof:name":"R.s.r.s. C.b",
    "wof:placetype":"venue"
},
  "geometry": {"coordinates":[-5.6615009308,40.9645957947],"type":"Point"}
}