{
  "type": "Feature",
  "properties": {
    "iso:country":"ES",
    "sg:address":"Calle de Sol Oriente, 11",
    "sg:city":"Salamanca",
    "sg:classifiers":[
        {
            "category":"Communications",
            "type":"Services"
        }
    ],
    "sg:phone":"+34 923 28 13 05",
    "sg:postcode":"37002",
    "sg:province":"Salamanca",
    "sg:tags":[
        "televisiones",
        "y",
        "radio"
    ],
    "wof:name":"Radio Popular S.a. Cope",
    "wof:placetype":"venue"
},
  "geometry": {"coordinates":[-5.6630458832,40.9684524536],"type":"Point"}
}