{
  "type": "Feature",
  "properties": {
    "iso:country":"ES",
    "sg:address":"Calle de Matematico Pedrayes, 19",
    "sg:city":"Oviedo",
    "sg:orig_category":"Institutos De Belleza",
    "sg:phone":"+34 985 27 70 63",
    "sg:postcode":"33005",
    "sg:province":"Asturias",
    "wof:name":"Oliver Fonderiz Irene",
    "wof:placetype":"venue"
},
  "geometry": {"coordinates":[-5.8573288918,43.3622131348],"type":"Point"}
}