{
  "type": "Feature",
  "properties": {
    "addr:full":"Cervantes, S/n Sotogordo Ja\u00e9n 23529",
    "addr:housenumber":"s",
    "addr:postcode":"23529",
    "addr:street":"Cervantes;/ N Sotogordo Jae\u0301N",
    "iso:country":"ES",
    "sg:address":"Cervantes, S/n",
    "sg:city":"Sotogordo",
    "sg:orig_category":"Centros De Educaci\u00d3n Especial",
    "sg:phone":"+34 953 37 80 04",
    "sg:postcode":"23529",
    "sg:province":"Ja\u00e9n",
    "wof:name":"Junta De Andalucia",
    "wof:placetype":"venue"
},
  "geometry": {"coordinates":[-3.5413920879,37.9486999512],"type":"Point"}
}