{
  "type": "Feature",
  "properties": {
    "addr:full":"Mestral (urb Turons Del Valles), 20 Ametlla Valles Barcelona 08480",
    "addr:housenumber":"20",
    "addr:postcode":"08480",
    "addr:street":"Urb;Ametlla Valles Barcelona",
    "iso:country":"ES",
    "sg:address":"Mestral (urb Turons Del Valles), 20",
    "sg:city":"Ametlla Valles",
    "sg:orig_category":"Puertas Autom\u00c1ticas, Puertas De Garaje",
    "sg:phone":"+34 938 44 96 53",
    "sg:postcode":"08480",
    "sg:province":"Barcelona",
    "wof:name":"J.j.t. Henos Mancebo S.l.",
    "wof:placetype":"venue"
},
  "geometry": {"coordinates":[2.2506830692,41.6418762207],"type":"Point"}
}