{
  "type": "Feature",
  "properties": {
    "iso:country":"ES",
    "sg:address":"Rua Vila, 56",
    "sg:city":"San Cosme",
    "sg:orig_category":"Cajas Para Embalar",
    "sg:phone":"+34 982 12 46 01",
    "sg:postcode":"27279",
    "sg:province":"Lugo",
    "wof:name":"Caixa Rural Galega S.c.c.l.g.",
    "wof:placetype":"venue"
},
  "geometry": {"coordinates":[-7.3913669586,43.096660614],"type":"Point"}
}