{
  "type": "Feature",
  "properties": {
    "addr:full":"Calle de Rio Mundo, S/n Torre-pacheco Murcia 30700",
    "addr:postcode":"30700",
    "addr:street":"Calle De Rio Mundo S / N",
    "iso:country":"ES",
    "sg:address":"Calle de Rio Mundo, S/n",
    "sg:city":"Torre-pacheco",
    "sg:orig_category":"Promotores Constructores",
    "sg:phone":"+34 968 58 57 93",
    "sg:postcode":"30700",
    "sg:province":"Murcia",
    "wof:name":"Alzaplan S.l.",
    "wof:placetype":"venue"
},
  "geometry": {"coordinates":[-0.9479508996,37.7495689392],"type":"Point"}
}