{
  "type": "Feature",
  "properties": {
    "addr:full":"Carrer de Felip Ii, 159 Barcelona Barcelona 08027",
    "addr:housenumber":"159",
    "addr:postcode":"08027",
    "addr:street":"Carrer De Felip Ii",
    "iso:country":"ES",
    "sg:address":"Carrer de Felip Ii, 159",
    "sg:city":"Barcelona",
    "sg:orig_category":"Cl\u00cdnicas Dentales",
    "sg:phone":"+34 933 49 54 76",
    "sg:postcode":"08027",
    "sg:province":"Barcelona",
    "wof:name":"Clinica Dental Maragall S.a.",
    "wof:placetype":"venue"
},
  "geometry": {"coordinates":[2.1820681095,41.4239234924],"type":"Point"}
}