{
  "type": "Feature",
  "properties": {
    "addr:full":"Calle de General Mola, 2 Beniel Murcia 30130",
    "addr:housenumber":"2",
    "addr:postcode":"30130",
    "addr:street":"Calle De General Mola",
    "iso:country":"ES",
    "sg:address":"Calle de General Mola, 2",
    "sg:city":"Beniel",
    "sg:orig_category":"Perfumer\u00cda (al Por Menor)",
    "sg:phone":"+34 968 60 02 10",
    "sg:postcode":"30130",
    "sg:province":"Murcia",
    "wof:name":"Sevilla Zaragoza Luis",
    "wof:placetype":"venue"
},
  "geometry": {"coordinates":[-1.0017089844,38.0486526489],"type":"Point"}
}