{
  "type": "Feature",
  "properties": {
    "addr:full":"Avda Santa Coloma, 14 Angles Girona 17160",
    "addr:housenumber":"14",
    "addr:postcode":"17160",
    "addr:street":"Avda Santa Coloma",
    "iso:country":"ES",
    "sg:address":"Avda Santa Coloma, 14",
    "sg:city":"Angles",
    "sg:orig_category":"Mec\u00c1nico Del Autom\u00d3vil",
    "sg:phone":"+34 972 42 10 03",
    "sg:postcode":"17160",
    "sg:province":"Girona",
    "wof:name":"Vilaplana Nou Pere",
    "wof:placetype":"venue"
},
  "geometry": {"coordinates":[2.6403100491,41.9532203674],"type":"Point"}
}