{
  "type": "Feature",
  "properties": {
    "addr:full":"Calle de Buen Pastor, 21 Benidorm Alicante 03500",
    "addr:housenumber":"21",
    "addr:postcode":"03500",
    "addr:street":"Calle De Buen Pastor",
    "iso:country":"ES",
    "sg:address":"Calle de Buen Pastor, 21",
    "sg:city":"Benidorm",
    "sg:orig_category":"Distribuci\u00d3n De Petr\u00d3leo Y Derivados",
    "sg:phone":"+34 965 86 07 60",
    "sg:postcode":"03500",
    "sg:province":"Alicante",
    "wof:name":"Pescados Hermanos Martinez S.l.",
    "wof:placetype":"venue"
},
  "geometry": {"coordinates":[-0.133491993,38.5405502319],"type":"Point"}
}