{
  "type": "Feature",
  "properties": {
    "iso:country":"ES",
    "sg:address":"Calle de Camino De Malaga, 19",
    "sg:city":"Velez-malaga",
    "sg:orig_category":"Inmobiliaria (agencias)",
    "sg:phone":"+34 952 54 94 62",
    "sg:postcode":"29700",
    "sg:province":"M\u00e1laga",
    "wof:name":"Lopez Diaz Laureano",
    "wof:placetype":"venue"
},
  "geometry": {"coordinates":[-4.1035666466,36.7788391113],"type":"Point"}
}