{
  "type": "Feature",
  "properties": {
    "addr:full":"Zubitxo Kalea, 33 Lezo Guip\u00f9zcoa 20100",
    "addr:housenumber":"33",
    "addr:postcode":"20100",
    "addr:street":"Zubitxo Kalea;Guipu\u0300Zcoa",
    "iso:country":"ES",
    "sg:address":"Zubitxo Kalea, 33",
    "sg:city":"Lezo",
    "sg:orig_category":"Farmacias",
    "sg:phone":"+34 943 52 24 86",
    "sg:postcode":"20100",
    "sg:province":"Guip\u00f9zcoa",
    "wof:name":"Laboa Urchipia Inmaculada",
    "wof:placetype":"venue"
},
  "geometry": {"coordinates":[-1.8947019577,43.3213233948],"type":"Point"}
}