{
  "type": "Feature",
  "properties": {
    "addr:full":"Calle de Guezala Antonio Pintor, 3 Bilbao Vizcaya 48015",
    "addr:housenumber":"3",
    "addr:postcode":"48015",
    "addr:street":"Calle De Guezala Antonio Pintor",
    "iso:country":"ES",
    "sg:address":"Calle de Guezala Antonio Pintor, 3",
    "sg:city":"Bilbao",
    "sg:orig_category":"Electricidad: Instaladores",
    "sg:phone":"+34 944 01 47 76",
    "sg:postcode":"48015",
    "sg:province":"Vizcaya",
    "wof:name":"Talleres Electricos Mikel",
    "wof:placetype":"venue"
},
  "geometry": {"coordinates":[-2.9585258961,43.2779197693],"type":"Point"}
}