{
  "type": "Feature",
  "properties": {
    "addr:full":"Calle de Juan Quintanilla, 7 Lora Rio Sevilla 41440",
    "addr:housenumber":"7",
    "addr:postcode":"41440",
    "addr:street":"Calle De Juan Quintanilla;Rio Sevilla",
    "iso:country":"ES",
    "sg:address":"Calle de Juan Quintanilla, 7",
    "sg:city":"Lora Rio",
    "sg:orig_category":"Farmacias",
    "sg:phone":"+34 955 80 24 72",
    "sg:postcode":"41440",
    "sg:province":"Sevilla",
    "wof:name":"Recuero Recuero Maria Del Carmen",
    "wof:placetype":"venue"
},
  "geometry": {"coordinates":[-5.5301141739,37.6548461914],"type":"Point"}
}