{
  "type": "Feature",
  "properties": {
    "addr:full":"Calle de San Andres, 142 Coru\u00d1a La Coru\u00f1a 15003",
    "addr:housenumber":"142",
    "addr:postcode":"15003",
    "addr:street":"Calle De San Andres;La Corun\u0303A",
    "iso:country":"ES",
    "sg:address":"Calle de San Andres, 142",
    "sg:city":"Coru\u00d1a",
    "sg:orig_category":"Estancos",
    "sg:phone":"+34 981 22 66 73",
    "sg:postcode":"15003",
    "sg:province":"La Coru\u00f1a",
    "wof:name":"Posse Paz Enrique Juan",
    "wof:placetype":"venue"
},
  "geometry": {"coordinates":[-8.404499054,43.3692703247],"type":"Point"}
}