{
  "type": "Feature",
  "properties": {
    "iso:country":"ES",
    "sg:address":"Carr Valencia, 31",
    "sg:city":"Girona",
    "sg:orig_category":"Supermercados Y Hipermercados",
    "sg:phone":"+34 972 24 35 56",
    "sg:postcode":"17005",
    "sg:province":"Girona",
    "wof:name":"Illa Planella Pere",
    "wof:placetype":"venue"
},
  "geometry": {"coordinates":[2.8086740971,41.96875],"type":"Point"}
}