{
  "type": "Feature",
  "properties": {
    "addr:full":"G Pol Ind Comarca I (agustinos), S/n Iru\u00f1a Navarra 31013",
    "addr:housenumber":"s",
    "addr:postcode":"31013",
    "addr:street":"/ N Irun\u0303A Navarra",
    "iso:country":"ES",
    "sg:address":"G Pol Ind Comarca I (agustinos), S/n",
    "sg:city":"Iru\u00f1a",
    "sg:orig_category":"Tubos Met\u00c1licos",
    "sg:phone":"+34 948 30 91 10",
    "sg:postcode":"31013",
    "sg:province":"Navarra",
    "wof:name":"Aceros Calibrados S.a.",
    "wof:placetype":"venue"
},
  "geometry": {"coordinates":[-1.6442149878,42.8179893494],"type":"Point"}
}