{
  "type": "Feature",
  "properties": {
    "iso:country":"ES",
    "sg:address":"Calle de La Compa\u00d1ia, 13",
    "sg:city":"Trigueros",
    "sg:orig_category":"Quincaller\u00cda (al Por Menor)",
    "sg:phone":"+34 959 30 50 77",
    "sg:postcode":"21620",
    "sg:province":"Huelva",
    "wof:name":"Camacho Valera Antonio",
    "wof:placetype":"venue"
},
  "geometry": {"coordinates":[-6.8301939964,37.3829040527],"type":"Point"}
}