{
  "type": "Feature",
  "properties": {
    "addr:full":"Calle de Juan Carlos I, 18 Arnedo La Rioja 26580",
    "addr:housenumber":"18",
    "addr:postcode":"26580",
    "addr:street":"Calle De Juan Carlos I;Rioja",
    "iso:country":"ES",
    "sg:address":"Calle de Juan Carlos I, 18",
    "sg:city":"Arnedo",
    "sg:orig_category":"Cajas De Ahorro",
    "sg:phone":"+34 941 38 01 09",
    "sg:postcode":"26580",
    "sg:province":"La Rioja",
    "wof:name":"Caja De Ahorros Y Monte De Piedad De Zaragoza Aragon Y Rioja",
    "wof:placetype":"venue"
},
  "geometry": {"coordinates":[-2.100399971,42.2267875671],"type":"Point"}
}