{
  "type": "Feature",
  "properties": {
    "addr:full":"Carr Via (de La), S/n Cassa Selva Girona 17244",
    "addr:postcode":"17244",
    "addr:street":"Carr Via De La S / N Cassa Selva Girona",
    "iso:country":"ES",
    "sg:address":"Carr Via (de La), S/n",
    "sg:city":"Cassa Selva",
    "sg:orig_category":"Ebanister\u00cda",
    "sg:phone":"+34 972 46 12 10",
    "sg:postcode":"17244",
    "sg:province":"Girona",
    "wof:name":"Mobles Artigas S.l.",
    "wof:placetype":"venue"
},
  "geometry": {"coordinates":[2.8780760765,41.8896598816],"type":"Point"}
}