{
  "type": "Feature",
  "properties": {
    "addr:full":"Calle de Guipuzcoa, 45 Gijon Asturias 33210",
    "addr:housenumber":"45",
    "addr:postcode":"33210",
    "addr:street":"Calle De Guipuzcoa",
    "iso:country":"ES",
    "sg:address":"Calle de Guipuzcoa, 45",
    "sg:city":"Gijon",
    "sg:orig_category":"Compresores",
    "sg:phone":"+34 985 38 72 43",
    "sg:postcode":"33210",
    "sg:province":"Asturias",
    "wof:name":"Talleres Electromecanicos Vader S.l.",
    "wof:placetype":"venue"
},
  "geometry": {"coordinates":[-5.6752004623,43.5260772705],"type":"Point"}
}