{
  "type": "Feature",
  "properties": {
    "iso:country":"ES",
    "sg:address":"Calle de Salvador Cuyas, 17",
    "sg:city":"Palmas De Gran Canaria",
    "sg:orig_category":"Arquitectos",
    "sg:phone":"+34 928 27 72 90",
    "sg:postcode":"35008",
    "sg:province":"Las Palmas",
    "wof:name":"Medina Hernandez Humberto",
    "wof:placetype":"venue"
},
  "geometry": {"coordinates":[-15.4308691025,28.1438407898],"type":"Point"}
}