{
  "type": "Feature",
  "properties": {
    "iso:country":"ES",
    "sg:address":"C/ Segarra, 19",
    "sg:city":"Tarrega",
    "sg:orig_category":"Bricolaje, Herramientas (al Por Menor)",
    "sg:phone":"+34 973 31 47 05",
    "sg:postcode":"25300",
    "sg:province":"Lleida",
    "wof:name":"Bricourgell Scp",
    "wof:placetype":"venue"
},
  "geometry": {"coordinates":[1.1406450272,41.651424408],"type":"Point"}
}