{
  "type": "Feature",
  "properties": {
    "iso:country":"ES",
    "sg:address":"Plaz Nueva, 3",
    "sg:city":"Pe\u00e7aranda De Bracamonte",
    "sg:orig_category":"Electrodom\u00c9sticos (al Por Menor)",
    "sg:phone":"+34 923 54 18 43",
    "sg:postcode":"37300",
    "sg:province":"Salamanca",
    "wof:name":"Diaz Piedra Petra",
    "wof:placetype":"venue"
},
  "geometry": {"coordinates":[-5.2003889084,40.902671814],"type":"Point"}
}