{
  "type": "Feature",
  "properties": {
    "addr:full":"Avda Andalucia, 42 Puerta De Segura Ja\u00e9n 23360",
    "addr:housenumber":"42",
    "addr:postcode":"23360",
    "addr:street":"Avda Andalucia;Jae\u0301N",
    "iso:country":"ES",
    "sg:address":"Avda Andalucia, 42",
    "sg:city":"Puerta De Segura",
    "sg:orig_category":"Relojer\u00cda (al Por Menor, Reparaci\u00d3n)",
    "sg:phone":"+34 953 48 60 85",
    "sg:postcode":"23360",
    "sg:province":"Ja\u00e9n",
    "wof:name":"Hermanos Escabia Garcia C.b.",
    "wof:placetype":"venue"
},
  "geometry": {"coordinates":[-2.7384710312,38.3514518738],"type":"Point"}
}