{
  "type": "Feature",
  "properties": {
    "addr:full":"Calle de Vicente Marti, 49 Ceuti Murcia 30562",
    "addr:housenumber":"49",
    "addr:postcode":"30562",
    "addr:street":"Calle De Vicente Marti",
    "iso:country":"ES",
    "sg:address":"Calle de Vicente Marti, 49",
    "sg:city":"Ceuti",
    "sg:classifiers":[
        {
            "category":"Autos & Motor Vehicles",
            "subcategory":"Automobile Sales",
            "type":"Retail Goods"
        }
    ],
    "sg:phone":"+34 968 69 34 50",
    "sg:postcode":"30562",
    "sg:province":"Murcia",
    "wof:name":"Autoescuela Pepe Y Dori S.l",
    "wof:placetype":"venue"
},
  "geometry": {"coordinates":[-1.2763990164,38.0793495178],"type":"Point"}
}