{
  "type": "Feature",
  "properties": {
    "iso:country":"ES",
    "sg:address":"Carrer de Passeig, 13",
    "sg:city":"Castellar Valles",
    "sg:orig_category":"Inmobiliaria (agencias)",
    "sg:phone":"+34 937 47 24 24",
    "sg:postcode":"08211",
    "sg:province":"Barcelona",
    "wof:name":"Comunidad De Propietarios Passeig 13-19",
    "wof:placetype":"venue"
},
  "geometry": {"coordinates":[2.0856359005,41.6153640747],"type":"Point"}
}