{
  "type": "Feature",
  "properties": {
    "addr:full":"Calle de Feria, 4 Albacete Albacete 02005",
    "addr:housenumber":"4",
    "addr:postcode":"02005",
    "addr:street":"Calle De Feria",
    "iso:country":"ES",
    "sg:address":"Calle de Feria, 4",
    "sg:city":"Albacete",
    "sg:orig_category":"Supermercados Y Hipermercados",
    "sg:phone":"+34 967 52 22 89",
    "sg:postcode":"02005",
    "sg:province":"Albacete",
    "wof:name":"Caprabo S.a.",
    "wof:placetype":"venue"
},
  "geometry": {"coordinates":[-1.8601690531,38.9959106445],"type":"Point"}
}