{
  "type": "Feature",
  "properties": {
    "addr:full":"Ctra Alicun (de), S/n Roquetas Mar Almer\u00eda 04740",
    "addr:postcode":"04740",
    "addr:street":"Ctra Alicun De S / N Roquetas Mar Almeri\u0301A",
    "iso:country":"ES",
    "sg:address":"Ctra Alicun (de), S/n",
    "sg:city":"Roquetas Mar",
    "sg:orig_category":"Caf\u00c9s, Bares, Cervecer\u00cdas",
    "sg:phone":"+34 950 32 10 32",
    "sg:postcode":"04740",
    "sg:province":"Almer\u00eda",
    "sg:website":"www.cafedeindias.com",
    "wof:name":"De Casas Y Gonzalez C.b.",
    "wof:placetype":"venue"
},
  "geometry": {"coordinates":[-2.6083889008,36.7824935913],"type":"Point"}
}