{
  "type": "Feature",
  "properties": {
    "addr:full":"Calle de Presbitero Juan Arocha Ayala, S/n Ingenio Las Palmas 35250",
    "addr:housenumber":"s / n",
    "addr:postcode":"35250",
    "addr:street":"Calle De Presbitero Juan Arocha Ayala",
    "iso:country":"ES",
    "sg:address":"Calle de Presbitero Juan Arocha Ayala, S/n",
    "sg:city":"Ingenio",
    "sg:orig_category":"Sales (al Por Mayor)",
    "sg:phone":"+34 928 78 41 90",
    "sg:postcode":"35250",
    "sg:province":"Las Palmas",
    "wof:name":"Mojo Canarion Artiles Ramirez S.l.u.",
    "wof:placetype":"venue"
},
  "geometry": {"coordinates":[-15.4393758774,27.9252891541],"type":"Point"}
}