{
  "type": "Feature",
  "properties": {
    "iso:country":"ES",
    "sg:address":"Calle de Reinante, 10",
    "sg:city":"Ribadeo",
    "sg:orig_category":"Muebles, Minoristas",
    "sg:phone":"+34 982 12 83 91",
    "sg:postcode":"27700",
    "sg:province":"Lugo",
    "wof:name":"Ron Novo Jose",
    "wof:placetype":"venue"
},
  "geometry": {"coordinates":[-7.0414919853,43.5362167358],"type":"Point"}
}