{
  "type": "Feature",
  "properties": {
    "iso:country":"ES",
    "sg:address":"Trav Garcia Lorca(urb Monteazahar), 2",
    "sg:city":"Beniajan",
    "sg:orig_category":"Institutos De Belleza",
    "sg:phone":"+34 968 82 25 61",
    "sg:postcode":"30570",
    "sg:province":"Murcia",
    "wof:name":"Martinez Lopez Sonia",
    "wof:placetype":"venue"
},
  "geometry": {"coordinates":[-1.0805039406,37.9669761658],"type":"Point"}
}