{
  "type": "Feature",
  "properties": {
    "addr:full":"Avda Regne De Valencia, 40 Valencia Valencia 46005",
    "addr:housenumber":"40",
    "addr:postcode":"46005",
    "addr:street":"Avda Regne De Valencia",
    "iso:country":"ES",
    "sg:address":"Avda Regne De Valencia, 40",
    "sg:city":"Valencia",
    "sg:orig_category":"Ense\u00d1anza, Formaci\u00d3n Profesional: Aprendizaje",
    "sg:phone":"+34 963 74 65 92",
    "sg:postcode":"46005",
    "sg:province":"Valencia",
    "sg:website":"www.escueladeartesanos.com",
    "wof:name":"Escuela De Artesanos Fundacion De La Comunidad Valenciana",
    "wof:placetype":"venue"
},
  "geometry": {"coordinates":[-0.3689900041,39.4637832642],"type":"Point"}
}