{
  "type": "Feature",
  "properties": {
    "addr:full":"Calle de Konporte, 30 Algorta Vizcaya 48992",
    "addr:housenumber":"30",
    "addr:postcode":"48992",
    "addr:street":"Calle De Konporte",
    "iso:country":"ES",
    "sg:address":"Calle de Konporte, 30",
    "sg:city":"Algorta",
    "sg:classifiers":[
        {
            "category":"Government",
            "subcategory":"Post Office",
            "type":"Public Place"
        }
    ],
    "sg:phone":"+34 944 60 26 03",
    "sg:postcode":"48992",
    "sg:province":"Vizcaya",
    "sg:tags":[
        "de",
        "yoga",
        "clases"
    ],
    "wof:name":"Benito Escondrillas Luis Miguel De",
    "wof:placetype":"venue"
},
  "geometry": {"coordinates":[-3.0062129498,43.344909668],"type":"Point"}
}