{
  "type": "Feature",
  "properties": {
    "iso:country":"ES",
    "sg:address":"Calle de Erdikokale, 3",
    "sg:city":"Mutriku",
    "sg:orig_category":"Farmacias",
    "sg:phone":"+34 943 60 32 50",
    "sg:postcode":"20830",
    "sg:province":"Guip\u00f9zcoa",
    "wof:name":"Apraiz Maturana Lon",
    "wof:placetype":"venue"
},
  "geometry": {"coordinates":[-2.386623621,43.3074035645],"type":"Point"}
}