{
  "type": "Feature",
  "properties": {
    "iso:country":"ES",
    "sg:address":"Avda Descubrimientos (los), S/n",
    "sg:city":"Mairena Aljarafe",
    "sg:orig_category":"Promotores Constructores",
    "sg:phone":"+34 955 60 22 22",
    "sg:postcode":"41927",
    "sg:province":"Sevilla",
    "sg:website":"www.aljapisa.com",
    "wof:name":"Inmobiliaria Aljapisa S.l.",
    "wof:placetype":"venue"
},
  "geometry": {"coordinates":[-6.048664093,37.3507614136],"type":"Point"}
}