{
  "type": "Feature",
  "properties": {
    "addr:full":"Calle de Eridano, 8 Madrid Madrid 28023",
    "addr:housenumber":"8",
    "addr:postcode":"madrid;28023",
    "addr:street":"Calle De Eridano",
    "iso:country":"ES",
    "sg:address":"Calle de Eridano, 8",
    "sg:city":"Madrid",
    "sg:orig_category":"Locales Y Clases De Danza",
    "sg:phone":"+34 913 57 36 07",
    "sg:postcode":"28023",
    "sg:province":"Madrid",
    "wof:name":"Corral Zunzunegui Marta Del",
    "wof:placetype":"venue"
},
  "geometry": {"coordinates":[-3.7862820625,40.4568061829],"type":"Point"}
}