{
  "type": "Feature",
  "properties": {
    "iso:country":"ES",
    "sg:address":"Mestre Goldar, 20",
    "sg:city":"Vigo",
    "sg:orig_category":"Molduras, Junquillos, Listones Y Molduras Perforadas",
    "sg:phone":"+34 986 23 45 61",
    "sg:postcode":"36213",
    "sg:province":"Pontevedra",
    "wof:name":"Groba Prego Eduardo",
    "wof:placetype":"venue"
},
  "geometry": {"coordinates":[-8.7258586884,42.2104797363],"type":"Point"}
}