{
  "type": "Feature",
  "properties": {
    "addr:full":"Carrer de Marina, 287 Barcelona Barcelona 08025",
    "addr:housenumber":"287",
    "addr:postcode":"08025",
    "addr:street":"Carrer De Marina",
    "iso:country":"ES",
    "sg:address":"Carrer de Marina, 287",
    "sg:city":"Barcelona",
    "sg:orig_category":"Agentes, Concesionarios Y Sucursales De Veh\u00cdculos",
    "sg:phone":"+34 934 36 50 35",
    "sg:postcode":"08025",
    "sg:province":"Barcelona",
    "wof:name":"Auto Serveis California S.a.l.",
    "wof:placetype":"venue"
},
  "geometry": {"coordinates":[2.1724529266,41.4058151245],"type":"Point"}
}