{
  "type": "Feature",
  "properties": {
    "iso:country":"ES",
    "sg:address":"Calle de Doctor Fleming, 4",
    "sg:city":"Coru\u00d1a",
    "sg:orig_category":"Bazares, Art\u00cdculos De Limpieza Y De Cocina (al Por Menor)",
    "sg:phone":"+34 981 24 52 81",
    "sg:postcode":"15005",
    "sg:province":"La Coru\u00f1a",
    "wof:name":"Refojo Jimenez Manuela",
    "wof:placetype":"venue"
},
  "geometry": {"coordinates":[-8.4089641571,43.3605232239],"type":"Point"}
}