{
  "type": "Feature",
  "properties": {
    "iso:country":"ES",
    "sg:address":"Rua Paz, 14",
    "sg:city":"Vigo",
    "sg:orig_category":"Comercio De Piezas De Recambio Y De Accesorios De Veh\u00cdculos, Veh\u00cdculos Industriales",
    "sg:phone":"+34 986 24 24 32",
    "sg:postcode":"36202",
    "sg:province":"Pontevedra",
    "wof:name":"Cecauto Norte S.a.",
    "wof:placetype":"venue"
},
  "geometry": {"coordinates":[-8.7355709076,42.2281723022],"type":"Point"}
}