{
  "type": "Feature",
  "properties": {
    "addr:full":"Calle de Barbate, 3 Benalup C\u00e1diz 11190",
    "addr:housenumber":"3",
    "addr:postcode":"11190",
    "addr:street":"Calle De Barbate;Ca\u0301Diz",
    "iso:country":"ES",
    "sg:address":"Calle de Barbate, 3",
    "sg:city":"Benalup",
    "sg:orig_category":"Contenedores (mercanc\u00cdas)",
    "sg:phone":"+34 956 42 45 12",
    "sg:postcode":"11190",
    "sg:province":"C\u00e1diz",
    "wof:name":"Perez Rodriguez Mario",
    "wof:placetype":"venue"
},
  "geometry": {"coordinates":[-5.8129701614,36.3453598022],"type":"Point"}
}