{
  "type": "Feature",
  "properties": {
    "iso:country":"ES",
    "sg:address":"Ctra De Cordoba-almeria, S/n",
    "sg:city":"Cambil",
    "sg:orig_category":"Ingeniero",
    "sg:phone":"+34 953 30 03 38",
    "sg:postcode":"23120",
    "sg:province":"Ja\u00e9n",
    "wof:name":"Gerion Ingenieria S.l.",
    "wof:placetype":"venue"
},
  "geometry": {"coordinates":[-3.446857214,37.6534576416],"type":"Point"}
}