{
  "type": "Feature",
  "properties": {
    "iso:country":"ES",
    "sg:address":"Rua Zamora, 39",
    "sg:city":"Vigo",
    "sg:orig_category":"Asesor\u00cda Sobre Comunicaci\u00d3n De Empresas",
    "sg:phone":"+34 986 48 34 34",
    "sg:postcode":"36203",
    "sg:province":"Pontevedra",
    "wof:name":"Martinez Lopez Antonio",
    "wof:placetype":"venue"
},
  "geometry": {"coordinates":[-8.7221069336,42.2257614136],"type":"Point"}
}