{
  "type": "Feature",
  "properties": {
    "addr:full":"Calle de Lucena, S/n Moriles C\u00f3rdoba 14510",
    "addr:housenumber":"s / n",
    "addr:postcode":"14510",
    "addr:street":"Calle De Lucena",
    "iso:country":"ES",
    "sg:address":"Calle de Lucena, S/n",
    "sg:city":"Moriles",
    "sg:orig_category":"Mec\u00c1nico Del Autom\u00d3vil",
    "sg:phone":"+34 957 53 74 04",
    "sg:postcode":"14510",
    "sg:province":"C\u00f3rdoba",
    "wof:name":"Auto Moriles S.l.",
    "wof:placetype":"venue"
},
  "geometry": {"coordinates":[-4.6064872742,37.4350280762],"type":"Point"}
}