{
  "type": "Feature",
  "properties": {
    "addr:full":"Ctra De La Rasa, S/n Burgo Osma Soria 42300",
    "addr:housenumber":"s / n",
    "addr:postcode":"42300",
    "addr:street":"Ctra De La Rasa",
    "iso:country":"ES",
    "sg:address":"Ctra De La Rasa, S/n",
    "sg:city":"Burgo Osma",
    "sg:orig_category":"Empresas De Carpinter\u00cda De Madera",
    "sg:phone":"+34 975 34 05 33",
    "sg:postcode":"42300",
    "sg:province":"Soria",
    "wof:name":"Puertas Uxama",
    "wof:placetype":"venue"
},
  "geometry": {"coordinates":[-3.0742990971,41.5880050659],"type":"Point"}
}