{
  "type": "Feature",
  "properties": {
    "iso:country":"ES",
    "sg:address":"Calle de San Sebastian, 25",
    "sg:city":"Tarifa",
    "sg:orig_category":"Poller\u00cda Y Caza (al Por Menor)",
    "sg:phone":"+34 956 68 43 57",
    "sg:postcode":"11380",
    "sg:province":"C\u00e1diz",
    "wof:name":"Araujo Espinosa Juan",
    "wof:placetype":"venue"
},
  "geometry": {"coordinates":[-5.607301712,36.0155258179],"type":"Point"}
}