{
  "type": "Feature",
  "properties": {
    "addr:full":"Calle de Cuesta De Moyano, 34 Perales De Taju\u00e7a Madrid 28540",
    "addr:housenumber":"34",
    "addr:postcode":"28540",
    "addr:street":"Calle De Cuesta De Moyano",
    "iso:country":"ES",
    "sg:address":"Calle de Cuesta De Moyano, 34",
    "sg:city":"Perales De Taju\u00e7a",
    "sg:orig_category":"Confecci\u00d3n De Guantes",
    "sg:phone":"+34 918 74 85 76",
    "sg:postcode":"28540",
    "sg:province":"Madrid",
    "wof:name":"Creaciones Gloria S. L.",
    "wof:placetype":"venue"
},
  "geometry": {"coordinates":[-3.3551568985,40.233631134],"type":"Point"}
}