{
  "type": "Feature",
  "properties": {
    "addr:full":"Calle de Cebolla, 2 Domingo Perez Toledo 45544",
    "addr:housenumber":"2",
    "addr:postcode":"45544",
    "addr:street":"Calle De Cebolla;Perez",
    "iso:country":"ES",
    "sg:address":"Calle de Cebolla, 2",
    "sg:city":"Domingo Perez",
    "sg:orig_category":"Iglesia Cat\u00d3lica",
    "sg:phone":"+34 925 88 05 05",
    "sg:postcode":"45544",
    "sg:province":"Toledo",
    "wof:name":"Parroquia Purisima Concepcion",
    "wof:placetype":"venue"
},
  "geometry": {"coordinates":[-4.5054783821,39.9756317139],"type":"Point"}
}