{
  "type": "Feature",
  "properties": {
    "addr:full":"Carr Torre La, 9 Igualada Barcelona 08700",
    "addr:housenumber":"9",
    "addr:postcode":"08700",
    "addr:street":"Carr Torre La",
    "iso:country":"ES",
    "sg:address":"Carr Torre La, 9",
    "sg:city":"Igualada",
    "sg:orig_category":"Asociaciones Y Clubs Deportivos",
    "sg:phone":"+34 938 03 96 89",
    "sg:postcode":"08700",
    "sg:province":"Barcelona",
    "wof:name":"Barquilla Perianes Josep Maria",
    "wof:placetype":"venue"
},
  "geometry": {"coordinates":[1.6323850155,41.5766448975],"type":"Point"}
}