{
  "type": "Feature",
  "properties": {
    "addr:full":"Av La Paz, 36 Onil Alicante 03430",
    "addr:housenumber":"36",
    "addr:postcode":"03430",
    "addr:street":"Av La Paz",
    "iso:country":"ES",
    "sg:address":"Av La Paz, 36",
    "sg:city":"Onil",
    "sg:orig_category":"Asesor\u00cda Fiscal Y Jur\u00cddica",
    "sg:phone":"+34 965 56 40 00",
    "sg:postcode":"03430",
    "sg:province":"Alicante",
    "wof:name":"Asesoria Fedeco S.l",
    "wof:placetype":"venue"
},
  "geometry": {"coordinates":[-0.6770418882,38.6278038025],"type":"Point"}
}