{
  "type": "Feature",
  "properties": {
    "iso:country":"ES",
    "sg:address":"Rua Horreos, 3",
    "sg:city":"Arteixo",
    "sg:orig_category":"Chapister\u00cda",
    "sg:phone":"+34 981 60 10 04",
    "sg:postcode":"15142",
    "sg:province":"La Coru\u00f1a",
    "wof:name":"Auto Taller El Castro S.l.",
    "wof:placetype":"venue"
},
  "geometry": {"coordinates":[-8.4961338043,43.3135566711],"type":"Point"}
}