{
  "type": "Feature",
  "properties": {
    "addr:full":"Calle de Moraleda, 22 Huetor-vega Granada 18198",
    "addr:housenumber":"22",
    "addr:postcode":"18198",
    "addr:street":"Calle De Moraleda",
    "iso:country":"ES",
    "sg:address":"Calle de Moraleda, 22",
    "sg:city":"Huetor-vega",
    "sg:orig_category":"Promotores Constructores",
    "sg:phone":"+34 958 50 07 29",
    "sg:postcode":"18198",
    "sg:province":"Granada",
    "wof:name":"Ortiz Molina S.l.",
    "wof:placetype":"venue"
},
  "geometry": {"coordinates":[-3.573734045,37.1474075317],"type":"Point"}
}