{
  "type": "Feature",
  "properties": {
    "addr:full":"Rua Pontevedra, 14 Cambados Pontevedra 36630",
    "addr:housenumber":"14",
    "addr:postcode":"36630",
    "addr:street":"Rua Pontevedra",
    "iso:country":"ES",
    "sg:address":"Rua Pontevedra, 14",
    "sg:city":"Cambados",
    "sg:orig_category":"Hoteles",
    "sg:phone":"+34 986 52 08 07",
    "sg:postcode":"36630",
    "sg:province":"Pontevedra",
    "wof:name":"Martinez Martinez Josefa",
    "wof:placetype":"venue"
},
  "geometry": {"coordinates":[-8.8137540817,42.5147743225],"type":"Point"}
}