{
  "type": "Feature",
  "properties": {
    "addr:full":"Ctra. Villabuena, 29 Ba\u00f1os Ebro \u00c1lava 01307",
    "addr:housenumber":"29",
    "addr:postcode":"01307",
    "addr:street":"Ctra. Villabuena",
    "iso:country":"ES",
    "sg:address":"Ctra. Villabuena, 29",
    "sg:city":"Ba\u00f1os Ebro",
    "sg:orig_category":"Productores Recolectores, Venta Directa De Vinos",
    "sg:phone":"+34 945 60 90 37",
    "sg:postcode":"01307",
    "sg:province":"\u00c1lava",
    "wof:name":"Bodegas Berzal Otero S.cv.",
    "wof:placetype":"venue"
},
  "geometry": {"coordinates":[-2.6686489582,42.5500984192],"type":"Point"}
}