{
  "type": "Feature",
  "properties": {
    "iso:country":"ES",
    "sg:address":"Calle de Tomas Maestre, S/n",
    "sg:city":"Catedral",
    "sg:orig_category":"\u00d3ptica: Instrumentos (fabricaci\u00d3n)",
    "sg:phone":"+34 968 21 01 33",
    "sg:postcode":"30004",
    "sg:province":"Murcia",
    "sg:website":"www.visionlab.es",
    "wof:name":"Visionlab S.a.",
    "wof:placetype":"venue"
},
  "geometry": {"coordinates":[-1.1313140392,37.9835090637],"type":"Point"}
}