{
  "type": "Feature",
  "properties": {
    "iso:country":"ES",
    "sg:address":"Rua Simon Bolivar, 8",
    "sg:city":"Vigo",
    "sg:orig_category":"Iglesia Cat\u00d3lica",
    "sg:phone":"+34 986 22 50 80",
    "sg:postcode":"36203",
    "sg:province":"Pontevedra",
    "wof:name":"Obispado Tui-vigo. Parroquia De San Xoan De Avila-vigo",
    "wof:placetype":"venue"
},
  "geometry": {"coordinates":[-8.7193584442,42.2337532043],"type":"Point"}
}