{
  "type": "Feature",
  "properties": {
    "iso:country":"ES",
    "sg:address":"Calle de Moli, 6",
    "sg:city":"Sant Joan De Mediona",
    "sg:orig_category":"Poller\u00cda Y Caza (al Por Menor)",
    "sg:phone":"+34 938 98 50 29",
    "sg:postcode":"08773",
    "sg:province":"Barcelona",
    "wof:name":"Gustems Raja Joan",
    "wof:placetype":"venue"
},
  "geometry": {"coordinates":[1.6139169931,41.4741821289],"type":"Point"}
}