{
  "type": "Feature",
  "properties": {
    "addr:full":"Calle de Hernando Colon, 18 Sevilla Sevilla 41004",
    "addr:housenumber":"18",
    "addr:postcode":"41004",
    "addr:street":"Calle De Hernando Colon",
    "iso:country":"ES",
    "sg:address":"Calle de Hernando Colon, 18",
    "sg:city":"Sevilla",
    "sg:orig_category":"Promotores Constructores",
    "sg:phone":"+34 954 21 20 75",
    "sg:postcode":"41004",
    "sg:province":"Sevilla",
    "sg:website":"www.promosal.com",
    "wof:name":"Promosal Inmuebles S.l.",
    "wof:placetype":"venue"
},
  "geometry": {"coordinates":[-5.9934492111,37.3874092102],"type":"Point"}
}