{
  "type": "Feature",
  "properties": {
    "addr:full":"Urbitarte Auzunea, 1 Azpeitia Guip\u00f9zcoa 20730",
    "addr:housenumber":"1",
    "addr:postcode":"20730",
    "addr:street":"Urbitarte Auzunea;Guipu\u0300Zcoa",
    "iso:country":"ES",
    "sg:address":"Urbitarte Auzunea, 1",
    "sg:city":"Azpeitia",
    "sg:orig_category":"Servicio De Salud",
    "sg:phone":"+34 943 81 11 79",
    "sg:postcode":"20730",
    "sg:province":"Guip\u00f9zcoa",
    "wof:name":"Gorrochategui Mugica Vicente",
    "wof:placetype":"venue"
},
  "geometry": {"coordinates":[-2.2699460983,43.1788711548],"type":"Point"}
}