{
  "type": "Feature",
  "properties": {
    "addr:full":"Calle de Avila, S/n Alcala Henares Madrid 28804",
    "addr:postcode":"28804",
    "addr:street":"Calle De Avila S / N",
    "iso:country":"ES",
    "sg:address":"Calle de Avila, S/n",
    "sg:city":"Alcala Henares",
    "sg:orig_category":"Centros De Educaci\u00d3n Especial",
    "sg:phone":"+34 918 89 45 78",
    "sg:postcode":"28804",
    "sg:province":"Madrid",
    "wof:name":"Comunidad Autonoma De Madrid-centros De Educacion",
    "wof:placetype":"venue"
},
  "geometry": {"coordinates":[-3.3534247875,40.4969520569],"type":"Point"}
}