{
  "type": "Feature",
  "properties": {
    "iso:country":"ES",
    "sg:address":"Calle de Fe, 1",
    "sg:city":"Madrid",
    "sg:orig_category":"Molduras, Junquillos, Listones Y Molduras Perforadas",
    "sg:phone":"+34 915 27 56 49",
    "sg:postcode":"28012",
    "sg:province":"Madrid",
    "wof:name":"Martin Sevilla Ana Isabel",
    "wof:placetype":"venue"
},
  "geometry": {"coordinates":[-3.7008650303,40.4091300964],"type":"Point"}
}