{
  "type": "Feature",
  "properties": {
    "addr:full":"Calle de Jose Lopez E Higueras, 3 Yuncos Toledo 45210",
    "addr:housenumber":"3",
    "addr:postcode":"45210",
    "addr:street":"Calle De Jose Lopez E Higueras",
    "iso:country":"ES",
    "sg:address":"Calle de Jose Lopez E Higueras, 3",
    "sg:city":"Yuncos",
    "sg:orig_category":"Inmobiliaria (agencias)",
    "sg:phone":"+34 925 55 72 10",
    "sg:postcode":"45210",
    "sg:province":"Toledo",
    "wof:name":"Viviendas Procalama S.l.",
    "wof:placetype":"venue"
},
  "geometry": {"coordinates":[-3.8738439083,40.0850982666],"type":"Point"}
}