{
  "type": "Feature",
  "properties": {
    "addr:full":"Pla\u00c7 Sant Eudald, 2 Centre Urba Girona 17500",
    "addr:housenumber":"2;urba",
    "addr:postcode":"17500",
    "addr:street":"Eudald",
    "iso:country":"ES",
    "sg:address":"Pla\u00c7 Sant Eudald, 2",
    "sg:city":"Centre Urba",
    "sg:orig_category":"Farmacias",
    "sg:phone":"+34 972 70 02 61",
    "sg:postcode":"17500",
    "sg:province":"Girona",
    "wof:name":"Sargatal Pellicer Maria Merce",
    "wof:placetype":"venue"
},
  "geometry": {"coordinates":[2.1959049702,42.1965866089],"type":"Point"}
}