{
  "type": "Feature",
  "properties": {
    "iso:country":"ES",
    "sg:address":"Ant. Carpinteros, 10",
    "sg:city":"Carmona",
    "sg:orig_category":"Arquitectos",
    "sg:phone":"+34 954 14 04 10",
    "sg:postcode":"41410",
    "sg:province":"Sevilla",
    "wof:name":"Millan Jimenez Maria Mireya",
    "wof:placetype":"venue"
},
  "geometry": {"coordinates":[-5.6433792114,37.4708709717],"type":"Point"}
}