{
  "type": "Feature",
  "properties": {
    "addr:full":"Urb A\u00f1oretagolf, 10 Rincon Victoria M\u00e1laga 29730",
    "addr:housenumber":"10",
    "addr:postcode":"29730",
    "addr:street":"Urb An\u0303Oretagolf;Ma\u0301Laga",
    "iso:country":"ES",
    "sg:address":"Urb A\u00f1oretagolf, 10",
    "sg:city":"Rincon Victoria",
    "sg:orig_category":"Agencias Y Agentes Comerciales, Representantes",
    "sg:phone":"+34 952 03 27 16",
    "sg:postcode":"29730",
    "sg:province":"M\u00e1laga",
    "wof:name":"Lottrup  Pierre",
    "wof:placetype":"venue"
},
  "geometry": {"coordinates":[-4.4200186729,36.7196464539],"type":"Point"}
}