{
  "type": "Feature",
  "properties": {
    "iso:country":"ES",
    "sg:address":"Carrer de Nou Del Nord, 19",
    "sg:city":"Carrer De Dalt -pineda -pla De L'alzina",
    "sg:orig_category":"Cerrajer\u00cda, Ferrallista",
    "sg:phone":"+34 938 64 82 58",
    "sg:postcode":"08184",
    "sg:province":"Barcelona",
    "wof:name":"Joan Olive S.l.",
    "wof:placetype":"venue"
},
  "geometry": {"coordinates":[2.1779334545,41.5977897644],"type":"Point"}
}