{
  "type": "Feature",
  "properties": {
    "addr:full":"Av Verge Montserrat, 78 Prat Llobregat Barcelona 08820",
    "addr:housenumber":"78",
    "addr:postcode":"08820",
    "addr:street":"Av Verge Montserrat;Llobregat",
    "iso:country":"ES",
    "sg:address":"Av Verge Montserrat, 78",
    "sg:city":"Prat Llobregat",
    "sg:orig_category":"Bisuter\u00cda, Joyer\u00cda, Relojer\u00cda (al Por Menor)",
    "sg:phone":"+34 933 79 42 84",
    "sg:postcode":"08820",
    "sg:province":"Barcelona",
    "wof:name":"Rodriguez Velasco Jesusa",
    "wof:placetype":"venue"
},
  "geometry": {"coordinates":[2.0864720345,41.3289909363],"type":"Point"}
}