{
  "type": "Feature",
  "properties": {
    "iso:country":"ES",
    "sg:address":"Calle de Godofredo Ortega Y Mu\u00d1oz, 17",
    "sg:city":"Badajoz",
    "sg:orig_category":"Asociaciones Y Clubs Deportivos",
    "sg:phone":"+34 924 25 69 77",
    "sg:postcode":"06011",
    "sg:province":"Badajoz",
    "wof:name":"Escobar Sanchez Maria De Guadalupe",
    "wof:placetype":"venue"
},
  "geometry": {"coordinates":[-6.9863348007,38.8665084839],"type":"Point"}
}