{
  "type": "Feature",
  "properties": {
    "addr:full":"Guaita, 1 Riudecanyes Tarragona 43771",
    "addr:housenumber":"1",
    "addr:postcode":"43771",
    "addr:street":"Guaita",
    "iso:country":"ES",
    "sg:address":"Guaita, 1",
    "sg:city":"Riudecanyes",
    "sg:orig_category":"Empresarios",
    "sg:phone":"+34 977 83 40 76",
    "sg:postcode":"43771",
    "sg:province":"Tarragona",
    "wof:name":"Nolla Salvado Pablo",
    "wof:placetype":"venue"
},
  "geometry": {"coordinates":[0.9603250027,41.1294898987],"type":"Point"}
}