{
  "type": "Feature",
  "properties": {
    "iso:country":"ES",
    "sg:address":"C/ Muro, 1",
    "sg:city":"Alcoi",
    "sg:orig_category":"Reposter\u00cdas",
    "sg:phone":"+34 965 33 15 87",
    "sg:postcode":"03804",
    "sg:province":"Alicante",
    "wof:name":"Panificadora Celenpan S. L.",
    "wof:placetype":"venue"
},
  "geometry": {"coordinates":[-0.4643549919,38.7070960999],"type":"Point"}
}