{
  "type": "Feature",
  "properties": {
    "addr:full":"Calle de San Martin (de), 7 Pinto Madrid 28320",
    "addr:postcode":"28320",
    "addr:street":"Calle De",
    "iso:country":"ES",
    "sg:address":"Calle de San Martin (de), 7",
    "sg:city":"Pinto",
    "sg:orig_category":"Electricidad: Instaladores",
    "sg:phone":"+34 916 92 14 73",
    "sg:postcode":"28320",
    "sg:province":"Madrid",
    "wof:name":"Ingenieria Y Construcciones Electricas S.a.",
    "wof:placetype":"venue"
},
  "geometry": {"coordinates":[-3.6970059872,40.2415809631],"type":"Point"}
}