{
  "type": "Feature",
  "properties": {
    "iso:country":"ES",
    "sg:address":"Carrer de Salvador Espriu, 80",
    "sg:city":"Mataro",
    "sg:orig_category":"Ropa Y Accesorios",
    "sg:phone":"+34 937 57 79 92",
    "sg:postcode":"08304",
    "sg:province":"Barcelona",
    "wof:name":"Maria De Los Angeles Miranda Martinez S.l.",
    "wof:placetype":"venue"
},
  "geometry": {"coordinates":[2.4427039623,41.553237915],"type":"Point"}
}