{
  "type": "Feature",
  "properties": {
    "iso:country":"ES",
    "sg:address":"Avda Rodriguez Acosta, 6",
    "sg:city":"Motril",
    "sg:orig_category":"Centros Empresariales",
    "sg:phone":"+34 958 60 83 67",
    "sg:postcode":"18600",
    "sg:province":"Granada",
    "wof:name":"Ana Belen Fernandez Gonzalez Sll",
    "wof:placetype":"venue"
},
  "geometry": {"coordinates":[-3.5162000656,36.7440490723],"type":"Point"}
}