{
  "type": "Feature",
  "properties": {
    "addr:full":"C/ Concepcion Arenal, 135 Elche Alicante 03204",
    "addr:housenumber":"135",
    "addr:postcode":"03204",
    "addr:street":"C / Concepcion Arenal",
    "iso:country":"ES",
    "sg:address":"C/ Concepcion Arenal, 135",
    "sg:city":"Elche",
    "sg:orig_category":"Chapister\u00cda",
    "sg:phone":"+34 966 63 41 36",
    "sg:postcode":"03204",
    "sg:province":"Alicante",
    "wof:name":"Talleres Terol S.l.",
    "wof:placetype":"venue"
},
  "geometry": {"coordinates":[-0.7076100111,38.2597808838],"type":"Point"}
}