{
  "type": "Feature",
  "properties": {
    "addr:full":"Calle de Matadero, 4 Tomelloso Ciudad Real 13700",
    "addr:housenumber":"4",
    "addr:postcode":"13700",
    "addr:street":"Calle De Matadero",
    "iso:country":"ES",
    "sg:address":"Calle de Matadero, 4",
    "sg:city":"Tomelloso",
    "sg:orig_category":"Supermercados Y Hipermercados",
    "sg:phone":"+34 926 51 23 79",
    "sg:postcode":"13700",
    "sg:province":"Ciudad Real",
    "wof:name":"Diez Lopez Juan Carlos",
    "wof:placetype":"venue"
},
  "geometry": {"coordinates":[-3.0334589481,39.1528892517],"type":"Point"}
}