{
  "type": "Feature",
  "properties": {
    "addr:full":"Calle de Jose Ramon Diez De Revenga, 5 Pozo Ca\u00e7ada Albacete 02510",
    "addr:housenumber":"5",
    "addr:postcode":"02510",
    "addr:street":"Calle De Jose Ramon;Revenga",
    "iso:country":"ES",
    "sg:address":"Calle de Jose Ramon Diez De Revenga, 5",
    "sg:city":"Pozo Ca\u00e7ada",
    "sg:orig_category":"Panader\u00cdas, Pasteler\u00cdas, Boller\u00cda Industriale (fabricaci\u00d3n, Al Por Mayor)",
    "sg:phone":"+34 967 25 02 09",
    "sg:postcode":"02510",
    "sg:province":"Albacete",
    "wof:name":"Panaderia Bolleria Jesus S.l.",
    "wof:placetype":"venue"
},
  "geometry": {"coordinates":[-1.7355890274,38.8000793457],"type":"Point"}
}