{
  "type": "Feature",
  "properties": {
    "iso:country":"ES",
    "sg:address":"Ctra. Estacion, 6",
    "sg:city":"Bienvenida",
    "sg:orig_category":"Plomeros",
    "sg:phone":"+34 924 50 63 89",
    "sg:postcode":"06250",
    "sg:province":"Badajoz",
    "wof:name":"Alava Cortes Antonio",
    "wof:placetype":"venue"
},
  "geometry": {"coordinates":[-6.2044153214,38.2984161377],"type":"Point"}
}