{
  "type": "Feature",
  "properties": {
    "iso:country":"ES",
    "sg:address":"Crt. Valtablado, S/n",
    "sg:city":"Ocentojo",
    "sg:orig_category":"Sales (al Por Mayor)",
    "sg:phone":"+34 949 81 41 14",
    "sg:postcode":"19432",
    "sg:province":"Guadalajara",
    "wof:name":"Salinas De Ocentejo S.a",
    "wof:placetype":"venue"
},
  "geometry": {"coordinates":[-2.4188001156,40.8321685791],"type":"Point"}
}