{
  "type": "Feature",
  "properties": {
    "addr:full":"Calle de Rio Valdemarias, 24 Poligono Sta M. De Benquerencia Toledo 45007",
    "addr:housenumber":"24 poligono",
    "addr:postcode":"45007",
    "addr:street":"Calle De Rio Valdemarias;Sta M. De Benquerencia",
    "iso:country":"ES",
    "sg:address":"Calle de Rio Valdemarias, 24",
    "sg:city":"Poligono Sta M. De Benquerencia",
    "sg:orig_category":"Servicios De Telecomunicaciones",
    "sg:phone":"+34 925 23 23 32",
    "sg:postcode":"45007",
    "sg:province":"Toledo",
    "wof:name":"Intelcom 2000 S.l.",
    "wof:placetype":"venue"
},
  "geometry": {"coordinates":[-3.9480690956,39.8688201904],"type":"Point"}
}