{
  "type": "Feature",
  "properties": {
    "addr:full":"Carrer de Moscou, 26 Barcelona Barcelona 08005",
    "addr:housenumber":"26",
    "addr:postcode":"08005",
    "addr:street":"Carrer De Moscou",
    "iso:country":"ES",
    "sg:address":"Carrer de Moscou, 26",
    "sg:city":"Barcelona",
    "sg:orig_category":"Confecci\u00d3n (fabricaci\u00d3n, Al Por Mayor)",
    "sg:phone":"+34 932 21 69 58",
    "sg:postcode":"08005",
    "sg:province":"Barcelona",
    "wof:name":"De La Fuente Pons Fernando",
    "wof:placetype":"venue"
},
  "geometry": {"coordinates":[2.1944229603,41.3896102905],"type":"Point"}
}