{
  "type": "Feature",
  "properties": {
    "addr:full":"Calle de Valcarlos, 34 Madrid Madrid 28050",
    "addr:housenumber":"34",
    "addr:postcode":"madrid;28050",
    "addr:street":"Calle De Valcarlos",
    "iso:country":"ES",
    "sg:address":"Calle de Valcarlos, 34",
    "sg:city":"Madrid",
    "sg:orig_category":"Ingenier\u00cda, Centros De Estudios (diversos)",
    "sg:phone":"+34 914 27 01 00",
    "sg:postcode":"28050",
    "sg:province":"Madrid",
    "wof:name":"Roesma Gabinete De Proyectos S.l.",
    "wof:placetype":"venue"
},
  "geometry": {"coordinates":[-3.6635730267,40.5055580139],"type":"Point"}
}