{
  "type": "Feature",
  "properties": {
    "iso:country":"ES",
    "sg:address":"Calle de Leonardo Da Vinci, S/n",
    "sg:city":"Maracena",
    "sg:orig_category":"Centros Empresariales",
    "sg:phone":"+34 958 42 11 66",
    "sg:postcode":"18200",
    "sg:province":"Granada",
    "wof:name":"Nora Y M\u00aa Paz, Cb",
    "wof:placetype":"venue"
},
  "geometry": {"coordinates":[-3.6315739155,37.2074699402],"type":"Point"}
}