{
  "type": "Feature",
  "properties": {
    "iso:country":"ES",
    "sg:address":"Union, 42",
    "sg:city":"Vecindario",
    "sg:orig_category":"Molduras, Junquillos, Listones Y Molduras Perforadas",
    "sg:phone":"+34 928 75 57 21",
    "sg:postcode":"35110",
    "sg:province":"Las Palmas",
    "wof:name":"Jesus Garcia Luis Antonio",
    "wof:placetype":"venue"
},
  "geometry": {"coordinates":[-15.4467802048,27.8487281799],"type":"Point"}
}