{
  "type": "Feature",
  "properties": {
    "addr:full":"Carrer de Mont Ral, 21 Barcelona Barcelona 08042",
    "addr:housenumber":"21",
    "addr:postcode":"08042",
    "addr:street":"Carrer De Mont Ral",
    "iso:country":"ES",
    "sg:address":"Carrer de Mont Ral, 21",
    "sg:city":"Barcelona",
    "sg:orig_category":"Maquinaria Para Industrias Diversas",
    "sg:phone":"+34 934 27 35 45",
    "sg:postcode":"08042",
    "sg:province":"Barcelona",
    "wof:name":"Torres Montejo Jose",
    "wof:placetype":"venue"
},
  "geometry": {"coordinates":[2.1630740166,41.4380683899],"type":"Point"}
}