{
  "type": "Feature",
  "properties": {
    "iso:country":"ES",
    "sg:address":"Crta. Solana, S/n",
    "sg:city":"Tomelloso",
    "sg:orig_category":"Confecci\u00d3n De Trajes Para Se\u00d1oras",
    "sg:phone":"+34 926 51 48 58",
    "sg:postcode":"13700",
    "sg:province":"Ciudad Real",
    "wof:name":"Confecciones Ca\u00f1as S.l.",
    "wof:placetype":"venue"
},
  "geometry": {"coordinates":[-3.0052940845,39.1665611267],"type":"Point"}
}