{
  "type": "Feature",
  "properties": {
    "iso:country":"ES",
    "sg:address":"Calle de Veronica (la), 17",
    "sg:city":"Santa Faz",
    "sg:orig_category":"Transportes Por Carretera: Lotes Completos, Mercanc\u00cdas Diversas",
    "sg:phone":"+34 965 65 65 12",
    "sg:postcode":"03550",
    "sg:province":"Alicante",
    "wof:name":"G.m.a. S.l.",
    "wof:placetype":"venue"
},
  "geometry": {"coordinates":[-0.4373329878,38.4024848938],"type":"Point"}
}