{
  "type": "Feature",
  "properties": {
    "iso:country":"ES",
    "sg:address":"Calle de Fuerteventura, S/n",
    "sg:city":"San Fernando",
    "sg:orig_category":"Zapatos (al Por Menor)",
    "sg:phone":"+34 928 77 80 67",
    "sg:postcode":"35100",
    "sg:province":"Las Palmas",
    "wof:name":"Perez Hidalgo Candida Petra",
    "wof:placetype":"venue"
},
  "geometry": {"coordinates":[-15.5842504501,28.0904903412],"type":"Point"}
}