{
  "type": "Feature",
  "properties": {
    "iso:country":"ES",
    "sg:address":"Ctra. Girona Olot, Km. 0027,1",
    "sg:city":"S. Ferriol",
    "sg:orig_category":"Distribuci\u00d3n De Petr\u00d3leo Y Derivados",
    "sg:phone":"+34 972 59 32 09",
    "sg:postcode":"17850",
    "sg:province":"Girona",
    "wof:name":"Velogas S.a.",
    "wof:placetype":"venue"
},
  "geometry": {"coordinates":[2.6976718903,42.2003211975],"type":"Point"}
}