{
  "type": "Feature",
  "properties": {
    "addr:full":"Calle de Teniente Pe\u00d1alver, 7 Prado Del Rey C\u00e1diz 11660",
    "addr:housenumber":"7",
    "addr:postcode":"11660",
    "addr:street":"Calle De Teniente Pen\u0303Alver",
    "iso:country":"ES",
    "sg:address":"Calle de Teniente Pe\u00d1alver, 7",
    "sg:city":"Prado Del Rey",
    "sg:orig_category":"Cajas Para Embalar",
    "sg:phone":"+34 956 72 34 82",
    "sg:postcode":"11660",
    "sg:province":"C\u00e1diz",
    "wof:name":"Caja Rural Del Sur Sociedad Cooperativa",
    "wof:placetype":"venue"
},
  "geometry": {"coordinates":[-5.5565290451,36.7883987427],"type":"Point"}
}