{
  "type": "Feature",
  "properties": {
    "iso:country":"ES",
    "sg:address":"Calle de Italia, 2",
    "sg:city":"Alacant",
    "sg:orig_category":"Abogados",
    "sg:phone":"+34 965 92 91 61",
    "sg:postcode":"03003",
    "sg:province":"Alicante",
    "wof:name":"Gimenez Artes Alberto Luis",
    "wof:placetype":"venue"
},
  "geometry": {"coordinates":[-0.4881150126,38.3419914246],"type":"Point"}
}