{
  "type": "Feature",
  "properties": {
    "iso:country":"ES",
    "sg:address":"Avda Matias Mena, S/n",
    "sg:city":"Cevico De La Torre",
    "sg:orig_category":"Reciclaje, Tratamiento De Pl\u00c1sticos",
    "sg:phone":"+34 979 78 31 87",
    "sg:postcode":"34218",
    "sg:province":"Palencia",
    "wof:name":"Plasticos Arranz S.l.",
    "wof:placetype":"venue"
},
  "geometry": {"coordinates":[-4.4114642143,41.852355957],"type":"Point"}
}