{
  "type": "Feature",
  "properties": {
    "iso:country":"ES",
    "sg:address":"Carr Mercaders, 30",
    "sg:city":"Girona",
    "sg:orig_category":"Florister\u00cdas",
    "sg:phone":"+34 972 20 64 78",
    "sg:postcode":"17004",
    "sg:province":"Girona",
    "wof:name":"Dalmau Borch Anna Maria",
    "wof:placetype":"venue"
},
  "geometry": {"coordinates":[2.8249819279,41.9844207764],"type":"Point"}
}