{
  "type": "Feature",
  "properties": {
    "iso:country":"ES",
    "sg:address":"Calle de Remedios, 17",
    "sg:city":"Navalmorales",
    "sg:orig_category":"Aceites Y Grasas Alimentarias (fabricaci\u00d3n, Al Por Mayor)",
    "sg:phone":"+34 925 40 42 87",
    "sg:postcode":"45140",
    "sg:province":"Toledo",
    "wof:name":"Aceites Mencia S.l.",
    "wof:placetype":"venue"
},
  "geometry": {"coordinates":[-4.6362986565,39.7301597595],"type":"Point"}
}