{
  "type": "Feature",
  "properties": {
    "addr:full":"Carrer de Santa Maria (de), 84 Vilassar De Mar Barcelona 08340",
    "addr:postcode":"08340",
    "addr:street":"Carrer De Santa",
    "iso:country":"ES",
    "sg:address":"Carrer de Santa Maria (de), 84",
    "sg:city":"Vilassar De Mar",
    "sg:orig_category":"Institutos De Belleza (productos Y Aparatos)",
    "sg:phone":"+34 937 59 42 41",
    "sg:postcode":"08340",
    "sg:province":"Barcelona",
    "wof:name":"Rio Tao S.l.",
    "wof:placetype":"venue"
},
  "geometry": {"coordinates":[2.3855619431,41.5018920898],"type":"Point"}
}