{
  "type": "Feature",
  "properties": {
    "addr:full":"Trva Teatinos, 2 Soria Soria 42002",
    "addr:housenumber":"2",
    "addr:postcode":"42002",
    "addr:street":"Trva Teatinos",
    "iso:country":"ES",
    "sg:address":"Trva Teatinos, 2",
    "sg:city":"Soria",
    "sg:orig_category":"Ropa Para Se\u00d1oras Y Caballeros (al Por Menor)",
    "sg:phone":"+34 975 21 27 88",
    "sg:postcode":"42002",
    "sg:province":"Soria",
    "wof:name":"Jose Luis Y Miguel Angel Martinez Sanchez Cdad.",
    "wof:placetype":"venue"
},
  "geometry": {"coordinates":[-2.4658510685,41.7648391724],"type":"Point"}
}