{
  "type": "Feature",
  "properties": {
    "addr:full":"P. I. Ciudad Blanca, S/n Dos Hermanas Sevilla 41700",
    "addr:housenumber":"s / n",
    "addr:postcode":"41700",
    "addr:street":"P. I. Ciudad Blanca",
    "iso:country":"ES",
    "sg:address":"P. I. Ciudad Blanca, S/n",
    "sg:city":"Dos Hermanas",
    "sg:orig_category":"Fabricaci\u00d3n De Capiteles",
    "sg:phone":"+34 955 67 57 25",
    "sg:postcode":"41700",
    "sg:province":"Sevilla",
    "wof:name":"Jose Luis Campos Aparicio Manufacturas De Objetos De Lona S.l.",
    "wof:placetype":"venue"
},
  "geometry": {"coordinates":[-5.9262075424,37.2705421448],"type":"Point"}
}