{
  "type": "Feature",
  "properties": {
    "addr:full":"Carrer de Font (de La), 16 Almoster Tarragona 43393",
    "addr:housenumber":"16",
    "addr:postcode":"43393",
    "addr:street":"Carrer De Font De La",
    "iso:country":"ES",
    "sg:address":"Carrer de Font (de La), 16",
    "sg:city":"Almoster",
    "sg:orig_category":"Cooperativas Agr\u00cdcolas",
    "sg:phone":"+34 977 85 51 36",
    "sg:postcode":"43393",
    "sg:province":"Tarragona",
    "wof:name":"Cooperativa Agricola D'almoster",
    "wof:placetype":"venue"
},
  "geometry": {"coordinates":[1.1128009558,41.1974334717],"type":"Point"}
}