{
  "type": "Feature",
  "properties": {
    "addr:full":"Afores, S/n Horta S. Joan Tarragona 43596",
    "addr:housenumber":"s / n",
    "addr:postcode":"43596",
    "addr:street":"Afores;Horta S. Joan",
    "iso:country":"ES",
    "sg:address":"Afores, S/n",
    "sg:city":"Horta S. Joan",
    "sg:orig_category":"Distribuci\u00d3n De Petr\u00d3leo Y Derivados",
    "sg:phone":"+34 977 43 56 95",
    "sg:postcode":"43596",
    "sg:province":"Tarragona",
    "wof:name":"Tejedor Micolau Miguel",
    "wof:placetype":"venue"
},
  "geometry": {"coordinates":[0.3148899972,40.9543838501],"type":"Point"}
}