{
  "type": "Feature",
  "properties": {
    "addr:full":"Calle de Corpus Christi, 2 Toledo Toledo 45005",
    "addr:housenumber":"2",
    "addr:postcode":"45005",
    "addr:street":"Calle De Corpus Christi",
    "iso:country":"ES",
    "sg:address":"Calle de Corpus Christi, 2",
    "sg:city":"Toledo",
    "sg:orig_category":"Ingenier\u00cda, Centros De Estudios (diversos)",
    "sg:phone":"+34 925 25 45 36",
    "sg:postcode":"45005",
    "sg:province":"Toledo",
    "wof:name":"Diaz Plaza Dionisio",
    "wof:placetype":"venue"
},
  "geometry": {"coordinates":[-4.0323162079,39.8747520447],"type":"Point"}
}