{
  "type": "Feature",
  "properties": {
    "iso:country":"ES",
    "sg:address":"Avgd Princep D'espanya, 6",
    "sg:city":"Alcudia",
    "sg:orig_category":"Inmobiliaria (agencias)",
    "sg:phone":"+34 971 54 66 69",
    "sg:postcode":"07400",
    "sg:province":"Islas Baleares",
    "wof:name":"M.beltran Insular S.l.",
    "wof:placetype":"venue"
},
  "geometry": {"coordinates":[3.1235249043,39.8517875671],"type":"Point"}
}