{
  "type": "Feature",
  "properties": {
    "iso:country":"ES",
    "sg:address":"Carrer de Bonaplata, 49",
    "sg:city":"Barcelona",
    "sg:orig_category":"Producci\u00d3n, Comercio De Cereales",
    "sg:phone":"+34 932 03 34 52",
    "sg:postcode":"08034",
    "sg:province":"Barcelona",
    "wof:name":"Mestieri S.l.",
    "wof:placetype":"venue"
},
  "geometry": {"coordinates":[2.124119997,41.396156311],"type":"Point"}
}