{
  "type": "Feature",
  "properties": {
    "addr:full":"Ctra. Hormigos, Km. 0001,0 Casar Escalona Toledo 45542",
    "addr:postcode":"45542",
    "addr:street":"Ctra. Hormigos Km. 0001,0",
    "iso:country":"ES",
    "sg:address":"Ctra. Hormigos, Km. 0001,0",
    "sg:city":"Casar Escalona",
    "sg:orig_category":"Ense\u00d1anza Agr\u00cdcola",
    "sg:phone":"+34 925 86 41 55",
    "sg:postcode":"45542",
    "sg:province":"Toledo",
    "wof:name":"International College Spain S.a.",
    "wof:placetype":"venue"
},
  "geometry": {"coordinates":[-4.5237989426,40.0466804504],"type":"Point"}
}