{
  "type": "Feature",
  "properties": {
    "iso:country":"ES",
    "sg:address":"Carrer de Marquesos De Barbera, 107",
    "sg:city":"Barbera Valles",
    "sg:orig_category":"Empresas De Carpinter\u00cda De Madera",
    "sg:phone":"+34 937 29 18 37",
    "sg:postcode":"08210",
    "sg:province":"Barcelona",
    "wof:name":"Carpinteria Yoni E Hijos S.c.p",
    "wof:placetype":"venue"
},
  "geometry": {"coordinates":[2.11845994,41.5185089111],"type":"Point"}
}