{
  "type": "Feature",
  "properties": {
    "addr:full":"Pla\u00c7 Sant Pere, 4 Sueca Valencia 46410",
    "addr:housenumber":"4",
    "addr:postcode":"46410",
    "addr:street":"Sant Pere",
    "iso:country":"ES",
    "sg:address":"Pla\u00c7 Sant Pere, 4",
    "sg:city":"Sueca",
    "sg:orig_category":"Farmacias",
    "sg:phone":"+34 961 70 03 24",
    "sg:postcode":"46410",
    "sg:province":"Valencia",
    "wof:name":"Piera Ventura Alejandra",
    "wof:placetype":"venue"
},
  "geometry": {"coordinates":[-0.3102099895,39.2016487122],"type":"Point"}
}