{
  "type": "Feature",
  "properties": {
    "addr:full":"Carrer de Muntaner, 178 Barcelona Barcelona 08036",
    "addr:housenumber":"178",
    "addr:postcode":"08036",
    "addr:street":"Carrer De Muntaner",
    "iso:country":"ES",
    "sg:address":"Carrer de Muntaner, 178",
    "sg:city":"Barcelona",
    "sg:orig_category":"Asesor\u00cdas Y Estudios Financieros",
    "sg:phone":"+34 933 21 18 81",
    "sg:postcode":"08036",
    "sg:province":"Barcelona",
    "wof:name":"Desenvolupament I Societat Estudis S.a.",
    "wof:placetype":"venue"
},
  "geometry": {"coordinates":[2.1523549557,41.392124176],"type":"Point"}
}