{
  "type": "Feature",
  "properties": {
    "iso:country":"ES",
    "sg:address":"Carrer de Mallorca, 451",
    "sg:city":"Barcelona",
    "sg:orig_category":"Platos Preparados Refrigerados (fabricaci\u00d3n, Al Por Mayor)",
    "sg:phone":"+34 934 56 07 69",
    "sg:postcode":"08013",
    "sg:province":"Barcelona",
    "wof:name":"Busines Two S.a.",
    "wof:placetype":"venue"
},
  "geometry": {"coordinates":[2.1782948971,41.4058380127],"type":"Point"}
}