{
  "type": "Feature",
  "properties": {
    "iso:country":"ES",
    "sg:address":"Calle de Habana (de La), 41",
    "sg:city":"Fuenlabrada",
    "sg:orig_category":"Empresas De Carpinter\u00cda De Madera",
    "sg:phone":"+34 916 06 66 31",
    "sg:postcode":"28945",
    "sg:province":"Madrid",
    "wof:name":"Lara Antequera Jose Luis",
    "wof:placetype":"venue"
},
  "geometry": {"coordinates":[-3.7843089104,40.2934646606],"type":"Point"}
}