{
  "type": "Feature",
  "properties": {
    "addr:full":"Urb La Florida, S/n Punta Prima Alicante 03189",
    "addr:postcode":"03189",
    "addr:street":"La Florida S / N",
    "iso:country":"ES",
    "sg:address":"Urb La Florida, S/n",
    "sg:city":"Punta Prima",
    "sg:orig_category":"Molduras, Junquillos, Listones Y Molduras Perforadas",
    "sg:phone":"+34 965 32 51 47",
    "sg:postcode":"03189",
    "sg:province":"Alicante",
    "wof:name":"Carpena Falco Francisco Jose",
    "wof:placetype":"venue"
},
  "geometry": {"coordinates":[-0.7534540296,37.9003753662],"type":"Point"}
}