{
  "type": "Feature",
  "properties": {
    "addr:full":"Calle de Doctor Cuesta Olay, 13 Nore\u00f1a Asturias 33180",
    "addr:housenumber":"13",
    "addr:postcode":"33180",
    "addr:street":"Calle De Doctor Cuesta Olay;Asturias",
    "iso:country":"ES",
    "sg:address":"Calle de Doctor Cuesta Olay, 13",
    "sg:city":"Nore\u00f1a",
    "sg:orig_category":"Arquitectos",
    "sg:phone":"+34 985 74 10 10",
    "sg:postcode":"33180",
    "sg:province":"Asturias",
    "wof:name":"Canga Fernandez Emilio",
    "wof:placetype":"venue"
},
  "geometry": {"coordinates":[-5.7020292282,43.4001083374],"type":"Point"}
}