{
  "type": "Feature",
  "properties": {
    "iso:country":"ES",
    "sg:address":"Calle de Alvarez De Baena, 2",
    "sg:city":"Madrid",
    "sg:orig_category":"Inform\u00c1tica Equipo Y Programas (al Por Mayor)",
    "sg:phone":"+34 915 62 76 37",
    "sg:postcode":"28006",
    "sg:province":"Madrid",
    "sg:website":"www.softwareag.com/spain",
    "wof:name":"Software Ag Espa\u00f1a S.a.",
    "wof:placetype":"venue"
},
  "geometry": {"coordinates":[-3.6890254021,40.4382705688],"type":"Point"}
}