{
  "type": "Feature",
  "properties": {
    "iso:country":"ES",
    "sg:address":"Calle de Parroco Jacinto Muela, 2",
    "sg:city":"Carolina",
    "sg:orig_category":"Abogados",
    "sg:phone":"+34 953 68 00 94",
    "sg:postcode":"23200",
    "sg:province":"Ja\u00e9n",
    "wof:name":"Perez Gelde Antonio",
    "wof:placetype":"venue"
},
  "geometry": {"coordinates":[-3.614989996,38.2744903564],"type":"Point"}
}