{
  "type": "Feature",
  "properties": {
    "iso:country":"ES",
    "sg:address":"Jabali-los Monteros, 17",
    "sg:city":"Marbella",
    "sg:orig_category":"Empresas De Electricidad En General",
    "sg:phone":"+34 952 86 65 77",
    "sg:postcode":"29600",
    "sg:province":"M\u00e1laga",
    "wof:name":"Hidroelectrica Del Cadagua S.a.",
    "wof:placetype":"venue"
},
  "geometry": {"coordinates":[-4.8833007812,36.5079956055],"type":"Point"}
}