{
  "type": "Feature",
  "properties": {
    "iso:country":"ES",
    "sg:address":"Carrer de Providencia, 103",
    "sg:city":"Barcelona",
    "sg:orig_category":"Peluqueros: De Se\u00d1oras",
    "sg:phone":"+34 932 10 62 52",
    "sg:postcode":"08024",
    "sg:province":"Barcelona",
    "wof:name":"Gil Rodriguez Cristina",
    "wof:placetype":"venue"
},
  "geometry": {"coordinates":[2.1605989933,41.4089050293],"type":"Point"}
}