{
  "type": "Feature",
  "properties": {
    "addr:full":"Avda Andalucia, 11 Arjonilla Ja\u00e9n 23750",
    "addr:housenumber":"11",
    "addr:postcode":"23750",
    "addr:street":"Avda Andalucia",
    "iso:country":"ES",
    "sg:address":"Avda Andalucia, 11",
    "sg:city":"Arjonilla",
    "sg:orig_category":"Cajas De Ahorro",
    "sg:phone":"+34 953 52 00 10",
    "sg:postcode":"23750",
    "sg:province":"Ja\u00e9n",
    "wof:name":"Unicaja",
    "wof:placetype":"venue"
},
  "geometry": {"coordinates":[-4.1049838066,37.9735374451],"type":"Point"}
}