{
  "type": "Feature",
  "properties": {
    "iso:country":"ES",
    "sg:address":"Calle de Angel Guimera, 3",
    "sg:city":"Arguineguin",
    "sg:orig_category":"Importaci\u00d3n",
    "sg:phone":"+34 928 18 51 05",
    "sg:postcode":"35120",
    "sg:province":"Las Palmas",
    "wof:name":"Segura Navarro Emilio Carmelo",
    "wof:placetype":"venue"
},
  "geometry": {"coordinates":[-15.682923317,27.7610874176],"type":"Point"}
}