{
  "type": "Feature",
  "properties": {
    "addr:full":"R\u00edo Tinto, 24 Valencia Valencia 46012",
    "addr:housenumber":"24",
    "addr:postcode":"46012",
    "addr:street":"Ri\u0301O Tinto",
    "iso:country":"ES",
    "sg:address":"R\u00edo Tinto, 24",
    "sg:city":"Valencia",
    "sg:orig_category":"Chapister\u00cda",
    "sg:phone":"+34 963 67 03 83",
    "sg:postcode":"46012",
    "sg:province":"Valencia",
    "sg:website":"www.hierrossanmarceliano.es",
    "wof:name":"Hierros San Marceliano S.a.",
    "wof:placetype":"venue"
},
  "geometry": {"coordinates":[-0.3426580131,39.441280365],"type":"Point"}
}