{
  "type": "Feature",
  "properties": {
    "addr:full":"Calle de Santa Barbara, 1 Almeria Almer\u00eda 04009",
    "addr:housenumber":"1",
    "addr:postcode":"04009",
    "addr:street":"Calle De Santa Barbara",
    "iso:country":"ES",
    "sg:address":"Calle de Santa Barbara, 1",
    "sg:city":"Almeria",
    "sg:orig_category":"Consultor\u00cdas Diversas",
    "sg:phone":"+34 950 23 81 65",
    "sg:postcode":"04009",
    "sg:province":"Almer\u00eda",
    "wof:name":"Jardines Mediterraneo De Al-andalus S.l.",
    "wof:placetype":"venue"
},
  "geometry": {"coordinates":[-2.4526851177,36.849811554],"type":"Point"}
}