{
  "type": "Feature",
  "properties": {
    "addr:full":"Carrer de Ramon Ribas, 8 Sant Feliu Llobregat Barcelona 08980",
    "addr:housenumber":"8",
    "addr:postcode":"08980",
    "addr:street":"Carrer De Ramon Ribas",
    "iso:country":"ES",
    "sg:address":"Carrer de Ramon Ribas, 8",
    "sg:city":"Sant Feliu Llobregat",
    "sg:orig_category":"M\u00c9dicos: Cirug\u00cda Urol\u00d3gica",
    "sg:phone":"+34 936 85 04 39",
    "sg:postcode":"08980",
    "sg:province":"Barcelona",
    "wof:name":"Suarez Suarez Jose Francisco",
    "wof:placetype":"venue"
},
  "geometry": {"coordinates":[2.0523159504,41.3829460144],"type":"Point"}
}