{
  "type": "Feature",
  "properties": {
    "addr:full":"Calle de Magdalena (de La), 1 Getafe Madrid 28901",
    "addr:housenumber":"1",
    "addr:postcode":"28901",
    "addr:street":"Calle De Magdalena De La",
    "iso:country":"ES",
    "sg:address":"Calle de Magdalena (de La), 1",
    "sg:city":"Getafe",
    "sg:orig_category":"\u00d3ptica: Instrumentos (fabricaci\u00d3n)",
    "sg:phone":"+34 916 95 01 71",
    "sg:postcode":"28901",
    "sg:province":"Madrid",
    "wof:name":"Pages Alemany Victoriano",
    "wof:placetype":"venue"
},
  "geometry": {"coordinates":[-3.7286660671,40.3071136475],"type":"Point"}
}