{
  "type": "Feature",
  "properties": {
    "iso:country":"ES",
    "sg:address":"Calle de Manolete, 6",
    "sg:city":"Molina Segura",
    "sg:orig_category":"Conservas De Legumbres (fabricaci\u00d3n, Al Por Mayor)",
    "sg:phone":"+34 968 61 52 09",
    "sg:postcode":"30500",
    "sg:province":"Murcia",
    "wof:name":"Conservas Murcianas S.l.",
    "wof:placetype":"venue"
},
  "geometry": {"coordinates":[-1.2121030092,38.0555000305],"type":"Point"}
}