{
  "type": "Feature",
  "properties": {
    "addr:full":"Calle de Cuartel, 1 Estepona M\u00e1laga 29680",
    "addr:housenumber":"1",
    "addr:postcode":"29680",
    "addr:street":"Calle De Cuartel",
    "iso:country":"ES",
    "sg:address":"Calle de Cuartel, 1",
    "sg:city":"Estepona",
    "sg:orig_category":"Papeler\u00cdas, Librer\u00cdas",
    "sg:phone":"+34 952 80 54 33",
    "sg:postcode":"29680",
    "sg:province":"M\u00e1laga",
    "wof:name":"Vazquez Bautista Elvira",
    "wof:placetype":"venue"
},
  "geometry": {"coordinates":[-5.1490187645,36.4324417114],"type":"Point"}
}