{
  "type": "Feature",
  "properties": {
    "iso:country":"ES",
    "sg:address":"Calle de Balneario, 6",
    "sg:city":"Medina Campo",
    "sg:orig_category":"Agencias Y Agentes Comerciales, Representantes",
    "sg:phone":"+34 983 80 03 90",
    "sg:postcode":"47400",
    "sg:province":"Valladolid",
    "wof:name":"San Roman Hernandez Miguel Angel",
    "wof:placetype":"venue"
},
  "geometry": {"coordinates":[-4.9161539078,41.2996253967],"type":"Point"}
}