{
  "type": "Feature",
  "properties": {
    "addr:full":"Pase Alameda Marques De Comillas, 2 Cadiz C\u00e1diz 11003",
    "addr:housenumber":"2",
    "addr:postcode":"11003",
    "addr:street":"Alameda Marques De Comillas",
    "iso:country":"ES",
    "sg:address":"Pase Alameda Marques De Comillas, 2",
    "sg:city":"Cadiz",
    "sg:orig_category":"Ense\u00d1anza Variada",
    "sg:phone":"+34 956 80 80 02",
    "sg:postcode":"11003",
    "sg:province":"C\u00e1diz",
    "wof:name":"Consorcio Escuela De Hosteleria De Cadiz",
    "wof:placetype":"venue"
},
  "geometry": {"coordinates":[-6.2996611595,36.5374603271],"type":"Point"}
}