{
  "type": "Feature",
  "properties": {
    "iso:country":"ES",
    "sg:address":"Calle de Cabroja (la), 4",
    "sg:city":"Cabez\u00f3n Sal",
    "sg:orig_category":"Estudios De Grabaci\u00d3n Sonora",
    "sg:phone":"+34 942 70 07 87",
    "sg:postcode":"39500",
    "sg:province":"Cantabria",
    "sg:website":"www.vumeter.net",
    "wof:name":"Estudio De Grabacion Vumeter",
    "wof:placetype":"venue"
},
  "geometry": {"coordinates":[-4.2336378098,43.3059272766],"type":"Point"}
}