{
  "type": "Feature",
  "properties": {
    "addr:full":"Avda Gasteiz, 19 Vitoria-gasteiz \u00c1lava 01008",
    "addr:housenumber":"19",
    "addr:postcode":"01008",
    "addr:street":"Avda Gasteiz",
    "iso:country":"ES",
    "sg:address":"Avda Gasteiz, 19",
    "sg:city":"Vitoria-gasteiz",
    "sg:orig_category":"Sociedades, Compa\u00d1\u00cdas Aseguradoras",
    "sg:phone":"+34 945 13 22 44",
    "sg:postcode":"01008",
    "sg:province":"\u00c1lava",
    "wof:name":"Bilbao Compa\u00f1ia Anonima De Seguros",
    "wof:placetype":"venue"
},
  "geometry": {"coordinates":[-2.6825110912,42.844367981],"type":"Point"}
}