{
  "type": "Feature",
  "properties": {
    "iso:country":"ES",
    "sg:address":"San Pedro Kalea, 10",
    "sg:city":"Portua",
    "sg:orig_category":"Construcciones Met\u00c1licas",
    "sg:phone":"+34 943 64 22 69",
    "sg:postcode":"20280",
    "sg:province":"Guip\u00f9zcoa",
    "wof:name":"Parra Rilo Juan",
    "wof:placetype":"venue"
},
  "geometry": {"coordinates":[-1.7936140299,43.3698997498],"type":"Point"}
}