{
  "type": "Feature",
  "properties": {
    "iso:country":"ES",
    "sg:address":"Calle de Camino De Malaga, 10",
    "sg:city":"Velez-malaga",
    "sg:orig_category":"Ropa Para Se\u00d1oras (al Por Menor)",
    "sg:phone":"+34 952 55 87 59",
    "sg:postcode":"29700",
    "sg:province":"M\u00e1laga",
    "wof:name":"Ariza Martin Antonio",
    "wof:placetype":"venue"
},
  "geometry": {"coordinates":[-4.1042456627,36.7804222107],"type":"Point"}
}