{
  "type": "Feature",
  "properties": {
    "iso:country":"ES",
    "sg:address":"Rua Cristobal Colon, 71",
    "sg:city":"Solana",
    "sg:orig_category":"Internados & Ense\u00d1anza Privada",
    "sg:phone":"+34 981 38 03 94",
    "sg:postcode":"15570",
    "sg:province":"La Coru\u00f1a",
    "wof:name":"Colegio Ayala S.coop.ltda.",
    "wof:placetype":"venue"
},
  "geometry": {"coordinates":[-8.1647539139,43.5165405273],"type":"Point"}
}