{
  "type": "Feature",
  "properties": {
    "iso:country":"ES",
    "sg:address":"Calle de Eguilaz, 1",
    "sg:city":"Jerez De La Frontera",
    "sg:orig_category":"Centros Empresariales",
    "sg:phone":"+34 956 34 21 59",
    "sg:postcode":"11403",
    "sg:province":"C\u00e1diz",
    "wof:name":"Lazude Sl",
    "wof:placetype":"venue"
},
  "geometry": {"coordinates":[-6.1379289627,36.6849784851],"type":"Point"}
}