{
  "type": "Feature",
  "properties": {
    "iso:country":"ES",
    "sg:address":"Calle de Luis De Salazar, 2",
    "sg:city":"Madrid",
    "sg:orig_category":"Centros Empresariales",
    "sg:phone":"+34 914 13 02 46",
    "sg:postcode":"28002",
    "sg:province":"Madrid",
    "wof:name":"Moran Abad Eduardo",
    "wof:placetype":"venue"
},
  "geometry": {"coordinates":[-3.6675772667,40.4475135803],"type":"Point"}
}