{
  "type": "Feature",
  "properties": {
    "iso:country":"ES",
    "sg:address":"Calle de Londres, 39",
    "sg:city":"Madrid",
    "sg:orig_category":"Agentes, Concesionarios Y Sucursales De Veh\u00cdculos",
    "sg:phone":"+34 917 26 08 95",
    "sg:postcode":"28028",
    "sg:province":"Madrid",
    "wof:name":"Cobra Expres S.l.",
    "wof:placetype":"venue"
},
  "geometry": {"coordinates":[-3.6668279171,40.431804657],"type":"Point"}
}