{
  "type": "Feature",
  "properties": {
    "iso:country":"ES",
    "sg:address":"Calle de Antonio Machado, 2",
    "sg:city":"Adrada",
    "sg:orig_category":"Promotores Constructores",
    "sg:phone":"+34 918 67 90 16",
    "sg:postcode":"05430",
    "sg:province":"\u00c1vila",
    "wof:name":"Construcciones Lorotietar S.l.",
    "wof:placetype":"venue"
},
  "geometry": {"coordinates":[-4.6384391785,40.3013000488],"type":"Point"}
}