{
  "type": "Feature",
  "properties": {
    "addr:full":"Avda Generalisimo, 45 Meira Lugo 27240",
    "addr:housenumber":"45",
    "addr:postcode":"27240",
    "addr:street":"Avda Generalisimo",
    "iso:country":"ES",
    "sg:address":"Avda Generalisimo, 45",
    "sg:city":"Meira",
    "sg:orig_category":"Mec\u00c1nico Del Autom\u00d3vil",
    "sg:phone":"+34 982 33 00 28",
    "sg:postcode":"27240",
    "sg:province":"Lugo",
    "wof:name":"Gonzalez Vallejo Julio",
    "wof:placetype":"venue"
},
  "geometry": {"coordinates":[-7.2944879532,43.2132644653],"type":"Point"}
}