{
  "type": "Feature",
  "properties": {
    "iso:country":"ES",
    "sg:address":"Calle de Calzada, 41",
    "sg:city":"San Pedro Arroyo",
    "sg:orig_category":"Extinci\u00d3n De Incendios: Material Y Suministros (fabricaci\u00d3n, Al Por Mayor)",
    "sg:phone":"+34 920 24 04 00",
    "sg:postcode":"05350",
    "sg:province":"\u00c1vila",
    "wof:name":"Ovejero Truijillano Jose Luis",
    "wof:placetype":"venue"
},
  "geometry": {"coordinates":[-4.8715186119,40.8022994995],"type":"Point"}
}