{
  "type": "Feature",
  "properties": {
    "addr:full":"Psaj Cardenal Benavides, 17 Baeza Ja\u00e9n 23440",
    "addr:housenumber":"17",
    "addr:postcode":"23440",
    "addr:street":"Benavides",
    "iso:country":"ES",
    "sg:address":"Psaj Cardenal Benavides, 17",
    "sg:city":"Baeza",
    "sg:orig_category":"Ingeniero",
    "sg:phone":"+34 953 74 25 74",
    "sg:postcode":"23440",
    "sg:province":"Ja\u00e9n",
    "wof:name":"Cameros Lopez Juan Vicente",
    "wof:placetype":"venue"
},
  "geometry": {"coordinates":[-3.4683389664,37.9931411743],"type":"Point"}
}