{
  "type": "Feature",
  "properties": {
    "addr:full":"Calle de Floresta, 4 Valencia Valencia 46022",
    "addr:housenumber":"4",
    "addr:postcode":"46022",
    "addr:street":"Calle De Floresta",
    "iso:country":"ES",
    "sg:address":"Calle de Floresta, 4",
    "sg:city":"Valencia",
    "sg:orig_category":"Fotograf\u00cda Publicitaria E Industrial",
    "sg:phone":"+34 963 30 85 04",
    "sg:postcode":"46022",
    "sg:province":"Valencia",
    "wof:name":"Arber Fotografia Industrial S.l.",
    "wof:placetype":"venue"
},
  "geometry": {"coordinates":[-0.349531889,39.4651298523],"type":"Point"}
}