{
  "type": "Feature",
  "properties": {
    "iso:country":"ES",
    "sg:address":"Calle de Sor Angela De La Cruz, 12",
    "sg:city":"Ecija",
    "sg:orig_category":"Producci\u00d3n, Venta De Productos De Agricultura Biol\u00d3gica",
    "sg:phone":"+34 954 83 08 65",
    "sg:postcode":"41400",
    "sg:province":"Sevilla",
    "wof:name":"Jocriagro S.l",
    "wof:placetype":"venue"
},
  "geometry": {"coordinates":[-5.0812058449,37.5397758484],"type":"Point"}
}