{
  "type": "Feature",
  "properties": {
    "iso:country":"ES",
    "sg:address":"Avda Constitucion, 84",
    "sg:city":"Valencia",
    "sg:orig_category":"Grafistas",
    "sg:phone":"+34 963 45 90 45",
    "sg:postcode":"46009",
    "sg:province":"Valencia",
    "wof:name":"Espirelius C.b.",
    "wof:placetype":"venue"
},
  "geometry": {"coordinates":[-0.3768019974,39.4878082275],"type":"Point"}
}