{
  "type": "Feature",
  "properties": {
    "addr:full":"Rda. Sant Telm, 37 Canet Mar Barcelona 08360",
    "addr:housenumber":"37",
    "addr:postcode":"08360",
    "addr:street":"Telm",
    "iso:country":"ES",
    "sg:address":"Rda. Sant Telm, 37",
    "sg:city":"Canet Mar",
    "sg:orig_category":"Bordado, Marcado A Medida",
    "sg:phone":"+34 937 95 41 39",
    "sg:postcode":"08360",
    "sg:province":"Barcelona",
    "wof:name":"Emilio's Difusion S.l.",
    "wof:placetype":"venue"
},
  "geometry": {"coordinates":[2.580630064,41.5922012329],"type":"Point"}
}