{
  "type": "Feature",
  "properties": {
    "addr:full":"Calle de Real De Villafranca, 9 Palacios Y Villafranca Sevilla 41720",
    "addr:housenumber":"9",
    "addr:postcode":"41720",
    "addr:street":"Calle De Real De Villafranca",
    "iso:country":"ES",
    "sg:address":"Calle de Real De Villafranca, 9",
    "sg:city":"Palacios Y Villafranca",
    "sg:orig_category":"Arquitectos",
    "sg:phone":"+34 955 81 28 39",
    "sg:postcode":"41720",
    "sg:province":"Sevilla",
    "wof:name":"C-dos Arquitectos S.c.",
    "wof:placetype":"venue"
},
  "geometry": {"coordinates":[-5.9241790771,37.1630935669],"type":"Point"}
}