{
  "type": "Feature",
  "properties": {
    "iso:country":"ES",
    "sg:address":"Calle de San Anton, 12",
    "sg:city":"Parla",
    "sg:orig_category":"Ropa Para Ni\u00d1os (al Por Menor)",
    "sg:phone":"+34 916 99 78 49",
    "sg:postcode":"28980",
    "sg:province":"Madrid",
    "wof:name":"Garcia Mu\u00f1oz Julian",
    "wof:placetype":"venue"
},
  "geometry": {"coordinates":[-3.7713871002,40.2347869873],"type":"Point"}
}