{
  "type": "Feature",
  "properties": {
    "addr:full":"Calle de Dolores Ibarruri, 41 Malaga M\u00e1laga 29004",
    "addr:housenumber":"41",
    "addr:postcode":"29004",
    "addr:street":"Calle De Dolores Ibarruri;Ma\u0301Laga",
    "iso:country":"ES",
    "sg:address":"Calle de Dolores Ibarruri, 41",
    "sg:city":"Malaga",
    "sg:orig_category":"M\u00c9dicos: Medicina Legal, Peritajes M\u00c9dicos",
    "sg:phone":"+34 952 23 95 60",
    "sg:postcode":"29004",
    "sg:province":"M\u00e1laga",
    "wof:name":"Prada Pagola Rafael",
    "wof:placetype":"venue"
},
  "geometry": {"coordinates":[-4.4644203186,36.6940383911],"type":"Point"}
}