{
  "type": "Feature",
  "properties": {
    "addr:full":"Calle de Mesones, 29 Talavera Reina Toledo 45600",
    "addr:housenumber":"29",
    "addr:postcode":"45600",
    "addr:street":"Calle De Mesones",
    "iso:country":"ES",
    "sg:address":"Calle de Mesones, 29",
    "sg:city":"Talavera Reina",
    "sg:orig_category":"Peluquer\u00cdas, Peluquer\u00cda Mixta",
    "sg:phone":"+34 925 80 76 20",
    "sg:postcode":"45600",
    "sg:province":"Toledo",
    "wof:name":"Dujan Rodriguez Maria Amor",
    "wof:placetype":"venue"
},
  "geometry": {"coordinates":[-4.8319301605,39.9629631042],"type":"Point"}
}