{
  "type": "Feature",
  "properties": {
    "addr:full":"Calle de Arcipreste De Hita, 19 Torre-pacheco Murcia 30700",
    "addr:housenumber":"19",
    "addr:postcode":"30700",
    "addr:street":"Calle De Arcipreste De Hita",
    "iso:country":"ES",
    "sg:address":"Calle de Arcipreste De Hita, 19",
    "sg:city":"Torre-pacheco",
    "sg:orig_category":"Producci\u00d3n, Venta De Productos De Agricultura Biol\u00d3gica",
    "sg:phone":"+34 968 57 96 07",
    "sg:postcode":"30700",
    "sg:province":"Murcia",
    "wof:name":"Agrogarme S.l.",
    "wof:placetype":"venue"
},
  "geometry": {"coordinates":[-0.9582123756,37.7375030518],"type":"Point"}
}