{
  "type": "Feature",
  "properties": {
    "iso:country":"ES",
    "sg:address":"Avda Juan Carlos I, Rey, 10",
    "sg:city":"Melilla",
    "sg:orig_category":"Bancos",
    "sg:phone":"+34 952 68 43 48",
    "sg:postcode":"52001",
    "sg:province":"Melilla",
    "wof:name":"Banco Espa\u00f1ol De Credito S.a.",
    "wof:placetype":"venue"
},
  "geometry": {"coordinates":[-2.9399330616,35.2933044434],"type":"Point"}
}