{
  "type": "Feature",
  "properties": {
    "iso:country":"ES",
    "sg:address":"Avgd President Companys, 100",
    "sg:city":"Badalona",
    "sg:orig_category":"Grafistas",
    "sg:phone":"+34 933 84 64 38",
    "sg:postcode":"08911",
    "sg:province":"Barcelona",
    "sg:website":"www.dortoka.com",
    "wof:name":"Dortoka Disseny S.l.",
    "wof:placetype":"venue"
},
  "geometry": {"coordinates":[2.2480270863,41.4549026489],"type":"Point"}
}