{
  "type": "Feature",
  "properties": {
    "iso:country":"ES",
    "sg:address":"Rua Hermanos Alvarez Araujo, 25",
    "sg:city":"Ribadavia",
    "sg:orig_category":"Mec\u00c1nico Del Autom\u00d3vil",
    "sg:phone":"+34 988 47 09 64",
    "sg:postcode":"32400",
    "sg:province":"Ourense",
    "wof:name":"Mosquera E Hijos S.l.",
    "wof:placetype":"venue"
},
  "geometry": {"coordinates":[-8.1371479034,42.2941627502],"type":"Point"}
}