{
  "type": "Feature",
  "properties": {
    "iso:country":"ES",
    "sg:address":"Av Progreso(b Progreso), 88",
    "sg:city":"Murcia",
    "sg:orig_category":"Muebles, Minoristas",
    "sg:phone":"+34 968 34 03 72",
    "sg:postcode":"30012",
    "sg:province":"Murcia",
    "wof:name":"Espin Garcia Jose Francisco",
    "wof:placetype":"venue"
},
  "geometry": {"coordinates":[-1.1205610037,37.9642486572],"type":"Point"}
}