{
  "type": "Feature",
  "properties": {
    "iso:country":"ES",
    "sg:address":"Calle de Luz, 1",
    "sg:city":"Ciudad Real",
    "sg:orig_category":"Mataderos Y Talleres De Despiezado",
    "sg:phone":"+34 926 25 09 07",
    "sg:postcode":"13003",
    "sg:province":"Ciudad Real",
    "wof:name":"Carnicas Puertollano S.l.",
    "wof:placetype":"venue"
},
  "geometry": {"coordinates":[-3.9267590046,38.9891281128],"type":"Point"}
}