{
  "type": "Feature",
  "properties": {
    "iso:country":"ES",
    "sg:address":"Calle de Santa Teresa De Jesus, S/n",
    "sg:city":"Santander",
    "sg:orig_category":"Frutas, Legumbres Frescas Y Tempranas (al Por Menor)",
    "sg:phone":"+34 942 21 77 51",
    "sg:postcode":"39003",
    "sg:province":"Cantabria",
    "wof:name":"Gonzalez Caneiro Miguel Enrique",
    "wof:placetype":"venue"
},
  "geometry": {"coordinates":[-3.801664114,43.4658203125],"type":"Point"}
}