{
  "type": "Feature",
  "properties": {
    "addr:full":"Calle de Sacramento, 2 Utrera Sevilla 41710",
    "addr:housenumber":"2",
    "addr:postcode":"41710",
    "addr:street":"Calle De Sacramento",
    "iso:country":"ES",
    "sg:address":"Calle de Sacramento, 2",
    "sg:city":"Utrera",
    "sg:orig_category":"Laboratorios Y Cl\u00cdnicas Veterinarias",
    "sg:phone":"+34 955 86 54 34",
    "sg:postcode":"41710",
    "sg:province":"Sevilla",
    "wof:name":"Garcia Hidalgo Rafael",
    "wof:placetype":"venue"
},
  "geometry": {"coordinates":[-5.7796139717,37.1801795959],"type":"Point"}
}