{
  "type": "Feature",
  "properties": {
    "addr:full":"Avda Juan Carlos I, Km. 0040,7 Estacion Madrid 28400",
    "addr:postcode":"28400",
    "addr:street":"Avda Juan Carlos I Km. 0040,7 Estacion",
    "iso:country":"ES",
    "sg:address":"Avda Juan Carlos I, Km. 0040,7",
    "sg:city":"Estacion",
    "sg:orig_category":"Agentes, Concesionarios Y Sucursales De Veh\u00cdculos",
    "sg:phone":"+34 918 49 07 53",
    "sg:postcode":"28400",
    "sg:province":"Madrid",
    "wof:name":"Motor Gomez S.a.",
    "wof:placetype":"venue"
},
  "geometry": {"coordinates":[-3.9919650555,40.6455612183],"type":"Point"}
}