{
  "type": "Feature",
  "properties": {
    "addr:full":"Calle de Principe De Vergara, 81 Madrid Madrid 28006",
    "addr:housenumber":"81",
    "addr:postcode":"madrid;28006",
    "addr:street":"Calle De Principe De Vergara",
    "iso:country":"ES",
    "sg:address":"Calle de Principe De Vergara, 81",
    "sg:city":"Madrid",
    "sg:orig_category":"Muebles Y Decoraci\u00d3n De Jardines (fabricaci\u00d3n, Venta)",
    "sg:phone":"+34 914 11 26 20",
    "sg:postcode":"28006",
    "sg:province":"Madrid",
    "sg:website":"www.kettal.es",
    "wof:name":"Kettal S.a.",
    "wof:placetype":"venue"
},
  "geometry": {"coordinates":[-3.6794540882,40.4354972839],"type":"Point"}
}