{
  "type": "Feature",
  "properties": {
    "addr:full":"Calle de Jaime Roig, 15 Valencia Valencia 46010",
    "addr:housenumber":"15",
    "addr:postcode":"46010",
    "addr:street":"Calle De Jaime Roig",
    "iso:country":"ES",
    "sg:address":"Calle de Jaime Roig, 15",
    "sg:city":"Valencia",
    "sg:orig_category":"Bancos",
    "sg:phone":"+34 963 39 43 30",
    "sg:postcode":"46010",
    "sg:province":"Valencia",
    "wof:name":"Lloyds Tsb Bank Sucursal En Espana",
    "wof:placetype":"venue"
},
  "geometry": {"coordinates":[-0.3642309904,39.4813766479],"type":"Point"}
}