{
  "type": "Feature",
  "properties": {
    "addr:full":"Calle de Pilar De Farinos, 2 Estepona M\u00e1laga 29680",
    "addr:housenumber":"2",
    "addr:postcode":"29680",
    "addr:street":"Calle De Pilar De Farinos",
    "iso:country":"ES",
    "sg:address":"Calle de Pilar De Farinos, 2",
    "sg:city":"Estepona",
    "sg:orig_category":"Electrodom\u00c9sticos (al Por Menor)",
    "sg:phone":"+34 952 80 25 90",
    "sg:postcode":"29680",
    "sg:province":"M\u00e1laga",
    "wof:name":"Presa Hernandez Abilio",
    "wof:placetype":"venue"
},
  "geometry": {"coordinates":[-5.1499261856,36.4271659851],"type":"Point"}
}