{
  "type": "Feature",
  "properties": {
    "addr:full":"Carrer de Concili De Trento, 42 Barcelona Barcelona 08018",
    "addr:housenumber":"42",
    "addr:postcode":"08018",
    "addr:street":"Carrer De Concili De Trento",
    "iso:country":"ES",
    "sg:address":"Carrer de Concili De Trento, 42",
    "sg:city":"Barcelona",
    "sg:orig_category":"Asociaciones, Organismos Culturales Y Socioeducativos",
    "sg:phone":"+34 933 07 04 83",
    "sg:postcode":"08018",
    "sg:province":"Barcelona",
    "wof:name":"Familia I Benestar Social Fundacio Privada",
    "wof:placetype":"venue"
},
  "geometry": {"coordinates":[2.1932311058,41.4115562439],"type":"Point"}
}