{
  "type": "Feature",
  "properties": {
    "iso:country":"ES",
    "sg:address":"Avda Garcia Barbon, 102",
    "sg:city":"Vigo",
    "sg:orig_category":"Caf\u00c9s, Bares, Cervecer\u00cdas",
    "sg:phone":"+34 986 22 50 01",
    "sg:postcode":"36201",
    "sg:province":"Pontevedra",
    "wof:name":"Depoca Vigo S.l.",
    "wof:placetype":"venue"
},
  "geometry": {"coordinates":[-8.7089242935,42.2388420105],"type":"Point"}
}