{
  "type": "Feature",
  "properties": {
    "addr:full":"Mlle Levante, S/n Alacant Alicante 03001",
    "addr:housenumber":"s / n",
    "addr:postcode":"03001",
    "addr:street":"Levante",
    "iso:country":"ES",
    "sg:address":"Mlle Levante, S/n",
    "sg:city":"Alacant",
    "sg:orig_category":"Deportes N\u00c1uticos, Acu\u00c1ticos Y Subacu\u00c1ticos: Art\u00cdculos Y Equipo (al Por Menor)",
    "sg:phone":"+34 965 21 31 96",
    "sg:postcode":"03001",
    "sg:province":"Alicante",
    "wof:name":"Sirius Yacht Brokers S.l.",
    "wof:placetype":"venue"
},
  "geometry": {"coordinates":[-0.4815289974,38.339263916],"type":"Point"}
}