{
  "type": "Feature",
  "properties": {
    "addr:full":"Ntra Sra Amargura, 11 Carmona Sevilla 41410",
    "addr:housenumber":"11",
    "addr:postcode":"41410",
    "addr:street":"Ntra Sra Amargura",
    "iso:country":"ES",
    "sg:address":"Ntra Sra Amargura, 11",
    "sg:city":"Carmona",
    "sg:orig_category":"Vallados Y Barreras",
    "sg:phone":"+34 954 19 16 27",
    "sg:postcode":"41410",
    "sg:province":"Sevilla",
    "wof:name":"Cerramientos Arrabal S.l.",
    "wof:placetype":"venue"
},
  "geometry": {"coordinates":[-5.6487021446,37.4771842957],"type":"Point"}
}