{
  "type": "Feature",
  "properties": {
    "iso:country":"ES",
    "sg:address":"Calle de Teresa Berganza, 30",
    "sg:city":"Getafe",
    "sg:orig_category":"Fachadas",
    "sg:phone":"+34 916 84 06 70",
    "sg:postcode":"28903",
    "sg:province":"Madrid",
    "wof:name":"A I A Rehabilitaciones Y Reformas Extreme\u00f1as S.l.",
    "wof:placetype":"venue"
},
  "geometry": {"coordinates":[-3.7133045197,40.3224029541],"type":"Point"}
}