{
  "type": "Feature",
  "properties": {
    "addr:full":"Ctra. Sant Carles, Km. 0008,3 Sta. Eularia Riu Islas Baleares 07840",
    "addr:postcode":"07840",
    "addr:street":"Ctra. Sant Carles Km. 0008,3;Baleares",
    "iso:country":"ES",
    "sg:address":"Ctra. Sant Carles, Km. 0008,3",
    "sg:city":"Sta. Eularia Riu",
    "sg:orig_category":"Art\u00cdculos De Madera (fabricaci\u00d3n Y Al Por Mayor)",
    "sg:phone":"+34 971 33 15 96",
    "sg:postcode":"07840",
    "sg:province":"Islas Baleares",
    "sg:website":"www.100x100ibiza.com",
    "wof:name":"Fernandez Oriol Guillermo Daniel",
    "wof:placetype":"venue"
},
  "geometry": {"coordinates":[1.5341850519,38.9850311279],"type":"Point"}
}