{
  "type": "Feature",
  "properties": {
    "iso:country":"ES",
    "sg:address":"Carrer de Industria, 12",
    "sg:city":"Masnou",
    "sg:orig_category":"Perfumer\u00cda Y Cosm\u00c9tica (fabricaci\u00d3n, Al Por Mayor)",
    "sg:phone":"+34 935 40 39 96",
    "sg:postcode":"08320",
    "sg:province":"Barcelona",
    "wof:name":"Cosmetica Cabinas S.l.",
    "wof:placetype":"venue"
},
  "geometry": {"coordinates":[2.3187379837,41.4887199402],"type":"Point"}
}