{
  "type": "Feature",
  "properties": {
    "iso:country":"ES",
    "sg:address":"Carrer de Colomines, 2",
    "sg:city":"Barcelona",
    "sg:orig_category":"Bricolaje, Herramientas (al Por Menor)",
    "sg:phone":"+34 933 19 35 49",
    "sg:postcode":"08003",
    "sg:province":"Barcelona",
    "wof:name":"Brico-ceide S.l.",
    "wof:placetype":"venue"
},
  "geometry": {"coordinates":[2.1789400578,41.3854980469],"type":"Point"}
}