{
  "type": "Feature",
  "properties": {
    "iso:country":"ES",
    "sg:address":"Calle de Alcalde Parrondo, 2",
    "sg:city":"Pola De Siero",
    "sg:orig_category":"Caf\u00c9s, Bares, Cervecer\u00cdas",
    "sg:phone":"+34 985 72 64 83",
    "sg:postcode":"33510",
    "sg:province":"Asturias",
    "wof:name":"Natival C. B.",
    "wof:placetype":"venue"
},
  "geometry": {"coordinates":[-5.6612401009,43.391368866],"type":"Point"}
}