{
  "type": "Feature",
  "properties": {
    "addr:full":"Avda Espa\u00d1a, 21 Linares Ja\u00e9n 23700",
    "addr:housenumber":"21",
    "addr:postcode":"23700",
    "addr:street":"Avda Espan\u0303A;Jae\u0301N",
    "iso:country":"ES",
    "sg:address":"Avda Espa\u00d1a, 21",
    "sg:city":"Linares",
    "sg:orig_category":"Mec\u00c1nico Del Autom\u00d3vil",
    "sg:phone":"+34 953 60 04 52",
    "sg:postcode":"23700",
    "sg:province":"Ja\u00e9n",
    "wof:name":"Automecanica Hellanes S.a.l.",
    "wof:placetype":"venue"
},
  "geometry": {"coordinates":[-3.6253120899,38.0883293152],"type":"Point"}
}