{
  "type": "Feature",
  "properties": {
    "iso:country":"ES",
    "sg:address":"Calle de Andres Mellado, 71",
    "sg:city":"Madrid",
    "sg:orig_category":"Cr\u00cda De Animales",
    "sg:phone":"+34 915 44 78 10",
    "sg:postcode":"28015",
    "sg:province":"Madrid",
    "wof:name":"San Juan Mayoral Anastasio",
    "wof:placetype":"venue"
},
  "geometry": {"coordinates":[-3.7141375542,40.4387245178],"type":"Point"}
}