{
  "type": "Feature",
  "properties": {
    "iso:country":"ES",
    "sg:address":"Calle de Consuelo, 22",
    "sg:city":"Valencia",
    "sg:orig_category":"Alimentaci\u00d3n General (al Por Mayor)",
    "sg:phone":"+34 963 24 20 59",
    "sg:postcode":"46011",
    "sg:province":"Valencia",
    "wof:name":"Diego Devesa S.l.",
    "wof:placetype":"venue"
},
  "geometry": {"coordinates":[-0.3362450004,39.4630470276],"type":"Point"}
}