{
  "type": "Feature",
  "properties": {
    "iso:country":"ES",
    "sg:address":"Calle de Luna, 10",
    "sg:city":"Majadahonda",
    "sg:orig_category":"Centros Empresariales",
    "sg:phone":"+34 916 38 93 61",
    "sg:postcode":"28220",
    "sg:province":"Madrid",
    "wof:name":"Proyectos Y Anclajes S.l.",
    "wof:placetype":"venue"
},
  "geometry": {"coordinates":[-3.8740129471,40.4693222046],"type":"Point"}
}