{
  "type": "Feature",
  "properties": {
    "iso:country":"ES",
    "sg:address":"Balbona, 8",
    "sg:city":"Balbona",
    "sg:orig_category":"Molduras, Junquillos, Listones Y Molduras Perforadas",
    "sg:phone":"+34 985 79 37 13",
    "sg:postcode":"33429",
    "sg:province":"Asturias",
    "wof:name":"Alvarez Lorenzo Jose Antonio",
    "wof:placetype":"venue"
},
  "geometry": {"coordinates":[-5.756731987,43.3949584961],"type":"Point"}
}