{
  "type": "Feature",
  "properties": {
    "iso:country":"ES",
    "sg:address":"Trva Doctor Bastos, 2",
    "sg:city":"Majadahonda",
    "sg:orig_category":"Ense\u00d1anza: Idiomas",
    "sg:phone":"+34 916 38 94 75",
    "sg:postcode":"28220",
    "sg:province":"Madrid",
    "sg:website":"www.burlingschool.com",
    "wof:name":"Aula De Estudios Ling\u00fcsticos S.l.",
    "wof:placetype":"venue"
},
  "geometry": {"coordinates":[-3.8754739761,40.4761886597],"type":"Point"}
}