{
  "type": "Feature",
  "properties": {
    "addr:full":"Carr Tolo, 3 Peralada Girona 17491",
    "addr:housenumber":"3",
    "addr:postcode":"17491",
    "addr:street":"Carr Tolo",
    "iso:country":"ES",
    "sg:address":"Carr Tolo, 3",
    "sg:city":"Peralada",
    "sg:orig_category":"Cl\u00cdnicas M\u00c9dicas",
    "sg:phone":"+34 972 53 85 64",
    "sg:postcode":"17491",
    "sg:province":"Girona",
    "sg:website":"www.alberasalut.org",
    "wof:name":"Albera Salut S.l.",
    "wof:placetype":"venue"
},
  "geometry": {"coordinates":[3.0275802612,42.3048019409],"type":"Point"}
}