{
  "type": "Feature",
  "properties": {
    "iso:country":"ES",
    "sg:address":"Calle de Carretera, S/n",
    "sg:city":"Torvizcon",
    "sg:orig_category":"Producci\u00d3n De Abonos Y De Fertilizantes",
    "sg:phone":"+34 958 76 40 74",
    "sg:postcode":"18430",
    "sg:province":"Granada",
    "wof:name":"Romera Santiago Francisco",
    "wof:placetype":"venue"
},
  "geometry": {"coordinates":[-3.3390166759,36.8503684998],"type":"Point"}
}