{
  "type": "Feature",
  "properties": {
    "iso:country":"ES",
    "sg:address":"Calle de Lago Como, 28",
    "sg:city":"Rivas Vaciamadrid",
    "sg:orig_category":"Inmobiliaria (agencias)",
    "sg:phone":"+34 916 70 45 55",
    "sg:postcode":"28529",
    "sg:province":"Madrid",
    "wof:name":"Inmobiliaria Bosch Sanfrutos S.l.",
    "wof:placetype":"venue"
},
  "geometry": {"coordinates":[-3.5116100311,40.3316230774],"type":"Point"}
}