{
  "type": "Feature",
  "properties": {
    "addr:full":"Calle de San Policarpo, 2 Torrevieja Alicante 03180",
    "addr:housenumber":"2",
    "addr:postcode":"03180",
    "addr:street":"Calle De San Policarpo",
    "iso:country":"ES",
    "sg:address":"Calle de San Policarpo, 2",
    "sg:city":"Torrevieja",
    "sg:orig_category":"Promotores Constructores",
    "sg:phone":"+34 965 71 09 53",
    "sg:postcode":"03180",
    "sg:province":"Alicante",
    "wof:name":"Campillo Olivares Jose",
    "wof:placetype":"venue"
},
  "geometry": {"coordinates":[-0.6854109764,37.9766464233],"type":"Point"}
}