{
  "type": "Feature",
  "properties": {
    "addr:full":"Calle de General Vara De Rey, 64 Logro\u00f1o La Rioja 26002",
    "addr:housenumber":"64",
    "addr:postcode":"26002",
    "addr:street":"Calle De General Vara De Rey;Rioja",
    "iso:country":"ES",
    "sg:address":"Calle de General Vara De Rey, 64",
    "sg:city":"Logro\u00f1o",
    "sg:orig_category":"Art\u00cdculos De Regalo (al Por Menor)",
    "sg:phone":"+34 941 25 30 12",
    "sg:postcode":"26002",
    "sg:province":"La Rioja",
    "wof:name":"Corzaga Calvo Maria Luisa",
    "wof:placetype":"venue"
},
  "geometry": {"coordinates":[-2.4469249249,42.4583587646],"type":"Point"}
}