{
  "type": "Feature",
  "properties": {
    "addr:full":"Jilguero, 2 Majadahonda Madrid 28220",
    "addr:housenumber":"2",
    "addr:postcode":"28220",
    "addr:street":"Jilguero",
    "iso:country":"ES",
    "sg:address":"Jilguero, 2",
    "sg:city":"Majadahonda",
    "sg:orig_category":"Organismos De Reclutamiento",
    "sg:phone":"+34 916 79 53 27",
    "sg:postcode":"28220",
    "sg:province":"Madrid",
    "wof:name":"Tec Media Servicios Y Consultoria S.l.",
    "wof:placetype":"venue"
},
  "geometry": {"coordinates":[-3.8716540337,40.4739151001],"type":"Point"}
}