{
  "type": "Feature",
  "properties": {
    "addr:full":"Calle de Pe\u00d1as Arriba, 2 Reinosa Cantabria 39200",
    "addr:housenumber":"2",
    "addr:postcode":"39200",
    "addr:street":"Calle De Pen\u0303As Arriba",
    "iso:country":"ES",
    "sg:address":"Calle de Pe\u00d1as Arriba, 2",
    "sg:city":"Reinosa",
    "sg:orig_category":"Ropa Para Ni\u00d1os (al Por Menor)",
    "sg:phone":"+34 942 75 12 98",
    "sg:postcode":"39200",
    "sg:province":"Cantabria",
    "wof:name":"Argueso Diez Mariola",
    "wof:placetype":"venue"
},
  "geometry": {"coordinates":[-4.1392931938,43.0003585815],"type":"Point"}
}