{
  "type": "Feature",
  "properties": {
    "addr:full":"Calle de Zazuar, 5 Madrid Madrid 28031",
    "addr:housenumber":"5",
    "addr:postcode":"28031",
    "addr:street":"Calle De Zazuar",
    "iso:country":"ES",
    "sg:address":"Calle de Zazuar, 5",
    "sg:city":"Madrid",
    "sg:orig_category":"Psic\u00d3logos",
    "sg:phone":"+34 913 31 88 95",
    "sg:postcode":"28031",
    "sg:province":"Madrid",
    "wof:name":"Schapira Goldin Ricardo",
    "wof:placetype":"venue"
},
  "geometry": {"coordinates":[-3.605768919,40.382598877],"type":"Point"}
}