{
  "type": "Feature",
  "properties": {
    "iso:country":"ES",
    "sg:address":"Rua Seixalbo (de), 20",
    "sg:city":"Seixalbo",
    "sg:orig_category":"Chapister\u00cda",
    "sg:phone":"+34 988 22 45 10",
    "sg:postcode":"32970",
    "sg:province":"Ourense",
    "wof:name":"Hispanomocion S.a.",
    "wof:placetype":"venue"
},
  "geometry": {"coordinates":[-7.8508682251,42.3009872437],"type":"Point"}
}