{
  "type": "Feature",
  "properties": {
    "addr:full":"Alam Areilza Doctor, 24 Bilbao Vizcaya 48011",
    "addr:housenumber":"24",
    "addr:postcode":"48011",
    "addr:street":"Alam;Doctor",
    "iso:country":"ES",
    "sg:address":"Alam Areilza Doctor, 24",
    "sg:city":"Bilbao",
    "sg:orig_category":"Tintes (fabricaci\u00d3n, Al Por Mayor)",
    "sg:phone":"+34 944 27 74 53",
    "sg:postcode":"48011",
    "sg:province":"Vizcaya",
    "wof:name":"Garbi-ziku, S.l.",
    "wof:placetype":"venue"
},
  "geometry": {"coordinates":[-2.942276001,43.262046814],"type":"Point"}
}