{
  "type": "Feature",
  "properties": {
    "iso:country":"ES",
    "sg:address":"Gibeleta, 8",
    "sg:city":"Hondarribia",
    "sg:orig_category":"Asociaciones Humanitarias, De Cooperaci\u00d3n, De Acci\u00d3n Social",
    "sg:phone":"+34 943 64 30 59",
    "sg:postcode":"20280",
    "sg:province":"Guip\u00f9zcoa",
    "wof:name":"Gibeleta S.a.",
    "wof:placetype":"venue"
},
  "geometry": {"coordinates":[-1.8061599731,43.3442802429],"type":"Point"}
}