{
  "type": "Feature",
  "properties": {
    "addr:full":"Carrer de Valencia, 73 Mataro Barcelona 08303",
    "addr:housenumber":"73",
    "addr:postcode":"08303",
    "addr:street":"Carrer De Valencia",
    "iso:country":"ES",
    "sg:address":"Carrer de Valencia, 73",
    "sg:city":"Mataro",
    "sg:orig_category":"Ense\u00d1anza: Peluquer\u00cda Est\u00c9tica",
    "sg:phone":"+34 937 41 59 62",
    "sg:postcode":"08303",
    "sg:province":"Barcelona",
    "wof:name":"Bona Nit Flex S.c.p.",
    "wof:placetype":"venue"
},
  "geometry": {"coordinates":[2.4233078957,41.5398406982],"type":"Point"}
}