{
  "type": "Feature",
  "properties": {
    "addr:full":"Aizkibel Kalea, 5 Azkoitia Guip\u00f9zcoa 20720",
    "addr:housenumber":"5",
    "addr:postcode":"20720",
    "addr:street":"Aizkibel Kalea;Guipu\u0300Zcoa",
    "iso:country":"ES",
    "sg:address":"Aizkibel Kalea, 5",
    "sg:city":"Azkoitia",
    "sg:orig_category":"Relojer\u00cda (al Por Menor, Reparaci\u00d3n)",
    "sg:phone":"+34 943 85 02 67",
    "sg:postcode":"20720",
    "sg:province":"Guip\u00f9zcoa",
    "wof:name":"Alkorta Bitxitegia, C.b.",
    "wof:placetype":"venue"
},
  "geometry": {"coordinates":[-2.3124203682,43.1783409119],"type":"Point"}
}