{
  "type": "Feature",
  "properties": {
    "addr:full":"Avgd Marina, De La, 25 Playa Valencia 46760",
    "addr:postcode":"46760",
    "addr:street":"Playa Valencia",
    "iso:country":"ES",
    "sg:address":"Avgd Marina, De La, 25",
    "sg:city":"Playa",
    "sg:orig_category":"Farmacias",
    "sg:phone":"+34 962 88 43 19",
    "sg:postcode":"46760",
    "sg:province":"Valencia",
    "wof:name":"Barrachina Vicente Jose Fernando",
    "wof:placetype":"venue"
},
  "geometry": {"coordinates":[-0.2594090104,39.0749702454],"type":"Point"}
}