{
  "type": "Feature",
  "properties": {
    "iso:country":"ES",
    "sg:address":"Avda General Pereyra, 33",
    "sg:city":"Requena",
    "sg:orig_category":"Quincaller\u00cda (al Por Menor)",
    "sg:phone":"+34 962 32 31 96",
    "sg:postcode":"46340",
    "sg:province":"Valencia",
    "wof:name":"Suministros Alberto Y Pedro S.l.l.",
    "wof:placetype":"venue"
},
  "geometry": {"coordinates":[-1.10374403,39.4894447327],"type":"Point"}
}