{
  "type": "Feature",
  "properties": {
    "addr:full":"Calle de Joaquin Velasco Martin, 9 Valladolid Valladolid 47014",
    "addr:housenumber":"9",
    "addr:postcode":"47014",
    "addr:street":"Calle De Joaquin Velasco Martin",
    "iso:country":"ES",
    "sg:address":"Calle de Joaquin Velasco Martin, 9",
    "sg:city":"Valladolid",
    "sg:orig_category":"Caf\u00c9s, Bares, Cervecer\u00cdas",
    "sg:phone":"+34 983 34 10 23",
    "sg:postcode":"47014",
    "sg:province":"Valladolid",
    "wof:name":"Calleja Granado Nicolas",
    "wof:placetype":"venue"
},
  "geometry": {"coordinates":[-4.7396187782,41.6467704773],"type":"Point"}
}