{
  "type": "Feature",
  "properties": {
    "addr:full":"Calle de Real, 17 Roquetas Mar Almer\u00eda 04740",
    "addr:housenumber":"17",
    "addr:postcode":"04740",
    "addr:street":"Calle De Real",
    "iso:country":"ES",
    "sg:address":"Calle de Real, 17",
    "sg:city":"Roquetas Mar",
    "sg:orig_category":"Invernaderos Y Semilleros",
    "sg:phone":"+34 950 32 01 38",
    "sg:postcode":"04740",
    "sg:province":"Almer\u00eda",
    "wof:name":"Amat Ayllon Gabriel",
    "wof:placetype":"venue"
},
  "geometry": {"coordinates":[-2.6577279568,36.7336387634],"type":"Point"}
}