{
  "type": "Feature",
  "properties": {
    "addr:full":"Calle de Secretario Artiles, 83 Palmas De Gran Canaria Las Palmas 35007",
    "addr:housenumber":"83",
    "addr:postcode":"35007",
    "addr:street":"Calle De Secretario Artiles",
    "iso:country":"ES",
    "sg:address":"Calle de Secretario Artiles, 83",
    "sg:city":"Palmas De Gran Canaria",
    "sg:orig_category":"Electricidad, Electr\u00d3nica: Material Y Suministros (al Por Mayor)",
    "sg:phone":"+34 928 27 43 84",
    "sg:postcode":"35007",
    "sg:province":"Las Palmas",
    "sg:website":"www.specsa.com",
    "wof:name":"Spec S. A.",
    "wof:placetype":"venue"
},
  "geometry": {"coordinates":[-15.4320907593,28.1412982941],"type":"Point"}
}