{
  "type": "Feature",
  "properties": {
    "addr:full":"Ctra La Coru\u00d1a, Km. 0160,0 Medina Campo Valladolid 47400",
    "addr:postcode":"47400",
    "addr:street":"Ctra La Corun\u0303A Km. 0160,0",
    "iso:country":"ES",
    "sg:address":"Ctra La Coru\u00d1a, Km. 0160,0",
    "sg:city":"Medina Campo",
    "sg:orig_category":"Art\u00cdculos De Decoraci\u00d3n (fabricaci\u00d3n Y Al Por Mayor)",
    "sg:phone":"+34 983 80 22 22",
    "sg:postcode":"47400",
    "sg:province":"Valladolid",
    "wof:name":"Muebles Olimpo Nanez Vegas S.l.",
    "wof:placetype":"venue"
},
  "geometry": {"coordinates":[-4.913184166,41.3120155334],"type":"Point"}
}