{
  "type": "Feature",
  "properties": {
    "addr:full":"Calle de Fuente Del Berro, 1 Madrid Madrid 28009",
    "addr:housenumber":"1",
    "addr:postcode":"28009",
    "addr:street":"Calle De Fuente Del Berro",
    "iso:country":"ES",
    "sg:address":"Calle de Fuente Del Berro, 1",
    "sg:city":"Madrid",
    "sg:orig_category":"Fabricaci\u00d3n De Telas Y Sedas",
    "sg:phone":"+34 913 09 58 83",
    "sg:postcode":"28009",
    "sg:province":"Madrid",
    "sg:website":"www.vestilab.com",
    "wof:name":"Vestilab S. A.",
    "wof:placetype":"venue"
},
  "geometry": {"coordinates":[-3.670593977,40.4267654419],"type":"Point"}
}