{
  "type": "Feature",
  "properties": {
    "iso:country":"ES",
    "sg:address":"Pg Fabra I Puig, 368",
    "sg:city":"Barcelona",
    "sg:orig_category":"Muebles, Minoristas",
    "sg:phone":"+34 933 58 85 75",
    "sg:postcode":"08031",
    "sg:province":"Barcelona",
    "wof:name":"Sucarrat Zueco Jorge",
    "wof:placetype":"venue"
},
  "geometry": {"coordinates":[2.1643960476,41.4310874939],"type":"Point"}
}