{
  "type": "Feature",
  "properties": {
    "iso:country":"ES",
    "sg:address":"Calle de Impresores, 6",
    "sg:city":"Getafe",
    "sg:orig_category":"Ferreter\u00cda (diversos)",
    "sg:phone":"+34 916 65 03 19",
    "sg:postcode":"28906",
    "sg:province":"Madrid",
    "wof:name":"Frada S.l.",
    "wof:placetype":"venue"
},
  "geometry": {"coordinates":[-3.7005620003,40.3103141785],"type":"Point"}
}