{
  "type": "Feature",
  "properties": {
    "iso:country":"ES",
    "sg:address":"Pla\u00c7 Catalunya, 1",
    "sg:city":"Fortia",
    "sg:orig_category":"Ense\u00d1anza, Formaci\u00d3n Profesional: Aprendizaje",
    "sg:phone":"+34 972 53 40 69",
    "sg:postcode":"17469",
    "sg:province":"Girona",
    "wof:name":"Ayuntamiento De Fortia",
    "wof:placetype":"venue"
},
  "geometry": {"coordinates":[2.9704549313,42.2177505493],"type":"Point"}
}