{
  "type": "Feature",
  "properties": {
    "addr:full":"Fuentecilla Del Soldado, 5 S. Roque C\u00e1diz 11360",
    "addr:housenumber":"5",
    "addr:postcode":"11360",
    "addr:street":"S. Roque Ca\u0301Diz",
    "iso:country":"ES",
    "sg:address":"Fuentecilla Del Soldado, 5",
    "sg:city":"S. Roque",
    "sg:orig_category":"Pescader\u00cdas (al Por Menor)",
    "sg:phone":"+34 956 78 13 07",
    "sg:postcode":"11360",
    "sg:province":"C\u00e1diz",
    "wof:name":"Izquierdo Moreno Maria Carmen",
    "wof:placetype":"venue"
},
  "geometry": {"coordinates":[-5.3897438049,36.209690094],"type":"Point"}
}