{
  "type": "Feature",
  "properties": {
    "addr:full":"Calle de Gregorio Bermejo Lopez, 17 Campo Criptana Ciudad Real 13610",
    "addr:housenumber":"17",
    "addr:postcode":"13610",
    "addr:street":"Calle De Gregorio Bermejo Lopez;Criptana",
    "iso:country":"ES",
    "sg:address":"Calle de Gregorio Bermejo Lopez, 17",
    "sg:city":"Campo Criptana",
    "sg:orig_category":"Mec\u00c1nico Del Autom\u00d3vil",
    "sg:phone":"+34 926 56 12 65",
    "sg:postcode":"13610",
    "sg:province":"Ciudad Real",
    "wof:name":"Masa Angulo Francisco Javier",
    "wof:placetype":"venue"
},
  "geometry": {"coordinates":[-3.1297690868,39.4028053284],"type":"Point"}
}