{
  "type": "Feature",
  "properties": {
    "addr:full":"Luis Morondo Urra, 2 Iru\u00f1a Navarra 31006",
    "addr:housenumber":"2",
    "addr:postcode":"31006",
    "addr:street":"Luis;Urra",
    "iso:country":"ES",
    "sg:address":"Luis Morondo Urra, 2",
    "sg:city":"Iru\u00f1a",
    "sg:orig_category":"Carnicer\u00cdas, Carnicer\u00cdas",
    "sg:phone":"+34 948 24 23 07",
    "sg:postcode":"31006",
    "sg:province":"Navarra",
    "wof:name":"Aguinaga Ezcurra Lourdes Y Mendiburu Larre Meliton S.cv.",
    "wof:placetype":"venue"
},
  "geometry": {"coordinates":[-1.6454956532,42.8019332886],"type":"Point"}
}