{
  "type": "Feature",
  "properties": {
    "iso:country":"ES",
    "sg:address":"Carrer de Alaba, 108",
    "sg:city":"Barcelona",
    "sg:orig_category":"Mensajer\u00cda Express, Portes Internacionales",
    "sg:phone":"+34 933 20 97 60",
    "sg:postcode":"08018",
    "sg:province":"Barcelona",
    "wof:name":"Gestio Transport I Transit Barcelona S.l.",
    "wof:placetype":"venue"
},
  "geometry": {"coordinates":[2.1881799698,41.4007415771],"type":"Point"}
}