{
  "type": "Feature",
  "properties": {
    "addr:full":"Carrer de Mossen Comellas, 6 Berga-ciudad Barcelona 08600",
    "addr:housenumber":"6",
    "addr:postcode":"08600",
    "addr:street":"Carrer De Mossen Comellas;Barcelona",
    "iso:country":"ES",
    "sg:address":"Carrer de Mossen Comellas, 6",
    "sg:city":"Berga-ciudad",
    "sg:orig_category":"Ropa Para Ni\u00d1os (al Por Menor)",
    "sg:phone":"+34 938 22 01 22",
    "sg:postcode":"08600",
    "sg:province":"Barcelona",
    "wof:name":"Golden Monkey S.l.",
    "wof:placetype":"venue"
},
  "geometry": {"coordinates":[1.8456009626,42.1036186218],"type":"Point"}
}