{
  "type": "Feature",
  "properties": {
    "addr:full":"Calle de Arquitecto Segura De Lago, 7 Valencia Valencia 46014",
    "addr:housenumber":"7",
    "addr:postcode":"46014",
    "addr:street":"Calle De Arquitecto Segura De Lago",
    "iso:country":"ES",
    "sg:address":"Calle de Arquitecto Segura De Lago, 7",
    "sg:city":"Valencia",
    "sg:orig_category":"Cajas De Ahorro",
    "sg:phone":"+34 963 58 15 13",
    "sg:postcode":"46014",
    "sg:province":"Valencia",
    "sg:website":"www.cam.es",
    "wof:name":"Caja De Ahorros Del Mediterraneo",
    "wof:placetype":"venue"
},
  "geometry": {"coordinates":[-0.4039019942,39.4550285339],"type":"Point"}
}