{
  "type": "Feature",
  "properties": {
    "addr:full":"Carr Cales Fonts, 22 Castell Islas Baleares 07720",
    "addr:housenumber":"22",
    "addr:postcode":"07720",
    "addr:street":"Carr Cales Fonts",
    "iso:country":"ES",
    "sg:address":"Carr Cales Fonts, 22",
    "sg:city":"Castell",
    "sg:orig_category":"Aguas (distribuci\u00d3n, Servicios)",
    "sg:phone":"+34 971 35 24 81",
    "sg:postcode":"07720",
    "sg:province":"Islas Baleares",
    "wof:name":"Sorea S.a.",
    "wof:placetype":"venue"
},
  "geometry": {"coordinates":[4.2850251198,39.8720703125],"type":"Point"}
}