{
  "type": "Feature",
  "properties": {
    "addr:full":"Ma\u00f1arieta Kalea, 7 Antzuola Guip\u00f9zcoa 20577",
    "addr:housenumber":"7",
    "addr:postcode":"20577",
    "addr:street":"Man\u0303Arieta Kalea;Guipu\u0300Zcoa",
    "iso:country":"ES",
    "sg:address":"Ma\u00f1arieta Kalea, 7",
    "sg:city":"Antzuola",
    "sg:orig_category":"Transportes Por V\u00cdas Navegables",
    "sg:phone":"+34 943 76 63 18",
    "sg:postcode":"20577",
    "sg:province":"Guip\u00f9zcoa",
    "wof:name":"Toledo Lizarralde Andres",
    "wof:placetype":"venue"
},
  "geometry": {"coordinates":[-2.3835690022,43.0991363525],"type":"Point"}
}