{
  "type": "Feature",
  "properties": {
    "iso:country":"ES",
    "sg:address":"Avda Francisco La Roche, 35",
    "sg:city":"Santa Cruz De Tenerife",
    "sg:orig_category":"Radiocomunicaciones, Telefon\u00cda M\u00d3vil, Radiomensajer\u00cda: Servicios, Comercializaci\u00d3n",
    "sg:phone":"+34 922 15 14 95",
    "sg:postcode":"38001",
    "sg:province":"Santa Cruz De Tenerife",
    "wof:name":"Machin Fernandez Miguel Angel",
    "wof:placetype":"venue"
},
  "geometry": {"coordinates":[-16.2449493408,28.4773406982],"type":"Point"}
}