{
  "type": "Feature",
  "properties": {
    "iso:country":"ES",
    "sg:address":"Calle de Revenga, 1",
    "sg:city":"Madrid",
    "sg:orig_category":"Molduras, Junquillos, Listones Y Molduras Perforadas",
    "sg:phone":"+34 914 63 13 73",
    "sg:postcode":"28047",
    "sg:province":"Madrid",
    "wof:name":"Alhambra Baena Amelia",
    "wof:placetype":"venue"
},
  "geometry": {"coordinates":[-3.7489833832,40.4028358459],"type":"Point"}
}