{
  "type": "Feature",
  "properties": {
    "iso:country":"ES",
    "sg:address":"Enric Granados(mata), 7",
    "sg:city":"Porqueres",
    "sg:orig_category":"Transportes Por V\u00cdas Navegables",
    "sg:phone":"+34 972 57 13 43",
    "sg:postcode":"17834",
    "sg:province":"Girona",
    "wof:name":"Pla Congost Gabriel",
    "wof:placetype":"venue"
},
  "geometry": {"coordinates":[2.7790899277,42.1037483215],"type":"Point"}
}