{
  "type": "Feature",
  "properties": {
    "iso:country":"ES",
    "sg:address":"Carrer de Girona, S/n",
    "sg:city":"Hospitalet Llobregat",
    "sg:orig_category":"Administraciones De Trabajo Y Empleo",
    "sg:phone":"+34 932 61 14 38",
    "sg:postcode":"08901",
    "sg:province":"Barcelona",
    "wof:name":"Centre De Telecomunicaciones De Catalunya",
    "wof:placetype":"venue"
},
  "geometry": {"coordinates":[2.1034350395,41.3614807129],"type":"Point"}
}