{
  "type": "Feature",
  "properties": {
    "addr:full":"Calle de V Centenario, 5 Marbella M\u00e1laga 29600",
    "addr:housenumber":"5",
    "addr:postcode":"29600",
    "addr:street":"Calle De V Centenario;Ma\u0301Laga",
    "iso:country":"ES",
    "sg:address":"Calle de V Centenario, 5",
    "sg:city":"Marbella",
    "sg:orig_category":"Agencias De Trabajo Temporal",
    "sg:phone":"+34 952 82 93 48",
    "sg:postcode":"29600",
    "sg:province":"M\u00e1laga",
    "wof:name":"Aura Empresa De Trabajo Temporal Soc Coop And",
    "wof:placetype":"venue"
},
  "geometry": {"coordinates":[-4.8789868355,36.5101013184],"type":"Point"}
}