{
  "type": "Feature",
  "properties": {
    "addr:full":"Ctra Zaragoza, 8 Azuara Zaragoza 50140",
    "addr:housenumber":"8",
    "addr:postcode":"50140",
    "addr:street":"Ctra Zaragoza",
    "iso:country":"ES",
    "sg:address":"Ctra Zaragoza, 8",
    "sg:city":"Azuara",
    "sg:orig_category":"Enfermeras: Consultas, Atenci\u00d3n A Domicilio",
    "sg:phone":"+34 976 83 41 77",
    "sg:postcode":"50140",
    "sg:province":"Zaragoza",
    "wof:name":"Belsue Zaldundo Encarnacion",
    "wof:placetype":"venue"
},
  "geometry": {"coordinates":[-0.8728680015,41.2585983276],"type":"Point"}
}