{
  "type": "Feature",
  "properties": {
    "addr:full":"Rua Cardenal Rodrigo De Castro, 27 Monforte De Lemos Lugo 27420",
    "addr:housenumber":"27",
    "addr:postcode":"27420",
    "addr:street":"Rua Cardenal Rodrigo De Castro",
    "iso:country":"ES",
    "sg:address":"Rua Cardenal Rodrigo De Castro, 27",
    "sg:city":"Monforte De Lemos",
    "sg:orig_category":"Loter\u00cda Y T\u00d3mbola",
    "sg:phone":"+34 982 41 02 69",
    "sg:postcode":"27420",
    "sg:province":"Lugo",
    "wof:name":"Lopez Balia Manuel",
    "wof:placetype":"venue"
},
  "geometry": {"coordinates":[-7.5264849663,42.496887207],"type":"Point"}
}