{
  "type": "Feature",
  "properties": {
    "addr:full":"Carr Son Morei, 10 Felanitx Islas Baleares 07200",
    "addr:housenumber":"10",
    "addr:postcode":"07200",
    "addr:street":"Carr Son Morei",
    "iso:country":"ES",
    "sg:address":"Carr Son Morei, 10",
    "sg:city":"Felanitx",
    "sg:orig_category":"Internados & Ense\u00d1anza Privada",
    "sg:phone":"+34 971 58 03 38",
    "sg:postcode":"07200",
    "sg:province":"Islas Baleares",
    "wof:name":"Religiosas T. Trinitarias",
    "wof:placetype":"venue"
},
  "geometry": {"coordinates":[3.1473679543,39.4676628113],"type":"Point"}
}