{
  "type": "Feature",
  "properties": {
    "addr:full":"Ctra Betancuria, S/n Gran Tarajal Las Palmas 35620",
    "addr:housenumber":"s / n",
    "addr:postcode":"35620",
    "addr:street":"Ctra Betancuria;Palmas",
    "iso:country":"ES",
    "sg:address":"Ctra Betancuria, S/n",
    "sg:city":"Gran Tarajal",
    "sg:orig_category":"Empresas De Hormig\u00d3n, Hormig\u00d3n Armado Y Pretensado",
    "sg:phone":"+34 928 16 27 72",
    "sg:postcode":"35620",
    "sg:province":"Las Palmas",
    "wof:name":"Langenbacher Tamm Rodolfo Alberto",
    "wof:placetype":"venue"
},
  "geometry": {"coordinates":[-14.0250358582,28.2110748291],"type":"Point"}
}