{
  "type": "Feature",
  "properties": {
    "iso:country":"ES",
    "sg:address":"Avda Ponte, 12",
    "sg:city":"Gorxal",
    "sg:classifiers":[
        {
            "category":"Autos & Motor Vehicles",
            "subcategory":"Automobile Sales",
            "type":"Retail Goods"
        }
    ],
    "sg:phone":"+34 986 37 78 03",
    "sg:postcode":"36215",
    "sg:province":"Pontevedra",
    "wof:name":"Ense\u00f1anzas Automovilisticas Cabral S.l.",
    "wof:placetype":"venue"
},
  "geometry": {"coordinates":[-8.663274765,42.2263412476],"type":"Point"}
}