{
  "type": "Feature",
  "properties": {
    "addr:full":"Avda Constitucion, 10 Aspe Alicante 03680",
    "addr:housenumber":"10",
    "addr:postcode":"03680",
    "addr:street":"Avda Constitucion",
    "iso:country":"ES",
    "sg:address":"Avda Constitucion, 10",
    "sg:city":"Aspe",
    "sg:orig_category":"Tintes (fabricaci\u00d3n, Al Por Mayor)",
    "sg:phone":"+34 965 49 61 73",
    "sg:postcode":"03680",
    "sg:province":"Alicante",
    "wof:name":"Franisec S.l.",
    "wof:placetype":"venue"
},
  "geometry": {"coordinates":[-0.7690989971,38.3465003967],"type":"Point"}
}