{
  "type": "Feature",
  "properties": {
    "addr:full":"Carr Iquique, 7 Santa Coloma De Farners Girona 17430",
    "addr:housenumber":"7",
    "addr:postcode":"17430",
    "addr:street":"Carr Iquique",
    "iso:country":"ES",
    "sg:address":"Carr Iquique, 7",
    "sg:city":"Santa Coloma De Farners",
    "sg:orig_category":"Empresarios",
    "sg:phone":"+34 972 84 19 89",
    "sg:postcode":"17430",
    "sg:province":"Girona",
    "wof:name":"Taberner Roca Francisco",
    "wof:placetype":"venue"
},
  "geometry": {"coordinates":[2.6750700474,41.8570137024],"type":"Point"}
}