{
  "type": "Feature",
  "properties": {
    "iso:country":"ES",
    "sg:address":"Avgd Joan Xxiii, 8",
    "sg:city":"Badalona",
    "sg:orig_category":"Asesor\u00cda Sobre Comunicaci\u00d3n De Empresas",
    "sg:phone":"+34 934 60 74 74",
    "sg:postcode":"08918",
    "sg:province":"Barcelona",
    "wof:name":"Easywork Ett S.a.",
    "wof:placetype":"venue"
},
  "geometry": {"coordinates":[2.2171149254,41.4331626892],"type":"Point"}
}