{
  "type": "Feature",
  "properties": {
    "iso:country":"ES",
    "sg:address":"Calle de Ferrocarril, 7",
    "sg:city":"S. Fernando",
    "sg:orig_category":"Agentes, Concesionarios Y Sucursales De Veh\u00cdculos",
    "sg:phone":"+34 956 59 47 34",
    "sg:postcode":"11100",
    "sg:province":"C\u00e1diz",
    "wof:name":"Taller Rober Diesel S.l.",
    "wof:placetype":"venue"
},
  "geometry": {"coordinates":[-6.2017550468,36.4739990234],"type":"Point"}
}