{
  "type": "Feature",
  "properties": {
    "iso:country":"ES",
    "sg:address":"Carrer de Nicaragua, 11",
    "sg:city":"Sant Cristofol Les Fonts",
    "sg:orig_category":"Negocio De Materiales De Construcci\u00d3n",
    "sg:phone":"+34 972 26 67 96",
    "sg:postcode":"17800",
    "sg:province":"Girona",
    "wof:name":"Ambient I Disseny S.l.",
    "wof:placetype":"venue"
},
  "geometry": {"coordinates":[2.4812366962,42.173500061],"type":"Point"}
}