{
  "type": "Feature",
  "properties": {
    "iso:country":"ES",
    "sg:address":"Avda Ca\u00d1ada (de La), 60",
    "sg:city":"Coslada",
    "sg:orig_category":"Organizaciones Profesionales",
    "sg:phone":"+34 916 72 03 83",
    "sg:postcode":"28820",
    "sg:province":"Madrid",
    "sg:website":"www.lotrans.es",
    "wof:name":"Lotrans Logistica Y Transporte S.a.",
    "wof:placetype":"venue"
},
  "geometry": {"coordinates":[-3.5408930779,40.436756134],"type":"Point"}
}