{
  "type": "Feature",
  "properties": {
    "iso:country":"ES",
    "sg:address":"Rua Santiago De Chile (de), 1",
    "sg:city":"Santiago De Compostela",
    "sg:orig_category":"Molduras, Junquillos, Listones Y Molduras Perforadas",
    "sg:phone":"+34 981 59 83 47",
    "sg:postcode":"15706",
    "sg:province":"La Coru\u00f1a",
    "wof:name":"Negreira Toja Julian",
    "wof:placetype":"venue"
},
  "geometry": {"coordinates":[-8.5514154434,42.8735847473],"type":"Point"}
}