{
  "type": "Feature",
  "properties": {
    "addr:full":"Carrer de Doctor Torrademe, S/n Perello Tarragona 43519",
    "addr:housenumber":"s",
    "addr:postcode":"43519",
    "addr:street":"Carrer De Doctor Torrademe;/ N",
    "iso:country":"ES",
    "sg:address":"Carrer de Doctor Torrademe, S/n",
    "sg:city":"Perello",
    "sg:orig_category":"Mec\u00c1nico Del Autom\u00d3vil",
    "sg:phone":"+34 977 49 00 24",
    "sg:postcode":"43519",
    "sg:province":"Tarragona",
    "wof:name":"Barbera Brull Juan",
    "wof:placetype":"venue"
},
  "geometry": {"coordinates":[0.7099450231,40.8737602234],"type":"Point"}
}