{
  "type": "Feature",
  "properties": {
    "iso:country":"ES",
    "sg:address":"Calle de Benita Lopez, 40",
    "sg:city":"Madrid",
    "sg:orig_category":"Bancos",
    "sg:phone":"+34 917 96 62 80",
    "sg:postcode":"28021",
    "sg:province":"Madrid",
    "wof:name":"Banco Vitalicio De Espa\u00d1a C.a.",
    "wof:placetype":"venue"
},
  "geometry": {"coordinates":[-3.6894528866,40.3492126465],"type":"Point"}
}