{
  "type": "Feature",
  "properties": {
    "addr:full":"Calle de Fernando El Catolico, 30 Madrid Madrid 28015",
    "addr:housenumber":"30",
    "addr:postcode":"madrid;28015",
    "addr:street":"Calle De Fernando El Catolico",
    "iso:country":"ES",
    "sg:address":"Calle de Fernando El Catolico, 30",
    "sg:city":"Madrid",
    "sg:orig_category":"Abogados",
    "sg:phone":"+34 915 44 70 69",
    "sg:postcode":"28015",
    "sg:province":"Madrid",
    "wof:name":"Ramirez Martinez Consuelo",
    "wof:placetype":"venue"
},
  "geometry": {"coordinates":[-3.7108769417,40.4342498779],"type":"Point"}
}