{
  "type": "Feature",
  "properties": {
    "addr:full":"Calle de San Salvador, 1 Merida Badajoz 06800",
    "addr:housenumber":"1",
    "addr:postcode":"06800",
    "addr:street":"Calle De San Salvador",
    "iso:country":"ES",
    "sg:address":"Calle de San Salvador, 1",
    "sg:city":"Merida",
    "sg:orig_category":"Agencias Y Agentes Comerciales, Representantes",
    "sg:phone":"+34 924 31 02 01",
    "sg:postcode":"06800",
    "sg:province":"Badajoz",
    "wof:name":"Arias Galan Avelino",
    "wof:placetype":"venue"
},
  "geometry": {"coordinates":[-6.3478097916,38.9165802002],"type":"Point"}
}