{
  "type": "Feature",
  "properties": {
    "addr:full":"Calle de Max Garcia Soriano, 15 Elda Alicante 03600",
    "addr:housenumber":"15",
    "addr:postcode":"03600",
    "addr:street":"Calle De Max Garcia Soriano",
    "iso:country":"ES",
    "sg:address":"Calle de Max Garcia Soriano, 15",
    "sg:city":"Elda",
    "sg:orig_category":"Zapater\u00cdas",
    "sg:phone":"+34 965 38 28 22",
    "sg:postcode":"03600",
    "sg:province":"Alicante",
    "wof:name":"Marcen Roman Enrique",
    "wof:placetype":"venue"
},
  "geometry": {"coordinates":[-0.7851399779,38.4754981995],"type":"Point"}
}