{
  "type": "Feature",
  "properties": {
    "iso:country":"ES",
    "sg:address":"Pase San Roque (de), 21",
    "sg:city":"Avila",
    "sg:orig_category":"Mutuas De Seguros",
    "sg:phone":"+34 920 25 34 10",
    "sg:postcode":"05003",
    "sg:province":"\u00c1vila",
    "sg:website":"www.fraternidad.com",
    "wof:name":"Fraternidad-muprespa Mutua De Accidentes De Trabajo Y Enfermedades Profesionales",
    "wof:placetype":"venue"
},
  "geometry": {"coordinates":[-4.6884198189,40.6536827087],"type":"Point"}
}