{
  "type": "Feature",
  "properties": {
    "iso:country":"ES",
    "sg:address":"Calle de Marques De Valero De Urria, 1",
    "sg:city":"Oviedo",
    "sg:orig_category":"Librer\u00cdas",
    "sg:phone":"+34 985 11 38 09",
    "sg:postcode":"33011",
    "sg:province":"Asturias",
    "wof:name":"Alaitasune Nieto Norniella",
    "wof:placetype":"venue"
},
  "geometry": {"coordinates":[-5.8395628929,43.3694992065],"type":"Point"}
}