{
  "type": "Feature",
  "properties": {
    "addr:full":"Calle de Soledad, 32 Campanario Badajoz 06460",
    "addr:housenumber":"32",
    "addr:postcode":"06460",
    "addr:street":"Calle De Soledad",
    "iso:country":"ES",
    "sg:address":"Calle de Soledad, 32",
    "sg:city":"Campanario",
    "sg:orig_category":"Ropa Para Se\u00d1oras Y Caballeros (al Por Menor)",
    "sg:phone":"+34 924 85 18 09",
    "sg:postcode":"06460",
    "sg:province":"Badajoz",
    "wof:name":"Blanco Mateos Juana",
    "wof:placetype":"venue"
},
  "geometry": {"coordinates":[-5.6141982079,38.860042572],"type":"Point"}
}