{
  "type": "Feature",
  "properties": {
    "iso:country":"ES",
    "sg:address":"Forte, 16",
    "sg:city":"Enfesta",
    "sg:classifiers":[
        {
            "category":"Cinema",
            "subcategory":"Movie Theater",
            "type":"Entertainment"
        }
    ],
    "sg:phone":"+34 981 88 80 46",
    "sg:postcode":"15884",
    "sg:province":"La Coru\u00f1a",
    "sg:tags":[
        "salas",
        "de",
        "cine"
    ],
    "wof:name":"Guindastres De Cinema S.l.",
    "wof:placetype":"venue"
},
  "geometry": {"coordinates":[-8.4691371918,42.9413528442],"type":"Point"}
}