{
  "type": "Feature",
  "properties": {
    "addr:full":"Av Rius I Taulet, 5 S. Cugat Valles Barcelona 08172",
    "addr:housenumber":"5",
    "addr:postcode":"08172",
    "addr:street":"Av Rius I Taulet;Barcelona",
    "iso:country":"ES",
    "sg:address":"Av Rius I Taulet, 5",
    "sg:city":"S. Cugat Valles",
    "sg:orig_category":"Asesor\u00cda Sobre Comunicaci\u00d3n De Empresas",
    "sg:phone":"+34 936 75 37 05",
    "sg:postcode":"08172",
    "sg:province":"Barcelona",
    "wof:name":"Tramit Serveis Professionals S.l.",
    "wof:placetype":"venue"
},
  "geometry": {"coordinates":[2.0817799568,41.4718399048],"type":"Point"}
}