{
  "type": "Feature",
  "properties": {
    "iso:country":"ES",
    "sg:address":"Calle de Mateo De Torres, 10",
    "sg:city":"Alcala Henares",
    "sg:orig_category":"Electricidad: Instaladores",
    "sg:phone":"+34 918 81 11 89",
    "sg:postcode":"28806",
    "sg:province":"Madrid",
    "sg:website":"www.tecnicaslorente.com",
    "wof:name":"Tecnicas Lorente S.l.",
    "wof:placetype":"venue"
},
  "geometry": {"coordinates":[-3.3783595562,40.491268158],"type":"Point"}
}