{
  "type": "Feature",
  "properties": {
    "addr:full":"Calle de J Artes De Arcos, 4 Alhama De Almeria Almer\u00eda 04400",
    "addr:postcode":"04400",
    "addr:street":"Calle De;Alhama;Almeri\u0301A",
    "iso:country":"ES",
    "sg:address":"Calle de J Artes De Arcos, 4",
    "sg:city":"Alhama De Almeria",
    "sg:orig_category":"Asesor\u00cda De Formaci\u00d3n Y Gesti\u00d3n De Personal",
    "sg:phone":"+34 950 64 07 74",
    "sg:postcode":"04400",
    "sg:province":"Almer\u00eda",
    "wof:name":"Romero Martinez Angel",
    "wof:placetype":"venue"
},
  "geometry": {"coordinates":[-2.5671710968,36.9576148987],"type":"Point"}
}