{
  "type": "Feature",
  "properties": {
    "iso:country":"ES",
    "sg:address":"Dorraburu, 1",
    "sg:city":"Huarte",
    "sg:orig_category":"Artes Gr\u00c1ficas, Artes Pl\u00c1sticas (curso)",
    "sg:phone":"+34 948 33 03 12",
    "sg:postcode":"31620",
    "sg:province":"Navarra",
    "sg:website":"www.zokoa.com",
    "wof:name":"Graficas Zokoa S. A.",
    "wof:placetype":"venue"
},
  "geometry": {"coordinates":[-1.5958919525,42.8307723999],"type":"Point"}
}