{
  "type": "Feature",
  "properties": {
    "addr:full":"Av. Pais Valencia, 4 Sedavi Valencia 46910",
    "addr:housenumber":"4",
    "addr:postcode":"46910",
    "addr:street":"Av. Pais Valencia",
    "iso:country":"ES",
    "sg:address":"Av. Pais Valencia, 4",
    "sg:city":"Sedavi",
    "sg:orig_category":"Alumbrados",
    "sg:phone":"+34 963 75 33 15",
    "sg:postcode":"46910",
    "sg:province":"Valencia",
    "sg:website":"www.luzete.com",
    "wof:name":"Luzete Iluminacion S.l.",
    "wof:placetype":"venue"
},
  "geometry": {"coordinates":[-0.3760989904,39.4240684509],"type":"Point"}
}