{
  "type": "Feature",
  "properties": {
    "addr:full":"Avda Benidorm, 23 Arnedo La Rioja 26580",
    "addr:housenumber":"23",
    "addr:postcode":"26580",
    "addr:street":"Avda Benidorm;Rioja",
    "iso:country":"ES",
    "sg:address":"Avda Benidorm, 23",
    "sg:city":"Arnedo",
    "sg:orig_category":"Laboratorios Y Trabajos De Fotograf\u00cda, V\u00cddeo Y Cine",
    "sg:phone":"+34 941 38 01 10",
    "sg:postcode":"26580",
    "sg:province":"La Rioja",
    "wof:name":"Mur Jimenez Miguel",
    "wof:placetype":"venue"
},
  "geometry": {"coordinates":[-2.0976929665,42.2261047363],"type":"Point"}
}