{
  "type": "Feature",
  "properties": {
    "iso:country":"ES",
    "sg:address":"Carr Sant Lluis, 77",
    "sg:city":"Balaguer",
    "sg:orig_category":"Arquitectos",
    "sg:phone":"+34 973 44 76 64",
    "sg:postcode":"25600",
    "sg:province":"Lleida",
    "wof:name":"Llobet Camarasa Jose Maria",
    "wof:placetype":"venue"
},
  "geometry": {"coordinates":[0.8071600199,41.7896003723],"type":"Point"}
}