{
  "type": "Feature",
  "properties": {
    "iso:country":"ES",
    "sg:address":"Carr Antonio De Oquendo, 42",
    "sg:city":"Mao",
    "sg:orig_category":"Promotores Constructores",
    "sg:phone":"+34 971 35 57 77",
    "sg:postcode":"07702",
    "sg:province":"Islas Baleares",
    "wof:name":"Edificaciones Ramos S. A.",
    "wof:placetype":"venue"
},
  "geometry": {"coordinates":[4.2698020935,39.8843383789],"type":"Point"}
}