{
  "type": "Feature",
  "properties": {
    "addr:full":"Calle de Luis Montoto, 105 Sevilla Sevilla 41007",
    "addr:housenumber":"105",
    "addr:postcode":"41007",
    "addr:street":"Calle De Luis Montoto",
    "iso:country":"ES",
    "sg:address":"Calle de Luis Montoto, 105",
    "sg:city":"Sevilla",
    "sg:orig_category":"Abogados",
    "sg:phone":"+34 954 57 28 72",
    "sg:postcode":"41007",
    "sg:province":"Sevilla",
    "wof:name":"Perez Morilla Jose Manuel",
    "wof:placetype":"venue"
},
  "geometry": {"coordinates":[-5.9707369804,37.3874664307],"type":"Point"}
}