{
  "type": "Feature",
  "properties": {
    "addr:full":"Calle de Virgen Del Casta\u00d1ar, 19 Madrid Madrid 28027",
    "addr:housenumber":"19",
    "addr:postcode":"madrid;28027",
    "addr:street":"Calle De Virgen Del Castan\u0303Ar",
    "iso:country":"ES",
    "sg:address":"Calle de Virgen Del Casta\u00d1ar, 19",
    "sg:city":"Madrid",
    "sg:orig_category":"Empresarios",
    "sg:phone":"+34 914 05 58 64",
    "sg:postcode":"28027",
    "sg:province":"Madrid",
    "wof:name":"Gonzalez Hernandez Jaime",
    "wof:placetype":"venue"
},
  "geometry": {"coordinates":[-3.6493420601,40.4392623901],"type":"Point"}
}