{
  "type": "Feature",
  "properties": {
    "addr:full":"Rua Nicolas Tenorio, 54 Viana Do Bolo Ourense 32550",
    "addr:housenumber":"54",
    "addr:postcode":"32550",
    "addr:street":"Rua Nicolas Tenorio",
    "iso:country":"ES",
    "sg:address":"Rua Nicolas Tenorio, 54",
    "sg:city":"Viana Do Bolo",
    "sg:orig_category":"T\u00c9cnicos Veterinarios",
    "sg:phone":"+34 988 32 92 64",
    "sg:postcode":"32550",
    "sg:province":"Ourense",
    "wof:name":"Dominguez Rodriguez Francisco Jose",
    "wof:placetype":"venue"
},
  "geometry": {"coordinates":[-7.1094288826,42.1798095703],"type":"Point"}
}