{
  "type": "Feature",
  "properties": {
    "addr:full":"Calle de Ruiz Mu\u00d1oz, 1 Palma Rio C\u00f3rdoba 14700",
    "addr:housenumber":"1",
    "addr:postcode":"14700",
    "addr:street":"Calle De Ruiz Mun\u0303Oz;Rio Co\u0301Rdoba",
    "iso:country":"ES",
    "sg:address":"Calle de Ruiz Mu\u00d1oz, 1",
    "sg:city":"Palma Rio",
    "sg:orig_category":"Ense\u00d1anza, Formaci\u00d3n Profesional: Aprendizaje",
    "sg:phone":"+34 957 64 59 26",
    "sg:postcode":"14700",
    "sg:province":"C\u00f3rdoba",
    "wof:name":"Ayuntamiento",
    "wof:placetype":"venue"
},
  "geometry": {"coordinates":[-5.2833709717,37.7014312744],"type":"Point"}
}