{
  "type": "Feature",
  "properties": {
    "iso:country":"ES",
    "sg:address":"Calle de Tetuan, 21",
    "sg:city":"Sevilla",
    "sg:orig_category":"Abogados",
    "sg:phone":"+34 954 22 76 58",
    "sg:postcode":"41001",
    "sg:province":"Sevilla",
    "wof:name":"Garcia Perez Del Cerro Agustin",
    "wof:placetype":"venue"
},
  "geometry": {"coordinates":[-5.9951810837,37.3897819519],"type":"Point"}
}