{
  "type": "Feature",
  "properties": {
    "iso:country":"ES",
    "sg:address":"Calle de Huesca, 7",
    "sg:city":"Casetas",
    "sg:orig_category":"Peluqueros: De Se\u00d1oras",
    "sg:phone":"+34 976 78 81 45",
    "sg:postcode":"50620",
    "sg:province":"Zaragoza",
    "wof:name":"Perez Gilaberte Rosalia",
    "wof:placetype":"venue"
},
  "geometry": {"coordinates":[-1.0265200138,41.7197761536],"type":"Point"}
}