{
  "type": "Feature",
  "properties": {
    "iso:country":"ES",
    "sg:address":"Carrer de Isaac Albeniz, 24",
    "sg:city":"Granollers",
    "sg:orig_category":"Supermercados Y Hipermercados",
    "sg:phone":"+34 938 79 57 76",
    "sg:postcode":"08402",
    "sg:province":"Barcelona",
    "wof:name":"Supermercados Arroyo Y Cervantes S.l.",
    "wof:placetype":"venue"
},
  "geometry": {"coordinates":[2.2897429466,41.5986404419],"type":"Point"}
}