{
  "type": "Feature",
  "properties": {
    "addr:full":"Carrer de Calvet, 3 Barcelona Barcelona 08021",
    "addr:housenumber":"3",
    "addr:postcode":"08021",
    "addr:street":"Carrer De Calvet",
    "iso:country":"ES",
    "sg:address":"Carrer de Calvet, 3",
    "sg:city":"Barcelona",
    "sg:orig_category":"Medias Y Calcetines (al Por Menor)",
    "sg:phone":"+34 932 00 10 66",
    "sg:postcode":"08021",
    "sg:province":"Barcelona",
    "sg:website":"www.calzedonia.com",
    "wof:name":"Avant Car 25 S.l.",
    "wof:placetype":"venue"
},
  "geometry": {"coordinates":[2.144908905,41.3934173584],"type":"Point"}
}