{
  "type": "Feature",
  "properties": {
    "addr:full":"Carr Camelia, 42 Badalona Barcelona 08912",
    "addr:housenumber":"42",
    "addr:postcode":"08912",
    "addr:street":"Carr Camelia",
    "iso:country":"ES",
    "sg:address":"Carr Camelia, 42",
    "sg:city":"Badalona",
    "sg:orig_category":"Control T\u00c9cnico De Veh\u00cdculos",
    "sg:phone":"+34 933 83 94 41",
    "sg:postcode":"08912",
    "sg:province":"Barcelona",
    "wof:name":"Fomento De Construcciones Y Contratas S.a.",
    "wof:placetype":"venue"
},
  "geometry": {"coordinates":[2.2393860817,41.4494552612],"type":"Point"}
}