{
  "type": "Feature",
  "properties": {
    "iso:country":"ES",
    "sg:address":"Calle de Republica Argentina, 28",
    "sg:city":"Carrizal",
    "sg:orig_category":"Laboratorios Y Trabajos De Fotograf\u00cda, V\u00cddeo Y Cine",
    "sg:phone":"+34 928 78 06 52",
    "sg:postcode":"35240",
    "sg:province":"Las Palmas",
    "wof:name":"Foto Viera Deniz S.l.",
    "wof:placetype":"venue"
},
  "geometry": {"coordinates":[-15.4088716507,27.9104499817],"type":"Point"}
}