{
  "type": "Feature",
  "properties": {
    "iso:country":"ES",
    "sg:address":"Toscal, S/n",
    "sg:city":"Ingenio",
    "sg:orig_category":"Aguas (distribuci\u00d3n, Servicios)",
    "sg:phone":"+34 928 78 38 08",
    "sg:postcode":"35250",
    "sg:province":"Las Palmas",
    "wof:name":"Aguas Del Toscal S.a.",
    "wof:placetype":"venue"
},
  "geometry": {"coordinates":[-15.4126653671,27.9299545288],"type":"Point"}
}