{
  "type": "Feature",
  "properties": {
    "iso:country":"ES",
    "sg:address":"Calle de Picazo, S/n",
    "sg:city":"Beteta",
    "sg:orig_category":"Asilos De Ancianos. Centros Privados",
    "sg:phone":"+34 969 31 82 76",
    "sg:postcode":"16870",
    "sg:province":"Cuenca",
    "wof:name":"Ayuntamiento De Beteta -vivienda Mayores",
    "wof:placetype":"venue"
},
  "geometry": {"coordinates":[-2.0767390728,40.5723800659],"type":"Point"}
}