{
  "type": "Feature",
  "properties": {
    "iso:country":"ES",
    "sg:address":"Calle de Padre Flores, 53",
    "sg:city":"Alcala Guadaira",
    "sg:orig_category":"Ropa Para Se\u00d1oras Y Caballeros (al Por Menor)",
    "sg:phone":"+34 955 68 63 57",
    "sg:postcode":"41500",
    "sg:province":"Sevilla",
    "wof:name":"Rico Donoso Francisco",
    "wof:placetype":"venue"
},
  "geometry": {"coordinates":[-5.8395738602,37.3401031494],"type":"Point"}
}