{
  "type": "Feature",
  "properties": {
    "addr:full":"Las Maravillas, S/n La Herradura Granada 18697",
    "addr:housenumber":"s / n",
    "addr:postcode":"18697",
    "addr:street":"Maravillas",
    "iso:country":"ES",
    "sg:address":"Las Maravillas, S/n",
    "sg:city":"La Herradura",
    "sg:orig_category":"Transportes Por V\u00cdas Navegables",
    "sg:phone":"+34 958 64 01 53",
    "sg:postcode":"18697",
    "sg:province":"Granada",
    "wof:name":"Martin Jimenez Jose",
    "wof:placetype":"venue"
},
  "geometry": {"coordinates":[-3.7373390198,36.7349243164],"type":"Point"}
}