{
  "type": "Feature",
  "properties": {
    "addr:full":"Calle de Lima, 4 Caceres C\u00e1ceres 10005",
    "addr:housenumber":"4",
    "addr:postcode":"10005",
    "addr:street":"Calle De Lima;Ca\u0301Ceres",
    "iso:country":"ES",
    "sg:address":"Calle de Lima, 4",
    "sg:city":"Caceres",
    "sg:orig_category":"Peluquer\u00cdas, Peluquer\u00cda Mixta",
    "sg:phone":"+34 927 23 17 60",
    "sg:postcode":"10005",
    "sg:province":"C\u00e1ceres",
    "wof:name":"Romero Rubio Karen",
    "wof:placetype":"venue"
},
  "geometry": {"coordinates":[-6.385529995,39.4660377502],"type":"Point"}
}