{
  "type": "Feature",
  "properties": {
    "iso:country":"ES",
    "sg:address":"Ctra Manresa, S/n",
    "sg:city":"Solsona",
    "sg:orig_category":"Carnicer\u00cdas, Carnicer\u00cdas",
    "sg:phone":"+34 973 48 20 55",
    "sg:postcode":"25280",
    "sg:province":"Lleida",
    "wof:name":"Xarcuteria Can Solvi S.l.",
    "wof:placetype":"venue"
},
  "geometry": {"coordinates":[1.5277813673,41.9942436218],"type":"Point"}
}