{
  "type": "Feature",
  "properties": {
    "addr:full":"Avda Andalucia, 40 Villanueva Rio Y Minas Sevilla 41350",
    "addr:housenumber":"40",
    "addr:postcode":"41350",
    "addr:street":"Avda Andalucia",
    "iso:country":"ES",
    "sg:address":"Avda Andalucia, 40",
    "sg:city":"Villanueva Rio Y Minas",
    "sg:orig_category":"Cer\u00c1mica Art\u00cdstica Y Decorativa",
    "sg:phone":"+34 954 74 74 40",
    "sg:postcode":"41350",
    "sg:province":"Sevilla",
    "wof:name":"Arte-mina S.l.",
    "wof:placetype":"venue"
},
  "geometry": {"coordinates":[-5.7117314339,37.6490707397],"type":"Point"}
}