{
  "type": "Feature",
  "properties": {
    "addr:full":"Carrer de Vallseca, 26 Barcelona Barcelona 08024",
    "addr:housenumber":"26",
    "addr:postcode":"08024",
    "addr:street":"Carrer De Vallseca",
    "iso:country":"ES",
    "sg:address":"Carrer de Vallseca, 26",
    "sg:city":"Barcelona",
    "sg:orig_category":"Institutos De Belleza",
    "sg:phone":"+34 932 85 05 55",
    "sg:postcode":"08024",
    "sg:province":"Barcelona",
    "wof:name":"Vives Fortuny Ana",
    "wof:placetype":"venue"
},
  "geometry": {"coordinates":[2.1627764702,41.4151229858],"type":"Point"}
}