{
  "type": "Feature",
  "properties": {
    "iso:country":"ES",
    "sg:address":"Calle de Espartinas, 5",
    "sg:city":"Madrid",
    "sg:orig_category":"Abogados",
    "sg:phone":"+34 915 78 12 10",
    "sg:postcode":"28001",
    "sg:province":"Madrid",
    "wof:name":"Ure\u00f1a Carrasco Jose",
    "wof:placetype":"venue"
},
  "geometry": {"coordinates":[-3.6795420647,40.4243087769],"type":"Point"}
}