{
  "type": "Feature",
  "properties": {
    "iso:country":"ES",
    "sg:address":"Avda Antonio Trueba, 42",
    "sg:city":"San Juan De Muskiz",
    "sg:orig_category":"Alimentaci\u00d3n General (al Por Menor)",
    "sg:phone":"+34 946 70 80 87",
    "sg:postcode":"48550",
    "sg:province":"Vizcaya",
    "wof:name":"Urar-muskiz S.l.",
    "wof:placetype":"venue"
},
  "geometry": {"coordinates":[-3.1171889305,43.3202781677],"type":"Point"}
}