{
  "type": "Feature",
  "properties": {
    "addr:full":"Calle de Carmen (b), 5 Brazatortas Ciudad Real 13450",
    "addr:housenumber":"5",
    "addr:postcode":"13450",
    "addr:street":"Calle De Carmen B",
    "iso:country":"ES",
    "sg:address":"Calle de Carmen (b), 5",
    "sg:city":"Brazatortas",
    "sg:orig_category":"Cajas Para Embalar",
    "sg:phone":"+34 926 47 15 63",
    "sg:postcode":"13450",
    "sg:province":"Ciudad Real",
    "wof:name":"Caja Rural Provincial De Ciudad Real",
    "wof:placetype":"venue"
},
  "geometry": {"coordinates":[-4.293990612,38.6586151123],"type":"Point"}
}