{
  "type": "Feature",
  "properties": {
    "addr:full":"Ctra S. J. Rinconada, Km. 0012,3 Brenes Sevilla 41310",
    "addr:postcode":"41310",
    "addr:street":"Ctra S. J. Rinconada Km. 0012,3 Brenes",
    "iso:country":"ES",
    "sg:address":"Ctra S. J. Rinconada, Km. 0012,3",
    "sg:city":"Brenes",
    "sg:orig_category":"Distribuci\u00d3n De Petr\u00d3leo Y Derivados",
    "sg:phone":"+34 955 65 38 75",
    "sg:postcode":"41310",
    "sg:province":"Sevilla",
    "wof:name":"Brenes Unidad De Suministro S.l.",
    "wof:placetype":"venue"
},
  "geometry": {"coordinates":[-5.8697390556,37.5507011414],"type":"Point"}
}