{
  "type": "Feature",
  "properties": {
    "iso:country":"ES",
    "sg:address":"Calle de San Blas, 77",
    "sg:city":"Alburquerque",
    "sg:orig_category":"Organizaciones Internacionales",
    "sg:phone":"+34 924 40 11 78",
    "sg:postcode":"06510",
    "sg:province":"Badajoz",
    "wof:name":"Adifisa",
    "wof:placetype":"venue"
},
  "geometry": {"coordinates":[-7.007956028,39.222278595],"type":"Point"}
}