{
  "type": "Feature",
  "properties": {
    "iso:country":"ES",
    "sg:address":"Calle de Calasanz, 4",
    "sg:city":"Alcala Henares",
    "sg:orig_category":"Reposter\u00cdas",
    "sg:phone":"+34 918 78 92 23",
    "sg:postcode":"28805",
    "sg:province":"Madrid",
    "wof:name":"Montenegro Rosado Alicia",
    "wof:placetype":"venue"
},
  "geometry": {"coordinates":[-3.359815836,40.4894180298],"type":"Point"}
}