{
  "type": "Feature",
  "properties": {
    "iso:country":"ES",
    "sg:address":"Calle de Arrabal, S/n",
    "sg:city":"Santander",
    "sg:orig_category":"Detectives, Agentes Investigadores Privados",
    "sg:phone":"+34 942 21 31 96",
    "sg:postcode":"39003",
    "sg:province":"Cantabria",
    "wof:name":"2000 Ar 12 S.l.",
    "wof:placetype":"venue"
},
  "geometry": {"coordinates":[-3.804391,43.463169],"type":"Point"}
}