{
  "type": "Feature",
  "properties": {
    "iso:country":"ES",
    "sg:address":"Port, S/n",
    "sg:city":"Palamos",
    "sg:orig_category":"Promotores Constructores",
    "sg:phone":"+34 972 60 17 71",
    "sg:postcode":"17230",
    "sg:province":"Girona",
    "wof:name":"Tecnologias Y Servicios Agrarios S.a.",
    "wof:placetype":"venue"
},
  "geometry": {"coordinates":[3.1296219826,41.8426475525],"type":"Point"}
}