{
  "type": "Feature",
  "properties": {
    "addr:full":"Paseo Publico, S/n Loja Granada 18300",
    "addr:housenumber":"s / n loja",
    "addr:postcode":"18300",
    "addr:street":"Paseo Publico",
    "iso:country":"ES",
    "sg:address":"Paseo Publico, S/n",
    "sg:city":"Loja",
    "sg:orig_category":"Hielo Artificial (fabricaci\u00d3n, Distribuci\u00d3n)",
    "sg:phone":"+34 958 32 12 15",
    "sg:postcode":"18300",
    "sg:province":"Granada",
    "wof:name":"Congelados Apolo S.l.",
    "wof:placetype":"venue"
},
  "geometry": {"coordinates":[-4.1505270004,37.1690177917],"type":"Point"}
}