{
  "type": "Feature",
  "properties": {
    "addr:full":"Ctra Const-puebla Infantes, Km. 0009,2 Constantina Sevilla 41450",
    "addr:postcode":"41450",
    "addr:street":"Ctra Const-Puebla Infantes Km. 0009,2",
    "iso:country":"ES",
    "sg:address":"Ctra Const-puebla Infantes, Km. 0009,2",
    "sg:city":"Constantina",
    "sg:orig_category":"Cr\u00cda De Animales",
    "sg:phone":"+34 955 95 40 79",
    "sg:postcode":"41450",
    "sg:province":"Sevilla",
    "wof:name":"La Guzmana S.cv.",
    "wof:placetype":"venue"
},
  "geometry": {"coordinates":[-5.6197562218,37.8712120056],"type":"Point"}
}