{
  "type": "Feature",
  "properties": {
    "iso:country":"ES",
    "sg:address":"Rava Santa Anna, 62",
    "sg:city":"Reus",
    "sg:orig_category":"Bisuter\u00cda, Joyer\u00cda, Relojer\u00cda (al Por Menor)",
    "sg:phone":"+34 977 34 50 64",
    "sg:postcode":"43201",
    "sg:province":"Tarragona",
    "wof:name":"Sole Joiers S.c.p.",
    "wof:placetype":"venue"
},
  "geometry": {"coordinates":[1.1102230549,41.156665802],"type":"Point"}
}