{
  "type": "Feature",
  "properties": {
    "addr:full":"Calle de Carcagente, 18 Valencia Valencia 46007",
    "addr:housenumber":"18",
    "addr:postcode":"46007",
    "addr:street":"Calle De Carcagente",
    "iso:country":"ES",
    "sg:address":"Calle de Carcagente, 18",
    "sg:city":"Valencia",
    "sg:orig_category":"Ropa De Hogar (al Por Menor)",
    "sg:phone":"+34 963 80 31 63",
    "sg:postcode":"46007",
    "sg:province":"Valencia",
    "wof:name":"Garcia Garcia Maria Angeles",
    "wof:placetype":"venue"
},
  "geometry": {"coordinates":[-0.3868716955,39.4593315125],"type":"Point"}
}