{
  "type": "Feature",
  "properties": {
    "iso:country":"ES",
    "sg:address":"Calle de Reyes Catolicos (de Los), 2",
    "sg:city":"Alcobendas",
    "sg:orig_category":"Producci\u00d3n, Distribuci\u00d3n De Electricidad",
    "sg:phone":"+34 914 90 06 01",
    "sg:postcode":"28108",
    "sg:province":"Madrid",
    "wof:name":"Dielectro Industrial S.a.",
    "wof:placetype":"venue"
},
  "geometry": {"coordinates":[-3.6549229622,40.5377883911],"type":"Point"}
}