{
  "type": "Feature",
  "properties": {
    "addr:full":"Cami Cami Del Bony - Poligono Industrial, S/n Catarroja Valencia 46470",
    "addr:postcode":"46470",
    "addr:street":"Cami Del Bony Poligono Industrial S / N",
    "iso:country":"ES",
    "sg:address":"Cami Cami Del Bony - Poligono Industrial, S/n",
    "sg:city":"Catarroja",
    "sg:orig_category":"Fabricaci\u00d3n De Mobiliario De Oficina",
    "sg:phone":"+34 961 27 00 84",
    "sg:postcode":"46470",
    "sg:province":"Valencia",
    "wof:name":"Jose Martinez Medina S. A.",
    "wof:placetype":"venue"
},
  "geometry": {"coordinates":[-0.414440006,39.3972015381],"type":"Point"}
}