{
  "type": "Feature",
  "properties": {
    "iso:country":"ES",
    "sg:address":"Calle de Velazquez, 35",
    "sg:city":"Madrid",
    "sg:orig_category":"Servicios De Telecomunicaciones",
    "sg:phone":"+34 914 31 54 26",
    "sg:postcode":"28001",
    "sg:province":"Madrid",
    "sg:website":"www.islalink.es",
    "wof:name":"Islalink Sa",
    "wof:placetype":"venue"
},
  "geometry": {"coordinates":[-3.6842648983,40.4256591797],"type":"Point"}
}