{
  "type": "Feature",
  "properties": {
    "iso:country":"ES",
    "sg:address":"Yegen, 3",
    "sg:city":"Granada",
    "sg:orig_category":"Bosques (trabajos, Asesor\u00cda, Gesti\u00d3n)",
    "sg:phone":"+34 958 80 44 37",
    "sg:postcode":"18003",
    "sg:province":"Granada",
    "wof:name":"Ibersilva Servicios S.a.u.",
    "wof:placetype":"venue"
},
  "geometry": {"coordinates":[-3.6194820404,37.1829376221],"type":"Point"}
}