{
  "type": "Feature",
  "properties": {
    "addr:full":"Calle de Juan Garcia Hortelano, 2 Valladolid Valladolid 47014",
    "addr:housenumber":"2",
    "addr:postcode":"47014",
    "addr:street":"Calle De Juan;Hortelano",
    "iso:country":"ES",
    "sg:address":"Calle de Juan Garcia Hortelano, 2",
    "sg:city":"Valladolid",
    "sg:orig_category":"Peluquer\u00cdas, Peluquer\u00cda Mixta",
    "sg:phone":"+34 983 37 32 81",
    "sg:postcode":"47014",
    "sg:province":"Valladolid",
    "wof:name":"Blanco Casta\u00f1o Maria Flor",
    "wof:placetype":"venue"
},
  "geometry": {"coordinates":[-4.7609820366,41.636882782],"type":"Point"}
}