{
  "type": "Feature",
  "properties": {
    "iso:country":"ES",
    "sg:address":"Av Can Sucarrats, S/n",
    "sg:city":"Rubi",
    "sg:orig_category":"Ingenier\u00cda, Centros De Estudios (industria)",
    "sg:phone":"+34 936 97 86 95",
    "sg:postcode":"08191",
    "sg:province":"Barcelona",
    "sg:website":"www.tecnicasdesolido.com",
    "wof:name":"Tecnicas De Solido S.a.",
    "wof:placetype":"venue"
},
  "geometry": {"coordinates":[2.0192379951,41.4868583679],"type":"Point"}
}