{
  "type": "Feature",
  "properties": {
    "iso:country":"ES",
    "sg:address":"Calle de Calderon, 2",
    "sg:city":"Albolote",
    "sg:orig_category":"Alumbrados",
    "sg:phone":"+34 958 46 66 27",
    "sg:postcode":"18220",
    "sg:province":"Granada",
    "wof:name":"Jimenez Cano Isabel",
    "wof:placetype":"venue"
},
  "geometry": {"coordinates":[-3.6571133137,37.2292633057],"type":"Point"}
}