{
  "type": "Feature",
  "properties": {
    "iso:country":"ES",
    "sg:address":"Calle de San Salvador, 5",
    "sg:city":"Merida",
    "sg:orig_category":"Cajas De Ahorro",
    "sg:phone":"+34 924 31 24 12",
    "sg:postcode":"06800",
    "sg:province":"Badajoz",
    "sg:website":"www.cajaextremadura.es",
    "wof:name":"Caja De Ahorros Y Monte De Piedad De Extremadura",
    "wof:placetype":"venue"
},
  "geometry": {"coordinates":[-6.3475589752,38.9166488647],"type":"Point"}
}