{
  "type": "Feature",
  "properties": {
    "addr:full":"Calle de Candelaria Ruiz Arbol, 55 Zamora Zamora 49017",
    "addr:housenumber":"55",
    "addr:postcode":"49017",
    "addr:street":"Calle De Candelaria Ruiz Arbol",
    "iso:country":"ES",
    "sg:address":"Calle de Candelaria Ruiz Arbol, 55",
    "sg:city":"Zamora",
    "sg:orig_category":"Producci\u00d3n, Venta De Productos De Agricultura Biol\u00d3gica",
    "sg:phone":"+34 980 52 63 04",
    "sg:postcode":"49017",
    "sg:province":"Zamora",
    "wof:name":"Comunidad De Bienes Hermanos Herrero Serrano",
    "wof:placetype":"venue"
},
  "geometry": {"coordinates":[-5.7358474731,41.5047302246],"type":"Point"}
}