{
  "type": "Feature",
  "properties": {
    "addr:full":"Carrer de Nena Casas, 66 Barcelona Barcelona 08017",
    "addr:housenumber":"66",
    "addr:postcode":"08017",
    "addr:street":"Carrer De Nena Casas",
    "iso:country":"ES",
    "sg:address":"Carrer de Nena Casas, 66",
    "sg:city":"Barcelona",
    "sg:orig_category":"Asesor\u00cdas Y Estudios Financieros",
    "sg:phone":"+34 932 04 22 85",
    "sg:postcode":"08017",
    "sg:province":"Barcelona",
    "wof:name":"Lopez Beiztegui Anastasio",
    "wof:placetype":"venue"
},
  "geometry": {"coordinates":[2.1304309368,41.396522522],"type":"Point"}
}