{
  "type": "Feature",
  "properties": {
    "addr:full":"Calle de Extremadura, 9 Orihuela Alicante 03300",
    "addr:housenumber":"9",
    "addr:postcode":"03300",
    "addr:street":"Calle De Extremadura",
    "iso:country":"ES",
    "sg:address":"Calle de Extremadura, 9",
    "sg:city":"Orihuela",
    "sg:orig_category":"Asesor\u00cda Sobre Comunicaci\u00d3n De Empresas",
    "sg:phone":"+34 966 74 00 67",
    "sg:postcode":"03300",
    "sg:province":"Alicante",
    "wof:name":"Factio S. L.",
    "wof:placetype":"venue"
},
  "geometry": {"coordinates":[-0.9462870955,38.0793304443],"type":"Point"}
}