{
  "type": "Feature",
  "properties": {
    "iso:country":"ES",
    "sg:address":"Avda San Francisco Javier, 22",
    "sg:city":"Sevilla",
    "sg:orig_category":"Peluquer\u00cdas, Peluquer\u00cda Mixta",
    "sg:phone":"+34 954 92 40 97",
    "sg:postcode":"41018",
    "sg:province":"Sevilla",
    "wof:name":"Linea De Estilismo S.l.",
    "wof:placetype":"venue"
},
  "geometry": {"coordinates":[-5.974960804,37.3787727356],"type":"Point"}
}