{
  "type": "Feature",
  "properties": {
    "iso:country":"ES",
    "sg:address":"Calle de Rafael Beca Mateos, 52",
    "sg:city":"Sevilla",
    "sg:orig_category":"Fabricaci\u00d3n De Juguetes Autom\u00c1ticos",
    "sg:phone":"+34 954 25 62 34",
    "sg:postcode":"41007",
    "sg:province":"Sevilla",
    "wof:name":"Automaticos Orenes S. L.",
    "wof:placetype":"venue"
},
  "geometry": {"coordinates":[-5.9503455162,37.3926353455],"type":"Point"}
}