{
  "type": "Feature",
  "properties": {
    "addr:full":"Calle de Dolores Montalbo, 6 Lora Rio Sevilla 41440",
    "addr:housenumber":"6",
    "addr:postcode":"41440",
    "addr:street":"Calle De Dolores Montalbo;Rio Sevilla",
    "iso:country":"ES",
    "sg:address":"Calle de Dolores Montalbo, 6",
    "sg:city":"Lora Rio",
    "sg:orig_category":"Asesor\u00cda De Formaci\u00d3n Y Gesti\u00d3n De Personal",
    "sg:phone":"+34 955 80 10 36",
    "sg:postcode":"41440",
    "sg:province":"Sevilla",
    "wof:name":"Aselora S.c.",
    "wof:placetype":"venue"
},
  "geometry": {"coordinates":[-5.5298309326,37.6550636292],"type":"Point"}
}