{
  "type": "Feature",
  "properties": {
    "addr:full":"Calle de San Ramon, 34 Barbastro Huesca 22300",
    "addr:housenumber":"34",
    "addr:postcode":"22300",
    "addr:street":"Calle De San Ramon",
    "iso:country":"ES",
    "sg:address":"Calle de San Ramon, 34",
    "sg:city":"Barbastro",
    "sg:orig_category":"Talleres: Ropa A Medida",
    "sg:phone":"+34 974 31 08 83",
    "sg:postcode":"22300",
    "sg:province":"Huesca",
    "wof:name":"Gibanel Gracia Antonio",
    "wof:placetype":"venue"
},
  "geometry": {"coordinates":[0.1247749999,42.0356140137],"type":"Point"}
}