{
  "type": "Feature",
  "properties": {
    "addr:full":"Barr Casar, S/n Casar Cantabria 39591",
    "addr:housenumber":"s / n",
    "addr:postcode":"39591",
    "iso:country":"ES",
    "sg:address":"Barr Casar, S/n",
    "sg:city":"Casar",
    "sg:orig_category":"Casas Con Estructura De Madera",
    "sg:phone":"+34 942 70 40 78",
    "sg:postcode":"39591",
    "sg:province":"Cantabria",
    "sg:website":"www.maderhouse.com",
    "wof:name":"Casas Maderhouse S.l.",
    "wof:placetype":"venue"
},
  "geometry": {"coordinates":[-4.1747808456,43.3386764526],"type":"Point"}
}