{
  "type": "Feature",
  "properties": {
    "addr:full":"Carrer de Manuel Moreno, 57 Vilassar Dalt Barcelona 08339",
    "addr:housenumber":"57",
    "addr:postcode":"08339",
    "addr:street":"Carrer De Manuel Moreno;Dalt Barcelona",
    "iso:country":"ES",
    "sg:address":"Carrer de Manuel Moreno, 57",
    "sg:city":"Vilassar Dalt",
    "sg:orig_category":"Grabados",
    "sg:phone":"+34 937 53 30 61",
    "sg:postcode":"08339",
    "sg:province":"Barcelona",
    "wof:name":"Graba Styl S. A.",
    "wof:placetype":"venue"
},
  "geometry": {"coordinates":[2.3615748882,41.5145187378],"type":"Point"}
}