{
  "type": "Feature",
  "properties": {
    "iso:country":"ES",
    "sg:address":"Calle de Arenal, 59",
    "sg:city":"Palacios Y Villafranca",
    "sg:orig_category":"Carnicer\u00cdas, Carnicer\u00cdas",
    "sg:phone":"+34 955 81 49 41",
    "sg:postcode":"41720",
    "sg:province":"Sevilla",
    "wof:name":"Parejo Gomez Consolacion",
    "wof:placetype":"venue"
},
  "geometry": {"coordinates":[-5.9279932976,37.1620597839],"type":"Point"}
}