{
  "type": "Feature",
  "properties": {
    "iso:country":"ES",
    "sg:address":"Calle de Molina, 12",
    "sg:city":"Astorga",
    "sg:orig_category":"Carb\u00d3n, Carb\u00d3n De Madera (al Por Mayor)",
    "sg:phone":"+34 987 61 64 30",
    "sg:postcode":"24700",
    "sg:province":"Le\u00f3n",
    "wof:name":"Martinez Alija Joaquin",
    "wof:placetype":"venue"
},
  "geometry": {"coordinates":[-6.0605139732,42.4613761902],"type":"Point"}
}