{
  "type": "Feature",
  "properties": {
    "iso:country":"ES",
    "sg:address":"Calle de Salvador Y Merino, S/n",
    "sg:city":"Coru\u00d1a",
    "sg:orig_category":"Alquiler De Gr\u00daas",
    "sg:phone":"+34 981 23 87 96",
    "sg:postcode":"15008",
    "sg:province":"La Coru\u00f1a",
    "wof:name":"Fari\u00f1a Ponte Jaime",
    "wof:placetype":"venue"
},
  "geometry": {"coordinates":[-8.4080896378,43.3507766724],"type":"Point"}
}