{
  "type": "Feature",
  "properties": {
    "iso:country":"ES",
    "sg:address":"Pase Platanos (los), 31",
    "sg:city":"Riopar",
    "sg:orig_category":"Supermercados Y Hipermercados",
    "sg:phone":"+34 967 43 59 22",
    "sg:postcode":"02450",
    "sg:province":"Albacete",
    "wof:name":"Maria Jose Ballesta Sanchez S.l.u",
    "wof:placetype":"venue"
},
  "geometry": {"coordinates":[-2.420331955,38.4986152649],"type":"Point"}
}