{
  "type": "Feature",
  "properties": {
    "addr:full":"Calle de Plata, 66 Valladolid Valladolid 47012",
    "addr:housenumber":"66",
    "addr:postcode":"47012",
    "addr:street":"Calle De Plata",
    "iso:country":"ES",
    "sg:address":"Calle de Plata, 66",
    "sg:city":"Valladolid",
    "sg:orig_category":"Almacenes Frigor\u00cdficos",
    "sg:phone":"+34 983 30 94 44",
    "sg:postcode":"47012",
    "sg:province":"Valladolid",
    "wof:name":"Frigorificos Callesa S.l.",
    "wof:placetype":"venue"
},
  "geometry": {"coordinates":[-4.7092847824,41.6162414551],"type":"Point"}
}