{
  "type": "Feature",
  "properties": {
    "iso:country":"ES",
    "sg:address":"Avda General Marva, 12",
    "sg:city":"Alacant",
    "sg:orig_category":"Sindicatos De Trabajadores",
    "sg:phone":"+34 965 21 99 51",
    "sg:postcode":"03004",
    "sg:province":"Alicante",
    "wof:name":"Agrupacion Sindical Provincial De Auto-escuelas",
    "wof:placetype":"venue"
},
  "geometry": {"coordinates":[-0.4913724959,38.3472061157],"type":"Point"}
}