{
  "type": "Feature",
  "properties": {
    "addr:full":"Calle de Nicolas Estevanez, 33 Palmas De Gran Canaria Las Palmas 35007",
    "addr:housenumber":"33",
    "addr:postcode":"35007",
    "addr:street":"Calle De Nicolas Estevanez",
    "iso:country":"ES",
    "sg:address":"Calle de Nicolas Estevanez, 33",
    "sg:city":"Palmas De Gran Canaria",
    "sg:orig_category":"Servicios De Telecomunicaciones",
    "sg:phone":"+34 928 22 89 33",
    "sg:postcode":"35007",
    "sg:province":"Las Palmas",
    "wof:name":"Aviles Guzman Maria Soledad",
    "wof:placetype":"venue"
},
  "geometry": {"coordinates":[-15.4341049194,28.1393795013],"type":"Point"}
}