{
  "type": "Feature",
  "properties": {
    "addr:full":"Av Joan Xxiii, S/n Gava Barcelona 08850",
    "addr:housenumber":"s / n",
    "addr:postcode":"08850",
    "addr:street":"Av Joan Xxiii",
    "iso:country":"ES",
    "sg:address":"Av Joan Xxiii, S/n",
    "sg:city":"Gava",
    "sg:orig_category":"Mercer\u00cda, Lencer\u00cda (al Por Menor)",
    "sg:phone":"+34 936 38 31 17",
    "sg:postcode":"08850",
    "sg:province":"Barcelona",
    "wof:name":"Damas Illana Paula",
    "wof:placetype":"venue"
},
  "geometry": {"coordinates":[2.0024399757,41.3095245361],"type":"Point"}
}