{
  "type": "Feature",
  "properties": {
    "addr:full":"Ctra. Montehermoso, S/n Carcaboso C\u00e1ceres 10670",
    "addr:housenumber":"s / n",
    "addr:postcode":"10670",
    "addr:street":"Ctra. Montehermoso;Ca\u0301Ceres",
    "iso:country":"ES",
    "sg:address":"Ctra. Montehermoso, S/n",
    "sg:city":"Carcaboso",
    "sg:orig_category":"Confiter\u00cda, Galletas Y Pastas, Chocolater\u00cda (al Por Mayor)",
    "sg:phone":"+34 927 40 23 96",
    "sg:postcode":"10670",
    "sg:province":"C\u00e1ceres",
    "wof:name":"Hermanos Moreno Albarran S. A.",
    "wof:placetype":"venue"
},
  "geometry": {"coordinates":[-6.2117791176,40.0478935242],"type":"Point"}
}