{
  "type": "Feature",
  "properties": {
    "addr:full":"Avda Jose Marti, 10 Santa Cruz De Tenerife Santa Cruz De Tenerife 38160",
    "addr:housenumber":"10",
    "addr:postcode":"38160",
    "addr:street":"Avda Jose Marti",
    "iso:country":"ES",
    "sg:address":"Avda Jose Marti, 10",
    "sg:city":"Santa Cruz De Tenerife",
    "sg:orig_category":"Empresas De Portes Y Mensajer\u00cda",
    "sg:phone":"+34 922 59 77 20",
    "sg:postcode":"38160",
    "sg:province":"Santa Cruz De Tenerife",
    "wof:name":"Milan Express S.a.",
    "wof:placetype":"venue"
},
  "geometry": {"coordinates":[-16.23595047,28.4893302917],"type":"Point"}
}