{
  "type": "Feature",
  "properties": {
    "iso:country":"ES",
    "sg:address":"Calle de Almendros Los, 16",
    "sg:city":"Alhaurin Torre",
    "sg:orig_category":"Electricidad, Electr\u00d3nica: Suministros (al Por Menor)",
    "sg:phone":"+34 952 96 35 05",
    "sg:postcode":"29130",
    "sg:province":"M\u00e1laga",
    "wof:name":"Nanpe Electronica S.l.",
    "wof:placetype":"venue"
},
  "geometry": {"coordinates":[-4.6138930321,36.7313957214],"type":"Point"}
}