{
  "type": "Feature",
  "properties": {
    "iso:country":"ES",
    "sg:address":"Carr Martin Plaja, 31",
    "sg:city":"Eliana",
    "sg:orig_category":"M\u00c9dicos: Medicina General Orientada A La Homeopat\u00cda",
    "sg:phone":"+34 962 74 43 15",
    "sg:postcode":"46183",
    "sg:province":"Valencia",
    "wof:name":"Anton Anton Concepcion",
    "wof:placetype":"venue"
},
  "geometry": {"coordinates":[-0.5323929787,39.5644683838],"type":"Point"}
}