{
  "type": "Feature",
  "properties": {
    "addr:full":"Calle de Alberto Aguilera, 7 Madrid Madrid 28015",
    "addr:housenumber":"7",
    "addr:postcode":"madrid;28015",
    "addr:street":"Calle De Alberto Aguilera",
    "iso:country":"ES",
    "sg:address":"Calle de Alberto Aguilera, 7",
    "sg:city":"Madrid",
    "sg:orig_category":"Ingenier\u00cda, Centros De Estudios (diversos)",
    "sg:phone":"+34 914 48 10 68",
    "sg:postcode":"28015",
    "sg:province":"Madrid",
    "wof:name":"Tecnicas Reunidas S.a.",
    "wof:placetype":"venue"
},
  "geometry": {"coordinates":[-3.7080640793,40.4297065735],"type":"Point"}
}