{
  "type": "Feature",
  "properties": {
    "iso:country":"ES",
    "sg:address":"Calle de Glorio (del), 3",
    "sg:city":"Colmenar Viejo",
    "sg:orig_category":"Ropa Para Se\u00d1oras (al Por Menor)",
    "sg:phone":"+34 918 48 67 71",
    "sg:postcode":"28770",
    "sg:province":"Madrid",
    "wof:name":"Gonzalez Baeza Maria Luisa",
    "wof:placetype":"venue"
},
  "geometry": {"coordinates":[-3.7645919323,40.6594161987],"type":"Point"}
}