{
  "type": "Feature",
  "properties": {
    "addr:full":"Calle de Ciudad De Riga, 2 Alacant Alicante 03005",
    "addr:housenumber":"2",
    "addr:postcode":"03005",
    "addr:street":"Calle De Ciudad De Riga",
    "iso:country":"ES",
    "sg:address":"Calle de Ciudad De Riga, 2",
    "sg:city":"Alacant",
    "sg:orig_category":"Laboratorios Y Cl\u00cdnicas Veterinarias",
    "sg:phone":"+34 966 35 14 74",
    "sg:postcode":"03005",
    "sg:province":"Alicante",
    "sg:website":"www.cvedral.onored.com",
    "wof:name":"Cv El Drac C.b.",
    "wof:placetype":"venue"
},
  "geometry": {"coordinates":[-0.5053070784,38.3591842651],"type":"Point"}
}