{
  "type": "Feature",
  "properties": {
    "addr:full":"Calle de Libreros, 40 Alcala Henares Madrid 28801",
    "addr:housenumber":"40",
    "addr:postcode":"28801",
    "addr:street":"Calle De Libreros",
    "iso:country":"ES",
    "sg:address":"Calle de Libreros, 40",
    "sg:city":"Alcala Henares",
    "sg:orig_category":"Institutos De Belleza",
    "sg:phone":"+34 918 82 03 77",
    "sg:postcode":"28801",
    "sg:province":"Madrid",
    "wof:name":"Corte Gonzalez Jose Luis",
    "wof:placetype":"venue"
},
  "geometry": {"coordinates":[-3.361905098,40.484577179],"type":"Point"}
}