{
  "type": "Feature",
  "properties": {
    "iso:country":"ES",
    "sg:address":"Calle de Moncada, 118",
    "sg:city":"Madrid",
    "sg:orig_category":"Peluquer\u00cdas, Peluquer\u00cda Mixta",
    "sg:phone":"+34 917 98 74 23",
    "sg:postcode":"28021",
    "sg:province":"Madrid",
    "wof:name":"Aznarez Rodriguez Jose",
    "wof:placetype":"venue"
},
  "geometry": {"coordinates":[-3.6920280457,40.3400001526],"type":"Point"}
}