{
  "type": "Feature",
  "properties": {
    "iso:country":"ES",
    "sg:address":"Calle de Arana, 7",
    "sg:city":"Vitoria-gasteiz",
    "sg:orig_category":"Psic\u00d3logos",
    "sg:phone":"+34 945 27 60 99",
    "sg:postcode":"01002",
    "sg:province":"\u00c1lava",
    "wof:name":"Abal Ciordia Jose Miguel",
    "wof:placetype":"venue"
},
  "geometry": {"coordinates":[-2.667517,42.850376],"type":"Point"}
}