{
  "type": "Feature",
  "properties": {
    "iso:country":"ES",
    "sg:address":"Carrer de Born, 36",
    "sg:city":"Manresa",
    "sg:orig_category":"Bancos",
    "sg:phone":"+34 938 72 18 11",
    "sg:postcode":"08241",
    "sg:province":"Barcelona",
    "wof:name":"Bt Espa\u00d1a Compa\u00d1ia De Servicios Globales De Telecomunicaciones S.a.u.",
    "wof:placetype":"venue"
},
  "geometry": {"coordinates":[1.8243060112,41.724773407],"type":"Point"}
}