{
  "type": "Feature",
  "properties": {
    "iso:country":"ES",
    "sg:address":"Carr Coll I Pujol, 101",
    "sg:city":"Badalona",
    "sg:orig_category":"Abogados",
    "sg:phone":"+34 933 99 54 96",
    "sg:postcode":"08912",
    "sg:province":"Barcelona",
    "wof:name":"Hernandez Garcia Francisco",
    "wof:placetype":"venue"
},
  "geometry": {"coordinates":[2.239948988,41.4505577087],"type":"Point"}
}