{
  "type": "Feature",
  "properties": {
    "iso:country":"ES",
    "sg:address":"Carrer de Raval Santa Coloma, 18",
    "sg:city":"Santa Coloma De Queralt",
    "sg:orig_category":"Peluqueros: De Se\u00d1oras",
    "sg:phone":"+34 977 88 10 06",
    "sg:postcode":"43420",
    "sg:province":"Tarragona",
    "wof:name":"Roca Corbella Luis",
    "wof:placetype":"venue"
},
  "geometry": {"coordinates":[1.3828719854,41.5321273804],"type":"Point"}
}