{
  "type": "Feature",
  "properties": {
    "addr:full":"Plaz San Luis Gonzaga, 4 Bre\u00d1as Las Palmas 35570",
    "addr:housenumber":"4",
    "addr:postcode":"35570",
    "addr:street":"Plaz San Luis Gonzaga;Las Palmas",
    "iso:country":"ES",
    "sg:address":"Plaz San Luis Gonzaga, 4",
    "sg:city":"Bre\u00d1as",
    "sg:orig_category":"Asociaciones, Organismos Culturales Y Socioeducativos",
    "sg:phone":"+34 928 83 04 43",
    "sg:postcode":"35570",
    "sg:province":"Las Palmas",
    "wof:name":"Ayuntamiento De Yaiza",
    "wof:placetype":"venue"
},
  "geometry": {"coordinates":[-15.4300060272,28.1248226166],"type":"Point"}
}