{
  "type": "Feature",
  "properties": {
    "iso:country":"ES",
    "sg:address":"Calle de Manuel Viola, 2",
    "sg:city":"Zaragoza",
    "sg:orig_category":"Peluqueros: De Se\u00d1oras",
    "sg:phone":"+34 976 47 66 45",
    "sg:postcode":"50014",
    "sg:province":"Zaragoza",
    "wof:name":"Martinez Lauber Sandra Gloria",
    "wof:placetype":"venue"
},
  "geometry": {"coordinates":[-0.8563690186,41.6590690613],"type":"Point"}
}