{
  "type": "Feature",
  "properties": {
    "addr:full":"Sant Llorenc, 39 Alaior Islas Baleares 07730",
    "addr:housenumber":"39",
    "addr:postcode":"07730",
    "addr:street":"Llorenc",
    "iso:country":"ES",
    "sg:address":"Sant Llorenc, 39",
    "sg:city":"Alaior",
    "sg:orig_category":"Carb\u00d3n, Carb\u00d3n De Madera (al Por Mayor)",
    "sg:phone":"+34 971 37 18 92",
    "sg:postcode":"07730",
    "sg:province":"Islas Baleares",
    "wof:name":"Hernandez Tuduri Marcelino",
    "wof:placetype":"venue"
},
  "geometry": {"coordinates":[4.1399030685,39.9369621277],"type":"Point"}
}