{
  "type": "Feature",
  "properties": {
    "addr:full":"Calle de O'donnell, 4 Madrid Madrid 28009",
    "addr:housenumber":"4",
    "addr:postcode":"28009",
    "addr:street":"Calle De O'Donnell",
    "iso:country":"ES",
    "sg:address":"Calle de O'donnell, 4",
    "sg:city":"Madrid",
    "sg:orig_category":"Inversiones",
    "sg:phone":"+34 917 81 42 20",
    "sg:postcode":"28009",
    "sg:province":"Madrid",
    "wof:name":"Inversiones Giromar S.l",
    "wof:placetype":"venue"
},
  "geometry": {"coordinates":[-3.6798892021,40.4216423035],"type":"Point"}
}