{
  "type": "Feature",
  "properties": {
    "iso:country":"ES",
    "sg:address":"Plaz Baco, 4",
    "sg:city":"Selaya",
    "sg:orig_category":"Sociedades, Compa\u00d1\u00cdas Aseguradoras",
    "sg:phone":"+34 942 59 19 05",
    "sg:postcode":"39696",
    "sg:province":"Cantabria",
    "wof:name":"Mazorra Y Gutierrez S.l.",
    "wof:placetype":"venue"
},
  "geometry": {"coordinates":[-3.8065640926,43.2147674561],"type":"Point"}
}