{
  "type": "Feature",
  "properties": {
    "addr:full":"Avda Granada, Km. 0040,0 Jaen Ja\u00e9n 23001",
    "addr:postcode":"23001",
    "addr:street":"Avda Granada Km. 0040,0 Jaen Jae\u0301N",
    "iso:country":"ES",
    "sg:address":"Avda Granada, Km. 0040,0",
    "sg:city":"Jaen",
    "sg:orig_category":"Freidur\u00cdas: Equipos Y Suministros",
    "sg:phone":"+34 953 23 94 68",
    "sg:postcode":"23001",
    "sg:province":"Ja\u00e9n",
    "wof:name":"Patatas Fritas Santo Reino S.l",
    "wof:placetype":"venue"
},
  "geometry": {"coordinates":[-3.7841889858,37.768699646],"type":"Point"}
}