{
  "type": "Feature",
  "properties": {
    "addr:full":"Calle de Duque De Alba, 44 Argamasilla Alba Ciudad Real 13710",
    "addr:housenumber":"44",
    "addr:postcode":"alba;13710",
    "addr:street":"Calle De Duque De Alba",
    "iso:country":"ES",
    "sg:address":"Calle de Duque De Alba, 44",
    "sg:city":"Argamasilla Alba",
    "sg:orig_category":"Arreglo, Reparaci\u00d3n, Piezas Sueltas De Televisi\u00d3n, V\u00cddeo, Hi",
    "sg:phone":"+34 926 52 20 43",
    "sg:postcode":"13710",
    "sg:province":"Ciudad Real",
    "wof:name":"Lopez De La Oliva Serrano Maria",
    "wof:placetype":"venue"
},
  "geometry": {"coordinates":[-3.0932917595,39.1314468384],"type":"Point"}
}