{
  "type": "Feature",
  "properties": {
    "addr:full":"Avda Primero De Mayo, 34 Valencia Valencia 46017",
    "addr:housenumber":"34",
    "addr:postcode":"46017",
    "addr:street":"Avda Primero De Mayo",
    "iso:country":"ES",
    "sg:address":"Avda Primero De Mayo, 34",
    "sg:city":"Valencia",
    "sg:orig_category":"Carnicer\u00cdas, Carnicer\u00cdas",
    "sg:phone":"+34 963 57 44 20",
    "sg:postcode":"46017",
    "sg:province":"Valencia",
    "wof:name":"Albarracin Varea Pascual",
    "wof:placetype":"venue"
},
  "geometry": {"coordinates":[-0.3896116018,39.4493103027],"type":"Point"}
}