{
  "type": "Feature",
  "properties": {
    "addr:full":"Crta Vinaroz-vitoria, Km. 0021,4 Jana Castell\u00f3n 12340",
    "addr:postcode":"12340",
    "addr:street":"Crta Vinaroz-Vitoria Km. 0021,4 Jana Castello\u0301N",
    "iso:country":"ES",
    "sg:address":"Crta Vinaroz-vitoria, Km. 0021,4",
    "sg:city":"Jana",
    "sg:orig_category":"Distribuci\u00d3n De Petr\u00d3leo Y Derivados",
    "sg:phone":"+34 964 49 70 64",
    "sg:postcode":"12340",
    "sg:province":"Castell\u00f3n",
    "wof:name":"Estacion De Servicios Balmapa S.l.",
    "wof:placetype":"venue"
},
  "geometry": {"coordinates":[0.2524600029,40.5128555298],"type":"Point"}
}