{
  "type": "Feature",
  "properties": {
    "addr:full":"A. Gmez Cuevas, 6 Casariche Sevilla 41580",
    "addr:housenumber":"6",
    "addr:postcode":"41580",
    "addr:street":"Cuevas",
    "iso:country":"ES",
    "sg:address":"A. Gmez Cuevas, 6",
    "sg:city":"Casariche",
    "sg:orig_category":"Fotograf\u00cda Y Cine: Aparatos, Pel\u00cdculas Y Accesorios (fabricaci\u00d3n, Al Por Mayor)",
    "sg:phone":"+34 954 01 10 20",
    "sg:postcode":"41580",
    "sg:province":"Sevilla",
    "wof:name":"Mendoza Tenor Pedro",
    "wof:placetype":"venue"
},
  "geometry": {"coordinates":[-4.7643399239,37.2960853577],"type":"Point"}
}