{
  "type": "Feature",
  "properties": {
    "addr:full":"Ptda Altabix, S/n Elche Alicante 03291",
    "addr:housenumber":"s / n",
    "addr:postcode":"03291",
    "addr:street":"Ptda Altabix",
    "iso:country":"ES",
    "sg:address":"Ptda Altabix, S/n",
    "sg:city":"Elche",
    "sg:orig_category":"Plomeros",
    "sg:phone":"+34 965 42 68 94",
    "sg:postcode":"03291",
    "sg:province":"Alicante",
    "wof:name":"Fontaneria La Galia S.l.l.",
    "wof:placetype":"venue"
},
  "geometry": {"coordinates":[-0.6765189767,38.2994346619],"type":"Point"}
}