{
  "type": "Feature",
  "properties": {
    "addr:full":"Carrer de Rossello, 224 Barcelona Barcelona 08008",
    "addr:housenumber":"224",
    "addr:postcode":"08008",
    "addr:street":"Carrer De Rossello",
    "iso:country":"ES",
    "sg:address":"Carrer de Rossello, 224",
    "sg:city":"Barcelona",
    "sg:orig_category":"Centros Empresariales",
    "sg:phone":"+34 934 67 20 21",
    "sg:postcode":"08008",
    "sg:province":"Barcelona",
    "wof:name":"Fergestion S.l.",
    "wof:placetype":"venue"
},
  "geometry": {"coordinates":[2.1596999168,41.3949127197],"type":"Point"}
}