{
  "type": "Feature",
  "properties": {
    "iso:country":"ES",
    "sg:address":"Calle de Matadero, 2",
    "sg:city":"Zaragoza",
    "sg:orig_category":"Inmobiliaria (agencias)",
    "sg:phone":"+34 976 48 02 90",
    "sg:postcode":"50013",
    "sg:province":"Zaragoza",
    "wof:name":"Servicios Administrativos Hibersis S.l.",
    "wof:placetype":"venue"
},
  "geometry": {"coordinates":[-0.8707410097,41.6445541382],"type":"Point"}
}