{
  "type": "Feature",
  "properties": {
    "addr:full":"Carrer de Raval Del Torrent, S/n Cubelles Barcelona 08880",
    "addr:housenumber":"s / n",
    "addr:postcode":"08880",
    "addr:street":"Carrer De Raval Del Torrent",
    "iso:country":"ES",
    "sg:address":"Carrer de Raval Del Torrent, S/n",
    "sg:city":"Cubelles",
    "sg:orig_category":"Empresarios",
    "sg:phone":"+34 938 95 38 24",
    "sg:postcode":"08880",
    "sg:province":"Barcelona",
    "wof:name":"Ajuntament De Cubelles",
    "wof:placetype":"venue"
},
  "geometry": {"coordinates":[1.669899106,41.2081184387],"type":"Point"}
}