{
  "type": "Feature",
  "properties": {
    "addr:full":"Calle de Enmedio, 1 Ciudad Real Ciudad Real 13002",
    "addr:housenumber":"1",
    "addr:postcode":"13002",
    "addr:street":"Calle De Enmedio",
    "iso:country":"ES",
    "sg:address":"Calle de Enmedio, 1",
    "sg:city":"Ciudad Real",
    "sg:orig_category":"Ense\u00d1anza, Formaci\u00d3n Profesional: Aprendizaje",
    "sg:phone":"+34 926 25 44 00",
    "sg:postcode":"13002",
    "sg:province":"Ciudad Real",
    "sg:website":"www.fecmes.es}}",
    "wof:name":"Federacion Empresarial De Castilla La Mancha De Economia Social",
    "wof:placetype":"venue"
},
  "geometry": {"coordinates":[-3.9329099655,38.9855117798],"type":"Point"}
}