{
  "type": "Feature",
  "properties": {
    "addr:full":"Calle de Cochabamba, 5 Palmas De Gran Canaria Las Palmas 35008",
    "addr:housenumber":"5",
    "addr:postcode":"35008",
    "addr:street":"Calle De Cochabamba",
    "iso:country":"ES",
    "sg:address":"Calle de Cochabamba, 5",
    "sg:city":"Palmas De Gran Canaria",
    "sg:orig_category":"Negocio De Materiales De Construcci\u00d3n",
    "sg:phone":"+34 928 46 92 26",
    "sg:postcode":"35008",
    "sg:province":"Las Palmas",
    "wof:name":"Medifonsa S.a.",
    "wof:placetype":"venue"
},
  "geometry": {"coordinates":[-15.4184579849,28.1543674469],"type":"Point"}
}