{
  "type": "Feature",
  "properties": {
    "iso:country":"ES",
    "sg:address":"Centro Comercial Aqualon, S/n",
    "sg:city":"Huelva",
    "sg:orig_category":"Complementos De Vestir (al Por Menor)",
    "sg:phone":"+34 959 35 91 02",
    "sg:postcode":"21001",
    "sg:province":"Huelva",
    "wof:name":"Fetiche Complements S.l.",
    "wof:placetype":"venue"
},
  "geometry": {"coordinates":[-6.9495940208,37.256313324],"type":"Point"}
}