{
  "type": "Feature",
  "properties": {
    "addr:full":"Calle de Pintor Agrasot, 10 Alacant Alicante 03001",
    "addr:housenumber":"10",
    "addr:postcode":"03001",
    "addr:street":"Calle De Pintor Agrasot",
    "iso:country":"ES",
    "sg:address":"Calle de Pintor Agrasot, 10",
    "sg:city":"Alacant",
    "sg:orig_category":"Bisuter\u00cda, Joyer\u00cda, Relojer\u00cda (al Por Menor)",
    "sg:phone":"+34 965 23 06 01",
    "sg:postcode":"03001",
    "sg:province":"Alicante",
    "sg:website":"www.tous.es",
    "wof:name":"Tous Joyeros Murcia S.l.",
    "wof:placetype":"venue"
},
  "geometry": {"coordinates":[-0.4887619913,38.3441848755],"type":"Point"}
}