{
  "type": "Feature",
  "properties": {
    "addr:full":"Avda Galicia De, 14 Oviedo Asturias 33005",
    "addr:housenumber":"14",
    "addr:postcode":"33005",
    "addr:street":"Avda Galicia De",
    "iso:country":"ES",
    "sg:address":"Avda Galicia De, 14",
    "sg:city":"Oviedo",
    "sg:orig_category":"Abogados",
    "sg:phone":"+34 985 27 33 27",
    "sg:postcode":"33005",
    "sg:province":"Asturias",
    "wof:name":"Menendez De Llano Lizana Javier",
    "wof:placetype":"venue"
},
  "geometry": {"coordinates":[-5.8554258347,43.3613471985],"type":"Point"}
}