{
  "type": "Feature",
  "properties": {
    "iso:country":"ES",
    "sg:address":"Calle de Salvador Dali, 10",
    "sg:city":"Zubia",
    "sg:orig_category":"Persianas Interiores, Exteriores",
    "sg:phone":"+34 958 59 05 29",
    "sg:postcode":"18140",
    "sg:province":"Granada",
    "wof:name":"Gallardo Gamez Bernardo",
    "wof:placetype":"venue"
},
  "geometry": {"coordinates":[-3.5828120708,37.1193809509],"type":"Point"}
}