{
  "type": "Feature",
  "properties": {
    "iso:country":"ES",
    "sg:address":"Calle de Marcelo Usera, 102",
    "sg:city":"Madrid",
    "sg:orig_category":"Asesor\u00cda Sobre Comunicaci\u00d3n De Empresas",
    "sg:phone":"+34 915 00 23 79",
    "sg:postcode":"28026",
    "sg:province":"Madrid",
    "wof:name":"Universo Asesoria De Empresas S.l.",
    "wof:placetype":"venue"
},
  "geometry": {"coordinates":[-3.708329916,40.3856239319],"type":"Point"}
}