{
  "type": "Feature",
  "properties": {
    "iso:country":"ES",
    "sg:address":"Avda Madrid, S/n",
    "sg:city":"Sotillo Adrada",
    "sg:orig_category":"Supermercados Y Hipermercados",
    "sg:phone":"+34 918 60 12 08",
    "sg:postcode":"05420",
    "sg:province":"\u00c1vila",
    "wof:name":"Zarzalejo Sanchez Luis",
    "wof:placetype":"venue"
},
  "geometry": {"coordinates":[-4.5853819847,40.2941131592],"type":"Point"}
}