{
  "type": "Feature",
  "properties": {
    "addr:full":"Poli Industrial C/t, S/n Rozas De Madrid Madrid 28230",
    "addr:housenumber":"s",
    "addr:postcode":"28230",
    "addr:street":"/ N Rozas",
    "iso:country":"ES",
    "sg:address":"Poli Industrial C/t, S/n",
    "sg:city":"Rozas De Madrid",
    "sg:orig_category":"Dibujo",
    "sg:phone":"+34 915 11 00 44",
    "sg:postcode":"28230",
    "sg:province":"Madrid",
    "wof:name":"Duran Consulting S.l.",
    "wof:placetype":"venue"
},
  "geometry": {"coordinates":[-3.8913800716,40.5247497559],"type":"Point"}
}