{
  "type": "Feature",
  "properties": {
    "addr:full":"Calle de Daniel Pereda, 7 Santurtzi Vizcaya 48980",
    "addr:housenumber":"7",
    "addr:postcode":"48980",
    "addr:street":"Calle De Daniel Pereda",
    "iso:country":"ES",
    "sg:address":"Calle de Daniel Pereda, 7",
    "sg:city":"Santurtzi",
    "sg:orig_category":"Mec\u00c1nico Del Autom\u00d3vil",
    "sg:phone":"+34 944 61 01 51",
    "sg:postcode":"48980",
    "sg:province":"Vizcaya",
    "wof:name":"Antu\u00f1ano Ortiz Pedro",
    "wof:placetype":"venue"
},
  "geometry": {"coordinates":[-3.0359404087,43.3230209351],"type":"Point"}
}