{
  "type": "Feature",
  "properties": {
    "iso:country":"ES",
    "sg:address":"Pase Barron -cegonyer-, 10",
    "sg:city":"Fraga",
    "sg:orig_category":"Farmacias",
    "sg:phone":"+34 974 47 24 94",
    "sg:postcode":"22520",
    "sg:province":"Huesca",
    "wof:name":"Masot Alcaine Jaime",
    "wof:placetype":"venue"
},
  "geometry": {"coordinates":[0.3503620028,41.5206718445],"type":"Point"}
}