{
  "type": "Feature",
  "properties": {
    "iso:country":"ES",
    "sg:address":"Pase Cementerio, 24",
    "sg:city":"Talavera Reina",
    "sg:orig_category":"Molduras, Junquillos, Listones Y Molduras Perforadas",
    "sg:phone":"+34 925 81 90 36",
    "sg:postcode":"45600",
    "sg:province":"Toledo",
    "wof:name":"Otero Otero Luis Miguel",
    "wof:placetype":"venue"
},
  "geometry": {"coordinates":[-4.8326292038,39.9584884644],"type":"Point"}
}