{
  "type": "Feature",
  "properties": {
    "iso:country":"ES",
    "sg:address":"Pob Tipico, S/n",
    "sg:city":"Empuriabrava",
    "sg:orig_category":"Molduras, Junquillos, Listones Y Molduras Perforadas",
    "sg:phone":"+34 972 45 52 75",
    "sg:postcode":"17487",
    "sg:province":"Girona",
    "wof:name":"Otero Oton Pablo",
    "wof:placetype":"venue"
},
  "geometry": {"coordinates":[3.1070549488,42.2568092346],"type":"Point"}
}