{
  "type": "Feature",
  "properties": {
    "iso:country":"ES",
    "sg:address":"Carrer de Can Cavalleria, 17",
    "sg:city":"Palma",
    "sg:orig_category":"Aparatos De Iluminaci\u00d3n (al Por Menor)",
    "sg:phone":"+34 971 71 07 75",
    "sg:postcode":"07012",
    "sg:province":"Islas Baleares",
    "wof:name":"Ducha Fresca C.b.",
    "wof:placetype":"venue"
},
  "geometry": {"coordinates":[2.6471590996,39.573299408],"type":"Point"}
}