{
  "type": "Feature",
  "properties": {
    "addr:full":"Cno Morron, 64 Villena Alicante 03400",
    "addr:housenumber":"64",
    "addr:postcode":"03400",
    "addr:street":"Cno Morron",
    "iso:country":"ES",
    "sg:address":"Cno Morron, 64",
    "sg:city":"Villena",
    "sg:orig_category":"Agricultura: Abastecimiento Y Cosechado (negocio)",
    "sg:phone":"+34 965 97 90 84",
    "sg:postcode":"03400",
    "sg:province":"Alicante",
    "wof:name":"De La Torre C.b",
    "wof:placetype":"venue"
},
  "geometry": {"coordinates":[-0.8688759804,38.6403198242],"type":"Point"}
}