{
  "type": "Feature",
  "properties": {
    "addr:full":"Calle de Nueva, 3 Matamala Almazan Soria 42211",
    "addr:housenumber":"3",
    "addr:postcode":"42211",
    "addr:street":"Calle De Nueva",
    "iso:country":"ES",
    "sg:address":"Calle de Nueva, 3",
    "sg:city":"Matamala Almazan",
    "sg:orig_category":"Sanatorios M\u00c9dico",
    "sg:phone":"+34 975 31 24 23",
    "sg:postcode":"42211",
    "sg:province":"Soria",
    "wof:name":"Ayuntamiento De Matamala De Almazan Oficinas",
    "wof:placetype":"venue"
},
  "geometry": {"coordinates":[-2.6149871349,41.4893836975],"type":"Point"}
}