{
  "type": "Feature",
  "properties": {
    "addr:full":"Carrer de Verge De L'esperanca, 8 Crevillent Alicante 03330",
    "addr:housenumber":"8",
    "addr:postcode":"03330",
    "addr:street":"Carrer De Verge De L'Esperanca",
    "iso:country":"ES",
    "sg:address":"Carrer de Verge De L'esperanca, 8",
    "sg:city":"Crevillent",
    "sg:orig_category":"Reposter\u00cdas",
    "sg:phone":"+34 965 40 36 35",
    "sg:postcode":"03330",
    "sg:province":"Alicante",
    "wof:name":"Guilabert Martinez Amelia",
    "wof:placetype":"venue"
},
  "geometry": {"coordinates":[-0.8081560135,38.2460479736],"type":"Point"}
}