{
  "type": "Feature",
  "properties": {
    "addr:full":"Calle de Feria, S/n Montoro C\u00f3rdoba 14600",
    "addr:housenumber":"s / n",
    "addr:postcode":"14600",
    "addr:street":"Calle De Feria;Co\u0301Rdoba",
    "iso:country":"ES",
    "sg:address":"Calle de Feria, S/n",
    "sg:city":"Montoro",
    "sg:orig_category":"Organizaci\u00d3n De Actos, Seminarios Y Congresos",
    "sg:phone":"+34 957 16 07 78",
    "sg:postcode":"14600",
    "sg:province":"C\u00f3rdoba",
    "wof:name":"Jose Carlos Molina E Hijos S.l",
    "wof:placetype":"venue"
},
  "geometry": {"coordinates":[-4.3855910301,38.0223655701],"type":"Point"}
}