{
  "type": "Feature",
  "properties": {
    "iso:country":"ES",
    "sg:address":"Tiburzio Anitua Kalea, 8",
    "sg:city":"Eibar",
    "sg:orig_category":"Reposter\u00cdas",
    "sg:phone":"+34 943 20 42 24",
    "sg:postcode":"20600",
    "sg:province":"Guip\u00f9zcoa",
    "wof:name":"Panaderia Bolintxo S. A.",
    "wof:placetype":"venue"
},
  "geometry": {"coordinates":[-2.48250103,43.1832466125],"type":"Point"}
}