{
  "type": "Feature",
  "properties": {
    "addr:full":"Cmno Cossa, De La, 1 Masarrochos Valencia 46112",
    "addr:housenumber":"1",
    "addr:postcode":"46112",
    "addr:street":"Cmno Cossa De La",
    "iso:country":"ES",
    "sg:address":"Cmno Cossa, De La, 1",
    "sg:city":"Masarrochos",
    "sg:orig_category":"Empresarios Y Productoras De Espect\u00c1culos",
    "sg:phone":"+34 961 30 11 80",
    "sg:postcode":"46112",
    "sg:province":"Valencia",
    "wof:name":"Asociacion Okrana Danza",
    "wof:placetype":"venue"
},
  "geometry": {"coordinates":[-0.3768048882,39.4702377319],"type":"Point"}
}