{
  "type": "Feature",
  "properties": {
    "addr:full":"Calle de Matarrosa, 5 Fuenlabrada Madrid 28947",
    "addr:housenumber":"5",
    "addr:postcode":"28947",
    "addr:street":"Calle De Matarrosa",
    "iso:country":"ES",
    "sg:address":"Calle de Matarrosa, 5",
    "sg:city":"Fuenlabrada",
    "sg:orig_category":"Transportes Por Carretera: Lotes Completos, Mercanc\u00cdas Diversas",
    "sg:phone":"+34 916 42 20 97",
    "sg:postcode":"28947",
    "sg:province":"Madrid",
    "wof:name":"E.mariscal Distribuciones Alimentarias S.l.",
    "wof:placetype":"venue"
},
  "geometry": {"coordinates":[-3.7506110668,40.2679023743],"type":"Point"}
}