{
  "type": "Feature",
  "properties": {
    "addr:full":"Cno. Vereda, 16 Beniparrell Valencia 46469",
    "addr:housenumber":"16",
    "addr:postcode":"46469",
    "addr:street":"Vereda",
    "iso:country":"ES",
    "sg:address":"Cno. Vereda, 16",
    "sg:city":"Beniparrell",
    "sg:orig_category":"Embalajes",
    "sg:phone":"+34 961 20 25 62",
    "sg:postcode":"46469",
    "sg:province":"Valencia",
    "wof:name":"I.r.beniparrell S.l.",
    "wof:placetype":"venue"
},
  "geometry": {"coordinates":[-0.402312994,39.385055542],"type":"Point"}
}