{
  "type": "Feature",
  "properties": {
    "addr:full":"Calle de Alvarez Haza\u00d1as, 26 Utrera Sevilla 41710",
    "addr:housenumber":"26",
    "addr:postcode":"41710",
    "addr:street":"Calle De Alvarez Hazan\u0303As",
    "iso:country":"ES",
    "sg:address":"Calle de Alvarez Haza\u00d1as, 26",
    "sg:city":"Utrera",
    "sg:orig_category":"Confiter\u00cdas, Chocolater\u00cdas (al Por Menor)",
    "sg:phone":"+34 954 86 02 53",
    "sg:postcode":"41710",
    "sg:province":"Sevilla",
    "wof:name":"Fernandez Rodriguez Rafael",
    "wof:placetype":"venue"
},
  "geometry": {"coordinates":[-5.7785258293,37.1799201965],"type":"Point"}
}