{
  "type": "Feature",
  "properties": {
    "iso:country":"ES",
    "sg:address":"Calle de Real, S/n",
    "sg:city":"Pi\u00e7a De Esgueva",
    "sg:orig_category":"Cr\u00cda De Cerdos",
    "sg:phone":"+34 983 68 54 21",
    "sg:postcode":"47175",
    "sg:province":"Valladolid",
    "wof:name":"Zan Lopez Pedro",
    "wof:placetype":"venue"
},
  "geometry": {"coordinates":[-4.4276747704,41.7279319763],"type":"Point"}
}