{
  "type": "Feature",
  "properties": {
    "iso:country":"ES",
    "sg:address":"Carrer de Mollet, 18",
    "sg:city":"Llagosta",
    "sg:orig_category":"Instalaci\u00d3n, Preparaci\u00d3n De Exposiciones, Ferias, Salones",
    "sg:phone":"+34 935 74 01 67",
    "sg:postcode":"08120",
    "sg:province":"Barcelona",
    "wof:name":"Global Display S.l.",
    "wof:placetype":"venue"
},
  "geometry": {"coordinates":[2.1970200539,41.5155792236],"type":"Point"}
}