{
  "type": "Feature",
  "properties": {
    "addr:full":"Calle de Carmen Juanola, 10 Estacion M\u00e1laga 29580",
    "addr:housenumber":"10 estacion",
    "addr:postcode":"29580",
    "addr:street":"Calle De Carmen Juanola;Ma\u0301Laga",
    "iso:country":"ES",
    "sg:address":"Calle de Carmen Juanola, 10",
    "sg:city":"Estacion",
    "sg:orig_category":"Peluquer\u00cdas, Peluquer\u00cda Mixta",
    "sg:phone":"+34 952 42 03 57",
    "sg:postcode":"29580",
    "sg:province":"M\u00e1laga",
    "wof:name":"Barrientos Moncayo Jose Manuel",
    "wof:placetype":"venue"
},
  "geometry": {"coordinates":[-4.6090288162,36.7356109619],"type":"Point"}
}