{
  "type": "Feature",
  "properties": {
    "addr:full":"Plaz Abilio Calderon, 4 Palencia Palencia 34001",
    "addr:housenumber":"4",
    "addr:postcode":"34001",
    "addr:street":"Plaz;Calderon",
    "iso:country":"ES",
    "sg:address":"Plaz Abilio Calderon, 4",
    "sg:city":"Palencia",
    "sg:orig_category":"Centros Empresariales",
    "sg:phone":"+34 979 70 25 28",
    "sg:postcode":"34001",
    "sg:province":"Palencia",
    "wof:name":"Confederacion Palentina De Organizaciones Empresariales",
    "wof:placetype":"venue"
},
  "geometry": {"coordinates":[-4.5308279991,42.0110816956],"type":"Point"}
}