{
  "type": "Feature",
  "properties": {
    "iso:country":"ES",
    "sg:address":"Calle de Lezcano, 25",
    "sg:city":"Sestrica",
    "sg:orig_category":"Cerrajer\u00cda, Ferrallista",
    "sg:phone":"+34 976 82 61 10",
    "sg:postcode":"50248",
    "sg:province":"Zaragoza",
    "wof:name":"Torrijo Cabello Antonio",
    "wof:placetype":"venue"
},
  "geometry": {"coordinates":[-1.5956677198,41.4868125916],"type":"Point"}
}