{
  "type": "Feature",
  "properties": {
    "iso:country":"ES",
    "sg:address":"Avda Sierra De Gata, 1",
    "sg:city":"Coria",
    "sg:orig_category":"Laboratorios Y Cl\u00cdnicas Veterinarias",
    "sg:phone":"+34 927 50 37 59",
    "sg:postcode":"10800",
    "sg:province":"C\u00e1ceres",
    "wof:name":"Bordallo Lourtau Maria Isabel",
    "wof:placetype":"venue"
},
  "geometry": {"coordinates":[-6.5369968414,39.9853401184],"type":"Point"}
}