{
  "type": "Feature",
  "properties": {
    "iso:country":"ES",
    "sg:address":"Carrer de Edison, 3",
    "sg:city":"Manresa",
    "sg:orig_category":"Rectificaci\u00d3n, Mecanizado, Fresado",
    "sg:phone":"+34 938 73 79 49",
    "sg:postcode":"08243",
    "sg:province":"Barcelona",
    "wof:name":"Talleres Mecanicos Alan S.l.",
    "wof:placetype":"venue"
},
  "geometry": {"coordinates":[1.8460400105,41.7160148621],"type":"Point"}
}