{
  "type": "Feature",
  "properties": {
    "addr:full":"Kaskalleta, 3 Iru\u00f1a Navarra 31015",
    "addr:housenumber":"3",
    "addr:postcode":"31015",
    "addr:street":"Kaskalleta",
    "iso:country":"ES",
    "sg:address":"Kaskalleta, 3",
    "sg:city":"Iru\u00f1a",
    "sg:orig_category":"Peluqueros: De Se\u00d1oras",
    "sg:phone":"+34 948 14 14 28",
    "sg:postcode":"31015",
    "sg:province":"Navarra",
    "wof:name":"Sastre Elrio Milagrosa",
    "wof:placetype":"venue"
},
  "geometry": {"coordinates":[-1.6330080032,42.8316841125],"type":"Point"}
}