{
  "type": "Feature",
  "properties": {
    "addr:full":"Estd Castela, 133 Ferrol La Coru\u00f1a 15404",
    "addr:housenumber":"133",
    "addr:postcode":"15404",
    "addr:street":"Castela;La Corun\u0303A",
    "iso:country":"ES",
    "sg:address":"Estd Castela, 133",
    "sg:city":"Ferrol",
    "sg:orig_category":"Transporte En General",
    "sg:phone":"+34 981 31 67 64",
    "sg:postcode":"15404",
    "sg:province":"La Coru\u00f1a",
    "wof:name":"Hiperxel S.l.",
    "wof:placetype":"venue"
},
  "geometry": {"coordinates":[-8.2201938629,43.4897994995],"type":"Point"}
}