{
  "type": "Feature",
  "properties": {
    "iso:country":"ES",
    "sg:address":"Almendros, S/n",
    "sg:city":"Logro\u00f1o",
    "sg:orig_category":"Embalajes",
    "sg:phone":"+34 941 23 11 34",
    "sg:postcode":"26006",
    "sg:province":"La Rioja",
    "wof:name":"Dise\u00f1o Ingenieria Y Fabricacion De Embalajes S.a.",
    "wof:placetype":"venue"
},
  "geometry": {"coordinates":[-2.4123699665,42.4752616882],"type":"Point"}
}