{
  "type": "Feature",
  "properties": {
    "addr:full":"Calle de Ezequiel Lopez, 24 Cedeira La Coru\u00f1a 15350",
    "addr:housenumber":"24",
    "addr:postcode":"15350",
    "addr:street":"Calle De Ezequiel Lopez;La Corun\u0303A",
    "iso:country":"ES",
    "sg:address":"Calle de Ezequiel Lopez, 24",
    "sg:city":"Cedeira",
    "sg:orig_category":"Navegaci\u00d3n (equipos Fluviales)",
    "sg:phone":"+34 981 48 27 63",
    "sg:postcode":"15350",
    "sg:province":"La Coru\u00f1a",
    "wof:name":"Hermanos Garcia Ya\u00f1ez S.a.",
    "wof:placetype":"venue"
},
  "geometry": {"coordinates":[-8.056183815,43.6606750488],"type":"Point"}
}