{
  "type": "Feature",
  "properties": {
    "addr:full":"Av Madrid, 198 Barcelona Barcelona 08028",
    "addr:housenumber":"198",
    "addr:postcode":"08028",
    "addr:street":"Av Madrid",
    "iso:country":"ES",
    "sg:address":"Av Madrid, 198",
    "sg:city":"Barcelona",
    "sg:orig_category":"Sociedades, Compa\u00d1\u00cdas Aseguradoras",
    "sg:phone":"+34 934 90 14 41",
    "sg:postcode":"08028",
    "sg:province":"Barcelona",
    "wof:name":"Jose Alburquerque Mediadores De Seguros S.l.",
    "wof:placetype":"venue"
},
  "geometry": {"coordinates":[2.1334469318,41.3809776306],"type":"Point"}
}